package com.fasterxml.Zm;

import com.fasterxml.Zb.Z_;
import com.fasterxml.Zb.Ze;
import com.fasterxml.Zb.Zf;
import com.fasterxml.Zb.Zg;
import com.fasterxml.Zb.Zi;
import com.fasterxml.Zb.Zj;
import com.fasterxml.Zb.Zmd;
import com.fasterxml.Zb.Zmk;
import com.fasterxml.Zb.Zy;
import com.fasterxml.Zj.Zv;
import com.fasterxml.Zor.Zyg;
import com.fasterxml.Zq.Zf;
import java.io.IOException;
import java.io.InputStream;
import java.math.BigDecimal;
import java.math.BigInteger;

public class Zl extends Zf {
  protected static final int ZP;
  
  protected Zmd ZZ;
  
  protected Ze Za;
  
  protected int ZE;
  
  protected Z_ Zi;
  
  protected boolean ZM;
  
  protected boolean Zb;
  
  protected boolean Zx;
  
  protected boolean ZO;
  
  protected boolean ZD;
  
  protected Ze5 Zh;
  
  protected Ze5 Zs;
  
  protected int Zc;
  
  protected Object Zf;
  
  protected Object Zm;
  
  protected boolean Zo;
  
  protected Zf Zr;
  
  private static final String[] c;
  
  private static final String[] d;
  
  public Zl(Zmd paramZmd, boolean paramBoolean) {
    // Byte code:
    //   0: aload_0
    //   1: invokespecial <init> : ()V
    //   4: aload_0
    //   5: invokestatic Zo : ()Lcom/fasterxml/Zb/Z_;
    //   8: putfield Zi : Lcom/fasterxml/Zb/Z_;
    //   11: aload_0
    //   12: iconst_0
    //   13: putfield Zo : Z
    //   16: aload_0
    //   17: aload_1
    //   18: putfield ZZ : Lcom/fasterxml/Zb/Zmd;
    //   21: aload_0
    //   22: getstatic com/fasterxml/Zm/Zl.ZP : I
    //   25: putfield ZE : I
    //   28: aload_0
    //   29: aconst_null
    //   30: invokestatic Zu : (Lcom/fasterxml/Zq/Zs;)Lcom/fasterxml/Zq/Zf;
    //   33: putfield Zr : Lcom/fasterxml/Zq/Zf;
    //   36: aload_0
    //   37: aload_0
    //   38: new com/fasterxml/Zm/Ze5
    //   41: dup
    //   42: invokespecial <init> : ()V
    //   45: dup_x1
    //   46: putfield Zs : Lcom/fasterxml/Zm/Ze5;
    //   49: putfield Zh : Lcom/fasterxml/Zm/Ze5;
    //   52: aload_0
    //   53: iconst_0
    //   54: putfield Zc : I
    //   57: aload_0
    //   58: iload_2
    //   59: putfield Zb : Z
    //   62: aload_0
    //   63: iload_2
    //   64: putfield Zx : Z
    //   67: aload_0
    //   68: aload_0
    //   69: getfield Zb : Z
    //   72: ifne -> 82
    //   75: aload_0
    //   76: getfield Zx : Z
    //   79: ifeq -> 90
    //   82: iconst_1
    //   83: goto -> 91
    //   86: invokestatic a : (Ljava/lang/Exception;)Ljava/lang/Exception;
    //   89: athrow
    //   90: iconst_0
    //   91: putfield ZO : Z
    //   94: return
    // Exception table:
    //   from	to	target	type
    //   75	86	86	java/lang/RuntimeException
  }
  
  public Zl(Zg paramZg, Zyg paramZyg) {
    // Byte code:
    //   0: aload_0
    //   1: invokespecial <init> : ()V
    //   4: aload_0
    //   5: invokestatic Zo : ()Lcom/fasterxml/Zb/Z_;
    //   8: putfield Zi : Lcom/fasterxml/Zb/Z_;
    //   11: invokestatic ZY : ()I
    //   14: aload_0
    //   15: iconst_0
    //   16: putfield Zo : Z
    //   19: istore_3
    //   20: aload_0
    //   21: aload_1
    //   22: invokevirtual Zv : ()Lcom/fasterxml/Zb/Zmd;
    //   25: putfield ZZ : Lcom/fasterxml/Zb/Zmd;
    //   28: aload_0
    //   29: aload_1
    //   30: invokevirtual ZG : ()Lcom/fasterxml/Zb/Z_;
    //   33: putfield Zi : Lcom/fasterxml/Zb/Z_;
    //   36: aload_0
    //   37: aload_1
    //   38: invokevirtual ZT1 : ()Lcom/fasterxml/Zb/Ze;
    //   41: putfield Za : Lcom/fasterxml/Zb/Ze;
    //   44: aload_0
    //   45: getstatic com/fasterxml/Zm/Zl.ZP : I
    //   48: putfield ZE : I
    //   51: aload_0
    //   52: aconst_null
    //   53: invokestatic Zu : (Lcom/fasterxml/Zq/Zs;)Lcom/fasterxml/Zq/Zf;
    //   56: putfield Zr : Lcom/fasterxml/Zq/Zf;
    //   59: aload_0
    //   60: aload_0
    //   61: new com/fasterxml/Zm/Ze5
    //   64: dup
    //   65: invokespecial <init> : ()V
    //   68: dup_x1
    //   69: putfield Zs : Lcom/fasterxml/Zm/Ze5;
    //   72: putfield Zh : Lcom/fasterxml/Zm/Ze5;
    //   75: aload_0
    //   76: iconst_0
    //   77: putfield Zc : I
    //   80: aload_0
    //   81: aload_1
    //   82: invokevirtual ZP : ()Z
    //   85: putfield Zb : Z
    //   88: aload_0
    //   89: aload_1
    //   90: invokevirtual ZM : ()Z
    //   93: putfield Zx : Z
    //   96: aload_0
    //   97: aload_0
    //   98: getfield Zb : Z
    //   101: ifne -> 118
    //   104: aload_0
    //   105: getfield Zx : Z
    //   108: ifeq -> 126
    //   111: goto -> 118
    //   114: invokestatic a : (Ljava/lang/Exception;)Ljava/lang/Exception;
    //   117: athrow
    //   118: iconst_1
    //   119: goto -> 127
    //   122: invokestatic a : (Ljava/lang/Exception;)Ljava/lang/Exception;
    //   125: athrow
    //   126: iconst_0
    //   127: putfield ZO : Z
    //   130: aload_0
    //   131: aload_2
    //   132: ifnonnull -> 143
    //   135: iconst_0
    //   136: goto -> 150
    //   139: invokestatic a : (Ljava/lang/Exception;)Ljava/lang/Exception;
    //   142: athrow
    //   143: aload_2
    //   144: getstatic com/fasterxml/Zor/Zyp.USE_BIG_DECIMAL_FOR_FLOATS : Lcom/fasterxml/Zor/Zyp;
    //   147: invokevirtual Zg : (Lcom/fasterxml/Zor/Zyp;)Z
    //   150: putfield ZD : Z
    //   153: invokestatic Zwu : ()[Lburp/Zbqc;
    //   156: ifnonnull -> 173
    //   159: iinc #3, 1
    //   162: iload_3
    //   163: invokestatic ZD : (I)V
    //   166: goto -> 173
    //   169: invokestatic a : (Ljava/lang/Exception;)Ljava/lang/Exception;
    //   172: athrow
    //   173: return
    // Exception table:
    //   from	to	target	type
    //   20	111	114	java/lang/RuntimeException
    //   104	122	122	java/lang/RuntimeException
    //   127	139	139	java/lang/RuntimeException
    //   150	166	169	java/lang/RuntimeException
  }
  
  public Zl ZI(boolean paramBoolean) {
    this.ZD = paramBoolean;
    return this;
  }
  
  public Zmk version() {
    return Zv.ZV;
  }
  
  public Zg Zp() {
    return Z_(this.ZZ);
  }
  
  public Zg ZD() throws IOException {
    Zg zg = Z_(this.ZZ);
    zg.ZV();
    return zg;
  }
  
  public Zg Z_(Zmd paramZmd) {
    return (Zg)new Zt(this.Zh, paramZmd, this.Zb, this.Zx, this.Za, this.Zi);
  }
  
  public Zg Zi(Z_ paramZ_) {
    return (Zg)new Zt(this.Zh, this.ZZ, this.Zb, this.Zx, this.Za, paramZ_);
  }
  
  public Zg Zv(Zg paramZg) {
    Zt zt = new Zt(this.Zh, paramZg.Zv(), this.Zb, this.Zx, this.Za, paramZg.ZG());
    zt.Zf(paramZg.ZQ());
    return (Zg)zt;
  }
  
  public com.fasterxml.Zb.Zl ZK() {
    return this.Zh.ZQ(0);
  }
  
  public Zl Zz(Zl paramZl) throws IOException {
    // Byte code:
    //   0: invokestatic Zo : ()I
    //   3: istore_2
    //   4: aload_0
    //   5: getfield Zb : Z
    //   8: ifne -> 26
    //   11: aload_0
    //   12: aload_1
    //   13: invokevirtual ZH : ()Z
    //   16: putfield Zb : Z
    //   19: goto -> 26
    //   22: invokestatic a : (Ljava/lang/Exception;)Ljava/lang/Exception;
    //   25: athrow
    //   26: aload_0
    //   27: getfield Zx : Z
    //   30: ifne -> 48
    //   33: aload_0
    //   34: aload_1
    //   35: invokevirtual ZB : ()Z
    //   38: putfield Zx : Z
    //   41: goto -> 48
    //   44: invokestatic a : (Ljava/lang/Exception;)Ljava/lang/Exception;
    //   47: athrow
    //   48: aload_0
    //   49: aload_0
    //   50: getfield Zb : Z
    //   53: ifne -> 70
    //   56: aload_0
    //   57: getfield Zx : Z
    //   60: ifeq -> 78
    //   63: goto -> 70
    //   66: invokestatic a : (Ljava/lang/Exception;)Ljava/lang/Exception;
    //   69: athrow
    //   70: iconst_1
    //   71: goto -> 79
    //   74: invokestatic a : (Ljava/lang/Exception;)Ljava/lang/Exception;
    //   77: athrow
    //   78: iconst_0
    //   79: putfield ZO : Z
    //   82: aload_1
    //   83: invokevirtual Zp : ()Lcom/fasterxml/Zb/Zg;
    //   86: astore_3
    //   87: aload_3
    //   88: invokevirtual ZV : ()Lcom/fasterxml/Zb/Zl;
    //   91: ifnull -> 103
    //   94: aload_0
    //   95: aload_3
    //   96: invokevirtual ZE : (Lcom/fasterxml/Zb/Zg;)V
    //   99: iload_2
    //   100: ifne -> 87
    //   103: aload_0
    //   104: areturn
    // Exception table:
    //   from	to	target	type
    //   4	19	22	java/io/IOException
    //   26	41	44	java/io/IOException
    //   48	63	66	java/io/IOException
    //   56	74	74	java/io/IOException
  }
  
  public void Zm(Zf paramZf) throws IOException {
    // Byte code:
    //   0: invokestatic ZY : ()I
    //   3: aload_0
    //   4: getfield Zh : Lcom/fasterxml/Zm/Ze5;
    //   7: astore_3
    //   8: iconst_m1
    //   9: istore #4
    //   11: aload_0
    //   12: getfield ZO : Z
    //   15: istore #5
    //   17: istore_2
    //   18: iload #5
    //   20: ifeq -> 45
    //   23: aload_3
    //   24: invokevirtual ZV : ()Z
    //   27: ifeq -> 45
    //   30: goto -> 37
    //   33: invokestatic a : (Ljava/lang/Exception;)Ljava/lang/Exception;
    //   36: athrow
    //   37: iconst_1
    //   38: goto -> 46
    //   41: invokestatic a : (Ljava/lang/Exception;)Ljava/lang/Exception;
    //   44: athrow
    //   45: iconst_0
    //   46: istore #6
    //   48: iinc #4, 1
    //   51: iload #4
    //   53: bipush #16
    //   55: if_icmplt -> 107
    //   58: iconst_0
    //   59: istore #4
    //   61: aload_3
    //   62: invokevirtual Zw : ()Lcom/fasterxml/Zm/Ze5;
    //   65: astore_3
    //   66: aload_3
    //   67: ifnonnull -> 77
    //   70: goto -> 974
    //   73: invokestatic a : (Ljava/lang/Exception;)Ljava/lang/Exception;
    //   76: athrow
    //   77: iload #5
    //   79: ifeq -> 104
    //   82: aload_3
    //   83: invokevirtual ZV : ()Z
    //   86: ifeq -> 104
    //   89: goto -> 96
    //   92: invokestatic a : (Ljava/lang/Exception;)Ljava/lang/Exception;
    //   95: athrow
    //   96: iconst_1
    //   97: goto -> 105
    //   100: invokestatic a : (Ljava/lang/Exception;)Ljava/lang/Exception;
    //   103: athrow
    //   104: iconst_0
    //   105: istore #6
    //   107: aload_3
    //   108: iload #4
    //   110: invokevirtual ZQ : (I)Lcom/fasterxml/Zb/Zl;
    //   113: astore #7
    //   115: aload #7
    //   117: ifnonnull -> 127
    //   120: goto -> 974
    //   123: invokestatic a : (Ljava/lang/Exception;)Ljava/lang/Exception;
    //   126: athrow
    //   127: iload #6
    //   129: ifeq -> 184
    //   132: aload_3
    //   133: iload #4
    //   135: invokevirtual Zs : (I)Ljava/lang/Object;
    //   138: astore #8
    //   140: aload #8
    //   142: ifnull -> 158
    //   145: aload_1
    //   146: aload #8
    //   148: invokevirtual ZV : (Ljava/lang/Object;)V
    //   151: goto -> 158
    //   154: invokestatic a : (Ljava/lang/Exception;)Ljava/lang/Exception;
    //   157: athrow
    //   158: aload_3
    //   159: iload #4
    //   161: invokevirtual Zj : (I)Ljava/lang/Object;
    //   164: astore #8
    //   166: aload #8
    //   168: ifnull -> 184
    //   171: aload_1
    //   172: aload #8
    //   174: invokevirtual Zu : (Ljava/lang/Object;)V
    //   177: goto -> 184
    //   180: invokestatic a : (Ljava/lang/Exception;)Ljava/lang/Exception;
    //   183: athrow
    //   184: getstatic com/fasterxml/Zm/Zg.Z_ : [I
    //   187: aload #7
    //   189: invokevirtual ordinal : ()I
    //   192: iaload
    //   193: tableswitch default -> 949, 1 -> 256, 2 -> 271, 3 -> 286, 4 -> 301, 5 -> 316, 6 -> 372, 7 -> 428, 8 -> 601, 9 -> 817, 10 -> 833, 11 -> 849, 12 -> 864
    //   256: aload_1
    //   257: invokevirtual ZJ : ()V
    //   260: iload_2
    //   261: ifeq -> 970
    //   264: goto -> 271
    //   267: invokestatic a : (Ljava/lang/Exception;)Ljava/lang/Exception;
    //   270: athrow
    //   271: aload_1
    //   272: invokevirtual Zh : ()V
    //   275: iload_2
    //   276: ifeq -> 970
    //   279: goto -> 286
    //   282: invokestatic a : (Ljava/lang/Exception;)Ljava/lang/Exception;
    //   285: athrow
    //   286: aload_1
    //   287: invokevirtual Zd : ()V
    //   290: iload_2
    //   291: ifeq -> 970
    //   294: goto -> 301
    //   297: invokestatic a : (Ljava/lang/Exception;)Ljava/lang/Exception;
    //   300: athrow
    //   301: aload_1
    //   302: invokevirtual ZI : ()V
    //   305: iload_2
    //   306: ifeq -> 970
    //   309: goto -> 316
    //   312: invokestatic a : (Ljava/lang/Exception;)Ljava/lang/Exception;
    //   315: athrow
    //   316: aload_3
    //   317: iload #4
    //   319: invokevirtual Z_ : (I)Ljava/lang/Object;
    //   322: astore #8
    //   324: aload #8
    //   326: instanceof com/fasterxml/Zb/Zj
    //   329: ifeq -> 352
    //   332: aload_1
    //   333: aload #8
    //   335: checkcast com/fasterxml/Zb/Zj
    //   338: invokevirtual Zm : (Lcom/fasterxml/Zb/Zj;)V
    //   341: iload_2
    //   342: ifeq -> 368
    //   345: goto -> 352
    //   348: invokestatic a : (Ljava/lang/Exception;)Ljava/lang/Exception;
    //   351: athrow
    //   352: aload_1
    //   353: aload #8
    //   355: checkcast java/lang/String
    //   358: invokevirtual ZY : (Ljava/lang/String;)V
    //   361: goto -> 368
    //   364: invokestatic a : (Ljava/lang/Exception;)Ljava/lang/Exception;
    //   367: athrow
    //   368: iload_2
    //   369: ifeq -> 970
    //   372: aload_3
    //   373: iload #4
    //   375: invokevirtual Z_ : (I)Ljava/lang/Object;
    //   378: astore #8
    //   380: aload #8
    //   382: instanceof com/fasterxml/Zb/Zj
    //   385: ifeq -> 408
    //   388: aload_1
    //   389: aload #8
    //   391: checkcast com/fasterxml/Zb/Zj
    //   394: invokevirtual Zr : (Lcom/fasterxml/Zb/Zj;)V
    //   397: iload_2
    //   398: ifeq -> 424
    //   401: goto -> 408
    //   404: invokestatic a : (Ljava/lang/Exception;)Ljava/lang/Exception;
    //   407: athrow
    //   408: aload_1
    //   409: aload #8
    //   411: checkcast java/lang/String
    //   414: invokevirtual ZD : (Ljava/lang/String;)V
    //   417: goto -> 424
    //   420: invokestatic a : (Ljava/lang/Exception;)Ljava/lang/Exception;
    //   423: athrow
    //   424: iload_2
    //   425: ifeq -> 970
    //   428: aload_3
    //   429: iload #4
    //   431: invokevirtual Z_ : (I)Ljava/lang/Object;
    //   434: astore #8
    //   436: aload #8
    //   438: instanceof java/lang/Integer
    //   441: ifeq -> 467
    //   444: aload_1
    //   445: aload #8
    //   447: checkcast java/lang/Integer
    //   450: invokevirtual intValue : ()I
    //   453: invokevirtual Zd : (I)V
    //   456: iload_2
    //   457: ifeq -> 597
    //   460: goto -> 467
    //   463: invokestatic a : (Ljava/lang/Exception;)Ljava/lang/Exception;
    //   466: athrow
    //   467: aload #8
    //   469: instanceof java/math/BigInteger
    //   472: ifeq -> 502
    //   475: goto -> 482
    //   478: invokestatic a : (Ljava/lang/Exception;)Ljava/lang/Exception;
    //   481: athrow
    //   482: aload_1
    //   483: aload #8
    //   485: checkcast java/math/BigInteger
    //   488: invokevirtual Zy : (Ljava/math/BigInteger;)V
    //   491: iload_2
    //   492: ifeq -> 597
    //   495: goto -> 502
    //   498: invokestatic a : (Ljava/lang/Exception;)Ljava/lang/Exception;
    //   501: athrow
    //   502: aload #8
    //   504: instanceof java/lang/Long
    //   507: ifeq -> 540
    //   510: goto -> 517
    //   513: invokestatic a : (Ljava/lang/Exception;)Ljava/lang/Exception;
    //   516: athrow
    //   517: aload_1
    //   518: aload #8
    //   520: checkcast java/lang/Long
    //   523: invokevirtual longValue : ()J
    //   526: invokevirtual Zw : (J)V
    //   529: iload_2
    //   530: ifeq -> 597
    //   533: goto -> 540
    //   536: invokestatic a : (Ljava/lang/Exception;)Ljava/lang/Exception;
    //   539: athrow
    //   540: aload #8
    //   542: instanceof java/lang/Short
    //   545: ifeq -> 578
    //   548: goto -> 555
    //   551: invokestatic a : (Ljava/lang/Exception;)Ljava/lang/Exception;
    //   554: athrow
    //   555: aload_1
    //   556: aload #8
    //   558: checkcast java/lang/Short
    //   561: invokevirtual shortValue : ()S
    //   564: invokevirtual ZF : (S)V
    //   567: iload_2
    //   568: ifeq -> 597
    //   571: goto -> 578
    //   574: invokestatic a : (Ljava/lang/Exception;)Ljava/lang/Exception;
    //   577: athrow
    //   578: aload_1
    //   579: aload #8
    //   581: checkcast java/lang/Number
    //   584: invokevirtual intValue : ()I
    //   587: invokevirtual Zd : (I)V
    //   590: goto -> 597
    //   593: invokestatic a : (Ljava/lang/Exception;)Ljava/lang/Exception;
    //   596: athrow
    //   597: iload_2
    //   598: ifeq -> 970
    //   601: aload_3
    //   602: iload #4
    //   604: invokevirtual Z_ : (I)Ljava/lang/Object;
    //   607: astore #8
    //   609: aload #8
    //   611: instanceof java/lang/Double
    //   614: ifeq -> 640
    //   617: aload_1
    //   618: aload #8
    //   620: checkcast java/lang/Double
    //   623: invokevirtual doubleValue : ()D
    //   626: invokevirtual ZF : (D)V
    //   629: iload_2
    //   630: ifeq -> 813
    //   633: goto -> 640
    //   636: invokestatic a : (Ljava/lang/Exception;)Ljava/lang/Exception;
    //   639: athrow
    //   640: aload #8
    //   642: instanceof java/math/BigDecimal
    //   645: ifeq -> 675
    //   648: goto -> 655
    //   651: invokestatic a : (Ljava/lang/Exception;)Ljava/lang/Exception;
    //   654: athrow
    //   655: aload_1
    //   656: aload #8
    //   658: checkcast java/math/BigDecimal
    //   661: invokevirtual ZI : (Ljava/math/BigDecimal;)V
    //   664: iload_2
    //   665: ifeq -> 813
    //   668: goto -> 675
    //   671: invokestatic a : (Ljava/lang/Exception;)Ljava/lang/Exception;
    //   674: athrow
    //   675: aload #8
    //   677: instanceof java/lang/Float
    //   680: ifeq -> 713
    //   683: goto -> 690
    //   686: invokestatic a : (Ljava/lang/Exception;)Ljava/lang/Exception;
    //   689: athrow
    //   690: aload_1
    //   691: aload #8
    //   693: checkcast java/lang/Float
    //   696: invokevirtual floatValue : ()F
    //   699: invokevirtual Za : (F)V
    //   702: iload_2
    //   703: ifeq -> 813
    //   706: goto -> 713
    //   709: invokestatic a : (Ljava/lang/Exception;)Ljava/lang/Exception;
    //   712: athrow
    //   713: aload #8
    //   715: ifnonnull -> 740
    //   718: goto -> 725
    //   721: invokestatic a : (Ljava/lang/Exception;)Ljava/lang/Exception;
    //   724: athrow
    //   725: aload_1
    //   726: invokevirtual ZT : ()V
    //   729: iload_2
    //   730: ifeq -> 813
    //   733: goto -> 740
    //   736: invokestatic a : (Ljava/lang/Exception;)Ljava/lang/Exception;
    //   739: athrow
    //   740: aload #8
    //   742: instanceof java/lang/String
    //   745: ifeq -> 775
    //   748: goto -> 755
    //   751: invokestatic a : (Ljava/lang/Exception;)Ljava/lang/Exception;
    //   754: athrow
    //   755: aload_1
    //   756: aload #8
    //   758: checkcast java/lang/String
    //   761: invokevirtual Zu : (Ljava/lang/String;)V
    //   764: iload_2
    //   765: ifeq -> 813
    //   768: goto -> 775
    //   771: invokestatic a : (Ljava/lang/Exception;)Ljava/lang/Exception;
    //   774: athrow
    //   775: aload_0
    //   776: sipush #-25855
    //   779: sipush #9277
    //   782: invokestatic b : (II)Ljava/lang/String;
    //   785: iconst_1
    //   786: anewarray java/lang/Object
    //   789: dup
    //   790: iconst_0
    //   791: aload #8
    //   793: invokevirtual getClass : ()Ljava/lang/Class;
    //   796: invokevirtual getName : ()Ljava/lang/String;
    //   799: aastore
    //   800: invokestatic format : (Ljava/lang/String;[Ljava/lang/Object;)Ljava/lang/String;
    //   803: invokevirtual Zr : (Ljava/lang/String;)V
    //   806: goto -> 813
    //   809: invokestatic a : (Ljava/lang/Exception;)Ljava/lang/Exception;
    //   812: athrow
    //   813: iload_2
    //   814: ifeq -> 970
    //   817: aload_1
    //   818: iconst_1
    //   819: invokevirtual Zs : (Z)V
    //   822: iload_2
    //   823: ifeq -> 970
    //   826: goto -> 833
    //   829: invokestatic a : (Ljava/lang/Exception;)Ljava/lang/Exception;
    //   832: athrow
    //   833: aload_1
    //   834: iconst_0
    //   835: invokevirtual Zs : (Z)V
    //   838: iload_2
    //   839: ifeq -> 970
    //   842: goto -> 849
    //   845: invokestatic a : (Ljava/lang/Exception;)Ljava/lang/Exception;
    //   848: athrow
    //   849: aload_1
    //   850: invokevirtual ZT : ()V
    //   853: iload_2
    //   854: ifeq -> 970
    //   857: goto -> 864
    //   860: invokestatic a : (Ljava/lang/Exception;)Ljava/lang/Exception;
    //   863: athrow
    //   864: aload_3
    //   865: iload #4
    //   867: invokevirtual Z_ : (I)Ljava/lang/Object;
    //   870: astore #8
    //   872: aload #8
    //   874: instanceof com/fasterxml/Zm/Zj
    //   877: ifeq -> 900
    //   880: aload #8
    //   882: checkcast com/fasterxml/Zm/Zj
    //   885: aload_1
    //   886: invokevirtual ZE : (Lcom/fasterxml/Zb/Zf;)V
    //   889: iload_2
    //   890: ifeq -> 945
    //   893: goto -> 900
    //   896: invokestatic a : (Ljava/lang/Exception;)Ljava/lang/Exception;
    //   899: athrow
    //   900: aload #8
    //   902: instanceof com/fasterxml/Zor/Zh
    //   905: ifeq -> 932
    //   908: goto -> 915
    //   911: invokestatic a : (Ljava/lang/Exception;)Ljava/lang/Exception;
    //   914: athrow
    //   915: aload_1
    //   916: aload #8
    //   918: invokevirtual ZZ : (Ljava/lang/Object;)V
    //   921: iload_2
    //   922: ifeq -> 945
    //   925: goto -> 932
    //   928: invokestatic a : (Ljava/lang/Exception;)Ljava/lang/Exception;
    //   931: athrow
    //   932: aload_1
    //   933: aload #8
    //   935: invokevirtual ZJ : (Ljava/lang/Object;)V
    //   938: goto -> 945
    //   941: invokestatic a : (Ljava/lang/Exception;)Ljava/lang/Exception;
    //   944: athrow
    //   945: iload_2
    //   946: ifeq -> 970
    //   949: new java/lang/RuntimeException
    //   952: dup
    //   953: sipush #-25847
    //   956: sipush #-21320
    //   959: invokestatic b : (II)Ljava/lang/String;
    //   962: invokespecial <init> : (Ljava/lang/String;)V
    //   965: athrow
    //   966: invokestatic a : (Ljava/lang/Exception;)Ljava/lang/Exception;
    //   969: athrow
    //   970: iload_2
    //   971: ifeq -> 48
    //   974: return
    // Exception table:
    //   from	to	target	type
    //   18	30	33	java/io/IOException
    //   23	41	41	java/io/IOException
    //   66	73	73	java/io/IOException
    //   77	89	92	java/io/IOException
    //   82	100	100	java/io/IOException
    //   115	123	123	java/io/IOException
    //   140	151	154	java/io/IOException
    //   166	177	180	java/io/IOException
    //   184	264	267	java/io/IOException
    //   256	279	282	java/io/IOException
    //   271	294	297	java/io/IOException
    //   286	309	312	java/io/IOException
    //   324	345	348	java/io/IOException
    //   332	361	364	java/io/IOException
    //   380	401	404	java/io/IOException
    //   388	417	420	java/io/IOException
    //   436	460	463	java/io/IOException
    //   444	475	478	java/io/IOException
    //   467	495	498	java/io/IOException
    //   482	510	513	java/io/IOException
    //   502	533	536	java/io/IOException
    //   517	548	551	java/io/IOException
    //   540	571	574	java/io/IOException
    //   555	590	593	java/io/IOException
    //   609	633	636	java/io/IOException
    //   617	648	651	java/io/IOException
    //   640	668	671	java/io/IOException
    //   655	683	686	java/io/IOException
    //   675	706	709	java/io/IOException
    //   690	718	721	java/io/IOException
    //   713	733	736	java/io/IOException
    //   725	748	751	java/io/IOException
    //   740	768	771	java/io/IOException
    //   755	806	809	java/io/IOException
    //   813	826	829	java/io/IOException
    //   817	842	845	java/io/IOException
    //   833	857	860	java/io/IOException
    //   872	893	896	java/io/IOException
    //   880	908	911	java/io/IOException
    //   900	925	928	java/io/IOException
    //   915	938	941	java/io/IOException
    //   945	966	966	java/io/IOException
  }
  
  public Zl Zw(Zg paramZg, Zyg paramZyg) throws IOException {
    try {
      if (!paramZg.ZL(com.fasterxml.Zb.Zl.FIELD_NAME)) {
        ZE(paramZg);
        return this;
      } 
    } catch (IOException iOException) {
      throw a(null);
    } 
    ZJ();
    while (true) {
      ZE(paramZg);
      com.fasterxml.Zb.Zl zl;
      if ((zl = paramZg.ZV()) != com.fasterxml.Zb.Zl.FIELD_NAME) {
        try {
          if (zl != com.fasterxml.Zb.Zl.END_OBJECT)
            paramZyg.ZY(Zl.class, com.fasterxml.Zb.Zl.END_OBJECT, b(-25856, 8521) + zl, new Object[0]); 
        } catch (IOException iOException) {
          throw a(null);
        } 
        break;
      } 
    } 
    Zh();
    return this;
  }
  
  public String toString() {
    // Byte code:
    //   0: invokestatic ZY : ()I
    //   3: bipush #100
    //   5: istore_2
    //   6: istore_1
    //   7: new java/lang/StringBuilder
    //   10: dup
    //   11: invokespecial <init> : ()V
    //   14: astore_3
    //   15: aload_3
    //   16: sipush #-25845
    //   19: sipush #-14888
    //   22: invokestatic b : (II)Ljava/lang/String;
    //   25: invokevirtual append : (Ljava/lang/String;)Ljava/lang/StringBuilder;
    //   28: pop
    //   29: aload_0
    //   30: invokevirtual Zp : ()Lcom/fasterxml/Zb/Zg;
    //   33: astore #4
    //   35: iconst_0
    //   36: istore #5
    //   38: aload_0
    //   39: getfield Zb : Z
    //   42: ifne -> 59
    //   45: aload_0
    //   46: getfield Zx : Z
    //   49: ifeq -> 67
    //   52: goto -> 59
    //   55: invokestatic a : (Ljava/lang/Exception;)Ljava/lang/Exception;
    //   58: athrow
    //   59: iconst_1
    //   60: goto -> 68
    //   63: invokestatic a : (Ljava/lang/Exception;)Ljava/lang/Exception;
    //   66: athrow
    //   67: iconst_0
    //   68: istore #6
    //   70: aload #4
    //   72: invokevirtual ZV : ()Lcom/fasterxml/Zb/Zl;
    //   75: astore #7
    //   77: aload #7
    //   79: ifnonnull -> 86
    //   82: iload_1
    //   83: ifeq -> 214
    //   86: iload #6
    //   88: ifeq -> 103
    //   91: aload_0
    //   92: aload_3
    //   93: invokespecial ZW : (Ljava/lang/StringBuilder;)V
    //   96: goto -> 103
    //   99: invokestatic a : (Ljava/lang/Exception;)Ljava/lang/Exception;
    //   102: athrow
    //   103: iload #5
    //   105: bipush #100
    //   107: if_icmpge -> 192
    //   110: iload #5
    //   112: ifle -> 143
    //   115: goto -> 122
    //   118: invokestatic a : (Ljava/lang/Exception;)Ljava/lang/Exception;
    //   121: athrow
    //   122: aload_3
    //   123: sipush #-25853
    //   126: sipush #5352
    //   129: invokestatic b : (II)Ljava/lang/String;
    //   132: invokevirtual append : (Ljava/lang/String;)Ljava/lang/StringBuilder;
    //   135: pop
    //   136: goto -> 143
    //   139: invokestatic a : (Ljava/lang/Exception;)Ljava/lang/Exception;
    //   142: athrow
    //   143: aload_3
    //   144: aload #7
    //   146: invokevirtual toString : ()Ljava/lang/String;
    //   149: invokevirtual append : (Ljava/lang/String;)Ljava/lang/StringBuilder;
    //   152: pop
    //   153: aload #7
    //   155: getstatic com/fasterxml/Zb/Zl.FIELD_NAME : Lcom/fasterxml/Zb/Zl;
    //   158: if_acmpne -> 192
    //   161: aload_3
    //   162: bipush #40
    //   164: invokevirtual append : (C)Ljava/lang/StringBuilder;
    //   167: pop
    //   168: aload_3
    //   169: aload #4
    //   171: invokevirtual ZS : ()Ljava/lang/String;
    //   174: invokevirtual append : (Ljava/lang/String;)Ljava/lang/StringBuilder;
    //   177: pop
    //   178: aload_3
    //   179: bipush #41
    //   181: invokevirtual append : (C)Ljava/lang/StringBuilder;
    //   184: pop
    //   185: goto -> 192
    //   188: invokestatic a : (Ljava/lang/Exception;)Ljava/lang/Exception;
    //   191: athrow
    //   192: goto -> 207
    //   195: astore #8
    //   197: new java/lang/IllegalStateException
    //   200: dup
    //   201: aload #8
    //   203: invokespecial <init> : (Ljava/lang/Throwable;)V
    //   206: athrow
    //   207: iinc #5, 1
    //   210: iload_1
    //   211: ifeq -> 70
    //   214: iload #5
    //   216: bipush #100
    //   218: if_icmplt -> 262
    //   221: aload_3
    //   222: sipush #-25849
    //   225: sipush #7773
    //   228: invokestatic b : (II)Ljava/lang/String;
    //   231: invokevirtual append : (Ljava/lang/String;)Ljava/lang/StringBuilder;
    //   234: iload #5
    //   236: bipush #100
    //   238: isub
    //   239: invokevirtual append : (I)Ljava/lang/StringBuilder;
    //   242: sipush #-25841
    //   245: sipush #-10327
    //   248: invokestatic b : (II)Ljava/lang/String;
    //   251: invokevirtual append : (Ljava/lang/String;)Ljava/lang/StringBuilder;
    //   254: pop
    //   255: goto -> 262
    //   258: invokestatic a : (Ljava/lang/Exception;)Ljava/lang/Exception;
    //   261: athrow
    //   262: aload_3
    //   263: bipush #93
    //   265: invokevirtual append : (C)Ljava/lang/StringBuilder;
    //   268: pop
    //   269: aload_3
    //   270: invokevirtual toString : ()Ljava/lang/String;
    //   273: areturn
    // Exception table:
    //   from	to	target	type
    //   38	52	55	java/io/IOException
    //   45	63	63	java/io/IOException
    //   70	82	195	java/io/IOException
    //   86	96	99	java/io/IOException
    //   86	192	195	java/io/IOException
    //   103	115	118	java/io/IOException
    //   110	136	139	java/io/IOException
    //   143	185	188	java/io/IOException
    //   214	255	258	java/io/IOException
  }
  
  private final void ZW(StringBuilder paramStringBuilder) {
    Object object1 = this.Zs.Zs(this.Zc - 1);
    try {
      if (object1 != null)
        paramStringBuilder.append(b(-25844, 8873)).append(String.valueOf(object1)).append(']'); 
    } catch (RuntimeException runtimeException) {
      throw a(null);
    } 
    Object object2 = this.Zs.Zj(this.Zc - 1);
    try {
      if (object2 != null)
        paramStringBuilder.append(b(-25846, -1946)).append(String.valueOf(object2)).append(']'); 
    } catch (RuntimeException runtimeException) {
      throw a(null);
    } 
  }
  
  public Zf Zf(Zi paramZi) {
    this.ZE &= paramZi.Zf() ^ 0xFFFFFFFF;
    return this;
  }
  
  public boolean Za(Zi paramZi) {
    try {
    
    } catch (RuntimeException runtimeException) {
      throw a(null);
    } 
    return ((this.ZE & paramZi.Zf()) != 0);
  }
  
  public int Za() {
    return this.ZE;
  }
  
  @Deprecated
  public Zf ZG(int paramInt) {
    this.ZE = paramInt;
    return this;
  }
  
  public Zf ZK(int paramInt1, int paramInt2) {
    int i = Za();
    this.ZE = i & (paramInt2 ^ 0xFFFFFFFF) | paramInt1 & paramInt2;
    return this;
  }
  
  public final Zf ZZ() {
    return this.Zr;
  }
  
  public boolean Ze() {
    return true;
  }
  
  public void flush() throws IOException {}
  
  public void close() throws IOException {
    this.ZM = true;
  }
  
  public boolean ZU() {
    return this.ZM;
  }
  
  public final void Zd() throws IOException {
    this.Zr.Zz();
    ZZ(com.fasterxml.Zb.Zl.START_ARRAY);
    this.Zr = this.Zr.Ze();
  }
  
  public void Zo(Object paramObject) throws IOException {
    this.Zr.Zz();
    ZZ(com.fasterxml.Zb.Zl.START_ARRAY);
    this.Zr = this.Zr.Zx(paramObject);
  }
  
  public void Zf(Object paramObject, int paramInt) throws IOException {
    this.Zr.Zz();
    ZZ(com.fasterxml.Zb.Zl.START_ARRAY);
    this.Zr = this.Zr.Zx(paramObject);
  }
  
  public final void ZI() throws IOException {
    Zu(com.fasterxml.Zb.Zl.END_ARRAY);
    Zf zf = this.Zr.ZJ();
    try {
      if (zf != null)
        this.Zr = zf; 
    } catch (IOException iOException) {
      throw a(null);
    } 
  }
  
  public final void ZJ() throws IOException {
    this.Zr.Zz();
    ZZ(com.fasterxml.Zb.Zl.START_OBJECT);
    this.Zr = this.Zr.ZD();
  }
  
  public void ZB(Object paramObject) throws IOException {
    this.Zr.Zz();
    ZZ(com.fasterxml.Zb.Zl.START_OBJECT);
    this.Zr = this.Zr.Zu(paramObject);
  }
  
  public void Ze(Object paramObject, int paramInt) throws IOException {
    this.Zr.Zz();
    ZZ(com.fasterxml.Zb.Zl.START_OBJECT);
    this.Zr = this.Zr.Zu(paramObject);
  }
  
  public final void Zh() throws IOException {
    Zu(com.fasterxml.Zb.Zl.END_OBJECT);
    Zf zf = this.Zr.ZJ();
    try {
      if (zf != null)
        this.Zr = zf; 
    } catch (IOException iOException) {
      throw a(null);
    } 
  }
  
  public final void ZY(String paramString) throws IOException {
    this.Zr.Zc(paramString);
    ZO(paramString);
  }
  
  public void Zm(Zj paramZj) throws IOException {
    this.Zr.Zc(paramZj.ZV());
    ZO(paramZj);
  }
  
  public void ZD(String paramString) throws IOException {
    int i = Zx.Zo();
    try {
      if (paramString == null) {
        try {
          ZT();
          if (i == 0) {
            ZN(com.fasterxml.Zb.Zl.VALUE_STRING, paramString);
            return;
          } 
        } catch (IOException iOException) {
          throw a(null);
        } 
        return;
      } 
    } catch (IOException iOException) {
      throw a(null);
    } 
    ZN(com.fasterxml.Zb.Zl.VALUE_STRING, paramString);
  }
  
  public void ZA(char[] paramArrayOfchar, int paramInt1, int paramInt2) throws IOException {
    ZD(new String(paramArrayOfchar, paramInt1, paramInt2));
  }
  
  public void Zr(Zj paramZj) throws IOException {
    int i = Zx.ZY();
    try {
      if (paramZj == null) {
        try {
          ZT();
          if (i != 0) {
            ZN(com.fasterxml.Zb.Zl.VALUE_STRING, paramZj);
            return;
          } 
        } catch (IOException iOException) {
          throw a(null);
        } 
        return;
      } 
    } catch (IOException iOException) {
      throw a(null);
    } 
    ZN(com.fasterxml.Zb.Zl.VALUE_STRING, paramZj);
  }
  
  public void ZM(String paramString) throws IOException {
    ZY();
  }
  
  public void Zt(String paramString, int paramInt1, int paramInt2) throws IOException {
    ZY();
  }
  
  public void Zg(Zj paramZj) throws IOException {
    ZY();
  }
  
  public void Zh(char[] paramArrayOfchar, int paramInt1, int paramInt2) throws IOException {
    ZY();
  }
  
  public void ZB(char paramChar) throws IOException {
    ZY();
  }
  
  public void Ze(String paramString) throws IOException {
    ZN(com.fasterxml.Zb.Zl.VALUE_EMBEDDED_OBJECT, new Zj(paramString));
  }
  
  public void ZF(short paramShort) throws IOException {
    ZN(com.fasterxml.Zb.Zl.VALUE_NUMBER_INT, Short.valueOf(paramShort));
  }
  
  public void Zd(int paramInt) throws IOException {
    ZN(com.fasterxml.Zb.Zl.VALUE_NUMBER_INT, Integer.valueOf(paramInt));
  }
  
  public void Zw(long paramLong) throws IOException {
    ZN(com.fasterxml.Zb.Zl.VALUE_NUMBER_INT, Long.valueOf(paramLong));
  }
  
  public void ZF(double paramDouble) throws IOException {
    ZN(com.fasterxml.Zb.Zl.VALUE_NUMBER_FLOAT, Double.valueOf(paramDouble));
  }
  
  public void Za(float paramFloat) throws IOException {
    ZN(com.fasterxml.Zb.Zl.VALUE_NUMBER_FLOAT, Float.valueOf(paramFloat));
  }
  
  public void ZI(BigDecimal paramBigDecimal) throws IOException {
    int i = Zx.ZY();
    try {
      if (paramBigDecimal == null) {
        try {
          ZT();
          if (i != 0) {
            ZN(com.fasterxml.Zb.Zl.VALUE_NUMBER_FLOAT, paramBigDecimal);
            return;
          } 
        } catch (IOException iOException) {
          throw a(null);
        } 
        return;
      } 
    } catch (IOException iOException) {
      throw a(null);
    } 
    ZN(com.fasterxml.Zb.Zl.VALUE_NUMBER_FLOAT, paramBigDecimal);
  }
  
  public void Zy(BigInteger paramBigInteger) throws IOException {
    int i = Zx.ZY();
    try {
      if (paramBigInteger == null) {
        try {
          ZT();
          if (i != 0) {
            ZN(com.fasterxml.Zb.Zl.VALUE_NUMBER_INT, paramBigInteger);
            return;
          } 
        } catch (IOException iOException) {
          throw a(null);
        } 
        return;
      } 
    } catch (IOException iOException) {
      throw a(null);
    } 
    ZN(com.fasterxml.Zb.Zl.VALUE_NUMBER_INT, paramBigInteger);
  }
  
  public void Zu(String paramString) throws IOException {
    ZN(com.fasterxml.Zb.Zl.VALUE_NUMBER_FLOAT, paramString);
  }
  
  private void ZD(Object paramObject) throws IOException {
    ZN(com.fasterxml.Zb.Zl.VALUE_NUMBER_INT, paramObject);
  }
  
  private void Zp(Object paramObject) throws IOException {
    ZN(com.fasterxml.Zb.Zl.VALUE_NUMBER_FLOAT, paramObject);
  }
  
  public void Zs(boolean paramBoolean) throws IOException {
    try {
    
    } catch (IOException iOException) {
      throw a(null);
    } 
    Zn(paramBoolean ? com.fasterxml.Zb.Zl.VALUE_TRUE : com.fasterxml.Zb.Zl.VALUE_FALSE);
  }
  
  public void ZT() throws IOException {
    Zn(com.fasterxml.Zb.Zl.VALUE_NULL);
  }
  
  public void ZZ(Object paramObject) throws IOException {
    // Byte code:
    //   0: invokestatic Zo : ()I
    //   3: istore_2
    //   4: aload_1
    //   5: ifnonnull -> 17
    //   8: aload_0
    //   9: invokevirtual ZT : ()V
    //   12: return
    //   13: invokestatic a : (Ljava/lang/Exception;)Ljava/lang/Exception;
    //   16: athrow
    //   17: aload_1
    //   18: invokevirtual getClass : ()Ljava/lang/Class;
    //   21: astore_3
    //   22: aload_3
    //   23: ldc [B
    //   25: if_acmpeq -> 42
    //   28: aload_1
    //   29: instanceof com/fasterxml/Zm/Zj
    //   32: ifeq -> 55
    //   35: goto -> 42
    //   38: invokestatic a : (Ljava/lang/Exception;)Ljava/lang/Exception;
    //   41: athrow
    //   42: aload_0
    //   43: getstatic com/fasterxml/Zb/Zl.VALUE_EMBEDDED_OBJECT : Lcom/fasterxml/Zb/Zl;
    //   46: aload_1
    //   47: invokevirtual ZN : (Lcom/fasterxml/Zb/Zl;Ljava/lang/Object;)V
    //   50: return
    //   51: invokestatic a : (Ljava/lang/Exception;)Ljava/lang/Exception;
    //   54: athrow
    //   55: aload_0
    //   56: getfield ZZ : Lcom/fasterxml/Zb/Zmd;
    //   59: ifnonnull -> 81
    //   62: aload_0
    //   63: getstatic com/fasterxml/Zb/Zl.VALUE_EMBEDDED_OBJECT : Lcom/fasterxml/Zb/Zl;
    //   66: aload_1
    //   67: invokevirtual ZN : (Lcom/fasterxml/Zb/Zl;Ljava/lang/Object;)V
    //   70: iload_2
    //   71: ifne -> 97
    //   74: goto -> 81
    //   77: invokestatic a : (Ljava/lang/Exception;)Ljava/lang/Exception;
    //   80: athrow
    //   81: aload_0
    //   82: getfield ZZ : Lcom/fasterxml/Zb/Zmd;
    //   85: aload_0
    //   86: aload_1
    //   87: invokevirtual ZZ : (Lcom/fasterxml/Zb/Zf;Ljava/lang/Object;)V
    //   90: goto -> 97
    //   93: invokestatic a : (Ljava/lang/Exception;)Ljava/lang/Exception;
    //   96: athrow
    //   97: return
    // Exception table:
    //   from	to	target	type
    //   4	13	13	java/io/IOException
    //   22	35	38	java/io/IOException
    //   28	51	51	java/io/IOException
    //   55	74	77	java/io/IOException
    //   62	90	93	java/io/IOException
  }
  
  public void Z_(Zy paramZy, byte[] paramArrayOfbyte, int paramInt1, int paramInt2) throws IOException {
    byte[] arrayOfByte = new byte[paramInt2];
    System.arraycopy(paramArrayOfbyte, paramInt1, arrayOfByte, 0, paramInt2);
    ZZ(arrayOfByte);
  }
  
  public int ZE(Zy paramZy, InputStream paramInputStream, int paramInt) {
    throw new UnsupportedOperationException();
  }
  
  public boolean ZH() {
    return this.Zb;
  }
  
  public boolean ZB() {
    return this.Zx;
  }
  
  public void Zu(Object paramObject) {
    this.Zf = paramObject;
    this.Zo = true;
  }
  
  public void ZV(Object paramObject) {
    this.Zm = paramObject;
    this.Zo = true;
  }
  
  public void ZJ(Object paramObject) throws IOException {
    ZN(com.fasterxml.Zb.Zl.VALUE_EMBEDDED_OBJECT, paramObject);
  }
  
  public void Zg(Zg paramZg) throws IOException {
    // Byte code:
    //   0: invokestatic ZY : ()I
    //   3: istore_2
    //   4: aload_0
    //   5: getfield ZO : Z
    //   8: ifeq -> 23
    //   11: aload_0
    //   12: aload_1
    //   13: invokespecial ZT : (Lcom/fasterxml/Zb/Zg;)V
    //   16: goto -> 23
    //   19: invokestatic a : (Ljava/lang/Exception;)Ljava/lang/Exception;
    //   22: athrow
    //   23: getstatic com/fasterxml/Zm/Zg.Z_ : [I
    //   26: aload_1
    //   27: invokevirtual Zh : ()Lcom/fasterxml/Zb/Zl;
    //   30: invokevirtual ordinal : ()I
    //   33: iaload
    //   34: tableswitch default -> 418, 1 -> 96, 2 -> 111, 3 -> 126, 4 -> 141, 5 -> 156, 6 -> 175, 7 -> 235, 8 -> 333, 9 -> 352, 10 -> 368, 11 -> 384, 12 -> 399
    //   96: aload_0
    //   97: invokevirtual ZJ : ()V
    //   100: iload_2
    //   101: ifeq -> 459
    //   104: goto -> 111
    //   107: invokestatic a : (Ljava/lang/Exception;)Ljava/lang/Exception;
    //   110: athrow
    //   111: aload_0
    //   112: invokevirtual Zh : ()V
    //   115: iload_2
    //   116: ifeq -> 459
    //   119: goto -> 126
    //   122: invokestatic a : (Ljava/lang/Exception;)Ljava/lang/Exception;
    //   125: athrow
    //   126: aload_0
    //   127: invokevirtual Zd : ()V
    //   130: iload_2
    //   131: ifeq -> 459
    //   134: goto -> 141
    //   137: invokestatic a : (Ljava/lang/Exception;)Ljava/lang/Exception;
    //   140: athrow
    //   141: aload_0
    //   142: invokevirtual ZI : ()V
    //   145: iload_2
    //   146: ifeq -> 459
    //   149: goto -> 156
    //   152: invokestatic a : (Ljava/lang/Exception;)Ljava/lang/Exception;
    //   155: athrow
    //   156: aload_0
    //   157: aload_1
    //   158: invokevirtual ZS : ()Ljava/lang/String;
    //   161: invokevirtual ZY : (Ljava/lang/String;)V
    //   164: iload_2
    //   165: ifeq -> 459
    //   168: goto -> 175
    //   171: invokestatic a : (Ljava/lang/Exception;)Ljava/lang/Exception;
    //   174: athrow
    //   175: aload_1
    //   176: invokevirtual Zi : ()Z
    //   179: ifeq -> 216
    //   182: goto -> 189
    //   185: invokestatic a : (Ljava/lang/Exception;)Ljava/lang/Exception;
    //   188: athrow
    //   189: aload_0
    //   190: aload_1
    //   191: invokevirtual ZW : ()[C
    //   194: aload_1
    //   195: invokevirtual Zk : ()I
    //   198: aload_1
    //   199: invokevirtual Zn : ()I
    //   202: invokevirtual ZA : ([CII)V
    //   205: iload_2
    //   206: ifeq -> 459
    //   209: goto -> 216
    //   212: invokestatic a : (Ljava/lang/Exception;)Ljava/lang/Exception;
    //   215: athrow
    //   216: aload_0
    //   217: aload_1
    //   218: invokevirtual ZR : ()Ljava/lang/String;
    //   221: invokevirtual ZD : (Ljava/lang/String;)V
    //   224: iload_2
    //   225: ifeq -> 459
    //   228: goto -> 235
    //   231: invokestatic a : (Ljava/lang/Exception;)Ljava/lang/Exception;
    //   234: athrow
    //   235: getstatic com/fasterxml/Zm/Zg.Zn : [I
    //   238: aload_1
    //   239: invokevirtual ZL : ()Lcom/fasterxml/Zb/Zk;
    //   242: invokevirtual ordinal : ()I
    //   245: iaload
    //   246: lookupswitch default -> 314, 1 -> 276, 2 -> 295
    //   272: invokestatic a : (Ljava/lang/Exception;)Ljava/lang/Exception;
    //   275: athrow
    //   276: aload_0
    //   277: aload_1
    //   278: invokevirtual Ze : ()I
    //   281: invokevirtual Zd : (I)V
    //   284: iload_2
    //   285: ifeq -> 459
    //   288: goto -> 295
    //   291: invokestatic a : (Ljava/lang/Exception;)Ljava/lang/Exception;
    //   294: athrow
    //   295: aload_0
    //   296: aload_1
    //   297: invokevirtual ZI : ()Ljava/lang/Object;
    //   300: invokespecial ZD : (Ljava/lang/Object;)V
    //   303: iload_2
    //   304: ifeq -> 459
    //   307: goto -> 314
    //   310: invokestatic a : (Ljava/lang/Exception;)Ljava/lang/Exception;
    //   313: athrow
    //   314: aload_0
    //   315: aload_1
    //   316: invokevirtual ZE : ()J
    //   319: invokevirtual Zw : (J)V
    //   322: iload_2
    //   323: ifeq -> 459
    //   326: goto -> 333
    //   329: invokestatic a : (Ljava/lang/Exception;)Ljava/lang/Exception;
    //   332: athrow
    //   333: aload_0
    //   334: aload_1
    //   335: invokevirtual ZI : ()Ljava/lang/Object;
    //   338: invokespecial Zp : (Ljava/lang/Object;)V
    //   341: iload_2
    //   342: ifeq -> 459
    //   345: goto -> 352
    //   348: invokestatic a : (Ljava/lang/Exception;)Ljava/lang/Exception;
    //   351: athrow
    //   352: aload_0
    //   353: iconst_1
    //   354: invokevirtual Zs : (Z)V
    //   357: iload_2
    //   358: ifeq -> 459
    //   361: goto -> 368
    //   364: invokestatic a : (Ljava/lang/Exception;)Ljava/lang/Exception;
    //   367: athrow
    //   368: aload_0
    //   369: iconst_0
    //   370: invokevirtual Zs : (Z)V
    //   373: iload_2
    //   374: ifeq -> 459
    //   377: goto -> 384
    //   380: invokestatic a : (Ljava/lang/Exception;)Ljava/lang/Exception;
    //   383: athrow
    //   384: aload_0
    //   385: invokevirtual ZT : ()V
    //   388: iload_2
    //   389: ifeq -> 459
    //   392: goto -> 399
    //   395: invokestatic a : (Ljava/lang/Exception;)Ljava/lang/Exception;
    //   398: athrow
    //   399: aload_0
    //   400: aload_1
    //   401: invokevirtual ZO : ()Ljava/lang/Object;
    //   404: invokevirtual ZZ : (Ljava/lang/Object;)V
    //   407: iload_2
    //   408: ifeq -> 459
    //   411: goto -> 418
    //   414: invokestatic a : (Ljava/lang/Exception;)Ljava/lang/Exception;
    //   417: athrow
    //   418: new java/lang/RuntimeException
    //   421: dup
    //   422: new java/lang/StringBuilder
    //   425: dup
    //   426: invokespecial <init> : ()V
    //   429: sipush #-25843
    //   432: sipush #31558
    //   435: invokestatic b : (II)Ljava/lang/String;
    //   438: invokevirtual append : (Ljava/lang/String;)Ljava/lang/StringBuilder;
    //   441: aload_1
    //   442: invokevirtual Zh : ()Lcom/fasterxml/Zb/Zl;
    //   445: invokevirtual append : (Ljava/lang/Object;)Ljava/lang/StringBuilder;
    //   448: invokevirtual toString : ()Ljava/lang/String;
    //   451: invokespecial <init> : (Ljava/lang/String;)V
    //   454: athrow
    //   455: invokestatic a : (Ljava/lang/Exception;)Ljava/lang/Exception;
    //   458: athrow
    //   459: return
    // Exception table:
    //   from	to	target	type
    //   4	16	19	java/io/IOException
    //   23	104	107	java/io/IOException
    //   96	119	122	java/io/IOException
    //   111	134	137	java/io/IOException
    //   126	149	152	java/io/IOException
    //   141	168	171	java/io/IOException
    //   156	182	185	java/io/IOException
    //   175	209	212	java/io/IOException
    //   189	228	231	java/io/IOException
    //   216	272	272	java/io/IOException
    //   235	288	291	java/io/IOException
    //   276	307	310	java/io/IOException
    //   295	326	329	java/io/IOException
    //   314	345	348	java/io/IOException
    //   333	361	364	java/io/IOException
    //   352	377	380	java/io/IOException
    //   368	392	395	java/io/IOException
    //   384	411	414	java/io/IOException
    //   399	455	455	java/io/IOException
  }
  
  public void ZE(Zg paramZg) throws IOException {
    // Byte code:
    //   0: invokestatic Zo : ()I
    //   3: aload_1
    //   4: invokevirtual Zh : ()Lcom/fasterxml/Zb/Zl;
    //   7: astore_3
    //   8: istore_2
    //   9: aload_3
    //   10: getstatic com/fasterxml/Zb/Zl.FIELD_NAME : Lcom/fasterxml/Zb/Zl;
    //   13: if_acmpne -> 59
    //   16: aload_0
    //   17: getfield ZO : Z
    //   20: ifeq -> 42
    //   23: goto -> 30
    //   26: invokestatic a : (Ljava/lang/Exception;)Ljava/lang/Exception;
    //   29: athrow
    //   30: aload_0
    //   31: aload_1
    //   32: invokespecial ZT : (Lcom/fasterxml/Zb/Zg;)V
    //   35: goto -> 42
    //   38: invokestatic a : (Ljava/lang/Exception;)Ljava/lang/Exception;
    //   41: athrow
    //   42: aload_0
    //   43: aload_1
    //   44: invokevirtual ZS : ()Ljava/lang/String;
    //   47: invokevirtual ZY : (Ljava/lang/String;)V
    //   50: aload_1
    //   51: invokevirtual ZV : ()Lcom/fasterxml/Zb/Zl;
    //   54: astore_3
    //   55: iload_2
    //   56: ifne -> 93
    //   59: aload_3
    //   60: ifnonnull -> 93
    //   63: goto -> 70
    //   66: invokestatic a : (Ljava/lang/Exception;)Ljava/lang/Exception;
    //   69: athrow
    //   70: new com/fasterxml/Zqd
    //   73: dup
    //   74: aload_1
    //   75: aconst_null
    //   76: sipush #-25848
    //   79: sipush #3811
    //   82: invokestatic b : (II)Ljava/lang/String;
    //   85: invokespecial <init> : (Lcom/fasterxml/Zb/Zg;Lcom/fasterxml/Zb/Zl;Ljava/lang/String;)V
    //   88: athrow
    //   89: invokestatic a : (Ljava/lang/Exception;)Ljava/lang/Exception;
    //   92: athrow
    //   93: getstatic com/fasterxml/Zm/Zg.Z_ : [I
    //   96: aload_3
    //   97: invokevirtual ordinal : ()I
    //   100: iaload
    //   101: tableswitch default -> 240, 1 -> 171, 2 -> 225, 3 -> 132, 4 -> 210
    //   132: aload_0
    //   133: getfield ZO : Z
    //   136: ifeq -> 158
    //   139: goto -> 146
    //   142: invokestatic a : (Ljava/lang/Exception;)Ljava/lang/Exception;
    //   145: athrow
    //   146: aload_0
    //   147: aload_1
    //   148: invokespecial ZT : (Lcom/fasterxml/Zb/Zg;)V
    //   151: goto -> 158
    //   154: invokestatic a : (Ljava/lang/Exception;)Ljava/lang/Exception;
    //   157: athrow
    //   158: aload_0
    //   159: invokevirtual Zd : ()V
    //   162: aload_0
    //   163: aload_1
    //   164: invokevirtual Zx : (Lcom/fasterxml/Zb/Zg;)V
    //   167: iload_2
    //   168: ifne -> 253
    //   171: aload_0
    //   172: getfield ZO : Z
    //   175: ifeq -> 197
    //   178: goto -> 185
    //   181: invokestatic a : (Ljava/lang/Exception;)Ljava/lang/Exception;
    //   184: athrow
    //   185: aload_0
    //   186: aload_1
    //   187: invokespecial ZT : (Lcom/fasterxml/Zb/Zg;)V
    //   190: goto -> 197
    //   193: invokestatic a : (Ljava/lang/Exception;)Ljava/lang/Exception;
    //   196: athrow
    //   197: aload_0
    //   198: invokevirtual ZJ : ()V
    //   201: aload_0
    //   202: aload_1
    //   203: invokevirtual Zx : (Lcom/fasterxml/Zb/Zg;)V
    //   206: iload_2
    //   207: ifne -> 253
    //   210: aload_0
    //   211: invokevirtual ZI : ()V
    //   214: iload_2
    //   215: ifne -> 253
    //   218: goto -> 225
    //   221: invokestatic a : (Ljava/lang/Exception;)Ljava/lang/Exception;
    //   224: athrow
    //   225: aload_0
    //   226: invokevirtual Zh : ()V
    //   229: iload_2
    //   230: ifne -> 253
    //   233: goto -> 240
    //   236: invokestatic a : (Ljava/lang/Exception;)Ljava/lang/Exception;
    //   239: athrow
    //   240: aload_0
    //   241: aload_1
    //   242: aload_3
    //   243: invokespecial Zb : (Lcom/fasterxml/Zb/Zg;Lcom/fasterxml/Zb/Zl;)V
    //   246: goto -> 253
    //   249: invokestatic a : (Ljava/lang/Exception;)Ljava/lang/Exception;
    //   252: athrow
    //   253: return
    // Exception table:
    //   from	to	target	type
    //   9	23	26	java/io/IOException
    //   16	35	38	java/io/IOException
    //   55	63	66	java/io/IOException
    //   59	89	89	java/io/IOException
    //   93	139	142	java/io/IOException
    //   132	151	154	java/io/IOException
    //   158	178	181	java/io/IOException
    //   171	190	193	java/io/IOException
    //   197	218	221	java/io/IOException
    //   210	233	236	java/io/IOException
    //   225	246	249	java/io/IOException
  }
  
  protected void Zx(Zg paramZg) throws IOException {
    byte b = 1;
    int i = Zx.ZY();
    com.fasterxml.Zb.Zl zl;
    while ((zl = paramZg.ZV()) != null) {
      try {
        switch (Zg.Z_[zl.ordinal()]) {
          case 5:
          
          case 3:
          
          case 1:
          
          case 4:
            ZI();
            if (--b == 0)
              return; 
            continue;
          case 2:
            Zh();
            if (--b == 0)
              return; 
            continue;
        } 
      } catch (IOException iOException) {
        throw a(null);
      } 
      Zb(paramZg, zl);
      continue;
      if (i != 0)
        break; 
    } 
  }
  
  private void Zb(Zg paramZg, com.fasterxml.Zb.Zl paramZl) throws IOException {
    // Byte code:
    //   0: invokestatic Zo : ()I
    //   3: istore_3
    //   4: aload_0
    //   5: getfield ZO : Z
    //   8: ifeq -> 23
    //   11: aload_0
    //   12: aload_1
    //   13: invokespecial ZT : (Lcom/fasterxml/Zb/Zg;)V
    //   16: goto -> 23
    //   19: invokestatic a : (Ljava/lang/Exception;)Ljava/lang/Exception;
    //   22: athrow
    //   23: getstatic com/fasterxml/Zm/Zg.Z_ : [I
    //   26: aload_2
    //   27: invokevirtual ordinal : ()I
    //   30: iaload
    //   31: tableswitch default -> 314, 6 -> 72, 7 -> 132, 8 -> 229, 9 -> 248, 10 -> 264, 11 -> 280, 12 -> 295
    //   72: aload_1
    //   73: invokevirtual Zi : ()Z
    //   76: ifeq -> 113
    //   79: goto -> 86
    //   82: invokestatic a : (Ljava/lang/Exception;)Ljava/lang/Exception;
    //   85: athrow
    //   86: aload_0
    //   87: aload_1
    //   88: invokevirtual ZW : ()[C
    //   91: aload_1
    //   92: invokevirtual Zk : ()I
    //   95: aload_1
    //   96: invokevirtual Zn : ()I
    //   99: invokevirtual ZA : ([CII)V
    //   102: iload_3
    //   103: ifne -> 352
    //   106: goto -> 113
    //   109: invokestatic a : (Ljava/lang/Exception;)Ljava/lang/Exception;
    //   112: athrow
    //   113: aload_0
    //   114: aload_1
    //   115: invokevirtual ZR : ()Ljava/lang/String;
    //   118: invokevirtual ZD : (Ljava/lang/String;)V
    //   121: iload_3
    //   122: ifne -> 352
    //   125: goto -> 132
    //   128: invokestatic a : (Ljava/lang/Exception;)Ljava/lang/Exception;
    //   131: athrow
    //   132: getstatic com/fasterxml/Zm/Zg.Zn : [I
    //   135: aload_1
    //   136: invokevirtual ZL : ()Lcom/fasterxml/Zb/Zk;
    //   139: invokevirtual ordinal : ()I
    //   142: iaload
    //   143: lookupswitch default -> 210, 1 -> 172, 2 -> 191
    //   168: invokestatic a : (Ljava/lang/Exception;)Ljava/lang/Exception;
    //   171: athrow
    //   172: aload_0
    //   173: aload_1
    //   174: invokevirtual Ze : ()I
    //   177: invokevirtual Zd : (I)V
    //   180: iload_3
    //   181: ifne -> 352
    //   184: goto -> 191
    //   187: invokestatic a : (Ljava/lang/Exception;)Ljava/lang/Exception;
    //   190: athrow
    //   191: aload_0
    //   192: aload_1
    //   193: invokevirtual ZI : ()Ljava/lang/Object;
    //   196: invokespecial ZD : (Ljava/lang/Object;)V
    //   199: iload_3
    //   200: ifne -> 352
    //   203: goto -> 210
    //   206: invokestatic a : (Ljava/lang/Exception;)Ljava/lang/Exception;
    //   209: athrow
    //   210: aload_0
    //   211: aload_1
    //   212: invokevirtual ZE : ()J
    //   215: invokevirtual Zw : (J)V
    //   218: iload_3
    //   219: ifne -> 352
    //   222: goto -> 229
    //   225: invokestatic a : (Ljava/lang/Exception;)Ljava/lang/Exception;
    //   228: athrow
    //   229: aload_0
    //   230: aload_1
    //   231: invokevirtual ZI : ()Ljava/lang/Object;
    //   234: invokespecial Zp : (Ljava/lang/Object;)V
    //   237: iload_3
    //   238: ifne -> 352
    //   241: goto -> 248
    //   244: invokestatic a : (Ljava/lang/Exception;)Ljava/lang/Exception;
    //   247: athrow
    //   248: aload_0
    //   249: iconst_1
    //   250: invokevirtual Zs : (Z)V
    //   253: iload_3
    //   254: ifne -> 352
    //   257: goto -> 264
    //   260: invokestatic a : (Ljava/lang/Exception;)Ljava/lang/Exception;
    //   263: athrow
    //   264: aload_0
    //   265: iconst_0
    //   266: invokevirtual Zs : (Z)V
    //   269: iload_3
    //   270: ifne -> 352
    //   273: goto -> 280
    //   276: invokestatic a : (Ljava/lang/Exception;)Ljava/lang/Exception;
    //   279: athrow
    //   280: aload_0
    //   281: invokevirtual ZT : ()V
    //   284: iload_3
    //   285: ifne -> 352
    //   288: goto -> 295
    //   291: invokestatic a : (Ljava/lang/Exception;)Ljava/lang/Exception;
    //   294: athrow
    //   295: aload_0
    //   296: aload_1
    //   297: invokevirtual ZO : ()Ljava/lang/Object;
    //   300: invokevirtual ZZ : (Ljava/lang/Object;)V
    //   303: iload_3
    //   304: ifne -> 352
    //   307: goto -> 314
    //   310: invokestatic a : (Ljava/lang/Exception;)Ljava/lang/Exception;
    //   313: athrow
    //   314: new java/lang/RuntimeException
    //   317: dup
    //   318: new java/lang/StringBuilder
    //   321: dup
    //   322: invokespecial <init> : ()V
    //   325: sipush #-25842
    //   328: sipush #-16517
    //   331: invokestatic b : (II)Ljava/lang/String;
    //   334: invokevirtual append : (Ljava/lang/String;)Ljava/lang/StringBuilder;
    //   337: aload_2
    //   338: invokevirtual append : (Ljava/lang/Object;)Ljava/lang/StringBuilder;
    //   341: invokevirtual toString : ()Ljava/lang/String;
    //   344: invokespecial <init> : (Ljava/lang/String;)V
    //   347: athrow
    //   348: invokestatic a : (Ljava/lang/Exception;)Ljava/lang/Exception;
    //   351: athrow
    //   352: return
    // Exception table:
    //   from	to	target	type
    //   4	16	19	java/io/IOException
    //   23	79	82	java/io/IOException
    //   72	106	109	java/io/IOException
    //   86	125	128	java/io/IOException
    //   113	168	168	java/io/IOException
    //   132	184	187	java/io/IOException
    //   172	203	206	java/io/IOException
    //   191	222	225	java/io/IOException
    //   210	241	244	java/io/IOException
    //   229	257	260	java/io/IOException
    //   248	273	276	java/io/IOException
    //   264	288	291	java/io/IOException
    //   280	307	310	java/io/IOException
    //   295	348	348	java/io/IOException
  }
  
  private final void ZT(Zg paramZg) throws IOException {
    try {
      if ((this.Zf = paramZg.ZJ()) != null)
        this.Zo = true; 
    } catch (IOException iOException) {
      throw a(null);
    } 
    try {
      if ((this.Zm = paramZg.ZZ()) != null)
        this.Zo = true; 
    } catch (IOException iOException) {
      throw a(null);
    } 
  }
  
  protected final void Zn(com.fasterxml.Zb.Zl paramZl) {
    // Byte code:
    //   0: invokestatic Zo : ()I
    //   3: aload_0
    //   4: getfield Zr : Lcom/fasterxml/Zq/Zf;
    //   7: invokevirtual Zz : ()I
    //   10: pop
    //   11: istore_2
    //   12: aload_0
    //   13: getfield Zo : Z
    //   16: ifeq -> 44
    //   19: aload_0
    //   20: getfield Zs : Lcom/fasterxml/Zm/Ze5;
    //   23: aload_0
    //   24: getfield Zc : I
    //   27: aload_1
    //   28: aload_0
    //   29: getfield Zm : Ljava/lang/Object;
    //   32: aload_0
    //   33: getfield Zf : Ljava/lang/Object;
    //   36: invokevirtual ZC : (ILcom/fasterxml/Zb/Zl;Ljava/lang/Object;Ljava/lang/Object;)Lcom/fasterxml/Zm/Ze5;
    //   39: astore_3
    //   40: iload_2
    //   41: ifne -> 57
    //   44: aload_0
    //   45: getfield Zs : Lcom/fasterxml/Zm/Ze5;
    //   48: aload_0
    //   49: getfield Zc : I
    //   52: aload_1
    //   53: invokevirtual Zk : (ILcom/fasterxml/Zb/Zl;)Lcom/fasterxml/Zm/Ze5;
    //   56: astore_3
    //   57: aload_3
    //   58: ifnonnull -> 82
    //   61: aload_0
    //   62: dup
    //   63: getfield Zc : I
    //   66: iconst_1
    //   67: iadd
    //   68: putfield Zc : I
    //   71: iload_2
    //   72: ifne -> 99
    //   75: goto -> 82
    //   78: invokestatic a : (Ljava/lang/Exception;)Ljava/lang/Exception;
    //   81: athrow
    //   82: aload_0
    //   83: aload_3
    //   84: putfield Zs : Lcom/fasterxml/Zm/Ze5;
    //   87: aload_0
    //   88: iconst_1
    //   89: putfield Zc : I
    //   92: goto -> 99
    //   95: invokestatic a : (Ljava/lang/Exception;)Ljava/lang/Exception;
    //   98: athrow
    //   99: return
    // Exception table:
    //   from	to	target	type
    //   57	75	78	java/lang/RuntimeException
    //   61	92	95	java/lang/RuntimeException
  }
  
  protected final void ZN(com.fasterxml.Zb.Zl paramZl, Object paramObject) {
    // Byte code:
    //   0: invokestatic ZY : ()I
    //   3: aload_0
    //   4: getfield Zr : Lcom/fasterxml/Zq/Zf;
    //   7: invokevirtual Zz : ()I
    //   10: pop
    //   11: istore_3
    //   12: aload_0
    //   13: getfield Zo : Z
    //   16: ifeq -> 46
    //   19: aload_0
    //   20: getfield Zs : Lcom/fasterxml/Zm/Ze5;
    //   23: aload_0
    //   24: getfield Zc : I
    //   27: aload_1
    //   28: aload_2
    //   29: aload_0
    //   30: getfield Zm : Ljava/lang/Object;
    //   33: aload_0
    //   34: getfield Zf : Ljava/lang/Object;
    //   37: invokevirtual ZW : (ILcom/fasterxml/Zb/Zl;Ljava/lang/Object;Ljava/lang/Object;Ljava/lang/Object;)Lcom/fasterxml/Zm/Ze5;
    //   40: astore #4
    //   42: iload_3
    //   43: ifeq -> 61
    //   46: aload_0
    //   47: getfield Zs : Lcom/fasterxml/Zm/Ze5;
    //   50: aload_0
    //   51: getfield Zc : I
    //   54: aload_1
    //   55: aload_2
    //   56: invokevirtual Zj : (ILcom/fasterxml/Zb/Zl;Ljava/lang/Object;)Lcom/fasterxml/Zm/Ze5;
    //   59: astore #4
    //   61: aload #4
    //   63: ifnonnull -> 87
    //   66: aload_0
    //   67: dup
    //   68: getfield Zc : I
    //   71: iconst_1
    //   72: iadd
    //   73: putfield Zc : I
    //   76: iload_3
    //   77: ifeq -> 105
    //   80: goto -> 87
    //   83: invokestatic a : (Ljava/lang/Exception;)Ljava/lang/Exception;
    //   86: athrow
    //   87: aload_0
    //   88: aload #4
    //   90: putfield Zs : Lcom/fasterxml/Zm/Ze5;
    //   93: aload_0
    //   94: iconst_1
    //   95: putfield Zc : I
    //   98: goto -> 105
    //   101: invokestatic a : (Ljava/lang/Exception;)Ljava/lang/Exception;
    //   104: athrow
    //   105: return
    // Exception table:
    //   from	to	target	type
    //   61	80	83	java/lang/RuntimeException
    //   66	98	101	java/lang/RuntimeException
  }
  
  protected final void ZO(Object paramObject) {
    // Byte code:
    //   0: invokestatic Zo : ()I
    //   3: istore_2
    //   4: aload_0
    //   5: getfield Zo : Z
    //   8: ifeq -> 39
    //   11: aload_0
    //   12: getfield Zs : Lcom/fasterxml/Zm/Ze5;
    //   15: aload_0
    //   16: getfield Zc : I
    //   19: getstatic com/fasterxml/Zb/Zl.FIELD_NAME : Lcom/fasterxml/Zb/Zl;
    //   22: aload_1
    //   23: aload_0
    //   24: getfield Zm : Ljava/lang/Object;
    //   27: aload_0
    //   28: getfield Zf : Ljava/lang/Object;
    //   31: invokevirtual ZW : (ILcom/fasterxml/Zb/Zl;Ljava/lang/Object;Ljava/lang/Object;Ljava/lang/Object;)Lcom/fasterxml/Zm/Ze5;
    //   34: astore_3
    //   35: iload_2
    //   36: ifne -> 55
    //   39: aload_0
    //   40: getfield Zs : Lcom/fasterxml/Zm/Ze5;
    //   43: aload_0
    //   44: getfield Zc : I
    //   47: getstatic com/fasterxml/Zb/Zl.FIELD_NAME : Lcom/fasterxml/Zb/Zl;
    //   50: aload_1
    //   51: invokevirtual Zj : (ILcom/fasterxml/Zb/Zl;Ljava/lang/Object;)Lcom/fasterxml/Zm/Ze5;
    //   54: astore_3
    //   55: aload_3
    //   56: ifnonnull -> 80
    //   59: aload_0
    //   60: dup
    //   61: getfield Zc : I
    //   64: iconst_1
    //   65: iadd
    //   66: putfield Zc : I
    //   69: iload_2
    //   70: ifne -> 97
    //   73: goto -> 80
    //   76: invokestatic a : (Ljava/lang/Exception;)Ljava/lang/Exception;
    //   79: athrow
    //   80: aload_0
    //   81: aload_3
    //   82: putfield Zs : Lcom/fasterxml/Zm/Ze5;
    //   85: aload_0
    //   86: iconst_1
    //   87: putfield Zc : I
    //   90: goto -> 97
    //   93: invokestatic a : (Ljava/lang/Exception;)Ljava/lang/Exception;
    //   96: athrow
    //   97: return
    // Exception table:
    //   from	to	target	type
    //   55	73	76	java/lang/RuntimeException
    //   59	90	93	java/lang/RuntimeException
  }
  
  protected final void ZZ(com.fasterxml.Zb.Zl paramZl) {
    // Byte code:
    //   0: invokestatic Zo : ()I
    //   3: istore_2
    //   4: aload_0
    //   5: getfield Zo : Z
    //   8: ifeq -> 36
    //   11: aload_0
    //   12: getfield Zs : Lcom/fasterxml/Zm/Ze5;
    //   15: aload_0
    //   16: getfield Zc : I
    //   19: aload_1
    //   20: aload_0
    //   21: getfield Zm : Ljava/lang/Object;
    //   24: aload_0
    //   25: getfield Zf : Ljava/lang/Object;
    //   28: invokevirtual ZC : (ILcom/fasterxml/Zb/Zl;Ljava/lang/Object;Ljava/lang/Object;)Lcom/fasterxml/Zm/Ze5;
    //   31: astore_3
    //   32: iload_2
    //   33: ifne -> 49
    //   36: aload_0
    //   37: getfield Zs : Lcom/fasterxml/Zm/Ze5;
    //   40: aload_0
    //   41: getfield Zc : I
    //   44: aload_1
    //   45: invokevirtual Zk : (ILcom/fasterxml/Zb/Zl;)Lcom/fasterxml/Zm/Ze5;
    //   48: astore_3
    //   49: aload_3
    //   50: ifnonnull -> 74
    //   53: aload_0
    //   54: dup
    //   55: getfield Zc : I
    //   58: iconst_1
    //   59: iadd
    //   60: putfield Zc : I
    //   63: iload_2
    //   64: ifne -> 91
    //   67: goto -> 74
    //   70: invokestatic a : (Ljava/lang/Exception;)Ljava/lang/Exception;
    //   73: athrow
    //   74: aload_0
    //   75: aload_3
    //   76: putfield Zs : Lcom/fasterxml/Zm/Ze5;
    //   79: aload_0
    //   80: iconst_1
    //   81: putfield Zc : I
    //   84: goto -> 91
    //   87: invokestatic a : (Ljava/lang/Exception;)Ljava/lang/Exception;
    //   90: athrow
    //   91: return
    // Exception table:
    //   from	to	target	type
    //   49	67	70	java/lang/RuntimeException
    //   53	84	87	java/lang/RuntimeException
  }
  
  protected final void Zu(com.fasterxml.Zb.Zl paramZl) {
    Ze5 ze5 = this.Zs.Zk(this.Zc, paramZl);
    int i = Zx.Zo();
    try {
      if (ze5 == null) {
        try {
          this.Zc++;
          if (i == 0) {
            this.Zs = ze5;
            this.Zc = 1;
            return;
          } 
        } catch (RuntimeException runtimeException) {
          throw a(null);
        } 
        return;
      } 
    } catch (RuntimeException runtimeException) {
      throw a(null);
    } 
    this.Zs = ze5;
    this.Zc = 1;
  }
  
  protected void ZY() {
    throw new UnsupportedOperationException(b(-25854, -11635));
  }
  
  static {
    // Byte code:
    //   0: bipush #13
    //   2: anewarray java/lang/String
    //   5: astore #5
    //   7: iconst_0
    //   8: istore_3
    //   9: ldc '];~\\beZ;B:\\tfEPE"`@-oyu\gzI&\\r7{\\tF vbD$JY@]~"b\\t*a!NW"4`^?,?B\\t\\nY""6\\rDgr"w: ,A\\npPV1HqV.Kr^?9=00Xpsmd|YKRt%.?;"=DCGIW{1fTo9[8P<6w!_XRlkN@:=aH0.o"o'
    //   11: dup
    //   12: astore_2
    //   13: invokevirtual length : ()I
    //   16: istore #4
    //   18: bipush #14
    //   20: istore_1
    //   21: iconst_m1
    //   22: istore_0
    //   23: bipush #83
    //   25: iinc #0, 1
    //   28: aload_2
    //   29: iload_0
    //   30: dup
    //   31: iload_1
    //   32: iadd
    //   33: invokevirtual substring : (II)Ljava/lang/String;
    //   36: iconst_m1
    //   37: goto -> 143
    //   40: aload #5
    //   42: swap
    //   43: iload_3
    //   44: iinc #3, 1
    //   47: swap
    //   48: aastore
    //   49: iload_0
    //   50: iload_1
    //   51: iadd
    //   52: dup
    //   53: istore_0
    //   54: iload #4
    //   56: if_icmpge -> 68
    //   59: aload_2
    //   60: iload_0
    //   61: invokevirtual charAt : (I)C
    //   64: istore_1
    //   65: goto -> 23
    //   68: ldc ']LJZ-q\5\YH]Rl\!F{04~nof|R4N5&`?\\n>R3R( ybz'
    //   70: dup
    //   71: astore_2
    //   72: invokevirtual length : ()I
    //   75: istore #4
    //   77: bipush #81
    //   79: istore_1
    //   80: iconst_m1
    //   81: istore_0
    //   82: bipush #111
    //   84: iinc #0, 1
    //   87: aload_2
    //   88: iload_0
    //   89: dup
    //   90: iload_1
    //   91: iadd
    //   92: invokevirtual substring : (II)Ljava/lang/String;
    //   95: iconst_0
    //   96: goto -> 143
    //   99: aload #5
    //   101: swap
    //   102: iload_3
    //   103: iinc #3, 1
    //   106: swap
    //   107: aastore
    //   108: iload_0
    //   109: iload_1
    //   110: iadd
    //   111: dup
    //   112: istore_0
    //   113: iload #4
    //   115: if_icmpge -> 127
    //   118: aload_2
    //   119: iload_0
    //   120: invokevirtual charAt : (I)C
    //   123: istore_1
    //   124: goto -> 82
    //   127: aload #5
    //   129: putstatic com/fasterxml/Zm/Zl.c : [Ljava/lang/String;
    //   132: bipush #13
    //   134: anewarray java/lang/String
    //   137: putstatic com/fasterxml/Zm/Zl.d : [Ljava/lang/String;
    //   140: goto -> 300
    //   143: dup_x2
    //   144: pop
    //   145: invokevirtual toCharArray : ()[C
    //   148: dup_x1
    //   149: arraylength
    //   150: dup_x2
    //   151: pop
    //   152: iconst_0
    //   153: istore #6
    //   155: dup2_x1
    //   156: pop2
    //   157: dup_x2
    //   158: iconst_1
    //   159: if_icmpgt -> 259
    //   162: dup2
    //   163: swap
    //   164: iload #6
    //   166: dup2_x1
    //   167: caload
    //   168: swap
    //   169: iload #6
    //   171: bipush #7
    //   173: irem
    //   174: tableswitch default -> 241, 0 -> 212, 1 -> 217, 2 -> 222, 3 -> 226, 4 -> 231, 5 -> 236
    //   212: bipush #66
    //   214: goto -> 243
    //   217: bipush #30
    //   219: goto -> 243
    //   222: iconst_1
    //   223: goto -> 243
    //   226: bipush #74
    //   228: goto -> 243
    //   231: bipush #105
    //   233: goto -> 243
    //   236: bipush #55
    //   238: goto -> 243
    //   241: bipush #6
    //   243: ixor
    //   244: ixor
    //   245: i2c
    //   246: castore
    //   247: iinc #6, 1
    //   250: dup
    //   251: ifne -> 259
    //   254: dup2
    //   255: dup_x1
    //   256: goto -> 166
    //   259: dup2_x1
    //   260: pop2
    //   261: dup_x2
    //   262: iload #6
    //   264: if_icmpgt -> 162
    //   267: pop
    //   268: new java/lang/String
    //   271: dup_x1
    //   272: swap
    //   273: invokespecial <init> : ([C)V
    //   276: invokevirtual intern : ()Ljava/lang/String;
    //   279: swap
    //   280: pop
    //   281: swap
    //   282: tableswitch default -> 40, 0 -> 99
    //   300: invokestatic ZN : ()I
    //   303: putstatic com/fasterxml/Zm/Zl.ZP : I
    //   306: return
  }
  
  private static Exception a(Exception paramException) {
    return paramException;
  }
  
  private static String b(int paramInt1, int paramInt2) {
    int i = (paramInt1 ^ 0xFFFF9B0B) & 0xFFFF;
    if (d[i] == null) {
      char[] arrayOfChar = c[i].toCharArray();
      switch (arrayOfChar[0] & 0xFF) {
        case 0:
        
        case 1:
        
        case 2:
        
        case 3:
        
        case 4:
        
        case 5:
        
        case 6:
        
        case 7:
        
        case 8:
        
        case 9:
        
        case 10:
        
        case 11:
        
        case 12:
        
        case 13:
        
        case 14:
        
        case 15:
        
        case 16:
        
        case 17:
        
        case 18:
        
        case 19:
        
        case 20:
        
        case 21:
        
        case 22:
        
        case 23:
        
        case 24:
        
        case 25:
        
        case 26:
        
        case 27:
        
        case 28:
        
        case 29:
        
        case 30:
        
        case 31:
        
        case 32:
        
        case 33:
        
        case 34:
        
        case 35:
        
        case 36:
        
        case 37:
        
        case 38:
        
        case 39:
        
        case 40:
        
        case 41:
        
        case 42:
        
        case 43:
        
        case 44:
        
        case 45:
        
        case 46:
        
        case 47:
        
        case 48:
        
        case 49:
        
        case 50:
        
        case 51:
        
        case 52:
        
        case 53:
        
        case 54:
        
        case 55:
        
        case 56:
        
        case 57:
        
        case 58:
        
        case 59:
        
        case 60:
        
        case 61:
        
        case 62:
        
        case 63:
        
        case 64:
        
        case 65:
        
        case 66:
        
        case 67:
        
        case 68:
        
        case 69:
        
        case 70:
        
        case 71:
        
        case 72:
        
        case 73:
        
        case 74:
        
        case 75:
        
        case 76:
        
        case 77:
        
        case 78:
        
        case 79:
        
        case 80:
        
        case 81:
        
        case 82:
        
        case 83:
        
        case 84:
        
        case 85:
        
        case 86:
        
        case 87:
        
        case 88:
        
        case 89:
        
        case 90:
        
        case 91:
        
        case 92:
        
        case 93:
        
        case 94:
        
        case 95:
        
        case 96:
        
        case 97:
        
        case 98:
        
        case 99:
        
        case 100:
        
        case 101:
        
        case 102:
        
        case 103:
        
        case 104:
        
        case 105:
        
        case 106:
        
        case 107:
        
        case 108:
        
        case 109:
        
        case 110:
        
        case 111:
        
        case 112:
        
        case 113:
        
        case 114:
        
        case 115:
        
        case 116:
        
        case 117:
        
        case 118:
        
        case 119:
        
        case 120:
        
        case 121:
        
        case 122:
        
        case 123:
        
        case 124:
        
        case 125:
        
        case 126:
        
        case 127:
        
        case 128:
        
        case 129:
        
        case 130:
        
        case 131:
        
        case 132:
        
        case 133:
        
        case 134:
        
        case 135:
        
        case 136:
        
        case 137:
        
        case 138:
        
        case 139:
        
        case 140:
        
        case 141:
        
        case 142:
        
        case 143:
        
        case 144:
        
        case 145:
        
        case 146:
        
        case 147:
        
        case 148:
        
        case 149:
        
        case 150:
        
        case 151:
        
        case 152:
        
        case 153:
        
        case 154:
        
        case 155:
        
        case 156:
        
        case 157:
        
        case 158:
        
        case 159:
        
        case 160:
        
        case 161:
        
        case 162:
        
        case 163:
        
        case 164:
        
        case 165:
        
        case 166:
        
        case 167:
        
        case 168:
        
        case 169:
        
        case 170:
        
        case 171:
        
        case 172:
        
        case 173:
        
        case 174:
        
        case 175:
        
        case 176:
        
        case 177:
        
        case 178:
        
        case 179:
        
        case 180:
        
        case 181:
        
        case 182:
        
        case 183:
        
        case 184:
        
        case 185:
        
        case 186:
        
        case 187:
        
        case 188:
        
        case 189:
        
        case 190:
        
        case 191:
        
        case 192:
        
        case 193:
        
        case 194:
        
        case 195:
        
        case 196:
        
        case 197:
        
        case 198:
        
        case 199:
        
        case 200:
        
        case 201:
        
        case 202:
        
        case 203:
        
        case 204:
        
        case 205:
        
        case 206:
        
        case 207:
        
        case 208:
        
        case 209:
        
        case 210:
        
        case 211:
        
        case 212:
        
        case 213:
        
        case 214:
        
        case 215:
        
        case 216:
        
        case 217:
        
        case 218:
        
        case 219:
        
        case 220:
        
        case 221:
        
        case 222:
        
        case 223:
        
        case 224:
        
        case 225:
        
        case 226:
        
        case 227:
        
        case 228:
        
        case 229:
        
        case 230:
        
        case 231:
        
        case 232:
        
        case 233:
        
        case 234:
        
        case 235:
        
        case 236:
        
        case 237:
        
        case 238:
        
        case 239:
        
        case 240:
        
        case 241:
        
        case 242:
        
        case 243:
        
        case 244:
        
        case 245:
        
        case 246:
        
        case 247:
        
        case 248:
        
        case 249:
        
        case 250:
        
        case 251:
        
        case 252:
        
        case 253:
        
        case 254:
        
        default:
          break;
      } 
      byte b1 = 2;
      int j = (paramInt2 & 0xFF) - b1;
      if (j < 0)
        j += 256; 
      int k = ((paramInt2 & 0xFFFF) >>> 8) - b1;
      if (k < 0)
        k += 256; 
      for (byte b2 = 0; b2 < arrayOfChar.length; b2++) {
        int m = b2 % 2;
        if (m == 0) {
          arrayOfChar[b2] = (char)(arrayOfChar[b2] ^ j);
          j = ((j >>> 3 | j << 5) ^ arrayOfChar[b2]) & 0xFF;
        } else {
          arrayOfChar[b2] = (char)(arrayOfChar[b2] ^ k);
          k = ((k >>> 3 | k << 5) ^ arrayOfChar[b2]) & 0xFF;
        } 
      } 
      d[i] = (new String(arrayOfChar)).intern();
    } 
    return d[i];
  }
}


/* Location:              C:\Program Files\BurpSuitePro\burpsuite_pro.jar!\com\fasterxml\Zm\Zl.class
 * Java compiler version: 8 (52.0)
 * JD-Core Version:       1.1.3
 */