package com.fasterxml.Zoz;

import com.fasterxml.Zd.Zn;
import com.fasterxml.Zgy;
import com.fasterxml.Zj.Zf;
import com.fasterxml.Zj.Zqn;
import com.fasterxml.Zm.Zx;
import com.fasterxml.Zor.Ze;
import com.fasterxml.Zor.Zk;
import com.fasterxml.Zor.Zr;
import com.fasterxml.Zor.Zt;
import com.fasterxml.Zz6;
import java.util.ArrayList;
import java.util.Collection;
import java.util.HashSet;
import java.util.Iterator;
import java.util.LinkedHashMap;
import java.util.LinkedList;
import java.util.List;
import java.util.Map;
import java.util.Set;

public class Zh {
  protected final Zf<?> Zz;
  
  protected final Zz Zv;
  
  protected final boolean Zi;
  
  protected final Zk Zb;
  
  protected final Zia Zq;
  
  protected final Zi8<?> Z_;
  
  protected final Zt ZG;
  
  protected final boolean Zd;
  
  protected final boolean ZM;
  
  protected boolean Zr;
  
  protected LinkedHashMap<String, Zb> Zt;
  
  protected LinkedList<Zb> Zu;
  
  protected Map<Zr, Zr> Zc;
  
  protected LinkedList<Ziz> ZO;
  
  protected LinkedList<Ziz> ZC;
  
  protected LinkedList<Ziq> ZA;
  
  protected LinkedList<Ziz> Zw;
  
  protected LinkedList<Ziz> Zn;
  
  protected LinkedList<Ziz> ZE;
  
  protected HashSet<String> ZI;
  
  protected LinkedHashMap<Object, Ziz> Zj;
  
  protected Zgy ZH;
  
  @Deprecated
  protected final boolean ZS;
  
  @Deprecated
  protected String Zf;
  
  private static final String[] a;
  
  private static final String[] b;
  
  protected Zh(Zf<?> paramZf, boolean paramBoolean, Zk paramZk, Zia paramZia, Zz paramZz) {
    // Byte code:
    //   0: invokestatic Zv : ()I
    //   3: aload_0
    //   4: invokespecial <init> : ()V
    //   7: aload_0
    //   8: sipush #8401
    //   11: sipush #3044
    //   14: invokestatic a : (II)Ljava/lang/String;
    //   17: putfield Zf : Ljava/lang/String;
    //   20: istore #6
    //   22: aload_0
    //   23: aload_1
    //   24: putfield Zz : Lcom/fasterxml/Zj/Zf;
    //   27: aload_0
    //   28: iload_2
    //   29: putfield Zi : Z
    //   32: aload_0
    //   33: aload_3
    //   34: putfield Zb : Lcom/fasterxml/Zor/Zk;
    //   37: aload_0
    //   38: aload #4
    //   40: putfield Zq : Lcom/fasterxml/Zoz/Zia;
    //   43: aload_0
    //   44: aload_0
    //   45: getfield Zb : Lcom/fasterxml/Zor/Zk;
    //   48: invokevirtual Zv : ()Z
    //   51: putfield ZM : Z
    //   54: aload_1
    //   55: invokevirtual Ze : ()Z
    //   58: ifeq -> 89
    //   61: aload_0
    //   62: iconst_1
    //   63: putfield Zd : Z
    //   66: aload_0
    //   67: aload_0
    //   68: getfield Zz : Lcom/fasterxml/Zj/Zf;
    //   71: invokevirtual ZK : ()Lcom/fasterxml/Zor/Zt;
    //   74: putfield ZG : Lcom/fasterxml/Zor/Zt;
    //   77: iload #6
    //   79: ifeq -> 108
    //   82: goto -> 89
    //   85: invokestatic a : (Ljava/lang/IllegalArgumentException;)Ljava/lang/IllegalArgumentException;
    //   88: athrow
    //   89: aload_0
    //   90: iconst_0
    //   91: putfield Zd : Z
    //   94: aload_0
    //   95: invokestatic ZH : ()Lcom/fasterxml/Zor/Zt;
    //   98: putfield ZG : Lcom/fasterxml/Zor/Zt;
    //   101: goto -> 108
    //   104: invokestatic a : (Ljava/lang/IllegalArgumentException;)Ljava/lang/IllegalArgumentException;
    //   107: athrow
    //   108: aload_0
    //   109: aload_0
    //   110: getfield Zz : Lcom/fasterxml/Zj/Zf;
    //   113: aload_3
    //   114: invokevirtual Zf : ()Ljava/lang/Class;
    //   117: aload #4
    //   119: invokevirtual Zr : (Ljava/lang/Class;Lcom/fasterxml/Zoz/Zia;)Lcom/fasterxml/Zoz/Zi8;
    //   122: putfield Z_ : Lcom/fasterxml/Zoz/Zi8;
    //   125: aload_0
    //   126: aload #5
    //   128: putfield Zv : Lcom/fasterxml/Zoz/Zz;
    //   131: aload_0
    //   132: aload_1
    //   133: getstatic com/fasterxml/Zor/Zy9.USE_STD_BEAN_NAMING : Lcom/fasterxml/Zor/Zy9;
    //   136: invokevirtual ZB : (Lcom/fasterxml/Zor/Zy9;)Z
    //   139: putfield ZS : Z
    //   142: return
    // Exception table:
    //   from	to	target	type
    //   22	82	85	java/lang/IllegalArgumentException
    //   61	101	104	java/lang/IllegalArgumentException
  }
  
  public Zf<?> Z_() {
    return this.Zz;
  }
  
  public Zk ZF() {
    return this.Zb;
  }
  
  public boolean ZT() {
    return this.ZM;
  }
  
  public Zia ZH() {
    return this.Zq;
  }
  
  public List<Zp> Zt() {
    Map<String, Zb> map = Zi();
    return new ArrayList<>(map.values());
  }
  
  public Map<Object, Ziz> Zf() {
    try {
      if (!this.Zr)
        ZA(); 
    } catch (IllegalArgumentException illegalArgumentException) {
      throw a(null);
    } 
    return this.Zj;
  }
  
  public Ziz ZS() {
    try {
      if (!this.Zr)
        ZA(); 
    } catch (IllegalArgumentException illegalArgumentException) {
      throw a(null);
    } 
    try {
      if (this.Zn != null) {
        try {
          if (this.Zn.size() > 1)
            try {
              if (!Ze(this.Zn))
                Zz(a(8403, -29759), new Object[] { this.Zn.get(0), this.Zn.get(1) }); 
            } catch (IllegalArgumentException illegalArgumentException) {
              throw a(null);
            }  
        } catch (IllegalArgumentException illegalArgumentException) {
          throw a(null);
        } 
        return this.Zn.get(0);
      } 
    } catch (IllegalArgumentException illegalArgumentException) {
      throw a(null);
    } 
    return null;
  }
  
  public Ziz ZQ() {
    try {
      if (!this.Zr)
        ZA(); 
    } catch (IllegalArgumentException illegalArgumentException) {
      throw a(null);
    } 
    try {
      if (this.ZE != null) {
        try {
          if (this.ZE.size() > 1)
            try {
              if (!Ze(this.ZE))
                Zz(a(8412, 18924), new Object[] { this.ZE.get(0), this.ZE.get(1) }); 
            } catch (IllegalArgumentException illegalArgumentException) {
              throw a(null);
            }  
        } catch (IllegalArgumentException illegalArgumentException) {
          throw a(null);
        } 
        return this.ZE.get(0);
      } 
    } catch (IllegalArgumentException illegalArgumentException) {
      throw a(null);
    } 
    return null;
  }
  
  public Ziz Zu() {
    try {
      if (!this.Zr)
        ZA(); 
    } catch (IllegalArgumentException illegalArgumentException) {
      throw a(null);
    } 
    try {
      if (this.ZC != null) {
        try {
          if (this.ZC.size() > 1)
            Zz(a(8413, 18491), new Object[] { this.ZC.get(0), this.ZC.get(1) }); 
        } catch (IllegalArgumentException illegalArgumentException) {
          throw a(null);
        } 
        return this.ZC.getFirst();
      } 
    } catch (IllegalArgumentException illegalArgumentException) {
      throw a(null);
    } 
    return null;
  }
  
  public Ziz Zd() {
    try {
      if (!this.Zr)
        ZA(); 
    } catch (IllegalArgumentException illegalArgumentException) {
      throw a(null);
    } 
    try {
      if (this.ZO != null) {
        try {
          if (this.ZO.size() > 1)
            Zz(a(8408, -31297), new Object[] { this.ZO.get(0), this.ZO.get(1) }); 
        } catch (IllegalArgumentException illegalArgumentException) {
          throw a(null);
        } 
        return this.ZO.getFirst();
      } 
    } catch (IllegalArgumentException illegalArgumentException) {
      throw a(null);
    } 
    return null;
  }
  
  public Ziz ZC() {
    try {
      if (!this.Zr)
        ZA(); 
    } catch (IllegalArgumentException illegalArgumentException) {
      throw a(null);
    } 
    try {
      if (this.Zw != null) {
        try {
          if (this.Zw.size() > 1)
            Zz(a(8409, -11291), new Object[] { this.Zw.get(0), this.Zw.get(1) }); 
        } catch (IllegalArgumentException illegalArgumentException) {
          throw a(null);
        } 
        return this.Zw.getFirst();
      } 
    } catch (IllegalArgumentException illegalArgumentException) {
      throw a(null);
    } 
    return null;
  }
  
  public Ziq ZL() {
    try {
      if (!this.Zr)
        ZA(); 
    } catch (IllegalArgumentException illegalArgumentException) {
      throw a(null);
    } 
    try {
      if (this.ZA != null) {
        try {
          if (this.ZA.size() > 1)
            Zz(a(8400, -3432), new Object[] { this.ZA.get(0), this.ZA.get(1) }); 
        } catch (IllegalArgumentException illegalArgumentException) {
          throw a(null);
        } 
        return this.ZA.getFirst();
      } 
    } catch (IllegalArgumentException illegalArgumentException) {
      throw a(null);
    } 
    return null;
  }
  
  public Set<String> ZZ() {
    return this.ZI;
  }
  
  public Zv Zw() {
    Zv zv = this.ZG.Zk(this.Zq);
    if (zv != null)
      zv = this.ZG.Zq(this.Zq, zv); 
    return zv;
  }
  
  protected Map<String, Zb> Zi() {
    try {
      if (!this.Zr)
        ZA(); 
    } catch (IllegalArgumentException illegalArgumentException) {
      throw a(null);
    } 
    return this.Zt;
  }
  
  public Zgy ZU() {
    // Byte code:
    //   0: invokestatic ZM : ()I
    //   3: istore_1
    //   4: aload_0
    //   5: getfield ZH : Lcom/fasterxml/Zgy;
    //   8: ifnonnull -> 93
    //   11: aconst_null
    //   12: astore_2
    //   13: aload_0
    //   14: getfield ZG : Lcom/fasterxml/Zor/Zt;
    //   17: ifnull -> 32
    //   20: aload_0
    //   21: getfield ZG : Lcom/fasterxml/Zor/Zt;
    //   24: aload_0
    //   25: getfield Zq : Lcom/fasterxml/Zoz/Zia;
    //   28: invokevirtual ZY : (Lcom/fasterxml/Zoz/Ziv;)Lcom/fasterxml/Zgy;
    //   31: astore_2
    //   32: aload_0
    //   33: getfield Zz : Lcom/fasterxml/Zj/Zf;
    //   36: aload_0
    //   37: getfield Zb : Lcom/fasterxml/Zor/Zk;
    //   40: invokevirtual Zf : ()Ljava/lang/Class;
    //   43: invokevirtual Zy : (Ljava/lang/Class;)Lcom/fasterxml/Zgy;
    //   46: astore_3
    //   47: aload_3
    //   48: ifnull -> 74
    //   51: aload_2
    //   52: ifnonnull -> 68
    //   55: goto -> 62
    //   58: invokestatic a : (Ljava/lang/IllegalArgumentException;)Ljava/lang/IllegalArgumentException;
    //   61: athrow
    //   62: aload_3
    //   63: astore_2
    //   64: iload_1
    //   65: ifne -> 74
    //   68: aload_2
    //   69: aload_3
    //   70: invokevirtual Zx : (Lcom/fasterxml/Zgy;)Lcom/fasterxml/Zgy;
    //   73: astore_2
    //   74: aload_0
    //   75: aload_2
    //   76: ifnonnull -> 89
    //   79: invokestatic Zm : ()Lcom/fasterxml/Zgy;
    //   82: goto -> 90
    //   85: invokestatic a : (Ljava/lang/IllegalArgumentException;)Ljava/lang/IllegalArgumentException;
    //   88: athrow
    //   89: aload_2
    //   90: putfield ZH : Lcom/fasterxml/Zgy;
    //   93: aload_0
    //   94: getfield ZH : Lcom/fasterxml/Zgy;
    //   97: areturn
    // Exception table:
    //   from	to	target	type
    //   47	55	58	java/lang/IllegalArgumentException
    //   74	85	85	java/lang/IllegalArgumentException
  }
  
  protected void ZA() {
    // Byte code:
    //   0: invokestatic ZM : ()I
    //   3: new java/util/LinkedHashMap
    //   6: dup
    //   7: invokespecial <init> : ()V
    //   10: astore_2
    //   11: istore_1
    //   12: aload_0
    //   13: invokevirtual ZT : ()Z
    //   16: istore_3
    //   17: iload_3
    //   18: ifeq -> 35
    //   21: aload_0
    //   22: getfield Zi : Z
    //   25: ifeq -> 47
    //   28: goto -> 35
    //   31: invokestatic a : (Ljava/lang/IllegalArgumentException;)Ljava/lang/IllegalArgumentException;
    //   34: athrow
    //   35: aload_0
    //   36: aload_2
    //   37: invokevirtual ZP : (Ljava/util/Map;)V
    //   40: goto -> 47
    //   43: invokestatic a : (Ljava/lang/IllegalArgumentException;)Ljava/lang/IllegalArgumentException;
    //   46: athrow
    //   47: aload_0
    //   48: aload_2
    //   49: invokevirtual Zm : (Ljava/util/Map;)V
    //   52: aload_0
    //   53: getfield Zq : Lcom/fasterxml/Zoz/Zia;
    //   56: invokevirtual Zk : ()Z
    //   59: ifne -> 99
    //   62: aload_0
    //   63: getfield Zi : Z
    //   66: ifeq -> 87
    //   69: goto -> 76
    //   72: invokestatic a : (Ljava/lang/IllegalArgumentException;)Ljava/lang/IllegalArgumentException;
    //   75: athrow
    //   76: iload_3
    //   77: ifne -> 99
    //   80: goto -> 87
    //   83: invokestatic a : (Ljava/lang/IllegalArgumentException;)Ljava/lang/IllegalArgumentException;
    //   86: athrow
    //   87: aload_0
    //   88: aload_2
    //   89: invokevirtual Zb : (Ljava/util/Map;)V
    //   92: goto -> 99
    //   95: invokestatic a : (Ljava/lang/IllegalArgumentException;)Ljava/lang/IllegalArgumentException;
    //   98: athrow
    //   99: aload_0
    //   100: aload_2
    //   101: invokevirtual ZK : (Ljava/util/Map;)V
    //   104: aload_0
    //   105: aload_2
    //   106: invokevirtual ZO : (Ljava/util/Map;)V
    //   109: aload_0
    //   110: aload_2
    //   111: invokevirtual Zu : (Ljava/util/Map;)V
    //   114: aload_0
    //   115: aload_2
    //   116: invokevirtual Zc : (Ljava/util/Map;)V
    //   119: aload_2
    //   120: invokevirtual values : ()Ljava/util/Collection;
    //   123: invokeinterface iterator : ()Ljava/util/Iterator;
    //   128: astore #4
    //   130: aload #4
    //   132: invokeinterface hasNext : ()Z
    //   137: ifeq -> 172
    //   140: aload #4
    //   142: invokeinterface next : ()Ljava/lang/Object;
    //   147: checkcast com/fasterxml/Zoz/Zb
    //   150: astore #5
    //   152: aload #5
    //   154: aload_0
    //   155: getfield Zi : Z
    //   158: invokevirtual Zr : (Z)V
    //   161: iload_1
    //   162: ifne -> 130
    //   165: iconst_5
    //   166: anewarray burp/Zbqc
    //   169: invokestatic Zr : ([Lburp/Zbqc;)V
    //   172: aload_0
    //   173: invokespecial Zv : ()Lcom/fasterxml/Zor/Ze;
    //   176: astore #4
    //   178: aload #4
    //   180: ifnull -> 197
    //   183: aload_0
    //   184: aload_2
    //   185: aload #4
    //   187: invokevirtual Zt : (Ljava/util/Map;Lcom/fasterxml/Zor/Ze;)V
    //   190: goto -> 197
    //   193: invokestatic a : (Ljava/lang/IllegalArgumentException;)Ljava/lang/IllegalArgumentException;
    //   196: athrow
    //   197: aload_2
    //   198: invokevirtual values : ()Ljava/util/Collection;
    //   201: invokeinterface iterator : ()Ljava/util/Iterator;
    //   206: astore #5
    //   208: aload #5
    //   210: invokeinterface hasNext : ()Z
    //   215: ifeq -> 239
    //   218: aload #5
    //   220: invokeinterface next : ()Ljava/lang/Object;
    //   225: checkcast com/fasterxml/Zoz/Zb
    //   228: astore #6
    //   230: aload #6
    //   232: invokevirtual Zm : ()V
    //   235: iload_1
    //   236: ifne -> 208
    //   239: aload_0
    //   240: getfield Zz : Lcom/fasterxml/Zj/Zf;
    //   243: getstatic com/fasterxml/Zor/Zy9.USE_WRAPPER_NAME_AS_PROPERTY_NAME : Lcom/fasterxml/Zor/Zy9;
    //   246: invokevirtual ZB : (Lcom/fasterxml/Zor/Zy9;)Z
    //   249: ifeq -> 264
    //   252: aload_0
    //   253: aload_2
    //   254: invokevirtual Zk : (Ljava/util/Map;)V
    //   257: goto -> 264
    //   260: invokestatic a : (Ljava/lang/IllegalArgumentException;)Ljava/lang/IllegalArgumentException;
    //   263: athrow
    //   264: aload_0
    //   265: aload_2
    //   266: invokevirtual Zh : (Ljava/util/Map;)V
    //   269: aload_0
    //   270: aload_2
    //   271: putfield Zt : Ljava/util/LinkedHashMap;
    //   274: aload_0
    //   275: iconst_1
    //   276: putfield Zr : Z
    //   279: return
    // Exception table:
    //   from	to	target	type
    //   17	28	31	java/lang/IllegalArgumentException
    //   21	40	43	java/lang/IllegalArgumentException
    //   47	69	72	java/lang/IllegalArgumentException
    //   62	80	83	java/lang/IllegalArgumentException
    //   76	92	95	java/lang/IllegalArgumentException
    //   178	190	193	java/lang/IllegalArgumentException
    //   239	257	260	java/lang/IllegalArgumentException
  }
  
  protected void ZP(Map<String, Zb> paramMap) {
    // Byte code:
    //   0: invokestatic ZM : ()I
    //   3: aload_0
    //   4: getfield ZG : Lcom/fasterxml/Zor/Zt;
    //   7: astore_3
    //   8: istore_2
    //   9: aload_0
    //   10: getfield Zi : Z
    //   13: ifne -> 44
    //   16: aload_0
    //   17: getfield Zz : Lcom/fasterxml/Zj/Zf;
    //   20: getstatic com/fasterxml/Zor/Zy9.ALLOW_FINAL_FIELDS_AS_MUTATORS : Lcom/fasterxml/Zor/Zy9;
    //   23: invokevirtual ZB : (Lcom/fasterxml/Zor/Zy9;)Z
    //   26: ifne -> 44
    //   29: goto -> 36
    //   32: invokestatic a : (Ljava/lang/IllegalArgumentException;)Ljava/lang/IllegalArgumentException;
    //   35: athrow
    //   36: iconst_1
    //   37: goto -> 45
    //   40: invokestatic a : (Ljava/lang/IllegalArgumentException;)Ljava/lang/IllegalArgumentException;
    //   43: athrow
    //   44: iconst_0
    //   45: istore #4
    //   47: aload_0
    //   48: getfield Zz : Lcom/fasterxml/Zj/Zf;
    //   51: getstatic com/fasterxml/Zor/Zy9.PROPAGATE_TRANSIENT_MARKER : Lcom/fasterxml/Zor/Zy9;
    //   54: invokevirtual ZB : (Lcom/fasterxml/Zor/Zy9;)Z
    //   57: istore #5
    //   59: aload_0
    //   60: getfield Zq : Lcom/fasterxml/Zoz/Zia;
    //   63: invokevirtual ZS : ()Ljava/lang/Iterable;
    //   66: invokeinterface iterator : ()Ljava/util/Iterator;
    //   71: astore #6
    //   73: aload #6
    //   75: invokeinterface hasNext : ()Z
    //   80: ifeq -> 763
    //   83: aload #6
    //   85: invokeinterface next : ()Ljava/lang/Object;
    //   90: checkcast com/fasterxml/Zoz/Zi6
    //   93: astore #7
    //   95: getstatic java/lang/Boolean.TRUE : Ljava/lang/Boolean;
    //   98: aload_3
    //   99: aload_0
    //   100: getfield Zz : Lcom/fasterxml/Zj/Zf;
    //   103: aload #7
    //   105: invokevirtual Zq : (Lcom/fasterxml/Zj/Zf;Lcom/fasterxml/Zoz/Ziv;)Ljava/lang/Boolean;
    //   108: invokevirtual equals : (Ljava/lang/Object;)Z
    //   111: ifeq -> 156
    //   114: aload_0
    //   115: getfield Zn : Ljava/util/LinkedList;
    //   118: ifnonnull -> 146
    //   121: goto -> 128
    //   124: invokestatic a : (Ljava/lang/IllegalArgumentException;)Ljava/lang/IllegalArgumentException;
    //   127: athrow
    //   128: aload_0
    //   129: new java/util/LinkedList
    //   132: dup
    //   133: invokespecial <init> : ()V
    //   136: putfield Zn : Ljava/util/LinkedList;
    //   139: goto -> 146
    //   142: invokestatic a : (Ljava/lang/IllegalArgumentException;)Ljava/lang/IllegalArgumentException;
    //   145: athrow
    //   146: aload_0
    //   147: getfield Zn : Ljava/util/LinkedList;
    //   150: aload #7
    //   152: invokevirtual add : (Ljava/lang/Object;)Z
    //   155: pop
    //   156: getstatic java/lang/Boolean.TRUE : Ljava/lang/Boolean;
    //   159: aload_3
    //   160: aload #7
    //   162: invokevirtual ZB : (Lcom/fasterxml/Zoz/Ziv;)Ljava/lang/Boolean;
    //   165: invokevirtual equals : (Ljava/lang/Object;)Z
    //   168: ifeq -> 217
    //   171: aload_0
    //   172: getfield ZE : Ljava/util/LinkedList;
    //   175: ifnonnull -> 203
    //   178: goto -> 185
    //   181: invokestatic a : (Ljava/lang/IllegalArgumentException;)Ljava/lang/IllegalArgumentException;
    //   184: athrow
    //   185: aload_0
    //   186: new java/util/LinkedList
    //   189: dup
    //   190: invokespecial <init> : ()V
    //   193: putfield ZE : Ljava/util/LinkedList;
    //   196: goto -> 203
    //   199: invokestatic a : (Ljava/lang/IllegalArgumentException;)Ljava/lang/IllegalArgumentException;
    //   202: athrow
    //   203: aload_0
    //   204: getfield ZE : Ljava/util/LinkedList;
    //   207: aload #7
    //   209: invokevirtual add : (Ljava/lang/Object;)Z
    //   212: pop
    //   213: iload_2
    //   214: ifne -> 73
    //   217: getstatic java/lang/Boolean.TRUE : Ljava/lang/Boolean;
    //   220: aload_3
    //   221: aload #7
    //   223: invokevirtual Zr : (Lcom/fasterxml/Zoz/Ziv;)Ljava/lang/Boolean;
    //   226: invokevirtual equals : (Ljava/lang/Object;)Z
    //   229: istore #8
    //   231: getstatic java/lang/Boolean.TRUE : Ljava/lang/Boolean;
    //   234: aload_3
    //   235: aload #7
    //   237: invokevirtual ZF : (Lcom/fasterxml/Zoz/Ziv;)Ljava/lang/Boolean;
    //   240: invokevirtual equals : (Ljava/lang/Object;)Z
    //   243: istore #9
    //   245: iload #8
    //   247: ifne -> 262
    //   250: iload #9
    //   252: ifeq -> 360
    //   255: goto -> 262
    //   258: invokestatic a : (Ljava/lang/IllegalArgumentException;)Ljava/lang/IllegalArgumentException;
    //   261: athrow
    //   262: iload #8
    //   264: ifeq -> 316
    //   267: goto -> 274
    //   270: invokestatic a : (Ljava/lang/IllegalArgumentException;)Ljava/lang/IllegalArgumentException;
    //   273: athrow
    //   274: aload_0
    //   275: getfield ZC : Ljava/util/LinkedList;
    //   278: ifnonnull -> 306
    //   281: goto -> 288
    //   284: invokestatic a : (Ljava/lang/IllegalArgumentException;)Ljava/lang/IllegalArgumentException;
    //   287: athrow
    //   288: aload_0
    //   289: new java/util/LinkedList
    //   292: dup
    //   293: invokespecial <init> : ()V
    //   296: putfield ZC : Ljava/util/LinkedList;
    //   299: goto -> 306
    //   302: invokestatic a : (Ljava/lang/IllegalArgumentException;)Ljava/lang/IllegalArgumentException;
    //   305: athrow
    //   306: aload_0
    //   307: getfield ZC : Ljava/util/LinkedList;
    //   310: aload #7
    //   312: invokevirtual add : (Ljava/lang/Object;)Z
    //   315: pop
    //   316: iload #9
    //   318: ifeq -> 73
    //   321: aload_0
    //   322: getfield Zw : Ljava/util/LinkedList;
    //   325: ifnonnull -> 346
    //   328: aload_0
    //   329: new java/util/LinkedList
    //   332: dup
    //   333: invokespecial <init> : ()V
    //   336: putfield Zw : Ljava/util/LinkedList;
    //   339: goto -> 346
    //   342: invokestatic a : (Ljava/lang/IllegalArgumentException;)Ljava/lang/IllegalArgumentException;
    //   345: athrow
    //   346: aload_0
    //   347: getfield Zw : Ljava/util/LinkedList;
    //   350: aload #7
    //   352: invokevirtual add : (Ljava/lang/Object;)Z
    //   355: pop
    //   356: iload_2
    //   357: ifne -> 73
    //   360: aload_3
    //   361: aload #7
    //   363: invokevirtual ZW : (Lcom/fasterxml/Zoz/Ziz;)Ljava/lang/String;
    //   366: astore #10
    //   368: aload #10
    //   370: ifnonnull -> 380
    //   373: aload #7
    //   375: invokevirtual ZW : ()Ljava/lang/String;
    //   378: astore #10
    //   380: aload_0
    //   381: getfield Zv : Lcom/fasterxml/Zoz/Zz;
    //   384: aload #7
    //   386: aload #10
    //   388: invokevirtual ZJ : (Lcom/fasterxml/Zoz/Zi6;Ljava/lang/String;)Ljava/lang/String;
    //   391: astore #10
    //   393: aload #10
    //   395: ifnonnull -> 409
    //   398: iload_2
    //   399: ifne -> 73
    //   402: goto -> 409
    //   405: invokestatic a : (Ljava/lang/IllegalArgumentException;)Ljava/lang/IllegalArgumentException;
    //   408: athrow
    //   409: aload_0
    //   410: aload #10
    //   412: invokespecial ZX : (Ljava/lang/String;)Lcom/fasterxml/Zor/Zr;
    //   415: astore #11
    //   417: aload_3
    //   418: aload_0
    //   419: getfield Zz : Lcom/fasterxml/Zj/Zf;
    //   422: aload #7
    //   424: aload #11
    //   426: invokevirtual ZM : (Lcom/fasterxml/Zj/Zf;Lcom/fasterxml/Zoz/Zi6;Lcom/fasterxml/Zor/Zr;)Lcom/fasterxml/Zor/Zr;
    //   429: astore #12
    //   431: aload #12
    //   433: ifnull -> 499
    //   436: aload #12
    //   438: aload #11
    //   440: invokevirtual equals : (Ljava/lang/Object;)Z
    //   443: ifne -> 499
    //   446: goto -> 453
    //   449: invokestatic a : (Ljava/lang/IllegalArgumentException;)Ljava/lang/IllegalArgumentException;
    //   452: athrow
    //   453: aload_0
    //   454: getfield Zc : Ljava/util/Map;
    //   457: ifnonnull -> 485
    //   460: goto -> 467
    //   463: invokestatic a : (Ljava/lang/IllegalArgumentException;)Ljava/lang/IllegalArgumentException;
    //   466: athrow
    //   467: aload_0
    //   468: new java/util/HashMap
    //   471: dup
    //   472: invokespecial <init> : ()V
    //   475: putfield Zc : Ljava/util/Map;
    //   478: goto -> 485
    //   481: invokestatic a : (Ljava/lang/IllegalArgumentException;)Ljava/lang/IllegalArgumentException;
    //   484: athrow
    //   485: aload_0
    //   486: getfield Zc : Ljava/util/Map;
    //   489: aload #12
    //   491: aload #11
    //   493: invokeinterface put : (Ljava/lang/Object;Ljava/lang/Object;)Ljava/lang/Object;
    //   498: pop
    //   499: aload_0
    //   500: getfield Zi : Z
    //   503: ifeq -> 518
    //   506: aload_3
    //   507: aload #7
    //   509: invokevirtual ZR : (Lcom/fasterxml/Zoz/Ziv;)Lcom/fasterxml/Zor/Zr;
    //   512: astore #13
    //   514: iload_2
    //   515: ifne -> 526
    //   518: aload_3
    //   519: aload #7
    //   521: invokevirtual ZK : (Lcom/fasterxml/Zoz/Ziv;)Lcom/fasterxml/Zor/Zr;
    //   524: astore #13
    //   526: aload #13
    //   528: ifnull -> 539
    //   531: iconst_1
    //   532: goto -> 540
    //   535: invokestatic a : (Ljava/lang/IllegalArgumentException;)Ljava/lang/IllegalArgumentException;
    //   538: athrow
    //   539: iconst_0
    //   540: istore #14
    //   542: iload #14
    //   544: istore #15
    //   546: iload #15
    //   548: ifeq -> 577
    //   551: aload #13
    //   553: invokevirtual Zf : ()Z
    //   556: ifeq -> 577
    //   559: goto -> 566
    //   562: invokestatic a : (Ljava/lang/IllegalArgumentException;)Ljava/lang/IllegalArgumentException;
    //   565: athrow
    //   566: aload_0
    //   567: aload #10
    //   569: invokespecial ZX : (Ljava/lang/String;)Lcom/fasterxml/Zor/Zr;
    //   572: astore #13
    //   574: iconst_0
    //   575: istore #15
    //   577: aload #13
    //   579: ifnull -> 590
    //   582: iconst_1
    //   583: goto -> 591
    //   586: invokestatic a : (Ljava/lang/IllegalArgumentException;)Ljava/lang/IllegalArgumentException;
    //   589: athrow
    //   590: iconst_0
    //   591: istore #16
    //   593: iload #16
    //   595: ifne -> 611
    //   598: aload_0
    //   599: getfield Z_ : Lcom/fasterxml/Zoz/Zi8;
    //   602: aload #7
    //   604: invokeinterface Zc : (Lcom/fasterxml/Zoz/Zi6;)Z
    //   609: istore #16
    //   611: aload_3
    //   612: aload #7
    //   614: invokevirtual ZV : (Lcom/fasterxml/Zoz/Ziz;)Z
    //   617: istore #17
    //   619: aload #7
    //   621: invokevirtual ZD : ()Z
    //   624: ifeq -> 681
    //   627: iload #14
    //   629: ifne -> 681
    //   632: goto -> 639
    //   635: invokestatic a : (Ljava/lang/IllegalArgumentException;)Ljava/lang/IllegalArgumentException;
    //   638: athrow
    //   639: iload #5
    //   641: ifeq -> 658
    //   644: goto -> 651
    //   647: invokestatic a : (Ljava/lang/IllegalArgumentException;)Ljava/lang/IllegalArgumentException;
    //   650: athrow
    //   651: iconst_1
    //   652: istore #17
    //   654: iload_2
    //   655: ifne -> 681
    //   658: iload #17
    //   660: ifne -> 681
    //   663: goto -> 670
    //   666: invokestatic a : (Ljava/lang/IllegalArgumentException;)Ljava/lang/IllegalArgumentException;
    //   669: athrow
    //   670: iload_2
    //   671: ifne -> 73
    //   674: goto -> 681
    //   677: invokestatic a : (Ljava/lang/IllegalArgumentException;)Ljava/lang/IllegalArgumentException;
    //   680: athrow
    //   681: iload #4
    //   683: ifeq -> 739
    //   686: aload #13
    //   688: ifnonnull -> 739
    //   691: goto -> 698
    //   694: invokestatic a : (Ljava/lang/IllegalArgumentException;)Ljava/lang/IllegalArgumentException;
    //   697: athrow
    //   698: iload #17
    //   700: ifne -> 739
    //   703: goto -> 710
    //   706: invokestatic a : (Ljava/lang/IllegalArgumentException;)Ljava/lang/IllegalArgumentException;
    //   709: athrow
    //   710: aload #7
    //   712: invokevirtual ZO : ()I
    //   715: invokestatic isFinal : (I)Z
    //   718: ifeq -> 739
    //   721: goto -> 728
    //   724: invokestatic a : (Ljava/lang/IllegalArgumentException;)Ljava/lang/IllegalArgumentException;
    //   727: athrow
    //   728: iload_2
    //   729: ifne -> 73
    //   732: goto -> 739
    //   735: invokestatic a : (Ljava/lang/IllegalArgumentException;)Ljava/lang/IllegalArgumentException;
    //   738: athrow
    //   739: aload_0
    //   740: aload_1
    //   741: aload #10
    //   743: invokevirtual ZX : (Ljava/util/Map;Ljava/lang/String;)Lcom/fasterxml/Zoz/Zb;
    //   746: aload #7
    //   748: aload #13
    //   750: iload #15
    //   752: iload #16
    //   754: iload #17
    //   756: invokevirtual Zq : (Lcom/fasterxml/Zoz/Zi6;Lcom/fasterxml/Zor/Zr;ZZZ)V
    //   759: iload_2
    //   760: ifne -> 73
    //   763: return
    // Exception table:
    //   from	to	target	type
    //   9	29	32	java/lang/IllegalArgumentException
    //   16	40	40	java/lang/IllegalArgumentException
    //   95	121	124	java/lang/IllegalArgumentException
    //   114	139	142	java/lang/IllegalArgumentException
    //   156	178	181	java/lang/IllegalArgumentException
    //   171	196	199	java/lang/IllegalArgumentException
    //   245	255	258	java/lang/IllegalArgumentException
    //   250	267	270	java/lang/IllegalArgumentException
    //   262	281	284	java/lang/IllegalArgumentException
    //   274	299	302	java/lang/IllegalArgumentException
    //   321	339	342	java/lang/IllegalArgumentException
    //   393	402	405	java/lang/IllegalArgumentException
    //   431	446	449	java/lang/IllegalArgumentException
    //   436	460	463	java/lang/IllegalArgumentException
    //   453	478	481	java/lang/IllegalArgumentException
    //   526	535	535	java/lang/IllegalArgumentException
    //   546	559	562	java/lang/IllegalArgumentException
    //   577	586	586	java/lang/IllegalArgumentException
    //   619	632	635	java/lang/IllegalArgumentException
    //   627	644	647	java/lang/IllegalArgumentException
    //   654	663	666	java/lang/IllegalArgumentException
    //   658	674	677	java/lang/IllegalArgumentException
    //   681	691	694	java/lang/IllegalArgumentException
    //   686	703	706	java/lang/IllegalArgumentException
    //   698	721	724	java/lang/IllegalArgumentException
    //   710	732	735	java/lang/IllegalArgumentException
  }
  
  protected void Zb(Map<String, Zb> paramMap) {
    int i = Ziv.ZM();
    if (this.Zd) {
      for (Zik zik : this.Zq.Zx()) {
        try {
          if (this.Zu == null)
            this.Zu = new LinkedList<>(); 
        } catch (IllegalArgumentException illegalArgumentException) {
          throw a(null);
        } 
        byte b = 0;
        int j = zik.ZL();
        while (b < j) {
          ZO(paramMap, zik.Zz(b));
          b++;
          if (i == 0)
            break; 
        } 
        if (i == 0)
          break; 
      } 
      for (Ziq ziq : this.Zq.Zj()) {
        try {
          if (this.Zu == null)
            this.Zu = new LinkedList<>(); 
        } catch (IllegalArgumentException illegalArgumentException) {
          throw a(null);
        } 
        byte b = 0;
        int j = ziq.ZL();
        while (b < j) {
          ZO(paramMap, ziq.Zz(b));
          b++;
          if (i == 0)
            break; 
        } 
        if (i == 0)
          break; 
      } 
    } 
    if (ZT()) {
      ArrayList<String> arrayList = new ArrayList();
      Zik zik = Zn.ZK(this.Zq, this.ZG, this.Zz, arrayList);
      try {
        if (zik != null) {
          try {
            if (this.Zu == null)
              this.Zu = new LinkedList<>(); 
          } catch (IllegalArgumentException illegalArgumentException) {
            throw a(null);
          } 
          HashSet<Zin> hashSet = new HashSet();
          for (Zb zb : this.Zu) {
            Iterator<Zin> iterator = zb.Zk();
            while (iterator.hasNext()) {
              Zin zin = iterator.next();
              try {
                if (zin.Zd().equals(zik))
                  hashSet.add(zin); 
              } catch (IllegalArgumentException illegalArgumentException) {
                throw a(null);
              } 
              if (i == 0)
                break; 
            } 
            if (i == 0)
              break; 
          } 
          try {
            if (this.Zu.isEmpty() || !hashSet.isEmpty()) {
              byte b = 0;
              while (b < zik.ZL()) {
                Zin zin = zik.Zz(b);
                try {
                  if (!hashSet.contains(zin))
                    Zv(paramMap, zin, arrayList.get(b)); 
                } catch (IllegalArgumentException illegalArgumentException) {
                  throw a(null);
                } 
                b++;
                if (i == 0)
                  break; 
              } 
            } 
          } catch (IllegalArgumentException illegalArgumentException) {
            throw a(null);
          } 
        } 
      } catch (IllegalArgumentException illegalArgumentException) {
        throw a(null);
      } 
    } 
  }
  
  protected void ZO(Map<String, Zb> paramMap, Zin paramZin) {
    Zv(paramMap, paramZin, null);
  }
  
  private void Zv(Map<String, Zb> paramMap, Zin paramZin, String paramString) {
    // Byte code:
    //   0: invokestatic ZM : ()I
    //   3: istore #4
    //   5: aload_3
    //   6: ifnull -> 17
    //   9: aload_3
    //   10: astore #5
    //   12: iload #4
    //   14: ifne -> 36
    //   17: aload_0
    //   18: getfield ZG : Lcom/fasterxml/Zor/Zt;
    //   21: aload_2
    //   22: invokevirtual ZW : (Lcom/fasterxml/Zoz/Ziz;)Ljava/lang/String;
    //   25: astore #5
    //   27: aload #5
    //   29: ifnonnull -> 36
    //   32: ldc ''
    //   34: astore #5
    //   36: aload_0
    //   37: getfield ZG : Lcom/fasterxml/Zor/Zt;
    //   40: aload_2
    //   41: invokevirtual ZK : (Lcom/fasterxml/Zoz/Ziv;)Lcom/fasterxml/Zor/Zr;
    //   44: astore #6
    //   46: aload #6
    //   48: ifnull -> 74
    //   51: aload #6
    //   53: invokevirtual Zf : ()Z
    //   56: ifne -> 74
    //   59: goto -> 66
    //   62: invokestatic a : (Ljava/lang/IllegalArgumentException;)Ljava/lang/IllegalArgumentException;
    //   65: athrow
    //   66: iconst_1
    //   67: goto -> 75
    //   70: invokestatic a : (Ljava/lang/IllegalArgumentException;)Ljava/lang/IllegalArgumentException;
    //   73: athrow
    //   74: iconst_0
    //   75: istore #7
    //   77: iload #7
    //   79: ifne -> 193
    //   82: aload #5
    //   84: invokevirtual isEmpty : ()Z
    //   87: ifeq -> 102
    //   90: goto -> 97
    //   93: invokestatic a : (Ljava/lang/IllegalArgumentException;)Ljava/lang/IllegalArgumentException;
    //   96: athrow
    //   97: return
    //   98: invokestatic a : (Ljava/lang/IllegalArgumentException;)Ljava/lang/IllegalArgumentException;
    //   101: athrow
    //   102: aload_0
    //   103: getfield ZG : Lcom/fasterxml/Zor/Zt;
    //   106: aload_0
    //   107: getfield Zz : Lcom/fasterxml/Zj/Zf;
    //   110: aload_2
    //   111: invokevirtual Zd : ()Lcom/fasterxml/Zoz/Zif;
    //   114: invokevirtual ZD : (Lcom/fasterxml/Zj/Zf;Lcom/fasterxml/Zoz/Ziv;)Lcom/fasterxml/Zgd;
    //   117: astore #8
    //   119: aload_3
    //   120: ifnull -> 131
    //   123: iconst_1
    //   124: goto -> 132
    //   127: invokestatic a : (Ljava/lang/IllegalArgumentException;)Ljava/lang/IllegalArgumentException;
    //   130: athrow
    //   131: iconst_0
    //   132: istore #9
    //   134: aload #8
    //   136: ifnull -> 169
    //   139: aload #8
    //   141: getstatic com/fasterxml/Zgd.DISABLED : Lcom/fasterxml/Zgd;
    //   144: if_acmpeq -> 169
    //   147: goto -> 154
    //   150: invokestatic a : (Ljava/lang/IllegalArgumentException;)Ljava/lang/IllegalArgumentException;
    //   153: athrow
    //   154: aload #8
    //   156: getstatic com/fasterxml/Zgd.DELEGATING : Lcom/fasterxml/Zgd;
    //   159: if_acmpne -> 186
    //   162: goto -> 169
    //   165: invokestatic a : (Ljava/lang/IllegalArgumentException;)Ljava/lang/IllegalArgumentException;
    //   168: athrow
    //   169: iload #9
    //   171: ifne -> 186
    //   174: goto -> 181
    //   177: invokestatic a : (Ljava/lang/IllegalArgumentException;)Ljava/lang/IllegalArgumentException;
    //   180: athrow
    //   181: return
    //   182: invokestatic a : (Ljava/lang/IllegalArgumentException;)Ljava/lang/IllegalArgumentException;
    //   185: athrow
    //   186: aload #5
    //   188: invokestatic Zf : (Ljava/lang/String;)Lcom/fasterxml/Zor/Zr;
    //   191: astore #6
    //   193: aload_0
    //   194: aload #5
    //   196: invokespecial Z_ : (Ljava/lang/String;)Ljava/lang/String;
    //   199: astore #5
    //   201: iload #7
    //   203: ifeq -> 235
    //   206: aload #5
    //   208: invokevirtual isEmpty : ()Z
    //   211: ifeq -> 235
    //   214: goto -> 221
    //   217: invokestatic a : (Ljava/lang/IllegalArgumentException;)Ljava/lang/IllegalArgumentException;
    //   220: athrow
    //   221: aload_0
    //   222: aload_1
    //   223: aload #6
    //   225: invokevirtual Zo : (Ljava/util/Map;Lcom/fasterxml/Zor/Zr;)Lcom/fasterxml/Zoz/Zb;
    //   228: goto -> 242
    //   231: invokestatic a : (Ljava/lang/IllegalArgumentException;)Ljava/lang/IllegalArgumentException;
    //   234: athrow
    //   235: aload_0
    //   236: aload_1
    //   237: aload #5
    //   239: invokevirtual ZX : (Ljava/util/Map;Ljava/lang/String;)Lcom/fasterxml/Zoz/Zb;
    //   242: astore #8
    //   244: aload #8
    //   246: aload_2
    //   247: aload #6
    //   249: iload #7
    //   251: iconst_1
    //   252: iconst_0
    //   253: invokevirtual Zf : (Lcom/fasterxml/Zoz/Zin;Lcom/fasterxml/Zor/Zr;ZZZ)V
    //   256: aload_0
    //   257: getfield Zu : Ljava/util/LinkedList;
    //   260: aload #8
    //   262: invokevirtual add : (Ljava/lang/Object;)Z
    //   265: pop
    //   266: return
    // Exception table:
    //   from	to	target	type
    //   46	59	62	java/lang/IllegalArgumentException
    //   51	70	70	java/lang/IllegalArgumentException
    //   77	90	93	java/lang/IllegalArgumentException
    //   82	98	98	java/lang/IllegalArgumentException
    //   119	127	127	java/lang/IllegalArgumentException
    //   134	147	150	java/lang/IllegalArgumentException
    //   139	162	165	java/lang/IllegalArgumentException
    //   154	174	177	java/lang/IllegalArgumentException
    //   169	182	182	java/lang/IllegalArgumentException
    //   201	214	217	java/lang/IllegalArgumentException
    //   206	231	231	java/lang/IllegalArgumentException
  }
  
  protected void Zm(Map<String, Zb> paramMap) {
    // Byte code:
    //   0: invokestatic ZM : ()I
    //   3: aload_0
    //   4: getfield Zq : Lcom/fasterxml/Zoz/Zia;
    //   7: invokevirtual Zl : ()Ljava/lang/Iterable;
    //   10: invokeinterface iterator : ()Ljava/util/Iterator;
    //   15: astore_3
    //   16: istore_2
    //   17: aload_3
    //   18: invokeinterface hasNext : ()Z
    //   23: ifeq -> 190
    //   26: aload_3
    //   27: invokeinterface next : ()Ljava/lang/Object;
    //   32: checkcast com/fasterxml/Zoz/Ziq
    //   35: astore #4
    //   37: aload #4
    //   39: invokevirtual ZL : ()I
    //   42: istore #5
    //   44: iload #5
    //   46: ifne -> 71
    //   49: aload_0
    //   50: aload_1
    //   51: aload #4
    //   53: aload_0
    //   54: getfield ZG : Lcom/fasterxml/Zor/Zt;
    //   57: invokevirtual Zl : (Ljava/util/Map;Lcom/fasterxml/Zoz/Ziq;Lcom/fasterxml/Zor/Zt;)V
    //   60: iload_2
    //   61: ifne -> 186
    //   64: goto -> 71
    //   67: invokestatic a : (Ljava/lang/IllegalArgumentException;)Ljava/lang/IllegalArgumentException;
    //   70: athrow
    //   71: iload #5
    //   73: iconst_1
    //   74: if_icmpne -> 106
    //   77: goto -> 84
    //   80: invokestatic a : (Ljava/lang/IllegalArgumentException;)Ljava/lang/IllegalArgumentException;
    //   83: athrow
    //   84: aload_0
    //   85: aload_1
    //   86: aload #4
    //   88: aload_0
    //   89: getfield ZG : Lcom/fasterxml/Zor/Zt;
    //   92: invokevirtual Zc : (Ljava/util/Map;Lcom/fasterxml/Zoz/Ziq;Lcom/fasterxml/Zor/Zt;)V
    //   95: iload_2
    //   96: ifne -> 186
    //   99: goto -> 106
    //   102: invokestatic a : (Ljava/lang/IllegalArgumentException;)Ljava/lang/IllegalArgumentException;
    //   105: athrow
    //   106: iload #5
    //   108: iconst_2
    //   109: if_icmpne -> 186
    //   112: goto -> 119
    //   115: invokestatic a : (Ljava/lang/IllegalArgumentException;)Ljava/lang/IllegalArgumentException;
    //   118: athrow
    //   119: getstatic java/lang/Boolean.TRUE : Ljava/lang/Boolean;
    //   122: aload_0
    //   123: getfield ZG : Lcom/fasterxml/Zor/Zt;
    //   126: aload #4
    //   128: invokevirtual ZF : (Lcom/fasterxml/Zoz/Ziv;)Ljava/lang/Boolean;
    //   131: invokevirtual equals : (Ljava/lang/Object;)Z
    //   134: ifeq -> 186
    //   137: goto -> 144
    //   140: invokestatic a : (Ljava/lang/IllegalArgumentException;)Ljava/lang/IllegalArgumentException;
    //   143: athrow
    //   144: aload_0
    //   145: getfield ZA : Ljava/util/LinkedList;
    //   148: ifnonnull -> 176
    //   151: goto -> 158
    //   154: invokestatic a : (Ljava/lang/IllegalArgumentException;)Ljava/lang/IllegalArgumentException;
    //   157: athrow
    //   158: aload_0
    //   159: new java/util/LinkedList
    //   162: dup
    //   163: invokespecial <init> : ()V
    //   166: putfield ZA : Ljava/util/LinkedList;
    //   169: goto -> 176
    //   172: invokestatic a : (Ljava/lang/IllegalArgumentException;)Ljava/lang/IllegalArgumentException;
    //   175: athrow
    //   176: aload_0
    //   177: getfield ZA : Ljava/util/LinkedList;
    //   180: aload #4
    //   182: invokevirtual add : (Ljava/lang/Object;)Z
    //   185: pop
    //   186: iload_2
    //   187: ifne -> 17
    //   190: return
    // Exception table:
    //   from	to	target	type
    //   44	64	67	java/lang/IllegalArgumentException
    //   49	77	80	java/lang/IllegalArgumentException
    //   71	99	102	java/lang/IllegalArgumentException
    //   84	112	115	java/lang/IllegalArgumentException
    //   106	137	140	java/lang/IllegalArgumentException
    //   119	151	154	java/lang/IllegalArgumentException
    //   144	169	172	java/lang/IllegalArgumentException
  }
  
  protected void Zl(Map<String, Zb> paramMap, Ziq paramZiq, Zt paramZt) {
    // Byte code:
    //   0: invokestatic ZM : ()I
    //   3: aload_2
    //   4: invokevirtual Zy : ()Ljava/lang/Class;
    //   7: astore #5
    //   9: istore #4
    //   11: aload #5
    //   13: getstatic java/lang/Void.TYPE : Ljava/lang/Class;
    //   16: if_acmpeq -> 53
    //   19: aload #5
    //   21: ldc java/lang/Void
    //   23: if_acmpne -> 58
    //   26: goto -> 33
    //   29: invokestatic a : (Ljava/lang/IllegalArgumentException;)Ljava/lang/IllegalArgumentException;
    //   32: athrow
    //   33: aload_0
    //   34: getfield Zz : Lcom/fasterxml/Zj/Zf;
    //   37: getstatic com/fasterxml/Zor/Zy9.ALLOW_VOID_VALUED_PROPERTIES : Lcom/fasterxml/Zor/Zy9;
    //   40: invokevirtual ZB : (Lcom/fasterxml/Zor/Zy9;)Z
    //   43: ifne -> 58
    //   46: goto -> 53
    //   49: invokestatic a : (Ljava/lang/IllegalArgumentException;)Ljava/lang/IllegalArgumentException;
    //   52: athrow
    //   53: return
    //   54: invokestatic a : (Ljava/lang/IllegalArgumentException;)Ljava/lang/IllegalArgumentException;
    //   57: athrow
    //   58: getstatic java/lang/Boolean.TRUE : Ljava/lang/Boolean;
    //   61: aload_3
    //   62: aload_2
    //   63: invokevirtual Zr : (Lcom/fasterxml/Zoz/Ziv;)Ljava/lang/Boolean;
    //   66: invokevirtual equals : (Ljava/lang/Object;)Z
    //   69: ifeq -> 114
    //   72: aload_0
    //   73: getfield ZO : Ljava/util/LinkedList;
    //   76: ifnonnull -> 104
    //   79: goto -> 86
    //   82: invokestatic a : (Ljava/lang/IllegalArgumentException;)Ljava/lang/IllegalArgumentException;
    //   85: athrow
    //   86: aload_0
    //   87: new java/util/LinkedList
    //   90: dup
    //   91: invokespecial <init> : ()V
    //   94: putfield ZO : Ljava/util/LinkedList;
    //   97: goto -> 104
    //   100: invokestatic a : (Ljava/lang/IllegalArgumentException;)Ljava/lang/IllegalArgumentException;
    //   103: athrow
    //   104: aload_0
    //   105: getfield ZO : Ljava/util/LinkedList;
    //   108: aload_2
    //   109: invokevirtual add : (Ljava/lang/Object;)Z
    //   112: pop
    //   113: return
    //   114: getstatic java/lang/Boolean.TRUE : Ljava/lang/Boolean;
    //   117: aload_3
    //   118: aload_0
    //   119: getfield Zz : Lcom/fasterxml/Zj/Zf;
    //   122: aload_2
    //   123: invokevirtual Zq : (Lcom/fasterxml/Zj/Zf;Lcom/fasterxml/Zoz/Ziv;)Ljava/lang/Boolean;
    //   126: invokevirtual equals : (Ljava/lang/Object;)Z
    //   129: ifeq -> 174
    //   132: aload_0
    //   133: getfield Zn : Ljava/util/LinkedList;
    //   136: ifnonnull -> 164
    //   139: goto -> 146
    //   142: invokestatic a : (Ljava/lang/IllegalArgumentException;)Ljava/lang/IllegalArgumentException;
    //   145: athrow
    //   146: aload_0
    //   147: new java/util/LinkedList
    //   150: dup
    //   151: invokespecial <init> : ()V
    //   154: putfield Zn : Ljava/util/LinkedList;
    //   157: goto -> 164
    //   160: invokestatic a : (Ljava/lang/IllegalArgumentException;)Ljava/lang/IllegalArgumentException;
    //   163: athrow
    //   164: aload_0
    //   165: getfield Zn : Ljava/util/LinkedList;
    //   168: aload_2
    //   169: invokevirtual add : (Ljava/lang/Object;)Z
    //   172: pop
    //   173: return
    //   174: getstatic java/lang/Boolean.TRUE : Ljava/lang/Boolean;
    //   177: aload_3
    //   178: aload_2
    //   179: invokevirtual ZB : (Lcom/fasterxml/Zoz/Ziv;)Ljava/lang/Boolean;
    //   182: invokevirtual equals : (Ljava/lang/Object;)Z
    //   185: ifeq -> 230
    //   188: aload_0
    //   189: getfield ZE : Ljava/util/LinkedList;
    //   192: ifnonnull -> 220
    //   195: goto -> 202
    //   198: invokestatic a : (Ljava/lang/IllegalArgumentException;)Ljava/lang/IllegalArgumentException;
    //   201: athrow
    //   202: aload_0
    //   203: new java/util/LinkedList
    //   206: dup
    //   207: invokespecial <init> : ()V
    //   210: putfield ZE : Ljava/util/LinkedList;
    //   213: goto -> 220
    //   216: invokestatic a : (Ljava/lang/IllegalArgumentException;)Ljava/lang/IllegalArgumentException;
    //   219: athrow
    //   220: aload_0
    //   221: getfield ZE : Ljava/util/LinkedList;
    //   224: aload_2
    //   225: invokevirtual add : (Ljava/lang/Object;)Z
    //   228: pop
    //   229: return
    //   230: aload_3
    //   231: aload_2
    //   232: invokevirtual ZR : (Lcom/fasterxml/Zoz/Ziv;)Lcom/fasterxml/Zor/Zr;
    //   235: astore #7
    //   237: aload #7
    //   239: ifnull -> 250
    //   242: iconst_1
    //   243: goto -> 251
    //   246: invokestatic a : (Ljava/lang/IllegalArgumentException;)Ljava/lang/IllegalArgumentException;
    //   249: athrow
    //   250: iconst_0
    //   251: istore #8
    //   253: iload #8
    //   255: ifne -> 345
    //   258: aload_3
    //   259: aload_2
    //   260: invokevirtual ZW : (Lcom/fasterxml/Zoz/Ziz;)Ljava/lang/String;
    //   263: astore #5
    //   265: aload #5
    //   267: ifnonnull -> 284
    //   270: aload_0
    //   271: getfield Zv : Lcom/fasterxml/Zoz/Zz;
    //   274: aload_2
    //   275: aload_2
    //   276: invokevirtual ZW : ()Ljava/lang/String;
    //   279: invokevirtual Zl : (Lcom/fasterxml/Zoz/Ziq;Ljava/lang/String;)Ljava/lang/String;
    //   282: astore #5
    //   284: aload #5
    //   286: ifnonnull -> 330
    //   289: aload_0
    //   290: getfield Zv : Lcom/fasterxml/Zoz/Zz;
    //   293: aload_2
    //   294: aload_2
    //   295: invokevirtual ZW : ()Ljava/lang/String;
    //   298: invokevirtual ZM : (Lcom/fasterxml/Zoz/Ziq;Ljava/lang/String;)Ljava/lang/String;
    //   301: astore #5
    //   303: aload #5
    //   305: ifnonnull -> 313
    //   308: return
    //   309: invokestatic a : (Ljava/lang/IllegalArgumentException;)Ljava/lang/IllegalArgumentException;
    //   312: athrow
    //   313: aload_0
    //   314: getfield Z_ : Lcom/fasterxml/Zoz/Zi8;
    //   317: aload_2
    //   318: invokeinterface ZN : (Lcom/fasterxml/Zoz/Ziq;)Z
    //   323: istore #6
    //   325: iload #4
    //   327: ifne -> 423
    //   330: aload_0
    //   331: getfield Z_ : Lcom/fasterxml/Zoz/Zi8;
    //   334: aload_2
    //   335: invokeinterface Ze : (Lcom/fasterxml/Zoz/Ziq;)Z
    //   340: istore #6
    //   342: goto -> 423
    //   345: aload_3
    //   346: aload_2
    //   347: invokevirtual ZW : (Lcom/fasterxml/Zoz/Ziz;)Ljava/lang/String;
    //   350: astore #5
    //   352: aload #5
    //   354: ifnonnull -> 390
    //   357: aload_0
    //   358: getfield Zv : Lcom/fasterxml/Zoz/Zz;
    //   361: aload_2
    //   362: aload_2
    //   363: invokevirtual ZW : ()Ljava/lang/String;
    //   366: invokevirtual Zl : (Lcom/fasterxml/Zoz/Ziq;Ljava/lang/String;)Ljava/lang/String;
    //   369: astore #5
    //   371: aload #5
    //   373: ifnonnull -> 390
    //   376: aload_0
    //   377: getfield Zv : Lcom/fasterxml/Zoz/Zz;
    //   380: aload_2
    //   381: aload_2
    //   382: invokevirtual ZW : ()Ljava/lang/String;
    //   385: invokevirtual ZM : (Lcom/fasterxml/Zoz/Ziq;Ljava/lang/String;)Ljava/lang/String;
    //   388: astore #5
    //   390: aload #5
    //   392: ifnonnull -> 401
    //   395: aload_2
    //   396: invokevirtual ZW : ()Ljava/lang/String;
    //   399: astore #5
    //   401: aload #7
    //   403: invokevirtual Zf : ()Z
    //   406: ifeq -> 420
    //   409: aload_0
    //   410: aload #5
    //   412: invokespecial ZX : (Ljava/lang/String;)Lcom/fasterxml/Zor/Zr;
    //   415: astore #7
    //   417: iconst_0
    //   418: istore #8
    //   420: iconst_1
    //   421: istore #6
    //   423: aload_0
    //   424: aload #5
    //   426: invokespecial Z_ : (Ljava/lang/String;)Ljava/lang/String;
    //   429: astore #5
    //   431: aload_3
    //   432: aload_2
    //   433: invokevirtual ZV : (Lcom/fasterxml/Zoz/Ziz;)Z
    //   436: istore #9
    //   438: aload_0
    //   439: aload_1
    //   440: aload #5
    //   442: invokevirtual ZX : (Ljava/util/Map;Ljava/lang/String;)Lcom/fasterxml/Zoz/Zb;
    //   445: aload_2
    //   446: aload #7
    //   448: iload #8
    //   450: iload #6
    //   452: iload #9
    //   454: invokevirtual Zj : (Lcom/fasterxml/Zoz/Ziq;Lcom/fasterxml/Zor/Zr;ZZZ)V
    //   457: return
    // Exception table:
    //   from	to	target	type
    //   11	26	29	java/lang/IllegalArgumentException
    //   19	46	49	java/lang/IllegalArgumentException
    //   33	54	54	java/lang/IllegalArgumentException
    //   58	79	82	java/lang/IllegalArgumentException
    //   72	97	100	java/lang/IllegalArgumentException
    //   114	139	142	java/lang/IllegalArgumentException
    //   132	157	160	java/lang/IllegalArgumentException
    //   174	195	198	java/lang/IllegalArgumentException
    //   188	213	216	java/lang/IllegalArgumentException
    //   237	246	246	java/lang/IllegalArgumentException
    //   303	309	309	java/lang/IllegalArgumentException
  }
  
  protected void Zc(Map<String, Zb> paramMap, Ziq paramZiq, Zt paramZt) {
    // Byte code:
    //   0: invokestatic ZM : ()I
    //   3: aload_3
    //   4: aload_2
    //   5: invokevirtual ZK : (Lcom/fasterxml/Zoz/Ziv;)Lcom/fasterxml/Zor/Zr;
    //   8: astore #7
    //   10: istore #4
    //   12: aload #7
    //   14: ifnull -> 25
    //   17: iconst_1
    //   18: goto -> 26
    //   21: invokestatic a : (Ljava/lang/IllegalArgumentException;)Ljava/lang/IllegalArgumentException;
    //   24: athrow
    //   25: iconst_0
    //   26: istore #8
    //   28: iload #8
    //   30: ifne -> 86
    //   33: aload_3
    //   34: aload_2
    //   35: invokevirtual ZW : (Lcom/fasterxml/Zoz/Ziz;)Ljava/lang/String;
    //   38: astore #5
    //   40: aload #5
    //   42: ifnonnull -> 59
    //   45: aload_0
    //   46: getfield Zv : Lcom/fasterxml/Zoz/Zz;
    //   49: aload_2
    //   50: aload_2
    //   51: invokevirtual ZW : ()Ljava/lang/String;
    //   54: invokevirtual ZJ : (Lcom/fasterxml/Zoz/Ziq;Ljava/lang/String;)Ljava/lang/String;
    //   57: astore #5
    //   59: aload #5
    //   61: ifnonnull -> 69
    //   64: return
    //   65: invokestatic a : (Ljava/lang/IllegalArgumentException;)Ljava/lang/IllegalArgumentException;
    //   68: athrow
    //   69: aload_0
    //   70: getfield Z_ : Lcom/fasterxml/Zoz/Zi8;
    //   73: aload_2
    //   74: invokeinterface ZQ : (Lcom/fasterxml/Zoz/Ziq;)Z
    //   79: istore #6
    //   81: iload #4
    //   83: ifne -> 145
    //   86: aload_3
    //   87: aload_2
    //   88: invokevirtual ZW : (Lcom/fasterxml/Zoz/Ziz;)Ljava/lang/String;
    //   91: astore #5
    //   93: aload #5
    //   95: ifnonnull -> 112
    //   98: aload_0
    //   99: getfield Zv : Lcom/fasterxml/Zoz/Zz;
    //   102: aload_2
    //   103: aload_2
    //   104: invokevirtual ZW : ()Ljava/lang/String;
    //   107: invokevirtual ZJ : (Lcom/fasterxml/Zoz/Ziq;Ljava/lang/String;)Ljava/lang/String;
    //   110: astore #5
    //   112: aload #5
    //   114: ifnonnull -> 123
    //   117: aload_2
    //   118: invokevirtual ZW : ()Ljava/lang/String;
    //   121: astore #5
    //   123: aload #7
    //   125: invokevirtual Zf : ()Z
    //   128: ifeq -> 142
    //   131: aload_0
    //   132: aload #5
    //   134: invokespecial ZX : (Ljava/lang/String;)Lcom/fasterxml/Zor/Zr;
    //   137: astore #7
    //   139: iconst_0
    //   140: istore #8
    //   142: iconst_1
    //   143: istore #6
    //   145: aload_0
    //   146: aload #5
    //   148: invokespecial Z_ : (Ljava/lang/String;)Ljava/lang/String;
    //   151: astore #5
    //   153: aload_3
    //   154: aload_2
    //   155: invokevirtual ZV : (Lcom/fasterxml/Zoz/Ziz;)Z
    //   158: istore #9
    //   160: aload_0
    //   161: aload_1
    //   162: aload #5
    //   164: invokevirtual ZX : (Ljava/util/Map;Ljava/lang/String;)Lcom/fasterxml/Zoz/Zb;
    //   167: aload_2
    //   168: aload #7
    //   170: iload #8
    //   172: iload #6
    //   174: iload #9
    //   176: invokevirtual ZT : (Lcom/fasterxml/Zoz/Ziq;Lcom/fasterxml/Zor/Zr;ZZZ)V
    //   179: return
    // Exception table:
    //   from	to	target	type
    //   12	21	21	java/lang/IllegalArgumentException
    //   59	65	65	java/lang/IllegalArgumentException
  }
  
  protected void Zc(Map<String, Zb> paramMap) {
    null = this.Zq.ZS().iterator();
    int i = Ziv.ZM();
    while (null.hasNext()) {
      Zi6 zi6 = null.next();
      ZL(this.ZG.ZU(zi6), zi6);
      if (i == 0)
        break; 
    } 
    for (Ziq ziq : this.Zq.Zl()) {
      try {
        if (ziq.ZL() == 1 || i == 0) {
          ZL(this.ZG.ZU(ziq), ziq);
          if (i == 0)
            break; 
        } 
      } catch (IllegalArgumentException illegalArgumentException) {
        throw a(null);
      } 
    } 
  }
  
  protected void ZL(Zz6 paramZz6, Ziz paramZiz) {
    try {
      if (paramZz6 == null)
        return; 
    } catch (IllegalArgumentException illegalArgumentException) {
      throw a(null);
    } 
    Object object = paramZz6.Zf();
    try {
      if (this.Zj == null)
        this.Zj = new LinkedHashMap<>(); 
    } catch (IllegalArgumentException illegalArgumentException) {
      throw a(null);
    } 
    Ziz ziz = this.Zj.put(object, paramZiz);
    try {
      if (ziz != null)
        try {
          if (ziz.getClass() == paramZiz.getClass())
            Zz(a(8414, 6610), new Object[] { object, Zx.ZZ(object) }); 
        } catch (IllegalArgumentException illegalArgumentException) {
          throw a(null);
        }  
    } catch (IllegalArgumentException illegalArgumentException) {
      throw a(null);
    } 
  }
  
  private Zr ZX(String paramString) {
    return Zr.ZE(paramString, null);
  }
  
  private String Z_(String paramString) {
    if (this.Zc != null) {
      Zr zr = this.Zc.get(ZX(paramString));
      if (zr != null)
        return zr.Zb(); 
    } 
    return paramString;
  }
  
  protected void ZK(Map<String, Zb> paramMap) {
    // Byte code:
    //   0: invokestatic ZM : ()I
    //   3: aload_1
    //   4: invokeinterface values : ()Ljava/util/Collection;
    //   9: invokeinterface iterator : ()Ljava/util/Iterator;
    //   14: astore_3
    //   15: istore_2
    //   16: aload_3
    //   17: invokeinterface hasNext : ()Z
    //   22: ifeq -> 189
    //   25: aload_3
    //   26: invokeinterface next : ()Ljava/lang/Object;
    //   31: checkcast com/fasterxml/Zoz/Zb
    //   34: astore #4
    //   36: aload #4
    //   38: invokevirtual Za : ()Z
    //   41: ifne -> 61
    //   44: aload_3
    //   45: invokeinterface remove : ()V
    //   50: iload_2
    //   51: ifne -> 16
    //   54: goto -> 61
    //   57: invokestatic a : (Ljava/lang/IllegalArgumentException;)Ljava/lang/IllegalArgumentException;
    //   60: athrow
    //   61: aload #4
    //   63: invokevirtual ZZ : ()Z
    //   66: ifeq -> 185
    //   69: aload_0
    //   70: invokevirtual ZT : ()Z
    //   73: ifeq -> 122
    //   76: goto -> 83
    //   79: invokestatic a : (Ljava/lang/IllegalArgumentException;)Ljava/lang/IllegalArgumentException;
    //   82: athrow
    //   83: aload_0
    //   84: getfield Zi : Z
    //   87: ifne -> 122
    //   90: goto -> 97
    //   93: invokestatic a : (Ljava/lang/IllegalArgumentException;)Ljava/lang/IllegalArgumentException;
    //   96: athrow
    //   97: aload #4
    //   99: invokevirtual ZG : ()V
    //   102: aload_0
    //   103: aload #4
    //   105: invokevirtual ZT : ()Ljava/lang/String;
    //   108: invokevirtual Zg : (Ljava/lang/String;)V
    //   111: iload_2
    //   112: ifne -> 16
    //   115: goto -> 122
    //   118: invokestatic a : (Ljava/lang/IllegalArgumentException;)Ljava/lang/IllegalArgumentException;
    //   121: athrow
    //   122: aload #4
    //   124: invokevirtual ZX : ()Z
    //   127: ifne -> 156
    //   130: aload_3
    //   131: invokeinterface remove : ()V
    //   136: aload_0
    //   137: aload #4
    //   139: invokevirtual ZT : ()Ljava/lang/String;
    //   142: invokevirtual Zg : (Ljava/lang/String;)V
    //   145: iload_2
    //   146: ifne -> 16
    //   149: goto -> 156
    //   152: invokestatic a : (Ljava/lang/IllegalArgumentException;)Ljava/lang/IllegalArgumentException;
    //   155: athrow
    //   156: aload #4
    //   158: invokevirtual ZG : ()V
    //   161: aload #4
    //   163: invokevirtual Zv : ()Z
    //   166: ifne -> 185
    //   169: aload_0
    //   170: aload #4
    //   172: invokevirtual ZT : ()Ljava/lang/String;
    //   175: invokevirtual Zg : (Ljava/lang/String;)V
    //   178: goto -> 185
    //   181: invokestatic a : (Ljava/lang/IllegalArgumentException;)Ljava/lang/IllegalArgumentException;
    //   184: athrow
    //   185: iload_2
    //   186: ifne -> 16
    //   189: return
    // Exception table:
    //   from	to	target	type
    //   36	54	57	java/lang/IllegalArgumentException
    //   61	76	79	java/lang/IllegalArgumentException
    //   69	90	93	java/lang/IllegalArgumentException
    //   83	115	118	java/lang/IllegalArgumentException
    //   122	149	152	java/lang/IllegalArgumentException
    //   156	178	181	java/lang/IllegalArgumentException
  }
  
  protected void ZO(Map<String, Zb> paramMap) {
    // Byte code:
    //   0: invokestatic Zv : ()I
    //   3: istore_2
    //   4: aload_0
    //   5: invokevirtual ZT : ()Z
    //   8: ifne -> 39
    //   11: aload_0
    //   12: getfield Zz : Lcom/fasterxml/Zj/Zf;
    //   15: getstatic com/fasterxml/Zor/Zy9.INFER_PROPERTY_MUTATORS : Lcom/fasterxml/Zor/Zy9;
    //   18: invokevirtual ZB : (Lcom/fasterxml/Zor/Zy9;)Z
    //   21: ifeq -> 39
    //   24: goto -> 31
    //   27: invokestatic a : (Ljava/lang/IllegalArgumentException;)Ljava/lang/IllegalArgumentException;
    //   30: athrow
    //   31: iconst_1
    //   32: goto -> 40
    //   35: invokestatic a : (Ljava/lang/IllegalArgumentException;)Ljava/lang/IllegalArgumentException;
    //   38: athrow
    //   39: iconst_0
    //   40: istore_3
    //   41: aload_1
    //   42: invokeinterface values : ()Ljava/util/Collection;
    //   47: invokeinterface iterator : ()Ljava/util/Iterator;
    //   52: astore #4
    //   54: aload #4
    //   56: invokeinterface hasNext : ()Z
    //   61: ifeq -> 103
    //   64: aload #4
    //   66: invokeinterface next : ()Ljava/lang/Object;
    //   71: checkcast com/fasterxml/Zoz/Zb
    //   74: astore #5
    //   76: aload #5
    //   78: iload_3
    //   79: aload_0
    //   80: getfield Zi : Z
    //   83: ifeq -> 94
    //   86: aconst_null
    //   87: goto -> 95
    //   90: invokestatic a : (Ljava/lang/IllegalArgumentException;)Ljava/lang/IllegalArgumentException;
    //   93: athrow
    //   94: aload_0
    //   95: invokevirtual Za : (ZLcom/fasterxml/Zoz/Zh;)Lcom/fasterxml/Zyj;
    //   98: pop
    //   99: iload_2
    //   100: ifeq -> 54
    //   103: return
    // Exception table:
    //   from	to	target	type
    //   4	24	27	java/lang/IllegalArgumentException
    //   11	35	35	java/lang/IllegalArgumentException
    //   76	90	90	java/lang/IllegalArgumentException
  }
  
  protected void Zg(String paramString) {
    try {
      if (!this.Zi)
        try {
          if (paramString != null) {
            try {
              if (this.ZI == null)
                this.ZI = new HashSet<>(); 
            } catch (IllegalArgumentException illegalArgumentException) {
              throw a(null);
            } 
            this.ZI.add(paramString);
          } 
        } catch (IllegalArgumentException illegalArgumentException) {
          throw a(null);
        }  
    } catch (IllegalArgumentException illegalArgumentException) {
      throw a(null);
    } 
  }
  
  protected void Zu(Map<String, Zb> paramMap) {
    // Byte code:
    //   0: invokestatic ZM : ()I
    //   3: aload_1
    //   4: invokeinterface entrySet : ()Ljava/util/Set;
    //   9: invokeinterface iterator : ()Ljava/util/Iterator;
    //   14: astore_3
    //   15: aconst_null
    //   16: astore #4
    //   18: istore_2
    //   19: aload_3
    //   20: invokeinterface hasNext : ()Z
    //   25: ifeq -> 161
    //   28: aload_3
    //   29: invokeinterface next : ()Ljava/lang/Object;
    //   34: checkcast java/util/Map$Entry
    //   37: astore #5
    //   39: aload #5
    //   41: invokeinterface getValue : ()Ljava/lang/Object;
    //   46: checkcast com/fasterxml/Zoz/Zb
    //   49: astore #6
    //   51: aload #6
    //   53: invokevirtual Zo : ()Ljava/util/Set;
    //   56: astore #7
    //   58: aload #7
    //   60: invokeinterface isEmpty : ()Z
    //   65: ifeq -> 79
    //   68: iload_2
    //   69: ifne -> 19
    //   72: goto -> 79
    //   75: invokestatic a : (Ljava/lang/IllegalArgumentException;)Ljava/lang/IllegalArgumentException;
    //   78: athrow
    //   79: aload_3
    //   80: invokeinterface remove : ()V
    //   85: aload #4
    //   87: ifnonnull -> 99
    //   90: new java/util/LinkedList
    //   93: dup
    //   94: invokespecial <init> : ()V
    //   97: astore #4
    //   99: aload #7
    //   101: invokeinterface size : ()I
    //   106: iconst_1
    //   107: if_icmpne -> 144
    //   110: aload #7
    //   112: invokeinterface iterator : ()Ljava/util/Iterator;
    //   117: invokeinterface next : ()Ljava/lang/Object;
    //   122: checkcast com/fasterxml/Zor/Zr
    //   125: astore #8
    //   127: aload #4
    //   129: aload #6
    //   131: aload #8
    //   133: invokevirtual Zk : (Lcom/fasterxml/Zor/Zr;)Lcom/fasterxml/Zoz/Zb;
    //   136: invokevirtual add : (Ljava/lang/Object;)Z
    //   139: pop
    //   140: iload_2
    //   141: ifne -> 19
    //   144: aload #4
    //   146: aload #6
    //   148: aload #7
    //   150: invokevirtual Zl : (Ljava/util/Collection;)Ljava/util/Collection;
    //   153: invokevirtual addAll : (Ljava/util/Collection;)Z
    //   156: pop
    //   157: iload_2
    //   158: ifne -> 19
    //   161: aload #4
    //   163: ifnull -> 304
    //   166: aload #4
    //   168: invokevirtual iterator : ()Ljava/util/Iterator;
    //   171: astore #5
    //   173: aload #5
    //   175: invokeinterface hasNext : ()Z
    //   180: ifeq -> 304
    //   183: aload #5
    //   185: invokeinterface next : ()Ljava/lang/Object;
    //   190: checkcast com/fasterxml/Zoz/Zb
    //   193: astore #6
    //   195: aload #6
    //   197: invokevirtual ZT : ()Ljava/lang/String;
    //   200: astore #7
    //   202: aload_1
    //   203: aload #7
    //   205: invokeinterface get : (Ljava/lang/Object;)Ljava/lang/Object;
    //   210: checkcast com/fasterxml/Zoz/Zb
    //   213: astore #8
    //   215: aload #8
    //   217: ifnonnull -> 242
    //   220: aload_1
    //   221: aload #7
    //   223: aload #6
    //   225: invokeinterface put : (Ljava/lang/Object;Ljava/lang/Object;)Ljava/lang/Object;
    //   230: pop
    //   231: iload_2
    //   232: ifne -> 256
    //   235: goto -> 242
    //   238: invokestatic a : (Ljava/lang/IllegalArgumentException;)Ljava/lang/IllegalArgumentException;
    //   241: athrow
    //   242: aload #8
    //   244: aload #6
    //   246: invokevirtual ZX : (Lcom/fasterxml/Zoz/Zb;)V
    //   249: goto -> 256
    //   252: invokestatic a : (Ljava/lang/IllegalArgumentException;)Ljava/lang/IllegalArgumentException;
    //   255: athrow
    //   256: aload_0
    //   257: aload #6
    //   259: aload_0
    //   260: getfield Zu : Ljava/util/LinkedList;
    //   263: invokevirtual Zl : (Lcom/fasterxml/Zoz/Zb;Ljava/util/List;)Z
    //   266: ifeq -> 300
    //   269: aload_0
    //   270: getfield ZI : Ljava/util/HashSet;
    //   273: ifnull -> 300
    //   276: goto -> 283
    //   279: invokestatic a : (Ljava/lang/IllegalArgumentException;)Ljava/lang/IllegalArgumentException;
    //   282: athrow
    //   283: aload_0
    //   284: getfield ZI : Ljava/util/HashSet;
    //   287: aload #7
    //   289: invokevirtual remove : (Ljava/lang/Object;)Z
    //   292: pop
    //   293: goto -> 300
    //   296: invokestatic a : (Ljava/lang/IllegalArgumentException;)Ljava/lang/IllegalArgumentException;
    //   299: athrow
    //   300: iload_2
    //   301: ifne -> 173
    //   304: return
    // Exception table:
    //   from	to	target	type
    //   58	72	75	java/lang/IllegalArgumentException
    //   215	235	238	java/lang/IllegalArgumentException
    //   220	249	252	java/lang/IllegalArgumentException
    //   256	276	279	java/lang/IllegalArgumentException
    //   269	293	296	java/lang/IllegalArgumentException
  }
  
  protected void Zt(Map<String, Zb> paramMap, Ze paramZe) {
    // Byte code:
    //   0: invokestatic Zv : ()I
    //   3: istore_3
    //   4: aload_0
    //   5: getfield Zb : Lcom/fasterxml/Zor/Zk;
    //   8: invokevirtual ZF : ()Z
    //   11: ifeq -> 39
    //   14: aload_0
    //   15: invokevirtual ZU : ()Lcom/fasterxml/Zgy;
    //   18: invokevirtual ZI : ()Lcom/fasterxml/Zqi;
    //   21: getstatic com/fasterxml/Zqi.OBJECT : Lcom/fasterxml/Zqi;
    //   24: if_acmpeq -> 39
    //   27: goto -> 34
    //   30: invokestatic a : (Ljava/lang/IllegalArgumentException;)Ljava/lang/IllegalArgumentException;
    //   33: athrow
    //   34: return
    //   35: invokestatic a : (Ljava/lang/IllegalArgumentException;)Ljava/lang/IllegalArgumentException;
    //   38: athrow
    //   39: aload_1
    //   40: invokeinterface values : ()Ljava/util/Collection;
    //   45: aload_1
    //   46: invokeinterface size : ()I
    //   51: anewarray com/fasterxml/Zoz/Zb
    //   54: invokeinterface toArray : ([Ljava/lang/Object;)[Ljava/lang/Object;
    //   59: checkcast [Lcom/fasterxml/Zoz/Zb;
    //   62: astore #4
    //   64: aload_1
    //   65: invokeinterface clear : ()V
    //   70: aload #4
    //   72: astore #5
    //   74: aload #5
    //   76: arraylength
    //   77: istore #6
    //   79: iconst_0
    //   80: istore #7
    //   82: iload #7
    //   84: iload #6
    //   86: if_icmpge -> 456
    //   89: aload #5
    //   91: iload #7
    //   93: aaload
    //   94: astore #8
    //   96: aload #8
    //   98: invokevirtual ZU : ()Lcom/fasterxml/Zor/Zr;
    //   101: astore #9
    //   103: aconst_null
    //   104: astore #10
    //   106: aload #8
    //   108: invokevirtual ZF : ()Z
    //   111: ifeq -> 134
    //   114: aload_0
    //   115: getfield Zz : Lcom/fasterxml/Zj/Zf;
    //   118: getstatic com/fasterxml/Zor/Zy9.ALLOW_EXPLICIT_PROPERTY_RENAMING : Lcom/fasterxml/Zor/Zy9;
    //   121: invokevirtual ZB : (Lcom/fasterxml/Zor/Zy9;)Z
    //   124: ifeq -> 338
    //   127: goto -> 134
    //   130: invokestatic a : (Ljava/lang/IllegalArgumentException;)Ljava/lang/IllegalArgumentException;
    //   133: athrow
    //   134: aload_0
    //   135: getfield Zi : Z
    //   138: ifeq -> 217
    //   141: goto -> 148
    //   144: invokestatic a : (Ljava/lang/IllegalArgumentException;)Ljava/lang/IllegalArgumentException;
    //   147: athrow
    //   148: aload #8
    //   150: invokevirtual ZA : ()Z
    //   153: ifeq -> 186
    //   156: goto -> 163
    //   159: invokestatic a : (Ljava/lang/IllegalArgumentException;)Ljava/lang/IllegalArgumentException;
    //   162: athrow
    //   163: aload_2
    //   164: aload_0
    //   165: getfield Zz : Lcom/fasterxml/Zj/Zf;
    //   168: aload #8
    //   170: invokevirtual Zz : ()Lcom/fasterxml/Zoz/Ziq;
    //   173: aload #9
    //   175: invokevirtual Zb : ()Ljava/lang/String;
    //   178: invokevirtual ZO : (Lcom/fasterxml/Zj/Zf;Lcom/fasterxml/Zoz/Ziq;Ljava/lang/String;)Ljava/lang/String;
    //   181: astore #10
    //   183: goto -> 338
    //   186: aload #8
    //   188: invokevirtual Zy : ()Z
    //   191: ifeq -> 338
    //   194: aload_2
    //   195: aload_0
    //   196: getfield Zz : Lcom/fasterxml/Zj/Zf;
    //   199: aload #8
    //   201: invokevirtual ZY : ()Lcom/fasterxml/Zoz/Zi6;
    //   204: aload #9
    //   206: invokevirtual Zb : ()Ljava/lang/String;
    //   209: invokevirtual ZY : (Lcom/fasterxml/Zj/Zf;Lcom/fasterxml/Zoz/Zi6;Ljava/lang/String;)Ljava/lang/String;
    //   212: astore #10
    //   214: goto -> 338
    //   217: aload #8
    //   219: invokevirtual Zg : ()Z
    //   222: ifeq -> 248
    //   225: aload_2
    //   226: aload_0
    //   227: getfield Zz : Lcom/fasterxml/Zj/Zf;
    //   230: aload #8
    //   232: invokevirtual Zl : ()Lcom/fasterxml/Zoz/Ziq;
    //   235: aload #9
    //   237: invokevirtual Zb : ()Ljava/lang/String;
    //   240: invokevirtual ZG : (Lcom/fasterxml/Zj/Zf;Lcom/fasterxml/Zoz/Ziq;Ljava/lang/String;)Ljava/lang/String;
    //   243: astore #10
    //   245: goto -> 338
    //   248: aload #8
    //   250: invokevirtual Zf : ()Z
    //   253: ifeq -> 279
    //   256: aload_2
    //   257: aload_0
    //   258: getfield Zz : Lcom/fasterxml/Zj/Zf;
    //   261: aload #8
    //   263: invokevirtual ZN : ()Lcom/fasterxml/Zoz/Zin;
    //   266: aload #9
    //   268: invokevirtual Zb : ()Ljava/lang/String;
    //   271: invokevirtual Zn : (Lcom/fasterxml/Zj/Zf;Lcom/fasterxml/Zoz/Zin;Ljava/lang/String;)Ljava/lang/String;
    //   274: astore #10
    //   276: goto -> 338
    //   279: aload #8
    //   281: invokevirtual Zy : ()Z
    //   284: ifeq -> 310
    //   287: aload_2
    //   288: aload_0
    //   289: getfield Zz : Lcom/fasterxml/Zj/Zf;
    //   292: aload #8
    //   294: invokevirtual Zq : ()Lcom/fasterxml/Zoz/Zi6;
    //   297: aload #9
    //   299: invokevirtual Zb : ()Ljava/lang/String;
    //   302: invokevirtual ZY : (Lcom/fasterxml/Zj/Zf;Lcom/fasterxml/Zoz/Zi6;Ljava/lang/String;)Ljava/lang/String;
    //   305: astore #10
    //   307: goto -> 338
    //   310: aload #8
    //   312: invokevirtual ZA : ()Z
    //   315: ifeq -> 338
    //   318: aload_2
    //   319: aload_0
    //   320: getfield Zz : Lcom/fasterxml/Zj/Zf;
    //   323: aload #8
    //   325: invokevirtual Zn : ()Lcom/fasterxml/Zoz/Ziq;
    //   328: aload #9
    //   330: invokevirtual Zb : ()Ljava/lang/String;
    //   333: invokevirtual ZO : (Lcom/fasterxml/Zj/Zf;Lcom/fasterxml/Zoz/Ziq;Ljava/lang/String;)Ljava/lang/String;
    //   336: astore #10
    //   338: aload #10
    //   340: ifnull -> 377
    //   343: aload #9
    //   345: aload #10
    //   347: invokevirtual ZF : (Ljava/lang/String;)Z
    //   350: ifne -> 377
    //   353: goto -> 360
    //   356: invokestatic a : (Ljava/lang/IllegalArgumentException;)Ljava/lang/IllegalArgumentException;
    //   359: athrow
    //   360: aload #8
    //   362: aload #10
    //   364: invokevirtual Zb : (Ljava/lang/String;)Lcom/fasterxml/Zoz/Zb;
    //   367: astore #8
    //   369: aload #10
    //   371: astore #11
    //   373: iload_3
    //   374: ifeq -> 384
    //   377: aload #9
    //   379: invokevirtual Zb : ()Ljava/lang/String;
    //   382: astore #11
    //   384: aload_1
    //   385: aload #11
    //   387: invokeinterface get : (Ljava/lang/Object;)Ljava/lang/Object;
    //   392: checkcast com/fasterxml/Zoz/Zb
    //   395: astore #12
    //   397: aload #12
    //   399: ifnonnull -> 424
    //   402: aload_1
    //   403: aload #11
    //   405: aload #8
    //   407: invokeinterface put : (Ljava/lang/Object;Ljava/lang/Object;)Ljava/lang/Object;
    //   412: pop
    //   413: iload_3
    //   414: ifeq -> 438
    //   417: goto -> 424
    //   420: invokestatic a : (Ljava/lang/IllegalArgumentException;)Ljava/lang/IllegalArgumentException;
    //   423: athrow
    //   424: aload #12
    //   426: aload #8
    //   428: invokevirtual ZX : (Lcom/fasterxml/Zoz/Zb;)V
    //   431: goto -> 438
    //   434: invokestatic a : (Ljava/lang/IllegalArgumentException;)Ljava/lang/IllegalArgumentException;
    //   437: athrow
    //   438: aload_0
    //   439: aload #8
    //   441: aload_0
    //   442: getfield Zu : Ljava/util/LinkedList;
    //   445: invokevirtual Zl : (Lcom/fasterxml/Zoz/Zb;Ljava/util/List;)Z
    //   448: pop
    //   449: iinc #7, 1
    //   452: iload_3
    //   453: ifeq -> 82
    //   456: return
    // Exception table:
    //   from	to	target	type
    //   4	27	30	java/lang/IllegalArgumentException
    //   14	35	35	java/lang/IllegalArgumentException
    //   106	127	130	java/lang/IllegalArgumentException
    //   114	141	144	java/lang/IllegalArgumentException
    //   134	156	159	java/lang/IllegalArgumentException
    //   338	353	356	java/lang/IllegalArgumentException
    //   397	417	420	java/lang/IllegalArgumentException
    //   402	431	434	java/lang/IllegalArgumentException
  }
  
  protected void Zk(Map<String, Zb> paramMap) {
    // Byte code:
    //   0: invokestatic ZM : ()I
    //   3: aload_1
    //   4: invokeinterface entrySet : ()Ljava/util/Set;
    //   9: invokeinterface iterator : ()Ljava/util/Iterator;
    //   14: astore_3
    //   15: aconst_null
    //   16: astore #4
    //   18: istore_2
    //   19: aload_3
    //   20: invokeinterface hasNext : ()Z
    //   25: ifeq -> 170
    //   28: aload_3
    //   29: invokeinterface next : ()Ljava/lang/Object;
    //   34: checkcast java/util/Map$Entry
    //   37: astore #5
    //   39: aload #5
    //   41: invokeinterface getValue : ()Ljava/lang/Object;
    //   46: checkcast com/fasterxml/Zoz/Zb
    //   49: astore #6
    //   51: aload #6
    //   53: invokevirtual Zu : ()Lcom/fasterxml/Zoz/Ziz;
    //   56: astore #7
    //   58: aload #7
    //   60: ifnonnull -> 74
    //   63: iload_2
    //   64: ifne -> 19
    //   67: goto -> 74
    //   70: invokestatic a : (Ljava/lang/IllegalArgumentException;)Ljava/lang/IllegalArgumentException;
    //   73: athrow
    //   74: aload_0
    //   75: getfield ZG : Lcom/fasterxml/Zor/Zt;
    //   78: aload #7
    //   80: invokevirtual ZP : (Lcom/fasterxml/Zoz/Ziv;)Lcom/fasterxml/Zor/Zr;
    //   83: astore #8
    //   85: aload #8
    //   87: ifnull -> 19
    //   90: aload #8
    //   92: invokevirtual ZA : ()Z
    //   95: ifne -> 109
    //   98: iload_2
    //   99: ifne -> 19
    //   102: goto -> 109
    //   105: invokestatic a : (Ljava/lang/IllegalArgumentException;)Ljava/lang/IllegalArgumentException;
    //   108: athrow
    //   109: aload #8
    //   111: aload #6
    //   113: invokevirtual ZU : ()Lcom/fasterxml/Zor/Zr;
    //   116: invokevirtual equals : (Ljava/lang/Object;)Z
    //   119: ifne -> 166
    //   122: aload #4
    //   124: ifnonnull -> 143
    //   127: goto -> 134
    //   130: invokestatic a : (Ljava/lang/IllegalArgumentException;)Ljava/lang/IllegalArgumentException;
    //   133: athrow
    //   134: new java/util/LinkedList
    //   137: dup
    //   138: invokespecial <init> : ()V
    //   141: astore #4
    //   143: aload #6
    //   145: aload #8
    //   147: invokevirtual Zk : (Lcom/fasterxml/Zor/Zr;)Lcom/fasterxml/Zoz/Zb;
    //   150: astore #6
    //   152: aload #4
    //   154: aload #6
    //   156: invokevirtual add : (Ljava/lang/Object;)Z
    //   159: pop
    //   160: aload_3
    //   161: invokeinterface remove : ()V
    //   166: iload_2
    //   167: ifne -> 19
    //   170: aload #4
    //   172: ifnull -> 269
    //   175: aload #4
    //   177: invokevirtual iterator : ()Ljava/util/Iterator;
    //   180: astore #5
    //   182: aload #5
    //   184: invokeinterface hasNext : ()Z
    //   189: ifeq -> 269
    //   192: aload #5
    //   194: invokeinterface next : ()Ljava/lang/Object;
    //   199: checkcast com/fasterxml/Zoz/Zb
    //   202: astore #6
    //   204: aload #6
    //   206: invokevirtual ZT : ()Ljava/lang/String;
    //   209: astore #7
    //   211: aload_1
    //   212: aload #7
    //   214: invokeinterface get : (Ljava/lang/Object;)Ljava/lang/Object;
    //   219: checkcast com/fasterxml/Zoz/Zb
    //   222: astore #8
    //   224: aload #8
    //   226: ifnonnull -> 251
    //   229: aload_1
    //   230: aload #7
    //   232: aload #6
    //   234: invokeinterface put : (Ljava/lang/Object;Ljava/lang/Object;)Ljava/lang/Object;
    //   239: pop
    //   240: iload_2
    //   241: ifne -> 265
    //   244: goto -> 251
    //   247: invokestatic a : (Ljava/lang/IllegalArgumentException;)Ljava/lang/IllegalArgumentException;
    //   250: athrow
    //   251: aload #8
    //   253: aload #6
    //   255: invokevirtual ZX : (Lcom/fasterxml/Zoz/Zb;)V
    //   258: goto -> 265
    //   261: invokestatic a : (Ljava/lang/IllegalArgumentException;)Ljava/lang/IllegalArgumentException;
    //   264: athrow
    //   265: iload_2
    //   266: ifne -> 182
    //   269: return
    // Exception table:
    //   from	to	target	type
    //   58	67	70	java/lang/IllegalArgumentException
    //   90	102	105	java/lang/IllegalArgumentException
    //   109	127	130	java/lang/IllegalArgumentException
    //   224	244	247	java/lang/IllegalArgumentException
    //   229	258	261	java/lang/IllegalArgumentException
  }
  
  protected void Zh(Map<String, Zb> paramMap) {
    // Byte code:
    //   0: invokestatic Zv : ()I
    //   3: aload_0
    //   4: getfield ZG : Lcom/fasterxml/Zor/Zt;
    //   7: astore_3
    //   8: istore_2
    //   9: aload_3
    //   10: aload_0
    //   11: getfield Zq : Lcom/fasterxml/Zoz/Zia;
    //   14: invokevirtual Zi : (Lcom/fasterxml/Zoz/Ziv;)Ljava/lang/Boolean;
    //   17: astore #4
    //   19: aload #4
    //   21: ifnonnull -> 38
    //   24: aload_0
    //   25: getfield Zz : Lcom/fasterxml/Zj/Zf;
    //   28: invokevirtual ZY : ()Z
    //   31: goto -> 43
    //   34: invokestatic a : (Ljava/lang/IllegalArgumentException;)Ljava/lang/IllegalArgumentException;
    //   37: athrow
    //   38: aload #4
    //   40: invokevirtual booleanValue : ()Z
    //   43: istore #5
    //   45: aload_0
    //   46: aload_1
    //   47: invokeinterface values : ()Ljava/util/Collection;
    //   52: invokespecial Zr : (Ljava/util/Collection;)Z
    //   55: istore #6
    //   57: aload_3
    //   58: aload_0
    //   59: getfield Zq : Lcom/fasterxml/Zoz/Zia;
    //   62: invokevirtual Zx : (Lcom/fasterxml/Zoz/Zia;)[Ljava/lang/String;
    //   65: astore #7
    //   67: iload #5
    //   69: ifne -> 115
    //   72: iload #6
    //   74: ifne -> 115
    //   77: goto -> 84
    //   80: invokestatic a : (Ljava/lang/IllegalArgumentException;)Ljava/lang/IllegalArgumentException;
    //   83: athrow
    //   84: aload_0
    //   85: getfield Zu : Ljava/util/LinkedList;
    //   88: ifnonnull -> 115
    //   91: goto -> 98
    //   94: invokestatic a : (Ljava/lang/IllegalArgumentException;)Ljava/lang/IllegalArgumentException;
    //   97: athrow
    //   98: aload #7
    //   100: ifnonnull -> 115
    //   103: goto -> 110
    //   106: invokestatic a : (Ljava/lang/IllegalArgumentException;)Ljava/lang/IllegalArgumentException;
    //   109: athrow
    //   110: return
    //   111: invokestatic a : (Ljava/lang/IllegalArgumentException;)Ljava/lang/IllegalArgumentException;
    //   114: athrow
    //   115: aload_1
    //   116: invokeinterface size : ()I
    //   121: istore #8
    //   123: iload #5
    //   125: ifeq -> 141
    //   128: new java/util/TreeMap
    //   131: dup
    //   132: invokespecial <init> : ()V
    //   135: astore #9
    //   137: iload_2
    //   138: ifeq -> 155
    //   141: new java/util/LinkedHashMap
    //   144: dup
    //   145: iload #8
    //   147: iload #8
    //   149: iadd
    //   150: invokespecial <init> : (I)V
    //   153: astore #9
    //   155: aload_1
    //   156: invokeinterface values : ()Ljava/util/Collection;
    //   161: invokeinterface iterator : ()Ljava/util/Iterator;
    //   166: astore #10
    //   168: aload #10
    //   170: invokeinterface hasNext : ()Z
    //   175: ifeq -> 209
    //   178: aload #10
    //   180: invokeinterface next : ()Ljava/lang/Object;
    //   185: checkcast com/fasterxml/Zoz/Zb
    //   188: astore #11
    //   190: aload #9
    //   192: aload #11
    //   194: invokevirtual ZT : ()Ljava/lang/String;
    //   197: aload #11
    //   199: invokeinterface put : (Ljava/lang/Object;Ljava/lang/Object;)Ljava/lang/Object;
    //   204: pop
    //   205: iload_2
    //   206: ifeq -> 168
    //   209: new java/util/LinkedHashMap
    //   212: dup
    //   213: iload #8
    //   215: iload #8
    //   217: iadd
    //   218: invokespecial <init> : (I)V
    //   221: astore #10
    //   223: aload #7
    //   225: ifnull -> 378
    //   228: aload #7
    //   230: astore #11
    //   232: aload #11
    //   234: arraylength
    //   235: istore #12
    //   237: iconst_0
    //   238: istore #13
    //   240: iload #13
    //   242: iload #12
    //   244: if_icmpge -> 378
    //   247: aload #11
    //   249: iload #13
    //   251: aaload
    //   252: astore #14
    //   254: aload #9
    //   256: aload #14
    //   258: invokeinterface remove : (Ljava/lang/Object;)Ljava/lang/Object;
    //   263: checkcast com/fasterxml/Zoz/Zb
    //   266: astore #15
    //   268: aload #15
    //   270: ifnonnull -> 347
    //   273: aload_1
    //   274: invokeinterface values : ()Ljava/util/Collection;
    //   279: invokeinterface iterator : ()Ljava/util/Iterator;
    //   284: astore #16
    //   286: aload #16
    //   288: invokeinterface hasNext : ()Z
    //   293: ifeq -> 347
    //   296: aload #16
    //   298: invokeinterface next : ()Ljava/lang/Object;
    //   303: checkcast com/fasterxml/Zoz/Zb
    //   306: astore #17
    //   308: aload #14
    //   310: aload #17
    //   312: invokevirtual ZW : ()Ljava/lang/String;
    //   315: invokevirtual equals : (Ljava/lang/Object;)Z
    //   318: ifeq -> 336
    //   321: aload #17
    //   323: astore #15
    //   325: aload #17
    //   327: invokevirtual ZT : ()Ljava/lang/String;
    //   330: astore #14
    //   332: iload_2
    //   333: ifeq -> 347
    //   336: iload_2
    //   337: ifeq -> 286
    //   340: goto -> 347
    //   343: invokestatic a : (Ljava/lang/IllegalArgumentException;)Ljava/lang/IllegalArgumentException;
    //   346: athrow
    //   347: aload #15
    //   349: ifnull -> 371
    //   352: aload #10
    //   354: aload #14
    //   356: aload #15
    //   358: invokeinterface put : (Ljava/lang/Object;Ljava/lang/Object;)Ljava/lang/Object;
    //   363: pop
    //   364: goto -> 371
    //   367: invokestatic a : (Ljava/lang/IllegalArgumentException;)Ljava/lang/IllegalArgumentException;
    //   370: athrow
    //   371: iinc #13, 1
    //   374: iload_2
    //   375: ifeq -> 240
    //   378: iload #6
    //   380: ifeq -> 540
    //   383: new java/util/TreeMap
    //   386: dup
    //   387: invokespecial <init> : ()V
    //   390: astore #11
    //   392: aload #9
    //   394: invokeinterface entrySet : ()Ljava/util/Set;
    //   399: invokeinterface iterator : ()Ljava/util/Iterator;
    //   404: astore #12
    //   406: aload #12
    //   408: invokeinterface hasNext : ()Z
    //   413: ifeq -> 485
    //   416: aload #12
    //   418: invokeinterface next : ()Ljava/lang/Object;
    //   423: checkcast java/util/Map$Entry
    //   426: astore #13
    //   428: aload #13
    //   430: invokeinterface getValue : ()Ljava/lang/Object;
    //   435: checkcast com/fasterxml/Zoz/Zb
    //   438: astore #14
    //   440: aload #14
    //   442: invokevirtual ZC : ()Lcom/fasterxml/Zor/Zyb;
    //   445: invokevirtual Zv : ()Ljava/lang/Integer;
    //   448: astore #15
    //   450: aload #15
    //   452: ifnull -> 481
    //   455: aload #11
    //   457: aload #15
    //   459: aload #14
    //   461: invokeinterface put : (Ljava/lang/Object;Ljava/lang/Object;)Ljava/lang/Object;
    //   466: pop
    //   467: aload #12
    //   469: invokeinterface remove : ()V
    //   474: goto -> 481
    //   477: invokestatic a : (Ljava/lang/IllegalArgumentException;)Ljava/lang/IllegalArgumentException;
    //   480: athrow
    //   481: iload_2
    //   482: ifeq -> 406
    //   485: aload #11
    //   487: invokeinterface values : ()Ljava/util/Collection;
    //   492: invokeinterface iterator : ()Ljava/util/Iterator;
    //   497: astore #13
    //   499: aload #13
    //   501: invokeinterface hasNext : ()Z
    //   506: ifeq -> 540
    //   509: aload #13
    //   511: invokeinterface next : ()Ljava/lang/Object;
    //   516: checkcast com/fasterxml/Zoz/Zb
    //   519: astore #14
    //   521: aload #10
    //   523: aload #14
    //   525: invokevirtual ZT : ()Ljava/lang/String;
    //   528: aload #14
    //   530: invokeinterface put : (Ljava/lang/Object;Ljava/lang/Object;)Ljava/lang/Object;
    //   535: pop
    //   536: iload_2
    //   537: ifeq -> 499
    //   540: aload_0
    //   541: getfield Zu : Ljava/util/LinkedList;
    //   544: ifnull -> 738
    //   547: iload #5
    //   549: ifeq -> 579
    //   552: goto -> 559
    //   555: invokestatic a : (Ljava/lang/IllegalArgumentException;)Ljava/lang/IllegalArgumentException;
    //   558: athrow
    //   559: aload_0
    //   560: getfield Zz : Lcom/fasterxml/Zj/Zf;
    //   563: getstatic com/fasterxml/Zor/Zy9.SORT_CREATOR_PROPERTIES_FIRST : Lcom/fasterxml/Zor/Zy9;
    //   566: invokevirtual ZB : (Lcom/fasterxml/Zor/Zy9;)Z
    //   569: ifeq -> 738
    //   572: goto -> 579
    //   575: invokestatic a : (Ljava/lang/IllegalArgumentException;)Ljava/lang/IllegalArgumentException;
    //   578: athrow
    //   579: iload #5
    //   581: ifeq -> 659
    //   584: goto -> 591
    //   587: invokestatic a : (Ljava/lang/IllegalArgumentException;)Ljava/lang/IllegalArgumentException;
    //   590: athrow
    //   591: new java/util/TreeMap
    //   594: dup
    //   595: invokespecial <init> : ()V
    //   598: astore #12
    //   600: aload_0
    //   601: getfield Zu : Ljava/util/LinkedList;
    //   604: invokevirtual iterator : ()Ljava/util/Iterator;
    //   607: astore #13
    //   609: aload #13
    //   611: invokeinterface hasNext : ()Z
    //   616: ifeq -> 648
    //   619: aload #13
    //   621: invokeinterface next : ()Ljava/lang/Object;
    //   626: checkcast com/fasterxml/Zoz/Zb
    //   629: astore #14
    //   631: aload #12
    //   633: aload #14
    //   635: invokevirtual ZT : ()Ljava/lang/String;
    //   638: aload #14
    //   640: invokevirtual put : (Ljava/lang/Object;Ljava/lang/Object;)Ljava/lang/Object;
    //   643: pop
    //   644: iload_2
    //   645: ifeq -> 609
    //   648: aload #12
    //   650: invokevirtual values : ()Ljava/util/Collection;
    //   653: astore #11
    //   655: iload_2
    //   656: ifeq -> 665
    //   659: aload_0
    //   660: getfield Zu : Ljava/util/LinkedList;
    //   663: astore #11
    //   665: aload #11
    //   667: invokeinterface iterator : ()Ljava/util/Iterator;
    //   672: astore #12
    //   674: aload #12
    //   676: invokeinterface hasNext : ()Z
    //   681: ifeq -> 738
    //   684: aload #12
    //   686: invokeinterface next : ()Ljava/lang/Object;
    //   691: checkcast com/fasterxml/Zoz/Zb
    //   694: astore #13
    //   696: aload #13
    //   698: invokevirtual ZT : ()Ljava/lang/String;
    //   701: astore #14
    //   703: aload #9
    //   705: aload #14
    //   707: invokeinterface containsKey : (Ljava/lang/Object;)Z
    //   712: ifeq -> 734
    //   715: aload #10
    //   717: aload #14
    //   719: aload #13
    //   721: invokeinterface put : (Ljava/lang/Object;Ljava/lang/Object;)Ljava/lang/Object;
    //   726: pop
    //   727: goto -> 734
    //   730: invokestatic a : (Ljava/lang/IllegalArgumentException;)Ljava/lang/IllegalArgumentException;
    //   733: athrow
    //   734: iload_2
    //   735: ifeq -> 674
    //   738: aload #10
    //   740: aload #9
    //   742: invokeinterface putAll : (Ljava/util/Map;)V
    //   747: aload_1
    //   748: invokeinterface clear : ()V
    //   753: aload_1
    //   754: aload #10
    //   756: invokeinterface putAll : (Ljava/util/Map;)V
    //   761: return
    // Exception table:
    //   from	to	target	type
    //   19	34	34	java/lang/IllegalArgumentException
    //   67	77	80	java/lang/IllegalArgumentException
    //   72	91	94	java/lang/IllegalArgumentException
    //   84	103	106	java/lang/IllegalArgumentException
    //   98	111	111	java/lang/IllegalArgumentException
    //   332	340	343	java/lang/IllegalArgumentException
    //   347	364	367	java/lang/IllegalArgumentException
    //   450	474	477	java/lang/IllegalArgumentException
    //   540	552	555	java/lang/IllegalArgumentException
    //   547	572	575	java/lang/IllegalArgumentException
    //   559	584	587	java/lang/IllegalArgumentException
    //   703	727	730	java/lang/IllegalArgumentException
  }
  
  private boolean Zr(Collection<Zb> paramCollection) {
    Iterator<Zb> iterator = paramCollection.iterator();
    int i = Ziv.ZM();
    while (iterator.hasNext()) {
      Zb zb = iterator.next();
      try {
        if (zb.ZC().ZE())
          return true; 
      } catch (IllegalArgumentException illegalArgumentException) {
        throw a(null);
      } 
      if (i == 0)
        break; 
    } 
    return false;
  }
  
  protected boolean Ze(List<Ziz> paramList) {
    int i = Ziv.ZM();
    while (true) {
      while (true) {
        Ziz ziz1 = paramList.get(0);
        Ziz ziz2 = paramList.get(1);
        break;
      } 
      if (paramList.size() <= 1)
        return true; 
    } 
  }
  
  protected void Zz(String paramString, Object... paramVarArgs) {
    if (paramVarArgs.length > 0)
      paramString = String.format(paramString, paramVarArgs); 
    throw new IllegalArgumentException(a(8410, 18534) + this.Zq + a(8411, -17470) + paramString);
  }
  
  protected Zb Zo(Map<String, Zb> paramMap, Zr paramZr) {
    String str = paramZr.Zb();
    Zb zb = paramMap.get(str);
    if (zb == null) {
      zb = new Zb(this.Zz, this.ZG, this.Zi, paramZr);
      paramMap.put(str, zb);
    } 
    return zb;
  }
  
  protected Zb ZX(Map<String, Zb> paramMap, String paramString) {
    Zb zb = paramMap.get(paramString);
    if (zb == null) {
      zb = new Zb(this.Zz, this.ZG, this.Zi, Zr.Zf(paramString));
      paramMap.put(paramString, zb);
    } 
    return zb;
  }
  
  private Ze Zv() {
    Object object = this.ZG.Zv(this.Zq);
    try {
      if (object == null)
        return this.Zz.Zl(); 
    } catch (IllegalArgumentException illegalArgumentException) {
      throw a(null);
    } 
    try {
      if (object instanceof Ze)
        return (Ze)object; 
    } catch (IllegalArgumentException illegalArgumentException) {
      throw a(null);
    } 
    try {
      if (!(object instanceof Class))
        Zz(a(8415, -24842), new Object[] { Zx.ZZ(object) }); 
    } catch (IllegalArgumentException illegalArgumentException) {
      throw a(null);
    } 
    Class<Ze> clazz = (Class)object;
    try {
      if (clazz == Ze.class)
        return null; 
    } catch (IllegalArgumentException illegalArgumentException) {
      throw a(null);
    } 
    try {
      if (!Ze.class.isAssignableFrom(clazz))
        Zz(a(8402, -24992), new Object[] { Zx.ZZ(clazz) }); 
    } catch (IllegalArgumentException illegalArgumentException) {
      throw a(null);
    } 
    Zqn zqn = this.Zz.Zf();
    if (zqn != null) {
      Ze ze = zqn.Zi(this.Zz, this.Zq, clazz);
      try {
        if (ze != null)
          return ze; 
      } catch (IllegalArgumentException illegalArgumentException) {
        throw a(null);
      } 
    } 
    return (Ze)Zx.ZR(clazz, this.Zz.Zd());
  }
  
  protected boolean Zl(Zb paramZb, List<Zb> paramList) {
    int i = Ziv.ZM();
    if (paramList != null) {
      String str = paramZb.ZW();
      byte b = 0;
      int j = paramList.size();
      while (b < j) {
        try {
          if (((Zb)paramList.get(b)).ZW().equals(str)) {
            paramList.set(b, paramZb);
            return true;
          } 
        } catch (IllegalArgumentException illegalArgumentException) {
          throw a(null);
        } 
        b++;
        if (i == 0)
          break; 
      } 
    } 
    return false;
  }
  
  private static IllegalArgumentException a(IllegalArgumentException paramIllegalArgumentException) {
    return paramIllegalArgumentException;
  }
  
  static {
    // Byte code:
    //   0: bipush #12
    //   2: anewarray java/lang/String
    //   5: astore #5
    //   7: iconst_0
    //   8: istore_3
    //   9: ldc '_+jdJ5vYO~2m}t0s}(?j<`\\n:8ZyRcfA:!m4;.Z/<{z\oci"/"[}zH7cGd:8 kG\\b1?<}o+[\\rggg OzN<OR:r=P-*Y(so2G&QS~r#<Lac\\rlj-<Y0HXyD3,rqG TDTB8[/jvtaK:9@\\nEL5Gnt*>SC$&eb4>h`c9e#'p2<HS*:!-A/U'@T(0<s}q.W]s|Gj)5~9E^A6.a \\tbd'
    //   11: dup
    //   12: astore_2
    //   13: invokevirtual length : ()I
    //   16: istore #4
    //   18: bipush #47
    //   20: istore_1
    //   21: iconst_m1
    //   22: istore_0
    //   23: bipush #61
    //   25: iinc #0, 1
    //   28: aload_2
    //   29: iload_0
    //   30: dup
    //   31: iload_1
    //   32: iadd
    //   33: invokevirtual substring : (II)Ljava/lang/String;
    //   36: iconst_m1
    //   37: goto -> 143
    //   40: aload #5
    //   42: swap
    //   43: iload_3
    //   44: iinc #3, 1
    //   47: swap
    //   48: aastore
    //   49: iload_0
    //   50: iload_1
    //   51: iadd
    //   52: dup
    //   53: istore_0
    //   54: iload #4
    //   56: if_icmpge -> 68
    //   59: aload_2
    //   60: iload_0
    //   61: invokevirtual charAt : (I)C
    //   64: istore_1
    //   65: goto -> 23
    //   68: ldc 'L:-B.jCm -n8z^(2RFNiY\t/ nQHQ\\t#er\\n"'d\\tJn|wm{^'
    //   70: dup
    //   71: astore_2
    //   72: invokevirtual length : ()I
    //   75: istore #4
    //   77: bipush #47
    //   79: istore_1
    //   80: iconst_m1
    //   81: istore_0
    //   82: bipush #59
    //   84: iinc #0, 1
    //   87: aload_2
    //   88: iload_0
    //   89: dup
    //   90: iload_1
    //   91: iadd
    //   92: invokevirtual substring : (II)Ljava/lang/String;
    //   95: iconst_0
    //   96: goto -> 143
    //   99: aload #5
    //   101: swap
    //   102: iload_3
    //   103: iinc #3, 1
    //   106: swap
    //   107: aastore
    //   108: iload_0
    //   109: iload_1
    //   110: iadd
    //   111: dup
    //   112: istore_0
    //   113: iload #4
    //   115: if_icmpge -> 127
    //   118: aload_2
    //   119: iload_0
    //   120: invokevirtual charAt : (I)C
    //   123: istore_1
    //   124: goto -> 82
    //   127: aload #5
    //   129: putstatic com/fasterxml/Zoz/Zh.a : [Ljava/lang/String;
    //   132: bipush #12
    //   134: anewarray java/lang/String
    //   137: putstatic com/fasterxml/Zoz/Zh.b : [Ljava/lang/String;
    //   140: goto -> 300
    //   143: dup_x2
    //   144: pop
    //   145: invokevirtual toCharArray : ()[C
    //   148: dup_x1
    //   149: arraylength
    //   150: dup_x2
    //   151: pop
    //   152: iconst_0
    //   153: istore #6
    //   155: dup2_x1
    //   156: pop2
    //   157: dup_x2
    //   158: iconst_1
    //   159: if_icmpgt -> 259
    //   162: dup2
    //   163: swap
    //   164: iload #6
    //   166: dup2_x1
    //   167: caload
    //   168: swap
    //   169: iload #6
    //   171: bipush #7
    //   173: irem
    //   174: tableswitch default -> 241, 0 -> 212, 1 -> 217, 2 -> 222, 3 -> 227, 4 -> 232, 5 -> 236
    //   212: bipush #52
    //   214: goto -> 243
    //   217: bipush #30
    //   219: goto -> 243
    //   222: bipush #96
    //   224: goto -> 243
    //   227: bipush #27
    //   229: goto -> 243
    //   232: iconst_1
    //   233: goto -> 243
    //   236: bipush #21
    //   238: goto -> 243
    //   241: bipush #82
    //   243: ixor
    //   244: ixor
    //   245: i2c
    //   246: castore
    //   247: iinc #6, 1
    //   250: dup
    //   251: ifne -> 259
    //   254: dup2
    //   255: dup_x1
    //   256: goto -> 166
    //   259: dup2_x1
    //   260: pop2
    //   261: dup_x2
    //   262: iload #6
    //   264: if_icmpgt -> 162
    //   267: pop
    //   268: new java/lang/String
    //   271: dup_x1
    //   272: swap
    //   273: invokespecial <init> : ([C)V
    //   276: invokevirtual intern : ()Ljava/lang/String;
    //   279: swap
    //   280: pop
    //   281: swap
    //   282: tableswitch default -> 40, 0 -> 99
    //   300: return
  }
  
  private static String a(int paramInt1, int paramInt2) {
    int i = (paramInt1 ^ 0x20D9) & 0xFFFF;
    if (b[i] == null) {
      char[] arrayOfChar = a[i].toCharArray();
      switch (arrayOfChar[0] & 0xFF) {
        case 0:
        
        case 1:
        
        case 2:
        
        case 3:
        
        case 4:
        
        case 5:
        
        case 6:
        
        case 7:
        
        case 8:
        
        case 9:
        
        case 10:
        
        case 11:
        
        case 12:
        
        case 13:
        
        case 14:
        
        case 15:
        
        case 16:
        
        case 17:
        
        case 18:
        
        case 19:
        
        case 20:
        
        case 21:
        
        case 22:
        
        case 23:
        
        case 24:
        
        case 25:
        
        case 26:
        
        case 27:
        
        case 28:
        
        case 29:
        
        case 30:
        
        case 31:
        
        case 32:
        
        case 33:
        
        case 34:
        
        case 35:
        
        case 36:
        
        case 37:
        
        case 38:
        
        case 39:
        
        case 40:
        
        case 41:
        
        case 42:
        
        case 43:
        
        case 44:
        
        case 45:
        
        case 46:
        
        case 47:
        
        case 48:
        
        case 49:
        
        case 50:
        
        case 51:
        
        case 52:
        
        case 53:
        
        case 54:
        
        case 55:
        
        case 56:
        
        case 57:
        
        case 58:
        
        case 59:
        
        case 60:
        
        case 61:
        
        case 62:
        
        case 63:
        
        case 64:
        
        case 65:
        
        case 66:
        
        case 67:
        
        case 68:
        
        case 69:
        
        case 70:
        
        case 71:
        
        case 72:
        
        case 73:
        
        case 74:
        
        case 75:
        
        case 76:
        
        case 77:
        
        case 78:
        
        case 79:
        
        case 80:
        
        case 81:
        
        case 82:
        
        case 83:
        
        case 84:
        
        case 85:
        
        case 86:
        
        case 87:
        
        case 88:
        
        case 89:
        
        case 90:
        
        case 91:
        
        case 92:
        
        case 93:
        
        case 94:
        
        case 95:
        
        case 96:
        
        case 97:
        
        case 98:
        
        case 99:
        
        case 100:
        
        case 101:
        
        case 102:
        
        case 103:
        
        case 104:
        
        case 105:
        
        case 106:
        
        case 107:
        
        case 108:
        
        case 109:
        
        case 110:
        
        case 111:
        
        case 112:
        
        case 113:
        
        case 114:
        
        case 115:
        
        case 116:
        
        case 117:
        
        case 118:
        
        case 119:
        
        case 120:
        
        case 121:
        
        case 122:
        
        case 123:
        
        case 124:
        
        case 125:
        
        case 126:
        
        case 127:
        
        case 128:
        
        case 129:
        
        case 130:
        
        case 131:
        
        case 132:
        
        case 133:
        
        case 134:
        
        case 135:
        
        case 136:
        
        case 137:
        
        case 138:
        
        case 139:
        
        case 140:
        
        case 141:
        
        case 142:
        
        case 143:
        
        case 144:
        
        case 145:
        
        case 146:
        
        case 147:
        
        case 148:
        
        case 149:
        
        case 150:
        
        case 151:
        
        case 152:
        
        case 153:
        
        case 154:
        
        case 155:
        
        case 156:
        
        case 157:
        
        case 158:
        
        case 159:
        
        case 160:
        
        case 161:
        
        case 162:
        
        case 163:
        
        case 164:
        
        case 165:
        
        case 166:
        
        case 167:
        
        case 168:
        
        case 169:
        
        case 170:
        
        case 171:
        
        case 172:
        
        case 173:
        
        case 174:
        
        case 175:
        
        case 176:
        
        case 177:
        
        case 178:
        
        case 179:
        
        case 180:
        
        case 181:
        
        case 182:
        
        case 183:
        
        case 184:
        
        case 185:
        
        case 186:
        
        case 187:
        
        case 188:
        
        case 189:
        
        case 190:
        
        case 191:
        
        case 192:
        
        case 193:
        
        case 194:
        
        case 195:
        
        case 196:
        
        case 197:
        
        case 198:
        
        case 199:
        
        case 200:
        
        case 201:
        
        case 202:
        
        case 203:
        
        case 204:
        
        case 205:
        
        case 206:
        
        case 207:
        
        case 208:
        
        case 209:
        
        case 210:
        
        case 211:
        
        case 212:
        
        case 213:
        
        case 214:
        
        case 215:
        
        case 216:
        
        case 217:
        
        case 218:
        
        case 219:
        
        case 220:
        
        case 221:
        
        case 222:
        
        case 223:
        
        case 224:
        
        case 225:
        
        case 226:
        
        case 227:
        
        case 228:
        
        case 229:
        
        case 230:
        
        case 231:
        
        case 232:
        
        case 233:
        
        case 234:
        
        case 235:
        
        case 236:
        
        case 237:
        
        case 238:
        
        case 239:
        
        case 240:
        
        case 241:
        
        case 242:
        
        case 243:
        
        case 244:
        
        case 245:
        
        case 246:
        
        case 247:
        
        case 248:
        
        case 249:
        
        case 250:
        
        case 251:
        
        case 252:
        
        case 253:
        
        case 254:
        
        default:
          break;
      } 
      byte b1 = 67;
      int j = (paramInt2 & 0xFF) - b1;
      if (j < 0)
        j += 256; 
      int k = ((paramInt2 & 0xFFFF) >>> 8) - b1;
      if (k < 0)
        k += 256; 
      for (byte b2 = 0; b2 < arrayOfChar.length; b2++) {
        int m = b2 % 2;
        if (m == 0) {
          arrayOfChar[b2] = (char)(arrayOfChar[b2] ^ j);
          j = ((j >>> 3 | j << 5) ^ arrayOfChar[b2]) & 0xFF;
        } else {
          arrayOfChar[b2] = (char)(arrayOfChar[b2] ^ k);
          k = ((k >>> 3 | k << 5) ^ arrayOfChar[b2]) & 0xFF;
        } 
      } 
      b[i] = (new String(arrayOfChar)).intern();
    } 
    return b[i];
  }
}


/* Location:              C:\Program Files\BurpSuitePro\burpsuite_pro.jar!\com\fasterxml\Zoz\Zh.class
 * Java compiler version: 8 (52.0)
 * JD-Core Version:       1.1.3
 */