package net.portswigger;

import java.util.BitSet;
import java.util.EnumSet;

class Zcf {
  private static Zkd ZNM(int paramInt, BitSet paramBitSet, EnumSet<Zkd> paramEnumSet) {
    // Byte code:
    //   0: invokestatic Zy : ()Z
    //   3: aconst_null
    //   4: astore #4
    //   6: istore_3
    //   7: iload_0
    //   8: bipush #35
    //   10: if_icmpne -> 23
    //   13: aload_1
    //   14: bipush #86
    //   16: invokevirtual set : (I)V
    //   19: iload_3
    //   20: ifeq -> 514
    //   23: iload_0
    //   24: bipush #48
    //   26: if_icmplt -> 76
    //   29: iload_0
    //   30: bipush #57
    //   32: if_icmpgt -> 76
    //   35: aload_1
    //   36: bipush #41
    //   38: invokevirtual set : (I)V
    //   41: aload_1
    //   42: sipush #181
    //   45: invokevirtual set : (I)V
    //   48: aload_1
    //   49: bipush #89
    //   51: invokevirtual set : (I)V
    //   54: aload_1
    //   55: bipush #6
    //   57: invokevirtual set : (I)V
    //   60: aload_1
    //   61: bipush #108
    //   63: invokevirtual set : (I)V
    //   66: aload_1
    //   67: bipush #28
    //   69: invokevirtual set : (I)V
    //   72: iload_3
    //   73: ifeq -> 514
    //   76: iload_0
    //   77: bipush #97
    //   79: if_icmpne -> 112
    //   82: aload_1
    //   83: sipush #168
    //   86: invokevirtual set : (I)V
    //   89: aload_1
    //   90: bipush #74
    //   92: invokevirtual set : (I)V
    //   95: aload_1
    //   96: bipush #113
    //   98: invokevirtual set : (I)V
    //   101: aload_1
    //   102: sipush #183
    //   105: invokevirtual set : (I)V
    //   108: iload_3
    //   109: ifeq -> 514
    //   112: iload_0
    //   113: bipush #98
    //   115: if_icmpne -> 129
    //   118: aload_1
    //   119: sipush #221
    //   122: invokevirtual set : (I)V
    //   125: iload_3
    //   126: ifeq -> 514
    //   129: iload_0
    //   130: bipush #99
    //   132: if_icmpne -> 157
    //   135: aload_1
    //   136: bipush #24
    //   138: invokevirtual set : (I)V
    //   141: aload_1
    //   142: bipush #125
    //   144: invokevirtual set : (I)V
    //   147: aload_1
    //   148: bipush #30
    //   150: invokevirtual set : (I)V
    //   153: iload_3
    //   154: ifeq -> 514
    //   157: iload_0
    //   158: bipush #100
    //   160: if_icmpne -> 186
    //   163: aload_1
    //   164: sipush #143
    //   167: invokevirtual set : (I)V
    //   170: aload_1
    //   171: bipush #39
    //   173: invokevirtual set : (I)V
    //   176: aload_1
    //   177: bipush #82
    //   179: invokevirtual set : (I)V
    //   182: iload_3
    //   183: ifeq -> 514
    //   186: iload_0
    //   187: bipush #101
    //   189: if_icmpne -> 208
    //   192: aload_1
    //   193: bipush #126
    //   195: invokevirtual set : (I)V
    //   198: aload_1
    //   199: bipush #88
    //   201: invokevirtual set : (I)V
    //   204: iload_3
    //   205: ifeq -> 514
    //   208: iload_0
    //   209: bipush #102
    //   211: if_icmpne -> 224
    //   214: aload_1
    //   215: bipush #57
    //   217: invokevirtual set : (I)V
    //   220: iload_3
    //   221: ifeq -> 514
    //   224: iload_0
    //   225: bipush #104
    //   227: if_icmpne -> 253
    //   230: aload_1
    //   231: bipush #90
    //   233: invokevirtual set : (I)V
    //   236: aload_1
    //   237: bipush #59
    //   239: invokevirtual set : (I)V
    //   242: aload_1
    //   243: sipush #207
    //   246: invokevirtual set : (I)V
    //   249: iload_3
    //   250: ifeq -> 514
    //   253: iload_0
    //   254: bipush #105
    //   256: if_icmpne -> 295
    //   259: aload_1
    //   260: bipush #121
    //   262: invokevirtual set : (I)V
    //   265: aload_1
    //   266: bipush #25
    //   268: invokevirtual set : (I)V
    //   271: aload_1
    //   272: sipush #186
    //   275: invokevirtual set : (I)V
    //   278: aload_1
    //   279: sipush #193
    //   282: invokevirtual set : (I)V
    //   285: aload_1
    //   286: bipush #120
    //   288: invokevirtual set : (I)V
    //   291: iload_3
    //   292: ifeq -> 514
    //   295: iload_0
    //   296: bipush #108
    //   298: if_icmpne -> 312
    //   301: aload_1
    //   302: sipush #197
    //   305: invokevirtual set : (I)V
    //   308: iload_3
    //   309: ifeq -> 514
    //   312: iload_0
    //   313: bipush #109
    //   315: if_icmpne -> 340
    //   318: aload_1
    //   319: bipush #91
    //   321: invokevirtual set : (I)V
    //   324: aload_1
    //   325: bipush #22
    //   327: invokevirtual set : (I)V
    //   330: aload_1
    //   331: bipush #53
    //   333: invokevirtual set : (I)V
    //   336: iload_3
    //   337: ifeq -> 514
    //   340: iload_0
    //   341: bipush #110
    //   343: if_icmpne -> 363
    //   346: aload_1
    //   347: bipush #72
    //   349: invokevirtual set : (I)V
    //   352: aload_1
    //   353: sipush #224
    //   356: invokevirtual set : (I)V
    //   359: iload_3
    //   360: ifeq -> 514
    //   363: iload_0
    //   364: bipush #111
    //   366: if_icmpne -> 380
    //   369: aload_1
    //   370: sipush #189
    //   373: invokevirtual set : (I)V
    //   376: iload_3
    //   377: ifeq -> 514
    //   380: iload_0
    //   381: bipush #112
    //   383: if_icmpne -> 397
    //   386: aload_1
    //   387: sipush #202
    //   390: invokevirtual set : (I)V
    //   393: iload_3
    //   394: ifeq -> 514
    //   397: iload_0
    //   398: bipush #113
    //   400: if_icmpne -> 421
    //   403: aload_1
    //   404: sipush #169
    //   407: invokevirtual set : (I)V
    //   410: aload_1
    //   411: sipush #194
    //   414: invokevirtual set : (I)V
    //   417: iload_3
    //   418: ifeq -> 514
    //   421: iload_0
    //   422: bipush #114
    //   424: if_icmpne -> 464
    //   427: aload_1
    //   428: bipush #13
    //   430: invokevirtual set : (I)V
    //   433: aload_1
    //   434: bipush #51
    //   436: invokevirtual set : (I)V
    //   439: aload_1
    //   440: sipush #175
    //   443: invokevirtual set : (I)V
    //   446: aload_1
    //   447: sipush #203
    //   450: invokevirtual set : (I)V
    //   453: aload_1
    //   454: sipush #219
    //   457: invokevirtual set : (I)V
    //   460: iload_3
    //   461: ifeq -> 514
    //   464: iload_0
    //   465: bipush #115
    //   467: if_icmpne -> 494
    //   470: aload_1
    //   471: bipush #58
    //   473: invokevirtual set : (I)V
    //   476: aload_1
    //   477: sipush #133
    //   480: invokevirtual set : (I)V
    //   483: aload_1
    //   484: sipush #147
    //   487: invokevirtual set : (I)V
    //   490: iload_3
    //   491: ifeq -> 514
    //   494: iload_0
    //   495: bipush #116
    //   497: if_icmpne -> 514
    //   500: aload_1
    //   501: sipush #177
    //   504: invokevirtual set : (I)V
    //   507: aload_1
    //   508: sipush #191
    //   511: invokevirtual set : (I)V
    //   514: iload_0
    //   515: bipush #65
    //   517: if_icmplt -> 526
    //   520: iload_0
    //   521: bipush #90
    //   523: if_icmple -> 544
    //   526: iload_0
    //   527: bipush #95
    //   529: if_icmpeq -> 544
    //   532: iload_0
    //   533: bipush #97
    //   535: if_icmplt -> 565
    //   538: iload_0
    //   539: bipush #122
    //   541: if_icmpgt -> 565
    //   544: aload_1
    //   545: bipush #119
    //   547: invokevirtual set : (I)V
    //   550: aload_2
    //   551: getstatic net/portswigger/Zkd.UNKNOWN_STRING : Lnet/portswigger/Zkd;
    //   554: invokevirtual contains : (Ljava/lang/Object;)Z
    //   557: ifeq -> 565
    //   560: getstatic net/portswigger/Zkd.UNKNOWN_STRING : Lnet/portswigger/Zkd;
    //   563: astore #4
    //   565: iload_0
    //   566: iflt -> 584
    //   569: aload_2
    //   570: getstatic net/portswigger/Zkd.UNKNOWN : Lnet/portswigger/Zkd;
    //   573: invokevirtual contains : (Ljava/lang/Object;)Z
    //   576: ifeq -> 584
    //   579: getstatic net/portswigger/Zkd.UNKNOWN : Lnet/portswigger/Zkd;
    //   582: astore #4
    //   584: iload_0
    //   585: bipush #46
    //   587: if_icmpne -> 609
    //   590: aload_2
    //   591: getstatic net/portswigger/Zkd.DOT : Lnet/portswigger/Zkd;
    //   594: invokevirtual contains : (Ljava/lang/Object;)Z
    //   597: ifeq -> 967
    //   600: getstatic net/portswigger/Zkd.DOT : Lnet/portswigger/Zkd;
    //   603: astore #4
    //   605: iload_3
    //   606: ifeq -> 967
    //   609: iload_0
    //   610: bipush #58
    //   612: if_icmpne -> 634
    //   615: aload_2
    //   616: getstatic net/portswigger/Zkd.COLON : Lnet/portswigger/Zkd;
    //   619: invokevirtual contains : (Ljava/lang/Object;)Z
    //   622: ifeq -> 967
    //   625: getstatic net/portswigger/Zkd.COLON : Lnet/portswigger/Zkd;
    //   628: astore #4
    //   630: iload_3
    //   631: ifeq -> 967
    //   634: iload_0
    //   635: bipush #123
    //   637: if_icmpne -> 659
    //   640: aload_2
    //   641: getstatic net/portswigger/Zkd.VARIABLE_START : Lnet/portswigger/Zkd;
    //   644: invokevirtual contains : (Ljava/lang/Object;)Z
    //   647: ifeq -> 967
    //   650: getstatic net/portswigger/Zkd.VARIABLE_START : Lnet/portswigger/Zkd;
    //   653: astore #4
    //   655: iload_3
    //   656: ifeq -> 967
    //   659: iload_0
    //   660: bipush #44
    //   662: if_icmpne -> 684
    //   665: aload_2
    //   666: getstatic net/portswigger/Zkd.COMMA : Lnet/portswigger/Zkd;
    //   669: invokevirtual contains : (Ljava/lang/Object;)Z
    //   672: ifeq -> 967
    //   675: getstatic net/portswigger/Zkd.COMMA : Lnet/portswigger/Zkd;
    //   678: astore #4
    //   680: iload_3
    //   681: ifeq -> 967
    //   684: iload_0
    //   685: bipush #48
    //   687: if_icmplt -> 715
    //   690: iload_0
    //   691: bipush #57
    //   693: if_icmpgt -> 715
    //   696: aload_2
    //   697: getstatic net/portswigger/Zkd.NATURAL_NUMBER : Lnet/portswigger/Zkd;
    //   700: invokevirtual contains : (Ljava/lang/Object;)Z
    //   703: ifeq -> 967
    //   706: getstatic net/portswigger/Zkd.NATURAL_NUMBER : Lnet/portswigger/Zkd;
    //   709: astore #4
    //   711: iload_3
    //   712: ifeq -> 967
    //   715: iload_0
    //   716: bipush #41
    //   718: if_icmpne -> 740
    //   721: aload_2
    //   722: getstatic net/portswigger/Zkd.CLOSE_BRACKET : Lnet/portswigger/Zkd;
    //   725: invokevirtual contains : (Ljava/lang/Object;)Z
    //   728: ifeq -> 967
    //   731: getstatic net/portswigger/Zkd.CLOSE_BRACKET : Lnet/portswigger/Zkd;
    //   734: astore #4
    //   736: iload_3
    //   737: ifeq -> 967
    //   740: iload_0
    //   741: bipush #40
    //   743: if_icmpne -> 765
    //   746: aload_2
    //   747: getstatic net/portswigger/Zkd.OPEN_BRACKET : Lnet/portswigger/Zkd;
    //   750: invokevirtual contains : (Ljava/lang/Object;)Z
    //   753: ifeq -> 967
    //   756: getstatic net/portswigger/Zkd.OPEN_BRACKET : Lnet/portswigger/Zkd;
    //   759: astore #4
    //   761: iload_3
    //   762: ifeq -> 967
    //   765: iload_0
    //   766: bipush #34
    //   768: if_icmpne -> 790
    //   771: aload_2
    //   772: getstatic net/portswigger/Zkd.LITERAL_STRING_OPENING_QUOTE : Lnet/portswigger/Zkd;
    //   775: invokevirtual contains : (Ljava/lang/Object;)Z
    //   778: ifeq -> 967
    //   781: getstatic net/portswigger/Zkd.LITERAL_STRING_OPENING_QUOTE : Lnet/portswigger/Zkd;
    //   784: astore #4
    //   786: iload_3
    //   787: ifeq -> 967
    //   790: iload_0
    //   791: bipush #96
    //   793: if_icmpne -> 815
    //   796: aload_2
    //   797: getstatic net/portswigger/Zkd.INTERPOLATABLE_STRING_OPENING_QUOTE : Lnet/portswigger/Zkd;
    //   800: invokevirtual contains : (Ljava/lang/Object;)Z
    //   803: ifeq -> 967
    //   806: getstatic net/portswigger/Zkd.INTERPOLATABLE_STRING_OPENING_QUOTE : Lnet/portswigger/Zkd;
    //   809: astore #4
    //   811: iload_3
    //   812: ifeq -> 967
    //   815: iload_0
    //   816: bipush #10
    //   818: if_icmpne -> 840
    //   821: aload_2
    //   822: getstatic net/portswigger/Zkd.NEWLINE : Lnet/portswigger/Zkd;
    //   825: invokevirtual contains : (Ljava/lang/Object;)Z
    //   828: ifeq -> 967
    //   831: getstatic net/portswigger/Zkd.NEWLINE : Lnet/portswigger/Zkd;
    //   834: astore #4
    //   836: iload_3
    //   837: ifeq -> 967
    //   840: iload_0
    //   841: bipush #35
    //   843: if_icmpne -> 871
    //   846: aload_1
    //   847: bipush #100
    //   849: invokevirtual set : (I)V
    //   852: aload_2
    //   853: getstatic net/portswigger/Zkd.COMMENT : Lnet/portswigger/Zkd;
    //   856: invokevirtual contains : (Ljava/lang/Object;)Z
    //   859: ifeq -> 967
    //   862: getstatic net/portswigger/Zkd.COMMENT : Lnet/portswigger/Zkd;
    //   865: astore #4
    //   867: iload_3
    //   868: ifeq -> 967
    //   871: iload_0
    //   872: bipush #12
    //   874: if_icmpne -> 896
    //   877: aload_2
    //   878: getstatic net/portswigger/Zkd._TOKEN_4 : Lnet/portswigger/Zkd;
    //   881: invokevirtual contains : (Ljava/lang/Object;)Z
    //   884: ifeq -> 967
    //   887: getstatic net/portswigger/Zkd._TOKEN_4 : Lnet/portswigger/Zkd;
    //   890: astore #4
    //   892: iload_3
    //   893: ifeq -> 967
    //   896: iload_0
    //   897: bipush #13
    //   899: if_icmpne -> 921
    //   902: aload_2
    //   903: getstatic net/portswigger/Zkd._TOKEN_3 : Lnet/portswigger/Zkd;
    //   906: invokevirtual contains : (Ljava/lang/Object;)Z
    //   909: ifeq -> 967
    //   912: getstatic net/portswigger/Zkd._TOKEN_3 : Lnet/portswigger/Zkd;
    //   915: astore #4
    //   917: iload_3
    //   918: ifeq -> 967
    //   921: iload_0
    //   922: bipush #9
    //   924: if_icmpne -> 946
    //   927: aload_2
    //   928: getstatic net/portswigger/Zkd._TOKEN_2 : Lnet/portswigger/Zkd;
    //   931: invokevirtual contains : (Ljava/lang/Object;)Z
    //   934: ifeq -> 967
    //   937: getstatic net/portswigger/Zkd._TOKEN_2 : Lnet/portswigger/Zkd;
    //   940: astore #4
    //   942: iload_3
    //   943: ifeq -> 967
    //   946: iload_0
    //   947: bipush #32
    //   949: if_icmpne -> 967
    //   952: aload_2
    //   953: getstatic net/portswigger/Zkd._TOKEN_1 : Lnet/portswigger/Zkd;
    //   956: invokevirtual contains : (Ljava/lang/Object;)Z
    //   959: ifeq -> 967
    //   962: getstatic net/portswigger/Zkd._TOKEN_1 : Lnet/portswigger/Zkd;
    //   965: astore #4
    //   967: aload #4
    //   969: areturn
  }
  
  private static Zkd Z_g(int paramInt, BitSet paramBitSet, EnumSet<Zkd> paramEnumSet) {
    Zkd zkd = null;
    if (paramInt == 114)
      paramBitSet.set(153); 
    return zkd;
  }
  
  private static Zkd ZNt(int paramInt, BitSet paramBitSet, EnumSet<Zkd> paramEnumSet) {
    Zkd zkd = null;
    if (paramInt == 101)
      paramBitSet.set(195); 
    return zkd;
  }
  
  private static Zkd Z_C(int paramInt, BitSet paramBitSet, EnumSet<Zkd> paramEnumSet) {
    Zkd zkd = null;
    if (paramInt == 116)
      paramBitSet.set(161); 
    return zkd;
  }
  
  private static Zkd ZNN(int paramInt, BitSet paramBitSet, EnumSet<Zkd> paramEnumSet) {
    Zkd zkd = null;
    if (paramInt == 103 && paramEnumSet.contains(Zkd.REMOVING))
      zkd = Zkd.REMOVING; 
    return zkd;
  }
  
  private static Zkd ZNP(int paramInt, BitSet paramBitSet, EnumSet<Zkd> paramEnumSet) {
    Zkd zkd = null;
    if (paramInt == 102 && paramEnumSet.contains(Zkd.IF_FOOTER))
      zkd = Zkd.IF_FOOTER; 
    return zkd;
  }
  
  private static Zkd Zr(int paramInt, BitSet paramBitSet, EnumSet<Zkd> paramEnumSet) {
    Zkd zkd = null;
    if (paramInt >= 48 && paramInt <= 57) {
      paramBitSet.set(181);
      paramBitSet.set(108);
      paramBitSet.set(41);
      paramBitSet.set(28);
      if (paramEnumSet.contains(Zkd.NATURAL_NUMBER))
        zkd = Zkd.NATURAL_NUMBER; 
    } 
    return zkd;
  }
  
  private static Zkd Zyf(int paramInt, BitSet paramBitSet, EnumSet<Zkd> paramEnumSet) {
    Zkd zkd = null;
    if (paramInt == 117)
      paramBitSet.set(132); 
    return zkd;
  }
  
  private static Zkd Zs(int paramInt, BitSet paramBitSet, EnumSet<Zkd> paramEnumSet) {
    Zkd zkd = null;
    if (paramInt == 117)
      paramBitSet.set(206); 
    return zkd;
  }
  
  private static Zkd ZNO(int paramInt, BitSet paramBitSet, EnumSet<Zkd> paramEnumSet) {
    Zkd zkd = null;
    if (paramInt == 105)
      paramBitSet.set(200); 
    return zkd;
  }
  
  private static Zkd ZyQ(int paramInt, BitSet paramBitSet, EnumSet<Zkd> paramEnumSet) {
    Zkd zkd = null;
    if (paramInt == 99)
      paramBitSet.set(49); 
    return zkd;
  }
  
  private static Zkd Z_i(int paramInt, BitSet paramBitSet, EnumSet<Zkd> paramEnumSet) {
    Zkd zkd = null;
    if (paramInt == 100 && paramEnumSet.contains(Zkd.SEND))
      zkd = Zkd.SEND; 
    return zkd;
  }
  
  private static Zkd Zyh(int paramInt, BitSet paramBitSet, EnumSet<Zkd> paramEnumSet) {
    Zkd zkd = null;
    if (paramInt == 116 && paramEnumSet.contains(Zkd.BOOL_NOT))
      zkd = Zkd.BOOL_NOT; 
    return zkd;
  }
  
  private static Zkd ZNm(int paramInt, BitSet paramBitSet, EnumSet<Zkd> paramEnumSet) {
    Zkd zkd = null;
    if (paramInt == 101)
      paramBitSet.set(19); 
    return zkd;
  }
  
  private static Zkd Z_2(int paramInt, BitSet paramBitSet, EnumSet<Zkd> paramEnumSet) {
    Zkd zkd = null;
    if (paramInt == 116)
      paramBitSet.set(217); 
    return zkd;
  }
  
  private static Zkd Z_k(int paramInt, BitSet paramBitSet, EnumSet<Zkd> paramEnumSet) {
    Zkd zkd = null;
    if (paramInt == 101)
      paramBitSet.set(140); 
    return zkd;
  }
  
  private static Zkd ZyU(int paramInt, BitSet paramBitSet, EnumSet<Zkd> paramEnumSet) {
    Zkd zkd = null;
    if (paramInt == 100)
      paramBitSet.set(9); 
    return zkd;
  }
  
  private static Zkd ZNI(int paramInt, BitSet paramBitSet, EnumSet<Zkd> paramEnumSet) {
    Zkd zkd = null;
    if (paramInt == 97)
      paramBitSet.set(220); 
    return zkd;
  }
  
  private static Zkd ZyZ(int paramInt, BitSet paramBitSet, EnumSet<Zkd> paramEnumSet) {
    Zkd zkd = null;
    if (paramInt == 109)
      paramBitSet.set(67); 
    return zkd;
  }
  
  private static Zkd Zy1(int paramInt, BitSet paramBitSet, EnumSet<Zkd> paramEnumSet) {
    Zkd zkd = null;
    if (paramInt == 112)
      paramBitSet.set(85); 
    return zkd;
  }
  
  private static Zkd ZX(int paramInt, BitSet paramBitSet, EnumSet<Zkd> paramEnumSet) {
    Zkd zkd = null;
    if (paramInt == 115)
      paramBitSet.set(160); 
    return zkd;
  }
  
  private static Zkd Z_n(int paramInt, BitSet paramBitSet, EnumSet<Zkd> paramEnumSet) {
    Zkd zkd = null;
    if (paramInt == 105)
      paramBitSet.set(117); 
    return zkd;
  }
  
  private static Zkd ZyW(int paramInt, BitSet paramBitSet, EnumSet<Zkd> paramEnumSet) {
    Zkd zkd = null;
    if (paramInt == 97)
      paramBitSet.set(212); 
    return zkd;
  }
  
  private static Zkd Zyi(int paramInt, BitSet paramBitSet, EnumSet<Zkd> paramEnumSet) {
    Zkd zkd = null;
    if (paramInt == 116)
      paramBitSet.set(99); 
    return zkd;
  }
  
  private static Zkd Zy9(int paramInt, BitSet paramBitSet, EnumSet<Zkd> paramEnumSet) {
    Zkd zkd = null;
    if (paramInt == 101)
      paramBitSet.set(107); 
    return zkd;
  }
  
  private static Zkd Zyn(int paramInt, BitSet paramBitSet, EnumSet<Zkd> paramEnumSet) {
    Zkd zkd = null;
    if (paramInt == 110 && paramEnumSet.contains(Zkd.IN_KEY))
      zkd = Zkd.IN_KEY; 
    return zkd;
  }
  
  private static Zkd ZyR(int paramInt, BitSet paramBitSet, EnumSet<Zkd> paramEnumSet) {
    Zkd zkd = null;
    if (paramInt == 102)
      paramBitSet.set(164); 
    return zkd;
  }
  
  private static Zkd ZNa(int paramInt, BitSet paramBitSet, EnumSet<Zkd> paramEnumSet) {
    Zkd zkd = null;
    if (paramInt == 115)
      paramBitSet.set(192); 
    return zkd;
  }
  
  private static Zkd Z_m(int paramInt, BitSet paramBitSet, EnumSet<Zkd> paramEnumSet) {
    Zkd zkd = null;
    if (paramInt >= 48 && paramInt <= 57) {
      paramBitSet.set(181);
      paramBitSet.set(108);
      if (paramEnumSet.contains(Zkd.NATURAL_NUMBER))
        zkd = Zkd.NATURAL_NUMBER; 
    } 
    return zkd;
  }
  
  private static Zkd Zy3(int paramInt, BitSet paramBitSet, EnumSet<Zkd> paramEnumSet) {
    Zkd zkd = null;
    if (paramInt == 101 && paramEnumSet.contains(Zkd.CONFIDENCE_HEADER))
      zkd = Zkd.CONFIDENCE_HEADER; 
    return zkd;
  }
  
  private static Zkd ZNp(int paramInt, BitSet paramBitSet, EnumSet<Zkd> paramEnumSet) {
    Zkd zkd = null;
    if (paramInt == 111)
      paramBitSet.set(208); 
    return zkd;
  }
  
  private static Zkd Z_R(int paramInt, BitSet paramBitSet, EnumSet<Zkd> paramEnumSet) {
    Zkd zkd = null;
    if (paramInt == 116)
      paramBitSet.set(78); 
    return zkd;
  }
  
  private static Zkd ZyA(int paramInt, BitSet paramBitSet, EnumSet<Zkd> paramEnumSet) {
    Zkd zkd = null;
    if (paramInt == 115 && paramEnumSet.contains(Zkd.INTERACTIONS_KEY))
      zkd = Zkd.INTERACTIONS_KEY; 
    return zkd;
  }
  
  private static Zkd ZNn(int paramInt, BitSet paramBitSet, EnumSet<Zkd> paramEnumSet) {
    Zkd zkd = null;
    if (paramInt == 100)
      paramBitSet.set(92); 
    return zkd;
  }
  
  private static Zkd Z_j(int paramInt, BitSet paramBitSet, EnumSet<Zkd> paramEnumSet) {
    Zkd zkd = null;
    if (paramInt == 105)
      paramBitSet.set(14); 
    return zkd;
  }
  
  private static Zkd ZN2(int paramInt, BitSet paramBitSet, EnumSet<Zkd> paramEnumSet) {
    Zkd zkd = null;
    if (paramInt == 116)
      paramBitSet.set(66); 
    return zkd;
  }
  
  private static Zkd ZNC(int paramInt, BitSet paramBitSet, EnumSet<Zkd> paramEnumSet) {
    Zkd zkd = null;
    if (paramInt == 116)
      paramBitSet.set(123); 
    return zkd;
  }
  
  private static Zkd ZD(int paramInt, BitSet paramBitSet, EnumSet<Zkd> paramEnumSet) {
    Zkd zkd = null;
    if (paramInt == 116)
      paramBitSet.set(216); 
    return zkd;
  }
  
  private static Zkd ZN4(int paramInt, BitSet paramBitSet, EnumSet<Zkd> paramEnumSet) {
    Zkd zkd = null;
    if (paramInt == 104 && paramEnumSet.contains(Zkd.HIGH_SEVERITY))
      zkd = Zkd.HIGH_SEVERITY; 
    return zkd;
  }
  
  private static Zkd ZyS(int paramInt, BitSet paramBitSet, EnumSet<Zkd> paramEnumSet) {
    Zkd zkd = null;
    if (paramInt == 101)
      paramBitSet.set(149); 
    return zkd;
  }
  
  private static Zkd Zn(int paramInt, BitSet paramBitSet, EnumSet<Zkd> paramEnumSet) {
    Zkd zkd = null;
    if (paramInt == 103 && paramEnumSet.contains(Zkd.APPENDING))
      zkd = Zkd.APPENDING; 
    return zkd;
  }
  
  private static Zkd ZNW(int paramInt, BitSet paramBitSet, EnumSet<Zkd> paramEnumSet) {
    Zkd zkd = null;
    if (paramInt >= 48 && paramInt <= 57) {
      paramBitSet.set(181);
      paramBitSet.set(108);
      paramBitSet.set(28);
      if (paramEnumSet.contains(Zkd.NATURAL_NUMBER))
        zkd = Zkd.NATURAL_NUMBER; 
    } 
    return zkd;
  }
  
  private static Zkd Z_(int paramInt, BitSet paramBitSet, EnumSet<Zkd> paramEnumSet) {
    Zkd zkd = null;
    if (paramInt == 97)
      paramBitSet.set(80); 
    return zkd;
  }
  
  private static Zkd Zf(int paramInt, BitSet paramBitSet, EnumSet<Zkd> paramEnumSet) {
    Zkd zkd = null;
    if (paramInt == 110)
      paramBitSet.set(11); 
    return zkd;
  }
  
  private static Zkd ZI(int paramInt, BitSet paramBitSet, EnumSet<Zkd> paramEnumSet) {
    Zkd zkd = null;
    if (paramInt == 105)
      paramBitSet.set(55); 
    return zkd;
  }
  
  private static Zkd Z_e(int paramInt, BitSet paramBitSet, EnumSet<Zkd> paramEnumSet) {
    Zkd zkd = null;
    if (paramInt == 121 && paramEnumSet.contains(Zkd.ANY_KEY))
      zkd = Zkd.ANY_KEY; 
    return zkd;
  }
  
  private static Zkd Zyb(int paramInt, BitSet paramBitSet, EnumSet<Zkd> paramEnumSet) {
    Zkd zkd = null;
    if (paramInt == 121 && paramEnumSet.contains(Zkd.BODY))
      zkd = Zkd.BODY; 
    return zkd;
  }
  
  private static Zkd ZN_(int paramInt, BitSet paramBitSet, EnumSet<Zkd> paramEnumSet) {
    Zkd zkd = null;
    if (paramInt == 116)
      paramBitSet.set(1); 
    return zkd;
  }
  
  private static Zkd ZyK(int paramInt, BitSet paramBitSet, EnumSet<Zkd> paramEnumSet) {
    Zkd zkd = null;
    if (paramInt == 100)
      paramBitSet.set(141); 
    return zkd;
  }
  
  private static Zkd Z_Q(int paramInt, BitSet paramBitSet, EnumSet<Zkd> paramEnumSet) {
    Zkd zkd = null;
    if (paramInt == 116)
      paramBitSet.set(130); 
    return zkd;
  }
  
  private static Zkd Z_l(int paramInt, BitSet paramBitSet, EnumSet<Zkd> paramEnumSet) {
    Zkd zkd = null;
    if (paramInt == 102)
      paramBitSet.set(198); 
    return zkd;
  }
  
  private static Zkd Zyv(int paramInt, BitSet paramBitSet, EnumSet<Zkd> paramEnumSet) {
    Zkd zkd = null;
    if (paramInt == 101)
      paramBitSet.set(18); 
    return zkd;
  }
  
  private static Zkd ZNx(int paramInt, BitSet paramBitSet, EnumSet<Zkd> paramEnumSet) {
    Zkd zkd = null;
    if (paramInt == 101 && paramEnumSet.contains(Zkd.ELSE_HEADER))
      zkd = Zkd.ELSE_HEADER; 
    return zkd;
  }
  
  private static Zkd ZY(int paramInt, BitSet paramBitSet, EnumSet<Zkd> paramEnumSet) {
    Zkd zkd = null;
    if (paramInt == 101)
      paramBitSet.set(167); 
    return zkd;
  }
  
  private static Zkd Za(int paramInt, BitSet paramBitSet, EnumSet<Zkd> paramEnumSet) {
    Zkd zkd = null;
    if (paramInt == 111 && paramEnumSet.contains(Zkd.INFO_SEVERITY))
      zkd = Zkd.INFO_SEVERITY; 
    return zkd;
  }
  
  private static Zkd ZyJ(int paramInt, BitSet paramBitSet, EnumSet<Zkd> paramEnumSet) {
    Zkd zkd = null;
    if (paramInt == 115)
      paramBitSet.set(215); 
    return zkd;
  }
  
  private static Zkd Zym(int paramInt, BitSet paramBitSet, EnumSet<Zkd> paramEnumSet) {
    Zkd zkd = null;
    if (paramInt == 99)
      paramBitSet.set(29); 
    return zkd;
  }
  
  private static Zkd ZNk(int paramInt, BitSet paramBitSet, EnumSet<Zkd> paramEnumSet) {
    Zkd zkd = null;
    if (paramInt == 105)
      paramBitSet.set(148); 
    return zkd;
  }
  
  private static Zkd ZA(int paramInt, BitSet paramBitSet, EnumSet<Zkd> paramEnumSet) {
    Zkd zkd = null;
    if (paramInt == 109)
      paramBitSet.set(37); 
    return zkd;
  }
  
  private static Zkd ZNg(int paramInt, BitSet paramBitSet, EnumSet<Zkd> paramEnumSet) {
    Zkd zkd = null;
    if (paramInt == 101)
      paramBitSet.set(152); 
    return zkd;
  }
  
  private static Zkd Z_X(int paramInt, BitSet paramBitSet, EnumSet<Zkd> paramEnumSet) {
    Zkd zkd = null;
    if (paramInt == 100)
      paramBitSet.set(15); 
    return zkd;
  }
  
  private static Zkd Zyw(int paramInt, BitSet paramBitSet, EnumSet<Zkd> paramEnumSet) {
    Zkd zkd = null;
    if (paramInt == 102)
      paramBitSet.set(145); 
    return zkd;
  }
  
  private static Zkd ZNf(int paramInt, BitSet paramBitSet, EnumSet<Zkd> paramEnumSet) {
    Zkd zkd = null;
    if (paramInt == 116)
      paramBitSet.set(98); 
    return zkd;
  }
  
  private static Zkd Z_f(int paramInt, BitSet paramBitSet, EnumSet<Zkd> paramEnumSet) {
    Zkd zkd = null;
    if (paramInt == 105)
      paramBitSet.set(5); 
    return zkd;
  }
  
  private static Zkd Z_U(int paramInt, BitSet paramBitSet, EnumSet<Zkd> paramEnumSet) {
    Zkd zkd = null;
    if (paramInt == 113)
      paramBitSet.set(8); 
    return zkd;
  }
  
  private static Zkd Zys(int paramInt, BitSet paramBitSet, EnumSet<Zkd> paramEnumSet) {
    Zkd zkd = null;
    if (paramInt == 115 && paramEnumSet.contains(Zkd.DNS_KEY))
      zkd = Zkd.DNS_KEY; 
    return zkd;
  }
  
  private static Zkd ZV(int paramInt, BitSet paramBitSet, EnumSet<Zkd> paramEnumSet) {
    Zkd zkd = null;
    if (paramInt == 97)
      paramBitSet.set(83); 
    return zkd;
  }
  
  private static Zkd Z_d(int paramInt, BitSet paramBitSet, EnumSet<Zkd> paramEnumSet) {
    Zkd zkd = null;
    if (paramInt == 111)
      paramBitSet.set(146); 
    return zkd;
  }
  
  private static Zkd Z_K(int paramInt, BitSet paramBitSet, EnumSet<Zkd> paramEnumSet) {
    Zkd zkd = null;
    if (paramInt == 110 && paramEnumSet.contains(Zkd.CERTAIN_CONFIDENCE))
      zkd = Zkd.CERTAIN_CONFIDENCE; 
    return zkd;
  }
  
  private static Zkd ZNo(int paramInt, BitSet paramBitSet, EnumSet<Zkd> paramEnumSet) {
    Zkd zkd = null;
    if (paramInt == 108 && paramEnumSet.contains(Zkd.DETAIL_HEADER))
      zkd = Zkd.DETAIL_HEADER; 
    return zkd;
  }
  
  private static Zkd ZNB(int paramInt, BitSet paramBitSet, EnumSet<Zkd> paramEnumSet) {
    Zkd zkd = null;
    if (paramInt == 101)
      paramBitSet.set(16); 
    return zkd;
  }
  
  private static Zkd Zz(int paramInt, BitSet paramBitSet, EnumSet<Zkd> paramEnumSet) {
    Zkd zkd = null;
    if (paramInt == 110)
      paramBitSet.set(95); 
    return zkd;
  }
  
  private static Zkd Zyr(int paramInt, BitSet paramBitSet, EnumSet<Zkd> paramEnumSet) {
    Zkd zkd = null;
    if (paramInt == 111)
      paramBitSet.set(12); 
    return zkd;
  }
  
  private static Zkd Z_s(int paramInt, BitSet paramBitSet, EnumSet<Zkd> paramEnumSet) {
    Zkd zkd = null;
    if (paramInt == 100 && paramEnumSet.contains(Zkd.BOOL_AND))
      zkd = Zkd.BOOL_AND; 
    return zkd;
  }
  
  private static Zkd Zy(int paramInt, BitSet paramBitSet, EnumSet<Zkd> paramEnumSet) {
    Zkd zkd = null;
    if (paramInt == 110)
      paramBitSet.set(73); 
    return zkd;
  }
  
  private static Zkd Zw(int paramInt, BitSet paramBitSet, EnumSet<Zkd> paramEnumSet) {
    Zkd zkd = null;
    if (paramInt == 121)
      paramBitSet.set(162); 
    return zkd;
  }
  
  private static Zkd ZyE(int paramInt, BitSet paramBitSet, EnumSet<Zkd> paramEnumSet) {
    Zkd zkd = null;
    if (paramInt == 105)
      paramBitSet.set(199); 
    return zkd;
  }
  
  private static Zkd ZT(int paramInt, BitSet paramBitSet, EnumSet<Zkd> paramEnumSet) {
    Zkd zkd = null;
    if (paramInt == 115 && paramEnumSet.contains(Zkd.HEADERS))
      zkd = Zkd.HEADERS; 
    return zkd;
  }
  
  private static Zkd ZN3(int paramInt, BitSet paramBitSet, EnumSet<Zkd> paramEnumSet) {
    Zkd zkd = null;
    if (paramInt == 101)
      paramBitSet.set(213); 
    return zkd;
  }
  
  private static Zkd Zyc(int paramInt, BitSet paramBitSet, EnumSet<Zkd> paramEnumSet) {
    Zkd zkd = null;
    if (paramInt == 97)
      paramBitSet.set(185); 
    return zkd;
  }
  
  private static Zkd ZH(int paramInt, BitSet paramBitSet, EnumSet<Zkd> paramEnumSet) {
    Zkd zkd = null;
    if (paramInt == 116)
      paramBitSet.set(173); 
    return zkd;
  }
  
  private static Zkd Z_Y(int paramInt, BitSet paramBitSet, EnumSet<Zkd> paramEnumSet) {
    Zkd zkd = null;
    if (paramInt == 114)
      paramBitSet.set(23); 
    return zkd;
  }
  
  private static Zkd ZNw(int paramInt, BitSet paramBitSet, EnumSet<Zkd> paramEnumSet) {
    Zkd zkd = null;
    if (paramInt == 105)
      paramBitSet.set(205); 
    return zkd;
  }
  
  private static Zkd Z_0(int paramInt, BitSet paramBitSet, EnumSet<Zkd> paramEnumSet) {
    Zkd zkd = null;
    if (paramInt == 105)
      paramBitSet.set(68); 
    return zkd;
  }
  
  private static Zkd Zya(int paramInt, BitSet paramBitSet, EnumSet<Zkd> paramEnumSet) {
    Zkd zkd = null;
    if (paramInt == 101)
      paramBitSet.set(135); 
    return zkd;
  }
  
  private static Zkd ZyI(int paramInt, BitSet paramBitSet, EnumSet<Zkd> paramEnumSet) {
    Zkd zkd = null;
    if (paramInt == 108)
      paramBitSet.set(17); 
    return zkd;
  }
  
  private static Zkd ZNU(int paramInt, BitSet paramBitSet, EnumSet<Zkd> paramEnumSet) {
    // Byte code:
    //   0: invokestatic Zy : ()Z
    //   3: aconst_null
    //   4: astore #4
    //   6: istore_3
    //   7: iload_0
    //   8: iflt -> 17
    //   11: iload_0
    //   12: bipush #9
    //   14: if_icmple -> 35
    //   17: iload_0
    //   18: bipush #11
    //   20: if_icmpeq -> 35
    //   23: iload_0
    //   24: bipush #12
    //   26: if_icmpeq -> 35
    //   29: iload_0
    //   30: bipush #14
    //   32: if_icmplt -> 45
    //   35: aload_1
    //   36: bipush #86
    //   38: invokevirtual set : (I)V
    //   41: iload_3
    //   42: ifeq -> 83
    //   45: iload_0
    //   46: bipush #13
    //   48: if_icmpne -> 62
    //   51: aload_1
    //   52: sipush #182
    //   55: invokevirtual set : (I)V
    //   58: iload_3
    //   59: ifeq -> 83
    //   62: iload_0
    //   63: bipush #10
    //   65: if_icmpne -> 83
    //   68: aload_2
    //   69: getstatic net/portswigger/Zkd._TOKEN_5 : Lnet/portswigger/Zkd;
    //   72: invokevirtual contains : (Ljava/lang/Object;)Z
    //   75: ifeq -> 83
    //   78: getstatic net/portswigger/Zkd._TOKEN_5 : Lnet/portswigger/Zkd;
    //   81: astore #4
    //   83: iload_0
    //   84: bipush #13
    //   86: if_icmpne -> 104
    //   89: aload_2
    //   90: getstatic net/portswigger/Zkd._TOKEN_5 : Lnet/portswigger/Zkd;
    //   93: invokevirtual contains : (Ljava/lang/Object;)Z
    //   96: ifeq -> 104
    //   99: getstatic net/portswigger/Zkd._TOKEN_5 : Lnet/portswigger/Zkd;
    //   102: astore #4
    //   104: aload #4
    //   106: areturn
  }
  
  private static Zkd Zyg(int paramInt, BitSet paramBitSet, EnumSet<Zkd> paramEnumSet) {
    Zkd zkd = null;
    if (paramInt == 104)
      paramBitSet.set(115); 
    return zkd;
  }
  
  private static Zkd Zye(int paramInt, BitSet paramBitSet, EnumSet<Zkd> paramEnumSet) {
    Zkd zkd = null;
    if (paramInt == 108)
      paramBitSet.set(97); 
    return zkd;
  }
  
  private static Zkd ZNj(int paramInt, BitSet paramBitSet, EnumSet<Zkd> paramEnumSet) {
    Zkd zkd = null;
    if (paramInt >= 48 && paramInt <= 57) {
      paramBitSet.set(181);
      paramBitSet.set(6);
      paramBitSet.set(108);
      paramBitSet.set(41);
      paramBitSet.set(28);
      if (paramEnumSet.contains(Zkd.NATURAL_NUMBER))
        zkd = Zkd.NATURAL_NUMBER; 
    } 
    return zkd;
  }
  
  private static Zkd Z_G(int paramInt, BitSet paramBitSet, EnumSet<Zkd> paramEnumSet) {
    Zkd zkd = null;
    if (paramInt == 105)
      paramBitSet.set(96); 
    return zkd;
  }
  
  private static Zkd Z_u(int paramInt, BitSet paramBitSet, EnumSet<Zkd> paramEnumSet) {
    Zkd zkd = null;
    if (paramInt == 101)
      paramBitSet.set(3); 
    return zkd;
  }
  
  private static Zkd ZE(int paramInt, BitSet paramBitSet, EnumSet<Zkd> paramEnumSet) {
    Zkd zkd = null;
    if (paramInt == 105)
      paramBitSet.set(151); 
    return zkd;
  }
  
  private static Zkd Z_A(int paramInt, BitSet paramBitSet, EnumSet<Zkd> paramEnumSet) {
    Zkd zkd = null;
    if (paramInt == 101)
      paramBitSet.set(109); 
    return zkd;
  }
  
  private static Zkd ZNc(int paramInt, BitSet paramBitSet, EnumSet<Zkd> paramEnumSet) {
    Zkd zkd = null;
    if (paramInt == 114)
      paramBitSet.set(154); 
    return zkd;
  }
  
  private static Zkd Z_O(int paramInt, BitSet paramBitSet, EnumSet<Zkd> paramEnumSet) {
    Zkd zkd = null;
    if (paramInt == 116)
      paramBitSet.set(42); 
    return zkd;
  }
  
  private static Zkd ZNl(int paramInt, BitSet paramBitSet, EnumSet<Zkd> paramEnumSet) {
    Zkd zkd = null;
    if (paramInt == 103)
      paramBitSet.set(38); 
    return zkd;
  }
  
  private static Zkd ZNd(int paramInt, BitSet paramBitSet, EnumSet<Zkd> paramEnumSet) {
    Zkd zkd = null;
    if (paramInt == 115)
      paramBitSet.set(52); 
    return zkd;
  }
  
  private static Zkd Zo(int paramInt, BitSet paramBitSet, EnumSet<Zkd> paramEnumSet) {
    Zkd zkd = null;
    if (paramInt == 105)
      paramBitSet.set(105); 
    return zkd;
  }
  
  private static Zkd Zy2(int paramInt, BitSet paramBitSet, EnumSet<Zkd> paramEnumSet) {
    Zkd zkd = null;
    if (paramInt == 32)
      paramBitSet.set(44); 
    return zkd;
  }
  
  private static Zkd ZNL(int paramInt, BitSet paramBitSet, EnumSet<Zkd> paramEnumSet) {
    Zkd zkd = null;
    if ((paramInt >= 0 && paramInt <= 9) || paramInt == 11 || paramInt == 12 || paramInt >= 14) {
      paramBitSet.set(100);
      if (paramEnumSet.contains(Zkd.COMMENT))
        zkd = Zkd.COMMENT; 
    } 
    return zkd;
  }
  
  private static Zkd ZN(int paramInt, BitSet paramBitSet, EnumSet<Zkd> paramEnumSet) {
    Zkd zkd = null;
    if (paramInt == 110)
      paramBitSet.set(138); 
    return zkd;
  }
  
  private static Zkd Z_S(int paramInt, BitSet paramBitSet, EnumSet<Zkd> paramEnumSet) {
    Zkd zkd = null;
    if (paramInt == 110)
      paramBitSet.set(210); 
    return zkd;
  }
  
  private static Zkd ZNy(int paramInt, BitSet paramBitSet, EnumSet<Zkd> paramEnumSet) {
    Zkd zkd = null;
    if (paramInt == 108)
      paramBitSet.set(201); 
    return zkd;
  }
  
  private static Zkd ZND(int paramInt, BitSet paramBitSet, EnumSet<Zkd> paramEnumSet) {
    Zkd zkd = null;
    if (paramInt == 111)
      paramBitSet.set(170); 
    return zkd;
  }
  
  private static Zkd Zy_(int paramInt, BitSet paramBitSet, EnumSet<Zkd> paramEnumSet) {
    Zkd zkd = null;
    if (paramInt == 111)
      paramBitSet.set(111); 
    return zkd;
  }
  
  private static Zkd ZN1(int paramInt, BitSet paramBitSet, EnumSet<Zkd> paramEnumSet) {
    Zkd zkd = null;
    if (paramInt == 109)
      paramBitSet.set(174); 
    return zkd;
  }
  
  private static Zkd ZN5(int paramInt, BitSet paramBitSet, EnumSet<Zkd> paramEnumSet) {
    Zkd zkd = null;
    if (paramInt == 114)
      paramBitSet.set(35); 
    return zkd;
  }
  
  private static Zkd Zy6(int paramInt, BitSet paramBitSet, EnumSet<Zkd> paramEnumSet) {
    Zkd zkd = null;
    if (paramInt >= 48 && paramInt <= 57 && paramEnumSet.contains(Zkd.NATURAL_NUMBER))
      zkd = Zkd.NATURAL_NUMBER; 
    return zkd;
  }
  
  private static Zkd Zt(int paramInt, BitSet paramBitSet, EnumSet<Zkd> paramEnumSet) {
    Zkd zkd = null;
    if (paramInt == 100 && paramEnumSet.contains(Zkd.CALLED))
      zkd = Zkd.CALLED; 
    return zkd;
  }
  
  private static Zkd ZNS(int paramInt, BitSet paramBitSet, EnumSet<Zkd> paramEnumSet) {
    Zkd zkd = null;
    if (paramInt == 110)
      paramBitSet.set(129); 
    return zkd;
  }
  
  private static Zkd ZZ(int paramInt, BitSet paramBitSet, EnumSet<Zkd> paramEnumSet) {
    Zkd zkd = null;
    if (paramInt == 110 && paramEnumSet.contains(Zkd.REMEDIATION_HEADER))
      zkd = Zkd.REMEDIATION_HEADER; 
    return zkd;
  }
  
  private static Zkd Zh(int paramInt, BitSet paramBitSet, EnumSet<Zkd> paramEnumSet) {
    Zkd zkd = null;
    if (paramInt == 105)
      paramBitSet.set(101); 
    return zkd;
  }
  
  private static Zkd Zyq(int paramInt, BitSet paramBitSet, EnumSet<Zkd> paramEnumSet) {
    Zkd zkd = null;
    if (paramInt == 112)
      paramBitSet.set(155); 
    return zkd;
  }
  
  private static Zkd ZNR(int paramInt, BitSet paramBitSet, EnumSet<Zkd> paramEnumSet) {
    Zkd zkd = null;
    if (paramInt == 112 && paramEnumSet.contains(Zkd.HTTP_KEY))
      zkd = Zkd.HTTP_KEY; 
    return zkd;
  }
  
  private static Zkd ZyG(int paramInt, BitSet paramBitSet, EnumSet<Zkd> paramEnumSet) {
    Zkd zkd = null;
    if (paramInt == 101)
      paramBitSet.set(158); 
    return zkd;
  }
  
  private static Zkd ZNi(int paramInt, BitSet paramBitSet, EnumSet<Zkd> paramEnumSet) {
    Zkd zkd = null;
    if (paramInt == 101 && paramEnumSet.contains(Zkd.AND_CONTINUE))
      zkd = Zkd.AND_CONTINUE; 
    return zkd;
  }
  
  private static Zkd ZyM(int paramInt, BitSet paramBitSet, EnumSet<Zkd> paramEnumSet) {
    Zkd zkd = null;
    if (paramInt == 117)
      paramBitSet.set(166); 
    return zkd;
  }
  
  private static Zkd Zyk(int paramInt, BitSet paramBitSet, EnumSet<Zkd> paramEnumSet) {
    Zkd zkd = null;
    if (paramInt == 103 && paramEnumSet.contains(Zkd.QUERY_STRING))
      zkd = Zkd.QUERY_STRING; 
    return zkd;
  }
  
  private static Zkd ZF(int paramInt, BitSet paramBitSet, EnumSet<Zkd> paramEnumSet) {
    Zkd zkd = null;
    if (paramInt >= 48 && paramInt <= 57) {
      paramBitSet.set(119);
      if (paramEnumSet.contains(Zkd.UNKNOWN_STRING))
        zkd = Zkd.UNKNOWN_STRING; 
    } else if ((paramInt >= 65 && paramInt <= 90) || paramInt == 95 || (paramInt >= 97 && paramInt <= 122)) {
      paramBitSet.set(119);
      if (paramEnumSet.contains(Zkd.UNKNOWN_STRING))
        zkd = Zkd.UNKNOWN_STRING; 
    } 
    return zkd;
  }
  
  private static Zkd ZNq(int paramInt, BitSet paramBitSet, EnumSet<Zkd> paramEnumSet) {
    Zkd zkd = null;
    if (paramInt == 115 && paramEnumSet.contains(Zkd.IS_KEY))
      zkd = Zkd.IS_KEY; 
    return zkd;
  }
  
  private static Zkd Zy0(int paramInt, BitSet paramBitSet, EnumSet<Zkd> paramEnumSet) {
    Zkd zkd = null;
    if (paramInt == 110)
      paramBitSet.set(187); 
    return zkd;
  }
  
  private static Zkd ZyH(int paramInt, BitSet paramBitSet, EnumSet<Zkd> paramEnumSet) {
    Zkd zkd = null;
    if (paramInt == 114)
      paramBitSet.set(27); 
    return zkd;
  }
  
  private static Zkd Z_y(int paramInt, BitSet paramBitSet, EnumSet<Zkd> paramEnumSet) {
    Zkd zkd = null;
    if (paramInt == 104 && paramEnumSet.contains(Zkd.PATH))
      zkd = Zkd.PATH; 
    return zkd;
  }
  
  private static Zkd ZO(int paramInt, BitSet paramBitSet, EnumSet<Zkd> paramEnumSet) {
    Zkd zkd = null;
    if (paramInt == 112)
      paramBitSet.set(127); 
    return zkd;
  }
  
  private static Zkd Z_6(int paramInt, BitSet paramBitSet, EnumSet<Zkd> paramEnumSet) {
    Zkd zkd = null;
    if (paramInt == 97)
      paramBitSet.set(103); 
    return zkd;
  }
  
  private static Zkd Z_4(int paramInt, BitSet paramBitSet, EnumSet<Zkd> paramEnumSet) {
    Zkd zkd = null;
    if (paramInt == 110)
      paramBitSet.set(172); 
    return zkd;
  }
  
  private static Zkd ZNV(int paramInt, BitSet paramBitSet, EnumSet<Zkd> paramEnumSet) {
    Zkd zkd = null;
    if (paramInt == 111)
      paramBitSet.set(81); 
    return zkd;
  }
  
  private static Zkd Zl(int paramInt, BitSet paramBitSet, EnumSet<Zkd> paramEnumSet) {
    Zkd zkd = null;
    if (paramInt == 114)
      paramBitSet.set(77); 
    return zkd;
  }
  
  private static Zkd ZNb(int paramInt, BitSet paramBitSet, EnumSet<Zkd> paramEnumSet) {
    Zkd zkd = null;
    if (paramInt == 116)
      paramBitSet.set(112); 
    return zkd;
  }
  
  private static Zkd ZyP(int paramInt, BitSet paramBitSet, EnumSet<Zkd> paramEnumSet) {
    Zkd zkd = null;
    if (paramInt == 105)
      paramBitSet.set(104); 
    return zkd;
  }
  
  private static Zkd ZNh(int paramInt, BitSet paramBitSet, EnumSet<Zkd> paramEnumSet) {
    Zkd zkd = null;
    if (paramInt == 109 && paramEnumSet.contains(Zkd.DIFFERS_FROM_KEY))
      zkd = Zkd.DIFFERS_FROM_KEY; 
    return zkd;
  }
  
  private static Zkd Z_Z(int paramInt, BitSet paramBitSet, EnumSet<Zkd> paramEnumSet) {
    Zkd zkd = null;
    if (paramInt == 101 && paramEnumSet.contains(Zkd.REPORT_ISSUE_HEADER))
      zkd = Zkd.REPORT_ISSUE_HEADER; 
    return zkd;
  }
  
  private static Zkd Ze(int paramInt, BitSet paramBitSet, EnumSet<Zkd> paramEnumSet) {
    Zkd zkd = null;
    if (paramInt == 101)
      paramBitSet.set(163); 
    return zkd;
  }
  
  private static Zkd Z_z(int paramInt, BitSet paramBitSet, EnumSet<Zkd> paramEnumSet) {
    Zkd zkd = null;
    if (paramInt == 111)
      paramBitSet.set(131); 
    return zkd;
  }
  
  private static Zkd Zi(int paramInt, BitSet paramBitSet, EnumSet<Zkd> paramEnumSet) {
    Zkd zkd = null;
    if (paramInt == 115 && paramEnumSet.contains(Zkd.QUERIES))
      zkd = Zkd.QUERIES; 
    return zkd;
  }
  
  private static Zkd ZU(int paramInt, BitSet paramBitSet, EnumSet<Zkd> paramEnumSet) {
    Zkd zkd = null;
    if (paramInt == 101)
      paramBitSet.set(128); 
    return zkd;
  }
  
  private static Zkd ZK(int paramInt, BitSet paramBitSet, EnumSet<Zkd> paramEnumSet) {
    Zkd zkd = null;
    if (paramInt == 105)
      paramBitSet.set(102); 
    return zkd;
  }
  
  private static Zkd Z_N(int paramInt, BitSet paramBitSet, EnumSet<Zkd> paramEnumSet) {
    Zkd zkd = null;
    if (paramInt == 117)
      paramBitSet.set(116); 
    return zkd;
  }
  
  private static Zkd ZyV(int paramInt, BitSet paramBitSet, EnumSet<Zkd> paramEnumSet) {
    Zkd zkd = null;
    if (paramInt == 110)
      paramBitSet.set(118); 
    return zkd;
  }
  
  private static Zkd Zyp(int paramInt, BitSet paramBitSet, EnumSet<Zkd> paramEnumSet) {
    Zkd zkd = null;
    if (paramInt == 110)
      paramBitSet.set(56); 
    return zkd;
  }
  
  private static Zkd ZyT(int paramInt, BitSet paramBitSet, EnumSet<Zkd> paramEnumSet) {
    Zkd zkd = null;
    if (paramInt == 32)
      paramBitSet.set(218); 
    return zkd;
  }
  
  private static Zkd ZyL(int paramInt, BitSet paramBitSet, EnumSet<Zkd> paramEnumSet) {
    Zkd zkd = null;
    if (paramInt == 100)
      paramBitSet.set(136); 
    return zkd;
  }
  
  private static Zkd Zy8(int paramInt, BitSet paramBitSet, EnumSet<Zkd> paramEnumSet) {
    Zkd zkd = null;
    if (paramInt == 110)
      paramBitSet.set(65); 
    return zkd;
  }
  
  private static Zkd Zyj(int paramInt, BitSet paramBitSet, EnumSet<Zkd> paramEnumSet) {
    Zkd zkd = null;
    if (paramInt == 101)
      paramBitSet.set(94); 
    return zkd;
  }
  
  private static Zkd ZNT(int paramInt, BitSet paramBitSet, EnumSet<Zkd> paramEnumSet) {
    Zkd zkd = null;
    if (paramInt == 105)
      paramBitSet.set(60); 
    return zkd;
  }
  
  private static Zkd Zd(int paramInt, BitSet paramBitSet, EnumSet<Zkd> paramEnumSet) {
    Zkd zkd = null;
    if (paramInt == 118)
      paramBitSet.set(76); 
    return zkd;
  }
  
  private static Zkd ZyN(int paramInt, BitSet paramBitSet, EnumSet<Zkd> paramEnumSet) {
    Zkd zkd = null;
    if (paramInt == 101)
      paramBitSet.set(43); 
    return zkd;
  }
  
  private static Zkd ZQ(int paramInt, BitSet paramBitSet, EnumSet<Zkd> paramEnumSet) {
    Zkd zkd = null;
    if (paramInt == 114)
      paramBitSet.set(204); 
    return zkd;
  }
  
  private static Zkd Z_H(int paramInt, BitSet paramBitSet, EnumSet<Zkd> paramEnumSet) {
    Zkd zkd = null;
    if (paramInt == 116)
      paramBitSet.set(79); 
    return zkd;
  }
  
  private static Zkd ZNK(int paramInt, BitSet paramBitSet, EnumSet<Zkd> paramEnumSet) {
    Zkd zkd = null;
    if (paramInt == 111)
      paramBitSet.set(157); 
    return zkd;
  }
  
  private static Zkd Z_9(int paramInt, BitSet paramBitSet, EnumSet<Zkd> paramEnumSet) {
    Zkd zkd = null;
    if (paramInt == 110)
      paramBitSet.set(40); 
    return zkd;
  }
  
  private static Zkd Zy5(int paramInt, BitSet paramBitSet, EnumSet<Zkd> paramEnumSet) {
    Zkd zkd = null;
    if (paramInt == 97)
      paramBitSet.set(142); 
    return zkd;
  }
  
  private static Zkd Zy4(int paramInt, BitSet paramBitSet, EnumSet<Zkd> paramEnumSet) {
    Zkd zkd = null;
    if (paramInt == 105)
      paramBitSet.set(139); 
    return zkd;
  }
  
  private static Zkd ZN7(int paramInt, BitSet paramBitSet, EnumSet<Zkd> paramEnumSet) {
    Zkd zkd = null;
    if (paramInt == 105)
      paramBitSet.set(84); 
    return zkd;
  }
  
  private static Zkd Zx(int paramInt, BitSet paramBitSet, EnumSet<Zkd> paramEnumSet) {
    Zkd zkd = null;
    if (paramInt == 112)
      paramBitSet.set(214); 
    return zkd;
  }
  
  private static Zkd Zyy(int paramInt, BitSet paramBitSet, EnumSet<Zkd> paramEnumSet) {
    Zkd zkd = null;
    if (paramInt == 101)
      paramBitSet.set(222); 
    return zkd;
  }
  
  private static Zkd ZB(int paramInt, BitSet paramBitSet, EnumSet<Zkd> paramEnumSet) {
    Zkd zkd = null;
    if (paramInt == 100 && paramEnumSet.contains(Zkd.METHOD))
      zkd = Zkd.METHOD; 
    return zkd;
  }
  
  private static Zkd ZyC(int paramInt, BitSet paramBitSet, EnumSet<Zkd> paramEnumSet) {
    Zkd zkd = null;
    if (paramInt == 115 && paramEnumSet.contains(Zkd.MATCHES_KEY))
      zkd = Zkd.MATCHES_KEY; 
    return zkd;
  }
  
  private static Zkd Z_P(int paramInt, BitSet paramBitSet, EnumSet<Zkd> paramEnumSet) {
    Zkd zkd = null;
    if (paramInt == 109)
      paramBitSet.set(70); 
    return zkd;
  }
  
  private static Zkd Z_3(int paramInt, BitSet paramBitSet, EnumSet<Zkd> paramEnumSet) {
    Zkd zkd = null;
    if (paramInt == 116 && paramEnumSet.contains(Zkd.REQUEST_HEADER))
      zkd = Zkd.REQUEST_HEADER; 
    return zkd;
  }
  
  private static Zkd Zp(int paramInt, BitSet paramBitSet, EnumSet<Zkd> paramEnumSet) {
    Zkd zkd = null;
    if (paramInt == 104)
      paramBitSet.set(150); 
    return zkd;
  }
  
  private static Zkd ZS(int paramInt, BitSet paramBitSet, EnumSet<Zkd> paramEnumSet) {
    Zkd zkd = null;
    if (paramInt == 95)
      paramBitSet.set(165); 
    return zkd;
  }
  
  private static Zkd Zyt(int paramInt, BitSet paramBitSet, EnumSet<Zkd> paramEnumSet) {
    Zkd zkd = null;
    if (paramInt == 118)
      paramBitSet.set(156); 
    return zkd;
  }
  
  private static Zkd Z_r(int paramInt, BitSet paramBitSet, EnumSet<Zkd> paramEnumSet) {
    Zkd zkd = null;
    if (paramInt == 101)
      paramBitSet.set(122); 
    return zkd;
  }
  
  private static Zkd ZyD(int paramInt, BitSet paramBitSet, EnumSet<Zkd> paramEnumSet) {
    Zkd zkd = null;
    if (paramInt == 115)
      paramBitSet.set(47); 
    return zkd;
  }
  
  private static Zkd Zu(int paramInt, BitSet paramBitSet, EnumSet<Zkd> paramEnumSet) {
    Zkd zkd = null;
    if (paramInt == 109 && paramEnumSet.contains(Zkd.MEDIUM_SEVERITY))
      zkd = Zkd.MEDIUM_SEVERITY; 
    return zkd;
  }
  
  private static Zkd ZM(int paramInt, BitSet paramBitSet, EnumSet<Zkd> paramEnumSet) {
    Zkd zkd = null;
    if (paramInt == 100)
      paramBitSet.set(21); 
    return zkd;
  }
  
  private static Zkd ZN9(int paramInt, BitSet paramBitSet, EnumSet<Zkd> paramEnumSet) {
    Zkd zkd = null;
    if (paramInt == 110)
      paramBitSet.set(45); 
    return zkd;
  }
  
  private static Zkd ZN0(int paramInt, BitSet paramBitSet, EnumSet<Zkd> paramEnumSet) {
    Zkd zkd = null;
    if (paramInt == 117)
      paramBitSet.set(144); 
    return zkd;
  }
  
  private static Zkd ZNY(int paramInt, BitSet paramBitSet, EnumSet<Zkd> paramEnumSet) {
    Zkd zkd = null;
    if (paramInt == 110)
      paramBitSet.set(32); 
    return zkd;
  }
  
  private static Zkd ZNJ(int paramInt, BitSet paramBitSet, EnumSet<Zkd> paramEnumSet) {
    Zkd zkd = null;
    if (paramInt == 32)
      paramBitSet.set(63); 
    return zkd;
  }
  
  private static Zkd ZNE(int paramInt, BitSet paramBitSet, EnumSet<Zkd> paramEnumSet) {
    Zkd zkd = null;
    if (paramInt == 100)
      paramBitSet.set(171); 
    return zkd;
  }
  
  private static Zkd ZyF(int paramInt, BitSet paramBitSet, EnumSet<Zkd> paramEnumSet) {
    Zkd zkd = null;
    if (paramInt == 105)
      paramBitSet.set(209); 
    return zkd;
  }
  
  private static Zkd ZG(int paramInt, BitSet paramBitSet, EnumSet<Zkd> paramEnumSet) {
    Zkd zkd = null;
    if (paramInt == 101 && paramEnumSet.contains(Zkd.ISSUE_NAME_HEADER))
      zkd = Zkd.ISSUE_NAME_HEADER; 
    return zkd;
  }
  
  private static Zkd ZN8(int paramInt, BitSet paramBitSet, EnumSet<Zkd> paramEnumSet) {
    Zkd zkd = null;
    if (paramInt == 101)
      paramBitSet.set(64); 
    return zkd;
  }
  
  private static Zkd ZNG(int paramInt, BitSet paramBitSet, EnumSet<Zkd> paramEnumSet) {
    Zkd zkd = null;
    if (paramInt == 119 && paramEnumSet.contains(Zkd.LOW_SEVERITY))
      zkd = Zkd.LOW_SEVERITY; 
    return zkd;
  }
  
  private static Zkd ZNz(int paramInt, BitSet paramBitSet, EnumSet<Zkd> paramEnumSet) {
    Zkd zkd = null;
    if (paramInt == 104)
      paramBitSet.set(179); 
    return zkd;
  }
  
  private static Zkd ZyY(int paramInt, BitSet paramBitSet, EnumSet<Zkd> paramEnumSet) {
    Zkd zkd = null;
    if (paramInt == 116)
      paramBitSet.set(114); 
    return zkd;
  }
  
  private static Zkd Zk(int paramInt, BitSet paramBitSet, EnumSet<Zkd> paramEnumSet) {
    Zkd zkd = null;
    if (paramInt == 101)
      paramBitSet.set(211); 
    return zkd;
  }
  
  private static Zkd ZNe(int paramInt, BitSet paramBitSet, EnumSet<Zkd> paramEnumSet) {
    Zkd zkd = null;
    if (paramInt == 99)
      paramBitSet.set(87); 
    return zkd;
  }
  
  private static Zkd Zy7(int paramInt, BitSet paramBitSet, EnumSet<Zkd> paramEnumSet) {
    Zkd zkd = null;
    if (paramInt >= 48 && paramInt <= 57) {
      paramBitSet.set(108);
      if (paramEnumSet.contains(Zkd.NATURAL_NUMBER))
        zkd = Zkd.NATURAL_NUMBER; 
    } 
    return zkd;
  }
  
  private static Zkd ZJ(int paramInt, BitSet paramBitSet, EnumSet<Zkd> paramEnumSet) {
    Zkd zkd = null;
    if (paramInt == 10 && paramEnumSet.contains(Zkd._TOKEN_5))
      zkd = Zkd._TOKEN_5; 
    return zkd;
  }
  
  private static Zkd Zj(int paramInt, BitSet paramBitSet, EnumSet<Zkd> paramEnumSet) {
    Zkd zkd = null;
    if (paramInt == 110)
      paramBitSet.set(48); 
    return zkd;
  }
  
  private static Zkd ZNX(int paramInt, BitSet paramBitSet, EnumSet<Zkd> paramEnumSet) {
    Zkd zkd = null;
    if (paramInt == 97)
      paramBitSet.set(10); 
    return zkd;
  }
  
  private static Zkd Zg(int paramInt, BitSet paramBitSet, EnumSet<Zkd> paramEnumSet) {
    Zkd zkd = null;
    if (paramInt == 105)
      paramBitSet.set(69); 
    return zkd;
  }
  
  private static Zkd Zyd(int paramInt, BitSet paramBitSet, EnumSet<Zkd> paramEnumSet) {
    Zkd zkd = null;
    if (paramInt == 102 && paramEnumSet.contains(Zkd.IF_HEADER))
      zkd = Zkd.IF_HEADER; 
    return zkd;
  }
  
  private static Zkd ZNQ(int paramInt, BitSet paramBitSet, EnumSet<Zkd> paramEnumSet) {
    Zkd zkd = null;
    if (paramInt == 102)
      paramBitSet.set(54); 
    return zkd;
  }
  
  private static Zkd Zv(int paramInt, BitSet paramBitSet, EnumSet<Zkd> paramEnumSet) {
    Zkd zkd = null;
    if (paramInt == 110)
      paramBitSet.set(33); 
    return zkd;
  }
  
  private static Zkd ZyO(int paramInt, BitSet paramBitSet, EnumSet<Zkd> paramEnumSet) {
    Zkd zkd = null;
    if (paramInt == 114 && paramEnumSet.contains(Zkd.BOOL_OR))
      zkd = Zkd.BOOL_OR; 
    return zkd;
  }
  
  private static Zkd ZNs(int paramInt, BitSet paramBitSet, EnumSet<Zkd> paramEnumSet) {
    Zkd zkd = null;
    if (paramInt == 101 && paramEnumSet.contains(Zkd.TENTATIVE_CONFIDENCE))
      zkd = Zkd.TENTATIVE_CONFIDENCE; 
    return zkd;
  }
  
  private static Zkd ZP(int paramInt, BitSet paramBitSet, EnumSet<Zkd> paramEnumSet) {
    Zkd zkd = null;
    if (paramInt == 101)
      paramBitSet.set(71); 
    return zkd;
  }
  
  private static Zkd Zyo(int paramInt, BitSet paramBitSet, EnumSet<Zkd> paramEnumSet) {
    Zkd zkd = null;
    if (paramInt == 32)
      paramBitSet.set(50); 
    return zkd;
  }
  
  private static Zkd ZNr(int paramInt, BitSet paramBitSet, EnumSet<Zkd> paramEnumSet) {
    Zkd zkd = null;
    if (paramInt == 110)
      paramBitSet.set(31); 
    return zkd;
  }
  
  private static Zkd ZL(int paramInt, BitSet paramBitSet, EnumSet<Zkd> paramEnumSet) {
    Zkd zkd = null;
    if (paramInt == 117)
      paramBitSet.set(2); 
    return zkd;
  }
  
  private static Zkd Zyx(int paramInt, BitSet paramBitSet, EnumSet<Zkd> paramEnumSet) {
    Zkd zkd = null;
    if (paramInt == 114)
      paramBitSet.set(75); 
    return zkd;
  }
  
  private static Zkd Z_7(int paramInt, BitSet paramBitSet, EnumSet<Zkd> paramEnumSet) {
    Zkd zkd = null;
    if (paramInt == 111)
      paramBitSet.set(110); 
    return zkd;
  }
  
  private static Zkd Z_b(int paramInt, BitSet paramBitSet, EnumSet<Zkd> paramEnumSet) {
    Zkd zkd = null;
    if (paramInt == 111)
      paramBitSet.set(176); 
    return zkd;
  }
  
  private static Zkd Z_v(int paramInt, BitSet paramBitSet, EnumSet<Zkd> paramEnumSet) {
    Zkd zkd = null;
    if (paramInt == 114)
      paramBitSet.set(134); 
    return zkd;
  }
  
  private static Zkd ZN6(int paramInt, BitSet paramBitSet, EnumSet<Zkd> paramEnumSet) {
    Zkd zkd = null;
    if (paramInt == 110)
      paramBitSet.set(4); 
    return zkd;
  }
  
  private static Zkd ZR(int paramInt, BitSet paramBitSet, EnumSet<Zkd> paramEnumSet) {
    Zkd zkd = null;
    if (paramInt == 97)
      paramBitSet.set(62); 
    return zkd;
  }
  
  private static Zkd ZNH(int paramInt, BitSet paramBitSet, EnumSet<Zkd> paramEnumSet) {
    Zkd zkd = null;
    if (paramInt == 108)
      paramBitSet.set(93); 
    return zkd;
  }
  
  private static Zkd Z_D(int paramInt, BitSet paramBitSet, EnumSet<Zkd> paramEnumSet) {
    Zkd zkd = null;
    if (paramInt == 97)
      paramBitSet.set(36); 
    return zkd;
  }
  
  private static Zkd ZNA(int paramInt, BitSet paramBitSet, EnumSet<Zkd> paramEnumSet) {
    Zkd zkd = null;
    if (paramInt == 101)
      paramBitSet.set(124); 
    return zkd;
  }
  
  private static Zkd Z_M(int paramInt, BitSet paramBitSet, EnumSet<Zkd> paramEnumSet) {
    Zkd zkd = null;
    if (paramInt == 109 && paramEnumSet.contains(Zkd.FIRM_CONFIDENCE))
      zkd = Zkd.FIRM_CONFIDENCE; 
    return zkd;
  }
  
  private static Zkd Z_L(int paramInt, BitSet paramBitSet, EnumSet<Zkd> paramEnumSet) {
    Zkd zkd = null;
    if (paramInt == 102)
      paramBitSet.set(26); 
    return zkd;
  }
  
  private static Zkd Zm(int paramInt, BitSet paramBitSet, EnumSet<Zkd> paramEnumSet) {
    Zkd zkd = null;
    if (paramInt == 101)
      paramBitSet.set(20); 
    return zkd;
  }
  
  private static Zkd ZNu(int paramInt, BitSet paramBitSet, EnumSet<Zkd> paramEnumSet) {
    Zkd zkd = null;
    if (paramInt == 116)
      paramBitSet.set(178); 
    return zkd;
  }
  
  private static Zkd ZyX(int paramInt, BitSet paramBitSet, EnumSet<Zkd> paramEnumSet) {
    Zkd zkd = null;
    if (paramInt == 110)
      paramBitSet.set(61); 
    return zkd;
  }
  
  private static Zkd ZNZ(int paramInt, BitSet paramBitSet, EnumSet<Zkd> paramEnumSet) {
    Zkd zkd = null;
    if (paramInt == 118)
      paramBitSet.set(190); 
    return zkd;
  }
  
  private static Zkd Zyl(int paramInt, BitSet paramBitSet, EnumSet<Zkd> paramEnumSet) {
    Zkd zkd = null;
    if (paramInt == 103 && paramEnumSet.contains(Zkd.REPLACING))
      zkd = Zkd.REPLACING; 
    return zkd;
  }
  
  private static Zkd Zyz(int paramInt, BitSet paramBitSet, EnumSet<Zkd> paramEnumSet) {
    Zkd zkd = null;
    if (paramInt == 110 && paramEnumSet.contains(Zkd.THEN))
      zkd = Zkd.THEN; 
    return zkd;
  }
  
  private static Zkd Z_t(int paramInt, BitSet paramBitSet, EnumSet<Zkd> paramEnumSet) {
    Zkd zkd = null;
    if (paramInt == 116)
      paramBitSet.set(180); 
    return zkd;
  }
  
  private static Zkd Zq(int paramInt, BitSet paramBitSet, EnumSet<Zkd> paramEnumSet) {
    Zkd zkd = null;
    if (paramInt == 114)
      paramBitSet.set(184); 
    return zkd;
  }
  
  private static Zkd ZyB(int paramInt, BitSet paramBitSet, EnumSet<Zkd> paramEnumSet) {
    Zkd zkd = null;
    if (paramInt == 101)
      paramBitSet.set(188); 
    return zkd;
  }
  
  private static Zkd Z_F(int paramInt, BitSet paramBitSet, EnumSet<Zkd> paramEnumSet) {
    Zkd zkd = null;
    if (paramInt == 115)
      paramBitSet.set(7); 
    return zkd;
  }
  
  private static Zkd Z_E(int paramInt, BitSet paramBitSet, EnumSet<Zkd> paramEnumSet) {
    Zkd zkd = null;
    if (paramInt == 112 && paramEnumSet.contains(Zkd.SMTP_KEY))
      zkd = Zkd.SMTP_KEY; 
    return zkd;
  }
  
  private static Zkd ZW(int paramInt, BitSet paramBitSet, EnumSet<Zkd> paramEnumSet) {
    Zkd zkd = null;
    if (paramInt == 121 && paramEnumSet.contains(Zkd.SEVERITY_HEADER))
      zkd = Zkd.SEVERITY_HEADER; 
    return zkd;
  }
  
  private static Zkd ZC(int paramInt, BitSet paramBitSet, EnumSet<Zkd> paramEnumSet) {
    Zkd zkd = null;
    if (paramInt == 99)
      paramBitSet.set(196); 
    return zkd;
  }
  
  private static Zkd Zb(int paramInt, BitSet paramBitSet, EnumSet<Zkd> paramEnumSet) {
    Zkd zkd = null;
    if (paramInt == 101)
      paramBitSet.set(159); 
    return zkd;
  }
  
  private static Zkd ZNF(int paramInt, BitSet paramBitSet, EnumSet<Zkd> paramEnumSet) {
    Zkd zkd = null;
    if (paramInt == 99)
      paramBitSet.set(137); 
    return zkd;
  }
  
  private static Zkd Zyu(int paramInt, BitSet paramBitSet, EnumSet<Zkd> paramEnumSet) {
    Zkd zkd = null;
    if (paramInt == 111)
      paramBitSet.set(223); 
    return zkd;
  }
  
  private static Zkd ZNv(int paramInt, BitSet paramBitSet, EnumSet<Zkd> paramEnumSet) {
    Zkd zkd = null;
    if (paramInt == 114)
      paramBitSet.set(34); 
    return zkd;
  }
  
  private static Zkd Zc(int paramInt, BitSet paramBitSet, EnumSet<Zkd> paramEnumSet) {
    Zkd zkd = null;
    if (paramInt == 100)
      paramBitSet.set(46); 
    return zkd;
  }
  
  private static Zkd Z_c(int paramInt, BitSet paramBitSet, EnumSet<Zkd> paramEnumSet) {
    Zkd zkd = null;
    if (paramInt == 97)
      paramBitSet.set(106); 
    return zkd;
  }
  
  private static void Zz() {
    Zch[] arrayOfZch = { 
        Zcf::ZNM, Zcf::Z_g, Zcf::ZNt, Zcf::Z_C, Zcf::ZNN, Zcf::ZNP, Zcf::Zr, Zcf::Zyf, Zcf::Zs, Zcf::ZNO, 
        Zcf::ZyQ, Zcf::Z_i, Zcf::Zyh, Zcf::ZNm, Zcf::Z_2, Zcf::Z_k, Zcf::ZyU, Zcf::ZNI, Zcf::ZyZ, Zcf::Zy1, 
        Zcf::ZX, Zcf::Z_n, Zcf::ZyW, Zcf::Zyi, Zcf::Zy9, Zcf::Zyn, Zcf::ZyR, Zcf::ZNa, Zcf::Z_m, Zcf::Zy3, 
        Zcf::ZNp, Zcf::Z_R, Zcf::ZyA, Zcf::ZNn, Zcf::Z_j, Zcf::ZN2, Zcf::ZNC, Zcf::ZD, Zcf::ZN4, Zcf::ZyS, 
        Zcf::Zn, Zcf::ZNW, Zcf::Z_, Zcf::Zf, Zcf::ZI, Zcf::Z_e, Zcf::Zyb, Zcf::ZN_, Zcf::ZyK, Zcf::Z_Q, 
        Zcf::Z_l, Zcf::Zyv, Zcf::ZNx, Zcf::ZY, Zcf::Za, Zcf::ZyJ, Zcf::Zym, Zcf::ZNk, Zcf::ZA, Zcf::ZNg, 
        Zcf::Z_X, Zcf::Zyw, Zcf::ZNf, Zcf::Z_f, Zcf::Z_U, Zcf::Zys, Zcf::ZV, Zcf::Z_d, Zcf::Z_K, Zcf::ZNo, 
        Zcf::ZNB, Zcf::Zz, Zcf::Zyr, Zcf::Z_s, Zcf::Zy, Zcf::Zw, Zcf::ZyE, Zcf::ZT, Zcf::ZN3, Zcf::Zyc, 
        Zcf::ZH, Zcf::Z_Y, Zcf::ZNw, Zcf::Z_0, Zcf::Zya, Zcf::ZyI, Zcf::ZNU, Zcf::Zyg, Zcf::Zye, Zcf::ZNj, 
        Zcf::Z_G, Zcf::Z_u, Zcf::ZE, Zcf::Z_A, Zcf::ZNc, Zcf::Z_O, Zcf::ZNl, Zcf::ZNd, Zcf::Zo, Zcf::Zy2, 
        Zcf::ZNL, Zcf::ZN, Zcf::Z_S, Zcf::ZNy, Zcf::ZND, Zcf::Zy_, Zcf::ZN1, Zcf::ZN5, Zcf::Zy6, Zcf::Zt, 
        Zcf::ZNS, Zcf::ZZ, Zcf::Zh, Zcf::Zyq, Zcf::ZNR, Zcf::ZyG, Zcf::ZNi, Zcf::ZyM, Zcf::Zyk, Zcf::ZF, 
        Zcf::ZNq, Zcf::Zy0, Zcf::ZyH, Zcf::Z_y, Zcf::ZO, Zcf::Z_6, Zcf::Z_4, Zcf::ZNV, Zcf::Zl, Zcf::ZNb, 
        Zcf::ZyP, Zcf::ZNh, Zcf::Z_Z, Zcf::Ze, Zcf::Z_z, Zcf::Zi, Zcf::ZU, Zcf::ZK, Zcf::Z_N, Zcf::ZyV, 
        Zcf::Zyp, Zcf::ZyT, Zcf::ZyL, Zcf::Zy8, Zcf::Zyj, Zcf::ZNT, Zcf::Zd, Zcf::ZyN, Zcf::ZQ, Zcf::Z_H, 
        Zcf::ZNK, Zcf::Z_9, Zcf::Zy5, Zcf::Zy4, Zcf::ZN7, Zcf::Zx, Zcf::Zyy, Zcf::ZB, Zcf::ZyC, Zcf::Z_P, 
        Zcf::Z_3, Zcf::Zp, Zcf::ZS, Zcf::Zyt, Zcf::Z_r, Zcf::ZyD, Zcf::Zu, Zcf::ZM, Zcf::ZN9, Zcf::ZN0, 
        Zcf::ZNY, Zcf::ZNJ, Zcf::ZNE, Zcf::ZyF, Zcf::ZG, Zcf::ZN8, Zcf::ZNG, Zcf::ZNz, Zcf::ZyY, Zcf::Zk, 
        Zcf::ZNe, Zcf::Zy7, Zcf::ZJ, Zcf::Zj, Zcf::ZNX, Zcf::Zg, Zcf::Zyd, Zcf::ZNQ, Zcf::Zv, Zcf::ZyO, 
        Zcf::ZNs, Zcf::ZP, Zcf::Zyo, Zcf::ZNr, Zcf::ZL, Zcf::Zyx, Zcf::Z_7, Zcf::Z_b, Zcf::Z_v, Zcf::ZN6, 
        Zcf::ZR, Zcf::ZNH, Zcf::Z_D, Zcf::ZNA, Zcf::Z_M, Zcf::Z_L, Zcf::Zm, Zcf::ZNu, Zcf::ZyX, Zcf::ZNZ, 
        Zcf::Zyl, Zcf::Zyz, Zcf::Z_t, Zcf::Zq, Zcf::ZyB, Zcf::Z_F, Zcf::Z_E, Zcf::ZW, Zcf::ZC, Zcf::Zb, 
        Zcf::ZNF, Zcf::Zyu, Zcf::ZNv, Zcf::Zc, Zcf::Z_c };
    Zf0.Zo.put(Zrm4.ActiveCheck, arrayOfZch);
  }
}


/* Location:              C:\Program Files\BurpSuitePro\burpsuite_pro.jar!\net\portswigger\Zcf.class
 * Java compiler version: 21 (65.0)
 * JD-Core Version:       1.1.3
 */