package net.portswigger;

import java.util.BitSet;
import java.util.EnumSet;

class Zoi {
  private static Zkd Zme(int paramInt, BitSet paramBitSet, EnumSet<Zkd> paramEnumSet) {
    // Byte code:
    //   0: invokestatic Zy : ()Z
    //   3: aconst_null
    //   4: astore #4
    //   6: istore_3
    //   7: iload_0
    //   8: bipush #35
    //   10: if_icmpne -> 23
    //   13: aload_1
    //   14: bipush #125
    //   16: invokevirtual set : (I)V
    //   19: iload_3
    //   20: ifeq -> 331
    //   23: iload_0
    //   24: bipush #48
    //   26: if_icmplt -> 75
    //   29: iload_0
    //   30: bipush #57
    //   32: if_icmpgt -> 75
    //   35: aload_1
    //   36: bipush #60
    //   38: invokevirtual set : (I)V
    //   41: aload_1
    //   42: bipush #80
    //   44: invokevirtual set : (I)V
    //   47: aload_1
    //   48: sipush #147
    //   51: invokevirtual set : (I)V
    //   54: aload_1
    //   55: bipush #76
    //   57: invokevirtual set : (I)V
    //   60: aload_1
    //   61: iconst_3
    //   62: invokevirtual set : (I)V
    //   65: aload_1
    //   66: bipush #74
    //   68: invokevirtual set : (I)V
    //   71: iload_3
    //   72: ifeq -> 331
    //   75: iload_0
    //   76: bipush #98
    //   78: if_icmpne -> 104
    //   81: aload_1
    //   82: sipush #128
    //   85: invokevirtual set : (I)V
    //   88: aload_1
    //   89: bipush #112
    //   91: invokevirtual set : (I)V
    //   94: aload_1
    //   95: bipush #99
    //   97: invokevirtual set : (I)V
    //   100: iload_3
    //   101: ifeq -> 331
    //   104: iload_0
    //   105: bipush #102
    //   107: if_icmpne -> 120
    //   110: aload_1
    //   111: bipush #102
    //   113: invokevirtual set : (I)V
    //   116: iload_3
    //   117: ifeq -> 331
    //   120: iload_0
    //   121: bipush #103
    //   123: if_icmpne -> 136
    //   126: aload_1
    //   127: bipush #18
    //   129: invokevirtual set : (I)V
    //   132: iload_3
    //   133: ifeq -> 331
    //   136: iload_0
    //   137: bipush #104
    //   139: if_icmpne -> 164
    //   142: aload_1
    //   143: bipush #35
    //   145: invokevirtual set : (I)V
    //   148: aload_1
    //   149: bipush #117
    //   151: invokevirtual set : (I)V
    //   154: aload_1
    //   155: bipush #32
    //   157: invokevirtual set : (I)V
    //   160: iload_3
    //   161: ifeq -> 331
    //   164: iload_0
    //   165: bipush #109
    //   167: if_icmpne -> 186
    //   170: aload_1
    //   171: bipush #115
    //   173: invokevirtual set : (I)V
    //   176: aload_1
    //   177: bipush #122
    //   179: invokevirtual set : (I)V
    //   182: iload_3
    //   183: ifeq -> 331
    //   186: iload_0
    //   187: bipush #112
    //   189: if_icmpne -> 215
    //   192: aload_1
    //   193: sipush #178
    //   196: invokevirtual set : (I)V
    //   199: aload_1
    //   200: bipush #50
    //   202: invokevirtual set : (I)V
    //   205: aload_1
    //   206: bipush #24
    //   208: invokevirtual set : (I)V
    //   211: iload_3
    //   212: ifeq -> 331
    //   215: iload_0
    //   216: bipush #113
    //   218: if_icmpne -> 231
    //   221: aload_1
    //   222: bipush #37
    //   224: invokevirtual set : (I)V
    //   227: iload_3
    //   228: ifeq -> 331
    //   231: iload_0
    //   232: bipush #114
    //   234: if_icmpne -> 267
    //   237: aload_1
    //   238: sipush #179
    //   241: invokevirtual set : (I)V
    //   244: aload_1
    //   245: sipush #143
    //   248: invokevirtual set : (I)V
    //   251: aload_1
    //   252: bipush #124
    //   254: invokevirtual set : (I)V
    //   257: aload_1
    //   258: bipush #62
    //   260: invokevirtual set : (I)V
    //   263: iload_3
    //   264: ifeq -> 331
    //   267: iload_0
    //   268: bipush #115
    //   270: if_icmpne -> 296
    //   273: aload_1
    //   274: bipush #70
    //   276: invokevirtual set : (I)V
    //   279: aload_1
    //   280: sipush #159
    //   283: invokevirtual set : (I)V
    //   286: aload_1
    //   287: bipush #13
    //   289: invokevirtual set : (I)V
    //   292: iload_3
    //   293: ifeq -> 331
    //   296: iload_0
    //   297: bipush #116
    //   299: if_icmpne -> 319
    //   302: aload_1
    //   303: sipush #180
    //   306: invokevirtual set : (I)V
    //   309: aload_1
    //   310: bipush #106
    //   312: invokevirtual set : (I)V
    //   315: iload_3
    //   316: ifeq -> 331
    //   319: iload_0
    //   320: bipush #117
    //   322: if_icmpne -> 331
    //   325: aload_1
    //   326: bipush #69
    //   328: invokevirtual set : (I)V
    //   331: iload_0
    //   332: bipush #65
    //   334: if_icmplt -> 343
    //   337: iload_0
    //   338: bipush #90
    //   340: if_icmple -> 361
    //   343: iload_0
    //   344: bipush #95
    //   346: if_icmpeq -> 361
    //   349: iload_0
    //   350: bipush #97
    //   352: if_icmplt -> 382
    //   355: iload_0
    //   356: bipush #122
    //   358: if_icmpgt -> 382
    //   361: aload_1
    //   362: bipush #52
    //   364: invokevirtual set : (I)V
    //   367: aload_2
    //   368: getstatic net/portswigger/Zkd.UNKNOWN_STRING : Lnet/portswigger/Zkd;
    //   371: invokevirtual contains : (Ljava/lang/Object;)Z
    //   374: ifeq -> 382
    //   377: getstatic net/portswigger/Zkd.UNKNOWN_STRING : Lnet/portswigger/Zkd;
    //   380: astore #4
    //   382: iload_0
    //   383: iflt -> 401
    //   386: aload_2
    //   387: getstatic net/portswigger/Zkd.UNKNOWN : Lnet/portswigger/Zkd;
    //   390: invokevirtual contains : (Ljava/lang/Object;)Z
    //   393: ifeq -> 401
    //   396: getstatic net/portswigger/Zkd.UNKNOWN : Lnet/portswigger/Zkd;
    //   399: astore #4
    //   401: iload_0
    //   402: bipush #46
    //   404: if_icmpne -> 426
    //   407: aload_2
    //   408: getstatic net/portswigger/Zkd.DOT : Lnet/portswigger/Zkd;
    //   411: invokevirtual contains : (Ljava/lang/Object;)Z
    //   414: ifeq -> 839
    //   417: getstatic net/portswigger/Zkd.DOT : Lnet/portswigger/Zkd;
    //   420: astore #4
    //   422: iload_3
    //   423: ifeq -> 839
    //   426: iload_0
    //   427: bipush #65
    //   429: if_icmplt -> 438
    //   432: iload_0
    //   433: bipush #90
    //   435: if_icmple -> 456
    //   438: iload_0
    //   439: bipush #95
    //   441: if_icmpeq -> 456
    //   444: iload_0
    //   445: bipush #97
    //   447: if_icmplt -> 481
    //   450: iload_0
    //   451: bipush #122
    //   453: if_icmpgt -> 481
    //   456: aload_1
    //   457: bipush #58
    //   459: invokevirtual set : (I)V
    //   462: aload_2
    //   463: getstatic net/portswigger/Zkd.VARIABLE_NAME : Lnet/portswigger/Zkd;
    //   466: invokevirtual contains : (Ljava/lang/Object;)Z
    //   469: ifeq -> 839
    //   472: getstatic net/portswigger/Zkd.VARIABLE_NAME : Lnet/portswigger/Zkd;
    //   475: astore #4
    //   477: iload_3
    //   478: ifeq -> 839
    //   481: iload_0
    //   482: bipush #125
    //   484: if_icmpne -> 506
    //   487: aload_2
    //   488: getstatic net/portswigger/Zkd.VARIABLE_END : Lnet/portswigger/Zkd;
    //   491: invokevirtual contains : (Ljava/lang/Object;)Z
    //   494: ifeq -> 839
    //   497: getstatic net/portswigger/Zkd.VARIABLE_END : Lnet/portswigger/Zkd;
    //   500: astore #4
    //   502: iload_3
    //   503: ifeq -> 839
    //   506: iload_0
    //   507: bipush #123
    //   509: if_icmpne -> 531
    //   512: aload_2
    //   513: getstatic net/portswigger/Zkd.VARIABLE_START : Lnet/portswigger/Zkd;
    //   516: invokevirtual contains : (Ljava/lang/Object;)Z
    //   519: ifeq -> 839
    //   522: getstatic net/portswigger/Zkd.VARIABLE_START : Lnet/portswigger/Zkd;
    //   525: astore #4
    //   527: iload_3
    //   528: ifeq -> 839
    //   531: iload_0
    //   532: bipush #44
    //   534: if_icmpne -> 556
    //   537: aload_2
    //   538: getstatic net/portswigger/Zkd.COMMA : Lnet/portswigger/Zkd;
    //   541: invokevirtual contains : (Ljava/lang/Object;)Z
    //   544: ifeq -> 839
    //   547: getstatic net/portswigger/Zkd.COMMA : Lnet/portswigger/Zkd;
    //   550: astore #4
    //   552: iload_3
    //   553: ifeq -> 839
    //   556: iload_0
    //   557: bipush #48
    //   559: if_icmplt -> 587
    //   562: iload_0
    //   563: bipush #57
    //   565: if_icmpgt -> 587
    //   568: aload_2
    //   569: getstatic net/portswigger/Zkd.NATURAL_NUMBER : Lnet/portswigger/Zkd;
    //   572: invokevirtual contains : (Ljava/lang/Object;)Z
    //   575: ifeq -> 839
    //   578: getstatic net/portswigger/Zkd.NATURAL_NUMBER : Lnet/portswigger/Zkd;
    //   581: astore #4
    //   583: iload_3
    //   584: ifeq -> 839
    //   587: iload_0
    //   588: bipush #41
    //   590: if_icmpne -> 612
    //   593: aload_2
    //   594: getstatic net/portswigger/Zkd.CLOSE_BRACKET : Lnet/portswigger/Zkd;
    //   597: invokevirtual contains : (Ljava/lang/Object;)Z
    //   600: ifeq -> 839
    //   603: getstatic net/portswigger/Zkd.CLOSE_BRACKET : Lnet/portswigger/Zkd;
    //   606: astore #4
    //   608: iload_3
    //   609: ifeq -> 839
    //   612: iload_0
    //   613: bipush #40
    //   615: if_icmpne -> 637
    //   618: aload_2
    //   619: getstatic net/portswigger/Zkd.OPEN_BRACKET : Lnet/portswigger/Zkd;
    //   622: invokevirtual contains : (Ljava/lang/Object;)Z
    //   625: ifeq -> 839
    //   628: getstatic net/portswigger/Zkd.OPEN_BRACKET : Lnet/portswigger/Zkd;
    //   631: astore #4
    //   633: iload_3
    //   634: ifeq -> 839
    //   637: iload_0
    //   638: bipush #34
    //   640: if_icmpne -> 662
    //   643: aload_2
    //   644: getstatic net/portswigger/Zkd.LITERAL_STRING_OPENING_QUOTE : Lnet/portswigger/Zkd;
    //   647: invokevirtual contains : (Ljava/lang/Object;)Z
    //   650: ifeq -> 839
    //   653: getstatic net/portswigger/Zkd.LITERAL_STRING_OPENING_QUOTE : Lnet/portswigger/Zkd;
    //   656: astore #4
    //   658: iload_3
    //   659: ifeq -> 839
    //   662: iload_0
    //   663: bipush #96
    //   665: if_icmpne -> 687
    //   668: aload_2
    //   669: getstatic net/portswigger/Zkd.INTERPOLATABLE_STRING_OPENING_QUOTE : Lnet/portswigger/Zkd;
    //   672: invokevirtual contains : (Ljava/lang/Object;)Z
    //   675: ifeq -> 839
    //   678: getstatic net/portswigger/Zkd.INTERPOLATABLE_STRING_OPENING_QUOTE : Lnet/portswigger/Zkd;
    //   681: astore #4
    //   683: iload_3
    //   684: ifeq -> 839
    //   687: iload_0
    //   688: bipush #10
    //   690: if_icmpne -> 712
    //   693: aload_2
    //   694: getstatic net/portswigger/Zkd.NEWLINE : Lnet/portswigger/Zkd;
    //   697: invokevirtual contains : (Ljava/lang/Object;)Z
    //   700: ifeq -> 839
    //   703: getstatic net/portswigger/Zkd.NEWLINE : Lnet/portswigger/Zkd;
    //   706: astore #4
    //   708: iload_3
    //   709: ifeq -> 839
    //   712: iload_0
    //   713: bipush #35
    //   715: if_icmpne -> 743
    //   718: aload_1
    //   719: bipush #71
    //   721: invokevirtual set : (I)V
    //   724: aload_2
    //   725: getstatic net/portswigger/Zkd.COMMENT : Lnet/portswigger/Zkd;
    //   728: invokevirtual contains : (Ljava/lang/Object;)Z
    //   731: ifeq -> 839
    //   734: getstatic net/portswigger/Zkd.COMMENT : Lnet/portswigger/Zkd;
    //   737: astore #4
    //   739: iload_3
    //   740: ifeq -> 839
    //   743: iload_0
    //   744: bipush #12
    //   746: if_icmpne -> 768
    //   749: aload_2
    //   750: getstatic net/portswigger/Zkd._TOKEN_4 : Lnet/portswigger/Zkd;
    //   753: invokevirtual contains : (Ljava/lang/Object;)Z
    //   756: ifeq -> 839
    //   759: getstatic net/portswigger/Zkd._TOKEN_4 : Lnet/portswigger/Zkd;
    //   762: astore #4
    //   764: iload_3
    //   765: ifeq -> 839
    //   768: iload_0
    //   769: bipush #13
    //   771: if_icmpne -> 793
    //   774: aload_2
    //   775: getstatic net/portswigger/Zkd._TOKEN_3 : Lnet/portswigger/Zkd;
    //   778: invokevirtual contains : (Ljava/lang/Object;)Z
    //   781: ifeq -> 839
    //   784: getstatic net/portswigger/Zkd._TOKEN_3 : Lnet/portswigger/Zkd;
    //   787: astore #4
    //   789: iload_3
    //   790: ifeq -> 839
    //   793: iload_0
    //   794: bipush #9
    //   796: if_icmpne -> 818
    //   799: aload_2
    //   800: getstatic net/portswigger/Zkd._TOKEN_2 : Lnet/portswigger/Zkd;
    //   803: invokevirtual contains : (Ljava/lang/Object;)Z
    //   806: ifeq -> 839
    //   809: getstatic net/portswigger/Zkd._TOKEN_2 : Lnet/portswigger/Zkd;
    //   812: astore #4
    //   814: iload_3
    //   815: ifeq -> 839
    //   818: iload_0
    //   819: bipush #32
    //   821: if_icmpne -> 839
    //   824: aload_2
    //   825: getstatic net/portswigger/Zkd._TOKEN_1 : Lnet/portswigger/Zkd;
    //   828: invokevirtual contains : (Ljava/lang/Object;)Z
    //   831: ifeq -> 839
    //   834: getstatic net/portswigger/Zkd._TOKEN_1 : Lnet/portswigger/Zkd;
    //   837: astore #4
    //   839: aload #4
    //   841: areturn
  }
  
  private static Zkd Zv0(int paramInt, BitSet paramBitSet, EnumSet<Zkd> paramEnumSet) {
    Zkd zkd = null;
    if (paramInt == 114)
      paramBitSet.set(96); 
    return zkd;
  }
  
  private static Zkd Zvd(int paramInt, BitSet paramBitSet, EnumSet<Zkd> paramEnumSet) {
    Zkd zkd = null;
    if (paramInt == 100)
      paramBitSet.set(148); 
    return zkd;
  }
  
  private static Zkd ZvB(int paramInt, BitSet paramBitSet, EnumSet<Zkd> paramEnumSet) {
    Zkd zkd = null;
    if (paramInt >= 48 && paramInt <= 57) {
      paramBitSet.set(60);
      paramBitSet.set(74);
      paramBitSet.set(147);
      if (paramEnumSet.contains(Zkd.NATURAL_NUMBER))
        zkd = Zkd.NATURAL_NUMBER; 
    } 
    return zkd;
  }
  
  private static Zkd Zmg(int paramInt, BitSet paramBitSet, EnumSet<Zkd> paramEnumSet) {
    Zkd zkd = null;
    if (paramInt == 115)
      paramBitSet.set(22); 
    return zkd;
  }
  
  private static Zkd ZmM(int paramInt, BitSet paramBitSet, EnumSet<Zkd> paramEnumSet) {
    Zkd zkd = null;
    if (paramInt == 111)
      paramBitSet.set(64); 
    return zkd;
  }
  
  private static Zkd Zmn(int paramInt, BitSet paramBitSet, EnumSet<Zkd> paramEnumSet) {
    Zkd zkd = null;
    if (paramInt == 108)
      paramBitSet.set(130); 
    return zkd;
  }
  
  private static Zkd ZvD(int paramInt, BitSet paramBitSet, EnumSet<Zkd> paramEnumSet) {
    Zkd zkd = null;
    if (paramInt == 108)
      paramBitSet.set(72); 
    return zkd;
  }
  
  private static Zkd Zvq(int paramInt, BitSet paramBitSet, EnumSet<Zkd> paramEnumSet) {
    Zkd zkd = null;
    if (paramInt == 99)
      paramBitSet.set(135); 
    return zkd;
  }
  
  private static Zkd Zmx(int paramInt, BitSet paramBitSet, EnumSet<Zkd> paramEnumSet) {
    Zkd zkd = null;
    if (paramInt == 115)
      paramBitSet.set(153); 
    return zkd;
  }
  
  private static Zkd Zf(int paramInt, BitSet paramBitSet, EnumSet<Zkd> paramEnumSet) {
    Zkd zkd = null;
    if (paramInt == 116)
      paramBitSet.set(173); 
    return zkd;
  }
  
  private static Zkd Zz(int paramInt, BitSet paramBitSet, EnumSet<Zkd> paramEnumSet) {
    Zkd zkd = null;
    if (paramInt == 116 && paramEnumSet.contains(Zkd.REQUEST_OBJECT))
      zkd = Zkd.REQUEST_OBJECT; 
    return zkd;
  }
  
  private static Zkd Zv6(int paramInt, BitSet paramBitSet, EnumSet<Zkd> paramEnumSet) {
    Zkd zkd = null;
    if (paramInt == 116)
      paramBitSet.set(177); 
    return zkd;
  }
  
  private static Zkd ZA(int paramInt, BitSet paramBitSet, EnumSet<Zkd> paramEnumSet) {
    Zkd zkd = null;
    if (paramInt == 116)
      paramBitSet.set(14); 
    return zkd;
  }
  
  private static Zkd Zw(int paramInt, BitSet paramBitSet, EnumSet<Zkd> paramEnumSet) {
    Zkd zkd = null;
    if (paramInt == 97)
      paramBitSet.set(39); 
    return zkd;
  }
  
  private static Zkd Zv1(int paramInt, BitSet paramBitSet, EnumSet<Zkd> paramEnumSet) {
    Zkd zkd = null;
    if (paramInt == 111)
      paramBitSet.set(113); 
    return zkd;
  }
  
  private static Zkd ZvQ(int paramInt, BitSet paramBitSet, EnumSet<Zkd> paramEnumSet) {
    Zkd zkd = null;
    if (paramInt == 111)
      paramBitSet.set(61); 
    return zkd;
  }
  
  private static Zkd Zvh(int paramInt, BitSet paramBitSet, EnumSet<Zkd> paramEnumSet) {
    Zkd zkd = null;
    if (paramInt == 120)
      paramBitSet.set(54); 
    return zkd;
  }
  
  private static Zkd ZB(int paramInt, BitSet paramBitSet, EnumSet<Zkd> paramEnumSet) {
    Zkd zkd = null;
    if (paramInt == 101)
      paramBitSet.set(75); 
    return zkd;
  }
  
  private static Zkd ZvW(int paramInt, BitSet paramBitSet, EnumSet<Zkd> paramEnumSet) {
    Zkd zkd = null;
    if (paramInt == 114)
      paramBitSet.set(85); 
    return zkd;
  }
  
  private static Zkd ZvA(int paramInt, BitSet paramBitSet, EnumSet<Zkd> paramEnumSet) {
    Zkd zkd = null;
    if (paramInt == 115 && paramEnumSet.contains(Zkd.REQUEST_RESPONSE_COMMON_PROPERTY))
      zkd = Zkd.REQUEST_RESPONSE_COMMON_PROPERTY; 
    return zkd;
  }
  
  private static Zkd Zd(int paramInt, BitSet paramBitSet, EnumSet<Zkd> paramEnumSet) {
    Zkd zkd = null;
    if (paramInt == 101 && paramEnumSet.contains(Zkd.REGEX_REPLACE_FUNCTION))
      zkd = Zkd.REGEX_REPLACE_FUNCTION; 
    return zkd;
  }
  
  private static Zkd Zr(int paramInt, BitSet paramBitSet, EnumSet<Zkd> paramEnumSet) {
    Zkd zkd = null;
    if (paramInt == 95)
      paramBitSet.set(95); 
    return zkd;
  }
  
  private static Zkd Zmt(int paramInt, BitSet paramBitSet, EnumSet<Zkd> paramEnumSet) {
    Zkd zkd = null;
    if (paramInt == 115)
      paramBitSet.set(172); 
    return zkd;
  }
  
  private static Zkd Zv8(int paramInt, BitSet paramBitSet, EnumSet<Zkd> paramEnumSet) {
    Zkd zkd = null;
    if (paramInt == 111)
      paramBitSet.set(110); 
    return zkd;
  }
  
  private static Zkd Zvr(int paramInt, BitSet paramBitSet, EnumSet<Zkd> paramEnumSet) {
    Zkd zkd = null;
    if (paramInt == 116)
      paramBitSet.set(42); 
    return zkd;
  }
  
  private static Zkd ZZ(int paramInt, BitSet paramBitSet, EnumSet<Zkd> paramEnumSet) {
    Zkd zkd = null;
    if (paramInt == 108 && paramEnumSet.contains(Zkd.URL_PROPERTY))
      zkd = Zkd.URL_PROPERTY; 
    return zkd;
  }
  
  private static Zkd ZmH(int paramInt, BitSet paramBitSet, EnumSet<Zkd> paramEnumSet) {
    Zkd zkd = null;
    if (paramInt == 114)
      paramBitSet.set(164); 
    return zkd;
  }
  
  private static Zkd Zx(int paramInt, BitSet paramBitSet, EnumSet<Zkd> paramEnumSet) {
    Zkd zkd = null;
    if (paramInt == 101)
      paramBitSet.set(121); 
    return zkd;
  }
  
  private static Zkd Zg(int paramInt, BitSet paramBitSet, EnumSet<Zkd> paramEnumSet) {
    Zkd zkd = null;
    if (paramInt == 99)
      paramBitSet.set(59); 
    return zkd;
  }
  
  private static Zkd ZmW(int paramInt, BitSet paramBitSet, EnumSet<Zkd> paramEnumSet) {
    Zkd zkd = null;
    if (paramInt == 101)
      paramBitSet.set(145); 
    return zkd;
  }
  
  private static Zkd ZvN(int paramInt, BitSet paramBitSet, EnumSet<Zkd> paramEnumSet) {
    Zkd zkd = null;
    if (paramInt == 101)
      paramBitSet.set(8); 
    return zkd;
  }
  
  private static Zkd ZvF(int paramInt, BitSet paramBitSet, EnumSet<Zkd> paramEnumSet) {
    Zkd zkd = null;
    if (paramInt == 101)
      paramBitSet.set(141); 
    return zkd;
  }
  
  private static Zkd Zms(int paramInt, BitSet paramBitSet, EnumSet<Zkd> paramEnumSet) {
    Zkd zkd = null;
    if (paramInt == 117)
      paramBitSet.set(93); 
    return zkd;
  }
  
  private static Zkd ZvK(int paramInt, BitSet paramBitSet, EnumSet<Zkd> paramEnumSet) {
    Zkd zkd = null;
    if (paramInt == 112)
      paramBitSet.set(6); 
    return zkd;
  }
  
  private static Zkd ZmB(int paramInt, BitSet paramBitSet, EnumSet<Zkd> paramEnumSet) {
    Zkd zkd = null;
    if (paramInt == 116)
      paramBitSet.set(171); 
    return zkd;
  }
  
  private static Zkd Zvt(int paramInt, BitSet paramBitSet, EnumSet<Zkd> paramEnumSet) {
    Zkd zkd = null;
    if (paramInt == 119)
      paramBitSet.set(81); 
    return zkd;
  }
  
  private static Zkd Zvo(int paramInt, BitSet paramBitSet, EnumSet<Zkd> paramEnumSet) {
    Zkd zkd = null;
    if (paramInt == 117)
      paramBitSet.set(163); 
    return zkd;
  }
  
  private static Zkd Zmh(int paramInt, BitSet paramBitSet, EnumSet<Zkd> paramEnumSet) {
    Zkd zkd = null;
    if (paramInt == 110 && paramEnumSet.contains(Zkd.REQUEST_RESPONSE_COMMON_PROPERTY))
      zkd = Zkd.REQUEST_RESPONSE_COMMON_PROPERTY; 
    return zkd;
  }
  
  private static Zkd Zvg(int paramInt, BitSet paramBitSet, EnumSet<Zkd> paramEnumSet) {
    Zkd zkd = null;
    if (paramInt == 116)
      paramBitSet.set(55); 
    return zkd;
  }
  
  private static Zkd ZgK(int paramInt, BitSet paramBitSet, EnumSet<Zkd> paramEnumSet) {
    Zkd zkd = null;
    if (paramInt == 111)
      paramBitSet.set(68); 
    return zkd;
  }
  
  private static Zkd Zu(int paramInt, BitSet paramBitSet, EnumSet<Zkd> paramEnumSet) {
    Zkd zkd = null;
    if (paramInt == 111)
      paramBitSet.set(25); 
    return zkd;
  }
  
  private static Zkd Zk(int paramInt, BitSet paramBitSet, EnumSet<Zkd> paramEnumSet) {
    Zkd zkd = null;
    if (paramInt == 111)
      paramBitSet.set(162); 
    return zkd;
  }
  
  private static Zkd Zva(int paramInt, BitSet paramBitSet, EnumSet<Zkd> paramEnumSet) {
    Zkd zkd = null;
    if (paramInt == 115)
      paramBitSet.set(161); 
    return zkd;
  }
  
  private static Zkd Zvv(int paramInt, BitSet paramBitSet, EnumSet<Zkd> paramEnumSet) {
    Zkd zkd = null;
    if (paramInt == 54 && paramEnumSet.contains(Zkd.SHA256_FUNCTION))
      zkd = Zkd.SHA256_FUNCTION; 
    return zkd;
  }
  
  private static Zkd Zy(int paramInt, BitSet paramBitSet, EnumSet<Zkd> paramEnumSet) {
    Zkd zkd = null;
    if (paramInt == 103)
      paramBitSet.set(174); 
    return zkd;
  }
  
  private static Zkd ZJ(int paramInt, BitSet paramBitSet, EnumSet<Zkd> paramEnumSet) {
    Zkd zkd = null;
    if (paramInt == 100)
      paramBitSet.set(114); 
    return zkd;
  }
  
  private static Zkd ZvV(int paramInt, BitSet paramBitSet, EnumSet<Zkd> paramEnumSet) {
    Zkd zkd = null;
    if (paramInt == 100)
      paramBitSet.set(31); 
    return zkd;
  }
  
  private static Zkd Zm(int paramInt, BitSet paramBitSet, EnumSet<Zkd> paramEnumSet) {
    Zkd zkd = null;
    if (paramInt == 115)
      paramBitSet.set(11); 
    return zkd;
  }
  
  private static Zkd Zvs(int paramInt, BitSet paramBitSet, EnumSet<Zkd> paramEnumSet) {
    Zkd zkd = null;
    if (paramInt == 95)
      paramBitSet.set(92); 
    return zkd;
  }
  
  private static Zkd Zmf(int paramInt, BitSet paramBitSet, EnumSet<Zkd> paramEnumSet) {
    Zkd zkd = null;
    if (paramInt == 114)
      paramBitSet.set(41); 
    return zkd;
  }
  
  private static Zkd ZmD(int paramInt, BitSet paramBitSet, EnumSet<Zkd> paramEnumSet) {
    Zkd zkd = null;
    if (paramInt == 10 && paramEnumSet.contains(Zkd._TOKEN_5))
      zkd = Zkd._TOKEN_5; 
    return zkd;
  }
  
  private static Zkd Zvl(int paramInt, BitSet paramBitSet, EnumSet<Zkd> paramEnumSet) {
    Zkd zkd = null;
    if (paramInt >= 48 && paramInt <= 57) {
      paramBitSet.set(52);
      if (paramEnumSet.contains(Zkd.UNKNOWN_STRING))
        zkd = Zkd.UNKNOWN_STRING; 
    } else if ((paramInt >= 65 && paramInt <= 90) || paramInt == 95 || (paramInt >= 97 && paramInt <= 122)) {
      paramBitSet.set(52);
      if (paramEnumSet.contains(Zkd.UNKNOWN_STRING))
        zkd = Zkd.UNKNOWN_STRING; 
    } 
    return zkd;
  }
  
  private static Zkd Z_(int paramInt, BitSet paramBitSet, EnumSet<Zkd> paramEnumSet) {
    Zkd zkd = null;
    if (paramInt == 97)
      paramBitSet.set(119); 
    return zkd;
  }
  
  private static Zkd ZO(int paramInt, BitSet paramBitSet, EnumSet<Zkd> paramEnumSet) {
    Zkd zkd = null;
    if (paramInt == 95)
      paramBitSet.set(1); 
    return zkd;
  }
  
  private static Zkd ZP(int paramInt, BitSet paramBitSet, EnumSet<Zkd> paramEnumSet) {
    Zkd zkd = null;
    if (paramInt == 117)
      paramBitSet.set(4); 
    return zkd;
  }
  
  private static Zkd Zn(int paramInt, BitSet paramBitSet, EnumSet<Zkd> paramEnumSet) {
    Zkd zkd = null;
    if (paramInt == 111)
      paramBitSet.set(38); 
    return zkd;
  }
  
  private static Zkd ZvJ(int paramInt, BitSet paramBitSet, EnumSet<Zkd> paramEnumSet) {
    Zkd zkd = null;
    if (paramInt == 49 && paramEnumSet.contains(Zkd.SHA1_FUNCTION))
      zkd = Zkd.SHA1_FUNCTION; 
    return zkd;
  }
  
  private static Zkd Zmr(int paramInt, BitSet paramBitSet, EnumSet<Zkd> paramEnumSet) {
    Zkd zkd = null;
    if (paramInt >= 48 && paramInt <= 57) {
      paramBitSet.set(58);
      if (paramEnumSet.contains(Zkd.VARIABLE_NAME))
        zkd = Zkd.VARIABLE_NAME; 
    } else if ((paramInt >= 65 && paramInt <= 90) || paramInt == 95 || (paramInt >= 97 && paramInt <= 122)) {
      paramBitSet.set(58);
      if (paramEnumSet.contains(Zkd.VARIABLE_NAME))
        zkd = Zkd.VARIABLE_NAME; 
    } 
    return zkd;
  }
  
  private static Zkd Zvp(int paramInt, BitSet paramBitSet, EnumSet<Zkd> paramEnumSet) {
    Zkd zkd = null;
    if (paramInt == 111)
      paramBitSet.set(142); 
    return zkd;
  }
  
  private static Zkd Zm5(int paramInt, BitSet paramBitSet, EnumSet<Zkd> paramEnumSet) {
    Zkd zkd = null;
    if (paramInt >= 48 && paramInt <= 57) {
      paramBitSet.set(74);
      if (paramEnumSet.contains(Zkd.NATURAL_NUMBER))
        zkd = Zkd.NATURAL_NUMBER; 
    } 
    return zkd;
  }
  
  private static Zkd Zi(int paramInt, BitSet paramBitSet, EnumSet<Zkd> paramEnumSet) {
    Zkd zkd = null;
    if (paramInt == 114)
      paramBitSet.set(87); 
    return zkd;
  }
  
  private static Zkd ZX(int paramInt, BitSet paramBitSet, EnumSet<Zkd> paramEnumSet) {
    Zkd zkd = null;
    if (paramInt == 97)
      paramBitSet.set(156); 
    return zkd;
  }
  
  private static Zkd ZmR(int paramInt, BitSet paramBitSet, EnumSet<Zkd> paramEnumSet) {
    Zkd zkd = null;
    if (paramInt == 53)
      paramBitSet.set(44); 
    return zkd;
  }
  
  private static Zkd Zvw(int paramInt, BitSet paramBitSet, EnumSet<Zkd> paramEnumSet) {
    Zkd zkd = null;
    if (paramInt == 109)
      paramBitSet.set(49); 
    return zkd;
  }
  
  private static Zkd ZR(int paramInt, BitSet paramBitSet, EnumSet<Zkd> paramEnumSet) {
    Zkd zkd = null;
    if (paramInt == 117)
      paramBitSet.set(91); 
    return zkd;
  }
  
  private static Zkd ZvX(int paramInt, BitSet paramBitSet, EnumSet<Zkd> paramEnumSet) {
    Zkd zkd = null;
    if (paramInt == 95)
      paramBitSet.set(29); 
    return zkd;
  }
  
  private static Zkd ZmE(int paramInt, BitSet paramBitSet, EnumSet<Zkd> paramEnumSet) {
    Zkd zkd = null;
    if (paramInt == 95)
      paramBitSet.set(79); 
    return zkd;
  }
  
  private static Zkd Zvf(int paramInt, BitSet paramBitSet, EnumSet<Zkd> paramEnumSet) {
    Zkd zkd = null;
    if (paramInt == 100)
      paramBitSet.set(101); 
    return zkd;
  }
  
  private static Zkd ZmF(int paramInt, BitSet paramBitSet, EnumSet<Zkd> paramEnumSet) {
    Zkd zkd = null;
    if (paramInt == 114)
      paramBitSet.set(94); 
    return zkd;
  }
  
  private static Zkd ZmC(int paramInt, BitSet paramBitSet, EnumSet<Zkd> paramEnumSet) {
    Zkd zkd = null;
    if (paramInt == 104)
      paramBitSet.set(53); 
    return zkd;
  }
  
  private static Zkd ZK(int paramInt, BitSet paramBitSet, EnumSet<Zkd> paramEnumSet) {
    Zkd zkd = null;
    if ((paramInt >= 0 && paramInt <= 9) || paramInt == 11 || paramInt == 12 || paramInt >= 14) {
      paramBitSet.set(71);
      if (paramEnumSet.contains(Zkd.COMMENT))
        zkd = Zkd.COMMENT; 
    } 
    return zkd;
  }
  
  private static Zkd ZvH(int paramInt, BitSet paramBitSet, EnumSet<Zkd> paramEnumSet) {
    Zkd zkd = null;
    if (paramInt == 97)
      paramBitSet.set(86); 
    return zkd;
  }
  
  private static Zkd ZE(int paramInt, BitSet paramBitSet, EnumSet<Zkd> paramEnumSet) {
    Zkd zkd = null;
    if (paramInt == 100)
      paramBitSet.set(146); 
    return zkd;
  }
  
  private static Zkd ZS(int paramInt, BitSet paramBitSet, EnumSet<Zkd> paramEnumSet) {
    Zkd zkd = null;
    if (paramInt >= 48 && paramInt <= 57 && paramEnumSet.contains(Zkd.NATURAL_NUMBER))
      zkd = Zkd.NATURAL_NUMBER; 
    return zkd;
  }
  
  private static Zkd Zvz(int paramInt, BitSet paramBitSet, EnumSet<Zkd> paramEnumSet) {
    Zkd zkd = null;
    if (paramInt == 110)
      paramBitSet.set(169); 
    return zkd;
  }
  
  private static Zkd ZmX(int paramInt, BitSet paramBitSet, EnumSet<Zkd> paramEnumSet) {
    Zkd zkd = null;
    if (paramInt >= 48 && paramInt <= 57) {
      paramBitSet.set(60);
      paramBitSet.set(74);
      paramBitSet.set(80);
      paramBitSet.set(3);
      paramBitSet.set(147);
      if (paramEnumSet.contains(Zkd.NATURAL_NUMBER))
        zkd = Zkd.NATURAL_NUMBER; 
    } 
    return zkd;
  }
  
  private static Zkd ZvC(int paramInt, BitSet paramBitSet, EnumSet<Zkd> paramEnumSet) {
    Zkd zkd = null;
    if (paramInt == 100)
      paramBitSet.set(84); 
    return zkd;
  }
  
  private static Zkd ZvR(int paramInt, BitSet paramBitSet, EnumSet<Zkd> paramEnumSet) {
    Zkd zkd = null;
    if (paramInt == 101 && paramEnumSet.contains(Zkd.URL_PROPERTY))
      zkd = Zkd.URL_PROPERTY; 
    return zkd;
  }
  
  private static Zkd Zmb(int paramInt, BitSet paramBitSet, EnumSet<Zkd> paramEnumSet) {
    Zkd zkd = null;
    if (paramInt == 97)
      paramBitSet.set(137); 
    return zkd;
  }
  
  private static Zkd Zmw(int paramInt, BitSet paramBitSet, EnumSet<Zkd> paramEnumSet) {
    Zkd zkd = null;
    if (paramInt >= 48 && paramInt <= 57) {
      paramBitSet.set(60);
      paramBitSet.set(74);
      paramBitSet.set(3);
      paramBitSet.set(147);
      if (paramEnumSet.contains(Zkd.NATURAL_NUMBER))
        zkd = Zkd.NATURAL_NUMBER; 
    } 
    return zkd;
  }
  
  private static Zkd Zvn(int paramInt, BitSet paramBitSet, EnumSet<Zkd> paramEnumSet) {
    Zkd zkd = null;
    if (paramInt == 101)
      paramBitSet.set(108); 
    return zkd;
  }
  
  private static Zkd Zv4(int paramInt, BitSet paramBitSet, EnumSet<Zkd> paramEnumSet) {
    Zkd zkd = null;
    if (paramInt == 108)
      paramBitSet.set(134); 
    return zkd;
  }
  
  private static Zkd Zvy(int paramInt, BitSet paramBitSet, EnumSet<Zkd> paramEnumSet) {
    Zkd zkd = null;
    if (paramInt == 116)
      paramBitSet.set(158); 
    return zkd;
  }
  
  private static Zkd Zmi(int paramInt, BitSet paramBitSet, EnumSet<Zkd> paramEnumSet) {
    Zkd zkd = null;
    if (paramInt == 114)
      paramBitSet.set(123); 
    return zkd;
  }
  
  private static Zkd Zve(int paramInt, BitSet paramBitSet, EnumSet<Zkd> paramEnumSet) {
    Zkd zkd = null;
    if (paramInt == 97)
      paramBitSet.set(12); 
    return zkd;
  }
  
  private static Zkd ZvY(int paramInt, BitSet paramBitSet, EnumSet<Zkd> paramEnumSet) {
    Zkd zkd = null;
    if (paramInt == 98)
      paramBitSet.set(16); 
    return zkd;
  }
  
  private static Zkd Zv9(int paramInt, BitSet paramBitSet, EnumSet<Zkd> paramEnumSet) {
    Zkd zkd = null;
    if (paramInt == 97)
      paramBitSet.set(83); 
    return zkd;
  }
  
  private static Zkd ZL(int paramInt, BitSet paramBitSet, EnumSet<Zkd> paramEnumSet) {
    Zkd zkd = null;
    if (paramInt == 95)
      paramBitSet.set(47); 
    return zkd;
  }
  
  private static Zkd ZT(int paramInt, BitSet paramBitSet, EnumSet<Zkd> paramEnumSet) {
    Zkd zkd = null;
    if (paramInt == 116 && paramEnumSet.contains(Zkd.URL_PROPERTY))
      zkd = Zkd.URL_PROPERTY; 
    return zkd;
  }
  
  private static Zkd Zmc(int paramInt, BitSet paramBitSet, EnumSet<Zkd> paramEnumSet) {
    Zkd zkd = null;
    if (paramInt == 121 && paramEnumSet.contains(Zkd.REQUEST_RESPONSE_COMMON_PROPERTY))
      zkd = Zkd.REQUEST_RESPONSE_COMMON_PROPERTY; 
    return zkd;
  }
  
  private static Zkd Zmo(int paramInt, BitSet paramBitSet, EnumSet<Zkd> paramEnumSet) {
    Zkd zkd = null;
    if (paramInt == 112)
      paramBitSet.set(181); 
    return zkd;
  }
  
  private static Zkd ZvS(int paramInt, BitSet paramBitSet, EnumSet<Zkd> paramEnumSet) {
    Zkd zkd = null;
    if (paramInt == 115)
      paramBitSet.set(10); 
    return zkd;
  }
  
  private static Zkd ZmA(int paramInt, BitSet paramBitSet, EnumSet<Zkd> paramEnumSet) {
    Zkd zkd = null;
    if (paramInt == 101)
      paramBitSet.set(48); 
    return zkd;
  }
  
  private static Zkd Zv2(int paramInt, BitSet paramBitSet, EnumSet<Zkd> paramEnumSet) {
    Zkd zkd = null;
    if (paramInt == 108 && paramEnumSet.contains(Zkd.URL))
      zkd = Zkd.URL; 
    return zkd;
  }
  
  private static Zkd Zv7(int paramInt, BitSet paramBitSet, EnumSet<Zkd> paramEnumSet) {
    Zkd zkd = null;
    if (paramInt == 99)
      paramBitSet.set(151); 
    return zkd;
  }
  
  private static Zkd ZmN(int paramInt, BitSet paramBitSet, EnumSet<Zkd> paramEnumSet) {
    Zkd zkd = null;
    if (paramInt == 101)
      paramBitSet.set(34); 
    return zkd;
  }
  
  private static Zkd ZvU(int paramInt, BitSet paramBitSet, EnumSet<Zkd> paramEnumSet) {
    Zkd zkd = null;
    if (paramInt == 99)
      paramBitSet.set(21); 
    return zkd;
  }
  
  private static Zkd Zmk(int paramInt, BitSet paramBitSet, EnumSet<Zkd> paramEnumSet) {
    Zkd zkd = null;
    if (paramInt == 52)
      paramBitSet.set(138); 
    return zkd;
  }
  
  private static Zkd ZmP(int paramInt, BitSet paramBitSet, EnumSet<Zkd> paramEnumSet) {
    Zkd zkd = null;
    if (paramInt == 97)
      paramBitSet.set(105); 
    return zkd;
  }
  
  private static Zkd Zm_(int paramInt, BitSet paramBitSet, EnumSet<Zkd> paramEnumSet) {
    Zkd zkd = null;
    if (paramInt == 52)
      paramBitSet.set(88); 
    return zkd;
  }
  
  private static Zkd Ze(int paramInt, BitSet paramBitSet, EnumSet<Zkd> paramEnumSet) {
    Zkd zkd = null;
    if (paramInt == 101 && paramEnumSet.contains(Zkd.BASE64_ENCODE_FUNCTION))
      zkd = Zkd.BASE64_ENCODE_FUNCTION; 
    return zkd;
  }
  
  private static Zkd Zvj(int paramInt, BitSet paramBitSet, EnumSet<Zkd> paramEnumSet) {
    Zkd zkd = null;
    if (paramInt == 105)
      paramBitSet.set(170); 
    return zkd;
  }
  
  private static Zkd Zp(int paramInt, BitSet paramBitSet, EnumSet<Zkd> paramEnumSet) {
    Zkd zkd = null;
    if (paramInt == 111)
      paramBitSet.set(26); 
    return zkd;
  }
  
  private static Zkd ZgI(int paramInt, BitSet paramBitSet, EnumSet<Zkd> paramEnumSet) {
    Zkd zkd = null;
    if (paramInt == 111)
      paramBitSet.set(107); 
    return zkd;
  }
  
  private static Zkd ZD(int paramInt, BitSet paramBitSet, EnumSet<Zkd> paramEnumSet) {
    Zkd zkd = null;
    if (paramInt == 115)
      paramBitSet.set(28); 
    return zkd;
  }
  
  private static Zkd Zm9(int paramInt, BitSet paramBitSet, EnumSet<Zkd> paramEnumSet) {
    Zkd zkd = null;
    if (paramInt == 111)
      paramBitSet.set(175); 
    return zkd;
  }
  
  private static Zkd Zj(int paramInt, BitSet paramBitSet, EnumSet<Zkd> paramEnumSet) {
    Zkd zkd = null;
    if (paramInt == 100 && paramEnumSet.contains(Zkd.REQUEST_SPECIFIC_PROPERTY))
      zkd = Zkd.REQUEST_SPECIFIC_PROPERTY; 
    return zkd;
  }
  
  private static Zkd ZmQ(int paramInt, BitSet paramBitSet, EnumSet<Zkd> paramEnumSet) {
    Zkd zkd = null;
    if (paramInt == 114 && paramEnumSet.contains(Zkd.TO_LOWER_FUNCTION))
      zkd = Zkd.TO_LOWER_FUNCTION; 
    return zkd;
  }
  
  private static Zkd ZvM(int paramInt, BitSet paramBitSet, EnumSet<Zkd> paramEnumSet) {
    Zkd zkd = null;
    if (paramInt == 112)
      paramBitSet.set(15); 
    return zkd;
  }
  
  private static Zkd Zl(int paramInt, BitSet paramBitSet, EnumSet<Zkd> paramEnumSet) {
    Zkd zkd = null;
    if (paramInt == 114)
      paramBitSet.set(89); 
    return zkd;
  }
  
  private static Zkd Zv_(int paramInt, BitSet paramBitSet, EnumSet<Zkd> paramEnumSet) {
    Zkd zkd = null;
    if (paramInt == 116)
      paramBitSet.set(136); 
    return zkd;
  }
  
  private static Zkd ZG(int paramInt, BitSet paramBitSet, EnumSet<Zkd> paramEnumSet) {
    Zkd zkd = null;
    if (paramInt == 111)
      paramBitSet.set(131); 
    return zkd;
  }
  
  private static Zkd Zv5(int paramInt, BitSet paramBitSet, EnumSet<Zkd> paramEnumSet) {
    Zkd zkd = null;
    if (paramInt == 110)
      paramBitSet.set(168); 
    return zkd;
  }
  
  private static Zkd ZvZ(int paramInt, BitSet paramBitSet, EnumSet<Zkd> paramEnumSet) {
    Zkd zkd = null;
    if (paramInt == 101)
      paramBitSet.set(120); 
    return zkd;
  }
  
  private static Zkd Za(int paramInt, BitSet paramBitSet, EnumSet<Zkd> paramEnumSet) {
    Zkd zkd = null;
    if (paramInt == 100)
      paramBitSet.set(139); 
    return zkd;
  }
  
  private static Zkd Zv3(int paramInt, BitSet paramBitSet, EnumSet<Zkd> paramEnumSet) {
    Zkd zkd = null;
    if (paramInt == 115)
      paramBitSet.set(129); 
    return zkd;
  }
  
  private static Zkd Zvx(int paramInt, BitSet paramBitSet, EnumSet<Zkd> paramEnumSet) {
    Zkd zkd = null;
    if (paramInt == 111)
      paramBitSet.set(9); 
    return zkd;
  }
  
  private static Zkd ZmJ(int paramInt, BitSet paramBitSet, EnumSet<Zkd> paramEnumSet) {
    Zkd zkd = null;
    if (paramInt == 99)
      paramBitSet.set(40); 
    return zkd;
  }
  
  private static Zkd Zvk(int paramInt, BitSet paramBitSet, EnumSet<Zkd> paramEnumSet) {
    Zkd zkd = null;
    if (paramInt == 50)
      paramBitSet.set(63); 
    return zkd;
  }
  
  private static Zkd Zvb(int paramInt, BitSet paramBitSet, EnumSet<Zkd> paramEnumSet) {
    Zkd zkd = null;
    if (paramInt == 114)
      paramBitSet.set(20); 
    return zkd;
  }
  
  private static Zkd ZI(int paramInt, BitSet paramBitSet, EnumSet<Zkd> paramEnumSet) {
    Zkd zkd = null;
    if (paramInt == 54)
      paramBitSet.set(100); 
    return zkd;
  }
  
  private static Zkd Zma(int paramInt, BitSet paramBitSet, EnumSet<Zkd> paramEnumSet) {
    Zkd zkd = null;
    if (paramInt == 101)
      paramBitSet.set(167); 
    return zkd;
  }
  
  private static Zkd Zvm(int paramInt, BitSet paramBitSet, EnumSet<Zkd> paramEnumSet) {
    Zkd zkd = null;
    if (paramInt == 101)
      paramBitSet.set(43); 
    return zkd;
  }
  
  private static Zkd Zmj(int paramInt, BitSet paramBitSet, EnumSet<Zkd> paramEnumSet) {
    Zkd zkd = null;
    if (paramInt == 101)
      paramBitSet.set(166); 
    return zkd;
  }
  
  private static Zkd Zmy(int paramInt, BitSet paramBitSet, EnumSet<Zkd> paramEnumSet) {
    // Byte code:
    //   0: invokestatic Zy : ()Z
    //   3: aconst_null
    //   4: astore #4
    //   6: istore_3
    //   7: iload_0
    //   8: iflt -> 17
    //   11: iload_0
    //   12: bipush #9
    //   14: if_icmple -> 35
    //   17: iload_0
    //   18: bipush #11
    //   20: if_icmpeq -> 35
    //   23: iload_0
    //   24: bipush #12
    //   26: if_icmpeq -> 35
    //   29: iload_0
    //   30: bipush #14
    //   32: if_icmplt -> 45
    //   35: aload_1
    //   36: bipush #125
    //   38: invokevirtual set : (I)V
    //   41: iload_3
    //   42: ifeq -> 82
    //   45: iload_0
    //   46: bipush #13
    //   48: if_icmpne -> 61
    //   51: aload_1
    //   52: bipush #51
    //   54: invokevirtual set : (I)V
    //   57: iload_3
    //   58: ifeq -> 82
    //   61: iload_0
    //   62: bipush #10
    //   64: if_icmpne -> 82
    //   67: aload_2
    //   68: getstatic net/portswigger/Zkd._TOKEN_5 : Lnet/portswigger/Zkd;
    //   71: invokevirtual contains : (Ljava/lang/Object;)Z
    //   74: ifeq -> 82
    //   77: getstatic net/portswigger/Zkd._TOKEN_5 : Lnet/portswigger/Zkd;
    //   80: astore #4
    //   82: iload_0
    //   83: bipush #13
    //   85: if_icmpne -> 103
    //   88: aload_2
    //   89: getstatic net/portswigger/Zkd._TOKEN_5 : Lnet/portswigger/Zkd;
    //   92: invokevirtual contains : (Ljava/lang/Object;)Z
    //   95: ifeq -> 103
    //   98: getstatic net/portswigger/Zkd._TOKEN_5 : Lnet/portswigger/Zkd;
    //   101: astore #4
    //   103: aload #4
    //   105: areturn
  }
  
  private static Zkd Zv(int paramInt, BitSet paramBitSet, EnumSet<Zkd> paramEnumSet) {
    Zkd zkd = null;
    if (paramInt == 110)
      paramBitSet.set(118); 
    return zkd;
  }
  
  private static Zkd ZmY(int paramInt, BitSet paramBitSet, EnumSet<Zkd> paramEnumSet) {
    Zkd zkd = null;
    if (paramInt == 114)
      paramBitSet.set(67); 
    return zkd;
  }
  
  private static Zkd Zm2(int paramInt, BitSet paramBitSet, EnumSet<Zkd> paramEnumSet) {
    Zkd zkd = null;
    if (paramInt == 97)
      paramBitSet.set(23); 
    return zkd;
  }
  
  private static Zkd ZY(int paramInt, BitSet paramBitSet, EnumSet<Zkd> paramEnumSet) {
    Zkd zkd = null;
    if (paramInt == 105)
      paramBitSet.set(56); 
    return zkd;
  }
  
  private static Zkd ZF(int paramInt, BitSet paramBitSet, EnumSet<Zkd> paramEnumSet) {
    Zkd zkd = null;
    if (paramInt == 97)
      paramBitSet.set(97); 
    return zkd;
  }
  
  private static Zkd Zt(int paramInt, BitSet paramBitSet, EnumSet<Zkd> paramEnumSet) {
    Zkd zkd = null;
    if (paramInt == 100)
      paramBitSet.set(90); 
    return zkd;
  }
  
  private static Zkd ZW(int paramInt, BitSet paramBitSet, EnumSet<Zkd> paramEnumSet) {
    Zkd zkd = null;
    if (paramInt == 101)
      paramBitSet.set(126); 
    return zkd;
  }
  
  private static Zkd Zm3(int paramInt, BitSet paramBitSet, EnumSet<Zkd> paramEnumSet) {
    Zkd zkd = null;
    if (paramInt == 104)
      paramBitSet.set(104); 
    return zkd;
  }
  
  private static Zkd ZV(int paramInt, BitSet paramBitSet, EnumSet<Zkd> paramEnumSet) {
    Zkd zkd = null;
    if (paramInt == 111)
      paramBitSet.set(36); 
    return zkd;
  }
  
  private static Zkd Zvc(int paramInt, BitSet paramBitSet, EnumSet<Zkd> paramEnumSet) {
    Zkd zkd = null;
    if (paramInt == 111)
      paramBitSet.set(73); 
    return zkd;
  }
  
  private static Zkd Zml(int paramInt, BitSet paramBitSet, EnumSet<Zkd> paramEnumSet) {
    Zkd zkd = null;
    if (paramInt == 104 && paramEnumSet.contains(Zkd.URL_PROPERTY))
      zkd = Zkd.URL_PROPERTY; 
    return zkd;
  }
  
  private static Zkd ZH(int paramInt, BitSet paramBitSet, EnumSet<Zkd> paramEnumSet) {
    Zkd zkd = null;
    if (paramInt == 100)
      paramBitSet.set(77); 
    return zkd;
  }
  
  private static Zkd ZmI(int paramInt, BitSet paramBitSet, EnumSet<Zkd> paramEnumSet) {
    Zkd zkd = null;
    if (paramInt == 95)
      paramBitSet.set(132); 
    return zkd;
  }
  
  private static Zkd ZmT(int paramInt, BitSet paramBitSet, EnumSet<Zkd> paramEnumSet) {
    Zkd zkd = null;
    if (paramInt == 53 && paramEnumSet.contains(Zkd.MD5_FUNCTION))
      zkd = Zkd.MD5_FUNCTION; 
    return zkd;
  }
  
  private static Zkd Zmv(int paramInt, BitSet paramBitSet, EnumSet<Zkd> paramEnumSet) {
    Zkd zkd = null;
    if (paramInt == 114)
      paramBitSet.set(116); 
    return zkd;
  }
  
  private static Zkd Zvi(int paramInt, BitSet paramBitSet, EnumSet<Zkd> paramEnumSet) {
    Zkd zkd = null;
    if (paramInt == 97)
      paramBitSet.set(46); 
    return zkd;
  }
  
  private static Zkd ZC(int paramInt, BitSet paramBitSet, EnumSet<Zkd> paramEnumSet) {
    Zkd zkd = null;
    if (paramInt == 108)
      paramBitSet.set(7); 
    return zkd;
  }
  
  private static Zkd ZmV(int paramInt, BitSet paramBitSet, EnumSet<Zkd> paramEnumSet) {
    Zkd zkd = null;
    if (paramInt == 101)
      paramBitSet.set(45); 
    return zkd;
  }
  
  private static Zkd ZvP(int paramInt, BitSet paramBitSet, EnumSet<Zkd> paramEnumSet) {
    Zkd zkd = null;
    if (paramInt == 101 && paramEnumSet.contains(Zkd.RESPONSE_OBJECT))
      zkd = Zkd.RESPONSE_OBJECT; 
    return zkd;
  }
  
  private static Zkd Zmm(int paramInt, BitSet paramBitSet, EnumSet<Zkd> paramEnumSet) {
    Zkd zkd = null;
    if (paramInt == 114 && paramEnumSet.contains(Zkd.TO_UPPER_FUNCTION))
      zkd = Zkd.TO_UPPER_FUNCTION; 
    return zkd;
  }
  
  private static Zkd Zgh(int paramInt, BitSet paramBitSet, EnumSet<Zkd> paramEnumSet) {
    Zkd zkd = null;
    if (paramInt == 101 && paramEnumSet.contains(Zkd.BASE64_DECODE_FUNCTION))
      zkd = Zkd.BASE64_DECODE_FUNCTION; 
    return zkd;
  }
  
  private static Zkd ZmU(int paramInt, BitSet paramBitSet, EnumSet<Zkd> paramEnumSet) {
    Zkd zkd = null;
    if (paramInt >= 48 && paramInt <= 57) {
      paramBitSet.set(60);
      paramBitSet.set(74);
      if (paramEnumSet.contains(Zkd.NATURAL_NUMBER))
        zkd = Zkd.NATURAL_NUMBER; 
    } 
    return zkd;
  }
  
  private static Zkd Zmd(int paramInt, BitSet paramBitSet, EnumSet<Zkd> paramEnumSet) {
    Zkd zkd = null;
    if (paramInt == 101 && paramEnumSet.contains(Zkd.RESPONSE_SPECIFIC_PROPERTY))
      zkd = Zkd.RESPONSE_SPECIFIC_PROPERTY; 
    return zkd;
  }
  
  private static Zkd ZM(int paramInt, BitSet paramBitSet, EnumSet<Zkd> paramEnumSet) {
    Zkd zkd = null;
    if (paramInt == 118)
      paramBitSet.set(157); 
    return zkd;
  }
  
  private static Zkd Zm1(int paramInt, BitSet paramBitSet, EnumSet<Zkd> paramEnumSet) {
    Zkd zkd = null;
    if (paramInt == 95)
      paramBitSet.set(82); 
    return zkd;
  }
  
  private static Zkd ZvG(int paramInt, BitSet paramBitSet, EnumSet<Zkd> paramEnumSet) {
    Zkd zkd = null;
    if (paramInt == 111)
      paramBitSet.set(2); 
    return zkd;
  }
  
  private static Zkd ZvE(int paramInt, BitSet paramBitSet, EnumSet<Zkd> paramEnumSet) {
    Zkd zkd = null;
    if (paramInt == 112)
      paramBitSet.set(155); 
    return zkd;
  }
  
  private static Zkd Zq(int paramInt, BitSet paramBitSet, EnumSet<Zkd> paramEnumSet) {
    Zkd zkd = null;
    if (paramInt == 116 && paramEnumSet.contains(Zkd.URL_PROPERTY))
      zkd = Zkd.URL_PROPERTY; 
    return zkd;
  }
  
  private static Zkd Zo(int paramInt, BitSet paramBitSet, EnumSet<Zkd> paramEnumSet) {
    Zkd zkd = null;
    if (paramInt == 54)
      paramBitSet.set(98); 
    return zkd;
  }
  
  private static Zkd ZmG(int paramInt, BitSet paramBitSet, EnumSet<Zkd> paramEnumSet) {
    Zkd zkd = null;
    if (paramInt == 95)
      paramBitSet.set(149); 
    return zkd;
  }
  
  private static Zkd Zb(int paramInt, BitSet paramBitSet, EnumSet<Zkd> paramEnumSet) {
    Zkd zkd = null;
    if (paramInt == 110)
      paramBitSet.set(176); 
    return zkd;
  }
  
  private static Zkd ZmO(int paramInt, BitSet paramBitSet, EnumSet<Zkd> paramEnumSet) {
    Zkd zkd = null;
    if (paramInt == 101)
      paramBitSet.set(140); 
    return zkd;
  }
  
  private static Zkd ZQ(int paramInt, BitSet paramBitSet, EnumSet<Zkd> paramEnumSet) {
    Zkd zkd = null;
    if (paramInt == 111)
      paramBitSet.set(127); 
    return zkd;
  }
  
  private static Zkd Zm7(int paramInt, BitSet paramBitSet, EnumSet<Zkd> paramEnumSet) {
    Zkd zkd = null;
    if (paramInt == 104)
      paramBitSet.set(160); 
    return zkd;
  }
  
  private static Zkd ZvT(int paramInt, BitSet paramBitSet, EnumSet<Zkd> paramEnumSet) {
    Zkd zkd = null;
    if (paramInt == 97)
      paramBitSet.set(57); 
    return zkd;
  }
  
  private static Zkd ZvI(int paramInt, BitSet paramBitSet, EnumSet<Zkd> paramEnumSet) {
    Zkd zkd = null;
    if (paramInt == 115 && paramEnumSet.contains(Zkd.GENERATE_COLLABORATOR_ADDRESS_FUNCTION))
      zkd = Zkd.GENERATE_COLLABORATOR_ADDRESS_FUNCTION; 
    return zkd;
  }
  
  private static Zkd ZmS(int paramInt, BitSet paramBitSet, EnumSet<Zkd> paramEnumSet) {
    Zkd zkd = null;
    if (paramInt == 99)
      paramBitSet.set(103); 
    return zkd;
  }
  
  private static Zkd Zmz(int paramInt, BitSet paramBitSet, EnumSet<Zkd> paramEnumSet) {
    Zkd zkd = null;
    if (paramInt == 101)
      paramBitSet.set(27); 
    return zkd;
  }
  
  private static Zkd Zmp(int paramInt, BitSet paramBitSet, EnumSet<Zkd> paramEnumSet) {
    Zkd zkd = null;
    if (paramInt == 121 && paramEnumSet.contains(Zkd.URL_PROPERTY))
      zkd = Zkd.URL_PROPERTY; 
    return zkd;
  }
  
  private static Zkd ZmL(int paramInt, BitSet paramBitSet, EnumSet<Zkd> paramEnumSet) {
    Zkd zkd = null;
    if (paramInt == 113)
      paramBitSet.set(33); 
    return zkd;
  }
  
  private static Zkd ZU(int paramInt, BitSet paramBitSet, EnumSet<Zkd> paramEnumSet) {
    Zkd zkd = null;
    if (paramInt == 115)
      paramBitSet.set(109); 
    return zkd;
  }
  
  private static Zkd ZmZ(int paramInt, BitSet paramBitSet, EnumSet<Zkd> paramEnumSet) {
    Zkd zkd = null;
    if (paramInt == 116)
      paramBitSet.set(133); 
    return zkd;
  }
  
  private static Zkd Zmq(int paramInt, BitSet paramBitSet, EnumSet<Zkd> paramEnumSet) {
    Zkd zkd = null;
    if (paramInt == 115)
      paramBitSet.set(144); 
    return zkd;
  }
  
  private static Zkd ZvO(int paramInt, BitSet paramBitSet, EnumSet<Zkd> paramEnumSet) {
    Zkd zkd = null;
    if (paramInt == 101)
      paramBitSet.set(19); 
    return zkd;
  }
  
  private static Zkd Zm0(int paramInt, BitSet paramBitSet, EnumSet<Zkd> paramEnumSet) {
    Zkd zkd = null;
    if (paramInt == 108)
      paramBitSet.set(78); 
    return zkd;
  }
  
  private static Zkd Zc(int paramInt, BitSet paramBitSet, EnumSet<Zkd> paramEnumSet) {
    Zkd zkd = null;
    if (paramInt == 116)
      paramBitSet.set(152); 
    return zkd;
  }
  
  private static Zkd Zvu(int paramInt, BitSet paramBitSet, EnumSet<Zkd> paramEnumSet) {
    Zkd zkd = null;
    if (paramInt == 101)
      paramBitSet.set(154); 
    return zkd;
  }
  
  private static Zkd ZN(int paramInt, BitSet paramBitSet, EnumSet<Zkd> paramEnumSet) {
    Zkd zkd = null;
    if (paramInt == 114 && paramEnumSet.contains(Zkd.RANDOM_STR_FUNCTION))
      zkd = Zkd.RANDOM_STR_FUNCTION; 
    return zkd;
  }
  
  private static Zkd Zh(int paramInt, BitSet paramBitSet, EnumSet<Zkd> paramEnumSet) {
    Zkd zkd = null;
    if (paramInt == 101)
      paramBitSet.set(17); 
    return zkd;
  }
  
  private static Zkd Zm4(int paramInt, BitSet paramBitSet, EnumSet<Zkd> paramEnumSet) {
    Zkd zkd = null;
    if (paramInt == 95)
      paramBitSet.set(65); 
    return zkd;
  }
  
  private static Zkd ZvL(int paramInt, BitSet paramBitSet, EnumSet<Zkd> paramEnumSet) {
    Zkd zkd = null;
    if (paramInt == 100)
      paramBitSet.set(5); 
    return zkd;
  }
  
  private static Zkd ZmK(int paramInt, BitSet paramBitSet, EnumSet<Zkd> paramEnumSet) {
    Zkd zkd = null;
    if (paramInt == 101)
      paramBitSet.set(66); 
    return zkd;
  }
  
  private static Zkd Zs(int paramInt, BitSet paramBitSet, EnumSet<Zkd> paramEnumSet) {
    Zkd zkd = null;
    if (paramInt == 97)
      paramBitSet.set(111); 
    return zkd;
  }
  
  private static Zkd Zmu(int paramInt, BitSet paramBitSet, EnumSet<Zkd> paramEnumSet) {
    Zkd zkd = null;
    if (paramInt == 101)
      paramBitSet.set(165); 
    return zkd;
  }
  
  private static Zkd Zm8(int paramInt, BitSet paramBitSet, EnumSet<Zkd> paramEnumSet) {
    Zkd zkd = null;
    if (paramInt == 111)
      paramBitSet.set(150); 
    return zkd;
  }
  
  private static Zkd Zm6(int paramInt, BitSet paramBitSet, EnumSet<Zkd> paramEnumSet) {
    Zkd zkd = null;
    if (paramInt == 112)
      paramBitSet.set(30); 
    return zkd;
  }
  
  private static void Z_() {
    Zch[] arrayOfZch = { 
        Zoi::Zme, Zoi::Zv0, Zoi::Zvd, Zoi::ZvB, Zoi::Zmg, Zoi::ZmM, Zoi::Zmn, Zoi::ZvD, Zoi::Zvq, Zoi::Zmx, 
        Zoi::Zf, Zoi::Zz, Zoi::Zv6, Zoi::ZA, Zoi::Zw, Zoi::Zv1, Zoi::ZvQ, Zoi::Zvh, Zoi::ZB, Zoi::ZvW, 
        Zoi::ZvA, Zoi::Zd, Zoi::Zr, Zoi::Zmt, Zoi::Zv8, Zoi::Zvr, Zoi::ZZ, Zoi::ZmH, Zoi::Zx, Zoi::Zg, 
        Zoi::ZmW, Zoi::ZvN, Zoi::ZvF, Zoi::Zms, Zoi::ZvK, Zoi::ZmB, Zoi::Zvt, Zoi::Zvo, Zoi::Zmh, Zoi::Zvg, 
        Zoi::ZgK, Zoi::Zu, Zoi::Zk, Zoi::Zva, Zoi::Zvv, Zoi::Zy, Zoi::ZJ, Zoi::ZvV, Zoi::Zm, Zoi::Zvs, 
        Zoi::Zmf, Zoi::ZmD, Zoi::Zvl, Zoi::Z_, Zoi::ZO, Zoi::ZP, Zoi::Zn, Zoi::ZvJ, Zoi::Zmr, Zoi::Zvp, 
        Zoi::Zm5, Zoi::Zi, Zoi::ZX, Zoi::ZmR, Zoi::Zvw, Zoi::ZR, Zoi::ZvX, Zoi::ZmE, Zoi::Zvf, Zoi::ZmF, 
        Zoi::ZmC, Zoi::ZK, Zoi::ZvH, Zoi::ZE, Zoi::ZS, Zoi::Zvz, Zoi::ZmX, Zoi::ZvC, Zoi::ZvR, Zoi::Zmb, 
        Zoi::Zmw, Zoi::Zvn, Zoi::Zv4, Zoi::Zvy, Zoi::Zmi, Zoi::Zve, Zoi::ZvY, Zoi::Zv9, Zoi::ZL, Zoi::ZT, 
        Zoi::Zmc, Zoi::Zmo, Zoi::ZvS, Zoi::ZmA, Zoi::Zv2, Zoi::Zv7, Zoi::ZmN, Zoi::ZvU, Zoi::Zmk, Zoi::ZmP, 
        Zoi::Zm_, Zoi::Ze, Zoi::Zvj, Zoi::Zp, Zoi::ZgI, Zoi::ZD, Zoi::Zm9, Zoi::Zj, Zoi::ZmQ, Zoi::ZvM, 
        Zoi::Zl, Zoi::Zv_, Zoi::ZG, Zoi::Zv5, Zoi::ZvZ, Zoi::Za, Zoi::Zv3, Zoi::Zvx, Zoi::ZmJ, Zoi::Zvk, 
        Zoi::Zvb, Zoi::ZI, Zoi::Zma, Zoi::Zvm, Zoi::Zmj, Zoi::Zmy, Zoi::Zv, Zoi::ZmY, Zoi::Zm2, Zoi::ZY, 
        Zoi::ZF, Zoi::Zt, Zoi::ZW, Zoi::Zm3, Zoi::ZV, Zoi::Zvc, Zoi::Zml, Zoi::ZH, Zoi::ZmI, Zoi::ZmT, 
        Zoi::Zmv, Zoi::Zvi, Zoi::ZC, Zoi::ZmV, Zoi::ZvP, Zoi::Zmm, Zoi::Zgh, Zoi::ZmU, Zoi::Zmd, Zoi::ZM, 
        Zoi::Zm1, Zoi::ZvG, Zoi::ZvE, Zoi::Zq, Zoi::Zo, Zoi::ZmG, Zoi::Zb, Zoi::ZmO, Zoi::ZQ, Zoi::Zm7, 
        Zoi::ZvT, Zoi::ZvI, Zoi::ZmS, Zoi::Zmz, Zoi::Zmp, Zoi::ZmL, Zoi::ZU, Zoi::ZmZ, Zoi::Zmq, Zoi::ZvO, 
        Zoi::Zm0, Zoi::Zc, Zoi::Zvu, Zoi::ZN, Zoi::Zh, Zoi::Zm4, Zoi::ZvL, Zoi::ZmK, Zoi::Zs, Zoi::Zmu, 
        Zoi::Zm8, Zoi::Zm6 };
    Zf0.Zo.put(Zrm4.WithinVariableRef, arrayOfZch);
  }
}


/* Location:              C:\Program Files\BurpSuitePro\burpsuite_pro.jar!\net\portswigger\Zoi.class
 * Java compiler version: 21 (65.0)
 * JD-Core Version:       1.1.3
 */