package net.portswigger;

import java.io.UnsupportedEncodingException;
import java.net.URLDecoder;
import java.util.Map;

public class Zrzt {
  public static final Map<String, Character> Z_;
  
  public static String Zk(String paramString) {
    // Byte code:
    //   0: invokestatic ZK : ()I
    //   3: aload_0
    //   4: invokevirtual length : ()I
    //   7: istore_2
    //   8: istore_1
    //   9: new java/lang/StringBuilder
    //   12: dup
    //   13: iload_2
    //   14: iconst_3
    //   15: imul
    //   16: invokespecial <init> : (I)V
    //   19: astore_3
    //   20: iconst_0
    //   21: istore #4
    //   23: iload #4
    //   25: iload_2
    //   26: if_icmpge -> 269
    //   29: aload_0
    //   30: iload #4
    //   32: invokevirtual charAt : (I)C
    //   35: istore #5
    //   37: iload #5
    //   39: bipush #32
    //   41: if_icmpne -> 62
    //   44: aload_3
    //   45: ldc '+'
    //   47: invokevirtual append : (Ljava/lang/String;)Ljava/lang/StringBuilder;
    //   50: pop
    //   51: iload_1
    //   52: ifeq -> 262
    //   55: goto -> 62
    //   58: invokestatic a : (Ljava/lang/Exception;)Ljava/lang/Exception;
    //   61: athrow
    //   62: iload #5
    //   64: bipush #48
    //   66: if_icmplt -> 90
    //   69: goto -> 76
    //   72: invokestatic a : (Ljava/lang/Exception;)Ljava/lang/Exception;
    //   75: athrow
    //   76: iload #5
    //   78: bipush #57
    //   80: if_icmple -> 202
    //   83: goto -> 90
    //   86: invokestatic a : (Ljava/lang/Exception;)Ljava/lang/Exception;
    //   89: athrow
    //   90: iload #5
    //   92: bipush #64
    //   94: if_icmplt -> 118
    //   97: goto -> 104
    //   100: invokestatic a : (Ljava/lang/Exception;)Ljava/lang/Exception;
    //   103: athrow
    //   104: iload #5
    //   106: bipush #90
    //   108: if_icmple -> 202
    //   111: goto -> 118
    //   114: invokestatic a : (Ljava/lang/Exception;)Ljava/lang/Exception;
    //   117: athrow
    //   118: iload #5
    //   120: bipush #97
    //   122: if_icmplt -> 146
    //   125: goto -> 132
    //   128: invokestatic a : (Ljava/lang/Exception;)Ljava/lang/Exception;
    //   131: athrow
    //   132: iload #5
    //   134: bipush #122
    //   136: if_icmple -> 202
    //   139: goto -> 146
    //   142: invokestatic a : (Ljava/lang/Exception;)Ljava/lang/Exception;
    //   145: athrow
    //   146: iload #5
    //   148: bipush #42
    //   150: if_icmpeq -> 202
    //   153: goto -> 160
    //   156: invokestatic a : (Ljava/lang/Exception;)Ljava/lang/Exception;
    //   159: athrow
    //   160: iload #5
    //   162: bipush #45
    //   164: if_icmpeq -> 202
    //   167: goto -> 174
    //   170: invokestatic a : (Ljava/lang/Exception;)Ljava/lang/Exception;
    //   173: athrow
    //   174: iload #5
    //   176: bipush #46
    //   178: if_icmpeq -> 202
    //   181: goto -> 188
    //   184: invokestatic a : (Ljava/lang/Exception;)Ljava/lang/Exception;
    //   187: athrow
    //   188: iload #5
    //   190: bipush #95
    //   192: if_icmpne -> 224
    //   195: goto -> 202
    //   198: invokestatic a : (Ljava/lang/Exception;)Ljava/lang/Exception;
    //   201: athrow
    //   202: aload_3
    //   203: aload_0
    //   204: iload #4
    //   206: invokevirtual charAt : (I)C
    //   209: invokevirtual append : (C)Ljava/lang/StringBuilder;
    //   212: pop
    //   213: iload_1
    //   214: ifeq -> 262
    //   217: goto -> 224
    //   220: invokestatic a : (Ljava/lang/Exception;)Ljava/lang/Exception;
    //   223: athrow
    //   224: iload #5
    //   226: invokestatic toHexString : (I)Ljava/lang/String;
    //   229: <illegal opcode> makeConcatWithConstants : (Ljava/lang/String;)Ljava/lang/String;
    //   234: astore #6
    //   236: aload #6
    //   238: aload #6
    //   240: invokevirtual length : ()I
    //   243: iconst_2
    //   244: isub
    //   245: invokevirtual substring : (I)Ljava/lang/String;
    //   248: astore #6
    //   250: aload_3
    //   251: ldc '%'
    //   253: invokevirtual append : (Ljava/lang/String;)Ljava/lang/StringBuilder;
    //   256: aload #6
    //   258: invokevirtual append : (Ljava/lang/String;)Ljava/lang/StringBuilder;
    //   261: pop
    //   262: iinc #4, 1
    //   265: iload_1
    //   266: ifeq -> 23
    //   269: aload_3
    //   270: invokevirtual toString : ()Ljava/lang/String;
    //   273: invokestatic Zwu : ()[Lburp/Zbqc;
    //   276: ifnonnull -> 293
    //   279: iinc #1, 1
    //   282: iload_1
    //   283: invokestatic ZX : (I)V
    //   286: goto -> 293
    //   289: invokestatic a : (Ljava/lang/Exception;)Ljava/lang/Exception;
    //   292: athrow
    //   293: areturn
    // Exception table:
    //   from	to	target	type
    //   37	55	58	java/lang/NumberFormatException
    //   44	69	72	java/lang/NumberFormatException
    //   62	83	86	java/lang/NumberFormatException
    //   76	97	100	java/lang/NumberFormatException
    //   90	111	114	java/lang/NumberFormatException
    //   104	125	128	java/lang/NumberFormatException
    //   118	139	142	java/lang/NumberFormatException
    //   132	153	156	java/lang/NumberFormatException
    //   146	167	170	java/lang/NumberFormatException
    //   160	181	184	java/lang/NumberFormatException
    //   174	195	198	java/lang/NumberFormatException
    //   188	217	220	java/lang/NumberFormatException
    //   269	286	289	java/lang/NumberFormatException
  }
  
  public static String ZJ(String paramString) {
    return ZN(paramString, true);
  }
  
  public static String Zm(String paramString) {
    return ZN(paramString, false);
  }
  
  private static String ZN(String paramString, boolean paramBoolean) {
    // Byte code:
    //   0: invokestatic ZZ : ()I
    //   3: aload_0
    //   4: invokevirtual length : ()I
    //   7: istore_3
    //   8: new java/lang/StringBuilder
    //   11: dup
    //   12: iload_3
    //   13: invokespecial <init> : (I)V
    //   16: astore #4
    //   18: iconst_0
    //   19: istore #5
    //   21: istore_2
    //   22: iload #5
    //   24: iload_3
    //   25: if_icmpge -> 155
    //   28: aload_0
    //   29: iload #5
    //   31: invokevirtual charAt : (I)C
    //   34: istore #6
    //   36: iload_1
    //   37: ifeq -> 62
    //   40: iload #6
    //   42: bipush #43
    //   44: if_icmpne -> 62
    //   47: goto -> 54
    //   50: invokestatic a : (Ljava/lang/Exception;)Ljava/lang/Exception;
    //   53: athrow
    //   54: bipush #32
    //   56: istore #6
    //   58: iload_2
    //   59: ifne -> 140
    //   62: iload #6
    //   64: bipush #37
    //   66: if_icmpne -> 140
    //   69: goto -> 76
    //   72: invokestatic a : (Ljava/lang/Exception;)Ljava/lang/Exception;
    //   75: athrow
    //   76: iload #5
    //   78: iconst_3
    //   79: iadd
    //   80: iload_3
    //   81: if_icmpgt -> 140
    //   84: goto -> 91
    //   87: invokestatic a : (Ljava/lang/Exception;)Ljava/lang/Exception;
    //   90: athrow
    //   91: aload_0
    //   92: iload #5
    //   94: iconst_1
    //   95: iadd
    //   96: iload #5
    //   98: iconst_3
    //   99: iadd
    //   100: invokevirtual substring : (II)Ljava/lang/String;
    //   103: bipush #16
    //   105: invokestatic parseInt : (Ljava/lang/String;I)I
    //   108: i2c
    //   109: istore #6
    //   111: iinc #5, 2
    //   114: goto -> 140
    //   117: astore #7
    //   119: aload #7
    //   121: getstatic net/portswigger/Zk_.IGNORED : Lnet/portswigger/Zk_;
    //   124: invokestatic Zl : (Ljava/lang/Throwable;Lnet/portswigger/Zk_;)V
    //   127: goto -> 140
    //   130: astore #7
    //   132: aload #7
    //   134: getstatic net/portswigger/Zk_.UNEXPECTED : Lnet/portswigger/Zk_;
    //   137: invokestatic Zl : (Ljava/lang/Throwable;Lnet/portswigger/Zk_;)V
    //   140: aload #4
    //   142: iload #6
    //   144: invokevirtual append : (C)Ljava/lang/StringBuilder;
    //   147: pop
    //   148: iinc #5, 1
    //   151: iload_2
    //   152: ifne -> 22
    //   155: aload #4
    //   157: invokevirtual toString : ()Ljava/lang/String;
    //   160: areturn
    // Exception table:
    //   from	to	target	type
    //   36	47	50	java/lang/NumberFormatException
    //   58	69	72	java/lang/NumberFormatException
    //   62	84	87	java/lang/NumberFormatException
    //   91	114	117	java/lang/NumberFormatException
    //   91	114	130	java/lang/Exception
  }
  
  public static String Zn(String paramString) {
    return ZE(paramString, null);
  }
  
  public static String ZE(String paramString, int[] paramArrayOfint) {
    try {
      if (paramString == null)
        return null; 
    } catch (Exception exception) {
      throw a(null);
    } 
    StringBuilder stringBuilder = new StringBuilder();
    int i = 0;
    int j = 0;
    while (true) {
      try {
        if (j < paramString.length()) {
          if (paramString.charAt(j) == '&') {
            int k;
            if ((k = paramString.indexOf(";", j)) != -1) {
              String str = paramString.substring(j + 1, k);
              if (str.startsWith("#")) {
                try {
                  char c;
                  if (str.substring(1, 2).equalsIgnoreCase("x")) {
                    c = (char)Integer.parseInt(str.substring(2), 16);
                  } else {
                    c = (char)Integer.parseInt(str.substring(1));
                  } 
                  try {
                    if (c < ' ')
                      throw new Exception(); 
                  } catch (Exception exception) {
                    throw a(null);
                  } 
                  stringBuilder.append(c);
                  j = k;
                } catch (Exception exception) {
                  Zah.Zl(exception, Zk_.IGNORED);
                  stringBuilder.append(paramString.charAt(j));
                } 
              } else {
                Character character = Z_.get(str.toLowerCase());
                try {
                  if (character == null) {
                    stringBuilder.append(paramString.charAt(j));
                  } else {
                    stringBuilder.append(character.charValue());
                    j = k;
                  } 
                } catch (Exception exception) {
                  throw a(null);
                } 
              } 
            } else {
              stringBuilder.append(paramString.charAt(j));
            } 
          } else {
            stringBuilder.append(paramString.charAt(j));
          } 
          if (paramArrayOfint != null)
            i = ZE(paramArrayOfint, i, stringBuilder.length(), j + 1); 
          j++;
          continue;
        } 
      } catch (Exception exception) {
        throw a(null);
      } 
      return stringBuilder.toString();
    } 
  }
  
  private static int ZE(int[] paramArrayOfint, int paramInt1, int paramInt2, int paramInt3) {
    int i = paramInt1;
    while (true) {
      try {
        if (i < paramArrayOfint.length) {
          try {
            if (paramArrayOfint[i] == paramInt2) {
              paramArrayOfint[i] = paramInt3;
              return i + 1;
            } 
          } catch (NumberFormatException numberFormatException) {
            throw a(null);
          } 
          i++;
          continue;
        } 
      } catch (NumberFormatException numberFormatException) {
        throw a(null);
      } 
      return paramInt1;
    } 
  }
  
  public static String ZP(String paramString) {
    try {
      try {
      
      } catch (UnsupportedEncodingException unsupportedEncodingException) {
        throw a(null);
      } 
      return (paramString != null) ? URLDecoder.decode(paramString, Zae.Z_.displayName()) : null;
    } catch (UnsupportedEncodingException unsupportedEncodingException) {
      throw new RuntimeException(unsupportedEncodingException);
    } 
  }
  
  static {
    // Byte code:
    //   0: bipush #101
    //   2: anewarray java/lang/String
    //   5: astore_0
    //   6: iconst_0
    //   7: istore #4
    //   9: ldc 'aKC?'uCG7`A\$ kV\:'@WX:bVhKV$,dWX:pA\$ fME/jCV#7dV\:'jQY70|WX:fG["qJZ$-jV\:'wCD#,@v}PWX:PA\$ DA\$ fAP2*jA\$ dA@"&\CV#7hKQ2,hCV$JQY70dGY?$uN@%.PEG75KV\:'PCV#7dEG75@CV#7DCV#7JCV#7wGRJA\$ pOYJV\:'Qjz\\r`V]lGM5/LWX:dRZ%qKX30jPQ;`CV#7vJLfGQ?/lCV#7cPT5pELA\$ dCV#7dP\8$dA\$ pEG75lA\$ |G[jEG75FAP2*tWZ"uM@8'LEG75vXY?$DWX:pCV#7vWEeJWX:DV\:'@EG75DP\8$dOEvWEdjPQ0fWG$&`EG75iVpWX:vWEgJEG75@A\$ cPT5rEgPC4"lWX:vGV"lEG75jWX:|CV#7DgY?$k@F&lS@30cPT5rCLCV#7aGRDEG75kMA'
    //   11: dup
    //   12: astore_3
    //   13: invokevirtual length : ()I
    //   16: istore #5
    //   18: bipush #6
    //   20: istore_2
    //   21: iconst_m1
    //   22: istore_1
    //   23: bipush #6
    //   25: iinc #1, 1
    //   28: aload_3
    //   29: iload_1
    //   30: dup
    //   31: iload_2
    //   32: iadd
    //   33: invokevirtual substring : (II)Ljava/lang/String;
    //   36: iconst_m1
    //   37: goto -> 129
    //   40: aload_0
    //   41: swap
    //   42: iload #4
    //   44: iinc #4, 1
    //   47: swap
    //   48: aastore
    //   49: iload_1
    //   50: iload_2
    //   51: iadd
    //   52: dup
    //   53: istore_1
    //   54: iload #5
    //   56: if_icmpge -> 68
    //   59: aload_3
    //   60: iload_1
    //   61: invokevirtual charAt : (I)C
    //   64: istore_2
    //   65: goto -> 23
    //   68: ldc 'HpAkl'
    //   70: dup
    //   71: astore_3
    //   72: invokevirtual length : ()I
    //   75: istore #5
    //   77: iconst_4
    //   78: istore_2
    //   79: iconst_m1
    //   80: istore_1
    //   81: bipush #46
    //   83: iinc #1, 1
    //   86: aload_3
    //   87: iload_1
    //   88: dup
    //   89: iload_2
    //   90: iadd
    //   91: invokevirtual substring : (II)Ljava/lang/String;
    //   94: iconst_0
    //   95: goto -> 129
    //   98: aload_0
    //   99: swap
    //   100: iload #4
    //   102: iinc #4, 1
    //   105: swap
    //   106: aastore
    //   107: iload_1
    //   108: iload_2
    //   109: iadd
    //   110: dup
    //   111: istore_1
    //   112: iload #5
    //   114: if_icmpge -> 126
    //   117: aload_3
    //   118: iload_1
    //   119: invokevirtual charAt : (I)C
    //   122: istore_2
    //   123: goto -> 81
    //   126: goto -> 288
    //   129: dup_x2
    //   130: pop
    //   131: invokevirtual toCharArray : ()[C
    //   134: dup_x1
    //   135: arraylength
    //   136: dup_x2
    //   137: pop
    //   138: iconst_0
    //   139: istore #6
    //   141: dup2_x1
    //   142: pop2
    //   143: dup_x2
    //   144: iconst_1
    //   145: if_icmpgt -> 247
    //   148: dup2
    //   149: swap
    //   150: iload #6
    //   152: dup2_x1
    //   153: caload
    //   154: swap
    //   155: iload #6
    //   157: bipush #7
    //   159: irem
    //   160: tableswitch default -> 229, 0 -> 200, 1 -> 204, 2 -> 209, 3 -> 214, 4 -> 219, 5 -> 224
    //   200: iconst_3
    //   201: goto -> 231
    //   204: bipush #36
    //   206: goto -> 231
    //   209: bipush #51
    //   211: goto -> 231
    //   214: bipush #80
    //   216: goto -> 231
    //   219: bipush #69
    //   221: goto -> 231
    //   224: bipush #119
    //   226: goto -> 231
    //   229: bipush #87
    //   231: ixor
    //   232: ixor
    //   233: i2c
    //   234: castore
    //   235: iinc #6, 1
    //   238: dup
    //   239: ifne -> 247
    //   242: dup2
    //   243: dup_x1
    //   244: goto -> 152
    //   247: dup2_x1
    //   248: pop2
    //   249: dup_x2
    //   250: iload #6
    //   252: if_icmpgt -> 148
    //   255: pop
    //   256: new java/lang/String
    //   259: dup_x1
    //   260: swap
    //   261: invokespecial <init> : ([C)V
    //   264: invokevirtual intern : ()Ljava/lang/String;
    //   267: swap
    //   268: pop
    //   269: swap
    //   270: tableswitch default -> 40, 0 -> 98
    //   288: new java/util/HashMap
    //   291: dup
    //   292: invokespecial <init> : ()V
    //   295: putstatic net/portswigger/Zrzt.Z_ : Ljava/util/Map;
    //   298: getstatic net/portswigger/Zrzt.Z_ : Ljava/util/Map;
    //   301: aload_0
    //   302: bipush #63
    //   304: aaload
    //   305: bipush #34
    //   307: invokestatic valueOf : (C)Ljava/lang/Character;
    //   310: invokeinterface put : (Ljava/lang/Object;Ljava/lang/Object;)Ljava/lang/Object;
    //   315: pop
    //   316: getstatic net/portswigger/Zrzt.Z_ : Ljava/util/Map;
    //   319: aload_0
    //   320: bipush #74
    //   322: aaload
    //   323: bipush #38
    //   325: invokestatic valueOf : (C)Ljava/lang/Character;
    //   328: invokeinterface put : (Ljava/lang/Object;Ljava/lang/Object;)Ljava/lang/Object;
    //   333: pop
    //   334: getstatic net/portswigger/Zrzt.Z_ : Ljava/util/Map;
    //   337: aload_0
    //   338: bipush #79
    //   340: aaload
    //   341: bipush #60
    //   343: invokestatic valueOf : (C)Ljava/lang/Character;
    //   346: invokeinterface put : (Ljava/lang/Object;Ljava/lang/Object;)Ljava/lang/Object;
    //   351: pop
    //   352: getstatic net/portswigger/Zrzt.Z_ : Ljava/util/Map;
    //   355: aload_0
    //   356: iconst_5
    //   357: aaload
    //   358: bipush #62
    //   360: invokestatic valueOf : (C)Ljava/lang/Character;
    //   363: invokeinterface put : (Ljava/lang/Object;Ljava/lang/Object;)Ljava/lang/Object;
    //   368: pop
    //   369: getstatic net/portswigger/Zrzt.Z_ : Ljava/util/Map;
    //   372: aload_0
    //   373: bipush #46
    //   375: aaload
    //   376: bipush #39
    //   378: invokestatic valueOf : (C)Ljava/lang/Character;
    //   381: invokeinterface put : (Ljava/lang/Object;Ljava/lang/Object;)Ljava/lang/Object;
    //   386: pop
    //   387: getstatic net/portswigger/Zrzt.Z_ : Ljava/util/Map;
    //   390: aload_0
    //   391: bipush #92
    //   393: aaload
    //   394: bipush #32
    //   396: invokestatic valueOf : (C)Ljava/lang/Character;
    //   399: invokeinterface put : (Ljava/lang/Object;Ljava/lang/Object;)Ljava/lang/Object;
    //   404: pop
    //   405: getstatic net/portswigger/Zrzt.Z_ : Ljava/util/Map;
    //   408: aload_0
    //   409: bipush #44
    //   411: aaload
    //   412: sipush #161
    //   415: invokestatic valueOf : (C)Ljava/lang/Character;
    //   418: invokeinterface put : (Ljava/lang/Object;Ljava/lang/Object;)Ljava/lang/Object;
    //   423: pop
    //   424: getstatic net/portswigger/Zrzt.Z_ : Ljava/util/Map;
    //   427: aload_0
    //   428: bipush #14
    //   430: aaload
    //   431: sipush #162
    //   434: invokestatic valueOf : (C)Ljava/lang/Character;
    //   437: invokeinterface put : (Ljava/lang/Object;Ljava/lang/Object;)Ljava/lang/Object;
    //   442: pop
    //   443: getstatic net/portswigger/Zrzt.Z_ : Ljava/util/Map;
    //   446: aload_0
    //   447: bipush #64
    //   449: aaload
    //   450: sipush #163
    //   453: invokestatic valueOf : (C)Ljava/lang/Character;
    //   456: invokeinterface put : (Ljava/lang/Object;Ljava/lang/Object;)Ljava/lang/Object;
    //   461: pop
    //   462: getstatic net/portswigger/Zrzt.Z_ : Ljava/util/Map;
    //   465: aload_0
    //   466: bipush #77
    //   468: aaload
    //   469: sipush #164
    //   472: invokestatic valueOf : (C)Ljava/lang/Character;
    //   475: invokeinterface put : (Ljava/lang/Object;Ljava/lang/Object;)Ljava/lang/Object;
    //   480: pop
    //   481: getstatic net/portswigger/Zrzt.Z_ : Ljava/util/Map;
    //   484: aload_0
    //   485: bipush #60
    //   487: aaload
    //   488: sipush #165
    //   491: invokestatic valueOf : (C)Ljava/lang/Character;
    //   494: invokeinterface put : (Ljava/lang/Object;Ljava/lang/Object;)Ljava/lang/Object;
    //   499: pop
    //   500: getstatic net/portswigger/Zrzt.Z_ : Ljava/util/Map;
    //   503: aload_0
    //   504: bipush #85
    //   506: aaload
    //   507: sipush #166
    //   510: invokestatic valueOf : (C)Ljava/lang/Character;
    //   513: invokeinterface put : (Ljava/lang/Object;Ljava/lang/Object;)Ljava/lang/Object;
    //   518: pop
    //   519: getstatic net/portswigger/Zrzt.Z_ : Ljava/util/Map;
    //   522: aload_0
    //   523: bipush #87
    //   525: aaload
    //   526: sipush #167
    //   529: invokestatic valueOf : (C)Ljava/lang/Character;
    //   532: invokeinterface put : (Ljava/lang/Object;Ljava/lang/Object;)Ljava/lang/Object;
    //   537: pop
    //   538: getstatic net/portswigger/Zrzt.Z_ : Ljava/util/Map;
    //   541: aload_0
    //   542: bipush #40
    //   544: aaload
    //   545: sipush #168
    //   548: invokestatic valueOf : (C)Ljava/lang/Character;
    //   551: invokeinterface put : (Ljava/lang/Object;Ljava/lang/Object;)Ljava/lang/Object;
    //   556: pop
    //   557: getstatic net/portswigger/Zrzt.Z_ : Ljava/util/Map;
    //   560: aload_0
    //   561: bipush #9
    //   563: aaload
    //   564: sipush #169
    //   567: invokestatic valueOf : (C)Ljava/lang/Character;
    //   570: invokeinterface put : (Ljava/lang/Object;Ljava/lang/Object;)Ljava/lang/Object;
    //   575: pop
    //   576: getstatic net/portswigger/Zrzt.Z_ : Ljava/util/Map;
    //   579: aload_0
    //   580: bipush #76
    //   582: aaload
    //   583: sipush #170
    //   586: invokestatic valueOf : (C)Ljava/lang/Character;
    //   589: invokeinterface put : (Ljava/lang/Object;Ljava/lang/Object;)Ljava/lang/Object;
    //   594: pop
    //   595: getstatic net/portswigger/Zrzt.Z_ : Ljava/util/Map;
    //   598: aload_0
    //   599: bipush #100
    //   601: aaload
    //   602: sipush #171
    //   605: invokestatic valueOf : (C)Ljava/lang/Character;
    //   608: invokeinterface put : (Ljava/lang/Object;Ljava/lang/Object;)Ljava/lang/Object;
    //   613: pop
    //   614: getstatic net/portswigger/Zrzt.Z_ : Ljava/util/Map;
    //   617: aload_0
    //   618: bipush #98
    //   620: aaload
    //   621: sipush #172
    //   624: invokestatic valueOf : (C)Ljava/lang/Character;
    //   627: invokeinterface put : (Ljava/lang/Object;Ljava/lang/Object;)Ljava/lang/Object;
    //   632: pop
    //   633: getstatic net/portswigger/Zrzt.Z_ : Ljava/util/Map;
    //   636: aload_0
    //   637: bipush #50
    //   639: aaload
    //   640: sipush #173
    //   643: invokestatic valueOf : (C)Ljava/lang/Character;
    //   646: invokeinterface put : (Ljava/lang/Object;Ljava/lang/Object;)Ljava/lang/Object;
    //   651: pop
    //   652: getstatic net/portswigger/Zrzt.Z_ : Ljava/util/Map;
    //   655: aload_0
    //   656: bipush #38
    //   658: aaload
    //   659: sipush #174
    //   662: invokestatic valueOf : (C)Ljava/lang/Character;
    //   665: invokeinterface put : (Ljava/lang/Object;Ljava/lang/Object;)Ljava/lang/Object;
    //   670: pop
    //   671: getstatic net/portswigger/Zrzt.Z_ : Ljava/util/Map;
    //   674: aload_0
    //   675: bipush #27
    //   677: aaload
    //   678: sipush #175
    //   681: invokestatic valueOf : (C)Ljava/lang/Character;
    //   684: invokeinterface put : (Ljava/lang/Object;Ljava/lang/Object;)Ljava/lang/Object;
    //   689: pop
    //   690: getstatic net/portswigger/Zrzt.Z_ : Ljava/util/Map;
    //   693: aload_0
    //   694: bipush #96
    //   696: aaload
    //   697: sipush #176
    //   700: invokestatic valueOf : (C)Ljava/lang/Character;
    //   703: invokeinterface put : (Ljava/lang/Object;Ljava/lang/Object;)Ljava/lang/Object;
    //   708: pop
    //   709: getstatic net/portswigger/Zrzt.Z_ : Ljava/util/Map;
    //   712: aload_0
    //   713: bipush #30
    //   715: aaload
    //   716: sipush #177
    //   719: invokestatic valueOf : (C)Ljava/lang/Character;
    //   722: invokeinterface put : (Ljava/lang/Object;Ljava/lang/Object;)Ljava/lang/Object;
    //   727: pop
    //   728: getstatic net/portswigger/Zrzt.Z_ : Ljava/util/Map;
    //   731: aload_0
    //   732: bipush #75
    //   734: aaload
    //   735: sipush #178
    //   738: invokestatic valueOf : (C)Ljava/lang/Character;
    //   741: invokeinterface put : (Ljava/lang/Object;Ljava/lang/Object;)Ljava/lang/Object;
    //   746: pop
    //   747: getstatic net/portswigger/Zrzt.Z_ : Ljava/util/Map;
    //   750: aload_0
    //   751: bipush #69
    //   753: aaload
    //   754: sipush #179
    //   757: invokestatic valueOf : (C)Ljava/lang/Character;
    //   760: invokeinterface put : (Ljava/lang/Object;Ljava/lang/Object;)Ljava/lang/Object;
    //   765: pop
    //   766: getstatic net/portswigger/Zrzt.Z_ : Ljava/util/Map;
    //   769: aload_0
    //   770: bipush #24
    //   772: aaload
    //   773: sipush #180
    //   776: invokestatic valueOf : (C)Ljava/lang/Character;
    //   779: invokeinterface put : (Ljava/lang/Object;Ljava/lang/Object;)Ljava/lang/Object;
    //   784: pop
    //   785: getstatic net/portswigger/Zrzt.Z_ : Ljava/util/Map;
    //   788: aload_0
    //   789: bipush #6
    //   791: aaload
    //   792: sipush #181
    //   795: invokestatic valueOf : (C)Ljava/lang/Character;
    //   798: invokeinterface put : (Ljava/lang/Object;Ljava/lang/Object;)Ljava/lang/Object;
    //   803: pop
    //   804: getstatic net/portswigger/Zrzt.Z_ : Ljava/util/Map;
    //   807: aload_0
    //   808: iconst_1
    //   809: aaload
    //   810: sipush #182
    //   813: invokestatic valueOf : (C)Ljava/lang/Character;
    //   816: invokeinterface put : (Ljava/lang/Object;Ljava/lang/Object;)Ljava/lang/Object;
    //   821: pop
    //   822: getstatic net/portswigger/Zrzt.Z_ : Ljava/util/Map;
    //   825: aload_0
    //   826: bipush #26
    //   828: aaload
    //   829: sipush #183
    //   832: invokestatic valueOf : (C)Ljava/lang/Character;
    //   835: invokeinterface put : (Ljava/lang/Object;Ljava/lang/Object;)Ljava/lang/Object;
    //   840: pop
    //   841: getstatic net/portswigger/Zrzt.Z_ : Ljava/util/Map;
    //   844: aload_0
    //   845: bipush #51
    //   847: aaload
    //   848: sipush #184
    //   851: invokestatic valueOf : (C)Ljava/lang/Character;
    //   854: invokeinterface put : (Ljava/lang/Object;Ljava/lang/Object;)Ljava/lang/Object;
    //   859: pop
    //   860: getstatic net/portswigger/Zrzt.Z_ : Ljava/util/Map;
    //   863: aload_0
    //   864: bipush #81
    //   866: aaload
    //   867: sipush #185
    //   870: invokestatic valueOf : (C)Ljava/lang/Character;
    //   873: invokeinterface put : (Ljava/lang/Object;Ljava/lang/Object;)Ljava/lang/Object;
    //   878: pop
    //   879: getstatic net/portswigger/Zrzt.Z_ : Ljava/util/Map;
    //   882: aload_0
    //   883: bipush #48
    //   885: aaload
    //   886: sipush #186
    //   889: invokestatic valueOf : (C)Ljava/lang/Character;
    //   892: invokeinterface put : (Ljava/lang/Object;Ljava/lang/Object;)Ljava/lang/Object;
    //   897: pop
    //   898: getstatic net/portswigger/Zrzt.Z_ : Ljava/util/Map;
    //   901: aload_0
    //   902: bipush #17
    //   904: aaload
    //   905: sipush #187
    //   908: invokestatic valueOf : (C)Ljava/lang/Character;
    //   911: invokeinterface put : (Ljava/lang/Object;Ljava/lang/Object;)Ljava/lang/Object;
    //   916: pop
    //   917: getstatic net/portswigger/Zrzt.Z_ : Ljava/util/Map;
    //   920: aload_0
    //   921: bipush #84
    //   923: aaload
    //   924: sipush #188
    //   927: invokestatic valueOf : (C)Ljava/lang/Character;
    //   930: invokeinterface put : (Ljava/lang/Object;Ljava/lang/Object;)Ljava/lang/Object;
    //   935: pop
    //   936: getstatic net/portswigger/Zrzt.Z_ : Ljava/util/Map;
    //   939: aload_0
    //   940: bipush #94
    //   942: aaload
    //   943: sipush #189
    //   946: invokestatic valueOf : (C)Ljava/lang/Character;
    //   949: invokeinterface put : (Ljava/lang/Object;Ljava/lang/Object;)Ljava/lang/Object;
    //   954: pop
    //   955: getstatic net/portswigger/Zrzt.Z_ : Ljava/util/Map;
    //   958: aload_0
    //   959: bipush #53
    //   961: aaload
    //   962: sipush #190
    //   965: invokestatic valueOf : (C)Ljava/lang/Character;
    //   968: invokeinterface put : (Ljava/lang/Object;Ljava/lang/Object;)Ljava/lang/Object;
    //   973: pop
    //   974: getstatic net/portswigger/Zrzt.Z_ : Ljava/util/Map;
    //   977: aload_0
    //   978: bipush #93
    //   980: aaload
    //   981: sipush #191
    //   984: invokestatic valueOf : (C)Ljava/lang/Character;
    //   987: invokeinterface put : (Ljava/lang/Object;Ljava/lang/Object;)Ljava/lang/Object;
    //   992: pop
    //   993: getstatic net/portswigger/Zrzt.Z_ : Ljava/util/Map;
    //   996: aload_0
    //   997: bipush #97
    //   999: aaload
    //   1000: sipush #192
    //   1003: invokestatic valueOf : (C)Ljava/lang/Character;
    //   1006: invokeinterface put : (Ljava/lang/Object;Ljava/lang/Object;)Ljava/lang/Object;
    //   1011: pop
    //   1012: getstatic net/portswigger/Zrzt.Z_ : Ljava/util/Map;
    //   1015: aload_0
    //   1016: bipush #36
    //   1018: aaload
    //   1019: sipush #193
    //   1022: invokestatic valueOf : (C)Ljava/lang/Character;
    //   1025: invokeinterface put : (Ljava/lang/Object;Ljava/lang/Object;)Ljava/lang/Object;
    //   1030: pop
    //   1031: getstatic net/portswigger/Zrzt.Z_ : Ljava/util/Map;
    //   1034: aload_0
    //   1035: bipush #21
    //   1037: aaload
    //   1038: sipush #194
    //   1041: invokestatic valueOf : (C)Ljava/lang/Character;
    //   1044: invokeinterface put : (Ljava/lang/Object;Ljava/lang/Object;)Ljava/lang/Object;
    //   1049: pop
    //   1050: getstatic net/portswigger/Zrzt.Z_ : Ljava/util/Map;
    //   1053: aload_0
    //   1054: bipush #71
    //   1056: aaload
    //   1057: sipush #195
    //   1060: invokestatic valueOf : (C)Ljava/lang/Character;
    //   1063: invokeinterface put : (Ljava/lang/Object;Ljava/lang/Object;)Ljava/lang/Object;
    //   1068: pop
    //   1069: getstatic net/portswigger/Zrzt.Z_ : Ljava/util/Map;
    //   1072: aload_0
    //   1073: bipush #67
    //   1075: aaload
    //   1076: sipush #196
    //   1079: invokestatic valueOf : (C)Ljava/lang/Character;
    //   1082: invokeinterface put : (Ljava/lang/Object;Ljava/lang/Object;)Ljava/lang/Object;
    //   1087: pop
    //   1088: getstatic net/portswigger/Zrzt.Z_ : Ljava/util/Map;
    //   1091: aload_0
    //   1092: bipush #73
    //   1094: aaload
    //   1095: sipush #197
    //   1098: invokestatic valueOf : (C)Ljava/lang/Character;
    //   1101: invokeinterface put : (Ljava/lang/Object;Ljava/lang/Object;)Ljava/lang/Object;
    //   1106: pop
    //   1107: getstatic net/portswigger/Zrzt.Z_ : Ljava/util/Map;
    //   1110: aload_0
    //   1111: bipush #91
    //   1113: aaload
    //   1114: sipush #198
    //   1117: invokestatic valueOf : (C)Ljava/lang/Character;
    //   1120: invokeinterface put : (Ljava/lang/Object;Ljava/lang/Object;)Ljava/lang/Object;
    //   1125: pop
    //   1126: getstatic net/portswigger/Zrzt.Z_ : Ljava/util/Map;
    //   1129: aload_0
    //   1130: bipush #62
    //   1132: aaload
    //   1133: sipush #199
    //   1136: invokestatic valueOf : (C)Ljava/lang/Character;
    //   1139: invokeinterface put : (Ljava/lang/Object;Ljava/lang/Object;)Ljava/lang/Object;
    //   1144: pop
    //   1145: getstatic net/portswigger/Zrzt.Z_ : Ljava/util/Map;
    //   1148: aload_0
    //   1149: bipush #72
    //   1151: aaload
    //   1152: sipush #200
    //   1155: invokestatic valueOf : (C)Ljava/lang/Character;
    //   1158: invokeinterface put : (Ljava/lang/Object;Ljava/lang/Object;)Ljava/lang/Object;
    //   1163: pop
    //   1164: getstatic net/portswigger/Zrzt.Z_ : Ljava/util/Map;
    //   1167: aload_0
    //   1168: bipush #35
    //   1170: aaload
    //   1171: sipush #201
    //   1174: invokestatic valueOf : (C)Ljava/lang/Character;
    //   1177: invokeinterface put : (Ljava/lang/Object;Ljava/lang/Object;)Ljava/lang/Object;
    //   1182: pop
    //   1183: getstatic net/portswigger/Zrzt.Z_ : Ljava/util/Map;
    //   1186: aload_0
    //   1187: bipush #83
    //   1189: aaload
    //   1190: sipush #202
    //   1193: invokestatic valueOf : (C)Ljava/lang/Character;
    //   1196: invokeinterface put : (Ljava/lang/Object;Ljava/lang/Object;)Ljava/lang/Object;
    //   1201: pop
    //   1202: getstatic net/portswigger/Zrzt.Z_ : Ljava/util/Map;
    //   1205: aload_0
    //   1206: iconst_4
    //   1207: aaload
    //   1208: sipush #203
    //   1211: invokestatic valueOf : (C)Ljava/lang/Character;
    //   1214: invokeinterface put : (Ljava/lang/Object;Ljava/lang/Object;)Ljava/lang/Object;
    //   1219: pop
    //   1220: getstatic net/portswigger/Zrzt.Z_ : Ljava/util/Map;
    //   1223: aload_0
    //   1224: bipush #65
    //   1226: aaload
    //   1227: sipush #204
    //   1230: invokestatic valueOf : (C)Ljava/lang/Character;
    //   1233: invokeinterface put : (Ljava/lang/Object;Ljava/lang/Object;)Ljava/lang/Object;
    //   1238: pop
    //   1239: getstatic net/portswigger/Zrzt.Z_ : Ljava/util/Map;
    //   1242: aload_0
    //   1243: bipush #95
    //   1245: aaload
    //   1246: sipush #205
    //   1249: invokestatic valueOf : (C)Ljava/lang/Character;
    //   1252: invokeinterface put : (Ljava/lang/Object;Ljava/lang/Object;)Ljava/lang/Object;
    //   1257: pop
    //   1258: getstatic net/portswigger/Zrzt.Z_ : Ljava/util/Map;
    //   1261: aload_0
    //   1262: bipush #54
    //   1264: aaload
    //   1265: sipush #206
    //   1268: invokestatic valueOf : (C)Ljava/lang/Character;
    //   1271: invokeinterface put : (Ljava/lang/Object;Ljava/lang/Object;)Ljava/lang/Object;
    //   1276: pop
    //   1277: getstatic net/portswigger/Zrzt.Z_ : Ljava/util/Map;
    //   1280: aload_0
    //   1281: bipush #45
    //   1283: aaload
    //   1284: sipush #207
    //   1287: invokestatic valueOf : (C)Ljava/lang/Character;
    //   1290: invokeinterface put : (Ljava/lang/Object;Ljava/lang/Object;)Ljava/lang/Object;
    //   1295: pop
    //   1296: getstatic net/portswigger/Zrzt.Z_ : Ljava/util/Map;
    //   1299: aload_0
    //   1300: bipush #18
    //   1302: aaload
    //   1303: sipush #208
    //   1306: invokestatic valueOf : (C)Ljava/lang/Character;
    //   1309: invokeinterface put : (Ljava/lang/Object;Ljava/lang/Object;)Ljava/lang/Object;
    //   1314: pop
    //   1315: getstatic net/portswigger/Zrzt.Z_ : Ljava/util/Map;
    //   1318: aload_0
    //   1319: bipush #32
    //   1321: aaload
    //   1322: sipush #209
    //   1325: invokestatic valueOf : (C)Ljava/lang/Character;
    //   1328: invokeinterface put : (Ljava/lang/Object;Ljava/lang/Object;)Ljava/lang/Object;
    //   1333: pop
    //   1334: getstatic net/portswigger/Zrzt.Z_ : Ljava/util/Map;
    //   1337: aload_0
    //   1338: bipush #82
    //   1340: aaload
    //   1341: sipush #210
    //   1344: invokestatic valueOf : (C)Ljava/lang/Character;
    //   1347: invokeinterface put : (Ljava/lang/Object;Ljava/lang/Object;)Ljava/lang/Object;
    //   1352: pop
    //   1353: getstatic net/portswigger/Zrzt.Z_ : Ljava/util/Map;
    //   1356: aload_0
    //   1357: bipush #37
    //   1359: aaload
    //   1360: sipush #211
    //   1363: invokestatic valueOf : (C)Ljava/lang/Character;
    //   1366: invokeinterface put : (Ljava/lang/Object;Ljava/lang/Object;)Ljava/lang/Object;
    //   1371: pop
    //   1372: getstatic net/portswigger/Zrzt.Z_ : Ljava/util/Map;
    //   1375: aload_0
    //   1376: bipush #39
    //   1378: aaload
    //   1379: sipush #212
    //   1382: invokestatic valueOf : (C)Ljava/lang/Character;
    //   1385: invokeinterface put : (Ljava/lang/Object;Ljava/lang/Object;)Ljava/lang/Object;
    //   1390: pop
    //   1391: getstatic net/portswigger/Zrzt.Z_ : Ljava/util/Map;
    //   1394: aload_0
    //   1395: bipush #41
    //   1397: aaload
    //   1398: sipush #213
    //   1401: invokestatic valueOf : (C)Ljava/lang/Character;
    //   1404: invokeinterface put : (Ljava/lang/Object;Ljava/lang/Object;)Ljava/lang/Object;
    //   1409: pop
    //   1410: getstatic net/portswigger/Zrzt.Z_ : Ljava/util/Map;
    //   1413: aload_0
    //   1414: bipush #70
    //   1416: aaload
    //   1417: sipush #214
    //   1420: invokestatic valueOf : (C)Ljava/lang/Character;
    //   1423: invokeinterface put : (Ljava/lang/Object;Ljava/lang/Object;)Ljava/lang/Object;
    //   1428: pop
    //   1429: getstatic net/portswigger/Zrzt.Z_ : Ljava/util/Map;
    //   1432: aload_0
    //   1433: bipush #47
    //   1435: aaload
    //   1436: sipush #215
    //   1439: invokestatic valueOf : (C)Ljava/lang/Character;
    //   1442: invokeinterface put : (Ljava/lang/Object;Ljava/lang/Object;)Ljava/lang/Object;
    //   1447: pop
    //   1448: getstatic net/portswigger/Zrzt.Z_ : Ljava/util/Map;
    //   1451: aload_0
    //   1452: bipush #28
    //   1454: aaload
    //   1455: sipush #216
    //   1458: invokestatic valueOf : (C)Ljava/lang/Character;
    //   1461: invokeinterface put : (Ljava/lang/Object;Ljava/lang/Object;)Ljava/lang/Object;
    //   1466: pop
    //   1467: getstatic net/portswigger/Zrzt.Z_ : Ljava/util/Map;
    //   1470: aload_0
    //   1471: bipush #31
    //   1473: aaload
    //   1474: sipush #217
    //   1477: invokestatic valueOf : (C)Ljava/lang/Character;
    //   1480: invokeinterface put : (Ljava/lang/Object;Ljava/lang/Object;)Ljava/lang/Object;
    //   1485: pop
    //   1486: getstatic net/portswigger/Zrzt.Z_ : Ljava/util/Map;
    //   1489: aload_0
    //   1490: bipush #33
    //   1492: aaload
    //   1493: sipush #218
    //   1496: invokestatic valueOf : (C)Ljava/lang/Character;
    //   1499: invokeinterface put : (Ljava/lang/Object;Ljava/lang/Object;)Ljava/lang/Object;
    //   1504: pop
    //   1505: getstatic net/portswigger/Zrzt.Z_ : Ljava/util/Map;
    //   1508: aload_0
    //   1509: bipush #20
    //   1511: aaload
    //   1512: sipush #219
    //   1515: invokestatic valueOf : (C)Ljava/lang/Character;
    //   1518: invokeinterface put : (Ljava/lang/Object;Ljava/lang/Object;)Ljava/lang/Object;
    //   1523: pop
    //   1524: getstatic net/portswigger/Zrzt.Z_ : Ljava/util/Map;
    //   1527: aload_0
    //   1528: bipush #19
    //   1530: aaload
    //   1531: sipush #220
    //   1534: invokestatic valueOf : (C)Ljava/lang/Character;
    //   1537: invokeinterface put : (Ljava/lang/Object;Ljava/lang/Object;)Ljava/lang/Object;
    //   1542: pop
    //   1543: getstatic net/portswigger/Zrzt.Z_ : Ljava/util/Map;
    //   1546: aload_0
    //   1547: bipush #25
    //   1549: aaload
    //   1550: sipush #221
    //   1553: invokestatic valueOf : (C)Ljava/lang/Character;
    //   1556: invokeinterface put : (Ljava/lang/Object;Ljava/lang/Object;)Ljava/lang/Object;
    //   1561: pop
    //   1562: getstatic net/portswigger/Zrzt.Z_ : Ljava/util/Map;
    //   1565: aload_0
    //   1566: bipush #42
    //   1568: aaload
    //   1569: sipush #222
    //   1572: invokestatic valueOf : (C)Ljava/lang/Character;
    //   1575: invokeinterface put : (Ljava/lang/Object;Ljava/lang/Object;)Ljava/lang/Object;
    //   1580: pop
    //   1581: getstatic net/portswigger/Zrzt.Z_ : Ljava/util/Map;
    //   1584: aload_0
    //   1585: bipush #66
    //   1587: aaload
    //   1588: sipush #223
    //   1591: invokestatic valueOf : (C)Ljava/lang/Character;
    //   1594: invokeinterface put : (Ljava/lang/Object;Ljava/lang/Object;)Ljava/lang/Object;
    //   1599: pop
    //   1600: getstatic net/portswigger/Zrzt.Z_ : Ljava/util/Map;
    //   1603: aload_0
    //   1604: bipush #34
    //   1606: aaload
    //   1607: sipush #224
    //   1610: invokestatic valueOf : (C)Ljava/lang/Character;
    //   1613: invokeinterface put : (Ljava/lang/Object;Ljava/lang/Object;)Ljava/lang/Object;
    //   1618: pop
    //   1619: getstatic net/portswigger/Zrzt.Z_ : Ljava/util/Map;
    //   1622: aload_0
    //   1623: bipush #55
    //   1625: aaload
    //   1626: sipush #225
    //   1629: invokestatic valueOf : (C)Ljava/lang/Character;
    //   1632: invokeinterface put : (Ljava/lang/Object;Ljava/lang/Object;)Ljava/lang/Object;
    //   1637: pop
    //   1638: getstatic net/portswigger/Zrzt.Z_ : Ljava/util/Map;
    //   1641: aload_0
    //   1642: bipush #57
    //   1644: aaload
    //   1645: sipush #226
    //   1648: invokestatic valueOf : (C)Ljava/lang/Character;
    //   1651: invokeinterface put : (Ljava/lang/Object;Ljava/lang/Object;)Ljava/lang/Object;
    //   1656: pop
    //   1657: getstatic net/portswigger/Zrzt.Z_ : Ljava/util/Map;
    //   1660: aload_0
    //   1661: bipush #11
    //   1663: aaload
    //   1664: sipush #227
    //   1667: invokestatic valueOf : (C)Ljava/lang/Character;
    //   1670: invokeinterface put : (Ljava/lang/Object;Ljava/lang/Object;)Ljava/lang/Object;
    //   1675: pop
    //   1676: getstatic net/portswigger/Zrzt.Z_ : Ljava/util/Map;
    //   1679: aload_0
    //   1680: bipush #7
    //   1682: aaload
    //   1683: sipush #228
    //   1686: invokestatic valueOf : (C)Ljava/lang/Character;
    //   1689: invokeinterface put : (Ljava/lang/Object;Ljava/lang/Object;)Ljava/lang/Object;
    //   1694: pop
    //   1695: getstatic net/portswigger/Zrzt.Z_ : Ljava/util/Map;
    //   1698: aload_0
    //   1699: bipush #56
    //   1701: aaload
    //   1702: sipush #229
    //   1705: invokestatic valueOf : (C)Ljava/lang/Character;
    //   1708: invokeinterface put : (Ljava/lang/Object;Ljava/lang/Object;)Ljava/lang/Object;
    //   1713: pop
    //   1714: getstatic net/portswigger/Zrzt.Z_ : Ljava/util/Map;
    //   1717: aload_0
    //   1718: bipush #29
    //   1720: aaload
    //   1721: sipush #230
    //   1724: invokestatic valueOf : (C)Ljava/lang/Character;
    //   1727: invokeinterface put : (Ljava/lang/Object;Ljava/lang/Object;)Ljava/lang/Object;
    //   1732: pop
    //   1733: getstatic net/portswigger/Zrzt.Z_ : Ljava/util/Map;
    //   1736: aload_0
    //   1737: bipush #22
    //   1739: aaload
    //   1740: sipush #231
    //   1743: invokestatic valueOf : (C)Ljava/lang/Character;
    //   1746: invokeinterface put : (Ljava/lang/Object;Ljava/lang/Object;)Ljava/lang/Object;
    //   1751: pop
    //   1752: getstatic net/portswigger/Zrzt.Z_ : Ljava/util/Map;
    //   1755: aload_0
    //   1756: bipush #78
    //   1758: aaload
    //   1759: sipush #232
    //   1762: invokestatic valueOf : (C)Ljava/lang/Character;
    //   1765: invokeinterface put : (Ljava/lang/Object;Ljava/lang/Object;)Ljava/lang/Object;
    //   1770: pop
    //   1771: getstatic net/portswigger/Zrzt.Z_ : Ljava/util/Map;
    //   1774: aload_0
    //   1775: bipush #49
    //   1777: aaload
    //   1778: sipush #233
    //   1781: invokestatic valueOf : (C)Ljava/lang/Character;
    //   1784: invokeinterface put : (Ljava/lang/Object;Ljava/lang/Object;)Ljava/lang/Object;
    //   1789: pop
    //   1790: getstatic net/portswigger/Zrzt.Z_ : Ljava/util/Map;
    //   1793: aload_0
    //   1794: iconst_2
    //   1795: aaload
    //   1796: sipush #234
    //   1799: invokestatic valueOf : (C)Ljava/lang/Character;
    //   1802: invokeinterface put : (Ljava/lang/Object;Ljava/lang/Object;)Ljava/lang/Object;
    //   1807: pop
    //   1808: getstatic net/portswigger/Zrzt.Z_ : Ljava/util/Map;
    //   1811: aload_0
    //   1812: bipush #99
    //   1814: aaload
    //   1815: sipush #235
    //   1818: invokestatic valueOf : (C)Ljava/lang/Character;
    //   1821: invokeinterface put : (Ljava/lang/Object;Ljava/lang/Object;)Ljava/lang/Object;
    //   1826: pop
    //   1827: getstatic net/portswigger/Zrzt.Z_ : Ljava/util/Map;
    //   1830: aload_0
    //   1831: bipush #88
    //   1833: aaload
    //   1834: sipush #236
    //   1837: invokestatic valueOf : (C)Ljava/lang/Character;
    //   1840: invokeinterface put : (Ljava/lang/Object;Ljava/lang/Object;)Ljava/lang/Object;
    //   1845: pop
    //   1846: getstatic net/portswigger/Zrzt.Z_ : Ljava/util/Map;
    //   1849: aload_0
    //   1850: bipush #52
    //   1852: aaload
    //   1853: sipush #237
    //   1856: invokestatic valueOf : (C)Ljava/lang/Character;
    //   1859: invokeinterface put : (Ljava/lang/Object;Ljava/lang/Object;)Ljava/lang/Object;
    //   1864: pop
    //   1865: getstatic net/portswigger/Zrzt.Z_ : Ljava/util/Map;
    //   1868: aload_0
    //   1869: bipush #59
    //   1871: aaload
    //   1872: sipush #238
    //   1875: invokestatic valueOf : (C)Ljava/lang/Character;
    //   1878: invokeinterface put : (Ljava/lang/Object;Ljava/lang/Object;)Ljava/lang/Object;
    //   1883: pop
    //   1884: getstatic net/portswigger/Zrzt.Z_ : Ljava/util/Map;
    //   1887: aload_0
    //   1888: bipush #86
    //   1890: aaload
    //   1891: sipush #239
    //   1894: invokestatic valueOf : (C)Ljava/lang/Character;
    //   1897: invokeinterface put : (Ljava/lang/Object;Ljava/lang/Object;)Ljava/lang/Object;
    //   1902: pop
    //   1903: getstatic net/portswigger/Zrzt.Z_ : Ljava/util/Map;
    //   1906: aload_0
    //   1907: bipush #43
    //   1909: aaload
    //   1910: sipush #240
    //   1913: invokestatic valueOf : (C)Ljava/lang/Character;
    //   1916: invokeinterface put : (Ljava/lang/Object;Ljava/lang/Object;)Ljava/lang/Object;
    //   1921: pop
    //   1922: getstatic net/portswigger/Zrzt.Z_ : Ljava/util/Map;
    //   1925: aload_0
    //   1926: iconst_3
    //   1927: aaload
    //   1928: sipush #241
    //   1931: invokestatic valueOf : (C)Ljava/lang/Character;
    //   1934: invokeinterface put : (Ljava/lang/Object;Ljava/lang/Object;)Ljava/lang/Object;
    //   1939: pop
    //   1940: getstatic net/portswigger/Zrzt.Z_ : Ljava/util/Map;
    //   1943: aload_0
    //   1944: bipush #61
    //   1946: aaload
    //   1947: sipush #242
    //   1950: invokestatic valueOf : (C)Ljava/lang/Character;
    //   1953: invokeinterface put : (Ljava/lang/Object;Ljava/lang/Object;)Ljava/lang/Object;
    //   1958: pop
    //   1959: getstatic net/portswigger/Zrzt.Z_ : Ljava/util/Map;
    //   1962: aload_0
    //   1963: bipush #10
    //   1965: aaload
    //   1966: sipush #243
    //   1969: invokestatic valueOf : (C)Ljava/lang/Character;
    //   1972: invokeinterface put : (Ljava/lang/Object;Ljava/lang/Object;)Ljava/lang/Object;
    //   1977: pop
    //   1978: getstatic net/portswigger/Zrzt.Z_ : Ljava/util/Map;
    //   1981: aload_0
    //   1982: bipush #23
    //   1984: aaload
    //   1985: sipush #244
    //   1988: invokestatic valueOf : (C)Ljava/lang/Character;
    //   1991: invokeinterface put : (Ljava/lang/Object;Ljava/lang/Object;)Ljava/lang/Object;
    //   1996: pop
    //   1997: getstatic net/portswigger/Zrzt.Z_ : Ljava/util/Map;
    //   2000: aload_0
    //   2001: bipush #16
    //   2003: aaload
    //   2004: sipush #245
    //   2007: invokestatic valueOf : (C)Ljava/lang/Character;
    //   2010: invokeinterface put : (Ljava/lang/Object;Ljava/lang/Object;)Ljava/lang/Object;
    //   2015: pop
    //   2016: getstatic net/portswigger/Zrzt.Z_ : Ljava/util/Map;
    //   2019: aload_0
    //   2020: bipush #89
    //   2022: aaload
    //   2023: sipush #246
    //   2026: invokestatic valueOf : (C)Ljava/lang/Character;
    //   2029: invokeinterface put : (Ljava/lang/Object;Ljava/lang/Object;)Ljava/lang/Object;
    //   2034: pop
    //   2035: getstatic net/portswigger/Zrzt.Z_ : Ljava/util/Map;
    //   2038: aload_0
    //   2039: iconst_0
    //   2040: aaload
    //   2041: sipush #247
    //   2044: invokestatic valueOf : (C)Ljava/lang/Character;
    //   2047: invokeinterface put : (Ljava/lang/Object;Ljava/lang/Object;)Ljava/lang/Object;
    //   2052: pop
    //   2053: getstatic net/portswigger/Zrzt.Z_ : Ljava/util/Map;
    //   2056: aload_0
    //   2057: bipush #12
    //   2059: aaload
    //   2060: sipush #248
    //   2063: invokestatic valueOf : (C)Ljava/lang/Character;
    //   2066: invokeinterface put : (Ljava/lang/Object;Ljava/lang/Object;)Ljava/lang/Object;
    //   2071: pop
    //   2072: getstatic net/portswigger/Zrzt.Z_ : Ljava/util/Map;
    //   2075: aload_0
    //   2076: bipush #58
    //   2078: aaload
    //   2079: sipush #249
    //   2082: invokestatic valueOf : (C)Ljava/lang/Character;
    //   2085: invokeinterface put : (Ljava/lang/Object;Ljava/lang/Object;)Ljava/lang/Object;
    //   2090: pop
    //   2091: getstatic net/portswigger/Zrzt.Z_ : Ljava/util/Map;
    //   2094: aload_0
    //   2095: bipush #68
    //   2097: aaload
    //   2098: sipush #250
    //   2101: invokestatic valueOf : (C)Ljava/lang/Character;
    //   2104: invokeinterface put : (Ljava/lang/Object;Ljava/lang/Object;)Ljava/lang/Object;
    //   2109: pop
    //   2110: getstatic net/portswigger/Zrzt.Z_ : Ljava/util/Map;
    //   2113: aload_0
    //   2114: bipush #8
    //   2116: aaload
    //   2117: sipush #251
    //   2120: invokestatic valueOf : (C)Ljava/lang/Character;
    //   2123: invokeinterface put : (Ljava/lang/Object;Ljava/lang/Object;)Ljava/lang/Object;
    //   2128: pop
    //   2129: getstatic net/portswigger/Zrzt.Z_ : Ljava/util/Map;
    //   2132: aload_0
    //   2133: bipush #80
    //   2135: aaload
    //   2136: sipush #252
    //   2139: invokestatic valueOf : (C)Ljava/lang/Character;
    //   2142: invokeinterface put : (Ljava/lang/Object;Ljava/lang/Object;)Ljava/lang/Object;
    //   2147: pop
    //   2148: getstatic net/portswigger/Zrzt.Z_ : Ljava/util/Map;
    //   2151: aload_0
    //   2152: bipush #90
    //   2154: aaload
    //   2155: sipush #253
    //   2158: invokestatic valueOf : (C)Ljava/lang/Character;
    //   2161: invokeinterface put : (Ljava/lang/Object;Ljava/lang/Object;)Ljava/lang/Object;
    //   2166: pop
    //   2167: getstatic net/portswigger/Zrzt.Z_ : Ljava/util/Map;
    //   2170: aload_0
    //   2171: bipush #15
    //   2173: aaload
    //   2174: sipush #254
    //   2177: invokestatic valueOf : (C)Ljava/lang/Character;
    //   2180: invokeinterface put : (Ljava/lang/Object;Ljava/lang/Object;)Ljava/lang/Object;
    //   2185: pop
    //   2186: getstatic net/portswigger/Zrzt.Z_ : Ljava/util/Map;
    //   2189: aload_0
    //   2190: bipush #13
    //   2192: aaload
    //   2193: sipush #255
    //   2196: invokestatic valueOf : (C)Ljava/lang/Character;
    //   2199: invokeinterface put : (Ljava/lang/Object;Ljava/lang/Object;)Ljava/lang/Object;
    //   2204: pop
    //   2205: return
  }
  
  private static Exception a(Exception paramException) {
    return paramException;
  }
}


/* Location:              C:\Program Files\BurpSuitePro\burpsuite_pro.jar!\net\portswigger\Zrzt.class
 * Java compiler version: 21 (65.0)
 * JD-Core Version:       1.1.3
 */