package net.portswigger;

import java.lang.reflect.Constructor;
import java.lang.reflect.GenericArrayType;
import java.lang.reflect.Modifier;
import java.lang.reflect.ParameterizedType;
import java.lang.reflect.Type;
import java.util.Arrays;
import java.util.List;
import java.util.Map;
import java.util.Set;
import java.util.function.Function;
import java.util.regex.Pattern;

public class Zt7 {
  private static final Set<Type> Zy;
  
  private static final String[] a;
  
  private static final String[] b;
  
  public static boolean Zb(Type paramType) {
    return Zy.contains(paramType);
  }
  
  public static boolean Zf(Type paramType) {
    if (paramType instanceof ParameterizedType) {
      ParameterizedType parameterizedType = (ParameterizedType)paramType;
      Type type = parameterizedType.getRawType();
      try {
        if (!List.class.equals(type)) {
          try {
            if (Map.class.equals(type));
          } catch (UnsupportedOperationException unsupportedOperationException) {
            throw a(null);
          } 
          return false;
        } 
      } catch (UnsupportedOperationException unsupportedOperationException) {
        throw a(null);
      } 
    } else {
      try {
        if (paramType instanceof GenericArrayType)
          return true; 
      } catch (UnsupportedOperationException unsupportedOperationException) {
        throw a(null);
      } 
      try {
        if (paramType instanceof Class)
          try {
            if (((Class)paramType).isArray())
              return true; 
          } catch (UnsupportedOperationException unsupportedOperationException) {
            throw a(null);
          }  
      } catch (UnsupportedOperationException unsupportedOperationException) {
        throw a(null);
      } 
      return false;
    } 
  }
  
  public static String Zu(String paramString) {
    StringBuilder stringBuilder = new StringBuilder();
    boolean bool = false;
    boolean bool1 = false;
    for (byte b = 0; b < paramString.length(); b++) {
      char c = paramString.charAt(b);
      try {
        if (Character.isUpperCase(c)) {
          try {
            if (b > 0)
              try {
                if (!bool)
                  stringBuilder.append('_'); 
              } catch (UnsupportedOperationException unsupportedOperationException) {
                throw a(null);
              }  
          } catch (UnsupportedOperationException unsupportedOperationException) {
            throw a(null);
          } 
          stringBuilder.append(Character.toLowerCase(c));
        } else {
          try {
            if (Character.isDigit(c)) {
              try {
                if (b > 0)
                  try {
                    if (!bool1)
                      try {
                        if (!bool)
                          stringBuilder.append('_'); 
                      } catch (UnsupportedOperationException unsupportedOperationException) {
                        throw a(null);
                      }  
                  } catch (UnsupportedOperationException unsupportedOperationException) {
                    throw a(null);
                  }  
              } catch (UnsupportedOperationException unsupportedOperationException) {
                throw a(null);
              } 
              stringBuilder.append(c);
            } else {
              stringBuilder.append(c);
            } 
          } catch (UnsupportedOperationException unsupportedOperationException) {
            throw a(null);
          } 
        } 
      } catch (UnsupportedOperationException unsupportedOperationException) {
        throw a(null);
      } 
      try {
      
      } catch (UnsupportedOperationException unsupportedOperationException) {
        throw a(null);
      } 
      bool = (c == '_') ? true : false;
      bool1 = Character.isDigit(c);
    } 
    return stringBuilder.toString();
  }
  
  static String Zm(String paramString1, String paramString2) {
    try {
    
    } catch (UnsupportedOperationException unsupportedOperationException) {
      throw a(null);
    } 
    return paramString1.isEmpty() ? paramString1 : ZS(a(-24717, -23858), Zcy.Zb, Zcy.Z_, paramString1, paramString2);
  }
  
  static String ZS(String paramString1, Pattern paramPattern, String paramString2, String paramString3, String paramString4) {
    try {
      if (paramString3.isEmpty() || !paramPattern.matcher(paramString3).matches()) {
        String str1 = paramString4;
        String str2 = paramString3;
        String str3 = paramString2;
        throw new UnsupportedOperationException(paramString1 + paramString1 + a(-24713, -30646) + str3 + a(-24715, 10449) + str2 + a(-24720, -15755));
      } 
    } catch (UnsupportedOperationException unsupportedOperationException) {
      throw a(null);
    } 
    return paramString3;
  }
  
  static String Zh(String paramString1, String paramString2) {
    return ZS(a(-24716, 5922), Zfm.ZU, a(-24719, -8236), paramString1, paramString2);
  }
  
  static Constructor ZY(Zas paramZas, Type paramType) {
    Class clazz = (Class)paramType;
    Constructor<Zox> constructor = null;
    for (Constructor<Zox> constructor1 : clazz.getDeclaredConstructors()) {
      Zox zox = constructor1.<Zox>getAnnotation(Zox.class);
      try {
        if (zox != null) {
          try {
            if (constructor != null)
              paramZas.Zs((Function)Zqg.Zw(Zla.CONSTRUCTOR), clazz, (Zsi)clazz.getAnnotation(Zsi.class), a(-24718, 2717), new Object[0]); 
          } catch (UnsupportedOperationException unsupportedOperationException) {
            throw a(null);
          } 
          int i = constructor1.getModifiers();
          try {
            if (!Modifier.isPublic(i))
              paramZas.Zs((Function)Zqg.Zy(Zla.MODIFIER), clazz, (Zsi)clazz.getAnnotation(Zsi.class), a(-24714, 7040), new Object[0]); 
          } catch (UnsupportedOperationException unsupportedOperationException) {
            throw a(null);
          } 
          constructor = constructor1;
        } 
      } catch (UnsupportedOperationException unsupportedOperationException) {
        throw a(null);
      } 
    } 
    return constructor;
  }
  
  public static boolean Zc(Type paramType1, Type paramType2) {
    try {
      if (paramType1 instanceof ParameterizedType)
        try {
          if (paramType2 instanceof ParameterizedType) {
            try {
              if (Arrays.equals((Object[])((ParameterizedType)paramType1).getActualTypeArguments(), (Object[])((ParameterizedType)paramType2).getActualTypeArguments()))
                try {
                  if (Zc(((ParameterizedType)paramType1).getRawType(), ((ParameterizedType)paramType2).getRawType()));
                } catch (UnsupportedOperationException unsupportedOperationException) {
                  throw a(null);
                }  
            } catch (UnsupportedOperationException unsupportedOperationException) {
              throw a(null);
            } 
            return false;
          } 
        } catch (UnsupportedOperationException unsupportedOperationException) {
          throw a(null);
        }  
    } catch (UnsupportedOperationException unsupportedOperationException) {
      throw a(null);
    } 
    try {
      if (paramType1 instanceof ParameterizedType)
        return Zc(((ParameterizedType)paramType1).getRawType(), paramType2); 
    } catch (UnsupportedOperationException unsupportedOperationException) {
      throw a(null);
    } 
    try {
      if (paramType2 instanceof ParameterizedType)
        return Zc(paramType1, ((ParameterizedType)paramType2).getRawType()); 
    } catch (UnsupportedOperationException unsupportedOperationException) {
      throw a(null);
    } 
    return Zd(paramType1).isAssignableFrom(Zd(paramType2));
  }
  
  public static Class<?> Zd(Type paramType) {
    try {
      if (byte.class.equals(paramType))
        return Byte.class; 
    } catch (UnsupportedOperationException unsupportedOperationException) {
      throw a(null);
    } 
    try {
      if (byte[].class.equals(paramType))
        return Byte[].class; 
    } catch (UnsupportedOperationException unsupportedOperationException) {
      throw a(null);
    } 
    try {
      if (char.class.equals(paramType))
        return Character.class; 
    } catch (UnsupportedOperationException unsupportedOperationException) {
      throw a(null);
    } 
    try {
      if (char[].class.equals(paramType))
        return Character[].class; 
    } catch (UnsupportedOperationException unsupportedOperationException) {
      throw a(null);
    } 
    try {
      if (short.class.equals(paramType))
        return Short.class; 
    } catch (UnsupportedOperationException unsupportedOperationException) {
      throw a(null);
    } 
    try {
      if (short[].class.equals(paramType))
        return Short[].class; 
    } catch (UnsupportedOperationException unsupportedOperationException) {
      throw a(null);
    } 
    try {
      if (int.class.equals(paramType))
        return Integer.class; 
    } catch (UnsupportedOperationException unsupportedOperationException) {
      throw a(null);
    } 
    try {
      if (int[].class.equals(paramType))
        return Integer[].class; 
    } catch (UnsupportedOperationException unsupportedOperationException) {
      throw a(null);
    } 
    try {
      if (long.class.equals(paramType))
        return Long.class; 
    } catch (UnsupportedOperationException unsupportedOperationException) {
      throw a(null);
    } 
    try {
      if (long[].class.equals(paramType))
        return Long[].class; 
    } catch (UnsupportedOperationException unsupportedOperationException) {
      throw a(null);
    } 
    try {
      if (float.class.equals(paramType))
        return Float.class; 
    } catch (UnsupportedOperationException unsupportedOperationException) {
      throw a(null);
    } 
    try {
      if (float[].class.equals(paramType))
        return Float[].class; 
    } catch (UnsupportedOperationException unsupportedOperationException) {
      throw a(null);
    } 
    try {
      if (double.class.equals(paramType))
        return Double.class; 
    } catch (UnsupportedOperationException unsupportedOperationException) {
      throw a(null);
    } 
    try {
      if (double[].class.equals(paramType))
        return Double[].class; 
    } catch (UnsupportedOperationException unsupportedOperationException) {
      throw a(null);
    } 
    try {
      if (boolean.class.equals(paramType))
        return Boolean.class; 
    } catch (UnsupportedOperationException unsupportedOperationException) {
      throw a(null);
    } 
    try {
      if (boolean[].class.equals(paramType))
        return Boolean[].class; 
    } catch (UnsupportedOperationException unsupportedOperationException) {
      throw a(null);
    } 
    return (Class)paramType;
  }
  
  public static Type Zp(Type paramType) {
    if (paramType instanceof ParameterizedType) {
      Type[] arrayOfType = ((ParameterizedType)paramType).getActualTypeArguments();
      return arrayOfType[arrayOfType.length - 1];
    } 
    try {
      if (paramType instanceof GenericArrayType)
        return ((GenericArrayType)paramType).getGenericComponentType(); 
    } catch (UnsupportedOperationException unsupportedOperationException) {
      throw a(null);
    } 
    return null;
  }
  
  static {
    // Byte code:
    //   0: bipush #8
    //   2: anewarray java/lang/String
    //   5: astore #5
    //   7: iconst_0
    //   8: istore_3
    //   9: ldc 'ÃŸÂ‡Ãš>Ã“Ã»#XÂ€+Â§Â˜Ã¶Â”vÃŸiÃ¥pÃ“'-ÃÂ¿Â²SÃ‘ÃšÂœSÂ‰Â™Â¡QÃ°Â¹Ã’RÂˆ@\\tÃ\\b+!`ÃªÂ„rÃ’Y8Ã§Ã’z_ÂˆÃ™Â±Â§('Â¿Â´ÃŠ1Â½Ã”Â¯Ã|ÂšÂ¼'Ã¯Ãƒ)ÂŽ/ qjÂ²Ã’ÂžÂ°Â§(VÃDÂ¤Â«Ã˜/*Â©Â“5iÃ‡Â¶Â…ÂÂ¸Â„Â½Â ÃÃšÃ£Ã¬Ã3Â„Â¬Ã‚'
    //   11: dup
    //   12: astore_2
    //   13: invokevirtual length : ()I
    //   16: istore #4
    //   18: bipush #26
    //   20: istore_1
    //   21: iconst_m1
    //   22: istore_0
    //   23: bipush #38
    //   25: iinc #0, 1
    //   28: aload_2
    //   29: iload_0
    //   30: dup
    //   31: iload_1
    //   32: iadd
    //   33: invokevirtual substring : (II)Ljava/lang/String;
    //   36: iconst_m1
    //   37: goto -> 143
    //   40: aload #5
    //   42: swap
    //   43: iload_3
    //   44: iinc #3, 1
    //   47: swap
    //   48: aastore
    //   49: iload_0
    //   50: iload_1
    //   51: iadd
    //   52: dup
    //   53: istore_0
    //   54: iload #4
    //   56: if_icmpge -> 68
    //   59: aload_2
    //   60: iload_0
    //   61: invokevirtual charAt : (I)C
    //   64: istore_1
    //   65: goto -> 23
    //   68: ldc 'Â­FÃ£ÃÂ€ÃšbtÂ»Â§ÃŸ\\tÂ˜ÂŸÂ«Â”WEwÃ‡Ã•FÂ¼ARUÃŸ`Ã”'
    //   70: dup
    //   71: astore_2
    //   72: invokevirtual length : ()I
    //   75: istore #4
    //   77: bipush #8
    //   79: istore_1
    //   80: iconst_m1
    //   81: istore_0
    //   82: bipush #49
    //   84: iinc #0, 1
    //   87: aload_2
    //   88: iload_0
    //   89: dup
    //   90: iload_1
    //   91: iadd
    //   92: invokevirtual substring : (II)Ljava/lang/String;
    //   95: iconst_0
    //   96: goto -> 143
    //   99: aload #5
    //   101: swap
    //   102: iload_3
    //   103: iinc #3, 1
    //   106: swap
    //   107: aastore
    //   108: iload_0
    //   109: iload_1
    //   110: iadd
    //   111: dup
    //   112: istore_0
    //   113: iload #4
    //   115: if_icmpge -> 127
    //   118: aload_2
    //   119: iload_0
    //   120: invokevirtual charAt : (I)C
    //   123: istore_1
    //   124: goto -> 82
    //   127: aload #5
    //   129: putstatic net/portswigger/Zt7.a : [Ljava/lang/String;
    //   132: bipush #8
    //   134: anewarray java/lang/String
    //   137: putstatic net/portswigger/Zt7.b : [Ljava/lang/String;
    //   140: goto -> 300
    //   143: dup_x2
    //   144: pop
    //   145: invokevirtual toCharArray : ()[C
    //   148: dup_x1
    //   149: arraylength
    //   150: dup_x2
    //   151: pop
    //   152: iconst_0
    //   153: istore #6
    //   155: dup2_x1
    //   156: pop2
    //   157: dup_x2
    //   158: iconst_1
    //   159: if_icmpgt -> 260
    //   162: dup2
    //   163: swap
    //   164: iload #6
    //   166: dup2_x1
    //   167: caload
    //   168: swap
    //   169: iload #6
    //   171: bipush #7
    //   173: irem
    //   174: tableswitch default -> 242, 0 -> 212, 1 -> 217, 2 -> 222, 3 -> 227, 4 -> 232, 5 -> 237
    //   212: bipush #124
    //   214: goto -> 244
    //   217: bipush #79
    //   219: goto -> 244
    //   222: bipush #45
    //   224: goto -> 244
    //   227: bipush #52
    //   229: goto -> 244
    //   232: bipush #24
    //   234: goto -> 244
    //   237: bipush #55
    //   239: goto -> 244
    //   242: bipush #55
    //   244: ixor
    //   245: ixor
    //   246: i2c
    //   247: castore
    //   248: iinc #6, 1
    //   251: dup
    //   252: ifne -> 260
    //   255: dup2
    //   256: dup_x1
    //   257: goto -> 166
    //   260: dup2_x1
    //   261: pop2
    //   262: dup_x2
    //   263: iload #6
    //   265: if_icmpgt -> 162
    //   268: pop
    //   269: new java/lang/String
    //   272: dup_x1
    //   273: swap
    //   274: invokespecial <init> : ([C)V
    //   277: invokevirtual intern : ()Ljava/lang/String;
    //   280: swap
    //   281: pop
    //   282: swap
    //   283: tableswitch default -> 40, 0 -> 99
    //   300: new net/portswigger/Zc6
    //   303: dup
    //   304: invokespecial <init> : ()V
    //   307: invokestatic unmodifiableSet : (Ljava/util/Set;)Ljava/util/Set;
    //   310: putstatic net/portswigger/Zt7.Zy : Ljava/util/Set;
    //   313: return
  }
  
  private static UnsupportedOperationException a(UnsupportedOperationException paramUnsupportedOperationException) {
    return paramUnsupportedOperationException;
  }
  
  private static String a(int paramInt1, int paramInt2) {
    int i = (paramInt1 ^ 0xFFFF9F76) & 0xFFFF;
    if (b[i] == null) {
      char[] arrayOfChar = a[i].toCharArray();
      switch (arrayOfChar[0] & 0xFF) {
        case 0:
        
        case 1:
        
        case 2:
        
        case 3:
        
        case 4:
        
        case 5:
        
        case 6:
        
        case 7:
        
        case 8:
        
        case 9:
        
        case 10:
        
        case 11:
        
        case 12:
        
        case 13:
        
        case 14:
        
        case 15:
        
        case 16:
        
        case 17:
        
        case 18:
        
        case 19:
        
        case 20:
        
        case 21:
        
        case 22:
        
        case 23:
        
        case 24:
        
        case 25:
        
        case 26:
        
        case 27:
        
        case 28:
        
        case 29:
        
        case 30:
        
        case 31:
        
        case 32:
        
        case 33:
        
        case 34:
        
        case 35:
        
        case 36:
        
        case 37:
        
        case 38:
        
        case 39:
        
        case 40:
        
        case 41:
        
        case 42:
        
        case 43:
        
        case 44:
        
        case 45:
        
        case 46:
        
        case 47:
        
        case 48:
        
        case 49:
        
        case 50:
        
        case 51:
        
        case 52:
        
        case 53:
        
        case 54:
        
        case 55:
        
        case 56:
        
        case 57:
        
        case 58:
        
        case 59:
        
        case 60:
        
        case 61:
        
        case 62:
        
        case 63:
        
        case 64:
        
        case 65:
        
        case 66:
        
        case 67:
        
        case 68:
        
        case 69:
        
        case 70:
        
        case 71:
        
        case 72:
        
        case 73:
        
        case 74:
        
        case 75:
        
        case 76:
        
        case 77:
        
        case 78:
        
        case 79:
        
        case 80:
        
        case 81:
        
        case 82:
        
        case 83:
        
        case 84:
        
        case 85:
        
        case 86:
        
        case 87:
        
        case 88:
        
        case 89:
        
        case 90:
        
        case 91:
        
        case 92:
        
        case 93:
        
        case 94:
        
        case 95:
        
        case 96:
        
        case 97:
        
        case 98:
        
        case 99:
        
        case 100:
        
        case 101:
        
        case 102:
        
        case 103:
        
        case 104:
        
        case 105:
        
        case 106:
        
        case 107:
        
        case 108:
        
        case 109:
        
        case 110:
        
        case 111:
        
        case 112:
        
        case 113:
        
        case 114:
        
        case 115:
        
        case 116:
        
        case 117:
        
        case 118:
        
        case 119:
        
        case 120:
        
        case 121:
        
        case 122:
        
        case 123:
        
        case 124:
        
        case 125:
        
        case 126:
        
        case 127:
        
        case 128:
        
        case 129:
        
        case 130:
        
        case 131:
        
        case 132:
        
        case 133:
        
        case 134:
        
        case 135:
        
        case 136:
        
        case 137:
        
        case 138:
        
        case 139:
        
        case 140:
        
        case 141:
        
        case 142:
        
        case 143:
        
        case 144:
        
        case 145:
        
        case 146:
        
        case 147:
        
        case 148:
        
        case 149:
        
        case 150:
        
        case 151:
        
        case 152:
        
        case 153:
        
        case 154:
        
        case 155:
        
        case 156:
        
        case 157:
        
        case 158:
        
        case 159:
        
        case 160:
        
        case 161:
        
        case 162:
        
        case 163:
        
        case 164:
        
        case 165:
        
        case 166:
        
        case 167:
        
        case 168:
        
        case 169:
        
        case 170:
        
        case 171:
        
        case 172:
        
        case 173:
        
        case 174:
        
        case 175:
        
        case 176:
        
        case 177:
        
        case 178:
        
        case 179:
        
        case 180:
        
        case 181:
        
        case 182:
        
        case 183:
        
        case 184:
        
        case 185:
        
        case 186:
        
        case 187:
        
        case 188:
        
        case 189:
        
        case 190:
        
        case 191:
        
        case 192:
        
        case 193:
        
        case 194:
        
        case 195:
        
        case 196:
        
        case 197:
        
        case 198:
        
        case 199:
        
        case 200:
        
        case 201:
        
        case 202:
        
        case 203:
        
        case 204:
        
        case 205:
        
        case 206:
        
        case 207:
        
        case 208:
        
        case 209:
        
        case 210:
        
        case 211:
        
        case 212:
        
        case 213:
        
        case 214:
        
        case 215:
        
        case 216:
        
        case 217:
        
        case 218:
        
        case 219:
        
        case 220:
        
        case 221:
        
        case 222:
        
        case 223:
        
        case 224:
        
        case 225:
        
        case 226:
        
        case 227:
        
        case 228:
        
        case 229:
        
        case 230:
        
        case 231:
        
        case 232:
        
        case 233:
        
        case 234:
        
        case 235:
        
        case 236:
        
        case 237:
        
        case 238:
        
        case 239:
        
        case 240:
        
        case 241:
        
        case 242:
        
        case 243:
        
        case 244:
        
        case 245:
        
        case 246:
        
        case 247:
        
        case 248:
        
        case 249:
        
        case 250:
        
        case 251:
        
        case 252:
        
        case 253:
        
        case 254:
        
        default:
          break;
      } 
      byte b1 = 13;
      int j = (paramInt2 & 0xFF) - b1;
      if (j < 0)
        j += 256; 
      int k = ((paramInt2 & 0xFFFF) >>> 8) - b1;
      if (k < 0)
        k += 256; 
      for (byte b2 = 0; b2 < arrayOfChar.length; b2++) {
        int m = b2 % 2;
        if (m == 0) {
          arrayOfChar[b2] = (char)(arrayOfChar[b2] ^ j);
          j = ((j >>> 3 | j << 5) ^ arrayOfChar[b2]) & 0xFF;
        } else {
          arrayOfChar[b2] = (char)(arrayOfChar[b2] ^ k);
          k = ((k >>> 3 | k << 5) ^ arrayOfChar[b2]) & 0xFF;
        } 
      } 
      b[i] = (new String(arrayOfChar)).intern();
    } 
    return b[i];
  }
}


/* Location:              C:\Program Files\BurpSuitePro\burpsuite_pro.jar!\net\portswigger\Zt7.class
 * Java compiler version: 11 (55.0)
 * JD-Core Version:       1.1.3
 */