package net.portswigger;

import java.util.BitSet;
import java.util.EnumSet;

class Zug {
  private static Zfh ZuJ(int paramInt, BitSet paramBitSet, EnumSet<Zfh> paramEnumSet) {
    // Byte code:
    //   0: invokestatic Za : ()[Ljava/lang/String;
    //   3: aconst_null
    //   4: astore #4
    //   6: astore_3
    //   7: iload_0
    //   8: bipush #35
    //   10: if_icmpne -> 23
    //   13: aload_1
    //   14: bipush #94
    //   16: invokevirtual set : (I)V
    //   19: aload_3
    //   20: ifnonnull -> 487
    //   23: iload_0
    //   24: bipush #48
    //   26: if_icmplt -> 76
    //   29: iload_0
    //   30: bipush #57
    //   32: if_icmpgt -> 76
    //   35: aload_1
    //   36: bipush #66
    //   38: invokevirtual set : (I)V
    //   41: aload_1
    //   42: bipush #65
    //   44: invokevirtual set : (I)V
    //   47: aload_1
    //   48: bipush #43
    //   50: invokevirtual set : (I)V
    //   53: aload_1
    //   54: sipush #198
    //   57: invokevirtual set : (I)V
    //   60: aload_1
    //   61: bipush #85
    //   63: invokevirtual set : (I)V
    //   66: aload_1
    //   67: bipush #27
    //   69: invokevirtual set : (I)V
    //   72: aload_3
    //   73: ifnonnull -> 487
    //   76: iload_0
    //   77: bipush #97
    //   79: if_icmpne -> 105
    //   82: aload_1
    //   83: bipush #106
    //   85: invokevirtual set : (I)V
    //   88: aload_1
    //   89: sipush #188
    //   92: invokevirtual set : (I)V
    //   95: aload_1
    //   96: bipush #37
    //   98: invokevirtual set : (I)V
    //   101: aload_3
    //   102: ifnonnull -> 487
    //   105: iload_0
    //   106: bipush #98
    //   108: if_icmpne -> 122
    //   111: aload_1
    //   112: sipush #190
    //   115: invokevirtual set : (I)V
    //   118: aload_3
    //   119: ifnonnull -> 487
    //   122: iload_0
    //   123: bipush #99
    //   125: if_icmpne -> 151
    //   128: aload_1
    //   129: sipush #160
    //   132: invokevirtual set : (I)V
    //   135: aload_1
    //   136: bipush #28
    //   138: invokevirtual set : (I)V
    //   141: aload_1
    //   142: bipush #45
    //   144: invokevirtual set : (I)V
    //   147: aload_3
    //   148: ifnonnull -> 487
    //   151: iload_0
    //   152: bipush #100
    //   154: if_icmpne -> 181
    //   157: aload_1
    //   158: bipush #96
    //   160: invokevirtual set : (I)V
    //   163: aload_1
    //   164: sipush #197
    //   167: invokevirtual set : (I)V
    //   170: aload_1
    //   171: sipush #165
    //   174: invokevirtual set : (I)V
    //   177: aload_3
    //   178: ifnonnull -> 487
    //   181: iload_0
    //   182: bipush #101
    //   184: if_icmpne -> 203
    //   187: aload_1
    //   188: bipush #16
    //   190: invokevirtual set : (I)V
    //   193: aload_1
    //   194: bipush #97
    //   196: invokevirtual set : (I)V
    //   199: aload_3
    //   200: ifnonnull -> 487
    //   203: iload_0
    //   204: bipush #102
    //   206: if_icmpne -> 219
    //   209: aload_1
    //   210: bipush #54
    //   212: invokevirtual set : (I)V
    //   215: aload_3
    //   216: ifnonnull -> 487
    //   219: iload_0
    //   220: bipush #104
    //   222: if_icmpne -> 247
    //   225: aload_1
    //   226: bipush #41
    //   228: invokevirtual set : (I)V
    //   231: aload_1
    //   232: bipush #108
    //   234: invokevirtual set : (I)V
    //   237: aload_1
    //   238: bipush #117
    //   240: invokevirtual set : (I)V
    //   243: aload_3
    //   244: ifnonnull -> 487
    //   247: iload_0
    //   248: bipush #105
    //   250: if_icmpne -> 288
    //   253: aload_1
    //   254: bipush #22
    //   256: invokevirtual set : (I)V
    //   259: aload_1
    //   260: bipush #82
    //   262: invokevirtual set : (I)V
    //   265: aload_1
    //   266: bipush #69
    //   268: invokevirtual set : (I)V
    //   271: aload_1
    //   272: sipush #142
    //   275: invokevirtual set : (I)V
    //   278: aload_1
    //   279: bipush #123
    //   281: invokevirtual set : (I)V
    //   284: aload_3
    //   285: ifnonnull -> 487
    //   288: iload_0
    //   289: bipush #108
    //   291: if_icmpne -> 304
    //   294: aload_1
    //   295: bipush #126
    //   297: invokevirtual set : (I)V
    //   300: aload_3
    //   301: ifnonnull -> 487
    //   304: iload_0
    //   305: bipush #109
    //   307: if_icmpne -> 332
    //   310: aload_1
    //   311: bipush #116
    //   313: invokevirtual set : (I)V
    //   316: aload_1
    //   317: bipush #79
    //   319: invokevirtual set : (I)V
    //   322: aload_1
    //   323: bipush #72
    //   325: invokevirtual set : (I)V
    //   328: aload_3
    //   329: ifnonnull -> 487
    //   332: iload_0
    //   333: bipush #110
    //   335: if_icmpne -> 348
    //   338: aload_1
    //   339: bipush #80
    //   341: invokevirtual set : (I)V
    //   344: aload_3
    //   345: ifnonnull -> 487
    //   348: iload_0
    //   349: bipush #111
    //   351: if_icmpne -> 365
    //   354: aload_1
    //   355: sipush #144
    //   358: invokevirtual set : (I)V
    //   361: aload_3
    //   362: ifnonnull -> 487
    //   365: iload_0
    //   366: bipush #112
    //   368: if_icmpne -> 382
    //   371: aload_1
    //   372: sipush #140
    //   375: invokevirtual set : (I)V
    //   378: aload_3
    //   379: ifnonnull -> 487
    //   382: iload_0
    //   383: bipush #113
    //   385: if_icmpne -> 398
    //   388: aload_1
    //   389: bipush #35
    //   391: invokevirtual set : (I)V
    //   394: aload_3
    //   395: ifnonnull -> 487
    //   398: iload_0
    //   399: bipush #114
    //   401: if_icmpne -> 441
    //   404: aload_1
    //   405: sipush #151
    //   408: invokevirtual set : (I)V
    //   411: aload_1
    //   412: sipush #139
    //   415: invokevirtual set : (I)V
    //   418: aload_1
    //   419: bipush #57
    //   421: invokevirtual set : (I)V
    //   424: aload_1
    //   425: bipush #122
    //   427: invokevirtual set : (I)V
    //   430: aload_1
    //   431: sipush #134
    //   434: invokevirtual set : (I)V
    //   437: aload_3
    //   438: ifnonnull -> 487
    //   441: iload_0
    //   442: bipush #115
    //   444: if_icmpne -> 469
    //   447: aload_1
    //   448: bipush #20
    //   450: invokevirtual set : (I)V
    //   453: aload_1
    //   454: bipush #17
    //   456: invokevirtual set : (I)V
    //   459: aload_1
    //   460: bipush #101
    //   462: invokevirtual set : (I)V
    //   465: aload_3
    //   466: ifnonnull -> 487
    //   469: iload_0
    //   470: bipush #116
    //   472: if_icmpne -> 487
    //   475: aload_1
    //   476: bipush #95
    //   478: invokevirtual set : (I)V
    //   481: aload_1
    //   482: bipush #18
    //   484: invokevirtual set : (I)V
    //   487: iload_0
    //   488: bipush #65
    //   490: if_icmplt -> 499
    //   493: iload_0
    //   494: bipush #90
    //   496: if_icmple -> 517
    //   499: iload_0
    //   500: bipush #95
    //   502: if_icmpeq -> 517
    //   505: iload_0
    //   506: bipush #97
    //   508: if_icmplt -> 538
    //   511: iload_0
    //   512: bipush #122
    //   514: if_icmpgt -> 538
    //   517: aload_1
    //   518: bipush #64
    //   520: invokevirtual set : (I)V
    //   523: aload_2
    //   524: getstatic net/portswigger/Zfh.UNKNOWN_STRING : Lnet/portswigger/Zfh;
    //   527: invokevirtual contains : (Ljava/lang/Object;)Z
    //   530: ifeq -> 538
    //   533: getstatic net/portswigger/Zfh.UNKNOWN_STRING : Lnet/portswigger/Zfh;
    //   536: astore #4
    //   538: iload_0
    //   539: iflt -> 557
    //   542: aload_2
    //   543: getstatic net/portswigger/Zfh.UNKNOWN : Lnet/portswigger/Zfh;
    //   546: invokevirtual contains : (Ljava/lang/Object;)Z
    //   549: ifeq -> 557
    //   552: getstatic net/portswigger/Zfh.UNKNOWN : Lnet/portswigger/Zfh;
    //   555: astore #4
    //   557: iload_0
    //   558: bipush #46
    //   560: if_icmpne -> 582
    //   563: aload_2
    //   564: getstatic net/portswigger/Zfh.DOT : Lnet/portswigger/Zfh;
    //   567: invokevirtual contains : (Ljava/lang/Object;)Z
    //   570: ifeq -> 940
    //   573: getstatic net/portswigger/Zfh.DOT : Lnet/portswigger/Zfh;
    //   576: astore #4
    //   578: aload_3
    //   579: ifnonnull -> 940
    //   582: iload_0
    //   583: bipush #58
    //   585: if_icmpne -> 607
    //   588: aload_2
    //   589: getstatic net/portswigger/Zfh.COLON : Lnet/portswigger/Zfh;
    //   592: invokevirtual contains : (Ljava/lang/Object;)Z
    //   595: ifeq -> 940
    //   598: getstatic net/portswigger/Zfh.COLON : Lnet/portswigger/Zfh;
    //   601: astore #4
    //   603: aload_3
    //   604: ifnonnull -> 940
    //   607: iload_0
    //   608: bipush #123
    //   610: if_icmpne -> 632
    //   613: aload_2
    //   614: getstatic net/portswigger/Zfh.VARIABLE_START : Lnet/portswigger/Zfh;
    //   617: invokevirtual contains : (Ljava/lang/Object;)Z
    //   620: ifeq -> 940
    //   623: getstatic net/portswigger/Zfh.VARIABLE_START : Lnet/portswigger/Zfh;
    //   626: astore #4
    //   628: aload_3
    //   629: ifnonnull -> 940
    //   632: iload_0
    //   633: bipush #44
    //   635: if_icmpne -> 657
    //   638: aload_2
    //   639: getstatic net/portswigger/Zfh.COMMA : Lnet/portswigger/Zfh;
    //   642: invokevirtual contains : (Ljava/lang/Object;)Z
    //   645: ifeq -> 940
    //   648: getstatic net/portswigger/Zfh.COMMA : Lnet/portswigger/Zfh;
    //   651: astore #4
    //   653: aload_3
    //   654: ifnonnull -> 940
    //   657: iload_0
    //   658: bipush #48
    //   660: if_icmplt -> 688
    //   663: iload_0
    //   664: bipush #57
    //   666: if_icmpgt -> 688
    //   669: aload_2
    //   670: getstatic net/portswigger/Zfh.NATURAL_NUMBER : Lnet/portswigger/Zfh;
    //   673: invokevirtual contains : (Ljava/lang/Object;)Z
    //   676: ifeq -> 940
    //   679: getstatic net/portswigger/Zfh.NATURAL_NUMBER : Lnet/portswigger/Zfh;
    //   682: astore #4
    //   684: aload_3
    //   685: ifnonnull -> 940
    //   688: iload_0
    //   689: bipush #41
    //   691: if_icmpne -> 713
    //   694: aload_2
    //   695: getstatic net/portswigger/Zfh.CLOSE_BRACKET : Lnet/portswigger/Zfh;
    //   698: invokevirtual contains : (Ljava/lang/Object;)Z
    //   701: ifeq -> 940
    //   704: getstatic net/portswigger/Zfh.CLOSE_BRACKET : Lnet/portswigger/Zfh;
    //   707: astore #4
    //   709: aload_3
    //   710: ifnonnull -> 940
    //   713: iload_0
    //   714: bipush #40
    //   716: if_icmpne -> 738
    //   719: aload_2
    //   720: getstatic net/portswigger/Zfh.OPEN_BRACKET : Lnet/portswigger/Zfh;
    //   723: invokevirtual contains : (Ljava/lang/Object;)Z
    //   726: ifeq -> 940
    //   729: getstatic net/portswigger/Zfh.OPEN_BRACKET : Lnet/portswigger/Zfh;
    //   732: astore #4
    //   734: aload_3
    //   735: ifnonnull -> 940
    //   738: iload_0
    //   739: bipush #34
    //   741: if_icmpne -> 763
    //   744: aload_2
    //   745: getstatic net/portswigger/Zfh.LITERAL_STRING_OPENING_QUOTE : Lnet/portswigger/Zfh;
    //   748: invokevirtual contains : (Ljava/lang/Object;)Z
    //   751: ifeq -> 940
    //   754: getstatic net/portswigger/Zfh.LITERAL_STRING_OPENING_QUOTE : Lnet/portswigger/Zfh;
    //   757: astore #4
    //   759: aload_3
    //   760: ifnonnull -> 940
    //   763: iload_0
    //   764: bipush #96
    //   766: if_icmpne -> 788
    //   769: aload_2
    //   770: getstatic net/portswigger/Zfh.INTERPOLATABLE_STRING_OPENING_QUOTE : Lnet/portswigger/Zfh;
    //   773: invokevirtual contains : (Ljava/lang/Object;)Z
    //   776: ifeq -> 940
    //   779: getstatic net/portswigger/Zfh.INTERPOLATABLE_STRING_OPENING_QUOTE : Lnet/portswigger/Zfh;
    //   782: astore #4
    //   784: aload_3
    //   785: ifnonnull -> 940
    //   788: iload_0
    //   789: bipush #10
    //   791: if_icmpne -> 813
    //   794: aload_2
    //   795: getstatic net/portswigger/Zfh.NEWLINE : Lnet/portswigger/Zfh;
    //   798: invokevirtual contains : (Ljava/lang/Object;)Z
    //   801: ifeq -> 940
    //   804: getstatic net/portswigger/Zfh.NEWLINE : Lnet/portswigger/Zfh;
    //   807: astore #4
    //   809: aload_3
    //   810: ifnonnull -> 940
    //   813: iload_0
    //   814: bipush #35
    //   816: if_icmpne -> 844
    //   819: aload_1
    //   820: bipush #59
    //   822: invokevirtual set : (I)V
    //   825: aload_2
    //   826: getstatic net/portswigger/Zfh.COMMENT : Lnet/portswigger/Zfh;
    //   829: invokevirtual contains : (Ljava/lang/Object;)Z
    //   832: ifeq -> 940
    //   835: getstatic net/portswigger/Zfh.COMMENT : Lnet/portswigger/Zfh;
    //   838: astore #4
    //   840: aload_3
    //   841: ifnonnull -> 940
    //   844: iload_0
    //   845: bipush #12
    //   847: if_icmpne -> 869
    //   850: aload_2
    //   851: getstatic net/portswigger/Zfh._TOKEN_4 : Lnet/portswigger/Zfh;
    //   854: invokevirtual contains : (Ljava/lang/Object;)Z
    //   857: ifeq -> 940
    //   860: getstatic net/portswigger/Zfh._TOKEN_4 : Lnet/portswigger/Zfh;
    //   863: astore #4
    //   865: aload_3
    //   866: ifnonnull -> 940
    //   869: iload_0
    //   870: bipush #13
    //   872: if_icmpne -> 894
    //   875: aload_2
    //   876: getstatic net/portswigger/Zfh._TOKEN_3 : Lnet/portswigger/Zfh;
    //   879: invokevirtual contains : (Ljava/lang/Object;)Z
    //   882: ifeq -> 940
    //   885: getstatic net/portswigger/Zfh._TOKEN_3 : Lnet/portswigger/Zfh;
    //   888: astore #4
    //   890: aload_3
    //   891: ifnonnull -> 940
    //   894: iload_0
    //   895: bipush #9
    //   897: if_icmpne -> 919
    //   900: aload_2
    //   901: getstatic net/portswigger/Zfh._TOKEN_2 : Lnet/portswigger/Zfh;
    //   904: invokevirtual contains : (Ljava/lang/Object;)Z
    //   907: ifeq -> 940
    //   910: getstatic net/portswigger/Zfh._TOKEN_2 : Lnet/portswigger/Zfh;
    //   913: astore #4
    //   915: aload_3
    //   916: ifnonnull -> 940
    //   919: iload_0
    //   920: bipush #32
    //   922: if_icmpne -> 940
    //   925: aload_2
    //   926: getstatic net/portswigger/Zfh._TOKEN_1 : Lnet/portswigger/Zfh;
    //   929: invokevirtual contains : (Ljava/lang/Object;)Z
    //   932: ifeq -> 940
    //   935: getstatic net/portswigger/Zfh._TOKEN_1 : Lnet/portswigger/Zfh;
    //   938: astore #4
    //   940: aload #4
    //   942: areturn
  }
  
  private static Zfh ZE(int paramInt, BitSet paramBitSet, EnumSet<Zfh> paramEnumSet) {
    Zfh zfh = null;
    if (paramInt == 105)
      paramBitSet.set(120); 
    return zfh;
  }
  
  private static Zfh Zw(int paramInt, BitSet paramBitSet, EnumSet<Zfh> paramEnumSet) {
    Zfh zfh = null;
    if (paramInt == 116)
      paramBitSet.set(131); 
    return zfh;
  }
  
  private static Zfh Zcj(int paramInt, BitSet paramBitSet, EnumSet<Zfh> paramEnumSet) {
    Zfh zfh = null;
    if (paramInt == 116)
      paramBitSet.set(137); 
    return zfh;
  }
  
  private static Zfh Zcb(int paramInt, BitSet paramBitSet, EnumSet<Zfh> paramEnumSet) {
    Zfh zfh = null;
    if (paramInt == 101)
      paramBitSet.set(176); 
    return zfh;
  }
  
  private static Zfh Zcz(int paramInt, BitSet paramBitSet, EnumSet<Zfh> paramEnumSet) {
    Zfh zfh = null;
    if (paramInt == 116 && paramEnumSet.contains(Zfh.BOOL_NOT))
      zfh = Zfh.BOOL_NOT; 
    return zfh;
  }
  
  private static Zfh Zri(int paramInt, BitSet paramBitSet, EnumSet<Zfh> paramEnumSet) {
    Zfh zfh = null;
    if (paramInt == 101)
      paramBitSet.set(78); 
    return zfh;
  }
  
  private static Zfh Zrf(int paramInt, BitSet paramBitSet, EnumSet<Zfh> paramEnumSet) {
    Zfh zfh = null;
    if (paramInt == 115 && paramEnumSet.contains(Zfh.HEADERS))
      zfh = Zfh.HEADERS; 
    return zfh;
  }
  
  private static Zfh Zcx(int paramInt, BitSet paramBitSet, EnumSet<Zfh> paramEnumSet) {
    Zfh zfh = null;
    if (paramInt == 116)
      paramBitSet.set(171); 
    return zfh;
  }
  
  private static Zfh Zuj(int paramInt, BitSet paramBitSet, EnumSet<Zfh> paramEnumSet) {
    Zfh zfh = null;
    if (paramInt == 114)
      paramBitSet.set(182); 
    return zfh;
  }
  
  private static Zfh Zp(int paramInt, BitSet paramBitSet, EnumSet<Zfh> paramEnumSet) {
    Zfh zfh = null;
    if (paramInt == 100 && paramEnumSet.contains(Zfh.SEND))
      zfh = Zfh.SEND; 
    return zfh;
  }
  
  private static Zfh Zcp(int paramInt, BitSet paramBitSet, EnumSet<Zfh> paramEnumSet) {
    Zfh zfh = null;
    if (paramInt == 116 && paramEnumSet.contains(Zfh.REQUEST_HEADER))
      zfh = Zfh.REQUEST_HEADER; 
    return zfh;
  }
  
  private static Zfh ZrF(int paramInt, BitSet paramBitSet, EnumSet<Zfh> paramEnumSet) {
    Zfh zfh = null;
    if (paramInt == 114)
      paramBitSet.set(192); 
    return zfh;
  }
  
  private static Zfh Zck(int paramInt, BitSet paramBitSet, EnumSet<Zfh> paramEnumSet) {
    Zfh zfh = null;
    if (paramInt == 103 && paramEnumSet.contains(Zfh.REMOVING))
      zfh = Zfh.REMOVING; 
    return zfh;
  }
  
  private static Zfh Zc5(int paramInt, BitSet paramBitSet, EnumSet<Zfh> paramEnumSet) {
    Zfh zfh = null;
    if (paramInt == 111 && paramEnumSet.contains(Zfh.INFO_SEVERITY))
      zfh = Zfh.INFO_SEVERITY; 
    return zfh;
  }
  
  private static Zfh ZuL(int paramInt, BitSet paramBitSet, EnumSet<Zfh> paramEnumSet) {
    Zfh zfh = null;
    if (paramInt == 101)
      paramBitSet.set(194); 
    return zfh;
  }
  
  private static Zfh Zra(int paramInt, BitSet paramBitSet, EnumSet<Zfh> paramEnumSet) {
    Zfh zfh = null;
    if (paramInt == 108)
      paramBitSet.set(58); 
    return zfh;
  }
  
  private static Zfh Zrb(int paramInt, BitSet paramBitSet, EnumSet<Zfh> paramEnumSet) {
    Zfh zfh = null;
    if (paramInt == 101)
      paramBitSet.set(75); 
    return zfh;
  }
  
  private static Zfh Zcm(int paramInt, BitSet paramBitSet, EnumSet<Zfh> paramEnumSet) {
    Zfh zfh = null;
    if (paramInt == 104)
      paramBitSet.set(138); 
    return zfh;
  }
  
  private static Zfh Zcd(int paramInt, BitSet paramBitSet, EnumSet<Zfh> paramEnumSet) {
    Zfh zfh = null;
    if (paramInt == 108)
      paramBitSet.set(102); 
    return zfh;
  }
  
  private static Zfh Zcq(int paramInt, BitSet paramBitSet, EnumSet<Zfh> paramEnumSet) {
    Zfh zfh = null;
    if (paramInt == 109)
      paramBitSet.set(3); 
    return zfh;
  }
  
  private static Zfh Zrr(int paramInt, BitSet paramBitSet, EnumSet<Zfh> paramEnumSet) {
    Zfh zfh = null;
    if (paramInt == 32)
      paramBitSet.set(187); 
    return zfh;
  }
  
  private static Zfh ZcZ(int paramInt, BitSet paramBitSet, EnumSet<Zfh> paramEnumSet) {
    Zfh zfh = null;
    if (paramInt == 115 && paramEnumSet.contains(Zfh.IS_KEY))
      zfh = Zfh.IS_KEY; 
    return zfh;
  }
  
  private static Zfh Zco(int paramInt, BitSet paramBitSet, EnumSet<Zfh> paramEnumSet) {
    Zfh zfh = null;
    if (paramInt == 105)
      paramBitSet.set(180); 
    return zfh;
  }
  
  private static Zfh ZcR(int paramInt, BitSet paramBitSet, EnumSet<Zfh> paramEnumSet) {
    Zfh zfh = null;
    if (paramInt == 110)
      paramBitSet.set(121); 
    return zfh;
  }
  
  private static Zfh ZrP(int paramInt, BitSet paramBitSet, EnumSet<Zfh> paramEnumSet) {
    Zfh zfh = null;
    if (paramInt == 104 && paramEnumSet.contains(Zfh.HIGH_SEVERITY))
      zfh = Zfh.HIGH_SEVERITY; 
    return zfh;
  }
  
  private static Zfh ZrR(int paramInt, BitSet paramBitSet, EnumSet<Zfh> paramEnumSet) {
    Zfh zfh = null;
    if (paramInt == 97)
      paramBitSet.set(183); 
    return zfh;
  }
  
  private static Zfh Zc3(int paramInt, BitSet paramBitSet, EnumSet<Zfh> paramEnumSet) {
    Zfh zfh = null;
    if (paramInt >= 48 && paramInt <= 57) {
      paramBitSet.set(66);
      paramBitSet.set(85);
      paramBitSet.set(65);
      paramBitSet.set(43);
      paramBitSet.set(198);
      if (paramEnumSet.contains(Zfh.NATURAL_NUMBER))
        zfh = Zfh.NATURAL_NUMBER; 
    } 
    return zfh;
  }
  
  private static Zfh Zrc(int paramInt, BitSet paramBitSet, EnumSet<Zfh> paramEnumSet) {
    Zfh zfh = null;
    if (paramInt == 111)
      paramBitSet.set(81); 
    return zfh;
  }
  
  private static Zfh ZuW(int paramInt, BitSet paramBitSet, EnumSet<Zfh> paramEnumSet) {
    Zfh zfh = null;
    if (paramInt == 111)
      paramBitSet.set(12); 
    return zfh;
  }
  
  private static Zfh Zrs(int paramInt, BitSet paramBitSet, EnumSet<Zfh> paramEnumSet) {
    Zfh zfh = null;
    if (paramInt == 10 && paramEnumSet.contains(Zfh._TOKEN_5))
      zfh = Zfh._TOKEN_5; 
    return zfh;
  }
  
  private static Zfh Zcw(int paramInt, BitSet paramBitSet, EnumSet<Zfh> paramEnumSet) {
    Zfh zfh = null;
    if (paramInt == 109 && paramEnumSet.contains(Zfh.MEDIUM_SEVERITY))
      zfh = Zfh.MEDIUM_SEVERITY; 
    return zfh;
  }
  
  private static Zfh Zr8(int paramInt, BitSet paramBitSet, EnumSet<Zfh> paramEnumSet) {
    Zfh zfh = null;
    if (paramInt == 110 && paramEnumSet.contains(Zfh.CERTAIN_CONFIDENCE))
      zfh = Zfh.CERTAIN_CONFIDENCE; 
    return zfh;
  }
  
  private static Zfh ZT(int paramInt, BitSet paramBitSet, EnumSet<Zfh> paramEnumSet) {
    Zfh zfh = null;
    if (paramInt == 114)
      paramBitSet.set(189); 
    return zfh;
  }
  
  private static Zfh ZrN(int paramInt, BitSet paramBitSet, EnumSet<Zfh> paramEnumSet) {
    Zfh zfh = null;
    if (paramInt == 116)
      paramBitSet.set(191); 
    return zfh;
  }
  
  private static Zfh ZrH(int paramInt, BitSet paramBitSet, EnumSet<Zfh> paramEnumSet) {
    Zfh zfh = null;
    if (paramInt == 117)
      paramBitSet.set(128); 
    return zfh;
  }
  
  private static Zfh ZW(int paramInt, BitSet paramBitSet, EnumSet<Zfh> paramEnumSet) {
    Zfh zfh = null;
    if (paramInt == 105)
      paramBitSet.set(175); 
    return zfh;
  }
  
  private static Zfh ZcW(int paramInt, BitSet paramBitSet, EnumSet<Zfh> paramEnumSet) {
    Zfh zfh = null;
    if (paramInt == 110)
      paramBitSet.set(159); 
    return zfh;
  }
  
  private static Zfh ZrY(int paramInt, BitSet paramBitSet, EnumSet<Zfh> paramEnumSet) {
    Zfh zfh = null;
    if (paramInt == 115 && paramEnumSet.contains(Zfh.MATCHES_KEY))
      zfh = Zfh.MATCHES_KEY; 
    return zfh;
  }
  
  private static Zfh Zr5(int paramInt, BitSet paramBitSet, EnumSet<Zfh> paramEnumSet) {
    Zfh zfh = null;
    if (paramInt == 32)
      paramBitSet.set(49); 
    return zfh;
  }
  
  private static Zfh Zd(int paramInt, BitSet paramBitSet, EnumSet<Zfh> paramEnumSet) {
    Zfh zfh = null;
    if (paramInt == 116)
      paramBitSet.set(26); 
    return zfh;
  }
  
  private static Zfh Zrz(int paramInt, BitSet paramBitSet, EnumSet<Zfh> paramEnumSet) {
    Zfh zfh = null;
    if (paramInt == 116)
      paramBitSet.set(2); 
    return zfh;
  }
  
  private static Zfh Zuq(int paramInt, BitSet paramBitSet, EnumSet<Zfh> paramEnumSet) {
    Zfh zfh = null;
    if (paramInt == 110 && paramEnumSet.contains(Zfh.REMEDIATION_HEADER))
      zfh = Zfh.REMEDIATION_HEADER; 
    return zfh;
  }
  
  private static Zfh Zrj(int paramInt, BitSet paramBitSet, EnumSet<Zfh> paramEnumSet) {
    Zfh zfh = null;
    if (paramInt >= 48 && paramInt <= 57) {
      paramBitSet.set(66);
      paramBitSet.set(85);
      paramBitSet.set(65);
      paramBitSet.set(198);
      if (paramEnumSet.contains(Zfh.NATURAL_NUMBER))
        zfh = Zfh.NATURAL_NUMBER; 
    } 
    return zfh;
  }
  
  private static Zfh Zr7(int paramInt, BitSet paramBitSet, EnumSet<Zfh> paramEnumSet) {
    Zfh zfh = null;
    if (paramInt == 99)
      paramBitSet.set(163); 
    return zfh;
  }
  
  private static Zfh Zr2(int paramInt, BitSet paramBitSet, EnumSet<Zfh> paramEnumSet) {
    Zfh zfh = null;
    if (paramInt == 97)
      paramBitSet.set(146); 
    return zfh;
  }
  
  private static Zfh Zru(int paramInt, BitSet paramBitSet, EnumSet<Zfh> paramEnumSet) {
    Zfh zfh = null;
    if (paramInt == 101)
      paramBitSet.set(168); 
    return zfh;
  }
  
  private static Zfh Zc7(int paramInt, BitSet paramBitSet, EnumSet<Zfh> paramEnumSet) {
    Zfh zfh = null;
    if (paramInt == 103)
      paramBitSet.set(25); 
    return zfh;
  }
  
  private static Zfh ZcJ(int paramInt, BitSet paramBitSet, EnumSet<Zfh> paramEnumSet) {
    Zfh zfh = null;
    if (paramInt == 110 && paramEnumSet.contains(Zfh.THEN))
      zfh = Zfh.THEN; 
    return zfh;
  }
  
  private static Zfh ZI(int paramInt, BitSet paramBitSet, EnumSet<Zfh> paramEnumSet) {
    Zfh zfh = null;
    if (paramInt == 102)
      paramBitSet.set(33); 
    return zfh;
  }
  
  private static Zfh Zry(int paramInt, BitSet paramBitSet, EnumSet<Zfh> paramEnumSet) {
    Zfh zfh = null;
    if (paramInt == 102)
      paramBitSet.set(14); 
    return zfh;
  }
  
  private static Zfh ZuE(int paramInt, BitSet paramBitSet, EnumSet<Zfh> paramEnumSet) {
    Zfh zfh = null;
    if (paramInt == 108 && paramEnumSet.contains(Zfh.DETAIL_HEADER))
      zfh = Zfh.DETAIL_HEADER; 
    return zfh;
  }
  
  private static Zfh ZcQ(int paramInt, BitSet paramBitSet, EnumSet<Zfh> paramEnumSet) {
    Zfh zfh = null;
    if (paramInt == 100)
      paramBitSet.set(154); 
    return zfh;
  }
  
  private static Zfh Zu9(int paramInt, BitSet paramBitSet, EnumSet<Zfh> paramEnumSet) {
    Zfh zfh = null;
    if (paramInt == 114)
      paramBitSet.set(7); 
    return zfh;
  }
  
  private static Zfh ZuG(int paramInt, BitSet paramBitSet, EnumSet<Zfh> paramEnumSet) {
    Zfh zfh = null;
    if (paramInt == 105)
      paramBitSet.set(9); 
    return zfh;
  }
  
  private static Zfh ZcP(int paramInt, BitSet paramBitSet, EnumSet<Zfh> paramEnumSet) {
    Zfh zfh = null;
    if (paramInt == 97)
      paramBitSet.set(199); 
    return zfh;
  }
  
  private static Zfh ZU(int paramInt, BitSet paramBitSet, EnumSet<Zfh> paramEnumSet) {
    Zfh zfh = null;
    if (paramInt == 109)
      paramBitSet.set(107); 
    return zfh;
  }
  
  private static Zfh Zce(int paramInt, BitSet paramBitSet, EnumSet<Zfh> paramEnumSet) {
    Zfh zfh = null;
    if (paramInt == 101)
      paramBitSet.set(73); 
    return zfh;
  }
  
  private static Zfh Zre(int paramInt, BitSet paramBitSet, EnumSet<Zfh> paramEnumSet) {
    Zfh zfh = null;
    if (paramInt == 115)
      paramBitSet.set(124); 
    return zfh;
  }
  
  private static Zfh Zrd(int paramInt, BitSet paramBitSet, EnumSet<Zfh> paramEnumSet) {
    Zfh zfh = null;
    if ((paramInt >= 0 && paramInt <= 9) || paramInt == 11 || paramInt == 12 || paramInt >= 14) {
      paramBitSet.set(59);
      if (paramEnumSet.contains(Zfh.COMMENT))
        zfh = Zfh.COMMENT; 
    } 
    return zfh;
  }
  
  private static Zfh ZrB(int paramInt, BitSet paramBitSet, EnumSet<Zfh> paramEnumSet) {
    Zfh zfh = null;
    if (paramInt == 108)
      paramBitSet.set(88); 
    return zfh;
  }
  
  private static Zfh ZrE(int paramInt, BitSet paramBitSet, EnumSet<Zfh> paramEnumSet) {
    Zfh zfh = null;
    if (paramInt == 101)
      paramBitSet.set(155); 
    return zfh;
  }
  
  private static Zfh ZM(int paramInt, BitSet paramBitSet, EnumSet<Zfh> paramEnumSet) {
    Zfh zfh = null;
    if (paramInt == 104)
      paramBitSet.set(84); 
    return zfh;
  }
  
  private static Zfh ZcC(int paramInt, BitSet paramBitSet, EnumSet<Zfh> paramEnumSet) {
    Zfh zfh = null;
    if (paramInt == 110)
      paramBitSet.set(10); 
    return zfh;
  }
  
  private static Zfh ZQ(int paramInt, BitSet paramBitSet, EnumSet<Zfh> paramEnumSet) {
    Zfh zfh = null;
    if (paramInt >= 48 && paramInt <= 57) {
      paramBitSet.set(64);
      if (paramEnumSet.contains(Zfh.UNKNOWN_STRING))
        zfh = Zfh.UNKNOWN_STRING; 
    } else if ((paramInt >= 65 && paramInt <= 90) || paramInt == 95 || (paramInt >= 97 && paramInt <= 122)) {
      paramBitSet.set(64);
      if (paramEnumSet.contains(Zfh.UNKNOWN_STRING))
        zfh = Zfh.UNKNOWN_STRING; 
    } 
    return zfh;
  }
  
  private static Zfh Zuv(int paramInt, BitSet paramBitSet, EnumSet<Zfh> paramEnumSet) {
    Zfh zfh = null;
    if (paramInt >= 48 && paramInt <= 57) {
      paramBitSet.set(66);
      paramBitSet.set(85);
      paramBitSet.set(198);
      if (paramEnumSet.contains(Zfh.NATURAL_NUMBER))
        zfh = Zfh.NATURAL_NUMBER; 
    } 
    return zfh;
  }
  
  private static Zfh Ze(int paramInt, BitSet paramBitSet, EnumSet<Zfh> paramEnumSet) {
    Zfh zfh = null;
    if (paramInt >= 48 && paramInt <= 57) {
      paramBitSet.set(85);
      paramBitSet.set(198);
      if (paramEnumSet.contains(Zfh.NATURAL_NUMBER))
        zfh = Zfh.NATURAL_NUMBER; 
    } 
    return zfh;
  }
  
  private static Zfh Zux(int paramInt, BitSet paramBitSet, EnumSet<Zfh> paramEnumSet) {
    Zfh zfh = null;
    if (paramInt == 121 && paramEnumSet.contains(Zfh.BODY))
      zfh = Zfh.BODY; 
    return zfh;
  }
  
  private static Zfh Zcs(int paramInt, BitSet paramBitSet, EnumSet<Zfh> paramEnumSet) {
    Zfh zfh = null;
    if (paramInt == 99)
      paramBitSet.set(141); 
    return zfh;
  }
  
  private static Zfh ZJ(int paramInt, BitSet paramBitSet, EnumSet<Zfh> paramEnumSet) {
    Zfh zfh = null;
    if (paramInt == 110)
      paramBitSet.set(178); 
    return zfh;
  }
  
  private static Zfh Zr_(int paramInt, BitSet paramBitSet, EnumSet<Zfh> paramEnumSet) {
    Zfh zfh = null;
    if (paramInt == 105)
      paramBitSet.set(32); 
    return zfh;
  }
  
  private static Zfh ZcE(int paramInt, BitSet paramBitSet, EnumSet<Zfh> paramEnumSet) {
    Zfh zfh = null;
    if (paramInt == 114)
      paramBitSet.set(164); 
    return zfh;
  }
  
  private static Zfh ZuU(int paramInt, BitSet paramBitSet, EnumSet<Zfh> paramEnumSet) {
    Zfh zfh = null;
    if (paramInt == 101)
      paramBitSet.set(152); 
    return zfh;
  }
  
  private static Zfh ZcY(int paramInt, BitSet paramBitSet, EnumSet<Zfh> paramEnumSet) {
    Zfh zfh = null;
    if (paramInt == 112)
      paramBitSet.set(60); 
    return zfh;
  }
  
  private static Zfh Zun(int paramInt, BitSet paramBitSet, EnumSet<Zfh> paramEnumSet) {
    Zfh zfh = null;
    if (paramInt == 101)
      paramBitSet.set(113); 
    return zfh;
  }
  
  private static Zfh Zn(int paramInt, BitSet paramBitSet, EnumSet<Zfh> paramEnumSet) {
    Zfh zfh = null;
    if (paramInt == 118)
      paramBitSet.set(15); 
    return zfh;
  }
  
  private static Zfh ZrD(int paramInt, BitSet paramBitSet, EnumSet<Zfh> paramEnumSet) {
    Zfh zfh = null;
    if (paramInt == 100)
      paramBitSet.set(161); 
    return zfh;
  }
  
  private static Zfh Zv(int paramInt, BitSet paramBitSet, EnumSet<Zfh> paramEnumSet) {
    Zfh zfh = null;
    if (paramInt == 115)
      paramBitSet.set(100); 
    return zfh;
  }
  
  private static Zfh ZcG(int paramInt, BitSet paramBitSet, EnumSet<Zfh> paramEnumSet) {
    Zfh zfh = null;
    if (paramInt == 114)
      paramBitSet.set(86); 
    return zfh;
  }
  
  private static Zfh Zcg(int paramInt, BitSet paramBitSet, EnumSet<Zfh> paramEnumSet) {
    Zfh zfh = null;
    if (paramInt == 97)
      paramBitSet.set(8); 
    return zfh;
  }
  
  private static Zfh Zh(int paramInt, BitSet paramBitSet, EnumSet<Zfh> paramEnumSet) {
    Zfh zfh = null;
    if (paramInt == 111)
      paramBitSet.set(5); 
    return zfh;
  }
  
  private static Zfh Zrn(int paramInt, BitSet paramBitSet, EnumSet<Zfh> paramEnumSet) {
    Zfh zfh = null;
    if (paramInt == 110)
      paramBitSet.set(130); 
    return zfh;
  }
  
  private static Zfh ZZ(int paramInt, BitSet paramBitSet, EnumSet<Zfh> paramEnumSet) {
    Zfh zfh = null;
    if (paramInt == 110 && paramEnumSet.contains(Zfh.IN_KEY))
      zfh = Zfh.IN_KEY; 
    return zfh;
  }
  
  private static Zfh Zus(int paramInt, BitSet paramBitSet, EnumSet<Zfh> paramEnumSet) {
    Zfh zfh = null;
    if (paramInt == 113)
      paramBitSet.set(132); 
    return zfh;
  }
  
  private static Zfh Zu(int paramInt, BitSet paramBitSet, EnumSet<Zfh> paramEnumSet) {
    Zfh zfh = null;
    if (paramInt == 101)
      paramBitSet.set(38); 
    return zfh;
  }
  
  private static Zfh Zcc(int paramInt, BitSet paramBitSet, EnumSet<Zfh> paramEnumSet) {
    Zfh zfh = null;
    if (paramInt >= 48 && paramInt <= 57) {
      paramBitSet.set(198);
      if (paramEnumSet.contains(Zfh.NATURAL_NUMBER))
        zfh = Zfh.NATURAL_NUMBER; 
    } 
    return zfh;
  }
  
  private static Zfh ZcU(int paramInt, BitSet paramBitSet, EnumSet<Zfh> paramEnumSet) {
    Zfh zfh = null;
    if (paramInt == 97)
      paramBitSet.set(44); 
    return zfh;
  }
  
  private static Zfh ZcA(int paramInt, BitSet paramBitSet, EnumSet<Zfh> paramEnumSet) {
    Zfh zfh = null;
    if (paramInt == 102)
      paramBitSet.set(156); 
    return zfh;
  }
  
  private static Zfh Zu4(int paramInt, BitSet paramBitSet, EnumSet<Zfh> paramEnumSet) {
    Zfh zfh = null;
    if (paramInt == 97)
      paramBitSet.set(105); 
    return zfh;
  }
  
  private static Zfh Zrk(int paramInt, BitSet paramBitSet, EnumSet<Zfh> paramEnumSet) {
    Zfh zfh = null;
    if (paramInt == 105)
      paramBitSet.set(115); 
    return zfh;
  }
  
  private static Zfh Zrh(int paramInt, BitSet paramBitSet, EnumSet<Zfh> paramEnumSet) {
    Zfh zfh = null;
    if (paramInt == 116)
      paramBitSet.set(185); 
    return zfh;
  }
  
  private static Zfh Z_(int paramInt, BitSet paramBitSet, EnumSet<Zfh> paramEnumSet) {
    Zfh zfh = null;
    if (paramInt == 109)
      paramBitSet.set(127); 
    return zfh;
  }
  
  private static Zfh ZrZ(int paramInt, BitSet paramBitSet, EnumSet<Zfh> paramEnumSet) {
    Zfh zfh = null;
    if (paramInt == 110)
      paramBitSet.set(179); 
    return zfh;
  }
  
  private static Zfh ZrO(int paramInt, BitSet paramBitSet, EnumSet<Zfh> paramEnumSet) {
    Zfh zfh = null;
    if (paramInt == 105)
      paramBitSet.set(153); 
    return zfh;
  }
  
  private static Zfh Zrg(int paramInt, BitSet paramBitSet, EnumSet<Zfh> paramEnumSet) {
    // Byte code:
    //   0: invokestatic Za : ()[Ljava/lang/String;
    //   3: aconst_null
    //   4: astore #4
    //   6: astore_3
    //   7: iload_0
    //   8: iflt -> 17
    //   11: iload_0
    //   12: bipush #9
    //   14: if_icmple -> 35
    //   17: iload_0
    //   18: bipush #11
    //   20: if_icmpeq -> 35
    //   23: iload_0
    //   24: bipush #12
    //   26: if_icmpeq -> 35
    //   29: iload_0
    //   30: bipush #14
    //   32: if_icmplt -> 45
    //   35: aload_1
    //   36: bipush #94
    //   38: invokevirtual set : (I)V
    //   41: aload_3
    //   42: ifnonnull -> 82
    //   45: iload_0
    //   46: bipush #13
    //   48: if_icmpne -> 61
    //   51: aload_1
    //   52: bipush #30
    //   54: invokevirtual set : (I)V
    //   57: aload_3
    //   58: ifnonnull -> 82
    //   61: iload_0
    //   62: bipush #10
    //   64: if_icmpne -> 82
    //   67: aload_2
    //   68: getstatic net/portswigger/Zfh._TOKEN_5 : Lnet/portswigger/Zfh;
    //   71: invokevirtual contains : (Ljava/lang/Object;)Z
    //   74: ifeq -> 82
    //   77: getstatic net/portswigger/Zfh._TOKEN_5 : Lnet/portswigger/Zfh;
    //   80: astore #4
    //   82: iload_0
    //   83: bipush #13
    //   85: if_icmpne -> 103
    //   88: aload_2
    //   89: getstatic net/portswigger/Zfh._TOKEN_5 : Lnet/portswigger/Zfh;
    //   92: invokevirtual contains : (Ljava/lang/Object;)Z
    //   95: ifeq -> 103
    //   98: getstatic net/portswigger/Zfh._TOKEN_5 : Lnet/portswigger/Zfh;
    //   101: astore #4
    //   103: aload #4
    //   105: areturn
  }
  
  private static Zfh Zf(int paramInt, BitSet paramBitSet, EnumSet<Zfh> paramEnumSet) {
    Zfh zfh = null;
    if (paramInt == 101)
      paramBitSet.set(24); 
    return zfh;
  }
  
  private static Zfh Zcf(int paramInt, BitSet paramBitSet, EnumSet<Zfh> paramEnumSet) {
    Zfh zfh = null;
    if (paramInt == 105)
      paramBitSet.set(87); 
    return zfh;
  }
  
  private static Zfh Zr1(int paramInt, BitSet paramBitSet, EnumSet<Zfh> paramEnumSet) {
    Zfh zfh = null;
    if (paramInt == 110)
      paramBitSet.set(111); 
    return zfh;
  }
  
  private static Zfh ZrA(int paramInt, BitSet paramBitSet, EnumSet<Zfh> paramEnumSet) {
    Zfh zfh = null;
    if (paramInt == 32)
      paramBitSet.set(89); 
    return zfh;
  }
  
  private static Zfh Zr(int paramInt, BitSet paramBitSet, EnumSet<Zfh> paramEnumSet) {
    Zfh zfh = null;
    if (paramInt == 110)
      paramBitSet.set(133); 
    return zfh;
  }
  
  private static Zfh Zrm(int paramInt, BitSet paramBitSet, EnumSet<Zfh> paramEnumSet) {
    Zfh zfh = null;
    if (paramInt == 117)
      paramBitSet.set(136); 
    return zfh;
  }
  
  private static Zfh Zrq(int paramInt, BitSet paramBitSet, EnumSet<Zfh> paramEnumSet) {
    Zfh zfh = null;
    if (paramInt == 101)
      paramBitSet.set(63); 
    return zfh;
  }
  
  private static Zfh ZrQ(int paramInt, BitSet paramBitSet, EnumSet<Zfh> paramEnumSet) {
    Zfh zfh = null;
    if (paramInt == 101)
      paramBitSet.set(145); 
    return zfh;
  }
  
  private static Zfh Zcr(int paramInt, BitSet paramBitSet, EnumSet<Zfh> paramEnumSet) {
    Zfh zfh = null;
    if (paramInt == 100)
      paramBitSet.set(23); 
    return zfh;
  }
  
  private static Zfh ZG(int paramInt, BitSet paramBitSet, EnumSet<Zfh> paramEnumSet) {
    Zfh zfh = null;
    if (paramInt == 100)
      paramBitSet.set(67); 
    return zfh;
  }
  
  private static Zfh ZcD(int paramInt, BitSet paramBitSet, EnumSet<Zfh> paramEnumSet) {
    Zfh zfh = null;
    if (paramInt == 99)
      paramBitSet.set(109); 
    return zfh;
  }
  
  private static Zfh Zr4(int paramInt, BitSet paramBitSet, EnumSet<Zfh> paramEnumSet) {
    Zfh zfh = null;
    if (paramInt == 112)
      paramBitSet.set(166); 
    return zfh;
  }
  
  private static Zfh ZcS(int paramInt, BitSet paramBitSet, EnumSet<Zfh> paramEnumSet) {
    Zfh zfh = null;
    if (paramInt == 111)
      paramBitSet.set(174); 
    return zfh;
  }
  
  private static Zfh ZcT(int paramInt, BitSet paramBitSet, EnumSet<Zfh> paramEnumSet) {
    Zfh zfh = null;
    if (paramInt == 101)
      paramBitSet.set(110); 
    return zfh;
  }
  
  private static Zfh Zcl(int paramInt, BitSet paramBitSet, EnumSet<Zfh> paramEnumSet) {
    Zfh zfh = null;
    if (paramInt == 105)
      paramBitSet.set(92); 
    return zfh;
  }
  
  private static Zfh Zrv(int paramInt, BitSet paramBitSet, EnumSet<Zfh> paramEnumSet) {
    Zfh zfh = null;
    if (paramInt == 97)
      paramBitSet.set(150); 
    return zfh;
  }
  
  private static Zfh ZrK(int paramInt, BitSet paramBitSet, EnumSet<Zfh> paramEnumSet) {
    Zfh zfh = null;
    if (paramInt == 100)
      paramBitSet.set(98); 
    return zfh;
  }
  
  private static Zfh Zt(int paramInt, BitSet paramBitSet, EnumSet<Zfh> paramEnumSet) {
    Zfh zfh = null;
    if (paramInt == 101 && paramEnumSet.contains(Zfh.TENTATIVE_CONFIDENCE))
      zfh = Zfh.TENTATIVE_CONFIDENCE; 
    return zfh;
  }
  
  private static Zfh Zui(int paramInt, BitSet paramBitSet, EnumSet<Zfh> paramEnumSet) {
    Zfh zfh = null;
    if (paramInt == 115)
      paramBitSet.set(11); 
    return zfh;
  }
  
  private static Zfh ZrT(int paramInt, BitSet paramBitSet, EnumSet<Zfh> paramEnumSet) {
    Zfh zfh = null;
    if (paramInt == 105)
      paramBitSet.set(90); 
    return zfh;
  }
  
  private static Zfh Zs(int paramInt, BitSet paramBitSet, EnumSet<Zfh> paramEnumSet) {
    Zfh zfh = null;
    if (paramInt == 102 && paramEnumSet.contains(Zfh.IF_FOOTER))
      zfh = Zfh.IF_FOOTER; 
    return zfh;
  }
  
  private static Zfh Zc0(int paramInt, BitSet paramBitSet, EnumSet<Zfh> paramEnumSet) {
    Zfh zfh = null;
    if (paramInt == 101)
      paramBitSet.set(103); 
    return zfh;
  }
  
  private static Zfh ZL(int paramInt, BitSet paramBitSet, EnumSet<Zfh> paramEnumSet) {
    Zfh zfh = null;
    if (paramInt == 105)
      paramBitSet.set(47); 
    return zfh;
  }
  
  private static Zfh Zc_(int paramInt, BitSet paramBitSet, EnumSet<Zfh> paramEnumSet) {
    Zfh zfh = null;
    if (paramInt == 97)
      paramBitSet.set(70); 
    return zfh;
  }
  
  private static Zfh Zc1(int paramInt, BitSet paramBitSet, EnumSet<Zfh> paramEnumSet) {
    Zfh zfh = null;
    if (paramInt == 114)
      paramBitSet.set(143); 
    return zfh;
  }
  
  private static Zfh Zg(int paramInt, BitSet paramBitSet, EnumSet<Zfh> paramEnumSet) {
    Zfh zfh = null;
    if (paramInt == 111)
      paramBitSet.set(193); 
    return zfh;
  }
  
  private static Zfh Zk(int paramInt, BitSet paramBitSet, EnumSet<Zfh> paramEnumSet) {
    Zfh zfh = null;
    if (paramInt == 116)
      paramBitSet.set(55); 
    return zfh;
  }
  
  private static Zfh ZcM(int paramInt, BitSet paramBitSet, EnumSet<Zfh> paramEnumSet) {
    Zfh zfh = null;
    if (paramInt == 101)
      paramBitSet.set(83); 
    return zfh;
  }
  
  private static Zfh ZP(int paramInt, BitSet paramBitSet, EnumSet<Zfh> paramEnumSet) {
    Zfh zfh = null;
    if (paramInt == 110)
      paramBitSet.set(50); 
    return zfh;
  }
  
  private static Zfh ZA(int paramInt, BitSet paramBitSet, EnumSet<Zfh> paramEnumSet) {
    Zfh zfh = null;
    if (paramInt == 101 && paramEnumSet.contains(Zfh.ELSE_HEADER))
      zfh = Zfh.ELSE_HEADER; 
    return zfh;
  }
  
  private static Zfh ZrW(int paramInt, BitSet paramBitSet, EnumSet<Zfh> paramEnumSet) {
    Zfh zfh = null;
    if (paramInt == 97)
      paramBitSet.set(34); 
    return zfh;
  }
  
  private static Zfh ZrL(int paramInt, BitSet paramBitSet, EnumSet<Zfh> paramEnumSet) {
    Zfh zfh = null;
    if (paramInt == 111)
      paramBitSet.set(181); 
    return zfh;
  }
  
  private static Zfh ZF(int paramInt, BitSet paramBitSet, EnumSet<Zfh> paramEnumSet) {
    Zfh zfh = null;
    if (paramInt == 101)
      paramBitSet.set(52); 
    return zfh;
  }
  
  private static Zfh ZcL(int paramInt, BitSet paramBitSet, EnumSet<Zfh> paramEnumSet) {
    Zfh zfh = null;
    if (paramInt == 101)
      paramBitSet.set(71); 
    return zfh;
  }
  
  private static Zfh Zc2(int paramInt, BitSet paramBitSet, EnumSet<Zfh> paramEnumSet) {
    Zfh zfh = null;
    if (paramInt == 116)
      paramBitSet.set(135); 
    return zfh;
  }
  
  private static Zfh ZuV(int paramInt, BitSet paramBitSet, EnumSet<Zfh> paramEnumSet) {
    Zfh zfh = null;
    if (paramInt == 102)
      paramBitSet.set(36); 
    return zfh;
  }
  
  private static Zfh ZV(int paramInt, BitSet paramBitSet, EnumSet<Zfh> paramEnumSet) {
    Zfh zfh = null;
    if (paramInt == 112 && paramEnumSet.contains(Zfh.HTTP_KEY))
      zfh = Zfh.HTTP_KEY; 
    return zfh;
  }
  
  private static Zfh Zy(int paramInt, BitSet paramBitSet, EnumSet<Zfh> paramEnumSet) {
    Zfh zfh = null;
    if (paramInt == 117)
      paramBitSet.set(74); 
    return zfh;
  }
  
  private static Zfh Zud(int paramInt, BitSet paramBitSet, EnumSet<Zfh> paramEnumSet) {
    Zfh zfh = null;
    if (paramInt == 103 && paramEnumSet.contains(Zfh.APPENDING))
      zfh = Zfh.APPENDING; 
    return zfh;
  }
  
  private static Zfh Zcv(int paramInt, BitSet paramBitSet, EnumSet<Zfh> paramEnumSet) {
    Zfh zfh = null;
    if (paramInt == 101)
      paramBitSet.set(196); 
    return zfh;
  }
  
  private static Zfh ZuO(int paramInt, BitSet paramBitSet, EnumSet<Zfh> paramEnumSet) {
    Zfh zfh = null;
    if (paramInt == 104 && paramEnumSet.contains(Zfh.PATH))
      zfh = Zfh.PATH; 
    return zfh;
  }
  
  private static Zfh Zc8(int paramInt, BitSet paramBitSet, EnumSet<Zfh> paramEnumSet) {
    Zfh zfh = null;
    if (paramInt == 101 && paramEnumSet.contains(Zfh.REPORT_ISSUE_HEADER))
      zfh = Zfh.REPORT_ISSUE_HEADER; 
    return zfh;
  }
  
  private static Zfh ZrC(int paramInt, BitSet paramBitSet, EnumSet<Zfh> paramEnumSet) {
    Zfh zfh = null;
    if (paramInt == 112 && paramEnumSet.contains(Zfh.SMTP_KEY))
      zfh = Zfh.SMTP_KEY; 
    return zfh;
  }
  
  private static Zfh Zct(int paramInt, BitSet paramBitSet, EnumSet<Zfh> paramEnumSet) {
    Zfh zfh = null;
    if (paramInt == 101)
      paramBitSet.set(48); 
    return zfh;
  }
  
  private static Zfh Zu_(int paramInt, BitSet paramBitSet, EnumSet<Zfh> paramEnumSet) {
    Zfh zfh = null;
    if (paramInt == 101)
      paramBitSet.set(91); 
    return zfh;
  }
  
  private static Zfh Zx(int paramInt, BitSet paramBitSet, EnumSet<Zfh> paramEnumSet) {
    Zfh zfh = null;
    if (paramInt == 97)
      paramBitSet.set(129); 
    return zfh;
  }
  
  private static Zfh Zz(int paramInt, BitSet paramBitSet, EnumSet<Zfh> paramEnumSet) {
    Zfh zfh = null;
    if (paramInt == 101 && paramEnumSet.contains(Zfh.CONFIDENCE_HEADER))
      zfh = Zfh.CONFIDENCE_HEADER; 
    return zfh;
  }
  
  private static Zfh Zcu(int paramInt, BitSet paramBitSet, EnumSet<Zfh> paramEnumSet) {
    Zfh zfh = null;
    if (paramInt == 102 && paramEnumSet.contains(Zfh.IF_HEADER))
      zfh = Zfh.IF_HEADER; 
    return zfh;
  }
  
  private static Zfh Zi(int paramInt, BitSet paramBitSet, EnumSet<Zfh> paramEnumSet) {
    Zfh zfh = null;
    if (paramInt == 116)
      paramBitSet.set(118); 
    return zfh;
  }
  
  private static Zfh ZcO(int paramInt, BitSet paramBitSet, EnumSet<Zfh> paramEnumSet) {
    Zfh zfh = null;
    if (paramInt == 114 && paramEnumSet.contains(Zfh.BOOL_OR))
      zfh = Zfh.BOOL_OR; 
    return zfh;
  }
  
  private static Zfh ZY(int paramInt, BitSet paramBitSet, EnumSet<Zfh> paramEnumSet) {
    Zfh zfh = null;
    if (paramInt == 100 && paramEnumSet.contains(Zfh.CALLED))
      zfh = Zfh.CALLED; 
    return zfh;
  }
  
  private static Zfh ZrJ(int paramInt, BitSet paramBitSet, EnumSet<Zfh> paramEnumSet) {
    Zfh zfh = null;
    if (paramInt == 108)
      paramBitSet.set(19); 
    return zfh;
  }
  
  private static Zfh Zr0(int paramInt, BitSet paramBitSet, EnumSet<Zfh> paramEnumSet) {
    Zfh zfh = null;
    if (paramInt == 115)
      paramBitSet.set(39); 
    return zfh;
  }
  
  private static Zfh ZuX(int paramInt, BitSet paramBitSet, EnumSet<Zfh> paramEnumSet) {
    Zfh zfh = null;
    if (paramInt == 109 && paramEnumSet.contains(Zfh.DIFFERS_FROM_KEY))
      zfh = Zfh.DIFFERS_FROM_KEY; 
    return zfh;
  }
  
  private static Zfh Zr9(int paramInt, BitSet paramBitSet, EnumSet<Zfh> paramEnumSet) {
    Zfh zfh = null;
    if (paramInt == 101)
      paramBitSet.set(53); 
    return zfh;
  }
  
  private static Zfh Zc4(int paramInt, BitSet paramBitSet, EnumSet<Zfh> paramEnumSet) {
    Zfh zfh = null;
    if (paramInt == 100)
      paramBitSet.set(149); 
    return zfh;
  }
  
  private static Zfh ZB(int paramInt, BitSet paramBitSet, EnumSet<Zfh> paramEnumSet) {
    Zfh zfh = null;
    if (paramInt == 101)
      paramBitSet.set(56); 
    return zfh;
  }
  
  private static Zfh Zci(int paramInt, BitSet paramBitSet, EnumSet<Zfh> paramEnumSet) {
    Zfh zfh = null;
    if (paramInt == 116)
      paramBitSet.set(184); 
    return zfh;
  }
  
  private static Zfh ZN(int paramInt, BitSet paramBitSet, EnumSet<Zfh> paramEnumSet) {
    Zfh zfh = null;
    if (paramInt == 118)
      paramBitSet.set(112); 
    return zfh;
  }
  
  private static Zfh Zrt(int paramInt, BitSet paramBitSet, EnumSet<Zfh> paramEnumSet) {
    Zfh zfh = null;
    if (paramInt == 105)
      paramBitSet.set(125); 
    return zfh;
  }
  
  private static Zfh ZrM(int paramInt, BitSet paramBitSet, EnumSet<Zfh> paramEnumSet) {
    Zfh zfh = null;
    if (paramInt == 115 && paramEnumSet.contains(Zfh.QUERIES))
      zfh = Zfh.QUERIES; 
    return zfh;
  }
  
  private static Zfh Zrl(int paramInt, BitSet paramBitSet, EnumSet<Zfh> paramEnumSet) {
    Zfh zfh = null;
    if (paramInt == 102)
      paramBitSet.set(157); 
    return zfh;
  }
  
  private static Zfh ZS(int paramInt, BitSet paramBitSet, EnumSet<Zfh> paramEnumSet) {
    Zfh zfh = null;
    if (paramInt == 101)
      paramBitSet.set(186); 
    return zfh;
  }
  
  private static Zfh Zl(int paramInt, BitSet paramBitSet, EnumSet<Zfh> paramEnumSet) {
    Zfh zfh = null;
    if (paramInt == 115)
      paramBitSet.set(77); 
    return zfh;
  }
  
  private static Zfh ZD(int paramInt, BitSet paramBitSet, EnumSet<Zfh> paramEnumSet) {
    Zfh zfh = null;
    if (paramInt == 121 && paramEnumSet.contains(Zfh.ANY_KEY))
      zfh = Zfh.ANY_KEY; 
    return zfh;
  }
  
  private static Zfh ZcX(int paramInt, BitSet paramBitSet, EnumSet<Zfh> paramEnumSet) {
    Zfh zfh = null;
    if (paramInt == 101)
      paramBitSet.set(119); 
    return zfh;
  }
  
  private static Zfh ZO(int paramInt, BitSet paramBitSet, EnumSet<Zfh> paramEnumSet) {
    Zfh zfh = null;
    if (paramInt == 105)
      paramBitSet.set(99); 
    return zfh;
  }
  
  private static Zfh ZC(int paramInt, BitSet paramBitSet, EnumSet<Zfh> paramEnumSet) {
    Zfh zfh = null;
    if (paramInt == 105)
      paramBitSet.set(170); 
    return zfh;
  }
  
  private static Zfh ZrX(int paramInt, BitSet paramBitSet, EnumSet<Zfh> paramEnumSet) {
    Zfh zfh = null;
    if (paramInt == 116)
      paramBitSet.set(1); 
    return zfh;
  }
  
  private static Zfh Zrx(int paramInt, BitSet paramBitSet, EnumSet<Zfh> paramEnumSet) {
    Zfh zfh = null;
    if (paramInt == 105)
      paramBitSet.set(61); 
    return zfh;
  }
  
  private static Zfh Zq(int paramInt, BitSet paramBitSet, EnumSet<Zfh> paramEnumSet) {
    Zfh zfh = null;
    if (paramInt == 110)
      paramBitSet.set(172); 
    return zfh;
  }
  
  private static Zfh Zca(int paramInt, BitSet paramBitSet, EnumSet<Zfh> paramEnumSet) {
    Zfh zfh = null;
    if (paramInt == 112)
      paramBitSet.set(46); 
    return zfh;
  }
  
  private static Zfh Zc9(int paramInt, BitSet paramBitSet, EnumSet<Zfh> paramEnumSet) {
    Zfh zfh = null;
    if (paramInt == 100 && paramEnumSet.contains(Zfh.BOOL_AND))
      zfh = Zfh.BOOL_AND; 
    return zfh;
  }
  
  private static Zfh Zc6(int paramInt, BitSet paramBitSet, EnumSet<Zfh> paramEnumSet) {
    Zfh zfh = null;
    if (paramInt == 110)
      paramBitSet.set(76); 
    return zfh;
  }
  
  private static Zfh ZcN(int paramInt, BitSet paramBitSet, EnumSet<Zfh> paramEnumSet) {
    Zfh zfh = null;
    if (paramInt == 111)
      paramBitSet.set(195); 
    return zfh;
  }
  
  private static Zfh Zc(int paramInt, BitSet paramBitSet, EnumSet<Zfh> paramEnumSet) {
    Zfh zfh = null;
    if (paramInt == 110)
      paramBitSet.set(13); 
    return zfh;
  }
  
  private static Zfh ZrV(int paramInt, BitSet paramBitSet, EnumSet<Zfh> paramEnumSet) {
    Zfh zfh = null;
    if (paramInt == 99)
      paramBitSet.set(62); 
    return zfh;
  }
  
  private static Zfh ZcF(int paramInt, BitSet paramBitSet, EnumSet<Zfh> paramEnumSet) {
    Zfh zfh = null;
    if (paramInt == 115 && paramEnumSet.contains(Zfh.DNS_KEY))
      zfh = Zfh.DNS_KEY; 
    return zfh;
  }
  
  private static Zfh Za(int paramInt, BitSet paramBitSet, EnumSet<Zfh> paramEnumSet) {
    Zfh zfh = null;
    if (paramInt == 111)
      paramBitSet.set(42); 
    return zfh;
  }
  
  private static Zfh ZH(int paramInt, BitSet paramBitSet, EnumSet<Zfh> paramEnumSet) {
    Zfh zfh = null;
    if (paramInt == 118)
      paramBitSet.set(162); 
    return zfh;
  }
  
  private static Zfh ZcK(int paramInt, BitSet paramBitSet, EnumSet<Zfh> paramEnumSet) {
    Zfh zfh = null;
    if (paramInt == 100)
      paramBitSet.set(4); 
    return zfh;
  }
  
  private static Zfh ZX(int paramInt, BitSet paramBitSet, EnumSet<Zfh> paramEnumSet) {
    Zfh zfh = null;
    if (paramInt == 110)
      paramBitSet.set(68); 
    return zfh;
  }
  
  private static Zfh ZuK(int paramInt, BitSet paramBitSet, EnumSet<Zfh> paramEnumSet) {
    Zfh zfh = null;
    if (paramInt == 115 && paramEnumSet.contains(Zfh.INTERACTIONS_KEY))
      zfh = Zfh.INTERACTIONS_KEY; 
    return zfh;
  }
  
  private static Zfh ZrS(int paramInt, BitSet paramBitSet, EnumSet<Zfh> paramEnumSet) {
    Zfh zfh = null;
    if (paramInt == 116)
      paramBitSet.set(6); 
    return zfh;
  }
  
  private static Zfh Zcy(int paramInt, BitSet paramBitSet, EnumSet<Zfh> paramEnumSet) {
    Zfh zfh = null;
    if (paramInt == 103 && paramEnumSet.contains(Zfh.REPLACING))
      zfh = Zfh.REPLACING; 
    return zfh;
  }
  
  private static Zfh Zch(int paramInt, BitSet paramBitSet, EnumSet<Zfh> paramEnumSet) {
    Zfh zfh = null;
    if (paramInt == 117)
      paramBitSet.set(31); 
    return zfh;
  }
  
  private static Zfh ZcV(int paramInt, BitSet paramBitSet, EnumSet<Zfh> paramEnumSet) {
    Zfh zfh = null;
    if (paramInt == 119 && paramEnumSet.contains(Zfh.LOW_SEVERITY))
      zfh = Zfh.LOW_SEVERITY; 
    return zfh;
  }
  
  private static Zfh ZrU(int paramInt, BitSet paramBitSet, EnumSet<Zfh> paramEnumSet) {
    Zfh zfh = null;
    if (paramInt == 109 && paramEnumSet.contains(Zfh.FIRM_CONFIDENCE))
      zfh = Zfh.FIRM_CONFIDENCE; 
    return zfh;
  }
  
  private static Zfh Zo(int paramInt, BitSet paramBitSet, EnumSet<Zfh> paramEnumSet) {
    Zfh zfh = null;
    if (paramInt == 105)
      paramBitSet.set(51); 
    return zfh;
  }
  
  private static Zfh Zro(int paramInt, BitSet paramBitSet, EnumSet<Zfh> paramEnumSet) {
    Zfh zfh = null;
    if (paramInt == 104)
      paramBitSet.set(169); 
    return zfh;
  }
  
  private static Zfh ZrI(int paramInt, BitSet paramBitSet, EnumSet<Zfh> paramEnumSet) {
    Zfh zfh = null;
    if (paramInt == 121 && paramEnumSet.contains(Zfh.SEVERITY_HEADER))
      zfh = Zfh.SEVERITY_HEADER; 
    return zfh;
  }
  
  private static Zfh Zr3(int paramInt, BitSet paramBitSet, EnumSet<Zfh> paramEnumSet) {
    Zfh zfh = null;
    if (paramInt == 114)
      paramBitSet.set(147); 
    return zfh;
  }
  
  private static Zfh ZcH(int paramInt, BitSet paramBitSet, EnumSet<Zfh> paramEnumSet) {
    Zfh zfh = null;
    if (paramInt == 105)
      paramBitSet.set(158); 
    return zfh;
  }
  
  private static Zfh Zj(int paramInt, BitSet paramBitSet, EnumSet<Zfh> paramEnumSet) {
    Zfh zfh = null;
    if (paramInt == 110)
      paramBitSet.set(167); 
    return zfh;
  }
  
  private static Zfh Zcn(int paramInt, BitSet paramBitSet, EnumSet<Zfh> paramEnumSet) {
    Zfh zfh = null;
    if (paramInt == 111)
      paramBitSet.set(148); 
    return zfh;
  }
  
  private static Zfh Zrw(int paramInt, BitSet paramBitSet, EnumSet<Zfh> paramEnumSet) {
    Zfh zfh = null;
    if (paramInt == 111)
      paramBitSet.set(104); 
    return zfh;
  }
  
  private static Zfh ZrG(int paramInt, BitSet paramBitSet, EnumSet<Zfh> paramEnumSet) {
    Zfh zfh = null;
    if (paramInt == 105)
      paramBitSet.set(173); 
    return zfh;
  }
  
  private static Zfh Zrp(int paramInt, BitSet paramBitSet, EnumSet<Zfh> paramEnumSet) {
    Zfh zfh = null;
    if (paramInt == 116)
      paramBitSet.set(21); 
    return zfh;
  }
  
  private static Zfh ZK(int paramInt, BitSet paramBitSet, EnumSet<Zfh> paramEnumSet) {
    Zfh zfh = null;
    if (paramInt == 110)
      paramBitSet.set(177); 
    return zfh;
  }
  
  private static Zfh ZcB(int paramInt, BitSet paramBitSet, EnumSet<Zfh> paramEnumSet) {
    Zfh zfh = null;
    if (paramInt == 114)
      paramBitSet.set(114); 
    return zfh;
  }
  
  private static Zfh ZcI(int paramInt, BitSet paramBitSet, EnumSet<Zfh> paramEnumSet) {
    Zfh zfh = null;
    if (paramInt == 100 && paramEnumSet.contains(Zfh.METHOD))
      zfh = Zfh.METHOD; 
    return zfh;
  }
  
  private static Zfh Zm(int paramInt, BitSet paramBitSet, EnumSet<Zfh> paramEnumSet) {
    Zfh zfh = null;
    if (paramInt == 112)
      paramBitSet.set(29); 
    return zfh;
  }
  
  private static Zfh Zr6(int paramInt, BitSet paramBitSet, EnumSet<Zfh> paramEnumSet) {
    Zfh zfh = null;
    if (paramInt == 101)
      paramBitSet.set(40); 
    return zfh;
  }
  
  private static Zfh ZR(int paramInt, BitSet paramBitSet, EnumSet<Zfh> paramEnumSet) {
    Zfh zfh = null;
    if (paramInt >= 48 && paramInt <= 57 && paramEnumSet.contains(Zfh.NATURAL_NUMBER))
      zfh = Zfh.NATURAL_NUMBER; 
    return zfh;
  }
  
  private static Zfh Zb(int paramInt, BitSet paramBitSet, EnumSet<Zfh> paramEnumSet) {
    Zfh zfh = null;
    if (paramInt == 116)
      paramBitSet.set(93); 
    return zfh;
  }
  
  private static void Zr() {
    Zfw[] arrayOfZfw = { 
        Zug::ZuJ, Zug::ZE, Zug::Zw, Zug::Zcj, Zug::Zcb, Zug::Zcz, Zug::Zri, Zug::Zrf, Zug::Zcx, Zug::Zuj, 
        Zug::Zp, Zug::Zcp, Zug::ZrF, Zug::Zck, Zug::Zc5, Zug::ZuL, Zug::Zra, Zug::Zrb, Zug::Zcm, Zug::Zcd, 
        Zug::Zcq, Zug::Zrr, Zug::ZcZ, Zug::Zco, Zug::ZcR, Zug::ZrP, Zug::ZrR, Zug::Zc3, Zug::Zrc, Zug::ZuW, 
        Zug::Zrs, Zug::Zcw, Zug::Zr8, Zug::ZT, Zug::ZrN, Zug::ZrH, Zug::ZW, Zug::ZcW, Zug::ZrY, Zug::Zr5, 
        Zug::Zd, Zug::Zrz, Zug::Zuq, Zug::Zrj, Zug::Zr7, Zug::Zr2, Zug::Zru, Zug::Zc7, Zug::ZcJ, Zug::ZI, 
        Zug::Zry, Zug::ZuE, Zug::ZcQ, Zug::Zu9, Zug::ZuG, Zug::ZcP, Zug::ZU, Zug::Zce, Zug::Zre, Zug::Zrd, 
        Zug::ZrB, Zug::ZrE, Zug::ZM, Zug::ZcC, Zug::ZQ, Zug::Zuv, Zug::Ze, Zug::Zux, Zug::Zcs, Zug::ZJ, 
        Zug::Zr_, Zug::ZcE, Zug::ZuU, Zug::ZcY, Zug::Zun, Zug::Zn, Zug::ZrD, Zug::Zv, Zug::ZcG, Zug::Zcg, 
        Zug::Zh, Zug::Zrn, Zug::ZZ, Zug::Zus, Zug::Zu, Zug::Zcc, Zug::ZcU, Zug::ZcA, Zug::Zu4, Zug::Zrk, 
        Zug::Zrh, Zug::Z_, Zug::ZrZ, Zug::ZrO, Zug::Zrg, Zug::Zf, Zug::Zcf, Zug::Zr1, Zug::ZrA, Zug::Zr, 
        Zug::Zrm, Zug::Zrq, Zug::ZrQ, Zug::Zcr, Zug::ZG, Zug::ZcD, Zug::Zr4, Zug::ZcS, Zug::ZcT, Zug::Zcl, 
        Zug::Zrv, Zug::ZrK, Zug::Zt, Zug::Zui, Zug::ZrT, Zug::Zs, Zug::Zc0, Zug::ZL, Zug::Zc_, Zug::Zc1, 
        Zug::Zg, Zug::Zk, Zug::ZcM, Zug::ZP, Zug::ZA, Zug::ZrW, Zug::ZrL, Zug::ZF, Zug::ZcL, Zug::Zc2, 
        Zug::ZuV, Zug::ZV, Zug::Zy, Zug::Zud, Zug::Zcv, Zug::ZuO, Zug::Zc8, Zug::ZrC, Zug::Zct, Zug::Zu_, 
        Zug::Zx, Zug::Zz, Zug::Zcu, Zug::Zi, Zug::ZcO, Zug::ZY, Zug::ZrJ, Zug::Zr0, Zug::ZuX, Zug::Zr9, 
        Zug::Zc4, Zug::ZB, Zug::Zci, Zug::ZN, Zug::Zrt, Zug::ZrM, Zug::Zrl, Zug::ZS, Zug::Zl, Zug::ZD, 
        Zug::ZcX, Zug::ZO, Zug::ZC, Zug::ZrX, Zug::Zrx, Zug::Zq, Zug::Zca, Zug::Zc9, Zug::Zc6, Zug::ZcN, 
        Zug::Zc, Zug::ZrV, Zug::ZcF, Zug::Za, Zug::ZH, Zug::ZcK, Zug::ZX, Zug::ZuK, Zug::ZrS, Zug::Zcy, 
        Zug::Zch, Zug::ZcV, Zug::ZrU, Zug::Zo, Zug::Zro, Zug::ZrI, Zug::Zr3, Zug::ZcH, Zug::Zj, Zug::Zcn, 
        Zug::Zrw, Zug::ZrG, Zug::Zrp, Zug::ZK, Zug::ZcB, Zug::ZcI, Zug::Zm, Zug::Zr6, Zug::ZR, Zug::Zb };
    Zuk.ZC.put(Zzv.ActiveCheck, arrayOfZfw);
  }
}


/* Location:              C:\Program Files\BurpSuitePro\burpsuite_pro.jar!\net\portswigger\Zug.class
 * Java compiler version: 21 (65.0)
 * JD-Core Version:       1.1.3
 */