package com.fasterxml.Zor;

import com.fasterxml.Zb.Za;
import com.fasterxml.Zb.Zb;
import com.fasterxml.Zb.Zf;
import com.fasterxml.Zb.Zg;
import com.fasterxml.Zb.Zl;
import com.fasterxml.Zb.Zm;
import com.fasterxml.Zb.Zma;
import com.fasterxml.Zb.Zmd;
import com.fasterxml.Zb.Zmi;
import com.fasterxml.Zb.Zmk;
import com.fasterxml.Zb.Zmt;
import com.fasterxml.Zb.Zp;
import com.fasterxml.Zb.Zu;
import com.fasterxml.Zc.Zf;
import com.fasterxml.Zc.Zo;
import com.fasterxml.Zg.Zfc;
import com.fasterxml.Zg.Zk;
import com.fasterxml.Zg.Zl;
import com.fasterxml.Zg.Zs;
import com.fasterxml.Zh.Zi;
import com.fasterxml.Zi.Za;
import com.fasterxml.Zi.Zg;
import com.fasterxml.Zj.Ze;
import com.fasterxml.Zj.Zn;
import com.fasterxml.Zj.Zp;
import com.fasterxml.Zj.Zqf;
import com.fasterxml.Zj.Zv;
import com.fasterxml.Zk.Zj;
import com.fasterxml.Zk.Zl;
import com.fasterxml.Zk.Zn;
import com.fasterxml.Zk.Zv;
import com.fasterxml.Zm.Zek;
import com.fasterxml.Zm.Zx;
import com.fasterxml.Zo.Zg;
import com.fasterxml.Zo.Zz;
import com.fasterxml.Zo.Zzd;
import com.fasterxml.Zo.Zzs;
import com.fasterxml.Zo3.Zk;
import com.fasterxml.Zoz.Z_;
import com.fasterxml.Zoz.Zg;
import com.fasterxml.Zoz.Ziw;
import com.fasterxml.Zp.Zd;
import com.fasterxml.Zp.Zq;
import com.fasterxml.Zqg;
import com.fasterxml.Zv_;
import com.fasterxml.Zy2;
import com.fasterxml.Zz_;
import java.io.Closeable;
import java.io.IOException;
import java.io.OutputStream;
import java.io.Serializable;
import java.io.Writer;
import java.lang.reflect.Type;
import java.util.LinkedHashSet;
import java.util.Map;
import java.util.Set;
import java.util.concurrent.ConcurrentHashMap;

public class Zy6 extends Zmd implements Zu, Serializable {
  private static final long serialVersionUID = 2L;
  
  protected static final Zt Zk;
  
  protected static final Ze Zh;
  
  protected final Zmi Zd;
  
  protected Zi ZG;
  
  protected Zyk Zw;
  
  protected Zq Zb;
  
  protected final Zn ZA;
  
  protected final Zqf ZW;
  
  protected Ziw ZK;
  
  protected Zy7 ZM;
  
  protected Zn ZC;
  
  protected Zl Zx;
  
  protected Zyc ZB;
  
  protected Zzd Zg;
  
  protected Set<Object> Zq;
  
  protected final ConcurrentHashMap<Zk, Zyo<Object>> Zf = new ConcurrentHashMap<>(64, 0.6F, 2);
  
  private static final String[] a;
  
  private static final String[] b;
  
  public Zy6() {
    this(null, null, null);
  }
  
  public Zy6(Zmi paramZmi) {
    this(paramZmi, null, null);
  }
  
  public Zy6(Zmi paramZmi, Zn paramZn, Zzd paramZzd) {
    if (paramZmi == null) {
      this.Zd = new Zyu(this);
    } else {
      try {
        this.Zd = paramZmi;
        if (paramZmi.Zo() == null)
          this.Zd.ZL(this); 
      } catch (IllegalArgumentException illegalArgumentException) {
        throw a(null);
      } 
    } 
    this.Zb = (Zq)new Zk();
    Zek zek = new Zek();
    this.ZG = Zi.ZF();
    Ziw ziw = new Ziw(null);
    this.ZK = ziw;
    Ze ze = Zh.Zm(ZZ());
    this.ZA = new Zn();
    this.ZW = new Zqf();
    this.ZM = new Zy7(ze, this.Zb, ziw, zek, this.ZA, Zp.ZA());
    this.ZB = new Zyc(ze, this.Zb, ziw, zek, this.ZA, this.ZW, Zp.ZA());
    boolean bool = this.Zd.ZE();
    try {
      if (bool ^ this.ZM.ZB(Zy9.SORT_PROPERTIES_ALPHABETICALLY))
        ZJ(Zy9.SORT_PROPERTIES_ALPHABETICALLY, bool); 
    } catch (IllegalArgumentException illegalArgumentException) {
      throw a(null);
    } 
    try {
    
    } catch (IllegalArgumentException illegalArgumentException) {
      throw a(null);
    } 
    try {
      this.ZC = (paramZn == null) ? (Zn)new Zj() : paramZn;
    } catch (IllegalArgumentException illegalArgumentException) {
      throw a(null);
    } 
    this.Zg = (paramZzd == null) ? (Zzd)new Zzs((Zz)Zg.ZI) : paramZzd;
    this.Zx = (Zl)Zv.ZV;
  }
  
  protected Zg ZZ() {
    return (Zg)new Z_();
  }
  
  protected Zy4 Zq(Zyc paramZyc, Zk paramZk, Object paramObject, Zb paramZb, Zyk paramZyk) {
    return new Zy4(this, paramZyc, paramZk, paramObject, paramZb, paramZyk);
  }
  
  protected Zn ZZ(Zy7 paramZy7) {
    return new Zn(this, paramZy7);
  }
  
  protected Zn Zo(Zy7 paramZy7, Zk paramZk, Zp paramZp) {
    return new Zn(this, paramZy7, paramZk, paramZp);
  }
  
  public Zmk version() {
    return Zv.ZV;
  }
  
  public Zy6 ZF(Za paramZa) {
    ZT(a(18655, -17656), paramZa);
    String str = paramZa.ZW();
    try {
      if (str == null)
        throw new IllegalArgumentException(a(18654, 23241)); 
    } catch (IllegalArgumentException illegalArgumentException) {
      throw a(null);
    } 
    Zmk zmk = paramZa.version();
    try {
      if (zmk == null)
        throw new IllegalArgumentException(a(18649, -24938)); 
    } catch (IllegalArgumentException illegalArgumentException) {
      throw a(null);
    } 
    for (Za za : paramZa.Zx())
      ZF(za); 
    if (ZH(Zy9.IGNORE_DUPLICATE_MODULE_REGISTRATIONS)) {
      Object object = paramZa.Zn();
      try {
        if (object != null) {
          try {
            if (this.Zq == null)
              this.Zq = new LinkedHashSet(); 
          } catch (IllegalArgumentException illegalArgumentException) {
            throw a(null);
          } 
          try {
            if (!this.Zq.add(object))
              return this; 
          } catch (IllegalArgumentException illegalArgumentException) {
            throw a(null);
          } 
        } 
      } catch (IllegalArgumentException illegalArgumentException) {
        throw a(null);
      } 
    } 
    paramZa.setupModule(new Zy(this));
    return this;
  }
  
  public Zf Ze(OutputStream paramOutputStream, Zma paramZma) throws IOException {
    ZT(a(18644, -1994), paramOutputStream);
    Zf zf = this.Zd.ZJ(paramOutputStream, paramZma);
    this.ZM.Za(zf);
    return zf;
  }
  
  public Zf ZB(Writer paramWriter) throws IOException {
    ZT("w", paramWriter);
    Zf zf = this.Zd.ZC(paramWriter);
    this.ZM.Za(zf);
    return zf;
  }
  
  public Zy7 ZQ() {
    return this.ZM;
  }
  
  public Zyc ZR() {
    return this.ZB;
  }
  
  public Zy6 Zd(Map<Class<?>, Class<?>> paramMap) {
    this.ZK.ZU(paramMap);
    return this;
  }
  
  public Zy6 Zx(Class<?> paramClass1, Class<?> paramClass2) {
    this.ZK.Zt(paramClass1, paramClass2);
    return this;
  }
  
  public Zq Z_() {
    return this.Zb;
  }
  
  public Zy6 ZJ(Ze paramZe) {
    this.ZM = (Zy7)this.ZM.Zt(paramZe);
    this.ZB = (Zyc)this.ZB.Zt(paramZe);
    return this;
  }
  
  public Zy6 ZQ(Zqg paramZqg) {
    Zo(Zz_.ZB(paramZqg, paramZqg));
    return this;
  }
  
  @Deprecated
  public Zy6 Zo(Zz_ paramZz_) {
    return Z_(paramZz_);
  }
  
  public Zy6 Z_(Zz_ paramZz_) {
    this.ZA.ZD(paramZz_);
    return this;
  }
  
  public void ZZ(Zd... paramVarArgs) {
    Z_().Zt(paramVarArgs);
  }
  
  public Zi ZS() {
    return this.ZG;
  }
  
  public Zk Zt(Type paramType) {
    ZT("t", paramType);
    return this.ZG.ZY(paramType);
  }
  
  public Zfc ZD() {
    return this.ZB.ZX();
  }
  
  public Zmi ZE() {
    return this.Zd;
  }
  
  public boolean ZH(Zy9 paramZy9) {
    return this.ZM.ZB(paramZy9);
  }
  
  @Deprecated
  public Zy6 ZJ(Zy9 paramZy9, boolean paramBoolean) {
    try {
    
    } catch (IllegalArgumentException illegalArgumentException) {
      throw a(null);
    } 
    try {
      this.ZM = paramBoolean ? (Zy7)this.ZM.ZW(new Zy9[] { paramZy9 }) : (Zy7)this.ZM.ZI(new Zy9[] { paramZy9 });
    } catch (IllegalArgumentException illegalArgumentException) {
      throw a(null);
    } 
    this.ZB = paramBoolean ? (Zyc)this.ZB.ZW(new Zy9[] { paramZy9 }) : (Zyc)this.ZB.ZI(new Zy9[] { paramZy9 });
    return this;
  }
  
  public Zy6 ZO(Zy0 paramZy0, boolean paramBoolean) {
    try {
    
    } catch (IllegalArgumentException illegalArgumentException) {
      throw a(null);
    } 
    this.ZM = paramBoolean ? this.ZM.ZI(paramZy0) : this.ZM.Zz(paramZy0);
    return this;
  }
  
  public boolean ZO(Zyp paramZyp) {
    return this.ZB.ZG(paramZyp);
  }
  
  public Zy6 ZZ(Zyp paramZyp, boolean paramBoolean) {
    try {
    
    } catch (IllegalArgumentException illegalArgumentException) {
      throw a(null);
    } 
    this.ZB = paramBoolean ? this.ZB.Zk(paramZyp) : this.ZB.ZL(paramZyp);
    return this;
  }
  
  public Zy6 Zi(Zyp paramZyp) {
    this.ZB = this.ZB.Zk(paramZyp);
    return this;
  }
  
  public Zy6 Z_(Zm... paramVarArgs) {
    for (Zm zm : paramVarArgs)
      this.Zd.Zs(zm); 
    return this;
  }
  
  public <T> T ZB(Zg paramZg, Class<T> paramClass) throws IOException, Za, Zym {
    ZT("p", paramZg);
    return (T)ZD(ZR(), paramZg, this.ZG.ZY(paramClass));
  }
  
  public <T extends Za> T Zz(Zg paramZg) throws IOException {
    Zs zs;
    ZT("p", paramZg);
    Zyc zyc = ZR();
    Zl zl = paramZg.Zh();
    if (zl == null) {
      zl = paramZg.ZV();
      try {
        if (zl == null)
          return null; 
      } catch (IOException iOException) {
        throw a(null);
      } 
    } 
    Zb zb = (Zb)ZD(zyc, paramZg, Zt(Zb.class));
    if (zb == null)
      zs = ZD().ZW(); 
    return (T)zs;
  }
  
  public Zb Za(String paramString) throws Zmt, Zy_ {
    ZT(a(18651, -14771), paramString);
    try {
      return Zo(this.Zd.ZH(paramString));
    } catch (Zmt zmt) {
      throw zmt;
    } catch (IOException iOException) {
      throw Zy_.ZG(iOException);
    } 
  }
  
  public Zb ZA(byte[] paramArrayOfbyte) throws IOException {
    ZT(a(18651, -14771), paramArrayOfbyte);
    return Zo(this.Zd.ZG(paramArrayOfbyte));
  }
  
  public void ZZ(Zf paramZf, Object paramObject) throws IOException, Zg, Zym {
    // Byte code:
    //   0: aload_0
    //   1: ldc 'g'
    //   3: aload_1
    //   4: invokevirtual ZT : (Ljava/lang/String;Ljava/lang/Object;)V
    //   7: invokestatic Zp : ()I
    //   10: aload_0
    //   11: invokevirtual ZQ : ()Lcom/fasterxml/Zor/Zy7;
    //   14: astore #4
    //   16: istore_3
    //   17: aload #4
    //   19: getstatic com/fasterxml/Zor/Zy0.INDENT_OUTPUT : Lcom/fasterxml/Zor/Zy0;
    //   22: invokevirtual Zo : (Lcom/fasterxml/Zor/Zy0;)Z
    //   25: ifeq -> 59
    //   28: aload_1
    //   29: invokevirtual ZP : ()Lcom/fasterxml/Zb/Zp;
    //   32: ifnonnull -> 59
    //   35: goto -> 42
    //   38: invokestatic a : (Ljava/lang/Throwable;)Ljava/lang/Throwable;
    //   41: athrow
    //   42: aload_1
    //   43: aload #4
    //   45: invokevirtual Zp : ()Lcom/fasterxml/Zb/Zp;
    //   48: invokevirtual Zy : (Lcom/fasterxml/Zb/Zp;)Lcom/fasterxml/Zb/Zf;
    //   51: pop
    //   52: goto -> 59
    //   55: invokestatic a : (Ljava/lang/Throwable;)Ljava/lang/Throwable;
    //   58: athrow
    //   59: aload #4
    //   61: getstatic com/fasterxml/Zor/Zy0.CLOSE_CLOSEABLE : Lcom/fasterxml/Zor/Zy0;
    //   64: invokevirtual Zo : (Lcom/fasterxml/Zor/Zy0;)Z
    //   67: ifeq -> 103
    //   70: aload_2
    //   71: instanceof java/io/Closeable
    //   74: ifeq -> 103
    //   77: goto -> 84
    //   80: invokestatic a : (Ljava/lang/Throwable;)Ljava/lang/Throwable;
    //   83: athrow
    //   84: aload_0
    //   85: aload_1
    //   86: aload_2
    //   87: aload #4
    //   89: invokespecial Zx : (Lcom/fasterxml/Zb/Zf;Ljava/lang/Object;Lcom/fasterxml/Zor/Zy7;)V
    //   92: iload_3
    //   93: ifne -> 143
    //   96: goto -> 103
    //   99: invokestatic a : (Ljava/lang/Throwable;)Ljava/lang/Throwable;
    //   102: athrow
    //   103: aload_0
    //   104: aload #4
    //   106: invokevirtual ZI : (Lcom/fasterxml/Zor/Zy7;)Lcom/fasterxml/Zk/Zn;
    //   109: aload_1
    //   110: aload_2
    //   111: invokevirtual Zz : (Lcom/fasterxml/Zb/Zf;Ljava/lang/Object;)V
    //   114: aload #4
    //   116: getstatic com/fasterxml/Zor/Zy0.FLUSH_AFTER_WRITE_VALUE : Lcom/fasterxml/Zor/Zy0;
    //   119: invokevirtual Zo : (Lcom/fasterxml/Zor/Zy0;)Z
    //   122: ifeq -> 143
    //   125: goto -> 132
    //   128: invokestatic a : (Ljava/lang/Throwable;)Ljava/lang/Throwable;
    //   131: athrow
    //   132: aload_1
    //   133: invokevirtual flush : ()V
    //   136: goto -> 143
    //   139: invokestatic a : (Ljava/lang/Throwable;)Ljava/lang/Throwable;
    //   142: athrow
    //   143: return
    // Exception table:
    //   from	to	target	type
    //   17	35	38	java/io/IOException
    //   28	52	55	java/io/IOException
    //   59	77	80	java/io/IOException
    //   70	96	99	java/io/IOException
    //   84	125	128	java/io/IOException
    //   103	136	139	java/io/IOException
  }
  
  public Zg ZF(Za paramZa) {
    ZT("n", paramZa);
    return (Zg)new Zk((Zb)paramZa, this);
  }
  
  public <T> T Zi(Za paramZa, Class<T> paramClass) throws IllegalArgumentException, Zmt {
    try {
      if (paramZa == null)
        return null; 
    } catch (Zmt zmt) {
      throw a(null);
    } 
    try {
      try {
        if (Za.class.isAssignableFrom(paramClass) && paramClass.isAssignableFrom(paramZa.getClass()))
          return (T)paramZa; 
      } catch (Zmt zmt) {
        throw a(null);
      } 
      Zl zl = paramZa.ZV();
      try {
        if (zl == Zl.VALUE_EMBEDDED_OBJECT && paramZa instanceof Zl) {
          Object object = ((Zl)paramZa).ZI();
          try {
            if (object == null || paramClass.isInstance(object))
              return (T)object; 
          } catch (Zmt zmt) {
            throw a(null);
          } 
        } 
      } catch (Zmt zmt) {
        throw a(null);
      } 
      return ZB(ZF(paramZa), paramClass);
    } catch (Zmt zmt) {
      throw zmt;
    } catch (IOException iOException) {
      throw new IllegalArgumentException(iOException.getMessage(), iOException);
    } 
  }
  
  public <T> T Za(String paramString, Class<T> paramClass) throws Zmt, Zy_ {
    ZT(a(18651, -14771), paramString);
    return ZK(paramString, this.ZG.ZY(paramClass));
  }
  
  public <T> T ZK(String paramString, Zk paramZk) throws Zmt, Zy_ {
    ZT(a(18650, -423), paramString);
    try {
      return (T)Zk(this.Zd.ZH(paramString), paramZk);
    } catch (Zmt zmt) {
      throw zmt;
    } catch (IOException iOException) {
      throw Zy_.ZG(iOException);
    } 
  }
  
  public String ZA(Object paramObject) throws Zmt {
    Zo zo = this.Zd.ZG();
    int i = Zyo.Zp();
    try {
      Exception exception;
      Zy2 zy2 = new Zy2(zo);
      Throwable throwable = null;
      try {
        Z_(ZB((Writer)zy2), paramObject);
        String str = zy2.Zb();
        try {
          if (zy2 != null) {
            if (throwable != null)
              return str; 
          } else {
            return str;
          } 
        } catch (Throwable throwable1) {
          throw a(null);
        } 
        return str;
      } catch (Throwable throwable1) {
        throwable = throwable1;
        throw throwable1;
      } finally {
        exception = null;
      } 
      zy2.close();
      throw exception;
    } catch (Zmt zmt) {
      throw zmt;
    } catch (IOException iOException) {
      throw Zy_.ZG(iOException);
    } finally {
      zo.Zh();
    } 
  }
  
  public byte[] ZG(Object paramObject) throws Zmt {
    Zo zo = this.Zd.ZG();
    int i = Zyo.ZZ();
    try {
      Exception exception;
      Zf zf = new Zf(zo);
      Throwable throwable = null;
      try {
        Z_(Ze((OutputStream)zf, Zma.UTF8), paramObject);
        byte[] arrayOfByte1 = zf.ZA();
        zf.Za();
        byte[] arrayOfByte2 = arrayOfByte1;
        try {
          if (zf != null) {
            if (throwable != null)
              return arrayOfByte2; 
          } else {
            return arrayOfByte2;
          } 
        } catch (Throwable throwable1) {
          throw a(null);
        } 
        return arrayOfByte2;
      } catch (Throwable throwable1) {
        throwable = throwable1;
        throw throwable1;
      } finally {
        exception = null;
      } 
      zf.close();
      throw exception;
    } catch (Zmt zmt) {
      throw zmt;
    } catch (IOException iOException) {
      throw Zy_.ZG(iOException);
    } finally {
      zo.Zh();
    } 
  }
  
  public Zn Zr() {
    return ZZ(ZQ());
  }
  
  public Zn ZN(Class<?> paramClass) {
    return ZZ(ZQ().ZX(paramClass));
  }
  
  public Zn ZD(Zp paramZp) {
    if (paramZp == null)
      paramZp = Zn.ZW; 
    return Zo(ZQ(), null, paramZp);
  }
  
  public Zy4 ZV(Class<?> paramClass) {
    try {
    
    } catch (IllegalArgumentException illegalArgumentException) {
      throw a(null);
    } 
    Zk zk = (paramClass == null) ? null : this.ZG.ZY(paramClass);
    return Zq(ZR(), zk, null, null, this.Zw);
  }
  
  public <T> T Zb(Object paramObject, Class<T> paramClass) throws IllegalArgumentException {
    return (T)ZJ(paramObject, this.ZG.ZY(paramClass));
  }
  
  public <T> T Zh(Object paramObject, Zk paramZk) throws IllegalArgumentException {
    return (T)ZJ(paramObject, paramZk);
  }
  
  protected Object ZJ(Object paramObject, Zk paramZk) throws IllegalArgumentException {
    // Byte code:
    //   0: invokestatic Zp : ()I
    //   3: aload_0
    //   4: invokevirtual ZQ : ()Lcom/fasterxml/Zor/Zy7;
    //   7: getstatic com/fasterxml/Zor/Zy0.WRAP_ROOT_VALUE : Lcom/fasterxml/Zor/Zy0;
    //   10: invokevirtual Zz : (Lcom/fasterxml/Zor/Zy0;)Lcom/fasterxml/Zor/Zy7;
    //   13: astore #4
    //   15: istore_3
    //   16: aload_0
    //   17: aload #4
    //   19: invokevirtual ZI : (Lcom/fasterxml/Zor/Zy7;)Lcom/fasterxml/Zk/Zn;
    //   22: astore #5
    //   24: aload #5
    //   26: aload_0
    //   27: invokevirtual Zn : (Lcom/fasterxml/Zb/Zmd;)Lcom/fasterxml/Zm/Zl;
    //   30: astore #6
    //   32: aload_0
    //   33: getstatic com/fasterxml/Zor/Zyp.USE_BIG_DECIMAL_FOR_FLOATS : Lcom/fasterxml/Zor/Zyp;
    //   36: invokevirtual ZO : (Lcom/fasterxml/Zor/Zyp;)Z
    //   39: ifeq -> 50
    //   42: aload #6
    //   44: iconst_1
    //   45: invokevirtual ZI : (Z)Lcom/fasterxml/Zm/Zl;
    //   48: astore #6
    //   50: aload #5
    //   52: aload #6
    //   54: aload_1
    //   55: invokevirtual Zz : (Lcom/fasterxml/Zb/Zf;Ljava/lang/Object;)V
    //   58: aload #6
    //   60: invokevirtual Zp : ()Lcom/fasterxml/Zb/Zg;
    //   63: astore #7
    //   65: aload_0
    //   66: invokevirtual ZR : ()Lcom/fasterxml/Zor/Zyc;
    //   69: astore #9
    //   71: aload_0
    //   72: aload #7
    //   74: aload_2
    //   75: invokevirtual Zt : (Lcom/fasterxml/Zb/Zg;Lcom/fasterxml/Zor/Zk;)Lcom/fasterxml/Zb/Zl;
    //   78: astore #10
    //   80: aload #10
    //   82: getstatic com/fasterxml/Zb/Zl.VALUE_NULL : Lcom/fasterxml/Zb/Zl;
    //   85: if_acmpne -> 116
    //   88: aload_0
    //   89: aload #7
    //   91: aload #9
    //   93: invokevirtual Zy : (Lcom/fasterxml/Zb/Zg;Lcom/fasterxml/Zor/Zyc;)Lcom/fasterxml/Zo/Zzd;
    //   96: astore #11
    //   98: aload_0
    //   99: aload #11
    //   101: aload_2
    //   102: invokevirtual Zg : (Lcom/fasterxml/Zor/Zyg;Lcom/fasterxml/Zor/Zk;)Lcom/fasterxml/Zor/Zyo;
    //   105: aload #11
    //   107: invokevirtual Zj : (Lcom/fasterxml/Zor/Zyg;)Ljava/lang/Object;
    //   110: astore #8
    //   112: iload_3
    //   113: ifne -> 183
    //   116: aload #10
    //   118: getstatic com/fasterxml/Zb/Zl.END_ARRAY : Lcom/fasterxml/Zb/Zl;
    //   121: if_acmpeq -> 146
    //   124: goto -> 131
    //   127: invokestatic a : (Ljava/lang/Throwable;)Ljava/lang/Throwable;
    //   130: athrow
    //   131: aload #10
    //   133: getstatic com/fasterxml/Zb/Zl.END_OBJECT : Lcom/fasterxml/Zb/Zl;
    //   136: if_acmpne -> 153
    //   139: goto -> 146
    //   142: invokestatic a : (Ljava/lang/Throwable;)Ljava/lang/Throwable;
    //   145: athrow
    //   146: aconst_null
    //   147: astore #8
    //   149: iload_3
    //   150: ifne -> 183
    //   153: aload_0
    //   154: aload #7
    //   156: aload #9
    //   158: invokevirtual Zy : (Lcom/fasterxml/Zb/Zg;Lcom/fasterxml/Zor/Zyc;)Lcom/fasterxml/Zo/Zzd;
    //   161: astore #11
    //   163: aload_0
    //   164: aload #11
    //   166: aload_2
    //   167: invokevirtual Zg : (Lcom/fasterxml/Zor/Zyg;Lcom/fasterxml/Zor/Zk;)Lcom/fasterxml/Zor/Zyo;
    //   170: astore #12
    //   172: aload #12
    //   174: aload #7
    //   176: aload #11
    //   178: invokevirtual deserialize : (Lcom/fasterxml/Zb/Zg;Lcom/fasterxml/Zor/Zyg;)Ljava/lang/Object;
    //   181: astore #8
    //   183: aload #7
    //   185: invokevirtual close : ()V
    //   188: aload #8
    //   190: areturn
    //   191: astore #7
    //   193: new java/lang/IllegalArgumentException
    //   196: dup
    //   197: aload #7
    //   199: invokevirtual getMessage : ()Ljava/lang/String;
    //   202: aload #7
    //   204: invokespecial <init> : (Ljava/lang/String;Ljava/lang/Throwable;)V
    //   207: athrow
    // Exception table:
    //   from	to	target	type
    //   50	190	191	java/io/IOException
    //   112	124	127	java/io/IOException
    //   116	139	142	java/io/IOException
  }
  
  protected Zn ZI(Zy7 paramZy7) {
    return this.ZC.ZE(paramZy7, this.Zx);
  }
  
  protected final void Z_(Zf paramZf, Object paramObject) throws IOException {
    Zy7 zy7 = ZQ();
    try {
      if (zy7.Zo(Zy0.CLOSE_CLOSEABLE))
        try {
          if (paramObject instanceof Closeable) {
            Za(paramZf, paramObject, zy7);
            return;
          } 
        } catch (Exception exception) {
          throw a(null);
        }  
    } catch (Exception exception) {
      throw a(null);
    } 
    try {
      ZI(zy7).Zz(paramZf, paramObject);
    } catch (Exception exception) {
      Zx.Zm(paramZf, exception);
      return;
    } 
    paramZf.close();
  }
  
  private final void Za(Zf paramZf, Object paramObject, Zy7 paramZy7) throws IOException {
    Closeable closeable = (Closeable)paramObject;
    try {
      ZI(paramZy7).Zz(paramZf, paramObject);
      Closeable closeable1 = closeable;
      closeable = null;
      closeable1.close();
    } catch (Exception exception) {
      Zx.ZP(paramZf, closeable, exception);
      return;
    } 
    paramZf.close();
  }
  
  private final void Zx(Zf paramZf, Object paramObject, Zy7 paramZy7) throws IOException {
    Closeable closeable = (Closeable)paramObject;
    try {
      ZI(paramZy7).Zz(paramZf, paramObject);
      if (paramZy7.Zo(Zy0.FLUSH_AFTER_WRITE_VALUE))
        paramZf.flush(); 
    } catch (Exception exception) {
      Zx.ZP(null, closeable, exception);
      return;
    } 
    closeable.close();
  }
  
  protected Object ZD(Zyc paramZyc, Zg paramZg, Zk paramZk) throws IOException {
    // Byte code:
    //   0: aload_0
    //   1: aload_2
    //   2: aload_3
    //   3: invokevirtual Zt : (Lcom/fasterxml/Zb/Zg;Lcom/fasterxml/Zor/Zk;)Lcom/fasterxml/Zb/Zl;
    //   6: astore #6
    //   8: invokestatic ZZ : ()I
    //   11: aload_0
    //   12: aload_2
    //   13: aload_1
    //   14: invokevirtual Zy : (Lcom/fasterxml/Zb/Zg;Lcom/fasterxml/Zor/Zyc;)Lcom/fasterxml/Zo/Zzd;
    //   17: astore #7
    //   19: istore #4
    //   21: aload #6
    //   23: getstatic com/fasterxml/Zb/Zl.VALUE_NULL : Lcom/fasterxml/Zb/Zl;
    //   26: if_acmpne -> 48
    //   29: aload_0
    //   30: aload #7
    //   32: aload_3
    //   33: invokevirtual Zg : (Lcom/fasterxml/Zor/Zyg;Lcom/fasterxml/Zor/Zk;)Lcom/fasterxml/Zor/Zyo;
    //   36: aload #7
    //   38: invokevirtual Zj : (Lcom/fasterxml/Zor/Zyg;)Ljava/lang/Object;
    //   41: astore #5
    //   43: iload #4
    //   45: ifeq -> 103
    //   48: aload #6
    //   50: getstatic com/fasterxml/Zb/Zl.END_ARRAY : Lcom/fasterxml/Zb/Zl;
    //   53: if_acmpeq -> 78
    //   56: goto -> 63
    //   59: invokestatic a : (Ljava/lang/Throwable;)Ljava/lang/Throwable;
    //   62: athrow
    //   63: aload #6
    //   65: getstatic com/fasterxml/Zb/Zl.END_OBJECT : Lcom/fasterxml/Zb/Zl;
    //   68: if_acmpne -> 86
    //   71: goto -> 78
    //   74: invokestatic a : (Ljava/lang/Throwable;)Ljava/lang/Throwable;
    //   77: athrow
    //   78: aconst_null
    //   79: astore #5
    //   81: iload #4
    //   83: ifeq -> 103
    //   86: aload #7
    //   88: aload_2
    //   89: aload_3
    //   90: aload_0
    //   91: aload #7
    //   93: aload_3
    //   94: invokevirtual Zg : (Lcom/fasterxml/Zor/Zyg;Lcom/fasterxml/Zor/Zk;)Lcom/fasterxml/Zor/Zyo;
    //   97: aconst_null
    //   98: invokevirtual ZU : (Lcom/fasterxml/Zb/Zg;Lcom/fasterxml/Zor/Zk;Lcom/fasterxml/Zor/Zyo;Ljava/lang/Object;)Ljava/lang/Object;
    //   101: astore #5
    //   103: aload_2
    //   104: invokevirtual Zo : ()V
    //   107: aload_1
    //   108: getstatic com/fasterxml/Zor/Zyp.FAIL_ON_TRAILING_TOKENS : Lcom/fasterxml/Zor/Zyp;
    //   111: invokevirtual ZG : (Lcom/fasterxml/Zor/Zyp;)Z
    //   114: ifeq -> 132
    //   117: aload_0
    //   118: aload_2
    //   119: aload #7
    //   121: aload_3
    //   122: invokevirtual Zx : (Lcom/fasterxml/Zb/Zg;Lcom/fasterxml/Zor/Zyg;Lcom/fasterxml/Zor/Zk;)V
    //   125: goto -> 132
    //   128: invokestatic a : (Ljava/lang/Throwable;)Ljava/lang/Throwable;
    //   131: athrow
    //   132: aload #5
    //   134: areturn
    // Exception table:
    //   from	to	target	type
    //   43	56	59	java/io/IOException
    //   48	71	74	java/io/IOException
    //   103	125	128	java/io/IOException
  }
  
  protected Object Zk(Zg paramZg, Zk paramZk) throws IOException {
    // Byte code:
    //   0: invokestatic ZZ : ()I
    //   3: aload_1
    //   4: astore #4
    //   6: aconst_null
    //   7: astore #5
    //   9: istore_3
    //   10: aload_0
    //   11: invokevirtual ZR : ()Lcom/fasterxml/Zor/Zyc;
    //   14: astore #7
    //   16: aload_0
    //   17: aload #4
    //   19: aload #7
    //   21: invokevirtual Zy : (Lcom/fasterxml/Zb/Zg;Lcom/fasterxml/Zor/Zyc;)Lcom/fasterxml/Zo/Zzd;
    //   24: astore #8
    //   26: aload_0
    //   27: aload #4
    //   29: aload_2
    //   30: invokevirtual Zt : (Lcom/fasterxml/Zb/Zg;Lcom/fasterxml/Zor/Zk;)Lcom/fasterxml/Zb/Zl;
    //   33: astore #9
    //   35: aload #9
    //   37: getstatic com/fasterxml/Zb/Zl.VALUE_NULL : Lcom/fasterxml/Zb/Zl;
    //   40: if_acmpne -> 61
    //   43: aload_0
    //   44: aload #8
    //   46: aload_2
    //   47: invokevirtual Zg : (Lcom/fasterxml/Zor/Zyg;Lcom/fasterxml/Zor/Zk;)Lcom/fasterxml/Zor/Zyo;
    //   50: aload #8
    //   52: invokevirtual Zj : (Lcom/fasterxml/Zor/Zyg;)Ljava/lang/Object;
    //   55: astore #6
    //   57: iload_3
    //   58: ifeq -> 121
    //   61: aload #9
    //   63: getstatic com/fasterxml/Zb/Zl.END_ARRAY : Lcom/fasterxml/Zb/Zl;
    //   66: if_acmpeq -> 91
    //   69: goto -> 76
    //   72: invokestatic a : (Ljava/lang/Throwable;)Ljava/lang/Throwable;
    //   75: athrow
    //   76: aload #9
    //   78: getstatic com/fasterxml/Zb/Zl.END_OBJECT : Lcom/fasterxml/Zb/Zl;
    //   81: if_acmpne -> 98
    //   84: goto -> 91
    //   87: invokestatic a : (Ljava/lang/Throwable;)Ljava/lang/Throwable;
    //   90: athrow
    //   91: aconst_null
    //   92: astore #6
    //   94: iload_3
    //   95: ifeq -> 121
    //   98: aload #8
    //   100: aload #4
    //   102: aload_2
    //   103: aload_0
    //   104: aload #8
    //   106: aload_2
    //   107: invokevirtual Zg : (Lcom/fasterxml/Zor/Zyg;Lcom/fasterxml/Zor/Zk;)Lcom/fasterxml/Zor/Zyo;
    //   110: aconst_null
    //   111: invokevirtual ZU : (Lcom/fasterxml/Zb/Zg;Lcom/fasterxml/Zor/Zk;Lcom/fasterxml/Zor/Zyo;Ljava/lang/Object;)Ljava/lang/Object;
    //   114: astore #6
    //   116: aload #8
    //   118: invokevirtual Zo : ()V
    //   121: aload #7
    //   123: getstatic com/fasterxml/Zor/Zyp.FAIL_ON_TRAILING_TOKENS : Lcom/fasterxml/Zor/Zyp;
    //   126: invokevirtual ZG : (Lcom/fasterxml/Zor/Zyp;)Z
    //   129: ifeq -> 148
    //   132: aload_0
    //   133: aload #4
    //   135: aload #8
    //   137: aload_2
    //   138: invokevirtual Zx : (Lcom/fasterxml/Zb/Zg;Lcom/fasterxml/Zor/Zyg;Lcom/fasterxml/Zor/Zk;)V
    //   141: goto -> 148
    //   144: invokestatic a : (Ljava/lang/Throwable;)Ljava/lang/Throwable;
    //   147: athrow
    //   148: aload #6
    //   150: astore #10
    //   152: aload #4
    //   154: ifnull -> 202
    //   157: aload #5
    //   159: ifnull -> 190
    //   162: goto -> 169
    //   165: invokestatic a : (Ljava/lang/Throwable;)Ljava/lang/Throwable;
    //   168: athrow
    //   169: aload #4
    //   171: invokevirtual close : ()V
    //   174: goto -> 202
    //   177: astore #11
    //   179: aload #5
    //   181: aload #11
    //   183: invokevirtual addSuppressed : (Ljava/lang/Throwable;)V
    //   186: iload_3
    //   187: ifeq -> 202
    //   190: aload #4
    //   192: invokevirtual close : ()V
    //   195: goto -> 202
    //   198: invokestatic a : (Ljava/lang/Throwable;)Ljava/lang/Throwable;
    //   201: athrow
    //   202: aload #10
    //   204: areturn
    //   205: astore #6
    //   207: aload #6
    //   209: astore #5
    //   211: aload #6
    //   213: athrow
    //   214: astore #12
    //   216: aload #4
    //   218: ifnull -> 266
    //   221: aload #5
    //   223: ifnull -> 254
    //   226: goto -> 233
    //   229: invokestatic a : (Ljava/lang/Throwable;)Ljava/lang/Throwable;
    //   232: athrow
    //   233: aload #4
    //   235: invokevirtual close : ()V
    //   238: goto -> 266
    //   241: astore #13
    //   243: aload #5
    //   245: aload #13
    //   247: invokevirtual addSuppressed : (Ljava/lang/Throwable;)V
    //   250: iload_3
    //   251: ifeq -> 266
    //   254: aload #4
    //   256: invokevirtual close : ()V
    //   259: goto -> 266
    //   262: invokestatic a : (Ljava/lang/Throwable;)Ljava/lang/Throwable;
    //   265: athrow
    //   266: aload #12
    //   268: athrow
    // Exception table:
    //   from	to	target	type
    //   10	152	205	java/lang/Throwable
    //   10	152	214	finally
    //   57	69	72	java/lang/Throwable
    //   61	84	87	java/lang/Throwable
    //   121	141	144	java/lang/Throwable
    //   152	162	165	java/lang/Throwable
    //   169	174	177	java/lang/Throwable
    //   179	195	198	java/lang/Throwable
    //   205	216	214	finally
    //   216	226	229	java/lang/Throwable
    //   233	238	241	java/lang/Throwable
    //   243	259	262	java/lang/Throwable
  }
  
  protected Zb Zo(Zg paramZg) throws IOException {
    // Byte code:
    //   0: invokestatic Zp : ()I
    //   3: aload_1
    //   4: astore_3
    //   5: aconst_null
    //   6: astore #4
    //   8: istore_2
    //   9: aload_0
    //   10: ldc com/fasterxml/Zor/Zb
    //   12: invokevirtual Zt : (Ljava/lang/reflect/Type;)Lcom/fasterxml/Zor/Zk;
    //   15: astore #5
    //   17: aload_0
    //   18: invokevirtual ZR : ()Lcom/fasterxml/Zor/Zyc;
    //   21: astore #6
    //   23: aload #6
    //   25: aload_3
    //   26: invokevirtual ZO : (Lcom/fasterxml/Zb/Zg;)Lcom/fasterxml/Zb/Zg;
    //   29: pop
    //   30: aload_3
    //   31: invokevirtual Zh : ()Lcom/fasterxml/Zb/Zl;
    //   34: astore #7
    //   36: aload #7
    //   38: ifnonnull -> 112
    //   41: aload_3
    //   42: invokevirtual ZV : ()Lcom/fasterxml/Zb/Zl;
    //   45: astore #7
    //   47: aload #7
    //   49: ifnonnull -> 112
    //   52: aload #6
    //   54: invokevirtual ZX : ()Lcom/fasterxml/Zg/Zfc;
    //   57: invokevirtual ZG : ()Lcom/fasterxml/Zor/Zb;
    //   60: astore #8
    //   62: aload_3
    //   63: ifnull -> 109
    //   66: aload #4
    //   68: ifnull -> 98
    //   71: goto -> 78
    //   74: invokestatic a : (Ljava/lang/Throwable;)Ljava/lang/Throwable;
    //   77: athrow
    //   78: aload_3
    //   79: invokevirtual close : ()V
    //   82: goto -> 109
    //   85: astore #9
    //   87: aload #4
    //   89: aload #9
    //   91: invokevirtual addSuppressed : (Ljava/lang/Throwable;)V
    //   94: iload_2
    //   95: ifne -> 109
    //   98: aload_3
    //   99: invokevirtual close : ()V
    //   102: goto -> 109
    //   105: invokestatic a : (Ljava/lang/Throwable;)Ljava/lang/Throwable;
    //   108: athrow
    //   109: aload #8
    //   111: areturn
    //   112: aload_0
    //   113: aload_3
    //   114: aload #6
    //   116: invokevirtual Zy : (Lcom/fasterxml/Zb/Zg;Lcom/fasterxml/Zor/Zyc;)Lcom/fasterxml/Zo/Zzd;
    //   119: astore #9
    //   121: aload #7
    //   123: getstatic com/fasterxml/Zb/Zl.VALUE_NULL : Lcom/fasterxml/Zb/Zl;
    //   126: if_acmpne -> 143
    //   129: aload #6
    //   131: invokevirtual ZX : ()Lcom/fasterxml/Zg/Zfc;
    //   134: invokevirtual ZW : ()Lcom/fasterxml/Zg/Zs;
    //   137: astore #8
    //   139: iload_2
    //   140: ifne -> 165
    //   143: aload #9
    //   145: aload_3
    //   146: aload #5
    //   148: aload_0
    //   149: aload #9
    //   151: aload #5
    //   153: invokevirtual Zg : (Lcom/fasterxml/Zor/Zyg;Lcom/fasterxml/Zor/Zk;)Lcom/fasterxml/Zor/Zyo;
    //   156: aconst_null
    //   157: invokevirtual ZU : (Lcom/fasterxml/Zb/Zg;Lcom/fasterxml/Zor/Zk;Lcom/fasterxml/Zor/Zyo;Ljava/lang/Object;)Ljava/lang/Object;
    //   160: checkcast com/fasterxml/Zor/Zb
    //   163: astore #8
    //   165: aload #6
    //   167: getstatic com/fasterxml/Zor/Zyp.FAIL_ON_TRAILING_TOKENS : Lcom/fasterxml/Zor/Zyp;
    //   170: invokevirtual ZG : (Lcom/fasterxml/Zor/Zyp;)Z
    //   173: ifeq -> 192
    //   176: aload_0
    //   177: aload_3
    //   178: aload #9
    //   180: aload #5
    //   182: invokevirtual Zx : (Lcom/fasterxml/Zb/Zg;Lcom/fasterxml/Zor/Zyg;Lcom/fasterxml/Zor/Zk;)V
    //   185: goto -> 192
    //   188: invokestatic a : (Ljava/lang/Throwable;)Ljava/lang/Throwable;
    //   191: athrow
    //   192: aload #8
    //   194: astore #10
    //   196: aload_3
    //   197: ifnull -> 243
    //   200: aload #4
    //   202: ifnull -> 232
    //   205: goto -> 212
    //   208: invokestatic a : (Ljava/lang/Throwable;)Ljava/lang/Throwable;
    //   211: athrow
    //   212: aload_3
    //   213: invokevirtual close : ()V
    //   216: goto -> 243
    //   219: astore #11
    //   221: aload #4
    //   223: aload #11
    //   225: invokevirtual addSuppressed : (Ljava/lang/Throwable;)V
    //   228: iload_2
    //   229: ifne -> 243
    //   232: aload_3
    //   233: invokevirtual close : ()V
    //   236: goto -> 243
    //   239: invokestatic a : (Ljava/lang/Throwable;)Ljava/lang/Throwable;
    //   242: athrow
    //   243: aload #10
    //   245: areturn
    //   246: astore #5
    //   248: aload #5
    //   250: astore #4
    //   252: aload #5
    //   254: athrow
    //   255: astore #12
    //   257: aload_3
    //   258: ifnull -> 304
    //   261: aload #4
    //   263: ifnull -> 293
    //   266: goto -> 273
    //   269: invokestatic a : (Ljava/lang/Throwable;)Ljava/lang/Throwable;
    //   272: athrow
    //   273: aload_3
    //   274: invokevirtual close : ()V
    //   277: goto -> 304
    //   280: astore #13
    //   282: aload #4
    //   284: aload #13
    //   286: invokevirtual addSuppressed : (Ljava/lang/Throwable;)V
    //   289: iload_2
    //   290: ifne -> 304
    //   293: aload_3
    //   294: invokevirtual close : ()V
    //   297: goto -> 304
    //   300: invokestatic a : (Ljava/lang/Throwable;)Ljava/lang/Throwable;
    //   303: athrow
    //   304: aload #12
    //   306: athrow
    // Exception table:
    //   from	to	target	type
    //   9	62	246	java/lang/Throwable
    //   9	62	255	finally
    //   62	71	74	java/lang/Throwable
    //   78	82	85	java/lang/Throwable
    //   87	102	105	java/lang/Throwable
    //   112	196	246	java/lang/Throwable
    //   112	196	255	finally
    //   165	185	188	java/lang/Throwable
    //   196	205	208	java/lang/Throwable
    //   212	216	219	java/lang/Throwable
    //   221	236	239	java/lang/Throwable
    //   246	257	255	finally
    //   257	266	269	java/lang/Throwable
    //   273	277	280	java/lang/Throwable
    //   282	297	300	java/lang/Throwable
  }
  
  protected Zzd Zy(Zg paramZg, Zyc paramZyc) {
    return this.Zg.Zz(paramZyc, paramZg, this.Zw);
  }
  
  protected Zl Zt(Zg paramZg, Zk paramZk) throws IOException {
    this.ZB.ZO(paramZg);
    Zl zl = paramZg.Zh();
    if (zl == null) {
      zl = paramZg.ZV();
      try {
        if (zl == null)
          throw Zv_.ZR(paramZg, paramZk, a(18653, -14624)); 
      } catch (IOException iOException) {
        throw a(null);
      } 
    } 
    return zl;
  }
  
  protected final void Zx(Zg paramZg, Zyg paramZyg, Zk paramZk) throws IOException {
    Zl zl = paramZg.ZV();
    if (zl != null) {
      Class<?> clazz = Zx.ZB(paramZk);
      paramZyg.Zq(clazz, paramZg, zl);
    } 
  }
  
  protected Zyo<Object> Zg(Zyg paramZyg, Zk paramZk) throws Zym {
    Zyo<Object> zyo = this.Zf.get(paramZk);
    try {
      if (zyo != null)
        return zyo; 
    } catch (Zym zym) {
      throw a(null);
    } 
    zyo = paramZyg.ZP(paramZk);
    try {
      if (zyo == null)
        return paramZyg.<Zyo<Object>>Zm(paramZk, a(18652, -15930) + paramZk); 
    } catch (Zym zym) {
      throw a(null);
    } 
    this.Zf.put(paramZk, zyo);
    return zyo;
  }
  
  protected final void ZT(String paramString, Object paramObject) {
    try {
      if (paramObject == null)
        throw new IllegalArgumentException(String.format(a(18648, 11854), new Object[] { paramString })); 
    } catch (IllegalArgumentException illegalArgumentException) {
      throw a(null);
    } 
  }
  
  static {
    // Byte code:
    //   0: bipush #9
    //   2: anewarray java/lang/String
    //   5: astore #5
    //   7: iconst_0
    //   8: istore_3
    //   9: ldc 'ÂŸÃ¼fÃ¯Â‚Â£zhÃ”~Â›ÃÃ¿>Ã”ÂŒe|Â…ZvÂ…Ã’u:|Ã¢=.Â¼Â”Ã¸"%=>ÃuÃ“FÃ ~q"!%Ã­Ã„Âƒ Â¨ wÂ›g/Ã§Â…ÂŽÃžÂÂ´Â®Â®ÂµhÂ—]VÂ­Ã½Ã¼Ã¯Â¸Ã€hÂ”ÂŸÂ‡a=ÃªhtÂŽÃ˜Ã‡WYÂšÂ‡'TÃ¢Â½=ÂºÂ½3Â€@CÃ¡`nÂ›Ã§Ã†Ã¥Âœ1Ã•ÃµÂ£Ã®ÃÃ›-2ÃµaÂƒSgÃ³Â’kÂ¦Ã¼\\tÂ½lÂ¤@ÃšpÂ¿Â’Â·Ã†#iÃi%'
    //   11: dup
    //   12: astore_2
    //   13: invokevirtual length : ()I
    //   16: istore #4
    //   18: bipush #36
    //   20: istore_1
    //   21: iconst_m1
    //   22: istore_0
    //   23: bipush #86
    //   25: iinc #0, 1
    //   28: aload_2
    //   29: iload_0
    //   30: dup
    //   31: iload_1
    //   32: iadd
    //   33: invokevirtual substring : (II)Ljava/lang/String;
    //   36: iconst_m1
    //   37: goto -> 143
    //   40: aload #5
    //   42: swap
    //   43: iload_3
    //   44: iinc #3, 1
    //   47: swap
    //   48: aastore
    //   49: iload_0
    //   50: iload_1
    //   51: iadd
    //   52: dup
    //   53: istore_0
    //   54: iload #4
    //   56: if_icmpge -> 68
    //   59: aload_2
    //   60: iload_0
    //   61: invokevirtual charAt : (I)C
    //   64: istore_1
    //   65: goto -> 23
    //   68: ldc 'ÃƒÂ“lÂ¨Ã¢Â¤0Ã¨'
    //   70: dup
    //   71: astore_2
    //   72: invokevirtual length : ()I
    //   75: istore #4
    //   77: bipush #7
    //   79: istore_1
    //   80: iconst_m1
    //   81: istore_0
    //   82: bipush #6
    //   84: iinc #0, 1
    //   87: aload_2
    //   88: iload_0
    //   89: dup
    //   90: iload_1
    //   91: iadd
    //   92: invokevirtual substring : (II)Ljava/lang/String;
    //   95: iconst_0
    //   96: goto -> 143
    //   99: aload #5
    //   101: swap
    //   102: iload_3
    //   103: iinc #3, 1
    //   106: swap
    //   107: aastore
    //   108: iload_0
    //   109: iload_1
    //   110: iadd
    //   111: dup
    //   112: istore_0
    //   113: iload #4
    //   115: if_icmpge -> 127
    //   118: aload_2
    //   119: iload_0
    //   120: invokevirtual charAt : (I)C
    //   123: istore_1
    //   124: goto -> 82
    //   127: aload #5
    //   129: putstatic com/fasterxml/Zor/Zy6.a : [Ljava/lang/String;
    //   132: bipush #9
    //   134: anewarray java/lang/String
    //   137: putstatic com/fasterxml/Zor/Zy6.b : [Ljava/lang/String;
    //   140: goto -> 300
    //   143: dup_x2
    //   144: pop
    //   145: invokevirtual toCharArray : ()[C
    //   148: dup_x1
    //   149: arraylength
    //   150: dup_x2
    //   151: pop
    //   152: iconst_0
    //   153: istore #6
    //   155: dup2_x1
    //   156: pop2
    //   157: dup_x2
    //   158: iconst_1
    //   159: if_icmpgt -> 260
    //   162: dup2
    //   163: swap
    //   164: iload #6
    //   166: dup2_x1
    //   167: caload
    //   168: swap
    //   169: iload #6
    //   171: bipush #7
    //   173: irem
    //   174: tableswitch default -> 242, 0 -> 212, 1 -> 217, 2 -> 222, 3 -> 227, 4 -> 232, 5 -> 237
    //   212: bipush #113
    //   214: goto -> 244
    //   217: bipush #61
    //   219: goto -> 244
    //   222: bipush #98
    //   224: goto -> 244
    //   227: bipush #104
    //   229: goto -> 244
    //   232: bipush #82
    //   234: goto -> 244
    //   237: bipush #24
    //   239: goto -> 244
    //   242: bipush #94
    //   244: ixor
    //   245: ixor
    //   246: i2c
    //   247: castore
    //   248: iinc #6, 1
    //   251: dup
    //   252: ifne -> 260
    //   255: dup2
    //   256: dup_x1
    //   257: goto -> 166
    //   260: dup2_x1
    //   261: pop2
    //   262: dup_x2
    //   263: iload #6
    //   265: if_icmpgt -> 162
    //   268: pop
    //   269: new java/lang/String
    //   272: dup_x1
    //   273: swap
    //   274: invokespecial <init> : ([C)V
    //   277: invokevirtual intern : ()Ljava/lang/String;
    //   280: swap
    //   281: pop
    //   282: swap
    //   283: tableswitch default -> 40, 0 -> 99
    //   300: new com/fasterxml/Zoz/Zd
    //   303: dup
    //   304: invokespecial <init> : ()V
    //   307: putstatic com/fasterxml/Zor/Zy6.Zk : Lcom/fasterxml/Zor/Zt;
    //   310: new com/fasterxml/Zj/Ze
    //   313: dup
    //   314: aconst_null
    //   315: getstatic com/fasterxml/Zor/Zy6.Zk : Lcom/fasterxml/Zor/Zt;
    //   318: aconst_null
    //   319: invokestatic ZF : ()Lcom/fasterxml/Zh/Zi;
    //   322: aconst_null
    //   323: getstatic com/fasterxml/Zm/Ze3.ZW : Lcom/fasterxml/Zm/Ze3;
    //   326: aconst_null
    //   327: invokestatic getDefault : ()Ljava/util/Locale;
    //   330: aconst_null
    //   331: invokestatic Zx : ()Lcom/fasterxml/Zb/Zy;
    //   334: getstatic com/fasterxml/Zo3/Zz.ZJ : Lcom/fasterxml/Zo3/Zz;
    //   337: new com/fasterxml/Zoz/Zr
    //   340: dup
    //   341: invokespecial <init> : ()V
    //   344: invokestatic ZU : ()Lcom/fasterxml/Zj/Zo;
    //   347: invokespecial <init> : (Lcom/fasterxml/Zoz/Zg;Lcom/fasterxml/Zor/Zt;Lcom/fasterxml/Zor/Ze;Lcom/fasterxml/Zh/Zi;Lcom/fasterxml/Zp/Zk;Ljava/text/DateFormat;Lcom/fasterxml/Zj/Zqn;Ljava/util/Locale;Ljava/util/TimeZone;Lcom/fasterxml/Zb/Zy;Lcom/fasterxml/Zp/Zp;Lcom/fasterxml/Zoz/Zu;Lcom/fasterxml/Zj/Zo;)V
    //   350: putstatic com/fasterxml/Zor/Zy6.Zh : Lcom/fasterxml/Zj/Ze;
    //   353: return
  }
  
  private static Throwable a(Throwable paramThrowable) {
    return paramThrowable;
  }
  
  private static String a(int paramInt1, int paramInt2) {
    int i = (paramInt1 ^ 0x48DC) & 0xFFFF;
    if (b[i] == null) {
      char[] arrayOfChar = a[i].toCharArray();
      switch (arrayOfChar[0] & 0xFF) {
        case 0:
        
        case 1:
        
        case 2:
        
        case 3:
        
        case 4:
        
        case 5:
        
        case 6:
        
        case 7:
        
        case 8:
        
        case 9:
        
        case 10:
        
        case 11:
        
        case 12:
        
        case 13:
        
        case 14:
        
        case 15:
        
        case 16:
        
        case 17:
        
        case 18:
        
        case 19:
        
        case 20:
        
        case 21:
        
        case 22:
        
        case 23:
        
        case 24:
        
        case 25:
        
        case 26:
        
        case 27:
        
        case 28:
        
        case 29:
        
        case 30:
        
        case 31:
        
        case 32:
        
        case 33:
        
        case 34:
        
        case 35:
        
        case 36:
        
        case 37:
        
        case 38:
        
        case 39:
        
        case 40:
        
        case 41:
        
        case 42:
        
        case 43:
        
        case 44:
        
        case 45:
        
        case 46:
        
        case 47:
        
        case 48:
        
        case 49:
        
        case 50:
        
        case 51:
        
        case 52:
        
        case 53:
        
        case 54:
        
        case 55:
        
        case 56:
        
        case 57:
        
        case 58:
        
        case 59:
        
        case 60:
        
        case 61:
        
        case 62:
        
        case 63:
        
        case 64:
        
        case 65:
        
        case 66:
        
        case 67:
        
        case 68:
        
        case 69:
        
        case 70:
        
        case 71:
        
        case 72:
        
        case 73:
        
        case 74:
        
        case 75:
        
        case 76:
        
        case 77:
        
        case 78:
        
        case 79:
        
        case 80:
        
        case 81:
        
        case 82:
        
        case 83:
        
        case 84:
        
        case 85:
        
        case 86:
        
        case 87:
        
        case 88:
        
        case 89:
        
        case 90:
        
        case 91:
        
        case 92:
        
        case 93:
        
        case 94:
        
        case 95:
        
        case 96:
        
        case 97:
        
        case 98:
        
        case 99:
        
        case 100:
        
        case 101:
        
        case 102:
        
        case 103:
        
        case 104:
        
        case 105:
        
        case 106:
        
        case 107:
        
        case 108:
        
        case 109:
        
        case 110:
        
        case 111:
        
        case 112:
        
        case 113:
        
        case 114:
        
        case 115:
        
        case 116:
        
        case 117:
        
        case 118:
        
        case 119:
        
        case 120:
        
        case 121:
        
        case 122:
        
        case 123:
        
        case 124:
        
        case 125:
        
        case 126:
        
        case 127:
        
        case 128:
        
        case 129:
        
        case 130:
        
        case 131:
        
        case 132:
        
        case 133:
        
        case 134:
        
        case 135:
        
        case 136:
        
        case 137:
        
        case 138:
        
        case 139:
        
        case 140:
        
        case 141:
        
        case 142:
        
        case 143:
        
        case 144:
        
        case 145:
        
        case 146:
        
        case 147:
        
        case 148:
        
        case 149:
        
        case 150:
        
        case 151:
        
        case 152:
        
        case 153:
        
        case 154:
        
        case 155:
        
        case 156:
        
        case 157:
        
        case 158:
        
        case 159:
        
        case 160:
        
        case 161:
        
        case 162:
        
        case 163:
        
        case 164:
        
        case 165:
        
        case 166:
        
        case 167:
        
        case 168:
        
        case 169:
        
        case 170:
        
        case 171:
        
        case 172:
        
        case 173:
        
        case 174:
        
        case 175:
        
        case 176:
        
        case 177:
        
        case 178:
        
        case 179:
        
        case 180:
        
        case 181:
        
        case 182:
        
        case 183:
        
        case 184:
        
        case 185:
        
        case 186:
        
        case 187:
        
        case 188:
        
        case 189:
        
        case 190:
        
        case 191:
        
        case 192:
        
        case 193:
        
        case 194:
        
        case 195:
        
        case 196:
        
        case 197:
        
        case 198:
        
        case 199:
        
        case 200:
        
        case 201:
        
        case 202:
        
        case 203:
        
        case 204:
        
        case 205:
        
        case 206:
        
        case 207:
        
        case 208:
        
        case 209:
        
        case 210:
        
        case 211:
        
        case 212:
        
        case 213:
        
        case 214:
        
        case 215:
        
        case 216:
        
        case 217:
        
        case 218:
        
        case 219:
        
        case 220:
        
        case 221:
        
        case 222:
        
        case 223:
        
        case 224:
        
        case 225:
        
        case 226:
        
        case 227:
        
        case 228:
        
        case 229:
        
        case 230:
        
        case 231:
        
        case 232:
        
        case 233:
        
        case 234:
        
        case 235:
        
        case 236:
        
        case 237:
        
        case 238:
        
        case 239:
        
        case 240:
        
        case 241:
        
        case 242:
        
        case 243:
        
        case 244:
        
        case 245:
        
        case 246:
        
        case 247:
        
        case 248:
        
        case 249:
        
        case 250:
        
        case 251:
        
        case 252:
        
        case 253:
        
        case 254:
        
        default:
          break;
      } 
      byte b1 = 41;
      int j = (paramInt2 & 0xFF) - b1;
      if (j < 0)
        j += 256; 
      int k = ((paramInt2 & 0xFFFF) >>> 8) - b1;
      if (k < 0)
        k += 256; 
      for (byte b2 = 0; b2 < arrayOfChar.length; b2++) {
        int m = b2 % 2;
        if (m == 0) {
          arrayOfChar[b2] = (char)(arrayOfChar[b2] ^ j);
          j = ((j >>> 3 | j << 5) ^ arrayOfChar[b2]) & 0xFF;
        } else {
          arrayOfChar[b2] = (char)(arrayOfChar[b2] ^ k);
          k = ((k >>> 3 | k << 5) ^ arrayOfChar[b2]) & 0xFF;
        } 
      } 
      b[i] = (new String(arrayOfChar)).intern();
    } 
    return b[i];
  }
}


/* Location:              C:\Program Files\BurpSuitePro\burpsuite_pro.jar!\com\fasterxml\Zor\Zy6.class
 * Java compiler version: 8 (52.0)
 * JD-Core Version:       1.1.3
 */