package org.openapi4j;

import java.util.regex.Pattern;

class Zp5 {
  static final Pattern Za;
  
  static final Pattern Zp;
  
  static final Pattern ZS;
  
  static final Pattern Zr;
  
  static final Pattern Zz;
  
  static final Pattern ZR;
  
  static final Pattern ZE;
  
  static final Pattern ZI;
  
  static final Pattern ZU;
  
  static {
    // Byte code:
    //   0: bipush #9
    //   2: anewarray java/lang/String
    //   5: astore_0
    //   6: iconst_0
    //   7: istore #4
    //   9: ldc 'l+axO\\n#6 -Fl+axO\\bbK~)+s%VC@Z{8?{(F[{.(~,\Xh!1a9WGv)1a [T\\b(~9W^n))n SG\\b(~9W^n))n4_Rj/x5YC\\b%m5?yl{a7S}`7ucM}gG{8%n!ORh51z5[S>1q?U\s)%m5?yaV76\\f?\\n\\n#b?\\rO7bf'
    //   11: dup
    //   12: astore_3
    //   13: invokevirtual length : ()I
    //   16: istore #5
    //   18: bipush #29
    //   20: istore_2
    //   21: iconst_m1
    //   22: istore_1
    //   23: bipush #63
    //   25: iinc #1, 1
    //   28: aload_3
    //   29: iload_1
    //   30: dup
    //   31: iload_2
    //   32: iadd
    //   33: invokevirtual substring : (II)Ljava/lang/String;
    //   36: iconst_m1
    //   37: goto -> 129
    //   40: aload_0
    //   41: swap
    //   42: iload #4
    //   44: iinc #4, 1
    //   47: swap
    //   48: aastore
    //   49: iload_1
    //   50: iload_2
    //   51: iadd
    //   52: dup
    //   53: istore_1
    //   54: iload #5
    //   56: if_icmpge -> 68
    //   59: aload_3
    //   60: iload_1
    //   61: invokevirtual charAt : (I)C
    //   64: istore_2
    //   65: goto -> 23
    //   68: ldc '){,Mb%,8SVw>#{1COk4$j1HZs8?a>[Bb04s=F^d9,{?FIb'
    //   70: dup
    //   71: astore_3
    //   72: invokevirtual length : ()I
    //   75: istore #5
    //   77: iconst_3
    //   78: istore_2
    //   79: iconst_m1
    //   80: istore_1
    //   81: bipush #34
    //   83: iinc #1, 1
    //   86: aload_3
    //   87: iload_1
    //   88: dup
    //   89: iload_2
    //   90: iadd
    //   91: invokevirtual substring : (II)Ljava/lang/String;
    //   94: iconst_0
    //   95: goto -> 129
    //   98: aload_0
    //   99: swap
    //   100: iload #4
    //   102: iinc #4, 1
    //   105: swap
    //   106: aastore
    //   107: iload_1
    //   108: iload_2
    //   109: iadd
    //   110: dup
    //   111: istore_1
    //   112: iload #5
    //   114: if_icmpge -> 126
    //   117: aload_3
    //   118: iload_1
    //   119: invokevirtual charAt : (I)C
    //   122: istore_2
    //   123: goto -> 81
    //   126: goto -> 288
    //   129: dup_x2
    //   130: pop
    //   131: invokevirtual toCharArray : ()[C
    //   134: dup_x1
    //   135: arraylength
    //   136: dup_x2
    //   137: pop
    //   138: iconst_0
    //   139: istore #6
    //   141: dup2_x1
    //   142: pop2
    //   143: dup_x2
    //   144: iconst_1
    //   145: if_icmpgt -> 247
    //   148: dup2
    //   149: swap
    //   150: iload #6
    //   152: dup2_x1
    //   153: caload
    //   154: swap
    //   155: iload #6
    //   157: bipush #7
    //   159: irem
    //   160: tableswitch default -> 230, 0 -> 200, 1 -> 205, 2 -> 210, 3 -> 215, 4 -> 220, 5 -> 225
    //   200: bipush #8
    //   202: goto -> 231
    //   205: bipush #37
    //   207: goto -> 231
    //   210: bipush #115
    //   212: goto -> 231
    //   215: bipush #114
    //   217: goto -> 231
    //   220: bipush #45
    //   222: goto -> 231
    //   225: bipush #111
    //   227: goto -> 231
    //   230: iconst_5
    //   231: ixor
    //   232: ixor
    //   233: i2c
    //   234: castore
    //   235: iinc #6, 1
    //   238: dup
    //   239: ifne -> 247
    //   242: dup2
    //   243: dup_x1
    //   244: goto -> 152
    //   247: dup2_x1
    //   248: pop2
    //   249: dup_x2
    //   250: iload #6
    //   252: if_icmpgt -> 148
    //   255: pop
    //   256: new java/lang/String
    //   259: dup_x1
    //   260: swap
    //   261: invokespecial <init> : ([C)V
    //   264: invokevirtual intern : ()Ljava/lang/String;
    //   267: swap
    //   268: pop
    //   269: swap
    //   270: tableswitch default -> 40, 0 -> 98
    //   288: aload_0
    //   289: bipush #7
    //   291: aaload
    //   292: invokestatic compile : (Ljava/lang/String;)Ljava/util/regex/Pattern;
    //   295: putstatic org/openapi4j/Zp5.Za : Ljava/util/regex/Pattern;
    //   298: aload_0
    //   299: bipush #6
    //   301: aaload
    //   302: invokestatic compile : (Ljava/lang/String;)Ljava/util/regex/Pattern;
    //   305: putstatic org/openapi4j/Zp5.Zp : Ljava/util/regex/Pattern;
    //   308: aload_0
    //   309: iconst_2
    //   310: aaload
    //   311: invokestatic compile : (Ljava/lang/String;)Ljava/util/regex/Pattern;
    //   314: putstatic org/openapi4j/Zp5.ZS : Ljava/util/regex/Pattern;
    //   317: aload_0
    //   318: iconst_3
    //   319: aaload
    //   320: invokestatic compile : (Ljava/lang/String;)Ljava/util/regex/Pattern;
    //   323: putstatic org/openapi4j/Zp5.Zr : Ljava/util/regex/Pattern;
    //   326: aload_0
    //   327: iconst_5
    //   328: aaload
    //   329: invokestatic compile : (Ljava/lang/String;)Ljava/util/regex/Pattern;
    //   332: putstatic org/openapi4j/Zp5.Zz : Ljava/util/regex/Pattern;
    //   335: aload_0
    //   336: bipush #8
    //   338: aaload
    //   339: invokestatic compile : (Ljava/lang/String;)Ljava/util/regex/Pattern;
    //   342: putstatic org/openapi4j/Zp5.ZR : Ljava/util/regex/Pattern;
    //   345: aload_0
    //   346: iconst_4
    //   347: aaload
    //   348: invokestatic compile : (Ljava/lang/String;)Ljava/util/regex/Pattern;
    //   351: putstatic org/openapi4j/Zp5.ZE : Ljava/util/regex/Pattern;
    //   354: aload_0
    //   355: iconst_1
    //   356: aaload
    //   357: invokestatic compile : (Ljava/lang/String;)Ljava/util/regex/Pattern;
    //   360: putstatic org/openapi4j/Zp5.ZI : Ljava/util/regex/Pattern;
    //   363: aload_0
    //   364: iconst_0
    //   365: aaload
    //   366: invokestatic compile : (Ljava/lang/String;)Ljava/util/regex/Pattern;
    //   369: putstatic org/openapi4j/Zp5.ZU : Ljava/util/regex/Pattern;
    //   372: return
  }
}


/* Location:              C:\Program Files\BurpSuitePro\burpsuite_pro.jar!\org\openapi4j\Zp5.class
 * Java compiler version: 21 (65.0)
 * JD-Core Version:       1.1.3
 */