package com.fasterxml.Zx;

import burp.Zbqc;
import burp.Zv8r;
import com.fasterxml.Zb.Z_;
import com.fasterxml.Zb.Ze;
import com.fasterxml.Zb.Zg;
import com.fasterxml.Zb.Zk;
import com.fasterxml.Zb.Zl;
import com.fasterxml.Zb.Zm;
import com.fasterxml.Zb.Zm0;
import com.fasterxml.Zb.Zm5;
import com.fasterxml.Zb.Zmk;
import com.fasterxml.Zb.Zmt;
import com.fasterxml.Zb.Zmv;
import com.fasterxml.Zb.Zq;
import com.fasterxml.Zb.Zy;
import com.fasterxml.Zc.Zf;
import com.fasterxml.Zc.Zg;
import com.fasterxml.Zc.Zz;
import com.fasterxml.Zi.Z_;
import com.fasterxml.Zq.Zb;
import com.fasterxml.Zq.Zn;
import com.fasterxml.Zq.Zs;
import com.fasterxml.Zq6;
import com.fasterxml.Zv9;
import com.fasterxml.Zyt;
import java.io.IOException;
import java.math.BigDecimal;
import java.math.BigInteger;
import java.util.Arrays;

public abstract class Zo extends Zm {
  protected static final Zz<Zq> ZF;
  
  protected final Zv9 Zf;
  
  protected final Z_ Zb;
  
  protected boolean Zj;
  
  protected int Zh;
  
  protected int Zy;
  
  protected long ZE;
  
  protected int ZC = 1;
  
  protected int ZD;
  
  protected long Zz;
  
  protected int Zm;
  
  protected int Zq;
  
  protected Zn Zx;
  
  protected Zl ZN;
  
  protected final Zg ZP;
  
  protected char[] ZJ;
  
  protected boolean ZT;
  
  protected Zf ZR;
  
  protected byte[] Zd;
  
  protected int ZI;
  
  protected int ZA;
  
  protected long ZL;
  
  protected float Zg;
  
  protected double ZW;
  
  protected BigInteger ZY;
  
  protected BigDecimal ZU;
  
  protected String Zi;
  
  protected boolean Zw;
  
  protected boolean ZX;
  
  protected int Zl;
  
  protected int Zn;
  
  protected int ZM;
  
  private static final String[] e;
  
  private static final String[] f;
  
  protected Zo(Zv9 paramZv9, int paramInt) {
    super(paramInt);
    int[] arrayOfInt = Zv8r.Zn();
    this.Zm = 1;
    this.ZI = 0;
    this.Zf = paramZv9;
    Z_ z_ = paramZv9.ZM();
    try {
    
    } catch (IllegalStateException illegalStateException) {
      throw c(null);
    } 
    try {
      this.Zb = (z_ == null) ? Z_.Zo() : z_;
      this.ZP = paramZv9.Zq();
    } catch (IllegalStateException illegalStateException) {
      throw c(null);
    } 
    Zs zs = Zm.STRICT_DUPLICATE_DETECTION.Zi(paramInt) ? Zs.Zd(this) : null;
    try {
      this.Zx = Zn.ZK(zs);
      if (arrayOfInt != null)
        Zbqc.Zr(new Zbqc[3]); 
    } catch (IllegalStateException illegalStateException) {
      throw c(null);
    } 
  }
  
  public Zmk version() {
    return Zb.Zk;
  }
  
  public void ZZ(Object paramObject) {
    this.Zx.Z_(paramObject);
  }
  
  @Deprecated
  public Zg ZC(int paramInt) {
    int i = this.Zo ^ paramInt;
    try {
      if (i != 0) {
        this.Zo = paramInt;
        Zd(paramInt, i);
      } 
    } catch (IllegalStateException illegalStateException) {
      throw c(null);
    } 
    return this;
  }
  
  public Zg ZG(int paramInt1, int paramInt2) {
    int i = this.Zo;
    int j = i & (paramInt2 ^ 0xFFFFFFFF) | paramInt1 & paramInt2;
    int k = i ^ j;
    try {
      if (k != 0) {
        this.Zo = j;
        Zd(j, k);
      } 
    } catch (IllegalStateException illegalStateException) {
      throw c(null);
    } 
    return this;
  }
  
  protected void Zd(int paramInt1, int paramInt2) {
    int i = Zm.STRICT_DUPLICATE_DETECTION.Zi();
    int[] arrayOfInt = Zv8r.Zn();
    try {
      if ((paramInt2 & i) != 0) {
        try {
          if ((paramInt1 & i) != 0) {
            try {
              if (this.Zx.Zt() == null) {
                try {
                  this.Zx = this.Zx.Zc(Zs.Zd(this));
                  if (arrayOfInt != null) {
                    this.Zx = this.Zx.Zc(null);
                    return;
                  } 
                } catch (IllegalStateException illegalStateException) {
                  throw c(null);
                } 
                return;
              } 
            } catch (IllegalStateException illegalStateException) {
              throw c(null);
            } 
          } else {
            return;
          } 
        } catch (IllegalStateException illegalStateException) {
          throw c(null);
        } 
      } else {
        return;
      } 
    } catch (IllegalStateException illegalStateException) {
      throw c(null);
    } 
    this.Zx = this.Zx.Zc(null);
  }
  
  @Deprecated
  public String ZD() throws IOException {
    try {
      if (this.Z_ == Zl.START_OBJECT || this.Z_ == Zl.START_ARRAY) {
        Zn zn = this.Zx.ZH();
        try {
          if (zn != null)
            return zn.Z_(); 
        } catch (IOException iOException) {
          throw c(null);
        } 
      } 
    } catch (IOException iOException) {
      throw c(null);
    } 
    return this.Zx.Z_();
  }
  
  public void close() throws IOException {
    if (!this.Zj) {
      this.Zh = Math.max(this.Zh, this.Zy);
      this.Zj = true;
      try {
        Zvs();
      } finally {
        Zvj();
        this.Zf.close();
      } 
    } 
  }
  
  public Zn ZvV() {
    return this.Zx;
  }
  
  @Deprecated
  public Zm5 ZK() {
    return new Zm5(ZvT(), -1L, Zvo(), Zvu(), ZvP());
  }
  
  @Deprecated
  public Zm5 Zl() {
    int i = this.Zh - this.ZD + 1;
    return new Zm5(ZvT(), -1L, this.ZE + this.Zh, this.ZC, i);
  }
  
  public boolean Zi() {
    try {
      if (this.Z_ == Zl.VALUE_STRING)
        return true; 
    } catch (IllegalStateException illegalStateException) {
      throw c(null);
    } 
    try {
      if (this.Z_ == Zl.FIELD_NAME)
        return this.ZT; 
    } catch (IllegalStateException illegalStateException) {
      throw c(null);
    } 
    return false;
  }
  
  public byte[] Zi(Zy paramZy) throws IOException {
    try {
      if (this.Zd == null) {
        try {
          if (this.Z_ != Zl.VALUE_STRING)
            Zk(c(5872, 14410) + this.Z_ + c(5866, 32503)); 
        } catch (IOException iOException) {
          throw c(null);
        } 
        Zf zf = ZvE();
        ZC(ZR(), zf, paramZy);
        this.Zd = zf.ZA();
      } 
    } catch (IOException iOException) {
      throw c(null);
    } 
    return this.Zd;
  }
  
  public long Zvo() {
    return this.Zz;
  }
  
  public int Zvu() {
    return this.Zm;
  }
  
  public int ZvP() {
    int i = this.Zq;
    try {
    
    } catch (IllegalStateException illegalStateException) {
      throw c(null);
    } 
    return (i < 0) ? i : (i + 1);
  }
  
  protected abstract void Zvs() throws IOException;
  
  protected void Zvj() throws IOException {
    this.ZP.Zw();
    char[] arrayOfChar = this.ZJ;
    try {
      if (arrayOfChar != null) {
        this.ZJ = null;
        this.Zf.ZO(arrayOfChar);
      } 
    } catch (IOException iOException) {
      throw c(null);
    } 
  }
  
  protected void Z_k() throws Zm0 {
    try {
      if (!this.Zx.Zk()) {
        try {
        
        } catch (Zm0 zm0) {
          throw c(null);
        } 
        String str = this.Zx.Zo() ? c(5877, -22043) : c(5873, 29628);
        Zm(String.format(c(5861, -24104), new Object[] { str, this.Zx.Zj(ZvT()) }), (Zl)null);
      } 
    } catch (Zm0 zm0) {
      throw c(null);
    } 
  }
  
  protected final int Zvz() throws Zm0 {
    Z_k();
    return -1;
  }
  
  public Zf ZvE() {
    int[] arrayOfInt = Zv8r.Zn();
    try {
      if (this.ZR == null) {
        try {
          this.ZR = new Zf();
          if (arrayOfInt != null) {
            this.ZR.Zt();
            return this.ZR;
          } 
        } catch (IllegalStateException illegalStateException) {
          throw c(null);
        } 
        return this.ZR;
      } 
    } catch (IllegalStateException illegalStateException) {
      throw c(null);
    } 
    this.ZR.Zt();
    return this.ZR;
  }
  
  protected final Zl ZS(boolean paramBoolean, int paramInt) throws IOException {
    this.Zb.ZZ(paramInt);
    this.ZX = paramBoolean;
    this.Zw = false;
    this.Zl = paramInt;
    this.Zn = 0;
    this.ZM = 0;
    this.ZI = 0;
    return Zl.VALUE_NUMBER_INT;
  }
  
  protected final Zl ZC(boolean paramBoolean, int paramInt1, int paramInt2, int paramInt3) throws IOException {
    this.Zb.Z_(paramInt1 + paramInt2 + paramInt3);
    this.ZX = paramBoolean;
    this.Zw = false;
    this.Zl = paramInt1;
    this.Zn = paramInt2;
    this.ZM = paramInt3;
    this.ZI = 0;
    return Zl.VALUE_NUMBER_FLOAT;
  }
  
  protected final Zl ZT(String paramString, double paramDouble) throws IOException {
    this.ZP.ZK(paramString);
    this.ZW = paramDouble;
    this.ZI = 8;
    this.Zw = true;
    return Zl.VALUE_NUMBER_FLOAT;
  }
  
  public boolean Zr() throws IOException {
    try {
      if (this.Z_ == Zl.VALUE_NUMBER_FLOAT)
        try {
          if (this.Zw);
        } catch (IOException iOException) {
          throw c(null);
        }  
    } catch (IOException iOException) {
      throw c(null);
    } 
    return false;
  }
  
  public Number Zb() throws IOException {
    try {
      if (this.ZI == 0)
        Zm(0); 
    } catch (IOException iOException) {
      throw c(null);
    } 
    try {
      if (this.Z_ == Zl.VALUE_NUMBER_INT) {
        try {
          if ((this.ZI & 0x1) != 0)
            return Integer.valueOf(this.ZA); 
        } catch (IOException iOException) {
          throw c(null);
        } 
        try {
          if ((this.ZI & 0x2) != 0)
            return Long.valueOf(this.ZL); 
        } catch (IOException iOException) {
          throw c(null);
        } 
        try {
          if ((this.ZI & 0x4) != 0)
            return Zv9(); 
        } catch (IOException iOException) {
          throw c(null);
        } 
        Z_A();
      } 
    } catch (IOException iOException) {
      throw c(null);
    } 
    try {
      if ((this.ZI & 0x10) != 0)
        return ZvW(); 
    } catch (IOException iOException) {
      throw c(null);
    } 
    try {
      if ((this.ZI & 0x20) != 0)
        return Float.valueOf(Zvn()); 
    } catch (IOException iOException) {
      throw c(null);
    } 
    try {
      if ((this.ZI & 0x8) == 0)
        Z_A(); 
    } catch (IOException iOException) {
      throw c(null);
    } 
    return Double.valueOf(Zva());
  }
  
  public Object ZI() throws IOException {
    try {
      if (this.Z_ == Zl.VALUE_NUMBER_INT) {
        try {
          if (this.ZI == 0)
            Zm(0); 
        } catch (IOException iOException) {
          throw c(null);
        } 
        try {
          if ((this.ZI & 0x1) != 0)
            return Integer.valueOf(this.ZA); 
        } catch (IOException iOException) {
          throw c(null);
        } 
        try {
          if ((this.ZI & 0x2) != 0)
            return Long.valueOf(this.ZL); 
        } catch (IOException iOException) {
          throw c(null);
        } 
        try {
          if ((this.ZI & 0x4) != 0) {
            try {
              if (this.ZY != null)
                return this.ZY; 
            } catch (IOException iOException) {
              throw c(null);
            } 
            try {
              if (this.Zi != null)
                return this.Zi; 
            } catch (IOException iOException) {
              throw c(null);
            } 
            return Zv9();
          } 
        } catch (IOException iOException) {
          throw c(null);
        } 
        Z_A();
      } 
    } catch (IOException iOException) {
      throw c(null);
    } 
    try {
      if (this.Z_ == Zl.VALUE_NUMBER_FLOAT) {
        try {
          if ((this.ZI & 0x10) != 0)
            return ZvW(); 
        } catch (IOException iOException) {
          throw c(null);
        } 
        try {
          if ((this.ZI & 0x8) != 0)
            return Double.valueOf(Zva()); 
        } catch (IOException iOException) {
          throw c(null);
        } 
        try {
          if ((this.ZI & 0x20) != 0)
            return Float.valueOf(Zvn()); 
        } catch (IOException iOException) {
          throw c(null);
        } 
        return this.ZP.ZK();
      } 
    } catch (IOException iOException) {
      throw c(null);
    } 
    return Zb();
  }
  
  public Zk ZL() throws IOException {
    try {
      if (this.ZI == 0)
        Zm(0); 
    } catch (IOException iOException) {
      throw c(null);
    } 
    try {
      if (this.Z_ == Zl.VALUE_NUMBER_INT) {
        try {
          if ((this.ZI & 0x1) != 0)
            return Zk.INT; 
        } catch (IOException iOException) {
          throw c(null);
        } 
        try {
          if ((this.ZI & 0x2) != 0)
            return Zk.LONG; 
        } catch (IOException iOException) {
          throw c(null);
        } 
        return Zk.BIG_INTEGER;
      } 
    } catch (IOException iOException) {
      throw c(null);
    } 
    try {
      if ((this.ZI & 0x10) != 0)
        return Zk.BIG_DECIMAL; 
    } catch (IOException iOException) {
      throw c(null);
    } 
    try {
      if ((this.ZI & 0x20) != 0)
        return Zk.FLOAT; 
    } catch (IOException iOException) {
      throw c(null);
    } 
    return Zk.DOUBLE;
  }
  
  public int Ze() throws IOException {
    try {
      if ((this.ZI & 0x1) == 0) {
        try {
          if (this.ZI == 0)
            return Zvt(); 
        } catch (IOException iOException) {
          throw c(null);
        } 
        try {
          if ((this.ZI & 0x1) == 0)
            ZvL(); 
        } catch (IOException iOException) {
          throw c(null);
        } 
      } 
    } catch (IOException iOException) {
      throw c(null);
    } 
    return this.ZA;
  }
  
  public long ZE() throws IOException {
    try {
      if ((this.ZI & 0x2) == 0) {
        try {
          if (this.ZI == 0)
            Zm(2); 
        } catch (IOException iOException) {
          throw c(null);
        } 
        try {
          if ((this.ZI & 0x2) == 0)
            Zv4(); 
        } catch (IOException iOException) {
          throw c(null);
        } 
      } 
    } catch (IOException iOException) {
      throw c(null);
    } 
    return this.ZL;
  }
  
  public BigInteger ZX() throws IOException {
    try {
      if ((this.ZI & 0x4) == 0) {
        try {
          if (this.ZI == 0)
            Zm(4); 
        } catch (IOException iOException) {
          throw c(null);
        } 
        try {
          if ((this.ZI & 0x4) == 0)
            ZvF(); 
        } catch (IOException iOException) {
          throw c(null);
        } 
      } 
    } catch (IOException iOException) {
      throw c(null);
    } 
    return Zv9();
  }
  
  public float Zg() throws IOException {
    try {
      if ((this.ZI & 0x20) == 0) {
        try {
          if (this.ZI == 0)
            Zm(32); 
        } catch (IOException iOException) {
          throw c(null);
        } 
        try {
          if ((this.ZI & 0x20) == 0)
            Zv_(); 
        } catch (IOException iOException) {
          throw c(null);
        } 
      } 
    } catch (IOException iOException) {
      throw c(null);
    } 
    return Zvn();
  }
  
  public double ZH() throws IOException {
    try {
      if ((this.ZI & 0x8) == 0) {
        try {
          if (this.ZI == 0)
            Zm(8); 
        } catch (IOException iOException) {
          throw c(null);
        } 
        try {
          if ((this.ZI & 0x8) == 0)
            ZvG(); 
        } catch (IOException iOException) {
          throw c(null);
        } 
      } 
    } catch (IOException iOException) {
      throw c(null);
    } 
    return Zva();
  }
  
  public BigDecimal ZT() throws IOException {
    try {
      if ((this.ZI & 0x10) == 0) {
        try {
          if (this.ZI == 0)
            Zm(16); 
        } catch (IOException iOException) {
          throw c(null);
        } 
        try {
          if ((this.ZI & 0x10) == 0)
            ZvM(); 
        } catch (IOException iOException) {
          throw c(null);
        } 
      } 
    } catch (IOException iOException) {
      throw c(null);
    } 
    return ZvW();
  }
  
  public Z_ ZG() {
    return this.Zb;
  }
  
  protected void Zm(int paramInt) throws IOException {
    try {
      if (this.Zj)
        Zk(c(5870, -14078)); 
    } catch (IOException iOException) {
      throw c(null);
    } 
    if (this.Z_ == Zl.VALUE_NUMBER_INT) {
      int i = this.Zl;
      try {
        if (i <= 9) {
          this.ZA = this.ZP.ZP(this.ZX);
          this.ZI = 1;
          return;
        } 
      } catch (IOException iOException) {
        throw c(null);
      } 
      if (i <= 18) {
        long l = this.ZP.ZS(this.ZX);
        try {
          if (i == 10)
            try {
              if (this.ZX) {
                try {
                  if (l >= -2147483648L) {
                    this.ZA = (int)l;
                    this.ZI = 1;
                    return;
                  } 
                } catch (IOException iOException) {
                  throw c(null);
                } 
              } else {
                try {
                  if (l <= 2147483647L) {
                    this.ZA = (int)l;
                    this.ZI = 1;
                    return;
                  } 
                } catch (IOException iOException) {
                  throw c(null);
                } 
              } 
            } catch (IOException iOException) {
              throw c(null);
            }  
        } catch (IOException iOException) {
          throw c(null);
        } 
        this.ZL = l;
        this.ZI = 2;
        return;
      } 
      if (i == 19) {
        char[] arrayOfChar = this.ZP.Zo();
        int j = this.ZP.ZP();
        try {
          if (this.ZX)
            j++; 
        } catch (IOException iOException) {
          throw c(null);
        } 
        try {
          if (Zyt.ZP(arrayOfChar, j, i, this.ZX)) {
            this.ZL = Zyt.Zj(arrayOfChar, j, this.ZX);
            this.ZI = 2;
            return;
          } 
        } catch (IOException iOException) {
          throw c(null);
        } 
      } 
      Zp(paramInt);
      return;
    } 
    try {
      if (this.Z_ == Zl.VALUE_NUMBER_FLOAT) {
        ZZ(paramInt);
        return;
      } 
    } catch (IOException iOException) {
      throw c(null);
    } 
    ZK(c(5869, 11799), this.Z_);
  }
  
  protected int Zvt() throws IOException {
    try {
      if (this.Zj)
        Zk(c(5874, 29210)); 
    } catch (IOException iOException) {
      throw c(null);
    } 
    try {
      if (this.Z_ == Zl.VALUE_NUMBER_INT && this.Zl <= 9) {
        int i = this.ZP.ZP(this.ZX);
        this.ZA = i;
        this.ZI = 1;
        return i;
      } 
    } catch (IOException iOException) {
      throw c(null);
    } 
    try {
      Zm(1);
      if ((this.ZI & 0x1) == 0)
        ZvL(); 
    } catch (IOException iOException) {
      throw c(null);
    } 
    return this.ZA;
  }
  
  private void ZZ(int paramInt) throws IOException {
    // Byte code:
    //   0: invokestatic Zn : ()[I
    //   3: astore_2
    //   4: iload_1
    //   5: bipush #16
    //   7: if_icmpne -> 43
    //   10: aload_0
    //   11: aconst_null
    //   12: putfield ZU : Ljava/math/BigDecimal;
    //   15: aload_0
    //   16: aload_0
    //   17: getfield ZP : Lcom/fasterxml/Zc/Zg;
    //   20: invokevirtual ZK : ()Ljava/lang/String;
    //   23: putfield Zi : Ljava/lang/String;
    //   26: aload_0
    //   27: bipush #16
    //   29: putfield ZI : I
    //   32: aload_2
    //   33: ifnull -> 118
    //   36: goto -> 43
    //   39: invokestatic c : (Ljava/lang/Exception;)Ljava/lang/Exception;
    //   42: athrow
    //   43: iload_1
    //   44: bipush #32
    //   46: if_icmpne -> 89
    //   49: goto -> 56
    //   52: invokestatic c : (Ljava/lang/Exception;)Ljava/lang/Exception;
    //   55: athrow
    //   56: aload_0
    //   57: fconst_0
    //   58: putfield Zg : F
    //   61: aload_0
    //   62: aload_0
    //   63: getfield ZP : Lcom/fasterxml/Zc/Zg;
    //   66: invokevirtual ZK : ()Ljava/lang/String;
    //   69: putfield Zi : Ljava/lang/String;
    //   72: aload_0
    //   73: bipush #32
    //   75: putfield ZI : I
    //   78: aload_2
    //   79: ifnull -> 118
    //   82: goto -> 89
    //   85: invokestatic c : (Ljava/lang/Exception;)Ljava/lang/Exception;
    //   88: athrow
    //   89: aload_0
    //   90: dconst_0
    //   91: putfield ZW : D
    //   94: aload_0
    //   95: aload_0
    //   96: getfield ZP : Lcom/fasterxml/Zc/Zg;
    //   99: invokevirtual ZK : ()Ljava/lang/String;
    //   102: putfield Zi : Ljava/lang/String;
    //   105: aload_0
    //   106: bipush #8
    //   108: putfield ZI : I
    //   111: goto -> 118
    //   114: invokestatic c : (Ljava/lang/Exception;)Ljava/lang/Exception;
    //   117: athrow
    //   118: return
    // Exception table:
    //   from	to	target	type
    //   4	36	39	java/io/IOException
    //   10	49	52	java/io/IOException
    //   43	82	85	java/io/IOException
    //   56	111	114	java/io/IOException
  }
  
  private void Zp(int paramInt) throws IOException {
    // Byte code:
    //   0: invokestatic Zn : ()[I
    //   3: aload_0
    //   4: getfield ZP : Lcom/fasterxml/Zc/Zg;
    //   7: invokevirtual ZK : ()Ljava/lang/String;
    //   10: astore_3
    //   11: astore_2
    //   12: iload_1
    //   13: iconst_1
    //   14: if_icmpeq -> 29
    //   17: iload_1
    //   18: iconst_2
    //   19: if_icmpne -> 42
    //   22: goto -> 29
    //   25: invokestatic c : (Ljava/lang/Exception;)Ljava/lang/Exception;
    //   28: athrow
    //   29: aload_0
    //   30: iload_1
    //   31: aload_3
    //   32: invokevirtual ZM : (ILjava/lang/String;)V
    //   35: goto -> 42
    //   38: invokestatic c : (Ljava/lang/Exception;)Ljava/lang/Exception;
    //   41: athrow
    //   42: iload_1
    //   43: bipush #8
    //   45: if_icmpeq -> 61
    //   48: iload_1
    //   49: bipush #32
    //   51: if_icmpne -> 83
    //   54: goto -> 61
    //   57: invokestatic c : (Ljava/lang/Exception;)Ljava/lang/Exception;
    //   60: athrow
    //   61: aload_0
    //   62: aload_3
    //   63: putfield Zi : Ljava/lang/String;
    //   66: aload_0
    //   67: bipush #8
    //   69: putfield ZI : I
    //   72: aload_2
    //   73: ifnull -> 105
    //   76: goto -> 83
    //   79: invokestatic c : (Ljava/lang/Exception;)Ljava/lang/Exception;
    //   82: athrow
    //   83: aload_0
    //   84: aconst_null
    //   85: putfield ZY : Ljava/math/BigInteger;
    //   88: aload_0
    //   89: aload_3
    //   90: putfield Zi : Ljava/lang/String;
    //   93: aload_0
    //   94: iconst_4
    //   95: putfield ZI : I
    //   98: goto -> 105
    //   101: invokestatic c : (Ljava/lang/Exception;)Ljava/lang/Exception;
    //   104: athrow
    //   105: return
    // Exception table:
    //   from	to	target	type
    //   12	22	25	java/io/IOException
    //   17	35	38	java/io/IOException
    //   42	54	57	java/io/IOException
    //   48	76	79	java/io/IOException
    //   61	98	101	java/io/IOException
  }
  
  protected void ZM(int paramInt, String paramString) throws IOException {
    int[] arrayOfInt = Zv8r.Zn();
    try {
      if (paramInt == 1) {
        try {
          ZV(paramString);
          if (arrayOfInt != null) {
            ZR(paramString);
            return;
          } 
        } catch (IOException iOException) {
          throw c(null);
        } 
        return;
      } 
    } catch (IOException iOException) {
      throw c(null);
    } 
    ZR(paramString);
  }
  
  protected void ZvL() throws IOException {
    // Byte code:
    //   0: invokestatic Zn : ()[I
    //   3: astore_1
    //   4: aload_0
    //   5: getfield ZI : I
    //   8: iconst_2
    //   9: iand
    //   10: ifeq -> 57
    //   13: aload_0
    //   14: getfield ZL : J
    //   17: l2i
    //   18: istore_2
    //   19: iload_2
    //   20: i2l
    //   21: aload_0
    //   22: getfield ZL : J
    //   25: lcmp
    //   26: ifeq -> 48
    //   29: aload_0
    //   30: aload_0
    //   31: invokevirtual ZR : ()Ljava/lang/String;
    //   34: aload_0
    //   35: invokevirtual Zh : ()Lcom/fasterxml/Zb/Zl;
    //   38: invokevirtual ZM : (Ljava/lang/String;Lcom/fasterxml/Zb/Zl;)V
    //   41: goto -> 48
    //   44: invokestatic c : (Ljava/lang/Exception;)Ljava/lang/Exception;
    //   47: athrow
    //   48: aload_0
    //   49: iload_2
    //   50: putfield ZA : I
    //   53: aload_1
    //   54: ifnull -> 277
    //   57: aload_0
    //   58: getfield ZI : I
    //   61: iconst_4
    //   62: iand
    //   63: ifeq -> 128
    //   66: goto -> 73
    //   69: invokestatic c : (Ljava/lang/Exception;)Ljava/lang/Exception;
    //   72: athrow
    //   73: aload_0
    //   74: invokevirtual Zv9 : ()Ljava/math/BigInteger;
    //   77: astore_2
    //   78: getstatic com/fasterxml/Zx/Zo.Zk : Ljava/math/BigInteger;
    //   81: aload_2
    //   82: invokevirtual compareTo : (Ljava/math/BigInteger;)I
    //   85: ifgt -> 105
    //   88: getstatic com/fasterxml/Zx/Zo.Zs : Ljava/math/BigInteger;
    //   91: aload_2
    //   92: invokevirtual compareTo : (Ljava/math/BigInteger;)I
    //   95: ifge -> 116
    //   98: goto -> 105
    //   101: invokestatic c : (Ljava/lang/Exception;)Ljava/lang/Exception;
    //   104: athrow
    //   105: aload_0
    //   106: invokevirtual Z_5 : ()V
    //   109: goto -> 116
    //   112: invokestatic c : (Ljava/lang/Exception;)Ljava/lang/Exception;
    //   115: athrow
    //   116: aload_0
    //   117: aload_2
    //   118: invokevirtual intValue : ()I
    //   121: putfield ZA : I
    //   124: aload_1
    //   125: ifnull -> 277
    //   128: aload_0
    //   129: getfield ZI : I
    //   132: bipush #8
    //   134: iand
    //   135: ifeq -> 194
    //   138: goto -> 145
    //   141: invokestatic c : (Ljava/lang/Exception;)Ljava/lang/Exception;
    //   144: athrow
    //   145: aload_0
    //   146: invokevirtual Zva : ()D
    //   149: dstore_2
    //   150: dload_2
    //   151: ldc2_w -2.147483648E9
    //   154: dcmpg
    //   155: iflt -> 173
    //   158: dload_2
    //   159: ldc2_w 2.147483647E9
    //   162: dcmpl
    //   163: ifle -> 184
    //   166: goto -> 173
    //   169: invokestatic c : (Ljava/lang/Exception;)Ljava/lang/Exception;
    //   172: athrow
    //   173: aload_0
    //   174: invokevirtual Z_5 : ()V
    //   177: goto -> 184
    //   180: invokestatic c : (Ljava/lang/Exception;)Ljava/lang/Exception;
    //   183: athrow
    //   184: aload_0
    //   185: dload_2
    //   186: d2i
    //   187: putfield ZA : I
    //   190: aload_1
    //   191: ifnull -> 277
    //   194: aload_0
    //   195: getfield ZI : I
    //   198: bipush #16
    //   200: iand
    //   201: ifeq -> 266
    //   204: goto -> 211
    //   207: invokestatic c : (Ljava/lang/Exception;)Ljava/lang/Exception;
    //   210: athrow
    //   211: aload_0
    //   212: invokevirtual ZvW : ()Ljava/math/BigDecimal;
    //   215: astore_2
    //   216: getstatic com/fasterxml/Zx/Zo.ZV : Ljava/math/BigDecimal;
    //   219: aload_2
    //   220: invokevirtual compareTo : (Ljava/math/BigDecimal;)I
    //   223: ifgt -> 243
    //   226: getstatic com/fasterxml/Zx/Zo.Zu : Ljava/math/BigDecimal;
    //   229: aload_2
    //   230: invokevirtual compareTo : (Ljava/math/BigDecimal;)I
    //   233: ifge -> 254
    //   236: goto -> 243
    //   239: invokestatic c : (Ljava/lang/Exception;)Ljava/lang/Exception;
    //   242: athrow
    //   243: aload_0
    //   244: invokevirtual Z_5 : ()V
    //   247: goto -> 254
    //   250: invokestatic c : (Ljava/lang/Exception;)Ljava/lang/Exception;
    //   253: athrow
    //   254: aload_0
    //   255: aload_2
    //   256: invokevirtual intValue : ()I
    //   259: putfield ZA : I
    //   262: aload_1
    //   263: ifnull -> 277
    //   266: aload_0
    //   267: invokevirtual Z_A : ()V
    //   270: goto -> 277
    //   273: invokestatic c : (Ljava/lang/Exception;)Ljava/lang/Exception;
    //   276: athrow
    //   277: aload_0
    //   278: dup
    //   279: getfield ZI : I
    //   282: iconst_1
    //   283: ior
    //   284: putfield ZI : I
    //   287: return
    // Exception table:
    //   from	to	target	type
    //   19	41	44	java/io/IOException
    //   48	66	69	java/io/IOException
    //   78	98	101	java/io/IOException
    //   88	109	112	java/io/IOException
    //   116	138	141	java/io/IOException
    //   150	166	169	java/io/IOException
    //   158	177	180	java/io/IOException
    //   184	204	207	java/io/IOException
    //   216	236	239	java/io/IOException
    //   226	247	250	java/io/IOException
    //   254	270	273	java/io/IOException
  }
  
  protected void Zv4() throws IOException {
    // Byte code:
    //   0: invokestatic Zn : ()[I
    //   3: astore_1
    //   4: aload_0
    //   5: getfield ZI : I
    //   8: iconst_1
    //   9: iand
    //   10: ifeq -> 33
    //   13: aload_0
    //   14: aload_0
    //   15: getfield ZA : I
    //   18: i2l
    //   19: putfield ZL : J
    //   22: aload_1
    //   23: ifnull -> 253
    //   26: goto -> 33
    //   29: invokestatic c : (Ljava/lang/Exception;)Ljava/lang/Exception;
    //   32: athrow
    //   33: aload_0
    //   34: getfield ZI : I
    //   37: iconst_4
    //   38: iand
    //   39: ifeq -> 104
    //   42: goto -> 49
    //   45: invokestatic c : (Ljava/lang/Exception;)Ljava/lang/Exception;
    //   48: athrow
    //   49: aload_0
    //   50: invokevirtual Zv9 : ()Ljava/math/BigInteger;
    //   53: astore_2
    //   54: getstatic com/fasterxml/Zx/Zo.ZS : Ljava/math/BigInteger;
    //   57: aload_2
    //   58: invokevirtual compareTo : (Ljava/math/BigInteger;)I
    //   61: ifgt -> 81
    //   64: getstatic com/fasterxml/Zx/Zo.Zr : Ljava/math/BigInteger;
    //   67: aload_2
    //   68: invokevirtual compareTo : (Ljava/math/BigInteger;)I
    //   71: ifge -> 92
    //   74: goto -> 81
    //   77: invokestatic c : (Ljava/lang/Exception;)Ljava/lang/Exception;
    //   80: athrow
    //   81: aload_0
    //   82: invokevirtual Z_G : ()V
    //   85: goto -> 92
    //   88: invokestatic c : (Ljava/lang/Exception;)Ljava/lang/Exception;
    //   91: athrow
    //   92: aload_0
    //   93: aload_2
    //   94: invokevirtual longValue : ()J
    //   97: putfield ZL : J
    //   100: aload_1
    //   101: ifnull -> 253
    //   104: aload_0
    //   105: getfield ZI : I
    //   108: bipush #8
    //   110: iand
    //   111: ifeq -> 170
    //   114: goto -> 121
    //   117: invokestatic c : (Ljava/lang/Exception;)Ljava/lang/Exception;
    //   120: athrow
    //   121: aload_0
    //   122: invokevirtual Zva : ()D
    //   125: dstore_2
    //   126: dload_2
    //   127: ldc2_w -9.223372036854776E18
    //   130: dcmpg
    //   131: iflt -> 149
    //   134: dload_2
    //   135: ldc2_w 9.223372036854776E18
    //   138: dcmpl
    //   139: ifle -> 160
    //   142: goto -> 149
    //   145: invokestatic c : (Ljava/lang/Exception;)Ljava/lang/Exception;
    //   148: athrow
    //   149: aload_0
    //   150: invokevirtual Z_G : ()V
    //   153: goto -> 160
    //   156: invokestatic c : (Ljava/lang/Exception;)Ljava/lang/Exception;
    //   159: athrow
    //   160: aload_0
    //   161: dload_2
    //   162: d2l
    //   163: putfield ZL : J
    //   166: aload_1
    //   167: ifnull -> 253
    //   170: aload_0
    //   171: getfield ZI : I
    //   174: bipush #16
    //   176: iand
    //   177: ifeq -> 242
    //   180: goto -> 187
    //   183: invokestatic c : (Ljava/lang/Exception;)Ljava/lang/Exception;
    //   186: athrow
    //   187: aload_0
    //   188: invokevirtual ZvW : ()Ljava/math/BigDecimal;
    //   191: astore_2
    //   192: getstatic com/fasterxml/Zx/Zo.Zv : Ljava/math/BigDecimal;
    //   195: aload_2
    //   196: invokevirtual compareTo : (Ljava/math/BigDecimal;)I
    //   199: ifgt -> 219
    //   202: getstatic com/fasterxml/Zx/Zo.Zp : Ljava/math/BigDecimal;
    //   205: aload_2
    //   206: invokevirtual compareTo : (Ljava/math/BigDecimal;)I
    //   209: ifge -> 230
    //   212: goto -> 219
    //   215: invokestatic c : (Ljava/lang/Exception;)Ljava/lang/Exception;
    //   218: athrow
    //   219: aload_0
    //   220: invokevirtual Z_G : ()V
    //   223: goto -> 230
    //   226: invokestatic c : (Ljava/lang/Exception;)Ljava/lang/Exception;
    //   229: athrow
    //   230: aload_0
    //   231: aload_2
    //   232: invokevirtual longValue : ()J
    //   235: putfield ZL : J
    //   238: aload_1
    //   239: ifnull -> 253
    //   242: aload_0
    //   243: invokevirtual Z_A : ()V
    //   246: goto -> 253
    //   249: invokestatic c : (Ljava/lang/Exception;)Ljava/lang/Exception;
    //   252: athrow
    //   253: aload_0
    //   254: dup
    //   255: getfield ZI : I
    //   258: iconst_2
    //   259: ior
    //   260: putfield ZI : I
    //   263: return
    // Exception table:
    //   from	to	target	type
    //   4	26	29	java/io/IOException
    //   13	42	45	java/io/IOException
    //   54	74	77	java/io/IOException
    //   64	85	88	java/io/IOException
    //   92	114	117	java/io/IOException
    //   126	142	145	java/io/IOException
    //   134	153	156	java/io/IOException
    //   160	180	183	java/io/IOException
    //   192	212	215	java/io/IOException
    //   202	223	226	java/io/IOException
    //   230	246	249	java/io/IOException
  }
  
  protected void ZvF() throws IOException {
    // Byte code:
    //   0: invokestatic Zn : ()[I
    //   3: astore_1
    //   4: aload_0
    //   5: getfield ZI : I
    //   8: bipush #16
    //   10: iand
    //   11: ifeq -> 37
    //   14: aload_0
    //   15: aload_0
    //   16: aload_0
    //   17: invokevirtual ZvW : ()Ljava/math/BigDecimal;
    //   20: invokevirtual Zp : (Ljava/math/BigDecimal;)Ljava/math/BigInteger;
    //   23: putfield ZY : Ljava/math/BigInteger;
    //   26: aload_1
    //   27: ifnull -> 205
    //   30: goto -> 37
    //   33: invokestatic c : (Ljava/lang/Exception;)Ljava/lang/Exception;
    //   36: athrow
    //   37: aload_0
    //   38: getfield ZI : I
    //   41: iconst_2
    //   42: iand
    //   43: ifeq -> 75
    //   46: goto -> 53
    //   49: invokestatic c : (Ljava/lang/Exception;)Ljava/lang/Exception;
    //   52: athrow
    //   53: aload_0
    //   54: aload_0
    //   55: getfield ZL : J
    //   58: invokestatic valueOf : (J)Ljava/math/BigInteger;
    //   61: putfield ZY : Ljava/math/BigInteger;
    //   64: aload_1
    //   65: ifnull -> 205
    //   68: goto -> 75
    //   71: invokestatic c : (Ljava/lang/Exception;)Ljava/lang/Exception;
    //   74: athrow
    //   75: aload_0
    //   76: getfield ZI : I
    //   79: iconst_1
    //   80: iand
    //   81: ifeq -> 114
    //   84: goto -> 91
    //   87: invokestatic c : (Ljava/lang/Exception;)Ljava/lang/Exception;
    //   90: athrow
    //   91: aload_0
    //   92: aload_0
    //   93: getfield ZA : I
    //   96: i2l
    //   97: invokestatic valueOf : (J)Ljava/math/BigInteger;
    //   100: putfield ZY : Ljava/math/BigInteger;
    //   103: aload_1
    //   104: ifnull -> 205
    //   107: goto -> 114
    //   110: invokestatic c : (Ljava/lang/Exception;)Ljava/lang/Exception;
    //   113: athrow
    //   114: aload_0
    //   115: getfield ZI : I
    //   118: bipush #8
    //   120: iand
    //   121: ifeq -> 194
    //   124: goto -> 131
    //   127: invokestatic c : (Ljava/lang/Exception;)Ljava/lang/Exception;
    //   130: athrow
    //   131: aload_0
    //   132: getfield Zi : Ljava/lang/String;
    //   135: ifnull -> 168
    //   138: goto -> 145
    //   141: invokestatic c : (Ljava/lang/Exception;)Ljava/lang/Exception;
    //   144: athrow
    //   145: aload_0
    //   146: aload_0
    //   147: aload_0
    //   148: invokevirtual ZvW : ()Ljava/math/BigDecimal;
    //   151: invokevirtual Zp : (Ljava/math/BigDecimal;)Ljava/math/BigInteger;
    //   154: putfield ZY : Ljava/math/BigInteger;
    //   157: aload_1
    //   158: ifnull -> 205
    //   161: goto -> 168
    //   164: invokestatic c : (Ljava/lang/Exception;)Ljava/lang/Exception;
    //   167: athrow
    //   168: aload_0
    //   169: aload_0
    //   170: aload_0
    //   171: invokevirtual Zva : ()D
    //   174: invokestatic valueOf : (D)Ljava/math/BigDecimal;
    //   177: invokevirtual Zp : (Ljava/math/BigDecimal;)Ljava/math/BigInteger;
    //   180: putfield ZY : Ljava/math/BigInteger;
    //   183: aload_1
    //   184: ifnull -> 205
    //   187: goto -> 194
    //   190: invokestatic c : (Ljava/lang/Exception;)Ljava/lang/Exception;
    //   193: athrow
    //   194: aload_0
    //   195: invokevirtual Z_A : ()V
    //   198: goto -> 205
    //   201: invokestatic c : (Ljava/lang/Exception;)Ljava/lang/Exception;
    //   204: athrow
    //   205: aload_0
    //   206: dup
    //   207: getfield ZI : I
    //   210: iconst_4
    //   211: ior
    //   212: putfield ZI : I
    //   215: return
    // Exception table:
    //   from	to	target	type
    //   4	30	33	java/io/IOException
    //   14	46	49	java/io/IOException
    //   37	68	71	java/io/IOException
    //   53	84	87	java/io/IOException
    //   75	107	110	java/io/IOException
    //   91	124	127	java/io/IOException
    //   114	138	141	java/io/IOException
    //   131	161	164	java/io/IOException
    //   145	187	190	java/io/IOException
    //   168	198	201	java/io/IOException
  }
  
  protected void ZvG() throws IOException {
    // Byte code:
    //   0: invokestatic Zn : ()[I
    //   3: astore_1
    //   4: aload_0
    //   5: getfield ZI : I
    //   8: bipush #16
    //   10: iand
    //   11: ifeq -> 69
    //   14: aload_0
    //   15: getfield Zi : Ljava/lang/String;
    //   18: ifnull -> 47
    //   21: goto -> 28
    //   24: invokestatic c : (Ljava/lang/Exception;)Ljava/lang/Exception;
    //   27: athrow
    //   28: aload_0
    //   29: aload_0
    //   30: invokevirtual Zva : ()D
    //   33: putfield ZW : D
    //   36: aload_1
    //   37: ifnull -> 293
    //   40: goto -> 47
    //   43: invokestatic c : (Ljava/lang/Exception;)Ljava/lang/Exception;
    //   46: athrow
    //   47: aload_0
    //   48: aload_0
    //   49: invokevirtual ZvW : ()Ljava/math/BigDecimal;
    //   52: invokevirtual doubleValue : ()D
    //   55: putfield ZW : D
    //   58: aload_1
    //   59: ifnull -> 293
    //   62: goto -> 69
    //   65: invokestatic c : (Ljava/lang/Exception;)Ljava/lang/Exception;
    //   68: athrow
    //   69: aload_0
    //   70: getfield ZI : I
    //   73: iconst_4
    //   74: iand
    //   75: ifeq -> 140
    //   78: goto -> 85
    //   81: invokestatic c : (Ljava/lang/Exception;)Ljava/lang/Exception;
    //   84: athrow
    //   85: aload_0
    //   86: getfield Zi : Ljava/lang/String;
    //   89: ifnull -> 118
    //   92: goto -> 99
    //   95: invokestatic c : (Ljava/lang/Exception;)Ljava/lang/Exception;
    //   98: athrow
    //   99: aload_0
    //   100: aload_0
    //   101: invokevirtual Zva : ()D
    //   104: putfield ZW : D
    //   107: aload_1
    //   108: ifnull -> 293
    //   111: goto -> 118
    //   114: invokestatic c : (Ljava/lang/Exception;)Ljava/lang/Exception;
    //   117: athrow
    //   118: aload_0
    //   119: aload_0
    //   120: invokevirtual Zv9 : ()Ljava/math/BigInteger;
    //   123: invokevirtual doubleValue : ()D
    //   126: putfield ZW : D
    //   129: aload_1
    //   130: ifnull -> 293
    //   133: goto -> 140
    //   136: invokestatic c : (Ljava/lang/Exception;)Ljava/lang/Exception;
    //   139: athrow
    //   140: aload_0
    //   141: getfield ZI : I
    //   144: iconst_2
    //   145: iand
    //   146: ifeq -> 176
    //   149: goto -> 156
    //   152: invokestatic c : (Ljava/lang/Exception;)Ljava/lang/Exception;
    //   155: athrow
    //   156: aload_0
    //   157: aload_0
    //   158: getfield ZL : J
    //   161: l2d
    //   162: putfield ZW : D
    //   165: aload_1
    //   166: ifnull -> 293
    //   169: goto -> 176
    //   172: invokestatic c : (Ljava/lang/Exception;)Ljava/lang/Exception;
    //   175: athrow
    //   176: aload_0
    //   177: getfield ZI : I
    //   180: iconst_1
    //   181: iand
    //   182: ifeq -> 212
    //   185: goto -> 192
    //   188: invokestatic c : (Ljava/lang/Exception;)Ljava/lang/Exception;
    //   191: athrow
    //   192: aload_0
    //   193: aload_0
    //   194: getfield ZA : I
    //   197: i2d
    //   198: putfield ZW : D
    //   201: aload_1
    //   202: ifnull -> 293
    //   205: goto -> 212
    //   208: invokestatic c : (Ljava/lang/Exception;)Ljava/lang/Exception;
    //   211: athrow
    //   212: aload_0
    //   213: getfield ZI : I
    //   216: bipush #32
    //   218: iand
    //   219: ifeq -> 282
    //   222: goto -> 229
    //   225: invokestatic c : (Ljava/lang/Exception;)Ljava/lang/Exception;
    //   228: athrow
    //   229: aload_0
    //   230: getfield Zi : Ljava/lang/String;
    //   233: ifnull -> 262
    //   236: goto -> 243
    //   239: invokestatic c : (Ljava/lang/Exception;)Ljava/lang/Exception;
    //   242: athrow
    //   243: aload_0
    //   244: aload_0
    //   245: invokevirtual Zva : ()D
    //   248: putfield ZW : D
    //   251: aload_1
    //   252: ifnull -> 293
    //   255: goto -> 262
    //   258: invokestatic c : (Ljava/lang/Exception;)Ljava/lang/Exception;
    //   261: athrow
    //   262: aload_0
    //   263: aload_0
    //   264: invokevirtual Zvn : ()F
    //   267: f2d
    //   268: putfield ZW : D
    //   271: aload_1
    //   272: ifnull -> 293
    //   275: goto -> 282
    //   278: invokestatic c : (Ljava/lang/Exception;)Ljava/lang/Exception;
    //   281: athrow
    //   282: aload_0
    //   283: invokevirtual Z_A : ()V
    //   286: goto -> 293
    //   289: invokestatic c : (Ljava/lang/Exception;)Ljava/lang/Exception;
    //   292: athrow
    //   293: aload_0
    //   294: dup
    //   295: getfield ZI : I
    //   298: bipush #8
    //   300: ior
    //   301: putfield ZI : I
    //   304: return
    // Exception table:
    //   from	to	target	type
    //   4	21	24	java/io/IOException
    //   14	40	43	java/io/IOException
    //   28	62	65	java/io/IOException
    //   47	78	81	java/io/IOException
    //   69	92	95	java/io/IOException
    //   85	111	114	java/io/IOException
    //   99	133	136	java/io/IOException
    //   118	149	152	java/io/IOException
    //   140	169	172	java/io/IOException
    //   156	185	188	java/io/IOException
    //   176	205	208	java/io/IOException
    //   192	222	225	java/io/IOException
    //   212	236	239	java/io/IOException
    //   229	255	258	java/io/IOException
    //   243	275	278	java/io/IOException
    //   262	286	289	java/io/IOException
  }
  
  protected void Zv_() throws IOException {
    // Byte code:
    //   0: invokestatic Zn : ()[I
    //   3: astore_1
    //   4: aload_0
    //   5: getfield ZI : I
    //   8: bipush #16
    //   10: iand
    //   11: ifeq -> 69
    //   14: aload_0
    //   15: getfield Zi : Ljava/lang/String;
    //   18: ifnull -> 47
    //   21: goto -> 28
    //   24: invokestatic c : (Ljava/lang/Exception;)Ljava/lang/Exception;
    //   27: athrow
    //   28: aload_0
    //   29: aload_0
    //   30: invokevirtual Zvn : ()F
    //   33: putfield Zg : F
    //   36: aload_1
    //   37: ifnull -> 293
    //   40: goto -> 47
    //   43: invokestatic c : (Ljava/lang/Exception;)Ljava/lang/Exception;
    //   46: athrow
    //   47: aload_0
    //   48: aload_0
    //   49: invokevirtual ZvW : ()Ljava/math/BigDecimal;
    //   52: invokevirtual floatValue : ()F
    //   55: putfield Zg : F
    //   58: aload_1
    //   59: ifnull -> 293
    //   62: goto -> 69
    //   65: invokestatic c : (Ljava/lang/Exception;)Ljava/lang/Exception;
    //   68: athrow
    //   69: aload_0
    //   70: getfield ZI : I
    //   73: iconst_4
    //   74: iand
    //   75: ifeq -> 140
    //   78: goto -> 85
    //   81: invokestatic c : (Ljava/lang/Exception;)Ljava/lang/Exception;
    //   84: athrow
    //   85: aload_0
    //   86: getfield Zi : Ljava/lang/String;
    //   89: ifnull -> 118
    //   92: goto -> 99
    //   95: invokestatic c : (Ljava/lang/Exception;)Ljava/lang/Exception;
    //   98: athrow
    //   99: aload_0
    //   100: aload_0
    //   101: invokevirtual Zvn : ()F
    //   104: putfield Zg : F
    //   107: aload_1
    //   108: ifnull -> 293
    //   111: goto -> 118
    //   114: invokestatic c : (Ljava/lang/Exception;)Ljava/lang/Exception;
    //   117: athrow
    //   118: aload_0
    //   119: aload_0
    //   120: invokevirtual Zv9 : ()Ljava/math/BigInteger;
    //   123: invokevirtual floatValue : ()F
    //   126: putfield Zg : F
    //   129: aload_1
    //   130: ifnull -> 293
    //   133: goto -> 140
    //   136: invokestatic c : (Ljava/lang/Exception;)Ljava/lang/Exception;
    //   139: athrow
    //   140: aload_0
    //   141: getfield ZI : I
    //   144: iconst_2
    //   145: iand
    //   146: ifeq -> 176
    //   149: goto -> 156
    //   152: invokestatic c : (Ljava/lang/Exception;)Ljava/lang/Exception;
    //   155: athrow
    //   156: aload_0
    //   157: aload_0
    //   158: getfield ZL : J
    //   161: l2f
    //   162: putfield Zg : F
    //   165: aload_1
    //   166: ifnull -> 293
    //   169: goto -> 176
    //   172: invokestatic c : (Ljava/lang/Exception;)Ljava/lang/Exception;
    //   175: athrow
    //   176: aload_0
    //   177: getfield ZI : I
    //   180: iconst_1
    //   181: iand
    //   182: ifeq -> 212
    //   185: goto -> 192
    //   188: invokestatic c : (Ljava/lang/Exception;)Ljava/lang/Exception;
    //   191: athrow
    //   192: aload_0
    //   193: aload_0
    //   194: getfield ZA : I
    //   197: i2f
    //   198: putfield Zg : F
    //   201: aload_1
    //   202: ifnull -> 293
    //   205: goto -> 212
    //   208: invokestatic c : (Ljava/lang/Exception;)Ljava/lang/Exception;
    //   211: athrow
    //   212: aload_0
    //   213: getfield ZI : I
    //   216: bipush #8
    //   218: iand
    //   219: ifeq -> 282
    //   222: goto -> 229
    //   225: invokestatic c : (Ljava/lang/Exception;)Ljava/lang/Exception;
    //   228: athrow
    //   229: aload_0
    //   230: getfield Zi : Ljava/lang/String;
    //   233: ifnull -> 262
    //   236: goto -> 243
    //   239: invokestatic c : (Ljava/lang/Exception;)Ljava/lang/Exception;
    //   242: athrow
    //   243: aload_0
    //   244: aload_0
    //   245: invokevirtual Zvn : ()F
    //   248: putfield Zg : F
    //   251: aload_1
    //   252: ifnull -> 293
    //   255: goto -> 262
    //   258: invokestatic c : (Ljava/lang/Exception;)Ljava/lang/Exception;
    //   261: athrow
    //   262: aload_0
    //   263: aload_0
    //   264: invokevirtual Zva : ()D
    //   267: d2f
    //   268: putfield Zg : F
    //   271: aload_1
    //   272: ifnull -> 293
    //   275: goto -> 282
    //   278: invokestatic c : (Ljava/lang/Exception;)Ljava/lang/Exception;
    //   281: athrow
    //   282: aload_0
    //   283: invokevirtual Z_A : ()V
    //   286: goto -> 293
    //   289: invokestatic c : (Ljava/lang/Exception;)Ljava/lang/Exception;
    //   292: athrow
    //   293: aload_0
    //   294: dup
    //   295: getfield ZI : I
    //   298: bipush #32
    //   300: ior
    //   301: putfield ZI : I
    //   304: return
    // Exception table:
    //   from	to	target	type
    //   4	21	24	java/io/IOException
    //   14	40	43	java/io/IOException
    //   28	62	65	java/io/IOException
    //   47	78	81	java/io/IOException
    //   69	92	95	java/io/IOException
    //   85	111	114	java/io/IOException
    //   99	133	136	java/io/IOException
    //   118	149	152	java/io/IOException
    //   140	169	172	java/io/IOException
    //   156	185	188	java/io/IOException
    //   176	205	208	java/io/IOException
    //   192	222	225	java/io/IOException
    //   212	236	239	java/io/IOException
    //   229	255	258	java/io/IOException
    //   243	275	278	java/io/IOException
    //   262	286	289	java/io/IOException
  }
  
  protected void ZvM() throws IOException {
    // Byte code:
    //   0: invokestatic Zn : ()[I
    //   3: astore_1
    //   4: aload_0
    //   5: getfield ZI : I
    //   8: bipush #8
    //   10: iand
    //   11: ifeq -> 63
    //   14: aload_0
    //   15: getfield Zi : Ljava/lang/String;
    //   18: ifnonnull -> 39
    //   21: goto -> 28
    //   24: invokestatic c : (Ljava/lang/Exception;)Ljava/lang/Exception;
    //   27: athrow
    //   28: aload_0
    //   29: invokevirtual ZR : ()Ljava/lang/String;
    //   32: goto -> 43
    //   35: invokestatic c : (Ljava/lang/Exception;)Ljava/lang/Exception;
    //   38: athrow
    //   39: aload_0
    //   40: getfield Zi : Ljava/lang/String;
    //   43: astore_2
    //   44: aload_0
    //   45: aload_2
    //   46: aload_0
    //   47: getstatic com/fasterxml/Zb/Zmv.USE_FAST_BIG_NUMBER_PARSER : Lcom/fasterxml/Zb/Zmv;
    //   50: invokevirtual Zt : (Lcom/fasterxml/Zb/Zmv;)Z
    //   53: invokestatic Zu : (Ljava/lang/String;Z)Ljava/math/BigDecimal;
    //   56: putfield ZU : Ljava/math/BigDecimal;
    //   59: aload_1
    //   60: ifnull -> 193
    //   63: aload_0
    //   64: getfield ZI : I
    //   67: iconst_4
    //   68: iand
    //   69: ifeq -> 105
    //   72: goto -> 79
    //   75: invokestatic c : (Ljava/lang/Exception;)Ljava/lang/Exception;
    //   78: athrow
    //   79: aload_0
    //   80: new java/math/BigDecimal
    //   83: dup
    //   84: aload_0
    //   85: invokevirtual Zv9 : ()Ljava/math/BigInteger;
    //   88: invokespecial <init> : (Ljava/math/BigInteger;)V
    //   91: putfield ZU : Ljava/math/BigDecimal;
    //   94: aload_1
    //   95: ifnull -> 193
    //   98: goto -> 105
    //   101: invokestatic c : (Ljava/lang/Exception;)Ljava/lang/Exception;
    //   104: athrow
    //   105: aload_0
    //   106: getfield ZI : I
    //   109: iconst_2
    //   110: iand
    //   111: ifeq -> 143
    //   114: goto -> 121
    //   117: invokestatic c : (Ljava/lang/Exception;)Ljava/lang/Exception;
    //   120: athrow
    //   121: aload_0
    //   122: aload_0
    //   123: getfield ZL : J
    //   126: invokestatic valueOf : (J)Ljava/math/BigDecimal;
    //   129: putfield ZU : Ljava/math/BigDecimal;
    //   132: aload_1
    //   133: ifnull -> 193
    //   136: goto -> 143
    //   139: invokestatic c : (Ljava/lang/Exception;)Ljava/lang/Exception;
    //   142: athrow
    //   143: aload_0
    //   144: getfield ZI : I
    //   147: iconst_1
    //   148: iand
    //   149: ifeq -> 182
    //   152: goto -> 159
    //   155: invokestatic c : (Ljava/lang/Exception;)Ljava/lang/Exception;
    //   158: athrow
    //   159: aload_0
    //   160: aload_0
    //   161: getfield ZA : I
    //   164: i2l
    //   165: invokestatic valueOf : (J)Ljava/math/BigDecimal;
    //   168: putfield ZU : Ljava/math/BigDecimal;
    //   171: aload_1
    //   172: ifnull -> 193
    //   175: goto -> 182
    //   178: invokestatic c : (Ljava/lang/Exception;)Ljava/lang/Exception;
    //   181: athrow
    //   182: aload_0
    //   183: invokevirtual Z_A : ()V
    //   186: goto -> 193
    //   189: invokestatic c : (Ljava/lang/Exception;)Ljava/lang/Exception;
    //   192: athrow
    //   193: aload_0
    //   194: dup
    //   195: getfield ZI : I
    //   198: bipush #16
    //   200: ior
    //   201: putfield ZI : I
    //   204: return
    // Exception table:
    //   from	to	target	type
    //   4	21	24	java/io/IOException
    //   14	35	35	java/io/IOException
    //   44	72	75	java/io/IOException
    //   63	98	101	java/io/IOException
    //   79	114	117	java/io/IOException
    //   105	136	139	java/io/IOException
    //   121	152	155	java/io/IOException
    //   143	175	178	java/io/IOException
    //   159	186	189	java/io/IOException
  }
  
  protected BigInteger Zp(BigDecimal paramBigDecimal) throws IOException {
    this.Zb.Zn(paramBigDecimal.scale());
    return paramBigDecimal.toBigInteger();
  }
  
  protected BigInteger Zv9() throws Zm0 {
    try {
      if (this.ZY != null)
        return this.ZY; 
    } catch (NumberFormatException numberFormatException) {
      throw c(null);
    } 
    try {
      if (this.Zi == null)
        throw new IllegalStateException(c(5883, 4294)); 
    } catch (NumberFormatException numberFormatException) {
      throw c(null);
    } 
    try {
      this.ZY = Zyt.ZI(this.Zi, Zt(Zmv.USE_FAST_BIG_NUMBER_PARSER));
    } catch (NumberFormatException numberFormatException) {
      ZL(c(5862, 17805) + ZU(this.Zi) + ")", numberFormatException);
    } 
    this.Zi = null;
    return this.ZY;
  }
  
  protected BigDecimal ZvW() throws Zm0 {
    try {
      if (this.ZU != null)
        return this.ZU; 
    } catch (NumberFormatException numberFormatException) {
      throw c(null);
    } 
    try {
      if (this.Zi == null)
        throw new IllegalStateException(c(5887, -18333)); 
    } catch (NumberFormatException numberFormatException) {
      throw c(null);
    } 
    try {
      this.ZU = Zyt.Zu(this.Zi, Zt(Zmv.USE_FAST_BIG_NUMBER_PARSER));
    } catch (NumberFormatException numberFormatException) {
      ZL(c(5862, 17805) + ZU(this.Zi) + ")", numberFormatException);
    } 
    this.Zi = null;
    return this.ZU;
  }
  
  protected double Zva() throws Zm0 {
    try {
      if (this.Zi != null) {
        try {
          this.ZW = Zyt.ZE(this.Zi, Zt(Zmv.USE_FAST_DOUBLE_PARSER));
        } catch (NumberFormatException numberFormatException) {
          ZL(c(5862, 17805) + ZU(this.Zi) + ")", numberFormatException);
        } 
        this.Zi = null;
      } 
    } catch (Zm0 zm0) {
      throw c(null);
    } 
    return this.ZW;
  }
  
  protected float Zvn() throws Zm0 {
    try {
      if (this.Zi != null) {
        try {
          this.Zg = Zyt.ZT(this.Zi, Zt(Zmv.USE_FAST_DOUBLE_PARSER));
        } catch (NumberFormatException numberFormatException) {
          ZL(c(5876, 14095) + ZU(this.Zi) + ")", numberFormatException);
        } 
        this.Zi = null;
      } 
    } catch (Zm0 zm0) {
      throw c(null);
    } 
    return this.Zg;
  }
  
  protected void ZU(int paramInt1, int paramInt2) throws IOException {
    this.Zx = this.Zx.Zs(paramInt1, paramInt2);
    this.Zb.Zi(this.Zx.Zs());
  }
  
  protected void Za(int paramInt1, int paramInt2) throws IOException {
    this.Zx = this.Zx.Zb(paramInt1, paramInt2);
    this.Zb.Zi(this.Zx.Zs());
  }
  
  protected char ZC(char paramChar) throws Zmt {
    try {
      if (Zx(Zm.ALLOW_BACKSLASH_ESCAPING_ANY_CHARACTER))
        return paramChar; 
    } catch (Zmt zmt) {
      throw c(null);
    } 
    try {
      if (paramChar == '\'')
        try {
          if (Zx(Zm.ALLOW_SINGLE_QUOTES))
            return paramChar; 
        } catch (Zmt zmt) {
          throw c(null);
        }  
    } catch (Zmt zmt) {
      throw c(null);
    } 
    throw Zw(c(5867, 5600) + ZU(paramChar), Z_h());
  }
  
  protected void Zf(int paramInt, char paramChar) throws Zm0 {
    Zn zn = ZvV();
    String str = String.format(c(5860, -31582), new Object[] { Character.valueOf((char)paramInt), Character.valueOf(paramChar), zn.ZF(), zn.Zj(ZvT()) });
    throw Zw(str, Z_h());
  }
  
  protected void ZF(int paramInt, String paramString) throws Zm0 {
    try {
      if (!Zx(Zm.ALLOW_UNQUOTED_CONTROL_CHARS) || paramInt > 32) {
        char c = (char)paramInt;
        String str = c(5886, -13309) + ZU(c) + c(5868, 8129) + paramString;
        throw Zw(str, Z_h());
      } 
    } catch (Zm0 zm0) {
      throw c(null);
    } 
  }
  
  protected String ZvH() throws IOException {
    return ZvU();
  }
  
  protected String ZvU() throws IOException {
    try {
      if (Zx(Zm.ALLOW_NON_NUMERIC_NUMBERS))
        return c(5881, -22914); 
    } catch (IOException iOException) {
      throw c(null);
    } 
    return c(5871, 18100);
  }
  
  protected char Zv1() throws IOException {
    throw new UnsupportedOperationException();
  }
  
  protected final int ZJ(Zy paramZy, int paramInt1, int paramInt2) throws IOException {
    try {
      if (paramInt1 != 92)
        throw Za(paramZy, paramInt1, paramInt2); 
    } catch (IOException iOException) {
      throw c(null);
    } 
    char c = Zv1();
    try {
      if (c <= ' ')
        try {
          if (paramInt2 == 0)
            return -1; 
        } catch (IOException iOException) {
          throw c(null);
        }  
    } catch (IOException iOException) {
      throw c(null);
    } 
    int i = paramZy.Zd(c);
    try {
      if (i < 0)
        try {
          if (i != -2)
            throw Za(paramZy, c, paramInt2); 
        } catch (IOException iOException) {
          throw c(null);
        }  
    } catch (IOException iOException) {
      throw c(null);
    } 
    return i;
  }
  
  protected final int ZY(Zy paramZy, char paramChar, int paramInt) throws IOException {
    try {
      if (paramChar != '\\')
        throw Za(paramZy, paramChar, paramInt); 
    } catch (IOException iOException) {
      throw c(null);
    } 
    char c = Zv1();
    try {
      if (c <= ' ')
        try {
          if (paramInt == 0)
            return -1; 
        } catch (IOException iOException) {
          throw c(null);
        }  
    } catch (IOException iOException) {
      throw c(null);
    } 
    int i = paramZy.Zd(c);
    try {
      if (i < 0)
        try {
          if (i == -2) {
            try {
              if (paramInt < 2)
                throw Za(paramZy, c, paramInt); 
            } catch (IOException iOException) {
              throw c(null);
            } 
          } else {
            throw Za(paramZy, c, paramInt);
          } 
        } catch (IOException iOException) {
          throw c(null);
        }  
    } catch (IOException iOException) {
      throw c(null);
    } 
    return i;
  }
  
  protected IllegalArgumentException Za(Zy paramZy, int paramInt1, int paramInt2) throws IllegalArgumentException {
    return Zp(paramZy, paramInt1, paramInt2, (String)null);
  }
  
  protected IllegalArgumentException Zp(Zy paramZy, int paramInt1, int paramInt2, String paramString) throws IllegalArgumentException {
    // Byte code:
    //   0: invokestatic Zn : ()[I
    //   3: astore #5
    //   5: iload_2
    //   6: bipush #32
    //   8: if_icmpgt -> 50
    //   11: sipush #5878
    //   14: sipush #24967
    //   17: invokestatic c : (II)Ljava/lang/String;
    //   20: iconst_2
    //   21: anewarray java/lang/Object
    //   24: dup
    //   25: iconst_0
    //   26: iload_2
    //   27: invokestatic toHexString : (I)Ljava/lang/String;
    //   30: aastore
    //   31: dup
    //   32: iconst_1
    //   33: iload_3
    //   34: iconst_1
    //   35: iadd
    //   36: invokestatic valueOf : (I)Ljava/lang/Integer;
    //   39: aastore
    //   40: invokestatic format : (Ljava/lang/String;[Ljava/lang/Object;)Ljava/lang/String;
    //   43: astore #6
    //   45: aload #5
    //   47: ifnull -> 267
    //   50: aload_1
    //   51: iload_2
    //   52: invokevirtual ZK : (I)Z
    //   55: ifeq -> 131
    //   58: goto -> 65
    //   61: invokestatic c : (Ljava/lang/Exception;)Ljava/lang/Exception;
    //   64: athrow
    //   65: new java/lang/StringBuilder
    //   68: dup
    //   69: invokespecial <init> : ()V
    //   72: sipush #5884
    //   75: sipush #-26801
    //   78: invokestatic c : (II)Ljava/lang/String;
    //   81: invokevirtual append : (Ljava/lang/String;)Ljava/lang/StringBuilder;
    //   84: aload_1
    //   85: invokevirtual Zx : ()C
    //   88: invokevirtual append : (C)Ljava/lang/StringBuilder;
    //   91: sipush #5885
    //   94: sipush #-7687
    //   97: invokestatic c : (II)Ljava/lang/String;
    //   100: invokevirtual append : (Ljava/lang/String;)Ljava/lang/StringBuilder;
    //   103: iload_3
    //   104: iconst_1
    //   105: iadd
    //   106: invokevirtual append : (I)Ljava/lang/StringBuilder;
    //   109: sipush #5880
    //   112: sipush #25886
    //   115: invokestatic c : (II)Ljava/lang/String;
    //   118: invokevirtual append : (Ljava/lang/String;)Ljava/lang/StringBuilder;
    //   121: invokevirtual toString : ()Ljava/lang/String;
    //   124: astore #6
    //   126: aload #5
    //   128: ifnull -> 267
    //   131: iload_2
    //   132: invokestatic isDefined : (I)Z
    //   135: ifeq -> 159
    //   138: goto -> 145
    //   141: invokestatic c : (Ljava/lang/Exception;)Ljava/lang/Exception;
    //   144: athrow
    //   145: iload_2
    //   146: invokestatic isISOControl : (I)Z
    //   149: ifeq -> 207
    //   152: goto -> 159
    //   155: invokestatic c : (Ljava/lang/Exception;)Ljava/lang/Exception;
    //   158: athrow
    //   159: new java/lang/StringBuilder
    //   162: dup
    //   163: invokespecial <init> : ()V
    //   166: sipush #5865
    //   169: sipush #-11630
    //   172: invokestatic c : (II)Ljava/lang/String;
    //   175: invokevirtual append : (Ljava/lang/String;)Ljava/lang/StringBuilder;
    //   178: iload_2
    //   179: invokestatic toHexString : (I)Ljava/lang/String;
    //   182: invokevirtual append : (Ljava/lang/String;)Ljava/lang/StringBuilder;
    //   185: sipush #5879
    //   188: sipush #-26813
    //   191: invokestatic c : (II)Ljava/lang/String;
    //   194: invokevirtual append : (Ljava/lang/String;)Ljava/lang/StringBuilder;
    //   197: invokevirtual toString : ()Ljava/lang/String;
    //   200: astore #6
    //   202: aload #5
    //   204: ifnull -> 267
    //   207: new java/lang/StringBuilder
    //   210: dup
    //   211: invokespecial <init> : ()V
    //   214: sipush #5857
    //   217: sipush #5444
    //   220: invokestatic c : (II)Ljava/lang/String;
    //   223: invokevirtual append : (Ljava/lang/String;)Ljava/lang/StringBuilder;
    //   226: iload_2
    //   227: i2c
    //   228: invokevirtual append : (C)Ljava/lang/StringBuilder;
    //   231: sipush #5863
    //   234: sipush #-18858
    //   237: invokestatic c : (II)Ljava/lang/String;
    //   240: invokevirtual append : (Ljava/lang/String;)Ljava/lang/StringBuilder;
    //   243: iload_2
    //   244: invokestatic toHexString : (I)Ljava/lang/String;
    //   247: invokevirtual append : (Ljava/lang/String;)Ljava/lang/StringBuilder;
    //   250: sipush #5864
    //   253: sipush #9543
    //   256: invokestatic c : (II)Ljava/lang/String;
    //   259: invokevirtual append : (Ljava/lang/String;)Ljava/lang/StringBuilder;
    //   262: invokevirtual toString : ()Ljava/lang/String;
    //   265: astore #6
    //   267: aload #4
    //   269: ifnull -> 306
    //   272: new java/lang/StringBuilder
    //   275: dup
    //   276: invokespecial <init> : ()V
    //   279: aload #6
    //   281: invokevirtual append : (Ljava/lang/String;)Ljava/lang/StringBuilder;
    //   284: sipush #5882
    //   287: sipush #20879
    //   290: invokestatic c : (II)Ljava/lang/String;
    //   293: invokevirtual append : (Ljava/lang/String;)Ljava/lang/StringBuilder;
    //   296: aload #4
    //   298: invokevirtual append : (Ljava/lang/String;)Ljava/lang/StringBuilder;
    //   301: invokevirtual toString : ()Ljava/lang/String;
    //   304: astore #6
    //   306: new java/lang/IllegalArgumentException
    //   309: dup
    //   310: aload #6
    //   312: invokespecial <init> : (Ljava/lang/String;)V
    //   315: areturn
    // Exception table:
    //   from	to	target	type
    //   45	58	61	java/lang/IllegalArgumentException
    //   126	138	141	java/lang/IllegalArgumentException
    //   131	152	155	java/lang/IllegalArgumentException
  }
  
  protected void Zm(Zy paramZy) throws IOException {
    Zk(paramZy.ZF());
  }
  
  protected Zq6 ZvT() {
    try {
      if (Zm.INCLUDE_SOURCE_IN_LOCATION.Zi(this.Zo))
        return this.Zf.ZJ(); 
    } catch (IllegalStateException illegalStateException) {
      throw c(null);
    } 
    return Zv0();
  }
  
  protected Zq6 Zv0() {
    return Zq6.Zx();
  }
  
  protected static int[] Zp(int[] paramArrayOfint, int paramInt) throws IllegalArgumentException {
    try {
      if (paramArrayOfint == null)
        return new int[paramInt]; 
    } catch (IllegalArgumentException illegalArgumentException) {
      throw c(null);
    } 
    int i = paramArrayOfint.length + paramInt;
    try {
      if (i < 0)
        throw new IllegalArgumentException(c(5875, 9639)); 
    } catch (IllegalArgumentException illegalArgumentException) {
      throw c(null);
    } 
    return Arrays.copyOf(paramArrayOfint, i);
  }
  
  protected int[] ZY(int[] paramArrayOfint, int paramInt) throws Z_ {
    this.Zb.Zr(paramArrayOfint.length << 2);
    return Zp(paramArrayOfint, paramInt);
  }
  
  protected void Zve() throws IOException {}
  
  static {
    // Byte code:
    //   0: bipush #29
    //   2: anewarray java/lang/String
    //   5: astore #5
    //   7: iconst_0
    //   8: istore_3
    //   9: ldc 'tA,$qngV?J4rMv5K/G/[fQT&g%nk\\rB1QOV3~ t=$f6\\nE2+X"Yx`2K$H'FSpwnp\\f\\nh2Q1rk7\\t_naTd/Zi&cV=DoB)VvKPw+[nKi Il ,=_b&\\rH2S>VM/K>2lJYN%)}#Ih46V@\\r5"oyQ[>6UJ 2LU@a\\f\o6D_}FmdGRb!\\nqG,,({ZR^<)erqj\\r+ (Gu+nZm,-#H40sR9\\rL/:c_%)jl<A7BZ-JFUr2WPy2w7o\\t:*EC{3Wio.J$y _Jl~-G@"rC^!lep/F!x[@w-gs}F\\r)aiG-ufc7."utiip4 w23Zi)`xnbbGhV$<O;U=T Rf~].7bc($MHp8', q]ESO\\fXX&U@ta\\r)zU<&l\#mWO>L5j\\tVl7U3s{^Zx,RQRSTPYw)*VL</,t\nx]jq3jO\\r`9c/^_O],3-,f86Lq\\t-7Q\\t2i`("z<3=C\\fCq\\fx#t\\nGz8^ND\\rbk%/\3k@:h\\ntY\\r?'
    //   11: dup
    //   12: astore_2
    //   13: invokevirtual length : ()I
    //   16: istore #4
    //   18: bipush #17
    //   20: istore_1
    //   21: iconst_m1
    //   22: istore_0
    //   23: bipush #119
    //   25: iinc #0, 1
    //   28: aload_2
    //   29: iload_0
    //   30: dup
    //   31: iload_1
    //   32: iadd
    //   33: invokevirtual substring : (II)Ljava/lang/String;
    //   36: iconst_m1
    //   37: goto -> 143
    //   40: aload #5
    //   42: swap
    //   43: iload_3
    //   44: iinc #3, 1
    //   47: swap
    //   48: aastore
    //   49: iload_0
    //   50: iload_1
    //   51: iadd
    //   52: dup
    //   53: istore_0
    //   54: iload #4
    //   56: if_icmpge -> 68
    //   59: aload_2
    //   60: iload_0
    //   61: invokevirtual charAt : (I)C
    //   64: istore_1
    //   65: goto -> 23
    //   68: ldc '\\r./mC'A&EF;Mo%uV'
    //   70: dup
    //   71: astore_2
    //   72: invokevirtual length : ()I
    //   75: istore #4
    //   77: bipush #25
    //   79: istore_1
    //   80: iconst_m1
    //   81: istore_0
    //   82: bipush #108
    //   84: iinc #0, 1
    //   87: aload_2
    //   88: iload_0
    //   89: dup
    //   90: iload_1
    //   91: iadd
    //   92: invokevirtual substring : (II)Ljava/lang/String;
    //   95: iconst_0
    //   96: goto -> 143
    //   99: aload #5
    //   101: swap
    //   102: iload_3
    //   103: iinc #3, 1
    //   106: swap
    //   107: aastore
    //   108: iload_0
    //   109: iload_1
    //   110: iadd
    //   111: dup
    //   112: istore_0
    //   113: iload #4
    //   115: if_icmpge -> 127
    //   118: aload_2
    //   119: iload_0
    //   120: invokevirtual charAt : (I)C
    //   123: istore_1
    //   124: goto -> 82
    //   127: aload #5
    //   129: putstatic com/fasterxml/Zx/Zo.e : [Ljava/lang/String;
    //   132: bipush #29
    //   134: anewarray java/lang/String
    //   137: putstatic com/fasterxml/Zx/Zo.f : [Ljava/lang/String;
    //   140: goto -> 300
    //   143: dup_x2
    //   144: pop
    //   145: invokevirtual toCharArray : ()[C
    //   148: dup_x1
    //   149: arraylength
    //   150: dup_x2
    //   151: pop
    //   152: iconst_0
    //   153: istore #6
    //   155: dup2_x1
    //   156: pop2
    //   157: dup_x2
    //   158: iconst_1
    //   159: if_icmpgt -> 260
    //   162: dup2
    //   163: swap
    //   164: iload #6
    //   166: dup2_x1
    //   167: caload
    //   168: swap
    //   169: iload #6
    //   171: bipush #7
    //   173: irem
    //   174: tableswitch default -> 242, 0 -> 212, 1 -> 217, 2 -> 222, 3 -> 227, 4 -> 232, 5 -> 237
    //   212: bipush #76
    //   214: goto -> 244
    //   217: bipush #30
    //   219: goto -> 244
    //   222: bipush #122
    //   224: goto -> 244
    //   227: bipush #116
    //   229: goto -> 244
    //   232: bipush #77
    //   234: goto -> 244
    //   237: bipush #93
    //   239: goto -> 244
    //   242: bipush #83
    //   244: ixor
    //   245: ixor
    //   246: i2c
    //   247: castore
    //   248: iinc #6, 1
    //   251: dup
    //   252: ifne -> 260
    //   255: dup2
    //   256: dup_x1
    //   257: goto -> 166
    //   260: dup2_x1
    //   261: pop2
    //   262: dup_x2
    //   263: iload #6
    //   265: if_icmpgt -> 162
    //   268: pop
    //   269: new java/lang/String
    //   272: dup_x1
    //   273: swap
    //   274: invokespecial <init> : ([C)V
    //   277: invokevirtual intern : ()Ljava/lang/String;
    //   280: swap
    //   281: pop
    //   282: swap
    //   283: tableswitch default -> 40, 0 -> 99
    //   300: getstatic com/fasterxml/Zx/Zo.ZH : Lcom/fasterxml/Zc/Zz;
    //   303: putstatic com/fasterxml/Zx/Zo.ZF : Lcom/fasterxml/Zc/Zz;
    //   306: return
  }
  
  private static Exception c(Exception paramException) {
    return paramException;
  }
  
  private static String c(int paramInt1, int paramInt2) {
    int i = (paramInt1 ^ 0x16FD) & 0xFFFF;
    if (f[i] == null) {
      char[] arrayOfChar = e[i].toCharArray();
      switch (arrayOfChar[0] & 0xFF) {
        case 0:
        
        case 1:
        
        case 2:
        
        case 3:
        
        case 4:
        
        case 5:
        
        case 6:
        
        case 7:
        
        case 8:
        
        case 9:
        
        case 10:
        
        case 11:
        
        case 12:
        
        case 13:
        
        case 14:
        
        case 15:
        
        case 16:
        
        case 17:
        
        case 18:
        
        case 19:
        
        case 20:
        
        case 21:
        
        case 22:
        
        case 23:
        
        case 24:
        
        case 25:
        
        case 26:
        
        case 27:
        
        case 28:
        
        case 29:
        
        case 30:
        
        case 31:
        
        case 32:
        
        case 33:
        
        case 34:
        
        case 35:
        
        case 36:
        
        case 37:
        
        case 38:
        
        case 39:
        
        case 40:
        
        case 41:
        
        case 42:
        
        case 43:
        
        case 44:
        
        case 45:
        
        case 46:
        
        case 47:
        
        case 48:
        
        case 49:
        
        case 50:
        
        case 51:
        
        case 52:
        
        case 53:
        
        case 54:
        
        case 55:
        
        case 56:
        
        case 57:
        
        case 58:
        
        case 59:
        
        case 60:
        
        case 61:
        
        case 62:
        
        case 63:
        
        case 64:
        
        case 65:
        
        case 66:
        
        case 67:
        
        case 68:
        
        case 69:
        
        case 70:
        
        case 71:
        
        case 72:
        
        case 73:
        
        case 74:
        
        case 75:
        
        case 76:
        
        case 77:
        
        case 78:
        
        case 79:
        
        case 80:
        
        case 81:
        
        case 82:
        
        case 83:
        
        case 84:
        
        case 85:
        
        case 86:
        
        case 87:
        
        case 88:
        
        case 89:
        
        case 90:
        
        case 91:
        
        case 92:
        
        case 93:
        
        case 94:
        
        case 95:
        
        case 96:
        
        case 97:
        
        case 98:
        
        case 99:
        
        case 100:
        
        case 101:
        
        case 102:
        
        case 103:
        
        case 104:
        
        case 105:
        
        case 106:
        
        case 107:
        
        case 108:
        
        case 109:
        
        case 110:
        
        case 111:
        
        case 112:
        
        case 113:
        
        case 114:
        
        case 115:
        
        case 116:
        
        case 117:
        
        case 118:
        
        case 119:
        
        case 120:
        
        case 121:
        
        case 122:
        
        case 123:
        
        case 124:
        
        case 125:
        
        case 126:
        
        case 127:
        
        case 128:
        
        case 129:
        
        case 130:
        
        case 131:
        
        case 132:
        
        case 133:
        
        case 134:
        
        case 135:
        
        case 136:
        
        case 137:
        
        case 138:
        
        case 139:
        
        case 140:
        
        case 141:
        
        case 142:
        
        case 143:
        
        case 144:
        
        case 145:
        
        case 146:
        
        case 147:
        
        case 148:
        
        case 149:
        
        case 150:
        
        case 151:
        
        case 152:
        
        case 153:
        
        case 154:
        
        case 155:
        
        case 156:
        
        case 157:
        
        case 158:
        
        case 159:
        
        case 160:
        
        case 161:
        
        case 162:
        
        case 163:
        
        case 164:
        
        case 165:
        
        case 166:
        
        case 167:
        
        case 168:
        
        case 169:
        
        case 170:
        
        case 171:
        
        case 172:
        
        case 173:
        
        case 174:
        
        case 175:
        
        case 176:
        
        case 177:
        
        case 178:
        
        case 179:
        
        case 180:
        
        case 181:
        
        case 182:
        
        case 183:
        
        case 184:
        
        case 185:
        
        case 186:
        
        case 187:
        
        case 188:
        
        case 189:
        
        case 190:
        
        case 191:
        
        case 192:
        
        case 193:
        
        case 194:
        
        case 195:
        
        case 196:
        
        case 197:
        
        case 198:
        
        case 199:
        
        case 200:
        
        case 201:
        
        case 202:
        
        case 203:
        
        case 204:
        
        case 205:
        
        case 206:
        
        case 207:
        
        case 208:
        
        case 209:
        
        case 210:
        
        case 211:
        
        case 212:
        
        case 213:
        
        case 214:
        
        case 215:
        
        case 216:
        
        case 217:
        
        case 218:
        
        case 219:
        
        case 220:
        
        case 221:
        
        case 222:
        
        case 223:
        
        case 224:
        
        case 225:
        
        case 226:
        
        case 227:
        
        case 228:
        
        case 229:
        
        case 230:
        
        case 231:
        
        case 232:
        
        case 233:
        
        case 234:
        
        case 235:
        
        case 236:
        
        case 237:
        
        case 238:
        
        case 239:
        
        case 240:
        
        case 241:
        
        case 242:
        
        case 243:
        
        case 244:
        
        case 245:
        
        case 246:
        
        case 247:
        
        case 248:
        
        case 249:
        
        case 250:
        
        case 251:
        
        case 252:
        
        case 253:
        
        case 254:
        
        default:
          break;
      } 
      char c = '';
      int j = (paramInt2 & 0xFF) - c;
      if (j < 0)
        j += 256; 
      int k = ((paramInt2 & 0xFFFF) >>> 8) - c;
      if (k < 0)
        k += 256; 
      for (byte b = 0; b < arrayOfChar.length; b++) {
        int m = b % 2;
        if (m == 0) {
          arrayOfChar[b] = (char)(arrayOfChar[b] ^ j);
          j = ((j >>> 3 | j << 5) ^ arrayOfChar[b]) & 0xFF;
        } else {
          arrayOfChar[b] = (char)(arrayOfChar[b] ^ k);
          k = ((k >>> 3 | k << 5) ^ arrayOfChar[b]) & 0xFF;
        } 
      } 
      f[i] = (new String(arrayOfChar)).intern();
    } 
    return f[i];
  }
}


/* Location:              C:\Program Files\BurpSuitePro\burpsuite_pro.jar!\com\fasterxml\Zx\Zo.class
 * Java compiler version: 8 (52.0)
 * JD-Core Version:       1.1.3
 */