package net.portswigger.devtools.client.impl.connection.local.process.chrome.binary;

public class Zl {
  public static final String ZN;
  
  public static final String ZS;
  
  static {
    // Byte code:
    //   0: bipush #52
    //   2: ldc '<f19Keg14;21kdlH90j6N:Lge`dM'
    //   4: iconst_m1
    //   5: goto -> 18
    //   8: putstatic net/portswigger/devtools/client/impl/connection/local/process/chrome/binary/Zl.ZS : Ljava/lang/String;
    //   11: getstatic net/portswigger/devtools/client/impl/connection/local/process/chrome/binary/Zl.ZS : Ljava/lang/String;
    //   14: pop
    //   15: goto -> 158
    //   18: dup_x2
    //   19: pop
    //   20: invokevirtual toCharArray : ()[C
    //   23: dup_x1
    //   24: arraylength
    //   25: dup_x2
    //   26: pop
    //   27: iconst_0
    //   28: istore_0
    //   29: dup2_x1
    //   30: pop2
    //   31: dup_x2
    //   32: iconst_1
    //   33: if_icmpgt -> 132
    //   36: dup2
    //   37: swap
    //   38: iload_0
    //   39: dup2_x1
    //   40: caload
    //   41: swap
    //   42: iload_0
    //   43: bipush #7
    //   45: irem
    //   46: tableswitch default -> 114, 0 -> 84, 1 -> 89, 2 -> 94, 3 -> 99, 4 -> 104, 5 -> 109
    //   84: bipush #48
    //   86: goto -> 116
    //   89: bipush #103
    //   91: goto -> 116
    //   94: bipush #50
    //   96: goto -> 116
    //   99: bipush #24
    //   101: goto -> 116
    //   104: bipush #62
    //   106: goto -> 116
    //   109: bipush #26
    //   111: goto -> 116
    //   114: bipush #53
    //   116: ixor
    //   117: ixor
    //   118: i2c
    //   119: castore
    //   120: iinc #0, 1
    //   123: dup
    //   124: ifne -> 132
    //   127: dup2
    //   128: dup_x1
    //   129: goto -> 39
    //   132: dup2_x1
    //   133: pop2
    //   134: dup_x2
    //   135: iload_0
    //   136: if_icmpgt -> 36
    //   139: pop
    //   140: new java/lang/String
    //   143: dup_x1
    //   144: swap
    //   145: invokespecial <init> : ([C)V
    //   148: invokevirtual intern : ()Ljava/lang/String;
    //   151: swap
    //   152: pop
    //   153: swap
    //   154: pop
    //   155: goto -> 8
    //   158: invokestatic ZW : ()Ljava/lang/String;
    //   161: putstatic net/portswigger/devtools/client/impl/connection/local/process/chrome/binary/Zl.ZN : Ljava/lang/String;
    //   164: return
  }
}


/* Location:              C:\Program Files\BurpSuitePro\burpsuite_pro.jar!\net\portswigger\devtools\client\impl\connection\local\process\chrome\binary\Zl.class
 * Java compiler version: 21 (65.0)
 * JD-Core Version:       1.1.3
 */