package burp;

public class Z_y extends Zni implements Zgzp {
  @Zzvo(1)
  private int ZH;
  
  @Zzvo(2)
  private boolean Zu;
  
  @Zzvo(3)
  private boolean ZM;
  
  @Zzvo(4)
  private boolean Zo;
  
  @Zzvo(5)
  private boolean ZD;
  
  @Zzvo(6)
  private boolean ZX;
  
  @Zzvo(7)
  private boolean Zq;
  
  @Zzvo(8)
  private boolean ZV;
  
  @Zzvo(9)
  private boolean Zl;
  
  @Zzvo(10)
  private boolean Zj;
  
  @Zzvo(11)
  private boolean ZL;
  
  @Zzvo(12)
  private boolean ZB;
  
  @Zzvo(13)
  private boolean Zb;
  
  @Zzvo(14)
  private boolean Z_;
  
  @Zzvo(15)
  private boolean ZZ;
  
  @Zzvo(16)
  private boolean Zh;
  
  @Zzvo(18)
  private String ZT;
  
  @Zzvo(19)
  private boolean Za;
  
  @Zzvo(20)
  private boolean ZJ;
  
  @Zzvo(21)
  private boolean ZE;
  
  @Zzvo(22)
  private boolean ZC;
  
  @Zzvo(23)
  private int Ze;
  
  @Zzvo(24)
  private int Zd;
  
  @Zzvo(17)
  private final boolean[] Zk;
  
  @Zzvo(25)
  private boolean Zp;
  
  @Zzvo(26)
  private final int ZG;
  
  @Zzvo(27)
  private Zrb5 ZS;
  
  private Zzca ZU;
  
  private static final String a;
  
  public Z_y(int paramInt1, int paramInt2) {
    this.ZG = paramInt1;
    this.ZH = paramInt2;
    this.ZT = "";
    this.Zk = new boolean[7];
  }
  
  public int Z_G() {
    return this.ZH;
  }
  
  public void Zk0(int paramInt) {
    this.ZH = paramInt;
  }
  
  public boolean Z_L() {
    return this.Zu;
  }
  
  public void ZPC(boolean paramBoolean) {
    this.Zu = paramBoolean;
  }
  
  public boolean Z_j() {
    return this.ZM;
  }
  
  public void ZPZ(boolean paramBoolean) {
    this.ZM = paramBoolean;
  }
  
  public boolean Z_K() {
    return this.Zo;
  }
  
  public void ZPK(boolean paramBoolean) {
    this.Zo = paramBoolean;
  }
  
  public boolean Z_e() {
    return this.ZD;
  }
  
  public void ZP2(boolean paramBoolean) {
    this.ZD = paramBoolean;
  }
  
  public boolean Z_q() {
    return this.ZX;
  }
  
  public void ZPe(boolean paramBoolean) {
    this.ZX = paramBoolean;
  }
  
  public boolean Z_r() {
    return this.Zq;
  }
  
  public void ZPP(boolean paramBoolean) {
    this.Zq = paramBoolean;
  }
  
  public boolean Z_Y() {
    return this.ZV;
  }
  
  public void ZPn(boolean paramBoolean) {
    this.ZV = paramBoolean;
  }
  
  public boolean Z_w() {
    return this.Zl;
  }
  
  public void ZPs(boolean paramBoolean) {
    this.Zl = paramBoolean;
  }
  
  public boolean Z_S() {
    return this.Zj;
  }
  
  public void ZPH(boolean paramBoolean) {
    this.Zj = paramBoolean;
  }
  
  public boolean Z_J() {
    return this.ZL;
  }
  
  public void ZPh(boolean paramBoolean) {
    this.ZL = paramBoolean;
  }
  
  public boolean Z_t() {
    return this.ZB;
  }
  
  public void ZPM(boolean paramBoolean) {
    this.ZB = paramBoolean;
  }
  
  public boolean Z_b() {
    return this.Zb;
  }
  
  public void ZP4(boolean paramBoolean) {
    this.Zb = paramBoolean;
  }
  
  public boolean Z_P() {
    return this.Z_;
  }
  
  public void ZPq(boolean paramBoolean) {
    this.Z_ = paramBoolean;
  }
  
  public boolean Z_u() {
    return this.ZZ;
  }
  
  public void ZP7(boolean paramBoolean) {
    this.ZZ = paramBoolean;
  }
  
  public boolean Z_4() {
    return this.Zh;
  }
  
  public void ZP5(boolean paramBoolean) {
    this.Zh = paramBoolean;
  }
  
  public boolean Zv(Zeew paramZeew) {
    return this.Zk[Zg0k.ZR(paramZeew)];
  }
  
  public void Zc(Zeew paramZeew, boolean paramBoolean) {
    this.Zk[Zg0k.ZR(paramZeew)] = paramBoolean;
  }
  
  public String Zbo() {
    return this.ZT;
  }
  
  public void ZP4(String paramString) {
    this.ZT = paramString;
  }
  
  public boolean ZbK() {
    return this.Za;
  }
  
  public void ZPr(boolean paramBoolean) {
    this.Za = paramBoolean;
  }
  
  public boolean Zbz() {
    return this.ZJ;
  }
  
  public void ZPW(boolean paramBoolean) {
    this.ZJ = paramBoolean;
  }
  
  public boolean Zb1() {
    return this.ZE;
  }
  
  public void ZP8(boolean paramBoolean) {
    this.ZE = paramBoolean;
  }
  
  public boolean Z_T() {
    return this.ZC;
  }
  
  public void ZPB(boolean paramBoolean) {
    this.ZC = paramBoolean;
  }
  
  public int Z_Q() {
    return this.Ze;
  }
  
  public void Zkh(int paramInt) {
    this.Ze = paramInt;
  }
  
  public int Z_E() {
    return this.Zd;
  }
  
  public void Zkm(int paramInt) {
    this.Zd = paramInt;
  }
  
  public boolean Z_g() {
    return this.Zp;
  }
  
  public void ZPc(boolean paramBoolean) {
    this.Zp = paramBoolean;
  }
  
  public int Z_l() {
    return this.ZG;
  }
  
  public String Z_W() {
    String str = (this.ZS == null) ? "" : this.ZS.ZJ();
    return str.isEmpty() ? a : str;
  }
  
  public void ZiY(String paramString) {
    if (this.ZS == null)
      this.ZS = new Zn9(); 
    this.ZS.Ze(paramString);
  }
  
  public Zzca Z_D() {
    if (this.ZU == null)
      this.ZU = Zzca.SETTINGS; 
    return this.ZU;
  }
  
  public void Zr(Zzca paramZzca) {
    this.ZU = paramZzca;
  }
  
  public Zeu4<Zgzp> ZF() {
    return Zgzp.ZF;
  }
  
  @Zzvo(28)
  private byte ZTg() {
    return Z_D().ZY();
  }
  
  static {
    // Byte code:
    //   0: bipush #83
    //   2: ldc '\\t|\\rlP)}%'
    //   4: iconst_m1
    //   5: goto -> 14
    //   8: putstatic burp/Z_y.a : Ljava/lang/String;
    //   11: goto -> 154
    //   14: dup_x2
    //   15: pop
    //   16: invokevirtual toCharArray : ()[C
    //   19: dup_x1
    //   20: arraylength
    //   21: dup_x2
    //   22: pop
    //   23: iconst_0
    //   24: istore_0
    //   25: dup2_x1
    //   26: pop2
    //   27: dup_x2
    //   28: iconst_1
    //   29: if_icmpgt -> 128
    //   32: dup2
    //   33: swap
    //   34: iload_0
    //   35: dup2_x1
    //   36: caload
    //   37: swap
    //   38: iload_0
    //   39: bipush #7
    //   41: irem
    //   42: tableswitch default -> 110, 0 -> 80, 1 -> 85, 2 -> 90, 3 -> 95, 4 -> 100, 5 -> 105
    //   80: bipush #53
    //   82: goto -> 112
    //   85: bipush #63
    //   87: goto -> 112
    //   90: bipush #91
    //   92: goto -> 112
    //   95: bipush #43
    //   97: goto -> 112
    //   100: bipush #77
    //   102: goto -> 112
    //   105: bipush #109
    //   107: goto -> 112
    //   110: bipush #90
    //   112: ixor
    //   113: ixor
    //   114: i2c
    //   115: castore
    //   116: iinc #0, 1
    //   119: dup
    //   120: ifne -> 128
    //   123: dup2
    //   124: dup_x1
    //   125: goto -> 35
    //   128: dup2_x1
    //   129: pop2
    //   130: dup_x2
    //   131: iload_0
    //   132: if_icmpgt -> 32
    //   135: pop
    //   136: new java/lang/String
    //   139: dup_x1
    //   140: swap
    //   141: invokespecial <init> : ([C)V
    //   144: invokevirtual intern : ()Ljava/lang/String;
    //   147: swap
    //   148: pop
    //   149: swap
    //   150: pop
    //   151: goto -> 8
    //   154: return
  }
}


/* Location:              C:\Program Files\BurpSuitePro\burpsuite_pro.jar!\burp\Z_y.class
 * Java compiler version: 21 (65.0)
 * JD-Core Version:       1.1.3
 */