package burp;

import java.math.BigInteger;

class Zb0z extends ClassLoader {
  static String ZM;
  
  static Object ZQ;
  
  private static final String[] a;
  
  private static final String[] b;
  
  static void ZZ(Object[] paramArrayOfObject, Object paramObject) throws Throwable {}
  
  static void ZB(Object paramObject) {
    Zkfa.Zy = a(-15261, -28522);
    Zkfa.Zw = new BigInteger(a(-15253, 19379));
    boolean bool = Zt2e.ZK();
    try {
      try {
        if (Zzou.ZN.charAt(Math.abs(((BigInteger)Zmlu.Zi).intValue() % 32)) > Zkco.Zz.charAt(Math.abs(((BigInteger)Ztdx.ZX).intValue() % 32))) {
          try {
            Ztd3.Zt(Class.forName(a(-15260, -28819)));
            if (bool)
              Zvh.Z_(Class.forName(a(-15263, 15996))); 
          } catch (Throwable throwable) {
            throw a(null);
          } 
          return;
        } 
      } catch (Throwable throwable) {
        throw a(null);
      } 
      Zvh.Z_(Class.forName(a(-15263, 15996)));
    } catch (Throwable throwable) {}
  }
  
  static boolean Zo(Object[] paramArrayOfObject, Object paramObject) throws Throwable {
    // Byte code:
    //   0: invokestatic ZN : ()Z
    //   3: istore_2
    //   4: getstatic burp/Zlpn.ZU : Ljava/lang/Object;
    //   7: checkcast java/math/BigInteger
    //   10: invokevirtual toByteArray : ()[B
    //   13: astore_3
    //   14: bipush #64
    //   16: newarray byte
    //   18: dup
    //   19: iconst_0
    //   20: bipush #-128
    //   22: bastore
    //   23: dup
    //   24: iconst_1
    //   25: iconst_0
    //   26: bastore
    //   27: dup
    //   28: iconst_2
    //   29: iconst_0
    //   30: bastore
    //   31: dup
    //   32: iconst_3
    //   33: iconst_0
    //   34: bastore
    //   35: dup
    //   36: iconst_4
    //   37: iconst_0
    //   38: bastore
    //   39: dup
    //   40: iconst_5
    //   41: iconst_0
    //   42: bastore
    //   43: dup
    //   44: bipush #6
    //   46: iconst_0
    //   47: bastore
    //   48: dup
    //   49: bipush #7
    //   51: iconst_0
    //   52: bastore
    //   53: dup
    //   54: bipush #8
    //   56: iconst_0
    //   57: bastore
    //   58: dup
    //   59: bipush #9
    //   61: iconst_0
    //   62: bastore
    //   63: dup
    //   64: bipush #10
    //   66: iconst_0
    //   67: bastore
    //   68: dup
    //   69: bipush #11
    //   71: iconst_0
    //   72: bastore
    //   73: dup
    //   74: bipush #12
    //   76: iconst_0
    //   77: bastore
    //   78: dup
    //   79: bipush #13
    //   81: iconst_0
    //   82: bastore
    //   83: dup
    //   84: bipush #14
    //   86: iconst_0
    //   87: bastore
    //   88: dup
    //   89: bipush #15
    //   91: iconst_0
    //   92: bastore
    //   93: dup
    //   94: bipush #16
    //   96: iconst_0
    //   97: bastore
    //   98: dup
    //   99: bipush #17
    //   101: iconst_0
    //   102: bastore
    //   103: dup
    //   104: bipush #18
    //   106: iconst_0
    //   107: bastore
    //   108: dup
    //   109: bipush #19
    //   111: iconst_0
    //   112: bastore
    //   113: dup
    //   114: bipush #20
    //   116: iconst_0
    //   117: bastore
    //   118: dup
    //   119: bipush #21
    //   121: iconst_0
    //   122: bastore
    //   123: dup
    //   124: bipush #22
    //   126: iconst_0
    //   127: bastore
    //   128: dup
    //   129: bipush #23
    //   131: iconst_0
    //   132: bastore
    //   133: dup
    //   134: bipush #24
    //   136: iconst_0
    //   137: bastore
    //   138: dup
    //   139: bipush #25
    //   141: iconst_0
    //   142: bastore
    //   143: dup
    //   144: bipush #26
    //   146: iconst_0
    //   147: bastore
    //   148: dup
    //   149: bipush #27
    //   151: iconst_0
    //   152: bastore
    //   153: dup
    //   154: bipush #28
    //   156: iconst_0
    //   157: bastore
    //   158: dup
    //   159: bipush #29
    //   161: iconst_0
    //   162: bastore
    //   163: dup
    //   164: bipush #30
    //   166: iconst_0
    //   167: bastore
    //   168: dup
    //   169: bipush #31
    //   171: iconst_0
    //   172: bastore
    //   173: dup
    //   174: bipush #32
    //   176: iconst_0
    //   177: bastore
    //   178: dup
    //   179: bipush #33
    //   181: iconst_0
    //   182: bastore
    //   183: dup
    //   184: bipush #34
    //   186: iconst_0
    //   187: bastore
    //   188: dup
    //   189: bipush #35
    //   191: iconst_0
    //   192: bastore
    //   193: dup
    //   194: bipush #36
    //   196: iconst_0
    //   197: bastore
    //   198: dup
    //   199: bipush #37
    //   201: iconst_0
    //   202: bastore
    //   203: dup
    //   204: bipush #38
    //   206: iconst_0
    //   207: bastore
    //   208: dup
    //   209: bipush #39
    //   211: iconst_0
    //   212: bastore
    //   213: dup
    //   214: bipush #40
    //   216: iconst_0
    //   217: bastore
    //   218: dup
    //   219: bipush #41
    //   221: iconst_0
    //   222: bastore
    //   223: dup
    //   224: bipush #42
    //   226: iconst_0
    //   227: bastore
    //   228: dup
    //   229: bipush #43
    //   231: iconst_0
    //   232: bastore
    //   233: dup
    //   234: bipush #44
    //   236: iconst_0
    //   237: bastore
    //   238: dup
    //   239: bipush #45
    //   241: iconst_0
    //   242: bastore
    //   243: dup
    //   244: bipush #46
    //   246: iconst_0
    //   247: bastore
    //   248: dup
    //   249: bipush #47
    //   251: iconst_0
    //   252: bastore
    //   253: dup
    //   254: bipush #48
    //   256: iconst_0
    //   257: bastore
    //   258: dup
    //   259: bipush #49
    //   261: iconst_0
    //   262: bastore
    //   263: dup
    //   264: bipush #50
    //   266: iconst_0
    //   267: bastore
    //   268: dup
    //   269: bipush #51
    //   271: iconst_0
    //   272: bastore
    //   273: dup
    //   274: bipush #52
    //   276: iconst_0
    //   277: bastore
    //   278: dup
    //   279: bipush #53
    //   281: iconst_0
    //   282: bastore
    //   283: dup
    //   284: bipush #54
    //   286: iconst_0
    //   287: bastore
    //   288: dup
    //   289: bipush #55
    //   291: iconst_0
    //   292: bastore
    //   293: dup
    //   294: bipush #56
    //   296: iconst_0
    //   297: bastore
    //   298: dup
    //   299: bipush #57
    //   301: iconst_0
    //   302: bastore
    //   303: dup
    //   304: bipush #58
    //   306: iconst_0
    //   307: bastore
    //   308: dup
    //   309: bipush #59
    //   311: iconst_0
    //   312: bastore
    //   313: dup
    //   314: bipush #60
    //   316: iconst_0
    //   317: bastore
    //   318: dup
    //   319: bipush #61
    //   321: iconst_0
    //   322: bastore
    //   323: dup
    //   324: bipush #62
    //   326: iconst_0
    //   327: bastore
    //   328: dup
    //   329: bipush #63
    //   331: iconst_0
    //   332: bastore
    //   333: astore #5
    //   335: bipush #64
    //   337: newarray int
    //   339: dup
    //   340: iconst_0
    //   341: ldc 1116352408
    //   343: iastore
    //   344: dup
    //   345: iconst_1
    //   346: ldc 1899447441
    //   348: iastore
    //   349: dup
    //   350: iconst_2
    //   351: ldc -1245643825
    //   353: iastore
    //   354: dup
    //   355: iconst_3
    //   356: ldc -373957723
    //   358: iastore
    //   359: dup
    //   360: iconst_4
    //   361: ldc 961987163
    //   363: iastore
    //   364: dup
    //   365: iconst_5
    //   366: ldc 1508970993
    //   368: iastore
    //   369: dup
    //   370: bipush #6
    //   372: ldc -1841331548
    //   374: iastore
    //   375: dup
    //   376: bipush #7
    //   378: ldc -1424204075
    //   380: iastore
    //   381: dup
    //   382: bipush #8
    //   384: ldc -670586216
    //   386: iastore
    //   387: dup
    //   388: bipush #9
    //   390: ldc 310598401
    //   392: iastore
    //   393: dup
    //   394: bipush #10
    //   396: ldc 607225278
    //   398: iastore
    //   399: dup
    //   400: bipush #11
    //   402: ldc 1426881987
    //   404: iastore
    //   405: dup
    //   406: bipush #12
    //   408: ldc 1925078388
    //   410: iastore
    //   411: dup
    //   412: bipush #13
    //   414: ldc -2132889090
    //   416: iastore
    //   417: dup
    //   418: bipush #14
    //   420: ldc -1680079193
    //   422: iastore
    //   423: dup
    //   424: bipush #15
    //   426: ldc -1046744716
    //   428: iastore
    //   429: dup
    //   430: bipush #16
    //   432: ldc -459576895
    //   434: iastore
    //   435: dup
    //   436: bipush #17
    //   438: ldc -272742522
    //   440: iastore
    //   441: dup
    //   442: bipush #18
    //   444: ldc 264347078
    //   446: iastore
    //   447: dup
    //   448: bipush #19
    //   450: ldc 604807628
    //   452: iastore
    //   453: dup
    //   454: bipush #20
    //   456: ldc 770255983
    //   458: iastore
    //   459: dup
    //   460: bipush #21
    //   462: ldc 1249150122
    //   464: iastore
    //   465: dup
    //   466: bipush #22
    //   468: ldc 1555081692
    //   470: iastore
    //   471: dup
    //   472: bipush #23
    //   474: ldc 1996064986
    //   476: iastore
    //   477: dup
    //   478: bipush #24
    //   480: ldc -1740746414
    //   482: iastore
    //   483: dup
    //   484: bipush #25
    //   486: ldc -1473132947
    //   488: iastore
    //   489: dup
    //   490: bipush #26
    //   492: ldc -1341970488
    //   494: iastore
    //   495: dup
    //   496: bipush #27
    //   498: ldc -1084653625
    //   500: iastore
    //   501: dup
    //   502: bipush #28
    //   504: ldc -958395405
    //   506: iastore
    //   507: dup
    //   508: bipush #29
    //   510: ldc -710438585
    //   512: iastore
    //   513: dup
    //   514: bipush #30
    //   516: ldc 113926993
    //   518: iastore
    //   519: dup
    //   520: bipush #31
    //   522: ldc 338241895
    //   524: iastore
    //   525: dup
    //   526: bipush #32
    //   528: ldc 666307205
    //   530: iastore
    //   531: dup
    //   532: bipush #33
    //   534: ldc 773529912
    //   536: iastore
    //   537: dup
    //   538: bipush #34
    //   540: ldc 1294757372
    //   542: iastore
    //   543: dup
    //   544: bipush #35
    //   546: ldc 1396182291
    //   548: iastore
    //   549: dup
    //   550: bipush #36
    //   552: ldc 1695183700
    //   554: iastore
    //   555: dup
    //   556: bipush #37
    //   558: ldc 1986661051
    //   560: iastore
    //   561: dup
    //   562: bipush #38
    //   564: ldc -2117940946
    //   566: iastore
    //   567: dup
    //   568: bipush #39
    //   570: ldc -1838011259
    //   572: iastore
    //   573: dup
    //   574: bipush #40
    //   576: ldc -1564481375
    //   578: iastore
    //   579: dup
    //   580: bipush #41
    //   582: ldc -1474664885
    //   584: iastore
    //   585: dup
    //   586: bipush #42
    //   588: ldc -1035236496
    //   590: iastore
    //   591: dup
    //   592: bipush #43
    //   594: ldc -949202525
    //   596: iastore
    //   597: dup
    //   598: bipush #44
    //   600: ldc -778901479
    //   602: iastore
    //   603: dup
    //   604: bipush #45
    //   606: ldc -694614492
    //   608: iastore
    //   609: dup
    //   610: bipush #46
    //   612: ldc -200395387
    //   614: iastore
    //   615: dup
    //   616: bipush #47
    //   618: ldc 275423344
    //   620: iastore
    //   621: dup
    //   622: bipush #48
    //   624: ldc 430227734
    //   626: iastore
    //   627: dup
    //   628: bipush #49
    //   630: ldc 506948616
    //   632: iastore
    //   633: dup
    //   634: bipush #50
    //   636: ldc 659060556
    //   638: iastore
    //   639: dup
    //   640: bipush #51
    //   642: ldc 883997877
    //   644: iastore
    //   645: dup
    //   646: bipush #52
    //   648: ldc 958139571
    //   650: iastore
    //   651: dup
    //   652: bipush #53
    //   654: ldc 1322822218
    //   656: iastore
    //   657: dup
    //   658: bipush #54
    //   660: ldc 1537002063
    //   662: iastore
    //   663: dup
    //   664: bipush #55
    //   666: ldc 1747873779
    //   668: iastore
    //   669: dup
    //   670: bipush #56
    //   672: ldc 1955562222
    //   674: iastore
    //   675: dup
    //   676: bipush #57
    //   678: ldc 2024104815
    //   680: iastore
    //   681: dup
    //   682: bipush #58
    //   684: ldc -2067236844
    //   686: iastore
    //   687: dup
    //   688: bipush #59
    //   690: ldc -1933114872
    //   692: iastore
    //   693: dup
    //   694: bipush #60
    //   696: ldc -1866530822
    //   698: iastore
    //   699: dup
    //   700: bipush #61
    //   702: ldc -1538233109
    //   704: iastore
    //   705: dup
    //   706: bipush #62
    //   708: ldc -1090935817
    //   710: iastore
    //   711: dup
    //   712: bipush #63
    //   714: ldc -965641998
    //   716: iastore
    //   717: astore #6
    //   719: iconst_2
    //   720: newarray int
    //   722: dup
    //   723: iconst_0
    //   724: iconst_0
    //   725: iastore
    //   726: dup
    //   727: iconst_1
    //   728: iconst_0
    //   729: iastore
    //   730: astore #7
    //   732: bipush #8
    //   734: newarray int
    //   736: dup
    //   737: iconst_0
    //   738: ldc 1779033703
    //   740: iastore
    //   741: dup
    //   742: iconst_1
    //   743: ldc -1150833019
    //   745: iastore
    //   746: dup
    //   747: iconst_2
    //   748: ldc 1013904242
    //   750: iastore
    //   751: dup
    //   752: iconst_3
    //   753: ldc -1521486534
    //   755: iastore
    //   756: dup
    //   757: iconst_4
    //   758: ldc 1359893119
    //   760: iastore
    //   761: dup
    //   762: iconst_5
    //   763: ldc -1694144372
    //   765: iastore
    //   766: dup
    //   767: bipush #6
    //   769: ldc 528734635
    //   771: iastore
    //   772: dup
    //   773: bipush #7
    //   775: ldc 1541459225
    //   777: iastore
    //   778: astore #8
    //   780: bipush #64
    //   782: newarray byte
    //   784: astore #9
    //   786: bipush #64
    //   788: newarray byte
    //   790: astore #10
    //   792: aload_3
    //   793: arraylength
    //   794: istore #11
    //   796: aload #7
    //   798: iconst_0
    //   799: iaload
    //   800: bipush #63
    //   802: iand
    //   803: istore #12
    //   805: aload #7
    //   807: iconst_0
    //   808: dup2
    //   809: iaload
    //   810: iload #11
    //   812: iadd
    //   813: iastore
    //   814: aload #7
    //   816: iconst_0
    //   817: dup2
    //   818: iaload
    //   819: iconst_m1
    //   820: iand
    //   821: iastore
    //   822: aload #7
    //   824: iconst_0
    //   825: iaload
    //   826: iload #11
    //   828: if_icmpge -> 846
    //   831: aload #7
    //   833: iconst_1
    //   834: dup2
    //   835: iaload
    //   836: iconst_1
    //   837: iadd
    //   838: iastore
    //   839: goto -> 846
    //   842: invokestatic a : (Ljava/lang/Throwable;)Ljava/lang/Throwable;
    //   845: athrow
    //   846: iconst_0
    //   847: istore #13
    //   849: iload #11
    //   851: bipush #64
    //   853: if_icmplt -> 1462
    //   856: iconst_0
    //   857: istore #14
    //   859: iload #14
    //   861: bipush #64
    //   863: if_icmpge -> 885
    //   866: aload #10
    //   868: iload #14
    //   870: aload_3
    //   871: iload #13
    //   873: iload #14
    //   875: iadd
    //   876: baload
    //   877: bastore
    //   878: iinc #14, 1
    //   881: iload_2
    //   882: ifne -> 859
    //   885: bipush #64
    //   887: newarray int
    //   889: astore #14
    //   891: bipush #8
    //   893: newarray int
    //   895: astore #15
    //   897: iconst_0
    //   898: istore #16
    //   900: iload #16
    //   902: bipush #8
    //   904: if_icmpge -> 924
    //   907: aload #15
    //   909: iload #16
    //   911: aload #8
    //   913: iload #16
    //   915: iaload
    //   916: iastore
    //   917: iinc #16, 1
    //   920: iload_2
    //   921: ifne -> 900
    //   924: iconst_0
    //   925: istore #16
    //   927: iload #16
    //   929: bipush #64
    //   931: if_icmpge -> 1422
    //   934: iload #16
    //   936: bipush #16
    //   938: if_icmpge -> 1019
    //   941: aload #14
    //   943: iload #16
    //   945: aload #10
    //   947: iconst_4
    //   948: iload #16
    //   950: imul
    //   951: baload
    //   952: sipush #255
    //   955: iand
    //   956: bipush #24
    //   958: ishl
    //   959: aload #10
    //   961: iconst_4
    //   962: iload #16
    //   964: imul
    //   965: iconst_1
    //   966: iadd
    //   967: baload
    //   968: sipush #255
    //   971: iand
    //   972: bipush #16
    //   974: ishl
    //   975: ior
    //   976: aload #10
    //   978: iconst_4
    //   979: iload #16
    //   981: imul
    //   982: iconst_2
    //   983: iadd
    //   984: baload
    //   985: sipush #255
    //   988: iand
    //   989: bipush #8
    //   991: ishl
    //   992: ior
    //   993: aload #10
    //   995: iconst_4
    //   996: iload #16
    //   998: imul
    //   999: iconst_3
    //   1000: iadd
    //   1001: baload
    //   1002: sipush #255
    //   1005: iand
    //   1006: ior
    //   1007: iastore
    //   1008: iload_2
    //   1009: ifne -> 1162
    //   1012: goto -> 1019
    //   1015: invokestatic a : (Ljava/lang/Throwable;)Ljava/lang/Throwable;
    //   1018: athrow
    //   1019: aload #14
    //   1021: iload #16
    //   1023: aload #14
    //   1025: iload #16
    //   1027: iconst_2
    //   1028: isub
    //   1029: iaload
    //   1030: bipush #17
    //   1032: iushr
    //   1033: aload #14
    //   1035: iload #16
    //   1037: iconst_2
    //   1038: isub
    //   1039: iaload
    //   1040: bipush #15
    //   1042: ishl
    //   1043: ior
    //   1044: aload #14
    //   1046: iload #16
    //   1048: iconst_2
    //   1049: isub
    //   1050: iaload
    //   1051: bipush #19
    //   1053: iushr
    //   1054: aload #14
    //   1056: iload #16
    //   1058: iconst_2
    //   1059: isub
    //   1060: iaload
    //   1061: bipush #13
    //   1063: ishl
    //   1064: ior
    //   1065: ixor
    //   1066: aload #14
    //   1068: iload #16
    //   1070: iconst_2
    //   1071: isub
    //   1072: iaload
    //   1073: bipush #10
    //   1075: iushr
    //   1076: ixor
    //   1077: aload #14
    //   1079: iload #16
    //   1081: bipush #7
    //   1083: isub
    //   1084: iaload
    //   1085: iadd
    //   1086: aload #14
    //   1088: iload #16
    //   1090: bipush #15
    //   1092: isub
    //   1093: iaload
    //   1094: bipush #7
    //   1096: iushr
    //   1097: aload #14
    //   1099: iload #16
    //   1101: bipush #15
    //   1103: isub
    //   1104: iaload
    //   1105: bipush #25
    //   1107: ishl
    //   1108: ior
    //   1109: aload #14
    //   1111: iload #16
    //   1113: bipush #15
    //   1115: isub
    //   1116: iaload
    //   1117: bipush #18
    //   1119: iushr
    //   1120: aload #14
    //   1122: iload #16
    //   1124: bipush #15
    //   1126: isub
    //   1127: iaload
    //   1128: bipush #14
    //   1130: ishl
    //   1131: ior
    //   1132: ixor
    //   1133: aload #14
    //   1135: iload #16
    //   1137: bipush #15
    //   1139: isub
    //   1140: iaload
    //   1141: iconst_3
    //   1142: iushr
    //   1143: ixor
    //   1144: iadd
    //   1145: aload #14
    //   1147: iload #16
    //   1149: bipush #16
    //   1151: isub
    //   1152: iaload
    //   1153: iadd
    //   1154: iastore
    //   1155: goto -> 1162
    //   1158: invokestatic a : (Ljava/lang/Throwable;)Ljava/lang/Throwable;
    //   1161: athrow
    //   1162: aload #15
    //   1164: bipush #7
    //   1166: iaload
    //   1167: aload #15
    //   1169: iconst_4
    //   1170: iaload
    //   1171: bipush #6
    //   1173: iushr
    //   1174: aload #15
    //   1176: iconst_4
    //   1177: iaload
    //   1178: bipush #26
    //   1180: ishl
    //   1181: ior
    //   1182: aload #15
    //   1184: iconst_4
    //   1185: iaload
    //   1186: bipush #11
    //   1188: iushr
    //   1189: aload #15
    //   1191: iconst_4
    //   1192: iaload
    //   1193: bipush #21
    //   1195: ishl
    //   1196: ior
    //   1197: ixor
    //   1198: aload #15
    //   1200: iconst_4
    //   1201: iaload
    //   1202: bipush #25
    //   1204: iushr
    //   1205: aload #15
    //   1207: iconst_4
    //   1208: iaload
    //   1209: bipush #7
    //   1211: ishl
    //   1212: ior
    //   1213: ixor
    //   1214: iadd
    //   1215: aload #15
    //   1217: bipush #6
    //   1219: iaload
    //   1220: aload #15
    //   1222: iconst_4
    //   1223: iaload
    //   1224: aload #15
    //   1226: iconst_5
    //   1227: iaload
    //   1228: aload #15
    //   1230: bipush #6
    //   1232: iaload
    //   1233: ixor
    //   1234: iand
    //   1235: ixor
    //   1236: iadd
    //   1237: aload #6
    //   1239: iload #16
    //   1241: iaload
    //   1242: iadd
    //   1243: aload #14
    //   1245: iload #16
    //   1247: iaload
    //   1248: iadd
    //   1249: istore #17
    //   1251: aload #15
    //   1253: iconst_0
    //   1254: iaload
    //   1255: iconst_2
    //   1256: iushr
    //   1257: aload #15
    //   1259: iconst_0
    //   1260: iaload
    //   1261: bipush #30
    //   1263: ishl
    //   1264: ior
    //   1265: aload #15
    //   1267: iconst_0
    //   1268: iaload
    //   1269: bipush #13
    //   1271: iushr
    //   1272: aload #15
    //   1274: iconst_0
    //   1275: iaload
    //   1276: bipush #19
    //   1278: ishl
    //   1279: ior
    //   1280: ixor
    //   1281: aload #15
    //   1283: iconst_0
    //   1284: iaload
    //   1285: bipush #22
    //   1287: iushr
    //   1288: aload #15
    //   1290: iconst_0
    //   1291: iaload
    //   1292: bipush #10
    //   1294: ishl
    //   1295: ior
    //   1296: ixor
    //   1297: aload #15
    //   1299: iconst_0
    //   1300: iaload
    //   1301: aload #15
    //   1303: iconst_1
    //   1304: iaload
    //   1305: iand
    //   1306: aload #15
    //   1308: iconst_2
    //   1309: iaload
    //   1310: aload #15
    //   1312: iconst_0
    //   1313: iaload
    //   1314: aload #15
    //   1316: iconst_1
    //   1317: iaload
    //   1318: ior
    //   1319: iand
    //   1320: ior
    //   1321: iadd
    //   1322: istore #18
    //   1324: aload #15
    //   1326: iconst_3
    //   1327: dup2
    //   1328: iaload
    //   1329: iload #17
    //   1331: iadd
    //   1332: iastore
    //   1333: aload #15
    //   1335: bipush #7
    //   1337: iload #17
    //   1339: iload #18
    //   1341: iadd
    //   1342: iastore
    //   1343: aload #15
    //   1345: bipush #7
    //   1347: iaload
    //   1348: istore #17
    //   1350: aload #15
    //   1352: bipush #7
    //   1354: aload #15
    //   1356: bipush #6
    //   1358: iaload
    //   1359: iastore
    //   1360: aload #15
    //   1362: bipush #6
    //   1364: aload #15
    //   1366: iconst_5
    //   1367: iaload
    //   1368: iastore
    //   1369: aload #15
    //   1371: iconst_5
    //   1372: aload #15
    //   1374: iconst_4
    //   1375: iaload
    //   1376: iastore
    //   1377: aload #15
    //   1379: iconst_4
    //   1380: aload #15
    //   1382: iconst_3
    //   1383: iaload
    //   1384: iastore
    //   1385: aload #15
    //   1387: iconst_3
    //   1388: aload #15
    //   1390: iconst_2
    //   1391: iaload
    //   1392: iastore
    //   1393: aload #15
    //   1395: iconst_2
    //   1396: aload #15
    //   1398: iconst_1
    //   1399: iaload
    //   1400: iastore
    //   1401: aload #15
    //   1403: iconst_1
    //   1404: aload #15
    //   1406: iconst_0
    //   1407: iaload
    //   1408: iastore
    //   1409: aload #15
    //   1411: iconst_0
    //   1412: iload #17
    //   1414: iastore
    //   1415: iinc #16, 1
    //   1418: iload_2
    //   1419: ifne -> 927
    //   1422: iconst_0
    //   1423: istore #16
    //   1425: iload #16
    //   1427: bipush #8
    //   1429: if_icmpge -> 1452
    //   1432: aload #8
    //   1434: iload #16
    //   1436: dup2
    //   1437: iaload
    //   1438: aload #15
    //   1440: iload #16
    //   1442: iaload
    //   1443: iadd
    //   1444: iastore
    //   1445: iinc #16, 1
    //   1448: iload_2
    //   1449: ifne -> 1425
    //   1452: iinc #13, 64
    //   1455: iinc #11, -64
    //   1458: iload_2
    //   1459: ifne -> 849
    //   1462: iload #11
    //   1464: ifle -> 1499
    //   1467: iconst_0
    //   1468: istore #14
    //   1470: iload #14
    //   1472: iload #11
    //   1474: if_icmpge -> 1499
    //   1477: aload #9
    //   1479: iload #12
    //   1481: iload #14
    //   1483: iadd
    //   1484: aload_3
    //   1485: iload #13
    //   1487: iload #14
    //   1489: iadd
    //   1490: baload
    //   1491: bastore
    //   1492: iinc #14, 1
    //   1495: iload_2
    //   1496: ifne -> 1470
    //   1499: aload #7
    //   1501: iconst_0
    //   1502: iaload
    //   1503: bipush #29
    //   1505: iushr
    //   1506: aload #7
    //   1508: iconst_1
    //   1509: iaload
    //   1510: iconst_3
    //   1511: ishl
    //   1512: ior
    //   1513: istore #14
    //   1515: aload #7
    //   1517: iconst_0
    //   1518: iaload
    //   1519: iconst_3
    //   1520: ishl
    //   1521: istore #15
    //   1523: aload #7
    //   1525: iconst_0
    //   1526: iaload
    //   1527: bipush #63
    //   1529: iand
    //   1530: istore #16
    //   1532: iload #16
    //   1534: bipush #56
    //   1536: if_icmpge -> 1551
    //   1539: bipush #56
    //   1541: iload #16
    //   1543: isub
    //   1544: goto -> 1556
    //   1547: invokestatic a : (Ljava/lang/Throwable;)Ljava/lang/Throwable;
    //   1550: athrow
    //   1551: bipush #120
    //   1553: iload #16
    //   1555: isub
    //   1556: istore #17
    //   1558: aload #7
    //   1560: iconst_0
    //   1561: iaload
    //   1562: bipush #63
    //   1564: iand
    //   1565: istore #12
    //   1567: bipush #64
    //   1569: iload #12
    //   1571: isub
    //   1572: istore #18
    //   1574: aload #7
    //   1576: iconst_0
    //   1577: dup2
    //   1578: iaload
    //   1579: iload #17
    //   1581: iadd
    //   1582: iastore
    //   1583: aload #7
    //   1585: iconst_0
    //   1586: dup2
    //   1587: iaload
    //   1588: iconst_m1
    //   1589: iand
    //   1590: iastore
    //   1591: aload #7
    //   1593: iconst_0
    //   1594: iaload
    //   1595: iload #17
    //   1597: if_icmpge -> 1615
    //   1600: aload #7
    //   1602: iconst_1
    //   1603: dup2
    //   1604: iaload
    //   1605: iconst_1
    //   1606: iadd
    //   1607: iastore
    //   1608: goto -> 1615
    //   1611: invokestatic a : (Ljava/lang/Throwable;)Ljava/lang/Throwable;
    //   1614: athrow
    //   1615: iconst_0
    //   1616: istore #13
    //   1618: iload #12
    //   1620: ifle -> 2251
    //   1623: iload #17
    //   1625: iload #18
    //   1627: if_icmplt -> 2251
    //   1630: goto -> 1637
    //   1633: invokestatic a : (Ljava/lang/Throwable;)Ljava/lang/Throwable;
    //   1636: athrow
    //   1637: iconst_0
    //   1638: istore #19
    //   1640: iload #19
    //   1642: iload #18
    //   1644: if_icmpge -> 1667
    //   1647: aload #9
    //   1649: iload #12
    //   1651: iload #19
    //   1653: iadd
    //   1654: aload #5
    //   1656: iload #19
    //   1658: baload
    //   1659: bastore
    //   1660: iinc #19, 1
    //   1663: iload_2
    //   1664: ifne -> 1640
    //   1667: bipush #64
    //   1669: newarray int
    //   1671: astore #19
    //   1673: bipush #8
    //   1675: newarray int
    //   1677: astore #20
    //   1679: iconst_0
    //   1680: istore #21
    //   1682: iload #21
    //   1684: bipush #8
    //   1686: if_icmpge -> 1706
    //   1689: aload #20
    //   1691: iload #21
    //   1693: aload #8
    //   1695: iload #21
    //   1697: iaload
    //   1698: iastore
    //   1699: iinc #21, 1
    //   1702: iload_2
    //   1703: ifne -> 1682
    //   1706: iconst_0
    //   1707: istore #21
    //   1709: iload #21
    //   1711: bipush #64
    //   1713: if_icmpge -> 2204
    //   1716: iload #21
    //   1718: bipush #16
    //   1720: if_icmpge -> 1801
    //   1723: aload #19
    //   1725: iload #21
    //   1727: aload #9
    //   1729: iconst_4
    //   1730: iload #21
    //   1732: imul
    //   1733: baload
    //   1734: sipush #255
    //   1737: iand
    //   1738: bipush #24
    //   1740: ishl
    //   1741: aload #9
    //   1743: iconst_4
    //   1744: iload #21
    //   1746: imul
    //   1747: iconst_1
    //   1748: iadd
    //   1749: baload
    //   1750: sipush #255
    //   1753: iand
    //   1754: bipush #16
    //   1756: ishl
    //   1757: ior
    //   1758: aload #9
    //   1760: iconst_4
    //   1761: iload #21
    //   1763: imul
    //   1764: iconst_2
    //   1765: iadd
    //   1766: baload
    //   1767: sipush #255
    //   1770: iand
    //   1771: bipush #8
    //   1773: ishl
    //   1774: ior
    //   1775: aload #9
    //   1777: iconst_4
    //   1778: iload #21
    //   1780: imul
    //   1781: iconst_3
    //   1782: iadd
    //   1783: baload
    //   1784: sipush #255
    //   1787: iand
    //   1788: ior
    //   1789: iastore
    //   1790: iload_2
    //   1791: ifne -> 1944
    //   1794: goto -> 1801
    //   1797: invokestatic a : (Ljava/lang/Throwable;)Ljava/lang/Throwable;
    //   1800: athrow
    //   1801: aload #19
    //   1803: iload #21
    //   1805: aload #19
    //   1807: iload #21
    //   1809: iconst_2
    //   1810: isub
    //   1811: iaload
    //   1812: bipush #17
    //   1814: iushr
    //   1815: aload #19
    //   1817: iload #21
    //   1819: iconst_2
    //   1820: isub
    //   1821: iaload
    //   1822: bipush #15
    //   1824: ishl
    //   1825: ior
    //   1826: aload #19
    //   1828: iload #21
    //   1830: iconst_2
    //   1831: isub
    //   1832: iaload
    //   1833: bipush #19
    //   1835: iushr
    //   1836: aload #19
    //   1838: iload #21
    //   1840: iconst_2
    //   1841: isub
    //   1842: iaload
    //   1843: bipush #13
    //   1845: ishl
    //   1846: ior
    //   1847: ixor
    //   1848: aload #19
    //   1850: iload #21
    //   1852: iconst_2
    //   1853: isub
    //   1854: iaload
    //   1855: bipush #10
    //   1857: iushr
    //   1858: ixor
    //   1859: aload #19
    //   1861: iload #21
    //   1863: bipush #7
    //   1865: isub
    //   1866: iaload
    //   1867: iadd
    //   1868: aload #19
    //   1870: iload #21
    //   1872: bipush #15
    //   1874: isub
    //   1875: iaload
    //   1876: bipush #7
    //   1878: iushr
    //   1879: aload #19
    //   1881: iload #21
    //   1883: bipush #15
    //   1885: isub
    //   1886: iaload
    //   1887: bipush #25
    //   1889: ishl
    //   1890: ior
    //   1891: aload #19
    //   1893: iload #21
    //   1895: bipush #15
    //   1897: isub
    //   1898: iaload
    //   1899: bipush #18
    //   1901: iushr
    //   1902: aload #19
    //   1904: iload #21
    //   1906: bipush #15
    //   1908: isub
    //   1909: iaload
    //   1910: bipush #14
    //   1912: ishl
    //   1913: ior
    //   1914: ixor
    //   1915: aload #19
    //   1917: iload #21
    //   1919: bipush #15
    //   1921: isub
    //   1922: iaload
    //   1923: iconst_3
    //   1924: iushr
    //   1925: ixor
    //   1926: iadd
    //   1927: aload #19
    //   1929: iload #21
    //   1931: bipush #16
    //   1933: isub
    //   1934: iaload
    //   1935: iadd
    //   1936: iastore
    //   1937: goto -> 1944
    //   1940: invokestatic a : (Ljava/lang/Throwable;)Ljava/lang/Throwable;
    //   1943: athrow
    //   1944: aload #20
    //   1946: bipush #7
    //   1948: iaload
    //   1949: aload #20
    //   1951: iconst_4
    //   1952: iaload
    //   1953: bipush #6
    //   1955: iushr
    //   1956: aload #20
    //   1958: iconst_4
    //   1959: iaload
    //   1960: bipush #26
    //   1962: ishl
    //   1963: ior
    //   1964: aload #20
    //   1966: iconst_4
    //   1967: iaload
    //   1968: bipush #11
    //   1970: iushr
    //   1971: aload #20
    //   1973: iconst_4
    //   1974: iaload
    //   1975: bipush #21
    //   1977: ishl
    //   1978: ior
    //   1979: ixor
    //   1980: aload #20
    //   1982: iconst_4
    //   1983: iaload
    //   1984: bipush #25
    //   1986: iushr
    //   1987: aload #20
    //   1989: iconst_4
    //   1990: iaload
    //   1991: bipush #7
    //   1993: ishl
    //   1994: ior
    //   1995: ixor
    //   1996: iadd
    //   1997: aload #20
    //   1999: bipush #6
    //   2001: iaload
    //   2002: aload #20
    //   2004: iconst_4
    //   2005: iaload
    //   2006: aload #20
    //   2008: iconst_5
    //   2009: iaload
    //   2010: aload #20
    //   2012: bipush #6
    //   2014: iaload
    //   2015: ixor
    //   2016: iand
    //   2017: ixor
    //   2018: iadd
    //   2019: aload #6
    //   2021: iload #21
    //   2023: iaload
    //   2024: iadd
    //   2025: aload #19
    //   2027: iload #21
    //   2029: iaload
    //   2030: iadd
    //   2031: istore #22
    //   2033: aload #20
    //   2035: iconst_0
    //   2036: iaload
    //   2037: iconst_2
    //   2038: iushr
    //   2039: aload #20
    //   2041: iconst_0
    //   2042: iaload
    //   2043: bipush #30
    //   2045: ishl
    //   2046: ior
    //   2047: aload #20
    //   2049: iconst_0
    //   2050: iaload
    //   2051: bipush #13
    //   2053: iushr
    //   2054: aload #20
    //   2056: iconst_0
    //   2057: iaload
    //   2058: bipush #19
    //   2060: ishl
    //   2061: ior
    //   2062: ixor
    //   2063: aload #20
    //   2065: iconst_0
    //   2066: iaload
    //   2067: bipush #22
    //   2069: iushr
    //   2070: aload #20
    //   2072: iconst_0
    //   2073: iaload
    //   2074: bipush #10
    //   2076: ishl
    //   2077: ior
    //   2078: ixor
    //   2079: aload #20
    //   2081: iconst_0
    //   2082: iaload
    //   2083: aload #20
    //   2085: iconst_1
    //   2086: iaload
    //   2087: iand
    //   2088: aload #20
    //   2090: iconst_2
    //   2091: iaload
    //   2092: aload #20
    //   2094: iconst_0
    //   2095: iaload
    //   2096: aload #20
    //   2098: iconst_1
    //   2099: iaload
    //   2100: ior
    //   2101: iand
    //   2102: ior
    //   2103: iadd
    //   2104: istore #23
    //   2106: aload #20
    //   2108: iconst_3
    //   2109: dup2
    //   2110: iaload
    //   2111: iload #22
    //   2113: iadd
    //   2114: iastore
    //   2115: aload #20
    //   2117: bipush #7
    //   2119: iload #22
    //   2121: iload #23
    //   2123: iadd
    //   2124: iastore
    //   2125: aload #20
    //   2127: bipush #7
    //   2129: iaload
    //   2130: istore #22
    //   2132: aload #20
    //   2134: bipush #7
    //   2136: aload #20
    //   2138: bipush #6
    //   2140: iaload
    //   2141: iastore
    //   2142: aload #20
    //   2144: bipush #6
    //   2146: aload #20
    //   2148: iconst_5
    //   2149: iaload
    //   2150: iastore
    //   2151: aload #20
    //   2153: iconst_5
    //   2154: aload #20
    //   2156: iconst_4
    //   2157: iaload
    //   2158: iastore
    //   2159: aload #20
    //   2161: iconst_4
    //   2162: aload #20
    //   2164: iconst_3
    //   2165: iaload
    //   2166: iastore
    //   2167: aload #20
    //   2169: iconst_3
    //   2170: aload #20
    //   2172: iconst_2
    //   2173: iaload
    //   2174: iastore
    //   2175: aload #20
    //   2177: iconst_2
    //   2178: aload #20
    //   2180: iconst_1
    //   2181: iaload
    //   2182: iastore
    //   2183: aload #20
    //   2185: iconst_1
    //   2186: aload #20
    //   2188: iconst_0
    //   2189: iaload
    //   2190: iastore
    //   2191: aload #20
    //   2193: iconst_0
    //   2194: iload #22
    //   2196: iastore
    //   2197: iinc #21, 1
    //   2200: iload_2
    //   2201: ifne -> 1709
    //   2204: iconst_0
    //   2205: istore #21
    //   2207: iload #21
    //   2209: bipush #8
    //   2211: if_icmpge -> 2234
    //   2214: aload #8
    //   2216: iload #21
    //   2218: dup2
    //   2219: iaload
    //   2220: aload #20
    //   2222: iload #21
    //   2224: iaload
    //   2225: iadd
    //   2226: iastore
    //   2227: iinc #21, 1
    //   2230: iload_2
    //   2231: ifne -> 2207
    //   2234: iload #13
    //   2236: iload #18
    //   2238: iadd
    //   2239: istore #13
    //   2241: iload #17
    //   2243: iload #18
    //   2245: isub
    //   2246: istore #17
    //   2248: iconst_0
    //   2249: istore #12
    //   2251: iload #17
    //   2253: bipush #64
    //   2255: if_icmplt -> 2865
    //   2258: iconst_0
    //   2259: istore #19
    //   2261: iload #19
    //   2263: bipush #64
    //   2265: if_icmpge -> 2288
    //   2268: aload #10
    //   2270: iload #19
    //   2272: aload #5
    //   2274: iload #13
    //   2276: iload #19
    //   2278: iadd
    //   2279: baload
    //   2280: bastore
    //   2281: iinc #19, 1
    //   2284: iload_2
    //   2285: ifne -> 2261
    //   2288: bipush #64
    //   2290: newarray int
    //   2292: astore #19
    //   2294: bipush #8
    //   2296: newarray int
    //   2298: astore #20
    //   2300: iconst_0
    //   2301: istore #21
    //   2303: iload #21
    //   2305: bipush #8
    //   2307: if_icmpge -> 2327
    //   2310: aload #20
    //   2312: iload #21
    //   2314: aload #8
    //   2316: iload #21
    //   2318: iaload
    //   2319: iastore
    //   2320: iinc #21, 1
    //   2323: iload_2
    //   2324: ifne -> 2303
    //   2327: iconst_0
    //   2328: istore #21
    //   2330: iload #21
    //   2332: bipush #64
    //   2334: if_icmpge -> 2825
    //   2337: iload #21
    //   2339: bipush #16
    //   2341: if_icmpge -> 2422
    //   2344: aload #19
    //   2346: iload #21
    //   2348: aload #10
    //   2350: iconst_4
    //   2351: iload #21
    //   2353: imul
    //   2354: baload
    //   2355: sipush #255
    //   2358: iand
    //   2359: bipush #24
    //   2361: ishl
    //   2362: aload #10
    //   2364: iconst_4
    //   2365: iload #21
    //   2367: imul
    //   2368: iconst_1
    //   2369: iadd
    //   2370: baload
    //   2371: sipush #255
    //   2374: iand
    //   2375: bipush #16
    //   2377: ishl
    //   2378: ior
    //   2379: aload #10
    //   2381: iconst_4
    //   2382: iload #21
    //   2384: imul
    //   2385: iconst_2
    //   2386: iadd
    //   2387: baload
    //   2388: sipush #255
    //   2391: iand
    //   2392: bipush #8
    //   2394: ishl
    //   2395: ior
    //   2396: aload #10
    //   2398: iconst_4
    //   2399: iload #21
    //   2401: imul
    //   2402: iconst_3
    //   2403: iadd
    //   2404: baload
    //   2405: sipush #255
    //   2408: iand
    //   2409: ior
    //   2410: iastore
    //   2411: iload_2
    //   2412: ifne -> 2565
    //   2415: goto -> 2422
    //   2418: invokestatic a : (Ljava/lang/Throwable;)Ljava/lang/Throwable;
    //   2421: athrow
    //   2422: aload #19
    //   2424: iload #21
    //   2426: aload #19
    //   2428: iload #21
    //   2430: iconst_2
    //   2431: isub
    //   2432: iaload
    //   2433: bipush #17
    //   2435: iushr
    //   2436: aload #19
    //   2438: iload #21
    //   2440: iconst_2
    //   2441: isub
    //   2442: iaload
    //   2443: bipush #15
    //   2445: ishl
    //   2446: ior
    //   2447: aload #19
    //   2449: iload #21
    //   2451: iconst_2
    //   2452: isub
    //   2453: iaload
    //   2454: bipush #19
    //   2456: iushr
    //   2457: aload #19
    //   2459: iload #21
    //   2461: iconst_2
    //   2462: isub
    //   2463: iaload
    //   2464: bipush #13
    //   2466: ishl
    //   2467: ior
    //   2468: ixor
    //   2469: aload #19
    //   2471: iload #21
    //   2473: iconst_2
    //   2474: isub
    //   2475: iaload
    //   2476: bipush #10
    //   2478: iushr
    //   2479: ixor
    //   2480: aload #19
    //   2482: iload #21
    //   2484: bipush #7
    //   2486: isub
    //   2487: iaload
    //   2488: iadd
    //   2489: aload #19
    //   2491: iload #21
    //   2493: bipush #15
    //   2495: isub
    //   2496: iaload
    //   2497: bipush #7
    //   2499: iushr
    //   2500: aload #19
    //   2502: iload #21
    //   2504: bipush #15
    //   2506: isub
    //   2507: iaload
    //   2508: bipush #25
    //   2510: ishl
    //   2511: ior
    //   2512: aload #19
    //   2514: iload #21
    //   2516: bipush #15
    //   2518: isub
    //   2519: iaload
    //   2520: bipush #18
    //   2522: iushr
    //   2523: aload #19
    //   2525: iload #21
    //   2527: bipush #15
    //   2529: isub
    //   2530: iaload
    //   2531: bipush #14
    //   2533: ishl
    //   2534: ior
    //   2535: ixor
    //   2536: aload #19
    //   2538: iload #21
    //   2540: bipush #15
    //   2542: isub
    //   2543: iaload
    //   2544: iconst_3
    //   2545: iushr
    //   2546: ixor
    //   2547: iadd
    //   2548: aload #19
    //   2550: iload #21
    //   2552: bipush #16
    //   2554: isub
    //   2555: iaload
    //   2556: iadd
    //   2557: iastore
    //   2558: goto -> 2565
    //   2561: invokestatic a : (Ljava/lang/Throwable;)Ljava/lang/Throwable;
    //   2564: athrow
    //   2565: aload #20
    //   2567: bipush #7
    //   2569: iaload
    //   2570: aload #20
    //   2572: iconst_4
    //   2573: iaload
    //   2574: bipush #6
    //   2576: iushr
    //   2577: aload #20
    //   2579: iconst_4
    //   2580: iaload
    //   2581: bipush #26
    //   2583: ishl
    //   2584: ior
    //   2585: aload #20
    //   2587: iconst_4
    //   2588: iaload
    //   2589: bipush #11
    //   2591: iushr
    //   2592: aload #20
    //   2594: iconst_4
    //   2595: iaload
    //   2596: bipush #21
    //   2598: ishl
    //   2599: ior
    //   2600: ixor
    //   2601: aload #20
    //   2603: iconst_4
    //   2604: iaload
    //   2605: bipush #25
    //   2607: iushr
    //   2608: aload #20
    //   2610: iconst_4
    //   2611: iaload
    //   2612: bipush #7
    //   2614: ishl
    //   2615: ior
    //   2616: ixor
    //   2617: iadd
    //   2618: aload #20
    //   2620: bipush #6
    //   2622: iaload
    //   2623: aload #20
    //   2625: iconst_4
    //   2626: iaload
    //   2627: aload #20
    //   2629: iconst_5
    //   2630: iaload
    //   2631: aload #20
    //   2633: bipush #6
    //   2635: iaload
    //   2636: ixor
    //   2637: iand
    //   2638: ixor
    //   2639: iadd
    //   2640: aload #6
    //   2642: iload #21
    //   2644: iaload
    //   2645: iadd
    //   2646: aload #19
    //   2648: iload #21
    //   2650: iaload
    //   2651: iadd
    //   2652: istore #22
    //   2654: aload #20
    //   2656: iconst_0
    //   2657: iaload
    //   2658: iconst_2
    //   2659: iushr
    //   2660: aload #20
    //   2662: iconst_0
    //   2663: iaload
    //   2664: bipush #30
    //   2666: ishl
    //   2667: ior
    //   2668: aload #20
    //   2670: iconst_0
    //   2671: iaload
    //   2672: bipush #13
    //   2674: iushr
    //   2675: aload #20
    //   2677: iconst_0
    //   2678: iaload
    //   2679: bipush #19
    //   2681: ishl
    //   2682: ior
    //   2683: ixor
    //   2684: aload #20
    //   2686: iconst_0
    //   2687: iaload
    //   2688: bipush #22
    //   2690: iushr
    //   2691: aload #20
    //   2693: iconst_0
    //   2694: iaload
    //   2695: bipush #10
    //   2697: ishl
    //   2698: ior
    //   2699: ixor
    //   2700: aload #20
    //   2702: iconst_0
    //   2703: iaload
    //   2704: aload #20
    //   2706: iconst_1
    //   2707: iaload
    //   2708: iand
    //   2709: aload #20
    //   2711: iconst_2
    //   2712: iaload
    //   2713: aload #20
    //   2715: iconst_0
    //   2716: iaload
    //   2717: aload #20
    //   2719: iconst_1
    //   2720: iaload
    //   2721: ior
    //   2722: iand
    //   2723: ior
    //   2724: iadd
    //   2725: istore #23
    //   2727: aload #20
    //   2729: iconst_3
    //   2730: dup2
    //   2731: iaload
    //   2732: iload #22
    //   2734: iadd
    //   2735: iastore
    //   2736: aload #20
    //   2738: bipush #7
    //   2740: iload #22
    //   2742: iload #23
    //   2744: iadd
    //   2745: iastore
    //   2746: aload #20
    //   2748: bipush #7
    //   2750: iaload
    //   2751: istore #22
    //   2753: aload #20
    //   2755: bipush #7
    //   2757: aload #20
    //   2759: bipush #6
    //   2761: iaload
    //   2762: iastore
    //   2763: aload #20
    //   2765: bipush #6
    //   2767: aload #20
    //   2769: iconst_5
    //   2770: iaload
    //   2771: iastore
    //   2772: aload #20
    //   2774: iconst_5
    //   2775: aload #20
    //   2777: iconst_4
    //   2778: iaload
    //   2779: iastore
    //   2780: aload #20
    //   2782: iconst_4
    //   2783: aload #20
    //   2785: iconst_3
    //   2786: iaload
    //   2787: iastore
    //   2788: aload #20
    //   2790: iconst_3
    //   2791: aload #20
    //   2793: iconst_2
    //   2794: iaload
    //   2795: iastore
    //   2796: aload #20
    //   2798: iconst_2
    //   2799: aload #20
    //   2801: iconst_1
    //   2802: iaload
    //   2803: iastore
    //   2804: aload #20
    //   2806: iconst_1
    //   2807: aload #20
    //   2809: iconst_0
    //   2810: iaload
    //   2811: iastore
    //   2812: aload #20
    //   2814: iconst_0
    //   2815: iload #22
    //   2817: iastore
    //   2818: iinc #21, 1
    //   2821: iload_2
    //   2822: ifne -> 2330
    //   2825: iconst_0
    //   2826: istore #21
    //   2828: iload #21
    //   2830: bipush #8
    //   2832: if_icmpge -> 2855
    //   2835: aload #8
    //   2837: iload #21
    //   2839: dup2
    //   2840: iaload
    //   2841: aload #20
    //   2843: iload #21
    //   2845: iaload
    //   2846: iadd
    //   2847: iastore
    //   2848: iinc #21, 1
    //   2851: iload_2
    //   2852: ifne -> 2828
    //   2855: iinc #13, 64
    //   2858: iinc #17, -64
    //   2861: iload_2
    //   2862: ifne -> 2251
    //   2865: iload #17
    //   2867: ifle -> 2903
    //   2870: iconst_0
    //   2871: istore #19
    //   2873: iload #19
    //   2875: iload #17
    //   2877: if_icmpge -> 2903
    //   2880: aload #9
    //   2882: iload #12
    //   2884: iload #19
    //   2886: iadd
    //   2887: aload #5
    //   2889: iload #13
    //   2891: iload #19
    //   2893: iadd
    //   2894: baload
    //   2895: bastore
    //   2896: iinc #19, 1
    //   2899: iload_2
    //   2900: ifne -> 2873
    //   2903: bipush #8
    //   2905: newarray byte
    //   2907: astore #19
    //   2909: aload #19
    //   2911: iconst_0
    //   2912: iload #14
    //   2914: bipush #24
    //   2916: iushr
    //   2917: i2b
    //   2918: bastore
    //   2919: aload #19
    //   2921: iconst_1
    //   2922: iload #14
    //   2924: bipush #16
    //   2926: iushr
    //   2927: i2b
    //   2928: bastore
    //   2929: aload #19
    //   2931: iconst_2
    //   2932: iload #14
    //   2934: bipush #8
    //   2936: iushr
    //   2937: i2b
    //   2938: bastore
    //   2939: aload #19
    //   2941: iconst_3
    //   2942: iload #14
    //   2944: i2b
    //   2945: bastore
    //   2946: aload #19
    //   2948: iconst_4
    //   2949: iload #15
    //   2951: bipush #24
    //   2953: iushr
    //   2954: i2b
    //   2955: bastore
    //   2956: aload #19
    //   2958: iconst_5
    //   2959: iload #15
    //   2961: bipush #16
    //   2963: iushr
    //   2964: i2b
    //   2965: bastore
    //   2966: aload #19
    //   2968: bipush #6
    //   2970: iload #15
    //   2972: bipush #8
    //   2974: iushr
    //   2975: i2b
    //   2976: bastore
    //   2977: aload #19
    //   2979: bipush #7
    //   2981: iload #15
    //   2983: i2b
    //   2984: bastore
    //   2985: bipush #8
    //   2987: istore #11
    //   2989: aload #7
    //   2991: iconst_0
    //   2992: iaload
    //   2993: bipush #63
    //   2995: iand
    //   2996: istore #12
    //   2998: bipush #64
    //   3000: iload #12
    //   3002: isub
    //   3003: istore #18
    //   3005: aload #7
    //   3007: iconst_0
    //   3008: dup2
    //   3009: iaload
    //   3010: iload #11
    //   3012: iadd
    //   3013: iastore
    //   3014: aload #7
    //   3016: iconst_0
    //   3017: dup2
    //   3018: iaload
    //   3019: iconst_m1
    //   3020: iand
    //   3021: iastore
    //   3022: aload #7
    //   3024: iconst_0
    //   3025: iaload
    //   3026: iload #11
    //   3028: if_icmpge -> 3046
    //   3031: aload #7
    //   3033: iconst_1
    //   3034: dup2
    //   3035: iaload
    //   3036: iconst_1
    //   3037: iadd
    //   3038: iastore
    //   3039: goto -> 3046
    //   3042: invokestatic a : (Ljava/lang/Throwable;)Ljava/lang/Throwable;
    //   3045: athrow
    //   3046: iload #12
    //   3048: ifle -> 3662
    //   3051: iload #11
    //   3053: iload #18
    //   3055: if_icmplt -> 3662
    //   3058: goto -> 3065
    //   3061: invokestatic a : (Ljava/lang/Throwable;)Ljava/lang/Throwable;
    //   3064: athrow
    //   3065: iconst_0
    //   3066: istore #20
    //   3068: iload #20
    //   3070: iload #18
    //   3072: if_icmpge -> 3095
    //   3075: aload #9
    //   3077: iload #12
    //   3079: iload #20
    //   3081: iadd
    //   3082: aload #19
    //   3084: iload #20
    //   3086: baload
    //   3087: bastore
    //   3088: iinc #20, 1
    //   3091: iload_2
    //   3092: ifne -> 3068
    //   3095: bipush #64
    //   3097: newarray int
    //   3099: astore #20
    //   3101: bipush #8
    //   3103: newarray int
    //   3105: astore #21
    //   3107: iconst_0
    //   3108: istore #22
    //   3110: iload #22
    //   3112: bipush #8
    //   3114: if_icmpge -> 3134
    //   3117: aload #21
    //   3119: iload #22
    //   3121: aload #8
    //   3123: iload #22
    //   3125: iaload
    //   3126: iastore
    //   3127: iinc #22, 1
    //   3130: iload_2
    //   3131: ifne -> 3110
    //   3134: iconst_0
    //   3135: istore #22
    //   3137: iload #22
    //   3139: bipush #64
    //   3141: if_icmpge -> 3632
    //   3144: iload #22
    //   3146: bipush #16
    //   3148: if_icmpge -> 3229
    //   3151: aload #20
    //   3153: iload #22
    //   3155: aload #9
    //   3157: iconst_4
    //   3158: iload #22
    //   3160: imul
    //   3161: baload
    //   3162: sipush #255
    //   3165: iand
    //   3166: bipush #24
    //   3168: ishl
    //   3169: aload #9
    //   3171: iconst_4
    //   3172: iload #22
    //   3174: imul
    //   3175: iconst_1
    //   3176: iadd
    //   3177: baload
    //   3178: sipush #255
    //   3181: iand
    //   3182: bipush #16
    //   3184: ishl
    //   3185: ior
    //   3186: aload #9
    //   3188: iconst_4
    //   3189: iload #22
    //   3191: imul
    //   3192: iconst_2
    //   3193: iadd
    //   3194: baload
    //   3195: sipush #255
    //   3198: iand
    //   3199: bipush #8
    //   3201: ishl
    //   3202: ior
    //   3203: aload #9
    //   3205: iconst_4
    //   3206: iload #22
    //   3208: imul
    //   3209: iconst_3
    //   3210: iadd
    //   3211: baload
    //   3212: sipush #255
    //   3215: iand
    //   3216: ior
    //   3217: iastore
    //   3218: iload_2
    //   3219: ifne -> 3372
    //   3222: goto -> 3229
    //   3225: invokestatic a : (Ljava/lang/Throwable;)Ljava/lang/Throwable;
    //   3228: athrow
    //   3229: aload #20
    //   3231: iload #22
    //   3233: aload #20
    //   3235: iload #22
    //   3237: iconst_2
    //   3238: isub
    //   3239: iaload
    //   3240: bipush #17
    //   3242: iushr
    //   3243: aload #20
    //   3245: iload #22
    //   3247: iconst_2
    //   3248: isub
    //   3249: iaload
    //   3250: bipush #15
    //   3252: ishl
    //   3253: ior
    //   3254: aload #20
    //   3256: iload #22
    //   3258: iconst_2
    //   3259: isub
    //   3260: iaload
    //   3261: bipush #19
    //   3263: iushr
    //   3264: aload #20
    //   3266: iload #22
    //   3268: iconst_2
    //   3269: isub
    //   3270: iaload
    //   3271: bipush #13
    //   3273: ishl
    //   3274: ior
    //   3275: ixor
    //   3276: aload #20
    //   3278: iload #22
    //   3280: iconst_2
    //   3281: isub
    //   3282: iaload
    //   3283: bipush #10
    //   3285: iushr
    //   3286: ixor
    //   3287: aload #20
    //   3289: iload #22
    //   3291: bipush #7
    //   3293: isub
    //   3294: iaload
    //   3295: iadd
    //   3296: aload #20
    //   3298: iload #22
    //   3300: bipush #15
    //   3302: isub
    //   3303: iaload
    //   3304: bipush #7
    //   3306: iushr
    //   3307: aload #20
    //   3309: iload #22
    //   3311: bipush #15
    //   3313: isub
    //   3314: iaload
    //   3315: bipush #25
    //   3317: ishl
    //   3318: ior
    //   3319: aload #20
    //   3321: iload #22
    //   3323: bipush #15
    //   3325: isub
    //   3326: iaload
    //   3327: bipush #18
    //   3329: iushr
    //   3330: aload #20
    //   3332: iload #22
    //   3334: bipush #15
    //   3336: isub
    //   3337: iaload
    //   3338: bipush #14
    //   3340: ishl
    //   3341: ior
    //   3342: ixor
    //   3343: aload #20
    //   3345: iload #22
    //   3347: bipush #15
    //   3349: isub
    //   3350: iaload
    //   3351: iconst_3
    //   3352: iushr
    //   3353: ixor
    //   3354: iadd
    //   3355: aload #20
    //   3357: iload #22
    //   3359: bipush #16
    //   3361: isub
    //   3362: iaload
    //   3363: iadd
    //   3364: iastore
    //   3365: goto -> 3372
    //   3368: invokestatic a : (Ljava/lang/Throwable;)Ljava/lang/Throwable;
    //   3371: athrow
    //   3372: aload #21
    //   3374: bipush #7
    //   3376: iaload
    //   3377: aload #21
    //   3379: iconst_4
    //   3380: iaload
    //   3381: bipush #6
    //   3383: iushr
    //   3384: aload #21
    //   3386: iconst_4
    //   3387: iaload
    //   3388: bipush #26
    //   3390: ishl
    //   3391: ior
    //   3392: aload #21
    //   3394: iconst_4
    //   3395: iaload
    //   3396: bipush #11
    //   3398: iushr
    //   3399: aload #21
    //   3401: iconst_4
    //   3402: iaload
    //   3403: bipush #21
    //   3405: ishl
    //   3406: ior
    //   3407: ixor
    //   3408: aload #21
    //   3410: iconst_4
    //   3411: iaload
    //   3412: bipush #25
    //   3414: iushr
    //   3415: aload #21
    //   3417: iconst_4
    //   3418: iaload
    //   3419: bipush #7
    //   3421: ishl
    //   3422: ior
    //   3423: ixor
    //   3424: iadd
    //   3425: aload #21
    //   3427: bipush #6
    //   3429: iaload
    //   3430: aload #21
    //   3432: iconst_4
    //   3433: iaload
    //   3434: aload #21
    //   3436: iconst_5
    //   3437: iaload
    //   3438: aload #21
    //   3440: bipush #6
    //   3442: iaload
    //   3443: ixor
    //   3444: iand
    //   3445: ixor
    //   3446: iadd
    //   3447: aload #6
    //   3449: iload #22
    //   3451: iaload
    //   3452: iadd
    //   3453: aload #20
    //   3455: iload #22
    //   3457: iaload
    //   3458: iadd
    //   3459: istore #23
    //   3461: aload #21
    //   3463: iconst_0
    //   3464: iaload
    //   3465: iconst_2
    //   3466: iushr
    //   3467: aload #21
    //   3469: iconst_0
    //   3470: iaload
    //   3471: bipush #30
    //   3473: ishl
    //   3474: ior
    //   3475: aload #21
    //   3477: iconst_0
    //   3478: iaload
    //   3479: bipush #13
    //   3481: iushr
    //   3482: aload #21
    //   3484: iconst_0
    //   3485: iaload
    //   3486: bipush #19
    //   3488: ishl
    //   3489: ior
    //   3490: ixor
    //   3491: aload #21
    //   3493: iconst_0
    //   3494: iaload
    //   3495: bipush #22
    //   3497: iushr
    //   3498: aload #21
    //   3500: iconst_0
    //   3501: iaload
    //   3502: bipush #10
    //   3504: ishl
    //   3505: ior
    //   3506: ixor
    //   3507: aload #21
    //   3509: iconst_0
    //   3510: iaload
    //   3511: aload #21
    //   3513: iconst_1
    //   3514: iaload
    //   3515: iand
    //   3516: aload #21
    //   3518: iconst_2
    //   3519: iaload
    //   3520: aload #21
    //   3522: iconst_0
    //   3523: iaload
    //   3524: aload #21
    //   3526: iconst_1
    //   3527: iaload
    //   3528: ior
    //   3529: iand
    //   3530: ior
    //   3531: iadd
    //   3532: istore #24
    //   3534: aload #21
    //   3536: iconst_3
    //   3537: dup2
    //   3538: iaload
    //   3539: iload #23
    //   3541: iadd
    //   3542: iastore
    //   3543: aload #21
    //   3545: bipush #7
    //   3547: iload #23
    //   3549: iload #24
    //   3551: iadd
    //   3552: iastore
    //   3553: aload #21
    //   3555: bipush #7
    //   3557: iaload
    //   3558: istore #23
    //   3560: aload #21
    //   3562: bipush #7
    //   3564: aload #21
    //   3566: bipush #6
    //   3568: iaload
    //   3569: iastore
    //   3570: aload #21
    //   3572: bipush #6
    //   3574: aload #21
    //   3576: iconst_5
    //   3577: iaload
    //   3578: iastore
    //   3579: aload #21
    //   3581: iconst_5
    //   3582: aload #21
    //   3584: iconst_4
    //   3585: iaload
    //   3586: iastore
    //   3587: aload #21
    //   3589: iconst_4
    //   3590: aload #21
    //   3592: iconst_3
    //   3593: iaload
    //   3594: iastore
    //   3595: aload #21
    //   3597: iconst_3
    //   3598: aload #21
    //   3600: iconst_2
    //   3601: iaload
    //   3602: iastore
    //   3603: aload #21
    //   3605: iconst_2
    //   3606: aload #21
    //   3608: iconst_1
    //   3609: iaload
    //   3610: iastore
    //   3611: aload #21
    //   3613: iconst_1
    //   3614: aload #21
    //   3616: iconst_0
    //   3617: iaload
    //   3618: iastore
    //   3619: aload #21
    //   3621: iconst_0
    //   3622: iload #23
    //   3624: iastore
    //   3625: iinc #22, 1
    //   3628: iload_2
    //   3629: ifne -> 3137
    //   3632: iconst_0
    //   3633: istore #22
    //   3635: iload #22
    //   3637: bipush #8
    //   3639: if_icmpge -> 3662
    //   3642: aload #8
    //   3644: iload #22
    //   3646: dup2
    //   3647: iaload
    //   3648: aload #21
    //   3650: iload #22
    //   3652: iaload
    //   3653: iadd
    //   3654: iastore
    //   3655: iinc #22, 1
    //   3658: iload_2
    //   3659: ifne -> 3635
    //   3662: bipush #32
    //   3664: newarray byte
    //   3666: astore #4
    //   3668: aload #4
    //   3670: iconst_0
    //   3671: aload #8
    //   3673: iconst_0
    //   3674: iaload
    //   3675: bipush #24
    //   3677: iushr
    //   3678: i2b
    //   3679: bastore
    //   3680: aload #4
    //   3682: iconst_1
    //   3683: aload #8
    //   3685: iconst_0
    //   3686: iaload
    //   3687: bipush #16
    //   3689: iushr
    //   3690: i2b
    //   3691: bastore
    //   3692: aload #4
    //   3694: iconst_2
    //   3695: aload #8
    //   3697: iconst_0
    //   3698: iaload
    //   3699: bipush #8
    //   3701: iushr
    //   3702: i2b
    //   3703: bastore
    //   3704: aload #4
    //   3706: iconst_3
    //   3707: aload #8
    //   3709: iconst_0
    //   3710: iaload
    //   3711: i2b
    //   3712: bastore
    //   3713: aload #4
    //   3715: iconst_4
    //   3716: aload #8
    //   3718: iconst_1
    //   3719: iaload
    //   3720: bipush #24
    //   3722: iushr
    //   3723: i2b
    //   3724: bastore
    //   3725: aload #4
    //   3727: iconst_5
    //   3728: aload #8
    //   3730: iconst_1
    //   3731: iaload
    //   3732: bipush #16
    //   3734: iushr
    //   3735: i2b
    //   3736: bastore
    //   3737: aload #4
    //   3739: bipush #6
    //   3741: aload #8
    //   3743: iconst_1
    //   3744: iaload
    //   3745: bipush #8
    //   3747: iushr
    //   3748: i2b
    //   3749: bastore
    //   3750: aload #4
    //   3752: bipush #7
    //   3754: aload #8
    //   3756: iconst_1
    //   3757: iaload
    //   3758: i2b
    //   3759: bastore
    //   3760: aload #4
    //   3762: bipush #8
    //   3764: aload #8
    //   3766: iconst_2
    //   3767: iaload
    //   3768: bipush #24
    //   3770: iushr
    //   3771: i2b
    //   3772: bastore
    //   3773: aload #4
    //   3775: bipush #9
    //   3777: aload #8
    //   3779: iconst_2
    //   3780: iaload
    //   3781: bipush #16
    //   3783: iushr
    //   3784: i2b
    //   3785: bastore
    //   3786: aload #4
    //   3788: bipush #10
    //   3790: aload #8
    //   3792: iconst_2
    //   3793: iaload
    //   3794: bipush #8
    //   3796: iushr
    //   3797: i2b
    //   3798: bastore
    //   3799: aload #4
    //   3801: bipush #11
    //   3803: aload #8
    //   3805: iconst_2
    //   3806: iaload
    //   3807: i2b
    //   3808: bastore
    //   3809: aload #4
    //   3811: bipush #12
    //   3813: aload #8
    //   3815: iconst_3
    //   3816: iaload
    //   3817: bipush #24
    //   3819: iushr
    //   3820: i2b
    //   3821: bastore
    //   3822: aload #4
    //   3824: bipush #13
    //   3826: aload #8
    //   3828: iconst_3
    //   3829: iaload
    //   3830: bipush #16
    //   3832: iushr
    //   3833: i2b
    //   3834: bastore
    //   3835: aload #4
    //   3837: bipush #14
    //   3839: aload #8
    //   3841: iconst_3
    //   3842: iaload
    //   3843: bipush #8
    //   3845: iushr
    //   3846: i2b
    //   3847: bastore
    //   3848: aload #4
    //   3850: bipush #15
    //   3852: aload #8
    //   3854: iconst_3
    //   3855: iaload
    //   3856: i2b
    //   3857: bastore
    //   3858: aload #4
    //   3860: bipush #16
    //   3862: aload #8
    //   3864: iconst_4
    //   3865: iaload
    //   3866: bipush #24
    //   3868: iushr
    //   3869: i2b
    //   3870: bastore
    //   3871: aload #4
    //   3873: bipush #17
    //   3875: aload #8
    //   3877: iconst_4
    //   3878: iaload
    //   3879: bipush #16
    //   3881: iushr
    //   3882: i2b
    //   3883: bastore
    //   3884: aload #4
    //   3886: bipush #18
    //   3888: aload #8
    //   3890: iconst_4
    //   3891: iaload
    //   3892: bipush #8
    //   3894: iushr
    //   3895: i2b
    //   3896: bastore
    //   3897: aload #4
    //   3899: bipush #19
    //   3901: aload #8
    //   3903: iconst_4
    //   3904: iaload
    //   3905: i2b
    //   3906: bastore
    //   3907: aload #4
    //   3909: bipush #20
    //   3911: aload #8
    //   3913: iconst_5
    //   3914: iaload
    //   3915: bipush #24
    //   3917: iushr
    //   3918: i2b
    //   3919: bastore
    //   3920: aload #4
    //   3922: bipush #21
    //   3924: aload #8
    //   3926: iconst_5
    //   3927: iaload
    //   3928: bipush #16
    //   3930: iushr
    //   3931: i2b
    //   3932: bastore
    //   3933: aload #4
    //   3935: bipush #22
    //   3937: aload #8
    //   3939: iconst_5
    //   3940: iaload
    //   3941: bipush #8
    //   3943: iushr
    //   3944: i2b
    //   3945: bastore
    //   3946: aload #4
    //   3948: bipush #23
    //   3950: aload #8
    //   3952: iconst_5
    //   3953: iaload
    //   3954: i2b
    //   3955: bastore
    //   3956: aload #4
    //   3958: bipush #24
    //   3960: aload #8
    //   3962: bipush #6
    //   3964: iaload
    //   3965: bipush #24
    //   3967: iushr
    //   3968: i2b
    //   3969: bastore
    //   3970: aload #4
    //   3972: bipush #25
    //   3974: aload #8
    //   3976: bipush #6
    //   3978: iaload
    //   3979: bipush #16
    //   3981: iushr
    //   3982: i2b
    //   3983: bastore
    //   3984: aload #4
    //   3986: bipush #26
    //   3988: aload #8
    //   3990: bipush #6
    //   3992: iaload
    //   3993: bipush #8
    //   3995: iushr
    //   3996: i2b
    //   3997: bastore
    //   3998: aload #4
    //   4000: bipush #27
    //   4002: aload #8
    //   4004: bipush #6
    //   4006: iaload
    //   4007: i2b
    //   4008: bastore
    //   4009: aload #4
    //   4011: bipush #28
    //   4013: aload #8
    //   4015: bipush #7
    //   4017: iaload
    //   4018: bipush #24
    //   4020: iushr
    //   4021: i2b
    //   4022: bastore
    //   4023: aload #4
    //   4025: bipush #29
    //   4027: aload #8
    //   4029: bipush #7
    //   4031: iaload
    //   4032: bipush #16
    //   4034: iushr
    //   4035: i2b
    //   4036: bastore
    //   4037: aload #4
    //   4039: bipush #30
    //   4041: aload #8
    //   4043: bipush #7
    //   4045: iaload
    //   4046: bipush #8
    //   4048: iushr
    //   4049: i2b
    //   4050: bastore
    //   4051: aload #4
    //   4053: bipush #31
    //   4055: aload #8
    //   4057: bipush #7
    //   4059: iaload
    //   4060: i2b
    //   4061: bastore
    //   4062: new java/math/BigInteger
    //   4065: dup
    //   4066: aload #4
    //   4068: invokespecial <init> : ([B)V
    //   4071: invokevirtual abs : ()Ljava/math/BigInteger;
    //   4074: putstatic burp/Zm5p.Ze : Ljava/lang/Object;
    //   4077: getstatic burp/Zx8t.ZA : Ljava/lang/Object;
    //   4080: checkcast java/math/BigInteger
    //   4083: invokevirtual toByteArray : ()[B
    //   4086: astore_3
    //   4087: bipush #32
    //   4089: newarray int
    //   4091: dup
    //   4092: iconst_0
    //   4093: ldc 876216579
    //   4095: iastore
    //   4096: dup
    //   4097: iconst_1
    //   4098: ldc 455999525
    //   4100: iastore
    //   4101: dup
    //   4102: iconst_2
    //   4103: ldc 1043334948
    //   4105: iastore
    //   4106: dup
    //   4107: iconst_3
    //   4108: ldc 439222784
    //   4110: iastore
    //   4111: dup
    //   4112: iconst_4
    //   4113: ldc 372376604
    //   4115: iastore
    //   4116: dup
    //   4117: iconst_5
    //   4118: ldc 707731490
    //   4120: iastore
    //   4121: dup
    //   4122: bipush #6
    //   4124: ldc 389426184
    //   4126: iastore
    //   4127: dup
    //   4128: bipush #7
    //   4130: ldc 973875457
    //   4132: iastore
    //   4133: dup
    //   4134: bipush #8
    //   4136: ldc 389160971
    //   4138: iastore
    //   4139: dup
    //   4140: bipush #9
    //   4142: ldc 907870729
    //   4144: iastore
    //   4145: dup
    //   4146: bipush #10
    //   4148: ldc 121057538
    //   4150: iastore
    //   4151: dup
    //   4152: bipush #11
    //   4154: ldc 840500228
    //   4156: iastore
    //   4157: dup
    //   4158: bipush #12
    //   4160: ldc 254150144
    //   4162: iastore
    //   4163: dup
    //   4164: bipush #13
    //   4166: ldc 924386310
    //   4168: iastore
    //   4169: dup
    //   4170: bipush #14
    //   4172: ldc 187632156
    //   4174: iastore
    //   4175: dup
    //   4176: bipush #15
    //   4178: ldc 874189824
    //   4180: iastore
    //   4181: dup
    //   4182: bipush #16
    //   4184: ldc 655302664
    //   4186: iastore
    //   4187: dup
    //   4188: bipush #17
    //   4190: ldc 890966315
    //   4192: iastore
    //   4193: dup
    //   4194: bipush #18
    //   4196: ldc 722417666
    //   4198: iastore
    //   4199: dup
    //   4200: bipush #19
    //   4202: ldc 1026621720
    //   4204: iastore
    //   4205: dup
    //   4206: bipush #20
    //   4208: ldc 957157408
    //   4210: iastore
    //   4211: dup
    //   4212: bipush #21
    //   4214: ldc 892536332
    //   4216: iastore
    //   4217: dup
    //   4218: bipush #22
    //   4220: ldc 689771012
    //   4222: iastore
    //   4223: dup
    //   4224: bipush #23
    //   4226: ldc 221709344
    //   4228: iastore
    //   4229: dup
    //   4230: bipush #24
    //   4232: ldc 940377620
    //   4234: iastore
    //   4235: dup
    //   4236: bipush #25
    //   4238: ldc 255209728
    //   4240: iastore
    //   4241: dup
    //   4242: bipush #26
    //   4244: ldc 1010368540
    //   4246: iastore
    //   4247: dup
    //   4248: bipush #27
    //   4250: ldc 220604441
    //   4252: iastore
    //   4253: dup
    //   4254: bipush #28
    //   4256: ldc 1008414755
    //   4258: iastore
    //   4259: dup
    //   4260: bipush #29
    //   4262: ldc 187049985
    //   4264: iastore
    //   4265: dup
    //   4266: bipush #30
    //   4268: ldc 943331329
    //   4270: iastore
    //   4271: dup
    //   4272: bipush #31
    //   4274: ldc 170788368
    //   4276: iastore
    //   4277: astore #5
    //   4279: bipush #64
    //   4281: newarray int
    //   4283: dup
    //   4284: iconst_0
    //   4285: ldc 16843776
    //   4287: iastore
    //   4288: dup
    //   4289: iconst_1
    //   4290: iconst_0
    //   4291: iastore
    //   4292: dup
    //   4293: iconst_2
    //   4294: ldc 65536
    //   4296: iastore
    //   4297: dup
    //   4298: iconst_3
    //   4299: ldc 16843780
    //   4301: iastore
    //   4302: dup
    //   4303: iconst_4
    //   4304: ldc 16842756
    //   4306: iastore
    //   4307: dup
    //   4308: iconst_5
    //   4309: ldc 66564
    //   4311: iastore
    //   4312: dup
    //   4313: bipush #6
    //   4315: iconst_4
    //   4316: iastore
    //   4317: dup
    //   4318: bipush #7
    //   4320: ldc 65536
    //   4322: iastore
    //   4323: dup
    //   4324: bipush #8
    //   4326: sipush #1024
    //   4329: iastore
    //   4330: dup
    //   4331: bipush #9
    //   4333: ldc 16843776
    //   4335: iastore
    //   4336: dup
    //   4337: bipush #10
    //   4339: ldc 16843780
    //   4341: iastore
    //   4342: dup
    //   4343: bipush #11
    //   4345: sipush #1024
    //   4348: iastore
    //   4349: dup
    //   4350: bipush #12
    //   4352: ldc 16778244
    //   4354: iastore
    //   4355: dup
    //   4356: bipush #13
    //   4358: ldc 16842756
    //   4360: iastore
    //   4361: dup
    //   4362: bipush #14
    //   4364: ldc 16777216
    //   4366: iastore
    //   4367: dup
    //   4368: bipush #15
    //   4370: iconst_4
    //   4371: iastore
    //   4372: dup
    //   4373: bipush #16
    //   4375: sipush #1028
    //   4378: iastore
    //   4379: dup
    //   4380: bipush #17
    //   4382: ldc 16778240
    //   4384: iastore
    //   4385: dup
    //   4386: bipush #18
    //   4388: ldc 16778240
    //   4390: iastore
    //   4391: dup
    //   4392: bipush #19
    //   4394: ldc 66560
    //   4396: iastore
    //   4397: dup
    //   4398: bipush #20
    //   4400: ldc 66560
    //   4402: iastore
    //   4403: dup
    //   4404: bipush #21
    //   4406: ldc 16842752
    //   4408: iastore
    //   4409: dup
    //   4410: bipush #22
    //   4412: ldc 16842752
    //   4414: iastore
    //   4415: dup
    //   4416: bipush #23
    //   4418: ldc 16778244
    //   4420: iastore
    //   4421: dup
    //   4422: bipush #24
    //   4424: ldc 65540
    //   4426: iastore
    //   4427: dup
    //   4428: bipush #25
    //   4430: ldc 16777220
    //   4432: iastore
    //   4433: dup
    //   4434: bipush #26
    //   4436: ldc 16777220
    //   4438: iastore
    //   4439: dup
    //   4440: bipush #27
    //   4442: ldc 65540
    //   4444: iastore
    //   4445: dup
    //   4446: bipush #28
    //   4448: iconst_0
    //   4449: iastore
    //   4450: dup
    //   4451: bipush #29
    //   4453: sipush #1028
    //   4456: iastore
    //   4457: dup
    //   4458: bipush #30
    //   4460: ldc 66564
    //   4462: iastore
    //   4463: dup
    //   4464: bipush #31
    //   4466: ldc 16777216
    //   4468: iastore
    //   4469: dup
    //   4470: bipush #32
    //   4472: ldc 65536
    //   4474: iastore
    //   4475: dup
    //   4476: bipush #33
    //   4478: ldc 16843780
    //   4480: iastore
    //   4481: dup
    //   4482: bipush #34
    //   4484: iconst_4
    //   4485: iastore
    //   4486: dup
    //   4487: bipush #35
    //   4489: ldc 16842752
    //   4491: iastore
    //   4492: dup
    //   4493: bipush #36
    //   4495: ldc 16843776
    //   4497: iastore
    //   4498: dup
    //   4499: bipush #37
    //   4501: ldc 16777216
    //   4503: iastore
    //   4504: dup
    //   4505: bipush #38
    //   4507: ldc 16777216
    //   4509: iastore
    //   4510: dup
    //   4511: bipush #39
    //   4513: sipush #1024
    //   4516: iastore
    //   4517: dup
    //   4518: bipush #40
    //   4520: ldc 16842756
    //   4522: iastore
    //   4523: dup
    //   4524: bipush #41
    //   4526: ldc 65536
    //   4528: iastore
    //   4529: dup
    //   4530: bipush #42
    //   4532: ldc 66560
    //   4534: iastore
    //   4535: dup
    //   4536: bipush #43
    //   4538: ldc 16777220
    //   4540: iastore
    //   4541: dup
    //   4542: bipush #44
    //   4544: sipush #1024
    //   4547: iastore
    //   4548: dup
    //   4549: bipush #45
    //   4551: iconst_4
    //   4552: iastore
    //   4553: dup
    //   4554: bipush #46
    //   4556: ldc 16778244
    //   4558: iastore
    //   4559: dup
    //   4560: bipush #47
    //   4562: ldc 66564
    //   4564: iastore
    //   4565: dup
    //   4566: bipush #48
    //   4568: ldc 16843780
    //   4570: iastore
    //   4571: dup
    //   4572: bipush #49
    //   4574: ldc 65540
    //   4576: iastore
    //   4577: dup
    //   4578: bipush #50
    //   4580: ldc 16842752
    //   4582: iastore
    //   4583: dup
    //   4584: bipush #51
    //   4586: ldc 16778244
    //   4588: iastore
    //   4589: dup
    //   4590: bipush #52
    //   4592: ldc 16777220
    //   4594: iastore
    //   4595: dup
    //   4596: bipush #53
    //   4598: sipush #1028
    //   4601: iastore
    //   4602: dup
    //   4603: bipush #54
    //   4605: ldc 66564
    //   4607: iastore
    //   4608: dup
    //   4609: bipush #55
    //   4611: ldc 16843776
    //   4613: iastore
    //   4614: dup
    //   4615: bipush #56
    //   4617: sipush #1028
    //   4620: iastore
    //   4621: dup
    //   4622: bipush #57
    //   4624: ldc 16778240
    //   4626: iastore
    //   4627: dup
    //   4628: bipush #58
    //   4630: ldc 16778240
    //   4632: iastore
    //   4633: dup
    //   4634: bipush #59
    //   4636: iconst_0
    //   4637: iastore
    //   4638: dup
    //   4639: bipush #60
    //   4641: ldc 65540
    //   4643: iastore
    //   4644: dup
    //   4645: bipush #61
    //   4647: ldc 66560
    //   4649: iastore
    //   4650: dup
    //   4651: bipush #62
    //   4653: iconst_0
    //   4654: iastore
    //   4655: dup
    //   4656: bipush #63
    //   4658: ldc 16842756
    //   4660: iastore
    //   4661: astore #6
    //   4663: bipush #64
    //   4665: newarray int
    //   4667: dup
    //   4668: iconst_0
    //   4669: ldc -2146402272
    //   4671: iastore
    //   4672: dup
    //   4673: iconst_1
    //   4674: ldc -2147450880
    //   4676: iastore
    //   4677: dup
    //   4678: iconst_2
    //   4679: ldc 32768
    //   4681: iastore
    //   4682: dup
    //   4683: iconst_3
    //   4684: ldc 1081376
    //   4686: iastore
    //   4687: dup
    //   4688: iconst_4
    //   4689: ldc 1048576
    //   4691: iastore
    //   4692: dup
    //   4693: iconst_5
    //   4694: bipush #32
    //   4696: iastore
    //   4697: dup
    //   4698: bipush #6
    //   4700: ldc -2146435040
    //   4702: iastore
    //   4703: dup
    //   4704: bipush #7
    //   4706: ldc -2147450848
    //   4708: iastore
    //   4709: dup
    //   4710: bipush #8
    //   4712: ldc -2147483616
    //   4714: iastore
    //   4715: dup
    //   4716: bipush #9
    //   4718: ldc -2146402272
    //   4720: iastore
    //   4721: dup
    //   4722: bipush #10
    //   4724: ldc -2146402304
    //   4726: iastore
    //   4727: dup
    //   4728: bipush #11
    //   4730: ldc -2147483648
    //   4732: iastore
    //   4733: dup
    //   4734: bipush #12
    //   4736: ldc -2147450880
    //   4738: iastore
    //   4739: dup
    //   4740: bipush #13
    //   4742: ldc 1048576
    //   4744: iastore
    //   4745: dup
    //   4746: bipush #14
    //   4748: bipush #32
    //   4750: iastore
    //   4751: dup
    //   4752: bipush #15
    //   4754: ldc -2146435040
    //   4756: iastore
    //   4757: dup
    //   4758: bipush #16
    //   4760: ldc 1081344
    //   4762: iastore
    //   4763: dup
    //   4764: bipush #17
    //   4766: ldc 1048608
    //   4768: iastore
    //   4769: dup
    //   4770: bipush #18
    //   4772: ldc -2147450848
    //   4774: iastore
    //   4775: dup
    //   4776: bipush #19
    //   4778: iconst_0
    //   4779: iastore
    //   4780: dup
    //   4781: bipush #20
    //   4783: ldc -2147483648
    //   4785: iastore
    //   4786: dup
    //   4787: bipush #21
    //   4789: ldc 32768
    //   4791: iastore
    //   4792: dup
    //   4793: bipush #22
    //   4795: ldc 1081376
    //   4797: iastore
    //   4798: dup
    //   4799: bipush #23
    //   4801: ldc -2146435072
    //   4803: iastore
    //   4804: dup
    //   4805: bipush #24
    //   4807: ldc 1048608
    //   4809: iastore
    //   4810: dup
    //   4811: bipush #25
    //   4813: ldc -2147483616
    //   4815: iastore
    //   4816: dup
    //   4817: bipush #26
    //   4819: iconst_0
    //   4820: iastore
    //   4821: dup
    //   4822: bipush #27
    //   4824: ldc 1081344
    //   4826: iastore
    //   4827: dup
    //   4828: bipush #28
    //   4830: ldc 32800
    //   4832: iastore
    //   4833: dup
    //   4834: bipush #29
    //   4836: ldc -2146402304
    //   4838: iastore
    //   4839: dup
    //   4840: bipush #30
    //   4842: ldc -2146435072
    //   4844: iastore
    //   4845: dup
    //   4846: bipush #31
    //   4848: ldc 32800
    //   4850: iastore
    //   4851: dup
    //   4852: bipush #32
    //   4854: iconst_0
    //   4855: iastore
    //   4856: dup
    //   4857: bipush #33
    //   4859: ldc 1081376
    //   4861: iastore
    //   4862: dup
    //   4863: bipush #34
    //   4865: ldc -2146435040
    //   4867: iastore
    //   4868: dup
    //   4869: bipush #35
    //   4871: ldc 1048576
    //   4873: iastore
    //   4874: dup
    //   4875: bipush #36
    //   4877: ldc -2147450848
    //   4879: iastore
    //   4880: dup
    //   4881: bipush #37
    //   4883: ldc -2146435072
    //   4885: iastore
    //   4886: dup
    //   4887: bipush #38
    //   4889: ldc -2146402304
    //   4891: iastore
    //   4892: dup
    //   4893: bipush #39
    //   4895: ldc 32768
    //   4897: iastore
    //   4898: dup
    //   4899: bipush #40
    //   4901: ldc -2146435072
    //   4903: iastore
    //   4904: dup
    //   4905: bipush #41
    //   4907: ldc -2147450880
    //   4909: iastore
    //   4910: dup
    //   4911: bipush #42
    //   4913: bipush #32
    //   4915: iastore
    //   4916: dup
    //   4917: bipush #43
    //   4919: ldc -2146402272
    //   4921: iastore
    //   4922: dup
    //   4923: bipush #44
    //   4925: ldc 1081376
    //   4927: iastore
    //   4928: dup
    //   4929: bipush #45
    //   4931: bipush #32
    //   4933: iastore
    //   4934: dup
    //   4935: bipush #46
    //   4937: ldc 32768
    //   4939: iastore
    //   4940: dup
    //   4941: bipush #47
    //   4943: ldc -2147483648
    //   4945: iastore
    //   4946: dup
    //   4947: bipush #48
    //   4949: ldc 32800
    //   4951: iastore
    //   4952: dup
    //   4953: bipush #49
    //   4955: ldc -2146402304
    //   4957: iastore
    //   4958: dup
    //   4959: bipush #50
    //   4961: ldc 1048576
    //   4963: iastore
    //   4964: dup
    //   4965: bipush #51
    //   4967: ldc -2147483616
    //   4969: iastore
    //   4970: dup
    //   4971: bipush #52
    //   4973: ldc 1048608
    //   4975: iastore
    //   4976: dup
    //   4977: bipush #53
    //   4979: ldc -2147450848
    //   4981: iastore
    //   4982: dup
    //   4983: bipush #54
    //   4985: ldc -2147483616
    //   4987: iastore
    //   4988: dup
    //   4989: bipush #55
    //   4991: ldc 1048608
    //   4993: iastore
    //   4994: dup
    //   4995: bipush #56
    //   4997: ldc 1081344
    //   4999: iastore
    //   5000: dup
    //   5001: bipush #57
    //   5003: iconst_0
    //   5004: iastore
    //   5005: dup
    //   5006: bipush #58
    //   5008: ldc -2147450880
    //   5010: iastore
    //   5011: dup
    //   5012: bipush #59
    //   5014: ldc 32800
    //   5016: iastore
    //   5017: dup
    //   5018: bipush #60
    //   5020: ldc -2147483648
    //   5022: iastore
    //   5023: dup
    //   5024: bipush #61
    //   5026: ldc -2146435040
    //   5028: iastore
    //   5029: dup
    //   5030: bipush #62
    //   5032: ldc -2146402272
    //   5034: iastore
    //   5035: dup
    //   5036: bipush #63
    //   5038: ldc 1081344
    //   5040: iastore
    //   5041: astore #7
    //   5043: bipush #64
    //   5045: newarray int
    //   5047: dup
    //   5048: iconst_0
    //   5049: sipush #520
    //   5052: iastore
    //   5053: dup
    //   5054: iconst_1
    //   5055: ldc 134349312
    //   5057: iastore
    //   5058: dup
    //   5059: iconst_2
    //   5060: iconst_0
    //   5061: iastore
    //   5062: dup
    //   5063: iconst_3
    //   5064: ldc 134348808
    //   5066: iastore
    //   5067: dup
    //   5068: iconst_4
    //   5069: ldc 134218240
    //   5071: iastore
    //   5072: dup
    //   5073: iconst_5
    //   5074: iconst_0
    //   5075: iastore
    //   5076: dup
    //   5077: bipush #6
    //   5079: ldc 131592
    //   5081: iastore
    //   5082: dup
    //   5083: bipush #7
    //   5085: ldc 134218240
    //   5087: iastore
    //   5088: dup
    //   5089: bipush #8
    //   5091: ldc 131080
    //   5093: iastore
    //   5094: dup
    //   5095: bipush #9
    //   5097: ldc 134217736
    //   5099: iastore
    //   5100: dup
    //   5101: bipush #10
    //   5103: ldc 134217736
    //   5105: iastore
    //   5106: dup
    //   5107: bipush #11
    //   5109: ldc 131072
    //   5111: iastore
    //   5112: dup
    //   5113: bipush #12
    //   5115: ldc 134349320
    //   5117: iastore
    //   5118: dup
    //   5119: bipush #13
    //   5121: ldc 131080
    //   5123: iastore
    //   5124: dup
    //   5125: bipush #14
    //   5127: ldc 134348800
    //   5129: iastore
    //   5130: dup
    //   5131: bipush #15
    //   5133: sipush #520
    //   5136: iastore
    //   5137: dup
    //   5138: bipush #16
    //   5140: ldc 134217728
    //   5142: iastore
    //   5143: dup
    //   5144: bipush #17
    //   5146: bipush #8
    //   5148: iastore
    //   5149: dup
    //   5150: bipush #18
    //   5152: ldc 134349312
    //   5154: iastore
    //   5155: dup
    //   5156: bipush #19
    //   5158: sipush #512
    //   5161: iastore
    //   5162: dup
    //   5163: bipush #20
    //   5165: ldc 131584
    //   5167: iastore
    //   5168: dup
    //   5169: bipush #21
    //   5171: ldc 134348800
    //   5173: iastore
    //   5174: dup
    //   5175: bipush #22
    //   5177: ldc 134348808
    //   5179: iastore
    //   5180: dup
    //   5181: bipush #23
    //   5183: ldc 131592
    //   5185: iastore
    //   5186: dup
    //   5187: bipush #24
    //   5189: ldc 134218248
    //   5191: iastore
    //   5192: dup
    //   5193: bipush #25
    //   5195: ldc 131584
    //   5197: iastore
    //   5198: dup
    //   5199: bipush #26
    //   5201: ldc 131072
    //   5203: iastore
    //   5204: dup
    //   5205: bipush #27
    //   5207: ldc 134218248
    //   5209: iastore
    //   5210: dup
    //   5211: bipush #28
    //   5213: bipush #8
    //   5215: iastore
    //   5216: dup
    //   5217: bipush #29
    //   5219: ldc 134349320
    //   5221: iastore
    //   5222: dup
    //   5223: bipush #30
    //   5225: sipush #512
    //   5228: iastore
    //   5229: dup
    //   5230: bipush #31
    //   5232: ldc 134217728
    //   5234: iastore
    //   5235: dup
    //   5236: bipush #32
    //   5238: ldc 134349312
    //   5240: iastore
    //   5241: dup
    //   5242: bipush #33
    //   5244: ldc 134217728
    //   5246: iastore
    //   5247: dup
    //   5248: bipush #34
    //   5250: ldc 131080
    //   5252: iastore
    //   5253: dup
    //   5254: bipush #35
    //   5256: sipush #520
    //   5259: iastore
    //   5260: dup
    //   5261: bipush #36
    //   5263: ldc 131072
    //   5265: iastore
    //   5266: dup
    //   5267: bipush #37
    //   5269: ldc 134349312
    //   5271: iastore
    //   5272: dup
    //   5273: bipush #38
    //   5275: ldc 134218240
    //   5277: iastore
    //   5278: dup
    //   5279: bipush #39
    //   5281: iconst_0
    //   5282: iastore
    //   5283: dup
    //   5284: bipush #40
    //   5286: sipush #512
    //   5289: iastore
    //   5290: dup
    //   5291: bipush #41
    //   5293: ldc 131080
    //   5295: iastore
    //   5296: dup
    //   5297: bipush #42
    //   5299: ldc 134349320
    //   5301: iastore
    //   5302: dup
    //   5303: bipush #43
    //   5305: ldc 134218240
    //   5307: iastore
    //   5308: dup
    //   5309: bipush #44
    //   5311: ldc 134217736
    //   5313: iastore
    //   5314: dup
    //   5315: bipush #45
    //   5317: sipush #512
    //   5320: iastore
    //   5321: dup
    //   5322: bipush #46
    //   5324: iconst_0
    //   5325: iastore
    //   5326: dup
    //   5327: bipush #47
    //   5329: ldc 134348808
    //   5331: iastore
    //   5332: dup
    //   5333: bipush #48
    //   5335: ldc 134218248
    //   5337: iastore
    //   5338: dup
    //   5339: bipush #49
    //   5341: ldc 131072
    //   5343: iastore
    //   5344: dup
    //   5345: bipush #50
    //   5347: ldc 134217728
    //   5349: iastore
    //   5350: dup
    //   5351: bipush #51
    //   5353: ldc 134349320
    //   5355: iastore
    //   5356: dup
    //   5357: bipush #52
    //   5359: bipush #8
    //   5361: iastore
    //   5362: dup
    //   5363: bipush #53
    //   5365: ldc 131592
    //   5367: iastore
    //   5368: dup
    //   5369: bipush #54
    //   5371: ldc 131584
    //   5373: iastore
    //   5374: dup
    //   5375: bipush #55
    //   5377: ldc 134217736
    //   5379: iastore
    //   5380: dup
    //   5381: bipush #56
    //   5383: ldc 134348800
    //   5385: iastore
    //   5386: dup
    //   5387: bipush #57
    //   5389: ldc 134218248
    //   5391: iastore
    //   5392: dup
    //   5393: bipush #58
    //   5395: sipush #520
    //   5398: iastore
    //   5399: dup
    //   5400: bipush #59
    //   5402: ldc 134348800
    //   5404: iastore
    //   5405: dup
    //   5406: bipush #60
    //   5408: ldc 131592
    //   5410: iastore
    //   5411: dup
    //   5412: bipush #61
    //   5414: bipush #8
    //   5416: iastore
    //   5417: dup
    //   5418: bipush #62
    //   5420: ldc 134348808
    //   5422: iastore
    //   5423: dup
    //   5424: bipush #63
    //   5426: ldc 131584
    //   5428: iastore
    //   5429: astore #8
    //   5431: bipush #64
    //   5433: newarray int
    //   5435: dup
    //   5436: iconst_0
    //   5437: ldc 8396801
    //   5439: iastore
    //   5440: dup
    //   5441: iconst_1
    //   5442: sipush #8321
    //   5445: iastore
    //   5446: dup
    //   5447: iconst_2
    //   5448: sipush #8321
    //   5451: iastore
    //   5452: dup
    //   5453: iconst_3
    //   5454: sipush #128
    //   5457: iastore
    //   5458: dup
    //   5459: iconst_4
    //   5460: ldc 8396928
    //   5462: iastore
    //   5463: dup
    //   5464: iconst_5
    //   5465: ldc 8388737
    //   5467: iastore
    //   5468: dup
    //   5469: bipush #6
    //   5471: ldc 8388609
    //   5473: iastore
    //   5474: dup
    //   5475: bipush #7
    //   5477: sipush #8193
    //   5480: iastore
    //   5481: dup
    //   5482: bipush #8
    //   5484: iconst_0
    //   5485: iastore
    //   5486: dup
    //   5487: bipush #9
    //   5489: ldc 8396800
    //   5491: iastore
    //   5492: dup
    //   5493: bipush #10
    //   5495: ldc 8396800
    //   5497: iastore
    //   5498: dup
    //   5499: bipush #11
    //   5501: ldc 8396929
    //   5503: iastore
    //   5504: dup
    //   5505: bipush #12
    //   5507: sipush #129
    //   5510: iastore
    //   5511: dup
    //   5512: bipush #13
    //   5514: iconst_0
    //   5515: iastore
    //   5516: dup
    //   5517: bipush #14
    //   5519: ldc 8388736
    //   5521: iastore
    //   5522: dup
    //   5523: bipush #15
    //   5525: ldc 8388609
    //   5527: iastore
    //   5528: dup
    //   5529: bipush #16
    //   5531: iconst_1
    //   5532: iastore
    //   5533: dup
    //   5534: bipush #17
    //   5536: sipush #8192
    //   5539: iastore
    //   5540: dup
    //   5541: bipush #18
    //   5543: ldc 8388608
    //   5545: iastore
    //   5546: dup
    //   5547: bipush #19
    //   5549: ldc 8396801
    //   5551: iastore
    //   5552: dup
    //   5553: bipush #20
    //   5555: sipush #128
    //   5558: iastore
    //   5559: dup
    //   5560: bipush #21
    //   5562: ldc 8388608
    //   5564: iastore
    //   5565: dup
    //   5566: bipush #22
    //   5568: sipush #8193
    //   5571: iastore
    //   5572: dup
    //   5573: bipush #23
    //   5575: sipush #8320
    //   5578: iastore
    //   5579: dup
    //   5580: bipush #24
    //   5582: ldc 8388737
    //   5584: iastore
    //   5585: dup
    //   5586: bipush #25
    //   5588: iconst_1
    //   5589: iastore
    //   5590: dup
    //   5591: bipush #26
    //   5593: sipush #8320
    //   5596: iastore
    //   5597: dup
    //   5598: bipush #27
    //   5600: ldc 8388736
    //   5602: iastore
    //   5603: dup
    //   5604: bipush #28
    //   5606: sipush #8192
    //   5609: iastore
    //   5610: dup
    //   5611: bipush #29
    //   5613: ldc 8396928
    //   5615: iastore
    //   5616: dup
    //   5617: bipush #30
    //   5619: ldc 8396929
    //   5621: iastore
    //   5622: dup
    //   5623: bipush #31
    //   5625: sipush #129
    //   5628: iastore
    //   5629: dup
    //   5630: bipush #32
    //   5632: ldc 8388736
    //   5634: iastore
    //   5635: dup
    //   5636: bipush #33
    //   5638: ldc 8388609
    //   5640: iastore
    //   5641: dup
    //   5642: bipush #34
    //   5644: ldc 8396800
    //   5646: iastore
    //   5647: dup
    //   5648: bipush #35
    //   5650: ldc 8396929
    //   5652: iastore
    //   5653: dup
    //   5654: bipush #36
    //   5656: sipush #129
    //   5659: iastore
    //   5660: dup
    //   5661: bipush #37
    //   5663: iconst_0
    //   5664: iastore
    //   5665: dup
    //   5666: bipush #38
    //   5668: iconst_0
    //   5669: iastore
    //   5670: dup
    //   5671: bipush #39
    //   5673: ldc 8396800
    //   5675: iastore
    //   5676: dup
    //   5677: bipush #40
    //   5679: sipush #8320
    //   5682: iastore
    //   5683: dup
    //   5684: bipush #41
    //   5686: ldc 8388736
    //   5688: iastore
    //   5689: dup
    //   5690: bipush #42
    //   5692: ldc 8388737
    //   5694: iastore
    //   5695: dup
    //   5696: bipush #43
    //   5698: iconst_1
    //   5699: iastore
    //   5700: dup
    //   5701: bipush #44
    //   5703: ldc 8396801
    //   5705: iastore
    //   5706: dup
    //   5707: bipush #45
    //   5709: sipush #8321
    //   5712: iastore
    //   5713: dup
    //   5714: bipush #46
    //   5716: sipush #8321
    //   5719: iastore
    //   5720: dup
    //   5721: bipush #47
    //   5723: sipush #128
    //   5726: iastore
    //   5727: dup
    //   5728: bipush #48
    //   5730: ldc 8396929
    //   5732: iastore
    //   5733: dup
    //   5734: bipush #49
    //   5736: sipush #129
    //   5739: iastore
    //   5740: dup
    //   5741: bipush #50
    //   5743: iconst_1
    //   5744: iastore
    //   5745: dup
    //   5746: bipush #51
    //   5748: sipush #8192
    //   5751: iastore
    //   5752: dup
    //   5753: bipush #52
    //   5755: ldc 8388609
    //   5757: iastore
    //   5758: dup
    //   5759: bipush #53
    //   5761: sipush #8193
    //   5764: iastore
    //   5765: dup
    //   5766: bipush #54
    //   5768: ldc 8396928
    //   5770: iastore
    //   5771: dup
    //   5772: bipush #55
    //   5774: ldc 8388737
    //   5776: iastore
    //   5777: dup
    //   5778: bipush #56
    //   5780: sipush #8193
    //   5783: iastore
    //   5784: dup
    //   5785: bipush #57
    //   5787: sipush #8320
    //   5790: iastore
    //   5791: dup
    //   5792: bipush #58
    //   5794: ldc 8388608
    //   5796: iastore
    //   5797: dup
    //   5798: bipush #59
    //   5800: ldc 8396801
    //   5802: iastore
    //   5803: dup
    //   5804: bipush #60
    //   5806: sipush #128
    //   5809: iastore
    //   5810: dup
    //   5811: bipush #61
    //   5813: ldc 8388608
    //   5815: iastore
    //   5816: dup
    //   5817: bipush #62
    //   5819: sipush #8192
    //   5822: iastore
    //   5823: dup
    //   5824: bipush #63
    //   5826: ldc 8396928
    //   5828: iastore
    //   5829: astore #9
    //   5831: bipush #64
    //   5833: newarray int
    //   5835: dup
    //   5836: iconst_0
    //   5837: sipush #256
    //   5840: iastore
    //   5841: dup
    //   5842: iconst_1
    //   5843: ldc 34078976
    //   5845: iastore
    //   5846: dup
    //   5847: iconst_2
    //   5848: ldc 34078720
    //   5850: iastore
    //   5851: dup
    //   5852: iconst_3
    //   5853: ldc 1107296512
    //   5855: iastore
    //   5856: dup
    //   5857: iconst_4
    //   5858: ldc 524288
    //   5860: iastore
    //   5861: dup
    //   5862: iconst_5
    //   5863: sipush #256
    //   5866: iastore
    //   5867: dup
    //   5868: bipush #6
    //   5870: ldc 1073741824
    //   5872: iastore
    //   5873: dup
    //   5874: bipush #7
    //   5876: ldc 34078720
    //   5878: iastore
    //   5879: dup
    //   5880: bipush #8
    //   5882: ldc 1074266368
    //   5884: iastore
    //   5885: dup
    //   5886: bipush #9
    //   5888: ldc 524288
    //   5890: iastore
    //   5891: dup
    //   5892: bipush #10
    //   5894: ldc 33554688
    //   5896: iastore
    //   5897: dup
    //   5898: bipush #11
    //   5900: ldc 1074266368
    //   5902: iastore
    //   5903: dup
    //   5904: bipush #12
    //   5906: ldc 1107296512
    //   5908: iastore
    //   5909: dup
    //   5910: bipush #13
    //   5912: ldc 1107820544
    //   5914: iastore
    //   5915: dup
    //   5916: bipush #14
    //   5918: ldc 524544
    //   5920: iastore
    //   5921: dup
    //   5922: bipush #15
    //   5924: ldc 1073741824
    //   5926: iastore
    //   5927: dup
    //   5928: bipush #16
    //   5930: ldc 33554432
    //   5932: iastore
    //   5933: dup
    //   5934: bipush #17
    //   5936: ldc 1074266112
    //   5938: iastore
    //   5939: dup
    //   5940: bipush #18
    //   5942: ldc 1074266112
    //   5944: iastore
    //   5945: dup
    //   5946: bipush #19
    //   5948: iconst_0
    //   5949: iastore
    //   5950: dup
    //   5951: bipush #20
    //   5953: ldc 1073742080
    //   5955: iastore
    //   5956: dup
    //   5957: bipush #21
    //   5959: ldc 1107820800
    //   5961: iastore
    //   5962: dup
    //   5963: bipush #22
    //   5965: ldc 1107820800
    //   5967: iastore
    //   5968: dup
    //   5969: bipush #23
    //   5971: ldc 33554688
    //   5973: iastore
    //   5974: dup
    //   5975: bipush #24
    //   5977: ldc 1107820544
    //   5979: iastore
    //   5980: dup
    //   5981: bipush #25
    //   5983: ldc 1073742080
    //   5985: iastore
    //   5986: dup
    //   5987: bipush #26
    //   5989: iconst_0
    //   5990: iastore
    //   5991: dup
    //   5992: bipush #27
    //   5994: ldc 1107296256
    //   5996: iastore
    //   5997: dup
    //   5998: bipush #28
    //   6000: ldc 34078976
    //   6002: iastore
    //   6003: dup
    //   6004: bipush #29
    //   6006: ldc 33554432
    //   6008: iastore
    //   6009: dup
    //   6010: bipush #30
    //   6012: ldc 1107296256
    //   6014: iastore
    //   6015: dup
    //   6016: bipush #31
    //   6018: ldc 524544
    //   6020: iastore
    //   6021: dup
    //   6022: bipush #32
    //   6024: ldc 524288
    //   6026: iastore
    //   6027: dup
    //   6028: bipush #33
    //   6030: ldc 1107296512
    //   6032: iastore
    //   6033: dup
    //   6034: bipush #34
    //   6036: sipush #256
    //   6039: iastore
    //   6040: dup
    //   6041: bipush #35
    //   6043: ldc 33554432
    //   6045: iastore
    //   6046: dup
    //   6047: bipush #36
    //   6049: ldc 1073741824
    //   6051: iastore
    //   6052: dup
    //   6053: bipush #37
    //   6055: ldc 34078720
    //   6057: iastore
    //   6058: dup
    //   6059: bipush #38
    //   6061: ldc 1107296512
    //   6063: iastore
    //   6064: dup
    //   6065: bipush #39
    //   6067: ldc 1074266368
    //   6069: iastore
    //   6070: dup
    //   6071: bipush #40
    //   6073: ldc 33554688
    //   6075: iastore
    //   6076: dup
    //   6077: bipush #41
    //   6079: ldc 1073741824
    //   6081: iastore
    //   6082: dup
    //   6083: bipush #42
    //   6085: ldc 1107820544
    //   6087: iastore
    //   6088: dup
    //   6089: bipush #43
    //   6091: ldc 34078976
    //   6093: iastore
    //   6094: dup
    //   6095: bipush #44
    //   6097: ldc 1074266368
    //   6099: iastore
    //   6100: dup
    //   6101: bipush #45
    //   6103: sipush #256
    //   6106: iastore
    //   6107: dup
    //   6108: bipush #46
    //   6110: ldc 33554432
    //   6112: iastore
    //   6113: dup
    //   6114: bipush #47
    //   6116: ldc 1107820544
    //   6118: iastore
    //   6119: dup
    //   6120: bipush #48
    //   6122: ldc 1107820800
    //   6124: iastore
    //   6125: dup
    //   6126: bipush #49
    //   6128: ldc 524544
    //   6130: iastore
    //   6131: dup
    //   6132: bipush #50
    //   6134: ldc 1107296256
    //   6136: iastore
    //   6137: dup
    //   6138: bipush #51
    //   6140: ldc 1107820800
    //   6142: iastore
    //   6143: dup
    //   6144: bipush #52
    //   6146: ldc 34078720
    //   6148: iastore
    //   6149: dup
    //   6150: bipush #53
    //   6152: iconst_0
    //   6153: iastore
    //   6154: dup
    //   6155: bipush #54
    //   6157: ldc 1074266112
    //   6159: iastore
    //   6160: dup
    //   6161: bipush #55
    //   6163: ldc 1107296256
    //   6165: iastore
    //   6166: dup
    //   6167: bipush #56
    //   6169: ldc 524544
    //   6171: iastore
    //   6172: dup
    //   6173: bipush #57
    //   6175: ldc 33554688
    //   6177: iastore
    //   6178: dup
    //   6179: bipush #58
    //   6181: ldc 1073742080
    //   6183: iastore
    //   6184: dup
    //   6185: bipush #59
    //   6187: ldc 524288
    //   6189: iastore
    //   6190: dup
    //   6191: bipush #60
    //   6193: iconst_0
    //   6194: iastore
    //   6195: dup
    //   6196: bipush #61
    //   6198: ldc 1074266112
    //   6200: iastore
    //   6201: dup
    //   6202: bipush #62
    //   6204: ldc 34078976
    //   6206: iastore
    //   6207: dup
    //   6208: bipush #63
    //   6210: ldc 1073742080
    //   6212: iastore
    //   6213: astore #10
    //   6215: bipush #64
    //   6217: newarray int
    //   6219: dup
    //   6220: iconst_0
    //   6221: ldc 536870928
    //   6223: iastore
    //   6224: dup
    //   6225: iconst_1
    //   6226: ldc 541065216
    //   6228: iastore
    //   6229: dup
    //   6230: iconst_2
    //   6231: sipush #16384
    //   6234: iastore
    //   6235: dup
    //   6236: iconst_3
    //   6237: ldc 541081616
    //   6239: iastore
    //   6240: dup
    //   6241: iconst_4
    //   6242: ldc 541065216
    //   6244: iastore
    //   6245: dup
    //   6246: iconst_5
    //   6247: bipush #16
    //   6249: iastore
    //   6250: dup
    //   6251: bipush #6
    //   6253: ldc 541081616
    //   6255: iastore
    //   6256: dup
    //   6257: bipush #7
    //   6259: ldc 4194304
    //   6261: iastore
    //   6262: dup
    //   6263: bipush #8
    //   6265: ldc 536887296
    //   6267: iastore
    //   6268: dup
    //   6269: bipush #9
    //   6271: ldc 4210704
    //   6273: iastore
    //   6274: dup
    //   6275: bipush #10
    //   6277: ldc 4194304
    //   6279: iastore
    //   6280: dup
    //   6281: bipush #11
    //   6283: ldc 536870928
    //   6285: iastore
    //   6286: dup
    //   6287: bipush #12
    //   6289: ldc 4194320
    //   6291: iastore
    //   6292: dup
    //   6293: bipush #13
    //   6295: ldc 536887296
    //   6297: iastore
    //   6298: dup
    //   6299: bipush #14
    //   6301: ldc 536870912
    //   6303: iastore
    //   6304: dup
    //   6305: bipush #15
    //   6307: sipush #16400
    //   6310: iastore
    //   6311: dup
    //   6312: bipush #16
    //   6314: iconst_0
    //   6315: iastore
    //   6316: dup
    //   6317: bipush #17
    //   6319: ldc 4194320
    //   6321: iastore
    //   6322: dup
    //   6323: bipush #18
    //   6325: ldc 536887312
    //   6327: iastore
    //   6328: dup
    //   6329: bipush #19
    //   6331: sipush #16384
    //   6334: iastore
    //   6335: dup
    //   6336: bipush #20
    //   6338: ldc 4210688
    //   6340: iastore
    //   6341: dup
    //   6342: bipush #21
    //   6344: ldc 536887312
    //   6346: iastore
    //   6347: dup
    //   6348: bipush #22
    //   6350: bipush #16
    //   6352: iastore
    //   6353: dup
    //   6354: bipush #23
    //   6356: ldc 541065232
    //   6358: iastore
    //   6359: dup
    //   6360: bipush #24
    //   6362: ldc 541065232
    //   6364: iastore
    //   6365: dup
    //   6366: bipush #25
    //   6368: iconst_0
    //   6369: iastore
    //   6370: dup
    //   6371: bipush #26
    //   6373: ldc 4210704
    //   6375: iastore
    //   6376: dup
    //   6377: bipush #27
    //   6379: ldc 541081600
    //   6381: iastore
    //   6382: dup
    //   6383: bipush #28
    //   6385: sipush #16400
    //   6388: iastore
    //   6389: dup
    //   6390: bipush #29
    //   6392: ldc 4210688
    //   6394: iastore
    //   6395: dup
    //   6396: bipush #30
    //   6398: ldc 541081600
    //   6400: iastore
    //   6401: dup
    //   6402: bipush #31
    //   6404: ldc 536870912
    //   6406: iastore
    //   6407: dup
    //   6408: bipush #32
    //   6410: ldc 536887296
    //   6412: iastore
    //   6413: dup
    //   6414: bipush #33
    //   6416: bipush #16
    //   6418: iastore
    //   6419: dup
    //   6420: bipush #34
    //   6422: ldc 541065232
    //   6424: iastore
    //   6425: dup
    //   6426: bipush #35
    //   6428: ldc 4210688
    //   6430: iastore
    //   6431: dup
    //   6432: bipush #36
    //   6434: ldc 541081616
    //   6436: iastore
    //   6437: dup
    //   6438: bipush #37
    //   6440: ldc 4194304
    //   6442: iastore
    //   6443: dup
    //   6444: bipush #38
    //   6446: sipush #16400
    //   6449: iastore
    //   6450: dup
    //   6451: bipush #39
    //   6453: ldc 536870928
    //   6455: iastore
    //   6456: dup
    //   6457: bipush #40
    //   6459: ldc 4194304
    //   6461: iastore
    //   6462: dup
    //   6463: bipush #41
    //   6465: ldc 536887296
    //   6467: iastore
    //   6468: dup
    //   6469: bipush #42
    //   6471: ldc 536870912
    //   6473: iastore
    //   6474: dup
    //   6475: bipush #43
    //   6477: sipush #16400
    //   6480: iastore
    //   6481: dup
    //   6482: bipush #44
    //   6484: ldc 536870928
    //   6486: iastore
    //   6487: dup
    //   6488: bipush #45
    //   6490: ldc 541081616
    //   6492: iastore
    //   6493: dup
    //   6494: bipush #46
    //   6496: ldc 4210688
    //   6498: iastore
    //   6499: dup
    //   6500: bipush #47
    //   6502: ldc 541065216
    //   6504: iastore
    //   6505: dup
    //   6506: bipush #48
    //   6508: ldc 4210704
    //   6510: iastore
    //   6511: dup
    //   6512: bipush #49
    //   6514: ldc 541081600
    //   6516: iastore
    //   6517: dup
    //   6518: bipush #50
    //   6520: iconst_0
    //   6521: iastore
    //   6522: dup
    //   6523: bipush #51
    //   6525: ldc 541065232
    //   6527: iastore
    //   6528: dup
    //   6529: bipush #52
    //   6531: bipush #16
    //   6533: iastore
    //   6534: dup
    //   6535: bipush #53
    //   6537: sipush #16384
    //   6540: iastore
    //   6541: dup
    //   6542: bipush #54
    //   6544: ldc 541065216
    //   6546: iastore
    //   6547: dup
    //   6548: bipush #55
    //   6550: ldc 4210704
    //   6552: iastore
    //   6553: dup
    //   6554: bipush #56
    //   6556: sipush #16384
    //   6559: iastore
    //   6560: dup
    //   6561: bipush #57
    //   6563: ldc 4194320
    //   6565: iastore
    //   6566: dup
    //   6567: bipush #58
    //   6569: ldc 536887312
    //   6571: iastore
    //   6572: dup
    //   6573: bipush #59
    //   6575: iconst_0
    //   6576: iastore
    //   6577: dup
    //   6578: bipush #60
    //   6580: ldc 541081600
    //   6582: iastore
    //   6583: dup
    //   6584: bipush #61
    //   6586: ldc 536870912
    //   6588: iastore
    //   6589: dup
    //   6590: bipush #62
    //   6592: ldc 4194320
    //   6594: iastore
    //   6595: dup
    //   6596: bipush #63
    //   6598: ldc 536887312
    //   6600: iastore
    //   6601: astore #11
    //   6603: bipush #64
    //   6605: newarray int
    //   6607: dup
    //   6608: iconst_0
    //   6609: ldc 2097152
    //   6611: iastore
    //   6612: dup
    //   6613: iconst_1
    //   6614: ldc 69206018
    //   6616: iastore
    //   6617: dup
    //   6618: iconst_2
    //   6619: ldc 67110914
    //   6621: iastore
    //   6622: dup
    //   6623: iconst_3
    //   6624: iconst_0
    //   6625: iastore
    //   6626: dup
    //   6627: iconst_4
    //   6628: sipush #2048
    //   6631: iastore
    //   6632: dup
    //   6633: iconst_5
    //   6634: ldc 67110914
    //   6636: iastore
    //   6637: dup
    //   6638: bipush #6
    //   6640: ldc 2099202
    //   6642: iastore
    //   6643: dup
    //   6644: bipush #7
    //   6646: ldc 69208064
    //   6648: iastore
    //   6649: dup
    //   6650: bipush #8
    //   6652: ldc 69208066
    //   6654: iastore
    //   6655: dup
    //   6656: bipush #9
    //   6658: ldc 2097152
    //   6660: iastore
    //   6661: dup
    //   6662: bipush #10
    //   6664: iconst_0
    //   6665: iastore
    //   6666: dup
    //   6667: bipush #11
    //   6669: ldc 67108866
    //   6671: iastore
    //   6672: dup
    //   6673: bipush #12
    //   6675: iconst_2
    //   6676: iastore
    //   6677: dup
    //   6678: bipush #13
    //   6680: ldc 67108864
    //   6682: iastore
    //   6683: dup
    //   6684: bipush #14
    //   6686: ldc 69206018
    //   6688: iastore
    //   6689: dup
    //   6690: bipush #15
    //   6692: sipush #2050
    //   6695: iastore
    //   6696: dup
    //   6697: bipush #16
    //   6699: ldc 67110912
    //   6701: iastore
    //   6702: dup
    //   6703: bipush #17
    //   6705: ldc 2099202
    //   6707: iastore
    //   6708: dup
    //   6709: bipush #18
    //   6711: ldc 2097154
    //   6713: iastore
    //   6714: dup
    //   6715: bipush #19
    //   6717: ldc 67110912
    //   6719: iastore
    //   6720: dup
    //   6721: bipush #20
    //   6723: ldc 67108866
    //   6725: iastore
    //   6726: dup
    //   6727: bipush #21
    //   6729: ldc 69206016
    //   6731: iastore
    //   6732: dup
    //   6733: bipush #22
    //   6735: ldc 69208064
    //   6737: iastore
    //   6738: dup
    //   6739: bipush #23
    //   6741: ldc 2097154
    //   6743: iastore
    //   6744: dup
    //   6745: bipush #24
    //   6747: ldc 69206016
    //   6749: iastore
    //   6750: dup
    //   6751: bipush #25
    //   6753: sipush #2048
    //   6756: iastore
    //   6757: dup
    //   6758: bipush #26
    //   6760: sipush #2050
    //   6763: iastore
    //   6764: dup
    //   6765: bipush #27
    //   6767: ldc 69208066
    //   6769: iastore
    //   6770: dup
    //   6771: bipush #28
    //   6773: ldc 2099200
    //   6775: iastore
    //   6776: dup
    //   6777: bipush #29
    //   6779: iconst_2
    //   6780: iastore
    //   6781: dup
    //   6782: bipush #30
    //   6784: ldc 67108864
    //   6786: iastore
    //   6787: dup
    //   6788: bipush #31
    //   6790: ldc 2099200
    //   6792: iastore
    //   6793: dup
    //   6794: bipush #32
    //   6796: ldc 67108864
    //   6798: iastore
    //   6799: dup
    //   6800: bipush #33
    //   6802: ldc 2099200
    //   6804: iastore
    //   6805: dup
    //   6806: bipush #34
    //   6808: ldc 2097152
    //   6810: iastore
    //   6811: dup
    //   6812: bipush #35
    //   6814: ldc 67110914
    //   6816: iastore
    //   6817: dup
    //   6818: bipush #36
    //   6820: ldc 67110914
    //   6822: iastore
    //   6823: dup
    //   6824: bipush #37
    //   6826: ldc 69206018
    //   6828: iastore
    //   6829: dup
    //   6830: bipush #38
    //   6832: ldc 69206018
    //   6834: iastore
    //   6835: dup
    //   6836: bipush #39
    //   6838: iconst_2
    //   6839: iastore
    //   6840: dup
    //   6841: bipush #40
    //   6843: ldc 2097154
    //   6845: iastore
    //   6846: dup
    //   6847: bipush #41
    //   6849: ldc 67108864
    //   6851: iastore
    //   6852: dup
    //   6853: bipush #42
    //   6855: ldc 67110912
    //   6857: iastore
    //   6858: dup
    //   6859: bipush #43
    //   6861: ldc 2097152
    //   6863: iastore
    //   6864: dup
    //   6865: bipush #44
    //   6867: ldc 69208064
    //   6869: iastore
    //   6870: dup
    //   6871: bipush #45
    //   6873: sipush #2050
    //   6876: iastore
    //   6877: dup
    //   6878: bipush #46
    //   6880: ldc 2099202
    //   6882: iastore
    //   6883: dup
    //   6884: bipush #47
    //   6886: ldc 69208064
    //   6888: iastore
    //   6889: dup
    //   6890: bipush #48
    //   6892: sipush #2050
    //   6895: iastore
    //   6896: dup
    //   6897: bipush #49
    //   6899: ldc 67108866
    //   6901: iastore
    //   6902: dup
    //   6903: bipush #50
    //   6905: ldc 69208066
    //   6907: iastore
    //   6908: dup
    //   6909: bipush #51
    //   6911: ldc 69206016
    //   6913: iastore
    //   6914: dup
    //   6915: bipush #52
    //   6917: ldc 2099200
    //   6919: iastore
    //   6920: dup
    //   6921: bipush #53
    //   6923: iconst_0
    //   6924: iastore
    //   6925: dup
    //   6926: bipush #54
    //   6928: iconst_2
    //   6929: iastore
    //   6930: dup
    //   6931: bipush #55
    //   6933: ldc 69208066
    //   6935: iastore
    //   6936: dup
    //   6937: bipush #56
    //   6939: iconst_0
    //   6940: iastore
    //   6941: dup
    //   6942: bipush #57
    //   6944: ldc 2099202
    //   6946: iastore
    //   6947: dup
    //   6948: bipush #58
    //   6950: ldc 69206016
    //   6952: iastore
    //   6953: dup
    //   6954: bipush #59
    //   6956: sipush #2048
    //   6959: iastore
    //   6960: dup
    //   6961: bipush #60
    //   6963: ldc 67108866
    //   6965: iastore
    //   6966: dup
    //   6967: bipush #61
    //   6969: ldc 67110912
    //   6971: iastore
    //   6972: dup
    //   6973: bipush #62
    //   6975: sipush #2048
    //   6978: iastore
    //   6979: dup
    //   6980: bipush #63
    //   6982: ldc 2097154
    //   6984: iastore
    //   6985: astore #12
    //   6987: bipush #64
    //   6989: newarray int
    //   6991: dup
    //   6992: iconst_0
    //   6993: ldc 268439616
    //   6995: iastore
    //   6996: dup
    //   6997: iconst_1
    //   6998: sipush #4096
    //   7001: iastore
    //   7002: dup
    //   7003: iconst_2
    //   7004: ldc 262144
    //   7006: iastore
    //   7007: dup
    //   7008: iconst_3
    //   7009: ldc 268701760
    //   7011: iastore
    //   7012: dup
    //   7013: iconst_4
    //   7014: ldc 268435456
    //   7016: iastore
    //   7017: dup
    //   7018: iconst_5
    //   7019: ldc 268439616
    //   7021: iastore
    //   7022: dup
    //   7023: bipush #6
    //   7025: bipush #64
    //   7027: iastore
    //   7028: dup
    //   7029: bipush #7
    //   7031: ldc 268435456
    //   7033: iastore
    //   7034: dup
    //   7035: bipush #8
    //   7037: ldc 262208
    //   7039: iastore
    //   7040: dup
    //   7041: bipush #9
    //   7043: ldc 268697600
    //   7045: iastore
    //   7046: dup
    //   7047: bipush #10
    //   7049: ldc 268701760
    //   7051: iastore
    //   7052: dup
    //   7053: bipush #11
    //   7055: ldc 266240
    //   7057: iastore
    //   7058: dup
    //   7059: bipush #12
    //   7061: ldc 268701696
    //   7063: iastore
    //   7064: dup
    //   7065: bipush #13
    //   7067: ldc 266304
    //   7069: iastore
    //   7070: dup
    //   7071: bipush #14
    //   7073: sipush #4096
    //   7076: iastore
    //   7077: dup
    //   7078: bipush #15
    //   7080: bipush #64
    //   7082: iastore
    //   7083: dup
    //   7084: bipush #16
    //   7086: ldc 268697600
    //   7088: iastore
    //   7089: dup
    //   7090: bipush #17
    //   7092: ldc 268435520
    //   7094: iastore
    //   7095: dup
    //   7096: bipush #18
    //   7098: ldc 268439552
    //   7100: iastore
    //   7101: dup
    //   7102: bipush #19
    //   7104: sipush #4160
    //   7107: iastore
    //   7108: dup
    //   7109: bipush #20
    //   7111: ldc 266240
    //   7113: iastore
    //   7114: dup
    //   7115: bipush #21
    //   7117: ldc 262208
    //   7119: iastore
    //   7120: dup
    //   7121: bipush #22
    //   7123: ldc 268697664
    //   7125: iastore
    //   7126: dup
    //   7127: bipush #23
    //   7129: ldc 268701696
    //   7131: iastore
    //   7132: dup
    //   7133: bipush #24
    //   7135: sipush #4160
    //   7138: iastore
    //   7139: dup
    //   7140: bipush #25
    //   7142: iconst_0
    //   7143: iastore
    //   7144: dup
    //   7145: bipush #26
    //   7147: iconst_0
    //   7148: iastore
    //   7149: dup
    //   7150: bipush #27
    //   7152: ldc 268697664
    //   7154: iastore
    //   7155: dup
    //   7156: bipush #28
    //   7158: ldc 268435520
    //   7160: iastore
    //   7161: dup
    //   7162: bipush #29
    //   7164: ldc 268439552
    //   7166: iastore
    //   7167: dup
    //   7168: bipush #30
    //   7170: ldc 266304
    //   7172: iastore
    //   7173: dup
    //   7174: bipush #31
    //   7176: ldc 262144
    //   7178: iastore
    //   7179: dup
    //   7180: bipush #32
    //   7182: ldc 266304
    //   7184: iastore
    //   7185: dup
    //   7186: bipush #33
    //   7188: ldc 262144
    //   7190: iastore
    //   7191: dup
    //   7192: bipush #34
    //   7194: ldc 268701696
    //   7196: iastore
    //   7197: dup
    //   7198: bipush #35
    //   7200: sipush #4096
    //   7203: iastore
    //   7204: dup
    //   7205: bipush #36
    //   7207: bipush #64
    //   7209: iastore
    //   7210: dup
    //   7211: bipush #37
    //   7213: ldc 268697664
    //   7215: iastore
    //   7216: dup
    //   7217: bipush #38
    //   7219: sipush #4096
    //   7222: iastore
    //   7223: dup
    //   7224: bipush #39
    //   7226: ldc 266304
    //   7228: iastore
    //   7229: dup
    //   7230: bipush #40
    //   7232: ldc 268439552
    //   7234: iastore
    //   7235: dup
    //   7236: bipush #41
    //   7238: bipush #64
    //   7240: iastore
    //   7241: dup
    //   7242: bipush #42
    //   7244: ldc 268435520
    //   7246: iastore
    //   7247: dup
    //   7248: bipush #43
    //   7250: ldc 268697600
    //   7252: iastore
    //   7253: dup
    //   7254: bipush #44
    //   7256: ldc 268697664
    //   7258: iastore
    //   7259: dup
    //   7260: bipush #45
    //   7262: ldc 268435456
    //   7264: iastore
    //   7265: dup
    //   7266: bipush #46
    //   7268: ldc 262144
    //   7270: iastore
    //   7271: dup
    //   7272: bipush #47
    //   7274: ldc 268439616
    //   7276: iastore
    //   7277: dup
    //   7278: bipush #48
    //   7280: iconst_0
    //   7281: iastore
    //   7282: dup
    //   7283: bipush #49
    //   7285: ldc 268701760
    //   7287: iastore
    //   7288: dup
    //   7289: bipush #50
    //   7291: ldc 262208
    //   7293: iastore
    //   7294: dup
    //   7295: bipush #51
    //   7297: ldc 268435520
    //   7299: iastore
    //   7300: dup
    //   7301: bipush #52
    //   7303: ldc 268697600
    //   7305: iastore
    //   7306: dup
    //   7307: bipush #53
    //   7309: ldc 268439552
    //   7311: iastore
    //   7312: dup
    //   7313: bipush #54
    //   7315: ldc 268439616
    //   7317: iastore
    //   7318: dup
    //   7319: bipush #55
    //   7321: iconst_0
    //   7322: iastore
    //   7323: dup
    //   7324: bipush #56
    //   7326: ldc 268701760
    //   7328: iastore
    //   7329: dup
    //   7330: bipush #57
    //   7332: ldc 266240
    //   7334: iastore
    //   7335: dup
    //   7336: bipush #58
    //   7338: ldc 266240
    //   7340: iastore
    //   7341: dup
    //   7342: bipush #59
    //   7344: sipush #4160
    //   7347: iastore
    //   7348: dup
    //   7349: bipush #60
    //   7351: sipush #4160
    //   7354: iastore
    //   7355: dup
    //   7356: bipush #61
    //   7358: ldc 262208
    //   7360: iastore
    //   7361: dup
    //   7362: bipush #62
    //   7364: ldc 268435456
    //   7366: iastore
    //   7367: dup
    //   7368: bipush #63
    //   7370: ldc 268701696
    //   7372: iastore
    //   7373: astore #13
    //   7375: aload_3
    //   7376: arraylength
    //   7377: istore #14
    //   7379: iload #14
    //   7381: bipush #8
    //   7383: irem
    //   7384: ifeq -> 7408
    //   7387: new java/lang/Exception
    //   7390: dup
    //   7391: sipush #-15254
    //   7394: sipush #-27242
    //   7397: invokestatic a : (II)Ljava/lang/String;
    //   7400: invokespecial <init> : (Ljava/lang/String;)V
    //   7403: athrow
    //   7404: invokestatic a : (Ljava/lang/Throwable;)Ljava/lang/Throwable;
    //   7407: athrow
    //   7408: iconst_2
    //   7409: newarray int
    //   7411: astore #15
    //   7413: iload #14
    //   7415: newarray byte
    //   7417: astore #16
    //   7419: iload #14
    //   7421: bipush #8
    //   7423: idiv
    //   7424: istore #17
    //   7426: iconst_0
    //   7427: istore #18
    //   7429: iload #18
    //   7431: iload #17
    //   7433: if_icmpge -> 8347
    //   7436: iload #18
    //   7438: bipush #8
    //   7440: imul
    //   7441: istore #19
    //   7443: iconst_0
    //   7444: istore #20
    //   7446: iload #20
    //   7448: iconst_2
    //   7449: if_icmpge -> 7534
    //   7452: aload #15
    //   7454: iload #20
    //   7456: aload_3
    //   7457: iload #19
    //   7459: iload #20
    //   7461: iconst_4
    //   7462: imul
    //   7463: iadd
    //   7464: baload
    //   7465: sipush #255
    //   7468: iand
    //   7469: bipush #24
    //   7471: ishl
    //   7472: aload_3
    //   7473: iload #19
    //   7475: iload #20
    //   7477: iconst_4
    //   7478: imul
    //   7479: iadd
    //   7480: iconst_1
    //   7481: iadd
    //   7482: baload
    //   7483: sipush #255
    //   7486: iand
    //   7487: bipush #16
    //   7489: ishl
    //   7490: ior
    //   7491: aload_3
    //   7492: iload #19
    //   7494: iload #20
    //   7496: iconst_4
    //   7497: imul
    //   7498: iadd
    //   7499: iconst_2
    //   7500: iadd
    //   7501: baload
    //   7502: sipush #255
    //   7505: iand
    //   7506: bipush #8
    //   7508: ishl
    //   7509: ior
    //   7510: aload_3
    //   7511: iload #19
    //   7513: iload #20
    //   7515: iconst_4
    //   7516: imul
    //   7517: iadd
    //   7518: iconst_3
    //   7519: iadd
    //   7520: baload
    //   7521: sipush #255
    //   7524: iand
    //   7525: ior
    //   7526: iastore
    //   7527: iinc #20, 1
    //   7530: iload_2
    //   7531: ifne -> 7446
    //   7534: iconst_0
    //   7535: istore #25
    //   7537: aload #15
    //   7539: iconst_0
    //   7540: iaload
    //   7541: istore #23
    //   7543: aload #15
    //   7545: iconst_1
    //   7546: iaload
    //   7547: istore #22
    //   7549: iload #23
    //   7551: iconst_4
    //   7552: iushr
    //   7553: iload #22
    //   7555: ixor
    //   7556: ldc 252645135
    //   7558: iand
    //   7559: istore #21
    //   7561: iload #22
    //   7563: iload #21
    //   7565: ixor
    //   7566: istore #22
    //   7568: iload #23
    //   7570: iload #21
    //   7572: iconst_4
    //   7573: ishl
    //   7574: ixor
    //   7575: istore #23
    //   7577: iload #23
    //   7579: bipush #16
    //   7581: iushr
    //   7582: iload #22
    //   7584: ixor
    //   7585: ldc 65535
    //   7587: iand
    //   7588: istore #21
    //   7590: iload #22
    //   7592: iload #21
    //   7594: ixor
    //   7595: istore #22
    //   7597: iload #23
    //   7599: iload #21
    //   7601: bipush #16
    //   7603: ishl
    //   7604: ixor
    //   7605: istore #23
    //   7607: iload #22
    //   7609: iconst_2
    //   7610: iushr
    //   7611: iload #23
    //   7613: ixor
    //   7614: ldc 858993459
    //   7616: iand
    //   7617: istore #21
    //   7619: iload #23
    //   7621: iload #21
    //   7623: ixor
    //   7624: istore #23
    //   7626: iload #22
    //   7628: iload #21
    //   7630: iconst_2
    //   7631: ishl
    //   7632: ixor
    //   7633: istore #22
    //   7635: iload #22
    //   7637: bipush #8
    //   7639: iushr
    //   7640: iload #23
    //   7642: ixor
    //   7643: ldc 16711935
    //   7645: iand
    //   7646: istore #21
    //   7648: iload #23
    //   7650: iload #21
    //   7652: ixor
    //   7653: istore #23
    //   7655: iload #22
    //   7657: iload #21
    //   7659: bipush #8
    //   7661: ishl
    //   7662: ixor
    //   7663: istore #22
    //   7665: iload #22
    //   7667: iconst_1
    //   7668: ishl
    //   7669: iload #22
    //   7671: bipush #31
    //   7673: iushr
    //   7674: iconst_1
    //   7675: iand
    //   7676: ior
    //   7677: istore #22
    //   7679: iload #23
    //   7681: iload #22
    //   7683: ixor
    //   7684: ldc -1431655766
    //   7686: iand
    //   7687: istore #21
    //   7689: iload #23
    //   7691: iload #21
    //   7693: ixor
    //   7694: istore #23
    //   7696: iload #22
    //   7698: iload #21
    //   7700: ixor
    //   7701: istore #22
    //   7703: iload #23
    //   7705: iconst_1
    //   7706: ishl
    //   7707: iload #23
    //   7709: bipush #31
    //   7711: iushr
    //   7712: iconst_1
    //   7713: iand
    //   7714: ior
    //   7715: istore #23
    //   7717: iconst_0
    //   7718: istore #24
    //   7720: iload #24
    //   7722: bipush #8
    //   7724: if_icmpge -> 8062
    //   7727: iload #22
    //   7729: bipush #28
    //   7731: ishl
    //   7732: iload #22
    //   7734: iconst_4
    //   7735: iushr
    //   7736: ior
    //   7737: istore #21
    //   7739: iload #21
    //   7741: aload #5
    //   7743: iload #25
    //   7745: iinc #25, 1
    //   7748: iaload
    //   7749: ixor
    //   7750: istore #21
    //   7752: aload #12
    //   7754: iload #21
    //   7756: bipush #63
    //   7758: iand
    //   7759: iaload
    //   7760: istore #20
    //   7762: iload #20
    //   7764: aload #10
    //   7766: iload #21
    //   7768: bipush #8
    //   7770: iushr
    //   7771: bipush #63
    //   7773: iand
    //   7774: iaload
    //   7775: ior
    //   7776: istore #20
    //   7778: iload #20
    //   7780: aload #8
    //   7782: iload #21
    //   7784: bipush #16
    //   7786: iushr
    //   7787: bipush #63
    //   7789: iand
    //   7790: iaload
    //   7791: ior
    //   7792: istore #20
    //   7794: iload #20
    //   7796: aload #6
    //   7798: iload #21
    //   7800: bipush #24
    //   7802: iushr
    //   7803: bipush #63
    //   7805: iand
    //   7806: iaload
    //   7807: ior
    //   7808: istore #20
    //   7810: iload #22
    //   7812: aload #5
    //   7814: iload #25
    //   7816: iinc #25, 1
    //   7819: iaload
    //   7820: ixor
    //   7821: istore #21
    //   7823: iload #20
    //   7825: aload #13
    //   7827: iload #21
    //   7829: bipush #63
    //   7831: iand
    //   7832: iaload
    //   7833: ior
    //   7834: istore #20
    //   7836: iload #20
    //   7838: aload #11
    //   7840: iload #21
    //   7842: bipush #8
    //   7844: iushr
    //   7845: bipush #63
    //   7847: iand
    //   7848: iaload
    //   7849: ior
    //   7850: istore #20
    //   7852: iload #20
    //   7854: aload #9
    //   7856: iload #21
    //   7858: bipush #16
    //   7860: iushr
    //   7861: bipush #63
    //   7863: iand
    //   7864: iaload
    //   7865: ior
    //   7866: istore #20
    //   7868: iload #20
    //   7870: aload #7
    //   7872: iload #21
    //   7874: bipush #24
    //   7876: iushr
    //   7877: bipush #63
    //   7879: iand
    //   7880: iaload
    //   7881: ior
    //   7882: istore #20
    //   7884: iload #23
    //   7886: iload #20
    //   7888: ixor
    //   7889: istore #23
    //   7891: iload #23
    //   7893: bipush #28
    //   7895: ishl
    //   7896: iload #23
    //   7898: iconst_4
    //   7899: iushr
    //   7900: ior
    //   7901: istore #21
    //   7903: iload #21
    //   7905: aload #5
    //   7907: iload #25
    //   7909: iinc #25, 1
    //   7912: iaload
    //   7913: ixor
    //   7914: istore #21
    //   7916: aload #12
    //   7918: iload #21
    //   7920: bipush #63
    //   7922: iand
    //   7923: iaload
    //   7924: istore #20
    //   7926: iload #20
    //   7928: aload #10
    //   7930: iload #21
    //   7932: bipush #8
    //   7934: iushr
    //   7935: bipush #63
    //   7937: iand
    //   7938: iaload
    //   7939: ior
    //   7940: istore #20
    //   7942: iload #20
    //   7944: aload #8
    //   7946: iload #21
    //   7948: bipush #16
    //   7950: iushr
    //   7951: bipush #63
    //   7953: iand
    //   7954: iaload
    //   7955: ior
    //   7956: istore #20
    //   7958: iload #20
    //   7960: aload #6
    //   7962: iload #21
    //   7964: bipush #24
    //   7966: iushr
    //   7967: bipush #63
    //   7969: iand
    //   7970: iaload
    //   7971: ior
    //   7972: istore #20
    //   7974: iload #23
    //   7976: aload #5
    //   7978: iload #25
    //   7980: iinc #25, 1
    //   7983: iaload
    //   7984: ixor
    //   7985: istore #21
    //   7987: iload #20
    //   7989: aload #13
    //   7991: iload #21
    //   7993: bipush #63
    //   7995: iand
    //   7996: iaload
    //   7997: ior
    //   7998: istore #20
    //   8000: iload #20
    //   8002: aload #11
    //   8004: iload #21
    //   8006: bipush #8
    //   8008: iushr
    //   8009: bipush #63
    //   8011: iand
    //   8012: iaload
    //   8013: ior
    //   8014: istore #20
    //   8016: iload #20
    //   8018: aload #9
    //   8020: iload #21
    //   8022: bipush #16
    //   8024: iushr
    //   8025: bipush #63
    //   8027: iand
    //   8028: iaload
    //   8029: ior
    //   8030: istore #20
    //   8032: iload #20
    //   8034: aload #7
    //   8036: iload #21
    //   8038: bipush #24
    //   8040: iushr
    //   8041: bipush #63
    //   8043: iand
    //   8044: iaload
    //   8045: ior
    //   8046: istore #20
    //   8048: iload #22
    //   8050: iload #20
    //   8052: ixor
    //   8053: istore #22
    //   8055: iinc #24, 1
    //   8058: iload_2
    //   8059: ifne -> 7720
    //   8062: iload #22
    //   8064: bipush #31
    //   8066: ishl
    //   8067: iload #22
    //   8069: iconst_1
    //   8070: iushr
    //   8071: ior
    //   8072: istore #22
    //   8074: iload #23
    //   8076: iload #22
    //   8078: ixor
    //   8079: ldc -1431655766
    //   8081: iand
    //   8082: istore #21
    //   8084: iload #23
    //   8086: iload #21
    //   8088: ixor
    //   8089: istore #23
    //   8091: iload #22
    //   8093: iload #21
    //   8095: ixor
    //   8096: istore #22
    //   8098: iload #23
    //   8100: bipush #31
    //   8102: ishl
    //   8103: iload #23
    //   8105: iconst_1
    //   8106: iushr
    //   8107: ior
    //   8108: istore #23
    //   8110: iload #23
    //   8112: bipush #8
    //   8114: iushr
    //   8115: iload #22
    //   8117: ixor
    //   8118: ldc 16711935
    //   8120: iand
    //   8121: istore #21
    //   8123: iload #22
    //   8125: iload #21
    //   8127: ixor
    //   8128: istore #22
    //   8130: iload #23
    //   8132: iload #21
    //   8134: bipush #8
    //   8136: ishl
    //   8137: ixor
    //   8138: istore #23
    //   8140: iload #23
    //   8142: iconst_2
    //   8143: iushr
    //   8144: iload #22
    //   8146: ixor
    //   8147: ldc 858993459
    //   8149: iand
    //   8150: istore #21
    //   8152: iload #22
    //   8154: iload #21
    //   8156: ixor
    //   8157: istore #22
    //   8159: iload #23
    //   8161: iload #21
    //   8163: iconst_2
    //   8164: ishl
    //   8165: ixor
    //   8166: istore #23
    //   8168: iload #22
    //   8170: bipush #16
    //   8172: iushr
    //   8173: iload #23
    //   8175: ixor
    //   8176: ldc 65535
    //   8178: iand
    //   8179: istore #21
    //   8181: iload #23
    //   8183: iload #21
    //   8185: ixor
    //   8186: istore #23
    //   8188: iload #22
    //   8190: iload #21
    //   8192: bipush #16
    //   8194: ishl
    //   8195: ixor
    //   8196: istore #22
    //   8198: iload #22
    //   8200: iconst_4
    //   8201: iushr
    //   8202: iload #23
    //   8204: ixor
    //   8205: ldc 252645135
    //   8207: iand
    //   8208: istore #21
    //   8210: iload #23
    //   8212: iload #21
    //   8214: ixor
    //   8215: istore #23
    //   8217: iload #22
    //   8219: iload #21
    //   8221: iconst_4
    //   8222: ishl
    //   8223: ixor
    //   8224: istore #22
    //   8226: aload #15
    //   8228: iconst_0
    //   8229: iload #22
    //   8231: iastore
    //   8232: aload #15
    //   8234: iconst_1
    //   8235: iload #23
    //   8237: iastore
    //   8238: iload #18
    //   8240: bipush #8
    //   8242: imul
    //   8243: istore #26
    //   8245: iconst_0
    //   8246: istore #27
    //   8248: iload #27
    //   8250: iconst_2
    //   8251: if_icmpge -> 8340
    //   8254: aload #16
    //   8256: iload #26
    //   8258: iload #27
    //   8260: iconst_4
    //   8261: imul
    //   8262: iadd
    //   8263: aload #15
    //   8265: iload #27
    //   8267: iaload
    //   8268: bipush #24
    //   8270: iushr
    //   8271: i2b
    //   8272: bastore
    //   8273: aload #16
    //   8275: iload #26
    //   8277: iload #27
    //   8279: iconst_4
    //   8280: imul
    //   8281: iadd
    //   8282: iconst_1
    //   8283: iadd
    //   8284: aload #15
    //   8286: iload #27
    //   8288: iaload
    //   8289: bipush #16
    //   8291: iushr
    //   8292: i2b
    //   8293: bastore
    //   8294: aload #16
    //   8296: iload #26
    //   8298: iload #27
    //   8300: iconst_4
    //   8301: imul
    //   8302: iadd
    //   8303: iconst_2
    //   8304: iadd
    //   8305: aload #15
    //   8307: iload #27
    //   8309: iaload
    //   8310: bipush #8
    //   8312: iushr
    //   8313: i2b
    //   8314: bastore
    //   8315: aload #16
    //   8317: iload #26
    //   8319: iload #27
    //   8321: iconst_4
    //   8322: imul
    //   8323: iadd
    //   8324: iconst_3
    //   8325: iadd
    //   8326: aload #15
    //   8328: iload #27
    //   8330: iaload
    //   8331: i2b
    //   8332: bastore
    //   8333: iinc #27, 1
    //   8336: iload_2
    //   8337: ifne -> 8248
    //   8340: iinc #18, 1
    //   8343: iload_2
    //   8344: ifne -> 7429
    //   8347: aload #16
    //   8349: aload #16
    //   8351: arraylength
    //   8352: iconst_1
    //   8353: isub
    //   8354: baload
    //   8355: istore #18
    //   8357: aload #16
    //   8359: arraylength
    //   8360: iload #18
    //   8362: isub
    //   8363: newarray byte
    //   8365: astore #4
    //   8367: aload #16
    //   8369: arraylength
    //   8370: aload #4
    //   8372: arraylength
    //   8373: if_icmpge -> 8397
    //   8376: new java/lang/Exception
    //   8379: dup
    //   8380: sipush #-15255
    //   8383: sipush #-14595
    //   8386: invokestatic a : (II)Ljava/lang/String;
    //   8389: invokespecial <init> : (Ljava/lang/String;)V
    //   8392: athrow
    //   8393: invokestatic a : (Ljava/lang/Throwable;)Ljava/lang/Throwable;
    //   8396: athrow
    //   8397: iconst_0
    //   8398: istore #19
    //   8400: iload #19
    //   8402: aload #4
    //   8404: arraylength
    //   8405: if_icmpge -> 8425
    //   8408: aload #4
    //   8410: iload #19
    //   8412: aload #16
    //   8414: iload #19
    //   8416: baload
    //   8417: bastore
    //   8418: iinc #19, 1
    //   8421: iload_2
    //   8422: ifne -> 8400
    //   8425: new java/math/BigInteger
    //   8428: dup
    //   8429: aload #4
    //   8431: invokespecial <init> : ([B)V
    //   8434: invokevirtual abs : ()Ljava/math/BigInteger;
    //   8437: putstatic burp/Zgt6.ZU : Ljava/lang/Object;
    //   8440: sipush #-15256
    //   8443: getstatic burp/Zs5y.Zd : Ljava/lang/Object;
    //   8446: checkcast java/math/BigInteger
    //   8449: getstatic burp/Zb29.ZM : Ljava/lang/Object;
    //   8452: checkcast java/math/BigInteger
    //   8455: invokevirtual subtract : (Ljava/math/BigInteger;)Ljava/math/BigInteger;
    //   8458: putstatic burp/Zlxs.ZK : Ljava/lang/Object;
    //   8461: sipush #-21682
    //   8464: invokestatic a : (II)Ljava/lang/String;
    //   8467: iconst_1
    //   8468: ldc burp/Zb20
    //   8470: invokevirtual getClassLoader : ()Ljava/lang/ClassLoader;
    //   8473: invokestatic forName : (Ljava/lang/String;ZLjava/lang/ClassLoader;)Ljava/lang/Class;
    //   8476: invokevirtual getDeclaredFields : ()[Ljava/lang/reflect/Field;
    //   8479: astore_3
    //   8480: aload_3
    //   8481: arraylength
    //   8482: istore #4
    //   8484: iconst_0
    //   8485: istore #5
    //   8487: iload #5
    //   8489: iload #4
    //   8491: if_icmpge -> 8628
    //   8494: aload_3
    //   8495: iload #5
    //   8497: aaload
    //   8498: astore #6
    //   8500: aload #6
    //   8502: invokevirtual getModifiers : ()I
    //   8505: invokestatic isStatic : (I)Z
    //   8508: ifne -> 8518
    //   8511: goto -> 8621
    //   8514: invokestatic a : (Ljava/lang/Throwable;)Ljava/lang/Throwable;
    //   8517: athrow
    //   8518: aload #6
    //   8520: invokevirtual getType : ()Ljava/lang/Class;
    //   8523: astore #7
    //   8525: aload #7
    //   8527: ifnull -> 8608
    //   8530: aload #7
    //   8532: invokevirtual isPrimitive : ()Z
    //   8535: ifne -> 8608
    //   8538: goto -> 8545
    //   8541: invokestatic a : (Ljava/lang/Throwable;)Ljava/lang/Throwable;
    //   8544: athrow
    //   8545: aload #7
    //   8547: invokevirtual getPackage : ()Ljava/lang/Package;
    //   8550: ifnull -> 8608
    //   8553: goto -> 8560
    //   8556: invokestatic a : (Ljava/lang/Throwable;)Ljava/lang/Throwable;
    //   8559: athrow
    //   8560: aload #7
    //   8562: invokevirtual getPackage : ()Ljava/lang/Package;
    //   8565: invokevirtual getName : ()Ljava/lang/String;
    //   8568: ifnull -> 8608
    //   8571: goto -> 8578
    //   8574: invokestatic a : (Ljava/lang/Throwable;)Ljava/lang/Throwable;
    //   8577: athrow
    //   8578: aload #7
    //   8580: invokevirtual getPackage : ()Ljava/lang/Package;
    //   8583: invokevirtual getName : ()Ljava/lang/String;
    //   8586: sipush #-15250
    //   8589: sipush #-21631
    //   8592: invokestatic a : (II)Ljava/lang/String;
    //   8595: invokevirtual startsWith : (Ljava/lang/String;)Z
    //   8598: ifne -> 8608
    //   8601: goto -> 8608
    //   8604: invokestatic a : (Ljava/lang/Throwable;)Ljava/lang/Throwable;
    //   8607: athrow
    //   8608: aload #6
    //   8610: iconst_1
    //   8611: invokevirtual setAccessible : (Z)V
    //   8614: aload #6
    //   8616: aconst_null
    //   8617: invokevirtual get : (Ljava/lang/Object;)Ljava/lang/Object;
    //   8620: pop
    //   8621: iinc #5, 1
    //   8624: iload_2
    //   8625: ifne -> 8487
    //   8628: sipush #-15252
    //   8631: sipush #-16041
    //   8634: invokestatic a : (II)Ljava/lang/String;
    //   8637: invokestatic forName : (Ljava/lang/String;)Ljava/lang/Class;
    //   8640: invokevirtual getDeclaredMethods : ()[Ljava/lang/reflect/Method;
    //   8643: astore_3
    //   8644: aload_3
    //   8645: arraylength
    //   8646: istore #4
    //   8648: iconst_0
    //   8649: istore #5
    //   8651: iload #5
    //   8653: iload #4
    //   8655: if_icmpge -> 8766
    //   8658: aload_3
    //   8659: iload #5
    //   8661: aaload
    //   8662: astore #6
    //   8664: aload #6
    //   8666: invokevirtual getParameterTypes : ()[Ljava/lang/Class;
    //   8669: pop
    //   8670: aload #6
    //   8672: invokevirtual getModifiers : ()I
    //   8675: invokestatic isStatic : (I)Z
    //   8678: ifeq -> 8752
    //   8681: aload #6
    //   8683: invokevirtual getParameterTypes : ()[Ljava/lang/Class;
    //   8686: arraylength
    //   8687: iconst_2
    //   8688: if_icmpne -> 8752
    //   8691: goto -> 8698
    //   8694: invokestatic a : (Ljava/lang/Throwable;)Ljava/lang/Throwable;
    //   8697: athrow
    //   8698: aload #6
    //   8700: invokevirtual getReturnType : ()Ljava/lang/Class;
    //   8703: getstatic java/lang/Boolean.TYPE : Ljava/lang/Class;
    //   8706: if_acmpne -> 8752
    //   8709: goto -> 8716
    //   8712: invokestatic a : (Ljava/lang/Throwable;)Ljava/lang/Throwable;
    //   8715: athrow
    //   8716: aload #6
    //   8718: iconst_1
    //   8719: invokevirtual setAccessible : (Z)V
    //   8722: aload #6
    //   8724: aconst_null
    //   8725: iconst_2
    //   8726: anewarray java/lang/Object
    //   8729: dup
    //   8730: iconst_0
    //   8731: aload_0
    //   8732: aastore
    //   8733: dup
    //   8734: iconst_1
    //   8735: aload_1
    //   8736: aastore
    //   8737: invokevirtual invoke : (Ljava/lang/Object;[Ljava/lang/Object;)Ljava/lang/Object;
    //   8740: pop
    //   8741: iload_2
    //   8742: ifne -> 8766
    //   8745: goto -> 8752
    //   8748: invokestatic a : (Ljava/lang/Throwable;)Ljava/lang/Throwable;
    //   8751: athrow
    //   8752: iinc #5, 1
    //   8755: iload_2
    //   8756: ifne -> 8651
    //   8759: goto -> 8766
    //   8762: invokestatic a : (Ljava/lang/Throwable;)Ljava/lang/Throwable;
    //   8765: athrow
    //   8766: sipush #-15249
    //   8769: sipush #32287
    //   8772: invokestatic a : (II)Ljava/lang/String;
    //   8775: iconst_1
    //   8776: ldc burp/Zzb2
    //   8778: invokevirtual getClassLoader : ()Ljava/lang/ClassLoader;
    //   8781: invokestatic forName : (Ljava/lang/String;ZLjava/lang/ClassLoader;)Ljava/lang/Class;
    //   8784: invokevirtual getDeclaredFields : ()[Ljava/lang/reflect/Field;
    //   8787: astore_3
    //   8788: aload_3
    //   8789: arraylength
    //   8790: istore #4
    //   8792: iconst_0
    //   8793: istore #5
    //   8795: iload #5
    //   8797: iload #4
    //   8799: if_icmpge -> 8936
    //   8802: aload_3
    //   8803: iload #5
    //   8805: aaload
    //   8806: astore #6
    //   8808: aload #6
    //   8810: invokevirtual getModifiers : ()I
    //   8813: invokestatic isStatic : (I)Z
    //   8816: ifne -> 8826
    //   8819: goto -> 8929
    //   8822: invokestatic a : (Ljava/lang/Throwable;)Ljava/lang/Throwable;
    //   8825: athrow
    //   8826: aload #6
    //   8828: invokevirtual getType : ()Ljava/lang/Class;
    //   8831: astore #7
    //   8833: aload #7
    //   8835: ifnull -> 8916
    //   8838: aload #7
    //   8840: invokevirtual isPrimitive : ()Z
    //   8843: ifne -> 8916
    //   8846: goto -> 8853
    //   8849: invokestatic a : (Ljava/lang/Throwable;)Ljava/lang/Throwable;
    //   8852: athrow
    //   8853: aload #7
    //   8855: invokevirtual getPackage : ()Ljava/lang/Package;
    //   8858: ifnull -> 8916
    //   8861: goto -> 8868
    //   8864: invokestatic a : (Ljava/lang/Throwable;)Ljava/lang/Throwable;
    //   8867: athrow
    //   8868: aload #7
    //   8870: invokevirtual getPackage : ()Ljava/lang/Package;
    //   8873: invokevirtual getName : ()Ljava/lang/String;
    //   8876: ifnull -> 8916
    //   8879: goto -> 8886
    //   8882: invokestatic a : (Ljava/lang/Throwable;)Ljava/lang/Throwable;
    //   8885: athrow
    //   8886: aload #7
    //   8888: invokevirtual getPackage : ()Ljava/lang/Package;
    //   8891: invokevirtual getName : ()Ljava/lang/String;
    //   8894: sipush #-15262
    //   8897: sipush #31365
    //   8900: invokestatic a : (II)Ljava/lang/String;
    //   8903: invokevirtual startsWith : (Ljava/lang/String;)Z
    //   8906: ifne -> 8916
    //   8909: goto -> 8916
    //   8912: invokestatic a : (Ljava/lang/Throwable;)Ljava/lang/Throwable;
    //   8915: athrow
    //   8916: aload #6
    //   8918: iconst_1
    //   8919: invokevirtual setAccessible : (Z)V
    //   8922: aload #6
    //   8924: aconst_null
    //   8925: invokevirtual get : (Ljava/lang/Object;)Ljava/lang/Object;
    //   8928: pop
    //   8929: iinc #5, 1
    //   8932: iload_2
    //   8933: ifne -> 8795
    //   8936: sipush #-15259
    //   8939: sipush #4803
    //   8942: invokestatic a : (II)Ljava/lang/String;
    //   8945: invokestatic forName : (Ljava/lang/String;)Ljava/lang/Class;
    //   8948: invokevirtual getDeclaredMethods : ()[Ljava/lang/reflect/Method;
    //   8951: astore_3
    //   8952: aload_3
    //   8953: arraylength
    //   8954: istore #4
    //   8956: iconst_0
    //   8957: istore #5
    //   8959: iload #5
    //   8961: iload #4
    //   8963: if_icmpge -> 9095
    //   8966: aload_3
    //   8967: iload #5
    //   8969: aaload
    //   8970: astore #6
    //   8972: aload #6
    //   8974: invokevirtual getParameterTypes : ()[Ljava/lang/Class;
    //   8977: pop
    //   8978: aload #6
    //   8980: invokevirtual getModifiers : ()I
    //   8983: invokestatic isStatic : (I)Z
    //   8986: ifeq -> 9081
    //   8989: aload #6
    //   8991: invokevirtual getParameterTypes : ()[Ljava/lang/Class;
    //   8994: arraylength
    //   8995: iconst_2
    //   8996: if_icmpne -> 9081
    //   8999: goto -> 9006
    //   9002: invokestatic a : (Ljava/lang/Throwable;)Ljava/lang/Throwable;
    //   9005: athrow
    //   9006: aload #6
    //   9008: invokevirtual getReturnType : ()Ljava/lang/Class;
    //   9011: getstatic java/lang/Void.TYPE : Ljava/lang/Class;
    //   9014: invokevirtual equals : (Ljava/lang/Object;)Z
    //   9017: ifeq -> 9081
    //   9020: goto -> 9027
    //   9023: invokestatic a : (Ljava/lang/Throwable;)Ljava/lang/Throwable;
    //   9026: athrow
    //   9027: aload #6
    //   9029: iconst_1
    //   9030: invokevirtual setAccessible : (Z)V
    //   9033: aload #6
    //   9035: aconst_null
    //   9036: iconst_2
    //   9037: anewarray java/lang/Object
    //   9040: dup
    //   9041: iconst_0
    //   9042: aload_0
    //   9043: aastore
    //   9044: dup
    //   9045: iconst_1
    //   9046: aload_1
    //   9047: ifnonnull -> 9065
    //   9050: goto -> 9057
    //   9053: invokestatic a : (Ljava/lang/Throwable;)Ljava/lang/Throwable;
    //   9056: athrow
    //   9057: aload_1
    //   9058: goto -> 9072
    //   9061: invokestatic a : (Ljava/lang/Throwable;)Ljava/lang/Throwable;
    //   9064: athrow
    //   9065: aload_1
    //   9066: checkcast [B
    //   9069: invokevirtual clone : ()Ljava/lang/Object;
    //   9072: aastore
    //   9073: invokevirtual invoke : (Ljava/lang/Object;[Ljava/lang/Object;)Ljava/lang/Object;
    //   9076: pop
    //   9077: iload_2
    //   9078: ifne -> 9095
    //   9081: iinc #5, 1
    //   9084: iload_2
    //   9085: ifne -> 8959
    //   9088: goto -> 9095
    //   9091: invokestatic a : (Ljava/lang/Throwable;)Ljava/lang/Throwable;
    //   9094: athrow
    //   9095: getstatic burp/Zem6.Zp : Ljava/lang/String;
    //   9098: getstatic burp/Zkdq.ZG : Ljava/lang/Object;
    //   9101: checkcast java/math/BigInteger
    //   9104: invokevirtual intValue : ()I
    //   9107: bipush #32
    //   9109: irem
    //   9110: invokestatic abs : (I)I
    //   9113: invokevirtual charAt : (I)C
    //   9116: getstatic burp/Zs6g.ZU : Ljava/lang/String;
    //   9119: getstatic burp/Zeai.ZI : Ljava/lang/Object;
    //   9122: checkcast java/math/BigInteger
    //   9125: invokevirtual intValue : ()I
    //   9128: bipush #32
    //   9130: irem
    //   9131: invokestatic abs : (I)I
    //   9134: invokevirtual charAt : (I)C
    //   9137: if_icmple -> 9252
    //   9140: getstatic burp/Zls0.ZI : Ljava/lang/String;
    //   9143: getstatic burp/Zz35.ZB : Ljava/lang/Object;
    //   9146: checkcast java/math/BigInteger
    //   9149: invokevirtual intValue : ()I
    //   9152: bipush #32
    //   9154: irem
    //   9155: invokestatic abs : (I)I
    //   9158: invokevirtual charAt : (I)C
    //   9161: getstatic burp/Zs0h.ZX : Ljava/lang/String;
    //   9164: getstatic burp/Ze4x.Zp : Ljava/lang/Object;
    //   9167: checkcast java/math/BigInteger
    //   9170: invokevirtual intValue : ()I
    //   9173: bipush #32
    //   9175: irem
    //   9176: invokestatic abs : (I)I
    //   9179: invokevirtual charAt : (I)C
    //   9182: if_icmpgt -> 9252
    //   9185: goto -> 9192
    //   9188: invokestatic a : (Ljava/lang/Throwable;)Ljava/lang/Throwable;
    //   9191: athrow
    //   9192: getstatic burp/Zrva.Zr : Ljava/lang/String;
    //   9195: getstatic burp/Zm6h.ZB : Ljava/lang/Object;
    //   9198: checkcast java/math/BigInteger
    //   9201: invokevirtual intValue : ()I
    //   9204: bipush #32
    //   9206: irem
    //   9207: invokestatic abs : (I)I
    //   9210: invokevirtual charAt : (I)C
    //   9213: getstatic burp/Zlpn.ZF : Ljava/lang/String;
    //   9216: getstatic burp/Zzco.ZC : Ljava/lang/Object;
    //   9219: checkcast java/math/BigInteger
    //   9222: invokevirtual intValue : ()I
    //   9225: bipush #32
    //   9227: irem
    //   9228: invokestatic abs : (I)I
    //   9231: invokevirtual charAt : (I)C
    //   9234: if_icmple -> 9252
    //   9237: goto -> 9244
    //   9240: invokestatic a : (Ljava/lang/Throwable;)Ljava/lang/Throwable;
    //   9243: athrow
    //   9244: iconst_1
    //   9245: goto -> 9253
    //   9248: invokestatic a : (Ljava/lang/Throwable;)Ljava/lang/Throwable;
    //   9251: athrow
    //   9252: iconst_0
    //   9253: ireturn
    //   9254: astore_3
    //   9255: new java/lang/Exception
    //   9258: dup
    //   9259: aload_3
    //   9260: invokevirtual getMessage : ()Ljava/lang/String;
    //   9263: invokespecial <init> : (Ljava/lang/String;)V
    //   9266: athrow
    // Exception table:
    //   from	to	target	type
    //   4	9253	9254	java/lang/Throwable
    //   805	839	842	java/lang/Throwable
    //   934	1012	1015	java/lang/Throwable
    //   941	1155	1158	java/lang/Throwable
    //   1532	1547	1547	java/lang/Throwable
    //   1574	1608	1611	java/lang/Throwable
    //   1618	1630	1633	java/lang/Throwable
    //   1716	1794	1797	java/lang/Throwable
    //   1723	1937	1940	java/lang/Throwable
    //   2337	2415	2418	java/lang/Throwable
    //   2344	2558	2561	java/lang/Throwable
    //   3005	3039	3042	java/lang/Throwable
    //   3046	3058	3061	java/lang/Throwable
    //   3144	3222	3225	java/lang/Throwable
    //   3151	3365	3368	java/lang/Throwable
    //   7379	7404	7404	java/lang/Throwable
    //   8367	8393	8393	java/lang/Throwable
    //   8500	8514	8514	java/lang/Throwable
    //   8525	8538	8541	java/lang/Throwable
    //   8530	8553	8556	java/lang/Throwable
    //   8545	8571	8574	java/lang/Throwable
    //   8560	8601	8604	java/lang/Throwable
    //   8664	8691	8694	java/lang/Throwable
    //   8681	8709	8712	java/lang/Throwable
    //   8698	8745	8748	java/lang/Throwable
    //   8716	8759	8762	java/lang/Throwable
    //   8808	8822	8822	java/lang/Throwable
    //   8833	8846	8849	java/lang/Throwable
    //   8838	8861	8864	java/lang/Throwable
    //   8853	8879	8882	java/lang/Throwable
    //   8868	8909	8912	java/lang/Throwable
    //   8972	8999	9002	java/lang/Throwable
    //   8989	9020	9023	java/lang/Throwable
    //   9006	9050	9053	java/lang/Throwable
    //   9027	9061	9061	java/lang/Throwable
    //   9072	9088	9091	java/lang/Throwable
    //   9095	9185	9188	java/lang/Throwable
    //   9140	9237	9240	java/lang/Throwable
    //   9192	9248	9248	java/lang/Throwable
  }
  
  static {
    // Byte code:
    //   0: bipush #14
    //   2: anewarray java/lang/String
    //   5: astore #5
    //   7: iconst_0
    //   8: istore_3
    //   9: ldc '($ico\\tHg}!HMV\\b4TRJMplS>3YztfxX#V@FkO+yn,PrT{\\fM6n?ts<0*[d DvM$g<du\\tW*^>C>Kaqi\\tKo\\tT3\\rE1\\t;o \\btKgt/G\\n[;[M {QXUH;REl-h^7~'
    //   11: dup
    //   12: astore_2
    //   13: invokevirtual length : ()I
    //   16: istore #4
    //   18: bipush #19
    //   20: istore_1
    //   21: iconst_m1
    //   22: istore_0
    //   23: bipush #119
    //   25: iinc #0, 1
    //   28: aload_2
    //   29: iload_0
    //   30: dup
    //   31: iload_1
    //   32: iadd
    //   33: invokevirtual substring : (II)Ljava/lang/String;
    //   36: iconst_m1
    //   37: goto -> 143
    //   40: aload #5
    //   42: swap
    //   43: iload_3
    //   44: iinc #3, 1
    //   47: swap
    //   48: aastore
    //   49: iload_0
    //   50: iload_1
    //   51: iadd
    //   52: dup
    //   53: istore_0
    //   54: iload #4
    //   56: if_icmpge -> 68
    //   59: aload_2
    //   60: iload_0
    //   61: invokevirtual charAt : (I)C
    //   64: istore_1
    //   65: goto -> 23
    //   68: ldc 'C\\tZ5`\\t6G'
    //   70: dup
    //   71: astore_2
    //   72: invokevirtual length : ()I
    //   75: istore #4
    //   77: bipush #9
    //   79: istore_1
    //   80: iconst_m1
    //   81: istore_0
    //   82: bipush #20
    //   84: iinc #0, 1
    //   87: aload_2
    //   88: iload_0
    //   89: dup
    //   90: iload_1
    //   91: iadd
    //   92: invokevirtual substring : (II)Ljava/lang/String;
    //   95: iconst_0
    //   96: goto -> 143
    //   99: aload #5
    //   101: swap
    //   102: iload_3
    //   103: iinc #3, 1
    //   106: swap
    //   107: aastore
    //   108: iload_0
    //   109: iload_1
    //   110: iadd
    //   111: dup
    //   112: istore_0
    //   113: iload #4
    //   115: if_icmpge -> 127
    //   118: aload_2
    //   119: iload_0
    //   120: invokevirtual charAt : (I)C
    //   123: istore_1
    //   124: goto -> 82
    //   127: aload #5
    //   129: putstatic burp/Zb0z.a : [Ljava/lang/String;
    //   132: bipush #14
    //   134: anewarray java/lang/String
    //   137: putstatic burp/Zb0z.b : [Ljava/lang/String;
    //   140: goto -> 300
    //   143: dup_x2
    //   144: pop
    //   145: invokevirtual toCharArray : ()[C
    //   148: dup_x1
    //   149: arraylength
    //   150: dup_x2
    //   151: pop
    //   152: iconst_0
    //   153: istore #6
    //   155: dup2_x1
    //   156: pop2
    //   157: dup_x2
    //   158: iconst_1
    //   159: if_icmpgt -> 260
    //   162: dup2
    //   163: swap
    //   164: iload #6
    //   166: dup2_x1
    //   167: caload
    //   168: swap
    //   169: iload #6
    //   171: bipush #7
    //   173: irem
    //   174: tableswitch default -> 242, 0 -> 212, 1 -> 217, 2 -> 222, 3 -> 227, 4 -> 232, 5 -> 237
    //   212: bipush #92
    //   214: goto -> 244
    //   217: bipush #77
    //   219: goto -> 244
    //   222: bipush #32
    //   224: goto -> 244
    //   227: bipush #92
    //   229: goto -> 244
    //   232: bipush #30
    //   234: goto -> 244
    //   237: bipush #71
    //   239: goto -> 244
    //   242: bipush #83
    //   244: ixor
    //   245: ixor
    //   246: i2c
    //   247: castore
    //   248: iinc #6, 1
    //   251: dup
    //   252: ifne -> 260
    //   255: dup2
    //   256: dup_x1
    //   257: goto -> 166
    //   260: dup2_x1
    //   261: pop2
    //   262: dup_x2
    //   263: iload #6
    //   265: if_icmpgt -> 162
    //   268: pop
    //   269: new java/lang/String
    //   272: dup_x1
    //   273: swap
    //   274: invokespecial <init> : ([C)V
    //   277: invokevirtual intern : ()Ljava/lang/String;
    //   280: swap
    //   281: pop
    //   282: swap
    //   283: tableswitch default -> 40, 0 -> 99
    //   300: sipush #-15264
    //   303: sipush #-24219
    //   306: invokestatic a : (II)Ljava/lang/String;
    //   309: putstatic burp/Zb0z.ZM : Ljava/lang/String;
    //   312: new java/math/BigInteger
    //   315: dup
    //   316: sipush #-15251
    //   319: sipush #-5316
    //   322: invokestatic a : (II)Ljava/lang/String;
    //   325: invokespecial <init> : (Ljava/lang/String;)V
    //   328: putstatic burp/Zb0z.ZQ : Ljava/lang/Object;
    //   331: return
  }
  
  private static Throwable a(Throwable paramThrowable) {
    return paramThrowable;
  }
  
  private static String a(int paramInt1, int paramInt2) {
    int i = (paramInt1 ^ 0xFFFFC469) & 0xFFFF;
    if (b[i] == null) {
      char[] arrayOfChar = a[i].toCharArray();
      switch (arrayOfChar[0] & 0xFF) {
        case 0:
        
        case 1:
        
        case 2:
        
        case 3:
        
        case 4:
        
        case 5:
        
        case 6:
        
        case 7:
        
        case 8:
        
        case 9:
        
        case 10:
        
        case 11:
        
        case 12:
        
        case 13:
        
        case 14:
        
        case 15:
        
        case 16:
        
        case 17:
        
        case 18:
        
        case 19:
        
        case 20:
        
        case 21:
        
        case 22:
        
        case 23:
        
        case 24:
        
        case 25:
        
        case 26:
        
        case 27:
        
        case 28:
        
        case 29:
        
        case 30:
        
        case 31:
        
        case 32:
        
        case 33:
        
        case 34:
        
        case 35:
        
        case 36:
        
        case 37:
        
        case 38:
        
        case 39:
        
        case 40:
        
        case 41:
        
        case 42:
        
        case 43:
        
        case 44:
        
        case 45:
        
        case 46:
        
        case 47:
        
        case 48:
        
        case 49:
        
        case 50:
        
        case 51:
        
        case 52:
        
        case 53:
        
        case 54:
        
        case 55:
        
        case 56:
        
        case 57:
        
        case 58:
        
        case 59:
        
        case 60:
        
        case 61:
        
        case 62:
        
        case 63:
        
        case 64:
        
        case 65:
        
        case 66:
        
        case 67:
        
        case 68:
        
        case 69:
        
        case 70:
        
        case 71:
        
        case 72:
        
        case 73:
        
        case 74:
        
        case 75:
        
        case 76:
        
        case 77:
        
        case 78:
        
        case 79:
        
        case 80:
        
        case 81:
        
        case 82:
        
        case 83:
        
        case 84:
        
        case 85:
        
        case 86:
        
        case 87:
        
        case 88:
        
        case 89:
        
        case 90:
        
        case 91:
        
        case 92:
        
        case 93:
        
        case 94:
        
        case 95:
        
        case 96:
        
        case 97:
        
        case 98:
        
        case 99:
        
        case 100:
        
        case 101:
        
        case 102:
        
        case 103:
        
        case 104:
        
        case 105:
        
        case 106:
        
        case 107:
        
        case 108:
        
        case 109:
        
        case 110:
        
        case 111:
        
        case 112:
        
        case 113:
        
        case 114:
        
        case 115:
        
        case 116:
        
        case 117:
        
        case 118:
        
        case 119:
        
        case 120:
        
        case 121:
        
        case 122:
        
        case 123:
        
        case 124:
        
        case 125:
        
        case 126:
        
        case 127:
        
        case 128:
        
        case 129:
        
        case 130:
        
        case 131:
        
        case 132:
        
        case 133:
        
        case 134:
        
        case 135:
        
        case 136:
        
        case 137:
        
        case 138:
        
        case 139:
        
        case 140:
        
        case 141:
        
        case 142:
        
        case 143:
        
        case 144:
        
        case 145:
        
        case 146:
        
        case 147:
        
        case 148:
        
        case 149:
        
        case 150:
        
        case 151:
        
        case 152:
        
        case 153:
        
        case 154:
        
        case 155:
        
        case 156:
        
        case 157:
        
        case 158:
        
        case 159:
        
        case 160:
        
        case 161:
        
        case 162:
        
        case 163:
        
        case 164:
        
        case 165:
        
        case 166:
        
        case 167:
        
        case 168:
        
        case 169:
        
        case 170:
        
        case 171:
        
        case 172:
        
        case 173:
        
        case 174:
        
        case 175:
        
        case 176:
        
        case 177:
        
        case 178:
        
        case 179:
        
        case 180:
        
        case 181:
        
        case 182:
        
        case 183:
        
        case 184:
        
        case 185:
        
        case 186:
        
        case 187:
        
        case 188:
        
        case 189:
        
        case 190:
        
        case 191:
        
        case 192:
        
        case 193:
        
        case 194:
        
        case 195:
        
        case 196:
        
        case 197:
        
        case 198:
        
        case 199:
        
        case 200:
        
        case 201:
        
        case 202:
        
        case 203:
        
        case 204:
        
        case 205:
        
        case 206:
        
        case 207:
        
        case 208:
        
        case 209:
        
        case 210:
        
        case 211:
        
        case 212:
        
        case 213:
        
        case 214:
        
        case 215:
        
        case 216:
        
        case 217:
        
        case 218:
        
        case 219:
        
        case 220:
        
        case 221:
        
        case 222:
        
        case 223:
        
        case 224:
        
        case 225:
        
        case 226:
        
        case 227:
        
        case 228:
        
        case 229:
        
        case 230:
        
        case 231:
        
        case 232:
        
        case 233:
        
        case 234:
        
        case 235:
        
        case 236:
        
        case 237:
        
        case 238:
        
        case 239:
        
        case 240:
        
        case 241:
        
        case 242:
        
        case 243:
        
        case 244:
        
        case 245:
        
        case 246:
        
        case 247:
        
        case 248:
        
        case 249:
        
        case 250:
        
        case 251:
        
        case 252:
        
        case 253:
        
        case 254:
        
        default:
          break;
      } 
      byte b1 = 0;
      int j = (paramInt2 & 0xFF) - b1;
      if (j < 0)
        j += 256; 
      int k = ((paramInt2 & 0xFFFF) >>> 8) - b1;
      if (k < 0)
        k += 256; 
      for (byte b2 = 0; b2 < arrayOfChar.length; b2++) {
        int m = b2 % 2;
        if (m == 0) {
          arrayOfChar[b2] = (char)(arrayOfChar[b2] ^ j);
          j = ((j >>> 3 | j << 5) ^ arrayOfChar[b2]) & 0xFF;
        } else {
          arrayOfChar[b2] = (char)(arrayOfChar[b2] ^ k);
          k = ((k >>> 3 | k << 5) ^ arrayOfChar[b2]) & 0xFF;
        } 
      } 
      b[i] = (new String(arrayOfChar)).intern();
    } 
    return b[i];
  }
}


/* Location:              C:\Program Files\BurpSuitePro\burpsuite_pro.jar!\burp\Zb0z.class
 * Java compiler version: 21 (65.0)
 * JD-Core Version:       1.1.3
 */