package burp;

import java.math.BigInteger;

class Zb20 extends ClassLoader {
  static String ZL;
  
  static Object Zq;
  
  private static final String[] a;
  
  private static final String[] b;
  
  static boolean ZD(Object[] paramArrayOfObject, Object paramObject) throws Throwable {
    // Byte code:
    //   0: invokestatic ZN : ()Z
    //   3: istore_2
    //   4: getstatic burp/Zgt6.ZU : Ljava/lang/Object;
    //   7: checkcast java/math/BigInteger
    //   10: getstatic burp/Zb14.ZT : Ljava/lang/Object;
    //   13: checkcast java/math/BigInteger
    //   16: invokevirtual add : (Ljava/math/BigInteger;)Ljava/math/BigInteger;
    //   19: putstatic burp/Zkco.Zg : Ljava/lang/Object;
    //   22: new java/lang/StringBuilder
    //   25: dup
    //   26: invokespecial <init> : ()V
    //   29: astore_3
    //   30: iconst_0
    //   31: istore #4
    //   33: iload #4
    //   35: bipush #32
    //   37: if_icmpge -> 1371
    //   40: iload #4
    //   42: tableswitch default -> 1364, 0 -> 184, 1 -> 221, 2 -> 258, 3 -> 295, 4 -> 332, 5 -> 369, 6 -> 406, 7 -> 443, 8 -> 480, 9 -> 517, 10 -> 554, 11 -> 591, 12 -> 628, 13 -> 665, 14 -> 702, 15 -> 739, 16 -> 776, 17 -> 813, 18 -> 850, 19 -> 887, 20 -> 924, 21 -> 961, 22 -> 998, 23 -> 1035, 24 -> 1072, 25 -> 1109, 26 -> 1146, 27 -> 1183, 28 -> 1220, 29 -> 1257, 30 -> 1294, 31 -> 1331
    //   184: aload_3
    //   185: getstatic burp/Zgt6.Zu : Ljava/lang/String;
    //   188: getstatic burp/Zrs0.Zz : Ljava/lang/Object;
    //   191: checkcast java/math/BigInteger
    //   194: invokevirtual intValue : ()I
    //   197: bipush #32
    //   199: irem
    //   200: invokestatic abs : (I)I
    //   203: invokevirtual charAt : (I)C
    //   206: invokevirtual append : (C)Ljava/lang/StringBuilder;
    //   209: pop
    //   210: iload_2
    //   211: ifne -> 1364
    //   214: goto -> 221
    //   217: invokestatic a : (Ljava/lang/Throwable;)Ljava/lang/Throwable;
    //   220: athrow
    //   221: aload_3
    //   222: getstatic burp/Zmtf.Zx : Ljava/lang/String;
    //   225: getstatic burp/Zzrb.Zj : Ljava/lang/Object;
    //   228: checkcast java/math/BigInteger
    //   231: invokevirtual intValue : ()I
    //   234: bipush #32
    //   236: irem
    //   237: invokestatic abs : (I)I
    //   240: invokevirtual charAt : (I)C
    //   243: invokevirtual append : (C)Ljava/lang/StringBuilder;
    //   246: pop
    //   247: iload_2
    //   248: ifne -> 1364
    //   251: goto -> 258
    //   254: invokestatic a : (Ljava/lang/Throwable;)Ljava/lang/Throwable;
    //   257: athrow
    //   258: aload_3
    //   259: getstatic burp/Zxtc.Zo : Ljava/lang/String;
    //   262: getstatic burp/Zrpy.ZG : Ljava/lang/Object;
    //   265: checkcast java/math/BigInteger
    //   268: invokevirtual intValue : ()I
    //   271: bipush #32
    //   273: irem
    //   274: invokestatic abs : (I)I
    //   277: invokevirtual charAt : (I)C
    //   280: invokevirtual append : (C)Ljava/lang/StringBuilder;
    //   283: pop
    //   284: iload_2
    //   285: ifne -> 1364
    //   288: goto -> 295
    //   291: invokestatic a : (Ljava/lang/Throwable;)Ljava/lang/Throwable;
    //   294: athrow
    //   295: aload_3
    //   296: getstatic burp/Ze_l.ZY : Ljava/lang/String;
    //   299: getstatic burp/Zeor.Zb : Ljava/lang/Object;
    //   302: checkcast java/math/BigInteger
    //   305: invokevirtual intValue : ()I
    //   308: bipush #32
    //   310: irem
    //   311: invokestatic abs : (I)I
    //   314: invokevirtual charAt : (I)C
    //   317: invokevirtual append : (C)Ljava/lang/StringBuilder;
    //   320: pop
    //   321: iload_2
    //   322: ifne -> 1364
    //   325: goto -> 332
    //   328: invokestatic a : (Ljava/lang/Throwable;)Ljava/lang/Throwable;
    //   331: athrow
    //   332: aload_3
    //   333: getstatic burp/Zlnq.ZQ : Ljava/lang/String;
    //   336: getstatic burp/Zlav.Zp : Ljava/lang/Object;
    //   339: checkcast java/math/BigInteger
    //   342: invokevirtual intValue : ()I
    //   345: bipush #32
    //   347: irem
    //   348: invokestatic abs : (I)I
    //   351: invokevirtual charAt : (I)C
    //   354: invokevirtual append : (C)Ljava/lang/StringBuilder;
    //   357: pop
    //   358: iload_2
    //   359: ifne -> 1364
    //   362: goto -> 369
    //   365: invokestatic a : (Ljava/lang/Throwable;)Ljava/lang/Throwable;
    //   368: athrow
    //   369: aload_3
    //   370: getstatic burp/Zmji.Zs : Ljava/lang/String;
    //   373: getstatic burp/Zrpy.ZG : Ljava/lang/Object;
    //   376: checkcast java/math/BigInteger
    //   379: invokevirtual intValue : ()I
    //   382: bipush #32
    //   384: irem
    //   385: invokestatic abs : (I)I
    //   388: invokevirtual charAt : (I)C
    //   391: invokevirtual append : (C)Ljava/lang/StringBuilder;
    //   394: pop
    //   395: iload_2
    //   396: ifne -> 1364
    //   399: goto -> 406
    //   402: invokestatic a : (Ljava/lang/Throwable;)Ljava/lang/Throwable;
    //   405: athrow
    //   406: aload_3
    //   407: getstatic burp/Zmrc.Zx : Ljava/lang/String;
    //   410: getstatic burp/Zrpy.ZG : Ljava/lang/Object;
    //   413: checkcast java/math/BigInteger
    //   416: invokevirtual intValue : ()I
    //   419: bipush #32
    //   421: irem
    //   422: invokestatic abs : (I)I
    //   425: invokevirtual charAt : (I)C
    //   428: invokevirtual append : (C)Ljava/lang/StringBuilder;
    //   431: pop
    //   432: iload_2
    //   433: ifne -> 1364
    //   436: goto -> 443
    //   439: invokestatic a : (Ljava/lang/Throwable;)Ljava/lang/Throwable;
    //   442: athrow
    //   443: aload_3
    //   444: getstatic burp/Zzok.ZC : Ljava/lang/String;
    //   447: getstatic burp/Zgkn.Zm : Ljava/lang/Object;
    //   450: checkcast java/math/BigInteger
    //   453: invokevirtual intValue : ()I
    //   456: bipush #32
    //   458: irem
    //   459: invokestatic abs : (I)I
    //   462: invokevirtual charAt : (I)C
    //   465: invokevirtual append : (C)Ljava/lang/StringBuilder;
    //   468: pop
    //   469: iload_2
    //   470: ifne -> 1364
    //   473: goto -> 480
    //   476: invokestatic a : (Ljava/lang/Throwable;)Ljava/lang/Throwable;
    //   479: athrow
    //   480: aload_3
    //   481: getstatic burp/Zb0z.ZM : Ljava/lang/String;
    //   484: getstatic burp/Zlsw.ZJ : Ljava/lang/Object;
    //   487: checkcast java/math/BigInteger
    //   490: invokevirtual intValue : ()I
    //   493: bipush #32
    //   495: irem
    //   496: invokestatic abs : (I)I
    //   499: invokevirtual charAt : (I)C
    //   502: invokevirtual append : (C)Ljava/lang/StringBuilder;
    //   505: pop
    //   506: iload_2
    //   507: ifne -> 1364
    //   510: goto -> 517
    //   513: invokestatic a : (Ljava/lang/Throwable;)Ljava/lang/Throwable;
    //   516: athrow
    //   517: aload_3
    //   518: getstatic burp/Zlr2.ZV : Ljava/lang/String;
    //   521: getstatic burp/Zr5k.Zj : Ljava/lang/Object;
    //   524: checkcast java/math/BigInteger
    //   527: invokevirtual intValue : ()I
    //   530: bipush #32
    //   532: irem
    //   533: invokestatic abs : (I)I
    //   536: invokevirtual charAt : (I)C
    //   539: invokevirtual append : (C)Ljava/lang/StringBuilder;
    //   542: pop
    //   543: iload_2
    //   544: ifne -> 1364
    //   547: goto -> 554
    //   550: invokestatic a : (Ljava/lang/Throwable;)Ljava/lang/Throwable;
    //   553: athrow
    //   554: aload_3
    //   555: getstatic burp/Zgta.ZL : Ljava/lang/String;
    //   558: getstatic burp/Zzbr.ZC : Ljava/lang/Object;
    //   561: checkcast java/math/BigInteger
    //   564: invokevirtual intValue : ()I
    //   567: bipush #32
    //   569: irem
    //   570: invokestatic abs : (I)I
    //   573: invokevirtual charAt : (I)C
    //   576: invokevirtual append : (C)Ljava/lang/StringBuilder;
    //   579: pop
    //   580: iload_2
    //   581: ifne -> 1364
    //   584: goto -> 591
    //   587: invokestatic a : (Ljava/lang/Throwable;)Ljava/lang/Throwable;
    //   590: athrow
    //   591: aload_3
    //   592: getstatic burp/Zejj.ZQ : Ljava/lang/String;
    //   595: getstatic burp/Zlo2.ZM : Ljava/lang/Object;
    //   598: checkcast java/math/BigInteger
    //   601: invokevirtual intValue : ()I
    //   604: bipush #32
    //   606: irem
    //   607: invokestatic abs : (I)I
    //   610: invokevirtual charAt : (I)C
    //   613: invokevirtual append : (C)Ljava/lang/StringBuilder;
    //   616: pop
    //   617: iload_2
    //   618: ifne -> 1364
    //   621: goto -> 628
    //   624: invokestatic a : (Ljava/lang/Throwable;)Ljava/lang/Throwable;
    //   627: athrow
    //   628: aload_3
    //   629: getstatic burp/Zss6.ZN : Ljava/lang/String;
    //   632: getstatic burp/Zb14.ZT : Ljava/lang/Object;
    //   635: checkcast java/math/BigInteger
    //   638: invokevirtual intValue : ()I
    //   641: bipush #32
    //   643: irem
    //   644: invokestatic abs : (I)I
    //   647: invokevirtual charAt : (I)C
    //   650: invokevirtual append : (C)Ljava/lang/StringBuilder;
    //   653: pop
    //   654: iload_2
    //   655: ifne -> 1364
    //   658: goto -> 665
    //   661: invokestatic a : (Ljava/lang/Throwable;)Ljava/lang/Throwable;
    //   664: athrow
    //   665: aload_3
    //   666: getstatic burp/Zm8i.Z_ : Ljava/lang/String;
    //   669: getstatic burp/Zejj.Zy : Ljava/lang/Object;
    //   672: checkcast java/math/BigInteger
    //   675: invokevirtual intValue : ()I
    //   678: bipush #32
    //   680: irem
    //   681: invokestatic abs : (I)I
    //   684: invokevirtual charAt : (I)C
    //   687: invokevirtual append : (C)Ljava/lang/StringBuilder;
    //   690: pop
    //   691: iload_2
    //   692: ifne -> 1364
    //   695: goto -> 702
    //   698: invokestatic a : (Ljava/lang/Throwable;)Ljava/lang/Throwable;
    //   701: athrow
    //   702: aload_3
    //   703: getstatic burp/Zgta.ZL : Ljava/lang/String;
    //   706: getstatic burp/Zlav.Zp : Ljava/lang/Object;
    //   709: checkcast java/math/BigInteger
    //   712: invokevirtual intValue : ()I
    //   715: bipush #32
    //   717: irem
    //   718: invokestatic abs : (I)I
    //   721: invokevirtual charAt : (I)C
    //   724: invokevirtual append : (C)Ljava/lang/StringBuilder;
    //   727: pop
    //   728: iload_2
    //   729: ifne -> 1364
    //   732: goto -> 739
    //   735: invokestatic a : (Ljava/lang/Throwable;)Ljava/lang/Throwable;
    //   738: athrow
    //   739: aload_3
    //   740: getstatic burp/Zgt7.ZO : Ljava/lang/String;
    //   743: getstatic burp/Zeqo.ZZ : Ljava/lang/Object;
    //   746: checkcast java/math/BigInteger
    //   749: invokevirtual intValue : ()I
    //   752: bipush #32
    //   754: irem
    //   755: invokestatic abs : (I)I
    //   758: invokevirtual charAt : (I)C
    //   761: invokevirtual append : (C)Ljava/lang/StringBuilder;
    //   764: pop
    //   765: iload_2
    //   766: ifne -> 1364
    //   769: goto -> 776
    //   772: invokestatic a : (Ljava/lang/Throwable;)Ljava/lang/Throwable;
    //   775: athrow
    //   776: aload_3
    //   777: getstatic burp/Zlo2.ZJ : Ljava/lang/String;
    //   780: getstatic burp/Zdk.Zy : Ljava/lang/Object;
    //   783: checkcast java/math/BigInteger
    //   786: invokevirtual intValue : ()I
    //   789: bipush #32
    //   791: irem
    //   792: invokestatic abs : (I)I
    //   795: invokevirtual charAt : (I)C
    //   798: invokevirtual append : (C)Ljava/lang/StringBuilder;
    //   801: pop
    //   802: iload_2
    //   803: ifne -> 1364
    //   806: goto -> 813
    //   809: invokestatic a : (Ljava/lang/Throwable;)Ljava/lang/Throwable;
    //   812: athrow
    //   813: aload_3
    //   814: getstatic burp/Zecw.Zb : Ljava/lang/String;
    //   817: getstatic burp/Zm8i.Zm : Ljava/lang/Object;
    //   820: checkcast java/math/BigInteger
    //   823: invokevirtual intValue : ()I
    //   826: bipush #32
    //   828: irem
    //   829: invokestatic abs : (I)I
    //   832: invokevirtual charAt : (I)C
    //   835: invokevirtual append : (C)Ljava/lang/StringBuilder;
    //   838: pop
    //   839: iload_2
    //   840: ifne -> 1364
    //   843: goto -> 850
    //   846: invokestatic a : (Ljava/lang/Throwable;)Ljava/lang/Throwable;
    //   849: athrow
    //   850: aload_3
    //   851: getstatic burp/Zl8y.ZY : Ljava/lang/String;
    //   854: getstatic burp/Zejj.Zy : Ljava/lang/Object;
    //   857: checkcast java/math/BigInteger
    //   860: invokevirtual intValue : ()I
    //   863: bipush #32
    //   865: irem
    //   866: invokestatic abs : (I)I
    //   869: invokevirtual charAt : (I)C
    //   872: invokevirtual append : (C)Ljava/lang/StringBuilder;
    //   875: pop
    //   876: iload_2
    //   877: ifne -> 1364
    //   880: goto -> 887
    //   883: invokestatic a : (Ljava/lang/Throwable;)Ljava/lang/Throwable;
    //   886: athrow
    //   887: aload_3
    //   888: getstatic burp/Zsf3.Zb : Ljava/lang/String;
    //   891: getstatic burp/Zgwu.ZD : Ljava/lang/Object;
    //   894: checkcast java/math/BigInteger
    //   897: invokevirtual intValue : ()I
    //   900: bipush #32
    //   902: irem
    //   903: invokestatic abs : (I)I
    //   906: invokevirtual charAt : (I)C
    //   909: invokevirtual append : (C)Ljava/lang/StringBuilder;
    //   912: pop
    //   913: iload_2
    //   914: ifne -> 1364
    //   917: goto -> 924
    //   920: invokestatic a : (Ljava/lang/Throwable;)Ljava/lang/Throwable;
    //   923: athrow
    //   924: aload_3
    //   925: getstatic burp/Zr9b.ZC : Ljava/lang/String;
    //   928: getstatic burp/Zldt.ZS : Ljava/lang/Object;
    //   931: checkcast java/math/BigInteger
    //   934: invokevirtual intValue : ()I
    //   937: bipush #32
    //   939: irem
    //   940: invokestatic abs : (I)I
    //   943: invokevirtual charAt : (I)C
    //   946: invokevirtual append : (C)Ljava/lang/StringBuilder;
    //   949: pop
    //   950: iload_2
    //   951: ifne -> 1364
    //   954: goto -> 961
    //   957: invokestatic a : (Ljava/lang/Throwable;)Ljava/lang/Throwable;
    //   960: athrow
    //   961: aload_3
    //   962: getstatic burp/Zmt7.Zl : Ljava/lang/String;
    //   965: getstatic burp/Zecw.ZE : Ljava/lang/Object;
    //   968: checkcast java/math/BigInteger
    //   971: invokevirtual intValue : ()I
    //   974: bipush #32
    //   976: irem
    //   977: invokestatic abs : (I)I
    //   980: invokevirtual charAt : (I)C
    //   983: invokevirtual append : (C)Ljava/lang/StringBuilder;
    //   986: pop
    //   987: iload_2
    //   988: ifne -> 1364
    //   991: goto -> 998
    //   994: invokestatic a : (Ljava/lang/Throwable;)Ljava/lang/Throwable;
    //   997: athrow
    //   998: aload_3
    //   999: getstatic burp/Zme.Zp : Ljava/lang/String;
    //   1002: getstatic burp/Zmt7.Z_ : Ljava/lang/Object;
    //   1005: checkcast java/math/BigInteger
    //   1008: invokevirtual intValue : ()I
    //   1011: bipush #32
    //   1013: irem
    //   1014: invokestatic abs : (I)I
    //   1017: invokevirtual charAt : (I)C
    //   1020: invokevirtual append : (C)Ljava/lang/StringBuilder;
    //   1023: pop
    //   1024: iload_2
    //   1025: ifne -> 1364
    //   1028: goto -> 1035
    //   1031: invokestatic a : (Ljava/lang/Throwable;)Ljava/lang/Throwable;
    //   1034: athrow
    //   1035: aload_3
    //   1036: getstatic burp/Zl8y.ZY : Ljava/lang/String;
    //   1039: getstatic burp/Zb9h.Zm : Ljava/lang/Object;
    //   1042: checkcast java/math/BigInteger
    //   1045: invokevirtual intValue : ()I
    //   1048: bipush #32
    //   1050: irem
    //   1051: invokestatic abs : (I)I
    //   1054: invokevirtual charAt : (I)C
    //   1057: invokevirtual append : (C)Ljava/lang/StringBuilder;
    //   1060: pop
    //   1061: iload_2
    //   1062: ifne -> 1364
    //   1065: goto -> 1072
    //   1068: invokestatic a : (Ljava/lang/Throwable;)Ljava/lang/Throwable;
    //   1071: athrow
    //   1072: aload_3
    //   1073: getstatic burp/Ze_l.ZY : Ljava/lang/String;
    //   1076: getstatic burp/Zkco.Zg : Ljava/lang/Object;
    //   1079: checkcast java/math/BigInteger
    //   1082: invokevirtual intValue : ()I
    //   1085: bipush #32
    //   1087: irem
    //   1088: invokestatic abs : (I)I
    //   1091: invokevirtual charAt : (I)C
    //   1094: invokevirtual append : (C)Ljava/lang/StringBuilder;
    //   1097: pop
    //   1098: iload_2
    //   1099: ifne -> 1364
    //   1102: goto -> 1109
    //   1105: invokestatic a : (Ljava/lang/Throwable;)Ljava/lang/Throwable;
    //   1108: athrow
    //   1109: aload_3
    //   1110: getstatic burp/Zkf9.ZS : Ljava/lang/String;
    //   1113: getstatic burp/Znp.ZJ : Ljava/lang/Object;
    //   1116: checkcast java/math/BigInteger
    //   1119: invokevirtual intValue : ()I
    //   1122: bipush #32
    //   1124: irem
    //   1125: invokestatic abs : (I)I
    //   1128: invokevirtual charAt : (I)C
    //   1131: invokevirtual append : (C)Ljava/lang/StringBuilder;
    //   1134: pop
    //   1135: iload_2
    //   1136: ifne -> 1364
    //   1139: goto -> 1146
    //   1142: invokestatic a : (Ljava/lang/Throwable;)Ljava/lang/Throwable;
    //   1145: athrow
    //   1146: aload_3
    //   1147: getstatic burp/Zg2.ZN : Ljava/lang/String;
    //   1150: getstatic burp/Zzok.ZY : Ljava/lang/Object;
    //   1153: checkcast java/math/BigInteger
    //   1156: invokevirtual intValue : ()I
    //   1159: bipush #32
    //   1161: irem
    //   1162: invokestatic abs : (I)I
    //   1165: invokevirtual charAt : (I)C
    //   1168: invokevirtual append : (C)Ljava/lang/StringBuilder;
    //   1171: pop
    //   1172: iload_2
    //   1173: ifne -> 1364
    //   1176: goto -> 1183
    //   1179: invokestatic a : (Ljava/lang/Throwable;)Ljava/lang/Throwable;
    //   1182: athrow
    //   1183: aload_3
    //   1184: getstatic burp/Zb2k.Zu : Ljava/lang/String;
    //   1187: getstatic burp/Zg2.ZE : Ljava/lang/Object;
    //   1190: checkcast java/math/BigInteger
    //   1193: invokevirtual intValue : ()I
    //   1196: bipush #32
    //   1198: irem
    //   1199: invokestatic abs : (I)I
    //   1202: invokevirtual charAt : (I)C
    //   1205: invokevirtual append : (C)Ljava/lang/StringBuilder;
    //   1208: pop
    //   1209: iload_2
    //   1210: ifne -> 1364
    //   1213: goto -> 1220
    //   1216: invokestatic a : (Ljava/lang/Throwable;)Ljava/lang/Throwable;
    //   1219: athrow
    //   1220: aload_3
    //   1221: getstatic burp/Ztkc.ZU : Ljava/lang/String;
    //   1224: getstatic burp/Zlnq.ZO : Ljava/lang/Object;
    //   1227: checkcast java/math/BigInteger
    //   1230: invokevirtual intValue : ()I
    //   1233: bipush #32
    //   1235: irem
    //   1236: invokestatic abs : (I)I
    //   1239: invokevirtual charAt : (I)C
    //   1242: invokevirtual append : (C)Ljava/lang/StringBuilder;
    //   1245: pop
    //   1246: iload_2
    //   1247: ifne -> 1364
    //   1250: goto -> 1257
    //   1253: invokestatic a : (Ljava/lang/Throwable;)Ljava/lang/Throwable;
    //   1256: athrow
    //   1257: aload_3
    //   1258: getstatic burp/Zrpy.Zr : Ljava/lang/String;
    //   1261: getstatic burp/Ze_l.ZX : Ljava/lang/Object;
    //   1264: checkcast java/math/BigInteger
    //   1267: invokevirtual intValue : ()I
    //   1270: bipush #32
    //   1272: irem
    //   1273: invokestatic abs : (I)I
    //   1276: invokevirtual charAt : (I)C
    //   1279: invokevirtual append : (C)Ljava/lang/StringBuilder;
    //   1282: pop
    //   1283: iload_2
    //   1284: ifne -> 1364
    //   1287: goto -> 1294
    //   1290: invokestatic a : (Ljava/lang/Throwable;)Ljava/lang/Throwable;
    //   1293: athrow
    //   1294: aload_3
    //   1295: getstatic burp/Zx_x.Zv : Ljava/lang/String;
    //   1298: getstatic burp/Zme.Zd : Ljava/lang/Object;
    //   1301: checkcast java/math/BigInteger
    //   1304: invokevirtual intValue : ()I
    //   1307: bipush #32
    //   1309: irem
    //   1310: invokestatic abs : (I)I
    //   1313: invokevirtual charAt : (I)C
    //   1316: invokevirtual append : (C)Ljava/lang/StringBuilder;
    //   1319: pop
    //   1320: iload_2
    //   1321: ifne -> 1364
    //   1324: goto -> 1331
    //   1327: invokestatic a : (Ljava/lang/Throwable;)Ljava/lang/Throwable;
    //   1330: athrow
    //   1331: aload_3
    //   1332: getstatic burp/Zmtf.Zx : Ljava/lang/String;
    //   1335: getstatic burp/Zrs0.Zz : Ljava/lang/Object;
    //   1338: checkcast java/math/BigInteger
    //   1341: invokevirtual intValue : ()I
    //   1344: bipush #32
    //   1346: irem
    //   1347: invokestatic abs : (I)I
    //   1350: invokevirtual charAt : (I)C
    //   1353: invokevirtual append : (C)Ljava/lang/StringBuilder;
    //   1356: pop
    //   1357: goto -> 1364
    //   1360: invokestatic a : (Ljava/lang/Throwable;)Ljava/lang/Throwable;
    //   1363: athrow
    //   1364: iinc #4, 1
    //   1367: iload_2
    //   1368: ifne -> 33
    //   1371: aload_3
    //   1372: invokevirtual toString : ()Ljava/lang/String;
    //   1375: putstatic burp/Zztz.Zp : Ljava/lang/String;
    //   1378: new java/lang/StringBuilder
    //   1381: dup
    //   1382: invokespecial <init> : ()V
    //   1385: astore #4
    //   1387: iconst_0
    //   1388: istore #5
    //   1390: iload #5
    //   1392: bipush #32
    //   1394: if_icmpge -> 2759
    //   1397: iload #5
    //   1399: tableswitch default -> 2752, 0 -> 1540, 1 -> 1578, 2 -> 1616, 3 -> 1654, 4 -> 1692, 5 -> 1730, 6 -> 1768, 7 -> 1806, 8 -> 1844, 9 -> 1882, 10 -> 1920, 11 -> 1958, 12 -> 1996, 13 -> 2034, 14 -> 2072, 15 -> 2110, 16 -> 2148, 17 -> 2186, 18 -> 2224, 19 -> 2262, 20 -> 2300, 21 -> 2338, 22 -> 2376, 23 -> 2414, 24 -> 2452, 25 -> 2490, 26 -> 2528, 27 -> 2566, 28 -> 2604, 29 -> 2642, 30 -> 2680, 31 -> 2718
    //   1540: aload #4
    //   1542: getstatic burp/Zdk.Ze : Ljava/lang/String;
    //   1545: getstatic burp/Zldt.ZS : Ljava/lang/Object;
    //   1548: checkcast java/math/BigInteger
    //   1551: invokevirtual intValue : ()I
    //   1554: bipush #32
    //   1556: irem
    //   1557: invokestatic abs : (I)I
    //   1560: invokevirtual charAt : (I)C
    //   1563: invokevirtual append : (C)Ljava/lang/StringBuilder;
    //   1566: pop
    //   1567: iload_2
    //   1568: ifne -> 2752
    //   1571: goto -> 1578
    //   1574: invokestatic a : (Ljava/lang/Throwable;)Ljava/lang/Throwable;
    //   1577: athrow
    //   1578: aload #4
    //   1580: getstatic burp/Zr5k.Zq : Ljava/lang/String;
    //   1583: getstatic burp/Zzpu.ZS : Ljava/lang/Object;
    //   1586: checkcast java/math/BigInteger
    //   1589: invokevirtual intValue : ()I
    //   1592: bipush #32
    //   1594: irem
    //   1595: invokestatic abs : (I)I
    //   1598: invokevirtual charAt : (I)C
    //   1601: invokevirtual append : (C)Ljava/lang/StringBuilder;
    //   1604: pop
    //   1605: iload_2
    //   1606: ifne -> 2752
    //   1609: goto -> 1616
    //   1612: invokestatic a : (Ljava/lang/Throwable;)Ljava/lang/Throwable;
    //   1615: athrow
    //   1616: aload #4
    //   1618: getstatic burp/Zsf3.Zb : Ljava/lang/String;
    //   1621: getstatic burp/Zzxv.ZZ : Ljava/lang/Object;
    //   1624: checkcast java/math/BigInteger
    //   1627: invokevirtual intValue : ()I
    //   1630: bipush #32
    //   1632: irem
    //   1633: invokestatic abs : (I)I
    //   1636: invokevirtual charAt : (I)C
    //   1639: invokevirtual append : (C)Ljava/lang/StringBuilder;
    //   1642: pop
    //   1643: iload_2
    //   1644: ifne -> 2752
    //   1647: goto -> 1654
    //   1650: invokestatic a : (Ljava/lang/Throwable;)Ljava/lang/Throwable;
    //   1653: athrow
    //   1654: aload #4
    //   1656: getstatic burp/Zlna.Zo : Ljava/lang/String;
    //   1659: getstatic burp/Zkco.Zg : Ljava/lang/Object;
    //   1662: checkcast java/math/BigInteger
    //   1665: invokevirtual intValue : ()I
    //   1668: bipush #32
    //   1670: irem
    //   1671: invokestatic abs : (I)I
    //   1674: invokevirtual charAt : (I)C
    //   1677: invokevirtual append : (C)Ljava/lang/StringBuilder;
    //   1680: pop
    //   1681: iload_2
    //   1682: ifne -> 2752
    //   1685: goto -> 1692
    //   1688: invokestatic a : (Ljava/lang/Throwable;)Ljava/lang/Throwable;
    //   1691: athrow
    //   1692: aload #4
    //   1694: getstatic burp/Zb14.Ze : Ljava/lang/String;
    //   1697: getstatic burp/Zlr2.Zq : Ljava/lang/Object;
    //   1700: checkcast java/math/BigInteger
    //   1703: invokevirtual intValue : ()I
    //   1706: bipush #32
    //   1708: irem
    //   1709: invokestatic abs : (I)I
    //   1712: invokevirtual charAt : (I)C
    //   1715: invokevirtual append : (C)Ljava/lang/StringBuilder;
    //   1718: pop
    //   1719: iload_2
    //   1720: ifne -> 2752
    //   1723: goto -> 1730
    //   1726: invokestatic a : (Ljava/lang/Throwable;)Ljava/lang/Throwable;
    //   1729: athrow
    //   1730: aload #4
    //   1732: getstatic burp/Zb0z.ZM : Ljava/lang/String;
    //   1735: getstatic burp/Zry0.Zr : Ljava/lang/Object;
    //   1738: checkcast java/math/BigInteger
    //   1741: invokevirtual intValue : ()I
    //   1744: bipush #32
    //   1746: irem
    //   1747: invokestatic abs : (I)I
    //   1750: invokevirtual charAt : (I)C
    //   1753: invokevirtual append : (C)Ljava/lang/StringBuilder;
    //   1756: pop
    //   1757: iload_2
    //   1758: ifne -> 2752
    //   1761: goto -> 1768
    //   1764: invokestatic a : (Ljava/lang/Throwable;)Ljava/lang/Throwable;
    //   1767: athrow
    //   1768: aload #4
    //   1770: getstatic burp/Zxtc.Zo : Ljava/lang/String;
    //   1773: getstatic burp/Zm5p.Ze : Ljava/lang/Object;
    //   1776: checkcast java/math/BigInteger
    //   1779: invokevirtual intValue : ()I
    //   1782: bipush #32
    //   1784: irem
    //   1785: invokestatic abs : (I)I
    //   1788: invokevirtual charAt : (I)C
    //   1791: invokevirtual append : (C)Ljava/lang/StringBuilder;
    //   1794: pop
    //   1795: iload_2
    //   1796: ifne -> 2752
    //   1799: goto -> 1806
    //   1802: invokestatic a : (Ljava/lang/Throwable;)Ljava/lang/Throwable;
    //   1805: athrow
    //   1806: aload #4
    //   1808: getstatic burp/Zgta.ZL : Ljava/lang/String;
    //   1811: getstatic burp/Zrpy.ZG : Ljava/lang/Object;
    //   1814: checkcast java/math/BigInteger
    //   1817: invokevirtual intValue : ()I
    //   1820: bipush #32
    //   1822: irem
    //   1823: invokestatic abs : (I)I
    //   1826: invokevirtual charAt : (I)C
    //   1829: invokevirtual append : (C)Ljava/lang/StringBuilder;
    //   1832: pop
    //   1833: iload_2
    //   1834: ifne -> 2752
    //   1837: goto -> 1844
    //   1840: invokestatic a : (Ljava/lang/Throwable;)Ljava/lang/Throwable;
    //   1843: athrow
    //   1844: aload #4
    //   1846: getstatic burp/Zrml.Zt : Ljava/lang/String;
    //   1849: getstatic burp/Zgkn.Zm : Ljava/lang/Object;
    //   1852: checkcast java/math/BigInteger
    //   1855: invokevirtual intValue : ()I
    //   1858: bipush #32
    //   1860: irem
    //   1861: invokestatic abs : (I)I
    //   1864: invokevirtual charAt : (I)C
    //   1867: invokevirtual append : (C)Ljava/lang/StringBuilder;
    //   1870: pop
    //   1871: iload_2
    //   1872: ifne -> 2752
    //   1875: goto -> 1882
    //   1878: invokestatic a : (Ljava/lang/Throwable;)Ljava/lang/Throwable;
    //   1881: athrow
    //   1882: aload #4
    //   1884: getstatic burp/Zlpn.ZF : Ljava/lang/String;
    //   1887: getstatic burp/Zz35.ZB : Ljava/lang/Object;
    //   1890: checkcast java/math/BigInteger
    //   1893: invokevirtual intValue : ()I
    //   1896: bipush #32
    //   1898: irem
    //   1899: invokestatic abs : (I)I
    //   1902: invokevirtual charAt : (I)C
    //   1905: invokevirtual append : (C)Ljava/lang/StringBuilder;
    //   1908: pop
    //   1909: iload_2
    //   1910: ifne -> 2752
    //   1913: goto -> 1920
    //   1916: invokestatic a : (Ljava/lang/Throwable;)Ljava/lang/Throwable;
    //   1919: athrow
    //   1920: aload #4
    //   1922: getstatic burp/Zx8t.Zi : Ljava/lang/String;
    //   1925: getstatic burp/Zzxv.ZZ : Ljava/lang/Object;
    //   1928: checkcast java/math/BigInteger
    //   1931: invokevirtual intValue : ()I
    //   1934: bipush #32
    //   1936: irem
    //   1937: invokestatic abs : (I)I
    //   1940: invokevirtual charAt : (I)C
    //   1943: invokevirtual append : (C)Ljava/lang/StringBuilder;
    //   1946: pop
    //   1947: iload_2
    //   1948: ifne -> 2752
    //   1951: goto -> 1958
    //   1954: invokestatic a : (Ljava/lang/Throwable;)Ljava/lang/Throwable;
    //   1957: athrow
    //   1958: aload #4
    //   1960: getstatic burp/Zefm.ZK : Ljava/lang/String;
    //   1963: getstatic burp/Zzxv.ZZ : Ljava/lang/Object;
    //   1966: checkcast java/math/BigInteger
    //   1969: invokevirtual intValue : ()I
    //   1972: bipush #32
    //   1974: irem
    //   1975: invokestatic abs : (I)I
    //   1978: invokevirtual charAt : (I)C
    //   1981: invokevirtual append : (C)Ljava/lang/StringBuilder;
    //   1984: pop
    //   1985: iload_2
    //   1986: ifne -> 2752
    //   1989: goto -> 1996
    //   1992: invokestatic a : (Ljava/lang/Throwable;)Ljava/lang/Throwable;
    //   1995: athrow
    //   1996: aload #4
    //   1998: getstatic burp/Zx8t.Zi : Ljava/lang/String;
    //   2001: getstatic burp/Zefm.ZP : Ljava/lang/Object;
    //   2004: checkcast java/math/BigInteger
    //   2007: invokevirtual intValue : ()I
    //   2010: bipush #32
    //   2012: irem
    //   2013: invokestatic abs : (I)I
    //   2016: invokevirtual charAt : (I)C
    //   2019: invokevirtual append : (C)Ljava/lang/StringBuilder;
    //   2022: pop
    //   2023: iload_2
    //   2024: ifne -> 2752
    //   2027: goto -> 2034
    //   2030: invokestatic a : (Ljava/lang/Throwable;)Ljava/lang/Throwable;
    //   2033: athrow
    //   2034: aload #4
    //   2036: getstatic burp/Zbzc.ZL : Ljava/lang/String;
    //   2039: getstatic burp/Znp.ZJ : Ljava/lang/Object;
    //   2042: checkcast java/math/BigInteger
    //   2045: invokevirtual intValue : ()I
    //   2048: bipush #32
    //   2050: irem
    //   2051: invokestatic abs : (I)I
    //   2054: invokevirtual charAt : (I)C
    //   2057: invokevirtual append : (C)Ljava/lang/StringBuilder;
    //   2060: pop
    //   2061: iload_2
    //   2062: ifne -> 2752
    //   2065: goto -> 2072
    //   2068: invokestatic a : (Ljava/lang/Throwable;)Ljava/lang/Throwable;
    //   2071: athrow
    //   2072: aload #4
    //   2074: getstatic burp/Zro5.ZY : Ljava/lang/String;
    //   2077: getstatic burp/Zbzc.Zp : Ljava/lang/Object;
    //   2080: checkcast java/math/BigInteger
    //   2083: invokevirtual intValue : ()I
    //   2086: bipush #32
    //   2088: irem
    //   2089: invokestatic abs : (I)I
    //   2092: invokevirtual charAt : (I)C
    //   2095: invokevirtual append : (C)Ljava/lang/StringBuilder;
    //   2098: pop
    //   2099: iload_2
    //   2100: ifne -> 2752
    //   2103: goto -> 2110
    //   2106: invokestatic a : (Ljava/lang/Throwable;)Ljava/lang/Throwable;
    //   2109: athrow
    //   2110: aload #4
    //   2112: getstatic burp/Zrod.ZQ : Ljava/lang/String;
    //   2115: getstatic burp/Zlr2.Zq : Ljava/lang/Object;
    //   2118: checkcast java/math/BigInteger
    //   2121: invokevirtual intValue : ()I
    //   2124: bipush #32
    //   2126: irem
    //   2127: invokestatic abs : (I)I
    //   2130: invokevirtual charAt : (I)C
    //   2133: invokevirtual append : (C)Ljava/lang/StringBuilder;
    //   2136: pop
    //   2137: iload_2
    //   2138: ifne -> 2752
    //   2141: goto -> 2148
    //   2144: invokestatic a : (Ljava/lang/Throwable;)Ljava/lang/Throwable;
    //   2147: athrow
    //   2148: aload #4
    //   2150: getstatic burp/Zl8y.ZY : Ljava/lang/String;
    //   2153: getstatic burp/Zgkn.Zm : Ljava/lang/Object;
    //   2156: checkcast java/math/BigInteger
    //   2159: invokevirtual intValue : ()I
    //   2162: bipush #32
    //   2164: irem
    //   2165: invokestatic abs : (I)I
    //   2168: invokevirtual charAt : (I)C
    //   2171: invokevirtual append : (C)Ljava/lang/StringBuilder;
    //   2174: pop
    //   2175: iload_2
    //   2176: ifne -> 2752
    //   2179: goto -> 2186
    //   2182: invokestatic a : (Ljava/lang/Throwable;)Ljava/lang/Throwable;
    //   2185: athrow
    //   2186: aload #4
    //   2188: getstatic burp/Zzxs.Zd : Ljava/lang/String;
    //   2191: getstatic burp/Zry0.Zr : Ljava/lang/Object;
    //   2194: checkcast java/math/BigInteger
    //   2197: invokevirtual intValue : ()I
    //   2200: bipush #32
    //   2202: irem
    //   2203: invokestatic abs : (I)I
    //   2206: invokevirtual charAt : (I)C
    //   2209: invokevirtual append : (C)Ljava/lang/StringBuilder;
    //   2212: pop
    //   2213: iload_2
    //   2214: ifne -> 2752
    //   2217: goto -> 2224
    //   2220: invokestatic a : (Ljava/lang/Throwable;)Ljava/lang/Throwable;
    //   2223: athrow
    //   2224: aload #4
    //   2226: getstatic burp/Zzxs.Zd : Ljava/lang/String;
    //   2229: getstatic burp/Zzh0.Z_ : Ljava/lang/Object;
    //   2232: checkcast java/math/BigInteger
    //   2235: invokevirtual intValue : ()I
    //   2238: bipush #32
    //   2240: irem
    //   2241: invokestatic abs : (I)I
    //   2244: invokevirtual charAt : (I)C
    //   2247: invokevirtual append : (C)Ljava/lang/StringBuilder;
    //   2250: pop
    //   2251: iload_2
    //   2252: ifne -> 2752
    //   2255: goto -> 2262
    //   2258: invokestatic a : (Ljava/lang/Throwable;)Ljava/lang/Throwable;
    //   2261: athrow
    //   2262: aload #4
    //   2264: getstatic burp/Zx_s.Za : Ljava/lang/String;
    //   2267: getstatic burp/Zxpb.Zo : Ljava/lang/Object;
    //   2270: checkcast java/math/BigInteger
    //   2273: invokevirtual intValue : ()I
    //   2276: bipush #32
    //   2278: irem
    //   2279: invokestatic abs : (I)I
    //   2282: invokevirtual charAt : (I)C
    //   2285: invokevirtual append : (C)Ljava/lang/StringBuilder;
    //   2288: pop
    //   2289: iload_2
    //   2290: ifne -> 2752
    //   2293: goto -> 2300
    //   2296: invokestatic a : (Ljava/lang/Throwable;)Ljava/lang/Throwable;
    //   2299: athrow
    //   2300: aload #4
    //   2302: getstatic burp/Zrd4.Zg : Ljava/lang/String;
    //   2305: getstatic burp/Zelc.ZR : Ljava/lang/Object;
    //   2308: checkcast java/math/BigInteger
    //   2311: invokevirtual intValue : ()I
    //   2314: bipush #32
    //   2316: irem
    //   2317: invokestatic abs : (I)I
    //   2320: invokevirtual charAt : (I)C
    //   2323: invokevirtual append : (C)Ljava/lang/StringBuilder;
    //   2326: pop
    //   2327: iload_2
    //   2328: ifne -> 2752
    //   2331: goto -> 2338
    //   2334: invokestatic a : (Ljava/lang/Throwable;)Ljava/lang/Throwable;
    //   2337: athrow
    //   2338: aload #4
    //   2340: getstatic burp/Zb9h.Zf : Ljava/lang/String;
    //   2343: getstatic burp/Zmzh.Zk : Ljava/lang/Object;
    //   2346: checkcast java/math/BigInteger
    //   2349: invokevirtual intValue : ()I
    //   2352: bipush #32
    //   2354: irem
    //   2355: invokestatic abs : (I)I
    //   2358: invokevirtual charAt : (I)C
    //   2361: invokevirtual append : (C)Ljava/lang/StringBuilder;
    //   2364: pop
    //   2365: iload_2
    //   2366: ifne -> 2752
    //   2369: goto -> 2376
    //   2372: invokestatic a : (Ljava/lang/Throwable;)Ljava/lang/Throwable;
    //   2375: athrow
    //   2376: aload #4
    //   2378: getstatic burp/Zlpn.ZF : Ljava/lang/String;
    //   2381: getstatic burp/Zz35.ZB : Ljava/lang/Object;
    //   2384: checkcast java/math/BigInteger
    //   2387: invokevirtual intValue : ()I
    //   2390: bipush #32
    //   2392: irem
    //   2393: invokestatic abs : (I)I
    //   2396: invokevirtual charAt : (I)C
    //   2399: invokevirtual append : (C)Ljava/lang/StringBuilder;
    //   2402: pop
    //   2403: iload_2
    //   2404: ifne -> 2752
    //   2407: goto -> 2414
    //   2410: invokestatic a : (Ljava/lang/Throwable;)Ljava/lang/Throwable;
    //   2413: athrow
    //   2414: aload #4
    //   2416: getstatic burp/Zlsw.ZE : Ljava/lang/String;
    //   2419: getstatic burp/Zb9h.Zm : Ljava/lang/Object;
    //   2422: checkcast java/math/BigInteger
    //   2425: invokevirtual intValue : ()I
    //   2428: bipush #32
    //   2430: irem
    //   2431: invokestatic abs : (I)I
    //   2434: invokevirtual charAt : (I)C
    //   2437: invokevirtual append : (C)Ljava/lang/StringBuilder;
    //   2440: pop
    //   2441: iload_2
    //   2442: ifne -> 2752
    //   2445: goto -> 2452
    //   2448: invokestatic a : (Ljava/lang/Throwable;)Ljava/lang/Throwable;
    //   2451: athrow
    //   2452: aload #4
    //   2454: getstatic burp/Zl8y.ZY : Ljava/lang/String;
    //   2457: getstatic burp/Zrpy.ZG : Ljava/lang/Object;
    //   2460: checkcast java/math/BigInteger
    //   2463: invokevirtual intValue : ()I
    //   2466: bipush #32
    //   2468: irem
    //   2469: invokestatic abs : (I)I
    //   2472: invokevirtual charAt : (I)C
    //   2475: invokevirtual append : (C)Ljava/lang/StringBuilder;
    //   2478: pop
    //   2479: iload_2
    //   2480: ifne -> 2752
    //   2483: goto -> 2490
    //   2486: invokestatic a : (Ljava/lang/Throwable;)Ljava/lang/Throwable;
    //   2489: athrow
    //   2490: aload #4
    //   2492: getstatic burp/Zzrb.ZA : Ljava/lang/String;
    //   2495: getstatic burp/Zlps.ZU : Ljava/lang/Object;
    //   2498: checkcast java/math/BigInteger
    //   2501: invokevirtual intValue : ()I
    //   2504: bipush #32
    //   2506: irem
    //   2507: invokestatic abs : (I)I
    //   2510: invokevirtual charAt : (I)C
    //   2513: invokevirtual append : (C)Ljava/lang/StringBuilder;
    //   2516: pop
    //   2517: iload_2
    //   2518: ifne -> 2752
    //   2521: goto -> 2528
    //   2524: invokestatic a : (Ljava/lang/Throwable;)Ljava/lang/Throwable;
    //   2527: athrow
    //   2528: aload #4
    //   2530: getstatic burp/Ze_l.ZY : Ljava/lang/String;
    //   2533: getstatic burp/Zr9b.ZF : Ljava/lang/Object;
    //   2536: checkcast java/math/BigInteger
    //   2539: invokevirtual intValue : ()I
    //   2542: bipush #32
    //   2544: irem
    //   2545: invokestatic abs : (I)I
    //   2548: invokevirtual charAt : (I)C
    //   2551: invokevirtual append : (C)Ljava/lang/StringBuilder;
    //   2554: pop
    //   2555: iload_2
    //   2556: ifne -> 2752
    //   2559: goto -> 2566
    //   2562: invokestatic a : (Ljava/lang/Throwable;)Ljava/lang/Throwable;
    //   2565: athrow
    //   2566: aload #4
    //   2568: getstatic burp/Zgt7.ZO : Ljava/lang/String;
    //   2571: getstatic burp/Zrf9.Zu : Ljava/lang/Object;
    //   2574: checkcast java/math/BigInteger
    //   2577: invokevirtual intValue : ()I
    //   2580: bipush #32
    //   2582: irem
    //   2583: invokestatic abs : (I)I
    //   2586: invokevirtual charAt : (I)C
    //   2589: invokevirtual append : (C)Ljava/lang/StringBuilder;
    //   2592: pop
    //   2593: iload_2
    //   2594: ifne -> 2752
    //   2597: goto -> 2604
    //   2600: invokestatic a : (Ljava/lang/Throwable;)Ljava/lang/Throwable;
    //   2603: athrow
    //   2604: aload #4
    //   2606: getstatic burp/Zzrb.ZA : Ljava/lang/String;
    //   2609: getstatic burp/Ztys.Zs : Ljava/lang/Object;
    //   2612: checkcast java/math/BigInteger
    //   2615: invokevirtual intValue : ()I
    //   2618: bipush #32
    //   2620: irem
    //   2621: invokestatic abs : (I)I
    //   2624: invokevirtual charAt : (I)C
    //   2627: invokevirtual append : (C)Ljava/lang/StringBuilder;
    //   2630: pop
    //   2631: iload_2
    //   2632: ifne -> 2752
    //   2635: goto -> 2642
    //   2638: invokestatic a : (Ljava/lang/Throwable;)Ljava/lang/Throwable;
    //   2641: athrow
    //   2642: aload #4
    //   2644: getstatic burp/Zgt7.ZO : Ljava/lang/String;
    //   2647: getstatic burp/Zrs0.Zz : Ljava/lang/Object;
    //   2650: checkcast java/math/BigInteger
    //   2653: invokevirtual intValue : ()I
    //   2656: bipush #32
    //   2658: irem
    //   2659: invokestatic abs : (I)I
    //   2662: invokevirtual charAt : (I)C
    //   2665: invokevirtual append : (C)Ljava/lang/StringBuilder;
    //   2668: pop
    //   2669: iload_2
    //   2670: ifne -> 2752
    //   2673: goto -> 2680
    //   2676: invokestatic a : (Ljava/lang/Throwable;)Ljava/lang/Throwable;
    //   2679: athrow
    //   2680: aload #4
    //   2682: getstatic burp/Zrs0.Zt : Ljava/lang/String;
    //   2685: getstatic burp/Zro5.ZT : Ljava/lang/Object;
    //   2688: checkcast java/math/BigInteger
    //   2691: invokevirtual intValue : ()I
    //   2694: bipush #32
    //   2696: irem
    //   2697: invokestatic abs : (I)I
    //   2700: invokevirtual charAt : (I)C
    //   2703: invokevirtual append : (C)Ljava/lang/StringBuilder;
    //   2706: pop
    //   2707: iload_2
    //   2708: ifne -> 2752
    //   2711: goto -> 2718
    //   2714: invokestatic a : (Ljava/lang/Throwable;)Ljava/lang/Throwable;
    //   2717: athrow
    //   2718: aload #4
    //   2720: getstatic burp/Zeb3.ZG : Ljava/lang/String;
    //   2723: getstatic burp/Zefm.ZP : Ljava/lang/Object;
    //   2726: checkcast java/math/BigInteger
    //   2729: invokevirtual intValue : ()I
    //   2732: bipush #32
    //   2734: irem
    //   2735: invokestatic abs : (I)I
    //   2738: invokevirtual charAt : (I)C
    //   2741: invokevirtual append : (C)Ljava/lang/StringBuilder;
    //   2744: pop
    //   2745: goto -> 2752
    //   2748: invokestatic a : (Ljava/lang/Throwable;)Ljava/lang/Throwable;
    //   2751: athrow
    //   2752: iinc #5, 1
    //   2755: iload_2
    //   2756: ifne -> 1390
    //   2759: aload #4
    //   2761: invokevirtual toString : ()Ljava/lang/String;
    //   2764: putstatic burp/Zrml.Zt : Ljava/lang/String;
    //   2767: sipush #-27378
    //   2770: sipush #-8532
    //   2773: invokestatic a : (II)Ljava/lang/String;
    //   2776: iconst_1
    //   2777: ldc burp/Zsk2
    //   2779: invokevirtual getClassLoader : ()Ljava/lang/ClassLoader;
    //   2782: invokestatic forName : (Ljava/lang/String;ZLjava/lang/ClassLoader;)Ljava/lang/Class;
    //   2785: invokevirtual getDeclaredFields : ()[Ljava/lang/reflect/Field;
    //   2788: astore #5
    //   2790: aload #5
    //   2792: arraylength
    //   2793: istore #6
    //   2795: iconst_0
    //   2796: istore #7
    //   2798: iload #7
    //   2800: iload #6
    //   2802: if_icmpge -> 2940
    //   2805: aload #5
    //   2807: iload #7
    //   2809: aaload
    //   2810: astore #8
    //   2812: aload #8
    //   2814: invokevirtual getModifiers : ()I
    //   2817: invokestatic isStatic : (I)Z
    //   2820: ifne -> 2830
    //   2823: goto -> 2933
    //   2826: invokestatic a : (Ljava/lang/Throwable;)Ljava/lang/Throwable;
    //   2829: athrow
    //   2830: aload #8
    //   2832: invokevirtual getType : ()Ljava/lang/Class;
    //   2835: astore #9
    //   2837: aload #9
    //   2839: ifnull -> 2920
    //   2842: aload #9
    //   2844: invokevirtual isPrimitive : ()Z
    //   2847: ifne -> 2920
    //   2850: goto -> 2857
    //   2853: invokestatic a : (Ljava/lang/Throwable;)Ljava/lang/Throwable;
    //   2856: athrow
    //   2857: aload #9
    //   2859: invokevirtual getPackage : ()Ljava/lang/Package;
    //   2862: ifnull -> 2920
    //   2865: goto -> 2872
    //   2868: invokestatic a : (Ljava/lang/Throwable;)Ljava/lang/Throwable;
    //   2871: athrow
    //   2872: aload #9
    //   2874: invokevirtual getPackage : ()Ljava/lang/Package;
    //   2877: invokevirtual getName : ()Ljava/lang/String;
    //   2880: ifnull -> 2920
    //   2883: goto -> 2890
    //   2886: invokestatic a : (Ljava/lang/Throwable;)Ljava/lang/Throwable;
    //   2889: athrow
    //   2890: aload #9
    //   2892: invokevirtual getPackage : ()Ljava/lang/Package;
    //   2895: invokevirtual getName : ()Ljava/lang/String;
    //   2898: sipush #-27381
    //   2901: sipush #4676
    //   2904: invokestatic a : (II)Ljava/lang/String;
    //   2907: invokevirtual startsWith : (Ljava/lang/String;)Z
    //   2910: ifne -> 2920
    //   2913: goto -> 2920
    //   2916: invokestatic a : (Ljava/lang/Throwable;)Ljava/lang/Throwable;
    //   2919: athrow
    //   2920: aload #8
    //   2922: iconst_1
    //   2923: invokevirtual setAccessible : (Z)V
    //   2926: aload #8
    //   2928: aconst_null
    //   2929: invokevirtual get : (Ljava/lang/Object;)Ljava/lang/Object;
    //   2932: pop
    //   2933: iinc #7, 1
    //   2936: iload_2
    //   2937: ifne -> 2798
    //   2940: sipush #-27383
    //   2943: sipush #-30023
    //   2946: invokestatic a : (II)Ljava/lang/String;
    //   2949: invokestatic forName : (Ljava/lang/String;)Ljava/lang/Class;
    //   2952: invokevirtual getDeclaredMethods : ()[Ljava/lang/reflect/Method;
    //   2955: astore #5
    //   2957: aload #5
    //   2959: arraylength
    //   2960: istore #6
    //   2962: iconst_0
    //   2963: istore #7
    //   2965: iload #7
    //   2967: iload #6
    //   2969: if_icmpge -> 3102
    //   2972: aload #5
    //   2974: iload #7
    //   2976: aaload
    //   2977: astore #8
    //   2979: aload #8
    //   2981: invokevirtual getParameterTypes : ()[Ljava/lang/Class;
    //   2984: pop
    //   2985: aload #8
    //   2987: invokevirtual getModifiers : ()I
    //   2990: invokestatic isStatic : (I)Z
    //   2993: ifeq -> 3088
    //   2996: aload #8
    //   2998: invokevirtual getParameterTypes : ()[Ljava/lang/Class;
    //   3001: arraylength
    //   3002: iconst_2
    //   3003: if_icmpne -> 3088
    //   3006: goto -> 3013
    //   3009: invokestatic a : (Ljava/lang/Throwable;)Ljava/lang/Throwable;
    //   3012: athrow
    //   3013: aload #8
    //   3015: invokevirtual getReturnType : ()Ljava/lang/Class;
    //   3018: getstatic java/lang/Void.TYPE : Ljava/lang/Class;
    //   3021: invokevirtual equals : (Ljava/lang/Object;)Z
    //   3024: ifeq -> 3088
    //   3027: goto -> 3034
    //   3030: invokestatic a : (Ljava/lang/Throwable;)Ljava/lang/Throwable;
    //   3033: athrow
    //   3034: aload #8
    //   3036: iconst_1
    //   3037: invokevirtual setAccessible : (Z)V
    //   3040: aload #8
    //   3042: aconst_null
    //   3043: iconst_2
    //   3044: anewarray java/lang/Object
    //   3047: dup
    //   3048: iconst_0
    //   3049: aload_0
    //   3050: aastore
    //   3051: dup
    //   3052: iconst_1
    //   3053: aload_1
    //   3054: ifnonnull -> 3072
    //   3057: goto -> 3064
    //   3060: invokestatic a : (Ljava/lang/Throwable;)Ljava/lang/Throwable;
    //   3063: athrow
    //   3064: aload_1
    //   3065: goto -> 3079
    //   3068: invokestatic a : (Ljava/lang/Throwable;)Ljava/lang/Throwable;
    //   3071: athrow
    //   3072: aload_1
    //   3073: checkcast [B
    //   3076: invokevirtual clone : ()Ljava/lang/Object;
    //   3079: aastore
    //   3080: invokevirtual invoke : (Ljava/lang/Object;[Ljava/lang/Object;)Ljava/lang/Object;
    //   3083: pop
    //   3084: iload_2
    //   3085: ifne -> 3102
    //   3088: iinc #7, 1
    //   3091: iload_2
    //   3092: ifne -> 2965
    //   3095: goto -> 3102
    //   3098: invokestatic a : (Ljava/lang/Throwable;)Ljava/lang/Throwable;
    //   3101: athrow
    //   3102: getstatic burp/Zx8t.Zi : Ljava/lang/String;
    //   3105: getstatic burp/Zrf9.Zu : Ljava/lang/Object;
    //   3108: checkcast java/math/BigInteger
    //   3111: invokevirtual intValue : ()I
    //   3114: bipush #32
    //   3116: irem
    //   3117: invokestatic abs : (I)I
    //   3120: invokevirtual charAt : (I)C
    //   3123: getstatic burp/Zzbr.Zp : Ljava/lang/String;
    //   3126: getstatic burp/Zlav.Zp : Ljava/lang/Object;
    //   3129: checkcast java/math/BigInteger
    //   3132: invokevirtual intValue : ()I
    //   3135: bipush #32
    //   3137: irem
    //   3138: invokestatic abs : (I)I
    //   3141: invokevirtual charAt : (I)C
    //   3144: if_icmple -> 3251
    //   3147: getstatic burp/Zbzc.ZL : Ljava/lang/String;
    //   3150: getstatic burp/Zr04.ZB : Ljava/lang/Object;
    //   3153: checkcast java/math/BigInteger
    //   3156: invokevirtual intValue : ()I
    //   3159: bipush #32
    //   3161: irem
    //   3162: invokestatic abs : (I)I
    //   3165: invokevirtual charAt : (I)C
    //   3168: getstatic burp/Zzpu.Zq : Ljava/lang/String;
    //   3171: getstatic burp/Zb2k.ZZ : Ljava/lang/Object;
    //   3174: checkcast java/math/BigInteger
    //   3177: invokevirtual intValue : ()I
    //   3180: bipush #32
    //   3182: irem
    //   3183: invokestatic abs : (I)I
    //   3186: invokevirtual charAt : (I)C
    //   3189: if_icmpgt -> 3251
    //   3192: goto -> 3199
    //   3195: invokestatic a : (Ljava/lang/Throwable;)Ljava/lang/Throwable;
    //   3198: athrow
    //   3199: getstatic burp/Zgw_.ZH : Ljava/lang/String;
    //   3202: getstatic burp/Ztd3.ZX : Ljava/lang/Object;
    //   3205: checkcast java/math/BigInteger
    //   3208: invokevirtual intValue : ()I
    //   3211: bipush #32
    //   3213: irem
    //   3214: invokestatic abs : (I)I
    //   3217: invokevirtual charAt : (I)C
    //   3220: getstatic burp/Zb2k.Zu : Ljava/lang/String;
    //   3223: getstatic burp/Zrml.ZA : Ljava/lang/Object;
    //   3226: checkcast java/math/BigInteger
    //   3229: invokevirtual intValue : ()I
    //   3232: bipush #32
    //   3234: irem
    //   3235: invokestatic abs : (I)I
    //   3238: invokevirtual charAt : (I)C
    //   3241: if_icmple -> 3259
    //   3244: goto -> 3251
    //   3247: invokestatic a : (Ljava/lang/Throwable;)Ljava/lang/Throwable;
    //   3250: athrow
    //   3251: iconst_1
    //   3252: goto -> 3260
    //   3255: invokestatic a : (Ljava/lang/Throwable;)Ljava/lang/Throwable;
    //   3258: athrow
    //   3259: iconst_0
    //   3260: ireturn
    //   3261: astore_3
    //   3262: new java/lang/Exception
    //   3265: dup
    //   3266: aload_3
    //   3267: invokevirtual getMessage : ()Ljava/lang/String;
    //   3270: invokespecial <init> : (Ljava/lang/String;)V
    //   3273: athrow
    // Exception table:
    //   from	to	target	type
    //   4	3260	3261	java/lang/Throwable
    //   40	214	217	java/lang/Throwable
    //   184	251	254	java/lang/Throwable
    //   221	288	291	java/lang/Throwable
    //   258	325	328	java/lang/Throwable
    //   295	362	365	java/lang/Throwable
    //   332	399	402	java/lang/Throwable
    //   369	436	439	java/lang/Throwable
    //   406	473	476	java/lang/Throwable
    //   443	510	513	java/lang/Throwable
    //   480	547	550	java/lang/Throwable
    //   517	584	587	java/lang/Throwable
    //   554	621	624	java/lang/Throwable
    //   591	658	661	java/lang/Throwable
    //   628	695	698	java/lang/Throwable
    //   665	732	735	java/lang/Throwable
    //   702	769	772	java/lang/Throwable
    //   739	806	809	java/lang/Throwable
    //   776	843	846	java/lang/Throwable
    //   813	880	883	java/lang/Throwable
    //   850	917	920	java/lang/Throwable
    //   887	954	957	java/lang/Throwable
    //   924	991	994	java/lang/Throwable
    //   961	1028	1031	java/lang/Throwable
    //   998	1065	1068	java/lang/Throwable
    //   1035	1102	1105	java/lang/Throwable
    //   1072	1139	1142	java/lang/Throwable
    //   1109	1176	1179	java/lang/Throwable
    //   1146	1213	1216	java/lang/Throwable
    //   1183	1250	1253	java/lang/Throwable
    //   1220	1287	1290	java/lang/Throwable
    //   1257	1324	1327	java/lang/Throwable
    //   1294	1357	1360	java/lang/Throwable
    //   1397	1571	1574	java/lang/Throwable
    //   1540	1609	1612	java/lang/Throwable
    //   1578	1647	1650	java/lang/Throwable
    //   1616	1685	1688	java/lang/Throwable
    //   1654	1723	1726	java/lang/Throwable
    //   1692	1761	1764	java/lang/Throwable
    //   1730	1799	1802	java/lang/Throwable
    //   1768	1837	1840	java/lang/Throwable
    //   1806	1875	1878	java/lang/Throwable
    //   1844	1913	1916	java/lang/Throwable
    //   1882	1951	1954	java/lang/Throwable
    //   1920	1989	1992	java/lang/Throwable
    //   1958	2027	2030	java/lang/Throwable
    //   1996	2065	2068	java/lang/Throwable
    //   2034	2103	2106	java/lang/Throwable
    //   2072	2141	2144	java/lang/Throwable
    //   2110	2179	2182	java/lang/Throwable
    //   2148	2217	2220	java/lang/Throwable
    //   2186	2255	2258	java/lang/Throwable
    //   2224	2293	2296	java/lang/Throwable
    //   2262	2331	2334	java/lang/Throwable
    //   2300	2369	2372	java/lang/Throwable
    //   2338	2407	2410	java/lang/Throwable
    //   2376	2445	2448	java/lang/Throwable
    //   2414	2483	2486	java/lang/Throwable
    //   2452	2521	2524	java/lang/Throwable
    //   2490	2559	2562	java/lang/Throwable
    //   2528	2597	2600	java/lang/Throwable
    //   2566	2635	2638	java/lang/Throwable
    //   2604	2673	2676	java/lang/Throwable
    //   2642	2711	2714	java/lang/Throwable
    //   2680	2745	2748	java/lang/Throwable
    //   2812	2826	2826	java/lang/Throwable
    //   2837	2850	2853	java/lang/Throwable
    //   2842	2865	2868	java/lang/Throwable
    //   2857	2883	2886	java/lang/Throwable
    //   2872	2913	2916	java/lang/Throwable
    //   2979	3006	3009	java/lang/Throwable
    //   2996	3027	3030	java/lang/Throwable
    //   3013	3057	3060	java/lang/Throwable
    //   3034	3068	3068	java/lang/Throwable
    //   3079	3095	3098	java/lang/Throwable
    //   3102	3192	3195	java/lang/Throwable
    //   3147	3244	3247	java/lang/Throwable
    //   3199	3255	3255	java/lang/Throwable
  }
  
  static void Zz(Object[] paramArrayOfObject, Object paramObject) throws Throwable {}
  
  static void Zy(Object paramObject) {
    Zb9h.Zf = a(-27384, 19917);
    Zb9h.Zm = new BigInteger(a(-27377, -9132));
    boolean bool = Zt2e.ZK();
    try {
      try {
        if (Zgw_.ZH.charAt(Math.abs(((BigInteger)Ztdx.ZX).intValue() % 32)) <= Ztdx.Zl.charAt(Math.abs(((BigInteger)Zro5.ZT).intValue() % 32))) {
          try {
            Zzhu.ZK(Class.forName(a(-27380, 4608)));
            if (bool)
              Zz3w.ZE(Class.forName(a(-27382, -9564))); 
          } catch (Throwable throwable) {
            throw a(null);
          } 
          return;
        } 
      } catch (Throwable throwable) {
        throw a(null);
      } 
      Zz3w.ZE(Class.forName(a(-27382, -9564)));
    } catch (Throwable throwable) {}
  }
  
  static {
    // Byte code:
    //   0: bipush #8
    //   2: anewarray java/lang/String
    //   5: astore #5
    //   7: iconst_0
    //   8: istore_3
    //   9: ldc '.3cPdIGMhrF\\t:l8Mc\\f!3r$uuJ2]p5=5aY<`2e_.pAGF:h'IG\\tGYv\\tD9*s| F45v5%p=Ck'
    //   11: dup
    //   12: astore_2
    //   13: invokevirtual length : ()I
    //   16: istore #4
    //   18: bipush #32
    //   20: istore_1
    //   21: iconst_m1
    //   22: istore_0
    //   23: bipush #7
    //   25: iinc #0, 1
    //   28: aload_2
    //   29: iload_0
    //   30: dup
    //   31: iload_1
    //   32: iadd
    //   33: invokevirtual substring : (II)Ljava/lang/String;
    //   36: iconst_m1
    //   37: goto -> 142
    //   40: aload #5
    //   42: swap
    //   43: iload_3
    //   44: iinc #3, 1
    //   47: swap
    //   48: aastore
    //   49: iload_0
    //   50: iload_1
    //   51: iadd
    //   52: dup
    //   53: istore_0
    //   54: iload #4
    //   56: if_icmpge -> 68
    //   59: aload_2
    //   60: iload_0
    //   61: invokevirtual charAt : (I)C
    //   64: istore_1
    //   65: goto -> 23
    //   68: ldc 'aM6\\t|Fo'
    //   70: dup
    //   71: astore_2
    //   72: invokevirtual length : ()I
    //   75: istore #4
    //   77: iconst_4
    //   78: istore_1
    //   79: iconst_m1
    //   80: istore_0
    //   81: bipush #101
    //   83: iinc #0, 1
    //   86: aload_2
    //   87: iload_0
    //   88: dup
    //   89: iload_1
    //   90: iadd
    //   91: invokevirtual substring : (II)Ljava/lang/String;
    //   94: iconst_0
    //   95: goto -> 142
    //   98: aload #5
    //   100: swap
    //   101: iload_3
    //   102: iinc #3, 1
    //   105: swap
    //   106: aastore
    //   107: iload_0
    //   108: iload_1
    //   109: iadd
    //   110: dup
    //   111: istore_0
    //   112: iload #4
    //   114: if_icmpge -> 126
    //   117: aload_2
    //   118: iload_0
    //   119: invokevirtual charAt : (I)C
    //   122: istore_1
    //   123: goto -> 81
    //   126: aload #5
    //   128: putstatic burp/Zb20.a : [Ljava/lang/String;
    //   131: bipush #8
    //   133: anewarray java/lang/String
    //   136: putstatic burp/Zb20.b : [Ljava/lang/String;
    //   139: goto -> 300
    //   142: dup_x2
    //   143: pop
    //   144: invokevirtual toCharArray : ()[C
    //   147: dup_x1
    //   148: arraylength
    //   149: dup_x2
    //   150: pop
    //   151: iconst_0
    //   152: istore #6
    //   154: dup2_x1
    //   155: pop2
    //   156: dup_x2
    //   157: iconst_1
    //   158: if_icmpgt -> 260
    //   161: dup2
    //   162: swap
    //   163: iload #6
    //   165: dup2_x1
    //   166: caload
    //   167: swap
    //   168: iload #6
    //   170: bipush #7
    //   172: irem
    //   173: tableswitch default -> 242, 0 -> 212, 1 -> 217, 2 -> 222, 3 -> 227, 4 -> 232, 5 -> 237
    //   212: bipush #90
    //   214: goto -> 244
    //   217: bipush #87
    //   219: goto -> 244
    //   222: bipush #23
    //   224: goto -> 244
    //   227: bipush #23
    //   229: goto -> 244
    //   232: bipush #127
    //   234: goto -> 244
    //   237: bipush #117
    //   239: goto -> 244
    //   242: bipush #122
    //   244: ixor
    //   245: ixor
    //   246: i2c
    //   247: castore
    //   248: iinc #6, 1
    //   251: dup
    //   252: ifne -> 260
    //   255: dup2
    //   256: dup_x1
    //   257: goto -> 165
    //   260: dup2_x1
    //   261: pop2
    //   262: dup_x2
    //   263: iload #6
    //   265: if_icmpgt -> 161
    //   268: pop
    //   269: new java/lang/String
    //   272: dup_x1
    //   273: swap
    //   274: invokespecial <init> : ([C)V
    //   277: invokevirtual intern : ()Ljava/lang/String;
    //   280: swap
    //   281: pop
    //   282: swap
    //   283: tableswitch default -> 40, 0 -> 98
    //   300: sipush #-27379
    //   303: sipush #15120
    //   306: invokestatic a : (II)Ljava/lang/String;
    //   309: putstatic burp/Zb20.ZL : Ljava/lang/String;
    //   312: new java/math/BigInteger
    //   315: dup
    //   316: bipush #32
    //   318: newarray byte
    //   320: dup
    //   321: iconst_0
    //   322: bipush #14
    //   324: bastore
    //   325: dup
    //   326: iconst_1
    //   327: bipush #-88
    //   329: bastore
    //   330: dup
    //   331: iconst_2
    //   332: iconst_2
    //   333: bastore
    //   334: dup
    //   335: iconst_3
    //   336: bipush #83
    //   338: bastore
    //   339: dup
    //   340: iconst_4
    //   341: bipush #-92
    //   343: bastore
    //   344: dup
    //   345: iconst_5
    //   346: bipush #89
    //   348: bastore
    //   349: dup
    //   350: bipush #6
    //   352: bipush #-111
    //   354: bastore
    //   355: dup
    //   356: bipush #7
    //   358: bipush #-8
    //   360: bastore
    //   361: dup
    //   362: bipush #8
    //   364: bipush #-100
    //   366: bastore
    //   367: dup
    //   368: bipush #9
    //   370: bipush #67
    //   372: bastore
    //   373: dup
    //   374: bipush #10
    //   376: bipush #-30
    //   378: bastore
    //   379: dup
    //   380: bipush #11
    //   382: bipush #-124
    //   384: bastore
    //   385: dup
    //   386: bipush #12
    //   388: bipush #58
    //   390: bastore
    //   391: dup
    //   392: bipush #13
    //   394: bipush #-81
    //   396: bastore
    //   397: dup
    //   398: bipush #14
    //   400: bipush #32
    //   402: bastore
    //   403: dup
    //   404: bipush #15
    //   406: bipush #118
    //   408: bastore
    //   409: dup
    //   410: bipush #16
    //   412: bipush #-16
    //   414: bastore
    //   415: dup
    //   416: bipush #17
    //   418: bipush #-45
    //   420: bastore
    //   421: dup
    //   422: bipush #18
    //   424: bipush #-121
    //   426: bastore
    //   427: dup
    //   428: bipush #19
    //   430: bipush #70
    //   432: bastore
    //   433: dup
    //   434: bipush #20
    //   436: iconst_5
    //   437: bastore
    //   438: dup
    //   439: bipush #21
    //   441: bipush #-17
    //   443: bastore
    //   444: dup
    //   445: bipush #22
    //   447: bipush #-122
    //   449: bastore
    //   450: dup
    //   451: bipush #23
    //   453: bipush #-48
    //   455: bastore
    //   456: dup
    //   457: bipush #24
    //   459: bipush #-19
    //   461: bastore
    //   462: dup
    //   463: bipush #25
    //   465: bipush #112
    //   467: bastore
    //   468: dup
    //   469: bipush #26
    //   471: bipush #-124
    //   473: bastore
    //   474: dup
    //   475: bipush #27
    //   477: bipush #-100
    //   479: bastore
    //   480: dup
    //   481: bipush #28
    //   483: bipush #91
    //   485: bastore
    //   486: dup
    //   487: bipush #29
    //   489: bipush #43
    //   491: bastore
    //   492: dup
    //   493: bipush #30
    //   495: bipush #-86
    //   497: bastore
    //   498: dup
    //   499: bipush #31
    //   501: bipush #-22
    //   503: bastore
    //   504: invokespecial <init> : ([B)V
    //   507: putstatic burp/Zb20.Zq : Ljava/lang/Object;
    //   510: return
  }
  
  private static Throwable a(Throwable paramThrowable) {
    return paramThrowable;
  }
  
  private static String a(int paramInt1, int paramInt2) {
    int i = (paramInt1 ^ 0xFFFF950D) & 0xFFFF;
    if (b[i] == null) {
      char[] arrayOfChar = a[i].toCharArray();
      switch (arrayOfChar[0] & 0xFF) {
        case 0:
        
        case 1:
        
        case 2:
        
        case 3:
        
        case 4:
        
        case 5:
        
        case 6:
        
        case 7:
        
        case 8:
        
        case 9:
        
        case 10:
        
        case 11:
        
        case 12:
        
        case 13:
        
        case 14:
        
        case 15:
        
        case 16:
        
        case 17:
        
        case 18:
        
        case 19:
        
        case 20:
        
        case 21:
        
        case 22:
        
        case 23:
        
        case 24:
        
        case 25:
        
        case 26:
        
        case 27:
        
        case 28:
        
        case 29:
        
        case 30:
        
        case 31:
        
        case 32:
        
        case 33:
        
        case 34:
        
        case 35:
        
        case 36:
        
        case 37:
        
        case 38:
        
        case 39:
        
        case 40:
        
        case 41:
        
        case 42:
        
        case 43:
        
        case 44:
        
        case 45:
        
        case 46:
        
        case 47:
        
        case 48:
        
        case 49:
        
        case 50:
        
        case 51:
        
        case 52:
        
        case 53:
        
        case 54:
        
        case 55:
        
        case 56:
        
        case 57:
        
        case 58:
        
        case 59:
        
        case 60:
        
        case 61:
        
        case 62:
        
        case 63:
        
        case 64:
        
        case 65:
        
        case 66:
        
        case 67:
        
        case 68:
        
        case 69:
        
        case 70:
        
        case 71:
        
        case 72:
        
        case 73:
        
        case 74:
        
        case 75:
        
        case 76:
        
        case 77:
        
        case 78:
        
        case 79:
        
        case 80:
        
        case 81:
        
        case 82:
        
        case 83:
        
        case 84:
        
        case 85:
        
        case 86:
        
        case 87:
        
        case 88:
        
        case 89:
        
        case 90:
        
        case 91:
        
        case 92:
        
        case 93:
        
        case 94:
        
        case 95:
        
        case 96:
        
        case 97:
        
        case 98:
        
        case 99:
        
        case 100:
        
        case 101:
        
        case 102:
        
        case 103:
        
        case 104:
        
        case 105:
        
        case 106:
        
        case 107:
        
        case 108:
        
        case 109:
        
        case 110:
        
        case 111:
        
        case 112:
        
        case 113:
        
        case 114:
        
        case 115:
        
        case 116:
        
        case 117:
        
        case 118:
        
        case 119:
        
        case 120:
        
        case 121:
        
        case 122:
        
        case 123:
        
        case 124:
        
        case 125:
        
        case 126:
        
        case 127:
        
        case 128:
        
        case 129:
        
        case 130:
        
        case 131:
        
        case 132:
        
        case 133:
        
        case 134:
        
        case 135:
        
        case 136:
        
        case 137:
        
        case 138:
        
        case 139:
        
        case 140:
        
        case 141:
        
        case 142:
        
        case 143:
        
        case 144:
        
        case 145:
        
        case 146:
        
        case 147:
        
        case 148:
        
        case 149:
        
        case 150:
        
        case 151:
        
        case 152:
        
        case 153:
        
        case 154:
        
        case 155:
        
        case 156:
        
        case 157:
        
        case 158:
        
        case 159:
        
        case 160:
        
        case 161:
        
        case 162:
        
        case 163:
        
        case 164:
        
        case 165:
        
        case 166:
        
        case 167:
        
        case 168:
        
        case 169:
        
        case 170:
        
        case 171:
        
        case 172:
        
        case 173:
        
        case 174:
        
        case 175:
        
        case 176:
        
        case 177:
        
        case 178:
        
        case 179:
        
        case 180:
        
        case 181:
        
        case 182:
        
        case 183:
        
        case 184:
        
        case 185:
        
        case 186:
        
        case 187:
        
        case 188:
        
        case 189:
        
        case 190:
        
        case 191:
        
        case 192:
        
        case 193:
        
        case 194:
        
        case 195:
        
        case 196:
        
        case 197:
        
        case 198:
        
        case 199:
        
        case 200:
        
        case 201:
        
        case 202:
        
        case 203:
        
        case 204:
        
        case 205:
        
        case 206:
        
        case 207:
        
        case 208:
        
        case 209:
        
        case 210:
        
        case 211:
        
        case 212:
        
        case 213:
        
        case 214:
        
        case 215:
        
        case 216:
        
        case 217:
        
        case 218:
        
        case 219:
        
        case 220:
        
        case 221:
        
        case 222:
        
        case 223:
        
        case 224:
        
        case 225:
        
        case 226:
        
        case 227:
        
        case 228:
        
        case 229:
        
        case 230:
        
        case 231:
        
        case 232:
        
        case 233:
        
        case 234:
        
        case 235:
        
        case 236:
        
        case 237:
        
        case 238:
        
        case 239:
        
        case 240:
        
        case 241:
        
        case 242:
        
        case 243:
        
        case 244:
        
        case 245:
        
        case 246:
        
        case 247:
        
        case 248:
        
        case 249:
        
        case 250:
        
        case 251:
        
        case 252:
        
        case 253:
        
        case 254:
        
        default:
          break;
      } 
      char c = '';
      int j = (paramInt2 & 0xFF) - c;
      if (j < 0)
        j += 256; 
      int k = ((paramInt2 & 0xFFFF) >>> 8) - c;
      if (k < 0)
        k += 256; 
      for (byte b = 0; b < arrayOfChar.length; b++) {
        int m = b % 2;
        if (m == 0) {
          arrayOfChar[b] = (char)(arrayOfChar[b] ^ j);
          j = ((j >>> 3 | j << 5) ^ arrayOfChar[b]) & 0xFF;
        } else {
          arrayOfChar[b] = (char)(arrayOfChar[b] ^ k);
          k = ((k >>> 3 | k << 5) ^ arrayOfChar[b]) & 0xFF;
        } 
      } 
      b[i] = (new String(arrayOfChar)).intern();
    } 
    return b[i];
  }
}


/* Location:              C:\Program Files\BurpSuitePro\burpsuite_pro.jar!\burp\Zb20.class
 * Java compiler version: 21 (65.0)
 * JD-Core Version:       1.1.3
 */