package burp;

import java.math.BigInteger;

class Zb2p extends ClassLoader {
  static Object ZQ;
  
  static String ZV;
  
  private static final String[] a;
  
  private static final String[] b;
  
  static boolean Zi(Object[] paramArrayOfObject, Object paramObject) throws Throwable {
    // Byte code:
    //   0: invokestatic ZN : ()Z
    //   3: istore_2
    //   4: new java/io/ByteArrayOutputStream
    //   7: dup
    //   8: invokespecial <init> : ()V
    //   11: astore_3
    //   12: getstatic burp/Zmgl.Zh : Ljava/lang/String;
    //   15: astore #4
    //   17: iconst_0
    //   18: istore #5
    //   20: iload #5
    //   22: aload #4
    //   24: invokevirtual length : ()I
    //   27: if_icmpge -> 57
    //   30: aload_3
    //   31: aload #4
    //   33: iload #5
    //   35: iload #5
    //   37: iconst_2
    //   38: iadd
    //   39: invokevirtual substring : (II)Ljava/lang/String;
    //   42: bipush #16
    //   44: invokestatic parseInt : (Ljava/lang/String;I)I
    //   47: invokevirtual write : (I)V
    //   50: iinc #5, 2
    //   53: iload_2
    //   54: ifne -> 20
    //   57: aload_3
    //   58: invokevirtual toByteArray : ()[B
    //   61: astore #5
    //   63: getstatic burp/Zmgl.ZI : Ljava/lang/Object;
    //   66: checkcast java/math/BigInteger
    //   69: invokevirtual toByteArray : ()[B
    //   72: astore #6
    //   74: sipush #256
    //   77: newarray byte
    //   79: astore #8
    //   81: sipush #256
    //   84: newarray int
    //   86: astore #9
    //   88: sipush #256
    //   91: newarray int
    //   93: astore #10
    //   95: sipush #256
    //   98: newarray int
    //   100: astore #11
    //   102: sipush #256
    //   105: newarray int
    //   107: astore #12
    //   109: bipush #10
    //   111: newarray int
    //   113: astore #13
    //   115: sipush #283
    //   118: istore #14
    //   120: iconst_0
    //   121: istore #16
    //   123: iload #16
    //   125: sipush #256
    //   128: if_icmpge -> 362
    //   131: sipush #11518
    //   134: sipush #29008
    //   137: invokestatic a : (II)Ljava/lang/String;
    //   140: iload #16
    //   142: iconst_1
    //   143: iushr
    //   144: invokevirtual charAt : (I)C
    //   147: istore #25
    //   149: iload #16
    //   151: iconst_1
    //   152: iand
    //   153: ifne -> 168
    //   156: iload #25
    //   158: bipush #8
    //   160: iushr
    //   161: goto -> 170
    //   164: invokestatic a : (Ljava/lang/Throwable;)Ljava/lang/Throwable;
    //   167: athrow
    //   168: iload #25
    //   170: i2b
    //   171: sipush #255
    //   174: iand
    //   175: istore #15
    //   177: iload #16
    //   179: iconst_1
    //   180: ishl
    //   181: istore #17
    //   183: iload #17
    //   185: sipush #256
    //   188: if_icmplt -> 198
    //   191: iload #17
    //   193: iload #14
    //   195: ixor
    //   196: istore #17
    //   198: iload #17
    //   200: iconst_1
    //   201: ishl
    //   202: istore #18
    //   204: iload #18
    //   206: sipush #256
    //   209: if_icmplt -> 219
    //   212: iload #18
    //   214: iload #14
    //   216: ixor
    //   217: istore #18
    //   219: iload #18
    //   221: iconst_1
    //   222: ishl
    //   223: istore #19
    //   225: iload #19
    //   227: sipush #256
    //   230: if_icmplt -> 240
    //   233: iload #19
    //   235: iload #14
    //   237: ixor
    //   238: istore #19
    //   240: iload #19
    //   242: iload #16
    //   244: ixor
    //   245: istore #20
    //   247: iload #20
    //   249: iload #17
    //   251: ixor
    //   252: istore #21
    //   254: iload #20
    //   256: iload #18
    //   258: ixor
    //   259: istore #22
    //   261: iload #19
    //   263: iload #18
    //   265: ixor
    //   266: iload #17
    //   268: ixor
    //   269: istore #23
    //   271: aload #8
    //   273: iload #16
    //   275: iload #15
    //   277: i2b
    //   278: bastore
    //   279: aload #9
    //   281: iload #15
    //   283: iload #23
    //   285: bipush #24
    //   287: ishl
    //   288: iload #20
    //   290: bipush #16
    //   292: ishl
    //   293: ior
    //   294: iload #22
    //   296: bipush #8
    //   298: ishl
    //   299: ior
    //   300: iload #21
    //   302: ior
    //   303: dup
    //   304: istore #24
    //   306: iastore
    //   307: aload #10
    //   309: iload #15
    //   311: iload #24
    //   313: bipush #8
    //   315: iushr
    //   316: iload #24
    //   318: bipush #24
    //   320: ishl
    //   321: ior
    //   322: iastore
    //   323: aload #11
    //   325: iload #15
    //   327: iload #24
    //   329: bipush #16
    //   331: iushr
    //   332: iload #24
    //   334: bipush #16
    //   336: ishl
    //   337: ior
    //   338: iastore
    //   339: aload #12
    //   341: iload #15
    //   343: iload #24
    //   345: bipush #24
    //   347: iushr
    //   348: iload #24
    //   350: bipush #8
    //   352: ishl
    //   353: ior
    //   354: iastore
    //   355: iinc #16, 1
    //   358: iload_2
    //   359: ifne -> 123
    //   362: iconst_1
    //   363: istore #25
    //   365: aload #13
    //   367: iconst_0
    //   368: iload #25
    //   370: bipush #24
    //   372: ishl
    //   373: iastore
    //   374: iconst_1
    //   375: istore #26
    //   377: iload #26
    //   379: bipush #10
    //   381: if_icmpge -> 422
    //   384: iload #25
    //   386: iconst_1
    //   387: ishl
    //   388: istore #25
    //   390: iload #25
    //   392: sipush #256
    //   395: if_icmplt -> 405
    //   398: iload #25
    //   400: iload #14
    //   402: ixor
    //   403: istore #25
    //   405: aload #13
    //   407: iload #26
    //   409: iload #25
    //   411: bipush #24
    //   413: ishl
    //   414: iastore
    //   415: iinc #26, 1
    //   418: iload_2
    //   419: ifne -> 377
    //   422: iconst_4
    //   423: istore #26
    //   425: iload #26
    //   427: bipush #6
    //   429: iadd
    //   430: istore #27
    //   432: iconst_4
    //   433: iload #27
    //   435: iconst_1
    //   436: iadd
    //   437: imul
    //   438: istore #28
    //   440: iload #28
    //   442: newarray int
    //   444: astore #29
    //   446: iload #28
    //   448: newarray int
    //   450: astore #30
    //   452: iconst_0
    //   453: istore #25
    //   455: iconst_0
    //   456: istore #32
    //   458: iconst_0
    //   459: istore #33
    //   461: iload #32
    //   463: iload #26
    //   465: if_icmpge -> 533
    //   468: aload #29
    //   470: iload #32
    //   472: aload #5
    //   474: iload #33
    //   476: baload
    //   477: bipush #24
    //   479: ishl
    //   480: aload #5
    //   482: iload #33
    //   484: iconst_1
    //   485: iadd
    //   486: baload
    //   487: sipush #255
    //   490: iand
    //   491: bipush #16
    //   493: ishl
    //   494: ior
    //   495: aload #5
    //   497: iload #33
    //   499: iconst_2
    //   500: iadd
    //   501: baload
    //   502: sipush #255
    //   505: iand
    //   506: bipush #8
    //   508: ishl
    //   509: ior
    //   510: aload #5
    //   512: iload #33
    //   514: iconst_3
    //   515: iadd
    //   516: baload
    //   517: sipush #255
    //   520: iand
    //   521: ior
    //   522: iastore
    //   523: iinc #32, 1
    //   526: iinc #33, 4
    //   529: iload_2
    //   530: ifne -> 461
    //   533: iload #26
    //   535: istore #32
    //   537: iconst_0
    //   538: istore #33
    //   540: iload #32
    //   542: iload #28
    //   544: if_icmpge -> 671
    //   547: aload #29
    //   549: iload #32
    //   551: iconst_1
    //   552: isub
    //   553: iaload
    //   554: istore #31
    //   556: iload #33
    //   558: ifne -> 645
    //   561: iload #26
    //   563: istore #33
    //   565: aload #8
    //   567: iload #31
    //   569: bipush #16
    //   571: iushr
    //   572: sipush #255
    //   575: iand
    //   576: baload
    //   577: bipush #24
    //   579: ishl
    //   580: aload #8
    //   582: iload #31
    //   584: bipush #8
    //   586: iushr
    //   587: sipush #255
    //   590: iand
    //   591: baload
    //   592: sipush #255
    //   595: iand
    //   596: bipush #16
    //   598: ishl
    //   599: ior
    //   600: aload #8
    //   602: iload #31
    //   604: sipush #255
    //   607: iand
    //   608: baload
    //   609: sipush #255
    //   612: iand
    //   613: bipush #8
    //   615: ishl
    //   616: ior
    //   617: aload #8
    //   619: iload #31
    //   621: bipush #24
    //   623: iushr
    //   624: baload
    //   625: sipush #255
    //   628: iand
    //   629: ior
    //   630: istore #31
    //   632: iload #31
    //   634: aload #13
    //   636: iload #25
    //   638: iinc #25, 1
    //   641: iaload
    //   642: ixor
    //   643: istore #31
    //   645: aload #29
    //   647: iload #32
    //   649: aload #29
    //   651: iload #32
    //   653: iload #26
    //   655: isub
    //   656: iaload
    //   657: iload #31
    //   659: ixor
    //   660: iastore
    //   661: iinc #32, 1
    //   664: iinc #33, -1
    //   667: iload_2
    //   668: ifne -> 540
    //   671: iconst_0
    //   672: istore #32
    //   674: iconst_4
    //   675: iload #27
    //   677: imul
    //   678: istore #33
    //   680: aload #30
    //   682: iload #32
    //   684: aload #29
    //   686: iload #33
    //   688: iaload
    //   689: iastore
    //   690: aload #30
    //   692: iload #32
    //   694: iconst_1
    //   695: iadd
    //   696: aload #29
    //   698: iload #33
    //   700: iconst_1
    //   701: iadd
    //   702: iaload
    //   703: iastore
    //   704: aload #30
    //   706: iload #32
    //   708: iconst_2
    //   709: iadd
    //   710: aload #29
    //   712: iload #33
    //   714: iconst_2
    //   715: iadd
    //   716: iaload
    //   717: iastore
    //   718: aload #30
    //   720: iload #32
    //   722: iconst_3
    //   723: iadd
    //   724: aload #29
    //   726: iload #33
    //   728: iconst_3
    //   729: iadd
    //   730: iaload
    //   731: iastore
    //   732: iinc #32, 4
    //   735: iinc #33, -4
    //   738: iconst_1
    //   739: istore #35
    //   741: iload #35
    //   743: iload #27
    //   745: if_icmpge -> 1109
    //   748: aload #29
    //   750: iload #33
    //   752: iaload
    //   753: istore #34
    //   755: aload #30
    //   757: iload #32
    //   759: aload #9
    //   761: aload #8
    //   763: iload #34
    //   765: bipush #24
    //   767: iushr
    //   768: baload
    //   769: sipush #255
    //   772: iand
    //   773: iaload
    //   774: aload #10
    //   776: aload #8
    //   778: iload #34
    //   780: bipush #16
    //   782: iushr
    //   783: sipush #255
    //   786: iand
    //   787: baload
    //   788: sipush #255
    //   791: iand
    //   792: iaload
    //   793: ixor
    //   794: aload #11
    //   796: aload #8
    //   798: iload #34
    //   800: bipush #8
    //   802: iushr
    //   803: sipush #255
    //   806: iand
    //   807: baload
    //   808: sipush #255
    //   811: iand
    //   812: iaload
    //   813: ixor
    //   814: aload #12
    //   816: aload #8
    //   818: iload #34
    //   820: sipush #255
    //   823: iand
    //   824: baload
    //   825: sipush #255
    //   828: iand
    //   829: iaload
    //   830: ixor
    //   831: iastore
    //   832: aload #29
    //   834: iload #33
    //   836: iconst_1
    //   837: iadd
    //   838: iaload
    //   839: istore #34
    //   841: aload #30
    //   843: iload #32
    //   845: iconst_1
    //   846: iadd
    //   847: aload #9
    //   849: aload #8
    //   851: iload #34
    //   853: bipush #24
    //   855: iushr
    //   856: baload
    //   857: sipush #255
    //   860: iand
    //   861: iaload
    //   862: aload #10
    //   864: aload #8
    //   866: iload #34
    //   868: bipush #16
    //   870: iushr
    //   871: sipush #255
    //   874: iand
    //   875: baload
    //   876: sipush #255
    //   879: iand
    //   880: iaload
    //   881: ixor
    //   882: aload #11
    //   884: aload #8
    //   886: iload #34
    //   888: bipush #8
    //   890: iushr
    //   891: sipush #255
    //   894: iand
    //   895: baload
    //   896: sipush #255
    //   899: iand
    //   900: iaload
    //   901: ixor
    //   902: aload #12
    //   904: aload #8
    //   906: iload #34
    //   908: sipush #255
    //   911: iand
    //   912: baload
    //   913: sipush #255
    //   916: iand
    //   917: iaload
    //   918: ixor
    //   919: iastore
    //   920: aload #29
    //   922: iload #33
    //   924: iconst_2
    //   925: iadd
    //   926: iaload
    //   927: istore #34
    //   929: aload #30
    //   931: iload #32
    //   933: iconst_2
    //   934: iadd
    //   935: aload #9
    //   937: aload #8
    //   939: iload #34
    //   941: bipush #24
    //   943: iushr
    //   944: baload
    //   945: sipush #255
    //   948: iand
    //   949: iaload
    //   950: aload #10
    //   952: aload #8
    //   954: iload #34
    //   956: bipush #16
    //   958: iushr
    //   959: sipush #255
    //   962: iand
    //   963: baload
    //   964: sipush #255
    //   967: iand
    //   968: iaload
    //   969: ixor
    //   970: aload #11
    //   972: aload #8
    //   974: iload #34
    //   976: bipush #8
    //   978: iushr
    //   979: sipush #255
    //   982: iand
    //   983: baload
    //   984: sipush #255
    //   987: iand
    //   988: iaload
    //   989: ixor
    //   990: aload #12
    //   992: aload #8
    //   994: iload #34
    //   996: sipush #255
    //   999: iand
    //   1000: baload
    //   1001: sipush #255
    //   1004: iand
    //   1005: iaload
    //   1006: ixor
    //   1007: iastore
    //   1008: aload #29
    //   1010: iload #33
    //   1012: iconst_3
    //   1013: iadd
    //   1014: iaload
    //   1015: istore #34
    //   1017: aload #30
    //   1019: iload #32
    //   1021: iconst_3
    //   1022: iadd
    //   1023: aload #9
    //   1025: aload #8
    //   1027: iload #34
    //   1029: bipush #24
    //   1031: iushr
    //   1032: baload
    //   1033: sipush #255
    //   1036: iand
    //   1037: iaload
    //   1038: aload #10
    //   1040: aload #8
    //   1042: iload #34
    //   1044: bipush #16
    //   1046: iushr
    //   1047: sipush #255
    //   1050: iand
    //   1051: baload
    //   1052: sipush #255
    //   1055: iand
    //   1056: iaload
    //   1057: ixor
    //   1058: aload #11
    //   1060: aload #8
    //   1062: iload #34
    //   1064: bipush #8
    //   1066: iushr
    //   1067: sipush #255
    //   1070: iand
    //   1071: baload
    //   1072: sipush #255
    //   1075: iand
    //   1076: iaload
    //   1077: ixor
    //   1078: aload #12
    //   1080: aload #8
    //   1082: iload #34
    //   1084: sipush #255
    //   1087: iand
    //   1088: baload
    //   1089: sipush #255
    //   1092: iand
    //   1093: iaload
    //   1094: ixor
    //   1095: iastore
    //   1096: iinc #32, 4
    //   1099: iinc #33, -4
    //   1102: iinc #35, 1
    //   1105: iload_2
    //   1106: ifne -> 741
    //   1109: aload #30
    //   1111: iload #32
    //   1113: aload #29
    //   1115: iload #33
    //   1117: iaload
    //   1118: iastore
    //   1119: aload #30
    //   1121: iload #32
    //   1123: iconst_1
    //   1124: iadd
    //   1125: aload #29
    //   1127: iload #33
    //   1129: iconst_1
    //   1130: iadd
    //   1131: iaload
    //   1132: iastore
    //   1133: aload #30
    //   1135: iload #32
    //   1137: iconst_2
    //   1138: iadd
    //   1139: aload #29
    //   1141: iload #33
    //   1143: iconst_2
    //   1144: iadd
    //   1145: iaload
    //   1146: iastore
    //   1147: aload #30
    //   1149: iload #32
    //   1151: iconst_3
    //   1152: iadd
    //   1153: aload #29
    //   1155: iload #33
    //   1157: iconst_3
    //   1158: iadd
    //   1159: iaload
    //   1160: iastore
    //   1161: iconst_0
    //   1162: newarray byte
    //   1164: astore #35
    //   1166: aload #6
    //   1168: arraylength
    //   1169: bipush #16
    //   1171: irem
    //   1172: ifeq -> 1196
    //   1175: new java/lang/Exception
    //   1178: dup
    //   1179: sipush #11489
    //   1182: sipush #-30584
    //   1185: invokestatic a : (II)Ljava/lang/String;
    //   1188: invokespecial <init> : (Ljava/lang/String;)V
    //   1191: athrow
    //   1192: invokestatic a : (Ljava/lang/Throwable;)Ljava/lang/Throwable;
    //   1195: athrow
    //   1196: bipush #10
    //   1198: istore #36
    //   1200: sipush #11497
    //   1203: sipush #256
    //   1206: newarray byte
    //   1208: astore #37
    //   1210: sipush #3671
    //   1213: sipush #256
    //   1216: newarray int
    //   1218: astore #38
    //   1220: sipush #256
    //   1223: newarray int
    //   1225: astore #39
    //   1227: sipush #256
    //   1230: newarray int
    //   1232: astore #40
    //   1234: sipush #256
    //   1237: newarray int
    //   1239: astore #41
    //   1241: sipush #283
    //   1244: istore #14
    //   1246: invokestatic a : (II)Ljava/lang/String;
    //   1249: astore #42
    //   1251: iconst_0
    //   1252: istore #16
    //   1254: iload #16
    //   1256: sipush #256
    //   1259: if_icmpge -> 1486
    //   1262: aload #42
    //   1264: iload #16
    //   1266: iconst_1
    //   1267: iushr
    //   1268: invokevirtual charAt : (I)C
    //   1271: istore #43
    //   1273: iload #16
    //   1275: iconst_1
    //   1276: iand
    //   1277: ifne -> 1292
    //   1280: iload #43
    //   1282: bipush #8
    //   1284: iushr
    //   1285: goto -> 1294
    //   1288: invokestatic a : (Ljava/lang/Throwable;)Ljava/lang/Throwable;
    //   1291: athrow
    //   1292: iload #43
    //   1294: i2b
    //   1295: sipush #255
    //   1298: iand
    //   1299: istore #15
    //   1301: iload #16
    //   1303: iconst_1
    //   1304: ishl
    //   1305: istore #17
    //   1307: iload #17
    //   1309: sipush #256
    //   1312: if_icmplt -> 1322
    //   1315: iload #17
    //   1317: iload #14
    //   1319: ixor
    //   1320: istore #17
    //   1322: iload #17
    //   1324: iconst_1
    //   1325: ishl
    //   1326: istore #18
    //   1328: iload #18
    //   1330: sipush #256
    //   1333: if_icmplt -> 1343
    //   1336: iload #18
    //   1338: iload #14
    //   1340: ixor
    //   1341: istore #18
    //   1343: iload #18
    //   1345: iconst_1
    //   1346: ishl
    //   1347: istore #19
    //   1349: iload #19
    //   1351: sipush #256
    //   1354: if_icmplt -> 1364
    //   1357: iload #19
    //   1359: iload #14
    //   1361: ixor
    //   1362: istore #19
    //   1364: iload #19
    //   1366: iload #16
    //   1368: ixor
    //   1369: istore #20
    //   1371: iload #20
    //   1373: iload #17
    //   1375: ixor
    //   1376: istore #21
    //   1378: iload #20
    //   1380: iload #18
    //   1382: ixor
    //   1383: istore #22
    //   1385: iload #19
    //   1387: iload #18
    //   1389: ixor
    //   1390: iload #17
    //   1392: ixor
    //   1393: istore #23
    //   1395: aload #37
    //   1397: iload #15
    //   1399: iload #16
    //   1401: i2b
    //   1402: bastore
    //   1403: aload #38
    //   1405: iload #15
    //   1407: iload #23
    //   1409: bipush #24
    //   1411: ishl
    //   1412: iload #20
    //   1414: bipush #16
    //   1416: ishl
    //   1417: ior
    //   1418: iload #22
    //   1420: bipush #8
    //   1422: ishl
    //   1423: ior
    //   1424: iload #21
    //   1426: ior
    //   1427: dup
    //   1428: istore #24
    //   1430: iastore
    //   1431: aload #39
    //   1433: iload #15
    //   1435: iload #24
    //   1437: bipush #8
    //   1439: iushr
    //   1440: iload #24
    //   1442: bipush #24
    //   1444: ishl
    //   1445: ior
    //   1446: iastore
    //   1447: aload #40
    //   1449: iload #15
    //   1451: iload #24
    //   1453: bipush #16
    //   1455: iushr
    //   1456: iload #24
    //   1458: bipush #16
    //   1460: ishl
    //   1461: ior
    //   1462: iastore
    //   1463: aload #41
    //   1465: iload #15
    //   1467: iload #24
    //   1469: bipush #24
    //   1471: iushr
    //   1472: iload #24
    //   1474: bipush #8
    //   1476: ishl
    //   1477: ior
    //   1478: iastore
    //   1479: iinc #16, 1
    //   1482: iload_2
    //   1483: ifne -> 1254
    //   1486: aload #6
    //   1488: arraylength
    //   1489: newarray byte
    //   1491: astore #43
    //   1493: iconst_0
    //   1494: istore #44
    //   1496: iload #44
    //   1498: aload #6
    //   1500: arraylength
    //   1501: bipush #16
    //   1503: idiv
    //   1504: if_icmpge -> 2418
    //   1507: bipush #16
    //   1509: newarray byte
    //   1511: astore #45
    //   1513: bipush #16
    //   1515: newarray byte
    //   1517: astore #46
    //   1519: iconst_0
    //   1520: istore #47
    //   1522: iload #47
    //   1524: bipush #16
    //   1526: if_icmpge -> 1552
    //   1529: aload #45
    //   1531: iload #47
    //   1533: aload #6
    //   1535: iload #47
    //   1537: iload #44
    //   1539: bipush #16
    //   1541: imul
    //   1542: iadd
    //   1543: baload
    //   1544: bastore
    //   1545: iinc #47, 1
    //   1548: iload_2
    //   1549: ifne -> 1522
    //   1552: iconst_0
    //   1553: istore #47
    //   1555: aload #45
    //   1557: iconst_0
    //   1558: baload
    //   1559: bipush #24
    //   1561: ishl
    //   1562: aload #45
    //   1564: iconst_1
    //   1565: baload
    //   1566: sipush #255
    //   1569: iand
    //   1570: bipush #16
    //   1572: ishl
    //   1573: ior
    //   1574: aload #45
    //   1576: iconst_2
    //   1577: baload
    //   1578: sipush #255
    //   1581: iand
    //   1582: bipush #8
    //   1584: ishl
    //   1585: ior
    //   1586: aload #45
    //   1588: iconst_3
    //   1589: baload
    //   1590: sipush #255
    //   1593: iand
    //   1594: ior
    //   1595: aload #30
    //   1597: iconst_0
    //   1598: iaload
    //   1599: ixor
    //   1600: istore #49
    //   1602: aload #45
    //   1604: iconst_4
    //   1605: baload
    //   1606: bipush #24
    //   1608: ishl
    //   1609: aload #45
    //   1611: iconst_5
    //   1612: baload
    //   1613: sipush #255
    //   1616: iand
    //   1617: bipush #16
    //   1619: ishl
    //   1620: ior
    //   1621: aload #45
    //   1623: bipush #6
    //   1625: baload
    //   1626: sipush #255
    //   1629: iand
    //   1630: bipush #8
    //   1632: ishl
    //   1633: ior
    //   1634: aload #45
    //   1636: bipush #7
    //   1638: baload
    //   1639: sipush #255
    //   1642: iand
    //   1643: ior
    //   1644: aload #30
    //   1646: iconst_1
    //   1647: iaload
    //   1648: ixor
    //   1649: istore #50
    //   1651: aload #45
    //   1653: bipush #8
    //   1655: baload
    //   1656: bipush #24
    //   1658: ishl
    //   1659: aload #45
    //   1661: bipush #9
    //   1663: baload
    //   1664: sipush #255
    //   1667: iand
    //   1668: bipush #16
    //   1670: ishl
    //   1671: ior
    //   1672: aload #45
    //   1674: bipush #10
    //   1676: baload
    //   1677: sipush #255
    //   1680: iand
    //   1681: bipush #8
    //   1683: ishl
    //   1684: ior
    //   1685: aload #45
    //   1687: bipush #11
    //   1689: baload
    //   1690: sipush #255
    //   1693: iand
    //   1694: ior
    //   1695: aload #30
    //   1697: iconst_2
    //   1698: iaload
    //   1699: ixor
    //   1700: istore #51
    //   1702: aload #45
    //   1704: bipush #12
    //   1706: baload
    //   1707: bipush #24
    //   1709: ishl
    //   1710: aload #45
    //   1712: bipush #13
    //   1714: baload
    //   1715: sipush #255
    //   1718: iand
    //   1719: bipush #16
    //   1721: ishl
    //   1722: ior
    //   1723: aload #45
    //   1725: bipush #14
    //   1727: baload
    //   1728: sipush #255
    //   1731: iand
    //   1732: bipush #8
    //   1734: ishl
    //   1735: ior
    //   1736: aload #45
    //   1738: bipush #15
    //   1740: baload
    //   1741: sipush #255
    //   1744: iand
    //   1745: ior
    //   1746: aload #30
    //   1748: iconst_3
    //   1749: iaload
    //   1750: ixor
    //   1751: istore #52
    //   1753: iconst_1
    //   1754: istore #53
    //   1756: iload #53
    //   1758: iload #36
    //   1760: if_icmpge -> 2003
    //   1763: iinc #47, 4
    //   1766: aload #38
    //   1768: iload #49
    //   1770: bipush #24
    //   1772: iushr
    //   1773: iaload
    //   1774: aload #39
    //   1776: iload #52
    //   1778: bipush #16
    //   1780: iushr
    //   1781: sipush #255
    //   1784: iand
    //   1785: iaload
    //   1786: ixor
    //   1787: aload #40
    //   1789: iload #51
    //   1791: bipush #8
    //   1793: iushr
    //   1794: sipush #255
    //   1797: iand
    //   1798: iaload
    //   1799: ixor
    //   1800: aload #41
    //   1802: iload #50
    //   1804: sipush #255
    //   1807: iand
    //   1808: iaload
    //   1809: ixor
    //   1810: aload #30
    //   1812: iload #47
    //   1814: iaload
    //   1815: ixor
    //   1816: istore #54
    //   1818: aload #38
    //   1820: iload #50
    //   1822: bipush #24
    //   1824: iushr
    //   1825: iaload
    //   1826: aload #39
    //   1828: iload #49
    //   1830: bipush #16
    //   1832: iushr
    //   1833: sipush #255
    //   1836: iand
    //   1837: iaload
    //   1838: ixor
    //   1839: aload #40
    //   1841: iload #52
    //   1843: bipush #8
    //   1845: iushr
    //   1846: sipush #255
    //   1849: iand
    //   1850: iaload
    //   1851: ixor
    //   1852: aload #41
    //   1854: iload #51
    //   1856: sipush #255
    //   1859: iand
    //   1860: iaload
    //   1861: ixor
    //   1862: aload #30
    //   1864: iload #47
    //   1866: iconst_1
    //   1867: iadd
    //   1868: iaload
    //   1869: ixor
    //   1870: istore #55
    //   1872: aload #38
    //   1874: iload #51
    //   1876: bipush #24
    //   1878: iushr
    //   1879: iaload
    //   1880: aload #39
    //   1882: iload #50
    //   1884: bipush #16
    //   1886: iushr
    //   1887: sipush #255
    //   1890: iand
    //   1891: iaload
    //   1892: ixor
    //   1893: aload #40
    //   1895: iload #49
    //   1897: bipush #8
    //   1899: iushr
    //   1900: sipush #255
    //   1903: iand
    //   1904: iaload
    //   1905: ixor
    //   1906: aload #41
    //   1908: iload #52
    //   1910: sipush #255
    //   1913: iand
    //   1914: iaload
    //   1915: ixor
    //   1916: aload #30
    //   1918: iload #47
    //   1920: iconst_2
    //   1921: iadd
    //   1922: iaload
    //   1923: ixor
    //   1924: istore #56
    //   1926: aload #38
    //   1928: iload #52
    //   1930: bipush #24
    //   1932: iushr
    //   1933: iaload
    //   1934: aload #39
    //   1936: iload #51
    //   1938: bipush #16
    //   1940: iushr
    //   1941: sipush #255
    //   1944: iand
    //   1945: iaload
    //   1946: ixor
    //   1947: aload #40
    //   1949: iload #50
    //   1951: bipush #8
    //   1953: iushr
    //   1954: sipush #255
    //   1957: iand
    //   1958: iaload
    //   1959: ixor
    //   1960: aload #41
    //   1962: iload #49
    //   1964: sipush #255
    //   1967: iand
    //   1968: iaload
    //   1969: ixor
    //   1970: aload #30
    //   1972: iload #47
    //   1974: iconst_3
    //   1975: iadd
    //   1976: iaload
    //   1977: ixor
    //   1978: istore #57
    //   1980: iload #54
    //   1982: istore #49
    //   1984: iload #55
    //   1986: istore #50
    //   1988: iload #56
    //   1990: istore #51
    //   1992: iload #57
    //   1994: istore #52
    //   1996: iinc #53, 1
    //   1999: iload_2
    //   2000: ifne -> 1756
    //   2003: iinc #47, 4
    //   2006: aload #30
    //   2008: iload #47
    //   2010: iaload
    //   2011: istore #48
    //   2013: aload #46
    //   2015: iconst_0
    //   2016: aload #37
    //   2018: iload #49
    //   2020: bipush #24
    //   2022: iushr
    //   2023: baload
    //   2024: iload #48
    //   2026: bipush #24
    //   2028: iushr
    //   2029: ixor
    //   2030: i2b
    //   2031: bastore
    //   2032: aload #46
    //   2034: iconst_1
    //   2035: aload #37
    //   2037: iload #52
    //   2039: bipush #16
    //   2041: iushr
    //   2042: sipush #255
    //   2045: iand
    //   2046: baload
    //   2047: iload #48
    //   2049: bipush #16
    //   2051: iushr
    //   2052: ixor
    //   2053: i2b
    //   2054: bastore
    //   2055: aload #46
    //   2057: iconst_2
    //   2058: aload #37
    //   2060: iload #51
    //   2062: bipush #8
    //   2064: iushr
    //   2065: sipush #255
    //   2068: iand
    //   2069: baload
    //   2070: iload #48
    //   2072: bipush #8
    //   2074: iushr
    //   2075: ixor
    //   2076: i2b
    //   2077: bastore
    //   2078: aload #46
    //   2080: iconst_3
    //   2081: aload #37
    //   2083: iload #50
    //   2085: sipush #255
    //   2088: iand
    //   2089: baload
    //   2090: iload #48
    //   2092: ixor
    //   2093: i2b
    //   2094: bastore
    //   2095: aload #30
    //   2097: iload #47
    //   2099: iconst_1
    //   2100: iadd
    //   2101: iaload
    //   2102: istore #48
    //   2104: aload #46
    //   2106: iconst_4
    //   2107: aload #37
    //   2109: iload #50
    //   2111: bipush #24
    //   2113: iushr
    //   2114: baload
    //   2115: iload #48
    //   2117: bipush #24
    //   2119: iushr
    //   2120: ixor
    //   2121: i2b
    //   2122: bastore
    //   2123: aload #46
    //   2125: iconst_5
    //   2126: aload #37
    //   2128: iload #49
    //   2130: bipush #16
    //   2132: iushr
    //   2133: sipush #255
    //   2136: iand
    //   2137: baload
    //   2138: iload #48
    //   2140: bipush #16
    //   2142: iushr
    //   2143: ixor
    //   2144: i2b
    //   2145: bastore
    //   2146: aload #46
    //   2148: bipush #6
    //   2150: aload #37
    //   2152: iload #52
    //   2154: bipush #8
    //   2156: iushr
    //   2157: sipush #255
    //   2160: iand
    //   2161: baload
    //   2162: iload #48
    //   2164: bipush #8
    //   2166: iushr
    //   2167: ixor
    //   2168: i2b
    //   2169: bastore
    //   2170: aload #46
    //   2172: bipush #7
    //   2174: aload #37
    //   2176: iload #51
    //   2178: sipush #255
    //   2181: iand
    //   2182: baload
    //   2183: iload #48
    //   2185: ixor
    //   2186: i2b
    //   2187: bastore
    //   2188: aload #30
    //   2190: iload #47
    //   2192: iconst_2
    //   2193: iadd
    //   2194: iaload
    //   2195: istore #48
    //   2197: aload #46
    //   2199: bipush #8
    //   2201: aload #37
    //   2203: iload #51
    //   2205: bipush #24
    //   2207: iushr
    //   2208: baload
    //   2209: iload #48
    //   2211: bipush #24
    //   2213: iushr
    //   2214: ixor
    //   2215: i2b
    //   2216: bastore
    //   2217: aload #46
    //   2219: bipush #9
    //   2221: aload #37
    //   2223: iload #50
    //   2225: bipush #16
    //   2227: iushr
    //   2228: sipush #255
    //   2231: iand
    //   2232: baload
    //   2233: iload #48
    //   2235: bipush #16
    //   2237: iushr
    //   2238: ixor
    //   2239: i2b
    //   2240: bastore
    //   2241: aload #46
    //   2243: bipush #10
    //   2245: aload #37
    //   2247: iload #49
    //   2249: bipush #8
    //   2251: iushr
    //   2252: sipush #255
    //   2255: iand
    //   2256: baload
    //   2257: iload #48
    //   2259: bipush #8
    //   2261: iushr
    //   2262: ixor
    //   2263: i2b
    //   2264: bastore
    //   2265: aload #46
    //   2267: bipush #11
    //   2269: aload #37
    //   2271: iload #52
    //   2273: sipush #255
    //   2276: iand
    //   2277: baload
    //   2278: iload #48
    //   2280: ixor
    //   2281: i2b
    //   2282: bastore
    //   2283: aload #30
    //   2285: iload #47
    //   2287: iconst_3
    //   2288: iadd
    //   2289: iaload
    //   2290: istore #48
    //   2292: aload #46
    //   2294: bipush #12
    //   2296: aload #37
    //   2298: iload #52
    //   2300: bipush #24
    //   2302: iushr
    //   2303: baload
    //   2304: iload #48
    //   2306: bipush #24
    //   2308: iushr
    //   2309: ixor
    //   2310: i2b
    //   2311: bastore
    //   2312: aload #46
    //   2314: bipush #13
    //   2316: aload #37
    //   2318: iload #51
    //   2320: bipush #16
    //   2322: iushr
    //   2323: sipush #255
    //   2326: iand
    //   2327: baload
    //   2328: iload #48
    //   2330: bipush #16
    //   2332: iushr
    //   2333: ixor
    //   2334: i2b
    //   2335: bastore
    //   2336: aload #46
    //   2338: bipush #14
    //   2340: aload #37
    //   2342: iload #50
    //   2344: bipush #8
    //   2346: iushr
    //   2347: sipush #255
    //   2350: iand
    //   2351: baload
    //   2352: iload #48
    //   2354: bipush #8
    //   2356: iushr
    //   2357: ixor
    //   2358: i2b
    //   2359: bastore
    //   2360: aload #46
    //   2362: bipush #15
    //   2364: aload #37
    //   2366: iload #49
    //   2368: sipush #255
    //   2371: iand
    //   2372: baload
    //   2373: iload #48
    //   2375: ixor
    //   2376: i2b
    //   2377: bastore
    //   2378: iconst_0
    //   2379: istore #53
    //   2381: iload #53
    //   2383: bipush #16
    //   2385: if_icmpge -> 2411
    //   2388: aload #43
    //   2390: iload #53
    //   2392: iload #44
    //   2394: bipush #16
    //   2396: imul
    //   2397: iadd
    //   2398: aload #46
    //   2400: iload #53
    //   2402: baload
    //   2403: bastore
    //   2404: iinc #53, 1
    //   2407: iload_2
    //   2408: ifne -> 2381
    //   2411: iinc #44, 1
    //   2414: iload_2
    //   2415: ifne -> 1496
    //   2418: aload #43
    //   2420: arraylength
    //   2421: ifle -> 2502
    //   2424: aload #43
    //   2426: aload #43
    //   2428: arraylength
    //   2429: iconst_1
    //   2430: isub
    //   2431: baload
    //   2432: istore #44
    //   2434: iload #44
    //   2436: bipush #16
    //   2438: if_icmple -> 2449
    //   2441: aload #43
    //   2443: astore #35
    //   2445: iload_2
    //   2446: ifne -> 2502
    //   2449: aload #43
    //   2451: arraylength
    //   2452: iload #44
    //   2454: isub
    //   2455: newarray byte
    //   2457: astore #35
    //   2459: iconst_0
    //   2460: istore #45
    //   2462: iload #45
    //   2464: aload #35
    //   2466: arraylength
    //   2467: if_icmpge -> 2502
    //   2470: iload #45
    //   2472: aload #43
    //   2474: arraylength
    //   2475: if_icmpge -> 2502
    //   2478: aload #35
    //   2480: iload #45
    //   2482: aload #43
    //   2484: iload #45
    //   2486: baload
    //   2487: bastore
    //   2488: iinc #45, 1
    //   2491: iload_2
    //   2492: ifne -> 2462
    //   2495: goto -> 2502
    //   2498: invokestatic a : (Ljava/lang/Throwable;)Ljava/lang/Throwable;
    //   2501: athrow
    //   2502: aload #35
    //   2504: astore #7
    //   2506: new java/math/BigInteger
    //   2509: dup
    //   2510: aload #7
    //   2512: invokespecial <init> : ([B)V
    //   2515: invokevirtual abs : ()Ljava/math/BigInteger;
    //   2518: putstatic burp/Zs26.Z_ : Ljava/lang/Object;
    //   2521: getstatic burp/Zg8.ZX : Ljava/lang/Object;
    //   2524: checkcast java/math/BigInteger
    //   2527: getstatic burp/Zry0.Zr : Ljava/lang/Object;
    //   2530: checkcast java/math/BigInteger
    //   2533: invokevirtual subtract : (Ljava/math/BigInteger;)Ljava/math/BigInteger;
    //   2536: putstatic burp/Zsin.Za : Ljava/lang/Object;
    //   2539: getstatic burp/Zkht.ZR : Ljava/lang/Object;
    //   2542: checkcast java/math/BigInteger
    //   2545: invokevirtual toByteArray : ()[B
    //   2548: astore_3
    //   2549: new java/lang/StringBuilder
    //   2552: dup
    //   2553: invokespecial <init> : ()V
    //   2556: astore #5
    //   2558: aload #5
    //   2560: sipush #11511
    //   2563: sipush #-30773
    //   2566: invokestatic a : (II)Ljava/lang/String;
    //   2569: invokevirtual append : (Ljava/lang/String;)Ljava/lang/StringBuilder;
    //   2572: pop
    //   2573: aload_3
    //   2574: astore #6
    //   2576: aload #6
    //   2578: arraylength
    //   2579: istore #7
    //   2581: iconst_0
    //   2582: istore #8
    //   2584: iload #8
    //   2586: iload #7
    //   2588: if_icmpge -> 2614
    //   2591: aload #6
    //   2593: iload #8
    //   2595: baload
    //   2596: istore #9
    //   2598: aload #5
    //   2600: iload #9
    //   2602: i2c
    //   2603: invokevirtual append : (C)Ljava/lang/StringBuilder;
    //   2606: pop
    //   2607: iinc #8, 1
    //   2610: iload_2
    //   2611: ifne -> 2584
    //   2614: aload #5
    //   2616: sipush #11495
    //   2619: sipush #26767
    //   2622: invokestatic a : (II)Ljava/lang/String;
    //   2625: ldc ''
    //   2627: invokestatic getProperty : (Ljava/lang/String;Ljava/lang/String;)Ljava/lang/String;
    //   2630: invokevirtual toLowerCase : ()Ljava/lang/String;
    //   2633: invokevirtual append : (Ljava/lang/String;)Ljava/lang/StringBuilder;
    //   2636: pop
    //   2637: aload #5
    //   2639: sipush #11500
    //   2642: sipush #12359
    //   2645: invokestatic a : (II)Ljava/lang/String;
    //   2648: ldc ''
    //   2650: invokestatic getProperty : (Ljava/lang/String;Ljava/lang/String;)Ljava/lang/String;
    //   2653: invokevirtual toLowerCase : ()Ljava/lang/String;
    //   2656: invokevirtual append : (Ljava/lang/String;)Ljava/lang/StringBuilder;
    //   2659: pop
    //   2660: aload #5
    //   2662: invokevirtual toString : ()Ljava/lang/String;
    //   2665: invokevirtual getBytes : ()[B
    //   2668: astore #4
    //   2670: aload #4
    //   2672: astore_3
    //   2673: aload_3
    //   2674: arraylength
    //   2675: bipush #8
    //   2677: iadd
    //   2678: bipush #6
    //   2680: ishr
    //   2681: iconst_1
    //   2682: iadd
    //   2683: bipush #16
    //   2685: imul
    //   2686: newarray int
    //   2688: astore #5
    //   2690: iconst_0
    //   2691: istore #6
    //   2693: iload #6
    //   2695: aload_3
    //   2696: arraylength
    //   2697: if_icmpge -> 2740
    //   2700: aload_3
    //   2701: iload #6
    //   2703: baload
    //   2704: sipush #255
    //   2707: iand
    //   2708: istore #7
    //   2710: aload #5
    //   2712: iload #6
    //   2714: iconst_2
    //   2715: ishr
    //   2716: dup2
    //   2717: iaload
    //   2718: iload #7
    //   2720: bipush #24
    //   2722: iload #6
    //   2724: iconst_4
    //   2725: irem
    //   2726: bipush #8
    //   2728: imul
    //   2729: isub
    //   2730: ishl
    //   2731: ior
    //   2732: iastore
    //   2733: iinc #6, 1
    //   2736: iload_2
    //   2737: ifne -> 2693
    //   2740: aload #5
    //   2742: iload #6
    //   2744: iconst_2
    //   2745: ishr
    //   2746: dup2
    //   2747: iaload
    //   2748: sipush #128
    //   2751: bipush #24
    //   2753: iload #6
    //   2755: iconst_4
    //   2756: irem
    //   2757: bipush #8
    //   2759: imul
    //   2760: isub
    //   2761: ishl
    //   2762: ior
    //   2763: iastore
    //   2764: aload #5
    //   2766: aload #5
    //   2768: arraylength
    //   2769: iconst_1
    //   2770: isub
    //   2771: aload_3
    //   2772: arraylength
    //   2773: bipush #8
    //   2775: imul
    //   2776: iastore
    //   2777: bipush #80
    //   2779: newarray int
    //   2781: astore #7
    //   2783: ldc 1732584193
    //   2785: istore #8
    //   2787: ldc -271733879
    //   2789: istore #9
    //   2791: ldc -1732584194
    //   2793: istore #10
    //   2795: ldc 271733878
    //   2797: istore #11
    //   2799: ldc -1009589776
    //   2801: istore #12
    //   2803: iconst_0
    //   2804: istore #6
    //   2806: iload #6
    //   2808: aload #5
    //   2810: arraylength
    //   2811: if_icmpge -> 3133
    //   2814: iload #8
    //   2816: istore #13
    //   2818: iload #9
    //   2820: istore #14
    //   2822: iload #10
    //   2824: istore #15
    //   2826: iload #11
    //   2828: istore #16
    //   2830: iload #12
    //   2832: istore #17
    //   2834: iconst_0
    //   2835: istore #18
    //   2837: iload #18
    //   2839: bipush #80
    //   2841: if_icmpge -> 3091
    //   2844: iload #18
    //   2846: bipush #16
    //   2848: if_icmpge -> 2875
    //   2851: aload #7
    //   2853: iload #18
    //   2855: aload #5
    //   2857: iload #6
    //   2859: iload #18
    //   2861: iadd
    //   2862: iaload
    //   2863: iastore
    //   2864: iload_2
    //   2865: ifne -> 2930
    //   2868: goto -> 2875
    //   2871: invokestatic a : (Ljava/lang/Throwable;)Ljava/lang/Throwable;
    //   2874: athrow
    //   2875: aload #7
    //   2877: iload #18
    //   2879: iconst_3
    //   2880: isub
    //   2881: iaload
    //   2882: aload #7
    //   2884: iload #18
    //   2886: bipush #8
    //   2888: isub
    //   2889: iaload
    //   2890: ixor
    //   2891: aload #7
    //   2893: iload #18
    //   2895: bipush #14
    //   2897: isub
    //   2898: iaload
    //   2899: ixor
    //   2900: aload #7
    //   2902: iload #18
    //   2904: bipush #16
    //   2906: isub
    //   2907: iaload
    //   2908: ixor
    //   2909: istore #19
    //   2911: iload #19
    //   2913: iconst_1
    //   2914: ishl
    //   2915: iload #19
    //   2917: bipush #31
    //   2919: iushr
    //   2920: ior
    //   2921: istore #20
    //   2923: aload #7
    //   2925: iload #18
    //   2927: iload #20
    //   2929: iastore
    //   2930: iload #8
    //   2932: iconst_5
    //   2933: ishl
    //   2934: iload #8
    //   2936: bipush #27
    //   2938: iushr
    //   2939: ior
    //   2940: istore #19
    //   2942: iload #19
    //   2944: iload #12
    //   2946: iadd
    //   2947: aload #7
    //   2949: iload #18
    //   2951: iaload
    //   2952: iadd
    //   2953: iload #18
    //   2955: bipush #20
    //   2957: if_icmpge -> 2983
    //   2960: ldc 1518500249
    //   2962: iload #9
    //   2964: iload #10
    //   2966: iand
    //   2967: iload #9
    //   2969: iconst_m1
    //   2970: ixor
    //   2971: iload #11
    //   2973: iand
    //   2974: ior
    //   2975: iadd
    //   2976: goto -> 3053
    //   2979: invokestatic a : (Ljava/lang/Throwable;)Ljava/lang/Throwable;
    //   2982: athrow
    //   2983: iload #18
    //   2985: bipush #40
    //   2987: if_icmpge -> 3008
    //   2990: ldc 1859775393
    //   2992: iload #9
    //   2994: iload #10
    //   2996: ixor
    //   2997: iload #11
    //   2999: ixor
    //   3000: iadd
    //   3001: goto -> 3053
    //   3004: invokestatic a : (Ljava/lang/Throwable;)Ljava/lang/Throwable;
    //   3007: athrow
    //   3008: iload #18
    //   3010: bipush #60
    //   3012: if_icmpge -> 3042
    //   3015: ldc -1894007588
    //   3017: iload #9
    //   3019: iload #10
    //   3021: iand
    //   3022: iload #9
    //   3024: iload #11
    //   3026: iand
    //   3027: ior
    //   3028: iload #10
    //   3030: iload #11
    //   3032: iand
    //   3033: ior
    //   3034: iadd
    //   3035: goto -> 3053
    //   3038: invokestatic a : (Ljava/lang/Throwable;)Ljava/lang/Throwable;
    //   3041: athrow
    //   3042: ldc -899497514
    //   3044: iload #9
    //   3046: iload #10
    //   3048: ixor
    //   3049: iload #11
    //   3051: ixor
    //   3052: iadd
    //   3053: iadd
    //   3054: istore #20
    //   3056: iload #11
    //   3058: istore #12
    //   3060: iload #10
    //   3062: istore #11
    //   3064: iload #9
    //   3066: bipush #30
    //   3068: ishl
    //   3069: iload #9
    //   3071: iconst_2
    //   3072: iushr
    //   3073: ior
    //   3074: istore #10
    //   3076: iload #8
    //   3078: istore #9
    //   3080: iload #20
    //   3082: istore #8
    //   3084: iinc #18, 1
    //   3087: iload_2
    //   3088: ifne -> 2837
    //   3091: iload #8
    //   3093: iload #13
    //   3095: iadd
    //   3096: istore #8
    //   3098: iload #9
    //   3100: iload #14
    //   3102: iadd
    //   3103: istore #9
    //   3105: iload #10
    //   3107: iload #15
    //   3109: iadd
    //   3110: istore #10
    //   3112: iload #11
    //   3114: iload #16
    //   3116: iadd
    //   3117: istore #11
    //   3119: iload #12
    //   3121: iload #17
    //   3123: iadd
    //   3124: istore #12
    //   3126: iinc #6, 16
    //   3129: iload_2
    //   3130: ifne -> 2806
    //   3133: iconst_5
    //   3134: newarray int
    //   3136: dup
    //   3137: iconst_0
    //   3138: iload #8
    //   3140: iastore
    //   3141: dup
    //   3142: iconst_1
    //   3143: iload #9
    //   3145: iastore
    //   3146: dup
    //   3147: iconst_2
    //   3148: iload #10
    //   3150: iastore
    //   3151: dup
    //   3152: iconst_3
    //   3153: iload #11
    //   3155: iastore
    //   3156: dup
    //   3157: iconst_4
    //   3158: iload #12
    //   3160: iastore
    //   3161: astore #13
    //   3163: bipush #20
    //   3165: newarray byte
    //   3167: astore #14
    //   3169: iconst_0
    //   3170: istore #15
    //   3172: iload #15
    //   3174: bipush #20
    //   3176: if_icmpge -> 3217
    //   3179: aload #13
    //   3181: iload #15
    //   3183: iconst_4
    //   3184: idiv
    //   3185: iaload
    //   3186: istore #16
    //   3188: iconst_3
    //   3189: iload #15
    //   3191: iconst_4
    //   3192: irem
    //   3193: isub
    //   3194: bipush #8
    //   3196: imul
    //   3197: istore #17
    //   3199: aload #14
    //   3201: iload #15
    //   3203: iload #16
    //   3205: iload #17
    //   3207: iushr
    //   3208: i2b
    //   3209: bastore
    //   3210: iinc #15, 1
    //   3213: iload_2
    //   3214: ifne -> 3172
    //   3217: aload #14
    //   3219: astore #4
    //   3221: sipush #11510
    //   3224: sipush #25897
    //   3227: invokestatic a : (II)Ljava/lang/String;
    //   3230: iconst_1
    //   3231: ldc burp/Zmuj
    //   3233: invokevirtual getClassLoader : ()Ljava/lang/ClassLoader;
    //   3236: invokestatic forName : (Ljava/lang/String;ZLjava/lang/ClassLoader;)Ljava/lang/Class;
    //   3239: invokevirtual getDeclaredFields : ()[Ljava/lang/reflect/Field;
    //   3242: astore_3
    //   3243: aload_3
    //   3244: arraylength
    //   3245: istore #4
    //   3247: iconst_0
    //   3248: istore #5
    //   3250: iload #5
    //   3252: iload #4
    //   3254: if_icmpge -> 3391
    //   3257: aload_3
    //   3258: iload #5
    //   3260: aaload
    //   3261: astore #6
    //   3263: aload #6
    //   3265: invokevirtual getModifiers : ()I
    //   3268: invokestatic isStatic : (I)Z
    //   3271: ifne -> 3281
    //   3274: goto -> 3384
    //   3277: invokestatic a : (Ljava/lang/Throwable;)Ljava/lang/Throwable;
    //   3280: athrow
    //   3281: aload #6
    //   3283: invokevirtual getType : ()Ljava/lang/Class;
    //   3286: astore #7
    //   3288: aload #7
    //   3290: ifnull -> 3371
    //   3293: aload #7
    //   3295: invokevirtual isPrimitive : ()Z
    //   3298: ifne -> 3371
    //   3301: goto -> 3308
    //   3304: invokestatic a : (Ljava/lang/Throwable;)Ljava/lang/Throwable;
    //   3307: athrow
    //   3308: aload #7
    //   3310: invokevirtual getPackage : ()Ljava/lang/Package;
    //   3313: ifnull -> 3371
    //   3316: goto -> 3323
    //   3319: invokestatic a : (Ljava/lang/Throwable;)Ljava/lang/Throwable;
    //   3322: athrow
    //   3323: aload #7
    //   3325: invokevirtual getPackage : ()Ljava/lang/Package;
    //   3328: invokevirtual getName : ()Ljava/lang/String;
    //   3331: ifnull -> 3371
    //   3334: goto -> 3341
    //   3337: invokestatic a : (Ljava/lang/Throwable;)Ljava/lang/Throwable;
    //   3340: athrow
    //   3341: aload #7
    //   3343: invokevirtual getPackage : ()Ljava/lang/Package;
    //   3346: invokevirtual getName : ()Ljava/lang/String;
    //   3349: sipush #11505
    //   3352: sipush #11341
    //   3355: invokestatic a : (II)Ljava/lang/String;
    //   3358: invokevirtual startsWith : (Ljava/lang/String;)Z
    //   3361: ifne -> 3371
    //   3364: goto -> 3371
    //   3367: invokestatic a : (Ljava/lang/Throwable;)Ljava/lang/Throwable;
    //   3370: athrow
    //   3371: aload #6
    //   3373: iconst_1
    //   3374: invokevirtual setAccessible : (Z)V
    //   3377: aload #6
    //   3379: aconst_null
    //   3380: invokevirtual get : (Ljava/lang/Object;)Ljava/lang/Object;
    //   3383: pop
    //   3384: iinc #5, 1
    //   3387: iload_2
    //   3388: ifne -> 3250
    //   3391: sipush #11498
    //   3394: sipush #-5909
    //   3397: invokestatic a : (II)Ljava/lang/String;
    //   3400: invokestatic forName : (Ljava/lang/String;)Ljava/lang/Class;
    //   3403: invokevirtual getDeclaredMethods : ()[Ljava/lang/reflect/Method;
    //   3406: astore_3
    //   3407: aload_3
    //   3408: arraylength
    //   3409: istore #4
    //   3411: iconst_0
    //   3412: istore #5
    //   3414: iload #5
    //   3416: iload #4
    //   3418: if_icmpge -> 3529
    //   3421: aload_3
    //   3422: iload #5
    //   3424: aaload
    //   3425: astore #6
    //   3427: aload #6
    //   3429: invokevirtual getParameterTypes : ()[Ljava/lang/Class;
    //   3432: pop
    //   3433: aload #6
    //   3435: invokevirtual getModifiers : ()I
    //   3438: invokestatic isStatic : (I)Z
    //   3441: ifeq -> 3515
    //   3444: aload #6
    //   3446: invokevirtual getParameterTypes : ()[Ljava/lang/Class;
    //   3449: arraylength
    //   3450: iconst_2
    //   3451: if_icmpne -> 3515
    //   3454: goto -> 3461
    //   3457: invokestatic a : (Ljava/lang/Throwable;)Ljava/lang/Throwable;
    //   3460: athrow
    //   3461: aload #6
    //   3463: invokevirtual getReturnType : ()Ljava/lang/Class;
    //   3466: getstatic java/lang/Boolean.TYPE : Ljava/lang/Class;
    //   3469: if_acmpne -> 3515
    //   3472: goto -> 3479
    //   3475: invokestatic a : (Ljava/lang/Throwable;)Ljava/lang/Throwable;
    //   3478: athrow
    //   3479: aload #6
    //   3481: iconst_1
    //   3482: invokevirtual setAccessible : (Z)V
    //   3485: aload #6
    //   3487: aconst_null
    //   3488: iconst_2
    //   3489: anewarray java/lang/Object
    //   3492: dup
    //   3493: iconst_0
    //   3494: aload_0
    //   3495: aastore
    //   3496: dup
    //   3497: iconst_1
    //   3498: aload_1
    //   3499: aastore
    //   3500: invokevirtual invoke : (Ljava/lang/Object;[Ljava/lang/Object;)Ljava/lang/Object;
    //   3503: pop
    //   3504: iload_2
    //   3505: ifne -> 3529
    //   3508: goto -> 3515
    //   3511: invokestatic a : (Ljava/lang/Throwable;)Ljava/lang/Throwable;
    //   3514: athrow
    //   3515: iinc #5, 1
    //   3518: iload_2
    //   3519: ifne -> 3414
    //   3522: goto -> 3529
    //   3525: invokestatic a : (Ljava/lang/Throwable;)Ljava/lang/Throwable;
    //   3528: athrow
    //   3529: sipush #11488
    //   3532: sipush #-3258
    //   3535: invokestatic a : (II)Ljava/lang/String;
    //   3538: iconst_1
    //   3539: ldc burp/Zr14
    //   3541: invokevirtual getClassLoader : ()Ljava/lang/ClassLoader;
    //   3544: invokestatic forName : (Ljava/lang/String;ZLjava/lang/ClassLoader;)Ljava/lang/Class;
    //   3547: invokevirtual getDeclaredFields : ()[Ljava/lang/reflect/Field;
    //   3550: astore_3
    //   3551: aload_3
    //   3552: arraylength
    //   3553: istore #4
    //   3555: iconst_0
    //   3556: istore #5
    //   3558: iload #5
    //   3560: iload #4
    //   3562: if_icmpge -> 3699
    //   3565: aload_3
    //   3566: iload #5
    //   3568: aaload
    //   3569: astore #6
    //   3571: aload #6
    //   3573: invokevirtual getModifiers : ()I
    //   3576: invokestatic isStatic : (I)Z
    //   3579: ifne -> 3589
    //   3582: goto -> 3692
    //   3585: invokestatic a : (Ljava/lang/Throwable;)Ljava/lang/Throwable;
    //   3588: athrow
    //   3589: aload #6
    //   3591: invokevirtual getType : ()Ljava/lang/Class;
    //   3594: astore #7
    //   3596: aload #7
    //   3598: ifnull -> 3679
    //   3601: aload #7
    //   3603: invokevirtual isPrimitive : ()Z
    //   3606: ifne -> 3679
    //   3609: goto -> 3616
    //   3612: invokestatic a : (Ljava/lang/Throwable;)Ljava/lang/Throwable;
    //   3615: athrow
    //   3616: aload #7
    //   3618: invokevirtual getPackage : ()Ljava/lang/Package;
    //   3621: ifnull -> 3679
    //   3624: goto -> 3631
    //   3627: invokestatic a : (Ljava/lang/Throwable;)Ljava/lang/Throwable;
    //   3630: athrow
    //   3631: aload #7
    //   3633: invokevirtual getPackage : ()Ljava/lang/Package;
    //   3636: invokevirtual getName : ()Ljava/lang/String;
    //   3639: ifnull -> 3679
    //   3642: goto -> 3649
    //   3645: invokestatic a : (Ljava/lang/Throwable;)Ljava/lang/Throwable;
    //   3648: athrow
    //   3649: aload #7
    //   3651: invokevirtual getPackage : ()Ljava/lang/Package;
    //   3654: invokevirtual getName : ()Ljava/lang/String;
    //   3657: sipush #11509
    //   3660: sipush #8697
    //   3663: invokestatic a : (II)Ljava/lang/String;
    //   3666: invokevirtual startsWith : (Ljava/lang/String;)Z
    //   3669: ifne -> 3679
    //   3672: goto -> 3679
    //   3675: invokestatic a : (Ljava/lang/Throwable;)Ljava/lang/Throwable;
    //   3678: athrow
    //   3679: aload #6
    //   3681: iconst_1
    //   3682: invokevirtual setAccessible : (Z)V
    //   3685: aload #6
    //   3687: aconst_null
    //   3688: invokevirtual get : (Ljava/lang/Object;)Ljava/lang/Object;
    //   3691: pop
    //   3692: iinc #5, 1
    //   3695: iload_2
    //   3696: ifne -> 3558
    //   3699: sipush #11493
    //   3702: sipush #-21553
    //   3705: invokestatic a : (II)Ljava/lang/String;
    //   3708: invokestatic forName : (Ljava/lang/String;)Ljava/lang/Class;
    //   3711: invokevirtual getDeclaredMethods : ()[Ljava/lang/reflect/Method;
    //   3714: astore_3
    //   3715: aload_3
    //   3716: arraylength
    //   3717: istore #4
    //   3719: iconst_0
    //   3720: istore #5
    //   3722: iload #5
    //   3724: iload #4
    //   3726: if_icmpge -> 3858
    //   3729: aload_3
    //   3730: iload #5
    //   3732: aaload
    //   3733: astore #6
    //   3735: aload #6
    //   3737: invokevirtual getParameterTypes : ()[Ljava/lang/Class;
    //   3740: pop
    //   3741: aload #6
    //   3743: invokevirtual getModifiers : ()I
    //   3746: invokestatic isStatic : (I)Z
    //   3749: ifeq -> 3844
    //   3752: aload #6
    //   3754: invokevirtual getParameterTypes : ()[Ljava/lang/Class;
    //   3757: arraylength
    //   3758: iconst_2
    //   3759: if_icmpne -> 3844
    //   3762: goto -> 3769
    //   3765: invokestatic a : (Ljava/lang/Throwable;)Ljava/lang/Throwable;
    //   3768: athrow
    //   3769: aload #6
    //   3771: invokevirtual getReturnType : ()Ljava/lang/Class;
    //   3774: getstatic java/lang/Void.TYPE : Ljava/lang/Class;
    //   3777: invokevirtual equals : (Ljava/lang/Object;)Z
    //   3780: ifeq -> 3844
    //   3783: goto -> 3790
    //   3786: invokestatic a : (Ljava/lang/Throwable;)Ljava/lang/Throwable;
    //   3789: athrow
    //   3790: aload #6
    //   3792: iconst_1
    //   3793: invokevirtual setAccessible : (Z)V
    //   3796: aload #6
    //   3798: aconst_null
    //   3799: iconst_2
    //   3800: anewarray java/lang/Object
    //   3803: dup
    //   3804: iconst_0
    //   3805: aload_0
    //   3806: aastore
    //   3807: dup
    //   3808: iconst_1
    //   3809: aload_1
    //   3810: ifnonnull -> 3828
    //   3813: goto -> 3820
    //   3816: invokestatic a : (Ljava/lang/Throwable;)Ljava/lang/Throwable;
    //   3819: athrow
    //   3820: aload_1
    //   3821: goto -> 3835
    //   3824: invokestatic a : (Ljava/lang/Throwable;)Ljava/lang/Throwable;
    //   3827: athrow
    //   3828: aload_1
    //   3829: checkcast [B
    //   3832: invokevirtual clone : ()Ljava/lang/Object;
    //   3835: aastore
    //   3836: invokevirtual invoke : (Ljava/lang/Object;[Ljava/lang/Object;)Ljava/lang/Object;
    //   3839: pop
    //   3840: iload_2
    //   3841: ifne -> 3858
    //   3844: iinc #5, 1
    //   3847: iload_2
    //   3848: ifne -> 3722
    //   3851: goto -> 3858
    //   3854: invokestatic a : (Ljava/lang/Throwable;)Ljava/lang/Throwable;
    //   3857: athrow
    //   3858: iconst_0
    //   3859: istore_3
    //   3860: getstatic burp/Zkk2.ZI : Ljava/lang/String;
    //   3863: getstatic burp/Zlp8.Zu : Ljava/lang/Object;
    //   3866: checkcast java/math/BigInteger
    //   3869: invokevirtual intValue : ()I
    //   3872: bipush #32
    //   3874: irem
    //   3875: invokestatic abs : (I)I
    //   3878: invokevirtual charAt : (I)C
    //   3881: getstatic burp/Zlkm.ZH : Ljava/lang/String;
    //   3884: getstatic burp/Zzh1.Zf : Ljava/lang/Object;
    //   3887: checkcast java/math/BigInteger
    //   3890: invokevirtual intValue : ()I
    //   3893: bipush #32
    //   3895: irem
    //   3896: invokestatic abs : (I)I
    //   3899: invokevirtual charAt : (I)C
    //   3902: if_icmpgt -> 4246
    //   3905: sipush #11491
    //   3908: sipush #-12979
    //   3911: invokestatic a : (II)Ljava/lang/String;
    //   3914: iconst_1
    //   3915: ldc burp/Zb2s
    //   3917: invokevirtual getClassLoader : ()Ljava/lang/ClassLoader;
    //   3920: invokestatic forName : (Ljava/lang/String;ZLjava/lang/ClassLoader;)Ljava/lang/Class;
    //   3923: invokevirtual getDeclaredFields : ()[Ljava/lang/reflect/Field;
    //   3926: astore #4
    //   3928: aload #4
    //   3930: arraylength
    //   3931: istore #5
    //   3933: iconst_0
    //   3934: istore #6
    //   3936: iload #6
    //   3938: iload #5
    //   3940: if_icmpge -> 4078
    //   3943: aload #4
    //   3945: iload #6
    //   3947: aaload
    //   3948: astore #7
    //   3950: aload #7
    //   3952: invokevirtual getModifiers : ()I
    //   3955: invokestatic isStatic : (I)Z
    //   3958: ifne -> 3968
    //   3961: goto -> 4071
    //   3964: invokestatic a : (Ljava/lang/Throwable;)Ljava/lang/Throwable;
    //   3967: athrow
    //   3968: aload #7
    //   3970: invokevirtual getType : ()Ljava/lang/Class;
    //   3973: astore #8
    //   3975: aload #8
    //   3977: ifnull -> 4058
    //   3980: aload #8
    //   3982: invokevirtual isPrimitive : ()Z
    //   3985: ifne -> 4058
    //   3988: goto -> 3995
    //   3991: invokestatic a : (Ljava/lang/Throwable;)Ljava/lang/Throwable;
    //   3994: athrow
    //   3995: aload #8
    //   3997: invokevirtual getPackage : ()Ljava/lang/Package;
    //   4000: ifnull -> 4058
    //   4003: goto -> 4010
    //   4006: invokestatic a : (Ljava/lang/Throwable;)Ljava/lang/Throwable;
    //   4009: athrow
    //   4010: aload #8
    //   4012: invokevirtual getPackage : ()Ljava/lang/Package;
    //   4015: invokevirtual getName : ()Ljava/lang/String;
    //   4018: ifnull -> 4058
    //   4021: goto -> 4028
    //   4024: invokestatic a : (Ljava/lang/Throwable;)Ljava/lang/Throwable;
    //   4027: athrow
    //   4028: aload #8
    //   4030: invokevirtual getPackage : ()Ljava/lang/Package;
    //   4033: invokevirtual getName : ()Ljava/lang/String;
    //   4036: sipush #11509
    //   4039: sipush #8697
    //   4042: invokestatic a : (II)Ljava/lang/String;
    //   4045: invokevirtual startsWith : (Ljava/lang/String;)Z
    //   4048: ifne -> 4058
    //   4051: goto -> 4058
    //   4054: invokestatic a : (Ljava/lang/Throwable;)Ljava/lang/Throwable;
    //   4057: athrow
    //   4058: aload #7
    //   4060: iconst_1
    //   4061: invokevirtual setAccessible : (Z)V
    //   4064: aload #7
    //   4066: aconst_null
    //   4067: invokevirtual get : (Ljava/lang/Object;)Ljava/lang/Object;
    //   4070: pop
    //   4071: iinc #6, 1
    //   4074: iload_2
    //   4075: ifne -> 3936
    //   4078: sipush #11506
    //   4081: sipush #19154
    //   4084: invokestatic a : (II)Ljava/lang/String;
    //   4087: invokestatic forName : (Ljava/lang/String;)Ljava/lang/Class;
    //   4090: invokevirtual getDeclaredMethods : ()[Ljava/lang/reflect/Method;
    //   4093: astore #4
    //   4095: aload #4
    //   4097: arraylength
    //   4098: istore #5
    //   4100: iconst_0
    //   4101: istore #6
    //   4103: iload #6
    //   4105: iload #5
    //   4107: if_icmpge -> 4243
    //   4110: aload #4
    //   4112: iload #6
    //   4114: aaload
    //   4115: astore #7
    //   4117: aload #7
    //   4119: invokevirtual getParameterTypes : ()[Ljava/lang/Class;
    //   4122: pop
    //   4123: aload #7
    //   4125: invokevirtual getModifiers : ()I
    //   4128: invokestatic isStatic : (I)Z
    //   4131: ifeq -> 4229
    //   4134: aload #7
    //   4136: invokevirtual getParameterTypes : ()[Ljava/lang/Class;
    //   4139: arraylength
    //   4140: iconst_2
    //   4141: if_icmpne -> 4229
    //   4144: goto -> 4151
    //   4147: invokestatic a : (Ljava/lang/Throwable;)Ljava/lang/Throwable;
    //   4150: athrow
    //   4151: aload #7
    //   4153: invokevirtual getReturnType : ()Ljava/lang/Class;
    //   4156: getstatic java/lang/Boolean.TYPE : Ljava/lang/Class;
    //   4159: if_acmpne -> 4229
    //   4162: goto -> 4169
    //   4165: invokestatic a : (Ljava/lang/Throwable;)Ljava/lang/Throwable;
    //   4168: athrow
    //   4169: aload #7
    //   4171: iconst_1
    //   4172: invokevirtual setAccessible : (Z)V
    //   4175: aload #7
    //   4177: aconst_null
    //   4178: iconst_2
    //   4179: anewarray java/lang/Object
    //   4182: dup
    //   4183: iconst_0
    //   4184: aload_0
    //   4185: aastore
    //   4186: dup
    //   4187: iconst_1
    //   4188: aload_1
    //   4189: ifnonnull -> 4207
    //   4192: goto -> 4199
    //   4195: invokestatic a : (Ljava/lang/Throwable;)Ljava/lang/Throwable;
    //   4198: athrow
    //   4199: aload_1
    //   4200: goto -> 4214
    //   4203: invokestatic a : (Ljava/lang/Throwable;)Ljava/lang/Throwable;
    //   4206: athrow
    //   4207: aload_1
    //   4208: checkcast [B
    //   4211: invokevirtual clone : ()Ljava/lang/Object;
    //   4214: aastore
    //   4215: invokevirtual invoke : (Ljava/lang/Object;[Ljava/lang/Object;)Ljava/lang/Object;
    //   4218: checkcast java/lang/Boolean
    //   4221: invokevirtual booleanValue : ()Z
    //   4224: istore_3
    //   4225: iload_2
    //   4226: ifne -> 4243
    //   4229: iinc #6, 1
    //   4232: iload_2
    //   4233: ifne -> 4103
    //   4236: goto -> 4243
    //   4239: invokestatic a : (Ljava/lang/Throwable;)Ljava/lang/Throwable;
    //   4242: athrow
    //   4243: goto -> 4584
    //   4246: sipush #11477
    //   4249: sipush #-1937
    //   4252: invokestatic a : (II)Ljava/lang/String;
    //   4255: iconst_1
    //   4256: ldc burp/Zmjw
    //   4258: invokevirtual getClassLoader : ()Ljava/lang/ClassLoader;
    //   4261: invokestatic forName : (Ljava/lang/String;ZLjava/lang/ClassLoader;)Ljava/lang/Class;
    //   4264: invokevirtual getDeclaredFields : ()[Ljava/lang/reflect/Field;
    //   4267: astore #4
    //   4269: aload #4
    //   4271: arraylength
    //   4272: istore #5
    //   4274: iconst_0
    //   4275: istore #6
    //   4277: iload #6
    //   4279: iload #5
    //   4281: if_icmpge -> 4419
    //   4284: aload #4
    //   4286: iload #6
    //   4288: aaload
    //   4289: astore #7
    //   4291: aload #7
    //   4293: invokevirtual getModifiers : ()I
    //   4296: invokestatic isStatic : (I)Z
    //   4299: ifne -> 4309
    //   4302: goto -> 4412
    //   4305: invokestatic a : (Ljava/lang/Throwable;)Ljava/lang/Throwable;
    //   4308: athrow
    //   4309: aload #7
    //   4311: invokevirtual getType : ()Ljava/lang/Class;
    //   4314: astore #8
    //   4316: aload #8
    //   4318: ifnull -> 4399
    //   4321: aload #8
    //   4323: invokevirtual isPrimitive : ()Z
    //   4326: ifne -> 4399
    //   4329: goto -> 4336
    //   4332: invokestatic a : (Ljava/lang/Throwable;)Ljava/lang/Throwable;
    //   4335: athrow
    //   4336: aload #8
    //   4338: invokevirtual getPackage : ()Ljava/lang/Package;
    //   4341: ifnull -> 4399
    //   4344: goto -> 4351
    //   4347: invokestatic a : (Ljava/lang/Throwable;)Ljava/lang/Throwable;
    //   4350: athrow
    //   4351: aload #8
    //   4353: invokevirtual getPackage : ()Ljava/lang/Package;
    //   4356: invokevirtual getName : ()Ljava/lang/String;
    //   4359: ifnull -> 4399
    //   4362: goto -> 4369
    //   4365: invokestatic a : (Ljava/lang/Throwable;)Ljava/lang/Throwable;
    //   4368: athrow
    //   4369: aload #8
    //   4371: invokevirtual getPackage : ()Ljava/lang/Package;
    //   4374: invokevirtual getName : ()Ljava/lang/String;
    //   4377: sipush #11509
    //   4380: sipush #8697
    //   4383: invokestatic a : (II)Ljava/lang/String;
    //   4386: invokevirtual startsWith : (Ljava/lang/String;)Z
    //   4389: ifne -> 4399
    //   4392: goto -> 4399
    //   4395: invokestatic a : (Ljava/lang/Throwable;)Ljava/lang/Throwable;
    //   4398: athrow
    //   4399: aload #7
    //   4401: iconst_1
    //   4402: invokevirtual setAccessible : (Z)V
    //   4405: aload #7
    //   4407: aconst_null
    //   4408: invokevirtual get : (Ljava/lang/Object;)Ljava/lang/Object;
    //   4411: pop
    //   4412: iinc #6, 1
    //   4415: iload_2
    //   4416: ifne -> 4277
    //   4419: sipush #11513
    //   4422: sipush #-4472
    //   4425: invokestatic a : (II)Ljava/lang/String;
    //   4428: invokestatic forName : (Ljava/lang/String;)Ljava/lang/Class;
    //   4431: invokevirtual getDeclaredMethods : ()[Ljava/lang/reflect/Method;
    //   4434: astore #4
    //   4436: aload #4
    //   4438: arraylength
    //   4439: istore #5
    //   4441: iconst_0
    //   4442: istore #6
    //   4444: iload #6
    //   4446: iload #5
    //   4448: if_icmpge -> 4584
    //   4451: aload #4
    //   4453: iload #6
    //   4455: aaload
    //   4456: astore #7
    //   4458: aload #7
    //   4460: invokevirtual getParameterTypes : ()[Ljava/lang/Class;
    //   4463: pop
    //   4464: aload #7
    //   4466: invokevirtual getModifiers : ()I
    //   4469: invokestatic isStatic : (I)Z
    //   4472: ifeq -> 4570
    //   4475: aload #7
    //   4477: invokevirtual getParameterTypes : ()[Ljava/lang/Class;
    //   4480: arraylength
    //   4481: iconst_2
    //   4482: if_icmpne -> 4570
    //   4485: goto -> 4492
    //   4488: invokestatic a : (Ljava/lang/Throwable;)Ljava/lang/Throwable;
    //   4491: athrow
    //   4492: aload #7
    //   4494: invokevirtual getReturnType : ()Ljava/lang/Class;
    //   4497: getstatic java/lang/Boolean.TYPE : Ljava/lang/Class;
    //   4500: if_acmpne -> 4570
    //   4503: goto -> 4510
    //   4506: invokestatic a : (Ljava/lang/Throwable;)Ljava/lang/Throwable;
    //   4509: athrow
    //   4510: aload #7
    //   4512: iconst_1
    //   4513: invokevirtual setAccessible : (Z)V
    //   4516: aload #7
    //   4518: aconst_null
    //   4519: iconst_2
    //   4520: anewarray java/lang/Object
    //   4523: dup
    //   4524: iconst_0
    //   4525: aload_0
    //   4526: aastore
    //   4527: dup
    //   4528: iconst_1
    //   4529: aload_1
    //   4530: ifnonnull -> 4548
    //   4533: goto -> 4540
    //   4536: invokestatic a : (Ljava/lang/Throwable;)Ljava/lang/Throwable;
    //   4539: athrow
    //   4540: aload_1
    //   4541: goto -> 4555
    //   4544: invokestatic a : (Ljava/lang/Throwable;)Ljava/lang/Throwable;
    //   4547: athrow
    //   4548: aload_1
    //   4549: checkcast [B
    //   4552: invokevirtual clone : ()Ljava/lang/Object;
    //   4555: aastore
    //   4556: invokevirtual invoke : (Ljava/lang/Object;[Ljava/lang/Object;)Ljava/lang/Object;
    //   4559: checkcast java/lang/Boolean
    //   4562: invokevirtual booleanValue : ()Z
    //   4565: istore_3
    //   4566: iload_2
    //   4567: ifne -> 4584
    //   4570: iinc #6, 1
    //   4573: iload_2
    //   4574: ifne -> 4444
    //   4577: goto -> 4584
    //   4580: invokestatic a : (Ljava/lang/Throwable;)Ljava/lang/Throwable;
    //   4583: athrow
    //   4584: iload_3
    //   4585: ifeq -> 4590
    //   4588: iload_3
    //   4589: ireturn
    //   4590: getstatic burp/Ztzh.ZE : Ljava/lang/String;
    //   4593: getstatic burp/Zg68.Zs : Ljava/lang/Object;
    //   4596: checkcast java/math/BigInteger
    //   4599: invokevirtual intValue : ()I
    //   4602: bipush #32
    //   4604: irem
    //   4605: invokestatic abs : (I)I
    //   4608: invokevirtual charAt : (I)C
    //   4611: getstatic burp/Zlo4.Zn : Ljava/lang/String;
    //   4614: getstatic burp/Zgjj.ZW : Ljava/lang/Object;
    //   4617: checkcast java/math/BigInteger
    //   4620: invokevirtual intValue : ()I
    //   4623: bipush #32
    //   4625: irem
    //   4626: invokestatic abs : (I)I
    //   4629: invokevirtual charAt : (I)C
    //   4632: if_icmple -> 4977
    //   4635: sipush #11517
    //   4638: sipush #-7656
    //   4641: invokestatic a : (II)Ljava/lang/String;
    //   4644: iconst_1
    //   4645: ldc burp/Zrc0
    //   4647: invokevirtual getClassLoader : ()Ljava/lang/ClassLoader;
    //   4650: invokestatic forName : (Ljava/lang/String;ZLjava/lang/ClassLoader;)Ljava/lang/Class;
    //   4653: invokevirtual getDeclaredFields : ()[Ljava/lang/reflect/Field;
    //   4656: astore #4
    //   4658: aload #4
    //   4660: arraylength
    //   4661: istore #5
    //   4663: iconst_0
    //   4664: istore #6
    //   4666: iload #6
    //   4668: iload #5
    //   4670: if_icmpge -> 4808
    //   4673: aload #4
    //   4675: iload #6
    //   4677: aaload
    //   4678: astore #7
    //   4680: aload #7
    //   4682: invokevirtual getModifiers : ()I
    //   4685: invokestatic isStatic : (I)Z
    //   4688: ifne -> 4698
    //   4691: goto -> 4801
    //   4694: invokestatic a : (Ljava/lang/Throwable;)Ljava/lang/Throwable;
    //   4697: athrow
    //   4698: aload #7
    //   4700: invokevirtual getType : ()Ljava/lang/Class;
    //   4703: astore #8
    //   4705: aload #8
    //   4707: ifnull -> 4788
    //   4710: aload #8
    //   4712: invokevirtual isPrimitive : ()Z
    //   4715: ifne -> 4788
    //   4718: goto -> 4725
    //   4721: invokestatic a : (Ljava/lang/Throwable;)Ljava/lang/Throwable;
    //   4724: athrow
    //   4725: aload #8
    //   4727: invokevirtual getPackage : ()Ljava/lang/Package;
    //   4730: ifnull -> 4788
    //   4733: goto -> 4740
    //   4736: invokestatic a : (Ljava/lang/Throwable;)Ljava/lang/Throwable;
    //   4739: athrow
    //   4740: aload #8
    //   4742: invokevirtual getPackage : ()Ljava/lang/Package;
    //   4745: invokevirtual getName : ()Ljava/lang/String;
    //   4748: ifnull -> 4788
    //   4751: goto -> 4758
    //   4754: invokestatic a : (Ljava/lang/Throwable;)Ljava/lang/Throwable;
    //   4757: athrow
    //   4758: aload #8
    //   4760: invokevirtual getPackage : ()Ljava/lang/Package;
    //   4763: invokevirtual getName : ()Ljava/lang/String;
    //   4766: sipush #11509
    //   4769: sipush #8697
    //   4772: invokestatic a : (II)Ljava/lang/String;
    //   4775: invokevirtual startsWith : (Ljava/lang/String;)Z
    //   4778: ifne -> 4788
    //   4781: goto -> 4788
    //   4784: invokestatic a : (Ljava/lang/Throwable;)Ljava/lang/Throwable;
    //   4787: athrow
    //   4788: aload #7
    //   4790: iconst_1
    //   4791: invokevirtual setAccessible : (Z)V
    //   4794: aload #7
    //   4796: aconst_null
    //   4797: invokevirtual get : (Ljava/lang/Object;)Ljava/lang/Object;
    //   4800: pop
    //   4801: iinc #6, 1
    //   4804: iload_2
    //   4805: ifne -> 4666
    //   4808: sipush #11499
    //   4811: sipush #18451
    //   4814: invokestatic a : (II)Ljava/lang/String;
    //   4817: invokestatic forName : (Ljava/lang/String;)Ljava/lang/Class;
    //   4820: invokevirtual getDeclaredMethods : ()[Ljava/lang/reflect/Method;
    //   4823: astore #4
    //   4825: aload #4
    //   4827: arraylength
    //   4828: istore #5
    //   4830: iconst_0
    //   4831: istore #6
    //   4833: iload #6
    //   4835: iload #5
    //   4837: if_icmpge -> 4973
    //   4840: aload #4
    //   4842: iload #6
    //   4844: aaload
    //   4845: astore #7
    //   4847: aload #7
    //   4849: invokevirtual getParameterTypes : ()[Ljava/lang/Class;
    //   4852: pop
    //   4853: aload #7
    //   4855: invokevirtual getModifiers : ()I
    //   4858: invokestatic isStatic : (I)Z
    //   4861: ifeq -> 4959
    //   4864: aload #7
    //   4866: invokevirtual getParameterTypes : ()[Ljava/lang/Class;
    //   4869: arraylength
    //   4870: iconst_2
    //   4871: if_icmpne -> 4959
    //   4874: goto -> 4881
    //   4877: invokestatic a : (Ljava/lang/Throwable;)Ljava/lang/Throwable;
    //   4880: athrow
    //   4881: aload #7
    //   4883: invokevirtual getReturnType : ()Ljava/lang/Class;
    //   4886: getstatic java/lang/Boolean.TYPE : Ljava/lang/Class;
    //   4889: if_acmpne -> 4959
    //   4892: goto -> 4899
    //   4895: invokestatic a : (Ljava/lang/Throwable;)Ljava/lang/Throwable;
    //   4898: athrow
    //   4899: aload #7
    //   4901: iconst_1
    //   4902: invokevirtual setAccessible : (Z)V
    //   4905: aload #7
    //   4907: aconst_null
    //   4908: iconst_2
    //   4909: anewarray java/lang/Object
    //   4912: dup
    //   4913: iconst_0
    //   4914: aload_0
    //   4915: aastore
    //   4916: dup
    //   4917: iconst_1
    //   4918: aload_1
    //   4919: ifnonnull -> 4937
    //   4922: goto -> 4929
    //   4925: invokestatic a : (Ljava/lang/Throwable;)Ljava/lang/Throwable;
    //   4928: athrow
    //   4929: aload_1
    //   4930: goto -> 4944
    //   4933: invokestatic a : (Ljava/lang/Throwable;)Ljava/lang/Throwable;
    //   4936: athrow
    //   4937: aload_1
    //   4938: checkcast [B
    //   4941: invokevirtual clone : ()Ljava/lang/Object;
    //   4944: aastore
    //   4945: invokevirtual invoke : (Ljava/lang/Object;[Ljava/lang/Object;)Ljava/lang/Object;
    //   4948: checkcast java/lang/Boolean
    //   4951: invokevirtual booleanValue : ()Z
    //   4954: istore_3
    //   4955: iload_2
    //   4956: ifne -> 4973
    //   4959: iinc #6, 1
    //   4962: iload_2
    //   4963: ifne -> 4833
    //   4966: goto -> 4973
    //   4969: invokestatic a : (Ljava/lang/Throwable;)Ljava/lang/Throwable;
    //   4972: athrow
    //   4973: iload_2
    //   4974: ifne -> 5315
    //   4977: sipush #11501
    //   4980: sipush #-26719
    //   4983: invokestatic a : (II)Ljava/lang/String;
    //   4986: iconst_1
    //   4987: ldc burp/Zeqr
    //   4989: invokevirtual getClassLoader : ()Ljava/lang/ClassLoader;
    //   4992: invokestatic forName : (Ljava/lang/String;ZLjava/lang/ClassLoader;)Ljava/lang/Class;
    //   4995: invokevirtual getDeclaredFields : ()[Ljava/lang/reflect/Field;
    //   4998: astore #4
    //   5000: aload #4
    //   5002: arraylength
    //   5003: istore #5
    //   5005: iconst_0
    //   5006: istore #6
    //   5008: iload #6
    //   5010: iload #5
    //   5012: if_icmpge -> 5150
    //   5015: aload #4
    //   5017: iload #6
    //   5019: aaload
    //   5020: astore #7
    //   5022: aload #7
    //   5024: invokevirtual getModifiers : ()I
    //   5027: invokestatic isStatic : (I)Z
    //   5030: ifne -> 5040
    //   5033: goto -> 5143
    //   5036: invokestatic a : (Ljava/lang/Throwable;)Ljava/lang/Throwable;
    //   5039: athrow
    //   5040: aload #7
    //   5042: invokevirtual getType : ()Ljava/lang/Class;
    //   5045: astore #8
    //   5047: aload #8
    //   5049: ifnull -> 5130
    //   5052: aload #8
    //   5054: invokevirtual isPrimitive : ()Z
    //   5057: ifne -> 5130
    //   5060: goto -> 5067
    //   5063: invokestatic a : (Ljava/lang/Throwable;)Ljava/lang/Throwable;
    //   5066: athrow
    //   5067: aload #8
    //   5069: invokevirtual getPackage : ()Ljava/lang/Package;
    //   5072: ifnull -> 5130
    //   5075: goto -> 5082
    //   5078: invokestatic a : (Ljava/lang/Throwable;)Ljava/lang/Throwable;
    //   5081: athrow
    //   5082: aload #8
    //   5084: invokevirtual getPackage : ()Ljava/lang/Package;
    //   5087: invokevirtual getName : ()Ljava/lang/String;
    //   5090: ifnull -> 5130
    //   5093: goto -> 5100
    //   5096: invokestatic a : (Ljava/lang/Throwable;)Ljava/lang/Throwable;
    //   5099: athrow
    //   5100: aload #8
    //   5102: invokevirtual getPackage : ()Ljava/lang/Package;
    //   5105: invokevirtual getName : ()Ljava/lang/String;
    //   5108: sipush #11509
    //   5111: sipush #8697
    //   5114: invokestatic a : (II)Ljava/lang/String;
    //   5117: invokevirtual startsWith : (Ljava/lang/String;)Z
    //   5120: ifne -> 5130
    //   5123: goto -> 5130
    //   5126: invokestatic a : (Ljava/lang/Throwable;)Ljava/lang/Throwable;
    //   5129: athrow
    //   5130: aload #7
    //   5132: iconst_1
    //   5133: invokevirtual setAccessible : (Z)V
    //   5136: aload #7
    //   5138: aconst_null
    //   5139: invokevirtual get : (Ljava/lang/Object;)Ljava/lang/Object;
    //   5142: pop
    //   5143: iinc #6, 1
    //   5146: iload_2
    //   5147: ifne -> 5008
    //   5150: sipush #11503
    //   5153: sipush #-5440
    //   5156: invokestatic a : (II)Ljava/lang/String;
    //   5159: invokestatic forName : (Ljava/lang/String;)Ljava/lang/Class;
    //   5162: invokevirtual getDeclaredMethods : ()[Ljava/lang/reflect/Method;
    //   5165: astore #4
    //   5167: aload #4
    //   5169: arraylength
    //   5170: istore #5
    //   5172: iconst_0
    //   5173: istore #6
    //   5175: iload #6
    //   5177: iload #5
    //   5179: if_icmpge -> 5315
    //   5182: aload #4
    //   5184: iload #6
    //   5186: aaload
    //   5187: astore #7
    //   5189: aload #7
    //   5191: invokevirtual getParameterTypes : ()[Ljava/lang/Class;
    //   5194: pop
    //   5195: aload #7
    //   5197: invokevirtual getModifiers : ()I
    //   5200: invokestatic isStatic : (I)Z
    //   5203: ifeq -> 5301
    //   5206: aload #7
    //   5208: invokevirtual getParameterTypes : ()[Ljava/lang/Class;
    //   5211: arraylength
    //   5212: iconst_2
    //   5213: if_icmpne -> 5301
    //   5216: goto -> 5223
    //   5219: invokestatic a : (Ljava/lang/Throwable;)Ljava/lang/Throwable;
    //   5222: athrow
    //   5223: aload #7
    //   5225: invokevirtual getReturnType : ()Ljava/lang/Class;
    //   5228: getstatic java/lang/Boolean.TYPE : Ljava/lang/Class;
    //   5231: if_acmpne -> 5301
    //   5234: goto -> 5241
    //   5237: invokestatic a : (Ljava/lang/Throwable;)Ljava/lang/Throwable;
    //   5240: athrow
    //   5241: aload #7
    //   5243: iconst_1
    //   5244: invokevirtual setAccessible : (Z)V
    //   5247: aload #7
    //   5249: aconst_null
    //   5250: iconst_2
    //   5251: anewarray java/lang/Object
    //   5254: dup
    //   5255: iconst_0
    //   5256: aload_0
    //   5257: aastore
    //   5258: dup
    //   5259: iconst_1
    //   5260: aload_1
    //   5261: ifnonnull -> 5279
    //   5264: goto -> 5271
    //   5267: invokestatic a : (Ljava/lang/Throwable;)Ljava/lang/Throwable;
    //   5270: athrow
    //   5271: aload_1
    //   5272: goto -> 5286
    //   5275: invokestatic a : (Ljava/lang/Throwable;)Ljava/lang/Throwable;
    //   5278: athrow
    //   5279: aload_1
    //   5280: checkcast [B
    //   5283: invokevirtual clone : ()Ljava/lang/Object;
    //   5286: aastore
    //   5287: invokevirtual invoke : (Ljava/lang/Object;[Ljava/lang/Object;)Ljava/lang/Object;
    //   5290: checkcast java/lang/Boolean
    //   5293: invokevirtual booleanValue : ()Z
    //   5296: istore_3
    //   5297: iload_2
    //   5298: ifne -> 5315
    //   5301: iinc #6, 1
    //   5304: iload_2
    //   5305: ifne -> 5175
    //   5308: goto -> 5315
    //   5311: invokestatic a : (Ljava/lang/Throwable;)Ljava/lang/Throwable;
    //   5314: athrow
    //   5315: iload_3
    //   5316: ifeq -> 5321
    //   5319: iload_3
    //   5320: ireturn
    //   5321: getstatic burp/Ztzh.ZE : Ljava/lang/String;
    //   5324: getstatic burp/Zf.Zh : Ljava/lang/Object;
    //   5327: checkcast java/math/BigInteger
    //   5330: invokevirtual intValue : ()I
    //   5333: bipush #32
    //   5335: irem
    //   5336: invokestatic abs : (I)I
    //   5339: invokevirtual charAt : (I)C
    //   5342: getstatic burp/Zbo2.Zr : Ljava/lang/String;
    //   5345: getstatic burp/Zgyc.ZT : Ljava/lang/Object;
    //   5348: checkcast java/math/BigInteger
    //   5351: invokevirtual intValue : ()I
    //   5354: bipush #32
    //   5356: irem
    //   5357: invokestatic abs : (I)I
    //   5360: invokevirtual charAt : (I)C
    //   5363: if_icmple -> 5708
    //   5366: sipush #11502
    //   5369: sipush #-21221
    //   5372: invokestatic a : (II)Ljava/lang/String;
    //   5375: iconst_1
    //   5376: ldc burp/Zxoa
    //   5378: invokevirtual getClassLoader : ()Ljava/lang/ClassLoader;
    //   5381: invokestatic forName : (Ljava/lang/String;ZLjava/lang/ClassLoader;)Ljava/lang/Class;
    //   5384: invokevirtual getDeclaredFields : ()[Ljava/lang/reflect/Field;
    //   5387: astore #4
    //   5389: aload #4
    //   5391: arraylength
    //   5392: istore #5
    //   5394: iconst_0
    //   5395: istore #6
    //   5397: iload #6
    //   5399: iload #5
    //   5401: if_icmpge -> 5539
    //   5404: aload #4
    //   5406: iload #6
    //   5408: aaload
    //   5409: astore #7
    //   5411: aload #7
    //   5413: invokevirtual getModifiers : ()I
    //   5416: invokestatic isStatic : (I)Z
    //   5419: ifne -> 5429
    //   5422: goto -> 5532
    //   5425: invokestatic a : (Ljava/lang/Throwable;)Ljava/lang/Throwable;
    //   5428: athrow
    //   5429: aload #7
    //   5431: invokevirtual getType : ()Ljava/lang/Class;
    //   5434: astore #8
    //   5436: aload #8
    //   5438: ifnull -> 5519
    //   5441: aload #8
    //   5443: invokevirtual isPrimitive : ()Z
    //   5446: ifne -> 5519
    //   5449: goto -> 5456
    //   5452: invokestatic a : (Ljava/lang/Throwable;)Ljava/lang/Throwable;
    //   5455: athrow
    //   5456: aload #8
    //   5458: invokevirtual getPackage : ()Ljava/lang/Package;
    //   5461: ifnull -> 5519
    //   5464: goto -> 5471
    //   5467: invokestatic a : (Ljava/lang/Throwable;)Ljava/lang/Throwable;
    //   5470: athrow
    //   5471: aload #8
    //   5473: invokevirtual getPackage : ()Ljava/lang/Package;
    //   5476: invokevirtual getName : ()Ljava/lang/String;
    //   5479: ifnull -> 5519
    //   5482: goto -> 5489
    //   5485: invokestatic a : (Ljava/lang/Throwable;)Ljava/lang/Throwable;
    //   5488: athrow
    //   5489: aload #8
    //   5491: invokevirtual getPackage : ()Ljava/lang/Package;
    //   5494: invokevirtual getName : ()Ljava/lang/String;
    //   5497: sipush #11509
    //   5500: sipush #8697
    //   5503: invokestatic a : (II)Ljava/lang/String;
    //   5506: invokevirtual startsWith : (Ljava/lang/String;)Z
    //   5509: ifne -> 5519
    //   5512: goto -> 5519
    //   5515: invokestatic a : (Ljava/lang/Throwable;)Ljava/lang/Throwable;
    //   5518: athrow
    //   5519: aload #7
    //   5521: iconst_1
    //   5522: invokevirtual setAccessible : (Z)V
    //   5525: aload #7
    //   5527: aconst_null
    //   5528: invokevirtual get : (Ljava/lang/Object;)Ljava/lang/Object;
    //   5531: pop
    //   5532: iinc #6, 1
    //   5535: iload_2
    //   5536: ifne -> 5397
    //   5539: sipush #11494
    //   5542: sipush #3857
    //   5545: invokestatic a : (II)Ljava/lang/String;
    //   5548: invokestatic forName : (Ljava/lang/String;)Ljava/lang/Class;
    //   5551: invokevirtual getDeclaredMethods : ()[Ljava/lang/reflect/Method;
    //   5554: astore #4
    //   5556: aload #4
    //   5558: arraylength
    //   5559: istore #5
    //   5561: iconst_0
    //   5562: istore #6
    //   5564: iload #6
    //   5566: iload #5
    //   5568: if_icmpge -> 5704
    //   5571: aload #4
    //   5573: iload #6
    //   5575: aaload
    //   5576: astore #7
    //   5578: aload #7
    //   5580: invokevirtual getParameterTypes : ()[Ljava/lang/Class;
    //   5583: pop
    //   5584: aload #7
    //   5586: invokevirtual getModifiers : ()I
    //   5589: invokestatic isStatic : (I)Z
    //   5592: ifeq -> 5690
    //   5595: aload #7
    //   5597: invokevirtual getParameterTypes : ()[Ljava/lang/Class;
    //   5600: arraylength
    //   5601: iconst_2
    //   5602: if_icmpne -> 5690
    //   5605: goto -> 5612
    //   5608: invokestatic a : (Ljava/lang/Throwable;)Ljava/lang/Throwable;
    //   5611: athrow
    //   5612: aload #7
    //   5614: invokevirtual getReturnType : ()Ljava/lang/Class;
    //   5617: getstatic java/lang/Boolean.TYPE : Ljava/lang/Class;
    //   5620: if_acmpne -> 5690
    //   5623: goto -> 5630
    //   5626: invokestatic a : (Ljava/lang/Throwable;)Ljava/lang/Throwable;
    //   5629: athrow
    //   5630: aload #7
    //   5632: iconst_1
    //   5633: invokevirtual setAccessible : (Z)V
    //   5636: aload #7
    //   5638: aconst_null
    //   5639: iconst_2
    //   5640: anewarray java/lang/Object
    //   5643: dup
    //   5644: iconst_0
    //   5645: aload_0
    //   5646: aastore
    //   5647: dup
    //   5648: iconst_1
    //   5649: aload_1
    //   5650: ifnonnull -> 5668
    //   5653: goto -> 5660
    //   5656: invokestatic a : (Ljava/lang/Throwable;)Ljava/lang/Throwable;
    //   5659: athrow
    //   5660: aload_1
    //   5661: goto -> 5675
    //   5664: invokestatic a : (Ljava/lang/Throwable;)Ljava/lang/Throwable;
    //   5667: athrow
    //   5668: aload_1
    //   5669: checkcast [B
    //   5672: invokevirtual clone : ()Ljava/lang/Object;
    //   5675: aastore
    //   5676: invokevirtual invoke : (Ljava/lang/Object;[Ljava/lang/Object;)Ljava/lang/Object;
    //   5679: checkcast java/lang/Boolean
    //   5682: invokevirtual booleanValue : ()Z
    //   5685: istore_3
    //   5686: iload_2
    //   5687: ifne -> 5704
    //   5690: iinc #6, 1
    //   5693: iload_2
    //   5694: ifne -> 5564
    //   5697: goto -> 5704
    //   5700: invokestatic a : (Ljava/lang/Throwable;)Ljava/lang/Throwable;
    //   5703: athrow
    //   5704: iload_2
    //   5705: ifne -> 6046
    //   5708: sipush #11508
    //   5711: sipush #-31469
    //   5714: invokestatic a : (II)Ljava/lang/String;
    //   5717: iconst_1
    //   5718: ldc burp/Zz4r
    //   5720: invokevirtual getClassLoader : ()Ljava/lang/ClassLoader;
    //   5723: invokestatic forName : (Ljava/lang/String;ZLjava/lang/ClassLoader;)Ljava/lang/Class;
    //   5726: invokevirtual getDeclaredFields : ()[Ljava/lang/reflect/Field;
    //   5729: astore #4
    //   5731: aload #4
    //   5733: arraylength
    //   5734: istore #5
    //   5736: iconst_0
    //   5737: istore #6
    //   5739: iload #6
    //   5741: iload #5
    //   5743: if_icmpge -> 5881
    //   5746: aload #4
    //   5748: iload #6
    //   5750: aaload
    //   5751: astore #7
    //   5753: aload #7
    //   5755: invokevirtual getModifiers : ()I
    //   5758: invokestatic isStatic : (I)Z
    //   5761: ifne -> 5771
    //   5764: goto -> 5874
    //   5767: invokestatic a : (Ljava/lang/Throwable;)Ljava/lang/Throwable;
    //   5770: athrow
    //   5771: aload #7
    //   5773: invokevirtual getType : ()Ljava/lang/Class;
    //   5776: astore #8
    //   5778: aload #8
    //   5780: ifnull -> 5861
    //   5783: aload #8
    //   5785: invokevirtual isPrimitive : ()Z
    //   5788: ifne -> 5861
    //   5791: goto -> 5798
    //   5794: invokestatic a : (Ljava/lang/Throwable;)Ljava/lang/Throwable;
    //   5797: athrow
    //   5798: aload #8
    //   5800: invokevirtual getPackage : ()Ljava/lang/Package;
    //   5803: ifnull -> 5861
    //   5806: goto -> 5813
    //   5809: invokestatic a : (Ljava/lang/Throwable;)Ljava/lang/Throwable;
    //   5812: athrow
    //   5813: aload #8
    //   5815: invokevirtual getPackage : ()Ljava/lang/Package;
    //   5818: invokevirtual getName : ()Ljava/lang/String;
    //   5821: ifnull -> 5861
    //   5824: goto -> 5831
    //   5827: invokestatic a : (Ljava/lang/Throwable;)Ljava/lang/Throwable;
    //   5830: athrow
    //   5831: aload #8
    //   5833: invokevirtual getPackage : ()Ljava/lang/Package;
    //   5836: invokevirtual getName : ()Ljava/lang/String;
    //   5839: sipush #11509
    //   5842: sipush #8697
    //   5845: invokestatic a : (II)Ljava/lang/String;
    //   5848: invokevirtual startsWith : (Ljava/lang/String;)Z
    //   5851: ifne -> 5861
    //   5854: goto -> 5861
    //   5857: invokestatic a : (Ljava/lang/Throwable;)Ljava/lang/Throwable;
    //   5860: athrow
    //   5861: aload #7
    //   5863: iconst_1
    //   5864: invokevirtual setAccessible : (Z)V
    //   5867: aload #7
    //   5869: aconst_null
    //   5870: invokevirtual get : (Ljava/lang/Object;)Ljava/lang/Object;
    //   5873: pop
    //   5874: iinc #6, 1
    //   5877: iload_2
    //   5878: ifne -> 5739
    //   5881: sipush #11519
    //   5884: sipush #19000
    //   5887: invokestatic a : (II)Ljava/lang/String;
    //   5890: invokestatic forName : (Ljava/lang/String;)Ljava/lang/Class;
    //   5893: invokevirtual getDeclaredMethods : ()[Ljava/lang/reflect/Method;
    //   5896: astore #4
    //   5898: aload #4
    //   5900: arraylength
    //   5901: istore #5
    //   5903: iconst_0
    //   5904: istore #6
    //   5906: iload #6
    //   5908: iload #5
    //   5910: if_icmpge -> 6046
    //   5913: aload #4
    //   5915: iload #6
    //   5917: aaload
    //   5918: astore #7
    //   5920: aload #7
    //   5922: invokevirtual getParameterTypes : ()[Ljava/lang/Class;
    //   5925: pop
    //   5926: aload #7
    //   5928: invokevirtual getModifiers : ()I
    //   5931: invokestatic isStatic : (I)Z
    //   5934: ifeq -> 6032
    //   5937: aload #7
    //   5939: invokevirtual getParameterTypes : ()[Ljava/lang/Class;
    //   5942: arraylength
    //   5943: iconst_2
    //   5944: if_icmpne -> 6032
    //   5947: goto -> 5954
    //   5950: invokestatic a : (Ljava/lang/Throwable;)Ljava/lang/Throwable;
    //   5953: athrow
    //   5954: aload #7
    //   5956: invokevirtual getReturnType : ()Ljava/lang/Class;
    //   5959: getstatic java/lang/Boolean.TYPE : Ljava/lang/Class;
    //   5962: if_acmpne -> 6032
    //   5965: goto -> 5972
    //   5968: invokestatic a : (Ljava/lang/Throwable;)Ljava/lang/Throwable;
    //   5971: athrow
    //   5972: aload #7
    //   5974: iconst_1
    //   5975: invokevirtual setAccessible : (Z)V
    //   5978: aload #7
    //   5980: aconst_null
    //   5981: iconst_2
    //   5982: anewarray java/lang/Object
    //   5985: dup
    //   5986: iconst_0
    //   5987: aload_0
    //   5988: aastore
    //   5989: dup
    //   5990: iconst_1
    //   5991: aload_1
    //   5992: ifnonnull -> 6010
    //   5995: goto -> 6002
    //   5998: invokestatic a : (Ljava/lang/Throwable;)Ljava/lang/Throwable;
    //   6001: athrow
    //   6002: aload_1
    //   6003: goto -> 6017
    //   6006: invokestatic a : (Ljava/lang/Throwable;)Ljava/lang/Throwable;
    //   6009: athrow
    //   6010: aload_1
    //   6011: checkcast [B
    //   6014: invokevirtual clone : ()Ljava/lang/Object;
    //   6017: aastore
    //   6018: invokevirtual invoke : (Ljava/lang/Object;[Ljava/lang/Object;)Ljava/lang/Object;
    //   6021: checkcast java/lang/Boolean
    //   6024: invokevirtual booleanValue : ()Z
    //   6027: istore_3
    //   6028: iload_2
    //   6029: ifne -> 6046
    //   6032: iinc #6, 1
    //   6035: iload_2
    //   6036: ifne -> 5906
    //   6039: goto -> 6046
    //   6042: invokestatic a : (Ljava/lang/Throwable;)Ljava/lang/Throwable;
    //   6045: athrow
    //   6046: iload_3
    //   6047: ifeq -> 6052
    //   6050: iload_3
    //   6051: ireturn
    //   6052: getstatic burp/Zgjs.Zp : Ljava/lang/String;
    //   6055: getstatic burp/Zxo4.ZV : Ljava/lang/Object;
    //   6058: checkcast java/math/BigInteger
    //   6061: invokevirtual intValue : ()I
    //   6064: bipush #32
    //   6066: irem
    //   6067: invokestatic abs : (I)I
    //   6070: invokevirtual charAt : (I)C
    //   6073: getstatic burp/Zrka.Zy : Ljava/lang/String;
    //   6076: getstatic burp/Zlp8.Zu : Ljava/lang/Object;
    //   6079: checkcast java/math/BigInteger
    //   6082: invokevirtual intValue : ()I
    //   6085: bipush #32
    //   6087: irem
    //   6088: invokestatic abs : (I)I
    //   6091: invokevirtual charAt : (I)C
    //   6094: if_icmple -> 6439
    //   6097: sipush #11512
    //   6100: sipush #-6663
    //   6103: invokestatic a : (II)Ljava/lang/String;
    //   6106: iconst_1
    //   6107: ldc burp/Zl5b
    //   6109: invokevirtual getClassLoader : ()Ljava/lang/ClassLoader;
    //   6112: invokestatic forName : (Ljava/lang/String;ZLjava/lang/ClassLoader;)Ljava/lang/Class;
    //   6115: invokevirtual getDeclaredFields : ()[Ljava/lang/reflect/Field;
    //   6118: astore #4
    //   6120: aload #4
    //   6122: arraylength
    //   6123: istore #5
    //   6125: iconst_0
    //   6126: istore #6
    //   6128: iload #6
    //   6130: iload #5
    //   6132: if_icmpge -> 6270
    //   6135: aload #4
    //   6137: iload #6
    //   6139: aaload
    //   6140: astore #7
    //   6142: aload #7
    //   6144: invokevirtual getModifiers : ()I
    //   6147: invokestatic isStatic : (I)Z
    //   6150: ifne -> 6160
    //   6153: goto -> 6263
    //   6156: invokestatic a : (Ljava/lang/Throwable;)Ljava/lang/Throwable;
    //   6159: athrow
    //   6160: aload #7
    //   6162: invokevirtual getType : ()Ljava/lang/Class;
    //   6165: astore #8
    //   6167: aload #8
    //   6169: ifnull -> 6250
    //   6172: aload #8
    //   6174: invokevirtual isPrimitive : ()Z
    //   6177: ifne -> 6250
    //   6180: goto -> 6187
    //   6183: invokestatic a : (Ljava/lang/Throwable;)Ljava/lang/Throwable;
    //   6186: athrow
    //   6187: aload #8
    //   6189: invokevirtual getPackage : ()Ljava/lang/Package;
    //   6192: ifnull -> 6250
    //   6195: goto -> 6202
    //   6198: invokestatic a : (Ljava/lang/Throwable;)Ljava/lang/Throwable;
    //   6201: athrow
    //   6202: aload #8
    //   6204: invokevirtual getPackage : ()Ljava/lang/Package;
    //   6207: invokevirtual getName : ()Ljava/lang/String;
    //   6210: ifnull -> 6250
    //   6213: goto -> 6220
    //   6216: invokestatic a : (Ljava/lang/Throwable;)Ljava/lang/Throwable;
    //   6219: athrow
    //   6220: aload #8
    //   6222: invokevirtual getPackage : ()Ljava/lang/Package;
    //   6225: invokevirtual getName : ()Ljava/lang/String;
    //   6228: sipush #11509
    //   6231: sipush #8697
    //   6234: invokestatic a : (II)Ljava/lang/String;
    //   6237: invokevirtual startsWith : (Ljava/lang/String;)Z
    //   6240: ifne -> 6250
    //   6243: goto -> 6250
    //   6246: invokestatic a : (Ljava/lang/Throwable;)Ljava/lang/Throwable;
    //   6249: athrow
    //   6250: aload #7
    //   6252: iconst_1
    //   6253: invokevirtual setAccessible : (Z)V
    //   6256: aload #7
    //   6258: aconst_null
    //   6259: invokevirtual get : (Ljava/lang/Object;)Ljava/lang/Object;
    //   6262: pop
    //   6263: iinc #6, 1
    //   6266: iload_2
    //   6267: ifne -> 6128
    //   6270: sipush #11492
    //   6273: sipush #18883
    //   6276: invokestatic a : (II)Ljava/lang/String;
    //   6279: invokestatic forName : (Ljava/lang/String;)Ljava/lang/Class;
    //   6282: invokevirtual getDeclaredMethods : ()[Ljava/lang/reflect/Method;
    //   6285: astore #4
    //   6287: aload #4
    //   6289: arraylength
    //   6290: istore #5
    //   6292: iconst_0
    //   6293: istore #6
    //   6295: iload #6
    //   6297: iload #5
    //   6299: if_icmpge -> 6435
    //   6302: aload #4
    //   6304: iload #6
    //   6306: aaload
    //   6307: astore #7
    //   6309: aload #7
    //   6311: invokevirtual getParameterTypes : ()[Ljava/lang/Class;
    //   6314: pop
    //   6315: aload #7
    //   6317: invokevirtual getModifiers : ()I
    //   6320: invokestatic isStatic : (I)Z
    //   6323: ifeq -> 6421
    //   6326: aload #7
    //   6328: invokevirtual getParameterTypes : ()[Ljava/lang/Class;
    //   6331: arraylength
    //   6332: iconst_2
    //   6333: if_icmpne -> 6421
    //   6336: goto -> 6343
    //   6339: invokestatic a : (Ljava/lang/Throwable;)Ljava/lang/Throwable;
    //   6342: athrow
    //   6343: aload #7
    //   6345: invokevirtual getReturnType : ()Ljava/lang/Class;
    //   6348: getstatic java/lang/Boolean.TYPE : Ljava/lang/Class;
    //   6351: if_acmpne -> 6421
    //   6354: goto -> 6361
    //   6357: invokestatic a : (Ljava/lang/Throwable;)Ljava/lang/Throwable;
    //   6360: athrow
    //   6361: aload #7
    //   6363: iconst_1
    //   6364: invokevirtual setAccessible : (Z)V
    //   6367: aload #7
    //   6369: aconst_null
    //   6370: iconst_2
    //   6371: anewarray java/lang/Object
    //   6374: dup
    //   6375: iconst_0
    //   6376: aload_0
    //   6377: aastore
    //   6378: dup
    //   6379: iconst_1
    //   6380: aload_1
    //   6381: ifnonnull -> 6399
    //   6384: goto -> 6391
    //   6387: invokestatic a : (Ljava/lang/Throwable;)Ljava/lang/Throwable;
    //   6390: athrow
    //   6391: aload_1
    //   6392: goto -> 6406
    //   6395: invokestatic a : (Ljava/lang/Throwable;)Ljava/lang/Throwable;
    //   6398: athrow
    //   6399: aload_1
    //   6400: checkcast [B
    //   6403: invokevirtual clone : ()Ljava/lang/Object;
    //   6406: aastore
    //   6407: invokevirtual invoke : (Ljava/lang/Object;[Ljava/lang/Object;)Ljava/lang/Object;
    //   6410: checkcast java/lang/Boolean
    //   6413: invokevirtual booleanValue : ()Z
    //   6416: istore_3
    //   6417: iload_2
    //   6418: ifne -> 6435
    //   6421: iinc #6, 1
    //   6424: iload_2
    //   6425: ifne -> 6295
    //   6428: goto -> 6435
    //   6431: invokestatic a : (Ljava/lang/Throwable;)Ljava/lang/Throwable;
    //   6434: athrow
    //   6435: iload_2
    //   6436: ifne -> 6777
    //   6439: sipush #11507
    //   6442: sipush #-26229
    //   6445: invokestatic a : (II)Ljava/lang/String;
    //   6448: iconst_1
    //   6449: ldc burp/Zxpb
    //   6451: invokevirtual getClassLoader : ()Ljava/lang/ClassLoader;
    //   6454: invokestatic forName : (Ljava/lang/String;ZLjava/lang/ClassLoader;)Ljava/lang/Class;
    //   6457: invokevirtual getDeclaredFields : ()[Ljava/lang/reflect/Field;
    //   6460: astore #4
    //   6462: aload #4
    //   6464: arraylength
    //   6465: istore #5
    //   6467: iconst_0
    //   6468: istore #6
    //   6470: iload #6
    //   6472: iload #5
    //   6474: if_icmpge -> 6612
    //   6477: aload #4
    //   6479: iload #6
    //   6481: aaload
    //   6482: astore #7
    //   6484: aload #7
    //   6486: invokevirtual getModifiers : ()I
    //   6489: invokestatic isStatic : (I)Z
    //   6492: ifne -> 6502
    //   6495: goto -> 6605
    //   6498: invokestatic a : (Ljava/lang/Throwable;)Ljava/lang/Throwable;
    //   6501: athrow
    //   6502: aload #7
    //   6504: invokevirtual getType : ()Ljava/lang/Class;
    //   6507: astore #8
    //   6509: aload #8
    //   6511: ifnull -> 6592
    //   6514: aload #8
    //   6516: invokevirtual isPrimitive : ()Z
    //   6519: ifne -> 6592
    //   6522: goto -> 6529
    //   6525: invokestatic a : (Ljava/lang/Throwable;)Ljava/lang/Throwable;
    //   6528: athrow
    //   6529: aload #8
    //   6531: invokevirtual getPackage : ()Ljava/lang/Package;
    //   6534: ifnull -> 6592
    //   6537: goto -> 6544
    //   6540: invokestatic a : (Ljava/lang/Throwable;)Ljava/lang/Throwable;
    //   6543: athrow
    //   6544: aload #8
    //   6546: invokevirtual getPackage : ()Ljava/lang/Package;
    //   6549: invokevirtual getName : ()Ljava/lang/String;
    //   6552: ifnull -> 6592
    //   6555: goto -> 6562
    //   6558: invokestatic a : (Ljava/lang/Throwable;)Ljava/lang/Throwable;
    //   6561: athrow
    //   6562: aload #8
    //   6564: invokevirtual getPackage : ()Ljava/lang/Package;
    //   6567: invokevirtual getName : ()Ljava/lang/String;
    //   6570: sipush #11509
    //   6573: sipush #8697
    //   6576: invokestatic a : (II)Ljava/lang/String;
    //   6579: invokevirtual startsWith : (Ljava/lang/String;)Z
    //   6582: ifne -> 6592
    //   6585: goto -> 6592
    //   6588: invokestatic a : (Ljava/lang/Throwable;)Ljava/lang/Throwable;
    //   6591: athrow
    //   6592: aload #7
    //   6594: iconst_1
    //   6595: invokevirtual setAccessible : (Z)V
    //   6598: aload #7
    //   6600: aconst_null
    //   6601: invokevirtual get : (Ljava/lang/Object;)Ljava/lang/Object;
    //   6604: pop
    //   6605: iinc #6, 1
    //   6608: iload_2
    //   6609: ifne -> 6470
    //   6612: sipush #11504
    //   6615: sipush #14911
    //   6618: invokestatic a : (II)Ljava/lang/String;
    //   6621: invokestatic forName : (Ljava/lang/String;)Ljava/lang/Class;
    //   6624: invokevirtual getDeclaredMethods : ()[Ljava/lang/reflect/Method;
    //   6627: astore #4
    //   6629: aload #4
    //   6631: arraylength
    //   6632: istore #5
    //   6634: iconst_0
    //   6635: istore #6
    //   6637: iload #6
    //   6639: iload #5
    //   6641: if_icmpge -> 6777
    //   6644: aload #4
    //   6646: iload #6
    //   6648: aaload
    //   6649: astore #7
    //   6651: aload #7
    //   6653: invokevirtual getParameterTypes : ()[Ljava/lang/Class;
    //   6656: pop
    //   6657: aload #7
    //   6659: invokevirtual getModifiers : ()I
    //   6662: invokestatic isStatic : (I)Z
    //   6665: ifeq -> 6763
    //   6668: aload #7
    //   6670: invokevirtual getParameterTypes : ()[Ljava/lang/Class;
    //   6673: arraylength
    //   6674: iconst_2
    //   6675: if_icmpne -> 6763
    //   6678: goto -> 6685
    //   6681: invokestatic a : (Ljava/lang/Throwable;)Ljava/lang/Throwable;
    //   6684: athrow
    //   6685: aload #7
    //   6687: invokevirtual getReturnType : ()Ljava/lang/Class;
    //   6690: getstatic java/lang/Boolean.TYPE : Ljava/lang/Class;
    //   6693: if_acmpne -> 6763
    //   6696: goto -> 6703
    //   6699: invokestatic a : (Ljava/lang/Throwable;)Ljava/lang/Throwable;
    //   6702: athrow
    //   6703: aload #7
    //   6705: iconst_1
    //   6706: invokevirtual setAccessible : (Z)V
    //   6709: aload #7
    //   6711: aconst_null
    //   6712: iconst_2
    //   6713: anewarray java/lang/Object
    //   6716: dup
    //   6717: iconst_0
    //   6718: aload_0
    //   6719: aastore
    //   6720: dup
    //   6721: iconst_1
    //   6722: aload_1
    //   6723: ifnonnull -> 6741
    //   6726: goto -> 6733
    //   6729: invokestatic a : (Ljava/lang/Throwable;)Ljava/lang/Throwable;
    //   6732: athrow
    //   6733: aload_1
    //   6734: goto -> 6748
    //   6737: invokestatic a : (Ljava/lang/Throwable;)Ljava/lang/Throwable;
    //   6740: athrow
    //   6741: aload_1
    //   6742: checkcast [B
    //   6745: invokevirtual clone : ()Ljava/lang/Object;
    //   6748: aastore
    //   6749: invokevirtual invoke : (Ljava/lang/Object;[Ljava/lang/Object;)Ljava/lang/Object;
    //   6752: checkcast java/lang/Boolean
    //   6755: invokevirtual booleanValue : ()Z
    //   6758: istore_3
    //   6759: iload_2
    //   6760: ifne -> 6777
    //   6763: iinc #6, 1
    //   6766: iload_2
    //   6767: ifne -> 6637
    //   6770: goto -> 6777
    //   6773: invokestatic a : (Ljava/lang/Throwable;)Ljava/lang/Throwable;
    //   6776: athrow
    //   6777: iload_3
    //   6778: ireturn
    //   6779: astore_3
    //   6780: new java/lang/Exception
    //   6783: dup
    //   6784: aload_3
    //   6785: invokevirtual getMessage : ()Ljava/lang/String;
    //   6788: invokespecial <init> : (Ljava/lang/String;)V
    //   6791: athrow
    // Exception table:
    //   from	to	target	type
    //   4	4589	6779	java/lang/Throwable
    //   149	164	164	java/lang/Throwable
    //   1166	1192	1192	java/lang/Throwable
    //   1273	1288	1288	java/lang/Throwable
    //   2470	2495	2498	java/lang/Throwable
    //   2844	2868	2871	java/lang/Throwable
    //   2942	2979	2979	java/lang/Throwable
    //   2983	3004	3004	java/lang/Throwable
    //   3008	3038	3038	java/lang/Throwable
    //   3263	3277	3277	java/lang/Throwable
    //   3288	3301	3304	java/lang/Throwable
    //   3293	3316	3319	java/lang/Throwable
    //   3308	3334	3337	java/lang/Throwable
    //   3323	3364	3367	java/lang/Throwable
    //   3427	3454	3457	java/lang/Throwable
    //   3444	3472	3475	java/lang/Throwable
    //   3461	3508	3511	java/lang/Throwable
    //   3479	3522	3525	java/lang/Throwable
    //   3571	3585	3585	java/lang/Throwable
    //   3596	3609	3612	java/lang/Throwable
    //   3601	3624	3627	java/lang/Throwable
    //   3616	3642	3645	java/lang/Throwable
    //   3631	3672	3675	java/lang/Throwable
    //   3735	3762	3765	java/lang/Throwable
    //   3752	3783	3786	java/lang/Throwable
    //   3769	3813	3816	java/lang/Throwable
    //   3790	3824	3824	java/lang/Throwable
    //   3835	3851	3854	java/lang/Throwable
    //   3950	3964	3964	java/lang/Throwable
    //   3975	3988	3991	java/lang/Throwable
    //   3980	4003	4006	java/lang/Throwable
    //   3995	4021	4024	java/lang/Throwable
    //   4010	4051	4054	java/lang/Throwable
    //   4117	4144	4147	java/lang/Throwable
    //   4134	4162	4165	java/lang/Throwable
    //   4151	4192	4195	java/lang/Throwable
    //   4169	4203	4203	java/lang/Throwable
    //   4225	4236	4239	java/lang/Throwable
    //   4291	4305	4305	java/lang/Throwable
    //   4316	4329	4332	java/lang/Throwable
    //   4321	4344	4347	java/lang/Throwable
    //   4336	4362	4365	java/lang/Throwable
    //   4351	4392	4395	java/lang/Throwable
    //   4458	4485	4488	java/lang/Throwable
    //   4475	4503	4506	java/lang/Throwable
    //   4492	4533	4536	java/lang/Throwable
    //   4510	4544	4544	java/lang/Throwable
    //   4566	4577	4580	java/lang/Throwable
    //   4590	5320	6779	java/lang/Throwable
    //   4680	4694	4694	java/lang/Throwable
    //   4705	4718	4721	java/lang/Throwable
    //   4710	4733	4736	java/lang/Throwable
    //   4725	4751	4754	java/lang/Throwable
    //   4740	4781	4784	java/lang/Throwable
    //   4847	4874	4877	java/lang/Throwable
    //   4864	4892	4895	java/lang/Throwable
    //   4881	4922	4925	java/lang/Throwable
    //   4899	4933	4933	java/lang/Throwable
    //   4955	4966	4969	java/lang/Throwable
    //   5022	5036	5036	java/lang/Throwable
    //   5047	5060	5063	java/lang/Throwable
    //   5052	5075	5078	java/lang/Throwable
    //   5067	5093	5096	java/lang/Throwable
    //   5082	5123	5126	java/lang/Throwable
    //   5189	5216	5219	java/lang/Throwable
    //   5206	5234	5237	java/lang/Throwable
    //   5223	5264	5267	java/lang/Throwable
    //   5241	5275	5275	java/lang/Throwable
    //   5297	5308	5311	java/lang/Throwable
    //   5321	6051	6779	java/lang/Throwable
    //   5411	5425	5425	java/lang/Throwable
    //   5436	5449	5452	java/lang/Throwable
    //   5441	5464	5467	java/lang/Throwable
    //   5456	5482	5485	java/lang/Throwable
    //   5471	5512	5515	java/lang/Throwable
    //   5578	5605	5608	java/lang/Throwable
    //   5595	5623	5626	java/lang/Throwable
    //   5612	5653	5656	java/lang/Throwable
    //   5630	5664	5664	java/lang/Throwable
    //   5686	5697	5700	java/lang/Throwable
    //   5753	5767	5767	java/lang/Throwable
    //   5778	5791	5794	java/lang/Throwable
    //   5783	5806	5809	java/lang/Throwable
    //   5798	5824	5827	java/lang/Throwable
    //   5813	5854	5857	java/lang/Throwable
    //   5920	5947	5950	java/lang/Throwable
    //   5937	5965	5968	java/lang/Throwable
    //   5954	5995	5998	java/lang/Throwable
    //   5972	6006	6006	java/lang/Throwable
    //   6028	6039	6042	java/lang/Throwable
    //   6052	6778	6779	java/lang/Throwable
    //   6142	6156	6156	java/lang/Throwable
    //   6167	6180	6183	java/lang/Throwable
    //   6172	6195	6198	java/lang/Throwable
    //   6187	6213	6216	java/lang/Throwable
    //   6202	6243	6246	java/lang/Throwable
    //   6309	6336	6339	java/lang/Throwable
    //   6326	6354	6357	java/lang/Throwable
    //   6343	6384	6387	java/lang/Throwable
    //   6361	6395	6395	java/lang/Throwable
    //   6417	6428	6431	java/lang/Throwable
    //   6484	6498	6498	java/lang/Throwable
    //   6509	6522	6525	java/lang/Throwable
    //   6514	6537	6540	java/lang/Throwable
    //   6529	6555	6558	java/lang/Throwable
    //   6544	6585	6588	java/lang/Throwable
    //   6651	6678	6681	java/lang/Throwable
    //   6668	6696	6699	java/lang/Throwable
    //   6685	6726	6729	java/lang/Throwable
    //   6703	6737	6737	java/lang/Throwable
    //   6759	6770	6773	java/lang/Throwable
  }
  
  static void ZB(Object[] paramArrayOfObject, Object paramObject) throws Throwable {}
  
  static void Zh(Object paramObject) {
    Zkht.Zd = a(11516, 27678);
    Zkht.ZR = new BigInteger(a(11515, 7314));
    boolean bool = Zt2e.ZN();
    try {
      try {
        if (Zt7j.Zx.charAt(Math.abs(((BigInteger)Zxd4.Zt).intValue() % 32)) <= Zl8i.Zb.charAt(Math.abs(((BigInteger)Zxf8.Zz).intValue() % 32))) {
          try {
            Zm14.ZX(Class.forName(a(11496, 14207)));
            if (!bool)
              Zzmo.ZU(Class.forName(a(11490, -25362))); 
          } catch (Throwable throwable) {
            throw a(null);
          } 
          return;
        } 
      } catch (Throwable throwable) {
        throw a(null);
      } 
      Zzmo.ZU(Class.forName(a(11490, -25362)));
    } catch (Throwable throwable) {}
  }
  
  static {
    // Byte code:
    //   0: bipush #33
    //   2: anewarray java/lang/String
    //   5: astore #5
    //   7: iconst_0
    //   8: istore_3
    //   9: ldc '\\bz^ 7/F\\bx)}\\t&fb#*SgJ\\t50}y&+\\teo]\\tKX\\r,\\t%f9\\t#!7 N!\\t^Sy4X=!%\\t"+n??\\t~h5U\\tDF)ZM\\n*T`+Ewa[O~(Qs\\r3Y \\fZGtuewR6;_P \\bWIzagK/]s0\\n HR\\tK&>i\\t@\\tk7\\b "\\bG 3u!\| q=<7C\\b\\tZJa\\t&5b\\tx%`\\tDSi-\\t\\r}c\\t(/\\b\\b??\\tftn\\thd'
    //   11: dup
    //   12: astore_2
    //   13: invokevirtual length : ()I
    //   16: istore #4
    //   18: iconst_4
    //   19: istore_1
    //   20: iconst_m1
    //   21: istore_0
    //   22: bipush #89
    //   24: iinc #0, 1
    //   27: aload_2
    //   28: iload_0
    //   29: dup
    //   30: iload_1
    //   31: iadd
    //   32: invokevirtual substring : (II)Ljava/lang/String;
    //   35: iconst_m1
    //   36: goto -> 142
    //   39: aload #5
    //   41: swap
    //   42: iload_3
    //   43: iinc #3, 1
    //   46: swap
    //   47: aastore
    //   48: iload_0
    //   49: iload_1
    //   50: iadd
    //   51: dup
    //   52: istore_0
    //   53: iload #4
    //   55: if_icmpge -> 67
    //   58: aload_2
    //   59: iload_0
    //   60: invokevirtual charAt : (I)C
    //   63: istore_1
    //   64: goto -> 22
    //   67: ldc 'z^_\\ti)WT'
    //   69: dup
    //   70: astore_2
    //   71: invokevirtual length : ()I
    //   74: istore #4
    //   76: bipush #9
    //   78: istore_1
    //   79: iconst_m1
    //   80: istore_0
    //   81: bipush #36
    //   83: iinc #0, 1
    //   86: aload_2
    //   87: iload_0
    //   88: dup
    //   89: iload_1
    //   90: iadd
    //   91: invokevirtual substring : (II)Ljava/lang/String;
    //   94: iconst_0
    //   95: goto -> 142
    //   98: aload #5
    //   100: swap
    //   101: iload_3
    //   102: iinc #3, 1
    //   105: swap
    //   106: aastore
    //   107: iload_0
    //   108: iload_1
    //   109: iadd
    //   110: dup
    //   111: istore_0
    //   112: iload #4
    //   114: if_icmpge -> 126
    //   117: aload_2
    //   118: iload_0
    //   119: invokevirtual charAt : (I)C
    //   122: istore_1
    //   123: goto -> 81
    //   126: aload #5
    //   128: putstatic burp/Zb2p.a : [Ljava/lang/String;
    //   131: bipush #33
    //   133: anewarray java/lang/String
    //   136: putstatic burp/Zb2p.b : [Ljava/lang/String;
    //   139: goto -> 300
    //   142: dup_x2
    //   143: pop
    //   144: invokevirtual toCharArray : ()[C
    //   147: dup_x1
    //   148: arraylength
    //   149: dup_x2
    //   150: pop
    //   151: iconst_0
    //   152: istore #6
    //   154: dup2_x1
    //   155: pop2
    //   156: dup_x2
    //   157: iconst_1
    //   158: if_icmpgt -> 259
    //   161: dup2
    //   162: swap
    //   163: iload #6
    //   165: dup2_x1
    //   166: caload
    //   167: swap
    //   168: iload #6
    //   170: bipush #7
    //   172: irem
    //   173: tableswitch default -> 241, 0 -> 212, 1 -> 216, 2 -> 221, 3 -> 226, 4 -> 231, 5 -> 236
    //   212: iconst_4
    //   213: goto -> 243
    //   216: bipush #90
    //   218: goto -> 243
    //   221: bipush #117
    //   223: goto -> 243
    //   226: bipush #104
    //   228: goto -> 243
    //   231: bipush #24
    //   233: goto -> 243
    //   236: bipush #113
    //   238: goto -> 243
    //   241: bipush #88
    //   243: ixor
    //   244: ixor
    //   245: i2c
    //   246: castore
    //   247: iinc #6, 1
    //   250: dup
    //   251: ifne -> 259
    //   254: dup2
    //   255: dup_x1
    //   256: goto -> 165
    //   259: dup2_x1
    //   260: pop2
    //   261: dup_x2
    //   262: iload #6
    //   264: if_icmpgt -> 161
    //   267: pop
    //   268: new java/lang/String
    //   271: dup_x1
    //   272: swap
    //   273: invokespecial <init> : ([C)V
    //   276: invokevirtual intern : ()Ljava/lang/String;
    //   279: swap
    //   280: pop
    //   281: swap
    //   282: tableswitch default -> 39, 0 -> 98
    //   300: new java/math/BigInteger
    //   303: dup
    //   304: bipush #32
    //   306: newarray byte
    //   308: dup
    //   309: iconst_0
    //   310: bipush #38
    //   312: bastore
    //   313: dup
    //   314: iconst_1
    //   315: bipush #-8
    //   317: bastore
    //   318: dup
    //   319: iconst_2
    //   320: bipush #46
    //   322: bastore
    //   323: dup
    //   324: iconst_3
    //   325: bipush #91
    //   327: bastore
    //   328: dup
    //   329: iconst_4
    //   330: bipush #69
    //   332: bastore
    //   333: dup
    //   334: iconst_5
    //   335: bipush #103
    //   337: bastore
    //   338: dup
    //   339: bipush #6
    //   341: bipush #-97
    //   343: bastore
    //   344: dup
    //   345: bipush #7
    //   347: bipush #96
    //   349: bastore
    //   350: dup
    //   351: bipush #8
    //   353: bipush #49
    //   355: bastore
    //   356: dup
    //   357: bipush #9
    //   359: bipush #50
    //   361: bastore
    //   362: dup
    //   363: bipush #10
    //   365: bipush #54
    //   367: bastore
    //   368: dup
    //   369: bipush #11
    //   371: bipush #63
    //   373: bastore
    //   374: dup
    //   375: bipush #12
    //   377: bipush #-43
    //   379: bastore
    //   380: dup
    //   381: bipush #13
    //   383: bipush #-38
    //   385: bastore
    //   386: dup
    //   387: bipush #14
    //   389: bipush #123
    //   391: bastore
    //   392: dup
    //   393: bipush #15
    //   395: bipush #33
    //   397: bastore
    //   398: dup
    //   399: bipush #16
    //   401: bipush #-103
    //   403: bastore
    //   404: dup
    //   405: bipush #17
    //   407: bipush #64
    //   409: bastore
    //   410: dup
    //   411: bipush #18
    //   413: bipush #38
    //   415: bastore
    //   416: dup
    //   417: bipush #19
    //   419: bipush #74
    //   421: bastore
    //   422: dup
    //   423: bipush #20
    //   425: bipush #-16
    //   427: bastore
    //   428: dup
    //   429: bipush #21
    //   431: bipush #38
    //   433: bastore
    //   434: dup
    //   435: bipush #22
    //   437: bipush #-13
    //   439: bastore
    //   440: dup
    //   441: bipush #23
    //   443: bipush #90
    //   445: bastore
    //   446: dup
    //   447: bipush #24
    //   449: bipush #89
    //   451: bastore
    //   452: dup
    //   453: bipush #25
    //   455: bipush #68
    //   457: bastore
    //   458: dup
    //   459: bipush #26
    //   461: bipush #-78
    //   463: bastore
    //   464: dup
    //   465: bipush #27
    //   467: bipush #-5
    //   469: bastore
    //   470: dup
    //   471: bipush #28
    //   473: bipush #-80
    //   475: bastore
    //   476: dup
    //   477: bipush #29
    //   479: bipush #48
    //   481: bastore
    //   482: dup
    //   483: bipush #30
    //   485: bipush #-2
    //   487: bastore
    //   488: dup
    //   489: bipush #31
    //   491: bipush #-37
    //   493: bastore
    //   494: invokespecial <init> : ([B)V
    //   497: putstatic burp/Zb2p.ZQ : Ljava/lang/Object;
    //   500: sipush #11514
    //   503: sipush #-31724
    //   506: invokestatic a : (II)Ljava/lang/String;
    //   509: putstatic burp/Zb2p.ZV : Ljava/lang/String;
    //   512: return
  }
  
  private static Throwable a(Throwable paramThrowable) {
    return paramThrowable;
  }
  
  private static String a(int paramInt1, int paramInt2) {
    int i = (paramInt1 ^ 0x2CF5) & 0xFFFF;
    if (b[i] == null) {
      char[] arrayOfChar = a[i].toCharArray();
      switch (arrayOfChar[0] & 0xFF) {
        case 0:
        
        case 1:
        
        case 2:
        
        case 3:
        
        case 4:
        
        case 5:
        
        case 6:
        
        case 7:
        
        case 8:
        
        case 9:
        
        case 10:
        
        case 11:
        
        case 12:
        
        case 13:
        
        case 14:
        
        case 15:
        
        case 16:
        
        case 17:
        
        case 18:
        
        case 19:
        
        case 20:
        
        case 21:
        
        case 22:
        
        case 23:
        
        case 24:
        
        case 25:
        
        case 26:
        
        case 27:
        
        case 28:
        
        case 29:
        
        case 30:
        
        case 31:
        
        case 32:
        
        case 33:
        
        case 34:
        
        case 35:
        
        case 36:
        
        case 37:
        
        case 38:
        
        case 39:
        
        case 40:
        
        case 41:
        
        case 42:
        
        case 43:
        
        case 44:
        
        case 45:
        
        case 46:
        
        case 47:
        
        case 48:
        
        case 49:
        
        case 50:
        
        case 51:
        
        case 52:
        
        case 53:
        
        case 54:
        
        case 55:
        
        case 56:
        
        case 57:
        
        case 58:
        
        case 59:
        
        case 60:
        
        case 61:
        
        case 62:
        
        case 63:
        
        case 64:
        
        case 65:
        
        case 66:
        
        case 67:
        
        case 68:
        
        case 69:
        
        case 70:
        
        case 71:
        
        case 72:
        
        case 73:
        
        case 74:
        
        case 75:
        
        case 76:
        
        case 77:
        
        case 78:
        
        case 79:
        
        case 80:
        
        case 81:
        
        case 82:
        
        case 83:
        
        case 84:
        
        case 85:
        
        case 86:
        
        case 87:
        
        case 88:
        
        case 89:
        
        case 90:
        
        case 91:
        
        case 92:
        
        case 93:
        
        case 94:
        
        case 95:
        
        case 96:
        
        case 97:
        
        case 98:
        
        case 99:
        
        case 100:
        
        case 101:
        
        case 102:
        
        case 103:
        
        case 104:
        
        case 105:
        
        case 106:
        
        case 107:
        
        case 108:
        
        case 109:
        
        case 110:
        
        case 111:
        
        case 112:
        
        case 113:
        
        case 114:
        
        case 115:
        
        case 116:
        
        case 117:
        
        case 118:
        
        case 119:
        
        case 120:
        
        case 121:
        
        case 122:
        
        case 123:
        
        case 124:
        
        case 125:
        
        case 126:
        
        case 127:
        
        case 128:
        
        case 129:
        
        case 130:
        
        case 131:
        
        case 132:
        
        case 133:
        
        case 134:
        
        case 135:
        
        case 136:
        
        case 137:
        
        case 138:
        
        case 139:
        
        case 140:
        
        case 141:
        
        case 142:
        
        case 143:
        
        case 144:
        
        case 145:
        
        case 146:
        
        case 147:
        
        case 148:
        
        case 149:
        
        case 150:
        
        case 151:
        
        case 152:
        
        case 153:
        
        case 154:
        
        case 155:
        
        case 156:
        
        case 157:
        
        case 158:
        
        case 159:
        
        case 160:
        
        case 161:
        
        case 162:
        
        case 163:
        
        case 164:
        
        case 165:
        
        case 166:
        
        case 167:
        
        case 168:
        
        case 169:
        
        case 170:
        
        case 171:
        
        case 172:
        
        case 173:
        
        case 174:
        
        case 175:
        
        case 176:
        
        case 177:
        
        case 178:
        
        case 179:
        
        case 180:
        
        case 181:
        
        case 182:
        
        case 183:
        
        case 184:
        
        case 185:
        
        case 186:
        
        case 187:
        
        case 188:
        
        case 189:
        
        case 190:
        
        case 191:
        
        case 192:
        
        case 193:
        
        case 194:
        
        case 195:
        
        case 196:
        
        case 197:
        
        case 198:
        
        case 199:
        
        case 200:
        
        case 201:
        
        case 202:
        
        case 203:
        
        case 204:
        
        case 205:
        
        case 206:
        
        case 207:
        
        case 208:
        
        case 209:
        
        case 210:
        
        case 211:
        
        case 212:
        
        case 213:
        
        case 214:
        
        case 215:
        
        case 216:
        
        case 217:
        
        case 218:
        
        case 219:
        
        case 220:
        
        case 221:
        
        case 222:
        
        case 223:
        
        case 224:
        
        case 225:
        
        case 226:
        
        case 227:
        
        case 228:
        
        case 229:
        
        case 230:
        
        case 231:
        
        case 232:
        
        case 233:
        
        case 234:
        
        case 235:
        
        case 236:
        
        case 237:
        
        case 238:
        
        case 239:
        
        case 240:
        
        case 241:
        
        case 242:
        
        case 243:
        
        case 244:
        
        case 245:
        
        case 246:
        
        case 247:
        
        case 248:
        
        case 249:
        
        case 250:
        
        case 251:
        
        case 252:
        
        case 253:
        
        case 254:
        
        default:
          break;
      } 
      byte b1 = 27;
      int j = (paramInt2 & 0xFF) - b1;
      if (j < 0)
        j += 256; 
      int k = ((paramInt2 & 0xFFFF) >>> 8) - b1;
      if (k < 0)
        k += 256; 
      for (byte b2 = 0; b2 < arrayOfChar.length; b2++) {
        int m = b2 % 2;
        if (m == 0) {
          arrayOfChar[b2] = (char)(arrayOfChar[b2] ^ j);
          j = ((j >>> 3 | j << 5) ^ arrayOfChar[b2]) & 0xFF;
        } else {
          arrayOfChar[b2] = (char)(arrayOfChar[b2] ^ k);
          k = ((k >>> 3 | k << 5) ^ arrayOfChar[b2]) & 0xFF;
        } 
      } 
      b[i] = (new String(arrayOfChar)).intern();
    } 
    return b[i];
  }
}


/* Location:              C:\Program Files\BurpSuitePro\burpsuite_pro.jar!\burp\Zb2p.class
 * Java compiler version: 21 (65.0)
 * JD-Core Version:       1.1.3
 */