package burp;

import java.math.BigInteger;

class Zb38 extends ClassLoader {
  static Object ZC;
  
  static String Zr;
  
  private static final String[] a;
  
  private static final String[] b;
  
  static boolean ZW(Object[] paramArrayOfObject, Object paramObject) throws Throwable {
    // Byte code:
    //   0: invokestatic ZN : ()Z
    //   3: istore_2
    //   4: sipush #-32596
    //   7: sipush #-30400
    //   10: invokestatic a : (II)Ljava/lang/String;
    //   13: invokestatic forName : (Ljava/lang/String;)Ljava/lang/Class;
    //   16: invokestatic Zz : (Ljava/lang/Object;)V
    //   19: getstatic burp/Zmv9.Zw : Ljava/lang/Object;
    //   22: checkcast java/math/BigInteger
    //   25: invokevirtual toByteArray : ()[B
    //   28: astore_3
    //   29: bipush #32
    //   31: newarray int
    //   33: dup
    //   34: iconst_0
    //   35: ldc 876216579
    //   37: iastore
    //   38: dup
    //   39: iconst_1
    //   40: ldc 455999525
    //   42: iastore
    //   43: dup
    //   44: iconst_2
    //   45: ldc 1043334948
    //   47: iastore
    //   48: dup
    //   49: iconst_3
    //   50: ldc 439222784
    //   52: iastore
    //   53: dup
    //   54: iconst_4
    //   55: ldc 372376604
    //   57: iastore
    //   58: dup
    //   59: iconst_5
    //   60: ldc 707731490
    //   62: iastore
    //   63: dup
    //   64: bipush #6
    //   66: ldc 389426184
    //   68: iastore
    //   69: dup
    //   70: bipush #7
    //   72: ldc 973875457
    //   74: iastore
    //   75: dup
    //   76: bipush #8
    //   78: ldc 389160971
    //   80: iastore
    //   81: dup
    //   82: bipush #9
    //   84: ldc 907870729
    //   86: iastore
    //   87: dup
    //   88: bipush #10
    //   90: ldc 121057538
    //   92: iastore
    //   93: dup
    //   94: bipush #11
    //   96: ldc 840500228
    //   98: iastore
    //   99: dup
    //   100: bipush #12
    //   102: ldc 254150144
    //   104: iastore
    //   105: dup
    //   106: bipush #13
    //   108: ldc 924386310
    //   110: iastore
    //   111: dup
    //   112: bipush #14
    //   114: ldc 187632156
    //   116: iastore
    //   117: dup
    //   118: bipush #15
    //   120: ldc 874189824
    //   122: iastore
    //   123: dup
    //   124: bipush #16
    //   126: ldc 655302664
    //   128: iastore
    //   129: dup
    //   130: bipush #17
    //   132: ldc 890966315
    //   134: iastore
    //   135: dup
    //   136: bipush #18
    //   138: ldc 722417666
    //   140: iastore
    //   141: dup
    //   142: bipush #19
    //   144: ldc 1026621720
    //   146: iastore
    //   147: dup
    //   148: bipush #20
    //   150: ldc 957157408
    //   152: iastore
    //   153: dup
    //   154: bipush #21
    //   156: ldc 892536332
    //   158: iastore
    //   159: dup
    //   160: bipush #22
    //   162: ldc 689771012
    //   164: iastore
    //   165: dup
    //   166: bipush #23
    //   168: ldc 221709344
    //   170: iastore
    //   171: dup
    //   172: bipush #24
    //   174: ldc 940377620
    //   176: iastore
    //   177: dup
    //   178: bipush #25
    //   180: ldc 255209728
    //   182: iastore
    //   183: dup
    //   184: bipush #26
    //   186: ldc 1010368540
    //   188: iastore
    //   189: dup
    //   190: bipush #27
    //   192: ldc 220604441
    //   194: iastore
    //   195: dup
    //   196: bipush #28
    //   198: ldc 1008414755
    //   200: iastore
    //   201: dup
    //   202: bipush #29
    //   204: ldc 187049985
    //   206: iastore
    //   207: dup
    //   208: bipush #30
    //   210: ldc 943331329
    //   212: iastore
    //   213: dup
    //   214: bipush #31
    //   216: ldc 170788368
    //   218: iastore
    //   219: astore #5
    //   221: bipush #64
    //   223: newarray int
    //   225: dup
    //   226: iconst_0
    //   227: ldc 16843776
    //   229: iastore
    //   230: dup
    //   231: iconst_1
    //   232: iconst_0
    //   233: iastore
    //   234: dup
    //   235: iconst_2
    //   236: ldc 65536
    //   238: iastore
    //   239: dup
    //   240: iconst_3
    //   241: ldc 16843780
    //   243: iastore
    //   244: dup
    //   245: iconst_4
    //   246: ldc 16842756
    //   248: iastore
    //   249: dup
    //   250: iconst_5
    //   251: ldc 66564
    //   253: iastore
    //   254: dup
    //   255: bipush #6
    //   257: iconst_4
    //   258: iastore
    //   259: dup
    //   260: bipush #7
    //   262: ldc 65536
    //   264: iastore
    //   265: dup
    //   266: bipush #8
    //   268: sipush #1024
    //   271: iastore
    //   272: dup
    //   273: bipush #9
    //   275: ldc 16843776
    //   277: iastore
    //   278: dup
    //   279: bipush #10
    //   281: ldc 16843780
    //   283: iastore
    //   284: dup
    //   285: bipush #11
    //   287: sipush #1024
    //   290: iastore
    //   291: dup
    //   292: bipush #12
    //   294: ldc 16778244
    //   296: iastore
    //   297: dup
    //   298: bipush #13
    //   300: ldc 16842756
    //   302: iastore
    //   303: dup
    //   304: bipush #14
    //   306: ldc 16777216
    //   308: iastore
    //   309: dup
    //   310: bipush #15
    //   312: iconst_4
    //   313: iastore
    //   314: dup
    //   315: bipush #16
    //   317: sipush #1028
    //   320: iastore
    //   321: dup
    //   322: bipush #17
    //   324: ldc 16778240
    //   326: iastore
    //   327: dup
    //   328: bipush #18
    //   330: ldc 16778240
    //   332: iastore
    //   333: dup
    //   334: bipush #19
    //   336: ldc 66560
    //   338: iastore
    //   339: dup
    //   340: bipush #20
    //   342: ldc 66560
    //   344: iastore
    //   345: dup
    //   346: bipush #21
    //   348: ldc 16842752
    //   350: iastore
    //   351: dup
    //   352: bipush #22
    //   354: ldc 16842752
    //   356: iastore
    //   357: dup
    //   358: bipush #23
    //   360: ldc 16778244
    //   362: iastore
    //   363: dup
    //   364: bipush #24
    //   366: ldc 65540
    //   368: iastore
    //   369: dup
    //   370: bipush #25
    //   372: ldc 16777220
    //   374: iastore
    //   375: dup
    //   376: bipush #26
    //   378: ldc 16777220
    //   380: iastore
    //   381: dup
    //   382: bipush #27
    //   384: ldc 65540
    //   386: iastore
    //   387: dup
    //   388: bipush #28
    //   390: iconst_0
    //   391: iastore
    //   392: dup
    //   393: bipush #29
    //   395: sipush #1028
    //   398: iastore
    //   399: dup
    //   400: bipush #30
    //   402: ldc 66564
    //   404: iastore
    //   405: dup
    //   406: bipush #31
    //   408: ldc 16777216
    //   410: iastore
    //   411: dup
    //   412: bipush #32
    //   414: ldc 65536
    //   416: iastore
    //   417: dup
    //   418: bipush #33
    //   420: ldc 16843780
    //   422: iastore
    //   423: dup
    //   424: bipush #34
    //   426: iconst_4
    //   427: iastore
    //   428: dup
    //   429: bipush #35
    //   431: ldc 16842752
    //   433: iastore
    //   434: dup
    //   435: bipush #36
    //   437: ldc 16843776
    //   439: iastore
    //   440: dup
    //   441: bipush #37
    //   443: ldc 16777216
    //   445: iastore
    //   446: dup
    //   447: bipush #38
    //   449: ldc 16777216
    //   451: iastore
    //   452: dup
    //   453: bipush #39
    //   455: sipush #1024
    //   458: iastore
    //   459: dup
    //   460: bipush #40
    //   462: ldc 16842756
    //   464: iastore
    //   465: dup
    //   466: bipush #41
    //   468: ldc 65536
    //   470: iastore
    //   471: dup
    //   472: bipush #42
    //   474: ldc 66560
    //   476: iastore
    //   477: dup
    //   478: bipush #43
    //   480: ldc 16777220
    //   482: iastore
    //   483: dup
    //   484: bipush #44
    //   486: sipush #1024
    //   489: iastore
    //   490: dup
    //   491: bipush #45
    //   493: iconst_4
    //   494: iastore
    //   495: dup
    //   496: bipush #46
    //   498: ldc 16778244
    //   500: iastore
    //   501: dup
    //   502: bipush #47
    //   504: ldc 66564
    //   506: iastore
    //   507: dup
    //   508: bipush #48
    //   510: ldc 16843780
    //   512: iastore
    //   513: dup
    //   514: bipush #49
    //   516: ldc 65540
    //   518: iastore
    //   519: dup
    //   520: bipush #50
    //   522: ldc 16842752
    //   524: iastore
    //   525: dup
    //   526: bipush #51
    //   528: ldc 16778244
    //   530: iastore
    //   531: dup
    //   532: bipush #52
    //   534: ldc 16777220
    //   536: iastore
    //   537: dup
    //   538: bipush #53
    //   540: sipush #1028
    //   543: iastore
    //   544: dup
    //   545: bipush #54
    //   547: ldc 66564
    //   549: iastore
    //   550: dup
    //   551: bipush #55
    //   553: ldc 16843776
    //   555: iastore
    //   556: dup
    //   557: bipush #56
    //   559: sipush #1028
    //   562: iastore
    //   563: dup
    //   564: bipush #57
    //   566: ldc 16778240
    //   568: iastore
    //   569: dup
    //   570: bipush #58
    //   572: ldc 16778240
    //   574: iastore
    //   575: dup
    //   576: bipush #59
    //   578: iconst_0
    //   579: iastore
    //   580: dup
    //   581: bipush #60
    //   583: ldc 65540
    //   585: iastore
    //   586: dup
    //   587: bipush #61
    //   589: ldc 66560
    //   591: iastore
    //   592: dup
    //   593: bipush #62
    //   595: iconst_0
    //   596: iastore
    //   597: dup
    //   598: bipush #63
    //   600: ldc 16842756
    //   602: iastore
    //   603: astore #6
    //   605: bipush #64
    //   607: newarray int
    //   609: dup
    //   610: iconst_0
    //   611: ldc -2146402272
    //   613: iastore
    //   614: dup
    //   615: iconst_1
    //   616: ldc -2147450880
    //   618: iastore
    //   619: dup
    //   620: iconst_2
    //   621: ldc 32768
    //   623: iastore
    //   624: dup
    //   625: iconst_3
    //   626: ldc 1081376
    //   628: iastore
    //   629: dup
    //   630: iconst_4
    //   631: ldc 1048576
    //   633: iastore
    //   634: dup
    //   635: iconst_5
    //   636: bipush #32
    //   638: iastore
    //   639: dup
    //   640: bipush #6
    //   642: ldc -2146435040
    //   644: iastore
    //   645: dup
    //   646: bipush #7
    //   648: ldc -2147450848
    //   650: iastore
    //   651: dup
    //   652: bipush #8
    //   654: ldc -2147483616
    //   656: iastore
    //   657: dup
    //   658: bipush #9
    //   660: ldc -2146402272
    //   662: iastore
    //   663: dup
    //   664: bipush #10
    //   666: ldc -2146402304
    //   668: iastore
    //   669: dup
    //   670: bipush #11
    //   672: ldc -2147483648
    //   674: iastore
    //   675: dup
    //   676: bipush #12
    //   678: ldc -2147450880
    //   680: iastore
    //   681: dup
    //   682: bipush #13
    //   684: ldc 1048576
    //   686: iastore
    //   687: dup
    //   688: bipush #14
    //   690: bipush #32
    //   692: iastore
    //   693: dup
    //   694: bipush #15
    //   696: ldc -2146435040
    //   698: iastore
    //   699: dup
    //   700: bipush #16
    //   702: ldc 1081344
    //   704: iastore
    //   705: dup
    //   706: bipush #17
    //   708: ldc 1048608
    //   710: iastore
    //   711: dup
    //   712: bipush #18
    //   714: ldc -2147450848
    //   716: iastore
    //   717: dup
    //   718: bipush #19
    //   720: iconst_0
    //   721: iastore
    //   722: dup
    //   723: bipush #20
    //   725: ldc -2147483648
    //   727: iastore
    //   728: dup
    //   729: bipush #21
    //   731: ldc 32768
    //   733: iastore
    //   734: dup
    //   735: bipush #22
    //   737: ldc 1081376
    //   739: iastore
    //   740: dup
    //   741: bipush #23
    //   743: ldc -2146435072
    //   745: iastore
    //   746: dup
    //   747: bipush #24
    //   749: ldc 1048608
    //   751: iastore
    //   752: dup
    //   753: bipush #25
    //   755: ldc -2147483616
    //   757: iastore
    //   758: dup
    //   759: bipush #26
    //   761: iconst_0
    //   762: iastore
    //   763: dup
    //   764: bipush #27
    //   766: ldc 1081344
    //   768: iastore
    //   769: dup
    //   770: bipush #28
    //   772: ldc 32800
    //   774: iastore
    //   775: dup
    //   776: bipush #29
    //   778: ldc -2146402304
    //   780: iastore
    //   781: dup
    //   782: bipush #30
    //   784: ldc -2146435072
    //   786: iastore
    //   787: dup
    //   788: bipush #31
    //   790: ldc 32800
    //   792: iastore
    //   793: dup
    //   794: bipush #32
    //   796: iconst_0
    //   797: iastore
    //   798: dup
    //   799: bipush #33
    //   801: ldc 1081376
    //   803: iastore
    //   804: dup
    //   805: bipush #34
    //   807: ldc -2146435040
    //   809: iastore
    //   810: dup
    //   811: bipush #35
    //   813: ldc 1048576
    //   815: iastore
    //   816: dup
    //   817: bipush #36
    //   819: ldc -2147450848
    //   821: iastore
    //   822: dup
    //   823: bipush #37
    //   825: ldc -2146435072
    //   827: iastore
    //   828: dup
    //   829: bipush #38
    //   831: ldc -2146402304
    //   833: iastore
    //   834: dup
    //   835: bipush #39
    //   837: ldc 32768
    //   839: iastore
    //   840: dup
    //   841: bipush #40
    //   843: ldc -2146435072
    //   845: iastore
    //   846: dup
    //   847: bipush #41
    //   849: ldc -2147450880
    //   851: iastore
    //   852: dup
    //   853: bipush #42
    //   855: bipush #32
    //   857: iastore
    //   858: dup
    //   859: bipush #43
    //   861: ldc -2146402272
    //   863: iastore
    //   864: dup
    //   865: bipush #44
    //   867: ldc 1081376
    //   869: iastore
    //   870: dup
    //   871: bipush #45
    //   873: bipush #32
    //   875: iastore
    //   876: dup
    //   877: bipush #46
    //   879: ldc 32768
    //   881: iastore
    //   882: dup
    //   883: bipush #47
    //   885: ldc -2147483648
    //   887: iastore
    //   888: dup
    //   889: bipush #48
    //   891: ldc 32800
    //   893: iastore
    //   894: dup
    //   895: bipush #49
    //   897: ldc -2146402304
    //   899: iastore
    //   900: dup
    //   901: bipush #50
    //   903: ldc 1048576
    //   905: iastore
    //   906: dup
    //   907: bipush #51
    //   909: ldc -2147483616
    //   911: iastore
    //   912: dup
    //   913: bipush #52
    //   915: ldc 1048608
    //   917: iastore
    //   918: dup
    //   919: bipush #53
    //   921: ldc -2147450848
    //   923: iastore
    //   924: dup
    //   925: bipush #54
    //   927: ldc -2147483616
    //   929: iastore
    //   930: dup
    //   931: bipush #55
    //   933: ldc 1048608
    //   935: iastore
    //   936: dup
    //   937: bipush #56
    //   939: ldc 1081344
    //   941: iastore
    //   942: dup
    //   943: bipush #57
    //   945: iconst_0
    //   946: iastore
    //   947: dup
    //   948: bipush #58
    //   950: ldc -2147450880
    //   952: iastore
    //   953: dup
    //   954: bipush #59
    //   956: ldc 32800
    //   958: iastore
    //   959: dup
    //   960: bipush #60
    //   962: ldc -2147483648
    //   964: iastore
    //   965: dup
    //   966: bipush #61
    //   968: ldc -2146435040
    //   970: iastore
    //   971: dup
    //   972: bipush #62
    //   974: ldc -2146402272
    //   976: iastore
    //   977: dup
    //   978: bipush #63
    //   980: ldc 1081344
    //   982: iastore
    //   983: astore #7
    //   985: bipush #64
    //   987: newarray int
    //   989: dup
    //   990: iconst_0
    //   991: sipush #520
    //   994: iastore
    //   995: dup
    //   996: iconst_1
    //   997: ldc 134349312
    //   999: iastore
    //   1000: dup
    //   1001: iconst_2
    //   1002: iconst_0
    //   1003: iastore
    //   1004: dup
    //   1005: iconst_3
    //   1006: ldc 134348808
    //   1008: iastore
    //   1009: dup
    //   1010: iconst_4
    //   1011: ldc 134218240
    //   1013: iastore
    //   1014: dup
    //   1015: iconst_5
    //   1016: iconst_0
    //   1017: iastore
    //   1018: dup
    //   1019: bipush #6
    //   1021: ldc 131592
    //   1023: iastore
    //   1024: dup
    //   1025: bipush #7
    //   1027: ldc 134218240
    //   1029: iastore
    //   1030: dup
    //   1031: bipush #8
    //   1033: ldc 131080
    //   1035: iastore
    //   1036: dup
    //   1037: bipush #9
    //   1039: ldc 134217736
    //   1041: iastore
    //   1042: dup
    //   1043: bipush #10
    //   1045: ldc 134217736
    //   1047: iastore
    //   1048: dup
    //   1049: bipush #11
    //   1051: ldc 131072
    //   1053: iastore
    //   1054: dup
    //   1055: bipush #12
    //   1057: ldc 134349320
    //   1059: iastore
    //   1060: dup
    //   1061: bipush #13
    //   1063: ldc 131080
    //   1065: iastore
    //   1066: dup
    //   1067: bipush #14
    //   1069: ldc 134348800
    //   1071: iastore
    //   1072: dup
    //   1073: bipush #15
    //   1075: sipush #520
    //   1078: iastore
    //   1079: dup
    //   1080: bipush #16
    //   1082: ldc 134217728
    //   1084: iastore
    //   1085: dup
    //   1086: bipush #17
    //   1088: bipush #8
    //   1090: iastore
    //   1091: dup
    //   1092: bipush #18
    //   1094: ldc 134349312
    //   1096: iastore
    //   1097: dup
    //   1098: bipush #19
    //   1100: sipush #512
    //   1103: iastore
    //   1104: dup
    //   1105: bipush #20
    //   1107: ldc 131584
    //   1109: iastore
    //   1110: dup
    //   1111: bipush #21
    //   1113: ldc 134348800
    //   1115: iastore
    //   1116: dup
    //   1117: bipush #22
    //   1119: ldc 134348808
    //   1121: iastore
    //   1122: dup
    //   1123: bipush #23
    //   1125: ldc 131592
    //   1127: iastore
    //   1128: dup
    //   1129: bipush #24
    //   1131: ldc 134218248
    //   1133: iastore
    //   1134: dup
    //   1135: bipush #25
    //   1137: ldc 131584
    //   1139: iastore
    //   1140: dup
    //   1141: bipush #26
    //   1143: ldc 131072
    //   1145: iastore
    //   1146: dup
    //   1147: bipush #27
    //   1149: ldc 134218248
    //   1151: iastore
    //   1152: dup
    //   1153: bipush #28
    //   1155: bipush #8
    //   1157: iastore
    //   1158: dup
    //   1159: bipush #29
    //   1161: ldc 134349320
    //   1163: iastore
    //   1164: dup
    //   1165: bipush #30
    //   1167: sipush #512
    //   1170: iastore
    //   1171: dup
    //   1172: bipush #31
    //   1174: ldc 134217728
    //   1176: iastore
    //   1177: dup
    //   1178: bipush #32
    //   1180: ldc 134349312
    //   1182: iastore
    //   1183: dup
    //   1184: bipush #33
    //   1186: ldc 134217728
    //   1188: iastore
    //   1189: dup
    //   1190: bipush #34
    //   1192: ldc 131080
    //   1194: iastore
    //   1195: dup
    //   1196: bipush #35
    //   1198: sipush #520
    //   1201: iastore
    //   1202: dup
    //   1203: bipush #36
    //   1205: ldc 131072
    //   1207: iastore
    //   1208: dup
    //   1209: bipush #37
    //   1211: ldc 134349312
    //   1213: iastore
    //   1214: dup
    //   1215: bipush #38
    //   1217: ldc 134218240
    //   1219: iastore
    //   1220: dup
    //   1221: bipush #39
    //   1223: iconst_0
    //   1224: iastore
    //   1225: dup
    //   1226: bipush #40
    //   1228: sipush #512
    //   1231: iastore
    //   1232: dup
    //   1233: bipush #41
    //   1235: ldc 131080
    //   1237: iastore
    //   1238: dup
    //   1239: bipush #42
    //   1241: ldc 134349320
    //   1243: iastore
    //   1244: dup
    //   1245: bipush #43
    //   1247: ldc 134218240
    //   1249: iastore
    //   1250: dup
    //   1251: bipush #44
    //   1253: ldc 134217736
    //   1255: iastore
    //   1256: dup
    //   1257: bipush #45
    //   1259: sipush #512
    //   1262: iastore
    //   1263: dup
    //   1264: bipush #46
    //   1266: iconst_0
    //   1267: iastore
    //   1268: dup
    //   1269: bipush #47
    //   1271: ldc 134348808
    //   1273: iastore
    //   1274: dup
    //   1275: bipush #48
    //   1277: ldc 134218248
    //   1279: iastore
    //   1280: dup
    //   1281: bipush #49
    //   1283: ldc 131072
    //   1285: iastore
    //   1286: dup
    //   1287: bipush #50
    //   1289: ldc 134217728
    //   1291: iastore
    //   1292: dup
    //   1293: bipush #51
    //   1295: ldc 134349320
    //   1297: iastore
    //   1298: dup
    //   1299: bipush #52
    //   1301: bipush #8
    //   1303: iastore
    //   1304: dup
    //   1305: bipush #53
    //   1307: ldc 131592
    //   1309: iastore
    //   1310: dup
    //   1311: bipush #54
    //   1313: ldc 131584
    //   1315: iastore
    //   1316: dup
    //   1317: bipush #55
    //   1319: ldc 134217736
    //   1321: iastore
    //   1322: dup
    //   1323: bipush #56
    //   1325: ldc 134348800
    //   1327: iastore
    //   1328: dup
    //   1329: bipush #57
    //   1331: ldc 134218248
    //   1333: iastore
    //   1334: dup
    //   1335: bipush #58
    //   1337: sipush #520
    //   1340: iastore
    //   1341: dup
    //   1342: bipush #59
    //   1344: ldc 134348800
    //   1346: iastore
    //   1347: dup
    //   1348: bipush #60
    //   1350: ldc 131592
    //   1352: iastore
    //   1353: dup
    //   1354: bipush #61
    //   1356: bipush #8
    //   1358: iastore
    //   1359: dup
    //   1360: bipush #62
    //   1362: ldc 134348808
    //   1364: iastore
    //   1365: dup
    //   1366: bipush #63
    //   1368: ldc 131584
    //   1370: iastore
    //   1371: astore #8
    //   1373: bipush #64
    //   1375: newarray int
    //   1377: dup
    //   1378: iconst_0
    //   1379: ldc 8396801
    //   1381: iastore
    //   1382: dup
    //   1383: iconst_1
    //   1384: sipush #8321
    //   1387: iastore
    //   1388: dup
    //   1389: iconst_2
    //   1390: sipush #8321
    //   1393: iastore
    //   1394: dup
    //   1395: iconst_3
    //   1396: sipush #128
    //   1399: iastore
    //   1400: dup
    //   1401: iconst_4
    //   1402: ldc 8396928
    //   1404: iastore
    //   1405: dup
    //   1406: iconst_5
    //   1407: ldc 8388737
    //   1409: iastore
    //   1410: dup
    //   1411: bipush #6
    //   1413: ldc 8388609
    //   1415: iastore
    //   1416: dup
    //   1417: bipush #7
    //   1419: sipush #8193
    //   1422: iastore
    //   1423: dup
    //   1424: bipush #8
    //   1426: iconst_0
    //   1427: iastore
    //   1428: dup
    //   1429: bipush #9
    //   1431: ldc 8396800
    //   1433: iastore
    //   1434: dup
    //   1435: bipush #10
    //   1437: ldc 8396800
    //   1439: iastore
    //   1440: dup
    //   1441: bipush #11
    //   1443: ldc 8396929
    //   1445: iastore
    //   1446: dup
    //   1447: bipush #12
    //   1449: sipush #129
    //   1452: iastore
    //   1453: dup
    //   1454: bipush #13
    //   1456: iconst_0
    //   1457: iastore
    //   1458: dup
    //   1459: bipush #14
    //   1461: ldc 8388736
    //   1463: iastore
    //   1464: dup
    //   1465: bipush #15
    //   1467: ldc 8388609
    //   1469: iastore
    //   1470: dup
    //   1471: bipush #16
    //   1473: iconst_1
    //   1474: iastore
    //   1475: dup
    //   1476: bipush #17
    //   1478: sipush #8192
    //   1481: iastore
    //   1482: dup
    //   1483: bipush #18
    //   1485: ldc 8388608
    //   1487: iastore
    //   1488: dup
    //   1489: bipush #19
    //   1491: ldc 8396801
    //   1493: iastore
    //   1494: dup
    //   1495: bipush #20
    //   1497: sipush #128
    //   1500: iastore
    //   1501: dup
    //   1502: bipush #21
    //   1504: ldc 8388608
    //   1506: iastore
    //   1507: dup
    //   1508: bipush #22
    //   1510: sipush #8193
    //   1513: iastore
    //   1514: dup
    //   1515: bipush #23
    //   1517: sipush #8320
    //   1520: iastore
    //   1521: dup
    //   1522: bipush #24
    //   1524: ldc 8388737
    //   1526: iastore
    //   1527: dup
    //   1528: bipush #25
    //   1530: iconst_1
    //   1531: iastore
    //   1532: dup
    //   1533: bipush #26
    //   1535: sipush #8320
    //   1538: iastore
    //   1539: dup
    //   1540: bipush #27
    //   1542: ldc 8388736
    //   1544: iastore
    //   1545: dup
    //   1546: bipush #28
    //   1548: sipush #8192
    //   1551: iastore
    //   1552: dup
    //   1553: bipush #29
    //   1555: ldc 8396928
    //   1557: iastore
    //   1558: dup
    //   1559: bipush #30
    //   1561: ldc 8396929
    //   1563: iastore
    //   1564: dup
    //   1565: bipush #31
    //   1567: sipush #129
    //   1570: iastore
    //   1571: dup
    //   1572: bipush #32
    //   1574: ldc 8388736
    //   1576: iastore
    //   1577: dup
    //   1578: bipush #33
    //   1580: ldc 8388609
    //   1582: iastore
    //   1583: dup
    //   1584: bipush #34
    //   1586: ldc 8396800
    //   1588: iastore
    //   1589: dup
    //   1590: bipush #35
    //   1592: ldc 8396929
    //   1594: iastore
    //   1595: dup
    //   1596: bipush #36
    //   1598: sipush #129
    //   1601: iastore
    //   1602: dup
    //   1603: bipush #37
    //   1605: iconst_0
    //   1606: iastore
    //   1607: dup
    //   1608: bipush #38
    //   1610: iconst_0
    //   1611: iastore
    //   1612: dup
    //   1613: bipush #39
    //   1615: ldc 8396800
    //   1617: iastore
    //   1618: dup
    //   1619: bipush #40
    //   1621: sipush #8320
    //   1624: iastore
    //   1625: dup
    //   1626: bipush #41
    //   1628: ldc 8388736
    //   1630: iastore
    //   1631: dup
    //   1632: bipush #42
    //   1634: ldc 8388737
    //   1636: iastore
    //   1637: dup
    //   1638: bipush #43
    //   1640: iconst_1
    //   1641: iastore
    //   1642: dup
    //   1643: bipush #44
    //   1645: ldc 8396801
    //   1647: iastore
    //   1648: dup
    //   1649: bipush #45
    //   1651: sipush #8321
    //   1654: iastore
    //   1655: dup
    //   1656: bipush #46
    //   1658: sipush #8321
    //   1661: iastore
    //   1662: dup
    //   1663: bipush #47
    //   1665: sipush #128
    //   1668: iastore
    //   1669: dup
    //   1670: bipush #48
    //   1672: ldc 8396929
    //   1674: iastore
    //   1675: dup
    //   1676: bipush #49
    //   1678: sipush #129
    //   1681: iastore
    //   1682: dup
    //   1683: bipush #50
    //   1685: iconst_1
    //   1686: iastore
    //   1687: dup
    //   1688: bipush #51
    //   1690: sipush #8192
    //   1693: iastore
    //   1694: dup
    //   1695: bipush #52
    //   1697: ldc 8388609
    //   1699: iastore
    //   1700: dup
    //   1701: bipush #53
    //   1703: sipush #8193
    //   1706: iastore
    //   1707: dup
    //   1708: bipush #54
    //   1710: ldc 8396928
    //   1712: iastore
    //   1713: dup
    //   1714: bipush #55
    //   1716: ldc 8388737
    //   1718: iastore
    //   1719: dup
    //   1720: bipush #56
    //   1722: sipush #8193
    //   1725: iastore
    //   1726: dup
    //   1727: bipush #57
    //   1729: sipush #8320
    //   1732: iastore
    //   1733: dup
    //   1734: bipush #58
    //   1736: ldc 8388608
    //   1738: iastore
    //   1739: dup
    //   1740: bipush #59
    //   1742: ldc 8396801
    //   1744: iastore
    //   1745: dup
    //   1746: bipush #60
    //   1748: sipush #128
    //   1751: iastore
    //   1752: dup
    //   1753: bipush #61
    //   1755: ldc 8388608
    //   1757: iastore
    //   1758: dup
    //   1759: bipush #62
    //   1761: sipush #8192
    //   1764: iastore
    //   1765: dup
    //   1766: bipush #63
    //   1768: ldc 8396928
    //   1770: iastore
    //   1771: astore #9
    //   1773: bipush #64
    //   1775: newarray int
    //   1777: dup
    //   1778: iconst_0
    //   1779: sipush #256
    //   1782: iastore
    //   1783: dup
    //   1784: iconst_1
    //   1785: ldc 34078976
    //   1787: iastore
    //   1788: dup
    //   1789: iconst_2
    //   1790: ldc 34078720
    //   1792: iastore
    //   1793: dup
    //   1794: iconst_3
    //   1795: ldc 1107296512
    //   1797: iastore
    //   1798: dup
    //   1799: iconst_4
    //   1800: ldc 524288
    //   1802: iastore
    //   1803: dup
    //   1804: iconst_5
    //   1805: sipush #256
    //   1808: iastore
    //   1809: dup
    //   1810: bipush #6
    //   1812: ldc 1073741824
    //   1814: iastore
    //   1815: dup
    //   1816: bipush #7
    //   1818: ldc 34078720
    //   1820: iastore
    //   1821: dup
    //   1822: bipush #8
    //   1824: ldc 1074266368
    //   1826: iastore
    //   1827: dup
    //   1828: bipush #9
    //   1830: ldc 524288
    //   1832: iastore
    //   1833: dup
    //   1834: bipush #10
    //   1836: ldc 33554688
    //   1838: iastore
    //   1839: dup
    //   1840: bipush #11
    //   1842: ldc 1074266368
    //   1844: iastore
    //   1845: dup
    //   1846: bipush #12
    //   1848: ldc 1107296512
    //   1850: iastore
    //   1851: dup
    //   1852: bipush #13
    //   1854: ldc 1107820544
    //   1856: iastore
    //   1857: dup
    //   1858: bipush #14
    //   1860: ldc 524544
    //   1862: iastore
    //   1863: dup
    //   1864: bipush #15
    //   1866: ldc 1073741824
    //   1868: iastore
    //   1869: dup
    //   1870: bipush #16
    //   1872: ldc 33554432
    //   1874: iastore
    //   1875: dup
    //   1876: bipush #17
    //   1878: ldc 1074266112
    //   1880: iastore
    //   1881: dup
    //   1882: bipush #18
    //   1884: ldc 1074266112
    //   1886: iastore
    //   1887: dup
    //   1888: bipush #19
    //   1890: iconst_0
    //   1891: iastore
    //   1892: dup
    //   1893: bipush #20
    //   1895: ldc 1073742080
    //   1897: iastore
    //   1898: dup
    //   1899: bipush #21
    //   1901: ldc 1107820800
    //   1903: iastore
    //   1904: dup
    //   1905: bipush #22
    //   1907: ldc 1107820800
    //   1909: iastore
    //   1910: dup
    //   1911: bipush #23
    //   1913: ldc 33554688
    //   1915: iastore
    //   1916: dup
    //   1917: bipush #24
    //   1919: ldc 1107820544
    //   1921: iastore
    //   1922: dup
    //   1923: bipush #25
    //   1925: ldc 1073742080
    //   1927: iastore
    //   1928: dup
    //   1929: bipush #26
    //   1931: iconst_0
    //   1932: iastore
    //   1933: dup
    //   1934: bipush #27
    //   1936: ldc 1107296256
    //   1938: iastore
    //   1939: dup
    //   1940: bipush #28
    //   1942: ldc 34078976
    //   1944: iastore
    //   1945: dup
    //   1946: bipush #29
    //   1948: ldc 33554432
    //   1950: iastore
    //   1951: dup
    //   1952: bipush #30
    //   1954: ldc 1107296256
    //   1956: iastore
    //   1957: dup
    //   1958: bipush #31
    //   1960: ldc 524544
    //   1962: iastore
    //   1963: dup
    //   1964: bipush #32
    //   1966: ldc 524288
    //   1968: iastore
    //   1969: dup
    //   1970: bipush #33
    //   1972: ldc 1107296512
    //   1974: iastore
    //   1975: dup
    //   1976: bipush #34
    //   1978: sipush #256
    //   1981: iastore
    //   1982: dup
    //   1983: bipush #35
    //   1985: ldc 33554432
    //   1987: iastore
    //   1988: dup
    //   1989: bipush #36
    //   1991: ldc 1073741824
    //   1993: iastore
    //   1994: dup
    //   1995: bipush #37
    //   1997: ldc 34078720
    //   1999: iastore
    //   2000: dup
    //   2001: bipush #38
    //   2003: ldc 1107296512
    //   2005: iastore
    //   2006: dup
    //   2007: bipush #39
    //   2009: ldc 1074266368
    //   2011: iastore
    //   2012: dup
    //   2013: bipush #40
    //   2015: ldc 33554688
    //   2017: iastore
    //   2018: dup
    //   2019: bipush #41
    //   2021: ldc 1073741824
    //   2023: iastore
    //   2024: dup
    //   2025: bipush #42
    //   2027: ldc 1107820544
    //   2029: iastore
    //   2030: dup
    //   2031: bipush #43
    //   2033: ldc 34078976
    //   2035: iastore
    //   2036: dup
    //   2037: bipush #44
    //   2039: ldc 1074266368
    //   2041: iastore
    //   2042: dup
    //   2043: bipush #45
    //   2045: sipush #256
    //   2048: iastore
    //   2049: dup
    //   2050: bipush #46
    //   2052: ldc 33554432
    //   2054: iastore
    //   2055: dup
    //   2056: bipush #47
    //   2058: ldc 1107820544
    //   2060: iastore
    //   2061: dup
    //   2062: bipush #48
    //   2064: ldc 1107820800
    //   2066: iastore
    //   2067: dup
    //   2068: bipush #49
    //   2070: ldc 524544
    //   2072: iastore
    //   2073: dup
    //   2074: bipush #50
    //   2076: ldc 1107296256
    //   2078: iastore
    //   2079: dup
    //   2080: bipush #51
    //   2082: ldc 1107820800
    //   2084: iastore
    //   2085: dup
    //   2086: bipush #52
    //   2088: ldc 34078720
    //   2090: iastore
    //   2091: dup
    //   2092: bipush #53
    //   2094: iconst_0
    //   2095: iastore
    //   2096: dup
    //   2097: bipush #54
    //   2099: ldc 1074266112
    //   2101: iastore
    //   2102: dup
    //   2103: bipush #55
    //   2105: ldc 1107296256
    //   2107: iastore
    //   2108: dup
    //   2109: bipush #56
    //   2111: ldc 524544
    //   2113: iastore
    //   2114: dup
    //   2115: bipush #57
    //   2117: ldc 33554688
    //   2119: iastore
    //   2120: dup
    //   2121: bipush #58
    //   2123: ldc 1073742080
    //   2125: iastore
    //   2126: dup
    //   2127: bipush #59
    //   2129: ldc 524288
    //   2131: iastore
    //   2132: dup
    //   2133: bipush #60
    //   2135: iconst_0
    //   2136: iastore
    //   2137: dup
    //   2138: bipush #61
    //   2140: ldc 1074266112
    //   2142: iastore
    //   2143: dup
    //   2144: bipush #62
    //   2146: ldc 34078976
    //   2148: iastore
    //   2149: dup
    //   2150: bipush #63
    //   2152: ldc 1073742080
    //   2154: iastore
    //   2155: astore #10
    //   2157: bipush #64
    //   2159: newarray int
    //   2161: dup
    //   2162: iconst_0
    //   2163: ldc 536870928
    //   2165: iastore
    //   2166: dup
    //   2167: iconst_1
    //   2168: ldc 541065216
    //   2170: iastore
    //   2171: dup
    //   2172: iconst_2
    //   2173: sipush #16384
    //   2176: iastore
    //   2177: dup
    //   2178: iconst_3
    //   2179: ldc 541081616
    //   2181: iastore
    //   2182: dup
    //   2183: iconst_4
    //   2184: ldc 541065216
    //   2186: iastore
    //   2187: dup
    //   2188: iconst_5
    //   2189: bipush #16
    //   2191: iastore
    //   2192: dup
    //   2193: bipush #6
    //   2195: ldc 541081616
    //   2197: iastore
    //   2198: dup
    //   2199: bipush #7
    //   2201: ldc 4194304
    //   2203: iastore
    //   2204: dup
    //   2205: bipush #8
    //   2207: ldc 536887296
    //   2209: iastore
    //   2210: dup
    //   2211: bipush #9
    //   2213: ldc 4210704
    //   2215: iastore
    //   2216: dup
    //   2217: bipush #10
    //   2219: ldc 4194304
    //   2221: iastore
    //   2222: dup
    //   2223: bipush #11
    //   2225: ldc 536870928
    //   2227: iastore
    //   2228: dup
    //   2229: bipush #12
    //   2231: ldc 4194320
    //   2233: iastore
    //   2234: dup
    //   2235: bipush #13
    //   2237: ldc 536887296
    //   2239: iastore
    //   2240: dup
    //   2241: bipush #14
    //   2243: ldc 536870912
    //   2245: iastore
    //   2246: dup
    //   2247: bipush #15
    //   2249: sipush #16400
    //   2252: iastore
    //   2253: dup
    //   2254: bipush #16
    //   2256: iconst_0
    //   2257: iastore
    //   2258: dup
    //   2259: bipush #17
    //   2261: ldc 4194320
    //   2263: iastore
    //   2264: dup
    //   2265: bipush #18
    //   2267: ldc 536887312
    //   2269: iastore
    //   2270: dup
    //   2271: bipush #19
    //   2273: sipush #16384
    //   2276: iastore
    //   2277: dup
    //   2278: bipush #20
    //   2280: ldc 4210688
    //   2282: iastore
    //   2283: dup
    //   2284: bipush #21
    //   2286: ldc 536887312
    //   2288: iastore
    //   2289: dup
    //   2290: bipush #22
    //   2292: bipush #16
    //   2294: iastore
    //   2295: dup
    //   2296: bipush #23
    //   2298: ldc 541065232
    //   2300: iastore
    //   2301: dup
    //   2302: bipush #24
    //   2304: ldc 541065232
    //   2306: iastore
    //   2307: dup
    //   2308: bipush #25
    //   2310: iconst_0
    //   2311: iastore
    //   2312: dup
    //   2313: bipush #26
    //   2315: ldc 4210704
    //   2317: iastore
    //   2318: dup
    //   2319: bipush #27
    //   2321: ldc 541081600
    //   2323: iastore
    //   2324: dup
    //   2325: bipush #28
    //   2327: sipush #16400
    //   2330: iastore
    //   2331: dup
    //   2332: bipush #29
    //   2334: ldc 4210688
    //   2336: iastore
    //   2337: dup
    //   2338: bipush #30
    //   2340: ldc 541081600
    //   2342: iastore
    //   2343: dup
    //   2344: bipush #31
    //   2346: ldc 536870912
    //   2348: iastore
    //   2349: dup
    //   2350: bipush #32
    //   2352: ldc 536887296
    //   2354: iastore
    //   2355: dup
    //   2356: bipush #33
    //   2358: bipush #16
    //   2360: iastore
    //   2361: dup
    //   2362: bipush #34
    //   2364: ldc 541065232
    //   2366: iastore
    //   2367: dup
    //   2368: bipush #35
    //   2370: ldc 4210688
    //   2372: iastore
    //   2373: dup
    //   2374: bipush #36
    //   2376: ldc 541081616
    //   2378: iastore
    //   2379: dup
    //   2380: bipush #37
    //   2382: ldc 4194304
    //   2384: iastore
    //   2385: dup
    //   2386: bipush #38
    //   2388: sipush #16400
    //   2391: iastore
    //   2392: dup
    //   2393: bipush #39
    //   2395: ldc 536870928
    //   2397: iastore
    //   2398: dup
    //   2399: bipush #40
    //   2401: ldc 4194304
    //   2403: iastore
    //   2404: dup
    //   2405: bipush #41
    //   2407: ldc 536887296
    //   2409: iastore
    //   2410: dup
    //   2411: bipush #42
    //   2413: ldc 536870912
    //   2415: iastore
    //   2416: dup
    //   2417: bipush #43
    //   2419: sipush #16400
    //   2422: iastore
    //   2423: dup
    //   2424: bipush #44
    //   2426: ldc 536870928
    //   2428: iastore
    //   2429: dup
    //   2430: bipush #45
    //   2432: ldc 541081616
    //   2434: iastore
    //   2435: dup
    //   2436: bipush #46
    //   2438: ldc 4210688
    //   2440: iastore
    //   2441: dup
    //   2442: bipush #47
    //   2444: ldc 541065216
    //   2446: iastore
    //   2447: dup
    //   2448: bipush #48
    //   2450: ldc 4210704
    //   2452: iastore
    //   2453: dup
    //   2454: bipush #49
    //   2456: ldc 541081600
    //   2458: iastore
    //   2459: dup
    //   2460: bipush #50
    //   2462: iconst_0
    //   2463: iastore
    //   2464: dup
    //   2465: bipush #51
    //   2467: ldc 541065232
    //   2469: iastore
    //   2470: dup
    //   2471: bipush #52
    //   2473: bipush #16
    //   2475: iastore
    //   2476: dup
    //   2477: bipush #53
    //   2479: sipush #16384
    //   2482: iastore
    //   2483: dup
    //   2484: bipush #54
    //   2486: ldc 541065216
    //   2488: iastore
    //   2489: dup
    //   2490: bipush #55
    //   2492: ldc 4210704
    //   2494: iastore
    //   2495: dup
    //   2496: bipush #56
    //   2498: sipush #16384
    //   2501: iastore
    //   2502: dup
    //   2503: bipush #57
    //   2505: ldc 4194320
    //   2507: iastore
    //   2508: dup
    //   2509: bipush #58
    //   2511: ldc 536887312
    //   2513: iastore
    //   2514: dup
    //   2515: bipush #59
    //   2517: iconst_0
    //   2518: iastore
    //   2519: dup
    //   2520: bipush #60
    //   2522: ldc 541081600
    //   2524: iastore
    //   2525: dup
    //   2526: bipush #61
    //   2528: ldc 536870912
    //   2530: iastore
    //   2531: dup
    //   2532: bipush #62
    //   2534: ldc 4194320
    //   2536: iastore
    //   2537: dup
    //   2538: bipush #63
    //   2540: ldc 536887312
    //   2542: iastore
    //   2543: astore #11
    //   2545: bipush #64
    //   2547: newarray int
    //   2549: dup
    //   2550: iconst_0
    //   2551: ldc 2097152
    //   2553: iastore
    //   2554: dup
    //   2555: iconst_1
    //   2556: ldc 69206018
    //   2558: iastore
    //   2559: dup
    //   2560: iconst_2
    //   2561: ldc 67110914
    //   2563: iastore
    //   2564: dup
    //   2565: iconst_3
    //   2566: iconst_0
    //   2567: iastore
    //   2568: dup
    //   2569: iconst_4
    //   2570: sipush #2048
    //   2573: iastore
    //   2574: dup
    //   2575: iconst_5
    //   2576: ldc 67110914
    //   2578: iastore
    //   2579: dup
    //   2580: bipush #6
    //   2582: ldc 2099202
    //   2584: iastore
    //   2585: dup
    //   2586: bipush #7
    //   2588: ldc 69208064
    //   2590: iastore
    //   2591: dup
    //   2592: bipush #8
    //   2594: ldc 69208066
    //   2596: iastore
    //   2597: dup
    //   2598: bipush #9
    //   2600: ldc 2097152
    //   2602: iastore
    //   2603: dup
    //   2604: bipush #10
    //   2606: iconst_0
    //   2607: iastore
    //   2608: dup
    //   2609: bipush #11
    //   2611: ldc 67108866
    //   2613: iastore
    //   2614: dup
    //   2615: bipush #12
    //   2617: iconst_2
    //   2618: iastore
    //   2619: dup
    //   2620: bipush #13
    //   2622: ldc 67108864
    //   2624: iastore
    //   2625: dup
    //   2626: bipush #14
    //   2628: ldc 69206018
    //   2630: iastore
    //   2631: dup
    //   2632: bipush #15
    //   2634: sipush #2050
    //   2637: iastore
    //   2638: dup
    //   2639: bipush #16
    //   2641: ldc 67110912
    //   2643: iastore
    //   2644: dup
    //   2645: bipush #17
    //   2647: ldc 2099202
    //   2649: iastore
    //   2650: dup
    //   2651: bipush #18
    //   2653: ldc 2097154
    //   2655: iastore
    //   2656: dup
    //   2657: bipush #19
    //   2659: ldc 67110912
    //   2661: iastore
    //   2662: dup
    //   2663: bipush #20
    //   2665: ldc 67108866
    //   2667: iastore
    //   2668: dup
    //   2669: bipush #21
    //   2671: ldc 69206016
    //   2673: iastore
    //   2674: dup
    //   2675: bipush #22
    //   2677: ldc 69208064
    //   2679: iastore
    //   2680: dup
    //   2681: bipush #23
    //   2683: ldc 2097154
    //   2685: iastore
    //   2686: dup
    //   2687: bipush #24
    //   2689: ldc 69206016
    //   2691: iastore
    //   2692: dup
    //   2693: bipush #25
    //   2695: sipush #2048
    //   2698: iastore
    //   2699: dup
    //   2700: bipush #26
    //   2702: sipush #2050
    //   2705: iastore
    //   2706: dup
    //   2707: bipush #27
    //   2709: ldc 69208066
    //   2711: iastore
    //   2712: dup
    //   2713: bipush #28
    //   2715: ldc 2099200
    //   2717: iastore
    //   2718: dup
    //   2719: bipush #29
    //   2721: iconst_2
    //   2722: iastore
    //   2723: dup
    //   2724: bipush #30
    //   2726: ldc 67108864
    //   2728: iastore
    //   2729: dup
    //   2730: bipush #31
    //   2732: ldc 2099200
    //   2734: iastore
    //   2735: dup
    //   2736: bipush #32
    //   2738: ldc 67108864
    //   2740: iastore
    //   2741: dup
    //   2742: bipush #33
    //   2744: ldc 2099200
    //   2746: iastore
    //   2747: dup
    //   2748: bipush #34
    //   2750: ldc 2097152
    //   2752: iastore
    //   2753: dup
    //   2754: bipush #35
    //   2756: ldc 67110914
    //   2758: iastore
    //   2759: dup
    //   2760: bipush #36
    //   2762: ldc 67110914
    //   2764: iastore
    //   2765: dup
    //   2766: bipush #37
    //   2768: ldc 69206018
    //   2770: iastore
    //   2771: dup
    //   2772: bipush #38
    //   2774: ldc 69206018
    //   2776: iastore
    //   2777: dup
    //   2778: bipush #39
    //   2780: iconst_2
    //   2781: iastore
    //   2782: dup
    //   2783: bipush #40
    //   2785: ldc 2097154
    //   2787: iastore
    //   2788: dup
    //   2789: bipush #41
    //   2791: ldc 67108864
    //   2793: iastore
    //   2794: dup
    //   2795: bipush #42
    //   2797: ldc 67110912
    //   2799: iastore
    //   2800: dup
    //   2801: bipush #43
    //   2803: ldc 2097152
    //   2805: iastore
    //   2806: dup
    //   2807: bipush #44
    //   2809: ldc 69208064
    //   2811: iastore
    //   2812: dup
    //   2813: bipush #45
    //   2815: sipush #2050
    //   2818: iastore
    //   2819: dup
    //   2820: bipush #46
    //   2822: ldc 2099202
    //   2824: iastore
    //   2825: dup
    //   2826: bipush #47
    //   2828: ldc 69208064
    //   2830: iastore
    //   2831: dup
    //   2832: bipush #48
    //   2834: sipush #2050
    //   2837: iastore
    //   2838: dup
    //   2839: bipush #49
    //   2841: ldc 67108866
    //   2843: iastore
    //   2844: dup
    //   2845: bipush #50
    //   2847: ldc 69208066
    //   2849: iastore
    //   2850: dup
    //   2851: bipush #51
    //   2853: ldc 69206016
    //   2855: iastore
    //   2856: dup
    //   2857: bipush #52
    //   2859: ldc 2099200
    //   2861: iastore
    //   2862: dup
    //   2863: bipush #53
    //   2865: iconst_0
    //   2866: iastore
    //   2867: dup
    //   2868: bipush #54
    //   2870: iconst_2
    //   2871: iastore
    //   2872: dup
    //   2873: bipush #55
    //   2875: ldc 69208066
    //   2877: iastore
    //   2878: dup
    //   2879: bipush #56
    //   2881: iconst_0
    //   2882: iastore
    //   2883: dup
    //   2884: bipush #57
    //   2886: ldc 2099202
    //   2888: iastore
    //   2889: dup
    //   2890: bipush #58
    //   2892: ldc 69206016
    //   2894: iastore
    //   2895: dup
    //   2896: bipush #59
    //   2898: sipush #2048
    //   2901: iastore
    //   2902: dup
    //   2903: bipush #60
    //   2905: ldc 67108866
    //   2907: iastore
    //   2908: dup
    //   2909: bipush #61
    //   2911: ldc 67110912
    //   2913: iastore
    //   2914: dup
    //   2915: bipush #62
    //   2917: sipush #2048
    //   2920: iastore
    //   2921: dup
    //   2922: bipush #63
    //   2924: ldc 2097154
    //   2926: iastore
    //   2927: astore #12
    //   2929: bipush #64
    //   2931: newarray int
    //   2933: dup
    //   2934: iconst_0
    //   2935: ldc 268439616
    //   2937: iastore
    //   2938: dup
    //   2939: iconst_1
    //   2940: sipush #4096
    //   2943: iastore
    //   2944: dup
    //   2945: iconst_2
    //   2946: ldc 262144
    //   2948: iastore
    //   2949: dup
    //   2950: iconst_3
    //   2951: ldc 268701760
    //   2953: iastore
    //   2954: dup
    //   2955: iconst_4
    //   2956: ldc 268435456
    //   2958: iastore
    //   2959: dup
    //   2960: iconst_5
    //   2961: ldc 268439616
    //   2963: iastore
    //   2964: dup
    //   2965: bipush #6
    //   2967: bipush #64
    //   2969: iastore
    //   2970: dup
    //   2971: bipush #7
    //   2973: ldc 268435456
    //   2975: iastore
    //   2976: dup
    //   2977: bipush #8
    //   2979: ldc 262208
    //   2981: iastore
    //   2982: dup
    //   2983: bipush #9
    //   2985: ldc 268697600
    //   2987: iastore
    //   2988: dup
    //   2989: bipush #10
    //   2991: ldc 268701760
    //   2993: iastore
    //   2994: dup
    //   2995: bipush #11
    //   2997: ldc 266240
    //   2999: iastore
    //   3000: dup
    //   3001: bipush #12
    //   3003: ldc 268701696
    //   3005: iastore
    //   3006: dup
    //   3007: bipush #13
    //   3009: ldc 266304
    //   3011: iastore
    //   3012: dup
    //   3013: bipush #14
    //   3015: sipush #4096
    //   3018: iastore
    //   3019: dup
    //   3020: bipush #15
    //   3022: bipush #64
    //   3024: iastore
    //   3025: dup
    //   3026: bipush #16
    //   3028: ldc 268697600
    //   3030: iastore
    //   3031: dup
    //   3032: bipush #17
    //   3034: ldc 268435520
    //   3036: iastore
    //   3037: dup
    //   3038: bipush #18
    //   3040: ldc 268439552
    //   3042: iastore
    //   3043: dup
    //   3044: bipush #19
    //   3046: sipush #4160
    //   3049: iastore
    //   3050: dup
    //   3051: bipush #20
    //   3053: ldc 266240
    //   3055: iastore
    //   3056: dup
    //   3057: bipush #21
    //   3059: ldc 262208
    //   3061: iastore
    //   3062: dup
    //   3063: bipush #22
    //   3065: ldc 268697664
    //   3067: iastore
    //   3068: dup
    //   3069: bipush #23
    //   3071: ldc 268701696
    //   3073: iastore
    //   3074: dup
    //   3075: bipush #24
    //   3077: sipush #4160
    //   3080: iastore
    //   3081: dup
    //   3082: bipush #25
    //   3084: iconst_0
    //   3085: iastore
    //   3086: dup
    //   3087: bipush #26
    //   3089: iconst_0
    //   3090: iastore
    //   3091: dup
    //   3092: bipush #27
    //   3094: ldc 268697664
    //   3096: iastore
    //   3097: dup
    //   3098: bipush #28
    //   3100: ldc 268435520
    //   3102: iastore
    //   3103: dup
    //   3104: bipush #29
    //   3106: ldc 268439552
    //   3108: iastore
    //   3109: dup
    //   3110: bipush #30
    //   3112: ldc 266304
    //   3114: iastore
    //   3115: dup
    //   3116: bipush #31
    //   3118: ldc 262144
    //   3120: iastore
    //   3121: dup
    //   3122: bipush #32
    //   3124: ldc 266304
    //   3126: iastore
    //   3127: dup
    //   3128: bipush #33
    //   3130: ldc 262144
    //   3132: iastore
    //   3133: dup
    //   3134: bipush #34
    //   3136: ldc 268701696
    //   3138: iastore
    //   3139: dup
    //   3140: bipush #35
    //   3142: sipush #4096
    //   3145: iastore
    //   3146: dup
    //   3147: bipush #36
    //   3149: bipush #64
    //   3151: iastore
    //   3152: dup
    //   3153: bipush #37
    //   3155: ldc 268697664
    //   3157: iastore
    //   3158: dup
    //   3159: bipush #38
    //   3161: sipush #4096
    //   3164: iastore
    //   3165: dup
    //   3166: bipush #39
    //   3168: ldc 266304
    //   3170: iastore
    //   3171: dup
    //   3172: bipush #40
    //   3174: ldc 268439552
    //   3176: iastore
    //   3177: dup
    //   3178: bipush #41
    //   3180: bipush #64
    //   3182: iastore
    //   3183: dup
    //   3184: bipush #42
    //   3186: ldc 268435520
    //   3188: iastore
    //   3189: dup
    //   3190: bipush #43
    //   3192: ldc 268697600
    //   3194: iastore
    //   3195: dup
    //   3196: bipush #44
    //   3198: ldc 268697664
    //   3200: iastore
    //   3201: dup
    //   3202: bipush #45
    //   3204: ldc 268435456
    //   3206: iastore
    //   3207: dup
    //   3208: bipush #46
    //   3210: ldc 262144
    //   3212: iastore
    //   3213: dup
    //   3214: bipush #47
    //   3216: ldc 268439616
    //   3218: iastore
    //   3219: dup
    //   3220: bipush #48
    //   3222: iconst_0
    //   3223: iastore
    //   3224: dup
    //   3225: bipush #49
    //   3227: ldc 268701760
    //   3229: iastore
    //   3230: dup
    //   3231: bipush #50
    //   3233: ldc 262208
    //   3235: iastore
    //   3236: dup
    //   3237: bipush #51
    //   3239: ldc 268435520
    //   3241: iastore
    //   3242: dup
    //   3243: bipush #52
    //   3245: ldc 268697600
    //   3247: iastore
    //   3248: dup
    //   3249: bipush #53
    //   3251: ldc 268439552
    //   3253: iastore
    //   3254: dup
    //   3255: bipush #54
    //   3257: ldc 268439616
    //   3259: iastore
    //   3260: dup
    //   3261: bipush #55
    //   3263: iconst_0
    //   3264: iastore
    //   3265: dup
    //   3266: bipush #56
    //   3268: ldc 268701760
    //   3270: iastore
    //   3271: dup
    //   3272: bipush #57
    //   3274: ldc 266240
    //   3276: iastore
    //   3277: dup
    //   3278: bipush #58
    //   3280: ldc 266240
    //   3282: iastore
    //   3283: dup
    //   3284: bipush #59
    //   3286: sipush #4160
    //   3289: iastore
    //   3290: dup
    //   3291: bipush #60
    //   3293: sipush #4160
    //   3296: iastore
    //   3297: dup
    //   3298: bipush #61
    //   3300: ldc 262208
    //   3302: iastore
    //   3303: dup
    //   3304: bipush #62
    //   3306: ldc 268435456
    //   3308: iastore
    //   3309: dup
    //   3310: bipush #63
    //   3312: ldc 268701696
    //   3314: iastore
    //   3315: astore #13
    //   3317: aload_3
    //   3318: arraylength
    //   3319: istore #14
    //   3321: iload #14
    //   3323: bipush #8
    //   3325: irem
    //   3326: ifeq -> 3350
    //   3329: new java/lang/Exception
    //   3332: dup
    //   3333: sipush #-32606
    //   3336: sipush #-32223
    //   3339: invokestatic a : (II)Ljava/lang/String;
    //   3342: invokespecial <init> : (Ljava/lang/String;)V
    //   3345: athrow
    //   3346: invokestatic a : (Ljava/lang/Throwable;)Ljava/lang/Throwable;
    //   3349: athrow
    //   3350: iconst_2
    //   3351: newarray int
    //   3353: astore #15
    //   3355: iload #14
    //   3357: newarray byte
    //   3359: astore #16
    //   3361: iload #14
    //   3363: bipush #8
    //   3365: idiv
    //   3366: istore #17
    //   3368: iconst_0
    //   3369: istore #18
    //   3371: iload #18
    //   3373: iload #17
    //   3375: if_icmpge -> 4289
    //   3378: iload #18
    //   3380: bipush #8
    //   3382: imul
    //   3383: istore #19
    //   3385: iconst_0
    //   3386: istore #20
    //   3388: iload #20
    //   3390: iconst_2
    //   3391: if_icmpge -> 3476
    //   3394: aload #15
    //   3396: iload #20
    //   3398: aload_3
    //   3399: iload #19
    //   3401: iload #20
    //   3403: iconst_4
    //   3404: imul
    //   3405: iadd
    //   3406: baload
    //   3407: sipush #255
    //   3410: iand
    //   3411: bipush #24
    //   3413: ishl
    //   3414: aload_3
    //   3415: iload #19
    //   3417: iload #20
    //   3419: iconst_4
    //   3420: imul
    //   3421: iadd
    //   3422: iconst_1
    //   3423: iadd
    //   3424: baload
    //   3425: sipush #255
    //   3428: iand
    //   3429: bipush #16
    //   3431: ishl
    //   3432: ior
    //   3433: aload_3
    //   3434: iload #19
    //   3436: iload #20
    //   3438: iconst_4
    //   3439: imul
    //   3440: iadd
    //   3441: iconst_2
    //   3442: iadd
    //   3443: baload
    //   3444: sipush #255
    //   3447: iand
    //   3448: bipush #8
    //   3450: ishl
    //   3451: ior
    //   3452: aload_3
    //   3453: iload #19
    //   3455: iload #20
    //   3457: iconst_4
    //   3458: imul
    //   3459: iadd
    //   3460: iconst_3
    //   3461: iadd
    //   3462: baload
    //   3463: sipush #255
    //   3466: iand
    //   3467: ior
    //   3468: iastore
    //   3469: iinc #20, 1
    //   3472: iload_2
    //   3473: ifne -> 3388
    //   3476: iconst_0
    //   3477: istore #25
    //   3479: aload #15
    //   3481: iconst_0
    //   3482: iaload
    //   3483: istore #23
    //   3485: aload #15
    //   3487: iconst_1
    //   3488: iaload
    //   3489: istore #22
    //   3491: iload #23
    //   3493: iconst_4
    //   3494: iushr
    //   3495: iload #22
    //   3497: ixor
    //   3498: ldc 252645135
    //   3500: iand
    //   3501: istore #21
    //   3503: iload #22
    //   3505: iload #21
    //   3507: ixor
    //   3508: istore #22
    //   3510: iload #23
    //   3512: iload #21
    //   3514: iconst_4
    //   3515: ishl
    //   3516: ixor
    //   3517: istore #23
    //   3519: iload #23
    //   3521: bipush #16
    //   3523: iushr
    //   3524: iload #22
    //   3526: ixor
    //   3527: ldc 65535
    //   3529: iand
    //   3530: istore #21
    //   3532: iload #22
    //   3534: iload #21
    //   3536: ixor
    //   3537: istore #22
    //   3539: iload #23
    //   3541: iload #21
    //   3543: bipush #16
    //   3545: ishl
    //   3546: ixor
    //   3547: istore #23
    //   3549: iload #22
    //   3551: iconst_2
    //   3552: iushr
    //   3553: iload #23
    //   3555: ixor
    //   3556: ldc 858993459
    //   3558: iand
    //   3559: istore #21
    //   3561: iload #23
    //   3563: iload #21
    //   3565: ixor
    //   3566: istore #23
    //   3568: iload #22
    //   3570: iload #21
    //   3572: iconst_2
    //   3573: ishl
    //   3574: ixor
    //   3575: istore #22
    //   3577: iload #22
    //   3579: bipush #8
    //   3581: iushr
    //   3582: iload #23
    //   3584: ixor
    //   3585: ldc 16711935
    //   3587: iand
    //   3588: istore #21
    //   3590: iload #23
    //   3592: iload #21
    //   3594: ixor
    //   3595: istore #23
    //   3597: iload #22
    //   3599: iload #21
    //   3601: bipush #8
    //   3603: ishl
    //   3604: ixor
    //   3605: istore #22
    //   3607: iload #22
    //   3609: iconst_1
    //   3610: ishl
    //   3611: iload #22
    //   3613: bipush #31
    //   3615: iushr
    //   3616: iconst_1
    //   3617: iand
    //   3618: ior
    //   3619: istore #22
    //   3621: iload #23
    //   3623: iload #22
    //   3625: ixor
    //   3626: ldc -1431655766
    //   3628: iand
    //   3629: istore #21
    //   3631: iload #23
    //   3633: iload #21
    //   3635: ixor
    //   3636: istore #23
    //   3638: iload #22
    //   3640: iload #21
    //   3642: ixor
    //   3643: istore #22
    //   3645: iload #23
    //   3647: iconst_1
    //   3648: ishl
    //   3649: iload #23
    //   3651: bipush #31
    //   3653: iushr
    //   3654: iconst_1
    //   3655: iand
    //   3656: ior
    //   3657: istore #23
    //   3659: iconst_0
    //   3660: istore #24
    //   3662: iload #24
    //   3664: bipush #8
    //   3666: if_icmpge -> 4004
    //   3669: iload #22
    //   3671: bipush #28
    //   3673: ishl
    //   3674: iload #22
    //   3676: iconst_4
    //   3677: iushr
    //   3678: ior
    //   3679: istore #21
    //   3681: iload #21
    //   3683: aload #5
    //   3685: iload #25
    //   3687: iinc #25, 1
    //   3690: iaload
    //   3691: ixor
    //   3692: istore #21
    //   3694: aload #12
    //   3696: iload #21
    //   3698: bipush #63
    //   3700: iand
    //   3701: iaload
    //   3702: istore #20
    //   3704: iload #20
    //   3706: aload #10
    //   3708: iload #21
    //   3710: bipush #8
    //   3712: iushr
    //   3713: bipush #63
    //   3715: iand
    //   3716: iaload
    //   3717: ior
    //   3718: istore #20
    //   3720: iload #20
    //   3722: aload #8
    //   3724: iload #21
    //   3726: bipush #16
    //   3728: iushr
    //   3729: bipush #63
    //   3731: iand
    //   3732: iaload
    //   3733: ior
    //   3734: istore #20
    //   3736: iload #20
    //   3738: aload #6
    //   3740: iload #21
    //   3742: bipush #24
    //   3744: iushr
    //   3745: bipush #63
    //   3747: iand
    //   3748: iaload
    //   3749: ior
    //   3750: istore #20
    //   3752: iload #22
    //   3754: aload #5
    //   3756: iload #25
    //   3758: iinc #25, 1
    //   3761: iaload
    //   3762: ixor
    //   3763: istore #21
    //   3765: iload #20
    //   3767: aload #13
    //   3769: iload #21
    //   3771: bipush #63
    //   3773: iand
    //   3774: iaload
    //   3775: ior
    //   3776: istore #20
    //   3778: iload #20
    //   3780: aload #11
    //   3782: iload #21
    //   3784: bipush #8
    //   3786: iushr
    //   3787: bipush #63
    //   3789: iand
    //   3790: iaload
    //   3791: ior
    //   3792: istore #20
    //   3794: iload #20
    //   3796: aload #9
    //   3798: iload #21
    //   3800: bipush #16
    //   3802: iushr
    //   3803: bipush #63
    //   3805: iand
    //   3806: iaload
    //   3807: ior
    //   3808: istore #20
    //   3810: iload #20
    //   3812: aload #7
    //   3814: iload #21
    //   3816: bipush #24
    //   3818: iushr
    //   3819: bipush #63
    //   3821: iand
    //   3822: iaload
    //   3823: ior
    //   3824: istore #20
    //   3826: iload #23
    //   3828: iload #20
    //   3830: ixor
    //   3831: istore #23
    //   3833: iload #23
    //   3835: bipush #28
    //   3837: ishl
    //   3838: iload #23
    //   3840: iconst_4
    //   3841: iushr
    //   3842: ior
    //   3843: istore #21
    //   3845: iload #21
    //   3847: aload #5
    //   3849: iload #25
    //   3851: iinc #25, 1
    //   3854: iaload
    //   3855: ixor
    //   3856: istore #21
    //   3858: aload #12
    //   3860: iload #21
    //   3862: bipush #63
    //   3864: iand
    //   3865: iaload
    //   3866: istore #20
    //   3868: iload #20
    //   3870: aload #10
    //   3872: iload #21
    //   3874: bipush #8
    //   3876: iushr
    //   3877: bipush #63
    //   3879: iand
    //   3880: iaload
    //   3881: ior
    //   3882: istore #20
    //   3884: iload #20
    //   3886: aload #8
    //   3888: iload #21
    //   3890: bipush #16
    //   3892: iushr
    //   3893: bipush #63
    //   3895: iand
    //   3896: iaload
    //   3897: ior
    //   3898: istore #20
    //   3900: iload #20
    //   3902: aload #6
    //   3904: iload #21
    //   3906: bipush #24
    //   3908: iushr
    //   3909: bipush #63
    //   3911: iand
    //   3912: iaload
    //   3913: ior
    //   3914: istore #20
    //   3916: iload #23
    //   3918: aload #5
    //   3920: iload #25
    //   3922: iinc #25, 1
    //   3925: iaload
    //   3926: ixor
    //   3927: istore #21
    //   3929: iload #20
    //   3931: aload #13
    //   3933: iload #21
    //   3935: bipush #63
    //   3937: iand
    //   3938: iaload
    //   3939: ior
    //   3940: istore #20
    //   3942: iload #20
    //   3944: aload #11
    //   3946: iload #21
    //   3948: bipush #8
    //   3950: iushr
    //   3951: bipush #63
    //   3953: iand
    //   3954: iaload
    //   3955: ior
    //   3956: istore #20
    //   3958: iload #20
    //   3960: aload #9
    //   3962: iload #21
    //   3964: bipush #16
    //   3966: iushr
    //   3967: bipush #63
    //   3969: iand
    //   3970: iaload
    //   3971: ior
    //   3972: istore #20
    //   3974: iload #20
    //   3976: aload #7
    //   3978: iload #21
    //   3980: bipush #24
    //   3982: iushr
    //   3983: bipush #63
    //   3985: iand
    //   3986: iaload
    //   3987: ior
    //   3988: istore #20
    //   3990: iload #22
    //   3992: iload #20
    //   3994: ixor
    //   3995: istore #22
    //   3997: iinc #24, 1
    //   4000: iload_2
    //   4001: ifne -> 3662
    //   4004: iload #22
    //   4006: bipush #31
    //   4008: ishl
    //   4009: iload #22
    //   4011: iconst_1
    //   4012: iushr
    //   4013: ior
    //   4014: istore #22
    //   4016: iload #23
    //   4018: iload #22
    //   4020: ixor
    //   4021: ldc -1431655766
    //   4023: iand
    //   4024: istore #21
    //   4026: iload #23
    //   4028: iload #21
    //   4030: ixor
    //   4031: istore #23
    //   4033: iload #22
    //   4035: iload #21
    //   4037: ixor
    //   4038: istore #22
    //   4040: iload #23
    //   4042: bipush #31
    //   4044: ishl
    //   4045: iload #23
    //   4047: iconst_1
    //   4048: iushr
    //   4049: ior
    //   4050: istore #23
    //   4052: iload #23
    //   4054: bipush #8
    //   4056: iushr
    //   4057: iload #22
    //   4059: ixor
    //   4060: ldc 16711935
    //   4062: iand
    //   4063: istore #21
    //   4065: iload #22
    //   4067: iload #21
    //   4069: ixor
    //   4070: istore #22
    //   4072: iload #23
    //   4074: iload #21
    //   4076: bipush #8
    //   4078: ishl
    //   4079: ixor
    //   4080: istore #23
    //   4082: iload #23
    //   4084: iconst_2
    //   4085: iushr
    //   4086: iload #22
    //   4088: ixor
    //   4089: ldc 858993459
    //   4091: iand
    //   4092: istore #21
    //   4094: iload #22
    //   4096: iload #21
    //   4098: ixor
    //   4099: istore #22
    //   4101: iload #23
    //   4103: iload #21
    //   4105: iconst_2
    //   4106: ishl
    //   4107: ixor
    //   4108: istore #23
    //   4110: iload #22
    //   4112: bipush #16
    //   4114: iushr
    //   4115: iload #23
    //   4117: ixor
    //   4118: ldc 65535
    //   4120: iand
    //   4121: istore #21
    //   4123: iload #23
    //   4125: iload #21
    //   4127: ixor
    //   4128: istore #23
    //   4130: iload #22
    //   4132: iload #21
    //   4134: bipush #16
    //   4136: ishl
    //   4137: ixor
    //   4138: istore #22
    //   4140: iload #22
    //   4142: iconst_4
    //   4143: iushr
    //   4144: iload #23
    //   4146: ixor
    //   4147: ldc 252645135
    //   4149: iand
    //   4150: istore #21
    //   4152: iload #23
    //   4154: iload #21
    //   4156: ixor
    //   4157: istore #23
    //   4159: iload #22
    //   4161: iload #21
    //   4163: iconst_4
    //   4164: ishl
    //   4165: ixor
    //   4166: istore #22
    //   4168: aload #15
    //   4170: iconst_0
    //   4171: iload #22
    //   4173: iastore
    //   4174: aload #15
    //   4176: iconst_1
    //   4177: iload #23
    //   4179: iastore
    //   4180: iload #18
    //   4182: bipush #8
    //   4184: imul
    //   4185: istore #26
    //   4187: iconst_0
    //   4188: istore #27
    //   4190: iload #27
    //   4192: iconst_2
    //   4193: if_icmpge -> 4282
    //   4196: aload #16
    //   4198: iload #26
    //   4200: iload #27
    //   4202: iconst_4
    //   4203: imul
    //   4204: iadd
    //   4205: aload #15
    //   4207: iload #27
    //   4209: iaload
    //   4210: bipush #24
    //   4212: iushr
    //   4213: i2b
    //   4214: bastore
    //   4215: aload #16
    //   4217: iload #26
    //   4219: iload #27
    //   4221: iconst_4
    //   4222: imul
    //   4223: iadd
    //   4224: iconst_1
    //   4225: iadd
    //   4226: aload #15
    //   4228: iload #27
    //   4230: iaload
    //   4231: bipush #16
    //   4233: iushr
    //   4234: i2b
    //   4235: bastore
    //   4236: aload #16
    //   4238: iload #26
    //   4240: iload #27
    //   4242: iconst_4
    //   4243: imul
    //   4244: iadd
    //   4245: iconst_2
    //   4246: iadd
    //   4247: aload #15
    //   4249: iload #27
    //   4251: iaload
    //   4252: bipush #8
    //   4254: iushr
    //   4255: i2b
    //   4256: bastore
    //   4257: aload #16
    //   4259: iload #26
    //   4261: iload #27
    //   4263: iconst_4
    //   4264: imul
    //   4265: iadd
    //   4266: iconst_3
    //   4267: iadd
    //   4268: aload #15
    //   4270: iload #27
    //   4272: iaload
    //   4273: i2b
    //   4274: bastore
    //   4275: iinc #27, 1
    //   4278: iload_2
    //   4279: ifne -> 4190
    //   4282: iinc #18, 1
    //   4285: iload_2
    //   4286: ifne -> 3371
    //   4289: aload #16
    //   4291: aload #16
    //   4293: arraylength
    //   4294: iconst_1
    //   4295: isub
    //   4296: baload
    //   4297: istore #18
    //   4299: aload #16
    //   4301: arraylength
    //   4302: iload #18
    //   4304: isub
    //   4305: newarray byte
    //   4307: astore #4
    //   4309: aload #16
    //   4311: arraylength
    //   4312: aload #4
    //   4314: arraylength
    //   4315: if_icmpge -> 4339
    //   4318: new java/lang/Exception
    //   4321: dup
    //   4322: sipush #-32594
    //   4325: sipush #-1151
    //   4328: invokestatic a : (II)Ljava/lang/String;
    //   4331: invokespecial <init> : (Ljava/lang/String;)V
    //   4334: athrow
    //   4335: invokestatic a : (Ljava/lang/Throwable;)Ljava/lang/Throwable;
    //   4338: athrow
    //   4339: iconst_0
    //   4340: istore #19
    //   4342: iload #19
    //   4344: aload #4
    //   4346: arraylength
    //   4347: if_icmpge -> 4367
    //   4350: aload #4
    //   4352: iload #19
    //   4354: aload #16
    //   4356: iload #19
    //   4358: baload
    //   4359: bastore
    //   4360: iinc #19, 1
    //   4363: iload_2
    //   4364: ifne -> 4342
    //   4367: new java/math/BigInteger
    //   4370: dup
    //   4371: aload #4
    //   4373: invokespecial <init> : ([B)V
    //   4376: invokevirtual abs : ()Ljava/math/BigInteger;
    //   4379: putstatic burp/Zlxs.ZK : Ljava/lang/Object;
    //   4382: new java/lang/StringBuilder
    //   4385: dup
    //   4386: invokespecial <init> : ()V
    //   4389: astore_3
    //   4390: iconst_0
    //   4391: istore #4
    //   4393: iload #4
    //   4395: bipush #32
    //   4397: if_icmpge -> 5731
    //   4400: iload #4
    //   4402: tableswitch default -> 5724, 0 -> 4544, 1 -> 4581, 2 -> 4618, 3 -> 4655, 4 -> 4692, 5 -> 4729, 6 -> 4766, 7 -> 4803, 8 -> 4840, 9 -> 4877, 10 -> 4914, 11 -> 4951, 12 -> 4988, 13 -> 5025, 14 -> 5062, 15 -> 5099, 16 -> 5136, 17 -> 5173, 18 -> 5210, 19 -> 5247, 20 -> 5284, 21 -> 5321, 22 -> 5358, 23 -> 5395, 24 -> 5432, 25 -> 5469, 26 -> 5506, 27 -> 5543, 28 -> 5580, 29 -> 5617, 30 -> 5654, 31 -> 5691
    //   4544: aload_3
    //   4545: getstatic burp/Zmzh.Zm : Ljava/lang/String;
    //   4548: getstatic burp/Zgfm.ZV : Ljava/lang/Object;
    //   4551: checkcast java/math/BigInteger
    //   4554: invokevirtual intValue : ()I
    //   4557: bipush #32
    //   4559: irem
    //   4560: invokestatic abs : (I)I
    //   4563: invokevirtual charAt : (I)C
    //   4566: invokevirtual append : (C)Ljava/lang/StringBuilder;
    //   4569: pop
    //   4570: iload_2
    //   4571: ifne -> 5724
    //   4574: goto -> 4581
    //   4577: invokestatic a : (Ljava/lang/Throwable;)Ljava/lang/Throwable;
    //   4580: athrow
    //   4581: aload_3
    //   4582: getstatic burp/Zbf9.Zp : Ljava/lang/String;
    //   4585: getstatic burp/Zmze.Zo : Ljava/lang/Object;
    //   4588: checkcast java/math/BigInteger
    //   4591: invokevirtual intValue : ()I
    //   4594: bipush #32
    //   4596: irem
    //   4597: invokestatic abs : (I)I
    //   4600: invokevirtual charAt : (I)C
    //   4603: invokevirtual append : (C)Ljava/lang/StringBuilder;
    //   4606: pop
    //   4607: iload_2
    //   4608: ifne -> 5724
    //   4611: goto -> 4618
    //   4614: invokestatic a : (Ljava/lang/Throwable;)Ljava/lang/Throwable;
    //   4617: athrow
    //   4618: aload_3
    //   4619: getstatic burp/Zluk.ZW : Ljava/lang/String;
    //   4622: getstatic burp/Zkm0.ZI : Ljava/lang/Object;
    //   4625: checkcast java/math/BigInteger
    //   4628: invokevirtual intValue : ()I
    //   4631: bipush #32
    //   4633: irem
    //   4634: invokestatic abs : (I)I
    //   4637: invokevirtual charAt : (I)C
    //   4640: invokevirtual append : (C)Ljava/lang/StringBuilder;
    //   4643: pop
    //   4644: iload_2
    //   4645: ifne -> 5724
    //   4648: goto -> 4655
    //   4651: invokestatic a : (Ljava/lang/Throwable;)Ljava/lang/Throwable;
    //   4654: athrow
    //   4655: aload_3
    //   4656: getstatic burp/Zea9.Zd : Ljava/lang/String;
    //   4659: getstatic burp/Zoa.ZI : Ljava/lang/Object;
    //   4662: checkcast java/math/BigInteger
    //   4665: invokevirtual intValue : ()I
    //   4668: bipush #32
    //   4670: irem
    //   4671: invokestatic abs : (I)I
    //   4674: invokevirtual charAt : (I)C
    //   4677: invokevirtual append : (C)Ljava/lang/StringBuilder;
    //   4680: pop
    //   4681: iload_2
    //   4682: ifne -> 5724
    //   4685: goto -> 4692
    //   4688: invokestatic a : (Ljava/lang/Throwable;)Ljava/lang/Throwable;
    //   4691: athrow
    //   4692: aload_3
    //   4693: getstatic burp/Zs1d.Zl : Ljava/lang/String;
    //   4696: getstatic burp/Zkk2.Zq : Ljava/lang/Object;
    //   4699: checkcast java/math/BigInteger
    //   4702: invokevirtual intValue : ()I
    //   4705: bipush #32
    //   4707: irem
    //   4708: invokestatic abs : (I)I
    //   4711: invokevirtual charAt : (I)C
    //   4714: invokevirtual append : (C)Ljava/lang/StringBuilder;
    //   4717: pop
    //   4718: iload_2
    //   4719: ifne -> 5724
    //   4722: goto -> 4729
    //   4725: invokestatic a : (Ljava/lang/Throwable;)Ljava/lang/Throwable;
    //   4728: athrow
    //   4729: aload_3
    //   4730: getstatic burp/Zxtn.Zu : Ljava/lang/String;
    //   4733: getstatic burp/Zgny.ZR : Ljava/lang/Object;
    //   4736: checkcast java/math/BigInteger
    //   4739: invokevirtual intValue : ()I
    //   4742: bipush #32
    //   4744: irem
    //   4745: invokestatic abs : (I)I
    //   4748: invokevirtual charAt : (I)C
    //   4751: invokevirtual append : (C)Ljava/lang/StringBuilder;
    //   4754: pop
    //   4755: iload_2
    //   4756: ifne -> 5724
    //   4759: goto -> 4766
    //   4762: invokestatic a : (Ljava/lang/Throwable;)Ljava/lang/Throwable;
    //   4765: athrow
    //   4766: aload_3
    //   4767: getstatic burp/Zlhu.ZC : Ljava/lang/String;
    //   4770: getstatic burp/Zb9k.Zi : Ljava/lang/Object;
    //   4773: checkcast java/math/BigInteger
    //   4776: invokevirtual intValue : ()I
    //   4779: bipush #32
    //   4781: irem
    //   4782: invokestatic abs : (I)I
    //   4785: invokevirtual charAt : (I)C
    //   4788: invokevirtual append : (C)Ljava/lang/StringBuilder;
    //   4791: pop
    //   4792: iload_2
    //   4793: ifne -> 5724
    //   4796: goto -> 4803
    //   4799: invokestatic a : (Ljava/lang/Throwable;)Ljava/lang/Throwable;
    //   4802: athrow
    //   4803: aload_3
    //   4804: getstatic burp/Ztg3.ZM : Ljava/lang/String;
    //   4807: getstatic burp/Zlc5.ZH : Ljava/lang/Object;
    //   4810: checkcast java/math/BigInteger
    //   4813: invokevirtual intValue : ()I
    //   4816: bipush #32
    //   4818: irem
    //   4819: invokestatic abs : (I)I
    //   4822: invokevirtual charAt : (I)C
    //   4825: invokevirtual append : (C)Ljava/lang/StringBuilder;
    //   4828: pop
    //   4829: iload_2
    //   4830: ifne -> 5724
    //   4833: goto -> 4840
    //   4836: invokestatic a : (Ljava/lang/Throwable;)Ljava/lang/Throwable;
    //   4839: athrow
    //   4840: aload_3
    //   4841: getstatic burp/Zgrf.ZE : Ljava/lang/String;
    //   4844: getstatic burp/Zg0j.ZV : Ljava/lang/Object;
    //   4847: checkcast java/math/BigInteger
    //   4850: invokevirtual intValue : ()I
    //   4853: bipush #32
    //   4855: irem
    //   4856: invokestatic abs : (I)I
    //   4859: invokevirtual charAt : (I)C
    //   4862: invokevirtual append : (C)Ljava/lang/StringBuilder;
    //   4865: pop
    //   4866: iload_2
    //   4867: ifne -> 5724
    //   4870: goto -> 4877
    //   4873: invokestatic a : (Ljava/lang/Throwable;)Ljava/lang/Throwable;
    //   4876: athrow
    //   4877: aload_3
    //   4878: getstatic burp/Zm4k.ZW : Ljava/lang/String;
    //   4881: getstatic burp/Zec_.ZN : Ljava/lang/Object;
    //   4884: checkcast java/math/BigInteger
    //   4887: invokevirtual intValue : ()I
    //   4890: bipush #32
    //   4892: irem
    //   4893: invokestatic abs : (I)I
    //   4896: invokevirtual charAt : (I)C
    //   4899: invokevirtual append : (C)Ljava/lang/StringBuilder;
    //   4902: pop
    //   4903: iload_2
    //   4904: ifne -> 5724
    //   4907: goto -> 4914
    //   4910: invokestatic a : (Ljava/lang/Throwable;)Ljava/lang/Throwable;
    //   4913: athrow
    //   4914: aload_3
    //   4915: getstatic burp/Zb8v.Zo : Ljava/lang/String;
    //   4918: getstatic burp/Zecw.ZE : Ljava/lang/Object;
    //   4921: checkcast java/math/BigInteger
    //   4924: invokevirtual intValue : ()I
    //   4927: bipush #32
    //   4929: irem
    //   4930: invokestatic abs : (I)I
    //   4933: invokevirtual charAt : (I)C
    //   4936: invokevirtual append : (C)Ljava/lang/StringBuilder;
    //   4939: pop
    //   4940: iload_2
    //   4941: ifne -> 5724
    //   4944: goto -> 4951
    //   4947: invokestatic a : (Ljava/lang/Throwable;)Ljava/lang/Throwable;
    //   4950: athrow
    //   4951: aload_3
    //   4952: getstatic burp/Zezn.Ze : Ljava/lang/String;
    //   4955: getstatic burp/Zzlg.Z_ : Ljava/lang/Object;
    //   4958: checkcast java/math/BigInteger
    //   4961: invokevirtual intValue : ()I
    //   4964: bipush #32
    //   4966: irem
    //   4967: invokestatic abs : (I)I
    //   4970: invokevirtual charAt : (I)C
    //   4973: invokevirtual append : (C)Ljava/lang/StringBuilder;
    //   4976: pop
    //   4977: iload_2
    //   4978: ifne -> 5724
    //   4981: goto -> 4988
    //   4984: invokestatic a : (Ljava/lang/Throwable;)Ljava/lang/Throwable;
    //   4987: athrow
    //   4988: aload_3
    //   4989: getstatic burp/Zl39.ZI : Ljava/lang/String;
    //   4992: getstatic burp/Zly0.ZB : Ljava/lang/Object;
    //   4995: checkcast java/math/BigInteger
    //   4998: invokevirtual intValue : ()I
    //   5001: bipush #32
    //   5003: irem
    //   5004: invokestatic abs : (I)I
    //   5007: invokevirtual charAt : (I)C
    //   5010: invokevirtual append : (C)Ljava/lang/StringBuilder;
    //   5013: pop
    //   5014: iload_2
    //   5015: ifne -> 5724
    //   5018: goto -> 5025
    //   5021: invokestatic a : (Ljava/lang/Throwable;)Ljava/lang/Throwable;
    //   5024: athrow
    //   5025: aload_3
    //   5026: getstatic burp/Zz8o.Zo : Ljava/lang/String;
    //   5029: getstatic burp/Zz80.ZR : Ljava/lang/Object;
    //   5032: checkcast java/math/BigInteger
    //   5035: invokevirtual intValue : ()I
    //   5038: bipush #32
    //   5040: irem
    //   5041: invokestatic abs : (I)I
    //   5044: invokevirtual charAt : (I)C
    //   5047: invokevirtual append : (C)Ljava/lang/StringBuilder;
    //   5050: pop
    //   5051: iload_2
    //   5052: ifne -> 5724
    //   5055: goto -> 5062
    //   5058: invokestatic a : (Ljava/lang/Throwable;)Ljava/lang/Throwable;
    //   5061: athrow
    //   5062: aload_3
    //   5063: getstatic burp/Zkby.Zf : Ljava/lang/String;
    //   5066: getstatic burp/Zrs0.Zz : Ljava/lang/Object;
    //   5069: checkcast java/math/BigInteger
    //   5072: invokevirtual intValue : ()I
    //   5075: bipush #32
    //   5077: irem
    //   5078: invokestatic abs : (I)I
    //   5081: invokevirtual charAt : (I)C
    //   5084: invokevirtual append : (C)Ljava/lang/StringBuilder;
    //   5087: pop
    //   5088: iload_2
    //   5089: ifne -> 5724
    //   5092: goto -> 5099
    //   5095: invokestatic a : (Ljava/lang/Throwable;)Ljava/lang/Throwable;
    //   5098: athrow
    //   5099: aload_3
    //   5100: getstatic burp/Zxzd.ZM : Ljava/lang/String;
    //   5103: getstatic burp/Zm6g.ZO : Ljava/lang/Object;
    //   5106: checkcast java/math/BigInteger
    //   5109: invokevirtual intValue : ()I
    //   5112: bipush #32
    //   5114: irem
    //   5115: invokestatic abs : (I)I
    //   5118: invokevirtual charAt : (I)C
    //   5121: invokevirtual append : (C)Ljava/lang/StringBuilder;
    //   5124: pop
    //   5125: iload_2
    //   5126: ifne -> 5724
    //   5129: goto -> 5136
    //   5132: invokestatic a : (Ljava/lang/Throwable;)Ljava/lang/Throwable;
    //   5135: athrow
    //   5136: aload_3
    //   5137: getstatic burp/Zk9s.ZM : Ljava/lang/String;
    //   5140: getstatic burp/Zzx8.Zi : Ljava/lang/Object;
    //   5143: checkcast java/math/BigInteger
    //   5146: invokevirtual intValue : ()I
    //   5149: bipush #32
    //   5151: irem
    //   5152: invokestatic abs : (I)I
    //   5155: invokevirtual charAt : (I)C
    //   5158: invokevirtual append : (C)Ljava/lang/StringBuilder;
    //   5161: pop
    //   5162: iload_2
    //   5163: ifne -> 5724
    //   5166: goto -> 5173
    //   5169: invokestatic a : (Ljava/lang/Throwable;)Ljava/lang/Throwable;
    //   5172: athrow
    //   5173: aload_3
    //   5174: getstatic burp/Zzmo.Zx : Ljava/lang/String;
    //   5177: getstatic burp/Zmzj.Zm : Ljava/lang/Object;
    //   5180: checkcast java/math/BigInteger
    //   5183: invokevirtual intValue : ()I
    //   5186: bipush #32
    //   5188: irem
    //   5189: invokestatic abs : (I)I
    //   5192: invokevirtual charAt : (I)C
    //   5195: invokevirtual append : (C)Ljava/lang/StringBuilder;
    //   5198: pop
    //   5199: iload_2
    //   5200: ifne -> 5724
    //   5203: goto -> 5210
    //   5206: invokestatic a : (Ljava/lang/Throwable;)Ljava/lang/Throwable;
    //   5209: athrow
    //   5210: aload_3
    //   5211: getstatic burp/Zct.Zy : Ljava/lang/String;
    //   5214: getstatic burp/Ztsc.Zr : Ljava/lang/Object;
    //   5217: checkcast java/math/BigInteger
    //   5220: invokevirtual intValue : ()I
    //   5223: bipush #32
    //   5225: irem
    //   5226: invokestatic abs : (I)I
    //   5229: invokevirtual charAt : (I)C
    //   5232: invokevirtual append : (C)Ljava/lang/StringBuilder;
    //   5235: pop
    //   5236: iload_2
    //   5237: ifne -> 5724
    //   5240: goto -> 5247
    //   5243: invokestatic a : (Ljava/lang/Throwable;)Ljava/lang/Throwable;
    //   5246: athrow
    //   5247: aload_3
    //   5248: getstatic burp/Zej5.Zo : Ljava/lang/String;
    //   5251: getstatic burp/Zghe.ZJ : Ljava/lang/Object;
    //   5254: checkcast java/math/BigInteger
    //   5257: invokevirtual intValue : ()I
    //   5260: bipush #32
    //   5262: irem
    //   5263: invokestatic abs : (I)I
    //   5266: invokevirtual charAt : (I)C
    //   5269: invokevirtual append : (C)Ljava/lang/StringBuilder;
    //   5272: pop
    //   5273: iload_2
    //   5274: ifne -> 5724
    //   5277: goto -> 5284
    //   5280: invokestatic a : (Ljava/lang/Throwable;)Ljava/lang/Throwable;
    //   5283: athrow
    //   5284: aload_3
    //   5285: getstatic burp/Zkdc.Zc : Ljava/lang/String;
    //   5288: getstatic burp/Zspk.ZF : Ljava/lang/Object;
    //   5291: checkcast java/math/BigInteger
    //   5294: invokevirtual intValue : ()I
    //   5297: bipush #32
    //   5299: irem
    //   5300: invokestatic abs : (I)I
    //   5303: invokevirtual charAt : (I)C
    //   5306: invokevirtual append : (C)Ljava/lang/StringBuilder;
    //   5309: pop
    //   5310: iload_2
    //   5311: ifne -> 5724
    //   5314: goto -> 5321
    //   5317: invokestatic a : (Ljava/lang/Throwable;)Ljava/lang/Throwable;
    //   5320: athrow
    //   5321: aload_3
    //   5322: getstatic burp/Zb38.Zr : Ljava/lang/String;
    //   5325: getstatic burp/Zm54.ZS : Ljava/lang/Object;
    //   5328: checkcast java/math/BigInteger
    //   5331: invokevirtual intValue : ()I
    //   5334: bipush #32
    //   5336: irem
    //   5337: invokestatic abs : (I)I
    //   5340: invokevirtual charAt : (I)C
    //   5343: invokevirtual append : (C)Ljava/lang/StringBuilder;
    //   5346: pop
    //   5347: iload_2
    //   5348: ifne -> 5724
    //   5351: goto -> 5358
    //   5354: invokestatic a : (Ljava/lang/Throwable;)Ljava/lang/Throwable;
    //   5357: athrow
    //   5358: aload_3
    //   5359: getstatic burp/Zb3z.Zi : Ljava/lang/String;
    //   5362: getstatic burp/Zm_w.ZW : Ljava/lang/Object;
    //   5365: checkcast java/math/BigInteger
    //   5368: invokevirtual intValue : ()I
    //   5371: bipush #32
    //   5373: irem
    //   5374: invokestatic abs : (I)I
    //   5377: invokevirtual charAt : (I)C
    //   5380: invokevirtual append : (C)Ljava/lang/StringBuilder;
    //   5383: pop
    //   5384: iload_2
    //   5385: ifne -> 5724
    //   5388: goto -> 5395
    //   5391: invokestatic a : (Ljava/lang/Throwable;)Ljava/lang/Throwable;
    //   5394: athrow
    //   5395: aload_3
    //   5396: getstatic burp/Zxrd.ZF : Ljava/lang/String;
    //   5399: getstatic burp/Zcc.Zd : Ljava/lang/Object;
    //   5402: checkcast java/math/BigInteger
    //   5405: invokevirtual intValue : ()I
    //   5408: bipush #32
    //   5410: irem
    //   5411: invokestatic abs : (I)I
    //   5414: invokevirtual charAt : (I)C
    //   5417: invokevirtual append : (C)Ljava/lang/StringBuilder;
    //   5420: pop
    //   5421: iload_2
    //   5422: ifne -> 5724
    //   5425: goto -> 5432
    //   5428: invokestatic a : (Ljava/lang/Throwable;)Ljava/lang/Throwable;
    //   5431: athrow
    //   5432: aload_3
    //   5433: getstatic burp/Zoa.ZF : Ljava/lang/String;
    //   5436: getstatic burp/Zx58.ZE : Ljava/lang/Object;
    //   5439: checkcast java/math/BigInteger
    //   5442: invokevirtual intValue : ()I
    //   5445: bipush #32
    //   5447: irem
    //   5448: invokestatic abs : (I)I
    //   5451: invokevirtual charAt : (I)C
    //   5454: invokevirtual append : (C)Ljava/lang/StringBuilder;
    //   5457: pop
    //   5458: iload_2
    //   5459: ifne -> 5724
    //   5462: goto -> 5469
    //   5465: invokestatic a : (Ljava/lang/Throwable;)Ljava/lang/Throwable;
    //   5468: athrow
    //   5469: aload_3
    //   5470: getstatic burp/Zg_5.ZG : Ljava/lang/String;
    //   5473: getstatic burp/Zm81.Zy : Ljava/lang/Object;
    //   5476: checkcast java/math/BigInteger
    //   5479: invokevirtual intValue : ()I
    //   5482: bipush #32
    //   5484: irem
    //   5485: invokestatic abs : (I)I
    //   5488: invokevirtual charAt : (I)C
    //   5491: invokevirtual append : (C)Ljava/lang/StringBuilder;
    //   5494: pop
    //   5495: iload_2
    //   5496: ifne -> 5724
    //   5499: goto -> 5506
    //   5502: invokestatic a : (Ljava/lang/Throwable;)Ljava/lang/Throwable;
    //   5505: athrow
    //   5506: aload_3
    //   5507: getstatic burp/Zle4.ZX : Ljava/lang/String;
    //   5510: getstatic burp/Zlno.ZU : Ljava/lang/Object;
    //   5513: checkcast java/math/BigInteger
    //   5516: invokevirtual intValue : ()I
    //   5519: bipush #32
    //   5521: irem
    //   5522: invokestatic abs : (I)I
    //   5525: invokevirtual charAt : (I)C
    //   5528: invokevirtual append : (C)Ljava/lang/StringBuilder;
    //   5531: pop
    //   5532: iload_2
    //   5533: ifne -> 5724
    //   5536: goto -> 5543
    //   5539: invokestatic a : (Ljava/lang/Throwable;)Ljava/lang/Throwable;
    //   5542: athrow
    //   5543: aload_3
    //   5544: getstatic burp/Zzxv.Z_ : Ljava/lang/String;
    //   5547: getstatic burp/Zxzd.ZD : Ljava/lang/Object;
    //   5550: checkcast java/math/BigInteger
    //   5553: invokevirtual intValue : ()I
    //   5556: bipush #32
    //   5558: irem
    //   5559: invokestatic abs : (I)I
    //   5562: invokevirtual charAt : (I)C
    //   5565: invokevirtual append : (C)Ljava/lang/StringBuilder;
    //   5568: pop
    //   5569: iload_2
    //   5570: ifne -> 5724
    //   5573: goto -> 5580
    //   5576: invokestatic a : (Ljava/lang/Throwable;)Ljava/lang/Throwable;
    //   5579: athrow
    //   5580: aload_3
    //   5581: getstatic burp/Ztg3.ZM : Ljava/lang/String;
    //   5584: getstatic burp/Zlsw.ZJ : Ljava/lang/Object;
    //   5587: checkcast java/math/BigInteger
    //   5590: invokevirtual intValue : ()I
    //   5593: bipush #32
    //   5595: irem
    //   5596: invokestatic abs : (I)I
    //   5599: invokevirtual charAt : (I)C
    //   5602: invokevirtual append : (C)Ljava/lang/StringBuilder;
    //   5605: pop
    //   5606: iload_2
    //   5607: ifne -> 5724
    //   5610: goto -> 5617
    //   5613: invokestatic a : (Ljava/lang/Throwable;)Ljava/lang/Throwable;
    //   5616: athrow
    //   5617: aload_3
    //   5618: getstatic burp/Zg_5.ZG : Ljava/lang/String;
    //   5621: getstatic burp/Zmu6.Zb : Ljava/lang/Object;
    //   5624: checkcast java/math/BigInteger
    //   5627: invokevirtual intValue : ()I
    //   5630: bipush #32
    //   5632: irem
    //   5633: invokestatic abs : (I)I
    //   5636: invokevirtual charAt : (I)C
    //   5639: invokevirtual append : (C)Ljava/lang/StringBuilder;
    //   5642: pop
    //   5643: iload_2
    //   5644: ifne -> 5724
    //   5647: goto -> 5654
    //   5650: invokestatic a : (Ljava/lang/Throwable;)Ljava/lang/Throwable;
    //   5653: athrow
    //   5654: aload_3
    //   5655: getstatic burp/Zz0.ZX : Ljava/lang/String;
    //   5658: getstatic burp/Zry9.Zw : Ljava/lang/Object;
    //   5661: checkcast java/math/BigInteger
    //   5664: invokevirtual intValue : ()I
    //   5667: bipush #32
    //   5669: irem
    //   5670: invokestatic abs : (I)I
    //   5673: invokevirtual charAt : (I)C
    //   5676: invokevirtual append : (C)Ljava/lang/StringBuilder;
    //   5679: pop
    //   5680: iload_2
    //   5681: ifne -> 5724
    //   5684: goto -> 5691
    //   5687: invokestatic a : (Ljava/lang/Throwable;)Ljava/lang/Throwable;
    //   5690: athrow
    //   5691: aload_3
    //   5692: getstatic burp/Zkaw.ZI : Ljava/lang/String;
    //   5695: getstatic burp/Zmy4.ZB : Ljava/lang/Object;
    //   5698: checkcast java/math/BigInteger
    //   5701: invokevirtual intValue : ()I
    //   5704: bipush #32
    //   5706: irem
    //   5707: invokestatic abs : (I)I
    //   5710: invokevirtual charAt : (I)C
    //   5713: invokevirtual append : (C)Ljava/lang/StringBuilder;
    //   5716: pop
    //   5717: goto -> 5724
    //   5720: invokestatic a : (Ljava/lang/Throwable;)Ljava/lang/Throwable;
    //   5723: athrow
    //   5724: iinc #4, 1
    //   5727: iload_2
    //   5728: ifne -> 4393
    //   5731: aload_3
    //   5732: invokevirtual toString : ()Ljava/lang/String;
    //   5735: putstatic burp/Zkby.Zf : Ljava/lang/String;
    //   5738: getstatic burp/Zkk2.Zq : Ljava/lang/Object;
    //   5741: checkcast java/math/BigInteger
    //   5744: invokevirtual toByteArray : ()[B
    //   5747: astore #4
    //   5749: bipush #32
    //   5751: newarray int
    //   5753: dup
    //   5754: iconst_0
    //   5755: ldc 876216579
    //   5757: iastore
    //   5758: dup
    //   5759: iconst_1
    //   5760: ldc 455999525
    //   5762: iastore
    //   5763: dup
    //   5764: iconst_2
    //   5765: ldc 1043334948
    //   5767: iastore
    //   5768: dup
    //   5769: iconst_3
    //   5770: ldc 439222784
    //   5772: iastore
    //   5773: dup
    //   5774: iconst_4
    //   5775: ldc 372376604
    //   5777: iastore
    //   5778: dup
    //   5779: iconst_5
    //   5780: ldc 707731490
    //   5782: iastore
    //   5783: dup
    //   5784: bipush #6
    //   5786: ldc 389426184
    //   5788: iastore
    //   5789: dup
    //   5790: bipush #7
    //   5792: ldc 973875457
    //   5794: iastore
    //   5795: dup
    //   5796: bipush #8
    //   5798: ldc 389160971
    //   5800: iastore
    //   5801: dup
    //   5802: bipush #9
    //   5804: ldc 907870729
    //   5806: iastore
    //   5807: dup
    //   5808: bipush #10
    //   5810: ldc 121057538
    //   5812: iastore
    //   5813: dup
    //   5814: bipush #11
    //   5816: ldc 840500228
    //   5818: iastore
    //   5819: dup
    //   5820: bipush #12
    //   5822: ldc 254150144
    //   5824: iastore
    //   5825: dup
    //   5826: bipush #13
    //   5828: ldc 924386310
    //   5830: iastore
    //   5831: dup
    //   5832: bipush #14
    //   5834: ldc 187632156
    //   5836: iastore
    //   5837: dup
    //   5838: bipush #15
    //   5840: ldc 874189824
    //   5842: iastore
    //   5843: dup
    //   5844: bipush #16
    //   5846: ldc 655302664
    //   5848: iastore
    //   5849: dup
    //   5850: bipush #17
    //   5852: ldc 890966315
    //   5854: iastore
    //   5855: dup
    //   5856: bipush #18
    //   5858: ldc 722417666
    //   5860: iastore
    //   5861: dup
    //   5862: bipush #19
    //   5864: ldc 1026621720
    //   5866: iastore
    //   5867: dup
    //   5868: bipush #20
    //   5870: ldc 957157408
    //   5872: iastore
    //   5873: dup
    //   5874: bipush #21
    //   5876: ldc 892536332
    //   5878: iastore
    //   5879: dup
    //   5880: bipush #22
    //   5882: ldc 689771012
    //   5884: iastore
    //   5885: dup
    //   5886: bipush #23
    //   5888: ldc 221709344
    //   5890: iastore
    //   5891: dup
    //   5892: bipush #24
    //   5894: ldc 940377620
    //   5896: iastore
    //   5897: dup
    //   5898: bipush #25
    //   5900: ldc 255209728
    //   5902: iastore
    //   5903: dup
    //   5904: bipush #26
    //   5906: ldc 1010368540
    //   5908: iastore
    //   5909: dup
    //   5910: bipush #27
    //   5912: ldc 220604441
    //   5914: iastore
    //   5915: dup
    //   5916: bipush #28
    //   5918: ldc 1008414755
    //   5920: iastore
    //   5921: dup
    //   5922: bipush #29
    //   5924: ldc 187049985
    //   5926: iastore
    //   5927: dup
    //   5928: bipush #30
    //   5930: ldc 943331329
    //   5932: iastore
    //   5933: dup
    //   5934: bipush #31
    //   5936: ldc 170788368
    //   5938: iastore
    //   5939: astore #6
    //   5941: bipush #64
    //   5943: newarray int
    //   5945: dup
    //   5946: iconst_0
    //   5947: ldc 16843776
    //   5949: iastore
    //   5950: dup
    //   5951: iconst_1
    //   5952: iconst_0
    //   5953: iastore
    //   5954: dup
    //   5955: iconst_2
    //   5956: ldc 65536
    //   5958: iastore
    //   5959: dup
    //   5960: iconst_3
    //   5961: ldc 16843780
    //   5963: iastore
    //   5964: dup
    //   5965: iconst_4
    //   5966: ldc 16842756
    //   5968: iastore
    //   5969: dup
    //   5970: iconst_5
    //   5971: ldc 66564
    //   5973: iastore
    //   5974: dup
    //   5975: bipush #6
    //   5977: iconst_4
    //   5978: iastore
    //   5979: dup
    //   5980: bipush #7
    //   5982: ldc 65536
    //   5984: iastore
    //   5985: dup
    //   5986: bipush #8
    //   5988: sipush #1024
    //   5991: iastore
    //   5992: dup
    //   5993: bipush #9
    //   5995: ldc 16843776
    //   5997: iastore
    //   5998: dup
    //   5999: bipush #10
    //   6001: ldc 16843780
    //   6003: iastore
    //   6004: dup
    //   6005: bipush #11
    //   6007: sipush #1024
    //   6010: iastore
    //   6011: dup
    //   6012: bipush #12
    //   6014: ldc 16778244
    //   6016: iastore
    //   6017: dup
    //   6018: bipush #13
    //   6020: ldc 16842756
    //   6022: iastore
    //   6023: dup
    //   6024: bipush #14
    //   6026: ldc 16777216
    //   6028: iastore
    //   6029: dup
    //   6030: bipush #15
    //   6032: iconst_4
    //   6033: iastore
    //   6034: dup
    //   6035: bipush #16
    //   6037: sipush #1028
    //   6040: iastore
    //   6041: dup
    //   6042: bipush #17
    //   6044: ldc 16778240
    //   6046: iastore
    //   6047: dup
    //   6048: bipush #18
    //   6050: ldc 16778240
    //   6052: iastore
    //   6053: dup
    //   6054: bipush #19
    //   6056: ldc 66560
    //   6058: iastore
    //   6059: dup
    //   6060: bipush #20
    //   6062: ldc 66560
    //   6064: iastore
    //   6065: dup
    //   6066: bipush #21
    //   6068: ldc 16842752
    //   6070: iastore
    //   6071: dup
    //   6072: bipush #22
    //   6074: ldc 16842752
    //   6076: iastore
    //   6077: dup
    //   6078: bipush #23
    //   6080: ldc 16778244
    //   6082: iastore
    //   6083: dup
    //   6084: bipush #24
    //   6086: ldc 65540
    //   6088: iastore
    //   6089: dup
    //   6090: bipush #25
    //   6092: ldc 16777220
    //   6094: iastore
    //   6095: dup
    //   6096: bipush #26
    //   6098: ldc 16777220
    //   6100: iastore
    //   6101: dup
    //   6102: bipush #27
    //   6104: ldc 65540
    //   6106: iastore
    //   6107: dup
    //   6108: bipush #28
    //   6110: iconst_0
    //   6111: iastore
    //   6112: dup
    //   6113: bipush #29
    //   6115: sipush #1028
    //   6118: iastore
    //   6119: dup
    //   6120: bipush #30
    //   6122: ldc 66564
    //   6124: iastore
    //   6125: dup
    //   6126: bipush #31
    //   6128: ldc 16777216
    //   6130: iastore
    //   6131: dup
    //   6132: bipush #32
    //   6134: ldc 65536
    //   6136: iastore
    //   6137: dup
    //   6138: bipush #33
    //   6140: ldc 16843780
    //   6142: iastore
    //   6143: dup
    //   6144: bipush #34
    //   6146: iconst_4
    //   6147: iastore
    //   6148: dup
    //   6149: bipush #35
    //   6151: ldc 16842752
    //   6153: iastore
    //   6154: dup
    //   6155: bipush #36
    //   6157: ldc 16843776
    //   6159: iastore
    //   6160: dup
    //   6161: bipush #37
    //   6163: ldc 16777216
    //   6165: iastore
    //   6166: dup
    //   6167: bipush #38
    //   6169: ldc 16777216
    //   6171: iastore
    //   6172: dup
    //   6173: bipush #39
    //   6175: sipush #1024
    //   6178: iastore
    //   6179: dup
    //   6180: bipush #40
    //   6182: ldc 16842756
    //   6184: iastore
    //   6185: dup
    //   6186: bipush #41
    //   6188: ldc 65536
    //   6190: iastore
    //   6191: dup
    //   6192: bipush #42
    //   6194: ldc 66560
    //   6196: iastore
    //   6197: dup
    //   6198: bipush #43
    //   6200: ldc 16777220
    //   6202: iastore
    //   6203: dup
    //   6204: bipush #44
    //   6206: sipush #1024
    //   6209: iastore
    //   6210: dup
    //   6211: bipush #45
    //   6213: iconst_4
    //   6214: iastore
    //   6215: dup
    //   6216: bipush #46
    //   6218: ldc 16778244
    //   6220: iastore
    //   6221: dup
    //   6222: bipush #47
    //   6224: ldc 66564
    //   6226: iastore
    //   6227: dup
    //   6228: bipush #48
    //   6230: ldc 16843780
    //   6232: iastore
    //   6233: dup
    //   6234: bipush #49
    //   6236: ldc 65540
    //   6238: iastore
    //   6239: dup
    //   6240: bipush #50
    //   6242: ldc 16842752
    //   6244: iastore
    //   6245: dup
    //   6246: bipush #51
    //   6248: ldc 16778244
    //   6250: iastore
    //   6251: dup
    //   6252: bipush #52
    //   6254: ldc 16777220
    //   6256: iastore
    //   6257: dup
    //   6258: bipush #53
    //   6260: sipush #1028
    //   6263: iastore
    //   6264: dup
    //   6265: bipush #54
    //   6267: ldc 66564
    //   6269: iastore
    //   6270: dup
    //   6271: bipush #55
    //   6273: ldc 16843776
    //   6275: iastore
    //   6276: dup
    //   6277: bipush #56
    //   6279: sipush #1028
    //   6282: iastore
    //   6283: dup
    //   6284: bipush #57
    //   6286: ldc 16778240
    //   6288: iastore
    //   6289: dup
    //   6290: bipush #58
    //   6292: ldc 16778240
    //   6294: iastore
    //   6295: dup
    //   6296: bipush #59
    //   6298: iconst_0
    //   6299: iastore
    //   6300: dup
    //   6301: bipush #60
    //   6303: ldc 65540
    //   6305: iastore
    //   6306: dup
    //   6307: bipush #61
    //   6309: ldc 66560
    //   6311: iastore
    //   6312: dup
    //   6313: bipush #62
    //   6315: iconst_0
    //   6316: iastore
    //   6317: dup
    //   6318: bipush #63
    //   6320: ldc 16842756
    //   6322: iastore
    //   6323: astore #7
    //   6325: bipush #64
    //   6327: newarray int
    //   6329: dup
    //   6330: iconst_0
    //   6331: ldc -2146402272
    //   6333: iastore
    //   6334: dup
    //   6335: iconst_1
    //   6336: ldc -2147450880
    //   6338: iastore
    //   6339: dup
    //   6340: iconst_2
    //   6341: ldc 32768
    //   6343: iastore
    //   6344: dup
    //   6345: iconst_3
    //   6346: ldc 1081376
    //   6348: iastore
    //   6349: dup
    //   6350: iconst_4
    //   6351: ldc 1048576
    //   6353: iastore
    //   6354: dup
    //   6355: iconst_5
    //   6356: bipush #32
    //   6358: iastore
    //   6359: dup
    //   6360: bipush #6
    //   6362: ldc -2146435040
    //   6364: iastore
    //   6365: dup
    //   6366: bipush #7
    //   6368: ldc -2147450848
    //   6370: iastore
    //   6371: dup
    //   6372: bipush #8
    //   6374: ldc -2147483616
    //   6376: iastore
    //   6377: dup
    //   6378: bipush #9
    //   6380: ldc -2146402272
    //   6382: iastore
    //   6383: dup
    //   6384: bipush #10
    //   6386: ldc -2146402304
    //   6388: iastore
    //   6389: dup
    //   6390: bipush #11
    //   6392: ldc -2147483648
    //   6394: iastore
    //   6395: dup
    //   6396: bipush #12
    //   6398: ldc -2147450880
    //   6400: iastore
    //   6401: dup
    //   6402: bipush #13
    //   6404: ldc 1048576
    //   6406: iastore
    //   6407: dup
    //   6408: bipush #14
    //   6410: bipush #32
    //   6412: iastore
    //   6413: dup
    //   6414: bipush #15
    //   6416: ldc -2146435040
    //   6418: iastore
    //   6419: dup
    //   6420: bipush #16
    //   6422: ldc 1081344
    //   6424: iastore
    //   6425: dup
    //   6426: bipush #17
    //   6428: ldc 1048608
    //   6430: iastore
    //   6431: dup
    //   6432: bipush #18
    //   6434: ldc -2147450848
    //   6436: iastore
    //   6437: dup
    //   6438: bipush #19
    //   6440: iconst_0
    //   6441: iastore
    //   6442: dup
    //   6443: bipush #20
    //   6445: ldc -2147483648
    //   6447: iastore
    //   6448: dup
    //   6449: bipush #21
    //   6451: ldc 32768
    //   6453: iastore
    //   6454: dup
    //   6455: bipush #22
    //   6457: ldc 1081376
    //   6459: iastore
    //   6460: dup
    //   6461: bipush #23
    //   6463: ldc -2146435072
    //   6465: iastore
    //   6466: dup
    //   6467: bipush #24
    //   6469: ldc 1048608
    //   6471: iastore
    //   6472: dup
    //   6473: bipush #25
    //   6475: ldc -2147483616
    //   6477: iastore
    //   6478: dup
    //   6479: bipush #26
    //   6481: iconst_0
    //   6482: iastore
    //   6483: dup
    //   6484: bipush #27
    //   6486: ldc 1081344
    //   6488: iastore
    //   6489: dup
    //   6490: bipush #28
    //   6492: ldc 32800
    //   6494: iastore
    //   6495: dup
    //   6496: bipush #29
    //   6498: ldc -2146402304
    //   6500: iastore
    //   6501: dup
    //   6502: bipush #30
    //   6504: ldc -2146435072
    //   6506: iastore
    //   6507: dup
    //   6508: bipush #31
    //   6510: ldc 32800
    //   6512: iastore
    //   6513: dup
    //   6514: bipush #32
    //   6516: iconst_0
    //   6517: iastore
    //   6518: dup
    //   6519: bipush #33
    //   6521: ldc 1081376
    //   6523: iastore
    //   6524: dup
    //   6525: bipush #34
    //   6527: ldc -2146435040
    //   6529: iastore
    //   6530: dup
    //   6531: bipush #35
    //   6533: ldc 1048576
    //   6535: iastore
    //   6536: dup
    //   6537: bipush #36
    //   6539: ldc -2147450848
    //   6541: iastore
    //   6542: dup
    //   6543: bipush #37
    //   6545: ldc -2146435072
    //   6547: iastore
    //   6548: dup
    //   6549: bipush #38
    //   6551: ldc -2146402304
    //   6553: iastore
    //   6554: dup
    //   6555: bipush #39
    //   6557: ldc 32768
    //   6559: iastore
    //   6560: dup
    //   6561: bipush #40
    //   6563: ldc -2146435072
    //   6565: iastore
    //   6566: dup
    //   6567: bipush #41
    //   6569: ldc -2147450880
    //   6571: iastore
    //   6572: dup
    //   6573: bipush #42
    //   6575: bipush #32
    //   6577: iastore
    //   6578: dup
    //   6579: bipush #43
    //   6581: ldc -2146402272
    //   6583: iastore
    //   6584: dup
    //   6585: bipush #44
    //   6587: ldc 1081376
    //   6589: iastore
    //   6590: dup
    //   6591: bipush #45
    //   6593: bipush #32
    //   6595: iastore
    //   6596: dup
    //   6597: bipush #46
    //   6599: ldc 32768
    //   6601: iastore
    //   6602: dup
    //   6603: bipush #47
    //   6605: ldc -2147483648
    //   6607: iastore
    //   6608: dup
    //   6609: bipush #48
    //   6611: ldc 32800
    //   6613: iastore
    //   6614: dup
    //   6615: bipush #49
    //   6617: ldc -2146402304
    //   6619: iastore
    //   6620: dup
    //   6621: bipush #50
    //   6623: ldc 1048576
    //   6625: iastore
    //   6626: dup
    //   6627: bipush #51
    //   6629: ldc -2147483616
    //   6631: iastore
    //   6632: dup
    //   6633: bipush #52
    //   6635: ldc 1048608
    //   6637: iastore
    //   6638: dup
    //   6639: bipush #53
    //   6641: ldc -2147450848
    //   6643: iastore
    //   6644: dup
    //   6645: bipush #54
    //   6647: ldc -2147483616
    //   6649: iastore
    //   6650: dup
    //   6651: bipush #55
    //   6653: ldc 1048608
    //   6655: iastore
    //   6656: dup
    //   6657: bipush #56
    //   6659: ldc 1081344
    //   6661: iastore
    //   6662: dup
    //   6663: bipush #57
    //   6665: iconst_0
    //   6666: iastore
    //   6667: dup
    //   6668: bipush #58
    //   6670: ldc -2147450880
    //   6672: iastore
    //   6673: dup
    //   6674: bipush #59
    //   6676: ldc 32800
    //   6678: iastore
    //   6679: dup
    //   6680: bipush #60
    //   6682: ldc -2147483648
    //   6684: iastore
    //   6685: dup
    //   6686: bipush #61
    //   6688: ldc -2146435040
    //   6690: iastore
    //   6691: dup
    //   6692: bipush #62
    //   6694: ldc -2146402272
    //   6696: iastore
    //   6697: dup
    //   6698: bipush #63
    //   6700: ldc 1081344
    //   6702: iastore
    //   6703: astore #8
    //   6705: bipush #64
    //   6707: newarray int
    //   6709: dup
    //   6710: iconst_0
    //   6711: sipush #520
    //   6714: iastore
    //   6715: dup
    //   6716: iconst_1
    //   6717: ldc 134349312
    //   6719: iastore
    //   6720: dup
    //   6721: iconst_2
    //   6722: iconst_0
    //   6723: iastore
    //   6724: dup
    //   6725: iconst_3
    //   6726: ldc 134348808
    //   6728: iastore
    //   6729: dup
    //   6730: iconst_4
    //   6731: ldc 134218240
    //   6733: iastore
    //   6734: dup
    //   6735: iconst_5
    //   6736: iconst_0
    //   6737: iastore
    //   6738: dup
    //   6739: bipush #6
    //   6741: ldc 131592
    //   6743: iastore
    //   6744: dup
    //   6745: bipush #7
    //   6747: ldc 134218240
    //   6749: iastore
    //   6750: dup
    //   6751: bipush #8
    //   6753: ldc 131080
    //   6755: iastore
    //   6756: dup
    //   6757: bipush #9
    //   6759: ldc 134217736
    //   6761: iastore
    //   6762: dup
    //   6763: bipush #10
    //   6765: ldc 134217736
    //   6767: iastore
    //   6768: dup
    //   6769: bipush #11
    //   6771: ldc 131072
    //   6773: iastore
    //   6774: dup
    //   6775: bipush #12
    //   6777: ldc 134349320
    //   6779: iastore
    //   6780: dup
    //   6781: bipush #13
    //   6783: ldc 131080
    //   6785: iastore
    //   6786: dup
    //   6787: bipush #14
    //   6789: ldc 134348800
    //   6791: iastore
    //   6792: dup
    //   6793: bipush #15
    //   6795: sipush #520
    //   6798: iastore
    //   6799: dup
    //   6800: bipush #16
    //   6802: ldc 134217728
    //   6804: iastore
    //   6805: dup
    //   6806: bipush #17
    //   6808: bipush #8
    //   6810: iastore
    //   6811: dup
    //   6812: bipush #18
    //   6814: ldc 134349312
    //   6816: iastore
    //   6817: dup
    //   6818: bipush #19
    //   6820: sipush #512
    //   6823: iastore
    //   6824: dup
    //   6825: bipush #20
    //   6827: ldc 131584
    //   6829: iastore
    //   6830: dup
    //   6831: bipush #21
    //   6833: ldc 134348800
    //   6835: iastore
    //   6836: dup
    //   6837: bipush #22
    //   6839: ldc 134348808
    //   6841: iastore
    //   6842: dup
    //   6843: bipush #23
    //   6845: ldc 131592
    //   6847: iastore
    //   6848: dup
    //   6849: bipush #24
    //   6851: ldc 134218248
    //   6853: iastore
    //   6854: dup
    //   6855: bipush #25
    //   6857: ldc 131584
    //   6859: iastore
    //   6860: dup
    //   6861: bipush #26
    //   6863: ldc 131072
    //   6865: iastore
    //   6866: dup
    //   6867: bipush #27
    //   6869: ldc 134218248
    //   6871: iastore
    //   6872: dup
    //   6873: bipush #28
    //   6875: bipush #8
    //   6877: iastore
    //   6878: dup
    //   6879: bipush #29
    //   6881: ldc 134349320
    //   6883: iastore
    //   6884: dup
    //   6885: bipush #30
    //   6887: sipush #512
    //   6890: iastore
    //   6891: dup
    //   6892: bipush #31
    //   6894: ldc 134217728
    //   6896: iastore
    //   6897: dup
    //   6898: bipush #32
    //   6900: ldc 134349312
    //   6902: iastore
    //   6903: dup
    //   6904: bipush #33
    //   6906: ldc 134217728
    //   6908: iastore
    //   6909: dup
    //   6910: bipush #34
    //   6912: ldc 131080
    //   6914: iastore
    //   6915: dup
    //   6916: bipush #35
    //   6918: sipush #520
    //   6921: iastore
    //   6922: dup
    //   6923: bipush #36
    //   6925: ldc 131072
    //   6927: iastore
    //   6928: dup
    //   6929: bipush #37
    //   6931: ldc 134349312
    //   6933: iastore
    //   6934: dup
    //   6935: bipush #38
    //   6937: ldc 134218240
    //   6939: iastore
    //   6940: dup
    //   6941: bipush #39
    //   6943: iconst_0
    //   6944: iastore
    //   6945: dup
    //   6946: bipush #40
    //   6948: sipush #512
    //   6951: iastore
    //   6952: dup
    //   6953: bipush #41
    //   6955: ldc 131080
    //   6957: iastore
    //   6958: dup
    //   6959: bipush #42
    //   6961: ldc 134349320
    //   6963: iastore
    //   6964: dup
    //   6965: bipush #43
    //   6967: ldc 134218240
    //   6969: iastore
    //   6970: dup
    //   6971: bipush #44
    //   6973: ldc 134217736
    //   6975: iastore
    //   6976: dup
    //   6977: bipush #45
    //   6979: sipush #512
    //   6982: iastore
    //   6983: dup
    //   6984: bipush #46
    //   6986: iconst_0
    //   6987: iastore
    //   6988: dup
    //   6989: bipush #47
    //   6991: ldc 134348808
    //   6993: iastore
    //   6994: dup
    //   6995: bipush #48
    //   6997: ldc 134218248
    //   6999: iastore
    //   7000: dup
    //   7001: bipush #49
    //   7003: ldc 131072
    //   7005: iastore
    //   7006: dup
    //   7007: bipush #50
    //   7009: ldc 134217728
    //   7011: iastore
    //   7012: dup
    //   7013: bipush #51
    //   7015: ldc 134349320
    //   7017: iastore
    //   7018: dup
    //   7019: bipush #52
    //   7021: bipush #8
    //   7023: iastore
    //   7024: dup
    //   7025: bipush #53
    //   7027: ldc 131592
    //   7029: iastore
    //   7030: dup
    //   7031: bipush #54
    //   7033: ldc 131584
    //   7035: iastore
    //   7036: dup
    //   7037: bipush #55
    //   7039: ldc 134217736
    //   7041: iastore
    //   7042: dup
    //   7043: bipush #56
    //   7045: ldc 134348800
    //   7047: iastore
    //   7048: dup
    //   7049: bipush #57
    //   7051: ldc 134218248
    //   7053: iastore
    //   7054: dup
    //   7055: bipush #58
    //   7057: sipush #520
    //   7060: iastore
    //   7061: dup
    //   7062: bipush #59
    //   7064: ldc 134348800
    //   7066: iastore
    //   7067: dup
    //   7068: bipush #60
    //   7070: ldc 131592
    //   7072: iastore
    //   7073: dup
    //   7074: bipush #61
    //   7076: bipush #8
    //   7078: iastore
    //   7079: dup
    //   7080: bipush #62
    //   7082: ldc 134348808
    //   7084: iastore
    //   7085: dup
    //   7086: bipush #63
    //   7088: ldc 131584
    //   7090: iastore
    //   7091: astore #9
    //   7093: bipush #64
    //   7095: newarray int
    //   7097: dup
    //   7098: iconst_0
    //   7099: ldc 8396801
    //   7101: iastore
    //   7102: dup
    //   7103: iconst_1
    //   7104: sipush #8321
    //   7107: iastore
    //   7108: dup
    //   7109: iconst_2
    //   7110: sipush #8321
    //   7113: iastore
    //   7114: dup
    //   7115: iconst_3
    //   7116: sipush #128
    //   7119: iastore
    //   7120: dup
    //   7121: iconst_4
    //   7122: ldc 8396928
    //   7124: iastore
    //   7125: dup
    //   7126: iconst_5
    //   7127: ldc 8388737
    //   7129: iastore
    //   7130: dup
    //   7131: bipush #6
    //   7133: ldc 8388609
    //   7135: iastore
    //   7136: dup
    //   7137: bipush #7
    //   7139: sipush #8193
    //   7142: iastore
    //   7143: dup
    //   7144: bipush #8
    //   7146: iconst_0
    //   7147: iastore
    //   7148: dup
    //   7149: bipush #9
    //   7151: ldc 8396800
    //   7153: iastore
    //   7154: dup
    //   7155: bipush #10
    //   7157: ldc 8396800
    //   7159: iastore
    //   7160: dup
    //   7161: bipush #11
    //   7163: ldc 8396929
    //   7165: iastore
    //   7166: dup
    //   7167: bipush #12
    //   7169: sipush #129
    //   7172: iastore
    //   7173: dup
    //   7174: bipush #13
    //   7176: iconst_0
    //   7177: iastore
    //   7178: dup
    //   7179: bipush #14
    //   7181: ldc 8388736
    //   7183: iastore
    //   7184: dup
    //   7185: bipush #15
    //   7187: ldc 8388609
    //   7189: iastore
    //   7190: dup
    //   7191: bipush #16
    //   7193: iconst_1
    //   7194: iastore
    //   7195: dup
    //   7196: bipush #17
    //   7198: sipush #8192
    //   7201: iastore
    //   7202: dup
    //   7203: bipush #18
    //   7205: ldc 8388608
    //   7207: iastore
    //   7208: dup
    //   7209: bipush #19
    //   7211: ldc 8396801
    //   7213: iastore
    //   7214: dup
    //   7215: bipush #20
    //   7217: sipush #128
    //   7220: iastore
    //   7221: dup
    //   7222: bipush #21
    //   7224: ldc 8388608
    //   7226: iastore
    //   7227: dup
    //   7228: bipush #22
    //   7230: sipush #8193
    //   7233: iastore
    //   7234: dup
    //   7235: bipush #23
    //   7237: sipush #8320
    //   7240: iastore
    //   7241: dup
    //   7242: bipush #24
    //   7244: ldc 8388737
    //   7246: iastore
    //   7247: dup
    //   7248: bipush #25
    //   7250: iconst_1
    //   7251: iastore
    //   7252: dup
    //   7253: bipush #26
    //   7255: sipush #8320
    //   7258: iastore
    //   7259: dup
    //   7260: bipush #27
    //   7262: ldc 8388736
    //   7264: iastore
    //   7265: dup
    //   7266: bipush #28
    //   7268: sipush #8192
    //   7271: iastore
    //   7272: dup
    //   7273: bipush #29
    //   7275: ldc 8396928
    //   7277: iastore
    //   7278: dup
    //   7279: bipush #30
    //   7281: ldc 8396929
    //   7283: iastore
    //   7284: dup
    //   7285: bipush #31
    //   7287: sipush #129
    //   7290: iastore
    //   7291: dup
    //   7292: bipush #32
    //   7294: ldc 8388736
    //   7296: iastore
    //   7297: dup
    //   7298: bipush #33
    //   7300: ldc 8388609
    //   7302: iastore
    //   7303: dup
    //   7304: bipush #34
    //   7306: ldc 8396800
    //   7308: iastore
    //   7309: dup
    //   7310: bipush #35
    //   7312: ldc 8396929
    //   7314: iastore
    //   7315: dup
    //   7316: bipush #36
    //   7318: sipush #129
    //   7321: iastore
    //   7322: dup
    //   7323: bipush #37
    //   7325: iconst_0
    //   7326: iastore
    //   7327: dup
    //   7328: bipush #38
    //   7330: iconst_0
    //   7331: iastore
    //   7332: dup
    //   7333: bipush #39
    //   7335: ldc 8396800
    //   7337: iastore
    //   7338: dup
    //   7339: bipush #40
    //   7341: sipush #8320
    //   7344: iastore
    //   7345: dup
    //   7346: bipush #41
    //   7348: ldc 8388736
    //   7350: iastore
    //   7351: dup
    //   7352: bipush #42
    //   7354: ldc 8388737
    //   7356: iastore
    //   7357: dup
    //   7358: bipush #43
    //   7360: iconst_1
    //   7361: iastore
    //   7362: dup
    //   7363: bipush #44
    //   7365: ldc 8396801
    //   7367: iastore
    //   7368: dup
    //   7369: bipush #45
    //   7371: sipush #8321
    //   7374: iastore
    //   7375: dup
    //   7376: bipush #46
    //   7378: sipush #8321
    //   7381: iastore
    //   7382: dup
    //   7383: bipush #47
    //   7385: sipush #128
    //   7388: iastore
    //   7389: dup
    //   7390: bipush #48
    //   7392: ldc 8396929
    //   7394: iastore
    //   7395: dup
    //   7396: bipush #49
    //   7398: sipush #129
    //   7401: iastore
    //   7402: dup
    //   7403: bipush #50
    //   7405: iconst_1
    //   7406: iastore
    //   7407: dup
    //   7408: bipush #51
    //   7410: sipush #8192
    //   7413: iastore
    //   7414: dup
    //   7415: bipush #52
    //   7417: ldc 8388609
    //   7419: iastore
    //   7420: dup
    //   7421: bipush #53
    //   7423: sipush #8193
    //   7426: iastore
    //   7427: dup
    //   7428: bipush #54
    //   7430: ldc 8396928
    //   7432: iastore
    //   7433: dup
    //   7434: bipush #55
    //   7436: ldc 8388737
    //   7438: iastore
    //   7439: dup
    //   7440: bipush #56
    //   7442: sipush #8193
    //   7445: iastore
    //   7446: dup
    //   7447: bipush #57
    //   7449: sipush #8320
    //   7452: iastore
    //   7453: dup
    //   7454: bipush #58
    //   7456: ldc 8388608
    //   7458: iastore
    //   7459: dup
    //   7460: bipush #59
    //   7462: ldc 8396801
    //   7464: iastore
    //   7465: dup
    //   7466: bipush #60
    //   7468: sipush #128
    //   7471: iastore
    //   7472: dup
    //   7473: bipush #61
    //   7475: ldc 8388608
    //   7477: iastore
    //   7478: dup
    //   7479: bipush #62
    //   7481: sipush #8192
    //   7484: iastore
    //   7485: dup
    //   7486: bipush #63
    //   7488: ldc 8396928
    //   7490: iastore
    //   7491: astore #10
    //   7493: bipush #64
    //   7495: newarray int
    //   7497: dup
    //   7498: iconst_0
    //   7499: sipush #256
    //   7502: iastore
    //   7503: dup
    //   7504: iconst_1
    //   7505: ldc 34078976
    //   7507: iastore
    //   7508: dup
    //   7509: iconst_2
    //   7510: ldc 34078720
    //   7512: iastore
    //   7513: dup
    //   7514: iconst_3
    //   7515: ldc 1107296512
    //   7517: iastore
    //   7518: dup
    //   7519: iconst_4
    //   7520: ldc 524288
    //   7522: iastore
    //   7523: dup
    //   7524: iconst_5
    //   7525: sipush #256
    //   7528: iastore
    //   7529: dup
    //   7530: bipush #6
    //   7532: ldc 1073741824
    //   7534: iastore
    //   7535: dup
    //   7536: bipush #7
    //   7538: ldc 34078720
    //   7540: iastore
    //   7541: dup
    //   7542: bipush #8
    //   7544: ldc 1074266368
    //   7546: iastore
    //   7547: dup
    //   7548: bipush #9
    //   7550: ldc 524288
    //   7552: iastore
    //   7553: dup
    //   7554: bipush #10
    //   7556: ldc 33554688
    //   7558: iastore
    //   7559: dup
    //   7560: bipush #11
    //   7562: ldc 1074266368
    //   7564: iastore
    //   7565: dup
    //   7566: bipush #12
    //   7568: ldc 1107296512
    //   7570: iastore
    //   7571: dup
    //   7572: bipush #13
    //   7574: ldc 1107820544
    //   7576: iastore
    //   7577: dup
    //   7578: bipush #14
    //   7580: ldc 524544
    //   7582: iastore
    //   7583: dup
    //   7584: bipush #15
    //   7586: ldc 1073741824
    //   7588: iastore
    //   7589: dup
    //   7590: bipush #16
    //   7592: ldc 33554432
    //   7594: iastore
    //   7595: dup
    //   7596: bipush #17
    //   7598: ldc 1074266112
    //   7600: iastore
    //   7601: dup
    //   7602: bipush #18
    //   7604: ldc 1074266112
    //   7606: iastore
    //   7607: dup
    //   7608: bipush #19
    //   7610: iconst_0
    //   7611: iastore
    //   7612: dup
    //   7613: bipush #20
    //   7615: ldc 1073742080
    //   7617: iastore
    //   7618: dup
    //   7619: bipush #21
    //   7621: ldc 1107820800
    //   7623: iastore
    //   7624: dup
    //   7625: bipush #22
    //   7627: ldc 1107820800
    //   7629: iastore
    //   7630: dup
    //   7631: bipush #23
    //   7633: ldc 33554688
    //   7635: iastore
    //   7636: dup
    //   7637: bipush #24
    //   7639: ldc 1107820544
    //   7641: iastore
    //   7642: dup
    //   7643: bipush #25
    //   7645: ldc 1073742080
    //   7647: iastore
    //   7648: dup
    //   7649: bipush #26
    //   7651: iconst_0
    //   7652: iastore
    //   7653: dup
    //   7654: bipush #27
    //   7656: ldc 1107296256
    //   7658: iastore
    //   7659: dup
    //   7660: bipush #28
    //   7662: ldc 34078976
    //   7664: iastore
    //   7665: dup
    //   7666: bipush #29
    //   7668: ldc 33554432
    //   7670: iastore
    //   7671: dup
    //   7672: bipush #30
    //   7674: ldc 1107296256
    //   7676: iastore
    //   7677: dup
    //   7678: bipush #31
    //   7680: ldc 524544
    //   7682: iastore
    //   7683: dup
    //   7684: bipush #32
    //   7686: ldc 524288
    //   7688: iastore
    //   7689: dup
    //   7690: bipush #33
    //   7692: ldc 1107296512
    //   7694: iastore
    //   7695: dup
    //   7696: bipush #34
    //   7698: sipush #256
    //   7701: iastore
    //   7702: dup
    //   7703: bipush #35
    //   7705: ldc 33554432
    //   7707: iastore
    //   7708: dup
    //   7709: bipush #36
    //   7711: ldc 1073741824
    //   7713: iastore
    //   7714: dup
    //   7715: bipush #37
    //   7717: ldc 34078720
    //   7719: iastore
    //   7720: dup
    //   7721: bipush #38
    //   7723: ldc 1107296512
    //   7725: iastore
    //   7726: dup
    //   7727: bipush #39
    //   7729: ldc 1074266368
    //   7731: iastore
    //   7732: dup
    //   7733: bipush #40
    //   7735: ldc 33554688
    //   7737: iastore
    //   7738: dup
    //   7739: bipush #41
    //   7741: ldc 1073741824
    //   7743: iastore
    //   7744: dup
    //   7745: bipush #42
    //   7747: ldc 1107820544
    //   7749: iastore
    //   7750: dup
    //   7751: bipush #43
    //   7753: ldc 34078976
    //   7755: iastore
    //   7756: dup
    //   7757: bipush #44
    //   7759: ldc 1074266368
    //   7761: iastore
    //   7762: dup
    //   7763: bipush #45
    //   7765: sipush #256
    //   7768: iastore
    //   7769: dup
    //   7770: bipush #46
    //   7772: ldc 33554432
    //   7774: iastore
    //   7775: dup
    //   7776: bipush #47
    //   7778: ldc 1107820544
    //   7780: iastore
    //   7781: dup
    //   7782: bipush #48
    //   7784: ldc 1107820800
    //   7786: iastore
    //   7787: dup
    //   7788: bipush #49
    //   7790: ldc 524544
    //   7792: iastore
    //   7793: dup
    //   7794: bipush #50
    //   7796: ldc 1107296256
    //   7798: iastore
    //   7799: dup
    //   7800: bipush #51
    //   7802: ldc 1107820800
    //   7804: iastore
    //   7805: dup
    //   7806: bipush #52
    //   7808: ldc 34078720
    //   7810: iastore
    //   7811: dup
    //   7812: bipush #53
    //   7814: iconst_0
    //   7815: iastore
    //   7816: dup
    //   7817: bipush #54
    //   7819: ldc 1074266112
    //   7821: iastore
    //   7822: dup
    //   7823: bipush #55
    //   7825: ldc 1107296256
    //   7827: iastore
    //   7828: dup
    //   7829: bipush #56
    //   7831: ldc 524544
    //   7833: iastore
    //   7834: dup
    //   7835: bipush #57
    //   7837: ldc 33554688
    //   7839: iastore
    //   7840: dup
    //   7841: bipush #58
    //   7843: ldc 1073742080
    //   7845: iastore
    //   7846: dup
    //   7847: bipush #59
    //   7849: ldc 524288
    //   7851: iastore
    //   7852: dup
    //   7853: bipush #60
    //   7855: iconst_0
    //   7856: iastore
    //   7857: dup
    //   7858: bipush #61
    //   7860: ldc 1074266112
    //   7862: iastore
    //   7863: dup
    //   7864: bipush #62
    //   7866: ldc 34078976
    //   7868: iastore
    //   7869: dup
    //   7870: bipush #63
    //   7872: ldc 1073742080
    //   7874: iastore
    //   7875: astore #11
    //   7877: bipush #64
    //   7879: newarray int
    //   7881: dup
    //   7882: iconst_0
    //   7883: ldc 536870928
    //   7885: iastore
    //   7886: dup
    //   7887: iconst_1
    //   7888: ldc 541065216
    //   7890: iastore
    //   7891: dup
    //   7892: iconst_2
    //   7893: sipush #16384
    //   7896: iastore
    //   7897: dup
    //   7898: iconst_3
    //   7899: ldc 541081616
    //   7901: iastore
    //   7902: dup
    //   7903: iconst_4
    //   7904: ldc 541065216
    //   7906: iastore
    //   7907: dup
    //   7908: iconst_5
    //   7909: bipush #16
    //   7911: iastore
    //   7912: dup
    //   7913: bipush #6
    //   7915: ldc 541081616
    //   7917: iastore
    //   7918: dup
    //   7919: bipush #7
    //   7921: ldc 4194304
    //   7923: iastore
    //   7924: dup
    //   7925: bipush #8
    //   7927: ldc 536887296
    //   7929: iastore
    //   7930: dup
    //   7931: bipush #9
    //   7933: ldc 4210704
    //   7935: iastore
    //   7936: dup
    //   7937: bipush #10
    //   7939: ldc 4194304
    //   7941: iastore
    //   7942: dup
    //   7943: bipush #11
    //   7945: ldc 536870928
    //   7947: iastore
    //   7948: dup
    //   7949: bipush #12
    //   7951: ldc 4194320
    //   7953: iastore
    //   7954: dup
    //   7955: bipush #13
    //   7957: ldc 536887296
    //   7959: iastore
    //   7960: dup
    //   7961: bipush #14
    //   7963: ldc 536870912
    //   7965: iastore
    //   7966: dup
    //   7967: bipush #15
    //   7969: sipush #16400
    //   7972: iastore
    //   7973: dup
    //   7974: bipush #16
    //   7976: iconst_0
    //   7977: iastore
    //   7978: dup
    //   7979: bipush #17
    //   7981: ldc 4194320
    //   7983: iastore
    //   7984: dup
    //   7985: bipush #18
    //   7987: ldc 536887312
    //   7989: iastore
    //   7990: dup
    //   7991: bipush #19
    //   7993: sipush #16384
    //   7996: iastore
    //   7997: dup
    //   7998: bipush #20
    //   8000: ldc 4210688
    //   8002: iastore
    //   8003: dup
    //   8004: bipush #21
    //   8006: ldc 536887312
    //   8008: iastore
    //   8009: dup
    //   8010: bipush #22
    //   8012: bipush #16
    //   8014: iastore
    //   8015: dup
    //   8016: bipush #23
    //   8018: ldc 541065232
    //   8020: iastore
    //   8021: dup
    //   8022: bipush #24
    //   8024: ldc 541065232
    //   8026: iastore
    //   8027: dup
    //   8028: bipush #25
    //   8030: iconst_0
    //   8031: iastore
    //   8032: dup
    //   8033: bipush #26
    //   8035: ldc 4210704
    //   8037: iastore
    //   8038: dup
    //   8039: bipush #27
    //   8041: ldc 541081600
    //   8043: iastore
    //   8044: dup
    //   8045: bipush #28
    //   8047: sipush #16400
    //   8050: iastore
    //   8051: dup
    //   8052: bipush #29
    //   8054: ldc 4210688
    //   8056: iastore
    //   8057: dup
    //   8058: bipush #30
    //   8060: ldc 541081600
    //   8062: iastore
    //   8063: dup
    //   8064: bipush #31
    //   8066: ldc 536870912
    //   8068: iastore
    //   8069: dup
    //   8070: bipush #32
    //   8072: ldc 536887296
    //   8074: iastore
    //   8075: dup
    //   8076: bipush #33
    //   8078: bipush #16
    //   8080: iastore
    //   8081: dup
    //   8082: bipush #34
    //   8084: ldc 541065232
    //   8086: iastore
    //   8087: dup
    //   8088: bipush #35
    //   8090: ldc 4210688
    //   8092: iastore
    //   8093: dup
    //   8094: bipush #36
    //   8096: ldc 541081616
    //   8098: iastore
    //   8099: dup
    //   8100: bipush #37
    //   8102: ldc 4194304
    //   8104: iastore
    //   8105: dup
    //   8106: bipush #38
    //   8108: sipush #16400
    //   8111: iastore
    //   8112: dup
    //   8113: bipush #39
    //   8115: ldc 536870928
    //   8117: iastore
    //   8118: dup
    //   8119: bipush #40
    //   8121: ldc 4194304
    //   8123: iastore
    //   8124: dup
    //   8125: bipush #41
    //   8127: ldc 536887296
    //   8129: iastore
    //   8130: dup
    //   8131: bipush #42
    //   8133: ldc 536870912
    //   8135: iastore
    //   8136: dup
    //   8137: bipush #43
    //   8139: sipush #16400
    //   8142: iastore
    //   8143: dup
    //   8144: bipush #44
    //   8146: ldc 536870928
    //   8148: iastore
    //   8149: dup
    //   8150: bipush #45
    //   8152: ldc 541081616
    //   8154: iastore
    //   8155: dup
    //   8156: bipush #46
    //   8158: ldc 4210688
    //   8160: iastore
    //   8161: dup
    //   8162: bipush #47
    //   8164: ldc 541065216
    //   8166: iastore
    //   8167: dup
    //   8168: bipush #48
    //   8170: ldc 4210704
    //   8172: iastore
    //   8173: dup
    //   8174: bipush #49
    //   8176: ldc 541081600
    //   8178: iastore
    //   8179: dup
    //   8180: bipush #50
    //   8182: iconst_0
    //   8183: iastore
    //   8184: dup
    //   8185: bipush #51
    //   8187: ldc 541065232
    //   8189: iastore
    //   8190: dup
    //   8191: bipush #52
    //   8193: bipush #16
    //   8195: iastore
    //   8196: dup
    //   8197: bipush #53
    //   8199: sipush #16384
    //   8202: iastore
    //   8203: dup
    //   8204: bipush #54
    //   8206: ldc 541065216
    //   8208: iastore
    //   8209: dup
    //   8210: bipush #55
    //   8212: ldc 4210704
    //   8214: iastore
    //   8215: dup
    //   8216: bipush #56
    //   8218: sipush #16384
    //   8221: iastore
    //   8222: dup
    //   8223: bipush #57
    //   8225: ldc 4194320
    //   8227: iastore
    //   8228: dup
    //   8229: bipush #58
    //   8231: ldc 536887312
    //   8233: iastore
    //   8234: dup
    //   8235: bipush #59
    //   8237: iconst_0
    //   8238: iastore
    //   8239: dup
    //   8240: bipush #60
    //   8242: ldc 541081600
    //   8244: iastore
    //   8245: dup
    //   8246: bipush #61
    //   8248: ldc 536870912
    //   8250: iastore
    //   8251: dup
    //   8252: bipush #62
    //   8254: ldc 4194320
    //   8256: iastore
    //   8257: dup
    //   8258: bipush #63
    //   8260: ldc 536887312
    //   8262: iastore
    //   8263: astore #12
    //   8265: bipush #64
    //   8267: newarray int
    //   8269: dup
    //   8270: iconst_0
    //   8271: ldc 2097152
    //   8273: iastore
    //   8274: dup
    //   8275: iconst_1
    //   8276: ldc 69206018
    //   8278: iastore
    //   8279: dup
    //   8280: iconst_2
    //   8281: ldc 67110914
    //   8283: iastore
    //   8284: dup
    //   8285: iconst_3
    //   8286: iconst_0
    //   8287: iastore
    //   8288: dup
    //   8289: iconst_4
    //   8290: sipush #2048
    //   8293: iastore
    //   8294: dup
    //   8295: iconst_5
    //   8296: ldc 67110914
    //   8298: iastore
    //   8299: dup
    //   8300: bipush #6
    //   8302: ldc 2099202
    //   8304: iastore
    //   8305: dup
    //   8306: bipush #7
    //   8308: ldc 69208064
    //   8310: iastore
    //   8311: dup
    //   8312: bipush #8
    //   8314: ldc 69208066
    //   8316: iastore
    //   8317: dup
    //   8318: bipush #9
    //   8320: ldc 2097152
    //   8322: iastore
    //   8323: dup
    //   8324: bipush #10
    //   8326: iconst_0
    //   8327: iastore
    //   8328: dup
    //   8329: bipush #11
    //   8331: ldc 67108866
    //   8333: iastore
    //   8334: dup
    //   8335: bipush #12
    //   8337: iconst_2
    //   8338: iastore
    //   8339: dup
    //   8340: bipush #13
    //   8342: ldc 67108864
    //   8344: iastore
    //   8345: dup
    //   8346: bipush #14
    //   8348: ldc 69206018
    //   8350: iastore
    //   8351: dup
    //   8352: bipush #15
    //   8354: sipush #2050
    //   8357: iastore
    //   8358: dup
    //   8359: bipush #16
    //   8361: ldc 67110912
    //   8363: iastore
    //   8364: dup
    //   8365: bipush #17
    //   8367: ldc 2099202
    //   8369: iastore
    //   8370: dup
    //   8371: bipush #18
    //   8373: ldc 2097154
    //   8375: iastore
    //   8376: dup
    //   8377: bipush #19
    //   8379: ldc 67110912
    //   8381: iastore
    //   8382: dup
    //   8383: bipush #20
    //   8385: ldc 67108866
    //   8387: iastore
    //   8388: dup
    //   8389: bipush #21
    //   8391: ldc 69206016
    //   8393: iastore
    //   8394: dup
    //   8395: bipush #22
    //   8397: ldc 69208064
    //   8399: iastore
    //   8400: dup
    //   8401: bipush #23
    //   8403: ldc 2097154
    //   8405: iastore
    //   8406: dup
    //   8407: bipush #24
    //   8409: ldc 69206016
    //   8411: iastore
    //   8412: dup
    //   8413: bipush #25
    //   8415: sipush #2048
    //   8418: iastore
    //   8419: dup
    //   8420: bipush #26
    //   8422: sipush #2050
    //   8425: iastore
    //   8426: dup
    //   8427: bipush #27
    //   8429: ldc 69208066
    //   8431: iastore
    //   8432: dup
    //   8433: bipush #28
    //   8435: ldc 2099200
    //   8437: iastore
    //   8438: dup
    //   8439: bipush #29
    //   8441: iconst_2
    //   8442: iastore
    //   8443: dup
    //   8444: bipush #30
    //   8446: ldc 67108864
    //   8448: iastore
    //   8449: dup
    //   8450: bipush #31
    //   8452: ldc 2099200
    //   8454: iastore
    //   8455: dup
    //   8456: bipush #32
    //   8458: ldc 67108864
    //   8460: iastore
    //   8461: dup
    //   8462: bipush #33
    //   8464: ldc 2099200
    //   8466: iastore
    //   8467: dup
    //   8468: bipush #34
    //   8470: ldc 2097152
    //   8472: iastore
    //   8473: dup
    //   8474: bipush #35
    //   8476: ldc 67110914
    //   8478: iastore
    //   8479: dup
    //   8480: bipush #36
    //   8482: ldc 67110914
    //   8484: iastore
    //   8485: dup
    //   8486: bipush #37
    //   8488: ldc 69206018
    //   8490: iastore
    //   8491: dup
    //   8492: bipush #38
    //   8494: ldc 69206018
    //   8496: iastore
    //   8497: dup
    //   8498: bipush #39
    //   8500: iconst_2
    //   8501: iastore
    //   8502: dup
    //   8503: bipush #40
    //   8505: ldc 2097154
    //   8507: iastore
    //   8508: dup
    //   8509: bipush #41
    //   8511: ldc 67108864
    //   8513: iastore
    //   8514: dup
    //   8515: bipush #42
    //   8517: ldc 67110912
    //   8519: iastore
    //   8520: dup
    //   8521: bipush #43
    //   8523: ldc 2097152
    //   8525: iastore
    //   8526: dup
    //   8527: bipush #44
    //   8529: ldc 69208064
    //   8531: iastore
    //   8532: dup
    //   8533: bipush #45
    //   8535: sipush #2050
    //   8538: iastore
    //   8539: dup
    //   8540: bipush #46
    //   8542: ldc 2099202
    //   8544: iastore
    //   8545: dup
    //   8546: bipush #47
    //   8548: ldc 69208064
    //   8550: iastore
    //   8551: dup
    //   8552: bipush #48
    //   8554: sipush #2050
    //   8557: iastore
    //   8558: dup
    //   8559: bipush #49
    //   8561: ldc 67108866
    //   8563: iastore
    //   8564: dup
    //   8565: bipush #50
    //   8567: ldc 69208066
    //   8569: iastore
    //   8570: dup
    //   8571: bipush #51
    //   8573: ldc 69206016
    //   8575: iastore
    //   8576: dup
    //   8577: bipush #52
    //   8579: ldc 2099200
    //   8581: iastore
    //   8582: dup
    //   8583: bipush #53
    //   8585: iconst_0
    //   8586: iastore
    //   8587: dup
    //   8588: bipush #54
    //   8590: iconst_2
    //   8591: iastore
    //   8592: dup
    //   8593: bipush #55
    //   8595: ldc 69208066
    //   8597: iastore
    //   8598: dup
    //   8599: bipush #56
    //   8601: iconst_0
    //   8602: iastore
    //   8603: dup
    //   8604: bipush #57
    //   8606: ldc 2099202
    //   8608: iastore
    //   8609: dup
    //   8610: bipush #58
    //   8612: ldc 69206016
    //   8614: iastore
    //   8615: dup
    //   8616: bipush #59
    //   8618: sipush #2048
    //   8621: iastore
    //   8622: dup
    //   8623: bipush #60
    //   8625: ldc 67108866
    //   8627: iastore
    //   8628: dup
    //   8629: bipush #61
    //   8631: ldc 67110912
    //   8633: iastore
    //   8634: dup
    //   8635: bipush #62
    //   8637: sipush #2048
    //   8640: iastore
    //   8641: dup
    //   8642: bipush #63
    //   8644: ldc 2097154
    //   8646: iastore
    //   8647: astore #13
    //   8649: bipush #64
    //   8651: newarray int
    //   8653: dup
    //   8654: iconst_0
    //   8655: ldc 268439616
    //   8657: iastore
    //   8658: dup
    //   8659: iconst_1
    //   8660: sipush #4096
    //   8663: iastore
    //   8664: dup
    //   8665: iconst_2
    //   8666: ldc 262144
    //   8668: iastore
    //   8669: dup
    //   8670: iconst_3
    //   8671: ldc 268701760
    //   8673: iastore
    //   8674: dup
    //   8675: iconst_4
    //   8676: ldc 268435456
    //   8678: iastore
    //   8679: dup
    //   8680: iconst_5
    //   8681: ldc 268439616
    //   8683: iastore
    //   8684: dup
    //   8685: bipush #6
    //   8687: bipush #64
    //   8689: iastore
    //   8690: dup
    //   8691: bipush #7
    //   8693: ldc 268435456
    //   8695: iastore
    //   8696: dup
    //   8697: bipush #8
    //   8699: ldc 262208
    //   8701: iastore
    //   8702: dup
    //   8703: bipush #9
    //   8705: ldc 268697600
    //   8707: iastore
    //   8708: dup
    //   8709: bipush #10
    //   8711: ldc 268701760
    //   8713: iastore
    //   8714: dup
    //   8715: bipush #11
    //   8717: ldc 266240
    //   8719: iastore
    //   8720: dup
    //   8721: bipush #12
    //   8723: ldc 268701696
    //   8725: iastore
    //   8726: dup
    //   8727: bipush #13
    //   8729: ldc 266304
    //   8731: iastore
    //   8732: dup
    //   8733: bipush #14
    //   8735: sipush #4096
    //   8738: iastore
    //   8739: dup
    //   8740: bipush #15
    //   8742: bipush #64
    //   8744: iastore
    //   8745: dup
    //   8746: bipush #16
    //   8748: ldc 268697600
    //   8750: iastore
    //   8751: dup
    //   8752: bipush #17
    //   8754: ldc 268435520
    //   8756: iastore
    //   8757: dup
    //   8758: bipush #18
    //   8760: ldc 268439552
    //   8762: iastore
    //   8763: dup
    //   8764: bipush #19
    //   8766: sipush #4160
    //   8769: iastore
    //   8770: dup
    //   8771: bipush #20
    //   8773: ldc 266240
    //   8775: iastore
    //   8776: dup
    //   8777: bipush #21
    //   8779: ldc 262208
    //   8781: iastore
    //   8782: dup
    //   8783: bipush #22
    //   8785: ldc 268697664
    //   8787: iastore
    //   8788: dup
    //   8789: bipush #23
    //   8791: ldc 268701696
    //   8793: iastore
    //   8794: dup
    //   8795: bipush #24
    //   8797: sipush #4160
    //   8800: iastore
    //   8801: dup
    //   8802: bipush #25
    //   8804: iconst_0
    //   8805: iastore
    //   8806: dup
    //   8807: bipush #26
    //   8809: iconst_0
    //   8810: iastore
    //   8811: dup
    //   8812: bipush #27
    //   8814: ldc 268697664
    //   8816: iastore
    //   8817: dup
    //   8818: bipush #28
    //   8820: ldc 268435520
    //   8822: iastore
    //   8823: dup
    //   8824: bipush #29
    //   8826: ldc 268439552
    //   8828: iastore
    //   8829: dup
    //   8830: bipush #30
    //   8832: ldc 266304
    //   8834: iastore
    //   8835: dup
    //   8836: bipush #31
    //   8838: ldc 262144
    //   8840: iastore
    //   8841: dup
    //   8842: bipush #32
    //   8844: ldc 266304
    //   8846: iastore
    //   8847: dup
    //   8848: bipush #33
    //   8850: ldc 262144
    //   8852: iastore
    //   8853: dup
    //   8854: bipush #34
    //   8856: ldc 268701696
    //   8858: iastore
    //   8859: dup
    //   8860: bipush #35
    //   8862: sipush #4096
    //   8865: iastore
    //   8866: dup
    //   8867: bipush #36
    //   8869: bipush #64
    //   8871: iastore
    //   8872: dup
    //   8873: bipush #37
    //   8875: ldc 268697664
    //   8877: iastore
    //   8878: dup
    //   8879: bipush #38
    //   8881: sipush #4096
    //   8884: iastore
    //   8885: dup
    //   8886: bipush #39
    //   8888: ldc 266304
    //   8890: iastore
    //   8891: dup
    //   8892: bipush #40
    //   8894: ldc 268439552
    //   8896: iastore
    //   8897: dup
    //   8898: bipush #41
    //   8900: bipush #64
    //   8902: iastore
    //   8903: dup
    //   8904: bipush #42
    //   8906: ldc 268435520
    //   8908: iastore
    //   8909: dup
    //   8910: bipush #43
    //   8912: ldc 268697600
    //   8914: iastore
    //   8915: dup
    //   8916: bipush #44
    //   8918: ldc 268697664
    //   8920: iastore
    //   8921: dup
    //   8922: bipush #45
    //   8924: ldc 268435456
    //   8926: iastore
    //   8927: dup
    //   8928: bipush #46
    //   8930: ldc 262144
    //   8932: iastore
    //   8933: dup
    //   8934: bipush #47
    //   8936: ldc 268439616
    //   8938: iastore
    //   8939: dup
    //   8940: bipush #48
    //   8942: iconst_0
    //   8943: iastore
    //   8944: dup
    //   8945: bipush #49
    //   8947: ldc 268701760
    //   8949: iastore
    //   8950: dup
    //   8951: bipush #50
    //   8953: ldc 262208
    //   8955: iastore
    //   8956: dup
    //   8957: bipush #51
    //   8959: ldc 268435520
    //   8961: iastore
    //   8962: dup
    //   8963: bipush #52
    //   8965: ldc 268697600
    //   8967: iastore
    //   8968: dup
    //   8969: bipush #53
    //   8971: ldc 268439552
    //   8973: iastore
    //   8974: dup
    //   8975: bipush #54
    //   8977: ldc 268439616
    //   8979: iastore
    //   8980: dup
    //   8981: bipush #55
    //   8983: iconst_0
    //   8984: iastore
    //   8985: dup
    //   8986: bipush #56
    //   8988: ldc 268701760
    //   8990: iastore
    //   8991: dup
    //   8992: bipush #57
    //   8994: ldc 266240
    //   8996: iastore
    //   8997: dup
    //   8998: bipush #58
    //   9000: ldc 266240
    //   9002: iastore
    //   9003: dup
    //   9004: bipush #59
    //   9006: sipush #4160
    //   9009: iastore
    //   9010: dup
    //   9011: bipush #60
    //   9013: sipush #4160
    //   9016: iastore
    //   9017: dup
    //   9018: bipush #61
    //   9020: ldc 262208
    //   9022: iastore
    //   9023: dup
    //   9024: bipush #62
    //   9026: ldc 268435456
    //   9028: iastore
    //   9029: dup
    //   9030: bipush #63
    //   9032: ldc 268701696
    //   9034: iastore
    //   9035: astore #14
    //   9037: aload #4
    //   9039: arraylength
    //   9040: istore #15
    //   9042: iload #15
    //   9044: bipush #8
    //   9046: irem
    //   9047: ifeq -> 9071
    //   9050: new java/lang/Exception
    //   9053: dup
    //   9054: sipush #-32594
    //   9057: sipush #-1151
    //   9060: invokestatic a : (II)Ljava/lang/String;
    //   9063: invokespecial <init> : (Ljava/lang/String;)V
    //   9066: athrow
    //   9067: invokestatic a : (Ljava/lang/Throwable;)Ljava/lang/Throwable;
    //   9070: athrow
    //   9071: iconst_2
    //   9072: newarray int
    //   9074: astore #16
    //   9076: iload #15
    //   9078: newarray byte
    //   9080: astore #17
    //   9082: iload #15
    //   9084: bipush #8
    //   9086: idiv
    //   9087: istore #18
    //   9089: iconst_0
    //   9090: istore #19
    //   9092: iload #19
    //   9094: iload #18
    //   9096: if_icmpge -> 10014
    //   9099: iload #19
    //   9101: bipush #8
    //   9103: imul
    //   9104: istore #20
    //   9106: iconst_0
    //   9107: istore #21
    //   9109: iload #21
    //   9111: iconst_2
    //   9112: if_icmpge -> 9201
    //   9115: aload #16
    //   9117: iload #21
    //   9119: aload #4
    //   9121: iload #20
    //   9123: iload #21
    //   9125: iconst_4
    //   9126: imul
    //   9127: iadd
    //   9128: baload
    //   9129: sipush #255
    //   9132: iand
    //   9133: bipush #24
    //   9135: ishl
    //   9136: aload #4
    //   9138: iload #20
    //   9140: iload #21
    //   9142: iconst_4
    //   9143: imul
    //   9144: iadd
    //   9145: iconst_1
    //   9146: iadd
    //   9147: baload
    //   9148: sipush #255
    //   9151: iand
    //   9152: bipush #16
    //   9154: ishl
    //   9155: ior
    //   9156: aload #4
    //   9158: iload #20
    //   9160: iload #21
    //   9162: iconst_4
    //   9163: imul
    //   9164: iadd
    //   9165: iconst_2
    //   9166: iadd
    //   9167: baload
    //   9168: sipush #255
    //   9171: iand
    //   9172: bipush #8
    //   9174: ishl
    //   9175: ior
    //   9176: aload #4
    //   9178: iload #20
    //   9180: iload #21
    //   9182: iconst_4
    //   9183: imul
    //   9184: iadd
    //   9185: iconst_3
    //   9186: iadd
    //   9187: baload
    //   9188: sipush #255
    //   9191: iand
    //   9192: ior
    //   9193: iastore
    //   9194: iinc #21, 1
    //   9197: iload_2
    //   9198: ifne -> 9109
    //   9201: iconst_0
    //   9202: istore #26
    //   9204: aload #16
    //   9206: iconst_0
    //   9207: iaload
    //   9208: istore #24
    //   9210: aload #16
    //   9212: iconst_1
    //   9213: iaload
    //   9214: istore #23
    //   9216: iload #24
    //   9218: iconst_4
    //   9219: iushr
    //   9220: iload #23
    //   9222: ixor
    //   9223: ldc 252645135
    //   9225: iand
    //   9226: istore #22
    //   9228: iload #23
    //   9230: iload #22
    //   9232: ixor
    //   9233: istore #23
    //   9235: iload #24
    //   9237: iload #22
    //   9239: iconst_4
    //   9240: ishl
    //   9241: ixor
    //   9242: istore #24
    //   9244: iload #24
    //   9246: bipush #16
    //   9248: iushr
    //   9249: iload #23
    //   9251: ixor
    //   9252: ldc 65535
    //   9254: iand
    //   9255: istore #22
    //   9257: iload #23
    //   9259: iload #22
    //   9261: ixor
    //   9262: istore #23
    //   9264: iload #24
    //   9266: iload #22
    //   9268: bipush #16
    //   9270: ishl
    //   9271: ixor
    //   9272: istore #24
    //   9274: iload #23
    //   9276: iconst_2
    //   9277: iushr
    //   9278: iload #24
    //   9280: ixor
    //   9281: ldc 858993459
    //   9283: iand
    //   9284: istore #22
    //   9286: iload #24
    //   9288: iload #22
    //   9290: ixor
    //   9291: istore #24
    //   9293: iload #23
    //   9295: iload #22
    //   9297: iconst_2
    //   9298: ishl
    //   9299: ixor
    //   9300: istore #23
    //   9302: iload #23
    //   9304: bipush #8
    //   9306: iushr
    //   9307: iload #24
    //   9309: ixor
    //   9310: ldc 16711935
    //   9312: iand
    //   9313: istore #22
    //   9315: iload #24
    //   9317: iload #22
    //   9319: ixor
    //   9320: istore #24
    //   9322: iload #23
    //   9324: iload #22
    //   9326: bipush #8
    //   9328: ishl
    //   9329: ixor
    //   9330: istore #23
    //   9332: iload #23
    //   9334: iconst_1
    //   9335: ishl
    //   9336: iload #23
    //   9338: bipush #31
    //   9340: iushr
    //   9341: iconst_1
    //   9342: iand
    //   9343: ior
    //   9344: istore #23
    //   9346: iload #24
    //   9348: iload #23
    //   9350: ixor
    //   9351: ldc -1431655766
    //   9353: iand
    //   9354: istore #22
    //   9356: iload #24
    //   9358: iload #22
    //   9360: ixor
    //   9361: istore #24
    //   9363: iload #23
    //   9365: iload #22
    //   9367: ixor
    //   9368: istore #23
    //   9370: iload #24
    //   9372: iconst_1
    //   9373: ishl
    //   9374: iload #24
    //   9376: bipush #31
    //   9378: iushr
    //   9379: iconst_1
    //   9380: iand
    //   9381: ior
    //   9382: istore #24
    //   9384: iconst_0
    //   9385: istore #25
    //   9387: iload #25
    //   9389: bipush #8
    //   9391: if_icmpge -> 9729
    //   9394: iload #23
    //   9396: bipush #28
    //   9398: ishl
    //   9399: iload #23
    //   9401: iconst_4
    //   9402: iushr
    //   9403: ior
    //   9404: istore #22
    //   9406: iload #22
    //   9408: aload #6
    //   9410: iload #26
    //   9412: iinc #26, 1
    //   9415: iaload
    //   9416: ixor
    //   9417: istore #22
    //   9419: aload #13
    //   9421: iload #22
    //   9423: bipush #63
    //   9425: iand
    //   9426: iaload
    //   9427: istore #21
    //   9429: iload #21
    //   9431: aload #11
    //   9433: iload #22
    //   9435: bipush #8
    //   9437: iushr
    //   9438: bipush #63
    //   9440: iand
    //   9441: iaload
    //   9442: ior
    //   9443: istore #21
    //   9445: iload #21
    //   9447: aload #9
    //   9449: iload #22
    //   9451: bipush #16
    //   9453: iushr
    //   9454: bipush #63
    //   9456: iand
    //   9457: iaload
    //   9458: ior
    //   9459: istore #21
    //   9461: iload #21
    //   9463: aload #7
    //   9465: iload #22
    //   9467: bipush #24
    //   9469: iushr
    //   9470: bipush #63
    //   9472: iand
    //   9473: iaload
    //   9474: ior
    //   9475: istore #21
    //   9477: iload #23
    //   9479: aload #6
    //   9481: iload #26
    //   9483: iinc #26, 1
    //   9486: iaload
    //   9487: ixor
    //   9488: istore #22
    //   9490: iload #21
    //   9492: aload #14
    //   9494: iload #22
    //   9496: bipush #63
    //   9498: iand
    //   9499: iaload
    //   9500: ior
    //   9501: istore #21
    //   9503: iload #21
    //   9505: aload #12
    //   9507: iload #22
    //   9509: bipush #8
    //   9511: iushr
    //   9512: bipush #63
    //   9514: iand
    //   9515: iaload
    //   9516: ior
    //   9517: istore #21
    //   9519: iload #21
    //   9521: aload #10
    //   9523: iload #22
    //   9525: bipush #16
    //   9527: iushr
    //   9528: bipush #63
    //   9530: iand
    //   9531: iaload
    //   9532: ior
    //   9533: istore #21
    //   9535: iload #21
    //   9537: aload #8
    //   9539: iload #22
    //   9541: bipush #24
    //   9543: iushr
    //   9544: bipush #63
    //   9546: iand
    //   9547: iaload
    //   9548: ior
    //   9549: istore #21
    //   9551: iload #24
    //   9553: iload #21
    //   9555: ixor
    //   9556: istore #24
    //   9558: iload #24
    //   9560: bipush #28
    //   9562: ishl
    //   9563: iload #24
    //   9565: iconst_4
    //   9566: iushr
    //   9567: ior
    //   9568: istore #22
    //   9570: iload #22
    //   9572: aload #6
    //   9574: iload #26
    //   9576: iinc #26, 1
    //   9579: iaload
    //   9580: ixor
    //   9581: istore #22
    //   9583: aload #13
    //   9585: iload #22
    //   9587: bipush #63
    //   9589: iand
    //   9590: iaload
    //   9591: istore #21
    //   9593: iload #21
    //   9595: aload #11
    //   9597: iload #22
    //   9599: bipush #8
    //   9601: iushr
    //   9602: bipush #63
    //   9604: iand
    //   9605: iaload
    //   9606: ior
    //   9607: istore #21
    //   9609: iload #21
    //   9611: aload #9
    //   9613: iload #22
    //   9615: bipush #16
    //   9617: iushr
    //   9618: bipush #63
    //   9620: iand
    //   9621: iaload
    //   9622: ior
    //   9623: istore #21
    //   9625: iload #21
    //   9627: aload #7
    //   9629: iload #22
    //   9631: bipush #24
    //   9633: iushr
    //   9634: bipush #63
    //   9636: iand
    //   9637: iaload
    //   9638: ior
    //   9639: istore #21
    //   9641: iload #24
    //   9643: aload #6
    //   9645: iload #26
    //   9647: iinc #26, 1
    //   9650: iaload
    //   9651: ixor
    //   9652: istore #22
    //   9654: iload #21
    //   9656: aload #14
    //   9658: iload #22
    //   9660: bipush #63
    //   9662: iand
    //   9663: iaload
    //   9664: ior
    //   9665: istore #21
    //   9667: iload #21
    //   9669: aload #12
    //   9671: iload #22
    //   9673: bipush #8
    //   9675: iushr
    //   9676: bipush #63
    //   9678: iand
    //   9679: iaload
    //   9680: ior
    //   9681: istore #21
    //   9683: iload #21
    //   9685: aload #10
    //   9687: iload #22
    //   9689: bipush #16
    //   9691: iushr
    //   9692: bipush #63
    //   9694: iand
    //   9695: iaload
    //   9696: ior
    //   9697: istore #21
    //   9699: iload #21
    //   9701: aload #8
    //   9703: iload #22
    //   9705: bipush #24
    //   9707: iushr
    //   9708: bipush #63
    //   9710: iand
    //   9711: iaload
    //   9712: ior
    //   9713: istore #21
    //   9715: iload #23
    //   9717: iload #21
    //   9719: ixor
    //   9720: istore #23
    //   9722: iinc #25, 1
    //   9725: iload_2
    //   9726: ifne -> 9387
    //   9729: iload #23
    //   9731: bipush #31
    //   9733: ishl
    //   9734: iload #23
    //   9736: iconst_1
    //   9737: iushr
    //   9738: ior
    //   9739: istore #23
    //   9741: iload #24
    //   9743: iload #23
    //   9745: ixor
    //   9746: ldc -1431655766
    //   9748: iand
    //   9749: istore #22
    //   9751: iload #24
    //   9753: iload #22
    //   9755: ixor
    //   9756: istore #24
    //   9758: iload #23
    //   9760: iload #22
    //   9762: ixor
    //   9763: istore #23
    //   9765: iload #24
    //   9767: bipush #31
    //   9769: ishl
    //   9770: iload #24
    //   9772: iconst_1
    //   9773: iushr
    //   9774: ior
    //   9775: istore #24
    //   9777: iload #24
    //   9779: bipush #8
    //   9781: iushr
    //   9782: iload #23
    //   9784: ixor
    //   9785: ldc 16711935
    //   9787: iand
    //   9788: istore #22
    //   9790: iload #23
    //   9792: iload #22
    //   9794: ixor
    //   9795: istore #23
    //   9797: iload #24
    //   9799: iload #22
    //   9801: bipush #8
    //   9803: ishl
    //   9804: ixor
    //   9805: istore #24
    //   9807: iload #24
    //   9809: iconst_2
    //   9810: iushr
    //   9811: iload #23
    //   9813: ixor
    //   9814: ldc 858993459
    //   9816: iand
    //   9817: istore #22
    //   9819: iload #23
    //   9821: iload #22
    //   9823: ixor
    //   9824: istore #23
    //   9826: iload #24
    //   9828: iload #22
    //   9830: iconst_2
    //   9831: ishl
    //   9832: ixor
    //   9833: istore #24
    //   9835: iload #23
    //   9837: bipush #16
    //   9839: iushr
    //   9840: iload #24
    //   9842: ixor
    //   9843: ldc 65535
    //   9845: iand
    //   9846: istore #22
    //   9848: iload #24
    //   9850: iload #22
    //   9852: ixor
    //   9853: istore #24
    //   9855: iload #23
    //   9857: iload #22
    //   9859: bipush #16
    //   9861: ishl
    //   9862: ixor
    //   9863: istore #23
    //   9865: iload #23
    //   9867: iconst_4
    //   9868: iushr
    //   9869: iload #24
    //   9871: ixor
    //   9872: ldc 252645135
    //   9874: iand
    //   9875: istore #22
    //   9877: iload #24
    //   9879: iload #22
    //   9881: ixor
    //   9882: istore #24
    //   9884: iload #23
    //   9886: iload #22
    //   9888: iconst_4
    //   9889: ishl
    //   9890: ixor
    //   9891: istore #23
    //   9893: aload #16
    //   9895: iconst_0
    //   9896: iload #23
    //   9898: iastore
    //   9899: aload #16
    //   9901: iconst_1
    //   9902: iload #24
    //   9904: iastore
    //   9905: iload #19
    //   9907: bipush #8
    //   9909: imul
    //   9910: istore #27
    //   9912: iconst_0
    //   9913: istore #28
    //   9915: iload #28
    //   9917: iconst_2
    //   9918: if_icmpge -> 10007
    //   9921: aload #17
    //   9923: iload #27
    //   9925: iload #28
    //   9927: iconst_4
    //   9928: imul
    //   9929: iadd
    //   9930: aload #16
    //   9932: iload #28
    //   9934: iaload
    //   9935: bipush #24
    //   9937: iushr
    //   9938: i2b
    //   9939: bastore
    //   9940: aload #17
    //   9942: iload #27
    //   9944: iload #28
    //   9946: iconst_4
    //   9947: imul
    //   9948: iadd
    //   9949: iconst_1
    //   9950: iadd
    //   9951: aload #16
    //   9953: iload #28
    //   9955: iaload
    //   9956: bipush #16
    //   9958: iushr
    //   9959: i2b
    //   9960: bastore
    //   9961: aload #17
    //   9963: iload #27
    //   9965: iload #28
    //   9967: iconst_4
    //   9968: imul
    //   9969: iadd
    //   9970: iconst_2
    //   9971: iadd
    //   9972: aload #16
    //   9974: iload #28
    //   9976: iaload
    //   9977: bipush #8
    //   9979: iushr
    //   9980: i2b
    //   9981: bastore
    //   9982: aload #17
    //   9984: iload #27
    //   9986: iload #28
    //   9988: iconst_4
    //   9989: imul
    //   9990: iadd
    //   9991: iconst_3
    //   9992: iadd
    //   9993: aload #16
    //   9995: iload #28
    //   9997: iaload
    //   9998: i2b
    //   9999: bastore
    //   10000: iinc #28, 1
    //   10003: iload_2
    //   10004: ifne -> 9915
    //   10007: iinc #19, 1
    //   10010: iload_2
    //   10011: ifne -> 9092
    //   10014: aload #17
    //   10016: aload #17
    //   10018: arraylength
    //   10019: iconst_1
    //   10020: isub
    //   10021: baload
    //   10022: istore #19
    //   10024: aload #17
    //   10026: arraylength
    //   10027: iload #19
    //   10029: isub
    //   10030: newarray byte
    //   10032: astore #5
    //   10034: aload #17
    //   10036: arraylength
    //   10037: aload #5
    //   10039: arraylength
    //   10040: if_icmpge -> 10064
    //   10043: new java/lang/Exception
    //   10046: dup
    //   10047: sipush #-32594
    //   10050: sipush #-1151
    //   10053: invokestatic a : (II)Ljava/lang/String;
    //   10056: invokespecial <init> : (Ljava/lang/String;)V
    //   10059: athrow
    //   10060: invokestatic a : (Ljava/lang/Throwable;)Ljava/lang/Throwable;
    //   10063: athrow
    //   10064: iconst_0
    //   10065: istore #20
    //   10067: iload #20
    //   10069: aload #5
    //   10071: arraylength
    //   10072: if_icmpge -> 10092
    //   10075: aload #5
    //   10077: iload #20
    //   10079: aload #17
    //   10081: iload #20
    //   10083: baload
    //   10084: bastore
    //   10085: iinc #20, 1
    //   10088: iload_2
    //   10089: ifne -> 10067
    //   10092: new java/math/BigInteger
    //   10095: dup
    //   10096: aload #5
    //   10098: invokespecial <init> : ([B)V
    //   10101: invokevirtual abs : ()Ljava/math/BigInteger;
    //   10104: putstatic burp/Ztip.Zc : Ljava/lang/Object;
    //   10107: sipush #-32604
    //   10110: sipush #17803
    //   10113: invokestatic a : (II)Ljava/lang/String;
    //   10116: iconst_1
    //   10117: ldc burp/Zro5
    //   10119: invokevirtual getClassLoader : ()Ljava/lang/ClassLoader;
    //   10122: invokestatic forName : (Ljava/lang/String;ZLjava/lang/ClassLoader;)Ljava/lang/Class;
    //   10125: invokevirtual getDeclaredFields : ()[Ljava/lang/reflect/Field;
    //   10128: astore #4
    //   10130: aload #4
    //   10132: arraylength
    //   10133: istore #5
    //   10135: iconst_0
    //   10136: istore #6
    //   10138: iload #6
    //   10140: iload #5
    //   10142: if_icmpge -> 10280
    //   10145: aload #4
    //   10147: iload #6
    //   10149: aaload
    //   10150: astore #7
    //   10152: aload #7
    //   10154: invokevirtual getModifiers : ()I
    //   10157: invokestatic isStatic : (I)Z
    //   10160: ifne -> 10170
    //   10163: goto -> 10273
    //   10166: invokestatic a : (Ljava/lang/Throwable;)Ljava/lang/Throwable;
    //   10169: athrow
    //   10170: aload #7
    //   10172: invokevirtual getType : ()Ljava/lang/Class;
    //   10175: astore #8
    //   10177: aload #8
    //   10179: ifnull -> 10260
    //   10182: aload #8
    //   10184: invokevirtual isPrimitive : ()Z
    //   10187: ifne -> 10260
    //   10190: goto -> 10197
    //   10193: invokestatic a : (Ljava/lang/Throwable;)Ljava/lang/Throwable;
    //   10196: athrow
    //   10197: aload #8
    //   10199: invokevirtual getPackage : ()Ljava/lang/Package;
    //   10202: ifnull -> 10260
    //   10205: goto -> 10212
    //   10208: invokestatic a : (Ljava/lang/Throwable;)Ljava/lang/Throwable;
    //   10211: athrow
    //   10212: aload #8
    //   10214: invokevirtual getPackage : ()Ljava/lang/Package;
    //   10217: invokevirtual getName : ()Ljava/lang/String;
    //   10220: ifnull -> 10260
    //   10223: goto -> 10230
    //   10226: invokestatic a : (Ljava/lang/Throwable;)Ljava/lang/Throwable;
    //   10229: athrow
    //   10230: aload #8
    //   10232: invokevirtual getPackage : ()Ljava/lang/Package;
    //   10235: invokevirtual getName : ()Ljava/lang/String;
    //   10238: sipush #-32602
    //   10241: sipush #22746
    //   10244: invokestatic a : (II)Ljava/lang/String;
    //   10247: invokevirtual startsWith : (Ljava/lang/String;)Z
    //   10250: ifne -> 10260
    //   10253: goto -> 10260
    //   10256: invokestatic a : (Ljava/lang/Throwable;)Ljava/lang/Throwable;
    //   10259: athrow
    //   10260: aload #7
    //   10262: iconst_1
    //   10263: invokevirtual setAccessible : (Z)V
    //   10266: aload #7
    //   10268: aconst_null
    //   10269: invokevirtual get : (Ljava/lang/Object;)Ljava/lang/Object;
    //   10272: pop
    //   10273: iinc #6, 1
    //   10276: iload_2
    //   10277: ifne -> 10138
    //   10280: sipush #-32603
    //   10283: sipush #-1239
    //   10286: invokestatic a : (II)Ljava/lang/String;
    //   10289: invokestatic forName : (Ljava/lang/String;)Ljava/lang/Class;
    //   10292: invokevirtual getDeclaredMethods : ()[Ljava/lang/reflect/Method;
    //   10295: astore #4
    //   10297: aload #4
    //   10299: arraylength
    //   10300: istore #5
    //   10302: iconst_0
    //   10303: istore #6
    //   10305: iload #6
    //   10307: iload #5
    //   10309: if_icmpge -> 10421
    //   10312: aload #4
    //   10314: iload #6
    //   10316: aaload
    //   10317: astore #7
    //   10319: aload #7
    //   10321: invokevirtual getParameterTypes : ()[Ljava/lang/Class;
    //   10324: pop
    //   10325: aload #7
    //   10327: invokevirtual getModifiers : ()I
    //   10330: invokestatic isStatic : (I)Z
    //   10333: ifeq -> 10407
    //   10336: aload #7
    //   10338: invokevirtual getParameterTypes : ()[Ljava/lang/Class;
    //   10341: arraylength
    //   10342: iconst_2
    //   10343: if_icmpne -> 10407
    //   10346: goto -> 10353
    //   10349: invokestatic a : (Ljava/lang/Throwable;)Ljava/lang/Throwable;
    //   10352: athrow
    //   10353: aload #7
    //   10355: invokevirtual getReturnType : ()Ljava/lang/Class;
    //   10358: getstatic java/lang/Boolean.TYPE : Ljava/lang/Class;
    //   10361: if_acmpne -> 10407
    //   10364: goto -> 10371
    //   10367: invokestatic a : (Ljava/lang/Throwable;)Ljava/lang/Throwable;
    //   10370: athrow
    //   10371: aload #7
    //   10373: iconst_1
    //   10374: invokevirtual setAccessible : (Z)V
    //   10377: aload #7
    //   10379: aconst_null
    //   10380: iconst_2
    //   10381: anewarray java/lang/Object
    //   10384: dup
    //   10385: iconst_0
    //   10386: aload_0
    //   10387: aastore
    //   10388: dup
    //   10389: iconst_1
    //   10390: aload_1
    //   10391: aastore
    //   10392: invokevirtual invoke : (Ljava/lang/Object;[Ljava/lang/Object;)Ljava/lang/Object;
    //   10395: pop
    //   10396: iload_2
    //   10397: ifne -> 10421
    //   10400: goto -> 10407
    //   10403: invokestatic a : (Ljava/lang/Throwable;)Ljava/lang/Throwable;
    //   10406: athrow
    //   10407: iinc #6, 1
    //   10410: iload_2
    //   10411: ifne -> 10305
    //   10414: goto -> 10421
    //   10417: invokestatic a : (Ljava/lang/Throwable;)Ljava/lang/Throwable;
    //   10420: athrow
    //   10421: sipush #-32599
    //   10424: sipush #18342
    //   10427: invokestatic a : (II)Ljava/lang/String;
    //   10430: iconst_1
    //   10431: ldc burp/Ztjh
    //   10433: invokevirtual getClassLoader : ()Ljava/lang/ClassLoader;
    //   10436: invokestatic forName : (Ljava/lang/String;ZLjava/lang/ClassLoader;)Ljava/lang/Class;
    //   10439: invokevirtual getDeclaredFields : ()[Ljava/lang/reflect/Field;
    //   10442: astore #4
    //   10444: aload #4
    //   10446: arraylength
    //   10447: istore #5
    //   10449: iconst_0
    //   10450: istore #6
    //   10452: iload #6
    //   10454: iload #5
    //   10456: if_icmpge -> 10594
    //   10459: aload #4
    //   10461: iload #6
    //   10463: aaload
    //   10464: astore #7
    //   10466: aload #7
    //   10468: invokevirtual getModifiers : ()I
    //   10471: invokestatic isStatic : (I)Z
    //   10474: ifne -> 10484
    //   10477: goto -> 10587
    //   10480: invokestatic a : (Ljava/lang/Throwable;)Ljava/lang/Throwable;
    //   10483: athrow
    //   10484: aload #7
    //   10486: invokevirtual getType : ()Ljava/lang/Class;
    //   10489: astore #8
    //   10491: aload #8
    //   10493: ifnull -> 10574
    //   10496: aload #8
    //   10498: invokevirtual isPrimitive : ()Z
    //   10501: ifne -> 10574
    //   10504: goto -> 10511
    //   10507: invokestatic a : (Ljava/lang/Throwable;)Ljava/lang/Throwable;
    //   10510: athrow
    //   10511: aload #8
    //   10513: invokevirtual getPackage : ()Ljava/lang/Package;
    //   10516: ifnull -> 10574
    //   10519: goto -> 10526
    //   10522: invokestatic a : (Ljava/lang/Throwable;)Ljava/lang/Throwable;
    //   10525: athrow
    //   10526: aload #8
    //   10528: invokevirtual getPackage : ()Ljava/lang/Package;
    //   10531: invokevirtual getName : ()Ljava/lang/String;
    //   10534: ifnull -> 10574
    //   10537: goto -> 10544
    //   10540: invokestatic a : (Ljava/lang/Throwable;)Ljava/lang/Throwable;
    //   10543: athrow
    //   10544: aload #8
    //   10546: invokevirtual getPackage : ()Ljava/lang/Package;
    //   10549: invokevirtual getName : ()Ljava/lang/String;
    //   10552: sipush #-32598
    //   10555: sipush #-30781
    //   10558: invokestatic a : (II)Ljava/lang/String;
    //   10561: invokevirtual startsWith : (Ljava/lang/String;)Z
    //   10564: ifne -> 10574
    //   10567: goto -> 10574
    //   10570: invokestatic a : (Ljava/lang/Throwable;)Ljava/lang/Throwable;
    //   10573: athrow
    //   10574: aload #7
    //   10576: iconst_1
    //   10577: invokevirtual setAccessible : (Z)V
    //   10580: aload #7
    //   10582: aconst_null
    //   10583: invokevirtual get : (Ljava/lang/Object;)Ljava/lang/Object;
    //   10586: pop
    //   10587: iinc #6, 1
    //   10590: iload_2
    //   10591: ifne -> 10452
    //   10594: sipush #-32593
    //   10597: sipush #-24028
    //   10600: invokestatic a : (II)Ljava/lang/String;
    //   10603: invokestatic forName : (Ljava/lang/String;)Ljava/lang/Class;
    //   10606: invokevirtual getDeclaredMethods : ()[Ljava/lang/reflect/Method;
    //   10609: astore #4
    //   10611: aload #4
    //   10613: arraylength
    //   10614: istore #5
    //   10616: iconst_0
    //   10617: istore #6
    //   10619: iload #6
    //   10621: iload #5
    //   10623: if_icmpge -> 10756
    //   10626: aload #4
    //   10628: iload #6
    //   10630: aaload
    //   10631: astore #7
    //   10633: aload #7
    //   10635: invokevirtual getParameterTypes : ()[Ljava/lang/Class;
    //   10638: pop
    //   10639: aload #7
    //   10641: invokevirtual getModifiers : ()I
    //   10644: invokestatic isStatic : (I)Z
    //   10647: ifeq -> 10742
    //   10650: aload #7
    //   10652: invokevirtual getParameterTypes : ()[Ljava/lang/Class;
    //   10655: arraylength
    //   10656: iconst_2
    //   10657: if_icmpne -> 10742
    //   10660: goto -> 10667
    //   10663: invokestatic a : (Ljava/lang/Throwable;)Ljava/lang/Throwable;
    //   10666: athrow
    //   10667: aload #7
    //   10669: invokevirtual getReturnType : ()Ljava/lang/Class;
    //   10672: getstatic java/lang/Void.TYPE : Ljava/lang/Class;
    //   10675: invokevirtual equals : (Ljava/lang/Object;)Z
    //   10678: ifeq -> 10742
    //   10681: goto -> 10688
    //   10684: invokestatic a : (Ljava/lang/Throwable;)Ljava/lang/Throwable;
    //   10687: athrow
    //   10688: aload #7
    //   10690: iconst_1
    //   10691: invokevirtual setAccessible : (Z)V
    //   10694: aload #7
    //   10696: aconst_null
    //   10697: iconst_2
    //   10698: anewarray java/lang/Object
    //   10701: dup
    //   10702: iconst_0
    //   10703: aload_0
    //   10704: aastore
    //   10705: dup
    //   10706: iconst_1
    //   10707: aload_1
    //   10708: ifnonnull -> 10726
    //   10711: goto -> 10718
    //   10714: invokestatic a : (Ljava/lang/Throwable;)Ljava/lang/Throwable;
    //   10717: athrow
    //   10718: aload_1
    //   10719: goto -> 10733
    //   10722: invokestatic a : (Ljava/lang/Throwable;)Ljava/lang/Throwable;
    //   10725: athrow
    //   10726: aload_1
    //   10727: checkcast [B
    //   10730: invokevirtual clone : ()Ljava/lang/Object;
    //   10733: aastore
    //   10734: invokevirtual invoke : (Ljava/lang/Object;[Ljava/lang/Object;)Ljava/lang/Object;
    //   10737: pop
    //   10738: iload_2
    //   10739: ifne -> 10756
    //   10742: iinc #6, 1
    //   10745: iload_2
    //   10746: ifne -> 10619
    //   10749: goto -> 10756
    //   10752: invokestatic a : (Ljava/lang/Throwable;)Ljava/lang/Throwable;
    //   10755: athrow
    //   10756: getstatic burp/Zlzs.Zp : Ljava/lang/String;
    //   10759: getstatic burp/Zgw7.Zi : Ljava/lang/Object;
    //   10762: checkcast java/math/BigInteger
    //   10765: invokevirtual intValue : ()I
    //   10768: bipush #32
    //   10770: irem
    //   10771: invokestatic abs : (I)I
    //   10774: invokevirtual charAt : (I)C
    //   10777: getstatic burp/Ze13.Zg : Ljava/lang/String;
    //   10780: getstatic burp/Zzah.Za : Ljava/lang/Object;
    //   10783: checkcast java/math/BigInteger
    //   10786: invokevirtual intValue : ()I
    //   10789: bipush #32
    //   10791: irem
    //   10792: invokestatic abs : (I)I
    //   10795: invokevirtual charAt : (I)C
    //   10798: if_icmpgt -> 10913
    //   10801: getstatic burp/Zkdq.ZZ : Ljava/lang/String;
    //   10804: getstatic burp/Zbsc.ZA : Ljava/lang/Object;
    //   10807: checkcast java/math/BigInteger
    //   10810: invokevirtual intValue : ()I
    //   10813: bipush #32
    //   10815: irem
    //   10816: invokestatic abs : (I)I
    //   10819: invokevirtual charAt : (I)C
    //   10822: getstatic burp/Zx4l.Zy : Ljava/lang/String;
    //   10825: getstatic burp/Zlzo.ZJ : Ljava/lang/Object;
    //   10828: checkcast java/math/BigInteger
    //   10831: invokevirtual intValue : ()I
    //   10834: bipush #32
    //   10836: irem
    //   10837: invokestatic abs : (I)I
    //   10840: invokevirtual charAt : (I)C
    //   10843: if_icmpgt -> 10913
    //   10846: goto -> 10853
    //   10849: invokestatic a : (Ljava/lang/Throwable;)Ljava/lang/Throwable;
    //   10852: athrow
    //   10853: getstatic burp/Zb4m.ZQ : Ljava/lang/String;
    //   10856: getstatic burp/Zlkm.ZQ : Ljava/lang/Object;
    //   10859: checkcast java/math/BigInteger
    //   10862: invokevirtual intValue : ()I
    //   10865: bipush #32
    //   10867: irem
    //   10868: invokestatic abs : (I)I
    //   10871: invokevirtual charAt : (I)C
    //   10874: getstatic burp/Zmt_.ZH : Ljava/lang/String;
    //   10877: getstatic burp/Zvh.Zb : Ljava/lang/Object;
    //   10880: checkcast java/math/BigInteger
    //   10883: invokevirtual intValue : ()I
    //   10886: bipush #32
    //   10888: irem
    //   10889: invokestatic abs : (I)I
    //   10892: invokevirtual charAt : (I)C
    //   10895: if_icmple -> 10913
    //   10898: goto -> 10905
    //   10901: invokestatic a : (Ljava/lang/Throwable;)Ljava/lang/Throwable;
    //   10904: athrow
    //   10905: iconst_1
    //   10906: goto -> 10914
    //   10909: invokestatic a : (Ljava/lang/Throwable;)Ljava/lang/Throwable;
    //   10912: athrow
    //   10913: iconst_0
    //   10914: ireturn
    //   10915: astore_3
    //   10916: new java/lang/Exception
    //   10919: dup
    //   10920: aload_3
    //   10921: invokevirtual getMessage : ()Ljava/lang/String;
    //   10924: invokespecial <init> : (Ljava/lang/String;)V
    //   10927: athrow
    // Exception table:
    //   from	to	target	type
    //   4	10914	10915	java/lang/Throwable
    //   3321	3346	3346	java/lang/Throwable
    //   4309	4335	4335	java/lang/Throwable
    //   4400	4574	4577	java/lang/Throwable
    //   4544	4611	4614	java/lang/Throwable
    //   4581	4648	4651	java/lang/Throwable
    //   4618	4685	4688	java/lang/Throwable
    //   4655	4722	4725	java/lang/Throwable
    //   4692	4759	4762	java/lang/Throwable
    //   4729	4796	4799	java/lang/Throwable
    //   4766	4833	4836	java/lang/Throwable
    //   4803	4870	4873	java/lang/Throwable
    //   4840	4907	4910	java/lang/Throwable
    //   4877	4944	4947	java/lang/Throwable
    //   4914	4981	4984	java/lang/Throwable
    //   4951	5018	5021	java/lang/Throwable
    //   4988	5055	5058	java/lang/Throwable
    //   5025	5092	5095	java/lang/Throwable
    //   5062	5129	5132	java/lang/Throwable
    //   5099	5166	5169	java/lang/Throwable
    //   5136	5203	5206	java/lang/Throwable
    //   5173	5240	5243	java/lang/Throwable
    //   5210	5277	5280	java/lang/Throwable
    //   5247	5314	5317	java/lang/Throwable
    //   5284	5351	5354	java/lang/Throwable
    //   5321	5388	5391	java/lang/Throwable
    //   5358	5425	5428	java/lang/Throwable
    //   5395	5462	5465	java/lang/Throwable
    //   5432	5499	5502	java/lang/Throwable
    //   5469	5536	5539	java/lang/Throwable
    //   5506	5573	5576	java/lang/Throwable
    //   5543	5610	5613	java/lang/Throwable
    //   5580	5647	5650	java/lang/Throwable
    //   5617	5684	5687	java/lang/Throwable
    //   5654	5717	5720	java/lang/Throwable
    //   9042	9067	9067	java/lang/Throwable
    //   10034	10060	10060	java/lang/Throwable
    //   10152	10166	10166	java/lang/Throwable
    //   10177	10190	10193	java/lang/Throwable
    //   10182	10205	10208	java/lang/Throwable
    //   10197	10223	10226	java/lang/Throwable
    //   10212	10253	10256	java/lang/Throwable
    //   10319	10346	10349	java/lang/Throwable
    //   10336	10364	10367	java/lang/Throwable
    //   10353	10400	10403	java/lang/Throwable
    //   10371	10414	10417	java/lang/Throwable
    //   10466	10480	10480	java/lang/Throwable
    //   10491	10504	10507	java/lang/Throwable
    //   10496	10519	10522	java/lang/Throwable
    //   10511	10537	10540	java/lang/Throwable
    //   10526	10567	10570	java/lang/Throwable
    //   10633	10660	10663	java/lang/Throwable
    //   10650	10681	10684	java/lang/Throwable
    //   10667	10711	10714	java/lang/Throwable
    //   10688	10722	10722	java/lang/Throwable
    //   10733	10749	10752	java/lang/Throwable
    //   10756	10846	10849	java/lang/Throwable
    //   10801	10898	10901	java/lang/Throwable
    //   10853	10909	10909	java/lang/Throwable
  }
  
  static void Zt(Object paramObject) {
    Zkk2.ZI = a(-32595, -16752);
    Zkk2.Zq = new BigInteger(a(-32600, -7524));
    boolean bool = Zt2e.ZK();
    try {
      try {
        if (Zxo4.ZW.charAt(Math.abs(((BigInteger)Zml.ZR).intValue() % 32)) <= Zml.ZN.charAt(Math.abs(((BigInteger)Zt7j.ZH).intValue() % 32))) {
          try {
            Zzoc.ZE(Class.forName(a(-32601, 22041)));
            if (bool)
              Zg7w.Zr(Class.forName(a(-32597, 14801))); 
          } catch (Throwable throwable) {
            throw a(null);
          } 
          return;
        } 
      } catch (Throwable throwable) {
        throw a(null);
      } 
      Zg7w.Zr(Class.forName(a(-32597, 14801)));
    } catch (Throwable throwable) {}
  }
  
  static void Zr(Object[] paramArrayOfObject, Object paramObject) throws Throwable {}
  
  static {
    // Byte code:
    //   0: bipush #14
    //   2: anewarray java/lang/String
    //   5: astore #5
    //   7: iconst_0
    //   8: istore_3
    //   9: ldc '>Xd@MZ&7<\\t4 drI#6i[(q=F\\t6Qo^\\tt\\fq\\t/ ')mMCl#nqW%.}:sHHEo7O9b4eZaY~6;~$5n|2\\t)xS&NO,\\t;4y\\t7#GIa3'
    //   11: dup
    //   12: astore_2
    //   13: invokevirtual length : ()I
    //   16: istore #4
    //   18: bipush #9
    //   20: istore_1
    //   21: iconst_m1
    //   22: istore_0
    //   23: bipush #26
    //   25: iinc #0, 1
    //   28: aload_2
    //   29: iload_0
    //   30: dup
    //   31: iload_1
    //   32: iadd
    //   33: invokevirtual substring : (II)Ljava/lang/String;
    //   36: iconst_m1
    //   37: goto -> 143
    //   40: aload #5
    //   42: swap
    //   43: iload_3
    //   44: iinc #3, 1
    //   47: swap
    //   48: aastore
    //   49: iload_0
    //   50: iload_1
    //   51: iadd
    //   52: dup
    //   53: istore_0
    //   54: iload #4
    //   56: if_icmpge -> 68
    //   59: aload_2
    //   60: iload_0
    //   61: invokevirtual charAt : (I)C
    //   64: istore_1
    //   65: goto -> 23
    //   68: ldc '`\xu[\a:jiR`R}y'
    //   70: dup
    //   71: astore_2
    //   72: invokevirtual length : ()I
    //   75: istore #4
    //   77: bipush #32
    //   79: istore_1
    //   80: iconst_m1
    //   81: istore_0
    //   82: bipush #121
    //   84: iinc #0, 1
    //   87: aload_2
    //   88: iload_0
    //   89: dup
    //   90: iload_1
    //   91: iadd
    //   92: invokevirtual substring : (II)Ljava/lang/String;
    //   95: iconst_0
    //   96: goto -> 143
    //   99: aload #5
    //   101: swap
    //   102: iload_3
    //   103: iinc #3, 1
    //   106: swap
    //   107: aastore
    //   108: iload_0
    //   109: iload_1
    //   110: iadd
    //   111: dup
    //   112: istore_0
    //   113: iload #4
    //   115: if_icmpge -> 127
    //   118: aload_2
    //   119: iload_0
    //   120: invokevirtual charAt : (I)C
    //   123: istore_1
    //   124: goto -> 82
    //   127: aload #5
    //   129: putstatic burp/Zb38.a : [Ljava/lang/String;
    //   132: bipush #14
    //   134: anewarray java/lang/String
    //   137: putstatic burp/Zb38.b : [Ljava/lang/String;
    //   140: goto -> 300
    //   143: dup_x2
    //   144: pop
    //   145: invokevirtual toCharArray : ()[C
    //   148: dup_x1
    //   149: arraylength
    //   150: dup_x2
    //   151: pop
    //   152: iconst_0
    //   153: istore #6
    //   155: dup2_x1
    //   156: pop2
    //   157: dup_x2
    //   158: iconst_1
    //   159: if_icmpgt -> 260
    //   162: dup2
    //   163: swap
    //   164: iload #6
    //   166: dup2_x1
    //   167: caload
    //   168: swap
    //   169: iload #6
    //   171: bipush #7
    //   173: irem
    //   174: tableswitch default -> 242, 0 -> 212, 1 -> 217, 2 -> 222, 3 -> 227, 4 -> 232, 5 -> 237
    //   212: bipush #15
    //   214: goto -> 244
    //   217: bipush #69
    //   219: goto -> 244
    //   222: bipush #33
    //   224: goto -> 244
    //   227: bipush #7
    //   229: goto -> 244
    //   232: bipush #66
    //   234: goto -> 244
    //   237: bipush #20
    //   239: goto -> 244
    //   242: bipush #23
    //   244: ixor
    //   245: ixor
    //   246: i2c
    //   247: castore
    //   248: iinc #6, 1
    //   251: dup
    //   252: ifne -> 260
    //   255: dup2
    //   256: dup_x1
    //   257: goto -> 166
    //   260: dup2_x1
    //   261: pop2
    //   262: dup_x2
    //   263: iload #6
    //   265: if_icmpgt -> 162
    //   268: pop
    //   269: new java/lang/String
    //   272: dup_x1
    //   273: swap
    //   274: invokespecial <init> : ([C)V
    //   277: invokevirtual intern : ()Ljava/lang/String;
    //   280: swap
    //   281: pop
    //   282: swap
    //   283: tableswitch default -> 40, 0 -> 99
    //   300: new java/math/BigInteger
    //   303: dup
    //   304: bipush #32
    //   306: newarray byte
    //   308: dup
    //   309: iconst_0
    //   310: bipush #84
    //   312: bastore
    //   313: dup
    //   314: iconst_1
    //   315: bipush #-10
    //   317: bastore
    //   318: dup
    //   319: iconst_2
    //   320: bipush #50
    //   322: bastore
    //   323: dup
    //   324: iconst_3
    //   325: bipush #126
    //   327: bastore
    //   328: dup
    //   329: iconst_4
    //   330: bipush #-119
    //   332: bastore
    //   333: dup
    //   334: iconst_5
    //   335: bipush #8
    //   337: bastore
    //   338: dup
    //   339: bipush #6
    //   341: bipush #24
    //   343: bastore
    //   344: dup
    //   345: bipush #7
    //   347: bipush #104
    //   349: bastore
    //   350: dup
    //   351: bipush #8
    //   353: bipush #-119
    //   355: bastore
    //   356: dup
    //   357: bipush #9
    //   359: bipush #95
    //   361: bastore
    //   362: dup
    //   363: bipush #10
    //   365: bipush #-92
    //   367: bastore
    //   368: dup
    //   369: bipush #11
    //   371: bipush #20
    //   373: bastore
    //   374: dup
    //   375: bipush #12
    //   377: bipush #-80
    //   379: bastore
    //   380: dup
    //   381: bipush #13
    //   383: bipush #19
    //   385: bastore
    //   386: dup
    //   387: bipush #14
    //   389: bipush #57
    //   391: bastore
    //   392: dup
    //   393: bipush #15
    //   395: bipush #122
    //   397: bastore
    //   398: dup
    //   399: bipush #16
    //   401: bipush #-112
    //   403: bastore
    //   404: dup
    //   405: bipush #17
    //   407: bipush #28
    //   409: bastore
    //   410: dup
    //   411: bipush #18
    //   413: bipush #-70
    //   415: bastore
    //   416: dup
    //   417: bipush #19
    //   419: bipush #124
    //   421: bastore
    //   422: dup
    //   423: bipush #20
    //   425: bipush #21
    //   427: bastore
    //   428: dup
    //   429: bipush #21
    //   431: bipush #-117
    //   433: bastore
    //   434: dup
    //   435: bipush #22
    //   437: bipush #-48
    //   439: bastore
    //   440: dup
    //   441: bipush #23
    //   443: bipush #-3
    //   445: bastore
    //   446: dup
    //   447: bipush #24
    //   449: bipush #90
    //   451: bastore
    //   452: dup
    //   453: bipush #25
    //   455: bipush #41
    //   457: bastore
    //   458: dup
    //   459: bipush #26
    //   461: bipush #-37
    //   463: bastore
    //   464: dup
    //   465: bipush #27
    //   467: bipush #-53
    //   469: bastore
    //   470: dup
    //   471: bipush #28
    //   473: bipush #48
    //   475: bastore
    //   476: dup
    //   477: bipush #29
    //   479: bipush #-110
    //   481: bastore
    //   482: dup
    //   483: bipush #30
    //   485: bipush #48
    //   487: bastore
    //   488: dup
    //   489: bipush #31
    //   491: bipush #121
    //   493: bastore
    //   494: invokespecial <init> : ([B)V
    //   497: putstatic burp/Zb38.ZC : Ljava/lang/Object;
    //   500: sipush #-32605
    //   503: sipush #277
    //   506: invokestatic a : (II)Ljava/lang/String;
    //   509: putstatic burp/Zb38.Zr : Ljava/lang/String;
    //   512: return
  }
  
  private static Throwable a(Throwable paramThrowable) {
    return paramThrowable;
  }
  
  private static String a(int paramInt1, int paramInt2) {
    int i = (paramInt1 ^ 0xFFFF80AF) & 0xFFFF;
    if (b[i] == null) {
      char[] arrayOfChar = a[i].toCharArray();
      switch (arrayOfChar[0] & 0xFF) {
        case 0:
        
        case 1:
        
        case 2:
        
        case 3:
        
        case 4:
        
        case 5:
        
        case 6:
        
        case 7:
        
        case 8:
        
        case 9:
        
        case 10:
        
        case 11:
        
        case 12:
        
        case 13:
        
        case 14:
        
        case 15:
        
        case 16:
        
        case 17:
        
        case 18:
        
        case 19:
        
        case 20:
        
        case 21:
        
        case 22:
        
        case 23:
        
        case 24:
        
        case 25:
        
        case 26:
        
        case 27:
        
        case 28:
        
        case 29:
        
        case 30:
        
        case 31:
        
        case 32:
        
        case 33:
        
        case 34:
        
        case 35:
        
        case 36:
        
        case 37:
        
        case 38:
        
        case 39:
        
        case 40:
        
        case 41:
        
        case 42:
        
        case 43:
        
        case 44:
        
        case 45:
        
        case 46:
        
        case 47:
        
        case 48:
        
        case 49:
        
        case 50:
        
        case 51:
        
        case 52:
        
        case 53:
        
        case 54:
        
        case 55:
        
        case 56:
        
        case 57:
        
        case 58:
        
        case 59:
        
        case 60:
        
        case 61:
        
        case 62:
        
        case 63:
        
        case 64:
        
        case 65:
        
        case 66:
        
        case 67:
        
        case 68:
        
        case 69:
        
        case 70:
        
        case 71:
        
        case 72:
        
        case 73:
        
        case 74:
        
        case 75:
        
        case 76:
        
        case 77:
        
        case 78:
        
        case 79:
        
        case 80:
        
        case 81:
        
        case 82:
        
        case 83:
        
        case 84:
        
        case 85:
        
        case 86:
        
        case 87:
        
        case 88:
        
        case 89:
        
        case 90:
        
        case 91:
        
        case 92:
        
        case 93:
        
        case 94:
        
        case 95:
        
        case 96:
        
        case 97:
        
        case 98:
        
        case 99:
        
        case 100:
        
        case 101:
        
        case 102:
        
        case 103:
        
        case 104:
        
        case 105:
        
        case 106:
        
        case 107:
        
        case 108:
        
        case 109:
        
        case 110:
        
        case 111:
        
        case 112:
        
        case 113:
        
        case 114:
        
        case 115:
        
        case 116:
        
        case 117:
        
        case 118:
        
        case 119:
        
        case 120:
        
        case 121:
        
        case 122:
        
        case 123:
        
        case 124:
        
        case 125:
        
        case 126:
        
        case 127:
        
        case 128:
        
        case 129:
        
        case 130:
        
        case 131:
        
        case 132:
        
        case 133:
        
        case 134:
        
        case 135:
        
        case 136:
        
        case 137:
        
        case 138:
        
        case 139:
        
        case 140:
        
        case 141:
        
        case 142:
        
        case 143:
        
        case 144:
        
        case 145:
        
        case 146:
        
        case 147:
        
        case 148:
        
        case 149:
        
        case 150:
        
        case 151:
        
        case 152:
        
        case 153:
        
        case 154:
        
        case 155:
        
        case 156:
        
        case 157:
        
        case 158:
        
        case 159:
        
        case 160:
        
        case 161:
        
        case 162:
        
        case 163:
        
        case 164:
        
        case 165:
        
        case 166:
        
        case 167:
        
        case 168:
        
        case 169:
        
        case 170:
        
        case 171:
        
        case 172:
        
        case 173:
        
        case 174:
        
        case 175:
        
        case 176:
        
        case 177:
        
        case 178:
        
        case 179:
        
        case 180:
        
        case 181:
        
        case 182:
        
        case 183:
        
        case 184:
        
        case 185:
        
        case 186:
        
        case 187:
        
        case 188:
        
        case 189:
        
        case 190:
        
        case 191:
        
        case 192:
        
        case 193:
        
        case 194:
        
        case 195:
        
        case 196:
        
        case 197:
        
        case 198:
        
        case 199:
        
        case 200:
        
        case 201:
        
        case 202:
        
        case 203:
        
        case 204:
        
        case 205:
        
        case 206:
        
        case 207:
        
        case 208:
        
        case 209:
        
        case 210:
        
        case 211:
        
        case 212:
        
        case 213:
        
        case 214:
        
        case 215:
        
        case 216:
        
        case 217:
        
        case 218:
        
        case 219:
        
        case 220:
        
        case 221:
        
        case 222:
        
        case 223:
        
        case 224:
        
        case 225:
        
        case 226:
        
        case 227:
        
        case 228:
        
        case 229:
        
        case 230:
        
        case 231:
        
        case 232:
        
        case 233:
        
        case 234:
        
        case 235:
        
        case 236:
        
        case 237:
        
        case 238:
        
        case 239:
        
        case 240:
        
        case 241:
        
        case 242:
        
        case 243:
        
        case 244:
        
        case 245:
        
        case 246:
        
        case 247:
        
        case 248:
        
        case 249:
        
        case 250:
        
        case 251:
        
        case 252:
        
        case 253:
        
        case 254:
        
        default:
          break;
      } 
      char c = '';
      int j = (paramInt2 & 0xFF) - c;
      if (j < 0)
        j += 256; 
      int k = ((paramInt2 & 0xFFFF) >>> 8) - c;
      if (k < 0)
        k += 256; 
      for (byte b = 0; b < arrayOfChar.length; b++) {
        int m = b % 2;
        if (m == 0) {
          arrayOfChar[b] = (char)(arrayOfChar[b] ^ j);
          j = ((j >>> 3 | j << 5) ^ arrayOfChar[b]) & 0xFF;
        } else {
          arrayOfChar[b] = (char)(arrayOfChar[b] ^ k);
          k = ((k >>> 3 | k << 5) ^ arrayOfChar[b]) & 0xFF;
        } 
      } 
      b[i] = (new String(arrayOfChar)).intern();
    } 
    return b[i];
  }
}


/* Location:              C:\Program Files\BurpSuitePro\burpsuite_pro.jar!\burp\Zb38.class
 * Java compiler version: 21 (65.0)
 * JD-Core Version:       1.1.3
 */