package burp;

import java.math.BigInteger;

class Zb4m extends ClassLoader {
  static Object Zp;
  
  static String ZQ;
  
  private static final String[] a;
  
  private static final String[] b;
  
  static boolean ZP(Object[] paramArrayOfObject, Object paramObject) throws Throwable {
    // Byte code:
    //   0: invokestatic ZK : ()Z
    //   3: istore_2
    //   4: new java/lang/StringBuilder
    //   7: dup
    //   8: invokespecial <init> : ()V
    //   11: astore_3
    //   12: iconst_0
    //   13: istore #4
    //   15: iload #4
    //   17: bipush #32
    //   19: if_icmpge -> 1355
    //   22: iload #4
    //   24: tableswitch default -> 1348, 0 -> 168, 1 -> 205, 2 -> 242, 3 -> 279, 4 -> 316, 5 -> 353, 6 -> 390, 7 -> 427, 8 -> 464, 9 -> 501, 10 -> 538, 11 -> 575, 12 -> 612, 13 -> 649, 14 -> 686, 15 -> 723, 16 -> 760, 17 -> 797, 18 -> 834, 19 -> 871, 20 -> 908, 21 -> 945, 22 -> 982, 23 -> 1019, 24 -> 1056, 25 -> 1093, 26 -> 1130, 27 -> 1167, 28 -> 1204, 29 -> 1241, 30 -> 1278, 31 -> 1315
    //   168: aload_3
    //   169: getstatic burp/Zrcy.Zq : Ljava/lang/String;
    //   172: getstatic burp/Zz0b.ZT : Ljava/lang/Object;
    //   175: checkcast java/math/BigInteger
    //   178: invokevirtual intValue : ()I
    //   181: bipush #32
    //   183: irem
    //   184: invokestatic abs : (I)I
    //   187: invokevirtual charAt : (I)C
    //   190: invokevirtual append : (C)Ljava/lang/StringBuilder;
    //   193: pop
    //   194: iload_2
    //   195: ifeq -> 1348
    //   198: goto -> 205
    //   201: invokestatic a : (Ljava/lang/Throwable;)Ljava/lang/Throwable;
    //   204: athrow
    //   205: aload_3
    //   206: getstatic burp/Zbwj.ZP : Ljava/lang/String;
    //   209: getstatic burp/Zs33.ZT : Ljava/lang/Object;
    //   212: checkcast java/math/BigInteger
    //   215: invokevirtual intValue : ()I
    //   218: bipush #32
    //   220: irem
    //   221: invokestatic abs : (I)I
    //   224: invokevirtual charAt : (I)C
    //   227: invokevirtual append : (C)Ljava/lang/StringBuilder;
    //   230: pop
    //   231: iload_2
    //   232: ifeq -> 1348
    //   235: goto -> 242
    //   238: invokestatic a : (Ljava/lang/Throwable;)Ljava/lang/Throwable;
    //   241: athrow
    //   242: aload_3
    //   243: getstatic burp/Zsf7.ZS : Ljava/lang/String;
    //   246: getstatic burp/Zlwi.Zw : Ljava/lang/Object;
    //   249: checkcast java/math/BigInteger
    //   252: invokevirtual intValue : ()I
    //   255: bipush #32
    //   257: irem
    //   258: invokestatic abs : (I)I
    //   261: invokevirtual charAt : (I)C
    //   264: invokevirtual append : (C)Ljava/lang/StringBuilder;
    //   267: pop
    //   268: iload_2
    //   269: ifeq -> 1348
    //   272: goto -> 279
    //   275: invokestatic a : (Ljava/lang/Throwable;)Ljava/lang/Throwable;
    //   278: athrow
    //   279: aload_3
    //   280: getstatic burp/Zzmw.Zd : Ljava/lang/String;
    //   283: getstatic burp/Zx4l.Zt : Ljava/lang/Object;
    //   286: checkcast java/math/BigInteger
    //   289: invokevirtual intValue : ()I
    //   292: bipush #32
    //   294: irem
    //   295: invokestatic abs : (I)I
    //   298: invokevirtual charAt : (I)C
    //   301: invokevirtual append : (C)Ljava/lang/StringBuilder;
    //   304: pop
    //   305: iload_2
    //   306: ifeq -> 1348
    //   309: goto -> 316
    //   312: invokestatic a : (Ljava/lang/Throwable;)Ljava/lang/Throwable;
    //   315: athrow
    //   316: aload_3
    //   317: getstatic burp/Zts_.Zx : Ljava/lang/String;
    //   320: getstatic burp/Zl6z.Zt : Ljava/lang/Object;
    //   323: checkcast java/math/BigInteger
    //   326: invokevirtual intValue : ()I
    //   329: bipush #32
    //   331: irem
    //   332: invokestatic abs : (I)I
    //   335: invokevirtual charAt : (I)C
    //   338: invokevirtual append : (C)Ljava/lang/StringBuilder;
    //   341: pop
    //   342: iload_2
    //   343: ifeq -> 1348
    //   346: goto -> 353
    //   349: invokestatic a : (Ljava/lang/Throwable;)Ljava/lang/Throwable;
    //   352: athrow
    //   353: aload_3
    //   354: getstatic burp/Zs56.ZW : Ljava/lang/String;
    //   357: getstatic burp/Zbz_.ZU : Ljava/lang/Object;
    //   360: checkcast java/math/BigInteger
    //   363: invokevirtual intValue : ()I
    //   366: bipush #32
    //   368: irem
    //   369: invokestatic abs : (I)I
    //   372: invokevirtual charAt : (I)C
    //   375: invokevirtual append : (C)Ljava/lang/StringBuilder;
    //   378: pop
    //   379: iload_2
    //   380: ifeq -> 1348
    //   383: goto -> 390
    //   386: invokestatic a : (Ljava/lang/Throwable;)Ljava/lang/Throwable;
    //   389: athrow
    //   390: aload_3
    //   391: getstatic burp/Zlbr.Zr : Ljava/lang/String;
    //   394: getstatic burp/Zlv6.ZN : Ljava/lang/Object;
    //   397: checkcast java/math/BigInteger
    //   400: invokevirtual intValue : ()I
    //   403: bipush #32
    //   405: irem
    //   406: invokestatic abs : (I)I
    //   409: invokevirtual charAt : (I)C
    //   412: invokevirtual append : (C)Ljava/lang/StringBuilder;
    //   415: pop
    //   416: iload_2
    //   417: ifeq -> 1348
    //   420: goto -> 427
    //   423: invokestatic a : (Ljava/lang/Throwable;)Ljava/lang/Throwable;
    //   426: athrow
    //   427: aload_3
    //   428: getstatic burp/Zlvb.Zs : Ljava/lang/String;
    //   431: getstatic burp/Ztkc.ZV : Ljava/lang/Object;
    //   434: checkcast java/math/BigInteger
    //   437: invokevirtual intValue : ()I
    //   440: bipush #32
    //   442: irem
    //   443: invokestatic abs : (I)I
    //   446: invokevirtual charAt : (I)C
    //   449: invokevirtual append : (C)Ljava/lang/StringBuilder;
    //   452: pop
    //   453: iload_2
    //   454: ifeq -> 1348
    //   457: goto -> 464
    //   460: invokestatic a : (Ljava/lang/Throwable;)Ljava/lang/Throwable;
    //   463: athrow
    //   464: aload_3
    //   465: getstatic burp/Ztc2.Zr : Ljava/lang/String;
    //   468: getstatic burp/Zghe.ZJ : Ljava/lang/Object;
    //   471: checkcast java/math/BigInteger
    //   474: invokevirtual intValue : ()I
    //   477: bipush #32
    //   479: irem
    //   480: invokestatic abs : (I)I
    //   483: invokevirtual charAt : (I)C
    //   486: invokevirtual append : (C)Ljava/lang/StringBuilder;
    //   489: pop
    //   490: iload_2
    //   491: ifeq -> 1348
    //   494: goto -> 501
    //   497: invokestatic a : (Ljava/lang/Throwable;)Ljava/lang/Throwable;
    //   500: athrow
    //   501: aload_3
    //   502: getstatic burp/Zblv.ZF : Ljava/lang/String;
    //   505: getstatic burp/Zmd.ZU : Ljava/lang/Object;
    //   508: checkcast java/math/BigInteger
    //   511: invokevirtual intValue : ()I
    //   514: bipush #32
    //   516: irem
    //   517: invokestatic abs : (I)I
    //   520: invokevirtual charAt : (I)C
    //   523: invokevirtual append : (C)Ljava/lang/StringBuilder;
    //   526: pop
    //   527: iload_2
    //   528: ifeq -> 1348
    //   531: goto -> 538
    //   534: invokestatic a : (Ljava/lang/Throwable;)Ljava/lang/Throwable;
    //   537: athrow
    //   538: aload_3
    //   539: getstatic burp/Zbp.Z_ : Ljava/lang/String;
    //   542: getstatic burp/Zrt9.Zy : Ljava/lang/Object;
    //   545: checkcast java/math/BigInteger
    //   548: invokevirtual intValue : ()I
    //   551: bipush #32
    //   553: irem
    //   554: invokestatic abs : (I)I
    //   557: invokevirtual charAt : (I)C
    //   560: invokevirtual append : (C)Ljava/lang/StringBuilder;
    //   563: pop
    //   564: iload_2
    //   565: ifeq -> 1348
    //   568: goto -> 575
    //   571: invokestatic a : (Ljava/lang/Throwable;)Ljava/lang/Throwable;
    //   574: athrow
    //   575: aload_3
    //   576: getstatic burp/Zlum.ZW : Ljava/lang/String;
    //   579: getstatic burp/Zlwm.Ze : Ljava/lang/Object;
    //   582: checkcast java/math/BigInteger
    //   585: invokevirtual intValue : ()I
    //   588: bipush #32
    //   590: irem
    //   591: invokestatic abs : (I)I
    //   594: invokevirtual charAt : (I)C
    //   597: invokevirtual append : (C)Ljava/lang/StringBuilder;
    //   600: pop
    //   601: iload_2
    //   602: ifeq -> 1348
    //   605: goto -> 612
    //   608: invokestatic a : (Ljava/lang/Throwable;)Ljava/lang/Throwable;
    //   611: athrow
    //   612: aload_3
    //   613: getstatic burp/Zbo7.ZZ : Ljava/lang/String;
    //   616: getstatic burp/Zlzs.ZL : Ljava/lang/Object;
    //   619: checkcast java/math/BigInteger
    //   622: invokevirtual intValue : ()I
    //   625: bipush #32
    //   627: irem
    //   628: invokestatic abs : (I)I
    //   631: invokevirtual charAt : (I)C
    //   634: invokevirtual append : (C)Ljava/lang/StringBuilder;
    //   637: pop
    //   638: iload_2
    //   639: ifeq -> 1348
    //   642: goto -> 649
    //   645: invokestatic a : (Ljava/lang/Throwable;)Ljava/lang/Throwable;
    //   648: athrow
    //   649: aload_3
    //   650: getstatic burp/Zvi.ZR : Ljava/lang/String;
    //   653: getstatic burp/Zzh1.Zf : Ljava/lang/Object;
    //   656: checkcast java/math/BigInteger
    //   659: invokevirtual intValue : ()I
    //   662: bipush #32
    //   664: irem
    //   665: invokestatic abs : (I)I
    //   668: invokevirtual charAt : (I)C
    //   671: invokevirtual append : (C)Ljava/lang/StringBuilder;
    //   674: pop
    //   675: iload_2
    //   676: ifeq -> 1348
    //   679: goto -> 686
    //   682: invokestatic a : (Ljava/lang/Throwable;)Ljava/lang/Throwable;
    //   685: athrow
    //   686: aload_3
    //   687: getstatic burp/Zxoa.Z_ : Ljava/lang/String;
    //   690: getstatic burp/Zbqk.ZT : Ljava/lang/Object;
    //   693: checkcast java/math/BigInteger
    //   696: invokevirtual intValue : ()I
    //   699: bipush #32
    //   701: irem
    //   702: invokestatic abs : (I)I
    //   705: invokevirtual charAt : (I)C
    //   708: invokevirtual append : (C)Ljava/lang/StringBuilder;
    //   711: pop
    //   712: iload_2
    //   713: ifeq -> 1348
    //   716: goto -> 723
    //   719: invokestatic a : (Ljava/lang/Throwable;)Ljava/lang/Throwable;
    //   722: athrow
    //   723: aload_3
    //   724: getstatic burp/Zeig.Zg : Ljava/lang/String;
    //   727: getstatic burp/Zr3q.Zn : Ljava/lang/Object;
    //   730: checkcast java/math/BigInteger
    //   733: invokevirtual intValue : ()I
    //   736: bipush #32
    //   738: irem
    //   739: invokestatic abs : (I)I
    //   742: invokevirtual charAt : (I)C
    //   745: invokevirtual append : (C)Ljava/lang/StringBuilder;
    //   748: pop
    //   749: iload_2
    //   750: ifeq -> 1348
    //   753: goto -> 760
    //   756: invokestatic a : (Ljava/lang/Throwable;)Ljava/lang/Throwable;
    //   759: athrow
    //   760: aload_3
    //   761: getstatic burp/Zm5s.Z_ : Ljava/lang/String;
    //   764: getstatic burp/Zr_y.ZI : Ljava/lang/Object;
    //   767: checkcast java/math/BigInteger
    //   770: invokevirtual intValue : ()I
    //   773: bipush #32
    //   775: irem
    //   776: invokestatic abs : (I)I
    //   779: invokevirtual charAt : (I)C
    //   782: invokevirtual append : (C)Ljava/lang/StringBuilder;
    //   785: pop
    //   786: iload_2
    //   787: ifeq -> 1348
    //   790: goto -> 797
    //   793: invokestatic a : (Ljava/lang/Throwable;)Ljava/lang/Throwable;
    //   796: athrow
    //   797: aload_3
    //   798: getstatic burp/Zlr2.ZV : Ljava/lang/String;
    //   801: getstatic burp/Zmtf.ZH : Ljava/lang/Object;
    //   804: checkcast java/math/BigInteger
    //   807: invokevirtual intValue : ()I
    //   810: bipush #32
    //   812: irem
    //   813: invokestatic abs : (I)I
    //   816: invokevirtual charAt : (I)C
    //   819: invokevirtual append : (C)Ljava/lang/StringBuilder;
    //   822: pop
    //   823: iload_2
    //   824: ifeq -> 1348
    //   827: goto -> 834
    //   830: invokestatic a : (Ljava/lang/Throwable;)Ljava/lang/Throwable;
    //   833: athrow
    //   834: aload_3
    //   835: getstatic burp/Zer1.ZV : Ljava/lang/String;
    //   838: getstatic burp/Zldx.ZM : Ljava/lang/Object;
    //   841: checkcast java/math/BigInteger
    //   844: invokevirtual intValue : ()I
    //   847: bipush #32
    //   849: irem
    //   850: invokestatic abs : (I)I
    //   853: invokevirtual charAt : (I)C
    //   856: invokevirtual append : (C)Ljava/lang/StringBuilder;
    //   859: pop
    //   860: iload_2
    //   861: ifeq -> 1348
    //   864: goto -> 871
    //   867: invokestatic a : (Ljava/lang/Throwable;)Ljava/lang/Throwable;
    //   870: athrow
    //   871: aload_3
    //   872: getstatic burp/Zry0.Zz : Ljava/lang/String;
    //   875: getstatic burp/Zztn.ZO : Ljava/lang/Object;
    //   878: checkcast java/math/BigInteger
    //   881: invokevirtual intValue : ()I
    //   884: bipush #32
    //   886: irem
    //   887: invokestatic abs : (I)I
    //   890: invokevirtual charAt : (I)C
    //   893: invokevirtual append : (C)Ljava/lang/StringBuilder;
    //   896: pop
    //   897: iload_2
    //   898: ifeq -> 1348
    //   901: goto -> 908
    //   904: invokestatic a : (Ljava/lang/Throwable;)Ljava/lang/Throwable;
    //   907: athrow
    //   908: aload_3
    //   909: getstatic burp/Zt7x.Zu : Ljava/lang/String;
    //   912: getstatic burp/Ze6t.Zu : Ljava/lang/Object;
    //   915: checkcast java/math/BigInteger
    //   918: invokevirtual intValue : ()I
    //   921: bipush #32
    //   923: irem
    //   924: invokestatic abs : (I)I
    //   927: invokevirtual charAt : (I)C
    //   930: invokevirtual append : (C)Ljava/lang/StringBuilder;
    //   933: pop
    //   934: iload_2
    //   935: ifeq -> 1348
    //   938: goto -> 945
    //   941: invokestatic a : (Ljava/lang/Throwable;)Ljava/lang/Throwable;
    //   944: athrow
    //   945: aload_3
    //   946: getstatic burp/Zod.ZS : Ljava/lang/String;
    //   949: getstatic burp/Zzbr.ZC : Ljava/lang/Object;
    //   952: checkcast java/math/BigInteger
    //   955: invokevirtual intValue : ()I
    //   958: bipush #32
    //   960: irem
    //   961: invokestatic abs : (I)I
    //   964: invokevirtual charAt : (I)C
    //   967: invokevirtual append : (C)Ljava/lang/StringBuilder;
    //   970: pop
    //   971: iload_2
    //   972: ifeq -> 1348
    //   975: goto -> 982
    //   978: invokestatic a : (Ljava/lang/Throwable;)Ljava/lang/Throwable;
    //   981: athrow
    //   982: aload_3
    //   983: getstatic burp/Ztpa.ZZ : Ljava/lang/String;
    //   986: getstatic burp/Zrc0.Zz : Ljava/lang/Object;
    //   989: checkcast java/math/BigInteger
    //   992: invokevirtual intValue : ()I
    //   995: bipush #32
    //   997: irem
    //   998: invokestatic abs : (I)I
    //   1001: invokevirtual charAt : (I)C
    //   1004: invokevirtual append : (C)Ljava/lang/StringBuilder;
    //   1007: pop
    //   1008: iload_2
    //   1009: ifeq -> 1348
    //   1012: goto -> 1019
    //   1015: invokestatic a : (Ljava/lang/Throwable;)Ljava/lang/Throwable;
    //   1018: athrow
    //   1019: aload_3
    //   1020: getstatic burp/Zr14.ZL : Ljava/lang/String;
    //   1023: getstatic burp/Zsvh.Zv : Ljava/lang/Object;
    //   1026: checkcast java/math/BigInteger
    //   1029: invokevirtual intValue : ()I
    //   1032: bipush #32
    //   1034: irem
    //   1035: invokestatic abs : (I)I
    //   1038: invokevirtual charAt : (I)C
    //   1041: invokevirtual append : (C)Ljava/lang/StringBuilder;
    //   1044: pop
    //   1045: iload_2
    //   1046: ifeq -> 1348
    //   1049: goto -> 1056
    //   1052: invokestatic a : (Ljava/lang/Throwable;)Ljava/lang/Throwable;
    //   1055: athrow
    //   1056: aload_3
    //   1057: getstatic burp/Ztgv.ZC : Ljava/lang/String;
    //   1060: getstatic burp/Zlp7.ZM : Ljava/lang/Object;
    //   1063: checkcast java/math/BigInteger
    //   1066: invokevirtual intValue : ()I
    //   1069: bipush #32
    //   1071: irem
    //   1072: invokestatic abs : (I)I
    //   1075: invokevirtual charAt : (I)C
    //   1078: invokevirtual append : (C)Ljava/lang/StringBuilder;
    //   1081: pop
    //   1082: iload_2
    //   1083: ifeq -> 1348
    //   1086: goto -> 1093
    //   1089: invokestatic a : (Ljava/lang/Throwable;)Ljava/lang/Throwable;
    //   1092: athrow
    //   1093: aload_3
    //   1094: getstatic burp/Zrhu.ZJ : Ljava/lang/String;
    //   1097: getstatic burp/Zzpu.ZS : Ljava/lang/Object;
    //   1100: checkcast java/math/BigInteger
    //   1103: invokevirtual intValue : ()I
    //   1106: bipush #32
    //   1108: irem
    //   1109: invokestatic abs : (I)I
    //   1112: invokevirtual charAt : (I)C
    //   1115: invokevirtual append : (C)Ljava/lang/StringBuilder;
    //   1118: pop
    //   1119: iload_2
    //   1120: ifeq -> 1348
    //   1123: goto -> 1130
    //   1126: invokestatic a : (Ljava/lang/Throwable;)Ljava/lang/Throwable;
    //   1129: athrow
    //   1130: aload_3
    //   1131: getstatic burp/Zke7.Zl : Ljava/lang/String;
    //   1134: getstatic burp/Ze6t.Zu : Ljava/lang/Object;
    //   1137: checkcast java/math/BigInteger
    //   1140: invokevirtual intValue : ()I
    //   1143: bipush #32
    //   1145: irem
    //   1146: invokestatic abs : (I)I
    //   1149: invokevirtual charAt : (I)C
    //   1152: invokevirtual append : (C)Ljava/lang/StringBuilder;
    //   1155: pop
    //   1156: iload_2
    //   1157: ifeq -> 1348
    //   1160: goto -> 1167
    //   1163: invokestatic a : (Ljava/lang/Throwable;)Ljava/lang/Throwable;
    //   1166: athrow
    //   1167: aload_3
    //   1168: getstatic burp/Zlp8.ZW : Ljava/lang/String;
    //   1171: getstatic burp/Zttj.ZF : Ljava/lang/Object;
    //   1174: checkcast java/math/BigInteger
    //   1177: invokevirtual intValue : ()I
    //   1180: bipush #32
    //   1182: irem
    //   1183: invokestatic abs : (I)I
    //   1186: invokevirtual charAt : (I)C
    //   1189: invokevirtual append : (C)Ljava/lang/StringBuilder;
    //   1192: pop
    //   1193: iload_2
    //   1194: ifeq -> 1348
    //   1197: goto -> 1204
    //   1200: invokestatic a : (Ljava/lang/Throwable;)Ljava/lang/Throwable;
    //   1203: athrow
    //   1204: aload_3
    //   1205: getstatic burp/Zz0j.Zf : Ljava/lang/String;
    //   1208: getstatic burp/Zmf6.ZD : Ljava/lang/Object;
    //   1211: checkcast java/math/BigInteger
    //   1214: invokevirtual intValue : ()I
    //   1217: bipush #32
    //   1219: irem
    //   1220: invokestatic abs : (I)I
    //   1223: invokevirtual charAt : (I)C
    //   1226: invokevirtual append : (C)Ljava/lang/StringBuilder;
    //   1229: pop
    //   1230: iload_2
    //   1231: ifeq -> 1348
    //   1234: goto -> 1241
    //   1237: invokestatic a : (Ljava/lang/Throwable;)Ljava/lang/Throwable;
    //   1240: athrow
    //   1241: aload_3
    //   1242: getstatic burp/Zrfh.ZH : Ljava/lang/String;
    //   1245: getstatic burp/Zm54.ZS : Ljava/lang/Object;
    //   1248: checkcast java/math/BigInteger
    //   1251: invokevirtual intValue : ()I
    //   1254: bipush #32
    //   1256: irem
    //   1257: invokestatic abs : (I)I
    //   1260: invokevirtual charAt : (I)C
    //   1263: invokevirtual append : (C)Ljava/lang/StringBuilder;
    //   1266: pop
    //   1267: iload_2
    //   1268: ifeq -> 1348
    //   1271: goto -> 1278
    //   1274: invokestatic a : (Ljava/lang/Throwable;)Ljava/lang/Throwable;
    //   1277: athrow
    //   1278: aload_3
    //   1279: getstatic burp/Zxdy.Zm : Ljava/lang/String;
    //   1282: getstatic burp/Zxof.Zi : Ljava/lang/Object;
    //   1285: checkcast java/math/BigInteger
    //   1288: invokevirtual intValue : ()I
    //   1291: bipush #32
    //   1293: irem
    //   1294: invokestatic abs : (I)I
    //   1297: invokevirtual charAt : (I)C
    //   1300: invokevirtual append : (C)Ljava/lang/StringBuilder;
    //   1303: pop
    //   1304: iload_2
    //   1305: ifeq -> 1348
    //   1308: goto -> 1315
    //   1311: invokestatic a : (Ljava/lang/Throwable;)Ljava/lang/Throwable;
    //   1314: athrow
    //   1315: aload_3
    //   1316: getstatic burp/Zz16.ZA : Ljava/lang/String;
    //   1319: getstatic burp/Zmcb.ZR : Ljava/lang/Object;
    //   1322: checkcast java/math/BigInteger
    //   1325: invokevirtual intValue : ()I
    //   1328: bipush #32
    //   1330: irem
    //   1331: invokestatic abs : (I)I
    //   1334: invokevirtual charAt : (I)C
    //   1337: invokevirtual append : (C)Ljava/lang/StringBuilder;
    //   1340: pop
    //   1341: goto -> 1348
    //   1344: invokestatic a : (Ljava/lang/Throwable;)Ljava/lang/Throwable;
    //   1347: athrow
    //   1348: iinc #4, 1
    //   1351: iload_2
    //   1352: ifeq -> 15
    //   1355: aload_3
    //   1356: invokevirtual toString : ()Ljava/lang/String;
    //   1359: putstatic burp/Zkfa.Zy : Ljava/lang/String;
    //   1362: sipush #-15748
    //   1365: sipush #11415
    //   1368: invokestatic a : (II)Ljava/lang/String;
    //   1371: iconst_1
    //   1372: ldc burp/Zlps
    //   1374: invokevirtual getClassLoader : ()Ljava/lang/ClassLoader;
    //   1377: invokestatic forName : (Ljava/lang/String;ZLjava/lang/ClassLoader;)Ljava/lang/Class;
    //   1380: invokevirtual getDeclaredFields : ()[Ljava/lang/reflect/Field;
    //   1383: astore #4
    //   1385: aload #4
    //   1387: arraylength
    //   1388: istore #5
    //   1390: iconst_0
    //   1391: istore #6
    //   1393: iload #6
    //   1395: iload #5
    //   1397: if_icmpge -> 1535
    //   1400: aload #4
    //   1402: iload #6
    //   1404: aaload
    //   1405: astore #7
    //   1407: aload #7
    //   1409: invokevirtual getModifiers : ()I
    //   1412: invokestatic isStatic : (I)Z
    //   1415: ifne -> 1425
    //   1418: goto -> 1528
    //   1421: invokestatic a : (Ljava/lang/Throwable;)Ljava/lang/Throwable;
    //   1424: athrow
    //   1425: aload #7
    //   1427: invokevirtual getType : ()Ljava/lang/Class;
    //   1430: astore #8
    //   1432: aload #8
    //   1434: ifnull -> 1515
    //   1437: aload #8
    //   1439: invokevirtual isPrimitive : ()Z
    //   1442: ifne -> 1515
    //   1445: goto -> 1452
    //   1448: invokestatic a : (Ljava/lang/Throwable;)Ljava/lang/Throwable;
    //   1451: athrow
    //   1452: aload #8
    //   1454: invokevirtual getPackage : ()Ljava/lang/Package;
    //   1457: ifnull -> 1515
    //   1460: goto -> 1467
    //   1463: invokestatic a : (Ljava/lang/Throwable;)Ljava/lang/Throwable;
    //   1466: athrow
    //   1467: aload #8
    //   1469: invokevirtual getPackage : ()Ljava/lang/Package;
    //   1472: invokevirtual getName : ()Ljava/lang/String;
    //   1475: ifnull -> 1515
    //   1478: goto -> 1485
    //   1481: invokestatic a : (Ljava/lang/Throwable;)Ljava/lang/Throwable;
    //   1484: athrow
    //   1485: aload #8
    //   1487: invokevirtual getPackage : ()Ljava/lang/Package;
    //   1490: invokevirtual getName : ()Ljava/lang/String;
    //   1493: sipush #-15756
    //   1496: sipush #15378
    //   1499: invokestatic a : (II)Ljava/lang/String;
    //   1502: invokevirtual startsWith : (Ljava/lang/String;)Z
    //   1505: ifne -> 1515
    //   1508: goto -> 1515
    //   1511: invokestatic a : (Ljava/lang/Throwable;)Ljava/lang/Throwable;
    //   1514: athrow
    //   1515: aload #7
    //   1517: iconst_1
    //   1518: invokevirtual setAccessible : (Z)V
    //   1521: aload #7
    //   1523: aconst_null
    //   1524: invokevirtual get : (Ljava/lang/Object;)Ljava/lang/Object;
    //   1527: pop
    //   1528: iinc #6, 1
    //   1531: iload_2
    //   1532: ifeq -> 1393
    //   1535: sipush #-15771
    //   1538: sipush #-5505
    //   1541: invokestatic a : (II)Ljava/lang/String;
    //   1544: invokestatic forName : (Ljava/lang/String;)Ljava/lang/Class;
    //   1547: invokevirtual getDeclaredMethods : ()[Ljava/lang/reflect/Method;
    //   1550: astore #4
    //   1552: aload #4
    //   1554: arraylength
    //   1555: istore #5
    //   1557: iconst_0
    //   1558: istore #6
    //   1560: iload #6
    //   1562: iload #5
    //   1564: if_icmpge -> 1676
    //   1567: aload #4
    //   1569: iload #6
    //   1571: aaload
    //   1572: astore #7
    //   1574: aload #7
    //   1576: invokevirtual getParameterTypes : ()[Ljava/lang/Class;
    //   1579: pop
    //   1580: aload #7
    //   1582: invokevirtual getModifiers : ()I
    //   1585: invokestatic isStatic : (I)Z
    //   1588: ifeq -> 1662
    //   1591: aload #7
    //   1593: invokevirtual getParameterTypes : ()[Ljava/lang/Class;
    //   1596: arraylength
    //   1597: iconst_2
    //   1598: if_icmpne -> 1662
    //   1601: goto -> 1608
    //   1604: invokestatic a : (Ljava/lang/Throwable;)Ljava/lang/Throwable;
    //   1607: athrow
    //   1608: aload #7
    //   1610: invokevirtual getReturnType : ()Ljava/lang/Class;
    //   1613: getstatic java/lang/Boolean.TYPE : Ljava/lang/Class;
    //   1616: if_acmpne -> 1662
    //   1619: goto -> 1626
    //   1622: invokestatic a : (Ljava/lang/Throwable;)Ljava/lang/Throwable;
    //   1625: athrow
    //   1626: aload #7
    //   1628: iconst_1
    //   1629: invokevirtual setAccessible : (Z)V
    //   1632: aload #7
    //   1634: aconst_null
    //   1635: iconst_2
    //   1636: anewarray java/lang/Object
    //   1639: dup
    //   1640: iconst_0
    //   1641: aload_0
    //   1642: aastore
    //   1643: dup
    //   1644: iconst_1
    //   1645: aload_1
    //   1646: aastore
    //   1647: invokevirtual invoke : (Ljava/lang/Object;[Ljava/lang/Object;)Ljava/lang/Object;
    //   1650: pop
    //   1651: iload_2
    //   1652: ifeq -> 1676
    //   1655: goto -> 1662
    //   1658: invokestatic a : (Ljava/lang/Throwable;)Ljava/lang/Throwable;
    //   1661: athrow
    //   1662: iinc #6, 1
    //   1665: iload_2
    //   1666: ifeq -> 1560
    //   1669: goto -> 1676
    //   1672: invokestatic a : (Ljava/lang/Throwable;)Ljava/lang/Throwable;
    //   1675: athrow
    //   1676: sipush #-15745
    //   1679: sipush #-20550
    //   1682: invokestatic a : (II)Ljava/lang/String;
    //   1685: iconst_1
    //   1686: ldc burp/Zrs0
    //   1688: invokevirtual getClassLoader : ()Ljava/lang/ClassLoader;
    //   1691: invokestatic forName : (Ljava/lang/String;ZLjava/lang/ClassLoader;)Ljava/lang/Class;
    //   1694: invokevirtual getDeclaredFields : ()[Ljava/lang/reflect/Field;
    //   1697: astore #4
    //   1699: aload #4
    //   1701: arraylength
    //   1702: istore #5
    //   1704: iconst_0
    //   1705: istore #6
    //   1707: iload #6
    //   1709: iload #5
    //   1711: if_icmpge -> 1849
    //   1714: aload #4
    //   1716: iload #6
    //   1718: aaload
    //   1719: astore #7
    //   1721: aload #7
    //   1723: invokevirtual getModifiers : ()I
    //   1726: invokestatic isStatic : (I)Z
    //   1729: ifne -> 1739
    //   1732: goto -> 1842
    //   1735: invokestatic a : (Ljava/lang/Throwable;)Ljava/lang/Throwable;
    //   1738: athrow
    //   1739: aload #7
    //   1741: invokevirtual getType : ()Ljava/lang/Class;
    //   1744: astore #8
    //   1746: aload #8
    //   1748: ifnull -> 1829
    //   1751: aload #8
    //   1753: invokevirtual isPrimitive : ()Z
    //   1756: ifne -> 1829
    //   1759: goto -> 1766
    //   1762: invokestatic a : (Ljava/lang/Throwable;)Ljava/lang/Throwable;
    //   1765: athrow
    //   1766: aload #8
    //   1768: invokevirtual getPackage : ()Ljava/lang/Package;
    //   1771: ifnull -> 1829
    //   1774: goto -> 1781
    //   1777: invokestatic a : (Ljava/lang/Throwable;)Ljava/lang/Throwable;
    //   1780: athrow
    //   1781: aload #8
    //   1783: invokevirtual getPackage : ()Ljava/lang/Package;
    //   1786: invokevirtual getName : ()Ljava/lang/String;
    //   1789: ifnull -> 1829
    //   1792: goto -> 1799
    //   1795: invokestatic a : (Ljava/lang/Throwable;)Ljava/lang/Throwable;
    //   1798: athrow
    //   1799: aload #8
    //   1801: invokevirtual getPackage : ()Ljava/lang/Package;
    //   1804: invokevirtual getName : ()Ljava/lang/String;
    //   1807: sipush #-15765
    //   1810: sipush #27139
    //   1813: invokestatic a : (II)Ljava/lang/String;
    //   1816: invokevirtual startsWith : (Ljava/lang/String;)Z
    //   1819: ifne -> 1829
    //   1822: goto -> 1829
    //   1825: invokestatic a : (Ljava/lang/Throwable;)Ljava/lang/Throwable;
    //   1828: athrow
    //   1829: aload #7
    //   1831: iconst_1
    //   1832: invokevirtual setAccessible : (Z)V
    //   1835: aload #7
    //   1837: aconst_null
    //   1838: invokevirtual get : (Ljava/lang/Object;)Ljava/lang/Object;
    //   1841: pop
    //   1842: iinc #6, 1
    //   1845: iload_2
    //   1846: ifeq -> 1707
    //   1849: sipush #-15746
    //   1852: sipush #23534
    //   1855: invokestatic a : (II)Ljava/lang/String;
    //   1858: invokestatic forName : (Ljava/lang/String;)Ljava/lang/Class;
    //   1861: invokevirtual getDeclaredMethods : ()[Ljava/lang/reflect/Method;
    //   1864: astore #4
    //   1866: aload #4
    //   1868: arraylength
    //   1869: istore #5
    //   1871: iconst_0
    //   1872: istore #6
    //   1874: iload #6
    //   1876: iload #5
    //   1878: if_icmpge -> 2008
    //   1881: aload #4
    //   1883: iload #6
    //   1885: aaload
    //   1886: astore #7
    //   1888: aload #7
    //   1890: invokevirtual getParameterTypes : ()[Ljava/lang/Class;
    //   1893: pop
    //   1894: aload #7
    //   1896: invokevirtual getModifiers : ()I
    //   1899: invokestatic isStatic : (I)Z
    //   1902: ifeq -> 1994
    //   1905: aload #7
    //   1907: invokevirtual getParameterTypes : ()[Ljava/lang/Class;
    //   1910: arraylength
    //   1911: iconst_2
    //   1912: if_icmpne -> 1994
    //   1915: goto -> 1922
    //   1918: invokestatic a : (Ljava/lang/Throwable;)Ljava/lang/Throwable;
    //   1921: athrow
    //   1922: aload #7
    //   1924: invokevirtual getReturnType : ()Ljava/lang/Class;
    //   1927: getstatic java/lang/Boolean.TYPE : Ljava/lang/Class;
    //   1930: if_acmpne -> 1994
    //   1933: goto -> 1940
    //   1936: invokestatic a : (Ljava/lang/Throwable;)Ljava/lang/Throwable;
    //   1939: athrow
    //   1940: aload #7
    //   1942: iconst_1
    //   1943: invokevirtual setAccessible : (Z)V
    //   1946: aload #7
    //   1948: aconst_null
    //   1949: iconst_2
    //   1950: anewarray java/lang/Object
    //   1953: dup
    //   1954: iconst_0
    //   1955: aload_0
    //   1956: aastore
    //   1957: dup
    //   1958: iconst_1
    //   1959: aload_1
    //   1960: ifnonnull -> 1978
    //   1963: goto -> 1970
    //   1966: invokestatic a : (Ljava/lang/Throwable;)Ljava/lang/Throwable;
    //   1969: athrow
    //   1970: aload_1
    //   1971: goto -> 1985
    //   1974: invokestatic a : (Ljava/lang/Throwable;)Ljava/lang/Throwable;
    //   1977: athrow
    //   1978: aload_1
    //   1979: checkcast [B
    //   1982: invokevirtual clone : ()Ljava/lang/Object;
    //   1985: aastore
    //   1986: invokevirtual invoke : (Ljava/lang/Object;[Ljava/lang/Object;)Ljava/lang/Object;
    //   1989: pop
    //   1990: iload_2
    //   1991: ifeq -> 2008
    //   1994: iinc #6, 1
    //   1997: iload_2
    //   1998: ifeq -> 1874
    //   2001: goto -> 2008
    //   2004: invokestatic a : (Ljava/lang/Throwable;)Ljava/lang/Throwable;
    //   2007: athrow
    //   2008: sipush #-15752
    //   2011: sipush #-16951
    //   2014: invokestatic a : (II)Ljava/lang/String;
    //   2017: iconst_1
    //   2018: ldc burp/Zrhp
    //   2020: invokevirtual getClassLoader : ()Ljava/lang/ClassLoader;
    //   2023: invokestatic forName : (Ljava/lang/String;ZLjava/lang/ClassLoader;)Ljava/lang/Class;
    //   2026: invokevirtual getDeclaredFields : ()[Ljava/lang/reflect/Field;
    //   2029: astore #4
    //   2031: aload #4
    //   2033: arraylength
    //   2034: istore #5
    //   2036: iconst_0
    //   2037: istore #6
    //   2039: iload #6
    //   2041: iload #5
    //   2043: if_icmpge -> 2181
    //   2046: aload #4
    //   2048: iload #6
    //   2050: aaload
    //   2051: astore #7
    //   2053: aload #7
    //   2055: invokevirtual getModifiers : ()I
    //   2058: invokestatic isStatic : (I)Z
    //   2061: ifne -> 2071
    //   2064: goto -> 2174
    //   2067: invokestatic a : (Ljava/lang/Throwable;)Ljava/lang/Throwable;
    //   2070: athrow
    //   2071: aload #7
    //   2073: invokevirtual getType : ()Ljava/lang/Class;
    //   2076: astore #8
    //   2078: aload #8
    //   2080: ifnull -> 2161
    //   2083: aload #8
    //   2085: invokevirtual isPrimitive : ()Z
    //   2088: ifne -> 2161
    //   2091: goto -> 2098
    //   2094: invokestatic a : (Ljava/lang/Throwable;)Ljava/lang/Throwable;
    //   2097: athrow
    //   2098: aload #8
    //   2100: invokevirtual getPackage : ()Ljava/lang/Package;
    //   2103: ifnull -> 2161
    //   2106: goto -> 2113
    //   2109: invokestatic a : (Ljava/lang/Throwable;)Ljava/lang/Throwable;
    //   2112: athrow
    //   2113: aload #8
    //   2115: invokevirtual getPackage : ()Ljava/lang/Package;
    //   2118: invokevirtual getName : ()Ljava/lang/String;
    //   2121: ifnull -> 2161
    //   2124: goto -> 2131
    //   2127: invokestatic a : (Ljava/lang/Throwable;)Ljava/lang/Throwable;
    //   2130: athrow
    //   2131: aload #8
    //   2133: invokevirtual getPackage : ()Ljava/lang/Package;
    //   2136: invokevirtual getName : ()Ljava/lang/String;
    //   2139: sipush #-15765
    //   2142: sipush #27139
    //   2145: invokestatic a : (II)Ljava/lang/String;
    //   2148: invokevirtual startsWith : (Ljava/lang/String;)Z
    //   2151: ifne -> 2161
    //   2154: goto -> 2161
    //   2157: invokestatic a : (Ljava/lang/Throwable;)Ljava/lang/Throwable;
    //   2160: athrow
    //   2161: aload #7
    //   2163: iconst_1
    //   2164: invokevirtual setAccessible : (Z)V
    //   2167: aload #7
    //   2169: aconst_null
    //   2170: invokevirtual get : (Ljava/lang/Object;)Ljava/lang/Object;
    //   2173: pop
    //   2174: iinc #6, 1
    //   2177: iload_2
    //   2178: ifeq -> 2039
    //   2181: sipush #-15760
    //   2184: sipush #20730
    //   2187: invokestatic a : (II)Ljava/lang/String;
    //   2190: invokestatic forName : (Ljava/lang/String;)Ljava/lang/Class;
    //   2193: invokevirtual getDeclaredMethods : ()[Ljava/lang/reflect/Method;
    //   2196: astore #4
    //   2198: aload #4
    //   2200: arraylength
    //   2201: istore #5
    //   2203: iconst_0
    //   2204: istore #6
    //   2206: iload #6
    //   2208: iload #5
    //   2210: if_icmpge -> 2343
    //   2213: aload #4
    //   2215: iload #6
    //   2217: aaload
    //   2218: astore #7
    //   2220: aload #7
    //   2222: invokevirtual getParameterTypes : ()[Ljava/lang/Class;
    //   2225: pop
    //   2226: aload #7
    //   2228: invokevirtual getModifiers : ()I
    //   2231: invokestatic isStatic : (I)Z
    //   2234: ifeq -> 2329
    //   2237: aload #7
    //   2239: invokevirtual getParameterTypes : ()[Ljava/lang/Class;
    //   2242: arraylength
    //   2243: iconst_2
    //   2244: if_icmpne -> 2329
    //   2247: goto -> 2254
    //   2250: invokestatic a : (Ljava/lang/Throwable;)Ljava/lang/Throwable;
    //   2253: athrow
    //   2254: aload #7
    //   2256: invokevirtual getReturnType : ()Ljava/lang/Class;
    //   2259: getstatic java/lang/Void.TYPE : Ljava/lang/Class;
    //   2262: invokevirtual equals : (Ljava/lang/Object;)Z
    //   2265: ifeq -> 2329
    //   2268: goto -> 2275
    //   2271: invokestatic a : (Ljava/lang/Throwable;)Ljava/lang/Throwable;
    //   2274: athrow
    //   2275: aload #7
    //   2277: iconst_1
    //   2278: invokevirtual setAccessible : (Z)V
    //   2281: aload #7
    //   2283: aconst_null
    //   2284: iconst_2
    //   2285: anewarray java/lang/Object
    //   2288: dup
    //   2289: iconst_0
    //   2290: aload_0
    //   2291: aastore
    //   2292: dup
    //   2293: iconst_1
    //   2294: aload_1
    //   2295: ifnonnull -> 2313
    //   2298: goto -> 2305
    //   2301: invokestatic a : (Ljava/lang/Throwable;)Ljava/lang/Throwable;
    //   2304: athrow
    //   2305: aload_1
    //   2306: goto -> 2320
    //   2309: invokestatic a : (Ljava/lang/Throwable;)Ljava/lang/Throwable;
    //   2312: athrow
    //   2313: aload_1
    //   2314: checkcast [B
    //   2317: invokevirtual clone : ()Ljava/lang/Object;
    //   2320: aastore
    //   2321: invokevirtual invoke : (Ljava/lang/Object;[Ljava/lang/Object;)Ljava/lang/Object;
    //   2324: pop
    //   2325: iload_2
    //   2326: ifeq -> 2343
    //   2329: iinc #6, 1
    //   2332: iload_2
    //   2333: ifeq -> 2206
    //   2336: goto -> 2343
    //   2339: invokestatic a : (Ljava/lang/Throwable;)Ljava/lang/Throwable;
    //   2342: athrow
    //   2343: iconst_0
    //   2344: istore #4
    //   2346: getstatic burp/Zzmo.Zx : Ljava/lang/String;
    //   2349: getstatic burp/Zlp8.Zu : Ljava/lang/Object;
    //   2352: checkcast java/math/BigInteger
    //   2355: invokevirtual intValue : ()I
    //   2358: bipush #32
    //   2360: irem
    //   2361: invokestatic abs : (I)I
    //   2364: invokevirtual charAt : (I)C
    //   2367: getstatic burp/Ztv8.ZJ : Ljava/lang/String;
    //   2370: getstatic burp/Zexn.Zl : Ljava/lang/Object;
    //   2373: checkcast java/math/BigInteger
    //   2376: invokevirtual intValue : ()I
    //   2379: bipush #32
    //   2381: irem
    //   2382: invokestatic abs : (I)I
    //   2385: invokevirtual charAt : (I)C
    //   2388: if_icmpgt -> 2733
    //   2391: sipush #-15772
    //   2394: sipush #-7375
    //   2397: invokestatic a : (II)Ljava/lang/String;
    //   2400: iconst_1
    //   2401: ldc burp/Zzuh
    //   2403: invokevirtual getClassLoader : ()Ljava/lang/ClassLoader;
    //   2406: invokestatic forName : (Ljava/lang/String;ZLjava/lang/ClassLoader;)Ljava/lang/Class;
    //   2409: invokevirtual getDeclaredFields : ()[Ljava/lang/reflect/Field;
    //   2412: astore #5
    //   2414: aload #5
    //   2416: arraylength
    //   2417: istore #6
    //   2419: iconst_0
    //   2420: istore #7
    //   2422: iload #7
    //   2424: iload #6
    //   2426: if_icmpge -> 2564
    //   2429: aload #5
    //   2431: iload #7
    //   2433: aaload
    //   2434: astore #8
    //   2436: aload #8
    //   2438: invokevirtual getModifiers : ()I
    //   2441: invokestatic isStatic : (I)Z
    //   2444: ifne -> 2454
    //   2447: goto -> 2557
    //   2450: invokestatic a : (Ljava/lang/Throwable;)Ljava/lang/Throwable;
    //   2453: athrow
    //   2454: aload #8
    //   2456: invokevirtual getType : ()Ljava/lang/Class;
    //   2459: astore #9
    //   2461: aload #9
    //   2463: ifnull -> 2544
    //   2466: aload #9
    //   2468: invokevirtual isPrimitive : ()Z
    //   2471: ifne -> 2544
    //   2474: goto -> 2481
    //   2477: invokestatic a : (Ljava/lang/Throwable;)Ljava/lang/Throwable;
    //   2480: athrow
    //   2481: aload #9
    //   2483: invokevirtual getPackage : ()Ljava/lang/Package;
    //   2486: ifnull -> 2544
    //   2489: goto -> 2496
    //   2492: invokestatic a : (Ljava/lang/Throwable;)Ljava/lang/Throwable;
    //   2495: athrow
    //   2496: aload #9
    //   2498: invokevirtual getPackage : ()Ljava/lang/Package;
    //   2501: invokevirtual getName : ()Ljava/lang/String;
    //   2504: ifnull -> 2544
    //   2507: goto -> 2514
    //   2510: invokestatic a : (Ljava/lang/Throwable;)Ljava/lang/Throwable;
    //   2513: athrow
    //   2514: aload #9
    //   2516: invokevirtual getPackage : ()Ljava/lang/Package;
    //   2519: invokevirtual getName : ()Ljava/lang/String;
    //   2522: sipush #-15765
    //   2525: sipush #27139
    //   2528: invokestatic a : (II)Ljava/lang/String;
    //   2531: invokevirtual startsWith : (Ljava/lang/String;)Z
    //   2534: ifne -> 2544
    //   2537: goto -> 2544
    //   2540: invokestatic a : (Ljava/lang/Throwable;)Ljava/lang/Throwable;
    //   2543: athrow
    //   2544: aload #8
    //   2546: iconst_1
    //   2547: invokevirtual setAccessible : (Z)V
    //   2550: aload #8
    //   2552: aconst_null
    //   2553: invokevirtual get : (Ljava/lang/Object;)Ljava/lang/Object;
    //   2556: pop
    //   2557: iinc #7, 1
    //   2560: iload_2
    //   2561: ifeq -> 2422
    //   2564: sipush #-15775
    //   2567: sipush #31731
    //   2570: invokestatic a : (II)Ljava/lang/String;
    //   2573: invokestatic forName : (Ljava/lang/String;)Ljava/lang/Class;
    //   2576: invokevirtual getDeclaredMethods : ()[Ljava/lang/reflect/Method;
    //   2579: astore #5
    //   2581: aload #5
    //   2583: arraylength
    //   2584: istore #6
    //   2586: iconst_0
    //   2587: istore #7
    //   2589: iload #7
    //   2591: iload #6
    //   2593: if_icmpge -> 2730
    //   2596: aload #5
    //   2598: iload #7
    //   2600: aaload
    //   2601: astore #8
    //   2603: aload #8
    //   2605: invokevirtual getParameterTypes : ()[Ljava/lang/Class;
    //   2608: pop
    //   2609: aload #8
    //   2611: invokevirtual getModifiers : ()I
    //   2614: invokestatic isStatic : (I)Z
    //   2617: ifeq -> 2716
    //   2620: aload #8
    //   2622: invokevirtual getParameterTypes : ()[Ljava/lang/Class;
    //   2625: arraylength
    //   2626: iconst_2
    //   2627: if_icmpne -> 2716
    //   2630: goto -> 2637
    //   2633: invokestatic a : (Ljava/lang/Throwable;)Ljava/lang/Throwable;
    //   2636: athrow
    //   2637: aload #8
    //   2639: invokevirtual getReturnType : ()Ljava/lang/Class;
    //   2642: getstatic java/lang/Boolean.TYPE : Ljava/lang/Class;
    //   2645: if_acmpne -> 2716
    //   2648: goto -> 2655
    //   2651: invokestatic a : (Ljava/lang/Throwable;)Ljava/lang/Throwable;
    //   2654: athrow
    //   2655: aload #8
    //   2657: iconst_1
    //   2658: invokevirtual setAccessible : (Z)V
    //   2661: aload #8
    //   2663: aconst_null
    //   2664: iconst_2
    //   2665: anewarray java/lang/Object
    //   2668: dup
    //   2669: iconst_0
    //   2670: aload_0
    //   2671: aastore
    //   2672: dup
    //   2673: iconst_1
    //   2674: aload_1
    //   2675: ifnonnull -> 2693
    //   2678: goto -> 2685
    //   2681: invokestatic a : (Ljava/lang/Throwable;)Ljava/lang/Throwable;
    //   2684: athrow
    //   2685: aload_1
    //   2686: goto -> 2700
    //   2689: invokestatic a : (Ljava/lang/Throwable;)Ljava/lang/Throwable;
    //   2692: athrow
    //   2693: aload_1
    //   2694: checkcast [B
    //   2697: invokevirtual clone : ()Ljava/lang/Object;
    //   2700: aastore
    //   2701: invokevirtual invoke : (Ljava/lang/Object;[Ljava/lang/Object;)Ljava/lang/Object;
    //   2704: checkcast java/lang/Boolean
    //   2707: invokevirtual booleanValue : ()Z
    //   2710: istore #4
    //   2712: iload_2
    //   2713: ifeq -> 2730
    //   2716: iinc #7, 1
    //   2719: iload_2
    //   2720: ifeq -> 2589
    //   2723: goto -> 2730
    //   2726: invokestatic a : (Ljava/lang/Throwable;)Ljava/lang/Throwable;
    //   2729: athrow
    //   2730: goto -> 3072
    //   2733: sipush #-15770
    //   2736: sipush #-1810
    //   2739: invokestatic a : (II)Ljava/lang/String;
    //   2742: iconst_1
    //   2743: ldc burp/Zrpx
    //   2745: invokevirtual getClassLoader : ()Ljava/lang/ClassLoader;
    //   2748: invokestatic forName : (Ljava/lang/String;ZLjava/lang/ClassLoader;)Ljava/lang/Class;
    //   2751: invokevirtual getDeclaredFields : ()[Ljava/lang/reflect/Field;
    //   2754: astore #5
    //   2756: aload #5
    //   2758: arraylength
    //   2759: istore #6
    //   2761: iconst_0
    //   2762: istore #7
    //   2764: iload #7
    //   2766: iload #6
    //   2768: if_icmpge -> 2906
    //   2771: aload #5
    //   2773: iload #7
    //   2775: aaload
    //   2776: astore #8
    //   2778: aload #8
    //   2780: invokevirtual getModifiers : ()I
    //   2783: invokestatic isStatic : (I)Z
    //   2786: ifne -> 2796
    //   2789: goto -> 2899
    //   2792: invokestatic a : (Ljava/lang/Throwable;)Ljava/lang/Throwable;
    //   2795: athrow
    //   2796: aload #8
    //   2798: invokevirtual getType : ()Ljava/lang/Class;
    //   2801: astore #9
    //   2803: aload #9
    //   2805: ifnull -> 2886
    //   2808: aload #9
    //   2810: invokevirtual isPrimitive : ()Z
    //   2813: ifne -> 2886
    //   2816: goto -> 2823
    //   2819: invokestatic a : (Ljava/lang/Throwable;)Ljava/lang/Throwable;
    //   2822: athrow
    //   2823: aload #9
    //   2825: invokevirtual getPackage : ()Ljava/lang/Package;
    //   2828: ifnull -> 2886
    //   2831: goto -> 2838
    //   2834: invokestatic a : (Ljava/lang/Throwable;)Ljava/lang/Throwable;
    //   2837: athrow
    //   2838: aload #9
    //   2840: invokevirtual getPackage : ()Ljava/lang/Package;
    //   2843: invokevirtual getName : ()Ljava/lang/String;
    //   2846: ifnull -> 2886
    //   2849: goto -> 2856
    //   2852: invokestatic a : (Ljava/lang/Throwable;)Ljava/lang/Throwable;
    //   2855: athrow
    //   2856: aload #9
    //   2858: invokevirtual getPackage : ()Ljava/lang/Package;
    //   2861: invokevirtual getName : ()Ljava/lang/String;
    //   2864: sipush #-15765
    //   2867: sipush #27139
    //   2870: invokestatic a : (II)Ljava/lang/String;
    //   2873: invokevirtual startsWith : (Ljava/lang/String;)Z
    //   2876: ifne -> 2886
    //   2879: goto -> 2886
    //   2882: invokestatic a : (Ljava/lang/Throwable;)Ljava/lang/Throwable;
    //   2885: athrow
    //   2886: aload #8
    //   2888: iconst_1
    //   2889: invokevirtual setAccessible : (Z)V
    //   2892: aload #8
    //   2894: aconst_null
    //   2895: invokevirtual get : (Ljava/lang/Object;)Ljava/lang/Object;
    //   2898: pop
    //   2899: iinc #7, 1
    //   2902: iload_2
    //   2903: ifeq -> 2764
    //   2906: sipush #-15750
    //   2909: sipush #-5865
    //   2912: invokestatic a : (II)Ljava/lang/String;
    //   2915: invokestatic forName : (Ljava/lang/String;)Ljava/lang/Class;
    //   2918: invokevirtual getDeclaredMethods : ()[Ljava/lang/reflect/Method;
    //   2921: astore #5
    //   2923: aload #5
    //   2925: arraylength
    //   2926: istore #6
    //   2928: iconst_0
    //   2929: istore #7
    //   2931: iload #7
    //   2933: iload #6
    //   2935: if_icmpge -> 3072
    //   2938: aload #5
    //   2940: iload #7
    //   2942: aaload
    //   2943: astore #8
    //   2945: aload #8
    //   2947: invokevirtual getParameterTypes : ()[Ljava/lang/Class;
    //   2950: pop
    //   2951: aload #8
    //   2953: invokevirtual getModifiers : ()I
    //   2956: invokestatic isStatic : (I)Z
    //   2959: ifeq -> 3058
    //   2962: aload #8
    //   2964: invokevirtual getParameterTypes : ()[Ljava/lang/Class;
    //   2967: arraylength
    //   2968: iconst_2
    //   2969: if_icmpne -> 3058
    //   2972: goto -> 2979
    //   2975: invokestatic a : (Ljava/lang/Throwable;)Ljava/lang/Throwable;
    //   2978: athrow
    //   2979: aload #8
    //   2981: invokevirtual getReturnType : ()Ljava/lang/Class;
    //   2984: getstatic java/lang/Boolean.TYPE : Ljava/lang/Class;
    //   2987: if_acmpne -> 3058
    //   2990: goto -> 2997
    //   2993: invokestatic a : (Ljava/lang/Throwable;)Ljava/lang/Throwable;
    //   2996: athrow
    //   2997: aload #8
    //   2999: iconst_1
    //   3000: invokevirtual setAccessible : (Z)V
    //   3003: aload #8
    //   3005: aconst_null
    //   3006: iconst_2
    //   3007: anewarray java/lang/Object
    //   3010: dup
    //   3011: iconst_0
    //   3012: aload_0
    //   3013: aastore
    //   3014: dup
    //   3015: iconst_1
    //   3016: aload_1
    //   3017: ifnonnull -> 3035
    //   3020: goto -> 3027
    //   3023: invokestatic a : (Ljava/lang/Throwable;)Ljava/lang/Throwable;
    //   3026: athrow
    //   3027: aload_1
    //   3028: goto -> 3042
    //   3031: invokestatic a : (Ljava/lang/Throwable;)Ljava/lang/Throwable;
    //   3034: athrow
    //   3035: aload_1
    //   3036: checkcast [B
    //   3039: invokevirtual clone : ()Ljava/lang/Object;
    //   3042: aastore
    //   3043: invokevirtual invoke : (Ljava/lang/Object;[Ljava/lang/Object;)Ljava/lang/Object;
    //   3046: checkcast java/lang/Boolean
    //   3049: invokevirtual booleanValue : ()Z
    //   3052: istore #4
    //   3054: iload_2
    //   3055: ifeq -> 3072
    //   3058: iinc #7, 1
    //   3061: iload_2
    //   3062: ifeq -> 2931
    //   3065: goto -> 3072
    //   3068: invokestatic a : (Ljava/lang/Throwable;)Ljava/lang/Throwable;
    //   3071: athrow
    //   3072: iload #4
    //   3074: ifeq -> 3080
    //   3077: iload #4
    //   3079: ireturn
    //   3080: getstatic burp/Zmha.Zo : Ljava/lang/String;
    //   3083: getstatic burp/Ztp.Zp : Ljava/lang/Object;
    //   3086: checkcast java/math/BigInteger
    //   3089: invokevirtual intValue : ()I
    //   3092: bipush #32
    //   3094: irem
    //   3095: invokestatic abs : (I)I
    //   3098: invokevirtual charAt : (I)C
    //   3101: getstatic burp/Zlxs.ZM : Ljava/lang/String;
    //   3104: getstatic burp/Zlo4.ZC : Ljava/lang/Object;
    //   3107: checkcast java/math/BigInteger
    //   3110: invokevirtual intValue : ()I
    //   3113: bipush #32
    //   3115: irem
    //   3116: invokestatic abs : (I)I
    //   3119: invokevirtual charAt : (I)C
    //   3122: if_icmpgt -> 3468
    //   3125: sipush #-15766
    //   3128: sipush #-13729
    //   3131: invokestatic a : (II)Ljava/lang/String;
    //   3134: iconst_1
    //   3135: ldc burp/Zrka
    //   3137: invokevirtual getClassLoader : ()Ljava/lang/ClassLoader;
    //   3140: invokestatic forName : (Ljava/lang/String;ZLjava/lang/ClassLoader;)Ljava/lang/Class;
    //   3143: invokevirtual getDeclaredFields : ()[Ljava/lang/reflect/Field;
    //   3146: astore #5
    //   3148: aload #5
    //   3150: arraylength
    //   3151: istore #6
    //   3153: iconst_0
    //   3154: istore #7
    //   3156: iload #7
    //   3158: iload #6
    //   3160: if_icmpge -> 3298
    //   3163: aload #5
    //   3165: iload #7
    //   3167: aaload
    //   3168: astore #8
    //   3170: aload #8
    //   3172: invokevirtual getModifiers : ()I
    //   3175: invokestatic isStatic : (I)Z
    //   3178: ifne -> 3188
    //   3181: goto -> 3291
    //   3184: invokestatic a : (Ljava/lang/Throwable;)Ljava/lang/Throwable;
    //   3187: athrow
    //   3188: aload #8
    //   3190: invokevirtual getType : ()Ljava/lang/Class;
    //   3193: astore #9
    //   3195: aload #9
    //   3197: ifnull -> 3278
    //   3200: aload #9
    //   3202: invokevirtual isPrimitive : ()Z
    //   3205: ifne -> 3278
    //   3208: goto -> 3215
    //   3211: invokestatic a : (Ljava/lang/Throwable;)Ljava/lang/Throwable;
    //   3214: athrow
    //   3215: aload #9
    //   3217: invokevirtual getPackage : ()Ljava/lang/Package;
    //   3220: ifnull -> 3278
    //   3223: goto -> 3230
    //   3226: invokestatic a : (Ljava/lang/Throwable;)Ljava/lang/Throwable;
    //   3229: athrow
    //   3230: aload #9
    //   3232: invokevirtual getPackage : ()Ljava/lang/Package;
    //   3235: invokevirtual getName : ()Ljava/lang/String;
    //   3238: ifnull -> 3278
    //   3241: goto -> 3248
    //   3244: invokestatic a : (Ljava/lang/Throwable;)Ljava/lang/Throwable;
    //   3247: athrow
    //   3248: aload #9
    //   3250: invokevirtual getPackage : ()Ljava/lang/Package;
    //   3253: invokevirtual getName : ()Ljava/lang/String;
    //   3256: sipush #-15765
    //   3259: sipush #27139
    //   3262: invokestatic a : (II)Ljava/lang/String;
    //   3265: invokevirtual startsWith : (Ljava/lang/String;)Z
    //   3268: ifne -> 3278
    //   3271: goto -> 3278
    //   3274: invokestatic a : (Ljava/lang/Throwable;)Ljava/lang/Throwable;
    //   3277: athrow
    //   3278: aload #8
    //   3280: iconst_1
    //   3281: invokevirtual setAccessible : (Z)V
    //   3284: aload #8
    //   3286: aconst_null
    //   3287: invokevirtual get : (Ljava/lang/Object;)Ljava/lang/Object;
    //   3290: pop
    //   3291: iinc #7, 1
    //   3294: iload_2
    //   3295: ifeq -> 3156
    //   3298: sipush #-15764
    //   3301: sipush #8568
    //   3304: invokestatic a : (II)Ljava/lang/String;
    //   3307: invokestatic forName : (Ljava/lang/String;)Ljava/lang/Class;
    //   3310: invokevirtual getDeclaredMethods : ()[Ljava/lang/reflect/Method;
    //   3313: astore #5
    //   3315: aload #5
    //   3317: arraylength
    //   3318: istore #6
    //   3320: iconst_0
    //   3321: istore #7
    //   3323: iload #7
    //   3325: iload #6
    //   3327: if_icmpge -> 3464
    //   3330: aload #5
    //   3332: iload #7
    //   3334: aaload
    //   3335: astore #8
    //   3337: aload #8
    //   3339: invokevirtual getParameterTypes : ()[Ljava/lang/Class;
    //   3342: pop
    //   3343: aload #8
    //   3345: invokevirtual getModifiers : ()I
    //   3348: invokestatic isStatic : (I)Z
    //   3351: ifeq -> 3450
    //   3354: aload #8
    //   3356: invokevirtual getParameterTypes : ()[Ljava/lang/Class;
    //   3359: arraylength
    //   3360: iconst_2
    //   3361: if_icmpne -> 3450
    //   3364: goto -> 3371
    //   3367: invokestatic a : (Ljava/lang/Throwable;)Ljava/lang/Throwable;
    //   3370: athrow
    //   3371: aload #8
    //   3373: invokevirtual getReturnType : ()Ljava/lang/Class;
    //   3376: getstatic java/lang/Boolean.TYPE : Ljava/lang/Class;
    //   3379: if_acmpne -> 3450
    //   3382: goto -> 3389
    //   3385: invokestatic a : (Ljava/lang/Throwable;)Ljava/lang/Throwable;
    //   3388: athrow
    //   3389: aload #8
    //   3391: iconst_1
    //   3392: invokevirtual setAccessible : (Z)V
    //   3395: aload #8
    //   3397: aconst_null
    //   3398: iconst_2
    //   3399: anewarray java/lang/Object
    //   3402: dup
    //   3403: iconst_0
    //   3404: aload_0
    //   3405: aastore
    //   3406: dup
    //   3407: iconst_1
    //   3408: aload_1
    //   3409: ifnonnull -> 3427
    //   3412: goto -> 3419
    //   3415: invokestatic a : (Ljava/lang/Throwable;)Ljava/lang/Throwable;
    //   3418: athrow
    //   3419: aload_1
    //   3420: goto -> 3434
    //   3423: invokestatic a : (Ljava/lang/Throwable;)Ljava/lang/Throwable;
    //   3426: athrow
    //   3427: aload_1
    //   3428: checkcast [B
    //   3431: invokevirtual clone : ()Ljava/lang/Object;
    //   3434: aastore
    //   3435: invokevirtual invoke : (Ljava/lang/Object;[Ljava/lang/Object;)Ljava/lang/Object;
    //   3438: checkcast java/lang/Boolean
    //   3441: invokevirtual booleanValue : ()Z
    //   3444: istore #4
    //   3446: iload_2
    //   3447: ifeq -> 3464
    //   3450: iinc #7, 1
    //   3453: iload_2
    //   3454: ifeq -> 3323
    //   3457: goto -> 3464
    //   3460: invokestatic a : (Ljava/lang/Throwable;)Ljava/lang/Throwable;
    //   3463: athrow
    //   3464: iload_2
    //   3465: ifeq -> 3807
    //   3468: sipush #-15753
    //   3471: sipush #29712
    //   3474: invokestatic a : (II)Ljava/lang/String;
    //   3477: iconst_1
    //   3478: ldc burp/Zxk9
    //   3480: invokevirtual getClassLoader : ()Ljava/lang/ClassLoader;
    //   3483: invokestatic forName : (Ljava/lang/String;ZLjava/lang/ClassLoader;)Ljava/lang/Class;
    //   3486: invokevirtual getDeclaredFields : ()[Ljava/lang/reflect/Field;
    //   3489: astore #5
    //   3491: aload #5
    //   3493: arraylength
    //   3494: istore #6
    //   3496: iconst_0
    //   3497: istore #7
    //   3499: iload #7
    //   3501: iload #6
    //   3503: if_icmpge -> 3641
    //   3506: aload #5
    //   3508: iload #7
    //   3510: aaload
    //   3511: astore #8
    //   3513: aload #8
    //   3515: invokevirtual getModifiers : ()I
    //   3518: invokestatic isStatic : (I)Z
    //   3521: ifne -> 3531
    //   3524: goto -> 3634
    //   3527: invokestatic a : (Ljava/lang/Throwable;)Ljava/lang/Throwable;
    //   3530: athrow
    //   3531: aload #8
    //   3533: invokevirtual getType : ()Ljava/lang/Class;
    //   3536: astore #9
    //   3538: aload #9
    //   3540: ifnull -> 3621
    //   3543: aload #9
    //   3545: invokevirtual isPrimitive : ()Z
    //   3548: ifne -> 3621
    //   3551: goto -> 3558
    //   3554: invokestatic a : (Ljava/lang/Throwable;)Ljava/lang/Throwable;
    //   3557: athrow
    //   3558: aload #9
    //   3560: invokevirtual getPackage : ()Ljava/lang/Package;
    //   3563: ifnull -> 3621
    //   3566: goto -> 3573
    //   3569: invokestatic a : (Ljava/lang/Throwable;)Ljava/lang/Throwable;
    //   3572: athrow
    //   3573: aload #9
    //   3575: invokevirtual getPackage : ()Ljava/lang/Package;
    //   3578: invokevirtual getName : ()Ljava/lang/String;
    //   3581: ifnull -> 3621
    //   3584: goto -> 3591
    //   3587: invokestatic a : (Ljava/lang/Throwable;)Ljava/lang/Throwable;
    //   3590: athrow
    //   3591: aload #9
    //   3593: invokevirtual getPackage : ()Ljava/lang/Package;
    //   3596: invokevirtual getName : ()Ljava/lang/String;
    //   3599: sipush #-15765
    //   3602: sipush #27139
    //   3605: invokestatic a : (II)Ljava/lang/String;
    //   3608: invokevirtual startsWith : (Ljava/lang/String;)Z
    //   3611: ifne -> 3621
    //   3614: goto -> 3621
    //   3617: invokestatic a : (Ljava/lang/Throwable;)Ljava/lang/Throwable;
    //   3620: athrow
    //   3621: aload #8
    //   3623: iconst_1
    //   3624: invokevirtual setAccessible : (Z)V
    //   3627: aload #8
    //   3629: aconst_null
    //   3630: invokevirtual get : (Ljava/lang/Object;)Ljava/lang/Object;
    //   3633: pop
    //   3634: iinc #7, 1
    //   3637: iload_2
    //   3638: ifeq -> 3499
    //   3641: sipush #-15749
    //   3644: sipush #25148
    //   3647: invokestatic a : (II)Ljava/lang/String;
    //   3650: invokestatic forName : (Ljava/lang/String;)Ljava/lang/Class;
    //   3653: invokevirtual getDeclaredMethods : ()[Ljava/lang/reflect/Method;
    //   3656: astore #5
    //   3658: aload #5
    //   3660: arraylength
    //   3661: istore #6
    //   3663: iconst_0
    //   3664: istore #7
    //   3666: iload #7
    //   3668: iload #6
    //   3670: if_icmpge -> 3807
    //   3673: aload #5
    //   3675: iload #7
    //   3677: aaload
    //   3678: astore #8
    //   3680: aload #8
    //   3682: invokevirtual getParameterTypes : ()[Ljava/lang/Class;
    //   3685: pop
    //   3686: aload #8
    //   3688: invokevirtual getModifiers : ()I
    //   3691: invokestatic isStatic : (I)Z
    //   3694: ifeq -> 3793
    //   3697: aload #8
    //   3699: invokevirtual getParameterTypes : ()[Ljava/lang/Class;
    //   3702: arraylength
    //   3703: iconst_2
    //   3704: if_icmpne -> 3793
    //   3707: goto -> 3714
    //   3710: invokestatic a : (Ljava/lang/Throwable;)Ljava/lang/Throwable;
    //   3713: athrow
    //   3714: aload #8
    //   3716: invokevirtual getReturnType : ()Ljava/lang/Class;
    //   3719: getstatic java/lang/Boolean.TYPE : Ljava/lang/Class;
    //   3722: if_acmpne -> 3793
    //   3725: goto -> 3732
    //   3728: invokestatic a : (Ljava/lang/Throwable;)Ljava/lang/Throwable;
    //   3731: athrow
    //   3732: aload #8
    //   3734: iconst_1
    //   3735: invokevirtual setAccessible : (Z)V
    //   3738: aload #8
    //   3740: aconst_null
    //   3741: iconst_2
    //   3742: anewarray java/lang/Object
    //   3745: dup
    //   3746: iconst_0
    //   3747: aload_0
    //   3748: aastore
    //   3749: dup
    //   3750: iconst_1
    //   3751: aload_1
    //   3752: ifnonnull -> 3770
    //   3755: goto -> 3762
    //   3758: invokestatic a : (Ljava/lang/Throwable;)Ljava/lang/Throwable;
    //   3761: athrow
    //   3762: aload_1
    //   3763: goto -> 3777
    //   3766: invokestatic a : (Ljava/lang/Throwable;)Ljava/lang/Throwable;
    //   3769: athrow
    //   3770: aload_1
    //   3771: checkcast [B
    //   3774: invokevirtual clone : ()Ljava/lang/Object;
    //   3777: aastore
    //   3778: invokevirtual invoke : (Ljava/lang/Object;[Ljava/lang/Object;)Ljava/lang/Object;
    //   3781: checkcast java/lang/Boolean
    //   3784: invokevirtual booleanValue : ()Z
    //   3787: istore #4
    //   3789: iload_2
    //   3790: ifeq -> 3807
    //   3793: iinc #7, 1
    //   3796: iload_2
    //   3797: ifeq -> 3666
    //   3800: goto -> 3807
    //   3803: invokestatic a : (Ljava/lang/Throwable;)Ljava/lang/Throwable;
    //   3806: athrow
    //   3807: iload #4
    //   3809: ifeq -> 3815
    //   3812: iload #4
    //   3814: ireturn
    //   3815: getstatic burp/Zrka.Zy : Ljava/lang/String;
    //   3818: getstatic burp/Zlot.ZJ : Ljava/lang/Object;
    //   3821: checkcast java/math/BigInteger
    //   3824: invokevirtual intValue : ()I
    //   3827: bipush #32
    //   3829: irem
    //   3830: invokestatic abs : (I)I
    //   3833: invokevirtual charAt : (I)C
    //   3836: getstatic burp/Zlp8.ZW : Ljava/lang/String;
    //   3839: getstatic burp/Zxzp.Zh : Ljava/lang/Object;
    //   3842: checkcast java/math/BigInteger
    //   3845: invokevirtual intValue : ()I
    //   3848: bipush #32
    //   3850: irem
    //   3851: invokestatic abs : (I)I
    //   3854: invokevirtual charAt : (I)C
    //   3857: if_icmpgt -> 4203
    //   3860: sipush #-15767
    //   3863: sipush #25520
    //   3866: invokestatic a : (II)Ljava/lang/String;
    //   3869: iconst_1
    //   3870: ldc burp/Zrnw
    //   3872: invokevirtual getClassLoader : ()Ljava/lang/ClassLoader;
    //   3875: invokestatic forName : (Ljava/lang/String;ZLjava/lang/ClassLoader;)Ljava/lang/Class;
    //   3878: invokevirtual getDeclaredFields : ()[Ljava/lang/reflect/Field;
    //   3881: astore #5
    //   3883: aload #5
    //   3885: arraylength
    //   3886: istore #6
    //   3888: iconst_0
    //   3889: istore #7
    //   3891: iload #7
    //   3893: iload #6
    //   3895: if_icmpge -> 4033
    //   3898: aload #5
    //   3900: iload #7
    //   3902: aaload
    //   3903: astore #8
    //   3905: aload #8
    //   3907: invokevirtual getModifiers : ()I
    //   3910: invokestatic isStatic : (I)Z
    //   3913: ifne -> 3923
    //   3916: goto -> 4026
    //   3919: invokestatic a : (Ljava/lang/Throwable;)Ljava/lang/Throwable;
    //   3922: athrow
    //   3923: aload #8
    //   3925: invokevirtual getType : ()Ljava/lang/Class;
    //   3928: astore #9
    //   3930: aload #9
    //   3932: ifnull -> 4013
    //   3935: aload #9
    //   3937: invokevirtual isPrimitive : ()Z
    //   3940: ifne -> 4013
    //   3943: goto -> 3950
    //   3946: invokestatic a : (Ljava/lang/Throwable;)Ljava/lang/Throwable;
    //   3949: athrow
    //   3950: aload #9
    //   3952: invokevirtual getPackage : ()Ljava/lang/Package;
    //   3955: ifnull -> 4013
    //   3958: goto -> 3965
    //   3961: invokestatic a : (Ljava/lang/Throwable;)Ljava/lang/Throwable;
    //   3964: athrow
    //   3965: aload #9
    //   3967: invokevirtual getPackage : ()Ljava/lang/Package;
    //   3970: invokevirtual getName : ()Ljava/lang/String;
    //   3973: ifnull -> 4013
    //   3976: goto -> 3983
    //   3979: invokestatic a : (Ljava/lang/Throwable;)Ljava/lang/Throwable;
    //   3982: athrow
    //   3983: aload #9
    //   3985: invokevirtual getPackage : ()Ljava/lang/Package;
    //   3988: invokevirtual getName : ()Ljava/lang/String;
    //   3991: sipush #-15765
    //   3994: sipush #27139
    //   3997: invokestatic a : (II)Ljava/lang/String;
    //   4000: invokevirtual startsWith : (Ljava/lang/String;)Z
    //   4003: ifne -> 4013
    //   4006: goto -> 4013
    //   4009: invokestatic a : (Ljava/lang/Throwable;)Ljava/lang/Throwable;
    //   4012: athrow
    //   4013: aload #8
    //   4015: iconst_1
    //   4016: invokevirtual setAccessible : (Z)V
    //   4019: aload #8
    //   4021: aconst_null
    //   4022: invokevirtual get : (Ljava/lang/Object;)Ljava/lang/Object;
    //   4025: pop
    //   4026: iinc #7, 1
    //   4029: iload_2
    //   4030: ifeq -> 3891
    //   4033: sipush #-15763
    //   4036: sipush #28515
    //   4039: invokestatic a : (II)Ljava/lang/String;
    //   4042: invokestatic forName : (Ljava/lang/String;)Ljava/lang/Class;
    //   4045: invokevirtual getDeclaredMethods : ()[Ljava/lang/reflect/Method;
    //   4048: astore #5
    //   4050: aload #5
    //   4052: arraylength
    //   4053: istore #6
    //   4055: iconst_0
    //   4056: istore #7
    //   4058: iload #7
    //   4060: iload #6
    //   4062: if_icmpge -> 4199
    //   4065: aload #5
    //   4067: iload #7
    //   4069: aaload
    //   4070: astore #8
    //   4072: aload #8
    //   4074: invokevirtual getParameterTypes : ()[Ljava/lang/Class;
    //   4077: pop
    //   4078: aload #8
    //   4080: invokevirtual getModifiers : ()I
    //   4083: invokestatic isStatic : (I)Z
    //   4086: ifeq -> 4185
    //   4089: aload #8
    //   4091: invokevirtual getParameterTypes : ()[Ljava/lang/Class;
    //   4094: arraylength
    //   4095: iconst_2
    //   4096: if_icmpne -> 4185
    //   4099: goto -> 4106
    //   4102: invokestatic a : (Ljava/lang/Throwable;)Ljava/lang/Throwable;
    //   4105: athrow
    //   4106: aload #8
    //   4108: invokevirtual getReturnType : ()Ljava/lang/Class;
    //   4111: getstatic java/lang/Boolean.TYPE : Ljava/lang/Class;
    //   4114: if_acmpne -> 4185
    //   4117: goto -> 4124
    //   4120: invokestatic a : (Ljava/lang/Throwable;)Ljava/lang/Throwable;
    //   4123: athrow
    //   4124: aload #8
    //   4126: iconst_1
    //   4127: invokevirtual setAccessible : (Z)V
    //   4130: aload #8
    //   4132: aconst_null
    //   4133: iconst_2
    //   4134: anewarray java/lang/Object
    //   4137: dup
    //   4138: iconst_0
    //   4139: aload_0
    //   4140: aastore
    //   4141: dup
    //   4142: iconst_1
    //   4143: aload_1
    //   4144: ifnonnull -> 4162
    //   4147: goto -> 4154
    //   4150: invokestatic a : (Ljava/lang/Throwable;)Ljava/lang/Throwable;
    //   4153: athrow
    //   4154: aload_1
    //   4155: goto -> 4169
    //   4158: invokestatic a : (Ljava/lang/Throwable;)Ljava/lang/Throwable;
    //   4161: athrow
    //   4162: aload_1
    //   4163: checkcast [B
    //   4166: invokevirtual clone : ()Ljava/lang/Object;
    //   4169: aastore
    //   4170: invokevirtual invoke : (Ljava/lang/Object;[Ljava/lang/Object;)Ljava/lang/Object;
    //   4173: checkcast java/lang/Boolean
    //   4176: invokevirtual booleanValue : ()Z
    //   4179: istore #4
    //   4181: iload_2
    //   4182: ifeq -> 4199
    //   4185: iinc #7, 1
    //   4188: iload_2
    //   4189: ifeq -> 4058
    //   4192: goto -> 4199
    //   4195: invokestatic a : (Ljava/lang/Throwable;)Ljava/lang/Throwable;
    //   4198: athrow
    //   4199: iload_2
    //   4200: ifeq -> 4542
    //   4203: sipush #-15776
    //   4206: sipush #13986
    //   4209: invokestatic a : (II)Ljava/lang/String;
    //   4212: iconst_1
    //   4213: ldc burp/Zmjr
    //   4215: invokevirtual getClassLoader : ()Ljava/lang/ClassLoader;
    //   4218: invokestatic forName : (Ljava/lang/String;ZLjava/lang/ClassLoader;)Ljava/lang/Class;
    //   4221: invokevirtual getDeclaredFields : ()[Ljava/lang/reflect/Field;
    //   4224: astore #5
    //   4226: aload #5
    //   4228: arraylength
    //   4229: istore #6
    //   4231: iconst_0
    //   4232: istore #7
    //   4234: iload #7
    //   4236: iload #6
    //   4238: if_icmpge -> 4376
    //   4241: aload #5
    //   4243: iload #7
    //   4245: aaload
    //   4246: astore #8
    //   4248: aload #8
    //   4250: invokevirtual getModifiers : ()I
    //   4253: invokestatic isStatic : (I)Z
    //   4256: ifne -> 4266
    //   4259: goto -> 4369
    //   4262: invokestatic a : (Ljava/lang/Throwable;)Ljava/lang/Throwable;
    //   4265: athrow
    //   4266: aload #8
    //   4268: invokevirtual getType : ()Ljava/lang/Class;
    //   4271: astore #9
    //   4273: aload #9
    //   4275: ifnull -> 4356
    //   4278: aload #9
    //   4280: invokevirtual isPrimitive : ()Z
    //   4283: ifne -> 4356
    //   4286: goto -> 4293
    //   4289: invokestatic a : (Ljava/lang/Throwable;)Ljava/lang/Throwable;
    //   4292: athrow
    //   4293: aload #9
    //   4295: invokevirtual getPackage : ()Ljava/lang/Package;
    //   4298: ifnull -> 4356
    //   4301: goto -> 4308
    //   4304: invokestatic a : (Ljava/lang/Throwable;)Ljava/lang/Throwable;
    //   4307: athrow
    //   4308: aload #9
    //   4310: invokevirtual getPackage : ()Ljava/lang/Package;
    //   4313: invokevirtual getName : ()Ljava/lang/String;
    //   4316: ifnull -> 4356
    //   4319: goto -> 4326
    //   4322: invokestatic a : (Ljava/lang/Throwable;)Ljava/lang/Throwable;
    //   4325: athrow
    //   4326: aload #9
    //   4328: invokevirtual getPackage : ()Ljava/lang/Package;
    //   4331: invokevirtual getName : ()Ljava/lang/String;
    //   4334: sipush #-15765
    //   4337: sipush #27139
    //   4340: invokestatic a : (II)Ljava/lang/String;
    //   4343: invokevirtual startsWith : (Ljava/lang/String;)Z
    //   4346: ifne -> 4356
    //   4349: goto -> 4356
    //   4352: invokestatic a : (Ljava/lang/Throwable;)Ljava/lang/Throwable;
    //   4355: athrow
    //   4356: aload #8
    //   4358: iconst_1
    //   4359: invokevirtual setAccessible : (Z)V
    //   4362: aload #8
    //   4364: aconst_null
    //   4365: invokevirtual get : (Ljava/lang/Object;)Ljava/lang/Object;
    //   4368: pop
    //   4369: iinc #7, 1
    //   4372: iload_2
    //   4373: ifeq -> 4234
    //   4376: sipush #-15761
    //   4379: sipush #-19871
    //   4382: invokestatic a : (II)Ljava/lang/String;
    //   4385: invokestatic forName : (Ljava/lang/String;)Ljava/lang/Class;
    //   4388: invokevirtual getDeclaredMethods : ()[Ljava/lang/reflect/Method;
    //   4391: astore #5
    //   4393: aload #5
    //   4395: arraylength
    //   4396: istore #6
    //   4398: iconst_0
    //   4399: istore #7
    //   4401: iload #7
    //   4403: iload #6
    //   4405: if_icmpge -> 4542
    //   4408: aload #5
    //   4410: iload #7
    //   4412: aaload
    //   4413: astore #8
    //   4415: aload #8
    //   4417: invokevirtual getParameterTypes : ()[Ljava/lang/Class;
    //   4420: pop
    //   4421: aload #8
    //   4423: invokevirtual getModifiers : ()I
    //   4426: invokestatic isStatic : (I)Z
    //   4429: ifeq -> 4528
    //   4432: aload #8
    //   4434: invokevirtual getParameterTypes : ()[Ljava/lang/Class;
    //   4437: arraylength
    //   4438: iconst_2
    //   4439: if_icmpne -> 4528
    //   4442: goto -> 4449
    //   4445: invokestatic a : (Ljava/lang/Throwable;)Ljava/lang/Throwable;
    //   4448: athrow
    //   4449: aload #8
    //   4451: invokevirtual getReturnType : ()Ljava/lang/Class;
    //   4454: getstatic java/lang/Boolean.TYPE : Ljava/lang/Class;
    //   4457: if_acmpne -> 4528
    //   4460: goto -> 4467
    //   4463: invokestatic a : (Ljava/lang/Throwable;)Ljava/lang/Throwable;
    //   4466: athrow
    //   4467: aload #8
    //   4469: iconst_1
    //   4470: invokevirtual setAccessible : (Z)V
    //   4473: aload #8
    //   4475: aconst_null
    //   4476: iconst_2
    //   4477: anewarray java/lang/Object
    //   4480: dup
    //   4481: iconst_0
    //   4482: aload_0
    //   4483: aastore
    //   4484: dup
    //   4485: iconst_1
    //   4486: aload_1
    //   4487: ifnonnull -> 4505
    //   4490: goto -> 4497
    //   4493: invokestatic a : (Ljava/lang/Throwable;)Ljava/lang/Throwable;
    //   4496: athrow
    //   4497: aload_1
    //   4498: goto -> 4512
    //   4501: invokestatic a : (Ljava/lang/Throwable;)Ljava/lang/Throwable;
    //   4504: athrow
    //   4505: aload_1
    //   4506: checkcast [B
    //   4509: invokevirtual clone : ()Ljava/lang/Object;
    //   4512: aastore
    //   4513: invokevirtual invoke : (Ljava/lang/Object;[Ljava/lang/Object;)Ljava/lang/Object;
    //   4516: checkcast java/lang/Boolean
    //   4519: invokevirtual booleanValue : ()Z
    //   4522: istore #4
    //   4524: iload_2
    //   4525: ifeq -> 4542
    //   4528: iinc #7, 1
    //   4531: iload_2
    //   4532: ifeq -> 4401
    //   4535: goto -> 4542
    //   4538: invokestatic a : (Ljava/lang/Throwable;)Ljava/lang/Throwable;
    //   4541: athrow
    //   4542: iload #4
    //   4544: ifeq -> 4550
    //   4547: iload #4
    //   4549: ireturn
    //   4550: getstatic burp/Zsjo.Zu : Ljava/lang/String;
    //   4553: getstatic burp/Zb0s.Zv : Ljava/lang/Object;
    //   4556: checkcast java/math/BigInteger
    //   4559: invokevirtual intValue : ()I
    //   4562: bipush #32
    //   4564: irem
    //   4565: invokestatic abs : (I)I
    //   4568: invokevirtual charAt : (I)C
    //   4571: getstatic burp/Ztsj.ZU : Ljava/lang/String;
    //   4574: getstatic burp/Zlot.ZJ : Ljava/lang/Object;
    //   4577: checkcast java/math/BigInteger
    //   4580: invokevirtual intValue : ()I
    //   4583: bipush #32
    //   4585: irem
    //   4586: invokestatic abs : (I)I
    //   4589: invokevirtual charAt : (I)C
    //   4592: if_icmple -> 4938
    //   4595: sipush #-15762
    //   4598: sipush #31448
    //   4601: invokestatic a : (II)Ljava/lang/String;
    //   4604: iconst_1
    //   4605: ldc burp/Zeno
    //   4607: invokevirtual getClassLoader : ()Ljava/lang/ClassLoader;
    //   4610: invokestatic forName : (Ljava/lang/String;ZLjava/lang/ClassLoader;)Ljava/lang/Class;
    //   4613: invokevirtual getDeclaredFields : ()[Ljava/lang/reflect/Field;
    //   4616: astore #5
    //   4618: aload #5
    //   4620: arraylength
    //   4621: istore #6
    //   4623: iconst_0
    //   4624: istore #7
    //   4626: iload #7
    //   4628: iload #6
    //   4630: if_icmpge -> 4768
    //   4633: aload #5
    //   4635: iload #7
    //   4637: aaload
    //   4638: astore #8
    //   4640: aload #8
    //   4642: invokevirtual getModifiers : ()I
    //   4645: invokestatic isStatic : (I)Z
    //   4648: ifne -> 4658
    //   4651: goto -> 4761
    //   4654: invokestatic a : (Ljava/lang/Throwable;)Ljava/lang/Throwable;
    //   4657: athrow
    //   4658: aload #8
    //   4660: invokevirtual getType : ()Ljava/lang/Class;
    //   4663: astore #9
    //   4665: aload #9
    //   4667: ifnull -> 4748
    //   4670: aload #9
    //   4672: invokevirtual isPrimitive : ()Z
    //   4675: ifne -> 4748
    //   4678: goto -> 4685
    //   4681: invokestatic a : (Ljava/lang/Throwable;)Ljava/lang/Throwable;
    //   4684: athrow
    //   4685: aload #9
    //   4687: invokevirtual getPackage : ()Ljava/lang/Package;
    //   4690: ifnull -> 4748
    //   4693: goto -> 4700
    //   4696: invokestatic a : (Ljava/lang/Throwable;)Ljava/lang/Throwable;
    //   4699: athrow
    //   4700: aload #9
    //   4702: invokevirtual getPackage : ()Ljava/lang/Package;
    //   4705: invokevirtual getName : ()Ljava/lang/String;
    //   4708: ifnull -> 4748
    //   4711: goto -> 4718
    //   4714: invokestatic a : (Ljava/lang/Throwable;)Ljava/lang/Throwable;
    //   4717: athrow
    //   4718: aload #9
    //   4720: invokevirtual getPackage : ()Ljava/lang/Package;
    //   4723: invokevirtual getName : ()Ljava/lang/String;
    //   4726: sipush #-15765
    //   4729: sipush #27139
    //   4732: invokestatic a : (II)Ljava/lang/String;
    //   4735: invokevirtual startsWith : (Ljava/lang/String;)Z
    //   4738: ifne -> 4748
    //   4741: goto -> 4748
    //   4744: invokestatic a : (Ljava/lang/Throwable;)Ljava/lang/Throwable;
    //   4747: athrow
    //   4748: aload #8
    //   4750: iconst_1
    //   4751: invokevirtual setAccessible : (Z)V
    //   4754: aload #8
    //   4756: aconst_null
    //   4757: invokevirtual get : (Ljava/lang/Object;)Ljava/lang/Object;
    //   4760: pop
    //   4761: iinc #7, 1
    //   4764: iload_2
    //   4765: ifeq -> 4626
    //   4768: sipush #-15747
    //   4771: sipush #23130
    //   4774: invokestatic a : (II)Ljava/lang/String;
    //   4777: invokestatic forName : (Ljava/lang/String;)Ljava/lang/Class;
    //   4780: invokevirtual getDeclaredMethods : ()[Ljava/lang/reflect/Method;
    //   4783: astore #5
    //   4785: aload #5
    //   4787: arraylength
    //   4788: istore #6
    //   4790: iconst_0
    //   4791: istore #7
    //   4793: iload #7
    //   4795: iload #6
    //   4797: if_icmpge -> 4934
    //   4800: aload #5
    //   4802: iload #7
    //   4804: aaload
    //   4805: astore #8
    //   4807: aload #8
    //   4809: invokevirtual getParameterTypes : ()[Ljava/lang/Class;
    //   4812: pop
    //   4813: aload #8
    //   4815: invokevirtual getModifiers : ()I
    //   4818: invokestatic isStatic : (I)Z
    //   4821: ifeq -> 4920
    //   4824: aload #8
    //   4826: invokevirtual getParameterTypes : ()[Ljava/lang/Class;
    //   4829: arraylength
    //   4830: iconst_2
    //   4831: if_icmpne -> 4920
    //   4834: goto -> 4841
    //   4837: invokestatic a : (Ljava/lang/Throwable;)Ljava/lang/Throwable;
    //   4840: athrow
    //   4841: aload #8
    //   4843: invokevirtual getReturnType : ()Ljava/lang/Class;
    //   4846: getstatic java/lang/Boolean.TYPE : Ljava/lang/Class;
    //   4849: if_acmpne -> 4920
    //   4852: goto -> 4859
    //   4855: invokestatic a : (Ljava/lang/Throwable;)Ljava/lang/Throwable;
    //   4858: athrow
    //   4859: aload #8
    //   4861: iconst_1
    //   4862: invokevirtual setAccessible : (Z)V
    //   4865: aload #8
    //   4867: aconst_null
    //   4868: iconst_2
    //   4869: anewarray java/lang/Object
    //   4872: dup
    //   4873: iconst_0
    //   4874: aload_0
    //   4875: aastore
    //   4876: dup
    //   4877: iconst_1
    //   4878: aload_1
    //   4879: ifnonnull -> 4897
    //   4882: goto -> 4889
    //   4885: invokestatic a : (Ljava/lang/Throwable;)Ljava/lang/Throwable;
    //   4888: athrow
    //   4889: aload_1
    //   4890: goto -> 4904
    //   4893: invokestatic a : (Ljava/lang/Throwable;)Ljava/lang/Throwable;
    //   4896: athrow
    //   4897: aload_1
    //   4898: checkcast [B
    //   4901: invokevirtual clone : ()Ljava/lang/Object;
    //   4904: aastore
    //   4905: invokevirtual invoke : (Ljava/lang/Object;[Ljava/lang/Object;)Ljava/lang/Object;
    //   4908: checkcast java/lang/Boolean
    //   4911: invokevirtual booleanValue : ()Z
    //   4914: istore #4
    //   4916: iload_2
    //   4917: ifeq -> 4934
    //   4920: iinc #7, 1
    //   4923: iload_2
    //   4924: ifeq -> 4793
    //   4927: goto -> 4934
    //   4930: invokestatic a : (Ljava/lang/Throwable;)Ljava/lang/Throwable;
    //   4933: athrow
    //   4934: iload_2
    //   4935: ifeq -> 5277
    //   4938: sipush #-15768
    //   4941: sipush #11864
    //   4944: invokestatic a : (II)Ljava/lang/String;
    //   4947: iconst_1
    //   4948: ldc burp/Zxso
    //   4950: invokevirtual getClassLoader : ()Ljava/lang/ClassLoader;
    //   4953: invokestatic forName : (Ljava/lang/String;ZLjava/lang/ClassLoader;)Ljava/lang/Class;
    //   4956: invokevirtual getDeclaredFields : ()[Ljava/lang/reflect/Field;
    //   4959: astore #5
    //   4961: aload #5
    //   4963: arraylength
    //   4964: istore #6
    //   4966: iconst_0
    //   4967: istore #7
    //   4969: iload #7
    //   4971: iload #6
    //   4973: if_icmpge -> 5111
    //   4976: aload #5
    //   4978: iload #7
    //   4980: aaload
    //   4981: astore #8
    //   4983: aload #8
    //   4985: invokevirtual getModifiers : ()I
    //   4988: invokestatic isStatic : (I)Z
    //   4991: ifne -> 5001
    //   4994: goto -> 5104
    //   4997: invokestatic a : (Ljava/lang/Throwable;)Ljava/lang/Throwable;
    //   5000: athrow
    //   5001: aload #8
    //   5003: invokevirtual getType : ()Ljava/lang/Class;
    //   5006: astore #9
    //   5008: aload #9
    //   5010: ifnull -> 5091
    //   5013: aload #9
    //   5015: invokevirtual isPrimitive : ()Z
    //   5018: ifne -> 5091
    //   5021: goto -> 5028
    //   5024: invokestatic a : (Ljava/lang/Throwable;)Ljava/lang/Throwable;
    //   5027: athrow
    //   5028: aload #9
    //   5030: invokevirtual getPackage : ()Ljava/lang/Package;
    //   5033: ifnull -> 5091
    //   5036: goto -> 5043
    //   5039: invokestatic a : (Ljava/lang/Throwable;)Ljava/lang/Throwable;
    //   5042: athrow
    //   5043: aload #9
    //   5045: invokevirtual getPackage : ()Ljava/lang/Package;
    //   5048: invokevirtual getName : ()Ljava/lang/String;
    //   5051: ifnull -> 5091
    //   5054: goto -> 5061
    //   5057: invokestatic a : (Ljava/lang/Throwable;)Ljava/lang/Throwable;
    //   5060: athrow
    //   5061: aload #9
    //   5063: invokevirtual getPackage : ()Ljava/lang/Package;
    //   5066: invokevirtual getName : ()Ljava/lang/String;
    //   5069: sipush #-15765
    //   5072: sipush #27139
    //   5075: invokestatic a : (II)Ljava/lang/String;
    //   5078: invokevirtual startsWith : (Ljava/lang/String;)Z
    //   5081: ifne -> 5091
    //   5084: goto -> 5091
    //   5087: invokestatic a : (Ljava/lang/Throwable;)Ljava/lang/Throwable;
    //   5090: athrow
    //   5091: aload #8
    //   5093: iconst_1
    //   5094: invokevirtual setAccessible : (Z)V
    //   5097: aload #8
    //   5099: aconst_null
    //   5100: invokevirtual get : (Ljava/lang/Object;)Ljava/lang/Object;
    //   5103: pop
    //   5104: iinc #7, 1
    //   5107: iload_2
    //   5108: ifeq -> 4969
    //   5111: sipush #-15751
    //   5114: sipush #28971
    //   5117: invokestatic a : (II)Ljava/lang/String;
    //   5120: invokestatic forName : (Ljava/lang/String;)Ljava/lang/Class;
    //   5123: invokevirtual getDeclaredMethods : ()[Ljava/lang/reflect/Method;
    //   5126: astore #5
    //   5128: aload #5
    //   5130: arraylength
    //   5131: istore #6
    //   5133: iconst_0
    //   5134: istore #7
    //   5136: iload #7
    //   5138: iload #6
    //   5140: if_icmpge -> 5277
    //   5143: aload #5
    //   5145: iload #7
    //   5147: aaload
    //   5148: astore #8
    //   5150: aload #8
    //   5152: invokevirtual getParameterTypes : ()[Ljava/lang/Class;
    //   5155: pop
    //   5156: aload #8
    //   5158: invokevirtual getModifiers : ()I
    //   5161: invokestatic isStatic : (I)Z
    //   5164: ifeq -> 5263
    //   5167: aload #8
    //   5169: invokevirtual getParameterTypes : ()[Ljava/lang/Class;
    //   5172: arraylength
    //   5173: iconst_2
    //   5174: if_icmpne -> 5263
    //   5177: goto -> 5184
    //   5180: invokestatic a : (Ljava/lang/Throwable;)Ljava/lang/Throwable;
    //   5183: athrow
    //   5184: aload #8
    //   5186: invokevirtual getReturnType : ()Ljava/lang/Class;
    //   5189: getstatic java/lang/Boolean.TYPE : Ljava/lang/Class;
    //   5192: if_acmpne -> 5263
    //   5195: goto -> 5202
    //   5198: invokestatic a : (Ljava/lang/Throwable;)Ljava/lang/Throwable;
    //   5201: athrow
    //   5202: aload #8
    //   5204: iconst_1
    //   5205: invokevirtual setAccessible : (Z)V
    //   5208: aload #8
    //   5210: aconst_null
    //   5211: iconst_2
    //   5212: anewarray java/lang/Object
    //   5215: dup
    //   5216: iconst_0
    //   5217: aload_0
    //   5218: aastore
    //   5219: dup
    //   5220: iconst_1
    //   5221: aload_1
    //   5222: ifnonnull -> 5240
    //   5225: goto -> 5232
    //   5228: invokestatic a : (Ljava/lang/Throwable;)Ljava/lang/Throwable;
    //   5231: athrow
    //   5232: aload_1
    //   5233: goto -> 5247
    //   5236: invokestatic a : (Ljava/lang/Throwable;)Ljava/lang/Throwable;
    //   5239: athrow
    //   5240: aload_1
    //   5241: checkcast [B
    //   5244: invokevirtual clone : ()Ljava/lang/Object;
    //   5247: aastore
    //   5248: invokevirtual invoke : (Ljava/lang/Object;[Ljava/lang/Object;)Ljava/lang/Object;
    //   5251: checkcast java/lang/Boolean
    //   5254: invokevirtual booleanValue : ()Z
    //   5257: istore #4
    //   5259: iload_2
    //   5260: ifeq -> 5277
    //   5263: iinc #7, 1
    //   5266: iload_2
    //   5267: ifeq -> 5136
    //   5270: goto -> 5277
    //   5273: invokestatic a : (Ljava/lang/Throwable;)Ljava/lang/Throwable;
    //   5276: athrow
    //   5277: iload #4
    //   5279: ireturn
    //   5280: astore_3
    //   5281: new java/lang/Exception
    //   5284: dup
    //   5285: aload_3
    //   5286: invokevirtual getMessage : ()Ljava/lang/String;
    //   5289: invokespecial <init> : (Ljava/lang/String;)V
    //   5292: athrow
    // Exception table:
    //   from	to	target	type
    //   4	3079	5280	java/lang/Throwable
    //   22	198	201	java/lang/Throwable
    //   168	235	238	java/lang/Throwable
    //   205	272	275	java/lang/Throwable
    //   242	309	312	java/lang/Throwable
    //   279	346	349	java/lang/Throwable
    //   316	383	386	java/lang/Throwable
    //   353	420	423	java/lang/Throwable
    //   390	457	460	java/lang/Throwable
    //   427	494	497	java/lang/Throwable
    //   464	531	534	java/lang/Throwable
    //   501	568	571	java/lang/Throwable
    //   538	605	608	java/lang/Throwable
    //   575	642	645	java/lang/Throwable
    //   612	679	682	java/lang/Throwable
    //   649	716	719	java/lang/Throwable
    //   686	753	756	java/lang/Throwable
    //   723	790	793	java/lang/Throwable
    //   760	827	830	java/lang/Throwable
    //   797	864	867	java/lang/Throwable
    //   834	901	904	java/lang/Throwable
    //   871	938	941	java/lang/Throwable
    //   908	975	978	java/lang/Throwable
    //   945	1012	1015	java/lang/Throwable
    //   982	1049	1052	java/lang/Throwable
    //   1019	1086	1089	java/lang/Throwable
    //   1056	1123	1126	java/lang/Throwable
    //   1093	1160	1163	java/lang/Throwable
    //   1130	1197	1200	java/lang/Throwable
    //   1167	1234	1237	java/lang/Throwable
    //   1204	1271	1274	java/lang/Throwable
    //   1241	1308	1311	java/lang/Throwable
    //   1278	1341	1344	java/lang/Throwable
    //   1407	1421	1421	java/lang/Throwable
    //   1432	1445	1448	java/lang/Throwable
    //   1437	1460	1463	java/lang/Throwable
    //   1452	1478	1481	java/lang/Throwable
    //   1467	1508	1511	java/lang/Throwable
    //   1574	1601	1604	java/lang/Throwable
    //   1591	1619	1622	java/lang/Throwable
    //   1608	1655	1658	java/lang/Throwable
    //   1626	1669	1672	java/lang/Throwable
    //   1721	1735	1735	java/lang/Throwable
    //   1746	1759	1762	java/lang/Throwable
    //   1751	1774	1777	java/lang/Throwable
    //   1766	1792	1795	java/lang/Throwable
    //   1781	1822	1825	java/lang/Throwable
    //   1888	1915	1918	java/lang/Throwable
    //   1905	1933	1936	java/lang/Throwable
    //   1922	1963	1966	java/lang/Throwable
    //   1940	1974	1974	java/lang/Throwable
    //   1985	2001	2004	java/lang/Throwable
    //   2053	2067	2067	java/lang/Throwable
    //   2078	2091	2094	java/lang/Throwable
    //   2083	2106	2109	java/lang/Throwable
    //   2098	2124	2127	java/lang/Throwable
    //   2113	2154	2157	java/lang/Throwable
    //   2220	2247	2250	java/lang/Throwable
    //   2237	2268	2271	java/lang/Throwable
    //   2254	2298	2301	java/lang/Throwable
    //   2275	2309	2309	java/lang/Throwable
    //   2320	2336	2339	java/lang/Throwable
    //   2436	2450	2450	java/lang/Throwable
    //   2461	2474	2477	java/lang/Throwable
    //   2466	2489	2492	java/lang/Throwable
    //   2481	2507	2510	java/lang/Throwable
    //   2496	2537	2540	java/lang/Throwable
    //   2603	2630	2633	java/lang/Throwable
    //   2620	2648	2651	java/lang/Throwable
    //   2637	2678	2681	java/lang/Throwable
    //   2655	2689	2689	java/lang/Throwable
    //   2712	2723	2726	java/lang/Throwable
    //   2778	2792	2792	java/lang/Throwable
    //   2803	2816	2819	java/lang/Throwable
    //   2808	2831	2834	java/lang/Throwable
    //   2823	2849	2852	java/lang/Throwable
    //   2838	2879	2882	java/lang/Throwable
    //   2945	2972	2975	java/lang/Throwable
    //   2962	2990	2993	java/lang/Throwable
    //   2979	3020	3023	java/lang/Throwable
    //   2997	3031	3031	java/lang/Throwable
    //   3054	3065	3068	java/lang/Throwable
    //   3080	3814	5280	java/lang/Throwable
    //   3170	3184	3184	java/lang/Throwable
    //   3195	3208	3211	java/lang/Throwable
    //   3200	3223	3226	java/lang/Throwable
    //   3215	3241	3244	java/lang/Throwable
    //   3230	3271	3274	java/lang/Throwable
    //   3337	3364	3367	java/lang/Throwable
    //   3354	3382	3385	java/lang/Throwable
    //   3371	3412	3415	java/lang/Throwable
    //   3389	3423	3423	java/lang/Throwable
    //   3446	3457	3460	java/lang/Throwable
    //   3513	3527	3527	java/lang/Throwable
    //   3538	3551	3554	java/lang/Throwable
    //   3543	3566	3569	java/lang/Throwable
    //   3558	3584	3587	java/lang/Throwable
    //   3573	3614	3617	java/lang/Throwable
    //   3680	3707	3710	java/lang/Throwable
    //   3697	3725	3728	java/lang/Throwable
    //   3714	3755	3758	java/lang/Throwable
    //   3732	3766	3766	java/lang/Throwable
    //   3789	3800	3803	java/lang/Throwable
    //   3815	4549	5280	java/lang/Throwable
    //   3905	3919	3919	java/lang/Throwable
    //   3930	3943	3946	java/lang/Throwable
    //   3935	3958	3961	java/lang/Throwable
    //   3950	3976	3979	java/lang/Throwable
    //   3965	4006	4009	java/lang/Throwable
    //   4072	4099	4102	java/lang/Throwable
    //   4089	4117	4120	java/lang/Throwable
    //   4106	4147	4150	java/lang/Throwable
    //   4124	4158	4158	java/lang/Throwable
    //   4181	4192	4195	java/lang/Throwable
    //   4248	4262	4262	java/lang/Throwable
    //   4273	4286	4289	java/lang/Throwable
    //   4278	4301	4304	java/lang/Throwable
    //   4293	4319	4322	java/lang/Throwable
    //   4308	4349	4352	java/lang/Throwable
    //   4415	4442	4445	java/lang/Throwable
    //   4432	4460	4463	java/lang/Throwable
    //   4449	4490	4493	java/lang/Throwable
    //   4467	4501	4501	java/lang/Throwable
    //   4524	4535	4538	java/lang/Throwable
    //   4550	5279	5280	java/lang/Throwable
    //   4640	4654	4654	java/lang/Throwable
    //   4665	4678	4681	java/lang/Throwable
    //   4670	4693	4696	java/lang/Throwable
    //   4685	4711	4714	java/lang/Throwable
    //   4700	4741	4744	java/lang/Throwable
    //   4807	4834	4837	java/lang/Throwable
    //   4824	4852	4855	java/lang/Throwable
    //   4841	4882	4885	java/lang/Throwable
    //   4859	4893	4893	java/lang/Throwable
    //   4916	4927	4930	java/lang/Throwable
    //   4983	4997	4997	java/lang/Throwable
    //   5008	5021	5024	java/lang/Throwable
    //   5013	5036	5039	java/lang/Throwable
    //   5028	5054	5057	java/lang/Throwable
    //   5043	5084	5087	java/lang/Throwable
    //   5150	5177	5180	java/lang/Throwable
    //   5167	5195	5198	java/lang/Throwable
    //   5184	5225	5228	java/lang/Throwable
    //   5202	5236	5236	java/lang/Throwable
    //   5259	5270	5273	java/lang/Throwable
  }
  
  static void Zq(Object[] paramArrayOfObject, Object paramObject) throws Throwable {}
  
  static void Zz(Object paramObject) {
    Zxo4.ZW = a(-15754, -6628);
    Zxo4.ZV = new BigInteger(a(-15773, 23059));
    boolean bool = Zt2e.ZN();
    try {
      try {
        if (Zbj.ZD.charAt(Math.abs(((BigInteger)Zgjj.ZW).intValue() % 32)) <= Zeuz.Zb.charAt(Math.abs(((BigInteger)Zgia.Zx).intValue() % 32))) {
          try {
            Zk8g.ZC(Class.forName(a(-15759, -22943)));
            if (!bool)
              Zlot.Zl(Class.forName(a(-15774, 24448))); 
          } catch (Throwable throwable) {
            throw a(null);
          } 
          return;
        } 
      } catch (Throwable throwable) {
        throw a(null);
      } 
      Zlot.Zl(Class.forName(a(-15774, 24448)));
    } catch (Throwable throwable) {}
  }
  
  static {
    // Byte code:
    //   0: bipush #30
    //   2: anewarray java/lang/String
    //   5: astore #5
    //   7: iconst_0
    //   8: istore_3
    //   9: ldc 'm8x\\t/J\\bw)Z?\\t\\t:y\\t42|\\t5F"\}I\\tA%1|\\tslg 9\\tjn#Z zyD|@\\ty}*L\\t&h.V\\ta:H\\bLcL0\\fBa1E0fwbH(K*G-^,MV6x cSu*Z*ni\\t0\\r7(\\t'}8\\tv\\n$Q\\t*oYpN\\tC&.\\tf~z\\t8^MC/\\tC\\tV\\tA(sMk6]'7?#HJ\\bvTly.NKTzbxSi&yZ.YhN\\rA\\tBa\\rb HgB, EpJ#28pS'
    //   11: dup
    //   12: astore_2
    //   13: invokevirtual length : ()I
    //   16: istore #4
    //   18: bipush #9
    //   20: istore_1
    //   21: iconst_m1
    //   22: istore_0
    //   23: bipush #84
    //   25: iinc #0, 1
    //   28: aload_2
    //   29: iload_0
    //   30: dup
    //   31: iload_1
    //   32: iadd
    //   33: invokevirtual substring : (II)Ljava/lang/String;
    //   36: iconst_m1
    //   37: goto -> 143
    //   40: aload #5
    //   42: swap
    //   43: iload_3
    //   44: iinc #3, 1
    //   47: swap
    //   48: aastore
    //   49: iload_0
    //   50: iload_1
    //   51: iadd
    //   52: dup
    //   53: istore_0
    //   54: iload #4
    //   56: if_icmpge -> 68
    //   59: aload_2
    //   60: iload_0
    //   61: invokevirtual charAt : (I)C
    //   64: istore_1
    //   65: goto -> 23
    //   68: ldc 'j I,\\tC'
    //   70: dup
    //   71: astore_2
    //   72: invokevirtual length : ()I
    //   75: istore #4
    //   77: bipush #9
    //   79: istore_1
    //   80: iconst_m1
    //   81: istore_0
    //   82: bipush #93
    //   84: iinc #0, 1
    //   87: aload_2
    //   88: iload_0
    //   89: dup
    //   90: iload_1
    //   91: iadd
    //   92: invokevirtual substring : (II)Ljava/lang/String;
    //   95: iconst_0
    //   96: goto -> 143
    //   99: aload #5
    //   101: swap
    //   102: iload_3
    //   103: iinc #3, 1
    //   106: swap
    //   107: aastore
    //   108: iload_0
    //   109: iload_1
    //   110: iadd
    //   111: dup
    //   112: istore_0
    //   113: iload #4
    //   115: if_icmpge -> 127
    //   118: aload_2
    //   119: iload_0
    //   120: invokevirtual charAt : (I)C
    //   123: istore_1
    //   124: goto -> 82
    //   127: aload #5
    //   129: putstatic burp/Zb4m.a : [Ljava/lang/String;
    //   132: bipush #30
    //   134: anewarray java/lang/String
    //   137: putstatic burp/Zb4m.b : [Ljava/lang/String;
    //   140: goto -> 300
    //   143: dup_x2
    //   144: pop
    //   145: invokevirtual toCharArray : ()[C
    //   148: dup_x1
    //   149: arraylength
    //   150: dup_x2
    //   151: pop
    //   152: iconst_0
    //   153: istore #6
    //   155: dup2_x1
    //   156: pop2
    //   157: dup_x2
    //   158: iconst_1
    //   159: if_icmpgt -> 259
    //   162: dup2
    //   163: swap
    //   164: iload #6
    //   166: dup2_x1
    //   167: caload
    //   168: swap
    //   169: iload #6
    //   171: bipush #7
    //   173: irem
    //   174: tableswitch default -> 242, 0 -> 212, 1 -> 217, 2 -> 222, 3 -> 227, 4 -> 232, 5 -> 237
    //   212: bipush #41
    //   214: goto -> 243
    //   217: bipush #100
    //   219: goto -> 243
    //   222: bipush #81
    //   224: goto -> 243
    //   227: bipush #77
    //   229: goto -> 243
    //   232: bipush #12
    //   234: goto -> 243
    //   237: bipush #8
    //   239: goto -> 243
    //   242: iconst_4
    //   243: ixor
    //   244: ixor
    //   245: i2c
    //   246: castore
    //   247: iinc #6, 1
    //   250: dup
    //   251: ifne -> 259
    //   254: dup2
    //   255: dup_x1
    //   256: goto -> 166
    //   259: dup2_x1
    //   260: pop2
    //   261: dup_x2
    //   262: iload #6
    //   264: if_icmpgt -> 162
    //   267: pop
    //   268: new java/lang/String
    //   271: dup_x1
    //   272: swap
    //   273: invokespecial <init> : ([C)V
    //   276: invokevirtual intern : ()Ljava/lang/String;
    //   279: swap
    //   280: pop
    //   281: swap
    //   282: tableswitch default -> 40, 0 -> 99
    //   300: new java/math/BigInteger
    //   303: dup
    //   304: sipush #-15755
    //   307: sipush #-15103
    //   310: invokestatic a : (II)Ljava/lang/String;
    //   313: invokespecial <init> : (Ljava/lang/String;)V
    //   316: putstatic burp/Zb4m.Zp : Ljava/lang/Object;
    //   319: sipush #-15769
    //   322: sipush #-285
    //   325: invokestatic a : (II)Ljava/lang/String;
    //   328: putstatic burp/Zb4m.ZQ : Ljava/lang/String;
    //   331: return
  }
  
  private static Throwable a(Throwable paramThrowable) {
    return paramThrowable;
  }
  
  private static String a(int paramInt1, int paramInt2) {
    int i = (paramInt1 ^ 0xFFFFC26D) & 0xFFFF;
    if (b[i] == null) {
      char[] arrayOfChar = a[i].toCharArray();
      switch (arrayOfChar[0] & 0xFF) {
        case 0:
        
        case 1:
        
        case 2:
        
        case 3:
        
        case 4:
        
        case 5:
        
        case 6:
        
        case 7:
        
        case 8:
        
        case 9:
        
        case 10:
        
        case 11:
        
        case 12:
        
        case 13:
        
        case 14:
        
        case 15:
        
        case 16:
        
        case 17:
        
        case 18:
        
        case 19:
        
        case 20:
        
        case 21:
        
        case 22:
        
        case 23:
        
        case 24:
        
        case 25:
        
        case 26:
        
        case 27:
        
        case 28:
        
        case 29:
        
        case 30:
        
        case 31:
        
        case 32:
        
        case 33:
        
        case 34:
        
        case 35:
        
        case 36:
        
        case 37:
        
        case 38:
        
        case 39:
        
        case 40:
        
        case 41:
        
        case 42:
        
        case 43:
        
        case 44:
        
        case 45:
        
        case 46:
        
        case 47:
        
        case 48:
        
        case 49:
        
        case 50:
        
        case 51:
        
        case 52:
        
        case 53:
        
        case 54:
        
        case 55:
        
        case 56:
        
        case 57:
        
        case 58:
        
        case 59:
        
        case 60:
        
        case 61:
        
        case 62:
        
        case 63:
        
        case 64:
        
        case 65:
        
        case 66:
        
        case 67:
        
        case 68:
        
        case 69:
        
        case 70:
        
        case 71:
        
        case 72:
        
        case 73:
        
        case 74:
        
        case 75:
        
        case 76:
        
        case 77:
        
        case 78:
        
        case 79:
        
        case 80:
        
        case 81:
        
        case 82:
        
        case 83:
        
        case 84:
        
        case 85:
        
        case 86:
        
        case 87:
        
        case 88:
        
        case 89:
        
        case 90:
        
        case 91:
        
        case 92:
        
        case 93:
        
        case 94:
        
        case 95:
        
        case 96:
        
        case 97:
        
        case 98:
        
        case 99:
        
        case 100:
        
        case 101:
        
        case 102:
        
        case 103:
        
        case 104:
        
        case 105:
        
        case 106:
        
        case 107:
        
        case 108:
        
        case 109:
        
        case 110:
        
        case 111:
        
        case 112:
        
        case 113:
        
        case 114:
        
        case 115:
        
        case 116:
        
        case 117:
        
        case 118:
        
        case 119:
        
        case 120:
        
        case 121:
        
        case 122:
        
        case 123:
        
        case 124:
        
        case 125:
        
        case 126:
        
        case 127:
        
        case 128:
        
        case 129:
        
        case 130:
        
        case 131:
        
        case 132:
        
        case 133:
        
        case 134:
        
        case 135:
        
        case 136:
        
        case 137:
        
        case 138:
        
        case 139:
        
        case 140:
        
        case 141:
        
        case 142:
        
        case 143:
        
        case 144:
        
        case 145:
        
        case 146:
        
        case 147:
        
        case 148:
        
        case 149:
        
        case 150:
        
        case 151:
        
        case 152:
        
        case 153:
        
        case 154:
        
        case 155:
        
        case 156:
        
        case 157:
        
        case 158:
        
        case 159:
        
        case 160:
        
        case 161:
        
        case 162:
        
        case 163:
        
        case 164:
        
        case 165:
        
        case 166:
        
        case 167:
        
        case 168:
        
        case 169:
        
        case 170:
        
        case 171:
        
        case 172:
        
        case 173:
        
        case 174:
        
        case 175:
        
        case 176:
        
        case 177:
        
        case 178:
        
        case 179:
        
        case 180:
        
        case 181:
        
        case 182:
        
        case 183:
        
        case 184:
        
        case 185:
        
        case 186:
        
        case 187:
        
        case 188:
        
        case 189:
        
        case 190:
        
        case 191:
        
        case 192:
        
        case 193:
        
        case 194:
        
        case 195:
        
        case 196:
        
        case 197:
        
        case 198:
        
        case 199:
        
        case 200:
        
        case 201:
        
        case 202:
        
        case 203:
        
        case 204:
        
        case 205:
        
        case 206:
        
        case 207:
        
        case 208:
        
        case 209:
        
        case 210:
        
        case 211:
        
        case 212:
        
        case 213:
        
        case 214:
        
        case 215:
        
        case 216:
        
        case 217:
        
        case 218:
        
        case 219:
        
        case 220:
        
        case 221:
        
        case 222:
        
        case 223:
        
        case 224:
        
        case 225:
        
        case 226:
        
        case 227:
        
        case 228:
        
        case 229:
        
        case 230:
        
        case 231:
        
        case 232:
        
        case 233:
        
        case 234:
        
        case 235:
        
        case 236:
        
        case 237:
        
        case 238:
        
        case 239:
        
        case 240:
        
        case 241:
        
        case 242:
        
        case 243:
        
        case 244:
        
        case 245:
        
        case 246:
        
        case 247:
        
        case 248:
        
        case 249:
        
        case 250:
        
        case 251:
        
        case 252:
        
        case 253:
        
        case 254:
        
        default:
          break;
      } 
      char c = '';
      int j = (paramInt2 & 0xFF) - c;
      if (j < 0)
        j += 256; 
      int k = ((paramInt2 & 0xFFFF) >>> 8) - c;
      if (k < 0)
        k += 256; 
      for (byte b = 0; b < arrayOfChar.length; b++) {
        int m = b % 2;
        if (m == 0) {
          arrayOfChar[b] = (char)(arrayOfChar[b] ^ j);
          j = ((j >>> 3 | j << 5) ^ arrayOfChar[b]) & 0xFF;
        } else {
          arrayOfChar[b] = (char)(arrayOfChar[b] ^ k);
          k = ((k >>> 3 | k << 5) ^ arrayOfChar[b]) & 0xFF;
        } 
      } 
      b[i] = (new String(arrayOfChar)).intern();
    } 
    return b[i];
  }
}


/* Location:              C:\Program Files\BurpSuitePro\burpsuite_pro.jar!\burp\Zb4m.class
 * Java compiler version: 21 (65.0)
 * JD-Core Version:       1.1.3
 */