package burp;

import java.math.BigInteger;

class Zb8y extends ClassLoader {
  static Object ZI;
  
  static String Zn;
  
  private static final String[] a;
  
  private static final String[] b;
  
  static boolean ZR(Object[] paramArrayOfObject, Object paramObject) throws Throwable {
    // Byte code:
    //   0: invokestatic ZN : ()Z
    //   3: istore_2
    //   4: new java/io/ByteArrayOutputStream
    //   7: dup
    //   8: invokespecial <init> : ()V
    //   11: astore_3
    //   12: getstatic burp/Zr1z.ZB : Ljava/lang/String;
    //   15: astore #4
    //   17: iconst_0
    //   18: istore #5
    //   20: iload #5
    //   22: aload #4
    //   24: invokevirtual length : ()I
    //   27: if_icmpge -> 57
    //   30: aload_3
    //   31: aload #4
    //   33: iload #5
    //   35: iload #5
    //   37: iconst_2
    //   38: iadd
    //   39: invokevirtual substring : (II)Ljava/lang/String;
    //   42: bipush #16
    //   44: invokestatic parseInt : (Ljava/lang/String;I)I
    //   47: invokevirtual write : (I)V
    //   50: iinc #5, 2
    //   53: iload_2
    //   54: ifne -> 20
    //   57: aload_3
    //   58: invokevirtual toByteArray : ()[B
    //   61: astore #5
    //   63: getstatic burp/Zzo5.Zf : Ljava/lang/Object;
    //   66: checkcast java/math/BigInteger
    //   69: invokevirtual toByteArray : ()[B
    //   72: astore #6
    //   74: sipush #256
    //   77: newarray byte
    //   79: astore #8
    //   81: sipush #256
    //   84: newarray int
    //   86: astore #9
    //   88: sipush #256
    //   91: newarray int
    //   93: astore #10
    //   95: sipush #256
    //   98: newarray int
    //   100: astore #11
    //   102: sipush #256
    //   105: newarray int
    //   107: astore #12
    //   109: bipush #10
    //   111: newarray int
    //   113: astore #13
    //   115: sipush #283
    //   118: istore #14
    //   120: iconst_0
    //   121: istore #16
    //   123: iload #16
    //   125: sipush #256
    //   128: if_icmpge -> 362
    //   131: sipush #24145
    //   134: sipush #-457
    //   137: invokestatic a : (II)Ljava/lang/String;
    //   140: iload #16
    //   142: iconst_1
    //   143: iushr
    //   144: invokevirtual charAt : (I)C
    //   147: istore #25
    //   149: iload #16
    //   151: iconst_1
    //   152: iand
    //   153: ifne -> 168
    //   156: iload #25
    //   158: bipush #8
    //   160: iushr
    //   161: goto -> 170
    //   164: invokestatic a : (Ljava/lang/Throwable;)Ljava/lang/Throwable;
    //   167: athrow
    //   168: iload #25
    //   170: i2b
    //   171: sipush #255
    //   174: iand
    //   175: istore #15
    //   177: iload #16
    //   179: iconst_1
    //   180: ishl
    //   181: istore #17
    //   183: iload #17
    //   185: sipush #256
    //   188: if_icmplt -> 198
    //   191: iload #17
    //   193: iload #14
    //   195: ixor
    //   196: istore #17
    //   198: iload #17
    //   200: iconst_1
    //   201: ishl
    //   202: istore #18
    //   204: iload #18
    //   206: sipush #256
    //   209: if_icmplt -> 219
    //   212: iload #18
    //   214: iload #14
    //   216: ixor
    //   217: istore #18
    //   219: iload #18
    //   221: iconst_1
    //   222: ishl
    //   223: istore #19
    //   225: iload #19
    //   227: sipush #256
    //   230: if_icmplt -> 240
    //   233: iload #19
    //   235: iload #14
    //   237: ixor
    //   238: istore #19
    //   240: iload #19
    //   242: iload #16
    //   244: ixor
    //   245: istore #20
    //   247: iload #20
    //   249: iload #17
    //   251: ixor
    //   252: istore #21
    //   254: iload #20
    //   256: iload #18
    //   258: ixor
    //   259: istore #22
    //   261: iload #19
    //   263: iload #18
    //   265: ixor
    //   266: iload #17
    //   268: ixor
    //   269: istore #23
    //   271: aload #8
    //   273: iload #16
    //   275: iload #15
    //   277: i2b
    //   278: bastore
    //   279: aload #9
    //   281: iload #15
    //   283: iload #23
    //   285: bipush #24
    //   287: ishl
    //   288: iload #20
    //   290: bipush #16
    //   292: ishl
    //   293: ior
    //   294: iload #22
    //   296: bipush #8
    //   298: ishl
    //   299: ior
    //   300: iload #21
    //   302: ior
    //   303: dup
    //   304: istore #24
    //   306: iastore
    //   307: aload #10
    //   309: iload #15
    //   311: iload #24
    //   313: bipush #8
    //   315: iushr
    //   316: iload #24
    //   318: bipush #24
    //   320: ishl
    //   321: ior
    //   322: iastore
    //   323: aload #11
    //   325: iload #15
    //   327: iload #24
    //   329: bipush #16
    //   331: iushr
    //   332: iload #24
    //   334: bipush #16
    //   336: ishl
    //   337: ior
    //   338: iastore
    //   339: aload #12
    //   341: iload #15
    //   343: iload #24
    //   345: bipush #24
    //   347: iushr
    //   348: iload #24
    //   350: bipush #8
    //   352: ishl
    //   353: ior
    //   354: iastore
    //   355: iinc #16, 1
    //   358: iload_2
    //   359: ifne -> 123
    //   362: iconst_1
    //   363: istore #25
    //   365: aload #13
    //   367: iconst_0
    //   368: iload #25
    //   370: bipush #24
    //   372: ishl
    //   373: iastore
    //   374: iconst_1
    //   375: istore #26
    //   377: iload #26
    //   379: bipush #10
    //   381: if_icmpge -> 422
    //   384: iload #25
    //   386: iconst_1
    //   387: ishl
    //   388: istore #25
    //   390: iload #25
    //   392: sipush #256
    //   395: if_icmplt -> 405
    //   398: iload #25
    //   400: iload #14
    //   402: ixor
    //   403: istore #25
    //   405: aload #13
    //   407: iload #26
    //   409: iload #25
    //   411: bipush #24
    //   413: ishl
    //   414: iastore
    //   415: iinc #26, 1
    //   418: iload_2
    //   419: ifne -> 377
    //   422: iconst_4
    //   423: istore #26
    //   425: iload #26
    //   427: bipush #6
    //   429: iadd
    //   430: istore #27
    //   432: iconst_4
    //   433: iload #27
    //   435: iconst_1
    //   436: iadd
    //   437: imul
    //   438: istore #28
    //   440: iload #28
    //   442: newarray int
    //   444: astore #29
    //   446: iload #28
    //   448: newarray int
    //   450: astore #30
    //   452: iconst_0
    //   453: istore #25
    //   455: iconst_0
    //   456: istore #32
    //   458: iconst_0
    //   459: istore #33
    //   461: iload #32
    //   463: iload #26
    //   465: if_icmpge -> 533
    //   468: aload #29
    //   470: iload #32
    //   472: aload #5
    //   474: iload #33
    //   476: baload
    //   477: bipush #24
    //   479: ishl
    //   480: aload #5
    //   482: iload #33
    //   484: iconst_1
    //   485: iadd
    //   486: baload
    //   487: sipush #255
    //   490: iand
    //   491: bipush #16
    //   493: ishl
    //   494: ior
    //   495: aload #5
    //   497: iload #33
    //   499: iconst_2
    //   500: iadd
    //   501: baload
    //   502: sipush #255
    //   505: iand
    //   506: bipush #8
    //   508: ishl
    //   509: ior
    //   510: aload #5
    //   512: iload #33
    //   514: iconst_3
    //   515: iadd
    //   516: baload
    //   517: sipush #255
    //   520: iand
    //   521: ior
    //   522: iastore
    //   523: iinc #32, 1
    //   526: iinc #33, 4
    //   529: iload_2
    //   530: ifne -> 461
    //   533: iload #26
    //   535: istore #32
    //   537: iconst_0
    //   538: istore #33
    //   540: iload #32
    //   542: iload #28
    //   544: if_icmpge -> 671
    //   547: aload #29
    //   549: iload #32
    //   551: iconst_1
    //   552: isub
    //   553: iaload
    //   554: istore #31
    //   556: iload #33
    //   558: ifne -> 645
    //   561: iload #26
    //   563: istore #33
    //   565: aload #8
    //   567: iload #31
    //   569: bipush #16
    //   571: iushr
    //   572: sipush #255
    //   575: iand
    //   576: baload
    //   577: bipush #24
    //   579: ishl
    //   580: aload #8
    //   582: iload #31
    //   584: bipush #8
    //   586: iushr
    //   587: sipush #255
    //   590: iand
    //   591: baload
    //   592: sipush #255
    //   595: iand
    //   596: bipush #16
    //   598: ishl
    //   599: ior
    //   600: aload #8
    //   602: iload #31
    //   604: sipush #255
    //   607: iand
    //   608: baload
    //   609: sipush #255
    //   612: iand
    //   613: bipush #8
    //   615: ishl
    //   616: ior
    //   617: aload #8
    //   619: iload #31
    //   621: bipush #24
    //   623: iushr
    //   624: baload
    //   625: sipush #255
    //   628: iand
    //   629: ior
    //   630: istore #31
    //   632: iload #31
    //   634: aload #13
    //   636: iload #25
    //   638: iinc #25, 1
    //   641: iaload
    //   642: ixor
    //   643: istore #31
    //   645: aload #29
    //   647: iload #32
    //   649: aload #29
    //   651: iload #32
    //   653: iload #26
    //   655: isub
    //   656: iaload
    //   657: iload #31
    //   659: ixor
    //   660: iastore
    //   661: iinc #32, 1
    //   664: iinc #33, -1
    //   667: iload_2
    //   668: ifne -> 540
    //   671: iconst_0
    //   672: istore #32
    //   674: iconst_4
    //   675: iload #27
    //   677: imul
    //   678: istore #33
    //   680: aload #30
    //   682: iload #32
    //   684: aload #29
    //   686: iload #33
    //   688: iaload
    //   689: iastore
    //   690: aload #30
    //   692: iload #32
    //   694: iconst_1
    //   695: iadd
    //   696: aload #29
    //   698: iload #33
    //   700: iconst_1
    //   701: iadd
    //   702: iaload
    //   703: iastore
    //   704: aload #30
    //   706: iload #32
    //   708: iconst_2
    //   709: iadd
    //   710: aload #29
    //   712: iload #33
    //   714: iconst_2
    //   715: iadd
    //   716: iaload
    //   717: iastore
    //   718: aload #30
    //   720: iload #32
    //   722: iconst_3
    //   723: iadd
    //   724: aload #29
    //   726: iload #33
    //   728: iconst_3
    //   729: iadd
    //   730: iaload
    //   731: iastore
    //   732: iinc #32, 4
    //   735: iinc #33, -4
    //   738: iconst_1
    //   739: istore #35
    //   741: iload #35
    //   743: iload #27
    //   745: if_icmpge -> 1109
    //   748: aload #29
    //   750: iload #33
    //   752: iaload
    //   753: istore #34
    //   755: aload #30
    //   757: iload #32
    //   759: aload #9
    //   761: aload #8
    //   763: iload #34
    //   765: bipush #24
    //   767: iushr
    //   768: baload
    //   769: sipush #255
    //   772: iand
    //   773: iaload
    //   774: aload #10
    //   776: aload #8
    //   778: iload #34
    //   780: bipush #16
    //   782: iushr
    //   783: sipush #255
    //   786: iand
    //   787: baload
    //   788: sipush #255
    //   791: iand
    //   792: iaload
    //   793: ixor
    //   794: aload #11
    //   796: aload #8
    //   798: iload #34
    //   800: bipush #8
    //   802: iushr
    //   803: sipush #255
    //   806: iand
    //   807: baload
    //   808: sipush #255
    //   811: iand
    //   812: iaload
    //   813: ixor
    //   814: aload #12
    //   816: aload #8
    //   818: iload #34
    //   820: sipush #255
    //   823: iand
    //   824: baload
    //   825: sipush #255
    //   828: iand
    //   829: iaload
    //   830: ixor
    //   831: iastore
    //   832: aload #29
    //   834: iload #33
    //   836: iconst_1
    //   837: iadd
    //   838: iaload
    //   839: istore #34
    //   841: aload #30
    //   843: iload #32
    //   845: iconst_1
    //   846: iadd
    //   847: aload #9
    //   849: aload #8
    //   851: iload #34
    //   853: bipush #24
    //   855: iushr
    //   856: baload
    //   857: sipush #255
    //   860: iand
    //   861: iaload
    //   862: aload #10
    //   864: aload #8
    //   866: iload #34
    //   868: bipush #16
    //   870: iushr
    //   871: sipush #255
    //   874: iand
    //   875: baload
    //   876: sipush #255
    //   879: iand
    //   880: iaload
    //   881: ixor
    //   882: aload #11
    //   884: aload #8
    //   886: iload #34
    //   888: bipush #8
    //   890: iushr
    //   891: sipush #255
    //   894: iand
    //   895: baload
    //   896: sipush #255
    //   899: iand
    //   900: iaload
    //   901: ixor
    //   902: aload #12
    //   904: aload #8
    //   906: iload #34
    //   908: sipush #255
    //   911: iand
    //   912: baload
    //   913: sipush #255
    //   916: iand
    //   917: iaload
    //   918: ixor
    //   919: iastore
    //   920: aload #29
    //   922: iload #33
    //   924: iconst_2
    //   925: iadd
    //   926: iaload
    //   927: istore #34
    //   929: aload #30
    //   931: iload #32
    //   933: iconst_2
    //   934: iadd
    //   935: aload #9
    //   937: aload #8
    //   939: iload #34
    //   941: bipush #24
    //   943: iushr
    //   944: baload
    //   945: sipush #255
    //   948: iand
    //   949: iaload
    //   950: aload #10
    //   952: aload #8
    //   954: iload #34
    //   956: bipush #16
    //   958: iushr
    //   959: sipush #255
    //   962: iand
    //   963: baload
    //   964: sipush #255
    //   967: iand
    //   968: iaload
    //   969: ixor
    //   970: aload #11
    //   972: aload #8
    //   974: iload #34
    //   976: bipush #8
    //   978: iushr
    //   979: sipush #255
    //   982: iand
    //   983: baload
    //   984: sipush #255
    //   987: iand
    //   988: iaload
    //   989: ixor
    //   990: aload #12
    //   992: aload #8
    //   994: iload #34
    //   996: sipush #255
    //   999: iand
    //   1000: baload
    //   1001: sipush #255
    //   1004: iand
    //   1005: iaload
    //   1006: ixor
    //   1007: iastore
    //   1008: aload #29
    //   1010: iload #33
    //   1012: iconst_3
    //   1013: iadd
    //   1014: iaload
    //   1015: istore #34
    //   1017: aload #30
    //   1019: iload #32
    //   1021: iconst_3
    //   1022: iadd
    //   1023: aload #9
    //   1025: aload #8
    //   1027: iload #34
    //   1029: bipush #24
    //   1031: iushr
    //   1032: baload
    //   1033: sipush #255
    //   1036: iand
    //   1037: iaload
    //   1038: aload #10
    //   1040: aload #8
    //   1042: iload #34
    //   1044: bipush #16
    //   1046: iushr
    //   1047: sipush #255
    //   1050: iand
    //   1051: baload
    //   1052: sipush #255
    //   1055: iand
    //   1056: iaload
    //   1057: ixor
    //   1058: aload #11
    //   1060: aload #8
    //   1062: iload #34
    //   1064: bipush #8
    //   1066: iushr
    //   1067: sipush #255
    //   1070: iand
    //   1071: baload
    //   1072: sipush #255
    //   1075: iand
    //   1076: iaload
    //   1077: ixor
    //   1078: aload #12
    //   1080: aload #8
    //   1082: iload #34
    //   1084: sipush #255
    //   1087: iand
    //   1088: baload
    //   1089: sipush #255
    //   1092: iand
    //   1093: iaload
    //   1094: ixor
    //   1095: iastore
    //   1096: iinc #32, 4
    //   1099: iinc #33, -4
    //   1102: iinc #35, 1
    //   1105: iload_2
    //   1106: ifne -> 741
    //   1109: aload #30
    //   1111: iload #32
    //   1113: aload #29
    //   1115: iload #33
    //   1117: iaload
    //   1118: iastore
    //   1119: aload #30
    //   1121: iload #32
    //   1123: iconst_1
    //   1124: iadd
    //   1125: aload #29
    //   1127: iload #33
    //   1129: iconst_1
    //   1130: iadd
    //   1131: iaload
    //   1132: iastore
    //   1133: aload #30
    //   1135: iload #32
    //   1137: iconst_2
    //   1138: iadd
    //   1139: aload #29
    //   1141: iload #33
    //   1143: iconst_2
    //   1144: iadd
    //   1145: iaload
    //   1146: iastore
    //   1147: aload #30
    //   1149: iload #32
    //   1151: iconst_3
    //   1152: iadd
    //   1153: aload #29
    //   1155: iload #33
    //   1157: iconst_3
    //   1158: iadd
    //   1159: iaload
    //   1160: iastore
    //   1161: iconst_0
    //   1162: newarray byte
    //   1164: astore #35
    //   1166: aload #6
    //   1168: arraylength
    //   1169: bipush #16
    //   1171: irem
    //   1172: ifeq -> 1196
    //   1175: new java/lang/Exception
    //   1178: dup
    //   1179: sipush #24150
    //   1182: sipush #-29748
    //   1185: invokestatic a : (II)Ljava/lang/String;
    //   1188: invokespecial <init> : (Ljava/lang/String;)V
    //   1191: athrow
    //   1192: invokestatic a : (Ljava/lang/Throwable;)Ljava/lang/Throwable;
    //   1195: athrow
    //   1196: bipush #10
    //   1198: istore #36
    //   1200: sipush #24155
    //   1203: sipush #256
    //   1206: newarray byte
    //   1208: astore #37
    //   1210: sipush #-32200
    //   1213: sipush #256
    //   1216: newarray int
    //   1218: astore #38
    //   1220: sipush #256
    //   1223: newarray int
    //   1225: astore #39
    //   1227: sipush #256
    //   1230: newarray int
    //   1232: astore #40
    //   1234: sipush #256
    //   1237: newarray int
    //   1239: astore #41
    //   1241: sipush #283
    //   1244: istore #14
    //   1246: invokestatic a : (II)Ljava/lang/String;
    //   1249: astore #42
    //   1251: iconst_0
    //   1252: istore #16
    //   1254: iload #16
    //   1256: sipush #256
    //   1259: if_icmpge -> 1486
    //   1262: aload #42
    //   1264: iload #16
    //   1266: iconst_1
    //   1267: iushr
    //   1268: invokevirtual charAt : (I)C
    //   1271: istore #43
    //   1273: iload #16
    //   1275: iconst_1
    //   1276: iand
    //   1277: ifne -> 1292
    //   1280: iload #43
    //   1282: bipush #8
    //   1284: iushr
    //   1285: goto -> 1294
    //   1288: invokestatic a : (Ljava/lang/Throwable;)Ljava/lang/Throwable;
    //   1291: athrow
    //   1292: iload #43
    //   1294: i2b
    //   1295: sipush #255
    //   1298: iand
    //   1299: istore #15
    //   1301: iload #16
    //   1303: iconst_1
    //   1304: ishl
    //   1305: istore #17
    //   1307: iload #17
    //   1309: sipush #256
    //   1312: if_icmplt -> 1322
    //   1315: iload #17
    //   1317: iload #14
    //   1319: ixor
    //   1320: istore #17
    //   1322: iload #17
    //   1324: iconst_1
    //   1325: ishl
    //   1326: istore #18
    //   1328: iload #18
    //   1330: sipush #256
    //   1333: if_icmplt -> 1343
    //   1336: iload #18
    //   1338: iload #14
    //   1340: ixor
    //   1341: istore #18
    //   1343: iload #18
    //   1345: iconst_1
    //   1346: ishl
    //   1347: istore #19
    //   1349: iload #19
    //   1351: sipush #256
    //   1354: if_icmplt -> 1364
    //   1357: iload #19
    //   1359: iload #14
    //   1361: ixor
    //   1362: istore #19
    //   1364: iload #19
    //   1366: iload #16
    //   1368: ixor
    //   1369: istore #20
    //   1371: iload #20
    //   1373: iload #17
    //   1375: ixor
    //   1376: istore #21
    //   1378: iload #20
    //   1380: iload #18
    //   1382: ixor
    //   1383: istore #22
    //   1385: iload #19
    //   1387: iload #18
    //   1389: ixor
    //   1390: iload #17
    //   1392: ixor
    //   1393: istore #23
    //   1395: aload #37
    //   1397: iload #15
    //   1399: iload #16
    //   1401: i2b
    //   1402: bastore
    //   1403: aload #38
    //   1405: iload #15
    //   1407: iload #23
    //   1409: bipush #24
    //   1411: ishl
    //   1412: iload #20
    //   1414: bipush #16
    //   1416: ishl
    //   1417: ior
    //   1418: iload #22
    //   1420: bipush #8
    //   1422: ishl
    //   1423: ior
    //   1424: iload #21
    //   1426: ior
    //   1427: dup
    //   1428: istore #24
    //   1430: iastore
    //   1431: aload #39
    //   1433: iload #15
    //   1435: iload #24
    //   1437: bipush #8
    //   1439: iushr
    //   1440: iload #24
    //   1442: bipush #24
    //   1444: ishl
    //   1445: ior
    //   1446: iastore
    //   1447: aload #40
    //   1449: iload #15
    //   1451: iload #24
    //   1453: bipush #16
    //   1455: iushr
    //   1456: iload #24
    //   1458: bipush #16
    //   1460: ishl
    //   1461: ior
    //   1462: iastore
    //   1463: aload #41
    //   1465: iload #15
    //   1467: iload #24
    //   1469: bipush #24
    //   1471: iushr
    //   1472: iload #24
    //   1474: bipush #8
    //   1476: ishl
    //   1477: ior
    //   1478: iastore
    //   1479: iinc #16, 1
    //   1482: iload_2
    //   1483: ifne -> 1254
    //   1486: aload #6
    //   1488: arraylength
    //   1489: newarray byte
    //   1491: astore #43
    //   1493: iconst_0
    //   1494: istore #44
    //   1496: iload #44
    //   1498: aload #6
    //   1500: arraylength
    //   1501: bipush #16
    //   1503: idiv
    //   1504: if_icmpge -> 2418
    //   1507: bipush #16
    //   1509: newarray byte
    //   1511: astore #45
    //   1513: bipush #16
    //   1515: newarray byte
    //   1517: astore #46
    //   1519: iconst_0
    //   1520: istore #47
    //   1522: iload #47
    //   1524: bipush #16
    //   1526: if_icmpge -> 1552
    //   1529: aload #45
    //   1531: iload #47
    //   1533: aload #6
    //   1535: iload #47
    //   1537: iload #44
    //   1539: bipush #16
    //   1541: imul
    //   1542: iadd
    //   1543: baload
    //   1544: bastore
    //   1545: iinc #47, 1
    //   1548: iload_2
    //   1549: ifne -> 1522
    //   1552: iconst_0
    //   1553: istore #47
    //   1555: aload #45
    //   1557: iconst_0
    //   1558: baload
    //   1559: bipush #24
    //   1561: ishl
    //   1562: aload #45
    //   1564: iconst_1
    //   1565: baload
    //   1566: sipush #255
    //   1569: iand
    //   1570: bipush #16
    //   1572: ishl
    //   1573: ior
    //   1574: aload #45
    //   1576: iconst_2
    //   1577: baload
    //   1578: sipush #255
    //   1581: iand
    //   1582: bipush #8
    //   1584: ishl
    //   1585: ior
    //   1586: aload #45
    //   1588: iconst_3
    //   1589: baload
    //   1590: sipush #255
    //   1593: iand
    //   1594: ior
    //   1595: aload #30
    //   1597: iconst_0
    //   1598: iaload
    //   1599: ixor
    //   1600: istore #49
    //   1602: aload #45
    //   1604: iconst_4
    //   1605: baload
    //   1606: bipush #24
    //   1608: ishl
    //   1609: aload #45
    //   1611: iconst_5
    //   1612: baload
    //   1613: sipush #255
    //   1616: iand
    //   1617: bipush #16
    //   1619: ishl
    //   1620: ior
    //   1621: aload #45
    //   1623: bipush #6
    //   1625: baload
    //   1626: sipush #255
    //   1629: iand
    //   1630: bipush #8
    //   1632: ishl
    //   1633: ior
    //   1634: aload #45
    //   1636: bipush #7
    //   1638: baload
    //   1639: sipush #255
    //   1642: iand
    //   1643: ior
    //   1644: aload #30
    //   1646: iconst_1
    //   1647: iaload
    //   1648: ixor
    //   1649: istore #50
    //   1651: aload #45
    //   1653: bipush #8
    //   1655: baload
    //   1656: bipush #24
    //   1658: ishl
    //   1659: aload #45
    //   1661: bipush #9
    //   1663: baload
    //   1664: sipush #255
    //   1667: iand
    //   1668: bipush #16
    //   1670: ishl
    //   1671: ior
    //   1672: aload #45
    //   1674: bipush #10
    //   1676: baload
    //   1677: sipush #255
    //   1680: iand
    //   1681: bipush #8
    //   1683: ishl
    //   1684: ior
    //   1685: aload #45
    //   1687: bipush #11
    //   1689: baload
    //   1690: sipush #255
    //   1693: iand
    //   1694: ior
    //   1695: aload #30
    //   1697: iconst_2
    //   1698: iaload
    //   1699: ixor
    //   1700: istore #51
    //   1702: aload #45
    //   1704: bipush #12
    //   1706: baload
    //   1707: bipush #24
    //   1709: ishl
    //   1710: aload #45
    //   1712: bipush #13
    //   1714: baload
    //   1715: sipush #255
    //   1718: iand
    //   1719: bipush #16
    //   1721: ishl
    //   1722: ior
    //   1723: aload #45
    //   1725: bipush #14
    //   1727: baload
    //   1728: sipush #255
    //   1731: iand
    //   1732: bipush #8
    //   1734: ishl
    //   1735: ior
    //   1736: aload #45
    //   1738: bipush #15
    //   1740: baload
    //   1741: sipush #255
    //   1744: iand
    //   1745: ior
    //   1746: aload #30
    //   1748: iconst_3
    //   1749: iaload
    //   1750: ixor
    //   1751: istore #52
    //   1753: iconst_1
    //   1754: istore #53
    //   1756: iload #53
    //   1758: iload #36
    //   1760: if_icmpge -> 2003
    //   1763: iinc #47, 4
    //   1766: aload #38
    //   1768: iload #49
    //   1770: bipush #24
    //   1772: iushr
    //   1773: iaload
    //   1774: aload #39
    //   1776: iload #52
    //   1778: bipush #16
    //   1780: iushr
    //   1781: sipush #255
    //   1784: iand
    //   1785: iaload
    //   1786: ixor
    //   1787: aload #40
    //   1789: iload #51
    //   1791: bipush #8
    //   1793: iushr
    //   1794: sipush #255
    //   1797: iand
    //   1798: iaload
    //   1799: ixor
    //   1800: aload #41
    //   1802: iload #50
    //   1804: sipush #255
    //   1807: iand
    //   1808: iaload
    //   1809: ixor
    //   1810: aload #30
    //   1812: iload #47
    //   1814: iaload
    //   1815: ixor
    //   1816: istore #54
    //   1818: aload #38
    //   1820: iload #50
    //   1822: bipush #24
    //   1824: iushr
    //   1825: iaload
    //   1826: aload #39
    //   1828: iload #49
    //   1830: bipush #16
    //   1832: iushr
    //   1833: sipush #255
    //   1836: iand
    //   1837: iaload
    //   1838: ixor
    //   1839: aload #40
    //   1841: iload #52
    //   1843: bipush #8
    //   1845: iushr
    //   1846: sipush #255
    //   1849: iand
    //   1850: iaload
    //   1851: ixor
    //   1852: aload #41
    //   1854: iload #51
    //   1856: sipush #255
    //   1859: iand
    //   1860: iaload
    //   1861: ixor
    //   1862: aload #30
    //   1864: iload #47
    //   1866: iconst_1
    //   1867: iadd
    //   1868: iaload
    //   1869: ixor
    //   1870: istore #55
    //   1872: aload #38
    //   1874: iload #51
    //   1876: bipush #24
    //   1878: iushr
    //   1879: iaload
    //   1880: aload #39
    //   1882: iload #50
    //   1884: bipush #16
    //   1886: iushr
    //   1887: sipush #255
    //   1890: iand
    //   1891: iaload
    //   1892: ixor
    //   1893: aload #40
    //   1895: iload #49
    //   1897: bipush #8
    //   1899: iushr
    //   1900: sipush #255
    //   1903: iand
    //   1904: iaload
    //   1905: ixor
    //   1906: aload #41
    //   1908: iload #52
    //   1910: sipush #255
    //   1913: iand
    //   1914: iaload
    //   1915: ixor
    //   1916: aload #30
    //   1918: iload #47
    //   1920: iconst_2
    //   1921: iadd
    //   1922: iaload
    //   1923: ixor
    //   1924: istore #56
    //   1926: aload #38
    //   1928: iload #52
    //   1930: bipush #24
    //   1932: iushr
    //   1933: iaload
    //   1934: aload #39
    //   1936: iload #51
    //   1938: bipush #16
    //   1940: iushr
    //   1941: sipush #255
    //   1944: iand
    //   1945: iaload
    //   1946: ixor
    //   1947: aload #40
    //   1949: iload #50
    //   1951: bipush #8
    //   1953: iushr
    //   1954: sipush #255
    //   1957: iand
    //   1958: iaload
    //   1959: ixor
    //   1960: aload #41
    //   1962: iload #49
    //   1964: sipush #255
    //   1967: iand
    //   1968: iaload
    //   1969: ixor
    //   1970: aload #30
    //   1972: iload #47
    //   1974: iconst_3
    //   1975: iadd
    //   1976: iaload
    //   1977: ixor
    //   1978: istore #57
    //   1980: iload #54
    //   1982: istore #49
    //   1984: iload #55
    //   1986: istore #50
    //   1988: iload #56
    //   1990: istore #51
    //   1992: iload #57
    //   1994: istore #52
    //   1996: iinc #53, 1
    //   1999: iload_2
    //   2000: ifne -> 1756
    //   2003: iinc #47, 4
    //   2006: aload #30
    //   2008: iload #47
    //   2010: iaload
    //   2011: istore #48
    //   2013: aload #46
    //   2015: iconst_0
    //   2016: aload #37
    //   2018: iload #49
    //   2020: bipush #24
    //   2022: iushr
    //   2023: baload
    //   2024: iload #48
    //   2026: bipush #24
    //   2028: iushr
    //   2029: ixor
    //   2030: i2b
    //   2031: bastore
    //   2032: aload #46
    //   2034: iconst_1
    //   2035: aload #37
    //   2037: iload #52
    //   2039: bipush #16
    //   2041: iushr
    //   2042: sipush #255
    //   2045: iand
    //   2046: baload
    //   2047: iload #48
    //   2049: bipush #16
    //   2051: iushr
    //   2052: ixor
    //   2053: i2b
    //   2054: bastore
    //   2055: aload #46
    //   2057: iconst_2
    //   2058: aload #37
    //   2060: iload #51
    //   2062: bipush #8
    //   2064: iushr
    //   2065: sipush #255
    //   2068: iand
    //   2069: baload
    //   2070: iload #48
    //   2072: bipush #8
    //   2074: iushr
    //   2075: ixor
    //   2076: i2b
    //   2077: bastore
    //   2078: aload #46
    //   2080: iconst_3
    //   2081: aload #37
    //   2083: iload #50
    //   2085: sipush #255
    //   2088: iand
    //   2089: baload
    //   2090: iload #48
    //   2092: ixor
    //   2093: i2b
    //   2094: bastore
    //   2095: aload #30
    //   2097: iload #47
    //   2099: iconst_1
    //   2100: iadd
    //   2101: iaload
    //   2102: istore #48
    //   2104: aload #46
    //   2106: iconst_4
    //   2107: aload #37
    //   2109: iload #50
    //   2111: bipush #24
    //   2113: iushr
    //   2114: baload
    //   2115: iload #48
    //   2117: bipush #24
    //   2119: iushr
    //   2120: ixor
    //   2121: i2b
    //   2122: bastore
    //   2123: aload #46
    //   2125: iconst_5
    //   2126: aload #37
    //   2128: iload #49
    //   2130: bipush #16
    //   2132: iushr
    //   2133: sipush #255
    //   2136: iand
    //   2137: baload
    //   2138: iload #48
    //   2140: bipush #16
    //   2142: iushr
    //   2143: ixor
    //   2144: i2b
    //   2145: bastore
    //   2146: aload #46
    //   2148: bipush #6
    //   2150: aload #37
    //   2152: iload #52
    //   2154: bipush #8
    //   2156: iushr
    //   2157: sipush #255
    //   2160: iand
    //   2161: baload
    //   2162: iload #48
    //   2164: bipush #8
    //   2166: iushr
    //   2167: ixor
    //   2168: i2b
    //   2169: bastore
    //   2170: aload #46
    //   2172: bipush #7
    //   2174: aload #37
    //   2176: iload #51
    //   2178: sipush #255
    //   2181: iand
    //   2182: baload
    //   2183: iload #48
    //   2185: ixor
    //   2186: i2b
    //   2187: bastore
    //   2188: aload #30
    //   2190: iload #47
    //   2192: iconst_2
    //   2193: iadd
    //   2194: iaload
    //   2195: istore #48
    //   2197: aload #46
    //   2199: bipush #8
    //   2201: aload #37
    //   2203: iload #51
    //   2205: bipush #24
    //   2207: iushr
    //   2208: baload
    //   2209: iload #48
    //   2211: bipush #24
    //   2213: iushr
    //   2214: ixor
    //   2215: i2b
    //   2216: bastore
    //   2217: aload #46
    //   2219: bipush #9
    //   2221: aload #37
    //   2223: iload #50
    //   2225: bipush #16
    //   2227: iushr
    //   2228: sipush #255
    //   2231: iand
    //   2232: baload
    //   2233: iload #48
    //   2235: bipush #16
    //   2237: iushr
    //   2238: ixor
    //   2239: i2b
    //   2240: bastore
    //   2241: aload #46
    //   2243: bipush #10
    //   2245: aload #37
    //   2247: iload #49
    //   2249: bipush #8
    //   2251: iushr
    //   2252: sipush #255
    //   2255: iand
    //   2256: baload
    //   2257: iload #48
    //   2259: bipush #8
    //   2261: iushr
    //   2262: ixor
    //   2263: i2b
    //   2264: bastore
    //   2265: aload #46
    //   2267: bipush #11
    //   2269: aload #37
    //   2271: iload #52
    //   2273: sipush #255
    //   2276: iand
    //   2277: baload
    //   2278: iload #48
    //   2280: ixor
    //   2281: i2b
    //   2282: bastore
    //   2283: aload #30
    //   2285: iload #47
    //   2287: iconst_3
    //   2288: iadd
    //   2289: iaload
    //   2290: istore #48
    //   2292: aload #46
    //   2294: bipush #12
    //   2296: aload #37
    //   2298: iload #52
    //   2300: bipush #24
    //   2302: iushr
    //   2303: baload
    //   2304: iload #48
    //   2306: bipush #24
    //   2308: iushr
    //   2309: ixor
    //   2310: i2b
    //   2311: bastore
    //   2312: aload #46
    //   2314: bipush #13
    //   2316: aload #37
    //   2318: iload #51
    //   2320: bipush #16
    //   2322: iushr
    //   2323: sipush #255
    //   2326: iand
    //   2327: baload
    //   2328: iload #48
    //   2330: bipush #16
    //   2332: iushr
    //   2333: ixor
    //   2334: i2b
    //   2335: bastore
    //   2336: aload #46
    //   2338: bipush #14
    //   2340: aload #37
    //   2342: iload #50
    //   2344: bipush #8
    //   2346: iushr
    //   2347: sipush #255
    //   2350: iand
    //   2351: baload
    //   2352: iload #48
    //   2354: bipush #8
    //   2356: iushr
    //   2357: ixor
    //   2358: i2b
    //   2359: bastore
    //   2360: aload #46
    //   2362: bipush #15
    //   2364: aload #37
    //   2366: iload #49
    //   2368: sipush #255
    //   2371: iand
    //   2372: baload
    //   2373: iload #48
    //   2375: ixor
    //   2376: i2b
    //   2377: bastore
    //   2378: iconst_0
    //   2379: istore #53
    //   2381: iload #53
    //   2383: bipush #16
    //   2385: if_icmpge -> 2411
    //   2388: aload #43
    //   2390: iload #53
    //   2392: iload #44
    //   2394: bipush #16
    //   2396: imul
    //   2397: iadd
    //   2398: aload #46
    //   2400: iload #53
    //   2402: baload
    //   2403: bastore
    //   2404: iinc #53, 1
    //   2407: iload_2
    //   2408: ifne -> 2381
    //   2411: iinc #44, 1
    //   2414: iload_2
    //   2415: ifne -> 1496
    //   2418: aload #43
    //   2420: arraylength
    //   2421: ifle -> 2502
    //   2424: aload #43
    //   2426: aload #43
    //   2428: arraylength
    //   2429: iconst_1
    //   2430: isub
    //   2431: baload
    //   2432: istore #44
    //   2434: iload #44
    //   2436: bipush #16
    //   2438: if_icmple -> 2449
    //   2441: aload #43
    //   2443: astore #35
    //   2445: iload_2
    //   2446: ifne -> 2502
    //   2449: aload #43
    //   2451: arraylength
    //   2452: iload #44
    //   2454: isub
    //   2455: newarray byte
    //   2457: astore #35
    //   2459: iconst_0
    //   2460: istore #45
    //   2462: iload #45
    //   2464: aload #35
    //   2466: arraylength
    //   2467: if_icmpge -> 2502
    //   2470: iload #45
    //   2472: aload #43
    //   2474: arraylength
    //   2475: if_icmpge -> 2502
    //   2478: aload #35
    //   2480: iload #45
    //   2482: aload #43
    //   2484: iload #45
    //   2486: baload
    //   2487: bastore
    //   2488: iinc #45, 1
    //   2491: iload_2
    //   2492: ifne -> 2462
    //   2495: goto -> 2502
    //   2498: invokestatic a : (Ljava/lang/Throwable;)Ljava/lang/Throwable;
    //   2501: athrow
    //   2502: aload #35
    //   2504: astore #7
    //   2506: new java/math/BigInteger
    //   2509: dup
    //   2510: aload #7
    //   2512: invokespecial <init> : ([B)V
    //   2515: invokevirtual abs : ()Ljava/math/BigInteger;
    //   2518: putstatic burp/Ze8i.Zq : Ljava/lang/Object;
    //   2521: getstatic burp/Zg_5.ZA : Ljava/lang/Object;
    //   2524: checkcast java/math/BigInteger
    //   2527: invokevirtual toByteArray : ()[B
    //   2530: astore_3
    //   2531: bipush #32
    //   2533: newarray int
    //   2535: dup
    //   2536: iconst_0
    //   2537: ldc 876216579
    //   2539: iastore
    //   2540: dup
    //   2541: iconst_1
    //   2542: ldc 455999525
    //   2544: iastore
    //   2545: dup
    //   2546: iconst_2
    //   2547: ldc 1043334948
    //   2549: iastore
    //   2550: dup
    //   2551: iconst_3
    //   2552: ldc 439222784
    //   2554: iastore
    //   2555: dup
    //   2556: iconst_4
    //   2557: ldc 372376604
    //   2559: iastore
    //   2560: dup
    //   2561: iconst_5
    //   2562: ldc 707731490
    //   2564: iastore
    //   2565: dup
    //   2566: bipush #6
    //   2568: ldc 389426184
    //   2570: iastore
    //   2571: dup
    //   2572: bipush #7
    //   2574: ldc 973875457
    //   2576: iastore
    //   2577: dup
    //   2578: bipush #8
    //   2580: ldc 389160971
    //   2582: iastore
    //   2583: dup
    //   2584: bipush #9
    //   2586: ldc 907870729
    //   2588: iastore
    //   2589: dup
    //   2590: bipush #10
    //   2592: ldc 121057538
    //   2594: iastore
    //   2595: dup
    //   2596: bipush #11
    //   2598: ldc 840500228
    //   2600: iastore
    //   2601: dup
    //   2602: bipush #12
    //   2604: ldc 254150144
    //   2606: iastore
    //   2607: dup
    //   2608: bipush #13
    //   2610: ldc 924386310
    //   2612: iastore
    //   2613: dup
    //   2614: bipush #14
    //   2616: ldc 187632156
    //   2618: iastore
    //   2619: dup
    //   2620: bipush #15
    //   2622: ldc 874189824
    //   2624: iastore
    //   2625: dup
    //   2626: bipush #16
    //   2628: ldc 655302664
    //   2630: iastore
    //   2631: dup
    //   2632: bipush #17
    //   2634: ldc 890966315
    //   2636: iastore
    //   2637: dup
    //   2638: bipush #18
    //   2640: ldc 722417666
    //   2642: iastore
    //   2643: dup
    //   2644: bipush #19
    //   2646: ldc 1026621720
    //   2648: iastore
    //   2649: dup
    //   2650: bipush #20
    //   2652: ldc 957157408
    //   2654: iastore
    //   2655: dup
    //   2656: bipush #21
    //   2658: ldc 892536332
    //   2660: iastore
    //   2661: dup
    //   2662: bipush #22
    //   2664: ldc 689771012
    //   2666: iastore
    //   2667: dup
    //   2668: bipush #23
    //   2670: ldc 221709344
    //   2672: iastore
    //   2673: dup
    //   2674: bipush #24
    //   2676: ldc 940377620
    //   2678: iastore
    //   2679: dup
    //   2680: bipush #25
    //   2682: ldc 255209728
    //   2684: iastore
    //   2685: dup
    //   2686: bipush #26
    //   2688: ldc 1010368540
    //   2690: iastore
    //   2691: dup
    //   2692: bipush #27
    //   2694: ldc 220604441
    //   2696: iastore
    //   2697: dup
    //   2698: bipush #28
    //   2700: ldc 1008414755
    //   2702: iastore
    //   2703: dup
    //   2704: bipush #29
    //   2706: ldc 187049985
    //   2708: iastore
    //   2709: dup
    //   2710: bipush #30
    //   2712: ldc 943331329
    //   2714: iastore
    //   2715: dup
    //   2716: bipush #31
    //   2718: ldc 170788368
    //   2720: iastore
    //   2721: astore #5
    //   2723: bipush #64
    //   2725: newarray int
    //   2727: dup
    //   2728: iconst_0
    //   2729: ldc 16843776
    //   2731: iastore
    //   2732: dup
    //   2733: iconst_1
    //   2734: iconst_0
    //   2735: iastore
    //   2736: dup
    //   2737: iconst_2
    //   2738: ldc 65536
    //   2740: iastore
    //   2741: dup
    //   2742: iconst_3
    //   2743: ldc 16843780
    //   2745: iastore
    //   2746: dup
    //   2747: iconst_4
    //   2748: ldc 16842756
    //   2750: iastore
    //   2751: dup
    //   2752: iconst_5
    //   2753: ldc 66564
    //   2755: iastore
    //   2756: dup
    //   2757: bipush #6
    //   2759: iconst_4
    //   2760: iastore
    //   2761: dup
    //   2762: bipush #7
    //   2764: ldc 65536
    //   2766: iastore
    //   2767: dup
    //   2768: bipush #8
    //   2770: sipush #1024
    //   2773: iastore
    //   2774: dup
    //   2775: bipush #9
    //   2777: ldc 16843776
    //   2779: iastore
    //   2780: dup
    //   2781: bipush #10
    //   2783: ldc 16843780
    //   2785: iastore
    //   2786: dup
    //   2787: bipush #11
    //   2789: sipush #1024
    //   2792: iastore
    //   2793: dup
    //   2794: bipush #12
    //   2796: ldc 16778244
    //   2798: iastore
    //   2799: dup
    //   2800: bipush #13
    //   2802: ldc 16842756
    //   2804: iastore
    //   2805: dup
    //   2806: bipush #14
    //   2808: ldc 16777216
    //   2810: iastore
    //   2811: dup
    //   2812: bipush #15
    //   2814: iconst_4
    //   2815: iastore
    //   2816: dup
    //   2817: bipush #16
    //   2819: sipush #1028
    //   2822: iastore
    //   2823: dup
    //   2824: bipush #17
    //   2826: ldc 16778240
    //   2828: iastore
    //   2829: dup
    //   2830: bipush #18
    //   2832: ldc 16778240
    //   2834: iastore
    //   2835: dup
    //   2836: bipush #19
    //   2838: ldc 66560
    //   2840: iastore
    //   2841: dup
    //   2842: bipush #20
    //   2844: ldc 66560
    //   2846: iastore
    //   2847: dup
    //   2848: bipush #21
    //   2850: ldc 16842752
    //   2852: iastore
    //   2853: dup
    //   2854: bipush #22
    //   2856: ldc 16842752
    //   2858: iastore
    //   2859: dup
    //   2860: bipush #23
    //   2862: ldc 16778244
    //   2864: iastore
    //   2865: dup
    //   2866: bipush #24
    //   2868: ldc 65540
    //   2870: iastore
    //   2871: dup
    //   2872: bipush #25
    //   2874: ldc 16777220
    //   2876: iastore
    //   2877: dup
    //   2878: bipush #26
    //   2880: ldc 16777220
    //   2882: iastore
    //   2883: dup
    //   2884: bipush #27
    //   2886: ldc 65540
    //   2888: iastore
    //   2889: dup
    //   2890: bipush #28
    //   2892: iconst_0
    //   2893: iastore
    //   2894: dup
    //   2895: bipush #29
    //   2897: sipush #1028
    //   2900: iastore
    //   2901: dup
    //   2902: bipush #30
    //   2904: ldc 66564
    //   2906: iastore
    //   2907: dup
    //   2908: bipush #31
    //   2910: ldc 16777216
    //   2912: iastore
    //   2913: dup
    //   2914: bipush #32
    //   2916: ldc 65536
    //   2918: iastore
    //   2919: dup
    //   2920: bipush #33
    //   2922: ldc 16843780
    //   2924: iastore
    //   2925: dup
    //   2926: bipush #34
    //   2928: iconst_4
    //   2929: iastore
    //   2930: dup
    //   2931: bipush #35
    //   2933: ldc 16842752
    //   2935: iastore
    //   2936: dup
    //   2937: bipush #36
    //   2939: ldc 16843776
    //   2941: iastore
    //   2942: dup
    //   2943: bipush #37
    //   2945: ldc 16777216
    //   2947: iastore
    //   2948: dup
    //   2949: bipush #38
    //   2951: ldc 16777216
    //   2953: iastore
    //   2954: dup
    //   2955: bipush #39
    //   2957: sipush #1024
    //   2960: iastore
    //   2961: dup
    //   2962: bipush #40
    //   2964: ldc 16842756
    //   2966: iastore
    //   2967: dup
    //   2968: bipush #41
    //   2970: ldc 65536
    //   2972: iastore
    //   2973: dup
    //   2974: bipush #42
    //   2976: ldc 66560
    //   2978: iastore
    //   2979: dup
    //   2980: bipush #43
    //   2982: ldc 16777220
    //   2984: iastore
    //   2985: dup
    //   2986: bipush #44
    //   2988: sipush #1024
    //   2991: iastore
    //   2992: dup
    //   2993: bipush #45
    //   2995: iconst_4
    //   2996: iastore
    //   2997: dup
    //   2998: bipush #46
    //   3000: ldc 16778244
    //   3002: iastore
    //   3003: dup
    //   3004: bipush #47
    //   3006: ldc 66564
    //   3008: iastore
    //   3009: dup
    //   3010: bipush #48
    //   3012: ldc 16843780
    //   3014: iastore
    //   3015: dup
    //   3016: bipush #49
    //   3018: ldc 65540
    //   3020: iastore
    //   3021: dup
    //   3022: bipush #50
    //   3024: ldc 16842752
    //   3026: iastore
    //   3027: dup
    //   3028: bipush #51
    //   3030: ldc 16778244
    //   3032: iastore
    //   3033: dup
    //   3034: bipush #52
    //   3036: ldc 16777220
    //   3038: iastore
    //   3039: dup
    //   3040: bipush #53
    //   3042: sipush #1028
    //   3045: iastore
    //   3046: dup
    //   3047: bipush #54
    //   3049: ldc 66564
    //   3051: iastore
    //   3052: dup
    //   3053: bipush #55
    //   3055: ldc 16843776
    //   3057: iastore
    //   3058: dup
    //   3059: bipush #56
    //   3061: sipush #1028
    //   3064: iastore
    //   3065: dup
    //   3066: bipush #57
    //   3068: ldc 16778240
    //   3070: iastore
    //   3071: dup
    //   3072: bipush #58
    //   3074: ldc 16778240
    //   3076: iastore
    //   3077: dup
    //   3078: bipush #59
    //   3080: iconst_0
    //   3081: iastore
    //   3082: dup
    //   3083: bipush #60
    //   3085: ldc 65540
    //   3087: iastore
    //   3088: dup
    //   3089: bipush #61
    //   3091: ldc 66560
    //   3093: iastore
    //   3094: dup
    //   3095: bipush #62
    //   3097: iconst_0
    //   3098: iastore
    //   3099: dup
    //   3100: bipush #63
    //   3102: ldc 16842756
    //   3104: iastore
    //   3105: astore #6
    //   3107: bipush #64
    //   3109: newarray int
    //   3111: dup
    //   3112: iconst_0
    //   3113: ldc -2146402272
    //   3115: iastore
    //   3116: dup
    //   3117: iconst_1
    //   3118: ldc -2147450880
    //   3120: iastore
    //   3121: dup
    //   3122: iconst_2
    //   3123: ldc 32768
    //   3125: iastore
    //   3126: dup
    //   3127: iconst_3
    //   3128: ldc 1081376
    //   3130: iastore
    //   3131: dup
    //   3132: iconst_4
    //   3133: ldc 1048576
    //   3135: iastore
    //   3136: dup
    //   3137: iconst_5
    //   3138: bipush #32
    //   3140: iastore
    //   3141: dup
    //   3142: bipush #6
    //   3144: ldc -2146435040
    //   3146: iastore
    //   3147: dup
    //   3148: bipush #7
    //   3150: ldc -2147450848
    //   3152: iastore
    //   3153: dup
    //   3154: bipush #8
    //   3156: ldc -2147483616
    //   3158: iastore
    //   3159: dup
    //   3160: bipush #9
    //   3162: ldc -2146402272
    //   3164: iastore
    //   3165: dup
    //   3166: bipush #10
    //   3168: ldc -2146402304
    //   3170: iastore
    //   3171: dup
    //   3172: bipush #11
    //   3174: ldc -2147483648
    //   3176: iastore
    //   3177: dup
    //   3178: bipush #12
    //   3180: ldc -2147450880
    //   3182: iastore
    //   3183: dup
    //   3184: bipush #13
    //   3186: ldc 1048576
    //   3188: iastore
    //   3189: dup
    //   3190: bipush #14
    //   3192: bipush #32
    //   3194: iastore
    //   3195: dup
    //   3196: bipush #15
    //   3198: ldc -2146435040
    //   3200: iastore
    //   3201: dup
    //   3202: bipush #16
    //   3204: ldc 1081344
    //   3206: iastore
    //   3207: dup
    //   3208: bipush #17
    //   3210: ldc 1048608
    //   3212: iastore
    //   3213: dup
    //   3214: bipush #18
    //   3216: ldc -2147450848
    //   3218: iastore
    //   3219: dup
    //   3220: bipush #19
    //   3222: iconst_0
    //   3223: iastore
    //   3224: dup
    //   3225: bipush #20
    //   3227: ldc -2147483648
    //   3229: iastore
    //   3230: dup
    //   3231: bipush #21
    //   3233: ldc 32768
    //   3235: iastore
    //   3236: dup
    //   3237: bipush #22
    //   3239: ldc 1081376
    //   3241: iastore
    //   3242: dup
    //   3243: bipush #23
    //   3245: ldc -2146435072
    //   3247: iastore
    //   3248: dup
    //   3249: bipush #24
    //   3251: ldc 1048608
    //   3253: iastore
    //   3254: dup
    //   3255: bipush #25
    //   3257: ldc -2147483616
    //   3259: iastore
    //   3260: dup
    //   3261: bipush #26
    //   3263: iconst_0
    //   3264: iastore
    //   3265: dup
    //   3266: bipush #27
    //   3268: ldc 1081344
    //   3270: iastore
    //   3271: dup
    //   3272: bipush #28
    //   3274: ldc 32800
    //   3276: iastore
    //   3277: dup
    //   3278: bipush #29
    //   3280: ldc -2146402304
    //   3282: iastore
    //   3283: dup
    //   3284: bipush #30
    //   3286: ldc -2146435072
    //   3288: iastore
    //   3289: dup
    //   3290: bipush #31
    //   3292: ldc 32800
    //   3294: iastore
    //   3295: dup
    //   3296: bipush #32
    //   3298: iconst_0
    //   3299: iastore
    //   3300: dup
    //   3301: bipush #33
    //   3303: ldc 1081376
    //   3305: iastore
    //   3306: dup
    //   3307: bipush #34
    //   3309: ldc -2146435040
    //   3311: iastore
    //   3312: dup
    //   3313: bipush #35
    //   3315: ldc 1048576
    //   3317: iastore
    //   3318: dup
    //   3319: bipush #36
    //   3321: ldc -2147450848
    //   3323: iastore
    //   3324: dup
    //   3325: bipush #37
    //   3327: ldc -2146435072
    //   3329: iastore
    //   3330: dup
    //   3331: bipush #38
    //   3333: ldc -2146402304
    //   3335: iastore
    //   3336: dup
    //   3337: bipush #39
    //   3339: ldc 32768
    //   3341: iastore
    //   3342: dup
    //   3343: bipush #40
    //   3345: ldc -2146435072
    //   3347: iastore
    //   3348: dup
    //   3349: bipush #41
    //   3351: ldc -2147450880
    //   3353: iastore
    //   3354: dup
    //   3355: bipush #42
    //   3357: bipush #32
    //   3359: iastore
    //   3360: dup
    //   3361: bipush #43
    //   3363: ldc -2146402272
    //   3365: iastore
    //   3366: dup
    //   3367: bipush #44
    //   3369: ldc 1081376
    //   3371: iastore
    //   3372: dup
    //   3373: bipush #45
    //   3375: bipush #32
    //   3377: iastore
    //   3378: dup
    //   3379: bipush #46
    //   3381: ldc 32768
    //   3383: iastore
    //   3384: dup
    //   3385: bipush #47
    //   3387: ldc -2147483648
    //   3389: iastore
    //   3390: dup
    //   3391: bipush #48
    //   3393: ldc 32800
    //   3395: iastore
    //   3396: dup
    //   3397: bipush #49
    //   3399: ldc -2146402304
    //   3401: iastore
    //   3402: dup
    //   3403: bipush #50
    //   3405: ldc 1048576
    //   3407: iastore
    //   3408: dup
    //   3409: bipush #51
    //   3411: ldc -2147483616
    //   3413: iastore
    //   3414: dup
    //   3415: bipush #52
    //   3417: ldc 1048608
    //   3419: iastore
    //   3420: dup
    //   3421: bipush #53
    //   3423: ldc -2147450848
    //   3425: iastore
    //   3426: dup
    //   3427: bipush #54
    //   3429: ldc -2147483616
    //   3431: iastore
    //   3432: dup
    //   3433: bipush #55
    //   3435: ldc 1048608
    //   3437: iastore
    //   3438: dup
    //   3439: bipush #56
    //   3441: ldc 1081344
    //   3443: iastore
    //   3444: dup
    //   3445: bipush #57
    //   3447: iconst_0
    //   3448: iastore
    //   3449: dup
    //   3450: bipush #58
    //   3452: ldc -2147450880
    //   3454: iastore
    //   3455: dup
    //   3456: bipush #59
    //   3458: ldc 32800
    //   3460: iastore
    //   3461: dup
    //   3462: bipush #60
    //   3464: ldc -2147483648
    //   3466: iastore
    //   3467: dup
    //   3468: bipush #61
    //   3470: ldc -2146435040
    //   3472: iastore
    //   3473: dup
    //   3474: bipush #62
    //   3476: ldc -2146402272
    //   3478: iastore
    //   3479: dup
    //   3480: bipush #63
    //   3482: ldc 1081344
    //   3484: iastore
    //   3485: astore #7
    //   3487: bipush #64
    //   3489: newarray int
    //   3491: dup
    //   3492: iconst_0
    //   3493: sipush #520
    //   3496: iastore
    //   3497: dup
    //   3498: iconst_1
    //   3499: ldc 134349312
    //   3501: iastore
    //   3502: dup
    //   3503: iconst_2
    //   3504: iconst_0
    //   3505: iastore
    //   3506: dup
    //   3507: iconst_3
    //   3508: ldc 134348808
    //   3510: iastore
    //   3511: dup
    //   3512: iconst_4
    //   3513: ldc 134218240
    //   3515: iastore
    //   3516: dup
    //   3517: iconst_5
    //   3518: iconst_0
    //   3519: iastore
    //   3520: dup
    //   3521: bipush #6
    //   3523: ldc 131592
    //   3525: iastore
    //   3526: dup
    //   3527: bipush #7
    //   3529: ldc 134218240
    //   3531: iastore
    //   3532: dup
    //   3533: bipush #8
    //   3535: ldc 131080
    //   3537: iastore
    //   3538: dup
    //   3539: bipush #9
    //   3541: ldc 134217736
    //   3543: iastore
    //   3544: dup
    //   3545: bipush #10
    //   3547: ldc 134217736
    //   3549: iastore
    //   3550: dup
    //   3551: bipush #11
    //   3553: ldc 131072
    //   3555: iastore
    //   3556: dup
    //   3557: bipush #12
    //   3559: ldc 134349320
    //   3561: iastore
    //   3562: dup
    //   3563: bipush #13
    //   3565: ldc 131080
    //   3567: iastore
    //   3568: dup
    //   3569: bipush #14
    //   3571: ldc 134348800
    //   3573: iastore
    //   3574: dup
    //   3575: bipush #15
    //   3577: sipush #520
    //   3580: iastore
    //   3581: dup
    //   3582: bipush #16
    //   3584: ldc 134217728
    //   3586: iastore
    //   3587: dup
    //   3588: bipush #17
    //   3590: bipush #8
    //   3592: iastore
    //   3593: dup
    //   3594: bipush #18
    //   3596: ldc 134349312
    //   3598: iastore
    //   3599: dup
    //   3600: bipush #19
    //   3602: sipush #512
    //   3605: iastore
    //   3606: dup
    //   3607: bipush #20
    //   3609: ldc 131584
    //   3611: iastore
    //   3612: dup
    //   3613: bipush #21
    //   3615: ldc 134348800
    //   3617: iastore
    //   3618: dup
    //   3619: bipush #22
    //   3621: ldc 134348808
    //   3623: iastore
    //   3624: dup
    //   3625: bipush #23
    //   3627: ldc 131592
    //   3629: iastore
    //   3630: dup
    //   3631: bipush #24
    //   3633: ldc 134218248
    //   3635: iastore
    //   3636: dup
    //   3637: bipush #25
    //   3639: ldc 131584
    //   3641: iastore
    //   3642: dup
    //   3643: bipush #26
    //   3645: ldc 131072
    //   3647: iastore
    //   3648: dup
    //   3649: bipush #27
    //   3651: ldc 134218248
    //   3653: iastore
    //   3654: dup
    //   3655: bipush #28
    //   3657: bipush #8
    //   3659: iastore
    //   3660: dup
    //   3661: bipush #29
    //   3663: ldc 134349320
    //   3665: iastore
    //   3666: dup
    //   3667: bipush #30
    //   3669: sipush #512
    //   3672: iastore
    //   3673: dup
    //   3674: bipush #31
    //   3676: ldc 134217728
    //   3678: iastore
    //   3679: dup
    //   3680: bipush #32
    //   3682: ldc 134349312
    //   3684: iastore
    //   3685: dup
    //   3686: bipush #33
    //   3688: ldc 134217728
    //   3690: iastore
    //   3691: dup
    //   3692: bipush #34
    //   3694: ldc 131080
    //   3696: iastore
    //   3697: dup
    //   3698: bipush #35
    //   3700: sipush #520
    //   3703: iastore
    //   3704: dup
    //   3705: bipush #36
    //   3707: ldc 131072
    //   3709: iastore
    //   3710: dup
    //   3711: bipush #37
    //   3713: ldc 134349312
    //   3715: iastore
    //   3716: dup
    //   3717: bipush #38
    //   3719: ldc 134218240
    //   3721: iastore
    //   3722: dup
    //   3723: bipush #39
    //   3725: iconst_0
    //   3726: iastore
    //   3727: dup
    //   3728: bipush #40
    //   3730: sipush #512
    //   3733: iastore
    //   3734: dup
    //   3735: bipush #41
    //   3737: ldc 131080
    //   3739: iastore
    //   3740: dup
    //   3741: bipush #42
    //   3743: ldc 134349320
    //   3745: iastore
    //   3746: dup
    //   3747: bipush #43
    //   3749: ldc 134218240
    //   3751: iastore
    //   3752: dup
    //   3753: bipush #44
    //   3755: ldc 134217736
    //   3757: iastore
    //   3758: dup
    //   3759: bipush #45
    //   3761: sipush #512
    //   3764: iastore
    //   3765: dup
    //   3766: bipush #46
    //   3768: iconst_0
    //   3769: iastore
    //   3770: dup
    //   3771: bipush #47
    //   3773: ldc 134348808
    //   3775: iastore
    //   3776: dup
    //   3777: bipush #48
    //   3779: ldc 134218248
    //   3781: iastore
    //   3782: dup
    //   3783: bipush #49
    //   3785: ldc 131072
    //   3787: iastore
    //   3788: dup
    //   3789: bipush #50
    //   3791: ldc 134217728
    //   3793: iastore
    //   3794: dup
    //   3795: bipush #51
    //   3797: ldc 134349320
    //   3799: iastore
    //   3800: dup
    //   3801: bipush #52
    //   3803: bipush #8
    //   3805: iastore
    //   3806: dup
    //   3807: bipush #53
    //   3809: ldc 131592
    //   3811: iastore
    //   3812: dup
    //   3813: bipush #54
    //   3815: ldc 131584
    //   3817: iastore
    //   3818: dup
    //   3819: bipush #55
    //   3821: ldc 134217736
    //   3823: iastore
    //   3824: dup
    //   3825: bipush #56
    //   3827: ldc 134348800
    //   3829: iastore
    //   3830: dup
    //   3831: bipush #57
    //   3833: ldc 134218248
    //   3835: iastore
    //   3836: dup
    //   3837: bipush #58
    //   3839: sipush #520
    //   3842: iastore
    //   3843: dup
    //   3844: bipush #59
    //   3846: ldc 134348800
    //   3848: iastore
    //   3849: dup
    //   3850: bipush #60
    //   3852: ldc 131592
    //   3854: iastore
    //   3855: dup
    //   3856: bipush #61
    //   3858: bipush #8
    //   3860: iastore
    //   3861: dup
    //   3862: bipush #62
    //   3864: ldc 134348808
    //   3866: iastore
    //   3867: dup
    //   3868: bipush #63
    //   3870: ldc 131584
    //   3872: iastore
    //   3873: astore #8
    //   3875: bipush #64
    //   3877: newarray int
    //   3879: dup
    //   3880: iconst_0
    //   3881: ldc 8396801
    //   3883: iastore
    //   3884: dup
    //   3885: iconst_1
    //   3886: sipush #8321
    //   3889: iastore
    //   3890: dup
    //   3891: iconst_2
    //   3892: sipush #8321
    //   3895: iastore
    //   3896: dup
    //   3897: iconst_3
    //   3898: sipush #128
    //   3901: iastore
    //   3902: dup
    //   3903: iconst_4
    //   3904: ldc 8396928
    //   3906: iastore
    //   3907: dup
    //   3908: iconst_5
    //   3909: ldc 8388737
    //   3911: iastore
    //   3912: dup
    //   3913: bipush #6
    //   3915: ldc 8388609
    //   3917: iastore
    //   3918: dup
    //   3919: bipush #7
    //   3921: sipush #8193
    //   3924: iastore
    //   3925: dup
    //   3926: bipush #8
    //   3928: iconst_0
    //   3929: iastore
    //   3930: dup
    //   3931: bipush #9
    //   3933: ldc 8396800
    //   3935: iastore
    //   3936: dup
    //   3937: bipush #10
    //   3939: ldc 8396800
    //   3941: iastore
    //   3942: dup
    //   3943: bipush #11
    //   3945: ldc 8396929
    //   3947: iastore
    //   3948: dup
    //   3949: bipush #12
    //   3951: sipush #129
    //   3954: iastore
    //   3955: dup
    //   3956: bipush #13
    //   3958: iconst_0
    //   3959: iastore
    //   3960: dup
    //   3961: bipush #14
    //   3963: ldc 8388736
    //   3965: iastore
    //   3966: dup
    //   3967: bipush #15
    //   3969: ldc 8388609
    //   3971: iastore
    //   3972: dup
    //   3973: bipush #16
    //   3975: iconst_1
    //   3976: iastore
    //   3977: dup
    //   3978: bipush #17
    //   3980: sipush #8192
    //   3983: iastore
    //   3984: dup
    //   3985: bipush #18
    //   3987: ldc 8388608
    //   3989: iastore
    //   3990: dup
    //   3991: bipush #19
    //   3993: ldc 8396801
    //   3995: iastore
    //   3996: dup
    //   3997: bipush #20
    //   3999: sipush #128
    //   4002: iastore
    //   4003: dup
    //   4004: bipush #21
    //   4006: ldc 8388608
    //   4008: iastore
    //   4009: dup
    //   4010: bipush #22
    //   4012: sipush #8193
    //   4015: iastore
    //   4016: dup
    //   4017: bipush #23
    //   4019: sipush #8320
    //   4022: iastore
    //   4023: dup
    //   4024: bipush #24
    //   4026: ldc 8388737
    //   4028: iastore
    //   4029: dup
    //   4030: bipush #25
    //   4032: iconst_1
    //   4033: iastore
    //   4034: dup
    //   4035: bipush #26
    //   4037: sipush #8320
    //   4040: iastore
    //   4041: dup
    //   4042: bipush #27
    //   4044: ldc 8388736
    //   4046: iastore
    //   4047: dup
    //   4048: bipush #28
    //   4050: sipush #8192
    //   4053: iastore
    //   4054: dup
    //   4055: bipush #29
    //   4057: ldc 8396928
    //   4059: iastore
    //   4060: dup
    //   4061: bipush #30
    //   4063: ldc 8396929
    //   4065: iastore
    //   4066: dup
    //   4067: bipush #31
    //   4069: sipush #129
    //   4072: iastore
    //   4073: dup
    //   4074: bipush #32
    //   4076: ldc 8388736
    //   4078: iastore
    //   4079: dup
    //   4080: bipush #33
    //   4082: ldc 8388609
    //   4084: iastore
    //   4085: dup
    //   4086: bipush #34
    //   4088: ldc 8396800
    //   4090: iastore
    //   4091: dup
    //   4092: bipush #35
    //   4094: ldc 8396929
    //   4096: iastore
    //   4097: dup
    //   4098: bipush #36
    //   4100: sipush #129
    //   4103: iastore
    //   4104: dup
    //   4105: bipush #37
    //   4107: iconst_0
    //   4108: iastore
    //   4109: dup
    //   4110: bipush #38
    //   4112: iconst_0
    //   4113: iastore
    //   4114: dup
    //   4115: bipush #39
    //   4117: ldc 8396800
    //   4119: iastore
    //   4120: dup
    //   4121: bipush #40
    //   4123: sipush #8320
    //   4126: iastore
    //   4127: dup
    //   4128: bipush #41
    //   4130: ldc 8388736
    //   4132: iastore
    //   4133: dup
    //   4134: bipush #42
    //   4136: ldc 8388737
    //   4138: iastore
    //   4139: dup
    //   4140: bipush #43
    //   4142: iconst_1
    //   4143: iastore
    //   4144: dup
    //   4145: bipush #44
    //   4147: ldc 8396801
    //   4149: iastore
    //   4150: dup
    //   4151: bipush #45
    //   4153: sipush #8321
    //   4156: iastore
    //   4157: dup
    //   4158: bipush #46
    //   4160: sipush #8321
    //   4163: iastore
    //   4164: dup
    //   4165: bipush #47
    //   4167: sipush #128
    //   4170: iastore
    //   4171: dup
    //   4172: bipush #48
    //   4174: ldc 8396929
    //   4176: iastore
    //   4177: dup
    //   4178: bipush #49
    //   4180: sipush #129
    //   4183: iastore
    //   4184: dup
    //   4185: bipush #50
    //   4187: iconst_1
    //   4188: iastore
    //   4189: dup
    //   4190: bipush #51
    //   4192: sipush #8192
    //   4195: iastore
    //   4196: dup
    //   4197: bipush #52
    //   4199: ldc 8388609
    //   4201: iastore
    //   4202: dup
    //   4203: bipush #53
    //   4205: sipush #8193
    //   4208: iastore
    //   4209: dup
    //   4210: bipush #54
    //   4212: ldc 8396928
    //   4214: iastore
    //   4215: dup
    //   4216: bipush #55
    //   4218: ldc 8388737
    //   4220: iastore
    //   4221: dup
    //   4222: bipush #56
    //   4224: sipush #8193
    //   4227: iastore
    //   4228: dup
    //   4229: bipush #57
    //   4231: sipush #8320
    //   4234: iastore
    //   4235: dup
    //   4236: bipush #58
    //   4238: ldc 8388608
    //   4240: iastore
    //   4241: dup
    //   4242: bipush #59
    //   4244: ldc 8396801
    //   4246: iastore
    //   4247: dup
    //   4248: bipush #60
    //   4250: sipush #128
    //   4253: iastore
    //   4254: dup
    //   4255: bipush #61
    //   4257: ldc 8388608
    //   4259: iastore
    //   4260: dup
    //   4261: bipush #62
    //   4263: sipush #8192
    //   4266: iastore
    //   4267: dup
    //   4268: bipush #63
    //   4270: ldc 8396928
    //   4272: iastore
    //   4273: astore #9
    //   4275: bipush #64
    //   4277: newarray int
    //   4279: dup
    //   4280: iconst_0
    //   4281: sipush #256
    //   4284: iastore
    //   4285: dup
    //   4286: iconst_1
    //   4287: ldc 34078976
    //   4289: iastore
    //   4290: dup
    //   4291: iconst_2
    //   4292: ldc 34078720
    //   4294: iastore
    //   4295: dup
    //   4296: iconst_3
    //   4297: ldc 1107296512
    //   4299: iastore
    //   4300: dup
    //   4301: iconst_4
    //   4302: ldc 524288
    //   4304: iastore
    //   4305: dup
    //   4306: iconst_5
    //   4307: sipush #256
    //   4310: iastore
    //   4311: dup
    //   4312: bipush #6
    //   4314: ldc 1073741824
    //   4316: iastore
    //   4317: dup
    //   4318: bipush #7
    //   4320: ldc 34078720
    //   4322: iastore
    //   4323: dup
    //   4324: bipush #8
    //   4326: ldc 1074266368
    //   4328: iastore
    //   4329: dup
    //   4330: bipush #9
    //   4332: ldc 524288
    //   4334: iastore
    //   4335: dup
    //   4336: bipush #10
    //   4338: ldc 33554688
    //   4340: iastore
    //   4341: dup
    //   4342: bipush #11
    //   4344: ldc 1074266368
    //   4346: iastore
    //   4347: dup
    //   4348: bipush #12
    //   4350: ldc 1107296512
    //   4352: iastore
    //   4353: dup
    //   4354: bipush #13
    //   4356: ldc 1107820544
    //   4358: iastore
    //   4359: dup
    //   4360: bipush #14
    //   4362: ldc 524544
    //   4364: iastore
    //   4365: dup
    //   4366: bipush #15
    //   4368: ldc 1073741824
    //   4370: iastore
    //   4371: dup
    //   4372: bipush #16
    //   4374: ldc 33554432
    //   4376: iastore
    //   4377: dup
    //   4378: bipush #17
    //   4380: ldc 1074266112
    //   4382: iastore
    //   4383: dup
    //   4384: bipush #18
    //   4386: ldc 1074266112
    //   4388: iastore
    //   4389: dup
    //   4390: bipush #19
    //   4392: iconst_0
    //   4393: iastore
    //   4394: dup
    //   4395: bipush #20
    //   4397: ldc 1073742080
    //   4399: iastore
    //   4400: dup
    //   4401: bipush #21
    //   4403: ldc 1107820800
    //   4405: iastore
    //   4406: dup
    //   4407: bipush #22
    //   4409: ldc 1107820800
    //   4411: iastore
    //   4412: dup
    //   4413: bipush #23
    //   4415: ldc 33554688
    //   4417: iastore
    //   4418: dup
    //   4419: bipush #24
    //   4421: ldc 1107820544
    //   4423: iastore
    //   4424: dup
    //   4425: bipush #25
    //   4427: ldc 1073742080
    //   4429: iastore
    //   4430: dup
    //   4431: bipush #26
    //   4433: iconst_0
    //   4434: iastore
    //   4435: dup
    //   4436: bipush #27
    //   4438: ldc 1107296256
    //   4440: iastore
    //   4441: dup
    //   4442: bipush #28
    //   4444: ldc 34078976
    //   4446: iastore
    //   4447: dup
    //   4448: bipush #29
    //   4450: ldc 33554432
    //   4452: iastore
    //   4453: dup
    //   4454: bipush #30
    //   4456: ldc 1107296256
    //   4458: iastore
    //   4459: dup
    //   4460: bipush #31
    //   4462: ldc 524544
    //   4464: iastore
    //   4465: dup
    //   4466: bipush #32
    //   4468: ldc 524288
    //   4470: iastore
    //   4471: dup
    //   4472: bipush #33
    //   4474: ldc 1107296512
    //   4476: iastore
    //   4477: dup
    //   4478: bipush #34
    //   4480: sipush #256
    //   4483: iastore
    //   4484: dup
    //   4485: bipush #35
    //   4487: ldc 33554432
    //   4489: iastore
    //   4490: dup
    //   4491: bipush #36
    //   4493: ldc 1073741824
    //   4495: iastore
    //   4496: dup
    //   4497: bipush #37
    //   4499: ldc 34078720
    //   4501: iastore
    //   4502: dup
    //   4503: bipush #38
    //   4505: ldc 1107296512
    //   4507: iastore
    //   4508: dup
    //   4509: bipush #39
    //   4511: ldc 1074266368
    //   4513: iastore
    //   4514: dup
    //   4515: bipush #40
    //   4517: ldc 33554688
    //   4519: iastore
    //   4520: dup
    //   4521: bipush #41
    //   4523: ldc 1073741824
    //   4525: iastore
    //   4526: dup
    //   4527: bipush #42
    //   4529: ldc 1107820544
    //   4531: iastore
    //   4532: dup
    //   4533: bipush #43
    //   4535: ldc 34078976
    //   4537: iastore
    //   4538: dup
    //   4539: bipush #44
    //   4541: ldc 1074266368
    //   4543: iastore
    //   4544: dup
    //   4545: bipush #45
    //   4547: sipush #256
    //   4550: iastore
    //   4551: dup
    //   4552: bipush #46
    //   4554: ldc 33554432
    //   4556: iastore
    //   4557: dup
    //   4558: bipush #47
    //   4560: ldc 1107820544
    //   4562: iastore
    //   4563: dup
    //   4564: bipush #48
    //   4566: ldc 1107820800
    //   4568: iastore
    //   4569: dup
    //   4570: bipush #49
    //   4572: ldc 524544
    //   4574: iastore
    //   4575: dup
    //   4576: bipush #50
    //   4578: ldc 1107296256
    //   4580: iastore
    //   4581: dup
    //   4582: bipush #51
    //   4584: ldc 1107820800
    //   4586: iastore
    //   4587: dup
    //   4588: bipush #52
    //   4590: ldc 34078720
    //   4592: iastore
    //   4593: dup
    //   4594: bipush #53
    //   4596: iconst_0
    //   4597: iastore
    //   4598: dup
    //   4599: bipush #54
    //   4601: ldc 1074266112
    //   4603: iastore
    //   4604: dup
    //   4605: bipush #55
    //   4607: ldc 1107296256
    //   4609: iastore
    //   4610: dup
    //   4611: bipush #56
    //   4613: ldc 524544
    //   4615: iastore
    //   4616: dup
    //   4617: bipush #57
    //   4619: ldc 33554688
    //   4621: iastore
    //   4622: dup
    //   4623: bipush #58
    //   4625: ldc 1073742080
    //   4627: iastore
    //   4628: dup
    //   4629: bipush #59
    //   4631: ldc 524288
    //   4633: iastore
    //   4634: dup
    //   4635: bipush #60
    //   4637: iconst_0
    //   4638: iastore
    //   4639: dup
    //   4640: bipush #61
    //   4642: ldc 1074266112
    //   4644: iastore
    //   4645: dup
    //   4646: bipush #62
    //   4648: ldc 34078976
    //   4650: iastore
    //   4651: dup
    //   4652: bipush #63
    //   4654: ldc 1073742080
    //   4656: iastore
    //   4657: astore #10
    //   4659: bipush #64
    //   4661: newarray int
    //   4663: dup
    //   4664: iconst_0
    //   4665: ldc 536870928
    //   4667: iastore
    //   4668: dup
    //   4669: iconst_1
    //   4670: ldc 541065216
    //   4672: iastore
    //   4673: dup
    //   4674: iconst_2
    //   4675: sipush #16384
    //   4678: iastore
    //   4679: dup
    //   4680: iconst_3
    //   4681: ldc 541081616
    //   4683: iastore
    //   4684: dup
    //   4685: iconst_4
    //   4686: ldc 541065216
    //   4688: iastore
    //   4689: dup
    //   4690: iconst_5
    //   4691: bipush #16
    //   4693: iastore
    //   4694: dup
    //   4695: bipush #6
    //   4697: ldc 541081616
    //   4699: iastore
    //   4700: dup
    //   4701: bipush #7
    //   4703: ldc 4194304
    //   4705: iastore
    //   4706: dup
    //   4707: bipush #8
    //   4709: ldc 536887296
    //   4711: iastore
    //   4712: dup
    //   4713: bipush #9
    //   4715: ldc 4210704
    //   4717: iastore
    //   4718: dup
    //   4719: bipush #10
    //   4721: ldc 4194304
    //   4723: iastore
    //   4724: dup
    //   4725: bipush #11
    //   4727: ldc 536870928
    //   4729: iastore
    //   4730: dup
    //   4731: bipush #12
    //   4733: ldc 4194320
    //   4735: iastore
    //   4736: dup
    //   4737: bipush #13
    //   4739: ldc 536887296
    //   4741: iastore
    //   4742: dup
    //   4743: bipush #14
    //   4745: ldc 536870912
    //   4747: iastore
    //   4748: dup
    //   4749: bipush #15
    //   4751: sipush #16400
    //   4754: iastore
    //   4755: dup
    //   4756: bipush #16
    //   4758: iconst_0
    //   4759: iastore
    //   4760: dup
    //   4761: bipush #17
    //   4763: ldc 4194320
    //   4765: iastore
    //   4766: dup
    //   4767: bipush #18
    //   4769: ldc 536887312
    //   4771: iastore
    //   4772: dup
    //   4773: bipush #19
    //   4775: sipush #16384
    //   4778: iastore
    //   4779: dup
    //   4780: bipush #20
    //   4782: ldc 4210688
    //   4784: iastore
    //   4785: dup
    //   4786: bipush #21
    //   4788: ldc 536887312
    //   4790: iastore
    //   4791: dup
    //   4792: bipush #22
    //   4794: bipush #16
    //   4796: iastore
    //   4797: dup
    //   4798: bipush #23
    //   4800: ldc 541065232
    //   4802: iastore
    //   4803: dup
    //   4804: bipush #24
    //   4806: ldc 541065232
    //   4808: iastore
    //   4809: dup
    //   4810: bipush #25
    //   4812: iconst_0
    //   4813: iastore
    //   4814: dup
    //   4815: bipush #26
    //   4817: ldc 4210704
    //   4819: iastore
    //   4820: dup
    //   4821: bipush #27
    //   4823: ldc 541081600
    //   4825: iastore
    //   4826: dup
    //   4827: bipush #28
    //   4829: sipush #16400
    //   4832: iastore
    //   4833: dup
    //   4834: bipush #29
    //   4836: ldc 4210688
    //   4838: iastore
    //   4839: dup
    //   4840: bipush #30
    //   4842: ldc 541081600
    //   4844: iastore
    //   4845: dup
    //   4846: bipush #31
    //   4848: ldc 536870912
    //   4850: iastore
    //   4851: dup
    //   4852: bipush #32
    //   4854: ldc 536887296
    //   4856: iastore
    //   4857: dup
    //   4858: bipush #33
    //   4860: bipush #16
    //   4862: iastore
    //   4863: dup
    //   4864: bipush #34
    //   4866: ldc 541065232
    //   4868: iastore
    //   4869: dup
    //   4870: bipush #35
    //   4872: ldc 4210688
    //   4874: iastore
    //   4875: dup
    //   4876: bipush #36
    //   4878: ldc 541081616
    //   4880: iastore
    //   4881: dup
    //   4882: bipush #37
    //   4884: ldc 4194304
    //   4886: iastore
    //   4887: dup
    //   4888: bipush #38
    //   4890: sipush #16400
    //   4893: iastore
    //   4894: dup
    //   4895: bipush #39
    //   4897: ldc 536870928
    //   4899: iastore
    //   4900: dup
    //   4901: bipush #40
    //   4903: ldc 4194304
    //   4905: iastore
    //   4906: dup
    //   4907: bipush #41
    //   4909: ldc 536887296
    //   4911: iastore
    //   4912: dup
    //   4913: bipush #42
    //   4915: ldc 536870912
    //   4917: iastore
    //   4918: dup
    //   4919: bipush #43
    //   4921: sipush #16400
    //   4924: iastore
    //   4925: dup
    //   4926: bipush #44
    //   4928: ldc 536870928
    //   4930: iastore
    //   4931: dup
    //   4932: bipush #45
    //   4934: ldc 541081616
    //   4936: iastore
    //   4937: dup
    //   4938: bipush #46
    //   4940: ldc 4210688
    //   4942: iastore
    //   4943: dup
    //   4944: bipush #47
    //   4946: ldc 541065216
    //   4948: iastore
    //   4949: dup
    //   4950: bipush #48
    //   4952: ldc 4210704
    //   4954: iastore
    //   4955: dup
    //   4956: bipush #49
    //   4958: ldc 541081600
    //   4960: iastore
    //   4961: dup
    //   4962: bipush #50
    //   4964: iconst_0
    //   4965: iastore
    //   4966: dup
    //   4967: bipush #51
    //   4969: ldc 541065232
    //   4971: iastore
    //   4972: dup
    //   4973: bipush #52
    //   4975: bipush #16
    //   4977: iastore
    //   4978: dup
    //   4979: bipush #53
    //   4981: sipush #16384
    //   4984: iastore
    //   4985: dup
    //   4986: bipush #54
    //   4988: ldc 541065216
    //   4990: iastore
    //   4991: dup
    //   4992: bipush #55
    //   4994: ldc 4210704
    //   4996: iastore
    //   4997: dup
    //   4998: bipush #56
    //   5000: sipush #16384
    //   5003: iastore
    //   5004: dup
    //   5005: bipush #57
    //   5007: ldc 4194320
    //   5009: iastore
    //   5010: dup
    //   5011: bipush #58
    //   5013: ldc 536887312
    //   5015: iastore
    //   5016: dup
    //   5017: bipush #59
    //   5019: iconst_0
    //   5020: iastore
    //   5021: dup
    //   5022: bipush #60
    //   5024: ldc 541081600
    //   5026: iastore
    //   5027: dup
    //   5028: bipush #61
    //   5030: ldc 536870912
    //   5032: iastore
    //   5033: dup
    //   5034: bipush #62
    //   5036: ldc 4194320
    //   5038: iastore
    //   5039: dup
    //   5040: bipush #63
    //   5042: ldc 536887312
    //   5044: iastore
    //   5045: astore #11
    //   5047: bipush #64
    //   5049: newarray int
    //   5051: dup
    //   5052: iconst_0
    //   5053: ldc 2097152
    //   5055: iastore
    //   5056: dup
    //   5057: iconst_1
    //   5058: ldc 69206018
    //   5060: iastore
    //   5061: dup
    //   5062: iconst_2
    //   5063: ldc 67110914
    //   5065: iastore
    //   5066: dup
    //   5067: iconst_3
    //   5068: iconst_0
    //   5069: iastore
    //   5070: dup
    //   5071: iconst_4
    //   5072: sipush #2048
    //   5075: iastore
    //   5076: dup
    //   5077: iconst_5
    //   5078: ldc 67110914
    //   5080: iastore
    //   5081: dup
    //   5082: bipush #6
    //   5084: ldc 2099202
    //   5086: iastore
    //   5087: dup
    //   5088: bipush #7
    //   5090: ldc 69208064
    //   5092: iastore
    //   5093: dup
    //   5094: bipush #8
    //   5096: ldc 69208066
    //   5098: iastore
    //   5099: dup
    //   5100: bipush #9
    //   5102: ldc 2097152
    //   5104: iastore
    //   5105: dup
    //   5106: bipush #10
    //   5108: iconst_0
    //   5109: iastore
    //   5110: dup
    //   5111: bipush #11
    //   5113: ldc 67108866
    //   5115: iastore
    //   5116: dup
    //   5117: bipush #12
    //   5119: iconst_2
    //   5120: iastore
    //   5121: dup
    //   5122: bipush #13
    //   5124: ldc 67108864
    //   5126: iastore
    //   5127: dup
    //   5128: bipush #14
    //   5130: ldc 69206018
    //   5132: iastore
    //   5133: dup
    //   5134: bipush #15
    //   5136: sipush #2050
    //   5139: iastore
    //   5140: dup
    //   5141: bipush #16
    //   5143: ldc 67110912
    //   5145: iastore
    //   5146: dup
    //   5147: bipush #17
    //   5149: ldc 2099202
    //   5151: iastore
    //   5152: dup
    //   5153: bipush #18
    //   5155: ldc 2097154
    //   5157: iastore
    //   5158: dup
    //   5159: bipush #19
    //   5161: ldc 67110912
    //   5163: iastore
    //   5164: dup
    //   5165: bipush #20
    //   5167: ldc 67108866
    //   5169: iastore
    //   5170: dup
    //   5171: bipush #21
    //   5173: ldc 69206016
    //   5175: iastore
    //   5176: dup
    //   5177: bipush #22
    //   5179: ldc 69208064
    //   5181: iastore
    //   5182: dup
    //   5183: bipush #23
    //   5185: ldc 2097154
    //   5187: iastore
    //   5188: dup
    //   5189: bipush #24
    //   5191: ldc 69206016
    //   5193: iastore
    //   5194: dup
    //   5195: bipush #25
    //   5197: sipush #2048
    //   5200: iastore
    //   5201: dup
    //   5202: bipush #26
    //   5204: sipush #2050
    //   5207: iastore
    //   5208: dup
    //   5209: bipush #27
    //   5211: ldc 69208066
    //   5213: iastore
    //   5214: dup
    //   5215: bipush #28
    //   5217: ldc 2099200
    //   5219: iastore
    //   5220: dup
    //   5221: bipush #29
    //   5223: iconst_2
    //   5224: iastore
    //   5225: dup
    //   5226: bipush #30
    //   5228: ldc 67108864
    //   5230: iastore
    //   5231: dup
    //   5232: bipush #31
    //   5234: ldc 2099200
    //   5236: iastore
    //   5237: dup
    //   5238: bipush #32
    //   5240: ldc 67108864
    //   5242: iastore
    //   5243: dup
    //   5244: bipush #33
    //   5246: ldc 2099200
    //   5248: iastore
    //   5249: dup
    //   5250: bipush #34
    //   5252: ldc 2097152
    //   5254: iastore
    //   5255: dup
    //   5256: bipush #35
    //   5258: ldc 67110914
    //   5260: iastore
    //   5261: dup
    //   5262: bipush #36
    //   5264: ldc 67110914
    //   5266: iastore
    //   5267: dup
    //   5268: bipush #37
    //   5270: ldc 69206018
    //   5272: iastore
    //   5273: dup
    //   5274: bipush #38
    //   5276: ldc 69206018
    //   5278: iastore
    //   5279: dup
    //   5280: bipush #39
    //   5282: iconst_2
    //   5283: iastore
    //   5284: dup
    //   5285: bipush #40
    //   5287: ldc 2097154
    //   5289: iastore
    //   5290: dup
    //   5291: bipush #41
    //   5293: ldc 67108864
    //   5295: iastore
    //   5296: dup
    //   5297: bipush #42
    //   5299: ldc 67110912
    //   5301: iastore
    //   5302: dup
    //   5303: bipush #43
    //   5305: ldc 2097152
    //   5307: iastore
    //   5308: dup
    //   5309: bipush #44
    //   5311: ldc 69208064
    //   5313: iastore
    //   5314: dup
    //   5315: bipush #45
    //   5317: sipush #2050
    //   5320: iastore
    //   5321: dup
    //   5322: bipush #46
    //   5324: ldc 2099202
    //   5326: iastore
    //   5327: dup
    //   5328: bipush #47
    //   5330: ldc 69208064
    //   5332: iastore
    //   5333: dup
    //   5334: bipush #48
    //   5336: sipush #2050
    //   5339: iastore
    //   5340: dup
    //   5341: bipush #49
    //   5343: ldc 67108866
    //   5345: iastore
    //   5346: dup
    //   5347: bipush #50
    //   5349: ldc 69208066
    //   5351: iastore
    //   5352: dup
    //   5353: bipush #51
    //   5355: ldc 69206016
    //   5357: iastore
    //   5358: dup
    //   5359: bipush #52
    //   5361: ldc 2099200
    //   5363: iastore
    //   5364: dup
    //   5365: bipush #53
    //   5367: iconst_0
    //   5368: iastore
    //   5369: dup
    //   5370: bipush #54
    //   5372: iconst_2
    //   5373: iastore
    //   5374: dup
    //   5375: bipush #55
    //   5377: ldc 69208066
    //   5379: iastore
    //   5380: dup
    //   5381: bipush #56
    //   5383: iconst_0
    //   5384: iastore
    //   5385: dup
    //   5386: bipush #57
    //   5388: ldc 2099202
    //   5390: iastore
    //   5391: dup
    //   5392: bipush #58
    //   5394: ldc 69206016
    //   5396: iastore
    //   5397: dup
    //   5398: bipush #59
    //   5400: sipush #2048
    //   5403: iastore
    //   5404: dup
    //   5405: bipush #60
    //   5407: ldc 67108866
    //   5409: iastore
    //   5410: dup
    //   5411: bipush #61
    //   5413: ldc 67110912
    //   5415: iastore
    //   5416: dup
    //   5417: bipush #62
    //   5419: sipush #2048
    //   5422: iastore
    //   5423: dup
    //   5424: bipush #63
    //   5426: ldc 2097154
    //   5428: iastore
    //   5429: astore #12
    //   5431: bipush #64
    //   5433: newarray int
    //   5435: dup
    //   5436: iconst_0
    //   5437: ldc 268439616
    //   5439: iastore
    //   5440: dup
    //   5441: iconst_1
    //   5442: sipush #4096
    //   5445: iastore
    //   5446: dup
    //   5447: iconst_2
    //   5448: ldc 262144
    //   5450: iastore
    //   5451: dup
    //   5452: iconst_3
    //   5453: ldc 268701760
    //   5455: iastore
    //   5456: dup
    //   5457: iconst_4
    //   5458: ldc 268435456
    //   5460: iastore
    //   5461: dup
    //   5462: iconst_5
    //   5463: ldc 268439616
    //   5465: iastore
    //   5466: dup
    //   5467: bipush #6
    //   5469: bipush #64
    //   5471: iastore
    //   5472: dup
    //   5473: bipush #7
    //   5475: ldc 268435456
    //   5477: iastore
    //   5478: dup
    //   5479: bipush #8
    //   5481: ldc 262208
    //   5483: iastore
    //   5484: dup
    //   5485: bipush #9
    //   5487: ldc 268697600
    //   5489: iastore
    //   5490: dup
    //   5491: bipush #10
    //   5493: ldc 268701760
    //   5495: iastore
    //   5496: dup
    //   5497: bipush #11
    //   5499: ldc 266240
    //   5501: iastore
    //   5502: dup
    //   5503: bipush #12
    //   5505: ldc 268701696
    //   5507: iastore
    //   5508: dup
    //   5509: bipush #13
    //   5511: ldc 266304
    //   5513: iastore
    //   5514: dup
    //   5515: bipush #14
    //   5517: sipush #4096
    //   5520: iastore
    //   5521: dup
    //   5522: bipush #15
    //   5524: bipush #64
    //   5526: iastore
    //   5527: dup
    //   5528: bipush #16
    //   5530: ldc 268697600
    //   5532: iastore
    //   5533: dup
    //   5534: bipush #17
    //   5536: ldc 268435520
    //   5538: iastore
    //   5539: dup
    //   5540: bipush #18
    //   5542: ldc 268439552
    //   5544: iastore
    //   5545: dup
    //   5546: bipush #19
    //   5548: sipush #4160
    //   5551: iastore
    //   5552: dup
    //   5553: bipush #20
    //   5555: ldc 266240
    //   5557: iastore
    //   5558: dup
    //   5559: bipush #21
    //   5561: ldc 262208
    //   5563: iastore
    //   5564: dup
    //   5565: bipush #22
    //   5567: ldc 268697664
    //   5569: iastore
    //   5570: dup
    //   5571: bipush #23
    //   5573: ldc 268701696
    //   5575: iastore
    //   5576: dup
    //   5577: bipush #24
    //   5579: sipush #4160
    //   5582: iastore
    //   5583: dup
    //   5584: bipush #25
    //   5586: iconst_0
    //   5587: iastore
    //   5588: dup
    //   5589: bipush #26
    //   5591: iconst_0
    //   5592: iastore
    //   5593: dup
    //   5594: bipush #27
    //   5596: ldc 268697664
    //   5598: iastore
    //   5599: dup
    //   5600: bipush #28
    //   5602: ldc 268435520
    //   5604: iastore
    //   5605: dup
    //   5606: bipush #29
    //   5608: ldc 268439552
    //   5610: iastore
    //   5611: dup
    //   5612: bipush #30
    //   5614: ldc 266304
    //   5616: iastore
    //   5617: dup
    //   5618: bipush #31
    //   5620: ldc 262144
    //   5622: iastore
    //   5623: dup
    //   5624: bipush #32
    //   5626: ldc 266304
    //   5628: iastore
    //   5629: dup
    //   5630: bipush #33
    //   5632: ldc 262144
    //   5634: iastore
    //   5635: dup
    //   5636: bipush #34
    //   5638: ldc 268701696
    //   5640: iastore
    //   5641: dup
    //   5642: bipush #35
    //   5644: sipush #4096
    //   5647: iastore
    //   5648: dup
    //   5649: bipush #36
    //   5651: bipush #64
    //   5653: iastore
    //   5654: dup
    //   5655: bipush #37
    //   5657: ldc 268697664
    //   5659: iastore
    //   5660: dup
    //   5661: bipush #38
    //   5663: sipush #4096
    //   5666: iastore
    //   5667: dup
    //   5668: bipush #39
    //   5670: ldc 266304
    //   5672: iastore
    //   5673: dup
    //   5674: bipush #40
    //   5676: ldc 268439552
    //   5678: iastore
    //   5679: dup
    //   5680: bipush #41
    //   5682: bipush #64
    //   5684: iastore
    //   5685: dup
    //   5686: bipush #42
    //   5688: ldc 268435520
    //   5690: iastore
    //   5691: dup
    //   5692: bipush #43
    //   5694: ldc 268697600
    //   5696: iastore
    //   5697: dup
    //   5698: bipush #44
    //   5700: ldc 268697664
    //   5702: iastore
    //   5703: dup
    //   5704: bipush #45
    //   5706: ldc 268435456
    //   5708: iastore
    //   5709: dup
    //   5710: bipush #46
    //   5712: ldc 262144
    //   5714: iastore
    //   5715: dup
    //   5716: bipush #47
    //   5718: ldc 268439616
    //   5720: iastore
    //   5721: dup
    //   5722: bipush #48
    //   5724: iconst_0
    //   5725: iastore
    //   5726: dup
    //   5727: bipush #49
    //   5729: ldc 268701760
    //   5731: iastore
    //   5732: dup
    //   5733: bipush #50
    //   5735: ldc 262208
    //   5737: iastore
    //   5738: dup
    //   5739: bipush #51
    //   5741: ldc 268435520
    //   5743: iastore
    //   5744: dup
    //   5745: bipush #52
    //   5747: ldc 268697600
    //   5749: iastore
    //   5750: dup
    //   5751: bipush #53
    //   5753: ldc 268439552
    //   5755: iastore
    //   5756: dup
    //   5757: bipush #54
    //   5759: ldc 268439616
    //   5761: iastore
    //   5762: dup
    //   5763: bipush #55
    //   5765: iconst_0
    //   5766: iastore
    //   5767: dup
    //   5768: bipush #56
    //   5770: ldc 268701760
    //   5772: iastore
    //   5773: dup
    //   5774: bipush #57
    //   5776: ldc 266240
    //   5778: iastore
    //   5779: dup
    //   5780: bipush #58
    //   5782: ldc 266240
    //   5784: iastore
    //   5785: dup
    //   5786: bipush #59
    //   5788: sipush #4160
    //   5791: iastore
    //   5792: dup
    //   5793: bipush #60
    //   5795: sipush #4160
    //   5798: iastore
    //   5799: dup
    //   5800: bipush #61
    //   5802: ldc 262208
    //   5804: iastore
    //   5805: dup
    //   5806: bipush #62
    //   5808: ldc 268435456
    //   5810: iastore
    //   5811: dup
    //   5812: bipush #63
    //   5814: ldc 268701696
    //   5816: iastore
    //   5817: astore #13
    //   5819: aload_3
    //   5820: arraylength
    //   5821: istore #14
    //   5823: iload #14
    //   5825: bipush #8
    //   5827: irem
    //   5828: ifeq -> 5852
    //   5831: new java/lang/Exception
    //   5834: dup
    //   5835: sipush #24149
    //   5838: sipush #12981
    //   5841: invokestatic a : (II)Ljava/lang/String;
    //   5844: invokespecial <init> : (Ljava/lang/String;)V
    //   5847: athrow
    //   5848: invokestatic a : (Ljava/lang/Throwable;)Ljava/lang/Throwable;
    //   5851: athrow
    //   5852: iconst_2
    //   5853: newarray int
    //   5855: astore #15
    //   5857: iload #14
    //   5859: newarray byte
    //   5861: astore #16
    //   5863: iload #14
    //   5865: bipush #8
    //   5867: idiv
    //   5868: istore #17
    //   5870: iconst_0
    //   5871: istore #18
    //   5873: iload #18
    //   5875: iload #17
    //   5877: if_icmpge -> 6791
    //   5880: iload #18
    //   5882: bipush #8
    //   5884: imul
    //   5885: istore #19
    //   5887: iconst_0
    //   5888: istore #20
    //   5890: iload #20
    //   5892: iconst_2
    //   5893: if_icmpge -> 5978
    //   5896: aload #15
    //   5898: iload #20
    //   5900: aload_3
    //   5901: iload #19
    //   5903: iload #20
    //   5905: iconst_4
    //   5906: imul
    //   5907: iadd
    //   5908: baload
    //   5909: sipush #255
    //   5912: iand
    //   5913: bipush #24
    //   5915: ishl
    //   5916: aload_3
    //   5917: iload #19
    //   5919: iload #20
    //   5921: iconst_4
    //   5922: imul
    //   5923: iadd
    //   5924: iconst_1
    //   5925: iadd
    //   5926: baload
    //   5927: sipush #255
    //   5930: iand
    //   5931: bipush #16
    //   5933: ishl
    //   5934: ior
    //   5935: aload_3
    //   5936: iload #19
    //   5938: iload #20
    //   5940: iconst_4
    //   5941: imul
    //   5942: iadd
    //   5943: iconst_2
    //   5944: iadd
    //   5945: baload
    //   5946: sipush #255
    //   5949: iand
    //   5950: bipush #8
    //   5952: ishl
    //   5953: ior
    //   5954: aload_3
    //   5955: iload #19
    //   5957: iload #20
    //   5959: iconst_4
    //   5960: imul
    //   5961: iadd
    //   5962: iconst_3
    //   5963: iadd
    //   5964: baload
    //   5965: sipush #255
    //   5968: iand
    //   5969: ior
    //   5970: iastore
    //   5971: iinc #20, 1
    //   5974: iload_2
    //   5975: ifne -> 5890
    //   5978: iconst_0
    //   5979: istore #25
    //   5981: aload #15
    //   5983: iconst_0
    //   5984: iaload
    //   5985: istore #23
    //   5987: aload #15
    //   5989: iconst_1
    //   5990: iaload
    //   5991: istore #22
    //   5993: iload #23
    //   5995: iconst_4
    //   5996: iushr
    //   5997: iload #22
    //   5999: ixor
    //   6000: ldc 252645135
    //   6002: iand
    //   6003: istore #21
    //   6005: iload #22
    //   6007: iload #21
    //   6009: ixor
    //   6010: istore #22
    //   6012: iload #23
    //   6014: iload #21
    //   6016: iconst_4
    //   6017: ishl
    //   6018: ixor
    //   6019: istore #23
    //   6021: iload #23
    //   6023: bipush #16
    //   6025: iushr
    //   6026: iload #22
    //   6028: ixor
    //   6029: ldc 65535
    //   6031: iand
    //   6032: istore #21
    //   6034: iload #22
    //   6036: iload #21
    //   6038: ixor
    //   6039: istore #22
    //   6041: iload #23
    //   6043: iload #21
    //   6045: bipush #16
    //   6047: ishl
    //   6048: ixor
    //   6049: istore #23
    //   6051: iload #22
    //   6053: iconst_2
    //   6054: iushr
    //   6055: iload #23
    //   6057: ixor
    //   6058: ldc 858993459
    //   6060: iand
    //   6061: istore #21
    //   6063: iload #23
    //   6065: iload #21
    //   6067: ixor
    //   6068: istore #23
    //   6070: iload #22
    //   6072: iload #21
    //   6074: iconst_2
    //   6075: ishl
    //   6076: ixor
    //   6077: istore #22
    //   6079: iload #22
    //   6081: bipush #8
    //   6083: iushr
    //   6084: iload #23
    //   6086: ixor
    //   6087: ldc 16711935
    //   6089: iand
    //   6090: istore #21
    //   6092: iload #23
    //   6094: iload #21
    //   6096: ixor
    //   6097: istore #23
    //   6099: iload #22
    //   6101: iload #21
    //   6103: bipush #8
    //   6105: ishl
    //   6106: ixor
    //   6107: istore #22
    //   6109: iload #22
    //   6111: iconst_1
    //   6112: ishl
    //   6113: iload #22
    //   6115: bipush #31
    //   6117: iushr
    //   6118: iconst_1
    //   6119: iand
    //   6120: ior
    //   6121: istore #22
    //   6123: iload #23
    //   6125: iload #22
    //   6127: ixor
    //   6128: ldc -1431655766
    //   6130: iand
    //   6131: istore #21
    //   6133: iload #23
    //   6135: iload #21
    //   6137: ixor
    //   6138: istore #23
    //   6140: iload #22
    //   6142: iload #21
    //   6144: ixor
    //   6145: istore #22
    //   6147: iload #23
    //   6149: iconst_1
    //   6150: ishl
    //   6151: iload #23
    //   6153: bipush #31
    //   6155: iushr
    //   6156: iconst_1
    //   6157: iand
    //   6158: ior
    //   6159: istore #23
    //   6161: iconst_0
    //   6162: istore #24
    //   6164: iload #24
    //   6166: bipush #8
    //   6168: if_icmpge -> 6506
    //   6171: iload #22
    //   6173: bipush #28
    //   6175: ishl
    //   6176: iload #22
    //   6178: iconst_4
    //   6179: iushr
    //   6180: ior
    //   6181: istore #21
    //   6183: iload #21
    //   6185: aload #5
    //   6187: iload #25
    //   6189: iinc #25, 1
    //   6192: iaload
    //   6193: ixor
    //   6194: istore #21
    //   6196: aload #12
    //   6198: iload #21
    //   6200: bipush #63
    //   6202: iand
    //   6203: iaload
    //   6204: istore #20
    //   6206: iload #20
    //   6208: aload #10
    //   6210: iload #21
    //   6212: bipush #8
    //   6214: iushr
    //   6215: bipush #63
    //   6217: iand
    //   6218: iaload
    //   6219: ior
    //   6220: istore #20
    //   6222: iload #20
    //   6224: aload #8
    //   6226: iload #21
    //   6228: bipush #16
    //   6230: iushr
    //   6231: bipush #63
    //   6233: iand
    //   6234: iaload
    //   6235: ior
    //   6236: istore #20
    //   6238: iload #20
    //   6240: aload #6
    //   6242: iload #21
    //   6244: bipush #24
    //   6246: iushr
    //   6247: bipush #63
    //   6249: iand
    //   6250: iaload
    //   6251: ior
    //   6252: istore #20
    //   6254: iload #22
    //   6256: aload #5
    //   6258: iload #25
    //   6260: iinc #25, 1
    //   6263: iaload
    //   6264: ixor
    //   6265: istore #21
    //   6267: iload #20
    //   6269: aload #13
    //   6271: iload #21
    //   6273: bipush #63
    //   6275: iand
    //   6276: iaload
    //   6277: ior
    //   6278: istore #20
    //   6280: iload #20
    //   6282: aload #11
    //   6284: iload #21
    //   6286: bipush #8
    //   6288: iushr
    //   6289: bipush #63
    //   6291: iand
    //   6292: iaload
    //   6293: ior
    //   6294: istore #20
    //   6296: iload #20
    //   6298: aload #9
    //   6300: iload #21
    //   6302: bipush #16
    //   6304: iushr
    //   6305: bipush #63
    //   6307: iand
    //   6308: iaload
    //   6309: ior
    //   6310: istore #20
    //   6312: iload #20
    //   6314: aload #7
    //   6316: iload #21
    //   6318: bipush #24
    //   6320: iushr
    //   6321: bipush #63
    //   6323: iand
    //   6324: iaload
    //   6325: ior
    //   6326: istore #20
    //   6328: iload #23
    //   6330: iload #20
    //   6332: ixor
    //   6333: istore #23
    //   6335: iload #23
    //   6337: bipush #28
    //   6339: ishl
    //   6340: iload #23
    //   6342: iconst_4
    //   6343: iushr
    //   6344: ior
    //   6345: istore #21
    //   6347: iload #21
    //   6349: aload #5
    //   6351: iload #25
    //   6353: iinc #25, 1
    //   6356: iaload
    //   6357: ixor
    //   6358: istore #21
    //   6360: aload #12
    //   6362: iload #21
    //   6364: bipush #63
    //   6366: iand
    //   6367: iaload
    //   6368: istore #20
    //   6370: iload #20
    //   6372: aload #10
    //   6374: iload #21
    //   6376: bipush #8
    //   6378: iushr
    //   6379: bipush #63
    //   6381: iand
    //   6382: iaload
    //   6383: ior
    //   6384: istore #20
    //   6386: iload #20
    //   6388: aload #8
    //   6390: iload #21
    //   6392: bipush #16
    //   6394: iushr
    //   6395: bipush #63
    //   6397: iand
    //   6398: iaload
    //   6399: ior
    //   6400: istore #20
    //   6402: iload #20
    //   6404: aload #6
    //   6406: iload #21
    //   6408: bipush #24
    //   6410: iushr
    //   6411: bipush #63
    //   6413: iand
    //   6414: iaload
    //   6415: ior
    //   6416: istore #20
    //   6418: iload #23
    //   6420: aload #5
    //   6422: iload #25
    //   6424: iinc #25, 1
    //   6427: iaload
    //   6428: ixor
    //   6429: istore #21
    //   6431: iload #20
    //   6433: aload #13
    //   6435: iload #21
    //   6437: bipush #63
    //   6439: iand
    //   6440: iaload
    //   6441: ior
    //   6442: istore #20
    //   6444: iload #20
    //   6446: aload #11
    //   6448: iload #21
    //   6450: bipush #8
    //   6452: iushr
    //   6453: bipush #63
    //   6455: iand
    //   6456: iaload
    //   6457: ior
    //   6458: istore #20
    //   6460: iload #20
    //   6462: aload #9
    //   6464: iload #21
    //   6466: bipush #16
    //   6468: iushr
    //   6469: bipush #63
    //   6471: iand
    //   6472: iaload
    //   6473: ior
    //   6474: istore #20
    //   6476: iload #20
    //   6478: aload #7
    //   6480: iload #21
    //   6482: bipush #24
    //   6484: iushr
    //   6485: bipush #63
    //   6487: iand
    //   6488: iaload
    //   6489: ior
    //   6490: istore #20
    //   6492: iload #22
    //   6494: iload #20
    //   6496: ixor
    //   6497: istore #22
    //   6499: iinc #24, 1
    //   6502: iload_2
    //   6503: ifne -> 6164
    //   6506: iload #22
    //   6508: bipush #31
    //   6510: ishl
    //   6511: iload #22
    //   6513: iconst_1
    //   6514: iushr
    //   6515: ior
    //   6516: istore #22
    //   6518: iload #23
    //   6520: iload #22
    //   6522: ixor
    //   6523: ldc -1431655766
    //   6525: iand
    //   6526: istore #21
    //   6528: iload #23
    //   6530: iload #21
    //   6532: ixor
    //   6533: istore #23
    //   6535: iload #22
    //   6537: iload #21
    //   6539: ixor
    //   6540: istore #22
    //   6542: iload #23
    //   6544: bipush #31
    //   6546: ishl
    //   6547: iload #23
    //   6549: iconst_1
    //   6550: iushr
    //   6551: ior
    //   6552: istore #23
    //   6554: iload #23
    //   6556: bipush #8
    //   6558: iushr
    //   6559: iload #22
    //   6561: ixor
    //   6562: ldc 16711935
    //   6564: iand
    //   6565: istore #21
    //   6567: iload #22
    //   6569: iload #21
    //   6571: ixor
    //   6572: istore #22
    //   6574: iload #23
    //   6576: iload #21
    //   6578: bipush #8
    //   6580: ishl
    //   6581: ixor
    //   6582: istore #23
    //   6584: iload #23
    //   6586: iconst_2
    //   6587: iushr
    //   6588: iload #22
    //   6590: ixor
    //   6591: ldc 858993459
    //   6593: iand
    //   6594: istore #21
    //   6596: iload #22
    //   6598: iload #21
    //   6600: ixor
    //   6601: istore #22
    //   6603: iload #23
    //   6605: iload #21
    //   6607: iconst_2
    //   6608: ishl
    //   6609: ixor
    //   6610: istore #23
    //   6612: iload #22
    //   6614: bipush #16
    //   6616: iushr
    //   6617: iload #23
    //   6619: ixor
    //   6620: ldc 65535
    //   6622: iand
    //   6623: istore #21
    //   6625: iload #23
    //   6627: iload #21
    //   6629: ixor
    //   6630: istore #23
    //   6632: iload #22
    //   6634: iload #21
    //   6636: bipush #16
    //   6638: ishl
    //   6639: ixor
    //   6640: istore #22
    //   6642: iload #22
    //   6644: iconst_4
    //   6645: iushr
    //   6646: iload #23
    //   6648: ixor
    //   6649: ldc 252645135
    //   6651: iand
    //   6652: istore #21
    //   6654: iload #23
    //   6656: iload #21
    //   6658: ixor
    //   6659: istore #23
    //   6661: iload #22
    //   6663: iload #21
    //   6665: iconst_4
    //   6666: ishl
    //   6667: ixor
    //   6668: istore #22
    //   6670: aload #15
    //   6672: iconst_0
    //   6673: iload #22
    //   6675: iastore
    //   6676: aload #15
    //   6678: iconst_1
    //   6679: iload #23
    //   6681: iastore
    //   6682: iload #18
    //   6684: bipush #8
    //   6686: imul
    //   6687: istore #26
    //   6689: iconst_0
    //   6690: istore #27
    //   6692: iload #27
    //   6694: iconst_2
    //   6695: if_icmpge -> 6784
    //   6698: aload #16
    //   6700: iload #26
    //   6702: iload #27
    //   6704: iconst_4
    //   6705: imul
    //   6706: iadd
    //   6707: aload #15
    //   6709: iload #27
    //   6711: iaload
    //   6712: bipush #24
    //   6714: iushr
    //   6715: i2b
    //   6716: bastore
    //   6717: aload #16
    //   6719: iload #26
    //   6721: iload #27
    //   6723: iconst_4
    //   6724: imul
    //   6725: iadd
    //   6726: iconst_1
    //   6727: iadd
    //   6728: aload #15
    //   6730: iload #27
    //   6732: iaload
    //   6733: bipush #16
    //   6735: iushr
    //   6736: i2b
    //   6737: bastore
    //   6738: aload #16
    //   6740: iload #26
    //   6742: iload #27
    //   6744: iconst_4
    //   6745: imul
    //   6746: iadd
    //   6747: iconst_2
    //   6748: iadd
    //   6749: aload #15
    //   6751: iload #27
    //   6753: iaload
    //   6754: bipush #8
    //   6756: iushr
    //   6757: i2b
    //   6758: bastore
    //   6759: aload #16
    //   6761: iload #26
    //   6763: iload #27
    //   6765: iconst_4
    //   6766: imul
    //   6767: iadd
    //   6768: iconst_3
    //   6769: iadd
    //   6770: aload #15
    //   6772: iload #27
    //   6774: iaload
    //   6775: i2b
    //   6776: bastore
    //   6777: iinc #27, 1
    //   6780: iload_2
    //   6781: ifne -> 6692
    //   6784: iinc #18, 1
    //   6787: iload_2
    //   6788: ifne -> 5873
    //   6791: aload #16
    //   6793: aload #16
    //   6795: arraylength
    //   6796: iconst_1
    //   6797: isub
    //   6798: baload
    //   6799: istore #18
    //   6801: aload #16
    //   6803: arraylength
    //   6804: iload #18
    //   6806: isub
    //   6807: newarray byte
    //   6809: astore #4
    //   6811: aload #16
    //   6813: arraylength
    //   6814: aload #4
    //   6816: arraylength
    //   6817: if_icmpge -> 6841
    //   6820: new java/lang/Exception
    //   6823: dup
    //   6824: sipush #24149
    //   6827: sipush #12981
    //   6830: invokestatic a : (II)Ljava/lang/String;
    //   6833: invokespecial <init> : (Ljava/lang/String;)V
    //   6836: athrow
    //   6837: invokestatic a : (Ljava/lang/Throwable;)Ljava/lang/Throwable;
    //   6840: athrow
    //   6841: iconst_0
    //   6842: istore #19
    //   6844: iload #19
    //   6846: aload #4
    //   6848: arraylength
    //   6849: if_icmpge -> 6869
    //   6852: aload #4
    //   6854: iload #19
    //   6856: aload #16
    //   6858: iload #19
    //   6860: baload
    //   6861: bastore
    //   6862: iinc #19, 1
    //   6865: iload_2
    //   6866: ifne -> 6844
    //   6869: new java/math/BigInteger
    //   6872: dup
    //   6873: aload #4
    //   6875: invokespecial <init> : ([B)V
    //   6878: invokevirtual abs : ()Ljava/math/BigInteger;
    //   6881: putstatic burp/Zvo3.Ze : Ljava/lang/Object;
    //   6884: sipush #24146
    //   6887: getstatic burp/Zzoi.ZI : Ljava/lang/Object;
    //   6890: checkcast java/math/BigInteger
    //   6893: getstatic burp/Zgqi.Zp : Ljava/lang/Object;
    //   6896: checkcast java/math/BigInteger
    //   6899: invokevirtual add : (Ljava/math/BigInteger;)Ljava/math/BigInteger;
    //   6902: putstatic burp/Zeb7.ZJ : Ljava/lang/Object;
    //   6905: sipush #-9826
    //   6908: invokestatic a : (II)Ljava/lang/String;
    //   6911: iconst_1
    //   6912: ldc burp/Ztys
    //   6914: invokevirtual getClassLoader : ()Ljava/lang/ClassLoader;
    //   6917: invokestatic forName : (Ljava/lang/String;ZLjava/lang/ClassLoader;)Ljava/lang/Class;
    //   6920: invokevirtual getDeclaredFields : ()[Ljava/lang/reflect/Field;
    //   6923: astore_3
    //   6924: aload_3
    //   6925: arraylength
    //   6926: istore #4
    //   6928: iconst_0
    //   6929: istore #5
    //   6931: iload #5
    //   6933: iload #4
    //   6935: if_icmpge -> 7072
    //   6938: aload_3
    //   6939: iload #5
    //   6941: aaload
    //   6942: astore #6
    //   6944: aload #6
    //   6946: invokevirtual getModifiers : ()I
    //   6949: invokestatic isStatic : (I)Z
    //   6952: ifne -> 6962
    //   6955: goto -> 7065
    //   6958: invokestatic a : (Ljava/lang/Throwable;)Ljava/lang/Throwable;
    //   6961: athrow
    //   6962: aload #6
    //   6964: invokevirtual getType : ()Ljava/lang/Class;
    //   6967: astore #7
    //   6969: aload #7
    //   6971: ifnull -> 7052
    //   6974: aload #7
    //   6976: invokevirtual isPrimitive : ()Z
    //   6979: ifne -> 7052
    //   6982: goto -> 6989
    //   6985: invokestatic a : (Ljava/lang/Throwable;)Ljava/lang/Throwable;
    //   6988: athrow
    //   6989: aload #7
    //   6991: invokevirtual getPackage : ()Ljava/lang/Package;
    //   6994: ifnull -> 7052
    //   6997: goto -> 7004
    //   7000: invokestatic a : (Ljava/lang/Throwable;)Ljava/lang/Throwable;
    //   7003: athrow
    //   7004: aload #7
    //   7006: invokevirtual getPackage : ()Ljava/lang/Package;
    //   7009: invokevirtual getName : ()Ljava/lang/String;
    //   7012: ifnull -> 7052
    //   7015: goto -> 7022
    //   7018: invokestatic a : (Ljava/lang/Throwable;)Ljava/lang/Throwable;
    //   7021: athrow
    //   7022: aload #7
    //   7024: invokevirtual getPackage : ()Ljava/lang/Package;
    //   7027: invokevirtual getName : ()Ljava/lang/String;
    //   7030: sipush #24153
    //   7033: sipush #14940
    //   7036: invokestatic a : (II)Ljava/lang/String;
    //   7039: invokevirtual startsWith : (Ljava/lang/String;)Z
    //   7042: ifne -> 7052
    //   7045: goto -> 7052
    //   7048: invokestatic a : (Ljava/lang/Throwable;)Ljava/lang/Throwable;
    //   7051: athrow
    //   7052: aload #6
    //   7054: iconst_1
    //   7055: invokevirtual setAccessible : (Z)V
    //   7058: aload #6
    //   7060: aconst_null
    //   7061: invokevirtual get : (Ljava/lang/Object;)Ljava/lang/Object;
    //   7064: pop
    //   7065: iinc #5, 1
    //   7068: iload_2
    //   7069: ifne -> 6931
    //   7072: sipush #24152
    //   7075: sipush #30125
    //   7078: invokestatic a : (II)Ljava/lang/String;
    //   7081: invokestatic forName : (Ljava/lang/String;)Ljava/lang/Class;
    //   7084: invokevirtual getDeclaredMethods : ()[Ljava/lang/reflect/Method;
    //   7087: astore_3
    //   7088: aload_3
    //   7089: arraylength
    //   7090: istore #4
    //   7092: iconst_0
    //   7093: istore #5
    //   7095: iload #5
    //   7097: iload #4
    //   7099: if_icmpge -> 7231
    //   7102: aload_3
    //   7103: iload #5
    //   7105: aaload
    //   7106: astore #6
    //   7108: aload #6
    //   7110: invokevirtual getParameterTypes : ()[Ljava/lang/Class;
    //   7113: pop
    //   7114: aload #6
    //   7116: invokevirtual getModifiers : ()I
    //   7119: invokestatic isStatic : (I)Z
    //   7122: ifeq -> 7217
    //   7125: aload #6
    //   7127: invokevirtual getParameterTypes : ()[Ljava/lang/Class;
    //   7130: arraylength
    //   7131: iconst_2
    //   7132: if_icmpne -> 7217
    //   7135: goto -> 7142
    //   7138: invokestatic a : (Ljava/lang/Throwable;)Ljava/lang/Throwable;
    //   7141: athrow
    //   7142: aload #6
    //   7144: invokevirtual getReturnType : ()Ljava/lang/Class;
    //   7147: getstatic java/lang/Void.TYPE : Ljava/lang/Class;
    //   7150: invokevirtual equals : (Ljava/lang/Object;)Z
    //   7153: ifeq -> 7217
    //   7156: goto -> 7163
    //   7159: invokestatic a : (Ljava/lang/Throwable;)Ljava/lang/Throwable;
    //   7162: athrow
    //   7163: aload #6
    //   7165: iconst_1
    //   7166: invokevirtual setAccessible : (Z)V
    //   7169: aload #6
    //   7171: aconst_null
    //   7172: iconst_2
    //   7173: anewarray java/lang/Object
    //   7176: dup
    //   7177: iconst_0
    //   7178: aload_0
    //   7179: aastore
    //   7180: dup
    //   7181: iconst_1
    //   7182: aload_1
    //   7183: ifnonnull -> 7201
    //   7186: goto -> 7193
    //   7189: invokestatic a : (Ljava/lang/Throwable;)Ljava/lang/Throwable;
    //   7192: athrow
    //   7193: aload_1
    //   7194: goto -> 7208
    //   7197: invokestatic a : (Ljava/lang/Throwable;)Ljava/lang/Throwable;
    //   7200: athrow
    //   7201: aload_1
    //   7202: checkcast [B
    //   7205: invokevirtual clone : ()Ljava/lang/Object;
    //   7208: aastore
    //   7209: invokevirtual invoke : (Ljava/lang/Object;[Ljava/lang/Object;)Ljava/lang/Object;
    //   7212: pop
    //   7213: iload_2
    //   7214: ifne -> 7231
    //   7217: iinc #5, 1
    //   7220: iload_2
    //   7221: ifne -> 7095
    //   7224: goto -> 7231
    //   7227: invokestatic a : (Ljava/lang/Throwable;)Ljava/lang/Throwable;
    //   7230: athrow
    //   7231: getstatic burp/Zl8f.ZK : Ljava/lang/String;
    //   7234: getstatic burp/Zm6h.ZB : Ljava/lang/Object;
    //   7237: checkcast java/math/BigInteger
    //   7240: invokevirtual intValue : ()I
    //   7243: bipush #32
    //   7245: irem
    //   7246: invokestatic abs : (I)I
    //   7249: invokevirtual charAt : (I)C
    //   7252: getstatic burp/Zeb7.ZH : Ljava/lang/String;
    //   7255: getstatic burp/Zgzv.Zb : Ljava/lang/Object;
    //   7258: checkcast java/math/BigInteger
    //   7261: invokevirtual intValue : ()I
    //   7264: bipush #32
    //   7266: irem
    //   7267: invokestatic abs : (I)I
    //   7270: invokevirtual charAt : (I)C
    //   7273: if_icmple -> 7388
    //   7276: getstatic burp/Zr48.ZG : Ljava/lang/String;
    //   7279: getstatic burp/Zm3p.Zz : Ljava/lang/Object;
    //   7282: checkcast java/math/BigInteger
    //   7285: invokevirtual intValue : ()I
    //   7288: bipush #32
    //   7290: irem
    //   7291: invokestatic abs : (I)I
    //   7294: invokevirtual charAt : (I)C
    //   7297: getstatic burp/Zlh8.ZY : Ljava/lang/String;
    //   7300: getstatic burp/Zkt7.ZY : Ljava/lang/Object;
    //   7303: checkcast java/math/BigInteger
    //   7306: invokevirtual intValue : ()I
    //   7309: bipush #32
    //   7311: irem
    //   7312: invokestatic abs : (I)I
    //   7315: invokevirtual charAt : (I)C
    //   7318: if_icmple -> 7388
    //   7321: goto -> 7328
    //   7324: invokestatic a : (Ljava/lang/Throwable;)Ljava/lang/Throwable;
    //   7327: athrow
    //   7328: getstatic burp/Zlh8.ZY : Ljava/lang/String;
    //   7331: getstatic burp/Zz6t.ZA : Ljava/lang/Object;
    //   7334: checkcast java/math/BigInteger
    //   7337: invokevirtual intValue : ()I
    //   7340: bipush #32
    //   7342: irem
    //   7343: invokestatic abs : (I)I
    //   7346: invokevirtual charAt : (I)C
    //   7349: getstatic burp/Zlo5.ZJ : Ljava/lang/String;
    //   7352: getstatic burp/Zvo3.Ze : Ljava/lang/Object;
    //   7355: checkcast java/math/BigInteger
    //   7358: invokevirtual intValue : ()I
    //   7361: bipush #32
    //   7363: irem
    //   7364: invokestatic abs : (I)I
    //   7367: invokevirtual charAt : (I)C
    //   7370: if_icmple -> 7388
    //   7373: goto -> 7380
    //   7376: invokestatic a : (Ljava/lang/Throwable;)Ljava/lang/Throwable;
    //   7379: athrow
    //   7380: iconst_1
    //   7381: goto -> 7389
    //   7384: invokestatic a : (Ljava/lang/Throwable;)Ljava/lang/Throwable;
    //   7387: athrow
    //   7388: iconst_0
    //   7389: ireturn
    //   7390: astore_3
    //   7391: new java/lang/Exception
    //   7394: dup
    //   7395: aload_3
    //   7396: invokevirtual getMessage : ()Ljava/lang/String;
    //   7399: invokespecial <init> : (Ljava/lang/String;)V
    //   7402: athrow
    // Exception table:
    //   from	to	target	type
    //   4	7389	7390	java/lang/Throwable
    //   149	164	164	java/lang/Throwable
    //   1166	1192	1192	java/lang/Throwable
    //   1273	1288	1288	java/lang/Throwable
    //   2470	2495	2498	java/lang/Throwable
    //   5823	5848	5848	java/lang/Throwable
    //   6811	6837	6837	java/lang/Throwable
    //   6944	6958	6958	java/lang/Throwable
    //   6969	6982	6985	java/lang/Throwable
    //   6974	6997	7000	java/lang/Throwable
    //   6989	7015	7018	java/lang/Throwable
    //   7004	7045	7048	java/lang/Throwable
    //   7108	7135	7138	java/lang/Throwable
    //   7125	7156	7159	java/lang/Throwable
    //   7142	7186	7189	java/lang/Throwable
    //   7163	7197	7197	java/lang/Throwable
    //   7208	7224	7227	java/lang/Throwable
    //   7231	7321	7324	java/lang/Throwable
    //   7276	7373	7376	java/lang/Throwable
    //   7328	7384	7384	java/lang/Throwable
  }
  
  static void ZO(Object paramObject) {
    Zz6t.Zx = a(24144, 28045);
    Zz6t.ZA = new BigInteger(a(24148, -14318));
    boolean bool = Zt2e.ZN();
    try {
      try {
        if (Zs2n.ZI.charAt(Math.abs(((BigInteger)Ze5f.Zh).intValue() % 32)) > Zl50.Zm.charAt(Math.abs(((BigInteger)Zix.ZO).intValue() % 32))) {
          try {
            Zm7x.Zb(Class.forName(a(24147, -9412)));
            if (!bool)
              Zllw.ZZ(Class.forName(a(24151, -10524))); 
          } catch (Throwable throwable) {
            throw a(null);
          } 
          return;
        } 
      } catch (Throwable throwable) {
        throw a(null);
      } 
      Zllw.ZZ(Class.forName(a(24151, -10524)));
    } catch (Throwable throwable) {}
  }
  
  static void ZU(Object[] paramArrayOfObject, Object paramObject) throws Throwable {}
  
  static {
    // Byte code:
    //   0: bipush #12
    //   2: anewarray java/lang/String
    //   5: astore #5
    //   7: iconst_0
    //   8: istore_3
    //   9: ldc '6;yyq.zzZ%G\\f{XX??\\t(mQkVC\\t/[t"MqUzGtba~}v=;1OJ;'fw$-m+;h/2uiXcLk\\f#\FVF\\tRul\\tTIo}'
    //   11: dup
    //   12: astore_2
    //   13: invokevirtual length : ()I
    //   16: istore #4
    //   18: bipush #32
    //   20: istore_1
    //   21: iconst_m1
    //   22: istore_0
    //   23: bipush #16
    //   25: iinc #0, 1
    //   28: aload_2
    //   29: iload_0
    //   30: dup
    //   31: iload_1
    //   32: iadd
    //   33: invokevirtual substring : (II)Ljava/lang/String;
    //   36: iconst_m1
    //   37: goto -> 143
    //   40: aload #5
    //   42: swap
    //   43: iload_3
    //   44: iinc #3, 1
    //   47: swap
    //   48: aastore
    //   49: iload_0
    //   50: iload_1
    //   51: iadd
    //   52: dup
    //   53: istore_0
    //   54: iload #4
    //   56: if_icmpge -> 68
    //   59: aload_2
    //   60: iload_0
    //   61: invokevirtual charAt : (I)C
    //   64: istore_1
    //   65: goto -> 23
    //   68: ldc '&p.bARLq\\bucK@??'
    //   70: dup
    //   71: astore_2
    //   72: invokevirtual length : ()I
    //   75: istore #4
    //   77: bipush #32
    //   79: istore_1
    //   80: iconst_m1
    //   81: istore_0
    //   82: bipush #97
    //   84: iinc #0, 1
    //   87: aload_2
    //   88: iload_0
    //   89: dup
    //   90: iload_1
    //   91: iadd
    //   92: invokevirtual substring : (II)Ljava/lang/String;
    //   95: iconst_0
    //   96: goto -> 143
    //   99: aload #5
    //   101: swap
    //   102: iload_3
    //   103: iinc #3, 1
    //   106: swap
    //   107: aastore
    //   108: iload_0
    //   109: iload_1
    //   110: iadd
    //   111: dup
    //   112: istore_0
    //   113: iload #4
    //   115: if_icmpge -> 127
    //   118: aload_2
    //   119: iload_0
    //   120: invokevirtual charAt : (I)C
    //   123: istore_1
    //   124: goto -> 82
    //   127: aload #5
    //   129: putstatic burp/Zb8y.a : [Ljava/lang/String;
    //   132: bipush #12
    //   134: anewarray java/lang/String
    //   137: putstatic burp/Zb8y.b : [Ljava/lang/String;
    //   140: goto -> 300
    //   143: dup_x2
    //   144: pop
    //   145: invokevirtual toCharArray : ()[C
    //   148: dup_x1
    //   149: arraylength
    //   150: dup_x2
    //   151: pop
    //   152: iconst_0
    //   153: istore #6
    //   155: dup2_x1
    //   156: pop2
    //   157: dup_x2
    //   158: iconst_1
    //   159: if_icmpgt -> 260
    //   162: dup2
    //   163: swap
    //   164: iload #6
    //   166: dup2_x1
    //   167: caload
    //   168: swap
    //   169: iload #6
    //   171: bipush #7
    //   173: irem
    //   174: tableswitch default -> 242, 0 -> 212, 1 -> 217, 2 -> 222, 3 -> 227, 4 -> 232, 5 -> 237
    //   212: bipush #91
    //   214: goto -> 244
    //   217: bipush #52
    //   219: goto -> 244
    //   222: bipush #113
    //   224: goto -> 244
    //   227: bipush #124
    //   229: goto -> 244
    //   232: bipush #111
    //   234: goto -> 244
    //   237: bipush #50
    //   239: goto -> 244
    //   242: bipush #12
    //   244: ixor
    //   245: ixor
    //   246: i2c
    //   247: castore
    //   248: iinc #6, 1
    //   251: dup
    //   252: ifne -> 260
    //   255: dup2
    //   256: dup_x1
    //   257: goto -> 166
    //   260: dup2_x1
    //   261: pop2
    //   262: dup_x2
    //   263: iload #6
    //   265: if_icmpgt -> 162
    //   268: pop
    //   269: new java/lang/String
    //   272: dup_x1
    //   273: swap
    //   274: invokespecial <init> : ([C)V
    //   277: invokevirtual intern : ()Ljava/lang/String;
    //   280: swap
    //   281: pop
    //   282: swap
    //   283: tableswitch default -> 40, 0 -> 99
    //   300: new java/math/BigInteger
    //   303: dup
    //   304: bipush #32
    //   306: newarray byte
    //   308: dup
    //   309: iconst_0
    //   310: bipush #25
    //   312: bastore
    //   313: dup
    //   314: iconst_1
    //   315: bipush #85
    //   317: bastore
    //   318: dup
    //   319: iconst_2
    //   320: bipush #-114
    //   322: bastore
    //   323: dup
    //   324: iconst_3
    //   325: bipush #-70
    //   327: bastore
    //   328: dup
    //   329: iconst_4
    //   330: bipush #65
    //   332: bastore
    //   333: dup
    //   334: iconst_5
    //   335: bipush #-75
    //   337: bastore
    //   338: dup
    //   339: bipush #6
    //   341: bipush #-75
    //   343: bastore
    //   344: dup
    //   345: bipush #7
    //   347: bipush #-99
    //   349: bastore
    //   350: dup
    //   351: bipush #8
    //   353: bipush #103
    //   355: bastore
    //   356: dup
    //   357: bipush #9
    //   359: bipush #123
    //   361: bastore
    //   362: dup
    //   363: bipush #10
    //   365: bipush #-33
    //   367: bastore
    //   368: dup
    //   369: bipush #11
    //   371: bipush #42
    //   373: bastore
    //   374: dup
    //   375: bipush #12
    //   377: bipush #23
    //   379: bastore
    //   380: dup
    //   381: bipush #13
    //   383: bipush #-21
    //   385: bastore
    //   386: dup
    //   387: bipush #14
    //   389: bipush #-21
    //   391: bastore
    //   392: dup
    //   393: bipush #15
    //   395: bipush #-61
    //   397: bastore
    //   398: dup
    //   399: bipush #16
    //   401: bipush #-72
    //   403: bastore
    //   404: dup
    //   405: bipush #17
    //   407: bipush #-82
    //   409: bastore
    //   410: dup
    //   411: bipush #18
    //   413: bipush #41
    //   415: bastore
    //   416: dup
    //   417: bipush #19
    //   419: bipush #-92
    //   421: bastore
    //   422: dup
    //   423: bipush #20
    //   425: bipush #-19
    //   427: bastore
    //   428: dup
    //   429: bipush #21
    //   431: bipush #97
    //   433: bastore
    //   434: dup
    //   435: bipush #22
    //   437: iconst_2
    //   438: bastore
    //   439: dup
    //   440: bipush #23
    //   442: bipush #-57
    //   444: bastore
    //   445: dup
    //   446: bipush #24
    //   448: bipush #46
    //   450: bastore
    //   451: dup
    //   452: bipush #25
    //   454: bipush #-6
    //   456: bastore
    //   457: dup
    //   458: bipush #26
    //   460: bipush #98
    //   462: bastore
    //   463: dup
    //   464: bipush #27
    //   466: bipush #39
    //   468: bastore
    //   469: dup
    //   470: bipush #28
    //   472: bipush #102
    //   474: bastore
    //   475: dup
    //   476: bipush #29
    //   478: bipush #-118
    //   480: bastore
    //   481: dup
    //   482: bipush #30
    //   484: bipush #-32
    //   486: bastore
    //   487: dup
    //   488: bipush #31
    //   490: bipush #109
    //   492: bastore
    //   493: invokespecial <init> : ([B)V
    //   496: putstatic burp/Zb8y.ZI : Ljava/lang/Object;
    //   499: sipush #24154
    //   502: sipush #25008
    //   505: invokestatic a : (II)Ljava/lang/String;
    //   508: putstatic burp/Zb8y.Zn : Ljava/lang/String;
    //   511: return
  }
  
  private static Throwable a(Throwable paramThrowable) {
    return paramThrowable;
  }
  
  private static String a(int paramInt1, int paramInt2) {
    int i = (paramInt1 ^ 0x5E50) & 0xFFFF;
    if (b[i] == null) {
      char[] arrayOfChar = a[i].toCharArray();
      switch (arrayOfChar[0] & 0xFF) {
        case 0:
        
        case 1:
        
        case 2:
        
        case 3:
        
        case 4:
        
        case 5:
        
        case 6:
        
        case 7:
        
        case 8:
        
        case 9:
        
        case 10:
        
        case 11:
        
        case 12:
        
        case 13:
        
        case 14:
        
        case 15:
        
        case 16:
        
        case 17:
        
        case 18:
        
        case 19:
        
        case 20:
        
        case 21:
        
        case 22:
        
        case 23:
        
        case 24:
        
        case 25:
        
        case 26:
        
        case 27:
        
        case 28:
        
        case 29:
        
        case 30:
        
        case 31:
        
        case 32:
        
        case 33:
        
        case 34:
        
        case 35:
        
        case 36:
        
        case 37:
        
        case 38:
        
        case 39:
        
        case 40:
        
        case 41:
        
        case 42:
        
        case 43:
        
        case 44:
        
        case 45:
        
        case 46:
        
        case 47:
        
        case 48:
        
        case 49:
        
        case 50:
        
        case 51:
        
        case 52:
        
        case 53:
        
        case 54:
        
        case 55:
        
        case 56:
        
        case 57:
        
        case 58:
        
        case 59:
        
        case 60:
        
        case 61:
        
        case 62:
        
        case 63:
        
        case 64:
        
        case 65:
        
        case 66:
        
        case 67:
        
        case 68:
        
        case 69:
        
        case 70:
        
        case 71:
        
        case 72:
        
        case 73:
        
        case 74:
        
        case 75:
        
        case 76:
        
        case 77:
        
        case 78:
        
        case 79:
        
        case 80:
        
        case 81:
        
        case 82:
        
        case 83:
        
        case 84:
        
        case 85:
        
        case 86:
        
        case 87:
        
        case 88:
        
        case 89:
        
        case 90:
        
        case 91:
        
        case 92:
        
        case 93:
        
        case 94:
        
        case 95:
        
        case 96:
        
        case 97:
        
        case 98:
        
        case 99:
        
        case 100:
        
        case 101:
        
        case 102:
        
        case 103:
        
        case 104:
        
        case 105:
        
        case 106:
        
        case 107:
        
        case 108:
        
        case 109:
        
        case 110:
        
        case 111:
        
        case 112:
        
        case 113:
        
        case 114:
        
        case 115:
        
        case 116:
        
        case 117:
        
        case 118:
        
        case 119:
        
        case 120:
        
        case 121:
        
        case 122:
        
        case 123:
        
        case 124:
        
        case 125:
        
        case 126:
        
        case 127:
        
        case 128:
        
        case 129:
        
        case 130:
        
        case 131:
        
        case 132:
        
        case 133:
        
        case 134:
        
        case 135:
        
        case 136:
        
        case 137:
        
        case 138:
        
        case 139:
        
        case 140:
        
        case 141:
        
        case 142:
        
        case 143:
        
        case 144:
        
        case 145:
        
        case 146:
        
        case 147:
        
        case 148:
        
        case 149:
        
        case 150:
        
        case 151:
        
        case 152:
        
        case 153:
        
        case 154:
        
        case 155:
        
        case 156:
        
        case 157:
        
        case 158:
        
        case 159:
        
        case 160:
        
        case 161:
        
        case 162:
        
        case 163:
        
        case 164:
        
        case 165:
        
        case 166:
        
        case 167:
        
        case 168:
        
        case 169:
        
        case 170:
        
        case 171:
        
        case 172:
        
        case 173:
        
        case 174:
        
        case 175:
        
        case 176:
        
        case 177:
        
        case 178:
        
        case 179:
        
        case 180:
        
        case 181:
        
        case 182:
        
        case 183:
        
        case 184:
        
        case 185:
        
        case 186:
        
        case 187:
        
        case 188:
        
        case 189:
        
        case 190:
        
        case 191:
        
        case 192:
        
        case 193:
        
        case 194:
        
        case 195:
        
        case 196:
        
        case 197:
        
        case 198:
        
        case 199:
        
        case 200:
        
        case 201:
        
        case 202:
        
        case 203:
        
        case 204:
        
        case 205:
        
        case 206:
        
        case 207:
        
        case 208:
        
        case 209:
        
        case 210:
        
        case 211:
        
        case 212:
        
        case 213:
        
        case 214:
        
        case 215:
        
        case 216:
        
        case 217:
        
        case 218:
        
        case 219:
        
        case 220:
        
        case 221:
        
        case 222:
        
        case 223:
        
        case 224:
        
        case 225:
        
        case 226:
        
        case 227:
        
        case 228:
        
        case 229:
        
        case 230:
        
        case 231:
        
        case 232:
        
        case 233:
        
        case 234:
        
        case 235:
        
        case 236:
        
        case 237:
        
        case 238:
        
        case 239:
        
        case 240:
        
        case 241:
        
        case 242:
        
        case 243:
        
        case 244:
        
        case 245:
        
        case 246:
        
        case 247:
        
        case 248:
        
        case 249:
        
        case 250:
        
        case 251:
        
        case 252:
        
        case 253:
        
        case 254:
        
        default:
          break;
      } 
      char c = '';
      int j = (paramInt2 & 0xFF) - c;
      if (j < 0)
        j += 256; 
      int k = ((paramInt2 & 0xFFFF) >>> 8) - c;
      if (k < 0)
        k += 256; 
      for (byte b = 0; b < arrayOfChar.length; b++) {
        int m = b % 2;
        if (m == 0) {
          arrayOfChar[b] = (char)(arrayOfChar[b] ^ j);
          j = ((j >>> 3 | j << 5) ^ arrayOfChar[b]) & 0xFF;
        } else {
          arrayOfChar[b] = (char)(arrayOfChar[b] ^ k);
          k = ((k >>> 3 | k << 5) ^ arrayOfChar[b]) & 0xFF;
        } 
      } 
      b[i] = (new String(arrayOfChar)).intern();
    } 
    return b[i];
  }
}


/* Location:              C:\Program Files\BurpSuitePro\burpsuite_pro.jar!\burp\Zb8y.class
 * Java compiler version: 21 (65.0)
 * JD-Core Version:       1.1.3
 */