package burp;

import java.math.BigInteger;

class Zb9k extends ClassLoader {
  static Object Zi;
  
  static String Za;
  
  private static final String[] a;
  
  private static final String[] b;
  
  static void Zz(Object[] paramArrayOfObject, Object paramObject) throws Throwable {}
  
  static boolean Zn(Object[] paramArrayOfObject, Object paramObject) throws Throwable {
    // Byte code:
    //   0: invokestatic ZN : ()Z
    //   3: istore_2
    //   4: sipush #32712
    //   7: sipush #-4016
    //   10: invokestatic a : (II)Ljava/lang/String;
    //   13: invokestatic forName : (Ljava/lang/String;)Ljava/lang/Class;
    //   16: invokestatic Zl : (Ljava/lang/Object;)V
    //   19: new java/lang/StringBuilder
    //   22: dup
    //   23: invokespecial <init> : ()V
    //   26: astore_3
    //   27: iconst_0
    //   28: istore #4
    //   30: iload #4
    //   32: bipush #32
    //   34: if_icmpge -> 1367
    //   37: iload #4
    //   39: tableswitch default -> 1360, 0 -> 180, 1 -> 217, 2 -> 254, 3 -> 291, 4 -> 328, 5 -> 365, 6 -> 402, 7 -> 439, 8 -> 476, 9 -> 513, 10 -> 550, 11 -> 587, 12 -> 624, 13 -> 661, 14 -> 698, 15 -> 735, 16 -> 772, 17 -> 809, 18 -> 846, 19 -> 883, 20 -> 920, 21 -> 957, 22 -> 994, 23 -> 1031, 24 -> 1068, 25 -> 1105, 26 -> 1142, 27 -> 1179, 28 -> 1216, 29 -> 1253, 30 -> 1290, 31 -> 1327
    //   180: aload_3
    //   181: getstatic burp/Zgq_.ZQ : Ljava/lang/String;
    //   184: getstatic burp/Zbz_.ZU : Ljava/lang/Object;
    //   187: checkcast java/math/BigInteger
    //   190: invokevirtual intValue : ()I
    //   193: bipush #32
    //   195: irem
    //   196: invokestatic abs : (I)I
    //   199: invokevirtual charAt : (I)C
    //   202: invokevirtual append : (C)Ljava/lang/StringBuilder;
    //   205: pop
    //   206: iload_2
    //   207: ifne -> 1360
    //   210: goto -> 217
    //   213: invokestatic a : (Ljava/lang/Throwable;)Ljava/lang/Throwable;
    //   216: athrow
    //   217: aload_3
    //   218: getstatic burp/Zlav.ZW : Ljava/lang/String;
    //   221: getstatic burp/Zbli.Zo : Ljava/lang/Object;
    //   224: checkcast java/math/BigInteger
    //   227: invokevirtual intValue : ()I
    //   230: bipush #32
    //   232: irem
    //   233: invokestatic abs : (I)I
    //   236: invokevirtual charAt : (I)C
    //   239: invokevirtual append : (C)Ljava/lang/StringBuilder;
    //   242: pop
    //   243: iload_2
    //   244: ifne -> 1360
    //   247: goto -> 254
    //   250: invokestatic a : (Ljava/lang/Throwable;)Ljava/lang/Throwable;
    //   253: athrow
    //   254: aload_3
    //   255: getstatic burp/Zs00.Zv : Ljava/lang/String;
    //   258: getstatic burp/Zbo7.Zl : Ljava/lang/Object;
    //   261: checkcast java/math/BigInteger
    //   264: invokevirtual intValue : ()I
    //   267: bipush #32
    //   269: irem
    //   270: invokestatic abs : (I)I
    //   273: invokevirtual charAt : (I)C
    //   276: invokevirtual append : (C)Ljava/lang/StringBuilder;
    //   279: pop
    //   280: iload_2
    //   281: ifne -> 1360
    //   284: goto -> 291
    //   287: invokestatic a : (Ljava/lang/Throwable;)Ljava/lang/Throwable;
    //   290: athrow
    //   291: aload_3
    //   292: getstatic burp/Zmt6.Zx : Ljava/lang/String;
    //   295: getstatic burp/Zdm.ZA : Ljava/lang/Object;
    //   298: checkcast java/math/BigInteger
    //   301: invokevirtual intValue : ()I
    //   304: bipush #32
    //   306: irem
    //   307: invokestatic abs : (I)I
    //   310: invokevirtual charAt : (I)C
    //   313: invokevirtual append : (C)Ljava/lang/StringBuilder;
    //   316: pop
    //   317: iload_2
    //   318: ifne -> 1360
    //   321: goto -> 328
    //   324: invokestatic a : (Ljava/lang/Throwable;)Ljava/lang/Throwable;
    //   327: athrow
    //   328: aload_3
    //   329: getstatic burp/Zlqq.Za : Ljava/lang/String;
    //   332: getstatic burp/Zrs0.Zz : Ljava/lang/Object;
    //   335: checkcast java/math/BigInteger
    //   338: invokevirtual intValue : ()I
    //   341: bipush #32
    //   343: irem
    //   344: invokestatic abs : (I)I
    //   347: invokevirtual charAt : (I)C
    //   350: invokevirtual append : (C)Ljava/lang/StringBuilder;
    //   353: pop
    //   354: iload_2
    //   355: ifne -> 1360
    //   358: goto -> 365
    //   361: invokestatic a : (Ljava/lang/Throwable;)Ljava/lang/Throwable;
    //   364: athrow
    //   365: aload_3
    //   366: getstatic burp/Zmha.Zo : Ljava/lang/String;
    //   369: getstatic burp/Zrxf.ZS : Ljava/lang/Object;
    //   372: checkcast java/math/BigInteger
    //   375: invokevirtual intValue : ()I
    //   378: bipush #32
    //   380: irem
    //   381: invokestatic abs : (I)I
    //   384: invokevirtual charAt : (I)C
    //   387: invokevirtual append : (C)Ljava/lang/StringBuilder;
    //   390: pop
    //   391: iload_2
    //   392: ifne -> 1360
    //   395: goto -> 402
    //   398: invokestatic a : (Ljava/lang/Throwable;)Ljava/lang/Throwable;
    //   401: athrow
    //   402: aload_3
    //   403: getstatic burp/Zz5l.ZH : Ljava/lang/String;
    //   406: getstatic burp/Zxk9.ZI : Ljava/lang/Object;
    //   409: checkcast java/math/BigInteger
    //   412: invokevirtual intValue : ()I
    //   415: bipush #32
    //   417: irem
    //   418: invokestatic abs : (I)I
    //   421: invokevirtual charAt : (I)C
    //   424: invokevirtual append : (C)Ljava/lang/StringBuilder;
    //   427: pop
    //   428: iload_2
    //   429: ifne -> 1360
    //   432: goto -> 439
    //   435: invokestatic a : (Ljava/lang/Throwable;)Ljava/lang/Throwable;
    //   438: athrow
    //   439: aload_3
    //   440: getstatic burp/Zz5l.ZH : Ljava/lang/String;
    //   443: getstatic burp/Zlqq.ZV : Ljava/lang/Object;
    //   446: checkcast java/math/BigInteger
    //   449: invokevirtual intValue : ()I
    //   452: bipush #32
    //   454: irem
    //   455: invokestatic abs : (I)I
    //   458: invokevirtual charAt : (I)C
    //   461: invokevirtual append : (C)Ljava/lang/StringBuilder;
    //   464: pop
    //   465: iload_2
    //   466: ifne -> 1360
    //   469: goto -> 476
    //   472: invokestatic a : (Ljava/lang/Throwable;)Ljava/lang/Throwable;
    //   475: athrow
    //   476: aload_3
    //   477: getstatic burp/Zsf4.ZA : Ljava/lang/String;
    //   480: getstatic burp/Ztgv.Zg : Ljava/lang/Object;
    //   483: checkcast java/math/BigInteger
    //   486: invokevirtual intValue : ()I
    //   489: bipush #32
    //   491: irem
    //   492: invokestatic abs : (I)I
    //   495: invokevirtual charAt : (I)C
    //   498: invokevirtual append : (C)Ljava/lang/StringBuilder;
    //   501: pop
    //   502: iload_2
    //   503: ifne -> 1360
    //   506: goto -> 513
    //   509: invokestatic a : (Ljava/lang/Throwable;)Ljava/lang/Throwable;
    //   512: athrow
    //   513: aload_3
    //   514: getstatic burp/Zgcg.Zk : Ljava/lang/String;
    //   517: getstatic burp/Zgb9.Zb : Ljava/lang/Object;
    //   520: checkcast java/math/BigInteger
    //   523: invokevirtual intValue : ()I
    //   526: bipush #32
    //   528: irem
    //   529: invokestatic abs : (I)I
    //   532: invokevirtual charAt : (I)C
    //   535: invokevirtual append : (C)Ljava/lang/StringBuilder;
    //   538: pop
    //   539: iload_2
    //   540: ifne -> 1360
    //   543: goto -> 550
    //   546: invokestatic a : (Ljava/lang/Throwable;)Ljava/lang/Throwable;
    //   549: athrow
    //   550: aload_3
    //   551: getstatic burp/Zr0u.Z_ : Ljava/lang/String;
    //   554: getstatic burp/Zbxa.ZS : Ljava/lang/Object;
    //   557: checkcast java/math/BigInteger
    //   560: invokevirtual intValue : ()I
    //   563: bipush #32
    //   565: irem
    //   566: invokestatic abs : (I)I
    //   569: invokevirtual charAt : (I)C
    //   572: invokevirtual append : (C)Ljava/lang/StringBuilder;
    //   575: pop
    //   576: iload_2
    //   577: ifne -> 1360
    //   580: goto -> 587
    //   583: invokestatic a : (Ljava/lang/Throwable;)Ljava/lang/Throwable;
    //   586: athrow
    //   587: aload_3
    //   588: getstatic burp/Zb2p.ZV : Ljava/lang/String;
    //   591: getstatic burp/Zlfg.Zv : Ljava/lang/Object;
    //   594: checkcast java/math/BigInteger
    //   597: invokevirtual intValue : ()I
    //   600: bipush #32
    //   602: irem
    //   603: invokestatic abs : (I)I
    //   606: invokevirtual charAt : (I)C
    //   609: invokevirtual append : (C)Ljava/lang/StringBuilder;
    //   612: pop
    //   613: iload_2
    //   614: ifne -> 1360
    //   617: goto -> 624
    //   620: invokestatic a : (Ljava/lang/Throwable;)Ljava/lang/Throwable;
    //   623: athrow
    //   624: aload_3
    //   625: getstatic burp/Zkm0.ZL : Ljava/lang/String;
    //   628: getstatic burp/Zbp.ZD : Ljava/lang/Object;
    //   631: checkcast java/math/BigInteger
    //   634: invokevirtual intValue : ()I
    //   637: bipush #32
    //   639: irem
    //   640: invokestatic abs : (I)I
    //   643: invokevirtual charAt : (I)C
    //   646: invokevirtual append : (C)Ljava/lang/StringBuilder;
    //   649: pop
    //   650: iload_2
    //   651: ifne -> 1360
    //   654: goto -> 661
    //   657: invokestatic a : (Ljava/lang/Throwable;)Ljava/lang/Throwable;
    //   660: athrow
    //   661: aload_3
    //   662: getstatic burp/Zl8i.Zb : Ljava/lang/String;
    //   665: getstatic burp/Zl1z.ZV : Ljava/lang/Object;
    //   668: checkcast java/math/BigInteger
    //   671: invokevirtual intValue : ()I
    //   674: bipush #32
    //   676: irem
    //   677: invokestatic abs : (I)I
    //   680: invokevirtual charAt : (I)C
    //   683: invokevirtual append : (C)Ljava/lang/StringBuilder;
    //   686: pop
    //   687: iload_2
    //   688: ifne -> 1360
    //   691: goto -> 698
    //   694: invokestatic a : (Ljava/lang/Throwable;)Ljava/lang/Throwable;
    //   697: athrow
    //   698: aload_3
    //   699: getstatic burp/Zg4d.ZE : Ljava/lang/String;
    //   702: getstatic burp/Zgkp.Zp : Ljava/lang/Object;
    //   705: checkcast java/math/BigInteger
    //   708: invokevirtual intValue : ()I
    //   711: bipush #32
    //   713: irem
    //   714: invokestatic abs : (I)I
    //   717: invokevirtual charAt : (I)C
    //   720: invokevirtual append : (C)Ljava/lang/StringBuilder;
    //   723: pop
    //   724: iload_2
    //   725: ifne -> 1360
    //   728: goto -> 735
    //   731: invokestatic a : (Ljava/lang/Throwable;)Ljava/lang/Throwable;
    //   734: athrow
    //   735: aload_3
    //   736: getstatic burp/Zlvb.Zs : Ljava/lang/String;
    //   739: getstatic burp/Zgw7.Zi : Ljava/lang/Object;
    //   742: checkcast java/math/BigInteger
    //   745: invokevirtual intValue : ()I
    //   748: bipush #32
    //   750: irem
    //   751: invokestatic abs : (I)I
    //   754: invokevirtual charAt : (I)C
    //   757: invokevirtual append : (C)Ljava/lang/StringBuilder;
    //   760: pop
    //   761: iload_2
    //   762: ifne -> 1360
    //   765: goto -> 772
    //   768: invokestatic a : (Ljava/lang/Throwable;)Ljava/lang/Throwable;
    //   771: athrow
    //   772: aload_3
    //   773: getstatic burp/Zrva.Zr : Ljava/lang/String;
    //   776: getstatic burp/Zxl5.Zh : Ljava/lang/Object;
    //   779: checkcast java/math/BigInteger
    //   782: invokevirtual intValue : ()I
    //   785: bipush #32
    //   787: irem
    //   788: invokestatic abs : (I)I
    //   791: invokevirtual charAt : (I)C
    //   794: invokevirtual append : (C)Ljava/lang/StringBuilder;
    //   797: pop
    //   798: iload_2
    //   799: ifne -> 1360
    //   802: goto -> 809
    //   805: invokestatic a : (Ljava/lang/Throwable;)Ljava/lang/Throwable;
    //   808: athrow
    //   809: aload_3
    //   810: getstatic burp/Zmv9.Zm : Ljava/lang/String;
    //   813: getstatic burp/Zl6z.Zt : Ljava/lang/Object;
    //   816: checkcast java/math/BigInteger
    //   819: invokevirtual intValue : ()I
    //   822: bipush #32
    //   824: irem
    //   825: invokestatic abs : (I)I
    //   828: invokevirtual charAt : (I)C
    //   831: invokevirtual append : (C)Ljava/lang/StringBuilder;
    //   834: pop
    //   835: iload_2
    //   836: ifne -> 1360
    //   839: goto -> 846
    //   842: invokestatic a : (Ljava/lang/Throwable;)Ljava/lang/Throwable;
    //   845: athrow
    //   846: aload_3
    //   847: getstatic burp/Zmsl.ZP : Ljava/lang/String;
    //   850: getstatic burp/Ze_e.Za : Ljava/lang/Object;
    //   853: checkcast java/math/BigInteger
    //   856: invokevirtual intValue : ()I
    //   859: bipush #32
    //   861: irem
    //   862: invokestatic abs : (I)I
    //   865: invokevirtual charAt : (I)C
    //   868: invokevirtual append : (C)Ljava/lang/StringBuilder;
    //   871: pop
    //   872: iload_2
    //   873: ifne -> 1360
    //   876: goto -> 883
    //   879: invokestatic a : (Ljava/lang/Throwable;)Ljava/lang/Throwable;
    //   882: athrow
    //   883: aload_3
    //   884: getstatic burp/Ztzw.Zi : Ljava/lang/String;
    //   887: getstatic burp/Zeor.Zb : Ljava/lang/Object;
    //   890: checkcast java/math/BigInteger
    //   893: invokevirtual intValue : ()I
    //   896: bipush #32
    //   898: irem
    //   899: invokestatic abs : (I)I
    //   902: invokevirtual charAt : (I)C
    //   905: invokevirtual append : (C)Ljava/lang/StringBuilder;
    //   908: pop
    //   909: iload_2
    //   910: ifne -> 1360
    //   913: goto -> 920
    //   916: invokestatic a : (Ljava/lang/Throwable;)Ljava/lang/Throwable;
    //   919: athrow
    //   920: aload_3
    //   921: getstatic burp/Zgu4.Za : Ljava/lang/String;
    //   924: getstatic burp/Zrqd.Zi : Ljava/lang/Object;
    //   927: checkcast java/math/BigInteger
    //   930: invokevirtual intValue : ()I
    //   933: bipush #32
    //   935: irem
    //   936: invokestatic abs : (I)I
    //   939: invokevirtual charAt : (I)C
    //   942: invokevirtual append : (C)Ljava/lang/StringBuilder;
    //   945: pop
    //   946: iload_2
    //   947: ifne -> 1360
    //   950: goto -> 957
    //   953: invokestatic a : (Ljava/lang/Throwable;)Ljava/lang/Throwable;
    //   956: athrow
    //   957: aload_3
    //   958: getstatic burp/Zmir.ZI : Ljava/lang/String;
    //   961: getstatic burp/Zrxm.ZL : Ljava/lang/Object;
    //   964: checkcast java/math/BigInteger
    //   967: invokevirtual intValue : ()I
    //   970: bipush #32
    //   972: irem
    //   973: invokestatic abs : (I)I
    //   976: invokevirtual charAt : (I)C
    //   979: invokevirtual append : (C)Ljava/lang/StringBuilder;
    //   982: pop
    //   983: iload_2
    //   984: ifne -> 1360
    //   987: goto -> 994
    //   990: invokestatic a : (Ljava/lang/Throwable;)Ljava/lang/Throwable;
    //   993: athrow
    //   994: aload_3
    //   995: getstatic burp/Zgwq.ZV : Ljava/lang/String;
    //   998: getstatic burp/Zsgj.ZK : Ljava/lang/Object;
    //   1001: checkcast java/math/BigInteger
    //   1004: invokevirtual intValue : ()I
    //   1007: bipush #32
    //   1009: irem
    //   1010: invokestatic abs : (I)I
    //   1013: invokevirtual charAt : (I)C
    //   1016: invokevirtual append : (C)Ljava/lang/StringBuilder;
    //   1019: pop
    //   1020: iload_2
    //   1021: ifne -> 1360
    //   1024: goto -> 1031
    //   1027: invokestatic a : (Ljava/lang/Throwable;)Ljava/lang/Throwable;
    //   1030: athrow
    //   1031: aload_3
    //   1032: getstatic burp/Zlkm.ZH : Ljava/lang/String;
    //   1035: getstatic burp/Zk7b.ZR : Ljava/lang/Object;
    //   1038: checkcast java/math/BigInteger
    //   1041: invokevirtual intValue : ()I
    //   1044: bipush #32
    //   1046: irem
    //   1047: invokestatic abs : (I)I
    //   1050: invokevirtual charAt : (I)C
    //   1053: invokevirtual append : (C)Ljava/lang/StringBuilder;
    //   1056: pop
    //   1057: iload_2
    //   1058: ifne -> 1360
    //   1061: goto -> 1068
    //   1064: invokestatic a : (Ljava/lang/Throwable;)Ljava/lang/Throwable;
    //   1067: athrow
    //   1068: aload_3
    //   1069: getstatic burp/Zzna.Zi : Ljava/lang/String;
    //   1072: getstatic burp/Zzoi.ZI : Ljava/lang/Object;
    //   1075: checkcast java/math/BigInteger
    //   1078: invokevirtual intValue : ()I
    //   1081: bipush #32
    //   1083: irem
    //   1084: invokestatic abs : (I)I
    //   1087: invokevirtual charAt : (I)C
    //   1090: invokevirtual append : (C)Ljava/lang/StringBuilder;
    //   1093: pop
    //   1094: iload_2
    //   1095: ifne -> 1360
    //   1098: goto -> 1105
    //   1101: invokestatic a : (Ljava/lang/Throwable;)Ljava/lang/Throwable;
    //   1104: athrow
    //   1105: aload_3
    //   1106: getstatic burp/Zxt5.ZM : Ljava/lang/String;
    //   1109: getstatic burp/Zf.Zh : Ljava/lang/Object;
    //   1112: checkcast java/math/BigInteger
    //   1115: invokevirtual intValue : ()I
    //   1118: bipush #32
    //   1120: irem
    //   1121: invokestatic abs : (I)I
    //   1124: invokevirtual charAt : (I)C
    //   1127: invokevirtual append : (C)Ljava/lang/StringBuilder;
    //   1130: pop
    //   1131: iload_2
    //   1132: ifne -> 1360
    //   1135: goto -> 1142
    //   1138: invokestatic a : (Ljava/lang/Throwable;)Ljava/lang/Throwable;
    //   1141: athrow
    //   1142: aload_3
    //   1143: getstatic burp/Zb8v.Zo : Ljava/lang/String;
    //   1146: getstatic burp/Zmh5.ZN : Ljava/lang/Object;
    //   1149: checkcast java/math/BigInteger
    //   1152: invokevirtual intValue : ()I
    //   1155: bipush #32
    //   1157: irem
    //   1158: invokestatic abs : (I)I
    //   1161: invokevirtual charAt : (I)C
    //   1164: invokevirtual append : (C)Ljava/lang/StringBuilder;
    //   1167: pop
    //   1168: iload_2
    //   1169: ifne -> 1360
    //   1172: goto -> 1179
    //   1175: invokestatic a : (Ljava/lang/Throwable;)Ljava/lang/Throwable;
    //   1178: athrow
    //   1179: aload_3
    //   1180: getstatic burp/Ze69.ZA : Ljava/lang/String;
    //   1183: getstatic burp/Zxt5.ZG : Ljava/lang/Object;
    //   1186: checkcast java/math/BigInteger
    //   1189: invokevirtual intValue : ()I
    //   1192: bipush #32
    //   1194: irem
    //   1195: invokestatic abs : (I)I
    //   1198: invokevirtual charAt : (I)C
    //   1201: invokevirtual append : (C)Ljava/lang/StringBuilder;
    //   1204: pop
    //   1205: iload_2
    //   1206: ifne -> 1360
    //   1209: goto -> 1216
    //   1212: invokestatic a : (Ljava/lang/Throwable;)Ljava/lang/Throwable;
    //   1215: athrow
    //   1216: aload_3
    //   1217: getstatic burp/Zvh.ZP : Ljava/lang/String;
    //   1220: getstatic burp/Zbp.ZD : Ljava/lang/Object;
    //   1223: checkcast java/math/BigInteger
    //   1226: invokevirtual intValue : ()I
    //   1229: bipush #32
    //   1231: irem
    //   1232: invokestatic abs : (I)I
    //   1235: invokevirtual charAt : (I)C
    //   1238: invokevirtual append : (C)Ljava/lang/StringBuilder;
    //   1241: pop
    //   1242: iload_2
    //   1243: ifne -> 1360
    //   1246: goto -> 1253
    //   1249: invokestatic a : (Ljava/lang/Throwable;)Ljava/lang/Throwable;
    //   1252: athrow
    //   1253: aload_3
    //   1254: getstatic burp/Zrp3.Zf : Ljava/lang/String;
    //   1257: getstatic burp/Zgz1.ZX : Ljava/lang/Object;
    //   1260: checkcast java/math/BigInteger
    //   1263: invokevirtual intValue : ()I
    //   1266: bipush #32
    //   1268: irem
    //   1269: invokestatic abs : (I)I
    //   1272: invokevirtual charAt : (I)C
    //   1275: invokevirtual append : (C)Ljava/lang/StringBuilder;
    //   1278: pop
    //   1279: iload_2
    //   1280: ifne -> 1360
    //   1283: goto -> 1290
    //   1286: invokestatic a : (Ljava/lang/Throwable;)Ljava/lang/Throwable;
    //   1289: athrow
    //   1290: aload_3
    //   1291: getstatic burp/Zm52.Ze : Ljava/lang/String;
    //   1294: getstatic burp/Zz1k.ZP : Ljava/lang/Object;
    //   1297: checkcast java/math/BigInteger
    //   1300: invokevirtual intValue : ()I
    //   1303: bipush #32
    //   1305: irem
    //   1306: invokestatic abs : (I)I
    //   1309: invokevirtual charAt : (I)C
    //   1312: invokevirtual append : (C)Ljava/lang/StringBuilder;
    //   1315: pop
    //   1316: iload_2
    //   1317: ifne -> 1360
    //   1320: goto -> 1327
    //   1323: invokestatic a : (Ljava/lang/Throwable;)Ljava/lang/Throwable;
    //   1326: athrow
    //   1327: aload_3
    //   1328: getstatic burp/Zmh0.Zs : Ljava/lang/String;
    //   1331: getstatic burp/Zkor.Ze : Ljava/lang/Object;
    //   1334: checkcast java/math/BigInteger
    //   1337: invokevirtual intValue : ()I
    //   1340: bipush #32
    //   1342: irem
    //   1343: invokestatic abs : (I)I
    //   1346: invokevirtual charAt : (I)C
    //   1349: invokevirtual append : (C)Ljava/lang/StringBuilder;
    //   1352: pop
    //   1353: goto -> 1360
    //   1356: invokestatic a : (Ljava/lang/Throwable;)Ljava/lang/Throwable;
    //   1359: athrow
    //   1360: iinc #4, 1
    //   1363: iload_2
    //   1364: ifne -> 30
    //   1367: aload_3
    //   1368: invokevirtual toString : ()Ljava/lang/String;
    //   1371: putstatic burp/Zxti.ZD : Ljava/lang/String;
    //   1374: sipush #32717
    //   1377: getstatic burp/Zlw8.ZA : Ljava/lang/Object;
    //   1380: checkcast java/math/BigInteger
    //   1383: getstatic burp/Zzsq.Zh : Ljava/lang/Object;
    //   1386: checkcast java/math/BigInteger
    //   1389: invokevirtual subtract : (Ljava/math/BigInteger;)Ljava/math/BigInteger;
    //   1392: putstatic burp/Zmpc.Zc : Ljava/lang/Object;
    //   1395: sipush #-21247
    //   1398: invokestatic a : (II)Ljava/lang/String;
    //   1401: iconst_1
    //   1402: ldc burp/Zldt
    //   1404: invokevirtual getClassLoader : ()Ljava/lang/ClassLoader;
    //   1407: invokestatic forName : (Ljava/lang/String;ZLjava/lang/ClassLoader;)Ljava/lang/Class;
    //   1410: invokevirtual getDeclaredFields : ()[Ljava/lang/reflect/Field;
    //   1413: astore #4
    //   1415: aload #4
    //   1417: arraylength
    //   1418: istore #5
    //   1420: iconst_0
    //   1421: istore #6
    //   1423: iload #6
    //   1425: iload #5
    //   1427: if_icmpge -> 1565
    //   1430: aload #4
    //   1432: iload #6
    //   1434: aaload
    //   1435: astore #7
    //   1437: aload #7
    //   1439: invokevirtual getModifiers : ()I
    //   1442: invokestatic isStatic : (I)Z
    //   1445: ifne -> 1455
    //   1448: goto -> 1558
    //   1451: invokestatic a : (Ljava/lang/Throwable;)Ljava/lang/Throwable;
    //   1454: athrow
    //   1455: aload #7
    //   1457: invokevirtual getType : ()Ljava/lang/Class;
    //   1460: astore #8
    //   1462: aload #8
    //   1464: ifnull -> 1545
    //   1467: aload #8
    //   1469: invokevirtual isPrimitive : ()Z
    //   1472: ifne -> 1545
    //   1475: goto -> 1482
    //   1478: invokestatic a : (Ljava/lang/Throwable;)Ljava/lang/Throwable;
    //   1481: athrow
    //   1482: aload #8
    //   1484: invokevirtual getPackage : ()Ljava/lang/Package;
    //   1487: ifnull -> 1545
    //   1490: goto -> 1497
    //   1493: invokestatic a : (Ljava/lang/Throwable;)Ljava/lang/Throwable;
    //   1496: athrow
    //   1497: aload #8
    //   1499: invokevirtual getPackage : ()Ljava/lang/Package;
    //   1502: invokevirtual getName : ()Ljava/lang/String;
    //   1505: ifnull -> 1545
    //   1508: goto -> 1515
    //   1511: invokestatic a : (Ljava/lang/Throwable;)Ljava/lang/Throwable;
    //   1514: athrow
    //   1515: aload #8
    //   1517: invokevirtual getPackage : ()Ljava/lang/Package;
    //   1520: invokevirtual getName : ()Ljava/lang/String;
    //   1523: sipush #32719
    //   1526: sipush #-26126
    //   1529: invokestatic a : (II)Ljava/lang/String;
    //   1532: invokevirtual startsWith : (Ljava/lang/String;)Z
    //   1535: ifne -> 1545
    //   1538: goto -> 1545
    //   1541: invokestatic a : (Ljava/lang/Throwable;)Ljava/lang/Throwable;
    //   1544: athrow
    //   1545: aload #7
    //   1547: iconst_1
    //   1548: invokevirtual setAccessible : (Z)V
    //   1551: aload #7
    //   1553: aconst_null
    //   1554: invokevirtual get : (Ljava/lang/Object;)Ljava/lang/Object;
    //   1557: pop
    //   1558: iinc #6, 1
    //   1561: iload_2
    //   1562: ifne -> 1423
    //   1565: sipush #32705
    //   1568: sipush #8823
    //   1571: invokestatic a : (II)Ljava/lang/String;
    //   1574: invokestatic forName : (Ljava/lang/String;)Ljava/lang/Class;
    //   1577: invokevirtual getDeclaredMethods : ()[Ljava/lang/reflect/Method;
    //   1580: astore #4
    //   1582: aload #4
    //   1584: arraylength
    //   1585: istore #5
    //   1587: iconst_0
    //   1588: istore #6
    //   1590: iload #6
    //   1592: iload #5
    //   1594: if_icmpge -> 1706
    //   1597: aload #4
    //   1599: iload #6
    //   1601: aaload
    //   1602: astore #7
    //   1604: aload #7
    //   1606: invokevirtual getParameterTypes : ()[Ljava/lang/Class;
    //   1609: pop
    //   1610: aload #7
    //   1612: invokevirtual getModifiers : ()I
    //   1615: invokestatic isStatic : (I)Z
    //   1618: ifeq -> 1692
    //   1621: aload #7
    //   1623: invokevirtual getParameterTypes : ()[Ljava/lang/Class;
    //   1626: arraylength
    //   1627: iconst_2
    //   1628: if_icmpne -> 1692
    //   1631: goto -> 1638
    //   1634: invokestatic a : (Ljava/lang/Throwable;)Ljava/lang/Throwable;
    //   1637: athrow
    //   1638: aload #7
    //   1640: invokevirtual getReturnType : ()Ljava/lang/Class;
    //   1643: getstatic java/lang/Boolean.TYPE : Ljava/lang/Class;
    //   1646: if_acmpne -> 1692
    //   1649: goto -> 1656
    //   1652: invokestatic a : (Ljava/lang/Throwable;)Ljava/lang/Throwable;
    //   1655: athrow
    //   1656: aload #7
    //   1658: iconst_1
    //   1659: invokevirtual setAccessible : (Z)V
    //   1662: aload #7
    //   1664: aconst_null
    //   1665: iconst_2
    //   1666: anewarray java/lang/Object
    //   1669: dup
    //   1670: iconst_0
    //   1671: aload_0
    //   1672: aastore
    //   1673: dup
    //   1674: iconst_1
    //   1675: aload_1
    //   1676: aastore
    //   1677: invokevirtual invoke : (Ljava/lang/Object;[Ljava/lang/Object;)Ljava/lang/Object;
    //   1680: pop
    //   1681: iload_2
    //   1682: ifne -> 1706
    //   1685: goto -> 1692
    //   1688: invokestatic a : (Ljava/lang/Throwable;)Ljava/lang/Throwable;
    //   1691: athrow
    //   1692: iinc #6, 1
    //   1695: iload_2
    //   1696: ifne -> 1590
    //   1699: goto -> 1706
    //   1702: invokestatic a : (Ljava/lang/Throwable;)Ljava/lang/Throwable;
    //   1705: athrow
    //   1706: sipush #32714
    //   1709: sipush #-29344
    //   1712: invokestatic a : (II)Ljava/lang/String;
    //   1715: iconst_1
    //   1716: ldc burp/Zbqk
    //   1718: invokevirtual getClassLoader : ()Ljava/lang/ClassLoader;
    //   1721: invokestatic forName : (Ljava/lang/String;ZLjava/lang/ClassLoader;)Ljava/lang/Class;
    //   1724: invokevirtual getDeclaredFields : ()[Ljava/lang/reflect/Field;
    //   1727: astore #4
    //   1729: aload #4
    //   1731: arraylength
    //   1732: istore #5
    //   1734: iconst_0
    //   1735: istore #6
    //   1737: iload #6
    //   1739: iload #5
    //   1741: if_icmpge -> 1879
    //   1744: aload #4
    //   1746: iload #6
    //   1748: aaload
    //   1749: astore #7
    //   1751: aload #7
    //   1753: invokevirtual getModifiers : ()I
    //   1756: invokestatic isStatic : (I)Z
    //   1759: ifne -> 1769
    //   1762: goto -> 1872
    //   1765: invokestatic a : (Ljava/lang/Throwable;)Ljava/lang/Throwable;
    //   1768: athrow
    //   1769: aload #7
    //   1771: invokevirtual getType : ()Ljava/lang/Class;
    //   1774: astore #8
    //   1776: aload #8
    //   1778: ifnull -> 1859
    //   1781: aload #8
    //   1783: invokevirtual isPrimitive : ()Z
    //   1786: ifne -> 1859
    //   1789: goto -> 1796
    //   1792: invokestatic a : (Ljava/lang/Throwable;)Ljava/lang/Throwable;
    //   1795: athrow
    //   1796: aload #8
    //   1798: invokevirtual getPackage : ()Ljava/lang/Package;
    //   1801: ifnull -> 1859
    //   1804: goto -> 1811
    //   1807: invokestatic a : (Ljava/lang/Throwable;)Ljava/lang/Throwable;
    //   1810: athrow
    //   1811: aload #8
    //   1813: invokevirtual getPackage : ()Ljava/lang/Package;
    //   1816: invokevirtual getName : ()Ljava/lang/String;
    //   1819: ifnull -> 1859
    //   1822: goto -> 1829
    //   1825: invokestatic a : (Ljava/lang/Throwable;)Ljava/lang/Throwable;
    //   1828: athrow
    //   1829: aload #8
    //   1831: invokevirtual getPackage : ()Ljava/lang/Package;
    //   1834: invokevirtual getName : ()Ljava/lang/String;
    //   1837: sipush #32706
    //   1840: sipush #5334
    //   1843: invokestatic a : (II)Ljava/lang/String;
    //   1846: invokevirtual startsWith : (Ljava/lang/String;)Z
    //   1849: ifne -> 1859
    //   1852: goto -> 1859
    //   1855: invokestatic a : (Ljava/lang/Throwable;)Ljava/lang/Throwable;
    //   1858: athrow
    //   1859: aload #7
    //   1861: iconst_1
    //   1862: invokevirtual setAccessible : (Z)V
    //   1865: aload #7
    //   1867: aconst_null
    //   1868: invokevirtual get : (Ljava/lang/Object;)Ljava/lang/Object;
    //   1871: pop
    //   1872: iinc #6, 1
    //   1875: iload_2
    //   1876: ifne -> 1737
    //   1879: sipush #32707
    //   1882: sipush #-23530
    //   1885: invokestatic a : (II)Ljava/lang/String;
    //   1888: invokestatic forName : (Ljava/lang/String;)Ljava/lang/Class;
    //   1891: invokevirtual getDeclaredMethods : ()[Ljava/lang/reflect/Method;
    //   1894: astore #4
    //   1896: aload #4
    //   1898: arraylength
    //   1899: istore #5
    //   1901: iconst_0
    //   1902: istore #6
    //   1904: iload #6
    //   1906: iload #5
    //   1908: if_icmpge -> 2041
    //   1911: aload #4
    //   1913: iload #6
    //   1915: aaload
    //   1916: astore #7
    //   1918: aload #7
    //   1920: invokevirtual getParameterTypes : ()[Ljava/lang/Class;
    //   1923: pop
    //   1924: aload #7
    //   1926: invokevirtual getModifiers : ()I
    //   1929: invokestatic isStatic : (I)Z
    //   1932: ifeq -> 2027
    //   1935: aload #7
    //   1937: invokevirtual getParameterTypes : ()[Ljava/lang/Class;
    //   1940: arraylength
    //   1941: iconst_2
    //   1942: if_icmpne -> 2027
    //   1945: goto -> 1952
    //   1948: invokestatic a : (Ljava/lang/Throwable;)Ljava/lang/Throwable;
    //   1951: athrow
    //   1952: aload #7
    //   1954: invokevirtual getReturnType : ()Ljava/lang/Class;
    //   1957: getstatic java/lang/Void.TYPE : Ljava/lang/Class;
    //   1960: invokevirtual equals : (Ljava/lang/Object;)Z
    //   1963: ifeq -> 2027
    //   1966: goto -> 1973
    //   1969: invokestatic a : (Ljava/lang/Throwable;)Ljava/lang/Throwable;
    //   1972: athrow
    //   1973: aload #7
    //   1975: iconst_1
    //   1976: invokevirtual setAccessible : (Z)V
    //   1979: aload #7
    //   1981: aconst_null
    //   1982: iconst_2
    //   1983: anewarray java/lang/Object
    //   1986: dup
    //   1987: iconst_0
    //   1988: aload_0
    //   1989: aastore
    //   1990: dup
    //   1991: iconst_1
    //   1992: aload_1
    //   1993: ifnonnull -> 2011
    //   1996: goto -> 2003
    //   1999: invokestatic a : (Ljava/lang/Throwable;)Ljava/lang/Throwable;
    //   2002: athrow
    //   2003: aload_1
    //   2004: goto -> 2018
    //   2007: invokestatic a : (Ljava/lang/Throwable;)Ljava/lang/Throwable;
    //   2010: athrow
    //   2011: aload_1
    //   2012: checkcast [B
    //   2015: invokevirtual clone : ()Ljava/lang/Object;
    //   2018: aastore
    //   2019: invokevirtual invoke : (Ljava/lang/Object;[Ljava/lang/Object;)Ljava/lang/Object;
    //   2022: pop
    //   2023: iload_2
    //   2024: ifne -> 2041
    //   2027: iinc #6, 1
    //   2030: iload_2
    //   2031: ifne -> 1904
    //   2034: goto -> 2041
    //   2037: invokestatic a : (Ljava/lang/Throwable;)Ljava/lang/Throwable;
    //   2040: athrow
    //   2041: getstatic burp/Zs4v.Za : Ljava/lang/String;
    //   2044: getstatic burp/Zrof.ZB : Ljava/lang/Object;
    //   2047: checkcast java/math/BigInteger
    //   2050: invokevirtual intValue : ()I
    //   2053: bipush #32
    //   2055: irem
    //   2056: invokestatic abs : (I)I
    //   2059: invokevirtual charAt : (I)C
    //   2062: getstatic burp/Zsq6.Zm : Ljava/lang/String;
    //   2065: getstatic burp/Zrnu.Zs : Ljava/lang/Object;
    //   2068: checkcast java/math/BigInteger
    //   2071: invokevirtual intValue : ()I
    //   2074: bipush #32
    //   2076: irem
    //   2077: invokestatic abs : (I)I
    //   2080: invokevirtual charAt : (I)C
    //   2083: if_icmple -> 2198
    //   2086: getstatic burp/Zmlr.ZJ : Ljava/lang/String;
    //   2089: getstatic burp/Ztq8.Zm : Ljava/lang/Object;
    //   2092: checkcast java/math/BigInteger
    //   2095: invokevirtual intValue : ()I
    //   2098: bipush #32
    //   2100: irem
    //   2101: invokestatic abs : (I)I
    //   2104: invokevirtual charAt : (I)C
    //   2107: getstatic burp/Zgvf.ZM : Ljava/lang/String;
    //   2110: getstatic burp/Zkk2.Zq : Ljava/lang/Object;
    //   2113: checkcast java/math/BigInteger
    //   2116: invokevirtual intValue : ()I
    //   2119: bipush #32
    //   2121: irem
    //   2122: invokestatic abs : (I)I
    //   2125: invokevirtual charAt : (I)C
    //   2128: if_icmple -> 2198
    //   2131: goto -> 2138
    //   2134: invokestatic a : (Ljava/lang/Throwable;)Ljava/lang/Throwable;
    //   2137: athrow
    //   2138: getstatic burp/Zxzv.ZI : Ljava/lang/String;
    //   2141: getstatic burp/Zxf8.Zz : Ljava/lang/Object;
    //   2144: checkcast java/math/BigInteger
    //   2147: invokevirtual intValue : ()I
    //   2150: bipush #32
    //   2152: irem
    //   2153: invokestatic abs : (I)I
    //   2156: invokevirtual charAt : (I)C
    //   2159: getstatic burp/Zl39.ZI : Ljava/lang/String;
    //   2162: getstatic burp/Zg_p.Zx : Ljava/lang/Object;
    //   2165: checkcast java/math/BigInteger
    //   2168: invokevirtual intValue : ()I
    //   2171: bipush #32
    //   2173: irem
    //   2174: invokestatic abs : (I)I
    //   2177: invokevirtual charAt : (I)C
    //   2180: if_icmple -> 2198
    //   2183: goto -> 2190
    //   2186: invokestatic a : (Ljava/lang/Throwable;)Ljava/lang/Throwable;
    //   2189: athrow
    //   2190: iconst_1
    //   2191: goto -> 2199
    //   2194: invokestatic a : (Ljava/lang/Throwable;)Ljava/lang/Throwable;
    //   2197: athrow
    //   2198: iconst_0
    //   2199: ireturn
    //   2200: astore_3
    //   2201: new java/lang/Exception
    //   2204: dup
    //   2205: aload_3
    //   2206: invokevirtual getMessage : ()Ljava/lang/String;
    //   2209: invokespecial <init> : (Ljava/lang/String;)V
    //   2212: athrow
    // Exception table:
    //   from	to	target	type
    //   4	2199	2200	java/lang/Throwable
    //   37	210	213	java/lang/Throwable
    //   180	247	250	java/lang/Throwable
    //   217	284	287	java/lang/Throwable
    //   254	321	324	java/lang/Throwable
    //   291	358	361	java/lang/Throwable
    //   328	395	398	java/lang/Throwable
    //   365	432	435	java/lang/Throwable
    //   402	469	472	java/lang/Throwable
    //   439	506	509	java/lang/Throwable
    //   476	543	546	java/lang/Throwable
    //   513	580	583	java/lang/Throwable
    //   550	617	620	java/lang/Throwable
    //   587	654	657	java/lang/Throwable
    //   624	691	694	java/lang/Throwable
    //   661	728	731	java/lang/Throwable
    //   698	765	768	java/lang/Throwable
    //   735	802	805	java/lang/Throwable
    //   772	839	842	java/lang/Throwable
    //   809	876	879	java/lang/Throwable
    //   846	913	916	java/lang/Throwable
    //   883	950	953	java/lang/Throwable
    //   920	987	990	java/lang/Throwable
    //   957	1024	1027	java/lang/Throwable
    //   994	1061	1064	java/lang/Throwable
    //   1031	1098	1101	java/lang/Throwable
    //   1068	1135	1138	java/lang/Throwable
    //   1105	1172	1175	java/lang/Throwable
    //   1142	1209	1212	java/lang/Throwable
    //   1179	1246	1249	java/lang/Throwable
    //   1216	1283	1286	java/lang/Throwable
    //   1253	1320	1323	java/lang/Throwable
    //   1290	1353	1356	java/lang/Throwable
    //   1437	1451	1451	java/lang/Throwable
    //   1462	1475	1478	java/lang/Throwable
    //   1467	1490	1493	java/lang/Throwable
    //   1482	1508	1511	java/lang/Throwable
    //   1497	1538	1541	java/lang/Throwable
    //   1604	1631	1634	java/lang/Throwable
    //   1621	1649	1652	java/lang/Throwable
    //   1638	1685	1688	java/lang/Throwable
    //   1656	1699	1702	java/lang/Throwable
    //   1751	1765	1765	java/lang/Throwable
    //   1776	1789	1792	java/lang/Throwable
    //   1781	1804	1807	java/lang/Throwable
    //   1796	1822	1825	java/lang/Throwable
    //   1811	1852	1855	java/lang/Throwable
    //   1918	1945	1948	java/lang/Throwable
    //   1935	1966	1969	java/lang/Throwable
    //   1952	1996	1999	java/lang/Throwable
    //   1973	2007	2007	java/lang/Throwable
    //   2018	2034	2037	java/lang/Throwable
    //   2041	2131	2134	java/lang/Throwable
    //   2086	2183	2186	java/lang/Throwable
    //   2138	2194	2194	java/lang/Throwable
  }
  
  static void ZA(Object paramObject) {
    Zsgj.ZN = a(32718, 13656);
    Zsgj.ZK = new BigInteger(a(32715, -16934));
    boolean bool = Zt2e.ZK();
    try {
      try {
        if (Zg97.ZX.charAt(Math.abs(((BigInteger)Zxnm.ZW).intValue() % 32)) <= Zl1u.ZO.charAt(Math.abs(((BigInteger)Zbxp.ZW).intValue() % 32))) {
          try {
            Zbxp.Zo(Class.forName(a(32713, -23326)));
            if (bool)
              Zebj.Zp(Class.forName(a(32716, 29077))); 
          } catch (Throwable throwable) {
            throw a(null);
          } 
          return;
        } 
      } catch (Throwable throwable) {
        throw a(null);
      } 
      Zebj.Zp(Class.forName(a(32716, 29077)));
    } catch (Throwable throwable) {}
  }
  
  static {
    // Byte code:
    //   0: bipush #12
    //   2: anewarray java/lang/String
    //   5: astore #5
    //   7: iconst_0
    //   8: istore_3
    //   9: ldc 'Ã¬BÃžÂ¬Â¼Ã£)Â–Ã¡MÃ£ÂŽ@Ã¾Ã¿.Ã–B_Â‡'Â¥ÂŽÃžÃ†Â¾DÂ¡kÂ™Â”\>Ã®Â†ÂÂ‚Âº@DÂ¤ÂŠÂƒ[Ã¬Â¹B?WÂ ^Â¥ÃŠtÃ°wÃ°cÂ…Ã¯KTÂ»0Ã˜Â¨ÃŸkÃ·Â’Ez%Ã‹ÂšÃ¯ZÃ¸\\t)Â”fvÂ«Â¸Ã‚Ã½Ã±\\tÃŸÃ€Â¸Ã¼pÃ©Â¾Ã‹Â™ ;Â²Ã9Â—Ã¢Â…1Â›Â¤ÂžZÂ–Ã»ÃŠ?Ã«h+AÃ¬!hLNm\\t,UÃ†NÂ¿Â¿I\\rÂ®\\tÃ‹*:Â¡ BÂ¸Â¾Â…Ã¯tÂ¾j\\t\\fÃƒÃ‚Âœ?Ã¥[qÃ­'
    //   11: dup
    //   12: astore_2
    //   13: invokevirtual length : ()I
    //   16: istore #4
    //   18: bipush #9
    //   20: istore_1
    //   21: iconst_m1
    //   22: istore_0
    //   23: bipush #67
    //   25: iinc #0, 1
    //   28: aload_2
    //   29: iload_0
    //   30: dup
    //   31: iload_1
    //   32: iadd
    //   33: invokevirtual substring : (II)Ljava/lang/String;
    //   36: iconst_m1
    //   37: goto -> 143
    //   40: aload #5
    //   42: swap
    //   43: iload_3
    //   44: iinc #3, 1
    //   47: swap
    //   48: aastore
    //   49: iload_0
    //   50: iload_1
    //   51: iadd
    //   52: dup
    //   53: istore_0
    //   54: iload #4
    //   56: if_icmpge -> 68
    //   59: aload_2
    //   60: iload_0
    //   61: invokevirtual charAt : (I)C
    //   64: istore_1
    //   65: goto -> 23
    //   68: ldc 'Â¹Ã±Ãn#ÃžÃ{ÂŠ4Â–Ã¬Ã…9\Ã¾wÃŽÂ´QÂ Ã´Ã«Ã“YlÃŠt\\tÂ¥'LÂ»UÂºÂ­Âœ'
    //   70: dup
    //   71: astore_2
    //   72: invokevirtual length : ()I
    //   75: istore #4
    //   77: bipush #32
    //   79: istore_1
    //   80: iconst_m1
    //   81: istore_0
    //   82: bipush #127
    //   84: iinc #0, 1
    //   87: aload_2
    //   88: iload_0
    //   89: dup
    //   90: iload_1
    //   91: iadd
    //   92: invokevirtual substring : (II)Ljava/lang/String;
    //   95: iconst_0
    //   96: goto -> 143
    //   99: aload #5
    //   101: swap
    //   102: iload_3
    //   103: iinc #3, 1
    //   106: swap
    //   107: aastore
    //   108: iload_0
    //   109: iload_1
    //   110: iadd
    //   111: dup
    //   112: istore_0
    //   113: iload #4
    //   115: if_icmpge -> 127
    //   118: aload_2
    //   119: iload_0
    //   120: invokevirtual charAt : (I)C
    //   123: istore_1
    //   124: goto -> 82
    //   127: aload #5
    //   129: putstatic burp/Zb9k.a : [Ljava/lang/String;
    //   132: bipush #12
    //   134: anewarray java/lang/String
    //   137: putstatic burp/Zb9k.b : [Ljava/lang/String;
    //   140: goto -> 300
    //   143: dup_x2
    //   144: pop
    //   145: invokevirtual toCharArray : ()[C
    //   148: dup_x1
    //   149: arraylength
    //   150: dup_x2
    //   151: pop
    //   152: iconst_0
    //   153: istore #6
    //   155: dup2_x1
    //   156: pop2
    //   157: dup_x2
    //   158: iconst_1
    //   159: if_icmpgt -> 260
    //   162: dup2
    //   163: swap
    //   164: iload #6
    //   166: dup2_x1
    //   167: caload
    //   168: swap
    //   169: iload #6
    //   171: bipush #7
    //   173: irem
    //   174: tableswitch default -> 242, 0 -> 212, 1 -> 217, 2 -> 222, 3 -> 227, 4 -> 232, 5 -> 237
    //   212: bipush #34
    //   214: goto -> 244
    //   217: bipush #104
    //   219: goto -> 244
    //   222: bipush #112
    //   224: goto -> 244
    //   227: bipush #105
    //   229: goto -> 244
    //   232: bipush #80
    //   234: goto -> 244
    //   237: bipush #84
    //   239: goto -> 244
    //   242: bipush #14
    //   244: ixor
    //   245: ixor
    //   246: i2c
    //   247: castore
    //   248: iinc #6, 1
    //   251: dup
    //   252: ifne -> 260
    //   255: dup2
    //   256: dup_x1
    //   257: goto -> 166
    //   260: dup2_x1
    //   261: pop2
    //   262: dup_x2
    //   263: iload #6
    //   265: if_icmpgt -> 162
    //   268: pop
    //   269: new java/lang/String
    //   272: dup_x1
    //   273: swap
    //   274: invokespecial <init> : ([C)V
    //   277: invokevirtual intern : ()Ljava/lang/String;
    //   280: swap
    //   281: pop
    //   282: swap
    //   283: tableswitch default -> 40, 0 -> 99
    //   300: new java/math/BigInteger
    //   303: dup
    //   304: iconst_1
    //   305: bipush #32
    //   307: newarray byte
    //   309: dup
    //   310: iconst_0
    //   311: bipush #94
    //   313: bastore
    //   314: dup
    //   315: iconst_1
    //   316: bipush #-99
    //   318: bastore
    //   319: dup
    //   320: iconst_2
    //   321: bipush #-47
    //   323: bastore
    //   324: dup
    //   325: iconst_3
    //   326: bipush #-31
    //   328: bastore
    //   329: dup
    //   330: iconst_4
    //   331: bipush #18
    //   333: bastore
    //   334: dup
    //   335: iconst_5
    //   336: bipush #114
    //   338: bastore
    //   339: dup
    //   340: bipush #6
    //   342: bipush #18
    //   344: bastore
    //   345: dup
    //   346: bipush #7
    //   348: bipush #-60
    //   350: bastore
    //   351: dup
    //   352: bipush #8
    //   354: bipush #-115
    //   356: bastore
    //   357: dup
    //   358: bipush #9
    //   360: bipush #93
    //   362: bastore
    //   363: dup
    //   364: bipush #10
    //   366: bipush #70
    //   368: bastore
    //   369: dup
    //   370: bipush #11
    //   372: bipush #57
    //   374: bastore
    //   375: dup
    //   376: bipush #12
    //   378: bipush #-78
    //   380: bastore
    //   381: dup
    //   382: bipush #13
    //   384: bipush #56
    //   386: bastore
    //   387: dup
    //   388: bipush #14
    //   390: iconst_0
    //   391: bastore
    //   392: dup
    //   393: bipush #15
    //   395: bipush #44
    //   397: bastore
    //   398: dup
    //   399: bipush #16
    //   401: bipush #41
    //   403: bastore
    //   404: dup
    //   405: bipush #17
    //   407: bipush #41
    //   409: bastore
    //   410: dup
    //   411: bipush #18
    //   413: bipush #63
    //   415: bastore
    //   416: dup
    //   417: bipush #19
    //   419: bipush #-79
    //   421: bastore
    //   422: dup
    //   423: bipush #20
    //   425: bipush #60
    //   427: bastore
    //   428: dup
    //   429: bipush #21
    //   431: bipush #-70
    //   433: bastore
    //   434: dup
    //   435: bipush #22
    //   437: bipush #62
    //   439: bastore
    //   440: dup
    //   441: bipush #23
    //   443: bipush #102
    //   445: bastore
    //   446: dup
    //   447: bipush #24
    //   449: bipush #116
    //   451: bastore
    //   452: dup
    //   453: bipush #25
    //   455: bipush #37
    //   457: bastore
    //   458: dup
    //   459: bipush #26
    //   461: bipush #69
    //   463: bastore
    //   464: dup
    //   465: bipush #27
    //   467: bipush #7
    //   469: bastore
    //   470: dup
    //   471: bipush #28
    //   473: bipush #-66
    //   475: bastore
    //   476: dup
    //   477: bipush #29
    //   479: bipush #-47
    //   481: bastore
    //   482: dup
    //   483: bipush #30
    //   485: bipush #-25
    //   487: bastore
    //   488: dup
    //   489: bipush #31
    //   491: bipush #120
    //   493: bastore
    //   494: invokespecial <init> : (I[B)V
    //   497: putstatic burp/Zb9k.Zi : Ljava/lang/Object;
    //   500: sipush #32704
    //   503: sipush #-8507
    //   506: invokestatic a : (II)Ljava/lang/String;
    //   509: putstatic burp/Zb9k.Za : Ljava/lang/String;
    //   512: return
  }
  
  private static Throwable a(Throwable paramThrowable) {
    return paramThrowable;
  }
  
  private static String a(int paramInt1, int paramInt2) {
    int i = (paramInt1 ^ 0x7FCA) & 0xFFFF;
    if (b[i] == null) {
      char[] arrayOfChar = a[i].toCharArray();
      switch (arrayOfChar[0] & 0xFF) {
        case 0:
        
        case 1:
        
        case 2:
        
        case 3:
        
        case 4:
        
        case 5:
        
        case 6:
        
        case 7:
        
        case 8:
        
        case 9:
        
        case 10:
        
        case 11:
        
        case 12:
        
        case 13:
        
        case 14:
        
        case 15:
        
        case 16:
        
        case 17:
        
        case 18:
        
        case 19:
        
        case 20:
        
        case 21:
        
        case 22:
        
        case 23:
        
        case 24:
        
        case 25:
        
        case 26:
        
        case 27:
        
        case 28:
        
        case 29:
        
        case 30:
        
        case 31:
        
        case 32:
        
        case 33:
        
        case 34:
        
        case 35:
        
        case 36:
        
        case 37:
        
        case 38:
        
        case 39:
        
        case 40:
        
        case 41:
        
        case 42:
        
        case 43:
        
        case 44:
        
        case 45:
        
        case 46:
        
        case 47:
        
        case 48:
        
        case 49:
        
        case 50:
        
        case 51:
        
        case 52:
        
        case 53:
        
        case 54:
        
        case 55:
        
        case 56:
        
        case 57:
        
        case 58:
        
        case 59:
        
        case 60:
        
        case 61:
        
        case 62:
        
        case 63:
        
        case 64:
        
        case 65:
        
        case 66:
        
        case 67:
        
        case 68:
        
        case 69:
        
        case 70:
        
        case 71:
        
        case 72:
        
        case 73:
        
        case 74:
        
        case 75:
        
        case 76:
        
        case 77:
        
        case 78:
        
        case 79:
        
        case 80:
        
        case 81:
        
        case 82:
        
        case 83:
        
        case 84:
        
        case 85:
        
        case 86:
        
        case 87:
        
        case 88:
        
        case 89:
        
        case 90:
        
        case 91:
        
        case 92:
        
        case 93:
        
        case 94:
        
        case 95:
        
        case 96:
        
        case 97:
        
        case 98:
        
        case 99:
        
        case 100:
        
        case 101:
        
        case 102:
        
        case 103:
        
        case 104:
        
        case 105:
        
        case 106:
        
        case 107:
        
        case 108:
        
        case 109:
        
        case 110:
        
        case 111:
        
        case 112:
        
        case 113:
        
        case 114:
        
        case 115:
        
        case 116:
        
        case 117:
        
        case 118:
        
        case 119:
        
        case 120:
        
        case 121:
        
        case 122:
        
        case 123:
        
        case 124:
        
        case 125:
        
        case 126:
        
        case 127:
        
        case 128:
        
        case 129:
        
        case 130:
        
        case 131:
        
        case 132:
        
        case 133:
        
        case 134:
        
        case 135:
        
        case 136:
        
        case 137:
        
        case 138:
        
        case 139:
        
        case 140:
        
        case 141:
        
        case 142:
        
        case 143:
        
        case 144:
        
        case 145:
        
        case 146:
        
        case 147:
        
        case 148:
        
        case 149:
        
        case 150:
        
        case 151:
        
        case 152:
        
        case 153:
        
        case 154:
        
        case 155:
        
        case 156:
        
        case 157:
        
        case 158:
        
        case 159:
        
        case 160:
        
        case 161:
        
        case 162:
        
        case 163:
        
        case 164:
        
        case 165:
        
        case 166:
        
        case 167:
        
        case 168:
        
        case 169:
        
        case 170:
        
        case 171:
        
        case 172:
        
        case 173:
        
        case 174:
        
        case 175:
        
        case 176:
        
        case 177:
        
        case 178:
        
        case 179:
        
        case 180:
        
        case 181:
        
        case 182:
        
        case 183:
        
        case 184:
        
        case 185:
        
        case 186:
        
        case 187:
        
        case 188:
        
        case 189:
        
        case 190:
        
        case 191:
        
        case 192:
        
        case 193:
        
        case 194:
        
        case 195:
        
        case 196:
        
        case 197:
        
        case 198:
        
        case 199:
        
        case 200:
        
        case 201:
        
        case 202:
        
        case 203:
        
        case 204:
        
        case 205:
        
        case 206:
        
        case 207:
        
        case 208:
        
        case 209:
        
        case 210:
        
        case 211:
        
        case 212:
        
        case 213:
        
        case 214:
        
        case 215:
        
        case 216:
        
        case 217:
        
        case 218:
        
        case 219:
        
        case 220:
        
        case 221:
        
        case 222:
        
        case 223:
        
        case 224:
        
        case 225:
        
        case 226:
        
        case 227:
        
        case 228:
        
        case 229:
        
        case 230:
        
        case 231:
        
        case 232:
        
        case 233:
        
        case 234:
        
        case 235:
        
        case 236:
        
        case 237:
        
        case 238:
        
        case 239:
        
        case 240:
        
        case 241:
        
        case 242:
        
        case 243:
        
        case 244:
        
        case 245:
        
        case 246:
        
        case 247:
        
        case 248:
        
        case 249:
        
        case 250:
        
        case 251:
        
        case 252:
        
        case 253:
        
        case 254:
        
        default:
          break;
      } 
      byte b1 = 77;
      int j = (paramInt2 & 0xFF) - b1;
      if (j < 0)
        j += 256; 
      int k = ((paramInt2 & 0xFFFF) >>> 8) - b1;
      if (k < 0)
        k += 256; 
      for (byte b2 = 0; b2 < arrayOfChar.length; b2++) {
        int m = b2 % 2;
        if (m == 0) {
          arrayOfChar[b2] = (char)(arrayOfChar[b2] ^ j);
          j = ((j >>> 3 | j << 5) ^ arrayOfChar[b2]) & 0xFF;
        } else {
          arrayOfChar[b2] = (char)(arrayOfChar[b2] ^ k);
          k = ((k >>> 3 | k << 5) ^ arrayOfChar[b2]) & 0xFF;
        } 
      } 
      b[i] = (new String(arrayOfChar)).intern();
    } 
    return b[i];
  }
}


/* Location:              C:\Program Files\BurpSuitePro\burpsuite_pro.jar!\burp\Zb9k.class
 * Java compiler version: 21 (65.0)
 * JD-Core Version:       1.1.3
 */