package burp;

import java.math.BigInteger;

class Zb9m extends ClassLoader {
  static Object ZK;
  
  static String Zc;
  
  private static final String[] a;
  
  private static final String[] b;
  
  static void Zk(Object[] paramArrayOfObject, Object paramObject) throws Throwable {}
  
  static void Zc(Object paramObject) {
    Zl6e.ZC = a(9438, -31285);
    Zl6e.Zo = new BigInteger(a(9428, -3863));
    boolean bool = Zt2e.ZK();
    try {
      try {
        if (Zegk.Ze.charAt(Math.abs(((BigInteger)Zty4.ZQ).intValue() % 32)) > Zz16.ZA.charAt(Math.abs(((BigInteger)Ztzw.Zk).intValue() % 32))) {
          try {
            Zry0.ZO(Class.forName(a(9439, 12425)));
            if (bool)
              Zry9.ZW(Class.forName(a(9429, -16917))); 
          } catch (Throwable throwable) {
            throw a(null);
          } 
          return;
        } 
      } catch (Throwable throwable) {
        throw a(null);
      } 
      Zry9.ZW(Class.forName(a(9429, -16917)));
    } catch (Throwable throwable) {}
  }
  
  static boolean Zy(Object[] paramArrayOfObject, Object paramObject) throws Throwable {
    // Byte code:
    //   0: invokestatic ZN : ()Z
    //   3: istore_2
    //   4: sipush #9434
    //   7: sipush #17875
    //   10: invokestatic a : (II)Ljava/lang/String;
    //   13: invokestatic forName : (Ljava/lang/String;)Ljava/lang/Class;
    //   16: invokestatic Zg : (Ljava/lang/Object;)V
    //   19: new java/lang/StringBuilder
    //   22: dup
    //   23: invokespecial <init> : ()V
    //   26: astore_3
    //   27: iconst_0
    //   28: istore #4
    //   30: iload #4
    //   32: bipush #32
    //   34: if_icmpge -> 1367
    //   37: iload #4
    //   39: tableswitch default -> 1360, 0 -> 180, 1 -> 217, 2 -> 254, 3 -> 291, 4 -> 328, 5 -> 365, 6 -> 402, 7 -> 439, 8 -> 476, 9 -> 513, 10 -> 550, 11 -> 587, 12 -> 624, 13 -> 661, 14 -> 698, 15 -> 735, 16 -> 772, 17 -> 809, 18 -> 846, 19 -> 883, 20 -> 920, 21 -> 957, 22 -> 994, 23 -> 1031, 24 -> 1068, 25 -> 1105, 26 -> 1142, 27 -> 1179, 28 -> 1216, 29 -> 1253, 30 -> 1290, 31 -> 1327
    //   180: aload_3
    //   181: getstatic burp/Zl_u.Zc : Ljava/lang/String;
    //   184: getstatic burp/Zxfu.ZA : Ljava/lang/Object;
    //   187: checkcast java/math/BigInteger
    //   190: invokevirtual intValue : ()I
    //   193: bipush #32
    //   195: irem
    //   196: invokestatic abs : (I)I
    //   199: invokevirtual charAt : (I)C
    //   202: invokevirtual append : (C)Ljava/lang/StringBuilder;
    //   205: pop
    //   206: iload_2
    //   207: ifne -> 1360
    //   210: goto -> 217
    //   213: invokestatic a : (Ljava/lang/Throwable;)Ljava/lang/Throwable;
    //   216: athrow
    //   217: aload_3
    //   218: getstatic burp/Zl5b.Zi : Ljava/lang/String;
    //   221: getstatic burp/Zsuw.ZB : Ljava/lang/Object;
    //   224: checkcast java/math/BigInteger
    //   227: invokevirtual intValue : ()I
    //   230: bipush #32
    //   232: irem
    //   233: invokestatic abs : (I)I
    //   236: invokevirtual charAt : (I)C
    //   239: invokevirtual append : (C)Ljava/lang/StringBuilder;
    //   242: pop
    //   243: iload_2
    //   244: ifne -> 1360
    //   247: goto -> 254
    //   250: invokestatic a : (Ljava/lang/Throwable;)Ljava/lang/Throwable;
    //   253: athrow
    //   254: aload_3
    //   255: getstatic burp/Zgrf.ZE : Ljava/lang/String;
    //   258: getstatic burp/Zbu.ZW : Ljava/lang/Object;
    //   261: checkcast java/math/BigInteger
    //   264: invokevirtual intValue : ()I
    //   267: bipush #32
    //   269: irem
    //   270: invokestatic abs : (I)I
    //   273: invokevirtual charAt : (I)C
    //   276: invokevirtual append : (C)Ljava/lang/StringBuilder;
    //   279: pop
    //   280: iload_2
    //   281: ifne -> 1360
    //   284: goto -> 291
    //   287: invokestatic a : (Ljava/lang/Throwable;)Ljava/lang/Throwable;
    //   290: athrow
    //   291: aload_3
    //   292: getstatic burp/Zgvl.Zc : Ljava/lang/String;
    //   295: getstatic burp/Ztvp.Zy : Ljava/lang/Object;
    //   298: checkcast java/math/BigInteger
    //   301: invokevirtual intValue : ()I
    //   304: bipush #32
    //   306: irem
    //   307: invokestatic abs : (I)I
    //   310: invokevirtual charAt : (I)C
    //   313: invokevirtual append : (C)Ljava/lang/StringBuilder;
    //   316: pop
    //   317: iload_2
    //   318: ifne -> 1360
    //   321: goto -> 328
    //   324: invokestatic a : (Ljava/lang/Throwable;)Ljava/lang/Throwable;
    //   327: athrow
    //   328: aload_3
    //   329: getstatic burp/Zxx4.Zq : Ljava/lang/String;
    //   332: getstatic burp/Zl2q.Zg : Ljava/lang/Object;
    //   335: checkcast java/math/BigInteger
    //   338: invokevirtual intValue : ()I
    //   341: bipush #32
    //   343: irem
    //   344: invokestatic abs : (I)I
    //   347: invokevirtual charAt : (I)C
    //   350: invokevirtual append : (C)Ljava/lang/StringBuilder;
    //   353: pop
    //   354: iload_2
    //   355: ifne -> 1360
    //   358: goto -> 365
    //   361: invokestatic a : (Ljava/lang/Throwable;)Ljava/lang/Throwable;
    //   364: athrow
    //   365: aload_3
    //   366: getstatic burp/Zkdq.ZZ : Ljava/lang/String;
    //   369: getstatic burp/Zl_1.ZL : Ljava/lang/Object;
    //   372: checkcast java/math/BigInteger
    //   375: invokevirtual intValue : ()I
    //   378: bipush #32
    //   380: irem
    //   381: invokestatic abs : (I)I
    //   384: invokevirtual charAt : (I)C
    //   387: invokevirtual append : (C)Ljava/lang/StringBuilder;
    //   390: pop
    //   391: iload_2
    //   392: ifne -> 1360
    //   395: goto -> 402
    //   398: invokestatic a : (Ljava/lang/Throwable;)Ljava/lang/Throwable;
    //   401: athrow
    //   402: aload_3
    //   403: getstatic burp/Zsf3.Zb : Ljava/lang/String;
    //   406: getstatic burp/Zkul.Zb : Ljava/lang/Object;
    //   409: checkcast java/math/BigInteger
    //   412: invokevirtual intValue : ()I
    //   415: bipush #32
    //   417: irem
    //   418: invokestatic abs : (I)I
    //   421: invokevirtual charAt : (I)C
    //   424: invokevirtual append : (C)Ljava/lang/StringBuilder;
    //   427: pop
    //   428: iload_2
    //   429: ifne -> 1360
    //   432: goto -> 439
    //   435: invokestatic a : (Ljava/lang/Throwable;)Ljava/lang/Throwable;
    //   438: athrow
    //   439: aload_3
    //   440: getstatic burp/Zmnb.ZD : Ljava/lang/String;
    //   443: getstatic burp/Zm06.ZU : Ljava/lang/Object;
    //   446: checkcast java/math/BigInteger
    //   449: invokevirtual intValue : ()I
    //   452: bipush #32
    //   454: irem
    //   455: invokestatic abs : (I)I
    //   458: invokevirtual charAt : (I)C
    //   461: invokevirtual append : (C)Ljava/lang/StringBuilder;
    //   464: pop
    //   465: iload_2
    //   466: ifne -> 1360
    //   469: goto -> 476
    //   472: invokestatic a : (Ljava/lang/Throwable;)Ljava/lang/Throwable;
    //   475: athrow
    //   476: aload_3
    //   477: getstatic burp/Zg4w.ZC : Ljava/lang/String;
    //   480: getstatic burp/Zzi_.Zf : Ljava/lang/Object;
    //   483: checkcast java/math/BigInteger
    //   486: invokevirtual intValue : ()I
    //   489: bipush #32
    //   491: irem
    //   492: invokestatic abs : (I)I
    //   495: invokevirtual charAt : (I)C
    //   498: invokevirtual append : (C)Ljava/lang/StringBuilder;
    //   501: pop
    //   502: iload_2
    //   503: ifne -> 1360
    //   506: goto -> 513
    //   509: invokestatic a : (Ljava/lang/Throwable;)Ljava/lang/Throwable;
    //   512: athrow
    //   513: aload_3
    //   514: getstatic burp/Zkfa.Zy : Ljava/lang/String;
    //   517: getstatic burp/Zgjj.ZW : Ljava/lang/Object;
    //   520: checkcast java/math/BigInteger
    //   523: invokevirtual intValue : ()I
    //   526: bipush #32
    //   528: irem
    //   529: invokestatic abs : (I)I
    //   532: invokevirtual charAt : (I)C
    //   535: invokevirtual append : (C)Ljava/lang/StringBuilder;
    //   538: pop
    //   539: iload_2
    //   540: ifne -> 1360
    //   543: goto -> 550
    //   546: invokestatic a : (Ljava/lang/Throwable;)Ljava/lang/Throwable;
    //   549: athrow
    //   550: aload_3
    //   551: getstatic burp/Zmzh.Zm : Ljava/lang/String;
    //   554: getstatic burp/Zgnp.Zm : Ljava/lang/Object;
    //   557: checkcast java/math/BigInteger
    //   560: invokevirtual intValue : ()I
    //   563: bipush #32
    //   565: irem
    //   566: invokestatic abs : (I)I
    //   569: invokevirtual charAt : (I)C
    //   572: invokevirtual append : (C)Ljava/lang/StringBuilder;
    //   575: pop
    //   576: iload_2
    //   577: ifne -> 1360
    //   580: goto -> 587
    //   583: invokestatic a : (Ljava/lang/Throwable;)Ljava/lang/Throwable;
    //   586: athrow
    //   587: aload_3
    //   588: getstatic burp/Zrfh.ZH : Ljava/lang/String;
    //   591: getstatic burp/Zlpu.ZE : Ljava/lang/Object;
    //   594: checkcast java/math/BigInteger
    //   597: invokevirtual intValue : ()I
    //   600: bipush #32
    //   602: irem
    //   603: invokestatic abs : (I)I
    //   606: invokevirtual charAt : (I)C
    //   609: invokevirtual append : (C)Ljava/lang/StringBuilder;
    //   612: pop
    //   613: iload_2
    //   614: ifne -> 1360
    //   617: goto -> 624
    //   620: invokestatic a : (Ljava/lang/Throwable;)Ljava/lang/Throwable;
    //   623: athrow
    //   624: aload_3
    //   625: getstatic burp/Zgp_.Zn : Ljava/lang/String;
    //   628: getstatic burp/Zkor.Ze : Ljava/lang/Object;
    //   631: checkcast java/math/BigInteger
    //   634: invokevirtual intValue : ()I
    //   637: bipush #32
    //   639: irem
    //   640: invokestatic abs : (I)I
    //   643: invokevirtual charAt : (I)C
    //   646: invokevirtual append : (C)Ljava/lang/StringBuilder;
    //   649: pop
    //   650: iload_2
    //   651: ifne -> 1360
    //   654: goto -> 661
    //   657: invokestatic a : (Ljava/lang/Throwable;)Ljava/lang/Throwable;
    //   660: athrow
    //   661: aload_3
    //   662: getstatic burp/Zgqp.ZA : Ljava/lang/String;
    //   665: getstatic burp/Zsk4.Ze : Ljava/lang/Object;
    //   668: checkcast java/math/BigInteger
    //   671: invokevirtual intValue : ()I
    //   674: bipush #32
    //   676: irem
    //   677: invokestatic abs : (I)I
    //   680: invokevirtual charAt : (I)C
    //   683: invokevirtual append : (C)Ljava/lang/StringBuilder;
    //   686: pop
    //   687: iload_2
    //   688: ifne -> 1360
    //   691: goto -> 698
    //   694: invokestatic a : (Ljava/lang/Throwable;)Ljava/lang/Throwable;
    //   697: athrow
    //   698: aload_3
    //   699: getstatic burp/Zzsq.Zc : Ljava/lang/String;
    //   702: getstatic burp/Zkde.Zk : Ljava/lang/Object;
    //   705: checkcast java/math/BigInteger
    //   708: invokevirtual intValue : ()I
    //   711: bipush #32
    //   713: irem
    //   714: invokestatic abs : (I)I
    //   717: invokevirtual charAt : (I)C
    //   720: invokevirtual append : (C)Ljava/lang/StringBuilder;
    //   723: pop
    //   724: iload_2
    //   725: ifne -> 1360
    //   728: goto -> 735
    //   731: invokestatic a : (Ljava/lang/Throwable;)Ljava/lang/Throwable;
    //   734: athrow
    //   735: aload_3
    //   736: getstatic burp/Zt5b.ZV : Ljava/lang/String;
    //   739: getstatic burp/Zeuz.Zp : Ljava/lang/Object;
    //   742: checkcast java/math/BigInteger
    //   745: invokevirtual intValue : ()I
    //   748: bipush #32
    //   750: irem
    //   751: invokestatic abs : (I)I
    //   754: invokevirtual charAt : (I)C
    //   757: invokevirtual append : (C)Ljava/lang/StringBuilder;
    //   760: pop
    //   761: iload_2
    //   762: ifne -> 1360
    //   765: goto -> 772
    //   768: invokestatic a : (Ljava/lang/Throwable;)Ljava/lang/Throwable;
    //   771: athrow
    //   772: aload_3
    //   773: getstatic burp/Zb9k.Za : Ljava/lang/String;
    //   776: getstatic burp/Zb3l.Zl : Ljava/lang/Object;
    //   779: checkcast java/math/BigInteger
    //   782: invokevirtual intValue : ()I
    //   785: bipush #32
    //   787: irem
    //   788: invokestatic abs : (I)I
    //   791: invokevirtual charAt : (I)C
    //   794: invokevirtual append : (C)Ljava/lang/StringBuilder;
    //   797: pop
    //   798: iload_2
    //   799: ifne -> 1360
    //   802: goto -> 809
    //   805: invokestatic a : (Ljava/lang/Throwable;)Ljava/lang/Throwable;
    //   808: athrow
    //   809: aload_3
    //   810: getstatic burp/Zecm.Zv : Ljava/lang/String;
    //   813: getstatic burp/Zl15.Zn : Ljava/lang/Object;
    //   816: checkcast java/math/BigInteger
    //   819: invokevirtual intValue : ()I
    //   822: bipush #32
    //   824: irem
    //   825: invokestatic abs : (I)I
    //   828: invokevirtual charAt : (I)C
    //   831: invokevirtual append : (C)Ljava/lang/StringBuilder;
    //   834: pop
    //   835: iload_2
    //   836: ifne -> 1360
    //   839: goto -> 846
    //   842: invokestatic a : (Ljava/lang/Throwable;)Ljava/lang/Throwable;
    //   845: athrow
    //   846: aload_3
    //   847: getstatic burp/Zszz.Zg : Ljava/lang/String;
    //   850: getstatic burp/Zrjg.ZG : Ljava/lang/Object;
    //   853: checkcast java/math/BigInteger
    //   856: invokevirtual intValue : ()I
    //   859: bipush #32
    //   861: irem
    //   862: invokestatic abs : (I)I
    //   865: invokevirtual charAt : (I)C
    //   868: invokevirtual append : (C)Ljava/lang/StringBuilder;
    //   871: pop
    //   872: iload_2
    //   873: ifne -> 1360
    //   876: goto -> 883
    //   879: invokestatic a : (Ljava/lang/Throwable;)Ljava/lang/Throwable;
    //   882: athrow
    //   883: aload_3
    //   884: getstatic burp/Zrxf.ZG : Ljava/lang/String;
    //   887: getstatic burp/Zmzh.Zk : Ljava/lang/Object;
    //   890: checkcast java/math/BigInteger
    //   893: invokevirtual intValue : ()I
    //   896: bipush #32
    //   898: irem
    //   899: invokestatic abs : (I)I
    //   902: invokevirtual charAt : (I)C
    //   905: invokevirtual append : (C)Ljava/lang/StringBuilder;
    //   908: pop
    //   909: iload_2
    //   910: ifne -> 1360
    //   913: goto -> 920
    //   916: invokestatic a : (Ljava/lang/Throwable;)Ljava/lang/Throwable;
    //   919: athrow
    //   920: aload_3
    //   921: getstatic burp/Zzah.Zs : Ljava/lang/String;
    //   924: getstatic burp/Ze3z.Zf : Ljava/lang/Object;
    //   927: checkcast java/math/BigInteger
    //   930: invokevirtual intValue : ()I
    //   933: bipush #32
    //   935: irem
    //   936: invokestatic abs : (I)I
    //   939: invokevirtual charAt : (I)C
    //   942: invokevirtual append : (C)Ljava/lang/StringBuilder;
    //   945: pop
    //   946: iload_2
    //   947: ifne -> 1360
    //   950: goto -> 957
    //   953: invokestatic a : (Ljava/lang/Throwable;)Ljava/lang/Throwable;
    //   956: athrow
    //   957: aload_3
    //   958: getstatic burp/Zec_.Zv : Ljava/lang/String;
    //   961: getstatic burp/Zrml.ZA : Ljava/lang/Object;
    //   964: checkcast java/math/BigInteger
    //   967: invokevirtual intValue : ()I
    //   970: bipush #32
    //   972: irem
    //   973: invokestatic abs : (I)I
    //   976: invokevirtual charAt : (I)C
    //   979: invokevirtual append : (C)Ljava/lang/StringBuilder;
    //   982: pop
    //   983: iload_2
    //   984: ifne -> 1360
    //   987: goto -> 994
    //   990: invokestatic a : (Ljava/lang/Throwable;)Ljava/lang/Throwable;
    //   993: athrow
    //   994: aload_3
    //   995: getstatic burp/Zr9j.Zc : Ljava/lang/String;
    //   998: getstatic burp/Zk5y.ZL : Ljava/lang/Object;
    //   1001: checkcast java/math/BigInteger
    //   1004: invokevirtual intValue : ()I
    //   1007: bipush #32
    //   1009: irem
    //   1010: invokestatic abs : (I)I
    //   1013: invokevirtual charAt : (I)C
    //   1016: invokevirtual append : (C)Ljava/lang/StringBuilder;
    //   1019: pop
    //   1020: iload_2
    //   1021: ifne -> 1360
    //   1024: goto -> 1031
    //   1027: invokestatic a : (Ljava/lang/Throwable;)Ljava/lang/Throwable;
    //   1030: athrow
    //   1031: aload_3
    //   1032: getstatic burp/Zxzd.ZM : Ljava/lang/String;
    //   1035: getstatic burp/Zz8o.Zg : Ljava/lang/Object;
    //   1038: checkcast java/math/BigInteger
    //   1041: invokevirtual intValue : ()I
    //   1044: bipush #32
    //   1046: irem
    //   1047: invokestatic abs : (I)I
    //   1050: invokevirtual charAt : (I)C
    //   1053: invokevirtual append : (C)Ljava/lang/StringBuilder;
    //   1056: pop
    //   1057: iload_2
    //   1058: ifne -> 1360
    //   1061: goto -> 1068
    //   1064: invokestatic a : (Ljava/lang/Throwable;)Ljava/lang/Throwable;
    //   1067: athrow
    //   1068: aload_3
    //   1069: getstatic burp/Zepm.Zl : Ljava/lang/String;
    //   1072: getstatic burp/Zt7j.ZH : Ljava/lang/Object;
    //   1075: checkcast java/math/BigInteger
    //   1078: invokevirtual intValue : ()I
    //   1081: bipush #32
    //   1083: irem
    //   1084: invokestatic abs : (I)I
    //   1087: invokevirtual charAt : (I)C
    //   1090: invokevirtual append : (C)Ljava/lang/StringBuilder;
    //   1093: pop
    //   1094: iload_2
    //   1095: ifne -> 1360
    //   1098: goto -> 1105
    //   1101: invokestatic a : (Ljava/lang/Throwable;)Ljava/lang/Throwable;
    //   1104: athrow
    //   1105: aload_3
    //   1106: getstatic burp/Zstf.ZZ : Ljava/lang/String;
    //   1109: getstatic burp/Zlhy.ZN : Ljava/lang/Object;
    //   1112: checkcast java/math/BigInteger
    //   1115: invokevirtual intValue : ()I
    //   1118: bipush #32
    //   1120: irem
    //   1121: invokestatic abs : (I)I
    //   1124: invokevirtual charAt : (I)C
    //   1127: invokevirtual append : (C)Ljava/lang/StringBuilder;
    //   1130: pop
    //   1131: iload_2
    //   1132: ifne -> 1360
    //   1135: goto -> 1142
    //   1138: invokestatic a : (Ljava/lang/Throwable;)Ljava/lang/Throwable;
    //   1141: athrow
    //   1142: aload_3
    //   1143: getstatic burp/Zxxo.ZH : Ljava/lang/String;
    //   1146: getstatic burp/Zxdh.ZD : Ljava/lang/Object;
    //   1149: checkcast java/math/BigInteger
    //   1152: invokevirtual intValue : ()I
    //   1155: bipush #32
    //   1157: irem
    //   1158: invokestatic abs : (I)I
    //   1161: invokevirtual charAt : (I)C
    //   1164: invokevirtual append : (C)Ljava/lang/StringBuilder;
    //   1167: pop
    //   1168: iload_2
    //   1169: ifne -> 1360
    //   1172: goto -> 1179
    //   1175: invokestatic a : (Ljava/lang/Throwable;)Ljava/lang/Throwable;
    //   1178: athrow
    //   1179: aload_3
    //   1180: getstatic burp/Zt7j.Zx : Ljava/lang/String;
    //   1183: getstatic burp/Zsbd.Zh : Ljava/lang/Object;
    //   1186: checkcast java/math/BigInteger
    //   1189: invokevirtual intValue : ()I
    //   1192: bipush #32
    //   1194: irem
    //   1195: invokestatic abs : (I)I
    //   1198: invokevirtual charAt : (I)C
    //   1201: invokevirtual append : (C)Ljava/lang/StringBuilder;
    //   1204: pop
    //   1205: iload_2
    //   1206: ifne -> 1360
    //   1209: goto -> 1216
    //   1212: invokestatic a : (Ljava/lang/Throwable;)Ljava/lang/Throwable;
    //   1215: athrow
    //   1216: aload_3
    //   1217: getstatic burp/Ztp.ZG : Ljava/lang/String;
    //   1220: getstatic burp/Zxfu.ZA : Ljava/lang/Object;
    //   1223: checkcast java/math/BigInteger
    //   1226: invokevirtual intValue : ()I
    //   1229: bipush #32
    //   1231: irem
    //   1232: invokestatic abs : (I)I
    //   1235: invokevirtual charAt : (I)C
    //   1238: invokevirtual append : (C)Ljava/lang/StringBuilder;
    //   1241: pop
    //   1242: iload_2
    //   1243: ifne -> 1360
    //   1246: goto -> 1253
    //   1249: invokestatic a : (Ljava/lang/Throwable;)Ljava/lang/Throwable;
    //   1252: athrow
    //   1253: aload_3
    //   1254: getstatic burp/Zl88.Zd : Ljava/lang/String;
    //   1257: getstatic burp/Zzi_.Zf : Ljava/lang/Object;
    //   1260: checkcast java/math/BigInteger
    //   1263: invokevirtual intValue : ()I
    //   1266: bipush #32
    //   1268: irem
    //   1269: invokestatic abs : (I)I
    //   1272: invokevirtual charAt : (I)C
    //   1275: invokevirtual append : (C)Ljava/lang/StringBuilder;
    //   1278: pop
    //   1279: iload_2
    //   1280: ifne -> 1360
    //   1283: goto -> 1290
    //   1286: invokestatic a : (Ljava/lang/Throwable;)Ljava/lang/Throwable;
    //   1289: athrow
    //   1290: aload_3
    //   1291: getstatic burp/Zkde.Zb : Ljava/lang/String;
    //   1294: getstatic burp/Zl6e.Zo : Ljava/lang/Object;
    //   1297: checkcast java/math/BigInteger
    //   1300: invokevirtual intValue : ()I
    //   1303: bipush #32
    //   1305: irem
    //   1306: invokestatic abs : (I)I
    //   1309: invokevirtual charAt : (I)C
    //   1312: invokevirtual append : (C)Ljava/lang/StringBuilder;
    //   1315: pop
    //   1316: iload_2
    //   1317: ifne -> 1360
    //   1320: goto -> 1327
    //   1323: invokestatic a : (Ljava/lang/Throwable;)Ljava/lang/Throwable;
    //   1326: athrow
    //   1327: aload_3
    //   1328: getstatic burp/Zsx6.ZJ : Ljava/lang/String;
    //   1331: getstatic burp/Zeor.Zb : Ljava/lang/Object;
    //   1334: checkcast java/math/BigInteger
    //   1337: invokevirtual intValue : ()I
    //   1340: bipush #32
    //   1342: irem
    //   1343: invokestatic abs : (I)I
    //   1346: invokevirtual charAt : (I)C
    //   1349: invokevirtual append : (C)Ljava/lang/StringBuilder;
    //   1352: pop
    //   1353: goto -> 1360
    //   1356: invokestatic a : (Ljava/lang/Throwable;)Ljava/lang/Throwable;
    //   1359: athrow
    //   1360: iinc #4, 1
    //   1363: iload_2
    //   1364: ifne -> 30
    //   1367: aload_3
    //   1368: invokevirtual toString : ()Ljava/lang/String;
    //   1371: putstatic burp/Zgwq.ZV : Ljava/lang/String;
    //   1374: getstatic burp/Zsmn.Zq : Ljava/lang/Object;
    //   1377: checkcast java/math/BigInteger
    //   1380: invokevirtual toByteArray : ()[B
    //   1383: astore #4
    //   1385: bipush #64
    //   1387: newarray byte
    //   1389: dup
    //   1390: iconst_0
    //   1391: bipush #-128
    //   1393: bastore
    //   1394: dup
    //   1395: iconst_1
    //   1396: iconst_0
    //   1397: bastore
    //   1398: dup
    //   1399: iconst_2
    //   1400: iconst_0
    //   1401: bastore
    //   1402: dup
    //   1403: iconst_3
    //   1404: iconst_0
    //   1405: bastore
    //   1406: dup
    //   1407: iconst_4
    //   1408: iconst_0
    //   1409: bastore
    //   1410: dup
    //   1411: iconst_5
    //   1412: iconst_0
    //   1413: bastore
    //   1414: dup
    //   1415: bipush #6
    //   1417: iconst_0
    //   1418: bastore
    //   1419: dup
    //   1420: bipush #7
    //   1422: iconst_0
    //   1423: bastore
    //   1424: dup
    //   1425: bipush #8
    //   1427: iconst_0
    //   1428: bastore
    //   1429: dup
    //   1430: bipush #9
    //   1432: iconst_0
    //   1433: bastore
    //   1434: dup
    //   1435: bipush #10
    //   1437: iconst_0
    //   1438: bastore
    //   1439: dup
    //   1440: bipush #11
    //   1442: iconst_0
    //   1443: bastore
    //   1444: dup
    //   1445: bipush #12
    //   1447: iconst_0
    //   1448: bastore
    //   1449: dup
    //   1450: bipush #13
    //   1452: iconst_0
    //   1453: bastore
    //   1454: dup
    //   1455: bipush #14
    //   1457: iconst_0
    //   1458: bastore
    //   1459: dup
    //   1460: bipush #15
    //   1462: iconst_0
    //   1463: bastore
    //   1464: dup
    //   1465: bipush #16
    //   1467: iconst_0
    //   1468: bastore
    //   1469: dup
    //   1470: bipush #17
    //   1472: iconst_0
    //   1473: bastore
    //   1474: dup
    //   1475: bipush #18
    //   1477: iconst_0
    //   1478: bastore
    //   1479: dup
    //   1480: bipush #19
    //   1482: iconst_0
    //   1483: bastore
    //   1484: dup
    //   1485: bipush #20
    //   1487: iconst_0
    //   1488: bastore
    //   1489: dup
    //   1490: bipush #21
    //   1492: iconst_0
    //   1493: bastore
    //   1494: dup
    //   1495: bipush #22
    //   1497: iconst_0
    //   1498: bastore
    //   1499: dup
    //   1500: bipush #23
    //   1502: iconst_0
    //   1503: bastore
    //   1504: dup
    //   1505: bipush #24
    //   1507: iconst_0
    //   1508: bastore
    //   1509: dup
    //   1510: bipush #25
    //   1512: iconst_0
    //   1513: bastore
    //   1514: dup
    //   1515: bipush #26
    //   1517: iconst_0
    //   1518: bastore
    //   1519: dup
    //   1520: bipush #27
    //   1522: iconst_0
    //   1523: bastore
    //   1524: dup
    //   1525: bipush #28
    //   1527: iconst_0
    //   1528: bastore
    //   1529: dup
    //   1530: bipush #29
    //   1532: iconst_0
    //   1533: bastore
    //   1534: dup
    //   1535: bipush #30
    //   1537: iconst_0
    //   1538: bastore
    //   1539: dup
    //   1540: bipush #31
    //   1542: iconst_0
    //   1543: bastore
    //   1544: dup
    //   1545: bipush #32
    //   1547: iconst_0
    //   1548: bastore
    //   1549: dup
    //   1550: bipush #33
    //   1552: iconst_0
    //   1553: bastore
    //   1554: dup
    //   1555: bipush #34
    //   1557: iconst_0
    //   1558: bastore
    //   1559: dup
    //   1560: bipush #35
    //   1562: iconst_0
    //   1563: bastore
    //   1564: dup
    //   1565: bipush #36
    //   1567: iconst_0
    //   1568: bastore
    //   1569: dup
    //   1570: bipush #37
    //   1572: iconst_0
    //   1573: bastore
    //   1574: dup
    //   1575: bipush #38
    //   1577: iconst_0
    //   1578: bastore
    //   1579: dup
    //   1580: bipush #39
    //   1582: iconst_0
    //   1583: bastore
    //   1584: dup
    //   1585: bipush #40
    //   1587: iconst_0
    //   1588: bastore
    //   1589: dup
    //   1590: bipush #41
    //   1592: iconst_0
    //   1593: bastore
    //   1594: dup
    //   1595: bipush #42
    //   1597: iconst_0
    //   1598: bastore
    //   1599: dup
    //   1600: bipush #43
    //   1602: iconst_0
    //   1603: bastore
    //   1604: dup
    //   1605: bipush #44
    //   1607: iconst_0
    //   1608: bastore
    //   1609: dup
    //   1610: bipush #45
    //   1612: iconst_0
    //   1613: bastore
    //   1614: dup
    //   1615: bipush #46
    //   1617: iconst_0
    //   1618: bastore
    //   1619: dup
    //   1620: bipush #47
    //   1622: iconst_0
    //   1623: bastore
    //   1624: dup
    //   1625: bipush #48
    //   1627: iconst_0
    //   1628: bastore
    //   1629: dup
    //   1630: bipush #49
    //   1632: iconst_0
    //   1633: bastore
    //   1634: dup
    //   1635: bipush #50
    //   1637: iconst_0
    //   1638: bastore
    //   1639: dup
    //   1640: bipush #51
    //   1642: iconst_0
    //   1643: bastore
    //   1644: dup
    //   1645: bipush #52
    //   1647: iconst_0
    //   1648: bastore
    //   1649: dup
    //   1650: bipush #53
    //   1652: iconst_0
    //   1653: bastore
    //   1654: dup
    //   1655: bipush #54
    //   1657: iconst_0
    //   1658: bastore
    //   1659: dup
    //   1660: bipush #55
    //   1662: iconst_0
    //   1663: bastore
    //   1664: dup
    //   1665: bipush #56
    //   1667: iconst_0
    //   1668: bastore
    //   1669: dup
    //   1670: bipush #57
    //   1672: iconst_0
    //   1673: bastore
    //   1674: dup
    //   1675: bipush #58
    //   1677: iconst_0
    //   1678: bastore
    //   1679: dup
    //   1680: bipush #59
    //   1682: iconst_0
    //   1683: bastore
    //   1684: dup
    //   1685: bipush #60
    //   1687: iconst_0
    //   1688: bastore
    //   1689: dup
    //   1690: bipush #61
    //   1692: iconst_0
    //   1693: bastore
    //   1694: dup
    //   1695: bipush #62
    //   1697: iconst_0
    //   1698: bastore
    //   1699: dup
    //   1700: bipush #63
    //   1702: iconst_0
    //   1703: bastore
    //   1704: astore #6
    //   1706: bipush #64
    //   1708: newarray int
    //   1710: dup
    //   1711: iconst_0
    //   1712: ldc 1116352408
    //   1714: iastore
    //   1715: dup
    //   1716: iconst_1
    //   1717: ldc 1899447441
    //   1719: iastore
    //   1720: dup
    //   1721: iconst_2
    //   1722: ldc -1245643825
    //   1724: iastore
    //   1725: dup
    //   1726: iconst_3
    //   1727: ldc -373957723
    //   1729: iastore
    //   1730: dup
    //   1731: iconst_4
    //   1732: ldc 961987163
    //   1734: iastore
    //   1735: dup
    //   1736: iconst_5
    //   1737: ldc 1508970993
    //   1739: iastore
    //   1740: dup
    //   1741: bipush #6
    //   1743: ldc -1841331548
    //   1745: iastore
    //   1746: dup
    //   1747: bipush #7
    //   1749: ldc -1424204075
    //   1751: iastore
    //   1752: dup
    //   1753: bipush #8
    //   1755: ldc -670586216
    //   1757: iastore
    //   1758: dup
    //   1759: bipush #9
    //   1761: ldc 310598401
    //   1763: iastore
    //   1764: dup
    //   1765: bipush #10
    //   1767: ldc 607225278
    //   1769: iastore
    //   1770: dup
    //   1771: bipush #11
    //   1773: ldc 1426881987
    //   1775: iastore
    //   1776: dup
    //   1777: bipush #12
    //   1779: ldc 1925078388
    //   1781: iastore
    //   1782: dup
    //   1783: bipush #13
    //   1785: ldc -2132889090
    //   1787: iastore
    //   1788: dup
    //   1789: bipush #14
    //   1791: ldc -1680079193
    //   1793: iastore
    //   1794: dup
    //   1795: bipush #15
    //   1797: ldc -1046744716
    //   1799: iastore
    //   1800: dup
    //   1801: bipush #16
    //   1803: ldc -459576895
    //   1805: iastore
    //   1806: dup
    //   1807: bipush #17
    //   1809: ldc -272742522
    //   1811: iastore
    //   1812: dup
    //   1813: bipush #18
    //   1815: ldc 264347078
    //   1817: iastore
    //   1818: dup
    //   1819: bipush #19
    //   1821: ldc 604807628
    //   1823: iastore
    //   1824: dup
    //   1825: bipush #20
    //   1827: ldc 770255983
    //   1829: iastore
    //   1830: dup
    //   1831: bipush #21
    //   1833: ldc 1249150122
    //   1835: iastore
    //   1836: dup
    //   1837: bipush #22
    //   1839: ldc 1555081692
    //   1841: iastore
    //   1842: dup
    //   1843: bipush #23
    //   1845: ldc 1996064986
    //   1847: iastore
    //   1848: dup
    //   1849: bipush #24
    //   1851: ldc -1740746414
    //   1853: iastore
    //   1854: dup
    //   1855: bipush #25
    //   1857: ldc -1473132947
    //   1859: iastore
    //   1860: dup
    //   1861: bipush #26
    //   1863: ldc -1341970488
    //   1865: iastore
    //   1866: dup
    //   1867: bipush #27
    //   1869: ldc -1084653625
    //   1871: iastore
    //   1872: dup
    //   1873: bipush #28
    //   1875: ldc -958395405
    //   1877: iastore
    //   1878: dup
    //   1879: bipush #29
    //   1881: ldc -710438585
    //   1883: iastore
    //   1884: dup
    //   1885: bipush #30
    //   1887: ldc 113926993
    //   1889: iastore
    //   1890: dup
    //   1891: bipush #31
    //   1893: ldc 338241895
    //   1895: iastore
    //   1896: dup
    //   1897: bipush #32
    //   1899: ldc 666307205
    //   1901: iastore
    //   1902: dup
    //   1903: bipush #33
    //   1905: ldc 773529912
    //   1907: iastore
    //   1908: dup
    //   1909: bipush #34
    //   1911: ldc 1294757372
    //   1913: iastore
    //   1914: dup
    //   1915: bipush #35
    //   1917: ldc 1396182291
    //   1919: iastore
    //   1920: dup
    //   1921: bipush #36
    //   1923: ldc 1695183700
    //   1925: iastore
    //   1926: dup
    //   1927: bipush #37
    //   1929: ldc 1986661051
    //   1931: iastore
    //   1932: dup
    //   1933: bipush #38
    //   1935: ldc -2117940946
    //   1937: iastore
    //   1938: dup
    //   1939: bipush #39
    //   1941: ldc -1838011259
    //   1943: iastore
    //   1944: dup
    //   1945: bipush #40
    //   1947: ldc -1564481375
    //   1949: iastore
    //   1950: dup
    //   1951: bipush #41
    //   1953: ldc -1474664885
    //   1955: iastore
    //   1956: dup
    //   1957: bipush #42
    //   1959: ldc -1035236496
    //   1961: iastore
    //   1962: dup
    //   1963: bipush #43
    //   1965: ldc -949202525
    //   1967: iastore
    //   1968: dup
    //   1969: bipush #44
    //   1971: ldc -778901479
    //   1973: iastore
    //   1974: dup
    //   1975: bipush #45
    //   1977: ldc -694614492
    //   1979: iastore
    //   1980: dup
    //   1981: bipush #46
    //   1983: ldc -200395387
    //   1985: iastore
    //   1986: dup
    //   1987: bipush #47
    //   1989: ldc 275423344
    //   1991: iastore
    //   1992: dup
    //   1993: bipush #48
    //   1995: ldc 430227734
    //   1997: iastore
    //   1998: dup
    //   1999: bipush #49
    //   2001: ldc 506948616
    //   2003: iastore
    //   2004: dup
    //   2005: bipush #50
    //   2007: ldc 659060556
    //   2009: iastore
    //   2010: dup
    //   2011: bipush #51
    //   2013: ldc 883997877
    //   2015: iastore
    //   2016: dup
    //   2017: bipush #52
    //   2019: ldc 958139571
    //   2021: iastore
    //   2022: dup
    //   2023: bipush #53
    //   2025: ldc 1322822218
    //   2027: iastore
    //   2028: dup
    //   2029: bipush #54
    //   2031: ldc 1537002063
    //   2033: iastore
    //   2034: dup
    //   2035: bipush #55
    //   2037: ldc 1747873779
    //   2039: iastore
    //   2040: dup
    //   2041: bipush #56
    //   2043: ldc 1955562222
    //   2045: iastore
    //   2046: dup
    //   2047: bipush #57
    //   2049: ldc 2024104815
    //   2051: iastore
    //   2052: dup
    //   2053: bipush #58
    //   2055: ldc -2067236844
    //   2057: iastore
    //   2058: dup
    //   2059: bipush #59
    //   2061: ldc -1933114872
    //   2063: iastore
    //   2064: dup
    //   2065: bipush #60
    //   2067: ldc -1866530822
    //   2069: iastore
    //   2070: dup
    //   2071: bipush #61
    //   2073: ldc -1538233109
    //   2075: iastore
    //   2076: dup
    //   2077: bipush #62
    //   2079: ldc -1090935817
    //   2081: iastore
    //   2082: dup
    //   2083: bipush #63
    //   2085: ldc -965641998
    //   2087: iastore
    //   2088: astore #7
    //   2090: iconst_2
    //   2091: newarray int
    //   2093: dup
    //   2094: iconst_0
    //   2095: iconst_0
    //   2096: iastore
    //   2097: dup
    //   2098: iconst_1
    //   2099: iconst_0
    //   2100: iastore
    //   2101: astore #8
    //   2103: bipush #8
    //   2105: newarray int
    //   2107: dup
    //   2108: iconst_0
    //   2109: ldc 1779033703
    //   2111: iastore
    //   2112: dup
    //   2113: iconst_1
    //   2114: ldc -1150833019
    //   2116: iastore
    //   2117: dup
    //   2118: iconst_2
    //   2119: ldc 1013904242
    //   2121: iastore
    //   2122: dup
    //   2123: iconst_3
    //   2124: ldc -1521486534
    //   2126: iastore
    //   2127: dup
    //   2128: iconst_4
    //   2129: ldc 1359893119
    //   2131: iastore
    //   2132: dup
    //   2133: iconst_5
    //   2134: ldc -1694144372
    //   2136: iastore
    //   2137: dup
    //   2138: bipush #6
    //   2140: ldc 528734635
    //   2142: iastore
    //   2143: dup
    //   2144: bipush #7
    //   2146: ldc 1541459225
    //   2148: iastore
    //   2149: astore #9
    //   2151: bipush #64
    //   2153: newarray byte
    //   2155: astore #10
    //   2157: bipush #64
    //   2159: newarray byte
    //   2161: astore #11
    //   2163: aload #4
    //   2165: arraylength
    //   2166: istore #12
    //   2168: aload #8
    //   2170: iconst_0
    //   2171: iaload
    //   2172: bipush #63
    //   2174: iand
    //   2175: istore #13
    //   2177: aload #8
    //   2179: iconst_0
    //   2180: dup2
    //   2181: iaload
    //   2182: iload #12
    //   2184: iadd
    //   2185: iastore
    //   2186: aload #8
    //   2188: iconst_0
    //   2189: dup2
    //   2190: iaload
    //   2191: iconst_m1
    //   2192: iand
    //   2193: iastore
    //   2194: aload #8
    //   2196: iconst_0
    //   2197: iaload
    //   2198: iload #12
    //   2200: if_icmpge -> 2218
    //   2203: aload #8
    //   2205: iconst_1
    //   2206: dup2
    //   2207: iaload
    //   2208: iconst_1
    //   2209: iadd
    //   2210: iastore
    //   2211: goto -> 2218
    //   2214: invokestatic a : (Ljava/lang/Throwable;)Ljava/lang/Throwable;
    //   2217: athrow
    //   2218: iconst_0
    //   2219: istore #14
    //   2221: iload #12
    //   2223: bipush #64
    //   2225: if_icmplt -> 2835
    //   2228: iconst_0
    //   2229: istore #15
    //   2231: iload #15
    //   2233: bipush #64
    //   2235: if_icmpge -> 2258
    //   2238: aload #11
    //   2240: iload #15
    //   2242: aload #4
    //   2244: iload #14
    //   2246: iload #15
    //   2248: iadd
    //   2249: baload
    //   2250: bastore
    //   2251: iinc #15, 1
    //   2254: iload_2
    //   2255: ifne -> 2231
    //   2258: bipush #64
    //   2260: newarray int
    //   2262: astore #15
    //   2264: bipush #8
    //   2266: newarray int
    //   2268: astore #16
    //   2270: iconst_0
    //   2271: istore #17
    //   2273: iload #17
    //   2275: bipush #8
    //   2277: if_icmpge -> 2297
    //   2280: aload #16
    //   2282: iload #17
    //   2284: aload #9
    //   2286: iload #17
    //   2288: iaload
    //   2289: iastore
    //   2290: iinc #17, 1
    //   2293: iload_2
    //   2294: ifne -> 2273
    //   2297: iconst_0
    //   2298: istore #17
    //   2300: iload #17
    //   2302: bipush #64
    //   2304: if_icmpge -> 2795
    //   2307: iload #17
    //   2309: bipush #16
    //   2311: if_icmpge -> 2392
    //   2314: aload #15
    //   2316: iload #17
    //   2318: aload #11
    //   2320: iconst_4
    //   2321: iload #17
    //   2323: imul
    //   2324: baload
    //   2325: sipush #255
    //   2328: iand
    //   2329: bipush #24
    //   2331: ishl
    //   2332: aload #11
    //   2334: iconst_4
    //   2335: iload #17
    //   2337: imul
    //   2338: iconst_1
    //   2339: iadd
    //   2340: baload
    //   2341: sipush #255
    //   2344: iand
    //   2345: bipush #16
    //   2347: ishl
    //   2348: ior
    //   2349: aload #11
    //   2351: iconst_4
    //   2352: iload #17
    //   2354: imul
    //   2355: iconst_2
    //   2356: iadd
    //   2357: baload
    //   2358: sipush #255
    //   2361: iand
    //   2362: bipush #8
    //   2364: ishl
    //   2365: ior
    //   2366: aload #11
    //   2368: iconst_4
    //   2369: iload #17
    //   2371: imul
    //   2372: iconst_3
    //   2373: iadd
    //   2374: baload
    //   2375: sipush #255
    //   2378: iand
    //   2379: ior
    //   2380: iastore
    //   2381: iload_2
    //   2382: ifne -> 2535
    //   2385: goto -> 2392
    //   2388: invokestatic a : (Ljava/lang/Throwable;)Ljava/lang/Throwable;
    //   2391: athrow
    //   2392: aload #15
    //   2394: iload #17
    //   2396: aload #15
    //   2398: iload #17
    //   2400: iconst_2
    //   2401: isub
    //   2402: iaload
    //   2403: bipush #17
    //   2405: iushr
    //   2406: aload #15
    //   2408: iload #17
    //   2410: iconst_2
    //   2411: isub
    //   2412: iaload
    //   2413: bipush #15
    //   2415: ishl
    //   2416: ior
    //   2417: aload #15
    //   2419: iload #17
    //   2421: iconst_2
    //   2422: isub
    //   2423: iaload
    //   2424: bipush #19
    //   2426: iushr
    //   2427: aload #15
    //   2429: iload #17
    //   2431: iconst_2
    //   2432: isub
    //   2433: iaload
    //   2434: bipush #13
    //   2436: ishl
    //   2437: ior
    //   2438: ixor
    //   2439: aload #15
    //   2441: iload #17
    //   2443: iconst_2
    //   2444: isub
    //   2445: iaload
    //   2446: bipush #10
    //   2448: iushr
    //   2449: ixor
    //   2450: aload #15
    //   2452: iload #17
    //   2454: bipush #7
    //   2456: isub
    //   2457: iaload
    //   2458: iadd
    //   2459: aload #15
    //   2461: iload #17
    //   2463: bipush #15
    //   2465: isub
    //   2466: iaload
    //   2467: bipush #7
    //   2469: iushr
    //   2470: aload #15
    //   2472: iload #17
    //   2474: bipush #15
    //   2476: isub
    //   2477: iaload
    //   2478: bipush #25
    //   2480: ishl
    //   2481: ior
    //   2482: aload #15
    //   2484: iload #17
    //   2486: bipush #15
    //   2488: isub
    //   2489: iaload
    //   2490: bipush #18
    //   2492: iushr
    //   2493: aload #15
    //   2495: iload #17
    //   2497: bipush #15
    //   2499: isub
    //   2500: iaload
    //   2501: bipush #14
    //   2503: ishl
    //   2504: ior
    //   2505: ixor
    //   2506: aload #15
    //   2508: iload #17
    //   2510: bipush #15
    //   2512: isub
    //   2513: iaload
    //   2514: iconst_3
    //   2515: iushr
    //   2516: ixor
    //   2517: iadd
    //   2518: aload #15
    //   2520: iload #17
    //   2522: bipush #16
    //   2524: isub
    //   2525: iaload
    //   2526: iadd
    //   2527: iastore
    //   2528: goto -> 2535
    //   2531: invokestatic a : (Ljava/lang/Throwable;)Ljava/lang/Throwable;
    //   2534: athrow
    //   2535: aload #16
    //   2537: bipush #7
    //   2539: iaload
    //   2540: aload #16
    //   2542: iconst_4
    //   2543: iaload
    //   2544: bipush #6
    //   2546: iushr
    //   2547: aload #16
    //   2549: iconst_4
    //   2550: iaload
    //   2551: bipush #26
    //   2553: ishl
    //   2554: ior
    //   2555: aload #16
    //   2557: iconst_4
    //   2558: iaload
    //   2559: bipush #11
    //   2561: iushr
    //   2562: aload #16
    //   2564: iconst_4
    //   2565: iaload
    //   2566: bipush #21
    //   2568: ishl
    //   2569: ior
    //   2570: ixor
    //   2571: aload #16
    //   2573: iconst_4
    //   2574: iaload
    //   2575: bipush #25
    //   2577: iushr
    //   2578: aload #16
    //   2580: iconst_4
    //   2581: iaload
    //   2582: bipush #7
    //   2584: ishl
    //   2585: ior
    //   2586: ixor
    //   2587: iadd
    //   2588: aload #16
    //   2590: bipush #6
    //   2592: iaload
    //   2593: aload #16
    //   2595: iconst_4
    //   2596: iaload
    //   2597: aload #16
    //   2599: iconst_5
    //   2600: iaload
    //   2601: aload #16
    //   2603: bipush #6
    //   2605: iaload
    //   2606: ixor
    //   2607: iand
    //   2608: ixor
    //   2609: iadd
    //   2610: aload #7
    //   2612: iload #17
    //   2614: iaload
    //   2615: iadd
    //   2616: aload #15
    //   2618: iload #17
    //   2620: iaload
    //   2621: iadd
    //   2622: istore #18
    //   2624: aload #16
    //   2626: iconst_0
    //   2627: iaload
    //   2628: iconst_2
    //   2629: iushr
    //   2630: aload #16
    //   2632: iconst_0
    //   2633: iaload
    //   2634: bipush #30
    //   2636: ishl
    //   2637: ior
    //   2638: aload #16
    //   2640: iconst_0
    //   2641: iaload
    //   2642: bipush #13
    //   2644: iushr
    //   2645: aload #16
    //   2647: iconst_0
    //   2648: iaload
    //   2649: bipush #19
    //   2651: ishl
    //   2652: ior
    //   2653: ixor
    //   2654: aload #16
    //   2656: iconst_0
    //   2657: iaload
    //   2658: bipush #22
    //   2660: iushr
    //   2661: aload #16
    //   2663: iconst_0
    //   2664: iaload
    //   2665: bipush #10
    //   2667: ishl
    //   2668: ior
    //   2669: ixor
    //   2670: aload #16
    //   2672: iconst_0
    //   2673: iaload
    //   2674: aload #16
    //   2676: iconst_1
    //   2677: iaload
    //   2678: iand
    //   2679: aload #16
    //   2681: iconst_2
    //   2682: iaload
    //   2683: aload #16
    //   2685: iconst_0
    //   2686: iaload
    //   2687: aload #16
    //   2689: iconst_1
    //   2690: iaload
    //   2691: ior
    //   2692: iand
    //   2693: ior
    //   2694: iadd
    //   2695: istore #19
    //   2697: aload #16
    //   2699: iconst_3
    //   2700: dup2
    //   2701: iaload
    //   2702: iload #18
    //   2704: iadd
    //   2705: iastore
    //   2706: aload #16
    //   2708: bipush #7
    //   2710: iload #18
    //   2712: iload #19
    //   2714: iadd
    //   2715: iastore
    //   2716: aload #16
    //   2718: bipush #7
    //   2720: iaload
    //   2721: istore #18
    //   2723: aload #16
    //   2725: bipush #7
    //   2727: aload #16
    //   2729: bipush #6
    //   2731: iaload
    //   2732: iastore
    //   2733: aload #16
    //   2735: bipush #6
    //   2737: aload #16
    //   2739: iconst_5
    //   2740: iaload
    //   2741: iastore
    //   2742: aload #16
    //   2744: iconst_5
    //   2745: aload #16
    //   2747: iconst_4
    //   2748: iaload
    //   2749: iastore
    //   2750: aload #16
    //   2752: iconst_4
    //   2753: aload #16
    //   2755: iconst_3
    //   2756: iaload
    //   2757: iastore
    //   2758: aload #16
    //   2760: iconst_3
    //   2761: aload #16
    //   2763: iconst_2
    //   2764: iaload
    //   2765: iastore
    //   2766: aload #16
    //   2768: iconst_2
    //   2769: aload #16
    //   2771: iconst_1
    //   2772: iaload
    //   2773: iastore
    //   2774: aload #16
    //   2776: iconst_1
    //   2777: aload #16
    //   2779: iconst_0
    //   2780: iaload
    //   2781: iastore
    //   2782: aload #16
    //   2784: iconst_0
    //   2785: iload #18
    //   2787: iastore
    //   2788: iinc #17, 1
    //   2791: iload_2
    //   2792: ifne -> 2300
    //   2795: iconst_0
    //   2796: istore #17
    //   2798: iload #17
    //   2800: bipush #8
    //   2802: if_icmpge -> 2825
    //   2805: aload #9
    //   2807: iload #17
    //   2809: dup2
    //   2810: iaload
    //   2811: aload #16
    //   2813: iload #17
    //   2815: iaload
    //   2816: iadd
    //   2817: iastore
    //   2818: iinc #17, 1
    //   2821: iload_2
    //   2822: ifne -> 2798
    //   2825: iinc #14, 64
    //   2828: iinc #12, -64
    //   2831: iload_2
    //   2832: ifne -> 2221
    //   2835: iload #12
    //   2837: ifle -> 2873
    //   2840: iconst_0
    //   2841: istore #15
    //   2843: iload #15
    //   2845: iload #12
    //   2847: if_icmpge -> 2873
    //   2850: aload #10
    //   2852: iload #13
    //   2854: iload #15
    //   2856: iadd
    //   2857: aload #4
    //   2859: iload #14
    //   2861: iload #15
    //   2863: iadd
    //   2864: baload
    //   2865: bastore
    //   2866: iinc #15, 1
    //   2869: iload_2
    //   2870: ifne -> 2843
    //   2873: aload #8
    //   2875: iconst_0
    //   2876: iaload
    //   2877: bipush #29
    //   2879: iushr
    //   2880: aload #8
    //   2882: iconst_1
    //   2883: iaload
    //   2884: iconst_3
    //   2885: ishl
    //   2886: ior
    //   2887: istore #15
    //   2889: aload #8
    //   2891: iconst_0
    //   2892: iaload
    //   2893: iconst_3
    //   2894: ishl
    //   2895: istore #16
    //   2897: aload #8
    //   2899: iconst_0
    //   2900: iaload
    //   2901: bipush #63
    //   2903: iand
    //   2904: istore #17
    //   2906: iload #17
    //   2908: bipush #56
    //   2910: if_icmpge -> 2925
    //   2913: bipush #56
    //   2915: iload #17
    //   2917: isub
    //   2918: goto -> 2930
    //   2921: invokestatic a : (Ljava/lang/Throwable;)Ljava/lang/Throwable;
    //   2924: athrow
    //   2925: bipush #120
    //   2927: iload #17
    //   2929: isub
    //   2930: istore #18
    //   2932: aload #8
    //   2934: iconst_0
    //   2935: iaload
    //   2936: bipush #63
    //   2938: iand
    //   2939: istore #13
    //   2941: bipush #64
    //   2943: iload #13
    //   2945: isub
    //   2946: istore #19
    //   2948: aload #8
    //   2950: iconst_0
    //   2951: dup2
    //   2952: iaload
    //   2953: iload #18
    //   2955: iadd
    //   2956: iastore
    //   2957: aload #8
    //   2959: iconst_0
    //   2960: dup2
    //   2961: iaload
    //   2962: iconst_m1
    //   2963: iand
    //   2964: iastore
    //   2965: aload #8
    //   2967: iconst_0
    //   2968: iaload
    //   2969: iload #18
    //   2971: if_icmpge -> 2989
    //   2974: aload #8
    //   2976: iconst_1
    //   2977: dup2
    //   2978: iaload
    //   2979: iconst_1
    //   2980: iadd
    //   2981: iastore
    //   2982: goto -> 2989
    //   2985: invokestatic a : (Ljava/lang/Throwable;)Ljava/lang/Throwable;
    //   2988: athrow
    //   2989: iconst_0
    //   2990: istore #14
    //   2992: iload #13
    //   2994: ifle -> 3625
    //   2997: iload #18
    //   2999: iload #19
    //   3001: if_icmplt -> 3625
    //   3004: goto -> 3011
    //   3007: invokestatic a : (Ljava/lang/Throwable;)Ljava/lang/Throwable;
    //   3010: athrow
    //   3011: iconst_0
    //   3012: istore #20
    //   3014: iload #20
    //   3016: iload #19
    //   3018: if_icmpge -> 3041
    //   3021: aload #10
    //   3023: iload #13
    //   3025: iload #20
    //   3027: iadd
    //   3028: aload #6
    //   3030: iload #20
    //   3032: baload
    //   3033: bastore
    //   3034: iinc #20, 1
    //   3037: iload_2
    //   3038: ifne -> 3014
    //   3041: bipush #64
    //   3043: newarray int
    //   3045: astore #20
    //   3047: bipush #8
    //   3049: newarray int
    //   3051: astore #21
    //   3053: iconst_0
    //   3054: istore #22
    //   3056: iload #22
    //   3058: bipush #8
    //   3060: if_icmpge -> 3080
    //   3063: aload #21
    //   3065: iload #22
    //   3067: aload #9
    //   3069: iload #22
    //   3071: iaload
    //   3072: iastore
    //   3073: iinc #22, 1
    //   3076: iload_2
    //   3077: ifne -> 3056
    //   3080: iconst_0
    //   3081: istore #22
    //   3083: iload #22
    //   3085: bipush #64
    //   3087: if_icmpge -> 3578
    //   3090: iload #22
    //   3092: bipush #16
    //   3094: if_icmpge -> 3175
    //   3097: aload #20
    //   3099: iload #22
    //   3101: aload #10
    //   3103: iconst_4
    //   3104: iload #22
    //   3106: imul
    //   3107: baload
    //   3108: sipush #255
    //   3111: iand
    //   3112: bipush #24
    //   3114: ishl
    //   3115: aload #10
    //   3117: iconst_4
    //   3118: iload #22
    //   3120: imul
    //   3121: iconst_1
    //   3122: iadd
    //   3123: baload
    //   3124: sipush #255
    //   3127: iand
    //   3128: bipush #16
    //   3130: ishl
    //   3131: ior
    //   3132: aload #10
    //   3134: iconst_4
    //   3135: iload #22
    //   3137: imul
    //   3138: iconst_2
    //   3139: iadd
    //   3140: baload
    //   3141: sipush #255
    //   3144: iand
    //   3145: bipush #8
    //   3147: ishl
    //   3148: ior
    //   3149: aload #10
    //   3151: iconst_4
    //   3152: iload #22
    //   3154: imul
    //   3155: iconst_3
    //   3156: iadd
    //   3157: baload
    //   3158: sipush #255
    //   3161: iand
    //   3162: ior
    //   3163: iastore
    //   3164: iload_2
    //   3165: ifne -> 3318
    //   3168: goto -> 3175
    //   3171: invokestatic a : (Ljava/lang/Throwable;)Ljava/lang/Throwable;
    //   3174: athrow
    //   3175: aload #20
    //   3177: iload #22
    //   3179: aload #20
    //   3181: iload #22
    //   3183: iconst_2
    //   3184: isub
    //   3185: iaload
    //   3186: bipush #17
    //   3188: iushr
    //   3189: aload #20
    //   3191: iload #22
    //   3193: iconst_2
    //   3194: isub
    //   3195: iaload
    //   3196: bipush #15
    //   3198: ishl
    //   3199: ior
    //   3200: aload #20
    //   3202: iload #22
    //   3204: iconst_2
    //   3205: isub
    //   3206: iaload
    //   3207: bipush #19
    //   3209: iushr
    //   3210: aload #20
    //   3212: iload #22
    //   3214: iconst_2
    //   3215: isub
    //   3216: iaload
    //   3217: bipush #13
    //   3219: ishl
    //   3220: ior
    //   3221: ixor
    //   3222: aload #20
    //   3224: iload #22
    //   3226: iconst_2
    //   3227: isub
    //   3228: iaload
    //   3229: bipush #10
    //   3231: iushr
    //   3232: ixor
    //   3233: aload #20
    //   3235: iload #22
    //   3237: bipush #7
    //   3239: isub
    //   3240: iaload
    //   3241: iadd
    //   3242: aload #20
    //   3244: iload #22
    //   3246: bipush #15
    //   3248: isub
    //   3249: iaload
    //   3250: bipush #7
    //   3252: iushr
    //   3253: aload #20
    //   3255: iload #22
    //   3257: bipush #15
    //   3259: isub
    //   3260: iaload
    //   3261: bipush #25
    //   3263: ishl
    //   3264: ior
    //   3265: aload #20
    //   3267: iload #22
    //   3269: bipush #15
    //   3271: isub
    //   3272: iaload
    //   3273: bipush #18
    //   3275: iushr
    //   3276: aload #20
    //   3278: iload #22
    //   3280: bipush #15
    //   3282: isub
    //   3283: iaload
    //   3284: bipush #14
    //   3286: ishl
    //   3287: ior
    //   3288: ixor
    //   3289: aload #20
    //   3291: iload #22
    //   3293: bipush #15
    //   3295: isub
    //   3296: iaload
    //   3297: iconst_3
    //   3298: iushr
    //   3299: ixor
    //   3300: iadd
    //   3301: aload #20
    //   3303: iload #22
    //   3305: bipush #16
    //   3307: isub
    //   3308: iaload
    //   3309: iadd
    //   3310: iastore
    //   3311: goto -> 3318
    //   3314: invokestatic a : (Ljava/lang/Throwable;)Ljava/lang/Throwable;
    //   3317: athrow
    //   3318: aload #21
    //   3320: bipush #7
    //   3322: iaload
    //   3323: aload #21
    //   3325: iconst_4
    //   3326: iaload
    //   3327: bipush #6
    //   3329: iushr
    //   3330: aload #21
    //   3332: iconst_4
    //   3333: iaload
    //   3334: bipush #26
    //   3336: ishl
    //   3337: ior
    //   3338: aload #21
    //   3340: iconst_4
    //   3341: iaload
    //   3342: bipush #11
    //   3344: iushr
    //   3345: aload #21
    //   3347: iconst_4
    //   3348: iaload
    //   3349: bipush #21
    //   3351: ishl
    //   3352: ior
    //   3353: ixor
    //   3354: aload #21
    //   3356: iconst_4
    //   3357: iaload
    //   3358: bipush #25
    //   3360: iushr
    //   3361: aload #21
    //   3363: iconst_4
    //   3364: iaload
    //   3365: bipush #7
    //   3367: ishl
    //   3368: ior
    //   3369: ixor
    //   3370: iadd
    //   3371: aload #21
    //   3373: bipush #6
    //   3375: iaload
    //   3376: aload #21
    //   3378: iconst_4
    //   3379: iaload
    //   3380: aload #21
    //   3382: iconst_5
    //   3383: iaload
    //   3384: aload #21
    //   3386: bipush #6
    //   3388: iaload
    //   3389: ixor
    //   3390: iand
    //   3391: ixor
    //   3392: iadd
    //   3393: aload #7
    //   3395: iload #22
    //   3397: iaload
    //   3398: iadd
    //   3399: aload #20
    //   3401: iload #22
    //   3403: iaload
    //   3404: iadd
    //   3405: istore #23
    //   3407: aload #21
    //   3409: iconst_0
    //   3410: iaload
    //   3411: iconst_2
    //   3412: iushr
    //   3413: aload #21
    //   3415: iconst_0
    //   3416: iaload
    //   3417: bipush #30
    //   3419: ishl
    //   3420: ior
    //   3421: aload #21
    //   3423: iconst_0
    //   3424: iaload
    //   3425: bipush #13
    //   3427: iushr
    //   3428: aload #21
    //   3430: iconst_0
    //   3431: iaload
    //   3432: bipush #19
    //   3434: ishl
    //   3435: ior
    //   3436: ixor
    //   3437: aload #21
    //   3439: iconst_0
    //   3440: iaload
    //   3441: bipush #22
    //   3443: iushr
    //   3444: aload #21
    //   3446: iconst_0
    //   3447: iaload
    //   3448: bipush #10
    //   3450: ishl
    //   3451: ior
    //   3452: ixor
    //   3453: aload #21
    //   3455: iconst_0
    //   3456: iaload
    //   3457: aload #21
    //   3459: iconst_1
    //   3460: iaload
    //   3461: iand
    //   3462: aload #21
    //   3464: iconst_2
    //   3465: iaload
    //   3466: aload #21
    //   3468: iconst_0
    //   3469: iaload
    //   3470: aload #21
    //   3472: iconst_1
    //   3473: iaload
    //   3474: ior
    //   3475: iand
    //   3476: ior
    //   3477: iadd
    //   3478: istore #24
    //   3480: aload #21
    //   3482: iconst_3
    //   3483: dup2
    //   3484: iaload
    //   3485: iload #23
    //   3487: iadd
    //   3488: iastore
    //   3489: aload #21
    //   3491: bipush #7
    //   3493: iload #23
    //   3495: iload #24
    //   3497: iadd
    //   3498: iastore
    //   3499: aload #21
    //   3501: bipush #7
    //   3503: iaload
    //   3504: istore #23
    //   3506: aload #21
    //   3508: bipush #7
    //   3510: aload #21
    //   3512: bipush #6
    //   3514: iaload
    //   3515: iastore
    //   3516: aload #21
    //   3518: bipush #6
    //   3520: aload #21
    //   3522: iconst_5
    //   3523: iaload
    //   3524: iastore
    //   3525: aload #21
    //   3527: iconst_5
    //   3528: aload #21
    //   3530: iconst_4
    //   3531: iaload
    //   3532: iastore
    //   3533: aload #21
    //   3535: iconst_4
    //   3536: aload #21
    //   3538: iconst_3
    //   3539: iaload
    //   3540: iastore
    //   3541: aload #21
    //   3543: iconst_3
    //   3544: aload #21
    //   3546: iconst_2
    //   3547: iaload
    //   3548: iastore
    //   3549: aload #21
    //   3551: iconst_2
    //   3552: aload #21
    //   3554: iconst_1
    //   3555: iaload
    //   3556: iastore
    //   3557: aload #21
    //   3559: iconst_1
    //   3560: aload #21
    //   3562: iconst_0
    //   3563: iaload
    //   3564: iastore
    //   3565: aload #21
    //   3567: iconst_0
    //   3568: iload #23
    //   3570: iastore
    //   3571: iinc #22, 1
    //   3574: iload_2
    //   3575: ifne -> 3083
    //   3578: iconst_0
    //   3579: istore #22
    //   3581: iload #22
    //   3583: bipush #8
    //   3585: if_icmpge -> 3608
    //   3588: aload #9
    //   3590: iload #22
    //   3592: dup2
    //   3593: iaload
    //   3594: aload #21
    //   3596: iload #22
    //   3598: iaload
    //   3599: iadd
    //   3600: iastore
    //   3601: iinc #22, 1
    //   3604: iload_2
    //   3605: ifne -> 3581
    //   3608: iload #14
    //   3610: iload #19
    //   3612: iadd
    //   3613: istore #14
    //   3615: iload #18
    //   3617: iload #19
    //   3619: isub
    //   3620: istore #18
    //   3622: iconst_0
    //   3623: istore #13
    //   3625: iload #18
    //   3627: bipush #64
    //   3629: if_icmplt -> 4239
    //   3632: iconst_0
    //   3633: istore #20
    //   3635: iload #20
    //   3637: bipush #64
    //   3639: if_icmpge -> 3662
    //   3642: aload #11
    //   3644: iload #20
    //   3646: aload #6
    //   3648: iload #14
    //   3650: iload #20
    //   3652: iadd
    //   3653: baload
    //   3654: bastore
    //   3655: iinc #20, 1
    //   3658: iload_2
    //   3659: ifne -> 3635
    //   3662: bipush #64
    //   3664: newarray int
    //   3666: astore #20
    //   3668: bipush #8
    //   3670: newarray int
    //   3672: astore #21
    //   3674: iconst_0
    //   3675: istore #22
    //   3677: iload #22
    //   3679: bipush #8
    //   3681: if_icmpge -> 3701
    //   3684: aload #21
    //   3686: iload #22
    //   3688: aload #9
    //   3690: iload #22
    //   3692: iaload
    //   3693: iastore
    //   3694: iinc #22, 1
    //   3697: iload_2
    //   3698: ifne -> 3677
    //   3701: iconst_0
    //   3702: istore #22
    //   3704: iload #22
    //   3706: bipush #64
    //   3708: if_icmpge -> 4199
    //   3711: iload #22
    //   3713: bipush #16
    //   3715: if_icmpge -> 3796
    //   3718: aload #20
    //   3720: iload #22
    //   3722: aload #11
    //   3724: iconst_4
    //   3725: iload #22
    //   3727: imul
    //   3728: baload
    //   3729: sipush #255
    //   3732: iand
    //   3733: bipush #24
    //   3735: ishl
    //   3736: aload #11
    //   3738: iconst_4
    //   3739: iload #22
    //   3741: imul
    //   3742: iconst_1
    //   3743: iadd
    //   3744: baload
    //   3745: sipush #255
    //   3748: iand
    //   3749: bipush #16
    //   3751: ishl
    //   3752: ior
    //   3753: aload #11
    //   3755: iconst_4
    //   3756: iload #22
    //   3758: imul
    //   3759: iconst_2
    //   3760: iadd
    //   3761: baload
    //   3762: sipush #255
    //   3765: iand
    //   3766: bipush #8
    //   3768: ishl
    //   3769: ior
    //   3770: aload #11
    //   3772: iconst_4
    //   3773: iload #22
    //   3775: imul
    //   3776: iconst_3
    //   3777: iadd
    //   3778: baload
    //   3779: sipush #255
    //   3782: iand
    //   3783: ior
    //   3784: iastore
    //   3785: iload_2
    //   3786: ifne -> 3939
    //   3789: goto -> 3796
    //   3792: invokestatic a : (Ljava/lang/Throwable;)Ljava/lang/Throwable;
    //   3795: athrow
    //   3796: aload #20
    //   3798: iload #22
    //   3800: aload #20
    //   3802: iload #22
    //   3804: iconst_2
    //   3805: isub
    //   3806: iaload
    //   3807: bipush #17
    //   3809: iushr
    //   3810: aload #20
    //   3812: iload #22
    //   3814: iconst_2
    //   3815: isub
    //   3816: iaload
    //   3817: bipush #15
    //   3819: ishl
    //   3820: ior
    //   3821: aload #20
    //   3823: iload #22
    //   3825: iconst_2
    //   3826: isub
    //   3827: iaload
    //   3828: bipush #19
    //   3830: iushr
    //   3831: aload #20
    //   3833: iload #22
    //   3835: iconst_2
    //   3836: isub
    //   3837: iaload
    //   3838: bipush #13
    //   3840: ishl
    //   3841: ior
    //   3842: ixor
    //   3843: aload #20
    //   3845: iload #22
    //   3847: iconst_2
    //   3848: isub
    //   3849: iaload
    //   3850: bipush #10
    //   3852: iushr
    //   3853: ixor
    //   3854: aload #20
    //   3856: iload #22
    //   3858: bipush #7
    //   3860: isub
    //   3861: iaload
    //   3862: iadd
    //   3863: aload #20
    //   3865: iload #22
    //   3867: bipush #15
    //   3869: isub
    //   3870: iaload
    //   3871: bipush #7
    //   3873: iushr
    //   3874: aload #20
    //   3876: iload #22
    //   3878: bipush #15
    //   3880: isub
    //   3881: iaload
    //   3882: bipush #25
    //   3884: ishl
    //   3885: ior
    //   3886: aload #20
    //   3888: iload #22
    //   3890: bipush #15
    //   3892: isub
    //   3893: iaload
    //   3894: bipush #18
    //   3896: iushr
    //   3897: aload #20
    //   3899: iload #22
    //   3901: bipush #15
    //   3903: isub
    //   3904: iaload
    //   3905: bipush #14
    //   3907: ishl
    //   3908: ior
    //   3909: ixor
    //   3910: aload #20
    //   3912: iload #22
    //   3914: bipush #15
    //   3916: isub
    //   3917: iaload
    //   3918: iconst_3
    //   3919: iushr
    //   3920: ixor
    //   3921: iadd
    //   3922: aload #20
    //   3924: iload #22
    //   3926: bipush #16
    //   3928: isub
    //   3929: iaload
    //   3930: iadd
    //   3931: iastore
    //   3932: goto -> 3939
    //   3935: invokestatic a : (Ljava/lang/Throwable;)Ljava/lang/Throwable;
    //   3938: athrow
    //   3939: aload #21
    //   3941: bipush #7
    //   3943: iaload
    //   3944: aload #21
    //   3946: iconst_4
    //   3947: iaload
    //   3948: bipush #6
    //   3950: iushr
    //   3951: aload #21
    //   3953: iconst_4
    //   3954: iaload
    //   3955: bipush #26
    //   3957: ishl
    //   3958: ior
    //   3959: aload #21
    //   3961: iconst_4
    //   3962: iaload
    //   3963: bipush #11
    //   3965: iushr
    //   3966: aload #21
    //   3968: iconst_4
    //   3969: iaload
    //   3970: bipush #21
    //   3972: ishl
    //   3973: ior
    //   3974: ixor
    //   3975: aload #21
    //   3977: iconst_4
    //   3978: iaload
    //   3979: bipush #25
    //   3981: iushr
    //   3982: aload #21
    //   3984: iconst_4
    //   3985: iaload
    //   3986: bipush #7
    //   3988: ishl
    //   3989: ior
    //   3990: ixor
    //   3991: iadd
    //   3992: aload #21
    //   3994: bipush #6
    //   3996: iaload
    //   3997: aload #21
    //   3999: iconst_4
    //   4000: iaload
    //   4001: aload #21
    //   4003: iconst_5
    //   4004: iaload
    //   4005: aload #21
    //   4007: bipush #6
    //   4009: iaload
    //   4010: ixor
    //   4011: iand
    //   4012: ixor
    //   4013: iadd
    //   4014: aload #7
    //   4016: iload #22
    //   4018: iaload
    //   4019: iadd
    //   4020: aload #20
    //   4022: iload #22
    //   4024: iaload
    //   4025: iadd
    //   4026: istore #23
    //   4028: aload #21
    //   4030: iconst_0
    //   4031: iaload
    //   4032: iconst_2
    //   4033: iushr
    //   4034: aload #21
    //   4036: iconst_0
    //   4037: iaload
    //   4038: bipush #30
    //   4040: ishl
    //   4041: ior
    //   4042: aload #21
    //   4044: iconst_0
    //   4045: iaload
    //   4046: bipush #13
    //   4048: iushr
    //   4049: aload #21
    //   4051: iconst_0
    //   4052: iaload
    //   4053: bipush #19
    //   4055: ishl
    //   4056: ior
    //   4057: ixor
    //   4058: aload #21
    //   4060: iconst_0
    //   4061: iaload
    //   4062: bipush #22
    //   4064: iushr
    //   4065: aload #21
    //   4067: iconst_0
    //   4068: iaload
    //   4069: bipush #10
    //   4071: ishl
    //   4072: ior
    //   4073: ixor
    //   4074: aload #21
    //   4076: iconst_0
    //   4077: iaload
    //   4078: aload #21
    //   4080: iconst_1
    //   4081: iaload
    //   4082: iand
    //   4083: aload #21
    //   4085: iconst_2
    //   4086: iaload
    //   4087: aload #21
    //   4089: iconst_0
    //   4090: iaload
    //   4091: aload #21
    //   4093: iconst_1
    //   4094: iaload
    //   4095: ior
    //   4096: iand
    //   4097: ior
    //   4098: iadd
    //   4099: istore #24
    //   4101: aload #21
    //   4103: iconst_3
    //   4104: dup2
    //   4105: iaload
    //   4106: iload #23
    //   4108: iadd
    //   4109: iastore
    //   4110: aload #21
    //   4112: bipush #7
    //   4114: iload #23
    //   4116: iload #24
    //   4118: iadd
    //   4119: iastore
    //   4120: aload #21
    //   4122: bipush #7
    //   4124: iaload
    //   4125: istore #23
    //   4127: aload #21
    //   4129: bipush #7
    //   4131: aload #21
    //   4133: bipush #6
    //   4135: iaload
    //   4136: iastore
    //   4137: aload #21
    //   4139: bipush #6
    //   4141: aload #21
    //   4143: iconst_5
    //   4144: iaload
    //   4145: iastore
    //   4146: aload #21
    //   4148: iconst_5
    //   4149: aload #21
    //   4151: iconst_4
    //   4152: iaload
    //   4153: iastore
    //   4154: aload #21
    //   4156: iconst_4
    //   4157: aload #21
    //   4159: iconst_3
    //   4160: iaload
    //   4161: iastore
    //   4162: aload #21
    //   4164: iconst_3
    //   4165: aload #21
    //   4167: iconst_2
    //   4168: iaload
    //   4169: iastore
    //   4170: aload #21
    //   4172: iconst_2
    //   4173: aload #21
    //   4175: iconst_1
    //   4176: iaload
    //   4177: iastore
    //   4178: aload #21
    //   4180: iconst_1
    //   4181: aload #21
    //   4183: iconst_0
    //   4184: iaload
    //   4185: iastore
    //   4186: aload #21
    //   4188: iconst_0
    //   4189: iload #23
    //   4191: iastore
    //   4192: iinc #22, 1
    //   4195: iload_2
    //   4196: ifne -> 3704
    //   4199: iconst_0
    //   4200: istore #22
    //   4202: iload #22
    //   4204: bipush #8
    //   4206: if_icmpge -> 4229
    //   4209: aload #9
    //   4211: iload #22
    //   4213: dup2
    //   4214: iaload
    //   4215: aload #21
    //   4217: iload #22
    //   4219: iaload
    //   4220: iadd
    //   4221: iastore
    //   4222: iinc #22, 1
    //   4225: iload_2
    //   4226: ifne -> 4202
    //   4229: iinc #14, 64
    //   4232: iinc #18, -64
    //   4235: iload_2
    //   4236: ifne -> 3625
    //   4239: iload #18
    //   4241: ifle -> 4277
    //   4244: iconst_0
    //   4245: istore #20
    //   4247: iload #20
    //   4249: iload #18
    //   4251: if_icmpge -> 4277
    //   4254: aload #10
    //   4256: iload #13
    //   4258: iload #20
    //   4260: iadd
    //   4261: aload #6
    //   4263: iload #14
    //   4265: iload #20
    //   4267: iadd
    //   4268: baload
    //   4269: bastore
    //   4270: iinc #20, 1
    //   4273: iload_2
    //   4274: ifne -> 4247
    //   4277: bipush #8
    //   4279: newarray byte
    //   4281: astore #20
    //   4283: aload #20
    //   4285: iconst_0
    //   4286: iload #15
    //   4288: bipush #24
    //   4290: iushr
    //   4291: i2b
    //   4292: bastore
    //   4293: aload #20
    //   4295: iconst_1
    //   4296: iload #15
    //   4298: bipush #16
    //   4300: iushr
    //   4301: i2b
    //   4302: bastore
    //   4303: aload #20
    //   4305: iconst_2
    //   4306: iload #15
    //   4308: bipush #8
    //   4310: iushr
    //   4311: i2b
    //   4312: bastore
    //   4313: aload #20
    //   4315: iconst_3
    //   4316: iload #15
    //   4318: i2b
    //   4319: bastore
    //   4320: aload #20
    //   4322: iconst_4
    //   4323: iload #16
    //   4325: bipush #24
    //   4327: iushr
    //   4328: i2b
    //   4329: bastore
    //   4330: aload #20
    //   4332: iconst_5
    //   4333: iload #16
    //   4335: bipush #16
    //   4337: iushr
    //   4338: i2b
    //   4339: bastore
    //   4340: aload #20
    //   4342: bipush #6
    //   4344: iload #16
    //   4346: bipush #8
    //   4348: iushr
    //   4349: i2b
    //   4350: bastore
    //   4351: aload #20
    //   4353: bipush #7
    //   4355: iload #16
    //   4357: i2b
    //   4358: bastore
    //   4359: bipush #8
    //   4361: istore #12
    //   4363: aload #8
    //   4365: iconst_0
    //   4366: iaload
    //   4367: bipush #63
    //   4369: iand
    //   4370: istore #13
    //   4372: bipush #64
    //   4374: iload #13
    //   4376: isub
    //   4377: istore #19
    //   4379: aload #8
    //   4381: iconst_0
    //   4382: dup2
    //   4383: iaload
    //   4384: iload #12
    //   4386: iadd
    //   4387: iastore
    //   4388: aload #8
    //   4390: iconst_0
    //   4391: dup2
    //   4392: iaload
    //   4393: iconst_m1
    //   4394: iand
    //   4395: iastore
    //   4396: aload #8
    //   4398: iconst_0
    //   4399: iaload
    //   4400: iload #12
    //   4402: if_icmpge -> 4420
    //   4405: aload #8
    //   4407: iconst_1
    //   4408: dup2
    //   4409: iaload
    //   4410: iconst_1
    //   4411: iadd
    //   4412: iastore
    //   4413: goto -> 4420
    //   4416: invokestatic a : (Ljava/lang/Throwable;)Ljava/lang/Throwable;
    //   4419: athrow
    //   4420: iload #13
    //   4422: ifle -> 5036
    //   4425: iload #12
    //   4427: iload #19
    //   4429: if_icmplt -> 5036
    //   4432: goto -> 4439
    //   4435: invokestatic a : (Ljava/lang/Throwable;)Ljava/lang/Throwable;
    //   4438: athrow
    //   4439: iconst_0
    //   4440: istore #21
    //   4442: iload #21
    //   4444: iload #19
    //   4446: if_icmpge -> 4469
    //   4449: aload #10
    //   4451: iload #13
    //   4453: iload #21
    //   4455: iadd
    //   4456: aload #20
    //   4458: iload #21
    //   4460: baload
    //   4461: bastore
    //   4462: iinc #21, 1
    //   4465: iload_2
    //   4466: ifne -> 4442
    //   4469: bipush #64
    //   4471: newarray int
    //   4473: astore #21
    //   4475: bipush #8
    //   4477: newarray int
    //   4479: astore #22
    //   4481: iconst_0
    //   4482: istore #23
    //   4484: iload #23
    //   4486: bipush #8
    //   4488: if_icmpge -> 4508
    //   4491: aload #22
    //   4493: iload #23
    //   4495: aload #9
    //   4497: iload #23
    //   4499: iaload
    //   4500: iastore
    //   4501: iinc #23, 1
    //   4504: iload_2
    //   4505: ifne -> 4484
    //   4508: iconst_0
    //   4509: istore #23
    //   4511: iload #23
    //   4513: bipush #64
    //   4515: if_icmpge -> 5006
    //   4518: iload #23
    //   4520: bipush #16
    //   4522: if_icmpge -> 4603
    //   4525: aload #21
    //   4527: iload #23
    //   4529: aload #10
    //   4531: iconst_4
    //   4532: iload #23
    //   4534: imul
    //   4535: baload
    //   4536: sipush #255
    //   4539: iand
    //   4540: bipush #24
    //   4542: ishl
    //   4543: aload #10
    //   4545: iconst_4
    //   4546: iload #23
    //   4548: imul
    //   4549: iconst_1
    //   4550: iadd
    //   4551: baload
    //   4552: sipush #255
    //   4555: iand
    //   4556: bipush #16
    //   4558: ishl
    //   4559: ior
    //   4560: aload #10
    //   4562: iconst_4
    //   4563: iload #23
    //   4565: imul
    //   4566: iconst_2
    //   4567: iadd
    //   4568: baload
    //   4569: sipush #255
    //   4572: iand
    //   4573: bipush #8
    //   4575: ishl
    //   4576: ior
    //   4577: aload #10
    //   4579: iconst_4
    //   4580: iload #23
    //   4582: imul
    //   4583: iconst_3
    //   4584: iadd
    //   4585: baload
    //   4586: sipush #255
    //   4589: iand
    //   4590: ior
    //   4591: iastore
    //   4592: iload_2
    //   4593: ifne -> 4746
    //   4596: goto -> 4603
    //   4599: invokestatic a : (Ljava/lang/Throwable;)Ljava/lang/Throwable;
    //   4602: athrow
    //   4603: aload #21
    //   4605: iload #23
    //   4607: aload #21
    //   4609: iload #23
    //   4611: iconst_2
    //   4612: isub
    //   4613: iaload
    //   4614: bipush #17
    //   4616: iushr
    //   4617: aload #21
    //   4619: iload #23
    //   4621: iconst_2
    //   4622: isub
    //   4623: iaload
    //   4624: bipush #15
    //   4626: ishl
    //   4627: ior
    //   4628: aload #21
    //   4630: iload #23
    //   4632: iconst_2
    //   4633: isub
    //   4634: iaload
    //   4635: bipush #19
    //   4637: iushr
    //   4638: aload #21
    //   4640: iload #23
    //   4642: iconst_2
    //   4643: isub
    //   4644: iaload
    //   4645: bipush #13
    //   4647: ishl
    //   4648: ior
    //   4649: ixor
    //   4650: aload #21
    //   4652: iload #23
    //   4654: iconst_2
    //   4655: isub
    //   4656: iaload
    //   4657: bipush #10
    //   4659: iushr
    //   4660: ixor
    //   4661: aload #21
    //   4663: iload #23
    //   4665: bipush #7
    //   4667: isub
    //   4668: iaload
    //   4669: iadd
    //   4670: aload #21
    //   4672: iload #23
    //   4674: bipush #15
    //   4676: isub
    //   4677: iaload
    //   4678: bipush #7
    //   4680: iushr
    //   4681: aload #21
    //   4683: iload #23
    //   4685: bipush #15
    //   4687: isub
    //   4688: iaload
    //   4689: bipush #25
    //   4691: ishl
    //   4692: ior
    //   4693: aload #21
    //   4695: iload #23
    //   4697: bipush #15
    //   4699: isub
    //   4700: iaload
    //   4701: bipush #18
    //   4703: iushr
    //   4704: aload #21
    //   4706: iload #23
    //   4708: bipush #15
    //   4710: isub
    //   4711: iaload
    //   4712: bipush #14
    //   4714: ishl
    //   4715: ior
    //   4716: ixor
    //   4717: aload #21
    //   4719: iload #23
    //   4721: bipush #15
    //   4723: isub
    //   4724: iaload
    //   4725: iconst_3
    //   4726: iushr
    //   4727: ixor
    //   4728: iadd
    //   4729: aload #21
    //   4731: iload #23
    //   4733: bipush #16
    //   4735: isub
    //   4736: iaload
    //   4737: iadd
    //   4738: iastore
    //   4739: goto -> 4746
    //   4742: invokestatic a : (Ljava/lang/Throwable;)Ljava/lang/Throwable;
    //   4745: athrow
    //   4746: aload #22
    //   4748: bipush #7
    //   4750: iaload
    //   4751: aload #22
    //   4753: iconst_4
    //   4754: iaload
    //   4755: bipush #6
    //   4757: iushr
    //   4758: aload #22
    //   4760: iconst_4
    //   4761: iaload
    //   4762: bipush #26
    //   4764: ishl
    //   4765: ior
    //   4766: aload #22
    //   4768: iconst_4
    //   4769: iaload
    //   4770: bipush #11
    //   4772: iushr
    //   4773: aload #22
    //   4775: iconst_4
    //   4776: iaload
    //   4777: bipush #21
    //   4779: ishl
    //   4780: ior
    //   4781: ixor
    //   4782: aload #22
    //   4784: iconst_4
    //   4785: iaload
    //   4786: bipush #25
    //   4788: iushr
    //   4789: aload #22
    //   4791: iconst_4
    //   4792: iaload
    //   4793: bipush #7
    //   4795: ishl
    //   4796: ior
    //   4797: ixor
    //   4798: iadd
    //   4799: aload #22
    //   4801: bipush #6
    //   4803: iaload
    //   4804: aload #22
    //   4806: iconst_4
    //   4807: iaload
    //   4808: aload #22
    //   4810: iconst_5
    //   4811: iaload
    //   4812: aload #22
    //   4814: bipush #6
    //   4816: iaload
    //   4817: ixor
    //   4818: iand
    //   4819: ixor
    //   4820: iadd
    //   4821: aload #7
    //   4823: iload #23
    //   4825: iaload
    //   4826: iadd
    //   4827: aload #21
    //   4829: iload #23
    //   4831: iaload
    //   4832: iadd
    //   4833: istore #24
    //   4835: aload #22
    //   4837: iconst_0
    //   4838: iaload
    //   4839: iconst_2
    //   4840: iushr
    //   4841: aload #22
    //   4843: iconst_0
    //   4844: iaload
    //   4845: bipush #30
    //   4847: ishl
    //   4848: ior
    //   4849: aload #22
    //   4851: iconst_0
    //   4852: iaload
    //   4853: bipush #13
    //   4855: iushr
    //   4856: aload #22
    //   4858: iconst_0
    //   4859: iaload
    //   4860: bipush #19
    //   4862: ishl
    //   4863: ior
    //   4864: ixor
    //   4865: aload #22
    //   4867: iconst_0
    //   4868: iaload
    //   4869: bipush #22
    //   4871: iushr
    //   4872: aload #22
    //   4874: iconst_0
    //   4875: iaload
    //   4876: bipush #10
    //   4878: ishl
    //   4879: ior
    //   4880: ixor
    //   4881: aload #22
    //   4883: iconst_0
    //   4884: iaload
    //   4885: aload #22
    //   4887: iconst_1
    //   4888: iaload
    //   4889: iand
    //   4890: aload #22
    //   4892: iconst_2
    //   4893: iaload
    //   4894: aload #22
    //   4896: iconst_0
    //   4897: iaload
    //   4898: aload #22
    //   4900: iconst_1
    //   4901: iaload
    //   4902: ior
    //   4903: iand
    //   4904: ior
    //   4905: iadd
    //   4906: istore #25
    //   4908: aload #22
    //   4910: iconst_3
    //   4911: dup2
    //   4912: iaload
    //   4913: iload #24
    //   4915: iadd
    //   4916: iastore
    //   4917: aload #22
    //   4919: bipush #7
    //   4921: iload #24
    //   4923: iload #25
    //   4925: iadd
    //   4926: iastore
    //   4927: aload #22
    //   4929: bipush #7
    //   4931: iaload
    //   4932: istore #24
    //   4934: aload #22
    //   4936: bipush #7
    //   4938: aload #22
    //   4940: bipush #6
    //   4942: iaload
    //   4943: iastore
    //   4944: aload #22
    //   4946: bipush #6
    //   4948: aload #22
    //   4950: iconst_5
    //   4951: iaload
    //   4952: iastore
    //   4953: aload #22
    //   4955: iconst_5
    //   4956: aload #22
    //   4958: iconst_4
    //   4959: iaload
    //   4960: iastore
    //   4961: aload #22
    //   4963: iconst_4
    //   4964: aload #22
    //   4966: iconst_3
    //   4967: iaload
    //   4968: iastore
    //   4969: aload #22
    //   4971: iconst_3
    //   4972: aload #22
    //   4974: iconst_2
    //   4975: iaload
    //   4976: iastore
    //   4977: aload #22
    //   4979: iconst_2
    //   4980: aload #22
    //   4982: iconst_1
    //   4983: iaload
    //   4984: iastore
    //   4985: aload #22
    //   4987: iconst_1
    //   4988: aload #22
    //   4990: iconst_0
    //   4991: iaload
    //   4992: iastore
    //   4993: aload #22
    //   4995: iconst_0
    //   4996: iload #24
    //   4998: iastore
    //   4999: iinc #23, 1
    //   5002: iload_2
    //   5003: ifne -> 4511
    //   5006: iconst_0
    //   5007: istore #23
    //   5009: iload #23
    //   5011: bipush #8
    //   5013: if_icmpge -> 5036
    //   5016: aload #9
    //   5018: iload #23
    //   5020: dup2
    //   5021: iaload
    //   5022: aload #22
    //   5024: iload #23
    //   5026: iaload
    //   5027: iadd
    //   5028: iastore
    //   5029: iinc #23, 1
    //   5032: iload_2
    //   5033: ifne -> 5009
    //   5036: bipush #32
    //   5038: newarray byte
    //   5040: astore #5
    //   5042: sipush #9430
    //   5045: aload #5
    //   5047: iconst_0
    //   5048: aload #9
    //   5050: iconst_0
    //   5051: iaload
    //   5052: bipush #24
    //   5054: iushr
    //   5055: i2b
    //   5056: bastore
    //   5057: sipush #13513
    //   5060: aload #5
    //   5062: iconst_1
    //   5063: aload #9
    //   5065: iconst_0
    //   5066: iaload
    //   5067: bipush #16
    //   5069: iushr
    //   5070: i2b
    //   5071: bastore
    //   5072: aload #5
    //   5074: iconst_2
    //   5075: aload #9
    //   5077: iconst_0
    //   5078: iaload
    //   5079: bipush #8
    //   5081: iushr
    //   5082: i2b
    //   5083: bastore
    //   5084: aload #5
    //   5086: iconst_3
    //   5087: aload #9
    //   5089: iconst_0
    //   5090: iaload
    //   5091: i2b
    //   5092: bastore
    //   5093: aload #5
    //   5095: iconst_4
    //   5096: aload #9
    //   5098: iconst_1
    //   5099: iaload
    //   5100: bipush #24
    //   5102: iushr
    //   5103: i2b
    //   5104: bastore
    //   5105: aload #5
    //   5107: iconst_5
    //   5108: aload #9
    //   5110: iconst_1
    //   5111: iaload
    //   5112: bipush #16
    //   5114: iushr
    //   5115: i2b
    //   5116: bastore
    //   5117: aload #5
    //   5119: bipush #6
    //   5121: aload #9
    //   5123: iconst_1
    //   5124: iaload
    //   5125: bipush #8
    //   5127: iushr
    //   5128: i2b
    //   5129: bastore
    //   5130: aload #5
    //   5132: bipush #7
    //   5134: aload #9
    //   5136: iconst_1
    //   5137: iaload
    //   5138: i2b
    //   5139: bastore
    //   5140: aload #5
    //   5142: bipush #8
    //   5144: aload #9
    //   5146: iconst_2
    //   5147: iaload
    //   5148: bipush #24
    //   5150: iushr
    //   5151: i2b
    //   5152: bastore
    //   5153: aload #5
    //   5155: bipush #9
    //   5157: aload #9
    //   5159: iconst_2
    //   5160: iaload
    //   5161: bipush #16
    //   5163: iushr
    //   5164: i2b
    //   5165: bastore
    //   5166: aload #5
    //   5168: bipush #10
    //   5170: aload #9
    //   5172: iconst_2
    //   5173: iaload
    //   5174: bipush #8
    //   5176: iushr
    //   5177: i2b
    //   5178: bastore
    //   5179: aload #5
    //   5181: bipush #11
    //   5183: aload #9
    //   5185: iconst_2
    //   5186: iaload
    //   5187: i2b
    //   5188: bastore
    //   5189: aload #5
    //   5191: bipush #12
    //   5193: aload #9
    //   5195: iconst_3
    //   5196: iaload
    //   5197: bipush #24
    //   5199: iushr
    //   5200: i2b
    //   5201: bastore
    //   5202: aload #5
    //   5204: bipush #13
    //   5206: aload #9
    //   5208: iconst_3
    //   5209: iaload
    //   5210: bipush #16
    //   5212: iushr
    //   5213: i2b
    //   5214: bastore
    //   5215: aload #5
    //   5217: bipush #14
    //   5219: aload #9
    //   5221: iconst_3
    //   5222: iaload
    //   5223: bipush #8
    //   5225: iushr
    //   5226: i2b
    //   5227: bastore
    //   5228: aload #5
    //   5230: bipush #15
    //   5232: aload #9
    //   5234: iconst_3
    //   5235: iaload
    //   5236: i2b
    //   5237: bastore
    //   5238: aload #5
    //   5240: bipush #16
    //   5242: aload #9
    //   5244: iconst_4
    //   5245: iaload
    //   5246: bipush #24
    //   5248: iushr
    //   5249: i2b
    //   5250: bastore
    //   5251: aload #5
    //   5253: bipush #17
    //   5255: aload #9
    //   5257: iconst_4
    //   5258: iaload
    //   5259: bipush #16
    //   5261: iushr
    //   5262: i2b
    //   5263: bastore
    //   5264: aload #5
    //   5266: bipush #18
    //   5268: aload #9
    //   5270: iconst_4
    //   5271: iaload
    //   5272: bipush #8
    //   5274: iushr
    //   5275: i2b
    //   5276: bastore
    //   5277: aload #5
    //   5279: bipush #19
    //   5281: aload #9
    //   5283: iconst_4
    //   5284: iaload
    //   5285: i2b
    //   5286: bastore
    //   5287: aload #5
    //   5289: bipush #20
    //   5291: aload #9
    //   5293: iconst_5
    //   5294: iaload
    //   5295: bipush #24
    //   5297: iushr
    //   5298: i2b
    //   5299: bastore
    //   5300: aload #5
    //   5302: bipush #21
    //   5304: aload #9
    //   5306: iconst_5
    //   5307: iaload
    //   5308: bipush #16
    //   5310: iushr
    //   5311: i2b
    //   5312: bastore
    //   5313: aload #5
    //   5315: bipush #22
    //   5317: aload #9
    //   5319: iconst_5
    //   5320: iaload
    //   5321: bipush #8
    //   5323: iushr
    //   5324: i2b
    //   5325: bastore
    //   5326: aload #5
    //   5328: bipush #23
    //   5330: aload #9
    //   5332: iconst_5
    //   5333: iaload
    //   5334: i2b
    //   5335: bastore
    //   5336: aload #5
    //   5338: bipush #24
    //   5340: aload #9
    //   5342: bipush #6
    //   5344: iaload
    //   5345: bipush #24
    //   5347: iushr
    //   5348: i2b
    //   5349: bastore
    //   5350: aload #5
    //   5352: bipush #25
    //   5354: aload #9
    //   5356: bipush #6
    //   5358: iaload
    //   5359: bipush #16
    //   5361: iushr
    //   5362: i2b
    //   5363: bastore
    //   5364: aload #5
    //   5366: bipush #26
    //   5368: aload #9
    //   5370: bipush #6
    //   5372: iaload
    //   5373: bipush #8
    //   5375: iushr
    //   5376: i2b
    //   5377: bastore
    //   5378: aload #5
    //   5380: bipush #27
    //   5382: aload #9
    //   5384: bipush #6
    //   5386: iaload
    //   5387: i2b
    //   5388: bastore
    //   5389: aload #5
    //   5391: bipush #28
    //   5393: aload #9
    //   5395: bipush #7
    //   5397: iaload
    //   5398: bipush #24
    //   5400: iushr
    //   5401: i2b
    //   5402: bastore
    //   5403: aload #5
    //   5405: bipush #29
    //   5407: aload #9
    //   5409: bipush #7
    //   5411: iaload
    //   5412: bipush #16
    //   5414: iushr
    //   5415: i2b
    //   5416: bastore
    //   5417: aload #5
    //   5419: bipush #30
    //   5421: aload #9
    //   5423: bipush #7
    //   5425: iaload
    //   5426: bipush #8
    //   5428: iushr
    //   5429: i2b
    //   5430: bastore
    //   5431: aload #5
    //   5433: bipush #31
    //   5435: aload #9
    //   5437: bipush #7
    //   5439: iaload
    //   5440: i2b
    //   5441: bastore
    //   5442: new java/math/BigInteger
    //   5445: dup
    //   5446: aload #5
    //   5448: invokespecial <init> : ([B)V
    //   5451: invokevirtual abs : ()Ljava/math/BigInteger;
    //   5454: putstatic burp/Zztx.ZM : Ljava/lang/Object;
    //   5457: invokestatic a : (II)Ljava/lang/String;
    //   5460: iconst_1
    //   5461: ldc burp/Zszz
    //   5463: invokevirtual getClassLoader : ()Ljava/lang/ClassLoader;
    //   5466: invokestatic forName : (Ljava/lang/String;ZLjava/lang/ClassLoader;)Ljava/lang/Class;
    //   5469: invokevirtual getDeclaredFields : ()[Ljava/lang/reflect/Field;
    //   5472: astore #4
    //   5474: aload #4
    //   5476: arraylength
    //   5477: istore #5
    //   5479: iconst_0
    //   5480: istore #6
    //   5482: iload #6
    //   5484: iload #5
    //   5486: if_icmpge -> 5624
    //   5489: aload #4
    //   5491: iload #6
    //   5493: aaload
    //   5494: astore #7
    //   5496: aload #7
    //   5498: invokevirtual getModifiers : ()I
    //   5501: invokestatic isStatic : (I)Z
    //   5504: ifne -> 5514
    //   5507: goto -> 5617
    //   5510: invokestatic a : (Ljava/lang/Throwable;)Ljava/lang/Throwable;
    //   5513: athrow
    //   5514: aload #7
    //   5516: invokevirtual getType : ()Ljava/lang/Class;
    //   5519: astore #8
    //   5521: aload #8
    //   5523: ifnull -> 5604
    //   5526: aload #8
    //   5528: invokevirtual isPrimitive : ()Z
    //   5531: ifne -> 5604
    //   5534: goto -> 5541
    //   5537: invokestatic a : (Ljava/lang/Throwable;)Ljava/lang/Throwable;
    //   5540: athrow
    //   5541: aload #8
    //   5543: invokevirtual getPackage : ()Ljava/lang/Package;
    //   5546: ifnull -> 5604
    //   5549: goto -> 5556
    //   5552: invokestatic a : (Ljava/lang/Throwable;)Ljava/lang/Throwable;
    //   5555: athrow
    //   5556: aload #8
    //   5558: invokevirtual getPackage : ()Ljava/lang/Package;
    //   5561: invokevirtual getName : ()Ljava/lang/String;
    //   5564: ifnull -> 5604
    //   5567: goto -> 5574
    //   5570: invokestatic a : (Ljava/lang/Throwable;)Ljava/lang/Throwable;
    //   5573: athrow
    //   5574: aload #8
    //   5576: invokevirtual getPackage : ()Ljava/lang/Package;
    //   5579: invokevirtual getName : ()Ljava/lang/String;
    //   5582: sipush #9431
    //   5585: sipush #11391
    //   5588: invokestatic a : (II)Ljava/lang/String;
    //   5591: invokevirtual startsWith : (Ljava/lang/String;)Z
    //   5594: ifne -> 5604
    //   5597: goto -> 5604
    //   5600: invokestatic a : (Ljava/lang/Throwable;)Ljava/lang/Throwable;
    //   5603: athrow
    //   5604: aload #7
    //   5606: iconst_1
    //   5607: invokevirtual setAccessible : (Z)V
    //   5610: aload #7
    //   5612: aconst_null
    //   5613: invokevirtual get : (Ljava/lang/Object;)Ljava/lang/Object;
    //   5616: pop
    //   5617: iinc #6, 1
    //   5620: iload_2
    //   5621: ifne -> 5482
    //   5624: sipush #9436
    //   5627: sipush #-7210
    //   5630: invokestatic a : (II)Ljava/lang/String;
    //   5633: invokestatic forName : (Ljava/lang/String;)Ljava/lang/Class;
    //   5636: invokevirtual getDeclaredMethods : ()[Ljava/lang/reflect/Method;
    //   5639: astore #4
    //   5641: aload #4
    //   5643: arraylength
    //   5644: istore #5
    //   5646: iconst_0
    //   5647: istore #6
    //   5649: iload #6
    //   5651: iload #5
    //   5653: if_icmpge -> 5765
    //   5656: aload #4
    //   5658: iload #6
    //   5660: aaload
    //   5661: astore #7
    //   5663: aload #7
    //   5665: invokevirtual getParameterTypes : ()[Ljava/lang/Class;
    //   5668: pop
    //   5669: aload #7
    //   5671: invokevirtual getModifiers : ()I
    //   5674: invokestatic isStatic : (I)Z
    //   5677: ifeq -> 5751
    //   5680: aload #7
    //   5682: invokevirtual getParameterTypes : ()[Ljava/lang/Class;
    //   5685: arraylength
    //   5686: iconst_2
    //   5687: if_icmpne -> 5751
    //   5690: goto -> 5697
    //   5693: invokestatic a : (Ljava/lang/Throwable;)Ljava/lang/Throwable;
    //   5696: athrow
    //   5697: aload #7
    //   5699: invokevirtual getReturnType : ()Ljava/lang/Class;
    //   5702: getstatic java/lang/Boolean.TYPE : Ljava/lang/Class;
    //   5705: if_acmpne -> 5751
    //   5708: goto -> 5715
    //   5711: invokestatic a : (Ljava/lang/Throwable;)Ljava/lang/Throwable;
    //   5714: athrow
    //   5715: aload #7
    //   5717: iconst_1
    //   5718: invokevirtual setAccessible : (Z)V
    //   5721: aload #7
    //   5723: aconst_null
    //   5724: iconst_2
    //   5725: anewarray java/lang/Object
    //   5728: dup
    //   5729: iconst_0
    //   5730: aload_0
    //   5731: aastore
    //   5732: dup
    //   5733: iconst_1
    //   5734: aload_1
    //   5735: aastore
    //   5736: invokevirtual invoke : (Ljava/lang/Object;[Ljava/lang/Object;)Ljava/lang/Object;
    //   5739: pop
    //   5740: iload_2
    //   5741: ifne -> 5765
    //   5744: goto -> 5751
    //   5747: invokestatic a : (Ljava/lang/Throwable;)Ljava/lang/Throwable;
    //   5750: athrow
    //   5751: iinc #6, 1
    //   5754: iload_2
    //   5755: ifne -> 5649
    //   5758: goto -> 5765
    //   5761: invokestatic a : (Ljava/lang/Throwable;)Ljava/lang/Throwable;
    //   5764: athrow
    //   5765: sipush #9433
    //   5768: sipush #9416
    //   5771: invokestatic a : (II)Ljava/lang/String;
    //   5774: iconst_1
    //   5775: ldc burp/Zbxp
    //   5777: invokevirtual getClassLoader : ()Ljava/lang/ClassLoader;
    //   5780: invokestatic forName : (Ljava/lang/String;ZLjava/lang/ClassLoader;)Ljava/lang/Class;
    //   5783: invokevirtual getDeclaredFields : ()[Ljava/lang/reflect/Field;
    //   5786: astore #4
    //   5788: aload #4
    //   5790: arraylength
    //   5791: istore #5
    //   5793: iconst_0
    //   5794: istore #6
    //   5796: iload #6
    //   5798: iload #5
    //   5800: if_icmpge -> 5938
    //   5803: aload #4
    //   5805: iload #6
    //   5807: aaload
    //   5808: astore #7
    //   5810: aload #7
    //   5812: invokevirtual getModifiers : ()I
    //   5815: invokestatic isStatic : (I)Z
    //   5818: ifne -> 5828
    //   5821: goto -> 5931
    //   5824: invokestatic a : (Ljava/lang/Throwable;)Ljava/lang/Throwable;
    //   5827: athrow
    //   5828: aload #7
    //   5830: invokevirtual getType : ()Ljava/lang/Class;
    //   5833: astore #8
    //   5835: aload #8
    //   5837: ifnull -> 5918
    //   5840: aload #8
    //   5842: invokevirtual isPrimitive : ()Z
    //   5845: ifne -> 5918
    //   5848: goto -> 5855
    //   5851: invokestatic a : (Ljava/lang/Throwable;)Ljava/lang/Throwable;
    //   5854: athrow
    //   5855: aload #8
    //   5857: invokevirtual getPackage : ()Ljava/lang/Package;
    //   5860: ifnull -> 5918
    //   5863: goto -> 5870
    //   5866: invokestatic a : (Ljava/lang/Throwable;)Ljava/lang/Throwable;
    //   5869: athrow
    //   5870: aload #8
    //   5872: invokevirtual getPackage : ()Ljava/lang/Package;
    //   5875: invokevirtual getName : ()Ljava/lang/String;
    //   5878: ifnull -> 5918
    //   5881: goto -> 5888
    //   5884: invokestatic a : (Ljava/lang/Throwable;)Ljava/lang/Throwable;
    //   5887: athrow
    //   5888: aload #8
    //   5890: invokevirtual getPackage : ()Ljava/lang/Package;
    //   5893: invokevirtual getName : ()Ljava/lang/String;
    //   5896: sipush #9435
    //   5899: sipush #-20566
    //   5902: invokestatic a : (II)Ljava/lang/String;
    //   5905: invokevirtual startsWith : (Ljava/lang/String;)Z
    //   5908: ifne -> 5918
    //   5911: goto -> 5918
    //   5914: invokestatic a : (Ljava/lang/Throwable;)Ljava/lang/Throwable;
    //   5917: athrow
    //   5918: aload #7
    //   5920: iconst_1
    //   5921: invokevirtual setAccessible : (Z)V
    //   5924: aload #7
    //   5926: aconst_null
    //   5927: invokevirtual get : (Ljava/lang/Object;)Ljava/lang/Object;
    //   5930: pop
    //   5931: iinc #6, 1
    //   5934: iload_2
    //   5935: ifne -> 5796
    //   5938: sipush #9437
    //   5941: sipush #-23502
    //   5944: invokestatic a : (II)Ljava/lang/String;
    //   5947: invokestatic forName : (Ljava/lang/String;)Ljava/lang/Class;
    //   5950: invokevirtual getDeclaredMethods : ()[Ljava/lang/reflect/Method;
    //   5953: astore #4
    //   5955: aload #4
    //   5957: arraylength
    //   5958: istore #5
    //   5960: iconst_0
    //   5961: istore #6
    //   5963: iload #6
    //   5965: iload #5
    //   5967: if_icmpge -> 6100
    //   5970: aload #4
    //   5972: iload #6
    //   5974: aaload
    //   5975: astore #7
    //   5977: aload #7
    //   5979: invokevirtual getParameterTypes : ()[Ljava/lang/Class;
    //   5982: pop
    //   5983: aload #7
    //   5985: invokevirtual getModifiers : ()I
    //   5988: invokestatic isStatic : (I)Z
    //   5991: ifeq -> 6086
    //   5994: aload #7
    //   5996: invokevirtual getParameterTypes : ()[Ljava/lang/Class;
    //   5999: arraylength
    //   6000: iconst_2
    //   6001: if_icmpne -> 6086
    //   6004: goto -> 6011
    //   6007: invokestatic a : (Ljava/lang/Throwable;)Ljava/lang/Throwable;
    //   6010: athrow
    //   6011: aload #7
    //   6013: invokevirtual getReturnType : ()Ljava/lang/Class;
    //   6016: getstatic java/lang/Void.TYPE : Ljava/lang/Class;
    //   6019: invokevirtual equals : (Ljava/lang/Object;)Z
    //   6022: ifeq -> 6086
    //   6025: goto -> 6032
    //   6028: invokestatic a : (Ljava/lang/Throwable;)Ljava/lang/Throwable;
    //   6031: athrow
    //   6032: aload #7
    //   6034: iconst_1
    //   6035: invokevirtual setAccessible : (Z)V
    //   6038: aload #7
    //   6040: aconst_null
    //   6041: iconst_2
    //   6042: anewarray java/lang/Object
    //   6045: dup
    //   6046: iconst_0
    //   6047: aload_0
    //   6048: aastore
    //   6049: dup
    //   6050: iconst_1
    //   6051: aload_1
    //   6052: ifnonnull -> 6070
    //   6055: goto -> 6062
    //   6058: invokestatic a : (Ljava/lang/Throwable;)Ljava/lang/Throwable;
    //   6061: athrow
    //   6062: aload_1
    //   6063: goto -> 6077
    //   6066: invokestatic a : (Ljava/lang/Throwable;)Ljava/lang/Throwable;
    //   6069: athrow
    //   6070: aload_1
    //   6071: checkcast [B
    //   6074: invokevirtual clone : ()Ljava/lang/Object;
    //   6077: aastore
    //   6078: invokevirtual invoke : (Ljava/lang/Object;[Ljava/lang/Object;)Ljava/lang/Object;
    //   6081: pop
    //   6082: iload_2
    //   6083: ifne -> 6100
    //   6086: iinc #6, 1
    //   6089: iload_2
    //   6090: ifne -> 5963
    //   6093: goto -> 6100
    //   6096: invokestatic a : (Ljava/lang/Throwable;)Ljava/lang/Throwable;
    //   6099: athrow
    //   6100: getstatic burp/Zg4d.ZE : Ljava/lang/String;
    //   6103: getstatic burp/Zl7k.ZS : Ljava/lang/Object;
    //   6106: checkcast java/math/BigInteger
    //   6109: invokevirtual intValue : ()I
    //   6112: bipush #32
    //   6114: irem
    //   6115: invokestatic abs : (I)I
    //   6118: invokevirtual charAt : (I)C
    //   6121: getstatic burp/Zzap.ZA : Ljava/lang/String;
    //   6124: getstatic burp/Zl2g.ZG : Ljava/lang/Object;
    //   6127: checkcast java/math/BigInteger
    //   6130: invokevirtual intValue : ()I
    //   6133: bipush #32
    //   6135: irem
    //   6136: invokestatic abs : (I)I
    //   6139: invokevirtual charAt : (I)C
    //   6142: if_icmple -> 6249
    //   6145: getstatic burp/Zero.ZL : Ljava/lang/String;
    //   6148: getstatic burp/Zz80.ZR : Ljava/lang/Object;
    //   6151: checkcast java/math/BigInteger
    //   6154: invokevirtual intValue : ()I
    //   6157: bipush #32
    //   6159: irem
    //   6160: invokestatic abs : (I)I
    //   6163: invokevirtual charAt : (I)C
    //   6166: getstatic burp/Zgdj.Zt : Ljava/lang/String;
    //   6169: getstatic burp/Ztq8.Zm : Ljava/lang/Object;
    //   6172: checkcast java/math/BigInteger
    //   6175: invokevirtual intValue : ()I
    //   6178: bipush #32
    //   6180: irem
    //   6181: invokestatic abs : (I)I
    //   6184: invokevirtual charAt : (I)C
    //   6187: if_icmpgt -> 6249
    //   6190: goto -> 6197
    //   6193: invokestatic a : (Ljava/lang/Throwable;)Ljava/lang/Throwable;
    //   6196: athrow
    //   6197: getstatic burp/Zmj8.ZL : Ljava/lang/String;
    //   6200: getstatic burp/Zr8s.Zt : Ljava/lang/Object;
    //   6203: checkcast java/math/BigInteger
    //   6206: invokevirtual intValue : ()I
    //   6209: bipush #32
    //   6211: irem
    //   6212: invokestatic abs : (I)I
    //   6215: invokevirtual charAt : (I)C
    //   6218: getstatic burp/Zgt6.Zu : Ljava/lang/String;
    //   6221: getstatic burp/Zsgj.ZK : Ljava/lang/Object;
    //   6224: checkcast java/math/BigInteger
    //   6227: invokevirtual intValue : ()I
    //   6230: bipush #32
    //   6232: irem
    //   6233: invokestatic abs : (I)I
    //   6236: invokevirtual charAt : (I)C
    //   6239: if_icmpgt -> 6257
    //   6242: goto -> 6249
    //   6245: invokestatic a : (Ljava/lang/Throwable;)Ljava/lang/Throwable;
    //   6248: athrow
    //   6249: iconst_1
    //   6250: goto -> 6258
    //   6253: invokestatic a : (Ljava/lang/Throwable;)Ljava/lang/Throwable;
    //   6256: athrow
    //   6257: iconst_0
    //   6258: ireturn
    //   6259: astore_3
    //   6260: new java/lang/Exception
    //   6263: dup
    //   6264: aload_3
    //   6265: invokevirtual getMessage : ()Ljava/lang/String;
    //   6268: invokespecial <init> : (Ljava/lang/String;)V
    //   6271: athrow
    // Exception table:
    //   from	to	target	type
    //   4	6258	6259	java/lang/Throwable
    //   37	210	213	java/lang/Throwable
    //   180	247	250	java/lang/Throwable
    //   217	284	287	java/lang/Throwable
    //   254	321	324	java/lang/Throwable
    //   291	358	361	java/lang/Throwable
    //   328	395	398	java/lang/Throwable
    //   365	432	435	java/lang/Throwable
    //   402	469	472	java/lang/Throwable
    //   439	506	509	java/lang/Throwable
    //   476	543	546	java/lang/Throwable
    //   513	580	583	java/lang/Throwable
    //   550	617	620	java/lang/Throwable
    //   587	654	657	java/lang/Throwable
    //   624	691	694	java/lang/Throwable
    //   661	728	731	java/lang/Throwable
    //   698	765	768	java/lang/Throwable
    //   735	802	805	java/lang/Throwable
    //   772	839	842	java/lang/Throwable
    //   809	876	879	java/lang/Throwable
    //   846	913	916	java/lang/Throwable
    //   883	950	953	java/lang/Throwable
    //   920	987	990	java/lang/Throwable
    //   957	1024	1027	java/lang/Throwable
    //   994	1061	1064	java/lang/Throwable
    //   1031	1098	1101	java/lang/Throwable
    //   1068	1135	1138	java/lang/Throwable
    //   1105	1172	1175	java/lang/Throwable
    //   1142	1209	1212	java/lang/Throwable
    //   1179	1246	1249	java/lang/Throwable
    //   1216	1283	1286	java/lang/Throwable
    //   1253	1320	1323	java/lang/Throwable
    //   1290	1353	1356	java/lang/Throwable
    //   2177	2211	2214	java/lang/Throwable
    //   2307	2385	2388	java/lang/Throwable
    //   2314	2528	2531	java/lang/Throwable
    //   2906	2921	2921	java/lang/Throwable
    //   2948	2982	2985	java/lang/Throwable
    //   2992	3004	3007	java/lang/Throwable
    //   3090	3168	3171	java/lang/Throwable
    //   3097	3311	3314	java/lang/Throwable
    //   3711	3789	3792	java/lang/Throwable
    //   3718	3932	3935	java/lang/Throwable
    //   4379	4413	4416	java/lang/Throwable
    //   4420	4432	4435	java/lang/Throwable
    //   4518	4596	4599	java/lang/Throwable
    //   4525	4739	4742	java/lang/Throwable
    //   5496	5510	5510	java/lang/Throwable
    //   5521	5534	5537	java/lang/Throwable
    //   5526	5549	5552	java/lang/Throwable
    //   5541	5567	5570	java/lang/Throwable
    //   5556	5597	5600	java/lang/Throwable
    //   5663	5690	5693	java/lang/Throwable
    //   5680	5708	5711	java/lang/Throwable
    //   5697	5744	5747	java/lang/Throwable
    //   5715	5758	5761	java/lang/Throwable
    //   5810	5824	5824	java/lang/Throwable
    //   5835	5848	5851	java/lang/Throwable
    //   5840	5863	5866	java/lang/Throwable
    //   5855	5881	5884	java/lang/Throwable
    //   5870	5911	5914	java/lang/Throwable
    //   5977	6004	6007	java/lang/Throwable
    //   5994	6025	6028	java/lang/Throwable
    //   6011	6055	6058	java/lang/Throwable
    //   6032	6066	6066	java/lang/Throwable
    //   6077	6093	6096	java/lang/Throwable
    //   6100	6190	6193	java/lang/Throwable
    //   6145	6242	6245	java/lang/Throwable
    //   6197	6253	6253	java/lang/Throwable
  }
  
  static {
    // Byte code:
    //   0: bipush #12
    //   2: anewarray java/lang/String
    //   5: astore #5
    //   7: iconst_0
    //   8: istore_3
    //   9: ldc '@"d{\\t?'Iz )[Az&\\nxtR\\tM -p{;XKuZrO(fO^\\t!*A\\t\\tTp,2MLZO@8i}EAFDH1.Qb37 ~'w$FPi4:r>(\\te+Pn'
    //   11: dup
    //   12: astore_2
    //   13: invokevirtual length : ()I
    //   16: istore #4
    //   18: bipush #9
    //   20: istore_1
    //   21: iconst_m1
    //   22: istore_0
    //   23: bipush #69
    //   25: iinc #0, 1
    //   28: aload_2
    //   29: iload_0
    //   30: dup
    //   31: iload_1
    //   32: iadd
    //   33: invokevirtual substring : (II)Ljava/lang/String;
    //   36: iconst_m1
    //   37: goto -> 143
    //   40: aload #5
    //   42: swap
    //   43: iload_3
    //   44: iinc #3, 1
    //   47: swap
    //   48: aastore
    //   49: iload_0
    //   50: iload_1
    //   51: iadd
    //   52: dup
    //   53: istore_0
    //   54: iload #4
    //   56: if_icmpge -> 68
    //   59: aload_2
    //   60: iload_0
    //   61: invokevirtual charAt : (I)C
    //   64: istore_1
    //   65: goto -> 23
    //   68: ldc '8Q li'
    //   70: dup
    //   71: astore_2
    //   72: invokevirtual length : ()I
    //   75: istore #4
    //   77: bipush #9
    //   79: istore_1
    //   80: iconst_m1
    //   81: istore_0
    //   82: bipush #77
    //   84: iinc #0, 1
    //   87: aload_2
    //   88: iload_0
    //   89: dup
    //   90: iload_1
    //   91: iadd
    //   92: invokevirtual substring : (II)Ljava/lang/String;
    //   95: iconst_0
    //   96: goto -> 143
    //   99: aload #5
    //   101: swap
    //   102: iload_3
    //   103: iinc #3, 1
    //   106: swap
    //   107: aastore
    //   108: iload_0
    //   109: iload_1
    //   110: iadd
    //   111: dup
    //   112: istore_0
    //   113: iload #4
    //   115: if_icmpge -> 127
    //   118: aload_2
    //   119: iload_0
    //   120: invokevirtual charAt : (I)C
    //   123: istore_1
    //   124: goto -> 82
    //   127: aload #5
    //   129: putstatic burp/Zb9m.a : [Ljava/lang/String;
    //   132: bipush #12
    //   134: anewarray java/lang/String
    //   137: putstatic burp/Zb9m.b : [Ljava/lang/String;
    //   140: goto -> 300
    //   143: dup_x2
    //   144: pop
    //   145: invokevirtual toCharArray : ()[C
    //   148: dup_x1
    //   149: arraylength
    //   150: dup_x2
    //   151: pop
    //   152: iconst_0
    //   153: istore #6
    //   155: dup2_x1
    //   156: pop2
    //   157: dup_x2
    //   158: iconst_1
    //   159: if_icmpgt -> 260
    //   162: dup2
    //   163: swap
    //   164: iload #6
    //   166: dup2_x1
    //   167: caload
    //   168: swap
    //   169: iload #6
    //   171: bipush #7
    //   173: irem
    //   174: tableswitch default -> 242, 0 -> 212, 1 -> 217, 2 -> 222, 3 -> 227, 4 -> 232, 5 -> 237
    //   212: bipush #92
    //   214: goto -> 244
    //   217: bipush #18
    //   219: goto -> 244
    //   222: bipush #7
    //   224: goto -> 244
    //   227: bipush #26
    //   229: goto -> 244
    //   232: bipush #53
    //   234: goto -> 244
    //   237: bipush #52
    //   239: goto -> 244
    //   242: bipush #82
    //   244: ixor
    //   245: ixor
    //   246: i2c
    //   247: castore
    //   248: iinc #6, 1
    //   251: dup
    //   252: ifne -> 260
    //   255: dup2
    //   256: dup_x1
    //   257: goto -> 166
    //   260: dup2_x1
    //   261: pop2
    //   262: dup_x2
    //   263: iload #6
    //   265: if_icmpgt -> 162
    //   268: pop
    //   269: new java/lang/String
    //   272: dup_x1
    //   273: swap
    //   274: invokespecial <init> : ([C)V
    //   277: invokevirtual intern : ()Ljava/lang/String;
    //   280: swap
    //   281: pop
    //   282: swap
    //   283: tableswitch default -> 40, 0 -> 99
    //   300: new java/math/BigInteger
    //   303: dup
    //   304: bipush #32
    //   306: newarray byte
    //   308: dup
    //   309: iconst_0
    //   310: bipush #72
    //   312: bastore
    //   313: dup
    //   314: iconst_1
    //   315: bipush #-64
    //   317: bastore
    //   318: dup
    //   319: iconst_2
    //   320: bipush #29
    //   322: bastore
    //   323: dup
    //   324: iconst_3
    //   325: bipush #105
    //   327: bastore
    //   328: dup
    //   329: iconst_4
    //   330: bipush #-114
    //   332: bastore
    //   333: dup
    //   334: iconst_5
    //   335: bipush #-114
    //   337: bastore
    //   338: dup
    //   339: bipush #6
    //   341: bipush #-100
    //   343: bastore
    //   344: dup
    //   345: bipush #7
    //   347: bipush #114
    //   349: bastore
    //   350: dup
    //   351: bipush #8
    //   353: bipush #-5
    //   355: bastore
    //   356: dup
    //   357: bipush #9
    //   359: bipush #-50
    //   361: bastore
    //   362: dup
    //   363: bipush #10
    //   365: bipush #28
    //   367: bastore
    //   368: dup
    //   369: bipush #11
    //   371: bipush #-42
    //   373: bastore
    //   374: dup
    //   375: bipush #12
    //   377: bipush #-123
    //   379: bastore
    //   380: dup
    //   381: bipush #13
    //   383: bipush #60
    //   385: bastore
    //   386: dup
    //   387: bipush #14
    //   389: bipush #-83
    //   391: bastore
    //   392: dup
    //   393: bipush #15
    //   395: bipush #115
    //   397: bastore
    //   398: dup
    //   399: bipush #16
    //   401: bipush #-85
    //   403: bastore
    //   404: dup
    //   405: bipush #17
    //   407: bipush #-60
    //   409: bastore
    //   410: dup
    //   411: bipush #18
    //   413: bipush #-30
    //   415: bastore
    //   416: dup
    //   417: bipush #19
    //   419: bipush #-84
    //   421: bastore
    //   422: dup
    //   423: bipush #20
    //   425: bipush #14
    //   427: bastore
    //   428: dup
    //   429: bipush #21
    //   431: bipush #-66
    //   433: bastore
    //   434: dup
    //   435: bipush #22
    //   437: bipush #-113
    //   439: bastore
    //   440: dup
    //   441: bipush #23
    //   443: bipush #-77
    //   445: bastore
    //   446: dup
    //   447: bipush #24
    //   449: bipush #-104
    //   451: bastore
    //   452: dup
    //   453: bipush #25
    //   455: bipush #-6
    //   457: bastore
    //   458: dup
    //   459: bipush #26
    //   461: bipush #-92
    //   463: bastore
    //   464: dup
    //   465: bipush #27
    //   467: bipush #-69
    //   469: bastore
    //   470: dup
    //   471: bipush #28
    //   473: bipush #-125
    //   475: bastore
    //   476: dup
    //   477: bipush #29
    //   479: iconst_0
    //   480: bastore
    //   481: dup
    //   482: bipush #30
    //   484: bipush #38
    //   486: bastore
    //   487: dup
    //   488: bipush #31
    //   490: bipush #73
    //   492: bastore
    //   493: invokespecial <init> : ([B)V
    //   496: putstatic burp/Zb9m.ZK : Ljava/lang/Object;
    //   499: sipush #9432
    //   502: sipush #-14397
    //   505: invokestatic a : (II)Ljava/lang/String;
    //   508: putstatic burp/Zb9m.Zc : Ljava/lang/String;
    //   511: return
  }
  
  private static Throwable a(Throwable paramThrowable) {
    return paramThrowable;
  }
  
  private static String a(int paramInt1, int paramInt2) {
    int i = (paramInt1 ^ 0x24DC) & 0xFFFF;
    if (b[i] == null) {
      char[] arrayOfChar = a[i].toCharArray();
      switch (arrayOfChar[0] & 0xFF) {
        case 0:
        
        case 1:
        
        case 2:
        
        case 3:
        
        case 4:
        
        case 5:
        
        case 6:
        
        case 7:
        
        case 8:
        
        case 9:
        
        case 10:
        
        case 11:
        
        case 12:
        
        case 13:
        
        case 14:
        
        case 15:
        
        case 16:
        
        case 17:
        
        case 18:
        
        case 19:
        
        case 20:
        
        case 21:
        
        case 22:
        
        case 23:
        
        case 24:
        
        case 25:
        
        case 26:
        
        case 27:
        
        case 28:
        
        case 29:
        
        case 30:
        
        case 31:
        
        case 32:
        
        case 33:
        
        case 34:
        
        case 35:
        
        case 36:
        
        case 37:
        
        case 38:
        
        case 39:
        
        case 40:
        
        case 41:
        
        case 42:
        
        case 43:
        
        case 44:
        
        case 45:
        
        case 46:
        
        case 47:
        
        case 48:
        
        case 49:
        
        case 50:
        
        case 51:
        
        case 52:
        
        case 53:
        
        case 54:
        
        case 55:
        
        case 56:
        
        case 57:
        
        case 58:
        
        case 59:
        
        case 60:
        
        case 61:
        
        case 62:
        
        case 63:
        
        case 64:
        
        case 65:
        
        case 66:
        
        case 67:
        
        case 68:
        
        case 69:
        
        case 70:
        
        case 71:
        
        case 72:
        
        case 73:
        
        case 74:
        
        case 75:
        
        case 76:
        
        case 77:
        
        case 78:
        
        case 79:
        
        case 80:
        
        case 81:
        
        case 82:
        
        case 83:
        
        case 84:
        
        case 85:
        
        case 86:
        
        case 87:
        
        case 88:
        
        case 89:
        
        case 90:
        
        case 91:
        
        case 92:
        
        case 93:
        
        case 94:
        
        case 95:
        
        case 96:
        
        case 97:
        
        case 98:
        
        case 99:
        
        case 100:
        
        case 101:
        
        case 102:
        
        case 103:
        
        case 104:
        
        case 105:
        
        case 106:
        
        case 107:
        
        case 108:
        
        case 109:
        
        case 110:
        
        case 111:
        
        case 112:
        
        case 113:
        
        case 114:
        
        case 115:
        
        case 116:
        
        case 117:
        
        case 118:
        
        case 119:
        
        case 120:
        
        case 121:
        
        case 122:
        
        case 123:
        
        case 124:
        
        case 125:
        
        case 126:
        
        case 127:
        
        case 128:
        
        case 129:
        
        case 130:
        
        case 131:
        
        case 132:
        
        case 133:
        
        case 134:
        
        case 135:
        
        case 136:
        
        case 137:
        
        case 138:
        
        case 139:
        
        case 140:
        
        case 141:
        
        case 142:
        
        case 143:
        
        case 144:
        
        case 145:
        
        case 146:
        
        case 147:
        
        case 148:
        
        case 149:
        
        case 150:
        
        case 151:
        
        case 152:
        
        case 153:
        
        case 154:
        
        case 155:
        
        case 156:
        
        case 157:
        
        case 158:
        
        case 159:
        
        case 160:
        
        case 161:
        
        case 162:
        
        case 163:
        
        case 164:
        
        case 165:
        
        case 166:
        
        case 167:
        
        case 168:
        
        case 169:
        
        case 170:
        
        case 171:
        
        case 172:
        
        case 173:
        
        case 174:
        
        case 175:
        
        case 176:
        
        case 177:
        
        case 178:
        
        case 179:
        
        case 180:
        
        case 181:
        
        case 182:
        
        case 183:
        
        case 184:
        
        case 185:
        
        case 186:
        
        case 187:
        
        case 188:
        
        case 189:
        
        case 190:
        
        case 191:
        
        case 192:
        
        case 193:
        
        case 194:
        
        case 195:
        
        case 196:
        
        case 197:
        
        case 198:
        
        case 199:
        
        case 200:
        
        case 201:
        
        case 202:
        
        case 203:
        
        case 204:
        
        case 205:
        
        case 206:
        
        case 207:
        
        case 208:
        
        case 209:
        
        case 210:
        
        case 211:
        
        case 212:
        
        case 213:
        
        case 214:
        
        case 215:
        
        case 216:
        
        case 217:
        
        case 218:
        
        case 219:
        
        case 220:
        
        case 221:
        
        case 222:
        
        case 223:
        
        case 224:
        
        case 225:
        
        case 226:
        
        case 227:
        
        case 228:
        
        case 229:
        
        case 230:
        
        case 231:
        
        case 232:
        
        case 233:
        
        case 234:
        
        case 235:
        
        case 236:
        
        case 237:
        
        case 238:
        
        case 239:
        
        case 240:
        
        case 241:
        
        case 242:
        
        case 243:
        
        case 244:
        
        case 245:
        
        case 246:
        
        case 247:
        
        case 248:
        
        case 249:
        
        case 250:
        
        case 251:
        
        case 252:
        
        case 253:
        
        case 254:
        
        default:
          break;
      } 
      char c = '';
      int j = (paramInt2 & 0xFF) - c;
      if (j < 0)
        j += 256; 
      int k = ((paramInt2 & 0xFFFF) >>> 8) - c;
      if (k < 0)
        k += 256; 
      for (byte b = 0; b < arrayOfChar.length; b++) {
        int m = b % 2;
        if (m == 0) {
          arrayOfChar[b] = (char)(arrayOfChar[b] ^ j);
          j = ((j >>> 3 | j << 5) ^ arrayOfChar[b]) & 0xFF;
        } else {
          arrayOfChar[b] = (char)(arrayOfChar[b] ^ k);
          k = ((k >>> 3 | k << 5) ^ arrayOfChar[b]) & 0xFF;
        } 
      } 
      b[i] = (new String(arrayOfChar)).intern();
    } 
    return b[i];
  }
}


/* Location:              C:\Program Files\BurpSuitePro\burpsuite_pro.jar!\burp\Zb9m.class
 * Java compiler version: 21 (65.0)
 * JD-Core Version:       1.1.3
 */