package burp;

import java.awt.Component;
import java.awt.GridBagConstraints;
import java.awt.GridBagLayout;
import java.awt.Insets;
import java.awt.event.ActionEvent;
import java.util.Collection;
import java.util.Locale;
import java.util.Set;
import javax.swing.ButtonGroup;

public class Zbee extends Zbv5 implements Zt3u {
  private final Zr1m ZU;
  
  private final Zlc Zv;
  
  private final Collection<String> Zj;
  
  private Zm99 ZO;
  
  private Zm99 Zi;
  
  private Zmg2 ZW;
  
  private Zmg2 ZT;
  
  private ButtonGroup ZK;
  
  private static final String[] a;
  
  private static final String[] b;
  
  public Zbee(Zr1m paramZr1m, Zlc paramZlc) {
    this.ZU = paramZr1m;
    this.Zv = paramZlc;
    this.Zj = Set.of(Zjd(), a(-30688, 28139), a(-30682, 19806));
    String[] arrayOfString = Zbeb.Z_();
    Zf();
    this.Zi.setIcon((new Ze3m(Zeuf.HORIZONTAL_WRAPPED_VIEW, Zlkk.FOREGROUND)).ZU(Zmcx.LINE_SIZE).Z_());
    this.ZO.setIcon((new Ze3m(Zeuf.HORIZONTAL_SCROLLING_VIEW, Zlkk.FOREGROUND)).ZU(Zmcx.LINE_SIZE).Z_());
    setName(a(-30687, 4711));
    if (arrayOfString == null)
      Zbqc.Zr(new Zbqc[1]); 
  }
  
  public String Zjd() {
    return a(-30681, -6134);
  }
  
  public String ZjS() {
    return a(-30685, 12239);
  }
  
  public Component ZjY() {
    Zbkr zbkr = new Zbkr();
    zbkr.ZP(Zjd().toLowerCase(Locale.ENGLISH), Zk97.DESKTOP_SETTINGS_TOOLS_REPEATER_TAB_VIEW, this.ZU, new String[] { a(-30686, -30605) });
    return zbkr;
  }
  
  public Collection<String> ZjD() {
    return this.Zj;
  }
  
  public void Zt2() {
    // Byte code:
    //   0: invokestatic Z_ : ()[Ljava/lang/String;
    //   3: astore_1
    //   4: getstatic burp/Zeq9.Z_ : [I
    //   7: aload_0
    //   8: getfield Zv : Lburp/Zlc;
    //   11: invokeinterface Zxi : ()Lburp/Ztal;
    //   16: invokevirtual ordinal : ()I
    //   19: iaload
    //   20: lookupswitch default -> 68, 1 -> 48, 2 -> 60
    //   48: aload_0
    //   49: getfield ZT : Lburp/Zmg2;
    //   52: iconst_1
    //   53: invokevirtual setSelected : (Z)V
    //   56: aload_1
    //   57: ifnonnull -> 68
    //   60: aload_0
    //   61: getfield ZW : Lburp/Zmg2;
    //   64: iconst_1
    //   65: invokevirtual setSelected : (Z)V
    //   68: return
  }
  
  private void Zf() {
    this.ZK = new ButtonGroup();
    this.ZW = new Zmg2();
    this.ZO = new Zm99();
    this.ZT = new Zmg2();
    this.Zi = new Zm99();
    GridBagLayout gridBagLayout = new GridBagLayout();
    gridBagLayout.columnWidths = new int[] { 0, 5, 0 };
    gridBagLayout.rowHeights = new int[] { 0, 5, 0 };
    setLayout(gridBagLayout);
    this.ZK.add(this.ZW);
    this.ZW.setText(a(-30683, 5709));
    this.ZW.addActionListener(new Zea3(this));
    GridBagConstraints gridBagConstraints = new GridBagConstraints();
    gridBagConstraints.gridx = 0;
    gridBagConstraints.gridy = 0;
    gridBagConstraints.anchor = 21;
    add(this.ZW, gridBagConstraints);
    gridBagConstraints = new GridBagConstraints();
    gridBagConstraints.gridx = 2;
    gridBagConstraints.gridy = 0;
    gridBagConstraints.anchor = 21;
    gridBagConstraints.insets = new Insets(0, 10, 0, 0);
    add(this.ZO, gridBagConstraints);
    this.ZK.add(this.ZT);
    this.ZT.setText(a(-30684, 16241));
    this.ZT.addActionListener(new Zmoz(this));
    gridBagConstraints = new GridBagConstraints();
    gridBagConstraints.gridx = 0;
    gridBagConstraints.gridy = 2;
    gridBagConstraints.anchor = 21;
    add(this.ZT, gridBagConstraints);
    gridBagConstraints = new GridBagConstraints();
    gridBagConstraints.gridx = 2;
    gridBagConstraints.gridy = 2;
    gridBagConstraints.anchor = 21;
    gridBagConstraints.weightx = 1.0D;
    gridBagConstraints.insets = new Insets(0, 10, 0, 0);
    add(this.Zi, gridBagConstraints);
  }
  
  private void ZF(ActionEvent paramActionEvent) {
    this.Zv.ZW(Ztal.WRAPPED);
  }
  
  private void Zj(ActionEvent paramActionEvent) {
    this.Zv.ZW(Ztal.SCROLLING);
  }
  
  static {
    // Byte code:
    //   0: bipush #8
    //   2: anewarray java/lang/String
    //   5: astore #5
    //   7: iconst_0
    //   8: istore_3
    //   9: ldc '5YVWRÃ€Âƒ/zÂ„Â Â“\\fÂ·Â‚ÂžÃ«Ã‚TrÃ®:$mÂ›\\bÃŸÂŽÃ³K\\nÂ¬|\\tÃ€ÂƒÃƒÃ§ 8ÃŽ;"Â²WÂ°2Ã…Â˜$+3Ã“>[2bÂ™Ã¨ÂœpÂ¢Ã¿Â§Ã±Ã«ÃŸÂ·{Ã§FÃ–'
    //   11: dup
    //   12: astore_2
    //   13: invokevirtual length : ()I
    //   16: istore #4
    //   18: bipush #14
    //   20: istore_1
    //   21: iconst_m1
    //   22: istore_0
    //   23: bipush #44
    //   25: iinc #0, 1
    //   28: aload_2
    //   29: iload_0
    //   30: dup
    //   31: iload_1
    //   32: iadd
    //   33: invokevirtual substring : (II)Ljava/lang/String;
    //   36: iconst_m1
    //   37: goto -> 143
    //   40: aload #5
    //   42: swap
    //   43: iload_3
    //   44: iinc #3, 1
    //   47: swap
    //   48: aastore
    //   49: iload_0
    //   50: iload_1
    //   51: iadd
    //   52: dup
    //   53: istore_0
    //   54: iload #4
    //   56: if_icmpge -> 68
    //   59: aload_2
    //   60: iload_0
    //   61: invokevirtual charAt : (I)C
    //   64: istore_1
    //   65: goto -> 23
    //   68: ldc '40Â¢Ã†ÃÂ¬PÂŽPmE(Ã£Ã¿~Â’-Â‰iÂ°e:/{Ã·ÃƒÃŸÃ€paÂºhÃ¿_]|Â´pÃ°ÃµmÃ•`Ã¬kÃÃ»!"Â²1Â—$w.Ã®WmÂSAÂdÂ·9Â£.Ã˜Ã—Ã¹a/ÂžÂ…{Â„\\nÂ¤5{}ÂAÂ›Â–iÃ‹\'
    //   70: dup
    //   71: astore_2
    //   72: invokevirtual length : ()I
    //   75: istore #4
    //   77: bipush #61
    //   79: istore_1
    //   80: iconst_m1
    //   81: istore_0
    //   82: bipush #110
    //   84: iinc #0, 1
    //   87: aload_2
    //   88: iload_0
    //   89: dup
    //   90: iload_1
    //   91: iadd
    //   92: invokevirtual substring : (II)Ljava/lang/String;
    //   95: iconst_0
    //   96: goto -> 143
    //   99: aload #5
    //   101: swap
    //   102: iload_3
    //   103: iinc #3, 1
    //   106: swap
    //   107: aastore
    //   108: iload_0
    //   109: iload_1
    //   110: iadd
    //   111: dup
    //   112: istore_0
    //   113: iload #4
    //   115: if_icmpge -> 127
    //   118: aload_2
    //   119: iload_0
    //   120: invokevirtual charAt : (I)C
    //   123: istore_1
    //   124: goto -> 82
    //   127: aload #5
    //   129: putstatic burp/Zbee.a : [Ljava/lang/String;
    //   132: bipush #8
    //   134: anewarray java/lang/String
    //   137: putstatic burp/Zbee.b : [Ljava/lang/String;
    //   140: goto -> 300
    //   143: dup_x2
    //   144: pop
    //   145: invokevirtual toCharArray : ()[C
    //   148: dup_x1
    //   149: arraylength
    //   150: dup_x2
    //   151: pop
    //   152: iconst_0
    //   153: istore #6
    //   155: dup2_x1
    //   156: pop2
    //   157: dup_x2
    //   158: iconst_1
    //   159: if_icmpgt -> 260
    //   162: dup2
    //   163: swap
    //   164: iload #6
    //   166: dup2_x1
    //   167: caload
    //   168: swap
    //   169: iload #6
    //   171: bipush #7
    //   173: irem
    //   174: tableswitch default -> 242, 0 -> 212, 1 -> 217, 2 -> 222, 3 -> 227, 4 -> 232, 5 -> 237
    //   212: bipush #10
    //   214: goto -> 244
    //   217: bipush #72
    //   219: goto -> 244
    //   222: bipush #92
    //   224: goto -> 244
    //   227: bipush #87
    //   229: goto -> 244
    //   232: bipush #14
    //   234: goto -> 244
    //   237: bipush #113
    //   239: goto -> 244
    //   242: bipush #88
    //   244: ixor
    //   245: ixor
    //   246: i2c
    //   247: castore
    //   248: iinc #6, 1
    //   251: dup
    //   252: ifne -> 260
    //   255: dup2
    //   256: dup_x1
    //   257: goto -> 166
    //   260: dup2_x1
    //   261: pop2
    //   262: dup_x2
    //   263: iload #6
    //   265: if_icmpgt -> 162
    //   268: pop
    //   269: new java/lang/String
    //   272: dup_x1
    //   273: swap
    //   274: invokespecial <init> : ([C)V
    //   277: invokevirtual intern : ()Ljava/lang/String;
    //   280: swap
    //   281: pop
    //   282: swap
    //   283: tableswitch default -> 40, 0 -> 99
    //   300: return
  }
  
  private static String a(int paramInt1, int paramInt2) {
    int i = (paramInt1 ^ 0xFFFF8825) & 0xFFFF;
    if (b[i] == null) {
      char[] arrayOfChar = a[i].toCharArray();
      switch (arrayOfChar[0] & 0xFF) {
        case 0:
        
        case 1:
        
        case 2:
        
        case 3:
        
        case 4:
        
        case 5:
        
        case 6:
        
        case 7:
        
        case 8:
        
        case 9:
        
        case 10:
        
        case 11:
        
        case 12:
        
        case 13:
        
        case 14:
        
        case 15:
        
        case 16:
        
        case 17:
        
        case 18:
        
        case 19:
        
        case 20:
        
        case 21:
        
        case 22:
        
        case 23:
        
        case 24:
        
        case 25:
        
        case 26:
        
        case 27:
        
        case 28:
        
        case 29:
        
        case 30:
        
        case 31:
        
        case 32:
        
        case 33:
        
        case 34:
        
        case 35:
        
        case 36:
        
        case 37:
        
        case 38:
        
        case 39:
        
        case 40:
        
        case 41:
        
        case 42:
        
        case 43:
        
        case 44:
        
        case 45:
        
        case 46:
        
        case 47:
        
        case 48:
        
        case 49:
        
        case 50:
        
        case 51:
        
        case 52:
        
        case 53:
        
        case 54:
        
        case 55:
        
        case 56:
        
        case 57:
        
        case 58:
        
        case 59:
        
        case 60:
        
        case 61:
        
        case 62:
        
        case 63:
        
        case 64:
        
        case 65:
        
        case 66:
        
        case 67:
        
        case 68:
        
        case 69:
        
        case 70:
        
        case 71:
        
        case 72:
        
        case 73:
        
        case 74:
        
        case 75:
        
        case 76:
        
        case 77:
        
        case 78:
        
        case 79:
        
        case 80:
        
        case 81:
        
        case 82:
        
        case 83:
        
        case 84:
        
        case 85:
        
        case 86:
        
        case 87:
        
        case 88:
        
        case 89:
        
        case 90:
        
        case 91:
        
        case 92:
        
        case 93:
        
        case 94:
        
        case 95:
        
        case 96:
        
        case 97:
        
        case 98:
        
        case 99:
        
        case 100:
        
        case 101:
        
        case 102:
        
        case 103:
        
        case 104:
        
        case 105:
        
        case 106:
        
        case 107:
        
        case 108:
        
        case 109:
        
        case 110:
        
        case 111:
        
        case 112:
        
        case 113:
        
        case 114:
        
        case 115:
        
        case 116:
        
        case 117:
        
        case 118:
        
        case 119:
        
        case 120:
        
        case 121:
        
        case 122:
        
        case 123:
        
        case 124:
        
        case 125:
        
        case 126:
        
        case 127:
        
        case 128:
        
        case 129:
        
        case 130:
        
        case 131:
        
        case 132:
        
        case 133:
        
        case 134:
        
        case 135:
        
        case 136:
        
        case 137:
        
        case 138:
        
        case 139:
        
        case 140:
        
        case 141:
        
        case 142:
        
        case 143:
        
        case 144:
        
        case 145:
        
        case 146:
        
        case 147:
        
        case 148:
        
        case 149:
        
        case 150:
        
        case 151:
        
        case 152:
        
        case 153:
        
        case 154:
        
        case 155:
        
        case 156:
        
        case 157:
        
        case 158:
        
        case 159:
        
        case 160:
        
        case 161:
        
        case 162:
        
        case 163:
        
        case 164:
        
        case 165:
        
        case 166:
        
        case 167:
        
        case 168:
        
        case 169:
        
        case 170:
        
        case 171:
        
        case 172:
        
        case 173:
        
        case 174:
        
        case 175:
        
        case 176:
        
        case 177:
        
        case 178:
        
        case 179:
        
        case 180:
        
        case 181:
        
        case 182:
        
        case 183:
        
        case 184:
        
        case 185:
        
        case 186:
        
        case 187:
        
        case 188:
        
        case 189:
        
        case 190:
        
        case 191:
        
        case 192:
        
        case 193:
        
        case 194:
        
        case 195:
        
        case 196:
        
        case 197:
        
        case 198:
        
        case 199:
        
        case 200:
        
        case 201:
        
        case 202:
        
        case 203:
        
        case 204:
        
        case 205:
        
        case 206:
        
        case 207:
        
        case 208:
        
        case 209:
        
        case 210:
        
        case 211:
        
        case 212:
        
        case 213:
        
        case 214:
        
        case 215:
        
        case 216:
        
        case 217:
        
        case 218:
        
        case 219:
        
        case 220:
        
        case 221:
        
        case 222:
        
        case 223:
        
        case 224:
        
        case 225:
        
        case 226:
        
        case 227:
        
        case 228:
        
        case 229:
        
        case 230:
        
        case 231:
        
        case 232:
        
        case 233:
        
        case 234:
        
        case 235:
        
        case 236:
        
        case 237:
        
        case 238:
        
        case 239:
        
        case 240:
        
        case 241:
        
        case 242:
        
        case 243:
        
        case 244:
        
        case 245:
        
        case 246:
        
        case 247:
        
        case 248:
        
        case 249:
        
        case 250:
        
        case 251:
        
        case 252:
        
        case 253:
        
        case 254:
        
        default:
          break;
      } 
      char c = 'Ã¢';
      int j = (paramInt2 & 0xFF) - c;
      if (j < 0)
        j += 256; 
      int k = ((paramInt2 & 0xFFFF) >>> 8) - c;
      if (k < 0)
        k += 256; 
      for (byte b = 0; b < arrayOfChar.length; b++) {
        int m = b % 2;
        if (m == 0) {
          arrayOfChar[b] = (char)(arrayOfChar[b] ^ j);
          j = ((j >>> 3 | j << 5) ^ arrayOfChar[b]) & 0xFF;
        } else {
          arrayOfChar[b] = (char)(arrayOfChar[b] ^ k);
          k = ((k >>> 3 | k << 5) ^ arrayOfChar[b]) & 0xFF;
        } 
      } 
      b[i] = (new String(arrayOfChar)).intern();
    } 
    return b[i];
  }
}


/* Location:              C:\Program Files\BurpSuitePro\burpsuite_pro.jar!\burp\Zbee.class
 * Java compiler version: 21 (65.0)
 * JD-Core Version:       1.1.3
 */