package burp;

import java.awt.GridBagConstraints;
import java.awt.GridBagLayout;
import java.awt.Insets;
import java.awt.event.ActionEvent;
import java.io.File;
import net.portswigger.Zah;
import net.portswigger.Zk_;

class Zbga extends Zbg2 {
  private final Zt4u ZM;
  
  private final Zr5w Zv;
  
  private Zm2o ZQ;
  
  private Zm99 Zr;
  
  private Zm99 ZS;
  
  private Ze01 Zm;
  
  private Zm99 ZC;
  
  private Zl8w ZO;
  
  private Zm9v Zf;
  
  private Zm9v Zw;
  
  public Zg85 ZW;
  
  private Ztln Za;
  
  private static final String[] a;
  
  private static final String[] b;
  
  Zbga(Zt4u paramZt4u, Zr5w paramZr5w) {
    this.ZM = paramZt4u;
    this.Zv = paramZr5w;
    Zo();
    this.Zf.setVisible(false);
    this.Zw.setVisible(false);
    this.ZB = new String[] { a(12243, -6244), a(12247, 29632) };
    this.ZA = new boolean[] { true, true };
    this.Zh = 1;
  }
  
  public Zsic Zn(int paramInt) {
    // Byte code:
    //   0: invokestatic ZV : ()Ljava/lang/String;
    //   3: astore_2
    //   4: iload_1
    //   5: lookupswitch default -> 106, 0 -> 32, 1 -> 41
    //   32: aload_0
    //   33: getfield Zv : Lburp/Zr5w;
    //   36: aload_0
    //   37: invokevirtual ZP : (Lburp/Zsic;)Lburp/Zsic;
    //   40: areturn
    //   41: aload_0
    //   42: getfield ZW : Lburp/Zg85;
    //   45: invokevirtual getText : ()Ljava/lang/String;
    //   48: aload_0
    //   49: getfield Zf : Lburp/Zm9v;
    //   52: invokestatic ZP : (Ljava/lang/String;Lburp/Zm9v;)Z
    //   55: istore_3
    //   56: aload_0
    //   57: getfield Za : Lburp/Ztln;
    //   60: invokevirtual getPassword : ()[C
    //   63: arraylength
    //   64: ifne -> 81
    //   67: aload_0
    //   68: getfield Zw : Lburp/Zm9v;
    //   71: iconst_1
    //   72: invokevirtual setVisible : (Z)V
    //   75: iconst_1
    //   76: istore_3
    //   77: aload_2
    //   78: ifnull -> 89
    //   81: aload_0
    //   82: getfield Zw : Lburp/Zm9v;
    //   85: iconst_0
    //   86: invokevirtual setVisible : (Z)V
    //   89: iload_3
    //   90: ifeq -> 97
    //   93: aload_0
    //   94: goto -> 105
    //   97: aload_0
    //   98: getfield Zv : Lburp/Zr5w;
    //   101: aload_0
    //   102: invokevirtual Zu : (Lburp/Zsic;)Lburp/Zsic;
    //   105: areturn
    //   106: iconst_0
    //   107: getstatic net/portswigger/Zqf.Zk : Lnet/portswigger/Zqf;
    //   110: iload_1
    //   111: i2l
    //   112: invokestatic Zv : (ZLnet/portswigger/Zqf;J)V
    //   115: aload_0
    //   116: areturn
  }
  
  private static boolean ZP(String paramString, Zm9v paramZm9v) {
    try {
      try {
        if (paramString.isEmpty())
          throw new Exception(); 
      } catch (Exception exception) {
        throw a(null);
      } 
      new File(paramString);
      paramZm9v.setVisible(false);
      return false;
    } catch (Exception exception) {
      Zah.Zl(exception, Zk_.USER_ERROR);
      paramZm9v.setVisible(true);
      return true;
    } 
  }
  
  String ZO() {
    return this.ZW.getText();
  }
  
  char[] Zw() {
    return this.Za.getPassword();
  }
  
  private void Zo() {
    this.ZW = new Zg85();
    this.Zr = new Zm99();
    this.ZO = new Zl8w();
    this.Zf = new Zm9v();
    this.Zw = new Zm9v();
    this.Za = new Ztln();
    this.Zm = new Ze01();
    this.ZQ = new Zm2o();
    this.ZS = new Zm99();
    this.ZC = new Zm99();
    GridBagLayout gridBagLayout = new GridBagLayout();
    gridBagLayout.columnWidths = new int[] { 0, 5, 0, 5, 0, 5, 0 };
    gridBagLayout.rowHeights = new int[] { 0, 5, 0, 5, 0, 5, 0, 5, 0 };
    setLayout(gridBagLayout);
    this.ZW.setEditable(false);
    this.ZW.setColumns(20);
    GridBagConstraints gridBagConstraints = new GridBagConstraints();
    gridBagConstraints.gridx = 4;
    gridBagConstraints.gridy = 2;
    gridBagConstraints.fill = 3;
    gridBagConstraints.anchor = 18;
    add(this.ZW, gridBagConstraints);
    this.Zr.setText(a(12241, 20931));
    gridBagConstraints = new GridBagConstraints();
    gridBagConstraints.gridx = 2;
    gridBagConstraints.gridy = 6;
    gridBagConstraints.anchor = 1280;
    add(this.Zr, gridBagConstraints);
    this.ZO.setText(a(12240, 25533));
    gridBagConstraints = new GridBagConstraints();
    gridBagConstraints.gridx = 2;
    gridBagConstraints.gridy = 0;
    gridBagConstraints.gridwidth = 5;
    gridBagConstraints.fill = 2;
    gridBagConstraints.anchor = 23;
    gridBagConstraints.weightx = 1.0D;
    add(this.ZO, gridBagConstraints);
    this.Zf.setText(a(12242, -21920));
    gridBagConstraints = new GridBagConstraints();
    gridBagConstraints.gridx = 4;
    gridBagConstraints.gridy = 4;
    gridBagConstraints.anchor = 18;
    add(this.Zf, gridBagConstraints);
    this.Zw.setText(a(12245, 478));
    gridBagConstraints = new GridBagConstraints();
    gridBagConstraints.gridx = 4;
    gridBagConstraints.gridy = 8;
    gridBagConstraints.anchor = 18;
    add(this.Zw, gridBagConstraints);
    this.Za.setColumns(15);
    gridBagConstraints = new GridBagConstraints();
    gridBagConstraints.gridx = 4;
    gridBagConstraints.gridy = 6;
    gridBagConstraints.fill = 1;
    gridBagConstraints.anchor = 1280;
    add(this.Za, gridBagConstraints);
    this.Zm.setText(a(12244, -32159));
    this.Zm.addActionListener(new Zzv0(this));
    gridBagConstraints = new GridBagConstraints();
    gridBagConstraints.gridx = 6;
    gridBagConstraints.gridy = 2;
    gridBagConstraints.anchor = 18;
    add(this.Zm, gridBagConstraints);
    this.ZQ.Zi(Zk97.DESKTOP_SETTINGS_NETWORK_TLS_CLIENT_TLS_CERTIFICATES);
    gridBagConstraints = new GridBagConstraints();
    gridBagConstraints.gridx = 0;
    gridBagConstraints.gridy = 0;
    gridBagConstraints.anchor = 23;
    gridBagConstraints.insets = new Insets(0, 0, 0, 5);
    add(this.ZQ, gridBagConstraints);
    this.ZS.setText(a(12246, 14629));
    gridBagConstraints = new GridBagConstraints();
    gridBagConstraints.gridx = 2;
    gridBagConstraints.gridy = 2;
    gridBagConstraints.anchor = 1280;
    add(this.ZS, gridBagConstraints);
    gridBagConstraints = new GridBagConstraints();
    gridBagConstraints.gridx = 2;
    gridBagConstraints.gridy = 8;
    gridBagConstraints.anchor = 23;
    gridBagConstraints.weighty = 1.0D;
    add(this.ZC, gridBagConstraints);
  }
  
  private void ZQ(ActionEvent paramActionEvent) {
    File file = Zs6n.Zp(Zg1m.CONFIG, this.ZM, this, 0, a(12254, -15278));
    if (file != null) {
      this.ZW.setText(file.getPath());
      this.Zf.setVisible(false);
    } 
  }
  
  private static Exception a(Exception paramException) {
    return paramException;
  }
  
  static {
    // Byte code:
    //   0: bipush #9
    //   2: anewarray java/lang/String
    //   5: astore #5
    //   7: iconst_0
    //   8: istore_3
    //   9: ldc 'Â¢ÂµÃŒ=Â·Ã»Ã¸Â­-Â»@fÃžÃºÃ/Â”Ã›bÃ¶Ã˜DÃ¢ÃµP9P Â¾Â„Ã¾N#2ÂŒNÂ€{Ã˜Â’c]ÃƒÃ‰.Â’2Ã!$Â¢Â—Â·q=5|Â‰Â¨Ã§Â’pÂ¢TÃ¾OwÃ¹`Ã©Ã¬Â©ÃŒÂÂ•&Ã©ÂšNÂ‡DÂ²t=Ã³Â½HVÂÃ¾Ãœ$ÃƒÃ‡Â©Â¨$Ã­Â“H(ÃŒÂÃ•Ã§Ã˜ÂšÂ±Ã‡ÂœÂ®ÂšÃ“3EqwÂdÂ¹Â­\\t>ÂœÂYÂ¢p\\n}Âƒ*^`Â¶Â¿jÂ½Ã Ã§Ã“ÂŸÃ„ÃŸÃ¾JÂ‰ÃµÂºÂÂ³Â±ÃŒ(6'
    //   11: dup
    //   12: astore_2
    //   13: invokevirtual length : ()I
    //   16: istore #4
    //   18: bipush #17
    //   20: istore_1
    //   21: iconst_m1
    //   22: istore_0
    //   23: bipush #81
    //   25: iinc #0, 1
    //   28: aload_2
    //   29: iload_0
    //   30: dup
    //   31: iload_1
    //   32: iadd
    //   33: invokevirtual substring : (II)Ljava/lang/String;
    //   36: iconst_m1
    //   37: goto -> 143
    //   40: aload #5
    //   42: swap
    //   43: iload_3
    //   44: iinc #3, 1
    //   47: swap
    //   48: aastore
    //   49: iload_0
    //   50: iload_1
    //   51: iadd
    //   52: dup
    //   53: istore_0
    //   54: iload #4
    //   56: if_icmpge -> 68
    //   59: aload_2
    //   60: iload_0
    //   61: invokevirtual charAt : (I)C
    //   64: istore_1
    //   65: goto -> 23
    //   68: ldc 'Ã¶eÃ™Ã®ÃšFÃµÂŠeÂ±zYÂ–_ÂŸÂ³Ã®|Ã¬mÃ¥Ã­ÂÃ†fÂÂ'
    //   70: dup
    //   71: astore_2
    //   72: invokevirtual length : ()I
    //   75: istore #4
    //   77: bipush #9
    //   79: istore_1
    //   80: iconst_m1
    //   81: istore_0
    //   82: bipush #9
    //   84: iinc #0, 1
    //   87: aload_2
    //   88: iload_0
    //   89: dup
    //   90: iload_1
    //   91: iadd
    //   92: invokevirtual substring : (II)Ljava/lang/String;
    //   95: iconst_0
    //   96: goto -> 143
    //   99: aload #5
    //   101: swap
    //   102: iload_3
    //   103: iinc #3, 1
    //   106: swap
    //   107: aastore
    //   108: iload_0
    //   109: iload_1
    //   110: iadd
    //   111: dup
    //   112: istore_0
    //   113: iload #4
    //   115: if_icmpge -> 127
    //   118: aload_2
    //   119: iload_0
    //   120: invokevirtual charAt : (I)C
    //   123: istore_1
    //   124: goto -> 82
    //   127: aload #5
    //   129: putstatic burp/Zbga.a : [Ljava/lang/String;
    //   132: bipush #9
    //   134: anewarray java/lang/String
    //   137: putstatic burp/Zbga.b : [Ljava/lang/String;
    //   140: goto -> 300
    //   143: dup_x2
    //   144: pop
    //   145: invokevirtual toCharArray : ()[C
    //   148: dup_x1
    //   149: arraylength
    //   150: dup_x2
    //   151: pop
    //   152: iconst_0
    //   153: istore #6
    //   155: dup2_x1
    //   156: pop2
    //   157: dup_x2
    //   158: iconst_1
    //   159: if_icmpgt -> 259
    //   162: dup2
    //   163: swap
    //   164: iload #6
    //   166: dup2_x1
    //   167: caload
    //   168: swap
    //   169: iload #6
    //   171: bipush #7
    //   173: irem
    //   174: tableswitch default -> 241, 0 -> 212, 1 -> 217, 2 -> 222, 3 -> 227, 4 -> 231, 5 -> 236
    //   212: bipush #7
    //   214: goto -> 243
    //   217: bipush #74
    //   219: goto -> 243
    //   222: bipush #90
    //   224: goto -> 243
    //   227: iconst_4
    //   228: goto -> 243
    //   231: bipush #75
    //   233: goto -> 243
    //   236: bipush #59
    //   238: goto -> 243
    //   241: bipush #49
    //   243: ixor
    //   244: ixor
    //   245: i2c
    //   246: castore
    //   247: iinc #6, 1
    //   250: dup
    //   251: ifne -> 259
    //   254: dup2
    //   255: dup_x1
    //   256: goto -> 166
    //   259: dup2_x1
    //   260: pop2
    //   261: dup_x2
    //   262: iload #6
    //   264: if_icmpgt -> 162
    //   267: pop
    //   268: new java/lang/String
    //   271: dup_x1
    //   272: swap
    //   273: invokespecial <init> : ([C)V
    //   276: invokevirtual intern : ()Ljava/lang/String;
    //   279: swap
    //   280: pop
    //   281: swap
    //   282: tableswitch default -> 40, 0 -> 99
    //   300: return
  }
  
  private static String a(int paramInt1, int paramInt2) {
    int i = (paramInt1 ^ 0x2FD6) & 0xFFFF;
    if (b[i] == null) {
      char[] arrayOfChar = a[i].toCharArray();
      switch (arrayOfChar[0] & 0xFF) {
        case 0:
        
        case 1:
        
        case 2:
        
        case 3:
        
        case 4:
        
        case 5:
        
        case 6:
        
        case 7:
        
        case 8:
        
        case 9:
        
        case 10:
        
        case 11:
        
        case 12:
        
        case 13:
        
        case 14:
        
        case 15:
        
        case 16:
        
        case 17:
        
        case 18:
        
        case 19:
        
        case 20:
        
        case 21:
        
        case 22:
        
        case 23:
        
        case 24:
        
        case 25:
        
        case 26:
        
        case 27:
        
        case 28:
        
        case 29:
        
        case 30:
        
        case 31:
        
        case 32:
        
        case 33:
        
        case 34:
        
        case 35:
        
        case 36:
        
        case 37:
        
        case 38:
        
        case 39:
        
        case 40:
        
        case 41:
        
        case 42:
        
        case 43:
        
        case 44:
        
        case 45:
        
        case 46:
        
        case 47:
        
        case 48:
        
        case 49:
        
        case 50:
        
        case 51:
        
        case 52:
        
        case 53:
        
        case 54:
        
        case 55:
        
        case 56:
        
        case 57:
        
        case 58:
        
        case 59:
        
        case 60:
        
        case 61:
        
        case 62:
        
        case 63:
        
        case 64:
        
        case 65:
        
        case 66:
        
        case 67:
        
        case 68:
        
        case 69:
        
        case 70:
        
        case 71:
        
        case 72:
        
        case 73:
        
        case 74:
        
        case 75:
        
        case 76:
        
        case 77:
        
        case 78:
        
        case 79:
        
        case 80:
        
        case 81:
        
        case 82:
        
        case 83:
        
        case 84:
        
        case 85:
        
        case 86:
        
        case 87:
        
        case 88:
        
        case 89:
        
        case 90:
        
        case 91:
        
        case 92:
        
        case 93:
        
        case 94:
        
        case 95:
        
        case 96:
        
        case 97:
        
        case 98:
        
        case 99:
        
        case 100:
        
        case 101:
        
        case 102:
        
        case 103:
        
        case 104:
        
        case 105:
        
        case 106:
        
        case 107:
        
        case 108:
        
        case 109:
        
        case 110:
        
        case 111:
        
        case 112:
        
        case 113:
        
        case 114:
        
        case 115:
        
        case 116:
        
        case 117:
        
        case 118:
        
        case 119:
        
        case 120:
        
        case 121:
        
        case 122:
        
        case 123:
        
        case 124:
        
        case 125:
        
        case 126:
        
        case 127:
        
        case 128:
        
        case 129:
        
        case 130:
        
        case 131:
        
        case 132:
        
        case 133:
        
        case 134:
        
        case 135:
        
        case 136:
        
        case 137:
        
        case 138:
        
        case 139:
        
        case 140:
        
        case 141:
        
        case 142:
        
        case 143:
        
        case 144:
        
        case 145:
        
        case 146:
        
        case 147:
        
        case 148:
        
        case 149:
        
        case 150:
        
        case 151:
        
        case 152:
        
        case 153:
        
        case 154:
        
        case 155:
        
        case 156:
        
        case 157:
        
        case 158:
        
        case 159:
        
        case 160:
        
        case 161:
        
        case 162:
        
        case 163:
        
        case 164:
        
        case 165:
        
        case 166:
        
        case 167:
        
        case 168:
        
        case 169:
        
        case 170:
        
        case 171:
        
        case 172:
        
        case 173:
        
        case 174:
        
        case 175:
        
        case 176:
        
        case 177:
        
        case 178:
        
        case 179:
        
        case 180:
        
        case 181:
        
        case 182:
        
        case 183:
        
        case 184:
        
        case 185:
        
        case 186:
        
        case 187:
        
        case 188:
        
        case 189:
        
        case 190:
        
        case 191:
        
        case 192:
        
        case 193:
        
        case 194:
        
        case 195:
        
        case 196:
        
        case 197:
        
        case 198:
        
        case 199:
        
        case 200:
        
        case 201:
        
        case 202:
        
        case 203:
        
        case 204:
        
        case 205:
        
        case 206:
        
        case 207:
        
        case 208:
        
        case 209:
        
        case 210:
        
        case 211:
        
        case 212:
        
        case 213:
        
        case 214:
        
        case 215:
        
        case 216:
        
        case 217:
        
        case 218:
        
        case 219:
        
        case 220:
        
        case 221:
        
        case 222:
        
        case 223:
        
        case 224:
        
        case 225:
        
        case 226:
        
        case 227:
        
        case 228:
        
        case 229:
        
        case 230:
        
        case 231:
        
        case 232:
        
        case 233:
        
        case 234:
        
        case 235:
        
        case 236:
        
        case 237:
        
        case 238:
        
        case 239:
        
        case 240:
        
        case 241:
        
        case 242:
        
        case 243:
        
        case 244:
        
        case 245:
        
        case 246:
        
        case 247:
        
        case 248:
        
        case 249:
        
        case 250:
        
        case 251:
        
        case 252:
        
        case 253:
        
        case 254:
        
        default:
          break;
      } 
      byte b1 = 4;
      int j = (paramInt2 & 0xFF) - b1;
      if (j < 0)
        j += 256; 
      int k = ((paramInt2 & 0xFFFF) >>> 8) - b1;
      if (k < 0)
        k += 256; 
      for (byte b2 = 0; b2 < arrayOfChar.length; b2++) {
        int m = b2 % 2;
        if (m == 0) {
          arrayOfChar[b2] = (char)(arrayOfChar[b2] ^ j);
          j = ((j >>> 3 | j << 5) ^ arrayOfChar[b2]) & 0xFF;
        } else {
          arrayOfChar[b2] = (char)(arrayOfChar[b2] ^ k);
          k = ((k >>> 3 | k << 5) ^ arrayOfChar[b2]) & 0xFF;
        } 
      } 
      b[i] = (new String(arrayOfChar)).intern();
    } 
    return b[i];
  }
}


/* Location:              C:\Program Files\BurpSuitePro\burpsuite_pro.jar!\burp\Zbga.class
 * Java compiler version: 21 (65.0)
 * JD-Core Version:       1.1.3
 */