package burp;

import com.nimbusds.jose.JOSEException;
import com.nimbusds.jose.JWSAlgorithm;
import com.nimbusds.jose.JWSHeader;
import com.nimbusds.jose.Payload;
import com.nimbusds.jose.crypto.RSASSASigner;
import com.nimbusds.jose.jwk.JWK;
import com.nimbusds.jose.jwk.RSAKey;
import com.nimbusds.jose.util.Base64URL;
import java.nio.charset.StandardCharsets;
import net.portswigger.Zah;
import net.portswigger.Zd4;
import net.portswigger.Zi7;
import net.portswigger.Zk_;
import net.portswigger.Zrmq;
import net.portswigger.Zv3;
import net.portswigger.Zv4;

public class Zbj3 extends Zbjs {
  private static final String[] c;
  
  private static final String[] d;
  
  Zbj3(String paramString, Zi7 paramZi7, Payload paramPayload, Base64URL paramBase64URL) {
    super(paramString, paramZi7, paramPayload, paramBase64URL);
  }
  
  public void ZC(String paramString1, String paramString2) {
    this.Zk.ZN(paramString1, (Zd4)Zv3.ZN(paramString2));
    this.ZJ = Zv4.ZN(this.Zk.toString());
  }
  
  public String ZW(String paramString) {
    Zrmq zrmq = this.Zk.Zo(paramString);
    return zrmq.Zr() ? zrmq.ZN().ZW() : "";
  }
  
  public void ZV(String paramString1, String paramString2) {
    this.Zk.ZN(paramString1, (Zd4)Zv3.Zx(paramString2));
    this.ZJ = Zv4.ZN(this.Zk.toString());
  }
  
  public String Zx() {
    return this.Zi.toString();
  }
  
  public void Zw(String paramString) {
    this.Zi = new Payload(paramString);
  }
  
  public String Zg() {
    return this.ZY.toString();
  }
  
  public byte[] Zd() {
    return this.ZY.decode();
  }
  
  public void Zr(String paramString) {
    this.ZY = new Base64URL(paramString);
  }
  
  public boolean Zz() {
    return (this.ZY != null && !this.ZY.toString().isEmpty());
  }
  
  public void ZR(String paramString) {
    try {
      RSAKey rSAKey = JWK.parseFromPEMEncodedObjects(paramString).toRSAKey();
      String str = String.format(b(29212, 21806), new Object[] { Zv4.ZN(this.Zk.toString()), Zv4.ZN(this.Zi.toString()) });
      JWSHeader jWSHeader = new JWSHeader(new JWSAlgorithm(this.Zk.Zo(b(29210, 3686)).ZN().ZW()));
      this.ZY = (new RSASSASigner(rSAKey)).sign(jWSHeader, str.getBytes(StandardCharsets.UTF_8));
    } catch (JOSEException jOSEException) {
      Zah.Zl((Throwable)jOSEException, Zk_.UNEXPECTED);
    } 
  }
  
  public Zbj3 ZG() {
    return new Zbj3(this.ZJ, (Zi7)this.Zk.Z_(), new Payload(this.Zi.toString()), new Base64URL(this.ZY.toString()));
  }
  
  public String ZB() {
    return String.format(b(29211, 31833), new Object[] { this.ZJ, Zv4.ZN(this.Zi.toString()) });
  }
  
  public String ZP() {
    return String.format(b(29209, 14547), new Object[] { this.ZJ, Zv4.ZN(this.Zi.toString()), this.ZY });
  }
  
  public String toString() {
    return String.format(b(29208, -11893), new Object[] { this.Zk.toString(), this.Zi.toString(), this.ZY });
  }
  
  static {
    // Byte code:
    //   0: iconst_5
    //   1: anewarray java/lang/String
    //   4: astore #5
    //   6: iconst_0
    //   7: istore_3
    //   8: ldc 'ê&À´.7?\\b=L×\\rB²¬Y'
    //   10: dup
    //   11: astore_2
    //   12: invokevirtual length : ()I
    //   15: istore #4
    //   17: bipush #8
    //   19: istore_1
    //   20: iconst_m1
    //   21: istore_0
    //   22: bipush #98
    //   24: iinc #0, 1
    //   27: aload_2
    //   28: iload_0
    //   29: dup
    //   30: iload_1
    //   31: iadd
    //   32: invokevirtual substring : (II)Ljava/lang/String;
    //   35: iconst_m1
    //   36: goto -> 140
    //   39: aload #5
    //   41: swap
    //   42: iload_3
    //   43: iinc #3, 1
    //   46: swap
    //   47: aastore
    //   48: iload_0
    //   49: iload_1
    //   50: iadd
    //   51: dup
    //   52: istore_0
    //   53: iload #4
    //   55: if_icmpge -> 67
    //   58: aload_2
    //   59: iload_0
    //   60: invokevirtual charAt : (I)C
    //   63: istore_1
    //   64: goto -> 22
    //   67: ldc 'üÜD×*T='
    //   69: dup
    //   70: astore_2
    //   71: invokevirtual length : ()I
    //   74: istore #4
    //   76: iconst_5
    //   77: istore_1
    //   78: iconst_m1
    //   79: istore_0
    //   80: bipush #115
    //   82: iinc #0, 1
    //   85: aload_2
    //   86: iload_0
    //   87: dup
    //   88: iload_1
    //   89: iadd
    //   90: invokevirtual substring : (II)Ljava/lang/String;
    //   93: iconst_0
    //   94: goto -> 140
    //   97: aload #5
    //   99: swap
    //   100: iload_3
    //   101: iinc #3, 1
    //   104: swap
    //   105: aastore
    //   106: iload_0
    //   107: iload_1
    //   108: iadd
    //   109: dup
    //   110: istore_0
    //   111: iload #4
    //   113: if_icmpge -> 125
    //   116: aload_2
    //   117: iload_0
    //   118: invokevirtual charAt : (I)C
    //   121: istore_1
    //   122: goto -> 80
    //   125: aload #5
    //   127: putstatic burp/Zbj3.c : [Ljava/lang/String;
    //   130: iconst_5
    //   131: anewarray java/lang/String
    //   134: putstatic burp/Zbj3.d : [Ljava/lang/String;
    //   137: goto -> 296
    //   140: dup_x2
    //   141: pop
    //   142: invokevirtual toCharArray : ()[C
    //   145: dup_x1
    //   146: arraylength
    //   147: dup_x2
    //   148: pop
    //   149: iconst_0
    //   150: istore #6
    //   152: dup2_x1
    //   153: pop2
    //   154: dup_x2
    //   155: iconst_1
    //   156: if_icmpgt -> 255
    //   159: dup2
    //   160: swap
    //   161: iload #6
    //   163: dup2_x1
    //   164: caload
    //   165: swap
    //   166: iload #6
    //   168: bipush #7
    //   170: irem
    //   171: tableswitch default -> 237, 0 -> 208, 1 -> 213, 2 -> 218, 3 -> 223, 4 -> 227, 5 -> 232
    //   208: bipush #99
    //   210: goto -> 239
    //   213: bipush #35
    //   215: goto -> 239
    //   218: bipush #112
    //   220: goto -> 239
    //   223: iconst_2
    //   224: goto -> 239
    //   227: bipush #60
    //   229: goto -> 239
    //   232: bipush #121
    //   234: goto -> 239
    //   237: bipush #53
    //   239: ixor
    //   240: ixor
    //   241: i2c
    //   242: castore
    //   243: iinc #6, 1
    //   246: dup
    //   247: ifne -> 255
    //   250: dup2
    //   251: dup_x1
    //   252: goto -> 163
    //   255: dup2_x1
    //   256: pop2
    //   257: dup_x2
    //   258: iload #6
    //   260: if_icmpgt -> 159
    //   263: pop
    //   264: new java/lang/String
    //   267: dup_x1
    //   268: swap
    //   269: invokespecial <init> : ([C)V
    //   272: invokevirtual intern : ()Ljava/lang/String;
    //   275: swap
    //   276: pop
    //   277: swap
    //   278: tableswitch default -> 39, 0 -> 97
    //   296: return
  }
  
  private static String b(int paramInt1, int paramInt2) {
    int i = (paramInt1 ^ 0x7218) & 0xFFFF;
    if (d[i] == null) {
      char[] arrayOfChar = c[i].toCharArray();
      switch (arrayOfChar[0] & 0xFF) {
        case 0:
        
        case 1:
        
        case 2:
        
        case 3:
        
        case 4:
        
        case 5:
        
        case 6:
        
        case 7:
        
        case 8:
        
        case 9:
        
        case 10:
        
        case 11:
        
        case 12:
        
        case 13:
        
        case 14:
        
        case 15:
        
        case 16:
        
        case 17:
        
        case 18:
        
        case 19:
        
        case 20:
        
        case 21:
        
        case 22:
        
        case 23:
        
        case 24:
        
        case 25:
        
        case 26:
        
        case 27:
        
        case 28:
        
        case 29:
        
        case 30:
        
        case 31:
        
        case 32:
        
        case 33:
        
        case 34:
        
        case 35:
        
        case 36:
        
        case 37:
        
        case 38:
        
        case 39:
        
        case 40:
        
        case 41:
        
        case 42:
        
        case 43:
        
        case 44:
        
        case 45:
        
        case 46:
        
        case 47:
        
        case 48:
        
        case 49:
        
        case 50:
        
        case 51:
        
        case 52:
        
        case 53:
        
        case 54:
        
        case 55:
        
        case 56:
        
        case 57:
        
        case 58:
        
        case 59:
        
        case 60:
        
        case 61:
        
        case 62:
        
        case 63:
        
        case 64:
        
        case 65:
        
        case 66:
        
        case 67:
        
        case 68:
        
        case 69:
        
        case 70:
        
        case 71:
        
        case 72:
        
        case 73:
        
        case 74:
        
        case 75:
        
        case 76:
        
        case 77:
        
        case 78:
        
        case 79:
        
        case 80:
        
        case 81:
        
        case 82:
        
        case 83:
        
        case 84:
        
        case 85:
        
        case 86:
        
        case 87:
        
        case 88:
        
        case 89:
        
        case 90:
        
        case 91:
        
        case 92:
        
        case 93:
        
        case 94:
        
        case 95:
        
        case 96:
        
        case 97:
        
        case 98:
        
        case 99:
        
        case 100:
        
        case 101:
        
        case 102:
        
        case 103:
        
        case 104:
        
        case 105:
        
        case 106:
        
        case 107:
        
        case 108:
        
        case 109:
        
        case 110:
        
        case 111:
        
        case 112:
        
        case 113:
        
        case 114:
        
        case 115:
        
        case 116:
        
        case 117:
        
        case 118:
        
        case 119:
        
        case 120:
        
        case 121:
        
        case 122:
        
        case 123:
        
        case 124:
        
        case 125:
        
        case 126:
        
        case 127:
        
        case 128:
        
        case 129:
        
        case 130:
        
        case 131:
        
        case 132:
        
        case 133:
        
        case 134:
        
        case 135:
        
        case 136:
        
        case 137:
        
        case 138:
        
        case 139:
        
        case 140:
        
        case 141:
        
        case 142:
        
        case 143:
        
        case 144:
        
        case 145:
        
        case 146:
        
        case 147:
        
        case 148:
        
        case 149:
        
        case 150:
        
        case 151:
        
        case 152:
        
        case 153:
        
        case 154:
        
        case 155:
        
        case 156:
        
        case 157:
        
        case 158:
        
        case 159:
        
        case 160:
        
        case 161:
        
        case 162:
        
        case 163:
        
        case 164:
        
        case 165:
        
        case 166:
        
        case 167:
        
        case 168:
        
        case 169:
        
        case 170:
        
        case 171:
        
        case 172:
        
        case 173:
        
        case 174:
        
        case 175:
        
        case 176:
        
        case 177:
        
        case 178:
        
        case 179:
        
        case 180:
        
        case 181:
        
        case 182:
        
        case 183:
        
        case 184:
        
        case 185:
        
        case 186:
        
        case 187:
        
        case 188:
        
        case 189:
        
        case 190:
        
        case 191:
        
        case 192:
        
        case 193:
        
        case 194:
        
        case 195:
        
        case 196:
        
        case 197:
        
        case 198:
        
        case 199:
        
        case 200:
        
        case 201:
        
        case 202:
        
        case 203:
        
        case 204:
        
        case 205:
        
        case 206:
        
        case 207:
        
        case 208:
        
        case 209:
        
        case 210:
        
        case 211:
        
        case 212:
        
        case 213:
        
        case 214:
        
        case 215:
        
        case 216:
        
        case 217:
        
        case 218:
        
        case 219:
        
        case 220:
        
        case 221:
        
        case 222:
        
        case 223:
        
        case 224:
        
        case 225:
        
        case 226:
        
        case 227:
        
        case 228:
        
        case 229:
        
        case 230:
        
        case 231:
        
        case 232:
        
        case 233:
        
        case 234:
        
        case 235:
        
        case 236:
        
        case 237:
        
        case 238:
        
        case 239:
        
        case 240:
        
        case 241:
        
        case 242:
        
        case 243:
        
        case 244:
        
        case 245:
        
        case 246:
        
        case 247:
        
        case 248:
        
        case 249:
        
        case 250:
        
        case 251:
        
        case 252:
        
        case 253:
        
        case 254:
        
        default:
          break;
      } 
      char c = 'ñ';
      int j = (paramInt2 & 0xFF) - c;
      if (j < 0)
        j += 256; 
      int k = ((paramInt2 & 0xFFFF) >>> 8) - c;
      if (k < 0)
        k += 256; 
      for (byte b = 0; b < arrayOfChar.length; b++) {
        int m = b % 2;
        if (m == 0) {
          arrayOfChar[b] = (char)(arrayOfChar[b] ^ j);
          j = ((j >>> 3 | j << 5) ^ arrayOfChar[b]) & 0xFF;
        } else {
          arrayOfChar[b] = (char)(arrayOfChar[b] ^ k);
          k = ((k >>> 3 | k << 5) ^ arrayOfChar[b]) & 0xFF;
        } 
      } 
      d[i] = (new String(arrayOfChar)).intern();
    } 
    return d[i];
  }
}


/* Location:              C:\Program Files\BurpSuitePro\burpsuite_pro.jar!\burp\Zbj3.class
 * Java compiler version: 21 (65.0)
 * JD-Core Version:       1.1.3
 */