package burp;

import java.awt.GridBagConstraints;
import java.awt.GridBagLayout;
import java.awt.event.ActionEvent;
import javax.swing.BorderFactory;
import net.portswigger.Zm2;

public class Zbku extends Zbv5 implements Zeq {
  private final Zg8i Zx;
  
  private final Zt0w Z_;
  
  private final Zbws Zc;
  
  private final Zbup Zl;
  
  private Zl8w ZU;
  
  private Zbkc ZX;
  
  private Ze01 Za;
  
  private Zmyz ZK;
  
  private static final String[] a;
  
  private static final String[] b;
  
  public Zbku() {
    Zi();
    this.ZK.Za(80);
    this.Z_ = new Zt0w();
    this.Zc = new Zbws(this.Z_);
    this.Zc.Zc(this);
    this.Zc.getSelectionModel().setSelectionMode(0);
    this.ZK.setLeftComponent(new Zbup(this.Zc));
    this.Zx = new Zg8i();
    this.Zl = new Zbup(this.Zx);
    this.ZK.setRightComponent(this.Zl);
    this.Za.ZX(Zt00.BOLD_FONT);
    this.Za.setIcon(Ze3m.ZC(Zeuf.PANEL_BROWSER, Zlkk.ACTION_NORMAL).Z_());
    this.Za.setText(a(-6279, 15965));
    this.Za.addActionListener(this::lambda$new$0);
    Zi(0);
  }
  
  public void ZG(Zvs paramZvs) {
    // Byte code:
    //   0: invokestatic ZlL : ()[I
    //   3: astore_2
    //   4: iconst_0
    //   5: istore_3
    //   6: iload_3
    //   7: aload_0
    //   8: getfield Z_ : Lburp/Zt0w;
    //   11: invokevirtual getRowCount : ()I
    //   14: if_icmpge -> 79
    //   17: aload_0
    //   18: getfield Z_ : Lburp/Zt0w;
    //   21: iload_3
    //   22: invokevirtual Zh : (I)Lburp/Zree;
    //   25: invokeinterface Za6 : ()Lburp/Zvs;
    //   30: aload_1
    //   31: if_acmpne -> 72
    //   34: aload_0
    //   35: getfield Zc : Lburp/Zbws;
    //   38: iload_3
    //   39: invokevirtual convertRowIndexToView : (I)I
    //   42: istore #4
    //   44: aload_0
    //   45: iload #4
    //   47: invokevirtual Zi : (I)V
    //   50: aload_0
    //   51: getfield Zc : Lburp/Zbws;
    //   54: aload_0
    //   55: getfield Zc : Lburp/Zbws;
    //   58: iload #4
    //   60: iconst_0
    //   61: iconst_1
    //   62: invokevirtual getCellRect : (IIZ)Ljava/awt/Rectangle;
    //   65: invokevirtual scrollRectToVisible : (Ljava/awt/Rectangle;)V
    //   68: aload_2
    //   69: ifnonnull -> 79
    //   72: iinc #3, 1
    //   75: aload_2
    //   76: ifnonnull -> 6
    //   79: return
  }
  
  public void ZK(int paramInt1, int paramInt2) {
    Zi(paramInt1);
  }
  
  private void Zi(int paramInt) {
    if (paramInt != 0)
      Zm2.Zo(Zze0.SCANNER_ISSUE_DEFINITIONS_VIEWED); 
    this.Zc.getSelectionModel().setSelectionInterval(paramInt, paramInt);
    int i = this.Zc.convertRowIndexToModel(paramInt);
    Zree zree = this.Z_.Zh(i);
    this.Zx.Zu(zree);
    this.Zl.getVerticalScrollBar().getModel().setValue(0);
  }
  
  private void Zi() {
    this.ZU = new Zl8w();
    this.ZX = new Zbkc();
    this.ZK = new Zmyz();
    this.Za = new Ze01();
    setBorder(BorderFactory.createEmptyBorder(10, 10, 10, 10));
    GridBagLayout gridBagLayout = new GridBagLayout();
    gridBagLayout.columnWidths = new int[] { 0, 5, 0, 5, 0, 5, 0 };
    gridBagLayout.rowHeights = new int[] { 0, 5, 0, 5, 0 };
    setLayout(gridBagLayout);
    this.ZU.setText(a(-6280, 16087));
    GridBagConstraints gridBagConstraints = new GridBagConstraints();
    gridBagConstraints.gridx = 0;
    gridBagConstraints.gridy = 2;
    gridBagConstraints.gridwidth = 7;
    gridBagConstraints.fill = 2;
    gridBagConstraints.weightx = 1.0D;
    add(this.ZU, gridBagConstraints);
    this.ZX.Zx(a(-6278, 6032));
    gridBagConstraints = new GridBagConstraints();
    gridBagConstraints.gridx = 0;
    gridBagConstraints.gridy = 0;
    gridBagConstraints.gridwidth = 5;
    gridBagConstraints.fill = 2;
    gridBagConstraints.anchor = 21;
    add(this.ZX, gridBagConstraints);
    gridBagConstraints = new GridBagConstraints();
    gridBagConstraints.gridx = 0;
    gridBagConstraints.gridy = 4;
    gridBagConstraints.gridwidth = 7;
    gridBagConstraints.fill = 1;
    gridBagConstraints.weighty = 1.0D;
    add(this.ZK, gridBagConstraints);
    gridBagConstraints = new GridBagConstraints();
    gridBagConstraints.gridx = 6;
    gridBagConstraints.gridy = 0;
    gridBagConstraints.fill = 3;
    gridBagConstraints.anchor = 768;
    add(this.Za, gridBagConstraints);
  }
  
  private void lambda$new$0(ActionEvent paramActionEvent) {
    Zke4.Zt(Zt2m.ZF(this), a(-6277, -31937), true);
  }
  
  static {
    // Byte code:
    //   0: iconst_4
    //   1: anewarray java/lang/String
    //   4: astore #5
    //   6: iconst_0
    //   7: istore_3
    //   8: ldc '#ÂŸF/`\\bhÃ³AÃºÃAYÂ¾Ã„Â›3Ã‰Â™Â¬Ã£\\fÂ@Ã‡Z7Ã“7p*Ã¦Ã—VAi/(Â…%Â¨ÂŸbP-|(;,Â¦Â±Â¥Â®Â•_CÃ¦%Â¸'ÂšÂ·ÃžÂ·@!Â«Â£}Â‘>QHuÃªÂ•5ÂÂ¾Ã¤AÃ®9?v]&-Â¦yÃ¼'
    //   10: dup
    //   11: astore_2
    //   12: invokevirtual length : ()I
    //   15: istore #4
    //   17: bipush #15
    //   19: istore_1
    //   20: iconst_m1
    //   21: istore_0
    //   22: bipush #115
    //   24: iinc #0, 1
    //   27: aload_2
    //   28: iload_0
    //   29: dup
    //   30: iload_1
    //   31: iadd
    //   32: invokevirtual substring : (II)Ljava/lang/String;
    //   35: iconst_m1
    //   36: goto -> 141
    //   39: aload #5
    //   41: swap
    //   42: iload_3
    //   43: iinc #3, 1
    //   46: swap
    //   47: aastore
    //   48: iload_0
    //   49: iload_1
    //   50: iadd
    //   51: dup
    //   52: istore_0
    //   53: iload #4
    //   55: if_icmpge -> 67
    //   58: aload_2
    //   59: iload_0
    //   60: invokevirtual charAt : (I)C
    //   63: istore_1
    //   64: goto -> 22
    //   67: ldc 'ÃšÂ­ZÂ†Â¹6SÂ©ÃÂ€ÂÂ\hÃ‚Ã¢kÃ¯$Ã¹7Ã¹Ã‘i+Â©CMÂ©zÂ„(Â“Ã”qÃƒÃ•%0Ã™PNqaÃ'
    //   69: dup
    //   70: astore_2
    //   71: invokevirtual length : ()I
    //   74: istore #4
    //   76: bipush #33
    //   78: istore_1
    //   79: iconst_m1
    //   80: istore_0
    //   81: bipush #44
    //   83: iinc #0, 1
    //   86: aload_2
    //   87: iload_0
    //   88: dup
    //   89: iload_1
    //   90: iadd
    //   91: invokevirtual substring : (II)Ljava/lang/String;
    //   94: iconst_0
    //   95: goto -> 141
    //   98: aload #5
    //   100: swap
    //   101: iload_3
    //   102: iinc #3, 1
    //   105: swap
    //   106: aastore
    //   107: iload_0
    //   108: iload_1
    //   109: iadd
    //   110: dup
    //   111: istore_0
    //   112: iload #4
    //   114: if_icmpge -> 126
    //   117: aload_2
    //   118: iload_0
    //   119: invokevirtual charAt : (I)C
    //   122: istore_1
    //   123: goto -> 81
    //   126: aload #5
    //   128: putstatic burp/Zbku.a : [Ljava/lang/String;
    //   131: iconst_4
    //   132: anewarray java/lang/String
    //   135: putstatic burp/Zbku.b : [Ljava/lang/String;
    //   138: goto -> 300
    //   141: dup_x2
    //   142: pop
    //   143: invokevirtual toCharArray : ()[C
    //   146: dup_x1
    //   147: arraylength
    //   148: dup_x2
    //   149: pop
    //   150: iconst_0
    //   151: istore #6
    //   153: dup2_x1
    //   154: pop2
    //   155: dup_x2
    //   156: iconst_1
    //   157: if_icmpgt -> 260
    //   160: dup2
    //   161: swap
    //   162: iload #6
    //   164: dup2_x1
    //   165: caload
    //   166: swap
    //   167: iload #6
    //   169: bipush #7
    //   171: irem
    //   172: tableswitch default -> 242, 0 -> 212, 1 -> 217, 2 -> 222, 3 -> 227, 4 -> 232, 5 -> 237
    //   212: bipush #60
    //   214: goto -> 244
    //   217: bipush #19
    //   219: goto -> 244
    //   222: bipush #62
    //   224: goto -> 244
    //   227: bipush #114
    //   229: goto -> 244
    //   232: bipush #21
    //   234: goto -> 244
    //   237: bipush #69
    //   239: goto -> 244
    //   242: bipush #93
    //   244: ixor
    //   245: ixor
    //   246: i2c
    //   247: castore
    //   248: iinc #6, 1
    //   251: dup
    //   252: ifne -> 260
    //   255: dup2
    //   256: dup_x1
    //   257: goto -> 164
    //   260: dup2_x1
    //   261: pop2
    //   262: dup_x2
    //   263: iload #6
    //   265: if_icmpgt -> 160
    //   268: pop
    //   269: new java/lang/String
    //   272: dup_x1
    //   273: swap
    //   274: invokespecial <init> : ([C)V
    //   277: invokevirtual intern : ()Ljava/lang/String;
    //   280: swap
    //   281: pop
    //   282: swap
    //   283: tableswitch default -> 39, 0 -> 98
    //   300: return
  }
  
  private static String a(int paramInt1, int paramInt2) {
    int i = (paramInt1 ^ 0xFFFFE779) & 0xFFFF;
    if (b[i] == null) {
      char[] arrayOfChar = a[i].toCharArray();
      switch (arrayOfChar[0] & 0xFF) {
        case 0:
        
        case 1:
        
        case 2:
        
        case 3:
        
        case 4:
        
        case 5:
        
        case 6:
        
        case 7:
        
        case 8:
        
        case 9:
        
        case 10:
        
        case 11:
        
        case 12:
        
        case 13:
        
        case 14:
        
        case 15:
        
        case 16:
        
        case 17:
        
        case 18:
        
        case 19:
        
        case 20:
        
        case 21:
        
        case 22:
        
        case 23:
        
        case 24:
        
        case 25:
        
        case 26:
        
        case 27:
        
        case 28:
        
        case 29:
        
        case 30:
        
        case 31:
        
        case 32:
        
        case 33:
        
        case 34:
        
        case 35:
        
        case 36:
        
        case 37:
        
        case 38:
        
        case 39:
        
        case 40:
        
        case 41:
        
        case 42:
        
        case 43:
        
        case 44:
        
        case 45:
        
        case 46:
        
        case 47:
        
        case 48:
        
        case 49:
        
        case 50:
        
        case 51:
        
        case 52:
        
        case 53:
        
        case 54:
        
        case 55:
        
        case 56:
        
        case 57:
        
        case 58:
        
        case 59:
        
        case 60:
        
        case 61:
        
        case 62:
        
        case 63:
        
        case 64:
        
        case 65:
        
        case 66:
        
        case 67:
        
        case 68:
        
        case 69:
        
        case 70:
        
        case 71:
        
        case 72:
        
        case 73:
        
        case 74:
        
        case 75:
        
        case 76:
        
        case 77:
        
        case 78:
        
        case 79:
        
        case 80:
        
        case 81:
        
        case 82:
        
        case 83:
        
        case 84:
        
        case 85:
        
        case 86:
        
        case 87:
        
        case 88:
        
        case 89:
        
        case 90:
        
        case 91:
        
        case 92:
        
        case 93:
        
        case 94:
        
        case 95:
        
        case 96:
        
        case 97:
        
        case 98:
        
        case 99:
        
        case 100:
        
        case 101:
        
        case 102:
        
        case 103:
        
        case 104:
        
        case 105:
        
        case 106:
        
        case 107:
        
        case 108:
        
        case 109:
        
        case 110:
        
        case 111:
        
        case 112:
        
        case 113:
        
        case 114:
        
        case 115:
        
        case 116:
        
        case 117:
        
        case 118:
        
        case 119:
        
        case 120:
        
        case 121:
        
        case 122:
        
        case 123:
        
        case 124:
        
        case 125:
        
        case 126:
        
        case 127:
        
        case 128:
        
        case 129:
        
        case 130:
        
        case 131:
        
        case 132:
        
        case 133:
        
        case 134:
        
        case 135:
        
        case 136:
        
        case 137:
        
        case 138:
        
        case 139:
        
        case 140:
        
        case 141:
        
        case 142:
        
        case 143:
        
        case 144:
        
        case 145:
        
        case 146:
        
        case 147:
        
        case 148:
        
        case 149:
        
        case 150:
        
        case 151:
        
        case 152:
        
        case 153:
        
        case 154:
        
        case 155:
        
        case 156:
        
        case 157:
        
        case 158:
        
        case 159:
        
        case 160:
        
        case 161:
        
        case 162:
        
        case 163:
        
        case 164:
        
        case 165:
        
        case 166:
        
        case 167:
        
        case 168:
        
        case 169:
        
        case 170:
        
        case 171:
        
        case 172:
        
        case 173:
        
        case 174:
        
        case 175:
        
        case 176:
        
        case 177:
        
        case 178:
        
        case 179:
        
        case 180:
        
        case 181:
        
        case 182:
        
        case 183:
        
        case 184:
        
        case 185:
        
        case 186:
        
        case 187:
        
        case 188:
        
        case 189:
        
        case 190:
        
        case 191:
        
        case 192:
        
        case 193:
        
        case 194:
        
        case 195:
        
        case 196:
        
        case 197:
        
        case 198:
        
        case 199:
        
        case 200:
        
        case 201:
        
        case 202:
        
        case 203:
        
        case 204:
        
        case 205:
        
        case 206:
        
        case 207:
        
        case 208:
        
        case 209:
        
        case 210:
        
        case 211:
        
        case 212:
        
        case 213:
        
        case 214:
        
        case 215:
        
        case 216:
        
        case 217:
        
        case 218:
        
        case 219:
        
        case 220:
        
        case 221:
        
        case 222:
        
        case 223:
        
        case 224:
        
        case 225:
        
        case 226:
        
        case 227:
        
        case 228:
        
        case 229:
        
        case 230:
        
        case 231:
        
        case 232:
        
        case 233:
        
        case 234:
        
        case 235:
        
        case 236:
        
        case 237:
        
        case 238:
        
        case 239:
        
        case 240:
        
        case 241:
        
        case 242:
        
        case 243:
        
        case 244:
        
        case 245:
        
        case 246:
        
        case 247:
        
        case 248:
        
        case 249:
        
        case 250:
        
        case 251:
        
        case 252:
        
        case 253:
        
        case 254:
        
        default:
          break;
      } 
      char c = 'Ãˆ';
      int j = (paramInt2 & 0xFF) - c;
      if (j < 0)
        j += 256; 
      int k = ((paramInt2 & 0xFFFF) >>> 8) - c;
      if (k < 0)
        k += 256; 
      for (byte b = 0; b < arrayOfChar.length; b++) {
        int m = b % 2;
        if (m == 0) {
          arrayOfChar[b] = (char)(arrayOfChar[b] ^ j);
          j = ((j >>> 3 | j << 5) ^ arrayOfChar[b]) & 0xFF;
        } else {
          arrayOfChar[b] = (char)(arrayOfChar[b] ^ k);
          k = ((k >>> 3 | k << 5) ^ arrayOfChar[b]) & 0xFF;
        } 
      } 
      b[i] = (new String(arrayOfChar)).intern();
    } 
    return b[i];
  }
}


/* Location:              C:\Program Files\BurpSuitePro\burpsuite_pro.jar!\burp\Zbku.class
 * Java compiler version: 21 (65.0)
 * JD-Core Version:       1.1.3
 */