package burp;

import java.math.BigInteger;

class Zblj extends ClassLoader {
  static Object Zl;
  
  static String Za;
  
  private static final String[] a;
  
  private static final String[] b;
  
  static boolean Zc(Object[] paramArrayOfObject, Object paramObject) throws Throwable {
    // Byte code:
    //   0: invokestatic ZN : ()Z
    //   3: istore_2
    //   4: getstatic burp/Zmh5.ZN : Ljava/lang/Object;
    //   7: checkcast java/math/BigInteger
    //   10: invokevirtual toByteArray : ()[B
    //   13: astore_3
    //   14: bipush #64
    //   16: newarray byte
    //   18: dup
    //   19: iconst_0
    //   20: bipush #-128
    //   22: bastore
    //   23: dup
    //   24: iconst_1
    //   25: iconst_0
    //   26: bastore
    //   27: dup
    //   28: iconst_2
    //   29: iconst_0
    //   30: bastore
    //   31: dup
    //   32: iconst_3
    //   33: iconst_0
    //   34: bastore
    //   35: dup
    //   36: iconst_4
    //   37: iconst_0
    //   38: bastore
    //   39: dup
    //   40: iconst_5
    //   41: iconst_0
    //   42: bastore
    //   43: dup
    //   44: bipush #6
    //   46: iconst_0
    //   47: bastore
    //   48: dup
    //   49: bipush #7
    //   51: iconst_0
    //   52: bastore
    //   53: dup
    //   54: bipush #8
    //   56: iconst_0
    //   57: bastore
    //   58: dup
    //   59: bipush #9
    //   61: iconst_0
    //   62: bastore
    //   63: dup
    //   64: bipush #10
    //   66: iconst_0
    //   67: bastore
    //   68: dup
    //   69: bipush #11
    //   71: iconst_0
    //   72: bastore
    //   73: dup
    //   74: bipush #12
    //   76: iconst_0
    //   77: bastore
    //   78: dup
    //   79: bipush #13
    //   81: iconst_0
    //   82: bastore
    //   83: dup
    //   84: bipush #14
    //   86: iconst_0
    //   87: bastore
    //   88: dup
    //   89: bipush #15
    //   91: iconst_0
    //   92: bastore
    //   93: dup
    //   94: bipush #16
    //   96: iconst_0
    //   97: bastore
    //   98: dup
    //   99: bipush #17
    //   101: iconst_0
    //   102: bastore
    //   103: dup
    //   104: bipush #18
    //   106: iconst_0
    //   107: bastore
    //   108: dup
    //   109: bipush #19
    //   111: iconst_0
    //   112: bastore
    //   113: dup
    //   114: bipush #20
    //   116: iconst_0
    //   117: bastore
    //   118: dup
    //   119: bipush #21
    //   121: iconst_0
    //   122: bastore
    //   123: dup
    //   124: bipush #22
    //   126: iconst_0
    //   127: bastore
    //   128: dup
    //   129: bipush #23
    //   131: iconst_0
    //   132: bastore
    //   133: dup
    //   134: bipush #24
    //   136: iconst_0
    //   137: bastore
    //   138: dup
    //   139: bipush #25
    //   141: iconst_0
    //   142: bastore
    //   143: dup
    //   144: bipush #26
    //   146: iconst_0
    //   147: bastore
    //   148: dup
    //   149: bipush #27
    //   151: iconst_0
    //   152: bastore
    //   153: dup
    //   154: bipush #28
    //   156: iconst_0
    //   157: bastore
    //   158: dup
    //   159: bipush #29
    //   161: iconst_0
    //   162: bastore
    //   163: dup
    //   164: bipush #30
    //   166: iconst_0
    //   167: bastore
    //   168: dup
    //   169: bipush #31
    //   171: iconst_0
    //   172: bastore
    //   173: dup
    //   174: bipush #32
    //   176: iconst_0
    //   177: bastore
    //   178: dup
    //   179: bipush #33
    //   181: iconst_0
    //   182: bastore
    //   183: dup
    //   184: bipush #34
    //   186: iconst_0
    //   187: bastore
    //   188: dup
    //   189: bipush #35
    //   191: iconst_0
    //   192: bastore
    //   193: dup
    //   194: bipush #36
    //   196: iconst_0
    //   197: bastore
    //   198: dup
    //   199: bipush #37
    //   201: iconst_0
    //   202: bastore
    //   203: dup
    //   204: bipush #38
    //   206: iconst_0
    //   207: bastore
    //   208: dup
    //   209: bipush #39
    //   211: iconst_0
    //   212: bastore
    //   213: dup
    //   214: bipush #40
    //   216: iconst_0
    //   217: bastore
    //   218: dup
    //   219: bipush #41
    //   221: iconst_0
    //   222: bastore
    //   223: dup
    //   224: bipush #42
    //   226: iconst_0
    //   227: bastore
    //   228: dup
    //   229: bipush #43
    //   231: iconst_0
    //   232: bastore
    //   233: dup
    //   234: bipush #44
    //   236: iconst_0
    //   237: bastore
    //   238: dup
    //   239: bipush #45
    //   241: iconst_0
    //   242: bastore
    //   243: dup
    //   244: bipush #46
    //   246: iconst_0
    //   247: bastore
    //   248: dup
    //   249: bipush #47
    //   251: iconst_0
    //   252: bastore
    //   253: dup
    //   254: bipush #48
    //   256: iconst_0
    //   257: bastore
    //   258: dup
    //   259: bipush #49
    //   261: iconst_0
    //   262: bastore
    //   263: dup
    //   264: bipush #50
    //   266: iconst_0
    //   267: bastore
    //   268: dup
    //   269: bipush #51
    //   271: iconst_0
    //   272: bastore
    //   273: dup
    //   274: bipush #52
    //   276: iconst_0
    //   277: bastore
    //   278: dup
    //   279: bipush #53
    //   281: iconst_0
    //   282: bastore
    //   283: dup
    //   284: bipush #54
    //   286: iconst_0
    //   287: bastore
    //   288: dup
    //   289: bipush #55
    //   291: iconst_0
    //   292: bastore
    //   293: dup
    //   294: bipush #56
    //   296: iconst_0
    //   297: bastore
    //   298: dup
    //   299: bipush #57
    //   301: iconst_0
    //   302: bastore
    //   303: dup
    //   304: bipush #58
    //   306: iconst_0
    //   307: bastore
    //   308: dup
    //   309: bipush #59
    //   311: iconst_0
    //   312: bastore
    //   313: dup
    //   314: bipush #60
    //   316: iconst_0
    //   317: bastore
    //   318: dup
    //   319: bipush #61
    //   321: iconst_0
    //   322: bastore
    //   323: dup
    //   324: bipush #62
    //   326: iconst_0
    //   327: bastore
    //   328: dup
    //   329: bipush #63
    //   331: iconst_0
    //   332: bastore
    //   333: astore #5
    //   335: bipush #64
    //   337: newarray int
    //   339: dup
    //   340: iconst_0
    //   341: ldc 1116352408
    //   343: iastore
    //   344: dup
    //   345: iconst_1
    //   346: ldc 1899447441
    //   348: iastore
    //   349: dup
    //   350: iconst_2
    //   351: ldc -1245643825
    //   353: iastore
    //   354: dup
    //   355: iconst_3
    //   356: ldc -373957723
    //   358: iastore
    //   359: dup
    //   360: iconst_4
    //   361: ldc 961987163
    //   363: iastore
    //   364: dup
    //   365: iconst_5
    //   366: ldc 1508970993
    //   368: iastore
    //   369: dup
    //   370: bipush #6
    //   372: ldc -1841331548
    //   374: iastore
    //   375: dup
    //   376: bipush #7
    //   378: ldc -1424204075
    //   380: iastore
    //   381: dup
    //   382: bipush #8
    //   384: ldc -670586216
    //   386: iastore
    //   387: dup
    //   388: bipush #9
    //   390: ldc 310598401
    //   392: iastore
    //   393: dup
    //   394: bipush #10
    //   396: ldc 607225278
    //   398: iastore
    //   399: dup
    //   400: bipush #11
    //   402: ldc 1426881987
    //   404: iastore
    //   405: dup
    //   406: bipush #12
    //   408: ldc 1925078388
    //   410: iastore
    //   411: dup
    //   412: bipush #13
    //   414: ldc -2132889090
    //   416: iastore
    //   417: dup
    //   418: bipush #14
    //   420: ldc -1680079193
    //   422: iastore
    //   423: dup
    //   424: bipush #15
    //   426: ldc -1046744716
    //   428: iastore
    //   429: dup
    //   430: bipush #16
    //   432: ldc -459576895
    //   434: iastore
    //   435: dup
    //   436: bipush #17
    //   438: ldc -272742522
    //   440: iastore
    //   441: dup
    //   442: bipush #18
    //   444: ldc 264347078
    //   446: iastore
    //   447: dup
    //   448: bipush #19
    //   450: ldc 604807628
    //   452: iastore
    //   453: dup
    //   454: bipush #20
    //   456: ldc 770255983
    //   458: iastore
    //   459: dup
    //   460: bipush #21
    //   462: ldc 1249150122
    //   464: iastore
    //   465: dup
    //   466: bipush #22
    //   468: ldc 1555081692
    //   470: iastore
    //   471: dup
    //   472: bipush #23
    //   474: ldc 1996064986
    //   476: iastore
    //   477: dup
    //   478: bipush #24
    //   480: ldc -1740746414
    //   482: iastore
    //   483: dup
    //   484: bipush #25
    //   486: ldc -1473132947
    //   488: iastore
    //   489: dup
    //   490: bipush #26
    //   492: ldc -1341970488
    //   494: iastore
    //   495: dup
    //   496: bipush #27
    //   498: ldc -1084653625
    //   500: iastore
    //   501: dup
    //   502: bipush #28
    //   504: ldc -958395405
    //   506: iastore
    //   507: dup
    //   508: bipush #29
    //   510: ldc -710438585
    //   512: iastore
    //   513: dup
    //   514: bipush #30
    //   516: ldc 113926993
    //   518: iastore
    //   519: dup
    //   520: bipush #31
    //   522: ldc 338241895
    //   524: iastore
    //   525: dup
    //   526: bipush #32
    //   528: ldc 666307205
    //   530: iastore
    //   531: dup
    //   532: bipush #33
    //   534: ldc 773529912
    //   536: iastore
    //   537: dup
    //   538: bipush #34
    //   540: ldc 1294757372
    //   542: iastore
    //   543: dup
    //   544: bipush #35
    //   546: ldc 1396182291
    //   548: iastore
    //   549: dup
    //   550: bipush #36
    //   552: ldc 1695183700
    //   554: iastore
    //   555: dup
    //   556: bipush #37
    //   558: ldc 1986661051
    //   560: iastore
    //   561: dup
    //   562: bipush #38
    //   564: ldc -2117940946
    //   566: iastore
    //   567: dup
    //   568: bipush #39
    //   570: ldc -1838011259
    //   572: iastore
    //   573: dup
    //   574: bipush #40
    //   576: ldc -1564481375
    //   578: iastore
    //   579: dup
    //   580: bipush #41
    //   582: ldc -1474664885
    //   584: iastore
    //   585: dup
    //   586: bipush #42
    //   588: ldc -1035236496
    //   590: iastore
    //   591: dup
    //   592: bipush #43
    //   594: ldc -949202525
    //   596: iastore
    //   597: dup
    //   598: bipush #44
    //   600: ldc -778901479
    //   602: iastore
    //   603: dup
    //   604: bipush #45
    //   606: ldc -694614492
    //   608: iastore
    //   609: dup
    //   610: bipush #46
    //   612: ldc -200395387
    //   614: iastore
    //   615: dup
    //   616: bipush #47
    //   618: ldc 275423344
    //   620: iastore
    //   621: dup
    //   622: bipush #48
    //   624: ldc 430227734
    //   626: iastore
    //   627: dup
    //   628: bipush #49
    //   630: ldc 506948616
    //   632: iastore
    //   633: dup
    //   634: bipush #50
    //   636: ldc 659060556
    //   638: iastore
    //   639: dup
    //   640: bipush #51
    //   642: ldc 883997877
    //   644: iastore
    //   645: dup
    //   646: bipush #52
    //   648: ldc 958139571
    //   650: iastore
    //   651: dup
    //   652: bipush #53
    //   654: ldc 1322822218
    //   656: iastore
    //   657: dup
    //   658: bipush #54
    //   660: ldc 1537002063
    //   662: iastore
    //   663: dup
    //   664: bipush #55
    //   666: ldc 1747873779
    //   668: iastore
    //   669: dup
    //   670: bipush #56
    //   672: ldc 1955562222
    //   674: iastore
    //   675: dup
    //   676: bipush #57
    //   678: ldc 2024104815
    //   680: iastore
    //   681: dup
    //   682: bipush #58
    //   684: ldc -2067236844
    //   686: iastore
    //   687: dup
    //   688: bipush #59
    //   690: ldc -1933114872
    //   692: iastore
    //   693: dup
    //   694: bipush #60
    //   696: ldc -1866530822
    //   698: iastore
    //   699: dup
    //   700: bipush #61
    //   702: ldc -1538233109
    //   704: iastore
    //   705: dup
    //   706: bipush #62
    //   708: ldc -1090935817
    //   710: iastore
    //   711: dup
    //   712: bipush #63
    //   714: ldc -965641998
    //   716: iastore
    //   717: astore #6
    //   719: iconst_2
    //   720: newarray int
    //   722: dup
    //   723: iconst_0
    //   724: iconst_0
    //   725: iastore
    //   726: dup
    //   727: iconst_1
    //   728: iconst_0
    //   729: iastore
    //   730: astore #7
    //   732: bipush #8
    //   734: newarray int
    //   736: dup
    //   737: iconst_0
    //   738: ldc 1779033703
    //   740: iastore
    //   741: dup
    //   742: iconst_1
    //   743: ldc -1150833019
    //   745: iastore
    //   746: dup
    //   747: iconst_2
    //   748: ldc 1013904242
    //   750: iastore
    //   751: dup
    //   752: iconst_3
    //   753: ldc -1521486534
    //   755: iastore
    //   756: dup
    //   757: iconst_4
    //   758: ldc 1359893119
    //   760: iastore
    //   761: dup
    //   762: iconst_5
    //   763: ldc -1694144372
    //   765: iastore
    //   766: dup
    //   767: bipush #6
    //   769: ldc 528734635
    //   771: iastore
    //   772: dup
    //   773: bipush #7
    //   775: ldc 1541459225
    //   777: iastore
    //   778: astore #8
    //   780: bipush #64
    //   782: newarray byte
    //   784: astore #9
    //   786: bipush #64
    //   788: newarray byte
    //   790: astore #10
    //   792: aload_3
    //   793: arraylength
    //   794: istore #11
    //   796: aload #7
    //   798: iconst_0
    //   799: iaload
    //   800: bipush #63
    //   802: iand
    //   803: istore #12
    //   805: aload #7
    //   807: iconst_0
    //   808: dup2
    //   809: iaload
    //   810: iload #11
    //   812: iadd
    //   813: iastore
    //   814: aload #7
    //   816: iconst_0
    //   817: dup2
    //   818: iaload
    //   819: iconst_m1
    //   820: iand
    //   821: iastore
    //   822: aload #7
    //   824: iconst_0
    //   825: iaload
    //   826: iload #11
    //   828: if_icmpge -> 846
    //   831: aload #7
    //   833: iconst_1
    //   834: dup2
    //   835: iaload
    //   836: iconst_1
    //   837: iadd
    //   838: iastore
    //   839: goto -> 846
    //   842: invokestatic a : (Ljava/lang/Throwable;)Ljava/lang/Throwable;
    //   845: athrow
    //   846: iconst_0
    //   847: istore #13
    //   849: iload #11
    //   851: bipush #64
    //   853: if_icmplt -> 1462
    //   856: iconst_0
    //   857: istore #14
    //   859: iload #14
    //   861: bipush #64
    //   863: if_icmpge -> 885
    //   866: aload #10
    //   868: iload #14
    //   870: aload_3
    //   871: iload #13
    //   873: iload #14
    //   875: iadd
    //   876: baload
    //   877: bastore
    //   878: iinc #14, 1
    //   881: iload_2
    //   882: ifne -> 859
    //   885: bipush #64
    //   887: newarray int
    //   889: astore #14
    //   891: bipush #8
    //   893: newarray int
    //   895: astore #15
    //   897: iconst_0
    //   898: istore #16
    //   900: iload #16
    //   902: bipush #8
    //   904: if_icmpge -> 924
    //   907: aload #15
    //   909: iload #16
    //   911: aload #8
    //   913: iload #16
    //   915: iaload
    //   916: iastore
    //   917: iinc #16, 1
    //   920: iload_2
    //   921: ifne -> 900
    //   924: iconst_0
    //   925: istore #16
    //   927: iload #16
    //   929: bipush #64
    //   931: if_icmpge -> 1422
    //   934: iload #16
    //   936: bipush #16
    //   938: if_icmpge -> 1019
    //   941: aload #14
    //   943: iload #16
    //   945: aload #10
    //   947: iconst_4
    //   948: iload #16
    //   950: imul
    //   951: baload
    //   952: sipush #255
    //   955: iand
    //   956: bipush #24
    //   958: ishl
    //   959: aload #10
    //   961: iconst_4
    //   962: iload #16
    //   964: imul
    //   965: iconst_1
    //   966: iadd
    //   967: baload
    //   968: sipush #255
    //   971: iand
    //   972: bipush #16
    //   974: ishl
    //   975: ior
    //   976: aload #10
    //   978: iconst_4
    //   979: iload #16
    //   981: imul
    //   982: iconst_2
    //   983: iadd
    //   984: baload
    //   985: sipush #255
    //   988: iand
    //   989: bipush #8
    //   991: ishl
    //   992: ior
    //   993: aload #10
    //   995: iconst_4
    //   996: iload #16
    //   998: imul
    //   999: iconst_3
    //   1000: iadd
    //   1001: baload
    //   1002: sipush #255
    //   1005: iand
    //   1006: ior
    //   1007: iastore
    //   1008: iload_2
    //   1009: ifne -> 1162
    //   1012: goto -> 1019
    //   1015: invokestatic a : (Ljava/lang/Throwable;)Ljava/lang/Throwable;
    //   1018: athrow
    //   1019: aload #14
    //   1021: iload #16
    //   1023: aload #14
    //   1025: iload #16
    //   1027: iconst_2
    //   1028: isub
    //   1029: iaload
    //   1030: bipush #17
    //   1032: iushr
    //   1033: aload #14
    //   1035: iload #16
    //   1037: iconst_2
    //   1038: isub
    //   1039: iaload
    //   1040: bipush #15
    //   1042: ishl
    //   1043: ior
    //   1044: aload #14
    //   1046: iload #16
    //   1048: iconst_2
    //   1049: isub
    //   1050: iaload
    //   1051: bipush #19
    //   1053: iushr
    //   1054: aload #14
    //   1056: iload #16
    //   1058: iconst_2
    //   1059: isub
    //   1060: iaload
    //   1061: bipush #13
    //   1063: ishl
    //   1064: ior
    //   1065: ixor
    //   1066: aload #14
    //   1068: iload #16
    //   1070: iconst_2
    //   1071: isub
    //   1072: iaload
    //   1073: bipush #10
    //   1075: iushr
    //   1076: ixor
    //   1077: aload #14
    //   1079: iload #16
    //   1081: bipush #7
    //   1083: isub
    //   1084: iaload
    //   1085: iadd
    //   1086: aload #14
    //   1088: iload #16
    //   1090: bipush #15
    //   1092: isub
    //   1093: iaload
    //   1094: bipush #7
    //   1096: iushr
    //   1097: aload #14
    //   1099: iload #16
    //   1101: bipush #15
    //   1103: isub
    //   1104: iaload
    //   1105: bipush #25
    //   1107: ishl
    //   1108: ior
    //   1109: aload #14
    //   1111: iload #16
    //   1113: bipush #15
    //   1115: isub
    //   1116: iaload
    //   1117: bipush #18
    //   1119: iushr
    //   1120: aload #14
    //   1122: iload #16
    //   1124: bipush #15
    //   1126: isub
    //   1127: iaload
    //   1128: bipush #14
    //   1130: ishl
    //   1131: ior
    //   1132: ixor
    //   1133: aload #14
    //   1135: iload #16
    //   1137: bipush #15
    //   1139: isub
    //   1140: iaload
    //   1141: iconst_3
    //   1142: iushr
    //   1143: ixor
    //   1144: iadd
    //   1145: aload #14
    //   1147: iload #16
    //   1149: bipush #16
    //   1151: isub
    //   1152: iaload
    //   1153: iadd
    //   1154: iastore
    //   1155: goto -> 1162
    //   1158: invokestatic a : (Ljava/lang/Throwable;)Ljava/lang/Throwable;
    //   1161: athrow
    //   1162: aload #15
    //   1164: bipush #7
    //   1166: iaload
    //   1167: aload #15
    //   1169: iconst_4
    //   1170: iaload
    //   1171: bipush #6
    //   1173: iushr
    //   1174: aload #15
    //   1176: iconst_4
    //   1177: iaload
    //   1178: bipush #26
    //   1180: ishl
    //   1181: ior
    //   1182: aload #15
    //   1184: iconst_4
    //   1185: iaload
    //   1186: bipush #11
    //   1188: iushr
    //   1189: aload #15
    //   1191: iconst_4
    //   1192: iaload
    //   1193: bipush #21
    //   1195: ishl
    //   1196: ior
    //   1197: ixor
    //   1198: aload #15
    //   1200: iconst_4
    //   1201: iaload
    //   1202: bipush #25
    //   1204: iushr
    //   1205: aload #15
    //   1207: iconst_4
    //   1208: iaload
    //   1209: bipush #7
    //   1211: ishl
    //   1212: ior
    //   1213: ixor
    //   1214: iadd
    //   1215: aload #15
    //   1217: bipush #6
    //   1219: iaload
    //   1220: aload #15
    //   1222: iconst_4
    //   1223: iaload
    //   1224: aload #15
    //   1226: iconst_5
    //   1227: iaload
    //   1228: aload #15
    //   1230: bipush #6
    //   1232: iaload
    //   1233: ixor
    //   1234: iand
    //   1235: ixor
    //   1236: iadd
    //   1237: aload #6
    //   1239: iload #16
    //   1241: iaload
    //   1242: iadd
    //   1243: aload #14
    //   1245: iload #16
    //   1247: iaload
    //   1248: iadd
    //   1249: istore #17
    //   1251: aload #15
    //   1253: iconst_0
    //   1254: iaload
    //   1255: iconst_2
    //   1256: iushr
    //   1257: aload #15
    //   1259: iconst_0
    //   1260: iaload
    //   1261: bipush #30
    //   1263: ishl
    //   1264: ior
    //   1265: aload #15
    //   1267: iconst_0
    //   1268: iaload
    //   1269: bipush #13
    //   1271: iushr
    //   1272: aload #15
    //   1274: iconst_0
    //   1275: iaload
    //   1276: bipush #19
    //   1278: ishl
    //   1279: ior
    //   1280: ixor
    //   1281: aload #15
    //   1283: iconst_0
    //   1284: iaload
    //   1285: bipush #22
    //   1287: iushr
    //   1288: aload #15
    //   1290: iconst_0
    //   1291: iaload
    //   1292: bipush #10
    //   1294: ishl
    //   1295: ior
    //   1296: ixor
    //   1297: aload #15
    //   1299: iconst_0
    //   1300: iaload
    //   1301: aload #15
    //   1303: iconst_1
    //   1304: iaload
    //   1305: iand
    //   1306: aload #15
    //   1308: iconst_2
    //   1309: iaload
    //   1310: aload #15
    //   1312: iconst_0
    //   1313: iaload
    //   1314: aload #15
    //   1316: iconst_1
    //   1317: iaload
    //   1318: ior
    //   1319: iand
    //   1320: ior
    //   1321: iadd
    //   1322: istore #18
    //   1324: aload #15
    //   1326: iconst_3
    //   1327: dup2
    //   1328: iaload
    //   1329: iload #17
    //   1331: iadd
    //   1332: iastore
    //   1333: aload #15
    //   1335: bipush #7
    //   1337: iload #17
    //   1339: iload #18
    //   1341: iadd
    //   1342: iastore
    //   1343: aload #15
    //   1345: bipush #7
    //   1347: iaload
    //   1348: istore #17
    //   1350: aload #15
    //   1352: bipush #7
    //   1354: aload #15
    //   1356: bipush #6
    //   1358: iaload
    //   1359: iastore
    //   1360: aload #15
    //   1362: bipush #6
    //   1364: aload #15
    //   1366: iconst_5
    //   1367: iaload
    //   1368: iastore
    //   1369: aload #15
    //   1371: iconst_5
    //   1372: aload #15
    //   1374: iconst_4
    //   1375: iaload
    //   1376: iastore
    //   1377: aload #15
    //   1379: iconst_4
    //   1380: aload #15
    //   1382: iconst_3
    //   1383: iaload
    //   1384: iastore
    //   1385: aload #15
    //   1387: iconst_3
    //   1388: aload #15
    //   1390: iconst_2
    //   1391: iaload
    //   1392: iastore
    //   1393: aload #15
    //   1395: iconst_2
    //   1396: aload #15
    //   1398: iconst_1
    //   1399: iaload
    //   1400: iastore
    //   1401: aload #15
    //   1403: iconst_1
    //   1404: aload #15
    //   1406: iconst_0
    //   1407: iaload
    //   1408: iastore
    //   1409: aload #15
    //   1411: iconst_0
    //   1412: iload #17
    //   1414: iastore
    //   1415: iinc #16, 1
    //   1418: iload_2
    //   1419: ifne -> 927
    //   1422: iconst_0
    //   1423: istore #16
    //   1425: iload #16
    //   1427: bipush #8
    //   1429: if_icmpge -> 1452
    //   1432: aload #8
    //   1434: iload #16
    //   1436: dup2
    //   1437: iaload
    //   1438: aload #15
    //   1440: iload #16
    //   1442: iaload
    //   1443: iadd
    //   1444: iastore
    //   1445: iinc #16, 1
    //   1448: iload_2
    //   1449: ifne -> 1425
    //   1452: iinc #13, 64
    //   1455: iinc #11, -64
    //   1458: iload_2
    //   1459: ifne -> 849
    //   1462: iload #11
    //   1464: ifle -> 1499
    //   1467: iconst_0
    //   1468: istore #14
    //   1470: iload #14
    //   1472: iload #11
    //   1474: if_icmpge -> 1499
    //   1477: aload #9
    //   1479: iload #12
    //   1481: iload #14
    //   1483: iadd
    //   1484: aload_3
    //   1485: iload #13
    //   1487: iload #14
    //   1489: iadd
    //   1490: baload
    //   1491: bastore
    //   1492: iinc #14, 1
    //   1495: iload_2
    //   1496: ifne -> 1470
    //   1499: aload #7
    //   1501: iconst_0
    //   1502: iaload
    //   1503: bipush #29
    //   1505: iushr
    //   1506: aload #7
    //   1508: iconst_1
    //   1509: iaload
    //   1510: iconst_3
    //   1511: ishl
    //   1512: ior
    //   1513: istore #14
    //   1515: aload #7
    //   1517: iconst_0
    //   1518: iaload
    //   1519: iconst_3
    //   1520: ishl
    //   1521: istore #15
    //   1523: aload #7
    //   1525: iconst_0
    //   1526: iaload
    //   1527: bipush #63
    //   1529: iand
    //   1530: istore #16
    //   1532: iload #16
    //   1534: bipush #56
    //   1536: if_icmpge -> 1551
    //   1539: bipush #56
    //   1541: iload #16
    //   1543: isub
    //   1544: goto -> 1556
    //   1547: invokestatic a : (Ljava/lang/Throwable;)Ljava/lang/Throwable;
    //   1550: athrow
    //   1551: bipush #120
    //   1553: iload #16
    //   1555: isub
    //   1556: istore #17
    //   1558: aload #7
    //   1560: iconst_0
    //   1561: iaload
    //   1562: bipush #63
    //   1564: iand
    //   1565: istore #12
    //   1567: bipush #64
    //   1569: iload #12
    //   1571: isub
    //   1572: istore #18
    //   1574: aload #7
    //   1576: iconst_0
    //   1577: dup2
    //   1578: iaload
    //   1579: iload #17
    //   1581: iadd
    //   1582: iastore
    //   1583: aload #7
    //   1585: iconst_0
    //   1586: dup2
    //   1587: iaload
    //   1588: iconst_m1
    //   1589: iand
    //   1590: iastore
    //   1591: aload #7
    //   1593: iconst_0
    //   1594: iaload
    //   1595: iload #17
    //   1597: if_icmpge -> 1615
    //   1600: aload #7
    //   1602: iconst_1
    //   1603: dup2
    //   1604: iaload
    //   1605: iconst_1
    //   1606: iadd
    //   1607: iastore
    //   1608: goto -> 1615
    //   1611: invokestatic a : (Ljava/lang/Throwable;)Ljava/lang/Throwable;
    //   1614: athrow
    //   1615: iconst_0
    //   1616: istore #13
    //   1618: iload #12
    //   1620: ifle -> 2251
    //   1623: iload #17
    //   1625: iload #18
    //   1627: if_icmplt -> 2251
    //   1630: goto -> 1637
    //   1633: invokestatic a : (Ljava/lang/Throwable;)Ljava/lang/Throwable;
    //   1636: athrow
    //   1637: iconst_0
    //   1638: istore #19
    //   1640: iload #19
    //   1642: iload #18
    //   1644: if_icmpge -> 1667
    //   1647: aload #9
    //   1649: iload #12
    //   1651: iload #19
    //   1653: iadd
    //   1654: aload #5
    //   1656: iload #19
    //   1658: baload
    //   1659: bastore
    //   1660: iinc #19, 1
    //   1663: iload_2
    //   1664: ifne -> 1640
    //   1667: bipush #64
    //   1669: newarray int
    //   1671: astore #19
    //   1673: bipush #8
    //   1675: newarray int
    //   1677: astore #20
    //   1679: iconst_0
    //   1680: istore #21
    //   1682: iload #21
    //   1684: bipush #8
    //   1686: if_icmpge -> 1706
    //   1689: aload #20
    //   1691: iload #21
    //   1693: aload #8
    //   1695: iload #21
    //   1697: iaload
    //   1698: iastore
    //   1699: iinc #21, 1
    //   1702: iload_2
    //   1703: ifne -> 1682
    //   1706: iconst_0
    //   1707: istore #21
    //   1709: iload #21
    //   1711: bipush #64
    //   1713: if_icmpge -> 2204
    //   1716: iload #21
    //   1718: bipush #16
    //   1720: if_icmpge -> 1801
    //   1723: aload #19
    //   1725: iload #21
    //   1727: aload #9
    //   1729: iconst_4
    //   1730: iload #21
    //   1732: imul
    //   1733: baload
    //   1734: sipush #255
    //   1737: iand
    //   1738: bipush #24
    //   1740: ishl
    //   1741: aload #9
    //   1743: iconst_4
    //   1744: iload #21
    //   1746: imul
    //   1747: iconst_1
    //   1748: iadd
    //   1749: baload
    //   1750: sipush #255
    //   1753: iand
    //   1754: bipush #16
    //   1756: ishl
    //   1757: ior
    //   1758: aload #9
    //   1760: iconst_4
    //   1761: iload #21
    //   1763: imul
    //   1764: iconst_2
    //   1765: iadd
    //   1766: baload
    //   1767: sipush #255
    //   1770: iand
    //   1771: bipush #8
    //   1773: ishl
    //   1774: ior
    //   1775: aload #9
    //   1777: iconst_4
    //   1778: iload #21
    //   1780: imul
    //   1781: iconst_3
    //   1782: iadd
    //   1783: baload
    //   1784: sipush #255
    //   1787: iand
    //   1788: ior
    //   1789: iastore
    //   1790: iload_2
    //   1791: ifne -> 1944
    //   1794: goto -> 1801
    //   1797: invokestatic a : (Ljava/lang/Throwable;)Ljava/lang/Throwable;
    //   1800: athrow
    //   1801: aload #19
    //   1803: iload #21
    //   1805: aload #19
    //   1807: iload #21
    //   1809: iconst_2
    //   1810: isub
    //   1811: iaload
    //   1812: bipush #17
    //   1814: iushr
    //   1815: aload #19
    //   1817: iload #21
    //   1819: iconst_2
    //   1820: isub
    //   1821: iaload
    //   1822: bipush #15
    //   1824: ishl
    //   1825: ior
    //   1826: aload #19
    //   1828: iload #21
    //   1830: iconst_2
    //   1831: isub
    //   1832: iaload
    //   1833: bipush #19
    //   1835: iushr
    //   1836: aload #19
    //   1838: iload #21
    //   1840: iconst_2
    //   1841: isub
    //   1842: iaload
    //   1843: bipush #13
    //   1845: ishl
    //   1846: ior
    //   1847: ixor
    //   1848: aload #19
    //   1850: iload #21
    //   1852: iconst_2
    //   1853: isub
    //   1854: iaload
    //   1855: bipush #10
    //   1857: iushr
    //   1858: ixor
    //   1859: aload #19
    //   1861: iload #21
    //   1863: bipush #7
    //   1865: isub
    //   1866: iaload
    //   1867: iadd
    //   1868: aload #19
    //   1870: iload #21
    //   1872: bipush #15
    //   1874: isub
    //   1875: iaload
    //   1876: bipush #7
    //   1878: iushr
    //   1879: aload #19
    //   1881: iload #21
    //   1883: bipush #15
    //   1885: isub
    //   1886: iaload
    //   1887: bipush #25
    //   1889: ishl
    //   1890: ior
    //   1891: aload #19
    //   1893: iload #21
    //   1895: bipush #15
    //   1897: isub
    //   1898: iaload
    //   1899: bipush #18
    //   1901: iushr
    //   1902: aload #19
    //   1904: iload #21
    //   1906: bipush #15
    //   1908: isub
    //   1909: iaload
    //   1910: bipush #14
    //   1912: ishl
    //   1913: ior
    //   1914: ixor
    //   1915: aload #19
    //   1917: iload #21
    //   1919: bipush #15
    //   1921: isub
    //   1922: iaload
    //   1923: iconst_3
    //   1924: iushr
    //   1925: ixor
    //   1926: iadd
    //   1927: aload #19
    //   1929: iload #21
    //   1931: bipush #16
    //   1933: isub
    //   1934: iaload
    //   1935: iadd
    //   1936: iastore
    //   1937: goto -> 1944
    //   1940: invokestatic a : (Ljava/lang/Throwable;)Ljava/lang/Throwable;
    //   1943: athrow
    //   1944: aload #20
    //   1946: bipush #7
    //   1948: iaload
    //   1949: aload #20
    //   1951: iconst_4
    //   1952: iaload
    //   1953: bipush #6
    //   1955: iushr
    //   1956: aload #20
    //   1958: iconst_4
    //   1959: iaload
    //   1960: bipush #26
    //   1962: ishl
    //   1963: ior
    //   1964: aload #20
    //   1966: iconst_4
    //   1967: iaload
    //   1968: bipush #11
    //   1970: iushr
    //   1971: aload #20
    //   1973: iconst_4
    //   1974: iaload
    //   1975: bipush #21
    //   1977: ishl
    //   1978: ior
    //   1979: ixor
    //   1980: aload #20
    //   1982: iconst_4
    //   1983: iaload
    //   1984: bipush #25
    //   1986: iushr
    //   1987: aload #20
    //   1989: iconst_4
    //   1990: iaload
    //   1991: bipush #7
    //   1993: ishl
    //   1994: ior
    //   1995: ixor
    //   1996: iadd
    //   1997: aload #20
    //   1999: bipush #6
    //   2001: iaload
    //   2002: aload #20
    //   2004: iconst_4
    //   2005: iaload
    //   2006: aload #20
    //   2008: iconst_5
    //   2009: iaload
    //   2010: aload #20
    //   2012: bipush #6
    //   2014: iaload
    //   2015: ixor
    //   2016: iand
    //   2017: ixor
    //   2018: iadd
    //   2019: aload #6
    //   2021: iload #21
    //   2023: iaload
    //   2024: iadd
    //   2025: aload #19
    //   2027: iload #21
    //   2029: iaload
    //   2030: iadd
    //   2031: istore #22
    //   2033: aload #20
    //   2035: iconst_0
    //   2036: iaload
    //   2037: iconst_2
    //   2038: iushr
    //   2039: aload #20
    //   2041: iconst_0
    //   2042: iaload
    //   2043: bipush #30
    //   2045: ishl
    //   2046: ior
    //   2047: aload #20
    //   2049: iconst_0
    //   2050: iaload
    //   2051: bipush #13
    //   2053: iushr
    //   2054: aload #20
    //   2056: iconst_0
    //   2057: iaload
    //   2058: bipush #19
    //   2060: ishl
    //   2061: ior
    //   2062: ixor
    //   2063: aload #20
    //   2065: iconst_0
    //   2066: iaload
    //   2067: bipush #22
    //   2069: iushr
    //   2070: aload #20
    //   2072: iconst_0
    //   2073: iaload
    //   2074: bipush #10
    //   2076: ishl
    //   2077: ior
    //   2078: ixor
    //   2079: aload #20
    //   2081: iconst_0
    //   2082: iaload
    //   2083: aload #20
    //   2085: iconst_1
    //   2086: iaload
    //   2087: iand
    //   2088: aload #20
    //   2090: iconst_2
    //   2091: iaload
    //   2092: aload #20
    //   2094: iconst_0
    //   2095: iaload
    //   2096: aload #20
    //   2098: iconst_1
    //   2099: iaload
    //   2100: ior
    //   2101: iand
    //   2102: ior
    //   2103: iadd
    //   2104: istore #23
    //   2106: aload #20
    //   2108: iconst_3
    //   2109: dup2
    //   2110: iaload
    //   2111: iload #22
    //   2113: iadd
    //   2114: iastore
    //   2115: aload #20
    //   2117: bipush #7
    //   2119: iload #22
    //   2121: iload #23
    //   2123: iadd
    //   2124: iastore
    //   2125: aload #20
    //   2127: bipush #7
    //   2129: iaload
    //   2130: istore #22
    //   2132: aload #20
    //   2134: bipush #7
    //   2136: aload #20
    //   2138: bipush #6
    //   2140: iaload
    //   2141: iastore
    //   2142: aload #20
    //   2144: bipush #6
    //   2146: aload #20
    //   2148: iconst_5
    //   2149: iaload
    //   2150: iastore
    //   2151: aload #20
    //   2153: iconst_5
    //   2154: aload #20
    //   2156: iconst_4
    //   2157: iaload
    //   2158: iastore
    //   2159: aload #20
    //   2161: iconst_4
    //   2162: aload #20
    //   2164: iconst_3
    //   2165: iaload
    //   2166: iastore
    //   2167: aload #20
    //   2169: iconst_3
    //   2170: aload #20
    //   2172: iconst_2
    //   2173: iaload
    //   2174: iastore
    //   2175: aload #20
    //   2177: iconst_2
    //   2178: aload #20
    //   2180: iconst_1
    //   2181: iaload
    //   2182: iastore
    //   2183: aload #20
    //   2185: iconst_1
    //   2186: aload #20
    //   2188: iconst_0
    //   2189: iaload
    //   2190: iastore
    //   2191: aload #20
    //   2193: iconst_0
    //   2194: iload #22
    //   2196: iastore
    //   2197: iinc #21, 1
    //   2200: iload_2
    //   2201: ifne -> 1709
    //   2204: iconst_0
    //   2205: istore #21
    //   2207: iload #21
    //   2209: bipush #8
    //   2211: if_icmpge -> 2234
    //   2214: aload #8
    //   2216: iload #21
    //   2218: dup2
    //   2219: iaload
    //   2220: aload #20
    //   2222: iload #21
    //   2224: iaload
    //   2225: iadd
    //   2226: iastore
    //   2227: iinc #21, 1
    //   2230: iload_2
    //   2231: ifne -> 2207
    //   2234: iload #13
    //   2236: iload #18
    //   2238: iadd
    //   2239: istore #13
    //   2241: iload #17
    //   2243: iload #18
    //   2245: isub
    //   2246: istore #17
    //   2248: iconst_0
    //   2249: istore #12
    //   2251: iload #17
    //   2253: bipush #64
    //   2255: if_icmplt -> 2865
    //   2258: iconst_0
    //   2259: istore #19
    //   2261: iload #19
    //   2263: bipush #64
    //   2265: if_icmpge -> 2288
    //   2268: aload #10
    //   2270: iload #19
    //   2272: aload #5
    //   2274: iload #13
    //   2276: iload #19
    //   2278: iadd
    //   2279: baload
    //   2280: bastore
    //   2281: iinc #19, 1
    //   2284: iload_2
    //   2285: ifne -> 2261
    //   2288: bipush #64
    //   2290: newarray int
    //   2292: astore #19
    //   2294: bipush #8
    //   2296: newarray int
    //   2298: astore #20
    //   2300: iconst_0
    //   2301: istore #21
    //   2303: iload #21
    //   2305: bipush #8
    //   2307: if_icmpge -> 2327
    //   2310: aload #20
    //   2312: iload #21
    //   2314: aload #8
    //   2316: iload #21
    //   2318: iaload
    //   2319: iastore
    //   2320: iinc #21, 1
    //   2323: iload_2
    //   2324: ifne -> 2303
    //   2327: iconst_0
    //   2328: istore #21
    //   2330: iload #21
    //   2332: bipush #64
    //   2334: if_icmpge -> 2825
    //   2337: iload #21
    //   2339: bipush #16
    //   2341: if_icmpge -> 2422
    //   2344: aload #19
    //   2346: iload #21
    //   2348: aload #10
    //   2350: iconst_4
    //   2351: iload #21
    //   2353: imul
    //   2354: baload
    //   2355: sipush #255
    //   2358: iand
    //   2359: bipush #24
    //   2361: ishl
    //   2362: aload #10
    //   2364: iconst_4
    //   2365: iload #21
    //   2367: imul
    //   2368: iconst_1
    //   2369: iadd
    //   2370: baload
    //   2371: sipush #255
    //   2374: iand
    //   2375: bipush #16
    //   2377: ishl
    //   2378: ior
    //   2379: aload #10
    //   2381: iconst_4
    //   2382: iload #21
    //   2384: imul
    //   2385: iconst_2
    //   2386: iadd
    //   2387: baload
    //   2388: sipush #255
    //   2391: iand
    //   2392: bipush #8
    //   2394: ishl
    //   2395: ior
    //   2396: aload #10
    //   2398: iconst_4
    //   2399: iload #21
    //   2401: imul
    //   2402: iconst_3
    //   2403: iadd
    //   2404: baload
    //   2405: sipush #255
    //   2408: iand
    //   2409: ior
    //   2410: iastore
    //   2411: iload_2
    //   2412: ifne -> 2565
    //   2415: goto -> 2422
    //   2418: invokestatic a : (Ljava/lang/Throwable;)Ljava/lang/Throwable;
    //   2421: athrow
    //   2422: aload #19
    //   2424: iload #21
    //   2426: aload #19
    //   2428: iload #21
    //   2430: iconst_2
    //   2431: isub
    //   2432: iaload
    //   2433: bipush #17
    //   2435: iushr
    //   2436: aload #19
    //   2438: iload #21
    //   2440: iconst_2
    //   2441: isub
    //   2442: iaload
    //   2443: bipush #15
    //   2445: ishl
    //   2446: ior
    //   2447: aload #19
    //   2449: iload #21
    //   2451: iconst_2
    //   2452: isub
    //   2453: iaload
    //   2454: bipush #19
    //   2456: iushr
    //   2457: aload #19
    //   2459: iload #21
    //   2461: iconst_2
    //   2462: isub
    //   2463: iaload
    //   2464: bipush #13
    //   2466: ishl
    //   2467: ior
    //   2468: ixor
    //   2469: aload #19
    //   2471: iload #21
    //   2473: iconst_2
    //   2474: isub
    //   2475: iaload
    //   2476: bipush #10
    //   2478: iushr
    //   2479: ixor
    //   2480: aload #19
    //   2482: iload #21
    //   2484: bipush #7
    //   2486: isub
    //   2487: iaload
    //   2488: iadd
    //   2489: aload #19
    //   2491: iload #21
    //   2493: bipush #15
    //   2495: isub
    //   2496: iaload
    //   2497: bipush #7
    //   2499: iushr
    //   2500: aload #19
    //   2502: iload #21
    //   2504: bipush #15
    //   2506: isub
    //   2507: iaload
    //   2508: bipush #25
    //   2510: ishl
    //   2511: ior
    //   2512: aload #19
    //   2514: iload #21
    //   2516: bipush #15
    //   2518: isub
    //   2519: iaload
    //   2520: bipush #18
    //   2522: iushr
    //   2523: aload #19
    //   2525: iload #21
    //   2527: bipush #15
    //   2529: isub
    //   2530: iaload
    //   2531: bipush #14
    //   2533: ishl
    //   2534: ior
    //   2535: ixor
    //   2536: aload #19
    //   2538: iload #21
    //   2540: bipush #15
    //   2542: isub
    //   2543: iaload
    //   2544: iconst_3
    //   2545: iushr
    //   2546: ixor
    //   2547: iadd
    //   2548: aload #19
    //   2550: iload #21
    //   2552: bipush #16
    //   2554: isub
    //   2555: iaload
    //   2556: iadd
    //   2557: iastore
    //   2558: goto -> 2565
    //   2561: invokestatic a : (Ljava/lang/Throwable;)Ljava/lang/Throwable;
    //   2564: athrow
    //   2565: aload #20
    //   2567: bipush #7
    //   2569: iaload
    //   2570: aload #20
    //   2572: iconst_4
    //   2573: iaload
    //   2574: bipush #6
    //   2576: iushr
    //   2577: aload #20
    //   2579: iconst_4
    //   2580: iaload
    //   2581: bipush #26
    //   2583: ishl
    //   2584: ior
    //   2585: aload #20
    //   2587: iconst_4
    //   2588: iaload
    //   2589: bipush #11
    //   2591: iushr
    //   2592: aload #20
    //   2594: iconst_4
    //   2595: iaload
    //   2596: bipush #21
    //   2598: ishl
    //   2599: ior
    //   2600: ixor
    //   2601: aload #20
    //   2603: iconst_4
    //   2604: iaload
    //   2605: bipush #25
    //   2607: iushr
    //   2608: aload #20
    //   2610: iconst_4
    //   2611: iaload
    //   2612: bipush #7
    //   2614: ishl
    //   2615: ior
    //   2616: ixor
    //   2617: iadd
    //   2618: aload #20
    //   2620: bipush #6
    //   2622: iaload
    //   2623: aload #20
    //   2625: iconst_4
    //   2626: iaload
    //   2627: aload #20
    //   2629: iconst_5
    //   2630: iaload
    //   2631: aload #20
    //   2633: bipush #6
    //   2635: iaload
    //   2636: ixor
    //   2637: iand
    //   2638: ixor
    //   2639: iadd
    //   2640: aload #6
    //   2642: iload #21
    //   2644: iaload
    //   2645: iadd
    //   2646: aload #19
    //   2648: iload #21
    //   2650: iaload
    //   2651: iadd
    //   2652: istore #22
    //   2654: aload #20
    //   2656: iconst_0
    //   2657: iaload
    //   2658: iconst_2
    //   2659: iushr
    //   2660: aload #20
    //   2662: iconst_0
    //   2663: iaload
    //   2664: bipush #30
    //   2666: ishl
    //   2667: ior
    //   2668: aload #20
    //   2670: iconst_0
    //   2671: iaload
    //   2672: bipush #13
    //   2674: iushr
    //   2675: aload #20
    //   2677: iconst_0
    //   2678: iaload
    //   2679: bipush #19
    //   2681: ishl
    //   2682: ior
    //   2683: ixor
    //   2684: aload #20
    //   2686: iconst_0
    //   2687: iaload
    //   2688: bipush #22
    //   2690: iushr
    //   2691: aload #20
    //   2693: iconst_0
    //   2694: iaload
    //   2695: bipush #10
    //   2697: ishl
    //   2698: ior
    //   2699: ixor
    //   2700: aload #20
    //   2702: iconst_0
    //   2703: iaload
    //   2704: aload #20
    //   2706: iconst_1
    //   2707: iaload
    //   2708: iand
    //   2709: aload #20
    //   2711: iconst_2
    //   2712: iaload
    //   2713: aload #20
    //   2715: iconst_0
    //   2716: iaload
    //   2717: aload #20
    //   2719: iconst_1
    //   2720: iaload
    //   2721: ior
    //   2722: iand
    //   2723: ior
    //   2724: iadd
    //   2725: istore #23
    //   2727: aload #20
    //   2729: iconst_3
    //   2730: dup2
    //   2731: iaload
    //   2732: iload #22
    //   2734: iadd
    //   2735: iastore
    //   2736: aload #20
    //   2738: bipush #7
    //   2740: iload #22
    //   2742: iload #23
    //   2744: iadd
    //   2745: iastore
    //   2746: aload #20
    //   2748: bipush #7
    //   2750: iaload
    //   2751: istore #22
    //   2753: aload #20
    //   2755: bipush #7
    //   2757: aload #20
    //   2759: bipush #6
    //   2761: iaload
    //   2762: iastore
    //   2763: aload #20
    //   2765: bipush #6
    //   2767: aload #20
    //   2769: iconst_5
    //   2770: iaload
    //   2771: iastore
    //   2772: aload #20
    //   2774: iconst_5
    //   2775: aload #20
    //   2777: iconst_4
    //   2778: iaload
    //   2779: iastore
    //   2780: aload #20
    //   2782: iconst_4
    //   2783: aload #20
    //   2785: iconst_3
    //   2786: iaload
    //   2787: iastore
    //   2788: aload #20
    //   2790: iconst_3
    //   2791: aload #20
    //   2793: iconst_2
    //   2794: iaload
    //   2795: iastore
    //   2796: aload #20
    //   2798: iconst_2
    //   2799: aload #20
    //   2801: iconst_1
    //   2802: iaload
    //   2803: iastore
    //   2804: aload #20
    //   2806: iconst_1
    //   2807: aload #20
    //   2809: iconst_0
    //   2810: iaload
    //   2811: iastore
    //   2812: aload #20
    //   2814: iconst_0
    //   2815: iload #22
    //   2817: iastore
    //   2818: iinc #21, 1
    //   2821: iload_2
    //   2822: ifne -> 2330
    //   2825: iconst_0
    //   2826: istore #21
    //   2828: iload #21
    //   2830: bipush #8
    //   2832: if_icmpge -> 2855
    //   2835: aload #8
    //   2837: iload #21
    //   2839: dup2
    //   2840: iaload
    //   2841: aload #20
    //   2843: iload #21
    //   2845: iaload
    //   2846: iadd
    //   2847: iastore
    //   2848: iinc #21, 1
    //   2851: iload_2
    //   2852: ifne -> 2828
    //   2855: iinc #13, 64
    //   2858: iinc #17, -64
    //   2861: iload_2
    //   2862: ifne -> 2251
    //   2865: iload #17
    //   2867: ifle -> 2903
    //   2870: iconst_0
    //   2871: istore #19
    //   2873: iload #19
    //   2875: iload #17
    //   2877: if_icmpge -> 2903
    //   2880: aload #9
    //   2882: iload #12
    //   2884: iload #19
    //   2886: iadd
    //   2887: aload #5
    //   2889: iload #13
    //   2891: iload #19
    //   2893: iadd
    //   2894: baload
    //   2895: bastore
    //   2896: iinc #19, 1
    //   2899: iload_2
    //   2900: ifne -> 2873
    //   2903: bipush #8
    //   2905: newarray byte
    //   2907: astore #19
    //   2909: aload #19
    //   2911: iconst_0
    //   2912: iload #14
    //   2914: bipush #24
    //   2916: iushr
    //   2917: i2b
    //   2918: bastore
    //   2919: aload #19
    //   2921: iconst_1
    //   2922: iload #14
    //   2924: bipush #16
    //   2926: iushr
    //   2927: i2b
    //   2928: bastore
    //   2929: aload #19
    //   2931: iconst_2
    //   2932: iload #14
    //   2934: bipush #8
    //   2936: iushr
    //   2937: i2b
    //   2938: bastore
    //   2939: aload #19
    //   2941: iconst_3
    //   2942: iload #14
    //   2944: i2b
    //   2945: bastore
    //   2946: aload #19
    //   2948: iconst_4
    //   2949: iload #15
    //   2951: bipush #24
    //   2953: iushr
    //   2954: i2b
    //   2955: bastore
    //   2956: aload #19
    //   2958: iconst_5
    //   2959: iload #15
    //   2961: bipush #16
    //   2963: iushr
    //   2964: i2b
    //   2965: bastore
    //   2966: aload #19
    //   2968: bipush #6
    //   2970: iload #15
    //   2972: bipush #8
    //   2974: iushr
    //   2975: i2b
    //   2976: bastore
    //   2977: aload #19
    //   2979: bipush #7
    //   2981: iload #15
    //   2983: i2b
    //   2984: bastore
    //   2985: bipush #8
    //   2987: istore #11
    //   2989: aload #7
    //   2991: iconst_0
    //   2992: iaload
    //   2993: bipush #63
    //   2995: iand
    //   2996: istore #12
    //   2998: bipush #64
    //   3000: iload #12
    //   3002: isub
    //   3003: istore #18
    //   3005: aload #7
    //   3007: iconst_0
    //   3008: dup2
    //   3009: iaload
    //   3010: iload #11
    //   3012: iadd
    //   3013: iastore
    //   3014: aload #7
    //   3016: iconst_0
    //   3017: dup2
    //   3018: iaload
    //   3019: iconst_m1
    //   3020: iand
    //   3021: iastore
    //   3022: aload #7
    //   3024: iconst_0
    //   3025: iaload
    //   3026: iload #11
    //   3028: if_icmpge -> 3046
    //   3031: aload #7
    //   3033: iconst_1
    //   3034: dup2
    //   3035: iaload
    //   3036: iconst_1
    //   3037: iadd
    //   3038: iastore
    //   3039: goto -> 3046
    //   3042: invokestatic a : (Ljava/lang/Throwable;)Ljava/lang/Throwable;
    //   3045: athrow
    //   3046: iload #12
    //   3048: ifle -> 3662
    //   3051: iload #11
    //   3053: iload #18
    //   3055: if_icmplt -> 3662
    //   3058: goto -> 3065
    //   3061: invokestatic a : (Ljava/lang/Throwable;)Ljava/lang/Throwable;
    //   3064: athrow
    //   3065: iconst_0
    //   3066: istore #20
    //   3068: iload #20
    //   3070: iload #18
    //   3072: if_icmpge -> 3095
    //   3075: aload #9
    //   3077: iload #12
    //   3079: iload #20
    //   3081: iadd
    //   3082: aload #19
    //   3084: iload #20
    //   3086: baload
    //   3087: bastore
    //   3088: iinc #20, 1
    //   3091: iload_2
    //   3092: ifne -> 3068
    //   3095: bipush #64
    //   3097: newarray int
    //   3099: astore #20
    //   3101: bipush #8
    //   3103: newarray int
    //   3105: astore #21
    //   3107: iconst_0
    //   3108: istore #22
    //   3110: iload #22
    //   3112: bipush #8
    //   3114: if_icmpge -> 3134
    //   3117: aload #21
    //   3119: iload #22
    //   3121: aload #8
    //   3123: iload #22
    //   3125: iaload
    //   3126: iastore
    //   3127: iinc #22, 1
    //   3130: iload_2
    //   3131: ifne -> 3110
    //   3134: iconst_0
    //   3135: istore #22
    //   3137: iload #22
    //   3139: bipush #64
    //   3141: if_icmpge -> 3632
    //   3144: iload #22
    //   3146: bipush #16
    //   3148: if_icmpge -> 3229
    //   3151: aload #20
    //   3153: iload #22
    //   3155: aload #9
    //   3157: iconst_4
    //   3158: iload #22
    //   3160: imul
    //   3161: baload
    //   3162: sipush #255
    //   3165: iand
    //   3166: bipush #24
    //   3168: ishl
    //   3169: aload #9
    //   3171: iconst_4
    //   3172: iload #22
    //   3174: imul
    //   3175: iconst_1
    //   3176: iadd
    //   3177: baload
    //   3178: sipush #255
    //   3181: iand
    //   3182: bipush #16
    //   3184: ishl
    //   3185: ior
    //   3186: aload #9
    //   3188: iconst_4
    //   3189: iload #22
    //   3191: imul
    //   3192: iconst_2
    //   3193: iadd
    //   3194: baload
    //   3195: sipush #255
    //   3198: iand
    //   3199: bipush #8
    //   3201: ishl
    //   3202: ior
    //   3203: aload #9
    //   3205: iconst_4
    //   3206: iload #22
    //   3208: imul
    //   3209: iconst_3
    //   3210: iadd
    //   3211: baload
    //   3212: sipush #255
    //   3215: iand
    //   3216: ior
    //   3217: iastore
    //   3218: iload_2
    //   3219: ifne -> 3372
    //   3222: goto -> 3229
    //   3225: invokestatic a : (Ljava/lang/Throwable;)Ljava/lang/Throwable;
    //   3228: athrow
    //   3229: aload #20
    //   3231: iload #22
    //   3233: aload #20
    //   3235: iload #22
    //   3237: iconst_2
    //   3238: isub
    //   3239: iaload
    //   3240: bipush #17
    //   3242: iushr
    //   3243: aload #20
    //   3245: iload #22
    //   3247: iconst_2
    //   3248: isub
    //   3249: iaload
    //   3250: bipush #15
    //   3252: ishl
    //   3253: ior
    //   3254: aload #20
    //   3256: iload #22
    //   3258: iconst_2
    //   3259: isub
    //   3260: iaload
    //   3261: bipush #19
    //   3263: iushr
    //   3264: aload #20
    //   3266: iload #22
    //   3268: iconst_2
    //   3269: isub
    //   3270: iaload
    //   3271: bipush #13
    //   3273: ishl
    //   3274: ior
    //   3275: ixor
    //   3276: aload #20
    //   3278: iload #22
    //   3280: iconst_2
    //   3281: isub
    //   3282: iaload
    //   3283: bipush #10
    //   3285: iushr
    //   3286: ixor
    //   3287: aload #20
    //   3289: iload #22
    //   3291: bipush #7
    //   3293: isub
    //   3294: iaload
    //   3295: iadd
    //   3296: aload #20
    //   3298: iload #22
    //   3300: bipush #15
    //   3302: isub
    //   3303: iaload
    //   3304: bipush #7
    //   3306: iushr
    //   3307: aload #20
    //   3309: iload #22
    //   3311: bipush #15
    //   3313: isub
    //   3314: iaload
    //   3315: bipush #25
    //   3317: ishl
    //   3318: ior
    //   3319: aload #20
    //   3321: iload #22
    //   3323: bipush #15
    //   3325: isub
    //   3326: iaload
    //   3327: bipush #18
    //   3329: iushr
    //   3330: aload #20
    //   3332: iload #22
    //   3334: bipush #15
    //   3336: isub
    //   3337: iaload
    //   3338: bipush #14
    //   3340: ishl
    //   3341: ior
    //   3342: ixor
    //   3343: aload #20
    //   3345: iload #22
    //   3347: bipush #15
    //   3349: isub
    //   3350: iaload
    //   3351: iconst_3
    //   3352: iushr
    //   3353: ixor
    //   3354: iadd
    //   3355: aload #20
    //   3357: iload #22
    //   3359: bipush #16
    //   3361: isub
    //   3362: iaload
    //   3363: iadd
    //   3364: iastore
    //   3365: goto -> 3372
    //   3368: invokestatic a : (Ljava/lang/Throwable;)Ljava/lang/Throwable;
    //   3371: athrow
    //   3372: aload #21
    //   3374: bipush #7
    //   3376: iaload
    //   3377: aload #21
    //   3379: iconst_4
    //   3380: iaload
    //   3381: bipush #6
    //   3383: iushr
    //   3384: aload #21
    //   3386: iconst_4
    //   3387: iaload
    //   3388: bipush #26
    //   3390: ishl
    //   3391: ior
    //   3392: aload #21
    //   3394: iconst_4
    //   3395: iaload
    //   3396: bipush #11
    //   3398: iushr
    //   3399: aload #21
    //   3401: iconst_4
    //   3402: iaload
    //   3403: bipush #21
    //   3405: ishl
    //   3406: ior
    //   3407: ixor
    //   3408: aload #21
    //   3410: iconst_4
    //   3411: iaload
    //   3412: bipush #25
    //   3414: iushr
    //   3415: aload #21
    //   3417: iconst_4
    //   3418: iaload
    //   3419: bipush #7
    //   3421: ishl
    //   3422: ior
    //   3423: ixor
    //   3424: iadd
    //   3425: aload #21
    //   3427: bipush #6
    //   3429: iaload
    //   3430: aload #21
    //   3432: iconst_4
    //   3433: iaload
    //   3434: aload #21
    //   3436: iconst_5
    //   3437: iaload
    //   3438: aload #21
    //   3440: bipush #6
    //   3442: iaload
    //   3443: ixor
    //   3444: iand
    //   3445: ixor
    //   3446: iadd
    //   3447: aload #6
    //   3449: iload #22
    //   3451: iaload
    //   3452: iadd
    //   3453: aload #20
    //   3455: iload #22
    //   3457: iaload
    //   3458: iadd
    //   3459: istore #23
    //   3461: aload #21
    //   3463: iconst_0
    //   3464: iaload
    //   3465: iconst_2
    //   3466: iushr
    //   3467: aload #21
    //   3469: iconst_0
    //   3470: iaload
    //   3471: bipush #30
    //   3473: ishl
    //   3474: ior
    //   3475: aload #21
    //   3477: iconst_0
    //   3478: iaload
    //   3479: bipush #13
    //   3481: iushr
    //   3482: aload #21
    //   3484: iconst_0
    //   3485: iaload
    //   3486: bipush #19
    //   3488: ishl
    //   3489: ior
    //   3490: ixor
    //   3491: aload #21
    //   3493: iconst_0
    //   3494: iaload
    //   3495: bipush #22
    //   3497: iushr
    //   3498: aload #21
    //   3500: iconst_0
    //   3501: iaload
    //   3502: bipush #10
    //   3504: ishl
    //   3505: ior
    //   3506: ixor
    //   3507: aload #21
    //   3509: iconst_0
    //   3510: iaload
    //   3511: aload #21
    //   3513: iconst_1
    //   3514: iaload
    //   3515: iand
    //   3516: aload #21
    //   3518: iconst_2
    //   3519: iaload
    //   3520: aload #21
    //   3522: iconst_0
    //   3523: iaload
    //   3524: aload #21
    //   3526: iconst_1
    //   3527: iaload
    //   3528: ior
    //   3529: iand
    //   3530: ior
    //   3531: iadd
    //   3532: istore #24
    //   3534: aload #21
    //   3536: iconst_3
    //   3537: dup2
    //   3538: iaload
    //   3539: iload #23
    //   3541: iadd
    //   3542: iastore
    //   3543: aload #21
    //   3545: bipush #7
    //   3547: iload #23
    //   3549: iload #24
    //   3551: iadd
    //   3552: iastore
    //   3553: aload #21
    //   3555: bipush #7
    //   3557: iaload
    //   3558: istore #23
    //   3560: aload #21
    //   3562: bipush #7
    //   3564: aload #21
    //   3566: bipush #6
    //   3568: iaload
    //   3569: iastore
    //   3570: aload #21
    //   3572: bipush #6
    //   3574: aload #21
    //   3576: iconst_5
    //   3577: iaload
    //   3578: iastore
    //   3579: aload #21
    //   3581: iconst_5
    //   3582: aload #21
    //   3584: iconst_4
    //   3585: iaload
    //   3586: iastore
    //   3587: aload #21
    //   3589: iconst_4
    //   3590: aload #21
    //   3592: iconst_3
    //   3593: iaload
    //   3594: iastore
    //   3595: aload #21
    //   3597: iconst_3
    //   3598: aload #21
    //   3600: iconst_2
    //   3601: iaload
    //   3602: iastore
    //   3603: aload #21
    //   3605: iconst_2
    //   3606: aload #21
    //   3608: iconst_1
    //   3609: iaload
    //   3610: iastore
    //   3611: aload #21
    //   3613: iconst_1
    //   3614: aload #21
    //   3616: iconst_0
    //   3617: iaload
    //   3618: iastore
    //   3619: aload #21
    //   3621: iconst_0
    //   3622: iload #23
    //   3624: iastore
    //   3625: iinc #22, 1
    //   3628: iload_2
    //   3629: ifne -> 3137
    //   3632: iconst_0
    //   3633: istore #22
    //   3635: iload #22
    //   3637: bipush #8
    //   3639: if_icmpge -> 3662
    //   3642: aload #8
    //   3644: iload #22
    //   3646: dup2
    //   3647: iaload
    //   3648: aload #21
    //   3650: iload #22
    //   3652: iaload
    //   3653: iadd
    //   3654: iastore
    //   3655: iinc #22, 1
    //   3658: iload_2
    //   3659: ifne -> 3635
    //   3662: bipush #32
    //   3664: newarray byte
    //   3666: astore #4
    //   3668: aload #4
    //   3670: iconst_0
    //   3671: aload #8
    //   3673: iconst_0
    //   3674: iaload
    //   3675: bipush #24
    //   3677: iushr
    //   3678: i2b
    //   3679: bastore
    //   3680: aload #4
    //   3682: iconst_1
    //   3683: aload #8
    //   3685: iconst_0
    //   3686: iaload
    //   3687: bipush #16
    //   3689: iushr
    //   3690: i2b
    //   3691: bastore
    //   3692: aload #4
    //   3694: iconst_2
    //   3695: aload #8
    //   3697: iconst_0
    //   3698: iaload
    //   3699: bipush #8
    //   3701: iushr
    //   3702: i2b
    //   3703: bastore
    //   3704: aload #4
    //   3706: iconst_3
    //   3707: aload #8
    //   3709: iconst_0
    //   3710: iaload
    //   3711: i2b
    //   3712: bastore
    //   3713: aload #4
    //   3715: iconst_4
    //   3716: aload #8
    //   3718: iconst_1
    //   3719: iaload
    //   3720: bipush #24
    //   3722: iushr
    //   3723: i2b
    //   3724: bastore
    //   3725: aload #4
    //   3727: iconst_5
    //   3728: aload #8
    //   3730: iconst_1
    //   3731: iaload
    //   3732: bipush #16
    //   3734: iushr
    //   3735: i2b
    //   3736: bastore
    //   3737: aload #4
    //   3739: bipush #6
    //   3741: aload #8
    //   3743: iconst_1
    //   3744: iaload
    //   3745: bipush #8
    //   3747: iushr
    //   3748: i2b
    //   3749: bastore
    //   3750: aload #4
    //   3752: bipush #7
    //   3754: aload #8
    //   3756: iconst_1
    //   3757: iaload
    //   3758: i2b
    //   3759: bastore
    //   3760: aload #4
    //   3762: bipush #8
    //   3764: aload #8
    //   3766: iconst_2
    //   3767: iaload
    //   3768: bipush #24
    //   3770: iushr
    //   3771: i2b
    //   3772: bastore
    //   3773: aload #4
    //   3775: bipush #9
    //   3777: aload #8
    //   3779: iconst_2
    //   3780: iaload
    //   3781: bipush #16
    //   3783: iushr
    //   3784: i2b
    //   3785: bastore
    //   3786: aload #4
    //   3788: bipush #10
    //   3790: aload #8
    //   3792: iconst_2
    //   3793: iaload
    //   3794: bipush #8
    //   3796: iushr
    //   3797: i2b
    //   3798: bastore
    //   3799: aload #4
    //   3801: bipush #11
    //   3803: aload #8
    //   3805: iconst_2
    //   3806: iaload
    //   3807: i2b
    //   3808: bastore
    //   3809: aload #4
    //   3811: bipush #12
    //   3813: aload #8
    //   3815: iconst_3
    //   3816: iaload
    //   3817: bipush #24
    //   3819: iushr
    //   3820: i2b
    //   3821: bastore
    //   3822: aload #4
    //   3824: bipush #13
    //   3826: aload #8
    //   3828: iconst_3
    //   3829: iaload
    //   3830: bipush #16
    //   3832: iushr
    //   3833: i2b
    //   3834: bastore
    //   3835: aload #4
    //   3837: bipush #14
    //   3839: aload #8
    //   3841: iconst_3
    //   3842: iaload
    //   3843: bipush #8
    //   3845: iushr
    //   3846: i2b
    //   3847: bastore
    //   3848: aload #4
    //   3850: bipush #15
    //   3852: aload #8
    //   3854: iconst_3
    //   3855: iaload
    //   3856: i2b
    //   3857: bastore
    //   3858: aload #4
    //   3860: bipush #16
    //   3862: aload #8
    //   3864: iconst_4
    //   3865: iaload
    //   3866: bipush #24
    //   3868: iushr
    //   3869: i2b
    //   3870: bastore
    //   3871: aload #4
    //   3873: bipush #17
    //   3875: aload #8
    //   3877: iconst_4
    //   3878: iaload
    //   3879: bipush #16
    //   3881: iushr
    //   3882: i2b
    //   3883: bastore
    //   3884: aload #4
    //   3886: bipush #18
    //   3888: aload #8
    //   3890: iconst_4
    //   3891: iaload
    //   3892: bipush #8
    //   3894: iushr
    //   3895: i2b
    //   3896: bastore
    //   3897: aload #4
    //   3899: bipush #19
    //   3901: aload #8
    //   3903: iconst_4
    //   3904: iaload
    //   3905: i2b
    //   3906: bastore
    //   3907: aload #4
    //   3909: bipush #20
    //   3911: aload #8
    //   3913: iconst_5
    //   3914: iaload
    //   3915: bipush #24
    //   3917: iushr
    //   3918: i2b
    //   3919: bastore
    //   3920: aload #4
    //   3922: bipush #21
    //   3924: aload #8
    //   3926: iconst_5
    //   3927: iaload
    //   3928: bipush #16
    //   3930: iushr
    //   3931: i2b
    //   3932: bastore
    //   3933: aload #4
    //   3935: bipush #22
    //   3937: aload #8
    //   3939: iconst_5
    //   3940: iaload
    //   3941: bipush #8
    //   3943: iushr
    //   3944: i2b
    //   3945: bastore
    //   3946: aload #4
    //   3948: bipush #23
    //   3950: aload #8
    //   3952: iconst_5
    //   3953: iaload
    //   3954: i2b
    //   3955: bastore
    //   3956: aload #4
    //   3958: bipush #24
    //   3960: aload #8
    //   3962: bipush #6
    //   3964: iaload
    //   3965: bipush #24
    //   3967: iushr
    //   3968: i2b
    //   3969: bastore
    //   3970: aload #4
    //   3972: bipush #25
    //   3974: aload #8
    //   3976: bipush #6
    //   3978: iaload
    //   3979: bipush #16
    //   3981: iushr
    //   3982: i2b
    //   3983: bastore
    //   3984: aload #4
    //   3986: bipush #26
    //   3988: aload #8
    //   3990: bipush #6
    //   3992: iaload
    //   3993: bipush #8
    //   3995: iushr
    //   3996: i2b
    //   3997: bastore
    //   3998: aload #4
    //   4000: bipush #27
    //   4002: aload #8
    //   4004: bipush #6
    //   4006: iaload
    //   4007: i2b
    //   4008: bastore
    //   4009: aload #4
    //   4011: bipush #28
    //   4013: aload #8
    //   4015: bipush #7
    //   4017: iaload
    //   4018: bipush #24
    //   4020: iushr
    //   4021: i2b
    //   4022: bastore
    //   4023: aload #4
    //   4025: bipush #29
    //   4027: aload #8
    //   4029: bipush #7
    //   4031: iaload
    //   4032: bipush #16
    //   4034: iushr
    //   4035: i2b
    //   4036: bastore
    //   4037: aload #4
    //   4039: bipush #30
    //   4041: aload #8
    //   4043: bipush #7
    //   4045: iaload
    //   4046: bipush #8
    //   4048: iushr
    //   4049: i2b
    //   4050: bastore
    //   4051: aload #4
    //   4053: bipush #31
    //   4055: aload #8
    //   4057: bipush #7
    //   4059: iaload
    //   4060: i2b
    //   4061: bastore
    //   4062: new java/math/BigInteger
    //   4065: dup
    //   4066: aload #4
    //   4068: invokespecial <init> : ([B)V
    //   4071: invokevirtual abs : ()Ljava/math/BigInteger;
    //   4074: putstatic burp/Zttq.Zh : Ljava/lang/Object;
    //   4077: getstatic burp/Zlot.ZJ : Ljava/lang/Object;
    //   4080: checkcast java/math/BigInteger
    //   4083: getstatic burp/Zb0s.Zv : Ljava/lang/Object;
    //   4086: checkcast java/math/BigInteger
    //   4089: invokevirtual add : (Ljava/math/BigInteger;)Ljava/math/BigInteger;
    //   4092: putstatic burp/Zr8h.ZH : Ljava/lang/Object;
    //   4095: getstatic burp/Zbqo.Zb : Ljava/lang/Object;
    //   4098: checkcast java/math/BigInteger
    //   4101: invokevirtual toByteArray : ()[B
    //   4104: astore_3
    //   4105: iconst_0
    //   4106: istore #5
    //   4108: iconst_0
    //   4109: istore #6
    //   4111: iload #6
    //   4113: aload_3
    //   4114: arraylength
    //   4115: if_icmpge -> 4260
    //   4118: aload_3
    //   4119: iload #6
    //   4121: baload
    //   4122: istore #7
    //   4124: iload #7
    //   4126: bipush #48
    //   4128: if_icmplt -> 4145
    //   4131: iload #7
    //   4133: bipush #57
    //   4135: if_icmple -> 4243
    //   4138: goto -> 4145
    //   4141: invokestatic a : (Ljava/lang/Throwable;)Ljava/lang/Throwable;
    //   4144: athrow
    //   4145: iload #7
    //   4147: bipush #65
    //   4149: if_icmplt -> 4173
    //   4152: goto -> 4159
    //   4155: invokestatic a : (Ljava/lang/Throwable;)Ljava/lang/Throwable;
    //   4158: athrow
    //   4159: iload #7
    //   4161: bipush #90
    //   4163: if_icmple -> 4243
    //   4166: goto -> 4173
    //   4169: invokestatic a : (Ljava/lang/Throwable;)Ljava/lang/Throwable;
    //   4172: athrow
    //   4173: iload #7
    //   4175: bipush #97
    //   4177: if_icmplt -> 4201
    //   4180: goto -> 4187
    //   4183: invokestatic a : (Ljava/lang/Throwable;)Ljava/lang/Throwable;
    //   4186: athrow
    //   4187: iload #7
    //   4189: bipush #122
    //   4191: if_icmple -> 4243
    //   4194: goto -> 4201
    //   4197: invokestatic a : (Ljava/lang/Throwable;)Ljava/lang/Throwable;
    //   4200: athrow
    //   4201: iload #7
    //   4203: bipush #43
    //   4205: if_icmpeq -> 4243
    //   4208: goto -> 4215
    //   4211: invokestatic a : (Ljava/lang/Throwable;)Ljava/lang/Throwable;
    //   4214: athrow
    //   4215: iload #7
    //   4217: bipush #47
    //   4219: if_icmpeq -> 4243
    //   4222: goto -> 4229
    //   4225: invokestatic a : (Ljava/lang/Throwable;)Ljava/lang/Throwable;
    //   4228: athrow
    //   4229: iload #7
    //   4231: bipush #61
    //   4233: if_icmpne -> 4253
    //   4236: goto -> 4243
    //   4239: invokestatic a : (Ljava/lang/Throwable;)Ljava/lang/Throwable;
    //   4242: athrow
    //   4243: iinc #5, 1
    //   4246: goto -> 4253
    //   4249: invokestatic a : (Ljava/lang/Throwable;)Ljava/lang/Throwable;
    //   4252: athrow
    //   4253: iinc #6, 1
    //   4256: iload_2
    //   4257: ifne -> 4111
    //   4260: iload #5
    //   4262: newarray byte
    //   4264: astore #6
    //   4266: iconst_0
    //   4267: istore #7
    //   4269: iconst_0
    //   4270: istore #8
    //   4272: iload #8
    //   4274: aload_3
    //   4275: arraylength
    //   4276: if_icmpge -> 4428
    //   4279: aload_3
    //   4280: iload #8
    //   4282: baload
    //   4283: istore #9
    //   4285: iload #9
    //   4287: bipush #48
    //   4289: if_icmplt -> 4306
    //   4292: iload #9
    //   4294: bipush #57
    //   4296: if_icmple -> 4404
    //   4299: goto -> 4306
    //   4302: invokestatic a : (Ljava/lang/Throwable;)Ljava/lang/Throwable;
    //   4305: athrow
    //   4306: iload #9
    //   4308: bipush #65
    //   4310: if_icmplt -> 4334
    //   4313: goto -> 4320
    //   4316: invokestatic a : (Ljava/lang/Throwable;)Ljava/lang/Throwable;
    //   4319: athrow
    //   4320: iload #9
    //   4322: bipush #90
    //   4324: if_icmple -> 4404
    //   4327: goto -> 4334
    //   4330: invokestatic a : (Ljava/lang/Throwable;)Ljava/lang/Throwable;
    //   4333: athrow
    //   4334: iload #9
    //   4336: bipush #97
    //   4338: if_icmplt -> 4362
    //   4341: goto -> 4348
    //   4344: invokestatic a : (Ljava/lang/Throwable;)Ljava/lang/Throwable;
    //   4347: athrow
    //   4348: iload #9
    //   4350: bipush #122
    //   4352: if_icmple -> 4404
    //   4355: goto -> 4362
    //   4358: invokestatic a : (Ljava/lang/Throwable;)Ljava/lang/Throwable;
    //   4361: athrow
    //   4362: iload #9
    //   4364: bipush #43
    //   4366: if_icmpeq -> 4404
    //   4369: goto -> 4376
    //   4372: invokestatic a : (Ljava/lang/Throwable;)Ljava/lang/Throwable;
    //   4375: athrow
    //   4376: iload #9
    //   4378: bipush #47
    //   4380: if_icmpeq -> 4404
    //   4383: goto -> 4390
    //   4386: invokestatic a : (Ljava/lang/Throwable;)Ljava/lang/Throwable;
    //   4389: athrow
    //   4390: iload #9
    //   4392: bipush #61
    //   4394: if_icmpne -> 4421
    //   4397: goto -> 4404
    //   4400: invokestatic a : (Ljava/lang/Throwable;)Ljava/lang/Throwable;
    //   4403: athrow
    //   4404: aload #6
    //   4406: iload #7
    //   4408: iload #9
    //   4410: bastore
    //   4411: iinc #7, 1
    //   4414: goto -> 4421
    //   4417: invokestatic a : (Ljava/lang/Throwable;)Ljava/lang/Throwable;
    //   4420: athrow
    //   4421: iinc #8, 1
    //   4424: iload_2
    //   4425: ifne -> 4272
    //   4428: aload #6
    //   4430: astore #4
    //   4432: aload #4
    //   4434: astore_3
    //   4435: aload_3
    //   4436: arraylength
    //   4437: istore #5
    //   4439: aload_3
    //   4440: iload #5
    //   4442: iconst_1
    //   4443: isub
    //   4444: baload
    //   4445: bipush #61
    //   4447: if_icmpne -> 4457
    //   4450: iinc #5, -1
    //   4453: iload_2
    //   4454: ifne -> 4439
    //   4457: iload #5
    //   4459: aload_3
    //   4460: arraylength
    //   4461: iconst_4
    //   4462: idiv
    //   4463: isub
    //   4464: newarray byte
    //   4466: astore #6
    //   4468: iconst_0
    //   4469: istore #7
    //   4471: iload #7
    //   4473: aload_3
    //   4474: arraylength
    //   4475: if_icmpge -> 4737
    //   4478: aload_3
    //   4479: iload #7
    //   4481: baload
    //   4482: bipush #61
    //   4484: if_icmpne -> 4503
    //   4487: aload_3
    //   4488: iload #7
    //   4490: iconst_0
    //   4491: bastore
    //   4492: iload_2
    //   4493: ifne -> 4730
    //   4496: goto -> 4503
    //   4499: invokestatic a : (Ljava/lang/Throwable;)Ljava/lang/Throwable;
    //   4502: athrow
    //   4503: aload_3
    //   4504: iload #7
    //   4506: baload
    //   4507: bipush #47
    //   4509: if_icmpne -> 4536
    //   4512: goto -> 4519
    //   4515: invokestatic a : (Ljava/lang/Throwable;)Ljava/lang/Throwable;
    //   4518: athrow
    //   4519: aload_3
    //   4520: iload #7
    //   4522: bipush #63
    //   4524: bastore
    //   4525: iload_2
    //   4526: ifne -> 4730
    //   4529: goto -> 4536
    //   4532: invokestatic a : (Ljava/lang/Throwable;)Ljava/lang/Throwable;
    //   4535: athrow
    //   4536: aload_3
    //   4537: iload #7
    //   4539: baload
    //   4540: bipush #43
    //   4542: if_icmpne -> 4569
    //   4545: goto -> 4552
    //   4548: invokestatic a : (Ljava/lang/Throwable;)Ljava/lang/Throwable;
    //   4551: athrow
    //   4552: aload_3
    //   4553: iload #7
    //   4555: bipush #62
    //   4557: bastore
    //   4558: iload_2
    //   4559: ifne -> 4730
    //   4562: goto -> 4569
    //   4565: invokestatic a : (Ljava/lang/Throwable;)Ljava/lang/Throwable;
    //   4568: athrow
    //   4569: aload_3
    //   4570: iload #7
    //   4572: baload
    //   4573: bipush #48
    //   4575: if_icmplt -> 4624
    //   4578: goto -> 4585
    //   4581: invokestatic a : (Ljava/lang/Throwable;)Ljava/lang/Throwable;
    //   4584: athrow
    //   4585: aload_3
    //   4586: iload #7
    //   4588: baload
    //   4589: bipush #57
    //   4591: if_icmpgt -> 4624
    //   4594: goto -> 4601
    //   4597: invokestatic a : (Ljava/lang/Throwable;)Ljava/lang/Throwable;
    //   4600: athrow
    //   4601: aload_3
    //   4602: iload #7
    //   4604: aload_3
    //   4605: iload #7
    //   4607: baload
    //   4608: bipush #-4
    //   4610: isub
    //   4611: i2b
    //   4612: bastore
    //   4613: iload_2
    //   4614: ifne -> 4730
    //   4617: goto -> 4624
    //   4620: invokestatic a : (Ljava/lang/Throwable;)Ljava/lang/Throwable;
    //   4623: athrow
    //   4624: aload_3
    //   4625: iload #7
    //   4627: baload
    //   4628: bipush #97
    //   4630: if_icmplt -> 4679
    //   4633: goto -> 4640
    //   4636: invokestatic a : (Ljava/lang/Throwable;)Ljava/lang/Throwable;
    //   4639: athrow
    //   4640: aload_3
    //   4641: iload #7
    //   4643: baload
    //   4644: bipush #122
    //   4646: if_icmpgt -> 4679
    //   4649: goto -> 4656
    //   4652: invokestatic a : (Ljava/lang/Throwable;)Ljava/lang/Throwable;
    //   4655: athrow
    //   4656: aload_3
    //   4657: iload #7
    //   4659: aload_3
    //   4660: iload #7
    //   4662: baload
    //   4663: bipush #71
    //   4665: isub
    //   4666: i2b
    //   4667: bastore
    //   4668: iload_2
    //   4669: ifne -> 4730
    //   4672: goto -> 4679
    //   4675: invokestatic a : (Ljava/lang/Throwable;)Ljava/lang/Throwable;
    //   4678: athrow
    //   4679: aload_3
    //   4680: iload #7
    //   4682: baload
    //   4683: bipush #65
    //   4685: if_icmplt -> 4730
    //   4688: goto -> 4695
    //   4691: invokestatic a : (Ljava/lang/Throwable;)Ljava/lang/Throwable;
    //   4694: athrow
    //   4695: aload_3
    //   4696: iload #7
    //   4698: baload
    //   4699: bipush #90
    //   4701: if_icmpgt -> 4730
    //   4704: goto -> 4711
    //   4707: invokestatic a : (Ljava/lang/Throwable;)Ljava/lang/Throwable;
    //   4710: athrow
    //   4711: aload_3
    //   4712: iload #7
    //   4714: aload_3
    //   4715: iload #7
    //   4717: baload
    //   4718: bipush #65
    //   4720: isub
    //   4721: i2b
    //   4722: bastore
    //   4723: goto -> 4730
    //   4726: invokestatic a : (Ljava/lang/Throwable;)Ljava/lang/Throwable;
    //   4729: athrow
    //   4730: iinc #7, 1
    //   4733: iload_2
    //   4734: ifne -> 4471
    //   4737: iconst_0
    //   4738: istore #7
    //   4740: iconst_0
    //   4741: istore #8
    //   4743: iload #8
    //   4745: aload #6
    //   4747: arraylength
    //   4748: iconst_2
    //   4749: isub
    //   4750: if_icmpge -> 4853
    //   4753: aload #6
    //   4755: iload #8
    //   4757: aload_3
    //   4758: iload #7
    //   4760: baload
    //   4761: iconst_2
    //   4762: ishl
    //   4763: sipush #255
    //   4766: iand
    //   4767: aload_3
    //   4768: iload #7
    //   4770: iconst_1
    //   4771: iadd
    //   4772: baload
    //   4773: iconst_4
    //   4774: iushr
    //   4775: iconst_3
    //   4776: iand
    //   4777: ior
    //   4778: i2b
    //   4779: bastore
    //   4780: aload #6
    //   4782: iload #8
    //   4784: iconst_1
    //   4785: iadd
    //   4786: aload_3
    //   4787: iload #7
    //   4789: iconst_1
    //   4790: iadd
    //   4791: baload
    //   4792: iconst_4
    //   4793: ishl
    //   4794: sipush #255
    //   4797: iand
    //   4798: aload_3
    //   4799: iload #7
    //   4801: iconst_2
    //   4802: iadd
    //   4803: baload
    //   4804: iconst_2
    //   4805: iushr
    //   4806: bipush #15
    //   4808: iand
    //   4809: ior
    //   4810: i2b
    //   4811: bastore
    //   4812: aload #6
    //   4814: iload #8
    //   4816: iconst_2
    //   4817: iadd
    //   4818: aload_3
    //   4819: iload #7
    //   4821: iconst_2
    //   4822: iadd
    //   4823: baload
    //   4824: bipush #6
    //   4826: ishl
    //   4827: sipush #255
    //   4830: iand
    //   4831: aload_3
    //   4832: iload #7
    //   4834: iconst_3
    //   4835: iadd
    //   4836: baload
    //   4837: bipush #63
    //   4839: iand
    //   4840: ior
    //   4841: i2b
    //   4842: bastore
    //   4843: iinc #7, 4
    //   4846: iinc #8, 3
    //   4849: iload_2
    //   4850: ifne -> 4743
    //   4853: iload #8
    //   4855: aload #6
    //   4857: arraylength
    //   4858: if_icmpge -> 4895
    //   4861: aload #6
    //   4863: iload #8
    //   4865: aload_3
    //   4866: iload #7
    //   4868: baload
    //   4869: iconst_2
    //   4870: ishl
    //   4871: sipush #255
    //   4874: iand
    //   4875: aload_3
    //   4876: iload #7
    //   4878: iconst_1
    //   4879: iadd
    //   4880: baload
    //   4881: iconst_4
    //   4882: iushr
    //   4883: iconst_3
    //   4884: iand
    //   4885: ior
    //   4886: i2b
    //   4887: bastore
    //   4888: goto -> 4895
    //   4891: invokestatic a : (Ljava/lang/Throwable;)Ljava/lang/Throwable;
    //   4894: athrow
    //   4895: iinc #8, 1
    //   4898: iload #8
    //   4900: aload #6
    //   4902: arraylength
    //   4903: if_icmpge -> 4943
    //   4906: aload #6
    //   4908: iload #8
    //   4910: aload_3
    //   4911: iload #7
    //   4913: iconst_1
    //   4914: iadd
    //   4915: baload
    //   4916: iconst_4
    //   4917: ishl
    //   4918: sipush #255
    //   4921: iand
    //   4922: aload_3
    //   4923: iload #7
    //   4925: iconst_2
    //   4926: iadd
    //   4927: baload
    //   4928: iconst_2
    //   4929: iushr
    //   4930: bipush #15
    //   4932: iand
    //   4933: ior
    //   4934: i2b
    //   4935: bastore
    //   4936: goto -> 4943
    //   4939: invokestatic a : (Ljava/lang/Throwable;)Ljava/lang/Throwable;
    //   4942: athrow
    //   4943: aload #6
    //   4945: astore #4
    //   4947: sipush #-5209
    //   4950: new java/math/BigInteger
    //   4953: dup
    //   4954: aload #4
    //   4956: invokespecial <init> : ([B)V
    //   4959: invokevirtual abs : ()Ljava/math/BigInteger;
    //   4962: putstatic burp/Zbnb.ZZ : Ljava/lang/Object;
    //   4965: sipush #9031
    //   4968: invokestatic a : (II)Ljava/lang/String;
    //   4971: iconst_1
    //   4972: ldc burp/Zrt3
    //   4974: invokevirtual getClassLoader : ()Ljava/lang/ClassLoader;
    //   4977: invokestatic forName : (Ljava/lang/String;ZLjava/lang/ClassLoader;)Ljava/lang/Class;
    //   4980: invokevirtual getDeclaredFields : ()[Ljava/lang/reflect/Field;
    //   4983: astore_3
    //   4984: aload_3
    //   4985: arraylength
    //   4986: istore #4
    //   4988: iconst_0
    //   4989: istore #5
    //   4991: iload #5
    //   4993: iload #4
    //   4995: if_icmpge -> 5132
    //   4998: aload_3
    //   4999: iload #5
    //   5001: aaload
    //   5002: astore #6
    //   5004: aload #6
    //   5006: invokevirtual getModifiers : ()I
    //   5009: invokestatic isStatic : (I)Z
    //   5012: ifne -> 5022
    //   5015: goto -> 5125
    //   5018: invokestatic a : (Ljava/lang/Throwable;)Ljava/lang/Throwable;
    //   5021: athrow
    //   5022: aload #6
    //   5024: invokevirtual getType : ()Ljava/lang/Class;
    //   5027: astore #7
    //   5029: aload #7
    //   5031: ifnull -> 5112
    //   5034: aload #7
    //   5036: invokevirtual isPrimitive : ()Z
    //   5039: ifne -> 5112
    //   5042: goto -> 5049
    //   5045: invokestatic a : (Ljava/lang/Throwable;)Ljava/lang/Throwable;
    //   5048: athrow
    //   5049: aload #7
    //   5051: invokevirtual getPackage : ()Ljava/lang/Package;
    //   5054: ifnull -> 5112
    //   5057: goto -> 5064
    //   5060: invokestatic a : (Ljava/lang/Throwable;)Ljava/lang/Throwable;
    //   5063: athrow
    //   5064: aload #7
    //   5066: invokevirtual getPackage : ()Ljava/lang/Package;
    //   5069: invokevirtual getName : ()Ljava/lang/String;
    //   5072: ifnull -> 5112
    //   5075: goto -> 5082
    //   5078: invokestatic a : (Ljava/lang/Throwable;)Ljava/lang/Throwable;
    //   5081: athrow
    //   5082: aload #7
    //   5084: invokevirtual getPackage : ()Ljava/lang/Package;
    //   5087: invokevirtual getName : ()Ljava/lang/String;
    //   5090: sipush #-5213
    //   5093: sipush #26593
    //   5096: invokestatic a : (II)Ljava/lang/String;
    //   5099: invokevirtual startsWith : (Ljava/lang/String;)Z
    //   5102: ifne -> 5112
    //   5105: goto -> 5112
    //   5108: invokestatic a : (Ljava/lang/Throwable;)Ljava/lang/Throwable;
    //   5111: athrow
    //   5112: aload #6
    //   5114: iconst_1
    //   5115: invokevirtual setAccessible : (Z)V
    //   5118: aload #6
    //   5120: aconst_null
    //   5121: invokevirtual get : (Ljava/lang/Object;)Ljava/lang/Object;
    //   5124: pop
    //   5125: iinc #5, 1
    //   5128: iload_2
    //   5129: ifne -> 4991
    //   5132: sipush #-5215
    //   5135: sipush #5687
    //   5138: invokestatic a : (II)Ljava/lang/String;
    //   5141: invokestatic forName : (Ljava/lang/String;)Ljava/lang/Class;
    //   5144: invokevirtual getDeclaredMethods : ()[Ljava/lang/reflect/Method;
    //   5147: astore_3
    //   5148: aload_3
    //   5149: arraylength
    //   5150: istore #4
    //   5152: iconst_0
    //   5153: istore #5
    //   5155: iload #5
    //   5157: iload #4
    //   5159: if_icmpge -> 5291
    //   5162: aload_3
    //   5163: iload #5
    //   5165: aaload
    //   5166: astore #6
    //   5168: aload #6
    //   5170: invokevirtual getParameterTypes : ()[Ljava/lang/Class;
    //   5173: pop
    //   5174: aload #6
    //   5176: invokevirtual getModifiers : ()I
    //   5179: invokestatic isStatic : (I)Z
    //   5182: ifeq -> 5277
    //   5185: aload #6
    //   5187: invokevirtual getParameterTypes : ()[Ljava/lang/Class;
    //   5190: arraylength
    //   5191: iconst_2
    //   5192: if_icmpne -> 5277
    //   5195: goto -> 5202
    //   5198: invokestatic a : (Ljava/lang/Throwable;)Ljava/lang/Throwable;
    //   5201: athrow
    //   5202: aload #6
    //   5204: invokevirtual getReturnType : ()Ljava/lang/Class;
    //   5207: getstatic java/lang/Void.TYPE : Ljava/lang/Class;
    //   5210: invokevirtual equals : (Ljava/lang/Object;)Z
    //   5213: ifeq -> 5277
    //   5216: goto -> 5223
    //   5219: invokestatic a : (Ljava/lang/Throwable;)Ljava/lang/Throwable;
    //   5222: athrow
    //   5223: aload #6
    //   5225: iconst_1
    //   5226: invokevirtual setAccessible : (Z)V
    //   5229: aload #6
    //   5231: aconst_null
    //   5232: iconst_2
    //   5233: anewarray java/lang/Object
    //   5236: dup
    //   5237: iconst_0
    //   5238: aload_0
    //   5239: aastore
    //   5240: dup
    //   5241: iconst_1
    //   5242: aload_1
    //   5243: ifnonnull -> 5261
    //   5246: goto -> 5253
    //   5249: invokestatic a : (Ljava/lang/Throwable;)Ljava/lang/Throwable;
    //   5252: athrow
    //   5253: aload_1
    //   5254: goto -> 5268
    //   5257: invokestatic a : (Ljava/lang/Throwable;)Ljava/lang/Throwable;
    //   5260: athrow
    //   5261: aload_1
    //   5262: checkcast [B
    //   5265: invokevirtual clone : ()Ljava/lang/Object;
    //   5268: aastore
    //   5269: invokevirtual invoke : (Ljava/lang/Object;[Ljava/lang/Object;)Ljava/lang/Object;
    //   5272: pop
    //   5273: iload_2
    //   5274: ifne -> 5291
    //   5277: iinc #5, 1
    //   5280: iload_2
    //   5281: ifne -> 5155
    //   5284: goto -> 5291
    //   5287: invokestatic a : (Ljava/lang/Throwable;)Ljava/lang/Throwable;
    //   5290: athrow
    //   5291: getstatic burp/Zzs9.Zg : Ljava/lang/String;
    //   5294: getstatic burp/Zx4u.Zn : Ljava/lang/Object;
    //   5297: checkcast java/math/BigInteger
    //   5300: invokevirtual intValue : ()I
    //   5303: bipush #32
    //   5305: irem
    //   5306: invokestatic abs : (I)I
    //   5309: invokevirtual charAt : (I)C
    //   5312: getstatic burp/Zejj.ZQ : Ljava/lang/String;
    //   5315: getstatic burp/Zl1z.ZV : Ljava/lang/Object;
    //   5318: checkcast java/math/BigInteger
    //   5321: invokevirtual intValue : ()I
    //   5324: bipush #32
    //   5326: irem
    //   5327: invokestatic abs : (I)I
    //   5330: invokevirtual charAt : (I)C
    //   5333: if_icmple -> 5440
    //   5336: getstatic burp/Zg2u.Zy : Ljava/lang/String;
    //   5339: getstatic burp/Zr1t.ZP : Ljava/lang/Object;
    //   5342: checkcast java/math/BigInteger
    //   5345: invokevirtual intValue : ()I
    //   5348: bipush #32
    //   5350: irem
    //   5351: invokestatic abs : (I)I
    //   5354: invokevirtual charAt : (I)C
    //   5357: getstatic burp/Zr8h.Zk : Ljava/lang/String;
    //   5360: getstatic burp/Zxsb.ZN : Ljava/lang/Object;
    //   5363: checkcast java/math/BigInteger
    //   5366: invokevirtual intValue : ()I
    //   5369: bipush #32
    //   5371: irem
    //   5372: invokestatic abs : (I)I
    //   5375: invokevirtual charAt : (I)C
    //   5378: if_icmple -> 5440
    //   5381: goto -> 5388
    //   5384: invokestatic a : (Ljava/lang/Throwable;)Ljava/lang/Throwable;
    //   5387: athrow
    //   5388: getstatic burp/Zrct.ZT : Ljava/lang/String;
    //   5391: getstatic burp/Zgly.ZN : Ljava/lang/Object;
    //   5394: checkcast java/math/BigInteger
    //   5397: invokevirtual intValue : ()I
    //   5400: bipush #32
    //   5402: irem
    //   5403: invokestatic abs : (I)I
    //   5406: invokevirtual charAt : (I)C
    //   5409: getstatic burp/Zg_i.ZW : Ljava/lang/String;
    //   5412: getstatic burp/Ztev.Zr : Ljava/lang/Object;
    //   5415: checkcast java/math/BigInteger
    //   5418: invokevirtual intValue : ()I
    //   5421: bipush #32
    //   5423: irem
    //   5424: invokestatic abs : (I)I
    //   5427: invokevirtual charAt : (I)C
    //   5430: if_icmpgt -> 5448
    //   5433: goto -> 5440
    //   5436: invokestatic a : (Ljava/lang/Throwable;)Ljava/lang/Throwable;
    //   5439: athrow
    //   5440: iconst_1
    //   5441: goto -> 5449
    //   5444: invokestatic a : (Ljava/lang/Throwable;)Ljava/lang/Throwable;
    //   5447: athrow
    //   5448: iconst_0
    //   5449: ireturn
    //   5450: astore_3
    //   5451: new java/lang/Exception
    //   5454: dup
    //   5455: aload_3
    //   5456: invokevirtual getMessage : ()Ljava/lang/String;
    //   5459: invokespecial <init> : (Ljava/lang/String;)V
    //   5462: athrow
    // Exception table:
    //   from	to	target	type
    //   4	5449	5450	java/lang/Throwable
    //   805	839	842	java/lang/Throwable
    //   934	1012	1015	java/lang/Throwable
    //   941	1155	1158	java/lang/Throwable
    //   1532	1547	1547	java/lang/Throwable
    //   1574	1608	1611	java/lang/Throwable
    //   1618	1630	1633	java/lang/Throwable
    //   1716	1794	1797	java/lang/Throwable
    //   1723	1937	1940	java/lang/Throwable
    //   2337	2415	2418	java/lang/Throwable
    //   2344	2558	2561	java/lang/Throwable
    //   3005	3039	3042	java/lang/Throwable
    //   3046	3058	3061	java/lang/Throwable
    //   3144	3222	3225	java/lang/Throwable
    //   3151	3365	3368	java/lang/Throwable
    //   4124	4138	4141	java/lang/Throwable
    //   4131	4152	4155	java/lang/Throwable
    //   4145	4166	4169	java/lang/Throwable
    //   4159	4180	4183	java/lang/Throwable
    //   4173	4194	4197	java/lang/Throwable
    //   4187	4208	4211	java/lang/Throwable
    //   4201	4222	4225	java/lang/Throwable
    //   4215	4236	4239	java/lang/Throwable
    //   4229	4246	4249	java/lang/Throwable
    //   4285	4299	4302	java/lang/Throwable
    //   4292	4313	4316	java/lang/Throwable
    //   4306	4327	4330	java/lang/Throwable
    //   4320	4341	4344	java/lang/Throwable
    //   4334	4355	4358	java/lang/Throwable
    //   4348	4369	4372	java/lang/Throwable
    //   4362	4383	4386	java/lang/Throwable
    //   4376	4397	4400	java/lang/Throwable
    //   4390	4414	4417	java/lang/Throwable
    //   4478	4496	4499	java/lang/Throwable
    //   4487	4512	4515	java/lang/Throwable
    //   4503	4529	4532	java/lang/Throwable
    //   4519	4545	4548	java/lang/Throwable
    //   4536	4562	4565	java/lang/Throwable
    //   4552	4578	4581	java/lang/Throwable
    //   4569	4594	4597	java/lang/Throwable
    //   4585	4617	4620	java/lang/Throwable
    //   4601	4633	4636	java/lang/Throwable
    //   4624	4649	4652	java/lang/Throwable
    //   4640	4672	4675	java/lang/Throwable
    //   4656	4688	4691	java/lang/Throwable
    //   4679	4704	4707	java/lang/Throwable
    //   4695	4723	4726	java/lang/Throwable
    //   4853	4888	4891	java/lang/Throwable
    //   4895	4936	4939	java/lang/Throwable
    //   5004	5018	5018	java/lang/Throwable
    //   5029	5042	5045	java/lang/Throwable
    //   5034	5057	5060	java/lang/Throwable
    //   5049	5075	5078	java/lang/Throwable
    //   5064	5105	5108	java/lang/Throwable
    //   5168	5195	5198	java/lang/Throwable
    //   5185	5216	5219	java/lang/Throwable
    //   5202	5246	5249	java/lang/Throwable
    //   5223	5257	5257	java/lang/Throwable
    //   5268	5284	5287	java/lang/Throwable
    //   5291	5381	5384	java/lang/Throwable
    //   5336	5433	5436	java/lang/Throwable
    //   5388	5444	5444	java/lang/Throwable
  }
  
  static void Zi(Object paramObject) {
    Zth7.Zf = a(-5216, -19683);
    Zth7.ZT = new BigInteger(a(-5214, -15720));
    boolean bool = Zt2e.ZN();
    try {
      try {
        if (Zle4.ZX.charAt(Math.abs(((BigInteger)Zsq5.ZF).intValue() % 32)) <= Zeno.ZL.charAt(Math.abs(((BigInteger)Zdm.ZA).intValue() % 32))) {
          try {
            Zkdc.ZA(Class.forName(a(-5212, 16346)));
            if (!bool)
              Zk8g.ZC(Class.forName(a(-5211, -3057))); 
          } catch (Throwable throwable) {
            throw a(null);
          } 
          return;
        } 
      } catch (Throwable throwable) {
        throw a(null);
      } 
      Zk8g.ZC(Class.forName(a(-5211, -3057)));
    } catch (Throwable throwable) {}
  }
  
  static void ZO(Object[] paramArrayOfObject, Object paramObject) throws Throwable {}
  
  static {
    // Byte code:
    //   0: bipush #8
    //   2: anewarray java/lang/String
    //   5: astore #5
    //   7: iconst_0
    //   8: istore_3
    //   9: ldc 'uX W|/KE&x\\t9PM mel'v^; 1$] Ms5 rV#DY3CS)LxI*d\\tZ6J\\b<NbVdj'
    //   11: dup
    //   12: astore_2
    //   13: invokevirtual length : ()I
    //   16: istore #4
    //   18: bipush #32
    //   20: istore_1
    //   21: iconst_m1
    //   22: istore_0
    //   23: bipush #16
    //   25: iinc #0, 1
    //   28: aload_2
    //   29: iload_0
    //   30: dup
    //   31: iload_1
    //   32: iadd
    //   33: invokevirtual substring : (II)Ljava/lang/String;
    //   36: iconst_m1
    //   37: goto -> 143
    //   40: aload #5
    //   42: swap
    //   43: iload_3
    //   44: iinc #3, 1
    //   47: swap
    //   48: aastore
    //   49: iload_0
    //   50: iload_1
    //   51: iadd
    //   52: dup
    //   53: istore_0
    //   54: iload #4
    //   56: if_icmpge -> 68
    //   59: aload_2
    //   60: iload_0
    //   61: invokevirtual charAt : (I)C
    //   64: istore_1
    //   65: goto -> 23
    //   68: ldc '^N)e`PQXgy\\bD8W.B\\t#v'
    //   70: dup
    //   71: astore_2
    //   72: invokevirtual length : ()I
    //   75: istore #4
    //   77: bipush #32
    //   79: istore_1
    //   80: iconst_m1
    //   81: istore_0
    //   82: bipush #12
    //   84: iinc #0, 1
    //   87: aload_2
    //   88: iload_0
    //   89: dup
    //   90: iload_1
    //   91: iadd
    //   92: invokevirtual substring : (II)Ljava/lang/String;
    //   95: iconst_0
    //   96: goto -> 143
    //   99: aload #5
    //   101: swap
    //   102: iload_3
    //   103: iinc #3, 1
    //   106: swap
    //   107: aastore
    //   108: iload_0
    //   109: iload_1
    //   110: iadd
    //   111: dup
    //   112: istore_0
    //   113: iload #4
    //   115: if_icmpge -> 127
    //   118: aload_2
    //   119: iload_0
    //   120: invokevirtual charAt : (I)C
    //   123: istore_1
    //   124: goto -> 82
    //   127: aload #5
    //   129: putstatic burp/Zblj.a : [Ljava/lang/String;
    //   132: bipush #8
    //   134: anewarray java/lang/String
    //   137: putstatic burp/Zblj.b : [Ljava/lang/String;
    //   140: goto -> 300
    //   143: dup_x2
    //   144: pop
    //   145: invokevirtual toCharArray : ()[C
    //   148: dup_x1
    //   149: arraylength
    //   150: dup_x2
    //   151: pop
    //   152: iconst_0
    //   153: istore #6
    //   155: dup2_x1
    //   156: pop2
    //   157: dup_x2
    //   158: iconst_1
    //   159: if_icmpgt -> 259
    //   162: dup2
    //   163: swap
    //   164: iload #6
    //   166: dup2_x1
    //   167: caload
    //   168: swap
    //   169: iload #6
    //   171: bipush #7
    //   173: irem
    //   174: tableswitch default -> 241, 0 -> 212, 1 -> 217, 2 -> 221, 3 -> 226, 4 -> 231, 5 -> 236
    //   212: bipush #11
    //   214: goto -> 243
    //   217: iconst_1
    //   218: goto -> 243
    //   221: bipush #125
    //   223: goto -> 243
    //   226: bipush #50
    //   228: goto -> 243
    //   231: bipush #67
    //   233: goto -> 243
    //   236: bipush #88
    //   238: goto -> 243
    //   241: bipush #71
    //   243: ixor
    //   244: ixor
    //   245: i2c
    //   246: castore
    //   247: iinc #6, 1
    //   250: dup
    //   251: ifne -> 259
    //   254: dup2
    //   255: dup_x1
    //   256: goto -> 166
    //   259: dup2_x1
    //   260: pop2
    //   261: dup_x2
    //   262: iload #6
    //   264: if_icmpgt -> 162
    //   267: pop
    //   268: new java/lang/String
    //   271: dup_x1
    //   272: swap
    //   273: invokespecial <init> : ([C)V
    //   276: invokevirtual intern : ()Ljava/lang/String;
    //   279: swap
    //   280: pop
    //   281: swap
    //   282: tableswitch default -> 40, 0 -> 99
    //   300: new java/math/BigInteger
    //   303: dup
    //   304: bipush #32
    //   306: newarray byte
    //   308: dup
    //   309: iconst_0
    //   310: bipush #91
    //   312: bastore
    //   313: dup
    //   314: iconst_1
    //   315: bipush #-128
    //   317: bastore
    //   318: dup
    //   319: iconst_2
    //   320: bipush #-50
    //   322: bastore
    //   323: dup
    //   324: iconst_3
    //   325: bipush #38
    //   327: bastore
    //   328: dup
    //   329: iconst_4
    //   330: bipush #100
    //   332: bastore
    //   333: dup
    //   334: iconst_5
    //   335: bipush #120
    //   337: bastore
    //   338: dup
    //   339: bipush #6
    //   341: bipush #-48
    //   343: bastore
    //   344: dup
    //   345: bipush #7
    //   347: bipush #-10
    //   349: bastore
    //   350: dup
    //   351: bipush #8
    //   353: bipush #-72
    //   355: bastore
    //   356: dup
    //   357: bipush #9
    //   359: bipush #-36
    //   361: bastore
    //   362: dup
    //   363: bipush #10
    //   365: bipush #-106
    //   367: bastore
    //   368: dup
    //   369: bipush #11
    //   371: bipush #-32
    //   373: bastore
    //   374: dup
    //   375: bipush #12
    //   377: bipush #-20
    //   379: bastore
    //   380: dup
    //   381: bipush #13
    //   383: bipush #-86
    //   385: bastore
    //   386: dup
    //   387: bipush #14
    //   389: bipush #-115
    //   391: bastore
    //   392: dup
    //   393: bipush #15
    //   395: bipush #-50
    //   397: bastore
    //   398: dup
    //   399: bipush #16
    //   401: bipush #-121
    //   403: bastore
    //   404: dup
    //   405: bipush #17
    //   407: bipush #71
    //   409: bastore
    //   410: dup
    //   411: bipush #18
    //   413: bipush #-118
    //   415: bastore
    //   416: dup
    //   417: bipush #19
    //   419: bipush #8
    //   421: bastore
    //   422: dup
    //   423: bipush #20
    //   425: bipush #-68
    //   427: bastore
    //   428: dup
    //   429: bipush #21
    //   431: bipush #115
    //   433: bastore
    //   434: dup
    //   435: bipush #22
    //   437: bipush #26
    //   439: bastore
    //   440: dup
    //   441: bipush #23
    //   443: bipush #59
    //   445: bastore
    //   446: dup
    //   447: bipush #24
    //   449: bipush #-104
    //   451: bastore
    //   452: dup
    //   453: bipush #25
    //   455: bipush #66
    //   457: bastore
    //   458: dup
    //   459: bipush #26
    //   461: bipush #-37
    //   463: bastore
    //   464: dup
    //   465: bipush #27
    //   467: bipush #-25
    //   469: bastore
    //   470: dup
    //   471: bipush #28
    //   473: bipush #-120
    //   475: bastore
    //   476: dup
    //   477: bipush #29
    //   479: bipush #-63
    //   481: bastore
    //   482: dup
    //   483: bipush #30
    //   485: bipush #-6
    //   487: bastore
    //   488: dup
    //   489: bipush #31
    //   491: bipush #14
    //   493: bastore
    //   494: invokespecial <init> : ([B)V
    //   497: putstatic burp/Zblj.Zl : Ljava/lang/Object;
    //   500: sipush #-5210
    //   503: sipush #2368
    //   506: invokestatic a : (II)Ljava/lang/String;
    //   509: putstatic burp/Zblj.Za : Ljava/lang/String;
    //   512: return
  }
  
  private static Throwable a(Throwable paramThrowable) {
    return paramThrowable;
  }
  
  private static String a(int paramInt1, int paramInt2) {
    int i = (paramInt1 ^ 0xFFFFEBA0) & 0xFFFF;
    if (b[i] == null) {
      char[] arrayOfChar = a[i].toCharArray();
      switch (arrayOfChar[0] & 0xFF) {
        case 0:
        
        case 1:
        
        case 2:
        
        case 3:
        
        case 4:
        
        case 5:
        
        case 6:
        
        case 7:
        
        case 8:
        
        case 9:
        
        case 10:
        
        case 11:
        
        case 12:
        
        case 13:
        
        case 14:
        
        case 15:
        
        case 16:
        
        case 17:
        
        case 18:
        
        case 19:
        
        case 20:
        
        case 21:
        
        case 22:
        
        case 23:
        
        case 24:
        
        case 25:
        
        case 26:
        
        case 27:
        
        case 28:
        
        case 29:
        
        case 30:
        
        case 31:
        
        case 32:
        
        case 33:
        
        case 34:
        
        case 35:
        
        case 36:
        
        case 37:
        
        case 38:
        
        case 39:
        
        case 40:
        
        case 41:
        
        case 42:
        
        case 43:
        
        case 44:
        
        case 45:
        
        case 46:
        
        case 47:
        
        case 48:
        
        case 49:
        
        case 50:
        
        case 51:
        
        case 52:
        
        case 53:
        
        case 54:
        
        case 55:
        
        case 56:
        
        case 57:
        
        case 58:
        
        case 59:
        
        case 60:
        
        case 61:
        
        case 62:
        
        case 63:
        
        case 64:
        
        case 65:
        
        case 66:
        
        case 67:
        
        case 68:
        
        case 69:
        
        case 70:
        
        case 71:
        
        case 72:
        
        case 73:
        
        case 74:
        
        case 75:
        
        case 76:
        
        case 77:
        
        case 78:
        
        case 79:
        
        case 80:
        
        case 81:
        
        case 82:
        
        case 83:
        
        case 84:
        
        case 85:
        
        case 86:
        
        case 87:
        
        case 88:
        
        case 89:
        
        case 90:
        
        case 91:
        
        case 92:
        
        case 93:
        
        case 94:
        
        case 95:
        
        case 96:
        
        case 97:
        
        case 98:
        
        case 99:
        
        case 100:
        
        case 101:
        
        case 102:
        
        case 103:
        
        case 104:
        
        case 105:
        
        case 106:
        
        case 107:
        
        case 108:
        
        case 109:
        
        case 110:
        
        case 111:
        
        case 112:
        
        case 113:
        
        case 114:
        
        case 115:
        
        case 116:
        
        case 117:
        
        case 118:
        
        case 119:
        
        case 120:
        
        case 121:
        
        case 122:
        
        case 123:
        
        case 124:
        
        case 125:
        
        case 126:
        
        case 127:
        
        case 128:
        
        case 129:
        
        case 130:
        
        case 131:
        
        case 132:
        
        case 133:
        
        case 134:
        
        case 135:
        
        case 136:
        
        case 137:
        
        case 138:
        
        case 139:
        
        case 140:
        
        case 141:
        
        case 142:
        
        case 143:
        
        case 144:
        
        case 145:
        
        case 146:
        
        case 147:
        
        case 148:
        
        case 149:
        
        case 150:
        
        case 151:
        
        case 152:
        
        case 153:
        
        case 154:
        
        case 155:
        
        case 156:
        
        case 157:
        
        case 158:
        
        case 159:
        
        case 160:
        
        case 161:
        
        case 162:
        
        case 163:
        
        case 164:
        
        case 165:
        
        case 166:
        
        case 167:
        
        case 168:
        
        case 169:
        
        case 170:
        
        case 171:
        
        case 172:
        
        case 173:
        
        case 174:
        
        case 175:
        
        case 176:
        
        case 177:
        
        case 178:
        
        case 179:
        
        case 180:
        
        case 181:
        
        case 182:
        
        case 183:
        
        case 184:
        
        case 185:
        
        case 186:
        
        case 187:
        
        case 188:
        
        case 189:
        
        case 190:
        
        case 191:
        
        case 192:
        
        case 193:
        
        case 194:
        
        case 195:
        
        case 196:
        
        case 197:
        
        case 198:
        
        case 199:
        
        case 200:
        
        case 201:
        
        case 202:
        
        case 203:
        
        case 204:
        
        case 205:
        
        case 206:
        
        case 207:
        
        case 208:
        
        case 209:
        
        case 210:
        
        case 211:
        
        case 212:
        
        case 213:
        
        case 214:
        
        case 215:
        
        case 216:
        
        case 217:
        
        case 218:
        
        case 219:
        
        case 220:
        
        case 221:
        
        case 222:
        
        case 223:
        
        case 224:
        
        case 225:
        
        case 226:
        
        case 227:
        
        case 228:
        
        case 229:
        
        case 230:
        
        case 231:
        
        case 232:
        
        case 233:
        
        case 234:
        
        case 235:
        
        case 236:
        
        case 237:
        
        case 238:
        
        case 239:
        
        case 240:
        
        case 241:
        
        case 242:
        
        case 243:
        
        case 244:
        
        case 245:
        
        case 246:
        
        case 247:
        
        case 248:
        
        case 249:
        
        case 250:
        
        case 251:
        
        case 252:
        
        case 253:
        
        case 254:
        
        default:
          break;
      } 
      char c = '';
      int j = (paramInt2 & 0xFF) - c;
      if (j < 0)
        j += 256; 
      int k = ((paramInt2 & 0xFFFF) >>> 8) - c;
      if (k < 0)
        k += 256; 
      for (byte b = 0; b < arrayOfChar.length; b++) {
        int m = b % 2;
        if (m == 0) {
          arrayOfChar[b] = (char)(arrayOfChar[b] ^ j);
          j = ((j >>> 3 | j << 5) ^ arrayOfChar[b]) & 0xFF;
        } else {
          arrayOfChar[b] = (char)(arrayOfChar[b] ^ k);
          k = ((k >>> 3 | k << 5) ^ arrayOfChar[b]) & 0xFF;
        } 
      } 
      b[i] = (new String(arrayOfChar)).intern();
    } 
    return b[i];
  }
}


/* Location:              C:\Program Files\BurpSuitePro\burpsuite_pro.jar!\burp\Zblj.class
 * Java compiler version: 21 (65.0)
 * JD-Core Version:       1.1.3
 */