package burp;

import java.awt.GridBagConstraints;
import java.awt.GridBagLayout;
import java.awt.Insets;
import java.awt.event.ActionEvent;
import java.io.File;

class Zbmu extends Zbv5 {
  private final Zt4u Zl;
  
  private Zgvc ZV;
  
  private Ze01 Zn;
  
  private Ze01 Zz;
  
  private Zzdy ZM;
  
  private Zzdy ZS;
  
  private Zzdy ZX;
  
  private Zzdy Zm;
  
  private Zzdy ZN;
  
  private Zzdy Zc;
  
  private Zzdy Z_;
  
  private Zzdy ZF;
  
  private Zl8w ZE;
  
  private Zm2o Zy;
  
  private Zm9v ZD;
  
  private Zm9v ZQ;
  
  private Zbkc Zb;
  
  private Zm99 Zu;
  
  private Zg85 Zw;
  
  private Zg85 Zs;
  
  private static final String[] a;
  
  private static final String[] b;
  
  Zbmu(Zt4u paramZt4u, Zgvc paramZgvc) {
    this.Zl = paramZt4u;
    this.ZV = paramZgvc;
    ZN();
    this.ZN.setName(a(31457, 10694));
    this.Zm.setName(a(31471, -21505));
    ZB((ActionEvent)null);
    ZZ((ActionEvent)null);
    ZW((ActionEvent)null);
    Zb((ActionEvent)null);
    Ze((ActionEvent)null);
    Zs((ActionEvent)null);
  }
  
  private void ZN() {
    this.ZF = new Zzdy();
    this.ZN = new Zzdy();
    this.Zc = new Zzdy();
    this.ZX = new Zzdy();
    this.Z_ = new Zzdy();
    this.Zm = new Zzdy();
    this.ZE = new Zl8w();
    this.Zb = new Zbkc();
    this.Zy = new Zm2o();
    this.ZS = new Zzdy();
    this.ZM = new Zzdy();
    this.Zs = new Zg85();
    this.Zz = new Ze01();
    this.Zw = new Zg85();
    this.Zn = new Ze01();
    this.Zu = new Zm99();
    this.ZQ = new Zm9v();
    this.ZD = new Zm9v();
    GridBagLayout gridBagLayout = new GridBagLayout();
    gridBagLayout.columnWidths = new int[] { 
        0, 5, 0, 5, 0, 5, 0, 5, 0, 5, 
        0 };
    gridBagLayout.rowHeights = new int[] { 
        0, 5, 0, 5, 0, 5, 0, 5, 0, 5, 
        0, 5, 0, 5, 0, 5, 0, 5, 0, 5, 
        0, 5, 0 };
    setLayout(gridBagLayout);
    this.ZF.setSelected(true);
    this.ZF.setText(a(31480, 71));
    this.ZF.addActionListener(new Zl51(this));
    GridBagConstraints gridBagConstraints = new GridBagConstraints();
    gridBagConstraints.gridx = 2;
    gridBagConstraints.gridy = 4;
    gridBagConstraints.gridwidth = 3;
    gridBagConstraints.anchor = 18;
    add(this.ZF, gridBagConstraints);
    this.ZN.setSelected(true);
    this.ZN.setText(a(31467, -9320));
    this.ZN.addActionListener(new Zzkv(this));
    gridBagConstraints = new GridBagConstraints();
    gridBagConstraints.gridx = 2;
    gridBagConstraints.gridy = 8;
    gridBagConstraints.gridwidth = 3;
    gridBagConstraints.anchor = 18;
    add(this.ZN, gridBagConstraints);
    this.Zc.setSelected(true);
    this.Zc.setText(a(31466, -8236));
    this.Zc.addActionListener(new Zgu6(this));
    gridBagConstraints = new GridBagConstraints();
    gridBagConstraints.gridx = 2;
    gridBagConstraints.gridy = 20;
    gridBagConstraints.gridwidth = 3;
    gridBagConstraints.anchor = 18;
    add(this.Zc, gridBagConstraints);
    this.ZX.setSelected(true);
    this.ZX.setText(a(31468, 25451));
    this.ZX.addActionListener(new Zeox(this));
    gridBagConstraints = new GridBagConstraints();
    gridBagConstraints.gridx = 2;
    gridBagConstraints.gridy = 22;
    gridBagConstraints.gridwidth = 3;
    gridBagConstraints.anchor = 18;
    add(this.ZX, gridBagConstraints);
    this.Z_.setSelected(true);
    this.Z_.setText(a(31456, 17035));
    this.Z_.addActionListener(new Zslq(this));
    gridBagConstraints = new GridBagConstraints();
    gridBagConstraints.gridx = 2;
    gridBagConstraints.gridy = 6;
    gridBagConstraints.gridwidth = 3;
    gridBagConstraints.anchor = 18;
    add(this.Z_, gridBagConstraints);
    this.Zm.setSelected(true);
    this.Zm.setText(a(31465, -2050));
    this.Zm.addActionListener(new Zr6b(this));
    gridBagConstraints = new GridBagConstraints();
    gridBagConstraints.gridx = 2;
    gridBagConstraints.gridy = 10;
    gridBagConstraints.gridwidth = 3;
    gridBagConstraints.anchor = 18;
    add(this.Zm, gridBagConstraints);
    this.ZE.setText(a(31482, -32692));
    gridBagConstraints = new GridBagConstraints();
    gridBagConstraints.gridx = 2;
    gridBagConstraints.gridy = 2;
    gridBagConstraints.gridwidth = 9;
    gridBagConstraints.fill = 2;
    gridBagConstraints.anchor = 1280;
    gridBagConstraints.weightx = 1.0D;
    add(this.ZE, gridBagConstraints);
    this.Zb.Zx(a(31458, -5800));
    gridBagConstraints = new GridBagConstraints();
    gridBagConstraints.gridx = 2;
    gridBagConstraints.gridy = 0;
    gridBagConstraints.gridwidth = 7;
    gridBagConstraints.anchor = 21;
    add(this.Zb, gridBagConstraints);
    this.Zy.Zi(Zk97.DESKTOP_FUNCTIONS_CONTENT_DISCOVERY_FILENAMES);
    gridBagConstraints = new GridBagConstraints();
    gridBagConstraints.gridx = 0;
    gridBagConstraints.gridy = 0;
    gridBagConstraints.gridheight = 5;
    gridBagConstraints.anchor = 23;
    gridBagConstraints.insets = new Insets(0, 0, 0, 5);
    add(this.Zy, gridBagConstraints);
    this.ZS.setText(a(31469, -3442));
    this.ZS.addActionListener(new Zlcr(this));
    gridBagConstraints = new GridBagConstraints();
    gridBagConstraints.gridx = 2;
    gridBagConstraints.gridy = 12;
    gridBagConstraints.gridwidth = 3;
    gridBagConstraints.anchor = 18;
    add(this.ZS, gridBagConstraints);
    this.ZM.setText(a(31470, 27866));
    this.ZM.addActionListener(new Zzby(this));
    gridBagConstraints = new GridBagConstraints();
    gridBagConstraints.gridx = 2;
    gridBagConstraints.gridy = 16;
    gridBagConstraints.gridwidth = 3;
    gridBagConstraints.anchor = 18;
    add(this.ZM, gridBagConstraints);
    this.Zs.setEditable(false);
    this.Zs.setColumns(35);
    gridBagConstraints = new GridBagConstraints();
    gridBagConstraints.gridx = 4;
    gridBagConstraints.gridy = 14;
    gridBagConstraints.gridwidth = 3;
    gridBagConstraints.fill = 2;
    gridBagConstraints.anchor = 18;
    add(this.Zs, gridBagConstraints);
    this.Zz.setText(a(31461, -20594));
    this.Zz.addActionListener(new Zx0y(this));
    gridBagConstraints = new GridBagConstraints();
    gridBagConstraints.gridx = 8;
    gridBagConstraints.gridy = 14;
    add(this.Zz, gridBagConstraints);
    this.Zw.setEditable(false);
    this.Zw.setColumns(35);
    gridBagConstraints = new GridBagConstraints();
    gridBagConstraints.gridx = 4;
    gridBagConstraints.gridy = 18;
    gridBagConstraints.gridwidth = 3;
    gridBagConstraints.fill = 2;
    gridBagConstraints.anchor = 18;
    add(this.Zw, gridBagConstraints);
    this.Zn.setText(a(31460, -13680));
    this.Zn.addActionListener(new Zkhb(this));
    gridBagConstraints = new GridBagConstraints();
    gridBagConstraints.gridx = 8;
    gridBagConstraints.gridy = 18;
    add(this.Zn, gridBagConstraints);
    this.Zu.setText(a(31459, 28853));
    gridBagConstraints = new GridBagConstraints();
    gridBagConstraints.gridx = 2;
    gridBagConstraints.gridy = 14;
    add(this.Zu, gridBagConstraints);
    gridBagConstraints = new GridBagConstraints();
    gridBagConstraints.gridx = 6;
    gridBagConstraints.gridy = 12;
    gridBagConstraints.anchor = 26;
    add(this.ZQ, gridBagConstraints);
    gridBagConstraints = new GridBagConstraints();
    gridBagConstraints.gridx = 6;
    gridBagConstraints.gridy = 16;
    gridBagConstraints.anchor = 26;
    add(this.ZD, gridBagConstraints);
  }
  
  private void ZB(ActionEvent paramActionEvent) {
    this.ZV.ZO(this.ZF.isSelected());
  }
  
  private void ZZ(ActionEvent paramActionEvent) {
    this.ZV.Zo(this.Z_.isSelected());
  }
  
  private void ZW(ActionEvent paramActionEvent) {
    this.ZV.Za(this.ZN.isSelected());
  }
  
  private void Zb(ActionEvent paramActionEvent) {
    this.ZV.ZP(this.Zm.isSelected());
  }
  
  private void Ze(ActionEvent paramActionEvent) {
    this.ZV.Zv(this.Zc.isSelected());
  }
  
  private void Zs(ActionEvent paramActionEvent) {
    this.ZV.Zi(this.ZX.isSelected());
  }
  
  private void ZH(ActionEvent paramActionEvent) {
    this.ZV.Z_(this.ZS.isSelected());
  }
  
  private void Zl(ActionEvent paramActionEvent) {
    this.ZV.Zt(this.ZM.isSelected());
  }
  
  private void ZC(ActionEvent paramActionEvent) {
    Zbqc[] arrayOfZbqc = Zm82.Zb();
    File file = Zs6n.Zp(Zg1m.CONFIG, this.Zl, this.ZV.ZB(), 0, a(31464, 22794));
    if (file != null) {
      this.Zs.setText(file.getPath());
      this.Zs.grabFocus();
      if (file.exists() && file.isFile() && file.canRead()) {
        this.ZV.Zo(file.getAbsolutePath());
        this.ZV.Z_(true);
        this.ZS.setSelected(true);
        this.ZQ.setText("");
        if (arrayOfZbqc == null) {
          this.ZV.Z_(false);
          this.ZS.setSelected(false);
          this.ZQ.setText(a(31462, -31813));
          return;
        } 
        return;
      } 
    } else {
      return;
    } 
    this.ZV.Z_(false);
    this.ZS.setSelected(false);
    this.ZQ.setText(a(31462, -31813));
  }
  
  private void Zn(ActionEvent paramActionEvent) {
    Zbqc[] arrayOfZbqc = Zm82.Zb();
    File file = Zs6n.Zp(Zg1m.CONFIG, this.Zl, this.ZV.ZB(), 0, a(31463, -16433));
    if (file != null) {
      this.Zw.setText(file.getPath());
      this.Zw.grabFocus();
      if (file.exists() && file.isFile() && file.canRead()) {
        this.ZV.ZU(file.getAbsolutePath());
        this.ZV.Zt(true);
        this.ZM.setSelected(true);
        this.ZD.setText("");
        if (arrayOfZbqc == null) {
          this.ZV.Zt(false);
          this.ZM.setSelected(false);
          this.ZD.setText(a(31483, 30618));
          return;
        } 
        return;
      } 
    } else {
      return;
    } 
    this.ZV.Zt(false);
    this.ZM.setSelected(false);
    this.ZD.setText(a(31483, 30618));
  }
  
  static {
    // Byte code:
    //   0: bipush #19
    //   2: anewarray java/lang/String
    //   5: astore #5
    //   7: iconst_0
    //   8: istore_3
    //   9: ldc 'ÃÃ |Â¾Â«KmNÂ“Ã­Â—Â•ÃžSÃŽO7Â¨Ã„ÃÃ„QÂ½Ã·pE8Ã  @|Â…ÂƒÂÃ—\\bÂ†Ã‹pÂ¸Â‡+|Ã§&WÂ’:uÂ´QvÂÂžÃ¾^ÂˆÂŸÃ•Â–rÂ—Â´9Ã’Ã HÃ²Ã‘RÃ­YDÂ¬#5Â¥Â¾$>\\nEÂ´^Â¨ÃÃ¼\\fÃ¬1GÃÂ²Â( Ã¦hÂÃ–ZÂƒHÂ™=@Ã’ Ã¦%ÃÂºÃ·+Â¯Â„"Â®Â§Ã™yÂPÂ¹Â·Â¯7qÃŽÂ£Ã­Ã«ÂÂ¡Ã¢Â¥Â¡pÂ¥Ã™Â³3Ã¯%JnÂ˜Ã§ÃŽÂ¬ÃÂµ_ÃÃ¿Â³ÃJÃ½_ÃœÃ»Â¤Â·2tÂ²#Â³hÃ»Â¦Ã£Ã j9Ã‘Âµ3Â¬QÂ°ÃÃ´1YÂ¤Â‚?7Ã§Ãª\\tÃ»Â¶Ã²}FrlÃ±Â…ÃÃ›7[(g8KÂ¾ÂPÂ¹ÂµÃ±S\Ã¶Ã¶ÂÃ¼Ã¡)Ã²ÃƒÃ¬Âµ0ÂŽÃ¾Â€&Âœ Â|Ã¢nÂ‹K-Â¹\\bÃ’\\rÃ—\\nÂ…VÃÃ¸zÂ›eÃ¾Ã„i@Ã§ÃŸÃŠxÂ€|Ã˜ÂƒÂ½Igd:Â‘Ã„ÃLÃ¤J3IlÃÃ—Â½Â¼Ã§ÂÃ‘Ã®m#ÃžBÃŽÂ€ÂœÃªXÃŒrÃÂŠÃ¢zÃœ)\\trÃ¯ÃŒT2Ã’Ã”ÃµÃ¤!Â·Â¤ÂE*hÃ®UOGÂ»ÃŽ]Â·Ã¶NÂ…QÃYÃ°1ÂºÂ¢P.%Ã©Â²ÂµÃ†Âˆ*-,Ã‚Â¨Ã¥jÃ˜eÂ¯[Ãƒ*fÂ™aÃ»Ã±HOÃžÃ‹Âž"ÂŸMÂ‰Â‘ÂrÃ³Â‰:ÂŽÂR8ÃŽÂ²Â¥Â€HÃ‡['
    //   11: dup
    //   12: astore_2
    //   13: invokevirtual length : ()I
    //   16: istore #4
    //   18: bipush #36
    //   20: istore_1
    //   21: iconst_m1
    //   22: istore_0
    //   23: bipush #46
    //   25: iinc #0, 1
    //   28: aload_2
    //   29: iload_0
    //   30: dup
    //   31: iload_1
    //   32: iadd
    //   33: invokevirtual substring : (II)Ljava/lang/String;
    //   36: iconst_m1
    //   37: goto -> 142
    //   40: aload #5
    //   42: swap
    //   43: iload_3
    //   44: iinc #3, 1
    //   47: swap
    //   48: aastore
    //   49: iload_0
    //   50: iload_1
    //   51: iadd
    //   52: dup
    //   53: istore_0
    //   54: iload #4
    //   56: if_icmpge -> 68
    //   59: aload_2
    //   60: iload_0
    //   61: invokevirtual charAt : (I)C
    //   64: istore_1
    //   65: goto -> 23
    //   68: ldc 'ÃšÃ—ÂK]Â¤^Ã¸Ã¢Â’Â€fÃ–ÂˆÂ¶.ÂŒqÃ“]Â“\Ã…B]Â¹#ÂœHA:5+Â¤Ân2Â¯UÃ¤'
    //   70: dup
    //   71: astore_2
    //   72: invokevirtual length : ()I
    //   75: istore #4
    //   77: bipush #19
    //   79: istore_1
    //   80: iconst_m1
    //   81: istore_0
    //   82: iconst_5
    //   83: iinc #0, 1
    //   86: aload_2
    //   87: iload_0
    //   88: dup
    //   89: iload_1
    //   90: iadd
    //   91: invokevirtual substring : (II)Ljava/lang/String;
    //   94: iconst_0
    //   95: goto -> 142
    //   98: aload #5
    //   100: swap
    //   101: iload_3
    //   102: iinc #3, 1
    //   105: swap
    //   106: aastore
    //   107: iload_0
    //   108: iload_1
    //   109: iadd
    //   110: dup
    //   111: istore_0
    //   112: iload #4
    //   114: if_icmpge -> 126
    //   117: aload_2
    //   118: iload_0
    //   119: invokevirtual charAt : (I)C
    //   122: istore_1
    //   123: goto -> 82
    //   126: aload #5
    //   128: putstatic burp/Zbmu.a : [Ljava/lang/String;
    //   131: bipush #19
    //   133: anewarray java/lang/String
    //   136: putstatic burp/Zbmu.b : [Ljava/lang/String;
    //   139: goto -> 300
    //   142: dup_x2
    //   143: pop
    //   144: invokevirtual toCharArray : ()[C
    //   147: dup_x1
    //   148: arraylength
    //   149: dup_x2
    //   150: pop
    //   151: iconst_0
    //   152: istore #6
    //   154: dup2_x1
    //   155: pop2
    //   156: dup_x2
    //   157: iconst_1
    //   158: if_icmpgt -> 260
    //   161: dup2
    //   162: swap
    //   163: iload #6
    //   165: dup2_x1
    //   166: caload
    //   167: swap
    //   168: iload #6
    //   170: bipush #7
    //   172: irem
    //   173: tableswitch default -> 242, 0 -> 212, 1 -> 217, 2 -> 222, 3 -> 227, 4 -> 232, 5 -> 237
    //   212: bipush #108
    //   214: goto -> 244
    //   217: bipush #97
    //   219: goto -> 244
    //   222: bipush #9
    //   224: goto -> 244
    //   227: bipush #77
    //   229: goto -> 244
    //   232: bipush #93
    //   234: goto -> 244
    //   237: bipush #55
    //   239: goto -> 244
    //   242: bipush #42
    //   244: ixor
    //   245: ixor
    //   246: i2c
    //   247: castore
    //   248: iinc #6, 1
    //   251: dup
    //   252: ifne -> 260
    //   255: dup2
    //   256: dup_x1
    //   257: goto -> 165
    //   260: dup2_x1
    //   261: pop2
    //   262: dup_x2
    //   263: iload #6
    //   265: if_icmpgt -> 161
    //   268: pop
    //   269: new java/lang/String
    //   272: dup_x1
    //   273: swap
    //   274: invokespecial <init> : ([C)V
    //   277: invokevirtual intern : ()Ljava/lang/String;
    //   280: swap
    //   281: pop
    //   282: swap
    //   283: tableswitch default -> 40, 0 -> 98
    //   300: return
  }
  
  private static String a(int paramInt1, int paramInt2) {
    int i = (paramInt1 ^ 0x7AEA) & 0xFFFF;
    if (b[i] == null) {
      char[] arrayOfChar = a[i].toCharArray();
      switch (arrayOfChar[0] & 0xFF) {
        case 0:
        
        case 1:
        
        case 2:
        
        case 3:
        
        case 4:
        
        case 5:
        
        case 6:
        
        case 7:
        
        case 8:
        
        case 9:
        
        case 10:
        
        case 11:
        
        case 12:
        
        case 13:
        
        case 14:
        
        case 15:
        
        case 16:
        
        case 17:
        
        case 18:
        
        case 19:
        
        case 20:
        
        case 21:
        
        case 22:
        
        case 23:
        
        case 24:
        
        case 25:
        
        case 26:
        
        case 27:
        
        case 28:
        
        case 29:
        
        case 30:
        
        case 31:
        
        case 32:
        
        case 33:
        
        case 34:
        
        case 35:
        
        case 36:
        
        case 37:
        
        case 38:
        
        case 39:
        
        case 40:
        
        case 41:
        
        case 42:
        
        case 43:
        
        case 44:
        
        case 45:
        
        case 46:
        
        case 47:
        
        case 48:
        
        case 49:
        
        case 50:
        
        case 51:
        
        case 52:
        
        case 53:
        
        case 54:
        
        case 55:
        
        case 56:
        
        case 57:
        
        case 58:
        
        case 59:
        
        case 60:
        
        case 61:
        
        case 62:
        
        case 63:
        
        case 64:
        
        case 65:
        
        case 66:
        
        case 67:
        
        case 68:
        
        case 69:
        
        case 70:
        
        case 71:
        
        case 72:
        
        case 73:
        
        case 74:
        
        case 75:
        
        case 76:
        
        case 77:
        
        case 78:
        
        case 79:
        
        case 80:
        
        case 81:
        
        case 82:
        
        case 83:
        
        case 84:
        
        case 85:
        
        case 86:
        
        case 87:
        
        case 88:
        
        case 89:
        
        case 90:
        
        case 91:
        
        case 92:
        
        case 93:
        
        case 94:
        
        case 95:
        
        case 96:
        
        case 97:
        
        case 98:
        
        case 99:
        
        case 100:
        
        case 101:
        
        case 102:
        
        case 103:
        
        case 104:
        
        case 105:
        
        case 106:
        
        case 107:
        
        case 108:
        
        case 109:
        
        case 110:
        
        case 111:
        
        case 112:
        
        case 113:
        
        case 114:
        
        case 115:
        
        case 116:
        
        case 117:
        
        case 118:
        
        case 119:
        
        case 120:
        
        case 121:
        
        case 122:
        
        case 123:
        
        case 124:
        
        case 125:
        
        case 126:
        
        case 127:
        
        case 128:
        
        case 129:
        
        case 130:
        
        case 131:
        
        case 132:
        
        case 133:
        
        case 134:
        
        case 135:
        
        case 136:
        
        case 137:
        
        case 138:
        
        case 139:
        
        case 140:
        
        case 141:
        
        case 142:
        
        case 143:
        
        case 144:
        
        case 145:
        
        case 146:
        
        case 147:
        
        case 148:
        
        case 149:
        
        case 150:
        
        case 151:
        
        case 152:
        
        case 153:
        
        case 154:
        
        case 155:
        
        case 156:
        
        case 157:
        
        case 158:
        
        case 159:
        
        case 160:
        
        case 161:
        
        case 162:
        
        case 163:
        
        case 164:
        
        case 165:
        
        case 166:
        
        case 167:
        
        case 168:
        
        case 169:
        
        case 170:
        
        case 171:
        
        case 172:
        
        case 173:
        
        case 174:
        
        case 175:
        
        case 176:
        
        case 177:
        
        case 178:
        
        case 179:
        
        case 180:
        
        case 181:
        
        case 182:
        
        case 183:
        
        case 184:
        
        case 185:
        
        case 186:
        
        case 187:
        
        case 188:
        
        case 189:
        
        case 190:
        
        case 191:
        
        case 192:
        
        case 193:
        
        case 194:
        
        case 195:
        
        case 196:
        
        case 197:
        
        case 198:
        
        case 199:
        
        case 200:
        
        case 201:
        
        case 202:
        
        case 203:
        
        case 204:
        
        case 205:
        
        case 206:
        
        case 207:
        
        case 208:
        
        case 209:
        
        case 210:
        
        case 211:
        
        case 212:
        
        case 213:
        
        case 214:
        
        case 215:
        
        case 216:
        
        case 217:
        
        case 218:
        
        case 219:
        
        case 220:
        
        case 221:
        
        case 222:
        
        case 223:
        
        case 224:
        
        case 225:
        
        case 226:
        
        case 227:
        
        case 228:
        
        case 229:
        
        case 230:
        
        case 231:
        
        case 232:
        
        case 233:
        
        case 234:
        
        case 235:
        
        case 236:
        
        case 237:
        
        case 238:
        
        case 239:
        
        case 240:
        
        case 241:
        
        case 242:
        
        case 243:
        
        case 244:
        
        case 245:
        
        case 246:
        
        case 247:
        
        case 248:
        
        case 249:
        
        case 250:
        
        case 251:
        
        case 252:
        
        case 253:
        
        case 254:
        
        default:
          break;
      } 
      byte b1 = 32;
      int j = (paramInt2 & 0xFF) - b1;
      if (j < 0)
        j += 256; 
      int k = ((paramInt2 & 0xFFFF) >>> 8) - b1;
      if (k < 0)
        k += 256; 
      for (byte b2 = 0; b2 < arrayOfChar.length; b2++) {
        int m = b2 % 2;
        if (m == 0) {
          arrayOfChar[b2] = (char)(arrayOfChar[b2] ^ j);
          j = ((j >>> 3 | j << 5) ^ arrayOfChar[b2]) & 0xFF;
        } else {
          arrayOfChar[b2] = (char)(arrayOfChar[b2] ^ k);
          k = ((k >>> 3 | k << 5) ^ arrayOfChar[b2]) & 0xFF;
        } 
      } 
      b[i] = (new String(arrayOfChar)).intern();
    } 
    return b[i];
  }
}


/* Location:              C:\Program Files\BurpSuitePro\burpsuite_pro.jar!\burp\Zbmu.class
 * Java compiler version: 21 (65.0)
 * JD-Core Version:       1.1.3
 */