package burp;

import java.math.BigInteger;

class Zbnk extends ClassLoader {
  static String Zg;
  
  static Object Zp;
  
  private static final String[] a;
  
  private static final String[] b;
  
  static void Z_(Object paramObject) {
    Zl_a.ZD = a(12084, 14306);
    Zl_a.ZP = new BigInteger(a(12086, 11331));
    boolean bool = Zt2e.ZN();
    try {
      try {
        if (Zedu.ZD.charAt(Math.abs(((BigInteger)Zmig.Zh).intValue() % 32)) > Zt81.ZL.charAt(Math.abs(((BigInteger)Zkhf.ZU).intValue() % 32))) {
          try {
            Zxzd.Zy(Class.forName(a(12091, -11218)));
            if (!bool)
              Zeub.Zx(Class.forName(a(12089, -17863))); 
          } catch (Throwable throwable) {
            throw a(null);
          } 
          return;
        } 
      } catch (Throwable throwable) {
        throw a(null);
      } 
      Zeub.Zx(Class.forName(a(12089, -17863)));
    } catch (Throwable throwable) {}
  }
  
  static void Zp(Object[] paramArrayOfObject, Object paramObject) throws Throwable {}
  
  static boolean ZW(Object[] paramArrayOfObject, Object paramObject) throws Throwable {
    // Byte code:
    //   0: invokestatic ZN : ()Z
    //   3: istore_2
    //   4: getstatic burp/Zt81.ZY : Ljava/lang/Object;
    //   7: checkcast java/math/BigInteger
    //   10: getstatic burp/Zmz.ZW : Ljava/lang/Object;
    //   13: checkcast java/math/BigInteger
    //   16: invokevirtual add : (Ljava/math/BigInteger;)Ljava/math/BigInteger;
    //   19: putstatic burp/Zvh.Zb : Ljava/lang/Object;
    //   22: getstatic burp/Zbl4.ZW : Ljava/lang/Object;
    //   25: checkcast java/math/BigInteger
    //   28: invokevirtual toByteArray : ()[B
    //   31: astore_3
    //   32: bipush #32
    //   34: newarray int
    //   36: dup
    //   37: iconst_0
    //   38: ldc 876216579
    //   40: iastore
    //   41: dup
    //   42: iconst_1
    //   43: ldc 455999525
    //   45: iastore
    //   46: dup
    //   47: iconst_2
    //   48: ldc 1043334948
    //   50: iastore
    //   51: dup
    //   52: iconst_3
    //   53: ldc 439222784
    //   55: iastore
    //   56: dup
    //   57: iconst_4
    //   58: ldc 372376604
    //   60: iastore
    //   61: dup
    //   62: iconst_5
    //   63: ldc 707731490
    //   65: iastore
    //   66: dup
    //   67: bipush #6
    //   69: ldc 389426184
    //   71: iastore
    //   72: dup
    //   73: bipush #7
    //   75: ldc 973875457
    //   77: iastore
    //   78: dup
    //   79: bipush #8
    //   81: ldc 389160971
    //   83: iastore
    //   84: dup
    //   85: bipush #9
    //   87: ldc 907870729
    //   89: iastore
    //   90: dup
    //   91: bipush #10
    //   93: ldc 121057538
    //   95: iastore
    //   96: dup
    //   97: bipush #11
    //   99: ldc 840500228
    //   101: iastore
    //   102: dup
    //   103: bipush #12
    //   105: ldc 254150144
    //   107: iastore
    //   108: dup
    //   109: bipush #13
    //   111: ldc 924386310
    //   113: iastore
    //   114: dup
    //   115: bipush #14
    //   117: ldc 187632156
    //   119: iastore
    //   120: dup
    //   121: bipush #15
    //   123: ldc 874189824
    //   125: iastore
    //   126: dup
    //   127: bipush #16
    //   129: ldc 655302664
    //   131: iastore
    //   132: dup
    //   133: bipush #17
    //   135: ldc 890966315
    //   137: iastore
    //   138: dup
    //   139: bipush #18
    //   141: ldc 722417666
    //   143: iastore
    //   144: dup
    //   145: bipush #19
    //   147: ldc 1026621720
    //   149: iastore
    //   150: dup
    //   151: bipush #20
    //   153: ldc 957157408
    //   155: iastore
    //   156: dup
    //   157: bipush #21
    //   159: ldc 892536332
    //   161: iastore
    //   162: dup
    //   163: bipush #22
    //   165: ldc 689771012
    //   167: iastore
    //   168: dup
    //   169: bipush #23
    //   171: ldc 221709344
    //   173: iastore
    //   174: dup
    //   175: bipush #24
    //   177: ldc 940377620
    //   179: iastore
    //   180: dup
    //   181: bipush #25
    //   183: ldc 255209728
    //   185: iastore
    //   186: dup
    //   187: bipush #26
    //   189: ldc 1010368540
    //   191: iastore
    //   192: dup
    //   193: bipush #27
    //   195: ldc 220604441
    //   197: iastore
    //   198: dup
    //   199: bipush #28
    //   201: ldc 1008414755
    //   203: iastore
    //   204: dup
    //   205: bipush #29
    //   207: ldc 187049985
    //   209: iastore
    //   210: dup
    //   211: bipush #30
    //   213: ldc 943331329
    //   215: iastore
    //   216: dup
    //   217: bipush #31
    //   219: ldc 170788368
    //   221: iastore
    //   222: astore #5
    //   224: bipush #64
    //   226: newarray int
    //   228: dup
    //   229: iconst_0
    //   230: ldc 16843776
    //   232: iastore
    //   233: dup
    //   234: iconst_1
    //   235: iconst_0
    //   236: iastore
    //   237: dup
    //   238: iconst_2
    //   239: ldc 65536
    //   241: iastore
    //   242: dup
    //   243: iconst_3
    //   244: ldc 16843780
    //   246: iastore
    //   247: dup
    //   248: iconst_4
    //   249: ldc 16842756
    //   251: iastore
    //   252: dup
    //   253: iconst_5
    //   254: ldc 66564
    //   256: iastore
    //   257: dup
    //   258: bipush #6
    //   260: iconst_4
    //   261: iastore
    //   262: dup
    //   263: bipush #7
    //   265: ldc 65536
    //   267: iastore
    //   268: dup
    //   269: bipush #8
    //   271: sipush #1024
    //   274: iastore
    //   275: dup
    //   276: bipush #9
    //   278: ldc 16843776
    //   280: iastore
    //   281: dup
    //   282: bipush #10
    //   284: ldc 16843780
    //   286: iastore
    //   287: dup
    //   288: bipush #11
    //   290: sipush #1024
    //   293: iastore
    //   294: dup
    //   295: bipush #12
    //   297: ldc 16778244
    //   299: iastore
    //   300: dup
    //   301: bipush #13
    //   303: ldc 16842756
    //   305: iastore
    //   306: dup
    //   307: bipush #14
    //   309: ldc 16777216
    //   311: iastore
    //   312: dup
    //   313: bipush #15
    //   315: iconst_4
    //   316: iastore
    //   317: dup
    //   318: bipush #16
    //   320: sipush #1028
    //   323: iastore
    //   324: dup
    //   325: bipush #17
    //   327: ldc 16778240
    //   329: iastore
    //   330: dup
    //   331: bipush #18
    //   333: ldc 16778240
    //   335: iastore
    //   336: dup
    //   337: bipush #19
    //   339: ldc 66560
    //   341: iastore
    //   342: dup
    //   343: bipush #20
    //   345: ldc 66560
    //   347: iastore
    //   348: dup
    //   349: bipush #21
    //   351: ldc 16842752
    //   353: iastore
    //   354: dup
    //   355: bipush #22
    //   357: ldc 16842752
    //   359: iastore
    //   360: dup
    //   361: bipush #23
    //   363: ldc 16778244
    //   365: iastore
    //   366: dup
    //   367: bipush #24
    //   369: ldc 65540
    //   371: iastore
    //   372: dup
    //   373: bipush #25
    //   375: ldc 16777220
    //   377: iastore
    //   378: dup
    //   379: bipush #26
    //   381: ldc 16777220
    //   383: iastore
    //   384: dup
    //   385: bipush #27
    //   387: ldc 65540
    //   389: iastore
    //   390: dup
    //   391: bipush #28
    //   393: iconst_0
    //   394: iastore
    //   395: dup
    //   396: bipush #29
    //   398: sipush #1028
    //   401: iastore
    //   402: dup
    //   403: bipush #30
    //   405: ldc 66564
    //   407: iastore
    //   408: dup
    //   409: bipush #31
    //   411: ldc 16777216
    //   413: iastore
    //   414: dup
    //   415: bipush #32
    //   417: ldc 65536
    //   419: iastore
    //   420: dup
    //   421: bipush #33
    //   423: ldc 16843780
    //   425: iastore
    //   426: dup
    //   427: bipush #34
    //   429: iconst_4
    //   430: iastore
    //   431: dup
    //   432: bipush #35
    //   434: ldc 16842752
    //   436: iastore
    //   437: dup
    //   438: bipush #36
    //   440: ldc 16843776
    //   442: iastore
    //   443: dup
    //   444: bipush #37
    //   446: ldc 16777216
    //   448: iastore
    //   449: dup
    //   450: bipush #38
    //   452: ldc 16777216
    //   454: iastore
    //   455: dup
    //   456: bipush #39
    //   458: sipush #1024
    //   461: iastore
    //   462: dup
    //   463: bipush #40
    //   465: ldc 16842756
    //   467: iastore
    //   468: dup
    //   469: bipush #41
    //   471: ldc 65536
    //   473: iastore
    //   474: dup
    //   475: bipush #42
    //   477: ldc 66560
    //   479: iastore
    //   480: dup
    //   481: bipush #43
    //   483: ldc 16777220
    //   485: iastore
    //   486: dup
    //   487: bipush #44
    //   489: sipush #1024
    //   492: iastore
    //   493: dup
    //   494: bipush #45
    //   496: iconst_4
    //   497: iastore
    //   498: dup
    //   499: bipush #46
    //   501: ldc 16778244
    //   503: iastore
    //   504: dup
    //   505: bipush #47
    //   507: ldc 66564
    //   509: iastore
    //   510: dup
    //   511: bipush #48
    //   513: ldc 16843780
    //   515: iastore
    //   516: dup
    //   517: bipush #49
    //   519: ldc 65540
    //   521: iastore
    //   522: dup
    //   523: bipush #50
    //   525: ldc 16842752
    //   527: iastore
    //   528: dup
    //   529: bipush #51
    //   531: ldc 16778244
    //   533: iastore
    //   534: dup
    //   535: bipush #52
    //   537: ldc 16777220
    //   539: iastore
    //   540: dup
    //   541: bipush #53
    //   543: sipush #1028
    //   546: iastore
    //   547: dup
    //   548: bipush #54
    //   550: ldc 66564
    //   552: iastore
    //   553: dup
    //   554: bipush #55
    //   556: ldc 16843776
    //   558: iastore
    //   559: dup
    //   560: bipush #56
    //   562: sipush #1028
    //   565: iastore
    //   566: dup
    //   567: bipush #57
    //   569: ldc 16778240
    //   571: iastore
    //   572: dup
    //   573: bipush #58
    //   575: ldc 16778240
    //   577: iastore
    //   578: dup
    //   579: bipush #59
    //   581: iconst_0
    //   582: iastore
    //   583: dup
    //   584: bipush #60
    //   586: ldc 65540
    //   588: iastore
    //   589: dup
    //   590: bipush #61
    //   592: ldc 66560
    //   594: iastore
    //   595: dup
    //   596: bipush #62
    //   598: iconst_0
    //   599: iastore
    //   600: dup
    //   601: bipush #63
    //   603: ldc 16842756
    //   605: iastore
    //   606: astore #6
    //   608: bipush #64
    //   610: newarray int
    //   612: dup
    //   613: iconst_0
    //   614: ldc -2146402272
    //   616: iastore
    //   617: dup
    //   618: iconst_1
    //   619: ldc -2147450880
    //   621: iastore
    //   622: dup
    //   623: iconst_2
    //   624: ldc 32768
    //   626: iastore
    //   627: dup
    //   628: iconst_3
    //   629: ldc 1081376
    //   631: iastore
    //   632: dup
    //   633: iconst_4
    //   634: ldc 1048576
    //   636: iastore
    //   637: dup
    //   638: iconst_5
    //   639: bipush #32
    //   641: iastore
    //   642: dup
    //   643: bipush #6
    //   645: ldc -2146435040
    //   647: iastore
    //   648: dup
    //   649: bipush #7
    //   651: ldc -2147450848
    //   653: iastore
    //   654: dup
    //   655: bipush #8
    //   657: ldc -2147483616
    //   659: iastore
    //   660: dup
    //   661: bipush #9
    //   663: ldc -2146402272
    //   665: iastore
    //   666: dup
    //   667: bipush #10
    //   669: ldc -2146402304
    //   671: iastore
    //   672: dup
    //   673: bipush #11
    //   675: ldc -2147483648
    //   677: iastore
    //   678: dup
    //   679: bipush #12
    //   681: ldc -2147450880
    //   683: iastore
    //   684: dup
    //   685: bipush #13
    //   687: ldc 1048576
    //   689: iastore
    //   690: dup
    //   691: bipush #14
    //   693: bipush #32
    //   695: iastore
    //   696: dup
    //   697: bipush #15
    //   699: ldc -2146435040
    //   701: iastore
    //   702: dup
    //   703: bipush #16
    //   705: ldc 1081344
    //   707: iastore
    //   708: dup
    //   709: bipush #17
    //   711: ldc 1048608
    //   713: iastore
    //   714: dup
    //   715: bipush #18
    //   717: ldc -2147450848
    //   719: iastore
    //   720: dup
    //   721: bipush #19
    //   723: iconst_0
    //   724: iastore
    //   725: dup
    //   726: bipush #20
    //   728: ldc -2147483648
    //   730: iastore
    //   731: dup
    //   732: bipush #21
    //   734: ldc 32768
    //   736: iastore
    //   737: dup
    //   738: bipush #22
    //   740: ldc 1081376
    //   742: iastore
    //   743: dup
    //   744: bipush #23
    //   746: ldc -2146435072
    //   748: iastore
    //   749: dup
    //   750: bipush #24
    //   752: ldc 1048608
    //   754: iastore
    //   755: dup
    //   756: bipush #25
    //   758: ldc -2147483616
    //   760: iastore
    //   761: dup
    //   762: bipush #26
    //   764: iconst_0
    //   765: iastore
    //   766: dup
    //   767: bipush #27
    //   769: ldc 1081344
    //   771: iastore
    //   772: dup
    //   773: bipush #28
    //   775: ldc 32800
    //   777: iastore
    //   778: dup
    //   779: bipush #29
    //   781: ldc -2146402304
    //   783: iastore
    //   784: dup
    //   785: bipush #30
    //   787: ldc -2146435072
    //   789: iastore
    //   790: dup
    //   791: bipush #31
    //   793: ldc 32800
    //   795: iastore
    //   796: dup
    //   797: bipush #32
    //   799: iconst_0
    //   800: iastore
    //   801: dup
    //   802: bipush #33
    //   804: ldc 1081376
    //   806: iastore
    //   807: dup
    //   808: bipush #34
    //   810: ldc -2146435040
    //   812: iastore
    //   813: dup
    //   814: bipush #35
    //   816: ldc 1048576
    //   818: iastore
    //   819: dup
    //   820: bipush #36
    //   822: ldc -2147450848
    //   824: iastore
    //   825: dup
    //   826: bipush #37
    //   828: ldc -2146435072
    //   830: iastore
    //   831: dup
    //   832: bipush #38
    //   834: ldc -2146402304
    //   836: iastore
    //   837: dup
    //   838: bipush #39
    //   840: ldc 32768
    //   842: iastore
    //   843: dup
    //   844: bipush #40
    //   846: ldc -2146435072
    //   848: iastore
    //   849: dup
    //   850: bipush #41
    //   852: ldc -2147450880
    //   854: iastore
    //   855: dup
    //   856: bipush #42
    //   858: bipush #32
    //   860: iastore
    //   861: dup
    //   862: bipush #43
    //   864: ldc -2146402272
    //   866: iastore
    //   867: dup
    //   868: bipush #44
    //   870: ldc 1081376
    //   872: iastore
    //   873: dup
    //   874: bipush #45
    //   876: bipush #32
    //   878: iastore
    //   879: dup
    //   880: bipush #46
    //   882: ldc 32768
    //   884: iastore
    //   885: dup
    //   886: bipush #47
    //   888: ldc -2147483648
    //   890: iastore
    //   891: dup
    //   892: bipush #48
    //   894: ldc 32800
    //   896: iastore
    //   897: dup
    //   898: bipush #49
    //   900: ldc -2146402304
    //   902: iastore
    //   903: dup
    //   904: bipush #50
    //   906: ldc 1048576
    //   908: iastore
    //   909: dup
    //   910: bipush #51
    //   912: ldc -2147483616
    //   914: iastore
    //   915: dup
    //   916: bipush #52
    //   918: ldc 1048608
    //   920: iastore
    //   921: dup
    //   922: bipush #53
    //   924: ldc -2147450848
    //   926: iastore
    //   927: dup
    //   928: bipush #54
    //   930: ldc -2147483616
    //   932: iastore
    //   933: dup
    //   934: bipush #55
    //   936: ldc 1048608
    //   938: iastore
    //   939: dup
    //   940: bipush #56
    //   942: ldc 1081344
    //   944: iastore
    //   945: dup
    //   946: bipush #57
    //   948: iconst_0
    //   949: iastore
    //   950: dup
    //   951: bipush #58
    //   953: ldc -2147450880
    //   955: iastore
    //   956: dup
    //   957: bipush #59
    //   959: ldc 32800
    //   961: iastore
    //   962: dup
    //   963: bipush #60
    //   965: ldc -2147483648
    //   967: iastore
    //   968: dup
    //   969: bipush #61
    //   971: ldc -2146435040
    //   973: iastore
    //   974: dup
    //   975: bipush #62
    //   977: ldc -2146402272
    //   979: iastore
    //   980: dup
    //   981: bipush #63
    //   983: ldc 1081344
    //   985: iastore
    //   986: astore #7
    //   988: bipush #64
    //   990: newarray int
    //   992: dup
    //   993: iconst_0
    //   994: sipush #520
    //   997: iastore
    //   998: dup
    //   999: iconst_1
    //   1000: ldc 134349312
    //   1002: iastore
    //   1003: dup
    //   1004: iconst_2
    //   1005: iconst_0
    //   1006: iastore
    //   1007: dup
    //   1008: iconst_3
    //   1009: ldc 134348808
    //   1011: iastore
    //   1012: dup
    //   1013: iconst_4
    //   1014: ldc 134218240
    //   1016: iastore
    //   1017: dup
    //   1018: iconst_5
    //   1019: iconst_0
    //   1020: iastore
    //   1021: dup
    //   1022: bipush #6
    //   1024: ldc 131592
    //   1026: iastore
    //   1027: dup
    //   1028: bipush #7
    //   1030: ldc 134218240
    //   1032: iastore
    //   1033: dup
    //   1034: bipush #8
    //   1036: ldc 131080
    //   1038: iastore
    //   1039: dup
    //   1040: bipush #9
    //   1042: ldc 134217736
    //   1044: iastore
    //   1045: dup
    //   1046: bipush #10
    //   1048: ldc 134217736
    //   1050: iastore
    //   1051: dup
    //   1052: bipush #11
    //   1054: ldc 131072
    //   1056: iastore
    //   1057: dup
    //   1058: bipush #12
    //   1060: ldc 134349320
    //   1062: iastore
    //   1063: dup
    //   1064: bipush #13
    //   1066: ldc 131080
    //   1068: iastore
    //   1069: dup
    //   1070: bipush #14
    //   1072: ldc 134348800
    //   1074: iastore
    //   1075: dup
    //   1076: bipush #15
    //   1078: sipush #520
    //   1081: iastore
    //   1082: dup
    //   1083: bipush #16
    //   1085: ldc 134217728
    //   1087: iastore
    //   1088: dup
    //   1089: bipush #17
    //   1091: bipush #8
    //   1093: iastore
    //   1094: dup
    //   1095: bipush #18
    //   1097: ldc 134349312
    //   1099: iastore
    //   1100: dup
    //   1101: bipush #19
    //   1103: sipush #512
    //   1106: iastore
    //   1107: dup
    //   1108: bipush #20
    //   1110: ldc 131584
    //   1112: iastore
    //   1113: dup
    //   1114: bipush #21
    //   1116: ldc 134348800
    //   1118: iastore
    //   1119: dup
    //   1120: bipush #22
    //   1122: ldc 134348808
    //   1124: iastore
    //   1125: dup
    //   1126: bipush #23
    //   1128: ldc 131592
    //   1130: iastore
    //   1131: dup
    //   1132: bipush #24
    //   1134: ldc 134218248
    //   1136: iastore
    //   1137: dup
    //   1138: bipush #25
    //   1140: ldc 131584
    //   1142: iastore
    //   1143: dup
    //   1144: bipush #26
    //   1146: ldc 131072
    //   1148: iastore
    //   1149: dup
    //   1150: bipush #27
    //   1152: ldc 134218248
    //   1154: iastore
    //   1155: dup
    //   1156: bipush #28
    //   1158: bipush #8
    //   1160: iastore
    //   1161: dup
    //   1162: bipush #29
    //   1164: ldc 134349320
    //   1166: iastore
    //   1167: dup
    //   1168: bipush #30
    //   1170: sipush #512
    //   1173: iastore
    //   1174: dup
    //   1175: bipush #31
    //   1177: ldc 134217728
    //   1179: iastore
    //   1180: dup
    //   1181: bipush #32
    //   1183: ldc 134349312
    //   1185: iastore
    //   1186: dup
    //   1187: bipush #33
    //   1189: ldc 134217728
    //   1191: iastore
    //   1192: dup
    //   1193: bipush #34
    //   1195: ldc 131080
    //   1197: iastore
    //   1198: dup
    //   1199: bipush #35
    //   1201: sipush #520
    //   1204: iastore
    //   1205: dup
    //   1206: bipush #36
    //   1208: ldc 131072
    //   1210: iastore
    //   1211: dup
    //   1212: bipush #37
    //   1214: ldc 134349312
    //   1216: iastore
    //   1217: dup
    //   1218: bipush #38
    //   1220: ldc 134218240
    //   1222: iastore
    //   1223: dup
    //   1224: bipush #39
    //   1226: iconst_0
    //   1227: iastore
    //   1228: dup
    //   1229: bipush #40
    //   1231: sipush #512
    //   1234: iastore
    //   1235: dup
    //   1236: bipush #41
    //   1238: ldc 131080
    //   1240: iastore
    //   1241: dup
    //   1242: bipush #42
    //   1244: ldc 134349320
    //   1246: iastore
    //   1247: dup
    //   1248: bipush #43
    //   1250: ldc 134218240
    //   1252: iastore
    //   1253: dup
    //   1254: bipush #44
    //   1256: ldc 134217736
    //   1258: iastore
    //   1259: dup
    //   1260: bipush #45
    //   1262: sipush #512
    //   1265: iastore
    //   1266: dup
    //   1267: bipush #46
    //   1269: iconst_0
    //   1270: iastore
    //   1271: dup
    //   1272: bipush #47
    //   1274: ldc 134348808
    //   1276: iastore
    //   1277: dup
    //   1278: bipush #48
    //   1280: ldc 134218248
    //   1282: iastore
    //   1283: dup
    //   1284: bipush #49
    //   1286: ldc 131072
    //   1288: iastore
    //   1289: dup
    //   1290: bipush #50
    //   1292: ldc 134217728
    //   1294: iastore
    //   1295: dup
    //   1296: bipush #51
    //   1298: ldc 134349320
    //   1300: iastore
    //   1301: dup
    //   1302: bipush #52
    //   1304: bipush #8
    //   1306: iastore
    //   1307: dup
    //   1308: bipush #53
    //   1310: ldc 131592
    //   1312: iastore
    //   1313: dup
    //   1314: bipush #54
    //   1316: ldc 131584
    //   1318: iastore
    //   1319: dup
    //   1320: bipush #55
    //   1322: ldc 134217736
    //   1324: iastore
    //   1325: dup
    //   1326: bipush #56
    //   1328: ldc 134348800
    //   1330: iastore
    //   1331: dup
    //   1332: bipush #57
    //   1334: ldc 134218248
    //   1336: iastore
    //   1337: dup
    //   1338: bipush #58
    //   1340: sipush #520
    //   1343: iastore
    //   1344: dup
    //   1345: bipush #59
    //   1347: ldc 134348800
    //   1349: iastore
    //   1350: dup
    //   1351: bipush #60
    //   1353: ldc 131592
    //   1355: iastore
    //   1356: dup
    //   1357: bipush #61
    //   1359: bipush #8
    //   1361: iastore
    //   1362: dup
    //   1363: bipush #62
    //   1365: ldc 134348808
    //   1367: iastore
    //   1368: dup
    //   1369: bipush #63
    //   1371: ldc 131584
    //   1373: iastore
    //   1374: astore #8
    //   1376: bipush #64
    //   1378: newarray int
    //   1380: dup
    //   1381: iconst_0
    //   1382: ldc 8396801
    //   1384: iastore
    //   1385: dup
    //   1386: iconst_1
    //   1387: sipush #8321
    //   1390: iastore
    //   1391: dup
    //   1392: iconst_2
    //   1393: sipush #8321
    //   1396: iastore
    //   1397: dup
    //   1398: iconst_3
    //   1399: sipush #128
    //   1402: iastore
    //   1403: dup
    //   1404: iconst_4
    //   1405: ldc 8396928
    //   1407: iastore
    //   1408: dup
    //   1409: iconst_5
    //   1410: ldc 8388737
    //   1412: iastore
    //   1413: dup
    //   1414: bipush #6
    //   1416: ldc 8388609
    //   1418: iastore
    //   1419: dup
    //   1420: bipush #7
    //   1422: sipush #8193
    //   1425: iastore
    //   1426: dup
    //   1427: bipush #8
    //   1429: iconst_0
    //   1430: iastore
    //   1431: dup
    //   1432: bipush #9
    //   1434: ldc 8396800
    //   1436: iastore
    //   1437: dup
    //   1438: bipush #10
    //   1440: ldc 8396800
    //   1442: iastore
    //   1443: dup
    //   1444: bipush #11
    //   1446: ldc 8396929
    //   1448: iastore
    //   1449: dup
    //   1450: bipush #12
    //   1452: sipush #129
    //   1455: iastore
    //   1456: dup
    //   1457: bipush #13
    //   1459: iconst_0
    //   1460: iastore
    //   1461: dup
    //   1462: bipush #14
    //   1464: ldc 8388736
    //   1466: iastore
    //   1467: dup
    //   1468: bipush #15
    //   1470: ldc 8388609
    //   1472: iastore
    //   1473: dup
    //   1474: bipush #16
    //   1476: iconst_1
    //   1477: iastore
    //   1478: dup
    //   1479: bipush #17
    //   1481: sipush #8192
    //   1484: iastore
    //   1485: dup
    //   1486: bipush #18
    //   1488: ldc 8388608
    //   1490: iastore
    //   1491: dup
    //   1492: bipush #19
    //   1494: ldc 8396801
    //   1496: iastore
    //   1497: dup
    //   1498: bipush #20
    //   1500: sipush #128
    //   1503: iastore
    //   1504: dup
    //   1505: bipush #21
    //   1507: ldc 8388608
    //   1509: iastore
    //   1510: dup
    //   1511: bipush #22
    //   1513: sipush #8193
    //   1516: iastore
    //   1517: dup
    //   1518: bipush #23
    //   1520: sipush #8320
    //   1523: iastore
    //   1524: dup
    //   1525: bipush #24
    //   1527: ldc 8388737
    //   1529: iastore
    //   1530: dup
    //   1531: bipush #25
    //   1533: iconst_1
    //   1534: iastore
    //   1535: dup
    //   1536: bipush #26
    //   1538: sipush #8320
    //   1541: iastore
    //   1542: dup
    //   1543: bipush #27
    //   1545: ldc 8388736
    //   1547: iastore
    //   1548: dup
    //   1549: bipush #28
    //   1551: sipush #8192
    //   1554: iastore
    //   1555: dup
    //   1556: bipush #29
    //   1558: ldc 8396928
    //   1560: iastore
    //   1561: dup
    //   1562: bipush #30
    //   1564: ldc 8396929
    //   1566: iastore
    //   1567: dup
    //   1568: bipush #31
    //   1570: sipush #129
    //   1573: iastore
    //   1574: dup
    //   1575: bipush #32
    //   1577: ldc 8388736
    //   1579: iastore
    //   1580: dup
    //   1581: bipush #33
    //   1583: ldc 8388609
    //   1585: iastore
    //   1586: dup
    //   1587: bipush #34
    //   1589: ldc 8396800
    //   1591: iastore
    //   1592: dup
    //   1593: bipush #35
    //   1595: ldc 8396929
    //   1597: iastore
    //   1598: dup
    //   1599: bipush #36
    //   1601: sipush #129
    //   1604: iastore
    //   1605: dup
    //   1606: bipush #37
    //   1608: iconst_0
    //   1609: iastore
    //   1610: dup
    //   1611: bipush #38
    //   1613: iconst_0
    //   1614: iastore
    //   1615: dup
    //   1616: bipush #39
    //   1618: ldc 8396800
    //   1620: iastore
    //   1621: dup
    //   1622: bipush #40
    //   1624: sipush #8320
    //   1627: iastore
    //   1628: dup
    //   1629: bipush #41
    //   1631: ldc 8388736
    //   1633: iastore
    //   1634: dup
    //   1635: bipush #42
    //   1637: ldc 8388737
    //   1639: iastore
    //   1640: dup
    //   1641: bipush #43
    //   1643: iconst_1
    //   1644: iastore
    //   1645: dup
    //   1646: bipush #44
    //   1648: ldc 8396801
    //   1650: iastore
    //   1651: dup
    //   1652: bipush #45
    //   1654: sipush #8321
    //   1657: iastore
    //   1658: dup
    //   1659: bipush #46
    //   1661: sipush #8321
    //   1664: iastore
    //   1665: dup
    //   1666: bipush #47
    //   1668: sipush #128
    //   1671: iastore
    //   1672: dup
    //   1673: bipush #48
    //   1675: ldc 8396929
    //   1677: iastore
    //   1678: dup
    //   1679: bipush #49
    //   1681: sipush #129
    //   1684: iastore
    //   1685: dup
    //   1686: bipush #50
    //   1688: iconst_1
    //   1689: iastore
    //   1690: dup
    //   1691: bipush #51
    //   1693: sipush #8192
    //   1696: iastore
    //   1697: dup
    //   1698: bipush #52
    //   1700: ldc 8388609
    //   1702: iastore
    //   1703: dup
    //   1704: bipush #53
    //   1706: sipush #8193
    //   1709: iastore
    //   1710: dup
    //   1711: bipush #54
    //   1713: ldc 8396928
    //   1715: iastore
    //   1716: dup
    //   1717: bipush #55
    //   1719: ldc 8388737
    //   1721: iastore
    //   1722: dup
    //   1723: bipush #56
    //   1725: sipush #8193
    //   1728: iastore
    //   1729: dup
    //   1730: bipush #57
    //   1732: sipush #8320
    //   1735: iastore
    //   1736: dup
    //   1737: bipush #58
    //   1739: ldc 8388608
    //   1741: iastore
    //   1742: dup
    //   1743: bipush #59
    //   1745: ldc 8396801
    //   1747: iastore
    //   1748: dup
    //   1749: bipush #60
    //   1751: sipush #128
    //   1754: iastore
    //   1755: dup
    //   1756: bipush #61
    //   1758: ldc 8388608
    //   1760: iastore
    //   1761: dup
    //   1762: bipush #62
    //   1764: sipush #8192
    //   1767: iastore
    //   1768: dup
    //   1769: bipush #63
    //   1771: ldc 8396928
    //   1773: iastore
    //   1774: astore #9
    //   1776: bipush #64
    //   1778: newarray int
    //   1780: dup
    //   1781: iconst_0
    //   1782: sipush #256
    //   1785: iastore
    //   1786: dup
    //   1787: iconst_1
    //   1788: ldc 34078976
    //   1790: iastore
    //   1791: dup
    //   1792: iconst_2
    //   1793: ldc 34078720
    //   1795: iastore
    //   1796: dup
    //   1797: iconst_3
    //   1798: ldc 1107296512
    //   1800: iastore
    //   1801: dup
    //   1802: iconst_4
    //   1803: ldc 524288
    //   1805: iastore
    //   1806: dup
    //   1807: iconst_5
    //   1808: sipush #256
    //   1811: iastore
    //   1812: dup
    //   1813: bipush #6
    //   1815: ldc 1073741824
    //   1817: iastore
    //   1818: dup
    //   1819: bipush #7
    //   1821: ldc 34078720
    //   1823: iastore
    //   1824: dup
    //   1825: bipush #8
    //   1827: ldc 1074266368
    //   1829: iastore
    //   1830: dup
    //   1831: bipush #9
    //   1833: ldc 524288
    //   1835: iastore
    //   1836: dup
    //   1837: bipush #10
    //   1839: ldc 33554688
    //   1841: iastore
    //   1842: dup
    //   1843: bipush #11
    //   1845: ldc 1074266368
    //   1847: iastore
    //   1848: dup
    //   1849: bipush #12
    //   1851: ldc 1107296512
    //   1853: iastore
    //   1854: dup
    //   1855: bipush #13
    //   1857: ldc 1107820544
    //   1859: iastore
    //   1860: dup
    //   1861: bipush #14
    //   1863: ldc 524544
    //   1865: iastore
    //   1866: dup
    //   1867: bipush #15
    //   1869: ldc 1073741824
    //   1871: iastore
    //   1872: dup
    //   1873: bipush #16
    //   1875: ldc 33554432
    //   1877: iastore
    //   1878: dup
    //   1879: bipush #17
    //   1881: ldc 1074266112
    //   1883: iastore
    //   1884: dup
    //   1885: bipush #18
    //   1887: ldc 1074266112
    //   1889: iastore
    //   1890: dup
    //   1891: bipush #19
    //   1893: iconst_0
    //   1894: iastore
    //   1895: dup
    //   1896: bipush #20
    //   1898: ldc 1073742080
    //   1900: iastore
    //   1901: dup
    //   1902: bipush #21
    //   1904: ldc 1107820800
    //   1906: iastore
    //   1907: dup
    //   1908: bipush #22
    //   1910: ldc 1107820800
    //   1912: iastore
    //   1913: dup
    //   1914: bipush #23
    //   1916: ldc 33554688
    //   1918: iastore
    //   1919: dup
    //   1920: bipush #24
    //   1922: ldc 1107820544
    //   1924: iastore
    //   1925: dup
    //   1926: bipush #25
    //   1928: ldc 1073742080
    //   1930: iastore
    //   1931: dup
    //   1932: bipush #26
    //   1934: iconst_0
    //   1935: iastore
    //   1936: dup
    //   1937: bipush #27
    //   1939: ldc 1107296256
    //   1941: iastore
    //   1942: dup
    //   1943: bipush #28
    //   1945: ldc 34078976
    //   1947: iastore
    //   1948: dup
    //   1949: bipush #29
    //   1951: ldc 33554432
    //   1953: iastore
    //   1954: dup
    //   1955: bipush #30
    //   1957: ldc 1107296256
    //   1959: iastore
    //   1960: dup
    //   1961: bipush #31
    //   1963: ldc 524544
    //   1965: iastore
    //   1966: dup
    //   1967: bipush #32
    //   1969: ldc 524288
    //   1971: iastore
    //   1972: dup
    //   1973: bipush #33
    //   1975: ldc 1107296512
    //   1977: iastore
    //   1978: dup
    //   1979: bipush #34
    //   1981: sipush #256
    //   1984: iastore
    //   1985: dup
    //   1986: bipush #35
    //   1988: ldc 33554432
    //   1990: iastore
    //   1991: dup
    //   1992: bipush #36
    //   1994: ldc 1073741824
    //   1996: iastore
    //   1997: dup
    //   1998: bipush #37
    //   2000: ldc 34078720
    //   2002: iastore
    //   2003: dup
    //   2004: bipush #38
    //   2006: ldc 1107296512
    //   2008: iastore
    //   2009: dup
    //   2010: bipush #39
    //   2012: ldc 1074266368
    //   2014: iastore
    //   2015: dup
    //   2016: bipush #40
    //   2018: ldc 33554688
    //   2020: iastore
    //   2021: dup
    //   2022: bipush #41
    //   2024: ldc 1073741824
    //   2026: iastore
    //   2027: dup
    //   2028: bipush #42
    //   2030: ldc 1107820544
    //   2032: iastore
    //   2033: dup
    //   2034: bipush #43
    //   2036: ldc 34078976
    //   2038: iastore
    //   2039: dup
    //   2040: bipush #44
    //   2042: ldc 1074266368
    //   2044: iastore
    //   2045: dup
    //   2046: bipush #45
    //   2048: sipush #256
    //   2051: iastore
    //   2052: dup
    //   2053: bipush #46
    //   2055: ldc 33554432
    //   2057: iastore
    //   2058: dup
    //   2059: bipush #47
    //   2061: ldc 1107820544
    //   2063: iastore
    //   2064: dup
    //   2065: bipush #48
    //   2067: ldc 1107820800
    //   2069: iastore
    //   2070: dup
    //   2071: bipush #49
    //   2073: ldc 524544
    //   2075: iastore
    //   2076: dup
    //   2077: bipush #50
    //   2079: ldc 1107296256
    //   2081: iastore
    //   2082: dup
    //   2083: bipush #51
    //   2085: ldc 1107820800
    //   2087: iastore
    //   2088: dup
    //   2089: bipush #52
    //   2091: ldc 34078720
    //   2093: iastore
    //   2094: dup
    //   2095: bipush #53
    //   2097: iconst_0
    //   2098: iastore
    //   2099: dup
    //   2100: bipush #54
    //   2102: ldc 1074266112
    //   2104: iastore
    //   2105: dup
    //   2106: bipush #55
    //   2108: ldc 1107296256
    //   2110: iastore
    //   2111: dup
    //   2112: bipush #56
    //   2114: ldc 524544
    //   2116: iastore
    //   2117: dup
    //   2118: bipush #57
    //   2120: ldc 33554688
    //   2122: iastore
    //   2123: dup
    //   2124: bipush #58
    //   2126: ldc 1073742080
    //   2128: iastore
    //   2129: dup
    //   2130: bipush #59
    //   2132: ldc 524288
    //   2134: iastore
    //   2135: dup
    //   2136: bipush #60
    //   2138: iconst_0
    //   2139: iastore
    //   2140: dup
    //   2141: bipush #61
    //   2143: ldc 1074266112
    //   2145: iastore
    //   2146: dup
    //   2147: bipush #62
    //   2149: ldc 34078976
    //   2151: iastore
    //   2152: dup
    //   2153: bipush #63
    //   2155: ldc 1073742080
    //   2157: iastore
    //   2158: astore #10
    //   2160: bipush #64
    //   2162: newarray int
    //   2164: dup
    //   2165: iconst_0
    //   2166: ldc 536870928
    //   2168: iastore
    //   2169: dup
    //   2170: iconst_1
    //   2171: ldc 541065216
    //   2173: iastore
    //   2174: dup
    //   2175: iconst_2
    //   2176: sipush #16384
    //   2179: iastore
    //   2180: dup
    //   2181: iconst_3
    //   2182: ldc 541081616
    //   2184: iastore
    //   2185: dup
    //   2186: iconst_4
    //   2187: ldc 541065216
    //   2189: iastore
    //   2190: dup
    //   2191: iconst_5
    //   2192: bipush #16
    //   2194: iastore
    //   2195: dup
    //   2196: bipush #6
    //   2198: ldc 541081616
    //   2200: iastore
    //   2201: dup
    //   2202: bipush #7
    //   2204: ldc 4194304
    //   2206: iastore
    //   2207: dup
    //   2208: bipush #8
    //   2210: ldc 536887296
    //   2212: iastore
    //   2213: dup
    //   2214: bipush #9
    //   2216: ldc 4210704
    //   2218: iastore
    //   2219: dup
    //   2220: bipush #10
    //   2222: ldc 4194304
    //   2224: iastore
    //   2225: dup
    //   2226: bipush #11
    //   2228: ldc 536870928
    //   2230: iastore
    //   2231: dup
    //   2232: bipush #12
    //   2234: ldc 4194320
    //   2236: iastore
    //   2237: dup
    //   2238: bipush #13
    //   2240: ldc 536887296
    //   2242: iastore
    //   2243: dup
    //   2244: bipush #14
    //   2246: ldc 536870912
    //   2248: iastore
    //   2249: dup
    //   2250: bipush #15
    //   2252: sipush #16400
    //   2255: iastore
    //   2256: dup
    //   2257: bipush #16
    //   2259: iconst_0
    //   2260: iastore
    //   2261: dup
    //   2262: bipush #17
    //   2264: ldc 4194320
    //   2266: iastore
    //   2267: dup
    //   2268: bipush #18
    //   2270: ldc 536887312
    //   2272: iastore
    //   2273: dup
    //   2274: bipush #19
    //   2276: sipush #16384
    //   2279: iastore
    //   2280: dup
    //   2281: bipush #20
    //   2283: ldc 4210688
    //   2285: iastore
    //   2286: dup
    //   2287: bipush #21
    //   2289: ldc 536887312
    //   2291: iastore
    //   2292: dup
    //   2293: bipush #22
    //   2295: bipush #16
    //   2297: iastore
    //   2298: dup
    //   2299: bipush #23
    //   2301: ldc 541065232
    //   2303: iastore
    //   2304: dup
    //   2305: bipush #24
    //   2307: ldc 541065232
    //   2309: iastore
    //   2310: dup
    //   2311: bipush #25
    //   2313: iconst_0
    //   2314: iastore
    //   2315: dup
    //   2316: bipush #26
    //   2318: ldc 4210704
    //   2320: iastore
    //   2321: dup
    //   2322: bipush #27
    //   2324: ldc 541081600
    //   2326: iastore
    //   2327: dup
    //   2328: bipush #28
    //   2330: sipush #16400
    //   2333: iastore
    //   2334: dup
    //   2335: bipush #29
    //   2337: ldc 4210688
    //   2339: iastore
    //   2340: dup
    //   2341: bipush #30
    //   2343: ldc 541081600
    //   2345: iastore
    //   2346: dup
    //   2347: bipush #31
    //   2349: ldc 536870912
    //   2351: iastore
    //   2352: dup
    //   2353: bipush #32
    //   2355: ldc 536887296
    //   2357: iastore
    //   2358: dup
    //   2359: bipush #33
    //   2361: bipush #16
    //   2363: iastore
    //   2364: dup
    //   2365: bipush #34
    //   2367: ldc 541065232
    //   2369: iastore
    //   2370: dup
    //   2371: bipush #35
    //   2373: ldc 4210688
    //   2375: iastore
    //   2376: dup
    //   2377: bipush #36
    //   2379: ldc 541081616
    //   2381: iastore
    //   2382: dup
    //   2383: bipush #37
    //   2385: ldc 4194304
    //   2387: iastore
    //   2388: dup
    //   2389: bipush #38
    //   2391: sipush #16400
    //   2394: iastore
    //   2395: dup
    //   2396: bipush #39
    //   2398: ldc 536870928
    //   2400: iastore
    //   2401: dup
    //   2402: bipush #40
    //   2404: ldc 4194304
    //   2406: iastore
    //   2407: dup
    //   2408: bipush #41
    //   2410: ldc 536887296
    //   2412: iastore
    //   2413: dup
    //   2414: bipush #42
    //   2416: ldc 536870912
    //   2418: iastore
    //   2419: dup
    //   2420: bipush #43
    //   2422: sipush #16400
    //   2425: iastore
    //   2426: dup
    //   2427: bipush #44
    //   2429: ldc 536870928
    //   2431: iastore
    //   2432: dup
    //   2433: bipush #45
    //   2435: ldc 541081616
    //   2437: iastore
    //   2438: dup
    //   2439: bipush #46
    //   2441: ldc 4210688
    //   2443: iastore
    //   2444: dup
    //   2445: bipush #47
    //   2447: ldc 541065216
    //   2449: iastore
    //   2450: dup
    //   2451: bipush #48
    //   2453: ldc 4210704
    //   2455: iastore
    //   2456: dup
    //   2457: bipush #49
    //   2459: ldc 541081600
    //   2461: iastore
    //   2462: dup
    //   2463: bipush #50
    //   2465: iconst_0
    //   2466: iastore
    //   2467: dup
    //   2468: bipush #51
    //   2470: ldc 541065232
    //   2472: iastore
    //   2473: dup
    //   2474: bipush #52
    //   2476: bipush #16
    //   2478: iastore
    //   2479: dup
    //   2480: bipush #53
    //   2482: sipush #16384
    //   2485: iastore
    //   2486: dup
    //   2487: bipush #54
    //   2489: ldc 541065216
    //   2491: iastore
    //   2492: dup
    //   2493: bipush #55
    //   2495: ldc 4210704
    //   2497: iastore
    //   2498: dup
    //   2499: bipush #56
    //   2501: sipush #16384
    //   2504: iastore
    //   2505: dup
    //   2506: bipush #57
    //   2508: ldc 4194320
    //   2510: iastore
    //   2511: dup
    //   2512: bipush #58
    //   2514: ldc 536887312
    //   2516: iastore
    //   2517: dup
    //   2518: bipush #59
    //   2520: iconst_0
    //   2521: iastore
    //   2522: dup
    //   2523: bipush #60
    //   2525: ldc 541081600
    //   2527: iastore
    //   2528: dup
    //   2529: bipush #61
    //   2531: ldc 536870912
    //   2533: iastore
    //   2534: dup
    //   2535: bipush #62
    //   2537: ldc 4194320
    //   2539: iastore
    //   2540: dup
    //   2541: bipush #63
    //   2543: ldc 536887312
    //   2545: iastore
    //   2546: astore #11
    //   2548: bipush #64
    //   2550: newarray int
    //   2552: dup
    //   2553: iconst_0
    //   2554: ldc 2097152
    //   2556: iastore
    //   2557: dup
    //   2558: iconst_1
    //   2559: ldc 69206018
    //   2561: iastore
    //   2562: dup
    //   2563: iconst_2
    //   2564: ldc 67110914
    //   2566: iastore
    //   2567: dup
    //   2568: iconst_3
    //   2569: iconst_0
    //   2570: iastore
    //   2571: dup
    //   2572: iconst_4
    //   2573: sipush #2048
    //   2576: iastore
    //   2577: dup
    //   2578: iconst_5
    //   2579: ldc 67110914
    //   2581: iastore
    //   2582: dup
    //   2583: bipush #6
    //   2585: ldc 2099202
    //   2587: iastore
    //   2588: dup
    //   2589: bipush #7
    //   2591: ldc 69208064
    //   2593: iastore
    //   2594: dup
    //   2595: bipush #8
    //   2597: ldc 69208066
    //   2599: iastore
    //   2600: dup
    //   2601: bipush #9
    //   2603: ldc 2097152
    //   2605: iastore
    //   2606: dup
    //   2607: bipush #10
    //   2609: iconst_0
    //   2610: iastore
    //   2611: dup
    //   2612: bipush #11
    //   2614: ldc 67108866
    //   2616: iastore
    //   2617: dup
    //   2618: bipush #12
    //   2620: iconst_2
    //   2621: iastore
    //   2622: dup
    //   2623: bipush #13
    //   2625: ldc 67108864
    //   2627: iastore
    //   2628: dup
    //   2629: bipush #14
    //   2631: ldc 69206018
    //   2633: iastore
    //   2634: dup
    //   2635: bipush #15
    //   2637: sipush #2050
    //   2640: iastore
    //   2641: dup
    //   2642: bipush #16
    //   2644: ldc 67110912
    //   2646: iastore
    //   2647: dup
    //   2648: bipush #17
    //   2650: ldc 2099202
    //   2652: iastore
    //   2653: dup
    //   2654: bipush #18
    //   2656: ldc 2097154
    //   2658: iastore
    //   2659: dup
    //   2660: bipush #19
    //   2662: ldc 67110912
    //   2664: iastore
    //   2665: dup
    //   2666: bipush #20
    //   2668: ldc 67108866
    //   2670: iastore
    //   2671: dup
    //   2672: bipush #21
    //   2674: ldc 69206016
    //   2676: iastore
    //   2677: dup
    //   2678: bipush #22
    //   2680: ldc 69208064
    //   2682: iastore
    //   2683: dup
    //   2684: bipush #23
    //   2686: ldc 2097154
    //   2688: iastore
    //   2689: dup
    //   2690: bipush #24
    //   2692: ldc 69206016
    //   2694: iastore
    //   2695: dup
    //   2696: bipush #25
    //   2698: sipush #2048
    //   2701: iastore
    //   2702: dup
    //   2703: bipush #26
    //   2705: sipush #2050
    //   2708: iastore
    //   2709: dup
    //   2710: bipush #27
    //   2712: ldc 69208066
    //   2714: iastore
    //   2715: dup
    //   2716: bipush #28
    //   2718: ldc 2099200
    //   2720: iastore
    //   2721: dup
    //   2722: bipush #29
    //   2724: iconst_2
    //   2725: iastore
    //   2726: dup
    //   2727: bipush #30
    //   2729: ldc 67108864
    //   2731: iastore
    //   2732: dup
    //   2733: bipush #31
    //   2735: ldc 2099200
    //   2737: iastore
    //   2738: dup
    //   2739: bipush #32
    //   2741: ldc 67108864
    //   2743: iastore
    //   2744: dup
    //   2745: bipush #33
    //   2747: ldc 2099200
    //   2749: iastore
    //   2750: dup
    //   2751: bipush #34
    //   2753: ldc 2097152
    //   2755: iastore
    //   2756: dup
    //   2757: bipush #35
    //   2759: ldc 67110914
    //   2761: iastore
    //   2762: dup
    //   2763: bipush #36
    //   2765: ldc 67110914
    //   2767: iastore
    //   2768: dup
    //   2769: bipush #37
    //   2771: ldc 69206018
    //   2773: iastore
    //   2774: dup
    //   2775: bipush #38
    //   2777: ldc 69206018
    //   2779: iastore
    //   2780: dup
    //   2781: bipush #39
    //   2783: iconst_2
    //   2784: iastore
    //   2785: dup
    //   2786: bipush #40
    //   2788: ldc 2097154
    //   2790: iastore
    //   2791: dup
    //   2792: bipush #41
    //   2794: ldc 67108864
    //   2796: iastore
    //   2797: dup
    //   2798: bipush #42
    //   2800: ldc 67110912
    //   2802: iastore
    //   2803: dup
    //   2804: bipush #43
    //   2806: ldc 2097152
    //   2808: iastore
    //   2809: dup
    //   2810: bipush #44
    //   2812: ldc 69208064
    //   2814: iastore
    //   2815: dup
    //   2816: bipush #45
    //   2818: sipush #2050
    //   2821: iastore
    //   2822: dup
    //   2823: bipush #46
    //   2825: ldc 2099202
    //   2827: iastore
    //   2828: dup
    //   2829: bipush #47
    //   2831: ldc 69208064
    //   2833: iastore
    //   2834: dup
    //   2835: bipush #48
    //   2837: sipush #2050
    //   2840: iastore
    //   2841: dup
    //   2842: bipush #49
    //   2844: ldc 67108866
    //   2846: iastore
    //   2847: dup
    //   2848: bipush #50
    //   2850: ldc 69208066
    //   2852: iastore
    //   2853: dup
    //   2854: bipush #51
    //   2856: ldc 69206016
    //   2858: iastore
    //   2859: dup
    //   2860: bipush #52
    //   2862: ldc 2099200
    //   2864: iastore
    //   2865: dup
    //   2866: bipush #53
    //   2868: iconst_0
    //   2869: iastore
    //   2870: dup
    //   2871: bipush #54
    //   2873: iconst_2
    //   2874: iastore
    //   2875: dup
    //   2876: bipush #55
    //   2878: ldc 69208066
    //   2880: iastore
    //   2881: dup
    //   2882: bipush #56
    //   2884: iconst_0
    //   2885: iastore
    //   2886: dup
    //   2887: bipush #57
    //   2889: ldc 2099202
    //   2891: iastore
    //   2892: dup
    //   2893: bipush #58
    //   2895: ldc 69206016
    //   2897: iastore
    //   2898: dup
    //   2899: bipush #59
    //   2901: sipush #2048
    //   2904: iastore
    //   2905: dup
    //   2906: bipush #60
    //   2908: ldc 67108866
    //   2910: iastore
    //   2911: dup
    //   2912: bipush #61
    //   2914: ldc 67110912
    //   2916: iastore
    //   2917: dup
    //   2918: bipush #62
    //   2920: sipush #2048
    //   2923: iastore
    //   2924: dup
    //   2925: bipush #63
    //   2927: ldc 2097154
    //   2929: iastore
    //   2930: astore #12
    //   2932: bipush #64
    //   2934: newarray int
    //   2936: dup
    //   2937: iconst_0
    //   2938: ldc 268439616
    //   2940: iastore
    //   2941: dup
    //   2942: iconst_1
    //   2943: sipush #4096
    //   2946: iastore
    //   2947: dup
    //   2948: iconst_2
    //   2949: ldc 262144
    //   2951: iastore
    //   2952: dup
    //   2953: iconst_3
    //   2954: ldc 268701760
    //   2956: iastore
    //   2957: dup
    //   2958: iconst_4
    //   2959: ldc 268435456
    //   2961: iastore
    //   2962: dup
    //   2963: iconst_5
    //   2964: ldc 268439616
    //   2966: iastore
    //   2967: dup
    //   2968: bipush #6
    //   2970: bipush #64
    //   2972: iastore
    //   2973: dup
    //   2974: bipush #7
    //   2976: ldc 268435456
    //   2978: iastore
    //   2979: dup
    //   2980: bipush #8
    //   2982: ldc 262208
    //   2984: iastore
    //   2985: dup
    //   2986: bipush #9
    //   2988: ldc 268697600
    //   2990: iastore
    //   2991: dup
    //   2992: bipush #10
    //   2994: ldc 268701760
    //   2996: iastore
    //   2997: dup
    //   2998: bipush #11
    //   3000: ldc 266240
    //   3002: iastore
    //   3003: dup
    //   3004: bipush #12
    //   3006: ldc 268701696
    //   3008: iastore
    //   3009: dup
    //   3010: bipush #13
    //   3012: ldc 266304
    //   3014: iastore
    //   3015: dup
    //   3016: bipush #14
    //   3018: sipush #4096
    //   3021: iastore
    //   3022: dup
    //   3023: bipush #15
    //   3025: bipush #64
    //   3027: iastore
    //   3028: dup
    //   3029: bipush #16
    //   3031: ldc 268697600
    //   3033: iastore
    //   3034: dup
    //   3035: bipush #17
    //   3037: ldc 268435520
    //   3039: iastore
    //   3040: dup
    //   3041: bipush #18
    //   3043: ldc 268439552
    //   3045: iastore
    //   3046: dup
    //   3047: bipush #19
    //   3049: sipush #4160
    //   3052: iastore
    //   3053: dup
    //   3054: bipush #20
    //   3056: ldc 266240
    //   3058: iastore
    //   3059: dup
    //   3060: bipush #21
    //   3062: ldc 262208
    //   3064: iastore
    //   3065: dup
    //   3066: bipush #22
    //   3068: ldc 268697664
    //   3070: iastore
    //   3071: dup
    //   3072: bipush #23
    //   3074: ldc 268701696
    //   3076: iastore
    //   3077: dup
    //   3078: bipush #24
    //   3080: sipush #4160
    //   3083: iastore
    //   3084: dup
    //   3085: bipush #25
    //   3087: iconst_0
    //   3088: iastore
    //   3089: dup
    //   3090: bipush #26
    //   3092: iconst_0
    //   3093: iastore
    //   3094: dup
    //   3095: bipush #27
    //   3097: ldc 268697664
    //   3099: iastore
    //   3100: dup
    //   3101: bipush #28
    //   3103: ldc 268435520
    //   3105: iastore
    //   3106: dup
    //   3107: bipush #29
    //   3109: ldc 268439552
    //   3111: iastore
    //   3112: dup
    //   3113: bipush #30
    //   3115: ldc 266304
    //   3117: iastore
    //   3118: dup
    //   3119: bipush #31
    //   3121: ldc 262144
    //   3123: iastore
    //   3124: dup
    //   3125: bipush #32
    //   3127: ldc 266304
    //   3129: iastore
    //   3130: dup
    //   3131: bipush #33
    //   3133: ldc 262144
    //   3135: iastore
    //   3136: dup
    //   3137: bipush #34
    //   3139: ldc 268701696
    //   3141: iastore
    //   3142: dup
    //   3143: bipush #35
    //   3145: sipush #4096
    //   3148: iastore
    //   3149: dup
    //   3150: bipush #36
    //   3152: bipush #64
    //   3154: iastore
    //   3155: dup
    //   3156: bipush #37
    //   3158: ldc 268697664
    //   3160: iastore
    //   3161: dup
    //   3162: bipush #38
    //   3164: sipush #4096
    //   3167: iastore
    //   3168: dup
    //   3169: bipush #39
    //   3171: ldc 266304
    //   3173: iastore
    //   3174: dup
    //   3175: bipush #40
    //   3177: ldc 268439552
    //   3179: iastore
    //   3180: dup
    //   3181: bipush #41
    //   3183: bipush #64
    //   3185: iastore
    //   3186: dup
    //   3187: bipush #42
    //   3189: ldc 268435520
    //   3191: iastore
    //   3192: dup
    //   3193: bipush #43
    //   3195: ldc 268697600
    //   3197: iastore
    //   3198: dup
    //   3199: bipush #44
    //   3201: ldc 268697664
    //   3203: iastore
    //   3204: dup
    //   3205: bipush #45
    //   3207: ldc 268435456
    //   3209: iastore
    //   3210: dup
    //   3211: bipush #46
    //   3213: ldc 262144
    //   3215: iastore
    //   3216: dup
    //   3217: bipush #47
    //   3219: ldc 268439616
    //   3221: iastore
    //   3222: dup
    //   3223: bipush #48
    //   3225: iconst_0
    //   3226: iastore
    //   3227: dup
    //   3228: bipush #49
    //   3230: ldc 268701760
    //   3232: iastore
    //   3233: dup
    //   3234: bipush #50
    //   3236: ldc 262208
    //   3238: iastore
    //   3239: dup
    //   3240: bipush #51
    //   3242: ldc 268435520
    //   3244: iastore
    //   3245: dup
    //   3246: bipush #52
    //   3248: ldc 268697600
    //   3250: iastore
    //   3251: dup
    //   3252: bipush #53
    //   3254: ldc 268439552
    //   3256: iastore
    //   3257: dup
    //   3258: bipush #54
    //   3260: ldc 268439616
    //   3262: iastore
    //   3263: dup
    //   3264: bipush #55
    //   3266: iconst_0
    //   3267: iastore
    //   3268: dup
    //   3269: bipush #56
    //   3271: ldc 268701760
    //   3273: iastore
    //   3274: dup
    //   3275: bipush #57
    //   3277: ldc 266240
    //   3279: iastore
    //   3280: dup
    //   3281: bipush #58
    //   3283: ldc 266240
    //   3285: iastore
    //   3286: dup
    //   3287: bipush #59
    //   3289: sipush #4160
    //   3292: iastore
    //   3293: dup
    //   3294: bipush #60
    //   3296: sipush #4160
    //   3299: iastore
    //   3300: dup
    //   3301: bipush #61
    //   3303: ldc 262208
    //   3305: iastore
    //   3306: dup
    //   3307: bipush #62
    //   3309: ldc 268435456
    //   3311: iastore
    //   3312: dup
    //   3313: bipush #63
    //   3315: ldc 268701696
    //   3317: iastore
    //   3318: astore #13
    //   3320: aload_3
    //   3321: arraylength
    //   3322: istore #14
    //   3324: iload #14
    //   3326: bipush #8
    //   3328: irem
    //   3329: ifeq -> 3353
    //   3332: new java/lang/Exception
    //   3335: dup
    //   3336: sipush #12090
    //   3339: sipush #1545
    //   3342: invokestatic a : (II)Ljava/lang/String;
    //   3345: invokespecial <init> : (Ljava/lang/String;)V
    //   3348: athrow
    //   3349: invokestatic a : (Ljava/lang/Throwable;)Ljava/lang/Throwable;
    //   3352: athrow
    //   3353: iconst_2
    //   3354: newarray int
    //   3356: astore #15
    //   3358: iload #14
    //   3360: newarray byte
    //   3362: astore #16
    //   3364: iload #14
    //   3366: bipush #8
    //   3368: idiv
    //   3369: istore #17
    //   3371: iconst_0
    //   3372: istore #18
    //   3374: iload #18
    //   3376: iload #17
    //   3378: if_icmpge -> 4292
    //   3381: iload #18
    //   3383: bipush #8
    //   3385: imul
    //   3386: istore #19
    //   3388: iconst_0
    //   3389: istore #20
    //   3391: iload #20
    //   3393: iconst_2
    //   3394: if_icmpge -> 3479
    //   3397: aload #15
    //   3399: iload #20
    //   3401: aload_3
    //   3402: iload #19
    //   3404: iload #20
    //   3406: iconst_4
    //   3407: imul
    //   3408: iadd
    //   3409: baload
    //   3410: sipush #255
    //   3413: iand
    //   3414: bipush #24
    //   3416: ishl
    //   3417: aload_3
    //   3418: iload #19
    //   3420: iload #20
    //   3422: iconst_4
    //   3423: imul
    //   3424: iadd
    //   3425: iconst_1
    //   3426: iadd
    //   3427: baload
    //   3428: sipush #255
    //   3431: iand
    //   3432: bipush #16
    //   3434: ishl
    //   3435: ior
    //   3436: aload_3
    //   3437: iload #19
    //   3439: iload #20
    //   3441: iconst_4
    //   3442: imul
    //   3443: iadd
    //   3444: iconst_2
    //   3445: iadd
    //   3446: baload
    //   3447: sipush #255
    //   3450: iand
    //   3451: bipush #8
    //   3453: ishl
    //   3454: ior
    //   3455: aload_3
    //   3456: iload #19
    //   3458: iload #20
    //   3460: iconst_4
    //   3461: imul
    //   3462: iadd
    //   3463: iconst_3
    //   3464: iadd
    //   3465: baload
    //   3466: sipush #255
    //   3469: iand
    //   3470: ior
    //   3471: iastore
    //   3472: iinc #20, 1
    //   3475: iload_2
    //   3476: ifne -> 3391
    //   3479: iconst_0
    //   3480: istore #25
    //   3482: aload #15
    //   3484: iconst_0
    //   3485: iaload
    //   3486: istore #23
    //   3488: aload #15
    //   3490: iconst_1
    //   3491: iaload
    //   3492: istore #22
    //   3494: iload #23
    //   3496: iconst_4
    //   3497: iushr
    //   3498: iload #22
    //   3500: ixor
    //   3501: ldc 252645135
    //   3503: iand
    //   3504: istore #21
    //   3506: iload #22
    //   3508: iload #21
    //   3510: ixor
    //   3511: istore #22
    //   3513: iload #23
    //   3515: iload #21
    //   3517: iconst_4
    //   3518: ishl
    //   3519: ixor
    //   3520: istore #23
    //   3522: iload #23
    //   3524: bipush #16
    //   3526: iushr
    //   3527: iload #22
    //   3529: ixor
    //   3530: ldc 65535
    //   3532: iand
    //   3533: istore #21
    //   3535: iload #22
    //   3537: iload #21
    //   3539: ixor
    //   3540: istore #22
    //   3542: iload #23
    //   3544: iload #21
    //   3546: bipush #16
    //   3548: ishl
    //   3549: ixor
    //   3550: istore #23
    //   3552: iload #22
    //   3554: iconst_2
    //   3555: iushr
    //   3556: iload #23
    //   3558: ixor
    //   3559: ldc 858993459
    //   3561: iand
    //   3562: istore #21
    //   3564: iload #23
    //   3566: iload #21
    //   3568: ixor
    //   3569: istore #23
    //   3571: iload #22
    //   3573: iload #21
    //   3575: iconst_2
    //   3576: ishl
    //   3577: ixor
    //   3578: istore #22
    //   3580: iload #22
    //   3582: bipush #8
    //   3584: iushr
    //   3585: iload #23
    //   3587: ixor
    //   3588: ldc 16711935
    //   3590: iand
    //   3591: istore #21
    //   3593: iload #23
    //   3595: iload #21
    //   3597: ixor
    //   3598: istore #23
    //   3600: iload #22
    //   3602: iload #21
    //   3604: bipush #8
    //   3606: ishl
    //   3607: ixor
    //   3608: istore #22
    //   3610: iload #22
    //   3612: iconst_1
    //   3613: ishl
    //   3614: iload #22
    //   3616: bipush #31
    //   3618: iushr
    //   3619: iconst_1
    //   3620: iand
    //   3621: ior
    //   3622: istore #22
    //   3624: iload #23
    //   3626: iload #22
    //   3628: ixor
    //   3629: ldc -1431655766
    //   3631: iand
    //   3632: istore #21
    //   3634: iload #23
    //   3636: iload #21
    //   3638: ixor
    //   3639: istore #23
    //   3641: iload #22
    //   3643: iload #21
    //   3645: ixor
    //   3646: istore #22
    //   3648: iload #23
    //   3650: iconst_1
    //   3651: ishl
    //   3652: iload #23
    //   3654: bipush #31
    //   3656: iushr
    //   3657: iconst_1
    //   3658: iand
    //   3659: ior
    //   3660: istore #23
    //   3662: iconst_0
    //   3663: istore #24
    //   3665: iload #24
    //   3667: bipush #8
    //   3669: if_icmpge -> 4007
    //   3672: iload #22
    //   3674: bipush #28
    //   3676: ishl
    //   3677: iload #22
    //   3679: iconst_4
    //   3680: iushr
    //   3681: ior
    //   3682: istore #21
    //   3684: iload #21
    //   3686: aload #5
    //   3688: iload #25
    //   3690: iinc #25, 1
    //   3693: iaload
    //   3694: ixor
    //   3695: istore #21
    //   3697: aload #12
    //   3699: iload #21
    //   3701: bipush #63
    //   3703: iand
    //   3704: iaload
    //   3705: istore #20
    //   3707: iload #20
    //   3709: aload #10
    //   3711: iload #21
    //   3713: bipush #8
    //   3715: iushr
    //   3716: bipush #63
    //   3718: iand
    //   3719: iaload
    //   3720: ior
    //   3721: istore #20
    //   3723: iload #20
    //   3725: aload #8
    //   3727: iload #21
    //   3729: bipush #16
    //   3731: iushr
    //   3732: bipush #63
    //   3734: iand
    //   3735: iaload
    //   3736: ior
    //   3737: istore #20
    //   3739: iload #20
    //   3741: aload #6
    //   3743: iload #21
    //   3745: bipush #24
    //   3747: iushr
    //   3748: bipush #63
    //   3750: iand
    //   3751: iaload
    //   3752: ior
    //   3753: istore #20
    //   3755: iload #22
    //   3757: aload #5
    //   3759: iload #25
    //   3761: iinc #25, 1
    //   3764: iaload
    //   3765: ixor
    //   3766: istore #21
    //   3768: iload #20
    //   3770: aload #13
    //   3772: iload #21
    //   3774: bipush #63
    //   3776: iand
    //   3777: iaload
    //   3778: ior
    //   3779: istore #20
    //   3781: iload #20
    //   3783: aload #11
    //   3785: iload #21
    //   3787: bipush #8
    //   3789: iushr
    //   3790: bipush #63
    //   3792: iand
    //   3793: iaload
    //   3794: ior
    //   3795: istore #20
    //   3797: iload #20
    //   3799: aload #9
    //   3801: iload #21
    //   3803: bipush #16
    //   3805: iushr
    //   3806: bipush #63
    //   3808: iand
    //   3809: iaload
    //   3810: ior
    //   3811: istore #20
    //   3813: iload #20
    //   3815: aload #7
    //   3817: iload #21
    //   3819: bipush #24
    //   3821: iushr
    //   3822: bipush #63
    //   3824: iand
    //   3825: iaload
    //   3826: ior
    //   3827: istore #20
    //   3829: iload #23
    //   3831: iload #20
    //   3833: ixor
    //   3834: istore #23
    //   3836: iload #23
    //   3838: bipush #28
    //   3840: ishl
    //   3841: iload #23
    //   3843: iconst_4
    //   3844: iushr
    //   3845: ior
    //   3846: istore #21
    //   3848: iload #21
    //   3850: aload #5
    //   3852: iload #25
    //   3854: iinc #25, 1
    //   3857: iaload
    //   3858: ixor
    //   3859: istore #21
    //   3861: aload #12
    //   3863: iload #21
    //   3865: bipush #63
    //   3867: iand
    //   3868: iaload
    //   3869: istore #20
    //   3871: iload #20
    //   3873: aload #10
    //   3875: iload #21
    //   3877: bipush #8
    //   3879: iushr
    //   3880: bipush #63
    //   3882: iand
    //   3883: iaload
    //   3884: ior
    //   3885: istore #20
    //   3887: iload #20
    //   3889: aload #8
    //   3891: iload #21
    //   3893: bipush #16
    //   3895: iushr
    //   3896: bipush #63
    //   3898: iand
    //   3899: iaload
    //   3900: ior
    //   3901: istore #20
    //   3903: iload #20
    //   3905: aload #6
    //   3907: iload #21
    //   3909: bipush #24
    //   3911: iushr
    //   3912: bipush #63
    //   3914: iand
    //   3915: iaload
    //   3916: ior
    //   3917: istore #20
    //   3919: iload #23
    //   3921: aload #5
    //   3923: iload #25
    //   3925: iinc #25, 1
    //   3928: iaload
    //   3929: ixor
    //   3930: istore #21
    //   3932: iload #20
    //   3934: aload #13
    //   3936: iload #21
    //   3938: bipush #63
    //   3940: iand
    //   3941: iaload
    //   3942: ior
    //   3943: istore #20
    //   3945: iload #20
    //   3947: aload #11
    //   3949: iload #21
    //   3951: bipush #8
    //   3953: iushr
    //   3954: bipush #63
    //   3956: iand
    //   3957: iaload
    //   3958: ior
    //   3959: istore #20
    //   3961: iload #20
    //   3963: aload #9
    //   3965: iload #21
    //   3967: bipush #16
    //   3969: iushr
    //   3970: bipush #63
    //   3972: iand
    //   3973: iaload
    //   3974: ior
    //   3975: istore #20
    //   3977: iload #20
    //   3979: aload #7
    //   3981: iload #21
    //   3983: bipush #24
    //   3985: iushr
    //   3986: bipush #63
    //   3988: iand
    //   3989: iaload
    //   3990: ior
    //   3991: istore #20
    //   3993: iload #22
    //   3995: iload #20
    //   3997: ixor
    //   3998: istore #22
    //   4000: iinc #24, 1
    //   4003: iload_2
    //   4004: ifne -> 3665
    //   4007: iload #22
    //   4009: bipush #31
    //   4011: ishl
    //   4012: iload #22
    //   4014: iconst_1
    //   4015: iushr
    //   4016: ior
    //   4017: istore #22
    //   4019: iload #23
    //   4021: iload #22
    //   4023: ixor
    //   4024: ldc -1431655766
    //   4026: iand
    //   4027: istore #21
    //   4029: iload #23
    //   4031: iload #21
    //   4033: ixor
    //   4034: istore #23
    //   4036: iload #22
    //   4038: iload #21
    //   4040: ixor
    //   4041: istore #22
    //   4043: iload #23
    //   4045: bipush #31
    //   4047: ishl
    //   4048: iload #23
    //   4050: iconst_1
    //   4051: iushr
    //   4052: ior
    //   4053: istore #23
    //   4055: iload #23
    //   4057: bipush #8
    //   4059: iushr
    //   4060: iload #22
    //   4062: ixor
    //   4063: ldc 16711935
    //   4065: iand
    //   4066: istore #21
    //   4068: iload #22
    //   4070: iload #21
    //   4072: ixor
    //   4073: istore #22
    //   4075: iload #23
    //   4077: iload #21
    //   4079: bipush #8
    //   4081: ishl
    //   4082: ixor
    //   4083: istore #23
    //   4085: iload #23
    //   4087: iconst_2
    //   4088: iushr
    //   4089: iload #22
    //   4091: ixor
    //   4092: ldc 858993459
    //   4094: iand
    //   4095: istore #21
    //   4097: iload #22
    //   4099: iload #21
    //   4101: ixor
    //   4102: istore #22
    //   4104: iload #23
    //   4106: iload #21
    //   4108: iconst_2
    //   4109: ishl
    //   4110: ixor
    //   4111: istore #23
    //   4113: iload #22
    //   4115: bipush #16
    //   4117: iushr
    //   4118: iload #23
    //   4120: ixor
    //   4121: ldc 65535
    //   4123: iand
    //   4124: istore #21
    //   4126: iload #23
    //   4128: iload #21
    //   4130: ixor
    //   4131: istore #23
    //   4133: iload #22
    //   4135: iload #21
    //   4137: bipush #16
    //   4139: ishl
    //   4140: ixor
    //   4141: istore #22
    //   4143: iload #22
    //   4145: iconst_4
    //   4146: iushr
    //   4147: iload #23
    //   4149: ixor
    //   4150: ldc 252645135
    //   4152: iand
    //   4153: istore #21
    //   4155: iload #23
    //   4157: iload #21
    //   4159: ixor
    //   4160: istore #23
    //   4162: iload #22
    //   4164: iload #21
    //   4166: iconst_4
    //   4167: ishl
    //   4168: ixor
    //   4169: istore #22
    //   4171: aload #15
    //   4173: iconst_0
    //   4174: iload #22
    //   4176: iastore
    //   4177: aload #15
    //   4179: iconst_1
    //   4180: iload #23
    //   4182: iastore
    //   4183: iload #18
    //   4185: bipush #8
    //   4187: imul
    //   4188: istore #26
    //   4190: iconst_0
    //   4191: istore #27
    //   4193: iload #27
    //   4195: iconst_2
    //   4196: if_icmpge -> 4285
    //   4199: aload #16
    //   4201: iload #26
    //   4203: iload #27
    //   4205: iconst_4
    //   4206: imul
    //   4207: iadd
    //   4208: aload #15
    //   4210: iload #27
    //   4212: iaload
    //   4213: bipush #24
    //   4215: iushr
    //   4216: i2b
    //   4217: bastore
    //   4218: aload #16
    //   4220: iload #26
    //   4222: iload #27
    //   4224: iconst_4
    //   4225: imul
    //   4226: iadd
    //   4227: iconst_1
    //   4228: iadd
    //   4229: aload #15
    //   4231: iload #27
    //   4233: iaload
    //   4234: bipush #16
    //   4236: iushr
    //   4237: i2b
    //   4238: bastore
    //   4239: aload #16
    //   4241: iload #26
    //   4243: iload #27
    //   4245: iconst_4
    //   4246: imul
    //   4247: iadd
    //   4248: iconst_2
    //   4249: iadd
    //   4250: aload #15
    //   4252: iload #27
    //   4254: iaload
    //   4255: bipush #8
    //   4257: iushr
    //   4258: i2b
    //   4259: bastore
    //   4260: aload #16
    //   4262: iload #26
    //   4264: iload #27
    //   4266: iconst_4
    //   4267: imul
    //   4268: iadd
    //   4269: iconst_3
    //   4270: iadd
    //   4271: aload #15
    //   4273: iload #27
    //   4275: iaload
    //   4276: i2b
    //   4277: bastore
    //   4278: iinc #27, 1
    //   4281: iload_2
    //   4282: ifne -> 4193
    //   4285: iinc #18, 1
    //   4288: iload_2
    //   4289: ifne -> 3374
    //   4292: aload #16
    //   4294: aload #16
    //   4296: arraylength
    //   4297: iconst_1
    //   4298: isub
    //   4299: baload
    //   4300: istore #18
    //   4302: aload #16
    //   4304: arraylength
    //   4305: iload #18
    //   4307: isub
    //   4308: newarray byte
    //   4310: astore #4
    //   4312: aload #16
    //   4314: arraylength
    //   4315: aload #4
    //   4317: arraylength
    //   4318: if_icmpge -> 4342
    //   4321: new java/lang/Exception
    //   4324: dup
    //   4325: sipush #12087
    //   4328: sipush #6962
    //   4331: invokestatic a : (II)Ljava/lang/String;
    //   4334: invokespecial <init> : (Ljava/lang/String;)V
    //   4337: athrow
    //   4338: invokestatic a : (Ljava/lang/Throwable;)Ljava/lang/Throwable;
    //   4341: athrow
    //   4342: iconst_0
    //   4343: istore #19
    //   4345: iload #19
    //   4347: aload #4
    //   4349: arraylength
    //   4350: if_icmpge -> 4370
    //   4353: aload #4
    //   4355: iload #19
    //   4357: aload #16
    //   4359: iload #19
    //   4361: baload
    //   4362: bastore
    //   4363: iinc #19, 1
    //   4366: iload_2
    //   4367: ifne -> 4345
    //   4370: new java/math/BigInteger
    //   4373: dup
    //   4374: aload #4
    //   4376: invokespecial <init> : ([B)V
    //   4379: invokevirtual abs : ()Ljava/math/BigInteger;
    //   4382: putstatic burp/Zs3m.ZW : Ljava/lang/Object;
    //   4385: getstatic burp/Zge2.Zv : Ljava/lang/Object;
    //   4388: checkcast java/math/BigInteger
    //   4391: invokevirtual toByteArray : ()[B
    //   4394: astore_3
    //   4395: bipush #32
    //   4397: newarray int
    //   4399: dup
    //   4400: iconst_0
    //   4401: ldc 943331329
    //   4403: iastore
    //   4404: dup
    //   4405: iconst_1
    //   4406: ldc 170788368
    //   4408: iastore
    //   4409: dup
    //   4410: iconst_2
    //   4411: ldc 1008414755
    //   4413: iastore
    //   4414: dup
    //   4415: iconst_3
    //   4416: ldc 187049985
    //   4418: iastore
    //   4419: dup
    //   4420: iconst_4
    //   4421: ldc 1010368540
    //   4423: iastore
    //   4424: dup
    //   4425: iconst_5
    //   4426: ldc 220604441
    //   4428: iastore
    //   4429: dup
    //   4430: bipush #6
    //   4432: ldc 940377620
    //   4434: iastore
    //   4435: dup
    //   4436: bipush #7
    //   4438: ldc 255209728
    //   4440: iastore
    //   4441: dup
    //   4442: bipush #8
    //   4444: ldc 689771012
    //   4446: iastore
    //   4447: dup
    //   4448: bipush #9
    //   4450: ldc 221709344
    //   4452: iastore
    //   4453: dup
    //   4454: bipush #10
    //   4456: ldc 957157408
    //   4458: iastore
    //   4459: dup
    //   4460: bipush #11
    //   4462: ldc 892536332
    //   4464: iastore
    //   4465: dup
    //   4466: bipush #12
    //   4468: ldc 722417666
    //   4470: iastore
    //   4471: dup
    //   4472: bipush #13
    //   4474: ldc 1026621720
    //   4476: iastore
    //   4477: dup
    //   4478: bipush #14
    //   4480: ldc 655302664
    //   4482: iastore
    //   4483: dup
    //   4484: bipush #15
    //   4486: ldc 890966315
    //   4488: iastore
    //   4489: dup
    //   4490: bipush #16
    //   4492: ldc 187632156
    //   4494: iastore
    //   4495: dup
    //   4496: bipush #17
    //   4498: ldc 874189824
    //   4500: iastore
    //   4501: dup
    //   4502: bipush #18
    //   4504: ldc 254150144
    //   4506: iastore
    //   4507: dup
    //   4508: bipush #19
    //   4510: ldc 924386310
    //   4512: iastore
    //   4513: dup
    //   4514: bipush #20
    //   4516: ldc 121057538
    //   4518: iastore
    //   4519: dup
    //   4520: bipush #21
    //   4522: ldc 840500228
    //   4524: iastore
    //   4525: dup
    //   4526: bipush #22
    //   4528: ldc 389160971
    //   4530: iastore
    //   4531: dup
    //   4532: bipush #23
    //   4534: ldc 907870729
    //   4536: iastore
    //   4537: dup
    //   4538: bipush #24
    //   4540: ldc 389426184
    //   4542: iastore
    //   4543: dup
    //   4544: bipush #25
    //   4546: ldc 973875457
    //   4548: iastore
    //   4549: dup
    //   4550: bipush #26
    //   4552: ldc 372376604
    //   4554: iastore
    //   4555: dup
    //   4556: bipush #27
    //   4558: ldc 707731490
    //   4560: iastore
    //   4561: dup
    //   4562: bipush #28
    //   4564: ldc 1043334948
    //   4566: iastore
    //   4567: dup
    //   4568: bipush #29
    //   4570: ldc 439222784
    //   4572: iastore
    //   4573: dup
    //   4574: bipush #30
    //   4576: ldc 876216579
    //   4578: iastore
    //   4579: dup
    //   4580: bipush #31
    //   4582: ldc 455999525
    //   4584: iastore
    //   4585: astore #5
    //   4587: bipush #8
    //   4589: aload_3
    //   4590: arraylength
    //   4591: bipush #8
    //   4593: irem
    //   4594: isub
    //   4595: istore #6
    //   4597: aload_3
    //   4598: arraylength
    //   4599: iload #6
    //   4601: iadd
    //   4602: newarray byte
    //   4604: astore #7
    //   4606: iconst_0
    //   4607: istore #8
    //   4609: iload #8
    //   4611: aload_3
    //   4612: arraylength
    //   4613: if_icmpge -> 4632
    //   4616: aload #7
    //   4618: iload #8
    //   4620: aload_3
    //   4621: iload #8
    //   4623: baload
    //   4624: bastore
    //   4625: iinc #8, 1
    //   4628: iload_2
    //   4629: ifne -> 4609
    //   4632: aload_3
    //   4633: arraylength
    //   4634: istore #8
    //   4636: iload #8
    //   4638: aload #7
    //   4640: arraylength
    //   4641: if_icmpge -> 4659
    //   4644: aload #7
    //   4646: iload #8
    //   4648: iload #6
    //   4650: i2b
    //   4651: bastore
    //   4652: iinc #8, 1
    //   4655: iload_2
    //   4656: ifne -> 4636
    //   4659: aload #7
    //   4661: astore_3
    //   4662: bipush #64
    //   4664: newarray int
    //   4666: dup
    //   4667: iconst_0
    //   4668: ldc 16843776
    //   4670: iastore
    //   4671: dup
    //   4672: iconst_1
    //   4673: iconst_0
    //   4674: iastore
    //   4675: dup
    //   4676: iconst_2
    //   4677: ldc 65536
    //   4679: iastore
    //   4680: dup
    //   4681: iconst_3
    //   4682: ldc 16843780
    //   4684: iastore
    //   4685: dup
    //   4686: iconst_4
    //   4687: ldc 16842756
    //   4689: iastore
    //   4690: dup
    //   4691: iconst_5
    //   4692: ldc 66564
    //   4694: iastore
    //   4695: dup
    //   4696: bipush #6
    //   4698: iconst_4
    //   4699: iastore
    //   4700: dup
    //   4701: bipush #7
    //   4703: ldc 65536
    //   4705: iastore
    //   4706: dup
    //   4707: bipush #8
    //   4709: sipush #1024
    //   4712: iastore
    //   4713: dup
    //   4714: bipush #9
    //   4716: ldc 16843776
    //   4718: iastore
    //   4719: dup
    //   4720: bipush #10
    //   4722: ldc 16843780
    //   4724: iastore
    //   4725: dup
    //   4726: bipush #11
    //   4728: sipush #1024
    //   4731: iastore
    //   4732: dup
    //   4733: bipush #12
    //   4735: ldc 16778244
    //   4737: iastore
    //   4738: dup
    //   4739: bipush #13
    //   4741: ldc 16842756
    //   4743: iastore
    //   4744: dup
    //   4745: bipush #14
    //   4747: ldc 16777216
    //   4749: iastore
    //   4750: dup
    //   4751: bipush #15
    //   4753: iconst_4
    //   4754: iastore
    //   4755: dup
    //   4756: bipush #16
    //   4758: sipush #1028
    //   4761: iastore
    //   4762: dup
    //   4763: bipush #17
    //   4765: ldc 16778240
    //   4767: iastore
    //   4768: dup
    //   4769: bipush #18
    //   4771: ldc 16778240
    //   4773: iastore
    //   4774: dup
    //   4775: bipush #19
    //   4777: ldc 66560
    //   4779: iastore
    //   4780: dup
    //   4781: bipush #20
    //   4783: ldc 66560
    //   4785: iastore
    //   4786: dup
    //   4787: bipush #21
    //   4789: ldc 16842752
    //   4791: iastore
    //   4792: dup
    //   4793: bipush #22
    //   4795: ldc 16842752
    //   4797: iastore
    //   4798: dup
    //   4799: bipush #23
    //   4801: ldc 16778244
    //   4803: iastore
    //   4804: dup
    //   4805: bipush #24
    //   4807: ldc 65540
    //   4809: iastore
    //   4810: dup
    //   4811: bipush #25
    //   4813: ldc 16777220
    //   4815: iastore
    //   4816: dup
    //   4817: bipush #26
    //   4819: ldc 16777220
    //   4821: iastore
    //   4822: dup
    //   4823: bipush #27
    //   4825: ldc 65540
    //   4827: iastore
    //   4828: dup
    //   4829: bipush #28
    //   4831: iconst_0
    //   4832: iastore
    //   4833: dup
    //   4834: bipush #29
    //   4836: sipush #1028
    //   4839: iastore
    //   4840: dup
    //   4841: bipush #30
    //   4843: ldc 66564
    //   4845: iastore
    //   4846: dup
    //   4847: bipush #31
    //   4849: ldc 16777216
    //   4851: iastore
    //   4852: dup
    //   4853: bipush #32
    //   4855: ldc 65536
    //   4857: iastore
    //   4858: dup
    //   4859: bipush #33
    //   4861: ldc 16843780
    //   4863: iastore
    //   4864: dup
    //   4865: bipush #34
    //   4867: iconst_4
    //   4868: iastore
    //   4869: dup
    //   4870: bipush #35
    //   4872: ldc 16842752
    //   4874: iastore
    //   4875: dup
    //   4876: bipush #36
    //   4878: ldc 16843776
    //   4880: iastore
    //   4881: dup
    //   4882: bipush #37
    //   4884: ldc 16777216
    //   4886: iastore
    //   4887: dup
    //   4888: bipush #38
    //   4890: ldc 16777216
    //   4892: iastore
    //   4893: dup
    //   4894: bipush #39
    //   4896: sipush #1024
    //   4899: iastore
    //   4900: dup
    //   4901: bipush #40
    //   4903: ldc 16842756
    //   4905: iastore
    //   4906: dup
    //   4907: bipush #41
    //   4909: ldc 65536
    //   4911: iastore
    //   4912: dup
    //   4913: bipush #42
    //   4915: ldc 66560
    //   4917: iastore
    //   4918: dup
    //   4919: bipush #43
    //   4921: ldc 16777220
    //   4923: iastore
    //   4924: dup
    //   4925: bipush #44
    //   4927: sipush #1024
    //   4930: iastore
    //   4931: dup
    //   4932: bipush #45
    //   4934: iconst_4
    //   4935: iastore
    //   4936: dup
    //   4937: bipush #46
    //   4939: ldc 16778244
    //   4941: iastore
    //   4942: dup
    //   4943: bipush #47
    //   4945: ldc 66564
    //   4947: iastore
    //   4948: dup
    //   4949: bipush #48
    //   4951: ldc 16843780
    //   4953: iastore
    //   4954: dup
    //   4955: bipush #49
    //   4957: ldc 65540
    //   4959: iastore
    //   4960: dup
    //   4961: bipush #50
    //   4963: ldc 16842752
    //   4965: iastore
    //   4966: dup
    //   4967: bipush #51
    //   4969: ldc 16778244
    //   4971: iastore
    //   4972: dup
    //   4973: bipush #52
    //   4975: ldc 16777220
    //   4977: iastore
    //   4978: dup
    //   4979: bipush #53
    //   4981: sipush #1028
    //   4984: iastore
    //   4985: dup
    //   4986: bipush #54
    //   4988: ldc 66564
    //   4990: iastore
    //   4991: dup
    //   4992: bipush #55
    //   4994: ldc 16843776
    //   4996: iastore
    //   4997: dup
    //   4998: bipush #56
    //   5000: sipush #1028
    //   5003: iastore
    //   5004: dup
    //   5005: bipush #57
    //   5007: ldc 16778240
    //   5009: iastore
    //   5010: dup
    //   5011: bipush #58
    //   5013: ldc 16778240
    //   5015: iastore
    //   5016: dup
    //   5017: bipush #59
    //   5019: iconst_0
    //   5020: iastore
    //   5021: dup
    //   5022: bipush #60
    //   5024: ldc 65540
    //   5026: iastore
    //   5027: dup
    //   5028: bipush #61
    //   5030: ldc 66560
    //   5032: iastore
    //   5033: dup
    //   5034: bipush #62
    //   5036: iconst_0
    //   5037: iastore
    //   5038: dup
    //   5039: bipush #63
    //   5041: ldc 16842756
    //   5043: iastore
    //   5044: astore #8
    //   5046: bipush #64
    //   5048: newarray int
    //   5050: dup
    //   5051: iconst_0
    //   5052: ldc -2146402272
    //   5054: iastore
    //   5055: dup
    //   5056: iconst_1
    //   5057: ldc -2147450880
    //   5059: iastore
    //   5060: dup
    //   5061: iconst_2
    //   5062: ldc 32768
    //   5064: iastore
    //   5065: dup
    //   5066: iconst_3
    //   5067: ldc 1081376
    //   5069: iastore
    //   5070: dup
    //   5071: iconst_4
    //   5072: ldc 1048576
    //   5074: iastore
    //   5075: dup
    //   5076: iconst_5
    //   5077: bipush #32
    //   5079: iastore
    //   5080: dup
    //   5081: bipush #6
    //   5083: ldc -2146435040
    //   5085: iastore
    //   5086: dup
    //   5087: bipush #7
    //   5089: ldc -2147450848
    //   5091: iastore
    //   5092: dup
    //   5093: bipush #8
    //   5095: ldc -2147483616
    //   5097: iastore
    //   5098: dup
    //   5099: bipush #9
    //   5101: ldc -2146402272
    //   5103: iastore
    //   5104: dup
    //   5105: bipush #10
    //   5107: ldc -2146402304
    //   5109: iastore
    //   5110: dup
    //   5111: bipush #11
    //   5113: ldc -2147483648
    //   5115: iastore
    //   5116: dup
    //   5117: bipush #12
    //   5119: ldc -2147450880
    //   5121: iastore
    //   5122: dup
    //   5123: bipush #13
    //   5125: ldc 1048576
    //   5127: iastore
    //   5128: dup
    //   5129: bipush #14
    //   5131: bipush #32
    //   5133: iastore
    //   5134: dup
    //   5135: bipush #15
    //   5137: ldc -2146435040
    //   5139: iastore
    //   5140: dup
    //   5141: bipush #16
    //   5143: ldc 1081344
    //   5145: iastore
    //   5146: dup
    //   5147: bipush #17
    //   5149: ldc 1048608
    //   5151: iastore
    //   5152: dup
    //   5153: bipush #18
    //   5155: ldc -2147450848
    //   5157: iastore
    //   5158: dup
    //   5159: bipush #19
    //   5161: iconst_0
    //   5162: iastore
    //   5163: dup
    //   5164: bipush #20
    //   5166: ldc -2147483648
    //   5168: iastore
    //   5169: dup
    //   5170: bipush #21
    //   5172: ldc 32768
    //   5174: iastore
    //   5175: dup
    //   5176: bipush #22
    //   5178: ldc 1081376
    //   5180: iastore
    //   5181: dup
    //   5182: bipush #23
    //   5184: ldc -2146435072
    //   5186: iastore
    //   5187: dup
    //   5188: bipush #24
    //   5190: ldc 1048608
    //   5192: iastore
    //   5193: dup
    //   5194: bipush #25
    //   5196: ldc -2147483616
    //   5198: iastore
    //   5199: dup
    //   5200: bipush #26
    //   5202: iconst_0
    //   5203: iastore
    //   5204: dup
    //   5205: bipush #27
    //   5207: ldc 1081344
    //   5209: iastore
    //   5210: dup
    //   5211: bipush #28
    //   5213: ldc 32800
    //   5215: iastore
    //   5216: dup
    //   5217: bipush #29
    //   5219: ldc -2146402304
    //   5221: iastore
    //   5222: dup
    //   5223: bipush #30
    //   5225: ldc -2146435072
    //   5227: iastore
    //   5228: dup
    //   5229: bipush #31
    //   5231: ldc 32800
    //   5233: iastore
    //   5234: dup
    //   5235: bipush #32
    //   5237: iconst_0
    //   5238: iastore
    //   5239: dup
    //   5240: bipush #33
    //   5242: ldc 1081376
    //   5244: iastore
    //   5245: dup
    //   5246: bipush #34
    //   5248: ldc -2146435040
    //   5250: iastore
    //   5251: dup
    //   5252: bipush #35
    //   5254: ldc 1048576
    //   5256: iastore
    //   5257: dup
    //   5258: bipush #36
    //   5260: ldc -2147450848
    //   5262: iastore
    //   5263: dup
    //   5264: bipush #37
    //   5266: ldc -2146435072
    //   5268: iastore
    //   5269: dup
    //   5270: bipush #38
    //   5272: ldc -2146402304
    //   5274: iastore
    //   5275: dup
    //   5276: bipush #39
    //   5278: ldc 32768
    //   5280: iastore
    //   5281: dup
    //   5282: bipush #40
    //   5284: ldc -2146435072
    //   5286: iastore
    //   5287: dup
    //   5288: bipush #41
    //   5290: ldc -2147450880
    //   5292: iastore
    //   5293: dup
    //   5294: bipush #42
    //   5296: bipush #32
    //   5298: iastore
    //   5299: dup
    //   5300: bipush #43
    //   5302: ldc -2146402272
    //   5304: iastore
    //   5305: dup
    //   5306: bipush #44
    //   5308: ldc 1081376
    //   5310: iastore
    //   5311: dup
    //   5312: bipush #45
    //   5314: bipush #32
    //   5316: iastore
    //   5317: dup
    //   5318: bipush #46
    //   5320: ldc 32768
    //   5322: iastore
    //   5323: dup
    //   5324: bipush #47
    //   5326: ldc -2147483648
    //   5328: iastore
    //   5329: dup
    //   5330: bipush #48
    //   5332: ldc 32800
    //   5334: iastore
    //   5335: dup
    //   5336: bipush #49
    //   5338: ldc -2146402304
    //   5340: iastore
    //   5341: dup
    //   5342: bipush #50
    //   5344: ldc 1048576
    //   5346: iastore
    //   5347: dup
    //   5348: bipush #51
    //   5350: ldc -2147483616
    //   5352: iastore
    //   5353: dup
    //   5354: bipush #52
    //   5356: ldc 1048608
    //   5358: iastore
    //   5359: dup
    //   5360: bipush #53
    //   5362: ldc -2147450848
    //   5364: iastore
    //   5365: dup
    //   5366: bipush #54
    //   5368: ldc -2147483616
    //   5370: iastore
    //   5371: dup
    //   5372: bipush #55
    //   5374: ldc 1048608
    //   5376: iastore
    //   5377: dup
    //   5378: bipush #56
    //   5380: ldc 1081344
    //   5382: iastore
    //   5383: dup
    //   5384: bipush #57
    //   5386: iconst_0
    //   5387: iastore
    //   5388: dup
    //   5389: bipush #58
    //   5391: ldc -2147450880
    //   5393: iastore
    //   5394: dup
    //   5395: bipush #59
    //   5397: ldc 32800
    //   5399: iastore
    //   5400: dup
    //   5401: bipush #60
    //   5403: ldc -2147483648
    //   5405: iastore
    //   5406: dup
    //   5407: bipush #61
    //   5409: ldc -2146435040
    //   5411: iastore
    //   5412: dup
    //   5413: bipush #62
    //   5415: ldc -2146402272
    //   5417: iastore
    //   5418: dup
    //   5419: bipush #63
    //   5421: ldc 1081344
    //   5423: iastore
    //   5424: astore #9
    //   5426: bipush #64
    //   5428: newarray int
    //   5430: dup
    //   5431: iconst_0
    //   5432: sipush #520
    //   5435: iastore
    //   5436: dup
    //   5437: iconst_1
    //   5438: ldc 134349312
    //   5440: iastore
    //   5441: dup
    //   5442: iconst_2
    //   5443: iconst_0
    //   5444: iastore
    //   5445: dup
    //   5446: iconst_3
    //   5447: ldc 134348808
    //   5449: iastore
    //   5450: dup
    //   5451: iconst_4
    //   5452: ldc 134218240
    //   5454: iastore
    //   5455: dup
    //   5456: iconst_5
    //   5457: iconst_0
    //   5458: iastore
    //   5459: dup
    //   5460: bipush #6
    //   5462: ldc 131592
    //   5464: iastore
    //   5465: dup
    //   5466: bipush #7
    //   5468: ldc 134218240
    //   5470: iastore
    //   5471: dup
    //   5472: bipush #8
    //   5474: ldc 131080
    //   5476: iastore
    //   5477: dup
    //   5478: bipush #9
    //   5480: ldc 134217736
    //   5482: iastore
    //   5483: dup
    //   5484: bipush #10
    //   5486: ldc 134217736
    //   5488: iastore
    //   5489: dup
    //   5490: bipush #11
    //   5492: ldc 131072
    //   5494: iastore
    //   5495: dup
    //   5496: bipush #12
    //   5498: ldc 134349320
    //   5500: iastore
    //   5501: dup
    //   5502: bipush #13
    //   5504: ldc 131080
    //   5506: iastore
    //   5507: dup
    //   5508: bipush #14
    //   5510: ldc 134348800
    //   5512: iastore
    //   5513: dup
    //   5514: bipush #15
    //   5516: sipush #520
    //   5519: iastore
    //   5520: dup
    //   5521: bipush #16
    //   5523: ldc 134217728
    //   5525: iastore
    //   5526: dup
    //   5527: bipush #17
    //   5529: bipush #8
    //   5531: iastore
    //   5532: dup
    //   5533: bipush #18
    //   5535: ldc 134349312
    //   5537: iastore
    //   5538: dup
    //   5539: bipush #19
    //   5541: sipush #512
    //   5544: iastore
    //   5545: dup
    //   5546: bipush #20
    //   5548: ldc 131584
    //   5550: iastore
    //   5551: dup
    //   5552: bipush #21
    //   5554: ldc 134348800
    //   5556: iastore
    //   5557: dup
    //   5558: bipush #22
    //   5560: ldc 134348808
    //   5562: iastore
    //   5563: dup
    //   5564: bipush #23
    //   5566: ldc 131592
    //   5568: iastore
    //   5569: dup
    //   5570: bipush #24
    //   5572: ldc 134218248
    //   5574: iastore
    //   5575: dup
    //   5576: bipush #25
    //   5578: ldc 131584
    //   5580: iastore
    //   5581: dup
    //   5582: bipush #26
    //   5584: ldc 131072
    //   5586: iastore
    //   5587: dup
    //   5588: bipush #27
    //   5590: ldc 134218248
    //   5592: iastore
    //   5593: dup
    //   5594: bipush #28
    //   5596: bipush #8
    //   5598: iastore
    //   5599: dup
    //   5600: bipush #29
    //   5602: ldc 134349320
    //   5604: iastore
    //   5605: dup
    //   5606: bipush #30
    //   5608: sipush #512
    //   5611: iastore
    //   5612: dup
    //   5613: bipush #31
    //   5615: ldc 134217728
    //   5617: iastore
    //   5618: dup
    //   5619: bipush #32
    //   5621: ldc 134349312
    //   5623: iastore
    //   5624: dup
    //   5625: bipush #33
    //   5627: ldc 134217728
    //   5629: iastore
    //   5630: dup
    //   5631: bipush #34
    //   5633: ldc 131080
    //   5635: iastore
    //   5636: dup
    //   5637: bipush #35
    //   5639: sipush #520
    //   5642: iastore
    //   5643: dup
    //   5644: bipush #36
    //   5646: ldc 131072
    //   5648: iastore
    //   5649: dup
    //   5650: bipush #37
    //   5652: ldc 134349312
    //   5654: iastore
    //   5655: dup
    //   5656: bipush #38
    //   5658: ldc 134218240
    //   5660: iastore
    //   5661: dup
    //   5662: bipush #39
    //   5664: iconst_0
    //   5665: iastore
    //   5666: dup
    //   5667: bipush #40
    //   5669: sipush #512
    //   5672: iastore
    //   5673: dup
    //   5674: bipush #41
    //   5676: ldc 131080
    //   5678: iastore
    //   5679: dup
    //   5680: bipush #42
    //   5682: ldc 134349320
    //   5684: iastore
    //   5685: dup
    //   5686: bipush #43
    //   5688: ldc 134218240
    //   5690: iastore
    //   5691: dup
    //   5692: bipush #44
    //   5694: ldc 134217736
    //   5696: iastore
    //   5697: dup
    //   5698: bipush #45
    //   5700: sipush #512
    //   5703: iastore
    //   5704: dup
    //   5705: bipush #46
    //   5707: iconst_0
    //   5708: iastore
    //   5709: dup
    //   5710: bipush #47
    //   5712: ldc 134348808
    //   5714: iastore
    //   5715: dup
    //   5716: bipush #48
    //   5718: ldc 134218248
    //   5720: iastore
    //   5721: dup
    //   5722: bipush #49
    //   5724: ldc 131072
    //   5726: iastore
    //   5727: dup
    //   5728: bipush #50
    //   5730: ldc 134217728
    //   5732: iastore
    //   5733: dup
    //   5734: bipush #51
    //   5736: ldc 134349320
    //   5738: iastore
    //   5739: dup
    //   5740: bipush #52
    //   5742: bipush #8
    //   5744: iastore
    //   5745: dup
    //   5746: bipush #53
    //   5748: ldc 131592
    //   5750: iastore
    //   5751: dup
    //   5752: bipush #54
    //   5754: ldc 131584
    //   5756: iastore
    //   5757: dup
    //   5758: bipush #55
    //   5760: ldc 134217736
    //   5762: iastore
    //   5763: dup
    //   5764: bipush #56
    //   5766: ldc 134348800
    //   5768: iastore
    //   5769: dup
    //   5770: bipush #57
    //   5772: ldc 134218248
    //   5774: iastore
    //   5775: dup
    //   5776: bipush #58
    //   5778: sipush #520
    //   5781: iastore
    //   5782: dup
    //   5783: bipush #59
    //   5785: ldc 134348800
    //   5787: iastore
    //   5788: dup
    //   5789: bipush #60
    //   5791: ldc 131592
    //   5793: iastore
    //   5794: dup
    //   5795: bipush #61
    //   5797: bipush #8
    //   5799: iastore
    //   5800: dup
    //   5801: bipush #62
    //   5803: ldc 134348808
    //   5805: iastore
    //   5806: dup
    //   5807: bipush #63
    //   5809: ldc 131584
    //   5811: iastore
    //   5812: astore #10
    //   5814: bipush #64
    //   5816: newarray int
    //   5818: dup
    //   5819: iconst_0
    //   5820: ldc 8396801
    //   5822: iastore
    //   5823: dup
    //   5824: iconst_1
    //   5825: sipush #8321
    //   5828: iastore
    //   5829: dup
    //   5830: iconst_2
    //   5831: sipush #8321
    //   5834: iastore
    //   5835: dup
    //   5836: iconst_3
    //   5837: sipush #128
    //   5840: iastore
    //   5841: dup
    //   5842: iconst_4
    //   5843: ldc 8396928
    //   5845: iastore
    //   5846: dup
    //   5847: iconst_5
    //   5848: ldc 8388737
    //   5850: iastore
    //   5851: dup
    //   5852: bipush #6
    //   5854: ldc 8388609
    //   5856: iastore
    //   5857: dup
    //   5858: bipush #7
    //   5860: sipush #8193
    //   5863: iastore
    //   5864: dup
    //   5865: bipush #8
    //   5867: iconst_0
    //   5868: iastore
    //   5869: dup
    //   5870: bipush #9
    //   5872: ldc 8396800
    //   5874: iastore
    //   5875: dup
    //   5876: bipush #10
    //   5878: ldc 8396800
    //   5880: iastore
    //   5881: dup
    //   5882: bipush #11
    //   5884: ldc 8396929
    //   5886: iastore
    //   5887: dup
    //   5888: bipush #12
    //   5890: sipush #129
    //   5893: iastore
    //   5894: dup
    //   5895: bipush #13
    //   5897: iconst_0
    //   5898: iastore
    //   5899: dup
    //   5900: bipush #14
    //   5902: ldc 8388736
    //   5904: iastore
    //   5905: dup
    //   5906: bipush #15
    //   5908: ldc 8388609
    //   5910: iastore
    //   5911: dup
    //   5912: bipush #16
    //   5914: iconst_1
    //   5915: iastore
    //   5916: dup
    //   5917: bipush #17
    //   5919: sipush #8192
    //   5922: iastore
    //   5923: dup
    //   5924: bipush #18
    //   5926: ldc 8388608
    //   5928: iastore
    //   5929: dup
    //   5930: bipush #19
    //   5932: ldc 8396801
    //   5934: iastore
    //   5935: dup
    //   5936: bipush #20
    //   5938: sipush #128
    //   5941: iastore
    //   5942: dup
    //   5943: bipush #21
    //   5945: ldc 8388608
    //   5947: iastore
    //   5948: dup
    //   5949: bipush #22
    //   5951: sipush #8193
    //   5954: iastore
    //   5955: dup
    //   5956: bipush #23
    //   5958: sipush #8320
    //   5961: iastore
    //   5962: dup
    //   5963: bipush #24
    //   5965: ldc 8388737
    //   5967: iastore
    //   5968: dup
    //   5969: bipush #25
    //   5971: iconst_1
    //   5972: iastore
    //   5973: dup
    //   5974: bipush #26
    //   5976: sipush #8320
    //   5979: iastore
    //   5980: dup
    //   5981: bipush #27
    //   5983: ldc 8388736
    //   5985: iastore
    //   5986: dup
    //   5987: bipush #28
    //   5989: sipush #8192
    //   5992: iastore
    //   5993: dup
    //   5994: bipush #29
    //   5996: ldc 8396928
    //   5998: iastore
    //   5999: dup
    //   6000: bipush #30
    //   6002: ldc 8396929
    //   6004: iastore
    //   6005: dup
    //   6006: bipush #31
    //   6008: sipush #129
    //   6011: iastore
    //   6012: dup
    //   6013: bipush #32
    //   6015: ldc 8388736
    //   6017: iastore
    //   6018: dup
    //   6019: bipush #33
    //   6021: ldc 8388609
    //   6023: iastore
    //   6024: dup
    //   6025: bipush #34
    //   6027: ldc 8396800
    //   6029: iastore
    //   6030: dup
    //   6031: bipush #35
    //   6033: ldc 8396929
    //   6035: iastore
    //   6036: dup
    //   6037: bipush #36
    //   6039: sipush #129
    //   6042: iastore
    //   6043: dup
    //   6044: bipush #37
    //   6046: iconst_0
    //   6047: iastore
    //   6048: dup
    //   6049: bipush #38
    //   6051: iconst_0
    //   6052: iastore
    //   6053: dup
    //   6054: bipush #39
    //   6056: ldc 8396800
    //   6058: iastore
    //   6059: dup
    //   6060: bipush #40
    //   6062: sipush #8320
    //   6065: iastore
    //   6066: dup
    //   6067: bipush #41
    //   6069: ldc 8388736
    //   6071: iastore
    //   6072: dup
    //   6073: bipush #42
    //   6075: ldc 8388737
    //   6077: iastore
    //   6078: dup
    //   6079: bipush #43
    //   6081: iconst_1
    //   6082: iastore
    //   6083: dup
    //   6084: bipush #44
    //   6086: ldc 8396801
    //   6088: iastore
    //   6089: dup
    //   6090: bipush #45
    //   6092: sipush #8321
    //   6095: iastore
    //   6096: dup
    //   6097: bipush #46
    //   6099: sipush #8321
    //   6102: iastore
    //   6103: dup
    //   6104: bipush #47
    //   6106: sipush #128
    //   6109: iastore
    //   6110: dup
    //   6111: bipush #48
    //   6113: ldc 8396929
    //   6115: iastore
    //   6116: dup
    //   6117: bipush #49
    //   6119: sipush #129
    //   6122: iastore
    //   6123: dup
    //   6124: bipush #50
    //   6126: iconst_1
    //   6127: iastore
    //   6128: dup
    //   6129: bipush #51
    //   6131: sipush #8192
    //   6134: iastore
    //   6135: dup
    //   6136: bipush #52
    //   6138: ldc 8388609
    //   6140: iastore
    //   6141: dup
    //   6142: bipush #53
    //   6144: sipush #8193
    //   6147: iastore
    //   6148: dup
    //   6149: bipush #54
    //   6151: ldc 8396928
    //   6153: iastore
    //   6154: dup
    //   6155: bipush #55
    //   6157: ldc 8388737
    //   6159: iastore
    //   6160: dup
    //   6161: bipush #56
    //   6163: sipush #8193
    //   6166: iastore
    //   6167: dup
    //   6168: bipush #57
    //   6170: sipush #8320
    //   6173: iastore
    //   6174: dup
    //   6175: bipush #58
    //   6177: ldc 8388608
    //   6179: iastore
    //   6180: dup
    //   6181: bipush #59
    //   6183: ldc 8396801
    //   6185: iastore
    //   6186: dup
    //   6187: bipush #60
    //   6189: sipush #128
    //   6192: iastore
    //   6193: dup
    //   6194: bipush #61
    //   6196: ldc 8388608
    //   6198: iastore
    //   6199: dup
    //   6200: bipush #62
    //   6202: sipush #8192
    //   6205: iastore
    //   6206: dup
    //   6207: bipush #63
    //   6209: ldc 8396928
    //   6211: iastore
    //   6212: astore #11
    //   6214: bipush #64
    //   6216: newarray int
    //   6218: dup
    //   6219: iconst_0
    //   6220: sipush #256
    //   6223: iastore
    //   6224: dup
    //   6225: iconst_1
    //   6226: ldc 34078976
    //   6228: iastore
    //   6229: dup
    //   6230: iconst_2
    //   6231: ldc 34078720
    //   6233: iastore
    //   6234: dup
    //   6235: iconst_3
    //   6236: ldc 1107296512
    //   6238: iastore
    //   6239: dup
    //   6240: iconst_4
    //   6241: ldc 524288
    //   6243: iastore
    //   6244: dup
    //   6245: iconst_5
    //   6246: sipush #256
    //   6249: iastore
    //   6250: dup
    //   6251: bipush #6
    //   6253: ldc 1073741824
    //   6255: iastore
    //   6256: dup
    //   6257: bipush #7
    //   6259: ldc 34078720
    //   6261: iastore
    //   6262: dup
    //   6263: bipush #8
    //   6265: ldc 1074266368
    //   6267: iastore
    //   6268: dup
    //   6269: bipush #9
    //   6271: ldc 524288
    //   6273: iastore
    //   6274: dup
    //   6275: bipush #10
    //   6277: ldc 33554688
    //   6279: iastore
    //   6280: dup
    //   6281: bipush #11
    //   6283: ldc 1074266368
    //   6285: iastore
    //   6286: dup
    //   6287: bipush #12
    //   6289: ldc 1107296512
    //   6291: iastore
    //   6292: dup
    //   6293: bipush #13
    //   6295: ldc 1107820544
    //   6297: iastore
    //   6298: dup
    //   6299: bipush #14
    //   6301: ldc 524544
    //   6303: iastore
    //   6304: dup
    //   6305: bipush #15
    //   6307: ldc 1073741824
    //   6309: iastore
    //   6310: dup
    //   6311: bipush #16
    //   6313: ldc 33554432
    //   6315: iastore
    //   6316: dup
    //   6317: bipush #17
    //   6319: ldc 1074266112
    //   6321: iastore
    //   6322: dup
    //   6323: bipush #18
    //   6325: ldc 1074266112
    //   6327: iastore
    //   6328: dup
    //   6329: bipush #19
    //   6331: iconst_0
    //   6332: iastore
    //   6333: dup
    //   6334: bipush #20
    //   6336: ldc 1073742080
    //   6338: iastore
    //   6339: dup
    //   6340: bipush #21
    //   6342: ldc 1107820800
    //   6344: iastore
    //   6345: dup
    //   6346: bipush #22
    //   6348: ldc 1107820800
    //   6350: iastore
    //   6351: dup
    //   6352: bipush #23
    //   6354: ldc 33554688
    //   6356: iastore
    //   6357: dup
    //   6358: bipush #24
    //   6360: ldc 1107820544
    //   6362: iastore
    //   6363: dup
    //   6364: bipush #25
    //   6366: ldc 1073742080
    //   6368: iastore
    //   6369: dup
    //   6370: bipush #26
    //   6372: iconst_0
    //   6373: iastore
    //   6374: dup
    //   6375: bipush #27
    //   6377: ldc 1107296256
    //   6379: iastore
    //   6380: dup
    //   6381: bipush #28
    //   6383: ldc 34078976
    //   6385: iastore
    //   6386: dup
    //   6387: bipush #29
    //   6389: ldc 33554432
    //   6391: iastore
    //   6392: dup
    //   6393: bipush #30
    //   6395: ldc 1107296256
    //   6397: iastore
    //   6398: dup
    //   6399: bipush #31
    //   6401: ldc 524544
    //   6403: iastore
    //   6404: dup
    //   6405: bipush #32
    //   6407: ldc 524288
    //   6409: iastore
    //   6410: dup
    //   6411: bipush #33
    //   6413: ldc 1107296512
    //   6415: iastore
    //   6416: dup
    //   6417: bipush #34
    //   6419: sipush #256
    //   6422: iastore
    //   6423: dup
    //   6424: bipush #35
    //   6426: ldc 33554432
    //   6428: iastore
    //   6429: dup
    //   6430: bipush #36
    //   6432: ldc 1073741824
    //   6434: iastore
    //   6435: dup
    //   6436: bipush #37
    //   6438: ldc 34078720
    //   6440: iastore
    //   6441: dup
    //   6442: bipush #38
    //   6444: ldc 1107296512
    //   6446: iastore
    //   6447: dup
    //   6448: bipush #39
    //   6450: ldc 1074266368
    //   6452: iastore
    //   6453: dup
    //   6454: bipush #40
    //   6456: ldc 33554688
    //   6458: iastore
    //   6459: dup
    //   6460: bipush #41
    //   6462: ldc 1073741824
    //   6464: iastore
    //   6465: dup
    //   6466: bipush #42
    //   6468: ldc 1107820544
    //   6470: iastore
    //   6471: dup
    //   6472: bipush #43
    //   6474: ldc 34078976
    //   6476: iastore
    //   6477: dup
    //   6478: bipush #44
    //   6480: ldc 1074266368
    //   6482: iastore
    //   6483: dup
    //   6484: bipush #45
    //   6486: sipush #256
    //   6489: iastore
    //   6490: dup
    //   6491: bipush #46
    //   6493: ldc 33554432
    //   6495: iastore
    //   6496: dup
    //   6497: bipush #47
    //   6499: ldc 1107820544
    //   6501: iastore
    //   6502: dup
    //   6503: bipush #48
    //   6505: ldc 1107820800
    //   6507: iastore
    //   6508: dup
    //   6509: bipush #49
    //   6511: ldc 524544
    //   6513: iastore
    //   6514: dup
    //   6515: bipush #50
    //   6517: ldc 1107296256
    //   6519: iastore
    //   6520: dup
    //   6521: bipush #51
    //   6523: ldc 1107820800
    //   6525: iastore
    //   6526: dup
    //   6527: bipush #52
    //   6529: ldc 34078720
    //   6531: iastore
    //   6532: dup
    //   6533: bipush #53
    //   6535: iconst_0
    //   6536: iastore
    //   6537: dup
    //   6538: bipush #54
    //   6540: ldc 1074266112
    //   6542: iastore
    //   6543: dup
    //   6544: bipush #55
    //   6546: ldc 1107296256
    //   6548: iastore
    //   6549: dup
    //   6550: bipush #56
    //   6552: ldc 524544
    //   6554: iastore
    //   6555: dup
    //   6556: bipush #57
    //   6558: ldc 33554688
    //   6560: iastore
    //   6561: dup
    //   6562: bipush #58
    //   6564: ldc 1073742080
    //   6566: iastore
    //   6567: dup
    //   6568: bipush #59
    //   6570: ldc 524288
    //   6572: iastore
    //   6573: dup
    //   6574: bipush #60
    //   6576: iconst_0
    //   6577: iastore
    //   6578: dup
    //   6579: bipush #61
    //   6581: ldc 1074266112
    //   6583: iastore
    //   6584: dup
    //   6585: bipush #62
    //   6587: ldc 34078976
    //   6589: iastore
    //   6590: dup
    //   6591: bipush #63
    //   6593: ldc 1073742080
    //   6595: iastore
    //   6596: astore #12
    //   6598: bipush #64
    //   6600: newarray int
    //   6602: dup
    //   6603: iconst_0
    //   6604: ldc 536870928
    //   6606: iastore
    //   6607: dup
    //   6608: iconst_1
    //   6609: ldc 541065216
    //   6611: iastore
    //   6612: dup
    //   6613: iconst_2
    //   6614: sipush #16384
    //   6617: iastore
    //   6618: dup
    //   6619: iconst_3
    //   6620: ldc 541081616
    //   6622: iastore
    //   6623: dup
    //   6624: iconst_4
    //   6625: ldc 541065216
    //   6627: iastore
    //   6628: dup
    //   6629: iconst_5
    //   6630: bipush #16
    //   6632: iastore
    //   6633: dup
    //   6634: bipush #6
    //   6636: ldc 541081616
    //   6638: iastore
    //   6639: dup
    //   6640: bipush #7
    //   6642: ldc 4194304
    //   6644: iastore
    //   6645: dup
    //   6646: bipush #8
    //   6648: ldc 536887296
    //   6650: iastore
    //   6651: dup
    //   6652: bipush #9
    //   6654: ldc 4210704
    //   6656: iastore
    //   6657: dup
    //   6658: bipush #10
    //   6660: ldc 4194304
    //   6662: iastore
    //   6663: dup
    //   6664: bipush #11
    //   6666: ldc 536870928
    //   6668: iastore
    //   6669: dup
    //   6670: bipush #12
    //   6672: ldc 4194320
    //   6674: iastore
    //   6675: dup
    //   6676: bipush #13
    //   6678: ldc 536887296
    //   6680: iastore
    //   6681: dup
    //   6682: bipush #14
    //   6684: ldc 536870912
    //   6686: iastore
    //   6687: dup
    //   6688: bipush #15
    //   6690: sipush #16400
    //   6693: iastore
    //   6694: dup
    //   6695: bipush #16
    //   6697: iconst_0
    //   6698: iastore
    //   6699: dup
    //   6700: bipush #17
    //   6702: ldc 4194320
    //   6704: iastore
    //   6705: dup
    //   6706: bipush #18
    //   6708: ldc 536887312
    //   6710: iastore
    //   6711: dup
    //   6712: bipush #19
    //   6714: sipush #16384
    //   6717: iastore
    //   6718: dup
    //   6719: bipush #20
    //   6721: ldc 4210688
    //   6723: iastore
    //   6724: dup
    //   6725: bipush #21
    //   6727: ldc 536887312
    //   6729: iastore
    //   6730: dup
    //   6731: bipush #22
    //   6733: bipush #16
    //   6735: iastore
    //   6736: dup
    //   6737: bipush #23
    //   6739: ldc 541065232
    //   6741: iastore
    //   6742: dup
    //   6743: bipush #24
    //   6745: ldc 541065232
    //   6747: iastore
    //   6748: dup
    //   6749: bipush #25
    //   6751: iconst_0
    //   6752: iastore
    //   6753: dup
    //   6754: bipush #26
    //   6756: ldc 4210704
    //   6758: iastore
    //   6759: dup
    //   6760: bipush #27
    //   6762: ldc 541081600
    //   6764: iastore
    //   6765: dup
    //   6766: bipush #28
    //   6768: sipush #16400
    //   6771: iastore
    //   6772: dup
    //   6773: bipush #29
    //   6775: ldc 4210688
    //   6777: iastore
    //   6778: dup
    //   6779: bipush #30
    //   6781: ldc 541081600
    //   6783: iastore
    //   6784: dup
    //   6785: bipush #31
    //   6787: ldc 536870912
    //   6789: iastore
    //   6790: dup
    //   6791: bipush #32
    //   6793: ldc 536887296
    //   6795: iastore
    //   6796: dup
    //   6797: bipush #33
    //   6799: bipush #16
    //   6801: iastore
    //   6802: dup
    //   6803: bipush #34
    //   6805: ldc 541065232
    //   6807: iastore
    //   6808: dup
    //   6809: bipush #35
    //   6811: ldc 4210688
    //   6813: iastore
    //   6814: dup
    //   6815: bipush #36
    //   6817: ldc 541081616
    //   6819: iastore
    //   6820: dup
    //   6821: bipush #37
    //   6823: ldc 4194304
    //   6825: iastore
    //   6826: dup
    //   6827: bipush #38
    //   6829: sipush #16400
    //   6832: iastore
    //   6833: dup
    //   6834: bipush #39
    //   6836: ldc 536870928
    //   6838: iastore
    //   6839: dup
    //   6840: bipush #40
    //   6842: ldc 4194304
    //   6844: iastore
    //   6845: dup
    //   6846: bipush #41
    //   6848: ldc 536887296
    //   6850: iastore
    //   6851: dup
    //   6852: bipush #42
    //   6854: ldc 536870912
    //   6856: iastore
    //   6857: dup
    //   6858: bipush #43
    //   6860: sipush #16400
    //   6863: iastore
    //   6864: dup
    //   6865: bipush #44
    //   6867: ldc 536870928
    //   6869: iastore
    //   6870: dup
    //   6871: bipush #45
    //   6873: ldc 541081616
    //   6875: iastore
    //   6876: dup
    //   6877: bipush #46
    //   6879: ldc 4210688
    //   6881: iastore
    //   6882: dup
    //   6883: bipush #47
    //   6885: ldc 541065216
    //   6887: iastore
    //   6888: dup
    //   6889: bipush #48
    //   6891: ldc 4210704
    //   6893: iastore
    //   6894: dup
    //   6895: bipush #49
    //   6897: ldc 541081600
    //   6899: iastore
    //   6900: dup
    //   6901: bipush #50
    //   6903: iconst_0
    //   6904: iastore
    //   6905: dup
    //   6906: bipush #51
    //   6908: ldc 541065232
    //   6910: iastore
    //   6911: dup
    //   6912: bipush #52
    //   6914: bipush #16
    //   6916: iastore
    //   6917: dup
    //   6918: bipush #53
    //   6920: sipush #16384
    //   6923: iastore
    //   6924: dup
    //   6925: bipush #54
    //   6927: ldc 541065216
    //   6929: iastore
    //   6930: dup
    //   6931: bipush #55
    //   6933: ldc 4210704
    //   6935: iastore
    //   6936: dup
    //   6937: bipush #56
    //   6939: sipush #16384
    //   6942: iastore
    //   6943: dup
    //   6944: bipush #57
    //   6946: ldc 4194320
    //   6948: iastore
    //   6949: dup
    //   6950: bipush #58
    //   6952: ldc 536887312
    //   6954: iastore
    //   6955: dup
    //   6956: bipush #59
    //   6958: iconst_0
    //   6959: iastore
    //   6960: dup
    //   6961: bipush #60
    //   6963: ldc 541081600
    //   6965: iastore
    //   6966: dup
    //   6967: bipush #61
    //   6969: ldc 536870912
    //   6971: iastore
    //   6972: dup
    //   6973: bipush #62
    //   6975: ldc 4194320
    //   6977: iastore
    //   6978: dup
    //   6979: bipush #63
    //   6981: ldc 536887312
    //   6983: iastore
    //   6984: astore #13
    //   6986: bipush #64
    //   6988: newarray int
    //   6990: dup
    //   6991: iconst_0
    //   6992: ldc 2097152
    //   6994: iastore
    //   6995: dup
    //   6996: iconst_1
    //   6997: ldc 69206018
    //   6999: iastore
    //   7000: dup
    //   7001: iconst_2
    //   7002: ldc 67110914
    //   7004: iastore
    //   7005: dup
    //   7006: iconst_3
    //   7007: iconst_0
    //   7008: iastore
    //   7009: dup
    //   7010: iconst_4
    //   7011: sipush #2048
    //   7014: iastore
    //   7015: dup
    //   7016: iconst_5
    //   7017: ldc 67110914
    //   7019: iastore
    //   7020: dup
    //   7021: bipush #6
    //   7023: ldc 2099202
    //   7025: iastore
    //   7026: dup
    //   7027: bipush #7
    //   7029: ldc 69208064
    //   7031: iastore
    //   7032: dup
    //   7033: bipush #8
    //   7035: ldc 69208066
    //   7037: iastore
    //   7038: dup
    //   7039: bipush #9
    //   7041: ldc 2097152
    //   7043: iastore
    //   7044: dup
    //   7045: bipush #10
    //   7047: iconst_0
    //   7048: iastore
    //   7049: dup
    //   7050: bipush #11
    //   7052: ldc 67108866
    //   7054: iastore
    //   7055: dup
    //   7056: bipush #12
    //   7058: iconst_2
    //   7059: iastore
    //   7060: dup
    //   7061: bipush #13
    //   7063: ldc 67108864
    //   7065: iastore
    //   7066: dup
    //   7067: bipush #14
    //   7069: ldc 69206018
    //   7071: iastore
    //   7072: dup
    //   7073: bipush #15
    //   7075: sipush #2050
    //   7078: iastore
    //   7079: dup
    //   7080: bipush #16
    //   7082: ldc 67110912
    //   7084: iastore
    //   7085: dup
    //   7086: bipush #17
    //   7088: ldc 2099202
    //   7090: iastore
    //   7091: dup
    //   7092: bipush #18
    //   7094: ldc 2097154
    //   7096: iastore
    //   7097: dup
    //   7098: bipush #19
    //   7100: ldc 67110912
    //   7102: iastore
    //   7103: dup
    //   7104: bipush #20
    //   7106: ldc 67108866
    //   7108: iastore
    //   7109: dup
    //   7110: bipush #21
    //   7112: ldc 69206016
    //   7114: iastore
    //   7115: dup
    //   7116: bipush #22
    //   7118: ldc 69208064
    //   7120: iastore
    //   7121: dup
    //   7122: bipush #23
    //   7124: ldc 2097154
    //   7126: iastore
    //   7127: dup
    //   7128: bipush #24
    //   7130: ldc 69206016
    //   7132: iastore
    //   7133: dup
    //   7134: bipush #25
    //   7136: sipush #2048
    //   7139: iastore
    //   7140: dup
    //   7141: bipush #26
    //   7143: sipush #2050
    //   7146: iastore
    //   7147: dup
    //   7148: bipush #27
    //   7150: ldc 69208066
    //   7152: iastore
    //   7153: dup
    //   7154: bipush #28
    //   7156: ldc 2099200
    //   7158: iastore
    //   7159: dup
    //   7160: bipush #29
    //   7162: iconst_2
    //   7163: iastore
    //   7164: dup
    //   7165: bipush #30
    //   7167: ldc 67108864
    //   7169: iastore
    //   7170: dup
    //   7171: bipush #31
    //   7173: ldc 2099200
    //   7175: iastore
    //   7176: dup
    //   7177: bipush #32
    //   7179: ldc 67108864
    //   7181: iastore
    //   7182: dup
    //   7183: bipush #33
    //   7185: ldc 2099200
    //   7187: iastore
    //   7188: dup
    //   7189: bipush #34
    //   7191: ldc 2097152
    //   7193: iastore
    //   7194: dup
    //   7195: bipush #35
    //   7197: ldc 67110914
    //   7199: iastore
    //   7200: dup
    //   7201: bipush #36
    //   7203: ldc 67110914
    //   7205: iastore
    //   7206: dup
    //   7207: bipush #37
    //   7209: ldc 69206018
    //   7211: iastore
    //   7212: dup
    //   7213: bipush #38
    //   7215: ldc 69206018
    //   7217: iastore
    //   7218: dup
    //   7219: bipush #39
    //   7221: iconst_2
    //   7222: iastore
    //   7223: dup
    //   7224: bipush #40
    //   7226: ldc 2097154
    //   7228: iastore
    //   7229: dup
    //   7230: bipush #41
    //   7232: ldc 67108864
    //   7234: iastore
    //   7235: dup
    //   7236: bipush #42
    //   7238: ldc 67110912
    //   7240: iastore
    //   7241: dup
    //   7242: bipush #43
    //   7244: ldc 2097152
    //   7246: iastore
    //   7247: dup
    //   7248: bipush #44
    //   7250: ldc 69208064
    //   7252: iastore
    //   7253: dup
    //   7254: bipush #45
    //   7256: sipush #2050
    //   7259: iastore
    //   7260: dup
    //   7261: bipush #46
    //   7263: ldc 2099202
    //   7265: iastore
    //   7266: dup
    //   7267: bipush #47
    //   7269: ldc 69208064
    //   7271: iastore
    //   7272: dup
    //   7273: bipush #48
    //   7275: sipush #2050
    //   7278: iastore
    //   7279: dup
    //   7280: bipush #49
    //   7282: ldc 67108866
    //   7284: iastore
    //   7285: dup
    //   7286: bipush #50
    //   7288: ldc 69208066
    //   7290: iastore
    //   7291: dup
    //   7292: bipush #51
    //   7294: ldc 69206016
    //   7296: iastore
    //   7297: dup
    //   7298: bipush #52
    //   7300: ldc 2099200
    //   7302: iastore
    //   7303: dup
    //   7304: bipush #53
    //   7306: iconst_0
    //   7307: iastore
    //   7308: dup
    //   7309: bipush #54
    //   7311: iconst_2
    //   7312: iastore
    //   7313: dup
    //   7314: bipush #55
    //   7316: ldc 69208066
    //   7318: iastore
    //   7319: dup
    //   7320: bipush #56
    //   7322: iconst_0
    //   7323: iastore
    //   7324: dup
    //   7325: bipush #57
    //   7327: ldc 2099202
    //   7329: iastore
    //   7330: dup
    //   7331: bipush #58
    //   7333: ldc 69206016
    //   7335: iastore
    //   7336: dup
    //   7337: bipush #59
    //   7339: sipush #2048
    //   7342: iastore
    //   7343: dup
    //   7344: bipush #60
    //   7346: ldc 67108866
    //   7348: iastore
    //   7349: dup
    //   7350: bipush #61
    //   7352: ldc 67110912
    //   7354: iastore
    //   7355: dup
    //   7356: bipush #62
    //   7358: sipush #2048
    //   7361: iastore
    //   7362: dup
    //   7363: bipush #63
    //   7365: ldc 2097154
    //   7367: iastore
    //   7368: astore #14
    //   7370: bipush #64
    //   7372: newarray int
    //   7374: dup
    //   7375: iconst_0
    //   7376: ldc 268439616
    //   7378: iastore
    //   7379: dup
    //   7380: iconst_1
    //   7381: sipush #4096
    //   7384: iastore
    //   7385: dup
    //   7386: iconst_2
    //   7387: ldc 262144
    //   7389: iastore
    //   7390: dup
    //   7391: iconst_3
    //   7392: ldc 268701760
    //   7394: iastore
    //   7395: dup
    //   7396: iconst_4
    //   7397: ldc 268435456
    //   7399: iastore
    //   7400: dup
    //   7401: iconst_5
    //   7402: ldc 268439616
    //   7404: iastore
    //   7405: dup
    //   7406: bipush #6
    //   7408: bipush #64
    //   7410: iastore
    //   7411: dup
    //   7412: bipush #7
    //   7414: ldc 268435456
    //   7416: iastore
    //   7417: dup
    //   7418: bipush #8
    //   7420: ldc 262208
    //   7422: iastore
    //   7423: dup
    //   7424: bipush #9
    //   7426: ldc 268697600
    //   7428: iastore
    //   7429: dup
    //   7430: bipush #10
    //   7432: ldc 268701760
    //   7434: iastore
    //   7435: dup
    //   7436: bipush #11
    //   7438: ldc 266240
    //   7440: iastore
    //   7441: dup
    //   7442: bipush #12
    //   7444: ldc 268701696
    //   7446: iastore
    //   7447: dup
    //   7448: bipush #13
    //   7450: ldc 266304
    //   7452: iastore
    //   7453: dup
    //   7454: bipush #14
    //   7456: sipush #4096
    //   7459: iastore
    //   7460: dup
    //   7461: bipush #15
    //   7463: bipush #64
    //   7465: iastore
    //   7466: dup
    //   7467: bipush #16
    //   7469: ldc 268697600
    //   7471: iastore
    //   7472: dup
    //   7473: bipush #17
    //   7475: ldc 268435520
    //   7477: iastore
    //   7478: dup
    //   7479: bipush #18
    //   7481: ldc 268439552
    //   7483: iastore
    //   7484: dup
    //   7485: bipush #19
    //   7487: sipush #4160
    //   7490: iastore
    //   7491: dup
    //   7492: bipush #20
    //   7494: ldc 266240
    //   7496: iastore
    //   7497: dup
    //   7498: bipush #21
    //   7500: ldc 262208
    //   7502: iastore
    //   7503: dup
    //   7504: bipush #22
    //   7506: ldc 268697664
    //   7508: iastore
    //   7509: dup
    //   7510: bipush #23
    //   7512: ldc 268701696
    //   7514: iastore
    //   7515: dup
    //   7516: bipush #24
    //   7518: sipush #4160
    //   7521: iastore
    //   7522: dup
    //   7523: bipush #25
    //   7525: iconst_0
    //   7526: iastore
    //   7527: dup
    //   7528: bipush #26
    //   7530: iconst_0
    //   7531: iastore
    //   7532: dup
    //   7533: bipush #27
    //   7535: ldc 268697664
    //   7537: iastore
    //   7538: dup
    //   7539: bipush #28
    //   7541: ldc 268435520
    //   7543: iastore
    //   7544: dup
    //   7545: bipush #29
    //   7547: ldc 268439552
    //   7549: iastore
    //   7550: dup
    //   7551: bipush #30
    //   7553: ldc 266304
    //   7555: iastore
    //   7556: dup
    //   7557: bipush #31
    //   7559: ldc 262144
    //   7561: iastore
    //   7562: dup
    //   7563: bipush #32
    //   7565: ldc 266304
    //   7567: iastore
    //   7568: dup
    //   7569: bipush #33
    //   7571: ldc 262144
    //   7573: iastore
    //   7574: dup
    //   7575: bipush #34
    //   7577: ldc 268701696
    //   7579: iastore
    //   7580: dup
    //   7581: bipush #35
    //   7583: sipush #4096
    //   7586: iastore
    //   7587: dup
    //   7588: bipush #36
    //   7590: bipush #64
    //   7592: iastore
    //   7593: dup
    //   7594: bipush #37
    //   7596: ldc 268697664
    //   7598: iastore
    //   7599: dup
    //   7600: bipush #38
    //   7602: sipush #4096
    //   7605: iastore
    //   7606: dup
    //   7607: bipush #39
    //   7609: ldc 266304
    //   7611: iastore
    //   7612: dup
    //   7613: bipush #40
    //   7615: ldc 268439552
    //   7617: iastore
    //   7618: dup
    //   7619: bipush #41
    //   7621: bipush #64
    //   7623: iastore
    //   7624: dup
    //   7625: bipush #42
    //   7627: ldc 268435520
    //   7629: iastore
    //   7630: dup
    //   7631: bipush #43
    //   7633: ldc 268697600
    //   7635: iastore
    //   7636: dup
    //   7637: bipush #44
    //   7639: ldc 268697664
    //   7641: iastore
    //   7642: dup
    //   7643: bipush #45
    //   7645: ldc 268435456
    //   7647: iastore
    //   7648: dup
    //   7649: bipush #46
    //   7651: ldc 262144
    //   7653: iastore
    //   7654: dup
    //   7655: bipush #47
    //   7657: ldc 268439616
    //   7659: iastore
    //   7660: dup
    //   7661: bipush #48
    //   7663: iconst_0
    //   7664: iastore
    //   7665: dup
    //   7666: bipush #49
    //   7668: ldc 268701760
    //   7670: iastore
    //   7671: dup
    //   7672: bipush #50
    //   7674: ldc 262208
    //   7676: iastore
    //   7677: dup
    //   7678: bipush #51
    //   7680: ldc 268435520
    //   7682: iastore
    //   7683: dup
    //   7684: bipush #52
    //   7686: ldc 268697600
    //   7688: iastore
    //   7689: dup
    //   7690: bipush #53
    //   7692: ldc 268439552
    //   7694: iastore
    //   7695: dup
    //   7696: bipush #54
    //   7698: ldc 268439616
    //   7700: iastore
    //   7701: dup
    //   7702: bipush #55
    //   7704: iconst_0
    //   7705: iastore
    //   7706: dup
    //   7707: bipush #56
    //   7709: ldc 268701760
    //   7711: iastore
    //   7712: dup
    //   7713: bipush #57
    //   7715: ldc 266240
    //   7717: iastore
    //   7718: dup
    //   7719: bipush #58
    //   7721: ldc 266240
    //   7723: iastore
    //   7724: dup
    //   7725: bipush #59
    //   7727: sipush #4160
    //   7730: iastore
    //   7731: dup
    //   7732: bipush #60
    //   7734: sipush #4160
    //   7737: iastore
    //   7738: dup
    //   7739: bipush #61
    //   7741: ldc 262208
    //   7743: iastore
    //   7744: dup
    //   7745: bipush #62
    //   7747: ldc 268435456
    //   7749: iastore
    //   7750: dup
    //   7751: bipush #63
    //   7753: ldc 268701696
    //   7755: iastore
    //   7756: astore #15
    //   7758: aload_3
    //   7759: arraylength
    //   7760: istore #16
    //   7762: iconst_2
    //   7763: newarray int
    //   7765: astore #17
    //   7767: iload #16
    //   7769: newarray byte
    //   7771: astore #4
    //   7773: iload #16
    //   7775: bipush #8
    //   7777: idiv
    //   7778: istore #18
    //   7780: iconst_0
    //   7781: istore #19
    //   7783: iload #19
    //   7785: iload #18
    //   7787: if_icmpge -> 8701
    //   7790: iload #19
    //   7792: bipush #8
    //   7794: imul
    //   7795: istore #20
    //   7797: iconst_0
    //   7798: istore #21
    //   7800: iload #21
    //   7802: iconst_2
    //   7803: if_icmpge -> 7888
    //   7806: aload #17
    //   7808: iload #21
    //   7810: aload_3
    //   7811: iload #20
    //   7813: iload #21
    //   7815: iconst_4
    //   7816: imul
    //   7817: iadd
    //   7818: baload
    //   7819: sipush #255
    //   7822: iand
    //   7823: bipush #24
    //   7825: ishl
    //   7826: aload_3
    //   7827: iload #20
    //   7829: iload #21
    //   7831: iconst_4
    //   7832: imul
    //   7833: iadd
    //   7834: iconst_1
    //   7835: iadd
    //   7836: baload
    //   7837: sipush #255
    //   7840: iand
    //   7841: bipush #16
    //   7843: ishl
    //   7844: ior
    //   7845: aload_3
    //   7846: iload #20
    //   7848: iload #21
    //   7850: iconst_4
    //   7851: imul
    //   7852: iadd
    //   7853: iconst_2
    //   7854: iadd
    //   7855: baload
    //   7856: sipush #255
    //   7859: iand
    //   7860: bipush #8
    //   7862: ishl
    //   7863: ior
    //   7864: aload_3
    //   7865: iload #20
    //   7867: iload #21
    //   7869: iconst_4
    //   7870: imul
    //   7871: iadd
    //   7872: iconst_3
    //   7873: iadd
    //   7874: baload
    //   7875: sipush #255
    //   7878: iand
    //   7879: ior
    //   7880: iastore
    //   7881: iinc #21, 1
    //   7884: iload_2
    //   7885: ifne -> 7800
    //   7888: iconst_0
    //   7889: istore #26
    //   7891: aload #17
    //   7893: iconst_0
    //   7894: iaload
    //   7895: istore #24
    //   7897: aload #17
    //   7899: iconst_1
    //   7900: iaload
    //   7901: istore #23
    //   7903: iload #24
    //   7905: iconst_4
    //   7906: iushr
    //   7907: iload #23
    //   7909: ixor
    //   7910: ldc 252645135
    //   7912: iand
    //   7913: istore #22
    //   7915: iload #23
    //   7917: iload #22
    //   7919: ixor
    //   7920: istore #23
    //   7922: iload #24
    //   7924: iload #22
    //   7926: iconst_4
    //   7927: ishl
    //   7928: ixor
    //   7929: istore #24
    //   7931: iload #24
    //   7933: bipush #16
    //   7935: iushr
    //   7936: iload #23
    //   7938: ixor
    //   7939: ldc 65535
    //   7941: iand
    //   7942: istore #22
    //   7944: iload #23
    //   7946: iload #22
    //   7948: ixor
    //   7949: istore #23
    //   7951: iload #24
    //   7953: iload #22
    //   7955: bipush #16
    //   7957: ishl
    //   7958: ixor
    //   7959: istore #24
    //   7961: iload #23
    //   7963: iconst_2
    //   7964: iushr
    //   7965: iload #24
    //   7967: ixor
    //   7968: ldc 858993459
    //   7970: iand
    //   7971: istore #22
    //   7973: iload #24
    //   7975: iload #22
    //   7977: ixor
    //   7978: istore #24
    //   7980: iload #23
    //   7982: iload #22
    //   7984: iconst_2
    //   7985: ishl
    //   7986: ixor
    //   7987: istore #23
    //   7989: iload #23
    //   7991: bipush #8
    //   7993: iushr
    //   7994: iload #24
    //   7996: ixor
    //   7997: ldc 16711935
    //   7999: iand
    //   8000: istore #22
    //   8002: iload #24
    //   8004: iload #22
    //   8006: ixor
    //   8007: istore #24
    //   8009: iload #23
    //   8011: iload #22
    //   8013: bipush #8
    //   8015: ishl
    //   8016: ixor
    //   8017: istore #23
    //   8019: iload #23
    //   8021: iconst_1
    //   8022: ishl
    //   8023: iload #23
    //   8025: bipush #31
    //   8027: iushr
    //   8028: iconst_1
    //   8029: iand
    //   8030: ior
    //   8031: istore #23
    //   8033: iload #24
    //   8035: iload #23
    //   8037: ixor
    //   8038: ldc -1431655766
    //   8040: iand
    //   8041: istore #22
    //   8043: iload #24
    //   8045: iload #22
    //   8047: ixor
    //   8048: istore #24
    //   8050: iload #23
    //   8052: iload #22
    //   8054: ixor
    //   8055: istore #23
    //   8057: iload #24
    //   8059: iconst_1
    //   8060: ishl
    //   8061: iload #24
    //   8063: bipush #31
    //   8065: iushr
    //   8066: iconst_1
    //   8067: iand
    //   8068: ior
    //   8069: istore #24
    //   8071: iconst_0
    //   8072: istore #25
    //   8074: iload #25
    //   8076: bipush #8
    //   8078: if_icmpge -> 8416
    //   8081: iload #23
    //   8083: bipush #28
    //   8085: ishl
    //   8086: iload #23
    //   8088: iconst_4
    //   8089: iushr
    //   8090: ior
    //   8091: istore #22
    //   8093: iload #22
    //   8095: aload #5
    //   8097: iload #26
    //   8099: iinc #26, 1
    //   8102: iaload
    //   8103: ixor
    //   8104: istore #22
    //   8106: aload #14
    //   8108: iload #22
    //   8110: bipush #63
    //   8112: iand
    //   8113: iaload
    //   8114: istore #21
    //   8116: iload #21
    //   8118: aload #12
    //   8120: iload #22
    //   8122: bipush #8
    //   8124: iushr
    //   8125: bipush #63
    //   8127: iand
    //   8128: iaload
    //   8129: ior
    //   8130: istore #21
    //   8132: iload #21
    //   8134: aload #10
    //   8136: iload #22
    //   8138: bipush #16
    //   8140: iushr
    //   8141: bipush #63
    //   8143: iand
    //   8144: iaload
    //   8145: ior
    //   8146: istore #21
    //   8148: iload #21
    //   8150: aload #8
    //   8152: iload #22
    //   8154: bipush #24
    //   8156: iushr
    //   8157: bipush #63
    //   8159: iand
    //   8160: iaload
    //   8161: ior
    //   8162: istore #21
    //   8164: iload #23
    //   8166: aload #5
    //   8168: iload #26
    //   8170: iinc #26, 1
    //   8173: iaload
    //   8174: ixor
    //   8175: istore #22
    //   8177: iload #21
    //   8179: aload #15
    //   8181: iload #22
    //   8183: bipush #63
    //   8185: iand
    //   8186: iaload
    //   8187: ior
    //   8188: istore #21
    //   8190: iload #21
    //   8192: aload #13
    //   8194: iload #22
    //   8196: bipush #8
    //   8198: iushr
    //   8199: bipush #63
    //   8201: iand
    //   8202: iaload
    //   8203: ior
    //   8204: istore #21
    //   8206: iload #21
    //   8208: aload #11
    //   8210: iload #22
    //   8212: bipush #16
    //   8214: iushr
    //   8215: bipush #63
    //   8217: iand
    //   8218: iaload
    //   8219: ior
    //   8220: istore #21
    //   8222: iload #21
    //   8224: aload #9
    //   8226: iload #22
    //   8228: bipush #24
    //   8230: iushr
    //   8231: bipush #63
    //   8233: iand
    //   8234: iaload
    //   8235: ior
    //   8236: istore #21
    //   8238: iload #24
    //   8240: iload #21
    //   8242: ixor
    //   8243: istore #24
    //   8245: iload #24
    //   8247: bipush #28
    //   8249: ishl
    //   8250: iload #24
    //   8252: iconst_4
    //   8253: iushr
    //   8254: ior
    //   8255: istore #22
    //   8257: iload #22
    //   8259: aload #5
    //   8261: iload #26
    //   8263: iinc #26, 1
    //   8266: iaload
    //   8267: ixor
    //   8268: istore #22
    //   8270: aload #14
    //   8272: iload #22
    //   8274: bipush #63
    //   8276: iand
    //   8277: iaload
    //   8278: istore #21
    //   8280: iload #21
    //   8282: aload #12
    //   8284: iload #22
    //   8286: bipush #8
    //   8288: iushr
    //   8289: bipush #63
    //   8291: iand
    //   8292: iaload
    //   8293: ior
    //   8294: istore #21
    //   8296: iload #21
    //   8298: aload #10
    //   8300: iload #22
    //   8302: bipush #16
    //   8304: iushr
    //   8305: bipush #63
    //   8307: iand
    //   8308: iaload
    //   8309: ior
    //   8310: istore #21
    //   8312: iload #21
    //   8314: aload #8
    //   8316: iload #22
    //   8318: bipush #24
    //   8320: iushr
    //   8321: bipush #63
    //   8323: iand
    //   8324: iaload
    //   8325: ior
    //   8326: istore #21
    //   8328: iload #24
    //   8330: aload #5
    //   8332: iload #26
    //   8334: iinc #26, 1
    //   8337: iaload
    //   8338: ixor
    //   8339: istore #22
    //   8341: iload #21
    //   8343: aload #15
    //   8345: iload #22
    //   8347: bipush #63
    //   8349: iand
    //   8350: iaload
    //   8351: ior
    //   8352: istore #21
    //   8354: iload #21
    //   8356: aload #13
    //   8358: iload #22
    //   8360: bipush #8
    //   8362: iushr
    //   8363: bipush #63
    //   8365: iand
    //   8366: iaload
    //   8367: ior
    //   8368: istore #21
    //   8370: iload #21
    //   8372: aload #11
    //   8374: iload #22
    //   8376: bipush #16
    //   8378: iushr
    //   8379: bipush #63
    //   8381: iand
    //   8382: iaload
    //   8383: ior
    //   8384: istore #21
    //   8386: iload #21
    //   8388: aload #9
    //   8390: iload #22
    //   8392: bipush #24
    //   8394: iushr
    //   8395: bipush #63
    //   8397: iand
    //   8398: iaload
    //   8399: ior
    //   8400: istore #21
    //   8402: iload #23
    //   8404: iload #21
    //   8406: ixor
    //   8407: istore #23
    //   8409: iinc #25, 1
    //   8412: iload_2
    //   8413: ifne -> 8074
    //   8416: iload #23
    //   8418: bipush #31
    //   8420: ishl
    //   8421: iload #23
    //   8423: iconst_1
    //   8424: iushr
    //   8425: ior
    //   8426: istore #23
    //   8428: iload #24
    //   8430: iload #23
    //   8432: ixor
    //   8433: ldc -1431655766
    //   8435: iand
    //   8436: istore #22
    //   8438: iload #24
    //   8440: iload #22
    //   8442: ixor
    //   8443: istore #24
    //   8445: iload #23
    //   8447: iload #22
    //   8449: ixor
    //   8450: istore #23
    //   8452: iload #24
    //   8454: bipush #31
    //   8456: ishl
    //   8457: iload #24
    //   8459: iconst_1
    //   8460: iushr
    //   8461: ior
    //   8462: istore #24
    //   8464: iload #24
    //   8466: bipush #8
    //   8468: iushr
    //   8469: iload #23
    //   8471: ixor
    //   8472: ldc 16711935
    //   8474: iand
    //   8475: istore #22
    //   8477: iload #23
    //   8479: iload #22
    //   8481: ixor
    //   8482: istore #23
    //   8484: iload #24
    //   8486: iload #22
    //   8488: bipush #8
    //   8490: ishl
    //   8491: ixor
    //   8492: istore #24
    //   8494: iload #24
    //   8496: iconst_2
    //   8497: iushr
    //   8498: iload #23
    //   8500: ixor
    //   8501: ldc 858993459
    //   8503: iand
    //   8504: istore #22
    //   8506: iload #23
    //   8508: iload #22
    //   8510: ixor
    //   8511: istore #23
    //   8513: iload #24
    //   8515: iload #22
    //   8517: iconst_2
    //   8518: ishl
    //   8519: ixor
    //   8520: istore #24
    //   8522: iload #23
    //   8524: bipush #16
    //   8526: iushr
    //   8527: iload #24
    //   8529: ixor
    //   8530: ldc 65535
    //   8532: iand
    //   8533: istore #22
    //   8535: iload #24
    //   8537: iload #22
    //   8539: ixor
    //   8540: istore #24
    //   8542: iload #23
    //   8544: iload #22
    //   8546: bipush #16
    //   8548: ishl
    //   8549: ixor
    //   8550: istore #23
    //   8552: iload #23
    //   8554: iconst_4
    //   8555: iushr
    //   8556: iload #24
    //   8558: ixor
    //   8559: ldc 252645135
    //   8561: iand
    //   8562: istore #22
    //   8564: iload #24
    //   8566: iload #22
    //   8568: ixor
    //   8569: istore #24
    //   8571: iload #23
    //   8573: iload #22
    //   8575: iconst_4
    //   8576: ishl
    //   8577: ixor
    //   8578: istore #23
    //   8580: aload #17
    //   8582: iconst_0
    //   8583: iload #23
    //   8585: iastore
    //   8586: aload #17
    //   8588: iconst_1
    //   8589: iload #24
    //   8591: iastore
    //   8592: iload #19
    //   8594: bipush #8
    //   8596: imul
    //   8597: istore #27
    //   8599: iconst_0
    //   8600: istore #28
    //   8602: iload #28
    //   8604: iconst_2
    //   8605: if_icmpge -> 8694
    //   8608: aload #4
    //   8610: iload #27
    //   8612: iload #28
    //   8614: iconst_4
    //   8615: imul
    //   8616: iadd
    //   8617: aload #17
    //   8619: iload #28
    //   8621: iaload
    //   8622: bipush #24
    //   8624: iushr
    //   8625: i2b
    //   8626: bastore
    //   8627: aload #4
    //   8629: iload #27
    //   8631: iload #28
    //   8633: iconst_4
    //   8634: imul
    //   8635: iadd
    //   8636: iconst_1
    //   8637: iadd
    //   8638: aload #17
    //   8640: iload #28
    //   8642: iaload
    //   8643: bipush #16
    //   8645: iushr
    //   8646: i2b
    //   8647: bastore
    //   8648: aload #4
    //   8650: iload #27
    //   8652: iload #28
    //   8654: iconst_4
    //   8655: imul
    //   8656: iadd
    //   8657: iconst_2
    //   8658: iadd
    //   8659: aload #17
    //   8661: iload #28
    //   8663: iaload
    //   8664: bipush #8
    //   8666: iushr
    //   8667: i2b
    //   8668: bastore
    //   8669: aload #4
    //   8671: iload #27
    //   8673: iload #28
    //   8675: iconst_4
    //   8676: imul
    //   8677: iadd
    //   8678: iconst_3
    //   8679: iadd
    //   8680: aload #17
    //   8682: iload #28
    //   8684: iaload
    //   8685: i2b
    //   8686: bastore
    //   8687: iinc #28, 1
    //   8690: iload_2
    //   8691: ifne -> 8602
    //   8694: iinc #19, 1
    //   8697: iload_2
    //   8698: ifne -> 7783
    //   8701: new java/math/BigInteger
    //   8704: dup
    //   8705: aload #4
    //   8707: invokespecial <init> : ([B)V
    //   8710: invokevirtual abs : ()Ljava/math/BigInteger;
    //   8713: putstatic burp/Zle9.ZI : Ljava/lang/Object;
    //   8716: sipush #12092
    //   8719: sipush #24528
    //   8722: invokestatic a : (II)Ljava/lang/String;
    //   8725: iconst_1
    //   8726: ldc burp/Ztjh
    //   8728: invokevirtual getClassLoader : ()Ljava/lang/ClassLoader;
    //   8731: invokestatic forName : (Ljava/lang/String;ZLjava/lang/ClassLoader;)Ljava/lang/Class;
    //   8734: invokevirtual getDeclaredFields : ()[Ljava/lang/reflect/Field;
    //   8737: astore_3
    //   8738: aload_3
    //   8739: arraylength
    //   8740: istore #4
    //   8742: iconst_0
    //   8743: istore #5
    //   8745: iload #5
    //   8747: iload #4
    //   8749: if_icmpge -> 8886
    //   8752: aload_3
    //   8753: iload #5
    //   8755: aaload
    //   8756: astore #6
    //   8758: aload #6
    //   8760: invokevirtual getModifiers : ()I
    //   8763: invokestatic isStatic : (I)Z
    //   8766: ifne -> 8776
    //   8769: goto -> 8879
    //   8772: invokestatic a : (Ljava/lang/Throwable;)Ljava/lang/Throwable;
    //   8775: athrow
    //   8776: aload #6
    //   8778: invokevirtual getType : ()Ljava/lang/Class;
    //   8781: astore #7
    //   8783: aload #7
    //   8785: ifnull -> 8866
    //   8788: aload #7
    //   8790: invokevirtual isPrimitive : ()Z
    //   8793: ifne -> 8866
    //   8796: goto -> 8803
    //   8799: invokestatic a : (Ljava/lang/Throwable;)Ljava/lang/Throwable;
    //   8802: athrow
    //   8803: aload #7
    //   8805: invokevirtual getPackage : ()Ljava/lang/Package;
    //   8808: ifnull -> 8866
    //   8811: goto -> 8818
    //   8814: invokestatic a : (Ljava/lang/Throwable;)Ljava/lang/Throwable;
    //   8817: athrow
    //   8818: aload #7
    //   8820: invokevirtual getPackage : ()Ljava/lang/Package;
    //   8823: invokevirtual getName : ()Ljava/lang/String;
    //   8826: ifnull -> 8866
    //   8829: goto -> 8836
    //   8832: invokestatic a : (Ljava/lang/Throwable;)Ljava/lang/Throwable;
    //   8835: athrow
    //   8836: aload #7
    //   8838: invokevirtual getPackage : ()Ljava/lang/Package;
    //   8841: invokevirtual getName : ()Ljava/lang/String;
    //   8844: sipush #12085
    //   8847: sipush #-10684
    //   8850: invokestatic a : (II)Ljava/lang/String;
    //   8853: invokevirtual startsWith : (Ljava/lang/String;)Z
    //   8856: ifne -> 8866
    //   8859: goto -> 8866
    //   8862: invokestatic a : (Ljava/lang/Throwable;)Ljava/lang/Throwable;
    //   8865: athrow
    //   8866: aload #6
    //   8868: iconst_1
    //   8869: invokevirtual setAccessible : (Z)V
    //   8872: aload #6
    //   8874: aconst_null
    //   8875: invokevirtual get : (Ljava/lang/Object;)Ljava/lang/Object;
    //   8878: pop
    //   8879: iinc #5, 1
    //   8882: iload_2
    //   8883: ifne -> 8745
    //   8886: sipush #12093
    //   8889: sipush #13781
    //   8892: invokestatic a : (II)Ljava/lang/String;
    //   8895: invokestatic forName : (Ljava/lang/String;)Ljava/lang/Class;
    //   8898: invokevirtual getDeclaredMethods : ()[Ljava/lang/reflect/Method;
    //   8901: astore_3
    //   8902: aload_3
    //   8903: arraylength
    //   8904: istore #4
    //   8906: iconst_0
    //   8907: istore #5
    //   8909: iload #5
    //   8911: iload #4
    //   8913: if_icmpge -> 9045
    //   8916: aload_3
    //   8917: iload #5
    //   8919: aaload
    //   8920: astore #6
    //   8922: aload #6
    //   8924: invokevirtual getParameterTypes : ()[Ljava/lang/Class;
    //   8927: pop
    //   8928: aload #6
    //   8930: invokevirtual getModifiers : ()I
    //   8933: invokestatic isStatic : (I)Z
    //   8936: ifeq -> 9031
    //   8939: aload #6
    //   8941: invokevirtual getParameterTypes : ()[Ljava/lang/Class;
    //   8944: arraylength
    //   8945: iconst_2
    //   8946: if_icmpne -> 9031
    //   8949: goto -> 8956
    //   8952: invokestatic a : (Ljava/lang/Throwable;)Ljava/lang/Throwable;
    //   8955: athrow
    //   8956: aload #6
    //   8958: invokevirtual getReturnType : ()Ljava/lang/Class;
    //   8961: getstatic java/lang/Void.TYPE : Ljava/lang/Class;
    //   8964: invokevirtual equals : (Ljava/lang/Object;)Z
    //   8967: ifeq -> 9031
    //   8970: goto -> 8977
    //   8973: invokestatic a : (Ljava/lang/Throwable;)Ljava/lang/Throwable;
    //   8976: athrow
    //   8977: aload #6
    //   8979: iconst_1
    //   8980: invokevirtual setAccessible : (Z)V
    //   8983: aload #6
    //   8985: aconst_null
    //   8986: iconst_2
    //   8987: anewarray java/lang/Object
    //   8990: dup
    //   8991: iconst_0
    //   8992: aload_0
    //   8993: aastore
    //   8994: dup
    //   8995: iconst_1
    //   8996: aload_1
    //   8997: ifnonnull -> 9015
    //   9000: goto -> 9007
    //   9003: invokestatic a : (Ljava/lang/Throwable;)Ljava/lang/Throwable;
    //   9006: athrow
    //   9007: aload_1
    //   9008: goto -> 9022
    //   9011: invokestatic a : (Ljava/lang/Throwable;)Ljava/lang/Throwable;
    //   9014: athrow
    //   9015: aload_1
    //   9016: checkcast [B
    //   9019: invokevirtual clone : ()Ljava/lang/Object;
    //   9022: aastore
    //   9023: invokevirtual invoke : (Ljava/lang/Object;[Ljava/lang/Object;)Ljava/lang/Object;
    //   9026: pop
    //   9027: iload_2
    //   9028: ifne -> 9045
    //   9031: iinc #5, 1
    //   9034: iload_2
    //   9035: ifne -> 8909
    //   9038: goto -> 9045
    //   9041: invokestatic a : (Ljava/lang/Throwable;)Ljava/lang/Throwable;
    //   9044: athrow
    //   9045: new java/io/ByteArrayOutputStream
    //   9048: dup
    //   9049: invokespecial <init> : ()V
    //   9052: astore_3
    //   9053: sipush #12094
    //   9056: aload_3
    //   9057: sipush #202
    //   9060: invokevirtual write : (I)V
    //   9063: sipush #-14604
    //   9066: aload_3
    //   9067: sipush #254
    //   9070: invokevirtual write : (I)V
    //   9073: aload_3
    //   9074: sipush #186
    //   9077: invokevirtual write : (I)V
    //   9080: aload_3
    //   9081: sipush #190
    //   9084: invokevirtual write : (I)V
    //   9087: aload_3
    //   9088: iconst_0
    //   9089: invokevirtual write : (I)V
    //   9092: aload_3
    //   9093: iconst_1
    //   9094: invokevirtual write : (I)V
    //   9097: aload_3
    //   9098: iconst_0
    //   9099: invokevirtual write : (I)V
    //   9102: aload_3
    //   9103: bipush #50
    //   9105: invokevirtual write : (I)V
    //   9108: aload_3
    //   9109: getstatic burp/Zscz.ZN : Ljava/lang/Object;
    //   9112: checkcast java/math/BigInteger
    //   9115: invokevirtual toByteArray : ()[B
    //   9118: invokevirtual write : ([B)V
    //   9121: aload_3
    //   9122: getstatic burp/Ztip.Zc : Ljava/lang/Object;
    //   9125: checkcast java/math/BigInteger
    //   9128: invokevirtual toByteArray : ()[B
    //   9131: invokevirtual write : ([B)V
    //   9134: aload_3
    //   9135: getstatic burp/Zg_5.ZA : Ljava/lang/Object;
    //   9138: checkcast java/math/BigInteger
    //   9141: invokevirtual toByteArray : ()[B
    //   9144: invokevirtual write : ([B)V
    //   9147: aload_3
    //   9148: invokevirtual toByteArray : ()[B
    //   9151: astore #4
    //   9153: aconst_null
    //   9154: astore #5
    //   9156: invokestatic a : (II)Ljava/lang/String;
    //   9159: invokestatic forName : (Ljava/lang/String;)Ljava/lang/Class;
    //   9162: invokevirtual getDeclaredMethods : ()[Ljava/lang/reflect/Method;
    //   9165: astore #6
    //   9167: aload #6
    //   9169: arraylength
    //   9170: istore #7
    //   9172: iconst_0
    //   9173: istore #8
    //   9175: iload #8
    //   9177: iload #7
    //   9179: if_icmpge -> 9307
    //   9182: aload #6
    //   9184: iload #8
    //   9186: aaload
    //   9187: astore #9
    //   9189: aload #9
    //   9191: invokevirtual getName : ()Ljava/lang/String;
    //   9194: sipush #12088
    //   9197: sipush #31210
    //   9200: invokestatic a : (II)Ljava/lang/String;
    //   9203: invokevirtual equals : (Ljava/lang/Object;)Z
    //   9206: ifeq -> 9300
    //   9209: aload #9
    //   9211: invokevirtual getParameterTypes : ()[Ljava/lang/Class;
    //   9214: astore #10
    //   9216: aload #10
    //   9218: arraylength
    //   9219: iconst_4
    //   9220: if_icmpeq -> 9230
    //   9223: goto -> 9300
    //   9226: invokestatic a : (Ljava/lang/Throwable;)Ljava/lang/Throwable;
    //   9229: athrow
    //   9230: aload #10
    //   9232: iconst_0
    //   9233: aaload
    //   9234: ldc java/lang/String
    //   9236: if_acmpeq -> 9246
    //   9239: goto -> 9300
    //   9242: invokestatic a : (Ljava/lang/Throwable;)Ljava/lang/Throwable;
    //   9245: athrow
    //   9246: aload #10
    //   9248: iconst_1
    //   9249: aaload
    //   9250: ldc [B
    //   9252: if_acmpeq -> 9262
    //   9255: goto -> 9300
    //   9258: invokestatic a : (Ljava/lang/Throwable;)Ljava/lang/Throwable;
    //   9261: athrow
    //   9262: aload #10
    //   9264: iconst_2
    //   9265: aaload
    //   9266: getstatic java/lang/Integer.TYPE : Ljava/lang/Class;
    //   9269: if_acmpeq -> 9279
    //   9272: goto -> 9300
    //   9275: invokestatic a : (Ljava/lang/Throwable;)Ljava/lang/Throwable;
    //   9278: athrow
    //   9279: aload #10
    //   9281: iconst_3
    //   9282: aaload
    //   9283: getstatic java/lang/Integer.TYPE : Ljava/lang/Class;
    //   9286: if_acmpeq -> 9296
    //   9289: goto -> 9300
    //   9292: invokestatic a : (Ljava/lang/Throwable;)Ljava/lang/Throwable;
    //   9295: athrow
    //   9296: aload #9
    //   9298: astore #5
    //   9300: iinc #8, 1
    //   9303: iload_2
    //   9304: ifne -> 9175
    //   9307: aload #5
    //   9309: iconst_1
    //   9310: invokevirtual setAccessible : (Z)V
    //   9313: ldc burp/Ztq2
    //   9315: iconst_0
    //   9316: anewarray java/lang/Class
    //   9319: invokevirtual getDeclaredConstructor : ([Ljava/lang/Class;)Ljava/lang/reflect/Constructor;
    //   9322: astore #6
    //   9324: aload #6
    //   9326: iconst_1
    //   9327: invokevirtual setAccessible : (Z)V
    //   9330: aload #5
    //   9332: aload #6
    //   9334: iconst_0
    //   9335: anewarray java/lang/Object
    //   9338: invokevirtual newInstance : ([Ljava/lang/Object;)Ljava/lang/Object;
    //   9341: iconst_4
    //   9342: anewarray java/lang/Object
    //   9345: dup
    //   9346: iconst_0
    //   9347: sipush #12080
    //   9350: sipush #18818
    //   9353: invokestatic a : (II)Ljava/lang/String;
    //   9356: aastore
    //   9357: dup
    //   9358: iconst_1
    //   9359: aload #4
    //   9361: aastore
    //   9362: dup
    //   9363: iconst_2
    //   9364: iconst_0
    //   9365: invokestatic valueOf : (I)Ljava/lang/Integer;
    //   9368: aastore
    //   9369: dup
    //   9370: iconst_3
    //   9371: aload #4
    //   9373: arraylength
    //   9374: invokestatic valueOf : (I)Ljava/lang/Integer;
    //   9377: aastore
    //   9378: invokevirtual invoke : (Ljava/lang/Object;[Ljava/lang/Object;)Ljava/lang/Object;
    //   9381: pop
    //   9382: goto -> 9386
    //   9385: astore_3
    //   9386: getstatic burp/Zb4d.ZS : Ljava/lang/String;
    //   9389: getstatic burp/Zti4.Zi : Ljava/lang/Object;
    //   9392: checkcast java/math/BigInteger
    //   9395: invokevirtual intValue : ()I
    //   9398: bipush #32
    //   9400: irem
    //   9401: invokestatic abs : (I)I
    //   9404: invokevirtual charAt : (I)C
    //   9407: getstatic burp/Zm3x.Zu : Ljava/lang/String;
    //   9410: getstatic burp/Zrwp.Zk : Ljava/lang/Object;
    //   9413: checkcast java/math/BigInteger
    //   9416: invokevirtual intValue : ()I
    //   9419: bipush #32
    //   9421: irem
    //   9422: invokestatic abs : (I)I
    //   9425: invokevirtual charAt : (I)C
    //   9428: if_icmpgt -> 9535
    //   9431: getstatic burp/Zzr8.ZY : Ljava/lang/String;
    //   9434: getstatic burp/Zb0q.ZK : Ljava/lang/Object;
    //   9437: checkcast java/math/BigInteger
    //   9440: invokevirtual intValue : ()I
    //   9443: bipush #32
    //   9445: irem
    //   9446: invokestatic abs : (I)I
    //   9449: invokevirtual charAt : (I)C
    //   9452: getstatic burp/Zvob.Zn : Ljava/lang/String;
    //   9455: getstatic burp/Zld9.ZF : Ljava/lang/Object;
    //   9458: checkcast java/math/BigInteger
    //   9461: invokevirtual intValue : ()I
    //   9464: bipush #32
    //   9466: irem
    //   9467: invokestatic abs : (I)I
    //   9470: invokevirtual charAt : (I)C
    //   9473: if_icmple -> 9535
    //   9476: goto -> 9483
    //   9479: invokestatic a : (Ljava/lang/Throwable;)Ljava/lang/Throwable;
    //   9482: athrow
    //   9483: getstatic burp/Zelt.ZJ : Ljava/lang/String;
    //   9486: getstatic burp/Zxdy.ZZ : Ljava/lang/Object;
    //   9489: checkcast java/math/BigInteger
    //   9492: invokevirtual intValue : ()I
    //   9495: bipush #32
    //   9497: irem
    //   9498: invokestatic abs : (I)I
    //   9501: invokevirtual charAt : (I)C
    //   9504: getstatic burp/Zgpx.Z_ : Ljava/lang/String;
    //   9507: getstatic burp/Zxzv.Zg : Ljava/lang/Object;
    //   9510: checkcast java/math/BigInteger
    //   9513: invokevirtual intValue : ()I
    //   9516: bipush #32
    //   9518: irem
    //   9519: invokestatic abs : (I)I
    //   9522: invokevirtual charAt : (I)C
    //   9525: if_icmple -> 9543
    //   9528: goto -> 9535
    //   9531: invokestatic a : (Ljava/lang/Throwable;)Ljava/lang/Throwable;
    //   9534: athrow
    //   9535: iconst_1
    //   9536: goto -> 9544
    //   9539: invokestatic a : (Ljava/lang/Throwable;)Ljava/lang/Throwable;
    //   9542: athrow
    //   9543: iconst_0
    //   9544: ireturn
    //   9545: astore_3
    //   9546: new java/lang/Exception
    //   9549: dup
    //   9550: aload_3
    //   9551: invokevirtual getMessage : ()Ljava/lang/String;
    //   9554: invokespecial <init> : (Ljava/lang/String;)V
    //   9557: athrow
    // Exception table:
    //   from	to	target	type
    //   4	9544	9545	java/lang/Throwable
    //   3324	3349	3349	java/lang/Throwable
    //   4312	4338	4338	java/lang/Throwable
    //   8758	8772	8772	java/lang/Throwable
    //   8783	8796	8799	java/lang/Throwable
    //   8788	8811	8814	java/lang/Throwable
    //   8803	8829	8832	java/lang/Throwable
    //   8818	8859	8862	java/lang/Throwable
    //   8922	8949	8952	java/lang/Throwable
    //   8939	8970	8973	java/lang/Throwable
    //   8956	9000	9003	java/lang/Throwable
    //   8977	9011	9011	java/lang/Throwable
    //   9022	9038	9041	java/lang/Throwable
    //   9045	9382	9385	java/lang/Throwable
    //   9216	9226	9226	java/lang/Throwable
    //   9230	9242	9242	java/lang/Throwable
    //   9246	9258	9258	java/lang/Throwable
    //   9262	9275	9275	java/lang/Throwable
    //   9279	9292	9292	java/lang/Throwable
    //   9386	9476	9479	java/lang/Throwable
    //   9431	9528	9531	java/lang/Throwable
    //   9483	9539	9539	java/lang/Throwable
  }
  
  static {
    // Byte code:
    //   0: bipush #13
    //   2: anewarray java/lang/String
    //   5: astore #5
    //   7: iconst_0
    //   8: istore_3
    //   9: ldc '$It\\t+ xmW@Aw<>K7ul'X, yo5-!%]lv0K`yAG]\\tn\\tC"4rXz)b`bSO4bU\\t+Si1 !&pyNxJ oYLkM{}M6<_L IM3FG)L);HNF\6GEXa6{GC>m'
    //   11: dup
    //   12: astore_2
    //   13: invokevirtual length : ()I
    //   16: istore #4
    //   18: bipush #9
    //   20: istore_1
    //   21: iconst_m1
    //   22: istore_0
    //   23: bipush #47
    //   25: iinc #0, 1
    //   28: aload_2
    //   29: iload_0
    //   30: dup
    //   31: iload_1
    //   32: iadd
    //   33: invokevirtual substring : (II)Ljava/lang/String;
    //   36: iconst_m1
    //   37: goto -> 143
    //   40: aload #5
    //   42: swap
    //   43: iload_3
    //   44: iinc #3, 1
    //   47: swap
    //   48: aastore
    //   49: iload_0
    //   50: iload_1
    //   51: iadd
    //   52: dup
    //   53: istore_0
    //   54: iload #4
    //   56: if_icmpge -> 68
    //   59: aload_2
    //   60: iload_0
    //   61: invokevirtual charAt : (I)C
    //   64: istore_1
    //   65: goto -> 23
    //   68: ldc 'Ij&$+\\bdI'
    //   70: dup
    //   71: astore_2
    //   72: invokevirtual length : ()I
    //   75: istore #4
    //   77: bipush #19
    //   79: istore_1
    //   80: iconst_m1
    //   81: istore_0
    //   82: bipush #89
    //   84: iinc #0, 1
    //   87: aload_2
    //   88: iload_0
    //   89: dup
    //   90: iload_1
    //   91: iadd
    //   92: invokevirtual substring : (II)Ljava/lang/String;
    //   95: iconst_0
    //   96: goto -> 143
    //   99: aload #5
    //   101: swap
    //   102: iload_3
    //   103: iinc #3, 1
    //   106: swap
    //   107: aastore
    //   108: iload_0
    //   109: iload_1
    //   110: iadd
    //   111: dup
    //   112: istore_0
    //   113: iload #4
    //   115: if_icmpge -> 127
    //   118: aload_2
    //   119: iload_0
    //   120: invokevirtual charAt : (I)C
    //   123: istore_1
    //   124: goto -> 82
    //   127: aload #5
    //   129: putstatic burp/Zbnk.a : [Ljava/lang/String;
    //   132: bipush #13
    //   134: anewarray java/lang/String
    //   137: putstatic burp/Zbnk.b : [Ljava/lang/String;
    //   140: goto -> 300
    //   143: dup_x2
    //   144: pop
    //   145: invokevirtual toCharArray : ()[C
    //   148: dup_x1
    //   149: arraylength
    //   150: dup_x2
    //   151: pop
    //   152: iconst_0
    //   153: istore #6
    //   155: dup2_x1
    //   156: pop2
    //   157: dup_x2
    //   158: iconst_1
    //   159: if_icmpgt -> 259
    //   162: dup2
    //   163: swap
    //   164: iload #6
    //   166: dup2_x1
    //   167: caload
    //   168: swap
    //   169: iload #6
    //   171: bipush #7
    //   173: irem
    //   174: tableswitch default -> 241, 0 -> 212, 1 -> 216, 2 -> 221, 3 -> 226, 4 -> 231, 5 -> 236
    //   212: iconst_1
    //   213: goto -> 243
    //   216: bipush #13
    //   218: goto -> 243
    //   221: bipush #17
    //   223: goto -> 243
    //   226: bipush #26
    //   228: goto -> 243
    //   231: bipush #55
    //   233: goto -> 243
    //   236: bipush #51
    //   238: goto -> 243
    //   241: bipush #33
    //   243: ixor
    //   244: ixor
    //   245: i2c
    //   246: castore
    //   247: iinc #6, 1
    //   250: dup
    //   251: ifne -> 259
    //   254: dup2
    //   255: dup_x1
    //   256: goto -> 166
    //   259: dup2_x1
    //   260: pop2
    //   261: dup_x2
    //   262: iload #6
    //   264: if_icmpgt -> 162
    //   267: pop
    //   268: new java/lang/String
    //   271: dup_x1
    //   272: swap
    //   273: invokespecial <init> : ([C)V
    //   276: invokevirtual intern : ()Ljava/lang/String;
    //   279: swap
    //   280: pop
    //   281: swap
    //   282: tableswitch default -> 40, 0 -> 99
    //   300: sipush #12095
    //   303: sipush #-6844
    //   306: invokestatic a : (II)Ljava/lang/String;
    //   309: putstatic burp/Zbnk.Zg : Ljava/lang/String;
    //   312: new java/math/BigInteger
    //   315: dup
    //   316: iconst_1
    //   317: bipush #31
    //   319: newarray byte
    //   321: dup
    //   322: iconst_0
    //   323: iconst_4
    //   324: bastore
    //   325: dup
    //   326: iconst_1
    //   327: bipush #-44
    //   329: bastore
    //   330: dup
    //   331: iconst_2
    //   332: bipush #-5
    //   334: bastore
    //   335: dup
    //   336: iconst_3
    //   337: bipush #98
    //   339: bastore
    //   340: dup
    //   341: iconst_4
    //   342: bipush #66
    //   344: bastore
    //   345: dup
    //   346: iconst_5
    //   347: bipush #-42
    //   349: bastore
    //   350: dup
    //   351: bipush #6
    //   353: bipush #-63
    //   355: bastore
    //   356: dup
    //   357: bipush #7
    //   359: bipush #7
    //   361: bastore
    //   362: dup
    //   363: bipush #8
    //   365: bipush #-45
    //   367: bastore
    //   368: dup
    //   369: bipush #9
    //   371: bipush #109
    //   373: bastore
    //   374: dup
    //   375: bipush #10
    //   377: bipush #-19
    //   379: bastore
    //   380: dup
    //   381: bipush #11
    //   383: bipush #65
    //   385: bastore
    //   386: dup
    //   387: bipush #12
    //   389: bipush #76
    //   391: bastore
    //   392: dup
    //   393: bipush #13
    //   395: bipush #-64
    //   397: bastore
    //   398: dup
    //   399: bipush #14
    //   401: bipush #64
    //   403: bastore
    //   404: dup
    //   405: bipush #15
    //   407: bipush #-21
    //   409: bastore
    //   410: dup
    //   411: bipush #16
    //   413: bipush #-46
    //   415: bastore
    //   416: dup
    //   417: bipush #17
    //   419: bipush #91
    //   421: bastore
    //   422: dup
    //   423: bipush #18
    //   425: bipush #89
    //   427: bastore
    //   428: dup
    //   429: bipush #19
    //   431: bipush #69
    //   433: bastore
    //   434: dup
    //   435: bipush #20
    //   437: bipush #18
    //   439: bastore
    //   440: dup
    //   441: bipush #21
    //   443: bipush #-66
    //   445: bastore
    //   446: dup
    //   447: bipush #22
    //   449: bipush #127
    //   451: bastore
    //   452: dup
    //   453: bipush #23
    //   455: bipush #-31
    //   457: bastore
    //   458: dup
    //   459: bipush #24
    //   461: bipush #-73
    //   463: bastore
    //   464: dup
    //   465: bipush #25
    //   467: bipush #39
    //   469: bastore
    //   470: dup
    //   471: bipush #26
    //   473: bipush #-44
    //   475: bastore
    //   476: dup
    //   477: bipush #27
    //   479: bipush #115
    //   481: bastore
    //   482: dup
    //   483: bipush #28
    //   485: bipush #-64
    //   487: bastore
    //   488: dup
    //   489: bipush #29
    //   491: bipush #-67
    //   493: bastore
    //   494: dup
    //   495: bipush #30
    //   497: bipush #94
    //   499: bastore
    //   500: invokespecial <init> : (I[B)V
    //   503: putstatic burp/Zbnk.Zp : Ljava/lang/Object;
    //   506: return
  }
  
  private static Throwable a(Throwable paramThrowable) {
    return paramThrowable;
  }
  
  private static String a(int paramInt1, int paramInt2) {
    int i = (paramInt1 ^ 0x2F3C) & 0xFFFF;
    if (b[i] == null) {
      char[] arrayOfChar = a[i].toCharArray();
      switch (arrayOfChar[0] & 0xFF) {
        case 0:
        
        case 1:
        
        case 2:
        
        case 3:
        
        case 4:
        
        case 5:
        
        case 6:
        
        case 7:
        
        case 8:
        
        case 9:
        
        case 10:
        
        case 11:
        
        case 12:
        
        case 13:
        
        case 14:
        
        case 15:
        
        case 16:
        
        case 17:
        
        case 18:
        
        case 19:
        
        case 20:
        
        case 21:
        
        case 22:
        
        case 23:
        
        case 24:
        
        case 25:
        
        case 26:
        
        case 27:
        
        case 28:
        
        case 29:
        
        case 30:
        
        case 31:
        
        case 32:
        
        case 33:
        
        case 34:
        
        case 35:
        
        case 36:
        
        case 37:
        
        case 38:
        
        case 39:
        
        case 40:
        
        case 41:
        
        case 42:
        
        case 43:
        
        case 44:
        
        case 45:
        
        case 46:
        
        case 47:
        
        case 48:
        
        case 49:
        
        case 50:
        
        case 51:
        
        case 52:
        
        case 53:
        
        case 54:
        
        case 55:
        
        case 56:
        
        case 57:
        
        case 58:
        
        case 59:
        
        case 60:
        
        case 61:
        
        case 62:
        
        case 63:
        
        case 64:
        
        case 65:
        
        case 66:
        
        case 67:
        
        case 68:
        
        case 69:
        
        case 70:
        
        case 71:
        
        case 72:
        
        case 73:
        
        case 74:
        
        case 75:
        
        case 76:
        
        case 77:
        
        case 78:
        
        case 79:
        
        case 80:
        
        case 81:
        
        case 82:
        
        case 83:
        
        case 84:
        
        case 85:
        
        case 86:
        
        case 87:
        
        case 88:
        
        case 89:
        
        case 90:
        
        case 91:
        
        case 92:
        
        case 93:
        
        case 94:
        
        case 95:
        
        case 96:
        
        case 97:
        
        case 98:
        
        case 99:
        
        case 100:
        
        case 101:
        
        case 102:
        
        case 103:
        
        case 104:
        
        case 105:
        
        case 106:
        
        case 107:
        
        case 108:
        
        case 109:
        
        case 110:
        
        case 111:
        
        case 112:
        
        case 113:
        
        case 114:
        
        case 115:
        
        case 116:
        
        case 117:
        
        case 118:
        
        case 119:
        
        case 120:
        
        case 121:
        
        case 122:
        
        case 123:
        
        case 124:
        
        case 125:
        
        case 126:
        
        case 127:
        
        case 128:
        
        case 129:
        
        case 130:
        
        case 131:
        
        case 132:
        
        case 133:
        
        case 134:
        
        case 135:
        
        case 136:
        
        case 137:
        
        case 138:
        
        case 139:
        
        case 140:
        
        case 141:
        
        case 142:
        
        case 143:
        
        case 144:
        
        case 145:
        
        case 146:
        
        case 147:
        
        case 148:
        
        case 149:
        
        case 150:
        
        case 151:
        
        case 152:
        
        case 153:
        
        case 154:
        
        case 155:
        
        case 156:
        
        case 157:
        
        case 158:
        
        case 159:
        
        case 160:
        
        case 161:
        
        case 162:
        
        case 163:
        
        case 164:
        
        case 165:
        
        case 166:
        
        case 167:
        
        case 168:
        
        case 169:
        
        case 170:
        
        case 171:
        
        case 172:
        
        case 173:
        
        case 174:
        
        case 175:
        
        case 176:
        
        case 177:
        
        case 178:
        
        case 179:
        
        case 180:
        
        case 181:
        
        case 182:
        
        case 183:
        
        case 184:
        
        case 185:
        
        case 186:
        
        case 187:
        
        case 188:
        
        case 189:
        
        case 190:
        
        case 191:
        
        case 192:
        
        case 193:
        
        case 194:
        
        case 195:
        
        case 196:
        
        case 197:
        
        case 198:
        
        case 199:
        
        case 200:
        
        case 201:
        
        case 202:
        
        case 203:
        
        case 204:
        
        case 205:
        
        case 206:
        
        case 207:
        
        case 208:
        
        case 209:
        
        case 210:
        
        case 211:
        
        case 212:
        
        case 213:
        
        case 214:
        
        case 215:
        
        case 216:
        
        case 217:
        
        case 218:
        
        case 219:
        
        case 220:
        
        case 221:
        
        case 222:
        
        case 223:
        
        case 224:
        
        case 225:
        
        case 226:
        
        case 227:
        
        case 228:
        
        case 229:
        
        case 230:
        
        case 231:
        
        case 232:
        
        case 233:
        
        case 234:
        
        case 235:
        
        case 236:
        
        case 237:
        
        case 238:
        
        case 239:
        
        case 240:
        
        case 241:
        
        case 242:
        
        case 243:
        
        case 244:
        
        case 245:
        
        case 246:
        
        case 247:
        
        case 248:
        
        case 249:
        
        case 250:
        
        case 251:
        
        case 252:
        
        case 253:
        
        case 254:
        
        default:
          break;
      } 
      byte b1 = 25;
      int j = (paramInt2 & 0xFF) - b1;
      if (j < 0)
        j += 256; 
      int k = ((paramInt2 & 0xFFFF) >>> 8) - b1;
      if (k < 0)
        k += 256; 
      for (byte b2 = 0; b2 < arrayOfChar.length; b2++) {
        int m = b2 % 2;
        if (m == 0) {
          arrayOfChar[b2] = (char)(arrayOfChar[b2] ^ j);
          j = ((j >>> 3 | j << 5) ^ arrayOfChar[b2]) & 0xFF;
        } else {
          arrayOfChar[b2] = (char)(arrayOfChar[b2] ^ k);
          k = ((k >>> 3 | k << 5) ^ arrayOfChar[b2]) & 0xFF;
        } 
      } 
      b[i] = (new String(arrayOfChar)).intern();
    } 
    return b[i];
  }
}


/* Location:              C:\Program Files\BurpSuitePro\burpsuite_pro.jar!\burp\Zbnk.class
 * Java compiler version: 21 (65.0)
 * JD-Core Version:       1.1.3
 */