package burp;

import java.math.BigInteger;

class Zbo2 extends ClassLoader {
  static String Zr;
  
  static Object ZQ;
  
  private static final String[] a;
  
  private static final String[] b;
  
  static boolean Zi(Object[] paramArrayOfObject, Object paramObject) throws Throwable {
    // Byte code:
    //   0: invokestatic ZK : ()Z
    //   3: istore_2
    //   4: getstatic burp/Zlp8.Zu : Ljava/lang/Object;
    //   7: checkcast java/math/BigInteger
    //   10: invokevirtual toByteArray : ()[B
    //   13: astore_3
    //   14: aload_3
    //   15: arraylength
    //   16: iconst_2
    //   17: iadd
    //   18: newarray byte
    //   20: astore #5
    //   22: iconst_0
    //   23: istore #6
    //   25: iload #6
    //   27: aload_3
    //   28: arraylength
    //   29: if_icmpge -> 48
    //   32: aload #5
    //   34: iload #6
    //   36: aload_3
    //   37: iload #6
    //   39: baload
    //   40: bastore
    //   41: iinc #6, 1
    //   44: iload_2
    //   45: ifeq -> 25
    //   48: aload #5
    //   50: arraylength
    //   51: iconst_3
    //   52: idiv
    //   53: iconst_4
    //   54: imul
    //   55: newarray byte
    //   57: astore #4
    //   59: iconst_0
    //   60: istore #6
    //   62: iconst_0
    //   63: istore #7
    //   65: iload #6
    //   67: aload_3
    //   68: arraylength
    //   69: if_icmpge -> 180
    //   72: aload #4
    //   74: iload #7
    //   76: aload #5
    //   78: iload #6
    //   80: baload
    //   81: iconst_2
    //   82: iushr
    //   83: bipush #63
    //   85: iand
    //   86: i2b
    //   87: bastore
    //   88: aload #4
    //   90: iload #7
    //   92: iconst_1
    //   93: iadd
    //   94: aload #5
    //   96: iload #6
    //   98: iconst_1
    //   99: iadd
    //   100: baload
    //   101: iconst_4
    //   102: iushr
    //   103: bipush #15
    //   105: iand
    //   106: aload #5
    //   108: iload #6
    //   110: baload
    //   111: iconst_4
    //   112: ishl
    //   113: bipush #63
    //   115: iand
    //   116: ior
    //   117: i2b
    //   118: bastore
    //   119: aload #4
    //   121: iload #7
    //   123: iconst_2
    //   124: iadd
    //   125: aload #5
    //   127: iload #6
    //   129: iconst_2
    //   130: iadd
    //   131: baload
    //   132: bipush #6
    //   134: iushr
    //   135: iconst_3
    //   136: iand
    //   137: aload #5
    //   139: iload #6
    //   141: iconst_1
    //   142: iadd
    //   143: baload
    //   144: iconst_2
    //   145: ishl
    //   146: bipush #63
    //   148: iand
    //   149: ior
    //   150: i2b
    //   151: bastore
    //   152: aload #4
    //   154: iload #7
    //   156: iconst_3
    //   157: iadd
    //   158: aload #5
    //   160: iload #6
    //   162: iconst_2
    //   163: iadd
    //   164: baload
    //   165: bipush #63
    //   167: iand
    //   168: i2b
    //   169: bastore
    //   170: iinc #6, 3
    //   173: iinc #7, 4
    //   176: iload_2
    //   177: ifeq -> 65
    //   180: iconst_0
    //   181: istore #6
    //   183: iload #6
    //   185: aload #4
    //   187: arraylength
    //   188: if_icmpge -> 372
    //   191: aload #4
    //   193: iload #6
    //   195: baload
    //   196: bipush #26
    //   198: if_icmpge -> 226
    //   201: aload #4
    //   203: iload #6
    //   205: aload #4
    //   207: iload #6
    //   209: baload
    //   210: bipush #65
    //   212: iadd
    //   213: i2b
    //   214: bastore
    //   215: iload_2
    //   216: ifeq -> 365
    //   219: goto -> 226
    //   222: invokestatic a : (Ljava/lang/Throwable;)Ljava/lang/Throwable;
    //   225: athrow
    //   226: aload #4
    //   228: iload #6
    //   230: baload
    //   231: bipush #52
    //   233: if_icmpge -> 271
    //   236: goto -> 243
    //   239: invokestatic a : (Ljava/lang/Throwable;)Ljava/lang/Throwable;
    //   242: athrow
    //   243: aload #4
    //   245: iload #6
    //   247: aload #4
    //   249: iload #6
    //   251: baload
    //   252: bipush #97
    //   254: iadd
    //   255: bipush #26
    //   257: isub
    //   258: i2b
    //   259: bastore
    //   260: iload_2
    //   261: ifeq -> 365
    //   264: goto -> 271
    //   267: invokestatic a : (Ljava/lang/Throwable;)Ljava/lang/Throwable;
    //   270: athrow
    //   271: aload #4
    //   273: iload #6
    //   275: baload
    //   276: bipush #62
    //   278: if_icmpge -> 316
    //   281: goto -> 288
    //   284: invokestatic a : (Ljava/lang/Throwable;)Ljava/lang/Throwable;
    //   287: athrow
    //   288: aload #4
    //   290: iload #6
    //   292: aload #4
    //   294: iload #6
    //   296: baload
    //   297: bipush #48
    //   299: iadd
    //   300: bipush #52
    //   302: isub
    //   303: i2b
    //   304: bastore
    //   305: iload_2
    //   306: ifeq -> 365
    //   309: goto -> 316
    //   312: invokestatic a : (Ljava/lang/Throwable;)Ljava/lang/Throwable;
    //   315: athrow
    //   316: aload #4
    //   318: iload #6
    //   320: baload
    //   321: bipush #63
    //   323: if_icmpge -> 351
    //   326: goto -> 333
    //   329: invokestatic a : (Ljava/lang/Throwable;)Ljava/lang/Throwable;
    //   332: athrow
    //   333: aload #4
    //   335: iload #6
    //   337: bipush #43
    //   339: bastore
    //   340: iload_2
    //   341: ifeq -> 365
    //   344: goto -> 351
    //   347: invokestatic a : (Ljava/lang/Throwable;)Ljava/lang/Throwable;
    //   350: athrow
    //   351: aload #4
    //   353: iload #6
    //   355: bipush #47
    //   357: bastore
    //   358: goto -> 365
    //   361: invokestatic a : (Ljava/lang/Throwable;)Ljava/lang/Throwable;
    //   364: athrow
    //   365: iinc #6, 1
    //   368: iload_2
    //   369: ifeq -> 183
    //   372: aload #4
    //   374: arraylength
    //   375: iconst_1
    //   376: isub
    //   377: istore #6
    //   379: iload #6
    //   381: aload_3
    //   382: arraylength
    //   383: iconst_4
    //   384: imul
    //   385: iconst_3
    //   386: idiv
    //   387: if_icmple -> 404
    //   390: aload #4
    //   392: iload #6
    //   394: bipush #61
    //   396: bastore
    //   397: iinc #6, -1
    //   400: iload_2
    //   401: ifeq -> 379
    //   404: new java/math/BigInteger
    //   407: dup
    //   408: aload #4
    //   410: invokespecial <init> : ([B)V
    //   413: invokevirtual abs : ()Ljava/math/BigInteger;
    //   416: putstatic burp/Ztv8.ZS : Ljava/lang/Object;
    //   419: new java/lang/StringBuilder
    //   422: dup
    //   423: invokespecial <init> : ()V
    //   426: astore_3
    //   427: iconst_0
    //   428: istore #4
    //   430: iload #4
    //   432: bipush #32
    //   434: if_icmpge -> 1767
    //   437: iload #4
    //   439: tableswitch default -> 1760, 0 -> 580, 1 -> 617, 2 -> 654, 3 -> 691, 4 -> 728, 5 -> 765, 6 -> 802, 7 -> 839, 8 -> 876, 9 -> 913, 10 -> 950, 11 -> 987, 12 -> 1024, 13 -> 1061, 14 -> 1098, 15 -> 1135, 16 -> 1172, 17 -> 1209, 18 -> 1246, 19 -> 1283, 20 -> 1320, 21 -> 1357, 22 -> 1394, 23 -> 1431, 24 -> 1468, 25 -> 1505, 26 -> 1542, 27 -> 1579, 28 -> 1616, 29 -> 1653, 30 -> 1690, 31 -> 1727
    //   580: aload_3
    //   581: getstatic burp/Zxd4.Zf : Ljava/lang/String;
    //   584: getstatic burp/Zkgp.Zw : Ljava/lang/Object;
    //   587: checkcast java/math/BigInteger
    //   590: invokevirtual intValue : ()I
    //   593: bipush #32
    //   595: irem
    //   596: invokestatic abs : (I)I
    //   599: invokevirtual charAt : (I)C
    //   602: invokevirtual append : (C)Ljava/lang/StringBuilder;
    //   605: pop
    //   606: iload_2
    //   607: ifeq -> 1760
    //   610: goto -> 617
    //   613: invokestatic a : (Ljava/lang/Throwable;)Ljava/lang/Throwable;
    //   616: athrow
    //   617: aload_3
    //   618: getstatic burp/Zva.Zi : Ljava/lang/String;
    //   621: getstatic burp/Zb2p.ZQ : Ljava/lang/Object;
    //   624: checkcast java/math/BigInteger
    //   627: invokevirtual intValue : ()I
    //   630: bipush #32
    //   632: irem
    //   633: invokestatic abs : (I)I
    //   636: invokevirtual charAt : (I)C
    //   639: invokevirtual append : (C)Ljava/lang/StringBuilder;
    //   642: pop
    //   643: iload_2
    //   644: ifeq -> 1760
    //   647: goto -> 654
    //   650: invokestatic a : (Ljava/lang/Throwable;)Ljava/lang/Throwable;
    //   653: athrow
    //   654: aload_3
    //   655: getstatic burp/Zlp8.ZW : Ljava/lang/String;
    //   658: getstatic burp/Zez0.ZT : Ljava/lang/Object;
    //   661: checkcast java/math/BigInteger
    //   664: invokevirtual intValue : ()I
    //   667: bipush #32
    //   669: irem
    //   670: invokestatic abs : (I)I
    //   673: invokevirtual charAt : (I)C
    //   676: invokevirtual append : (C)Ljava/lang/StringBuilder;
    //   679: pop
    //   680: iload_2
    //   681: ifeq -> 1760
    //   684: goto -> 691
    //   687: invokestatic a : (Ljava/lang/Throwable;)Ljava/lang/Throwable;
    //   690: athrow
    //   691: aload_3
    //   692: getstatic burp/Zmuj.ZG : Ljava/lang/String;
    //   695: getstatic burp/Zgjj.ZW : Ljava/lang/Object;
    //   698: checkcast java/math/BigInteger
    //   701: invokevirtual intValue : ()I
    //   704: bipush #32
    //   706: irem
    //   707: invokestatic abs : (I)I
    //   710: invokevirtual charAt : (I)C
    //   713: invokevirtual append : (C)Ljava/lang/StringBuilder;
    //   716: pop
    //   717: iload_2
    //   718: ifeq -> 1760
    //   721: goto -> 728
    //   724: invokestatic a : (Ljava/lang/Throwable;)Ljava/lang/Throwable;
    //   727: athrow
    //   728: aload_3
    //   729: getstatic burp/Ztv8.ZJ : Ljava/lang/String;
    //   732: getstatic burp/Zb4m.Zp : Ljava/lang/Object;
    //   735: checkcast java/math/BigInteger
    //   738: invokevirtual intValue : ()I
    //   741: bipush #32
    //   743: irem
    //   744: invokestatic abs : (I)I
    //   747: invokevirtual charAt : (I)C
    //   750: invokevirtual append : (C)Ljava/lang/StringBuilder;
    //   753: pop
    //   754: iload_2
    //   755: ifeq -> 1760
    //   758: goto -> 765
    //   761: invokestatic a : (Ljava/lang/Throwable;)Ljava/lang/Throwable;
    //   764: athrow
    //   765: aload_3
    //   766: getstatic burp/Zk88.ZZ : Ljava/lang/String;
    //   769: getstatic burp/Zrka.Zr : Ljava/lang/Object;
    //   772: checkcast java/math/BigInteger
    //   775: invokevirtual intValue : ()I
    //   778: bipush #32
    //   780: irem
    //   781: invokestatic abs : (I)I
    //   784: invokevirtual charAt : (I)C
    //   787: invokevirtual append : (C)Ljava/lang/StringBuilder;
    //   790: pop
    //   791: iload_2
    //   792: ifeq -> 1760
    //   795: goto -> 802
    //   798: invokestatic a : (Ljava/lang/Throwable;)Ljava/lang/Throwable;
    //   801: athrow
    //   802: aload_3
    //   803: getstatic burp/Zxzp.ZH : Ljava/lang/String;
    //   806: getstatic burp/Zmgl.ZI : Ljava/lang/Object;
    //   809: checkcast java/math/BigInteger
    //   812: invokevirtual intValue : ()I
    //   815: bipush #32
    //   817: irem
    //   818: invokestatic abs : (I)I
    //   821: invokevirtual charAt : (I)C
    //   824: invokevirtual append : (C)Ljava/lang/StringBuilder;
    //   827: pop
    //   828: iload_2
    //   829: ifeq -> 1760
    //   832: goto -> 839
    //   835: invokestatic a : (Ljava/lang/Throwable;)Ljava/lang/Throwable;
    //   838: athrow
    //   839: aload_3
    //   840: getstatic burp/Zxt5.ZM : Ljava/lang/String;
    //   843: getstatic burp/Zlp8.Zu : Ljava/lang/Object;
    //   846: checkcast java/math/BigInteger
    //   849: invokevirtual intValue : ()I
    //   852: bipush #32
    //   854: irem
    //   855: invokestatic abs : (I)I
    //   858: invokevirtual charAt : (I)C
    //   861: invokevirtual append : (C)Ljava/lang/StringBuilder;
    //   864: pop
    //   865: iload_2
    //   866: ifeq -> 1760
    //   869: goto -> 876
    //   872: invokestatic a : (Ljava/lang/Throwable;)Ljava/lang/Throwable;
    //   875: athrow
    //   876: aload_3
    //   877: getstatic burp/Zl8i.Zb : Ljava/lang/String;
    //   880: getstatic burp/Zll8.ZE : Ljava/lang/Object;
    //   883: checkcast java/math/BigInteger
    //   886: invokevirtual intValue : ()I
    //   889: bipush #32
    //   891: irem
    //   892: invokestatic abs : (I)I
    //   895: invokevirtual charAt : (I)C
    //   898: invokevirtual append : (C)Ljava/lang/StringBuilder;
    //   901: pop
    //   902: iload_2
    //   903: ifeq -> 1760
    //   906: goto -> 913
    //   909: invokestatic a : (Ljava/lang/Throwable;)Ljava/lang/Throwable;
    //   912: athrow
    //   913: aload_3
    //   914: getstatic burp/Zlp8.ZW : Ljava/lang/String;
    //   917: getstatic burp/Zxt5.ZG : Ljava/lang/Object;
    //   920: checkcast java/math/BigInteger
    //   923: invokevirtual intValue : ()I
    //   926: bipush #32
    //   928: irem
    //   929: invokestatic abs : (I)I
    //   932: invokevirtual charAt : (I)C
    //   935: invokevirtual append : (C)Ljava/lang/StringBuilder;
    //   938: pop
    //   939: iload_2
    //   940: ifeq -> 1760
    //   943: goto -> 950
    //   946: invokestatic a : (Ljava/lang/Throwable;)Ljava/lang/Throwable;
    //   949: athrow
    //   950: aload_3
    //   951: getstatic burp/Zkk2.ZI : Ljava/lang/String;
    //   954: getstatic burp/Zlbt.ZF : Ljava/lang/Object;
    //   957: checkcast java/math/BigInteger
    //   960: invokevirtual intValue : ()I
    //   963: bipush #32
    //   965: irem
    //   966: invokestatic abs : (I)I
    //   969: invokevirtual charAt : (I)C
    //   972: invokevirtual append : (C)Ljava/lang/StringBuilder;
    //   975: pop
    //   976: iload_2
    //   977: ifeq -> 1760
    //   980: goto -> 987
    //   983: invokestatic a : (Ljava/lang/Throwable;)Ljava/lang/Throwable;
    //   986: athrow
    //   987: aload_3
    //   988: getstatic burp/Zlp8.ZW : Ljava/lang/String;
    //   991: getstatic burp/Zzmo.ZI : Ljava/lang/Object;
    //   994: checkcast java/math/BigInteger
    //   997: invokevirtual intValue : ()I
    //   1000: bipush #32
    //   1002: irem
    //   1003: invokestatic abs : (I)I
    //   1006: invokevirtual charAt : (I)C
    //   1009: invokevirtual append : (C)Ljava/lang/StringBuilder;
    //   1012: pop
    //   1013: iload_2
    //   1014: ifeq -> 1760
    //   1017: goto -> 1024
    //   1020: invokestatic a : (Ljava/lang/Throwable;)Ljava/lang/Throwable;
    //   1023: athrow
    //   1024: aload_3
    //   1025: getstatic burp/Zb2p.ZV : Ljava/lang/String;
    //   1028: getstatic burp/Zvos.Zr : Ljava/lang/Object;
    //   1031: checkcast java/math/BigInteger
    //   1034: invokevirtual intValue : ()I
    //   1037: bipush #32
    //   1039: irem
    //   1040: invokestatic abs : (I)I
    //   1043: invokevirtual charAt : (I)C
    //   1046: invokevirtual append : (C)Ljava/lang/StringBuilder;
    //   1049: pop
    //   1050: iload_2
    //   1051: ifeq -> 1760
    //   1054: goto -> 1061
    //   1057: invokestatic a : (Ljava/lang/Throwable;)Ljava/lang/Throwable;
    //   1060: athrow
    //   1061: aload_3
    //   1062: getstatic burp/Zmu6.Zl : Ljava/lang/String;
    //   1065: getstatic burp/Zexn.Zl : Ljava/lang/Object;
    //   1068: checkcast java/math/BigInteger
    //   1071: invokevirtual intValue : ()I
    //   1074: bipush #32
    //   1076: irem
    //   1077: invokestatic abs : (I)I
    //   1080: invokevirtual charAt : (I)C
    //   1083: invokevirtual append : (C)Ljava/lang/StringBuilder;
    //   1086: pop
    //   1087: iload_2
    //   1088: ifeq -> 1760
    //   1091: goto -> 1098
    //   1094: invokestatic a : (Ljava/lang/Throwable;)Ljava/lang/Throwable;
    //   1097: athrow
    //   1098: aload_3
    //   1099: getstatic burp/Zzh1.Zn : Ljava/lang/String;
    //   1102: getstatic burp/Zmuj.ZH : Ljava/lang/Object;
    //   1105: checkcast java/math/BigInteger
    //   1108: invokevirtual intValue : ()I
    //   1111: bipush #32
    //   1113: irem
    //   1114: invokestatic abs : (I)I
    //   1117: invokevirtual charAt : (I)C
    //   1120: invokevirtual append : (C)Ljava/lang/StringBuilder;
    //   1123: pop
    //   1124: iload_2
    //   1125: ifeq -> 1760
    //   1128: goto -> 1135
    //   1131: invokestatic a : (Ljava/lang/Throwable;)Ljava/lang/Throwable;
    //   1134: athrow
    //   1135: aload_3
    //   1136: getstatic burp/Zbj.ZD : Ljava/lang/String;
    //   1139: getstatic burp/Zf.Zh : Ljava/lang/Object;
    //   1142: checkcast java/math/BigInteger
    //   1145: invokevirtual intValue : ()I
    //   1148: bipush #32
    //   1150: irem
    //   1151: invokestatic abs : (I)I
    //   1154: invokevirtual charAt : (I)C
    //   1157: invokevirtual append : (C)Ljava/lang/StringBuilder;
    //   1160: pop
    //   1161: iload_2
    //   1162: ifeq -> 1760
    //   1165: goto -> 1172
    //   1168: invokestatic a : (Ljava/lang/Throwable;)Ljava/lang/Throwable;
    //   1171: athrow
    //   1172: aload_3
    //   1173: getstatic burp/Zrpm.ZG : Ljava/lang/String;
    //   1176: getstatic burp/Zf.Zh : Ljava/lang/Object;
    //   1179: checkcast java/math/BigInteger
    //   1182: invokevirtual intValue : ()I
    //   1185: bipush #32
    //   1187: irem
    //   1188: invokestatic abs : (I)I
    //   1191: invokevirtual charAt : (I)C
    //   1194: invokevirtual append : (C)Ljava/lang/StringBuilder;
    //   1197: pop
    //   1198: iload_2
    //   1199: ifeq -> 1760
    //   1202: goto -> 1209
    //   1205: invokestatic a : (Ljava/lang/Throwable;)Ljava/lang/Throwable;
    //   1208: athrow
    //   1209: aload_3
    //   1210: getstatic burp/Zxd4.Zf : Ljava/lang/String;
    //   1213: getstatic burp/Zgly.ZN : Ljava/lang/Object;
    //   1216: checkcast java/math/BigInteger
    //   1219: invokevirtual intValue : ()I
    //   1222: bipush #32
    //   1224: irem
    //   1225: invokestatic abs : (I)I
    //   1228: invokevirtual charAt : (I)C
    //   1231: invokevirtual append : (C)Ljava/lang/StringBuilder;
    //   1234: pop
    //   1235: iload_2
    //   1236: ifeq -> 1760
    //   1239: goto -> 1246
    //   1242: invokestatic a : (Ljava/lang/Throwable;)Ljava/lang/Throwable;
    //   1245: athrow
    //   1246: aload_3
    //   1247: getstatic burp/Zlp8.ZW : Ljava/lang/String;
    //   1250: getstatic burp/Zxf8.Zz : Ljava/lang/Object;
    //   1253: checkcast java/math/BigInteger
    //   1256: invokevirtual intValue : ()I
    //   1259: bipush #32
    //   1261: irem
    //   1262: invokestatic abs : (I)I
    //   1265: invokevirtual charAt : (I)C
    //   1268: invokevirtual append : (C)Ljava/lang/StringBuilder;
    //   1271: pop
    //   1272: iload_2
    //   1273: ifeq -> 1760
    //   1276: goto -> 1283
    //   1279: invokestatic a : (Ljava/lang/Throwable;)Ljava/lang/Throwable;
    //   1282: athrow
    //   1283: aload_3
    //   1284: getstatic burp/Zsjo.Zu : Ljava/lang/String;
    //   1287: getstatic burp/Zs26.Z_ : Ljava/lang/Object;
    //   1290: checkcast java/math/BigInteger
    //   1293: invokevirtual intValue : ()I
    //   1296: bipush #32
    //   1298: irem
    //   1299: invokestatic abs : (I)I
    //   1302: invokevirtual charAt : (I)C
    //   1305: invokevirtual append : (C)Ljava/lang/StringBuilder;
    //   1308: pop
    //   1309: iload_2
    //   1310: ifeq -> 1760
    //   1313: goto -> 1320
    //   1316: invokestatic a : (Ljava/lang/Throwable;)Ljava/lang/Throwable;
    //   1319: athrow
    //   1320: aload_3
    //   1321: getstatic burp/Zmy4.ZS : Ljava/lang/String;
    //   1324: getstatic burp/Zb6a.Zz : Ljava/lang/Object;
    //   1327: checkcast java/math/BigInteger
    //   1330: invokevirtual intValue : ()I
    //   1333: bipush #32
    //   1335: irem
    //   1336: invokestatic abs : (I)I
    //   1339: invokevirtual charAt : (I)C
    //   1342: invokevirtual append : (C)Ljava/lang/StringBuilder;
    //   1345: pop
    //   1346: iload_2
    //   1347: ifeq -> 1760
    //   1350: goto -> 1357
    //   1353: invokestatic a : (Ljava/lang/Throwable;)Ljava/lang/Throwable;
    //   1356: athrow
    //   1357: aload_3
    //   1358: getstatic burp/Zg68.Zg : Ljava/lang/String;
    //   1361: getstatic burp/Zbo2.ZQ : Ljava/lang/Object;
    //   1364: checkcast java/math/BigInteger
    //   1367: invokevirtual intValue : ()I
    //   1370: bipush #32
    //   1372: irem
    //   1373: invokestatic abs : (I)I
    //   1376: invokevirtual charAt : (I)C
    //   1379: invokevirtual append : (C)Ljava/lang/StringBuilder;
    //   1382: pop
    //   1383: iload_2
    //   1384: ifeq -> 1760
    //   1387: goto -> 1394
    //   1390: invokestatic a : (Ljava/lang/Throwable;)Ljava/lang/Throwable;
    //   1393: athrow
    //   1394: aload_3
    //   1395: getstatic burp/Zk88.ZZ : Ljava/lang/String;
    //   1398: getstatic burp/Zeuz.Zp : Ljava/lang/Object;
    //   1401: checkcast java/math/BigInteger
    //   1404: invokevirtual intValue : ()I
    //   1407: bipush #32
    //   1409: irem
    //   1410: invokestatic abs : (I)I
    //   1413: invokevirtual charAt : (I)C
    //   1416: invokevirtual append : (C)Ljava/lang/StringBuilder;
    //   1419: pop
    //   1420: iload_2
    //   1421: ifeq -> 1760
    //   1424: goto -> 1431
    //   1427: invokestatic a : (Ljava/lang/Throwable;)Ljava/lang/Throwable;
    //   1430: athrow
    //   1431: aload_3
    //   1432: getstatic burp/Ze_0.Zi : Ljava/lang/String;
    //   1435: getstatic burp/Zrka.Zr : Ljava/lang/Object;
    //   1438: checkcast java/math/BigInteger
    //   1441: invokevirtual intValue : ()I
    //   1444: bipush #32
    //   1446: irem
    //   1447: invokestatic abs : (I)I
    //   1450: invokevirtual charAt : (I)C
    //   1453: invokevirtual append : (C)Ljava/lang/StringBuilder;
    //   1456: pop
    //   1457: iload_2
    //   1458: ifeq -> 1760
    //   1461: goto -> 1468
    //   1464: invokestatic a : (Ljava/lang/Throwable;)Ljava/lang/Throwable;
    //   1467: athrow
    //   1468: aload_3
    //   1469: getstatic burp/Zll8.ZZ : Ljava/lang/String;
    //   1472: getstatic burp/Zmze.Zo : Ljava/lang/Object;
    //   1475: checkcast java/math/BigInteger
    //   1478: invokevirtual intValue : ()I
    //   1481: bipush #32
    //   1483: irem
    //   1484: invokestatic abs : (I)I
    //   1487: invokevirtual charAt : (I)C
    //   1490: invokevirtual append : (C)Ljava/lang/StringBuilder;
    //   1493: pop
    //   1494: iload_2
    //   1495: ifeq -> 1760
    //   1498: goto -> 1505
    //   1501: invokestatic a : (Ljava/lang/Throwable;)Ljava/lang/Throwable;
    //   1504: athrow
    //   1505: aload_3
    //   1506: getstatic burp/Zgre.Zj : Ljava/lang/String;
    //   1509: getstatic burp/Zg7w.Zy : Ljava/lang/Object;
    //   1512: checkcast java/math/BigInteger
    //   1515: invokevirtual intValue : ()I
    //   1518: bipush #32
    //   1520: irem
    //   1521: invokestatic abs : (I)I
    //   1524: invokevirtual charAt : (I)C
    //   1527: invokevirtual append : (C)Ljava/lang/StringBuilder;
    //   1530: pop
    //   1531: iload_2
    //   1532: ifeq -> 1760
    //   1535: goto -> 1542
    //   1538: invokestatic a : (Ljava/lang/Throwable;)Ljava/lang/Throwable;
    //   1541: athrow
    //   1542: aload_3
    //   1543: getstatic burp/Zb6a.ZY : Ljava/lang/String;
    //   1546: getstatic burp/Zxo4.ZV : Ljava/lang/Object;
    //   1549: checkcast java/math/BigInteger
    //   1552: invokevirtual intValue : ()I
    //   1555: bipush #32
    //   1557: irem
    //   1558: invokestatic abs : (I)I
    //   1561: invokevirtual charAt : (I)C
    //   1564: invokevirtual append : (C)Ljava/lang/StringBuilder;
    //   1567: pop
    //   1568: iload_2
    //   1569: ifeq -> 1760
    //   1572: goto -> 1579
    //   1575: invokestatic a : (Ljava/lang/Throwable;)Ljava/lang/Throwable;
    //   1578: athrow
    //   1579: aload_3
    //   1580: getstatic burp/Zbqk.ZZ : Ljava/lang/String;
    //   1583: getstatic burp/Zmv9.Zw : Ljava/lang/Object;
    //   1586: checkcast java/math/BigInteger
    //   1589: invokevirtual intValue : ()I
    //   1592: bipush #32
    //   1594: irem
    //   1595: invokestatic abs : (I)I
    //   1598: invokevirtual charAt : (I)C
    //   1601: invokevirtual append : (C)Ljava/lang/StringBuilder;
    //   1604: pop
    //   1605: iload_2
    //   1606: ifeq -> 1760
    //   1609: goto -> 1616
    //   1612: invokestatic a : (Ljava/lang/Throwable;)Ljava/lang/Throwable;
    //   1615: athrow
    //   1616: aload_3
    //   1617: getstatic burp/Zgyc.Zj : Ljava/lang/String;
    //   1620: getstatic burp/Zzri.ZG : Ljava/lang/Object;
    //   1623: checkcast java/math/BigInteger
    //   1626: invokevirtual intValue : ()I
    //   1629: bipush #32
    //   1631: irem
    //   1632: invokestatic abs : (I)I
    //   1635: invokevirtual charAt : (I)C
    //   1638: invokevirtual append : (C)Ljava/lang/StringBuilder;
    //   1641: pop
    //   1642: iload_2
    //   1643: ifeq -> 1760
    //   1646: goto -> 1653
    //   1649: invokestatic a : (Ljava/lang/Throwable;)Ljava/lang/Throwable;
    //   1652: athrow
    //   1653: aload_3
    //   1654: getstatic burp/Zxd4.Zf : Ljava/lang/String;
    //   1657: getstatic burp/Zzh1.Zf : Ljava/lang/Object;
    //   1660: checkcast java/math/BigInteger
    //   1663: invokevirtual intValue : ()I
    //   1666: bipush #32
    //   1668: irem
    //   1669: invokestatic abs : (I)I
    //   1672: invokevirtual charAt : (I)C
    //   1675: invokevirtual append : (C)Ljava/lang/StringBuilder;
    //   1678: pop
    //   1679: iload_2
    //   1680: ifeq -> 1760
    //   1683: goto -> 1690
    //   1686: invokestatic a : (Ljava/lang/Throwable;)Ljava/lang/Throwable;
    //   1689: athrow
    //   1690: aload_3
    //   1691: getstatic burp/Zlbt.ZE : Ljava/lang/String;
    //   1694: getstatic burp/Zt7j.ZH : Ljava/lang/Object;
    //   1697: checkcast java/math/BigInteger
    //   1700: invokevirtual intValue : ()I
    //   1703: bipush #32
    //   1705: irem
    //   1706: invokestatic abs : (I)I
    //   1709: invokevirtual charAt : (I)C
    //   1712: invokevirtual append : (C)Ljava/lang/StringBuilder;
    //   1715: pop
    //   1716: iload_2
    //   1717: ifeq -> 1760
    //   1720: goto -> 1727
    //   1723: invokestatic a : (Ljava/lang/Throwable;)Ljava/lang/Throwable;
    //   1726: athrow
    //   1727: aload_3
    //   1728: getstatic burp/Zrly.ZS : Ljava/lang/String;
    //   1731: getstatic burp/Zkk2.Zq : Ljava/lang/Object;
    //   1734: checkcast java/math/BigInteger
    //   1737: invokevirtual intValue : ()I
    //   1740: bipush #32
    //   1742: irem
    //   1743: invokestatic abs : (I)I
    //   1746: invokevirtual charAt : (I)C
    //   1749: invokevirtual append : (C)Ljava/lang/StringBuilder;
    //   1752: pop
    //   1753: goto -> 1760
    //   1756: invokestatic a : (Ljava/lang/Throwable;)Ljava/lang/Throwable;
    //   1759: athrow
    //   1760: iinc #4, 1
    //   1763: iload_2
    //   1764: ifeq -> 430
    //   1767: aload_3
    //   1768: invokevirtual toString : ()Ljava/lang/String;
    //   1771: putstatic burp/Zkqx.Ze : Ljava/lang/String;
    //   1774: sipush #-18928
    //   1777: sipush #13076
    //   1780: invokestatic a : (II)Ljava/lang/String;
    //   1783: iconst_1
    //   1784: ldc burp/Zsin
    //   1786: invokevirtual getClassLoader : ()Ljava/lang/ClassLoader;
    //   1789: invokestatic forName : (Ljava/lang/String;ZLjava/lang/ClassLoader;)Ljava/lang/Class;
    //   1792: invokevirtual getDeclaredFields : ()[Ljava/lang/reflect/Field;
    //   1795: astore #4
    //   1797: aload #4
    //   1799: arraylength
    //   1800: istore #5
    //   1802: iconst_0
    //   1803: istore #6
    //   1805: iload #6
    //   1807: iload #5
    //   1809: if_icmpge -> 1947
    //   1812: aload #4
    //   1814: iload #6
    //   1816: aaload
    //   1817: astore #7
    //   1819: aload #7
    //   1821: invokevirtual getModifiers : ()I
    //   1824: invokestatic isStatic : (I)Z
    //   1827: ifne -> 1837
    //   1830: goto -> 1940
    //   1833: invokestatic a : (Ljava/lang/Throwable;)Ljava/lang/Throwable;
    //   1836: athrow
    //   1837: aload #7
    //   1839: invokevirtual getType : ()Ljava/lang/Class;
    //   1842: astore #8
    //   1844: aload #8
    //   1846: ifnull -> 1927
    //   1849: aload #8
    //   1851: invokevirtual isPrimitive : ()Z
    //   1854: ifne -> 1927
    //   1857: goto -> 1864
    //   1860: invokestatic a : (Ljava/lang/Throwable;)Ljava/lang/Throwable;
    //   1863: athrow
    //   1864: aload #8
    //   1866: invokevirtual getPackage : ()Ljava/lang/Package;
    //   1869: ifnull -> 1927
    //   1872: goto -> 1879
    //   1875: invokestatic a : (Ljava/lang/Throwable;)Ljava/lang/Throwable;
    //   1878: athrow
    //   1879: aload #8
    //   1881: invokevirtual getPackage : ()Ljava/lang/Package;
    //   1884: invokevirtual getName : ()Ljava/lang/String;
    //   1887: ifnull -> 1927
    //   1890: goto -> 1897
    //   1893: invokestatic a : (Ljava/lang/Throwable;)Ljava/lang/Throwable;
    //   1896: athrow
    //   1897: aload #8
    //   1899: invokevirtual getPackage : ()Ljava/lang/Package;
    //   1902: invokevirtual getName : ()Ljava/lang/String;
    //   1905: sipush #-18925
    //   1908: sipush #-15201
    //   1911: invokestatic a : (II)Ljava/lang/String;
    //   1914: invokevirtual startsWith : (Ljava/lang/String;)Z
    //   1917: ifne -> 1927
    //   1920: goto -> 1927
    //   1923: invokestatic a : (Ljava/lang/Throwable;)Ljava/lang/Throwable;
    //   1926: athrow
    //   1927: aload #7
    //   1929: iconst_1
    //   1930: invokevirtual setAccessible : (Z)V
    //   1933: aload #7
    //   1935: aconst_null
    //   1936: invokevirtual get : (Ljava/lang/Object;)Ljava/lang/Object;
    //   1939: pop
    //   1940: iinc #6, 1
    //   1943: iload_2
    //   1944: ifeq -> 1805
    //   1947: sipush #-18924
    //   1950: sipush #-22911
    //   1953: invokestatic a : (II)Ljava/lang/String;
    //   1956: invokestatic forName : (Ljava/lang/String;)Ljava/lang/Class;
    //   1959: invokevirtual getDeclaredMethods : ()[Ljava/lang/reflect/Method;
    //   1962: astore #4
    //   1964: aload #4
    //   1966: arraylength
    //   1967: istore #5
    //   1969: iconst_0
    //   1970: istore #6
    //   1972: iload #6
    //   1974: iload #5
    //   1976: if_icmpge -> 2109
    //   1979: aload #4
    //   1981: iload #6
    //   1983: aaload
    //   1984: astore #7
    //   1986: aload #7
    //   1988: invokevirtual getParameterTypes : ()[Ljava/lang/Class;
    //   1991: pop
    //   1992: aload #7
    //   1994: invokevirtual getModifiers : ()I
    //   1997: invokestatic isStatic : (I)Z
    //   2000: ifeq -> 2095
    //   2003: aload #7
    //   2005: invokevirtual getParameterTypes : ()[Ljava/lang/Class;
    //   2008: arraylength
    //   2009: iconst_2
    //   2010: if_icmpne -> 2095
    //   2013: goto -> 2020
    //   2016: invokestatic a : (Ljava/lang/Throwable;)Ljava/lang/Throwable;
    //   2019: athrow
    //   2020: aload #7
    //   2022: invokevirtual getReturnType : ()Ljava/lang/Class;
    //   2025: getstatic java/lang/Void.TYPE : Ljava/lang/Class;
    //   2028: invokevirtual equals : (Ljava/lang/Object;)Z
    //   2031: ifeq -> 2095
    //   2034: goto -> 2041
    //   2037: invokestatic a : (Ljava/lang/Throwable;)Ljava/lang/Throwable;
    //   2040: athrow
    //   2041: aload #7
    //   2043: iconst_1
    //   2044: invokevirtual setAccessible : (Z)V
    //   2047: aload #7
    //   2049: aconst_null
    //   2050: iconst_2
    //   2051: anewarray java/lang/Object
    //   2054: dup
    //   2055: iconst_0
    //   2056: aload_0
    //   2057: aastore
    //   2058: dup
    //   2059: iconst_1
    //   2060: aload_1
    //   2061: ifnonnull -> 2079
    //   2064: goto -> 2071
    //   2067: invokestatic a : (Ljava/lang/Throwable;)Ljava/lang/Throwable;
    //   2070: athrow
    //   2071: aload_1
    //   2072: goto -> 2086
    //   2075: invokestatic a : (Ljava/lang/Throwable;)Ljava/lang/Throwable;
    //   2078: athrow
    //   2079: aload_1
    //   2080: checkcast [B
    //   2083: invokevirtual clone : ()Ljava/lang/Object;
    //   2086: aastore
    //   2087: invokevirtual invoke : (Ljava/lang/Object;[Ljava/lang/Object;)Ljava/lang/Object;
    //   2090: pop
    //   2091: iload_2
    //   2092: ifeq -> 2109
    //   2095: iinc #6, 1
    //   2098: iload_2
    //   2099: ifeq -> 1972
    //   2102: goto -> 2109
    //   2105: invokestatic a : (Ljava/lang/Throwable;)Ljava/lang/Throwable;
    //   2108: athrow
    //   2109: getstatic burp/Zkht.Zd : Ljava/lang/String;
    //   2112: getstatic burp/Zvk.ZN : Ljava/lang/Object;
    //   2115: checkcast java/math/BigInteger
    //   2118: invokevirtual intValue : ()I
    //   2121: bipush #32
    //   2123: irem
    //   2124: invokestatic abs : (I)I
    //   2127: invokevirtual charAt : (I)C
    //   2130: getstatic burp/Zf.Zd : Ljava/lang/String;
    //   2133: getstatic burp/Zll8.ZE : Ljava/lang/Object;
    //   2136: checkcast java/math/BigInteger
    //   2139: invokevirtual intValue : ()I
    //   2142: bipush #32
    //   2144: irem
    //   2145: invokestatic abs : (I)I
    //   2148: invokevirtual charAt : (I)C
    //   2151: if_icmple -> 2266
    //   2154: getstatic burp/Zxd4.Zf : Ljava/lang/String;
    //   2157: getstatic burp/Zb6a.Zz : Ljava/lang/Object;
    //   2160: checkcast java/math/BigInteger
    //   2163: invokevirtual intValue : ()I
    //   2166: bipush #32
    //   2168: irem
    //   2169: invokestatic abs : (I)I
    //   2172: invokevirtual charAt : (I)C
    //   2175: getstatic burp/Zml.ZN : Ljava/lang/String;
    //   2178: getstatic burp/Zb2p.ZQ : Ljava/lang/Object;
    //   2181: checkcast java/math/BigInteger
    //   2184: invokevirtual intValue : ()I
    //   2187: bipush #32
    //   2189: irem
    //   2190: invokestatic abs : (I)I
    //   2193: invokevirtual charAt : (I)C
    //   2196: if_icmpgt -> 2266
    //   2199: goto -> 2206
    //   2202: invokestatic a : (Ljava/lang/Throwable;)Ljava/lang/Throwable;
    //   2205: athrow
    //   2206: getstatic burp/Zgrf.ZE : Ljava/lang/String;
    //   2209: getstatic burp/Zmu6.Zb : Ljava/lang/Object;
    //   2212: checkcast java/math/BigInteger
    //   2215: invokevirtual intValue : ()I
    //   2218: bipush #32
    //   2220: irem
    //   2221: invokestatic abs : (I)I
    //   2224: invokevirtual charAt : (I)C
    //   2227: getstatic burp/Zlo4.Zn : Ljava/lang/String;
    //   2230: getstatic burp/Ze57.ZR : Ljava/lang/Object;
    //   2233: checkcast java/math/BigInteger
    //   2236: invokevirtual intValue : ()I
    //   2239: bipush #32
    //   2241: irem
    //   2242: invokestatic abs : (I)I
    //   2245: invokevirtual charAt : (I)C
    //   2248: if_icmple -> 2266
    //   2251: goto -> 2258
    //   2254: invokestatic a : (Ljava/lang/Throwable;)Ljava/lang/Throwable;
    //   2257: athrow
    //   2258: iconst_1
    //   2259: goto -> 2267
    //   2262: invokestatic a : (Ljava/lang/Throwable;)Ljava/lang/Throwable;
    //   2265: athrow
    //   2266: iconst_0
    //   2267: ireturn
    //   2268: astore_3
    //   2269: new java/lang/Exception
    //   2272: dup
    //   2273: aload_3
    //   2274: invokevirtual getMessage : ()Ljava/lang/String;
    //   2277: invokespecial <init> : (Ljava/lang/String;)V
    //   2280: athrow
    // Exception table:
    //   from	to	target	type
    //   4	2267	2268	java/lang/Throwable
    //   191	219	222	java/lang/Throwable
    //   201	236	239	java/lang/Throwable
    //   226	264	267	java/lang/Throwable
    //   243	281	284	java/lang/Throwable
    //   271	309	312	java/lang/Throwable
    //   288	326	329	java/lang/Throwable
    //   316	344	347	java/lang/Throwable
    //   333	358	361	java/lang/Throwable
    //   437	610	613	java/lang/Throwable
    //   580	647	650	java/lang/Throwable
    //   617	684	687	java/lang/Throwable
    //   654	721	724	java/lang/Throwable
    //   691	758	761	java/lang/Throwable
    //   728	795	798	java/lang/Throwable
    //   765	832	835	java/lang/Throwable
    //   802	869	872	java/lang/Throwable
    //   839	906	909	java/lang/Throwable
    //   876	943	946	java/lang/Throwable
    //   913	980	983	java/lang/Throwable
    //   950	1017	1020	java/lang/Throwable
    //   987	1054	1057	java/lang/Throwable
    //   1024	1091	1094	java/lang/Throwable
    //   1061	1128	1131	java/lang/Throwable
    //   1098	1165	1168	java/lang/Throwable
    //   1135	1202	1205	java/lang/Throwable
    //   1172	1239	1242	java/lang/Throwable
    //   1209	1276	1279	java/lang/Throwable
    //   1246	1313	1316	java/lang/Throwable
    //   1283	1350	1353	java/lang/Throwable
    //   1320	1387	1390	java/lang/Throwable
    //   1357	1424	1427	java/lang/Throwable
    //   1394	1461	1464	java/lang/Throwable
    //   1431	1498	1501	java/lang/Throwable
    //   1468	1535	1538	java/lang/Throwable
    //   1505	1572	1575	java/lang/Throwable
    //   1542	1609	1612	java/lang/Throwable
    //   1579	1646	1649	java/lang/Throwable
    //   1616	1683	1686	java/lang/Throwable
    //   1653	1720	1723	java/lang/Throwable
    //   1690	1753	1756	java/lang/Throwable
    //   1819	1833	1833	java/lang/Throwable
    //   1844	1857	1860	java/lang/Throwable
    //   1849	1872	1875	java/lang/Throwable
    //   1864	1890	1893	java/lang/Throwable
    //   1879	1920	1923	java/lang/Throwable
    //   1986	2013	2016	java/lang/Throwable
    //   2003	2034	2037	java/lang/Throwable
    //   2020	2064	2067	java/lang/Throwable
    //   2041	2075	2075	java/lang/Throwable
    //   2086	2102	2105	java/lang/Throwable
    //   2109	2199	2202	java/lang/Throwable
    //   2154	2251	2254	java/lang/Throwable
    //   2206	2262	2262	java/lang/Throwable
  }
  
  static void ZU(Object[] paramArrayOfObject, Object paramObject) throws Throwable {}
  
  static void Zw(Object paramObject) {
    Zva.Zi = a(-18922, 20068);
    Zva.Zu = new BigInteger(a(-18927, 9271));
    boolean bool = Zt2e.ZK();
    try {
      try {
        if (Zle6.Zh.charAt(Math.abs(((BigInteger)Zmha.ZM).intValue() % 32)) > Zzri.ZL.charAt(Math.abs(((BigInteger)Zgja.ZD).intValue() % 32))) {
          try {
            Zl8i.ZV(Class.forName(a(-18921, 32033)));
            if (bool)
              Zscz.Zk(Class.forName(a(-18923, -10038))); 
          } catch (Throwable throwable) {
            throw a(null);
          } 
          return;
        } 
      } catch (Throwable throwable) {
        throw a(null);
      } 
      Zscz.Zk(Class.forName(a(-18923, -10038)));
    } catch (Throwable throwable) {}
  }
  
  static {
    // Byte code:
    //   0: bipush #8
    //   2: anewarray java/lang/String
    //   5: astore #5
    //   7: iconst_0
    //   8: istore_3
    //   9: ldc 'xW<Ã¥Ã¥ÂµÃžÂ¾Â’Â›1_cÃŸÃÂ ÂµÃ•Ã¦#{Â¦Ã‡Ã”Â¶6Â£Ã‹RÂ°Â¾Ã¿ÃšT+Â·Â¢mÃ¸eÃ˜\\nÂ¦m\\fÂŽg^Â£;Â°Ã›Ã†Ã±Â¿b6xÂ®Â \;Â»Ã¨Â­Ã—Â™n\\bÂ€Ã‚NS9Â6}Â‡\\f ÂœÃ€WÂ£Ã”BV?Ã’ÂœÂ„Ã«egzÃªÃ§aY4`Ã¸Ã’6 ,]Â·ÂˆhÃš\\tÃ•Ã£Ã»ÃŸ!Ã°Ã–Â¬^\\b,SÃ„Ã‰Ã†2(Â¡'
    //   11: dup
    //   12: astore_2
    //   13: invokevirtual length : ()I
    //   16: istore #4
    //   18: bipush #77
    //   20: istore_1
    //   21: iconst_m1
    //   22: istore_0
    //   23: bipush #100
    //   25: iinc #0, 1
    //   28: aload_2
    //   29: iload_0
    //   30: dup
    //   31: iload_1
    //   32: iadd
    //   33: invokevirtual substring : (II)Ljava/lang/String;
    //   36: iconst_m1
    //   37: goto -> 143
    //   40: aload #5
    //   42: swap
    //   43: iload_3
    //   44: iinc #3, 1
    //   47: swap
    //   48: aastore
    //   49: iload_0
    //   50: iload_1
    //   51: iadd
    //   52: dup
    //   53: istore_0
    //   54: iload #4
    //   56: if_icmpge -> 68
    //   59: aload_2
    //   60: iload_0
    //   61: invokevirtual charAt : (I)C
    //   64: istore_1
    //   65: goto -> 23
    //   68: ldc 'ÃˆHÂ¢PÃ°Ã»\\t1Â¬ ÂœÂ•[4Ã’nÃÃ¢Â”1{ÃŒ>NÃ‰H3Ã“Â”ÂœÃ¸Â–ÃŽÂ¡RÂ†Â•Ã¾Ã˜ÃÂ¡'
    //   70: dup
    //   71: astore_2
    //   72: invokevirtual length : ()I
    //   75: istore #4
    //   77: bipush #9
    //   79: istore_1
    //   80: iconst_m1
    //   81: istore_0
    //   82: bipush #16
    //   84: iinc #0, 1
    //   87: aload_2
    //   88: iload_0
    //   89: dup
    //   90: iload_1
    //   91: iadd
    //   92: invokevirtual substring : (II)Ljava/lang/String;
    //   95: iconst_0
    //   96: goto -> 143
    //   99: aload #5
    //   101: swap
    //   102: iload_3
    //   103: iinc #3, 1
    //   106: swap
    //   107: aastore
    //   108: iload_0
    //   109: iload_1
    //   110: iadd
    //   111: dup
    //   112: istore_0
    //   113: iload #4
    //   115: if_icmpge -> 127
    //   118: aload_2
    //   119: iload_0
    //   120: invokevirtual charAt : (I)C
    //   123: istore_1
    //   124: goto -> 82
    //   127: aload #5
    //   129: putstatic burp/Zbo2.a : [Ljava/lang/String;
    //   132: bipush #8
    //   134: anewarray java/lang/String
    //   137: putstatic burp/Zbo2.b : [Ljava/lang/String;
    //   140: goto -> 300
    //   143: dup_x2
    //   144: pop
    //   145: invokevirtual toCharArray : ()[C
    //   148: dup_x1
    //   149: arraylength
    //   150: dup_x2
    //   151: pop
    //   152: iconst_0
    //   153: istore #6
    //   155: dup2_x1
    //   156: pop2
    //   157: dup_x2
    //   158: iconst_1
    //   159: if_icmpgt -> 260
    //   162: dup2
    //   163: swap
    //   164: iload #6
    //   166: dup2_x1
    //   167: caload
    //   168: swap
    //   169: iload #6
    //   171: bipush #7
    //   173: irem
    //   174: tableswitch default -> 242, 0 -> 212, 1 -> 217, 2 -> 222, 3 -> 227, 4 -> 232, 5 -> 237
    //   212: bipush #21
    //   214: goto -> 244
    //   217: bipush #38
    //   219: goto -> 244
    //   222: bipush #87
    //   224: goto -> 244
    //   227: bipush #36
    //   229: goto -> 244
    //   232: bipush #78
    //   234: goto -> 244
    //   237: bipush #67
    //   239: goto -> 244
    //   242: bipush #66
    //   244: ixor
    //   245: ixor
    //   246: i2c
    //   247: castore
    //   248: iinc #6, 1
    //   251: dup
    //   252: ifne -> 260
    //   255: dup2
    //   256: dup_x1
    //   257: goto -> 166
    //   260: dup2_x1
    //   261: pop2
    //   262: dup_x2
    //   263: iload #6
    //   265: if_icmpgt -> 162
    //   268: pop
    //   269: new java/lang/String
    //   272: dup_x1
    //   273: swap
    //   274: invokespecial <init> : ([C)V
    //   277: invokevirtual intern : ()Ljava/lang/String;
    //   280: swap
    //   281: pop
    //   282: swap
    //   283: tableswitch default -> 40, 0 -> 99
    //   300: sipush #-18926
    //   303: sipush #-16750
    //   306: invokestatic a : (II)Ljava/lang/String;
    //   309: putstatic burp/Zbo2.Zr : Ljava/lang/String;
    //   312: new java/math/BigInteger
    //   315: dup
    //   316: bipush #32
    //   318: newarray byte
    //   320: dup
    //   321: iconst_0
    //   322: bipush #111
    //   324: bastore
    //   325: dup
    //   326: iconst_1
    //   327: bipush #-39
    //   329: bastore
    //   330: dup
    //   331: iconst_2
    //   332: bipush #95
    //   334: bastore
    //   335: dup
    //   336: iconst_3
    //   337: bipush #122
    //   339: bastore
    //   340: dup
    //   341: iconst_4
    //   342: bipush #-116
    //   344: bastore
    //   345: dup
    //   346: iconst_5
    //   347: bipush #32
    //   349: bastore
    //   350: dup
    //   351: bipush #6
    //   353: bipush #33
    //   355: bastore
    //   356: dup
    //   357: bipush #7
    //   359: bipush #-67
    //   361: bastore
    //   362: dup
    //   363: bipush #8
    //   365: bipush #-114
    //   367: bastore
    //   368: dup
    //   369: bipush #9
    //   371: bipush #75
    //   373: bastore
    //   374: dup
    //   375: bipush #10
    //   377: bipush #41
    //   379: bastore
    //   380: dup
    //   381: bipush #11
    //   383: iconst_0
    //   384: bastore
    //   385: dup
    //   386: bipush #12
    //   388: bipush #69
    //   390: bastore
    //   391: dup
    //   392: bipush #13
    //   394: bipush #-44
    //   396: bastore
    //   397: dup
    //   398: bipush #14
    //   400: bipush #-110
    //   402: bastore
    //   403: dup
    //   404: bipush #15
    //   406: bipush #104
    //   408: bastore
    //   409: dup
    //   410: bipush #16
    //   412: bipush #12
    //   414: bastore
    //   415: dup
    //   416: bipush #17
    //   418: bipush #-123
    //   420: bastore
    //   421: dup
    //   422: bipush #18
    //   424: bipush #-74
    //   426: bastore
    //   427: dup
    //   428: bipush #19
    //   430: bipush #15
    //   432: bastore
    //   433: dup
    //   434: bipush #20
    //   436: bipush #-126
    //   438: bastore
    //   439: dup
    //   440: bipush #21
    //   442: bipush #41
    //   444: bastore
    //   445: dup
    //   446: bipush #22
    //   448: bipush #-71
    //   450: bastore
    //   451: dup
    //   452: bipush #23
    //   454: bipush #-111
    //   456: bastore
    //   457: dup
    //   458: bipush #24
    //   460: bipush #36
    //   462: bastore
    //   463: dup
    //   464: bipush #25
    //   466: iconst_0
    //   467: bastore
    //   468: dup
    //   469: bipush #26
    //   471: bipush #119
    //   473: bastore
    //   474: dup
    //   475: bipush #27
    //   477: bipush #-11
    //   479: bastore
    //   480: dup
    //   481: bipush #28
    //   483: bipush #89
    //   485: bastore
    //   486: dup
    //   487: bipush #29
    //   489: iconst_4
    //   490: bastore
    //   491: dup
    //   492: bipush #30
    //   494: bipush #-25
    //   496: bastore
    //   497: dup
    //   498: bipush #31
    //   500: bipush #-67
    //   502: bastore
    //   503: invokespecial <init> : ([B)V
    //   506: putstatic burp/Zbo2.ZQ : Ljava/lang/Object;
    //   509: return
  }
  
  private static Throwable a(Throwable paramThrowable) {
    return paramThrowable;
  }
  
  private static String a(int paramInt1, int paramInt2) {
    int i = (paramInt1 ^ 0xFFFFB611) & 0xFFFF;
    if (b[i] == null) {
      char[] arrayOfChar = a[i].toCharArray();
      switch (arrayOfChar[0] & 0xFF) {
        case 0:
        
        case 1:
        
        case 2:
        
        case 3:
        
        case 4:
        
        case 5:
        
        case 6:
        
        case 7:
        
        case 8:
        
        case 9:
        
        case 10:
        
        case 11:
        
        case 12:
        
        case 13:
        
        case 14:
        
        case 15:
        
        case 16:
        
        case 17:
        
        case 18:
        
        case 19:
        
        case 20:
        
        case 21:
        
        case 22:
        
        case 23:
        
        case 24:
        
        case 25:
        
        case 26:
        
        case 27:
        
        case 28:
        
        case 29:
        
        case 30:
        
        case 31:
        
        case 32:
        
        case 33:
        
        case 34:
        
        case 35:
        
        case 36:
        
        case 37:
        
        case 38:
        
        case 39:
        
        case 40:
        
        case 41:
        
        case 42:
        
        case 43:
        
        case 44:
        
        case 45:
        
        case 46:
        
        case 47:
        
        case 48:
        
        case 49:
        
        case 50:
        
        case 51:
        
        case 52:
        
        case 53:
        
        case 54:
        
        case 55:
        
        case 56:
        
        case 57:
        
        case 58:
        
        case 59:
        
        case 60:
        
        case 61:
        
        case 62:
        
        case 63:
        
        case 64:
        
        case 65:
        
        case 66:
        
        case 67:
        
        case 68:
        
        case 69:
        
        case 70:
        
        case 71:
        
        case 72:
        
        case 73:
        
        case 74:
        
        case 75:
        
        case 76:
        
        case 77:
        
        case 78:
        
        case 79:
        
        case 80:
        
        case 81:
        
        case 82:
        
        case 83:
        
        case 84:
        
        case 85:
        
        case 86:
        
        case 87:
        
        case 88:
        
        case 89:
        
        case 90:
        
        case 91:
        
        case 92:
        
        case 93:
        
        case 94:
        
        case 95:
        
        case 96:
        
        case 97:
        
        case 98:
        
        case 99:
        
        case 100:
        
        case 101:
        
        case 102:
        
        case 103:
        
        case 104:
        
        case 105:
        
        case 106:
        
        case 107:
        
        case 108:
        
        case 109:
        
        case 110:
        
        case 111:
        
        case 112:
        
        case 113:
        
        case 114:
        
        case 115:
        
        case 116:
        
        case 117:
        
        case 118:
        
        case 119:
        
        case 120:
        
        case 121:
        
        case 122:
        
        case 123:
        
        case 124:
        
        case 125:
        
        case 126:
        
        case 127:
        
        case 128:
        
        case 129:
        
        case 130:
        
        case 131:
        
        case 132:
        
        case 133:
        
        case 134:
        
        case 135:
        
        case 136:
        
        case 137:
        
        case 138:
        
        case 139:
        
        case 140:
        
        case 141:
        
        case 142:
        
        case 143:
        
        case 144:
        
        case 145:
        
        case 146:
        
        case 147:
        
        case 148:
        
        case 149:
        
        case 150:
        
        case 151:
        
        case 152:
        
        case 153:
        
        case 154:
        
        case 155:
        
        case 156:
        
        case 157:
        
        case 158:
        
        case 159:
        
        case 160:
        
        case 161:
        
        case 162:
        
        case 163:
        
        case 164:
        
        case 165:
        
        case 166:
        
        case 167:
        
        case 168:
        
        case 169:
        
        case 170:
        
        case 171:
        
        case 172:
        
        case 173:
        
        case 174:
        
        case 175:
        
        case 176:
        
        case 177:
        
        case 178:
        
        case 179:
        
        case 180:
        
        case 181:
        
        case 182:
        
        case 183:
        
        case 184:
        
        case 185:
        
        case 186:
        
        case 187:
        
        case 188:
        
        case 189:
        
        case 190:
        
        case 191:
        
        case 192:
        
        case 193:
        
        case 194:
        
        case 195:
        
        case 196:
        
        case 197:
        
        case 198:
        
        case 199:
        
        case 200:
        
        case 201:
        
        case 202:
        
        case 203:
        
        case 204:
        
        case 205:
        
        case 206:
        
        case 207:
        
        case 208:
        
        case 209:
        
        case 210:
        
        case 211:
        
        case 212:
        
        case 213:
        
        case 214:
        
        case 215:
        
        case 216:
        
        case 217:
        
        case 218:
        
        case 219:
        
        case 220:
        
        case 221:
        
        case 222:
        
        case 223:
        
        case 224:
        
        case 225:
        
        case 226:
        
        case 227:
        
        case 228:
        
        case 229:
        
        case 230:
        
        case 231:
        
        case 232:
        
        case 233:
        
        case 234:
        
        case 235:
        
        case 236:
        
        case 237:
        
        case 238:
        
        case 239:
        
        case 240:
        
        case 241:
        
        case 242:
        
        case 243:
        
        case 244:
        
        case 245:
        
        case 246:
        
        case 247:
        
        case 248:
        
        case 249:
        
        case 250:
        
        case 251:
        
        case 252:
        
        case 253:
        
        case 254:
        
        default:
          break;
      } 
      byte b1 = 76;
      int j = (paramInt2 & 0xFF) - b1;
      if (j < 0)
        j += 256; 
      int k = ((paramInt2 & 0xFFFF) >>> 8) - b1;
      if (k < 0)
        k += 256; 
      for (byte b2 = 0; b2 < arrayOfChar.length; b2++) {
        int m = b2 % 2;
        if (m == 0) {
          arrayOfChar[b2] = (char)(arrayOfChar[b2] ^ j);
          j = ((j >>> 3 | j << 5) ^ arrayOfChar[b2]) & 0xFF;
        } else {
          arrayOfChar[b2] = (char)(arrayOfChar[b2] ^ k);
          k = ((k >>> 3 | k << 5) ^ arrayOfChar[b2]) & 0xFF;
        } 
      } 
      b[i] = (new String(arrayOfChar)).intern();
    } 
    return b[i];
  }
}


/* Location:              C:\Program Files\BurpSuitePro\burpsuite_pro.jar!\burp\Zbo2.class
 * Java compiler version: 21 (65.0)
 * JD-Core Version:       1.1.3
 */