package burp;

import java.io.File;
import java.io.FileNotFoundException;
import java.io.OutputStream;
import java.nio.file.Path;
import java.nio.file.Paths;
import java.util.ArrayList;
import java.util.HashSet;
import java.util.List;
import java.util.Map;
import java.util.Objects;
import java.util.Set;
import java.util.concurrent.CopyOnWriteArrayList;
import javax.swing.SwingUtilities;
import net.portswigger.Zah;
import net.portswigger.Zk_;
import net.portswigger.Zl0;
import net.portswigger.Zlz;
import net.portswigger.Zrzg;

public class Zbqx implements Zgb6 {
  private static final List<String> Zf;
  
  private final Set<Zz0g> Zs = new HashSet<>();
  
  private final List<Zm3g> ZU = new ArrayList<>();
  
  private final Zm39 Zd;
  
  private final Ztvq ZD;
  
  private final Zrul ZC;
  
  private final Zl0 Zr;
  
  private final List<Zl1c> ZW;
  
  private final Map<Zeew, OutputStream> Zp;
  
  private final Map<Zeew, OutputStream> ZO;
  
  private final Zerg ZE;
  
  private final Zrzg ZM;
  
  private final List<Zo4> Zh;
  
  private final List<Zsmc> Zsa;
  
  private final List<Ztjo> ZA;
  
  private final List<Zern> Zg;
  
  private final List<Zxoz> Zw;
  
  private final Zget ZK;
  
  private Zedo Za;
  
  private boolean ZT;
  
  private String Zv;
  
  private boolean ZsE;
  
  private boolean ZN;
  
  private String ZQ;
  
  private int ZL;
  
  private boolean Z_;
  
  private boolean Zu;
  
  private int ZY;
  
  private String ZsD;
  
  private boolean Ze;
  
  private String Zl;
  
  private boolean ZZ;
  
  private int Zz;
  
  private boolean ZX;
  
  private boolean ZB;
  
  private boolean ZG;
  
  private boolean Zb;
  
  private boolean Zm;
  
  private boolean Zi;
  
  private int ZS;
  
  private Zmfm ZI;
  
  private boolean ZJ;
  
  private String ZP;
  
  private boolean Zk;
  
  private boolean Zn;
  
  private boolean ZsA;
  
  private boolean ZH;
  
  private boolean ZR;
  
  private String Zq;
  
  private boolean ZV;
  
  private boolean Zy;
  
  private boolean Zx;
  
  private Zmsv Zj;
  
  private Zrpp Zo;
  
  private boolean ZF;
  
  private boolean Zt;
  
  private Path Zc;
  
  private static final String[] a;
  
  private static final String[] b;
  
  public Zbqx(Zm39 paramZm39, Zrul paramZrul, Ztvq paramZtvq, Zr5v paramZr5v, Zerg paramZerg, Zl0 paramZl0, Zrzg paramZrzg, Zra1 paramZra1) {
    this.Zd = paramZm39;
    this.ZD = paramZtvq;
    this.ZC = paramZrul;
    this.ZE = paramZerg;
    this.Zr = paramZl0;
    this.ZM = paramZrzg;
    this.ZW = new ArrayList<>();
    this.ZK = new Zget(paramZra1, paramZr5v, paramZm39);
    Zd(paramZr5v);
    this.Zl = "";
    this.ZsD = "";
    this.ZQ = "";
    this.Zv = "";
    this.Zq = "";
    this.Zj = Zmsv.DEFAULT;
    this.Zo = Zrpp.DEFAULT;
    this.Zh = new ArrayList<>();
    this.Zsa = new ArrayList<>();
    this.ZA = new ArrayList<>();
    this.Zp = new Zb13<>();
    this.ZO = new Zb13<>();
    this.Zg = new CopyOnWriteArrayList<>();
    this.Zw = new CopyOnWriteArrayList<>();
    this.Zt = false;
    this.Ze = true;
    if (paramZrzg != null)
      this.Zc = paramZrzg.Zc().toPath().resolve(a(-17105, -27760)).resolve(a(-17011, 2442)); 
  }
  
  public void Zd(Zm3g paramZm3g) {
    this.ZU.add(paramZm3g);
  }
  
  public void Zm(Zmfm paramZmfm) {
    this.ZI = paramZmfm;
  }
  
  public void ZH6(boolean paramBoolean) {
    this.Zd.ZCG(paramBoolean);
  }
  
  public boolean ZfJ() {
    return this.Zd.ZO6();
  }
  
  public void ZH2(boolean paramBoolean) {
    this.Zd.ZCp(paramBoolean);
  }
  
  public boolean Zfj() {
    return this.Zd.Zfc();
  }
  
  public void ZJW(boolean paramBoolean) {
    this.Zd.ZCE(paramBoolean);
  }
  
  public boolean Zcq() {
    return this.Zd.Zf0();
  }
  
  public void ZJU(boolean paramBoolean) {
    this.Zd.ZC3(paramBoolean);
  }
  
  public boolean ZcC() {
    return this.Zd.ZOR();
  }
  
  public void Z_(int paramInt) {
    this.Zd.ZDX(paramInt);
  }
  
  public int ZfT() {
    return this.Zd.ZfW();
  }
  
  public void Zw(int paramInt) {
    this.Zd.ZDB(paramInt);
  }
  
  public int ZEj() {
    return this.Zd.Zf_();
  }
  
  public void Zn(int paramInt) {
    this.Zd.ZDi(paramInt);
  }
  
  public int ZfZ() {
    return this.Zd.ZfA();
  }
  
  public int Zfl() {
    return this.Zd.ZfL();
  }
  
  public void ZB(int paramInt) {
    this.Zd.ZDa(paramInt);
    System.setProperty(a(-16968, 17314), Integer.toString(paramInt / 1000 - 1));
  }
  
  public int Zfv() {
    return this.Zd.Zfa();
  }
  
  public void ZJ(int paramInt) {
    this.Zd.ZD8(paramInt);
    System.setProperty(a(-16941, 8090), Integer.toString(paramInt / 1000 - 1));
  }
  
  public boolean ZfU() {
    return this.ZD.Zp9();
  }
  
  public String Zfp() {
    return this.ZD.Zpk();
  }
  
  public int ZEm() {
    return this.ZD.Zpl();
  }
  
  public String Zf5() {
    return this.ZD.ZpM();
  }
  
  public String ZfL() {
    return this.ZD.Zpp();
  }
  
  public boolean ZfS() {
    return this.ZD.Zpu();
  }
  
  public boolean Zfu() {
    return this.Zd.Zfl();
  }
  
  public void ZHm(boolean paramBoolean) {
    this.Zd.ZCK(paramBoolean);
  }
  
  public boolean Zfa() {
    return this.Zd.ZfN();
  }
  
  public void ZHo(boolean paramBoolean) {
    this.Zd.ZC6(paramBoolean);
  }
  
  public boolean Zf0() {
    return this.Zd.Zfv();
  }
  
  public void ZH3(boolean paramBoolean) {
    this.Zd.ZCe(paramBoolean);
  }
  
  public boolean Zfz() {
    return this.Zd.Zf8();
  }
  
  public void ZH0(boolean paramBoolean) {
    this.Zd.ZCc(paramBoolean);
  }
  
  public boolean Zf3() {
    return this.Zd.ZfV();
  }
  
  public void ZH_(boolean paramBoolean) {
    this.Zd.ZCR(paramBoolean);
  }
  
  public int ZEn() {
    try {
    
    } catch (Zrtn zrtn) {
      throw a(null);
    } 
    try {
    
    } catch (Zrtn zrtn) {
      throw a(null);
    } 
    try {
    
    } catch (Zrtn zrtn) {
      throw a(null);
    } 
    try {
    
    } catch (Zrtn zrtn) {
      throw a(null);
    } 
    try {
    
    } catch (Zrtn zrtn) {
      throw a(null);
    } 
    return (this.Zd.Zfl() ? 1 : 0) | (this.Zd.ZfN() ? 2 : 0) | (this.Zd.Zfv() ? 4 : 0) | (this.Zd.Zf8() ? 8 : 0) | (this.Zd.ZfV() ? 16 : 0);
  }
  
  public boolean Zff() {
    return this.ZT;
  }
  
  public void ZHV(boolean paramBoolean) {
    this.ZT = paramBoolean;
  }
  
  public String Zf1() {
    return this.Zv;
  }
  
  public void ZJ(String paramString) {
    this.Zv = paramString;
  }
  
  public boolean Zqj() {
    return this.Zb;
  }
  
  public void ZHg(boolean paramBoolean) {
    this.Zb = paramBoolean;
  }
  
  public int ZES() {
    return this.ZS;
  }
  
  public void ZL(int paramInt) {
    this.ZS = paramInt;
  }
  
  public boolean Zfi() {
    return this.Zd.ZOr();
  }
  
  public void ZHZ(boolean paramBoolean) {
    this.Zd.ZCT(paramBoolean);
  }
  
  public String Zf4() {
    return this.Zl;
  }
  
  public void Za(String paramString) {
    this.Zl = paramString;
  }
  
  public boolean ZfN() {
    return this.ZsE;
  }
  
  public void ZHf(boolean paramBoolean) {
    this.ZsE = paramBoolean;
    ZKm();
  }
  
  public boolean ZfV() {
    return this.ZN;
  }
  
  public void ZHv(boolean paramBoolean) {
    this.ZN = paramBoolean;
    ZKm();
  }
  
  public String Zf8() {
    return this.ZQ;
  }
  
  public void Zt(String paramString) {
    this.ZQ = paramString;
    ZKm();
  }
  
  public int ZfF() {
    return this.ZL;
  }
  
  public void Zy(int paramInt) {
    this.ZL = paramInt;
    ZKm();
  }
  
  public boolean Zf2() {
    return this.Z_;
  }
  
  public void ZHD(boolean paramBoolean) {
    this.Z_ = paramBoolean;
    ZKm();
  }
  
  public boolean Zfd() {
    return this.Zu;
  }
  
  public void ZHj(boolean paramBoolean) {
    this.Zu = paramBoolean;
  }
  
  public boolean ZfM() {
    return this.Zk;
  }
  
  public void ZHB(boolean paramBoolean) {
    this.Zk = paramBoolean;
  }
  
  public boolean ZfX() {
    return this.Zn;
  }
  
  public void ZHw(boolean paramBoolean) {
    this.Zn = paramBoolean;
  }
  
  public boolean Zf6() {
    return this.ZsA;
  }
  
  public void ZHC(boolean paramBoolean) {
    this.ZsA = paramBoolean;
  }
  
  public boolean ZfD() {
    return this.ZC.ZPy();
  }
  
  public boolean ZEy() {
    return this.ZH;
  }
  
  public void ZHh(boolean paramBoolean) {
    this.ZH = paramBoolean;
  }
  
  public boolean Zf7() {
    return this.ZC.ZPa();
  }
  
  public Ztnt ZfW() {
    return this.ZC.ZP5();
  }
  
  public boolean ZfP() {
    return this.Zd.ZO3();
  }
  
  public void ZH5(boolean paramBoolean) {
    this.Zd.ZC9(paramBoolean);
  }
  
  public boolean ZfA() {
    return this.Zd.Zf1();
  }
  
  public void ZHa(boolean paramBoolean) {
    this.Zd.ZCD(paramBoolean);
  }
  
  public Zbii Zfm() {
    return this.Zd.ZO0();
  }
  
  public void ZA(Zbii paramZbii) {
    try {
      this.Zd.Zr(paramZbii);
      if (paramZbii == Zbii.USE_CUSTOM)
        try {
          if (this.ZI != null)
            this.ZI.Zo(); 
        } catch (Zrtn zrtn) {
          throw a(null);
        }  
    } catch (Zrtn zrtn) {
      throw a(null);
    } 
  }
  
  public boolean ZE2() {
    return this.Zm;
  }
  
  public void ZHU(boolean paramBoolean) {
    this.Zm = paramBoolean;
  }
  
  public boolean ZfG() {
    return this.Zi;
  }
  
  public void ZHs(boolean paramBoolean) {
    this.Zi = paramBoolean;
  }
  
  public boolean ZE1() {
    return this.Zd.ZfP();
  }
  
  public void ZHE(boolean paramBoolean) {
    try {
      this.Zd.ZCW(paramBoolean);
    } catch (Zrtn zrtn) {
      throw a(null);
    } 
    System.setProperty(a(-16939, 24221), paramBoolean ? a(-16938, 16429) : a(-16983, -24182));
  }
  
  public boolean ZfO() {
    return this.Zd.ZO4();
  }
  
  public void ZHu(boolean paramBoolean) {
    this.Zd.ZCs(paramBoolean);
  }
  
  public boolean Zfq() {
    return this.Zd.ZOu();
  }
  
  public void ZHF(boolean paramBoolean) {
    this.Zd.ZCk(paramBoolean);
  }
  
  public int ZfC() {
    return this.ZY;
  }
  
  public void Zk(int paramInt) {
    this.ZY = paramInt;
  }
  
  public String Zf_() {
    return this.ZsD;
  }
  
  public void ZW(String paramString) {
    this.ZsD = paramString;
  }
  
  public boolean Zfg() {
    return this.Ze;
  }
  
  public void ZH8(boolean paramBoolean) {
    this.Ze = paramBoolean;
  }
  
  public boolean ZU3() {
    return this.ZK.ZU3();
  }
  
  public void ZdC(boolean paramBoolean) {
    this.ZK.ZdC(paramBoolean);
  }
  
  public String ZUV() {
    return this.ZK.ZUV();
  }
  
  public void ZY(String paramString) {
    this.ZK.ZY(paramString);
  }
  
  public String ZUT() {
    return this.ZK.ZUT();
  }
  
  public void Zu(String paramString) {
    this.ZK.Zu(paramString);
  }
  
  public int ZUY() {
    return this.ZK.ZUY();
  }
  
  public void Zf(int paramInt) {
    this.ZK.Zf(paramInt);
  }
  
  public boolean ZUv() {
    return this.ZK.ZUv();
  }
  
  public void Zd1(boolean paramBoolean) {
    this.ZK.Zd1(paramBoolean);
  }
  
  public Zes1 ZU0() {
    return this.ZK.ZU0();
  }
  
  public void ZC(Zz0g paramZz0g) {
    synchronized (this.Zs) {
      this.Zs.add(paramZz0g);
    } 
  }
  
  public void Zr(Zz0g paramZz0g) {
    synchronized (this.Zs) {
      this.Zs.remove(paramZz0g);
    } 
  }
  
  public void Z_(Ztsg paramZtsg) {
    this.ZK.Z_(paramZtsg);
  }
  
  public void ZI(Ztsg paramZtsg) {
    this.ZK.ZI(paramZtsg);
  }
  
  public Zefg<Zmg8> Zfh() {
    return this.Zd.Zfg();
  }
  
  public Zefg<Zzp3> Zfx() {
    return this.Zd.ZOz();
  }
  
  public Zefg<Zsdr> ZfB() {
    return this.Zd.ZfY();
  }
  
  public Zefg<Zsdr> ZfR() {
    return this.Zd.Zfo();
  }
  
  public boolean ZfY() {
    return this.ZZ;
  }
  
  public void ZHW(boolean paramBoolean) {
    this.ZZ = paramBoolean;
  }
  
  public int Zfs() {
    return this.Zz;
  }
  
  public void ZW(int paramInt) {
    this.Zz = paramInt;
  }
  
  public boolean ZEv() {
    return this.ZX;
  }
  
  public void ZH7(boolean paramBoolean) {
    this.ZX = paramBoolean;
  }
  
  public boolean ZEl() {
    return this.ZB;
  }
  
  public void ZHT(boolean paramBoolean) {
    this.ZB = paramBoolean;
  }
  
  public boolean Zf9() {
    return this.ZG;
  }
  
  public void ZHn(boolean paramBoolean) {
    this.ZG = paramBoolean;
  }
  
  public Zrs4 Zfo() {
    return Zrs4.ZU();
  }
  
  public boolean ZKR() {
    return this.Zd.ZfS();
  }
  
  public void Zgo(boolean paramBoolean) {
    this.Zd.ZCx(paramBoolean);
  }
  
  public boolean ZK5() {
    return this.Zd.Zfi();
  }
  
  public void Zg2(boolean paramBoolean) {
    this.Zd.ZCm(paramBoolean);
  }
  
  public boolean ZK2() {
    return this.ZR;
  }
  
  public void Zgs(boolean paramBoolean) {
    this.ZR = paramBoolean;
  }
  
  public String ZKz() {
    try {
    
    } catch (Zrtn zrtn) {
      throw a(null);
    } 
    return Zsw8.ZP(this.Zq) ? this.ZM.Zc().toPath().resolve(a(-17102, 20944)).toString() : this.Zq;
  }
  
  public void Zi(String paramString) {
    this.Zq = paramString;
  }
  
  public boolean Zfr() {
    return this.ZV;
  }
  
  public void ZH9(boolean paramBoolean) {
    this.ZV = paramBoolean;
  }
  
  public boolean ZfQ() {
    try {
      if (Zlz.Zu(Zfy()))
        try {
          if (this.ZJ);
        } catch (Zrtn zrtn) {
          throw a(null);
        }  
    } catch (Zrtn zrtn) {
      throw a(null);
    } 
    return false;
  }
  
  public void ZHN(boolean paramBoolean) {
    this.ZJ = paramBoolean;
  }
  
  public void ZM(String paramString) {
    this.ZP = paramString;
  }
  
  public String Zfy() {
    try {
      if (this.ZP != null)
        try {
          if (!this.ZP.isEmpty())
            return this.ZP; 
        } catch (Zrtn zrtn) {
          throw a(null);
        }  
    } catch (Zrtn zrtn) {
      throw a(null);
    } 
    File file = this.ZM.Zc();
    try {
    
    } catch (Zrtn zrtn) {
      throw a(null);
    } 
    return (file == null) ? "" : Paths.get(file.toURI()).resolve(a(-17005, -17419)).toString();
  }
  
  public boolean ZfE() {
    return this.Zy;
  }
  
  public void ZHG(boolean paramBoolean) {
    this.Zy = paramBoolean;
  }
  
  public boolean Zfb() {
    return this.Zx;
  }
  
  public void ZHY(boolean paramBoolean) {
    this.Zx = paramBoolean;
  }
  
  public Zmsv ZEa() {
    return this.Zj;
  }
  
  public void Za(Zmsv paramZmsv) {
    this.Zj = paramZmsv;
    this.Zw.forEach(paramZmsv::lambda$setInspectorDisplayMode$0);
  }
  
  public Zrpp Zfn() {
    return this.Zo;
  }
  
  public void Zi(Zrpp paramZrpp) {
    this.Zo = paramZrpp;
    this.Zg.forEach(paramZrpp::lambda$setInspectorPosition$1);
  }
  
  public void ZD(Zern paramZern) {
    this.Zg.add(paramZern);
  }
  
  public void ZF(Zern paramZern) {
    this.Zg.remove(paramZern);
  }
  
  public void ZS(Zxoz paramZxoz) {
    this.Zw.add(paramZxoz);
  }
  
  public void Zd(Zxoz paramZxoz) {
    this.Zw.remove(paramZxoz);
  }
  
  public List<Zo4> ZfK() {
    return this.Zh;
  }
  
  public void Zt(List<Zo4> paramList) {
    this.Zh.clear();
    Objects.requireNonNull(this.Zh);
    paramList.stream().map(Zo4::ZD).forEach(this.Zh::add);
  }
  
  public List<Zsmc> ZE0() {
    return this.Zsa;
  }
  
  public List<Ztjo> Zfe() {
    return this.ZA;
  }
  
  public void Zj(List<Zsmc> paramList) {
    this.Zsa.clear();
    Objects.requireNonNull(this.Zsa);
    paramList.stream().map(Zsmc::Zf).forEach(this.Zsa::add);
  }
  
  public void Zo(List<Ztjo> paramList) {
    this.ZA.clear();
    Objects.requireNonNull(this.ZA);
    paramList.stream().map(Ztjo::Zf).forEach(this.ZA::add);
  }
  
  public boolean ZKh() {
    return this.Zt;
  }
  
  public void Zgr(boolean paramBoolean) {
    this.Zt = paramBoolean;
  }
  
  public Path ZKU() {
    return this.Zc;
  }
  
  public void Zg(Path paramPath) {
    this.Zc = Objects.<Path>requireNonNull(paramPath);
  }
  
  public List<Zl1c> Zfk() {
    return this.ZW;
  }
  
  public void ZT(Zedo paramZedo) {
    this.Za = paramZedo;
  }
  
  public void Zfw() {
    try {
      if (this.Za != null)
        this.Za.Zt2(); 
    } catch (Zrtn zrtn) {
      throw a(null);
    } 
  }
  
  public boolean Zh(Zeew paramZeew) {
    return this.Zd.Zo(paramZeew);
  }
  
  public void ZS(Zeew paramZeew, boolean paramBoolean) {
    this.Zd.ZJ(paramZeew, paramBoolean);
  }
  
  public OutputStream ZY(Zeew paramZeew) {
    return this.Zp.get(paramZeew);
  }
  
  public OutputStream Zr(Zeew paramZeew) {
    return this.ZO.get(paramZeew);
  }
  
  public void ZM(Zeew paramZeew, String paramString) throws FileNotFoundException {
    try {
      if (Ze(paramZeew)) {
        this.Zd.ZQ(paramZeew, null);
        ZH(paramZeew, paramString, this.Zp);
        this.Zd.ZQ(paramZeew, paramString);
      } 
    } catch (FileNotFoundException fileNotFoundException) {
      throw a(null);
    } 
  }
  
  public void ZU(Zeew paramZeew, String paramString) throws FileNotFoundException {
    try {
      if (Ze(paramZeew)) {
        this.Zd.ZK(paramZeew, null);
        ZH(paramZeew, paramString, this.ZO);
        this.Zd.ZK(paramZeew, paramString);
      } 
    } catch (FileNotFoundException fileNotFoundException) {
      throw a(null);
    } 
  }
  
  public void ZX(String paramString) throws FileNotFoundException {
    ZM(Zeew.SUITE, paramString);
    OutputStream outputStream = ZY(Zeew.SUITE);
    Zeew[] arrayOfZeew = Zeew.values();
    int i = arrayOfZeew.length;
    byte b = 0;
    int[] arrayOfInt = Ze5r.Zj();
    while (b < i) {
      Zeew zeew = arrayOfZeew[b];
      try {
        if (Ze(zeew)) {
          this.Zd.ZQ(zeew, paramString);
          Zk(zeew, outputStream, this.Zp);
        } 
      } catch (FileNotFoundException fileNotFoundException) {
        throw a(null);
      } 
      b++;
      if (arrayOfInt != null)
        break; 
    } 
  }
  
  public void Zn(String paramString) throws FileNotFoundException {
    ZU(Zeew.SUITE, paramString);
    OutputStream outputStream = Zr(Zeew.SUITE);
    Zeew[] arrayOfZeew = Zeew.values();
    int i = arrayOfZeew.length;
    byte b = 0;
    int[] arrayOfInt = Ze5r.Zj();
    while (b < i) {
      Zeew zeew = arrayOfZeew[b];
      try {
        if (Ze(zeew)) {
          this.Zd.ZK(zeew, paramString);
          Zk(zeew, outputStream, this.ZO);
        } 
      } catch (FileNotFoundException fileNotFoundException) {
        throw a(null);
      } 
      b++;
      if (arrayOfInt != null)
        break; 
    } 
  }
  
  public void ZL(Zeew paramZeew) {
    this.Zp.put(paramZeew, this.ZO.get(paramZeew));
    this.Zd.ZQ(paramZeew, this.Zd.Zm(paramZeew));
  }
  
  public void ZT(Zeew paramZeew) {
    this.ZO.put(paramZeew, this.Zp.get(paramZeew));
    this.Zd.ZK(paramZeew, this.Zd.Zi(paramZeew));
  }
  
  public void Zft() {
    String str = this.Zd.Zm(Zeew.SUITE);
    OutputStream outputStream = Zr(Zeew.SUITE);
    this.Zd.ZQ(Zeew.SUITE, str);
    int[] arrayOfInt = Ze5r.Zj();
    Zk(Zeew.SUITE, outputStream, this.Zp);
    Zeew[] arrayOfZeew = Zeew.values();
    int i = arrayOfZeew.length;
    byte b = 0;
    while (b < i) {
      Zeew zeew = arrayOfZeew[b];
      try {
        if (Ze(zeew)) {
          this.Zd.ZQ(zeew, str);
          Zk(zeew, outputStream, this.Zp);
        } 
      } catch (Zrtn zrtn) {
        throw a(null);
      } 
      b++;
      if (arrayOfInt != null)
        break; 
    } 
  }
  
  public void Zfc() {
    String str = this.Zd.Zi(Zeew.SUITE);
    OutputStream outputStream = ZY(Zeew.SUITE);
    this.Zd.ZK(Zeew.SUITE, str);
    Zk(Zeew.SUITE, outputStream, this.ZO);
    Zeew[] arrayOfZeew = Zeew.values();
    int[] arrayOfInt = Ze5r.Zj();
    int i = arrayOfZeew.length;
    byte b = 0;
    while (b < i) {
      Zeew zeew = arrayOfZeew[b];
      try {
        if (Ze(zeew)) {
          this.Zd.ZK(zeew, str);
          Zk(zeew, outputStream, this.ZO);
        } 
      } catch (Zrtn zrtn) {
        throw a(null);
      } 
      b++;
      if (arrayOfInt != null)
        break; 
    } 
  }
  
  public void ZK_() {
    // Byte code:
    //   0: aload_0
    //   1: getfield Zd : Lburp/Zm39;
    //   4: getstatic burp/Zeew.SUITE : Lburp/Zeew;
    //   7: invokeinterface Zi : (Lburp/Zeew;)Ljava/lang/String;
    //   12: astore_2
    //   13: invokestatic Zj : ()[I
    //   16: aload_0
    //   17: getfield Zd : Lburp/Zm39;
    //   20: getstatic burp/Zeew.SUITE : Lburp/Zeew;
    //   23: invokeinterface Zm : (Lburp/Zeew;)Ljava/lang/String;
    //   28: astore_3
    //   29: astore_1
    //   30: aload_2
    //   31: ifnull -> 45
    //   34: aload_3
    //   35: ifnonnull -> 218
    //   38: goto -> 45
    //   41: invokestatic a : (Ljava/lang/Exception;)Ljava/lang/Exception;
    //   44: athrow
    //   45: invokestatic values : ()[Lburp/Zeew;
    //   48: astore #4
    //   50: aload #4
    //   52: arraylength
    //   53: istore #5
    //   55: iconst_0
    //   56: istore #6
    //   58: iload #6
    //   60: iload #5
    //   62: if_icmpge -> 218
    //   65: aload #4
    //   67: iload #6
    //   69: aaload
    //   70: astore #7
    //   72: aload_0
    //   73: aload #7
    //   75: invokevirtual Ze : (Lburp/Zeew;)Z
    //   78: ifeq -> 211
    //   81: aload_0
    //   82: getfield Zd : Lburp/Zm39;
    //   85: aload #7
    //   87: invokeinterface Zi : (Lburp/Zeew;)Ljava/lang/String;
    //   92: astore #8
    //   94: aload_0
    //   95: getfield Zd : Lburp/Zm39;
    //   98: aload #7
    //   100: invokeinterface Zm : (Lburp/Zeew;)Ljava/lang/String;
    //   105: astore #9
    //   107: aload_2
    //   108: ifnonnull -> 136
    //   111: aload_0
    //   112: aload #7
    //   114: aload #8
    //   116: invokevirtual ZM : (Lburp/Zeew;Ljava/lang/String;)V
    //   119: goto -> 136
    //   122: invokestatic a : (Ljava/lang/Exception;)Ljava/lang/Exception;
    //   125: athrow
    //   126: astore #10
    //   128: aload #10
    //   130: getstatic net/portswigger/Zk_.COMMON_RUNTIME_FAILURE : Lnet/portswigger/Zk_;
    //   133: invokestatic Zl : (Ljava/lang/Throwable;Lnet/portswigger/Zk_;)V
    //   136: aload_3
    //   137: ifnonnull -> 211
    //   140: aload #9
    //   142: ifnull -> 186
    //   145: goto -> 152
    //   148: invokestatic a : (Ljava/lang/Exception;)Ljava/lang/Exception;
    //   151: athrow
    //   152: aload #9
    //   154: aload #8
    //   156: invokevirtual equals : (Ljava/lang/Object;)Z
    //   159: ifeq -> 186
    //   162: goto -> 169
    //   165: invokestatic a : (Ljava/lang/Exception;)Ljava/lang/Exception;
    //   168: athrow
    //   169: aload_0
    //   170: aload #7
    //   172: invokevirtual ZT : (Lburp/Zeew;)V
    //   175: aload_1
    //   176: ifnull -> 211
    //   179: goto -> 186
    //   182: invokestatic a : (Ljava/lang/Exception;)Ljava/lang/Exception;
    //   185: athrow
    //   186: aload_0
    //   187: aload #7
    //   189: aload #9
    //   191: invokevirtual ZU : (Lburp/Zeew;Ljava/lang/String;)V
    //   194: goto -> 211
    //   197: invokestatic a : (Ljava/lang/Exception;)Ljava/lang/Exception;
    //   200: athrow
    //   201: astore #10
    //   203: aload #10
    //   205: getstatic net/portswigger/Zk_.COMMON_RUNTIME_FAILURE : Lnet/portswigger/Zk_;
    //   208: invokestatic Zl : (Ljava/lang/Throwable;Lnet/portswigger/Zk_;)V
    //   211: iinc #6, 1
    //   214: aload_1
    //   215: ifnull -> 58
    //   218: aload_2
    //   219: ifnonnull -> 248
    //   222: aload_0
    //   223: getstatic burp/Zeew.SUITE : Lburp/Zeew;
    //   226: aconst_null
    //   227: checkcast java/io/OutputStream
    //   230: aload_0
    //   231: getfield Zp : Ljava/util/Map;
    //   234: invokevirtual Zk : (Lburp/Zeew;Ljava/io/OutputStream;Ljava/util/Map;)V
    //   237: aload_1
    //   238: ifnull -> 270
    //   241: goto -> 248
    //   244: invokestatic a : (Ljava/lang/Exception;)Ljava/lang/Exception;
    //   247: athrow
    //   248: aload_0
    //   249: aload_2
    //   250: invokevirtual ZX : (Ljava/lang/String;)V
    //   253: goto -> 270
    //   256: invokestatic a : (Ljava/lang/Exception;)Ljava/lang/Exception;
    //   259: athrow
    //   260: astore #4
    //   262: aload #4
    //   264: getstatic net/portswigger/Zk_.COMMON_RUNTIME_FAILURE : Lnet/portswigger/Zk_;
    //   267: invokestatic Zl : (Ljava/lang/Throwable;Lnet/portswigger/Zk_;)V
    //   270: aload_3
    //   271: ifnonnull -> 300
    //   274: aload_0
    //   275: getstatic burp/Zeew.SUITE : Lburp/Zeew;
    //   278: aconst_null
    //   279: checkcast java/io/OutputStream
    //   282: aload_0
    //   283: getfield ZO : Ljava/util/Map;
    //   286: invokevirtual Zk : (Lburp/Zeew;Ljava/io/OutputStream;Ljava/util/Map;)V
    //   289: aload_1
    //   290: ifnull -> 352
    //   293: goto -> 300
    //   296: invokestatic a : (Ljava/lang/Exception;)Ljava/lang/Exception;
    //   299: athrow
    //   300: aload_3
    //   301: aload_2
    //   302: invokevirtual equals : (Ljava/lang/Object;)Z
    //   305: ifeq -> 330
    //   308: goto -> 315
    //   311: invokestatic a : (Ljava/lang/Exception;)Ljava/lang/Exception;
    //   314: athrow
    //   315: aload_0
    //   316: invokevirtual Zfc : ()V
    //   319: aload_1
    //   320: ifnull -> 352
    //   323: goto -> 330
    //   326: invokestatic a : (Ljava/lang/Exception;)Ljava/lang/Exception;
    //   329: athrow
    //   330: aload_0
    //   331: aload_3
    //   332: invokevirtual Zn : (Ljava/lang/String;)V
    //   335: goto -> 352
    //   338: invokestatic a : (Ljava/lang/Exception;)Ljava/lang/Exception;
    //   341: athrow
    //   342: astore #4
    //   344: aload #4
    //   346: getstatic net/portswigger/Zk_.COMMON_RUNTIME_FAILURE : Lnet/portswigger/Zk_;
    //   349: invokestatic Zl : (Ljava/lang/Throwable;Lnet/portswigger/Zk_;)V
    //   352: return
    // Exception table:
    //   from	to	target	type
    //   30	38	41	java/io/FileNotFoundException
    //   107	122	122	burp/Zrtn
    //   111	119	126	java/io/FileNotFoundException
    //   136	145	148	java/io/FileNotFoundException
    //   140	162	165	java/io/FileNotFoundException
    //   152	179	182	java/io/FileNotFoundException
    //   169	197	197	burp/Zrtn
    //   186	194	201	java/io/FileNotFoundException
    //   218	241	244	java/io/FileNotFoundException
    //   222	256	256	burp/Zrtn
    //   248	253	260	java/io/FileNotFoundException
    //   270	293	296	java/io/FileNotFoundException
    //   274	308	311	java/io/FileNotFoundException
    //   300	323	326	java/io/FileNotFoundException
    //   315	338	338	burp/Zrtn
    //   330	335	342	java/io/FileNotFoundException
  }
  
  private void ZH(Zeew paramZeew, String paramString, Map<Zeew, OutputStream> paramMap) throws FileNotFoundException {
    try {
    
    } catch (FileNotFoundException fileNotFoundException) {
      throw a(null);
    } 
    OutputStream outputStream = (paramString == null) ? null : this.Zr.Zr(paramString, true);
    Zk(paramZeew, outputStream, paramMap);
  }
  
  private void Zk(Zeew paramZeew, OutputStream paramOutputStream, Map<Zeew, OutputStream> paramMap) {
    ZJ(paramMap.get(paramZeew));
    paramMap.put(paramZeew, paramOutputStream);
  }
  
  private static void ZJ(OutputStream paramOutputStream) {
    try {
      if (paramOutputStream == null)
        return; 
    } catch (Exception exception) {
      throw a(null);
    } 
    try {
      paramOutputStream.flush();
      paramOutputStream.close();
    } catch (Exception exception) {
      Zah.Zl(exception, Zk_.IGNORED);
    } 
  }
  
  private boolean Ze(Zeew paramZeew) {
    try {
      if (paramZeew != Zeew.SUITE) {
        try {
          if (this.ZE != null)
            try {
              if (this.ZE.ZU(paramZeew))
                try {
                  if (paramZeew.supportsLegacyLogging);
                } catch (Zrtn zrtn) {
                  throw a(null);
                }  
            } catch (Zrtn zrtn) {
              throw a(null);
            }  
        } catch (Zrtn zrtn) {
          throw a(null);
        } 
        return false;
      } 
    } catch (Zrtn zrtn) {
      throw a(null);
    } 
  }
  
  private void ZKm() {
    int[] arrayOfInt = Ze5r.Zj();
    synchronized (this.Zs) {
      for (Zz0g zz0g : this.Zs) {
        Objects.requireNonNull(zz0g);
        SwingUtilities.invokeLater(zz0g::Ze);
        if (arrayOfInt != null)
          break; 
      } 
    } 
  }
  
  public void Zd(Zmf_ paramZmf_) {
    // Byte code:
    //   0: aload_0
    //   1: getfield ZK : Lburp/Zget;
    //   4: aload_1
    //   5: invokevirtual Zd : (Lburp/Zmf_;)V
    //   8: invokestatic Zj : ()[I
    //   11: aload_1
    //   12: invokeinterface ZK : ()V
    //   17: astore_2
    //   18: aload_0
    //   19: aload_1
    //   20: sipush #-16945
    //   23: sipush #-15790
    //   26: invokestatic a : (II)Ljava/lang/String;
    //   29: aload_0
    //   30: getfield ZY : I
    //   33: invokeinterface ZA : (Ljava/lang/String;I)I
    //   38: putfield ZY : I
    //   41: aload_0
    //   42: aload_1
    //   43: sipush #-16915
    //   46: sipush #-9317
    //   49: invokestatic a : (II)Ljava/lang/String;
    //   52: aload_0
    //   53: getfield ZsD : Ljava/lang/String;
    //   56: invokeinterface Zn : (Ljava/lang/String;Ljava/lang/String;)Ljava/lang/String;
    //   61: putfield ZsD : Ljava/lang/String;
    //   64: aload_1
    //   65: sipush #-16960
    //   68: sipush #-29022
    //   71: invokestatic a : (II)Ljava/lang/String;
    //   74: aload_0
    //   75: getfield ZQ : Ljava/lang/String;
    //   78: invokeinterface Zn : (Ljava/lang/String;Ljava/lang/String;)Ljava/lang/String;
    //   83: astore_3
    //   84: aload_0
    //   85: invokestatic ZI : ()Lburp/Ztja;
    //   88: ifnull -> 108
    //   91: invokestatic ZI : ()Lburp/Ztja;
    //   94: aload_3
    //   95: invokevirtual Zb : (Ljava/lang/String;)Z
    //   98: ifeq -> 116
    //   101: goto -> 108
    //   104: invokestatic a : (Ljava/lang/Exception;)Ljava/lang/Exception;
    //   107: athrow
    //   108: aload_3
    //   109: goto -> 122
    //   112: invokestatic a : (Ljava/lang/Exception;)Ljava/lang/Exception;
    //   115: athrow
    //   116: invokestatic ZI : ()Lburp/Ztja;
    //   119: getfield Z_ : Ljava/lang/String;
    //   122: putfield ZQ : Ljava/lang/String;
    //   125: aload_0
    //   126: aload_1
    //   127: sipush #-16900
    //   130: sipush #21167
    //   133: invokestatic a : (II)Ljava/lang/String;
    //   136: aload_0
    //   137: getfield ZL : I
    //   140: invokeinterface ZA : (Ljava/lang/String;I)I
    //   145: putfield ZL : I
    //   148: aload_0
    //   149: aload_1
    //   150: sipush #-17093
    //   153: sipush #-9661
    //   156: invokestatic a : (II)Ljava/lang/String;
    //   159: aload_0
    //   160: getfield Z_ : Z
    //   163: invokeinterface ZC : (Ljava/lang/String;Z)Z
    //   168: putfield Z_ : Z
    //   171: aload_0
    //   172: aload_1
    //   173: sipush #-17116
    //   176: sipush #20063
    //   179: invokestatic a : (II)Ljava/lang/String;
    //   182: aload_0
    //   183: getfield Zu : Z
    //   186: invokeinterface ZC : (Ljava/lang/String;Z)Z
    //   191: putfield Zu : Z
    //   194: aload_0
    //   195: aload_1
    //   196: sipush #-17142
    //   199: sipush #-17472
    //   202: invokestatic a : (II)Ljava/lang/String;
    //   205: aload_0
    //   206: getfield ZsE : Z
    //   209: invokeinterface ZC : (Ljava/lang/String;Z)Z
    //   214: putfield ZsE : Z
    //   217: aload_0
    //   218: aload_1
    //   219: sipush #-16952
    //   222: sipush #28165
    //   225: invokestatic a : (II)Ljava/lang/String;
    //   228: aload_0
    //   229: getfield ZN : Z
    //   232: invokeinterface ZC : (Ljava/lang/String;Z)Z
    //   237: putfield ZN : Z
    //   240: aload_0
    //   241: aload_1
    //   242: sipush #-17141
    //   245: sipush #28999
    //   248: invokestatic a : (II)Ljava/lang/String;
    //   251: aload_0
    //   252: getfield ZT : Z
    //   255: invokeinterface ZC : (Ljava/lang/String;Z)Z
    //   260: putfield ZT : Z
    //   263: aload_0
    //   264: aload_1
    //   265: invokevirtual Zj : (Lburp/Zmf_;)V
    //   268: aload_1
    //   269: invokeinterface Zb : ()Z
    //   274: ifeq -> 288
    //   277: aload_0
    //   278: invokevirtual ZKm : ()V
    //   281: goto -> 288
    //   284: invokestatic a : (Ljava/lang/Exception;)Ljava/lang/Exception;
    //   287: athrow
    //   288: aload_0
    //   289: aload_1
    //   290: sipush #-16944
    //   293: sipush #-18425
    //   296: invokestatic a : (II)Ljava/lang/String;
    //   299: aload_0
    //   300: getfield Zl : Ljava/lang/String;
    //   303: invokeinterface Zm : (Ljava/lang/String;Ljava/lang/String;)Ljava/lang/String;
    //   308: putfield Zl : Ljava/lang/String;
    //   311: aload_0
    //   312: aload_1
    //   313: sipush #-17101
    //   316: sipush #29356
    //   319: invokestatic a : (II)Ljava/lang/String;
    //   322: aload_0
    //   323: getfield ZZ : Z
    //   326: invokeinterface ZC : (Ljava/lang/String;Z)Z
    //   331: putfield ZZ : Z
    //   334: aload_0
    //   335: aload_1
    //   336: sipush #-16963
    //   339: sipush #-3235
    //   342: invokestatic a : (II)Ljava/lang/String;
    //   345: aload_0
    //   346: getfield Zz : I
    //   349: invokeinterface ZA : (Ljava/lang/String;I)I
    //   354: putfield Zz : I
    //   357: aload_0
    //   358: aload_1
    //   359: sipush #-16953
    //   362: sipush #22853
    //   365: invokestatic a : (II)Ljava/lang/String;
    //   368: aload_0
    //   369: getfield ZX : Z
    //   372: invokeinterface ZC : (Ljava/lang/String;Z)Z
    //   377: putfield ZX : Z
    //   380: aload_0
    //   381: aload_1
    //   382: sipush #-17115
    //   385: sipush #-25531
    //   388: invokestatic a : (II)Ljava/lang/String;
    //   391: aload_0
    //   392: getfield ZB : Z
    //   395: invokeinterface ZC : (Ljava/lang/String;Z)Z
    //   400: putfield ZB : Z
    //   403: aload_0
    //   404: aload_1
    //   405: sipush #-16970
    //   408: sipush #-18094
    //   411: invokestatic a : (II)Ljava/lang/String;
    //   414: aload_0
    //   415: getfield ZG : Z
    //   418: invokeinterface ZC : (Ljava/lang/String;Z)Z
    //   423: putfield ZG : Z
    //   426: aload_0
    //   427: aload_1
    //   428: sipush #-16903
    //   431: sipush #26321
    //   434: invokestatic a : (II)Ljava/lang/String;
    //   437: getstatic burp/Zbqx.Zf : Ljava/util/List;
    //   440: aload_0
    //   441: getfield ZS : I
    //   444: invokeinterface ZM : (Ljava/lang/String;Ljava/util/List;I)I
    //   449: putfield ZS : I
    //   452: aload_0
    //   453: aload_1
    //   454: sipush #-16959
    //   457: sipush #11533
    //   460: invokestatic a : (II)Ljava/lang/String;
    //   463: aload_0
    //   464: getfield Zb : Z
    //   467: invokeinterface ZC : (Ljava/lang/String;Z)Z
    //   472: putfield Zb : Z
    //   475: aload_0
    //   476: aload_1
    //   477: sipush #-16962
    //   480: sipush #30560
    //   483: invokestatic a : (II)Ljava/lang/String;
    //   486: aload_0
    //   487: getfield Zb : Z
    //   490: invokeinterface ZC : (Ljava/lang/String;Z)Z
    //   495: putfield Zb : Z
    //   498: aload_0
    //   499: aload_1
    //   500: sipush #-16943
    //   503: sipush #-17899
    //   506: invokestatic a : (II)Ljava/lang/String;
    //   509: aload_0
    //   510: getfield ZJ : Z
    //   513: invokeinterface ZC : (Ljava/lang/String;Z)Z
    //   518: putfield ZJ : Z
    //   521: aload_0
    //   522: aload_1
    //   523: sipush #-17010
    //   526: sipush #10332
    //   529: invokestatic a : (II)Ljava/lang/String;
    //   532: aload_0
    //   533: getfield ZP : Ljava/lang/String;
    //   536: invokeinterface Zm : (Ljava/lang/String;Ljava/lang/String;)Ljava/lang/String;
    //   541: putfield ZP : Ljava/lang/String;
    //   544: aload_0
    //   545: aload_1
    //   546: sipush #-17096
    //   549: sipush #-10644
    //   552: invokestatic a : (II)Ljava/lang/String;
    //   555: aload_0
    //   556: getfield Zk : Z
    //   559: invokeinterface ZC : (Ljava/lang/String;Z)Z
    //   564: putfield Zk : Z
    //   567: aload_0
    //   568: aload_1
    //   569: sipush #-17114
    //   572: sipush #7183
    //   575: invokestatic a : (II)Ljava/lang/String;
    //   578: aload_0
    //   579: getfield Zn : Z
    //   582: invokeinterface ZC : (Ljava/lang/String;Z)Z
    //   587: putfield Zn : Z
    //   590: aload_0
    //   591: aload_1
    //   592: sipush #-16913
    //   595: sipush #25710
    //   598: invokestatic a : (II)Ljava/lang/String;
    //   601: aload_0
    //   602: getfield ZsA : Z
    //   605: invokeinterface ZC : (Ljava/lang/String;Z)Z
    //   610: putfield ZsA : Z
    //   613: aload_0
    //   614: aload_1
    //   615: sipush #-16926
    //   618: sipush #-20054
    //   621: invokestatic a : (II)Ljava/lang/String;
    //   624: aload_0
    //   625: getfield ZH : Z
    //   628: invokeinterface ZC : (Ljava/lang/String;Z)Z
    //   633: putfield ZH : Z
    //   636: aload_0
    //   637: aload_1
    //   638: sipush #-17020
    //   641: sipush #-30875
    //   644: invokestatic a : (II)Ljava/lang/String;
    //   647: aload_0
    //   648: getfield ZR : Z
    //   651: invokeinterface ZC : (Ljava/lang/String;Z)Z
    //   656: putfield ZR : Z
    //   659: aload_0
    //   660: aload_1
    //   661: sipush #-16990
    //   664: sipush #4081
    //   667: invokestatic a : (II)Ljava/lang/String;
    //   670: aload_0
    //   671: getfield Zq : Ljava/lang/String;
    //   674: invokeinterface Zm : (Ljava/lang/String;Ljava/lang/String;)Ljava/lang/String;
    //   679: putfield Zq : Ljava/lang/String;
    //   682: aload_0
    //   683: aload_1
    //   684: sipush #-17111
    //   687: sipush #-17935
    //   690: invokestatic a : (II)Ljava/lang/String;
    //   693: aload_0
    //   694: getfield ZV : Z
    //   697: invokeinterface ZC : (Ljava/lang/String;Z)Z
    //   702: putfield ZV : Z
    //   705: aload_0
    //   706: aload_1
    //   707: sipush #-17104
    //   710: sipush #-7169
    //   713: invokestatic a : (II)Ljava/lang/String;
    //   716: aload_0
    //   717: getfield Ze : Z
    //   720: invokeinterface ZC : (Ljava/lang/String;Z)Z
    //   725: putfield Ze : Z
    //   728: aload_0
    //   729: aload_1
    //   730: sipush #-17103
    //   733: sipush #29214
    //   736: invokestatic a : (II)Ljava/lang/String;
    //   739: aload_0
    //   740: getfield Zy : Z
    //   743: invokeinterface ZC : (Ljava/lang/String;Z)Z
    //   748: putfield Zy : Z
    //   751: aload_0
    //   752: aload_1
    //   753: sipush #-17138
    //   756: sipush #8018
    //   759: invokestatic a : (II)Ljava/lang/String;
    //   762: aload_0
    //   763: getfield Zx : Z
    //   766: invokeinterface ZC : (Ljava/lang/String;Z)Z
    //   771: putfield Zx : Z
    //   774: aload_1
    //   775: sipush #-17001
    //   778: sipush #-15973
    //   781: invokestatic a : (II)Ljava/lang/String;
    //   784: <illegal opcode> Zu : ()Lburp/Zsh4;
    //   789: invokeinterface Zs : (Ljava/lang/String;Lburp/Zsh4;)Ljava/util/List;
    //   794: astore #4
    //   796: aload #4
    //   798: ifnull -> 897
    //   801: aload #4
    //   803: invokeinterface stream : ()Ljava/util/stream/Stream;
    //   808: <illegal opcode> test : ()Ljava/util/function/Predicate;
    //   813: invokeinterface filter : (Ljava/util/function/Predicate;)Ljava/util/stream/Stream;
    //   818: invokestatic toList : ()Ljava/util/stream/Collector;
    //   821: invokeinterface collect : (Ljava/util/stream/Collector;)Ljava/lang/Object;
    //   826: checkcast java/util/List
    //   829: astore #4
    //   831: aload #4
    //   833: getstatic burp/Zo4.ZL : Lburp/Zo4;
    //   836: invokeinterface addFirst : (Ljava/lang/Object;)V
    //   841: aload #4
    //   843: invokeinterface size : ()I
    //   848: invokestatic values : ()[Lburp/Zmjk;
    //   851: arraylength
    //   852: if_icmpeq -> 876
    //   855: new burp/Zrtn
    //   858: dup
    //   859: sipush #-16908
    //   862: sipush #-2225
    //   865: invokestatic a : (II)Ljava/lang/String;
    //   868: invokespecial <init> : (Ljava/lang/String;)V
    //   871: athrow
    //   872: invokestatic a : (Ljava/lang/Exception;)Ljava/lang/Exception;
    //   875: athrow
    //   876: aload_0
    //   877: getfield Zh : Ljava/util/List;
    //   880: invokeinterface clear : ()V
    //   885: aload_0
    //   886: getfield Zh : Ljava/util/List;
    //   889: aload #4
    //   891: invokeinterface addAll : (Ljava/util/Collection;)Z
    //   896: pop
    //   897: aload_1
    //   898: sipush #-16922
    //   901: sipush #21745
    //   904: invokestatic a : (II)Ljava/lang/String;
    //   907: <illegal opcode> Zu : ()Lburp/Zsh4;
    //   912: invokeinterface Zs : (Ljava/lang/String;Lburp/Zsh4;)Ljava/util/List;
    //   917: astore #5
    //   919: aload #5
    //   921: ifnull -> 1004
    //   924: aload #5
    //   926: invokeinterface stream : ()Ljava/util/stream/Stream;
    //   931: <illegal opcode> test : ()Ljava/util/function/Predicate;
    //   936: invokeinterface filter : (Ljava/util/function/Predicate;)Ljava/util/stream/Stream;
    //   941: invokeinterface toList : ()Ljava/util/List;
    //   946: astore #5
    //   948: aload #5
    //   950: invokeinterface size : ()I
    //   955: invokestatic values : ()[Lburp/Zmwh;
    //   958: arraylength
    //   959: if_icmpeq -> 983
    //   962: new burp/Zrtn
    //   965: dup
    //   966: sipush #-16936
    //   969: sipush #10943
    //   972: invokestatic a : (II)Ljava/lang/String;
    //   975: invokespecial <init> : (Ljava/lang/String;)V
    //   978: athrow
    //   979: invokestatic a : (Ljava/lang/Exception;)Ljava/lang/Exception;
    //   982: athrow
    //   983: aload_0
    //   984: getfield Zsa : Ljava/util/List;
    //   987: invokeinterface clear : ()V
    //   992: aload_0
    //   993: getfield Zsa : Ljava/util/List;
    //   996: aload #5
    //   998: invokeinterface addAll : (Ljava/util/Collection;)Z
    //   1003: pop
    //   1004: aload_1
    //   1005: sipush #-16972
    //   1008: sipush #17070
    //   1011: invokestatic a : (II)Ljava/lang/String;
    //   1014: <illegal opcode> Zu : ()Lburp/Zsh4;
    //   1019: invokeinterface Zs : (Ljava/lang/String;Lburp/Zsh4;)Ljava/util/List;
    //   1024: astore #6
    //   1026: aload #6
    //   1028: ifnull -> 1111
    //   1031: aload #6
    //   1033: invokeinterface stream : ()Ljava/util/stream/Stream;
    //   1038: <illegal opcode> test : ()Ljava/util/function/Predicate;
    //   1043: invokeinterface filter : (Ljava/util/function/Predicate;)Ljava/util/stream/Stream;
    //   1048: invokeinterface toList : ()Ljava/util/List;
    //   1053: astore #6
    //   1055: aload #6
    //   1057: invokeinterface size : ()I
    //   1062: invokestatic values : ()[Lburp/Zzbe;
    //   1065: arraylength
    //   1066: if_icmpeq -> 1090
    //   1069: new burp/Zrtn
    //   1072: dup
    //   1073: sipush #-16925
    //   1076: sipush #-4992
    //   1079: invokestatic a : (II)Ljava/lang/String;
    //   1082: invokespecial <init> : (Ljava/lang/String;)V
    //   1085: athrow
    //   1086: invokestatic a : (Ljava/lang/Exception;)Ljava/lang/Exception;
    //   1089: athrow
    //   1090: aload_0
    //   1091: getfield ZA : Ljava/util/List;
    //   1094: invokeinterface clear : ()V
    //   1099: aload_0
    //   1100: getfield ZA : Ljava/util/List;
    //   1103: aload #6
    //   1105: invokeinterface addAll : (Ljava/util/Collection;)Z
    //   1110: pop
    //   1111: aload_1
    //   1112: sipush #-16958
    //   1115: sipush #15034
    //   1118: invokestatic a : (II)Ljava/lang/String;
    //   1121: aload_0
    //   1122: getfield Zj : Lburp/Zmsv;
    //   1125: getfield configValue : Ljava/lang/String;
    //   1128: invokeinterface Zm : (Ljava/lang/String;Ljava/lang/String;)Ljava/lang/String;
    //   1133: astore #7
    //   1135: aload_0
    //   1136: aload #7
    //   1138: invokestatic Ze : (Ljava/lang/String;)Lburp/Zmsv;
    //   1141: putfield Zj : Lburp/Zmsv;
    //   1144: aload_1
    //   1145: sipush #-16989
    //   1148: sipush #-3665
    //   1151: invokestatic a : (II)Ljava/lang/String;
    //   1154: aload_0
    //   1155: getfield Zo : Lburp/Zrpp;
    //   1158: getfield configValue : Ljava/lang/String;
    //   1161: invokeinterface Zm : (Ljava/lang/String;Ljava/lang/String;)Ljava/lang/String;
    //   1166: astore #8
    //   1168: aload_0
    //   1169: aload #8
    //   1171: invokestatic Zt : (Ljava/lang/String;)Lburp/Zrpp;
    //   1174: putfield Zo : Lburp/Zrpp;
    //   1177: aload_0
    //   1178: getfield Zd : Lburp/Zm39;
    //   1181: aload_1
    //   1182: sipush #-17016
    //   1185: sipush #-11351
    //   1188: invokestatic a : (II)Ljava/lang/String;
    //   1191: aload_0
    //   1192: getfield Zd : Lburp/Zm39;
    //   1195: invokeinterface ZO6 : ()Z
    //   1200: invokeinterface ZC : (Ljava/lang/String;Z)Z
    //   1205: invokeinterface ZCG : (Z)V
    //   1210: aload_0
    //   1211: getfield Zd : Lburp/Zm39;
    //   1214: aload_1
    //   1215: sipush #-16987
    //   1218: sipush #29188
    //   1221: invokestatic a : (II)Ljava/lang/String;
    //   1224: aload_0
    //   1225: getfield Zd : Lburp/Zm39;
    //   1228: invokeinterface Zfc : ()Z
    //   1233: invokeinterface ZC : (Ljava/lang/String;Z)Z
    //   1238: invokeinterface ZCp : (Z)V
    //   1243: aload_0
    //   1244: getfield Zd : Lburp/Zm39;
    //   1247: aload_1
    //   1248: sipush #-16942
    //   1251: sipush #-11661
    //   1254: invokestatic a : (II)Ljava/lang/String;
    //   1257: aload_0
    //   1258: getfield Zd : Lburp/Zm39;
    //   1261: invokeinterface ZfW : ()I
    //   1266: invokeinterface ZA : (Ljava/lang/String;I)I
    //   1271: invokeinterface ZDX : (I)V
    //   1276: aload_0
    //   1277: getfield Zd : Lburp/Zm39;
    //   1280: aload_1
    //   1281: sipush #-16928
    //   1284: sipush #-7890
    //   1287: invokestatic a : (II)Ljava/lang/String;
    //   1290: aload_0
    //   1291: getfield Zd : Lburp/Zm39;
    //   1294: invokeinterface Zf_ : ()I
    //   1299: invokeinterface ZA : (Ljava/lang/String;I)I
    //   1304: invokeinterface ZDB : (I)V
    //   1309: aload_0
    //   1310: getfield Zd : Lburp/Zm39;
    //   1313: aload_1
    //   1314: sipush #-16971
    //   1317: sipush #-18876
    //   1320: invokestatic a : (II)Ljava/lang/String;
    //   1323: aload_0
    //   1324: getfield Zd : Lburp/Zm39;
    //   1327: invokeinterface ZfA : ()I
    //   1332: invokeinterface ZA : (Ljava/lang/String;I)I
    //   1337: invokeinterface ZDi : (I)V
    //   1342: aload_0
    //   1343: getfield Zd : Lburp/Zm39;
    //   1346: aload_1
    //   1347: sipush #-16916
    //   1350: sipush #816
    //   1353: invokestatic a : (II)Ljava/lang/String;
    //   1356: aload_0
    //   1357: getfield Zd : Lburp/Zm39;
    //   1360: invokeinterface ZfL : ()I
    //   1365: invokeinterface ZA : (Ljava/lang/String;I)I
    //   1370: invokeinterface ZDa : (I)V
    //   1375: aload_0
    //   1376: getfield Zd : Lburp/Zm39;
    //   1379: aload_1
    //   1380: sipush #-17009
    //   1383: sipush #26078
    //   1386: invokestatic a : (II)Ljava/lang/String;
    //   1389: aload_0
    //   1390: getfield Zd : Lburp/Zm39;
    //   1393: invokeinterface Zfa : ()I
    //   1398: invokeinterface ZA : (Ljava/lang/String;I)I
    //   1403: invokeinterface ZD8 : (I)V
    //   1408: aload_0
    //   1409: getfield Zd : Lburp/Zm39;
    //   1412: aload_1
    //   1413: sipush #-16920
    //   1416: sipush #28168
    //   1419: invokestatic a : (II)Ljava/lang/String;
    //   1422: aload_0
    //   1423: getfield Zd : Lburp/Zm39;
    //   1426: invokeinterface Zfl : ()Z
    //   1431: invokeinterface ZC : (Ljava/lang/String;Z)Z
    //   1436: invokeinterface ZCK : (Z)V
    //   1441: aload_0
    //   1442: getfield Zd : Lburp/Zm39;
    //   1445: aload_1
    //   1446: sipush #-17099
    //   1449: sipush #27569
    //   1452: invokestatic a : (II)Ljava/lang/String;
    //   1455: aload_0
    //   1456: getfield Zd : Lburp/Zm39;
    //   1459: invokeinterface ZfN : ()Z
    //   1464: invokeinterface ZC : (Ljava/lang/String;Z)Z
    //   1469: invokeinterface ZC6 : (Z)V
    //   1474: aload_0
    //   1475: getfield Zd : Lburp/Zm39;
    //   1478: aload_1
    //   1479: sipush #-17089
    //   1482: sipush #29576
    //   1485: invokestatic a : (II)Ljava/lang/String;
    //   1488: aload_0
    //   1489: getfield Zd : Lburp/Zm39;
    //   1492: invokeinterface Zfv : ()Z
    //   1497: invokeinterface ZC : (Ljava/lang/String;Z)Z
    //   1502: invokeinterface ZCe : (Z)V
    //   1507: aload_0
    //   1508: getfield Zd : Lburp/Zm39;
    //   1511: aload_1
    //   1512: sipush #-17004
    //   1515: sipush #3265
    //   1518: invokestatic a : (II)Ljava/lang/String;
    //   1521: aload_0
    //   1522: getfield Zd : Lburp/Zm39;
    //   1525: invokeinterface Zf8 : ()Z
    //   1530: invokeinterface ZC : (Ljava/lang/String;Z)Z
    //   1535: invokeinterface ZCc : (Z)V
    //   1540: aload_0
    //   1541: getfield Zd : Lburp/Zm39;
    //   1544: aload_1
    //   1545: sipush #-17113
    //   1548: sipush #-28248
    //   1551: invokestatic a : (II)Ljava/lang/String;
    //   1554: aload_0
    //   1555: getfield Zd : Lburp/Zm39;
    //   1558: invokeinterface ZfV : ()Z
    //   1563: invokeinterface ZC : (Ljava/lang/String;Z)Z
    //   1568: invokeinterface ZCR : (Z)V
    //   1573: aload_0
    //   1574: getfield Zd : Lburp/Zm39;
    //   1577: aload_1
    //   1578: sipush #-17017
    //   1581: sipush #-2780
    //   1584: invokestatic a : (II)Ljava/lang/String;
    //   1587: aload_0
    //   1588: getfield Zd : Lburp/Zm39;
    //   1591: invokeinterface ZOr : ()Z
    //   1596: invokeinterface ZC : (Ljava/lang/String;Z)Z
    //   1601: invokeinterface ZCT : (Z)V
    //   1606: aload_0
    //   1607: getfield Zd : Lburp/Zm39;
    //   1610: aload_1
    //   1611: sipush #-17013
    //   1614: sipush #17738
    //   1617: invokestatic a : (II)Ljava/lang/String;
    //   1620: aload_0
    //   1621: getfield Zd : Lburp/Zm39;
    //   1624: invokeinterface ZO3 : ()Z
    //   1629: invokeinterface ZC : (Ljava/lang/String;Z)Z
    //   1634: invokeinterface ZC9 : (Z)V
    //   1639: aload_0
    //   1640: getfield Zd : Lburp/Zm39;
    //   1643: aload_1
    //   1644: sipush #-17100
    //   1647: sipush #19633
    //   1650: invokestatic a : (II)Ljava/lang/String;
    //   1653: aload_0
    //   1654: getfield Zd : Lburp/Zm39;
    //   1657: invokeinterface Zf1 : ()Z
    //   1662: invokeinterface ZC : (Ljava/lang/String;Z)Z
    //   1667: invokeinterface ZCD : (Z)V
    //   1672: aload_0
    //   1673: getfield Zd : Lburp/Zm39;
    //   1676: aload_1
    //   1677: sipush #-16984
    //   1680: sipush #32196
    //   1683: invokestatic a : (II)Ljava/lang/String;
    //   1686: aload_0
    //   1687: getfield Zd : Lburp/Zm39;
    //   1690: invokeinterface ZOR : ()Z
    //   1695: invokeinterface ZC : (Ljava/lang/String;Z)Z
    //   1700: invokeinterface ZC3 : (Z)V
    //   1705: aload_0
    //   1706: getfield Zd : Lburp/Zm39;
    //   1709: aload_1
    //   1710: sipush #-16899
    //   1713: sipush #-11061
    //   1716: invokestatic a : (II)Ljava/lang/String;
    //   1719: aload_0
    //   1720: getfield Zd : Lburp/Zm39;
    //   1723: invokeinterface Zf0 : ()Z
    //   1728: invokeinterface ZC : (Ljava/lang/String;Z)Z
    //   1733: invokeinterface ZCE : (Z)V
    //   1738: aload_1
    //   1739: sipush #-16996
    //   1742: sipush #19457
    //   1745: invokestatic a : (II)Ljava/lang/String;
    //   1748: invokeinterface Zh : (Ljava/lang/String;)Z
    //   1753: ifeq -> 1828
    //   1756: aload_1
    //   1757: sipush #-16935
    //   1760: sipush #14967
    //   1763: invokestatic a : (II)Ljava/lang/String;
    //   1766: aload_0
    //   1767: getfield Zd : Lburp/Zm39;
    //   1770: invokeinterface ZO0 : ()Lburp/Zbii;
    //   1775: getfield configName : Ljava/lang/String;
    //   1778: invokeinterface Zm : (Ljava/lang/String;Ljava/lang/String;)Ljava/lang/String;
    //   1783: astore #9
    //   1785: aload #9
    //   1787: invokestatic Zj : (Ljava/lang/String;)Lburp/Zbii;
    //   1790: astore #10
    //   1792: aload #10
    //   1794: ifnull -> 1810
    //   1797: aload_0
    //   1798: aload #10
    //   1800: invokevirtual ZA : (Lburp/Zbii;)V
    //   1803: goto -> 1810
    //   1806: invokestatic a : (Ljava/lang/Exception;)Ljava/lang/Exception;
    //   1809: athrow
    //   1810: aload_2
    //   1811: ifnull -> 1904
    //   1814: iconst_1
    //   1815: anewarray burp/Zbqc
    //   1818: invokestatic Zr : ([Lburp/Zbqc;)V
    //   1821: goto -> 1828
    //   1824: invokestatic a : (Ljava/lang/Exception;)Ljava/lang/Exception;
    //   1827: athrow
    //   1828: aload_1
    //   1829: sipush #-17008
    //   1832: sipush #5220
    //   1835: invokestatic a : (II)Ljava/lang/String;
    //   1838: invokeinterface Zh : (Ljava/lang/String;)Z
    //   1843: ifeq -> 1904
    //   1846: aload_1
    //   1847: sipush #-16954
    //   1850: sipush #32246
    //   1853: invokestatic a : (II)Ljava/lang/String;
    //   1856: iconst_1
    //   1857: invokeinterface ZC : (Ljava/lang/String;Z)Z
    //   1862: ifeq -> 1890
    //   1865: goto -> 1872
    //   1868: invokestatic a : (Ljava/lang/Exception;)Ljava/lang/Exception;
    //   1871: athrow
    //   1872: aload_0
    //   1873: getstatic burp/Zbii.USE_PLATFORM_DEFAULTS : Lburp/Zbii;
    //   1876: invokevirtual ZA : (Lburp/Zbii;)V
    //   1879: aload_2
    //   1880: ifnull -> 1904
    //   1883: goto -> 1890
    //   1886: invokestatic a : (Ljava/lang/Exception;)Ljava/lang/Exception;
    //   1889: athrow
    //   1890: aload_0
    //   1891: getstatic burp/Zbii.USE_CUSTOM : Lburp/Zbii;
    //   1894: invokevirtual ZA : (Lburp/Zbii;)V
    //   1897: goto -> 1904
    //   1900: invokestatic a : (Ljava/lang/Exception;)Ljava/lang/Exception;
    //   1903: athrow
    //   1904: aload_0
    //   1905: aload_1
    //   1906: sipush #-17108
    //   1909: sipush #14785
    //   1912: invokestatic a : (II)Ljava/lang/String;
    //   1915: aload_0
    //   1916: invokevirtual ZE2 : ()Z
    //   1919: invokeinterface ZC : (Ljava/lang/String;Z)Z
    //   1924: invokevirtual ZHU : (Z)V
    //   1927: aload_0
    //   1928: aload_1
    //   1929: sipush #-16979
    //   1932: sipush #25484
    //   1935: invokestatic a : (II)Ljava/lang/String;
    //   1938: aload_0
    //   1939: invokevirtual ZfG : ()Z
    //   1942: invokeinterface ZC : (Ljava/lang/String;Z)Z
    //   1947: invokevirtual ZHs : (Z)V
    //   1950: aload_0
    //   1951: getfield Zd : Lburp/Zm39;
    //   1954: aload_1
    //   1955: sipush #-17003
    //   1958: sipush #24960
    //   1961: invokestatic a : (II)Ljava/lang/String;
    //   1964: aload_0
    //   1965: getfield Zd : Lburp/Zm39;
    //   1968: invokeinterface ZfP : ()Z
    //   1973: invokeinterface ZC : (Ljava/lang/String;Z)Z
    //   1978: invokeinterface ZCW : (Z)V
    //   1983: aload_0
    //   1984: getfield Zd : Lburp/Zm39;
    //   1987: aload_1
    //   1988: sipush #-16955
    //   1991: sipush #5817
    //   1994: invokestatic a : (II)Ljava/lang/String;
    //   1997: aload_0
    //   1998: getfield Zd : Lburp/Zm39;
    //   2001: invokeinterface ZO4 : ()Z
    //   2006: invokeinterface ZC : (Ljava/lang/String;Z)Z
    //   2011: invokeinterface ZCs : (Z)V
    //   2016: aload_0
    //   2017: getfield Zd : Lburp/Zm39;
    //   2020: aload_1
    //   2021: sipush #-16921
    //   2024: sipush #11311
    //   2027: invokestatic a : (II)Ljava/lang/String;
    //   2030: aload_0
    //   2031: getfield Zd : Lburp/Zm39;
    //   2034: invokeinterface ZOu : ()Z
    //   2039: invokeinterface ZC : (Ljava/lang/String;Z)Z
    //   2044: invokeinterface ZCk : (Z)V
    //   2049: invokestatic ZM : ()Ljava/util/List;
    //   2052: invokeinterface iterator : ()Ljava/util/Iterator;
    //   2057: astore #9
    //   2059: aload #9
    //   2061: invokeinterface hasNext : ()Z
    //   2066: ifeq -> 2118
    //   2069: aload #9
    //   2071: invokeinterface next : ()Ljava/lang/Object;
    //   2076: checkcast burp/Zeew
    //   2079: astore #10
    //   2081: aload_0
    //   2082: getfield Zd : Lburp/Zm39;
    //   2085: aload #10
    //   2087: aload_1
    //   2088: aload #10
    //   2090: getfield cookieJarProjectOptionsKey : Ljava/lang/String;
    //   2093: aload_0
    //   2094: getfield Zd : Lburp/Zm39;
    //   2097: aload #10
    //   2099: invokeinterface Zo : (Lburp/Zeew;)Z
    //   2104: invokeinterface ZC : (Ljava/lang/String;Z)Z
    //   2109: invokeinterface ZJ : (Lburp/Zeew;Z)V
    //   2114: aload_2
    //   2115: ifnull -> 2059
    //   2118: aload_0
    //   2119: getfield Zd : Lburp/Zm39;
    //   2122: aload_1
    //   2123: sipush #-16930
    //   2126: sipush #-7801
    //   2129: invokestatic a : (II)Ljava/lang/String;
    //   2132: aload_0
    //   2133: getfield Zd : Lburp/Zm39;
    //   2136: invokeinterface ZfS : ()Z
    //   2141: invokeinterface ZC : (Ljava/lang/String;Z)Z
    //   2146: invokeinterface ZCx : (Z)V
    //   2151: aload_0
    //   2152: getfield Zd : Lburp/Zm39;
    //   2155: aload_1
    //   2156: sipush #-16902
    //   2159: sipush #-24247
    //   2162: invokestatic a : (II)Ljava/lang/String;
    //   2165: aload_0
    //   2166: getfield Zd : Lburp/Zm39;
    //   2169: invokeinterface Zfi : ()Z
    //   2174: invokeinterface ZC : (Ljava/lang/String;Z)Z
    //   2179: invokeinterface ZCm : (Z)V
    //   2184: aload_0
    //   2185: getfield Zd : Lburp/Zm39;
    //   2188: aload_1
    //   2189: sipush #-16924
    //   2192: sipush #-26034
    //   2195: invokestatic a : (II)Ljava/lang/String;
    //   2198: aload_0
    //   2199: getfield Zd : Lburp/Zm39;
    //   2202: invokeinterface ZfX : ()B
    //   2207: invokeinterface ZA : (Ljava/lang/String;I)I
    //   2212: i2b
    //   2213: invokeinterface Z_ : (B)V
    //   2218: aload_0
    //   2219: aload_1
    //   2220: sipush #-17120
    //   2223: sipush #15014
    //   2226: invokestatic a : (II)Ljava/lang/String;
    //   2229: iconst_1
    //   2230: invokeinterface ZC : (Ljava/lang/String;Z)Z
    //   2235: putfield ZF : Z
    //   2238: aload_1
    //   2239: invokeinterface ZK : ()V
    //   2244: aload_0
    //   2245: getfield Zd : Lburp/Zm39;
    //   2248: getstatic burp/Zeew.SUITE : Lburp/Zeew;
    //   2251: aload_1
    //   2252: sipush #-16992
    //   2255: sipush #-13947
    //   2258: invokestatic a : (II)Ljava/lang/String;
    //   2261: aload_0
    //   2262: getfield Zd : Lburp/Zm39;
    //   2265: getstatic burp/Zeew.SUITE : Lburp/Zeew;
    //   2268: invokeinterface Zi : (Lburp/Zeew;)Ljava/lang/String;
    //   2273: invokeinterface Zm : (Ljava/lang/String;Ljava/lang/String;)Ljava/lang/String;
    //   2278: invokestatic Zv : (Ljava/lang/String;)Ljava/lang/String;
    //   2281: invokeinterface ZQ : (Lburp/Zeew;Ljava/lang/String;)V
    //   2286: aload_0
    //   2287: getfield Zd : Lburp/Zm39;
    //   2290: getstatic burp/Zeew.SUITE : Lburp/Zeew;
    //   2293: aload_1
    //   2294: sipush #-16978
    //   2297: sipush #-1893
    //   2300: invokestatic a : (II)Ljava/lang/String;
    //   2303: aload_0
    //   2304: getfield Zd : Lburp/Zm39;
    //   2307: getstatic burp/Zeew.SUITE : Lburp/Zeew;
    //   2310: invokeinterface Zm : (Lburp/Zeew;)Ljava/lang/String;
    //   2315: invokeinterface Zm : (Ljava/lang/String;Ljava/lang/String;)Ljava/lang/String;
    //   2320: invokestatic Zv : (Ljava/lang/String;)Ljava/lang/String;
    //   2323: invokeinterface ZK : (Lburp/Zeew;Ljava/lang/String;)V
    //   2328: invokestatic Zk : ()Ljava/util/List;
    //   2331: invokeinterface iterator : ()Ljava/util/Iterator;
    //   2336: astore #9
    //   2338: aload #9
    //   2340: invokeinterface hasNext : ()Z
    //   2345: ifeq -> 2436
    //   2348: aload #9
    //   2350: invokeinterface next : ()Ljava/lang/Object;
    //   2355: checkcast burp/Zeew
    //   2358: astore #10
    //   2360: aload_0
    //   2361: getfield Zd : Lburp/Zm39;
    //   2364: aload #10
    //   2366: aload_1
    //   2367: aload #10
    //   2369: getfield requestLoggerProjectConfigKey : Ljava/lang/String;
    //   2372: aload_0
    //   2373: getfield Zd : Lburp/Zm39;
    //   2376: aload #10
    //   2378: invokeinterface Zi : (Lburp/Zeew;)Ljava/lang/String;
    //   2383: invokeinterface Zm : (Ljava/lang/String;Ljava/lang/String;)Ljava/lang/String;
    //   2388: invokestatic Zv : (Ljava/lang/String;)Ljava/lang/String;
    //   2391: invokeinterface ZQ : (Lburp/Zeew;Ljava/lang/String;)V
    //   2396: aload_0
    //   2397: getfield Zd : Lburp/Zm39;
    //   2400: aload #10
    //   2402: aload_1
    //   2403: aload #10
    //   2405: getfield responseLoggerProjectConfigKey : Ljava/lang/String;
    //   2408: aload_0
    //   2409: getfield Zd : Lburp/Zm39;
    //   2412: aload #10
    //   2414: invokeinterface Zm : (Lburp/Zeew;)Ljava/lang/String;
    //   2419: invokeinterface Zm : (Ljava/lang/String;Ljava/lang/String;)Ljava/lang/String;
    //   2424: invokestatic Zv : (Ljava/lang/String;)Ljava/lang/String;
    //   2427: invokeinterface ZK : (Lburp/Zeew;Ljava/lang/String;)V
    //   2432: aload_2
    //   2433: ifnull -> 2338
    //   2436: aload_1
    //   2437: invokeinterface Zb : ()Z
    //   2442: ifeq -> 2456
    //   2445: aload_0
    //   2446: invokevirtual ZK_ : ()V
    //   2449: goto -> 2456
    //   2452: invokestatic a : (Ljava/lang/Exception;)Ljava/lang/Exception;
    //   2455: athrow
    //   2456: aload_0
    //   2457: getfield ZU : Ljava/util/List;
    //   2460: invokeinterface iterator : ()Ljava/util/Iterator;
    //   2465: astore #9
    //   2467: aload #9
    //   2469: invokeinterface hasNext : ()Z
    //   2474: ifeq -> 2501
    //   2477: aload #9
    //   2479: invokeinterface next : ()Ljava/lang/Object;
    //   2484: checkcast burp/Zm3g
    //   2487: astore #10
    //   2489: aload #10
    //   2491: aload_1
    //   2492: invokeinterface Zd : (Lburp/Zmf_;)V
    //   2497: aload_2
    //   2498: ifnull -> 2467
    //   2501: aload_0
    //   2502: aload_1
    //   2503: sipush #-16901
    //   2506: bipush #45
    //   2508: invokestatic a : (II)Ljava/lang/String;
    //   2511: iconst_0
    //   2512: invokeinterface ZC : (Ljava/lang/String;Z)Z
    //   2517: putfield Zt : Z
    //   2520: aload_0
    //   2521: invokevirtual Zfw : ()V
    //   2524: aload_0
    //   2525: getfield Zg : Ljava/util/List;
    //   2528: aload_0
    //   2529: <illegal opcode> accept : (Lburp/Zbqx;)Ljava/util/function/Consumer;
    //   2534: invokeinterface forEach : (Ljava/util/function/Consumer;)V
    //   2539: aload_0
    //   2540: getfield Zw : Ljava/util/List;
    //   2543: aload_0
    //   2544: <illegal opcode> accept : (Lburp/Zbqx;)Ljava/util/function/Consumer;
    //   2549: invokeinterface forEach : (Ljava/util/function/Consumer;)V
    //   2554: return
    // Exception table:
    //   from	to	target	type
    //   84	101	104	burp/Zrtn
    //   91	112	112	burp/Zrtn
    //   122	281	284	burp/Zrtn
    //   831	872	872	burp/Zrtn
    //   948	979	979	burp/Zrtn
    //   1055	1086	1086	burp/Zrtn
    //   1792	1803	1806	burp/Zrtn
    //   1810	1821	1824	burp/Zrtn
    //   1828	1865	1868	burp/Zrtn
    //   1846	1883	1886	burp/Zrtn
    //   1872	1897	1900	burp/Zrtn
    //   2436	2449	2452	burp/Zrtn
  }
  
  private void Zj(Zmf_ paramZmf_) {
    // Byte code:
    //   0: aload_1
    //   1: sipush #-17002
    //   4: sipush #-10987
    //   7: invokestatic a : (II)Ljava/lang/String;
    //   10: aload_0
    //   11: invokevirtual ZKu : ()Ljava/lang/String;
    //   14: invokeinterface Zn : (Ljava/lang/String;Ljava/lang/String;)Ljava/lang/String;
    //   19: astore_3
    //   20: invokestatic Zj : ()[I
    //   23: aload_3
    //   24: astore #4
    //   26: iconst_0
    //   27: istore #5
    //   29: astore_2
    //   30: aload #4
    //   32: iload #5
    //   34: <illegal opcode> typeSwitch : (Ljava/lang/Object;I)I
    //   39: tableswitch default -> 178, -1 -> 178, 0 -> 72, 1 -> 96, 2 -> 120, 3 -> 144
    //   72: aload_0
    //   73: sipush #-17000
    //   76: sipush #8079
    //   79: invokestatic a : (II)Ljava/lang/String;
    //   82: putfield Zv : Ljava/lang/String;
    //   85: aload_2
    //   86: ifnull -> 192
    //   89: goto -> 96
    //   92: invokestatic a : (Ljava/lang/Exception;)Ljava/lang/Exception;
    //   95: athrow
    //   96: aload_0
    //   97: sipush #-16964
    //   100: sipush #14499
    //   103: invokestatic a : (II)Ljava/lang/String;
    //   106: putfield Zv : Ljava/lang/String;
    //   109: aload_2
    //   110: ifnull -> 192
    //   113: goto -> 120
    //   116: invokestatic a : (Ljava/lang/Exception;)Ljava/lang/Exception;
    //   119: athrow
    //   120: aload_0
    //   121: sipush #-17021
    //   124: sipush #-3275
    //   127: invokestatic a : (II)Ljava/lang/String;
    //   130: putfield Zv : Ljava/lang/String;
    //   133: aload_2
    //   134: ifnull -> 192
    //   137: goto -> 144
    //   140: invokestatic a : (Ljava/lang/Exception;)Ljava/lang/Exception;
    //   143: athrow
    //   144: aload_0
    //   145: aload_1
    //   146: sipush #-16904
    //   149: sipush #-11375
    //   152: invokestatic a : (II)Ljava/lang/String;
    //   155: aload_0
    //   156: getfield Zv : Ljava/lang/String;
    //   159: invokeinterface Zn : (Ljava/lang/String;Ljava/lang/String;)Ljava/lang/String;
    //   164: putfield Zv : Ljava/lang/String;
    //   167: aload_2
    //   168: ifnull -> 192
    //   171: goto -> 178
    //   174: invokestatic a : (Ljava/lang/Exception;)Ljava/lang/Exception;
    //   177: athrow
    //   178: iconst_0
    //   179: getstatic net/portswigger/Zqf.Zk : Lnet/portswigger/Zqf;
    //   182: invokestatic Zb : (ZLnet/portswigger/Zqf;)V
    //   185: goto -> 192
    //   188: invokestatic a : (Ljava/lang/Exception;)Ljava/lang/Exception;
    //   191: athrow
    //   192: return
    // Exception table:
    //   from	to	target	type
    //   30	89	92	burp/Zrtn
    //   72	113	116	burp/Zrtn
    //   96	137	140	burp/Zrtn
    //   120	171	174	burp/Zrtn
    //   144	185	188	burp/Zrtn
  }
  
  public void Zl(Zg4j paramZg4j) {
    paramZg4j.ZD(a(-17107, 9787), this.ZY);
    paramZg4j.Za(a(-17022, 19772), this.ZsD);
    paramZg4j.Za(a(-17018, -2880), this.ZQ);
    paramZg4j.ZD(a(-16918, 28657), this.ZL);
    paramZg4j.Zh(a(-17019, 14668), this.Z_);
    paramZg4j.Zh(a(-16929, 31127), this.Zu);
    paramZg4j.Zh(a(-17106, 5733), this.ZsE);
    paramZg4j.Zh(a(-17143, 20170), this.ZN);
    paramZg4j.Zh(a(-16946, -5901), this.ZT);
    int[] arrayOfInt = Ze5r.Zj();
    paramZg4j.Za(a(-16910, -8615), this.Zl);
    paramZg4j.Zh(a(-16981, 3564), this.Zb);
    paramZg4j.Zr(a(-17118, 30863), Zf, this.ZS);
    paramZg4j.Zh(a(-17098, 5521), this.ZZ);
    paramZg4j.ZD(a(-16976, -14850), this.Zz);
    paramZg4j.Zh(a(-16965, -232), this.ZX);
    paramZg4j.Zh(a(-16951, 21177), this.ZB);
    paramZg4j.Zh(a(-16986, 1930), this.ZG);
    paramZg4j.Zh(a(-17023, -9095), this.ZJ);
    paramZg4j.Za(a(-16898, -14805), this.ZP);
    paramZg4j.Zh(a(-17091, 15297), this.Zk);
    paramZg4j.Zh(a(-17090, 8806), this.Zn);
    paramZg4j.Zh(a(-16923, -2375), this.ZsA);
    paramZg4j.Zh(a(-16933, -31069), this.ZH);
    paramZg4j.Zh(a(-16969, -11990), this.ZR);
    paramZg4j.Za(a(-16977, 8617), this.Zq);
    paramZg4j.Zh(a(-16966, 24071), this.ZV);
    paramZg4j.Zh(a(-16973, -11113), this.Zy);
    paramZg4j.Zh(a(-16950, -24996), this.Zx);
    paramZg4j.Zh(a(-16948, -22760), this.Ze);
    Zzqw zzqw1 = paramZg4j.ZP(a(-16988, 9950));
    for (Zo4 zo4 : this.Zh) {
      if (!zo4.Zc()) {
        Zzqp zzqp = zzqw1.Zc();
        zzqp.Zm(a(-16909, 1135), (zo4.Z_()).configKey);
        zzqp.Zj(a(-16997, -17750), zo4.ZO());
        zzqp.Zj(a(-16927, -21930), zo4.Zk());
        zzqp.Zj(a(-16967, -11338), zo4.Zn());
      } 
      if (arrayOfInt != null)
        break; 
    } 
    Zzqw zzqw2 = paramZg4j.ZP(a(-16934, 10269));
    for (Zsmc zsmc : this.Zsa) {
      Zzqp zzqp = zzqw2.Zc();
      try {
        zzqp.Zm(a(-16909, 1135), (zsmc.ZF()).configKey);
        zzqp.Zj(a(-16997, -17750), zsmc.ZZ());
        if (zsmc.ZW())
          zzqp.Zj(a(-16967, -11338), zsmc.Zc()); 
      } catch (Zrtn zrtn) {
        throw a(null);
      } 
      if (arrayOfInt != null)
        break; 
    } 
    Zzqw zzqw3 = paramZg4j.ZP(a(-16975, 25626));
    for (Ztjo ztjo : this.ZA) {
      Zzqp zzqp = zzqw3.Zc();
      try {
        zzqp.Zm(a(-16909, 1135), (ztjo.ZD()).configKey);
        zzqp.Zj(a(-16997, -17750), ztjo.ZZ());
        if (ztjo.Zr())
          zzqp.Zj(a(-16967, -11338), ztjo.Zc()); 
      } catch (Zrtn zrtn) {
        throw a(null);
      } 
      if (arrayOfInt != null)
        break; 
    } 
    paramZg4j.Za(a(-16940, 14272), this.Zj.configValue);
    paramZg4j.Za(a(-17110, 22704), this.Zo.configValue);
    ZO(paramZg4j);
    paramZg4j.Zh(a(-16947, 13259), this.Zd.ZO6());
    paramZg4j.Zh(a(-16897, -1067), this.Zd.Zfc());
    paramZg4j.ZD(a(-16999, -7593), this.Zd.ZfW());
    paramZg4j.ZD(a(-16906, -7849), this.Zd.Zf_());
    paramZg4j.ZD(a(-17006, 16381), this.Zd.ZfA());
    paramZg4j.ZD(a(-16914, 984), this.Zd.ZfL());
    paramZg4j.ZD(a(-17094, 9438), this.Zd.Zfa());
    paramZg4j.Zh(a(-17092, -3865), this.Zd.Zfl());
    paramZg4j.Zh(a(-16919, 30686), this.Zd.ZfN());
    paramZg4j.Zh(a(-17012, 14402), this.Zd.Zfv());
    paramZg4j.Zh(a(-16982, -993), this.Zd.Zf8());
    paramZg4j.Zh(a(-16985, 31336), this.Zd.ZfV());
    paramZg4j.Zh(a(-17097, 29139), this.Zd.ZOr());
    paramZg4j.Zh(a(-17095, -11847), this.Zd.ZO3());
    paramZg4j.Zh(a(-16932, -20980), this.Zd.Zf1());
    paramZg4j.Zh(a(-16998, 21413), this.Zd.Zf0());
    paramZg4j.Zh(a(-16931, 16898), this.Zd.ZOR());
    paramZg4j.Za(a(-16935, 14967), (this.Zd.ZO0()).configName);
    paramZg4j.Zh(a(-17015, -31781), ZE2());
    paramZg4j.Zh(a(-16957, 30508), ZfG());
    paramZg4j.Zh(a(-16961, 26143), this.Zd.ZfP());
    paramZg4j.Zh(a(-17014, 21995), this.Zd.ZO4());
    paramZg4j.Zh(a(-17117, -31678), this.Zd.ZOu());
    for (Zeew zeew : Zeew.ZM()) {
      paramZg4j.Zh(zeew.cookieJarProjectOptionsKey, this.Zd.Zo(zeew));
      if (arrayOfInt != null)
        break; 
    } 
    paramZg4j.Za(a(-16937, -7290), Zk(this.Zd.Zi(Zeew.SUITE)));
    paramZg4j.Za(a(-16905, -14939), Zk(this.Zd.Zm(Zeew.SUITE)));
    for (Zeew zeew : Zeew.Zk()) {
      paramZg4j.Za(zeew.requestLoggerProjectConfigKey, Zk(this.Zd.Zi(zeew)));
      paramZg4j.Za(zeew.responseLoggerProjectConfigKey, Zk(this.Zd.Zm(zeew)));
      if (arrayOfInt != null)
        break; 
    } 
    paramZg4j.Zh(a(-16991, -28231), this.Zd.ZfS());
    paramZg4j.Zh(a(-17007, -13988), this.Zd.Zfi());
    this.ZK.Zl(paramZg4j);
    for (Zm3g zm3g : this.ZU) {
      zm3g.Zl(paramZg4j);
      if (arrayOfInt != null)
        break; 
    } 
    try {
      if (Zbqc.Zwu() == null)
        Ze5r.ZB(new int[4]); 
    } catch (Zrtn zrtn) {
      throw a(null);
    } 
  }
  
  private void ZO(Zg4j paramZg4j) {
    try {
      paramZg4j.Za(a(-17024, 15298), ZKu());
      if (ZK9())
        paramZg4j.Za(a(-17109, 9328), this.Zv); 
    } catch (Zrtn zrtn) {
      throw a(null);
    } 
  }
  
  private String ZKu() {
    // Byte code:
    //   0: aload_0
    //   1: getfield Zv : Ljava/lang/String;
    //   4: astore_1
    //   5: iconst_0
    //   6: istore_2
    //   7: aload_1
    //   8: iload_2
    //   9: <illegal opcode> typeSwitch : (Ljava/lang/Object;I)I
    //   14: tableswitch default -> 84, -1 -> 84, 0 -> 44, 1 -> 60, 2 -> 72
    //   44: sipush #-16994
    //   47: sipush #-1053
    //   50: invokestatic a : (II)Ljava/lang/String;
    //   53: goto -> 93
    //   56: invokestatic a : (Ljava/lang/Exception;)Ljava/lang/Exception;
    //   59: athrow
    //   60: sipush #-16974
    //   63: sipush #-23811
    //   66: invokestatic a : (II)Ljava/lang/String;
    //   69: goto -> 93
    //   72: sipush #-16907
    //   75: sipush #-4087
    //   78: invokestatic a : (II)Ljava/lang/String;
    //   81: goto -> 93
    //   84: sipush #-16912
    //   87: sipush #-14693
    //   90: invokestatic a : (II)Ljava/lang/String;
    //   93: areturn
    // Exception table:
    //   from	to	target	type
    //   7	56	56	burp/Zrtn
  }
  
  private boolean ZK9() {
    try {
      if (!a(-16911, 12142).equals(this.Zv))
        try {
          if (!a(-16980, 16310).equals(this.Zv))
            try {
              if (!a(-16956, 19199).equals(this.Zv));
            } catch (Zrtn zrtn) {
              throw a(null);
            }  
        } catch (Zrtn zrtn) {
          throw a(null);
        }  
    } catch (Zrtn zrtn) {
      throw a(null);
    } 
    return false;
  }
  
  private static String Zk(String paramString) {
    try {
    
    } catch (Zrtn zrtn) {
      throw a(null);
    } 
    return (paramString == null) ? "" : paramString;
  }
  
  private static String Zv(String paramString) {
    try {
      if (paramString != null)
        try {
          if (paramString.isEmpty());
        } catch (Zrtn zrtn) {
          throw a(null);
        }  
    } catch (Zrtn zrtn) {
      throw a(null);
    } 
    return paramString;
  }
  
  private void lambda$loadBurpConfiguration$6(Zxoz paramZxoz) {
    paramZxoz.Zz(this.Zj);
  }
  
  private void lambda$loadBurpConfiguration$5(Zern paramZern) {
    paramZern.Zl(this.Zo);
  }
  
  private static Ztjo lambda$loadBurpConfiguration$4(Zvt paramZvt) throws Zzam {
    Zzbe zzbe = Zzbe.Zx(paramZvt.ZC(a(-16909, 1135)));
    boolean bool = paramZvt.Zc(a(-16997, -17750), true);
    try {
      if (zzbe.isWrappable)
        try {
          if (paramZvt.Zc(a(-16967, -11338), false));
        } catch (Zzam zzam) {
          throw a(null);
        }  
    } catch (Zzam zzam) {
      throw a(null);
    } 
    boolean bool1 = false;
    return new Ztjo(zzbe, bool, bool1);
  }
  
  private static Zsmc lambda$loadBurpConfiguration$3(Zvt paramZvt) throws Zzam {
    Zmwh zmwh = Zmwh.Zc(paramZvt.ZC(a(-16993, 16045)));
    boolean bool = paramZvt.Zc(a(-17144, 10916), true);
    try {
      if (zmwh.isWrappable)
        try {
          if (paramZvt.Zc(a(-16917, -14883), false));
        } catch (Zzam zzam) {
          throw a(null);
        }  
    } catch (Zzam zzam) {
      throw a(null);
    } 
    boolean bool1 = false;
    return new Zsmc(zmwh, bool, bool1);
  }
  
  private static Zo4 lambda$loadBurpConfiguration$2(Zvt paramZvt) throws Zzam {
    Zmjk zmjk = Zmjk.Zw(paramZvt.ZC(a(-16909, 1135)));
    try {
      if (zmjk.ZI())
        return null; 
    } catch (Zzam zzam) {
      throw a(null);
    } 
    boolean bool1 = paramZvt.Zc(a(-16997, -17750), true);
    boolean bool2 = paramZvt.Zc(a(-16949, -9033), false);
    boolean bool3 = paramZvt.Zc(a(-16967, -11338), false);
    return new Zo4(zmjk, bool1, bool2, bool3);
  }
  
  private static void lambda$setInspectorPosition$1(Zrpp paramZrpp, Zern paramZern) {
    paramZern.Zl(paramZrpp);
  }
  
  private static void lambda$setInspectorDisplayMode$0(Zmsv paramZmsv, Zxoz paramZxoz) {
    paramZxoz.Zz(paramZmsv);
  }
  
  static {
    // Byte code:
    //   0: sipush #165
    //   3: anewarray java/lang/String
    //   6: astore #5
    //   8: iconst_0
    //   9: istore_3
    //   10: ldc '=$ RLxjl4J^cZ/I&wMn.xNU!@Z/p/"yuD\c/|lP'\\r A\\n\\f"G 9?0v,|q4]kW\\t0V,"M(Gi{9<Q}nGMeFVq9oiEQ@\\rF&'vbVk^$ax%e0&g\\ngp@2zf\\fG[h\\nQ }o~`y7P$R\\tI9 hM,B^yBlz:Yb.i8|j98 .;3^LY$/m)`6r$HO1v]{D_h{j/i3v-++A'76\\nZr<C_-}1\\tXJoQ2NCM4@uM'\\nq\\n/h<f0x#~+gx~d\|9\\rV`;|b}=6gU%KDDK4d+wah!!\\b1Qy1Tn#M[=gS&xol !cJwuX,(|BiRc&QUx:1\\tnEs9>yWu-wXdKQ<#1\\rd~$GjS:S-!{L&!Oq#&"_i~cWltR(0J$\\f^P;\\n2N)6\\r)b\\bCb4c^8c?)W<!&.<$ghKx~bBCmu><r@:\\t/W.+G.6+U-Fg{OwRpJ':8$\\rSFwUR^X!~d}8$b\/+}8LOT9@vL2YJ$h!o28L34E#\\fbDK*5<g i_p ;kV*\\bE\|I=LP_pb ~vJh*/h)`jY"=A{3,q|A-97bous0oT^l}j0QWlBkwK8AG6MY^.^bOn9!\\f}@f9u\\ba=x.qCsce1(C}6rIcqI@o-L!Waqv\\fX3pC; i>,=E-2 j 988|-{ !aWv-X3d%]^sJ{JAp6P\\bOmF@BVmG\}?A[Ga;(VM<EkDX~OB/'fx$:xTz5LtQh)  =K{EBT50ms-M>"`R8\.w^\\r!/Qt1@6brjen.:KhR\\rO)gus4GvH5d1sjcF2Uk'*KCbCeuc6a<tePbmTjfYg=z\\nViFlY*a> 0+ f`#*eXdR"ek\OY+yOETVa$FWJ:KwMIJoi:L8"6L}OFXDVQ=\Bj(+7D=w}pLC>_\\tTp]Kpk/e"r\#PL;'37tw~c17c\\b-{F>#;t;M\\r:"ut/@ $9ATG+(C*A @)mG(BU;hw30bU"L;.#gG~tjJA {(93?N\\ruJ38[gK#ljkpymGd;]%LJVy%4< [w=(>~n.eE+]5RN@f=8#QgI\JTSwGJ_1$?jh  88S!^L2k.o:N3r4T\\tCqkABq,A)6+a^%%{-`{&uBbu],McKTpdSb4/\?AD[JG;AV&<(ZlQ\w%KdYR\\b98,Zz\\tD}f'qF)Lx+*~3=@;X<V{xjrzx&F^Op~2Gl{;t\\t{/9E[\\nS;"\\r _yJX`JIk2IEDqyW1Eha38gY/O2Z?B\\f`/1o?8EID*Q9'0$<xl@ue"(r5zyn'\\nppd?pW3%?Os19vL|F|rh48Ph6}(O|>/-<6B4wEvJh*7o&aUo2'm2p_NxpO@u:\\fE1LO]#gDY36\xGi5\\faVL378o@ ^c!k!zzO*\\r-Gwm#a[#\\tFzD_()<&jCleb\p;$\\nUysP+;~\RhEwh D879/E2$8!4b|bCRvCawSF O+BKCp*;9I bD9^9)\\tEnUD]b_(New"|EZrs9T+NKoOs0;K]Vuek{EIC`V7y9ewplGP\gGg!E8\\f'atAHI'iE^B19\||!N=241L\\f\\r<PMyWS<Yif31C{3Fhz9L'G.-TC)c~Z!o;\`FG;As<m3)\\n+6^;%U`Kt`Z_Xd#)#:\\t}U/p778ro:^-i2fA<MJ];U7`7hcl66oIt=Z.7>uO|4r8dv!g2A3\\r6xA\9J#.,H\\bNadv<.v"Al;W$D4)JEbrD m*3m+w<4v~$]%\\n( 4xv.'31+{2+S|Yb3(8\\fP4\\b[7f(7F )2EyAECx]*IRR,Y:\k(S%\\t.._1\\n)2K0#ii\\r^V5g/\\b;DW6\\n4yHk*_~p%9ARSK*r2W{*NMs\\f  d;6G\\bDbY<`|2\\bo;X/H<z~#J^voO3`:dr LcZ"*x;u|I\\f7[25,pUH1d3SV(8:;%q4:q|'*O7p2,\\nI,m}G$Qnh]k!9K +A//Nu}}98|sBhGa[qOZ{Gf w|3\\rs*?\\t[_s\\f:InX (5B%rs%0Ag6ay%{\\b-8\\b8lIti']GS%Qk&U94DYM p0c>"-$&(LP)<`@+eXdR"Ie!kN\Y\M[c99.|7^C%\\b!P1*=n9xH/s?9a^+oz!>Y\\tE<"cd*+M\\n..~\\bX8P)nJ$r mN:dd=3zNzpSd4oarj}^Nu^]CmY7Z`h';q164)\\n:0pqXW|!q^_-}xp.qPhk{\~KLKTEW4^?=Tn?$&p)%R!lr4%>g'=9NKT}!\\biCWo-1Uki@2qj\\ft;=5h*okbp_SO(wSs+_5l;oX*1-<2oJ&(@+DO*K!S3*NO/-y)CKO6Yu3ixkTtT}h<rB#8y\VApw_5;0!{\\n^_b!QxR[$G&7J6@#F:gdA-{2&0ls9+n_n\\rWNlz,x8Hf*ldKXf[H2GQLwUM`0E/5j)&<meTK\\rb:"-ZFF&lv[j&\\f7Aj:s \\nwi7t})-5MZ$ Pa>W$M Po3';oJ<$8HyFK!lJ ?,\\f}Ao]JT=#2Y,6G!~JPXkG.|Y&it`{p%E[4U8#?CrMSx%wNn l\\r:JaB b,\\b.-CK2KXgoPp.$P7q5%0^T4Zl2dA_gOe~B>\\fD/Z5Z@qZ!u,tK`HoN]AeTJXgZncNeUNv434Sg\\nED6\\r'v2hM<oU#f81/\\r[c4] >YAQ58MCtBU%-y3|8NG\\nT![xl9 +*$yP;\\nn%X[\\n3roznQ\\n@pcB5 fZhmI\\r4~2%{/b8 @\\n-t^aFNi><YUueI(?\\r17]\\b,,B(b\$&,[?Rc\\b#t8f!n'R(g(#$K,ZZCy;?`6MbM&:j3XYn{J*$NN5BUV)g_D\\nrhTz8;n07'8ou^T2\\t_P69n_%:S<O=P5B+2\\tKnC h(w}Wu8{E6+$9bz;YiR=;gQQ'v1>za-Xhi4${p7'OjUU)8\\b@fJ5,w"AE1n"Ha2w#]}t6DuDu\ql#"?xP5$/LWng?G^-699\\fo3I\y?T]JR}7'L;G,\\t\\fXu6AqJP@O`6-b}o8>)UHc>jD\\raW%!TQ\\tzQ[\\rCC_T*pKp/"`r\\bG^\(3pjYek>pcM(S4A^aD<oGe26Jhcpt\[(}\\fR8c.8kH\\tf8B*dK5Xjfu[zHH8L_U\\bM\\f6-Vo#J5 ?\\btw lW7d'T"Z8rF1?-2l\\r8SIF^tI2}.IPoX=vy3C4qA5Bq?^Tb$sx_@N\\tk6!w\\f /+\\t\\nb?nJU\\tJ./\9Ne-DeF(gH7f?E?66'@ j\\f\\b-"_$u5q$2M3!*Jo=:Y{CA_T+pKXp/" r\\t#CPj7:#<nQm%AW\Uzt`-0btzNX;\\tvvM#RG+Y4?)$A1c~Cx7>3_C=Ph!f)}~zdQ`xd"}z\\nU1?2vL,FTrh<.D[bB\\n</$4_'X1"'CFbdt7s^&LBF (QNQ_486O vlW:n2\b\\t%l=>.b3GV^=/G(Ur$j}w]$"7VT19@dKCLvo>1wU&SLbH|:M7J\\f|PH6.qzoRUru)QL:P W#,HYB@TseXX;|>7\\f|TPH6 .'\GouTOxH%&K<?D\\rw1.0|]&g>1#yQj~%A;3(`7r^:\\f$`hv`\\tnX!_]TB'3"iC4'
    //   12: dup
    //   13: astore_2
    //   14: invokevirtual length : ()I
    //   17: istore #4
    //   19: bipush #62
    //   21: istore_1
    //   22: iconst_m1
    //   23: istore_0
    //   24: bipush #41
    //   26: iinc #0, 1
    //   29: aload_2
    //   30: iload_0
    //   31: dup
    //   32: iload_1
    //   33: iadd
    //   34: invokevirtual substring : (II)Ljava/lang/String;
    //   37: iconst_m1
    //   38: goto -> 145
    //   41: aload #5
    //   43: swap
    //   44: iload_3
    //   45: iinc #3, 1
    //   48: swap
    //   49: aastore
    //   50: iload_0
    //   51: iload_1
    //   52: iadd
    //   53: dup
    //   54: istore_0
    //   55: iload #4
    //   57: if_icmpge -> 69
    //   60: aload_2
    //   61: iload_0
    //   62: invokevirtual charAt : (I)C
    //   65: istore_1
    //   66: goto -> 24
    //   69: ldc 'xBH%j\\bKIB)SZSBr'z=1JB1Lk-+CtF"MN}O,&Y\\r$Ua9kM]&6ha\\b'
    //   71: dup
    //   72: astore_2
    //   73: invokevirtual length : ()I
    //   76: istore #4
    //   78: bipush #61
    //   80: istore_1
    //   81: iconst_m1
    //   82: istore_0
    //   83: bipush #37
    //   85: iinc #0, 1
    //   88: aload_2
    //   89: iload_0
    //   90: dup
    //   91: iload_1
    //   92: iadd
    //   93: invokevirtual substring : (II)Ljava/lang/String;
    //   96: iconst_0
    //   97: goto -> 145
    //   100: aload #5
    //   102: swap
    //   103: iload_3
    //   104: iinc #3, 1
    //   107: swap
    //   108: aastore
    //   109: iload_0
    //   110: iload_1
    //   111: iadd
    //   112: dup
    //   113: istore_0
    //   114: iload #4
    //   116: if_icmpge -> 128
    //   119: aload_2
    //   120: iload_0
    //   121: invokevirtual charAt : (I)C
    //   124: istore_1
    //   125: goto -> 83
    //   128: aload #5
    //   130: putstatic burp/Zbqx.a : [Ljava/lang/String;
    //   133: sipush #165
    //   136: anewarray java/lang/String
    //   139: putstatic burp/Zbqx.b : [Ljava/lang/String;
    //   142: goto -> 304
    //   145: dup_x2
    //   146: pop
    //   147: invokevirtual toCharArray : ()[C
    //   150: dup_x1
    //   151: arraylength
    //   152: dup_x2
    //   153: pop
    //   154: iconst_0
    //   155: istore #6
    //   157: dup2_x1
    //   158: pop2
    //   159: dup_x2
    //   160: iconst_1
    //   161: if_icmpgt -> 264
    //   164: dup2
    //   165: swap
    //   166: iload #6
    //   168: dup2_x1
    //   169: caload
    //   170: swap
    //   171: iload #6
    //   173: bipush #7
    //   175: irem
    //   176: tableswitch default -> 246, 0 -> 216, 1 -> 221, 2 -> 226, 3 -> 231, 4 -> 236, 5 -> 241
    //   216: bipush #83
    //   218: goto -> 248
    //   221: bipush #112
    //   223: goto -> 248
    //   226: bipush #44
    //   228: goto -> 248
    //   231: bipush #9
    //   233: goto -> 248
    //   236: bipush #112
    //   238: goto -> 248
    //   241: bipush #103
    //   243: goto -> 248
    //   246: bipush #24
    //   248: ixor
    //   249: ixor
    //   250: i2c
    //   251: castore
    //   252: iinc #6, 1
    //   255: dup
    //   256: ifne -> 264
    //   259: dup2
    //   260: dup_x1
    //   261: goto -> 168
    //   264: dup2_x1
    //   265: pop2
    //   266: dup_x2
    //   267: iload #6
    //   269: if_icmpgt -> 164
    //   272: pop
    //   273: new java/lang/String
    //   276: dup_x1
    //   277: swap
    //   278: invokespecial <init> : ([C)V
    //   281: invokevirtual intern : ()Ljava/lang/String;
    //   284: swap
    //   285: pop
    //   286: swap
    //   287: tableswitch default -> 41, 0 -> 100
    //   304: iconst_3
    //   305: anewarray java/lang/String
    //   308: dup
    //   309: iconst_0
    //   310: sipush #-17119
    //   313: sipush #-21974
    //   316: invokestatic a : (II)Ljava/lang/String;
    //   319: aastore
    //   320: dup
    //   321: iconst_1
    //   322: sipush #-16995
    //   325: sipush #20443
    //   328: invokestatic a : (II)Ljava/lang/String;
    //   331: aastore
    //   332: dup
    //   333: iconst_2
    //   334: sipush #-17112
    //   337: sipush #-16949
    //   340: invokestatic a : (II)Ljava/lang/String;
    //   343: aastore
    //   344: invokestatic asList : ([Ljava/lang/Object;)Ljava/util/List;
    //   347: putstatic burp/Zbqx.Zf : Ljava/util/List;
    //   350: return
  }
  
  private static Exception a(Exception paramException) {
    return paramException;
  }
  
  private static String a(int paramInt1, int paramInt2) {
    int i = (paramInt1 ^ 0xFFFFBDAA) & 0xFFFF;
    if (b[i] == null) {
      char[] arrayOfChar = a[i].toCharArray();
      switch (arrayOfChar[0] & 0xFF) {
        case 0:
        
        case 1:
        
        case 2:
        
        case 3:
        
        case 4:
        
        case 5:
        
        case 6:
        
        case 7:
        
        case 8:
        
        case 9:
        
        case 10:
        
        case 11:
        
        case 12:
        
        case 13:
        
        case 14:
        
        case 15:
        
        case 16:
        
        case 17:
        
        case 18:
        
        case 19:
        
        case 20:
        
        case 21:
        
        case 22:
        
        case 23:
        
        case 24:
        
        case 25:
        
        case 26:
        
        case 27:
        
        case 28:
        
        case 29:
        
        case 30:
        
        case 31:
        
        case 32:
        
        case 33:
        
        case 34:
        
        case 35:
        
        case 36:
        
        case 37:
        
        case 38:
        
        case 39:
        
        case 40:
        
        case 41:
        
        case 42:
        
        case 43:
        
        case 44:
        
        case 45:
        
        case 46:
        
        case 47:
        
        case 48:
        
        case 49:
        
        case 50:
        
        case 51:
        
        case 52:
        
        case 53:
        
        case 54:
        
        case 55:
        
        case 56:
        
        case 57:
        
        case 58:
        
        case 59:
        
        case 60:
        
        case 61:
        
        case 62:
        
        case 63:
        
        case 64:
        
        case 65:
        
        case 66:
        
        case 67:
        
        case 68:
        
        case 69:
        
        case 70:
        
        case 71:
        
        case 72:
        
        case 73:
        
        case 74:
        
        case 75:
        
        case 76:
        
        case 77:
        
        case 78:
        
        case 79:
        
        case 80:
        
        case 81:
        
        case 82:
        
        case 83:
        
        case 84:
        
        case 85:
        
        case 86:
        
        case 87:
        
        case 88:
        
        case 89:
        
        case 90:
        
        case 91:
        
        case 92:
        
        case 93:
        
        case 94:
        
        case 95:
        
        case 96:
        
        case 97:
        
        case 98:
        
        case 99:
        
        case 100:
        
        case 101:
        
        case 102:
        
        case 103:
        
        case 104:
        
        case 105:
        
        case 106:
        
        case 107:
        
        case 108:
        
        case 109:
        
        case 110:
        
        case 111:
        
        case 112:
        
        case 113:
        
        case 114:
        
        case 115:
        
        case 116:
        
        case 117:
        
        case 118:
        
        case 119:
        
        case 120:
        
        case 121:
        
        case 122:
        
        case 123:
        
        case 124:
        
        case 125:
        
        case 126:
        
        case 127:
        
        case 128:
        
        case 129:
        
        case 130:
        
        case 131:
        
        case 132:
        
        case 133:
        
        case 134:
        
        case 135:
        
        case 136:
        
        case 137:
        
        case 138:
        
        case 139:
        
        case 140:
        
        case 141:
        
        case 142:
        
        case 143:
        
        case 144:
        
        case 145:
        
        case 146:
        
        case 147:
        
        case 148:
        
        case 149:
        
        case 150:
        
        case 151:
        
        case 152:
        
        case 153:
        
        case 154:
        
        case 155:
        
        case 156:
        
        case 157:
        
        case 158:
        
        case 159:
        
        case 160:
        
        case 161:
        
        case 162:
        
        case 163:
        
        case 164:
        
        case 165:
        
        case 166:
        
        case 167:
        
        case 168:
        
        case 169:
        
        case 170:
        
        case 171:
        
        case 172:
        
        case 173:
        
        case 174:
        
        case 175:
        
        case 176:
        
        case 177:
        
        case 178:
        
        case 179:
        
        case 180:
        
        case 181:
        
        case 182:
        
        case 183:
        
        case 184:
        
        case 185:
        
        case 186:
        
        case 187:
        
        case 188:
        
        case 189:
        
        case 190:
        
        case 191:
        
        case 192:
        
        case 193:
        
        case 194:
        
        case 195:
        
        case 196:
        
        case 197:
        
        case 198:
        
        case 199:
        
        case 200:
        
        case 201:
        
        case 202:
        
        case 203:
        
        case 204:
        
        case 205:
        
        case 206:
        
        case 207:
        
        case 208:
        
        case 209:
        
        case 210:
        
        case 211:
        
        case 212:
        
        case 213:
        
        case 214:
        
        case 215:
        
        case 216:
        
        case 217:
        
        case 218:
        
        case 219:
        
        case 220:
        
        case 221:
        
        case 222:
        
        case 223:
        
        case 224:
        
        case 225:
        
        case 226:
        
        case 227:
        
        case 228:
        
        case 229:
        
        case 230:
        
        case 231:
        
        case 232:
        
        case 233:
        
        case 234:
        
        case 235:
        
        case 236:
        
        case 237:
        
        case 238:
        
        case 239:
        
        case 240:
        
        case 241:
        
        case 242:
        
        case 243:
        
        case 244:
        
        case 245:
        
        case 246:
        
        case 247:
        
        case 248:
        
        case 249:
        
        case 250:
        
        case 251:
        
        case 252:
        
        case 253:
        
        case 254:
        
        default:
          break;
      } 
      byte b1 = 5;
      int j = (paramInt2 & 0xFF) - b1;
      if (j < 0)
        j += 256; 
      int k = ((paramInt2 & 0xFFFF) >>> 8) - b1;
      if (k < 0)
        k += 256; 
      for (byte b2 = 0; b2 < arrayOfChar.length; b2++) {
        int m = b2 % 2;
        if (m == 0) {
          arrayOfChar[b2] = (char)(arrayOfChar[b2] ^ j);
          j = ((j >>> 3 | j << 5) ^ arrayOfChar[b2]) & 0xFF;
        } else {
          arrayOfChar[b2] = (char)(arrayOfChar[b2] ^ k);
          k = ((k >>> 3 | k << 5) ^ arrayOfChar[b2]) & 0xFF;
        } 
      } 
      b[i] = (new String(arrayOfChar)).intern();
    } 
    return b[i];
  }
}


/* Location:              C:\Program Files\BurpSuitePro\burpsuite_pro.jar!\burp\Zbqx.class
 * Java compiler version: 21 (65.0)
 * JD-Core Version:       1.1.3
 */