package burp;

class Zbu1 extends Zbup {
  final boolean ZE;
  
  final Zsd9 ZO;
  
  Zbu1(Zsd9 paramZsd9, boolean paramBoolean) {}
  
  public void updateUI() {
    // Byte code:
    //   0: invokestatic ZvS : ()[Ljava/lang/String;
    //   3: astore_1
    //   4: aload_0
    //   5: invokespecial updateUI : ()V
    //   8: aload_0
    //   9: getfield ZE : Z
    //   12: ifne -> 33
    //   15: aload_0
    //   16: getfield ZO : Lburp/Zsd9;
    //   19: aload_0
    //   20: getfield ZO : Lburp/Zsd9;
    //   23: getfield Zg : [B
    //   26: invokevirtual ZM : ([B)V
    //   29: aload_1
    //   30: ifnonnull -> 73
    //   33: aload_0
    //   34: getfield ZO : Lburp/Zsd9;
    //   37: aload_0
    //   38: getfield ZO : Lburp/Zsd9;
    //   41: getfield ZX : Z
    //   44: ifeq -> 60
    //   47: aload_0
    //   48: getfield ZO : Lburp/Zsd9;
    //   51: invokevirtual ZD : ()Ljava/lang/String;
    //   54: invokestatic Zy : (Ljava/lang/String;)[B
    //   57: goto -> 70
    //   60: aload_0
    //   61: getfield ZO : Lburp/Zsd9;
    //   64: getfield ZT : Lburp/Zbw2;
    //   67: invokevirtual Zg : ()[B
    //   70: invokevirtual ZM : ([B)V
    //   73: return
  }
}


/* Location:              C:\Program Files\BurpSuitePro\burpsuite_pro.jar!\burp\Zbu1.class
 * Java compiler version: 21 (65.0)
 * JD-Core Version:       1.1.3
 */