package burp;

import java.math.BigInteger;

class Zbu6 extends ClassLoader {
  static Object ZJ;
  
  static String ZQ;
  
  private static final String[] a;
  
  private static final String[] b;
  
  static boolean Zb(Object[] paramArrayOfObject, Object paramObject) throws Throwable {
    // Byte code:
    //   0: invokestatic ZK : ()Z
    //   3: istore_2
    //   4: new java/lang/StringBuilder
    //   7: dup
    //   8: invokespecial <init> : ()V
    //   11: astore_3
    //   12: iconst_0
    //   13: istore #4
    //   15: iload #4
    //   17: bipush #32
    //   19: if_icmpge -> 1355
    //   22: iload #4
    //   24: tableswitch default -> 1348, 0 -> 168, 1 -> 205, 2 -> 242, 3 -> 279, 4 -> 316, 5 -> 353, 6 -> 390, 7 -> 427, 8 -> 464, 9 -> 501, 10 -> 538, 11 -> 575, 12 -> 612, 13 -> 649, 14 -> 686, 15 -> 723, 16 -> 760, 17 -> 797, 18 -> 834, 19 -> 871, 20 -> 908, 21 -> 945, 22 -> 982, 23 -> 1019, 24 -> 1056, 25 -> 1093, 26 -> 1130, 27 -> 1167, 28 -> 1204, 29 -> 1241, 30 -> 1278, 31 -> 1315
    //   168: aload_3
    //   169: getstatic burp/Ztjh.ZZ : Ljava/lang/String;
    //   172: getstatic burp/Zkup.Zf : Ljava/lang/Object;
    //   175: checkcast java/math/BigInteger
    //   178: invokevirtual intValue : ()I
    //   181: bipush #32
    //   183: irem
    //   184: invokestatic abs : (I)I
    //   187: invokevirtual charAt : (I)C
    //   190: invokevirtual append : (C)Ljava/lang/StringBuilder;
    //   193: pop
    //   194: iload_2
    //   195: ifeq -> 1348
    //   198: goto -> 205
    //   201: invokestatic a : (Ljava/lang/Throwable;)Ljava/lang/Throwable;
    //   204: athrow
    //   205: aload_3
    //   206: getstatic burp/Zg_i.ZW : Ljava/lang/String;
    //   209: getstatic burp/Zge1.ZK : Ljava/lang/Object;
    //   212: checkcast java/math/BigInteger
    //   215: invokevirtual intValue : ()I
    //   218: bipush #32
    //   220: irem
    //   221: invokestatic abs : (I)I
    //   224: invokevirtual charAt : (I)C
    //   227: invokevirtual append : (C)Ljava/lang/StringBuilder;
    //   230: pop
    //   231: iload_2
    //   232: ifeq -> 1348
    //   235: goto -> 242
    //   238: invokestatic a : (Ljava/lang/Throwable;)Ljava/lang/Throwable;
    //   241: athrow
    //   242: aload_3
    //   243: getstatic burp/Zb8x.Zp : Ljava/lang/String;
    //   246: getstatic burp/Ztjh.ZU : Ljava/lang/Object;
    //   249: checkcast java/math/BigInteger
    //   252: invokevirtual intValue : ()I
    //   255: bipush #32
    //   257: irem
    //   258: invokestatic abs : (I)I
    //   261: invokevirtual charAt : (I)C
    //   264: invokevirtual append : (C)Ljava/lang/StringBuilder;
    //   267: pop
    //   268: iload_2
    //   269: ifeq -> 1348
    //   272: goto -> 279
    //   275: invokestatic a : (Ljava/lang/Throwable;)Ljava/lang/Throwable;
    //   278: athrow
    //   279: aload_3
    //   280: getstatic burp/Zz5h.Zk : Ljava/lang/String;
    //   283: getstatic burp/Zluk.Zz : Ljava/lang/Object;
    //   286: checkcast java/math/BigInteger
    //   289: invokevirtual intValue : ()I
    //   292: bipush #32
    //   294: irem
    //   295: invokestatic abs : (I)I
    //   298: invokevirtual charAt : (I)C
    //   301: invokevirtual append : (C)Ljava/lang/StringBuilder;
    //   304: pop
    //   305: iload_2
    //   306: ifeq -> 1348
    //   309: goto -> 316
    //   312: invokestatic a : (Ljava/lang/Throwable;)Ljava/lang/Throwable;
    //   315: athrow
    //   316: aload_3
    //   317: getstatic burp/Zgil.ZK : Ljava/lang/String;
    //   320: getstatic burp/Zts_.ZH : Ljava/lang/Object;
    //   323: checkcast java/math/BigInteger
    //   326: invokevirtual intValue : ()I
    //   329: bipush #32
    //   331: irem
    //   332: invokestatic abs : (I)I
    //   335: invokevirtual charAt : (I)C
    //   338: invokevirtual append : (C)Ljava/lang/StringBuilder;
    //   341: pop
    //   342: iload_2
    //   343: ifeq -> 1348
    //   346: goto -> 353
    //   349: invokestatic a : (Ljava/lang/Throwable;)Ljava/lang/Throwable;
    //   352: athrow
    //   353: aload_3
    //   354: getstatic burp/Zm0v.Zd : Ljava/lang/String;
    //   357: getstatic burp/Zlfg.Zv : Ljava/lang/Object;
    //   360: checkcast java/math/BigInteger
    //   363: invokevirtual intValue : ()I
    //   366: bipush #32
    //   368: irem
    //   369: invokestatic abs : (I)I
    //   372: invokevirtual charAt : (I)C
    //   375: invokevirtual append : (C)Ljava/lang/StringBuilder;
    //   378: pop
    //   379: iload_2
    //   380: ifeq -> 1348
    //   383: goto -> 390
    //   386: invokestatic a : (Ljava/lang/Throwable;)Ljava/lang/Throwable;
    //   389: athrow
    //   390: aload_3
    //   391: getstatic burp/Zep8.ZC : Ljava/lang/String;
    //   394: getstatic burp/Zstq.Zf : Ljava/lang/Object;
    //   397: checkcast java/math/BigInteger
    //   400: invokevirtual intValue : ()I
    //   403: bipush #32
    //   405: irem
    //   406: invokestatic abs : (I)I
    //   409: invokevirtual charAt : (I)C
    //   412: invokevirtual append : (C)Ljava/lang/StringBuilder;
    //   415: pop
    //   416: iload_2
    //   417: ifeq -> 1348
    //   420: goto -> 427
    //   423: invokestatic a : (Ljava/lang/Throwable;)Ljava/lang/Throwable;
    //   426: athrow
    //   427: aload_3
    //   428: getstatic burp/Zluk.ZW : Ljava/lang/String;
    //   431: getstatic burp/Zep8.Zs : Ljava/lang/Object;
    //   434: checkcast java/math/BigInteger
    //   437: invokevirtual intValue : ()I
    //   440: bipush #32
    //   442: irem
    //   443: invokestatic abs : (I)I
    //   446: invokevirtual charAt : (I)C
    //   449: invokevirtual append : (C)Ljava/lang/StringBuilder;
    //   452: pop
    //   453: iload_2
    //   454: ifeq -> 1348
    //   457: goto -> 464
    //   460: invokestatic a : (Ljava/lang/Throwable;)Ljava/lang/Throwable;
    //   463: athrow
    //   464: aload_3
    //   465: getstatic burp/Zr_w.Zi : Ljava/lang/String;
    //   468: getstatic burp/Zgz2.Zs : Ljava/lang/Object;
    //   471: checkcast java/math/BigInteger
    //   474: invokevirtual intValue : ()I
    //   477: bipush #32
    //   479: irem
    //   480: invokestatic abs : (I)I
    //   483: invokevirtual charAt : (I)C
    //   486: invokevirtual append : (C)Ljava/lang/StringBuilder;
    //   489: pop
    //   490: iload_2
    //   491: ifeq -> 1348
    //   494: goto -> 501
    //   497: invokestatic a : (Ljava/lang/Throwable;)Ljava/lang/Throwable;
    //   500: athrow
    //   501: aload_3
    //   502: getstatic burp/Zrdo.Zj : Ljava/lang/String;
    //   505: getstatic burp/Zr64.ZN : Ljava/lang/Object;
    //   508: checkcast java/math/BigInteger
    //   511: invokevirtual intValue : ()I
    //   514: bipush #32
    //   516: irem
    //   517: invokestatic abs : (I)I
    //   520: invokevirtual charAt : (I)C
    //   523: invokevirtual append : (C)Ljava/lang/StringBuilder;
    //   526: pop
    //   527: iload_2
    //   528: ifeq -> 1348
    //   531: goto -> 538
    //   534: invokestatic a : (Ljava/lang/Throwable;)Ljava/lang/Throwable;
    //   537: athrow
    //   538: aload_3
    //   539: getstatic burp/Zr_w.Zi : Ljava/lang/String;
    //   542: getstatic burp/Zm0v.ZH : Ljava/lang/Object;
    //   545: checkcast java/math/BigInteger
    //   548: invokevirtual intValue : ()I
    //   551: bipush #32
    //   553: irem
    //   554: invokestatic abs : (I)I
    //   557: invokevirtual charAt : (I)C
    //   560: invokevirtual append : (C)Ljava/lang/StringBuilder;
    //   563: pop
    //   564: iload_2
    //   565: ifeq -> 1348
    //   568: goto -> 575
    //   571: invokestatic a : (Ljava/lang/Throwable;)Ljava/lang/Throwable;
    //   574: athrow
    //   575: aload_3
    //   576: getstatic burp/Zkby.Zf : Ljava/lang/String;
    //   579: getstatic burp/Zgh3.ZZ : Ljava/lang/Object;
    //   582: checkcast java/math/BigInteger
    //   585: invokevirtual intValue : ()I
    //   588: bipush #32
    //   590: irem
    //   591: invokestatic abs : (I)I
    //   594: invokevirtual charAt : (I)C
    //   597: invokevirtual append : (C)Ljava/lang/StringBuilder;
    //   600: pop
    //   601: iload_2
    //   602: ifeq -> 1348
    //   605: goto -> 612
    //   608: invokestatic a : (Ljava/lang/Throwable;)Ljava/lang/Throwable;
    //   611: athrow
    //   612: aload_3
    //   613: getstatic burp/Ze0z.ZU : Ljava/lang/String;
    //   616: getstatic burp/Zep1.ZW : Ljava/lang/Object;
    //   619: checkcast java/math/BigInteger
    //   622: invokevirtual intValue : ()I
    //   625: bipush #32
    //   627: irem
    //   628: invokestatic abs : (I)I
    //   631: invokevirtual charAt : (I)C
    //   634: invokevirtual append : (C)Ljava/lang/StringBuilder;
    //   637: pop
    //   638: iload_2
    //   639: ifeq -> 1348
    //   642: goto -> 649
    //   645: invokestatic a : (Ljava/lang/Throwable;)Ljava/lang/Throwable;
    //   648: athrow
    //   649: aload_3
    //   650: getstatic burp/Zeyd.Zr : Ljava/lang/String;
    //   653: getstatic burp/Zx0t.Zt : Ljava/lang/Object;
    //   656: checkcast java/math/BigInteger
    //   659: invokevirtual intValue : ()I
    //   662: bipush #32
    //   664: irem
    //   665: invokestatic abs : (I)I
    //   668: invokevirtual charAt : (I)C
    //   671: invokevirtual append : (C)Ljava/lang/StringBuilder;
    //   674: pop
    //   675: iload_2
    //   676: ifeq -> 1348
    //   679: goto -> 686
    //   682: invokestatic a : (Ljava/lang/Throwable;)Ljava/lang/Throwable;
    //   685: athrow
    //   686: aload_3
    //   687: getstatic burp/Zep1.ZQ : Ljava/lang/String;
    //   690: getstatic burp/Zgqp.Zf : Ljava/lang/Object;
    //   693: checkcast java/math/BigInteger
    //   696: invokevirtual intValue : ()I
    //   699: bipush #32
    //   701: irem
    //   702: invokestatic abs : (I)I
    //   705: invokevirtual charAt : (I)C
    //   708: invokevirtual append : (C)Ljava/lang/StringBuilder;
    //   711: pop
    //   712: iload_2
    //   713: ifeq -> 1348
    //   716: goto -> 723
    //   719: invokestatic a : (Ljava/lang/Throwable;)Ljava/lang/Throwable;
    //   722: athrow
    //   723: aload_3
    //   724: getstatic burp/Zl55.Zp : Ljava/lang/String;
    //   727: getstatic burp/Zgk1.ZD : Ljava/lang/Object;
    //   730: checkcast java/math/BigInteger
    //   733: invokevirtual intValue : ()I
    //   736: bipush #32
    //   738: irem
    //   739: invokestatic abs : (I)I
    //   742: invokevirtual charAt : (I)C
    //   745: invokevirtual append : (C)Ljava/lang/StringBuilder;
    //   748: pop
    //   749: iload_2
    //   750: ifeq -> 1348
    //   753: goto -> 760
    //   756: invokestatic a : (Ljava/lang/Throwable;)Ljava/lang/Throwable;
    //   759: athrow
    //   760: aload_3
    //   761: getstatic burp/Zgz2.ZI : Ljava/lang/String;
    //   764: getstatic burp/Zr_w.ZK : Ljava/lang/Object;
    //   767: checkcast java/math/BigInteger
    //   770: invokevirtual intValue : ()I
    //   773: bipush #32
    //   775: irem
    //   776: invokestatic abs : (I)I
    //   779: invokevirtual charAt : (I)C
    //   782: invokevirtual append : (C)Ljava/lang/StringBuilder;
    //   785: pop
    //   786: iload_2
    //   787: ifeq -> 1348
    //   790: goto -> 797
    //   793: invokestatic a : (Ljava/lang/Throwable;)Ljava/lang/Throwable;
    //   796: athrow
    //   797: aload_3
    //   798: getstatic burp/Zg_y.ZF : Ljava/lang/String;
    //   801: getstatic burp/Zr64.ZN : Ljava/lang/Object;
    //   804: checkcast java/math/BigInteger
    //   807: invokevirtual intValue : ()I
    //   810: bipush #32
    //   812: irem
    //   813: invokestatic abs : (I)I
    //   816: invokevirtual charAt : (I)C
    //   819: invokevirtual append : (C)Ljava/lang/StringBuilder;
    //   822: pop
    //   823: iload_2
    //   824: ifeq -> 1348
    //   827: goto -> 834
    //   830: invokestatic a : (Ljava/lang/Throwable;)Ljava/lang/Throwable;
    //   833: athrow
    //   834: aload_3
    //   835: getstatic burp/Zrqd.Zk : Ljava/lang/String;
    //   838: getstatic burp/Zep8.Zs : Ljava/lang/Object;
    //   841: checkcast java/math/BigInteger
    //   844: invokevirtual intValue : ()I
    //   847: bipush #32
    //   849: irem
    //   850: invokestatic abs : (I)I
    //   853: invokevirtual charAt : (I)C
    //   856: invokevirtual append : (C)Ljava/lang/StringBuilder;
    //   859: pop
    //   860: iload_2
    //   861: ifeq -> 1348
    //   864: goto -> 871
    //   867: invokestatic a : (Ljava/lang/Throwable;)Ljava/lang/Throwable;
    //   870: athrow
    //   871: aload_3
    //   872: getstatic burp/Zkby.Zf : Ljava/lang/String;
    //   875: getstatic burp/Zlhk.ZD : Ljava/lang/Object;
    //   878: checkcast java/math/BigInteger
    //   881: invokevirtual intValue : ()I
    //   884: bipush #32
    //   886: irem
    //   887: invokestatic abs : (I)I
    //   890: invokevirtual charAt : (I)C
    //   893: invokevirtual append : (C)Ljava/lang/StringBuilder;
    //   896: pop
    //   897: iload_2
    //   898: ifeq -> 1348
    //   901: goto -> 908
    //   904: invokestatic a : (Ljava/lang/Throwable;)Ljava/lang/Throwable;
    //   907: athrow
    //   908: aload_3
    //   909: getstatic burp/Zb1.Z_ : Ljava/lang/String;
    //   912: getstatic burp/Zmwu.Zy : Ljava/lang/Object;
    //   915: checkcast java/math/BigInteger
    //   918: invokevirtual intValue : ()I
    //   921: bipush #32
    //   923: irem
    //   924: invokestatic abs : (I)I
    //   927: invokevirtual charAt : (I)C
    //   930: invokevirtual append : (C)Ljava/lang/StringBuilder;
    //   933: pop
    //   934: iload_2
    //   935: ifeq -> 1348
    //   938: goto -> 945
    //   941: invokestatic a : (Ljava/lang/Throwable;)Ljava/lang/Throwable;
    //   944: athrow
    //   945: aload_3
    //   946: getstatic burp/Zlhk.Zb : Ljava/lang/String;
    //   949: getstatic burp/Zb9d.Ze : Ljava/lang/Object;
    //   952: checkcast java/math/BigInteger
    //   955: invokevirtual intValue : ()I
    //   958: bipush #32
    //   960: irem
    //   961: invokestatic abs : (I)I
    //   964: invokevirtual charAt : (I)C
    //   967: invokevirtual append : (C)Ljava/lang/StringBuilder;
    //   970: pop
    //   971: iload_2
    //   972: ifeq -> 1348
    //   975: goto -> 982
    //   978: invokestatic a : (Ljava/lang/Throwable;)Ljava/lang/Throwable;
    //   981: athrow
    //   982: aload_3
    //   983: getstatic burp/Zkby.Zf : Ljava/lang/String;
    //   986: getstatic burp/Zgk1.ZD : Ljava/lang/Object;
    //   989: checkcast java/math/BigInteger
    //   992: invokevirtual intValue : ()I
    //   995: bipush #32
    //   997: irem
    //   998: invokestatic abs : (I)I
    //   1001: invokevirtual charAt : (I)C
    //   1004: invokevirtual append : (C)Ljava/lang/StringBuilder;
    //   1007: pop
    //   1008: iload_2
    //   1009: ifeq -> 1348
    //   1012: goto -> 1019
    //   1015: invokestatic a : (Ljava/lang/Throwable;)Ljava/lang/Throwable;
    //   1018: athrow
    //   1019: aload_3
    //   1020: getstatic burp/Ztvn.ZU : Ljava/lang/String;
    //   1023: getstatic burp/Zg_i.ZQ : Ljava/lang/Object;
    //   1026: checkcast java/math/BigInteger
    //   1029: invokevirtual intValue : ()I
    //   1032: bipush #32
    //   1034: irem
    //   1035: invokestatic abs : (I)I
    //   1038: invokevirtual charAt : (I)C
    //   1041: invokevirtual append : (C)Ljava/lang/StringBuilder;
    //   1044: pop
    //   1045: iload_2
    //   1046: ifeq -> 1348
    //   1049: goto -> 1056
    //   1052: invokestatic a : (Ljava/lang/Throwable;)Ljava/lang/Throwable;
    //   1055: athrow
    //   1056: aload_3
    //   1057: getstatic burp/Zxz_.Zb : Ljava/lang/String;
    //   1060: getstatic burp/Zgl4.Zb : Ljava/lang/Object;
    //   1063: checkcast java/math/BigInteger
    //   1066: invokevirtual intValue : ()I
    //   1069: bipush #32
    //   1071: irem
    //   1072: invokestatic abs : (I)I
    //   1075: invokevirtual charAt : (I)C
    //   1078: invokevirtual append : (C)Ljava/lang/StringBuilder;
    //   1081: pop
    //   1082: iload_2
    //   1083: ifeq -> 1348
    //   1086: goto -> 1093
    //   1089: invokestatic a : (Ljava/lang/Throwable;)Ljava/lang/Throwable;
    //   1092: athrow
    //   1093: aload_3
    //   1094: getstatic burp/Zl8l.ZG : Ljava/lang/String;
    //   1097: getstatic burp/Zkor.Ze : Ljava/lang/Object;
    //   1100: checkcast java/math/BigInteger
    //   1103: invokevirtual intValue : ()I
    //   1106: bipush #32
    //   1108: irem
    //   1109: invokestatic abs : (I)I
    //   1112: invokevirtual charAt : (I)C
    //   1115: invokevirtual append : (C)Ljava/lang/StringBuilder;
    //   1118: pop
    //   1119: iload_2
    //   1120: ifeq -> 1348
    //   1123: goto -> 1130
    //   1126: invokestatic a : (Ljava/lang/Throwable;)Ljava/lang/Throwable;
    //   1129: athrow
    //   1130: aload_3
    //   1131: getstatic burp/Zrc0.ZL : Ljava/lang/String;
    //   1134: getstatic burp/Zge1.ZK : Ljava/lang/Object;
    //   1137: checkcast java/math/BigInteger
    //   1140: invokevirtual intValue : ()I
    //   1143: bipush #32
    //   1145: irem
    //   1146: invokestatic abs : (I)I
    //   1149: invokevirtual charAt : (I)C
    //   1152: invokevirtual append : (C)Ljava/lang/StringBuilder;
    //   1155: pop
    //   1156: iload_2
    //   1157: ifeq -> 1348
    //   1160: goto -> 1167
    //   1163: invokestatic a : (Ljava/lang/Throwable;)Ljava/lang/Throwable;
    //   1166: athrow
    //   1167: aload_3
    //   1168: getstatic burp/Zeoa.Zn : Ljava/lang/String;
    //   1171: getstatic burp/Zm6g.ZO : Ljava/lang/Object;
    //   1174: checkcast java/math/BigInteger
    //   1177: invokevirtual intValue : ()I
    //   1180: bipush #32
    //   1182: irem
    //   1183: invokestatic abs : (I)I
    //   1186: invokevirtual charAt : (I)C
    //   1189: invokevirtual append : (C)Ljava/lang/StringBuilder;
    //   1192: pop
    //   1193: iload_2
    //   1194: ifeq -> 1348
    //   1197: goto -> 1204
    //   1200: invokestatic a : (Ljava/lang/Throwable;)Ljava/lang/Throwable;
    //   1203: athrow
    //   1204: aload_3
    //   1205: getstatic burp/Zg_y.ZF : Ljava/lang/String;
    //   1208: getstatic burp/Zgk1.ZD : Ljava/lang/Object;
    //   1211: checkcast java/math/BigInteger
    //   1214: invokevirtual intValue : ()I
    //   1217: bipush #32
    //   1219: irem
    //   1220: invokestatic abs : (I)I
    //   1223: invokevirtual charAt : (I)C
    //   1226: invokevirtual append : (C)Ljava/lang/StringBuilder;
    //   1229: pop
    //   1230: iload_2
    //   1231: ifeq -> 1348
    //   1234: goto -> 1241
    //   1237: invokestatic a : (Ljava/lang/Throwable;)Ljava/lang/Throwable;
    //   1240: athrow
    //   1241: aload_3
    //   1242: getstatic burp/Ze6t.ZR : Ljava/lang/String;
    //   1245: getstatic burp/Zm0v.ZH : Ljava/lang/Object;
    //   1248: checkcast java/math/BigInteger
    //   1251: invokevirtual intValue : ()I
    //   1254: bipush #32
    //   1256: irem
    //   1257: invokestatic abs : (I)I
    //   1260: invokevirtual charAt : (I)C
    //   1263: invokevirtual append : (C)Ljava/lang/StringBuilder;
    //   1266: pop
    //   1267: iload_2
    //   1268: ifeq -> 1348
    //   1271: goto -> 1278
    //   1274: invokestatic a : (Ljava/lang/Throwable;)Ljava/lang/Throwable;
    //   1277: athrow
    //   1278: aload_3
    //   1279: getstatic burp/Zmcb.Zl : Ljava/lang/String;
    //   1282: getstatic burp/Zlfg.Zv : Ljava/lang/Object;
    //   1285: checkcast java/math/BigInteger
    //   1288: invokevirtual intValue : ()I
    //   1291: bipush #32
    //   1293: irem
    //   1294: invokestatic abs : (I)I
    //   1297: invokevirtual charAt : (I)C
    //   1300: invokevirtual append : (C)Ljava/lang/StringBuilder;
    //   1303: pop
    //   1304: iload_2
    //   1305: ifeq -> 1348
    //   1308: goto -> 1315
    //   1311: invokestatic a : (Ljava/lang/Throwable;)Ljava/lang/Throwable;
    //   1314: athrow
    //   1315: aload_3
    //   1316: getstatic burp/Zxzt.ZG : Ljava/lang/String;
    //   1319: getstatic burp/Zsvh.Zv : Ljava/lang/Object;
    //   1322: checkcast java/math/BigInteger
    //   1325: invokevirtual intValue : ()I
    //   1328: bipush #32
    //   1330: irem
    //   1331: invokestatic abs : (I)I
    //   1334: invokevirtual charAt : (I)C
    //   1337: invokevirtual append : (C)Ljava/lang/StringBuilder;
    //   1340: pop
    //   1341: goto -> 1348
    //   1344: invokestatic a : (Ljava/lang/Throwable;)Ljava/lang/Throwable;
    //   1347: athrow
    //   1348: iinc #4, 1
    //   1351: iload_2
    //   1352: ifeq -> 15
    //   1355: aload_3
    //   1356: invokevirtual toString : ()Ljava/lang/String;
    //   1359: putstatic burp/Zg3v.Zt : Ljava/lang/String;
    //   1362: getstatic burp/Zm0v.ZH : Ljava/lang/Object;
    //   1365: checkcast java/math/BigInteger
    //   1368: invokevirtual toByteArray : ()[B
    //   1371: astore #4
    //   1373: aload #4
    //   1375: arraylength
    //   1376: iconst_2
    //   1377: iadd
    //   1378: newarray byte
    //   1380: astore #6
    //   1382: iconst_0
    //   1383: istore #7
    //   1385: iload #7
    //   1387: aload #4
    //   1389: arraylength
    //   1390: if_icmpge -> 1410
    //   1393: aload #6
    //   1395: iload #7
    //   1397: aload #4
    //   1399: iload #7
    //   1401: baload
    //   1402: bastore
    //   1403: iinc #7, 1
    //   1406: iload_2
    //   1407: ifeq -> 1385
    //   1410: aload #6
    //   1412: arraylength
    //   1413: iconst_3
    //   1414: idiv
    //   1415: iconst_4
    //   1416: imul
    //   1417: newarray byte
    //   1419: astore #5
    //   1421: iconst_0
    //   1422: istore #7
    //   1424: iconst_0
    //   1425: istore #8
    //   1427: iload #7
    //   1429: aload #4
    //   1431: arraylength
    //   1432: if_icmpge -> 1543
    //   1435: aload #5
    //   1437: iload #8
    //   1439: aload #6
    //   1441: iload #7
    //   1443: baload
    //   1444: iconst_2
    //   1445: iushr
    //   1446: bipush #63
    //   1448: iand
    //   1449: i2b
    //   1450: bastore
    //   1451: aload #5
    //   1453: iload #8
    //   1455: iconst_1
    //   1456: iadd
    //   1457: aload #6
    //   1459: iload #7
    //   1461: iconst_1
    //   1462: iadd
    //   1463: baload
    //   1464: iconst_4
    //   1465: iushr
    //   1466: bipush #15
    //   1468: iand
    //   1469: aload #6
    //   1471: iload #7
    //   1473: baload
    //   1474: iconst_4
    //   1475: ishl
    //   1476: bipush #63
    //   1478: iand
    //   1479: ior
    //   1480: i2b
    //   1481: bastore
    //   1482: aload #5
    //   1484: iload #8
    //   1486: iconst_2
    //   1487: iadd
    //   1488: aload #6
    //   1490: iload #7
    //   1492: iconst_2
    //   1493: iadd
    //   1494: baload
    //   1495: bipush #6
    //   1497: iushr
    //   1498: iconst_3
    //   1499: iand
    //   1500: aload #6
    //   1502: iload #7
    //   1504: iconst_1
    //   1505: iadd
    //   1506: baload
    //   1507: iconst_2
    //   1508: ishl
    //   1509: bipush #63
    //   1511: iand
    //   1512: ior
    //   1513: i2b
    //   1514: bastore
    //   1515: aload #5
    //   1517: iload #8
    //   1519: iconst_3
    //   1520: iadd
    //   1521: aload #6
    //   1523: iload #7
    //   1525: iconst_2
    //   1526: iadd
    //   1527: baload
    //   1528: bipush #63
    //   1530: iand
    //   1531: i2b
    //   1532: bastore
    //   1533: iinc #7, 3
    //   1536: iinc #8, 4
    //   1539: iload_2
    //   1540: ifeq -> 1427
    //   1543: iconst_0
    //   1544: istore #7
    //   1546: iload #7
    //   1548: aload #5
    //   1550: arraylength
    //   1551: if_icmpge -> 1735
    //   1554: aload #5
    //   1556: iload #7
    //   1558: baload
    //   1559: bipush #26
    //   1561: if_icmpge -> 1589
    //   1564: aload #5
    //   1566: iload #7
    //   1568: aload #5
    //   1570: iload #7
    //   1572: baload
    //   1573: bipush #65
    //   1575: iadd
    //   1576: i2b
    //   1577: bastore
    //   1578: iload_2
    //   1579: ifeq -> 1728
    //   1582: goto -> 1589
    //   1585: invokestatic a : (Ljava/lang/Throwable;)Ljava/lang/Throwable;
    //   1588: athrow
    //   1589: aload #5
    //   1591: iload #7
    //   1593: baload
    //   1594: bipush #52
    //   1596: if_icmpge -> 1634
    //   1599: goto -> 1606
    //   1602: invokestatic a : (Ljava/lang/Throwable;)Ljava/lang/Throwable;
    //   1605: athrow
    //   1606: aload #5
    //   1608: iload #7
    //   1610: aload #5
    //   1612: iload #7
    //   1614: baload
    //   1615: bipush #97
    //   1617: iadd
    //   1618: bipush #26
    //   1620: isub
    //   1621: i2b
    //   1622: bastore
    //   1623: iload_2
    //   1624: ifeq -> 1728
    //   1627: goto -> 1634
    //   1630: invokestatic a : (Ljava/lang/Throwable;)Ljava/lang/Throwable;
    //   1633: athrow
    //   1634: aload #5
    //   1636: iload #7
    //   1638: baload
    //   1639: bipush #62
    //   1641: if_icmpge -> 1679
    //   1644: goto -> 1651
    //   1647: invokestatic a : (Ljava/lang/Throwable;)Ljava/lang/Throwable;
    //   1650: athrow
    //   1651: aload #5
    //   1653: iload #7
    //   1655: aload #5
    //   1657: iload #7
    //   1659: baload
    //   1660: bipush #48
    //   1662: iadd
    //   1663: bipush #52
    //   1665: isub
    //   1666: i2b
    //   1667: bastore
    //   1668: iload_2
    //   1669: ifeq -> 1728
    //   1672: goto -> 1679
    //   1675: invokestatic a : (Ljava/lang/Throwable;)Ljava/lang/Throwable;
    //   1678: athrow
    //   1679: aload #5
    //   1681: iload #7
    //   1683: baload
    //   1684: bipush #63
    //   1686: if_icmpge -> 1714
    //   1689: goto -> 1696
    //   1692: invokestatic a : (Ljava/lang/Throwable;)Ljava/lang/Throwable;
    //   1695: athrow
    //   1696: aload #5
    //   1698: iload #7
    //   1700: bipush #43
    //   1702: bastore
    //   1703: iload_2
    //   1704: ifeq -> 1728
    //   1707: goto -> 1714
    //   1710: invokestatic a : (Ljava/lang/Throwable;)Ljava/lang/Throwable;
    //   1713: athrow
    //   1714: aload #5
    //   1716: iload #7
    //   1718: bipush #47
    //   1720: bastore
    //   1721: goto -> 1728
    //   1724: invokestatic a : (Ljava/lang/Throwable;)Ljava/lang/Throwable;
    //   1727: athrow
    //   1728: iinc #7, 1
    //   1731: iload_2
    //   1732: ifeq -> 1546
    //   1735: aload #5
    //   1737: arraylength
    //   1738: iconst_1
    //   1739: isub
    //   1740: istore #7
    //   1742: iload #7
    //   1744: aload #4
    //   1746: arraylength
    //   1747: iconst_4
    //   1748: imul
    //   1749: iconst_3
    //   1750: idiv
    //   1751: if_icmple -> 1768
    //   1754: aload #5
    //   1756: iload #7
    //   1758: bipush #61
    //   1760: bastore
    //   1761: iinc #7, -1
    //   1764: iload_2
    //   1765: ifeq -> 1742
    //   1768: new java/math/BigInteger
    //   1771: dup
    //   1772: aload #5
    //   1774: invokespecial <init> : ([B)V
    //   1777: invokevirtual abs : ()Ljava/math/BigInteger;
    //   1780: putstatic burp/Zg_y.ZR : Ljava/lang/Object;
    //   1783: getstatic burp/Zgfq.Za : Ljava/lang/Object;
    //   1786: checkcast java/math/BigInteger
    //   1789: invokevirtual toByteArray : ()[B
    //   1792: astore #4
    //   1794: aload #4
    //   1796: arraylength
    //   1797: bipush #8
    //   1799: iadd
    //   1800: bipush #6
    //   1802: ishr
    //   1803: iconst_1
    //   1804: iadd
    //   1805: bipush #16
    //   1807: imul
    //   1808: newarray int
    //   1810: astore #6
    //   1812: iconst_0
    //   1813: istore #7
    //   1815: iload #7
    //   1817: aload #4
    //   1819: arraylength
    //   1820: if_icmpge -> 1864
    //   1823: aload #4
    //   1825: iload #7
    //   1827: baload
    //   1828: sipush #255
    //   1831: iand
    //   1832: istore #8
    //   1834: aload #6
    //   1836: iload #7
    //   1838: iconst_2
    //   1839: ishr
    //   1840: dup2
    //   1841: iaload
    //   1842: iload #8
    //   1844: bipush #24
    //   1846: iload #7
    //   1848: iconst_4
    //   1849: irem
    //   1850: bipush #8
    //   1852: imul
    //   1853: isub
    //   1854: ishl
    //   1855: ior
    //   1856: iastore
    //   1857: iinc #7, 1
    //   1860: iload_2
    //   1861: ifeq -> 1815
    //   1864: aload #6
    //   1866: iload #7
    //   1868: iconst_2
    //   1869: ishr
    //   1870: dup2
    //   1871: iaload
    //   1872: sipush #128
    //   1875: bipush #24
    //   1877: iload #7
    //   1879: iconst_4
    //   1880: irem
    //   1881: bipush #8
    //   1883: imul
    //   1884: isub
    //   1885: ishl
    //   1886: ior
    //   1887: iastore
    //   1888: aload #6
    //   1890: aload #6
    //   1892: arraylength
    //   1893: iconst_1
    //   1894: isub
    //   1895: aload #4
    //   1897: arraylength
    //   1898: bipush #8
    //   1900: imul
    //   1901: iastore
    //   1902: bipush #80
    //   1904: newarray int
    //   1906: astore #8
    //   1908: ldc 1732584193
    //   1910: istore #9
    //   1912: ldc -271733879
    //   1914: istore #10
    //   1916: ldc -1732584194
    //   1918: istore #11
    //   1920: ldc 271733878
    //   1922: istore #12
    //   1924: ldc -1009589776
    //   1926: istore #13
    //   1928: iconst_0
    //   1929: istore #7
    //   1931: iload #7
    //   1933: aload #6
    //   1935: arraylength
    //   1936: if_icmpge -> 2258
    //   1939: iload #9
    //   1941: istore #14
    //   1943: iload #10
    //   1945: istore #15
    //   1947: iload #11
    //   1949: istore #16
    //   1951: iload #12
    //   1953: istore #17
    //   1955: iload #13
    //   1957: istore #18
    //   1959: iconst_0
    //   1960: istore #19
    //   1962: iload #19
    //   1964: bipush #80
    //   1966: if_icmpge -> 2216
    //   1969: iload #19
    //   1971: bipush #16
    //   1973: if_icmpge -> 2000
    //   1976: aload #8
    //   1978: iload #19
    //   1980: aload #6
    //   1982: iload #7
    //   1984: iload #19
    //   1986: iadd
    //   1987: iaload
    //   1988: iastore
    //   1989: iload_2
    //   1990: ifeq -> 2055
    //   1993: goto -> 2000
    //   1996: invokestatic a : (Ljava/lang/Throwable;)Ljava/lang/Throwable;
    //   1999: athrow
    //   2000: aload #8
    //   2002: iload #19
    //   2004: iconst_3
    //   2005: isub
    //   2006: iaload
    //   2007: aload #8
    //   2009: iload #19
    //   2011: bipush #8
    //   2013: isub
    //   2014: iaload
    //   2015: ixor
    //   2016: aload #8
    //   2018: iload #19
    //   2020: bipush #14
    //   2022: isub
    //   2023: iaload
    //   2024: ixor
    //   2025: aload #8
    //   2027: iload #19
    //   2029: bipush #16
    //   2031: isub
    //   2032: iaload
    //   2033: ixor
    //   2034: istore #20
    //   2036: iload #20
    //   2038: iconst_1
    //   2039: ishl
    //   2040: iload #20
    //   2042: bipush #31
    //   2044: iushr
    //   2045: ior
    //   2046: istore #21
    //   2048: aload #8
    //   2050: iload #19
    //   2052: iload #21
    //   2054: iastore
    //   2055: iload #9
    //   2057: iconst_5
    //   2058: ishl
    //   2059: iload #9
    //   2061: bipush #27
    //   2063: iushr
    //   2064: ior
    //   2065: istore #20
    //   2067: iload #20
    //   2069: iload #13
    //   2071: iadd
    //   2072: aload #8
    //   2074: iload #19
    //   2076: iaload
    //   2077: iadd
    //   2078: iload #19
    //   2080: bipush #20
    //   2082: if_icmpge -> 2108
    //   2085: ldc 1518500249
    //   2087: iload #10
    //   2089: iload #11
    //   2091: iand
    //   2092: iload #10
    //   2094: iconst_m1
    //   2095: ixor
    //   2096: iload #12
    //   2098: iand
    //   2099: ior
    //   2100: iadd
    //   2101: goto -> 2178
    //   2104: invokestatic a : (Ljava/lang/Throwable;)Ljava/lang/Throwable;
    //   2107: athrow
    //   2108: iload #19
    //   2110: bipush #40
    //   2112: if_icmpge -> 2133
    //   2115: ldc 1859775393
    //   2117: iload #10
    //   2119: iload #11
    //   2121: ixor
    //   2122: iload #12
    //   2124: ixor
    //   2125: iadd
    //   2126: goto -> 2178
    //   2129: invokestatic a : (Ljava/lang/Throwable;)Ljava/lang/Throwable;
    //   2132: athrow
    //   2133: iload #19
    //   2135: bipush #60
    //   2137: if_icmpge -> 2167
    //   2140: ldc -1894007588
    //   2142: iload #10
    //   2144: iload #11
    //   2146: iand
    //   2147: iload #10
    //   2149: iload #12
    //   2151: iand
    //   2152: ior
    //   2153: iload #11
    //   2155: iload #12
    //   2157: iand
    //   2158: ior
    //   2159: iadd
    //   2160: goto -> 2178
    //   2163: invokestatic a : (Ljava/lang/Throwable;)Ljava/lang/Throwable;
    //   2166: athrow
    //   2167: ldc -899497514
    //   2169: iload #10
    //   2171: iload #11
    //   2173: ixor
    //   2174: iload #12
    //   2176: ixor
    //   2177: iadd
    //   2178: iadd
    //   2179: istore #21
    //   2181: iload #12
    //   2183: istore #13
    //   2185: iload #11
    //   2187: istore #12
    //   2189: iload #10
    //   2191: bipush #30
    //   2193: ishl
    //   2194: iload #10
    //   2196: iconst_2
    //   2197: iushr
    //   2198: ior
    //   2199: istore #11
    //   2201: iload #9
    //   2203: istore #10
    //   2205: iload #21
    //   2207: istore #9
    //   2209: iinc #19, 1
    //   2212: iload_2
    //   2213: ifeq -> 1962
    //   2216: iload #9
    //   2218: iload #14
    //   2220: iadd
    //   2221: istore #9
    //   2223: iload #10
    //   2225: iload #15
    //   2227: iadd
    //   2228: istore #10
    //   2230: iload #11
    //   2232: iload #16
    //   2234: iadd
    //   2235: istore #11
    //   2237: iload #12
    //   2239: iload #17
    //   2241: iadd
    //   2242: istore #12
    //   2244: iload #13
    //   2246: iload #18
    //   2248: iadd
    //   2249: istore #13
    //   2251: iinc #7, 16
    //   2254: iload_2
    //   2255: ifeq -> 1931
    //   2258: iconst_5
    //   2259: newarray int
    //   2261: dup
    //   2262: iconst_0
    //   2263: iload #9
    //   2265: iastore
    //   2266: dup
    //   2267: iconst_1
    //   2268: iload #10
    //   2270: iastore
    //   2271: dup
    //   2272: iconst_2
    //   2273: iload #11
    //   2275: iastore
    //   2276: dup
    //   2277: iconst_3
    //   2278: iload #12
    //   2280: iastore
    //   2281: dup
    //   2282: iconst_4
    //   2283: iload #13
    //   2285: iastore
    //   2286: astore #14
    //   2288: bipush #20
    //   2290: newarray byte
    //   2292: astore #15
    //   2294: iconst_0
    //   2295: istore #16
    //   2297: iload #16
    //   2299: bipush #20
    //   2301: if_icmpge -> 2342
    //   2304: aload #14
    //   2306: iload #16
    //   2308: iconst_4
    //   2309: idiv
    //   2310: iaload
    //   2311: istore #17
    //   2313: iconst_3
    //   2314: iload #16
    //   2316: iconst_4
    //   2317: irem
    //   2318: isub
    //   2319: bipush #8
    //   2321: imul
    //   2322: istore #18
    //   2324: aload #15
    //   2326: iload #16
    //   2328: iload #17
    //   2330: iload #18
    //   2332: iushr
    //   2333: i2b
    //   2334: bastore
    //   2335: iinc #16, 1
    //   2338: iload_2
    //   2339: ifeq -> 2297
    //   2342: aload #15
    //   2344: astore #5
    //   2346: sipush #16568
    //   2349: new java/math/BigInteger
    //   2352: dup
    //   2353: aload #5
    //   2355: invokespecial <init> : ([B)V
    //   2358: invokevirtual abs : ()Ljava/math/BigInteger;
    //   2361: putstatic burp/Zbu6.ZJ : Ljava/lang/Object;
    //   2364: sipush #22226
    //   2367: invokestatic a : (II)Ljava/lang/String;
    //   2370: iconst_1
    //   2371: ldc burp/Zmh5
    //   2373: invokevirtual getClassLoader : ()Ljava/lang/ClassLoader;
    //   2376: invokestatic forName : (Ljava/lang/String;ZLjava/lang/ClassLoader;)Ljava/lang/Class;
    //   2379: invokevirtual getDeclaredFields : ()[Ljava/lang/reflect/Field;
    //   2382: astore #4
    //   2384: aload #4
    //   2386: arraylength
    //   2387: istore #5
    //   2389: iconst_0
    //   2390: istore #6
    //   2392: iload #6
    //   2394: iload #5
    //   2396: if_icmpge -> 2534
    //   2399: aload #4
    //   2401: iload #6
    //   2403: aaload
    //   2404: astore #7
    //   2406: aload #7
    //   2408: invokevirtual getModifiers : ()I
    //   2411: invokestatic isStatic : (I)Z
    //   2414: ifne -> 2424
    //   2417: goto -> 2527
    //   2420: invokestatic a : (Ljava/lang/Throwable;)Ljava/lang/Throwable;
    //   2423: athrow
    //   2424: aload #7
    //   2426: invokevirtual getType : ()Ljava/lang/Class;
    //   2429: astore #8
    //   2431: aload #8
    //   2433: ifnull -> 2514
    //   2436: aload #8
    //   2438: invokevirtual isPrimitive : ()Z
    //   2441: ifne -> 2514
    //   2444: goto -> 2451
    //   2447: invokestatic a : (Ljava/lang/Throwable;)Ljava/lang/Throwable;
    //   2450: athrow
    //   2451: aload #8
    //   2453: invokevirtual getPackage : ()Ljava/lang/Package;
    //   2456: ifnull -> 2514
    //   2459: goto -> 2466
    //   2462: invokestatic a : (Ljava/lang/Throwable;)Ljava/lang/Throwable;
    //   2465: athrow
    //   2466: aload #8
    //   2468: invokevirtual getPackage : ()Ljava/lang/Package;
    //   2471: invokevirtual getName : ()Ljava/lang/String;
    //   2474: ifnull -> 2514
    //   2477: goto -> 2484
    //   2480: invokestatic a : (Ljava/lang/Throwable;)Ljava/lang/Throwable;
    //   2483: athrow
    //   2484: aload #8
    //   2486: invokevirtual getPackage : ()Ljava/lang/Package;
    //   2489: invokevirtual getName : ()Ljava/lang/String;
    //   2492: sipush #16567
    //   2495: sipush #-16657
    //   2498: invokestatic a : (II)Ljava/lang/String;
    //   2501: invokevirtual startsWith : (Ljava/lang/String;)Z
    //   2504: ifne -> 2514
    //   2507: goto -> 2514
    //   2510: invokestatic a : (Ljava/lang/Throwable;)Ljava/lang/Throwable;
    //   2513: athrow
    //   2514: aload #7
    //   2516: iconst_1
    //   2517: invokevirtual setAccessible : (Z)V
    //   2520: aload #7
    //   2522: aconst_null
    //   2523: invokevirtual get : (Ljava/lang/Object;)Ljava/lang/Object;
    //   2526: pop
    //   2527: iinc #6, 1
    //   2530: iload_2
    //   2531: ifeq -> 2392
    //   2534: sipush #16561
    //   2537: sipush #22895
    //   2540: invokestatic a : (II)Ljava/lang/String;
    //   2543: invokestatic forName : (Ljava/lang/String;)Ljava/lang/Class;
    //   2546: invokevirtual getDeclaredMethods : ()[Ljava/lang/reflect/Method;
    //   2549: astore #4
    //   2551: aload #4
    //   2553: arraylength
    //   2554: istore #5
    //   2556: iconst_0
    //   2557: istore #6
    //   2559: iload #6
    //   2561: iload #5
    //   2563: if_icmpge -> 2696
    //   2566: aload #4
    //   2568: iload #6
    //   2570: aaload
    //   2571: astore #7
    //   2573: aload #7
    //   2575: invokevirtual getParameterTypes : ()[Ljava/lang/Class;
    //   2578: pop
    //   2579: aload #7
    //   2581: invokevirtual getModifiers : ()I
    //   2584: invokestatic isStatic : (I)Z
    //   2587: ifeq -> 2682
    //   2590: aload #7
    //   2592: invokevirtual getParameterTypes : ()[Ljava/lang/Class;
    //   2595: arraylength
    //   2596: iconst_2
    //   2597: if_icmpne -> 2682
    //   2600: goto -> 2607
    //   2603: invokestatic a : (Ljava/lang/Throwable;)Ljava/lang/Throwable;
    //   2606: athrow
    //   2607: aload #7
    //   2609: invokevirtual getReturnType : ()Ljava/lang/Class;
    //   2612: getstatic java/lang/Void.TYPE : Ljava/lang/Class;
    //   2615: invokevirtual equals : (Ljava/lang/Object;)Z
    //   2618: ifeq -> 2682
    //   2621: goto -> 2628
    //   2624: invokestatic a : (Ljava/lang/Throwable;)Ljava/lang/Throwable;
    //   2627: athrow
    //   2628: aload #7
    //   2630: iconst_1
    //   2631: invokevirtual setAccessible : (Z)V
    //   2634: aload #7
    //   2636: aconst_null
    //   2637: iconst_2
    //   2638: anewarray java/lang/Object
    //   2641: dup
    //   2642: iconst_0
    //   2643: aload_0
    //   2644: aastore
    //   2645: dup
    //   2646: iconst_1
    //   2647: aload_1
    //   2648: ifnonnull -> 2666
    //   2651: goto -> 2658
    //   2654: invokestatic a : (Ljava/lang/Throwable;)Ljava/lang/Throwable;
    //   2657: athrow
    //   2658: aload_1
    //   2659: goto -> 2673
    //   2662: invokestatic a : (Ljava/lang/Throwable;)Ljava/lang/Throwable;
    //   2665: athrow
    //   2666: aload_1
    //   2667: checkcast [B
    //   2670: invokevirtual clone : ()Ljava/lang/Object;
    //   2673: aastore
    //   2674: invokevirtual invoke : (Ljava/lang/Object;[Ljava/lang/Object;)Ljava/lang/Object;
    //   2677: pop
    //   2678: iload_2
    //   2679: ifeq -> 2696
    //   2682: iinc #6, 1
    //   2685: iload_2
    //   2686: ifeq -> 2559
    //   2689: goto -> 2696
    //   2692: invokestatic a : (Ljava/lang/Throwable;)Ljava/lang/Throwable;
    //   2695: athrow
    //   2696: getstatic burp/Zx0t.Ze : Ljava/lang/String;
    //   2699: getstatic burp/Zluk.Zz : Ljava/lang/Object;
    //   2702: checkcast java/math/BigInteger
    //   2705: invokevirtual intValue : ()I
    //   2708: bipush #32
    //   2710: irem
    //   2711: invokestatic abs : (I)I
    //   2714: invokevirtual charAt : (I)C
    //   2717: getstatic burp/Zmpv.Zb : Ljava/lang/String;
    //   2720: getstatic burp/Zlfg.Zv : Ljava/lang/Object;
    //   2723: checkcast java/math/BigInteger
    //   2726: invokevirtual intValue : ()I
    //   2729: bipush #32
    //   2731: irem
    //   2732: invokestatic abs : (I)I
    //   2735: invokevirtual charAt : (I)C
    //   2738: if_icmple -> 2853
    //   2741: getstatic burp/Zm3s.Ze : Ljava/lang/String;
    //   2744: getstatic burp/Zrug.Zp : Ljava/lang/Object;
    //   2747: checkcast java/math/BigInteger
    //   2750: invokevirtual intValue : ()I
    //   2753: bipush #32
    //   2755: irem
    //   2756: invokestatic abs : (I)I
    //   2759: invokevirtual charAt : (I)C
    //   2762: getstatic burp/Zmwx.ZB : Ljava/lang/String;
    //   2765: getstatic burp/Zlqy.ZP : Ljava/lang/Object;
    //   2768: checkcast java/math/BigInteger
    //   2771: invokevirtual intValue : ()I
    //   2774: bipush #32
    //   2776: irem
    //   2777: invokestatic abs : (I)I
    //   2780: invokevirtual charAt : (I)C
    //   2783: if_icmpgt -> 2853
    //   2786: goto -> 2793
    //   2789: invokestatic a : (Ljava/lang/Throwable;)Ljava/lang/Throwable;
    //   2792: athrow
    //   2793: getstatic burp/Zsji.Zr : Ljava/lang/String;
    //   2796: getstatic burp/Zgmo.Zo : Ljava/lang/Object;
    //   2799: checkcast java/math/BigInteger
    //   2802: invokevirtual intValue : ()I
    //   2805: bipush #32
    //   2807: irem
    //   2808: invokestatic abs : (I)I
    //   2811: invokevirtual charAt : (I)C
    //   2814: getstatic burp/Zxti.ZD : Ljava/lang/String;
    //   2817: getstatic burp/Zmjw.ZD : Ljava/lang/Object;
    //   2820: checkcast java/math/BigInteger
    //   2823: invokevirtual intValue : ()I
    //   2826: bipush #32
    //   2828: irem
    //   2829: invokestatic abs : (I)I
    //   2832: invokevirtual charAt : (I)C
    //   2835: if_icmple -> 2853
    //   2838: goto -> 2845
    //   2841: invokestatic a : (Ljava/lang/Throwable;)Ljava/lang/Throwable;
    //   2844: athrow
    //   2845: iconst_1
    //   2846: goto -> 2854
    //   2849: invokestatic a : (Ljava/lang/Throwable;)Ljava/lang/Throwable;
    //   2852: athrow
    //   2853: iconst_0
    //   2854: ireturn
    //   2855: astore_3
    //   2856: new java/lang/Exception
    //   2859: dup
    //   2860: aload_3
    //   2861: invokevirtual getMessage : ()Ljava/lang/String;
    //   2864: invokespecial <init> : (Ljava/lang/String;)V
    //   2867: athrow
    // Exception table:
    //   from	to	target	type
    //   4	2854	2855	java/lang/Throwable
    //   22	198	201	java/lang/Throwable
    //   168	235	238	java/lang/Throwable
    //   205	272	275	java/lang/Throwable
    //   242	309	312	java/lang/Throwable
    //   279	346	349	java/lang/Throwable
    //   316	383	386	java/lang/Throwable
    //   353	420	423	java/lang/Throwable
    //   390	457	460	java/lang/Throwable
    //   427	494	497	java/lang/Throwable
    //   464	531	534	java/lang/Throwable
    //   501	568	571	java/lang/Throwable
    //   538	605	608	java/lang/Throwable
    //   575	642	645	java/lang/Throwable
    //   612	679	682	java/lang/Throwable
    //   649	716	719	java/lang/Throwable
    //   686	753	756	java/lang/Throwable
    //   723	790	793	java/lang/Throwable
    //   760	827	830	java/lang/Throwable
    //   797	864	867	java/lang/Throwable
    //   834	901	904	java/lang/Throwable
    //   871	938	941	java/lang/Throwable
    //   908	975	978	java/lang/Throwable
    //   945	1012	1015	java/lang/Throwable
    //   982	1049	1052	java/lang/Throwable
    //   1019	1086	1089	java/lang/Throwable
    //   1056	1123	1126	java/lang/Throwable
    //   1093	1160	1163	java/lang/Throwable
    //   1130	1197	1200	java/lang/Throwable
    //   1167	1234	1237	java/lang/Throwable
    //   1204	1271	1274	java/lang/Throwable
    //   1241	1308	1311	java/lang/Throwable
    //   1278	1341	1344	java/lang/Throwable
    //   1554	1582	1585	java/lang/Throwable
    //   1564	1599	1602	java/lang/Throwable
    //   1589	1627	1630	java/lang/Throwable
    //   1606	1644	1647	java/lang/Throwable
    //   1634	1672	1675	java/lang/Throwable
    //   1651	1689	1692	java/lang/Throwable
    //   1679	1707	1710	java/lang/Throwable
    //   1696	1721	1724	java/lang/Throwable
    //   1969	1993	1996	java/lang/Throwable
    //   2067	2104	2104	java/lang/Throwable
    //   2108	2129	2129	java/lang/Throwable
    //   2133	2163	2163	java/lang/Throwable
    //   2406	2420	2420	java/lang/Throwable
    //   2431	2444	2447	java/lang/Throwable
    //   2436	2459	2462	java/lang/Throwable
    //   2451	2477	2480	java/lang/Throwable
    //   2466	2507	2510	java/lang/Throwable
    //   2573	2600	2603	java/lang/Throwable
    //   2590	2621	2624	java/lang/Throwable
    //   2607	2651	2654	java/lang/Throwable
    //   2628	2662	2662	java/lang/Throwable
    //   2673	2689	2692	java/lang/Throwable
    //   2696	2786	2789	java/lang/Throwable
    //   2741	2838	2841	java/lang/Throwable
    //   2793	2849	2849	java/lang/Throwable
  }
  
  static void ZX(Object paramObject) {
    Zk52.ZL = a(16562, 14935);
    Zk52.Zu = new BigInteger(a(16564, -29568));
    boolean bool = Zt2e.ZN();
    try {
      try {
        if (Zmwu.ZM.charAt(Math.abs(((BigInteger)Ze6t.Zu).intValue() % 32)) > Zmwu.ZM.charAt(Math.abs(((BigInteger)Zgk1.ZD).intValue() % 32))) {
          try {
            Zrye.ZF(Class.forName(a(16563, 16470)));
            if (!bool)
              Zg_i.Zc(Class.forName(a(16566, 19772))); 
          } catch (Throwable throwable) {
            throw a(null);
          } 
          return;
        } 
      } catch (Throwable throwable) {
        throw a(null);
      } 
      Zg_i.Zc(Class.forName(a(16566, 19772)));
    } catch (Throwable throwable) {}
  }
  
  static void Zj(Object[] paramArrayOfObject, Object paramObject) throws Throwable {}
  
  static {
    // Byte code:
    //   0: bipush #9
    //   2: anewarray java/lang/String
    //   5: astore #5
    //   7: iconst_0
    //   8: istore_3
    //   9: ldc '[Â›N]uÂ¼C7IÃ´CÃw[sÃ &YÂ·Â4ÂŒÃµÃ¸Â˜Ã¥Ã£\\tÃ²Ã¢;ÂšÃÃ•Ã‚ÂY Â«Ã°\\rÃœÃºÂ¡Ã¼)XÃ¾HCÂœÂ±ÂÂ–<*Ã›Â›ÃˆÃ·(BbÂŒÂ³Ã¤\\tÂ·Â¿Â“1Ã‹Â kcRMÂ—Â‰Ã¯;ÂªÃ´\\rÂ½g>@Ã¶tÂ‡Â’"Ã—qÂŒÃºhÂ &ÂF5Â¡\\fÃÃ³\\t6Âªk|Ã·Ã¾jÃ€eÂ—*}Ã²Ã¶<Ã”$J8Ã•\Â°Ã‚Ã·Â¡EÂ¢<Ã‹IL^]Ã¯Ã‰Â»ÃM_Ã±Ã·Ã°Â³Â¶\\tÃ¶\\t}Â¥ÃœÃˆÃ†Âƒ>Ã›B.:|;Ã£Ã„Ã§$eÃ›Â´Â#M8ÃŒÃªÂš.LÂ›Ã¾Ã„]Ã¼Â¸ÂŸ^^8Â•ÃL4Ã‹GÃ tÃ€Ã°QÃÃªÂˆÃªÂŒoÂ»Ã†Â¸\\t$Ã«Ã¡Â»Â…Ã±Â´Go'
    //   11: dup
    //   12: astore_2
    //   13: invokevirtual length : ()I
    //   16: istore #4
    //   18: bipush #32
    //   20: istore_1
    //   21: iconst_m1
    //   22: istore_0
    //   23: iconst_3
    //   24: iinc #0, 1
    //   27: aload_2
    //   28: iload_0
    //   29: dup
    //   30: iload_1
    //   31: iadd
    //   32: invokevirtual substring : (II)Ljava/lang/String;
    //   35: iconst_m1
    //   36: goto -> 141
    //   39: aload #5
    //   41: swap
    //   42: iload_3
    //   43: iinc #3, 1
    //   46: swap
    //   47: aastore
    //   48: iload_0
    //   49: iload_1
    //   50: iadd
    //   51: dup
    //   52: istore_0
    //   53: iload #4
    //   55: if_icmpge -> 67
    //   58: aload_2
    //   59: iload_0
    //   60: invokevirtual charAt : (I)C
    //   63: istore_1
    //   64: goto -> 23
    //   67: ldc 'Ã®Ã—Ã‰\\tÃ¾DhÂœfÃ‡3'
    //   69: dup
    //   70: astore_2
    //   71: invokevirtual length : ()I
    //   74: istore #4
    //   76: iconst_4
    //   77: istore_1
    //   78: iconst_m1
    //   79: istore_0
    //   80: bipush #126
    //   82: iinc #0, 1
    //   85: aload_2
    //   86: iload_0
    //   87: dup
    //   88: iload_1
    //   89: iadd
    //   90: invokevirtual substring : (II)Ljava/lang/String;
    //   93: iconst_0
    //   94: goto -> 141
    //   97: aload #5
    //   99: swap
    //   100: iload_3
    //   101: iinc #3, 1
    //   104: swap
    //   105: aastore
    //   106: iload_0
    //   107: iload_1
    //   108: iadd
    //   109: dup
    //   110: istore_0
    //   111: iload #4
    //   113: if_icmpge -> 125
    //   116: aload_2
    //   117: iload_0
    //   118: invokevirtual charAt : (I)C
    //   121: istore_1
    //   122: goto -> 80
    //   125: aload #5
    //   127: putstatic burp/Zbu6.a : [Ljava/lang/String;
    //   130: bipush #9
    //   132: anewarray java/lang/String
    //   135: putstatic burp/Zbu6.b : [Ljava/lang/String;
    //   138: goto -> 300
    //   141: dup_x2
    //   142: pop
    //   143: invokevirtual toCharArray : ()[C
    //   146: dup_x1
    //   147: arraylength
    //   148: dup_x2
    //   149: pop
    //   150: iconst_0
    //   151: istore #6
    //   153: dup2_x1
    //   154: pop2
    //   155: dup_x2
    //   156: iconst_1
    //   157: if_icmpgt -> 260
    //   160: dup2
    //   161: swap
    //   162: iload #6
    //   164: dup2_x1
    //   165: caload
    //   166: swap
    //   167: iload #6
    //   169: bipush #7
    //   171: irem
    //   172: tableswitch default -> 242, 0 -> 212, 1 -> 217, 2 -> 222, 3 -> 227, 4 -> 232, 5 -> 237
    //   212: bipush #49
    //   214: goto -> 244
    //   217: bipush #24
    //   219: goto -> 244
    //   222: bipush #124
    //   224: goto -> 244
    //   227: bipush #13
    //   229: goto -> 244
    //   232: bipush #71
    //   234: goto -> 244
    //   237: bipush #96
    //   239: goto -> 244
    //   242: bipush #30
    //   244: ixor
    //   245: ixor
    //   246: i2c
    //   247: castore
    //   248: iinc #6, 1
    //   251: dup
    //   252: ifne -> 260
    //   255: dup2
    //   256: dup_x1
    //   257: goto -> 164
    //   260: dup2_x1
    //   261: pop2
    //   262: dup_x2
    //   263: iload #6
    //   265: if_icmpgt -> 160
    //   268: pop
    //   269: new java/lang/String
    //   272: dup_x1
    //   273: swap
    //   274: invokespecial <init> : ([C)V
    //   277: invokevirtual intern : ()Ljava/lang/String;
    //   280: swap
    //   281: pop
    //   282: swap
    //   283: tableswitch default -> 39, 0 -> 97
    //   300: new java/math/BigInteger
    //   303: dup
    //   304: sipush #16565
    //   307: sipush #-4758
    //   310: invokestatic a : (II)Ljava/lang/String;
    //   313: invokespecial <init> : (Ljava/lang/String;)V
    //   316: putstatic burp/Zbu6.ZJ : Ljava/lang/Object;
    //   319: sipush #16560
    //   322: sipush #-27154
    //   325: invokestatic a : (II)Ljava/lang/String;
    //   328: putstatic burp/Zbu6.ZQ : Ljava/lang/String;
    //   331: return
  }
  
  private static Throwable a(Throwable paramThrowable) {
    return paramThrowable;
  }
  
  private static String a(int paramInt1, int paramInt2) {
    int i = (paramInt1 ^ 0x40B0) & 0xFFFF;
    if (b[i] == null) {
      char[] arrayOfChar = a[i].toCharArray();
      switch (arrayOfChar[0] & 0xFF) {
        case 0:
        
        case 1:
        
        case 2:
        
        case 3:
        
        case 4:
        
        case 5:
        
        case 6:
        
        case 7:
        
        case 8:
        
        case 9:
        
        case 10:
        
        case 11:
        
        case 12:
        
        case 13:
        
        case 14:
        
        case 15:
        
        case 16:
        
        case 17:
        
        case 18:
        
        case 19:
        
        case 20:
        
        case 21:
        
        case 22:
        
        case 23:
        
        case 24:
        
        case 25:
        
        case 26:
        
        case 27:
        
        case 28:
        
        case 29:
        
        case 30:
        
        case 31:
        
        case 32:
        
        case 33:
        
        case 34:
        
        case 35:
        
        case 36:
        
        case 37:
        
        case 38:
        
        case 39:
        
        case 40:
        
        case 41:
        
        case 42:
        
        case 43:
        
        case 44:
        
        case 45:
        
        case 46:
        
        case 47:
        
        case 48:
        
        case 49:
        
        case 50:
        
        case 51:
        
        case 52:
        
        case 53:
        
        case 54:
        
        case 55:
        
        case 56:
        
        case 57:
        
        case 58:
        
        case 59:
        
        case 60:
        
        case 61:
        
        case 62:
        
        case 63:
        
        case 64:
        
        case 65:
        
        case 66:
        
        case 67:
        
        case 68:
        
        case 69:
        
        case 70:
        
        case 71:
        
        case 72:
        
        case 73:
        
        case 74:
        
        case 75:
        
        case 76:
        
        case 77:
        
        case 78:
        
        case 79:
        
        case 80:
        
        case 81:
        
        case 82:
        
        case 83:
        
        case 84:
        
        case 85:
        
        case 86:
        
        case 87:
        
        case 88:
        
        case 89:
        
        case 90:
        
        case 91:
        
        case 92:
        
        case 93:
        
        case 94:
        
        case 95:
        
        case 96:
        
        case 97:
        
        case 98:
        
        case 99:
        
        case 100:
        
        case 101:
        
        case 102:
        
        case 103:
        
        case 104:
        
        case 105:
        
        case 106:
        
        case 107:
        
        case 108:
        
        case 109:
        
        case 110:
        
        case 111:
        
        case 112:
        
        case 113:
        
        case 114:
        
        case 115:
        
        case 116:
        
        case 117:
        
        case 118:
        
        case 119:
        
        case 120:
        
        case 121:
        
        case 122:
        
        case 123:
        
        case 124:
        
        case 125:
        
        case 126:
        
        case 127:
        
        case 128:
        
        case 129:
        
        case 130:
        
        case 131:
        
        case 132:
        
        case 133:
        
        case 134:
        
        case 135:
        
        case 136:
        
        case 137:
        
        case 138:
        
        case 139:
        
        case 140:
        
        case 141:
        
        case 142:
        
        case 143:
        
        case 144:
        
        case 145:
        
        case 146:
        
        case 147:
        
        case 148:
        
        case 149:
        
        case 150:
        
        case 151:
        
        case 152:
        
        case 153:
        
        case 154:
        
        case 155:
        
        case 156:
        
        case 157:
        
        case 158:
        
        case 159:
        
        case 160:
        
        case 161:
        
        case 162:
        
        case 163:
        
        case 164:
        
        case 165:
        
        case 166:
        
        case 167:
        
        case 168:
        
        case 169:
        
        case 170:
        
        case 171:
        
        case 172:
        
        case 173:
        
        case 174:
        
        case 175:
        
        case 176:
        
        case 177:
        
        case 178:
        
        case 179:
        
        case 180:
        
        case 181:
        
        case 182:
        
        case 183:
        
        case 184:
        
        case 185:
        
        case 186:
        
        case 187:
        
        case 188:
        
        case 189:
        
        case 190:
        
        case 191:
        
        case 192:
        
        case 193:
        
        case 194:
        
        case 195:
        
        case 196:
        
        case 197:
        
        case 198:
        
        case 199:
        
        case 200:
        
        case 201:
        
        case 202:
        
        case 203:
        
        case 204:
        
        case 205:
        
        case 206:
        
        case 207:
        
        case 208:
        
        case 209:
        
        case 210:
        
        case 211:
        
        case 212:
        
        case 213:
        
        case 214:
        
        case 215:
        
        case 216:
        
        case 217:
        
        case 218:
        
        case 219:
        
        case 220:
        
        case 221:
        
        case 222:
        
        case 223:
        
        case 224:
        
        case 225:
        
        case 226:
        
        case 227:
        
        case 228:
        
        case 229:
        
        case 230:
        
        case 231:
        
        case 232:
        
        case 233:
        
        case 234:
        
        case 235:
        
        case 236:
        
        case 237:
        
        case 238:
        
        case 239:
        
        case 240:
        
        case 241:
        
        case 242:
        
        case 243:
        
        case 244:
        
        case 245:
        
        case 246:
        
        case 247:
        
        case 248:
        
        case 249:
        
        case 250:
        
        case 251:
        
        case 252:
        
        case 253:
        
        case 254:
        
        default:
          break;
      } 
      char c = 'Â”';
      int j = (paramInt2 & 0xFF) - c;
      if (j < 0)
        j += 256; 
      int k = ((paramInt2 & 0xFFFF) >>> 8) - c;
      if (k < 0)
        k += 256; 
      for (byte b = 0; b < arrayOfChar.length; b++) {
        int m = b % 2;
        if (m == 0) {
          arrayOfChar[b] = (char)(arrayOfChar[b] ^ j);
          j = ((j >>> 3 | j << 5) ^ arrayOfChar[b]) & 0xFF;
        } else {
          arrayOfChar[b] = (char)(arrayOfChar[b] ^ k);
          k = ((k >>> 3 | k << 5) ^ arrayOfChar[b]) & 0xFF;
        } 
      } 
      b[i] = (new String(arrayOfChar)).intern();
    } 
    return b[i];
  }
}


/* Location:              C:\Program Files\BurpSuitePro\burpsuite_pro.jar!\burp\Zbu6.class
 * Java compiler version: 21 (65.0)
 * JD-Core Version:       1.1.3
 */