package burp;

import java.math.BigInteger;

class Zbuc extends ClassLoader {
  static String Zu;
  
  static Object ZE;
  
  private static final String[] a;
  
  private static final String[] b;
  
  static void Zr(Object[] paramArrayOfObject, Object paramObject) throws Throwable {}
  
  static void Zo(Object paramObject) {
    Zv8l.Zo = a(22564, 14036);
    Zv8l.ZL = new BigInteger(1, new byte[] { 
          32, 27, -11, 53, -31, -75, -14, -83, -30, -35, 
          -5, 114, -46, 38, 56, -117, -29, 62, 23, 111, 
          -45, 79, 53, -13, 116, 49, 60, -106, 49, 3, 
          -90, -112 });
    boolean bool = Zt2e.ZN();
    try {
      try {
        if (Zgr4.Zi.charAt(Math.abs(((BigInteger)Zgwh.Zl).intValue() % 32)) <= Zxnm.Zw.charAt(Math.abs(((BigInteger)Zso7.ZB).intValue() % 32))) {
          try {
            Zzh0.ZM(Class.forName(a(22566, -29555)));
            if (!bool)
              Zb20.Zy(Class.forName(a(22574, -4715))); 
          } catch (Throwable throwable) {
            throw a(null);
          } 
          return;
        } 
      } catch (Throwable throwable) {
        throw a(null);
      } 
      Zb20.Zy(Class.forName(a(22574, -4715)));
    } catch (Throwable throwable) {}
  }
  
  static boolean ZR(Object[] paramArrayOfObject, Object paramObject) throws Throwable {
    // Byte code:
    //   0: invokestatic ZK : ()Z
    //   3: istore_2
    //   4: new java/lang/StringBuilder
    //   7: dup
    //   8: invokespecial <init> : ()V
    //   11: astore_3
    //   12: iconst_0
    //   13: istore #4
    //   15: iload #4
    //   17: bipush #32
    //   19: if_icmpge -> 1355
    //   22: iload #4
    //   24: tableswitch default -> 1348, 0 -> 168, 1 -> 205, 2 -> 242, 3 -> 279, 4 -> 316, 5 -> 353, 6 -> 390, 7 -> 427, 8 -> 464, 9 -> 501, 10 -> 538, 11 -> 575, 12 -> 612, 13 -> 649, 14 -> 686, 15 -> 723, 16 -> 760, 17 -> 797, 18 -> 834, 19 -> 871, 20 -> 908, 21 -> 945, 22 -> 982, 23 -> 1019, 24 -> 1056, 25 -> 1093, 26 -> 1130, 27 -> 1167, 28 -> 1204, 29 -> 1241, 30 -> 1278, 31 -> 1315
    //   168: aload_3
    //   169: getstatic burp/Zkql.ZR : Ljava/lang/String;
    //   172: getstatic burp/Ze6w.Ze : Ljava/lang/Object;
    //   175: checkcast java/math/BigInteger
    //   178: invokevirtual intValue : ()I
    //   181: bipush #32
    //   183: irem
    //   184: invokestatic abs : (I)I
    //   187: invokevirtual charAt : (I)C
    //   190: invokevirtual append : (C)Ljava/lang/StringBuilder;
    //   193: pop
    //   194: iload_2
    //   195: ifeq -> 1348
    //   198: goto -> 205
    //   201: invokestatic a : (Ljava/lang/Throwable;)Ljava/lang/Throwable;
    //   204: athrow
    //   205: aload_3
    //   206: getstatic burp/Ze6w.ZY : Ljava/lang/String;
    //   209: getstatic burp/Zlf7.ZE : Ljava/lang/Object;
    //   212: checkcast java/math/BigInteger
    //   215: invokevirtual intValue : ()I
    //   218: bipush #32
    //   220: irem
    //   221: invokestatic abs : (I)I
    //   224: invokevirtual charAt : (I)C
    //   227: invokevirtual append : (C)Ljava/lang/StringBuilder;
    //   230: pop
    //   231: iload_2
    //   232: ifeq -> 1348
    //   235: goto -> 242
    //   238: invokestatic a : (Ljava/lang/Throwable;)Ljava/lang/Throwable;
    //   241: athrow
    //   242: aload_3
    //   243: getstatic burp/Zgis.Zh : Ljava/lang/String;
    //   246: getstatic burp/Ztq4.ZA : Ljava/lang/Object;
    //   249: checkcast java/math/BigInteger
    //   252: invokevirtual intValue : ()I
    //   255: bipush #32
    //   257: irem
    //   258: invokestatic abs : (I)I
    //   261: invokevirtual charAt : (I)C
    //   264: invokevirtual append : (C)Ljava/lang/StringBuilder;
    //   267: pop
    //   268: iload_2
    //   269: ifeq -> 1348
    //   272: goto -> 279
    //   275: invokestatic a : (Ljava/lang/Throwable;)Ljava/lang/Throwable;
    //   278: athrow
    //   279: aload_3
    //   280: getstatic burp/Zrkd.ZL : Ljava/lang/String;
    //   283: getstatic burp/Zmz.ZW : Ljava/lang/Object;
    //   286: checkcast java/math/BigInteger
    //   289: invokevirtual intValue : ()I
    //   292: bipush #32
    //   294: irem
    //   295: invokestatic abs : (I)I
    //   298: invokevirtual charAt : (I)C
    //   301: invokevirtual append : (C)Ljava/lang/StringBuilder;
    //   304: pop
    //   305: iload_2
    //   306: ifeq -> 1348
    //   309: goto -> 316
    //   312: invokestatic a : (Ljava/lang/Throwable;)Ljava/lang/Throwable;
    //   315: athrow
    //   316: aload_3
    //   317: getstatic burp/Zz41.Zc : Ljava/lang/String;
    //   320: getstatic burp/Zb9q.ZI : Ljava/lang/Object;
    //   323: checkcast java/math/BigInteger
    //   326: invokevirtual intValue : ()I
    //   329: bipush #32
    //   331: irem
    //   332: invokestatic abs : (I)I
    //   335: invokevirtual charAt : (I)C
    //   338: invokevirtual append : (C)Ljava/lang/StringBuilder;
    //   341: pop
    //   342: iload_2
    //   343: ifeq -> 1348
    //   346: goto -> 353
    //   349: invokestatic a : (Ljava/lang/Throwable;)Ljava/lang/Throwable;
    //   352: athrow
    //   353: aload_3
    //   354: getstatic burp/Zlf7.ZM : Ljava/lang/String;
    //   357: getstatic burp/Zql.Zt : Ljava/lang/Object;
    //   360: checkcast java/math/BigInteger
    //   363: invokevirtual intValue : ()I
    //   366: bipush #32
    //   368: irem
    //   369: invokestatic abs : (I)I
    //   372: invokevirtual charAt : (I)C
    //   375: invokevirtual append : (C)Ljava/lang/StringBuilder;
    //   378: pop
    //   379: iload_2
    //   380: ifeq -> 1348
    //   383: goto -> 390
    //   386: invokestatic a : (Ljava/lang/Throwable;)Ljava/lang/Throwable;
    //   389: athrow
    //   390: aload_3
    //   391: getstatic burp/Zse8.Ze : Ljava/lang/String;
    //   394: getstatic burp/Zb_1.ZK : Ljava/lang/Object;
    //   397: checkcast java/math/BigInteger
    //   400: invokevirtual intValue : ()I
    //   403: bipush #32
    //   405: irem
    //   406: invokestatic abs : (I)I
    //   409: invokevirtual charAt : (I)C
    //   412: invokevirtual append : (C)Ljava/lang/StringBuilder;
    //   415: pop
    //   416: iload_2
    //   417: ifeq -> 1348
    //   420: goto -> 427
    //   423: invokestatic a : (Ljava/lang/Throwable;)Ljava/lang/Throwable;
    //   426: athrow
    //   427: aload_3
    //   428: getstatic burp/Zsn9.Zp : Ljava/lang/String;
    //   431: getstatic burp/Zxxf.ZZ : Ljava/lang/Object;
    //   434: checkcast java/math/BigInteger
    //   437: invokevirtual intValue : ()I
    //   440: bipush #32
    //   442: irem
    //   443: invokestatic abs : (I)I
    //   446: invokevirtual charAt : (I)C
    //   449: invokevirtual append : (C)Ljava/lang/StringBuilder;
    //   452: pop
    //   453: iload_2
    //   454: ifeq -> 1348
    //   457: goto -> 464
    //   460: invokestatic a : (Ljava/lang/Throwable;)Ljava/lang/Throwable;
    //   463: athrow
    //   464: aload_3
    //   465: getstatic burp/Zxju.Zt : Ljava/lang/String;
    //   468: getstatic burp/Zbss.Zh : Ljava/lang/Object;
    //   471: checkcast java/math/BigInteger
    //   474: invokevirtual intValue : ()I
    //   477: bipush #32
    //   479: irem
    //   480: invokestatic abs : (I)I
    //   483: invokevirtual charAt : (I)C
    //   486: invokevirtual append : (C)Ljava/lang/StringBuilder;
    //   489: pop
    //   490: iload_2
    //   491: ifeq -> 1348
    //   494: goto -> 501
    //   497: invokestatic a : (Ljava/lang/Throwable;)Ljava/lang/Throwable;
    //   500: athrow
    //   501: aload_3
    //   502: getstatic burp/Zmzj.Zb : Ljava/lang/String;
    //   505: getstatic burp/Zgrz.ZX : Ljava/lang/Object;
    //   508: checkcast java/math/BigInteger
    //   511: invokevirtual intValue : ()I
    //   514: bipush #32
    //   516: irem
    //   517: invokestatic abs : (I)I
    //   520: invokevirtual charAt : (I)C
    //   523: invokevirtual append : (C)Ljava/lang/StringBuilder;
    //   526: pop
    //   527: iload_2
    //   528: ifeq -> 1348
    //   531: goto -> 538
    //   534: invokestatic a : (Ljava/lang/Throwable;)Ljava/lang/Throwable;
    //   537: athrow
    //   538: aload_3
    //   539: getstatic burp/Zz0y.ZM : Ljava/lang/String;
    //   542: getstatic burp/Zeub.ZD : Ljava/lang/Object;
    //   545: checkcast java/math/BigInteger
    //   548: invokevirtual intValue : ()I
    //   551: bipush #32
    //   553: irem
    //   554: invokestatic abs : (I)I
    //   557: invokevirtual charAt : (I)C
    //   560: invokevirtual append : (C)Ljava/lang/StringBuilder;
    //   563: pop
    //   564: iload_2
    //   565: ifeq -> 1348
    //   568: goto -> 575
    //   571: invokestatic a : (Ljava/lang/Throwable;)Ljava/lang/Throwable;
    //   574: athrow
    //   575: aload_3
    //   576: getstatic burp/Zz4j.ZS : Ljava/lang/String;
    //   579: getstatic burp/Zrom.ZF : Ljava/lang/Object;
    //   582: checkcast java/math/BigInteger
    //   585: invokevirtual intValue : ()I
    //   588: bipush #32
    //   590: irem
    //   591: invokestatic abs : (I)I
    //   594: invokevirtual charAt : (I)C
    //   597: invokevirtual append : (C)Ljava/lang/StringBuilder;
    //   600: pop
    //   601: iload_2
    //   602: ifeq -> 1348
    //   605: goto -> 612
    //   608: invokestatic a : (Ljava/lang/Throwable;)Ljava/lang/Throwable;
    //   611: athrow
    //   612: aload_3
    //   613: getstatic burp/Zgu4.Za : Ljava/lang/String;
    //   616: getstatic burp/Zgpx.ZQ : Ljava/lang/Object;
    //   619: checkcast java/math/BigInteger
    //   622: invokevirtual intValue : ()I
    //   625: bipush #32
    //   627: irem
    //   628: invokestatic abs : (I)I
    //   631: invokevirtual charAt : (I)C
    //   634: invokevirtual append : (C)Ljava/lang/StringBuilder;
    //   637: pop
    //   638: iload_2
    //   639: ifeq -> 1348
    //   642: goto -> 649
    //   645: invokestatic a : (Ljava/lang/Throwable;)Ljava/lang/Throwable;
    //   648: athrow
    //   649: aload_3
    //   650: getstatic burp/Zl7x.Zo : Ljava/lang/String;
    //   653: getstatic burp/Zlf7.ZE : Ljava/lang/Object;
    //   656: checkcast java/math/BigInteger
    //   659: invokevirtual intValue : ()I
    //   662: bipush #32
    //   664: irem
    //   665: invokestatic abs : (I)I
    //   668: invokevirtual charAt : (I)C
    //   671: invokevirtual append : (C)Ljava/lang/StringBuilder;
    //   674: pop
    //   675: iload_2
    //   676: ifeq -> 1348
    //   679: goto -> 686
    //   682: invokestatic a : (Ljava/lang/Throwable;)Ljava/lang/Throwable;
    //   685: athrow
    //   686: aload_3
    //   687: getstatic burp/Zt4p.ZL : Ljava/lang/String;
    //   690: getstatic burp/Zk8i.ZN : Ljava/lang/Object;
    //   693: checkcast java/math/BigInteger
    //   696: invokevirtual intValue : ()I
    //   699: bipush #32
    //   701: irem
    //   702: invokestatic abs : (I)I
    //   705: invokevirtual charAt : (I)C
    //   708: invokevirtual append : (C)Ljava/lang/StringBuilder;
    //   711: pop
    //   712: iload_2
    //   713: ifeq -> 1348
    //   716: goto -> 723
    //   719: invokestatic a : (Ljava/lang/Throwable;)Ljava/lang/Throwable;
    //   722: athrow
    //   723: aload_3
    //   724: getstatic burp/Zgi9.Zv : Ljava/lang/String;
    //   727: getstatic burp/Zsn3.Zy : Ljava/lang/Object;
    //   730: checkcast java/math/BigInteger
    //   733: invokevirtual intValue : ()I
    //   736: bipush #32
    //   738: irem
    //   739: invokestatic abs : (I)I
    //   742: invokevirtual charAt : (I)C
    //   745: invokevirtual append : (C)Ljava/lang/StringBuilder;
    //   748: pop
    //   749: iload_2
    //   750: ifeq -> 1348
    //   753: goto -> 760
    //   756: invokestatic a : (Ljava/lang/Throwable;)Ljava/lang/Throwable;
    //   759: athrow
    //   760: aload_3
    //   761: getstatic burp/Zk5k.Zx : Ljava/lang/String;
    //   764: getstatic burp/Zxln.ZJ : Ljava/lang/Object;
    //   767: checkcast java/math/BigInteger
    //   770: invokevirtual intValue : ()I
    //   773: bipush #32
    //   775: irem
    //   776: invokestatic abs : (I)I
    //   779: invokevirtual charAt : (I)C
    //   782: invokevirtual append : (C)Ljava/lang/StringBuilder;
    //   785: pop
    //   786: iload_2
    //   787: ifeq -> 1348
    //   790: goto -> 797
    //   793: invokestatic a : (Ljava/lang/Throwable;)Ljava/lang/Throwable;
    //   796: athrow
    //   797: aload_3
    //   798: getstatic burp/Zxd1.ZQ : Ljava/lang/String;
    //   801: getstatic burp/Zsn4.ZQ : Ljava/lang/Object;
    //   804: checkcast java/math/BigInteger
    //   807: invokevirtual intValue : ()I
    //   810: bipush #32
    //   812: irem
    //   813: invokestatic abs : (I)I
    //   816: invokevirtual charAt : (I)C
    //   819: invokevirtual append : (C)Ljava/lang/StringBuilder;
    //   822: pop
    //   823: iload_2
    //   824: ifeq -> 1348
    //   827: goto -> 834
    //   830: invokestatic a : (Ljava/lang/Throwable;)Ljava/lang/Throwable;
    //   833: athrow
    //   834: aload_3
    //   835: getstatic burp/Zmh3.Zy : Ljava/lang/String;
    //   838: getstatic burp/Zm3x.ZM : Ljava/lang/Object;
    //   841: checkcast java/math/BigInteger
    //   844: invokevirtual intValue : ()I
    //   847: bipush #32
    //   849: irem
    //   850: invokestatic abs : (I)I
    //   853: invokevirtual charAt : (I)C
    //   856: invokevirtual append : (C)Ljava/lang/StringBuilder;
    //   859: pop
    //   860: iload_2
    //   861: ifeq -> 1348
    //   864: goto -> 871
    //   867: invokestatic a : (Ljava/lang/Throwable;)Ljava/lang/Throwable;
    //   870: athrow
    //   871: aload_3
    //   872: getstatic burp/Ze6w.ZY : Ljava/lang/String;
    //   875: getstatic burp/Ztlo.ZP : Ljava/lang/Object;
    //   878: checkcast java/math/BigInteger
    //   881: invokevirtual intValue : ()I
    //   884: bipush #32
    //   886: irem
    //   887: invokestatic abs : (I)I
    //   890: invokevirtual charAt : (I)C
    //   893: invokevirtual append : (C)Ljava/lang/StringBuilder;
    //   896: pop
    //   897: iload_2
    //   898: ifeq -> 1348
    //   901: goto -> 908
    //   904: invokestatic a : (Ljava/lang/Throwable;)Ljava/lang/Throwable;
    //   907: athrow
    //   908: aload_3
    //   909: getstatic burp/Zrm6.ZV : Ljava/lang/String;
    //   912: getstatic burp/Zgi9.Zc : Ljava/lang/Object;
    //   915: checkcast java/math/BigInteger
    //   918: invokevirtual intValue : ()I
    //   921: bipush #32
    //   923: irem
    //   924: invokestatic abs : (I)I
    //   927: invokevirtual charAt : (I)C
    //   930: invokevirtual append : (C)Ljava/lang/StringBuilder;
    //   933: pop
    //   934: iload_2
    //   935: ifeq -> 1348
    //   938: goto -> 945
    //   941: invokestatic a : (Ljava/lang/Throwable;)Ljava/lang/Throwable;
    //   944: athrow
    //   945: aload_3
    //   946: getstatic burp/Zl2t.Zg : Ljava/lang/String;
    //   949: getstatic burp/Zti4.Zi : Ljava/lang/Object;
    //   952: checkcast java/math/BigInteger
    //   955: invokevirtual intValue : ()I
    //   958: bipush #32
    //   960: irem
    //   961: invokestatic abs : (I)I
    //   964: invokevirtual charAt : (I)C
    //   967: invokevirtual append : (C)Ljava/lang/StringBuilder;
    //   970: pop
    //   971: iload_2
    //   972: ifeq -> 1348
    //   975: goto -> 982
    //   978: invokestatic a : (Ljava/lang/Throwable;)Ljava/lang/Throwable;
    //   981: athrow
    //   982: aload_3
    //   983: getstatic burp/Zgtx.ZN : Ljava/lang/String;
    //   986: getstatic burp/Ze25.ZW : Ljava/lang/Object;
    //   989: checkcast java/math/BigInteger
    //   992: invokevirtual intValue : ()I
    //   995: bipush #32
    //   997: irem
    //   998: invokestatic abs : (I)I
    //   1001: invokevirtual charAt : (I)C
    //   1004: invokevirtual append : (C)Ljava/lang/StringBuilder;
    //   1007: pop
    //   1008: iload_2
    //   1009: ifeq -> 1348
    //   1012: goto -> 1019
    //   1015: invokestatic a : (Ljava/lang/Throwable;)Ljava/lang/Throwable;
    //   1018: athrow
    //   1019: aload_3
    //   1020: getstatic burp/Zelt.ZJ : Ljava/lang/String;
    //   1023: getstatic burp/Zt81.ZY : Ljava/lang/Object;
    //   1026: checkcast java/math/BigInteger
    //   1029: invokevirtual intValue : ()I
    //   1032: bipush #32
    //   1034: irem
    //   1035: invokestatic abs : (I)I
    //   1038: invokevirtual charAt : (I)C
    //   1041: invokevirtual append : (C)Ljava/lang/StringBuilder;
    //   1044: pop
    //   1045: iload_2
    //   1046: ifeq -> 1348
    //   1049: goto -> 1056
    //   1052: invokestatic a : (Ljava/lang/Throwable;)Ljava/lang/Throwable;
    //   1055: athrow
    //   1056: aload_3
    //   1057: getstatic burp/Zs1d.Zl : Ljava/lang/String;
    //   1060: getstatic burp/Zrjw.Zu : Ljava/lang/Object;
    //   1063: checkcast java/math/BigInteger
    //   1066: invokevirtual intValue : ()I
    //   1069: bipush #32
    //   1071: irem
    //   1072: invokestatic abs : (I)I
    //   1075: invokevirtual charAt : (I)C
    //   1078: invokevirtual append : (C)Ljava/lang/StringBuilder;
    //   1081: pop
    //   1082: iload_2
    //   1083: ifeq -> 1348
    //   1086: goto -> 1093
    //   1089: invokestatic a : (Ljava/lang/Throwable;)Ljava/lang/Throwable;
    //   1092: athrow
    //   1093: aload_3
    //   1094: getstatic burp/Zkeb.ZW : Ljava/lang/String;
    //   1097: getstatic burp/Zbl4.ZW : Ljava/lang/Object;
    //   1100: checkcast java/math/BigInteger
    //   1103: invokevirtual intValue : ()I
    //   1106: bipush #32
    //   1108: irem
    //   1109: invokestatic abs : (I)I
    //   1112: invokevirtual charAt : (I)C
    //   1115: invokevirtual append : (C)Ljava/lang/StringBuilder;
    //   1118: pop
    //   1119: iload_2
    //   1120: ifeq -> 1348
    //   1123: goto -> 1130
    //   1126: invokestatic a : (Ljava/lang/Throwable;)Ljava/lang/Throwable;
    //   1129: athrow
    //   1130: aload_3
    //   1131: getstatic burp/Zxcn.ZF : Ljava/lang/String;
    //   1134: getstatic burp/Zk8i.ZN : Ljava/lang/Object;
    //   1137: checkcast java/math/BigInteger
    //   1140: invokevirtual intValue : ()I
    //   1143: bipush #32
    //   1145: irem
    //   1146: invokestatic abs : (I)I
    //   1149: invokevirtual charAt : (I)C
    //   1152: invokevirtual append : (C)Ljava/lang/StringBuilder;
    //   1155: pop
    //   1156: iload_2
    //   1157: ifeq -> 1348
    //   1160: goto -> 1167
    //   1163: invokestatic a : (Ljava/lang/Throwable;)Ljava/lang/Throwable;
    //   1166: athrow
    //   1167: aload_3
    //   1168: getstatic burp/Zepy.Zg : Ljava/lang/String;
    //   1171: getstatic burp/Zl7b.ZK : Ljava/lang/Object;
    //   1174: checkcast java/math/BigInteger
    //   1177: invokevirtual intValue : ()I
    //   1180: bipush #32
    //   1182: irem
    //   1183: invokestatic abs : (I)I
    //   1186: invokevirtual charAt : (I)C
    //   1189: invokevirtual append : (C)Ljava/lang/StringBuilder;
    //   1192: pop
    //   1193: iload_2
    //   1194: ifeq -> 1348
    //   1197: goto -> 1204
    //   1200: invokestatic a : (Ljava/lang/Throwable;)Ljava/lang/Throwable;
    //   1203: athrow
    //   1204: aload_3
    //   1205: getstatic burp/Zsjw.ZQ : Ljava/lang/String;
    //   1208: getstatic burp/Ztvy.ZH : Ljava/lang/Object;
    //   1211: checkcast java/math/BigInteger
    //   1214: invokevirtual intValue : ()I
    //   1217: bipush #32
    //   1219: irem
    //   1220: invokestatic abs : (I)I
    //   1223: invokevirtual charAt : (I)C
    //   1226: invokevirtual append : (C)Ljava/lang/StringBuilder;
    //   1229: pop
    //   1230: iload_2
    //   1231: ifeq -> 1348
    //   1234: goto -> 1241
    //   1237: invokestatic a : (Ljava/lang/Throwable;)Ljava/lang/Throwable;
    //   1240: athrow
    //   1241: aload_3
    //   1242: getstatic burp/Ztlo.Zs : Ljava/lang/String;
    //   1245: getstatic burp/Zrd3.ZI : Ljava/lang/Object;
    //   1248: checkcast java/math/BigInteger
    //   1251: invokevirtual intValue : ()I
    //   1254: bipush #32
    //   1256: irem
    //   1257: invokestatic abs : (I)I
    //   1260: invokevirtual charAt : (I)C
    //   1263: invokevirtual append : (C)Ljava/lang/StringBuilder;
    //   1266: pop
    //   1267: iload_2
    //   1268: ifeq -> 1348
    //   1271: goto -> 1278
    //   1274: invokestatic a : (Ljava/lang/Throwable;)Ljava/lang/Throwable;
    //   1277: athrow
    //   1278: aload_3
    //   1279: getstatic burp/Zsn9.Zp : Ljava/lang/String;
    //   1282: getstatic burp/Ztgv.Zg : Ljava/lang/Object;
    //   1285: checkcast java/math/BigInteger
    //   1288: invokevirtual intValue : ()I
    //   1291: bipush #32
    //   1293: irem
    //   1294: invokestatic abs : (I)I
    //   1297: invokevirtual charAt : (I)C
    //   1300: invokevirtual append : (C)Ljava/lang/StringBuilder;
    //   1303: pop
    //   1304: iload_2
    //   1305: ifeq -> 1348
    //   1308: goto -> 1315
    //   1311: invokestatic a : (Ljava/lang/Throwable;)Ljava/lang/Throwable;
    //   1314: athrow
    //   1315: aload_3
    //   1316: getstatic burp/Zxcn.ZF : Ljava/lang/String;
    //   1319: getstatic burp/Ztbn.ZA : Ljava/lang/Object;
    //   1322: checkcast java/math/BigInteger
    //   1325: invokevirtual intValue : ()I
    //   1328: bipush #32
    //   1330: irem
    //   1331: invokestatic abs : (I)I
    //   1334: invokevirtual charAt : (I)C
    //   1337: invokevirtual append : (C)Ljava/lang/StringBuilder;
    //   1340: pop
    //   1341: goto -> 1348
    //   1344: invokestatic a : (Ljava/lang/Throwable;)Ljava/lang/Throwable;
    //   1347: athrow
    //   1348: iinc #4, 1
    //   1351: iload_2
    //   1352: ifeq -> 15
    //   1355: sipush #22563
    //   1358: sipush #-11323
    //   1361: invokestatic a : (II)Ljava/lang/String;
    //   1364: invokestatic forName : (Ljava/lang/String;)Ljava/lang/Class;
    //   1367: invokevirtual getDeclaredFields : ()[Ljava/lang/reflect/Field;
    //   1370: astore #4
    //   1372: aload #4
    //   1374: arraylength
    //   1375: istore #5
    //   1377: iconst_0
    //   1378: istore #6
    //   1380: iload #6
    //   1382: iload #5
    //   1384: if_icmpge -> 1461
    //   1387: aload #4
    //   1389: iload #6
    //   1391: aaload
    //   1392: astore #7
    //   1394: aload #7
    //   1396: invokevirtual getType : ()Ljava/lang/Class;
    //   1399: ldc java/lang/String
    //   1401: invokevirtual equals : (Ljava/lang/Object;)Z
    //   1404: ifeq -> 1447
    //   1407: aload #7
    //   1409: iconst_1
    //   1410: invokevirtual setAccessible : (Z)V
    //   1413: aload #7
    //   1415: aconst_null
    //   1416: aload #7
    //   1418: aconst_null
    //   1419: invokevirtual get : (Ljava/lang/Object;)Ljava/lang/Object;
    //   1422: checkcast java/lang/String
    //   1425: getstatic burp/Zbuc.Zu : Ljava/lang/String;
    //   1428: <illegal opcode> makeConcatWithConstants : (Ljava/lang/String;Ljava/lang/String;)Ljava/lang/String;
    //   1433: invokevirtual set : (Ljava/lang/Object;Ljava/lang/Object;)V
    //   1436: iload_2
    //   1437: ifeq -> 1461
    //   1440: goto -> 1447
    //   1443: invokestatic a : (Ljava/lang/Throwable;)Ljava/lang/Throwable;
    //   1446: athrow
    //   1447: iinc #6, 1
    //   1450: iload_2
    //   1451: ifeq -> 1380
    //   1454: goto -> 1461
    //   1457: invokestatic a : (Ljava/lang/Throwable;)Ljava/lang/Throwable;
    //   1460: athrow
    //   1461: sipush #22575
    //   1464: sipush #28178
    //   1467: invokestatic a : (II)Ljava/lang/String;
    //   1470: iconst_1
    //   1471: ldc burp/Zlot
    //   1473: invokevirtual getClassLoader : ()Ljava/lang/ClassLoader;
    //   1476: invokestatic forName : (Ljava/lang/String;ZLjava/lang/ClassLoader;)Ljava/lang/Class;
    //   1479: invokevirtual getDeclaredFields : ()[Ljava/lang/reflect/Field;
    //   1482: astore #4
    //   1484: aload #4
    //   1486: arraylength
    //   1487: istore #5
    //   1489: iconst_0
    //   1490: istore #6
    //   1492: iload #6
    //   1494: iload #5
    //   1496: if_icmpge -> 1634
    //   1499: aload #4
    //   1501: iload #6
    //   1503: aaload
    //   1504: astore #7
    //   1506: aload #7
    //   1508: invokevirtual getModifiers : ()I
    //   1511: invokestatic isStatic : (I)Z
    //   1514: ifne -> 1524
    //   1517: goto -> 1627
    //   1520: invokestatic a : (Ljava/lang/Throwable;)Ljava/lang/Throwable;
    //   1523: athrow
    //   1524: aload #7
    //   1526: invokevirtual getType : ()Ljava/lang/Class;
    //   1529: astore #8
    //   1531: aload #8
    //   1533: ifnull -> 1614
    //   1536: aload #8
    //   1538: invokevirtual isPrimitive : ()Z
    //   1541: ifne -> 1614
    //   1544: goto -> 1551
    //   1547: invokestatic a : (Ljava/lang/Throwable;)Ljava/lang/Throwable;
    //   1550: athrow
    //   1551: aload #8
    //   1553: invokevirtual getPackage : ()Ljava/lang/Package;
    //   1556: ifnull -> 1614
    //   1559: goto -> 1566
    //   1562: invokestatic a : (Ljava/lang/Throwable;)Ljava/lang/Throwable;
    //   1565: athrow
    //   1566: aload #8
    //   1568: invokevirtual getPackage : ()Ljava/lang/Package;
    //   1571: invokevirtual getName : ()Ljava/lang/String;
    //   1574: ifnull -> 1614
    //   1577: goto -> 1584
    //   1580: invokestatic a : (Ljava/lang/Throwable;)Ljava/lang/Throwable;
    //   1583: athrow
    //   1584: aload #8
    //   1586: invokevirtual getPackage : ()Ljava/lang/Package;
    //   1589: invokevirtual getName : ()Ljava/lang/String;
    //   1592: sipush #22560
    //   1595: sipush #27340
    //   1598: invokestatic a : (II)Ljava/lang/String;
    //   1601: invokevirtual startsWith : (Ljava/lang/String;)Z
    //   1604: ifne -> 1614
    //   1607: goto -> 1614
    //   1610: invokestatic a : (Ljava/lang/Throwable;)Ljava/lang/Throwable;
    //   1613: athrow
    //   1614: aload #7
    //   1616: iconst_1
    //   1617: invokevirtual setAccessible : (Z)V
    //   1620: aload #7
    //   1622: aconst_null
    //   1623: invokevirtual get : (Ljava/lang/Object;)Ljava/lang/Object;
    //   1626: pop
    //   1627: iinc #6, 1
    //   1630: iload_2
    //   1631: ifeq -> 1492
    //   1634: sipush #22561
    //   1637: sipush #-13527
    //   1640: invokestatic a : (II)Ljava/lang/String;
    //   1643: invokestatic forName : (Ljava/lang/String;)Ljava/lang/Class;
    //   1646: invokevirtual getDeclaredMethods : ()[Ljava/lang/reflect/Method;
    //   1649: astore #4
    //   1651: aload #4
    //   1653: arraylength
    //   1654: istore #5
    //   1656: iconst_0
    //   1657: istore #6
    //   1659: iload #6
    //   1661: iload #5
    //   1663: if_icmpge -> 1796
    //   1666: aload #4
    //   1668: iload #6
    //   1670: aaload
    //   1671: astore #7
    //   1673: aload #7
    //   1675: invokevirtual getParameterTypes : ()[Ljava/lang/Class;
    //   1678: pop
    //   1679: aload #7
    //   1681: invokevirtual getModifiers : ()I
    //   1684: invokestatic isStatic : (I)Z
    //   1687: ifeq -> 1782
    //   1690: aload #7
    //   1692: invokevirtual getParameterTypes : ()[Ljava/lang/Class;
    //   1695: arraylength
    //   1696: iconst_2
    //   1697: if_icmpne -> 1782
    //   1700: goto -> 1707
    //   1703: invokestatic a : (Ljava/lang/Throwable;)Ljava/lang/Throwable;
    //   1706: athrow
    //   1707: aload #7
    //   1709: invokevirtual getReturnType : ()Ljava/lang/Class;
    //   1712: getstatic java/lang/Void.TYPE : Ljava/lang/Class;
    //   1715: invokevirtual equals : (Ljava/lang/Object;)Z
    //   1718: ifeq -> 1782
    //   1721: goto -> 1728
    //   1724: invokestatic a : (Ljava/lang/Throwable;)Ljava/lang/Throwable;
    //   1727: athrow
    //   1728: aload #7
    //   1730: iconst_1
    //   1731: invokevirtual setAccessible : (Z)V
    //   1734: aload #7
    //   1736: aconst_null
    //   1737: iconst_2
    //   1738: anewarray java/lang/Object
    //   1741: dup
    //   1742: iconst_0
    //   1743: aload_0
    //   1744: aastore
    //   1745: dup
    //   1746: iconst_1
    //   1747: aload_1
    //   1748: ifnonnull -> 1766
    //   1751: goto -> 1758
    //   1754: invokestatic a : (Ljava/lang/Throwable;)Ljava/lang/Throwable;
    //   1757: athrow
    //   1758: aload_1
    //   1759: goto -> 1773
    //   1762: invokestatic a : (Ljava/lang/Throwable;)Ljava/lang/Throwable;
    //   1765: athrow
    //   1766: aload_1
    //   1767: checkcast [B
    //   1770: invokevirtual clone : ()Ljava/lang/Object;
    //   1773: aastore
    //   1774: invokevirtual invoke : (Ljava/lang/Object;[Ljava/lang/Object;)Ljava/lang/Object;
    //   1777: pop
    //   1778: iload_2
    //   1779: ifeq -> 1796
    //   1782: iinc #6, 1
    //   1785: iload_2
    //   1786: ifeq -> 1659
    //   1789: goto -> 1796
    //   1792: invokestatic a : (Ljava/lang/Throwable;)Ljava/lang/Throwable;
    //   1795: athrow
    //   1796: getstatic burp/Zmhq.Zy : Ljava/lang/String;
    //   1799: getstatic burp/Zrym.Zk : Ljava/lang/Object;
    //   1802: checkcast java/math/BigInteger
    //   1805: invokevirtual intValue : ()I
    //   1808: bipush #32
    //   1810: irem
    //   1811: invokestatic abs : (I)I
    //   1814: invokevirtual charAt : (I)C
    //   1817: getstatic burp/Zb_1.Zc : Ljava/lang/String;
    //   1820: getstatic burp/Ztvg.ZO : Ljava/lang/Object;
    //   1823: checkcast java/math/BigInteger
    //   1826: invokevirtual intValue : ()I
    //   1829: bipush #32
    //   1831: irem
    //   1832: invokestatic abs : (I)I
    //   1835: invokevirtual charAt : (I)C
    //   1838: if_icmple -> 1945
    //   1841: getstatic burp/Zebc.ZC : Ljava/lang/String;
    //   1844: getstatic burp/Ze7e.Z_ : Ljava/lang/Object;
    //   1847: checkcast java/math/BigInteger
    //   1850: invokevirtual intValue : ()I
    //   1853: bipush #32
    //   1855: irem
    //   1856: invokestatic abs : (I)I
    //   1859: invokevirtual charAt : (I)C
    //   1862: getstatic burp/Zb6m.ZR : Ljava/lang/String;
    //   1865: getstatic burp/Zk7o.ZO : Ljava/lang/Object;
    //   1868: checkcast java/math/BigInteger
    //   1871: invokevirtual intValue : ()I
    //   1874: bipush #32
    //   1876: irem
    //   1877: invokestatic abs : (I)I
    //   1880: invokevirtual charAt : (I)C
    //   1883: if_icmpgt -> 1945
    //   1886: goto -> 1893
    //   1889: invokestatic a : (Ljava/lang/Throwable;)Ljava/lang/Throwable;
    //   1892: athrow
    //   1893: getstatic burp/Zl3j.Zr : Ljava/lang/String;
    //   1896: getstatic burp/Zea9.Zt : Ljava/lang/Object;
    //   1899: checkcast java/math/BigInteger
    //   1902: invokevirtual intValue : ()I
    //   1905: bipush #32
    //   1907: irem
    //   1908: invokestatic abs : (I)I
    //   1911: invokevirtual charAt : (I)C
    //   1914: getstatic burp/Zz3b.Zi : Ljava/lang/String;
    //   1917: getstatic burp/Ztle.ZP : Ljava/lang/Object;
    //   1920: checkcast java/math/BigInteger
    //   1923: invokevirtual intValue : ()I
    //   1926: bipush #32
    //   1928: irem
    //   1929: invokestatic abs : (I)I
    //   1932: invokevirtual charAt : (I)C
    //   1935: if_icmpgt -> 1953
    //   1938: goto -> 1945
    //   1941: invokestatic a : (Ljava/lang/Throwable;)Ljava/lang/Throwable;
    //   1944: athrow
    //   1945: iconst_1
    //   1946: goto -> 1954
    //   1949: invokestatic a : (Ljava/lang/Throwable;)Ljava/lang/Throwable;
    //   1952: athrow
    //   1953: iconst_0
    //   1954: ireturn
    //   1955: astore_3
    //   1956: new java/lang/Exception
    //   1959: dup
    //   1960: aload_3
    //   1961: invokevirtual getMessage : ()Ljava/lang/String;
    //   1964: invokespecial <init> : (Ljava/lang/String;)V
    //   1967: athrow
    // Exception table:
    //   from	to	target	type
    //   4	1954	1955	java/lang/Throwable
    //   22	198	201	java/lang/Throwable
    //   168	235	238	java/lang/Throwable
    //   205	272	275	java/lang/Throwable
    //   242	309	312	java/lang/Throwable
    //   279	346	349	java/lang/Throwable
    //   316	383	386	java/lang/Throwable
    //   353	420	423	java/lang/Throwable
    //   390	457	460	java/lang/Throwable
    //   427	494	497	java/lang/Throwable
    //   464	531	534	java/lang/Throwable
    //   501	568	571	java/lang/Throwable
    //   538	605	608	java/lang/Throwable
    //   575	642	645	java/lang/Throwable
    //   612	679	682	java/lang/Throwable
    //   649	716	719	java/lang/Throwable
    //   686	753	756	java/lang/Throwable
    //   723	790	793	java/lang/Throwable
    //   760	827	830	java/lang/Throwable
    //   797	864	867	java/lang/Throwable
    //   834	901	904	java/lang/Throwable
    //   871	938	941	java/lang/Throwable
    //   908	975	978	java/lang/Throwable
    //   945	1012	1015	java/lang/Throwable
    //   982	1049	1052	java/lang/Throwable
    //   1019	1086	1089	java/lang/Throwable
    //   1056	1123	1126	java/lang/Throwable
    //   1093	1160	1163	java/lang/Throwable
    //   1130	1197	1200	java/lang/Throwable
    //   1167	1234	1237	java/lang/Throwable
    //   1204	1271	1274	java/lang/Throwable
    //   1241	1308	1311	java/lang/Throwable
    //   1278	1341	1344	java/lang/Throwable
    //   1394	1440	1443	java/lang/Throwable
    //   1407	1454	1457	java/lang/Throwable
    //   1506	1520	1520	java/lang/Throwable
    //   1531	1544	1547	java/lang/Throwable
    //   1536	1559	1562	java/lang/Throwable
    //   1551	1577	1580	java/lang/Throwable
    //   1566	1607	1610	java/lang/Throwable
    //   1673	1700	1703	java/lang/Throwable
    //   1690	1721	1724	java/lang/Throwable
    //   1707	1751	1754	java/lang/Throwable
    //   1728	1762	1762	java/lang/Throwable
    //   1773	1789	1792	java/lang/Throwable
    //   1796	1886	1889	java/lang/Throwable
    //   1841	1938	1941	java/lang/Throwable
    //   1893	1949	1949	java/lang/Throwable
  }
  
  static {
    // Byte code:
    //   0: bipush #10
    //   2: anewarray java/lang/String
    //   5: astore #5
    //   7: iconst_0
    //   8: istore_3
    //   9: ldc '¤2SÃ87age0=9ÚÍÆG®$ ÖFÐ°gâ ÌbÇùp1Áwe;+bí]XÄ.èÒ¤²ò"½)K¥J0´EÖÂ¹«QÏîøÇáß ()ªrL7-s·ú´vd õãi¨¢q½å­q4(.Ðrß(]åÇIWËNR[©êÕk$Ö(V);«ÅùwÏaY)§å¨y9;ÄØ~6Ù\ä\\tíÈÜ¿2×ßbr\\nßÄüo>Ã6çÅT/§ÊÒ«)·2`³¹ìçeªOtAèR±ÝÑ8zÿW¿­uØ×½/©ãÂV¢kuú¾®ÅÚG?ÃÚ 4)uW3PÛ´ÝEÌ­U=ga+83XÂ¤RÌÿ¡ym%Þ)\\n°Â¹¹H)ÑÅ­±áÌ3 j¹¥ñøj~«\\tù\\bþ NF´Ót©HsÒ·Æ¬JêÀæÂÌz5jíE¯!ÓÄ(KlV2åZv[ `ìbïèÀÏáy%åÖV ­¹}åbÖ Ñ&ÀQZa_a<µÌûÁÎë^@ÁNÑsk¼\\f)múâm\\r Ì4úDK"Êò*Ê{ò7Sz.jè¾t³3êÞq¹¼ÞÞô¨?v¹ÊIC 4»/ÁUÐ8åÈþÊÉz à|Ãr37È(~-\\fSK&ÙrSÈêÅ`Jòu§ÊæÆó¡£HÂá ÅRîÛ¿«¡zfï¡4ÝØ_ñ+×üT¨"ØlIï!ßß°ªUK¯­`äh\\nK·Í aöãþB©²©´#ÐúL1"ÙxCõxÍ>ïúAÂ\\rV+¾'_¥Ûâ Ó)O[êvüåÐÛT¸Ì~%ÁÑ¦äNàû(:ÄJ6ötT¡«x\ÓÖ*Yì/|á<ß^~þÂ¼ÉÇfºaÞ e_°Îækqã,º4ÒýFWÎ:LÜ©1>^Æ8;LÁ±rNó1<ç}þåÏ1¡F`¯o^lhÝoY²\°âVÈ_Nk¶"9aÕd t\\nÎgHÉ"2\\tëIÜx\\b1ÿ%Ð¥ñO-föá¹°oÍ©¸ éë­Èº¯æ4µ$¯7:¼GJ,y/lß¿\)Û»'P¼¢ÇÙºRûlº>1A?!ÚLLkñ-j%î²a\\nWÐ¹©ÊÀ¿h£©TìÎÑi#¾J>±ú¨_.ÓI4.±O~%C¾9-sþó:Á¦\\fe;Êq\\b°D%-:oëÃoG®Ç@±KD°¨­¢IÈN°5&ºòÆ¥M]²c\\fa©Êr"}µFìÔ4cãÕá*Igä"-+Ç)¹uÞ¤º"ªvØçÕÌ°«¡eùøNÆïUæ>¶É»_ÝrOý{°Úá rÈ­y\\r³<§&cg4øÈ|E7©¤nïÕ¿/åózAº¢ÊÆÐ,ZÿÉÔÓr²ëÜz¬Q¿ÜI½I{CqS^:H»ÎþIçÛËMó×ÇV9óy?Ú¥ZãÒ·?&{;;ÀíuÓ`Æûó~8Ô@ZùÃ*ÎÕfS¼ÆE¸ßdÓ4j3Ü|¸òæsCv.³¤ÖlÊÄ$¨­¯lUCx¶,ªPÇ|wcN:¾®sX^å¶?6)?Ð_Ô1³Kò9¼£ºI´§\\nÿ¹«z½Z^Ò?.é]æ+«x)½Ot%B¬/MwÂLKC4n¦#ÌMSo"Y=\\toXXcoqû\¡°ï-ùy¹9|÷£t'&opº<þOH/$0çGIÎfâ0]ûè}¥®à0h1¹h¤b®@3þîÎFè<SAêÈ×©#`ü75«ÞræìWAÏtëa*&ý mù\b+"*f«\\fÈ,¢\\fèa-rS·C?eóz\\bÜvýt2ÿþÆõøÛZ}A\\r\\n\\t\\bÛqf8­ö`¿\ûGî|L1IÛÇ$ÔÊy·å2í££¿ãè`Â v44^\ªw]'KçûËê§xâj±Ô\\t¯,0 5üÔÝÿ ;(\ø¼@â§ ñz~ÄzÈ» [ÉþÊðXa)à(­RFÌ1¦_\\b¡Q&¤uçð÷ôh\\fÈwk,ð3è cDv¤F{iy@ÞFQjK&r,5óÒ¹êT\\b<5]³#\\n¦÷êK¾êºò>"´ _ù<í;ÿNÓÝÓwXÉ¨ÓÝÞg^Ã··r³Ú×g%aHî\\tX90Þ@»\\fÌºÓh¦äÌÎî2R¶Üóÿ/Y«º¦ñ_;ÛÐåÏÔ+cOñF8»¥4WKº639CZ±ÒÄk¡Æ?Ôò¢Ft°L±TÌ´NK® ä|ZL§Î³ýÁ}z}çè R+k©ª(WÝB6ô{É«¼7¦Ö[íRcJ¿3ÙlÉX¿å©Æïô#U&N8úvzì½pà#6Á¶ªÖuû¸Ñ1kTcï´:ÖLÝs\\n8\\bJá+²Æ¢ÁîÙð­Éx£?ÿ]·¨,âXeh^s°S¯o=ÿxÑ£À³.ù\\boìÍÚ³=ÂÅKÒõô5;äùbá{T:ñ¬{¶ÇW{B ôÄÓçBÕ.Mvsn¶~Aø{z¹å0«OxH^5÷.\\r Ù¼C©õ2Û%°fÍ±5­®Q"fÈg\38ô¸+¤d^e½R?.qÁIm¼j½v"ÓëzÖ®8h"#õß(Ô7ÛÑìmâ@7ÇÂ¸|+Ôä1ê\\n¸%lRN\\bfF¯ªèä/ò_ºN6p«Õ]ÕH_]@ã×Èö±>djôyoÑh\\t&ÅøLìù-A §!ðä£gRb:½§<í;¯ÎëðçFm7f"\\bt\\nÜÑÿÊÏ¾{\\bgë§Ý\\b`j¹SÃÒÇ»LÏË"oº"'âÜ±\\ryÿpSy-×CñYæ¢1¸Â¤Ë»SÁøo+êq-Y¶!áwâÒÜÔßé<<æYÜïc,DK&µ¤9ÄÊ|Æ âNáÜxÛo£µ`Æ;(C´Ì`\\t\\nfÜO»4®É¤ã¢ûdV,Ó§±»·örÂ£«¾Ggw-úÝùÆ!-Ä+Öáý\\bàHw$¤Ì¬7àÅEC±9ÉEâ=*ãÌþtóøR©(â|[¶<\\n0Ñ61ïSòå¹ì)¥öðBà/'ù?ÆNUiÖB%l¹f( æ2+ú«²$ÜÆ(Îß¾üµ"Ñ¹«ØçZ0y°#þ.CJxIUfTÓPä)õ*ðÕ8QpÓIjÕF¬:ìk7ïGe·Bë\\fýx¿ô9a¨3®DëX¨Ö=ºxJ¸\v&Ì¤cJËÿ¸W Å`:·I$¥ä$¸ëÇ½' W»§=]ïá²»VÉÂuç\\fà!É<8[síÒ\\ftXü\\fMK§s\\fUÖÞ\\r¶¿FS8\\b4Uox£ï¾õ48,Xo»Þ~}¯ÙÇn¯õ2~ãBhÚÛ>úÕwK>¬Xn²'Ô] íÍ1^:4ë/lp¢4gÏ$ªyTpÉ)mÐzK±|¹Ð¥²Bxã R¡¿#ü$ÉÝä°>g_Ö+ïNW3¡²[æð»©meQÊÜê¨ÄOÅ+¾f¢&ìtÊa~¸\\r²X°ÀÏ¸iwÄÓNªGö4ô~uÊ~Rjâ\\tLâ\\tñ¸ËíK«M5¾\\fÕS\[6ýyÈ¯ñxÁ6ïëTBß±CÜÃ1£`®~\\tÊB!TÚ;1K ºÕË×/6HÓÿçÊËÄÏÒ}ÝÚ'd«0Æ3Cé<I¾@*4ürK{!ê'H³5'ó§ïÂRËKH}rXgäz<Ô³c¨Ü2[Þ½\\tÊÚýpµjÓæÓ{í¡ê½ÌWdvÕ¬fíÙ$§;Ø+¿¸,XÎ ø£òDóRg¨4í¬î¦ïàF·R> íbÃtùSå®CÜqÊö^³Qó©U?y(0°L`½2GØDý,% è7_@/C®éÞä hDº£&¿åD¥Rl²°H"Ý_CÞ­ØõV÷vVßEÀ<¹ÿ§úÈdÆÒ¾¶ÈÐoó¹Aë$ÄmGpÏºDñ¡B5|ªõB¾î*v¬mFswÓÈ#ñ ÔàécxîQ71 \\rÃq :a°çAµ­Í¾þ:²)¡Ú{±ýõV3µ)±ò´G2"e/ó¾ãv¬ºÐ»«åÆò*íCâ*ÆÍÅvöÒè\\b)K8j<äyeRUÛ¹ëÜ\\fA®5|)Ï<BH÷¯ÆêìÏµ]4¼A!~2¹Ù±~"T(U\\tG.Èc 7y´Õ¥ô®îÂ£Ý`TÊõêDU¤ÚÎ}w@ÎøõfÞñò¬,¤ÊÜLN\\fâÊ(c&ÜÆ&vè+=?Ú`âÿ§jc~øóÅÝ`RË,"³IÕzc¢§&I¹=H|0kêa¨¿FûùLö*oÞmÈ6ðoÅ~¿Îðf72[]7á%GÁÄø~Öÿ%*Ø®Ð±h=õi\\fÔ¢Myvå\\n­iÍ>îLÜA43:NÍÊ\\nadïa×_ôâ{âQ*?F:(ó¡éù47%ÆÓ:}¸QVøæl\§rjß=PéÓ N¿çA¥Ä§!ü®S}f/8jÃ_¬¤;áÞIßßÓªäoô\\r¤9µì9ï¨±:3y,²]\\bbçY&ù@!×'qûóí\\rb¶ýîôu,N«9b,:ö{@g\\bp »Cøj·NóHÃ\\tªåÛä7âÛÓ)/\\t]çêµâ\\rþ7+ôEÌÝbIKéî¾¾Û¡ríyfôîMyro\\bÒ\\r'^l<"ÝQGÐÛV>8\\f!\\b\\t«½4Èsé>ÍÞókIm÷BÕÎÐe<?Ý¬Ljm°cw~ôê§åp<"ÖàCw!!òêðÀKýz-As¥q\\t´²+õ".tE=nmÍÝ'»f8/*Q#]©8 PYePÙèn÷ìðzºhBÅã5M´vç³´ç'kí?ØéÝÄfòû«G×÷<}Q Ù°`vÆÔyÆÖ&¦Ï¥üä.áô\\bsç,Ü|Ãî?Åy®ü"jV×u+9\\r§õÀbâ¿°F÷°Z&½£¦+4/£ ¡ý`m­m$kÚ\\n´Zx+(7¹²2Æí|b(ðG?¥C\]³r\\nì÷Ç­kùãå²ï2à­"v§]O¡døíâ³úÚÄ¡½ï2IpýâsX;TnXÎ´¿(Pþ÷i\\bÄ¢OÒÔðapÝºe8çc=5¯vv";øÔ!¶QNza¼O³¥·oZYÀÿYdþIÄ_þ»\\r¹X/ö ·ÁO¥*ÂÈ0­a½²dOÎñgÔ¤&Ûþ$»®ØðÄlB¸6º£'zc\\nãeØÁÑcý£ß67·RÓåë¤Àg·q)ÓPV4ÔM¦TyXÜ\\t?ëR\\r3H^¯´þ¬3Cªê¶h2<7Y_Ë6ÿW:"xÂÒMTÙjáñ>7¼ÑPÿXµp¶\\b$ì¹¨öü*c¨Ú½AÒA2nùtÆr2$èí¸¼ö¸ýôC^á|8ø\\tmÔë@?<E®2ÿG¦ã&xufØjc[¶Þ2àÖs-¤w$@ÈRá\\bÿ/N!xð¸E\Ë\\rkvÿÍ±?ÜeIjZnûº©¨SqÛm(vå¾$9uB$ØÜ­·¿£`x Å+Ø7¿C~÷\6Û)yù'ÖîcìoÁº»ê{"aîø5áÕ\\f¶6<}áÇ-ôòFÕò{S Â\\tÞ&d\Ê«\\t- SlªÖÐqúÞ*$OVÐ_Xç&tÈÅ¯!ªU%³dri.·[»²ÝâÀHÛáÐÊ÷±*F× ÈòýÍÄ^¦6#!k=ú~_¢mrCôÔMþúy¡9¬±¾¾2pý¡ ÿ?0×p.tñÌùdÜë§%>÷]-ºåÁÚ$ï\ÜKbq¼ñMü /ÒaLñÀj,\â{U¸Ç¹]AéÃÖIÄ¾¢®ÇäX"\\tC µ2'¼¶NZ_½#uÆ¯Jã¥s/zÜfËmZ¶rùYØ<3»vÚÂI)Oë\\tm×°|ÄZ9lJøDOóêµúD àïòÞ«Þ-Íê·7,Þ×ÒwHK²Æª{Bðáy!F3å+s#¡H£V"ù÷o2·¥Ýð×ÌØ!àß+µ¿î\\fÂ@¹WÜÚr;Áýn(0)çÐ\\fJ/DÑá4Øec]tô|¬ ©ÀÕD°7ÚWæü$ýlÛM×-ÂFÈhyKIóC<\\t|~}Ò>Ä@DèMä0#4³æAGy®p\\r¸`Çñjg³¯:>´c]µk÷ÖZu¥²eÇX§MÔ:ªí±ðIè¸0sÀs7TLö zC mXN±ÿàôÇ²#±gî)·MÜÐY&k%Uþx¤|ì§îxÈ"fÖ ëdèã¹Õcx±X©â)¡]>ûõö!K÷Â*PáùØu\\f·}ÅñÎlÕç°fã°7É1eea²»çPpÔa¼µ·+üoRÈ8oî Êm¦¡ûbAµ°ê®-g¨VÚÏ`²dðßaÒÇübCf«¨Í\\n®°zr=<â³£U9mÛ§ÍÄWàÝ8nß#ä¯kqÜ\\b£o*%QS»g½&SäA¬G½»¡ÍpÉçBfXè ?³û;ÙÏ®=Rq:8£`(>tQá4§­;+'/°ª%>\\n\\rõ6mÐÎº|Àwõz«wõÅâwÁ²_MN3*:à¿@~/GZ)IÉ)JåªZÊ+ÔK°®Þ\\b?¿ëÄÒëgðA,u¨ñò\v¤áJ2q2lèçêÃ­~¿êÄÒéq×Ð¾¥x­ÄêDöØÃ/^L]¼(q!uË*qù¾,K©:lWÐH®"\\b±=ù\\tmÙ¯§)Ü{·Øö'@ !RZÉõ"â6\îß^Xë² Ãð¤4£Û¢ôÚª¨âe«#ý1}-É*"BhjØ/MÒ×Çö$òg FÚuCÒ­ãÄ*õH]ZëêVÉÈ8QÏ) Ge°*,]ÿ©u\\bðüÉ ÁHy) Dí (È³á]Z~$\\r/ îÞ9pUÄìæ[÷ÒOÅYÝDö-"µð¼ã¶3ÏÝwIîgÃwP!ô2´¼¶'5¥\\bqØ\#ðá¦Ç. "Á®-¨&Ü_gµ¢¦·5ÐéMzÜOÛ¢­C÷ü¤®¢ÖþèòJ ¶öO¢j:)íúumtHÆæ¯VGÊ_WÓçiÞ²Ët3üz´¦i9NÕVlMè1|[[£û¤+§Äð^É&wO\S!#Ö²¿DÚë?-ò*[FX\\n^gþ %ïäÚcâ«÷\\nbÃñûAGÄ[ Ma¿»{Éri¬\\fá­£KF ,aøpÛ&i5këÃHü±¹0jìn\{ì/2J%àôìÞdãÚôìø½ç,k/[.¼p²ZÁûÂUÛõH µîÕ­ù_cX¾Ð¨É@¹¤àü½ÒPç(8ãÐ=_VyJ É´Ëµ«Â¢ìª(×Òlñ­àè²p®üñ]Çk9@ì]/zÇOÈJ¤\\\n_IëzxÈý=!}¦_I\\fT.¥å7Ý\\nPOpî9iGcöGãÛ°\\tª5c×Ó2~[S*ù^Î½ ²Ìm½òRãrÕD©S¨3O_«ìÏ[4j&¸kZ1\\n°\\nU¡Þg§B2q*Àº{ ùW}\Á®Af.àk/æólLLmÖåµ~\ÎRÈ+N'"öÓÄUcyÀOj4¶RÎ\\rnRæpn:Ù4E"üd©×X Ý\\f§~\\r2K\\fÅn£j"ÒôO[ZÅ¯Éb6ñõy|µN$Äpµ^&\\tÇ#qZÏ¸46Æ\\t\\tßm¦áJ¼CØ\\r«]ÌObM°1] =3¡²òµv£ßÈ×/®_uæ«¢99zï÷$·*nIC\\b\\f%ôûDÀ%r°aÚ{+:½VÀC¬CÆh\\t{N¹Têa{k¦ÅlËØs#BÊ\\fäÎã?ìÅê¦Tk½8hBmÇ ®ið_iÔ}õØ¶=Û£Db[«(^¢çµÛ%÷Zi:ìeï·ÅBbC6+ZòÔP³ÑPDü¢ 7ÒõÌ½>8û_Úõ%|ãr\qü=ê;ôöøÙ¦jæ,KÑÏ¸eû}îPØ!.P½9sìR1wÊç\\fO»SNáÔfÚÙÃì¼¯7·ÃçÅÓÿHâ|È\\b$Ûÿ¨TÑ­\\ry)&igüýaãûÚt\\r=0m£$dñ7ÈyeK øÌ\\fR}g¯+·F÷ýEÒ~Õ9¿-K4SwA?üKÅÄ^Q¹wÞ»_ÿ¿vd)q6-\\b7c=ð]ST]ü²\,8¯7áOâ.Iã{äámkrÕµ7á§ä×QU7`\\tpÓ\\rù¡õ>Ì¡?Éj¨òÐßQWSwÓ±©aÿRçîQé©þÈ]{F\qÂ(_ûN|[#Æõ/.?qmRrGý*ÎGnÜUKuÛrÒ\üÐ"L\\nÑ·qàD{Î+vøÓ82¿~aÐµÆT\ÆTV¦j³TªÐ\\fÙänÛ~«1þv}ú\\f%_Å(G{¬¢¼Q¡väßÀæQ"V·®æÏé:sçÛë2<&áNïD«Î)#íÒ2Èï,\\nëEUçtñ«©Äözää$róãf?hòñqèÆ´¤ô[ãE°î#Î¿þB¼\\rx´o¢ÃöpÀ<÷ðç50/0ñ¿ù`OîÌFh½è7Ä=æÑãH÷Óu\\r7ï ÕêèÖÅ ×³l¨-Ò,ÂDI4<s>ÔÂÞ+À·c;2ÔúÌ¬<Ä<UÈDÐ¸°*>½a$r°f_@©ýr4¨hx5ÚÃ*Q%õ¢ëÃ%çó±ÈÄ8`m³~|~ÂNÐÁb»)y4j»£¥íÔºÇx5A¡¹Þ+chð$á üÍmcí¸Ï§Aª¥¢¢%ìV85º£\\tX³±þ6tSPÞA½(¡«zcå±ùCD_ÓDöêÄ£©Cü°c\\nwøÂBí6`JoFùà,¡@ïÒwuÆðk\\bÆÓWìJû9;TçSÁLzvÓ¶¹ÈN \\fÿm/s CÒÜµ÷y^]5Ñ¢ÙEu\2ÏÕB\\bóaÂR;ß£ÊÇIc:g\\t±)ÏW¥Ç0.-ÙÃæ¥ÛX#\\b±aµ y&äJS/Ã éQ¾<Y@(il»~^`UxáãRº¾>¬h*xÇ­0Kß¶aQÃ#Bü#âW:_¬g6õ.ÞÐû7 qâÐß\\nUëÑû¢mWº¾ýÀR\\nWV(s*®QVæÁùÑÅºØRYL=zmÖÓZý^(w·èîÉ}O]Çk^è¨Ñj§àÙðuÚP2!\\fzáEÉÓrF¾ÀØ¢pT¸Vó®°z`Dtç£­b(v1§yY¼¤Mïø¦ý\\nFâ´­cfþ»ßÎPF!×ébFÝÒ¹·EyËR£\\tÐ©,þI7[ºªï?£öÖó­uUÕU¯S\\b6eÖ7Uó%}²]ÄOÜVlÌ>LLY(¸é$Íy×EF©7ÃÙÏë£N[VÏ¨Ë!¼ÖfI¼wxßñ%®sbh?èå.Ë½¦ù%ÞïhÔûedã¶·$aÒ*÷±Øðbgêüw°½boxñÍn¥Ð÷ë÷ªôþú­©Ø*TS\¿îù»ÅÿQÊKÔé¹ZpíkFª\\ta-þP¤¶Ç\\nêùz@Âw\\f?É,U.]Oå°^²{º kZOê²¤më¿mé»èøØîËç%AhPY{óRwùØCê¢X¬Øäö§$5QgåEèfßWêDtøeröx¡ðô´.x=AZ%ze\\fR¥>4eU[DÎÉtï3¢ÙÝ½rø´¡·(1¨\\nM­V´]ÏÙTôj¤Þº"ÇRHVÈOíÙ)ú*~¥¥o=E £ #<À¸ª%.VÜ CR"(\b1ÚR*µ]¢GÝ\\rr¯¸¼oâ\\fÛ NN#°s2yQ}Cc«òbÏýÊ)D¹v!êGwÂñ¶ýúÞî!lk¹\\t~»=ÍFG;í`\\tßþâ%³\\t,8:\ >òºC\©=P¶ÉÞ\\bÓ;(%ó§ëâOB­ÆX%^{\\n>kynE¶yCß\\b#ÌOGi½½n°¥oVç3tcHÞ\\b¢BÙp{ä°3vÖ¼ølª¹H<e¶x}wïò¦ÈÎü¶6m8¡ÞÞ\\n/ÂRiâYLA999ÊÍu{wotAÉFë\\t\\nîí¡;ï\\r§æ>|ôVÅG>4r@DNj\\t,°áxÒÇm#'ElP ³·Î<ô}è ?.?ýzRtúßê-vvÖyeHyÏíÌ7PuõY¤¥(î©Àv#?þæÅW¿ÁòJ/\\fß%j9*7<¨{±F<ã6Ä¢Ç5£¢høb*eP"«Ñ}$Cq¯%'¡¹Mkáh2Û*â\\t;¿0_ô=j9ÞNáìVôÑ¶dÂ<îCÛwú\\bG\\f+CÍýUlý¡}×9\\t\\nH;I¸'
    //   11: dup
    //   12: astore_2
    //   13: invokevirtual length : ()I
    //   16: istore #4
    //   18: sipush #8929
    //   21: istore_1
    //   22: iconst_m1
    //   23: istore_0
    //   24: bipush #69
    //   26: iinc #0, 1
    //   29: aload_2
    //   30: iload_0
    //   31: dup
    //   32: iload_1
    //   33: iadd
    //   34: invokevirtual substring : (II)Ljava/lang/String;
    //   37: iconst_m1
    //   38: goto -> 204
    //   41: aload #5
    //   43: swap
    //   44: iload_3
    //   45: iinc #3, 1
    //   48: swap
    //   49: aastore
    //   50: iload_0
    //   51: iload_1
    //   52: iadd
    //   53: dup
    //   54: istore_0
    //   55: iload #4
    //   57: if_icmpge -> 69
    //   60: aload_2
    //   61: iload_0
    //   62: invokevirtual charAt : (I)C
    //   65: istore_1
    //   66: goto -> 24
    //   69: ldc 'I£#+Ce¶|ç\\bY=RÐ¸\\r;åº"SùE%ÅâV:\\f|¬\\nu§¡\\n¥Í)ÜUÚ¨Áç ü$X\\rº®4ÊÕ8¯¹¢ÿr4i~`ÇHË1Éû{ÇñÑüÑ¤¶ßÃ"¡KÚ\\nÉ³ËpÍ]ºèp²aÊÍ[°õºÐú¹áCnîtâHx8Sí*_®OH&)i§Ôº³²7öýé^Ûõ´Po\\r¾É®.=¹ÈO{\\fKå6AÐa»ªªÜa·Êd¯°ÝÚkäA5­è\?©iPëµ¨F¥ÖË{íxXHJk_üÎð¿«ôØGê6éiHkÕÖªÆäÎû¡ï8rÈ(Íx|/aö¹±PW$ØaíÎPé·ªK)ÿé:ÑÍ¨Y^âcCzcÓHªüs$r=ÁM¶Ç<8æVyÎu²oû~Óô£#|cñ°ý~õå3îÀr¯° !~\\t\\f<&´ü_U»Ê-~msúþ¨ïH±Û.Ë&ZÔc¯ûÇ }ªI®\\fs^8:0ËsO%ñ6Ñå+\\t?Ä\Ó}àÇcéMöcçhÜÅu½bÖôkãB`Sj¥RlÌ­_jV=_òMK&+×©¾íÃù#¼þ0ÿóq}ó©}{g1;Ø õMÕOpâM tnD¤0\\nCñ0Ã/é\\fLBeêÈÇ¨²ô£ê¼v¨m`´Pèë?KTü¥ä©6&ÂVÔ¼Èíù<ÉªêL£4T®OFë$_ÛØ:Æ\\tÇDgú[¼í\\be¢oC3ið/JÉ6(?;¼úeÌÓùî£IÅÃÍ£½©ÈìEâC«&«£#\\nvëµÿMq ¬V¢gF$ÚaÇAfcÄÃÎÃ3WÜ Ì÷¦ÄK}FBÏAÌn¯ªô8¿Û!t\\bí\\nºX2%i¢jn©#)ÃÑ$Ô4=^®º7V\\nº§R]¹ïÇý~/;ýÓ¬ÚßFé6D9ßSí!²ä,]67ßT)Îþ:¨ãÝâeØKÄÆ5£SÆÒÛ°¾£ASæ%jò0ì.Bã'âïùu*ÅC²vþã"|C^9£µ\ôÈÜG9K¬?ÿrTIÂðäá¼{g!ÖHìIÁÆÖ ã4 ÷ý£;é¤öÏ1a9ä`âYáE@çÜ.H¬tÁÖ;a¼ìõ.XìÕRì°t ðRkÐwóoºTûÞ`:Õ²q!àC<z¶Hxú¿××\\rCráåsxå`®iï½¾Ã¥@÷½8Qï\\tTå ×åÖJ\\tÙ7¡9¸Ãæz²¸\\fÄ=b®Í\\nIÎÛØ¯byuEÍ_ÖïØËãl£¥z!p©FIxvÌ¶üÈÆ?U¸«t-M ¼y§\\bå'¹ÖÙ\\b°1QLÊêÍ[@ù¸°½1saW \\fc@ìlg®mÝuHU´À·ü?"â©¨òEªíOV.=gªX+OSÄi©J¶`CBL÷ºPç@Ô/cüTªõUÉ]hÍD åªôR¼Ãý8ù¾\û`S&PûÐW¡Ý9×å}®'1¨ý$d7ÂÄ4¯ÄU3îûêmxp´q§¡\ÄcÄk°¹púÛ£yÑï$GÌY^Ë?\\nKáÔ´w6wâF@ÓoêÕ|/ÔÔìùubmj&ÄÍvÙ[!Pï!#ØëPKógDä¿DÙ¨ì£/è¯3å&3®\\n×+ÝgR,.\\f'Ë§ÜÓÄf99}~mñÑßHÀé´a,¦ÐÊ~Ò¨·9Jc­}}ãQm®ÙV=î¾dpÀß5è}¢Oì¹¸vy%}* 3¸K=¥FQã³3 7ß\\bül$§B<à:en»A:ÊV¨4ä6©YÀ?×oÔ0æçßÈxä:& xr)gº6¼Ç´©:FL<ô=&Ò~2lU1/²jòdéèòÆÆÐá¹ÓgM% ¢ÄÅ8AÙ-;yÿ\\rQ¤3ØÝñÓ×X3[QÝðæU!**òYàS¿ÒÌ'F\\tfÍbyz±$´3»4*ûgwus@¥ú%LYYaîÇSt­#Ä%>bÆÎóaëÛNàåo´\\f6§ÄvmðªØBJÊ·¹©¤m¬ðÉ@sí8µ£i6ç;Là¡:)µy±ïFA ¿\\tbÙà³3û.©+±Nø9;9"¤/ìÐy]z£o$'¿äwvÄµ:Væå×þB_\\t©¬f>4Sí2þÛ;éáëáåî0Ø1+ð/züñXºÚ1Oå´¡w.ïx)ä×ûNSÈá`«[¹DÜý¼3Ì9HcjâH½n¿h~èääÎJQæn+¥¦Ü°Ï\\tX:®µ='&Ñ_\\b¥®>Ï³t¥"\\r¿ÎHÖ1·ìÕÿ¬q7âëû><ä\\t{N®OðHabþÀ?à'GZ"çShÞ:}(/u@T¯²tÛ¹W#ª­½?ß/OºýÖ5ôñgâ#¼ZàI5­æ;¼«cÐmÌ;Ð¹ÑG>Ómn%V¡Y #\\bGjOÅÙ8pERJý´jÆ¡kJ$lGÛøàÇüùãõÊâ_É ³Â=$\\f÷JRJßø8(÷s}GýY¿Ö×4TL ªBEÞU\\nIXìõY:Â«ÔÏöÜ×¶N(4ù#®{øVD*KÎq{ë>ãm²¸0uÜ~}­aÁ¤î/qói¤'gj[!ëý¦ÏfÓw&c}TpPäÄÜW2)':½S]]DÑ¿Êc1ò4°UêØçYCk¾³ðõ*¢½¤JTÞïbÐ7~ä«:Q÷FGü_{XBù:54º»j¯Ó#¯sÇ*Á¬»®S{ÖÊjl>ÒºZ²ÉÖ£äg÷ê\\t®c¨è©ð¡Ç\\tßý>ØL²ÜÑÒ«ÜB/.±a~{ÎÅ$ÕÖú(ðDzGÝBèä>Óz8G©Èëé?^CµÏ£~!øècäà±;Ò6Þ5^H²GûV«ºðªä©În3²3¯+Ïvs(þ!½iÃO¨.Ilì?V#"¿¹Ô4è+å\\n#ÁsÕí}pÐ9á9¢Ðõìe2ÔïÍµ,Ë°h»ôVÌE{hÊ\\nwa¡ô6ZC%Ø©_a)cß¹ÜÂd¯Écñ¸ØÄG±Ù¶mZ½!hÃGõºúÔüåÏ5 múàmàB³5DôûZZ òÈ\\t u³nB[GC~ðòMaw;I^úpá\\b+>Û3îº«¦u[ilËÚ£[¤¨f&Ç6<R¤âU9eÕÁÌ}ÏgúÒÑQ]ÀWbb{ôYðpLzÅ)ÅýÔB°ø^æÝ6­\mm$`¯f>ùâ\\b9¼g´bB¦ºì^ â!ÛXVr¯7ÑKJ>$ä³þ?îæöÁv¶\\rz?\\fÚv5µS5è1c%\4(í¸Ç=Ë-Ìæî)¿@9Ù[éRU¢\\nÒ¼·ÀX@à\cA½àÅ{½TFb6@0O©À¼ IÊ%7O%6øR+¾jÝ¶¥gÐL)È®ÀJYmç|8úh":­\\bFs9}-¾âdë-8·_ýo½zÉ¬)=Aß~e¸ê¥j°¬rS/\\nÉö^°·ì¿4+ÛaYJº®»^ãÎÏì#üHÇÈÞöÿ¢Íy9e¦(_ñ¥_ú[<Å>BÊ*UÞ}°_µ·ç°ò>zUsrð¹ëä2É|Í]\\b×ßÏ½Ô®"vpèÁPA_©UuÊ\\nCåÀ>»ÏÐTy#¸=Im}dà_5çD|rØåAËÀ°z¸ãË?:NÕ¦tÕ¯M)sßãÎ{×|k\\fÈî§iq¼ãx?÷n 8zÛàÚïg5Wd^ÇÆø^>$½à²ûXÏBBäÜ7ûüö$G:4iv Ûû;Æ3tü&Ú§£ù¹*áÚX}x`Ã°'n¡J+\\b8Â_ÔøFNYtÞÝ®~ NiüéüÀÇV66nÏáïCÈ.fä§\\b\\t²Û`ª¶Û×°¯lñS(ju8AzÃX£4ÁÖsAãnV÷Ø[×)¡PuùùÅ_M]Uo¢lg·U-Ä9¶é<R\\näö+ÊõËü\\f}I\68¾ovKþgAÉ}ÂÂ>A¡SØ-¨ÕC¼x¸æÊWY`¿ icü56O\\nB,Äµè%FLBÃW]£ØæþÒqRñÚÛé« UOTY1©ûþþs÷9WB2?ûª«OêK<[ì½5Tú\\rHìP¬õ[Lñ³?<}ùàgz/ïÞ£ß}Æ¢¼á§Le}º<ìL[ÃJÖÝ°aÄRù»Ø¼4âÅDì²3PîL?¢¤ñ[h¹Ví ÈxÂA#kKËUÜ°ÈÀ\ÚsÎi#µW\\n¼#Ââ¦ÄÎ'2¾·á*lá-ýSÝ+5íÝ9pÕw²R£bè\\bL8±,ô,ô[f&éCRÎjóÚò)sÄÝµTW >(":Æú¼²¬uAà0Aÿz2Ø1Û²zs¬6½9´ûªXøä×þ·HôÊÞ=àÞ¼ ¼dFÍæQ wtÇ2`NÕï¿6lá©W¬a³MRR¥`ÙâË/2ÁeUIÐùãEÆØ«ó××['ÎvQñß{~Ö7¾ÕUïi1æÈ×+­ÞÕµ8^G\rEÑÓ×Ãþ\¾5]ýúË´ý_<ãX£j¿¢k;KRòßiû\\n¥,Þ[!Cºa\\n,ä{Å>ÌþK<âM>N4!òGôÛh1b7dõ&é®bV2Op^czÃ{0»/ÌÌ®ê\\bp\\rI!»ïWâ¯Ë#,/ÈêF6'á"«lâr5Í&´¿ô1Öb\\t¥>¿þ|2OÚU=6øí%u-âõQ8Uè¬Ó|Í×oíe¬2oy×\\tv/ºúÔ/Íaä}ª¯§åàg}ûoMg¨¡¸0·z-\\tM)EPAZ &!gBC=HÁ¦g4J¦T6ÅÊ«Ç§ÇúÝ{$ñÛ×d%ª¬r?r¤¹vVÿnãÚßýÛËæËLuÿ%ÒTÇÿ8"Tm±ËÒÃv¿)yvçás2Î£j,%l1Zþ±£'ìÍCÉUVW1!ÑTY`ÎMwz­k\lHIü/ÌÏ@Ïp<È×»BTÌÏd~|N}¤\\bñùà6¡xk¸lÅ>OJa\\ru>ýnÅâBZ×_ìÞ¹è&%Vµ¸®í`å®ùò¬\\n1w¬n¶üÖó1Ë*ÔCF|hîakþÖ±qGÿo¬1¤ô²ÇkgQÝO±¯ÙV²Ìí¾Ú+sì¥ÜL,s4.ô:Ù°Ã~HÜ1GçFñß@(h_1\\bîMáÞ"@KrO\\r¿ÅÔX9¹f¼SÉõkÔâåß¦õÍm"àò\`"'Lz¡!ñ!TBÖzÞÊÍ,ÃuÞ²{>Ë !ÖÖ±Î8m=LÀ´ªM®ækô%6ÅaÙ¥ËõoòÃ.!¬-á;MÑâ;ó§ÖÛwbçþ'Ø¨¨]³fþ¹\<Ðiêr.¯ö¦a¼R}»ñ¿Wàª~þéÀ§8×Ü >9½¨ ¾8")ZyéÛªpÐôo­I{ãH'°²ÈdÎ©b[ÛCx]5Ò³{ú±8ãgÂ0iÙt`ùò;pYtªò1&iØSugíbøbt89ÖéÇ¶]Ú¯S;èNÌBOÓ\\fK¿Ü÷/ÝóåÏ@i­È2¼ã({ö¨Î|Oä¦ÓS ê®ktz  8\4EÇå÷ý5m»ïC~ûû^àK<Ñzâ±q¨.ØÚªÉç4{¯ëÁDÞsj\\t,>ýåÚÂ¢\\t<²÷gjõ2ªKsÄÄ$´\\n×t2j\\rÌeÒ¼òó|)wEgüÇÎ_L¬!Øû`"ªßbMÿû¾WôDÖ°EÕ`òÖÇpÉÜ}©FlÑSò[G\ÁHõ¥Yä­gì#õqSw6ú2b¶~iùduÄ«ÃN³1eü)4¸ñy=¢Ò|»h+&a~W¿svIÝG1÷\\rý\\bN\\nüªçe¡QÄe÷¿#ÉÀ?_¨©ßì§ñ4¤¨æ&c7Äy¸2µSÇ8¢}õV³.£©Ì:Îi}ÒBWgg·i¾OÀ]væ³ÓJ\ºï·°¡fÅFæÅ\\n9aÖ!aÊåìòz"M$Ä¥ü®q³Ê4Áiè§¾¿ò<f)|Iö`2=Ê{zó\*6²S®¬dOo¬Ý§û)Ö©·EÁ«MõÐcÜ±hè~-B¢î?EUüöØET÷Î¯×'¡zÔ%èv­x¯Öº`í]þí®rjuéU÷F¤¦æn$Ò::qø½±VñX¯®b\\rßfÇÍjÛÿ^ÀfbùÛñN;s§àO.ÎDÿ-È>9ûç¦q®ìò¦èYìO(ÞZ\\r8§zX õë0^Ñ¡åçc¾J/[`øUvàWæ°Ä\\të\\tD°4¢4SéT_ÐÂ,¥\t\\n0B8RêaÇØ!ªs]4m¦11ab +\¾iñàÒvö_m\\n´1²ÒtØ$Á?°æO¡b¦#~gÃlf(X^",ÙÀ^»]nB«T3óXo}üÐdÂx\\rÍ^¸ê6Ìïµð¦Î©x4o4]õ'0®xÍQÈLïÇ¨îÄñ¢>sö|ñÂå2¼«®ÎÔÊÄÛýGL\ÒÇyÁ×CÝÕLT>ÌZªæ·\YÉÈÉi¾UëÙ©6µÌÎ)½\\t|^ÐàÐâçÚMñ,WòrK8o«·\\b'"ß»»àMõ+ÎHªQ#û )\½ä°(Zj{¬üãÉ{ôH[`íÅ¸n!bsýÐ±\\f|©mØÕ*g&Ê\\ny%ñâ b×cùæç©gTö!w²»fÛÖ!WxÓB¦?w,UúÛ(ÈhåwZÄ´¸g®¯+¢ÍqÛÄ«5(+Ð¬3WâÜÕÖ3#Ìf&-¦Pé°EL)/p%C?N<ñÙÿ¸bvÞ¤ÁÊÇbøÌõ³ó[4&}¤ÿ5ÙõT÷º+?2±hTÔµùöG.pÔ`$6¥JYiáx3T2-Ìw9ã3o.¨¯Ð5Æg\\b~êÚêMîéµr4ÞÈr¤*\\b¿9Â©jjùh±å:S³jâKÒÛ$&õ*"ÓV®(`ÙU.vÕãÌiÇ<À¹¤þ`çGfavÈ0:ýÖ³pFgnVð±FSÊÙÊz/òü¾Çj8«(ª]'xô!7pÁifÂ@¿ð¡xÑUKÅô\\f>[òÁr\´oÙ­ónF/(i!*ãÏ_2h,U¾|í\\b8ØÌäÏ³¹µ¶U^¿iÏä?Ð-k:LÂÜ¬*ËS¦À#¿Pä0£îûè&C¹m]*"*ÕÎj÷2w?\\feZ@Z'$ÍÄ§Ò¶|x°0vmçUÄÝÎ²=ªtÈ:B}yaÚâkm08&e%=å¡'d-÷-ü«¡=3:´xá+J3¯´\\bHròÁ+÷ÎýÜ-f¦x·wÛ£woÚ6çð©$i2\\n!<^Þl¢C*áRUðÉýãÛK@öEUímÍòMp:~[[åÜ\\fÉûJîFØ}å`µ¡ÔÍ¾©\\rÓòâË$ýX+2î?áG7¦ÈÞÎC]5%ÞöS)³¬ÔºË'¸ÊfÞ\\bZúUçû,ÿñÞù)ÚÍil07Öé&Ï[½].BV8Ú ,Nt'O@ÊáeCÉkÚþ\\bëSQü<+\\fÀG³ÇyôÐªðìd12úò-×ïÙøòÉ²¨UÔì¶á 6oÝØdFèæ¹6Cñ"5äßþlãÿJÁHôº.{Ã\\tPD×´!f@H/ã<a&ÛñvçXgí|,ä3LææuÐ#¹¯ºÖóàê­']ÿ³3Ëiìýc¿>\\t-ý%Q×*¢9Ç1¤;Å+Ë&cÒïé m4M ÕÚÌÑÃÔ¼ÇFÒ§&hÏpzNªjmm+d'°%EM&,Iað·AE] ºyÖÒÕõÜûóÚª6J~8Úó\\bûI,+hvÅ£=éIE¢å\\bï÷±ULJì/wî¹^v-ðñ_þ:e' >%)7ý\QÔþOü"¢ö·ÎLNãÇ¨ÑØú1O%\\ru<º£Vúh³+çÔÖ-dMìº¾·Au¥CK*µ¢¶îÓ¿ö}pÙÔÑùæÚ5÷*U(æ|ðàä~µ^W(¿­-éÒÔ\\rÑ&³Kt#XArKöÓíáv89êV©¡@ì»ÎOr²\\r60Ñ·á¢M9Úí&Ã¢x;Jü+®Ã(Úúº¸ô½ã î,i°r:TÜYetº¤C½ko{ìA7¢÷wªµ[¹Ta¢´þ>à(Y­wN¿®t±oTT¾#g6ðEyfIîÐ¿¥ÕÍ'+Æ,<«ú}*¶\\bÛ þ»ù0^?òiëðMÙ¨u¿À°ârî9ÅÜ2ï\\nó1u\\fA¦Ò!zµfñ\\nq >êä.âÞ*®14*¡r$<!½IcÅ|3óAf\\rE^ ß1^> è©Ìé+¼A~K;gîMË¥xWK¨|Ýíe±9Ýf±±ug«¦½qa²]Ò+H¶s±|zÎ!.¸¦a¥ xr¨\\nÊu¢7ÓzOÿsÊqø¦j¦IEBó§£Tr7)>v0*¤s·ê$ºë¾¦=;ß0LíAZ1¨úzIGgtef®{ ËµD}"J5Ng®'þ¿v:F©AwòñL®ríd ¡ä¹ÏM[Ý\\bm¨%¤Ëö;c×rP_²A\\no ¼oëå`ÕÓd3£JÔBð¤+äÝÜëçÉÆ lÍ¼êEV2e6j"!"-°QJ½3Ê´ +Ø\\fMtE:`\\fÅ)§3ÿ»@mØX=°F & ©Y=÷cr¬/Ä@OéØv<JÚ`j±E1,»T´âÜvd<f"sYCèuºoz'¹YG?¿9·4¯|mÃ`_Ï´¥Þ#0*3ÒT%RÝg5ÆTÜs¬âàjWUxEÕw[¸TsâiÇÉ ßÏ1½­\@¿\\tà,B=ù¿±e*·#9{I¾\\tþ¯f jÂbK¶:·ÌImê»î¨´gZ¬Ö`TëÙ½=´é^ANß¼ÜÞð=-R×âÛ>æ[òm7xç¿¤\\nÄÎF¨ËÞ4öÏºcæ&=1Óî9RN«n¿øTs>¶Ï²Èä3e4÷÷Yøðªh".o|ßO7®G8+¥ñµÚ*n/à«Dmè0Ìé©H=/nò9Zd.Lc«:ø3M\\bÈ#éê}:y¸¤üÄûÂ7w+Ö°j]ÞÓ÷°ùr§;ÆIÍPX' õ+KÃ<¡èpqÜ`Ä:bÚ°ÛS (}þ£=]áµÁ÷ÑÞR¨õ»ÐDô±õeÜHP£Æõ?DfOE¨ô#°2¯Þ\\fPÜÌRûah´\\tègº=a.Ì,{â3`Pó\\nhß4o¹¯ìvÜ¸þ=zÐø|ª/oå$¶Í?P30ôZÑ8(§WÌlþç,Mó¢F¡ùs'Í½Ë\\r¹E#¶VñKÌ4¶¡¾\\bö¸¾ÁWãÓæXÏ¸¹Olv_+4²æýáÜã¿àbeÿ\\fÉÞñu8\\tá$§\\tÝ &d¼ÜU@jñÑèþ³4æÑnX3¾ç@ì\\t"±¾Kq\\fõ\\b}fk+è©pþï%û@/{\\bôéì4\\r=8¢Ù6Ü 3ö­®?i,òG}{1Â-yCS:.¢ÆÒÁÛÿp7p®¨êy¼´±<0ï¾ \\b¥ W²$"0ÊfoPoË2"òÿ¶*ÔÖÐãn¿ì«'æÀ^,½çª6Ïn}³ò«,õN72wX u7s`ææë`\\rTK/&\\r:ÎtÕfÚ>AÀõJcë2\º× ³»ýÍ@<oo­Ô4îæÔt]s¼îñ?ÑÉ_S¬¶WÏºÊ¹¼ùù÷ª+ËÞï+\\fj¥ü×_L8Õ~Çÿ¯&¸~ûUrK%QÀO6¹þ*±y 2Ò%.6é°z¬N]gÂê[?sEØl÷\Ä·ÎÎ?v#Ï8äûE¾Nðå&þìqÁhÜú¿4_z®À0öos±2þôÆV¦jÈÞ6Jñ/¢KÒÉfèE+_êrwâ®_÷ê¸ÌÇOÕbCÈÌù|`ÌnÇ|ÎîÍæÛèz}E9ñZþõÅ=Uý÷)5áðÄ~O\\b¸§·S³(.tcí©(ÝPÄóÐ)§7I»¸å<Å./]rWã+ÁTB?PgTìwKÒÃ\]Ù÷!¸Z<\\tr½#hÐ²qÎHBz¬ÇòU¬ê*·+nHº§ aíê_J¸ÞâÒÇÝàÍÓ¼>CCÍ;<cû^7*Èì1x«XZââ2Èí!jãÁÄÈ³±Íg6¶Då`v¡n¿H«ü$Ûß[9\\bSÄ[U#-ÎÕakNs<]zÔ¸´A /ÕÍ»'Nªç¾AáoG\\r¼OHLhSÚ\\b·sG´¾ïëDp\^z©m~\\b¥éß^I§$ö-\\b{WðËRÉñÃì2½¢JÌëKÛ:í5ÄÑx-ïÉÌ¾xP5Ò\\tÂv¯HZ?ìQd×U¶%\\n·Âò,j´o\\f ¡¡¨å;´ç8tÖÑæeÃ\\t^\\rëÿ¥veç7^C9¿ó±¯Q%TÈÜ]«¶µ®7ü×êu[.IÞ\\rÓ÷ÜWì7?áëHó:N@^íÂa÷\\riÐÜÏ÷+é­@@±\\tÜvxàkav¥\\nú^Ë`ªyìKAGØåC¸,õÙ(¡«Ò³<l[\\tº$=\\f,²Å\\t=«Eð<_æödÔ3>à¡fgùaü7ÇRL6AaÔ¼dè¹` È!r°³¥b÷<Ì!ª¢©$ë}"Ú«&Ó\\bE´ø>¶[99´ÓÅ\\b3©suyìtè+b®/CÆö$Â¢bíÓnTåµaÙ¡òØ´î=OÜÀæ!×IËA¥³FÝVfµêöÔ}vèÍo^@åM»"wÎzõ®Ó4ßÑkä{fl`PÈ¤¦ÜöéÖö)#+j.f0´ $:¢¹Ê«ã&ÃlC§ËuUùQìýI¥¶·ðÈú?ØðVGÔhäð¨hu2OÑïh¨þA²§<ú %§¿µñèw6yÊÅîfµ0Ø¢©m10Ö¥ßçÍ½Á¢zäG× <ó¸ÐÕÇÍ gPª`½qÐdä|\\f¶üÞÔýW;µKkKëçµääKÈÙ/zQIÅ´*)Õüs¼ì@°'Wy¤:óTüU$\\fð(\\bÛKn±Àæ2Ê ­UÏfhd%7téô=j ¥ÜÙ§°K]±z@&ÏÆþ¯ÖÑÛûèóóÜ¾½Ý\\rhtkÊBã®7\\f¼vC4óÂHí-îq\\nl¼¹'3>\\toðÂÈãÿ9¥AËv¸«ê]LIè4^ç*®W\\nÛw§ñ2xHWEC^`°òÕ(Ùâ´¶:E<Aà¢£Ù2Ë¼'Ë¼«9îÎNÄÀÄ¤^s·ÿñ°4ïM¡6ÞÀsÅ~QÁ=Jj/%l39'ì7\\fö(;ÝºîXg*åÿTMæ-½OHý6Üt^ JºÉ|'Pãf[_IÇ OX\\nNìÝýë·ÞÜ]/§¨«(gâª!{ 9èÂ}]ÖµæhZ£¯ZoÕÌÉ2\\t\\nø3\\f8sb¢Æ(s;/AÓHüÄm¨Óp<\\næks£·ÓF¢ñè;Ä+)+Í<³ü;Äg´©ÓÑ0uÛðâ{ª{\\r]+ªï·YéUx2!p(Mû#f)ó¡e./á«b yâ8÷K_OÐÏ¾tQY¦,\\t±»vãv¯\9#Oæû\\tçixèB,±à`};êAÄ\\bÖÚêù¢²b½´ÙgÔ¢UºW m6fÐ WÕeÐ»!&J}ÑÖÍâßûé«Ú.#Rä×tZ|>¥Vl¶iáá¥îdÙ»R(=®(:tg^uC|E/ÞC¢v½½ÒH³ P0»d9¬ÂæL` `;¦bÇfÅmG~YßË;òa·{È(Dõ¯?ö£F\\tN#ó²ü³¹7ù#>ú\\rª¹²ÇÉtQ=»~\\t\â¸+þÐè]FWo ¡Ë*5Q<õÇç.R·Y¥ä¸X1Ipþký´\\r¸´Ñç:×ÃE½W)³G$1rÇäF¤OIaHp2[åj9:÷nÅ/}$oB§Ã|\\fñG®\fª¨r¤\\n}+ôpAK¦d}Ï&":rJÙÊÅÇPFø¢ ÒµÜ2I}:þÙ½d¥dì\\têÔB¢ÕÂ÷©E¬bï|8\sÌA=@Ì\\rÛpù9_àÊB/Üñ\\4N's!4ÓwK¤ZúíjfyVÖq4é/5ºY\\rÀ£ÛM@ g­^ñBz´'Ddú\\n¡wâA\\t§8X°ZÞOº¯\\ræ`Æ"\\rÆú{\\r§úïÎmØ(§v¿ëq1lW>Ox^%Ù$ÜUZ|l"å°ªä©òÝótÀ4kVå'ÊÖµ^·Xa\\fºcËâ¼°Ò;×§°þ0÷faBÃzÛ°ÊÕ¹ß3ÀY^4¡aè¬MCî4wÇU7sSüóU(A Ohü@b=çA³èV2t.T_3©ÕóÆYø¡eí^5å@ÑÊ577g®Oc{×ø»ñUÏS\\b¤'zè£¾CÊ\\tæKiç½´Ñ_yì´+¶`bNÞtWÌAúï#^6Ìf{­ä4ÛwØíKxÑü©ëè[á h:£cÞ5ÍÁðóHÙª-Sär+â«&¯©ÑnãÅ"vý¤ÞR"F3ÌyåêUÊÕïèæíúDHß©¿8F|òÿQÜ5ÜqÍâÊâgánBW/ÊöK_Cb·&Õä³Ø³1ÌØ´ëøcç}8×,á§½MïÅ¹ß¢¶y÷ tìô:. ÓdõTÁÓ­Q®`ùñ,«ý¥2o§ÏRûÚ¥·­Í^ÿlB±gWÓRQ¾æÕBó_ê¸;íu³K º`}{/d\\t*û2<zâx{~HNÁÝðEO´ê0ë]NF$«øbNP\\bäü'ç¿´Q(õ½õ)0³FýÙÞ´s\\rãÊ)®V[3gw[*Ñ©0IµÊWõ¿¢øzUJ\\t¿#»²\\n·9ò'eoûp0»|Tý/÷Í06±oóÐ\kS3;Í¥þ£ÈXªÕQ)t!±¤g8WØÖÛx:ÏH¶gª±ìúH2\\bË\\tÀ¯ÚÍ¢p;JrÃ+ÖMËhßÏëz\\n!F\\nÀÆàpF ]~ q}ýå+<\\bL£ÌsÒ8ÍwÀ&úÅîuUE#¥2ò!Ò&,»"".jûë(K/¾\\t\\n¨í`¼ìÇø3¤O¶^kùÏUï¬jUé¯hÎSp<ÿÜ^,ø-©\\tÙ[Þ«z\\bë\\t·Äéµä¼Kx³NIh(º¹âØëÎibAÛi.ã\\t#ÐçÄe"]2Y< YyLN9Ã&#"0¥x~¹UG©L¤i6}\\rBæ®-eSÒá|_ß§ØêãKÜNÜöç/°Za´±Rin'\\fQâ\\f¥¾Ùùã]Ã_ÚU²ÎÈ¦áÔâ\\f(L^Z8ô\\rð?FYaJ!p\\fèE×èñ!Ô`uN~dÓtRpTÀ(ÿ4û5Ðë£.Lþ9ä\\r<tÂð2ÏÆöÊùV|@T-Ü¶B¹[Äzæ²Uó§¡ÈïÈúÁLë\\b!\\bl*z:²8«ö¯¥ \\f÷ayN;=0½Ta­è©²`ÛÀ¢à^Æt.U#áCÒì^ó¤Ã LÔÿQ;@ùÔÔ6bºèß¬\êËYÙë/ûk0ÄZF\\ràòÛÊ>¢E¨q;ø~úRI¯" óUóÖò°x¹þÛù\\fe¸,q*t\\tI£¿«a|ä]íÈåçÑIËÜíç`úw;®²ÍR@PÄ<&£«\\fäYÀ¿Á±&¿í\0¨T0N{nM1*xw§<«âlm!Ý]39înQ$Ù¡¶÷kºÏ;ý_Ña-ó¥p!få_\YàZ\\r,óØ2KÉàìI@kb¬²kòîØFÉZ L±FµÇ,ñÏ}teI\\f{KF:qó øÇÃÏÎ9¥&Ë\\tmüÌwCêØ¼ Íý:bjÎÿj7*È¦UkÓaóÿiw7<WßÚ¼ÈL$øÃýAa¶É,ÁHSäè>a%W)lý(YùìesØ\\fÈ\\f§,éXyðVwAUm¬3Æ1T§¨"¼TäNw7`V²`ôXîÝ6¤9·eÈå¸KóÞÜP$òtËß¡sÊzVÖÛäç(É¡5¦Ï6\\nJ£õý0é\bô~ùhT\\t£@öqkµã¶7=¥@<¹èRla.Úë`4Fg½ÞnÄ@Ä^Îx×gØ{-×sÁß«»Ã0Ð·Ãé§\\f dmbkvþÔ°j$ù|Ö-²Õ,rÛ¾­¹ÖH1$LV(6g\\tuI(uTËj·ÊÕ½kÐ(éå¹ýÑÖ¨upLdBb;È¡¦Zß2_VlLÓ|øÚÏgÄâ£¡Ñ2ÁÌÛÍýN:1e¶ tZi¶=ý?ÐKç©LÏ¤Ì%!Ï"DvÞG­BÉ¡Oª|©q\\b8ås¦$ÐLÈ¸vüÍ«=ëÅª{#p|rMNÐuZ"¿¯«Ôæ\\r_èzÂH¾ÂeP óÊ<|Öó¯Í¶pa©u+ÃËÐ½+Bf .|ôÅ«_Ñ©IËê¥ÿmÿ 'VÉÏ6"ú\\nQ'¦ì¹Ï¨pu Z²{E^D»0ÔXµôðbö:eä ³"i\\b¬~¯GLÅ¤\\f{|ÚíBÜßg8ä6«@A¨;ájá,½xoÜf··PkíØÅKòW(ÆF½þEÔô´ô®<^\\bxÇK$oèB'¢y\¸v®ÍºWwh\\nDô¤øî]AlÞølejÞÌ¶>õdôã!r°4jjÙª²uR* å¹:ÞTÅè±º¸ÙÛãëÿF²ÇOýs:<ÀïÔí^¹,|YZûMdýé²íÆ&ÙYèF£6îXm¶ýR<ÜØ#GÀñ¬¢¥µÁLÄ»¤ß¥ðW?Ø°@[9dÇáR&k2¿©ó±¹NLÃIái±Ç¿îõ :MÙ·Üÿ$YrñAÑEW³Ïèê\\tÆü<ÐXä¹«[Ijai²õÖÊ J`¦\\b÷»|ÎgÈ\\tVÁë÷©r¥¼h¸\\rBM×#îi%`(O34{N (zSeÃÕxÐÀ¼rmçLö¯~¨k57DÞ_t»ó)Áeí\\n¬ôï÷Ó§±ú"VUë<SXx·>ºh&ºÊ©¼|ð»Åÿ|á`;{Cz1ë2 ¼Ç¢öWâ1»A,Í1[¤,úÁ°|uît+®cu¿H¿>¢îG³´Ù?»hTX8\\reoÂ$Wø«æwÎBÑ±akÌÁ>ØskåäËähô³FoøY=\\bJèHl÷$bXXÄ\\bºÄÓÛï¤è!ÀW.£ÎOôr=F]\\rÄ¸Ñð77ÁT-ãYV¦&\\t¨_9X^/&Ë.®ÿ\\frÙHèád!7`uGx>¦ð'{lBÜ+Ê8²:+Ç%P]Ø¿¨Âç «½4áJÙhÄÞõô¿¦yü(ÝK¸3ð¶\\t/1À Î¹ìQ9ô¶²Dçr2ð%&E:<òêÓt»ÅiÅ`8\\n\h7í&Rovº<8n­ r¿g²ËH4gÁ\\røÂØjNõ)Wì¸ÐNöÀ"¯;ïà'Àb)S#.Þ¬GWèà* 8wgghÖý%äÒ29íYÂ7Ç×h+om*G@ùóa Kµæ3ya`l5çð©-i \\néëo$Öî÷à=FK{iZz>c¿.ÀÄ¿?ÍCÜÛ 7wÀù¯Ö»&ôùüGyÅÒ¿ZÐü%*6d±Ü!FëÅöý\s5?tjã5x.ø@yô­;fHÁÛ2¡÷Ì¹üÖ¯.,/P;xÿí¥tTÜ´{Ê^h¾ÿ¢ª7}@¬¢°êÔØDç4ôN]\ñ#Þ$Öõôþ\\rµ`é4\LfïÀõÿ4Nª¹ùÛDÄ:(ÿ1-ã#æ/ÚãeaNÄqønÅ4AL;M ú.UrÓÌ»Ø«ë¥÷¯86z²ð>¹DÍiÿº¯jËïÞ\\ba|!±rÒFFA¨>H½|Ñ½i÷ûÓïæ§ïmÉ%Áªeúüh(ÛÕú9\\bxù®N,Q¢U}- ²êP#²øøÜDÿÝàw»~¢/¼è\\t u5ÛÂ\\rÛy¢]³ \\tL«õ@Â¼-ÆAüºm¼E"z>b7ÉO;1°¿$'YÀ§/ÂX¢;^Nç0ñ?måÆW>½Yá]Ñ£apxAYpµ="ø%%}Æ'ïQÚÓ`Uä²Çj*R1>©¸Íc}ÀZh¡=I9 Øí#ô8!&%3µÜ$Ê¡°48úÿAÈn¹UÐ N1í.LãFÂl$9JµåoËÈ\\bÜ÷Âa§:¤¥ò9å<97sI}æÅ8Eúù<µMÞò¿$4t!ä3zÇìÃ­QIØâ\\b³A!Ïï±HLz·O+:áoÐðâNZo7ØÂ¨n|hä¿ØRí/bÍÃR¾;VÝíþfkõn< Ð´£èapw9²'6Vk£6éïºuÓuèéjt3ö¿îµå*àË0ðqpáÊ£Óz¢ÛÙß=;÷\\nvÃãeñ>%d]Bj3g!²·7¡H²LW1ÖÓ\d{ápäo# ¨¼^K²½$xæxî*jHöP55¨]Ê£mVs&N,mZg·^YRiW½¼[CÈ1ZkÃ$7ÑìÅyG/¡W8í0Xp4&£A8tTýAÓïfü»_¨«&Î(àN¾¥Þ¿K[üÇËR)KpÕ¾3âG#RpÅ·ØÇÑ\\f¡hú@ð\\rþW¤¨òÇâ>à¸ºrð4\;þèõåAc¸aL$Rvï´"6ÖÈðà0}hëô¸!&u¿!ø@}ãµ g[êlíðÔÚ m¦­-èõ!èÇüþvõRz®\\bÞ\\b´B3g½H\\f ¼"BLÐöãP Ç]78dêçÄ]¾^;ÉÜÒ¶æl<Éü2¢yIÿæ"æD§Pq/ÅÞ6\\nÞ|m§>ûK(Ü7ræ=7¹\ëaoñÎkæ¯tDÈ=4Tåî¹Ã½*óc¹ÙÒ\\nõ¸ÞP\\b©Æ±»BöAîÆáwå%¿±yé^³Ñ÷r}G5¢(Ã£©¥\\b¢G»[âáù°ß½WÉqþ. zr\\n¹6#æ«a4ýÿß¯Á9½vY¬ðHYÃeµ¥·OfÅ¾\\r|ÝÁ\\bÊã'¢×å[è,ròA\\tN\\rãÉ)¨¢<Öe _ôìb\m£ÇNFµ+B¡Ãï¹¯)\\fMüÔÍ'1øwi_Bh.|m\\fÏ*IpjkjTñª,ñä££\\fà &Ü@*ä$f¾4VÙ\\tÎòiÜ{Ùø0xuxJôÐ÷½8ÓfçßÀÖè+\\t» \\nó5 ¶A\\t¯# À­;2kÇLrÕ$¼Zëu\\f=ü\\fgÝ\\r{.¿]c÷¨íPÌxPiV¢ÆüþH¬ÙÄÑíJé°ÖlR9)³ÔvÒ³ÅRs [Ioå­³_ó¾ìñ(\\t4V|ªe7êUksv}&|Ê*ïÿ\\f] íÕÏ¬ØudAßãUqvA"OjÉÆobã Ü<ÜY"âBÚUòáøÆUºÝ3kÕëÕÒÉ1åRmoúã\\brrqù\\t`fº"¢áaÒTi?r;¶öÐ Ùuà~_¿"(¾k_Ï²ÏÌÄµä (eDd\\r 8¸>m<õÒ52KøÙ(pÕð Õø«dåøâCq+±{Çp\\t\\tÿ@ã%H¡¶Vï}K\\r­O7¿²°&\\f½04VYuT¦×l]´WÍ\\f\\n\\nÌ:£\\rD'SðÆ& ·wh­æi*A>DÎ· qì¾7¼æ<d3µ `7Ò\\b¹a´ú±ªóaª*m8Rí#lÍkoòaÝ²/ÿôkK©@ãm£ª!VÔê¿eIÙX\\fª1c2|Ø'¼ðÉc¾+Ë=«ÚSUü)DE#|ÚO×%.ÞµhËAÀg|øwÿ2©~èþÖ)nÂkVØ@útU{H`8¨ õÊÊQÀ·»D´¹×ÆÜ©êµ¬HfA¶Ã\T¼êÚ×à#3Z R\\t­qu¦áñ$#qbÎú}wÄ)"Ô1äëå%¸#ÿ>zPW"2\Ï4\XÜßü3§¹GcõFéj-LoKÝRÔ/K/ªçcY\ã°ø¯î^¢ßÚc§f´¿~ TwïóA]Q¨Ê¸]üÆFÁ=ÚVü~ÉË3'Ú zQÐ]ÇÞ¢Á{äW`v^YíÖ$}!q%¬\\fã¦ß:ÜÐ°3Ù\\nÀMcãmø¥ãvÒW+¿íÎ[¬@¾yåÕp3îþÑ£Y\\bVó9{¼\\f\\nKé2Þãí¸¢U7×ÚÂ¿¦êfÈ^M|è±fÏÒ­.4§TÝ½s?tXå»«Ípu;RÞ«×þ¦öºZT¹6#8¾µÔjHjæÊóÕt@ Ð_&g,\\rc;¬æMÊ*"ÂØüÁ?¹cR£ñØHßY¸ã<Hxªg¸i.¥*hX¶DHÑØG*£îÙñÜW'V\\bÿåWñ0YIMá öøÅÁÈØnçÒ#£°»Ó©¦üÓöXÿÍUoÁ%Ô.Cäoê+¾Z!6¦,}XunLëv~rúSu7ÔL;À(Ø¯H¢¼Þ3ÔÙõïØJ¾¯zvÇ*RX!EÅ}ßÎÐ,ì>§¼/øo'úC¼Wc¼?Î9ªÀ3g(3¬fRI°ÀZ*Èo\\n^%¼ñ×"YE üaÖÅ3ÔØ½ë~ÝaéAwt¸@¦~ß¨)pïO!¤Ý®TóVFp\\bêCOÏ×ÎÕþÒã\\t÷¢%mR1¢âÔRÂsÝÙiÞò\\f>*`Ûí7nÂ¶5Ö£AÔ_Ò$Çiµz¸4¶â§Yp'ÃLJ1¡<ú'µ¬O\\t?åIW¹u:ãi3 5­^>ëØ¥#³eÉ<Ã¤äGæÊKÐ¨eýFæVYµ8Qý,[ÕèIãy];ÈþáÇãCTnØ\\tê!U%\sÊÚOPÈìeiüzÉ;¸ ÜýÓ3µ|ÞT¡kNÒc\3m%>PÆéj_wþ{rÉ½·×Àf\uêõ\\béF?[­RÁm>EÖÞÏA»ô~?XuLsûî´åh^kúéCÂµÞ>1òhaè}\\tÖD·Ëà¸Î6NµUÒ¤«ëY :Å>0÷¸âvGîÆ'ÆRÀBòªI¦/6áDy¾7S%­^e¿E\\fÞîcÖ´bæGÍÙ¥ÛcIÑùNsÇô¸©X½×ñ6\\bM°G~mpnòÛÍèd§»9X¥s¿ddøÉ>èÇ%Dd¬(ØþÕ17dA>ÕÀ Lï¢Ø×Ã¡.ö£³Ù:ûPÇÑ¹1µ\¡ÞdÓ.æ&A<ß&¦)Ùl4\\nsR9x$Õ?¼ÎYÿðÇ@9LêyPGÈ¯Lý©\ü^¤Ë¨?8­çEÿÅt`·²gÑ¢åÝ­k>cºò¬°fìy¨wòÆhØ7Å{TNdâ&ç2ÔøÂ|õa§¦ësJj[ü:ØEB"u@§\\bÔë*%V\\n°¦j¨êÊØ«Ü\\rPts¼\\fEO<b v UaMÀÖ¦¸DçÔ²ºôê}ØH§ú<aÁ!ï½(púÔdèIð§GmóÍªqã¥5ó´m"Ôî¬ág|ãÆFÓS¼VÎ³zßa^Bç2«ÈaBx¢:ÏÍ#mLøg;~x}WSú²7!f¨µ°ôÕæàûÃë¢É;n)3®¹ÁeêÕWèÌ^Õ0àRÏg§\Rô éBæAkU¬(Ò¶ûþ4j/ësWÜ÷Æ]ÆÁaòn÷äèJ7£LÞ·5Ò-\\fåY=¬ÂC`Ì~/]ö1U\\f>%½ÐÎ7b¢m"ÝÖsÌËÛÀ?HòçÀyÉ~`»>éìBY½·ÃuÙöùc>P`¦Ú×ÔEÆ,"J-õ\\nÃÙw\\r!±»Ëï~FÔ%ù3Å5yØå°¬Mf ï¸xN±ºr\\bµÙU§`ué½)PÍâÿ©6L\\bk\\n¶¨eÔgÒç±xC^qÏÄëBèä·A¢ôH-²Q¦\\b7$¨lðÄ´\\tVqemÌ¦Æ^óG¾3ÿ«W{ÈÅYÀmã#ÄMýèí_éP²düØ]Söl¹ »\\n\¡°Lé®AïQ>¥sºÍ¡Êu¨Â16|ý¦[ézNG´\\t±YÞUÔò½üû«§Æ°©Zô9ütjàu#µ_<«ËH7?Óöïp®¶>ªÃ59;§¸bp»¤ÙÃªÂ,Ç ,>8ÿbùÛ,{SÛ«ã/Ðj±!lf¥k¡¸®®ãb\\b±`íö¤A$bª¶XõÓõf£\\tÉnì!ûÛ&¨K"7úVumÝzäîí²î'oø.?ñF5Ú4 ÏU¤'ÎÂEÀ,.CÛhmpÜ)=\\tÍ]èÒ½ñòkA]`¡öjÃ"t%J4´£-85dC+ËÊTnm¿\\r¦Hµ¹=c4uJ¦Ùx°÷¬ÚRv¢oæÆy\\bµ@ä½¨ÆMqQ«\\t\\t£^®¿"<¸Éâ¯]<We©¾ä0 æt:Dsë\HlÚO.!íÞãÖ~¡ðöo¢°Ò#x*ÖL,sW3ÝÁN .iXø  ý¼e¾=E\\b¦ÉÄgÑaÒx3/è½TC]òN+*Â9¡Æd`Jö pbE6\\fü)% ×p*,ôîø[@¨ä7WÎ+9&  ~Hè\\f¢²÷ð}q¾}²ÿ8?§ëÁ\\tõJíÏnô\\tVª5w¿0*ÎàÖÕU¿Â=f[QÌ½7#ð¸µË>èPJ@¨ðs%\\f\\tø×KÂ\\bï0DëzÛI+{yÅY¨Ù´ ¨A=ómó?P¥bdÆ~µµUº7;|åÚÌ;+L¦=CÕ£(p&ÓwùÖ<S\\fÓîÐßPòíh\\bå\\rÂ5>Ô¡/=ËÉû¶\"L¾sDômÄÇ$'ï®+%¹ººÿú¡µ\\bbdÙýq·ðÚt¶n­¿z¡b@¤¼V[+)Úö©¦håils´gÓê©ê9á¥ô3ÚÏw\\nÄövc[ÔRøbª³éX[zÈëÝÏÅ½ä×\\fdd\\n+¯ÉÍâË ½cbõÃ©¶ G'PúýÞÈj­ÛïÓÓ§·r=±¡0âÐ \\fáµG/=åí¿}OÖµà@bPs¹)ÏKÐÐÁá\\n\\bÄV¾°E¨ÉöA÷7%ç¨7ÏJ$ZÑ,Dö8°w6¼soµ`bïÕËäl£-}MÀöFËà%#²Ù"ßIt`Ïõ/ª¢æZäh]HÊ±W0ÁÆ£eJUÁ]´ÜOèÁéèÆl°Ð©Öãb\\b$JÔÏ#\\f©hÌC¾]ðb_Í!ýBè\\rÇñ¬j2ÙäÞCK¯¯&<,À­Ù[Ø³Q}Ç:¦î|ÕÖ\\nX¯J±F\$¹fTl7S')´ÇÒB[=¯ÖYÕmP%MÖZpª3%J6§±;M!Í\\b+yL¾C*bEÖOïUryk\\nÈMÏ\\n·f¶±6 ¾\\fYÎOö&(þI«ícóððdu<ÓÿtcÑlø¾3ý}³a¡k`§RÙ¾u¯¤ã\\tü4ùÜµ\\tP´#ÆH-úÓu\\r ~>Adsg&2Sª³Vïàéáo>SÐ¼Mäöú;¦&ÏK'}%ÝºF>²^\\bñ2°õ$¤~«¬þl]Ü¿ì×\\b¦GbÅB²0þ¶s­*ÈöÆè5èýÕëñQ«GK¢õß\«Îy¼Ì¨­+çw.Ó×%üÐÌÔ¹ÍÞÆ° ³rêÜ¢úHEü¨¬gU'©'¤ÕÛ®Mc£ëþJè9,pÆâÄÈãéyW÷\\rOÉ©mÛê&³ý3ikò+vZ\\nÙ4³÷§Z»Ì*U¦w=W¸ªÛ\\t'!\\tæË§.§¸´NbÜg®×\\rTnd#9ÅC;q¨ÏÌÈG^©È¼ÇÓBùBþcÛ6ÖØ8¾=3-ì@Óar©Ü4ç/Í\\r§\\b¹B)`3\\rYN'ïéeE7IiÄ³ºúo·¡ a=¥ómÝÙ\\tT.èè=Eòu!n3í)Ad¢ïLf¼/pQØ÷|éSB1¨¿ó& 6\\fYÿÑFAðz«xüc/¹4Ñ§ûý¥<Ô¼Ö@yà¤ oà®bÑ^ÁûéÅÄ¼?§¾c7cU$øï,t:Ïë/$8×ÈªÄØ·V»Çt¾ûPS..esVú7«ÉÊvG2UèA´aA½W»ê®#±¸éøØH\¶ü@K\3À¶ORðB¯iüÿÈthÚÉÓ»! b5!ðhùBßñFò¤ü~$81q1öD\\n(ü5rÎÛÉÓ\\r<[¬[wØ"ÁÚÃTÓh"ìçcä_^[°Ú¼YÆÑL¥Q«/"º÷rä ÚKäc:PjÛC%Lð+VªU4ÂãÀ]{:YÃÎKä%É¾2fäA®Ùàþ}à{oÎ_ÊWêÊ~8}=ó~oGZÐ·Oûäm£þ!Ø&¬_x÷ÁÓ\ð¥Ô½Ú´9w¨ÌÇ0/¡Ç1ø¨^5B~XX¾\\f]×ÛÝïs¼a zæ«i¸i¦Ìg%4W­¤çt´0¢`ñvÐ\\b*C0q\\nïät[ÌR\\tby¾á:ÏrUÁjJÃ«0¬Â©Ïõ³à4vDB bú¥ÃâæÐy¯ Ï»èêXë]ûÞ=ÃÜèq}iÈ&áx1Ý51$´Óî:iÛÌ_õöè+¤Ë0öeà¿ùH L¾¥ ­?Ä5Ã!|ñ/¥YIµÓ%NM§¸ÜU5"M«ýºâ!»ðoQ·Ú6_ùú­­èJÅuê$ÒïÜ\\nßËFc,\\f` \\f\\t×LÜÙy)ßÍ òÝÙur»ÈâÄýa¥Ð¶òùì\\nvºèV?d*kÛîzÂS2JúfzWQ¼6G8¤~UÇ»µâºO[}º(Y%èzS8\\tw&\©å¨Ú#ÛéÓC)RûÂÿÉß=H·ÕEÔåÍíûÅÚóÜön¬Ã?ÝQsoOð~½U:\\t¤Dð¼8K>GàN¥@ÓJDO©Q÷>·½N´ü|ÿf½eÃøózÆÌäÞu6¥J74ÁÝV%Æ¢/Ô³$GZrb4âAôäV;Õ¼®LÔXn &ù\9wq8òþ÷'£éIÙ\\f4¡¥w96©üüãöpL;U_NÀèFH¼)¿¬­ñ4kµ}¹+çæÂþRéÔ¶Kß9|[ÕYéäÔ<wÅJYm8tÝ9½ïãÁ[ ®Å\\r<«4ÌÆû#¾ÑåI;éª|XâSv1ØçékX(n×Fà&Ò1¶ÓÔ³­NV¹©eËS÷¥iè(0\\bd¸ìü2¬Ê¯r\\fÅÓ\ò®;Ä¦\\tK^ì½ °kGY¨Ô©Üôñ¨E%mÝ%|S;Y¹>½,§v\\n©c+7KÏÊÇ{Z ®sá²4Î³Q¿\\b§pµççýEÖ·÷×Jj"«D\Ç;ý"Y¬Ï8Â«\\bDÕû¾ð8øbèhI(býÉîÒHôÚKï¼4ÛB,¨°"ð2Ý\\b¥â±_éjðÉôj³«ì«¯ÚI´§n¦­£|gØx£¨¢´Y­7®³"Ã+~Ú¨3¯éèaTãmx/P´E¹Óí¾jás;õ@¾08vùeÊÁYÑùg® >:ÂÖ½0øRå\§ª\\r­¸÷SRÊõÿvO³Çp²g¥¶¼¬Õ60ZG¯dzû¢Êöä<àá\\r [\\tWz¯:Ã·)ï£01é¾»±Û}xPÈScýXfÑÄH¬¦r%ÕÔ$:ms|F´;}=æ½JúCE.xÌ\ÇÒÔör7µ¢Ìz»vj]_ú\wDªsscòúuÉºNW\\tHPÅG¢§¾ô<X5¿j¶ù$Ú±døÚ:SíR²+ZÏ j«4Ìe^¨x"WÖD»Í¶\\fí±t,@)¶úsh³àÎô|_òB4º\\r¸½jä Õ:ëÅKG8{fc'&,J/Ö»CwÈÇNg\\tiu³U-íà¸m)\\fV,¾£+²7ÇÑyÝ­êó]WL\\td£ÌÝÆÁÝ¼ÍtÔwÓÍ®RüÐ:ÅÁ\\tÌYM}¥îq¤¦\Wç´Ùt»ïÝ!ñÎI»®ÙQÆ¤57oË¾Læè Ê;Ï<ªfS'6§óA¯Ö{¿·øMÝÂÕû+¾Ü³7:m6èÈk¹Gt?ÛÐ£ñY\\rO®ô¤ÌJ="F(Y±:wìño~§£5x?wðsFKR¦È¯Lé3àåD³WáÁD9Ç¥½NOå`v¯õK[p;³áD1¥s$ÜdõÛù'¡!uÅ Á1¹ÀvhêG*bõËÿÃ¼W¢\\bõl3Â5%ËÅ´Ã²l'íº&ÿäð\\bJ)á=/IÏÐªKê¹c ÿ©MªHôG%DÆEO~^Ty;U®i/±vÓÎÕÞ|E\\t\\n©K¹¢h*LSâ¥lSÎsk\\nÁ?^AÇ2û¶õÁZRìß \\r¡Õ³¯ÉxÜJNÃÿìðË#ü!Ãi\\b!¯8Lèã¬Éù³+P²9P½®Ô^ª°­ÎkÙFªsë;ñçéÕ.l·va¡8É\\nC1(Õ+'H¯£µ½{<¤8\\b5mÍûNàE%5gå@ýÝ³¼Â$Sëè\\bÝæqö|÷¼T&MÝXò [ÄÏ¢jÚY;v-êV«àVÙ9EÞ,Q·cãÕÌÒüEÍÿZªjÔ}UCÒBuÿUOCÈÃÌRråw~ÇµEà bÌ[ö/°b,/\\n{å5)|Ví+õ\\nä|§Kº­)¨/\í7Ti&\\t)íqÏ·Â`$ÈË»ÝrrÊë\T¿qæ°rÂd²Y X-Í±x/ULé¥MümÂí8ÐÑl50*"¾¹ÀN±\\b6êÔäÜ ³É¿É\\bÎ»3¶rÝ×TsWdw?þmþ]°¡¢ÿÚ¾¾±ì¯òÐ>¯£ÔR ® Ì2^ Ì{úFÏJ0\\bÒëôcËë[Û³!t\\nÖBxp|ÑéF\â1ðÉ²Eªø<Ã®bgïsÂÄ$]ÿ¼+ô=;üc*:õ#U{MOJd µË\\n´åf Lõè/àLÖ\\r¬l]ZÝøX<Q°¾92*Ql©8ÃCMâ´Þ¬ApJõ WÍK\\bë©íT\\b¤vèQ<böÒïXò¡áßÛÎxèÇSÑ|ó­nE¢ÊG·GÏ%³J«*Í×þÖÂp:æñ¾q[MòM£ÔÇ'åãAKsõÈ6Î(ö:ÿ¾àZ±²E >7|0Å&<oÚ°<¹íñ¨ïL É|ú'yrÈÒbÈþ:Qw<èºm*îs¿§]Gw3¹V`[Hk¢Ï_yN1@sRo¦Îo°¸«A°ØèÏfÂþ5ïHy³'RÆp5Óuêáû±Zx='qac!~"âåÙA2Þç7)n\\r«ÒmüóKb§¦Äö@Uvoöó+\\r®YkMq£OÝFbTé-°î×7ÿ2Ì³¸ÑèÊFËØ\\rõÒýl)÷w«QÆÁÖ¶EïÎ¹&@Eª¸ â%Þûk`Ð/b`ò]âùóÃÿóu2&¦wÛ5(Ý½Õú3\\bB¯iÄYsiõÉ'Ål>ÑIXðÂ3fÕÏr#pr*zXéXj¤.7-rË.Q@ºÅÎ^jY ³ÈÖÐ]3¾K©¦Ä_esSíütUÏ0nü¬\\f<K\\re?÷w¡R±´g¦)XJïyÊéù©(Ð%)+~Él=ÛYxîUR¡ÝrËãôhæ6©,ö4¸±ìt1$ûÐ£Æ¢äÒú1Óñ!âµVÿ"\\ré0ý,j ùÞ×¾ñÅì-X`Ë×Q7ère*¤Y¸H±©S=~åw¾Ùº{9Åszp·Xðl3k]õhíuB´Ûf*Ý:ëLòÆsÕô\\ní L7¢õÄ2û4ûb¸ÎeàÛa<Ã¿¯·Ûÿ;#+ÛÝØ°=dÅß5b<5æÇ\\brAôÞ2c­7Ø{Óòú:E_\\nE9x^NÆDc±/iÌe¿Á!ÞA*réÁ³ÄÅÂúpÑâööDgßÚ½Ebìü8e3s,@«^>¦©úvs»ÕËÙ[ÂpÝ¯¼¾â@$"#7³ÆÝ"É\\n\\tròü¯yqhã'º±»8ò]x7bÄQÆ^ûÅÂµ[Ï&%%WíåTãú\viýT7©±×¤,¶r·ÌÖOæ¨°'F$ÆÑ(ZÁJô nðsvz\\nÕÂW| V¾ÄÖR¼E66ªª@nSöÝyã¢¢ü¸0û!¢Ï»g×ÉÁgMåÑÎj´ÓaÿÞ 'Ì+i$©ë6#-Håìý%åà¹Zë4®£ìúµÁjÓ°²ðÇÍné§Ó¦ó4x0Z'/á§PO¬êg°\\bo_Aº!°'Á\ÿB¨Ò¨:ð.pÒ\\rØÄ¾áÕëÑ­-ÊÕ£P;Oq\\t\\r¿}_Rú9ÉW÷Lq|l×oQ©pÆ@`=F<ANQÔñÃ¤·Të/Eáíë/w/¶Õ(îM>Z«ÐMÔ7oB1ûv?uÐ8/:¾!^ls¿´¯?1>ñaÄþÆø[§"Oô*:Í¥Ø¡XC»]#0,ÏIãâÃñtØÃokäÎGôt÷\\fVNóç4ÞuJÍ³G^K3ê·ÁÝ+Mléý ¾ncÀ¨ERËÐ"x*M¼/·M9%Ý?å]dÁ1¿Ã_ÕO?Äßåþ­wÃõ°\\fà½Ç¹â¿ØEß²GøÈ¢ÂØø~».JMa¯a 9cRÂ:ÑÏ|p§òÍâ,7Ø=4ûÞº^K~]+ù áî­¤Ú«\\r£ªÝ=HïÞ;PÅÎ¾¸Âû³ùÀ\\r4Å/_ì^2<K. +ÓR'>²w¨}®Áó-&)ÎÍù"ßÀþ\Jiy\\fYI1¨µ°å®áÉE}ðWÉæ¦£±6\\r,æ¬ HóÂ\\fç.\Û ¼12£±Ôæ#·ô\\tm\\rÉBi9TÓM^hÐ*¨O+ÃäBå«4KÉ H[M)À©Ñ:\-fmÿY§µ ÛNé¬Oþ¬]è.'2gâCCÂVÆÙØ=ï2JÒi}ù²§¨îu+/¸lï1Þ{ZcZ)ëðF½ß9yì\ß+©PSx¡\\bÛ`Há¶~2àXS&x§S\\føF¾øs®3u+B5¡Lø¦¬®dyóÖ×¦Lîw]x´HÒ»a{ 2)X,(ú8s¥2ª¥J=«MRv¿W¨ÞÉõî*Ûðc-©çdN\\næ¤«[G[kkâ ²É,AXªVÏä¡¨\\n:CfÁ3¿Þóm;/áCÚêæÙûàXè@HÜ\\nÉëßXü\\n¿iA{*AK×tì´£xc mZÚþÎ ãºV²\\nç,uw.9w¡×Ì«ºwGÑÞÇô¦Ë¤®À/'½Ï¤cÇm" *ho ¨a½R}ïÚÚ\\fÿú©¾¹b9CP@§ú=ñ¢¬ð!<öùdO,CûvÿË/|n´ ¹¾ÚÉ5={aAÛ¡Ò"/øy*!¦Ê¯Z1óË;$Wt´/ÆMBTK*ò\\rïlM5ôÿ\\tàæEÓFº@8kÇK±ßîÄµ¿·ÄM6RGÏL]ORwæj[@õúµ¶,¾¸EáS±Ìy¼=K¿ÞÒLêHä®!.ÆºÂ×V_Amjéä§,j{~W'eôÔFÉäë9öàlúÖÐ/i*\\nïû¿\\b$ò©<ûX¾dfUu±I­ÉÍ?9B\ç°Øë{Só»¾bãX34Áïâ³°¿®û±õIÐfd¿H¤½#Çþ_æ_´e+µ¦&¹rÂÓ7lÄÈ&Ê^\\n[¾B~É}ÏsÛ%²%%\\b*RÚ¯ÁW«þ e."^áZ·5|Á¡Dj|Äï5çz%t×'Ò¨X¯ù\\n\\n%ÐtBÈ 0iÇqÆ×ÇS§ÎÑ1é\\f+÷>JQx }^.â{Ù9h\¥n\\b0u$©}SíÌ!§ÓÑév0q³\\nªÍFrZhzãxòÑ4ú\\nò5ìM3ÈÄ<Èû@}ÓW³Íð»¹ÈÎ]õ'A§,RÑÉ45¯ëzv7+ä¹O§»pvY>øæÛXÈòIlxï±?úÛJÒÆq\ ØÞVÂÉÅx]\\fIäMð;sLC\\nã#ÇëÔþ1·scB­[á?Ð·Í@°k ¾yÄÃ³¨üÝj{vôïè6xs¿.«$]A7áf¿^rÖðøÂë¤IóüNøc>\\nÊåáÌ0N4Ö+_tÌ&ÌahÇÖ WÀ0»=äqL¨â¼¬dª<VØRõªkÄêË:Ü¿ö&ESÛn§«M;{jÚn¡7-x@eÔq0öÅeJ) î\\b¤é0ülMsÚ-Ì0à®+¨/á¦µÇö9QïUØiÝÆç»6Fõå\\rvã/ªÛ"rl\\nv0¸ã¸£ÖöquÈb­ pÒeÝ<Ä½¢ûxpÖñÝ÷Ð\\bÆ\\r'p¤¹ªü¿bàòÀ;Zf5sèÃyYa$»g;%x$ÕÝôóßsVñòõáìÝ&mµõÓj[¹M£ÅÏÜÐ46aÐvaç¬Úßòld¦¯a± ÞÌÀó@x Ô­©nð&ÅômAC´XVËíñ«)\\b|i²nÎ\\b·2NÍÃêúbIÿÑý¿é±täi9Tö.ä\÷»ßÐ'´IÕ¡·:®dyÎÒ¤²r_¬NEHÕg¤!$K\¿NÔÍ`ým¾!eÍÒô û÷º/äTØv´ÈrD~âØU\\tçzp°j|-ÈhVÞ6¿úxN _\ËgÉ¾G+ã¼¶ÊA´©s¾7°\u ¸ìhEPk\\rf0û|2Z\\t&´5#â¸´ÀÜÜjU@>Ö!7}ÞÛÙ~Äj\\b2Y)0¥é:ôÕ×ÌÂº4jÉfh±ð¥ÊoÀ»ëCÔk ­\\nÇuyÑs<ªh68!Ê_dw'UÎB6%¶tÞ+\\n¾{$n\\rý*õòMäöÃ~CûÁò\\f·°ÞåÚô)¶Éþi#Ò¸ÊøXz¤mHt&¯57ÈÌDãë"×pù^[¤*MWö¶èj&{Ï.£Ú¦YØP¶°¡~3]¾*ÉbÀ0À­â¨Ns¹Ý1ñ Û\\t?]IûËÃÜvëp<rÐöïºáÓk7L=«µÖ]ß\\rËç\\fO`}²rÔÐ±\\r¨wGù&à6Î×l£Eó¢hÑýñU" Ã(°l@0âIéèKfªC\\tý6:Câø>UUþåò­@Ø\¸2,¥!Rþ{!êø\Ø¤iaônvQ»ø4ó«þñf174ÆY¬ª¼;iÛÏ Äý±Óîª=3FãuÙO¬èõä ¯nú,Ëý©çMCK~Xi¤C×rWE}_ lôYñ¥\}Tå I°¢%Q!$a#mÀpPV¦è\\tø3h¿òGÍZB&\\fÐ¿|nµ=N5Vÿß/íhÍAWx¾KÕ2)¼a\\f,MÅ<_ôö¬vÓárQ) ¨_As,\\tZÞØÓ§d;?0/ (ë24+l_0ø1ª:®?íÑ°Ó:$-Q_-ô¼_HÈPÎÛl²áQin`Cõíg£\\n&ëñ/éq¶ÈnXÂXÓ|TºÉÚ!I´Aà`Enr]¤øX @U*¿à0µ¯¢°_¬-&cg¬À©\\fÄä8Aj¼¿bRýß<s&æÕªÖ{\\f/mrª¡Ì²«Z¹<À{ï0ìO£©< yìË³.î°v^¡hIÃo\\fÆ¡,þþ×¦'w{_r¬Õ1«id Ñ¢ºtø<¡¶õoÖUÌ :ÃüIÈ6´¦«Ò%OP«wÑÙ10Ê£×Èa²'÷«Þ8¤_ìýâ!ÕÉ­f°@,¦XT¯Vt2W2-]@M:K ¼¢\\b:áéKceÌâ<ýStÎýb6-YvwS8×]"cø$$"¸]ÿ`òO£lz}2XH¤ÕWfæIlÚV%Ðß:jø¹bF+Eb|³3Ì¾ÒM\\fYûu@|"G¢HõOûÝkÓÅ©õÛ®l1Äë[RºÝ.vG¦a¬Øh¹¨Bú¯ ðÊR@Ð¡GºÙNÚ4PIè9xÙgòÅaÙ.È~e]ÎQ(D ÷¯téÊîuÚl9ü\\nl#D¿\\tÌ16Ð¢äÎ(¨Ä¢~ÀÜ\\f¼þQ&¼µ4C¾#¡¹'îüÚ\\tÓgÓsê¤z\J{)z¹bZÎkü¶ñ!D4\\nYf\ßl&fM«*\\bØÐÝWÎ¡(â<ÕgÞÊ^²E!¦&Q£8¦'fÐ¸r¦ëÙãí_g\\f»Úëû.L_/Ë!^©Ùã¬%~-é'\¸ß¾\Û|HwBDß9m¨e~¶4mê?dó´OU´5/¯.L5å\\rÖóÖi¹}Ñ\\rðG³Iµ¯Ht²xTyÞª{]nË/ù½R¦WÆ`ÌI±Ce¼GZaß{9¿KÏ~­RQnÒ+Í®D\\nßï¦WyLø]ÆcÐçÁâÁmÄf©ÌÛ´Ü7nï¯-3«Úø»_Kfs¼·\\fÏ`Ò\\tê(NiLú7?ß>TZGØiéobOAáàÈÎ¹Gr§MÂ6FóúÛµæInj¤Û`ËuXØgª]\M,?,W!Àp¤$NyEüâì5Bõûì7\?ð¿ë à¥;wÕëFßÇ{»o¶P7_Pzø`×û³£¡Y¦Í*1¨ïßx§ÈÍ¿vÿ¶âî?Ò#FÕôa¨ËzÉ)?´<;îgÓYý*ge¼¤^n&xJÀÒf:GõÐ£pG&Ir[aV¼"=&Mbòî;ÎnD0X£h_æ¶Kþº0gÝ>ç¦h>;åyaS#à¡úèÁeéã  w#apA=AQ5V/·uÞîqu-âkñI#lO¹Nhaª3iè8´Pw¿®º33`{Öp\\f(åuë'/I`tù£ir(ý6eC9¯cKJµGñðÊÁÀ¤HU9ÎfÇçj~Á ÝöªÀÍa=ùÖ{ý/ÐP=ð QÄn\âFMã e¼¢Èý:Hh¹©qø­ù-ÍË8[íígºQS}7¾¼ìPóî'Ck"3Ü)¾aVF6aõÅý=/LÃ[¬éÎÖiÛÖ½¥W8!K6ËjcÝ3?¯ç&oüµ}bÍrÀÎ»2ggTËõê0]Âqó@%Iû¸'Kò-ûÈ4øXüÉx;Z¹Î´Oç[õ«Û}]Ö­òúî?ù BQÛMð­ësºHøé¦î×pt/I3Î¢ÄÀÏ®¹ûÙþÏ;Z·\üáíËïNr÷È¢Jã|Îîä~ëåóUfêy¥×n4Æ HN\\nì »ÌgôEyÙtýÒ:~ðjõÜå,mQ¤( ¶æÌ(4À6;©@ Gu/úÒ~\\r}×¸Uç%é+µ~Að%9\\ta~ßG\{Uëx±¨ ÈÃùúÇ¹t×©ØzI÷yÃ±JØÝ%g;?æõã\\ráÿ ±ükOÑsfù8páEÙs+õWÔm55q>e=~ãU?h\\b2m}Ú\\tk¨\4úÞÓ¢°¾¸ëY&3ø3µ!ö'hg·eDªàuf\f¿þ\0üÚ¨£ÂW\\rm2õ,ÓÒ`9àÍ3ÀÊX~¥:QGTì²1òÿµ¢i"g~AfÁRÉÜáòùµ´4p÷Ö_÷;¡ÆTîÂÈm¦ÌwsÑsðá\\fSöÕS<ûÄêÍ¯&CÚ×~«½l3T«U¤©PLÓñ`¥¢Z¼Hû´|wº¯°8¦Ôq[ÍÍµckýÅÈ ý¥7:Ù\\fí|]-EÅüuÏ)á3i(mziåh¿ë2£(6+F(R qÜ UI²È¶#R fë«^zàBýï¢c¶ÒË;H\#W)í5rDý\Û\\\tbï!oB&<aî-C\\n¦¼®rqÏ%Ûð'·__¶çøËaôÝy~ôB3²0gV¹7èÅN-·HxÖ<Gb×ò<ðÒ<SÐ8m·¡¨Q,ê´ý¨Atðþ<^\\n<ëà.(R«¬L0>Çt\\n·ô.Í¯ñÁcÙ@A¦¸<Zðä´)ØÏf\Û,¤ÃÔ­'æ'î£IíaøëÐÛÂÝuÐôj^½¡©qÔ@¶F;(±D^ì-UÂ+þ\\bDíÕ?uÎÆÜtôü« L§Ûg ©ã¦îÑ­WØòö\\nÊ8ÁÛç*RxÎ1ÞQA)\\b¬wVÕã@¶×èZ¬~²TQ\\r/Î¥C[á\\rMzúxGfA¨ÑlJê§ß^G¥,ú+Ö$Ü½¤ âOO0DYýÅ¥4ð¢\w¶%.æYMûåä¢WQâw«\\r­[á/Lñ@t0 ÇÀíÍ#í$¥é"Vá2n,­1á\ïÃYÇT!e%tè%¹Ô}Ëá7ÓÚà9ô´¨>K-ãRpkÆeS!á5Ho¦÷Y§WWR²]î½~ø'eùvqu2~aõ[M«Ìÿ¦À¼cºøâñÎ`·OØ+YmÃÂ'Ùúä\\n¬)O£eÕé5hY+l:¤<ªnÝøßM®OÌ45Ôu-ãùmÖ=´ÆF,Ò©êsóD3Xëæ¶ØKsO'ëI¯~'9¬}"ªÙÛØÊcl\\rìÍI¡ÂôßJ/ìVÇÔ=Ú.¶iL¡½ÂMöbw«Z:µesv±%EðÛ)ÛøSP@ÑÑ\\r¥¼6Ïëí}\\b ®ªa½Q´D ¡¾ª§ÄÜ´îy³ì ÞUÏ­³ÿYô5Îòd)mëè'Ã6k»^£Cû{¸¸QøJÕÁd6e|Vjc\\tO\\núZ\\t¨ÈßôÊðÛ^WLð;ÅrI2Ù6vGÚPåõ\\f4+§ö/ø/¿u¦þ,Ãªl²\\f^©ñ4ÁI¯8Kô·9¡'FIìÏ¯;w_-_zA{V ä1/y¯§¶×¢$Ð ªÚ=úð8QhúyEOpA9ã:Ë<ÓhS\\t¸ó5÷~Á¹çìÛDÞi×O)63ÐcKý¼\\rÞÚ]ÉÅxµÔá³,¼_ VoålÐºÇ@¡vÿ¿K>8ª£#êÞDóõn)¥ \\nu¾Ä1bãöÀGG¬XîuóËc!\\nNnÒ5\\r+Ø![L³Î5É3.¥Yçïø}Ùa¬Ñþ9â#iH^½°1,À]1ÿ·2 ?:]ÅòÆ5êÛ±tµ¢W-UvXÛ_Å¨ æ÷Ào´æU]³\Çé£ù¯Áqi×EÕò]ò¥îêýñK²Ôóí%ÐÜk~0üä*´NÿkDÙx¡3*F"ÍnÚ±ó«R²\\rËÿ!ÿØBBR¸wô È{iês¡Ñ¸ý/Ìê¤ËUEJÇíp®Mð¹6UdO©A\\rïg.\\f=¶\\f¤©UÛI×>'kÂa>\\nÅ1ÎÔÞ?H¯fûµ¢©9*kt;¤éfÍ? ¹âZ=ýöAaN©ìz>;ocù ¥5Ë G5Ie¦ó¹®ÙÀVrÿ\Ë3>)7\\bd\\f¬Ï ¶¢*ÐÚ¥lk'ÉîSÚð³Hx<RlHþÔ= G?ÐÇ5x\6¿)y b´Uñ6îxîô/5:~WÆH£òØ³]1oÕß{ÀuÄ[1Ù×S^Ö RÕ¹¬·°¹ÈsTÊ¥mÅk*kü7`eëÆçÜ7tÐ$.Çyÿ#e&wìJÑÕ5PsYÒÝÔ»¯¿Àÿä¶9êû=.»L£s£j!3>;?dOc·°,ýëÛ<Mì¢ÜÒJex\\r§åósn)×Ý8ÂpÚ`sòÁ>ö=Ò TÃbþ@ ÚÍ%G^~º:åHÙ&È©ëÎ»ç7Ì±{¼.ü2Ó´S¶uÊýöC¥Ü¹_úQ#¥Q FuÝüeÇõ*<%û^XC\{?ºá¸q lHà¤ 7!?/ÂÚIÚíSÎK´1àEês¥O&¹'6ÞqCÉ¿ÞàEV\\tmØy²ÙþIyåýcNNÓm@n\\rü*ÈrK!QÕf»×Ø0úÎ_.t?©`oÒ¾É\\bÙ¶ôKB´ä§1úîmÁ'Smº´\\fÇ%ZO0°¤\\f1.ßRz \\rTKI5ÚVÜ Ó<±CtÂÜfûº®Ë©2ûÅÊþfDu¨ÎT(¾¤õ >nG\\fÔÌûÿìâ}C2ÑEü'X´¼y6Ímjñ0-ÄLiUJ*i»Ëàóókùb_Ã °[-¸»Ù\\fgg,vÂrTÙä®3+z)©apoÂ1µ#ëÕTõ|"1ÌX÷-QÕ0WôÂ¾>ï¯4ÊóÇ6\\r4@oÁºëºç¼c´YGÔ/®{î£(¥¹âó2Óéõw ÌÅ#VÜEi:Yp0é Ò8â]yý2ù \ppÛ6Sv+åãN çñeÔûÏ×Æ¿Â®í6í¤³ÝPÃa¡a!ßÙ4=)×ÔoBóÕõc¯^_Ð ÕsäÒhmá%ÚB¯:X¹<ú°O¼1%vª<\\n;wmÑêfôl0üX)ù±ÅÙâçÌöUC¢ÌßÒCð*¬ÃØ³v.»?«ÞJUm'é²y°Ao¦þ$3&´ÉEmÝôÖâ\\f45Û^²½£w¾÷cµßëë\JI"æ«ó*æB¢µvcú["~Ý¤Ùã²o,ól¨\\f8B÷þ¢\\bj*äp³r­,n]ÄAø1Î_ã:pBcë]N©x®Ô¢*\\r?^¤½É;6ÊåÐ4Õ[Ñ\\t\\f©ÉP@·ÊÖ#ZIT¼ÅÍ><a1ô]Î×A­ ã1  2z+l·`'¡ôÜÍÏAYøf,^ã¦¼·a®%µwl«17sg6ØP ýÐ¿:÷ôÂ×.¯çñr(%#ÑD:ý®A¬¡ªa{ºiäîßS\\fÛ¼£ÜíH·¯Àí\\bmð UW\\r\\n\\nHð¥÷IÒ? þæm`ëéÑº´Ê&yé%fËC:á_Ê,ig..[¹4Ysê.RÖ Ú¬½Ö*ø£ÃRßZìÀ#Þ3m£}^bÚMÖ\k´r6=D ùÉXnVj_\\tb_æÚ1ÝGÌµ$3ª// \\n»?o{ïõiÙ§$º}XåaÀ6Õ¿>%º®#'{Q\\f!µ¥ïj¿ÈøâÛBoýMÒÓ¤Mô\\r×üE¡ âþÀ\\f NÝW«GÒÀNÚÈáshÄ1Î9\Ð¦w·ËëCjðYÌ!}º~ç)-ßÝ\\bÉYy¬\\f° Û®Ë' yß!_K\\fN®S¼/©Á\\nÔN³×PýezjÚã¿!²6R\\bÌãfÑ\\nKÞèQSÅaÄÂ¼ÍðÕg0ly |ÛulË\\b[Pâ±\\f£ÚÞTæ£ë¤¢1¡ªDºÉ8¼eX£Ä\Lö¬·9i«°Ö7ÜÏ[Û\\tNú|dt'à0|-U.J±Ü9\\r úB\\nåæj¯J(ÈcË8é*S\\bÁk§}«ìé©k;+ùÇ¨%%ì5'çé\\bm»ljÎ|<PúXz0SÖz ]¦N62ä{íU·²é éÙ§èÌº>mF|¬Êty0ÎÕãíMÕ'Þ¸ëùë¶ÔMp\\tx)þ¯(îªB´*ÄK]`êjòAØºóNu±¼ÀîÄq0+z½6i7GîkÅÓ3]Ê©ËòÞ½I­ødáÀ¨¡;Z6â\\tÁ&ªqP2¶2èíûõu#Dí(Þ|È\\f¢fEåjC4ÐÍ"èæí®©èo±z¹Ë÷+ùM)o4îÇÉm'L@ÇÂ4vÍ` zm¤²r'Úÿ|wÃ¾ãl\\nQ$&ÿ\\nc#é¢ÜìZþINtÒB08k½Æ¬-\\t­±Õ<2%+ET;£â.sâüvÔ4mT ©¶ê×f%YG7q0)¢u¿Ky¾`) ûv|äÃpEÝÌS©ïõ;óWù@9OéÙM\\t<d"çSëÈ'mmg\\nÚ,\\n¼Ãz¸Ó®èç1hØy»é±Ò6ÑïR¨-ð¦X-µ7*OMY S»)^¡ÿåõ±±NöJçA¨óâEôÑE]¥ óÙ½i×7¶ÐÎ20&jkànßMJpyØ½n®XS4]lç»V¾c0þ~Ü©û~dñG<(o_hlÆ(VüÛ¨ «Eì©îAz#ù{¡7%8ã=»Ýî\\t>.¾¸BÆsÜÐÿz<_è°«n¦¬õO¡ìaÁo¨Q í1M@)E]¼2p)õGRd\\ný¹¶½à«dr¢<À\\tÆ7MÊ;5ìL4Ã¿òp×êòÓ§°[*Iéàbx£uüL¨¿m ­ÒJ¼ª;qO@nòoVrÊzµ}\\f®ôéõ1ÌÑÚ,{5$D@ÌKÛaÕÕjø[7à!\\nPén\\bÌÈ)É\\b5ì­Ø;âQ¬j4¸vl\\f$µôZtJ£íâåI%øûEHr_¦ä§ìo/5J¶DïÔ2FþtÔ4An£:Â- ¹_òB~2ó6OÀe:Jl¨qÿòèýsUMý®¤IØ®p ©_°±¡Ö×fÓózlNß( ]£DþúÅµ¢§2u\\nò`#P°uñÚSÀô4\Aæ¤T; aæwN2©\\rRå\\fÎö6+K©¦¡>å^a·#à2úÁ+é* waA¡AÂe5VÝ«V©/å·æÞq;-+RñnÇðO*Na^ªúiÑ8Pýw¿=È3E3©{ïp+(uw'¼It·jiK(Ú6eß9<c9JûGVñ­×Ê`]À¤:UwÎ¯Ç ÀjÁ¯¸ª\\tÍX=Þ2{a¼Ð"=¾Éhãn¸âFM +¼×ÈÚ:¬ô¹:q­·-Ë­8|\\tíg)#S37w¼ÕPÔîÃC÷"3®)ðaF*6FYý®/>ÃJ[eé÷6ÖÛJ½6WJo6!ìjA3¬¯ho5µD¼ÍîÀÎÉ2)®T¾Ë1õ0ÁÂâó2kI2¸KÕ-È 4kXã²É±;c¹é´«çÇõ«©}Þ]EÖÕúÿî?j 0QÆMbJÿo¿Üxnv×ßºZÔýÄàSFªwÁâ%æ·§ËEÚMþÜ´ñà\\t|égÔH|¼o/¡oF¼[=fª÷ú)F\\b¬)ÉÜqßdW?Ý^®WÂ£!U·%Lz\\n:D5ÆÚ@ÇÔtJÖWÒ~Ø!Æ®ÀaÜnKxIü\\b**üõóDi.\En,­¹9=ÿÀ´jWC+ÂùÙNÈRøinÀ~dm~aÉr;´·ÐÚw¦§-À8]ÔÙ>ºXþ%éÏ¿~Ðg»|XÏ|PVòñøÿÊÍ83¾»éo\\rDÇÿ¤qµÀLpíÏw=-³ÃÑ-~§*äKô£s¤Æ¤?¥!Æài¡Z3¯à¸4U¾>I$GY«cHÂZ5¢`u%½çqCò7«à#\\t¢Á*WÚ[c^å/ügûÂ}0N×±~å½q\\nCC|á@zõÂb)¿pÂYÖÌ³¹ÔÞûÀ%¦ÁåRßì>¶ROC¿.(`5ì0\\ti ¬Â%ö3ãM:Bâë5Ì×³®ð14#a¸ÿ¿äÂVÌoÛ¢Õ_o*ÀaüIÚÇ=«<º±Yçaµ"-mu_¸an6M*$(ÆC{óÔ\\r¸Bù¶dsAY¢´\\b5¡W~7Cÿî<t*dHdVÓh'ùE¤*¤­Wü±_¿Ë¹GXîÉ¢âìÊÎ.U!ëÍÏÕø«8Ð¾¸%°pãÀ¬Ó¥³$Jì_ØN¬YãqQ¢ý6µ.ÏJ¦ìoFlÙ?=¼rHº#yFj,!lzÿÁ!ðØ&óÌb(N\\rL.¬-É£ätÑ5Hk£nNÎ´½=÷_D±ä©ûÇúÙíJb+?êÑ²"²¯a©Ü4Ò\\tÀRR9ºácÜÃø4´î´ñòrÛXXÔØÁeùð2fd<í(TîbÎLØ#YTêZî¥l*ÿTUËÅüÚPs¢:|JH\\r,È)©MÔiÎ¥ûÖJüdÈâûp®tÚTwµ'¹r@÷¥¢kQj÷3Û×ë×·É¦i]tèê¹öÛ#9ú!µX÷êÀ·eãºJxé¼}@ZÛ[! ¢µ¶i\\tÝæER¢¶L66$YØø#G~ÒN­4T¦45Uýña\\rj/)¹Ù4²pT2ô8öX)°ÑD4²bÏ%bïa¾\\bÎ\\n é³AQÌ1ÕZb2`éHWdìlì2£êvÏfråÎa¿´íGlhà>=w¥À%Ùàô'
    //   71: dup
    //   72: astore_2
    //   73: invokevirtual length : ()I
    //   76: istore #4
    //   78: sipush #32767
    //   81: istore_1
    //   82: iconst_m1
    //   83: istore_0
    //   84: bipush #61
    //   86: iinc #0, 1
    //   89: aload_2
    //   90: iload_0
    //   91: dup
    //   92: iload_1
    //   93: iadd
    //   94: invokevirtual substring : (II)Ljava/lang/String;
    //   97: iconst_0
    //   98: goto -> 204
    //   101: aload #5
    //   103: swap
    //   104: iload_3
    //   105: iinc #3, 1
    //   108: swap
    //   109: aastore
    //   110: iload_0
    //   111: iload_1
    //   112: iadd
    //   113: dup
    //   114: istore_0
    //   115: iload #4
    //   117: if_icmpge -> 129
    //   120: aload_2
    //   121: iload_0
    //   122: invokevirtual charAt : (I)C
    //   125: istore_1
    //   126: goto -> 84
    //   129: ldc 'Á9õèÆ±ÙoÙÓyí°ç/±¬)¦\\n¬éª?piÿ$<\\t}býlë'ÔQM]r!Ë£Ù:Eîb3ï|,%q.fãÐÑ=\\r·ì§gÐÙË¸nÕ`pM+í>T\\fôB1j¡ÙPeÏAÑ,²! ËÏ}ö\\t¨³5"\\fµ®Cè:=\\t%ö1 ¾Ý\\t`b,/íÄ'
    //   131: dup
    //   132: astore_2
    //   133: invokevirtual length : ()I
    //   136: istore #4
    //   138: bipush #32
    //   140: istore_1
    //   141: iconst_m1
    //   142: istore_0
    //   143: bipush #21
    //   145: iinc #0, 1
    //   148: aload_2
    //   149: iload_0
    //   150: dup
    //   151: iload_1
    //   152: iadd
    //   153: invokevirtual substring : (II)Ljava/lang/String;
    //   156: iconst_1
    //   157: goto -> 204
    //   160: aload #5
    //   162: swap
    //   163: iload_3
    //   164: iinc #3, 1
    //   167: swap
    //   168: aastore
    //   169: iload_0
    //   170: iload_1
    //   171: iadd
    //   172: dup
    //   173: istore_0
    //   174: iload #4
    //   176: if_icmpge -> 188
    //   179: aload_2
    //   180: iload_0
    //   181: invokevirtual charAt : (I)C
    //   184: istore_1
    //   185: goto -> 143
    //   188: aload #5
    //   190: putstatic burp/Zbuc.a : [Ljava/lang/String;
    //   193: bipush #10
    //   195: anewarray java/lang/String
    //   198: putstatic burp/Zbuc.b : [Ljava/lang/String;
    //   201: goto -> 364
    //   204: dup_x2
    //   205: pop
    //   206: invokevirtual toCharArray : ()[C
    //   209: dup_x1
    //   210: arraylength
    //   211: dup_x2
    //   212: pop
    //   213: iconst_0
    //   214: istore #6
    //   216: dup2_x1
    //   217: pop2
    //   218: dup_x2
    //   219: iconst_1
    //   220: if_icmpgt -> 320
    //   223: dup2
    //   224: swap
    //   225: iload #6
    //   227: dup2_x1
    //   228: caload
    //   229: swap
    //   230: iload #6
    //   232: bipush #7
    //   234: irem
    //   235: tableswitch default -> 302, 0 -> 272, 1 -> 277, 2 -> 282, 3 -> 287, 4 -> 292, 5 -> 297
    //   272: bipush #46
    //   274: goto -> 304
    //   277: bipush #48
    //   279: goto -> 304
    //   282: bipush #124
    //   284: goto -> 304
    //   287: bipush #58
    //   289: goto -> 304
    //   292: bipush #126
    //   294: goto -> 304
    //   297: bipush #126
    //   299: goto -> 304
    //   302: bipush #24
    //   304: ixor
    //   305: ixor
    //   306: i2c
    //   307: castore
    //   308: iinc #6, 1
    //   311: dup
    //   312: ifne -> 320
    //   315: dup2
    //   316: dup_x1
    //   317: goto -> 227
    //   320: dup2_x1
    //   321: pop2
    //   322: dup_x2
    //   323: iload #6
    //   325: if_icmpgt -> 223
    //   328: pop
    //   329: new java/lang/String
    //   332: dup_x1
    //   333: swap
    //   334: invokespecial <init> : ([C)V
    //   337: invokevirtual intern : ()Ljava/lang/String;
    //   340: swap
    //   341: pop
    //   342: swap
    //   343: tableswitch default -> 41, 0 -> 101, 1 -> 160
    //   364: sipush #22565
    //   367: sipush #23500
    //   370: invokestatic a : (II)Ljava/lang/String;
    //   373: putstatic burp/Zbuc.Zu : Ljava/lang/String;
    //   376: getstatic burp/Zbuc.Zu : Ljava/lang/String;
    //   379: sipush #22567
    //   382: sipush #-28211
    //   385: invokestatic a : (II)Ljava/lang/String;
    //   388: <illegal opcode> makeConcatWithConstants : (Ljava/lang/String;Ljava/lang/String;)Ljava/lang/String;
    //   393: putstatic burp/Zbuc.Zu : Ljava/lang/String;
    //   396: new java/math/BigInteger
    //   399: dup
    //   400: sipush #22562
    //   403: sipush #-11852
    //   406: invokestatic a : (II)Ljava/lang/String;
    //   409: invokespecial <init> : (Ljava/lang/String;)V
    //   412: putstatic burp/Zbuc.ZE : Ljava/lang/Object;
    //   415: return
  }
  
  private static Throwable a(Throwable paramThrowable) {
    return paramThrowable;
  }
  
  private static String a(int paramInt1, int paramInt2) {
    int i = (paramInt1 ^ 0x5827) & 0xFFFF;
    if (b[i] == null) {
      char[] arrayOfChar = a[i].toCharArray();
      switch (arrayOfChar[0] & 0xFF) {
        case 0:
        
        case 1:
        
        case 2:
        
        case 3:
        
        case 4:
        
        case 5:
        
        case 6:
        
        case 7:
        
        case 8:
        
        case 9:
        
        case 10:
        
        case 11:
        
        case 12:
        
        case 13:
        
        case 14:
        
        case 15:
        
        case 16:
        
        case 17:
        
        case 18:
        
        case 19:
        
        case 20:
        
        case 21:
        
        case 22:
        
        case 23:
        
        case 24:
        
        case 25:
        
        case 26:
        
        case 27:
        
        case 28:
        
        case 29:
        
        case 30:
        
        case 31:
        
        case 32:
        
        case 33:
        
        case 34:
        
        case 35:
        
        case 36:
        
        case 37:
        
        case 38:
        
        case 39:
        
        case 40:
        
        case 41:
        
        case 42:
        
        case 43:
        
        case 44:
        
        case 45:
        
        case 46:
        
        case 47:
        
        case 48:
        
        case 49:
        
        case 50:
        
        case 51:
        
        case 52:
        
        case 53:
        
        case 54:
        
        case 55:
        
        case 56:
        
        case 57:
        
        case 58:
        
        case 59:
        
        case 60:
        
        case 61:
        
        case 62:
        
        case 63:
        
        case 64:
        
        case 65:
        
        case 66:
        
        case 67:
        
        case 68:
        
        case 69:
        
        case 70:
        
        case 71:
        
        case 72:
        
        case 73:
        
        case 74:
        
        case 75:
        
        case 76:
        
        case 77:
        
        case 78:
        
        case 79:
        
        case 80:
        
        case 81:
        
        case 82:
        
        case 83:
        
        case 84:
        
        case 85:
        
        case 86:
        
        case 87:
        
        case 88:
        
        case 89:
        
        case 90:
        
        case 91:
        
        case 92:
        
        case 93:
        
        case 94:
        
        case 95:
        
        case 96:
        
        case 97:
        
        case 98:
        
        case 99:
        
        case 100:
        
        case 101:
        
        case 102:
        
        case 103:
        
        case 104:
        
        case 105:
        
        case 106:
        
        case 107:
        
        case 108:
        
        case 109:
        
        case 110:
        
        case 111:
        
        case 112:
        
        case 113:
        
        case 114:
        
        case 115:
        
        case 116:
        
        case 117:
        
        case 118:
        
        case 119:
        
        case 120:
        
        case 121:
        
        case 122:
        
        case 123:
        
        case 124:
        
        case 125:
        
        case 126:
        
        case 127:
        
        case 128:
        
        case 129:
        
        case 130:
        
        case 131:
        
        case 132:
        
        case 133:
        
        case 134:
        
        case 135:
        
        case 136:
        
        case 137:
        
        case 138:
        
        case 139:
        
        case 140:
        
        case 141:
        
        case 142:
        
        case 143:
        
        case 144:
        
        case 145:
        
        case 146:
        
        case 147:
        
        case 148:
        
        case 149:
        
        case 150:
        
        case 151:
        
        case 152:
        
        case 153:
        
        case 154:
        
        case 155:
        
        case 156:
        
        case 157:
        
        case 158:
        
        case 159:
        
        case 160:
        
        case 161:
        
        case 162:
        
        case 163:
        
        case 164:
        
        case 165:
        
        case 166:
        
        case 167:
        
        case 168:
        
        case 169:
        
        case 170:
        
        case 171:
        
        case 172:
        
        case 173:
        
        case 174:
        
        case 175:
        
        case 176:
        
        case 177:
        
        case 178:
        
        case 179:
        
        case 180:
        
        case 181:
        
        case 182:
        
        case 183:
        
        case 184:
        
        case 185:
        
        case 186:
        
        case 187:
        
        case 188:
        
        case 189:
        
        case 190:
        
        case 191:
        
        case 192:
        
        case 193:
        
        case 194:
        
        case 195:
        
        case 196:
        
        case 197:
        
        case 198:
        
        case 199:
        
        case 200:
        
        case 201:
        
        case 202:
        
        case 203:
        
        case 204:
        
        case 205:
        
        case 206:
        
        case 207:
        
        case 208:
        
        case 209:
        
        case 210:
        
        case 211:
        
        case 212:
        
        case 213:
        
        case 214:
        
        case 215:
        
        case 216:
        
        case 217:
        
        case 218:
        
        case 219:
        
        case 220:
        
        case 221:
        
        case 222:
        
        case 223:
        
        case 224:
        
        case 225:
        
        case 226:
        
        case 227:
        
        case 228:
        
        case 229:
        
        case 230:
        
        case 231:
        
        case 232:
        
        case 233:
        
        case 234:
        
        case 235:
        
        case 236:
        
        case 237:
        
        case 238:
        
        case 239:
        
        case 240:
        
        case 241:
        
        case 242:
        
        case 243:
        
        case 244:
        
        case 245:
        
        case 246:
        
        case 247:
        
        case 248:
        
        case 249:
        
        case 250:
        
        case 251:
        
        case 252:
        
        case 253:
        
        case 254:
        
        default:
          break;
      } 
      byte b1 = 97;
      int j = (paramInt2 & 0xFF) - b1;
      if (j < 0)
        j += 256; 
      int k = ((paramInt2 & 0xFFFF) >>> 8) - b1;
      if (k < 0)
        k += 256; 
      for (byte b2 = 0; b2 < arrayOfChar.length; b2++) {
        int m = b2 % 2;
        if (m == 0) {
          arrayOfChar[b2] = (char)(arrayOfChar[b2] ^ j);
          j = ((j >>> 3 | j << 5) ^ arrayOfChar[b2]) & 0xFF;
        } else {
          arrayOfChar[b2] = (char)(arrayOfChar[b2] ^ k);
          k = ((k >>> 3 | k << 5) ^ arrayOfChar[b2]) & 0xFF;
        } 
      } 
      b[i] = (new String(arrayOfChar)).intern();
    } 
    return b[i];
  }
}


/* Location:              C:\Program Files\BurpSuitePro\burpsuite_pro.jar!\burp\Zbuc.class
 * Java compiler version: 21 (65.0)
 * JD-Core Version:       1.1.3
 */