package burp;

import java.math.BigInteger;

class Zbw5 extends ClassLoader {
  static String ZC;
  
  static Object ZR;
  
  private static final String[] a;
  
  private static final String[] b;
  
  static boolean Zh(Object[] paramArrayOfObject, Object paramObject) throws Throwable {
    // Byte code:
    //   0: invokestatic ZN : ()Z
    //   3: istore_2
    //   4: getstatic burp/Ztvy.ZH : Ljava/lang/Object;
    //   7: checkcast java/math/BigInteger
    //   10: invokevirtual toByteArray : ()[B
    //   13: astore_3
    //   14: aload_3
    //   15: arraylength
    //   16: bipush #8
    //   18: iadd
    //   19: bipush #6
    //   21: ishr
    //   22: iconst_1
    //   23: iadd
    //   24: bipush #16
    //   26: imul
    //   27: newarray int
    //   29: astore #5
    //   31: iconst_0
    //   32: istore #6
    //   34: iload #6
    //   36: aload_3
    //   37: arraylength
    //   38: if_icmpge -> 81
    //   41: aload_3
    //   42: iload #6
    //   44: baload
    //   45: sipush #255
    //   48: iand
    //   49: istore #7
    //   51: aload #5
    //   53: iload #6
    //   55: iconst_2
    //   56: ishr
    //   57: dup2
    //   58: iaload
    //   59: iload #7
    //   61: bipush #24
    //   63: iload #6
    //   65: iconst_4
    //   66: irem
    //   67: bipush #8
    //   69: imul
    //   70: isub
    //   71: ishl
    //   72: ior
    //   73: iastore
    //   74: iinc #6, 1
    //   77: iload_2
    //   78: ifne -> 34
    //   81: aload #5
    //   83: iload #6
    //   85: iconst_2
    //   86: ishr
    //   87: dup2
    //   88: iaload
    //   89: sipush #128
    //   92: bipush #24
    //   94: iload #6
    //   96: iconst_4
    //   97: irem
    //   98: bipush #8
    //   100: imul
    //   101: isub
    //   102: ishl
    //   103: ior
    //   104: iastore
    //   105: aload #5
    //   107: aload #5
    //   109: arraylength
    //   110: iconst_1
    //   111: isub
    //   112: aload_3
    //   113: arraylength
    //   114: bipush #8
    //   116: imul
    //   117: iastore
    //   118: bipush #80
    //   120: newarray int
    //   122: astore #7
    //   124: ldc 1732584193
    //   126: istore #8
    //   128: ldc -271733879
    //   130: istore #9
    //   132: ldc -1732584194
    //   134: istore #10
    //   136: ldc 271733878
    //   138: istore #11
    //   140: ldc -1009589776
    //   142: istore #12
    //   144: iconst_0
    //   145: istore #6
    //   147: iload #6
    //   149: aload #5
    //   151: arraylength
    //   152: if_icmpge -> 474
    //   155: iload #8
    //   157: istore #13
    //   159: iload #9
    //   161: istore #14
    //   163: iload #10
    //   165: istore #15
    //   167: iload #11
    //   169: istore #16
    //   171: iload #12
    //   173: istore #17
    //   175: iconst_0
    //   176: istore #18
    //   178: iload #18
    //   180: bipush #80
    //   182: if_icmpge -> 432
    //   185: iload #18
    //   187: bipush #16
    //   189: if_icmpge -> 216
    //   192: aload #7
    //   194: iload #18
    //   196: aload #5
    //   198: iload #6
    //   200: iload #18
    //   202: iadd
    //   203: iaload
    //   204: iastore
    //   205: iload_2
    //   206: ifne -> 271
    //   209: goto -> 216
    //   212: invokestatic a : (Ljava/lang/Throwable;)Ljava/lang/Throwable;
    //   215: athrow
    //   216: aload #7
    //   218: iload #18
    //   220: iconst_3
    //   221: isub
    //   222: iaload
    //   223: aload #7
    //   225: iload #18
    //   227: bipush #8
    //   229: isub
    //   230: iaload
    //   231: ixor
    //   232: aload #7
    //   234: iload #18
    //   236: bipush #14
    //   238: isub
    //   239: iaload
    //   240: ixor
    //   241: aload #7
    //   243: iload #18
    //   245: bipush #16
    //   247: isub
    //   248: iaload
    //   249: ixor
    //   250: istore #19
    //   252: iload #19
    //   254: iconst_1
    //   255: ishl
    //   256: iload #19
    //   258: bipush #31
    //   260: iushr
    //   261: ior
    //   262: istore #20
    //   264: aload #7
    //   266: iload #18
    //   268: iload #20
    //   270: iastore
    //   271: iload #8
    //   273: iconst_5
    //   274: ishl
    //   275: iload #8
    //   277: bipush #27
    //   279: iushr
    //   280: ior
    //   281: istore #19
    //   283: iload #19
    //   285: iload #12
    //   287: iadd
    //   288: aload #7
    //   290: iload #18
    //   292: iaload
    //   293: iadd
    //   294: iload #18
    //   296: bipush #20
    //   298: if_icmpge -> 324
    //   301: ldc 1518500249
    //   303: iload #9
    //   305: iload #10
    //   307: iand
    //   308: iload #9
    //   310: iconst_m1
    //   311: ixor
    //   312: iload #11
    //   314: iand
    //   315: ior
    //   316: iadd
    //   317: goto -> 394
    //   320: invokestatic a : (Ljava/lang/Throwable;)Ljava/lang/Throwable;
    //   323: athrow
    //   324: iload #18
    //   326: bipush #40
    //   328: if_icmpge -> 349
    //   331: ldc 1859775393
    //   333: iload #9
    //   335: iload #10
    //   337: ixor
    //   338: iload #11
    //   340: ixor
    //   341: iadd
    //   342: goto -> 394
    //   345: invokestatic a : (Ljava/lang/Throwable;)Ljava/lang/Throwable;
    //   348: athrow
    //   349: iload #18
    //   351: bipush #60
    //   353: if_icmpge -> 383
    //   356: ldc -1894007588
    //   358: iload #9
    //   360: iload #10
    //   362: iand
    //   363: iload #9
    //   365: iload #11
    //   367: iand
    //   368: ior
    //   369: iload #10
    //   371: iload #11
    //   373: iand
    //   374: ior
    //   375: iadd
    //   376: goto -> 394
    //   379: invokestatic a : (Ljava/lang/Throwable;)Ljava/lang/Throwable;
    //   382: athrow
    //   383: ldc -899497514
    //   385: iload #9
    //   387: iload #10
    //   389: ixor
    //   390: iload #11
    //   392: ixor
    //   393: iadd
    //   394: iadd
    //   395: istore #20
    //   397: iload #11
    //   399: istore #12
    //   401: iload #10
    //   403: istore #11
    //   405: iload #9
    //   407: bipush #30
    //   409: ishl
    //   410: iload #9
    //   412: iconst_2
    //   413: iushr
    //   414: ior
    //   415: istore #10
    //   417: iload #8
    //   419: istore #9
    //   421: iload #20
    //   423: istore #8
    //   425: iinc #18, 1
    //   428: iload_2
    //   429: ifne -> 178
    //   432: iload #8
    //   434: iload #13
    //   436: iadd
    //   437: istore #8
    //   439: iload #9
    //   441: iload #14
    //   443: iadd
    //   444: istore #9
    //   446: iload #10
    //   448: iload #15
    //   450: iadd
    //   451: istore #10
    //   453: iload #11
    //   455: iload #16
    //   457: iadd
    //   458: istore #11
    //   460: iload #12
    //   462: iload #17
    //   464: iadd
    //   465: istore #12
    //   467: iinc #6, 16
    //   470: iload_2
    //   471: ifne -> 147
    //   474: iconst_5
    //   475: newarray int
    //   477: dup
    //   478: iconst_0
    //   479: iload #8
    //   481: iastore
    //   482: dup
    //   483: iconst_1
    //   484: iload #9
    //   486: iastore
    //   487: dup
    //   488: iconst_2
    //   489: iload #10
    //   491: iastore
    //   492: dup
    //   493: iconst_3
    //   494: iload #11
    //   496: iastore
    //   497: dup
    //   498: iconst_4
    //   499: iload #12
    //   501: iastore
    //   502: astore #13
    //   504: bipush #20
    //   506: newarray byte
    //   508: astore #14
    //   510: iconst_0
    //   511: istore #15
    //   513: iload #15
    //   515: bipush #20
    //   517: if_icmpge -> 558
    //   520: aload #13
    //   522: iload #15
    //   524: iconst_4
    //   525: idiv
    //   526: iaload
    //   527: istore #16
    //   529: iconst_3
    //   530: iload #15
    //   532: iconst_4
    //   533: irem
    //   534: isub
    //   535: bipush #8
    //   537: imul
    //   538: istore #17
    //   540: aload #14
    //   542: iload #15
    //   544: iload #16
    //   546: iload #17
    //   548: iushr
    //   549: i2b
    //   550: bastore
    //   551: iinc #15, 1
    //   554: iload_2
    //   555: ifne -> 513
    //   558: aload #14
    //   560: astore #4
    //   562: new java/math/BigInteger
    //   565: dup
    //   566: aload #4
    //   568: invokespecial <init> : ([B)V
    //   571: invokevirtual abs : ()Ljava/math/BigInteger;
    //   574: putstatic burp/Zrex.Zr : Ljava/lang/Object;
    //   577: getstatic burp/Zgsy.ZC : Ljava/lang/Object;
    //   580: checkcast java/math/BigInteger
    //   583: getstatic burp/Zk8i.ZN : Ljava/lang/Object;
    //   586: checkcast java/math/BigInteger
    //   589: invokevirtual subtract : (Ljava/math/BigInteger;)Ljava/math/BigInteger;
    //   592: putstatic burp/Zb3r.ZI : Ljava/lang/Object;
    //   595: getstatic burp/Zs1d.Zo : Ljava/lang/Object;
    //   598: checkcast java/math/BigInteger
    //   601: invokevirtual toByteArray : ()[B
    //   604: astore_3
    //   605: bipush #64
    //   607: newarray byte
    //   609: dup
    //   610: iconst_0
    //   611: bipush #-128
    //   613: bastore
    //   614: dup
    //   615: iconst_1
    //   616: iconst_0
    //   617: bastore
    //   618: dup
    //   619: iconst_2
    //   620: iconst_0
    //   621: bastore
    //   622: dup
    //   623: iconst_3
    //   624: iconst_0
    //   625: bastore
    //   626: dup
    //   627: iconst_4
    //   628: iconst_0
    //   629: bastore
    //   630: dup
    //   631: iconst_5
    //   632: iconst_0
    //   633: bastore
    //   634: dup
    //   635: bipush #6
    //   637: iconst_0
    //   638: bastore
    //   639: dup
    //   640: bipush #7
    //   642: iconst_0
    //   643: bastore
    //   644: dup
    //   645: bipush #8
    //   647: iconst_0
    //   648: bastore
    //   649: dup
    //   650: bipush #9
    //   652: iconst_0
    //   653: bastore
    //   654: dup
    //   655: bipush #10
    //   657: iconst_0
    //   658: bastore
    //   659: dup
    //   660: bipush #11
    //   662: iconst_0
    //   663: bastore
    //   664: dup
    //   665: bipush #12
    //   667: iconst_0
    //   668: bastore
    //   669: dup
    //   670: bipush #13
    //   672: iconst_0
    //   673: bastore
    //   674: dup
    //   675: bipush #14
    //   677: iconst_0
    //   678: bastore
    //   679: dup
    //   680: bipush #15
    //   682: iconst_0
    //   683: bastore
    //   684: dup
    //   685: bipush #16
    //   687: iconst_0
    //   688: bastore
    //   689: dup
    //   690: bipush #17
    //   692: iconst_0
    //   693: bastore
    //   694: dup
    //   695: bipush #18
    //   697: iconst_0
    //   698: bastore
    //   699: dup
    //   700: bipush #19
    //   702: iconst_0
    //   703: bastore
    //   704: dup
    //   705: bipush #20
    //   707: iconst_0
    //   708: bastore
    //   709: dup
    //   710: bipush #21
    //   712: iconst_0
    //   713: bastore
    //   714: dup
    //   715: bipush #22
    //   717: iconst_0
    //   718: bastore
    //   719: dup
    //   720: bipush #23
    //   722: iconst_0
    //   723: bastore
    //   724: dup
    //   725: bipush #24
    //   727: iconst_0
    //   728: bastore
    //   729: dup
    //   730: bipush #25
    //   732: iconst_0
    //   733: bastore
    //   734: dup
    //   735: bipush #26
    //   737: iconst_0
    //   738: bastore
    //   739: dup
    //   740: bipush #27
    //   742: iconst_0
    //   743: bastore
    //   744: dup
    //   745: bipush #28
    //   747: iconst_0
    //   748: bastore
    //   749: dup
    //   750: bipush #29
    //   752: iconst_0
    //   753: bastore
    //   754: dup
    //   755: bipush #30
    //   757: iconst_0
    //   758: bastore
    //   759: dup
    //   760: bipush #31
    //   762: iconst_0
    //   763: bastore
    //   764: dup
    //   765: bipush #32
    //   767: iconst_0
    //   768: bastore
    //   769: dup
    //   770: bipush #33
    //   772: iconst_0
    //   773: bastore
    //   774: dup
    //   775: bipush #34
    //   777: iconst_0
    //   778: bastore
    //   779: dup
    //   780: bipush #35
    //   782: iconst_0
    //   783: bastore
    //   784: dup
    //   785: bipush #36
    //   787: iconst_0
    //   788: bastore
    //   789: dup
    //   790: bipush #37
    //   792: iconst_0
    //   793: bastore
    //   794: dup
    //   795: bipush #38
    //   797: iconst_0
    //   798: bastore
    //   799: dup
    //   800: bipush #39
    //   802: iconst_0
    //   803: bastore
    //   804: dup
    //   805: bipush #40
    //   807: iconst_0
    //   808: bastore
    //   809: dup
    //   810: bipush #41
    //   812: iconst_0
    //   813: bastore
    //   814: dup
    //   815: bipush #42
    //   817: iconst_0
    //   818: bastore
    //   819: dup
    //   820: bipush #43
    //   822: iconst_0
    //   823: bastore
    //   824: dup
    //   825: bipush #44
    //   827: iconst_0
    //   828: bastore
    //   829: dup
    //   830: bipush #45
    //   832: iconst_0
    //   833: bastore
    //   834: dup
    //   835: bipush #46
    //   837: iconst_0
    //   838: bastore
    //   839: dup
    //   840: bipush #47
    //   842: iconst_0
    //   843: bastore
    //   844: dup
    //   845: bipush #48
    //   847: iconst_0
    //   848: bastore
    //   849: dup
    //   850: bipush #49
    //   852: iconst_0
    //   853: bastore
    //   854: dup
    //   855: bipush #50
    //   857: iconst_0
    //   858: bastore
    //   859: dup
    //   860: bipush #51
    //   862: iconst_0
    //   863: bastore
    //   864: dup
    //   865: bipush #52
    //   867: iconst_0
    //   868: bastore
    //   869: dup
    //   870: bipush #53
    //   872: iconst_0
    //   873: bastore
    //   874: dup
    //   875: bipush #54
    //   877: iconst_0
    //   878: bastore
    //   879: dup
    //   880: bipush #55
    //   882: iconst_0
    //   883: bastore
    //   884: dup
    //   885: bipush #56
    //   887: iconst_0
    //   888: bastore
    //   889: dup
    //   890: bipush #57
    //   892: iconst_0
    //   893: bastore
    //   894: dup
    //   895: bipush #58
    //   897: iconst_0
    //   898: bastore
    //   899: dup
    //   900: bipush #59
    //   902: iconst_0
    //   903: bastore
    //   904: dup
    //   905: bipush #60
    //   907: iconst_0
    //   908: bastore
    //   909: dup
    //   910: bipush #61
    //   912: iconst_0
    //   913: bastore
    //   914: dup
    //   915: bipush #62
    //   917: iconst_0
    //   918: bastore
    //   919: dup
    //   920: bipush #63
    //   922: iconst_0
    //   923: bastore
    //   924: astore #5
    //   926: bipush #64
    //   928: newarray int
    //   930: dup
    //   931: iconst_0
    //   932: ldc 1116352408
    //   934: iastore
    //   935: dup
    //   936: iconst_1
    //   937: ldc 1899447441
    //   939: iastore
    //   940: dup
    //   941: iconst_2
    //   942: ldc -1245643825
    //   944: iastore
    //   945: dup
    //   946: iconst_3
    //   947: ldc -373957723
    //   949: iastore
    //   950: dup
    //   951: iconst_4
    //   952: ldc 961987163
    //   954: iastore
    //   955: dup
    //   956: iconst_5
    //   957: ldc 1508970993
    //   959: iastore
    //   960: dup
    //   961: bipush #6
    //   963: ldc -1841331548
    //   965: iastore
    //   966: dup
    //   967: bipush #7
    //   969: ldc -1424204075
    //   971: iastore
    //   972: dup
    //   973: bipush #8
    //   975: ldc -670586216
    //   977: iastore
    //   978: dup
    //   979: bipush #9
    //   981: ldc 310598401
    //   983: iastore
    //   984: dup
    //   985: bipush #10
    //   987: ldc 607225278
    //   989: iastore
    //   990: dup
    //   991: bipush #11
    //   993: ldc 1426881987
    //   995: iastore
    //   996: dup
    //   997: bipush #12
    //   999: ldc 1925078388
    //   1001: iastore
    //   1002: dup
    //   1003: bipush #13
    //   1005: ldc -2132889090
    //   1007: iastore
    //   1008: dup
    //   1009: bipush #14
    //   1011: ldc -1680079193
    //   1013: iastore
    //   1014: dup
    //   1015: bipush #15
    //   1017: ldc -1046744716
    //   1019: iastore
    //   1020: dup
    //   1021: bipush #16
    //   1023: ldc -459576895
    //   1025: iastore
    //   1026: dup
    //   1027: bipush #17
    //   1029: ldc -272742522
    //   1031: iastore
    //   1032: dup
    //   1033: bipush #18
    //   1035: ldc 264347078
    //   1037: iastore
    //   1038: dup
    //   1039: bipush #19
    //   1041: ldc 604807628
    //   1043: iastore
    //   1044: dup
    //   1045: bipush #20
    //   1047: ldc 770255983
    //   1049: iastore
    //   1050: dup
    //   1051: bipush #21
    //   1053: ldc 1249150122
    //   1055: iastore
    //   1056: dup
    //   1057: bipush #22
    //   1059: ldc 1555081692
    //   1061: iastore
    //   1062: dup
    //   1063: bipush #23
    //   1065: ldc 1996064986
    //   1067: iastore
    //   1068: dup
    //   1069: bipush #24
    //   1071: ldc -1740746414
    //   1073: iastore
    //   1074: dup
    //   1075: bipush #25
    //   1077: ldc -1473132947
    //   1079: iastore
    //   1080: dup
    //   1081: bipush #26
    //   1083: ldc -1341970488
    //   1085: iastore
    //   1086: dup
    //   1087: bipush #27
    //   1089: ldc -1084653625
    //   1091: iastore
    //   1092: dup
    //   1093: bipush #28
    //   1095: ldc -958395405
    //   1097: iastore
    //   1098: dup
    //   1099: bipush #29
    //   1101: ldc -710438585
    //   1103: iastore
    //   1104: dup
    //   1105: bipush #30
    //   1107: ldc 113926993
    //   1109: iastore
    //   1110: dup
    //   1111: bipush #31
    //   1113: ldc 338241895
    //   1115: iastore
    //   1116: dup
    //   1117: bipush #32
    //   1119: ldc 666307205
    //   1121: iastore
    //   1122: dup
    //   1123: bipush #33
    //   1125: ldc 773529912
    //   1127: iastore
    //   1128: dup
    //   1129: bipush #34
    //   1131: ldc 1294757372
    //   1133: iastore
    //   1134: dup
    //   1135: bipush #35
    //   1137: ldc 1396182291
    //   1139: iastore
    //   1140: dup
    //   1141: bipush #36
    //   1143: ldc 1695183700
    //   1145: iastore
    //   1146: dup
    //   1147: bipush #37
    //   1149: ldc 1986661051
    //   1151: iastore
    //   1152: dup
    //   1153: bipush #38
    //   1155: ldc -2117940946
    //   1157: iastore
    //   1158: dup
    //   1159: bipush #39
    //   1161: ldc -1838011259
    //   1163: iastore
    //   1164: dup
    //   1165: bipush #40
    //   1167: ldc -1564481375
    //   1169: iastore
    //   1170: dup
    //   1171: bipush #41
    //   1173: ldc -1474664885
    //   1175: iastore
    //   1176: dup
    //   1177: bipush #42
    //   1179: ldc -1035236496
    //   1181: iastore
    //   1182: dup
    //   1183: bipush #43
    //   1185: ldc -949202525
    //   1187: iastore
    //   1188: dup
    //   1189: bipush #44
    //   1191: ldc -778901479
    //   1193: iastore
    //   1194: dup
    //   1195: bipush #45
    //   1197: ldc -694614492
    //   1199: iastore
    //   1200: dup
    //   1201: bipush #46
    //   1203: ldc -200395387
    //   1205: iastore
    //   1206: dup
    //   1207: bipush #47
    //   1209: ldc 275423344
    //   1211: iastore
    //   1212: dup
    //   1213: bipush #48
    //   1215: ldc 430227734
    //   1217: iastore
    //   1218: dup
    //   1219: bipush #49
    //   1221: ldc 506948616
    //   1223: iastore
    //   1224: dup
    //   1225: bipush #50
    //   1227: ldc 659060556
    //   1229: iastore
    //   1230: dup
    //   1231: bipush #51
    //   1233: ldc 883997877
    //   1235: iastore
    //   1236: dup
    //   1237: bipush #52
    //   1239: ldc 958139571
    //   1241: iastore
    //   1242: dup
    //   1243: bipush #53
    //   1245: ldc 1322822218
    //   1247: iastore
    //   1248: dup
    //   1249: bipush #54
    //   1251: ldc 1537002063
    //   1253: iastore
    //   1254: dup
    //   1255: bipush #55
    //   1257: ldc 1747873779
    //   1259: iastore
    //   1260: dup
    //   1261: bipush #56
    //   1263: ldc 1955562222
    //   1265: iastore
    //   1266: dup
    //   1267: bipush #57
    //   1269: ldc 2024104815
    //   1271: iastore
    //   1272: dup
    //   1273: bipush #58
    //   1275: ldc -2067236844
    //   1277: iastore
    //   1278: dup
    //   1279: bipush #59
    //   1281: ldc -1933114872
    //   1283: iastore
    //   1284: dup
    //   1285: bipush #60
    //   1287: ldc -1866530822
    //   1289: iastore
    //   1290: dup
    //   1291: bipush #61
    //   1293: ldc -1538233109
    //   1295: iastore
    //   1296: dup
    //   1297: bipush #62
    //   1299: ldc -1090935817
    //   1301: iastore
    //   1302: dup
    //   1303: bipush #63
    //   1305: ldc -965641998
    //   1307: iastore
    //   1308: astore #6
    //   1310: iconst_2
    //   1311: newarray int
    //   1313: dup
    //   1314: iconst_0
    //   1315: iconst_0
    //   1316: iastore
    //   1317: dup
    //   1318: iconst_1
    //   1319: iconst_0
    //   1320: iastore
    //   1321: astore #7
    //   1323: bipush #8
    //   1325: newarray int
    //   1327: dup
    //   1328: iconst_0
    //   1329: ldc 1779033703
    //   1331: iastore
    //   1332: dup
    //   1333: iconst_1
    //   1334: ldc -1150833019
    //   1336: iastore
    //   1337: dup
    //   1338: iconst_2
    //   1339: ldc 1013904242
    //   1341: iastore
    //   1342: dup
    //   1343: iconst_3
    //   1344: ldc -1521486534
    //   1346: iastore
    //   1347: dup
    //   1348: iconst_4
    //   1349: ldc 1359893119
    //   1351: iastore
    //   1352: dup
    //   1353: iconst_5
    //   1354: ldc -1694144372
    //   1356: iastore
    //   1357: dup
    //   1358: bipush #6
    //   1360: ldc 528734635
    //   1362: iastore
    //   1363: dup
    //   1364: bipush #7
    //   1366: ldc 1541459225
    //   1368: iastore
    //   1369: astore #8
    //   1371: bipush #64
    //   1373: newarray byte
    //   1375: astore #9
    //   1377: bipush #64
    //   1379: newarray byte
    //   1381: astore #10
    //   1383: aload_3
    //   1384: arraylength
    //   1385: istore #11
    //   1387: aload #7
    //   1389: iconst_0
    //   1390: iaload
    //   1391: bipush #63
    //   1393: iand
    //   1394: istore #12
    //   1396: aload #7
    //   1398: iconst_0
    //   1399: dup2
    //   1400: iaload
    //   1401: iload #11
    //   1403: iadd
    //   1404: iastore
    //   1405: aload #7
    //   1407: iconst_0
    //   1408: dup2
    //   1409: iaload
    //   1410: iconst_m1
    //   1411: iand
    //   1412: iastore
    //   1413: aload #7
    //   1415: iconst_0
    //   1416: iaload
    //   1417: iload #11
    //   1419: if_icmpge -> 1437
    //   1422: aload #7
    //   1424: iconst_1
    //   1425: dup2
    //   1426: iaload
    //   1427: iconst_1
    //   1428: iadd
    //   1429: iastore
    //   1430: goto -> 1437
    //   1433: invokestatic a : (Ljava/lang/Throwable;)Ljava/lang/Throwable;
    //   1436: athrow
    //   1437: iconst_0
    //   1438: istore #13
    //   1440: iload #11
    //   1442: bipush #64
    //   1444: if_icmplt -> 2053
    //   1447: iconst_0
    //   1448: istore #14
    //   1450: iload #14
    //   1452: bipush #64
    //   1454: if_icmpge -> 1476
    //   1457: aload #10
    //   1459: iload #14
    //   1461: aload_3
    //   1462: iload #13
    //   1464: iload #14
    //   1466: iadd
    //   1467: baload
    //   1468: bastore
    //   1469: iinc #14, 1
    //   1472: iload_2
    //   1473: ifne -> 1450
    //   1476: bipush #64
    //   1478: newarray int
    //   1480: astore #14
    //   1482: bipush #8
    //   1484: newarray int
    //   1486: astore #15
    //   1488: iconst_0
    //   1489: istore #16
    //   1491: iload #16
    //   1493: bipush #8
    //   1495: if_icmpge -> 1515
    //   1498: aload #15
    //   1500: iload #16
    //   1502: aload #8
    //   1504: iload #16
    //   1506: iaload
    //   1507: iastore
    //   1508: iinc #16, 1
    //   1511: iload_2
    //   1512: ifne -> 1491
    //   1515: iconst_0
    //   1516: istore #16
    //   1518: iload #16
    //   1520: bipush #64
    //   1522: if_icmpge -> 2013
    //   1525: iload #16
    //   1527: bipush #16
    //   1529: if_icmpge -> 1610
    //   1532: aload #14
    //   1534: iload #16
    //   1536: aload #10
    //   1538: iconst_4
    //   1539: iload #16
    //   1541: imul
    //   1542: baload
    //   1543: sipush #255
    //   1546: iand
    //   1547: bipush #24
    //   1549: ishl
    //   1550: aload #10
    //   1552: iconst_4
    //   1553: iload #16
    //   1555: imul
    //   1556: iconst_1
    //   1557: iadd
    //   1558: baload
    //   1559: sipush #255
    //   1562: iand
    //   1563: bipush #16
    //   1565: ishl
    //   1566: ior
    //   1567: aload #10
    //   1569: iconst_4
    //   1570: iload #16
    //   1572: imul
    //   1573: iconst_2
    //   1574: iadd
    //   1575: baload
    //   1576: sipush #255
    //   1579: iand
    //   1580: bipush #8
    //   1582: ishl
    //   1583: ior
    //   1584: aload #10
    //   1586: iconst_4
    //   1587: iload #16
    //   1589: imul
    //   1590: iconst_3
    //   1591: iadd
    //   1592: baload
    //   1593: sipush #255
    //   1596: iand
    //   1597: ior
    //   1598: iastore
    //   1599: iload_2
    //   1600: ifne -> 1753
    //   1603: goto -> 1610
    //   1606: invokestatic a : (Ljava/lang/Throwable;)Ljava/lang/Throwable;
    //   1609: athrow
    //   1610: aload #14
    //   1612: iload #16
    //   1614: aload #14
    //   1616: iload #16
    //   1618: iconst_2
    //   1619: isub
    //   1620: iaload
    //   1621: bipush #17
    //   1623: iushr
    //   1624: aload #14
    //   1626: iload #16
    //   1628: iconst_2
    //   1629: isub
    //   1630: iaload
    //   1631: bipush #15
    //   1633: ishl
    //   1634: ior
    //   1635: aload #14
    //   1637: iload #16
    //   1639: iconst_2
    //   1640: isub
    //   1641: iaload
    //   1642: bipush #19
    //   1644: iushr
    //   1645: aload #14
    //   1647: iload #16
    //   1649: iconst_2
    //   1650: isub
    //   1651: iaload
    //   1652: bipush #13
    //   1654: ishl
    //   1655: ior
    //   1656: ixor
    //   1657: aload #14
    //   1659: iload #16
    //   1661: iconst_2
    //   1662: isub
    //   1663: iaload
    //   1664: bipush #10
    //   1666: iushr
    //   1667: ixor
    //   1668: aload #14
    //   1670: iload #16
    //   1672: bipush #7
    //   1674: isub
    //   1675: iaload
    //   1676: iadd
    //   1677: aload #14
    //   1679: iload #16
    //   1681: bipush #15
    //   1683: isub
    //   1684: iaload
    //   1685: bipush #7
    //   1687: iushr
    //   1688: aload #14
    //   1690: iload #16
    //   1692: bipush #15
    //   1694: isub
    //   1695: iaload
    //   1696: bipush #25
    //   1698: ishl
    //   1699: ior
    //   1700: aload #14
    //   1702: iload #16
    //   1704: bipush #15
    //   1706: isub
    //   1707: iaload
    //   1708: bipush #18
    //   1710: iushr
    //   1711: aload #14
    //   1713: iload #16
    //   1715: bipush #15
    //   1717: isub
    //   1718: iaload
    //   1719: bipush #14
    //   1721: ishl
    //   1722: ior
    //   1723: ixor
    //   1724: aload #14
    //   1726: iload #16
    //   1728: bipush #15
    //   1730: isub
    //   1731: iaload
    //   1732: iconst_3
    //   1733: iushr
    //   1734: ixor
    //   1735: iadd
    //   1736: aload #14
    //   1738: iload #16
    //   1740: bipush #16
    //   1742: isub
    //   1743: iaload
    //   1744: iadd
    //   1745: iastore
    //   1746: goto -> 1753
    //   1749: invokestatic a : (Ljava/lang/Throwable;)Ljava/lang/Throwable;
    //   1752: athrow
    //   1753: aload #15
    //   1755: bipush #7
    //   1757: iaload
    //   1758: aload #15
    //   1760: iconst_4
    //   1761: iaload
    //   1762: bipush #6
    //   1764: iushr
    //   1765: aload #15
    //   1767: iconst_4
    //   1768: iaload
    //   1769: bipush #26
    //   1771: ishl
    //   1772: ior
    //   1773: aload #15
    //   1775: iconst_4
    //   1776: iaload
    //   1777: bipush #11
    //   1779: iushr
    //   1780: aload #15
    //   1782: iconst_4
    //   1783: iaload
    //   1784: bipush #21
    //   1786: ishl
    //   1787: ior
    //   1788: ixor
    //   1789: aload #15
    //   1791: iconst_4
    //   1792: iaload
    //   1793: bipush #25
    //   1795: iushr
    //   1796: aload #15
    //   1798: iconst_4
    //   1799: iaload
    //   1800: bipush #7
    //   1802: ishl
    //   1803: ior
    //   1804: ixor
    //   1805: iadd
    //   1806: aload #15
    //   1808: bipush #6
    //   1810: iaload
    //   1811: aload #15
    //   1813: iconst_4
    //   1814: iaload
    //   1815: aload #15
    //   1817: iconst_5
    //   1818: iaload
    //   1819: aload #15
    //   1821: bipush #6
    //   1823: iaload
    //   1824: ixor
    //   1825: iand
    //   1826: ixor
    //   1827: iadd
    //   1828: aload #6
    //   1830: iload #16
    //   1832: iaload
    //   1833: iadd
    //   1834: aload #14
    //   1836: iload #16
    //   1838: iaload
    //   1839: iadd
    //   1840: istore #17
    //   1842: aload #15
    //   1844: iconst_0
    //   1845: iaload
    //   1846: iconst_2
    //   1847: iushr
    //   1848: aload #15
    //   1850: iconst_0
    //   1851: iaload
    //   1852: bipush #30
    //   1854: ishl
    //   1855: ior
    //   1856: aload #15
    //   1858: iconst_0
    //   1859: iaload
    //   1860: bipush #13
    //   1862: iushr
    //   1863: aload #15
    //   1865: iconst_0
    //   1866: iaload
    //   1867: bipush #19
    //   1869: ishl
    //   1870: ior
    //   1871: ixor
    //   1872: aload #15
    //   1874: iconst_0
    //   1875: iaload
    //   1876: bipush #22
    //   1878: iushr
    //   1879: aload #15
    //   1881: iconst_0
    //   1882: iaload
    //   1883: bipush #10
    //   1885: ishl
    //   1886: ior
    //   1887: ixor
    //   1888: aload #15
    //   1890: iconst_0
    //   1891: iaload
    //   1892: aload #15
    //   1894: iconst_1
    //   1895: iaload
    //   1896: iand
    //   1897: aload #15
    //   1899: iconst_2
    //   1900: iaload
    //   1901: aload #15
    //   1903: iconst_0
    //   1904: iaload
    //   1905: aload #15
    //   1907: iconst_1
    //   1908: iaload
    //   1909: ior
    //   1910: iand
    //   1911: ior
    //   1912: iadd
    //   1913: istore #18
    //   1915: aload #15
    //   1917: iconst_3
    //   1918: dup2
    //   1919: iaload
    //   1920: iload #17
    //   1922: iadd
    //   1923: iastore
    //   1924: aload #15
    //   1926: bipush #7
    //   1928: iload #17
    //   1930: iload #18
    //   1932: iadd
    //   1933: iastore
    //   1934: aload #15
    //   1936: bipush #7
    //   1938: iaload
    //   1939: istore #17
    //   1941: aload #15
    //   1943: bipush #7
    //   1945: aload #15
    //   1947: bipush #6
    //   1949: iaload
    //   1950: iastore
    //   1951: aload #15
    //   1953: bipush #6
    //   1955: aload #15
    //   1957: iconst_5
    //   1958: iaload
    //   1959: iastore
    //   1960: aload #15
    //   1962: iconst_5
    //   1963: aload #15
    //   1965: iconst_4
    //   1966: iaload
    //   1967: iastore
    //   1968: aload #15
    //   1970: iconst_4
    //   1971: aload #15
    //   1973: iconst_3
    //   1974: iaload
    //   1975: iastore
    //   1976: aload #15
    //   1978: iconst_3
    //   1979: aload #15
    //   1981: iconst_2
    //   1982: iaload
    //   1983: iastore
    //   1984: aload #15
    //   1986: iconst_2
    //   1987: aload #15
    //   1989: iconst_1
    //   1990: iaload
    //   1991: iastore
    //   1992: aload #15
    //   1994: iconst_1
    //   1995: aload #15
    //   1997: iconst_0
    //   1998: iaload
    //   1999: iastore
    //   2000: aload #15
    //   2002: iconst_0
    //   2003: iload #17
    //   2005: iastore
    //   2006: iinc #16, 1
    //   2009: iload_2
    //   2010: ifne -> 1518
    //   2013: iconst_0
    //   2014: istore #16
    //   2016: iload #16
    //   2018: bipush #8
    //   2020: if_icmpge -> 2043
    //   2023: aload #8
    //   2025: iload #16
    //   2027: dup2
    //   2028: iaload
    //   2029: aload #15
    //   2031: iload #16
    //   2033: iaload
    //   2034: iadd
    //   2035: iastore
    //   2036: iinc #16, 1
    //   2039: iload_2
    //   2040: ifne -> 2016
    //   2043: iinc #13, 64
    //   2046: iinc #11, -64
    //   2049: iload_2
    //   2050: ifne -> 1440
    //   2053: iload #11
    //   2055: ifle -> 2090
    //   2058: iconst_0
    //   2059: istore #14
    //   2061: iload #14
    //   2063: iload #11
    //   2065: if_icmpge -> 2090
    //   2068: aload #9
    //   2070: iload #12
    //   2072: iload #14
    //   2074: iadd
    //   2075: aload_3
    //   2076: iload #13
    //   2078: iload #14
    //   2080: iadd
    //   2081: baload
    //   2082: bastore
    //   2083: iinc #14, 1
    //   2086: iload_2
    //   2087: ifne -> 2061
    //   2090: aload #7
    //   2092: iconst_0
    //   2093: iaload
    //   2094: bipush #29
    //   2096: iushr
    //   2097: aload #7
    //   2099: iconst_1
    //   2100: iaload
    //   2101: iconst_3
    //   2102: ishl
    //   2103: ior
    //   2104: istore #14
    //   2106: aload #7
    //   2108: iconst_0
    //   2109: iaload
    //   2110: iconst_3
    //   2111: ishl
    //   2112: istore #15
    //   2114: aload #7
    //   2116: iconst_0
    //   2117: iaload
    //   2118: bipush #63
    //   2120: iand
    //   2121: istore #16
    //   2123: iload #16
    //   2125: bipush #56
    //   2127: if_icmpge -> 2142
    //   2130: bipush #56
    //   2132: iload #16
    //   2134: isub
    //   2135: goto -> 2147
    //   2138: invokestatic a : (Ljava/lang/Throwable;)Ljava/lang/Throwable;
    //   2141: athrow
    //   2142: bipush #120
    //   2144: iload #16
    //   2146: isub
    //   2147: istore #17
    //   2149: aload #7
    //   2151: iconst_0
    //   2152: iaload
    //   2153: bipush #63
    //   2155: iand
    //   2156: istore #12
    //   2158: bipush #64
    //   2160: iload #12
    //   2162: isub
    //   2163: istore #18
    //   2165: aload #7
    //   2167: iconst_0
    //   2168: dup2
    //   2169: iaload
    //   2170: iload #17
    //   2172: iadd
    //   2173: iastore
    //   2174: aload #7
    //   2176: iconst_0
    //   2177: dup2
    //   2178: iaload
    //   2179: iconst_m1
    //   2180: iand
    //   2181: iastore
    //   2182: aload #7
    //   2184: iconst_0
    //   2185: iaload
    //   2186: iload #17
    //   2188: if_icmpge -> 2206
    //   2191: aload #7
    //   2193: iconst_1
    //   2194: dup2
    //   2195: iaload
    //   2196: iconst_1
    //   2197: iadd
    //   2198: iastore
    //   2199: goto -> 2206
    //   2202: invokestatic a : (Ljava/lang/Throwable;)Ljava/lang/Throwable;
    //   2205: athrow
    //   2206: iconst_0
    //   2207: istore #13
    //   2209: iload #12
    //   2211: ifle -> 2842
    //   2214: iload #17
    //   2216: iload #18
    //   2218: if_icmplt -> 2842
    //   2221: goto -> 2228
    //   2224: invokestatic a : (Ljava/lang/Throwable;)Ljava/lang/Throwable;
    //   2227: athrow
    //   2228: iconst_0
    //   2229: istore #19
    //   2231: iload #19
    //   2233: iload #18
    //   2235: if_icmpge -> 2258
    //   2238: aload #9
    //   2240: iload #12
    //   2242: iload #19
    //   2244: iadd
    //   2245: aload #5
    //   2247: iload #19
    //   2249: baload
    //   2250: bastore
    //   2251: iinc #19, 1
    //   2254: iload_2
    //   2255: ifne -> 2231
    //   2258: bipush #64
    //   2260: newarray int
    //   2262: astore #19
    //   2264: bipush #8
    //   2266: newarray int
    //   2268: astore #20
    //   2270: iconst_0
    //   2271: istore #21
    //   2273: iload #21
    //   2275: bipush #8
    //   2277: if_icmpge -> 2297
    //   2280: aload #20
    //   2282: iload #21
    //   2284: aload #8
    //   2286: iload #21
    //   2288: iaload
    //   2289: iastore
    //   2290: iinc #21, 1
    //   2293: iload_2
    //   2294: ifne -> 2273
    //   2297: iconst_0
    //   2298: istore #21
    //   2300: iload #21
    //   2302: bipush #64
    //   2304: if_icmpge -> 2795
    //   2307: iload #21
    //   2309: bipush #16
    //   2311: if_icmpge -> 2392
    //   2314: aload #19
    //   2316: iload #21
    //   2318: aload #9
    //   2320: iconst_4
    //   2321: iload #21
    //   2323: imul
    //   2324: baload
    //   2325: sipush #255
    //   2328: iand
    //   2329: bipush #24
    //   2331: ishl
    //   2332: aload #9
    //   2334: iconst_4
    //   2335: iload #21
    //   2337: imul
    //   2338: iconst_1
    //   2339: iadd
    //   2340: baload
    //   2341: sipush #255
    //   2344: iand
    //   2345: bipush #16
    //   2347: ishl
    //   2348: ior
    //   2349: aload #9
    //   2351: iconst_4
    //   2352: iload #21
    //   2354: imul
    //   2355: iconst_2
    //   2356: iadd
    //   2357: baload
    //   2358: sipush #255
    //   2361: iand
    //   2362: bipush #8
    //   2364: ishl
    //   2365: ior
    //   2366: aload #9
    //   2368: iconst_4
    //   2369: iload #21
    //   2371: imul
    //   2372: iconst_3
    //   2373: iadd
    //   2374: baload
    //   2375: sipush #255
    //   2378: iand
    //   2379: ior
    //   2380: iastore
    //   2381: iload_2
    //   2382: ifne -> 2535
    //   2385: goto -> 2392
    //   2388: invokestatic a : (Ljava/lang/Throwable;)Ljava/lang/Throwable;
    //   2391: athrow
    //   2392: aload #19
    //   2394: iload #21
    //   2396: aload #19
    //   2398: iload #21
    //   2400: iconst_2
    //   2401: isub
    //   2402: iaload
    //   2403: bipush #17
    //   2405: iushr
    //   2406: aload #19
    //   2408: iload #21
    //   2410: iconst_2
    //   2411: isub
    //   2412: iaload
    //   2413: bipush #15
    //   2415: ishl
    //   2416: ior
    //   2417: aload #19
    //   2419: iload #21
    //   2421: iconst_2
    //   2422: isub
    //   2423: iaload
    //   2424: bipush #19
    //   2426: iushr
    //   2427: aload #19
    //   2429: iload #21
    //   2431: iconst_2
    //   2432: isub
    //   2433: iaload
    //   2434: bipush #13
    //   2436: ishl
    //   2437: ior
    //   2438: ixor
    //   2439: aload #19
    //   2441: iload #21
    //   2443: iconst_2
    //   2444: isub
    //   2445: iaload
    //   2446: bipush #10
    //   2448: iushr
    //   2449: ixor
    //   2450: aload #19
    //   2452: iload #21
    //   2454: bipush #7
    //   2456: isub
    //   2457: iaload
    //   2458: iadd
    //   2459: aload #19
    //   2461: iload #21
    //   2463: bipush #15
    //   2465: isub
    //   2466: iaload
    //   2467: bipush #7
    //   2469: iushr
    //   2470: aload #19
    //   2472: iload #21
    //   2474: bipush #15
    //   2476: isub
    //   2477: iaload
    //   2478: bipush #25
    //   2480: ishl
    //   2481: ior
    //   2482: aload #19
    //   2484: iload #21
    //   2486: bipush #15
    //   2488: isub
    //   2489: iaload
    //   2490: bipush #18
    //   2492: iushr
    //   2493: aload #19
    //   2495: iload #21
    //   2497: bipush #15
    //   2499: isub
    //   2500: iaload
    //   2501: bipush #14
    //   2503: ishl
    //   2504: ior
    //   2505: ixor
    //   2506: aload #19
    //   2508: iload #21
    //   2510: bipush #15
    //   2512: isub
    //   2513: iaload
    //   2514: iconst_3
    //   2515: iushr
    //   2516: ixor
    //   2517: iadd
    //   2518: aload #19
    //   2520: iload #21
    //   2522: bipush #16
    //   2524: isub
    //   2525: iaload
    //   2526: iadd
    //   2527: iastore
    //   2528: goto -> 2535
    //   2531: invokestatic a : (Ljava/lang/Throwable;)Ljava/lang/Throwable;
    //   2534: athrow
    //   2535: aload #20
    //   2537: bipush #7
    //   2539: iaload
    //   2540: aload #20
    //   2542: iconst_4
    //   2543: iaload
    //   2544: bipush #6
    //   2546: iushr
    //   2547: aload #20
    //   2549: iconst_4
    //   2550: iaload
    //   2551: bipush #26
    //   2553: ishl
    //   2554: ior
    //   2555: aload #20
    //   2557: iconst_4
    //   2558: iaload
    //   2559: bipush #11
    //   2561: iushr
    //   2562: aload #20
    //   2564: iconst_4
    //   2565: iaload
    //   2566: bipush #21
    //   2568: ishl
    //   2569: ior
    //   2570: ixor
    //   2571: aload #20
    //   2573: iconst_4
    //   2574: iaload
    //   2575: bipush #25
    //   2577: iushr
    //   2578: aload #20
    //   2580: iconst_4
    //   2581: iaload
    //   2582: bipush #7
    //   2584: ishl
    //   2585: ior
    //   2586: ixor
    //   2587: iadd
    //   2588: aload #20
    //   2590: bipush #6
    //   2592: iaload
    //   2593: aload #20
    //   2595: iconst_4
    //   2596: iaload
    //   2597: aload #20
    //   2599: iconst_5
    //   2600: iaload
    //   2601: aload #20
    //   2603: bipush #6
    //   2605: iaload
    //   2606: ixor
    //   2607: iand
    //   2608: ixor
    //   2609: iadd
    //   2610: aload #6
    //   2612: iload #21
    //   2614: iaload
    //   2615: iadd
    //   2616: aload #19
    //   2618: iload #21
    //   2620: iaload
    //   2621: iadd
    //   2622: istore #22
    //   2624: aload #20
    //   2626: iconst_0
    //   2627: iaload
    //   2628: iconst_2
    //   2629: iushr
    //   2630: aload #20
    //   2632: iconst_0
    //   2633: iaload
    //   2634: bipush #30
    //   2636: ishl
    //   2637: ior
    //   2638: aload #20
    //   2640: iconst_0
    //   2641: iaload
    //   2642: bipush #13
    //   2644: iushr
    //   2645: aload #20
    //   2647: iconst_0
    //   2648: iaload
    //   2649: bipush #19
    //   2651: ishl
    //   2652: ior
    //   2653: ixor
    //   2654: aload #20
    //   2656: iconst_0
    //   2657: iaload
    //   2658: bipush #22
    //   2660: iushr
    //   2661: aload #20
    //   2663: iconst_0
    //   2664: iaload
    //   2665: bipush #10
    //   2667: ishl
    //   2668: ior
    //   2669: ixor
    //   2670: aload #20
    //   2672: iconst_0
    //   2673: iaload
    //   2674: aload #20
    //   2676: iconst_1
    //   2677: iaload
    //   2678: iand
    //   2679: aload #20
    //   2681: iconst_2
    //   2682: iaload
    //   2683: aload #20
    //   2685: iconst_0
    //   2686: iaload
    //   2687: aload #20
    //   2689: iconst_1
    //   2690: iaload
    //   2691: ior
    //   2692: iand
    //   2693: ior
    //   2694: iadd
    //   2695: istore #23
    //   2697: aload #20
    //   2699: iconst_3
    //   2700: dup2
    //   2701: iaload
    //   2702: iload #22
    //   2704: iadd
    //   2705: iastore
    //   2706: aload #20
    //   2708: bipush #7
    //   2710: iload #22
    //   2712: iload #23
    //   2714: iadd
    //   2715: iastore
    //   2716: aload #20
    //   2718: bipush #7
    //   2720: iaload
    //   2721: istore #22
    //   2723: aload #20
    //   2725: bipush #7
    //   2727: aload #20
    //   2729: bipush #6
    //   2731: iaload
    //   2732: iastore
    //   2733: aload #20
    //   2735: bipush #6
    //   2737: aload #20
    //   2739: iconst_5
    //   2740: iaload
    //   2741: iastore
    //   2742: aload #20
    //   2744: iconst_5
    //   2745: aload #20
    //   2747: iconst_4
    //   2748: iaload
    //   2749: iastore
    //   2750: aload #20
    //   2752: iconst_4
    //   2753: aload #20
    //   2755: iconst_3
    //   2756: iaload
    //   2757: iastore
    //   2758: aload #20
    //   2760: iconst_3
    //   2761: aload #20
    //   2763: iconst_2
    //   2764: iaload
    //   2765: iastore
    //   2766: aload #20
    //   2768: iconst_2
    //   2769: aload #20
    //   2771: iconst_1
    //   2772: iaload
    //   2773: iastore
    //   2774: aload #20
    //   2776: iconst_1
    //   2777: aload #20
    //   2779: iconst_0
    //   2780: iaload
    //   2781: iastore
    //   2782: aload #20
    //   2784: iconst_0
    //   2785: iload #22
    //   2787: iastore
    //   2788: iinc #21, 1
    //   2791: iload_2
    //   2792: ifne -> 2300
    //   2795: iconst_0
    //   2796: istore #21
    //   2798: iload #21
    //   2800: bipush #8
    //   2802: if_icmpge -> 2825
    //   2805: aload #8
    //   2807: iload #21
    //   2809: dup2
    //   2810: iaload
    //   2811: aload #20
    //   2813: iload #21
    //   2815: iaload
    //   2816: iadd
    //   2817: iastore
    //   2818: iinc #21, 1
    //   2821: iload_2
    //   2822: ifne -> 2798
    //   2825: iload #13
    //   2827: iload #18
    //   2829: iadd
    //   2830: istore #13
    //   2832: iload #17
    //   2834: iload #18
    //   2836: isub
    //   2837: istore #17
    //   2839: iconst_0
    //   2840: istore #12
    //   2842: iload #17
    //   2844: bipush #64
    //   2846: if_icmplt -> 3456
    //   2849: iconst_0
    //   2850: istore #19
    //   2852: iload #19
    //   2854: bipush #64
    //   2856: if_icmpge -> 2879
    //   2859: aload #10
    //   2861: iload #19
    //   2863: aload #5
    //   2865: iload #13
    //   2867: iload #19
    //   2869: iadd
    //   2870: baload
    //   2871: bastore
    //   2872: iinc #19, 1
    //   2875: iload_2
    //   2876: ifne -> 2852
    //   2879: bipush #64
    //   2881: newarray int
    //   2883: astore #19
    //   2885: bipush #8
    //   2887: newarray int
    //   2889: astore #20
    //   2891: iconst_0
    //   2892: istore #21
    //   2894: iload #21
    //   2896: bipush #8
    //   2898: if_icmpge -> 2918
    //   2901: aload #20
    //   2903: iload #21
    //   2905: aload #8
    //   2907: iload #21
    //   2909: iaload
    //   2910: iastore
    //   2911: iinc #21, 1
    //   2914: iload_2
    //   2915: ifne -> 2894
    //   2918: iconst_0
    //   2919: istore #21
    //   2921: iload #21
    //   2923: bipush #64
    //   2925: if_icmpge -> 3416
    //   2928: iload #21
    //   2930: bipush #16
    //   2932: if_icmpge -> 3013
    //   2935: aload #19
    //   2937: iload #21
    //   2939: aload #10
    //   2941: iconst_4
    //   2942: iload #21
    //   2944: imul
    //   2945: baload
    //   2946: sipush #255
    //   2949: iand
    //   2950: bipush #24
    //   2952: ishl
    //   2953: aload #10
    //   2955: iconst_4
    //   2956: iload #21
    //   2958: imul
    //   2959: iconst_1
    //   2960: iadd
    //   2961: baload
    //   2962: sipush #255
    //   2965: iand
    //   2966: bipush #16
    //   2968: ishl
    //   2969: ior
    //   2970: aload #10
    //   2972: iconst_4
    //   2973: iload #21
    //   2975: imul
    //   2976: iconst_2
    //   2977: iadd
    //   2978: baload
    //   2979: sipush #255
    //   2982: iand
    //   2983: bipush #8
    //   2985: ishl
    //   2986: ior
    //   2987: aload #10
    //   2989: iconst_4
    //   2990: iload #21
    //   2992: imul
    //   2993: iconst_3
    //   2994: iadd
    //   2995: baload
    //   2996: sipush #255
    //   2999: iand
    //   3000: ior
    //   3001: iastore
    //   3002: iload_2
    //   3003: ifne -> 3156
    //   3006: goto -> 3013
    //   3009: invokestatic a : (Ljava/lang/Throwable;)Ljava/lang/Throwable;
    //   3012: athrow
    //   3013: aload #19
    //   3015: iload #21
    //   3017: aload #19
    //   3019: iload #21
    //   3021: iconst_2
    //   3022: isub
    //   3023: iaload
    //   3024: bipush #17
    //   3026: iushr
    //   3027: aload #19
    //   3029: iload #21
    //   3031: iconst_2
    //   3032: isub
    //   3033: iaload
    //   3034: bipush #15
    //   3036: ishl
    //   3037: ior
    //   3038: aload #19
    //   3040: iload #21
    //   3042: iconst_2
    //   3043: isub
    //   3044: iaload
    //   3045: bipush #19
    //   3047: iushr
    //   3048: aload #19
    //   3050: iload #21
    //   3052: iconst_2
    //   3053: isub
    //   3054: iaload
    //   3055: bipush #13
    //   3057: ishl
    //   3058: ior
    //   3059: ixor
    //   3060: aload #19
    //   3062: iload #21
    //   3064: iconst_2
    //   3065: isub
    //   3066: iaload
    //   3067: bipush #10
    //   3069: iushr
    //   3070: ixor
    //   3071: aload #19
    //   3073: iload #21
    //   3075: bipush #7
    //   3077: isub
    //   3078: iaload
    //   3079: iadd
    //   3080: aload #19
    //   3082: iload #21
    //   3084: bipush #15
    //   3086: isub
    //   3087: iaload
    //   3088: bipush #7
    //   3090: iushr
    //   3091: aload #19
    //   3093: iload #21
    //   3095: bipush #15
    //   3097: isub
    //   3098: iaload
    //   3099: bipush #25
    //   3101: ishl
    //   3102: ior
    //   3103: aload #19
    //   3105: iload #21
    //   3107: bipush #15
    //   3109: isub
    //   3110: iaload
    //   3111: bipush #18
    //   3113: iushr
    //   3114: aload #19
    //   3116: iload #21
    //   3118: bipush #15
    //   3120: isub
    //   3121: iaload
    //   3122: bipush #14
    //   3124: ishl
    //   3125: ior
    //   3126: ixor
    //   3127: aload #19
    //   3129: iload #21
    //   3131: bipush #15
    //   3133: isub
    //   3134: iaload
    //   3135: iconst_3
    //   3136: iushr
    //   3137: ixor
    //   3138: iadd
    //   3139: aload #19
    //   3141: iload #21
    //   3143: bipush #16
    //   3145: isub
    //   3146: iaload
    //   3147: iadd
    //   3148: iastore
    //   3149: goto -> 3156
    //   3152: invokestatic a : (Ljava/lang/Throwable;)Ljava/lang/Throwable;
    //   3155: athrow
    //   3156: aload #20
    //   3158: bipush #7
    //   3160: iaload
    //   3161: aload #20
    //   3163: iconst_4
    //   3164: iaload
    //   3165: bipush #6
    //   3167: iushr
    //   3168: aload #20
    //   3170: iconst_4
    //   3171: iaload
    //   3172: bipush #26
    //   3174: ishl
    //   3175: ior
    //   3176: aload #20
    //   3178: iconst_4
    //   3179: iaload
    //   3180: bipush #11
    //   3182: iushr
    //   3183: aload #20
    //   3185: iconst_4
    //   3186: iaload
    //   3187: bipush #21
    //   3189: ishl
    //   3190: ior
    //   3191: ixor
    //   3192: aload #20
    //   3194: iconst_4
    //   3195: iaload
    //   3196: bipush #25
    //   3198: iushr
    //   3199: aload #20
    //   3201: iconst_4
    //   3202: iaload
    //   3203: bipush #7
    //   3205: ishl
    //   3206: ior
    //   3207: ixor
    //   3208: iadd
    //   3209: aload #20
    //   3211: bipush #6
    //   3213: iaload
    //   3214: aload #20
    //   3216: iconst_4
    //   3217: iaload
    //   3218: aload #20
    //   3220: iconst_5
    //   3221: iaload
    //   3222: aload #20
    //   3224: bipush #6
    //   3226: iaload
    //   3227: ixor
    //   3228: iand
    //   3229: ixor
    //   3230: iadd
    //   3231: aload #6
    //   3233: iload #21
    //   3235: iaload
    //   3236: iadd
    //   3237: aload #19
    //   3239: iload #21
    //   3241: iaload
    //   3242: iadd
    //   3243: istore #22
    //   3245: aload #20
    //   3247: iconst_0
    //   3248: iaload
    //   3249: iconst_2
    //   3250: iushr
    //   3251: aload #20
    //   3253: iconst_0
    //   3254: iaload
    //   3255: bipush #30
    //   3257: ishl
    //   3258: ior
    //   3259: aload #20
    //   3261: iconst_0
    //   3262: iaload
    //   3263: bipush #13
    //   3265: iushr
    //   3266: aload #20
    //   3268: iconst_0
    //   3269: iaload
    //   3270: bipush #19
    //   3272: ishl
    //   3273: ior
    //   3274: ixor
    //   3275: aload #20
    //   3277: iconst_0
    //   3278: iaload
    //   3279: bipush #22
    //   3281: iushr
    //   3282: aload #20
    //   3284: iconst_0
    //   3285: iaload
    //   3286: bipush #10
    //   3288: ishl
    //   3289: ior
    //   3290: ixor
    //   3291: aload #20
    //   3293: iconst_0
    //   3294: iaload
    //   3295: aload #20
    //   3297: iconst_1
    //   3298: iaload
    //   3299: iand
    //   3300: aload #20
    //   3302: iconst_2
    //   3303: iaload
    //   3304: aload #20
    //   3306: iconst_0
    //   3307: iaload
    //   3308: aload #20
    //   3310: iconst_1
    //   3311: iaload
    //   3312: ior
    //   3313: iand
    //   3314: ior
    //   3315: iadd
    //   3316: istore #23
    //   3318: aload #20
    //   3320: iconst_3
    //   3321: dup2
    //   3322: iaload
    //   3323: iload #22
    //   3325: iadd
    //   3326: iastore
    //   3327: aload #20
    //   3329: bipush #7
    //   3331: iload #22
    //   3333: iload #23
    //   3335: iadd
    //   3336: iastore
    //   3337: aload #20
    //   3339: bipush #7
    //   3341: iaload
    //   3342: istore #22
    //   3344: aload #20
    //   3346: bipush #7
    //   3348: aload #20
    //   3350: bipush #6
    //   3352: iaload
    //   3353: iastore
    //   3354: aload #20
    //   3356: bipush #6
    //   3358: aload #20
    //   3360: iconst_5
    //   3361: iaload
    //   3362: iastore
    //   3363: aload #20
    //   3365: iconst_5
    //   3366: aload #20
    //   3368: iconst_4
    //   3369: iaload
    //   3370: iastore
    //   3371: aload #20
    //   3373: iconst_4
    //   3374: aload #20
    //   3376: iconst_3
    //   3377: iaload
    //   3378: iastore
    //   3379: aload #20
    //   3381: iconst_3
    //   3382: aload #20
    //   3384: iconst_2
    //   3385: iaload
    //   3386: iastore
    //   3387: aload #20
    //   3389: iconst_2
    //   3390: aload #20
    //   3392: iconst_1
    //   3393: iaload
    //   3394: iastore
    //   3395: aload #20
    //   3397: iconst_1
    //   3398: aload #20
    //   3400: iconst_0
    //   3401: iaload
    //   3402: iastore
    //   3403: aload #20
    //   3405: iconst_0
    //   3406: iload #22
    //   3408: iastore
    //   3409: iinc #21, 1
    //   3412: iload_2
    //   3413: ifne -> 2921
    //   3416: iconst_0
    //   3417: istore #21
    //   3419: iload #21
    //   3421: bipush #8
    //   3423: if_icmpge -> 3446
    //   3426: aload #8
    //   3428: iload #21
    //   3430: dup2
    //   3431: iaload
    //   3432: aload #20
    //   3434: iload #21
    //   3436: iaload
    //   3437: iadd
    //   3438: iastore
    //   3439: iinc #21, 1
    //   3442: iload_2
    //   3443: ifne -> 3419
    //   3446: iinc #13, 64
    //   3449: iinc #17, -64
    //   3452: iload_2
    //   3453: ifne -> 2842
    //   3456: iload #17
    //   3458: ifle -> 3494
    //   3461: iconst_0
    //   3462: istore #19
    //   3464: iload #19
    //   3466: iload #17
    //   3468: if_icmpge -> 3494
    //   3471: aload #9
    //   3473: iload #12
    //   3475: iload #19
    //   3477: iadd
    //   3478: aload #5
    //   3480: iload #13
    //   3482: iload #19
    //   3484: iadd
    //   3485: baload
    //   3486: bastore
    //   3487: iinc #19, 1
    //   3490: iload_2
    //   3491: ifne -> 3464
    //   3494: bipush #8
    //   3496: newarray byte
    //   3498: astore #19
    //   3500: aload #19
    //   3502: iconst_0
    //   3503: iload #14
    //   3505: bipush #24
    //   3507: iushr
    //   3508: i2b
    //   3509: bastore
    //   3510: aload #19
    //   3512: iconst_1
    //   3513: iload #14
    //   3515: bipush #16
    //   3517: iushr
    //   3518: i2b
    //   3519: bastore
    //   3520: aload #19
    //   3522: iconst_2
    //   3523: iload #14
    //   3525: bipush #8
    //   3527: iushr
    //   3528: i2b
    //   3529: bastore
    //   3530: aload #19
    //   3532: iconst_3
    //   3533: iload #14
    //   3535: i2b
    //   3536: bastore
    //   3537: aload #19
    //   3539: iconst_4
    //   3540: iload #15
    //   3542: bipush #24
    //   3544: iushr
    //   3545: i2b
    //   3546: bastore
    //   3547: aload #19
    //   3549: iconst_5
    //   3550: iload #15
    //   3552: bipush #16
    //   3554: iushr
    //   3555: i2b
    //   3556: bastore
    //   3557: aload #19
    //   3559: bipush #6
    //   3561: iload #15
    //   3563: bipush #8
    //   3565: iushr
    //   3566: i2b
    //   3567: bastore
    //   3568: aload #19
    //   3570: bipush #7
    //   3572: iload #15
    //   3574: i2b
    //   3575: bastore
    //   3576: bipush #8
    //   3578: istore #11
    //   3580: aload #7
    //   3582: iconst_0
    //   3583: iaload
    //   3584: bipush #63
    //   3586: iand
    //   3587: istore #12
    //   3589: bipush #64
    //   3591: iload #12
    //   3593: isub
    //   3594: istore #18
    //   3596: aload #7
    //   3598: iconst_0
    //   3599: dup2
    //   3600: iaload
    //   3601: iload #11
    //   3603: iadd
    //   3604: iastore
    //   3605: aload #7
    //   3607: iconst_0
    //   3608: dup2
    //   3609: iaload
    //   3610: iconst_m1
    //   3611: iand
    //   3612: iastore
    //   3613: aload #7
    //   3615: iconst_0
    //   3616: iaload
    //   3617: iload #11
    //   3619: if_icmpge -> 3637
    //   3622: aload #7
    //   3624: iconst_1
    //   3625: dup2
    //   3626: iaload
    //   3627: iconst_1
    //   3628: iadd
    //   3629: iastore
    //   3630: goto -> 3637
    //   3633: invokestatic a : (Ljava/lang/Throwable;)Ljava/lang/Throwable;
    //   3636: athrow
    //   3637: iload #12
    //   3639: ifle -> 4253
    //   3642: iload #11
    //   3644: iload #18
    //   3646: if_icmplt -> 4253
    //   3649: goto -> 3656
    //   3652: invokestatic a : (Ljava/lang/Throwable;)Ljava/lang/Throwable;
    //   3655: athrow
    //   3656: iconst_0
    //   3657: istore #20
    //   3659: iload #20
    //   3661: iload #18
    //   3663: if_icmpge -> 3686
    //   3666: aload #9
    //   3668: iload #12
    //   3670: iload #20
    //   3672: iadd
    //   3673: aload #19
    //   3675: iload #20
    //   3677: baload
    //   3678: bastore
    //   3679: iinc #20, 1
    //   3682: iload_2
    //   3683: ifne -> 3659
    //   3686: bipush #64
    //   3688: newarray int
    //   3690: astore #20
    //   3692: bipush #8
    //   3694: newarray int
    //   3696: astore #21
    //   3698: iconst_0
    //   3699: istore #22
    //   3701: iload #22
    //   3703: bipush #8
    //   3705: if_icmpge -> 3725
    //   3708: aload #21
    //   3710: iload #22
    //   3712: aload #8
    //   3714: iload #22
    //   3716: iaload
    //   3717: iastore
    //   3718: iinc #22, 1
    //   3721: iload_2
    //   3722: ifne -> 3701
    //   3725: iconst_0
    //   3726: istore #22
    //   3728: iload #22
    //   3730: bipush #64
    //   3732: if_icmpge -> 4223
    //   3735: iload #22
    //   3737: bipush #16
    //   3739: if_icmpge -> 3820
    //   3742: aload #20
    //   3744: iload #22
    //   3746: aload #9
    //   3748: iconst_4
    //   3749: iload #22
    //   3751: imul
    //   3752: baload
    //   3753: sipush #255
    //   3756: iand
    //   3757: bipush #24
    //   3759: ishl
    //   3760: aload #9
    //   3762: iconst_4
    //   3763: iload #22
    //   3765: imul
    //   3766: iconst_1
    //   3767: iadd
    //   3768: baload
    //   3769: sipush #255
    //   3772: iand
    //   3773: bipush #16
    //   3775: ishl
    //   3776: ior
    //   3777: aload #9
    //   3779: iconst_4
    //   3780: iload #22
    //   3782: imul
    //   3783: iconst_2
    //   3784: iadd
    //   3785: baload
    //   3786: sipush #255
    //   3789: iand
    //   3790: bipush #8
    //   3792: ishl
    //   3793: ior
    //   3794: aload #9
    //   3796: iconst_4
    //   3797: iload #22
    //   3799: imul
    //   3800: iconst_3
    //   3801: iadd
    //   3802: baload
    //   3803: sipush #255
    //   3806: iand
    //   3807: ior
    //   3808: iastore
    //   3809: iload_2
    //   3810: ifne -> 3963
    //   3813: goto -> 3820
    //   3816: invokestatic a : (Ljava/lang/Throwable;)Ljava/lang/Throwable;
    //   3819: athrow
    //   3820: aload #20
    //   3822: iload #22
    //   3824: aload #20
    //   3826: iload #22
    //   3828: iconst_2
    //   3829: isub
    //   3830: iaload
    //   3831: bipush #17
    //   3833: iushr
    //   3834: aload #20
    //   3836: iload #22
    //   3838: iconst_2
    //   3839: isub
    //   3840: iaload
    //   3841: bipush #15
    //   3843: ishl
    //   3844: ior
    //   3845: aload #20
    //   3847: iload #22
    //   3849: iconst_2
    //   3850: isub
    //   3851: iaload
    //   3852: bipush #19
    //   3854: iushr
    //   3855: aload #20
    //   3857: iload #22
    //   3859: iconst_2
    //   3860: isub
    //   3861: iaload
    //   3862: bipush #13
    //   3864: ishl
    //   3865: ior
    //   3866: ixor
    //   3867: aload #20
    //   3869: iload #22
    //   3871: iconst_2
    //   3872: isub
    //   3873: iaload
    //   3874: bipush #10
    //   3876: iushr
    //   3877: ixor
    //   3878: aload #20
    //   3880: iload #22
    //   3882: bipush #7
    //   3884: isub
    //   3885: iaload
    //   3886: iadd
    //   3887: aload #20
    //   3889: iload #22
    //   3891: bipush #15
    //   3893: isub
    //   3894: iaload
    //   3895: bipush #7
    //   3897: iushr
    //   3898: aload #20
    //   3900: iload #22
    //   3902: bipush #15
    //   3904: isub
    //   3905: iaload
    //   3906: bipush #25
    //   3908: ishl
    //   3909: ior
    //   3910: aload #20
    //   3912: iload #22
    //   3914: bipush #15
    //   3916: isub
    //   3917: iaload
    //   3918: bipush #18
    //   3920: iushr
    //   3921: aload #20
    //   3923: iload #22
    //   3925: bipush #15
    //   3927: isub
    //   3928: iaload
    //   3929: bipush #14
    //   3931: ishl
    //   3932: ior
    //   3933: ixor
    //   3934: aload #20
    //   3936: iload #22
    //   3938: bipush #15
    //   3940: isub
    //   3941: iaload
    //   3942: iconst_3
    //   3943: iushr
    //   3944: ixor
    //   3945: iadd
    //   3946: aload #20
    //   3948: iload #22
    //   3950: bipush #16
    //   3952: isub
    //   3953: iaload
    //   3954: iadd
    //   3955: iastore
    //   3956: goto -> 3963
    //   3959: invokestatic a : (Ljava/lang/Throwable;)Ljava/lang/Throwable;
    //   3962: athrow
    //   3963: aload #21
    //   3965: bipush #7
    //   3967: iaload
    //   3968: aload #21
    //   3970: iconst_4
    //   3971: iaload
    //   3972: bipush #6
    //   3974: iushr
    //   3975: aload #21
    //   3977: iconst_4
    //   3978: iaload
    //   3979: bipush #26
    //   3981: ishl
    //   3982: ior
    //   3983: aload #21
    //   3985: iconst_4
    //   3986: iaload
    //   3987: bipush #11
    //   3989: iushr
    //   3990: aload #21
    //   3992: iconst_4
    //   3993: iaload
    //   3994: bipush #21
    //   3996: ishl
    //   3997: ior
    //   3998: ixor
    //   3999: aload #21
    //   4001: iconst_4
    //   4002: iaload
    //   4003: bipush #25
    //   4005: iushr
    //   4006: aload #21
    //   4008: iconst_4
    //   4009: iaload
    //   4010: bipush #7
    //   4012: ishl
    //   4013: ior
    //   4014: ixor
    //   4015: iadd
    //   4016: aload #21
    //   4018: bipush #6
    //   4020: iaload
    //   4021: aload #21
    //   4023: iconst_4
    //   4024: iaload
    //   4025: aload #21
    //   4027: iconst_5
    //   4028: iaload
    //   4029: aload #21
    //   4031: bipush #6
    //   4033: iaload
    //   4034: ixor
    //   4035: iand
    //   4036: ixor
    //   4037: iadd
    //   4038: aload #6
    //   4040: iload #22
    //   4042: iaload
    //   4043: iadd
    //   4044: aload #20
    //   4046: iload #22
    //   4048: iaload
    //   4049: iadd
    //   4050: istore #23
    //   4052: aload #21
    //   4054: iconst_0
    //   4055: iaload
    //   4056: iconst_2
    //   4057: iushr
    //   4058: aload #21
    //   4060: iconst_0
    //   4061: iaload
    //   4062: bipush #30
    //   4064: ishl
    //   4065: ior
    //   4066: aload #21
    //   4068: iconst_0
    //   4069: iaload
    //   4070: bipush #13
    //   4072: iushr
    //   4073: aload #21
    //   4075: iconst_0
    //   4076: iaload
    //   4077: bipush #19
    //   4079: ishl
    //   4080: ior
    //   4081: ixor
    //   4082: aload #21
    //   4084: iconst_0
    //   4085: iaload
    //   4086: bipush #22
    //   4088: iushr
    //   4089: aload #21
    //   4091: iconst_0
    //   4092: iaload
    //   4093: bipush #10
    //   4095: ishl
    //   4096: ior
    //   4097: ixor
    //   4098: aload #21
    //   4100: iconst_0
    //   4101: iaload
    //   4102: aload #21
    //   4104: iconst_1
    //   4105: iaload
    //   4106: iand
    //   4107: aload #21
    //   4109: iconst_2
    //   4110: iaload
    //   4111: aload #21
    //   4113: iconst_0
    //   4114: iaload
    //   4115: aload #21
    //   4117: iconst_1
    //   4118: iaload
    //   4119: ior
    //   4120: iand
    //   4121: ior
    //   4122: iadd
    //   4123: istore #24
    //   4125: aload #21
    //   4127: iconst_3
    //   4128: dup2
    //   4129: iaload
    //   4130: iload #23
    //   4132: iadd
    //   4133: iastore
    //   4134: aload #21
    //   4136: bipush #7
    //   4138: iload #23
    //   4140: iload #24
    //   4142: iadd
    //   4143: iastore
    //   4144: aload #21
    //   4146: bipush #7
    //   4148: iaload
    //   4149: istore #23
    //   4151: aload #21
    //   4153: bipush #7
    //   4155: aload #21
    //   4157: bipush #6
    //   4159: iaload
    //   4160: iastore
    //   4161: aload #21
    //   4163: bipush #6
    //   4165: aload #21
    //   4167: iconst_5
    //   4168: iaload
    //   4169: iastore
    //   4170: aload #21
    //   4172: iconst_5
    //   4173: aload #21
    //   4175: iconst_4
    //   4176: iaload
    //   4177: iastore
    //   4178: aload #21
    //   4180: iconst_4
    //   4181: aload #21
    //   4183: iconst_3
    //   4184: iaload
    //   4185: iastore
    //   4186: aload #21
    //   4188: iconst_3
    //   4189: aload #21
    //   4191: iconst_2
    //   4192: iaload
    //   4193: iastore
    //   4194: aload #21
    //   4196: iconst_2
    //   4197: aload #21
    //   4199: iconst_1
    //   4200: iaload
    //   4201: iastore
    //   4202: aload #21
    //   4204: iconst_1
    //   4205: aload #21
    //   4207: iconst_0
    //   4208: iaload
    //   4209: iastore
    //   4210: aload #21
    //   4212: iconst_0
    //   4213: iload #23
    //   4215: iastore
    //   4216: iinc #22, 1
    //   4219: iload_2
    //   4220: ifne -> 3728
    //   4223: iconst_0
    //   4224: istore #22
    //   4226: iload #22
    //   4228: bipush #8
    //   4230: if_icmpge -> 4253
    //   4233: aload #8
    //   4235: iload #22
    //   4237: dup2
    //   4238: iaload
    //   4239: aload #21
    //   4241: iload #22
    //   4243: iaload
    //   4244: iadd
    //   4245: iastore
    //   4246: iinc #22, 1
    //   4249: iload_2
    //   4250: ifne -> 4226
    //   4253: bipush #32
    //   4255: newarray byte
    //   4257: astore #4
    //   4259: sipush #27833
    //   4262: aload #4
    //   4264: iconst_0
    //   4265: aload #8
    //   4267: iconst_0
    //   4268: iaload
    //   4269: bipush #24
    //   4271: iushr
    //   4272: i2b
    //   4273: bastore
    //   4274: sipush #15097
    //   4277: aload #4
    //   4279: iconst_1
    //   4280: aload #8
    //   4282: iconst_0
    //   4283: iaload
    //   4284: bipush #16
    //   4286: iushr
    //   4287: i2b
    //   4288: bastore
    //   4289: aload #4
    //   4291: iconst_2
    //   4292: aload #8
    //   4294: iconst_0
    //   4295: iaload
    //   4296: bipush #8
    //   4298: iushr
    //   4299: i2b
    //   4300: bastore
    //   4301: aload #4
    //   4303: iconst_3
    //   4304: aload #8
    //   4306: iconst_0
    //   4307: iaload
    //   4308: i2b
    //   4309: bastore
    //   4310: aload #4
    //   4312: iconst_4
    //   4313: aload #8
    //   4315: iconst_1
    //   4316: iaload
    //   4317: bipush #24
    //   4319: iushr
    //   4320: i2b
    //   4321: bastore
    //   4322: aload #4
    //   4324: iconst_5
    //   4325: aload #8
    //   4327: iconst_1
    //   4328: iaload
    //   4329: bipush #16
    //   4331: iushr
    //   4332: i2b
    //   4333: bastore
    //   4334: aload #4
    //   4336: bipush #6
    //   4338: aload #8
    //   4340: iconst_1
    //   4341: iaload
    //   4342: bipush #8
    //   4344: iushr
    //   4345: i2b
    //   4346: bastore
    //   4347: aload #4
    //   4349: bipush #7
    //   4351: aload #8
    //   4353: iconst_1
    //   4354: iaload
    //   4355: i2b
    //   4356: bastore
    //   4357: aload #4
    //   4359: bipush #8
    //   4361: aload #8
    //   4363: iconst_2
    //   4364: iaload
    //   4365: bipush #24
    //   4367: iushr
    //   4368: i2b
    //   4369: bastore
    //   4370: aload #4
    //   4372: bipush #9
    //   4374: aload #8
    //   4376: iconst_2
    //   4377: iaload
    //   4378: bipush #16
    //   4380: iushr
    //   4381: i2b
    //   4382: bastore
    //   4383: aload #4
    //   4385: bipush #10
    //   4387: aload #8
    //   4389: iconst_2
    //   4390: iaload
    //   4391: bipush #8
    //   4393: iushr
    //   4394: i2b
    //   4395: bastore
    //   4396: aload #4
    //   4398: bipush #11
    //   4400: aload #8
    //   4402: iconst_2
    //   4403: iaload
    //   4404: i2b
    //   4405: bastore
    //   4406: aload #4
    //   4408: bipush #12
    //   4410: aload #8
    //   4412: iconst_3
    //   4413: iaload
    //   4414: bipush #24
    //   4416: iushr
    //   4417: i2b
    //   4418: bastore
    //   4419: aload #4
    //   4421: bipush #13
    //   4423: aload #8
    //   4425: iconst_3
    //   4426: iaload
    //   4427: bipush #16
    //   4429: iushr
    //   4430: i2b
    //   4431: bastore
    //   4432: aload #4
    //   4434: bipush #14
    //   4436: aload #8
    //   4438: iconst_3
    //   4439: iaload
    //   4440: bipush #8
    //   4442: iushr
    //   4443: i2b
    //   4444: bastore
    //   4445: aload #4
    //   4447: bipush #15
    //   4449: aload #8
    //   4451: iconst_3
    //   4452: iaload
    //   4453: i2b
    //   4454: bastore
    //   4455: aload #4
    //   4457: bipush #16
    //   4459: aload #8
    //   4461: iconst_4
    //   4462: iaload
    //   4463: bipush #24
    //   4465: iushr
    //   4466: i2b
    //   4467: bastore
    //   4468: aload #4
    //   4470: bipush #17
    //   4472: aload #8
    //   4474: iconst_4
    //   4475: iaload
    //   4476: bipush #16
    //   4478: iushr
    //   4479: i2b
    //   4480: bastore
    //   4481: aload #4
    //   4483: bipush #18
    //   4485: aload #8
    //   4487: iconst_4
    //   4488: iaload
    //   4489: bipush #8
    //   4491: iushr
    //   4492: i2b
    //   4493: bastore
    //   4494: aload #4
    //   4496: bipush #19
    //   4498: aload #8
    //   4500: iconst_4
    //   4501: iaload
    //   4502: i2b
    //   4503: bastore
    //   4504: aload #4
    //   4506: bipush #20
    //   4508: aload #8
    //   4510: iconst_5
    //   4511: iaload
    //   4512: bipush #24
    //   4514: iushr
    //   4515: i2b
    //   4516: bastore
    //   4517: aload #4
    //   4519: bipush #21
    //   4521: aload #8
    //   4523: iconst_5
    //   4524: iaload
    //   4525: bipush #16
    //   4527: iushr
    //   4528: i2b
    //   4529: bastore
    //   4530: aload #4
    //   4532: bipush #22
    //   4534: aload #8
    //   4536: iconst_5
    //   4537: iaload
    //   4538: bipush #8
    //   4540: iushr
    //   4541: i2b
    //   4542: bastore
    //   4543: aload #4
    //   4545: bipush #23
    //   4547: aload #8
    //   4549: iconst_5
    //   4550: iaload
    //   4551: i2b
    //   4552: bastore
    //   4553: aload #4
    //   4555: bipush #24
    //   4557: aload #8
    //   4559: bipush #6
    //   4561: iaload
    //   4562: bipush #24
    //   4564: iushr
    //   4565: i2b
    //   4566: bastore
    //   4567: aload #4
    //   4569: bipush #25
    //   4571: aload #8
    //   4573: bipush #6
    //   4575: iaload
    //   4576: bipush #16
    //   4578: iushr
    //   4579: i2b
    //   4580: bastore
    //   4581: aload #4
    //   4583: bipush #26
    //   4585: aload #8
    //   4587: bipush #6
    //   4589: iaload
    //   4590: bipush #8
    //   4592: iushr
    //   4593: i2b
    //   4594: bastore
    //   4595: aload #4
    //   4597: bipush #27
    //   4599: aload #8
    //   4601: bipush #6
    //   4603: iaload
    //   4604: i2b
    //   4605: bastore
    //   4606: aload #4
    //   4608: bipush #28
    //   4610: aload #8
    //   4612: bipush #7
    //   4614: iaload
    //   4615: bipush #24
    //   4617: iushr
    //   4618: i2b
    //   4619: bastore
    //   4620: aload #4
    //   4622: bipush #29
    //   4624: aload #8
    //   4626: bipush #7
    //   4628: iaload
    //   4629: bipush #16
    //   4631: iushr
    //   4632: i2b
    //   4633: bastore
    //   4634: aload #4
    //   4636: bipush #30
    //   4638: aload #8
    //   4640: bipush #7
    //   4642: iaload
    //   4643: bipush #8
    //   4645: iushr
    //   4646: i2b
    //   4647: bastore
    //   4648: aload #4
    //   4650: bipush #31
    //   4652: aload #8
    //   4654: bipush #7
    //   4656: iaload
    //   4657: i2b
    //   4658: bastore
    //   4659: new java/math/BigInteger
    //   4662: dup
    //   4663: aload #4
    //   4665: invokespecial <init> : ([B)V
    //   4668: invokevirtual abs : ()Ljava/math/BigInteger;
    //   4671: putstatic burp/Ztwp.Ze : Ljava/lang/Object;
    //   4674: invokestatic a : (II)Ljava/lang/String;
    //   4677: iconst_1
    //   4678: ldc burp/Zrcy
    //   4680: invokevirtual getClassLoader : ()Ljava/lang/ClassLoader;
    //   4683: invokestatic forName : (Ljava/lang/String;ZLjava/lang/ClassLoader;)Ljava/lang/Class;
    //   4686: invokevirtual getDeclaredFields : ()[Ljava/lang/reflect/Field;
    //   4689: astore_3
    //   4690: aload_3
    //   4691: arraylength
    //   4692: istore #4
    //   4694: iconst_0
    //   4695: istore #5
    //   4697: iload #5
    //   4699: iload #4
    //   4701: if_icmpge -> 4838
    //   4704: aload_3
    //   4705: iload #5
    //   4707: aaload
    //   4708: astore #6
    //   4710: aload #6
    //   4712: invokevirtual getModifiers : ()I
    //   4715: invokestatic isStatic : (I)Z
    //   4718: ifne -> 4728
    //   4721: goto -> 4831
    //   4724: invokestatic a : (Ljava/lang/Throwable;)Ljava/lang/Throwable;
    //   4727: athrow
    //   4728: aload #6
    //   4730: invokevirtual getType : ()Ljava/lang/Class;
    //   4733: astore #7
    //   4735: aload #7
    //   4737: ifnull -> 4818
    //   4740: aload #7
    //   4742: invokevirtual isPrimitive : ()Z
    //   4745: ifne -> 4818
    //   4748: goto -> 4755
    //   4751: invokestatic a : (Ljava/lang/Throwable;)Ljava/lang/Throwable;
    //   4754: athrow
    //   4755: aload #7
    //   4757: invokevirtual getPackage : ()Ljava/lang/Package;
    //   4760: ifnull -> 4818
    //   4763: goto -> 4770
    //   4766: invokestatic a : (Ljava/lang/Throwable;)Ljava/lang/Throwable;
    //   4769: athrow
    //   4770: aload #7
    //   4772: invokevirtual getPackage : ()Ljava/lang/Package;
    //   4775: invokevirtual getName : ()Ljava/lang/String;
    //   4778: ifnull -> 4818
    //   4781: goto -> 4788
    //   4784: invokestatic a : (Ljava/lang/Throwable;)Ljava/lang/Throwable;
    //   4787: athrow
    //   4788: aload #7
    //   4790: invokevirtual getPackage : ()Ljava/lang/Package;
    //   4793: invokevirtual getName : ()Ljava/lang/String;
    //   4796: sipush #27838
    //   4799: sipush #-3561
    //   4802: invokestatic a : (II)Ljava/lang/String;
    //   4805: invokevirtual startsWith : (Ljava/lang/String;)Z
    //   4808: ifne -> 4818
    //   4811: goto -> 4818
    //   4814: invokestatic a : (Ljava/lang/Throwable;)Ljava/lang/Throwable;
    //   4817: athrow
    //   4818: aload #6
    //   4820: iconst_1
    //   4821: invokevirtual setAccessible : (Z)V
    //   4824: aload #6
    //   4826: aconst_null
    //   4827: invokevirtual get : (Ljava/lang/Object;)Ljava/lang/Object;
    //   4830: pop
    //   4831: iinc #5, 1
    //   4834: iload_2
    //   4835: ifne -> 4697
    //   4838: sipush #27831
    //   4841: sipush #-25136
    //   4844: invokestatic a : (II)Ljava/lang/String;
    //   4847: invokestatic forName : (Ljava/lang/String;)Ljava/lang/Class;
    //   4850: invokevirtual getDeclaredMethods : ()[Ljava/lang/reflect/Method;
    //   4853: astore_3
    //   4854: aload_3
    //   4855: arraylength
    //   4856: istore #4
    //   4858: iconst_0
    //   4859: istore #5
    //   4861: iload #5
    //   4863: iload #4
    //   4865: if_icmpge -> 4997
    //   4868: aload_3
    //   4869: iload #5
    //   4871: aaload
    //   4872: astore #6
    //   4874: aload #6
    //   4876: invokevirtual getParameterTypes : ()[Ljava/lang/Class;
    //   4879: pop
    //   4880: aload #6
    //   4882: invokevirtual getModifiers : ()I
    //   4885: invokestatic isStatic : (I)Z
    //   4888: ifeq -> 4983
    //   4891: aload #6
    //   4893: invokevirtual getParameterTypes : ()[Ljava/lang/Class;
    //   4896: arraylength
    //   4897: iconst_2
    //   4898: if_icmpne -> 4983
    //   4901: goto -> 4908
    //   4904: invokestatic a : (Ljava/lang/Throwable;)Ljava/lang/Throwable;
    //   4907: athrow
    //   4908: aload #6
    //   4910: invokevirtual getReturnType : ()Ljava/lang/Class;
    //   4913: getstatic java/lang/Void.TYPE : Ljava/lang/Class;
    //   4916: invokevirtual equals : (Ljava/lang/Object;)Z
    //   4919: ifeq -> 4983
    //   4922: goto -> 4929
    //   4925: invokestatic a : (Ljava/lang/Throwable;)Ljava/lang/Throwable;
    //   4928: athrow
    //   4929: aload #6
    //   4931: iconst_1
    //   4932: invokevirtual setAccessible : (Z)V
    //   4935: aload #6
    //   4937: aconst_null
    //   4938: iconst_2
    //   4939: anewarray java/lang/Object
    //   4942: dup
    //   4943: iconst_0
    //   4944: aload_0
    //   4945: aastore
    //   4946: dup
    //   4947: iconst_1
    //   4948: aload_1
    //   4949: ifnonnull -> 4967
    //   4952: goto -> 4959
    //   4955: invokestatic a : (Ljava/lang/Throwable;)Ljava/lang/Throwable;
    //   4958: athrow
    //   4959: aload_1
    //   4960: goto -> 4974
    //   4963: invokestatic a : (Ljava/lang/Throwable;)Ljava/lang/Throwable;
    //   4966: athrow
    //   4967: aload_1
    //   4968: checkcast [B
    //   4971: invokevirtual clone : ()Ljava/lang/Object;
    //   4974: aastore
    //   4975: invokevirtual invoke : (Ljava/lang/Object;[Ljava/lang/Object;)Ljava/lang/Object;
    //   4978: pop
    //   4979: iload_2
    //   4980: ifne -> 4997
    //   4983: iinc #5, 1
    //   4986: iload_2
    //   4987: ifne -> 4861
    //   4990: goto -> 4997
    //   4993: invokestatic a : (Ljava/lang/Throwable;)Ljava/lang/Throwable;
    //   4996: athrow
    //   4997: getstatic burp/Zrym.Zk : Ljava/lang/Object;
    //   5000: checkcast java/math/BigInteger
    //   5003: invokevirtual toByteArray : ()[B
    //   5006: astore_3
    //   5007: bipush #32
    //   5009: newarray int
    //   5011: dup
    //   5012: iconst_0
    //   5013: ldc 943331329
    //   5015: iastore
    //   5016: dup
    //   5017: iconst_1
    //   5018: ldc 170788368
    //   5020: iastore
    //   5021: dup
    //   5022: iconst_2
    //   5023: ldc 1008414755
    //   5025: iastore
    //   5026: dup
    //   5027: iconst_3
    //   5028: ldc 187049985
    //   5030: iastore
    //   5031: dup
    //   5032: iconst_4
    //   5033: ldc 1010368540
    //   5035: iastore
    //   5036: dup
    //   5037: iconst_5
    //   5038: ldc 220604441
    //   5040: iastore
    //   5041: dup
    //   5042: bipush #6
    //   5044: ldc 940377620
    //   5046: iastore
    //   5047: dup
    //   5048: bipush #7
    //   5050: ldc 255209728
    //   5052: iastore
    //   5053: dup
    //   5054: bipush #8
    //   5056: ldc 689771012
    //   5058: iastore
    //   5059: dup
    //   5060: bipush #9
    //   5062: ldc 221709344
    //   5064: iastore
    //   5065: dup
    //   5066: bipush #10
    //   5068: ldc 957157408
    //   5070: iastore
    //   5071: dup
    //   5072: bipush #11
    //   5074: ldc 892536332
    //   5076: iastore
    //   5077: dup
    //   5078: bipush #12
    //   5080: ldc 722417666
    //   5082: iastore
    //   5083: dup
    //   5084: bipush #13
    //   5086: ldc 1026621720
    //   5088: iastore
    //   5089: dup
    //   5090: bipush #14
    //   5092: ldc 655302664
    //   5094: iastore
    //   5095: dup
    //   5096: bipush #15
    //   5098: ldc 890966315
    //   5100: iastore
    //   5101: dup
    //   5102: bipush #16
    //   5104: ldc 187632156
    //   5106: iastore
    //   5107: dup
    //   5108: bipush #17
    //   5110: ldc 874189824
    //   5112: iastore
    //   5113: dup
    //   5114: bipush #18
    //   5116: ldc 254150144
    //   5118: iastore
    //   5119: dup
    //   5120: bipush #19
    //   5122: ldc 924386310
    //   5124: iastore
    //   5125: dup
    //   5126: bipush #20
    //   5128: ldc 121057538
    //   5130: iastore
    //   5131: dup
    //   5132: bipush #21
    //   5134: ldc 840500228
    //   5136: iastore
    //   5137: dup
    //   5138: bipush #22
    //   5140: ldc 389160971
    //   5142: iastore
    //   5143: dup
    //   5144: bipush #23
    //   5146: ldc 907870729
    //   5148: iastore
    //   5149: dup
    //   5150: bipush #24
    //   5152: ldc 389426184
    //   5154: iastore
    //   5155: dup
    //   5156: bipush #25
    //   5158: ldc 973875457
    //   5160: iastore
    //   5161: dup
    //   5162: bipush #26
    //   5164: ldc 372376604
    //   5166: iastore
    //   5167: dup
    //   5168: bipush #27
    //   5170: ldc 707731490
    //   5172: iastore
    //   5173: dup
    //   5174: bipush #28
    //   5176: ldc 1043334948
    //   5178: iastore
    //   5179: dup
    //   5180: bipush #29
    //   5182: ldc 439222784
    //   5184: iastore
    //   5185: dup
    //   5186: bipush #30
    //   5188: ldc 876216579
    //   5190: iastore
    //   5191: dup
    //   5192: bipush #31
    //   5194: ldc 455999525
    //   5196: iastore
    //   5197: astore #5
    //   5199: bipush #8
    //   5201: aload_3
    //   5202: arraylength
    //   5203: bipush #8
    //   5205: irem
    //   5206: isub
    //   5207: istore #6
    //   5209: aload_3
    //   5210: arraylength
    //   5211: iload #6
    //   5213: iadd
    //   5214: newarray byte
    //   5216: astore #7
    //   5218: iconst_0
    //   5219: istore #8
    //   5221: iload #8
    //   5223: aload_3
    //   5224: arraylength
    //   5225: if_icmpge -> 5244
    //   5228: aload #7
    //   5230: iload #8
    //   5232: aload_3
    //   5233: iload #8
    //   5235: baload
    //   5236: bastore
    //   5237: iinc #8, 1
    //   5240: iload_2
    //   5241: ifne -> 5221
    //   5244: aload_3
    //   5245: arraylength
    //   5246: istore #8
    //   5248: iload #8
    //   5250: aload #7
    //   5252: arraylength
    //   5253: if_icmpge -> 5271
    //   5256: aload #7
    //   5258: iload #8
    //   5260: iload #6
    //   5262: i2b
    //   5263: bastore
    //   5264: iinc #8, 1
    //   5267: iload_2
    //   5268: ifne -> 5248
    //   5271: aload #7
    //   5273: astore_3
    //   5274: bipush #64
    //   5276: newarray int
    //   5278: dup
    //   5279: iconst_0
    //   5280: ldc 16843776
    //   5282: iastore
    //   5283: dup
    //   5284: iconst_1
    //   5285: iconst_0
    //   5286: iastore
    //   5287: dup
    //   5288: iconst_2
    //   5289: ldc 65536
    //   5291: iastore
    //   5292: dup
    //   5293: iconst_3
    //   5294: ldc 16843780
    //   5296: iastore
    //   5297: dup
    //   5298: iconst_4
    //   5299: ldc 16842756
    //   5301: iastore
    //   5302: dup
    //   5303: iconst_5
    //   5304: ldc 66564
    //   5306: iastore
    //   5307: dup
    //   5308: bipush #6
    //   5310: iconst_4
    //   5311: iastore
    //   5312: dup
    //   5313: bipush #7
    //   5315: ldc 65536
    //   5317: iastore
    //   5318: dup
    //   5319: bipush #8
    //   5321: sipush #1024
    //   5324: iastore
    //   5325: dup
    //   5326: bipush #9
    //   5328: ldc 16843776
    //   5330: iastore
    //   5331: dup
    //   5332: bipush #10
    //   5334: ldc 16843780
    //   5336: iastore
    //   5337: dup
    //   5338: bipush #11
    //   5340: sipush #1024
    //   5343: iastore
    //   5344: dup
    //   5345: bipush #12
    //   5347: ldc 16778244
    //   5349: iastore
    //   5350: dup
    //   5351: bipush #13
    //   5353: ldc 16842756
    //   5355: iastore
    //   5356: dup
    //   5357: bipush #14
    //   5359: ldc 16777216
    //   5361: iastore
    //   5362: dup
    //   5363: bipush #15
    //   5365: iconst_4
    //   5366: iastore
    //   5367: dup
    //   5368: bipush #16
    //   5370: sipush #1028
    //   5373: iastore
    //   5374: dup
    //   5375: bipush #17
    //   5377: ldc 16778240
    //   5379: iastore
    //   5380: dup
    //   5381: bipush #18
    //   5383: ldc 16778240
    //   5385: iastore
    //   5386: dup
    //   5387: bipush #19
    //   5389: ldc 66560
    //   5391: iastore
    //   5392: dup
    //   5393: bipush #20
    //   5395: ldc 66560
    //   5397: iastore
    //   5398: dup
    //   5399: bipush #21
    //   5401: ldc 16842752
    //   5403: iastore
    //   5404: dup
    //   5405: bipush #22
    //   5407: ldc 16842752
    //   5409: iastore
    //   5410: dup
    //   5411: bipush #23
    //   5413: ldc 16778244
    //   5415: iastore
    //   5416: dup
    //   5417: bipush #24
    //   5419: ldc 65540
    //   5421: iastore
    //   5422: dup
    //   5423: bipush #25
    //   5425: ldc 16777220
    //   5427: iastore
    //   5428: dup
    //   5429: bipush #26
    //   5431: ldc 16777220
    //   5433: iastore
    //   5434: dup
    //   5435: bipush #27
    //   5437: ldc 65540
    //   5439: iastore
    //   5440: dup
    //   5441: bipush #28
    //   5443: iconst_0
    //   5444: iastore
    //   5445: dup
    //   5446: bipush #29
    //   5448: sipush #1028
    //   5451: iastore
    //   5452: dup
    //   5453: bipush #30
    //   5455: ldc 66564
    //   5457: iastore
    //   5458: dup
    //   5459: bipush #31
    //   5461: ldc 16777216
    //   5463: iastore
    //   5464: dup
    //   5465: bipush #32
    //   5467: ldc 65536
    //   5469: iastore
    //   5470: dup
    //   5471: bipush #33
    //   5473: ldc 16843780
    //   5475: iastore
    //   5476: dup
    //   5477: bipush #34
    //   5479: iconst_4
    //   5480: iastore
    //   5481: dup
    //   5482: bipush #35
    //   5484: ldc 16842752
    //   5486: iastore
    //   5487: dup
    //   5488: bipush #36
    //   5490: ldc 16843776
    //   5492: iastore
    //   5493: dup
    //   5494: bipush #37
    //   5496: ldc 16777216
    //   5498: iastore
    //   5499: dup
    //   5500: bipush #38
    //   5502: ldc 16777216
    //   5504: iastore
    //   5505: dup
    //   5506: bipush #39
    //   5508: sipush #1024
    //   5511: iastore
    //   5512: dup
    //   5513: bipush #40
    //   5515: ldc 16842756
    //   5517: iastore
    //   5518: dup
    //   5519: bipush #41
    //   5521: ldc 65536
    //   5523: iastore
    //   5524: dup
    //   5525: bipush #42
    //   5527: ldc 66560
    //   5529: iastore
    //   5530: dup
    //   5531: bipush #43
    //   5533: ldc 16777220
    //   5535: iastore
    //   5536: dup
    //   5537: bipush #44
    //   5539: sipush #1024
    //   5542: iastore
    //   5543: dup
    //   5544: bipush #45
    //   5546: iconst_4
    //   5547: iastore
    //   5548: dup
    //   5549: bipush #46
    //   5551: ldc 16778244
    //   5553: iastore
    //   5554: dup
    //   5555: bipush #47
    //   5557: ldc 66564
    //   5559: iastore
    //   5560: dup
    //   5561: bipush #48
    //   5563: ldc 16843780
    //   5565: iastore
    //   5566: dup
    //   5567: bipush #49
    //   5569: ldc 65540
    //   5571: iastore
    //   5572: dup
    //   5573: bipush #50
    //   5575: ldc 16842752
    //   5577: iastore
    //   5578: dup
    //   5579: bipush #51
    //   5581: ldc 16778244
    //   5583: iastore
    //   5584: dup
    //   5585: bipush #52
    //   5587: ldc 16777220
    //   5589: iastore
    //   5590: dup
    //   5591: bipush #53
    //   5593: sipush #1028
    //   5596: iastore
    //   5597: dup
    //   5598: bipush #54
    //   5600: ldc 66564
    //   5602: iastore
    //   5603: dup
    //   5604: bipush #55
    //   5606: ldc 16843776
    //   5608: iastore
    //   5609: dup
    //   5610: bipush #56
    //   5612: sipush #1028
    //   5615: iastore
    //   5616: dup
    //   5617: bipush #57
    //   5619: ldc 16778240
    //   5621: iastore
    //   5622: dup
    //   5623: bipush #58
    //   5625: ldc 16778240
    //   5627: iastore
    //   5628: dup
    //   5629: bipush #59
    //   5631: iconst_0
    //   5632: iastore
    //   5633: dup
    //   5634: bipush #60
    //   5636: ldc 65540
    //   5638: iastore
    //   5639: dup
    //   5640: bipush #61
    //   5642: ldc 66560
    //   5644: iastore
    //   5645: dup
    //   5646: bipush #62
    //   5648: iconst_0
    //   5649: iastore
    //   5650: dup
    //   5651: bipush #63
    //   5653: ldc 16842756
    //   5655: iastore
    //   5656: astore #8
    //   5658: bipush #64
    //   5660: newarray int
    //   5662: dup
    //   5663: iconst_0
    //   5664: ldc -2146402272
    //   5666: iastore
    //   5667: dup
    //   5668: iconst_1
    //   5669: ldc -2147450880
    //   5671: iastore
    //   5672: dup
    //   5673: iconst_2
    //   5674: ldc 32768
    //   5676: iastore
    //   5677: dup
    //   5678: iconst_3
    //   5679: ldc 1081376
    //   5681: iastore
    //   5682: dup
    //   5683: iconst_4
    //   5684: ldc 1048576
    //   5686: iastore
    //   5687: dup
    //   5688: iconst_5
    //   5689: bipush #32
    //   5691: iastore
    //   5692: dup
    //   5693: bipush #6
    //   5695: ldc -2146435040
    //   5697: iastore
    //   5698: dup
    //   5699: bipush #7
    //   5701: ldc -2147450848
    //   5703: iastore
    //   5704: dup
    //   5705: bipush #8
    //   5707: ldc -2147483616
    //   5709: iastore
    //   5710: dup
    //   5711: bipush #9
    //   5713: ldc -2146402272
    //   5715: iastore
    //   5716: dup
    //   5717: bipush #10
    //   5719: ldc -2146402304
    //   5721: iastore
    //   5722: dup
    //   5723: bipush #11
    //   5725: ldc -2147483648
    //   5727: iastore
    //   5728: dup
    //   5729: bipush #12
    //   5731: ldc -2147450880
    //   5733: iastore
    //   5734: dup
    //   5735: bipush #13
    //   5737: ldc 1048576
    //   5739: iastore
    //   5740: dup
    //   5741: bipush #14
    //   5743: bipush #32
    //   5745: iastore
    //   5746: dup
    //   5747: bipush #15
    //   5749: ldc -2146435040
    //   5751: iastore
    //   5752: dup
    //   5753: bipush #16
    //   5755: ldc 1081344
    //   5757: iastore
    //   5758: dup
    //   5759: bipush #17
    //   5761: ldc 1048608
    //   5763: iastore
    //   5764: dup
    //   5765: bipush #18
    //   5767: ldc -2147450848
    //   5769: iastore
    //   5770: dup
    //   5771: bipush #19
    //   5773: iconst_0
    //   5774: iastore
    //   5775: dup
    //   5776: bipush #20
    //   5778: ldc -2147483648
    //   5780: iastore
    //   5781: dup
    //   5782: bipush #21
    //   5784: ldc 32768
    //   5786: iastore
    //   5787: dup
    //   5788: bipush #22
    //   5790: ldc 1081376
    //   5792: iastore
    //   5793: dup
    //   5794: bipush #23
    //   5796: ldc -2146435072
    //   5798: iastore
    //   5799: dup
    //   5800: bipush #24
    //   5802: ldc 1048608
    //   5804: iastore
    //   5805: dup
    //   5806: bipush #25
    //   5808: ldc -2147483616
    //   5810: iastore
    //   5811: dup
    //   5812: bipush #26
    //   5814: iconst_0
    //   5815: iastore
    //   5816: dup
    //   5817: bipush #27
    //   5819: ldc 1081344
    //   5821: iastore
    //   5822: dup
    //   5823: bipush #28
    //   5825: ldc 32800
    //   5827: iastore
    //   5828: dup
    //   5829: bipush #29
    //   5831: ldc -2146402304
    //   5833: iastore
    //   5834: dup
    //   5835: bipush #30
    //   5837: ldc -2146435072
    //   5839: iastore
    //   5840: dup
    //   5841: bipush #31
    //   5843: ldc 32800
    //   5845: iastore
    //   5846: dup
    //   5847: bipush #32
    //   5849: iconst_0
    //   5850: iastore
    //   5851: dup
    //   5852: bipush #33
    //   5854: ldc 1081376
    //   5856: iastore
    //   5857: dup
    //   5858: bipush #34
    //   5860: ldc -2146435040
    //   5862: iastore
    //   5863: dup
    //   5864: bipush #35
    //   5866: ldc 1048576
    //   5868: iastore
    //   5869: dup
    //   5870: bipush #36
    //   5872: ldc -2147450848
    //   5874: iastore
    //   5875: dup
    //   5876: bipush #37
    //   5878: ldc -2146435072
    //   5880: iastore
    //   5881: dup
    //   5882: bipush #38
    //   5884: ldc -2146402304
    //   5886: iastore
    //   5887: dup
    //   5888: bipush #39
    //   5890: ldc 32768
    //   5892: iastore
    //   5893: dup
    //   5894: bipush #40
    //   5896: ldc -2146435072
    //   5898: iastore
    //   5899: dup
    //   5900: bipush #41
    //   5902: ldc -2147450880
    //   5904: iastore
    //   5905: dup
    //   5906: bipush #42
    //   5908: bipush #32
    //   5910: iastore
    //   5911: dup
    //   5912: bipush #43
    //   5914: ldc -2146402272
    //   5916: iastore
    //   5917: dup
    //   5918: bipush #44
    //   5920: ldc 1081376
    //   5922: iastore
    //   5923: dup
    //   5924: bipush #45
    //   5926: bipush #32
    //   5928: iastore
    //   5929: dup
    //   5930: bipush #46
    //   5932: ldc 32768
    //   5934: iastore
    //   5935: dup
    //   5936: bipush #47
    //   5938: ldc -2147483648
    //   5940: iastore
    //   5941: dup
    //   5942: bipush #48
    //   5944: ldc 32800
    //   5946: iastore
    //   5947: dup
    //   5948: bipush #49
    //   5950: ldc -2146402304
    //   5952: iastore
    //   5953: dup
    //   5954: bipush #50
    //   5956: ldc 1048576
    //   5958: iastore
    //   5959: dup
    //   5960: bipush #51
    //   5962: ldc -2147483616
    //   5964: iastore
    //   5965: dup
    //   5966: bipush #52
    //   5968: ldc 1048608
    //   5970: iastore
    //   5971: dup
    //   5972: bipush #53
    //   5974: ldc -2147450848
    //   5976: iastore
    //   5977: dup
    //   5978: bipush #54
    //   5980: ldc -2147483616
    //   5982: iastore
    //   5983: dup
    //   5984: bipush #55
    //   5986: ldc 1048608
    //   5988: iastore
    //   5989: dup
    //   5990: bipush #56
    //   5992: ldc 1081344
    //   5994: iastore
    //   5995: dup
    //   5996: bipush #57
    //   5998: iconst_0
    //   5999: iastore
    //   6000: dup
    //   6001: bipush #58
    //   6003: ldc -2147450880
    //   6005: iastore
    //   6006: dup
    //   6007: bipush #59
    //   6009: ldc 32800
    //   6011: iastore
    //   6012: dup
    //   6013: bipush #60
    //   6015: ldc -2147483648
    //   6017: iastore
    //   6018: dup
    //   6019: bipush #61
    //   6021: ldc -2146435040
    //   6023: iastore
    //   6024: dup
    //   6025: bipush #62
    //   6027: ldc -2146402272
    //   6029: iastore
    //   6030: dup
    //   6031: bipush #63
    //   6033: ldc 1081344
    //   6035: iastore
    //   6036: astore #9
    //   6038: bipush #64
    //   6040: newarray int
    //   6042: dup
    //   6043: iconst_0
    //   6044: sipush #520
    //   6047: iastore
    //   6048: dup
    //   6049: iconst_1
    //   6050: ldc 134349312
    //   6052: iastore
    //   6053: dup
    //   6054: iconst_2
    //   6055: iconst_0
    //   6056: iastore
    //   6057: dup
    //   6058: iconst_3
    //   6059: ldc 134348808
    //   6061: iastore
    //   6062: dup
    //   6063: iconst_4
    //   6064: ldc 134218240
    //   6066: iastore
    //   6067: dup
    //   6068: iconst_5
    //   6069: iconst_0
    //   6070: iastore
    //   6071: dup
    //   6072: bipush #6
    //   6074: ldc 131592
    //   6076: iastore
    //   6077: dup
    //   6078: bipush #7
    //   6080: ldc 134218240
    //   6082: iastore
    //   6083: dup
    //   6084: bipush #8
    //   6086: ldc 131080
    //   6088: iastore
    //   6089: dup
    //   6090: bipush #9
    //   6092: ldc 134217736
    //   6094: iastore
    //   6095: dup
    //   6096: bipush #10
    //   6098: ldc 134217736
    //   6100: iastore
    //   6101: dup
    //   6102: bipush #11
    //   6104: ldc 131072
    //   6106: iastore
    //   6107: dup
    //   6108: bipush #12
    //   6110: ldc 134349320
    //   6112: iastore
    //   6113: dup
    //   6114: bipush #13
    //   6116: ldc 131080
    //   6118: iastore
    //   6119: dup
    //   6120: bipush #14
    //   6122: ldc 134348800
    //   6124: iastore
    //   6125: dup
    //   6126: bipush #15
    //   6128: sipush #520
    //   6131: iastore
    //   6132: dup
    //   6133: bipush #16
    //   6135: ldc 134217728
    //   6137: iastore
    //   6138: dup
    //   6139: bipush #17
    //   6141: bipush #8
    //   6143: iastore
    //   6144: dup
    //   6145: bipush #18
    //   6147: ldc 134349312
    //   6149: iastore
    //   6150: dup
    //   6151: bipush #19
    //   6153: sipush #512
    //   6156: iastore
    //   6157: dup
    //   6158: bipush #20
    //   6160: ldc 131584
    //   6162: iastore
    //   6163: dup
    //   6164: bipush #21
    //   6166: ldc 134348800
    //   6168: iastore
    //   6169: dup
    //   6170: bipush #22
    //   6172: ldc 134348808
    //   6174: iastore
    //   6175: dup
    //   6176: bipush #23
    //   6178: ldc 131592
    //   6180: iastore
    //   6181: dup
    //   6182: bipush #24
    //   6184: ldc 134218248
    //   6186: iastore
    //   6187: dup
    //   6188: bipush #25
    //   6190: ldc 131584
    //   6192: iastore
    //   6193: dup
    //   6194: bipush #26
    //   6196: ldc 131072
    //   6198: iastore
    //   6199: dup
    //   6200: bipush #27
    //   6202: ldc 134218248
    //   6204: iastore
    //   6205: dup
    //   6206: bipush #28
    //   6208: bipush #8
    //   6210: iastore
    //   6211: dup
    //   6212: bipush #29
    //   6214: ldc 134349320
    //   6216: iastore
    //   6217: dup
    //   6218: bipush #30
    //   6220: sipush #512
    //   6223: iastore
    //   6224: dup
    //   6225: bipush #31
    //   6227: ldc 134217728
    //   6229: iastore
    //   6230: dup
    //   6231: bipush #32
    //   6233: ldc 134349312
    //   6235: iastore
    //   6236: dup
    //   6237: bipush #33
    //   6239: ldc 134217728
    //   6241: iastore
    //   6242: dup
    //   6243: bipush #34
    //   6245: ldc 131080
    //   6247: iastore
    //   6248: dup
    //   6249: bipush #35
    //   6251: sipush #520
    //   6254: iastore
    //   6255: dup
    //   6256: bipush #36
    //   6258: ldc 131072
    //   6260: iastore
    //   6261: dup
    //   6262: bipush #37
    //   6264: ldc 134349312
    //   6266: iastore
    //   6267: dup
    //   6268: bipush #38
    //   6270: ldc 134218240
    //   6272: iastore
    //   6273: dup
    //   6274: bipush #39
    //   6276: iconst_0
    //   6277: iastore
    //   6278: dup
    //   6279: bipush #40
    //   6281: sipush #512
    //   6284: iastore
    //   6285: dup
    //   6286: bipush #41
    //   6288: ldc 131080
    //   6290: iastore
    //   6291: dup
    //   6292: bipush #42
    //   6294: ldc 134349320
    //   6296: iastore
    //   6297: dup
    //   6298: bipush #43
    //   6300: ldc 134218240
    //   6302: iastore
    //   6303: dup
    //   6304: bipush #44
    //   6306: ldc 134217736
    //   6308: iastore
    //   6309: dup
    //   6310: bipush #45
    //   6312: sipush #512
    //   6315: iastore
    //   6316: dup
    //   6317: bipush #46
    //   6319: iconst_0
    //   6320: iastore
    //   6321: dup
    //   6322: bipush #47
    //   6324: ldc 134348808
    //   6326: iastore
    //   6327: dup
    //   6328: bipush #48
    //   6330: ldc 134218248
    //   6332: iastore
    //   6333: dup
    //   6334: bipush #49
    //   6336: ldc 131072
    //   6338: iastore
    //   6339: dup
    //   6340: bipush #50
    //   6342: ldc 134217728
    //   6344: iastore
    //   6345: dup
    //   6346: bipush #51
    //   6348: ldc 134349320
    //   6350: iastore
    //   6351: dup
    //   6352: bipush #52
    //   6354: bipush #8
    //   6356: iastore
    //   6357: dup
    //   6358: bipush #53
    //   6360: ldc 131592
    //   6362: iastore
    //   6363: dup
    //   6364: bipush #54
    //   6366: ldc 131584
    //   6368: iastore
    //   6369: dup
    //   6370: bipush #55
    //   6372: ldc 134217736
    //   6374: iastore
    //   6375: dup
    //   6376: bipush #56
    //   6378: ldc 134348800
    //   6380: iastore
    //   6381: dup
    //   6382: bipush #57
    //   6384: ldc 134218248
    //   6386: iastore
    //   6387: dup
    //   6388: bipush #58
    //   6390: sipush #520
    //   6393: iastore
    //   6394: dup
    //   6395: bipush #59
    //   6397: ldc 134348800
    //   6399: iastore
    //   6400: dup
    //   6401: bipush #60
    //   6403: ldc 131592
    //   6405: iastore
    //   6406: dup
    //   6407: bipush #61
    //   6409: bipush #8
    //   6411: iastore
    //   6412: dup
    //   6413: bipush #62
    //   6415: ldc 134348808
    //   6417: iastore
    //   6418: dup
    //   6419: bipush #63
    //   6421: ldc 131584
    //   6423: iastore
    //   6424: astore #10
    //   6426: bipush #64
    //   6428: newarray int
    //   6430: dup
    //   6431: iconst_0
    //   6432: ldc 8396801
    //   6434: iastore
    //   6435: dup
    //   6436: iconst_1
    //   6437: sipush #8321
    //   6440: iastore
    //   6441: dup
    //   6442: iconst_2
    //   6443: sipush #8321
    //   6446: iastore
    //   6447: dup
    //   6448: iconst_3
    //   6449: sipush #128
    //   6452: iastore
    //   6453: dup
    //   6454: iconst_4
    //   6455: ldc 8396928
    //   6457: iastore
    //   6458: dup
    //   6459: iconst_5
    //   6460: ldc 8388737
    //   6462: iastore
    //   6463: dup
    //   6464: bipush #6
    //   6466: ldc 8388609
    //   6468: iastore
    //   6469: dup
    //   6470: bipush #7
    //   6472: sipush #8193
    //   6475: iastore
    //   6476: dup
    //   6477: bipush #8
    //   6479: iconst_0
    //   6480: iastore
    //   6481: dup
    //   6482: bipush #9
    //   6484: ldc 8396800
    //   6486: iastore
    //   6487: dup
    //   6488: bipush #10
    //   6490: ldc 8396800
    //   6492: iastore
    //   6493: dup
    //   6494: bipush #11
    //   6496: ldc 8396929
    //   6498: iastore
    //   6499: dup
    //   6500: bipush #12
    //   6502: sipush #129
    //   6505: iastore
    //   6506: dup
    //   6507: bipush #13
    //   6509: iconst_0
    //   6510: iastore
    //   6511: dup
    //   6512: bipush #14
    //   6514: ldc 8388736
    //   6516: iastore
    //   6517: dup
    //   6518: bipush #15
    //   6520: ldc 8388609
    //   6522: iastore
    //   6523: dup
    //   6524: bipush #16
    //   6526: iconst_1
    //   6527: iastore
    //   6528: dup
    //   6529: bipush #17
    //   6531: sipush #8192
    //   6534: iastore
    //   6535: dup
    //   6536: bipush #18
    //   6538: ldc 8388608
    //   6540: iastore
    //   6541: dup
    //   6542: bipush #19
    //   6544: ldc 8396801
    //   6546: iastore
    //   6547: dup
    //   6548: bipush #20
    //   6550: sipush #128
    //   6553: iastore
    //   6554: dup
    //   6555: bipush #21
    //   6557: ldc 8388608
    //   6559: iastore
    //   6560: dup
    //   6561: bipush #22
    //   6563: sipush #8193
    //   6566: iastore
    //   6567: dup
    //   6568: bipush #23
    //   6570: sipush #8320
    //   6573: iastore
    //   6574: dup
    //   6575: bipush #24
    //   6577: ldc 8388737
    //   6579: iastore
    //   6580: dup
    //   6581: bipush #25
    //   6583: iconst_1
    //   6584: iastore
    //   6585: dup
    //   6586: bipush #26
    //   6588: sipush #8320
    //   6591: iastore
    //   6592: dup
    //   6593: bipush #27
    //   6595: ldc 8388736
    //   6597: iastore
    //   6598: dup
    //   6599: bipush #28
    //   6601: sipush #8192
    //   6604: iastore
    //   6605: dup
    //   6606: bipush #29
    //   6608: ldc 8396928
    //   6610: iastore
    //   6611: dup
    //   6612: bipush #30
    //   6614: ldc 8396929
    //   6616: iastore
    //   6617: dup
    //   6618: bipush #31
    //   6620: sipush #129
    //   6623: iastore
    //   6624: dup
    //   6625: bipush #32
    //   6627: ldc 8388736
    //   6629: iastore
    //   6630: dup
    //   6631: bipush #33
    //   6633: ldc 8388609
    //   6635: iastore
    //   6636: dup
    //   6637: bipush #34
    //   6639: ldc 8396800
    //   6641: iastore
    //   6642: dup
    //   6643: bipush #35
    //   6645: ldc 8396929
    //   6647: iastore
    //   6648: dup
    //   6649: bipush #36
    //   6651: sipush #129
    //   6654: iastore
    //   6655: dup
    //   6656: bipush #37
    //   6658: iconst_0
    //   6659: iastore
    //   6660: dup
    //   6661: bipush #38
    //   6663: iconst_0
    //   6664: iastore
    //   6665: dup
    //   6666: bipush #39
    //   6668: ldc 8396800
    //   6670: iastore
    //   6671: dup
    //   6672: bipush #40
    //   6674: sipush #8320
    //   6677: iastore
    //   6678: dup
    //   6679: bipush #41
    //   6681: ldc 8388736
    //   6683: iastore
    //   6684: dup
    //   6685: bipush #42
    //   6687: ldc 8388737
    //   6689: iastore
    //   6690: dup
    //   6691: bipush #43
    //   6693: iconst_1
    //   6694: iastore
    //   6695: dup
    //   6696: bipush #44
    //   6698: ldc 8396801
    //   6700: iastore
    //   6701: dup
    //   6702: bipush #45
    //   6704: sipush #8321
    //   6707: iastore
    //   6708: dup
    //   6709: bipush #46
    //   6711: sipush #8321
    //   6714: iastore
    //   6715: dup
    //   6716: bipush #47
    //   6718: sipush #128
    //   6721: iastore
    //   6722: dup
    //   6723: bipush #48
    //   6725: ldc 8396929
    //   6727: iastore
    //   6728: dup
    //   6729: bipush #49
    //   6731: sipush #129
    //   6734: iastore
    //   6735: dup
    //   6736: bipush #50
    //   6738: iconst_1
    //   6739: iastore
    //   6740: dup
    //   6741: bipush #51
    //   6743: sipush #8192
    //   6746: iastore
    //   6747: dup
    //   6748: bipush #52
    //   6750: ldc 8388609
    //   6752: iastore
    //   6753: dup
    //   6754: bipush #53
    //   6756: sipush #8193
    //   6759: iastore
    //   6760: dup
    //   6761: bipush #54
    //   6763: ldc 8396928
    //   6765: iastore
    //   6766: dup
    //   6767: bipush #55
    //   6769: ldc 8388737
    //   6771: iastore
    //   6772: dup
    //   6773: bipush #56
    //   6775: sipush #8193
    //   6778: iastore
    //   6779: dup
    //   6780: bipush #57
    //   6782: sipush #8320
    //   6785: iastore
    //   6786: dup
    //   6787: bipush #58
    //   6789: ldc 8388608
    //   6791: iastore
    //   6792: dup
    //   6793: bipush #59
    //   6795: ldc 8396801
    //   6797: iastore
    //   6798: dup
    //   6799: bipush #60
    //   6801: sipush #128
    //   6804: iastore
    //   6805: dup
    //   6806: bipush #61
    //   6808: ldc 8388608
    //   6810: iastore
    //   6811: dup
    //   6812: bipush #62
    //   6814: sipush #8192
    //   6817: iastore
    //   6818: dup
    //   6819: bipush #63
    //   6821: ldc 8396928
    //   6823: iastore
    //   6824: astore #11
    //   6826: bipush #64
    //   6828: newarray int
    //   6830: dup
    //   6831: iconst_0
    //   6832: sipush #256
    //   6835: iastore
    //   6836: dup
    //   6837: iconst_1
    //   6838: ldc 34078976
    //   6840: iastore
    //   6841: dup
    //   6842: iconst_2
    //   6843: ldc 34078720
    //   6845: iastore
    //   6846: dup
    //   6847: iconst_3
    //   6848: ldc 1107296512
    //   6850: iastore
    //   6851: dup
    //   6852: iconst_4
    //   6853: ldc 524288
    //   6855: iastore
    //   6856: dup
    //   6857: iconst_5
    //   6858: sipush #256
    //   6861: iastore
    //   6862: dup
    //   6863: bipush #6
    //   6865: ldc 1073741824
    //   6867: iastore
    //   6868: dup
    //   6869: bipush #7
    //   6871: ldc 34078720
    //   6873: iastore
    //   6874: dup
    //   6875: bipush #8
    //   6877: ldc 1074266368
    //   6879: iastore
    //   6880: dup
    //   6881: bipush #9
    //   6883: ldc 524288
    //   6885: iastore
    //   6886: dup
    //   6887: bipush #10
    //   6889: ldc 33554688
    //   6891: iastore
    //   6892: dup
    //   6893: bipush #11
    //   6895: ldc 1074266368
    //   6897: iastore
    //   6898: dup
    //   6899: bipush #12
    //   6901: ldc 1107296512
    //   6903: iastore
    //   6904: dup
    //   6905: bipush #13
    //   6907: ldc 1107820544
    //   6909: iastore
    //   6910: dup
    //   6911: bipush #14
    //   6913: ldc 524544
    //   6915: iastore
    //   6916: dup
    //   6917: bipush #15
    //   6919: ldc 1073741824
    //   6921: iastore
    //   6922: dup
    //   6923: bipush #16
    //   6925: ldc 33554432
    //   6927: iastore
    //   6928: dup
    //   6929: bipush #17
    //   6931: ldc 1074266112
    //   6933: iastore
    //   6934: dup
    //   6935: bipush #18
    //   6937: ldc 1074266112
    //   6939: iastore
    //   6940: dup
    //   6941: bipush #19
    //   6943: iconst_0
    //   6944: iastore
    //   6945: dup
    //   6946: bipush #20
    //   6948: ldc 1073742080
    //   6950: iastore
    //   6951: dup
    //   6952: bipush #21
    //   6954: ldc 1107820800
    //   6956: iastore
    //   6957: dup
    //   6958: bipush #22
    //   6960: ldc 1107820800
    //   6962: iastore
    //   6963: dup
    //   6964: bipush #23
    //   6966: ldc 33554688
    //   6968: iastore
    //   6969: dup
    //   6970: bipush #24
    //   6972: ldc 1107820544
    //   6974: iastore
    //   6975: dup
    //   6976: bipush #25
    //   6978: ldc 1073742080
    //   6980: iastore
    //   6981: dup
    //   6982: bipush #26
    //   6984: iconst_0
    //   6985: iastore
    //   6986: dup
    //   6987: bipush #27
    //   6989: ldc 1107296256
    //   6991: iastore
    //   6992: dup
    //   6993: bipush #28
    //   6995: ldc 34078976
    //   6997: iastore
    //   6998: dup
    //   6999: bipush #29
    //   7001: ldc 33554432
    //   7003: iastore
    //   7004: dup
    //   7005: bipush #30
    //   7007: ldc 1107296256
    //   7009: iastore
    //   7010: dup
    //   7011: bipush #31
    //   7013: ldc 524544
    //   7015: iastore
    //   7016: dup
    //   7017: bipush #32
    //   7019: ldc 524288
    //   7021: iastore
    //   7022: dup
    //   7023: bipush #33
    //   7025: ldc 1107296512
    //   7027: iastore
    //   7028: dup
    //   7029: bipush #34
    //   7031: sipush #256
    //   7034: iastore
    //   7035: dup
    //   7036: bipush #35
    //   7038: ldc 33554432
    //   7040: iastore
    //   7041: dup
    //   7042: bipush #36
    //   7044: ldc 1073741824
    //   7046: iastore
    //   7047: dup
    //   7048: bipush #37
    //   7050: ldc 34078720
    //   7052: iastore
    //   7053: dup
    //   7054: bipush #38
    //   7056: ldc 1107296512
    //   7058: iastore
    //   7059: dup
    //   7060: bipush #39
    //   7062: ldc 1074266368
    //   7064: iastore
    //   7065: dup
    //   7066: bipush #40
    //   7068: ldc 33554688
    //   7070: iastore
    //   7071: dup
    //   7072: bipush #41
    //   7074: ldc 1073741824
    //   7076: iastore
    //   7077: dup
    //   7078: bipush #42
    //   7080: ldc 1107820544
    //   7082: iastore
    //   7083: dup
    //   7084: bipush #43
    //   7086: ldc 34078976
    //   7088: iastore
    //   7089: dup
    //   7090: bipush #44
    //   7092: ldc 1074266368
    //   7094: iastore
    //   7095: dup
    //   7096: bipush #45
    //   7098: sipush #256
    //   7101: iastore
    //   7102: dup
    //   7103: bipush #46
    //   7105: ldc 33554432
    //   7107: iastore
    //   7108: dup
    //   7109: bipush #47
    //   7111: ldc 1107820544
    //   7113: iastore
    //   7114: dup
    //   7115: bipush #48
    //   7117: ldc 1107820800
    //   7119: iastore
    //   7120: dup
    //   7121: bipush #49
    //   7123: ldc 524544
    //   7125: iastore
    //   7126: dup
    //   7127: bipush #50
    //   7129: ldc 1107296256
    //   7131: iastore
    //   7132: dup
    //   7133: bipush #51
    //   7135: ldc 1107820800
    //   7137: iastore
    //   7138: dup
    //   7139: bipush #52
    //   7141: ldc 34078720
    //   7143: iastore
    //   7144: dup
    //   7145: bipush #53
    //   7147: iconst_0
    //   7148: iastore
    //   7149: dup
    //   7150: bipush #54
    //   7152: ldc 1074266112
    //   7154: iastore
    //   7155: dup
    //   7156: bipush #55
    //   7158: ldc 1107296256
    //   7160: iastore
    //   7161: dup
    //   7162: bipush #56
    //   7164: ldc 524544
    //   7166: iastore
    //   7167: dup
    //   7168: bipush #57
    //   7170: ldc 33554688
    //   7172: iastore
    //   7173: dup
    //   7174: bipush #58
    //   7176: ldc 1073742080
    //   7178: iastore
    //   7179: dup
    //   7180: bipush #59
    //   7182: ldc 524288
    //   7184: iastore
    //   7185: dup
    //   7186: bipush #60
    //   7188: iconst_0
    //   7189: iastore
    //   7190: dup
    //   7191: bipush #61
    //   7193: ldc 1074266112
    //   7195: iastore
    //   7196: dup
    //   7197: bipush #62
    //   7199: ldc 34078976
    //   7201: iastore
    //   7202: dup
    //   7203: bipush #63
    //   7205: ldc 1073742080
    //   7207: iastore
    //   7208: astore #12
    //   7210: bipush #64
    //   7212: newarray int
    //   7214: dup
    //   7215: iconst_0
    //   7216: ldc 536870928
    //   7218: iastore
    //   7219: dup
    //   7220: iconst_1
    //   7221: ldc 541065216
    //   7223: iastore
    //   7224: dup
    //   7225: iconst_2
    //   7226: sipush #16384
    //   7229: iastore
    //   7230: dup
    //   7231: iconst_3
    //   7232: ldc 541081616
    //   7234: iastore
    //   7235: dup
    //   7236: iconst_4
    //   7237: ldc 541065216
    //   7239: iastore
    //   7240: dup
    //   7241: iconst_5
    //   7242: bipush #16
    //   7244: iastore
    //   7245: dup
    //   7246: bipush #6
    //   7248: ldc 541081616
    //   7250: iastore
    //   7251: dup
    //   7252: bipush #7
    //   7254: ldc 4194304
    //   7256: iastore
    //   7257: dup
    //   7258: bipush #8
    //   7260: ldc 536887296
    //   7262: iastore
    //   7263: dup
    //   7264: bipush #9
    //   7266: ldc 4210704
    //   7268: iastore
    //   7269: dup
    //   7270: bipush #10
    //   7272: ldc 4194304
    //   7274: iastore
    //   7275: dup
    //   7276: bipush #11
    //   7278: ldc 536870928
    //   7280: iastore
    //   7281: dup
    //   7282: bipush #12
    //   7284: ldc 4194320
    //   7286: iastore
    //   7287: dup
    //   7288: bipush #13
    //   7290: ldc 536887296
    //   7292: iastore
    //   7293: dup
    //   7294: bipush #14
    //   7296: ldc 536870912
    //   7298: iastore
    //   7299: dup
    //   7300: bipush #15
    //   7302: sipush #16400
    //   7305: iastore
    //   7306: dup
    //   7307: bipush #16
    //   7309: iconst_0
    //   7310: iastore
    //   7311: dup
    //   7312: bipush #17
    //   7314: ldc 4194320
    //   7316: iastore
    //   7317: dup
    //   7318: bipush #18
    //   7320: ldc 536887312
    //   7322: iastore
    //   7323: dup
    //   7324: bipush #19
    //   7326: sipush #16384
    //   7329: iastore
    //   7330: dup
    //   7331: bipush #20
    //   7333: ldc 4210688
    //   7335: iastore
    //   7336: dup
    //   7337: bipush #21
    //   7339: ldc 536887312
    //   7341: iastore
    //   7342: dup
    //   7343: bipush #22
    //   7345: bipush #16
    //   7347: iastore
    //   7348: dup
    //   7349: bipush #23
    //   7351: ldc 541065232
    //   7353: iastore
    //   7354: dup
    //   7355: bipush #24
    //   7357: ldc 541065232
    //   7359: iastore
    //   7360: dup
    //   7361: bipush #25
    //   7363: iconst_0
    //   7364: iastore
    //   7365: dup
    //   7366: bipush #26
    //   7368: ldc 4210704
    //   7370: iastore
    //   7371: dup
    //   7372: bipush #27
    //   7374: ldc 541081600
    //   7376: iastore
    //   7377: dup
    //   7378: bipush #28
    //   7380: sipush #16400
    //   7383: iastore
    //   7384: dup
    //   7385: bipush #29
    //   7387: ldc 4210688
    //   7389: iastore
    //   7390: dup
    //   7391: bipush #30
    //   7393: ldc 541081600
    //   7395: iastore
    //   7396: dup
    //   7397: bipush #31
    //   7399: ldc 536870912
    //   7401: iastore
    //   7402: dup
    //   7403: bipush #32
    //   7405: ldc 536887296
    //   7407: iastore
    //   7408: dup
    //   7409: bipush #33
    //   7411: bipush #16
    //   7413: iastore
    //   7414: dup
    //   7415: bipush #34
    //   7417: ldc 541065232
    //   7419: iastore
    //   7420: dup
    //   7421: bipush #35
    //   7423: ldc 4210688
    //   7425: iastore
    //   7426: dup
    //   7427: bipush #36
    //   7429: ldc 541081616
    //   7431: iastore
    //   7432: dup
    //   7433: bipush #37
    //   7435: ldc 4194304
    //   7437: iastore
    //   7438: dup
    //   7439: bipush #38
    //   7441: sipush #16400
    //   7444: iastore
    //   7445: dup
    //   7446: bipush #39
    //   7448: ldc 536870928
    //   7450: iastore
    //   7451: dup
    //   7452: bipush #40
    //   7454: ldc 4194304
    //   7456: iastore
    //   7457: dup
    //   7458: bipush #41
    //   7460: ldc 536887296
    //   7462: iastore
    //   7463: dup
    //   7464: bipush #42
    //   7466: ldc 536870912
    //   7468: iastore
    //   7469: dup
    //   7470: bipush #43
    //   7472: sipush #16400
    //   7475: iastore
    //   7476: dup
    //   7477: bipush #44
    //   7479: ldc 536870928
    //   7481: iastore
    //   7482: dup
    //   7483: bipush #45
    //   7485: ldc 541081616
    //   7487: iastore
    //   7488: dup
    //   7489: bipush #46
    //   7491: ldc 4210688
    //   7493: iastore
    //   7494: dup
    //   7495: bipush #47
    //   7497: ldc 541065216
    //   7499: iastore
    //   7500: dup
    //   7501: bipush #48
    //   7503: ldc 4210704
    //   7505: iastore
    //   7506: dup
    //   7507: bipush #49
    //   7509: ldc 541081600
    //   7511: iastore
    //   7512: dup
    //   7513: bipush #50
    //   7515: iconst_0
    //   7516: iastore
    //   7517: dup
    //   7518: bipush #51
    //   7520: ldc 541065232
    //   7522: iastore
    //   7523: dup
    //   7524: bipush #52
    //   7526: bipush #16
    //   7528: iastore
    //   7529: dup
    //   7530: bipush #53
    //   7532: sipush #16384
    //   7535: iastore
    //   7536: dup
    //   7537: bipush #54
    //   7539: ldc 541065216
    //   7541: iastore
    //   7542: dup
    //   7543: bipush #55
    //   7545: ldc 4210704
    //   7547: iastore
    //   7548: dup
    //   7549: bipush #56
    //   7551: sipush #16384
    //   7554: iastore
    //   7555: dup
    //   7556: bipush #57
    //   7558: ldc 4194320
    //   7560: iastore
    //   7561: dup
    //   7562: bipush #58
    //   7564: ldc 536887312
    //   7566: iastore
    //   7567: dup
    //   7568: bipush #59
    //   7570: iconst_0
    //   7571: iastore
    //   7572: dup
    //   7573: bipush #60
    //   7575: ldc 541081600
    //   7577: iastore
    //   7578: dup
    //   7579: bipush #61
    //   7581: ldc 536870912
    //   7583: iastore
    //   7584: dup
    //   7585: bipush #62
    //   7587: ldc 4194320
    //   7589: iastore
    //   7590: dup
    //   7591: bipush #63
    //   7593: ldc 536887312
    //   7595: iastore
    //   7596: astore #13
    //   7598: bipush #64
    //   7600: newarray int
    //   7602: dup
    //   7603: iconst_0
    //   7604: ldc 2097152
    //   7606: iastore
    //   7607: dup
    //   7608: iconst_1
    //   7609: ldc 69206018
    //   7611: iastore
    //   7612: dup
    //   7613: iconst_2
    //   7614: ldc 67110914
    //   7616: iastore
    //   7617: dup
    //   7618: iconst_3
    //   7619: iconst_0
    //   7620: iastore
    //   7621: dup
    //   7622: iconst_4
    //   7623: sipush #2048
    //   7626: iastore
    //   7627: dup
    //   7628: iconst_5
    //   7629: ldc 67110914
    //   7631: iastore
    //   7632: dup
    //   7633: bipush #6
    //   7635: ldc 2099202
    //   7637: iastore
    //   7638: dup
    //   7639: bipush #7
    //   7641: ldc 69208064
    //   7643: iastore
    //   7644: dup
    //   7645: bipush #8
    //   7647: ldc 69208066
    //   7649: iastore
    //   7650: dup
    //   7651: bipush #9
    //   7653: ldc 2097152
    //   7655: iastore
    //   7656: dup
    //   7657: bipush #10
    //   7659: iconst_0
    //   7660: iastore
    //   7661: dup
    //   7662: bipush #11
    //   7664: ldc 67108866
    //   7666: iastore
    //   7667: dup
    //   7668: bipush #12
    //   7670: iconst_2
    //   7671: iastore
    //   7672: dup
    //   7673: bipush #13
    //   7675: ldc 67108864
    //   7677: iastore
    //   7678: dup
    //   7679: bipush #14
    //   7681: ldc 69206018
    //   7683: iastore
    //   7684: dup
    //   7685: bipush #15
    //   7687: sipush #2050
    //   7690: iastore
    //   7691: dup
    //   7692: bipush #16
    //   7694: ldc 67110912
    //   7696: iastore
    //   7697: dup
    //   7698: bipush #17
    //   7700: ldc 2099202
    //   7702: iastore
    //   7703: dup
    //   7704: bipush #18
    //   7706: ldc 2097154
    //   7708: iastore
    //   7709: dup
    //   7710: bipush #19
    //   7712: ldc 67110912
    //   7714: iastore
    //   7715: dup
    //   7716: bipush #20
    //   7718: ldc 67108866
    //   7720: iastore
    //   7721: dup
    //   7722: bipush #21
    //   7724: ldc 69206016
    //   7726: iastore
    //   7727: dup
    //   7728: bipush #22
    //   7730: ldc 69208064
    //   7732: iastore
    //   7733: dup
    //   7734: bipush #23
    //   7736: ldc 2097154
    //   7738: iastore
    //   7739: dup
    //   7740: bipush #24
    //   7742: ldc 69206016
    //   7744: iastore
    //   7745: dup
    //   7746: bipush #25
    //   7748: sipush #2048
    //   7751: iastore
    //   7752: dup
    //   7753: bipush #26
    //   7755: sipush #2050
    //   7758: iastore
    //   7759: dup
    //   7760: bipush #27
    //   7762: ldc 69208066
    //   7764: iastore
    //   7765: dup
    //   7766: bipush #28
    //   7768: ldc 2099200
    //   7770: iastore
    //   7771: dup
    //   7772: bipush #29
    //   7774: iconst_2
    //   7775: iastore
    //   7776: dup
    //   7777: bipush #30
    //   7779: ldc 67108864
    //   7781: iastore
    //   7782: dup
    //   7783: bipush #31
    //   7785: ldc 2099200
    //   7787: iastore
    //   7788: dup
    //   7789: bipush #32
    //   7791: ldc 67108864
    //   7793: iastore
    //   7794: dup
    //   7795: bipush #33
    //   7797: ldc 2099200
    //   7799: iastore
    //   7800: dup
    //   7801: bipush #34
    //   7803: ldc 2097152
    //   7805: iastore
    //   7806: dup
    //   7807: bipush #35
    //   7809: ldc 67110914
    //   7811: iastore
    //   7812: dup
    //   7813: bipush #36
    //   7815: ldc 67110914
    //   7817: iastore
    //   7818: dup
    //   7819: bipush #37
    //   7821: ldc 69206018
    //   7823: iastore
    //   7824: dup
    //   7825: bipush #38
    //   7827: ldc 69206018
    //   7829: iastore
    //   7830: dup
    //   7831: bipush #39
    //   7833: iconst_2
    //   7834: iastore
    //   7835: dup
    //   7836: bipush #40
    //   7838: ldc 2097154
    //   7840: iastore
    //   7841: dup
    //   7842: bipush #41
    //   7844: ldc 67108864
    //   7846: iastore
    //   7847: dup
    //   7848: bipush #42
    //   7850: ldc 67110912
    //   7852: iastore
    //   7853: dup
    //   7854: bipush #43
    //   7856: ldc 2097152
    //   7858: iastore
    //   7859: dup
    //   7860: bipush #44
    //   7862: ldc 69208064
    //   7864: iastore
    //   7865: dup
    //   7866: bipush #45
    //   7868: sipush #2050
    //   7871: iastore
    //   7872: dup
    //   7873: bipush #46
    //   7875: ldc 2099202
    //   7877: iastore
    //   7878: dup
    //   7879: bipush #47
    //   7881: ldc 69208064
    //   7883: iastore
    //   7884: dup
    //   7885: bipush #48
    //   7887: sipush #2050
    //   7890: iastore
    //   7891: dup
    //   7892: bipush #49
    //   7894: ldc 67108866
    //   7896: iastore
    //   7897: dup
    //   7898: bipush #50
    //   7900: ldc 69208066
    //   7902: iastore
    //   7903: dup
    //   7904: bipush #51
    //   7906: ldc 69206016
    //   7908: iastore
    //   7909: dup
    //   7910: bipush #52
    //   7912: ldc 2099200
    //   7914: iastore
    //   7915: dup
    //   7916: bipush #53
    //   7918: iconst_0
    //   7919: iastore
    //   7920: dup
    //   7921: bipush #54
    //   7923: iconst_2
    //   7924: iastore
    //   7925: dup
    //   7926: bipush #55
    //   7928: ldc 69208066
    //   7930: iastore
    //   7931: dup
    //   7932: bipush #56
    //   7934: iconst_0
    //   7935: iastore
    //   7936: dup
    //   7937: bipush #57
    //   7939: ldc 2099202
    //   7941: iastore
    //   7942: dup
    //   7943: bipush #58
    //   7945: ldc 69206016
    //   7947: iastore
    //   7948: dup
    //   7949: bipush #59
    //   7951: sipush #2048
    //   7954: iastore
    //   7955: dup
    //   7956: bipush #60
    //   7958: ldc 67108866
    //   7960: iastore
    //   7961: dup
    //   7962: bipush #61
    //   7964: ldc 67110912
    //   7966: iastore
    //   7967: dup
    //   7968: bipush #62
    //   7970: sipush #2048
    //   7973: iastore
    //   7974: dup
    //   7975: bipush #63
    //   7977: ldc 2097154
    //   7979: iastore
    //   7980: astore #14
    //   7982: bipush #64
    //   7984: newarray int
    //   7986: dup
    //   7987: iconst_0
    //   7988: ldc 268439616
    //   7990: iastore
    //   7991: dup
    //   7992: iconst_1
    //   7993: sipush #4096
    //   7996: iastore
    //   7997: dup
    //   7998: iconst_2
    //   7999: ldc 262144
    //   8001: iastore
    //   8002: dup
    //   8003: iconst_3
    //   8004: ldc 268701760
    //   8006: iastore
    //   8007: dup
    //   8008: iconst_4
    //   8009: ldc 268435456
    //   8011: iastore
    //   8012: dup
    //   8013: iconst_5
    //   8014: ldc 268439616
    //   8016: iastore
    //   8017: dup
    //   8018: bipush #6
    //   8020: bipush #64
    //   8022: iastore
    //   8023: dup
    //   8024: bipush #7
    //   8026: ldc 268435456
    //   8028: iastore
    //   8029: dup
    //   8030: bipush #8
    //   8032: ldc 262208
    //   8034: iastore
    //   8035: dup
    //   8036: bipush #9
    //   8038: ldc 268697600
    //   8040: iastore
    //   8041: dup
    //   8042: bipush #10
    //   8044: ldc 268701760
    //   8046: iastore
    //   8047: dup
    //   8048: bipush #11
    //   8050: ldc 266240
    //   8052: iastore
    //   8053: dup
    //   8054: bipush #12
    //   8056: ldc 268701696
    //   8058: iastore
    //   8059: dup
    //   8060: bipush #13
    //   8062: ldc 266304
    //   8064: iastore
    //   8065: dup
    //   8066: bipush #14
    //   8068: sipush #4096
    //   8071: iastore
    //   8072: dup
    //   8073: bipush #15
    //   8075: bipush #64
    //   8077: iastore
    //   8078: dup
    //   8079: bipush #16
    //   8081: ldc 268697600
    //   8083: iastore
    //   8084: dup
    //   8085: bipush #17
    //   8087: ldc 268435520
    //   8089: iastore
    //   8090: dup
    //   8091: bipush #18
    //   8093: ldc 268439552
    //   8095: iastore
    //   8096: dup
    //   8097: bipush #19
    //   8099: sipush #4160
    //   8102: iastore
    //   8103: dup
    //   8104: bipush #20
    //   8106: ldc 266240
    //   8108: iastore
    //   8109: dup
    //   8110: bipush #21
    //   8112: ldc 262208
    //   8114: iastore
    //   8115: dup
    //   8116: bipush #22
    //   8118: ldc 268697664
    //   8120: iastore
    //   8121: dup
    //   8122: bipush #23
    //   8124: ldc 268701696
    //   8126: iastore
    //   8127: dup
    //   8128: bipush #24
    //   8130: sipush #4160
    //   8133: iastore
    //   8134: dup
    //   8135: bipush #25
    //   8137: iconst_0
    //   8138: iastore
    //   8139: dup
    //   8140: bipush #26
    //   8142: iconst_0
    //   8143: iastore
    //   8144: dup
    //   8145: bipush #27
    //   8147: ldc 268697664
    //   8149: iastore
    //   8150: dup
    //   8151: bipush #28
    //   8153: ldc 268435520
    //   8155: iastore
    //   8156: dup
    //   8157: bipush #29
    //   8159: ldc 268439552
    //   8161: iastore
    //   8162: dup
    //   8163: bipush #30
    //   8165: ldc 266304
    //   8167: iastore
    //   8168: dup
    //   8169: bipush #31
    //   8171: ldc 262144
    //   8173: iastore
    //   8174: dup
    //   8175: bipush #32
    //   8177: ldc 266304
    //   8179: iastore
    //   8180: dup
    //   8181: bipush #33
    //   8183: ldc 262144
    //   8185: iastore
    //   8186: dup
    //   8187: bipush #34
    //   8189: ldc 268701696
    //   8191: iastore
    //   8192: dup
    //   8193: bipush #35
    //   8195: sipush #4096
    //   8198: iastore
    //   8199: dup
    //   8200: bipush #36
    //   8202: bipush #64
    //   8204: iastore
    //   8205: dup
    //   8206: bipush #37
    //   8208: ldc 268697664
    //   8210: iastore
    //   8211: dup
    //   8212: bipush #38
    //   8214: sipush #4096
    //   8217: iastore
    //   8218: dup
    //   8219: bipush #39
    //   8221: ldc 266304
    //   8223: iastore
    //   8224: dup
    //   8225: bipush #40
    //   8227: ldc 268439552
    //   8229: iastore
    //   8230: dup
    //   8231: bipush #41
    //   8233: bipush #64
    //   8235: iastore
    //   8236: dup
    //   8237: bipush #42
    //   8239: ldc 268435520
    //   8241: iastore
    //   8242: dup
    //   8243: bipush #43
    //   8245: ldc 268697600
    //   8247: iastore
    //   8248: dup
    //   8249: bipush #44
    //   8251: ldc 268697664
    //   8253: iastore
    //   8254: dup
    //   8255: bipush #45
    //   8257: ldc 268435456
    //   8259: iastore
    //   8260: dup
    //   8261: bipush #46
    //   8263: ldc 262144
    //   8265: iastore
    //   8266: dup
    //   8267: bipush #47
    //   8269: ldc 268439616
    //   8271: iastore
    //   8272: dup
    //   8273: bipush #48
    //   8275: iconst_0
    //   8276: iastore
    //   8277: dup
    //   8278: bipush #49
    //   8280: ldc 268701760
    //   8282: iastore
    //   8283: dup
    //   8284: bipush #50
    //   8286: ldc 262208
    //   8288: iastore
    //   8289: dup
    //   8290: bipush #51
    //   8292: ldc 268435520
    //   8294: iastore
    //   8295: dup
    //   8296: bipush #52
    //   8298: ldc 268697600
    //   8300: iastore
    //   8301: dup
    //   8302: bipush #53
    //   8304: ldc 268439552
    //   8306: iastore
    //   8307: dup
    //   8308: bipush #54
    //   8310: ldc 268439616
    //   8312: iastore
    //   8313: dup
    //   8314: bipush #55
    //   8316: iconst_0
    //   8317: iastore
    //   8318: dup
    //   8319: bipush #56
    //   8321: ldc 268701760
    //   8323: iastore
    //   8324: dup
    //   8325: bipush #57
    //   8327: ldc 266240
    //   8329: iastore
    //   8330: dup
    //   8331: bipush #58
    //   8333: ldc 266240
    //   8335: iastore
    //   8336: dup
    //   8337: bipush #59
    //   8339: sipush #4160
    //   8342: iastore
    //   8343: dup
    //   8344: bipush #60
    //   8346: sipush #4160
    //   8349: iastore
    //   8350: dup
    //   8351: bipush #61
    //   8353: ldc 262208
    //   8355: iastore
    //   8356: dup
    //   8357: bipush #62
    //   8359: ldc 268435456
    //   8361: iastore
    //   8362: dup
    //   8363: bipush #63
    //   8365: ldc 268701696
    //   8367: iastore
    //   8368: astore #15
    //   8370: aload_3
    //   8371: arraylength
    //   8372: istore #16
    //   8374: iconst_2
    //   8375: newarray int
    //   8377: astore #17
    //   8379: iload #16
    //   8381: newarray byte
    //   8383: astore #4
    //   8385: iload #16
    //   8387: bipush #8
    //   8389: idiv
    //   8390: istore #18
    //   8392: iconst_0
    //   8393: istore #19
    //   8395: iload #19
    //   8397: iload #18
    //   8399: if_icmpge -> 9313
    //   8402: iload #19
    //   8404: bipush #8
    //   8406: imul
    //   8407: istore #20
    //   8409: iconst_0
    //   8410: istore #21
    //   8412: iload #21
    //   8414: iconst_2
    //   8415: if_icmpge -> 8500
    //   8418: aload #17
    //   8420: iload #21
    //   8422: aload_3
    //   8423: iload #20
    //   8425: iload #21
    //   8427: iconst_4
    //   8428: imul
    //   8429: iadd
    //   8430: baload
    //   8431: sipush #255
    //   8434: iand
    //   8435: bipush #24
    //   8437: ishl
    //   8438: aload_3
    //   8439: iload #20
    //   8441: iload #21
    //   8443: iconst_4
    //   8444: imul
    //   8445: iadd
    //   8446: iconst_1
    //   8447: iadd
    //   8448: baload
    //   8449: sipush #255
    //   8452: iand
    //   8453: bipush #16
    //   8455: ishl
    //   8456: ior
    //   8457: aload_3
    //   8458: iload #20
    //   8460: iload #21
    //   8462: iconst_4
    //   8463: imul
    //   8464: iadd
    //   8465: iconst_2
    //   8466: iadd
    //   8467: baload
    //   8468: sipush #255
    //   8471: iand
    //   8472: bipush #8
    //   8474: ishl
    //   8475: ior
    //   8476: aload_3
    //   8477: iload #20
    //   8479: iload #21
    //   8481: iconst_4
    //   8482: imul
    //   8483: iadd
    //   8484: iconst_3
    //   8485: iadd
    //   8486: baload
    //   8487: sipush #255
    //   8490: iand
    //   8491: ior
    //   8492: iastore
    //   8493: iinc #21, 1
    //   8496: iload_2
    //   8497: ifne -> 8412
    //   8500: iconst_0
    //   8501: istore #26
    //   8503: aload #17
    //   8505: iconst_0
    //   8506: iaload
    //   8507: istore #24
    //   8509: aload #17
    //   8511: iconst_1
    //   8512: iaload
    //   8513: istore #23
    //   8515: iload #24
    //   8517: iconst_4
    //   8518: iushr
    //   8519: iload #23
    //   8521: ixor
    //   8522: ldc 252645135
    //   8524: iand
    //   8525: istore #22
    //   8527: iload #23
    //   8529: iload #22
    //   8531: ixor
    //   8532: istore #23
    //   8534: iload #24
    //   8536: iload #22
    //   8538: iconst_4
    //   8539: ishl
    //   8540: ixor
    //   8541: istore #24
    //   8543: iload #24
    //   8545: bipush #16
    //   8547: iushr
    //   8548: iload #23
    //   8550: ixor
    //   8551: ldc 65535
    //   8553: iand
    //   8554: istore #22
    //   8556: iload #23
    //   8558: iload #22
    //   8560: ixor
    //   8561: istore #23
    //   8563: iload #24
    //   8565: iload #22
    //   8567: bipush #16
    //   8569: ishl
    //   8570: ixor
    //   8571: istore #24
    //   8573: iload #23
    //   8575: iconst_2
    //   8576: iushr
    //   8577: iload #24
    //   8579: ixor
    //   8580: ldc 858993459
    //   8582: iand
    //   8583: istore #22
    //   8585: iload #24
    //   8587: iload #22
    //   8589: ixor
    //   8590: istore #24
    //   8592: iload #23
    //   8594: iload #22
    //   8596: iconst_2
    //   8597: ishl
    //   8598: ixor
    //   8599: istore #23
    //   8601: iload #23
    //   8603: bipush #8
    //   8605: iushr
    //   8606: iload #24
    //   8608: ixor
    //   8609: ldc 16711935
    //   8611: iand
    //   8612: istore #22
    //   8614: iload #24
    //   8616: iload #22
    //   8618: ixor
    //   8619: istore #24
    //   8621: iload #23
    //   8623: iload #22
    //   8625: bipush #8
    //   8627: ishl
    //   8628: ixor
    //   8629: istore #23
    //   8631: iload #23
    //   8633: iconst_1
    //   8634: ishl
    //   8635: iload #23
    //   8637: bipush #31
    //   8639: iushr
    //   8640: iconst_1
    //   8641: iand
    //   8642: ior
    //   8643: istore #23
    //   8645: iload #24
    //   8647: iload #23
    //   8649: ixor
    //   8650: ldc -1431655766
    //   8652: iand
    //   8653: istore #22
    //   8655: iload #24
    //   8657: iload #22
    //   8659: ixor
    //   8660: istore #24
    //   8662: iload #23
    //   8664: iload #22
    //   8666: ixor
    //   8667: istore #23
    //   8669: iload #24
    //   8671: iconst_1
    //   8672: ishl
    //   8673: iload #24
    //   8675: bipush #31
    //   8677: iushr
    //   8678: iconst_1
    //   8679: iand
    //   8680: ior
    //   8681: istore #24
    //   8683: iconst_0
    //   8684: istore #25
    //   8686: iload #25
    //   8688: bipush #8
    //   8690: if_icmpge -> 9028
    //   8693: iload #23
    //   8695: bipush #28
    //   8697: ishl
    //   8698: iload #23
    //   8700: iconst_4
    //   8701: iushr
    //   8702: ior
    //   8703: istore #22
    //   8705: iload #22
    //   8707: aload #5
    //   8709: iload #26
    //   8711: iinc #26, 1
    //   8714: iaload
    //   8715: ixor
    //   8716: istore #22
    //   8718: aload #14
    //   8720: iload #22
    //   8722: bipush #63
    //   8724: iand
    //   8725: iaload
    //   8726: istore #21
    //   8728: iload #21
    //   8730: aload #12
    //   8732: iload #22
    //   8734: bipush #8
    //   8736: iushr
    //   8737: bipush #63
    //   8739: iand
    //   8740: iaload
    //   8741: ior
    //   8742: istore #21
    //   8744: iload #21
    //   8746: aload #10
    //   8748: iload #22
    //   8750: bipush #16
    //   8752: iushr
    //   8753: bipush #63
    //   8755: iand
    //   8756: iaload
    //   8757: ior
    //   8758: istore #21
    //   8760: iload #21
    //   8762: aload #8
    //   8764: iload #22
    //   8766: bipush #24
    //   8768: iushr
    //   8769: bipush #63
    //   8771: iand
    //   8772: iaload
    //   8773: ior
    //   8774: istore #21
    //   8776: iload #23
    //   8778: aload #5
    //   8780: iload #26
    //   8782: iinc #26, 1
    //   8785: iaload
    //   8786: ixor
    //   8787: istore #22
    //   8789: iload #21
    //   8791: aload #15
    //   8793: iload #22
    //   8795: bipush #63
    //   8797: iand
    //   8798: iaload
    //   8799: ior
    //   8800: istore #21
    //   8802: iload #21
    //   8804: aload #13
    //   8806: iload #22
    //   8808: bipush #8
    //   8810: iushr
    //   8811: bipush #63
    //   8813: iand
    //   8814: iaload
    //   8815: ior
    //   8816: istore #21
    //   8818: iload #21
    //   8820: aload #11
    //   8822: iload #22
    //   8824: bipush #16
    //   8826: iushr
    //   8827: bipush #63
    //   8829: iand
    //   8830: iaload
    //   8831: ior
    //   8832: istore #21
    //   8834: iload #21
    //   8836: aload #9
    //   8838: iload #22
    //   8840: bipush #24
    //   8842: iushr
    //   8843: bipush #63
    //   8845: iand
    //   8846: iaload
    //   8847: ior
    //   8848: istore #21
    //   8850: iload #24
    //   8852: iload #21
    //   8854: ixor
    //   8855: istore #24
    //   8857: iload #24
    //   8859: bipush #28
    //   8861: ishl
    //   8862: iload #24
    //   8864: iconst_4
    //   8865: iushr
    //   8866: ior
    //   8867: istore #22
    //   8869: iload #22
    //   8871: aload #5
    //   8873: iload #26
    //   8875: iinc #26, 1
    //   8878: iaload
    //   8879: ixor
    //   8880: istore #22
    //   8882: aload #14
    //   8884: iload #22
    //   8886: bipush #63
    //   8888: iand
    //   8889: iaload
    //   8890: istore #21
    //   8892: iload #21
    //   8894: aload #12
    //   8896: iload #22
    //   8898: bipush #8
    //   8900: iushr
    //   8901: bipush #63
    //   8903: iand
    //   8904: iaload
    //   8905: ior
    //   8906: istore #21
    //   8908: iload #21
    //   8910: aload #10
    //   8912: iload #22
    //   8914: bipush #16
    //   8916: iushr
    //   8917: bipush #63
    //   8919: iand
    //   8920: iaload
    //   8921: ior
    //   8922: istore #21
    //   8924: iload #21
    //   8926: aload #8
    //   8928: iload #22
    //   8930: bipush #24
    //   8932: iushr
    //   8933: bipush #63
    //   8935: iand
    //   8936: iaload
    //   8937: ior
    //   8938: istore #21
    //   8940: iload #24
    //   8942: aload #5
    //   8944: iload #26
    //   8946: iinc #26, 1
    //   8949: iaload
    //   8950: ixor
    //   8951: istore #22
    //   8953: iload #21
    //   8955: aload #15
    //   8957: iload #22
    //   8959: bipush #63
    //   8961: iand
    //   8962: iaload
    //   8963: ior
    //   8964: istore #21
    //   8966: iload #21
    //   8968: aload #13
    //   8970: iload #22
    //   8972: bipush #8
    //   8974: iushr
    //   8975: bipush #63
    //   8977: iand
    //   8978: iaload
    //   8979: ior
    //   8980: istore #21
    //   8982: iload #21
    //   8984: aload #11
    //   8986: iload #22
    //   8988: bipush #16
    //   8990: iushr
    //   8991: bipush #63
    //   8993: iand
    //   8994: iaload
    //   8995: ior
    //   8996: istore #21
    //   8998: iload #21
    //   9000: aload #9
    //   9002: iload #22
    //   9004: bipush #24
    //   9006: iushr
    //   9007: bipush #63
    //   9009: iand
    //   9010: iaload
    //   9011: ior
    //   9012: istore #21
    //   9014: iload #23
    //   9016: iload #21
    //   9018: ixor
    //   9019: istore #23
    //   9021: iinc #25, 1
    //   9024: iload_2
    //   9025: ifne -> 8686
    //   9028: iload #23
    //   9030: bipush #31
    //   9032: ishl
    //   9033: iload #23
    //   9035: iconst_1
    //   9036: iushr
    //   9037: ior
    //   9038: istore #23
    //   9040: iload #24
    //   9042: iload #23
    //   9044: ixor
    //   9045: ldc -1431655766
    //   9047: iand
    //   9048: istore #22
    //   9050: iload #24
    //   9052: iload #22
    //   9054: ixor
    //   9055: istore #24
    //   9057: iload #23
    //   9059: iload #22
    //   9061: ixor
    //   9062: istore #23
    //   9064: iload #24
    //   9066: bipush #31
    //   9068: ishl
    //   9069: iload #24
    //   9071: iconst_1
    //   9072: iushr
    //   9073: ior
    //   9074: istore #24
    //   9076: iload #24
    //   9078: bipush #8
    //   9080: iushr
    //   9081: iload #23
    //   9083: ixor
    //   9084: ldc 16711935
    //   9086: iand
    //   9087: istore #22
    //   9089: iload #23
    //   9091: iload #22
    //   9093: ixor
    //   9094: istore #23
    //   9096: iload #24
    //   9098: iload #22
    //   9100: bipush #8
    //   9102: ishl
    //   9103: ixor
    //   9104: istore #24
    //   9106: iload #24
    //   9108: iconst_2
    //   9109: iushr
    //   9110: iload #23
    //   9112: ixor
    //   9113: ldc 858993459
    //   9115: iand
    //   9116: istore #22
    //   9118: iload #23
    //   9120: iload #22
    //   9122: ixor
    //   9123: istore #23
    //   9125: iload #24
    //   9127: iload #22
    //   9129: iconst_2
    //   9130: ishl
    //   9131: ixor
    //   9132: istore #24
    //   9134: iload #23
    //   9136: bipush #16
    //   9138: iushr
    //   9139: iload #24
    //   9141: ixor
    //   9142: ldc 65535
    //   9144: iand
    //   9145: istore #22
    //   9147: iload #24
    //   9149: iload #22
    //   9151: ixor
    //   9152: istore #24
    //   9154: iload #23
    //   9156: iload #22
    //   9158: bipush #16
    //   9160: ishl
    //   9161: ixor
    //   9162: istore #23
    //   9164: iload #23
    //   9166: iconst_4
    //   9167: iushr
    //   9168: iload #24
    //   9170: ixor
    //   9171: ldc 252645135
    //   9173: iand
    //   9174: istore #22
    //   9176: iload #24
    //   9178: iload #22
    //   9180: ixor
    //   9181: istore #24
    //   9183: iload #23
    //   9185: iload #22
    //   9187: iconst_4
    //   9188: ishl
    //   9189: ixor
    //   9190: istore #23
    //   9192: aload #17
    //   9194: iconst_0
    //   9195: iload #23
    //   9197: iastore
    //   9198: aload #17
    //   9200: iconst_1
    //   9201: iload #24
    //   9203: iastore
    //   9204: iload #19
    //   9206: bipush #8
    //   9208: imul
    //   9209: istore #27
    //   9211: iconst_0
    //   9212: istore #28
    //   9214: iload #28
    //   9216: iconst_2
    //   9217: if_icmpge -> 9306
    //   9220: aload #4
    //   9222: iload #27
    //   9224: iload #28
    //   9226: iconst_4
    //   9227: imul
    //   9228: iadd
    //   9229: aload #17
    //   9231: iload #28
    //   9233: iaload
    //   9234: bipush #24
    //   9236: iushr
    //   9237: i2b
    //   9238: bastore
    //   9239: aload #4
    //   9241: iload #27
    //   9243: iload #28
    //   9245: iconst_4
    //   9246: imul
    //   9247: iadd
    //   9248: iconst_1
    //   9249: iadd
    //   9250: aload #17
    //   9252: iload #28
    //   9254: iaload
    //   9255: bipush #16
    //   9257: iushr
    //   9258: i2b
    //   9259: bastore
    //   9260: aload #4
    //   9262: iload #27
    //   9264: iload #28
    //   9266: iconst_4
    //   9267: imul
    //   9268: iadd
    //   9269: iconst_2
    //   9270: iadd
    //   9271: aload #17
    //   9273: iload #28
    //   9275: iaload
    //   9276: bipush #8
    //   9278: iushr
    //   9279: i2b
    //   9280: bastore
    //   9281: aload #4
    //   9283: iload #27
    //   9285: iload #28
    //   9287: iconst_4
    //   9288: imul
    //   9289: iadd
    //   9290: iconst_3
    //   9291: iadd
    //   9292: aload #17
    //   9294: iload #28
    //   9296: iaload
    //   9297: i2b
    //   9298: bastore
    //   9299: iinc #28, 1
    //   9302: iload_2
    //   9303: ifne -> 9214
    //   9306: iinc #19, 1
    //   9309: iload_2
    //   9310: ifne -> 8395
    //   9313: getstatic burp/Zxdp.ZN : Ljava/lang/String;
    //   9316: getstatic burp/Zrn4.Zq : Ljava/lang/Object;
    //   9319: checkcast java/math/BigInteger
    //   9322: invokevirtual intValue : ()I
    //   9325: bipush #32
    //   9327: irem
    //   9328: invokestatic abs : (I)I
    //   9331: invokevirtual charAt : (I)C
    //   9334: getstatic burp/Zlcc.Zw : Ljava/lang/String;
    //   9337: getstatic burp/Zt9f.Zl : Ljava/lang/Object;
    //   9340: checkcast java/math/BigInteger
    //   9343: invokevirtual intValue : ()I
    //   9346: bipush #32
    //   9348: irem
    //   9349: invokestatic abs : (I)I
    //   9352: invokevirtual charAt : (I)C
    //   9355: if_icmple -> 9462
    //   9358: getstatic burp/Zzah.Zs : Ljava/lang/String;
    //   9361: getstatic burp/Zg1l.Zg : Ljava/lang/Object;
    //   9364: checkcast java/math/BigInteger
    //   9367: invokevirtual intValue : ()I
    //   9370: bipush #32
    //   9372: irem
    //   9373: invokestatic abs : (I)I
    //   9376: invokevirtual charAt : (I)C
    //   9379: getstatic burp/Zkkl.Zh : Ljava/lang/String;
    //   9382: getstatic burp/Zmf6.ZD : Ljava/lang/Object;
    //   9385: checkcast java/math/BigInteger
    //   9388: invokevirtual intValue : ()I
    //   9391: bipush #32
    //   9393: irem
    //   9394: invokestatic abs : (I)I
    //   9397: invokevirtual charAt : (I)C
    //   9400: if_icmple -> 9462
    //   9403: goto -> 9410
    //   9406: invokestatic a : (Ljava/lang/Throwable;)Ljava/lang/Throwable;
    //   9409: athrow
    //   9410: getstatic burp/Zbx5.Zz : Ljava/lang/String;
    //   9413: getstatic burp/Zz66.ZQ : Ljava/lang/Object;
    //   9416: checkcast java/math/BigInteger
    //   9419: invokevirtual intValue : ()I
    //   9422: bipush #32
    //   9424: irem
    //   9425: invokestatic abs : (I)I
    //   9428: invokevirtual charAt : (I)C
    //   9431: getstatic burp/Zk8i.ZS : Ljava/lang/String;
    //   9434: getstatic burp/Zl7b.ZK : Ljava/lang/Object;
    //   9437: checkcast java/math/BigInteger
    //   9440: invokevirtual intValue : ()I
    //   9443: bipush #32
    //   9445: irem
    //   9446: invokestatic abs : (I)I
    //   9449: invokevirtual charAt : (I)C
    //   9452: if_icmple -> 9470
    //   9455: goto -> 9462
    //   9458: invokestatic a : (Ljava/lang/Throwable;)Ljava/lang/Throwable;
    //   9461: athrow
    //   9462: iconst_1
    //   9463: goto -> 9471
    //   9466: invokestatic a : (Ljava/lang/Throwable;)Ljava/lang/Throwable;
    //   9469: athrow
    //   9470: iconst_0
    //   9471: ireturn
    //   9472: astore_3
    //   9473: new java/lang/Exception
    //   9476: dup
    //   9477: aload_3
    //   9478: invokevirtual getMessage : ()Ljava/lang/String;
    //   9481: invokespecial <init> : (Ljava/lang/String;)V
    //   9484: athrow
    // Exception table:
    //   from	to	target	type
    //   4	9471	9472	java/lang/Throwable
    //   185	209	212	java/lang/Throwable
    //   283	320	320	java/lang/Throwable
    //   324	345	345	java/lang/Throwable
    //   349	379	379	java/lang/Throwable
    //   1396	1430	1433	java/lang/Throwable
    //   1525	1603	1606	java/lang/Throwable
    //   1532	1746	1749	java/lang/Throwable
    //   2123	2138	2138	java/lang/Throwable
    //   2165	2199	2202	java/lang/Throwable
    //   2209	2221	2224	java/lang/Throwable
    //   2307	2385	2388	java/lang/Throwable
    //   2314	2528	2531	java/lang/Throwable
    //   2928	3006	3009	java/lang/Throwable
    //   2935	3149	3152	java/lang/Throwable
    //   3596	3630	3633	java/lang/Throwable
    //   3637	3649	3652	java/lang/Throwable
    //   3735	3813	3816	java/lang/Throwable
    //   3742	3956	3959	java/lang/Throwable
    //   4710	4724	4724	java/lang/Throwable
    //   4735	4748	4751	java/lang/Throwable
    //   4740	4763	4766	java/lang/Throwable
    //   4755	4781	4784	java/lang/Throwable
    //   4770	4811	4814	java/lang/Throwable
    //   4874	4901	4904	java/lang/Throwable
    //   4891	4922	4925	java/lang/Throwable
    //   4908	4952	4955	java/lang/Throwable
    //   4929	4963	4963	java/lang/Throwable
    //   4974	4990	4993	java/lang/Throwable
    //   9313	9403	9406	java/lang/Throwable
    //   9358	9455	9458	java/lang/Throwable
    //   9410	9466	9466	java/lang/Throwable
  }
  
  static void Zn(Object[] paramArrayOfObject, Object paramObject) throws Throwable {}
  
  static void ZH(Object paramObject) {
    Zl1e.Z_ = a(27836, 29826);
    Zl1e.Zp = new BigInteger(a(27839, 4520));
    boolean bool = Zt2e.ZN();
    try {
      try {
        if (Zzyb.Zh.charAt(Math.abs(((BigInteger)Zb3l.Zl).intValue() % 32)) > Zx5w.Zq.charAt(Math.abs(((BigInteger)Ztbn.ZA).intValue() % 32))) {
          try {
            Zlwm.ZU(Class.forName(a(27832, 24405)));
            if (!bool)
              Zgl2.Ze(Class.forName(a(27837, -31028))); 
          } catch (Throwable throwable) {
            throw a(null);
          } 
          return;
        } 
      } catch (Throwable throwable) {
        throw a(null);
      } 
      Zgl2.Ze(Class.forName(a(27837, -31028)));
    } catch (Throwable throwable) {}
  }
  
  static {
    // Byte code:
    //   0: bipush #9
    //   2: anewarray java/lang/String
    //   5: astore #5
    //   7: iconst_0
    //   8: istore_3
    //   9: ldc '\\t0771W\\b!x5a#9:QVN-v#W$Sf%o= 3\\tELG Y"`Wfdi$$50D  d!A5A#i=sPNt52A8(wL\\rnoNX-QlmIi4J!%$WTp8\\rOhTS{v0<R(OL\\te-b(\\n'
    //   11: dup
    //   12: astore_2
    //   13: invokevirtual length : ()I
    //   16: istore #4
    //   18: bipush #77
    //   20: istore_1
    //   21: iconst_m1
    //   22: istore_0
    //   23: bipush #48
    //   25: iinc #0, 1
    //   28: aload_2
    //   29: iload_0
    //   30: dup
    //   31: iload_1
    //   32: iadd
    //   33: invokevirtual substring : (II)Ljava/lang/String;
    //   36: iconst_m1
    //   37: goto -> 143
    //   40: aload #5
    //   42: swap
    //   43: iload_3
    //   44: iinc #3, 1
    //   47: swap
    //   48: aastore
    //   49: iload_0
    //   50: iload_1
    //   51: iadd
    //   52: dup
    //   53: istore_0
    //   54: iload #4
    //   56: if_icmpge -> 68
    //   59: aload_2
    //   60: iload_0
    //   61: invokevirtual charAt : (I)C
    //   64: istore_1
    //   65: goto -> 23
    //   68: ldc '$Q:Rl'\\t"P7_'
    //   70: dup
    //   71: astore_2
    //   72: invokevirtual length : ()I
    //   75: istore #4
    //   77: bipush #9
    //   79: istore_1
    //   80: iconst_m1
    //   81: istore_0
    //   82: bipush #18
    //   84: iinc #0, 1
    //   87: aload_2
    //   88: iload_0
    //   89: dup
    //   90: iload_1
    //   91: iadd
    //   92: invokevirtual substring : (II)Ljava/lang/String;
    //   95: iconst_0
    //   96: goto -> 143
    //   99: aload #5
    //   101: swap
    //   102: iload_3
    //   103: iinc #3, 1
    //   106: swap
    //   107: aastore
    //   108: iload_0
    //   109: iload_1
    //   110: iadd
    //   111: dup
    //   112: istore_0
    //   113: iload #4
    //   115: if_icmpge -> 127
    //   118: aload_2
    //   119: iload_0
    //   120: invokevirtual charAt : (I)C
    //   123: istore_1
    //   124: goto -> 82
    //   127: aload #5
    //   129: putstatic burp/Zbw5.a : [Ljava/lang/String;
    //   132: bipush #9
    //   134: anewarray java/lang/String
    //   137: putstatic burp/Zbw5.b : [Ljava/lang/String;
    //   140: goto -> 300
    //   143: dup_x2
    //   144: pop
    //   145: invokevirtual toCharArray : ()[C
    //   148: dup_x1
    //   149: arraylength
    //   150: dup_x2
    //   151: pop
    //   152: iconst_0
    //   153: istore #6
    //   155: dup2_x1
    //   156: pop2
    //   157: dup_x2
    //   158: iconst_1
    //   159: if_icmpgt -> 260
    //   162: dup2
    //   163: swap
    //   164: iload #6
    //   166: dup2_x1
    //   167: caload
    //   168: swap
    //   169: iload #6
    //   171: bipush #7
    //   173: irem
    //   174: tableswitch default -> 242, 0 -> 212, 1 -> 217, 2 -> 222, 3 -> 227, 4 -> 232, 5 -> 237
    //   212: bipush #73
    //   214: goto -> 244
    //   217: bipush #17
    //   219: goto -> 244
    //   222: bipush #19
    //   224: goto -> 244
    //   227: bipush #113
    //   229: goto -> 244
    //   232: bipush #76
    //   234: goto -> 244
    //   237: bipush #88
    //   239: goto -> 244
    //   242: bipush #124
    //   244: ixor
    //   245: ixor
    //   246: i2c
    //   247: castore
    //   248: iinc #6, 1
    //   251: dup
    //   252: ifne -> 260
    //   255: dup2
    //   256: dup_x1
    //   257: goto -> 166
    //   260: dup2_x1
    //   261: pop2
    //   262: dup_x2
    //   263: iload #6
    //   265: if_icmpgt -> 162
    //   268: pop
    //   269: new java/lang/String
    //   272: dup_x1
    //   273: swap
    //   274: invokespecial <init> : ([C)V
    //   277: invokevirtual intern : ()Ljava/lang/String;
    //   280: swap
    //   281: pop
    //   282: swap
    //   283: tableswitch default -> 40, 0 -> 99
    //   300: sipush #27835
    //   303: sipush #-1340
    //   306: invokestatic a : (II)Ljava/lang/String;
    //   309: putstatic burp/Zbw5.ZC : Ljava/lang/String;
    //   312: new java/math/BigInteger
    //   315: dup
    //   316: sipush #27834
    //   319: sipush #14949
    //   322: invokestatic a : (II)Ljava/lang/String;
    //   325: invokespecial <init> : (Ljava/lang/String;)V
    //   328: putstatic burp/Zbw5.ZR : Ljava/lang/Object;
    //   331: return
  }
  
  private static Throwable a(Throwable paramThrowable) {
    return paramThrowable;
  }
  
  private static String a(int paramInt1, int paramInt2) {
    int i = (paramInt1 ^ 0x6CBF) & 0xFFFF;
    if (b[i] == null) {
      char[] arrayOfChar = a[i].toCharArray();
      switch (arrayOfChar[0] & 0xFF) {
        case 0:
        
        case 1:
        
        case 2:
        
        case 3:
        
        case 4:
        
        case 5:
        
        case 6:
        
        case 7:
        
        case 8:
        
        case 9:
        
        case 10:
        
        case 11:
        
        case 12:
        
        case 13:
        
        case 14:
        
        case 15:
        
        case 16:
        
        case 17:
        
        case 18:
        
        case 19:
        
        case 20:
        
        case 21:
        
        case 22:
        
        case 23:
        
        case 24:
        
        case 25:
        
        case 26:
        
        case 27:
        
        case 28:
        
        case 29:
        
        case 30:
        
        case 31:
        
        case 32:
        
        case 33:
        
        case 34:
        
        case 35:
        
        case 36:
        
        case 37:
        
        case 38:
        
        case 39:
        
        case 40:
        
        case 41:
        
        case 42:
        
        case 43:
        
        case 44:
        
        case 45:
        
        case 46:
        
        case 47:
        
        case 48:
        
        case 49:
        
        case 50:
        
        case 51:
        
        case 52:
        
        case 53:
        
        case 54:
        
        case 55:
        
        case 56:
        
        case 57:
        
        case 58:
        
        case 59:
        
        case 60:
        
        case 61:
        
        case 62:
        
        case 63:
        
        case 64:
        
        case 65:
        
        case 66:
        
        case 67:
        
        case 68:
        
        case 69:
        
        case 70:
        
        case 71:
        
        case 72:
        
        case 73:
        
        case 74:
        
        case 75:
        
        case 76:
        
        case 77:
        
        case 78:
        
        case 79:
        
        case 80:
        
        case 81:
        
        case 82:
        
        case 83:
        
        case 84:
        
        case 85:
        
        case 86:
        
        case 87:
        
        case 88:
        
        case 89:
        
        case 90:
        
        case 91:
        
        case 92:
        
        case 93:
        
        case 94:
        
        case 95:
        
        case 96:
        
        case 97:
        
        case 98:
        
        case 99:
        
        case 100:
        
        case 101:
        
        case 102:
        
        case 103:
        
        case 104:
        
        case 105:
        
        case 106:
        
        case 107:
        
        case 108:
        
        case 109:
        
        case 110:
        
        case 111:
        
        case 112:
        
        case 113:
        
        case 114:
        
        case 115:
        
        case 116:
        
        case 117:
        
        case 118:
        
        case 119:
        
        case 120:
        
        case 121:
        
        case 122:
        
        case 123:
        
        case 124:
        
        case 125:
        
        case 126:
        
        case 127:
        
        case 128:
        
        case 129:
        
        case 130:
        
        case 131:
        
        case 132:
        
        case 133:
        
        case 134:
        
        case 135:
        
        case 136:
        
        case 137:
        
        case 138:
        
        case 139:
        
        case 140:
        
        case 141:
        
        case 142:
        
        case 143:
        
        case 144:
        
        case 145:
        
        case 146:
        
        case 147:
        
        case 148:
        
        case 149:
        
        case 150:
        
        case 151:
        
        case 152:
        
        case 153:
        
        case 154:
        
        case 155:
        
        case 156:
        
        case 157:
        
        case 158:
        
        case 159:
        
        case 160:
        
        case 161:
        
        case 162:
        
        case 163:
        
        case 164:
        
        case 165:
        
        case 166:
        
        case 167:
        
        case 168:
        
        case 169:
        
        case 170:
        
        case 171:
        
        case 172:
        
        case 173:
        
        case 174:
        
        case 175:
        
        case 176:
        
        case 177:
        
        case 178:
        
        case 179:
        
        case 180:
        
        case 181:
        
        case 182:
        
        case 183:
        
        case 184:
        
        case 185:
        
        case 186:
        
        case 187:
        
        case 188:
        
        case 189:
        
        case 190:
        
        case 191:
        
        case 192:
        
        case 193:
        
        case 194:
        
        case 195:
        
        case 196:
        
        case 197:
        
        case 198:
        
        case 199:
        
        case 200:
        
        case 201:
        
        case 202:
        
        case 203:
        
        case 204:
        
        case 205:
        
        case 206:
        
        case 207:
        
        case 208:
        
        case 209:
        
        case 210:
        
        case 211:
        
        case 212:
        
        case 213:
        
        case 214:
        
        case 215:
        
        case 216:
        
        case 217:
        
        case 218:
        
        case 219:
        
        case 220:
        
        case 221:
        
        case 222:
        
        case 223:
        
        case 224:
        
        case 225:
        
        case 226:
        
        case 227:
        
        case 228:
        
        case 229:
        
        case 230:
        
        case 231:
        
        case 232:
        
        case 233:
        
        case 234:
        
        case 235:
        
        case 236:
        
        case 237:
        
        case 238:
        
        case 239:
        
        case 240:
        
        case 241:
        
        case 242:
        
        case 243:
        
        case 244:
        
        case 245:
        
        case 246:
        
        case 247:
        
        case 248:
        
        case 249:
        
        case 250:
        
        case 251:
        
        case 252:
        
        case 253:
        
        case 254:
        
        default:
          break;
      } 
      byte b1 = 120;
      int j = (paramInt2 & 0xFF) - b1;
      if (j < 0)
        j += 256; 
      int k = ((paramInt2 & 0xFFFF) >>> 8) - b1;
      if (k < 0)
        k += 256; 
      for (byte b2 = 0; b2 < arrayOfChar.length; b2++) {
        int m = b2 % 2;
        if (m == 0) {
          arrayOfChar[b2] = (char)(arrayOfChar[b2] ^ j);
          j = ((j >>> 3 | j << 5) ^ arrayOfChar[b2]) & 0xFF;
        } else {
          arrayOfChar[b2] = (char)(arrayOfChar[b2] ^ k);
          k = ((k >>> 3 | k << 5) ^ arrayOfChar[b2]) & 0xFF;
        } 
      } 
      b[i] = (new String(arrayOfChar)).intern();
    } 
    return b[i];
  }
}


/* Location:              C:\Program Files\BurpSuitePro\burpsuite_pro.jar!\burp\Zbw5.class
 * Java compiler version: 21 (65.0)
 * JD-Core Version:       1.1.3
 */