package burp;

public class Zbxs implements Zmky {
  private final Zeun Zs = new Zeun();
  
  private boolean ZS;
  
  private boolean ZO;
  
  public void ZI(Ztu8 paramZtu8) {
    // Byte code:
    //   0: invokestatic ZG : ()[Ljava/lang/String;
    //   3: astore_2
    //   4: aload_0
    //   5: getfield ZO : Z
    //   8: ifeq -> 12
    //   11: return
    //   12: aload_0
    //   13: getfield ZS : Z
    //   16: ifeq -> 64
    //   19: aload_1
    //   20: invokestatic Za : (Lburp/Ztu8;)Z
    //   23: ifeq -> 40
    //   26: aload_0
    //   27: iconst_0
    //   28: putfield ZS : Z
    //   31: aload_0
    //   32: iconst_1
    //   33: putfield ZO : Z
    //   36: aload_2
    //   37: ifnull -> 76
    //   40: aload_1
    //   41: invokestatic ZS : (Lburp/Ztu8;)Z
    //   44: ifeq -> 76
    //   47: aload_0
    //   48: getfield Zs : Lburp/Zeun;
    //   51: aload_1
    //   52: invokeinterface Zlv : ()Ljava/lang/String;
    //   57: invokevirtual Zk : (Ljava/lang/String;)V
    //   60: aload_2
    //   61: ifnull -> 76
    //   64: aload_1
    //   65: invokestatic ZC : (Lburp/Ztu8;)Z
    //   68: ifeq -> 76
    //   71: aload_0
    //   72: iconst_1
    //   73: putfield ZS : Z
    //   76: return
  }
  
  public void ZW(Zt82 paramZt82) {
    this.Zs.Zv(paramZt82, Zq());
  }
  
  public Zlug Zq() {
    return Zlug.FIRST_HEADER_TAG;
  }
}


/* Location:              C:\Program Files\BurpSuitePro\burpsuite_pro.jar!\burp\Zbxs.class
 * Java compiler version: 21 (65.0)
 * JD-Core Version:       1.1.3
 */