package burp;

class Zbz7 {
  static final byte[] Zd;
  
  int ZK;
  
  int ZH;
  
  int ZQ;
  
  long Zp;
  
  long Zc;
  
  long ZY;
  
  long Zg;
  
  long ZS;
  
  long Zh;
  
  long Zf;
  
  long Zq;
  
  long Zn;
  
  int Zm;
  
  int Zi;
  
  int Zy;
  
  int ZU;
  
  int ZI;
  
  int ZB;
  
  long Zr;
  
  long ZA;
  
  long ZX;
  
  long ZF;
  
  int Zw;
  
  int Za;
  
  long Zx;
  
  long ZV;
  
  long ZW;
  
  long Z_;
  
  long Zb;
  
  long Zk;
  
  Zgjh[] ZE;
  
  private static final String a;
  
  Zbz7(Zg08 paramZg08) throws Exception {
    // Byte code:
    //   0: aload_0
    //   1: invokespecial <init> : ()V
    //   4: aload_0
    //   5: aload_1
    //   6: invokevirtual ZZ : ()I
    //   9: putfield ZK : I
    //   12: invokestatic ZL : ()[I
    //   15: aload_0
    //   16: aload_1
    //   17: invokevirtual Zl : ()I
    //   20: putfield ZH : I
    //   23: aload_0
    //   24: aload_1
    //   25: invokevirtual Zl : ()I
    //   28: putfield ZQ : I
    //   31: aload_0
    //   32: aload_1
    //   33: invokevirtual Zh : ()J
    //   36: putfield Zp : J
    //   39: astore_2
    //   40: aload_0
    //   41: aload_1
    //   42: invokevirtual Zh : ()J
    //   45: putfield Zc : J
    //   48: aload_0
    //   49: aload_1
    //   50: invokevirtual Zh : ()J
    //   53: putfield ZY : J
    //   56: aload_0
    //   57: aload_1
    //   58: invokevirtual Zh : ()J
    //   61: putfield Zg : J
    //   64: aload_0
    //   65: aload_1
    //   66: invokevirtual Zh : ()J
    //   69: putfield ZS : J
    //   72: aload_0
    //   73: getfield ZK : I
    //   76: sipush #267
    //   79: if_icmpne -> 283
    //   82: aload_0
    //   83: aload_1
    //   84: invokevirtual Zh : ()J
    //   87: putfield Zh : J
    //   90: aload_0
    //   91: aload_1
    //   92: invokevirtual Zh : ()J
    //   95: putfield Zf : J
    //   98: aload_0
    //   99: aload_1
    //   100: invokevirtual Zh : ()J
    //   103: putfield Zq : J
    //   106: aload_0
    //   107: aload_1
    //   108: invokevirtual Zh : ()J
    //   111: putfield Zn : J
    //   114: aload_0
    //   115: aload_1
    //   116: invokevirtual ZZ : ()I
    //   119: putfield Zm : I
    //   122: aload_0
    //   123: aload_1
    //   124: invokevirtual ZZ : ()I
    //   127: putfield Zi : I
    //   130: aload_0
    //   131: aload_1
    //   132: invokevirtual ZZ : ()I
    //   135: putfield Zy : I
    //   138: aload_0
    //   139: aload_1
    //   140: invokevirtual ZZ : ()I
    //   143: putfield ZU : I
    //   146: aload_0
    //   147: aload_1
    //   148: invokevirtual ZZ : ()I
    //   151: putfield ZI : I
    //   154: aload_0
    //   155: aload_1
    //   156: invokevirtual ZZ : ()I
    //   159: putfield ZB : I
    //   162: aload_0
    //   163: aload_1
    //   164: invokevirtual Zh : ()J
    //   167: putfield Zr : J
    //   170: aload_0
    //   171: aload_1
    //   172: invokevirtual Zh : ()J
    //   175: putfield ZA : J
    //   178: aload_0
    //   179: aload_1
    //   180: invokevirtual Zh : ()J
    //   183: putfield ZX : J
    //   186: aload_0
    //   187: aload_1
    //   188: invokevirtual Zh : ()J
    //   191: putfield ZF : J
    //   194: aload_0
    //   195: aload_1
    //   196: invokevirtual ZZ : ()I
    //   199: putfield Zw : I
    //   202: aload_0
    //   203: aload_1
    //   204: invokevirtual ZZ : ()I
    //   207: putfield Za : I
    //   210: aload_0
    //   211: aload_1
    //   212: invokevirtual Zh : ()J
    //   215: putfield Zx : J
    //   218: aload_0
    //   219: aload_1
    //   220: invokevirtual Zh : ()J
    //   223: putfield ZV : J
    //   226: aload_0
    //   227: aload_1
    //   228: invokevirtual Zh : ()J
    //   231: putfield ZW : J
    //   234: aload_0
    //   235: aload_1
    //   236: invokevirtual Zh : ()J
    //   239: putfield Z_ : J
    //   242: aload_0
    //   243: aload_1
    //   244: invokevirtual Zh : ()J
    //   247: putfield Zb : J
    //   250: aload_0
    //   251: aload_1
    //   252: invokevirtual Zh : ()J
    //   255: putfield Zk : J
    //   258: aload_2
    //   259: ifnonnull -> 487
    //   262: goto -> 269
    //   265: invokestatic a : (Ljava/lang/Exception;)Ljava/lang/Exception;
    //   268: athrow
    //   269: iconst_1
    //   270: anewarray burp/Zbqc
    //   273: invokestatic Zr : ([Lburp/Zbqc;)V
    //   276: goto -> 283
    //   279: invokestatic a : (Ljava/lang/Exception;)Ljava/lang/Exception;
    //   282: athrow
    //   283: aload_0
    //   284: getfield ZK : I
    //   287: sipush #523
    //   290: if_icmpne -> 472
    //   293: aload_0
    //   294: aload_1
    //   295: invokevirtual ZF : ()J
    //   298: putfield Zf : J
    //   301: aload_0
    //   302: aload_1
    //   303: invokevirtual Zh : ()J
    //   306: putfield Zq : J
    //   309: aload_0
    //   310: aload_1
    //   311: invokevirtual Zh : ()J
    //   314: putfield Zn : J
    //   317: aload_0
    //   318: aload_1
    //   319: invokevirtual ZZ : ()I
    //   322: putfield Zm : I
    //   325: aload_0
    //   326: aload_1
    //   327: invokevirtual ZZ : ()I
    //   330: putfield Zi : I
    //   333: aload_0
    //   334: aload_1
    //   335: invokevirtual ZZ : ()I
    //   338: putfield Zy : I
    //   341: aload_0
    //   342: aload_1
    //   343: invokevirtual ZZ : ()I
    //   346: putfield ZU : I
    //   349: aload_0
    //   350: aload_1
    //   351: invokevirtual ZZ : ()I
    //   354: putfield ZI : I
    //   357: aload_0
    //   358: aload_1
    //   359: invokevirtual ZZ : ()I
    //   362: putfield ZB : I
    //   365: aload_0
    //   366: aload_1
    //   367: invokevirtual Zh : ()J
    //   370: putfield Zr : J
    //   373: aload_0
    //   374: aload_1
    //   375: invokevirtual Zh : ()J
    //   378: putfield ZA : J
    //   381: aload_0
    //   382: aload_1
    //   383: invokevirtual Zh : ()J
    //   386: putfield ZX : J
    //   389: aload_0
    //   390: aload_1
    //   391: invokevirtual Zh : ()J
    //   394: putfield ZF : J
    //   397: aload_0
    //   398: aload_1
    //   399: invokevirtual ZZ : ()I
    //   402: putfield Zw : I
    //   405: aload_0
    //   406: aload_1
    //   407: invokevirtual ZZ : ()I
    //   410: putfield Za : I
    //   413: aload_0
    //   414: aload_1
    //   415: invokevirtual ZF : ()J
    //   418: putfield Zx : J
    //   421: aload_0
    //   422: aload_1
    //   423: invokevirtual ZF : ()J
    //   426: putfield ZV : J
    //   429: aload_0
    //   430: aload_1
    //   431: invokevirtual ZF : ()J
    //   434: putfield ZW : J
    //   437: aload_0
    //   438: aload_1
    //   439: invokevirtual ZF : ()J
    //   442: putfield Z_ : J
    //   445: aload_0
    //   446: aload_1
    //   447: invokevirtual Zh : ()J
    //   450: putfield Zb : J
    //   453: aload_0
    //   454: aload_1
    //   455: invokevirtual Zh : ()J
    //   458: putfield Zk : J
    //   461: aload_2
    //   462: ifnonnull -> 487
    //   465: goto -> 472
    //   468: invokestatic a : (Ljava/lang/Exception;)Ljava/lang/Exception;
    //   471: athrow
    //   472: new java/lang/Exception
    //   475: dup
    //   476: getstatic burp/Zbz7.a : Ljava/lang/String;
    //   479: invokespecial <init> : (Ljava/lang/String;)V
    //   482: athrow
    //   483: invokestatic a : (Ljava/lang/Exception;)Ljava/lang/Exception;
    //   486: athrow
    //   487: aload_0
    //   488: aload_0
    //   489: getfield Zk : J
    //   492: l2i
    //   493: anewarray burp/Zgjh
    //   496: putfield ZE : [Lburp/Zgjh;
    //   499: iconst_0
    //   500: istore_3
    //   501: iload_3
    //   502: i2l
    //   503: aload_0
    //   504: getfield Zk : J
    //   507: lcmp
    //   508: ifge -> 532
    //   511: aload_0
    //   512: getfield ZE : [Lburp/Zgjh;
    //   515: iload_3
    //   516: new burp/Zgjh
    //   519: dup
    //   520: aload_1
    //   521: invokespecial <init> : (Lburp/Zg08;)V
    //   524: aastore
    //   525: iinc #3, 1
    //   528: aload_2
    //   529: ifnonnull -> 501
    //   532: return
    // Exception table:
    //   from	to	target	type
    //   40	262	265	java/lang/Exception
    //   82	276	279	java/lang/Exception
    //   283	465	468	java/lang/Exception
    //   293	483	483	java/lang/Exception
  }
  
  static {
    // Byte code:
    //   0: bipush #85
    //   2: ldc '~PFn9|\\bb<m'
    //   4: iconst_m1
    //   5: goto -> 14
    //   8: putstatic burp/Zbz7.a : Ljava/lang/String;
    //   11: goto -> 154
    //   14: dup_x2
    //   15: pop
    //   16: invokevirtual toCharArray : ()[C
    //   19: dup_x1
    //   20: arraylength
    //   21: dup_x2
    //   22: pop
    //   23: iconst_0
    //   24: istore_0
    //   25: dup2_x1
    //   26: pop2
    //   27: dup_x2
    //   28: iconst_1
    //   29: if_icmpgt -> 128
    //   32: dup2
    //   33: swap
    //   34: iload_0
    //   35: dup2_x1
    //   36: caload
    //   37: swap
    //   38: iload_0
    //   39: bipush #7
    //   41: irem
    //   42: tableswitch default -> 110, 0 -> 80, 1 -> 85, 2 -> 90, 3 -> 95, 4 -> 100, 5 -> 105
    //   80: bipush #41
    //   82: goto -> 112
    //   85: bipush #74
    //   87: goto -> 112
    //   90: bipush #97
    //   92: goto -> 112
    //   95: bipush #51
    //   97: goto -> 112
    //   100: bipush #63
    //   102: goto -> 112
    //   105: bipush #90
    //   107: goto -> 112
    //   110: bipush #11
    //   112: ixor
    //   113: ixor
    //   114: i2c
    //   115: castore
    //   116: iinc #0, 1
    //   119: dup
    //   120: ifne -> 128
    //   123: dup2
    //   124: dup_x1
    //   125: goto -> 35
    //   128: dup2_x1
    //   129: pop2
    //   130: dup_x2
    //   131: iload_0
    //   132: if_icmpgt -> 32
    //   135: pop
    //   136: new java/lang/String
    //   139: dup_x1
    //   140: swap
    //   141: invokespecial <init> : ([C)V
    //   144: invokevirtual intern : ()Ljava/lang/String;
    //   147: swap
    //   148: pop
    //   149: swap
    //   150: pop
    //   151: goto -> 8
    //   154: iconst_4
    //   155: newarray byte
    //   157: dup
    //   158: iconst_0
    //   159: bipush #80
    //   161: bastore
    //   162: dup
    //   163: iconst_1
    //   164: bipush #69
    //   166: bastore
    //   167: dup
    //   168: iconst_2
    //   169: iconst_0
    //   170: bastore
    //   171: dup
    //   172: iconst_3
    //   173: iconst_0
    //   174: bastore
    //   175: putstatic burp/Zbz7.Zd : [B
    //   178: return
  }
  
  private static Exception a(Exception paramException) {
    return paramException;
  }
}


/* Location:              C:\Program Files\BurpSuitePro\burpsuite_pro.jar!\burp\Zbz7.class
 * Java compiler version: 21 (65.0)
 * JD-Core Version:       1.1.3
 */