package burp;

import java.math.BigInteger;

class Zbz_ extends ClassLoader {
  static String ZW;
  
  static Object ZU;
  
  private static final String[] a;
  
  private static final String[] b;
  
  static boolean ZM(Object[] paramArrayOfObject, Object paramObject) throws Throwable {
    // Byte code:
    //   0: invokestatic ZK : ()Z
    //   3: istore_2
    //   4: new java/lang/StringBuilder
    //   7: dup
    //   8: invokespecial <init> : ()V
    //   11: astore_3
    //   12: iconst_0
    //   13: istore #4
    //   15: iload #4
    //   17: bipush #32
    //   19: if_icmpge -> 1355
    //   22: iload #4
    //   24: tableswitch default -> 1348, 0 -> 168, 1 -> 205, 2 -> 242, 3 -> 279, 4 -> 316, 5 -> 353, 6 -> 390, 7 -> 427, 8 -> 464, 9 -> 501, 10 -> 538, 11 -> 575, 12 -> 612, 13 -> 649, 14 -> 686, 15 -> 723, 16 -> 760, 17 -> 797, 18 -> 834, 19 -> 871, 20 -> 908, 21 -> 945, 22 -> 982, 23 -> 1019, 24 -> 1056, 25 -> 1093, 26 -> 1130, 27 -> 1167, 28 -> 1204, 29 -> 1241, 30 -> 1278, 31 -> 1315
    //   168: aload_3
    //   169: getstatic burp/Zzmo.Zx : Ljava/lang/String;
    //   172: getstatic burp/Zsjo.ZB : Ljava/lang/Object;
    //   175: checkcast java/math/BigInteger
    //   178: invokevirtual intValue : ()I
    //   181: bipush #32
    //   183: irem
    //   184: invokestatic abs : (I)I
    //   187: invokevirtual charAt : (I)C
    //   190: invokevirtual append : (C)Ljava/lang/StringBuilder;
    //   193: pop
    //   194: iload_2
    //   195: ifeq -> 1348
    //   198: goto -> 205
    //   201: invokestatic a : (Ljava/lang/Throwable;)Ljava/lang/Throwable;
    //   204: athrow
    //   205: aload_3
    //   206: getstatic burp/Zsts.ZI : Ljava/lang/String;
    //   209: getstatic burp/Ztgj.ZY : Ljava/lang/Object;
    //   212: checkcast java/math/BigInteger
    //   215: invokevirtual intValue : ()I
    //   218: bipush #32
    //   220: irem
    //   221: invokestatic abs : (I)I
    //   224: invokevirtual charAt : (I)C
    //   227: invokevirtual append : (C)Ljava/lang/StringBuilder;
    //   230: pop
    //   231: iload_2
    //   232: ifeq -> 1348
    //   235: goto -> 242
    //   238: invokestatic a : (Ljava/lang/Throwable;)Ljava/lang/Throwable;
    //   241: athrow
    //   242: aload_3
    //   243: getstatic burp/Ztip.Z_ : Ljava/lang/String;
    //   246: getstatic burp/Zmu6.Zb : Ljava/lang/Object;
    //   249: checkcast java/math/BigInteger
    //   252: invokevirtual intValue : ()I
    //   255: bipush #32
    //   257: irem
    //   258: invokestatic abs : (I)I
    //   261: invokevirtual charAt : (I)C
    //   264: invokevirtual append : (C)Ljava/lang/StringBuilder;
    //   267: pop
    //   268: iload_2
    //   269: ifeq -> 1348
    //   272: goto -> 279
    //   275: invokestatic a : (Ljava/lang/Throwable;)Ljava/lang/Throwable;
    //   278: athrow
    //   279: aload_3
    //   280: getstatic burp/Zbj.ZD : Ljava/lang/String;
    //   283: getstatic burp/Zstf.ZA : Ljava/lang/Object;
    //   286: checkcast java/math/BigInteger
    //   289: invokevirtual intValue : ()I
    //   292: bipush #32
    //   294: irem
    //   295: invokestatic abs : (I)I
    //   298: invokevirtual charAt : (I)C
    //   301: invokevirtual append : (C)Ljava/lang/StringBuilder;
    //   304: pop
    //   305: iload_2
    //   306: ifeq -> 1348
    //   309: goto -> 316
    //   312: invokestatic a : (Ljava/lang/Throwable;)Ljava/lang/Throwable;
    //   315: athrow
    //   316: aload_3
    //   317: getstatic burp/Ztgj.Zw : Ljava/lang/String;
    //   320: getstatic burp/Zrn0.ZE : Ljava/lang/Object;
    //   323: checkcast java/math/BigInteger
    //   326: invokevirtual intValue : ()I
    //   329: bipush #32
    //   331: irem
    //   332: invokestatic abs : (I)I
    //   335: invokevirtual charAt : (I)C
    //   338: invokevirtual append : (C)Ljava/lang/StringBuilder;
    //   341: pop
    //   342: iload_2
    //   343: ifeq -> 1348
    //   346: goto -> 353
    //   349: invokestatic a : (Ljava/lang/Throwable;)Ljava/lang/Throwable;
    //   352: athrow
    //   353: aload_3
    //   354: getstatic burp/Zb0s.Zi : Ljava/lang/String;
    //   357: getstatic burp/Ztp.Zp : Ljava/lang/Object;
    //   360: checkcast java/math/BigInteger
    //   363: invokevirtual intValue : ()I
    //   366: bipush #32
    //   368: irem
    //   369: invokestatic abs : (I)I
    //   372: invokevirtual charAt : (I)C
    //   375: invokevirtual append : (C)Ljava/lang/StringBuilder;
    //   378: pop
    //   379: iload_2
    //   380: ifeq -> 1348
    //   383: goto -> 390
    //   386: invokestatic a : (Ljava/lang/Throwable;)Ljava/lang/Throwable;
    //   389: athrow
    //   390: aload_3
    //   391: getstatic burp/Zzco.Zu : Ljava/lang/String;
    //   394: getstatic burp/Zlot.ZJ : Ljava/lang/Object;
    //   397: checkcast java/math/BigInteger
    //   400: invokevirtual intValue : ()I
    //   403: bipush #32
    //   405: irem
    //   406: invokestatic abs : (I)I
    //   409: invokevirtual charAt : (I)C
    //   412: invokevirtual append : (C)Ljava/lang/StringBuilder;
    //   415: pop
    //   416: iload_2
    //   417: ifeq -> 1348
    //   420: goto -> 427
    //   423: invokestatic a : (Ljava/lang/Throwable;)Ljava/lang/Throwable;
    //   426: athrow
    //   427: aload_3
    //   428: getstatic burp/Zva.Zi : Ljava/lang/String;
    //   431: getstatic burp/Zxd4.Zt : Ljava/lang/Object;
    //   434: checkcast java/math/BigInteger
    //   437: invokevirtual intValue : ()I
    //   440: bipush #32
    //   442: irem
    //   443: invokestatic abs : (I)I
    //   446: invokevirtual charAt : (I)C
    //   449: invokevirtual append : (C)Ljava/lang/StringBuilder;
    //   452: pop
    //   453: iload_2
    //   454: ifeq -> 1348
    //   457: goto -> 464
    //   460: invokestatic a : (Ljava/lang/Throwable;)Ljava/lang/Throwable;
    //   463: athrow
    //   464: aload_3
    //   465: getstatic burp/Zrly.ZS : Ljava/lang/String;
    //   468: getstatic burp/Zlkm.ZQ : Ljava/lang/Object;
    //   471: checkcast java/math/BigInteger
    //   474: invokevirtual intValue : ()I
    //   477: bipush #32
    //   479: irem
    //   480: invokestatic abs : (I)I
    //   483: invokevirtual charAt : (I)C
    //   486: invokevirtual append : (C)Ljava/lang/StringBuilder;
    //   489: pop
    //   490: iload_2
    //   491: ifeq -> 1348
    //   494: goto -> 501
    //   497: invokestatic a : (Ljava/lang/Throwable;)Ljava/lang/Throwable;
    //   500: athrow
    //   501: aload_3
    //   502: getstatic burp/Zgjs.Zp : Ljava/lang/String;
    //   505: getstatic burp/Zmze.Zo : Ljava/lang/Object;
    //   508: checkcast java/math/BigInteger
    //   511: invokevirtual intValue : ()I
    //   514: bipush #32
    //   516: irem
    //   517: invokestatic abs : (I)I
    //   520: invokevirtual charAt : (I)C
    //   523: invokevirtual append : (C)Ljava/lang/StringBuilder;
    //   526: pop
    //   527: iload_2
    //   528: ifeq -> 1348
    //   531: goto -> 538
    //   534: invokestatic a : (Ljava/lang/Throwable;)Ljava/lang/Throwable;
    //   537: athrow
    //   538: aload_3
    //   539: getstatic burp/Zrn0.Zd : Ljava/lang/String;
    //   542: getstatic burp/Zb0s.Zv : Ljava/lang/Object;
    //   545: checkcast java/math/BigInteger
    //   548: invokevirtual intValue : ()I
    //   551: bipush #32
    //   553: irem
    //   554: invokestatic abs : (I)I
    //   557: invokevirtual charAt : (I)C
    //   560: invokevirtual append : (C)Ljava/lang/StringBuilder;
    //   563: pop
    //   564: iload_2
    //   565: ifeq -> 1348
    //   568: goto -> 575
    //   571: invokestatic a : (Ljava/lang/Throwable;)Ljava/lang/Throwable;
    //   574: athrow
    //   575: aload_3
    //   576: getstatic burp/Zmgl.Zh : Ljava/lang/String;
    //   579: getstatic burp/Zb4m.Zp : Ljava/lang/Object;
    //   582: checkcast java/math/BigInteger
    //   585: invokevirtual intValue : ()I
    //   588: bipush #32
    //   590: irem
    //   591: invokestatic abs : (I)I
    //   594: invokevirtual charAt : (I)C
    //   597: invokevirtual append : (C)Ljava/lang/StringBuilder;
    //   600: pop
    //   601: iload_2
    //   602: ifeq -> 1348
    //   605: goto -> 612
    //   608: invokestatic a : (Ljava/lang/Throwable;)Ljava/lang/Throwable;
    //   611: athrow
    //   612: aload_3
    //   613: getstatic burp/Zlbt.ZE : Ljava/lang/String;
    //   616: getstatic burp/Zzco.ZC : Ljava/lang/Object;
    //   619: checkcast java/math/BigInteger
    //   622: invokevirtual intValue : ()I
    //   625: bipush #32
    //   627: irem
    //   628: invokestatic abs : (I)I
    //   631: invokevirtual charAt : (I)C
    //   634: invokevirtual append : (C)Ljava/lang/StringBuilder;
    //   637: pop
    //   638: iload_2
    //   639: ifeq -> 1348
    //   642: goto -> 649
    //   645: invokestatic a : (Ljava/lang/Throwable;)Ljava/lang/Throwable;
    //   648: athrow
    //   649: aload_3
    //   650: getstatic burp/Zrka.Zy : Ljava/lang/String;
    //   653: getstatic burp/Zxf8.Zz : Ljava/lang/Object;
    //   656: checkcast java/math/BigInteger
    //   659: invokevirtual intValue : ()I
    //   662: bipush #32
    //   664: irem
    //   665: invokestatic abs : (I)I
    //   668: invokevirtual charAt : (I)C
    //   671: invokevirtual append : (C)Ljava/lang/StringBuilder;
    //   674: pop
    //   675: iload_2
    //   676: ifeq -> 1348
    //   679: goto -> 686
    //   682: invokestatic a : (Ljava/lang/Throwable;)Ljava/lang/Throwable;
    //   685: athrow
    //   686: aload_3
    //   687: getstatic burp/Zlo4.Zn : Ljava/lang/String;
    //   690: getstatic burp/Zrka.Zr : Ljava/lang/Object;
    //   693: checkcast java/math/BigInteger
    //   696: invokevirtual intValue : ()I
    //   699: bipush #32
    //   701: irem
    //   702: invokestatic abs : (I)I
    //   705: invokevirtual charAt : (I)C
    //   708: invokevirtual append : (C)Ljava/lang/StringBuilder;
    //   711: pop
    //   712: iload_2
    //   713: ifeq -> 1348
    //   716: goto -> 723
    //   719: invokestatic a : (Ljava/lang/Throwable;)Ljava/lang/Throwable;
    //   722: athrow
    //   723: aload_3
    //   724: getstatic burp/Zg8v.Zd : Ljava/lang/String;
    //   727: getstatic burp/Zlxs.ZK : Ljava/lang/Object;
    //   730: checkcast java/math/BigInteger
    //   733: invokevirtual intValue : ()I
    //   736: bipush #32
    //   738: irem
    //   739: invokestatic abs : (I)I
    //   742: invokevirtual charAt : (I)C
    //   745: invokevirtual append : (C)Ljava/lang/StringBuilder;
    //   748: pop
    //   749: iload_2
    //   750: ifeq -> 1348
    //   753: goto -> 760
    //   756: invokestatic a : (Ljava/lang/Throwable;)Ljava/lang/Throwable;
    //   759: athrow
    //   760: aload_3
    //   761: getstatic burp/Zgjs.Zp : Ljava/lang/String;
    //   764: getstatic burp/Zrly.ZB : Ljava/lang/Object;
    //   767: checkcast java/math/BigInteger
    //   770: invokevirtual intValue : ()I
    //   773: bipush #32
    //   775: irem
    //   776: invokestatic abs : (I)I
    //   779: invokevirtual charAt : (I)C
    //   782: invokevirtual append : (C)Ljava/lang/StringBuilder;
    //   785: pop
    //   786: iload_2
    //   787: ifeq -> 1348
    //   790: goto -> 797
    //   793: invokestatic a : (Ljava/lang/Throwable;)Ljava/lang/Throwable;
    //   796: athrow
    //   797: aload_3
    //   798: getstatic burp/Zkk2.ZI : Ljava/lang/String;
    //   801: getstatic burp/Zbz_.ZU : Ljava/lang/Object;
    //   804: checkcast java/math/BigInteger
    //   807: invokevirtual intValue : ()I
    //   810: bipush #32
    //   812: irem
    //   813: invokestatic abs : (I)I
    //   816: invokevirtual charAt : (I)C
    //   819: invokevirtual append : (C)Ljava/lang/StringBuilder;
    //   822: pop
    //   823: iload_2
    //   824: ifeq -> 1348
    //   827: goto -> 834
    //   830: invokestatic a : (Ljava/lang/Throwable;)Ljava/lang/Throwable;
    //   833: athrow
    //   834: aload_3
    //   835: getstatic burp/Zrpm.ZG : Ljava/lang/String;
    //   838: getstatic burp/Zgre.ZD : Ljava/lang/Object;
    //   841: checkcast java/math/BigInteger
    //   844: invokevirtual intValue : ()I
    //   847: bipush #32
    //   849: irem
    //   850: invokestatic abs : (I)I
    //   853: invokevirtual charAt : (I)C
    //   856: invokevirtual append : (C)Ljava/lang/StringBuilder;
    //   859: pop
    //   860: iload_2
    //   861: ifeq -> 1348
    //   864: goto -> 871
    //   867: invokestatic a : (Ljava/lang/Throwable;)Ljava/lang/Throwable;
    //   870: athrow
    //   871: aload_3
    //   872: getstatic burp/Zb2p.ZV : Ljava/lang/String;
    //   875: getstatic burp/Zg7w.Zy : Ljava/lang/Object;
    //   878: checkcast java/math/BigInteger
    //   881: invokevirtual intValue : ()I
    //   884: bipush #32
    //   886: irem
    //   887: invokestatic abs : (I)I
    //   890: invokevirtual charAt : (I)C
    //   893: invokevirtual append : (C)Ljava/lang/StringBuilder;
    //   896: pop
    //   897: iload_2
    //   898: ifeq -> 1348
    //   901: goto -> 908
    //   904: invokestatic a : (Ljava/lang/Throwable;)Ljava/lang/Throwable;
    //   907: athrow
    //   908: aload_3
    //   909: getstatic burp/Zgja.Zb : Ljava/lang/String;
    //   912: getstatic burp/Zgjs.Za : Ljava/lang/Object;
    //   915: checkcast java/math/BigInteger
    //   918: invokevirtual intValue : ()I
    //   921: bipush #32
    //   923: irem
    //   924: invokestatic abs : (I)I
    //   927: invokevirtual charAt : (I)C
    //   930: invokevirtual append : (C)Ljava/lang/StringBuilder;
    //   933: pop
    //   934: iload_2
    //   935: ifeq -> 1348
    //   938: goto -> 945
    //   941: invokestatic a : (Ljava/lang/Throwable;)Ljava/lang/Throwable;
    //   944: athrow
    //   945: aload_3
    //   946: getstatic burp/Zlbt.ZE : Ljava/lang/String;
    //   949: getstatic burp/Zb0s.Zv : Ljava/lang/Object;
    //   952: checkcast java/math/BigInteger
    //   955: invokevirtual intValue : ()I
    //   958: bipush #32
    //   960: irem
    //   961: invokestatic abs : (I)I
    //   964: invokevirtual charAt : (I)C
    //   967: invokevirtual append : (C)Ljava/lang/StringBuilder;
    //   970: pop
    //   971: iload_2
    //   972: ifeq -> 1348
    //   975: goto -> 982
    //   978: invokestatic a : (Ljava/lang/Throwable;)Ljava/lang/Throwable;
    //   981: athrow
    //   982: aload_3
    //   983: getstatic burp/Zmze.ZO : Ljava/lang/String;
    //   986: getstatic burp/Zle6.ZM : Ljava/lang/Object;
    //   989: checkcast java/math/BigInteger
    //   992: invokevirtual intValue : ()I
    //   995: bipush #32
    //   997: irem
    //   998: invokestatic abs : (I)I
    //   1001: invokevirtual charAt : (I)C
    //   1004: invokevirtual append : (C)Ljava/lang/StringBuilder;
    //   1007: pop
    //   1008: iload_2
    //   1009: ifeq -> 1348
    //   1012: goto -> 1019
    //   1015: invokestatic a : (Ljava/lang/Throwable;)Ljava/lang/Throwable;
    //   1018: athrow
    //   1019: aload_3
    //   1020: getstatic burp/Zkq9.ZO : Ljava/lang/String;
    //   1023: getstatic burp/Zb0s.Zv : Ljava/lang/Object;
    //   1026: checkcast java/math/BigInteger
    //   1029: invokevirtual intValue : ()I
    //   1032: bipush #32
    //   1034: irem
    //   1035: invokestatic abs : (I)I
    //   1038: invokevirtual charAt : (I)C
    //   1041: invokevirtual append : (C)Ljava/lang/StringBuilder;
    //   1044: pop
    //   1045: iload_2
    //   1046: ifeq -> 1348
    //   1049: goto -> 1056
    //   1052: invokestatic a : (Ljava/lang/Throwable;)Ljava/lang/Throwable;
    //   1055: athrow
    //   1056: aload_3
    //   1057: getstatic burp/Zkgp.ZM : Ljava/lang/String;
    //   1060: getstatic burp/Zmuj.ZH : Ljava/lang/Object;
    //   1063: checkcast java/math/BigInteger
    //   1066: invokevirtual intValue : ()I
    //   1069: bipush #32
    //   1071: irem
    //   1072: invokestatic abs : (I)I
    //   1075: invokevirtual charAt : (I)C
    //   1078: invokevirtual append : (C)Ljava/lang/StringBuilder;
    //   1081: pop
    //   1082: iload_2
    //   1083: ifeq -> 1348
    //   1086: goto -> 1093
    //   1089: invokestatic a : (Ljava/lang/Throwable;)Ljava/lang/Throwable;
    //   1092: athrow
    //   1093: aload_3
    //   1094: getstatic burp/Zgre.Zj : Ljava/lang/String;
    //   1097: getstatic burp/Zgre.ZD : Ljava/lang/Object;
    //   1100: checkcast java/math/BigInteger
    //   1103: invokevirtual intValue : ()I
    //   1106: bipush #32
    //   1108: irem
    //   1109: invokestatic abs : (I)I
    //   1112: invokevirtual charAt : (I)C
    //   1115: invokevirtual append : (C)Ljava/lang/StringBuilder;
    //   1118: pop
    //   1119: iload_2
    //   1120: ifeq -> 1348
    //   1123: goto -> 1130
    //   1126: invokestatic a : (Ljava/lang/Throwable;)Ljava/lang/Throwable;
    //   1129: athrow
    //   1130: aload_3
    //   1131: getstatic burp/Zxt5.ZM : Ljava/lang/String;
    //   1134: getstatic burp/Zvk.ZN : Ljava/lang/Object;
    //   1137: checkcast java/math/BigInteger
    //   1140: invokevirtual intValue : ()I
    //   1143: bipush #32
    //   1145: irem
    //   1146: invokestatic abs : (I)I
    //   1149: invokevirtual charAt : (I)C
    //   1152: invokevirtual append : (C)Ljava/lang/StringBuilder;
    //   1155: pop
    //   1156: iload_2
    //   1157: ifeq -> 1348
    //   1160: goto -> 1167
    //   1163: invokestatic a : (Ljava/lang/Throwable;)Ljava/lang/Throwable;
    //   1166: athrow
    //   1167: aload_3
    //   1168: getstatic burp/Zexn.ZE : Ljava/lang/String;
    //   1171: getstatic burp/Zkgp.Zw : Ljava/lang/Object;
    //   1174: checkcast java/math/BigInteger
    //   1177: invokevirtual intValue : ()I
    //   1180: bipush #32
    //   1182: irem
    //   1183: invokestatic abs : (I)I
    //   1186: invokevirtual charAt : (I)C
    //   1189: invokevirtual append : (C)Ljava/lang/StringBuilder;
    //   1192: pop
    //   1193: iload_2
    //   1194: ifeq -> 1348
    //   1197: goto -> 1204
    //   1200: invokestatic a : (Ljava/lang/Throwable;)Ljava/lang/Throwable;
    //   1203: athrow
    //   1204: aload_3
    //   1205: getstatic burp/Ze_0.Zi : Ljava/lang/String;
    //   1208: getstatic burp/Zgds.Z_ : Ljava/lang/Object;
    //   1211: checkcast java/math/BigInteger
    //   1214: invokevirtual intValue : ()I
    //   1217: bipush #32
    //   1219: irem
    //   1220: invokestatic abs : (I)I
    //   1223: invokevirtual charAt : (I)C
    //   1226: invokevirtual append : (C)Ljava/lang/StringBuilder;
    //   1229: pop
    //   1230: iload_2
    //   1231: ifeq -> 1348
    //   1234: goto -> 1241
    //   1237: invokestatic a : (Ljava/lang/Throwable;)Ljava/lang/Throwable;
    //   1240: athrow
    //   1241: aload_3
    //   1242: getstatic burp/Zbo2.Zr : Ljava/lang/String;
    //   1245: getstatic burp/Zb4m.Zp : Ljava/lang/Object;
    //   1248: checkcast java/math/BigInteger
    //   1251: invokevirtual intValue : ()I
    //   1254: bipush #32
    //   1256: irem
    //   1257: invokestatic abs : (I)I
    //   1260: invokevirtual charAt : (I)C
    //   1263: invokevirtual append : (C)Ljava/lang/StringBuilder;
    //   1266: pop
    //   1267: iload_2
    //   1268: ifeq -> 1348
    //   1271: goto -> 1278
    //   1274: invokestatic a : (Ljava/lang/Throwable;)Ljava/lang/Throwable;
    //   1277: athrow
    //   1278: aload_3
    //   1279: getstatic burp/Zgly.Zb : Ljava/lang/String;
    //   1282: getstatic burp/Zzco.ZC : Ljava/lang/Object;
    //   1285: checkcast java/math/BigInteger
    //   1288: invokevirtual intValue : ()I
    //   1291: bipush #32
    //   1293: irem
    //   1294: invokestatic abs : (I)I
    //   1297: invokevirtual charAt : (I)C
    //   1300: invokevirtual append : (C)Ljava/lang/StringBuilder;
    //   1303: pop
    //   1304: iload_2
    //   1305: ifeq -> 1348
    //   1308: goto -> 1315
    //   1311: invokestatic a : (Ljava/lang/Throwable;)Ljava/lang/Throwable;
    //   1314: athrow
    //   1315: aload_3
    //   1316: getstatic burp/Zlp8.ZW : Ljava/lang/String;
    //   1319: getstatic burp/Zgds.Z_ : Ljava/lang/Object;
    //   1322: checkcast java/math/BigInteger
    //   1325: invokevirtual intValue : ()I
    //   1328: bipush #32
    //   1330: irem
    //   1331: invokestatic abs : (I)I
    //   1334: invokevirtual charAt : (I)C
    //   1337: invokevirtual append : (C)Ljava/lang/StringBuilder;
    //   1340: pop
    //   1341: goto -> 1348
    //   1344: invokestatic a : (Ljava/lang/Throwable;)Ljava/lang/Throwable;
    //   1347: athrow
    //   1348: iinc #4, 1
    //   1351: iload_2
    //   1352: ifeq -> 15
    //   1355: aload_3
    //   1356: invokevirtual toString : ()Ljava/lang/String;
    //   1359: putstatic burp/Zkht.Zd : Ljava/lang/String;
    //   1362: sipush #-1192
    //   1365: sipush #11326
    //   1368: invokestatic a : (II)Ljava/lang/String;
    //   1371: iconst_1
    //   1372: ldc burp/Zl39
    //   1374: invokevirtual getClassLoader : ()Ljava/lang/ClassLoader;
    //   1377: invokestatic forName : (Ljava/lang/String;ZLjava/lang/ClassLoader;)Ljava/lang/Class;
    //   1380: invokevirtual getDeclaredFields : ()[Ljava/lang/reflect/Field;
    //   1383: astore #4
    //   1385: aload #4
    //   1387: arraylength
    //   1388: istore #5
    //   1390: iconst_0
    //   1391: istore #6
    //   1393: iload #6
    //   1395: iload #5
    //   1397: if_icmpge -> 1535
    //   1400: aload #4
    //   1402: iload #6
    //   1404: aaload
    //   1405: astore #7
    //   1407: aload #7
    //   1409: invokevirtual getModifiers : ()I
    //   1412: invokestatic isStatic : (I)Z
    //   1415: ifne -> 1425
    //   1418: goto -> 1528
    //   1421: invokestatic a : (Ljava/lang/Throwable;)Ljava/lang/Throwable;
    //   1424: athrow
    //   1425: aload #7
    //   1427: invokevirtual getType : ()Ljava/lang/Class;
    //   1430: astore #8
    //   1432: aload #8
    //   1434: ifnull -> 1515
    //   1437: aload #8
    //   1439: invokevirtual isPrimitive : ()Z
    //   1442: ifne -> 1515
    //   1445: goto -> 1452
    //   1448: invokestatic a : (Ljava/lang/Throwable;)Ljava/lang/Throwable;
    //   1451: athrow
    //   1452: aload #8
    //   1454: invokevirtual getPackage : ()Ljava/lang/Package;
    //   1457: ifnull -> 1515
    //   1460: goto -> 1467
    //   1463: invokestatic a : (Ljava/lang/Throwable;)Ljava/lang/Throwable;
    //   1466: athrow
    //   1467: aload #8
    //   1469: invokevirtual getPackage : ()Ljava/lang/Package;
    //   1472: invokevirtual getName : ()Ljava/lang/String;
    //   1475: ifnull -> 1515
    //   1478: goto -> 1485
    //   1481: invokestatic a : (Ljava/lang/Throwable;)Ljava/lang/Throwable;
    //   1484: athrow
    //   1485: aload #8
    //   1487: invokevirtual getPackage : ()Ljava/lang/Package;
    //   1490: invokevirtual getName : ()Ljava/lang/String;
    //   1493: sipush #-1187
    //   1496: sipush #-2873
    //   1499: invokestatic a : (II)Ljava/lang/String;
    //   1502: invokevirtual startsWith : (Ljava/lang/String;)Z
    //   1505: ifne -> 1515
    //   1508: goto -> 1515
    //   1511: invokestatic a : (Ljava/lang/Throwable;)Ljava/lang/Throwable;
    //   1514: athrow
    //   1515: aload #7
    //   1517: iconst_1
    //   1518: invokevirtual setAccessible : (Z)V
    //   1521: aload #7
    //   1523: aconst_null
    //   1524: invokevirtual get : (Ljava/lang/Object;)Ljava/lang/Object;
    //   1527: pop
    //   1528: iinc #6, 1
    //   1531: iload_2
    //   1532: ifeq -> 1393
    //   1535: sipush #-1199
    //   1538: sipush #3553
    //   1541: invokestatic a : (II)Ljava/lang/String;
    //   1544: invokestatic forName : (Ljava/lang/String;)Ljava/lang/Class;
    //   1547: invokevirtual getDeclaredMethods : ()[Ljava/lang/reflect/Method;
    //   1550: astore #4
    //   1552: aload #4
    //   1554: arraylength
    //   1555: istore #5
    //   1557: iconst_0
    //   1558: istore #6
    //   1560: iload #6
    //   1562: iload #5
    //   1564: if_icmpge -> 1697
    //   1567: aload #4
    //   1569: iload #6
    //   1571: aaload
    //   1572: astore #7
    //   1574: aload #7
    //   1576: invokevirtual getParameterTypes : ()[Ljava/lang/Class;
    //   1579: pop
    //   1580: aload #7
    //   1582: invokevirtual getModifiers : ()I
    //   1585: invokestatic isStatic : (I)Z
    //   1588: ifeq -> 1683
    //   1591: aload #7
    //   1593: invokevirtual getParameterTypes : ()[Ljava/lang/Class;
    //   1596: arraylength
    //   1597: iconst_2
    //   1598: if_icmpne -> 1683
    //   1601: goto -> 1608
    //   1604: invokestatic a : (Ljava/lang/Throwable;)Ljava/lang/Throwable;
    //   1607: athrow
    //   1608: aload #7
    //   1610: invokevirtual getReturnType : ()Ljava/lang/Class;
    //   1613: getstatic java/lang/Void.TYPE : Ljava/lang/Class;
    //   1616: invokevirtual equals : (Ljava/lang/Object;)Z
    //   1619: ifeq -> 1683
    //   1622: goto -> 1629
    //   1625: invokestatic a : (Ljava/lang/Throwable;)Ljava/lang/Throwable;
    //   1628: athrow
    //   1629: aload #7
    //   1631: iconst_1
    //   1632: invokevirtual setAccessible : (Z)V
    //   1635: aload #7
    //   1637: aconst_null
    //   1638: iconst_2
    //   1639: anewarray java/lang/Object
    //   1642: dup
    //   1643: iconst_0
    //   1644: aload_0
    //   1645: aastore
    //   1646: dup
    //   1647: iconst_1
    //   1648: aload_1
    //   1649: ifnonnull -> 1667
    //   1652: goto -> 1659
    //   1655: invokestatic a : (Ljava/lang/Throwable;)Ljava/lang/Throwable;
    //   1658: athrow
    //   1659: aload_1
    //   1660: goto -> 1674
    //   1663: invokestatic a : (Ljava/lang/Throwable;)Ljava/lang/Throwable;
    //   1666: athrow
    //   1667: aload_1
    //   1668: checkcast [B
    //   1671: invokevirtual clone : ()Ljava/lang/Object;
    //   1674: aastore
    //   1675: invokevirtual invoke : (Ljava/lang/Object;[Ljava/lang/Object;)Ljava/lang/Object;
    //   1678: pop
    //   1679: iload_2
    //   1680: ifeq -> 1697
    //   1683: iinc #6, 1
    //   1686: iload_2
    //   1687: ifeq -> 1560
    //   1690: goto -> 1697
    //   1693: invokestatic a : (Ljava/lang/Throwable;)Ljava/lang/Throwable;
    //   1696: athrow
    //   1697: getstatic burp/Zf.Zh : Ljava/lang/Object;
    //   1700: checkcast java/math/BigInteger
    //   1703: invokevirtual toByteArray : ()[B
    //   1706: astore #4
    //   1708: new java/lang/StringBuilder
    //   1711: dup
    //   1712: invokespecial <init> : ()V
    //   1715: astore #6
    //   1717: aload #6
    //   1719: sipush #-1186
    //   1722: sipush #32036
    //   1725: invokestatic a : (II)Ljava/lang/String;
    //   1728: invokevirtual append : (Ljava/lang/String;)Ljava/lang/StringBuilder;
    //   1731: pop
    //   1732: aload #4
    //   1734: astore #7
    //   1736: aload #7
    //   1738: arraylength
    //   1739: istore #8
    //   1741: iconst_0
    //   1742: istore #9
    //   1744: iload #9
    //   1746: iload #8
    //   1748: if_icmpge -> 1774
    //   1751: aload #7
    //   1753: iload #9
    //   1755: baload
    //   1756: istore #10
    //   1758: aload #6
    //   1760: iload #10
    //   1762: i2c
    //   1763: invokevirtual append : (C)Ljava/lang/StringBuilder;
    //   1766: pop
    //   1767: iinc #9, 1
    //   1770: iload_2
    //   1771: ifeq -> 1744
    //   1774: aload #6
    //   1776: sipush #-1198
    //   1779: sipush #26187
    //   1782: invokestatic a : (II)Ljava/lang/String;
    //   1785: ldc ''
    //   1787: invokestatic getProperty : (Ljava/lang/String;Ljava/lang/String;)Ljava/lang/String;
    //   1790: invokevirtual toLowerCase : ()Ljava/lang/String;
    //   1793: invokevirtual append : (Ljava/lang/String;)Ljava/lang/StringBuilder;
    //   1796: pop
    //   1797: aload #6
    //   1799: sipush #-1191
    //   1802: sipush #-14684
    //   1805: invokestatic a : (II)Ljava/lang/String;
    //   1808: ldc ''
    //   1810: invokestatic getProperty : (Ljava/lang/String;Ljava/lang/String;)Ljava/lang/String;
    //   1813: invokevirtual toLowerCase : ()Ljava/lang/String;
    //   1816: invokevirtual append : (Ljava/lang/String;)Ljava/lang/StringBuilder;
    //   1819: pop
    //   1820: aload #6
    //   1822: invokevirtual toString : ()Ljava/lang/String;
    //   1825: invokevirtual getBytes : ()[B
    //   1828: astore #5
    //   1830: aload #5
    //   1832: astore #4
    //   1834: aload #4
    //   1836: arraylength
    //   1837: bipush #8
    //   1839: iadd
    //   1840: bipush #6
    //   1842: ishr
    //   1843: iconst_1
    //   1844: iadd
    //   1845: bipush #16
    //   1847: imul
    //   1848: newarray int
    //   1850: astore #6
    //   1852: iconst_0
    //   1853: istore #7
    //   1855: iload #7
    //   1857: aload #4
    //   1859: arraylength
    //   1860: if_icmpge -> 1904
    //   1863: aload #4
    //   1865: iload #7
    //   1867: baload
    //   1868: sipush #255
    //   1871: iand
    //   1872: istore #8
    //   1874: aload #6
    //   1876: iload #7
    //   1878: iconst_2
    //   1879: ishr
    //   1880: dup2
    //   1881: iaload
    //   1882: iload #8
    //   1884: bipush #24
    //   1886: iload #7
    //   1888: iconst_4
    //   1889: irem
    //   1890: bipush #8
    //   1892: imul
    //   1893: isub
    //   1894: ishl
    //   1895: ior
    //   1896: iastore
    //   1897: iinc #7, 1
    //   1900: iload_2
    //   1901: ifeq -> 1855
    //   1904: aload #6
    //   1906: iload #7
    //   1908: iconst_2
    //   1909: ishr
    //   1910: dup2
    //   1911: iaload
    //   1912: sipush #128
    //   1915: bipush #24
    //   1917: iload #7
    //   1919: iconst_4
    //   1920: irem
    //   1921: bipush #8
    //   1923: imul
    //   1924: isub
    //   1925: ishl
    //   1926: ior
    //   1927: iastore
    //   1928: aload #6
    //   1930: aload #6
    //   1932: arraylength
    //   1933: iconst_1
    //   1934: isub
    //   1935: aload #4
    //   1937: arraylength
    //   1938: bipush #8
    //   1940: imul
    //   1941: iastore
    //   1942: bipush #80
    //   1944: newarray int
    //   1946: astore #8
    //   1948: ldc 1732584193
    //   1950: istore #9
    //   1952: ldc -271733879
    //   1954: istore #10
    //   1956: ldc -1732584194
    //   1958: istore #11
    //   1960: ldc 271733878
    //   1962: istore #12
    //   1964: ldc -1009589776
    //   1966: istore #13
    //   1968: iconst_0
    //   1969: istore #7
    //   1971: iload #7
    //   1973: aload #6
    //   1975: arraylength
    //   1976: if_icmpge -> 2298
    //   1979: iload #9
    //   1981: istore #14
    //   1983: iload #10
    //   1985: istore #15
    //   1987: iload #11
    //   1989: istore #16
    //   1991: iload #12
    //   1993: istore #17
    //   1995: iload #13
    //   1997: istore #18
    //   1999: iconst_0
    //   2000: istore #19
    //   2002: iload #19
    //   2004: bipush #80
    //   2006: if_icmpge -> 2256
    //   2009: iload #19
    //   2011: bipush #16
    //   2013: if_icmpge -> 2040
    //   2016: aload #8
    //   2018: iload #19
    //   2020: aload #6
    //   2022: iload #7
    //   2024: iload #19
    //   2026: iadd
    //   2027: iaload
    //   2028: iastore
    //   2029: iload_2
    //   2030: ifeq -> 2095
    //   2033: goto -> 2040
    //   2036: invokestatic a : (Ljava/lang/Throwable;)Ljava/lang/Throwable;
    //   2039: athrow
    //   2040: aload #8
    //   2042: iload #19
    //   2044: iconst_3
    //   2045: isub
    //   2046: iaload
    //   2047: aload #8
    //   2049: iload #19
    //   2051: bipush #8
    //   2053: isub
    //   2054: iaload
    //   2055: ixor
    //   2056: aload #8
    //   2058: iload #19
    //   2060: bipush #14
    //   2062: isub
    //   2063: iaload
    //   2064: ixor
    //   2065: aload #8
    //   2067: iload #19
    //   2069: bipush #16
    //   2071: isub
    //   2072: iaload
    //   2073: ixor
    //   2074: istore #20
    //   2076: iload #20
    //   2078: iconst_1
    //   2079: ishl
    //   2080: iload #20
    //   2082: bipush #31
    //   2084: iushr
    //   2085: ior
    //   2086: istore #21
    //   2088: aload #8
    //   2090: iload #19
    //   2092: iload #21
    //   2094: iastore
    //   2095: iload #9
    //   2097: iconst_5
    //   2098: ishl
    //   2099: iload #9
    //   2101: bipush #27
    //   2103: iushr
    //   2104: ior
    //   2105: istore #20
    //   2107: iload #20
    //   2109: iload #13
    //   2111: iadd
    //   2112: aload #8
    //   2114: iload #19
    //   2116: iaload
    //   2117: iadd
    //   2118: iload #19
    //   2120: bipush #20
    //   2122: if_icmpge -> 2148
    //   2125: ldc 1518500249
    //   2127: iload #10
    //   2129: iload #11
    //   2131: iand
    //   2132: iload #10
    //   2134: iconst_m1
    //   2135: ixor
    //   2136: iload #12
    //   2138: iand
    //   2139: ior
    //   2140: iadd
    //   2141: goto -> 2218
    //   2144: invokestatic a : (Ljava/lang/Throwable;)Ljava/lang/Throwable;
    //   2147: athrow
    //   2148: iload #19
    //   2150: bipush #40
    //   2152: if_icmpge -> 2173
    //   2155: ldc 1859775393
    //   2157: iload #10
    //   2159: iload #11
    //   2161: ixor
    //   2162: iload #12
    //   2164: ixor
    //   2165: iadd
    //   2166: goto -> 2218
    //   2169: invokestatic a : (Ljava/lang/Throwable;)Ljava/lang/Throwable;
    //   2172: athrow
    //   2173: iload #19
    //   2175: bipush #60
    //   2177: if_icmpge -> 2207
    //   2180: ldc -1894007588
    //   2182: iload #10
    //   2184: iload #11
    //   2186: iand
    //   2187: iload #10
    //   2189: iload #12
    //   2191: iand
    //   2192: ior
    //   2193: iload #11
    //   2195: iload #12
    //   2197: iand
    //   2198: ior
    //   2199: iadd
    //   2200: goto -> 2218
    //   2203: invokestatic a : (Ljava/lang/Throwable;)Ljava/lang/Throwable;
    //   2206: athrow
    //   2207: ldc -899497514
    //   2209: iload #10
    //   2211: iload #11
    //   2213: ixor
    //   2214: iload #12
    //   2216: ixor
    //   2217: iadd
    //   2218: iadd
    //   2219: istore #21
    //   2221: iload #12
    //   2223: istore #13
    //   2225: iload #11
    //   2227: istore #12
    //   2229: iload #10
    //   2231: bipush #30
    //   2233: ishl
    //   2234: iload #10
    //   2236: iconst_2
    //   2237: iushr
    //   2238: ior
    //   2239: istore #11
    //   2241: iload #9
    //   2243: istore #10
    //   2245: iload #21
    //   2247: istore #9
    //   2249: iinc #19, 1
    //   2252: iload_2
    //   2253: ifeq -> 2002
    //   2256: iload #9
    //   2258: iload #14
    //   2260: iadd
    //   2261: istore #9
    //   2263: iload #10
    //   2265: iload #15
    //   2267: iadd
    //   2268: istore #10
    //   2270: iload #11
    //   2272: iload #16
    //   2274: iadd
    //   2275: istore #11
    //   2277: iload #12
    //   2279: iload #17
    //   2281: iadd
    //   2282: istore #12
    //   2284: iload #13
    //   2286: iload #18
    //   2288: iadd
    //   2289: istore #13
    //   2291: iinc #7, 16
    //   2294: iload_2
    //   2295: ifeq -> 1971
    //   2298: iconst_5
    //   2299: newarray int
    //   2301: dup
    //   2302: iconst_0
    //   2303: iload #9
    //   2305: iastore
    //   2306: dup
    //   2307: iconst_1
    //   2308: iload #10
    //   2310: iastore
    //   2311: dup
    //   2312: iconst_2
    //   2313: iload #11
    //   2315: iastore
    //   2316: dup
    //   2317: iconst_3
    //   2318: iload #12
    //   2320: iastore
    //   2321: dup
    //   2322: iconst_4
    //   2323: iload #13
    //   2325: iastore
    //   2326: astore #14
    //   2328: bipush #20
    //   2330: newarray byte
    //   2332: astore #15
    //   2334: iconst_0
    //   2335: istore #16
    //   2337: iload #16
    //   2339: bipush #20
    //   2341: if_icmpge -> 2382
    //   2344: aload #14
    //   2346: iload #16
    //   2348: iconst_4
    //   2349: idiv
    //   2350: iaload
    //   2351: istore #17
    //   2353: iconst_3
    //   2354: iload #16
    //   2356: iconst_4
    //   2357: irem
    //   2358: isub
    //   2359: bipush #8
    //   2361: imul
    //   2362: istore #18
    //   2364: aload #15
    //   2366: iload #16
    //   2368: iload #17
    //   2370: iload #18
    //   2372: iushr
    //   2373: i2b
    //   2374: bastore
    //   2375: iinc #16, 1
    //   2378: iload_2
    //   2379: ifeq -> 2337
    //   2382: aload #15
    //   2384: astore #5
    //   2386: getstatic burp/Zgja.Zb : Ljava/lang/String;
    //   2389: getstatic burp/Zez0.ZT : Ljava/lang/Object;
    //   2392: checkcast java/math/BigInteger
    //   2395: invokevirtual intValue : ()I
    //   2398: bipush #32
    //   2400: irem
    //   2401: invokestatic abs : (I)I
    //   2404: invokevirtual charAt : (I)C
    //   2407: getstatic burp/Zle6.Zh : Ljava/lang/String;
    //   2410: getstatic burp/Zgre.ZD : Ljava/lang/Object;
    //   2413: checkcast java/math/BigInteger
    //   2416: invokevirtual intValue : ()I
    //   2419: bipush #32
    //   2421: irem
    //   2422: invokestatic abs : (I)I
    //   2425: invokevirtual charAt : (I)C
    //   2428: if_icmple -> 2535
    //   2431: getstatic burp/Zml.ZN : Ljava/lang/String;
    //   2434: getstatic burp/Ztzh.ZT : Ljava/lang/Object;
    //   2437: checkcast java/math/BigInteger
    //   2440: invokevirtual intValue : ()I
    //   2443: bipush #32
    //   2445: irem
    //   2446: invokestatic abs : (I)I
    //   2449: invokevirtual charAt : (I)C
    //   2452: getstatic burp/Zrn0.Zd : Ljava/lang/String;
    //   2455: getstatic burp/Zf.Zh : Ljava/lang/Object;
    //   2458: checkcast java/math/BigInteger
    //   2461: invokevirtual intValue : ()I
    //   2464: bipush #32
    //   2466: irem
    //   2467: invokestatic abs : (I)I
    //   2470: invokevirtual charAt : (I)C
    //   2473: if_icmple -> 2535
    //   2476: goto -> 2483
    //   2479: invokestatic a : (Ljava/lang/Throwable;)Ljava/lang/Throwable;
    //   2482: athrow
    //   2483: getstatic burp/Zxc.Zx : Ljava/lang/String;
    //   2486: getstatic burp/Zb2p.ZQ : Ljava/lang/Object;
    //   2489: checkcast java/math/BigInteger
    //   2492: invokevirtual intValue : ()I
    //   2495: bipush #32
    //   2497: irem
    //   2498: invokestatic abs : (I)I
    //   2501: invokevirtual charAt : (I)C
    //   2504: getstatic burp/Zmze.ZO : Ljava/lang/String;
    //   2507: getstatic burp/Zk88.ZX : Ljava/lang/Object;
    //   2510: checkcast java/math/BigInteger
    //   2513: invokevirtual intValue : ()I
    //   2516: bipush #32
    //   2518: irem
    //   2519: invokestatic abs : (I)I
    //   2522: invokevirtual charAt : (I)C
    //   2525: if_icmpgt -> 2543
    //   2528: goto -> 2535
    //   2531: invokestatic a : (Ljava/lang/Throwable;)Ljava/lang/Throwable;
    //   2534: athrow
    //   2535: iconst_1
    //   2536: goto -> 2544
    //   2539: invokestatic a : (Ljava/lang/Throwable;)Ljava/lang/Throwable;
    //   2542: athrow
    //   2543: iconst_0
    //   2544: ireturn
    //   2545: astore_3
    //   2546: new java/lang/Exception
    //   2549: dup
    //   2550: aload_3
    //   2551: invokevirtual getMessage : ()Ljava/lang/String;
    //   2554: invokespecial <init> : (Ljava/lang/String;)V
    //   2557: athrow
    // Exception table:
    //   from	to	target	type
    //   4	2544	2545	java/lang/Throwable
    //   22	198	201	java/lang/Throwable
    //   168	235	238	java/lang/Throwable
    //   205	272	275	java/lang/Throwable
    //   242	309	312	java/lang/Throwable
    //   279	346	349	java/lang/Throwable
    //   316	383	386	java/lang/Throwable
    //   353	420	423	java/lang/Throwable
    //   390	457	460	java/lang/Throwable
    //   427	494	497	java/lang/Throwable
    //   464	531	534	java/lang/Throwable
    //   501	568	571	java/lang/Throwable
    //   538	605	608	java/lang/Throwable
    //   575	642	645	java/lang/Throwable
    //   612	679	682	java/lang/Throwable
    //   649	716	719	java/lang/Throwable
    //   686	753	756	java/lang/Throwable
    //   723	790	793	java/lang/Throwable
    //   760	827	830	java/lang/Throwable
    //   797	864	867	java/lang/Throwable
    //   834	901	904	java/lang/Throwable
    //   871	938	941	java/lang/Throwable
    //   908	975	978	java/lang/Throwable
    //   945	1012	1015	java/lang/Throwable
    //   982	1049	1052	java/lang/Throwable
    //   1019	1086	1089	java/lang/Throwable
    //   1056	1123	1126	java/lang/Throwable
    //   1093	1160	1163	java/lang/Throwable
    //   1130	1197	1200	java/lang/Throwable
    //   1167	1234	1237	java/lang/Throwable
    //   1204	1271	1274	java/lang/Throwable
    //   1241	1308	1311	java/lang/Throwable
    //   1278	1341	1344	java/lang/Throwable
    //   1407	1421	1421	java/lang/Throwable
    //   1432	1445	1448	java/lang/Throwable
    //   1437	1460	1463	java/lang/Throwable
    //   1452	1478	1481	java/lang/Throwable
    //   1467	1508	1511	java/lang/Throwable
    //   1574	1601	1604	java/lang/Throwable
    //   1591	1622	1625	java/lang/Throwable
    //   1608	1652	1655	java/lang/Throwable
    //   1629	1663	1663	java/lang/Throwable
    //   1674	1690	1693	java/lang/Throwable
    //   2009	2033	2036	java/lang/Throwable
    //   2107	2144	2144	java/lang/Throwable
    //   2148	2169	2169	java/lang/Throwable
    //   2173	2203	2203	java/lang/Throwable
    //   2386	2476	2479	java/lang/Throwable
    //   2431	2528	2531	java/lang/Throwable
    //   2483	2539	2539	java/lang/Throwable
  }
  
  static void Zo(Object[] paramArrayOfObject, Object paramObject) throws Throwable {}
  
  static void Zp(Object paramObject) {
    Zlxs.ZM = a(-1200, 22478);
    Zlxs.ZK = new BigInteger(a(-1190, -3284));
    boolean bool = Zt2e.ZN();
    try {
      try {
        if (Ztip.Z_.charAt(Math.abs(((BigInteger)Zmuj.ZH).intValue() % 32)) <= Zgre.Zj.charAt(Math.abs(((BigInteger)Zg8v.ZB).intValue() % 32))) {
          try {
            Zle6.ZE(Class.forName(a(-1188, 25997)));
            if (!bool)
              Zmu6.Zh(Class.forName(a(-1185, 23141))); 
          } catch (Throwable throwable) {
            throw a(null);
          } 
          return;
        } 
      } catch (Throwable throwable) {
        throw a(null);
      } 
      Zmu6.Zh(Class.forName(a(-1185, 23141)));
    } catch (Throwable throwable) {}
  }
  
  static {
    // Byte code:
    //   0: bipush #11
    //   2: anewarray java/lang/String
    //   5: astore #5
    //   7: iconst_0
    //   8: istore_3
    //   9: ldc 'MÃ§[Ã›ÃŽÃªÂ«Ã…\\tÂšÂ7Â…4cÂ£fMÃ¥L+2wÂ¤Ã”\Ã›/Ãœ"ÂŠ|Ã¸?I`Ã¼%Ã¾Â¾ÂªÃ Â˜Â€y\\tÂŸÂ£Ã™ÂŽL\\bÂ°Ã‡zÃ„ÂHÂšÂŠÂ¶Â„Â¤Â¦Â³bÃ FÃÃšvcÃgÃ‚Â±ÂŒÃ±Â„r9Â»ÂždrÂ¼ ÂšÃ–ÃŒÂ¬ÂŒn7ÂšwÂ¥tÂ«Ã´B2ÂˆÂ²Â…Ã¾nÃ­"Ã½eÃ‚Ãž\\tPÂŒÃ±Â¶Â›N<=ÃDÂ¾z 3Â\Â‘Ã­~Â¡?Ã˜=@\\b6z;KÂŸÃ’Â€Â‡IÃ½m!,xÂ‹eÂŒ\\t5P Ã¸#ÂºÃ£.w ÃÂ†Ã‰tJÂ·dÃ¤(Â·ÃœÃ«Ã‘eÃÃƒÃµ-U5MÂw%ÃªÃ„'
    //   11: dup
    //   12: astore_2
    //   13: invokevirtual length : ()I
    //   16: istore #4
    //   18: bipush #9
    //   20: istore_1
    //   21: iconst_m1
    //   22: istore_0
    //   23: bipush #107
    //   25: iinc #0, 1
    //   28: aload_2
    //   29: iload_0
    //   30: dup
    //   31: iload_1
    //   32: iadd
    //   33: invokevirtual substring : (II)Ljava/lang/String;
    //   36: iconst_m1
    //   37: goto -> 143
    //   40: aload #5
    //   42: swap
    //   43: iload_3
    //   44: iinc #3, 1
    //   47: swap
    //   48: aastore
    //   49: iload_0
    //   50: iload_1
    //   51: iadd
    //   52: dup
    //   53: istore_0
    //   54: iload #4
    //   56: if_icmpge -> 68
    //   59: aload_2
    //   60: iload_0
    //   61: invokevirtual charAt : (I)C
    //   64: istore_1
    //   65: goto -> 23
    //   68: ldc 'ÃƒgÃ¥Â€ÂšÂªÃAÃ‡EÃ‰\\fmÂ¤'
    //   70: dup
    //   71: astore_2
    //   72: invokevirtual length : ()I
    //   75: istore #4
    //   77: bipush #9
    //   79: istore_1
    //   80: iconst_m1
    //   81: istore_0
    //   82: bipush #115
    //   84: iinc #0, 1
    //   87: aload_2
    //   88: iload_0
    //   89: dup
    //   90: iload_1
    //   91: iadd
    //   92: invokevirtual substring : (II)Ljava/lang/String;
    //   95: iconst_0
    //   96: goto -> 143
    //   99: aload #5
    //   101: swap
    //   102: iload_3
    //   103: iinc #3, 1
    //   106: swap
    //   107: aastore
    //   108: iload_0
    //   109: iload_1
    //   110: iadd
    //   111: dup
    //   112: istore_0
    //   113: iload #4
    //   115: if_icmpge -> 127
    //   118: aload_2
    //   119: iload_0
    //   120: invokevirtual charAt : (I)C
    //   123: istore_1
    //   124: goto -> 82
    //   127: aload #5
    //   129: putstatic burp/Zbz_.a : [Ljava/lang/String;
    //   132: bipush #11
    //   134: anewarray java/lang/String
    //   137: putstatic burp/Zbz_.b : [Ljava/lang/String;
    //   140: goto -> 300
    //   143: dup_x2
    //   144: pop
    //   145: invokevirtual toCharArray : ()[C
    //   148: dup_x1
    //   149: arraylength
    //   150: dup_x2
    //   151: pop
    //   152: iconst_0
    //   153: istore #6
    //   155: dup2_x1
    //   156: pop2
    //   157: dup_x2
    //   158: iconst_1
    //   159: if_icmpgt -> 260
    //   162: dup2
    //   163: swap
    //   164: iload #6
    //   166: dup2_x1
    //   167: caload
    //   168: swap
    //   169: iload #6
    //   171: bipush #7
    //   173: irem
    //   174: tableswitch default -> 242, 0 -> 212, 1 -> 217, 2 -> 222, 3 -> 227, 4 -> 232, 5 -> 237
    //   212: bipush #46
    //   214: goto -> 244
    //   217: bipush #73
    //   219: goto -> 244
    //   222: bipush #25
    //   224: goto -> 244
    //   227: bipush #118
    //   229: goto -> 244
    //   232: bipush #16
    //   234: goto -> 244
    //   237: bipush #73
    //   239: goto -> 244
    //   242: bipush #18
    //   244: ixor
    //   245: ixor
    //   246: i2c
    //   247: castore
    //   248: iinc #6, 1
    //   251: dup
    //   252: ifne -> 260
    //   255: dup2
    //   256: dup_x1
    //   257: goto -> 166
    //   260: dup2_x1
    //   261: pop2
    //   262: dup_x2
    //   263: iload #6
    //   265: if_icmpgt -> 162
    //   268: pop
    //   269: new java/lang/String
    //   272: dup_x1
    //   273: swap
    //   274: invokespecial <init> : ([C)V
    //   277: invokevirtual intern : ()Ljava/lang/String;
    //   280: swap
    //   281: pop
    //   282: swap
    //   283: tableswitch default -> 40, 0 -> 99
    //   300: sipush #-1189
    //   303: sipush #-16409
    //   306: invokestatic a : (II)Ljava/lang/String;
    //   309: putstatic burp/Zbz_.ZW : Ljava/lang/String;
    //   312: new java/math/BigInteger
    //   315: dup
    //   316: iconst_1
    //   317: bipush #32
    //   319: newarray byte
    //   321: dup
    //   322: iconst_0
    //   323: bipush #104
    //   325: bastore
    //   326: dup
    //   327: iconst_1
    //   328: bipush #56
    //   330: bastore
    //   331: dup
    //   332: iconst_2
    //   333: bipush #43
    //   335: bastore
    //   336: dup
    //   337: iconst_3
    //   338: bipush #110
    //   340: bastore
    //   341: dup
    //   342: iconst_4
    //   343: bipush #-60
    //   345: bastore
    //   346: dup
    //   347: iconst_5
    //   348: bipush #66
    //   350: bastore
    //   351: dup
    //   352: bipush #6
    //   354: bipush #59
    //   356: bastore
    //   357: dup
    //   358: bipush #7
    //   360: bipush #-30
    //   362: bastore
    //   363: dup
    //   364: bipush #8
    //   366: bipush #-13
    //   368: bastore
    //   369: dup
    //   370: bipush #9
    //   372: bipush #-74
    //   374: bastore
    //   375: dup
    //   376: bipush #10
    //   378: bipush #-101
    //   380: bastore
    //   381: dup
    //   382: bipush #11
    //   384: bipush #9
    //   386: bastore
    //   387: dup
    //   388: bipush #12
    //   390: bipush #59
    //   392: bastore
    //   393: dup
    //   394: bipush #13
    //   396: bipush #50
    //   398: bastore
    //   399: dup
    //   400: bipush #14
    //   402: bipush #-45
    //   404: bastore
    //   405: dup
    //   406: bipush #15
    //   408: bipush #-51
    //   410: bastore
    //   411: dup
    //   412: bipush #16
    //   414: bipush #-102
    //   416: bastore
    //   417: dup
    //   418: bipush #17
    //   420: bipush #79
    //   422: bastore
    //   423: dup
    //   424: bipush #18
    //   426: bipush #-17
    //   428: bastore
    //   429: dup
    //   430: bipush #19
    //   432: bipush #82
    //   434: bastore
    //   435: dup
    //   436: bipush #20
    //   438: bipush #9
    //   440: bastore
    //   441: dup
    //   442: bipush #21
    //   444: bipush #118
    //   446: bastore
    //   447: dup
    //   448: bipush #22
    //   450: bipush #-65
    //   452: bastore
    //   453: dup
    //   454: bipush #23
    //   456: bipush #-4
    //   458: bastore
    //   459: dup
    //   460: bipush #24
    //   462: bipush #-19
    //   464: bastore
    //   465: dup
    //   466: bipush #25
    //   468: bipush #83
    //   470: bastore
    //   471: dup
    //   472: bipush #26
    //   474: bipush #-79
    //   476: bastore
    //   477: dup
    //   478: bipush #27
    //   480: bipush #29
    //   482: bastore
    //   483: dup
    //   484: bipush #28
    //   486: bipush #15
    //   488: bastore
    //   489: dup
    //   490: bipush #29
    //   492: bipush #-118
    //   494: bastore
    //   495: dup
    //   496: bipush #30
    //   498: bipush #-39
    //   500: bastore
    //   501: dup
    //   502: bipush #31
    //   504: bipush #-96
    //   506: bastore
    //   507: invokespecial <init> : (I[B)V
    //   510: putstatic burp/Zbz_.ZU : Ljava/lang/Object;
    //   513: return
  }
  
  private static Throwable a(Throwable paramThrowable) {
    return paramThrowable;
  }
  
  private static String a(int paramInt1, int paramInt2) {
    int i = (paramInt1 ^ 0xFFFFFB58) & 0xFFFF;
    if (b[i] == null) {
      char[] arrayOfChar = a[i].toCharArray();
      switch (arrayOfChar[0] & 0xFF) {
        case 0:
        
        case 1:
        
        case 2:
        
        case 3:
        
        case 4:
        
        case 5:
        
        case 6:
        
        case 7:
        
        case 8:
        
        case 9:
        
        case 10:
        
        case 11:
        
        case 12:
        
        case 13:
        
        case 14:
        
        case 15:
        
        case 16:
        
        case 17:
        
        case 18:
        
        case 19:
        
        case 20:
        
        case 21:
        
        case 22:
        
        case 23:
        
        case 24:
        
        case 25:
        
        case 26:
        
        case 27:
        
        case 28:
        
        case 29:
        
        case 30:
        
        case 31:
        
        case 32:
        
        case 33:
        
        case 34:
        
        case 35:
        
        case 36:
        
        case 37:
        
        case 38:
        
        case 39:
        
        case 40:
        
        case 41:
        
        case 42:
        
        case 43:
        
        case 44:
        
        case 45:
        
        case 46:
        
        case 47:
        
        case 48:
        
        case 49:
        
        case 50:
        
        case 51:
        
        case 52:
        
        case 53:
        
        case 54:
        
        case 55:
        
        case 56:
        
        case 57:
        
        case 58:
        
        case 59:
        
        case 60:
        
        case 61:
        
        case 62:
        
        case 63:
        
        case 64:
        
        case 65:
        
        case 66:
        
        case 67:
        
        case 68:
        
        case 69:
        
        case 70:
        
        case 71:
        
        case 72:
        
        case 73:
        
        case 74:
        
        case 75:
        
        case 76:
        
        case 77:
        
        case 78:
        
        case 79:
        
        case 80:
        
        case 81:
        
        case 82:
        
        case 83:
        
        case 84:
        
        case 85:
        
        case 86:
        
        case 87:
        
        case 88:
        
        case 89:
        
        case 90:
        
        case 91:
        
        case 92:
        
        case 93:
        
        case 94:
        
        case 95:
        
        case 96:
        
        case 97:
        
        case 98:
        
        case 99:
        
        case 100:
        
        case 101:
        
        case 102:
        
        case 103:
        
        case 104:
        
        case 105:
        
        case 106:
        
        case 107:
        
        case 108:
        
        case 109:
        
        case 110:
        
        case 111:
        
        case 112:
        
        case 113:
        
        case 114:
        
        case 115:
        
        case 116:
        
        case 117:
        
        case 118:
        
        case 119:
        
        case 120:
        
        case 121:
        
        case 122:
        
        case 123:
        
        case 124:
        
        case 125:
        
        case 126:
        
        case 127:
        
        case 128:
        
        case 129:
        
        case 130:
        
        case 131:
        
        case 132:
        
        case 133:
        
        case 134:
        
        case 135:
        
        case 136:
        
        case 137:
        
        case 138:
        
        case 139:
        
        case 140:
        
        case 141:
        
        case 142:
        
        case 143:
        
        case 144:
        
        case 145:
        
        case 146:
        
        case 147:
        
        case 148:
        
        case 149:
        
        case 150:
        
        case 151:
        
        case 152:
        
        case 153:
        
        case 154:
        
        case 155:
        
        case 156:
        
        case 157:
        
        case 158:
        
        case 159:
        
        case 160:
        
        case 161:
        
        case 162:
        
        case 163:
        
        case 164:
        
        case 165:
        
        case 166:
        
        case 167:
        
        case 168:
        
        case 169:
        
        case 170:
        
        case 171:
        
        case 172:
        
        case 173:
        
        case 174:
        
        case 175:
        
        case 176:
        
        case 177:
        
        case 178:
        
        case 179:
        
        case 180:
        
        case 181:
        
        case 182:
        
        case 183:
        
        case 184:
        
        case 185:
        
        case 186:
        
        case 187:
        
        case 188:
        
        case 189:
        
        case 190:
        
        case 191:
        
        case 192:
        
        case 193:
        
        case 194:
        
        case 195:
        
        case 196:
        
        case 197:
        
        case 198:
        
        case 199:
        
        case 200:
        
        case 201:
        
        case 202:
        
        case 203:
        
        case 204:
        
        case 205:
        
        case 206:
        
        case 207:
        
        case 208:
        
        case 209:
        
        case 210:
        
        case 211:
        
        case 212:
        
        case 213:
        
        case 214:
        
        case 215:
        
        case 216:
        
        case 217:
        
        case 218:
        
        case 219:
        
        case 220:
        
        case 221:
        
        case 222:
        
        case 223:
        
        case 224:
        
        case 225:
        
        case 226:
        
        case 227:
        
        case 228:
        
        case 229:
        
        case 230:
        
        case 231:
        
        case 232:
        
        case 233:
        
        case 234:
        
        case 235:
        
        case 236:
        
        case 237:
        
        case 238:
        
        case 239:
        
        case 240:
        
        case 241:
        
        case 242:
        
        case 243:
        
        case 244:
        
        case 245:
        
        case 246:
        
        case 247:
        
        case 248:
        
        case 249:
        
        case 250:
        
        case 251:
        
        case 252:
        
        case 253:
        
        case 254:
        
        default:
          break;
      } 
      byte b1 = 104;
      int j = (paramInt2 & 0xFF) - b1;
      if (j < 0)
        j += 256; 
      int k = ((paramInt2 & 0xFFFF) >>> 8) - b1;
      if (k < 0)
        k += 256; 
      for (byte b2 = 0; b2 < arrayOfChar.length; b2++) {
        int m = b2 % 2;
        if (m == 0) {
          arrayOfChar[b2] = (char)(arrayOfChar[b2] ^ j);
          j = ((j >>> 3 | j << 5) ^ arrayOfChar[b2]) & 0xFF;
        } else {
          arrayOfChar[b2] = (char)(arrayOfChar[b2] ^ k);
          k = ((k >>> 3 | k << 5) ^ arrayOfChar[b2]) & 0xFF;
        } 
      } 
      b[i] = (new String(arrayOfChar)).intern();
    } 
    return b[i];
  }
}


/* Location:              C:\Program Files\BurpSuitePro\burpsuite_pro.jar!\burp\Zbz_.class
 * Java compiler version: 21 (65.0)
 * JD-Core Version:       1.1.3
 */