package burp;

import java.math.BigInteger;

class Zbze extends ClassLoader {
  static String ZK;
  
  static Object ZM;
  
  private static final String[] a;
  
  private static final String[] b;
  
  static boolean ZE(Object[] paramArrayOfObject, Object paramObject) throws Throwable {
    // Byte code:
    //   0: invokestatic ZK : ()Z
    //   3: istore_2
    //   4: getstatic burp/Ze7e.Z_ : Ljava/lang/Object;
    //   7: checkcast java/math/BigInteger
    //   10: invokevirtual toByteArray : ()[B
    //   13: astore_3
    //   14: aload_3
    //   15: arraylength
    //   16: iconst_2
    //   17: iadd
    //   18: newarray byte
    //   20: astore #5
    //   22: iconst_0
    //   23: istore #6
    //   25: iload #6
    //   27: aload_3
    //   28: arraylength
    //   29: if_icmpge -> 48
    //   32: aload #5
    //   34: iload #6
    //   36: aload_3
    //   37: iload #6
    //   39: baload
    //   40: bastore
    //   41: iinc #6, 1
    //   44: iload_2
    //   45: ifeq -> 25
    //   48: aload #5
    //   50: arraylength
    //   51: iconst_3
    //   52: idiv
    //   53: iconst_4
    //   54: imul
    //   55: newarray byte
    //   57: astore #4
    //   59: iconst_0
    //   60: istore #6
    //   62: iconst_0
    //   63: istore #7
    //   65: iload #6
    //   67: aload_3
    //   68: arraylength
    //   69: if_icmpge -> 180
    //   72: aload #4
    //   74: iload #7
    //   76: aload #5
    //   78: iload #6
    //   80: baload
    //   81: iconst_2
    //   82: iushr
    //   83: bipush #63
    //   85: iand
    //   86: i2b
    //   87: bastore
    //   88: aload #4
    //   90: iload #7
    //   92: iconst_1
    //   93: iadd
    //   94: aload #5
    //   96: iload #6
    //   98: iconst_1
    //   99: iadd
    //   100: baload
    //   101: iconst_4
    //   102: iushr
    //   103: bipush #15
    //   105: iand
    //   106: aload #5
    //   108: iload #6
    //   110: baload
    //   111: iconst_4
    //   112: ishl
    //   113: bipush #63
    //   115: iand
    //   116: ior
    //   117: i2b
    //   118: bastore
    //   119: aload #4
    //   121: iload #7
    //   123: iconst_2
    //   124: iadd
    //   125: aload #5
    //   127: iload #6
    //   129: iconst_2
    //   130: iadd
    //   131: baload
    //   132: bipush #6
    //   134: iushr
    //   135: iconst_3
    //   136: iand
    //   137: aload #5
    //   139: iload #6
    //   141: iconst_1
    //   142: iadd
    //   143: baload
    //   144: iconst_2
    //   145: ishl
    //   146: bipush #63
    //   148: iand
    //   149: ior
    //   150: i2b
    //   151: bastore
    //   152: aload #4
    //   154: iload #7
    //   156: iconst_3
    //   157: iadd
    //   158: aload #5
    //   160: iload #6
    //   162: iconst_2
    //   163: iadd
    //   164: baload
    //   165: bipush #63
    //   167: iand
    //   168: i2b
    //   169: bastore
    //   170: iinc #6, 3
    //   173: iinc #7, 4
    //   176: iload_2
    //   177: ifeq -> 65
    //   180: iconst_0
    //   181: istore #6
    //   183: iload #6
    //   185: aload #4
    //   187: arraylength
    //   188: if_icmpge -> 372
    //   191: aload #4
    //   193: iload #6
    //   195: baload
    //   196: bipush #26
    //   198: if_icmpge -> 226
    //   201: aload #4
    //   203: iload #6
    //   205: aload #4
    //   207: iload #6
    //   209: baload
    //   210: bipush #65
    //   212: iadd
    //   213: i2b
    //   214: bastore
    //   215: iload_2
    //   216: ifeq -> 365
    //   219: goto -> 226
    //   222: invokestatic a : (Ljava/lang/Throwable;)Ljava/lang/Throwable;
    //   225: athrow
    //   226: aload #4
    //   228: iload #6
    //   230: baload
    //   231: bipush #52
    //   233: if_icmpge -> 271
    //   236: goto -> 243
    //   239: invokestatic a : (Ljava/lang/Throwable;)Ljava/lang/Throwable;
    //   242: athrow
    //   243: aload #4
    //   245: iload #6
    //   247: aload #4
    //   249: iload #6
    //   251: baload
    //   252: bipush #97
    //   254: iadd
    //   255: bipush #26
    //   257: isub
    //   258: i2b
    //   259: bastore
    //   260: iload_2
    //   261: ifeq -> 365
    //   264: goto -> 271
    //   267: invokestatic a : (Ljava/lang/Throwable;)Ljava/lang/Throwable;
    //   270: athrow
    //   271: aload #4
    //   273: iload #6
    //   275: baload
    //   276: bipush #62
    //   278: if_icmpge -> 316
    //   281: goto -> 288
    //   284: invokestatic a : (Ljava/lang/Throwable;)Ljava/lang/Throwable;
    //   287: athrow
    //   288: aload #4
    //   290: iload #6
    //   292: aload #4
    //   294: iload #6
    //   296: baload
    //   297: bipush #48
    //   299: iadd
    //   300: bipush #52
    //   302: isub
    //   303: i2b
    //   304: bastore
    //   305: iload_2
    //   306: ifeq -> 365
    //   309: goto -> 316
    //   312: invokestatic a : (Ljava/lang/Throwable;)Ljava/lang/Throwable;
    //   315: athrow
    //   316: aload #4
    //   318: iload #6
    //   320: baload
    //   321: bipush #63
    //   323: if_icmpge -> 351
    //   326: goto -> 333
    //   329: invokestatic a : (Ljava/lang/Throwable;)Ljava/lang/Throwable;
    //   332: athrow
    //   333: aload #4
    //   335: iload #6
    //   337: bipush #43
    //   339: bastore
    //   340: iload_2
    //   341: ifeq -> 365
    //   344: goto -> 351
    //   347: invokestatic a : (Ljava/lang/Throwable;)Ljava/lang/Throwable;
    //   350: athrow
    //   351: aload #4
    //   353: iload #6
    //   355: bipush #47
    //   357: bastore
    //   358: goto -> 365
    //   361: invokestatic a : (Ljava/lang/Throwable;)Ljava/lang/Throwable;
    //   364: athrow
    //   365: iinc #6, 1
    //   368: iload_2
    //   369: ifeq -> 183
    //   372: aload #4
    //   374: arraylength
    //   375: iconst_1
    //   376: isub
    //   377: istore #6
    //   379: iload #6
    //   381: aload_3
    //   382: arraylength
    //   383: iconst_4
    //   384: imul
    //   385: iconst_3
    //   386: idiv
    //   387: if_icmple -> 404
    //   390: aload #4
    //   392: iload #6
    //   394: bipush #61
    //   396: bastore
    //   397: iinc #6, -1
    //   400: iload_2
    //   401: ifeq -> 379
    //   404: new java/math/BigInteger
    //   407: dup
    //   408: aload #4
    //   410: invokespecial <init> : ([B)V
    //   413: invokevirtual abs : ()Ljava/math/BigInteger;
    //   416: putstatic burp/Zb6m.ZQ : Ljava/lang/Object;
    //   419: getstatic burp/Zm_u.Zf : Ljava/lang/Object;
    //   422: checkcast java/math/BigInteger
    //   425: getstatic burp/Zg61.Zp : Ljava/lang/Object;
    //   428: checkcast java/math/BigInteger
    //   431: invokevirtual subtract : (Ljava/math/BigInteger;)Ljava/math/BigInteger;
    //   434: putstatic burp/Zmll.ZU : Ljava/lang/Object;
    //   437: getstatic burp/Zt6z.Zl : Ljava/lang/Object;
    //   440: checkcast java/math/BigInteger
    //   443: invokevirtual toByteArray : ()[B
    //   446: astore_3
    //   447: aload_3
    //   448: arraylength
    //   449: iconst_2
    //   450: iadd
    //   451: newarray byte
    //   453: astore #5
    //   455: iconst_0
    //   456: istore #6
    //   458: iload #6
    //   460: aload_3
    //   461: arraylength
    //   462: if_icmpge -> 481
    //   465: aload #5
    //   467: iload #6
    //   469: aload_3
    //   470: iload #6
    //   472: baload
    //   473: bastore
    //   474: iinc #6, 1
    //   477: iload_2
    //   478: ifeq -> 458
    //   481: aload #5
    //   483: arraylength
    //   484: iconst_3
    //   485: idiv
    //   486: iconst_4
    //   487: imul
    //   488: newarray byte
    //   490: astore #4
    //   492: iconst_0
    //   493: istore #6
    //   495: iconst_0
    //   496: istore #7
    //   498: iload #6
    //   500: aload_3
    //   501: arraylength
    //   502: if_icmpge -> 613
    //   505: aload #4
    //   507: iload #7
    //   509: aload #5
    //   511: iload #6
    //   513: baload
    //   514: iconst_2
    //   515: iushr
    //   516: bipush #63
    //   518: iand
    //   519: i2b
    //   520: bastore
    //   521: aload #4
    //   523: iload #7
    //   525: iconst_1
    //   526: iadd
    //   527: aload #5
    //   529: iload #6
    //   531: iconst_1
    //   532: iadd
    //   533: baload
    //   534: iconst_4
    //   535: iushr
    //   536: bipush #15
    //   538: iand
    //   539: aload #5
    //   541: iload #6
    //   543: baload
    //   544: iconst_4
    //   545: ishl
    //   546: bipush #63
    //   548: iand
    //   549: ior
    //   550: i2b
    //   551: bastore
    //   552: aload #4
    //   554: iload #7
    //   556: iconst_2
    //   557: iadd
    //   558: aload #5
    //   560: iload #6
    //   562: iconst_2
    //   563: iadd
    //   564: baload
    //   565: bipush #6
    //   567: iushr
    //   568: iconst_3
    //   569: iand
    //   570: aload #5
    //   572: iload #6
    //   574: iconst_1
    //   575: iadd
    //   576: baload
    //   577: iconst_2
    //   578: ishl
    //   579: bipush #63
    //   581: iand
    //   582: ior
    //   583: i2b
    //   584: bastore
    //   585: aload #4
    //   587: iload #7
    //   589: iconst_3
    //   590: iadd
    //   591: aload #5
    //   593: iload #6
    //   595: iconst_2
    //   596: iadd
    //   597: baload
    //   598: bipush #63
    //   600: iand
    //   601: i2b
    //   602: bastore
    //   603: iinc #6, 3
    //   606: iinc #7, 4
    //   609: iload_2
    //   610: ifeq -> 498
    //   613: iconst_0
    //   614: istore #6
    //   616: iload #6
    //   618: aload #4
    //   620: arraylength
    //   621: if_icmpge -> 805
    //   624: aload #4
    //   626: iload #6
    //   628: baload
    //   629: bipush #26
    //   631: if_icmpge -> 659
    //   634: aload #4
    //   636: iload #6
    //   638: aload #4
    //   640: iload #6
    //   642: baload
    //   643: bipush #65
    //   645: iadd
    //   646: i2b
    //   647: bastore
    //   648: iload_2
    //   649: ifeq -> 798
    //   652: goto -> 659
    //   655: invokestatic a : (Ljava/lang/Throwable;)Ljava/lang/Throwable;
    //   658: athrow
    //   659: aload #4
    //   661: iload #6
    //   663: baload
    //   664: bipush #52
    //   666: if_icmpge -> 704
    //   669: goto -> 676
    //   672: invokestatic a : (Ljava/lang/Throwable;)Ljava/lang/Throwable;
    //   675: athrow
    //   676: aload #4
    //   678: iload #6
    //   680: aload #4
    //   682: iload #6
    //   684: baload
    //   685: bipush #97
    //   687: iadd
    //   688: bipush #26
    //   690: isub
    //   691: i2b
    //   692: bastore
    //   693: iload_2
    //   694: ifeq -> 798
    //   697: goto -> 704
    //   700: invokestatic a : (Ljava/lang/Throwable;)Ljava/lang/Throwable;
    //   703: athrow
    //   704: aload #4
    //   706: iload #6
    //   708: baload
    //   709: bipush #62
    //   711: if_icmpge -> 749
    //   714: goto -> 721
    //   717: invokestatic a : (Ljava/lang/Throwable;)Ljava/lang/Throwable;
    //   720: athrow
    //   721: aload #4
    //   723: iload #6
    //   725: aload #4
    //   727: iload #6
    //   729: baload
    //   730: bipush #48
    //   732: iadd
    //   733: bipush #52
    //   735: isub
    //   736: i2b
    //   737: bastore
    //   738: iload_2
    //   739: ifeq -> 798
    //   742: goto -> 749
    //   745: invokestatic a : (Ljava/lang/Throwable;)Ljava/lang/Throwable;
    //   748: athrow
    //   749: aload #4
    //   751: iload #6
    //   753: baload
    //   754: bipush #63
    //   756: if_icmpge -> 784
    //   759: goto -> 766
    //   762: invokestatic a : (Ljava/lang/Throwable;)Ljava/lang/Throwable;
    //   765: athrow
    //   766: aload #4
    //   768: iload #6
    //   770: bipush #43
    //   772: bastore
    //   773: iload_2
    //   774: ifeq -> 798
    //   777: goto -> 784
    //   780: invokestatic a : (Ljava/lang/Throwable;)Ljava/lang/Throwable;
    //   783: athrow
    //   784: aload #4
    //   786: iload #6
    //   788: bipush #47
    //   790: bastore
    //   791: goto -> 798
    //   794: invokestatic a : (Ljava/lang/Throwable;)Ljava/lang/Throwable;
    //   797: athrow
    //   798: iinc #6, 1
    //   801: iload_2
    //   802: ifeq -> 616
    //   805: aload #4
    //   807: arraylength
    //   808: iconst_1
    //   809: isub
    //   810: istore #6
    //   812: iload #6
    //   814: aload_3
    //   815: arraylength
    //   816: iconst_4
    //   817: imul
    //   818: iconst_3
    //   819: idiv
    //   820: if_icmple -> 837
    //   823: aload #4
    //   825: iload #6
    //   827: bipush #61
    //   829: bastore
    //   830: iinc #6, -1
    //   833: iload_2
    //   834: ifeq -> 812
    //   837: new java/math/BigInteger
    //   840: dup
    //   841: aload #4
    //   843: invokespecial <init> : ([B)V
    //   846: invokevirtual abs : ()Ljava/math/BigInteger;
    //   849: putstatic burp/Zbx4.Zw : Ljava/lang/Object;
    //   852: sipush #-26009
    //   855: sipush #-1036
    //   858: invokestatic a : (II)Ljava/lang/String;
    //   861: iconst_1
    //   862: ldc burp/Zmj8
    //   864: invokevirtual getClassLoader : ()Ljava/lang/ClassLoader;
    //   867: invokestatic forName : (Ljava/lang/String;ZLjava/lang/ClassLoader;)Ljava/lang/Class;
    //   870: invokevirtual getDeclaredFields : ()[Ljava/lang/reflect/Field;
    //   873: astore_3
    //   874: aload_3
    //   875: arraylength
    //   876: istore #4
    //   878: iconst_0
    //   879: istore #5
    //   881: iload #5
    //   883: iload #4
    //   885: if_icmpge -> 1022
    //   888: aload_3
    //   889: iload #5
    //   891: aaload
    //   892: astore #6
    //   894: aload #6
    //   896: invokevirtual getModifiers : ()I
    //   899: invokestatic isStatic : (I)Z
    //   902: ifne -> 912
    //   905: goto -> 1015
    //   908: invokestatic a : (Ljava/lang/Throwable;)Ljava/lang/Throwable;
    //   911: athrow
    //   912: aload #6
    //   914: invokevirtual getType : ()Ljava/lang/Class;
    //   917: astore #7
    //   919: aload #7
    //   921: ifnull -> 1002
    //   924: aload #7
    //   926: invokevirtual isPrimitive : ()Z
    //   929: ifne -> 1002
    //   932: goto -> 939
    //   935: invokestatic a : (Ljava/lang/Throwable;)Ljava/lang/Throwable;
    //   938: athrow
    //   939: aload #7
    //   941: invokevirtual getPackage : ()Ljava/lang/Package;
    //   944: ifnull -> 1002
    //   947: goto -> 954
    //   950: invokestatic a : (Ljava/lang/Throwable;)Ljava/lang/Throwable;
    //   953: athrow
    //   954: aload #7
    //   956: invokevirtual getPackage : ()Ljava/lang/Package;
    //   959: invokevirtual getName : ()Ljava/lang/String;
    //   962: ifnull -> 1002
    //   965: goto -> 972
    //   968: invokestatic a : (Ljava/lang/Throwable;)Ljava/lang/Throwable;
    //   971: athrow
    //   972: aload #7
    //   974: invokevirtual getPackage : ()Ljava/lang/Package;
    //   977: invokevirtual getName : ()Ljava/lang/String;
    //   980: sipush #-26004
    //   983: sipush #-23916
    //   986: invokestatic a : (II)Ljava/lang/String;
    //   989: invokevirtual startsWith : (Ljava/lang/String;)Z
    //   992: ifne -> 1002
    //   995: goto -> 1002
    //   998: invokestatic a : (Ljava/lang/Throwable;)Ljava/lang/Throwable;
    //   1001: athrow
    //   1002: aload #6
    //   1004: iconst_1
    //   1005: invokevirtual setAccessible : (Z)V
    //   1008: aload #6
    //   1010: aconst_null
    //   1011: invokevirtual get : (Ljava/lang/Object;)Ljava/lang/Object;
    //   1014: pop
    //   1015: iinc #5, 1
    //   1018: iload_2
    //   1019: ifeq -> 881
    //   1022: sipush #-26014
    //   1025: sipush #18735
    //   1028: invokestatic a : (II)Ljava/lang/String;
    //   1031: invokestatic forName : (Ljava/lang/String;)Ljava/lang/Class;
    //   1034: invokevirtual getDeclaredMethods : ()[Ljava/lang/reflect/Method;
    //   1037: astore_3
    //   1038: aload_3
    //   1039: arraylength
    //   1040: istore #4
    //   1042: iconst_0
    //   1043: istore #5
    //   1045: iload #5
    //   1047: iload #4
    //   1049: if_icmpge -> 1181
    //   1052: aload_3
    //   1053: iload #5
    //   1055: aaload
    //   1056: astore #6
    //   1058: aload #6
    //   1060: invokevirtual getParameterTypes : ()[Ljava/lang/Class;
    //   1063: pop
    //   1064: aload #6
    //   1066: invokevirtual getModifiers : ()I
    //   1069: invokestatic isStatic : (I)Z
    //   1072: ifeq -> 1167
    //   1075: aload #6
    //   1077: invokevirtual getParameterTypes : ()[Ljava/lang/Class;
    //   1080: arraylength
    //   1081: iconst_2
    //   1082: if_icmpne -> 1167
    //   1085: goto -> 1092
    //   1088: invokestatic a : (Ljava/lang/Throwable;)Ljava/lang/Throwable;
    //   1091: athrow
    //   1092: aload #6
    //   1094: invokevirtual getReturnType : ()Ljava/lang/Class;
    //   1097: getstatic java/lang/Void.TYPE : Ljava/lang/Class;
    //   1100: invokevirtual equals : (Ljava/lang/Object;)Z
    //   1103: ifeq -> 1167
    //   1106: goto -> 1113
    //   1109: invokestatic a : (Ljava/lang/Throwable;)Ljava/lang/Throwable;
    //   1112: athrow
    //   1113: aload #6
    //   1115: iconst_1
    //   1116: invokevirtual setAccessible : (Z)V
    //   1119: aload #6
    //   1121: aconst_null
    //   1122: iconst_2
    //   1123: anewarray java/lang/Object
    //   1126: dup
    //   1127: iconst_0
    //   1128: aload_0
    //   1129: aastore
    //   1130: dup
    //   1131: iconst_1
    //   1132: aload_1
    //   1133: ifnonnull -> 1151
    //   1136: goto -> 1143
    //   1139: invokestatic a : (Ljava/lang/Throwable;)Ljava/lang/Throwable;
    //   1142: athrow
    //   1143: aload_1
    //   1144: goto -> 1158
    //   1147: invokestatic a : (Ljava/lang/Throwable;)Ljava/lang/Throwable;
    //   1150: athrow
    //   1151: aload_1
    //   1152: checkcast [B
    //   1155: invokevirtual clone : ()Ljava/lang/Object;
    //   1158: aastore
    //   1159: invokevirtual invoke : (Ljava/lang/Object;[Ljava/lang/Object;)Ljava/lang/Object;
    //   1162: pop
    //   1163: iload_2
    //   1164: ifeq -> 1181
    //   1167: iinc #5, 1
    //   1170: iload_2
    //   1171: ifeq -> 1045
    //   1174: goto -> 1181
    //   1177: invokestatic a : (Ljava/lang/Throwable;)Ljava/lang/Throwable;
    //   1180: athrow
    //   1181: getstatic burp/Zea8.ZF : Ljava/lang/Object;
    //   1184: checkcast java/math/BigInteger
    //   1187: invokevirtual toByteArray : ()[B
    //   1190: astore_3
    //   1191: new java/lang/StringBuilder
    //   1194: dup
    //   1195: invokespecial <init> : ()V
    //   1198: astore #5
    //   1200: aload #5
    //   1202: sipush #-26015
    //   1205: sipush #9974
    //   1208: invokestatic a : (II)Ljava/lang/String;
    //   1211: invokevirtual append : (Ljava/lang/String;)Ljava/lang/StringBuilder;
    //   1214: pop
    //   1215: aload_3
    //   1216: astore #6
    //   1218: aload #6
    //   1220: arraylength
    //   1221: istore #7
    //   1223: iconst_0
    //   1224: istore #8
    //   1226: iload #8
    //   1228: iload #7
    //   1230: if_icmpge -> 1256
    //   1233: aload #6
    //   1235: iload #8
    //   1237: baload
    //   1238: istore #9
    //   1240: aload #5
    //   1242: iload #9
    //   1244: i2c
    //   1245: invokevirtual append : (C)Ljava/lang/StringBuilder;
    //   1248: pop
    //   1249: iinc #8, 1
    //   1252: iload_2
    //   1253: ifeq -> 1226
    //   1256: aload #5
    //   1258: sipush #-26010
    //   1261: sipush #1448
    //   1264: invokestatic a : (II)Ljava/lang/String;
    //   1267: ldc ''
    //   1269: invokestatic getProperty : (Ljava/lang/String;Ljava/lang/String;)Ljava/lang/String;
    //   1272: invokevirtual toLowerCase : ()Ljava/lang/String;
    //   1275: invokevirtual append : (Ljava/lang/String;)Ljava/lang/StringBuilder;
    //   1278: pop
    //   1279: aload #5
    //   1281: sipush #-26001
    //   1284: sipush #-8771
    //   1287: invokestatic a : (II)Ljava/lang/String;
    //   1290: ldc ''
    //   1292: invokestatic getProperty : (Ljava/lang/String;Ljava/lang/String;)Ljava/lang/String;
    //   1295: invokevirtual toLowerCase : ()Ljava/lang/String;
    //   1298: invokevirtual append : (Ljava/lang/String;)Ljava/lang/StringBuilder;
    //   1301: pop
    //   1302: aload #5
    //   1304: invokevirtual toString : ()Ljava/lang/String;
    //   1307: invokevirtual getBytes : ()[B
    //   1310: astore #4
    //   1312: aload #4
    //   1314: astore_3
    //   1315: aload_3
    //   1316: arraylength
    //   1317: bipush #8
    //   1319: iadd
    //   1320: bipush #6
    //   1322: ishr
    //   1323: iconst_1
    //   1324: iadd
    //   1325: bipush #16
    //   1327: imul
    //   1328: newarray int
    //   1330: astore #5
    //   1332: iconst_0
    //   1333: istore #6
    //   1335: iload #6
    //   1337: aload_3
    //   1338: arraylength
    //   1339: if_icmpge -> 1382
    //   1342: aload_3
    //   1343: iload #6
    //   1345: baload
    //   1346: sipush #255
    //   1349: iand
    //   1350: istore #7
    //   1352: aload #5
    //   1354: iload #6
    //   1356: iconst_2
    //   1357: ishr
    //   1358: dup2
    //   1359: iaload
    //   1360: iload #7
    //   1362: bipush #24
    //   1364: iload #6
    //   1366: iconst_4
    //   1367: irem
    //   1368: bipush #8
    //   1370: imul
    //   1371: isub
    //   1372: ishl
    //   1373: ior
    //   1374: iastore
    //   1375: iinc #6, 1
    //   1378: iload_2
    //   1379: ifeq -> 1335
    //   1382: aload #5
    //   1384: iload #6
    //   1386: iconst_2
    //   1387: ishr
    //   1388: dup2
    //   1389: iaload
    //   1390: sipush #128
    //   1393: bipush #24
    //   1395: iload #6
    //   1397: iconst_4
    //   1398: irem
    //   1399: bipush #8
    //   1401: imul
    //   1402: isub
    //   1403: ishl
    //   1404: ior
    //   1405: iastore
    //   1406: aload #5
    //   1408: aload #5
    //   1410: arraylength
    //   1411: iconst_1
    //   1412: isub
    //   1413: aload_3
    //   1414: arraylength
    //   1415: bipush #8
    //   1417: imul
    //   1418: iastore
    //   1419: bipush #80
    //   1421: newarray int
    //   1423: astore #7
    //   1425: ldc 1732584193
    //   1427: istore #8
    //   1429: ldc -271733879
    //   1431: istore #9
    //   1433: ldc -1732584194
    //   1435: istore #10
    //   1437: ldc 271733878
    //   1439: istore #11
    //   1441: ldc -1009589776
    //   1443: istore #12
    //   1445: iconst_0
    //   1446: istore #6
    //   1448: iload #6
    //   1450: aload #5
    //   1452: arraylength
    //   1453: if_icmpge -> 1775
    //   1456: iload #8
    //   1458: istore #13
    //   1460: iload #9
    //   1462: istore #14
    //   1464: iload #10
    //   1466: istore #15
    //   1468: iload #11
    //   1470: istore #16
    //   1472: iload #12
    //   1474: istore #17
    //   1476: iconst_0
    //   1477: istore #18
    //   1479: iload #18
    //   1481: bipush #80
    //   1483: if_icmpge -> 1733
    //   1486: iload #18
    //   1488: bipush #16
    //   1490: if_icmpge -> 1517
    //   1493: aload #7
    //   1495: iload #18
    //   1497: aload #5
    //   1499: iload #6
    //   1501: iload #18
    //   1503: iadd
    //   1504: iaload
    //   1505: iastore
    //   1506: iload_2
    //   1507: ifeq -> 1572
    //   1510: goto -> 1517
    //   1513: invokestatic a : (Ljava/lang/Throwable;)Ljava/lang/Throwable;
    //   1516: athrow
    //   1517: aload #7
    //   1519: iload #18
    //   1521: iconst_3
    //   1522: isub
    //   1523: iaload
    //   1524: aload #7
    //   1526: iload #18
    //   1528: bipush #8
    //   1530: isub
    //   1531: iaload
    //   1532: ixor
    //   1533: aload #7
    //   1535: iload #18
    //   1537: bipush #14
    //   1539: isub
    //   1540: iaload
    //   1541: ixor
    //   1542: aload #7
    //   1544: iload #18
    //   1546: bipush #16
    //   1548: isub
    //   1549: iaload
    //   1550: ixor
    //   1551: istore #19
    //   1553: iload #19
    //   1555: iconst_1
    //   1556: ishl
    //   1557: iload #19
    //   1559: bipush #31
    //   1561: iushr
    //   1562: ior
    //   1563: istore #20
    //   1565: aload #7
    //   1567: iload #18
    //   1569: iload #20
    //   1571: iastore
    //   1572: iload #8
    //   1574: iconst_5
    //   1575: ishl
    //   1576: iload #8
    //   1578: bipush #27
    //   1580: iushr
    //   1581: ior
    //   1582: istore #19
    //   1584: iload #19
    //   1586: iload #12
    //   1588: iadd
    //   1589: aload #7
    //   1591: iload #18
    //   1593: iaload
    //   1594: iadd
    //   1595: iload #18
    //   1597: bipush #20
    //   1599: if_icmpge -> 1625
    //   1602: ldc 1518500249
    //   1604: iload #9
    //   1606: iload #10
    //   1608: iand
    //   1609: iload #9
    //   1611: iconst_m1
    //   1612: ixor
    //   1613: iload #11
    //   1615: iand
    //   1616: ior
    //   1617: iadd
    //   1618: goto -> 1695
    //   1621: invokestatic a : (Ljava/lang/Throwable;)Ljava/lang/Throwable;
    //   1624: athrow
    //   1625: iload #18
    //   1627: bipush #40
    //   1629: if_icmpge -> 1650
    //   1632: ldc 1859775393
    //   1634: iload #9
    //   1636: iload #10
    //   1638: ixor
    //   1639: iload #11
    //   1641: ixor
    //   1642: iadd
    //   1643: goto -> 1695
    //   1646: invokestatic a : (Ljava/lang/Throwable;)Ljava/lang/Throwable;
    //   1649: athrow
    //   1650: iload #18
    //   1652: bipush #60
    //   1654: if_icmpge -> 1684
    //   1657: ldc -1894007588
    //   1659: iload #9
    //   1661: iload #10
    //   1663: iand
    //   1664: iload #9
    //   1666: iload #11
    //   1668: iand
    //   1669: ior
    //   1670: iload #10
    //   1672: iload #11
    //   1674: iand
    //   1675: ior
    //   1676: iadd
    //   1677: goto -> 1695
    //   1680: invokestatic a : (Ljava/lang/Throwable;)Ljava/lang/Throwable;
    //   1683: athrow
    //   1684: ldc -899497514
    //   1686: iload #9
    //   1688: iload #10
    //   1690: ixor
    //   1691: iload #11
    //   1693: ixor
    //   1694: iadd
    //   1695: iadd
    //   1696: istore #20
    //   1698: iload #11
    //   1700: istore #12
    //   1702: iload #10
    //   1704: istore #11
    //   1706: iload #9
    //   1708: bipush #30
    //   1710: ishl
    //   1711: iload #9
    //   1713: iconst_2
    //   1714: iushr
    //   1715: ior
    //   1716: istore #10
    //   1718: iload #8
    //   1720: istore #9
    //   1722: iload #20
    //   1724: istore #8
    //   1726: iinc #18, 1
    //   1729: iload_2
    //   1730: ifeq -> 1479
    //   1733: iload #8
    //   1735: iload #13
    //   1737: iadd
    //   1738: istore #8
    //   1740: iload #9
    //   1742: iload #14
    //   1744: iadd
    //   1745: istore #9
    //   1747: iload #10
    //   1749: iload #15
    //   1751: iadd
    //   1752: istore #10
    //   1754: iload #11
    //   1756: iload #16
    //   1758: iadd
    //   1759: istore #11
    //   1761: iload #12
    //   1763: iload #17
    //   1765: iadd
    //   1766: istore #12
    //   1768: iinc #6, 16
    //   1771: iload_2
    //   1772: ifeq -> 1448
    //   1775: iconst_5
    //   1776: newarray int
    //   1778: dup
    //   1779: iconst_0
    //   1780: iload #8
    //   1782: iastore
    //   1783: dup
    //   1784: iconst_1
    //   1785: iload #9
    //   1787: iastore
    //   1788: dup
    //   1789: iconst_2
    //   1790: iload #10
    //   1792: iastore
    //   1793: dup
    //   1794: iconst_3
    //   1795: iload #11
    //   1797: iastore
    //   1798: dup
    //   1799: iconst_4
    //   1800: iload #12
    //   1802: iastore
    //   1803: astore #13
    //   1805: bipush #20
    //   1807: newarray byte
    //   1809: astore #14
    //   1811: iconst_0
    //   1812: istore #15
    //   1814: iload #15
    //   1816: bipush #20
    //   1818: if_icmpge -> 1859
    //   1821: aload #13
    //   1823: iload #15
    //   1825: iconst_4
    //   1826: idiv
    //   1827: iaload
    //   1828: istore #16
    //   1830: iconst_3
    //   1831: iload #15
    //   1833: iconst_4
    //   1834: irem
    //   1835: isub
    //   1836: bipush #8
    //   1838: imul
    //   1839: istore #17
    //   1841: aload #14
    //   1843: iload #15
    //   1845: iload #16
    //   1847: iload #17
    //   1849: iushr
    //   1850: i2b
    //   1851: bastore
    //   1852: iinc #15, 1
    //   1855: iload_2
    //   1856: ifeq -> 1814
    //   1859: aload #14
    //   1861: astore #4
    //   1863: getstatic burp/Zg7u.ZA : Ljava/lang/String;
    //   1866: getstatic burp/Zt4p.Zh : Ljava/lang/Object;
    //   1869: checkcast java/math/BigInteger
    //   1872: invokevirtual intValue : ()I
    //   1875: bipush #32
    //   1877: irem
    //   1878: invokestatic abs : (I)I
    //   1881: invokevirtual charAt : (I)C
    //   1884: getstatic burp/Ztgv.ZC : Ljava/lang/String;
    //   1887: getstatic burp/Zrkd.ZO : Ljava/lang/Object;
    //   1890: checkcast java/math/BigInteger
    //   1893: invokevirtual intValue : ()I
    //   1896: bipush #32
    //   1898: irem
    //   1899: invokestatic abs : (I)I
    //   1902: invokevirtual charAt : (I)C
    //   1905: if_icmpgt -> 2012
    //   1908: getstatic burp/Zr60.ZQ : Ljava/lang/String;
    //   1911: getstatic burp/Zt7x.ZE : Ljava/lang/Object;
    //   1914: checkcast java/math/BigInteger
    //   1917: invokevirtual intValue : ()I
    //   1920: bipush #32
    //   1922: irem
    //   1923: invokestatic abs : (I)I
    //   1926: invokevirtual charAt : (I)C
    //   1929: getstatic burp/Zenr.Z_ : Ljava/lang/String;
    //   1932: getstatic burp/Zk5k.Zr : Ljava/lang/Object;
    //   1935: checkcast java/math/BigInteger
    //   1938: invokevirtual intValue : ()I
    //   1941: bipush #32
    //   1943: irem
    //   1944: invokestatic abs : (I)I
    //   1947: invokevirtual charAt : (I)C
    //   1950: if_icmple -> 2012
    //   1953: goto -> 1960
    //   1956: invokestatic a : (Ljava/lang/Throwable;)Ljava/lang/Throwable;
    //   1959: athrow
    //   1960: getstatic burp/Zv8l.Zo : Ljava/lang/String;
    //   1963: getstatic burp/Zgrz.ZX : Ljava/lang/Object;
    //   1966: checkcast java/math/BigInteger
    //   1969: invokevirtual intValue : ()I
    //   1972: bipush #32
    //   1974: irem
    //   1975: invokestatic abs : (I)I
    //   1978: invokevirtual charAt : (I)C
    //   1981: getstatic burp/Zkeb.ZW : Ljava/lang/String;
    //   1984: getstatic burp/Zsn4.ZQ : Ljava/lang/Object;
    //   1987: checkcast java/math/BigInteger
    //   1990: invokevirtual intValue : ()I
    //   1993: bipush #32
    //   1995: irem
    //   1996: invokestatic abs : (I)I
    //   1999: invokevirtual charAt : (I)C
    //   2002: if_icmple -> 2020
    //   2005: goto -> 2012
    //   2008: invokestatic a : (Ljava/lang/Throwable;)Ljava/lang/Throwable;
    //   2011: athrow
    //   2012: iconst_1
    //   2013: goto -> 2021
    //   2016: invokestatic a : (Ljava/lang/Throwable;)Ljava/lang/Throwable;
    //   2019: athrow
    //   2020: iconst_0
    //   2021: ireturn
    //   2022: astore_3
    //   2023: new java/lang/Exception
    //   2026: dup
    //   2027: aload_3
    //   2028: invokevirtual getMessage : ()Ljava/lang/String;
    //   2031: invokespecial <init> : (Ljava/lang/String;)V
    //   2034: athrow
    // Exception table:
    //   from	to	target	type
    //   4	2021	2022	java/lang/Throwable
    //   191	219	222	java/lang/Throwable
    //   201	236	239	java/lang/Throwable
    //   226	264	267	java/lang/Throwable
    //   243	281	284	java/lang/Throwable
    //   271	309	312	java/lang/Throwable
    //   288	326	329	java/lang/Throwable
    //   316	344	347	java/lang/Throwable
    //   333	358	361	java/lang/Throwable
    //   624	652	655	java/lang/Throwable
    //   634	669	672	java/lang/Throwable
    //   659	697	700	java/lang/Throwable
    //   676	714	717	java/lang/Throwable
    //   704	742	745	java/lang/Throwable
    //   721	759	762	java/lang/Throwable
    //   749	777	780	java/lang/Throwable
    //   766	791	794	java/lang/Throwable
    //   894	908	908	java/lang/Throwable
    //   919	932	935	java/lang/Throwable
    //   924	947	950	java/lang/Throwable
    //   939	965	968	java/lang/Throwable
    //   954	995	998	java/lang/Throwable
    //   1058	1085	1088	java/lang/Throwable
    //   1075	1106	1109	java/lang/Throwable
    //   1092	1136	1139	java/lang/Throwable
    //   1113	1147	1147	java/lang/Throwable
    //   1158	1174	1177	java/lang/Throwable
    //   1486	1510	1513	java/lang/Throwable
    //   1584	1621	1621	java/lang/Throwable
    //   1625	1646	1646	java/lang/Throwable
    //   1650	1680	1680	java/lang/Throwable
    //   1863	1953	1956	java/lang/Throwable
    //   1908	2005	2008	java/lang/Throwable
    //   1960	2016	2016	java/lang/Throwable
  }
  
  static void Zf(Object paramObject) {
    Zscf.Zu = a(-26013, -19258);
    Zscf.ZG = new BigInteger(a(-26012, 30162));
    boolean bool = Zt2e.ZK();
    try {
      try {
        if (Zrt3.Zu.charAt(Math.abs(((BigInteger)Zrt3.ZG).intValue() % 32)) > Zm7v.ZX.charAt(Math.abs(((BigInteger)Zz41.Zv).intValue() % 32))) {
          try {
            Zbw5.ZH(Class.forName(a(-26016, -31421)));
            if (bool)
              Zb38.Zt(Class.forName(a(-26011, 18473))); 
          } catch (Throwable throwable) {
            throw a(null);
          } 
          return;
        } 
      } catch (Throwable throwable) {
        throw a(null);
      } 
      Zb38.Zt(Class.forName(a(-26011, 18473)));
    } catch (Throwable throwable) {}
  }
  
  static void ZK(Object[] paramArrayOfObject, Object paramObject) throws Throwable {}
  
  static {
    // Byte code:
    //   0: bipush #11
    //   2: anewarray java/lang/String
    //   5: astore #5
    //   7: iconst_0
    //   8: istore_3
    //   9: ldc 'Ã°Â·Â»ÂƒT_*Â²MaÂ±WÂ¬Ã˜ÂŸÂ•0(uXÂ’&>Ã€Ã¿GBzÂƒfWÃ±Ã›lbÂƒÂ“iÃˆ;=MÂŽ&Ã¿awÃ‹Â±Â¤Ã„%1Â¬}C{Â€Ã¢Ã¿Â¦ Ã­2vbÃ§)ZSa#ÃÃšÂ§Âª\\rSÂ‡\\tÂÃ¼ÃªÃ¡rÂœÃ$Â¬Ã‘8ÂÃ‚6 Â°Ã³RÃ¿nÂ‹Ã¶wÂ³}SÂ©6>Ã¡4ÃŽÂ¼Â’mÃ½Âƒ|ÃªÂ°mJU Ã\\tÂ®pÂ´-Â¹\\reÃ¹ JvÃ¬/ÃÃ¨\\r>Ã¹\\nÃ¦YÂ¦ÃŸiÃ±ÃŽÂªÂ­Â•Ã¸J>@bÃ›Ã€3\\tÂ‰DÃƒÂ§Ã˜Â»E ÃÂ­$}(Â‚Â \\tÃÃmBGÂ’ÂžÃ­Ã†aÂšÂ§Â‡Âƒ\Âp 3Â–'
    //   11: dup
    //   12: astore_2
    //   13: invokevirtual length : ()I
    //   16: istore #4
    //   18: bipush #9
    //   20: istore_1
    //   21: iconst_m1
    //   22: istore_0
    //   23: bipush #116
    //   25: iinc #0, 1
    //   28: aload_2
    //   29: iload_0
    //   30: dup
    //   31: iload_1
    //   32: iadd
    //   33: invokevirtual substring : (II)Ljava/lang/String;
    //   36: iconst_m1
    //   37: goto -> 142
    //   40: aload #5
    //   42: swap
    //   43: iload_3
    //   44: iinc #3, 1
    //   47: swap
    //   48: aastore
    //   49: iload_0
    //   50: iload_1
    //   51: iadd
    //   52: dup
    //   53: istore_0
    //   54: iload #4
    //   56: if_icmpge -> 68
    //   59: aload_2
    //   60: iload_0
    //   61: invokevirtual charAt : (I)C
    //   64: istore_1
    //   65: goto -> 23
    //   68: ldc 'L8Â¢Ã¼\\tÂœÂ‹ZNHÂ¥T'
    //   70: dup
    //   71: astore_2
    //   72: invokevirtual length : ()I
    //   75: istore #4
    //   77: iconst_4
    //   78: istore_1
    //   79: iconst_m1
    //   80: istore_0
    //   81: bipush #50
    //   83: iinc #0, 1
    //   86: aload_2
    //   87: iload_0
    //   88: dup
    //   89: iload_1
    //   90: iadd
    //   91: invokevirtual substring : (II)Ljava/lang/String;
    //   94: iconst_0
    //   95: goto -> 142
    //   98: aload #5
    //   100: swap
    //   101: iload_3
    //   102: iinc #3, 1
    //   105: swap
    //   106: aastore
    //   107: iload_0
    //   108: iload_1
    //   109: iadd
    //   110: dup
    //   111: istore_0
    //   112: iload #4
    //   114: if_icmpge -> 126
    //   117: aload_2
    //   118: iload_0
    //   119: invokevirtual charAt : (I)C
    //   122: istore_1
    //   123: goto -> 81
    //   126: aload #5
    //   128: putstatic burp/Zbze.a : [Ljava/lang/String;
    //   131: bipush #11
    //   133: anewarray java/lang/String
    //   136: putstatic burp/Zbze.b : [Ljava/lang/String;
    //   139: goto -> 300
    //   142: dup_x2
    //   143: pop
    //   144: invokevirtual toCharArray : ()[C
    //   147: dup_x1
    //   148: arraylength
    //   149: dup_x2
    //   150: pop
    //   151: iconst_0
    //   152: istore #6
    //   154: dup2_x1
    //   155: pop2
    //   156: dup_x2
    //   157: iconst_1
    //   158: if_icmpgt -> 259
    //   161: dup2
    //   162: swap
    //   163: iload #6
    //   165: dup2_x1
    //   166: caload
    //   167: swap
    //   168: iload #6
    //   170: bipush #7
    //   172: irem
    //   173: tableswitch default -> 241, 0 -> 212, 1 -> 217, 2 -> 221, 3 -> 226, 4 -> 231, 5 -> 236
    //   212: bipush #115
    //   214: goto -> 243
    //   217: iconst_2
    //   218: goto -> 243
    //   221: bipush #109
    //   223: goto -> 243
    //   226: bipush #100
    //   228: goto -> 243
    //   231: bipush #102
    //   233: goto -> 243
    //   236: bipush #125
    //   238: goto -> 243
    //   241: bipush #24
    //   243: ixor
    //   244: ixor
    //   245: i2c
    //   246: castore
    //   247: iinc #6, 1
    //   250: dup
    //   251: ifne -> 259
    //   254: dup2
    //   255: dup_x1
    //   256: goto -> 165
    //   259: dup2_x1
    //   260: pop2
    //   261: dup_x2
    //   262: iload #6
    //   264: if_icmpgt -> 161
    //   267: pop
    //   268: new java/lang/String
    //   271: dup_x1
    //   272: swap
    //   273: invokespecial <init> : ([C)V
    //   276: invokevirtual intern : ()Ljava/lang/String;
    //   279: swap
    //   280: pop
    //   281: swap
    //   282: tableswitch default -> 40, 0 -> 98
    //   300: sipush #-26003
    //   303: sipush #31529
    //   306: invokestatic a : (II)Ljava/lang/String;
    //   309: putstatic burp/Zbze.ZK : Ljava/lang/String;
    //   312: new java/math/BigInteger
    //   315: dup
    //   316: iconst_1
    //   317: bipush #32
    //   319: newarray byte
    //   321: dup
    //   322: iconst_0
    //   323: bipush #114
    //   325: bastore
    //   326: dup
    //   327: iconst_1
    //   328: bipush #51
    //   330: bastore
    //   331: dup
    //   332: iconst_2
    //   333: iconst_5
    //   334: bastore
    //   335: dup
    //   336: iconst_3
    //   337: bipush #87
    //   339: bastore
    //   340: dup
    //   341: iconst_4
    //   342: bipush #114
    //   344: bastore
    //   345: dup
    //   346: iconst_5
    //   347: bipush #79
    //   349: bastore
    //   350: dup
    //   351: bipush #6
    //   353: bipush #-99
    //   355: bastore
    //   356: dup
    //   357: bipush #7
    //   359: bipush #-13
    //   361: bastore
    //   362: dup
    //   363: bipush #8
    //   365: bipush #114
    //   367: bastore
    //   368: dup
    //   369: bipush #9
    //   371: bipush #38
    //   373: bastore
    //   374: dup
    //   375: bipush #10
    //   377: bipush #-109
    //   379: bastore
    //   380: dup
    //   381: bipush #11
    //   383: bipush #-66
    //   385: bastore
    //   386: dup
    //   387: bipush #12
    //   389: bipush #-29
    //   391: bastore
    //   392: dup
    //   393: bipush #13
    //   395: bipush #117
    //   397: bastore
    //   398: dup
    //   399: bipush #14
    //   401: bipush #-7
    //   403: bastore
    //   404: dup
    //   405: bipush #15
    //   407: bipush #124
    //   409: bastore
    //   410: dup
    //   411: bipush #16
    //   413: bipush #-13
    //   415: bastore
    //   416: dup
    //   417: bipush #17
    //   419: bipush #-120
    //   421: bastore
    //   422: dup
    //   423: bipush #18
    //   425: bipush #-68
    //   427: bastore
    //   428: dup
    //   429: bipush #19
    //   431: bipush #-41
    //   433: bastore
    //   434: dup
    //   435: bipush #20
    //   437: bipush #-51
    //   439: bastore
    //   440: dup
    //   441: bipush #21
    //   443: bipush #74
    //   445: bastore
    //   446: dup
    //   447: bipush #22
    //   449: bipush #-67
    //   451: bastore
    //   452: dup
    //   453: bipush #23
    //   455: bipush #-50
    //   457: bastore
    //   458: dup
    //   459: bipush #24
    //   461: bipush #-13
    //   463: bastore
    //   464: dup
    //   465: bipush #25
    //   467: bipush #94
    //   469: bastore
    //   470: dup
    //   471: bipush #26
    //   473: bipush #99
    //   475: bastore
    //   476: dup
    //   477: bipush #27
    //   479: bipush #-24
    //   481: bastore
    //   482: dup
    //   483: bipush #28
    //   485: bipush #-90
    //   487: bastore
    //   488: dup
    //   489: bipush #29
    //   491: bipush #-87
    //   493: bastore
    //   494: dup
    //   495: bipush #30
    //   497: bipush #120
    //   499: bastore
    //   500: dup
    //   501: bipush #31
    //   503: bipush #113
    //   505: bastore
    //   506: invokespecial <init> : (I[B)V
    //   509: putstatic burp/Zbze.ZM : Ljava/lang/Object;
    //   512: return
  }
  
  private static Throwable a(Throwable paramThrowable) {
    return paramThrowable;
  }
  
  private static String a(int paramInt1, int paramInt2) {
    int i = (paramInt1 ^ 0xFFFF9A65) & 0xFFFF;
    if (b[i] == null) {
      char[] arrayOfChar = a[i].toCharArray();
      switch (arrayOfChar[0] & 0xFF) {
        case 0:
        
        case 1:
        
        case 2:
        
        case 3:
        
        case 4:
        
        case 5:
        
        case 6:
        
        case 7:
        
        case 8:
        
        case 9:
        
        case 10:
        
        case 11:
        
        case 12:
        
        case 13:
        
        case 14:
        
        case 15:
        
        case 16:
        
        case 17:
        
        case 18:
        
        case 19:
        
        case 20:
        
        case 21:
        
        case 22:
        
        case 23:
        
        case 24:
        
        case 25:
        
        case 26:
        
        case 27:
        
        case 28:
        
        case 29:
        
        case 30:
        
        case 31:
        
        case 32:
        
        case 33:
        
        case 34:
        
        case 35:
        
        case 36:
        
        case 37:
        
        case 38:
        
        case 39:
        
        case 40:
        
        case 41:
        
        case 42:
        
        case 43:
        
        case 44:
        
        case 45:
        
        case 46:
        
        case 47:
        
        case 48:
        
        case 49:
        
        case 50:
        
        case 51:
        
        case 52:
        
        case 53:
        
        case 54:
        
        case 55:
        
        case 56:
        
        case 57:
        
        case 58:
        
        case 59:
        
        case 60:
        
        case 61:
        
        case 62:
        
        case 63:
        
        case 64:
        
        case 65:
        
        case 66:
        
        case 67:
        
        case 68:
        
        case 69:
        
        case 70:
        
        case 71:
        
        case 72:
        
        case 73:
        
        case 74:
        
        case 75:
        
        case 76:
        
        case 77:
        
        case 78:
        
        case 79:
        
        case 80:
        
        case 81:
        
        case 82:
        
        case 83:
        
        case 84:
        
        case 85:
        
        case 86:
        
        case 87:
        
        case 88:
        
        case 89:
        
        case 90:
        
        case 91:
        
        case 92:
        
        case 93:
        
        case 94:
        
        case 95:
        
        case 96:
        
        case 97:
        
        case 98:
        
        case 99:
        
        case 100:
        
        case 101:
        
        case 102:
        
        case 103:
        
        case 104:
        
        case 105:
        
        case 106:
        
        case 107:
        
        case 108:
        
        case 109:
        
        case 110:
        
        case 111:
        
        case 112:
        
        case 113:
        
        case 114:
        
        case 115:
        
        case 116:
        
        case 117:
        
        case 118:
        
        case 119:
        
        case 120:
        
        case 121:
        
        case 122:
        
        case 123:
        
        case 124:
        
        case 125:
        
        case 126:
        
        case 127:
        
        case 128:
        
        case 129:
        
        case 130:
        
        case 131:
        
        case 132:
        
        case 133:
        
        case 134:
        
        case 135:
        
        case 136:
        
        case 137:
        
        case 138:
        
        case 139:
        
        case 140:
        
        case 141:
        
        case 142:
        
        case 143:
        
        case 144:
        
        case 145:
        
        case 146:
        
        case 147:
        
        case 148:
        
        case 149:
        
        case 150:
        
        case 151:
        
        case 152:
        
        case 153:
        
        case 154:
        
        case 155:
        
        case 156:
        
        case 157:
        
        case 158:
        
        case 159:
        
        case 160:
        
        case 161:
        
        case 162:
        
        case 163:
        
        case 164:
        
        case 165:
        
        case 166:
        
        case 167:
        
        case 168:
        
        case 169:
        
        case 170:
        
        case 171:
        
        case 172:
        
        case 173:
        
        case 174:
        
        case 175:
        
        case 176:
        
        case 177:
        
        case 178:
        
        case 179:
        
        case 180:
        
        case 181:
        
        case 182:
        
        case 183:
        
        case 184:
        
        case 185:
        
        case 186:
        
        case 187:
        
        case 188:
        
        case 189:
        
        case 190:
        
        case 191:
        
        case 192:
        
        case 193:
        
        case 194:
        
        case 195:
        
        case 196:
        
        case 197:
        
        case 198:
        
        case 199:
        
        case 200:
        
        case 201:
        
        case 202:
        
        case 203:
        
        case 204:
        
        case 205:
        
        case 206:
        
        case 207:
        
        case 208:
        
        case 209:
        
        case 210:
        
        case 211:
        
        case 212:
        
        case 213:
        
        case 214:
        
        case 215:
        
        case 216:
        
        case 217:
        
        case 218:
        
        case 219:
        
        case 220:
        
        case 221:
        
        case 222:
        
        case 223:
        
        case 224:
        
        case 225:
        
        case 226:
        
        case 227:
        
        case 228:
        
        case 229:
        
        case 230:
        
        case 231:
        
        case 232:
        
        case 233:
        
        case 234:
        
        case 235:
        
        case 236:
        
        case 237:
        
        case 238:
        
        case 239:
        
        case 240:
        
        case 241:
        
        case 242:
        
        case 243:
        
        case 244:
        
        case 245:
        
        case 246:
        
        case 247:
        
        case 248:
        
        case 249:
        
        case 250:
        
        case 251:
        
        case 252:
        
        case 253:
        
        case 254:
        
        default:
          break;
      } 
      byte b1 = 13;
      int j = (paramInt2 & 0xFF) - b1;
      if (j < 0)
        j += 256; 
      int k = ((paramInt2 & 0xFFFF) >>> 8) - b1;
      if (k < 0)
        k += 256; 
      for (byte b2 = 0; b2 < arrayOfChar.length; b2++) {
        int m = b2 % 2;
        if (m == 0) {
          arrayOfChar[b2] = (char)(arrayOfChar[b2] ^ j);
          j = ((j >>> 3 | j << 5) ^ arrayOfChar[b2]) & 0xFF;
        } else {
          arrayOfChar[b2] = (char)(arrayOfChar[b2] ^ k);
          k = ((k >>> 3 | k << 5) ^ arrayOfChar[b2]) & 0xFF;
        } 
      } 
      b[i] = (new String(arrayOfChar)).intern();
    } 
    return b[i];
  }
}


/* Location:              C:\Program Files\BurpSuitePro\burpsuite_pro.jar!\burp\Zbze.class
 * Java compiler version: 21 (65.0)
 * JD-Core Version:       1.1.3
 */