package burp;

import java.math.BigInteger;

class Zct extends ClassLoader {
  static Object ZW;
  
  static String Zy;
  
  private static final String[] a;
  
  private static final String[] b;
  
  static boolean Zh(Object[] paramArrayOfObject, Object paramObject) throws Throwable {
    // Byte code:
    //   0: invokestatic ZN : ()Z
    //   3: istore_2
    //   4: sipush #-11945
    //   7: sipush #6701
    //   10: invokestatic a : (II)Ljava/lang/String;
    //   13: invokestatic forName : (Ljava/lang/String;)Ljava/lang/Class;
    //   16: invokestatic Zz : (Ljava/lang/Object;)V
    //   19: new java/lang/StringBuilder
    //   22: dup
    //   23: invokespecial <init> : ()V
    //   26: astore_3
    //   27: iconst_0
    //   28: istore #4
    //   30: iload #4
    //   32: bipush #32
    //   34: if_icmpge -> 1367
    //   37: iload #4
    //   39: tableswitch default -> 1360, 0 -> 180, 1 -> 217, 2 -> 254, 3 -> 291, 4 -> 328, 5 -> 365, 6 -> 402, 7 -> 439, 8 -> 476, 9 -> 513, 10 -> 550, 11 -> 587, 12 -> 624, 13 -> 661, 14 -> 698, 15 -> 735, 16 -> 772, 17 -> 809, 18 -> 846, 19 -> 883, 20 -> 920, 21 -> 957, 22 -> 994, 23 -> 1031, 24 -> 1068, 25 -> 1105, 26 -> 1142, 27 -> 1179, 28 -> 1216, 29 -> 1253, 30 -> 1290, 31 -> 1327
    //   180: aload_3
    //   181: getstatic burp/Zgb9.Zk : Ljava/lang/String;
    //   184: getstatic burp/Zs_3.ZZ : Ljava/lang/Object;
    //   187: checkcast java/math/BigInteger
    //   190: invokevirtual intValue : ()I
    //   193: bipush #32
    //   195: irem
    //   196: invokestatic abs : (I)I
    //   199: invokevirtual charAt : (I)C
    //   202: invokevirtual append : (C)Ljava/lang/StringBuilder;
    //   205: pop
    //   206: iload_2
    //   207: ifne -> 1360
    //   210: goto -> 217
    //   213: invokestatic a : (Ljava/lang/Throwable;)Ljava/lang/Throwable;
    //   216: athrow
    //   217: aload_3
    //   218: getstatic burp/Zzky.Zj : Ljava/lang/String;
    //   221: getstatic burp/Zx_s.ZX : Ljava/lang/Object;
    //   224: checkcast java/math/BigInteger
    //   227: invokevirtual intValue : ()I
    //   230: bipush #32
    //   232: irem
    //   233: invokestatic abs : (I)I
    //   236: invokevirtual charAt : (I)C
    //   239: invokevirtual append : (C)Ljava/lang/StringBuilder;
    //   242: pop
    //   243: iload_2
    //   244: ifne -> 1360
    //   247: goto -> 254
    //   250: invokestatic a : (Ljava/lang/Throwable;)Ljava/lang/Throwable;
    //   253: athrow
    //   254: aload_3
    //   255: getstatic burp/Zmdm.Za : Ljava/lang/String;
    //   258: getstatic burp/Zewo.ZZ : Ljava/lang/Object;
    //   261: checkcast java/math/BigInteger
    //   264: invokevirtual intValue : ()I
    //   267: bipush #32
    //   269: irem
    //   270: invokestatic abs : (I)I
    //   273: invokevirtual charAt : (I)C
    //   276: invokevirtual append : (C)Ljava/lang/StringBuilder;
    //   279: pop
    //   280: iload_2
    //   281: ifne -> 1360
    //   284: goto -> 291
    //   287: invokestatic a : (Ljava/lang/Throwable;)Ljava/lang/Throwable;
    //   290: athrow
    //   291: aload_3
    //   292: getstatic burp/Zs15.Zs : Ljava/lang/String;
    //   295: getstatic burp/Zzrb.Zj : Ljava/lang/Object;
    //   298: checkcast java/math/BigInteger
    //   301: invokevirtual intValue : ()I
    //   304: bipush #32
    //   306: irem
    //   307: invokestatic abs : (I)I
    //   310: invokevirtual charAt : (I)C
    //   313: invokevirtual append : (C)Ljava/lang/StringBuilder;
    //   316: pop
    //   317: iload_2
    //   318: ifne -> 1360
    //   321: goto -> 328
    //   324: invokestatic a : (Ljava/lang/Throwable;)Ljava/lang/Throwable;
    //   327: athrow
    //   328: aload_3
    //   329: getstatic burp/Zkvr.Zm : Ljava/lang/String;
    //   332: getstatic burp/Zrcx.Za : Ljava/lang/Object;
    //   335: checkcast java/math/BigInteger
    //   338: invokevirtual intValue : ()I
    //   341: bipush #32
    //   343: irem
    //   344: invokestatic abs : (I)I
    //   347: invokevirtual charAt : (I)C
    //   350: invokevirtual append : (C)Ljava/lang/StringBuilder;
    //   353: pop
    //   354: iload_2
    //   355: ifne -> 1360
    //   358: goto -> 365
    //   361: invokestatic a : (Ljava/lang/Throwable;)Ljava/lang/Throwable;
    //   364: athrow
    //   365: aload_3
    //   366: getstatic burp/Zm6h.Za : Ljava/lang/String;
    //   369: getstatic burp/Zgnp.Zm : Ljava/lang/Object;
    //   372: checkcast java/math/BigInteger
    //   375: invokevirtual intValue : ()I
    //   378: bipush #32
    //   380: irem
    //   381: invokestatic abs : (I)I
    //   384: invokevirtual charAt : (I)C
    //   387: invokevirtual append : (C)Ljava/lang/StringBuilder;
    //   390: pop
    //   391: iload_2
    //   392: ifne -> 1360
    //   395: goto -> 402
    //   398: invokestatic a : (Ljava/lang/Throwable;)Ljava/lang/Throwable;
    //   401: athrow
    //   402: aload_3
    //   403: getstatic burp/Zstf.ZZ : Ljava/lang/String;
    //   406: getstatic burp/Zxoa.Zr : Ljava/lang/Object;
    //   409: checkcast java/math/BigInteger
    //   412: invokevirtual intValue : ()I
    //   415: bipush #32
    //   417: irem
    //   418: invokestatic abs : (I)I
    //   421: invokevirtual charAt : (I)C
    //   424: invokevirtual append : (C)Ljava/lang/StringBuilder;
    //   427: pop
    //   428: iload_2
    //   429: ifne -> 1360
    //   432: goto -> 439
    //   435: invokestatic a : (Ljava/lang/Throwable;)Ljava/lang/Throwable;
    //   438: athrow
    //   439: aload_3
    //   440: getstatic burp/Zsq5.ZA : Ljava/lang/String;
    //   443: getstatic burp/Zzqj.Zq : Ljava/lang/Object;
    //   446: checkcast java/math/BigInteger
    //   449: invokevirtual intValue : ()I
    //   452: bipush #32
    //   454: irem
    //   455: invokestatic abs : (I)I
    //   458: invokevirtual charAt : (I)C
    //   461: invokevirtual append : (C)Ljava/lang/StringBuilder;
    //   464: pop
    //   465: iload_2
    //   466: ifne -> 1360
    //   469: goto -> 476
    //   472: invokestatic a : (Ljava/lang/Throwable;)Ljava/lang/Throwable;
    //   475: athrow
    //   476: aload_3
    //   477: getstatic burp/Zeno.ZL : Ljava/lang/String;
    //   480: getstatic burp/Zrd4.Ze : Ljava/lang/Object;
    //   483: checkcast java/math/BigInteger
    //   486: invokevirtual intValue : ()I
    //   489: bipush #32
    //   491: irem
    //   492: invokestatic abs : (I)I
    //   495: invokevirtual charAt : (I)C
    //   498: invokevirtual append : (C)Ljava/lang/StringBuilder;
    //   501: pop
    //   502: iload_2
    //   503: ifne -> 1360
    //   506: goto -> 513
    //   509: invokestatic a : (Ljava/lang/Throwable;)Ljava/lang/Throwable;
    //   512: athrow
    //   513: aload_3
    //   514: getstatic burp/Zgmo.Zr : Ljava/lang/String;
    //   517: getstatic burp/Zr1t.ZP : Ljava/lang/Object;
    //   520: checkcast java/math/BigInteger
    //   523: invokevirtual intValue : ()I
    //   526: bipush #32
    //   528: irem
    //   529: invokestatic abs : (I)I
    //   532: invokevirtual charAt : (I)C
    //   535: invokevirtual append : (C)Ljava/lang/StringBuilder;
    //   538: pop
    //   539: iload_2
    //   540: ifne -> 1360
    //   543: goto -> 550
    //   546: invokestatic a : (Ljava/lang/Throwable;)Ljava/lang/Throwable;
    //   549: athrow
    //   550: aload_3
    //   551: getstatic burp/Zxdy.Zm : Ljava/lang/String;
    //   554: getstatic burp/Zrfh.ZJ : Ljava/lang/Object;
    //   557: checkcast java/math/BigInteger
    //   560: invokevirtual intValue : ()I
    //   563: bipush #32
    //   565: irem
    //   566: invokestatic abs : (I)I
    //   569: invokevirtual charAt : (I)C
    //   572: invokevirtual append : (C)Ljava/lang/StringBuilder;
    //   575: pop
    //   576: iload_2
    //   577: ifne -> 1360
    //   580: goto -> 587
    //   583: invokestatic a : (Ljava/lang/Throwable;)Ljava/lang/Throwable;
    //   586: athrow
    //   587: aload_3
    //   588: getstatic burp/Ze_l.ZY : Ljava/lang/String;
    //   591: getstatic burp/Zb14.ZT : Ljava/lang/Object;
    //   594: checkcast java/math/BigInteger
    //   597: invokevirtual intValue : ()I
    //   600: bipush #32
    //   602: irem
    //   603: invokestatic abs : (I)I
    //   606: invokevirtual charAt : (I)C
    //   609: invokevirtual append : (C)Ljava/lang/StringBuilder;
    //   612: pop
    //   613: iload_2
    //   614: ifne -> 1360
    //   617: goto -> 624
    //   620: invokestatic a : (Ljava/lang/Throwable;)Ljava/lang/Throwable;
    //   623: athrow
    //   624: aload_3
    //   625: getstatic burp/Zs56.ZW : Ljava/lang/String;
    //   628: getstatic burp/Zkw.ZY : Ljava/lang/Object;
    //   631: checkcast java/math/BigInteger
    //   634: invokevirtual intValue : ()I
    //   637: bipush #32
    //   639: irem
    //   640: invokestatic abs : (I)I
    //   643: invokevirtual charAt : (I)C
    //   646: invokevirtual append : (C)Ljava/lang/StringBuilder;
    //   649: pop
    //   650: iload_2
    //   651: ifne -> 1360
    //   654: goto -> 661
    //   657: invokestatic a : (Ljava/lang/Throwable;)Ljava/lang/Throwable;
    //   660: athrow
    //   661: aload_3
    //   662: getstatic burp/Zex5.Zh : Ljava/lang/String;
    //   665: getstatic burp/Ztcv.ZY : Ljava/lang/Object;
    //   668: checkcast java/math/BigInteger
    //   671: invokevirtual intValue : ()I
    //   674: bipush #32
    //   676: irem
    //   677: invokestatic abs : (I)I
    //   680: invokevirtual charAt : (I)C
    //   683: invokevirtual append : (C)Ljava/lang/StringBuilder;
    //   686: pop
    //   687: iload_2
    //   688: ifne -> 1360
    //   691: goto -> 698
    //   694: invokestatic a : (Ljava/lang/Throwable;)Ljava/lang/Throwable;
    //   697: athrow
    //   698: aload_3
    //   699: getstatic burp/Zgvl.Zc : Ljava/lang/String;
    //   702: getstatic burp/Zljx.ZZ : Ljava/lang/Object;
    //   705: checkcast java/math/BigInteger
    //   708: invokevirtual intValue : ()I
    //   711: bipush #32
    //   713: irem
    //   714: invokestatic abs : (I)I
    //   717: invokevirtual charAt : (I)C
    //   720: invokevirtual append : (C)Ljava/lang/StringBuilder;
    //   723: pop
    //   724: iload_2
    //   725: ifne -> 1360
    //   728: goto -> 735
    //   731: invokestatic a : (Ljava/lang/Throwable;)Ljava/lang/Throwable;
    //   734: athrow
    //   735: aload_3
    //   736: getstatic burp/Zxdh.Zj : Ljava/lang/String;
    //   739: getstatic burp/Zsmn.Zq : Ljava/lang/Object;
    //   742: checkcast java/math/BigInteger
    //   745: invokevirtual intValue : ()I
    //   748: bipush #32
    //   750: irem
    //   751: invokestatic abs : (I)I
    //   754: invokevirtual charAt : (I)C
    //   757: invokevirtual append : (C)Ljava/lang/StringBuilder;
    //   760: pop
    //   761: iload_2
    //   762: ifne -> 1360
    //   765: goto -> 772
    //   768: invokestatic a : (Ljava/lang/Throwable;)Ljava/lang/Throwable;
    //   771: athrow
    //   772: aload_3
    //   773: getstatic burp/Zb8v.Zo : Ljava/lang/String;
    //   776: getstatic burp/Zez0.ZT : Ljava/lang/Object;
    //   779: checkcast java/math/BigInteger
    //   782: invokevirtual intValue : ()I
    //   785: bipush #32
    //   787: irem
    //   788: invokestatic abs : (I)I
    //   791: invokevirtual charAt : (I)C
    //   794: invokevirtual append : (C)Ljava/lang/StringBuilder;
    //   797: pop
    //   798: iload_2
    //   799: ifne -> 1360
    //   802: goto -> 809
    //   805: invokestatic a : (Ljava/lang/Throwable;)Ljava/lang/Throwable;
    //   808: athrow
    //   809: aload_3
    //   810: getstatic burp/Zrhu.ZJ : Ljava/lang/String;
    //   813: getstatic burp/Zl8i.ZY : Ljava/lang/Object;
    //   816: checkcast java/math/BigInteger
    //   819: invokevirtual intValue : ()I
    //   822: bipush #32
    //   824: irem
    //   825: invokestatic abs : (I)I
    //   828: invokevirtual charAt : (I)C
    //   831: invokevirtual append : (C)Ljava/lang/StringBuilder;
    //   834: pop
    //   835: iload_2
    //   836: ifne -> 1360
    //   839: goto -> 846
    //   842: invokestatic a : (Ljava/lang/Throwable;)Ljava/lang/Throwable;
    //   845: athrow
    //   846: aload_3
    //   847: getstatic burp/Zmy3.ZP : Ljava/lang/String;
    //   850: getstatic burp/Zzmo.ZI : Ljava/lang/Object;
    //   853: checkcast java/math/BigInteger
    //   856: invokevirtual intValue : ()I
    //   859: bipush #32
    //   861: irem
    //   862: invokestatic abs : (I)I
    //   865: invokevirtual charAt : (I)C
    //   868: invokevirtual append : (C)Ljava/lang/StringBuilder;
    //   871: pop
    //   872: iload_2
    //   873: ifne -> 1360
    //   876: goto -> 883
    //   879: invokestatic a : (Ljava/lang/Throwable;)Ljava/lang/Throwable;
    //   882: athrow
    //   883: aload_3
    //   884: getstatic burp/Zx0t.Ze : Ljava/lang/String;
    //   887: getstatic burp/Zzoc.Zx : Ljava/lang/Object;
    //   890: checkcast java/math/BigInteger
    //   893: invokevirtual intValue : ()I
    //   896: bipush #32
    //   898: irem
    //   899: invokestatic abs : (I)I
    //   902: invokevirtual charAt : (I)C
    //   905: invokevirtual append : (C)Ljava/lang/StringBuilder;
    //   908: pop
    //   909: iload_2
    //   910: ifne -> 1360
    //   913: goto -> 920
    //   916: invokestatic a : (Ljava/lang/Throwable;)Ljava/lang/Throwable;
    //   919: athrow
    //   920: aload_3
    //   921: getstatic burp/Zk8b.ZT : Ljava/lang/String;
    //   924: getstatic burp/Zzh0.Z_ : Ljava/lang/Object;
    //   927: checkcast java/math/BigInteger
    //   930: invokevirtual intValue : ()I
    //   933: bipush #32
    //   935: irem
    //   936: invokestatic abs : (I)I
    //   939: invokevirtual charAt : (I)C
    //   942: invokevirtual append : (C)Ljava/lang/StringBuilder;
    //   945: pop
    //   946: iload_2
    //   947: ifne -> 1360
    //   950: goto -> 957
    //   953: invokestatic a : (Ljava/lang/Throwable;)Ljava/lang/Throwable;
    //   956: athrow
    //   957: aload_3
    //   958: getstatic burp/Zgvf.ZM : Ljava/lang/String;
    //   961: getstatic burp/Zlsw.ZJ : Ljava/lang/Object;
    //   964: checkcast java/math/BigInteger
    //   967: invokevirtual intValue : ()I
    //   970: bipush #32
    //   972: irem
    //   973: invokestatic abs : (I)I
    //   976: invokevirtual charAt : (I)C
    //   979: invokevirtual append : (C)Ljava/lang/StringBuilder;
    //   982: pop
    //   983: iload_2
    //   984: ifne -> 1360
    //   987: goto -> 994
    //   990: invokestatic a : (Ljava/lang/Throwable;)Ljava/lang/Throwable;
    //   993: athrow
    //   994: aload_3
    //   995: getstatic burp/Zrnu.ZO : Ljava/lang/String;
    //   998: getstatic burp/Zl5.ZY : Ljava/lang/Object;
    //   1001: checkcast java/math/BigInteger
    //   1004: invokevirtual intValue : ()I
    //   1007: bipush #32
    //   1009: irem
    //   1010: invokestatic abs : (I)I
    //   1013: invokevirtual charAt : (I)C
    //   1016: invokevirtual append : (C)Ljava/lang/StringBuilder;
    //   1019: pop
    //   1020: iload_2
    //   1021: ifne -> 1360
    //   1024: goto -> 1031
    //   1027: invokestatic a : (Ljava/lang/Throwable;)Ljava/lang/Throwable;
    //   1030: athrow
    //   1031: aload_3
    //   1032: getstatic burp/Zrpy.Zr : Ljava/lang/String;
    //   1035: getstatic burp/Zltz.Zg : Ljava/lang/Object;
    //   1038: checkcast java/math/BigInteger
    //   1041: invokevirtual intValue : ()I
    //   1044: bipush #32
    //   1046: irem
    //   1047: invokestatic abs : (I)I
    //   1050: invokevirtual charAt : (I)C
    //   1053: invokevirtual append : (C)Ljava/lang/StringBuilder;
    //   1056: pop
    //   1057: iload_2
    //   1058: ifne -> 1360
    //   1061: goto -> 1068
    //   1064: invokestatic a : (Ljava/lang/Throwable;)Ljava/lang/Throwable;
    //   1067: athrow
    //   1068: aload_3
    //   1069: getstatic burp/Zkgp.ZM : Ljava/lang/String;
    //   1072: getstatic burp/Ztjh.ZU : Ljava/lang/Object;
    //   1075: checkcast java/math/BigInteger
    //   1078: invokevirtual intValue : ()I
    //   1081: bipush #32
    //   1083: irem
    //   1084: invokestatic abs : (I)I
    //   1087: invokevirtual charAt : (I)C
    //   1090: invokevirtual append : (C)Ljava/lang/StringBuilder;
    //   1093: pop
    //   1094: iload_2
    //   1095: ifne -> 1360
    //   1098: goto -> 1105
    //   1101: invokestatic a : (Ljava/lang/Throwable;)Ljava/lang/Throwable;
    //   1104: athrow
    //   1105: aload_3
    //   1106: getstatic burp/Zre1.ZA : Ljava/lang/String;
    //   1109: getstatic burp/Zdm.ZA : Ljava/lang/Object;
    //   1112: checkcast java/math/BigInteger
    //   1115: invokevirtual intValue : ()I
    //   1118: bipush #32
    //   1120: irem
    //   1121: invokestatic abs : (I)I
    //   1124: invokevirtual charAt : (I)C
    //   1127: invokevirtual append : (C)Ljava/lang/StringBuilder;
    //   1130: pop
    //   1131: iload_2
    //   1132: ifne -> 1360
    //   1135: goto -> 1142
    //   1138: invokestatic a : (Ljava/lang/Throwable;)Ljava/lang/Throwable;
    //   1141: athrow
    //   1142: aload_3
    //   1143: getstatic burp/Zeoi.Zh : Ljava/lang/String;
    //   1146: getstatic burp/Zgw_.Zf : Ljava/lang/Object;
    //   1149: checkcast java/math/BigInteger
    //   1152: invokevirtual intValue : ()I
    //   1155: bipush #32
    //   1157: irem
    //   1158: invokestatic abs : (I)I
    //   1161: invokevirtual charAt : (I)C
    //   1164: invokevirtual append : (C)Ljava/lang/StringBuilder;
    //   1167: pop
    //   1168: iload_2
    //   1169: ifne -> 1360
    //   1172: goto -> 1179
    //   1175: invokestatic a : (Ljava/lang/Throwable;)Ljava/lang/Throwable;
    //   1178: athrow
    //   1179: aload_3
    //   1180: getstatic burp/Zgfm.ZE : Ljava/lang/String;
    //   1183: getstatic burp/Zmrc.ZU : Ljava/lang/Object;
    //   1186: checkcast java/math/BigInteger
    //   1189: invokevirtual intValue : ()I
    //   1192: bipush #32
    //   1194: irem
    //   1195: invokestatic abs : (I)I
    //   1198: invokevirtual charAt : (I)C
    //   1201: invokevirtual append : (C)Ljava/lang/StringBuilder;
    //   1204: pop
    //   1205: iload_2
    //   1206: ifne -> 1360
    //   1209: goto -> 1216
    //   1212: invokestatic a : (Ljava/lang/Throwable;)Ljava/lang/Throwable;
    //   1215: athrow
    //   1216: aload_3
    //   1217: getstatic burp/Ztgj.Zw : Ljava/lang/String;
    //   1220: getstatic burp/Zkk6.Zb : Ljava/lang/Object;
    //   1223: checkcast java/math/BigInteger
    //   1226: invokevirtual intValue : ()I
    //   1229: bipush #32
    //   1231: irem
    //   1232: invokestatic abs : (I)I
    //   1235: invokevirtual charAt : (I)C
    //   1238: invokevirtual append : (C)Ljava/lang/StringBuilder;
    //   1241: pop
    //   1242: iload_2
    //   1243: ifne -> 1360
    //   1246: goto -> 1253
    //   1249: invokestatic a : (Ljava/lang/Throwable;)Ljava/lang/Throwable;
    //   1252: athrow
    //   1253: aload_3
    //   1254: getstatic burp/Zblv.ZF : Ljava/lang/String;
    //   1257: getstatic burp/Zrfh.ZJ : Ljava/lang/Object;
    //   1260: checkcast java/math/BigInteger
    //   1263: invokevirtual intValue : ()I
    //   1266: bipush #32
    //   1268: irem
    //   1269: invokestatic abs : (I)I
    //   1272: invokevirtual charAt : (I)C
    //   1275: invokevirtual append : (C)Ljava/lang/StringBuilder;
    //   1278: pop
    //   1279: iload_2
    //   1280: ifne -> 1360
    //   1283: goto -> 1290
    //   1286: invokestatic a : (Ljava/lang/Throwable;)Ljava/lang/Throwable;
    //   1289: athrow
    //   1290: aload_3
    //   1291: getstatic burp/Zblv.ZF : Ljava/lang/String;
    //   1294: getstatic burp/Zxti.ZJ : Ljava/lang/Object;
    //   1297: checkcast java/math/BigInteger
    //   1300: invokevirtual intValue : ()I
    //   1303: bipush #32
    //   1305: irem
    //   1306: invokestatic abs : (I)I
    //   1309: invokevirtual charAt : (I)C
    //   1312: invokevirtual append : (C)Ljava/lang/StringBuilder;
    //   1315: pop
    //   1316: iload_2
    //   1317: ifne -> 1360
    //   1320: goto -> 1327
    //   1323: invokestatic a : (Ljava/lang/Throwable;)Ljava/lang/Throwable;
    //   1326: athrow
    //   1327: aload_3
    //   1328: getstatic burp/Zz5l.ZH : Ljava/lang/String;
    //   1331: getstatic burp/Zkig.ZK : Ljava/lang/Object;
    //   1334: checkcast java/math/BigInteger
    //   1337: invokevirtual intValue : ()I
    //   1340: bipush #32
    //   1342: irem
    //   1343: invokestatic abs : (I)I
    //   1346: invokevirtual charAt : (I)C
    //   1349: invokevirtual append : (C)Ljava/lang/StringBuilder;
    //   1352: pop
    //   1353: goto -> 1360
    //   1356: invokestatic a : (Ljava/lang/Throwable;)Ljava/lang/Throwable;
    //   1359: athrow
    //   1360: iinc #4, 1
    //   1363: iload_2
    //   1364: ifne -> 30
    //   1367: aload_3
    //   1368: invokevirtual toString : ()Ljava/lang/String;
    //   1371: putstatic burp/Ztdt.Zk : Ljava/lang/String;
    //   1374: sipush #-11947
    //   1377: getstatic burp/Zmz.ZW : Ljava/lang/Object;
    //   1380: checkcast java/math/BigInteger
    //   1383: getstatic burp/Zx0t.Zt : Ljava/lang/Object;
    //   1386: checkcast java/math/BigInteger
    //   1389: invokevirtual subtract : (Ljava/math/BigInteger;)Ljava/math/BigInteger;
    //   1392: putstatic burp/Zxdy.ZZ : Ljava/lang/Object;
    //   1395: sipush #29685
    //   1398: getstatic burp/Zli5.Zt : Ljava/lang/Object;
    //   1401: checkcast java/math/BigInteger
    //   1404: getstatic burp/Zzmo.ZI : Ljava/lang/Object;
    //   1407: checkcast java/math/BigInteger
    //   1410: invokevirtual subtract : (Ljava/math/BigInteger;)Ljava/math/BigInteger;
    //   1413: putstatic burp/Zgta.ZF : Ljava/lang/Object;
    //   1416: invokestatic a : (II)Ljava/lang/String;
    //   1419: iconst_1
    //   1420: ldc burp/Zrxf
    //   1422: invokevirtual getClassLoader : ()Ljava/lang/ClassLoader;
    //   1425: invokestatic forName : (Ljava/lang/String;ZLjava/lang/ClassLoader;)Ljava/lang/Class;
    //   1428: invokevirtual getDeclaredFields : ()[Ljava/lang/reflect/Field;
    //   1431: astore #4
    //   1433: aload #4
    //   1435: arraylength
    //   1436: istore #5
    //   1438: iconst_0
    //   1439: istore #6
    //   1441: iload #6
    //   1443: iload #5
    //   1445: if_icmpge -> 1583
    //   1448: aload #4
    //   1450: iload #6
    //   1452: aaload
    //   1453: astore #7
    //   1455: aload #7
    //   1457: invokevirtual getModifiers : ()I
    //   1460: invokestatic isStatic : (I)Z
    //   1463: ifne -> 1473
    //   1466: goto -> 1576
    //   1469: invokestatic a : (Ljava/lang/Throwable;)Ljava/lang/Throwable;
    //   1472: athrow
    //   1473: aload #7
    //   1475: invokevirtual getType : ()Ljava/lang/Class;
    //   1478: astore #8
    //   1480: aload #8
    //   1482: ifnull -> 1563
    //   1485: aload #8
    //   1487: invokevirtual isPrimitive : ()Z
    //   1490: ifne -> 1563
    //   1493: goto -> 1500
    //   1496: invokestatic a : (Ljava/lang/Throwable;)Ljava/lang/Throwable;
    //   1499: athrow
    //   1500: aload #8
    //   1502: invokevirtual getPackage : ()Ljava/lang/Package;
    //   1505: ifnull -> 1563
    //   1508: goto -> 1515
    //   1511: invokestatic a : (Ljava/lang/Throwable;)Ljava/lang/Throwable;
    //   1514: athrow
    //   1515: aload #8
    //   1517: invokevirtual getPackage : ()Ljava/lang/Package;
    //   1520: invokevirtual getName : ()Ljava/lang/String;
    //   1523: ifnull -> 1563
    //   1526: goto -> 1533
    //   1529: invokestatic a : (Ljava/lang/Throwable;)Ljava/lang/Throwable;
    //   1532: athrow
    //   1533: aload #8
    //   1535: invokevirtual getPackage : ()Ljava/lang/Package;
    //   1538: invokevirtual getName : ()Ljava/lang/String;
    //   1541: sipush #-11951
    //   1544: sipush #329
    //   1547: invokestatic a : (II)Ljava/lang/String;
    //   1550: invokevirtual startsWith : (Ljava/lang/String;)Z
    //   1553: ifne -> 1563
    //   1556: goto -> 1563
    //   1559: invokestatic a : (Ljava/lang/Throwable;)Ljava/lang/Throwable;
    //   1562: athrow
    //   1563: aload #7
    //   1565: iconst_1
    //   1566: invokevirtual setAccessible : (Z)V
    //   1569: aload #7
    //   1571: aconst_null
    //   1572: invokevirtual get : (Ljava/lang/Object;)Ljava/lang/Object;
    //   1575: pop
    //   1576: iinc #6, 1
    //   1579: iload_2
    //   1580: ifne -> 1441
    //   1583: sipush #-11952
    //   1586: sipush #-10154
    //   1589: invokestatic a : (II)Ljava/lang/String;
    //   1592: invokestatic forName : (Ljava/lang/String;)Ljava/lang/Class;
    //   1595: invokevirtual getDeclaredMethods : ()[Ljava/lang/reflect/Method;
    //   1598: astore #4
    //   1600: aload #4
    //   1602: arraylength
    //   1603: istore #5
    //   1605: iconst_0
    //   1606: istore #6
    //   1608: iload #6
    //   1610: iload #5
    //   1612: if_icmpge -> 1745
    //   1615: aload #4
    //   1617: iload #6
    //   1619: aaload
    //   1620: astore #7
    //   1622: aload #7
    //   1624: invokevirtual getParameterTypes : ()[Ljava/lang/Class;
    //   1627: pop
    //   1628: aload #7
    //   1630: invokevirtual getModifiers : ()I
    //   1633: invokestatic isStatic : (I)Z
    //   1636: ifeq -> 1731
    //   1639: aload #7
    //   1641: invokevirtual getParameterTypes : ()[Ljava/lang/Class;
    //   1644: arraylength
    //   1645: iconst_2
    //   1646: if_icmpne -> 1731
    //   1649: goto -> 1656
    //   1652: invokestatic a : (Ljava/lang/Throwable;)Ljava/lang/Throwable;
    //   1655: athrow
    //   1656: aload #7
    //   1658: invokevirtual getReturnType : ()Ljava/lang/Class;
    //   1661: getstatic java/lang/Void.TYPE : Ljava/lang/Class;
    //   1664: invokevirtual equals : (Ljava/lang/Object;)Z
    //   1667: ifeq -> 1731
    //   1670: goto -> 1677
    //   1673: invokestatic a : (Ljava/lang/Throwable;)Ljava/lang/Throwable;
    //   1676: athrow
    //   1677: aload #7
    //   1679: iconst_1
    //   1680: invokevirtual setAccessible : (Z)V
    //   1683: aload #7
    //   1685: aconst_null
    //   1686: iconst_2
    //   1687: anewarray java/lang/Object
    //   1690: dup
    //   1691: iconst_0
    //   1692: aload_0
    //   1693: aastore
    //   1694: dup
    //   1695: iconst_1
    //   1696: aload_1
    //   1697: ifnonnull -> 1715
    //   1700: goto -> 1707
    //   1703: invokestatic a : (Ljava/lang/Throwable;)Ljava/lang/Throwable;
    //   1706: athrow
    //   1707: aload_1
    //   1708: goto -> 1722
    //   1711: invokestatic a : (Ljava/lang/Throwable;)Ljava/lang/Throwable;
    //   1714: athrow
    //   1715: aload_1
    //   1716: checkcast [B
    //   1719: invokevirtual clone : ()Ljava/lang/Object;
    //   1722: aastore
    //   1723: invokevirtual invoke : (Ljava/lang/Object;[Ljava/lang/Object;)Ljava/lang/Object;
    //   1726: pop
    //   1727: iload_2
    //   1728: ifne -> 1745
    //   1731: iinc #6, 1
    //   1734: iload_2
    //   1735: ifne -> 1608
    //   1738: goto -> 1745
    //   1741: invokestatic a : (Ljava/lang/Throwable;)Ljava/lang/Throwable;
    //   1744: athrow
    //   1745: getstatic burp/Zr_y.ZI : Ljava/lang/Object;
    //   1748: checkcast java/math/BigInteger
    //   1751: invokevirtual intValue : ()I
    //   1754: i2l
    //   1755: invokestatic currentTimeMillis : ()J
    //   1758: ladd
    //   1759: getstatic burp/Zldx.ZM : Ljava/lang/Object;
    //   1762: checkcast java/math/BigInteger
    //   1765: invokevirtual intValue : ()I
    //   1768: i2l
    //   1769: lcmp
    //   1770: ifge -> 2108
    //   1773: sipush #-11946
    //   1776: sipush #25453
    //   1779: invokestatic a : (II)Ljava/lang/String;
    //   1782: iconst_1
    //   1783: ldc burp/Zg5
    //   1785: invokevirtual getClassLoader : ()Ljava/lang/ClassLoader;
    //   1788: invokestatic forName : (Ljava/lang/String;ZLjava/lang/ClassLoader;)Ljava/lang/Class;
    //   1791: invokevirtual getDeclaredFields : ()[Ljava/lang/reflect/Field;
    //   1794: astore #4
    //   1796: aload #4
    //   1798: arraylength
    //   1799: istore #5
    //   1801: iconst_0
    //   1802: istore #6
    //   1804: iload #6
    //   1806: iload #5
    //   1808: if_icmpge -> 1946
    //   1811: aload #4
    //   1813: iload #6
    //   1815: aaload
    //   1816: astore #7
    //   1818: aload #7
    //   1820: invokevirtual getModifiers : ()I
    //   1823: invokestatic isStatic : (I)Z
    //   1826: ifne -> 1836
    //   1829: goto -> 1939
    //   1832: invokestatic a : (Ljava/lang/Throwable;)Ljava/lang/Throwable;
    //   1835: athrow
    //   1836: aload #7
    //   1838: invokevirtual getType : ()Ljava/lang/Class;
    //   1841: astore #8
    //   1843: aload #8
    //   1845: ifnull -> 1926
    //   1848: aload #8
    //   1850: invokevirtual isPrimitive : ()Z
    //   1853: ifne -> 1926
    //   1856: goto -> 1863
    //   1859: invokestatic a : (Ljava/lang/Throwable;)Ljava/lang/Throwable;
    //   1862: athrow
    //   1863: aload #8
    //   1865: invokevirtual getPackage : ()Ljava/lang/Package;
    //   1868: ifnull -> 1926
    //   1871: goto -> 1878
    //   1874: invokestatic a : (Ljava/lang/Throwable;)Ljava/lang/Throwable;
    //   1877: athrow
    //   1878: aload #8
    //   1880: invokevirtual getPackage : ()Ljava/lang/Package;
    //   1883: invokevirtual getName : ()Ljava/lang/String;
    //   1886: ifnull -> 1926
    //   1889: goto -> 1896
    //   1892: invokestatic a : (Ljava/lang/Throwable;)Ljava/lang/Throwable;
    //   1895: athrow
    //   1896: aload #8
    //   1898: invokevirtual getPackage : ()Ljava/lang/Package;
    //   1901: invokevirtual getName : ()Ljava/lang/String;
    //   1904: sipush #-11941
    //   1907: sipush #18919
    //   1910: invokestatic a : (II)Ljava/lang/String;
    //   1913: invokevirtual startsWith : (Ljava/lang/String;)Z
    //   1916: ifne -> 1926
    //   1919: goto -> 1926
    //   1922: invokestatic a : (Ljava/lang/Throwable;)Ljava/lang/Throwable;
    //   1925: athrow
    //   1926: aload #7
    //   1928: iconst_1
    //   1929: invokevirtual setAccessible : (Z)V
    //   1932: aload #7
    //   1934: aconst_null
    //   1935: invokevirtual get : (Ljava/lang/Object;)Ljava/lang/Object;
    //   1938: pop
    //   1939: iinc #6, 1
    //   1942: iload_2
    //   1943: ifne -> 1804
    //   1946: sipush #-11944
    //   1949: sipush #-3766
    //   1952: invokestatic a : (II)Ljava/lang/String;
    //   1955: invokestatic forName : (Ljava/lang/String;)Ljava/lang/Class;
    //   1958: invokevirtual getDeclaredMethods : ()[Ljava/lang/reflect/Method;
    //   1961: astore #4
    //   1963: aload #4
    //   1965: arraylength
    //   1966: istore #5
    //   1968: iconst_0
    //   1969: istore #6
    //   1971: iload #6
    //   1973: iload #5
    //   1975: if_icmpge -> 2108
    //   1978: aload #4
    //   1980: iload #6
    //   1982: aaload
    //   1983: astore #7
    //   1985: aload #7
    //   1987: invokevirtual getParameterTypes : ()[Ljava/lang/Class;
    //   1990: pop
    //   1991: aload #7
    //   1993: invokevirtual getModifiers : ()I
    //   1996: invokestatic isStatic : (I)Z
    //   1999: ifeq -> 2094
    //   2002: aload #7
    //   2004: invokevirtual getParameterTypes : ()[Ljava/lang/Class;
    //   2007: arraylength
    //   2008: iconst_2
    //   2009: if_icmpne -> 2094
    //   2012: goto -> 2019
    //   2015: invokestatic a : (Ljava/lang/Throwable;)Ljava/lang/Throwable;
    //   2018: athrow
    //   2019: aload #7
    //   2021: invokevirtual getReturnType : ()Ljava/lang/Class;
    //   2024: getstatic java/lang/Void.TYPE : Ljava/lang/Class;
    //   2027: invokevirtual equals : (Ljava/lang/Object;)Z
    //   2030: ifeq -> 2094
    //   2033: goto -> 2040
    //   2036: invokestatic a : (Ljava/lang/Throwable;)Ljava/lang/Throwable;
    //   2039: athrow
    //   2040: aload #7
    //   2042: iconst_1
    //   2043: invokevirtual setAccessible : (Z)V
    //   2046: aload #7
    //   2048: aconst_null
    //   2049: iconst_2
    //   2050: anewarray java/lang/Object
    //   2053: dup
    //   2054: iconst_0
    //   2055: aload_0
    //   2056: aastore
    //   2057: dup
    //   2058: iconst_1
    //   2059: aload_1
    //   2060: ifnonnull -> 2078
    //   2063: goto -> 2070
    //   2066: invokestatic a : (Ljava/lang/Throwable;)Ljava/lang/Throwable;
    //   2069: athrow
    //   2070: aload_1
    //   2071: goto -> 2085
    //   2074: invokestatic a : (Ljava/lang/Throwable;)Ljava/lang/Throwable;
    //   2077: athrow
    //   2078: aload_1
    //   2079: checkcast [B
    //   2082: invokevirtual clone : ()Ljava/lang/Object;
    //   2085: aastore
    //   2086: invokevirtual invoke : (Ljava/lang/Object;[Ljava/lang/Object;)Ljava/lang/Object;
    //   2089: pop
    //   2090: iload_2
    //   2091: ifne -> 2108
    //   2094: iinc #6, 1
    //   2097: iload_2
    //   2098: ifne -> 1971
    //   2101: goto -> 2108
    //   2104: invokestatic a : (Ljava/lang/Throwable;)Ljava/lang/Throwable;
    //   2107: athrow
    //   2108: getstatic burp/Ztd6.Zu : Ljava/lang/String;
    //   2111: getstatic burp/Zg_y.ZR : Ljava/lang/Object;
    //   2114: checkcast java/math/BigInteger
    //   2117: invokevirtual intValue : ()I
    //   2120: bipush #32
    //   2122: irem
    //   2123: invokestatic abs : (I)I
    //   2126: invokevirtual charAt : (I)C
    //   2129: getstatic burp/Zmnb.ZD : Ljava/lang/String;
    //   2132: getstatic burp/Zbzk.ZI : Ljava/lang/Object;
    //   2135: checkcast java/math/BigInteger
    //   2138: invokevirtual intValue : ()I
    //   2141: bipush #32
    //   2143: irem
    //   2144: invokestatic abs : (I)I
    //   2147: invokevirtual charAt : (I)C
    //   2150: if_icmple -> 2257
    //   2153: getstatic burp/Zgvl.Zc : Ljava/lang/String;
    //   2156: getstatic burp/Zsdn.ZE : Ljava/lang/Object;
    //   2159: checkcast java/math/BigInteger
    //   2162: invokevirtual intValue : ()I
    //   2165: bipush #32
    //   2167: irem
    //   2168: invokestatic abs : (I)I
    //   2171: invokevirtual charAt : (I)C
    //   2174: getstatic burp/Zmcb.Zl : Ljava/lang/String;
    //   2177: getstatic burp/Zg8.ZX : Ljava/lang/Object;
    //   2180: checkcast java/math/BigInteger
    //   2183: invokevirtual intValue : ()I
    //   2186: bipush #32
    //   2188: irem
    //   2189: invokestatic abs : (I)I
    //   2192: invokevirtual charAt : (I)C
    //   2195: if_icmpgt -> 2257
    //   2198: goto -> 2205
    //   2201: invokestatic a : (Ljava/lang/Throwable;)Ljava/lang/Throwable;
    //   2204: athrow
    //   2205: getstatic burp/Zeoi.Zh : Ljava/lang/String;
    //   2208: getstatic burp/Zlg1.ZH : Ljava/lang/Object;
    //   2211: checkcast java/math/BigInteger
    //   2214: invokevirtual intValue : ()I
    //   2217: bipush #32
    //   2219: irem
    //   2220: invokestatic abs : (I)I
    //   2223: invokevirtual charAt : (I)C
    //   2226: getstatic burp/Zlps.ZO : Ljava/lang/String;
    //   2229: getstatic burp/Zkq9.Ze : Ljava/lang/Object;
    //   2232: checkcast java/math/BigInteger
    //   2235: invokevirtual intValue : ()I
    //   2238: bipush #32
    //   2240: irem
    //   2241: invokestatic abs : (I)I
    //   2244: invokevirtual charAt : (I)C
    //   2247: if_icmpgt -> 2265
    //   2250: goto -> 2257
    //   2253: invokestatic a : (Ljava/lang/Throwable;)Ljava/lang/Throwable;
    //   2256: athrow
    //   2257: iconst_1
    //   2258: goto -> 2266
    //   2261: invokestatic a : (Ljava/lang/Throwable;)Ljava/lang/Throwable;
    //   2264: athrow
    //   2265: iconst_0
    //   2266: ireturn
    //   2267: astore_3
    //   2268: new java/lang/Exception
    //   2271: dup
    //   2272: aload_3
    //   2273: invokevirtual getMessage : ()Ljava/lang/String;
    //   2276: invokespecial <init> : (Ljava/lang/String;)V
    //   2279: athrow
    // Exception table:
    //   from	to	target	type
    //   4	2266	2267	java/lang/Throwable
    //   37	210	213	java/lang/Throwable
    //   180	247	250	java/lang/Throwable
    //   217	284	287	java/lang/Throwable
    //   254	321	324	java/lang/Throwable
    //   291	358	361	java/lang/Throwable
    //   328	395	398	java/lang/Throwable
    //   365	432	435	java/lang/Throwable
    //   402	469	472	java/lang/Throwable
    //   439	506	509	java/lang/Throwable
    //   476	543	546	java/lang/Throwable
    //   513	580	583	java/lang/Throwable
    //   550	617	620	java/lang/Throwable
    //   587	654	657	java/lang/Throwable
    //   624	691	694	java/lang/Throwable
    //   661	728	731	java/lang/Throwable
    //   698	765	768	java/lang/Throwable
    //   735	802	805	java/lang/Throwable
    //   772	839	842	java/lang/Throwable
    //   809	876	879	java/lang/Throwable
    //   846	913	916	java/lang/Throwable
    //   883	950	953	java/lang/Throwable
    //   920	987	990	java/lang/Throwable
    //   957	1024	1027	java/lang/Throwable
    //   994	1061	1064	java/lang/Throwable
    //   1031	1098	1101	java/lang/Throwable
    //   1068	1135	1138	java/lang/Throwable
    //   1105	1172	1175	java/lang/Throwable
    //   1142	1209	1212	java/lang/Throwable
    //   1179	1246	1249	java/lang/Throwable
    //   1216	1283	1286	java/lang/Throwable
    //   1253	1320	1323	java/lang/Throwable
    //   1290	1353	1356	java/lang/Throwable
    //   1455	1469	1469	java/lang/Throwable
    //   1480	1493	1496	java/lang/Throwable
    //   1485	1508	1511	java/lang/Throwable
    //   1500	1526	1529	java/lang/Throwable
    //   1515	1556	1559	java/lang/Throwable
    //   1622	1649	1652	java/lang/Throwable
    //   1639	1670	1673	java/lang/Throwable
    //   1656	1700	1703	java/lang/Throwable
    //   1677	1711	1711	java/lang/Throwable
    //   1722	1738	1741	java/lang/Throwable
    //   1818	1832	1832	java/lang/Throwable
    //   1843	1856	1859	java/lang/Throwable
    //   1848	1871	1874	java/lang/Throwable
    //   1863	1889	1892	java/lang/Throwable
    //   1878	1919	1922	java/lang/Throwable
    //   1985	2012	2015	java/lang/Throwable
    //   2002	2033	2036	java/lang/Throwable
    //   2019	2063	2066	java/lang/Throwable
    //   2040	2074	2074	java/lang/Throwable
    //   2085	2101	2104	java/lang/Throwable
    //   2108	2198	2201	java/lang/Throwable
    //   2153	2250	2253	java/lang/Throwable
    //   2205	2261	2261	java/lang/Throwable
  }
  
  static void ZF(Object[] paramArrayOfObject, Object paramObject) throws Throwable {}
  
  static void Zl(Object paramObject) {
    Zgkp.ZS = a(-11950, 4307);
    Zgkp.Zp = new BigInteger(a(-11942, -29917));
    boolean bool = Zt2e.ZN();
    try {
      try {
        if (Zr_y.Zb.charAt(Math.abs(((BigInteger)Zlhz.Zy).intValue() % 32)) <= Zepm.Zl.charAt(Math.abs(((BigInteger)Zs9k.ZX).intValue() % 32))) {
          try {
            Zr3j.Zc(Class.forName(a(-11949, -14423)));
            if (!bool)
              Zezq.Zu(Class.forName(a(-11948, 28431))); 
          } catch (Throwable throwable) {
            throw a(null);
          } 
          return;
        } 
      } catch (Throwable throwable) {
        throw a(null);
      } 
      Zezq.Zu(Class.forName(a(-11948, 28431)));
    } catch (Throwable throwable) {}
  }
  
  static {
    // Byte code:
    //   0: bipush #12
    //   2: anewarray java/lang/String
    //   5: astore #5
    //   7: iconst_0
    //   8: istore_3
    //   9: ldc '#Â¯V ' UgÃ¹ÃŽÃƒÂ‘ Ã—Â½s=Â•Â©Ãœ $Ã€Â³Ã .0\\bZI:pe\\tFÃºÂ±Â¶GÃ¾ÃÂÃfÂÂµÃ»\\b 4yo^Ã…Ã²Ã³\\tGÂŽÂ‘8C/PÂ¶Ã²\\tZ2i7Ã†Â¤+\\tÃ¢R%Â£Ã•\ÂƒÃˆÃ¬MwÃ¢Â§Ã»ÂºÃ²ÂÃ•EÃ•OÃÂVÂ¸Ã‰tQChÂˆÃ‰TXÂ ?ÂªCl\\rtiÂ£"pÂ¦@\\rÃªÂª:Â·Ã¬Â—.Ã™ÃŒÂ›>Ã²IÂ€\\tÃ¸Ã†Ã¿CO$Â¬ÂŒÃ“Â‘1KjÃ…FÂªm\\buÃ•Ã—S'
    //   11: dup
    //   12: astore_2
    //   13: invokevirtual length : ()I
    //   16: istore #4
    //   18: bipush #32
    //   20: istore_1
    //   21: iconst_m1
    //   22: istore_0
    //   23: bipush #71
    //   25: iinc #0, 1
    //   28: aload_2
    //   29: iload_0
    //   30: dup
    //   31: iload_1
    //   32: iadd
    //   33: invokevirtual substring : (II)Ljava/lang/String;
    //   36: iconst_m1
    //   37: goto -> 143
    //   40: aload #5
    //   42: swap
    //   43: iload_3
    //   44: iinc #3, 1
    //   47: swap
    //   48: aastore
    //   49: iload_0
    //   50: iload_1
    //   51: iadd
    //   52: dup
    //   53: istore_0
    //   54: iload #4
    //   56: if_icmpge -> 68
    //   59: aload_2
    //   60: iload_0
    //   61: invokevirtual charAt : (I)C
    //   64: istore_1
    //   65: goto -> 23
    //   68: ldc '?ÂºÂŠÂª4iÂ¾rÂ€ Â¥ÂšÂ£Ã»-Âƒ&Â´~Â‘n8\Ã…Â“<Â¡Ã¢v9Ã“XGW*Ã¡7pÂ’Â–'
    //   70: dup
    //   71: astore_2
    //   72: invokevirtual length : ()I
    //   75: istore #4
    //   77: bipush #9
    //   79: istore_1
    //   80: iconst_m1
    //   81: istore_0
    //   82: bipush #60
    //   84: iinc #0, 1
    //   87: aload_2
    //   88: iload_0
    //   89: dup
    //   90: iload_1
    //   91: iadd
    //   92: invokevirtual substring : (II)Ljava/lang/String;
    //   95: iconst_0
    //   96: goto -> 143
    //   99: aload #5
    //   101: swap
    //   102: iload_3
    //   103: iinc #3, 1
    //   106: swap
    //   107: aastore
    //   108: iload_0
    //   109: iload_1
    //   110: iadd
    //   111: dup
    //   112: istore_0
    //   113: iload #4
    //   115: if_icmpge -> 127
    //   118: aload_2
    //   119: iload_0
    //   120: invokevirtual charAt : (I)C
    //   123: istore_1
    //   124: goto -> 82
    //   127: aload #5
    //   129: putstatic burp/Zct.a : [Ljava/lang/String;
    //   132: bipush #12
    //   134: anewarray java/lang/String
    //   137: putstatic burp/Zct.b : [Ljava/lang/String;
    //   140: goto -> 300
    //   143: dup_x2
    //   144: pop
    //   145: invokevirtual toCharArray : ()[C
    //   148: dup_x1
    //   149: arraylength
    //   150: dup_x2
    //   151: pop
    //   152: iconst_0
    //   153: istore #6
    //   155: dup2_x1
    //   156: pop2
    //   157: dup_x2
    //   158: iconst_1
    //   159: if_icmpgt -> 260
    //   162: dup2
    //   163: swap
    //   164: iload #6
    //   166: dup2_x1
    //   167: caload
    //   168: swap
    //   169: iload #6
    //   171: bipush #7
    //   173: irem
    //   174: tableswitch default -> 242, 0 -> 212, 1 -> 217, 2 -> 222, 3 -> 227, 4 -> 232, 5 -> 237
    //   212: bipush #111
    //   214: goto -> 244
    //   217: bipush #70
    //   219: goto -> 244
    //   222: bipush #103
    //   224: goto -> 244
    //   227: bipush #37
    //   229: goto -> 244
    //   232: bipush #32
    //   234: goto -> 244
    //   237: bipush #7
    //   239: goto -> 244
    //   242: bipush #20
    //   244: ixor
    //   245: ixor
    //   246: i2c
    //   247: castore
    //   248: iinc #6, 1
    //   251: dup
    //   252: ifne -> 260
    //   255: dup2
    //   256: dup_x1
    //   257: goto -> 166
    //   260: dup2_x1
    //   261: pop2
    //   262: dup_x2
    //   263: iload #6
    //   265: if_icmpgt -> 162
    //   268: pop
    //   269: new java/lang/String
    //   272: dup_x1
    //   273: swap
    //   274: invokespecial <init> : ([C)V
    //   277: invokevirtual intern : ()Ljava/lang/String;
    //   280: swap
    //   281: pop
    //   282: swap
    //   283: tableswitch default -> 40, 0 -> 99
    //   300: new java/math/BigInteger
    //   303: dup
    //   304: bipush #32
    //   306: newarray byte
    //   308: dup
    //   309: iconst_0
    //   310: bipush #29
    //   312: bastore
    //   313: dup
    //   314: iconst_1
    //   315: bipush #-2
    //   317: bastore
    //   318: dup
    //   319: iconst_2
    //   320: bipush #126
    //   322: bastore
    //   323: dup
    //   324: iconst_3
    //   325: bipush #-66
    //   327: bastore
    //   328: dup
    //   329: iconst_4
    //   330: bipush #91
    //   332: bastore
    //   333: dup
    //   334: iconst_5
    //   335: bipush #-24
    //   337: bastore
    //   338: dup
    //   339: bipush #6
    //   341: bipush #-57
    //   343: bastore
    //   344: dup
    //   345: bipush #7
    //   347: bipush #-32
    //   349: bastore
    //   350: dup
    //   351: bipush #8
    //   353: iconst_1
    //   354: bastore
    //   355: dup
    //   356: bipush #9
    //   358: bipush #-82
    //   360: bastore
    //   361: dup
    //   362: bipush #10
    //   364: bipush #95
    //   366: bastore
    //   367: dup
    //   368: bipush #11
    //   370: bipush #-6
    //   372: bastore
    //   373: dup
    //   374: bipush #12
    //   376: bipush #44
    //   378: bastore
    //   379: dup
    //   380: bipush #13
    //   382: bipush #30
    //   384: bastore
    //   385: dup
    //   386: bipush #14
    //   388: bipush #6
    //   390: bastore
    //   391: dup
    //   392: bipush #15
    //   394: bipush #76
    //   396: bastore
    //   397: dup
    //   398: bipush #16
    //   400: bipush #-46
    //   402: bastore
    //   403: dup
    //   404: bipush #17
    //   406: bipush #-64
    //   408: bastore
    //   409: dup
    //   410: bipush #18
    //   412: bipush #120
    //   414: bastore
    //   415: dup
    //   416: bipush #19
    //   418: bipush #-38
    //   420: bastore
    //   421: dup
    //   422: bipush #20
    //   424: bipush #-72
    //   426: bastore
    //   427: dup
    //   428: bipush #21
    //   430: bipush #113
    //   432: bastore
    //   433: dup
    //   434: bipush #22
    //   436: bipush #-43
    //   438: bastore
    //   439: dup
    //   440: bipush #23
    //   442: bipush #-114
    //   444: bastore
    //   445: dup
    //   446: bipush #24
    //   448: bipush #117
    //   450: bastore
    //   451: dup
    //   452: bipush #25
    //   454: bipush #-109
    //   456: bastore
    //   457: dup
    //   458: bipush #26
    //   460: bipush #-60
    //   462: bastore
    //   463: dup
    //   464: bipush #27
    //   466: bipush #52
    //   468: bastore
    //   469: dup
    //   470: bipush #28
    //   472: bipush #-76
    //   474: bastore
    //   475: dup
    //   476: bipush #29
    //   478: bipush #73
    //   480: bastore
    //   481: dup
    //   482: bipush #30
    //   484: bipush #75
    //   486: bastore
    //   487: dup
    //   488: bipush #31
    //   490: bipush #35
    //   492: bastore
    //   493: invokespecial <init> : ([B)V
    //   496: putstatic burp/Zct.ZW : Ljava/lang/Object;
    //   499: sipush #-11943
    //   502: sipush #-14069
    //   505: invokestatic a : (II)Ljava/lang/String;
    //   508: putstatic burp/Zct.Zy : Ljava/lang/String;
    //   511: return
  }
  
  private static Throwable a(Throwable paramThrowable) {
    return paramThrowable;
  }
  
  private static String a(int paramInt1, int paramInt2) {
    int i = (paramInt1 ^ 0xFFFFD152) & 0xFFFF;
    if (b[i] == null) {
      char[] arrayOfChar = a[i].toCharArray();
      switch (arrayOfChar[0] & 0xFF) {
        case 0:
        
        case 1:
        
        case 2:
        
        case 3:
        
        case 4:
        
        case 5:
        
        case 6:
        
        case 7:
        
        case 8:
        
        case 9:
        
        case 10:
        
        case 11:
        
        case 12:
        
        case 13:
        
        case 14:
        
        case 15:
        
        case 16:
        
        case 17:
        
        case 18:
        
        case 19:
        
        case 20:
        
        case 21:
        
        case 22:
        
        case 23:
        
        case 24:
        
        case 25:
        
        case 26:
        
        case 27:
        
        case 28:
        
        case 29:
        
        case 30:
        
        case 31:
        
        case 32:
        
        case 33:
        
        case 34:
        
        case 35:
        
        case 36:
        
        case 37:
        
        case 38:
        
        case 39:
        
        case 40:
        
        case 41:
        
        case 42:
        
        case 43:
        
        case 44:
        
        case 45:
        
        case 46:
        
        case 47:
        
        case 48:
        
        case 49:
        
        case 50:
        
        case 51:
        
        case 52:
        
        case 53:
        
        case 54:
        
        case 55:
        
        case 56:
        
        case 57:
        
        case 58:
        
        case 59:
        
        case 60:
        
        case 61:
        
        case 62:
        
        case 63:
        
        case 64:
        
        case 65:
        
        case 66:
        
        case 67:
        
        case 68:
        
        case 69:
        
        case 70:
        
        case 71:
        
        case 72:
        
        case 73:
        
        case 74:
        
        case 75:
        
        case 76:
        
        case 77:
        
        case 78:
        
        case 79:
        
        case 80:
        
        case 81:
        
        case 82:
        
        case 83:
        
        case 84:
        
        case 85:
        
        case 86:
        
        case 87:
        
        case 88:
        
        case 89:
        
        case 90:
        
        case 91:
        
        case 92:
        
        case 93:
        
        case 94:
        
        case 95:
        
        case 96:
        
        case 97:
        
        case 98:
        
        case 99:
        
        case 100:
        
        case 101:
        
        case 102:
        
        case 103:
        
        case 104:
        
        case 105:
        
        case 106:
        
        case 107:
        
        case 108:
        
        case 109:
        
        case 110:
        
        case 111:
        
        case 112:
        
        case 113:
        
        case 114:
        
        case 115:
        
        case 116:
        
        case 117:
        
        case 118:
        
        case 119:
        
        case 120:
        
        case 121:
        
        case 122:
        
        case 123:
        
        case 124:
        
        case 125:
        
        case 126:
        
        case 127:
        
        case 128:
        
        case 129:
        
        case 130:
        
        case 131:
        
        case 132:
        
        case 133:
        
        case 134:
        
        case 135:
        
        case 136:
        
        case 137:
        
        case 138:
        
        case 139:
        
        case 140:
        
        case 141:
        
        case 142:
        
        case 143:
        
        case 144:
        
        case 145:
        
        case 146:
        
        case 147:
        
        case 148:
        
        case 149:
        
        case 150:
        
        case 151:
        
        case 152:
        
        case 153:
        
        case 154:
        
        case 155:
        
        case 156:
        
        case 157:
        
        case 158:
        
        case 159:
        
        case 160:
        
        case 161:
        
        case 162:
        
        case 163:
        
        case 164:
        
        case 165:
        
        case 166:
        
        case 167:
        
        case 168:
        
        case 169:
        
        case 170:
        
        case 171:
        
        case 172:
        
        case 173:
        
        case 174:
        
        case 175:
        
        case 176:
        
        case 177:
        
        case 178:
        
        case 179:
        
        case 180:
        
        case 181:
        
        case 182:
        
        case 183:
        
        case 184:
        
        case 185:
        
        case 186:
        
        case 187:
        
        case 188:
        
        case 189:
        
        case 190:
        
        case 191:
        
        case 192:
        
        case 193:
        
        case 194:
        
        case 195:
        
        case 196:
        
        case 197:
        
        case 198:
        
        case 199:
        
        case 200:
        
        case 201:
        
        case 202:
        
        case 203:
        
        case 204:
        
        case 205:
        
        case 206:
        
        case 207:
        
        case 208:
        
        case 209:
        
        case 210:
        
        case 211:
        
        case 212:
        
        case 213:
        
        case 214:
        
        case 215:
        
        case 216:
        
        case 217:
        
        case 218:
        
        case 219:
        
        case 220:
        
        case 221:
        
        case 222:
        
        case 223:
        
        case 224:
        
        case 225:
        
        case 226:
        
        case 227:
        
        case 228:
        
        case 229:
        
        case 230:
        
        case 231:
        
        case 232:
        
        case 233:
        
        case 234:
        
        case 235:
        
        case 236:
        
        case 237:
        
        case 238:
        
        case 239:
        
        case 240:
        
        case 241:
        
        case 242:
        
        case 243:
        
        case 244:
        
        case 245:
        
        case 246:
        
        case 247:
        
        case 248:
        
        case 249:
        
        case 250:
        
        case 251:
        
        case 252:
        
        case 253:
        
        case 254:
        
        default:
          break;
      } 
      char c = 'Â”';
      int j = (paramInt2 & 0xFF) - c;
      if (j < 0)
        j += 256; 
      int k = ((paramInt2 & 0xFFFF) >>> 8) - c;
      if (k < 0)
        k += 256; 
      for (byte b = 0; b < arrayOfChar.length; b++) {
        int m = b % 2;
        if (m == 0) {
          arrayOfChar[b] = (char)(arrayOfChar[b] ^ j);
          j = ((j >>> 3 | j << 5) ^ arrayOfChar[b]) & 0xFF;
        } else {
          arrayOfChar[b] = (char)(arrayOfChar[b] ^ k);
          k = ((k >>> 3 | k << 5) ^ arrayOfChar[b]) & 0xFF;
        } 
      } 
      b[i] = (new String(arrayOfChar)).intern();
    } 
    return b[i];
  }
}


/* Location:              C:\Program Files\BurpSuitePro\burpsuite_pro.jar!\burp\Zct.class
 * Java compiler version: 21 (65.0)
 * JD-Core Version:       1.1.3
 */