package burp;

import java.math.BigInteger;

class Zdk extends ClassLoader {
  static String Ze;
  
  static Object Zy;
  
  private static final String[] a;
  
  private static final String[] b;
  
  static boolean Zz(Object[] paramArrayOfObject, Object paramObject) throws Throwable {
    // Byte code:
    //   0: invokestatic ZK : ()Z
    //   3: istore_2
    //   4: getstatic burp/Zb_u.Zp : Ljava/lang/Object;
    //   7: checkcast java/math/BigInteger
    //   10: getstatic burp/Zr9b.ZF : Ljava/lang/Object;
    //   13: checkcast java/math/BigInteger
    //   16: invokevirtual subtract : (Ljava/math/BigInteger;)Ljava/math/BigInteger;
    //   19: putstatic burp/Zgii.ZD : Ljava/lang/Object;
    //   22: new java/lang/StringBuilder
    //   25: dup
    //   26: invokespecial <init> : ()V
    //   29: astore_3
    //   30: iconst_0
    //   31: istore #4
    //   33: iload #4
    //   35: bipush #32
    //   37: if_icmpge -> 1371
    //   40: iload #4
    //   42: tableswitch default -> 1364, 0 -> 184, 1 -> 221, 2 -> 258, 3 -> 295, 4 -> 332, 5 -> 369, 6 -> 406, 7 -> 443, 8 -> 480, 9 -> 517, 10 -> 554, 11 -> 591, 12 -> 628, 13 -> 665, 14 -> 702, 15 -> 739, 16 -> 776, 17 -> 813, 18 -> 850, 19 -> 887, 20 -> 924, 21 -> 961, 22 -> 998, 23 -> 1035, 24 -> 1072, 25 -> 1109, 26 -> 1146, 27 -> 1183, 28 -> 1220, 29 -> 1257, 30 -> 1294, 31 -> 1331
    //   184: aload_3
    //   185: getstatic burp/Zlpn.ZF : Ljava/lang/String;
    //   188: getstatic burp/Zr8s.Zt : Ljava/lang/Object;
    //   191: checkcast java/math/BigInteger
    //   194: invokevirtual intValue : ()I
    //   197: bipush #32
    //   199: irem
    //   200: invokestatic abs : (I)I
    //   203: invokevirtual charAt : (I)C
    //   206: invokevirtual append : (C)Ljava/lang/StringBuilder;
    //   209: pop
    //   210: iload_2
    //   211: ifeq -> 1364
    //   214: goto -> 221
    //   217: invokestatic a : (Ljava/lang/Throwable;)Ljava/lang/Throwable;
    //   220: athrow
    //   221: aload_3
    //   222: getstatic burp/Zr3j.Zj : Ljava/lang/String;
    //   225: getstatic burp/Zz3k.Zz : Ljava/lang/Object;
    //   228: checkcast java/math/BigInteger
    //   231: invokevirtual intValue : ()I
    //   234: bipush #32
    //   236: irem
    //   237: invokestatic abs : (I)I
    //   240: invokevirtual charAt : (I)C
    //   243: invokevirtual append : (C)Ljava/lang/StringBuilder;
    //   246: pop
    //   247: iload_2
    //   248: ifeq -> 1364
    //   251: goto -> 258
    //   254: invokestatic a : (Ljava/lang/Throwable;)Ljava/lang/Throwable;
    //   257: athrow
    //   258: aload_3
    //   259: getstatic burp/Ztgv.ZC : Ljava/lang/String;
    //   262: getstatic burp/Zl3j.ZY : Ljava/lang/Object;
    //   265: checkcast java/math/BigInteger
    //   268: invokevirtual intValue : ()I
    //   271: bipush #32
    //   273: irem
    //   274: invokestatic abs : (I)I
    //   277: invokevirtual charAt : (I)C
    //   280: invokevirtual append : (C)Ljava/lang/StringBuilder;
    //   283: pop
    //   284: iload_2
    //   285: ifeq -> 1364
    //   288: goto -> 295
    //   291: invokestatic a : (Ljava/lang/Throwable;)Ljava/lang/Throwable;
    //   294: athrow
    //   295: aload_3
    //   296: getstatic burp/Zz4r.Zq : Ljava/lang/String;
    //   299: getstatic burp/Zera.Zy : Ljava/lang/Object;
    //   302: checkcast java/math/BigInteger
    //   305: invokevirtual intValue : ()I
    //   308: bipush #32
    //   310: irem
    //   311: invokestatic abs : (I)I
    //   314: invokevirtual charAt : (I)C
    //   317: invokevirtual append : (C)Ljava/lang/StringBuilder;
    //   320: pop
    //   321: iload_2
    //   322: ifeq -> 1364
    //   325: goto -> 332
    //   328: invokestatic a : (Ljava/lang/Throwable;)Ljava/lang/Throwable;
    //   331: athrow
    //   332: aload_3
    //   333: getstatic burp/Zl7k.ZX : Ljava/lang/String;
    //   336: getstatic burp/Zlc5.ZH : Ljava/lang/Object;
    //   339: checkcast java/math/BigInteger
    //   342: invokevirtual intValue : ()I
    //   345: bipush #32
    //   347: irem
    //   348: invokestatic abs : (I)I
    //   351: invokevirtual charAt : (I)C
    //   354: invokevirtual append : (C)Ljava/lang/StringBuilder;
    //   357: pop
    //   358: iload_2
    //   359: ifeq -> 1364
    //   362: goto -> 369
    //   365: invokestatic a : (Ljava/lang/Throwable;)Ljava/lang/Throwable;
    //   368: athrow
    //   369: aload_3
    //   370: getstatic burp/Ze82.Zx : Ljava/lang/String;
    //   373: getstatic burp/Ztv8.ZS : Ljava/lang/Object;
    //   376: checkcast java/math/BigInteger
    //   379: invokevirtual intValue : ()I
    //   382: bipush #32
    //   384: irem
    //   385: invokestatic abs : (I)I
    //   388: invokevirtual charAt : (I)C
    //   391: invokevirtual append : (C)Ljava/lang/StringBuilder;
    //   394: pop
    //   395: iload_2
    //   396: ifeq -> 1364
    //   399: goto -> 406
    //   402: invokestatic a : (Ljava/lang/Throwable;)Ljava/lang/Throwable;
    //   405: athrow
    //   406: aload_3
    //   407: getstatic burp/Zkde.Zb : Ljava/lang/String;
    //   410: getstatic burp/Zr5k.Zj : Ljava/lang/Object;
    //   413: checkcast java/math/BigInteger
    //   416: invokevirtual intValue : ()I
    //   419: bipush #32
    //   421: irem
    //   422: invokestatic abs : (I)I
    //   425: invokevirtual charAt : (I)C
    //   428: invokevirtual append : (C)Ljava/lang/StringBuilder;
    //   431: pop
    //   432: iload_2
    //   433: ifeq -> 1364
    //   436: goto -> 443
    //   439: invokestatic a : (Ljava/lang/Throwable;)Ljava/lang/Throwable;
    //   442: athrow
    //   443: aload_3
    //   444: getstatic burp/Zlot.ZD : Ljava/lang/String;
    //   447: getstatic burp/Zzwl.Z_ : Ljava/lang/Object;
    //   450: checkcast java/math/BigInteger
    //   453: invokevirtual intValue : ()I
    //   456: bipush #32
    //   458: irem
    //   459: invokestatic abs : (I)I
    //   462: invokevirtual charAt : (I)C
    //   465: invokevirtual append : (C)Ljava/lang/StringBuilder;
    //   468: pop
    //   469: iload_2
    //   470: ifeq -> 1364
    //   473: goto -> 480
    //   476: invokestatic a : (Ljava/lang/Throwable;)Ljava/lang/Throwable;
    //   479: athrow
    //   480: aload_3
    //   481: getstatic burp/Zgnp.ZL : Ljava/lang/String;
    //   484: getstatic burp/Zxrd.ZL : Ljava/lang/Object;
    //   487: checkcast java/math/BigInteger
    //   490: invokevirtual intValue : ()I
    //   493: bipush #32
    //   495: irem
    //   496: invokestatic abs : (I)I
    //   499: invokevirtual charAt : (I)C
    //   502: invokevirtual append : (C)Ljava/lang/StringBuilder;
    //   505: pop
    //   506: iload_2
    //   507: ifeq -> 1364
    //   510: goto -> 517
    //   513: invokestatic a : (Ljava/lang/Throwable;)Ljava/lang/Throwable;
    //   516: athrow
    //   517: aload_3
    //   518: getstatic burp/Zz75.ZT : Ljava/lang/String;
    //   521: getstatic burp/Zblj.Zl : Ljava/lang/Object;
    //   524: checkcast java/math/BigInteger
    //   527: invokevirtual intValue : ()I
    //   530: bipush #32
    //   532: irem
    //   533: invokestatic abs : (I)I
    //   536: invokevirtual charAt : (I)C
    //   539: invokevirtual append : (C)Ljava/lang/StringBuilder;
    //   542: pop
    //   543: iload_2
    //   544: ifeq -> 1364
    //   547: goto -> 554
    //   550: invokestatic a : (Ljava/lang/Throwable;)Ljava/lang/Throwable;
    //   553: athrow
    //   554: aload_3
    //   555: getstatic burp/Zzyr.Z_ : Ljava/lang/String;
    //   558: getstatic burp/Zl_1.ZL : Ljava/lang/Object;
    //   561: checkcast java/math/BigInteger
    //   564: invokevirtual intValue : ()I
    //   567: bipush #32
    //   569: irem
    //   570: invokestatic abs : (I)I
    //   573: invokevirtual charAt : (I)C
    //   576: invokevirtual append : (C)Ljava/lang/StringBuilder;
    //   579: pop
    //   580: iload_2
    //   581: ifeq -> 1364
    //   584: goto -> 591
    //   587: invokestatic a : (Ljava/lang/Throwable;)Ljava/lang/Throwable;
    //   590: athrow
    //   591: aload_3
    //   592: getstatic burp/Zz67.Zc : Ljava/lang/String;
    //   595: getstatic burp/Zlsw.ZJ : Ljava/lang/Object;
    //   598: checkcast java/math/BigInteger
    //   601: invokevirtual intValue : ()I
    //   604: bipush #32
    //   606: irem
    //   607: invokestatic abs : (I)I
    //   610: invokevirtual charAt : (I)C
    //   613: invokevirtual append : (C)Ljava/lang/StringBuilder;
    //   616: pop
    //   617: iload_2
    //   618: ifeq -> 1364
    //   621: goto -> 628
    //   624: invokestatic a : (Ljava/lang/Throwable;)Ljava/lang/Throwable;
    //   627: athrow
    //   628: aload_3
    //   629: getstatic burp/Zbqk.ZZ : Ljava/lang/String;
    //   632: getstatic burp/Zs5k.Zg : Ljava/lang/Object;
    //   635: checkcast java/math/BigInteger
    //   638: invokevirtual intValue : ()I
    //   641: bipush #32
    //   643: irem
    //   644: invokestatic abs : (I)I
    //   647: invokevirtual charAt : (I)C
    //   650: invokevirtual append : (C)Ljava/lang/StringBuilder;
    //   653: pop
    //   654: iload_2
    //   655: ifeq -> 1364
    //   658: goto -> 665
    //   661: invokestatic a : (Ljava/lang/Throwable;)Ljava/lang/Throwable;
    //   664: athrow
    //   665: aload_3
    //   666: getstatic burp/Zg2.ZN : Ljava/lang/String;
    //   669: getstatic burp/Zeu2.ZW : Ljava/lang/Object;
    //   672: checkcast java/math/BigInteger
    //   675: invokevirtual intValue : ()I
    //   678: bipush #32
    //   680: irem
    //   681: invokestatic abs : (I)I
    //   684: invokevirtual charAt : (I)C
    //   687: invokevirtual append : (C)Ljava/lang/StringBuilder;
    //   690: pop
    //   691: iload_2
    //   692: ifeq -> 1364
    //   695: goto -> 702
    //   698: invokestatic a : (Ljava/lang/Throwable;)Ljava/lang/Throwable;
    //   701: athrow
    //   702: aload_3
    //   703: getstatic burp/Zgrf.ZE : Ljava/lang/String;
    //   706: getstatic burp/Zlv6.ZN : Ljava/lang/Object;
    //   709: checkcast java/math/BigInteger
    //   712: invokevirtual intValue : ()I
    //   715: bipush #32
    //   717: irem
    //   718: invokestatic abs : (I)I
    //   721: invokevirtual charAt : (I)C
    //   724: invokevirtual append : (C)Ljava/lang/StringBuilder;
    //   727: pop
    //   728: iload_2
    //   729: ifeq -> 1364
    //   732: goto -> 739
    //   735: invokestatic a : (Ljava/lang/Throwable;)Ljava/lang/Throwable;
    //   738: athrow
    //   739: aload_3
    //   740: getstatic burp/Zelc.ZI : Ljava/lang/String;
    //   743: getstatic burp/Zls_.ZR : Ljava/lang/Object;
    //   746: checkcast java/math/BigInteger
    //   749: invokevirtual intValue : ()I
    //   752: bipush #32
    //   754: irem
    //   755: invokestatic abs : (I)I
    //   758: invokevirtual charAt : (I)C
    //   761: invokevirtual append : (C)Ljava/lang/StringBuilder;
    //   764: pop
    //   765: iload_2
    //   766: ifeq -> 1364
    //   769: goto -> 776
    //   772: invokestatic a : (Ljava/lang/Throwable;)Ljava/lang/Throwable;
    //   775: athrow
    //   776: aload_3
    //   777: getstatic burp/Zls0.ZI : Ljava/lang/String;
    //   780: getstatic burp/Ze7y.Zh : Ljava/lang/Object;
    //   783: checkcast java/math/BigInteger
    //   786: invokevirtual intValue : ()I
    //   789: bipush #32
    //   791: irem
    //   792: invokestatic abs : (I)I
    //   795: invokevirtual charAt : (I)C
    //   798: invokevirtual append : (C)Ljava/lang/StringBuilder;
    //   801: pop
    //   802: iload_2
    //   803: ifeq -> 1364
    //   806: goto -> 813
    //   809: invokestatic a : (Ljava/lang/Throwable;)Ljava/lang/Throwable;
    //   812: athrow
    //   813: aload_3
    //   814: getstatic burp/Zm4k.ZW : Ljava/lang/String;
    //   817: getstatic burp/Zg6f.Zl : Ljava/lang/Object;
    //   820: checkcast java/math/BigInteger
    //   823: invokevirtual intValue : ()I
    //   826: bipush #32
    //   828: irem
    //   829: invokestatic abs : (I)I
    //   832: invokevirtual charAt : (I)C
    //   835: invokevirtual append : (C)Ljava/lang/StringBuilder;
    //   838: pop
    //   839: iload_2
    //   840: ifeq -> 1364
    //   843: goto -> 850
    //   846: invokestatic a : (Ljava/lang/Throwable;)Ljava/lang/Throwable;
    //   849: athrow
    //   850: aload_3
    //   851: getstatic burp/Zs59.Zc : Ljava/lang/String;
    //   854: getstatic burp/Zl2t.ZS : Ljava/lang/Object;
    //   857: checkcast java/math/BigInteger
    //   860: invokevirtual intValue : ()I
    //   863: bipush #32
    //   865: irem
    //   866: invokestatic abs : (I)I
    //   869: invokevirtual charAt : (I)C
    //   872: invokevirtual append : (C)Ljava/lang/StringBuilder;
    //   875: pop
    //   876: iload_2
    //   877: ifeq -> 1364
    //   880: goto -> 887
    //   883: invokestatic a : (Ljava/lang/Throwable;)Ljava/lang/Throwable;
    //   886: athrow
    //   887: aload_3
    //   888: getstatic burp/Zkup.Zr : Ljava/lang/String;
    //   891: getstatic burp/Zkco.Zg : Ljava/lang/Object;
    //   894: checkcast java/math/BigInteger
    //   897: invokevirtual intValue : ()I
    //   900: bipush #32
    //   902: irem
    //   903: invokestatic abs : (I)I
    //   906: invokevirtual charAt : (I)C
    //   909: invokevirtual append : (C)Ljava/lang/StringBuilder;
    //   912: pop
    //   913: iload_2
    //   914: ifeq -> 1364
    //   917: goto -> 924
    //   920: invokestatic a : (Ljava/lang/Throwable;)Ljava/lang/Throwable;
    //   923: athrow
    //   924: aload_3
    //   925: getstatic burp/Zxti.ZD : Ljava/lang/String;
    //   928: getstatic burp/Zzco.ZC : Ljava/lang/Object;
    //   931: checkcast java/math/BigInteger
    //   934: invokevirtual intValue : ()I
    //   937: bipush #32
    //   939: irem
    //   940: invokestatic abs : (I)I
    //   943: invokevirtual charAt : (I)C
    //   946: invokevirtual append : (C)Ljava/lang/StringBuilder;
    //   949: pop
    //   950: iload_2
    //   951: ifeq -> 1364
    //   954: goto -> 961
    //   957: invokestatic a : (Ljava/lang/Throwable;)Ljava/lang/Throwable;
    //   960: athrow
    //   961: aload_3
    //   962: getstatic burp/Zx4k.ZC : Ljava/lang/String;
    //   965: getstatic burp/Zzlg.Z_ : Ljava/lang/Object;
    //   968: checkcast java/math/BigInteger
    //   971: invokevirtual intValue : ()I
    //   974: bipush #32
    //   976: irem
    //   977: invokestatic abs : (I)I
    //   980: invokevirtual charAt : (I)C
    //   983: invokevirtual append : (C)Ljava/lang/StringBuilder;
    //   986: pop
    //   987: iload_2
    //   988: ifeq -> 1364
    //   991: goto -> 998
    //   994: invokestatic a : (Ljava/lang/Throwable;)Ljava/lang/Throwable;
    //   997: athrow
    //   998: aload_3
    //   999: getstatic burp/Zrd4.Zg : Ljava/lang/String;
    //   1002: getstatic burp/Zzmo.ZI : Ljava/lang/Object;
    //   1005: checkcast java/math/BigInteger
    //   1008: invokevirtual intValue : ()I
    //   1011: bipush #32
    //   1013: irem
    //   1014: invokestatic abs : (I)I
    //   1017: invokevirtual charAt : (I)C
    //   1020: invokevirtual append : (C)Ljava/lang/StringBuilder;
    //   1023: pop
    //   1024: iload_2
    //   1025: ifeq -> 1364
    //   1028: goto -> 1035
    //   1031: invokestatic a : (Ljava/lang/Throwable;)Ljava/lang/Throwable;
    //   1034: athrow
    //   1035: aload_3
    //   1036: getstatic burp/Zlnq.ZQ : Ljava/lang/String;
    //   1039: getstatic burp/Zl_k.ZH : Ljava/lang/Object;
    //   1042: checkcast java/math/BigInteger
    //   1045: invokevirtual intValue : ()I
    //   1048: bipush #32
    //   1050: irem
    //   1051: invokestatic abs : (I)I
    //   1054: invokevirtual charAt : (I)C
    //   1057: invokevirtual append : (C)Ljava/lang/StringBuilder;
    //   1060: pop
    //   1061: iload_2
    //   1062: ifeq -> 1364
    //   1065: goto -> 1072
    //   1068: invokestatic a : (Ljava/lang/Throwable;)Ljava/lang/Throwable;
    //   1071: athrow
    //   1072: aload_3
    //   1073: getstatic burp/Zzvr.Zc : Ljava/lang/String;
    //   1076: getstatic burp/Zkf9.ZX : Ljava/lang/Object;
    //   1079: checkcast java/math/BigInteger
    //   1082: invokevirtual intValue : ()I
    //   1085: bipush #32
    //   1087: irem
    //   1088: invokestatic abs : (I)I
    //   1091: invokevirtual charAt : (I)C
    //   1094: invokevirtual append : (C)Ljava/lang/StringBuilder;
    //   1097: pop
    //   1098: iload_2
    //   1099: ifeq -> 1364
    //   1102: goto -> 1109
    //   1105: invokestatic a : (Ljava/lang/Throwable;)Ljava/lang/Throwable;
    //   1108: athrow
    //   1109: aload_3
    //   1110: getstatic burp/Zk52.ZL : Ljava/lang/String;
    //   1113: getstatic burp/Zl39.ZA : Ljava/lang/Object;
    //   1116: checkcast java/math/BigInteger
    //   1119: invokevirtual intValue : ()I
    //   1122: bipush #32
    //   1124: irem
    //   1125: invokestatic abs : (I)I
    //   1128: invokevirtual charAt : (I)C
    //   1131: invokevirtual append : (C)Ljava/lang/StringBuilder;
    //   1134: pop
    //   1135: iload_2
    //   1136: ifeq -> 1364
    //   1139: goto -> 1146
    //   1142: invokestatic a : (Ljava/lang/Throwable;)Ljava/lang/Throwable;
    //   1145: athrow
    //   1146: aload_3
    //   1147: getstatic burp/Zg5.ZF : Ljava/lang/String;
    //   1150: getstatic burp/Zt7x.ZE : Ljava/lang/Object;
    //   1153: checkcast java/math/BigInteger
    //   1156: invokevirtual intValue : ()I
    //   1159: bipush #32
    //   1161: irem
    //   1162: invokestatic abs : (I)I
    //   1165: invokevirtual charAt : (I)C
    //   1168: invokevirtual append : (C)Ljava/lang/StringBuilder;
    //   1171: pop
    //   1172: iload_2
    //   1173: ifeq -> 1364
    //   1176: goto -> 1183
    //   1179: invokestatic a : (Ljava/lang/Throwable;)Ljava/lang/Throwable;
    //   1182: athrow
    //   1183: aload_3
    //   1184: getstatic burp/Zzpu.Zq : Ljava/lang/String;
    //   1187: getstatic burp/Znp.ZJ : Ljava/lang/Object;
    //   1190: checkcast java/math/BigInteger
    //   1193: invokevirtual intValue : ()I
    //   1196: bipush #32
    //   1198: irem
    //   1199: invokestatic abs : (I)I
    //   1202: invokevirtual charAt : (I)C
    //   1205: invokevirtual append : (C)Ljava/lang/StringBuilder;
    //   1208: pop
    //   1209: iload_2
    //   1210: ifeq -> 1364
    //   1213: goto -> 1220
    //   1216: invokestatic a : (Ljava/lang/Throwable;)Ljava/lang/Throwable;
    //   1219: athrow
    //   1220: aload_3
    //   1221: getstatic burp/Ztzh.ZE : Ljava/lang/String;
    //   1224: getstatic burp/Zkor.Ze : Ljava/lang/Object;
    //   1227: checkcast java/math/BigInteger
    //   1230: invokevirtual intValue : ()I
    //   1233: bipush #32
    //   1235: irem
    //   1236: invokestatic abs : (I)I
    //   1239: invokevirtual charAt : (I)C
    //   1242: invokevirtual append : (C)Ljava/lang/StringBuilder;
    //   1245: pop
    //   1246: iload_2
    //   1247: ifeq -> 1364
    //   1250: goto -> 1257
    //   1253: invokestatic a : (Ljava/lang/Throwable;)Ljava/lang/Throwable;
    //   1256: athrow
    //   1257: aload_3
    //   1258: getstatic burp/Zenq.ZG : Ljava/lang/String;
    //   1261: getstatic burp/Zeqr.ZM : Ljava/lang/Object;
    //   1264: checkcast java/math/BigInteger
    //   1267: invokevirtual intValue : ()I
    //   1270: bipush #32
    //   1272: irem
    //   1273: invokestatic abs : (I)I
    //   1276: invokevirtual charAt : (I)C
    //   1279: invokevirtual append : (C)Ljava/lang/StringBuilder;
    //   1282: pop
    //   1283: iload_2
    //   1284: ifeq -> 1364
    //   1287: goto -> 1294
    //   1290: invokestatic a : (Ljava/lang/Throwable;)Ljava/lang/Throwable;
    //   1293: athrow
    //   1294: aload_3
    //   1295: getstatic burp/Zt7x.Zu : Ljava/lang/String;
    //   1298: getstatic burp/Ztbf.Zv : Ljava/lang/Object;
    //   1301: checkcast java/math/BigInteger
    //   1304: invokevirtual intValue : ()I
    //   1307: bipush #32
    //   1309: irem
    //   1310: invokestatic abs : (I)I
    //   1313: invokevirtual charAt : (I)C
    //   1316: invokevirtual append : (C)Ljava/lang/StringBuilder;
    //   1319: pop
    //   1320: iload_2
    //   1321: ifeq -> 1364
    //   1324: goto -> 1331
    //   1327: invokestatic a : (Ljava/lang/Throwable;)Ljava/lang/Throwable;
    //   1330: athrow
    //   1331: aload_3
    //   1332: getstatic burp/Zzi_.ZG : Ljava/lang/String;
    //   1335: getstatic burp/Zrfl.Z_ : Ljava/lang/Object;
    //   1338: checkcast java/math/BigInteger
    //   1341: invokevirtual intValue : ()I
    //   1344: bipush #32
    //   1346: irem
    //   1347: invokestatic abs : (I)I
    //   1350: invokevirtual charAt : (I)C
    //   1353: invokevirtual append : (C)Ljava/lang/StringBuilder;
    //   1356: pop
    //   1357: goto -> 1364
    //   1360: invokestatic a : (Ljava/lang/Throwable;)Ljava/lang/Throwable;
    //   1363: athrow
    //   1364: iinc #4, 1
    //   1367: iload_2
    //   1368: ifeq -> 33
    //   1371: aload_3
    //   1372: invokevirtual toString : ()Ljava/lang/String;
    //   1375: putstatic burp/Zmtf.Zx : Ljava/lang/String;
    //   1378: getstatic burp/Zmzh.Zk : Ljava/lang/Object;
    //   1381: checkcast java/math/BigInteger
    //   1384: invokevirtual toByteArray : ()[B
    //   1387: astore #4
    //   1389: bipush #32
    //   1391: newarray int
    //   1393: dup
    //   1394: iconst_0
    //   1395: ldc 943331329
    //   1397: iastore
    //   1398: dup
    //   1399: iconst_1
    //   1400: ldc 170788368
    //   1402: iastore
    //   1403: dup
    //   1404: iconst_2
    //   1405: ldc 1008414755
    //   1407: iastore
    //   1408: dup
    //   1409: iconst_3
    //   1410: ldc 187049985
    //   1412: iastore
    //   1413: dup
    //   1414: iconst_4
    //   1415: ldc 1010368540
    //   1417: iastore
    //   1418: dup
    //   1419: iconst_5
    //   1420: ldc 220604441
    //   1422: iastore
    //   1423: dup
    //   1424: bipush #6
    //   1426: ldc 940377620
    //   1428: iastore
    //   1429: dup
    //   1430: bipush #7
    //   1432: ldc 255209728
    //   1434: iastore
    //   1435: dup
    //   1436: bipush #8
    //   1438: ldc 689771012
    //   1440: iastore
    //   1441: dup
    //   1442: bipush #9
    //   1444: ldc 221709344
    //   1446: iastore
    //   1447: dup
    //   1448: bipush #10
    //   1450: ldc 957157408
    //   1452: iastore
    //   1453: dup
    //   1454: bipush #11
    //   1456: ldc 892536332
    //   1458: iastore
    //   1459: dup
    //   1460: bipush #12
    //   1462: ldc 722417666
    //   1464: iastore
    //   1465: dup
    //   1466: bipush #13
    //   1468: ldc 1026621720
    //   1470: iastore
    //   1471: dup
    //   1472: bipush #14
    //   1474: ldc 655302664
    //   1476: iastore
    //   1477: dup
    //   1478: bipush #15
    //   1480: ldc 890966315
    //   1482: iastore
    //   1483: dup
    //   1484: bipush #16
    //   1486: ldc 187632156
    //   1488: iastore
    //   1489: dup
    //   1490: bipush #17
    //   1492: ldc 874189824
    //   1494: iastore
    //   1495: dup
    //   1496: bipush #18
    //   1498: ldc 254150144
    //   1500: iastore
    //   1501: dup
    //   1502: bipush #19
    //   1504: ldc 924386310
    //   1506: iastore
    //   1507: dup
    //   1508: bipush #20
    //   1510: ldc 121057538
    //   1512: iastore
    //   1513: dup
    //   1514: bipush #21
    //   1516: ldc 840500228
    //   1518: iastore
    //   1519: dup
    //   1520: bipush #22
    //   1522: ldc 389160971
    //   1524: iastore
    //   1525: dup
    //   1526: bipush #23
    //   1528: ldc 907870729
    //   1530: iastore
    //   1531: dup
    //   1532: bipush #24
    //   1534: ldc 389426184
    //   1536: iastore
    //   1537: dup
    //   1538: bipush #25
    //   1540: ldc 973875457
    //   1542: iastore
    //   1543: dup
    //   1544: bipush #26
    //   1546: ldc 372376604
    //   1548: iastore
    //   1549: dup
    //   1550: bipush #27
    //   1552: ldc 707731490
    //   1554: iastore
    //   1555: dup
    //   1556: bipush #28
    //   1558: ldc 1043334948
    //   1560: iastore
    //   1561: dup
    //   1562: bipush #29
    //   1564: ldc 439222784
    //   1566: iastore
    //   1567: dup
    //   1568: bipush #30
    //   1570: ldc 876216579
    //   1572: iastore
    //   1573: dup
    //   1574: bipush #31
    //   1576: ldc 455999525
    //   1578: iastore
    //   1579: astore #6
    //   1581: bipush #8
    //   1583: aload #4
    //   1585: arraylength
    //   1586: bipush #8
    //   1588: irem
    //   1589: isub
    //   1590: istore #7
    //   1592: aload #4
    //   1594: arraylength
    //   1595: iload #7
    //   1597: iadd
    //   1598: newarray byte
    //   1600: astore #8
    //   1602: iconst_0
    //   1603: istore #9
    //   1605: iload #9
    //   1607: aload #4
    //   1609: arraylength
    //   1610: if_icmpge -> 1630
    //   1613: aload #8
    //   1615: iload #9
    //   1617: aload #4
    //   1619: iload #9
    //   1621: baload
    //   1622: bastore
    //   1623: iinc #9, 1
    //   1626: iload_2
    //   1627: ifeq -> 1605
    //   1630: aload #4
    //   1632: arraylength
    //   1633: istore #9
    //   1635: iload #9
    //   1637: aload #8
    //   1639: arraylength
    //   1640: if_icmpge -> 1658
    //   1643: aload #8
    //   1645: iload #9
    //   1647: iload #7
    //   1649: i2b
    //   1650: bastore
    //   1651: iinc #9, 1
    //   1654: iload_2
    //   1655: ifeq -> 1635
    //   1658: aload #8
    //   1660: astore #4
    //   1662: bipush #64
    //   1664: newarray int
    //   1666: dup
    //   1667: iconst_0
    //   1668: ldc 16843776
    //   1670: iastore
    //   1671: dup
    //   1672: iconst_1
    //   1673: iconst_0
    //   1674: iastore
    //   1675: dup
    //   1676: iconst_2
    //   1677: ldc 65536
    //   1679: iastore
    //   1680: dup
    //   1681: iconst_3
    //   1682: ldc 16843780
    //   1684: iastore
    //   1685: dup
    //   1686: iconst_4
    //   1687: ldc 16842756
    //   1689: iastore
    //   1690: dup
    //   1691: iconst_5
    //   1692: ldc 66564
    //   1694: iastore
    //   1695: dup
    //   1696: bipush #6
    //   1698: iconst_4
    //   1699: iastore
    //   1700: dup
    //   1701: bipush #7
    //   1703: ldc 65536
    //   1705: iastore
    //   1706: dup
    //   1707: bipush #8
    //   1709: sipush #1024
    //   1712: iastore
    //   1713: dup
    //   1714: bipush #9
    //   1716: ldc 16843776
    //   1718: iastore
    //   1719: dup
    //   1720: bipush #10
    //   1722: ldc 16843780
    //   1724: iastore
    //   1725: dup
    //   1726: bipush #11
    //   1728: sipush #1024
    //   1731: iastore
    //   1732: dup
    //   1733: bipush #12
    //   1735: ldc 16778244
    //   1737: iastore
    //   1738: dup
    //   1739: bipush #13
    //   1741: ldc 16842756
    //   1743: iastore
    //   1744: dup
    //   1745: bipush #14
    //   1747: ldc 16777216
    //   1749: iastore
    //   1750: dup
    //   1751: bipush #15
    //   1753: iconst_4
    //   1754: iastore
    //   1755: dup
    //   1756: bipush #16
    //   1758: sipush #1028
    //   1761: iastore
    //   1762: dup
    //   1763: bipush #17
    //   1765: ldc 16778240
    //   1767: iastore
    //   1768: dup
    //   1769: bipush #18
    //   1771: ldc 16778240
    //   1773: iastore
    //   1774: dup
    //   1775: bipush #19
    //   1777: ldc 66560
    //   1779: iastore
    //   1780: dup
    //   1781: bipush #20
    //   1783: ldc 66560
    //   1785: iastore
    //   1786: dup
    //   1787: bipush #21
    //   1789: ldc 16842752
    //   1791: iastore
    //   1792: dup
    //   1793: bipush #22
    //   1795: ldc 16842752
    //   1797: iastore
    //   1798: dup
    //   1799: bipush #23
    //   1801: ldc 16778244
    //   1803: iastore
    //   1804: dup
    //   1805: bipush #24
    //   1807: ldc 65540
    //   1809: iastore
    //   1810: dup
    //   1811: bipush #25
    //   1813: ldc 16777220
    //   1815: iastore
    //   1816: dup
    //   1817: bipush #26
    //   1819: ldc 16777220
    //   1821: iastore
    //   1822: dup
    //   1823: bipush #27
    //   1825: ldc 65540
    //   1827: iastore
    //   1828: dup
    //   1829: bipush #28
    //   1831: iconst_0
    //   1832: iastore
    //   1833: dup
    //   1834: bipush #29
    //   1836: sipush #1028
    //   1839: iastore
    //   1840: dup
    //   1841: bipush #30
    //   1843: ldc 66564
    //   1845: iastore
    //   1846: dup
    //   1847: bipush #31
    //   1849: ldc 16777216
    //   1851: iastore
    //   1852: dup
    //   1853: bipush #32
    //   1855: ldc 65536
    //   1857: iastore
    //   1858: dup
    //   1859: bipush #33
    //   1861: ldc 16843780
    //   1863: iastore
    //   1864: dup
    //   1865: bipush #34
    //   1867: iconst_4
    //   1868: iastore
    //   1869: dup
    //   1870: bipush #35
    //   1872: ldc 16842752
    //   1874: iastore
    //   1875: dup
    //   1876: bipush #36
    //   1878: ldc 16843776
    //   1880: iastore
    //   1881: dup
    //   1882: bipush #37
    //   1884: ldc 16777216
    //   1886: iastore
    //   1887: dup
    //   1888: bipush #38
    //   1890: ldc 16777216
    //   1892: iastore
    //   1893: dup
    //   1894: bipush #39
    //   1896: sipush #1024
    //   1899: iastore
    //   1900: dup
    //   1901: bipush #40
    //   1903: ldc 16842756
    //   1905: iastore
    //   1906: dup
    //   1907: bipush #41
    //   1909: ldc 65536
    //   1911: iastore
    //   1912: dup
    //   1913: bipush #42
    //   1915: ldc 66560
    //   1917: iastore
    //   1918: dup
    //   1919: bipush #43
    //   1921: ldc 16777220
    //   1923: iastore
    //   1924: dup
    //   1925: bipush #44
    //   1927: sipush #1024
    //   1930: iastore
    //   1931: dup
    //   1932: bipush #45
    //   1934: iconst_4
    //   1935: iastore
    //   1936: dup
    //   1937: bipush #46
    //   1939: ldc 16778244
    //   1941: iastore
    //   1942: dup
    //   1943: bipush #47
    //   1945: ldc 66564
    //   1947: iastore
    //   1948: dup
    //   1949: bipush #48
    //   1951: ldc 16843780
    //   1953: iastore
    //   1954: dup
    //   1955: bipush #49
    //   1957: ldc 65540
    //   1959: iastore
    //   1960: dup
    //   1961: bipush #50
    //   1963: ldc 16842752
    //   1965: iastore
    //   1966: dup
    //   1967: bipush #51
    //   1969: ldc 16778244
    //   1971: iastore
    //   1972: dup
    //   1973: bipush #52
    //   1975: ldc 16777220
    //   1977: iastore
    //   1978: dup
    //   1979: bipush #53
    //   1981: sipush #1028
    //   1984: iastore
    //   1985: dup
    //   1986: bipush #54
    //   1988: ldc 66564
    //   1990: iastore
    //   1991: dup
    //   1992: bipush #55
    //   1994: ldc 16843776
    //   1996: iastore
    //   1997: dup
    //   1998: bipush #56
    //   2000: sipush #1028
    //   2003: iastore
    //   2004: dup
    //   2005: bipush #57
    //   2007: ldc 16778240
    //   2009: iastore
    //   2010: dup
    //   2011: bipush #58
    //   2013: ldc 16778240
    //   2015: iastore
    //   2016: dup
    //   2017: bipush #59
    //   2019: iconst_0
    //   2020: iastore
    //   2021: dup
    //   2022: bipush #60
    //   2024: ldc 65540
    //   2026: iastore
    //   2027: dup
    //   2028: bipush #61
    //   2030: ldc 66560
    //   2032: iastore
    //   2033: dup
    //   2034: bipush #62
    //   2036: iconst_0
    //   2037: iastore
    //   2038: dup
    //   2039: bipush #63
    //   2041: ldc 16842756
    //   2043: iastore
    //   2044: astore #9
    //   2046: bipush #64
    //   2048: newarray int
    //   2050: dup
    //   2051: iconst_0
    //   2052: ldc -2146402272
    //   2054: iastore
    //   2055: dup
    //   2056: iconst_1
    //   2057: ldc -2147450880
    //   2059: iastore
    //   2060: dup
    //   2061: iconst_2
    //   2062: ldc 32768
    //   2064: iastore
    //   2065: dup
    //   2066: iconst_3
    //   2067: ldc 1081376
    //   2069: iastore
    //   2070: dup
    //   2071: iconst_4
    //   2072: ldc 1048576
    //   2074: iastore
    //   2075: dup
    //   2076: iconst_5
    //   2077: bipush #32
    //   2079: iastore
    //   2080: dup
    //   2081: bipush #6
    //   2083: ldc -2146435040
    //   2085: iastore
    //   2086: dup
    //   2087: bipush #7
    //   2089: ldc -2147450848
    //   2091: iastore
    //   2092: dup
    //   2093: bipush #8
    //   2095: ldc -2147483616
    //   2097: iastore
    //   2098: dup
    //   2099: bipush #9
    //   2101: ldc -2146402272
    //   2103: iastore
    //   2104: dup
    //   2105: bipush #10
    //   2107: ldc -2146402304
    //   2109: iastore
    //   2110: dup
    //   2111: bipush #11
    //   2113: ldc -2147483648
    //   2115: iastore
    //   2116: dup
    //   2117: bipush #12
    //   2119: ldc -2147450880
    //   2121: iastore
    //   2122: dup
    //   2123: bipush #13
    //   2125: ldc 1048576
    //   2127: iastore
    //   2128: dup
    //   2129: bipush #14
    //   2131: bipush #32
    //   2133: iastore
    //   2134: dup
    //   2135: bipush #15
    //   2137: ldc -2146435040
    //   2139: iastore
    //   2140: dup
    //   2141: bipush #16
    //   2143: ldc 1081344
    //   2145: iastore
    //   2146: dup
    //   2147: bipush #17
    //   2149: ldc 1048608
    //   2151: iastore
    //   2152: dup
    //   2153: bipush #18
    //   2155: ldc -2147450848
    //   2157: iastore
    //   2158: dup
    //   2159: bipush #19
    //   2161: iconst_0
    //   2162: iastore
    //   2163: dup
    //   2164: bipush #20
    //   2166: ldc -2147483648
    //   2168: iastore
    //   2169: dup
    //   2170: bipush #21
    //   2172: ldc 32768
    //   2174: iastore
    //   2175: dup
    //   2176: bipush #22
    //   2178: ldc 1081376
    //   2180: iastore
    //   2181: dup
    //   2182: bipush #23
    //   2184: ldc -2146435072
    //   2186: iastore
    //   2187: dup
    //   2188: bipush #24
    //   2190: ldc 1048608
    //   2192: iastore
    //   2193: dup
    //   2194: bipush #25
    //   2196: ldc -2147483616
    //   2198: iastore
    //   2199: dup
    //   2200: bipush #26
    //   2202: iconst_0
    //   2203: iastore
    //   2204: dup
    //   2205: bipush #27
    //   2207: ldc 1081344
    //   2209: iastore
    //   2210: dup
    //   2211: bipush #28
    //   2213: ldc 32800
    //   2215: iastore
    //   2216: dup
    //   2217: bipush #29
    //   2219: ldc -2146402304
    //   2221: iastore
    //   2222: dup
    //   2223: bipush #30
    //   2225: ldc -2146435072
    //   2227: iastore
    //   2228: dup
    //   2229: bipush #31
    //   2231: ldc 32800
    //   2233: iastore
    //   2234: dup
    //   2235: bipush #32
    //   2237: iconst_0
    //   2238: iastore
    //   2239: dup
    //   2240: bipush #33
    //   2242: ldc 1081376
    //   2244: iastore
    //   2245: dup
    //   2246: bipush #34
    //   2248: ldc -2146435040
    //   2250: iastore
    //   2251: dup
    //   2252: bipush #35
    //   2254: ldc 1048576
    //   2256: iastore
    //   2257: dup
    //   2258: bipush #36
    //   2260: ldc -2147450848
    //   2262: iastore
    //   2263: dup
    //   2264: bipush #37
    //   2266: ldc -2146435072
    //   2268: iastore
    //   2269: dup
    //   2270: bipush #38
    //   2272: ldc -2146402304
    //   2274: iastore
    //   2275: dup
    //   2276: bipush #39
    //   2278: ldc 32768
    //   2280: iastore
    //   2281: dup
    //   2282: bipush #40
    //   2284: ldc -2146435072
    //   2286: iastore
    //   2287: dup
    //   2288: bipush #41
    //   2290: ldc -2147450880
    //   2292: iastore
    //   2293: dup
    //   2294: bipush #42
    //   2296: bipush #32
    //   2298: iastore
    //   2299: dup
    //   2300: bipush #43
    //   2302: ldc -2146402272
    //   2304: iastore
    //   2305: dup
    //   2306: bipush #44
    //   2308: ldc 1081376
    //   2310: iastore
    //   2311: dup
    //   2312: bipush #45
    //   2314: bipush #32
    //   2316: iastore
    //   2317: dup
    //   2318: bipush #46
    //   2320: ldc 32768
    //   2322: iastore
    //   2323: dup
    //   2324: bipush #47
    //   2326: ldc -2147483648
    //   2328: iastore
    //   2329: dup
    //   2330: bipush #48
    //   2332: ldc 32800
    //   2334: iastore
    //   2335: dup
    //   2336: bipush #49
    //   2338: ldc -2146402304
    //   2340: iastore
    //   2341: dup
    //   2342: bipush #50
    //   2344: ldc 1048576
    //   2346: iastore
    //   2347: dup
    //   2348: bipush #51
    //   2350: ldc -2147483616
    //   2352: iastore
    //   2353: dup
    //   2354: bipush #52
    //   2356: ldc 1048608
    //   2358: iastore
    //   2359: dup
    //   2360: bipush #53
    //   2362: ldc -2147450848
    //   2364: iastore
    //   2365: dup
    //   2366: bipush #54
    //   2368: ldc -2147483616
    //   2370: iastore
    //   2371: dup
    //   2372: bipush #55
    //   2374: ldc 1048608
    //   2376: iastore
    //   2377: dup
    //   2378: bipush #56
    //   2380: ldc 1081344
    //   2382: iastore
    //   2383: dup
    //   2384: bipush #57
    //   2386: iconst_0
    //   2387: iastore
    //   2388: dup
    //   2389: bipush #58
    //   2391: ldc -2147450880
    //   2393: iastore
    //   2394: dup
    //   2395: bipush #59
    //   2397: ldc 32800
    //   2399: iastore
    //   2400: dup
    //   2401: bipush #60
    //   2403: ldc -2147483648
    //   2405: iastore
    //   2406: dup
    //   2407: bipush #61
    //   2409: ldc -2146435040
    //   2411: iastore
    //   2412: dup
    //   2413: bipush #62
    //   2415: ldc -2146402272
    //   2417: iastore
    //   2418: dup
    //   2419: bipush #63
    //   2421: ldc 1081344
    //   2423: iastore
    //   2424: astore #10
    //   2426: bipush #64
    //   2428: newarray int
    //   2430: dup
    //   2431: iconst_0
    //   2432: sipush #520
    //   2435: iastore
    //   2436: dup
    //   2437: iconst_1
    //   2438: ldc 134349312
    //   2440: iastore
    //   2441: dup
    //   2442: iconst_2
    //   2443: iconst_0
    //   2444: iastore
    //   2445: dup
    //   2446: iconst_3
    //   2447: ldc 134348808
    //   2449: iastore
    //   2450: dup
    //   2451: iconst_4
    //   2452: ldc 134218240
    //   2454: iastore
    //   2455: dup
    //   2456: iconst_5
    //   2457: iconst_0
    //   2458: iastore
    //   2459: dup
    //   2460: bipush #6
    //   2462: ldc 131592
    //   2464: iastore
    //   2465: dup
    //   2466: bipush #7
    //   2468: ldc 134218240
    //   2470: iastore
    //   2471: dup
    //   2472: bipush #8
    //   2474: ldc 131080
    //   2476: iastore
    //   2477: dup
    //   2478: bipush #9
    //   2480: ldc 134217736
    //   2482: iastore
    //   2483: dup
    //   2484: bipush #10
    //   2486: ldc 134217736
    //   2488: iastore
    //   2489: dup
    //   2490: bipush #11
    //   2492: ldc 131072
    //   2494: iastore
    //   2495: dup
    //   2496: bipush #12
    //   2498: ldc 134349320
    //   2500: iastore
    //   2501: dup
    //   2502: bipush #13
    //   2504: ldc 131080
    //   2506: iastore
    //   2507: dup
    //   2508: bipush #14
    //   2510: ldc 134348800
    //   2512: iastore
    //   2513: dup
    //   2514: bipush #15
    //   2516: sipush #520
    //   2519: iastore
    //   2520: dup
    //   2521: bipush #16
    //   2523: ldc 134217728
    //   2525: iastore
    //   2526: dup
    //   2527: bipush #17
    //   2529: bipush #8
    //   2531: iastore
    //   2532: dup
    //   2533: bipush #18
    //   2535: ldc 134349312
    //   2537: iastore
    //   2538: dup
    //   2539: bipush #19
    //   2541: sipush #512
    //   2544: iastore
    //   2545: dup
    //   2546: bipush #20
    //   2548: ldc 131584
    //   2550: iastore
    //   2551: dup
    //   2552: bipush #21
    //   2554: ldc 134348800
    //   2556: iastore
    //   2557: dup
    //   2558: bipush #22
    //   2560: ldc 134348808
    //   2562: iastore
    //   2563: dup
    //   2564: bipush #23
    //   2566: ldc 131592
    //   2568: iastore
    //   2569: dup
    //   2570: bipush #24
    //   2572: ldc 134218248
    //   2574: iastore
    //   2575: dup
    //   2576: bipush #25
    //   2578: ldc 131584
    //   2580: iastore
    //   2581: dup
    //   2582: bipush #26
    //   2584: ldc 131072
    //   2586: iastore
    //   2587: dup
    //   2588: bipush #27
    //   2590: ldc 134218248
    //   2592: iastore
    //   2593: dup
    //   2594: bipush #28
    //   2596: bipush #8
    //   2598: iastore
    //   2599: dup
    //   2600: bipush #29
    //   2602: ldc 134349320
    //   2604: iastore
    //   2605: dup
    //   2606: bipush #30
    //   2608: sipush #512
    //   2611: iastore
    //   2612: dup
    //   2613: bipush #31
    //   2615: ldc 134217728
    //   2617: iastore
    //   2618: dup
    //   2619: bipush #32
    //   2621: ldc 134349312
    //   2623: iastore
    //   2624: dup
    //   2625: bipush #33
    //   2627: ldc 134217728
    //   2629: iastore
    //   2630: dup
    //   2631: bipush #34
    //   2633: ldc 131080
    //   2635: iastore
    //   2636: dup
    //   2637: bipush #35
    //   2639: sipush #520
    //   2642: iastore
    //   2643: dup
    //   2644: bipush #36
    //   2646: ldc 131072
    //   2648: iastore
    //   2649: dup
    //   2650: bipush #37
    //   2652: ldc 134349312
    //   2654: iastore
    //   2655: dup
    //   2656: bipush #38
    //   2658: ldc 134218240
    //   2660: iastore
    //   2661: dup
    //   2662: bipush #39
    //   2664: iconst_0
    //   2665: iastore
    //   2666: dup
    //   2667: bipush #40
    //   2669: sipush #512
    //   2672: iastore
    //   2673: dup
    //   2674: bipush #41
    //   2676: ldc 131080
    //   2678: iastore
    //   2679: dup
    //   2680: bipush #42
    //   2682: ldc 134349320
    //   2684: iastore
    //   2685: dup
    //   2686: bipush #43
    //   2688: ldc 134218240
    //   2690: iastore
    //   2691: dup
    //   2692: bipush #44
    //   2694: ldc 134217736
    //   2696: iastore
    //   2697: dup
    //   2698: bipush #45
    //   2700: sipush #512
    //   2703: iastore
    //   2704: dup
    //   2705: bipush #46
    //   2707: iconst_0
    //   2708: iastore
    //   2709: dup
    //   2710: bipush #47
    //   2712: ldc 134348808
    //   2714: iastore
    //   2715: dup
    //   2716: bipush #48
    //   2718: ldc 134218248
    //   2720: iastore
    //   2721: dup
    //   2722: bipush #49
    //   2724: ldc 131072
    //   2726: iastore
    //   2727: dup
    //   2728: bipush #50
    //   2730: ldc 134217728
    //   2732: iastore
    //   2733: dup
    //   2734: bipush #51
    //   2736: ldc 134349320
    //   2738: iastore
    //   2739: dup
    //   2740: bipush #52
    //   2742: bipush #8
    //   2744: iastore
    //   2745: dup
    //   2746: bipush #53
    //   2748: ldc 131592
    //   2750: iastore
    //   2751: dup
    //   2752: bipush #54
    //   2754: ldc 131584
    //   2756: iastore
    //   2757: dup
    //   2758: bipush #55
    //   2760: ldc 134217736
    //   2762: iastore
    //   2763: dup
    //   2764: bipush #56
    //   2766: ldc 134348800
    //   2768: iastore
    //   2769: dup
    //   2770: bipush #57
    //   2772: ldc 134218248
    //   2774: iastore
    //   2775: dup
    //   2776: bipush #58
    //   2778: sipush #520
    //   2781: iastore
    //   2782: dup
    //   2783: bipush #59
    //   2785: ldc 134348800
    //   2787: iastore
    //   2788: dup
    //   2789: bipush #60
    //   2791: ldc 131592
    //   2793: iastore
    //   2794: dup
    //   2795: bipush #61
    //   2797: bipush #8
    //   2799: iastore
    //   2800: dup
    //   2801: bipush #62
    //   2803: ldc 134348808
    //   2805: iastore
    //   2806: dup
    //   2807: bipush #63
    //   2809: ldc 131584
    //   2811: iastore
    //   2812: astore #11
    //   2814: bipush #64
    //   2816: newarray int
    //   2818: dup
    //   2819: iconst_0
    //   2820: ldc 8396801
    //   2822: iastore
    //   2823: dup
    //   2824: iconst_1
    //   2825: sipush #8321
    //   2828: iastore
    //   2829: dup
    //   2830: iconst_2
    //   2831: sipush #8321
    //   2834: iastore
    //   2835: dup
    //   2836: iconst_3
    //   2837: sipush #128
    //   2840: iastore
    //   2841: dup
    //   2842: iconst_4
    //   2843: ldc 8396928
    //   2845: iastore
    //   2846: dup
    //   2847: iconst_5
    //   2848: ldc 8388737
    //   2850: iastore
    //   2851: dup
    //   2852: bipush #6
    //   2854: ldc 8388609
    //   2856: iastore
    //   2857: dup
    //   2858: bipush #7
    //   2860: sipush #8193
    //   2863: iastore
    //   2864: dup
    //   2865: bipush #8
    //   2867: iconst_0
    //   2868: iastore
    //   2869: dup
    //   2870: bipush #9
    //   2872: ldc 8396800
    //   2874: iastore
    //   2875: dup
    //   2876: bipush #10
    //   2878: ldc 8396800
    //   2880: iastore
    //   2881: dup
    //   2882: bipush #11
    //   2884: ldc 8396929
    //   2886: iastore
    //   2887: dup
    //   2888: bipush #12
    //   2890: sipush #129
    //   2893: iastore
    //   2894: dup
    //   2895: bipush #13
    //   2897: iconst_0
    //   2898: iastore
    //   2899: dup
    //   2900: bipush #14
    //   2902: ldc 8388736
    //   2904: iastore
    //   2905: dup
    //   2906: bipush #15
    //   2908: ldc 8388609
    //   2910: iastore
    //   2911: dup
    //   2912: bipush #16
    //   2914: iconst_1
    //   2915: iastore
    //   2916: dup
    //   2917: bipush #17
    //   2919: sipush #8192
    //   2922: iastore
    //   2923: dup
    //   2924: bipush #18
    //   2926: ldc 8388608
    //   2928: iastore
    //   2929: dup
    //   2930: bipush #19
    //   2932: ldc 8396801
    //   2934: iastore
    //   2935: dup
    //   2936: bipush #20
    //   2938: sipush #128
    //   2941: iastore
    //   2942: dup
    //   2943: bipush #21
    //   2945: ldc 8388608
    //   2947: iastore
    //   2948: dup
    //   2949: bipush #22
    //   2951: sipush #8193
    //   2954: iastore
    //   2955: dup
    //   2956: bipush #23
    //   2958: sipush #8320
    //   2961: iastore
    //   2962: dup
    //   2963: bipush #24
    //   2965: ldc 8388737
    //   2967: iastore
    //   2968: dup
    //   2969: bipush #25
    //   2971: iconst_1
    //   2972: iastore
    //   2973: dup
    //   2974: bipush #26
    //   2976: sipush #8320
    //   2979: iastore
    //   2980: dup
    //   2981: bipush #27
    //   2983: ldc 8388736
    //   2985: iastore
    //   2986: dup
    //   2987: bipush #28
    //   2989: sipush #8192
    //   2992: iastore
    //   2993: dup
    //   2994: bipush #29
    //   2996: ldc 8396928
    //   2998: iastore
    //   2999: dup
    //   3000: bipush #30
    //   3002: ldc 8396929
    //   3004: iastore
    //   3005: dup
    //   3006: bipush #31
    //   3008: sipush #129
    //   3011: iastore
    //   3012: dup
    //   3013: bipush #32
    //   3015: ldc 8388736
    //   3017: iastore
    //   3018: dup
    //   3019: bipush #33
    //   3021: ldc 8388609
    //   3023: iastore
    //   3024: dup
    //   3025: bipush #34
    //   3027: ldc 8396800
    //   3029: iastore
    //   3030: dup
    //   3031: bipush #35
    //   3033: ldc 8396929
    //   3035: iastore
    //   3036: dup
    //   3037: bipush #36
    //   3039: sipush #129
    //   3042: iastore
    //   3043: dup
    //   3044: bipush #37
    //   3046: iconst_0
    //   3047: iastore
    //   3048: dup
    //   3049: bipush #38
    //   3051: iconst_0
    //   3052: iastore
    //   3053: dup
    //   3054: bipush #39
    //   3056: ldc 8396800
    //   3058: iastore
    //   3059: dup
    //   3060: bipush #40
    //   3062: sipush #8320
    //   3065: iastore
    //   3066: dup
    //   3067: bipush #41
    //   3069: ldc 8388736
    //   3071: iastore
    //   3072: dup
    //   3073: bipush #42
    //   3075: ldc 8388737
    //   3077: iastore
    //   3078: dup
    //   3079: bipush #43
    //   3081: iconst_1
    //   3082: iastore
    //   3083: dup
    //   3084: bipush #44
    //   3086: ldc 8396801
    //   3088: iastore
    //   3089: dup
    //   3090: bipush #45
    //   3092: sipush #8321
    //   3095: iastore
    //   3096: dup
    //   3097: bipush #46
    //   3099: sipush #8321
    //   3102: iastore
    //   3103: dup
    //   3104: bipush #47
    //   3106: sipush #128
    //   3109: iastore
    //   3110: dup
    //   3111: bipush #48
    //   3113: ldc 8396929
    //   3115: iastore
    //   3116: dup
    //   3117: bipush #49
    //   3119: sipush #129
    //   3122: iastore
    //   3123: dup
    //   3124: bipush #50
    //   3126: iconst_1
    //   3127: iastore
    //   3128: dup
    //   3129: bipush #51
    //   3131: sipush #8192
    //   3134: iastore
    //   3135: dup
    //   3136: bipush #52
    //   3138: ldc 8388609
    //   3140: iastore
    //   3141: dup
    //   3142: bipush #53
    //   3144: sipush #8193
    //   3147: iastore
    //   3148: dup
    //   3149: bipush #54
    //   3151: ldc 8396928
    //   3153: iastore
    //   3154: dup
    //   3155: bipush #55
    //   3157: ldc 8388737
    //   3159: iastore
    //   3160: dup
    //   3161: bipush #56
    //   3163: sipush #8193
    //   3166: iastore
    //   3167: dup
    //   3168: bipush #57
    //   3170: sipush #8320
    //   3173: iastore
    //   3174: dup
    //   3175: bipush #58
    //   3177: ldc 8388608
    //   3179: iastore
    //   3180: dup
    //   3181: bipush #59
    //   3183: ldc 8396801
    //   3185: iastore
    //   3186: dup
    //   3187: bipush #60
    //   3189: sipush #128
    //   3192: iastore
    //   3193: dup
    //   3194: bipush #61
    //   3196: ldc 8388608
    //   3198: iastore
    //   3199: dup
    //   3200: bipush #62
    //   3202: sipush #8192
    //   3205: iastore
    //   3206: dup
    //   3207: bipush #63
    //   3209: ldc 8396928
    //   3211: iastore
    //   3212: astore #12
    //   3214: bipush #64
    //   3216: newarray int
    //   3218: dup
    //   3219: iconst_0
    //   3220: sipush #256
    //   3223: iastore
    //   3224: dup
    //   3225: iconst_1
    //   3226: ldc 34078976
    //   3228: iastore
    //   3229: dup
    //   3230: iconst_2
    //   3231: ldc 34078720
    //   3233: iastore
    //   3234: dup
    //   3235: iconst_3
    //   3236: ldc 1107296512
    //   3238: iastore
    //   3239: dup
    //   3240: iconst_4
    //   3241: ldc 524288
    //   3243: iastore
    //   3244: dup
    //   3245: iconst_5
    //   3246: sipush #256
    //   3249: iastore
    //   3250: dup
    //   3251: bipush #6
    //   3253: ldc 1073741824
    //   3255: iastore
    //   3256: dup
    //   3257: bipush #7
    //   3259: ldc 34078720
    //   3261: iastore
    //   3262: dup
    //   3263: bipush #8
    //   3265: ldc 1074266368
    //   3267: iastore
    //   3268: dup
    //   3269: bipush #9
    //   3271: ldc 524288
    //   3273: iastore
    //   3274: dup
    //   3275: bipush #10
    //   3277: ldc 33554688
    //   3279: iastore
    //   3280: dup
    //   3281: bipush #11
    //   3283: ldc 1074266368
    //   3285: iastore
    //   3286: dup
    //   3287: bipush #12
    //   3289: ldc 1107296512
    //   3291: iastore
    //   3292: dup
    //   3293: bipush #13
    //   3295: ldc 1107820544
    //   3297: iastore
    //   3298: dup
    //   3299: bipush #14
    //   3301: ldc 524544
    //   3303: iastore
    //   3304: dup
    //   3305: bipush #15
    //   3307: ldc 1073741824
    //   3309: iastore
    //   3310: dup
    //   3311: bipush #16
    //   3313: ldc 33554432
    //   3315: iastore
    //   3316: dup
    //   3317: bipush #17
    //   3319: ldc 1074266112
    //   3321: iastore
    //   3322: dup
    //   3323: bipush #18
    //   3325: ldc 1074266112
    //   3327: iastore
    //   3328: dup
    //   3329: bipush #19
    //   3331: iconst_0
    //   3332: iastore
    //   3333: dup
    //   3334: bipush #20
    //   3336: ldc 1073742080
    //   3338: iastore
    //   3339: dup
    //   3340: bipush #21
    //   3342: ldc 1107820800
    //   3344: iastore
    //   3345: dup
    //   3346: bipush #22
    //   3348: ldc 1107820800
    //   3350: iastore
    //   3351: dup
    //   3352: bipush #23
    //   3354: ldc 33554688
    //   3356: iastore
    //   3357: dup
    //   3358: bipush #24
    //   3360: ldc 1107820544
    //   3362: iastore
    //   3363: dup
    //   3364: bipush #25
    //   3366: ldc 1073742080
    //   3368: iastore
    //   3369: dup
    //   3370: bipush #26
    //   3372: iconst_0
    //   3373: iastore
    //   3374: dup
    //   3375: bipush #27
    //   3377: ldc 1107296256
    //   3379: iastore
    //   3380: dup
    //   3381: bipush #28
    //   3383: ldc 34078976
    //   3385: iastore
    //   3386: dup
    //   3387: bipush #29
    //   3389: ldc 33554432
    //   3391: iastore
    //   3392: dup
    //   3393: bipush #30
    //   3395: ldc 1107296256
    //   3397: iastore
    //   3398: dup
    //   3399: bipush #31
    //   3401: ldc 524544
    //   3403: iastore
    //   3404: dup
    //   3405: bipush #32
    //   3407: ldc 524288
    //   3409: iastore
    //   3410: dup
    //   3411: bipush #33
    //   3413: ldc 1107296512
    //   3415: iastore
    //   3416: dup
    //   3417: bipush #34
    //   3419: sipush #256
    //   3422: iastore
    //   3423: dup
    //   3424: bipush #35
    //   3426: ldc 33554432
    //   3428: iastore
    //   3429: dup
    //   3430: bipush #36
    //   3432: ldc 1073741824
    //   3434: iastore
    //   3435: dup
    //   3436: bipush #37
    //   3438: ldc 34078720
    //   3440: iastore
    //   3441: dup
    //   3442: bipush #38
    //   3444: ldc 1107296512
    //   3446: iastore
    //   3447: dup
    //   3448: bipush #39
    //   3450: ldc 1074266368
    //   3452: iastore
    //   3453: dup
    //   3454: bipush #40
    //   3456: ldc 33554688
    //   3458: iastore
    //   3459: dup
    //   3460: bipush #41
    //   3462: ldc 1073741824
    //   3464: iastore
    //   3465: dup
    //   3466: bipush #42
    //   3468: ldc 1107820544
    //   3470: iastore
    //   3471: dup
    //   3472: bipush #43
    //   3474: ldc 34078976
    //   3476: iastore
    //   3477: dup
    //   3478: bipush #44
    //   3480: ldc 1074266368
    //   3482: iastore
    //   3483: dup
    //   3484: bipush #45
    //   3486: sipush #256
    //   3489: iastore
    //   3490: dup
    //   3491: bipush #46
    //   3493: ldc 33554432
    //   3495: iastore
    //   3496: dup
    //   3497: bipush #47
    //   3499: ldc 1107820544
    //   3501: iastore
    //   3502: dup
    //   3503: bipush #48
    //   3505: ldc 1107820800
    //   3507: iastore
    //   3508: dup
    //   3509: bipush #49
    //   3511: ldc 524544
    //   3513: iastore
    //   3514: dup
    //   3515: bipush #50
    //   3517: ldc 1107296256
    //   3519: iastore
    //   3520: dup
    //   3521: bipush #51
    //   3523: ldc 1107820800
    //   3525: iastore
    //   3526: dup
    //   3527: bipush #52
    //   3529: ldc 34078720
    //   3531: iastore
    //   3532: dup
    //   3533: bipush #53
    //   3535: iconst_0
    //   3536: iastore
    //   3537: dup
    //   3538: bipush #54
    //   3540: ldc 1074266112
    //   3542: iastore
    //   3543: dup
    //   3544: bipush #55
    //   3546: ldc 1107296256
    //   3548: iastore
    //   3549: dup
    //   3550: bipush #56
    //   3552: ldc 524544
    //   3554: iastore
    //   3555: dup
    //   3556: bipush #57
    //   3558: ldc 33554688
    //   3560: iastore
    //   3561: dup
    //   3562: bipush #58
    //   3564: ldc 1073742080
    //   3566: iastore
    //   3567: dup
    //   3568: bipush #59
    //   3570: ldc 524288
    //   3572: iastore
    //   3573: dup
    //   3574: bipush #60
    //   3576: iconst_0
    //   3577: iastore
    //   3578: dup
    //   3579: bipush #61
    //   3581: ldc 1074266112
    //   3583: iastore
    //   3584: dup
    //   3585: bipush #62
    //   3587: ldc 34078976
    //   3589: iastore
    //   3590: dup
    //   3591: bipush #63
    //   3593: ldc 1073742080
    //   3595: iastore
    //   3596: astore #13
    //   3598: bipush #64
    //   3600: newarray int
    //   3602: dup
    //   3603: iconst_0
    //   3604: ldc 536870928
    //   3606: iastore
    //   3607: dup
    //   3608: iconst_1
    //   3609: ldc 541065216
    //   3611: iastore
    //   3612: dup
    //   3613: iconst_2
    //   3614: sipush #16384
    //   3617: iastore
    //   3618: dup
    //   3619: iconst_3
    //   3620: ldc 541081616
    //   3622: iastore
    //   3623: dup
    //   3624: iconst_4
    //   3625: ldc 541065216
    //   3627: iastore
    //   3628: dup
    //   3629: iconst_5
    //   3630: bipush #16
    //   3632: iastore
    //   3633: dup
    //   3634: bipush #6
    //   3636: ldc 541081616
    //   3638: iastore
    //   3639: dup
    //   3640: bipush #7
    //   3642: ldc 4194304
    //   3644: iastore
    //   3645: dup
    //   3646: bipush #8
    //   3648: ldc 536887296
    //   3650: iastore
    //   3651: dup
    //   3652: bipush #9
    //   3654: ldc 4210704
    //   3656: iastore
    //   3657: dup
    //   3658: bipush #10
    //   3660: ldc 4194304
    //   3662: iastore
    //   3663: dup
    //   3664: bipush #11
    //   3666: ldc 536870928
    //   3668: iastore
    //   3669: dup
    //   3670: bipush #12
    //   3672: ldc 4194320
    //   3674: iastore
    //   3675: dup
    //   3676: bipush #13
    //   3678: ldc 536887296
    //   3680: iastore
    //   3681: dup
    //   3682: bipush #14
    //   3684: ldc 536870912
    //   3686: iastore
    //   3687: dup
    //   3688: bipush #15
    //   3690: sipush #16400
    //   3693: iastore
    //   3694: dup
    //   3695: bipush #16
    //   3697: iconst_0
    //   3698: iastore
    //   3699: dup
    //   3700: bipush #17
    //   3702: ldc 4194320
    //   3704: iastore
    //   3705: dup
    //   3706: bipush #18
    //   3708: ldc 536887312
    //   3710: iastore
    //   3711: dup
    //   3712: bipush #19
    //   3714: sipush #16384
    //   3717: iastore
    //   3718: dup
    //   3719: bipush #20
    //   3721: ldc 4210688
    //   3723: iastore
    //   3724: dup
    //   3725: bipush #21
    //   3727: ldc 536887312
    //   3729: iastore
    //   3730: dup
    //   3731: bipush #22
    //   3733: bipush #16
    //   3735: iastore
    //   3736: dup
    //   3737: bipush #23
    //   3739: ldc 541065232
    //   3741: iastore
    //   3742: dup
    //   3743: bipush #24
    //   3745: ldc 541065232
    //   3747: iastore
    //   3748: dup
    //   3749: bipush #25
    //   3751: iconst_0
    //   3752: iastore
    //   3753: dup
    //   3754: bipush #26
    //   3756: ldc 4210704
    //   3758: iastore
    //   3759: dup
    //   3760: bipush #27
    //   3762: ldc 541081600
    //   3764: iastore
    //   3765: dup
    //   3766: bipush #28
    //   3768: sipush #16400
    //   3771: iastore
    //   3772: dup
    //   3773: bipush #29
    //   3775: ldc 4210688
    //   3777: iastore
    //   3778: dup
    //   3779: bipush #30
    //   3781: ldc 541081600
    //   3783: iastore
    //   3784: dup
    //   3785: bipush #31
    //   3787: ldc 536870912
    //   3789: iastore
    //   3790: dup
    //   3791: bipush #32
    //   3793: ldc 536887296
    //   3795: iastore
    //   3796: dup
    //   3797: bipush #33
    //   3799: bipush #16
    //   3801: iastore
    //   3802: dup
    //   3803: bipush #34
    //   3805: ldc 541065232
    //   3807: iastore
    //   3808: dup
    //   3809: bipush #35
    //   3811: ldc 4210688
    //   3813: iastore
    //   3814: dup
    //   3815: bipush #36
    //   3817: ldc 541081616
    //   3819: iastore
    //   3820: dup
    //   3821: bipush #37
    //   3823: ldc 4194304
    //   3825: iastore
    //   3826: dup
    //   3827: bipush #38
    //   3829: sipush #16400
    //   3832: iastore
    //   3833: dup
    //   3834: bipush #39
    //   3836: ldc 536870928
    //   3838: iastore
    //   3839: dup
    //   3840: bipush #40
    //   3842: ldc 4194304
    //   3844: iastore
    //   3845: dup
    //   3846: bipush #41
    //   3848: ldc 536887296
    //   3850: iastore
    //   3851: dup
    //   3852: bipush #42
    //   3854: ldc 536870912
    //   3856: iastore
    //   3857: dup
    //   3858: bipush #43
    //   3860: sipush #16400
    //   3863: iastore
    //   3864: dup
    //   3865: bipush #44
    //   3867: ldc 536870928
    //   3869: iastore
    //   3870: dup
    //   3871: bipush #45
    //   3873: ldc 541081616
    //   3875: iastore
    //   3876: dup
    //   3877: bipush #46
    //   3879: ldc 4210688
    //   3881: iastore
    //   3882: dup
    //   3883: bipush #47
    //   3885: ldc 541065216
    //   3887: iastore
    //   3888: dup
    //   3889: bipush #48
    //   3891: ldc 4210704
    //   3893: iastore
    //   3894: dup
    //   3895: bipush #49
    //   3897: ldc 541081600
    //   3899: iastore
    //   3900: dup
    //   3901: bipush #50
    //   3903: iconst_0
    //   3904: iastore
    //   3905: dup
    //   3906: bipush #51
    //   3908: ldc 541065232
    //   3910: iastore
    //   3911: dup
    //   3912: bipush #52
    //   3914: bipush #16
    //   3916: iastore
    //   3917: dup
    //   3918: bipush #53
    //   3920: sipush #16384
    //   3923: iastore
    //   3924: dup
    //   3925: bipush #54
    //   3927: ldc 541065216
    //   3929: iastore
    //   3930: dup
    //   3931: bipush #55
    //   3933: ldc 4210704
    //   3935: iastore
    //   3936: dup
    //   3937: bipush #56
    //   3939: sipush #16384
    //   3942: iastore
    //   3943: dup
    //   3944: bipush #57
    //   3946: ldc 4194320
    //   3948: iastore
    //   3949: dup
    //   3950: bipush #58
    //   3952: ldc 536887312
    //   3954: iastore
    //   3955: dup
    //   3956: bipush #59
    //   3958: iconst_0
    //   3959: iastore
    //   3960: dup
    //   3961: bipush #60
    //   3963: ldc 541081600
    //   3965: iastore
    //   3966: dup
    //   3967: bipush #61
    //   3969: ldc 536870912
    //   3971: iastore
    //   3972: dup
    //   3973: bipush #62
    //   3975: ldc 4194320
    //   3977: iastore
    //   3978: dup
    //   3979: bipush #63
    //   3981: ldc 536887312
    //   3983: iastore
    //   3984: astore #14
    //   3986: bipush #64
    //   3988: newarray int
    //   3990: dup
    //   3991: iconst_0
    //   3992: ldc 2097152
    //   3994: iastore
    //   3995: dup
    //   3996: iconst_1
    //   3997: ldc 69206018
    //   3999: iastore
    //   4000: dup
    //   4001: iconst_2
    //   4002: ldc 67110914
    //   4004: iastore
    //   4005: dup
    //   4006: iconst_3
    //   4007: iconst_0
    //   4008: iastore
    //   4009: dup
    //   4010: iconst_4
    //   4011: sipush #2048
    //   4014: iastore
    //   4015: dup
    //   4016: iconst_5
    //   4017: ldc 67110914
    //   4019: iastore
    //   4020: dup
    //   4021: bipush #6
    //   4023: ldc 2099202
    //   4025: iastore
    //   4026: dup
    //   4027: bipush #7
    //   4029: ldc 69208064
    //   4031: iastore
    //   4032: dup
    //   4033: bipush #8
    //   4035: ldc 69208066
    //   4037: iastore
    //   4038: dup
    //   4039: bipush #9
    //   4041: ldc 2097152
    //   4043: iastore
    //   4044: dup
    //   4045: bipush #10
    //   4047: iconst_0
    //   4048: iastore
    //   4049: dup
    //   4050: bipush #11
    //   4052: ldc 67108866
    //   4054: iastore
    //   4055: dup
    //   4056: bipush #12
    //   4058: iconst_2
    //   4059: iastore
    //   4060: dup
    //   4061: bipush #13
    //   4063: ldc 67108864
    //   4065: iastore
    //   4066: dup
    //   4067: bipush #14
    //   4069: ldc 69206018
    //   4071: iastore
    //   4072: dup
    //   4073: bipush #15
    //   4075: sipush #2050
    //   4078: iastore
    //   4079: dup
    //   4080: bipush #16
    //   4082: ldc 67110912
    //   4084: iastore
    //   4085: dup
    //   4086: bipush #17
    //   4088: ldc 2099202
    //   4090: iastore
    //   4091: dup
    //   4092: bipush #18
    //   4094: ldc 2097154
    //   4096: iastore
    //   4097: dup
    //   4098: bipush #19
    //   4100: ldc 67110912
    //   4102: iastore
    //   4103: dup
    //   4104: bipush #20
    //   4106: ldc 67108866
    //   4108: iastore
    //   4109: dup
    //   4110: bipush #21
    //   4112: ldc 69206016
    //   4114: iastore
    //   4115: dup
    //   4116: bipush #22
    //   4118: ldc 69208064
    //   4120: iastore
    //   4121: dup
    //   4122: bipush #23
    //   4124: ldc 2097154
    //   4126: iastore
    //   4127: dup
    //   4128: bipush #24
    //   4130: ldc 69206016
    //   4132: iastore
    //   4133: dup
    //   4134: bipush #25
    //   4136: sipush #2048
    //   4139: iastore
    //   4140: dup
    //   4141: bipush #26
    //   4143: sipush #2050
    //   4146: iastore
    //   4147: dup
    //   4148: bipush #27
    //   4150: ldc 69208066
    //   4152: iastore
    //   4153: dup
    //   4154: bipush #28
    //   4156: ldc 2099200
    //   4158: iastore
    //   4159: dup
    //   4160: bipush #29
    //   4162: iconst_2
    //   4163: iastore
    //   4164: dup
    //   4165: bipush #30
    //   4167: ldc 67108864
    //   4169: iastore
    //   4170: dup
    //   4171: bipush #31
    //   4173: ldc 2099200
    //   4175: iastore
    //   4176: dup
    //   4177: bipush #32
    //   4179: ldc 67108864
    //   4181: iastore
    //   4182: dup
    //   4183: bipush #33
    //   4185: ldc 2099200
    //   4187: iastore
    //   4188: dup
    //   4189: bipush #34
    //   4191: ldc 2097152
    //   4193: iastore
    //   4194: dup
    //   4195: bipush #35
    //   4197: ldc 67110914
    //   4199: iastore
    //   4200: dup
    //   4201: bipush #36
    //   4203: ldc 67110914
    //   4205: iastore
    //   4206: dup
    //   4207: bipush #37
    //   4209: ldc 69206018
    //   4211: iastore
    //   4212: dup
    //   4213: bipush #38
    //   4215: ldc 69206018
    //   4217: iastore
    //   4218: dup
    //   4219: bipush #39
    //   4221: iconst_2
    //   4222: iastore
    //   4223: dup
    //   4224: bipush #40
    //   4226: ldc 2097154
    //   4228: iastore
    //   4229: dup
    //   4230: bipush #41
    //   4232: ldc 67108864
    //   4234: iastore
    //   4235: dup
    //   4236: bipush #42
    //   4238: ldc 67110912
    //   4240: iastore
    //   4241: dup
    //   4242: bipush #43
    //   4244: ldc 2097152
    //   4246: iastore
    //   4247: dup
    //   4248: bipush #44
    //   4250: ldc 69208064
    //   4252: iastore
    //   4253: dup
    //   4254: bipush #45
    //   4256: sipush #2050
    //   4259: iastore
    //   4260: dup
    //   4261: bipush #46
    //   4263: ldc 2099202
    //   4265: iastore
    //   4266: dup
    //   4267: bipush #47
    //   4269: ldc 69208064
    //   4271: iastore
    //   4272: dup
    //   4273: bipush #48
    //   4275: sipush #2050
    //   4278: iastore
    //   4279: dup
    //   4280: bipush #49
    //   4282: ldc 67108866
    //   4284: iastore
    //   4285: dup
    //   4286: bipush #50
    //   4288: ldc 69208066
    //   4290: iastore
    //   4291: dup
    //   4292: bipush #51
    //   4294: ldc 69206016
    //   4296: iastore
    //   4297: dup
    //   4298: bipush #52
    //   4300: ldc 2099200
    //   4302: iastore
    //   4303: dup
    //   4304: bipush #53
    //   4306: iconst_0
    //   4307: iastore
    //   4308: dup
    //   4309: bipush #54
    //   4311: iconst_2
    //   4312: iastore
    //   4313: dup
    //   4314: bipush #55
    //   4316: ldc 69208066
    //   4318: iastore
    //   4319: dup
    //   4320: bipush #56
    //   4322: iconst_0
    //   4323: iastore
    //   4324: dup
    //   4325: bipush #57
    //   4327: ldc 2099202
    //   4329: iastore
    //   4330: dup
    //   4331: bipush #58
    //   4333: ldc 69206016
    //   4335: iastore
    //   4336: dup
    //   4337: bipush #59
    //   4339: sipush #2048
    //   4342: iastore
    //   4343: dup
    //   4344: bipush #60
    //   4346: ldc 67108866
    //   4348: iastore
    //   4349: dup
    //   4350: bipush #61
    //   4352: ldc 67110912
    //   4354: iastore
    //   4355: dup
    //   4356: bipush #62
    //   4358: sipush #2048
    //   4361: iastore
    //   4362: dup
    //   4363: bipush #63
    //   4365: ldc 2097154
    //   4367: iastore
    //   4368: astore #15
    //   4370: bipush #64
    //   4372: newarray int
    //   4374: dup
    //   4375: iconst_0
    //   4376: ldc 268439616
    //   4378: iastore
    //   4379: dup
    //   4380: iconst_1
    //   4381: sipush #4096
    //   4384: iastore
    //   4385: dup
    //   4386: iconst_2
    //   4387: ldc 262144
    //   4389: iastore
    //   4390: dup
    //   4391: iconst_3
    //   4392: ldc 268701760
    //   4394: iastore
    //   4395: dup
    //   4396: iconst_4
    //   4397: ldc 268435456
    //   4399: iastore
    //   4400: dup
    //   4401: iconst_5
    //   4402: ldc 268439616
    //   4404: iastore
    //   4405: dup
    //   4406: bipush #6
    //   4408: bipush #64
    //   4410: iastore
    //   4411: dup
    //   4412: bipush #7
    //   4414: ldc 268435456
    //   4416: iastore
    //   4417: dup
    //   4418: bipush #8
    //   4420: ldc 262208
    //   4422: iastore
    //   4423: dup
    //   4424: bipush #9
    //   4426: ldc 268697600
    //   4428: iastore
    //   4429: dup
    //   4430: bipush #10
    //   4432: ldc 268701760
    //   4434: iastore
    //   4435: dup
    //   4436: bipush #11
    //   4438: ldc 266240
    //   4440: iastore
    //   4441: dup
    //   4442: bipush #12
    //   4444: ldc 268701696
    //   4446: iastore
    //   4447: dup
    //   4448: bipush #13
    //   4450: ldc 266304
    //   4452: iastore
    //   4453: dup
    //   4454: bipush #14
    //   4456: sipush #4096
    //   4459: iastore
    //   4460: dup
    //   4461: bipush #15
    //   4463: bipush #64
    //   4465: iastore
    //   4466: dup
    //   4467: bipush #16
    //   4469: ldc 268697600
    //   4471: iastore
    //   4472: dup
    //   4473: bipush #17
    //   4475: ldc 268435520
    //   4477: iastore
    //   4478: dup
    //   4479: bipush #18
    //   4481: ldc 268439552
    //   4483: iastore
    //   4484: dup
    //   4485: bipush #19
    //   4487: sipush #4160
    //   4490: iastore
    //   4491: dup
    //   4492: bipush #20
    //   4494: ldc 266240
    //   4496: iastore
    //   4497: dup
    //   4498: bipush #21
    //   4500: ldc 262208
    //   4502: iastore
    //   4503: dup
    //   4504: bipush #22
    //   4506: ldc 268697664
    //   4508: iastore
    //   4509: dup
    //   4510: bipush #23
    //   4512: ldc 268701696
    //   4514: iastore
    //   4515: dup
    //   4516: bipush #24
    //   4518: sipush #4160
    //   4521: iastore
    //   4522: dup
    //   4523: bipush #25
    //   4525: iconst_0
    //   4526: iastore
    //   4527: dup
    //   4528: bipush #26
    //   4530: iconst_0
    //   4531: iastore
    //   4532: dup
    //   4533: bipush #27
    //   4535: ldc 268697664
    //   4537: iastore
    //   4538: dup
    //   4539: bipush #28
    //   4541: ldc 268435520
    //   4543: iastore
    //   4544: dup
    //   4545: bipush #29
    //   4547: ldc 268439552
    //   4549: iastore
    //   4550: dup
    //   4551: bipush #30
    //   4553: ldc 266304
    //   4555: iastore
    //   4556: dup
    //   4557: bipush #31
    //   4559: ldc 262144
    //   4561: iastore
    //   4562: dup
    //   4563: bipush #32
    //   4565: ldc 266304
    //   4567: iastore
    //   4568: dup
    //   4569: bipush #33
    //   4571: ldc 262144
    //   4573: iastore
    //   4574: dup
    //   4575: bipush #34
    //   4577: ldc 268701696
    //   4579: iastore
    //   4580: dup
    //   4581: bipush #35
    //   4583: sipush #4096
    //   4586: iastore
    //   4587: dup
    //   4588: bipush #36
    //   4590: bipush #64
    //   4592: iastore
    //   4593: dup
    //   4594: bipush #37
    //   4596: ldc 268697664
    //   4598: iastore
    //   4599: dup
    //   4600: bipush #38
    //   4602: sipush #4096
    //   4605: iastore
    //   4606: dup
    //   4607: bipush #39
    //   4609: ldc 266304
    //   4611: iastore
    //   4612: dup
    //   4613: bipush #40
    //   4615: ldc 268439552
    //   4617: iastore
    //   4618: dup
    //   4619: bipush #41
    //   4621: bipush #64
    //   4623: iastore
    //   4624: dup
    //   4625: bipush #42
    //   4627: ldc 268435520
    //   4629: iastore
    //   4630: dup
    //   4631: bipush #43
    //   4633: ldc 268697600
    //   4635: iastore
    //   4636: dup
    //   4637: bipush #44
    //   4639: ldc 268697664
    //   4641: iastore
    //   4642: dup
    //   4643: bipush #45
    //   4645: ldc 268435456
    //   4647: iastore
    //   4648: dup
    //   4649: bipush #46
    //   4651: ldc 262144
    //   4653: iastore
    //   4654: dup
    //   4655: bipush #47
    //   4657: ldc 268439616
    //   4659: iastore
    //   4660: dup
    //   4661: bipush #48
    //   4663: iconst_0
    //   4664: iastore
    //   4665: dup
    //   4666: bipush #49
    //   4668: ldc 268701760
    //   4670: iastore
    //   4671: dup
    //   4672: bipush #50
    //   4674: ldc 262208
    //   4676: iastore
    //   4677: dup
    //   4678: bipush #51
    //   4680: ldc 268435520
    //   4682: iastore
    //   4683: dup
    //   4684: bipush #52
    //   4686: ldc 268697600
    //   4688: iastore
    //   4689: dup
    //   4690: bipush #53
    //   4692: ldc 268439552
    //   4694: iastore
    //   4695: dup
    //   4696: bipush #54
    //   4698: ldc 268439616
    //   4700: iastore
    //   4701: dup
    //   4702: bipush #55
    //   4704: iconst_0
    //   4705: iastore
    //   4706: dup
    //   4707: bipush #56
    //   4709: ldc 268701760
    //   4711: iastore
    //   4712: dup
    //   4713: bipush #57
    //   4715: ldc 266240
    //   4717: iastore
    //   4718: dup
    //   4719: bipush #58
    //   4721: ldc 266240
    //   4723: iastore
    //   4724: dup
    //   4725: bipush #59
    //   4727: sipush #4160
    //   4730: iastore
    //   4731: dup
    //   4732: bipush #60
    //   4734: sipush #4160
    //   4737: iastore
    //   4738: dup
    //   4739: bipush #61
    //   4741: ldc 262208
    //   4743: iastore
    //   4744: dup
    //   4745: bipush #62
    //   4747: ldc 268435456
    //   4749: iastore
    //   4750: dup
    //   4751: bipush #63
    //   4753: ldc 268701696
    //   4755: iastore
    //   4756: astore #16
    //   4758: aload #4
    //   4760: arraylength
    //   4761: istore #17
    //   4763: iconst_2
    //   4764: newarray int
    //   4766: astore #18
    //   4768: iload #17
    //   4770: newarray byte
    //   4772: astore #5
    //   4774: iload #17
    //   4776: bipush #8
    //   4778: idiv
    //   4779: istore #19
    //   4781: iconst_0
    //   4782: istore #20
    //   4784: iload #20
    //   4786: iload #19
    //   4788: if_icmpge -> 5706
    //   4791: iload #20
    //   4793: bipush #8
    //   4795: imul
    //   4796: istore #21
    //   4798: iconst_0
    //   4799: istore #22
    //   4801: iload #22
    //   4803: iconst_2
    //   4804: if_icmpge -> 4893
    //   4807: aload #18
    //   4809: iload #22
    //   4811: aload #4
    //   4813: iload #21
    //   4815: iload #22
    //   4817: iconst_4
    //   4818: imul
    //   4819: iadd
    //   4820: baload
    //   4821: sipush #255
    //   4824: iand
    //   4825: bipush #24
    //   4827: ishl
    //   4828: aload #4
    //   4830: iload #21
    //   4832: iload #22
    //   4834: iconst_4
    //   4835: imul
    //   4836: iadd
    //   4837: iconst_1
    //   4838: iadd
    //   4839: baload
    //   4840: sipush #255
    //   4843: iand
    //   4844: bipush #16
    //   4846: ishl
    //   4847: ior
    //   4848: aload #4
    //   4850: iload #21
    //   4852: iload #22
    //   4854: iconst_4
    //   4855: imul
    //   4856: iadd
    //   4857: iconst_2
    //   4858: iadd
    //   4859: baload
    //   4860: sipush #255
    //   4863: iand
    //   4864: bipush #8
    //   4866: ishl
    //   4867: ior
    //   4868: aload #4
    //   4870: iload #21
    //   4872: iload #22
    //   4874: iconst_4
    //   4875: imul
    //   4876: iadd
    //   4877: iconst_3
    //   4878: iadd
    //   4879: baload
    //   4880: sipush #255
    //   4883: iand
    //   4884: ior
    //   4885: iastore
    //   4886: iinc #22, 1
    //   4889: iload_2
    //   4890: ifeq -> 4801
    //   4893: iconst_0
    //   4894: istore #27
    //   4896: aload #18
    //   4898: iconst_0
    //   4899: iaload
    //   4900: istore #25
    //   4902: aload #18
    //   4904: iconst_1
    //   4905: iaload
    //   4906: istore #24
    //   4908: iload #25
    //   4910: iconst_4
    //   4911: iushr
    //   4912: iload #24
    //   4914: ixor
    //   4915: ldc 252645135
    //   4917: iand
    //   4918: istore #23
    //   4920: iload #24
    //   4922: iload #23
    //   4924: ixor
    //   4925: istore #24
    //   4927: iload #25
    //   4929: iload #23
    //   4931: iconst_4
    //   4932: ishl
    //   4933: ixor
    //   4934: istore #25
    //   4936: iload #25
    //   4938: bipush #16
    //   4940: iushr
    //   4941: iload #24
    //   4943: ixor
    //   4944: ldc 65535
    //   4946: iand
    //   4947: istore #23
    //   4949: iload #24
    //   4951: iload #23
    //   4953: ixor
    //   4954: istore #24
    //   4956: iload #25
    //   4958: iload #23
    //   4960: bipush #16
    //   4962: ishl
    //   4963: ixor
    //   4964: istore #25
    //   4966: iload #24
    //   4968: iconst_2
    //   4969: iushr
    //   4970: iload #25
    //   4972: ixor
    //   4973: ldc 858993459
    //   4975: iand
    //   4976: istore #23
    //   4978: iload #25
    //   4980: iload #23
    //   4982: ixor
    //   4983: istore #25
    //   4985: iload #24
    //   4987: iload #23
    //   4989: iconst_2
    //   4990: ishl
    //   4991: ixor
    //   4992: istore #24
    //   4994: iload #24
    //   4996: bipush #8
    //   4998: iushr
    //   4999: iload #25
    //   5001: ixor
    //   5002: ldc 16711935
    //   5004: iand
    //   5005: istore #23
    //   5007: iload #25
    //   5009: iload #23
    //   5011: ixor
    //   5012: istore #25
    //   5014: iload #24
    //   5016: iload #23
    //   5018: bipush #8
    //   5020: ishl
    //   5021: ixor
    //   5022: istore #24
    //   5024: iload #24
    //   5026: iconst_1
    //   5027: ishl
    //   5028: iload #24
    //   5030: bipush #31
    //   5032: iushr
    //   5033: iconst_1
    //   5034: iand
    //   5035: ior
    //   5036: istore #24
    //   5038: iload #25
    //   5040: iload #24
    //   5042: ixor
    //   5043: ldc -1431655766
    //   5045: iand
    //   5046: istore #23
    //   5048: iload #25
    //   5050: iload #23
    //   5052: ixor
    //   5053: istore #25
    //   5055: iload #24
    //   5057: iload #23
    //   5059: ixor
    //   5060: istore #24
    //   5062: iload #25
    //   5064: iconst_1
    //   5065: ishl
    //   5066: iload #25
    //   5068: bipush #31
    //   5070: iushr
    //   5071: iconst_1
    //   5072: iand
    //   5073: ior
    //   5074: istore #25
    //   5076: iconst_0
    //   5077: istore #26
    //   5079: iload #26
    //   5081: bipush #8
    //   5083: if_icmpge -> 5421
    //   5086: iload #24
    //   5088: bipush #28
    //   5090: ishl
    //   5091: iload #24
    //   5093: iconst_4
    //   5094: iushr
    //   5095: ior
    //   5096: istore #23
    //   5098: iload #23
    //   5100: aload #6
    //   5102: iload #27
    //   5104: iinc #27, 1
    //   5107: iaload
    //   5108: ixor
    //   5109: istore #23
    //   5111: aload #15
    //   5113: iload #23
    //   5115: bipush #63
    //   5117: iand
    //   5118: iaload
    //   5119: istore #22
    //   5121: iload #22
    //   5123: aload #13
    //   5125: iload #23
    //   5127: bipush #8
    //   5129: iushr
    //   5130: bipush #63
    //   5132: iand
    //   5133: iaload
    //   5134: ior
    //   5135: istore #22
    //   5137: iload #22
    //   5139: aload #11
    //   5141: iload #23
    //   5143: bipush #16
    //   5145: iushr
    //   5146: bipush #63
    //   5148: iand
    //   5149: iaload
    //   5150: ior
    //   5151: istore #22
    //   5153: iload #22
    //   5155: aload #9
    //   5157: iload #23
    //   5159: bipush #24
    //   5161: iushr
    //   5162: bipush #63
    //   5164: iand
    //   5165: iaload
    //   5166: ior
    //   5167: istore #22
    //   5169: iload #24
    //   5171: aload #6
    //   5173: iload #27
    //   5175: iinc #27, 1
    //   5178: iaload
    //   5179: ixor
    //   5180: istore #23
    //   5182: iload #22
    //   5184: aload #16
    //   5186: iload #23
    //   5188: bipush #63
    //   5190: iand
    //   5191: iaload
    //   5192: ior
    //   5193: istore #22
    //   5195: iload #22
    //   5197: aload #14
    //   5199: iload #23
    //   5201: bipush #8
    //   5203: iushr
    //   5204: bipush #63
    //   5206: iand
    //   5207: iaload
    //   5208: ior
    //   5209: istore #22
    //   5211: iload #22
    //   5213: aload #12
    //   5215: iload #23
    //   5217: bipush #16
    //   5219: iushr
    //   5220: bipush #63
    //   5222: iand
    //   5223: iaload
    //   5224: ior
    //   5225: istore #22
    //   5227: iload #22
    //   5229: aload #10
    //   5231: iload #23
    //   5233: bipush #24
    //   5235: iushr
    //   5236: bipush #63
    //   5238: iand
    //   5239: iaload
    //   5240: ior
    //   5241: istore #22
    //   5243: iload #25
    //   5245: iload #22
    //   5247: ixor
    //   5248: istore #25
    //   5250: iload #25
    //   5252: bipush #28
    //   5254: ishl
    //   5255: iload #25
    //   5257: iconst_4
    //   5258: iushr
    //   5259: ior
    //   5260: istore #23
    //   5262: iload #23
    //   5264: aload #6
    //   5266: iload #27
    //   5268: iinc #27, 1
    //   5271: iaload
    //   5272: ixor
    //   5273: istore #23
    //   5275: aload #15
    //   5277: iload #23
    //   5279: bipush #63
    //   5281: iand
    //   5282: iaload
    //   5283: istore #22
    //   5285: iload #22
    //   5287: aload #13
    //   5289: iload #23
    //   5291: bipush #8
    //   5293: iushr
    //   5294: bipush #63
    //   5296: iand
    //   5297: iaload
    //   5298: ior
    //   5299: istore #22
    //   5301: iload #22
    //   5303: aload #11
    //   5305: iload #23
    //   5307: bipush #16
    //   5309: iushr
    //   5310: bipush #63
    //   5312: iand
    //   5313: iaload
    //   5314: ior
    //   5315: istore #22
    //   5317: iload #22
    //   5319: aload #9
    //   5321: iload #23
    //   5323: bipush #24
    //   5325: iushr
    //   5326: bipush #63
    //   5328: iand
    //   5329: iaload
    //   5330: ior
    //   5331: istore #22
    //   5333: iload #25
    //   5335: aload #6
    //   5337: iload #27
    //   5339: iinc #27, 1
    //   5342: iaload
    //   5343: ixor
    //   5344: istore #23
    //   5346: iload #22
    //   5348: aload #16
    //   5350: iload #23
    //   5352: bipush #63
    //   5354: iand
    //   5355: iaload
    //   5356: ior
    //   5357: istore #22
    //   5359: iload #22
    //   5361: aload #14
    //   5363: iload #23
    //   5365: bipush #8
    //   5367: iushr
    //   5368: bipush #63
    //   5370: iand
    //   5371: iaload
    //   5372: ior
    //   5373: istore #22
    //   5375: iload #22
    //   5377: aload #12
    //   5379: iload #23
    //   5381: bipush #16
    //   5383: iushr
    //   5384: bipush #63
    //   5386: iand
    //   5387: iaload
    //   5388: ior
    //   5389: istore #22
    //   5391: iload #22
    //   5393: aload #10
    //   5395: iload #23
    //   5397: bipush #24
    //   5399: iushr
    //   5400: bipush #63
    //   5402: iand
    //   5403: iaload
    //   5404: ior
    //   5405: istore #22
    //   5407: iload #24
    //   5409: iload #22
    //   5411: ixor
    //   5412: istore #24
    //   5414: iinc #26, 1
    //   5417: iload_2
    //   5418: ifeq -> 5079
    //   5421: iload #24
    //   5423: bipush #31
    //   5425: ishl
    //   5426: iload #24
    //   5428: iconst_1
    //   5429: iushr
    //   5430: ior
    //   5431: istore #24
    //   5433: iload #25
    //   5435: iload #24
    //   5437: ixor
    //   5438: ldc -1431655766
    //   5440: iand
    //   5441: istore #23
    //   5443: iload #25
    //   5445: iload #23
    //   5447: ixor
    //   5448: istore #25
    //   5450: iload #24
    //   5452: iload #23
    //   5454: ixor
    //   5455: istore #24
    //   5457: iload #25
    //   5459: bipush #31
    //   5461: ishl
    //   5462: iload #25
    //   5464: iconst_1
    //   5465: iushr
    //   5466: ior
    //   5467: istore #25
    //   5469: iload #25
    //   5471: bipush #8
    //   5473: iushr
    //   5474: iload #24
    //   5476: ixor
    //   5477: ldc 16711935
    //   5479: iand
    //   5480: istore #23
    //   5482: iload #24
    //   5484: iload #23
    //   5486: ixor
    //   5487: istore #24
    //   5489: iload #25
    //   5491: iload #23
    //   5493: bipush #8
    //   5495: ishl
    //   5496: ixor
    //   5497: istore #25
    //   5499: iload #25
    //   5501: iconst_2
    //   5502: iushr
    //   5503: iload #24
    //   5505: ixor
    //   5506: ldc 858993459
    //   5508: iand
    //   5509: istore #23
    //   5511: iload #24
    //   5513: iload #23
    //   5515: ixor
    //   5516: istore #24
    //   5518: iload #25
    //   5520: iload #23
    //   5522: iconst_2
    //   5523: ishl
    //   5524: ixor
    //   5525: istore #25
    //   5527: iload #24
    //   5529: bipush #16
    //   5531: iushr
    //   5532: iload #25
    //   5534: ixor
    //   5535: ldc 65535
    //   5537: iand
    //   5538: istore #23
    //   5540: iload #25
    //   5542: iload #23
    //   5544: ixor
    //   5545: istore #25
    //   5547: iload #24
    //   5549: iload #23
    //   5551: bipush #16
    //   5553: ishl
    //   5554: ixor
    //   5555: istore #24
    //   5557: iload #24
    //   5559: iconst_4
    //   5560: iushr
    //   5561: iload #25
    //   5563: ixor
    //   5564: ldc 252645135
    //   5566: iand
    //   5567: istore #23
    //   5569: iload #25
    //   5571: iload #23
    //   5573: ixor
    //   5574: istore #25
    //   5576: iload #24
    //   5578: iload #23
    //   5580: iconst_4
    //   5581: ishl
    //   5582: ixor
    //   5583: istore #24
    //   5585: aload #18
    //   5587: iconst_0
    //   5588: iload #24
    //   5590: iastore
    //   5591: aload #18
    //   5593: iconst_1
    //   5594: iload #25
    //   5596: iastore
    //   5597: iload #20
    //   5599: bipush #8
    //   5601: imul
    //   5602: istore #28
    //   5604: iconst_0
    //   5605: istore #29
    //   5607: iload #29
    //   5609: iconst_2
    //   5610: if_icmpge -> 5699
    //   5613: aload #5
    //   5615: iload #28
    //   5617: iload #29
    //   5619: iconst_4
    //   5620: imul
    //   5621: iadd
    //   5622: aload #18
    //   5624: iload #29
    //   5626: iaload
    //   5627: bipush #24
    //   5629: iushr
    //   5630: i2b
    //   5631: bastore
    //   5632: aload #5
    //   5634: iload #28
    //   5636: iload #29
    //   5638: iconst_4
    //   5639: imul
    //   5640: iadd
    //   5641: iconst_1
    //   5642: iadd
    //   5643: aload #18
    //   5645: iload #29
    //   5647: iaload
    //   5648: bipush #16
    //   5650: iushr
    //   5651: i2b
    //   5652: bastore
    //   5653: aload #5
    //   5655: iload #28
    //   5657: iload #29
    //   5659: iconst_4
    //   5660: imul
    //   5661: iadd
    //   5662: iconst_2
    //   5663: iadd
    //   5664: aload #18
    //   5666: iload #29
    //   5668: iaload
    //   5669: bipush #8
    //   5671: iushr
    //   5672: i2b
    //   5673: bastore
    //   5674: aload #5
    //   5676: iload #28
    //   5678: iload #29
    //   5680: iconst_4
    //   5681: imul
    //   5682: iadd
    //   5683: iconst_3
    //   5684: iadd
    //   5685: aload #18
    //   5687: iload #29
    //   5689: iaload
    //   5690: i2b
    //   5691: bastore
    //   5692: iinc #29, 1
    //   5695: iload_2
    //   5696: ifeq -> 5607
    //   5699: iinc #20, 1
    //   5702: iload_2
    //   5703: ifeq -> 4784
    //   5706: new java/math/BigInteger
    //   5709: dup
    //   5710: aload #5
    //   5712: invokespecial <init> : ([B)V
    //   5715: invokevirtual abs : ()Ljava/math/BigInteger;
    //   5718: putstatic burp/Zmzh.Zk : Ljava/lang/Object;
    //   5721: sipush #-9033
    //   5724: sipush #-21207
    //   5727: invokestatic a : (II)Ljava/lang/String;
    //   5730: iconst_1
    //   5731: ldc burp/Zl1u
    //   5733: invokevirtual getClassLoader : ()Ljava/lang/ClassLoader;
    //   5736: invokestatic forName : (Ljava/lang/String;ZLjava/lang/ClassLoader;)Ljava/lang/Class;
    //   5739: invokevirtual getDeclaredFields : ()[Ljava/lang/reflect/Field;
    //   5742: astore #4
    //   5744: aload #4
    //   5746: arraylength
    //   5747: istore #5
    //   5749: iconst_0
    //   5750: istore #6
    //   5752: iload #6
    //   5754: iload #5
    //   5756: if_icmpge -> 5894
    //   5759: aload #4
    //   5761: iload #6
    //   5763: aaload
    //   5764: astore #7
    //   5766: aload #7
    //   5768: invokevirtual getModifiers : ()I
    //   5771: invokestatic isStatic : (I)Z
    //   5774: ifne -> 5784
    //   5777: goto -> 5887
    //   5780: invokestatic a : (Ljava/lang/Throwable;)Ljava/lang/Throwable;
    //   5783: athrow
    //   5784: aload #7
    //   5786: invokevirtual getType : ()Ljava/lang/Class;
    //   5789: astore #8
    //   5791: aload #8
    //   5793: ifnull -> 5874
    //   5796: aload #8
    //   5798: invokevirtual isPrimitive : ()Z
    //   5801: ifne -> 5874
    //   5804: goto -> 5811
    //   5807: invokestatic a : (Ljava/lang/Throwable;)Ljava/lang/Throwable;
    //   5810: athrow
    //   5811: aload #8
    //   5813: invokevirtual getPackage : ()Ljava/lang/Package;
    //   5816: ifnull -> 5874
    //   5819: goto -> 5826
    //   5822: invokestatic a : (Ljava/lang/Throwable;)Ljava/lang/Throwable;
    //   5825: athrow
    //   5826: aload #8
    //   5828: invokevirtual getPackage : ()Ljava/lang/Package;
    //   5831: invokevirtual getName : ()Ljava/lang/String;
    //   5834: ifnull -> 5874
    //   5837: goto -> 5844
    //   5840: invokestatic a : (Ljava/lang/Throwable;)Ljava/lang/Throwable;
    //   5843: athrow
    //   5844: aload #8
    //   5846: invokevirtual getPackage : ()Ljava/lang/Package;
    //   5849: invokevirtual getName : ()Ljava/lang/String;
    //   5852: sipush #-9048
    //   5855: sipush #-11925
    //   5858: invokestatic a : (II)Ljava/lang/String;
    //   5861: invokevirtual startsWith : (Ljava/lang/String;)Z
    //   5864: ifne -> 5874
    //   5867: goto -> 5874
    //   5870: invokestatic a : (Ljava/lang/Throwable;)Ljava/lang/Throwable;
    //   5873: athrow
    //   5874: aload #7
    //   5876: iconst_1
    //   5877: invokevirtual setAccessible : (Z)V
    //   5880: aload #7
    //   5882: aconst_null
    //   5883: invokevirtual get : (Ljava/lang/Object;)Ljava/lang/Object;
    //   5886: pop
    //   5887: iinc #6, 1
    //   5890: iload_2
    //   5891: ifeq -> 5752
    //   5894: sipush #-9055
    //   5897: sipush #4965
    //   5900: invokestatic a : (II)Ljava/lang/String;
    //   5903: invokestatic forName : (Ljava/lang/String;)Ljava/lang/Class;
    //   5906: invokevirtual getDeclaredMethods : ()[Ljava/lang/reflect/Method;
    //   5909: astore #4
    //   5911: aload #4
    //   5913: arraylength
    //   5914: istore #5
    //   5916: iconst_0
    //   5917: istore #6
    //   5919: iload #6
    //   5921: iload #5
    //   5923: if_icmpge -> 6053
    //   5926: aload #4
    //   5928: iload #6
    //   5930: aaload
    //   5931: astore #7
    //   5933: aload #7
    //   5935: invokevirtual getParameterTypes : ()[Ljava/lang/Class;
    //   5938: pop
    //   5939: aload #7
    //   5941: invokevirtual getModifiers : ()I
    //   5944: invokestatic isStatic : (I)Z
    //   5947: ifeq -> 6039
    //   5950: aload #7
    //   5952: invokevirtual getParameterTypes : ()[Ljava/lang/Class;
    //   5955: arraylength
    //   5956: iconst_2
    //   5957: if_icmpne -> 6039
    //   5960: goto -> 5967
    //   5963: invokestatic a : (Ljava/lang/Throwable;)Ljava/lang/Throwable;
    //   5966: athrow
    //   5967: aload #7
    //   5969: invokevirtual getReturnType : ()Ljava/lang/Class;
    //   5972: getstatic java/lang/Boolean.TYPE : Ljava/lang/Class;
    //   5975: if_acmpne -> 6039
    //   5978: goto -> 5985
    //   5981: invokestatic a : (Ljava/lang/Throwable;)Ljava/lang/Throwable;
    //   5984: athrow
    //   5985: aload #7
    //   5987: iconst_1
    //   5988: invokevirtual setAccessible : (Z)V
    //   5991: aload #7
    //   5993: aconst_null
    //   5994: iconst_2
    //   5995: anewarray java/lang/Object
    //   5998: dup
    //   5999: iconst_0
    //   6000: aload_0
    //   6001: aastore
    //   6002: dup
    //   6003: iconst_1
    //   6004: aload_1
    //   6005: ifnonnull -> 6023
    //   6008: goto -> 6015
    //   6011: invokestatic a : (Ljava/lang/Throwable;)Ljava/lang/Throwable;
    //   6014: athrow
    //   6015: aload_1
    //   6016: goto -> 6030
    //   6019: invokestatic a : (Ljava/lang/Throwable;)Ljava/lang/Throwable;
    //   6022: athrow
    //   6023: aload_1
    //   6024: checkcast [B
    //   6027: invokevirtual clone : ()Ljava/lang/Object;
    //   6030: aastore
    //   6031: invokevirtual invoke : (Ljava/lang/Object;[Ljava/lang/Object;)Ljava/lang/Object;
    //   6034: pop
    //   6035: iload_2
    //   6036: ifeq -> 6053
    //   6039: iinc #6, 1
    //   6042: iload_2
    //   6043: ifeq -> 5919
    //   6046: goto -> 6053
    //   6049: invokestatic a : (Ljava/lang/Throwable;)Ljava/lang/Throwable;
    //   6052: athrow
    //   6053: sipush #-9056
    //   6056: sipush #-24823
    //   6059: invokestatic a : (II)Ljava/lang/String;
    //   6062: iconst_1
    //   6063: ldc burp/Zm1l
    //   6065: invokevirtual getClassLoader : ()Ljava/lang/ClassLoader;
    //   6068: invokestatic forName : (Ljava/lang/String;ZLjava/lang/ClassLoader;)Ljava/lang/Class;
    //   6071: invokevirtual getDeclaredFields : ()[Ljava/lang/reflect/Field;
    //   6074: astore #4
    //   6076: aload #4
    //   6078: arraylength
    //   6079: istore #5
    //   6081: iconst_0
    //   6082: istore #6
    //   6084: iload #6
    //   6086: iload #5
    //   6088: if_icmpge -> 6226
    //   6091: aload #4
    //   6093: iload #6
    //   6095: aaload
    //   6096: astore #7
    //   6098: aload #7
    //   6100: invokevirtual getModifiers : ()I
    //   6103: invokestatic isStatic : (I)Z
    //   6106: ifne -> 6116
    //   6109: goto -> 6219
    //   6112: invokestatic a : (Ljava/lang/Throwable;)Ljava/lang/Throwable;
    //   6115: athrow
    //   6116: aload #7
    //   6118: invokevirtual getType : ()Ljava/lang/Class;
    //   6121: astore #8
    //   6123: aload #8
    //   6125: ifnull -> 6206
    //   6128: aload #8
    //   6130: invokevirtual isPrimitive : ()Z
    //   6133: ifne -> 6206
    //   6136: goto -> 6143
    //   6139: invokestatic a : (Ljava/lang/Throwable;)Ljava/lang/Throwable;
    //   6142: athrow
    //   6143: aload #8
    //   6145: invokevirtual getPackage : ()Ljava/lang/Package;
    //   6148: ifnull -> 6206
    //   6151: goto -> 6158
    //   6154: invokestatic a : (Ljava/lang/Throwable;)Ljava/lang/Throwable;
    //   6157: athrow
    //   6158: aload #8
    //   6160: invokevirtual getPackage : ()Ljava/lang/Package;
    //   6163: invokevirtual getName : ()Ljava/lang/String;
    //   6166: ifnull -> 6206
    //   6169: goto -> 6176
    //   6172: invokestatic a : (Ljava/lang/Throwable;)Ljava/lang/Throwable;
    //   6175: athrow
    //   6176: aload #8
    //   6178: invokevirtual getPackage : ()Ljava/lang/Package;
    //   6181: invokevirtual getName : ()Ljava/lang/String;
    //   6184: sipush #-9041
    //   6187: sipush #11557
    //   6190: invokestatic a : (II)Ljava/lang/String;
    //   6193: invokevirtual startsWith : (Ljava/lang/String;)Z
    //   6196: ifne -> 6206
    //   6199: goto -> 6206
    //   6202: invokestatic a : (Ljava/lang/Throwable;)Ljava/lang/Throwable;
    //   6205: athrow
    //   6206: aload #7
    //   6208: iconst_1
    //   6209: invokevirtual setAccessible : (Z)V
    //   6212: aload #7
    //   6214: aconst_null
    //   6215: invokevirtual get : (Ljava/lang/Object;)Ljava/lang/Object;
    //   6218: pop
    //   6219: iinc #6, 1
    //   6222: iload_2
    //   6223: ifeq -> 6084
    //   6226: sipush #-9025
    //   6229: sipush #23557
    //   6232: invokestatic a : (II)Ljava/lang/String;
    //   6235: invokestatic forName : (Ljava/lang/String;)Ljava/lang/Class;
    //   6238: invokevirtual getDeclaredMethods : ()[Ljava/lang/reflect/Method;
    //   6241: astore #4
    //   6243: aload #4
    //   6245: arraylength
    //   6246: istore #5
    //   6248: iconst_0
    //   6249: istore #6
    //   6251: iload #6
    //   6253: iload #5
    //   6255: if_icmpge -> 6388
    //   6258: aload #4
    //   6260: iload #6
    //   6262: aaload
    //   6263: astore #7
    //   6265: aload #7
    //   6267: invokevirtual getParameterTypes : ()[Ljava/lang/Class;
    //   6270: pop
    //   6271: aload #7
    //   6273: invokevirtual getModifiers : ()I
    //   6276: invokestatic isStatic : (I)Z
    //   6279: ifeq -> 6374
    //   6282: aload #7
    //   6284: invokevirtual getParameterTypes : ()[Ljava/lang/Class;
    //   6287: arraylength
    //   6288: iconst_2
    //   6289: if_icmpne -> 6374
    //   6292: goto -> 6299
    //   6295: invokestatic a : (Ljava/lang/Throwable;)Ljava/lang/Throwable;
    //   6298: athrow
    //   6299: aload #7
    //   6301: invokevirtual getReturnType : ()Ljava/lang/Class;
    //   6304: getstatic java/lang/Void.TYPE : Ljava/lang/Class;
    //   6307: invokevirtual equals : (Ljava/lang/Object;)Z
    //   6310: ifeq -> 6374
    //   6313: goto -> 6320
    //   6316: invokestatic a : (Ljava/lang/Throwable;)Ljava/lang/Throwable;
    //   6319: athrow
    //   6320: aload #7
    //   6322: iconst_1
    //   6323: invokevirtual setAccessible : (Z)V
    //   6326: aload #7
    //   6328: aconst_null
    //   6329: iconst_2
    //   6330: anewarray java/lang/Object
    //   6333: dup
    //   6334: iconst_0
    //   6335: aload_0
    //   6336: aastore
    //   6337: dup
    //   6338: iconst_1
    //   6339: aload_1
    //   6340: ifnonnull -> 6358
    //   6343: goto -> 6350
    //   6346: invokestatic a : (Ljava/lang/Throwable;)Ljava/lang/Throwable;
    //   6349: athrow
    //   6350: aload_1
    //   6351: goto -> 6365
    //   6354: invokestatic a : (Ljava/lang/Throwable;)Ljava/lang/Throwable;
    //   6357: athrow
    //   6358: aload_1
    //   6359: checkcast [B
    //   6362: invokevirtual clone : ()Ljava/lang/Object;
    //   6365: aastore
    //   6366: invokevirtual invoke : (Ljava/lang/Object;[Ljava/lang/Object;)Ljava/lang/Object;
    //   6369: pop
    //   6370: iload_2
    //   6371: ifeq -> 6388
    //   6374: iinc #6, 1
    //   6377: iload_2
    //   6378: ifeq -> 6251
    //   6381: goto -> 6388
    //   6384: invokestatic a : (Ljava/lang/Throwable;)Ljava/lang/Throwable;
    //   6387: athrow
    //   6388: iconst_0
    //   6389: istore #4
    //   6391: getstatic burp/Zx8t.Zi : Ljava/lang/String;
    //   6394: getstatic burp/Zefm.ZP : Ljava/lang/Object;
    //   6397: checkcast java/math/BigInteger
    //   6400: invokevirtual intValue : ()I
    //   6403: bipush #32
    //   6405: irem
    //   6406: invokestatic abs : (I)I
    //   6409: invokevirtual charAt : (I)C
    //   6412: getstatic burp/Zl8y.ZY : Ljava/lang/String;
    //   6415: getstatic burp/Zgta.ZF : Ljava/lang/Object;
    //   6418: checkcast java/math/BigInteger
    //   6421: invokevirtual intValue : ()I
    //   6424: bipush #32
    //   6426: irem
    //   6427: invokestatic abs : (I)I
    //   6430: invokevirtual charAt : (I)C
    //   6433: if_icmpgt -> 6778
    //   6436: sipush #-9046
    //   6439: sipush #-16670
    //   6442: invokestatic a : (II)Ljava/lang/String;
    //   6445: iconst_1
    //   6446: ldc burp/Zb8x
    //   6448: invokevirtual getClassLoader : ()Ljava/lang/ClassLoader;
    //   6451: invokestatic forName : (Ljava/lang/String;ZLjava/lang/ClassLoader;)Ljava/lang/Class;
    //   6454: invokevirtual getDeclaredFields : ()[Ljava/lang/reflect/Field;
    //   6457: astore #5
    //   6459: aload #5
    //   6461: arraylength
    //   6462: istore #6
    //   6464: iconst_0
    //   6465: istore #7
    //   6467: iload #7
    //   6469: iload #6
    //   6471: if_icmpge -> 6609
    //   6474: aload #5
    //   6476: iload #7
    //   6478: aaload
    //   6479: astore #8
    //   6481: aload #8
    //   6483: invokevirtual getModifiers : ()I
    //   6486: invokestatic isStatic : (I)Z
    //   6489: ifne -> 6499
    //   6492: goto -> 6602
    //   6495: invokestatic a : (Ljava/lang/Throwable;)Ljava/lang/Throwable;
    //   6498: athrow
    //   6499: aload #8
    //   6501: invokevirtual getType : ()Ljava/lang/Class;
    //   6504: astore #9
    //   6506: aload #9
    //   6508: ifnull -> 6589
    //   6511: aload #9
    //   6513: invokevirtual isPrimitive : ()Z
    //   6516: ifne -> 6589
    //   6519: goto -> 6526
    //   6522: invokestatic a : (Ljava/lang/Throwable;)Ljava/lang/Throwable;
    //   6525: athrow
    //   6526: aload #9
    //   6528: invokevirtual getPackage : ()Ljava/lang/Package;
    //   6531: ifnull -> 6589
    //   6534: goto -> 6541
    //   6537: invokestatic a : (Ljava/lang/Throwable;)Ljava/lang/Throwable;
    //   6540: athrow
    //   6541: aload #9
    //   6543: invokevirtual getPackage : ()Ljava/lang/Package;
    //   6546: invokevirtual getName : ()Ljava/lang/String;
    //   6549: ifnull -> 6589
    //   6552: goto -> 6559
    //   6555: invokestatic a : (Ljava/lang/Throwable;)Ljava/lang/Throwable;
    //   6558: athrow
    //   6559: aload #9
    //   6561: invokevirtual getPackage : ()Ljava/lang/Package;
    //   6564: invokevirtual getName : ()Ljava/lang/String;
    //   6567: sipush #-9041
    //   6570: sipush #11557
    //   6573: invokestatic a : (II)Ljava/lang/String;
    //   6576: invokevirtual startsWith : (Ljava/lang/String;)Z
    //   6579: ifne -> 6589
    //   6582: goto -> 6589
    //   6585: invokestatic a : (Ljava/lang/Throwable;)Ljava/lang/Throwable;
    //   6588: athrow
    //   6589: aload #8
    //   6591: iconst_1
    //   6592: invokevirtual setAccessible : (Z)V
    //   6595: aload #8
    //   6597: aconst_null
    //   6598: invokevirtual get : (Ljava/lang/Object;)Ljava/lang/Object;
    //   6601: pop
    //   6602: iinc #7, 1
    //   6605: iload_2
    //   6606: ifeq -> 6467
    //   6609: sipush #-9042
    //   6612: sipush #-27321
    //   6615: invokestatic a : (II)Ljava/lang/String;
    //   6618: invokestatic forName : (Ljava/lang/String;)Ljava/lang/Class;
    //   6621: invokevirtual getDeclaredMethods : ()[Ljava/lang/reflect/Method;
    //   6624: astore #5
    //   6626: aload #5
    //   6628: arraylength
    //   6629: istore #6
    //   6631: iconst_0
    //   6632: istore #7
    //   6634: iload #7
    //   6636: iload #6
    //   6638: if_icmpge -> 6775
    //   6641: aload #5
    //   6643: iload #7
    //   6645: aaload
    //   6646: astore #8
    //   6648: aload #8
    //   6650: invokevirtual getParameterTypes : ()[Ljava/lang/Class;
    //   6653: pop
    //   6654: aload #8
    //   6656: invokevirtual getModifiers : ()I
    //   6659: invokestatic isStatic : (I)Z
    //   6662: ifeq -> 6761
    //   6665: aload #8
    //   6667: invokevirtual getParameterTypes : ()[Ljava/lang/Class;
    //   6670: arraylength
    //   6671: iconst_2
    //   6672: if_icmpne -> 6761
    //   6675: goto -> 6682
    //   6678: invokestatic a : (Ljava/lang/Throwable;)Ljava/lang/Throwable;
    //   6681: athrow
    //   6682: aload #8
    //   6684: invokevirtual getReturnType : ()Ljava/lang/Class;
    //   6687: getstatic java/lang/Boolean.TYPE : Ljava/lang/Class;
    //   6690: if_acmpne -> 6761
    //   6693: goto -> 6700
    //   6696: invokestatic a : (Ljava/lang/Throwable;)Ljava/lang/Throwable;
    //   6699: athrow
    //   6700: aload #8
    //   6702: iconst_1
    //   6703: invokevirtual setAccessible : (Z)V
    //   6706: aload #8
    //   6708: aconst_null
    //   6709: iconst_2
    //   6710: anewarray java/lang/Object
    //   6713: dup
    //   6714: iconst_0
    //   6715: aload_0
    //   6716: aastore
    //   6717: dup
    //   6718: iconst_1
    //   6719: aload_1
    //   6720: ifnonnull -> 6738
    //   6723: goto -> 6730
    //   6726: invokestatic a : (Ljava/lang/Throwable;)Ljava/lang/Throwable;
    //   6729: athrow
    //   6730: aload_1
    //   6731: goto -> 6745
    //   6734: invokestatic a : (Ljava/lang/Throwable;)Ljava/lang/Throwable;
    //   6737: athrow
    //   6738: aload_1
    //   6739: checkcast [B
    //   6742: invokevirtual clone : ()Ljava/lang/Object;
    //   6745: aastore
    //   6746: invokevirtual invoke : (Ljava/lang/Object;[Ljava/lang/Object;)Ljava/lang/Object;
    //   6749: checkcast java/lang/Boolean
    //   6752: invokevirtual booleanValue : ()Z
    //   6755: istore #4
    //   6757: iload_2
    //   6758: ifeq -> 6775
    //   6761: iinc #7, 1
    //   6764: iload_2
    //   6765: ifeq -> 6634
    //   6768: goto -> 6775
    //   6771: invokestatic a : (Ljava/lang/Throwable;)Ljava/lang/Throwable;
    //   6774: athrow
    //   6775: goto -> 7117
    //   6778: sipush #-9040
    //   6781: sipush #-29294
    //   6784: invokestatic a : (II)Ljava/lang/String;
    //   6787: iconst_1
    //   6788: ldc burp/Zt7w
    //   6790: invokevirtual getClassLoader : ()Ljava/lang/ClassLoader;
    //   6793: invokestatic forName : (Ljava/lang/String;ZLjava/lang/ClassLoader;)Ljava/lang/Class;
    //   6796: invokevirtual getDeclaredFields : ()[Ljava/lang/reflect/Field;
    //   6799: astore #5
    //   6801: aload #5
    //   6803: arraylength
    //   6804: istore #6
    //   6806: iconst_0
    //   6807: istore #7
    //   6809: iload #7
    //   6811: iload #6
    //   6813: if_icmpge -> 6951
    //   6816: aload #5
    //   6818: iload #7
    //   6820: aaload
    //   6821: astore #8
    //   6823: aload #8
    //   6825: invokevirtual getModifiers : ()I
    //   6828: invokestatic isStatic : (I)Z
    //   6831: ifne -> 6841
    //   6834: goto -> 6944
    //   6837: invokestatic a : (Ljava/lang/Throwable;)Ljava/lang/Throwable;
    //   6840: athrow
    //   6841: aload #8
    //   6843: invokevirtual getType : ()Ljava/lang/Class;
    //   6846: astore #9
    //   6848: aload #9
    //   6850: ifnull -> 6931
    //   6853: aload #9
    //   6855: invokevirtual isPrimitive : ()Z
    //   6858: ifne -> 6931
    //   6861: goto -> 6868
    //   6864: invokestatic a : (Ljava/lang/Throwable;)Ljava/lang/Throwable;
    //   6867: athrow
    //   6868: aload #9
    //   6870: invokevirtual getPackage : ()Ljava/lang/Package;
    //   6873: ifnull -> 6931
    //   6876: goto -> 6883
    //   6879: invokestatic a : (Ljava/lang/Throwable;)Ljava/lang/Throwable;
    //   6882: athrow
    //   6883: aload #9
    //   6885: invokevirtual getPackage : ()Ljava/lang/Package;
    //   6888: invokevirtual getName : ()Ljava/lang/String;
    //   6891: ifnull -> 6931
    //   6894: goto -> 6901
    //   6897: invokestatic a : (Ljava/lang/Throwable;)Ljava/lang/Throwable;
    //   6900: athrow
    //   6901: aload #9
    //   6903: invokevirtual getPackage : ()Ljava/lang/Package;
    //   6906: invokevirtual getName : ()Ljava/lang/String;
    //   6909: sipush #-9041
    //   6912: sipush #11557
    //   6915: invokestatic a : (II)Ljava/lang/String;
    //   6918: invokevirtual startsWith : (Ljava/lang/String;)Z
    //   6921: ifne -> 6931
    //   6924: goto -> 6931
    //   6927: invokestatic a : (Ljava/lang/Throwable;)Ljava/lang/Throwable;
    //   6930: athrow
    //   6931: aload #8
    //   6933: iconst_1
    //   6934: invokevirtual setAccessible : (Z)V
    //   6937: aload #8
    //   6939: aconst_null
    //   6940: invokevirtual get : (Ljava/lang/Object;)Ljava/lang/Object;
    //   6943: pop
    //   6944: iinc #7, 1
    //   6947: iload_2
    //   6948: ifeq -> 6809
    //   6951: sipush #-9039
    //   6954: sipush #-22145
    //   6957: invokestatic a : (II)Ljava/lang/String;
    //   6960: invokestatic forName : (Ljava/lang/String;)Ljava/lang/Class;
    //   6963: invokevirtual getDeclaredMethods : ()[Ljava/lang/reflect/Method;
    //   6966: astore #5
    //   6968: aload #5
    //   6970: arraylength
    //   6971: istore #6
    //   6973: iconst_0
    //   6974: istore #7
    //   6976: iload #7
    //   6978: iload #6
    //   6980: if_icmpge -> 7117
    //   6983: aload #5
    //   6985: iload #7
    //   6987: aaload
    //   6988: astore #8
    //   6990: aload #8
    //   6992: invokevirtual getParameterTypes : ()[Ljava/lang/Class;
    //   6995: pop
    //   6996: aload #8
    //   6998: invokevirtual getModifiers : ()I
    //   7001: invokestatic isStatic : (I)Z
    //   7004: ifeq -> 7103
    //   7007: aload #8
    //   7009: invokevirtual getParameterTypes : ()[Ljava/lang/Class;
    //   7012: arraylength
    //   7013: iconst_2
    //   7014: if_icmpne -> 7103
    //   7017: goto -> 7024
    //   7020: invokestatic a : (Ljava/lang/Throwable;)Ljava/lang/Throwable;
    //   7023: athrow
    //   7024: aload #8
    //   7026: invokevirtual getReturnType : ()Ljava/lang/Class;
    //   7029: getstatic java/lang/Boolean.TYPE : Ljava/lang/Class;
    //   7032: if_acmpne -> 7103
    //   7035: goto -> 7042
    //   7038: invokestatic a : (Ljava/lang/Throwable;)Ljava/lang/Throwable;
    //   7041: athrow
    //   7042: aload #8
    //   7044: iconst_1
    //   7045: invokevirtual setAccessible : (Z)V
    //   7048: aload #8
    //   7050: aconst_null
    //   7051: iconst_2
    //   7052: anewarray java/lang/Object
    //   7055: dup
    //   7056: iconst_0
    //   7057: aload_0
    //   7058: aastore
    //   7059: dup
    //   7060: iconst_1
    //   7061: aload_1
    //   7062: ifnonnull -> 7080
    //   7065: goto -> 7072
    //   7068: invokestatic a : (Ljava/lang/Throwable;)Ljava/lang/Throwable;
    //   7071: athrow
    //   7072: aload_1
    //   7073: goto -> 7087
    //   7076: invokestatic a : (Ljava/lang/Throwable;)Ljava/lang/Throwable;
    //   7079: athrow
    //   7080: aload_1
    //   7081: checkcast [B
    //   7084: invokevirtual clone : ()Ljava/lang/Object;
    //   7087: aastore
    //   7088: invokevirtual invoke : (Ljava/lang/Object;[Ljava/lang/Object;)Ljava/lang/Object;
    //   7091: checkcast java/lang/Boolean
    //   7094: invokevirtual booleanValue : ()Z
    //   7097: istore #4
    //   7099: iload_2
    //   7100: ifeq -> 7117
    //   7103: iinc #7, 1
    //   7106: iload_2
    //   7107: ifeq -> 6976
    //   7110: goto -> 7117
    //   7113: invokestatic a : (Ljava/lang/Throwable;)Ljava/lang/Throwable;
    //   7116: athrow
    //   7117: iload #4
    //   7119: ifeq -> 7125
    //   7122: iload #4
    //   7124: ireturn
    //   7125: getstatic burp/Zr9b.ZC : Ljava/lang/String;
    //   7128: getstatic burp/Zr5k.Zj : Ljava/lang/Object;
    //   7131: checkcast java/math/BigInteger
    //   7134: invokevirtual intValue : ()I
    //   7137: bipush #32
    //   7139: irem
    //   7140: invokestatic abs : (I)I
    //   7143: invokevirtual charAt : (I)C
    //   7146: getstatic burp/Zzok.ZC : Ljava/lang/String;
    //   7149: getstatic burp/Zmt7.Z_ : Ljava/lang/Object;
    //   7152: checkcast java/math/BigInteger
    //   7155: invokevirtual intValue : ()I
    //   7158: bipush #32
    //   7160: irem
    //   7161: invokestatic abs : (I)I
    //   7164: invokevirtual charAt : (I)C
    //   7167: if_icmple -> 7513
    //   7170: sipush #-9035
    //   7173: sipush #32454
    //   7176: invokestatic a : (II)Ljava/lang/String;
    //   7179: iconst_1
    //   7180: ldc burp/Zrnu
    //   7182: invokevirtual getClassLoader : ()Ljava/lang/ClassLoader;
    //   7185: invokestatic forName : (Ljava/lang/String;ZLjava/lang/ClassLoader;)Ljava/lang/Class;
    //   7188: invokevirtual getDeclaredFields : ()[Ljava/lang/reflect/Field;
    //   7191: astore #5
    //   7193: aload #5
    //   7195: arraylength
    //   7196: istore #6
    //   7198: iconst_0
    //   7199: istore #7
    //   7201: iload #7
    //   7203: iload #6
    //   7205: if_icmpge -> 7343
    //   7208: aload #5
    //   7210: iload #7
    //   7212: aaload
    //   7213: astore #8
    //   7215: aload #8
    //   7217: invokevirtual getModifiers : ()I
    //   7220: invokestatic isStatic : (I)Z
    //   7223: ifne -> 7233
    //   7226: goto -> 7336
    //   7229: invokestatic a : (Ljava/lang/Throwable;)Ljava/lang/Throwable;
    //   7232: athrow
    //   7233: aload #8
    //   7235: invokevirtual getType : ()Ljava/lang/Class;
    //   7238: astore #9
    //   7240: aload #9
    //   7242: ifnull -> 7323
    //   7245: aload #9
    //   7247: invokevirtual isPrimitive : ()Z
    //   7250: ifne -> 7323
    //   7253: goto -> 7260
    //   7256: invokestatic a : (Ljava/lang/Throwable;)Ljava/lang/Throwable;
    //   7259: athrow
    //   7260: aload #9
    //   7262: invokevirtual getPackage : ()Ljava/lang/Package;
    //   7265: ifnull -> 7323
    //   7268: goto -> 7275
    //   7271: invokestatic a : (Ljava/lang/Throwable;)Ljava/lang/Throwable;
    //   7274: athrow
    //   7275: aload #9
    //   7277: invokevirtual getPackage : ()Ljava/lang/Package;
    //   7280: invokevirtual getName : ()Ljava/lang/String;
    //   7283: ifnull -> 7323
    //   7286: goto -> 7293
    //   7289: invokestatic a : (Ljava/lang/Throwable;)Ljava/lang/Throwable;
    //   7292: athrow
    //   7293: aload #9
    //   7295: invokevirtual getPackage : ()Ljava/lang/Package;
    //   7298: invokevirtual getName : ()Ljava/lang/String;
    //   7301: sipush #-9041
    //   7304: sipush #11557
    //   7307: invokestatic a : (II)Ljava/lang/String;
    //   7310: invokevirtual startsWith : (Ljava/lang/String;)Z
    //   7313: ifne -> 7323
    //   7316: goto -> 7323
    //   7319: invokestatic a : (Ljava/lang/Throwable;)Ljava/lang/Throwable;
    //   7322: athrow
    //   7323: aload #8
    //   7325: iconst_1
    //   7326: invokevirtual setAccessible : (Z)V
    //   7329: aload #8
    //   7331: aconst_null
    //   7332: invokevirtual get : (Ljava/lang/Object;)Ljava/lang/Object;
    //   7335: pop
    //   7336: iinc #7, 1
    //   7339: iload_2
    //   7340: ifeq -> 7201
    //   7343: sipush #-9047
    //   7346: sipush #24480
    //   7349: invokestatic a : (II)Ljava/lang/String;
    //   7352: invokestatic forName : (Ljava/lang/String;)Ljava/lang/Class;
    //   7355: invokevirtual getDeclaredMethods : ()[Ljava/lang/reflect/Method;
    //   7358: astore #5
    //   7360: aload #5
    //   7362: arraylength
    //   7363: istore #6
    //   7365: iconst_0
    //   7366: istore #7
    //   7368: iload #7
    //   7370: iload #6
    //   7372: if_icmpge -> 7509
    //   7375: aload #5
    //   7377: iload #7
    //   7379: aaload
    //   7380: astore #8
    //   7382: aload #8
    //   7384: invokevirtual getParameterTypes : ()[Ljava/lang/Class;
    //   7387: pop
    //   7388: aload #8
    //   7390: invokevirtual getModifiers : ()I
    //   7393: invokestatic isStatic : (I)Z
    //   7396: ifeq -> 7495
    //   7399: aload #8
    //   7401: invokevirtual getParameterTypes : ()[Ljava/lang/Class;
    //   7404: arraylength
    //   7405: iconst_2
    //   7406: if_icmpne -> 7495
    //   7409: goto -> 7416
    //   7412: invokestatic a : (Ljava/lang/Throwable;)Ljava/lang/Throwable;
    //   7415: athrow
    //   7416: aload #8
    //   7418: invokevirtual getReturnType : ()Ljava/lang/Class;
    //   7421: getstatic java/lang/Boolean.TYPE : Ljava/lang/Class;
    //   7424: if_acmpne -> 7495
    //   7427: goto -> 7434
    //   7430: invokestatic a : (Ljava/lang/Throwable;)Ljava/lang/Throwable;
    //   7433: athrow
    //   7434: aload #8
    //   7436: iconst_1
    //   7437: invokevirtual setAccessible : (Z)V
    //   7440: aload #8
    //   7442: aconst_null
    //   7443: iconst_2
    //   7444: anewarray java/lang/Object
    //   7447: dup
    //   7448: iconst_0
    //   7449: aload_0
    //   7450: aastore
    //   7451: dup
    //   7452: iconst_1
    //   7453: aload_1
    //   7454: ifnonnull -> 7472
    //   7457: goto -> 7464
    //   7460: invokestatic a : (Ljava/lang/Throwable;)Ljava/lang/Throwable;
    //   7463: athrow
    //   7464: aload_1
    //   7465: goto -> 7479
    //   7468: invokestatic a : (Ljava/lang/Throwable;)Ljava/lang/Throwable;
    //   7471: athrow
    //   7472: aload_1
    //   7473: checkcast [B
    //   7476: invokevirtual clone : ()Ljava/lang/Object;
    //   7479: aastore
    //   7480: invokevirtual invoke : (Ljava/lang/Object;[Ljava/lang/Object;)Ljava/lang/Object;
    //   7483: checkcast java/lang/Boolean
    //   7486: invokevirtual booleanValue : ()Z
    //   7489: istore #4
    //   7491: iload_2
    //   7492: ifeq -> 7509
    //   7495: iinc #7, 1
    //   7498: iload_2
    //   7499: ifeq -> 7368
    //   7502: goto -> 7509
    //   7505: invokestatic a : (Ljava/lang/Throwable;)Ljava/lang/Throwable;
    //   7508: athrow
    //   7509: iload_2
    //   7510: ifeq -> 7852
    //   7513: sipush #-9045
    //   7516: sipush #-28595
    //   7519: invokestatic a : (II)Ljava/lang/String;
    //   7522: iconst_1
    //   7523: ldc burp/Zgly
    //   7525: invokevirtual getClassLoader : ()Ljava/lang/ClassLoader;
    //   7528: invokestatic forName : (Ljava/lang/String;ZLjava/lang/ClassLoader;)Ljava/lang/Class;
    //   7531: invokevirtual getDeclaredFields : ()[Ljava/lang/reflect/Field;
    //   7534: astore #5
    //   7536: aload #5
    //   7538: arraylength
    //   7539: istore #6
    //   7541: iconst_0
    //   7542: istore #7
    //   7544: iload #7
    //   7546: iload #6
    //   7548: if_icmpge -> 7686
    //   7551: aload #5
    //   7553: iload #7
    //   7555: aaload
    //   7556: astore #8
    //   7558: aload #8
    //   7560: invokevirtual getModifiers : ()I
    //   7563: invokestatic isStatic : (I)Z
    //   7566: ifne -> 7576
    //   7569: goto -> 7679
    //   7572: invokestatic a : (Ljava/lang/Throwable;)Ljava/lang/Throwable;
    //   7575: athrow
    //   7576: aload #8
    //   7578: invokevirtual getType : ()Ljava/lang/Class;
    //   7581: astore #9
    //   7583: aload #9
    //   7585: ifnull -> 7666
    //   7588: aload #9
    //   7590: invokevirtual isPrimitive : ()Z
    //   7593: ifne -> 7666
    //   7596: goto -> 7603
    //   7599: invokestatic a : (Ljava/lang/Throwable;)Ljava/lang/Throwable;
    //   7602: athrow
    //   7603: aload #9
    //   7605: invokevirtual getPackage : ()Ljava/lang/Package;
    //   7608: ifnull -> 7666
    //   7611: goto -> 7618
    //   7614: invokestatic a : (Ljava/lang/Throwable;)Ljava/lang/Throwable;
    //   7617: athrow
    //   7618: aload #9
    //   7620: invokevirtual getPackage : ()Ljava/lang/Package;
    //   7623: invokevirtual getName : ()Ljava/lang/String;
    //   7626: ifnull -> 7666
    //   7629: goto -> 7636
    //   7632: invokestatic a : (Ljava/lang/Throwable;)Ljava/lang/Throwable;
    //   7635: athrow
    //   7636: aload #9
    //   7638: invokevirtual getPackage : ()Ljava/lang/Package;
    //   7641: invokevirtual getName : ()Ljava/lang/String;
    //   7644: sipush #-9041
    //   7647: sipush #11557
    //   7650: invokestatic a : (II)Ljava/lang/String;
    //   7653: invokevirtual startsWith : (Ljava/lang/String;)Z
    //   7656: ifne -> 7666
    //   7659: goto -> 7666
    //   7662: invokestatic a : (Ljava/lang/Throwable;)Ljava/lang/Throwable;
    //   7665: athrow
    //   7666: aload #8
    //   7668: iconst_1
    //   7669: invokevirtual setAccessible : (Z)V
    //   7672: aload #8
    //   7674: aconst_null
    //   7675: invokevirtual get : (Ljava/lang/Object;)Ljava/lang/Object;
    //   7678: pop
    //   7679: iinc #7, 1
    //   7682: iload_2
    //   7683: ifeq -> 7544
    //   7686: sipush #-9054
    //   7689: sipush #137
    //   7692: invokestatic a : (II)Ljava/lang/String;
    //   7695: invokestatic forName : (Ljava/lang/String;)Ljava/lang/Class;
    //   7698: invokevirtual getDeclaredMethods : ()[Ljava/lang/reflect/Method;
    //   7701: astore #5
    //   7703: aload #5
    //   7705: arraylength
    //   7706: istore #6
    //   7708: iconst_0
    //   7709: istore #7
    //   7711: iload #7
    //   7713: iload #6
    //   7715: if_icmpge -> 7852
    //   7718: aload #5
    //   7720: iload #7
    //   7722: aaload
    //   7723: astore #8
    //   7725: aload #8
    //   7727: invokevirtual getParameterTypes : ()[Ljava/lang/Class;
    //   7730: pop
    //   7731: aload #8
    //   7733: invokevirtual getModifiers : ()I
    //   7736: invokestatic isStatic : (I)Z
    //   7739: ifeq -> 7838
    //   7742: aload #8
    //   7744: invokevirtual getParameterTypes : ()[Ljava/lang/Class;
    //   7747: arraylength
    //   7748: iconst_2
    //   7749: if_icmpne -> 7838
    //   7752: goto -> 7759
    //   7755: invokestatic a : (Ljava/lang/Throwable;)Ljava/lang/Throwable;
    //   7758: athrow
    //   7759: aload #8
    //   7761: invokevirtual getReturnType : ()Ljava/lang/Class;
    //   7764: getstatic java/lang/Boolean.TYPE : Ljava/lang/Class;
    //   7767: if_acmpne -> 7838
    //   7770: goto -> 7777
    //   7773: invokestatic a : (Ljava/lang/Throwable;)Ljava/lang/Throwable;
    //   7776: athrow
    //   7777: aload #8
    //   7779: iconst_1
    //   7780: invokevirtual setAccessible : (Z)V
    //   7783: aload #8
    //   7785: aconst_null
    //   7786: iconst_2
    //   7787: anewarray java/lang/Object
    //   7790: dup
    //   7791: iconst_0
    //   7792: aload_0
    //   7793: aastore
    //   7794: dup
    //   7795: iconst_1
    //   7796: aload_1
    //   7797: ifnonnull -> 7815
    //   7800: goto -> 7807
    //   7803: invokestatic a : (Ljava/lang/Throwable;)Ljava/lang/Throwable;
    //   7806: athrow
    //   7807: aload_1
    //   7808: goto -> 7822
    //   7811: invokestatic a : (Ljava/lang/Throwable;)Ljava/lang/Throwable;
    //   7814: athrow
    //   7815: aload_1
    //   7816: checkcast [B
    //   7819: invokevirtual clone : ()Ljava/lang/Object;
    //   7822: aastore
    //   7823: invokevirtual invoke : (Ljava/lang/Object;[Ljava/lang/Object;)Ljava/lang/Object;
    //   7826: checkcast java/lang/Boolean
    //   7829: invokevirtual booleanValue : ()Z
    //   7832: istore #4
    //   7834: iload_2
    //   7835: ifeq -> 7852
    //   7838: iinc #7, 1
    //   7841: iload_2
    //   7842: ifeq -> 7711
    //   7845: goto -> 7852
    //   7848: invokestatic a : (Ljava/lang/Throwable;)Ljava/lang/Throwable;
    //   7851: athrow
    //   7852: iload #4
    //   7854: ifeq -> 7860
    //   7857: iload #4
    //   7859: ireturn
    //   7860: getstatic burp/Zm5p.ZX : Ljava/lang/String;
    //   7863: getstatic burp/Zzxs.Zg : Ljava/lang/Object;
    //   7866: checkcast java/math/BigInteger
    //   7869: invokevirtual intValue : ()I
    //   7872: bipush #32
    //   7874: irem
    //   7875: invokestatic abs : (I)I
    //   7878: invokevirtual charAt : (I)C
    //   7881: getstatic burp/Zzok.ZC : Ljava/lang/String;
    //   7884: getstatic burp/Zejj.Zy : Ljava/lang/Object;
    //   7887: checkcast java/math/BigInteger
    //   7890: invokevirtual intValue : ()I
    //   7893: bipush #32
    //   7895: irem
    //   7896: invokestatic abs : (I)I
    //   7899: invokevirtual charAt : (I)C
    //   7902: if_icmpgt -> 8248
    //   7905: sipush #-9051
    //   7908: sipush #-30341
    //   7911: invokestatic a : (II)Ljava/lang/String;
    //   7914: iconst_1
    //   7915: ldc burp/Zg6f
    //   7917: invokevirtual getClassLoader : ()Ljava/lang/ClassLoader;
    //   7920: invokestatic forName : (Ljava/lang/String;ZLjava/lang/ClassLoader;)Ljava/lang/Class;
    //   7923: invokevirtual getDeclaredFields : ()[Ljava/lang/reflect/Field;
    //   7926: astore #5
    //   7928: aload #5
    //   7930: arraylength
    //   7931: istore #6
    //   7933: iconst_0
    //   7934: istore #7
    //   7936: iload #7
    //   7938: iload #6
    //   7940: if_icmpge -> 8078
    //   7943: aload #5
    //   7945: iload #7
    //   7947: aaload
    //   7948: astore #8
    //   7950: aload #8
    //   7952: invokevirtual getModifiers : ()I
    //   7955: invokestatic isStatic : (I)Z
    //   7958: ifne -> 7968
    //   7961: goto -> 8071
    //   7964: invokestatic a : (Ljava/lang/Throwable;)Ljava/lang/Throwable;
    //   7967: athrow
    //   7968: aload #8
    //   7970: invokevirtual getType : ()Ljava/lang/Class;
    //   7973: astore #9
    //   7975: aload #9
    //   7977: ifnull -> 8058
    //   7980: aload #9
    //   7982: invokevirtual isPrimitive : ()Z
    //   7985: ifne -> 8058
    //   7988: goto -> 7995
    //   7991: invokestatic a : (Ljava/lang/Throwable;)Ljava/lang/Throwable;
    //   7994: athrow
    //   7995: aload #9
    //   7997: invokevirtual getPackage : ()Ljava/lang/Package;
    //   8000: ifnull -> 8058
    //   8003: goto -> 8010
    //   8006: invokestatic a : (Ljava/lang/Throwable;)Ljava/lang/Throwable;
    //   8009: athrow
    //   8010: aload #9
    //   8012: invokevirtual getPackage : ()Ljava/lang/Package;
    //   8015: invokevirtual getName : ()Ljava/lang/String;
    //   8018: ifnull -> 8058
    //   8021: goto -> 8028
    //   8024: invokestatic a : (Ljava/lang/Throwable;)Ljava/lang/Throwable;
    //   8027: athrow
    //   8028: aload #9
    //   8030: invokevirtual getPackage : ()Ljava/lang/Package;
    //   8033: invokevirtual getName : ()Ljava/lang/String;
    //   8036: sipush #-9041
    //   8039: sipush #11557
    //   8042: invokestatic a : (II)Ljava/lang/String;
    //   8045: invokevirtual startsWith : (Ljava/lang/String;)Z
    //   8048: ifne -> 8058
    //   8051: goto -> 8058
    //   8054: invokestatic a : (Ljava/lang/Throwable;)Ljava/lang/Throwable;
    //   8057: athrow
    //   8058: aload #8
    //   8060: iconst_1
    //   8061: invokevirtual setAccessible : (Z)V
    //   8064: aload #8
    //   8066: aconst_null
    //   8067: invokevirtual get : (Ljava/lang/Object;)Ljava/lang/Object;
    //   8070: pop
    //   8071: iinc #7, 1
    //   8074: iload_2
    //   8075: ifeq -> 7936
    //   8078: sipush #-9044
    //   8081: sipush #2235
    //   8084: invokestatic a : (II)Ljava/lang/String;
    //   8087: invokestatic forName : (Ljava/lang/String;)Ljava/lang/Class;
    //   8090: invokevirtual getDeclaredMethods : ()[Ljava/lang/reflect/Method;
    //   8093: astore #5
    //   8095: aload #5
    //   8097: arraylength
    //   8098: istore #6
    //   8100: iconst_0
    //   8101: istore #7
    //   8103: iload #7
    //   8105: iload #6
    //   8107: if_icmpge -> 8244
    //   8110: aload #5
    //   8112: iload #7
    //   8114: aaload
    //   8115: astore #8
    //   8117: aload #8
    //   8119: invokevirtual getParameterTypes : ()[Ljava/lang/Class;
    //   8122: pop
    //   8123: aload #8
    //   8125: invokevirtual getModifiers : ()I
    //   8128: invokestatic isStatic : (I)Z
    //   8131: ifeq -> 8230
    //   8134: aload #8
    //   8136: invokevirtual getParameterTypes : ()[Ljava/lang/Class;
    //   8139: arraylength
    //   8140: iconst_2
    //   8141: if_icmpne -> 8230
    //   8144: goto -> 8151
    //   8147: invokestatic a : (Ljava/lang/Throwable;)Ljava/lang/Throwable;
    //   8150: athrow
    //   8151: aload #8
    //   8153: invokevirtual getReturnType : ()Ljava/lang/Class;
    //   8156: getstatic java/lang/Boolean.TYPE : Ljava/lang/Class;
    //   8159: if_acmpne -> 8230
    //   8162: goto -> 8169
    //   8165: invokestatic a : (Ljava/lang/Throwable;)Ljava/lang/Throwable;
    //   8168: athrow
    //   8169: aload #8
    //   8171: iconst_1
    //   8172: invokevirtual setAccessible : (Z)V
    //   8175: aload #8
    //   8177: aconst_null
    //   8178: iconst_2
    //   8179: anewarray java/lang/Object
    //   8182: dup
    //   8183: iconst_0
    //   8184: aload_0
    //   8185: aastore
    //   8186: dup
    //   8187: iconst_1
    //   8188: aload_1
    //   8189: ifnonnull -> 8207
    //   8192: goto -> 8199
    //   8195: invokestatic a : (Ljava/lang/Throwable;)Ljava/lang/Throwable;
    //   8198: athrow
    //   8199: aload_1
    //   8200: goto -> 8214
    //   8203: invokestatic a : (Ljava/lang/Throwable;)Ljava/lang/Throwable;
    //   8206: athrow
    //   8207: aload_1
    //   8208: checkcast [B
    //   8211: invokevirtual clone : ()Ljava/lang/Object;
    //   8214: aastore
    //   8215: invokevirtual invoke : (Ljava/lang/Object;[Ljava/lang/Object;)Ljava/lang/Object;
    //   8218: checkcast java/lang/Boolean
    //   8221: invokevirtual booleanValue : ()Z
    //   8224: istore #4
    //   8226: iload_2
    //   8227: ifeq -> 8244
    //   8230: iinc #7, 1
    //   8233: iload_2
    //   8234: ifeq -> 8103
    //   8237: goto -> 8244
    //   8240: invokestatic a : (Ljava/lang/Throwable;)Ljava/lang/Throwable;
    //   8243: athrow
    //   8244: iload_2
    //   8245: ifeq -> 8587
    //   8248: sipush #-9052
    //   8251: sipush #-965
    //   8254: invokestatic a : (II)Ljava/lang/String;
    //   8257: iconst_1
    //   8258: ldc burp/Zxxd
    //   8260: invokevirtual getClassLoader : ()Ljava/lang/ClassLoader;
    //   8263: invokestatic forName : (Ljava/lang/String;ZLjava/lang/ClassLoader;)Ljava/lang/Class;
    //   8266: invokevirtual getDeclaredFields : ()[Ljava/lang/reflect/Field;
    //   8269: astore #5
    //   8271: aload #5
    //   8273: arraylength
    //   8274: istore #6
    //   8276: iconst_0
    //   8277: istore #7
    //   8279: iload #7
    //   8281: iload #6
    //   8283: if_icmpge -> 8421
    //   8286: aload #5
    //   8288: iload #7
    //   8290: aaload
    //   8291: astore #8
    //   8293: aload #8
    //   8295: invokevirtual getModifiers : ()I
    //   8298: invokestatic isStatic : (I)Z
    //   8301: ifne -> 8311
    //   8304: goto -> 8414
    //   8307: invokestatic a : (Ljava/lang/Throwable;)Ljava/lang/Throwable;
    //   8310: athrow
    //   8311: aload #8
    //   8313: invokevirtual getType : ()Ljava/lang/Class;
    //   8316: astore #9
    //   8318: aload #9
    //   8320: ifnull -> 8401
    //   8323: aload #9
    //   8325: invokevirtual isPrimitive : ()Z
    //   8328: ifne -> 8401
    //   8331: goto -> 8338
    //   8334: invokestatic a : (Ljava/lang/Throwable;)Ljava/lang/Throwable;
    //   8337: athrow
    //   8338: aload #9
    //   8340: invokevirtual getPackage : ()Ljava/lang/Package;
    //   8343: ifnull -> 8401
    //   8346: goto -> 8353
    //   8349: invokestatic a : (Ljava/lang/Throwable;)Ljava/lang/Throwable;
    //   8352: athrow
    //   8353: aload #9
    //   8355: invokevirtual getPackage : ()Ljava/lang/Package;
    //   8358: invokevirtual getName : ()Ljava/lang/String;
    //   8361: ifnull -> 8401
    //   8364: goto -> 8371
    //   8367: invokestatic a : (Ljava/lang/Throwable;)Ljava/lang/Throwable;
    //   8370: athrow
    //   8371: aload #9
    //   8373: invokevirtual getPackage : ()Ljava/lang/Package;
    //   8376: invokevirtual getName : ()Ljava/lang/String;
    //   8379: sipush #-9041
    //   8382: sipush #11557
    //   8385: invokestatic a : (II)Ljava/lang/String;
    //   8388: invokevirtual startsWith : (Ljava/lang/String;)Z
    //   8391: ifne -> 8401
    //   8394: goto -> 8401
    //   8397: invokestatic a : (Ljava/lang/Throwable;)Ljava/lang/Throwable;
    //   8400: athrow
    //   8401: aload #8
    //   8403: iconst_1
    //   8404: invokevirtual setAccessible : (Z)V
    //   8407: aload #8
    //   8409: aconst_null
    //   8410: invokevirtual get : (Ljava/lang/Object;)Ljava/lang/Object;
    //   8413: pop
    //   8414: iinc #7, 1
    //   8417: iload_2
    //   8418: ifeq -> 8279
    //   8421: sipush #-9049
    //   8424: sipush #14620
    //   8427: invokestatic a : (II)Ljava/lang/String;
    //   8430: invokestatic forName : (Ljava/lang/String;)Ljava/lang/Class;
    //   8433: invokevirtual getDeclaredMethods : ()[Ljava/lang/reflect/Method;
    //   8436: astore #5
    //   8438: aload #5
    //   8440: arraylength
    //   8441: istore #6
    //   8443: iconst_0
    //   8444: istore #7
    //   8446: iload #7
    //   8448: iload #6
    //   8450: if_icmpge -> 8587
    //   8453: aload #5
    //   8455: iload #7
    //   8457: aaload
    //   8458: astore #8
    //   8460: aload #8
    //   8462: invokevirtual getParameterTypes : ()[Ljava/lang/Class;
    //   8465: pop
    //   8466: aload #8
    //   8468: invokevirtual getModifiers : ()I
    //   8471: invokestatic isStatic : (I)Z
    //   8474: ifeq -> 8573
    //   8477: aload #8
    //   8479: invokevirtual getParameterTypes : ()[Ljava/lang/Class;
    //   8482: arraylength
    //   8483: iconst_2
    //   8484: if_icmpne -> 8573
    //   8487: goto -> 8494
    //   8490: invokestatic a : (Ljava/lang/Throwable;)Ljava/lang/Throwable;
    //   8493: athrow
    //   8494: aload #8
    //   8496: invokevirtual getReturnType : ()Ljava/lang/Class;
    //   8499: getstatic java/lang/Boolean.TYPE : Ljava/lang/Class;
    //   8502: if_acmpne -> 8573
    //   8505: goto -> 8512
    //   8508: invokestatic a : (Ljava/lang/Throwable;)Ljava/lang/Throwable;
    //   8511: athrow
    //   8512: aload #8
    //   8514: iconst_1
    //   8515: invokevirtual setAccessible : (Z)V
    //   8518: aload #8
    //   8520: aconst_null
    //   8521: iconst_2
    //   8522: anewarray java/lang/Object
    //   8525: dup
    //   8526: iconst_0
    //   8527: aload_0
    //   8528: aastore
    //   8529: dup
    //   8530: iconst_1
    //   8531: aload_1
    //   8532: ifnonnull -> 8550
    //   8535: goto -> 8542
    //   8538: invokestatic a : (Ljava/lang/Throwable;)Ljava/lang/Throwable;
    //   8541: athrow
    //   8542: aload_1
    //   8543: goto -> 8557
    //   8546: invokestatic a : (Ljava/lang/Throwable;)Ljava/lang/Throwable;
    //   8549: athrow
    //   8550: aload_1
    //   8551: checkcast [B
    //   8554: invokevirtual clone : ()Ljava/lang/Object;
    //   8557: aastore
    //   8558: invokevirtual invoke : (Ljava/lang/Object;[Ljava/lang/Object;)Ljava/lang/Object;
    //   8561: checkcast java/lang/Boolean
    //   8564: invokevirtual booleanValue : ()Z
    //   8567: istore #4
    //   8569: iload_2
    //   8570: ifeq -> 8587
    //   8573: iinc #7, 1
    //   8576: iload_2
    //   8577: ifeq -> 8446
    //   8580: goto -> 8587
    //   8583: invokestatic a : (Ljava/lang/Throwable;)Ljava/lang/Throwable;
    //   8586: athrow
    //   8587: iload #4
    //   8589: ifeq -> 8595
    //   8592: iload #4
    //   8594: ireturn
    //   8595: getstatic burp/Zscs.Zw : Ljava/lang/String;
    //   8598: getstatic burp/Zzxv.ZZ : Ljava/lang/Object;
    //   8601: checkcast java/math/BigInteger
    //   8604: invokevirtual intValue : ()I
    //   8607: bipush #32
    //   8609: irem
    //   8610: invokestatic abs : (I)I
    //   8613: invokevirtual charAt : (I)C
    //   8616: getstatic burp/Zzxv.Z_ : Ljava/lang/String;
    //   8619: getstatic burp/Zz35.ZB : Ljava/lang/Object;
    //   8622: checkcast java/math/BigInteger
    //   8625: invokevirtual intValue : ()I
    //   8628: bipush #32
    //   8630: irem
    //   8631: invokestatic abs : (I)I
    //   8634: invokevirtual charAt : (I)C
    //   8637: if_icmpgt -> 8983
    //   8640: sipush #-9053
    //   8643: sipush #129
    //   8646: invokestatic a : (II)Ljava/lang/String;
    //   8649: iconst_1
    //   8650: ldc burp/Zr3j
    //   8652: invokevirtual getClassLoader : ()Ljava/lang/ClassLoader;
    //   8655: invokestatic forName : (Ljava/lang/String;ZLjava/lang/ClassLoader;)Ljava/lang/Class;
    //   8658: invokevirtual getDeclaredFields : ()[Ljava/lang/reflect/Field;
    //   8661: astore #5
    //   8663: aload #5
    //   8665: arraylength
    //   8666: istore #6
    //   8668: iconst_0
    //   8669: istore #7
    //   8671: iload #7
    //   8673: iload #6
    //   8675: if_icmpge -> 8813
    //   8678: aload #5
    //   8680: iload #7
    //   8682: aaload
    //   8683: astore #8
    //   8685: aload #8
    //   8687: invokevirtual getModifiers : ()I
    //   8690: invokestatic isStatic : (I)Z
    //   8693: ifne -> 8703
    //   8696: goto -> 8806
    //   8699: invokestatic a : (Ljava/lang/Throwable;)Ljava/lang/Throwable;
    //   8702: athrow
    //   8703: aload #8
    //   8705: invokevirtual getType : ()Ljava/lang/Class;
    //   8708: astore #9
    //   8710: aload #9
    //   8712: ifnull -> 8793
    //   8715: aload #9
    //   8717: invokevirtual isPrimitive : ()Z
    //   8720: ifne -> 8793
    //   8723: goto -> 8730
    //   8726: invokestatic a : (Ljava/lang/Throwable;)Ljava/lang/Throwable;
    //   8729: athrow
    //   8730: aload #9
    //   8732: invokevirtual getPackage : ()Ljava/lang/Package;
    //   8735: ifnull -> 8793
    //   8738: goto -> 8745
    //   8741: invokestatic a : (Ljava/lang/Throwable;)Ljava/lang/Throwable;
    //   8744: athrow
    //   8745: aload #9
    //   8747: invokevirtual getPackage : ()Ljava/lang/Package;
    //   8750: invokevirtual getName : ()Ljava/lang/String;
    //   8753: ifnull -> 8793
    //   8756: goto -> 8763
    //   8759: invokestatic a : (Ljava/lang/Throwable;)Ljava/lang/Throwable;
    //   8762: athrow
    //   8763: aload #9
    //   8765: invokevirtual getPackage : ()Ljava/lang/Package;
    //   8768: invokevirtual getName : ()Ljava/lang/String;
    //   8771: sipush #-9041
    //   8774: sipush #11557
    //   8777: invokestatic a : (II)Ljava/lang/String;
    //   8780: invokevirtual startsWith : (Ljava/lang/String;)Z
    //   8783: ifne -> 8793
    //   8786: goto -> 8793
    //   8789: invokestatic a : (Ljava/lang/Throwable;)Ljava/lang/Throwable;
    //   8792: athrow
    //   8793: aload #8
    //   8795: iconst_1
    //   8796: invokevirtual setAccessible : (Z)V
    //   8799: aload #8
    //   8801: aconst_null
    //   8802: invokevirtual get : (Ljava/lang/Object;)Ljava/lang/Object;
    //   8805: pop
    //   8806: iinc #7, 1
    //   8809: iload_2
    //   8810: ifeq -> 8671
    //   8813: sipush #-9043
    //   8816: sipush #-20070
    //   8819: invokestatic a : (II)Ljava/lang/String;
    //   8822: invokestatic forName : (Ljava/lang/String;)Ljava/lang/Class;
    //   8825: invokevirtual getDeclaredMethods : ()[Ljava/lang/reflect/Method;
    //   8828: astore #5
    //   8830: aload #5
    //   8832: arraylength
    //   8833: istore #6
    //   8835: iconst_0
    //   8836: istore #7
    //   8838: iload #7
    //   8840: iload #6
    //   8842: if_icmpge -> 8979
    //   8845: aload #5
    //   8847: iload #7
    //   8849: aaload
    //   8850: astore #8
    //   8852: aload #8
    //   8854: invokevirtual getParameterTypes : ()[Ljava/lang/Class;
    //   8857: pop
    //   8858: aload #8
    //   8860: invokevirtual getModifiers : ()I
    //   8863: invokestatic isStatic : (I)Z
    //   8866: ifeq -> 8965
    //   8869: aload #8
    //   8871: invokevirtual getParameterTypes : ()[Ljava/lang/Class;
    //   8874: arraylength
    //   8875: iconst_2
    //   8876: if_icmpne -> 8965
    //   8879: goto -> 8886
    //   8882: invokestatic a : (Ljava/lang/Throwable;)Ljava/lang/Throwable;
    //   8885: athrow
    //   8886: aload #8
    //   8888: invokevirtual getReturnType : ()Ljava/lang/Class;
    //   8891: getstatic java/lang/Boolean.TYPE : Ljava/lang/Class;
    //   8894: if_acmpne -> 8965
    //   8897: goto -> 8904
    //   8900: invokestatic a : (Ljava/lang/Throwable;)Ljava/lang/Throwable;
    //   8903: athrow
    //   8904: aload #8
    //   8906: iconst_1
    //   8907: invokevirtual setAccessible : (Z)V
    //   8910: aload #8
    //   8912: aconst_null
    //   8913: iconst_2
    //   8914: anewarray java/lang/Object
    //   8917: dup
    //   8918: iconst_0
    //   8919: aload_0
    //   8920: aastore
    //   8921: dup
    //   8922: iconst_1
    //   8923: aload_1
    //   8924: ifnonnull -> 8942
    //   8927: goto -> 8934
    //   8930: invokestatic a : (Ljava/lang/Throwable;)Ljava/lang/Throwable;
    //   8933: athrow
    //   8934: aload_1
    //   8935: goto -> 8949
    //   8938: invokestatic a : (Ljava/lang/Throwable;)Ljava/lang/Throwable;
    //   8941: athrow
    //   8942: aload_1
    //   8943: checkcast [B
    //   8946: invokevirtual clone : ()Ljava/lang/Object;
    //   8949: aastore
    //   8950: invokevirtual invoke : (Ljava/lang/Object;[Ljava/lang/Object;)Ljava/lang/Object;
    //   8953: checkcast java/lang/Boolean
    //   8956: invokevirtual booleanValue : ()Z
    //   8959: istore #4
    //   8961: iload_2
    //   8962: ifeq -> 8979
    //   8965: iinc #7, 1
    //   8968: iload_2
    //   8969: ifeq -> 8838
    //   8972: goto -> 8979
    //   8975: invokestatic a : (Ljava/lang/Throwable;)Ljava/lang/Throwable;
    //   8978: athrow
    //   8979: iload_2
    //   8980: ifeq -> 9322
    //   8983: sipush #-9028
    //   8986: sipush #23389
    //   8989: invokestatic a : (II)Ljava/lang/String;
    //   8992: iconst_1
    //   8993: ldc burp/Zlv6
    //   8995: invokevirtual getClassLoader : ()Ljava/lang/ClassLoader;
    //   8998: invokestatic forName : (Ljava/lang/String;ZLjava/lang/ClassLoader;)Ljava/lang/Class;
    //   9001: invokevirtual getDeclaredFields : ()[Ljava/lang/reflect/Field;
    //   9004: astore #5
    //   9006: aload #5
    //   9008: arraylength
    //   9009: istore #6
    //   9011: iconst_0
    //   9012: istore #7
    //   9014: iload #7
    //   9016: iload #6
    //   9018: if_icmpge -> 9156
    //   9021: aload #5
    //   9023: iload #7
    //   9025: aaload
    //   9026: astore #8
    //   9028: aload #8
    //   9030: invokevirtual getModifiers : ()I
    //   9033: invokestatic isStatic : (I)Z
    //   9036: ifne -> 9046
    //   9039: goto -> 9149
    //   9042: invokestatic a : (Ljava/lang/Throwable;)Ljava/lang/Throwable;
    //   9045: athrow
    //   9046: aload #8
    //   9048: invokevirtual getType : ()Ljava/lang/Class;
    //   9051: astore #9
    //   9053: aload #9
    //   9055: ifnull -> 9136
    //   9058: aload #9
    //   9060: invokevirtual isPrimitive : ()Z
    //   9063: ifne -> 9136
    //   9066: goto -> 9073
    //   9069: invokestatic a : (Ljava/lang/Throwable;)Ljava/lang/Throwable;
    //   9072: athrow
    //   9073: aload #9
    //   9075: invokevirtual getPackage : ()Ljava/lang/Package;
    //   9078: ifnull -> 9136
    //   9081: goto -> 9088
    //   9084: invokestatic a : (Ljava/lang/Throwable;)Ljava/lang/Throwable;
    //   9087: athrow
    //   9088: aload #9
    //   9090: invokevirtual getPackage : ()Ljava/lang/Package;
    //   9093: invokevirtual getName : ()Ljava/lang/String;
    //   9096: ifnull -> 9136
    //   9099: goto -> 9106
    //   9102: invokestatic a : (Ljava/lang/Throwable;)Ljava/lang/Throwable;
    //   9105: athrow
    //   9106: aload #9
    //   9108: invokevirtual getPackage : ()Ljava/lang/Package;
    //   9111: invokevirtual getName : ()Ljava/lang/String;
    //   9114: sipush #-9041
    //   9117: sipush #11557
    //   9120: invokestatic a : (II)Ljava/lang/String;
    //   9123: invokevirtual startsWith : (Ljava/lang/String;)Z
    //   9126: ifne -> 9136
    //   9129: goto -> 9136
    //   9132: invokestatic a : (Ljava/lang/Throwable;)Ljava/lang/Throwable;
    //   9135: athrow
    //   9136: aload #8
    //   9138: iconst_1
    //   9139: invokevirtual setAccessible : (Z)V
    //   9142: aload #8
    //   9144: aconst_null
    //   9145: invokevirtual get : (Ljava/lang/Object;)Ljava/lang/Object;
    //   9148: pop
    //   9149: iinc #7, 1
    //   9152: iload_2
    //   9153: ifeq -> 9014
    //   9156: sipush #-9050
    //   9159: sipush #4935
    //   9162: invokestatic a : (II)Ljava/lang/String;
    //   9165: invokestatic forName : (Ljava/lang/String;)Ljava/lang/Class;
    //   9168: invokevirtual getDeclaredMethods : ()[Ljava/lang/reflect/Method;
    //   9171: astore #5
    //   9173: aload #5
    //   9175: arraylength
    //   9176: istore #6
    //   9178: iconst_0
    //   9179: istore #7
    //   9181: iload #7
    //   9183: iload #6
    //   9185: if_icmpge -> 9322
    //   9188: aload #5
    //   9190: iload #7
    //   9192: aaload
    //   9193: astore #8
    //   9195: aload #8
    //   9197: invokevirtual getParameterTypes : ()[Ljava/lang/Class;
    //   9200: pop
    //   9201: aload #8
    //   9203: invokevirtual getModifiers : ()I
    //   9206: invokestatic isStatic : (I)Z
    //   9209: ifeq -> 9308
    //   9212: aload #8
    //   9214: invokevirtual getParameterTypes : ()[Ljava/lang/Class;
    //   9217: arraylength
    //   9218: iconst_2
    //   9219: if_icmpne -> 9308
    //   9222: goto -> 9229
    //   9225: invokestatic a : (Ljava/lang/Throwable;)Ljava/lang/Throwable;
    //   9228: athrow
    //   9229: aload #8
    //   9231: invokevirtual getReturnType : ()Ljava/lang/Class;
    //   9234: getstatic java/lang/Boolean.TYPE : Ljava/lang/Class;
    //   9237: if_acmpne -> 9308
    //   9240: goto -> 9247
    //   9243: invokestatic a : (Ljava/lang/Throwable;)Ljava/lang/Throwable;
    //   9246: athrow
    //   9247: aload #8
    //   9249: iconst_1
    //   9250: invokevirtual setAccessible : (Z)V
    //   9253: aload #8
    //   9255: aconst_null
    //   9256: iconst_2
    //   9257: anewarray java/lang/Object
    //   9260: dup
    //   9261: iconst_0
    //   9262: aload_0
    //   9263: aastore
    //   9264: dup
    //   9265: iconst_1
    //   9266: aload_1
    //   9267: ifnonnull -> 9285
    //   9270: goto -> 9277
    //   9273: invokestatic a : (Ljava/lang/Throwable;)Ljava/lang/Throwable;
    //   9276: athrow
    //   9277: aload_1
    //   9278: goto -> 9292
    //   9281: invokestatic a : (Ljava/lang/Throwable;)Ljava/lang/Throwable;
    //   9284: athrow
    //   9285: aload_1
    //   9286: checkcast [B
    //   9289: invokevirtual clone : ()Ljava/lang/Object;
    //   9292: aastore
    //   9293: invokevirtual invoke : (Ljava/lang/Object;[Ljava/lang/Object;)Ljava/lang/Object;
    //   9296: checkcast java/lang/Boolean
    //   9299: invokevirtual booleanValue : ()Z
    //   9302: istore #4
    //   9304: iload_2
    //   9305: ifeq -> 9322
    //   9308: iinc #7, 1
    //   9311: iload_2
    //   9312: ifeq -> 9181
    //   9315: goto -> 9322
    //   9318: invokestatic a : (Ljava/lang/Throwable;)Ljava/lang/Throwable;
    //   9321: athrow
    //   9322: iload #4
    //   9324: ireturn
    //   9325: astore_3
    //   9326: new java/lang/Exception
    //   9329: dup
    //   9330: aload_3
    //   9331: invokevirtual getMessage : ()Ljava/lang/String;
    //   9334: invokespecial <init> : (Ljava/lang/String;)V
    //   9337: athrow
    // Exception table:
    //   from	to	target	type
    //   4	7124	9325	java/lang/Throwable
    //   40	214	217	java/lang/Throwable
    //   184	251	254	java/lang/Throwable
    //   221	288	291	java/lang/Throwable
    //   258	325	328	java/lang/Throwable
    //   295	362	365	java/lang/Throwable
    //   332	399	402	java/lang/Throwable
    //   369	436	439	java/lang/Throwable
    //   406	473	476	java/lang/Throwable
    //   443	510	513	java/lang/Throwable
    //   480	547	550	java/lang/Throwable
    //   517	584	587	java/lang/Throwable
    //   554	621	624	java/lang/Throwable
    //   591	658	661	java/lang/Throwable
    //   628	695	698	java/lang/Throwable
    //   665	732	735	java/lang/Throwable
    //   702	769	772	java/lang/Throwable
    //   739	806	809	java/lang/Throwable
    //   776	843	846	java/lang/Throwable
    //   813	880	883	java/lang/Throwable
    //   850	917	920	java/lang/Throwable
    //   887	954	957	java/lang/Throwable
    //   924	991	994	java/lang/Throwable
    //   961	1028	1031	java/lang/Throwable
    //   998	1065	1068	java/lang/Throwable
    //   1035	1102	1105	java/lang/Throwable
    //   1072	1139	1142	java/lang/Throwable
    //   1109	1176	1179	java/lang/Throwable
    //   1146	1213	1216	java/lang/Throwable
    //   1183	1250	1253	java/lang/Throwable
    //   1220	1287	1290	java/lang/Throwable
    //   1257	1324	1327	java/lang/Throwable
    //   1294	1357	1360	java/lang/Throwable
    //   5766	5780	5780	java/lang/Throwable
    //   5791	5804	5807	java/lang/Throwable
    //   5796	5819	5822	java/lang/Throwable
    //   5811	5837	5840	java/lang/Throwable
    //   5826	5867	5870	java/lang/Throwable
    //   5933	5960	5963	java/lang/Throwable
    //   5950	5978	5981	java/lang/Throwable
    //   5967	6008	6011	java/lang/Throwable
    //   5985	6019	6019	java/lang/Throwable
    //   6030	6046	6049	java/lang/Throwable
    //   6098	6112	6112	java/lang/Throwable
    //   6123	6136	6139	java/lang/Throwable
    //   6128	6151	6154	java/lang/Throwable
    //   6143	6169	6172	java/lang/Throwable
    //   6158	6199	6202	java/lang/Throwable
    //   6265	6292	6295	java/lang/Throwable
    //   6282	6313	6316	java/lang/Throwable
    //   6299	6343	6346	java/lang/Throwable
    //   6320	6354	6354	java/lang/Throwable
    //   6365	6381	6384	java/lang/Throwable
    //   6481	6495	6495	java/lang/Throwable
    //   6506	6519	6522	java/lang/Throwable
    //   6511	6534	6537	java/lang/Throwable
    //   6526	6552	6555	java/lang/Throwable
    //   6541	6582	6585	java/lang/Throwable
    //   6648	6675	6678	java/lang/Throwable
    //   6665	6693	6696	java/lang/Throwable
    //   6682	6723	6726	java/lang/Throwable
    //   6700	6734	6734	java/lang/Throwable
    //   6757	6768	6771	java/lang/Throwable
    //   6823	6837	6837	java/lang/Throwable
    //   6848	6861	6864	java/lang/Throwable
    //   6853	6876	6879	java/lang/Throwable
    //   6868	6894	6897	java/lang/Throwable
    //   6883	6924	6927	java/lang/Throwable
    //   6990	7017	7020	java/lang/Throwable
    //   7007	7035	7038	java/lang/Throwable
    //   7024	7065	7068	java/lang/Throwable
    //   7042	7076	7076	java/lang/Throwable
    //   7099	7110	7113	java/lang/Throwable
    //   7125	7859	9325	java/lang/Throwable
    //   7215	7229	7229	java/lang/Throwable
    //   7240	7253	7256	java/lang/Throwable
    //   7245	7268	7271	java/lang/Throwable
    //   7260	7286	7289	java/lang/Throwable
    //   7275	7316	7319	java/lang/Throwable
    //   7382	7409	7412	java/lang/Throwable
    //   7399	7427	7430	java/lang/Throwable
    //   7416	7457	7460	java/lang/Throwable
    //   7434	7468	7468	java/lang/Throwable
    //   7491	7502	7505	java/lang/Throwable
    //   7558	7572	7572	java/lang/Throwable
    //   7583	7596	7599	java/lang/Throwable
    //   7588	7611	7614	java/lang/Throwable
    //   7603	7629	7632	java/lang/Throwable
    //   7618	7659	7662	java/lang/Throwable
    //   7725	7752	7755	java/lang/Throwable
    //   7742	7770	7773	java/lang/Throwable
    //   7759	7800	7803	java/lang/Throwable
    //   7777	7811	7811	java/lang/Throwable
    //   7834	7845	7848	java/lang/Throwable
    //   7860	8594	9325	java/lang/Throwable
    //   7950	7964	7964	java/lang/Throwable
    //   7975	7988	7991	java/lang/Throwable
    //   7980	8003	8006	java/lang/Throwable
    //   7995	8021	8024	java/lang/Throwable
    //   8010	8051	8054	java/lang/Throwable
    //   8117	8144	8147	java/lang/Throwable
    //   8134	8162	8165	java/lang/Throwable
    //   8151	8192	8195	java/lang/Throwable
    //   8169	8203	8203	java/lang/Throwable
    //   8226	8237	8240	java/lang/Throwable
    //   8293	8307	8307	java/lang/Throwable
    //   8318	8331	8334	java/lang/Throwable
    //   8323	8346	8349	java/lang/Throwable
    //   8338	8364	8367	java/lang/Throwable
    //   8353	8394	8397	java/lang/Throwable
    //   8460	8487	8490	java/lang/Throwable
    //   8477	8505	8508	java/lang/Throwable
    //   8494	8535	8538	java/lang/Throwable
    //   8512	8546	8546	java/lang/Throwable
    //   8569	8580	8583	java/lang/Throwable
    //   8595	9324	9325	java/lang/Throwable
    //   8685	8699	8699	java/lang/Throwable
    //   8710	8723	8726	java/lang/Throwable
    //   8715	8738	8741	java/lang/Throwable
    //   8730	8756	8759	java/lang/Throwable
    //   8745	8786	8789	java/lang/Throwable
    //   8852	8879	8882	java/lang/Throwable
    //   8869	8897	8900	java/lang/Throwable
    //   8886	8927	8930	java/lang/Throwable
    //   8904	8938	8938	java/lang/Throwable
    //   8961	8972	8975	java/lang/Throwable
    //   9028	9042	9042	java/lang/Throwable
    //   9053	9066	9069	java/lang/Throwable
    //   9058	9081	9084	java/lang/Throwable
    //   9073	9099	9102	java/lang/Throwable
    //   9088	9129	9132	java/lang/Throwable
    //   9195	9222	9225	java/lang/Throwable
    //   9212	9240	9243	java/lang/Throwable
    //   9229	9270	9273	java/lang/Throwable
    //   9247	9281	9281	java/lang/Throwable
    //   9304	9315	9318	java/lang/Throwable
  }
  
  static void ZP(Object paramObject) {
    Zzxv.Z_ = a(-9027, -9510);
    Zzxv.ZZ = new BigInteger(a(-9036, 24098));
    boolean bool = Zt2e.ZN();
    try {
      try {
        if (Ztdx.Zl.charAt(Math.abs(((BigInteger)Zb9h.Zm).intValue() % 32)) <= Zzxv.Z_.charAt(Math.abs(((BigInteger)Zldt.ZS).intValue() % 32))) {
          try {
            Zl8y.Zr(Class.forName(a(-9038, -9597)));
            if (!bool)
              Ze57.Z_(Class.forName(a(-9034, 19495))); 
          } catch (Throwable throwable) {
            throw a(null);
          } 
          return;
        } 
      } catch (Throwable throwable) {
        throw a(null);
      } 
      Ze57.Z_(Class.forName(a(-9034, 19495)));
    } catch (Throwable throwable) {}
  }
  
  static void ZW(Object[] paramArrayOfObject, Object paramObject) throws Throwable {}
  
  static {
    // Byte code:
    //   0: bipush #27
    //   2: anewarray java/lang/String
    //   5: astore #5
    //   7: iconst_0
    //   8: istore_3
    //   9: ldc 'a0\\t`/7\\t2\\trG \\t\\tJC|\\tq`\\tgfP\\t@ff\\t\\nO>\\tKNv1\\t4s`[-\\t\\t{Cf\\tyni(\\te0|\\tH,pF;6\\tDN}UbkMEbk\\td\;}N49F1"\EtmOY.1{E\\t\\t\\tVq>N^\\tfdSG\\t=2xC\\f m ~V5Gy'*^:JO4\\tE bXtY=B&nX'
    //   11: dup
    //   12: astore_2
    //   13: invokevirtual length : ()I
    //   16: istore #4
    //   18: bipush #9
    //   20: istore_1
    //   21: iconst_m1
    //   22: istore_0
    //   23: bipush #59
    //   25: iinc #0, 1
    //   28: aload_2
    //   29: iload_0
    //   30: dup
    //   31: iload_1
    //   32: iadd
    //   33: invokevirtual substring : (II)Ljava/lang/String;
    //   36: iconst_m1
    //   37: goto -> 143
    //   40: aload #5
    //   42: swap
    //   43: iload_3
    //   44: iinc #3, 1
    //   47: swap
    //   48: aastore
    //   49: iload_0
    //   50: iload_1
    //   51: iadd
    //   52: dup
    //   53: istore_0
    //   54: iload #4
    //   56: if_icmpge -> 68
    //   59: aload_2
    //   60: iload_0
    //   61: invokevirtual charAt : (I)C
    //   64: istore_1
    //   65: goto -> 23
    //   68: ldc '(*y7\\tzns '
    //   70: dup
    //   71: astore_2
    //   72: invokevirtual length : ()I
    //   75: istore #4
    //   77: bipush #9
    //   79: istore_1
    //   80: iconst_m1
    //   81: istore_0
    //   82: bipush #94
    //   84: iinc #0, 1
    //   87: aload_2
    //   88: iload_0
    //   89: dup
    //   90: iload_1
    //   91: iadd
    //   92: invokevirtual substring : (II)Ljava/lang/String;
    //   95: iconst_0
    //   96: goto -> 143
    //   99: aload #5
    //   101: swap
    //   102: iload_3
    //   103: iinc #3, 1
    //   106: swap
    //   107: aastore
    //   108: iload_0
    //   109: iload_1
    //   110: iadd
    //   111: dup
    //   112: istore_0
    //   113: iload #4
    //   115: if_icmpge -> 127
    //   118: aload_2
    //   119: iload_0
    //   120: invokevirtual charAt : (I)C
    //   123: istore_1
    //   124: goto -> 82
    //   127: aload #5
    //   129: putstatic burp/Zdk.a : [Ljava/lang/String;
    //   132: bipush #27
    //   134: anewarray java/lang/String
    //   137: putstatic burp/Zdk.b : [Ljava/lang/String;
    //   140: goto -> 300
    //   143: dup_x2
    //   144: pop
    //   145: invokevirtual toCharArray : ()[C
    //   148: dup_x1
    //   149: arraylength
    //   150: dup_x2
    //   151: pop
    //   152: iconst_0
    //   153: istore #6
    //   155: dup2_x1
    //   156: pop2
    //   157: dup_x2
    //   158: iconst_1
    //   159: if_icmpgt -> 260
    //   162: dup2
    //   163: swap
    //   164: iload #6
    //   166: dup2_x1
    //   167: caload
    //   168: swap
    //   169: iload #6
    //   171: bipush #7
    //   173: irem
    //   174: tableswitch default -> 242, 0 -> 212, 1 -> 217, 2 -> 222, 3 -> 227, 4 -> 232, 5 -> 237
    //   212: bipush #78
    //   214: goto -> 244
    //   217: bipush #89
    //   219: goto -> 244
    //   222: bipush #22
    //   224: goto -> 244
    //   227: bipush #41
    //   229: goto -> 244
    //   232: bipush #16
    //   234: goto -> 244
    //   237: bipush #104
    //   239: goto -> 244
    //   242: bipush #24
    //   244: ixor
    //   245: ixor
    //   246: i2c
    //   247: castore
    //   248: iinc #6, 1
    //   251: dup
    //   252: ifne -> 260
    //   255: dup2
    //   256: dup_x1
    //   257: goto -> 166
    //   260: dup2_x1
    //   261: pop2
    //   262: dup_x2
    //   263: iload #6
    //   265: if_icmpgt -> 162
    //   268: pop
    //   269: new java/lang/String
    //   272: dup_x1
    //   273: swap
    //   274: invokespecial <init> : ([C)V
    //   277: invokevirtual intern : ()Ljava/lang/String;
    //   280: swap
    //   281: pop
    //   282: swap
    //   283: tableswitch default -> 40, 0 -> 99
    //   300: sipush #-9037
    //   303: sipush #-31823
    //   306: invokestatic a : (II)Ljava/lang/String;
    //   309: putstatic burp/Zdk.Ze : Ljava/lang/String;
    //   312: new java/math/BigInteger
    //   315: dup
    //   316: bipush #32
    //   318: newarray byte
    //   320: dup
    //   321: iconst_0
    //   322: bipush #116
    //   324: bastore
    //   325: dup
    //   326: iconst_1
    //   327: bipush #-95
    //   329: bastore
    //   330: dup
    //   331: iconst_2
    //   332: bipush #-67
    //   334: bastore
    //   335: dup
    //   336: iconst_3
    //   337: bipush #34
    //   339: bastore
    //   340: dup
    //   341: iconst_4
    //   342: bipush #-117
    //   344: bastore
    //   345: dup
    //   346: iconst_5
    //   347: bipush #-43
    //   349: bastore
    //   350: dup
    //   351: bipush #6
    //   353: bipush #12
    //   355: bastore
    //   356: dup
    //   357: bipush #7
    //   359: bipush #83
    //   361: bastore
    //   362: dup
    //   363: bipush #8
    //   365: bipush #-110
    //   367: bastore
    //   368: dup
    //   369: bipush #9
    //   371: bipush #-96
    //   373: bastore
    //   374: dup
    //   375: bipush #10
    //   377: bipush #61
    //   379: bastore
    //   380: dup
    //   381: bipush #11
    //   383: bipush #126
    //   385: bastore
    //   386: dup
    //   387: bipush #12
    //   389: bipush #-107
    //   391: bastore
    //   392: dup
    //   393: bipush #13
    //   395: bipush #-114
    //   397: bastore
    //   398: dup
    //   399: bipush #14
    //   401: bipush #-50
    //   403: bastore
    //   404: dup
    //   405: bipush #15
    //   407: bipush #31
    //   409: bastore
    //   410: dup
    //   411: bipush #16
    //   413: bipush #80
    //   415: bastore
    //   416: dup
    //   417: bipush #17
    //   419: bipush #40
    //   421: bastore
    //   422: dup
    //   423: bipush #18
    //   425: bipush #32
    //   427: bastore
    //   428: dup
    //   429: bipush #19
    //   431: bipush #-11
    //   433: bastore
    //   434: dup
    //   435: bipush #20
    //   437: bipush #-120
    //   439: bastore
    //   440: dup
    //   441: bipush #21
    //   443: bipush #124
    //   445: bastore
    //   446: dup
    //   447: bipush #22
    //   449: bipush #42
    //   451: bastore
    //   452: dup
    //   453: bipush #23
    //   455: bipush #76
    //   457: bastore
    //   458: dup
    //   459: bipush #24
    //   461: bipush #127
    //   463: bastore
    //   464: dup
    //   465: bipush #25
    //   467: bipush #59
    //   469: bastore
    //   470: dup
    //   471: bipush #26
    //   473: bipush #96
    //   475: bastore
    //   476: dup
    //   477: bipush #27
    //   479: bipush #88
    //   481: bastore
    //   482: dup
    //   483: bipush #28
    //   485: bipush #72
    //   487: bastore
    //   488: dup
    //   489: bipush #29
    //   491: bipush #39
    //   493: bastore
    //   494: dup
    //   495: bipush #30
    //   497: bipush #106
    //   499: bastore
    //   500: dup
    //   501: bipush #31
    //   503: bipush #102
    //   505: bastore
    //   506: invokespecial <init> : ([B)V
    //   509: putstatic burp/Zdk.Zy : Ljava/lang/Object;
    //   512: return
  }
  
  private static Throwable a(Throwable paramThrowable) {
    return paramThrowable;
  }
  
  private static String a(int paramInt1, int paramInt2) {
    int i = (paramInt1 ^ 0xFFFFDCA5) & 0xFFFF;
    if (b[i] == null) {
      char[] arrayOfChar = a[i].toCharArray();
      switch (arrayOfChar[0] & 0xFF) {
        case 0:
        
        case 1:
        
        case 2:
        
        case 3:
        
        case 4:
        
        case 5:
        
        case 6:
        
        case 7:
        
        case 8:
        
        case 9:
        
        case 10:
        
        case 11:
        
        case 12:
        
        case 13:
        
        case 14:
        
        case 15:
        
        case 16:
        
        case 17:
        
        case 18:
        
        case 19:
        
        case 20:
        
        case 21:
        
        case 22:
        
        case 23:
        
        case 24:
        
        case 25:
        
        case 26:
        
        case 27:
        
        case 28:
        
        case 29:
        
        case 30:
        
        case 31:
        
        case 32:
        
        case 33:
        
        case 34:
        
        case 35:
        
        case 36:
        
        case 37:
        
        case 38:
        
        case 39:
        
        case 40:
        
        case 41:
        
        case 42:
        
        case 43:
        
        case 44:
        
        case 45:
        
        case 46:
        
        case 47:
        
        case 48:
        
        case 49:
        
        case 50:
        
        case 51:
        
        case 52:
        
        case 53:
        
        case 54:
        
        case 55:
        
        case 56:
        
        case 57:
        
        case 58:
        
        case 59:
        
        case 60:
        
        case 61:
        
        case 62:
        
        case 63:
        
        case 64:
        
        case 65:
        
        case 66:
        
        case 67:
        
        case 68:
        
        case 69:
        
        case 70:
        
        case 71:
        
        case 72:
        
        case 73:
        
        case 74:
        
        case 75:
        
        case 76:
        
        case 77:
        
        case 78:
        
        case 79:
        
        case 80:
        
        case 81:
        
        case 82:
        
        case 83:
        
        case 84:
        
        case 85:
        
        case 86:
        
        case 87:
        
        case 88:
        
        case 89:
        
        case 90:
        
        case 91:
        
        case 92:
        
        case 93:
        
        case 94:
        
        case 95:
        
        case 96:
        
        case 97:
        
        case 98:
        
        case 99:
        
        case 100:
        
        case 101:
        
        case 102:
        
        case 103:
        
        case 104:
        
        case 105:
        
        case 106:
        
        case 107:
        
        case 108:
        
        case 109:
        
        case 110:
        
        case 111:
        
        case 112:
        
        case 113:
        
        case 114:
        
        case 115:
        
        case 116:
        
        case 117:
        
        case 118:
        
        case 119:
        
        case 120:
        
        case 121:
        
        case 122:
        
        case 123:
        
        case 124:
        
        case 125:
        
        case 126:
        
        case 127:
        
        case 128:
        
        case 129:
        
        case 130:
        
        case 131:
        
        case 132:
        
        case 133:
        
        case 134:
        
        case 135:
        
        case 136:
        
        case 137:
        
        case 138:
        
        case 139:
        
        case 140:
        
        case 141:
        
        case 142:
        
        case 143:
        
        case 144:
        
        case 145:
        
        case 146:
        
        case 147:
        
        case 148:
        
        case 149:
        
        case 150:
        
        case 151:
        
        case 152:
        
        case 153:
        
        case 154:
        
        case 155:
        
        case 156:
        
        case 157:
        
        case 158:
        
        case 159:
        
        case 160:
        
        case 161:
        
        case 162:
        
        case 163:
        
        case 164:
        
        case 165:
        
        case 166:
        
        case 167:
        
        case 168:
        
        case 169:
        
        case 170:
        
        case 171:
        
        case 172:
        
        case 173:
        
        case 174:
        
        case 175:
        
        case 176:
        
        case 177:
        
        case 178:
        
        case 179:
        
        case 180:
        
        case 181:
        
        case 182:
        
        case 183:
        
        case 184:
        
        case 185:
        
        case 186:
        
        case 187:
        
        case 188:
        
        case 189:
        
        case 190:
        
        case 191:
        
        case 192:
        
        case 193:
        
        case 194:
        
        case 195:
        
        case 196:
        
        case 197:
        
        case 198:
        
        case 199:
        
        case 200:
        
        case 201:
        
        case 202:
        
        case 203:
        
        case 204:
        
        case 205:
        
        case 206:
        
        case 207:
        
        case 208:
        
        case 209:
        
        case 210:
        
        case 211:
        
        case 212:
        
        case 213:
        
        case 214:
        
        case 215:
        
        case 216:
        
        case 217:
        
        case 218:
        
        case 219:
        
        case 220:
        
        case 221:
        
        case 222:
        
        case 223:
        
        case 224:
        
        case 225:
        
        case 226:
        
        case 227:
        
        case 228:
        
        case 229:
        
        case 230:
        
        case 231:
        
        case 232:
        
        case 233:
        
        case 234:
        
        case 235:
        
        case 236:
        
        case 237:
        
        case 238:
        
        case 239:
        
        case 240:
        
        case 241:
        
        case 242:
        
        case 243:
        
        case 244:
        
        case 245:
        
        case 246:
        
        case 247:
        
        case 248:
        
        case 249:
        
        case 250:
        
        case 251:
        
        case 252:
        
        case 253:
        
        case 254:
        
        default:
          break;
      } 
      char c = '';
      int j = (paramInt2 & 0xFF) - c;
      if (j < 0)
        j += 256; 
      int k = ((paramInt2 & 0xFFFF) >>> 8) - c;
      if (k < 0)
        k += 256; 
      for (byte b = 0; b < arrayOfChar.length; b++) {
        int m = b % 2;
        if (m == 0) {
          arrayOfChar[b] = (char)(arrayOfChar[b] ^ j);
          j = ((j >>> 3 | j << 5) ^ arrayOfChar[b]) & 0xFF;
        } else {
          arrayOfChar[b] = (char)(arrayOfChar[b] ^ k);
          k = ((k >>> 3 | k << 5) ^ arrayOfChar[b]) & 0xFF;
        } 
      } 
      b[i] = (new String(arrayOfChar)).intern();
    } 
    return b[i];
  }
}


/* Location:              C:\Program Files\BurpSuitePro\burpsuite_pro.jar!\burp\Zdk.class
 * Java compiler version: 21 (65.0)
 * JD-Core Version:       1.1.3
 */