package burp;

import java.math.BigInteger;

class Zdm extends ClassLoader {
  static String ZJ;
  
  static Object ZA;
  
  private static final String[] a;
  
  private static final String[] b;
  
  static void Zr(Object[] paramArrayOfObject, Object paramObject) throws Throwable {}
  
  static boolean ZG(Object[] paramArrayOfObject, Object paramObject) throws Throwable {
    // Byte code:
    //   0: invokestatic ZK : ()Z
    //   3: istore_2
    //   4: new java/io/ByteArrayOutputStream
    //   7: dup
    //   8: invokespecial <init> : ()V
    //   11: astore_3
    //   12: getstatic burp/Zsun.Zu : Ljava/lang/String;
    //   15: astore #4
    //   17: iconst_0
    //   18: istore #5
    //   20: iload #5
    //   22: aload #4
    //   24: invokevirtual length : ()I
    //   27: if_icmpge -> 57
    //   30: aload_3
    //   31: aload #4
    //   33: iload #5
    //   35: iload #5
    //   37: iconst_2
    //   38: iadd
    //   39: invokevirtual substring : (II)Ljava/lang/String;
    //   42: bipush #16
    //   44: invokestatic parseInt : (Ljava/lang/String;I)I
    //   47: invokevirtual write : (I)V
    //   50: iinc #5, 2
    //   53: iload_2
    //   54: ifeq -> 20
    //   57: aload_3
    //   58: invokevirtual toByteArray : ()[B
    //   61: astore #5
    //   63: getstatic burp/Zlg1.ZH : Ljava/lang/Object;
    //   66: checkcast java/math/BigInteger
    //   69: invokevirtual toByteArray : ()[B
    //   72: astore #6
    //   74: sipush #256
    //   77: newarray byte
    //   79: astore #8
    //   81: sipush #256
    //   84: newarray int
    //   86: astore #9
    //   88: sipush #256
    //   91: newarray int
    //   93: astore #10
    //   95: sipush #256
    //   98: newarray int
    //   100: astore #11
    //   102: sipush #256
    //   105: newarray int
    //   107: astore #12
    //   109: bipush #10
    //   111: newarray int
    //   113: astore #13
    //   115: sipush #283
    //   118: istore #14
    //   120: iconst_0
    //   121: istore #16
    //   123: iload #16
    //   125: sipush #256
    //   128: if_icmpge -> 362
    //   131: sipush #-5325
    //   134: sipush #31429
    //   137: invokestatic a : (II)Ljava/lang/String;
    //   140: iload #16
    //   142: iconst_1
    //   143: iushr
    //   144: invokevirtual charAt : (I)C
    //   147: istore #25
    //   149: iload #16
    //   151: iconst_1
    //   152: iand
    //   153: ifne -> 168
    //   156: iload #25
    //   158: bipush #8
    //   160: iushr
    //   161: goto -> 170
    //   164: invokestatic a : (Ljava/lang/Throwable;)Ljava/lang/Throwable;
    //   167: athrow
    //   168: iload #25
    //   170: i2b
    //   171: sipush #255
    //   174: iand
    //   175: istore #15
    //   177: iload #16
    //   179: iconst_1
    //   180: ishl
    //   181: istore #17
    //   183: iload #17
    //   185: sipush #256
    //   188: if_icmplt -> 198
    //   191: iload #17
    //   193: iload #14
    //   195: ixor
    //   196: istore #17
    //   198: iload #17
    //   200: iconst_1
    //   201: ishl
    //   202: istore #18
    //   204: iload #18
    //   206: sipush #256
    //   209: if_icmplt -> 219
    //   212: iload #18
    //   214: iload #14
    //   216: ixor
    //   217: istore #18
    //   219: iload #18
    //   221: iconst_1
    //   222: ishl
    //   223: istore #19
    //   225: iload #19
    //   227: sipush #256
    //   230: if_icmplt -> 240
    //   233: iload #19
    //   235: iload #14
    //   237: ixor
    //   238: istore #19
    //   240: iload #19
    //   242: iload #16
    //   244: ixor
    //   245: istore #20
    //   247: iload #20
    //   249: iload #17
    //   251: ixor
    //   252: istore #21
    //   254: iload #20
    //   256: iload #18
    //   258: ixor
    //   259: istore #22
    //   261: iload #19
    //   263: iload #18
    //   265: ixor
    //   266: iload #17
    //   268: ixor
    //   269: istore #23
    //   271: aload #8
    //   273: iload #16
    //   275: iload #15
    //   277: i2b
    //   278: bastore
    //   279: aload #9
    //   281: iload #15
    //   283: iload #23
    //   285: bipush #24
    //   287: ishl
    //   288: iload #20
    //   290: bipush #16
    //   292: ishl
    //   293: ior
    //   294: iload #22
    //   296: bipush #8
    //   298: ishl
    //   299: ior
    //   300: iload #21
    //   302: ior
    //   303: dup
    //   304: istore #24
    //   306: iastore
    //   307: aload #10
    //   309: iload #15
    //   311: iload #24
    //   313: bipush #8
    //   315: iushr
    //   316: iload #24
    //   318: bipush #24
    //   320: ishl
    //   321: ior
    //   322: iastore
    //   323: aload #11
    //   325: iload #15
    //   327: iload #24
    //   329: bipush #16
    //   331: iushr
    //   332: iload #24
    //   334: bipush #16
    //   336: ishl
    //   337: ior
    //   338: iastore
    //   339: aload #12
    //   341: iload #15
    //   343: iload #24
    //   345: bipush #24
    //   347: iushr
    //   348: iload #24
    //   350: bipush #8
    //   352: ishl
    //   353: ior
    //   354: iastore
    //   355: iinc #16, 1
    //   358: iload_2
    //   359: ifeq -> 123
    //   362: iconst_1
    //   363: istore #25
    //   365: aload #13
    //   367: iconst_0
    //   368: iload #25
    //   370: bipush #24
    //   372: ishl
    //   373: iastore
    //   374: iconst_1
    //   375: istore #26
    //   377: iload #26
    //   379: bipush #10
    //   381: if_icmpge -> 422
    //   384: iload #25
    //   386: iconst_1
    //   387: ishl
    //   388: istore #25
    //   390: iload #25
    //   392: sipush #256
    //   395: if_icmplt -> 405
    //   398: iload #25
    //   400: iload #14
    //   402: ixor
    //   403: istore #25
    //   405: aload #13
    //   407: iload #26
    //   409: iload #25
    //   411: bipush #24
    //   413: ishl
    //   414: iastore
    //   415: iinc #26, 1
    //   418: iload_2
    //   419: ifeq -> 377
    //   422: iconst_4
    //   423: istore #26
    //   425: iload #26
    //   427: bipush #6
    //   429: iadd
    //   430: istore #27
    //   432: iconst_4
    //   433: iload #27
    //   435: iconst_1
    //   436: iadd
    //   437: imul
    //   438: istore #28
    //   440: iload #28
    //   442: newarray int
    //   444: astore #29
    //   446: iload #28
    //   448: newarray int
    //   450: astore #30
    //   452: iconst_0
    //   453: istore #25
    //   455: iconst_0
    //   456: istore #32
    //   458: iconst_0
    //   459: istore #33
    //   461: iload #32
    //   463: iload #26
    //   465: if_icmpge -> 533
    //   468: aload #29
    //   470: iload #32
    //   472: aload #5
    //   474: iload #33
    //   476: baload
    //   477: bipush #24
    //   479: ishl
    //   480: aload #5
    //   482: iload #33
    //   484: iconst_1
    //   485: iadd
    //   486: baload
    //   487: sipush #255
    //   490: iand
    //   491: bipush #16
    //   493: ishl
    //   494: ior
    //   495: aload #5
    //   497: iload #33
    //   499: iconst_2
    //   500: iadd
    //   501: baload
    //   502: sipush #255
    //   505: iand
    //   506: bipush #8
    //   508: ishl
    //   509: ior
    //   510: aload #5
    //   512: iload #33
    //   514: iconst_3
    //   515: iadd
    //   516: baload
    //   517: sipush #255
    //   520: iand
    //   521: ior
    //   522: iastore
    //   523: iinc #32, 1
    //   526: iinc #33, 4
    //   529: iload_2
    //   530: ifeq -> 461
    //   533: iload #26
    //   535: istore #32
    //   537: iconst_0
    //   538: istore #33
    //   540: iload #32
    //   542: iload #28
    //   544: if_icmpge -> 671
    //   547: aload #29
    //   549: iload #32
    //   551: iconst_1
    //   552: isub
    //   553: iaload
    //   554: istore #31
    //   556: iload #33
    //   558: ifne -> 645
    //   561: iload #26
    //   563: istore #33
    //   565: aload #8
    //   567: iload #31
    //   569: bipush #16
    //   571: iushr
    //   572: sipush #255
    //   575: iand
    //   576: baload
    //   577: bipush #24
    //   579: ishl
    //   580: aload #8
    //   582: iload #31
    //   584: bipush #8
    //   586: iushr
    //   587: sipush #255
    //   590: iand
    //   591: baload
    //   592: sipush #255
    //   595: iand
    //   596: bipush #16
    //   598: ishl
    //   599: ior
    //   600: aload #8
    //   602: iload #31
    //   604: sipush #255
    //   607: iand
    //   608: baload
    //   609: sipush #255
    //   612: iand
    //   613: bipush #8
    //   615: ishl
    //   616: ior
    //   617: aload #8
    //   619: iload #31
    //   621: bipush #24
    //   623: iushr
    //   624: baload
    //   625: sipush #255
    //   628: iand
    //   629: ior
    //   630: istore #31
    //   632: iload #31
    //   634: aload #13
    //   636: iload #25
    //   638: iinc #25, 1
    //   641: iaload
    //   642: ixor
    //   643: istore #31
    //   645: aload #29
    //   647: iload #32
    //   649: aload #29
    //   651: iload #32
    //   653: iload #26
    //   655: isub
    //   656: iaload
    //   657: iload #31
    //   659: ixor
    //   660: iastore
    //   661: iinc #32, 1
    //   664: iinc #33, -1
    //   667: iload_2
    //   668: ifeq -> 540
    //   671: iconst_0
    //   672: istore #32
    //   674: iconst_4
    //   675: iload #27
    //   677: imul
    //   678: istore #33
    //   680: aload #30
    //   682: iload #32
    //   684: aload #29
    //   686: iload #33
    //   688: iaload
    //   689: iastore
    //   690: aload #30
    //   692: iload #32
    //   694: iconst_1
    //   695: iadd
    //   696: aload #29
    //   698: iload #33
    //   700: iconst_1
    //   701: iadd
    //   702: iaload
    //   703: iastore
    //   704: aload #30
    //   706: iload #32
    //   708: iconst_2
    //   709: iadd
    //   710: aload #29
    //   712: iload #33
    //   714: iconst_2
    //   715: iadd
    //   716: iaload
    //   717: iastore
    //   718: aload #30
    //   720: iload #32
    //   722: iconst_3
    //   723: iadd
    //   724: aload #29
    //   726: iload #33
    //   728: iconst_3
    //   729: iadd
    //   730: iaload
    //   731: iastore
    //   732: iinc #32, 4
    //   735: iinc #33, -4
    //   738: iconst_1
    //   739: istore #35
    //   741: iload #35
    //   743: iload #27
    //   745: if_icmpge -> 1109
    //   748: aload #29
    //   750: iload #33
    //   752: iaload
    //   753: istore #34
    //   755: aload #30
    //   757: iload #32
    //   759: aload #9
    //   761: aload #8
    //   763: iload #34
    //   765: bipush #24
    //   767: iushr
    //   768: baload
    //   769: sipush #255
    //   772: iand
    //   773: iaload
    //   774: aload #10
    //   776: aload #8
    //   778: iload #34
    //   780: bipush #16
    //   782: iushr
    //   783: sipush #255
    //   786: iand
    //   787: baload
    //   788: sipush #255
    //   791: iand
    //   792: iaload
    //   793: ixor
    //   794: aload #11
    //   796: aload #8
    //   798: iload #34
    //   800: bipush #8
    //   802: iushr
    //   803: sipush #255
    //   806: iand
    //   807: baload
    //   808: sipush #255
    //   811: iand
    //   812: iaload
    //   813: ixor
    //   814: aload #12
    //   816: aload #8
    //   818: iload #34
    //   820: sipush #255
    //   823: iand
    //   824: baload
    //   825: sipush #255
    //   828: iand
    //   829: iaload
    //   830: ixor
    //   831: iastore
    //   832: aload #29
    //   834: iload #33
    //   836: iconst_1
    //   837: iadd
    //   838: iaload
    //   839: istore #34
    //   841: aload #30
    //   843: iload #32
    //   845: iconst_1
    //   846: iadd
    //   847: aload #9
    //   849: aload #8
    //   851: iload #34
    //   853: bipush #24
    //   855: iushr
    //   856: baload
    //   857: sipush #255
    //   860: iand
    //   861: iaload
    //   862: aload #10
    //   864: aload #8
    //   866: iload #34
    //   868: bipush #16
    //   870: iushr
    //   871: sipush #255
    //   874: iand
    //   875: baload
    //   876: sipush #255
    //   879: iand
    //   880: iaload
    //   881: ixor
    //   882: aload #11
    //   884: aload #8
    //   886: iload #34
    //   888: bipush #8
    //   890: iushr
    //   891: sipush #255
    //   894: iand
    //   895: baload
    //   896: sipush #255
    //   899: iand
    //   900: iaload
    //   901: ixor
    //   902: aload #12
    //   904: aload #8
    //   906: iload #34
    //   908: sipush #255
    //   911: iand
    //   912: baload
    //   913: sipush #255
    //   916: iand
    //   917: iaload
    //   918: ixor
    //   919: iastore
    //   920: aload #29
    //   922: iload #33
    //   924: iconst_2
    //   925: iadd
    //   926: iaload
    //   927: istore #34
    //   929: aload #30
    //   931: iload #32
    //   933: iconst_2
    //   934: iadd
    //   935: aload #9
    //   937: aload #8
    //   939: iload #34
    //   941: bipush #24
    //   943: iushr
    //   944: baload
    //   945: sipush #255
    //   948: iand
    //   949: iaload
    //   950: aload #10
    //   952: aload #8
    //   954: iload #34
    //   956: bipush #16
    //   958: iushr
    //   959: sipush #255
    //   962: iand
    //   963: baload
    //   964: sipush #255
    //   967: iand
    //   968: iaload
    //   969: ixor
    //   970: aload #11
    //   972: aload #8
    //   974: iload #34
    //   976: bipush #8
    //   978: iushr
    //   979: sipush #255
    //   982: iand
    //   983: baload
    //   984: sipush #255
    //   987: iand
    //   988: iaload
    //   989: ixor
    //   990: aload #12
    //   992: aload #8
    //   994: iload #34
    //   996: sipush #255
    //   999: iand
    //   1000: baload
    //   1001: sipush #255
    //   1004: iand
    //   1005: iaload
    //   1006: ixor
    //   1007: iastore
    //   1008: aload #29
    //   1010: iload #33
    //   1012: iconst_3
    //   1013: iadd
    //   1014: iaload
    //   1015: istore #34
    //   1017: aload #30
    //   1019: iload #32
    //   1021: iconst_3
    //   1022: iadd
    //   1023: aload #9
    //   1025: aload #8
    //   1027: iload #34
    //   1029: bipush #24
    //   1031: iushr
    //   1032: baload
    //   1033: sipush #255
    //   1036: iand
    //   1037: iaload
    //   1038: aload #10
    //   1040: aload #8
    //   1042: iload #34
    //   1044: bipush #16
    //   1046: iushr
    //   1047: sipush #255
    //   1050: iand
    //   1051: baload
    //   1052: sipush #255
    //   1055: iand
    //   1056: iaload
    //   1057: ixor
    //   1058: aload #11
    //   1060: aload #8
    //   1062: iload #34
    //   1064: bipush #8
    //   1066: iushr
    //   1067: sipush #255
    //   1070: iand
    //   1071: baload
    //   1072: sipush #255
    //   1075: iand
    //   1076: iaload
    //   1077: ixor
    //   1078: aload #12
    //   1080: aload #8
    //   1082: iload #34
    //   1084: sipush #255
    //   1087: iand
    //   1088: baload
    //   1089: sipush #255
    //   1092: iand
    //   1093: iaload
    //   1094: ixor
    //   1095: iastore
    //   1096: iinc #32, 4
    //   1099: iinc #33, -4
    //   1102: iinc #35, 1
    //   1105: iload_2
    //   1106: ifeq -> 741
    //   1109: aload #30
    //   1111: iload #32
    //   1113: aload #29
    //   1115: iload #33
    //   1117: iaload
    //   1118: iastore
    //   1119: aload #30
    //   1121: iload #32
    //   1123: iconst_1
    //   1124: iadd
    //   1125: aload #29
    //   1127: iload #33
    //   1129: iconst_1
    //   1130: iadd
    //   1131: iaload
    //   1132: iastore
    //   1133: aload #30
    //   1135: iload #32
    //   1137: iconst_2
    //   1138: iadd
    //   1139: aload #29
    //   1141: iload #33
    //   1143: iconst_2
    //   1144: iadd
    //   1145: iaload
    //   1146: iastore
    //   1147: aload #30
    //   1149: iload #32
    //   1151: iconst_3
    //   1152: iadd
    //   1153: aload #29
    //   1155: iload #33
    //   1157: iconst_3
    //   1158: iadd
    //   1159: iaload
    //   1160: iastore
    //   1161: iconst_0
    //   1162: newarray byte
    //   1164: astore #35
    //   1166: aload #6
    //   1168: arraylength
    //   1169: bipush #16
    //   1171: irem
    //   1172: ifeq -> 1196
    //   1175: new java/lang/Exception
    //   1178: dup
    //   1179: sipush #-5322
    //   1182: sipush #17194
    //   1185: invokestatic a : (II)Ljava/lang/String;
    //   1188: invokespecial <init> : (Ljava/lang/String;)V
    //   1191: athrow
    //   1192: invokestatic a : (Ljava/lang/Throwable;)Ljava/lang/Throwable;
    //   1195: athrow
    //   1196: bipush #10
    //   1198: istore #36
    //   1200: sipush #-5327
    //   1203: sipush #256
    //   1206: newarray byte
    //   1208: astore #37
    //   1210: sipush #-23721
    //   1213: sipush #256
    //   1216: newarray int
    //   1218: astore #38
    //   1220: sipush #256
    //   1223: newarray int
    //   1225: astore #39
    //   1227: sipush #256
    //   1230: newarray int
    //   1232: astore #40
    //   1234: sipush #256
    //   1237: newarray int
    //   1239: astore #41
    //   1241: sipush #283
    //   1244: istore #14
    //   1246: invokestatic a : (II)Ljava/lang/String;
    //   1249: astore #42
    //   1251: iconst_0
    //   1252: istore #16
    //   1254: iload #16
    //   1256: sipush #256
    //   1259: if_icmpge -> 1486
    //   1262: aload #42
    //   1264: iload #16
    //   1266: iconst_1
    //   1267: iushr
    //   1268: invokevirtual charAt : (I)C
    //   1271: istore #43
    //   1273: iload #16
    //   1275: iconst_1
    //   1276: iand
    //   1277: ifne -> 1292
    //   1280: iload #43
    //   1282: bipush #8
    //   1284: iushr
    //   1285: goto -> 1294
    //   1288: invokestatic a : (Ljava/lang/Throwable;)Ljava/lang/Throwable;
    //   1291: athrow
    //   1292: iload #43
    //   1294: i2b
    //   1295: sipush #255
    //   1298: iand
    //   1299: istore #15
    //   1301: iload #16
    //   1303: iconst_1
    //   1304: ishl
    //   1305: istore #17
    //   1307: iload #17
    //   1309: sipush #256
    //   1312: if_icmplt -> 1322
    //   1315: iload #17
    //   1317: iload #14
    //   1319: ixor
    //   1320: istore #17
    //   1322: iload #17
    //   1324: iconst_1
    //   1325: ishl
    //   1326: istore #18
    //   1328: iload #18
    //   1330: sipush #256
    //   1333: if_icmplt -> 1343
    //   1336: iload #18
    //   1338: iload #14
    //   1340: ixor
    //   1341: istore #18
    //   1343: iload #18
    //   1345: iconst_1
    //   1346: ishl
    //   1347: istore #19
    //   1349: iload #19
    //   1351: sipush #256
    //   1354: if_icmplt -> 1364
    //   1357: iload #19
    //   1359: iload #14
    //   1361: ixor
    //   1362: istore #19
    //   1364: iload #19
    //   1366: iload #16
    //   1368: ixor
    //   1369: istore #20
    //   1371: iload #20
    //   1373: iload #17
    //   1375: ixor
    //   1376: istore #21
    //   1378: iload #20
    //   1380: iload #18
    //   1382: ixor
    //   1383: istore #22
    //   1385: iload #19
    //   1387: iload #18
    //   1389: ixor
    //   1390: iload #17
    //   1392: ixor
    //   1393: istore #23
    //   1395: aload #37
    //   1397: iload #15
    //   1399: iload #16
    //   1401: i2b
    //   1402: bastore
    //   1403: aload #38
    //   1405: iload #15
    //   1407: iload #23
    //   1409: bipush #24
    //   1411: ishl
    //   1412: iload #20
    //   1414: bipush #16
    //   1416: ishl
    //   1417: ior
    //   1418: iload #22
    //   1420: bipush #8
    //   1422: ishl
    //   1423: ior
    //   1424: iload #21
    //   1426: ior
    //   1427: dup
    //   1428: istore #24
    //   1430: iastore
    //   1431: aload #39
    //   1433: iload #15
    //   1435: iload #24
    //   1437: bipush #8
    //   1439: iushr
    //   1440: iload #24
    //   1442: bipush #24
    //   1444: ishl
    //   1445: ior
    //   1446: iastore
    //   1447: aload #40
    //   1449: iload #15
    //   1451: iload #24
    //   1453: bipush #16
    //   1455: iushr
    //   1456: iload #24
    //   1458: bipush #16
    //   1460: ishl
    //   1461: ior
    //   1462: iastore
    //   1463: aload #41
    //   1465: iload #15
    //   1467: iload #24
    //   1469: bipush #24
    //   1471: iushr
    //   1472: iload #24
    //   1474: bipush #8
    //   1476: ishl
    //   1477: ior
    //   1478: iastore
    //   1479: iinc #16, 1
    //   1482: iload_2
    //   1483: ifeq -> 1254
    //   1486: aload #6
    //   1488: arraylength
    //   1489: newarray byte
    //   1491: astore #43
    //   1493: iconst_0
    //   1494: istore #44
    //   1496: iload #44
    //   1498: aload #6
    //   1500: arraylength
    //   1501: bipush #16
    //   1503: idiv
    //   1504: if_icmpge -> 2418
    //   1507: bipush #16
    //   1509: newarray byte
    //   1511: astore #45
    //   1513: bipush #16
    //   1515: newarray byte
    //   1517: astore #46
    //   1519: iconst_0
    //   1520: istore #47
    //   1522: iload #47
    //   1524: bipush #16
    //   1526: if_icmpge -> 1552
    //   1529: aload #45
    //   1531: iload #47
    //   1533: aload #6
    //   1535: iload #47
    //   1537: iload #44
    //   1539: bipush #16
    //   1541: imul
    //   1542: iadd
    //   1543: baload
    //   1544: bastore
    //   1545: iinc #47, 1
    //   1548: iload_2
    //   1549: ifeq -> 1522
    //   1552: iconst_0
    //   1553: istore #47
    //   1555: aload #45
    //   1557: iconst_0
    //   1558: baload
    //   1559: bipush #24
    //   1561: ishl
    //   1562: aload #45
    //   1564: iconst_1
    //   1565: baload
    //   1566: sipush #255
    //   1569: iand
    //   1570: bipush #16
    //   1572: ishl
    //   1573: ior
    //   1574: aload #45
    //   1576: iconst_2
    //   1577: baload
    //   1578: sipush #255
    //   1581: iand
    //   1582: bipush #8
    //   1584: ishl
    //   1585: ior
    //   1586: aload #45
    //   1588: iconst_3
    //   1589: baload
    //   1590: sipush #255
    //   1593: iand
    //   1594: ior
    //   1595: aload #30
    //   1597: iconst_0
    //   1598: iaload
    //   1599: ixor
    //   1600: istore #49
    //   1602: aload #45
    //   1604: iconst_4
    //   1605: baload
    //   1606: bipush #24
    //   1608: ishl
    //   1609: aload #45
    //   1611: iconst_5
    //   1612: baload
    //   1613: sipush #255
    //   1616: iand
    //   1617: bipush #16
    //   1619: ishl
    //   1620: ior
    //   1621: aload #45
    //   1623: bipush #6
    //   1625: baload
    //   1626: sipush #255
    //   1629: iand
    //   1630: bipush #8
    //   1632: ishl
    //   1633: ior
    //   1634: aload #45
    //   1636: bipush #7
    //   1638: baload
    //   1639: sipush #255
    //   1642: iand
    //   1643: ior
    //   1644: aload #30
    //   1646: iconst_1
    //   1647: iaload
    //   1648: ixor
    //   1649: istore #50
    //   1651: aload #45
    //   1653: bipush #8
    //   1655: baload
    //   1656: bipush #24
    //   1658: ishl
    //   1659: aload #45
    //   1661: bipush #9
    //   1663: baload
    //   1664: sipush #255
    //   1667: iand
    //   1668: bipush #16
    //   1670: ishl
    //   1671: ior
    //   1672: aload #45
    //   1674: bipush #10
    //   1676: baload
    //   1677: sipush #255
    //   1680: iand
    //   1681: bipush #8
    //   1683: ishl
    //   1684: ior
    //   1685: aload #45
    //   1687: bipush #11
    //   1689: baload
    //   1690: sipush #255
    //   1693: iand
    //   1694: ior
    //   1695: aload #30
    //   1697: iconst_2
    //   1698: iaload
    //   1699: ixor
    //   1700: istore #51
    //   1702: aload #45
    //   1704: bipush #12
    //   1706: baload
    //   1707: bipush #24
    //   1709: ishl
    //   1710: aload #45
    //   1712: bipush #13
    //   1714: baload
    //   1715: sipush #255
    //   1718: iand
    //   1719: bipush #16
    //   1721: ishl
    //   1722: ior
    //   1723: aload #45
    //   1725: bipush #14
    //   1727: baload
    //   1728: sipush #255
    //   1731: iand
    //   1732: bipush #8
    //   1734: ishl
    //   1735: ior
    //   1736: aload #45
    //   1738: bipush #15
    //   1740: baload
    //   1741: sipush #255
    //   1744: iand
    //   1745: ior
    //   1746: aload #30
    //   1748: iconst_3
    //   1749: iaload
    //   1750: ixor
    //   1751: istore #52
    //   1753: iconst_1
    //   1754: istore #53
    //   1756: iload #53
    //   1758: iload #36
    //   1760: if_icmpge -> 2003
    //   1763: iinc #47, 4
    //   1766: aload #38
    //   1768: iload #49
    //   1770: bipush #24
    //   1772: iushr
    //   1773: iaload
    //   1774: aload #39
    //   1776: iload #52
    //   1778: bipush #16
    //   1780: iushr
    //   1781: sipush #255
    //   1784: iand
    //   1785: iaload
    //   1786: ixor
    //   1787: aload #40
    //   1789: iload #51
    //   1791: bipush #8
    //   1793: iushr
    //   1794: sipush #255
    //   1797: iand
    //   1798: iaload
    //   1799: ixor
    //   1800: aload #41
    //   1802: iload #50
    //   1804: sipush #255
    //   1807: iand
    //   1808: iaload
    //   1809: ixor
    //   1810: aload #30
    //   1812: iload #47
    //   1814: iaload
    //   1815: ixor
    //   1816: istore #54
    //   1818: aload #38
    //   1820: iload #50
    //   1822: bipush #24
    //   1824: iushr
    //   1825: iaload
    //   1826: aload #39
    //   1828: iload #49
    //   1830: bipush #16
    //   1832: iushr
    //   1833: sipush #255
    //   1836: iand
    //   1837: iaload
    //   1838: ixor
    //   1839: aload #40
    //   1841: iload #52
    //   1843: bipush #8
    //   1845: iushr
    //   1846: sipush #255
    //   1849: iand
    //   1850: iaload
    //   1851: ixor
    //   1852: aload #41
    //   1854: iload #51
    //   1856: sipush #255
    //   1859: iand
    //   1860: iaload
    //   1861: ixor
    //   1862: aload #30
    //   1864: iload #47
    //   1866: iconst_1
    //   1867: iadd
    //   1868: iaload
    //   1869: ixor
    //   1870: istore #55
    //   1872: aload #38
    //   1874: iload #51
    //   1876: bipush #24
    //   1878: iushr
    //   1879: iaload
    //   1880: aload #39
    //   1882: iload #50
    //   1884: bipush #16
    //   1886: iushr
    //   1887: sipush #255
    //   1890: iand
    //   1891: iaload
    //   1892: ixor
    //   1893: aload #40
    //   1895: iload #49
    //   1897: bipush #8
    //   1899: iushr
    //   1900: sipush #255
    //   1903: iand
    //   1904: iaload
    //   1905: ixor
    //   1906: aload #41
    //   1908: iload #52
    //   1910: sipush #255
    //   1913: iand
    //   1914: iaload
    //   1915: ixor
    //   1916: aload #30
    //   1918: iload #47
    //   1920: iconst_2
    //   1921: iadd
    //   1922: iaload
    //   1923: ixor
    //   1924: istore #56
    //   1926: aload #38
    //   1928: iload #52
    //   1930: bipush #24
    //   1932: iushr
    //   1933: iaload
    //   1934: aload #39
    //   1936: iload #51
    //   1938: bipush #16
    //   1940: iushr
    //   1941: sipush #255
    //   1944: iand
    //   1945: iaload
    //   1946: ixor
    //   1947: aload #40
    //   1949: iload #50
    //   1951: bipush #8
    //   1953: iushr
    //   1954: sipush #255
    //   1957: iand
    //   1958: iaload
    //   1959: ixor
    //   1960: aload #41
    //   1962: iload #49
    //   1964: sipush #255
    //   1967: iand
    //   1968: iaload
    //   1969: ixor
    //   1970: aload #30
    //   1972: iload #47
    //   1974: iconst_3
    //   1975: iadd
    //   1976: iaload
    //   1977: ixor
    //   1978: istore #57
    //   1980: iload #54
    //   1982: istore #49
    //   1984: iload #55
    //   1986: istore #50
    //   1988: iload #56
    //   1990: istore #51
    //   1992: iload #57
    //   1994: istore #52
    //   1996: iinc #53, 1
    //   1999: iload_2
    //   2000: ifeq -> 1756
    //   2003: iinc #47, 4
    //   2006: aload #30
    //   2008: iload #47
    //   2010: iaload
    //   2011: istore #48
    //   2013: aload #46
    //   2015: iconst_0
    //   2016: aload #37
    //   2018: iload #49
    //   2020: bipush #24
    //   2022: iushr
    //   2023: baload
    //   2024: iload #48
    //   2026: bipush #24
    //   2028: iushr
    //   2029: ixor
    //   2030: i2b
    //   2031: bastore
    //   2032: aload #46
    //   2034: iconst_1
    //   2035: aload #37
    //   2037: iload #52
    //   2039: bipush #16
    //   2041: iushr
    //   2042: sipush #255
    //   2045: iand
    //   2046: baload
    //   2047: iload #48
    //   2049: bipush #16
    //   2051: iushr
    //   2052: ixor
    //   2053: i2b
    //   2054: bastore
    //   2055: aload #46
    //   2057: iconst_2
    //   2058: aload #37
    //   2060: iload #51
    //   2062: bipush #8
    //   2064: iushr
    //   2065: sipush #255
    //   2068: iand
    //   2069: baload
    //   2070: iload #48
    //   2072: bipush #8
    //   2074: iushr
    //   2075: ixor
    //   2076: i2b
    //   2077: bastore
    //   2078: aload #46
    //   2080: iconst_3
    //   2081: aload #37
    //   2083: iload #50
    //   2085: sipush #255
    //   2088: iand
    //   2089: baload
    //   2090: iload #48
    //   2092: ixor
    //   2093: i2b
    //   2094: bastore
    //   2095: aload #30
    //   2097: iload #47
    //   2099: iconst_1
    //   2100: iadd
    //   2101: iaload
    //   2102: istore #48
    //   2104: aload #46
    //   2106: iconst_4
    //   2107: aload #37
    //   2109: iload #50
    //   2111: bipush #24
    //   2113: iushr
    //   2114: baload
    //   2115: iload #48
    //   2117: bipush #24
    //   2119: iushr
    //   2120: ixor
    //   2121: i2b
    //   2122: bastore
    //   2123: aload #46
    //   2125: iconst_5
    //   2126: aload #37
    //   2128: iload #49
    //   2130: bipush #16
    //   2132: iushr
    //   2133: sipush #255
    //   2136: iand
    //   2137: baload
    //   2138: iload #48
    //   2140: bipush #16
    //   2142: iushr
    //   2143: ixor
    //   2144: i2b
    //   2145: bastore
    //   2146: aload #46
    //   2148: bipush #6
    //   2150: aload #37
    //   2152: iload #52
    //   2154: bipush #8
    //   2156: iushr
    //   2157: sipush #255
    //   2160: iand
    //   2161: baload
    //   2162: iload #48
    //   2164: bipush #8
    //   2166: iushr
    //   2167: ixor
    //   2168: i2b
    //   2169: bastore
    //   2170: aload #46
    //   2172: bipush #7
    //   2174: aload #37
    //   2176: iload #51
    //   2178: sipush #255
    //   2181: iand
    //   2182: baload
    //   2183: iload #48
    //   2185: ixor
    //   2186: i2b
    //   2187: bastore
    //   2188: aload #30
    //   2190: iload #47
    //   2192: iconst_2
    //   2193: iadd
    //   2194: iaload
    //   2195: istore #48
    //   2197: aload #46
    //   2199: bipush #8
    //   2201: aload #37
    //   2203: iload #51
    //   2205: bipush #24
    //   2207: iushr
    //   2208: baload
    //   2209: iload #48
    //   2211: bipush #24
    //   2213: iushr
    //   2214: ixor
    //   2215: i2b
    //   2216: bastore
    //   2217: aload #46
    //   2219: bipush #9
    //   2221: aload #37
    //   2223: iload #50
    //   2225: bipush #16
    //   2227: iushr
    //   2228: sipush #255
    //   2231: iand
    //   2232: baload
    //   2233: iload #48
    //   2235: bipush #16
    //   2237: iushr
    //   2238: ixor
    //   2239: i2b
    //   2240: bastore
    //   2241: aload #46
    //   2243: bipush #10
    //   2245: aload #37
    //   2247: iload #49
    //   2249: bipush #8
    //   2251: iushr
    //   2252: sipush #255
    //   2255: iand
    //   2256: baload
    //   2257: iload #48
    //   2259: bipush #8
    //   2261: iushr
    //   2262: ixor
    //   2263: i2b
    //   2264: bastore
    //   2265: aload #46
    //   2267: bipush #11
    //   2269: aload #37
    //   2271: iload #52
    //   2273: sipush #255
    //   2276: iand
    //   2277: baload
    //   2278: iload #48
    //   2280: ixor
    //   2281: i2b
    //   2282: bastore
    //   2283: aload #30
    //   2285: iload #47
    //   2287: iconst_3
    //   2288: iadd
    //   2289: iaload
    //   2290: istore #48
    //   2292: aload #46
    //   2294: bipush #12
    //   2296: aload #37
    //   2298: iload #52
    //   2300: bipush #24
    //   2302: iushr
    //   2303: baload
    //   2304: iload #48
    //   2306: bipush #24
    //   2308: iushr
    //   2309: ixor
    //   2310: i2b
    //   2311: bastore
    //   2312: aload #46
    //   2314: bipush #13
    //   2316: aload #37
    //   2318: iload #51
    //   2320: bipush #16
    //   2322: iushr
    //   2323: sipush #255
    //   2326: iand
    //   2327: baload
    //   2328: iload #48
    //   2330: bipush #16
    //   2332: iushr
    //   2333: ixor
    //   2334: i2b
    //   2335: bastore
    //   2336: aload #46
    //   2338: bipush #14
    //   2340: aload #37
    //   2342: iload #50
    //   2344: bipush #8
    //   2346: iushr
    //   2347: sipush #255
    //   2350: iand
    //   2351: baload
    //   2352: iload #48
    //   2354: bipush #8
    //   2356: iushr
    //   2357: ixor
    //   2358: i2b
    //   2359: bastore
    //   2360: aload #46
    //   2362: bipush #15
    //   2364: aload #37
    //   2366: iload #49
    //   2368: sipush #255
    //   2371: iand
    //   2372: baload
    //   2373: iload #48
    //   2375: ixor
    //   2376: i2b
    //   2377: bastore
    //   2378: iconst_0
    //   2379: istore #53
    //   2381: iload #53
    //   2383: bipush #16
    //   2385: if_icmpge -> 2411
    //   2388: aload #43
    //   2390: iload #53
    //   2392: iload #44
    //   2394: bipush #16
    //   2396: imul
    //   2397: iadd
    //   2398: aload #46
    //   2400: iload #53
    //   2402: baload
    //   2403: bastore
    //   2404: iinc #53, 1
    //   2407: iload_2
    //   2408: ifeq -> 2381
    //   2411: iinc #44, 1
    //   2414: iload_2
    //   2415: ifeq -> 1496
    //   2418: aload #43
    //   2420: arraylength
    //   2421: ifle -> 2502
    //   2424: aload #43
    //   2426: aload #43
    //   2428: arraylength
    //   2429: iconst_1
    //   2430: isub
    //   2431: baload
    //   2432: istore #44
    //   2434: iload #44
    //   2436: bipush #16
    //   2438: if_icmple -> 2449
    //   2441: aload #43
    //   2443: astore #35
    //   2445: iload_2
    //   2446: ifeq -> 2502
    //   2449: aload #43
    //   2451: arraylength
    //   2452: iload #44
    //   2454: isub
    //   2455: newarray byte
    //   2457: astore #35
    //   2459: iconst_0
    //   2460: istore #45
    //   2462: iload #45
    //   2464: aload #35
    //   2466: arraylength
    //   2467: if_icmpge -> 2502
    //   2470: iload #45
    //   2472: aload #43
    //   2474: arraylength
    //   2475: if_icmpge -> 2502
    //   2478: aload #35
    //   2480: iload #45
    //   2482: aload #43
    //   2484: iload #45
    //   2486: baload
    //   2487: bastore
    //   2488: iinc #45, 1
    //   2491: iload_2
    //   2492: ifeq -> 2462
    //   2495: goto -> 2502
    //   2498: invokestatic a : (Ljava/lang/Throwable;)Ljava/lang/Throwable;
    //   2501: athrow
    //   2502: aload #35
    //   2504: astore #7
    //   2506: new java/math/BigInteger
    //   2509: dup
    //   2510: aload #7
    //   2512: invokespecial <init> : ([B)V
    //   2515: invokevirtual abs : ()Ljava/math/BigInteger;
    //   2518: putstatic burp/Zl3l.Zv : Ljava/lang/Object;
    //   2521: getstatic burp/Zz3k.Zz : Ljava/lang/Object;
    //   2524: checkcast java/math/BigInteger
    //   2527: invokevirtual toByteArray : ()[B
    //   2530: astore_3
    //   2531: aload_3
    //   2532: arraylength
    //   2533: iconst_2
    //   2534: iadd
    //   2535: newarray byte
    //   2537: astore #5
    //   2539: iconst_0
    //   2540: istore #6
    //   2542: iload #6
    //   2544: aload_3
    //   2545: arraylength
    //   2546: if_icmpge -> 2565
    //   2549: aload #5
    //   2551: iload #6
    //   2553: aload_3
    //   2554: iload #6
    //   2556: baload
    //   2557: bastore
    //   2558: iinc #6, 1
    //   2561: iload_2
    //   2562: ifeq -> 2542
    //   2565: aload #5
    //   2567: arraylength
    //   2568: iconst_3
    //   2569: idiv
    //   2570: iconst_4
    //   2571: imul
    //   2572: newarray byte
    //   2574: astore #4
    //   2576: iconst_0
    //   2577: istore #6
    //   2579: iconst_0
    //   2580: istore #7
    //   2582: iload #6
    //   2584: aload_3
    //   2585: arraylength
    //   2586: if_icmpge -> 2697
    //   2589: aload #4
    //   2591: iload #7
    //   2593: aload #5
    //   2595: iload #6
    //   2597: baload
    //   2598: iconst_2
    //   2599: iushr
    //   2600: bipush #63
    //   2602: iand
    //   2603: i2b
    //   2604: bastore
    //   2605: aload #4
    //   2607: iload #7
    //   2609: iconst_1
    //   2610: iadd
    //   2611: aload #5
    //   2613: iload #6
    //   2615: iconst_1
    //   2616: iadd
    //   2617: baload
    //   2618: iconst_4
    //   2619: iushr
    //   2620: bipush #15
    //   2622: iand
    //   2623: aload #5
    //   2625: iload #6
    //   2627: baload
    //   2628: iconst_4
    //   2629: ishl
    //   2630: bipush #63
    //   2632: iand
    //   2633: ior
    //   2634: i2b
    //   2635: bastore
    //   2636: aload #4
    //   2638: iload #7
    //   2640: iconst_2
    //   2641: iadd
    //   2642: aload #5
    //   2644: iload #6
    //   2646: iconst_2
    //   2647: iadd
    //   2648: baload
    //   2649: bipush #6
    //   2651: iushr
    //   2652: iconst_3
    //   2653: iand
    //   2654: aload #5
    //   2656: iload #6
    //   2658: iconst_1
    //   2659: iadd
    //   2660: baload
    //   2661: iconst_2
    //   2662: ishl
    //   2663: bipush #63
    //   2665: iand
    //   2666: ior
    //   2667: i2b
    //   2668: bastore
    //   2669: aload #4
    //   2671: iload #7
    //   2673: iconst_3
    //   2674: iadd
    //   2675: aload #5
    //   2677: iload #6
    //   2679: iconst_2
    //   2680: iadd
    //   2681: baload
    //   2682: bipush #63
    //   2684: iand
    //   2685: i2b
    //   2686: bastore
    //   2687: iinc #6, 3
    //   2690: iinc #7, 4
    //   2693: iload_2
    //   2694: ifeq -> 2582
    //   2697: iconst_0
    //   2698: istore #6
    //   2700: iload #6
    //   2702: aload #4
    //   2704: arraylength
    //   2705: if_icmpge -> 2889
    //   2708: aload #4
    //   2710: iload #6
    //   2712: baload
    //   2713: bipush #26
    //   2715: if_icmpge -> 2743
    //   2718: aload #4
    //   2720: iload #6
    //   2722: aload #4
    //   2724: iload #6
    //   2726: baload
    //   2727: bipush #65
    //   2729: iadd
    //   2730: i2b
    //   2731: bastore
    //   2732: iload_2
    //   2733: ifeq -> 2882
    //   2736: goto -> 2743
    //   2739: invokestatic a : (Ljava/lang/Throwable;)Ljava/lang/Throwable;
    //   2742: athrow
    //   2743: aload #4
    //   2745: iload #6
    //   2747: baload
    //   2748: bipush #52
    //   2750: if_icmpge -> 2788
    //   2753: goto -> 2760
    //   2756: invokestatic a : (Ljava/lang/Throwable;)Ljava/lang/Throwable;
    //   2759: athrow
    //   2760: aload #4
    //   2762: iload #6
    //   2764: aload #4
    //   2766: iload #6
    //   2768: baload
    //   2769: bipush #97
    //   2771: iadd
    //   2772: bipush #26
    //   2774: isub
    //   2775: i2b
    //   2776: bastore
    //   2777: iload_2
    //   2778: ifeq -> 2882
    //   2781: goto -> 2788
    //   2784: invokestatic a : (Ljava/lang/Throwable;)Ljava/lang/Throwable;
    //   2787: athrow
    //   2788: aload #4
    //   2790: iload #6
    //   2792: baload
    //   2793: bipush #62
    //   2795: if_icmpge -> 2833
    //   2798: goto -> 2805
    //   2801: invokestatic a : (Ljava/lang/Throwable;)Ljava/lang/Throwable;
    //   2804: athrow
    //   2805: aload #4
    //   2807: iload #6
    //   2809: aload #4
    //   2811: iload #6
    //   2813: baload
    //   2814: bipush #48
    //   2816: iadd
    //   2817: bipush #52
    //   2819: isub
    //   2820: i2b
    //   2821: bastore
    //   2822: iload_2
    //   2823: ifeq -> 2882
    //   2826: goto -> 2833
    //   2829: invokestatic a : (Ljava/lang/Throwable;)Ljava/lang/Throwable;
    //   2832: athrow
    //   2833: aload #4
    //   2835: iload #6
    //   2837: baload
    //   2838: bipush #63
    //   2840: if_icmpge -> 2868
    //   2843: goto -> 2850
    //   2846: invokestatic a : (Ljava/lang/Throwable;)Ljava/lang/Throwable;
    //   2849: athrow
    //   2850: aload #4
    //   2852: iload #6
    //   2854: bipush #43
    //   2856: bastore
    //   2857: iload_2
    //   2858: ifeq -> 2882
    //   2861: goto -> 2868
    //   2864: invokestatic a : (Ljava/lang/Throwable;)Ljava/lang/Throwable;
    //   2867: athrow
    //   2868: aload #4
    //   2870: iload #6
    //   2872: bipush #47
    //   2874: bastore
    //   2875: goto -> 2882
    //   2878: invokestatic a : (Ljava/lang/Throwable;)Ljava/lang/Throwable;
    //   2881: athrow
    //   2882: iinc #6, 1
    //   2885: iload_2
    //   2886: ifeq -> 2700
    //   2889: aload #4
    //   2891: arraylength
    //   2892: iconst_1
    //   2893: isub
    //   2894: istore #6
    //   2896: iload #6
    //   2898: aload_3
    //   2899: arraylength
    //   2900: iconst_4
    //   2901: imul
    //   2902: iconst_3
    //   2903: idiv
    //   2904: if_icmple -> 2921
    //   2907: aload #4
    //   2909: iload #6
    //   2911: bipush #61
    //   2913: bastore
    //   2914: iinc #6, -1
    //   2917: iload_2
    //   2918: ifeq -> 2896
    //   2921: new java/math/BigInteger
    //   2924: dup
    //   2925: aload #4
    //   2927: invokespecial <init> : ([B)V
    //   2930: invokevirtual abs : ()Ljava/math/BigInteger;
    //   2933: putstatic burp/Zrj3.ZA : Ljava/lang/Object;
    //   2936: new java/lang/StringBuilder
    //   2939: dup
    //   2940: invokespecial <init> : ()V
    //   2943: astore_3
    //   2944: iconst_0
    //   2945: istore #4
    //   2947: iload #4
    //   2949: bipush #32
    //   2951: if_icmpge -> 4287
    //   2954: iload #4
    //   2956: tableswitch default -> 4280, 0 -> 3100, 1 -> 3137, 2 -> 3174, 3 -> 3211, 4 -> 3248, 5 -> 3285, 6 -> 3322, 7 -> 3359, 8 -> 3396, 9 -> 3433, 10 -> 3470, 11 -> 3507, 12 -> 3544, 13 -> 3581, 14 -> 3618, 15 -> 3655, 16 -> 3692, 17 -> 3729, 18 -> 3766, 19 -> 3803, 20 -> 3840, 21 -> 3877, 22 -> 3914, 23 -> 3951, 24 -> 3988, 25 -> 4025, 26 -> 4062, 27 -> 4099, 28 -> 4136, 29 -> 4173, 30 -> 4210, 31 -> 4247
    //   3100: aload_3
    //   3101: getstatic burp/Zgyk.ZB : Ljava/lang/String;
    //   3104: getstatic burp/Zl3l.Zv : Ljava/lang/Object;
    //   3107: checkcast java/math/BigInteger
    //   3110: invokevirtual intValue : ()I
    //   3113: bipush #32
    //   3115: irem
    //   3116: invokestatic abs : (I)I
    //   3119: invokevirtual charAt : (I)C
    //   3122: invokevirtual append : (C)Ljava/lang/StringBuilder;
    //   3125: pop
    //   3126: iload_2
    //   3127: ifeq -> 4280
    //   3130: goto -> 3137
    //   3133: invokestatic a : (Ljava/lang/Throwable;)Ljava/lang/Throwable;
    //   3136: athrow
    //   3137: aload_3
    //   3138: getstatic burp/Zlzo.Zs : Ljava/lang/String;
    //   3141: getstatic burp/Zr0.ZX : Ljava/lang/Object;
    //   3144: checkcast java/math/BigInteger
    //   3147: invokevirtual intValue : ()I
    //   3150: bipush #32
    //   3152: irem
    //   3153: invokestatic abs : (I)I
    //   3156: invokevirtual charAt : (I)C
    //   3159: invokevirtual append : (C)Ljava/lang/StringBuilder;
    //   3162: pop
    //   3163: iload_2
    //   3164: ifeq -> 4280
    //   3167: goto -> 3174
    //   3170: invokestatic a : (Ljava/lang/Throwable;)Ljava/lang/Throwable;
    //   3173: athrow
    //   3174: aload_3
    //   3175: getstatic burp/Zeu2.ZK : Ljava/lang/String;
    //   3178: getstatic burp/Zeud.Zs : Ljava/lang/Object;
    //   3181: checkcast java/math/BigInteger
    //   3184: invokevirtual intValue : ()I
    //   3187: bipush #32
    //   3189: irem
    //   3190: invokestatic abs : (I)I
    //   3193: invokevirtual charAt : (I)C
    //   3196: invokevirtual append : (C)Ljava/lang/StringBuilder;
    //   3199: pop
    //   3200: iload_2
    //   3201: ifeq -> 4280
    //   3204: goto -> 3211
    //   3207: invokestatic a : (Ljava/lang/Throwable;)Ljava/lang/Throwable;
    //   3210: athrow
    //   3211: aload_3
    //   3212: getstatic burp/Zlxm.Zv : Ljava/lang/String;
    //   3215: getstatic burp/Zgvl.ZK : Ljava/lang/Object;
    //   3218: checkcast java/math/BigInteger
    //   3221: invokevirtual intValue : ()I
    //   3224: bipush #32
    //   3226: irem
    //   3227: invokestatic abs : (I)I
    //   3230: invokevirtual charAt : (I)C
    //   3233: invokevirtual append : (C)Ljava/lang/StringBuilder;
    //   3236: pop
    //   3237: iload_2
    //   3238: ifeq -> 4280
    //   3241: goto -> 3248
    //   3244: invokestatic a : (Ljava/lang/Throwable;)Ljava/lang/Throwable;
    //   3247: athrow
    //   3248: aload_3
    //   3249: getstatic burp/Zttq.ZO : Ljava/lang/String;
    //   3252: getstatic burp/Zry7.ZZ : Ljava/lang/Object;
    //   3255: checkcast java/math/BigInteger
    //   3258: invokevirtual intValue : ()I
    //   3261: bipush #32
    //   3263: irem
    //   3264: invokestatic abs : (I)I
    //   3267: invokevirtual charAt : (I)C
    //   3270: invokevirtual append : (C)Ljava/lang/StringBuilder;
    //   3273: pop
    //   3274: iload_2
    //   3275: ifeq -> 4280
    //   3278: goto -> 3285
    //   3281: invokestatic a : (Ljava/lang/Throwable;)Ljava/lang/Throwable;
    //   3284: athrow
    //   3285: aload_3
    //   3286: getstatic burp/Zlxm.Zv : Ljava/lang/String;
    //   3289: getstatic burp/Zgw7.Zi : Ljava/lang/Object;
    //   3292: checkcast java/math/BigInteger
    //   3295: invokevirtual intValue : ()I
    //   3298: bipush #32
    //   3300: irem
    //   3301: invokestatic abs : (I)I
    //   3304: invokevirtual charAt : (I)C
    //   3307: invokevirtual append : (C)Ljava/lang/StringBuilder;
    //   3310: pop
    //   3311: iload_2
    //   3312: ifeq -> 4280
    //   3315: goto -> 3322
    //   3318: invokestatic a : (Ljava/lang/Throwable;)Ljava/lang/Throwable;
    //   3321: athrow
    //   3322: aload_3
    //   3323: getstatic burp/Ze_b.ZX : Ljava/lang/String;
    //   3326: getstatic burp/Zezn.Zh : Ljava/lang/Object;
    //   3329: checkcast java/math/BigInteger
    //   3332: invokevirtual intValue : ()I
    //   3335: bipush #32
    //   3337: irem
    //   3338: invokestatic abs : (I)I
    //   3341: invokevirtual charAt : (I)C
    //   3344: invokevirtual append : (C)Ljava/lang/StringBuilder;
    //   3347: pop
    //   3348: iload_2
    //   3349: ifeq -> 4280
    //   3352: goto -> 3359
    //   3355: invokestatic a : (Ljava/lang/Throwable;)Ljava/lang/Throwable;
    //   3358: athrow
    //   3359: aload_3
    //   3360: getstatic burp/Zrd0.Zk : Ljava/lang/String;
    //   3363: getstatic burp/Zz3k.Zz : Ljava/lang/Object;
    //   3366: checkcast java/math/BigInteger
    //   3369: invokevirtual intValue : ()I
    //   3372: bipush #32
    //   3374: irem
    //   3375: invokestatic abs : (I)I
    //   3378: invokevirtual charAt : (I)C
    //   3381: invokevirtual append : (C)Ljava/lang/StringBuilder;
    //   3384: pop
    //   3385: iload_2
    //   3386: ifeq -> 4280
    //   3389: goto -> 3396
    //   3392: invokestatic a : (Ljava/lang/Throwable;)Ljava/lang/Throwable;
    //   3395: athrow
    //   3396: aload_3
    //   3397: getstatic burp/Ztmy.ZF : Ljava/lang/String;
    //   3400: getstatic burp/Zrxm.ZL : Ljava/lang/Object;
    //   3403: checkcast java/math/BigInteger
    //   3406: invokevirtual intValue : ()I
    //   3409: bipush #32
    //   3411: irem
    //   3412: invokestatic abs : (I)I
    //   3415: invokevirtual charAt : (I)C
    //   3418: invokevirtual append : (C)Ljava/lang/StringBuilder;
    //   3421: pop
    //   3422: iload_2
    //   3423: ifeq -> 4280
    //   3426: goto -> 3433
    //   3429: invokestatic a : (Ljava/lang/Throwable;)Ljava/lang/Throwable;
    //   3432: athrow
    //   3433: aload_3
    //   3434: getstatic burp/Zlxm.Zv : Ljava/lang/String;
    //   3437: getstatic burp/Zgyk.ZO : Ljava/lang/Object;
    //   3440: checkcast java/math/BigInteger
    //   3443: invokevirtual intValue : ()I
    //   3446: bipush #32
    //   3448: irem
    //   3449: invokestatic abs : (I)I
    //   3452: invokevirtual charAt : (I)C
    //   3455: invokevirtual append : (C)Ljava/lang/StringBuilder;
    //   3458: pop
    //   3459: iload_2
    //   3460: ifeq -> 4280
    //   3463: goto -> 3470
    //   3466: invokestatic a : (Ljava/lang/Throwable;)Ljava/lang/Throwable;
    //   3469: athrow
    //   3470: aload_3
    //   3471: getstatic burp/Zlg1.ZG : Ljava/lang/String;
    //   3474: getstatic burp/Zb_c.ZN : Ljava/lang/Object;
    //   3477: checkcast java/math/BigInteger
    //   3480: invokevirtual intValue : ()I
    //   3483: bipush #32
    //   3485: irem
    //   3486: invokestatic abs : (I)I
    //   3489: invokevirtual charAt : (I)C
    //   3492: invokevirtual append : (C)Ljava/lang/StringBuilder;
    //   3495: pop
    //   3496: iload_2
    //   3497: ifeq -> 4280
    //   3500: goto -> 3507
    //   3503: invokestatic a : (Ljava/lang/Throwable;)Ljava/lang/Throwable;
    //   3506: athrow
    //   3507: aload_3
    //   3508: getstatic burp/Zs9k.Zx : Ljava/lang/String;
    //   3511: getstatic burp/Zkhy.Zc : Ljava/lang/Object;
    //   3514: checkcast java/math/BigInteger
    //   3517: invokevirtual intValue : ()I
    //   3520: bipush #32
    //   3522: irem
    //   3523: invokestatic abs : (I)I
    //   3526: invokevirtual charAt : (I)C
    //   3529: invokevirtual append : (C)Ljava/lang/StringBuilder;
    //   3532: pop
    //   3533: iload_2
    //   3534: ifeq -> 4280
    //   3537: goto -> 3544
    //   3540: invokestatic a : (Ljava/lang/Throwable;)Ljava/lang/Throwable;
    //   3543: athrow
    //   3544: aload_3
    //   3545: getstatic burp/Ze_b.ZX : Ljava/lang/String;
    //   3548: getstatic burp/Zz9v.Zl : Ljava/lang/Object;
    //   3551: checkcast java/math/BigInteger
    //   3554: invokevirtual intValue : ()I
    //   3557: bipush #32
    //   3559: irem
    //   3560: invokestatic abs : (I)I
    //   3563: invokevirtual charAt : (I)C
    //   3566: invokevirtual append : (C)Ljava/lang/StringBuilder;
    //   3569: pop
    //   3570: iload_2
    //   3571: ifeq -> 4280
    //   3574: goto -> 3581
    //   3577: invokestatic a : (Ljava/lang/Throwable;)Ljava/lang/Throwable;
    //   3580: athrow
    //   3581: aload_3
    //   3582: getstatic burp/Zldx.Zm : Ljava/lang/String;
    //   3585: getstatic burp/Zgj5.ZO : Ljava/lang/Object;
    //   3588: checkcast java/math/BigInteger
    //   3591: invokevirtual intValue : ()I
    //   3594: bipush #32
    //   3596: irem
    //   3597: invokestatic abs : (I)I
    //   3600: invokevirtual charAt : (I)C
    //   3603: invokevirtual append : (C)Ljava/lang/StringBuilder;
    //   3606: pop
    //   3607: iload_2
    //   3608: ifeq -> 4280
    //   3611: goto -> 3618
    //   3614: invokestatic a : (Ljava/lang/Throwable;)Ljava/lang/Throwable;
    //   3617: athrow
    //   3618: aload_3
    //   3619: getstatic burp/Zs9k.Zx : Ljava/lang/String;
    //   3622: getstatic burp/Ztod.ZP : Ljava/lang/Object;
    //   3625: checkcast java/math/BigInteger
    //   3628: invokevirtual intValue : ()I
    //   3631: bipush #32
    //   3633: irem
    //   3634: invokestatic abs : (I)I
    //   3637: invokevirtual charAt : (I)C
    //   3640: invokevirtual append : (C)Ljava/lang/StringBuilder;
    //   3643: pop
    //   3644: iload_2
    //   3645: ifeq -> 4280
    //   3648: goto -> 3655
    //   3651: invokestatic a : (Ljava/lang/Throwable;)Ljava/lang/Throwable;
    //   3654: athrow
    //   3655: aload_3
    //   3656: getstatic burp/Zero.ZL : Ljava/lang/String;
    //   3659: getstatic burp/Zete.Zm : Ljava/lang/Object;
    //   3662: checkcast java/math/BigInteger
    //   3665: invokevirtual intValue : ()I
    //   3668: bipush #32
    //   3670: irem
    //   3671: invokestatic abs : (I)I
    //   3674: invokevirtual charAt : (I)C
    //   3677: invokevirtual append : (C)Ljava/lang/StringBuilder;
    //   3680: pop
    //   3681: iload_2
    //   3682: ifeq -> 4280
    //   3685: goto -> 3692
    //   3688: invokestatic a : (Ljava/lang/Throwable;)Ljava/lang/Throwable;
    //   3691: athrow
    //   3692: aload_3
    //   3693: getstatic burp/Zry7.Z_ : Ljava/lang/String;
    //   3696: getstatic burp/Zek5.ZP : Ljava/lang/Object;
    //   3699: checkcast java/math/BigInteger
    //   3702: invokevirtual intValue : ()I
    //   3705: bipush #32
    //   3707: irem
    //   3708: invokestatic abs : (I)I
    //   3711: invokevirtual charAt : (I)C
    //   3714: invokevirtual append : (C)Ljava/lang/StringBuilder;
    //   3717: pop
    //   3718: iload_2
    //   3719: ifeq -> 4280
    //   3722: goto -> 3729
    //   3725: invokestatic a : (Ljava/lang/Throwable;)Ljava/lang/Throwable;
    //   3728: athrow
    //   3729: aload_3
    //   3730: getstatic burp/Zgw7.ZN : Ljava/lang/String;
    //   3733: getstatic burp/Zeu2.ZW : Ljava/lang/Object;
    //   3736: checkcast java/math/BigInteger
    //   3739: invokevirtual intValue : ()I
    //   3742: bipush #32
    //   3744: irem
    //   3745: invokestatic abs : (I)I
    //   3748: invokevirtual charAt : (I)C
    //   3751: invokevirtual append : (C)Ljava/lang/StringBuilder;
    //   3754: pop
    //   3755: iload_2
    //   3756: ifeq -> 4280
    //   3759: goto -> 3766
    //   3762: invokestatic a : (Ljava/lang/Throwable;)Ljava/lang/Throwable;
    //   3765: athrow
    //   3766: aload_3
    //   3767: getstatic burp/Zgkp.ZS : Ljava/lang/String;
    //   3770: getstatic burp/Zrkc.ZI : Ljava/lang/Object;
    //   3773: checkcast java/math/BigInteger
    //   3776: invokevirtual intValue : ()I
    //   3779: bipush #32
    //   3781: irem
    //   3782: invokestatic abs : (I)I
    //   3785: invokevirtual charAt : (I)C
    //   3788: invokevirtual append : (C)Ljava/lang/StringBuilder;
    //   3791: pop
    //   3792: iload_2
    //   3793: ifeq -> 4280
    //   3796: goto -> 3803
    //   3799: invokestatic a : (Ljava/lang/Throwable;)Ljava/lang/Throwable;
    //   3802: athrow
    //   3803: aload_3
    //   3804: getstatic burp/Zl5b.Zi : Ljava/lang/String;
    //   3807: getstatic burp/Zl3l.Zv : Ljava/lang/Object;
    //   3810: checkcast java/math/BigInteger
    //   3813: invokevirtual intValue : ()I
    //   3816: bipush #32
    //   3818: irem
    //   3819: invokestatic abs : (I)I
    //   3822: invokevirtual charAt : (I)C
    //   3825: invokevirtual append : (C)Ljava/lang/StringBuilder;
    //   3828: pop
    //   3829: iload_2
    //   3830: ifeq -> 4280
    //   3833: goto -> 3840
    //   3836: invokestatic a : (Ljava/lang/Throwable;)Ljava/lang/Throwable;
    //   3839: athrow
    //   3840: aload_3
    //   3841: getstatic burp/Zr_y.Zb : Ljava/lang/String;
    //   3844: getstatic burp/Zrm4.ZB : Ljava/lang/Object;
    //   3847: checkcast java/math/BigInteger
    //   3850: invokevirtual intValue : ()I
    //   3853: bipush #32
    //   3855: irem
    //   3856: invokestatic abs : (I)I
    //   3859: invokevirtual charAt : (I)C
    //   3862: invokevirtual append : (C)Ljava/lang/StringBuilder;
    //   3865: pop
    //   3866: iload_2
    //   3867: ifeq -> 4280
    //   3870: goto -> 3877
    //   3873: invokestatic a : (Ljava/lang/Throwable;)Ljava/lang/Throwable;
    //   3876: athrow
    //   3877: aload_3
    //   3878: getstatic burp/Zgkp.ZS : Ljava/lang/String;
    //   3881: getstatic burp/Zeu2.ZW : Ljava/lang/Object;
    //   3884: checkcast java/math/BigInteger
    //   3887: invokevirtual intValue : ()I
    //   3890: bipush #32
    //   3892: irem
    //   3893: invokestatic abs : (I)I
    //   3896: invokevirtual charAt : (I)C
    //   3899: invokevirtual append : (C)Ljava/lang/StringBuilder;
    //   3902: pop
    //   3903: iload_2
    //   3904: ifeq -> 4280
    //   3907: goto -> 3914
    //   3910: invokestatic a : (Ljava/lang/Throwable;)Ljava/lang/Throwable;
    //   3913: athrow
    //   3914: aload_3
    //   3915: getstatic burp/Zb_c.ZS : Ljava/lang/String;
    //   3918: getstatic burp/Zrd0.Zs : Ljava/lang/Object;
    //   3921: checkcast java/math/BigInteger
    //   3924: invokevirtual intValue : ()I
    //   3927: bipush #32
    //   3929: irem
    //   3930: invokestatic abs : (I)I
    //   3933: invokevirtual charAt : (I)C
    //   3936: invokevirtual append : (C)Ljava/lang/StringBuilder;
    //   3939: pop
    //   3940: iload_2
    //   3941: ifeq -> 4280
    //   3944: goto -> 3951
    //   3947: invokestatic a : (Ljava/lang/Throwable;)Ljava/lang/Throwable;
    //   3950: athrow
    //   3951: aload_3
    //   3952: getstatic burp/Zct.Zy : Ljava/lang/String;
    //   3955: getstatic burp/Zsk2.ZD : Ljava/lang/Object;
    //   3958: checkcast java/math/BigInteger
    //   3961: invokevirtual intValue : ()I
    //   3964: bipush #32
    //   3966: irem
    //   3967: invokestatic abs : (I)I
    //   3970: invokevirtual charAt : (I)C
    //   3973: invokevirtual append : (C)Ljava/lang/StringBuilder;
    //   3976: pop
    //   3977: iload_2
    //   3978: ifeq -> 4280
    //   3981: goto -> 3988
    //   3984: invokestatic a : (Ljava/lang/Throwable;)Ljava/lang/Throwable;
    //   3987: athrow
    //   3988: aload_3
    //   3989: getstatic burp/Zzlg.Zw : Ljava/lang/String;
    //   3992: getstatic burp/Zkhy.Zc : Ljava/lang/Object;
    //   3995: checkcast java/math/BigInteger
    //   3998: invokevirtual intValue : ()I
    //   4001: bipush #32
    //   4003: irem
    //   4004: invokestatic abs : (I)I
    //   4007: invokevirtual charAt : (I)C
    //   4010: invokevirtual append : (C)Ljava/lang/StringBuilder;
    //   4013: pop
    //   4014: iload_2
    //   4015: ifeq -> 4280
    //   4018: goto -> 4025
    //   4021: invokestatic a : (Ljava/lang/Throwable;)Ljava/lang/Throwable;
    //   4024: athrow
    //   4025: aload_3
    //   4026: getstatic burp/Zxjw.Zv : Ljava/lang/String;
    //   4029: getstatic burp/Zz5d.Zk : Ljava/lang/Object;
    //   4032: checkcast java/math/BigInteger
    //   4035: invokevirtual intValue : ()I
    //   4038: bipush #32
    //   4040: irem
    //   4041: invokestatic abs : (I)I
    //   4044: invokevirtual charAt : (I)C
    //   4047: invokevirtual append : (C)Ljava/lang/StringBuilder;
    //   4050: pop
    //   4051: iload_2
    //   4052: ifeq -> 4280
    //   4055: goto -> 4062
    //   4058: invokestatic a : (Ljava/lang/Throwable;)Ljava/lang/Throwable;
    //   4061: athrow
    //   4062: aload_3
    //   4063: getstatic burp/Zgwh.Zq : Ljava/lang/String;
    //   4066: getstatic burp/Zkk6.Zb : Ljava/lang/Object;
    //   4069: checkcast java/math/BigInteger
    //   4072: invokevirtual intValue : ()I
    //   4075: bipush #32
    //   4077: irem
    //   4078: invokestatic abs : (I)I
    //   4081: invokevirtual charAt : (I)C
    //   4084: invokevirtual append : (C)Ljava/lang/StringBuilder;
    //   4087: pop
    //   4088: iload_2
    //   4089: ifeq -> 4280
    //   4092: goto -> 4099
    //   4095: invokestatic a : (Ljava/lang/Throwable;)Ljava/lang/Throwable;
    //   4098: athrow
    //   4099: aload_3
    //   4100: getstatic burp/Zzlg.Zw : Ljava/lang/String;
    //   4103: getstatic burp/Zz5d.Zk : Ljava/lang/Object;
    //   4106: checkcast java/math/BigInteger
    //   4109: invokevirtual intValue : ()I
    //   4112: bipush #32
    //   4114: irem
    //   4115: invokestatic abs : (I)I
    //   4118: invokevirtual charAt : (I)C
    //   4121: invokevirtual append : (C)Ljava/lang/StringBuilder;
    //   4124: pop
    //   4125: iload_2
    //   4126: ifeq -> 4280
    //   4129: goto -> 4136
    //   4132: invokestatic a : (Ljava/lang/Throwable;)Ljava/lang/Throwable;
    //   4135: athrow
    //   4136: aload_3
    //   4137: getstatic burp/Zbqo.ZS : Ljava/lang/String;
    //   4140: getstatic burp/Zezn.Zh : Ljava/lang/Object;
    //   4143: checkcast java/math/BigInteger
    //   4146: invokevirtual intValue : ()I
    //   4149: bipush #32
    //   4151: irem
    //   4152: invokestatic abs : (I)I
    //   4155: invokevirtual charAt : (I)C
    //   4158: invokevirtual append : (C)Ljava/lang/StringBuilder;
    //   4161: pop
    //   4162: iload_2
    //   4163: ifeq -> 4280
    //   4166: goto -> 4173
    //   4169: invokestatic a : (Ljava/lang/Throwable;)Ljava/lang/Throwable;
    //   4172: athrow
    //   4173: aload_3
    //   4174: getstatic burp/Zkdc.Zc : Ljava/lang/String;
    //   4177: getstatic burp/Zrj3.ZA : Ljava/lang/Object;
    //   4180: checkcast java/math/BigInteger
    //   4183: invokevirtual intValue : ()I
    //   4186: bipush #32
    //   4188: irem
    //   4189: invokestatic abs : (I)I
    //   4192: invokevirtual charAt : (I)C
    //   4195: invokevirtual append : (C)Ljava/lang/StringBuilder;
    //   4198: pop
    //   4199: iload_2
    //   4200: ifeq -> 4280
    //   4203: goto -> 4210
    //   4206: invokestatic a : (Ljava/lang/Throwable;)Ljava/lang/Throwable;
    //   4209: athrow
    //   4210: aload_3
    //   4211: getstatic burp/Zlxm.Zv : Ljava/lang/String;
    //   4214: getstatic burp/Zryq.ZR : Ljava/lang/Object;
    //   4217: checkcast java/math/BigInteger
    //   4220: invokevirtual intValue : ()I
    //   4223: bipush #32
    //   4225: irem
    //   4226: invokestatic abs : (I)I
    //   4229: invokevirtual charAt : (I)C
    //   4232: invokevirtual append : (C)Ljava/lang/StringBuilder;
    //   4235: pop
    //   4236: iload_2
    //   4237: ifeq -> 4280
    //   4240: goto -> 4247
    //   4243: invokestatic a : (Ljava/lang/Throwable;)Ljava/lang/Throwable;
    //   4246: athrow
    //   4247: aload_3
    //   4248: getstatic burp/Zero.ZL : Ljava/lang/String;
    //   4251: getstatic burp/Zezn.Zh : Ljava/lang/Object;
    //   4254: checkcast java/math/BigInteger
    //   4257: invokevirtual intValue : ()I
    //   4260: bipush #32
    //   4262: irem
    //   4263: invokestatic abs : (I)I
    //   4266: invokevirtual charAt : (I)C
    //   4269: invokevirtual append : (C)Ljava/lang/StringBuilder;
    //   4272: pop
    //   4273: goto -> 4280
    //   4276: invokestatic a : (Ljava/lang/Throwable;)Ljava/lang/Throwable;
    //   4279: athrow
    //   4280: iinc #4, 1
    //   4283: iload_2
    //   4284: ifeq -> 2947
    //   4287: aload_3
    //   4288: invokevirtual toString : ()Ljava/lang/String;
    //   4291: putstatic burp/Zryq.Zb : Ljava/lang/String;
    //   4294: sipush #-5326
    //   4297: sipush #-21945
    //   4300: invokestatic a : (II)Ljava/lang/String;
    //   4303: iconst_1
    //   4304: ldc burp/Ze3d
    //   4306: invokevirtual getClassLoader : ()Ljava/lang/ClassLoader;
    //   4309: invokestatic forName : (Ljava/lang/String;ZLjava/lang/ClassLoader;)Ljava/lang/Class;
    //   4312: invokevirtual getDeclaredFields : ()[Ljava/lang/reflect/Field;
    //   4315: astore #4
    //   4317: aload #4
    //   4319: arraylength
    //   4320: istore #5
    //   4322: iconst_0
    //   4323: istore #6
    //   4325: iload #6
    //   4327: iload #5
    //   4329: if_icmpge -> 4467
    //   4332: aload #4
    //   4334: iload #6
    //   4336: aaload
    //   4337: astore #7
    //   4339: aload #7
    //   4341: invokevirtual getModifiers : ()I
    //   4344: invokestatic isStatic : (I)Z
    //   4347: ifne -> 4357
    //   4350: goto -> 4460
    //   4353: invokestatic a : (Ljava/lang/Throwable;)Ljava/lang/Throwable;
    //   4356: athrow
    //   4357: aload #7
    //   4359: invokevirtual getType : ()Ljava/lang/Class;
    //   4362: astore #8
    //   4364: aload #8
    //   4366: ifnull -> 4447
    //   4369: aload #8
    //   4371: invokevirtual isPrimitive : ()Z
    //   4374: ifne -> 4447
    //   4377: goto -> 4384
    //   4380: invokestatic a : (Ljava/lang/Throwable;)Ljava/lang/Throwable;
    //   4383: athrow
    //   4384: aload #8
    //   4386: invokevirtual getPackage : ()Ljava/lang/Package;
    //   4389: ifnull -> 4447
    //   4392: goto -> 4399
    //   4395: invokestatic a : (Ljava/lang/Throwable;)Ljava/lang/Throwable;
    //   4398: athrow
    //   4399: aload #8
    //   4401: invokevirtual getPackage : ()Ljava/lang/Package;
    //   4404: invokevirtual getName : ()Ljava/lang/String;
    //   4407: ifnull -> 4447
    //   4410: goto -> 4417
    //   4413: invokestatic a : (Ljava/lang/Throwable;)Ljava/lang/Throwable;
    //   4416: athrow
    //   4417: aload #8
    //   4419: invokevirtual getPackage : ()Ljava/lang/Package;
    //   4422: invokevirtual getName : ()Ljava/lang/String;
    //   4425: sipush #-5324
    //   4428: sipush #3102
    //   4431: invokestatic a : (II)Ljava/lang/String;
    //   4434: invokevirtual startsWith : (Ljava/lang/String;)Z
    //   4437: ifne -> 4447
    //   4440: goto -> 4447
    //   4443: invokestatic a : (Ljava/lang/Throwable;)Ljava/lang/Throwable;
    //   4446: athrow
    //   4447: aload #7
    //   4449: iconst_1
    //   4450: invokevirtual setAccessible : (Z)V
    //   4453: aload #7
    //   4455: aconst_null
    //   4456: invokevirtual get : (Ljava/lang/Object;)Ljava/lang/Object;
    //   4459: pop
    //   4460: iinc #6, 1
    //   4463: iload_2
    //   4464: ifeq -> 4325
    //   4467: sipush #-5328
    //   4470: sipush #17365
    //   4473: invokestatic a : (II)Ljava/lang/String;
    //   4476: invokestatic forName : (Ljava/lang/String;)Ljava/lang/Class;
    //   4479: invokevirtual getDeclaredMethods : ()[Ljava/lang/reflect/Method;
    //   4482: astore #4
    //   4484: aload #4
    //   4486: arraylength
    //   4487: istore #5
    //   4489: iconst_0
    //   4490: istore #6
    //   4492: iload #6
    //   4494: iload #5
    //   4496: if_icmpge -> 4629
    //   4499: aload #4
    //   4501: iload #6
    //   4503: aaload
    //   4504: astore #7
    //   4506: aload #7
    //   4508: invokevirtual getParameterTypes : ()[Ljava/lang/Class;
    //   4511: pop
    //   4512: aload #7
    //   4514: invokevirtual getModifiers : ()I
    //   4517: invokestatic isStatic : (I)Z
    //   4520: ifeq -> 4615
    //   4523: aload #7
    //   4525: invokevirtual getParameterTypes : ()[Ljava/lang/Class;
    //   4528: arraylength
    //   4529: iconst_2
    //   4530: if_icmpne -> 4615
    //   4533: goto -> 4540
    //   4536: invokestatic a : (Ljava/lang/Throwable;)Ljava/lang/Throwable;
    //   4539: athrow
    //   4540: aload #7
    //   4542: invokevirtual getReturnType : ()Ljava/lang/Class;
    //   4545: getstatic java/lang/Void.TYPE : Ljava/lang/Class;
    //   4548: invokevirtual equals : (Ljava/lang/Object;)Z
    //   4551: ifeq -> 4615
    //   4554: goto -> 4561
    //   4557: invokestatic a : (Ljava/lang/Throwable;)Ljava/lang/Throwable;
    //   4560: athrow
    //   4561: aload #7
    //   4563: iconst_1
    //   4564: invokevirtual setAccessible : (Z)V
    //   4567: aload #7
    //   4569: aconst_null
    //   4570: iconst_2
    //   4571: anewarray java/lang/Object
    //   4574: dup
    //   4575: iconst_0
    //   4576: aload_0
    //   4577: aastore
    //   4578: dup
    //   4579: iconst_1
    //   4580: aload_1
    //   4581: ifnonnull -> 4599
    //   4584: goto -> 4591
    //   4587: invokestatic a : (Ljava/lang/Throwable;)Ljava/lang/Throwable;
    //   4590: athrow
    //   4591: aload_1
    //   4592: goto -> 4606
    //   4595: invokestatic a : (Ljava/lang/Throwable;)Ljava/lang/Throwable;
    //   4598: athrow
    //   4599: aload_1
    //   4600: checkcast [B
    //   4603: invokevirtual clone : ()Ljava/lang/Object;
    //   4606: aastore
    //   4607: invokevirtual invoke : (Ljava/lang/Object;[Ljava/lang/Object;)Ljava/lang/Object;
    //   4610: pop
    //   4611: iload_2
    //   4612: ifeq -> 4629
    //   4615: iinc #6, 1
    //   4618: iload_2
    //   4619: ifeq -> 4492
    //   4622: goto -> 4629
    //   4625: invokestatic a : (Ljava/lang/Throwable;)Ljava/lang/Throwable;
    //   4628: athrow
    //   4629: getstatic burp/Zrxm.Zp : Ljava/lang/String;
    //   4632: getstatic burp/Zsk2.ZD : Ljava/lang/Object;
    //   4635: checkcast java/math/BigInteger
    //   4638: invokevirtual intValue : ()I
    //   4641: bipush #32
    //   4643: irem
    //   4644: invokestatic abs : (I)I
    //   4647: invokevirtual charAt : (I)C
    //   4650: getstatic burp/Zzlg.Zw : Ljava/lang/String;
    //   4653: getstatic burp/Zr0.ZX : Ljava/lang/Object;
    //   4656: checkcast java/math/BigInteger
    //   4659: invokevirtual intValue : ()I
    //   4662: bipush #32
    //   4664: irem
    //   4665: invokestatic abs : (I)I
    //   4668: invokevirtual charAt : (I)C
    //   4671: if_icmpgt -> 4778
    //   4674: getstatic burp/Ztap.Zk : Ljava/lang/String;
    //   4677: getstatic burp/Ztap.ZK : Ljava/lang/Object;
    //   4680: checkcast java/math/BigInteger
    //   4683: invokevirtual intValue : ()I
    //   4686: bipush #32
    //   4688: irem
    //   4689: invokestatic abs : (I)I
    //   4692: invokevirtual charAt : (I)C
    //   4695: getstatic burp/Zr4k.Zy : Ljava/lang/String;
    //   4698: getstatic burp/Zgw7.Zi : Ljava/lang/Object;
    //   4701: checkcast java/math/BigInteger
    //   4704: invokevirtual intValue : ()I
    //   4707: bipush #32
    //   4709: irem
    //   4710: invokestatic abs : (I)I
    //   4713: invokevirtual charAt : (I)C
    //   4716: if_icmpgt -> 4778
    //   4719: goto -> 4726
    //   4722: invokestatic a : (Ljava/lang/Throwable;)Ljava/lang/Throwable;
    //   4725: athrow
    //   4726: getstatic burp/Ze0w.ZT : Ljava/lang/String;
    //   4729: getstatic burp/Zgwh.Zl : Ljava/lang/Object;
    //   4732: checkcast java/math/BigInteger
    //   4735: invokevirtual intValue : ()I
    //   4738: bipush #32
    //   4740: irem
    //   4741: invokestatic abs : (I)I
    //   4744: invokevirtual charAt : (I)C
    //   4747: getstatic burp/Zth7.Zf : Ljava/lang/String;
    //   4750: getstatic burp/Zbnb.ZZ : Ljava/lang/Object;
    //   4753: checkcast java/math/BigInteger
    //   4756: invokevirtual intValue : ()I
    //   4759: bipush #32
    //   4761: irem
    //   4762: invokestatic abs : (I)I
    //   4765: invokevirtual charAt : (I)C
    //   4768: if_icmple -> 4786
    //   4771: goto -> 4778
    //   4774: invokestatic a : (Ljava/lang/Throwable;)Ljava/lang/Throwable;
    //   4777: athrow
    //   4778: iconst_1
    //   4779: goto -> 4787
    //   4782: invokestatic a : (Ljava/lang/Throwable;)Ljava/lang/Throwable;
    //   4785: athrow
    //   4786: iconst_0
    //   4787: ireturn
    //   4788: astore_3
    //   4789: new java/lang/Exception
    //   4792: dup
    //   4793: aload_3
    //   4794: invokevirtual getMessage : ()Ljava/lang/String;
    //   4797: invokespecial <init> : (Ljava/lang/String;)V
    //   4800: athrow
    // Exception table:
    //   from	to	target	type
    //   4	4787	4788	java/lang/Throwable
    //   149	164	164	java/lang/Throwable
    //   1166	1192	1192	java/lang/Throwable
    //   1273	1288	1288	java/lang/Throwable
    //   2470	2495	2498	java/lang/Throwable
    //   2708	2736	2739	java/lang/Throwable
    //   2718	2753	2756	java/lang/Throwable
    //   2743	2781	2784	java/lang/Throwable
    //   2760	2798	2801	java/lang/Throwable
    //   2788	2826	2829	java/lang/Throwable
    //   2805	2843	2846	java/lang/Throwable
    //   2833	2861	2864	java/lang/Throwable
    //   2850	2875	2878	java/lang/Throwable
    //   2954	3130	3133	java/lang/Throwable
    //   3100	3167	3170	java/lang/Throwable
    //   3137	3204	3207	java/lang/Throwable
    //   3174	3241	3244	java/lang/Throwable
    //   3211	3278	3281	java/lang/Throwable
    //   3248	3315	3318	java/lang/Throwable
    //   3285	3352	3355	java/lang/Throwable
    //   3322	3389	3392	java/lang/Throwable
    //   3359	3426	3429	java/lang/Throwable
    //   3396	3463	3466	java/lang/Throwable
    //   3433	3500	3503	java/lang/Throwable
    //   3470	3537	3540	java/lang/Throwable
    //   3507	3574	3577	java/lang/Throwable
    //   3544	3611	3614	java/lang/Throwable
    //   3581	3648	3651	java/lang/Throwable
    //   3618	3685	3688	java/lang/Throwable
    //   3655	3722	3725	java/lang/Throwable
    //   3692	3759	3762	java/lang/Throwable
    //   3729	3796	3799	java/lang/Throwable
    //   3766	3833	3836	java/lang/Throwable
    //   3803	3870	3873	java/lang/Throwable
    //   3840	3907	3910	java/lang/Throwable
    //   3877	3944	3947	java/lang/Throwable
    //   3914	3981	3984	java/lang/Throwable
    //   3951	4018	4021	java/lang/Throwable
    //   3988	4055	4058	java/lang/Throwable
    //   4025	4092	4095	java/lang/Throwable
    //   4062	4129	4132	java/lang/Throwable
    //   4099	4166	4169	java/lang/Throwable
    //   4136	4203	4206	java/lang/Throwable
    //   4173	4240	4243	java/lang/Throwable
    //   4210	4273	4276	java/lang/Throwable
    //   4339	4353	4353	java/lang/Throwable
    //   4364	4377	4380	java/lang/Throwable
    //   4369	4392	4395	java/lang/Throwable
    //   4384	4410	4413	java/lang/Throwable
    //   4399	4440	4443	java/lang/Throwable
    //   4506	4533	4536	java/lang/Throwable
    //   4523	4554	4557	java/lang/Throwable
    //   4540	4584	4587	java/lang/Throwable
    //   4561	4595	4595	java/lang/Throwable
    //   4606	4622	4625	java/lang/Throwable
    //   4629	4719	4722	java/lang/Throwable
    //   4674	4771	4774	java/lang/Throwable
    //   4726	4782	4782	java/lang/Throwable
  }
  
  static void Zw(Object paramObject) {
    Zezq.Zp = a(-5321, -17516);
    Zezq.Zu = new BigInteger(a(-5318, 24096));
    boolean bool = Zt2e.ZK();
    try {
      try {
        if (Zs9k.Zx.charAt(Math.abs(((BigInteger)Zxdh.ZD).intValue() % 32)) <= Zxdh.Zj.charAt(Math.abs(((BigInteger)Zezq.Zu).intValue() % 32))) {
          try {
            Zgw7.Z_(Class.forName(a(-5319, 11543)));
            if (bool)
              Zrxm.Zj(Class.forName(a(-5317, -647))); 
          } catch (Throwable throwable) {
            throw a(null);
          } 
          return;
        } 
      } catch (Throwable throwable) {
        throw a(null);
      } 
      Zrxm.Zj(Class.forName(a(-5317, -647)));
    } catch (Throwable throwable) {}
  }
  
  static {
    // Byte code:
    //   0: bipush #11
    //   2: anewarray java/lang/String
    //   5: astore #5
    //   7: iconst_0
    //   8: istore_3
    //   9: ldc '??\\t&&<??\\tcc' A!JI(}P&X[~+2Gx? *o'X~MwW\1Ln$D\\rWI\\t6\\fi}'
    //   11: dup
    //   12: astore_2
    //   13: invokevirtual length : ()I
    //   16: istore #4
    //   18: sipush #128
    //   21: istore_1
    //   22: iconst_m1
    //   23: istore_0
    //   24: bipush #122
    //   26: iinc #0, 1
    //   29: aload_2
    //   30: iload_0
    //   31: dup
    //   32: iload_1
    //   33: iadd
    //   34: invokevirtual substring : (II)Ljava/lang/String;
    //   37: iconst_m1
    //   38: goto -> 144
    //   41: aload #5
    //   43: swap
    //   44: iload_3
    //   45: iinc #3, 1
    //   48: swap
    //   49: aastore
    //   50: iload_0
    //   51: iload_1
    //   52: iadd
    //   53: dup
    //   54: istore_0
    //   55: iload #4
    //   57: if_icmpge -> 69
    //   60: aload_2
    //   61: iload_0
    //   62: invokevirtual charAt : (I)C
    //   65: istore_1
    //   66: goto -> 24
    //   69: ldc '{Fu3#8^v;@7}diUX%4gpAB\\b@2~)CX|G\\tHeAmu'
    //   71: dup
    //   72: astore_2
    //   73: invokevirtual length : ()I
    //   76: istore #4
    //   78: bipush #77
    //   80: istore_1
    //   81: iconst_m1
    //   82: istore_0
    //   83: bipush #16
    //   85: iinc #0, 1
    //   88: aload_2
    //   89: iload_0
    //   90: dup
    //   91: iload_1
    //   92: iadd
    //   93: invokevirtual substring : (II)Ljava/lang/String;
    //   96: iconst_0
    //   97: goto -> 144
    //   100: aload #5
    //   102: swap
    //   103: iload_3
    //   104: iinc #3, 1
    //   107: swap
    //   108: aastore
    //   109: iload_0
    //   110: iload_1
    //   111: iadd
    //   112: dup
    //   113: istore_0
    //   114: iload #4
    //   116: if_icmpge -> 128
    //   119: aload_2
    //   120: iload_0
    //   121: invokevirtual charAt : (I)C
    //   124: istore_1
    //   125: goto -> 83
    //   128: aload #5
    //   130: putstatic burp/Zdm.a : [Ljava/lang/String;
    //   133: bipush #11
    //   135: anewarray java/lang/String
    //   138: putstatic burp/Zdm.b : [Ljava/lang/String;
    //   141: goto -> 300
    //   144: dup_x2
    //   145: pop
    //   146: invokevirtual toCharArray : ()[C
    //   149: dup_x1
    //   150: arraylength
    //   151: dup_x2
    //   152: pop
    //   153: iconst_0
    //   154: istore #6
    //   156: dup2_x1
    //   157: pop2
    //   158: dup_x2
    //   159: iconst_1
    //   160: if_icmpgt -> 260
    //   163: dup2
    //   164: swap
    //   165: iload #6
    //   167: dup2_x1
    //   168: caload
    //   169: swap
    //   170: iload #6
    //   172: bipush #7
    //   174: irem
    //   175: tableswitch default -> 242, 0 -> 212, 1 -> 217, 2 -> 222, 3 -> 227, 4 -> 232, 5 -> 237
    //   212: bipush #38
    //   214: goto -> 244
    //   217: bipush #50
    //   219: goto -> 244
    //   222: bipush #91
    //   224: goto -> 244
    //   227: bipush #18
    //   229: goto -> 244
    //   232: bipush #29
    //   234: goto -> 244
    //   237: bipush #41
    //   239: goto -> 244
    //   242: bipush #85
    //   244: ixor
    //   245: ixor
    //   246: i2c
    //   247: castore
    //   248: iinc #6, 1
    //   251: dup
    //   252: ifne -> 260
    //   255: dup2
    //   256: dup_x1
    //   257: goto -> 167
    //   260: dup2_x1
    //   261: pop2
    //   262: dup_x2
    //   263: iload #6
    //   265: if_icmpgt -> 163
    //   268: pop
    //   269: new java/lang/String
    //   272: dup_x1
    //   273: swap
    //   274: invokespecial <init> : ([C)V
    //   277: invokevirtual intern : ()Ljava/lang/String;
    //   280: swap
    //   281: pop
    //   282: swap
    //   283: tableswitch default -> 41, 0 -> 100
    //   300: sipush #-5323
    //   303: sipush #8021
    //   306: invokestatic a : (II)Ljava/lang/String;
    //   309: putstatic burp/Zdm.ZJ : Ljava/lang/String;
    //   312: new java/math/BigInteger
    //   315: dup
    //   316: iconst_1
    //   317: bipush #32
    //   319: newarray byte
    //   321: dup
    //   322: iconst_0
    //   323: bipush #79
    //   325: bastore
    //   326: dup
    //   327: iconst_1
    //   328: bipush #48
    //   330: bastore
    //   331: dup
    //   332: iconst_2
    //   333: bipush #-101
    //   335: bastore
    //   336: dup
    //   337: iconst_3
    //   338: iconst_m1
    //   339: bastore
    //   340: dup
    //   341: iconst_4
    //   342: bipush #-54
    //   344: bastore
    //   345: dup
    //   346: iconst_5
    //   347: bipush #-54
    //   349: bastore
    //   350: dup
    //   351: bipush #6
    //   353: bipush #-85
    //   355: bastore
    //   356: dup
    //   357: bipush #7
    //   359: bipush #-91
    //   361: bastore
    //   362: dup
    //   363: bipush #8
    //   365: bipush #-51
    //   367: bastore
    //   368: dup
    //   369: bipush #9
    //   371: bipush #-122
    //   373: bastore
    //   374: dup
    //   375: bipush #10
    //   377: bipush #47
    //   379: bastore
    //   380: dup
    //   381: bipush #11
    //   383: bipush #-124
    //   385: bastore
    //   386: dup
    //   387: bipush #12
    //   389: bipush #-97
    //   391: bastore
    //   392: dup
    //   393: bipush #13
    //   395: bipush #-85
    //   397: bastore
    //   398: dup
    //   399: bipush #14
    //   401: bipush #83
    //   403: bastore
    //   404: dup
    //   405: bipush #15
    //   407: bipush #-93
    //   409: bastore
    //   410: dup
    //   411: bipush #16
    //   413: bipush #47
    //   415: bastore
    //   416: dup
    //   417: bipush #17
    //   419: bipush #110
    //   421: bastore
    //   422: dup
    //   423: bipush #18
    //   425: bipush #-109
    //   427: bastore
    //   428: dup
    //   429: bipush #19
    //   431: bipush #-57
    //   433: bastore
    //   434: dup
    //   435: bipush #20
    //   437: bipush #-99
    //   439: bastore
    //   440: dup
    //   441: bipush #21
    //   443: bipush #124
    //   445: bastore
    //   446: dup
    //   447: bipush #22
    //   449: iconst_4
    //   450: bastore
    //   451: dup
    //   452: bipush #23
    //   454: bipush #-48
    //   456: bastore
    //   457: dup
    //   458: bipush #24
    //   460: bipush #-74
    //   462: bastore
    //   463: dup
    //   464: bipush #25
    //   466: bipush #-10
    //   468: bastore
    //   469: dup
    //   470: bipush #26
    //   472: bipush #-50
    //   474: bastore
    //   475: dup
    //   476: bipush #27
    //   478: bipush #70
    //   480: bastore
    //   481: dup
    //   482: bipush #28
    //   484: bipush #72
    //   486: bastore
    //   487: dup
    //   488: bipush #29
    //   490: bipush #-5
    //   492: bastore
    //   493: dup
    //   494: bipush #30
    //   496: bipush #-109
    //   498: bastore
    //   499: dup
    //   500: bipush #31
    //   502: bipush #52
    //   504: bastore
    //   505: invokespecial <init> : (I[B)V
    //   508: putstatic burp/Zdm.ZA : Ljava/lang/Object;
    //   511: return
  }
  
  private static Throwable a(Throwable paramThrowable) {
    return paramThrowable;
  }
  
  private static String a(int paramInt1, int paramInt2) {
    int i = (paramInt1 ^ 0xFFFFEB33) & 0xFFFF;
    if (b[i] == null) {
      char[] arrayOfChar = a[i].toCharArray();
      switch (arrayOfChar[0] & 0xFF) {
        case 0:
        
        case 1:
        
        case 2:
        
        case 3:
        
        case 4:
        
        case 5:
        
        case 6:
        
        case 7:
        
        case 8:
        
        case 9:
        
        case 10:
        
        case 11:
        
        case 12:
        
        case 13:
        
        case 14:
        
        case 15:
        
        case 16:
        
        case 17:
        
        case 18:
        
        case 19:
        
        case 20:
        
        case 21:
        
        case 22:
        
        case 23:
        
        case 24:
        
        case 25:
        
        case 26:
        
        case 27:
        
        case 28:
        
        case 29:
        
        case 30:
        
        case 31:
        
        case 32:
        
        case 33:
        
        case 34:
        
        case 35:
        
        case 36:
        
        case 37:
        
        case 38:
        
        case 39:
        
        case 40:
        
        case 41:
        
        case 42:
        
        case 43:
        
        case 44:
        
        case 45:
        
        case 46:
        
        case 47:
        
        case 48:
        
        case 49:
        
        case 50:
        
        case 51:
        
        case 52:
        
        case 53:
        
        case 54:
        
        case 55:
        
        case 56:
        
        case 57:
        
        case 58:
        
        case 59:
        
        case 60:
        
        case 61:
        
        case 62:
        
        case 63:
        
        case 64:
        
        case 65:
        
        case 66:
        
        case 67:
        
        case 68:
        
        case 69:
        
        case 70:
        
        case 71:
        
        case 72:
        
        case 73:
        
        case 74:
        
        case 75:
        
        case 76:
        
        case 77:
        
        case 78:
        
        case 79:
        
        case 80:
        
        case 81:
        
        case 82:
        
        case 83:
        
        case 84:
        
        case 85:
        
        case 86:
        
        case 87:
        
        case 88:
        
        case 89:
        
        case 90:
        
        case 91:
        
        case 92:
        
        case 93:
        
        case 94:
        
        case 95:
        
        case 96:
        
        case 97:
        
        case 98:
        
        case 99:
        
        case 100:
        
        case 101:
        
        case 102:
        
        case 103:
        
        case 104:
        
        case 105:
        
        case 106:
        
        case 107:
        
        case 108:
        
        case 109:
        
        case 110:
        
        case 111:
        
        case 112:
        
        case 113:
        
        case 114:
        
        case 115:
        
        case 116:
        
        case 117:
        
        case 118:
        
        case 119:
        
        case 120:
        
        case 121:
        
        case 122:
        
        case 123:
        
        case 124:
        
        case 125:
        
        case 126:
        
        case 127:
        
        case 128:
        
        case 129:
        
        case 130:
        
        case 131:
        
        case 132:
        
        case 133:
        
        case 134:
        
        case 135:
        
        case 136:
        
        case 137:
        
        case 138:
        
        case 139:
        
        case 140:
        
        case 141:
        
        case 142:
        
        case 143:
        
        case 144:
        
        case 145:
        
        case 146:
        
        case 147:
        
        case 148:
        
        case 149:
        
        case 150:
        
        case 151:
        
        case 152:
        
        case 153:
        
        case 154:
        
        case 155:
        
        case 156:
        
        case 157:
        
        case 158:
        
        case 159:
        
        case 160:
        
        case 161:
        
        case 162:
        
        case 163:
        
        case 164:
        
        case 165:
        
        case 166:
        
        case 167:
        
        case 168:
        
        case 169:
        
        case 170:
        
        case 171:
        
        case 172:
        
        case 173:
        
        case 174:
        
        case 175:
        
        case 176:
        
        case 177:
        
        case 178:
        
        case 179:
        
        case 180:
        
        case 181:
        
        case 182:
        
        case 183:
        
        case 184:
        
        case 185:
        
        case 186:
        
        case 187:
        
        case 188:
        
        case 189:
        
        case 190:
        
        case 191:
        
        case 192:
        
        case 193:
        
        case 194:
        
        case 195:
        
        case 196:
        
        case 197:
        
        case 198:
        
        case 199:
        
        case 200:
        
        case 201:
        
        case 202:
        
        case 203:
        
        case 204:
        
        case 205:
        
        case 206:
        
        case 207:
        
        case 208:
        
        case 209:
        
        case 210:
        
        case 211:
        
        case 212:
        
        case 213:
        
        case 214:
        
        case 215:
        
        case 216:
        
        case 217:
        
        case 218:
        
        case 219:
        
        case 220:
        
        case 221:
        
        case 222:
        
        case 223:
        
        case 224:
        
        case 225:
        
        case 226:
        
        case 227:
        
        case 228:
        
        case 229:
        
        case 230:
        
        case 231:
        
        case 232:
        
        case 233:
        
        case 234:
        
        case 235:
        
        case 236:
        
        case 237:
        
        case 238:
        
        case 239:
        
        case 240:
        
        case 241:
        
        case 242:
        
        case 243:
        
        case 244:
        
        case 245:
        
        case 246:
        
        case 247:
        
        case 248:
        
        case 249:
        
        case 250:
        
        case 251:
        
        case 252:
        
        case 253:
        
        case 254:
        
        default:
          break;
      } 
      byte b1 = 1;
      int j = (paramInt2 & 0xFF) - b1;
      if (j < 0)
        j += 256; 
      int k = ((paramInt2 & 0xFFFF) >>> 8) - b1;
      if (k < 0)
        k += 256; 
      for (byte b2 = 0; b2 < arrayOfChar.length; b2++) {
        int m = b2 % 2;
        if (m == 0) {
          arrayOfChar[b2] = (char)(arrayOfChar[b2] ^ j);
          j = ((j >>> 3 | j << 5) ^ arrayOfChar[b2]) & 0xFF;
        } else {
          arrayOfChar[b2] = (char)(arrayOfChar[b2] ^ k);
          k = ((k >>> 3 | k << 5) ^ arrayOfChar[b2]) & 0xFF;
        } 
      } 
      b[i] = (new String(arrayOfChar)).intern();
    } 
    return b[i];
  }
}


/* Location:              C:\Program Files\BurpSuitePro\burpsuite_pro.jar!\burp\Zdm.class
 * Java compiler version: 21 (65.0)
 * JD-Core Version:       1.1.3
 */