package burp;

import java.math.BigInteger;

class Ze13 extends ClassLoader {
  static String Zg;
  
  static Object ZD;
  
  private static final String[] a;
  
  private static final String[] b;
  
  static boolean Ze(Object[] paramArrayOfObject, Object paramObject) throws Throwable {
    // Byte code:
    //   0: invokestatic ZN : ()Z
    //   3: istore_2
    //   4: getstatic burp/Zxyp.ZZ : Ljava/lang/Object;
    //   7: checkcast java/math/BigInteger
    //   10: getstatic burp/Zehi.Zb : Ljava/lang/Object;
    //   13: checkcast java/math/BigInteger
    //   16: invokevirtual add : (Ljava/math/BigInteger;)Ljava/math/BigInteger;
    //   19: putstatic burp/Zlv6.ZN : Ljava/lang/Object;
    //   22: getstatic burp/Zedz.Za : Ljava/lang/Object;
    //   25: checkcast java/math/BigInteger
    //   28: invokevirtual toByteArray : ()[B
    //   31: astore_3
    //   32: iconst_0
    //   33: istore #5
    //   35: iconst_0
    //   36: istore #6
    //   38: iload #6
    //   40: aload_3
    //   41: arraylength
    //   42: if_icmpge -> 187
    //   45: aload_3
    //   46: iload #6
    //   48: baload
    //   49: istore #7
    //   51: iload #7
    //   53: bipush #48
    //   55: if_icmplt -> 72
    //   58: iload #7
    //   60: bipush #57
    //   62: if_icmple -> 170
    //   65: goto -> 72
    //   68: invokestatic a : (Ljava/lang/Throwable;)Ljava/lang/Throwable;
    //   71: athrow
    //   72: iload #7
    //   74: bipush #65
    //   76: if_icmplt -> 100
    //   79: goto -> 86
    //   82: invokestatic a : (Ljava/lang/Throwable;)Ljava/lang/Throwable;
    //   85: athrow
    //   86: iload #7
    //   88: bipush #90
    //   90: if_icmple -> 170
    //   93: goto -> 100
    //   96: invokestatic a : (Ljava/lang/Throwable;)Ljava/lang/Throwable;
    //   99: athrow
    //   100: iload #7
    //   102: bipush #97
    //   104: if_icmplt -> 128
    //   107: goto -> 114
    //   110: invokestatic a : (Ljava/lang/Throwable;)Ljava/lang/Throwable;
    //   113: athrow
    //   114: iload #7
    //   116: bipush #122
    //   118: if_icmple -> 170
    //   121: goto -> 128
    //   124: invokestatic a : (Ljava/lang/Throwable;)Ljava/lang/Throwable;
    //   127: athrow
    //   128: iload #7
    //   130: bipush #43
    //   132: if_icmpeq -> 170
    //   135: goto -> 142
    //   138: invokestatic a : (Ljava/lang/Throwable;)Ljava/lang/Throwable;
    //   141: athrow
    //   142: iload #7
    //   144: bipush #47
    //   146: if_icmpeq -> 170
    //   149: goto -> 156
    //   152: invokestatic a : (Ljava/lang/Throwable;)Ljava/lang/Throwable;
    //   155: athrow
    //   156: iload #7
    //   158: bipush #61
    //   160: if_icmpne -> 180
    //   163: goto -> 170
    //   166: invokestatic a : (Ljava/lang/Throwable;)Ljava/lang/Throwable;
    //   169: athrow
    //   170: iinc #5, 1
    //   173: goto -> 180
    //   176: invokestatic a : (Ljava/lang/Throwable;)Ljava/lang/Throwable;
    //   179: athrow
    //   180: iinc #6, 1
    //   183: iload_2
    //   184: ifne -> 38
    //   187: iload #5
    //   189: newarray byte
    //   191: astore #6
    //   193: iconst_0
    //   194: istore #7
    //   196: iconst_0
    //   197: istore #8
    //   199: iload #8
    //   201: aload_3
    //   202: arraylength
    //   203: if_icmpge -> 355
    //   206: aload_3
    //   207: iload #8
    //   209: baload
    //   210: istore #9
    //   212: iload #9
    //   214: bipush #48
    //   216: if_icmplt -> 233
    //   219: iload #9
    //   221: bipush #57
    //   223: if_icmple -> 331
    //   226: goto -> 233
    //   229: invokestatic a : (Ljava/lang/Throwable;)Ljava/lang/Throwable;
    //   232: athrow
    //   233: iload #9
    //   235: bipush #65
    //   237: if_icmplt -> 261
    //   240: goto -> 247
    //   243: invokestatic a : (Ljava/lang/Throwable;)Ljava/lang/Throwable;
    //   246: athrow
    //   247: iload #9
    //   249: bipush #90
    //   251: if_icmple -> 331
    //   254: goto -> 261
    //   257: invokestatic a : (Ljava/lang/Throwable;)Ljava/lang/Throwable;
    //   260: athrow
    //   261: iload #9
    //   263: bipush #97
    //   265: if_icmplt -> 289
    //   268: goto -> 275
    //   271: invokestatic a : (Ljava/lang/Throwable;)Ljava/lang/Throwable;
    //   274: athrow
    //   275: iload #9
    //   277: bipush #122
    //   279: if_icmple -> 331
    //   282: goto -> 289
    //   285: invokestatic a : (Ljava/lang/Throwable;)Ljava/lang/Throwable;
    //   288: athrow
    //   289: iload #9
    //   291: bipush #43
    //   293: if_icmpeq -> 331
    //   296: goto -> 303
    //   299: invokestatic a : (Ljava/lang/Throwable;)Ljava/lang/Throwable;
    //   302: athrow
    //   303: iload #9
    //   305: bipush #47
    //   307: if_icmpeq -> 331
    //   310: goto -> 317
    //   313: invokestatic a : (Ljava/lang/Throwable;)Ljava/lang/Throwable;
    //   316: athrow
    //   317: iload #9
    //   319: bipush #61
    //   321: if_icmpne -> 348
    //   324: goto -> 331
    //   327: invokestatic a : (Ljava/lang/Throwable;)Ljava/lang/Throwable;
    //   330: athrow
    //   331: aload #6
    //   333: iload #7
    //   335: iload #9
    //   337: bastore
    //   338: iinc #7, 1
    //   341: goto -> 348
    //   344: invokestatic a : (Ljava/lang/Throwable;)Ljava/lang/Throwable;
    //   347: athrow
    //   348: iinc #8, 1
    //   351: iload_2
    //   352: ifne -> 199
    //   355: aload #6
    //   357: astore #4
    //   359: aload #4
    //   361: astore_3
    //   362: aload_3
    //   363: arraylength
    //   364: istore #5
    //   366: aload_3
    //   367: iload #5
    //   369: iconst_1
    //   370: isub
    //   371: baload
    //   372: bipush #61
    //   374: if_icmpne -> 384
    //   377: iinc #5, -1
    //   380: iload_2
    //   381: ifne -> 366
    //   384: iload #5
    //   386: aload_3
    //   387: arraylength
    //   388: iconst_4
    //   389: idiv
    //   390: isub
    //   391: newarray byte
    //   393: astore #6
    //   395: iconst_0
    //   396: istore #7
    //   398: iload #7
    //   400: aload_3
    //   401: arraylength
    //   402: if_icmpge -> 664
    //   405: aload_3
    //   406: iload #7
    //   408: baload
    //   409: bipush #61
    //   411: if_icmpne -> 430
    //   414: aload_3
    //   415: iload #7
    //   417: iconst_0
    //   418: bastore
    //   419: iload_2
    //   420: ifne -> 657
    //   423: goto -> 430
    //   426: invokestatic a : (Ljava/lang/Throwable;)Ljava/lang/Throwable;
    //   429: athrow
    //   430: aload_3
    //   431: iload #7
    //   433: baload
    //   434: bipush #47
    //   436: if_icmpne -> 463
    //   439: goto -> 446
    //   442: invokestatic a : (Ljava/lang/Throwable;)Ljava/lang/Throwable;
    //   445: athrow
    //   446: aload_3
    //   447: iload #7
    //   449: bipush #63
    //   451: bastore
    //   452: iload_2
    //   453: ifne -> 657
    //   456: goto -> 463
    //   459: invokestatic a : (Ljava/lang/Throwable;)Ljava/lang/Throwable;
    //   462: athrow
    //   463: aload_3
    //   464: iload #7
    //   466: baload
    //   467: bipush #43
    //   469: if_icmpne -> 496
    //   472: goto -> 479
    //   475: invokestatic a : (Ljava/lang/Throwable;)Ljava/lang/Throwable;
    //   478: athrow
    //   479: aload_3
    //   480: iload #7
    //   482: bipush #62
    //   484: bastore
    //   485: iload_2
    //   486: ifne -> 657
    //   489: goto -> 496
    //   492: invokestatic a : (Ljava/lang/Throwable;)Ljava/lang/Throwable;
    //   495: athrow
    //   496: aload_3
    //   497: iload #7
    //   499: baload
    //   500: bipush #48
    //   502: if_icmplt -> 551
    //   505: goto -> 512
    //   508: invokestatic a : (Ljava/lang/Throwable;)Ljava/lang/Throwable;
    //   511: athrow
    //   512: aload_3
    //   513: iload #7
    //   515: baload
    //   516: bipush #57
    //   518: if_icmpgt -> 551
    //   521: goto -> 528
    //   524: invokestatic a : (Ljava/lang/Throwable;)Ljava/lang/Throwable;
    //   527: athrow
    //   528: aload_3
    //   529: iload #7
    //   531: aload_3
    //   532: iload #7
    //   534: baload
    //   535: bipush #-4
    //   537: isub
    //   538: i2b
    //   539: bastore
    //   540: iload_2
    //   541: ifne -> 657
    //   544: goto -> 551
    //   547: invokestatic a : (Ljava/lang/Throwable;)Ljava/lang/Throwable;
    //   550: athrow
    //   551: aload_3
    //   552: iload #7
    //   554: baload
    //   555: bipush #97
    //   557: if_icmplt -> 606
    //   560: goto -> 567
    //   563: invokestatic a : (Ljava/lang/Throwable;)Ljava/lang/Throwable;
    //   566: athrow
    //   567: aload_3
    //   568: iload #7
    //   570: baload
    //   571: bipush #122
    //   573: if_icmpgt -> 606
    //   576: goto -> 583
    //   579: invokestatic a : (Ljava/lang/Throwable;)Ljava/lang/Throwable;
    //   582: athrow
    //   583: aload_3
    //   584: iload #7
    //   586: aload_3
    //   587: iload #7
    //   589: baload
    //   590: bipush #71
    //   592: isub
    //   593: i2b
    //   594: bastore
    //   595: iload_2
    //   596: ifne -> 657
    //   599: goto -> 606
    //   602: invokestatic a : (Ljava/lang/Throwable;)Ljava/lang/Throwable;
    //   605: athrow
    //   606: aload_3
    //   607: iload #7
    //   609: baload
    //   610: bipush #65
    //   612: if_icmplt -> 657
    //   615: goto -> 622
    //   618: invokestatic a : (Ljava/lang/Throwable;)Ljava/lang/Throwable;
    //   621: athrow
    //   622: aload_3
    //   623: iload #7
    //   625: baload
    //   626: bipush #90
    //   628: if_icmpgt -> 657
    //   631: goto -> 638
    //   634: invokestatic a : (Ljava/lang/Throwable;)Ljava/lang/Throwable;
    //   637: athrow
    //   638: aload_3
    //   639: iload #7
    //   641: aload_3
    //   642: iload #7
    //   644: baload
    //   645: bipush #65
    //   647: isub
    //   648: i2b
    //   649: bastore
    //   650: goto -> 657
    //   653: invokestatic a : (Ljava/lang/Throwable;)Ljava/lang/Throwable;
    //   656: athrow
    //   657: iinc #7, 1
    //   660: iload_2
    //   661: ifne -> 398
    //   664: iconst_0
    //   665: istore #7
    //   667: iconst_0
    //   668: istore #8
    //   670: iload #8
    //   672: aload #6
    //   674: arraylength
    //   675: iconst_2
    //   676: isub
    //   677: if_icmpge -> 780
    //   680: aload #6
    //   682: iload #8
    //   684: aload_3
    //   685: iload #7
    //   687: baload
    //   688: iconst_2
    //   689: ishl
    //   690: sipush #255
    //   693: iand
    //   694: aload_3
    //   695: iload #7
    //   697: iconst_1
    //   698: iadd
    //   699: baload
    //   700: iconst_4
    //   701: iushr
    //   702: iconst_3
    //   703: iand
    //   704: ior
    //   705: i2b
    //   706: bastore
    //   707: aload #6
    //   709: iload #8
    //   711: iconst_1
    //   712: iadd
    //   713: aload_3
    //   714: iload #7
    //   716: iconst_1
    //   717: iadd
    //   718: baload
    //   719: iconst_4
    //   720: ishl
    //   721: sipush #255
    //   724: iand
    //   725: aload_3
    //   726: iload #7
    //   728: iconst_2
    //   729: iadd
    //   730: baload
    //   731: iconst_2
    //   732: iushr
    //   733: bipush #15
    //   735: iand
    //   736: ior
    //   737: i2b
    //   738: bastore
    //   739: aload #6
    //   741: iload #8
    //   743: iconst_2
    //   744: iadd
    //   745: aload_3
    //   746: iload #7
    //   748: iconst_2
    //   749: iadd
    //   750: baload
    //   751: bipush #6
    //   753: ishl
    //   754: sipush #255
    //   757: iand
    //   758: aload_3
    //   759: iload #7
    //   761: iconst_3
    //   762: iadd
    //   763: baload
    //   764: bipush #63
    //   766: iand
    //   767: ior
    //   768: i2b
    //   769: bastore
    //   770: iinc #7, 4
    //   773: iinc #8, 3
    //   776: iload_2
    //   777: ifne -> 670
    //   780: iload #8
    //   782: aload #6
    //   784: arraylength
    //   785: if_icmpge -> 822
    //   788: aload #6
    //   790: iload #8
    //   792: aload_3
    //   793: iload #7
    //   795: baload
    //   796: iconst_2
    //   797: ishl
    //   798: sipush #255
    //   801: iand
    //   802: aload_3
    //   803: iload #7
    //   805: iconst_1
    //   806: iadd
    //   807: baload
    //   808: iconst_4
    //   809: iushr
    //   810: iconst_3
    //   811: iand
    //   812: ior
    //   813: i2b
    //   814: bastore
    //   815: goto -> 822
    //   818: invokestatic a : (Ljava/lang/Throwable;)Ljava/lang/Throwable;
    //   821: athrow
    //   822: iinc #8, 1
    //   825: iload #8
    //   827: aload #6
    //   829: arraylength
    //   830: if_icmpge -> 870
    //   833: aload #6
    //   835: iload #8
    //   837: aload_3
    //   838: iload #7
    //   840: iconst_1
    //   841: iadd
    //   842: baload
    //   843: iconst_4
    //   844: ishl
    //   845: sipush #255
    //   848: iand
    //   849: aload_3
    //   850: iload #7
    //   852: iconst_2
    //   853: iadd
    //   854: baload
    //   855: iconst_2
    //   856: iushr
    //   857: bipush #15
    //   859: iand
    //   860: ior
    //   861: i2b
    //   862: bastore
    //   863: goto -> 870
    //   866: invokestatic a : (Ljava/lang/Throwable;)Ljava/lang/Throwable;
    //   869: athrow
    //   870: aload #6
    //   872: astore #4
    //   874: new java/math/BigInteger
    //   877: dup
    //   878: aload #4
    //   880: invokespecial <init> : ([B)V
    //   883: invokevirtual abs : ()Ljava/math/BigInteger;
    //   886: putstatic burp/Zl_k.ZH : Ljava/lang/Object;
    //   889: new java/lang/StringBuilder
    //   892: dup
    //   893: invokespecial <init> : ()V
    //   896: astore_3
    //   897: iconst_0
    //   898: istore #4
    //   900: iload #4
    //   902: bipush #32
    //   904: if_icmpge -> 2239
    //   907: iload #4
    //   909: tableswitch default -> 2232, 0 -> 1052, 1 -> 1089, 2 -> 1126, 3 -> 1163, 4 -> 1200, 5 -> 1237, 6 -> 1274, 7 -> 1311, 8 -> 1348, 9 -> 1385, 10 -> 1422, 11 -> 1459, 12 -> 1496, 13 -> 1533, 14 -> 1570, 15 -> 1607, 16 -> 1644, 17 -> 1681, 18 -> 1718, 19 -> 1755, 20 -> 1792, 21 -> 1829, 22 -> 1866, 23 -> 1903, 24 -> 1940, 25 -> 1977, 26 -> 2014, 27 -> 2051, 28 -> 2088, 29 -> 2125, 30 -> 2162, 31 -> 2199
    //   1052: aload_3
    //   1053: getstatic burp/Zzip.Za : Ljava/lang/String;
    //   1056: getstatic burp/Ztnw.Zt : Ljava/lang/Object;
    //   1059: checkcast java/math/BigInteger
    //   1062: invokevirtual intValue : ()I
    //   1065: bipush #32
    //   1067: irem
    //   1068: invokestatic abs : (I)I
    //   1071: invokevirtual charAt : (I)C
    //   1074: invokevirtual append : (C)Ljava/lang/StringBuilder;
    //   1077: pop
    //   1078: iload_2
    //   1079: ifne -> 2232
    //   1082: goto -> 1089
    //   1085: invokestatic a : (Ljava/lang/Throwable;)Ljava/lang/Throwable;
    //   1088: athrow
    //   1089: aload_3
    //   1090: getstatic burp/Zx4l.Zy : Ljava/lang/String;
    //   1093: getstatic burp/Zxso.ZF : Ljava/lang/Object;
    //   1096: checkcast java/math/BigInteger
    //   1099: invokevirtual intValue : ()I
    //   1102: bipush #32
    //   1104: irem
    //   1105: invokestatic abs : (I)I
    //   1108: invokevirtual charAt : (I)C
    //   1111: invokevirtual append : (C)Ljava/lang/StringBuilder;
    //   1114: pop
    //   1115: iload_2
    //   1116: ifne -> 2232
    //   1119: goto -> 1126
    //   1122: invokestatic a : (Ljava/lang/Throwable;)Ljava/lang/Throwable;
    //   1125: athrow
    //   1126: aload_3
    //   1127: getstatic burp/Zter.ZE : Ljava/lang/String;
    //   1130: getstatic burp/Ztuj.Ze : Ljava/lang/Object;
    //   1133: checkcast java/math/BigInteger
    //   1136: invokevirtual intValue : ()I
    //   1139: bipush #32
    //   1141: irem
    //   1142: invokestatic abs : (I)I
    //   1145: invokevirtual charAt : (I)C
    //   1148: invokevirtual append : (C)Ljava/lang/StringBuilder;
    //   1151: pop
    //   1152: iload_2
    //   1153: ifne -> 2232
    //   1156: goto -> 1163
    //   1159: invokestatic a : (Ljava/lang/Throwable;)Ljava/lang/Throwable;
    //   1162: athrow
    //   1163: aload_3
    //   1164: getstatic burp/Zbo7.ZZ : Ljava/lang/String;
    //   1167: getstatic burp/Ztuj.Ze : Ljava/lang/Object;
    //   1170: checkcast java/math/BigInteger
    //   1173: invokevirtual intValue : ()I
    //   1176: bipush #32
    //   1178: irem
    //   1179: invokestatic abs : (I)I
    //   1182: invokevirtual charAt : (I)C
    //   1185: invokevirtual append : (C)Ljava/lang/StringBuilder;
    //   1188: pop
    //   1189: iload_2
    //   1190: ifne -> 2232
    //   1193: goto -> 1200
    //   1196: invokestatic a : (Ljava/lang/Throwable;)Ljava/lang/Throwable;
    //   1199: athrow
    //   1200: aload_3
    //   1201: getstatic burp/Zzip.Za : Ljava/lang/String;
    //   1204: getstatic burp/Zg0j.ZV : Ljava/lang/Object;
    //   1207: checkcast java/math/BigInteger
    //   1210: invokevirtual intValue : ()I
    //   1213: bipush #32
    //   1215: irem
    //   1216: invokestatic abs : (I)I
    //   1219: invokevirtual charAt : (I)C
    //   1222: invokevirtual append : (C)Ljava/lang/StringBuilder;
    //   1225: pop
    //   1226: iload_2
    //   1227: ifne -> 2232
    //   1230: goto -> 1237
    //   1233: invokestatic a : (Ljava/lang/Throwable;)Ljava/lang/Throwable;
    //   1236: athrow
    //   1237: aload_3
    //   1238: getstatic burp/Zgss.Zc : Ljava/lang/String;
    //   1241: getstatic burp/Zzap.ZL : Ljava/lang/Object;
    //   1244: checkcast java/math/BigInteger
    //   1247: invokevirtual intValue : ()I
    //   1250: bipush #32
    //   1252: irem
    //   1253: invokestatic abs : (I)I
    //   1256: invokevirtual charAt : (I)C
    //   1259: invokevirtual append : (C)Ljava/lang/StringBuilder;
    //   1262: pop
    //   1263: iload_2
    //   1264: ifne -> 2232
    //   1267: goto -> 1274
    //   1270: invokestatic a : (Ljava/lang/Throwable;)Ljava/lang/Throwable;
    //   1273: athrow
    //   1274: aload_3
    //   1275: getstatic burp/Zedz.Zh : Ljava/lang/String;
    //   1278: getstatic burp/Ze3j.Ze : Ljava/lang/Object;
    //   1281: checkcast java/math/BigInteger
    //   1284: invokevirtual intValue : ()I
    //   1287: bipush #32
    //   1289: irem
    //   1290: invokestatic abs : (I)I
    //   1293: invokevirtual charAt : (I)C
    //   1296: invokevirtual append : (C)Ljava/lang/StringBuilder;
    //   1299: pop
    //   1300: iload_2
    //   1301: ifne -> 2232
    //   1304: goto -> 1311
    //   1307: invokestatic a : (Ljava/lang/Throwable;)Ljava/lang/Throwable;
    //   1310: athrow
    //   1311: aload_3
    //   1312: getstatic burp/Zz1k.ZC : Ljava/lang/String;
    //   1315: getstatic burp/Zkfz.Zr : Ljava/lang/Object;
    //   1318: checkcast java/math/BigInteger
    //   1321: invokevirtual intValue : ()I
    //   1324: bipush #32
    //   1326: irem
    //   1327: invokestatic abs : (I)I
    //   1330: invokevirtual charAt : (I)C
    //   1333: invokevirtual append : (C)Ljava/lang/StringBuilder;
    //   1336: pop
    //   1337: iload_2
    //   1338: ifne -> 2232
    //   1341: goto -> 1348
    //   1344: invokestatic a : (Ljava/lang/Throwable;)Ljava/lang/Throwable;
    //   1347: athrow
    //   1348: aload_3
    //   1349: getstatic burp/Zsxj.Zp : Ljava/lang/String;
    //   1352: getstatic burp/Zm__.Zz : Ljava/lang/Object;
    //   1355: checkcast java/math/BigInteger
    //   1358: invokevirtual intValue : ()I
    //   1361: bipush #32
    //   1363: irem
    //   1364: invokestatic abs : (I)I
    //   1367: invokevirtual charAt : (I)C
    //   1370: invokevirtual append : (C)Ljava/lang/StringBuilder;
    //   1373: pop
    //   1374: iload_2
    //   1375: ifne -> 2232
    //   1378: goto -> 1385
    //   1381: invokestatic a : (Ljava/lang/Throwable;)Ljava/lang/Throwable;
    //   1384: athrow
    //   1385: aload_3
    //   1386: getstatic burp/Zl88.Zd : Ljava/lang/String;
    //   1389: getstatic burp/Zt4g.Zv : Ljava/lang/Object;
    //   1392: checkcast java/math/BigInteger
    //   1395: invokevirtual intValue : ()I
    //   1398: bipush #32
    //   1400: irem
    //   1401: invokestatic abs : (I)I
    //   1404: invokevirtual charAt : (I)C
    //   1407: invokevirtual append : (C)Ljava/lang/StringBuilder;
    //   1410: pop
    //   1411: iload_2
    //   1412: ifne -> 2232
    //   1415: goto -> 1422
    //   1418: invokestatic a : (Ljava/lang/Throwable;)Ljava/lang/Throwable;
    //   1421: athrow
    //   1422: aload_3
    //   1423: getstatic burp/Zbo7.ZZ : Ljava/lang/String;
    //   1426: getstatic burp/Zm0s.Zl : Ljava/lang/Object;
    //   1429: checkcast java/math/BigInteger
    //   1432: invokevirtual intValue : ()I
    //   1435: bipush #32
    //   1437: irem
    //   1438: invokestatic abs : (I)I
    //   1441: invokevirtual charAt : (I)C
    //   1444: invokevirtual append : (C)Ljava/lang/StringBuilder;
    //   1447: pop
    //   1448: iload_2
    //   1449: ifne -> 2232
    //   1452: goto -> 1459
    //   1455: invokestatic a : (Ljava/lang/Throwable;)Ljava/lang/Throwable;
    //   1458: athrow
    //   1459: aload_3
    //   1460: getstatic burp/Zlv6.Zt : Ljava/lang/String;
    //   1463: getstatic burp/Zk9s.ZY : Ljava/lang/Object;
    //   1466: checkcast java/math/BigInteger
    //   1469: invokevirtual intValue : ()I
    //   1472: bipush #32
    //   1474: irem
    //   1475: invokestatic abs : (I)I
    //   1478: invokevirtual charAt : (I)C
    //   1481: invokevirtual append : (C)Ljava/lang/StringBuilder;
    //   1484: pop
    //   1485: iload_2
    //   1486: ifne -> 2232
    //   1489: goto -> 1496
    //   1492: invokestatic a : (Ljava/lang/Throwable;)Ljava/lang/Throwable;
    //   1495: athrow
    //   1496: aload_3
    //   1497: getstatic burp/Zl2q.ZI : Ljava/lang/String;
    //   1500: getstatic burp/Zx54.Zn : Ljava/lang/Object;
    //   1503: checkcast java/math/BigInteger
    //   1506: invokevirtual intValue : ()I
    //   1509: bipush #32
    //   1511: irem
    //   1512: invokestatic abs : (I)I
    //   1515: invokevirtual charAt : (I)C
    //   1518: invokevirtual append : (C)Ljava/lang/StringBuilder;
    //   1521: pop
    //   1522: iload_2
    //   1523: ifne -> 2232
    //   1526: goto -> 1533
    //   1529: invokestatic a : (Ljava/lang/Throwable;)Ljava/lang/Throwable;
    //   1532: athrow
    //   1533: aload_3
    //   1534: getstatic burp/Zx4w.Zo : Ljava/lang/String;
    //   1537: getstatic burp/Zlhm.ZT : Ljava/lang/Object;
    //   1540: checkcast java/math/BigInteger
    //   1543: invokevirtual intValue : ()I
    //   1546: bipush #32
    //   1548: irem
    //   1549: invokestatic abs : (I)I
    //   1552: invokevirtual charAt : (I)C
    //   1555: invokevirtual append : (C)Ljava/lang/StringBuilder;
    //   1558: pop
    //   1559: iload_2
    //   1560: ifne -> 2232
    //   1563: goto -> 1570
    //   1566: invokestatic a : (Ljava/lang/Throwable;)Ljava/lang/Throwable;
    //   1569: athrow
    //   1570: aload_3
    //   1571: getstatic burp/Ztbf.Zf : Ljava/lang/String;
    //   1574: getstatic burp/Zes_.ZJ : Ljava/lang/Object;
    //   1577: checkcast java/math/BigInteger
    //   1580: invokevirtual intValue : ()I
    //   1583: bipush #32
    //   1585: irem
    //   1586: invokestatic abs : (I)I
    //   1589: invokevirtual charAt : (I)C
    //   1592: invokevirtual append : (C)Ljava/lang/StringBuilder;
    //   1595: pop
    //   1596: iload_2
    //   1597: ifne -> 2232
    //   1600: goto -> 1607
    //   1603: invokestatic a : (Ljava/lang/Throwable;)Ljava/lang/Throwable;
    //   1606: athrow
    //   1607: aload_3
    //   1608: getstatic burp/Zk9s.ZM : Ljava/lang/String;
    //   1611: getstatic burp/Zxyp.ZZ : Ljava/lang/Object;
    //   1614: checkcast java/math/BigInteger
    //   1617: invokevirtual intValue : ()I
    //   1620: bipush #32
    //   1622: irem
    //   1623: invokestatic abs : (I)I
    //   1626: invokevirtual charAt : (I)C
    //   1629: invokevirtual append : (C)Ljava/lang/StringBuilder;
    //   1632: pop
    //   1633: iload_2
    //   1634: ifne -> 2232
    //   1637: goto -> 1644
    //   1640: invokestatic a : (Ljava/lang/Throwable;)Ljava/lang/Throwable;
    //   1643: athrow
    //   1644: aload_3
    //   1645: getstatic burp/Zlos.Zp : Ljava/lang/String;
    //   1648: getstatic burp/Zg7p.Zb : Ljava/lang/Object;
    //   1651: checkcast java/math/BigInteger
    //   1654: invokevirtual intValue : ()I
    //   1657: bipush #32
    //   1659: irem
    //   1660: invokestatic abs : (I)I
    //   1663: invokevirtual charAt : (I)C
    //   1666: invokevirtual append : (C)Ljava/lang/StringBuilder;
    //   1669: pop
    //   1670: iload_2
    //   1671: ifne -> 2232
    //   1674: goto -> 1681
    //   1677: invokestatic a : (Ljava/lang/Throwable;)Ljava/lang/Throwable;
    //   1680: athrow
    //   1681: aload_3
    //   1682: getstatic burp/Zzai.Zy : Ljava/lang/String;
    //   1685: getstatic burp/Zlos.Zk : Ljava/lang/Object;
    //   1688: checkcast java/math/BigInteger
    //   1691: invokevirtual intValue : ()I
    //   1694: bipush #32
    //   1696: irem
    //   1697: invokestatic abs : (I)I
    //   1700: invokevirtual charAt : (I)C
    //   1703: invokevirtual append : (C)Ljava/lang/StringBuilder;
    //   1706: pop
    //   1707: iload_2
    //   1708: ifne -> 2232
    //   1711: goto -> 1718
    //   1714: invokestatic a : (Ljava/lang/Throwable;)Ljava/lang/Throwable;
    //   1717: athrow
    //   1718: aload_3
    //   1719: getstatic burp/Zg7z.Zf : Ljava/lang/String;
    //   1722: getstatic burp/Zrbp.Z_ : Ljava/lang/Object;
    //   1725: checkcast java/math/BigInteger
    //   1728: invokevirtual intValue : ()I
    //   1731: bipush #32
    //   1733: irem
    //   1734: invokestatic abs : (I)I
    //   1737: invokevirtual charAt : (I)C
    //   1740: invokevirtual append : (C)Ljava/lang/StringBuilder;
    //   1743: pop
    //   1744: iload_2
    //   1745: ifne -> 2232
    //   1748: goto -> 1755
    //   1751: invokestatic a : (Ljava/lang/Throwable;)Ljava/lang/Throwable;
    //   1754: athrow
    //   1755: aload_3
    //   1756: getstatic burp/Zb3z.Zi : Ljava/lang/String;
    //   1759: getstatic burp/Zbp.ZD : Ljava/lang/Object;
    //   1762: checkcast java/math/BigInteger
    //   1765: invokevirtual intValue : ()I
    //   1768: bipush #32
    //   1770: irem
    //   1771: invokestatic abs : (I)I
    //   1774: invokevirtual charAt : (I)C
    //   1777: invokevirtual append : (C)Ljava/lang/StringBuilder;
    //   1780: pop
    //   1781: iload_2
    //   1782: ifne -> 2232
    //   1785: goto -> 1792
    //   1788: invokestatic a : (Ljava/lang/Throwable;)Ljava/lang/Throwable;
    //   1791: athrow
    //   1792: aload_3
    //   1793: getstatic burp/Zter.ZE : Ljava/lang/String;
    //   1796: getstatic burp/Zedz.Za : Ljava/lang/Object;
    //   1799: checkcast java/math/BigInteger
    //   1802: invokevirtual intValue : ()I
    //   1805: bipush #32
    //   1807: irem
    //   1808: invokestatic abs : (I)I
    //   1811: invokevirtual charAt : (I)C
    //   1814: invokevirtual append : (C)Ljava/lang/StringBuilder;
    //   1817: pop
    //   1818: iload_2
    //   1819: ifne -> 2232
    //   1822: goto -> 1829
    //   1825: invokestatic a : (Ljava/lang/Throwable;)Ljava/lang/Throwable;
    //   1828: athrow
    //   1829: aload_3
    //   1830: getstatic burp/Zkmx.Zg : Ljava/lang/String;
    //   1833: getstatic burp/Zlos.Zk : Ljava/lang/Object;
    //   1836: checkcast java/math/BigInteger
    //   1839: invokevirtual intValue : ()I
    //   1842: bipush #32
    //   1844: irem
    //   1845: invokestatic abs : (I)I
    //   1848: invokevirtual charAt : (I)C
    //   1851: invokevirtual append : (C)Ljava/lang/StringBuilder;
    //   1854: pop
    //   1855: iload_2
    //   1856: ifne -> 2232
    //   1859: goto -> 1866
    //   1862: invokestatic a : (Ljava/lang/Throwable;)Ljava/lang/Throwable;
    //   1865: athrow
    //   1866: aload_3
    //   1867: getstatic burp/Zrnu.ZO : Ljava/lang/String;
    //   1870: getstatic burp/Zxl5.Zh : Ljava/lang/Object;
    //   1873: checkcast java/math/BigInteger
    //   1876: invokevirtual intValue : ()I
    //   1879: bipush #32
    //   1881: irem
    //   1882: invokestatic abs : (I)I
    //   1885: invokevirtual charAt : (I)C
    //   1888: invokevirtual append : (C)Ljava/lang/StringBuilder;
    //   1891: pop
    //   1892: iload_2
    //   1893: ifne -> 2232
    //   1896: goto -> 1903
    //   1899: invokestatic a : (Ljava/lang/Throwable;)Ljava/lang/Throwable;
    //   1902: athrow
    //   1903: aload_3
    //   1904: getstatic burp/Zg7p.ZA : Ljava/lang/String;
    //   1907: getstatic burp/Zzai.Z_ : Ljava/lang/Object;
    //   1910: checkcast java/math/BigInteger
    //   1913: invokevirtual intValue : ()I
    //   1916: bipush #32
    //   1918: irem
    //   1919: invokestatic abs : (I)I
    //   1922: invokevirtual charAt : (I)C
    //   1925: invokevirtual append : (C)Ljava/lang/StringBuilder;
    //   1928: pop
    //   1929: iload_2
    //   1930: ifne -> 2232
    //   1933: goto -> 1940
    //   1936: invokestatic a : (Ljava/lang/Throwable;)Ljava/lang/Throwable;
    //   1939: athrow
    //   1940: aload_3
    //   1941: getstatic burp/Zrbp.Ze : Ljava/lang/String;
    //   1944: getstatic burp/Zrdy.Zt : Ljava/lang/Object;
    //   1947: checkcast java/math/BigInteger
    //   1950: invokevirtual intValue : ()I
    //   1953: bipush #32
    //   1955: irem
    //   1956: invokestatic abs : (I)I
    //   1959: invokevirtual charAt : (I)C
    //   1962: invokevirtual append : (C)Ljava/lang/StringBuilder;
    //   1965: pop
    //   1966: iload_2
    //   1967: ifne -> 2232
    //   1970: goto -> 1977
    //   1973: invokestatic a : (Ljava/lang/Throwable;)Ljava/lang/Throwable;
    //   1976: athrow
    //   1977: aload_3
    //   1978: getstatic burp/Zk8b.ZT : Ljava/lang/String;
    //   1981: getstatic burp/Zsby.ZZ : Ljava/lang/Object;
    //   1984: checkcast java/math/BigInteger
    //   1987: invokevirtual intValue : ()I
    //   1990: bipush #32
    //   1992: irem
    //   1993: invokestatic abs : (I)I
    //   1996: invokevirtual charAt : (I)C
    //   1999: invokevirtual append : (C)Ljava/lang/StringBuilder;
    //   2002: pop
    //   2003: iload_2
    //   2004: ifne -> 2232
    //   2007: goto -> 2014
    //   2010: invokestatic a : (Ljava/lang/Throwable;)Ljava/lang/Throwable;
    //   2013: athrow
    //   2014: aload_3
    //   2015: getstatic burp/Ztuj.Zk : Ljava/lang/String;
    //   2018: getstatic burp/Zxso.ZF : Ljava/lang/Object;
    //   2021: checkcast java/math/BigInteger
    //   2024: invokevirtual intValue : ()I
    //   2027: bipush #32
    //   2029: irem
    //   2030: invokestatic abs : (I)I
    //   2033: invokevirtual charAt : (I)C
    //   2036: invokevirtual append : (C)Ljava/lang/StringBuilder;
    //   2039: pop
    //   2040: iload_2
    //   2041: ifne -> 2232
    //   2044: goto -> 2051
    //   2047: invokestatic a : (Ljava/lang/Throwable;)Ljava/lang/Throwable;
    //   2050: athrow
    //   2051: aload_3
    //   2052: getstatic burp/Zl_u.Zc : Ljava/lang/String;
    //   2055: getstatic burp/Zr8h.ZH : Ljava/lang/Object;
    //   2058: checkcast java/math/BigInteger
    //   2061: invokevirtual intValue : ()I
    //   2064: bipush #32
    //   2066: irem
    //   2067: invokestatic abs : (I)I
    //   2070: invokevirtual charAt : (I)C
    //   2073: invokevirtual append : (C)Ljava/lang/StringBuilder;
    //   2076: pop
    //   2077: iload_2
    //   2078: ifne -> 2232
    //   2081: goto -> 2088
    //   2084: invokestatic a : (Ljava/lang/Throwable;)Ljava/lang/Throwable;
    //   2087: athrow
    //   2088: aload_3
    //   2089: getstatic burp/Zr0u.Z_ : Ljava/lang/String;
    //   2092: getstatic burp/Zxso.ZF : Ljava/lang/Object;
    //   2095: checkcast java/math/BigInteger
    //   2098: invokevirtual intValue : ()I
    //   2101: bipush #32
    //   2103: irem
    //   2104: invokestatic abs : (I)I
    //   2107: invokevirtual charAt : (I)C
    //   2110: invokevirtual append : (C)Ljava/lang/StringBuilder;
    //   2113: pop
    //   2114: iload_2
    //   2115: ifne -> 2232
    //   2118: goto -> 2125
    //   2121: invokestatic a : (Ljava/lang/Throwable;)Ljava/lang/Throwable;
    //   2124: athrow
    //   2125: aload_3
    //   2126: getstatic burp/Zllw.Zg : Ljava/lang/String;
    //   2129: getstatic burp/Zg7p.Zb : Ljava/lang/Object;
    //   2132: checkcast java/math/BigInteger
    //   2135: invokevirtual intValue : ()I
    //   2138: bipush #32
    //   2140: irem
    //   2141: invokestatic abs : (I)I
    //   2144: invokevirtual charAt : (I)C
    //   2147: invokevirtual append : (C)Ljava/lang/StringBuilder;
    //   2150: pop
    //   2151: iload_2
    //   2152: ifne -> 2232
    //   2155: goto -> 2162
    //   2158: invokestatic a : (Ljava/lang/Throwable;)Ljava/lang/Throwable;
    //   2161: athrow
    //   2162: aload_3
    //   2163: getstatic burp/Zkyc.ZK : Ljava/lang/String;
    //   2166: getstatic burp/Zk9s.ZY : Ljava/lang/Object;
    //   2169: checkcast java/math/BigInteger
    //   2172: invokevirtual intValue : ()I
    //   2175: bipush #32
    //   2177: irem
    //   2178: invokestatic abs : (I)I
    //   2181: invokevirtual charAt : (I)C
    //   2184: invokevirtual append : (C)Ljava/lang/StringBuilder;
    //   2187: pop
    //   2188: iload_2
    //   2189: ifne -> 2232
    //   2192: goto -> 2199
    //   2195: invokestatic a : (Ljava/lang/Throwable;)Ljava/lang/Throwable;
    //   2198: athrow
    //   2199: aload_3
    //   2200: getstatic burp/Zxfu.Zo : Ljava/lang/String;
    //   2203: getstatic burp/Zxk9.ZI : Ljava/lang/Object;
    //   2206: checkcast java/math/BigInteger
    //   2209: invokevirtual intValue : ()I
    //   2212: bipush #32
    //   2214: irem
    //   2215: invokestatic abs : (I)I
    //   2218: invokevirtual charAt : (I)C
    //   2221: invokevirtual append : (C)Ljava/lang/StringBuilder;
    //   2224: pop
    //   2225: goto -> 2232
    //   2228: invokestatic a : (Ljava/lang/Throwable;)Ljava/lang/Throwable;
    //   2231: athrow
    //   2232: iinc #4, 1
    //   2235: iload_2
    //   2236: ifne -> 900
    //   2239: aload_3
    //   2240: invokevirtual toString : ()Ljava/lang/String;
    //   2243: putstatic burp/Zz1k.ZC : Ljava/lang/String;
    //   2246: sipush #31025
    //   2249: sipush #-24853
    //   2252: invokestatic a : (II)Ljava/lang/String;
    //   2255: iconst_1
    //   2256: ldc burp/Zry7
    //   2258: invokevirtual getClassLoader : ()Ljava/lang/ClassLoader;
    //   2261: invokestatic forName : (Ljava/lang/String;ZLjava/lang/ClassLoader;)Ljava/lang/Class;
    //   2264: invokevirtual getDeclaredFields : ()[Ljava/lang/reflect/Field;
    //   2267: astore #4
    //   2269: aload #4
    //   2271: arraylength
    //   2272: istore #5
    //   2274: iconst_0
    //   2275: istore #6
    //   2277: iload #6
    //   2279: iload #5
    //   2281: if_icmpge -> 2419
    //   2284: aload #4
    //   2286: iload #6
    //   2288: aaload
    //   2289: astore #7
    //   2291: aload #7
    //   2293: invokevirtual getModifiers : ()I
    //   2296: invokestatic isStatic : (I)Z
    //   2299: ifne -> 2309
    //   2302: goto -> 2412
    //   2305: invokestatic a : (Ljava/lang/Throwable;)Ljava/lang/Throwable;
    //   2308: athrow
    //   2309: aload #7
    //   2311: invokevirtual getType : ()Ljava/lang/Class;
    //   2314: astore #8
    //   2316: aload #8
    //   2318: ifnull -> 2399
    //   2321: aload #8
    //   2323: invokevirtual isPrimitive : ()Z
    //   2326: ifne -> 2399
    //   2329: goto -> 2336
    //   2332: invokestatic a : (Ljava/lang/Throwable;)Ljava/lang/Throwable;
    //   2335: athrow
    //   2336: aload #8
    //   2338: invokevirtual getPackage : ()Ljava/lang/Package;
    //   2341: ifnull -> 2399
    //   2344: goto -> 2351
    //   2347: invokestatic a : (Ljava/lang/Throwable;)Ljava/lang/Throwable;
    //   2350: athrow
    //   2351: aload #8
    //   2353: invokevirtual getPackage : ()Ljava/lang/Package;
    //   2356: invokevirtual getName : ()Ljava/lang/String;
    //   2359: ifnull -> 2399
    //   2362: goto -> 2369
    //   2365: invokestatic a : (Ljava/lang/Throwable;)Ljava/lang/Throwable;
    //   2368: athrow
    //   2369: aload #8
    //   2371: invokevirtual getPackage : ()Ljava/lang/Package;
    //   2374: invokevirtual getName : ()Ljava/lang/String;
    //   2377: sipush #31032
    //   2380: sipush #4755
    //   2383: invokestatic a : (II)Ljava/lang/String;
    //   2386: invokevirtual startsWith : (Ljava/lang/String;)Z
    //   2389: ifne -> 2399
    //   2392: goto -> 2399
    //   2395: invokestatic a : (Ljava/lang/Throwable;)Ljava/lang/Throwable;
    //   2398: athrow
    //   2399: aload #7
    //   2401: iconst_1
    //   2402: invokevirtual setAccessible : (Z)V
    //   2405: aload #7
    //   2407: aconst_null
    //   2408: invokevirtual get : (Ljava/lang/Object;)Ljava/lang/Object;
    //   2411: pop
    //   2412: iinc #6, 1
    //   2415: iload_2
    //   2416: ifne -> 2277
    //   2419: sipush #31024
    //   2422: sipush #3259
    //   2425: invokestatic a : (II)Ljava/lang/String;
    //   2428: invokestatic forName : (Ljava/lang/String;)Ljava/lang/Class;
    //   2431: invokevirtual getDeclaredMethods : ()[Ljava/lang/reflect/Method;
    //   2434: astore #4
    //   2436: aload #4
    //   2438: arraylength
    //   2439: istore #5
    //   2441: iconst_0
    //   2442: istore #6
    //   2444: iload #6
    //   2446: iload #5
    //   2448: if_icmpge -> 2581
    //   2451: aload #4
    //   2453: iload #6
    //   2455: aaload
    //   2456: astore #7
    //   2458: aload #7
    //   2460: invokevirtual getParameterTypes : ()[Ljava/lang/Class;
    //   2463: pop
    //   2464: aload #7
    //   2466: invokevirtual getModifiers : ()I
    //   2469: invokestatic isStatic : (I)Z
    //   2472: ifeq -> 2567
    //   2475: aload #7
    //   2477: invokevirtual getParameterTypes : ()[Ljava/lang/Class;
    //   2480: arraylength
    //   2481: iconst_2
    //   2482: if_icmpne -> 2567
    //   2485: goto -> 2492
    //   2488: invokestatic a : (Ljava/lang/Throwable;)Ljava/lang/Throwable;
    //   2491: athrow
    //   2492: aload #7
    //   2494: invokevirtual getReturnType : ()Ljava/lang/Class;
    //   2497: getstatic java/lang/Void.TYPE : Ljava/lang/Class;
    //   2500: invokevirtual equals : (Ljava/lang/Object;)Z
    //   2503: ifeq -> 2567
    //   2506: goto -> 2513
    //   2509: invokestatic a : (Ljava/lang/Throwable;)Ljava/lang/Throwable;
    //   2512: athrow
    //   2513: aload #7
    //   2515: iconst_1
    //   2516: invokevirtual setAccessible : (Z)V
    //   2519: aload #7
    //   2521: aconst_null
    //   2522: iconst_2
    //   2523: anewarray java/lang/Object
    //   2526: dup
    //   2527: iconst_0
    //   2528: aload_0
    //   2529: aastore
    //   2530: dup
    //   2531: iconst_1
    //   2532: aload_1
    //   2533: ifnonnull -> 2551
    //   2536: goto -> 2543
    //   2539: invokestatic a : (Ljava/lang/Throwable;)Ljava/lang/Throwable;
    //   2542: athrow
    //   2543: aload_1
    //   2544: goto -> 2558
    //   2547: invokestatic a : (Ljava/lang/Throwable;)Ljava/lang/Throwable;
    //   2550: athrow
    //   2551: aload_1
    //   2552: checkcast [B
    //   2555: invokevirtual clone : ()Ljava/lang/Object;
    //   2558: aastore
    //   2559: invokevirtual invoke : (Ljava/lang/Object;[Ljava/lang/Object;)Ljava/lang/Object;
    //   2562: pop
    //   2563: iload_2
    //   2564: ifne -> 2581
    //   2567: iinc #6, 1
    //   2570: iload_2
    //   2571: ifne -> 2444
    //   2574: goto -> 2581
    //   2577: invokestatic a : (Ljava/lang/Throwable;)Ljava/lang/Throwable;
    //   2580: athrow
    //   2581: getstatic burp/Zehi.Zb : Ljava/lang/Object;
    //   2584: checkcast java/math/BigInteger
    //   2587: invokevirtual toByteArray : ()[B
    //   2590: astore #4
    //   2592: bipush #32
    //   2594: newarray int
    //   2596: dup
    //   2597: iconst_0
    //   2598: ldc 943331329
    //   2600: iastore
    //   2601: dup
    //   2602: iconst_1
    //   2603: ldc 170788368
    //   2605: iastore
    //   2606: dup
    //   2607: iconst_2
    //   2608: ldc 1008414755
    //   2610: iastore
    //   2611: dup
    //   2612: iconst_3
    //   2613: ldc 187049985
    //   2615: iastore
    //   2616: dup
    //   2617: iconst_4
    //   2618: ldc 1010368540
    //   2620: iastore
    //   2621: dup
    //   2622: iconst_5
    //   2623: ldc 220604441
    //   2625: iastore
    //   2626: dup
    //   2627: bipush #6
    //   2629: ldc 940377620
    //   2631: iastore
    //   2632: dup
    //   2633: bipush #7
    //   2635: ldc 255209728
    //   2637: iastore
    //   2638: dup
    //   2639: bipush #8
    //   2641: ldc 689771012
    //   2643: iastore
    //   2644: dup
    //   2645: bipush #9
    //   2647: ldc 221709344
    //   2649: iastore
    //   2650: dup
    //   2651: bipush #10
    //   2653: ldc 957157408
    //   2655: iastore
    //   2656: dup
    //   2657: bipush #11
    //   2659: ldc 892536332
    //   2661: iastore
    //   2662: dup
    //   2663: bipush #12
    //   2665: ldc 722417666
    //   2667: iastore
    //   2668: dup
    //   2669: bipush #13
    //   2671: ldc 1026621720
    //   2673: iastore
    //   2674: dup
    //   2675: bipush #14
    //   2677: ldc 655302664
    //   2679: iastore
    //   2680: dup
    //   2681: bipush #15
    //   2683: ldc 890966315
    //   2685: iastore
    //   2686: dup
    //   2687: bipush #16
    //   2689: ldc 187632156
    //   2691: iastore
    //   2692: dup
    //   2693: bipush #17
    //   2695: ldc 874189824
    //   2697: iastore
    //   2698: dup
    //   2699: bipush #18
    //   2701: ldc 254150144
    //   2703: iastore
    //   2704: dup
    //   2705: bipush #19
    //   2707: ldc 924386310
    //   2709: iastore
    //   2710: dup
    //   2711: bipush #20
    //   2713: ldc 121057538
    //   2715: iastore
    //   2716: dup
    //   2717: bipush #21
    //   2719: ldc 840500228
    //   2721: iastore
    //   2722: dup
    //   2723: bipush #22
    //   2725: ldc 389160971
    //   2727: iastore
    //   2728: dup
    //   2729: bipush #23
    //   2731: ldc 907870729
    //   2733: iastore
    //   2734: dup
    //   2735: bipush #24
    //   2737: ldc 389426184
    //   2739: iastore
    //   2740: dup
    //   2741: bipush #25
    //   2743: ldc 973875457
    //   2745: iastore
    //   2746: dup
    //   2747: bipush #26
    //   2749: ldc 372376604
    //   2751: iastore
    //   2752: dup
    //   2753: bipush #27
    //   2755: ldc 707731490
    //   2757: iastore
    //   2758: dup
    //   2759: bipush #28
    //   2761: ldc 1043334948
    //   2763: iastore
    //   2764: dup
    //   2765: bipush #29
    //   2767: ldc 439222784
    //   2769: iastore
    //   2770: dup
    //   2771: bipush #30
    //   2773: ldc 876216579
    //   2775: iastore
    //   2776: dup
    //   2777: bipush #31
    //   2779: ldc 455999525
    //   2781: iastore
    //   2782: astore #6
    //   2784: bipush #8
    //   2786: aload #4
    //   2788: arraylength
    //   2789: bipush #8
    //   2791: irem
    //   2792: isub
    //   2793: istore #7
    //   2795: aload #4
    //   2797: arraylength
    //   2798: iload #7
    //   2800: iadd
    //   2801: newarray byte
    //   2803: astore #8
    //   2805: iconst_0
    //   2806: istore #9
    //   2808: iload #9
    //   2810: aload #4
    //   2812: arraylength
    //   2813: if_icmpge -> 2833
    //   2816: aload #8
    //   2818: iload #9
    //   2820: aload #4
    //   2822: iload #9
    //   2824: baload
    //   2825: bastore
    //   2826: iinc #9, 1
    //   2829: iload_2
    //   2830: ifne -> 2808
    //   2833: aload #4
    //   2835: arraylength
    //   2836: istore #9
    //   2838: iload #9
    //   2840: aload #8
    //   2842: arraylength
    //   2843: if_icmpge -> 2861
    //   2846: aload #8
    //   2848: iload #9
    //   2850: iload #7
    //   2852: i2b
    //   2853: bastore
    //   2854: iinc #9, 1
    //   2857: iload_2
    //   2858: ifne -> 2838
    //   2861: aload #8
    //   2863: astore #4
    //   2865: bipush #64
    //   2867: newarray int
    //   2869: dup
    //   2870: iconst_0
    //   2871: ldc 16843776
    //   2873: iastore
    //   2874: dup
    //   2875: iconst_1
    //   2876: iconst_0
    //   2877: iastore
    //   2878: dup
    //   2879: iconst_2
    //   2880: ldc 65536
    //   2882: iastore
    //   2883: dup
    //   2884: iconst_3
    //   2885: ldc 16843780
    //   2887: iastore
    //   2888: dup
    //   2889: iconst_4
    //   2890: ldc 16842756
    //   2892: iastore
    //   2893: dup
    //   2894: iconst_5
    //   2895: ldc 66564
    //   2897: iastore
    //   2898: dup
    //   2899: bipush #6
    //   2901: iconst_4
    //   2902: iastore
    //   2903: dup
    //   2904: bipush #7
    //   2906: ldc 65536
    //   2908: iastore
    //   2909: dup
    //   2910: bipush #8
    //   2912: sipush #1024
    //   2915: iastore
    //   2916: dup
    //   2917: bipush #9
    //   2919: ldc 16843776
    //   2921: iastore
    //   2922: dup
    //   2923: bipush #10
    //   2925: ldc 16843780
    //   2927: iastore
    //   2928: dup
    //   2929: bipush #11
    //   2931: sipush #1024
    //   2934: iastore
    //   2935: dup
    //   2936: bipush #12
    //   2938: ldc 16778244
    //   2940: iastore
    //   2941: dup
    //   2942: bipush #13
    //   2944: ldc 16842756
    //   2946: iastore
    //   2947: dup
    //   2948: bipush #14
    //   2950: ldc 16777216
    //   2952: iastore
    //   2953: dup
    //   2954: bipush #15
    //   2956: iconst_4
    //   2957: iastore
    //   2958: dup
    //   2959: bipush #16
    //   2961: sipush #1028
    //   2964: iastore
    //   2965: dup
    //   2966: bipush #17
    //   2968: ldc 16778240
    //   2970: iastore
    //   2971: dup
    //   2972: bipush #18
    //   2974: ldc 16778240
    //   2976: iastore
    //   2977: dup
    //   2978: bipush #19
    //   2980: ldc 66560
    //   2982: iastore
    //   2983: dup
    //   2984: bipush #20
    //   2986: ldc 66560
    //   2988: iastore
    //   2989: dup
    //   2990: bipush #21
    //   2992: ldc 16842752
    //   2994: iastore
    //   2995: dup
    //   2996: bipush #22
    //   2998: ldc 16842752
    //   3000: iastore
    //   3001: dup
    //   3002: bipush #23
    //   3004: ldc 16778244
    //   3006: iastore
    //   3007: dup
    //   3008: bipush #24
    //   3010: ldc 65540
    //   3012: iastore
    //   3013: dup
    //   3014: bipush #25
    //   3016: ldc 16777220
    //   3018: iastore
    //   3019: dup
    //   3020: bipush #26
    //   3022: ldc 16777220
    //   3024: iastore
    //   3025: dup
    //   3026: bipush #27
    //   3028: ldc 65540
    //   3030: iastore
    //   3031: dup
    //   3032: bipush #28
    //   3034: iconst_0
    //   3035: iastore
    //   3036: dup
    //   3037: bipush #29
    //   3039: sipush #1028
    //   3042: iastore
    //   3043: dup
    //   3044: bipush #30
    //   3046: ldc 66564
    //   3048: iastore
    //   3049: dup
    //   3050: bipush #31
    //   3052: ldc 16777216
    //   3054: iastore
    //   3055: dup
    //   3056: bipush #32
    //   3058: ldc 65536
    //   3060: iastore
    //   3061: dup
    //   3062: bipush #33
    //   3064: ldc 16843780
    //   3066: iastore
    //   3067: dup
    //   3068: bipush #34
    //   3070: iconst_4
    //   3071: iastore
    //   3072: dup
    //   3073: bipush #35
    //   3075: ldc 16842752
    //   3077: iastore
    //   3078: dup
    //   3079: bipush #36
    //   3081: ldc 16843776
    //   3083: iastore
    //   3084: dup
    //   3085: bipush #37
    //   3087: ldc 16777216
    //   3089: iastore
    //   3090: dup
    //   3091: bipush #38
    //   3093: ldc 16777216
    //   3095: iastore
    //   3096: dup
    //   3097: bipush #39
    //   3099: sipush #1024
    //   3102: iastore
    //   3103: dup
    //   3104: bipush #40
    //   3106: ldc 16842756
    //   3108: iastore
    //   3109: dup
    //   3110: bipush #41
    //   3112: ldc 65536
    //   3114: iastore
    //   3115: dup
    //   3116: bipush #42
    //   3118: ldc 66560
    //   3120: iastore
    //   3121: dup
    //   3122: bipush #43
    //   3124: ldc 16777220
    //   3126: iastore
    //   3127: dup
    //   3128: bipush #44
    //   3130: sipush #1024
    //   3133: iastore
    //   3134: dup
    //   3135: bipush #45
    //   3137: iconst_4
    //   3138: iastore
    //   3139: dup
    //   3140: bipush #46
    //   3142: ldc 16778244
    //   3144: iastore
    //   3145: dup
    //   3146: bipush #47
    //   3148: ldc 66564
    //   3150: iastore
    //   3151: dup
    //   3152: bipush #48
    //   3154: ldc 16843780
    //   3156: iastore
    //   3157: dup
    //   3158: bipush #49
    //   3160: ldc 65540
    //   3162: iastore
    //   3163: dup
    //   3164: bipush #50
    //   3166: ldc 16842752
    //   3168: iastore
    //   3169: dup
    //   3170: bipush #51
    //   3172: ldc 16778244
    //   3174: iastore
    //   3175: dup
    //   3176: bipush #52
    //   3178: ldc 16777220
    //   3180: iastore
    //   3181: dup
    //   3182: bipush #53
    //   3184: sipush #1028
    //   3187: iastore
    //   3188: dup
    //   3189: bipush #54
    //   3191: ldc 66564
    //   3193: iastore
    //   3194: dup
    //   3195: bipush #55
    //   3197: ldc 16843776
    //   3199: iastore
    //   3200: dup
    //   3201: bipush #56
    //   3203: sipush #1028
    //   3206: iastore
    //   3207: dup
    //   3208: bipush #57
    //   3210: ldc 16778240
    //   3212: iastore
    //   3213: dup
    //   3214: bipush #58
    //   3216: ldc 16778240
    //   3218: iastore
    //   3219: dup
    //   3220: bipush #59
    //   3222: iconst_0
    //   3223: iastore
    //   3224: dup
    //   3225: bipush #60
    //   3227: ldc 65540
    //   3229: iastore
    //   3230: dup
    //   3231: bipush #61
    //   3233: ldc 66560
    //   3235: iastore
    //   3236: dup
    //   3237: bipush #62
    //   3239: iconst_0
    //   3240: iastore
    //   3241: dup
    //   3242: bipush #63
    //   3244: ldc 16842756
    //   3246: iastore
    //   3247: astore #9
    //   3249: bipush #64
    //   3251: newarray int
    //   3253: dup
    //   3254: iconst_0
    //   3255: ldc -2146402272
    //   3257: iastore
    //   3258: dup
    //   3259: iconst_1
    //   3260: ldc -2147450880
    //   3262: iastore
    //   3263: dup
    //   3264: iconst_2
    //   3265: ldc 32768
    //   3267: iastore
    //   3268: dup
    //   3269: iconst_3
    //   3270: ldc 1081376
    //   3272: iastore
    //   3273: dup
    //   3274: iconst_4
    //   3275: ldc 1048576
    //   3277: iastore
    //   3278: dup
    //   3279: iconst_5
    //   3280: bipush #32
    //   3282: iastore
    //   3283: dup
    //   3284: bipush #6
    //   3286: ldc -2146435040
    //   3288: iastore
    //   3289: dup
    //   3290: bipush #7
    //   3292: ldc -2147450848
    //   3294: iastore
    //   3295: dup
    //   3296: bipush #8
    //   3298: ldc -2147483616
    //   3300: iastore
    //   3301: dup
    //   3302: bipush #9
    //   3304: ldc -2146402272
    //   3306: iastore
    //   3307: dup
    //   3308: bipush #10
    //   3310: ldc -2146402304
    //   3312: iastore
    //   3313: dup
    //   3314: bipush #11
    //   3316: ldc -2147483648
    //   3318: iastore
    //   3319: dup
    //   3320: bipush #12
    //   3322: ldc -2147450880
    //   3324: iastore
    //   3325: dup
    //   3326: bipush #13
    //   3328: ldc 1048576
    //   3330: iastore
    //   3331: dup
    //   3332: bipush #14
    //   3334: bipush #32
    //   3336: iastore
    //   3337: dup
    //   3338: bipush #15
    //   3340: ldc -2146435040
    //   3342: iastore
    //   3343: dup
    //   3344: bipush #16
    //   3346: ldc 1081344
    //   3348: iastore
    //   3349: dup
    //   3350: bipush #17
    //   3352: ldc 1048608
    //   3354: iastore
    //   3355: dup
    //   3356: bipush #18
    //   3358: ldc -2147450848
    //   3360: iastore
    //   3361: dup
    //   3362: bipush #19
    //   3364: iconst_0
    //   3365: iastore
    //   3366: dup
    //   3367: bipush #20
    //   3369: ldc -2147483648
    //   3371: iastore
    //   3372: dup
    //   3373: bipush #21
    //   3375: ldc 32768
    //   3377: iastore
    //   3378: dup
    //   3379: bipush #22
    //   3381: ldc 1081376
    //   3383: iastore
    //   3384: dup
    //   3385: bipush #23
    //   3387: ldc -2146435072
    //   3389: iastore
    //   3390: dup
    //   3391: bipush #24
    //   3393: ldc 1048608
    //   3395: iastore
    //   3396: dup
    //   3397: bipush #25
    //   3399: ldc -2147483616
    //   3401: iastore
    //   3402: dup
    //   3403: bipush #26
    //   3405: iconst_0
    //   3406: iastore
    //   3407: dup
    //   3408: bipush #27
    //   3410: ldc 1081344
    //   3412: iastore
    //   3413: dup
    //   3414: bipush #28
    //   3416: ldc 32800
    //   3418: iastore
    //   3419: dup
    //   3420: bipush #29
    //   3422: ldc -2146402304
    //   3424: iastore
    //   3425: dup
    //   3426: bipush #30
    //   3428: ldc -2146435072
    //   3430: iastore
    //   3431: dup
    //   3432: bipush #31
    //   3434: ldc 32800
    //   3436: iastore
    //   3437: dup
    //   3438: bipush #32
    //   3440: iconst_0
    //   3441: iastore
    //   3442: dup
    //   3443: bipush #33
    //   3445: ldc 1081376
    //   3447: iastore
    //   3448: dup
    //   3449: bipush #34
    //   3451: ldc -2146435040
    //   3453: iastore
    //   3454: dup
    //   3455: bipush #35
    //   3457: ldc 1048576
    //   3459: iastore
    //   3460: dup
    //   3461: bipush #36
    //   3463: ldc -2147450848
    //   3465: iastore
    //   3466: dup
    //   3467: bipush #37
    //   3469: ldc -2146435072
    //   3471: iastore
    //   3472: dup
    //   3473: bipush #38
    //   3475: ldc -2146402304
    //   3477: iastore
    //   3478: dup
    //   3479: bipush #39
    //   3481: ldc 32768
    //   3483: iastore
    //   3484: dup
    //   3485: bipush #40
    //   3487: ldc -2146435072
    //   3489: iastore
    //   3490: dup
    //   3491: bipush #41
    //   3493: ldc -2147450880
    //   3495: iastore
    //   3496: dup
    //   3497: bipush #42
    //   3499: bipush #32
    //   3501: iastore
    //   3502: dup
    //   3503: bipush #43
    //   3505: ldc -2146402272
    //   3507: iastore
    //   3508: dup
    //   3509: bipush #44
    //   3511: ldc 1081376
    //   3513: iastore
    //   3514: dup
    //   3515: bipush #45
    //   3517: bipush #32
    //   3519: iastore
    //   3520: dup
    //   3521: bipush #46
    //   3523: ldc 32768
    //   3525: iastore
    //   3526: dup
    //   3527: bipush #47
    //   3529: ldc -2147483648
    //   3531: iastore
    //   3532: dup
    //   3533: bipush #48
    //   3535: ldc 32800
    //   3537: iastore
    //   3538: dup
    //   3539: bipush #49
    //   3541: ldc -2146402304
    //   3543: iastore
    //   3544: dup
    //   3545: bipush #50
    //   3547: ldc 1048576
    //   3549: iastore
    //   3550: dup
    //   3551: bipush #51
    //   3553: ldc -2147483616
    //   3555: iastore
    //   3556: dup
    //   3557: bipush #52
    //   3559: ldc 1048608
    //   3561: iastore
    //   3562: dup
    //   3563: bipush #53
    //   3565: ldc -2147450848
    //   3567: iastore
    //   3568: dup
    //   3569: bipush #54
    //   3571: ldc -2147483616
    //   3573: iastore
    //   3574: dup
    //   3575: bipush #55
    //   3577: ldc 1048608
    //   3579: iastore
    //   3580: dup
    //   3581: bipush #56
    //   3583: ldc 1081344
    //   3585: iastore
    //   3586: dup
    //   3587: bipush #57
    //   3589: iconst_0
    //   3590: iastore
    //   3591: dup
    //   3592: bipush #58
    //   3594: ldc -2147450880
    //   3596: iastore
    //   3597: dup
    //   3598: bipush #59
    //   3600: ldc 32800
    //   3602: iastore
    //   3603: dup
    //   3604: bipush #60
    //   3606: ldc -2147483648
    //   3608: iastore
    //   3609: dup
    //   3610: bipush #61
    //   3612: ldc -2146435040
    //   3614: iastore
    //   3615: dup
    //   3616: bipush #62
    //   3618: ldc -2146402272
    //   3620: iastore
    //   3621: dup
    //   3622: bipush #63
    //   3624: ldc 1081344
    //   3626: iastore
    //   3627: astore #10
    //   3629: bipush #64
    //   3631: newarray int
    //   3633: dup
    //   3634: iconst_0
    //   3635: sipush #520
    //   3638: iastore
    //   3639: dup
    //   3640: iconst_1
    //   3641: ldc 134349312
    //   3643: iastore
    //   3644: dup
    //   3645: iconst_2
    //   3646: iconst_0
    //   3647: iastore
    //   3648: dup
    //   3649: iconst_3
    //   3650: ldc 134348808
    //   3652: iastore
    //   3653: dup
    //   3654: iconst_4
    //   3655: ldc 134218240
    //   3657: iastore
    //   3658: dup
    //   3659: iconst_5
    //   3660: iconst_0
    //   3661: iastore
    //   3662: dup
    //   3663: bipush #6
    //   3665: ldc 131592
    //   3667: iastore
    //   3668: dup
    //   3669: bipush #7
    //   3671: ldc 134218240
    //   3673: iastore
    //   3674: dup
    //   3675: bipush #8
    //   3677: ldc 131080
    //   3679: iastore
    //   3680: dup
    //   3681: bipush #9
    //   3683: ldc 134217736
    //   3685: iastore
    //   3686: dup
    //   3687: bipush #10
    //   3689: ldc 134217736
    //   3691: iastore
    //   3692: dup
    //   3693: bipush #11
    //   3695: ldc 131072
    //   3697: iastore
    //   3698: dup
    //   3699: bipush #12
    //   3701: ldc 134349320
    //   3703: iastore
    //   3704: dup
    //   3705: bipush #13
    //   3707: ldc 131080
    //   3709: iastore
    //   3710: dup
    //   3711: bipush #14
    //   3713: ldc 134348800
    //   3715: iastore
    //   3716: dup
    //   3717: bipush #15
    //   3719: sipush #520
    //   3722: iastore
    //   3723: dup
    //   3724: bipush #16
    //   3726: ldc 134217728
    //   3728: iastore
    //   3729: dup
    //   3730: bipush #17
    //   3732: bipush #8
    //   3734: iastore
    //   3735: dup
    //   3736: bipush #18
    //   3738: ldc 134349312
    //   3740: iastore
    //   3741: dup
    //   3742: bipush #19
    //   3744: sipush #512
    //   3747: iastore
    //   3748: dup
    //   3749: bipush #20
    //   3751: ldc 131584
    //   3753: iastore
    //   3754: dup
    //   3755: bipush #21
    //   3757: ldc 134348800
    //   3759: iastore
    //   3760: dup
    //   3761: bipush #22
    //   3763: ldc 134348808
    //   3765: iastore
    //   3766: dup
    //   3767: bipush #23
    //   3769: ldc 131592
    //   3771: iastore
    //   3772: dup
    //   3773: bipush #24
    //   3775: ldc 134218248
    //   3777: iastore
    //   3778: dup
    //   3779: bipush #25
    //   3781: ldc 131584
    //   3783: iastore
    //   3784: dup
    //   3785: bipush #26
    //   3787: ldc 131072
    //   3789: iastore
    //   3790: dup
    //   3791: bipush #27
    //   3793: ldc 134218248
    //   3795: iastore
    //   3796: dup
    //   3797: bipush #28
    //   3799: bipush #8
    //   3801: iastore
    //   3802: dup
    //   3803: bipush #29
    //   3805: ldc 134349320
    //   3807: iastore
    //   3808: dup
    //   3809: bipush #30
    //   3811: sipush #512
    //   3814: iastore
    //   3815: dup
    //   3816: bipush #31
    //   3818: ldc 134217728
    //   3820: iastore
    //   3821: dup
    //   3822: bipush #32
    //   3824: ldc 134349312
    //   3826: iastore
    //   3827: dup
    //   3828: bipush #33
    //   3830: ldc 134217728
    //   3832: iastore
    //   3833: dup
    //   3834: bipush #34
    //   3836: ldc 131080
    //   3838: iastore
    //   3839: dup
    //   3840: bipush #35
    //   3842: sipush #520
    //   3845: iastore
    //   3846: dup
    //   3847: bipush #36
    //   3849: ldc 131072
    //   3851: iastore
    //   3852: dup
    //   3853: bipush #37
    //   3855: ldc 134349312
    //   3857: iastore
    //   3858: dup
    //   3859: bipush #38
    //   3861: ldc 134218240
    //   3863: iastore
    //   3864: dup
    //   3865: bipush #39
    //   3867: iconst_0
    //   3868: iastore
    //   3869: dup
    //   3870: bipush #40
    //   3872: sipush #512
    //   3875: iastore
    //   3876: dup
    //   3877: bipush #41
    //   3879: ldc 131080
    //   3881: iastore
    //   3882: dup
    //   3883: bipush #42
    //   3885: ldc 134349320
    //   3887: iastore
    //   3888: dup
    //   3889: bipush #43
    //   3891: ldc 134218240
    //   3893: iastore
    //   3894: dup
    //   3895: bipush #44
    //   3897: ldc 134217736
    //   3899: iastore
    //   3900: dup
    //   3901: bipush #45
    //   3903: sipush #512
    //   3906: iastore
    //   3907: dup
    //   3908: bipush #46
    //   3910: iconst_0
    //   3911: iastore
    //   3912: dup
    //   3913: bipush #47
    //   3915: ldc 134348808
    //   3917: iastore
    //   3918: dup
    //   3919: bipush #48
    //   3921: ldc 134218248
    //   3923: iastore
    //   3924: dup
    //   3925: bipush #49
    //   3927: ldc 131072
    //   3929: iastore
    //   3930: dup
    //   3931: bipush #50
    //   3933: ldc 134217728
    //   3935: iastore
    //   3936: dup
    //   3937: bipush #51
    //   3939: ldc 134349320
    //   3941: iastore
    //   3942: dup
    //   3943: bipush #52
    //   3945: bipush #8
    //   3947: iastore
    //   3948: dup
    //   3949: bipush #53
    //   3951: ldc 131592
    //   3953: iastore
    //   3954: dup
    //   3955: bipush #54
    //   3957: ldc 131584
    //   3959: iastore
    //   3960: dup
    //   3961: bipush #55
    //   3963: ldc 134217736
    //   3965: iastore
    //   3966: dup
    //   3967: bipush #56
    //   3969: ldc 134348800
    //   3971: iastore
    //   3972: dup
    //   3973: bipush #57
    //   3975: ldc 134218248
    //   3977: iastore
    //   3978: dup
    //   3979: bipush #58
    //   3981: sipush #520
    //   3984: iastore
    //   3985: dup
    //   3986: bipush #59
    //   3988: ldc 134348800
    //   3990: iastore
    //   3991: dup
    //   3992: bipush #60
    //   3994: ldc 131592
    //   3996: iastore
    //   3997: dup
    //   3998: bipush #61
    //   4000: bipush #8
    //   4002: iastore
    //   4003: dup
    //   4004: bipush #62
    //   4006: ldc 134348808
    //   4008: iastore
    //   4009: dup
    //   4010: bipush #63
    //   4012: ldc 131584
    //   4014: iastore
    //   4015: astore #11
    //   4017: bipush #64
    //   4019: newarray int
    //   4021: dup
    //   4022: iconst_0
    //   4023: ldc 8396801
    //   4025: iastore
    //   4026: dup
    //   4027: iconst_1
    //   4028: sipush #8321
    //   4031: iastore
    //   4032: dup
    //   4033: iconst_2
    //   4034: sipush #8321
    //   4037: iastore
    //   4038: dup
    //   4039: iconst_3
    //   4040: sipush #128
    //   4043: iastore
    //   4044: dup
    //   4045: iconst_4
    //   4046: ldc 8396928
    //   4048: iastore
    //   4049: dup
    //   4050: iconst_5
    //   4051: ldc 8388737
    //   4053: iastore
    //   4054: dup
    //   4055: bipush #6
    //   4057: ldc 8388609
    //   4059: iastore
    //   4060: dup
    //   4061: bipush #7
    //   4063: sipush #8193
    //   4066: iastore
    //   4067: dup
    //   4068: bipush #8
    //   4070: iconst_0
    //   4071: iastore
    //   4072: dup
    //   4073: bipush #9
    //   4075: ldc 8396800
    //   4077: iastore
    //   4078: dup
    //   4079: bipush #10
    //   4081: ldc 8396800
    //   4083: iastore
    //   4084: dup
    //   4085: bipush #11
    //   4087: ldc 8396929
    //   4089: iastore
    //   4090: dup
    //   4091: bipush #12
    //   4093: sipush #129
    //   4096: iastore
    //   4097: dup
    //   4098: bipush #13
    //   4100: iconst_0
    //   4101: iastore
    //   4102: dup
    //   4103: bipush #14
    //   4105: ldc 8388736
    //   4107: iastore
    //   4108: dup
    //   4109: bipush #15
    //   4111: ldc 8388609
    //   4113: iastore
    //   4114: dup
    //   4115: bipush #16
    //   4117: iconst_1
    //   4118: iastore
    //   4119: dup
    //   4120: bipush #17
    //   4122: sipush #8192
    //   4125: iastore
    //   4126: dup
    //   4127: bipush #18
    //   4129: ldc 8388608
    //   4131: iastore
    //   4132: dup
    //   4133: bipush #19
    //   4135: ldc 8396801
    //   4137: iastore
    //   4138: dup
    //   4139: bipush #20
    //   4141: sipush #128
    //   4144: iastore
    //   4145: dup
    //   4146: bipush #21
    //   4148: ldc 8388608
    //   4150: iastore
    //   4151: dup
    //   4152: bipush #22
    //   4154: sipush #8193
    //   4157: iastore
    //   4158: dup
    //   4159: bipush #23
    //   4161: sipush #8320
    //   4164: iastore
    //   4165: dup
    //   4166: bipush #24
    //   4168: ldc 8388737
    //   4170: iastore
    //   4171: dup
    //   4172: bipush #25
    //   4174: iconst_1
    //   4175: iastore
    //   4176: dup
    //   4177: bipush #26
    //   4179: sipush #8320
    //   4182: iastore
    //   4183: dup
    //   4184: bipush #27
    //   4186: ldc 8388736
    //   4188: iastore
    //   4189: dup
    //   4190: bipush #28
    //   4192: sipush #8192
    //   4195: iastore
    //   4196: dup
    //   4197: bipush #29
    //   4199: ldc 8396928
    //   4201: iastore
    //   4202: dup
    //   4203: bipush #30
    //   4205: ldc 8396929
    //   4207: iastore
    //   4208: dup
    //   4209: bipush #31
    //   4211: sipush #129
    //   4214: iastore
    //   4215: dup
    //   4216: bipush #32
    //   4218: ldc 8388736
    //   4220: iastore
    //   4221: dup
    //   4222: bipush #33
    //   4224: ldc 8388609
    //   4226: iastore
    //   4227: dup
    //   4228: bipush #34
    //   4230: ldc 8396800
    //   4232: iastore
    //   4233: dup
    //   4234: bipush #35
    //   4236: ldc 8396929
    //   4238: iastore
    //   4239: dup
    //   4240: bipush #36
    //   4242: sipush #129
    //   4245: iastore
    //   4246: dup
    //   4247: bipush #37
    //   4249: iconst_0
    //   4250: iastore
    //   4251: dup
    //   4252: bipush #38
    //   4254: iconst_0
    //   4255: iastore
    //   4256: dup
    //   4257: bipush #39
    //   4259: ldc 8396800
    //   4261: iastore
    //   4262: dup
    //   4263: bipush #40
    //   4265: sipush #8320
    //   4268: iastore
    //   4269: dup
    //   4270: bipush #41
    //   4272: ldc 8388736
    //   4274: iastore
    //   4275: dup
    //   4276: bipush #42
    //   4278: ldc 8388737
    //   4280: iastore
    //   4281: dup
    //   4282: bipush #43
    //   4284: iconst_1
    //   4285: iastore
    //   4286: dup
    //   4287: bipush #44
    //   4289: ldc 8396801
    //   4291: iastore
    //   4292: dup
    //   4293: bipush #45
    //   4295: sipush #8321
    //   4298: iastore
    //   4299: dup
    //   4300: bipush #46
    //   4302: sipush #8321
    //   4305: iastore
    //   4306: dup
    //   4307: bipush #47
    //   4309: sipush #128
    //   4312: iastore
    //   4313: dup
    //   4314: bipush #48
    //   4316: ldc 8396929
    //   4318: iastore
    //   4319: dup
    //   4320: bipush #49
    //   4322: sipush #129
    //   4325: iastore
    //   4326: dup
    //   4327: bipush #50
    //   4329: iconst_1
    //   4330: iastore
    //   4331: dup
    //   4332: bipush #51
    //   4334: sipush #8192
    //   4337: iastore
    //   4338: dup
    //   4339: bipush #52
    //   4341: ldc 8388609
    //   4343: iastore
    //   4344: dup
    //   4345: bipush #53
    //   4347: sipush #8193
    //   4350: iastore
    //   4351: dup
    //   4352: bipush #54
    //   4354: ldc 8396928
    //   4356: iastore
    //   4357: dup
    //   4358: bipush #55
    //   4360: ldc 8388737
    //   4362: iastore
    //   4363: dup
    //   4364: bipush #56
    //   4366: sipush #8193
    //   4369: iastore
    //   4370: dup
    //   4371: bipush #57
    //   4373: sipush #8320
    //   4376: iastore
    //   4377: dup
    //   4378: bipush #58
    //   4380: ldc 8388608
    //   4382: iastore
    //   4383: dup
    //   4384: bipush #59
    //   4386: ldc 8396801
    //   4388: iastore
    //   4389: dup
    //   4390: bipush #60
    //   4392: sipush #128
    //   4395: iastore
    //   4396: dup
    //   4397: bipush #61
    //   4399: ldc 8388608
    //   4401: iastore
    //   4402: dup
    //   4403: bipush #62
    //   4405: sipush #8192
    //   4408: iastore
    //   4409: dup
    //   4410: bipush #63
    //   4412: ldc 8396928
    //   4414: iastore
    //   4415: astore #12
    //   4417: bipush #64
    //   4419: newarray int
    //   4421: dup
    //   4422: iconst_0
    //   4423: sipush #256
    //   4426: iastore
    //   4427: dup
    //   4428: iconst_1
    //   4429: ldc 34078976
    //   4431: iastore
    //   4432: dup
    //   4433: iconst_2
    //   4434: ldc 34078720
    //   4436: iastore
    //   4437: dup
    //   4438: iconst_3
    //   4439: ldc 1107296512
    //   4441: iastore
    //   4442: dup
    //   4443: iconst_4
    //   4444: ldc 524288
    //   4446: iastore
    //   4447: dup
    //   4448: iconst_5
    //   4449: sipush #256
    //   4452: iastore
    //   4453: dup
    //   4454: bipush #6
    //   4456: ldc 1073741824
    //   4458: iastore
    //   4459: dup
    //   4460: bipush #7
    //   4462: ldc 34078720
    //   4464: iastore
    //   4465: dup
    //   4466: bipush #8
    //   4468: ldc 1074266368
    //   4470: iastore
    //   4471: dup
    //   4472: bipush #9
    //   4474: ldc 524288
    //   4476: iastore
    //   4477: dup
    //   4478: bipush #10
    //   4480: ldc 33554688
    //   4482: iastore
    //   4483: dup
    //   4484: bipush #11
    //   4486: ldc 1074266368
    //   4488: iastore
    //   4489: dup
    //   4490: bipush #12
    //   4492: ldc 1107296512
    //   4494: iastore
    //   4495: dup
    //   4496: bipush #13
    //   4498: ldc 1107820544
    //   4500: iastore
    //   4501: dup
    //   4502: bipush #14
    //   4504: ldc 524544
    //   4506: iastore
    //   4507: dup
    //   4508: bipush #15
    //   4510: ldc 1073741824
    //   4512: iastore
    //   4513: dup
    //   4514: bipush #16
    //   4516: ldc 33554432
    //   4518: iastore
    //   4519: dup
    //   4520: bipush #17
    //   4522: ldc 1074266112
    //   4524: iastore
    //   4525: dup
    //   4526: bipush #18
    //   4528: ldc 1074266112
    //   4530: iastore
    //   4531: dup
    //   4532: bipush #19
    //   4534: iconst_0
    //   4535: iastore
    //   4536: dup
    //   4537: bipush #20
    //   4539: ldc 1073742080
    //   4541: iastore
    //   4542: dup
    //   4543: bipush #21
    //   4545: ldc 1107820800
    //   4547: iastore
    //   4548: dup
    //   4549: bipush #22
    //   4551: ldc 1107820800
    //   4553: iastore
    //   4554: dup
    //   4555: bipush #23
    //   4557: ldc 33554688
    //   4559: iastore
    //   4560: dup
    //   4561: bipush #24
    //   4563: ldc 1107820544
    //   4565: iastore
    //   4566: dup
    //   4567: bipush #25
    //   4569: ldc 1073742080
    //   4571: iastore
    //   4572: dup
    //   4573: bipush #26
    //   4575: iconst_0
    //   4576: iastore
    //   4577: dup
    //   4578: bipush #27
    //   4580: ldc 1107296256
    //   4582: iastore
    //   4583: dup
    //   4584: bipush #28
    //   4586: ldc 34078976
    //   4588: iastore
    //   4589: dup
    //   4590: bipush #29
    //   4592: ldc 33554432
    //   4594: iastore
    //   4595: dup
    //   4596: bipush #30
    //   4598: ldc 1107296256
    //   4600: iastore
    //   4601: dup
    //   4602: bipush #31
    //   4604: ldc 524544
    //   4606: iastore
    //   4607: dup
    //   4608: bipush #32
    //   4610: ldc 524288
    //   4612: iastore
    //   4613: dup
    //   4614: bipush #33
    //   4616: ldc 1107296512
    //   4618: iastore
    //   4619: dup
    //   4620: bipush #34
    //   4622: sipush #256
    //   4625: iastore
    //   4626: dup
    //   4627: bipush #35
    //   4629: ldc 33554432
    //   4631: iastore
    //   4632: dup
    //   4633: bipush #36
    //   4635: ldc 1073741824
    //   4637: iastore
    //   4638: dup
    //   4639: bipush #37
    //   4641: ldc 34078720
    //   4643: iastore
    //   4644: dup
    //   4645: bipush #38
    //   4647: ldc 1107296512
    //   4649: iastore
    //   4650: dup
    //   4651: bipush #39
    //   4653: ldc 1074266368
    //   4655: iastore
    //   4656: dup
    //   4657: bipush #40
    //   4659: ldc 33554688
    //   4661: iastore
    //   4662: dup
    //   4663: bipush #41
    //   4665: ldc 1073741824
    //   4667: iastore
    //   4668: dup
    //   4669: bipush #42
    //   4671: ldc 1107820544
    //   4673: iastore
    //   4674: dup
    //   4675: bipush #43
    //   4677: ldc 34078976
    //   4679: iastore
    //   4680: dup
    //   4681: bipush #44
    //   4683: ldc 1074266368
    //   4685: iastore
    //   4686: dup
    //   4687: bipush #45
    //   4689: sipush #256
    //   4692: iastore
    //   4693: dup
    //   4694: bipush #46
    //   4696: ldc 33554432
    //   4698: iastore
    //   4699: dup
    //   4700: bipush #47
    //   4702: ldc 1107820544
    //   4704: iastore
    //   4705: dup
    //   4706: bipush #48
    //   4708: ldc 1107820800
    //   4710: iastore
    //   4711: dup
    //   4712: bipush #49
    //   4714: ldc 524544
    //   4716: iastore
    //   4717: dup
    //   4718: bipush #50
    //   4720: ldc 1107296256
    //   4722: iastore
    //   4723: dup
    //   4724: bipush #51
    //   4726: ldc 1107820800
    //   4728: iastore
    //   4729: dup
    //   4730: bipush #52
    //   4732: ldc 34078720
    //   4734: iastore
    //   4735: dup
    //   4736: bipush #53
    //   4738: iconst_0
    //   4739: iastore
    //   4740: dup
    //   4741: bipush #54
    //   4743: ldc 1074266112
    //   4745: iastore
    //   4746: dup
    //   4747: bipush #55
    //   4749: ldc 1107296256
    //   4751: iastore
    //   4752: dup
    //   4753: bipush #56
    //   4755: ldc 524544
    //   4757: iastore
    //   4758: dup
    //   4759: bipush #57
    //   4761: ldc 33554688
    //   4763: iastore
    //   4764: dup
    //   4765: bipush #58
    //   4767: ldc 1073742080
    //   4769: iastore
    //   4770: dup
    //   4771: bipush #59
    //   4773: ldc 524288
    //   4775: iastore
    //   4776: dup
    //   4777: bipush #60
    //   4779: iconst_0
    //   4780: iastore
    //   4781: dup
    //   4782: bipush #61
    //   4784: ldc 1074266112
    //   4786: iastore
    //   4787: dup
    //   4788: bipush #62
    //   4790: ldc 34078976
    //   4792: iastore
    //   4793: dup
    //   4794: bipush #63
    //   4796: ldc 1073742080
    //   4798: iastore
    //   4799: astore #13
    //   4801: bipush #64
    //   4803: newarray int
    //   4805: dup
    //   4806: iconst_0
    //   4807: ldc 536870928
    //   4809: iastore
    //   4810: dup
    //   4811: iconst_1
    //   4812: ldc 541065216
    //   4814: iastore
    //   4815: dup
    //   4816: iconst_2
    //   4817: sipush #16384
    //   4820: iastore
    //   4821: dup
    //   4822: iconst_3
    //   4823: ldc 541081616
    //   4825: iastore
    //   4826: dup
    //   4827: iconst_4
    //   4828: ldc 541065216
    //   4830: iastore
    //   4831: dup
    //   4832: iconst_5
    //   4833: bipush #16
    //   4835: iastore
    //   4836: dup
    //   4837: bipush #6
    //   4839: ldc 541081616
    //   4841: iastore
    //   4842: dup
    //   4843: bipush #7
    //   4845: ldc 4194304
    //   4847: iastore
    //   4848: dup
    //   4849: bipush #8
    //   4851: ldc 536887296
    //   4853: iastore
    //   4854: dup
    //   4855: bipush #9
    //   4857: ldc 4210704
    //   4859: iastore
    //   4860: dup
    //   4861: bipush #10
    //   4863: ldc 4194304
    //   4865: iastore
    //   4866: dup
    //   4867: bipush #11
    //   4869: ldc 536870928
    //   4871: iastore
    //   4872: dup
    //   4873: bipush #12
    //   4875: ldc 4194320
    //   4877: iastore
    //   4878: dup
    //   4879: bipush #13
    //   4881: ldc 536887296
    //   4883: iastore
    //   4884: dup
    //   4885: bipush #14
    //   4887: ldc 536870912
    //   4889: iastore
    //   4890: dup
    //   4891: bipush #15
    //   4893: sipush #16400
    //   4896: iastore
    //   4897: dup
    //   4898: bipush #16
    //   4900: iconst_0
    //   4901: iastore
    //   4902: dup
    //   4903: bipush #17
    //   4905: ldc 4194320
    //   4907: iastore
    //   4908: dup
    //   4909: bipush #18
    //   4911: ldc 536887312
    //   4913: iastore
    //   4914: dup
    //   4915: bipush #19
    //   4917: sipush #16384
    //   4920: iastore
    //   4921: dup
    //   4922: bipush #20
    //   4924: ldc 4210688
    //   4926: iastore
    //   4927: dup
    //   4928: bipush #21
    //   4930: ldc 536887312
    //   4932: iastore
    //   4933: dup
    //   4934: bipush #22
    //   4936: bipush #16
    //   4938: iastore
    //   4939: dup
    //   4940: bipush #23
    //   4942: ldc 541065232
    //   4944: iastore
    //   4945: dup
    //   4946: bipush #24
    //   4948: ldc 541065232
    //   4950: iastore
    //   4951: dup
    //   4952: bipush #25
    //   4954: iconst_0
    //   4955: iastore
    //   4956: dup
    //   4957: bipush #26
    //   4959: ldc 4210704
    //   4961: iastore
    //   4962: dup
    //   4963: bipush #27
    //   4965: ldc 541081600
    //   4967: iastore
    //   4968: dup
    //   4969: bipush #28
    //   4971: sipush #16400
    //   4974: iastore
    //   4975: dup
    //   4976: bipush #29
    //   4978: ldc 4210688
    //   4980: iastore
    //   4981: dup
    //   4982: bipush #30
    //   4984: ldc 541081600
    //   4986: iastore
    //   4987: dup
    //   4988: bipush #31
    //   4990: ldc 536870912
    //   4992: iastore
    //   4993: dup
    //   4994: bipush #32
    //   4996: ldc 536887296
    //   4998: iastore
    //   4999: dup
    //   5000: bipush #33
    //   5002: bipush #16
    //   5004: iastore
    //   5005: dup
    //   5006: bipush #34
    //   5008: ldc 541065232
    //   5010: iastore
    //   5011: dup
    //   5012: bipush #35
    //   5014: ldc 4210688
    //   5016: iastore
    //   5017: dup
    //   5018: bipush #36
    //   5020: ldc 541081616
    //   5022: iastore
    //   5023: dup
    //   5024: bipush #37
    //   5026: ldc 4194304
    //   5028: iastore
    //   5029: dup
    //   5030: bipush #38
    //   5032: sipush #16400
    //   5035: iastore
    //   5036: dup
    //   5037: bipush #39
    //   5039: ldc 536870928
    //   5041: iastore
    //   5042: dup
    //   5043: bipush #40
    //   5045: ldc 4194304
    //   5047: iastore
    //   5048: dup
    //   5049: bipush #41
    //   5051: ldc 536887296
    //   5053: iastore
    //   5054: dup
    //   5055: bipush #42
    //   5057: ldc 536870912
    //   5059: iastore
    //   5060: dup
    //   5061: bipush #43
    //   5063: sipush #16400
    //   5066: iastore
    //   5067: dup
    //   5068: bipush #44
    //   5070: ldc 536870928
    //   5072: iastore
    //   5073: dup
    //   5074: bipush #45
    //   5076: ldc 541081616
    //   5078: iastore
    //   5079: dup
    //   5080: bipush #46
    //   5082: ldc 4210688
    //   5084: iastore
    //   5085: dup
    //   5086: bipush #47
    //   5088: ldc 541065216
    //   5090: iastore
    //   5091: dup
    //   5092: bipush #48
    //   5094: ldc 4210704
    //   5096: iastore
    //   5097: dup
    //   5098: bipush #49
    //   5100: ldc 541081600
    //   5102: iastore
    //   5103: dup
    //   5104: bipush #50
    //   5106: iconst_0
    //   5107: iastore
    //   5108: dup
    //   5109: bipush #51
    //   5111: ldc 541065232
    //   5113: iastore
    //   5114: dup
    //   5115: bipush #52
    //   5117: bipush #16
    //   5119: iastore
    //   5120: dup
    //   5121: bipush #53
    //   5123: sipush #16384
    //   5126: iastore
    //   5127: dup
    //   5128: bipush #54
    //   5130: ldc 541065216
    //   5132: iastore
    //   5133: dup
    //   5134: bipush #55
    //   5136: ldc 4210704
    //   5138: iastore
    //   5139: dup
    //   5140: bipush #56
    //   5142: sipush #16384
    //   5145: iastore
    //   5146: dup
    //   5147: bipush #57
    //   5149: ldc 4194320
    //   5151: iastore
    //   5152: dup
    //   5153: bipush #58
    //   5155: ldc 536887312
    //   5157: iastore
    //   5158: dup
    //   5159: bipush #59
    //   5161: iconst_0
    //   5162: iastore
    //   5163: dup
    //   5164: bipush #60
    //   5166: ldc 541081600
    //   5168: iastore
    //   5169: dup
    //   5170: bipush #61
    //   5172: ldc 536870912
    //   5174: iastore
    //   5175: dup
    //   5176: bipush #62
    //   5178: ldc 4194320
    //   5180: iastore
    //   5181: dup
    //   5182: bipush #63
    //   5184: ldc 536887312
    //   5186: iastore
    //   5187: astore #14
    //   5189: bipush #64
    //   5191: newarray int
    //   5193: dup
    //   5194: iconst_0
    //   5195: ldc 2097152
    //   5197: iastore
    //   5198: dup
    //   5199: iconst_1
    //   5200: ldc 69206018
    //   5202: iastore
    //   5203: dup
    //   5204: iconst_2
    //   5205: ldc 67110914
    //   5207: iastore
    //   5208: dup
    //   5209: iconst_3
    //   5210: iconst_0
    //   5211: iastore
    //   5212: dup
    //   5213: iconst_4
    //   5214: sipush #2048
    //   5217: iastore
    //   5218: dup
    //   5219: iconst_5
    //   5220: ldc 67110914
    //   5222: iastore
    //   5223: dup
    //   5224: bipush #6
    //   5226: ldc 2099202
    //   5228: iastore
    //   5229: dup
    //   5230: bipush #7
    //   5232: ldc 69208064
    //   5234: iastore
    //   5235: dup
    //   5236: bipush #8
    //   5238: ldc 69208066
    //   5240: iastore
    //   5241: dup
    //   5242: bipush #9
    //   5244: ldc 2097152
    //   5246: iastore
    //   5247: dup
    //   5248: bipush #10
    //   5250: iconst_0
    //   5251: iastore
    //   5252: dup
    //   5253: bipush #11
    //   5255: ldc 67108866
    //   5257: iastore
    //   5258: dup
    //   5259: bipush #12
    //   5261: iconst_2
    //   5262: iastore
    //   5263: dup
    //   5264: bipush #13
    //   5266: ldc 67108864
    //   5268: iastore
    //   5269: dup
    //   5270: bipush #14
    //   5272: ldc 69206018
    //   5274: iastore
    //   5275: dup
    //   5276: bipush #15
    //   5278: sipush #2050
    //   5281: iastore
    //   5282: dup
    //   5283: bipush #16
    //   5285: ldc 67110912
    //   5287: iastore
    //   5288: dup
    //   5289: bipush #17
    //   5291: ldc 2099202
    //   5293: iastore
    //   5294: dup
    //   5295: bipush #18
    //   5297: ldc 2097154
    //   5299: iastore
    //   5300: dup
    //   5301: bipush #19
    //   5303: ldc 67110912
    //   5305: iastore
    //   5306: dup
    //   5307: bipush #20
    //   5309: ldc 67108866
    //   5311: iastore
    //   5312: dup
    //   5313: bipush #21
    //   5315: ldc 69206016
    //   5317: iastore
    //   5318: dup
    //   5319: bipush #22
    //   5321: ldc 69208064
    //   5323: iastore
    //   5324: dup
    //   5325: bipush #23
    //   5327: ldc 2097154
    //   5329: iastore
    //   5330: dup
    //   5331: bipush #24
    //   5333: ldc 69206016
    //   5335: iastore
    //   5336: dup
    //   5337: bipush #25
    //   5339: sipush #2048
    //   5342: iastore
    //   5343: dup
    //   5344: bipush #26
    //   5346: sipush #2050
    //   5349: iastore
    //   5350: dup
    //   5351: bipush #27
    //   5353: ldc 69208066
    //   5355: iastore
    //   5356: dup
    //   5357: bipush #28
    //   5359: ldc 2099200
    //   5361: iastore
    //   5362: dup
    //   5363: bipush #29
    //   5365: iconst_2
    //   5366: iastore
    //   5367: dup
    //   5368: bipush #30
    //   5370: ldc 67108864
    //   5372: iastore
    //   5373: dup
    //   5374: bipush #31
    //   5376: ldc 2099200
    //   5378: iastore
    //   5379: dup
    //   5380: bipush #32
    //   5382: ldc 67108864
    //   5384: iastore
    //   5385: dup
    //   5386: bipush #33
    //   5388: ldc 2099200
    //   5390: iastore
    //   5391: dup
    //   5392: bipush #34
    //   5394: ldc 2097152
    //   5396: iastore
    //   5397: dup
    //   5398: bipush #35
    //   5400: ldc 67110914
    //   5402: iastore
    //   5403: dup
    //   5404: bipush #36
    //   5406: ldc 67110914
    //   5408: iastore
    //   5409: dup
    //   5410: bipush #37
    //   5412: ldc 69206018
    //   5414: iastore
    //   5415: dup
    //   5416: bipush #38
    //   5418: ldc 69206018
    //   5420: iastore
    //   5421: dup
    //   5422: bipush #39
    //   5424: iconst_2
    //   5425: iastore
    //   5426: dup
    //   5427: bipush #40
    //   5429: ldc 2097154
    //   5431: iastore
    //   5432: dup
    //   5433: bipush #41
    //   5435: ldc 67108864
    //   5437: iastore
    //   5438: dup
    //   5439: bipush #42
    //   5441: ldc 67110912
    //   5443: iastore
    //   5444: dup
    //   5445: bipush #43
    //   5447: ldc 2097152
    //   5449: iastore
    //   5450: dup
    //   5451: bipush #44
    //   5453: ldc 69208064
    //   5455: iastore
    //   5456: dup
    //   5457: bipush #45
    //   5459: sipush #2050
    //   5462: iastore
    //   5463: dup
    //   5464: bipush #46
    //   5466: ldc 2099202
    //   5468: iastore
    //   5469: dup
    //   5470: bipush #47
    //   5472: ldc 69208064
    //   5474: iastore
    //   5475: dup
    //   5476: bipush #48
    //   5478: sipush #2050
    //   5481: iastore
    //   5482: dup
    //   5483: bipush #49
    //   5485: ldc 67108866
    //   5487: iastore
    //   5488: dup
    //   5489: bipush #50
    //   5491: ldc 69208066
    //   5493: iastore
    //   5494: dup
    //   5495: bipush #51
    //   5497: ldc 69206016
    //   5499: iastore
    //   5500: dup
    //   5501: bipush #52
    //   5503: ldc 2099200
    //   5505: iastore
    //   5506: dup
    //   5507: bipush #53
    //   5509: iconst_0
    //   5510: iastore
    //   5511: dup
    //   5512: bipush #54
    //   5514: iconst_2
    //   5515: iastore
    //   5516: dup
    //   5517: bipush #55
    //   5519: ldc 69208066
    //   5521: iastore
    //   5522: dup
    //   5523: bipush #56
    //   5525: iconst_0
    //   5526: iastore
    //   5527: dup
    //   5528: bipush #57
    //   5530: ldc 2099202
    //   5532: iastore
    //   5533: dup
    //   5534: bipush #58
    //   5536: ldc 69206016
    //   5538: iastore
    //   5539: dup
    //   5540: bipush #59
    //   5542: sipush #2048
    //   5545: iastore
    //   5546: dup
    //   5547: bipush #60
    //   5549: ldc 67108866
    //   5551: iastore
    //   5552: dup
    //   5553: bipush #61
    //   5555: ldc 67110912
    //   5557: iastore
    //   5558: dup
    //   5559: bipush #62
    //   5561: sipush #2048
    //   5564: iastore
    //   5565: dup
    //   5566: bipush #63
    //   5568: ldc 2097154
    //   5570: iastore
    //   5571: astore #15
    //   5573: bipush #64
    //   5575: newarray int
    //   5577: dup
    //   5578: iconst_0
    //   5579: ldc 268439616
    //   5581: iastore
    //   5582: dup
    //   5583: iconst_1
    //   5584: sipush #4096
    //   5587: iastore
    //   5588: dup
    //   5589: iconst_2
    //   5590: ldc 262144
    //   5592: iastore
    //   5593: dup
    //   5594: iconst_3
    //   5595: ldc 268701760
    //   5597: iastore
    //   5598: dup
    //   5599: iconst_4
    //   5600: ldc 268435456
    //   5602: iastore
    //   5603: dup
    //   5604: iconst_5
    //   5605: ldc 268439616
    //   5607: iastore
    //   5608: dup
    //   5609: bipush #6
    //   5611: bipush #64
    //   5613: iastore
    //   5614: dup
    //   5615: bipush #7
    //   5617: ldc 268435456
    //   5619: iastore
    //   5620: dup
    //   5621: bipush #8
    //   5623: ldc 262208
    //   5625: iastore
    //   5626: dup
    //   5627: bipush #9
    //   5629: ldc 268697600
    //   5631: iastore
    //   5632: dup
    //   5633: bipush #10
    //   5635: ldc 268701760
    //   5637: iastore
    //   5638: dup
    //   5639: bipush #11
    //   5641: ldc 266240
    //   5643: iastore
    //   5644: dup
    //   5645: bipush #12
    //   5647: ldc 268701696
    //   5649: iastore
    //   5650: dup
    //   5651: bipush #13
    //   5653: ldc 266304
    //   5655: iastore
    //   5656: dup
    //   5657: bipush #14
    //   5659: sipush #4096
    //   5662: iastore
    //   5663: dup
    //   5664: bipush #15
    //   5666: bipush #64
    //   5668: iastore
    //   5669: dup
    //   5670: bipush #16
    //   5672: ldc 268697600
    //   5674: iastore
    //   5675: dup
    //   5676: bipush #17
    //   5678: ldc 268435520
    //   5680: iastore
    //   5681: dup
    //   5682: bipush #18
    //   5684: ldc 268439552
    //   5686: iastore
    //   5687: dup
    //   5688: bipush #19
    //   5690: sipush #4160
    //   5693: iastore
    //   5694: dup
    //   5695: bipush #20
    //   5697: ldc 266240
    //   5699: iastore
    //   5700: dup
    //   5701: bipush #21
    //   5703: ldc 262208
    //   5705: iastore
    //   5706: dup
    //   5707: bipush #22
    //   5709: ldc 268697664
    //   5711: iastore
    //   5712: dup
    //   5713: bipush #23
    //   5715: ldc 268701696
    //   5717: iastore
    //   5718: dup
    //   5719: bipush #24
    //   5721: sipush #4160
    //   5724: iastore
    //   5725: dup
    //   5726: bipush #25
    //   5728: iconst_0
    //   5729: iastore
    //   5730: dup
    //   5731: bipush #26
    //   5733: iconst_0
    //   5734: iastore
    //   5735: dup
    //   5736: bipush #27
    //   5738: ldc 268697664
    //   5740: iastore
    //   5741: dup
    //   5742: bipush #28
    //   5744: ldc 268435520
    //   5746: iastore
    //   5747: dup
    //   5748: bipush #29
    //   5750: ldc 268439552
    //   5752: iastore
    //   5753: dup
    //   5754: bipush #30
    //   5756: ldc 266304
    //   5758: iastore
    //   5759: dup
    //   5760: bipush #31
    //   5762: ldc 262144
    //   5764: iastore
    //   5765: dup
    //   5766: bipush #32
    //   5768: ldc 266304
    //   5770: iastore
    //   5771: dup
    //   5772: bipush #33
    //   5774: ldc 262144
    //   5776: iastore
    //   5777: dup
    //   5778: bipush #34
    //   5780: ldc 268701696
    //   5782: iastore
    //   5783: dup
    //   5784: bipush #35
    //   5786: sipush #4096
    //   5789: iastore
    //   5790: dup
    //   5791: bipush #36
    //   5793: bipush #64
    //   5795: iastore
    //   5796: dup
    //   5797: bipush #37
    //   5799: ldc 268697664
    //   5801: iastore
    //   5802: dup
    //   5803: bipush #38
    //   5805: sipush #4096
    //   5808: iastore
    //   5809: dup
    //   5810: bipush #39
    //   5812: ldc 266304
    //   5814: iastore
    //   5815: dup
    //   5816: bipush #40
    //   5818: ldc 268439552
    //   5820: iastore
    //   5821: dup
    //   5822: bipush #41
    //   5824: bipush #64
    //   5826: iastore
    //   5827: dup
    //   5828: bipush #42
    //   5830: ldc 268435520
    //   5832: iastore
    //   5833: dup
    //   5834: bipush #43
    //   5836: ldc 268697600
    //   5838: iastore
    //   5839: dup
    //   5840: bipush #44
    //   5842: ldc 268697664
    //   5844: iastore
    //   5845: dup
    //   5846: bipush #45
    //   5848: ldc 268435456
    //   5850: iastore
    //   5851: dup
    //   5852: bipush #46
    //   5854: ldc 262144
    //   5856: iastore
    //   5857: dup
    //   5858: bipush #47
    //   5860: ldc 268439616
    //   5862: iastore
    //   5863: dup
    //   5864: bipush #48
    //   5866: iconst_0
    //   5867: iastore
    //   5868: dup
    //   5869: bipush #49
    //   5871: ldc 268701760
    //   5873: iastore
    //   5874: dup
    //   5875: bipush #50
    //   5877: ldc 262208
    //   5879: iastore
    //   5880: dup
    //   5881: bipush #51
    //   5883: ldc 268435520
    //   5885: iastore
    //   5886: dup
    //   5887: bipush #52
    //   5889: ldc 268697600
    //   5891: iastore
    //   5892: dup
    //   5893: bipush #53
    //   5895: ldc 268439552
    //   5897: iastore
    //   5898: dup
    //   5899: bipush #54
    //   5901: ldc 268439616
    //   5903: iastore
    //   5904: dup
    //   5905: bipush #55
    //   5907: iconst_0
    //   5908: iastore
    //   5909: dup
    //   5910: bipush #56
    //   5912: ldc 268701760
    //   5914: iastore
    //   5915: dup
    //   5916: bipush #57
    //   5918: ldc 266240
    //   5920: iastore
    //   5921: dup
    //   5922: bipush #58
    //   5924: ldc 266240
    //   5926: iastore
    //   5927: dup
    //   5928: bipush #59
    //   5930: sipush #4160
    //   5933: iastore
    //   5934: dup
    //   5935: bipush #60
    //   5937: sipush #4160
    //   5940: iastore
    //   5941: dup
    //   5942: bipush #61
    //   5944: ldc 262208
    //   5946: iastore
    //   5947: dup
    //   5948: bipush #62
    //   5950: ldc 268435456
    //   5952: iastore
    //   5953: dup
    //   5954: bipush #63
    //   5956: ldc 268701696
    //   5958: iastore
    //   5959: astore #16
    //   5961: aload #4
    //   5963: arraylength
    //   5964: istore #17
    //   5966: iconst_2
    //   5967: newarray int
    //   5969: astore #18
    //   5971: iload #17
    //   5973: newarray byte
    //   5975: astore #5
    //   5977: iload #17
    //   5979: bipush #8
    //   5981: idiv
    //   5982: istore #19
    //   5984: iconst_0
    //   5985: istore #20
    //   5987: iload #20
    //   5989: iload #19
    //   5991: if_icmpge -> 6909
    //   5994: iload #20
    //   5996: bipush #8
    //   5998: imul
    //   5999: istore #21
    //   6001: iconst_0
    //   6002: istore #22
    //   6004: iload #22
    //   6006: iconst_2
    //   6007: if_icmpge -> 6096
    //   6010: aload #18
    //   6012: iload #22
    //   6014: aload #4
    //   6016: iload #21
    //   6018: iload #22
    //   6020: iconst_4
    //   6021: imul
    //   6022: iadd
    //   6023: baload
    //   6024: sipush #255
    //   6027: iand
    //   6028: bipush #24
    //   6030: ishl
    //   6031: aload #4
    //   6033: iload #21
    //   6035: iload #22
    //   6037: iconst_4
    //   6038: imul
    //   6039: iadd
    //   6040: iconst_1
    //   6041: iadd
    //   6042: baload
    //   6043: sipush #255
    //   6046: iand
    //   6047: bipush #16
    //   6049: ishl
    //   6050: ior
    //   6051: aload #4
    //   6053: iload #21
    //   6055: iload #22
    //   6057: iconst_4
    //   6058: imul
    //   6059: iadd
    //   6060: iconst_2
    //   6061: iadd
    //   6062: baload
    //   6063: sipush #255
    //   6066: iand
    //   6067: bipush #8
    //   6069: ishl
    //   6070: ior
    //   6071: aload #4
    //   6073: iload #21
    //   6075: iload #22
    //   6077: iconst_4
    //   6078: imul
    //   6079: iadd
    //   6080: iconst_3
    //   6081: iadd
    //   6082: baload
    //   6083: sipush #255
    //   6086: iand
    //   6087: ior
    //   6088: iastore
    //   6089: iinc #22, 1
    //   6092: iload_2
    //   6093: ifne -> 6004
    //   6096: iconst_0
    //   6097: istore #27
    //   6099: aload #18
    //   6101: iconst_0
    //   6102: iaload
    //   6103: istore #25
    //   6105: aload #18
    //   6107: iconst_1
    //   6108: iaload
    //   6109: istore #24
    //   6111: iload #25
    //   6113: iconst_4
    //   6114: iushr
    //   6115: iload #24
    //   6117: ixor
    //   6118: ldc 252645135
    //   6120: iand
    //   6121: istore #23
    //   6123: iload #24
    //   6125: iload #23
    //   6127: ixor
    //   6128: istore #24
    //   6130: iload #25
    //   6132: iload #23
    //   6134: iconst_4
    //   6135: ishl
    //   6136: ixor
    //   6137: istore #25
    //   6139: iload #25
    //   6141: bipush #16
    //   6143: iushr
    //   6144: iload #24
    //   6146: ixor
    //   6147: ldc 65535
    //   6149: iand
    //   6150: istore #23
    //   6152: iload #24
    //   6154: iload #23
    //   6156: ixor
    //   6157: istore #24
    //   6159: iload #25
    //   6161: iload #23
    //   6163: bipush #16
    //   6165: ishl
    //   6166: ixor
    //   6167: istore #25
    //   6169: iload #24
    //   6171: iconst_2
    //   6172: iushr
    //   6173: iload #25
    //   6175: ixor
    //   6176: ldc 858993459
    //   6178: iand
    //   6179: istore #23
    //   6181: iload #25
    //   6183: iload #23
    //   6185: ixor
    //   6186: istore #25
    //   6188: iload #24
    //   6190: iload #23
    //   6192: iconst_2
    //   6193: ishl
    //   6194: ixor
    //   6195: istore #24
    //   6197: iload #24
    //   6199: bipush #8
    //   6201: iushr
    //   6202: iload #25
    //   6204: ixor
    //   6205: ldc 16711935
    //   6207: iand
    //   6208: istore #23
    //   6210: iload #25
    //   6212: iload #23
    //   6214: ixor
    //   6215: istore #25
    //   6217: iload #24
    //   6219: iload #23
    //   6221: bipush #8
    //   6223: ishl
    //   6224: ixor
    //   6225: istore #24
    //   6227: iload #24
    //   6229: iconst_1
    //   6230: ishl
    //   6231: iload #24
    //   6233: bipush #31
    //   6235: iushr
    //   6236: iconst_1
    //   6237: iand
    //   6238: ior
    //   6239: istore #24
    //   6241: iload #25
    //   6243: iload #24
    //   6245: ixor
    //   6246: ldc -1431655766
    //   6248: iand
    //   6249: istore #23
    //   6251: iload #25
    //   6253: iload #23
    //   6255: ixor
    //   6256: istore #25
    //   6258: iload #24
    //   6260: iload #23
    //   6262: ixor
    //   6263: istore #24
    //   6265: iload #25
    //   6267: iconst_1
    //   6268: ishl
    //   6269: iload #25
    //   6271: bipush #31
    //   6273: iushr
    //   6274: iconst_1
    //   6275: iand
    //   6276: ior
    //   6277: istore #25
    //   6279: iconst_0
    //   6280: istore #26
    //   6282: iload #26
    //   6284: bipush #8
    //   6286: if_icmpge -> 6624
    //   6289: iload #24
    //   6291: bipush #28
    //   6293: ishl
    //   6294: iload #24
    //   6296: iconst_4
    //   6297: iushr
    //   6298: ior
    //   6299: istore #23
    //   6301: iload #23
    //   6303: aload #6
    //   6305: iload #27
    //   6307: iinc #27, 1
    //   6310: iaload
    //   6311: ixor
    //   6312: istore #23
    //   6314: aload #15
    //   6316: iload #23
    //   6318: bipush #63
    //   6320: iand
    //   6321: iaload
    //   6322: istore #22
    //   6324: iload #22
    //   6326: aload #13
    //   6328: iload #23
    //   6330: bipush #8
    //   6332: iushr
    //   6333: bipush #63
    //   6335: iand
    //   6336: iaload
    //   6337: ior
    //   6338: istore #22
    //   6340: iload #22
    //   6342: aload #11
    //   6344: iload #23
    //   6346: bipush #16
    //   6348: iushr
    //   6349: bipush #63
    //   6351: iand
    //   6352: iaload
    //   6353: ior
    //   6354: istore #22
    //   6356: iload #22
    //   6358: aload #9
    //   6360: iload #23
    //   6362: bipush #24
    //   6364: iushr
    //   6365: bipush #63
    //   6367: iand
    //   6368: iaload
    //   6369: ior
    //   6370: istore #22
    //   6372: iload #24
    //   6374: aload #6
    //   6376: iload #27
    //   6378: iinc #27, 1
    //   6381: iaload
    //   6382: ixor
    //   6383: istore #23
    //   6385: iload #22
    //   6387: aload #16
    //   6389: iload #23
    //   6391: bipush #63
    //   6393: iand
    //   6394: iaload
    //   6395: ior
    //   6396: istore #22
    //   6398: iload #22
    //   6400: aload #14
    //   6402: iload #23
    //   6404: bipush #8
    //   6406: iushr
    //   6407: bipush #63
    //   6409: iand
    //   6410: iaload
    //   6411: ior
    //   6412: istore #22
    //   6414: iload #22
    //   6416: aload #12
    //   6418: iload #23
    //   6420: bipush #16
    //   6422: iushr
    //   6423: bipush #63
    //   6425: iand
    //   6426: iaload
    //   6427: ior
    //   6428: istore #22
    //   6430: iload #22
    //   6432: aload #10
    //   6434: iload #23
    //   6436: bipush #24
    //   6438: iushr
    //   6439: bipush #63
    //   6441: iand
    //   6442: iaload
    //   6443: ior
    //   6444: istore #22
    //   6446: iload #25
    //   6448: iload #22
    //   6450: ixor
    //   6451: istore #25
    //   6453: iload #25
    //   6455: bipush #28
    //   6457: ishl
    //   6458: iload #25
    //   6460: iconst_4
    //   6461: iushr
    //   6462: ior
    //   6463: istore #23
    //   6465: iload #23
    //   6467: aload #6
    //   6469: iload #27
    //   6471: iinc #27, 1
    //   6474: iaload
    //   6475: ixor
    //   6476: istore #23
    //   6478: aload #15
    //   6480: iload #23
    //   6482: bipush #63
    //   6484: iand
    //   6485: iaload
    //   6486: istore #22
    //   6488: iload #22
    //   6490: aload #13
    //   6492: iload #23
    //   6494: bipush #8
    //   6496: iushr
    //   6497: bipush #63
    //   6499: iand
    //   6500: iaload
    //   6501: ior
    //   6502: istore #22
    //   6504: iload #22
    //   6506: aload #11
    //   6508: iload #23
    //   6510: bipush #16
    //   6512: iushr
    //   6513: bipush #63
    //   6515: iand
    //   6516: iaload
    //   6517: ior
    //   6518: istore #22
    //   6520: iload #22
    //   6522: aload #9
    //   6524: iload #23
    //   6526: bipush #24
    //   6528: iushr
    //   6529: bipush #63
    //   6531: iand
    //   6532: iaload
    //   6533: ior
    //   6534: istore #22
    //   6536: iload #25
    //   6538: aload #6
    //   6540: iload #27
    //   6542: iinc #27, 1
    //   6545: iaload
    //   6546: ixor
    //   6547: istore #23
    //   6549: iload #22
    //   6551: aload #16
    //   6553: iload #23
    //   6555: bipush #63
    //   6557: iand
    //   6558: iaload
    //   6559: ior
    //   6560: istore #22
    //   6562: iload #22
    //   6564: aload #14
    //   6566: iload #23
    //   6568: bipush #8
    //   6570: iushr
    //   6571: bipush #63
    //   6573: iand
    //   6574: iaload
    //   6575: ior
    //   6576: istore #22
    //   6578: iload #22
    //   6580: aload #12
    //   6582: iload #23
    //   6584: bipush #16
    //   6586: iushr
    //   6587: bipush #63
    //   6589: iand
    //   6590: iaload
    //   6591: ior
    //   6592: istore #22
    //   6594: iload #22
    //   6596: aload #10
    //   6598: iload #23
    //   6600: bipush #24
    //   6602: iushr
    //   6603: bipush #63
    //   6605: iand
    //   6606: iaload
    //   6607: ior
    //   6608: istore #22
    //   6610: iload #24
    //   6612: iload #22
    //   6614: ixor
    //   6615: istore #24
    //   6617: iinc #26, 1
    //   6620: iload_2
    //   6621: ifne -> 6282
    //   6624: iload #24
    //   6626: bipush #31
    //   6628: ishl
    //   6629: iload #24
    //   6631: iconst_1
    //   6632: iushr
    //   6633: ior
    //   6634: istore #24
    //   6636: iload #25
    //   6638: iload #24
    //   6640: ixor
    //   6641: ldc -1431655766
    //   6643: iand
    //   6644: istore #23
    //   6646: iload #25
    //   6648: iload #23
    //   6650: ixor
    //   6651: istore #25
    //   6653: iload #24
    //   6655: iload #23
    //   6657: ixor
    //   6658: istore #24
    //   6660: iload #25
    //   6662: bipush #31
    //   6664: ishl
    //   6665: iload #25
    //   6667: iconst_1
    //   6668: iushr
    //   6669: ior
    //   6670: istore #25
    //   6672: iload #25
    //   6674: bipush #8
    //   6676: iushr
    //   6677: iload #24
    //   6679: ixor
    //   6680: ldc 16711935
    //   6682: iand
    //   6683: istore #23
    //   6685: iload #24
    //   6687: iload #23
    //   6689: ixor
    //   6690: istore #24
    //   6692: iload #25
    //   6694: iload #23
    //   6696: bipush #8
    //   6698: ishl
    //   6699: ixor
    //   6700: istore #25
    //   6702: iload #25
    //   6704: iconst_2
    //   6705: iushr
    //   6706: iload #24
    //   6708: ixor
    //   6709: ldc 858993459
    //   6711: iand
    //   6712: istore #23
    //   6714: iload #24
    //   6716: iload #23
    //   6718: ixor
    //   6719: istore #24
    //   6721: iload #25
    //   6723: iload #23
    //   6725: iconst_2
    //   6726: ishl
    //   6727: ixor
    //   6728: istore #25
    //   6730: iload #24
    //   6732: bipush #16
    //   6734: iushr
    //   6735: iload #25
    //   6737: ixor
    //   6738: ldc 65535
    //   6740: iand
    //   6741: istore #23
    //   6743: iload #25
    //   6745: iload #23
    //   6747: ixor
    //   6748: istore #25
    //   6750: iload #24
    //   6752: iload #23
    //   6754: bipush #16
    //   6756: ishl
    //   6757: ixor
    //   6758: istore #24
    //   6760: iload #24
    //   6762: iconst_4
    //   6763: iushr
    //   6764: iload #25
    //   6766: ixor
    //   6767: ldc 252645135
    //   6769: iand
    //   6770: istore #23
    //   6772: iload #25
    //   6774: iload #23
    //   6776: ixor
    //   6777: istore #25
    //   6779: iload #24
    //   6781: iload #23
    //   6783: iconst_4
    //   6784: ishl
    //   6785: ixor
    //   6786: istore #24
    //   6788: aload #18
    //   6790: iconst_0
    //   6791: iload #24
    //   6793: iastore
    //   6794: aload #18
    //   6796: iconst_1
    //   6797: iload #25
    //   6799: iastore
    //   6800: iload #20
    //   6802: bipush #8
    //   6804: imul
    //   6805: istore #28
    //   6807: iconst_0
    //   6808: istore #29
    //   6810: iload #29
    //   6812: iconst_2
    //   6813: if_icmpge -> 6902
    //   6816: aload #5
    //   6818: iload #28
    //   6820: iload #29
    //   6822: iconst_4
    //   6823: imul
    //   6824: iadd
    //   6825: aload #18
    //   6827: iload #29
    //   6829: iaload
    //   6830: bipush #24
    //   6832: iushr
    //   6833: i2b
    //   6834: bastore
    //   6835: aload #5
    //   6837: iload #28
    //   6839: iload #29
    //   6841: iconst_4
    //   6842: imul
    //   6843: iadd
    //   6844: iconst_1
    //   6845: iadd
    //   6846: aload #18
    //   6848: iload #29
    //   6850: iaload
    //   6851: bipush #16
    //   6853: iushr
    //   6854: i2b
    //   6855: bastore
    //   6856: aload #5
    //   6858: iload #28
    //   6860: iload #29
    //   6862: iconst_4
    //   6863: imul
    //   6864: iadd
    //   6865: iconst_2
    //   6866: iadd
    //   6867: aload #18
    //   6869: iload #29
    //   6871: iaload
    //   6872: bipush #8
    //   6874: iushr
    //   6875: i2b
    //   6876: bastore
    //   6877: aload #5
    //   6879: iload #28
    //   6881: iload #29
    //   6883: iconst_4
    //   6884: imul
    //   6885: iadd
    //   6886: iconst_3
    //   6887: iadd
    //   6888: aload #18
    //   6890: iload #29
    //   6892: iaload
    //   6893: i2b
    //   6894: bastore
    //   6895: iinc #29, 1
    //   6898: iload_2
    //   6899: ifne -> 6810
    //   6902: iinc #20, 1
    //   6905: iload_2
    //   6906: ifne -> 5987
    //   6909: getstatic burp/Zkfz.Zs : Ljava/lang/String;
    //   6912: getstatic burp/Zsm3.ZC : Ljava/lang/Object;
    //   6915: checkcast java/math/BigInteger
    //   6918: invokevirtual intValue : ()I
    //   6921: bipush #32
    //   6923: irem
    //   6924: invokestatic abs : (I)I
    //   6927: invokevirtual charAt : (I)C
    //   6930: getstatic burp/Zeh9.ZF : Ljava/lang/String;
    //   6933: getstatic burp/Zl_u.ZR : Ljava/lang/Object;
    //   6936: checkcast java/math/BigInteger
    //   6939: invokevirtual intValue : ()I
    //   6942: bipush #32
    //   6944: irem
    //   6945: invokestatic abs : (I)I
    //   6948: invokevirtual charAt : (I)C
    //   6951: if_icmpgt -> 7066
    //   6954: getstatic burp/Zgss.Zc : Ljava/lang/String;
    //   6957: getstatic burp/Zrnu.Zs : Ljava/lang/Object;
    //   6960: checkcast java/math/BigInteger
    //   6963: invokevirtual intValue : ()I
    //   6966: bipush #32
    //   6968: irem
    //   6969: invokestatic abs : (I)I
    //   6972: invokevirtual charAt : (I)C
    //   6975: getstatic burp/Zlv6.Zt : Ljava/lang/String;
    //   6978: getstatic burp/Zl2g.ZG : Ljava/lang/Object;
    //   6981: checkcast java/math/BigInteger
    //   6984: invokevirtual intValue : ()I
    //   6987: bipush #32
    //   6989: irem
    //   6990: invokestatic abs : (I)I
    //   6993: invokevirtual charAt : (I)C
    //   6996: if_icmpgt -> 7066
    //   6999: goto -> 7006
    //   7002: invokestatic a : (Ljava/lang/Throwable;)Ljava/lang/Throwable;
    //   7005: athrow
    //   7006: getstatic burp/Zsde.Zi : Ljava/lang/String;
    //   7009: getstatic burp/Zx54.Zn : Ljava/lang/Object;
    //   7012: checkcast java/math/BigInteger
    //   7015: invokevirtual intValue : ()I
    //   7018: bipush #32
    //   7020: irem
    //   7021: invokestatic abs : (I)I
    //   7024: invokevirtual charAt : (I)C
    //   7027: getstatic burp/Zm0s.Zm : Ljava/lang/String;
    //   7030: getstatic burp/Zshq.ZK : Ljava/lang/Object;
    //   7033: checkcast java/math/BigInteger
    //   7036: invokevirtual intValue : ()I
    //   7039: bipush #32
    //   7041: irem
    //   7042: invokestatic abs : (I)I
    //   7045: invokevirtual charAt : (I)C
    //   7048: if_icmpgt -> 7066
    //   7051: goto -> 7058
    //   7054: invokestatic a : (Ljava/lang/Throwable;)Ljava/lang/Throwable;
    //   7057: athrow
    //   7058: iconst_1
    //   7059: goto -> 7067
    //   7062: invokestatic a : (Ljava/lang/Throwable;)Ljava/lang/Throwable;
    //   7065: athrow
    //   7066: iconst_0
    //   7067: ireturn
    //   7068: astore_3
    //   7069: new java/lang/Exception
    //   7072: dup
    //   7073: aload_3
    //   7074: invokevirtual getMessage : ()Ljava/lang/String;
    //   7077: invokespecial <init> : (Ljava/lang/String;)V
    //   7080: athrow
    // Exception table:
    //   from	to	target	type
    //   4	7067	7068	java/lang/Throwable
    //   51	65	68	java/lang/Throwable
    //   58	79	82	java/lang/Throwable
    //   72	93	96	java/lang/Throwable
    //   86	107	110	java/lang/Throwable
    //   100	121	124	java/lang/Throwable
    //   114	135	138	java/lang/Throwable
    //   128	149	152	java/lang/Throwable
    //   142	163	166	java/lang/Throwable
    //   156	173	176	java/lang/Throwable
    //   212	226	229	java/lang/Throwable
    //   219	240	243	java/lang/Throwable
    //   233	254	257	java/lang/Throwable
    //   247	268	271	java/lang/Throwable
    //   261	282	285	java/lang/Throwable
    //   275	296	299	java/lang/Throwable
    //   289	310	313	java/lang/Throwable
    //   303	324	327	java/lang/Throwable
    //   317	341	344	java/lang/Throwable
    //   405	423	426	java/lang/Throwable
    //   414	439	442	java/lang/Throwable
    //   430	456	459	java/lang/Throwable
    //   446	472	475	java/lang/Throwable
    //   463	489	492	java/lang/Throwable
    //   479	505	508	java/lang/Throwable
    //   496	521	524	java/lang/Throwable
    //   512	544	547	java/lang/Throwable
    //   528	560	563	java/lang/Throwable
    //   551	576	579	java/lang/Throwable
    //   567	599	602	java/lang/Throwable
    //   583	615	618	java/lang/Throwable
    //   606	631	634	java/lang/Throwable
    //   622	650	653	java/lang/Throwable
    //   780	815	818	java/lang/Throwable
    //   822	863	866	java/lang/Throwable
    //   907	1082	1085	java/lang/Throwable
    //   1052	1119	1122	java/lang/Throwable
    //   1089	1156	1159	java/lang/Throwable
    //   1126	1193	1196	java/lang/Throwable
    //   1163	1230	1233	java/lang/Throwable
    //   1200	1267	1270	java/lang/Throwable
    //   1237	1304	1307	java/lang/Throwable
    //   1274	1341	1344	java/lang/Throwable
    //   1311	1378	1381	java/lang/Throwable
    //   1348	1415	1418	java/lang/Throwable
    //   1385	1452	1455	java/lang/Throwable
    //   1422	1489	1492	java/lang/Throwable
    //   1459	1526	1529	java/lang/Throwable
    //   1496	1563	1566	java/lang/Throwable
    //   1533	1600	1603	java/lang/Throwable
    //   1570	1637	1640	java/lang/Throwable
    //   1607	1674	1677	java/lang/Throwable
    //   1644	1711	1714	java/lang/Throwable
    //   1681	1748	1751	java/lang/Throwable
    //   1718	1785	1788	java/lang/Throwable
    //   1755	1822	1825	java/lang/Throwable
    //   1792	1859	1862	java/lang/Throwable
    //   1829	1896	1899	java/lang/Throwable
    //   1866	1933	1936	java/lang/Throwable
    //   1903	1970	1973	java/lang/Throwable
    //   1940	2007	2010	java/lang/Throwable
    //   1977	2044	2047	java/lang/Throwable
    //   2014	2081	2084	java/lang/Throwable
    //   2051	2118	2121	java/lang/Throwable
    //   2088	2155	2158	java/lang/Throwable
    //   2125	2192	2195	java/lang/Throwable
    //   2162	2225	2228	java/lang/Throwable
    //   2291	2305	2305	java/lang/Throwable
    //   2316	2329	2332	java/lang/Throwable
    //   2321	2344	2347	java/lang/Throwable
    //   2336	2362	2365	java/lang/Throwable
    //   2351	2392	2395	java/lang/Throwable
    //   2458	2485	2488	java/lang/Throwable
    //   2475	2506	2509	java/lang/Throwable
    //   2492	2536	2539	java/lang/Throwable
    //   2513	2547	2547	java/lang/Throwable
    //   2558	2574	2577	java/lang/Throwable
    //   6909	6999	7002	java/lang/Throwable
    //   6954	7051	7054	java/lang/Throwable
    //   7006	7062	7062	java/lang/Throwable
  }
  
  static void ZA(Object paramObject) {
    Zer.Zp = a(31030, 25552);
    Zer.Zk = new BigInteger(a(31031, -25495));
    boolean bool = Zt2e.ZK();
    try {
      try {
        if (Zzsq.Zc.charAt(Math.abs(((BigInteger)Zxzd.ZD).intValue() % 32)) > Zx54.Zs.charAt(Math.abs(((BigInteger)Zxfu.ZA).intValue() % 32))) {
          try {
            Zsxj.Zz(Class.forName(a(31028, 9444)));
            if (bool)
              Ztpa.ZD(Class.forName(a(31027, 7993))); 
          } catch (Throwable throwable) {
            throw a(null);
          } 
          return;
        } 
      } catch (Throwable throwable) {
        throw a(null);
      } 
      Ztpa.ZD(Class.forName(a(31027, 7993)));
    } catch (Throwable throwable) {}
  }
  
  static void ZR(Object[] paramArrayOfObject, Object paramObject) throws Throwable {}
  
  static {
    // Byte code:
    //   0: bipush #9
    //   2: anewarray java/lang/String
    //   5: astore #5
    //   7: iconst_0
    //   8: istore_3
    //   9: ldc '.;q{\\tGVMGv$JL/_1:</1IuWW~=#u[^oF)gX\\rs\\tFQh\\tN HHBW1m]y_dB? *{s7--`'
    //   11: dup
    //   12: astore_2
    //   13: invokevirtual length : ()I
    //   16: istore #4
    //   18: bipush #9
    //   20: istore_1
    //   21: iconst_m1
    //   22: istore_0
    //   23: bipush #18
    //   25: iinc #0, 1
    //   28: aload_2
    //   29: iload_0
    //   30: dup
    //   31: iload_1
    //   32: iadd
    //   33: invokevirtual substring : (II)Ljava/lang/String;
    //   36: iconst_m1
    //   37: goto -> 143
    //   40: aload #5
    //   42: swap
    //   43: iload_3
    //   44: iinc #3, 1
    //   47: swap
    //   48: aastore
    //   49: iload_0
    //   50: iload_1
    //   51: iadd
    //   52: dup
    //   53: istore_0
    //   54: iload #4
    //   56: if_icmpge -> 68
    //   59: aload_2
    //   60: iload_0
    //   61: invokevirtual charAt : (I)C
    //   64: istore_1
    //   65: goto -> 23
    //   68: ldc ',?\?dqJ[y'$s$?\+&HY'
    //   70: dup
    //   71: astore_2
    //   72: invokevirtual length : ()I
    //   75: istore #4
    //   77: bipush #77
    //   79: istore_1
    //   80: iconst_m1
    //   81: istore_0
    //   82: bipush #46
    //   84: iinc #0, 1
    //   87: aload_2
    //   88: iload_0
    //   89: dup
    //   90: iload_1
    //   91: iadd
    //   92: invokevirtual substring : (II)Ljava/lang/String;
    //   95: iconst_0
    //   96: goto -> 143
    //   99: aload #5
    //   101: swap
    //   102: iload_3
    //   103: iinc #3, 1
    //   106: swap
    //   107: aastore
    //   108: iload_0
    //   109: iload_1
    //   110: iadd
    //   111: dup
    //   112: istore_0
    //   113: iload #4
    //   115: if_icmpge -> 127
    //   118: aload_2
    //   119: iload_0
    //   120: invokevirtual charAt : (I)C
    //   123: istore_1
    //   124: goto -> 82
    //   127: aload #5
    //   129: putstatic burp/Ze13.a : [Ljava/lang/String;
    //   132: bipush #9
    //   134: anewarray java/lang/String
    //   137: putstatic burp/Ze13.b : [Ljava/lang/String;
    //   140: goto -> 300
    //   143: dup_x2
    //   144: pop
    //   145: invokevirtual toCharArray : ()[C
    //   148: dup_x1
    //   149: arraylength
    //   150: dup_x2
    //   151: pop
    //   152: iconst_0
    //   153: istore #6
    //   155: dup2_x1
    //   156: pop2
    //   157: dup_x2
    //   158: iconst_1
    //   159: if_icmpgt -> 260
    //   162: dup2
    //   163: swap
    //   164: iload #6
    //   166: dup2_x1
    //   167: caload
    //   168: swap
    //   169: iload #6
    //   171: bipush #7
    //   173: irem
    //   174: tableswitch default -> 242, 0 -> 212, 1 -> 217, 2 -> 222, 3 -> 227, 4 -> 232, 5 -> 237
    //   212: bipush #98
    //   214: goto -> 244
    //   217: bipush #60
    //   219: goto -> 244
    //   222: bipush #120
    //   224: goto -> 244
    //   227: bipush #82
    //   229: goto -> 244
    //   232: bipush #114
    //   234: goto -> 244
    //   237: bipush #40
    //   239: goto -> 244
    //   242: bipush #34
    //   244: ixor
    //   245: ixor
    //   246: i2c
    //   247: castore
    //   248: iinc #6, 1
    //   251: dup
    //   252: ifne -> 260
    //   255: dup2
    //   256: dup_x1
    //   257: goto -> 166
    //   260: dup2_x1
    //   261: pop2
    //   262: dup_x2
    //   263: iload #6
    //   265: if_icmpgt -> 162
    //   268: pop
    //   269: new java/lang/String
    //   272: dup_x1
    //   273: swap
    //   274: invokespecial <init> : ([C)V
    //   277: invokevirtual intern : ()Ljava/lang/String;
    //   280: swap
    //   281: pop
    //   282: swap
    //   283: tableswitch default -> 40, 0 -> 99
    //   300: sipush #31029
    //   303: sipush #-30476
    //   306: invokestatic a : (II)Ljava/lang/String;
    //   309: putstatic burp/Ze13.Zg : Ljava/lang/String;
    //   312: new java/math/BigInteger
    //   315: dup
    //   316: sipush #31026
    //   319: sipush #1180
    //   322: invokestatic a : (II)Ljava/lang/String;
    //   325: invokespecial <init> : (Ljava/lang/String;)V
    //   328: putstatic burp/Ze13.ZD : Ljava/lang/Object;
    //   331: return
  }
  
  private static Throwable a(Throwable paramThrowable) {
    return paramThrowable;
  }
  
  private static String a(int paramInt1, int paramInt2) {
    int i = (paramInt1 ^ 0x7930) & 0xFFFF;
    if (b[i] == null) {
      char[] arrayOfChar = a[i].toCharArray();
      switch (arrayOfChar[0] & 0xFF) {
        case 0:
        
        case 1:
        
        case 2:
        
        case 3:
        
        case 4:
        
        case 5:
        
        case 6:
        
        case 7:
        
        case 8:
        
        case 9:
        
        case 10:
        
        case 11:
        
        case 12:
        
        case 13:
        
        case 14:
        
        case 15:
        
        case 16:
        
        case 17:
        
        case 18:
        
        case 19:
        
        case 20:
        
        case 21:
        
        case 22:
        
        case 23:
        
        case 24:
        
        case 25:
        
        case 26:
        
        case 27:
        
        case 28:
        
        case 29:
        
        case 30:
        
        case 31:
        
        case 32:
        
        case 33:
        
        case 34:
        
        case 35:
        
        case 36:
        
        case 37:
        
        case 38:
        
        case 39:
        
        case 40:
        
        case 41:
        
        case 42:
        
        case 43:
        
        case 44:
        
        case 45:
        
        case 46:
        
        case 47:
        
        case 48:
        
        case 49:
        
        case 50:
        
        case 51:
        
        case 52:
        
        case 53:
        
        case 54:
        
        case 55:
        
        case 56:
        
        case 57:
        
        case 58:
        
        case 59:
        
        case 60:
        
        case 61:
        
        case 62:
        
        case 63:
        
        case 64:
        
        case 65:
        
        case 66:
        
        case 67:
        
        case 68:
        
        case 69:
        
        case 70:
        
        case 71:
        
        case 72:
        
        case 73:
        
        case 74:
        
        case 75:
        
        case 76:
        
        case 77:
        
        case 78:
        
        case 79:
        
        case 80:
        
        case 81:
        
        case 82:
        
        case 83:
        
        case 84:
        
        case 85:
        
        case 86:
        
        case 87:
        
        case 88:
        
        case 89:
        
        case 90:
        
        case 91:
        
        case 92:
        
        case 93:
        
        case 94:
        
        case 95:
        
        case 96:
        
        case 97:
        
        case 98:
        
        case 99:
        
        case 100:
        
        case 101:
        
        case 102:
        
        case 103:
        
        case 104:
        
        case 105:
        
        case 106:
        
        case 107:
        
        case 108:
        
        case 109:
        
        case 110:
        
        case 111:
        
        case 112:
        
        case 113:
        
        case 114:
        
        case 115:
        
        case 116:
        
        case 117:
        
        case 118:
        
        case 119:
        
        case 120:
        
        case 121:
        
        case 122:
        
        case 123:
        
        case 124:
        
        case 125:
        
        case 126:
        
        case 127:
        
        case 128:
        
        case 129:
        
        case 130:
        
        case 131:
        
        case 132:
        
        case 133:
        
        case 134:
        
        case 135:
        
        case 136:
        
        case 137:
        
        case 138:
        
        case 139:
        
        case 140:
        
        case 141:
        
        case 142:
        
        case 143:
        
        case 144:
        
        case 145:
        
        case 146:
        
        case 147:
        
        case 148:
        
        case 149:
        
        case 150:
        
        case 151:
        
        case 152:
        
        case 153:
        
        case 154:
        
        case 155:
        
        case 156:
        
        case 157:
        
        case 158:
        
        case 159:
        
        case 160:
        
        case 161:
        
        case 162:
        
        case 163:
        
        case 164:
        
        case 165:
        
        case 166:
        
        case 167:
        
        case 168:
        
        case 169:
        
        case 170:
        
        case 171:
        
        case 172:
        
        case 173:
        
        case 174:
        
        case 175:
        
        case 176:
        
        case 177:
        
        case 178:
        
        case 179:
        
        case 180:
        
        case 181:
        
        case 182:
        
        case 183:
        
        case 184:
        
        case 185:
        
        case 186:
        
        case 187:
        
        case 188:
        
        case 189:
        
        case 190:
        
        case 191:
        
        case 192:
        
        case 193:
        
        case 194:
        
        case 195:
        
        case 196:
        
        case 197:
        
        case 198:
        
        case 199:
        
        case 200:
        
        case 201:
        
        case 202:
        
        case 203:
        
        case 204:
        
        case 205:
        
        case 206:
        
        case 207:
        
        case 208:
        
        case 209:
        
        case 210:
        
        case 211:
        
        case 212:
        
        case 213:
        
        case 214:
        
        case 215:
        
        case 216:
        
        case 217:
        
        case 218:
        
        case 219:
        
        case 220:
        
        case 221:
        
        case 222:
        
        case 223:
        
        case 224:
        
        case 225:
        
        case 226:
        
        case 227:
        
        case 228:
        
        case 229:
        
        case 230:
        
        case 231:
        
        case 232:
        
        case 233:
        
        case 234:
        
        case 235:
        
        case 236:
        
        case 237:
        
        case 238:
        
        case 239:
        
        case 240:
        
        case 241:
        
        case 242:
        
        case 243:
        
        case 244:
        
        case 245:
        
        case 246:
        
        case 247:
        
        case 248:
        
        case 249:
        
        case 250:
        
        case 251:
        
        case 252:
        
        case 253:
        
        case 254:
        
        default:
          break;
      } 
      char c = '';
      int j = (paramInt2 & 0xFF) - c;
      if (j < 0)
        j += 256; 
      int k = ((paramInt2 & 0xFFFF) >>> 8) - c;
      if (k < 0)
        k += 256; 
      for (byte b = 0; b < arrayOfChar.length; b++) {
        int m = b % 2;
        if (m == 0) {
          arrayOfChar[b] = (char)(arrayOfChar[b] ^ j);
          j = ((j >>> 3 | j << 5) ^ arrayOfChar[b]) & 0xFF;
        } else {
          arrayOfChar[b] = (char)(arrayOfChar[b] ^ k);
          k = ((k >>> 3 | k << 5) ^ arrayOfChar[b]) & 0xFF;
        } 
      } 
      b[i] = (new String(arrayOfChar)).intern();
    } 
    return b[i];
  }
}


/* Location:              C:\Program Files\BurpSuitePro\burpsuite_pro.jar!\burp\Ze13.class
 * Java compiler version: 21 (65.0)
 * JD-Core Version:       1.1.3
 */