package burp;

import java.math.BigInteger;

class Ze25 extends ClassLoader {
  static String Zp;
  
  static Object ZW;
  
  private static final String[] a;
  
  private static final String[] b;
  
  static boolean ZJ(Object[] paramArrayOfObject, Object paramObject) throws Throwable {
    // Byte code:
    //   0: invokestatic ZK : ()Z
    //   3: istore_2
    //   4: getstatic burp/Zlw8.ZA : Ljava/lang/Object;
    //   7: checkcast java/math/BigInteger
    //   10: getstatic burp/Zmf2.Zx : Ljava/lang/Object;
    //   13: checkcast java/math/BigInteger
    //   16: invokevirtual subtract : (Ljava/math/BigInteger;)Ljava/math/BigInteger;
    //   19: putstatic burp/Zmtr.Zv : Ljava/lang/Object;
    //   22: new java/lang/StringBuilder
    //   25: dup
    //   26: invokespecial <init> : ()V
    //   29: astore_3
    //   30: iconst_0
    //   31: istore #4
    //   33: iload #4
    //   35: bipush #32
    //   37: if_icmpge -> 1371
    //   40: iload #4
    //   42: tableswitch default -> 1364, 0 -> 184, 1 -> 221, 2 -> 258, 3 -> 295, 4 -> 332, 5 -> 369, 6 -> 406, 7 -> 443, 8 -> 480, 9 -> 517, 10 -> 554, 11 -> 591, 12 -> 628, 13 -> 665, 14 -> 702, 15 -> 739, 16 -> 776, 17 -> 813, 18 -> 850, 19 -> 887, 20 -> 924, 21 -> 961, 22 -> 998, 23 -> 1035, 24 -> 1072, 25 -> 1109, 26 -> 1146, 27 -> 1183, 28 -> 1220, 29 -> 1257, 30 -> 1294, 31 -> 1331
    //   184: aload_3
    //   185: getstatic burp/Zm63.Zs : Ljava/lang/String;
    //   188: getstatic burp/Zoe.ZG : Ljava/lang/Object;
    //   191: checkcast java/math/BigInteger
    //   194: invokevirtual intValue : ()I
    //   197: bipush #32
    //   199: irem
    //   200: invokestatic abs : (I)I
    //   203: invokevirtual charAt : (I)C
    //   206: invokevirtual append : (C)Ljava/lang/StringBuilder;
    //   209: pop
    //   210: iload_2
    //   211: ifeq -> 1364
    //   214: goto -> 221
    //   217: invokestatic a : (Ljava/lang/Throwable;)Ljava/lang/Throwable;
    //   220: athrow
    //   221: aload_3
    //   222: getstatic burp/Zrw0.Zj : Ljava/lang/String;
    //   225: getstatic burp/Zg4l.ZI : Ljava/lang/Object;
    //   228: checkcast java/math/BigInteger
    //   231: invokevirtual intValue : ()I
    //   234: bipush #32
    //   236: irem
    //   237: invokestatic abs : (I)I
    //   240: invokevirtual charAt : (I)C
    //   243: invokevirtual append : (C)Ljava/lang/StringBuilder;
    //   246: pop
    //   247: iload_2
    //   248: ifeq -> 1364
    //   251: goto -> 258
    //   254: invokestatic a : (Ljava/lang/Throwable;)Ljava/lang/Throwable;
    //   257: athrow
    //   258: aload_3
    //   259: getstatic burp/Zz91.Zx : Ljava/lang/String;
    //   262: getstatic burp/Zmh3.ZF : Ljava/lang/Object;
    //   265: checkcast java/math/BigInteger
    //   268: invokevirtual intValue : ()I
    //   271: bipush #32
    //   273: irem
    //   274: invokestatic abs : (I)I
    //   277: invokevirtual charAt : (I)C
    //   280: invokevirtual append : (C)Ljava/lang/StringBuilder;
    //   283: pop
    //   284: iload_2
    //   285: ifeq -> 1364
    //   288: goto -> 295
    //   291: invokestatic a : (Ljava/lang/Throwable;)Ljava/lang/Throwable;
    //   294: athrow
    //   295: aload_3
    //   296: getstatic burp/Zs_m.Zt : Ljava/lang/String;
    //   299: getstatic burp/Zrw0.ZC : Ljava/lang/Object;
    //   302: checkcast java/math/BigInteger
    //   305: invokevirtual intValue : ()I
    //   308: bipush #32
    //   310: irem
    //   311: invokestatic abs : (I)I
    //   314: invokevirtual charAt : (I)C
    //   317: invokevirtual append : (C)Ljava/lang/StringBuilder;
    //   320: pop
    //   321: iload_2
    //   322: ifeq -> 1364
    //   325: goto -> 332
    //   328: invokestatic a : (Ljava/lang/Throwable;)Ljava/lang/Throwable;
    //   331: athrow
    //   332: aload_3
    //   333: getstatic burp/Zv8l.Zo : Ljava/lang/String;
    //   336: getstatic burp/Zz41.Zv : Ljava/lang/Object;
    //   339: checkcast java/math/BigInteger
    //   342: invokevirtual intValue : ()I
    //   345: bipush #32
    //   347: irem
    //   348: invokestatic abs : (I)I
    //   351: invokevirtual charAt : (I)C
    //   354: invokevirtual append : (C)Ljava/lang/StringBuilder;
    //   357: pop
    //   358: iload_2
    //   359: ifeq -> 1364
    //   362: goto -> 369
    //   365: invokestatic a : (Ljava/lang/Throwable;)Ljava/lang/Throwable;
    //   368: athrow
    //   369: aload_3
    //   370: getstatic burp/Zmll.Zu : Ljava/lang/String;
    //   373: getstatic burp/Zrip.ZB : Ljava/lang/Object;
    //   376: checkcast java/math/BigInteger
    //   379: invokevirtual intValue : ()I
    //   382: bipush #32
    //   384: irem
    //   385: invokestatic abs : (I)I
    //   388: invokevirtual charAt : (I)C
    //   391: invokevirtual append : (C)Ljava/lang/StringBuilder;
    //   394: pop
    //   395: iload_2
    //   396: ifeq -> 1364
    //   399: goto -> 406
    //   402: invokestatic a : (Ljava/lang/Throwable;)Ljava/lang/Throwable;
    //   405: athrow
    //   406: aload_3
    //   407: getstatic burp/Zejz.Zd : Ljava/lang/String;
    //   410: getstatic burp/Ze84.Zj : Ljava/lang/Object;
    //   413: checkcast java/math/BigInteger
    //   416: invokevirtual intValue : ()I
    //   419: bipush #32
    //   421: irem
    //   422: invokestatic abs : (I)I
    //   425: invokevirtual charAt : (I)C
    //   428: invokevirtual append : (C)Ljava/lang/StringBuilder;
    //   431: pop
    //   432: iload_2
    //   433: ifeq -> 1364
    //   436: goto -> 443
    //   439: invokestatic a : (Ljava/lang/Throwable;)Ljava/lang/Throwable;
    //   442: athrow
    //   443: aload_3
    //   444: getstatic burp/Zmtr.Zd : Ljava/lang/String;
    //   447: getstatic burp/Zmig.Zh : Ljava/lang/Object;
    //   450: checkcast java/math/BigInteger
    //   453: invokevirtual intValue : ()I
    //   456: bipush #32
    //   458: irem
    //   459: invokestatic abs : (I)I
    //   462: invokevirtual charAt : (I)C
    //   465: invokevirtual append : (C)Ljava/lang/StringBuilder;
    //   468: pop
    //   469: iload_2
    //   470: ifeq -> 1364
    //   473: goto -> 480
    //   476: invokestatic a : (Ljava/lang/Throwable;)Ljava/lang/Throwable;
    //   479: athrow
    //   480: aload_3
    //   481: getstatic burp/Zxd1.ZQ : Ljava/lang/String;
    //   484: getstatic burp/Zlt1.ZH : Ljava/lang/Object;
    //   487: checkcast java/math/BigInteger
    //   490: invokevirtual intValue : ()I
    //   493: bipush #32
    //   495: irem
    //   496: invokestatic abs : (I)I
    //   499: invokevirtual charAt : (I)C
    //   502: invokevirtual append : (C)Ljava/lang/StringBuilder;
    //   505: pop
    //   506: iload_2
    //   507: ifeq -> 1364
    //   510: goto -> 517
    //   513: invokestatic a : (Ljava/lang/Throwable;)Ljava/lang/Throwable;
    //   516: athrow
    //   517: aload_3
    //   518: getstatic burp/Ztdl.ZK : Ljava/lang/String;
    //   521: getstatic burp/Zvob.ZX : Ljava/lang/Object;
    //   524: checkcast java/math/BigInteger
    //   527: invokevirtual intValue : ()I
    //   530: bipush #32
    //   532: irem
    //   533: invokestatic abs : (I)I
    //   536: invokevirtual charAt : (I)C
    //   539: invokevirtual append : (C)Ljava/lang/StringBuilder;
    //   542: pop
    //   543: iload_2
    //   544: ifeq -> 1364
    //   547: goto -> 554
    //   550: invokestatic a : (Ljava/lang/Throwable;)Ljava/lang/Throwable;
    //   553: athrow
    //   554: aload_3
    //   555: getstatic burp/Zemp.Zs : Ljava/lang/String;
    //   558: getstatic burp/Zepy.Ze : Ljava/lang/Object;
    //   561: checkcast java/math/BigInteger
    //   564: invokevirtual intValue : ()I
    //   567: bipush #32
    //   569: irem
    //   570: invokestatic abs : (I)I
    //   573: invokevirtual charAt : (I)C
    //   576: invokevirtual append : (C)Ljava/lang/StringBuilder;
    //   579: pop
    //   580: iload_2
    //   581: ifeq -> 1364
    //   584: goto -> 591
    //   587: invokestatic a : (Ljava/lang/Throwable;)Ljava/lang/Throwable;
    //   590: athrow
    //   591: aload_3
    //   592: getstatic burp/Zxzv.ZI : Ljava/lang/String;
    //   595: getstatic burp/Zmpx.ZZ : Ljava/lang/Object;
    //   598: checkcast java/math/BigInteger
    //   601: invokevirtual intValue : ()I
    //   604: bipush #32
    //   606: irem
    //   607: invokestatic abs : (I)I
    //   610: invokevirtual charAt : (I)C
    //   613: invokevirtual append : (C)Ljava/lang/StringBuilder;
    //   616: pop
    //   617: iload_2
    //   618: ifeq -> 1364
    //   621: goto -> 628
    //   624: invokestatic a : (Ljava/lang/Throwable;)Ljava/lang/Throwable;
    //   627: athrow
    //   628: aload_3
    //   629: getstatic burp/Zb0q.Zr : Ljava/lang/String;
    //   632: getstatic burp/Zk9q.ZH : Ljava/lang/Object;
    //   635: checkcast java/math/BigInteger
    //   638: invokevirtual intValue : ()I
    //   641: bipush #32
    //   643: irem
    //   644: invokestatic abs : (I)I
    //   647: invokevirtual charAt : (I)C
    //   650: invokevirtual append : (C)Ljava/lang/StringBuilder;
    //   653: pop
    //   654: iload_2
    //   655: ifeq -> 1364
    //   658: goto -> 665
    //   661: invokestatic a : (Ljava/lang/Throwable;)Ljava/lang/Throwable;
    //   664: athrow
    //   665: aload_3
    //   666: getstatic burp/Zg1l.Zl : Ljava/lang/String;
    //   669: getstatic burp/Zrqe.ZX : Ljava/lang/Object;
    //   672: checkcast java/math/BigInteger
    //   675: invokevirtual intValue : ()I
    //   678: bipush #32
    //   680: irem
    //   681: invokestatic abs : (I)I
    //   684: invokevirtual charAt : (I)C
    //   687: invokevirtual append : (C)Ljava/lang/StringBuilder;
    //   690: pop
    //   691: iload_2
    //   692: ifeq -> 1364
    //   695: goto -> 702
    //   698: invokestatic a : (Ljava/lang/Throwable;)Ljava/lang/Throwable;
    //   701: athrow
    //   702: aload_3
    //   703: getstatic burp/Znu.ZF : Ljava/lang/String;
    //   706: getstatic burp/Zkca.ZQ : Ljava/lang/Object;
    //   709: checkcast java/math/BigInteger
    //   712: invokevirtual intValue : ()I
    //   715: bipush #32
    //   717: irem
    //   718: invokestatic abs : (I)I
    //   721: invokevirtual charAt : (I)C
    //   724: invokevirtual append : (C)Ljava/lang/StringBuilder;
    //   727: pop
    //   728: iload_2
    //   729: ifeq -> 1364
    //   732: goto -> 739
    //   735: invokestatic a : (Ljava/lang/Throwable;)Ljava/lang/Throwable;
    //   738: athrow
    //   739: aload_3
    //   740: getstatic burp/Zr02.ZG : Ljava/lang/String;
    //   743: getstatic burp/Zrnt.Zh : Ljava/lang/Object;
    //   746: checkcast java/math/BigInteger
    //   749: invokevirtual intValue : ()I
    //   752: bipush #32
    //   754: irem
    //   755: invokestatic abs : (I)I
    //   758: invokevirtual charAt : (I)C
    //   761: invokevirtual append : (C)Ljava/lang/StringBuilder;
    //   764: pop
    //   765: iload_2
    //   766: ifeq -> 1364
    //   769: goto -> 776
    //   772: invokestatic a : (Ljava/lang/Throwable;)Ljava/lang/Throwable;
    //   775: athrow
    //   776: aload_3
    //   777: getstatic burp/Zrl5.ZG : Ljava/lang/String;
    //   780: getstatic burp/Zgsy.ZC : Ljava/lang/Object;
    //   783: checkcast java/math/BigInteger
    //   786: invokevirtual intValue : ()I
    //   789: bipush #32
    //   791: irem
    //   792: invokestatic abs : (I)I
    //   795: invokevirtual charAt : (I)C
    //   798: invokevirtual append : (C)Ljava/lang/StringBuilder;
    //   801: pop
    //   802: iload_2
    //   803: ifeq -> 1364
    //   806: goto -> 813
    //   809: invokestatic a : (Ljava/lang/Throwable;)Ljava/lang/Throwable;
    //   812: athrow
    //   813: aload_3
    //   814: getstatic burp/Zr17.Zu : Ljava/lang/String;
    //   817: getstatic burp/Zelt.ZC : Ljava/lang/Object;
    //   820: checkcast java/math/BigInteger
    //   823: invokevirtual intValue : ()I
    //   826: bipush #32
    //   828: irem
    //   829: invokestatic abs : (I)I
    //   832: invokevirtual charAt : (I)C
    //   835: invokevirtual append : (C)Ljava/lang/StringBuilder;
    //   838: pop
    //   839: iload_2
    //   840: ifeq -> 1364
    //   843: goto -> 850
    //   846: invokestatic a : (Ljava/lang/Throwable;)Ljava/lang/Throwable;
    //   849: athrow
    //   850: aload_3
    //   851: getstatic burp/Zrjw.Zz : Ljava/lang/String;
    //   854: getstatic burp/Zr02.ZB : Ljava/lang/Object;
    //   857: checkcast java/math/BigInteger
    //   860: invokevirtual intValue : ()I
    //   863: bipush #32
    //   865: irem
    //   866: invokestatic abs : (I)I
    //   869: invokevirtual charAt : (I)C
    //   872: invokevirtual append : (C)Ljava/lang/StringBuilder;
    //   875: pop
    //   876: iload_2
    //   877: ifeq -> 1364
    //   880: goto -> 887
    //   883: invokestatic a : (Ljava/lang/Throwable;)Ljava/lang/Throwable;
    //   886: athrow
    //   887: aload_3
    //   888: getstatic burp/Zrfa.ZT : Ljava/lang/String;
    //   891: getstatic burp/Zetf.Zs : Ljava/lang/Object;
    //   894: checkcast java/math/BigInteger
    //   897: invokevirtual intValue : ()I
    //   900: bipush #32
    //   902: irem
    //   903: invokestatic abs : (I)I
    //   906: invokevirtual charAt : (I)C
    //   909: invokevirtual append : (C)Ljava/lang/StringBuilder;
    //   912: pop
    //   913: iload_2
    //   914: ifeq -> 1364
    //   917: goto -> 924
    //   920: invokestatic a : (Ljava/lang/Throwable;)Ljava/lang/Throwable;
    //   923: athrow
    //   924: aload_3
    //   925: getstatic burp/Zos.Za : Ljava/lang/String;
    //   928: getstatic burp/Zl1e.Zp : Ljava/lang/Object;
    //   931: checkcast java/math/BigInteger
    //   934: invokevirtual intValue : ()I
    //   937: bipush #32
    //   939: irem
    //   940: invokestatic abs : (I)I
    //   943: invokevirtual charAt : (I)C
    //   946: invokevirtual append : (C)Ljava/lang/StringBuilder;
    //   949: pop
    //   950: iload_2
    //   951: ifeq -> 1364
    //   954: goto -> 961
    //   957: invokestatic a : (Ljava/lang/Throwable;)Ljava/lang/Throwable;
    //   960: athrow
    //   961: aload_3
    //   962: getstatic burp/Zlo0.ZD : Ljava/lang/String;
    //   965: getstatic burp/Zgk9.ZD : Ljava/lang/Object;
    //   968: checkcast java/math/BigInteger
    //   971: invokevirtual intValue : ()I
    //   974: bipush #32
    //   976: irem
    //   977: invokestatic abs : (I)I
    //   980: invokevirtual charAt : (I)C
    //   983: invokevirtual append : (C)Ljava/lang/StringBuilder;
    //   986: pop
    //   987: iload_2
    //   988: ifeq -> 1364
    //   991: goto -> 998
    //   994: invokestatic a : (Ljava/lang/Throwable;)Ljava/lang/Throwable;
    //   997: athrow
    //   998: aload_3
    //   999: getstatic burp/Zgpx.Z_ : Ljava/lang/String;
    //   1002: getstatic burp/Zk5k.Zr : Ljava/lang/Object;
    //   1005: checkcast java/math/BigInteger
    //   1008: invokevirtual intValue : ()I
    //   1011: bipush #32
    //   1013: irem
    //   1014: invokestatic abs : (I)I
    //   1017: invokevirtual charAt : (I)C
    //   1020: invokevirtual append : (C)Ljava/lang/StringBuilder;
    //   1023: pop
    //   1024: iload_2
    //   1025: ifeq -> 1364
    //   1028: goto -> 1035
    //   1031: invokestatic a : (Ljava/lang/Throwable;)Ljava/lang/Throwable;
    //   1034: athrow
    //   1035: aload_3
    //   1036: getstatic burp/Zxxo.ZH : Ljava/lang/String;
    //   1039: getstatic burp/Zmhq.ZK : Ljava/lang/Object;
    //   1042: checkcast java/math/BigInteger
    //   1045: invokevirtual intValue : ()I
    //   1048: bipush #32
    //   1050: irem
    //   1051: invokestatic abs : (I)I
    //   1054: invokevirtual charAt : (I)C
    //   1057: invokevirtual append : (C)Ljava/lang/StringBuilder;
    //   1060: pop
    //   1061: iload_2
    //   1062: ifeq -> 1364
    //   1065: goto -> 1072
    //   1068: invokestatic a : (Ljava/lang/Throwable;)Ljava/lang/Throwable;
    //   1071: athrow
    //   1072: aload_3
    //   1073: getstatic burp/Zbun.ZS : Ljava/lang/String;
    //   1076: getstatic burp/Zm_u.Zf : Ljava/lang/Object;
    //   1079: checkcast java/math/BigInteger
    //   1082: invokevirtual intValue : ()I
    //   1085: bipush #32
    //   1087: irem
    //   1088: invokestatic abs : (I)I
    //   1091: invokevirtual charAt : (I)C
    //   1094: invokevirtual append : (C)Ljava/lang/StringBuilder;
    //   1097: pop
    //   1098: iload_2
    //   1099: ifeq -> 1364
    //   1102: goto -> 1109
    //   1105: invokestatic a : (Ljava/lang/Throwable;)Ljava/lang/Throwable;
    //   1108: athrow
    //   1109: aload_3
    //   1110: getstatic burp/Zlw8.Zs : Ljava/lang/String;
    //   1113: getstatic burp/Zsbv.Zl : Ljava/lang/Object;
    //   1116: checkcast java/math/BigInteger
    //   1119: invokevirtual intValue : ()I
    //   1122: bipush #32
    //   1124: irem
    //   1125: invokestatic abs : (I)I
    //   1128: invokevirtual charAt : (I)C
    //   1131: invokevirtual append : (C)Ljava/lang/StringBuilder;
    //   1134: pop
    //   1135: iload_2
    //   1136: ifeq -> 1364
    //   1139: goto -> 1146
    //   1142: invokestatic a : (Ljava/lang/Throwable;)Ljava/lang/Throwable;
    //   1145: athrow
    //   1146: aload_3
    //   1147: getstatic burp/Zt5t.ZK : Ljava/lang/String;
    //   1150: getstatic burp/Zlw8.ZA : Ljava/lang/Object;
    //   1153: checkcast java/math/BigInteger
    //   1156: invokevirtual intValue : ()I
    //   1159: bipush #32
    //   1161: irem
    //   1162: invokestatic abs : (I)I
    //   1165: invokevirtual charAt : (I)C
    //   1168: invokevirtual append : (C)Ljava/lang/StringBuilder;
    //   1171: pop
    //   1172: iload_2
    //   1173: ifeq -> 1364
    //   1176: goto -> 1183
    //   1179: invokestatic a : (Ljava/lang/Throwable;)Ljava/lang/Throwable;
    //   1182: athrow
    //   1183: aload_3
    //   1184: getstatic burp/Ztlo.Zs : Ljava/lang/String;
    //   1187: getstatic burp/Zry1.Zf : Ljava/lang/Object;
    //   1190: checkcast java/math/BigInteger
    //   1193: invokevirtual intValue : ()I
    //   1196: bipush #32
    //   1198: irem
    //   1199: invokestatic abs : (I)I
    //   1202: invokevirtual charAt : (I)C
    //   1205: invokevirtual append : (C)Ljava/lang/StringBuilder;
    //   1208: pop
    //   1209: iload_2
    //   1210: ifeq -> 1364
    //   1213: goto -> 1220
    //   1216: invokestatic a : (Ljava/lang/Throwable;)Ljava/lang/Throwable;
    //   1219: athrow
    //   1220: aload_3
    //   1221: getstatic burp/Zbl4.Ze : Ljava/lang/String;
    //   1224: getstatic burp/Zxn9.ZN : Ljava/lang/Object;
    //   1227: checkcast java/math/BigInteger
    //   1230: invokevirtual intValue : ()I
    //   1233: bipush #32
    //   1235: irem
    //   1236: invokestatic abs : (I)I
    //   1239: invokevirtual charAt : (I)C
    //   1242: invokevirtual append : (C)Ljava/lang/StringBuilder;
    //   1245: pop
    //   1246: iload_2
    //   1247: ifeq -> 1364
    //   1250: goto -> 1257
    //   1253: invokestatic a : (Ljava/lang/Throwable;)Ljava/lang/Throwable;
    //   1256: athrow
    //   1257: aload_3
    //   1258: getstatic burp/Ztle.ZR : Ljava/lang/String;
    //   1261: getstatic burp/Zr_x.Zd : Ljava/lang/Object;
    //   1264: checkcast java/math/BigInteger
    //   1267: invokevirtual intValue : ()I
    //   1270: bipush #32
    //   1272: irem
    //   1273: invokestatic abs : (I)I
    //   1276: invokevirtual charAt : (I)C
    //   1279: invokevirtual append : (C)Ljava/lang/StringBuilder;
    //   1282: pop
    //   1283: iload_2
    //   1284: ifeq -> 1364
    //   1287: goto -> 1294
    //   1290: invokestatic a : (Ljava/lang/Throwable;)Ljava/lang/Throwable;
    //   1293: athrow
    //   1294: aload_3
    //   1295: getstatic burp/Zkql.ZR : Ljava/lang/String;
    //   1298: getstatic burp/Zse8.Zn : Ljava/lang/Object;
    //   1301: checkcast java/math/BigInteger
    //   1304: invokevirtual intValue : ()I
    //   1307: bipush #32
    //   1309: irem
    //   1310: invokestatic abs : (I)I
    //   1313: invokevirtual charAt : (I)C
    //   1316: invokevirtual append : (C)Ljava/lang/StringBuilder;
    //   1319: pop
    //   1320: iload_2
    //   1321: ifeq -> 1364
    //   1324: goto -> 1331
    //   1327: invokestatic a : (Ljava/lang/Throwable;)Ljava/lang/Throwable;
    //   1330: athrow
    //   1331: aload_3
    //   1332: getstatic burp/Zbl4.Ze : Ljava/lang/String;
    //   1335: getstatic burp/Ztq4.ZA : Ljava/lang/Object;
    //   1338: checkcast java/math/BigInteger
    //   1341: invokevirtual intValue : ()I
    //   1344: bipush #32
    //   1346: irem
    //   1347: invokestatic abs : (I)I
    //   1350: invokevirtual charAt : (I)C
    //   1353: invokevirtual append : (C)Ljava/lang/StringBuilder;
    //   1356: pop
    //   1357: goto -> 1364
    //   1360: invokestatic a : (Ljava/lang/Throwable;)Ljava/lang/Throwable;
    //   1363: athrow
    //   1364: iinc #4, 1
    //   1367: iload_2
    //   1368: ifeq -> 33
    //   1371: aload_3
    //   1372: invokevirtual toString : ()Ljava/lang/String;
    //   1375: putstatic burp/Zea9.Zd : Ljava/lang/String;
    //   1378: new java/lang/StringBuilder
    //   1381: dup
    //   1382: invokespecial <init> : ()V
    //   1385: astore #4
    //   1387: iconst_0
    //   1388: istore #5
    //   1390: iload #5
    //   1392: bipush #32
    //   1394: if_icmpge -> 2759
    //   1397: iload #5
    //   1399: tableswitch default -> 2752, 0 -> 1540, 1 -> 1578, 2 -> 1616, 3 -> 1654, 4 -> 1692, 5 -> 1730, 6 -> 1768, 7 -> 1806, 8 -> 1844, 9 -> 1882, 10 -> 1920, 11 -> 1958, 12 -> 1996, 13 -> 2034, 14 -> 2072, 15 -> 2110, 16 -> 2148, 17 -> 2186, 18 -> 2224, 19 -> 2262, 20 -> 2300, 21 -> 2338, 22 -> 2376, 23 -> 2414, 24 -> 2452, 25 -> 2490, 26 -> 2528, 27 -> 2566, 28 -> 2604, 29 -> 2642, 30 -> 2680, 31 -> 2718
    //   1540: aload #4
    //   1542: getstatic burp/Zt6z.ZL : Ljava/lang/String;
    //   1545: getstatic burp/Zr14.Zy : Ljava/lang/Object;
    //   1548: checkcast java/math/BigInteger
    //   1551: invokevirtual intValue : ()I
    //   1554: bipush #32
    //   1556: irem
    //   1557: invokestatic abs : (I)I
    //   1560: invokevirtual charAt : (I)C
    //   1563: invokevirtual append : (C)Ljava/lang/StringBuilder;
    //   1566: pop
    //   1567: iload_2
    //   1568: ifeq -> 2752
    //   1571: goto -> 1578
    //   1574: invokestatic a : (Ljava/lang/Throwable;)Ljava/lang/Throwable;
    //   1577: athrow
    //   1578: aload #4
    //   1580: getstatic burp/Zxxh.Zm : Ljava/lang/String;
    //   1583: getstatic burp/Zg2u.ZI : Ljava/lang/Object;
    //   1586: checkcast java/math/BigInteger
    //   1589: invokevirtual intValue : ()I
    //   1592: bipush #32
    //   1594: irem
    //   1595: invokestatic abs : (I)I
    //   1598: invokevirtual charAt : (I)C
    //   1601: invokevirtual append : (C)Ljava/lang/StringBuilder;
    //   1604: pop
    //   1605: iload_2
    //   1606: ifeq -> 2752
    //   1609: goto -> 1616
    //   1612: invokestatic a : (Ljava/lang/Throwable;)Ljava/lang/Throwable;
    //   1615: athrow
    //   1616: aload #4
    //   1618: getstatic burp/Zscf.Zu : Ljava/lang/String;
    //   1621: getstatic burp/Zkeb.ZH : Ljava/lang/Object;
    //   1624: checkcast java/math/BigInteger
    //   1627: invokevirtual intValue : ()I
    //   1630: bipush #32
    //   1632: irem
    //   1633: invokestatic abs : (I)I
    //   1636: invokevirtual charAt : (I)C
    //   1639: invokevirtual append : (C)Ljava/lang/StringBuilder;
    //   1642: pop
    //   1643: iload_2
    //   1644: ifeq -> 2752
    //   1647: goto -> 1654
    //   1650: invokestatic a : (Ljava/lang/Throwable;)Ljava/lang/Throwable;
    //   1653: athrow
    //   1654: aload #4
    //   1656: getstatic burp/Zkdq.ZZ : Ljava/lang/String;
    //   1659: getstatic burp/Ze4w.Zd : Ljava/lang/Object;
    //   1662: checkcast java/math/BigInteger
    //   1665: invokevirtual intValue : ()I
    //   1668: bipush #32
    //   1670: irem
    //   1671: invokestatic abs : (I)I
    //   1674: invokevirtual charAt : (I)C
    //   1677: invokevirtual append : (C)Ljava/lang/StringBuilder;
    //   1680: pop
    //   1681: iload_2
    //   1682: ifeq -> 2752
    //   1685: goto -> 1692
    //   1688: invokestatic a : (Ljava/lang/Throwable;)Ljava/lang/Throwable;
    //   1691: athrow
    //   1692: aload #4
    //   1694: getstatic burp/Zzi_.ZG : Ljava/lang/String;
    //   1697: getstatic burp/Zm8j.Zj : Ljava/lang/Object;
    //   1700: checkcast java/math/BigInteger
    //   1703: invokevirtual intValue : ()I
    //   1706: bipush #32
    //   1708: irem
    //   1709: invokestatic abs : (I)I
    //   1712: invokevirtual charAt : (I)C
    //   1715: invokevirtual append : (C)Ljava/lang/StringBuilder;
    //   1718: pop
    //   1719: iload_2
    //   1720: ifeq -> 2752
    //   1723: goto -> 1730
    //   1726: invokestatic a : (Ljava/lang/Throwable;)Ljava/lang/Throwable;
    //   1729: athrow
    //   1730: aload #4
    //   1732: getstatic burp/Zrfa.ZT : Ljava/lang/String;
    //   1735: getstatic burp/Zkkl.ZE : Ljava/lang/Object;
    //   1738: checkcast java/math/BigInteger
    //   1741: invokevirtual intValue : ()I
    //   1744: bipush #32
    //   1746: irem
    //   1747: invokestatic abs : (I)I
    //   1750: invokevirtual charAt : (I)C
    //   1753: invokevirtual append : (C)Ljava/lang/StringBuilder;
    //   1756: pop
    //   1757: iload_2
    //   1758: ifeq -> 2752
    //   1761: goto -> 1768
    //   1764: invokestatic a : (Ljava/lang/Throwable;)Ljava/lang/Throwable;
    //   1767: athrow
    //   1768: aload #4
    //   1770: getstatic burp/Zrqi.Zu : Ljava/lang/String;
    //   1773: getstatic burp/Zgi9.Zc : Ljava/lang/Object;
    //   1776: checkcast java/math/BigInteger
    //   1779: invokevirtual intValue : ()I
    //   1782: bipush #32
    //   1784: irem
    //   1785: invokestatic abs : (I)I
    //   1788: invokevirtual charAt : (I)C
    //   1791: invokevirtual append : (C)Ljava/lang/StringBuilder;
    //   1794: pop
    //   1795: iload_2
    //   1796: ifeq -> 2752
    //   1799: goto -> 1806
    //   1802: invokestatic a : (Ljava/lang/Throwable;)Ljava/lang/Throwable;
    //   1805: athrow
    //   1806: aload #4
    //   1808: getstatic burp/Zrw0.Zj : Ljava/lang/String;
    //   1811: getstatic burp/Zx4u.Zn : Ljava/lang/Object;
    //   1814: checkcast java/math/BigInteger
    //   1817: invokevirtual intValue : ()I
    //   1820: bipush #32
    //   1822: irem
    //   1823: invokestatic abs : (I)I
    //   1826: invokevirtual charAt : (I)C
    //   1829: invokevirtual append : (C)Ljava/lang/StringBuilder;
    //   1832: pop
    //   1833: iload_2
    //   1834: ifeq -> 2752
    //   1837: goto -> 1844
    //   1840: invokestatic a : (Ljava/lang/Throwable;)Ljava/lang/Throwable;
    //   1843: athrow
    //   1844: aload #4
    //   1846: getstatic burp/Zxxh.Zm : Ljava/lang/String;
    //   1849: getstatic burp/Zz0f.ZL : Ljava/lang/Object;
    //   1852: checkcast java/math/BigInteger
    //   1855: invokevirtual intValue : ()I
    //   1858: bipush #32
    //   1860: irem
    //   1861: invokestatic abs : (I)I
    //   1864: invokevirtual charAt : (I)C
    //   1867: invokevirtual append : (C)Ljava/lang/StringBuilder;
    //   1870: pop
    //   1871: iload_2
    //   1872: ifeq -> 2752
    //   1875: goto -> 1882
    //   1878: invokestatic a : (Ljava/lang/Throwable;)Ljava/lang/Throwable;
    //   1881: athrow
    //   1882: aload #4
    //   1884: getstatic burp/Zxln.Zz : Ljava/lang/String;
    //   1887: getstatic burp/Zkeb.ZH : Ljava/lang/Object;
    //   1890: checkcast java/math/BigInteger
    //   1893: invokevirtual intValue : ()I
    //   1896: bipush #32
    //   1898: irem
    //   1899: invokestatic abs : (I)I
    //   1902: invokevirtual charAt : (I)C
    //   1905: invokevirtual append : (C)Ljava/lang/StringBuilder;
    //   1908: pop
    //   1909: iload_2
    //   1910: ifeq -> 2752
    //   1913: goto -> 1920
    //   1916: invokestatic a : (Ljava/lang/Throwable;)Ljava/lang/Throwable;
    //   1919: athrow
    //   1920: aload #4
    //   1922: getstatic burp/Zgeq.ZF : Ljava/lang/String;
    //   1925: getstatic burp/Zxcn.Zq : Ljava/lang/Object;
    //   1928: checkcast java/math/BigInteger
    //   1931: invokevirtual intValue : ()I
    //   1934: bipush #32
    //   1936: irem
    //   1937: invokestatic abs : (I)I
    //   1940: invokevirtual charAt : (I)C
    //   1943: invokevirtual append : (C)Ljava/lang/StringBuilder;
    //   1946: pop
    //   1947: iload_2
    //   1948: ifeq -> 2752
    //   1951: goto -> 1958
    //   1954: invokestatic a : (Ljava/lang/Throwable;)Ljava/lang/Throwable;
    //   1957: athrow
    //   1958: aload #4
    //   1960: getstatic burp/Zm0d.ZV : Ljava/lang/String;
    //   1963: getstatic burp/Zthx.ZH : Ljava/lang/Object;
    //   1966: checkcast java/math/BigInteger
    //   1969: invokevirtual intValue : ()I
    //   1972: bipush #32
    //   1974: irem
    //   1975: invokestatic abs : (I)I
    //   1978: invokevirtual charAt : (I)C
    //   1981: invokevirtual append : (C)Ljava/lang/StringBuilder;
    //   1984: pop
    //   1985: iload_2
    //   1986: ifeq -> 2752
    //   1989: goto -> 1996
    //   1992: invokestatic a : (Ljava/lang/Throwable;)Ljava/lang/Throwable;
    //   1995: athrow
    //   1996: aload #4
    //   1998: getstatic burp/Zb2n.Za : Ljava/lang/String;
    //   2001: getstatic burp/Zbw5.ZR : Ljava/lang/Object;
    //   2004: checkcast java/math/BigInteger
    //   2007: invokevirtual intValue : ()I
    //   2010: bipush #32
    //   2012: irem
    //   2013: invokestatic abs : (I)I
    //   2016: invokevirtual charAt : (I)C
    //   2019: invokevirtual append : (C)Ljava/lang/StringBuilder;
    //   2022: pop
    //   2023: iload_2
    //   2024: ifeq -> 2752
    //   2027: goto -> 2034
    //   2030: invokestatic a : (Ljava/lang/Throwable;)Ljava/lang/Throwable;
    //   2033: athrow
    //   2034: aload #4
    //   2036: getstatic burp/Zea.Zj : Ljava/lang/String;
    //   2039: getstatic burp/Zti7.Zw : Ljava/lang/Object;
    //   2042: checkcast java/math/BigInteger
    //   2045: invokevirtual intValue : ()I
    //   2048: bipush #32
    //   2050: irem
    //   2051: invokestatic abs : (I)I
    //   2054: invokevirtual charAt : (I)C
    //   2057: invokevirtual append : (C)Ljava/lang/StringBuilder;
    //   2060: pop
    //   2061: iload_2
    //   2062: ifeq -> 2752
    //   2065: goto -> 2072
    //   2068: invokestatic a : (Ljava/lang/Throwable;)Ljava/lang/Throwable;
    //   2071: athrow
    //   2072: aload #4
    //   2074: getstatic burp/Zk1.Zg : Ljava/lang/String;
    //   2077: getstatic burp/Zs8w.ZW : Ljava/lang/Object;
    //   2080: checkcast java/math/BigInteger
    //   2083: invokevirtual intValue : ()I
    //   2086: bipush #32
    //   2088: irem
    //   2089: invokestatic abs : (I)I
    //   2092: invokevirtual charAt : (I)C
    //   2095: invokevirtual append : (C)Ljava/lang/StringBuilder;
    //   2098: pop
    //   2099: iload_2
    //   2100: ifeq -> 2752
    //   2103: goto -> 2110
    //   2106: invokestatic a : (Ljava/lang/Throwable;)Ljava/lang/Throwable;
    //   2109: athrow
    //   2110: aload #4
    //   2112: getstatic burp/Zbx5.Zz : Ljava/lang/String;
    //   2115: getstatic burp/Zr9u.ZX : Ljava/lang/Object;
    //   2118: checkcast java/math/BigInteger
    //   2121: invokevirtual intValue : ()I
    //   2124: bipush #32
    //   2126: irem
    //   2127: invokestatic abs : (I)I
    //   2130: invokevirtual charAt : (I)C
    //   2133: invokevirtual append : (C)Ljava/lang/StringBuilder;
    //   2136: pop
    //   2137: iload_2
    //   2138: ifeq -> 2752
    //   2141: goto -> 2148
    //   2144: invokestatic a : (Ljava/lang/Throwable;)Ljava/lang/Throwable;
    //   2147: athrow
    //   2148: aload #4
    //   2150: getstatic burp/Zej8.ZP : Ljava/lang/String;
    //   2153: getstatic burp/Znu.Zf : Ljava/lang/Object;
    //   2156: checkcast java/math/BigInteger
    //   2159: invokevirtual intValue : ()I
    //   2162: bipush #32
    //   2164: irem
    //   2165: invokestatic abs : (I)I
    //   2168: invokevirtual charAt : (I)C
    //   2171: invokevirtual append : (C)Ljava/lang/StringBuilder;
    //   2174: pop
    //   2175: iload_2
    //   2176: ifeq -> 2752
    //   2179: goto -> 2186
    //   2182: invokestatic a : (Ljava/lang/Throwable;)Ljava/lang/Throwable;
    //   2185: athrow
    //   2186: aload #4
    //   2188: getstatic burp/Zz91.Zx : Ljava/lang/String;
    //   2191: getstatic burp/Zejz.ZF : Ljava/lang/Object;
    //   2194: checkcast java/math/BigInteger
    //   2197: invokevirtual intValue : ()I
    //   2200: bipush #32
    //   2202: irem
    //   2203: invokestatic abs : (I)I
    //   2206: invokevirtual charAt : (I)C
    //   2209: invokevirtual append : (C)Ljava/lang/StringBuilder;
    //   2212: pop
    //   2213: iload_2
    //   2214: ifeq -> 2752
    //   2217: goto -> 2224
    //   2220: invokestatic a : (Ljava/lang/Throwable;)Ljava/lang/Throwable;
    //   2223: athrow
    //   2224: aload #4
    //   2226: getstatic burp/Zge9.Zp : Ljava/lang/String;
    //   2229: getstatic burp/Zzre.ZE : Ljava/lang/Object;
    //   2232: checkcast java/math/BigInteger
    //   2235: invokevirtual intValue : ()I
    //   2238: bipush #32
    //   2240: irem
    //   2241: invokestatic abs : (I)I
    //   2244: invokevirtual charAt : (I)C
    //   2247: invokevirtual append : (C)Ljava/lang/StringBuilder;
    //   2250: pop
    //   2251: iload_2
    //   2252: ifeq -> 2752
    //   2255: goto -> 2262
    //   2258: invokestatic a : (Ljava/lang/Throwable;)Ljava/lang/Throwable;
    //   2261: athrow
    //   2262: aload #4
    //   2264: getstatic burp/Zv8l.Zo : Ljava/lang/String;
    //   2267: getstatic burp/Zrnt.Zh : Ljava/lang/Object;
    //   2270: checkcast java/math/BigInteger
    //   2273: invokevirtual intValue : ()I
    //   2276: bipush #32
    //   2278: irem
    //   2279: invokestatic abs : (I)I
    //   2282: invokevirtual charAt : (I)C
    //   2285: invokevirtual append : (C)Ljava/lang/StringBuilder;
    //   2288: pop
    //   2289: iload_2
    //   2290: ifeq -> 2752
    //   2293: goto -> 2300
    //   2296: invokestatic a : (Ljava/lang/Throwable;)Ljava/lang/Throwable;
    //   2299: athrow
    //   2300: aload #4
    //   2302: getstatic burp/Zb3l.Zz : Ljava/lang/String;
    //   2305: getstatic burp/Zgsb.Zl : Ljava/lang/Object;
    //   2308: checkcast java/math/BigInteger
    //   2311: invokevirtual intValue : ()I
    //   2314: bipush #32
    //   2316: irem
    //   2317: invokestatic abs : (I)I
    //   2320: invokevirtual charAt : (I)C
    //   2323: invokevirtual append : (C)Ljava/lang/StringBuilder;
    //   2326: pop
    //   2327: iload_2
    //   2328: ifeq -> 2752
    //   2331: goto -> 2338
    //   2334: invokestatic a : (Ljava/lang/Throwable;)Ljava/lang/Throwable;
    //   2337: athrow
    //   2338: aload #4
    //   2340: getstatic burp/Zz66.ZM : Ljava/lang/String;
    //   2343: getstatic burp/Zb4d.Ze : Ljava/lang/Object;
    //   2346: checkcast java/math/BigInteger
    //   2349: invokevirtual intValue : ()I
    //   2352: bipush #32
    //   2354: irem
    //   2355: invokestatic abs : (I)I
    //   2358: invokevirtual charAt : (I)C
    //   2361: invokevirtual append : (C)Ljava/lang/StringBuilder;
    //   2364: pop
    //   2365: iload_2
    //   2366: ifeq -> 2752
    //   2369: goto -> 2376
    //   2372: invokestatic a : (Ljava/lang/Throwable;)Ljava/lang/Throwable;
    //   2375: athrow
    //   2376: aload #4
    //   2378: getstatic burp/Zzna.Zi : Ljava/lang/String;
    //   2381: getstatic burp/Zbw5.ZR : Ljava/lang/Object;
    //   2384: checkcast java/math/BigInteger
    //   2387: invokevirtual intValue : ()I
    //   2390: bipush #32
    //   2392: irem
    //   2393: invokestatic abs : (I)I
    //   2396: invokevirtual charAt : (I)C
    //   2399: invokevirtual append : (C)Ljava/lang/StringBuilder;
    //   2402: pop
    //   2403: iload_2
    //   2404: ifeq -> 2752
    //   2407: goto -> 2414
    //   2410: invokestatic a : (Ljava/lang/Throwable;)Ljava/lang/Throwable;
    //   2413: athrow
    //   2414: aload #4
    //   2416: getstatic burp/Zsfj.Zg : Ljava/lang/String;
    //   2419: getstatic burp/Ztlo.ZP : Ljava/lang/Object;
    //   2422: checkcast java/math/BigInteger
    //   2425: invokevirtual intValue : ()I
    //   2428: bipush #32
    //   2430: irem
    //   2431: invokestatic abs : (I)I
    //   2434: invokevirtual charAt : (I)C
    //   2437: invokevirtual append : (C)Ljava/lang/StringBuilder;
    //   2440: pop
    //   2441: iload_2
    //   2442: ifeq -> 2752
    //   2445: goto -> 2452
    //   2448: invokestatic a : (Ljava/lang/Throwable;)Ljava/lang/Throwable;
    //   2451: athrow
    //   2452: aload #4
    //   2454: getstatic burp/Zthx.Ze : Ljava/lang/String;
    //   2457: getstatic burp/Zrh_.Zb : Ljava/lang/Object;
    //   2460: checkcast java/math/BigInteger
    //   2463: invokevirtual intValue : ()I
    //   2466: bipush #32
    //   2468: irem
    //   2469: invokestatic abs : (I)I
    //   2472: invokevirtual charAt : (I)C
    //   2475: invokevirtual append : (C)Ljava/lang/StringBuilder;
    //   2478: pop
    //   2479: iload_2
    //   2480: ifeq -> 2752
    //   2483: goto -> 2490
    //   2486: invokestatic a : (Ljava/lang/Throwable;)Ljava/lang/Throwable;
    //   2489: athrow
    //   2490: aload #4
    //   2492: getstatic burp/Zsp9.ZA : Ljava/lang/String;
    //   2495: getstatic burp/Zdv.Zw : Ljava/lang/Object;
    //   2498: checkcast java/math/BigInteger
    //   2501: invokevirtual intValue : ()I
    //   2504: bipush #32
    //   2506: irem
    //   2507: invokestatic abs : (I)I
    //   2510: invokevirtual charAt : (I)C
    //   2513: invokevirtual append : (C)Ljava/lang/StringBuilder;
    //   2516: pop
    //   2517: iload_2
    //   2518: ifeq -> 2752
    //   2521: goto -> 2528
    //   2524: invokestatic a : (Ljava/lang/Throwable;)Ljava/lang/Throwable;
    //   2527: athrow
    //   2528: aload #4
    //   2530: getstatic burp/Zeva.Zo : Ljava/lang/String;
    //   2533: getstatic burp/Zbw5.ZR : Ljava/lang/Object;
    //   2536: checkcast java/math/BigInteger
    //   2539: invokevirtual intValue : ()I
    //   2542: bipush #32
    //   2544: irem
    //   2545: invokestatic abs : (I)I
    //   2548: invokevirtual charAt : (I)C
    //   2551: invokevirtual append : (C)Ljava/lang/StringBuilder;
    //   2554: pop
    //   2555: iload_2
    //   2556: ifeq -> 2752
    //   2559: goto -> 2566
    //   2562: invokestatic a : (Ljava/lang/Throwable;)Ljava/lang/Throwable;
    //   2565: athrow
    //   2566: aload #4
    //   2568: getstatic burp/Ztq8.ZI : Ljava/lang/String;
    //   2571: getstatic burp/Zxp1.ZP : Ljava/lang/Object;
    //   2574: checkcast java/math/BigInteger
    //   2577: invokevirtual intValue : ()I
    //   2580: bipush #32
    //   2582: irem
    //   2583: invokestatic abs : (I)I
    //   2586: invokevirtual charAt : (I)C
    //   2589: invokevirtual append : (C)Ljava/lang/StringBuilder;
    //   2592: pop
    //   2593: iload_2
    //   2594: ifeq -> 2752
    //   2597: goto -> 2604
    //   2600: invokestatic a : (Ljava/lang/Throwable;)Ljava/lang/Throwable;
    //   2603: athrow
    //   2604: aload #4
    //   2606: getstatic burp/Zg6z.ZY : Ljava/lang/String;
    //   2609: getstatic burp/Zegj.ZT : Ljava/lang/Object;
    //   2612: checkcast java/math/BigInteger
    //   2615: invokevirtual intValue : ()I
    //   2618: bipush #32
    //   2620: irem
    //   2621: invokestatic abs : (I)I
    //   2624: invokevirtual charAt : (I)C
    //   2627: invokevirtual append : (C)Ljava/lang/StringBuilder;
    //   2630: pop
    //   2631: iload_2
    //   2632: ifeq -> 2752
    //   2635: goto -> 2642
    //   2638: invokestatic a : (Ljava/lang/Throwable;)Ljava/lang/Throwable;
    //   2641: athrow
    //   2642: aload #4
    //   2644: getstatic burp/Zz7j.ZP : Ljava/lang/String;
    //   2647: getstatic burp/Zst7.ZI : Ljava/lang/Object;
    //   2650: checkcast java/math/BigInteger
    //   2653: invokevirtual intValue : ()I
    //   2656: bipush #32
    //   2658: irem
    //   2659: invokestatic abs : (I)I
    //   2662: invokevirtual charAt : (I)C
    //   2665: invokevirtual append : (C)Ljava/lang/StringBuilder;
    //   2668: pop
    //   2669: iload_2
    //   2670: ifeq -> 2752
    //   2673: goto -> 2680
    //   2676: invokestatic a : (Ljava/lang/Throwable;)Ljava/lang/Throwable;
    //   2679: athrow
    //   2680: aload #4
    //   2682: getstatic burp/Zrt3.Zu : Ljava/lang/String;
    //   2685: getstatic burp/Ze7e.Z_ : Ljava/lang/Object;
    //   2688: checkcast java/math/BigInteger
    //   2691: invokevirtual intValue : ()I
    //   2694: bipush #32
    //   2696: irem
    //   2697: invokestatic abs : (I)I
    //   2700: invokevirtual charAt : (I)C
    //   2703: invokevirtual append : (C)Ljava/lang/StringBuilder;
    //   2706: pop
    //   2707: iload_2
    //   2708: ifeq -> 2752
    //   2711: goto -> 2718
    //   2714: invokestatic a : (Ljava/lang/Throwable;)Ljava/lang/Throwable;
    //   2717: athrow
    //   2718: aload #4
    //   2720: getstatic burp/Zst7.Zi : Ljava/lang/String;
    //   2723: getstatic burp/Zvob.ZX : Ljava/lang/Object;
    //   2726: checkcast java/math/BigInteger
    //   2729: invokevirtual intValue : ()I
    //   2732: bipush #32
    //   2734: irem
    //   2735: invokestatic abs : (I)I
    //   2738: invokevirtual charAt : (I)C
    //   2741: invokevirtual append : (C)Ljava/lang/StringBuilder;
    //   2744: pop
    //   2745: goto -> 2752
    //   2748: invokestatic a : (Ljava/lang/Throwable;)Ljava/lang/Throwable;
    //   2751: athrow
    //   2752: iinc #5, 1
    //   2755: iload_2
    //   2756: ifeq -> 1390
    //   2759: aload #4
    //   2761: invokevirtual toString : ()Ljava/lang/String;
    //   2764: putstatic burp/Zs4g.ZV : Ljava/lang/String;
    //   2767: sipush #24266
    //   2770: sipush #12046
    //   2773: invokestatic a : (II)Ljava/lang/String;
    //   2776: iconst_1
    //   2777: ldc burp/Zzy5
    //   2779: invokevirtual getClassLoader : ()Ljava/lang/ClassLoader;
    //   2782: invokestatic forName : (Ljava/lang/String;ZLjava/lang/ClassLoader;)Ljava/lang/Class;
    //   2785: invokevirtual getDeclaredFields : ()[Ljava/lang/reflect/Field;
    //   2788: astore #5
    //   2790: aload #5
    //   2792: arraylength
    //   2793: istore #6
    //   2795: iconst_0
    //   2796: istore #7
    //   2798: iload #7
    //   2800: iload #6
    //   2802: if_icmpge -> 2940
    //   2805: aload #5
    //   2807: iload #7
    //   2809: aaload
    //   2810: astore #8
    //   2812: aload #8
    //   2814: invokevirtual getModifiers : ()I
    //   2817: invokestatic isStatic : (I)Z
    //   2820: ifne -> 2830
    //   2823: goto -> 2933
    //   2826: invokestatic a : (Ljava/lang/Throwable;)Ljava/lang/Throwable;
    //   2829: athrow
    //   2830: aload #8
    //   2832: invokevirtual getType : ()Ljava/lang/Class;
    //   2835: astore #9
    //   2837: aload #9
    //   2839: ifnull -> 2920
    //   2842: aload #9
    //   2844: invokevirtual isPrimitive : ()Z
    //   2847: ifne -> 2920
    //   2850: goto -> 2857
    //   2853: invokestatic a : (Ljava/lang/Throwable;)Ljava/lang/Throwable;
    //   2856: athrow
    //   2857: aload #9
    //   2859: invokevirtual getPackage : ()Ljava/lang/Package;
    //   2862: ifnull -> 2920
    //   2865: goto -> 2872
    //   2868: invokestatic a : (Ljava/lang/Throwable;)Ljava/lang/Throwable;
    //   2871: athrow
    //   2872: aload #9
    //   2874: invokevirtual getPackage : ()Ljava/lang/Package;
    //   2877: invokevirtual getName : ()Ljava/lang/String;
    //   2880: ifnull -> 2920
    //   2883: goto -> 2890
    //   2886: invokestatic a : (Ljava/lang/Throwable;)Ljava/lang/Throwable;
    //   2889: athrow
    //   2890: aload #9
    //   2892: invokevirtual getPackage : ()Ljava/lang/Package;
    //   2895: invokevirtual getName : ()Ljava/lang/String;
    //   2898: sipush #24269
    //   2901: sipush #-1243
    //   2904: invokestatic a : (II)Ljava/lang/String;
    //   2907: invokevirtual startsWith : (Ljava/lang/String;)Z
    //   2910: ifne -> 2920
    //   2913: goto -> 2920
    //   2916: invokestatic a : (Ljava/lang/Throwable;)Ljava/lang/Throwable;
    //   2919: athrow
    //   2920: aload #8
    //   2922: iconst_1
    //   2923: invokevirtual setAccessible : (Z)V
    //   2926: aload #8
    //   2928: aconst_null
    //   2929: invokevirtual get : (Ljava/lang/Object;)Ljava/lang/Object;
    //   2932: pop
    //   2933: iinc #7, 1
    //   2936: iload_2
    //   2937: ifeq -> 2798
    //   2940: sipush #24283
    //   2943: sipush #-32218
    //   2946: invokestatic a : (II)Ljava/lang/String;
    //   2949: invokestatic forName : (Ljava/lang/String;)Ljava/lang/Class;
    //   2952: invokevirtual getDeclaredMethods : ()[Ljava/lang/reflect/Method;
    //   2955: astore #5
    //   2957: aload #5
    //   2959: arraylength
    //   2960: istore #6
    //   2962: iconst_0
    //   2963: istore #7
    //   2965: iload #7
    //   2967: iload #6
    //   2969: if_icmpge -> 3102
    //   2972: aload #5
    //   2974: iload #7
    //   2976: aaload
    //   2977: astore #8
    //   2979: aload #8
    //   2981: invokevirtual getParameterTypes : ()[Ljava/lang/Class;
    //   2984: pop
    //   2985: aload #8
    //   2987: invokevirtual getModifiers : ()I
    //   2990: invokestatic isStatic : (I)Z
    //   2993: ifeq -> 3088
    //   2996: aload #8
    //   2998: invokevirtual getParameterTypes : ()[Ljava/lang/Class;
    //   3001: arraylength
    //   3002: iconst_2
    //   3003: if_icmpne -> 3088
    //   3006: goto -> 3013
    //   3009: invokestatic a : (Ljava/lang/Throwable;)Ljava/lang/Throwable;
    //   3012: athrow
    //   3013: aload #8
    //   3015: invokevirtual getReturnType : ()Ljava/lang/Class;
    //   3018: getstatic java/lang/Void.TYPE : Ljava/lang/Class;
    //   3021: invokevirtual equals : (Ljava/lang/Object;)Z
    //   3024: ifeq -> 3088
    //   3027: goto -> 3034
    //   3030: invokestatic a : (Ljava/lang/Throwable;)Ljava/lang/Throwable;
    //   3033: athrow
    //   3034: aload #8
    //   3036: iconst_1
    //   3037: invokevirtual setAccessible : (Z)V
    //   3040: aload #8
    //   3042: aconst_null
    //   3043: iconst_2
    //   3044: anewarray java/lang/Object
    //   3047: dup
    //   3048: iconst_0
    //   3049: aload_0
    //   3050: aastore
    //   3051: dup
    //   3052: iconst_1
    //   3053: aload_1
    //   3054: ifnonnull -> 3072
    //   3057: goto -> 3064
    //   3060: invokestatic a : (Ljava/lang/Throwable;)Ljava/lang/Throwable;
    //   3063: athrow
    //   3064: aload_1
    //   3065: goto -> 3079
    //   3068: invokestatic a : (Ljava/lang/Throwable;)Ljava/lang/Throwable;
    //   3071: athrow
    //   3072: aload_1
    //   3073: checkcast [B
    //   3076: invokevirtual clone : ()Ljava/lang/Object;
    //   3079: aastore
    //   3080: invokevirtual invoke : (Ljava/lang/Object;[Ljava/lang/Object;)Ljava/lang/Object;
    //   3083: pop
    //   3084: iload_2
    //   3085: ifeq -> 3102
    //   3088: iinc #7, 1
    //   3091: iload_2
    //   3092: ifeq -> 2965
    //   3095: goto -> 3102
    //   3098: invokestatic a : (Ljava/lang/Throwable;)Ljava/lang/Throwable;
    //   3101: athrow
    //   3102: iconst_0
    //   3103: istore #5
    //   3105: getstatic burp/Zxxh.Zm : Ljava/lang/String;
    //   3108: getstatic burp/Zb2n.ZR : Ljava/lang/Object;
    //   3111: checkcast java/math/BigInteger
    //   3114: invokevirtual intValue : ()I
    //   3117: bipush #32
    //   3119: irem
    //   3120: invokestatic abs : (I)I
    //   3123: invokevirtual charAt : (I)C
    //   3126: getstatic burp/Zzah.Zs : Ljava/lang/String;
    //   3129: getstatic burp/Zsbo.ZG : Ljava/lang/Object;
    //   3132: checkcast java/math/BigInteger
    //   3135: invokevirtual intValue : ()I
    //   3138: bipush #32
    //   3140: irem
    //   3141: invokestatic abs : (I)I
    //   3144: invokevirtual charAt : (I)C
    //   3147: if_icmple -> 3492
    //   3150: sipush #24265
    //   3153: sipush #24420
    //   3156: invokestatic a : (II)Ljava/lang/String;
    //   3159: iconst_1
    //   3160: ldc burp/Zs1d
    //   3162: invokevirtual getClassLoader : ()Ljava/lang/ClassLoader;
    //   3165: invokestatic forName : (Ljava/lang/String;ZLjava/lang/ClassLoader;)Ljava/lang/Class;
    //   3168: invokevirtual getDeclaredFields : ()[Ljava/lang/reflect/Field;
    //   3171: astore #6
    //   3173: aload #6
    //   3175: arraylength
    //   3176: istore #7
    //   3178: iconst_0
    //   3179: istore #8
    //   3181: iload #8
    //   3183: iload #7
    //   3185: if_icmpge -> 3323
    //   3188: aload #6
    //   3190: iload #8
    //   3192: aaload
    //   3193: astore #9
    //   3195: aload #9
    //   3197: invokevirtual getModifiers : ()I
    //   3200: invokestatic isStatic : (I)Z
    //   3203: ifne -> 3213
    //   3206: goto -> 3316
    //   3209: invokestatic a : (Ljava/lang/Throwable;)Ljava/lang/Throwable;
    //   3212: athrow
    //   3213: aload #9
    //   3215: invokevirtual getType : ()Ljava/lang/Class;
    //   3218: astore #10
    //   3220: aload #10
    //   3222: ifnull -> 3303
    //   3225: aload #10
    //   3227: invokevirtual isPrimitive : ()Z
    //   3230: ifne -> 3303
    //   3233: goto -> 3240
    //   3236: invokestatic a : (Ljava/lang/Throwable;)Ljava/lang/Throwable;
    //   3239: athrow
    //   3240: aload #10
    //   3242: invokevirtual getPackage : ()Ljava/lang/Package;
    //   3245: ifnull -> 3303
    //   3248: goto -> 3255
    //   3251: invokestatic a : (Ljava/lang/Throwable;)Ljava/lang/Throwable;
    //   3254: athrow
    //   3255: aload #10
    //   3257: invokevirtual getPackage : ()Ljava/lang/Package;
    //   3260: invokevirtual getName : ()Ljava/lang/String;
    //   3263: ifnull -> 3303
    //   3266: goto -> 3273
    //   3269: invokestatic a : (Ljava/lang/Throwable;)Ljava/lang/Throwable;
    //   3272: athrow
    //   3273: aload #10
    //   3275: invokevirtual getPackage : ()Ljava/lang/Package;
    //   3278: invokevirtual getName : ()Ljava/lang/String;
    //   3281: sipush #24280
    //   3284: sipush #-3610
    //   3287: invokestatic a : (II)Ljava/lang/String;
    //   3290: invokevirtual startsWith : (Ljava/lang/String;)Z
    //   3293: ifne -> 3303
    //   3296: goto -> 3303
    //   3299: invokestatic a : (Ljava/lang/Throwable;)Ljava/lang/Throwable;
    //   3302: athrow
    //   3303: aload #9
    //   3305: iconst_1
    //   3306: invokevirtual setAccessible : (Z)V
    //   3309: aload #9
    //   3311: aconst_null
    //   3312: invokevirtual get : (Ljava/lang/Object;)Ljava/lang/Object;
    //   3315: pop
    //   3316: iinc #8, 1
    //   3319: iload_2
    //   3320: ifeq -> 3181
    //   3323: sipush #24279
    //   3326: sipush #21119
    //   3329: invokestatic a : (II)Ljava/lang/String;
    //   3332: invokestatic forName : (Ljava/lang/String;)Ljava/lang/Class;
    //   3335: invokevirtual getDeclaredMethods : ()[Ljava/lang/reflect/Method;
    //   3338: astore #6
    //   3340: aload #6
    //   3342: arraylength
    //   3343: istore #7
    //   3345: iconst_0
    //   3346: istore #8
    //   3348: iload #8
    //   3350: iload #7
    //   3352: if_icmpge -> 3489
    //   3355: aload #6
    //   3357: iload #8
    //   3359: aaload
    //   3360: astore #9
    //   3362: aload #9
    //   3364: invokevirtual getParameterTypes : ()[Ljava/lang/Class;
    //   3367: pop
    //   3368: aload #9
    //   3370: invokevirtual getModifiers : ()I
    //   3373: invokestatic isStatic : (I)Z
    //   3376: ifeq -> 3475
    //   3379: aload #9
    //   3381: invokevirtual getParameterTypes : ()[Ljava/lang/Class;
    //   3384: arraylength
    //   3385: iconst_2
    //   3386: if_icmpne -> 3475
    //   3389: goto -> 3396
    //   3392: invokestatic a : (Ljava/lang/Throwable;)Ljava/lang/Throwable;
    //   3395: athrow
    //   3396: aload #9
    //   3398: invokevirtual getReturnType : ()Ljava/lang/Class;
    //   3401: getstatic java/lang/Boolean.TYPE : Ljava/lang/Class;
    //   3404: if_acmpne -> 3475
    //   3407: goto -> 3414
    //   3410: invokestatic a : (Ljava/lang/Throwable;)Ljava/lang/Throwable;
    //   3413: athrow
    //   3414: aload #9
    //   3416: iconst_1
    //   3417: invokevirtual setAccessible : (Z)V
    //   3420: aload #9
    //   3422: aconst_null
    //   3423: iconst_2
    //   3424: anewarray java/lang/Object
    //   3427: dup
    //   3428: iconst_0
    //   3429: aload_0
    //   3430: aastore
    //   3431: dup
    //   3432: iconst_1
    //   3433: aload_1
    //   3434: ifnonnull -> 3452
    //   3437: goto -> 3444
    //   3440: invokestatic a : (Ljava/lang/Throwable;)Ljava/lang/Throwable;
    //   3443: athrow
    //   3444: aload_1
    //   3445: goto -> 3459
    //   3448: invokestatic a : (Ljava/lang/Throwable;)Ljava/lang/Throwable;
    //   3451: athrow
    //   3452: aload_1
    //   3453: checkcast [B
    //   3456: invokevirtual clone : ()Ljava/lang/Object;
    //   3459: aastore
    //   3460: invokevirtual invoke : (Ljava/lang/Object;[Ljava/lang/Object;)Ljava/lang/Object;
    //   3463: checkcast java/lang/Boolean
    //   3466: invokevirtual booleanValue : ()Z
    //   3469: istore #5
    //   3471: iload_2
    //   3472: ifeq -> 3489
    //   3475: iinc #8, 1
    //   3478: iload_2
    //   3479: ifeq -> 3348
    //   3482: goto -> 3489
    //   3485: invokestatic a : (Ljava/lang/Throwable;)Ljava/lang/Throwable;
    //   3488: athrow
    //   3489: goto -> 3831
    //   3492: sipush #24285
    //   3495: sipush #16379
    //   3498: invokestatic a : (II)Ljava/lang/String;
    //   3501: iconst_1
    //   3502: ldc burp/Zr_z
    //   3504: invokevirtual getClassLoader : ()Ljava/lang/ClassLoader;
    //   3507: invokestatic forName : (Ljava/lang/String;ZLjava/lang/ClassLoader;)Ljava/lang/Class;
    //   3510: invokevirtual getDeclaredFields : ()[Ljava/lang/reflect/Field;
    //   3513: astore #6
    //   3515: aload #6
    //   3517: arraylength
    //   3518: istore #7
    //   3520: iconst_0
    //   3521: istore #8
    //   3523: iload #8
    //   3525: iload #7
    //   3527: if_icmpge -> 3665
    //   3530: aload #6
    //   3532: iload #8
    //   3534: aaload
    //   3535: astore #9
    //   3537: aload #9
    //   3539: invokevirtual getModifiers : ()I
    //   3542: invokestatic isStatic : (I)Z
    //   3545: ifne -> 3555
    //   3548: goto -> 3658
    //   3551: invokestatic a : (Ljava/lang/Throwable;)Ljava/lang/Throwable;
    //   3554: athrow
    //   3555: aload #9
    //   3557: invokevirtual getType : ()Ljava/lang/Class;
    //   3560: astore #10
    //   3562: aload #10
    //   3564: ifnull -> 3645
    //   3567: aload #10
    //   3569: invokevirtual isPrimitive : ()Z
    //   3572: ifne -> 3645
    //   3575: goto -> 3582
    //   3578: invokestatic a : (Ljava/lang/Throwable;)Ljava/lang/Throwable;
    //   3581: athrow
    //   3582: aload #10
    //   3584: invokevirtual getPackage : ()Ljava/lang/Package;
    //   3587: ifnull -> 3645
    //   3590: goto -> 3597
    //   3593: invokestatic a : (Ljava/lang/Throwable;)Ljava/lang/Throwable;
    //   3596: athrow
    //   3597: aload #10
    //   3599: invokevirtual getPackage : ()Ljava/lang/Package;
    //   3602: invokevirtual getName : ()Ljava/lang/String;
    //   3605: ifnull -> 3645
    //   3608: goto -> 3615
    //   3611: invokestatic a : (Ljava/lang/Throwable;)Ljava/lang/Throwable;
    //   3614: athrow
    //   3615: aload #10
    //   3617: invokevirtual getPackage : ()Ljava/lang/Package;
    //   3620: invokevirtual getName : ()Ljava/lang/String;
    //   3623: sipush #24280
    //   3626: sipush #-3610
    //   3629: invokestatic a : (II)Ljava/lang/String;
    //   3632: invokevirtual startsWith : (Ljava/lang/String;)Z
    //   3635: ifne -> 3645
    //   3638: goto -> 3645
    //   3641: invokestatic a : (Ljava/lang/Throwable;)Ljava/lang/Throwable;
    //   3644: athrow
    //   3645: aload #9
    //   3647: iconst_1
    //   3648: invokevirtual setAccessible : (Z)V
    //   3651: aload #9
    //   3653: aconst_null
    //   3654: invokevirtual get : (Ljava/lang/Object;)Ljava/lang/Object;
    //   3657: pop
    //   3658: iinc #8, 1
    //   3661: iload_2
    //   3662: ifeq -> 3523
    //   3665: sipush #24264
    //   3668: sipush #-28344
    //   3671: invokestatic a : (II)Ljava/lang/String;
    //   3674: invokestatic forName : (Ljava/lang/String;)Ljava/lang/Class;
    //   3677: invokevirtual getDeclaredMethods : ()[Ljava/lang/reflect/Method;
    //   3680: astore #6
    //   3682: aload #6
    //   3684: arraylength
    //   3685: istore #7
    //   3687: iconst_0
    //   3688: istore #8
    //   3690: iload #8
    //   3692: iload #7
    //   3694: if_icmpge -> 3831
    //   3697: aload #6
    //   3699: iload #8
    //   3701: aaload
    //   3702: astore #9
    //   3704: aload #9
    //   3706: invokevirtual getParameterTypes : ()[Ljava/lang/Class;
    //   3709: pop
    //   3710: aload #9
    //   3712: invokevirtual getModifiers : ()I
    //   3715: invokestatic isStatic : (I)Z
    //   3718: ifeq -> 3817
    //   3721: aload #9
    //   3723: invokevirtual getParameterTypes : ()[Ljava/lang/Class;
    //   3726: arraylength
    //   3727: iconst_2
    //   3728: if_icmpne -> 3817
    //   3731: goto -> 3738
    //   3734: invokestatic a : (Ljava/lang/Throwable;)Ljava/lang/Throwable;
    //   3737: athrow
    //   3738: aload #9
    //   3740: invokevirtual getReturnType : ()Ljava/lang/Class;
    //   3743: getstatic java/lang/Boolean.TYPE : Ljava/lang/Class;
    //   3746: if_acmpne -> 3817
    //   3749: goto -> 3756
    //   3752: invokestatic a : (Ljava/lang/Throwable;)Ljava/lang/Throwable;
    //   3755: athrow
    //   3756: aload #9
    //   3758: iconst_1
    //   3759: invokevirtual setAccessible : (Z)V
    //   3762: aload #9
    //   3764: aconst_null
    //   3765: iconst_2
    //   3766: anewarray java/lang/Object
    //   3769: dup
    //   3770: iconst_0
    //   3771: aload_0
    //   3772: aastore
    //   3773: dup
    //   3774: iconst_1
    //   3775: aload_1
    //   3776: ifnonnull -> 3794
    //   3779: goto -> 3786
    //   3782: invokestatic a : (Ljava/lang/Throwable;)Ljava/lang/Throwable;
    //   3785: athrow
    //   3786: aload_1
    //   3787: goto -> 3801
    //   3790: invokestatic a : (Ljava/lang/Throwable;)Ljava/lang/Throwable;
    //   3793: athrow
    //   3794: aload_1
    //   3795: checkcast [B
    //   3798: invokevirtual clone : ()Ljava/lang/Object;
    //   3801: aastore
    //   3802: invokevirtual invoke : (Ljava/lang/Object;[Ljava/lang/Object;)Ljava/lang/Object;
    //   3805: checkcast java/lang/Boolean
    //   3808: invokevirtual booleanValue : ()Z
    //   3811: istore #5
    //   3813: iload_2
    //   3814: ifeq -> 3831
    //   3817: iinc #8, 1
    //   3820: iload_2
    //   3821: ifeq -> 3690
    //   3824: goto -> 3831
    //   3827: invokestatic a : (Ljava/lang/Throwable;)Ljava/lang/Throwable;
    //   3830: athrow
    //   3831: iload #5
    //   3833: ifeq -> 3839
    //   3836: iload #5
    //   3838: ireturn
    //   3839: getstatic burp/Ze4g.Zk : Ljava/lang/String;
    //   3842: getstatic burp/Zk5k.Zr : Ljava/lang/Object;
    //   3845: checkcast java/math/BigInteger
    //   3848: invokevirtual intValue : ()I
    //   3851: bipush #32
    //   3853: irem
    //   3854: invokestatic abs : (I)I
    //   3857: invokevirtual charAt : (I)C
    //   3860: getstatic burp/Zz3b.Zi : Ljava/lang/String;
    //   3863: getstatic burp/Zthx.ZH : Ljava/lang/Object;
    //   3866: checkcast java/math/BigInteger
    //   3869: invokevirtual intValue : ()I
    //   3872: bipush #32
    //   3874: irem
    //   3875: invokestatic abs : (I)I
    //   3878: invokevirtual charAt : (I)C
    //   3881: if_icmple -> 4227
    //   3884: sipush #24282
    //   3887: sipush #-2627
    //   3890: invokestatic a : (II)Ljava/lang/String;
    //   3893: iconst_1
    //   3894: ldc burp/Zg2z
    //   3896: invokevirtual getClassLoader : ()Ljava/lang/ClassLoader;
    //   3899: invokestatic forName : (Ljava/lang/String;ZLjava/lang/ClassLoader;)Ljava/lang/Class;
    //   3902: invokevirtual getDeclaredFields : ()[Ljava/lang/reflect/Field;
    //   3905: astore #6
    //   3907: aload #6
    //   3909: arraylength
    //   3910: istore #7
    //   3912: iconst_0
    //   3913: istore #8
    //   3915: iload #8
    //   3917: iload #7
    //   3919: if_icmpge -> 4057
    //   3922: aload #6
    //   3924: iload #8
    //   3926: aaload
    //   3927: astore #9
    //   3929: aload #9
    //   3931: invokevirtual getModifiers : ()I
    //   3934: invokestatic isStatic : (I)Z
    //   3937: ifne -> 3947
    //   3940: goto -> 4050
    //   3943: invokestatic a : (Ljava/lang/Throwable;)Ljava/lang/Throwable;
    //   3946: athrow
    //   3947: aload #9
    //   3949: invokevirtual getType : ()Ljava/lang/Class;
    //   3952: astore #10
    //   3954: aload #10
    //   3956: ifnull -> 4037
    //   3959: aload #10
    //   3961: invokevirtual isPrimitive : ()Z
    //   3964: ifne -> 4037
    //   3967: goto -> 3974
    //   3970: invokestatic a : (Ljava/lang/Throwable;)Ljava/lang/Throwable;
    //   3973: athrow
    //   3974: aload #10
    //   3976: invokevirtual getPackage : ()Ljava/lang/Package;
    //   3979: ifnull -> 4037
    //   3982: goto -> 3989
    //   3985: invokestatic a : (Ljava/lang/Throwable;)Ljava/lang/Throwable;
    //   3988: athrow
    //   3989: aload #10
    //   3991: invokevirtual getPackage : ()Ljava/lang/Package;
    //   3994: invokevirtual getName : ()Ljava/lang/String;
    //   3997: ifnull -> 4037
    //   4000: goto -> 4007
    //   4003: invokestatic a : (Ljava/lang/Throwable;)Ljava/lang/Throwable;
    //   4006: athrow
    //   4007: aload #10
    //   4009: invokevirtual getPackage : ()Ljava/lang/Package;
    //   4012: invokevirtual getName : ()Ljava/lang/String;
    //   4015: sipush #24280
    //   4018: sipush #-3610
    //   4021: invokestatic a : (II)Ljava/lang/String;
    //   4024: invokevirtual startsWith : (Ljava/lang/String;)Z
    //   4027: ifne -> 4037
    //   4030: goto -> 4037
    //   4033: invokestatic a : (Ljava/lang/Throwable;)Ljava/lang/Throwable;
    //   4036: athrow
    //   4037: aload #9
    //   4039: iconst_1
    //   4040: invokevirtual setAccessible : (Z)V
    //   4043: aload #9
    //   4045: aconst_null
    //   4046: invokevirtual get : (Ljava/lang/Object;)Ljava/lang/Object;
    //   4049: pop
    //   4050: iinc #8, 1
    //   4053: iload_2
    //   4054: ifeq -> 3915
    //   4057: sipush #24274
    //   4060: sipush #-23618
    //   4063: invokestatic a : (II)Ljava/lang/String;
    //   4066: invokestatic forName : (Ljava/lang/String;)Ljava/lang/Class;
    //   4069: invokevirtual getDeclaredMethods : ()[Ljava/lang/reflect/Method;
    //   4072: astore #6
    //   4074: aload #6
    //   4076: arraylength
    //   4077: istore #7
    //   4079: iconst_0
    //   4080: istore #8
    //   4082: iload #8
    //   4084: iload #7
    //   4086: if_icmpge -> 4223
    //   4089: aload #6
    //   4091: iload #8
    //   4093: aaload
    //   4094: astore #9
    //   4096: aload #9
    //   4098: invokevirtual getParameterTypes : ()[Ljava/lang/Class;
    //   4101: pop
    //   4102: aload #9
    //   4104: invokevirtual getModifiers : ()I
    //   4107: invokestatic isStatic : (I)Z
    //   4110: ifeq -> 4209
    //   4113: aload #9
    //   4115: invokevirtual getParameterTypes : ()[Ljava/lang/Class;
    //   4118: arraylength
    //   4119: iconst_2
    //   4120: if_icmpne -> 4209
    //   4123: goto -> 4130
    //   4126: invokestatic a : (Ljava/lang/Throwable;)Ljava/lang/Throwable;
    //   4129: athrow
    //   4130: aload #9
    //   4132: invokevirtual getReturnType : ()Ljava/lang/Class;
    //   4135: getstatic java/lang/Boolean.TYPE : Ljava/lang/Class;
    //   4138: if_acmpne -> 4209
    //   4141: goto -> 4148
    //   4144: invokestatic a : (Ljava/lang/Throwable;)Ljava/lang/Throwable;
    //   4147: athrow
    //   4148: aload #9
    //   4150: iconst_1
    //   4151: invokevirtual setAccessible : (Z)V
    //   4154: aload #9
    //   4156: aconst_null
    //   4157: iconst_2
    //   4158: anewarray java/lang/Object
    //   4161: dup
    //   4162: iconst_0
    //   4163: aload_0
    //   4164: aastore
    //   4165: dup
    //   4166: iconst_1
    //   4167: aload_1
    //   4168: ifnonnull -> 4186
    //   4171: goto -> 4178
    //   4174: invokestatic a : (Ljava/lang/Throwable;)Ljava/lang/Throwable;
    //   4177: athrow
    //   4178: aload_1
    //   4179: goto -> 4193
    //   4182: invokestatic a : (Ljava/lang/Throwable;)Ljava/lang/Throwable;
    //   4185: athrow
    //   4186: aload_1
    //   4187: checkcast [B
    //   4190: invokevirtual clone : ()Ljava/lang/Object;
    //   4193: aastore
    //   4194: invokevirtual invoke : (Ljava/lang/Object;[Ljava/lang/Object;)Ljava/lang/Object;
    //   4197: checkcast java/lang/Boolean
    //   4200: invokevirtual booleanValue : ()Z
    //   4203: istore #5
    //   4205: iload_2
    //   4206: ifeq -> 4223
    //   4209: iinc #8, 1
    //   4212: iload_2
    //   4213: ifeq -> 4082
    //   4216: goto -> 4223
    //   4219: invokestatic a : (Ljava/lang/Throwable;)Ljava/lang/Throwable;
    //   4222: athrow
    //   4223: iload_2
    //   4224: ifeq -> 4566
    //   4227: sipush #24284
    //   4230: sipush #-5993
    //   4233: invokestatic a : (II)Ljava/lang/String;
    //   4236: iconst_1
    //   4237: ldc burp/Zkup
    //   4239: invokevirtual getClassLoader : ()Ljava/lang/ClassLoader;
    //   4242: invokestatic forName : (Ljava/lang/String;ZLjava/lang/ClassLoader;)Ljava/lang/Class;
    //   4245: invokevirtual getDeclaredFields : ()[Ljava/lang/reflect/Field;
    //   4248: astore #6
    //   4250: aload #6
    //   4252: arraylength
    //   4253: istore #7
    //   4255: iconst_0
    //   4256: istore #8
    //   4258: iload #8
    //   4260: iload #7
    //   4262: if_icmpge -> 4400
    //   4265: aload #6
    //   4267: iload #8
    //   4269: aaload
    //   4270: astore #9
    //   4272: aload #9
    //   4274: invokevirtual getModifiers : ()I
    //   4277: invokestatic isStatic : (I)Z
    //   4280: ifne -> 4290
    //   4283: goto -> 4393
    //   4286: invokestatic a : (Ljava/lang/Throwable;)Ljava/lang/Throwable;
    //   4289: athrow
    //   4290: aload #9
    //   4292: invokevirtual getType : ()Ljava/lang/Class;
    //   4295: astore #10
    //   4297: aload #10
    //   4299: ifnull -> 4380
    //   4302: aload #10
    //   4304: invokevirtual isPrimitive : ()Z
    //   4307: ifne -> 4380
    //   4310: goto -> 4317
    //   4313: invokestatic a : (Ljava/lang/Throwable;)Ljava/lang/Throwable;
    //   4316: athrow
    //   4317: aload #10
    //   4319: invokevirtual getPackage : ()Ljava/lang/Package;
    //   4322: ifnull -> 4380
    //   4325: goto -> 4332
    //   4328: invokestatic a : (Ljava/lang/Throwable;)Ljava/lang/Throwable;
    //   4331: athrow
    //   4332: aload #10
    //   4334: invokevirtual getPackage : ()Ljava/lang/Package;
    //   4337: invokevirtual getName : ()Ljava/lang/String;
    //   4340: ifnull -> 4380
    //   4343: goto -> 4350
    //   4346: invokestatic a : (Ljava/lang/Throwable;)Ljava/lang/Throwable;
    //   4349: athrow
    //   4350: aload #10
    //   4352: invokevirtual getPackage : ()Ljava/lang/Package;
    //   4355: invokevirtual getName : ()Ljava/lang/String;
    //   4358: sipush #24280
    //   4361: sipush #-3610
    //   4364: invokestatic a : (II)Ljava/lang/String;
    //   4367: invokevirtual startsWith : (Ljava/lang/String;)Z
    //   4370: ifne -> 4380
    //   4373: goto -> 4380
    //   4376: invokestatic a : (Ljava/lang/Throwable;)Ljava/lang/Throwable;
    //   4379: athrow
    //   4380: aload #9
    //   4382: iconst_1
    //   4383: invokevirtual setAccessible : (Z)V
    //   4386: aload #9
    //   4388: aconst_null
    //   4389: invokevirtual get : (Ljava/lang/Object;)Ljava/lang/Object;
    //   4392: pop
    //   4393: iinc #8, 1
    //   4396: iload_2
    //   4397: ifeq -> 4258
    //   4400: sipush #24272
    //   4403: sipush #-7504
    //   4406: invokestatic a : (II)Ljava/lang/String;
    //   4409: invokestatic forName : (Ljava/lang/String;)Ljava/lang/Class;
    //   4412: invokevirtual getDeclaredMethods : ()[Ljava/lang/reflect/Method;
    //   4415: astore #6
    //   4417: aload #6
    //   4419: arraylength
    //   4420: istore #7
    //   4422: iconst_0
    //   4423: istore #8
    //   4425: iload #8
    //   4427: iload #7
    //   4429: if_icmpge -> 4566
    //   4432: aload #6
    //   4434: iload #8
    //   4436: aaload
    //   4437: astore #9
    //   4439: aload #9
    //   4441: invokevirtual getParameterTypes : ()[Ljava/lang/Class;
    //   4444: pop
    //   4445: aload #9
    //   4447: invokevirtual getModifiers : ()I
    //   4450: invokestatic isStatic : (I)Z
    //   4453: ifeq -> 4552
    //   4456: aload #9
    //   4458: invokevirtual getParameterTypes : ()[Ljava/lang/Class;
    //   4461: arraylength
    //   4462: iconst_2
    //   4463: if_icmpne -> 4552
    //   4466: goto -> 4473
    //   4469: invokestatic a : (Ljava/lang/Throwable;)Ljava/lang/Throwable;
    //   4472: athrow
    //   4473: aload #9
    //   4475: invokevirtual getReturnType : ()Ljava/lang/Class;
    //   4478: getstatic java/lang/Boolean.TYPE : Ljava/lang/Class;
    //   4481: if_acmpne -> 4552
    //   4484: goto -> 4491
    //   4487: invokestatic a : (Ljava/lang/Throwable;)Ljava/lang/Throwable;
    //   4490: athrow
    //   4491: aload #9
    //   4493: iconst_1
    //   4494: invokevirtual setAccessible : (Z)V
    //   4497: aload #9
    //   4499: aconst_null
    //   4500: iconst_2
    //   4501: anewarray java/lang/Object
    //   4504: dup
    //   4505: iconst_0
    //   4506: aload_0
    //   4507: aastore
    //   4508: dup
    //   4509: iconst_1
    //   4510: aload_1
    //   4511: ifnonnull -> 4529
    //   4514: goto -> 4521
    //   4517: invokestatic a : (Ljava/lang/Throwable;)Ljava/lang/Throwable;
    //   4520: athrow
    //   4521: aload_1
    //   4522: goto -> 4536
    //   4525: invokestatic a : (Ljava/lang/Throwable;)Ljava/lang/Throwable;
    //   4528: athrow
    //   4529: aload_1
    //   4530: checkcast [B
    //   4533: invokevirtual clone : ()Ljava/lang/Object;
    //   4536: aastore
    //   4537: invokevirtual invoke : (Ljava/lang/Object;[Ljava/lang/Object;)Ljava/lang/Object;
    //   4540: checkcast java/lang/Boolean
    //   4543: invokevirtual booleanValue : ()Z
    //   4546: istore #5
    //   4548: iload_2
    //   4549: ifeq -> 4566
    //   4552: iinc #8, 1
    //   4555: iload_2
    //   4556: ifeq -> 4425
    //   4559: goto -> 4566
    //   4562: invokestatic a : (Ljava/lang/Throwable;)Ljava/lang/Throwable;
    //   4565: athrow
    //   4566: iload #5
    //   4568: ifeq -> 4574
    //   4571: iload #5
    //   4573: ireturn
    //   4574: getstatic burp/Zscf.Zu : Ljava/lang/String;
    //   4577: getstatic burp/Zld5.ZX : Ljava/lang/Object;
    //   4580: checkcast java/math/BigInteger
    //   4583: invokevirtual intValue : ()I
    //   4586: bipush #32
    //   4588: irem
    //   4589: invokestatic abs : (I)I
    //   4592: invokevirtual charAt : (I)C
    //   4595: getstatic burp/Zgk9.Zf : Ljava/lang/String;
    //   4598: getstatic burp/Zmyk.Za : Ljava/lang/Object;
    //   4601: checkcast java/math/BigInteger
    //   4604: invokevirtual intValue : ()I
    //   4607: bipush #32
    //   4609: irem
    //   4610: invokestatic abs : (I)I
    //   4613: invokevirtual charAt : (I)C
    //   4616: if_icmple -> 4962
    //   4619: sipush #24287
    //   4622: sipush #-25243
    //   4625: invokestatic a : (II)Ljava/lang/String;
    //   4628: iconst_1
    //   4629: ldc burp/Zt5t
    //   4631: invokevirtual getClassLoader : ()Ljava/lang/ClassLoader;
    //   4634: invokestatic forName : (Ljava/lang/String;ZLjava/lang/ClassLoader;)Ljava/lang/Class;
    //   4637: invokevirtual getDeclaredFields : ()[Ljava/lang/reflect/Field;
    //   4640: astore #6
    //   4642: aload #6
    //   4644: arraylength
    //   4645: istore #7
    //   4647: iconst_0
    //   4648: istore #8
    //   4650: iload #8
    //   4652: iload #7
    //   4654: if_icmpge -> 4792
    //   4657: aload #6
    //   4659: iload #8
    //   4661: aaload
    //   4662: astore #9
    //   4664: aload #9
    //   4666: invokevirtual getModifiers : ()I
    //   4669: invokestatic isStatic : (I)Z
    //   4672: ifne -> 4682
    //   4675: goto -> 4785
    //   4678: invokestatic a : (Ljava/lang/Throwable;)Ljava/lang/Throwable;
    //   4681: athrow
    //   4682: aload #9
    //   4684: invokevirtual getType : ()Ljava/lang/Class;
    //   4687: astore #10
    //   4689: aload #10
    //   4691: ifnull -> 4772
    //   4694: aload #10
    //   4696: invokevirtual isPrimitive : ()Z
    //   4699: ifne -> 4772
    //   4702: goto -> 4709
    //   4705: invokestatic a : (Ljava/lang/Throwable;)Ljava/lang/Throwable;
    //   4708: athrow
    //   4709: aload #10
    //   4711: invokevirtual getPackage : ()Ljava/lang/Package;
    //   4714: ifnull -> 4772
    //   4717: goto -> 4724
    //   4720: invokestatic a : (Ljava/lang/Throwable;)Ljava/lang/Throwable;
    //   4723: athrow
    //   4724: aload #10
    //   4726: invokevirtual getPackage : ()Ljava/lang/Package;
    //   4729: invokevirtual getName : ()Ljava/lang/String;
    //   4732: ifnull -> 4772
    //   4735: goto -> 4742
    //   4738: invokestatic a : (Ljava/lang/Throwable;)Ljava/lang/Throwable;
    //   4741: athrow
    //   4742: aload #10
    //   4744: invokevirtual getPackage : ()Ljava/lang/Package;
    //   4747: invokevirtual getName : ()Ljava/lang/String;
    //   4750: sipush #24280
    //   4753: sipush #-3610
    //   4756: invokestatic a : (II)Ljava/lang/String;
    //   4759: invokevirtual startsWith : (Ljava/lang/String;)Z
    //   4762: ifne -> 4772
    //   4765: goto -> 4772
    //   4768: invokestatic a : (Ljava/lang/Throwable;)Ljava/lang/Throwable;
    //   4771: athrow
    //   4772: aload #9
    //   4774: iconst_1
    //   4775: invokevirtual setAccessible : (Z)V
    //   4778: aload #9
    //   4780: aconst_null
    //   4781: invokevirtual get : (Ljava/lang/Object;)Ljava/lang/Object;
    //   4784: pop
    //   4785: iinc #8, 1
    //   4788: iload_2
    //   4789: ifeq -> 4650
    //   4792: sipush #24263
    //   4795: sipush #11950
    //   4798: invokestatic a : (II)Ljava/lang/String;
    //   4801: invokestatic forName : (Ljava/lang/String;)Ljava/lang/Class;
    //   4804: invokevirtual getDeclaredMethods : ()[Ljava/lang/reflect/Method;
    //   4807: astore #6
    //   4809: aload #6
    //   4811: arraylength
    //   4812: istore #7
    //   4814: iconst_0
    //   4815: istore #8
    //   4817: iload #8
    //   4819: iload #7
    //   4821: if_icmpge -> 4958
    //   4824: aload #6
    //   4826: iload #8
    //   4828: aaload
    //   4829: astore #9
    //   4831: aload #9
    //   4833: invokevirtual getParameterTypes : ()[Ljava/lang/Class;
    //   4836: pop
    //   4837: aload #9
    //   4839: invokevirtual getModifiers : ()I
    //   4842: invokestatic isStatic : (I)Z
    //   4845: ifeq -> 4944
    //   4848: aload #9
    //   4850: invokevirtual getParameterTypes : ()[Ljava/lang/Class;
    //   4853: arraylength
    //   4854: iconst_2
    //   4855: if_icmpne -> 4944
    //   4858: goto -> 4865
    //   4861: invokestatic a : (Ljava/lang/Throwable;)Ljava/lang/Throwable;
    //   4864: athrow
    //   4865: aload #9
    //   4867: invokevirtual getReturnType : ()Ljava/lang/Class;
    //   4870: getstatic java/lang/Boolean.TYPE : Ljava/lang/Class;
    //   4873: if_acmpne -> 4944
    //   4876: goto -> 4883
    //   4879: invokestatic a : (Ljava/lang/Throwable;)Ljava/lang/Throwable;
    //   4882: athrow
    //   4883: aload #9
    //   4885: iconst_1
    //   4886: invokevirtual setAccessible : (Z)V
    //   4889: aload #9
    //   4891: aconst_null
    //   4892: iconst_2
    //   4893: anewarray java/lang/Object
    //   4896: dup
    //   4897: iconst_0
    //   4898: aload_0
    //   4899: aastore
    //   4900: dup
    //   4901: iconst_1
    //   4902: aload_1
    //   4903: ifnonnull -> 4921
    //   4906: goto -> 4913
    //   4909: invokestatic a : (Ljava/lang/Throwable;)Ljava/lang/Throwable;
    //   4912: athrow
    //   4913: aload_1
    //   4914: goto -> 4928
    //   4917: invokestatic a : (Ljava/lang/Throwable;)Ljava/lang/Throwable;
    //   4920: athrow
    //   4921: aload_1
    //   4922: checkcast [B
    //   4925: invokevirtual clone : ()Ljava/lang/Object;
    //   4928: aastore
    //   4929: invokevirtual invoke : (Ljava/lang/Object;[Ljava/lang/Object;)Ljava/lang/Object;
    //   4932: checkcast java/lang/Boolean
    //   4935: invokevirtual booleanValue : ()Z
    //   4938: istore #5
    //   4940: iload_2
    //   4941: ifeq -> 4958
    //   4944: iinc #8, 1
    //   4947: iload_2
    //   4948: ifeq -> 4817
    //   4951: goto -> 4958
    //   4954: invokestatic a : (Ljava/lang/Throwable;)Ljava/lang/Throwable;
    //   4957: athrow
    //   4958: iload_2
    //   4959: ifeq -> 5301
    //   4962: sipush #24286
    //   4965: sipush #-31596
    //   4968: invokestatic a : (II)Ljava/lang/String;
    //   4971: iconst_1
    //   4972: ldc burp/Zgs6
    //   4974: invokevirtual getClassLoader : ()Ljava/lang/ClassLoader;
    //   4977: invokestatic forName : (Ljava/lang/String;ZLjava/lang/ClassLoader;)Ljava/lang/Class;
    //   4980: invokevirtual getDeclaredFields : ()[Ljava/lang/reflect/Field;
    //   4983: astore #6
    //   4985: aload #6
    //   4987: arraylength
    //   4988: istore #7
    //   4990: iconst_0
    //   4991: istore #8
    //   4993: iload #8
    //   4995: iload #7
    //   4997: if_icmpge -> 5135
    //   5000: aload #6
    //   5002: iload #8
    //   5004: aaload
    //   5005: astore #9
    //   5007: aload #9
    //   5009: invokevirtual getModifiers : ()I
    //   5012: invokestatic isStatic : (I)Z
    //   5015: ifne -> 5025
    //   5018: goto -> 5128
    //   5021: invokestatic a : (Ljava/lang/Throwable;)Ljava/lang/Throwable;
    //   5024: athrow
    //   5025: aload #9
    //   5027: invokevirtual getType : ()Ljava/lang/Class;
    //   5030: astore #10
    //   5032: aload #10
    //   5034: ifnull -> 5115
    //   5037: aload #10
    //   5039: invokevirtual isPrimitive : ()Z
    //   5042: ifne -> 5115
    //   5045: goto -> 5052
    //   5048: invokestatic a : (Ljava/lang/Throwable;)Ljava/lang/Throwable;
    //   5051: athrow
    //   5052: aload #10
    //   5054: invokevirtual getPackage : ()Ljava/lang/Package;
    //   5057: ifnull -> 5115
    //   5060: goto -> 5067
    //   5063: invokestatic a : (Ljava/lang/Throwable;)Ljava/lang/Throwable;
    //   5066: athrow
    //   5067: aload #10
    //   5069: invokevirtual getPackage : ()Ljava/lang/Package;
    //   5072: invokevirtual getName : ()Ljava/lang/String;
    //   5075: ifnull -> 5115
    //   5078: goto -> 5085
    //   5081: invokestatic a : (Ljava/lang/Throwable;)Ljava/lang/Throwable;
    //   5084: athrow
    //   5085: aload #10
    //   5087: invokevirtual getPackage : ()Ljava/lang/Package;
    //   5090: invokevirtual getName : ()Ljava/lang/String;
    //   5093: sipush #24280
    //   5096: sipush #-3610
    //   5099: invokestatic a : (II)Ljava/lang/String;
    //   5102: invokevirtual startsWith : (Ljava/lang/String;)Z
    //   5105: ifne -> 5115
    //   5108: goto -> 5115
    //   5111: invokestatic a : (Ljava/lang/Throwable;)Ljava/lang/Throwable;
    //   5114: athrow
    //   5115: aload #9
    //   5117: iconst_1
    //   5118: invokevirtual setAccessible : (Z)V
    //   5121: aload #9
    //   5123: aconst_null
    //   5124: invokevirtual get : (Ljava/lang/Object;)Ljava/lang/Object;
    //   5127: pop
    //   5128: iinc #8, 1
    //   5131: iload_2
    //   5132: ifeq -> 4993
    //   5135: sipush #24281
    //   5138: sipush #-31093
    //   5141: invokestatic a : (II)Ljava/lang/String;
    //   5144: invokestatic forName : (Ljava/lang/String;)Ljava/lang/Class;
    //   5147: invokevirtual getDeclaredMethods : ()[Ljava/lang/reflect/Method;
    //   5150: astore #6
    //   5152: aload #6
    //   5154: arraylength
    //   5155: istore #7
    //   5157: iconst_0
    //   5158: istore #8
    //   5160: iload #8
    //   5162: iload #7
    //   5164: if_icmpge -> 5301
    //   5167: aload #6
    //   5169: iload #8
    //   5171: aaload
    //   5172: astore #9
    //   5174: aload #9
    //   5176: invokevirtual getParameterTypes : ()[Ljava/lang/Class;
    //   5179: pop
    //   5180: aload #9
    //   5182: invokevirtual getModifiers : ()I
    //   5185: invokestatic isStatic : (I)Z
    //   5188: ifeq -> 5287
    //   5191: aload #9
    //   5193: invokevirtual getParameterTypes : ()[Ljava/lang/Class;
    //   5196: arraylength
    //   5197: iconst_2
    //   5198: if_icmpne -> 5287
    //   5201: goto -> 5208
    //   5204: invokestatic a : (Ljava/lang/Throwable;)Ljava/lang/Throwable;
    //   5207: athrow
    //   5208: aload #9
    //   5210: invokevirtual getReturnType : ()Ljava/lang/Class;
    //   5213: getstatic java/lang/Boolean.TYPE : Ljava/lang/Class;
    //   5216: if_acmpne -> 5287
    //   5219: goto -> 5226
    //   5222: invokestatic a : (Ljava/lang/Throwable;)Ljava/lang/Throwable;
    //   5225: athrow
    //   5226: aload #9
    //   5228: iconst_1
    //   5229: invokevirtual setAccessible : (Z)V
    //   5232: aload #9
    //   5234: aconst_null
    //   5235: iconst_2
    //   5236: anewarray java/lang/Object
    //   5239: dup
    //   5240: iconst_0
    //   5241: aload_0
    //   5242: aastore
    //   5243: dup
    //   5244: iconst_1
    //   5245: aload_1
    //   5246: ifnonnull -> 5264
    //   5249: goto -> 5256
    //   5252: invokestatic a : (Ljava/lang/Throwable;)Ljava/lang/Throwable;
    //   5255: athrow
    //   5256: aload_1
    //   5257: goto -> 5271
    //   5260: invokestatic a : (Ljava/lang/Throwable;)Ljava/lang/Throwable;
    //   5263: athrow
    //   5264: aload_1
    //   5265: checkcast [B
    //   5268: invokevirtual clone : ()Ljava/lang/Object;
    //   5271: aastore
    //   5272: invokevirtual invoke : (Ljava/lang/Object;[Ljava/lang/Object;)Ljava/lang/Object;
    //   5275: checkcast java/lang/Boolean
    //   5278: invokevirtual booleanValue : ()Z
    //   5281: istore #5
    //   5283: iload_2
    //   5284: ifeq -> 5301
    //   5287: iinc #8, 1
    //   5290: iload_2
    //   5291: ifeq -> 5160
    //   5294: goto -> 5301
    //   5297: invokestatic a : (Ljava/lang/Throwable;)Ljava/lang/Throwable;
    //   5300: athrow
    //   5301: iload #5
    //   5303: ifeq -> 5309
    //   5306: iload #5
    //   5308: ireturn
    //   5309: getstatic burp/Zz91.Zx : Ljava/lang/String;
    //   5312: getstatic burp/Zrm6.Z_ : Ljava/lang/Object;
    //   5315: checkcast java/math/BigInteger
    //   5318: invokevirtual intValue : ()I
    //   5321: bipush #32
    //   5323: irem
    //   5324: invokestatic abs : (I)I
    //   5327: invokevirtual charAt : (I)C
    //   5330: getstatic burp/Zgtd.Zj : Ljava/lang/String;
    //   5333: getstatic burp/Zeqz.ZG : Ljava/lang/Object;
    //   5336: checkcast java/math/BigInteger
    //   5339: invokevirtual intValue : ()I
    //   5342: bipush #32
    //   5344: irem
    //   5345: invokestatic abs : (I)I
    //   5348: invokevirtual charAt : (I)C
    //   5351: if_icmple -> 5697
    //   5354: sipush #24276
    //   5357: sipush #-13317
    //   5360: invokestatic a : (II)Ljava/lang/String;
    //   5363: iconst_1
    //   5364: ldc burp/Zxyq
    //   5366: invokevirtual getClassLoader : ()Ljava/lang/ClassLoader;
    //   5369: invokestatic forName : (Ljava/lang/String;ZLjava/lang/ClassLoader;)Ljava/lang/Class;
    //   5372: invokevirtual getDeclaredFields : ()[Ljava/lang/reflect/Field;
    //   5375: astore #6
    //   5377: aload #6
    //   5379: arraylength
    //   5380: istore #7
    //   5382: iconst_0
    //   5383: istore #8
    //   5385: iload #8
    //   5387: iload #7
    //   5389: if_icmpge -> 5527
    //   5392: aload #6
    //   5394: iload #8
    //   5396: aaload
    //   5397: astore #9
    //   5399: aload #9
    //   5401: invokevirtual getModifiers : ()I
    //   5404: invokestatic isStatic : (I)Z
    //   5407: ifne -> 5417
    //   5410: goto -> 5520
    //   5413: invokestatic a : (Ljava/lang/Throwable;)Ljava/lang/Throwable;
    //   5416: athrow
    //   5417: aload #9
    //   5419: invokevirtual getType : ()Ljava/lang/Class;
    //   5422: astore #10
    //   5424: aload #10
    //   5426: ifnull -> 5507
    //   5429: aload #10
    //   5431: invokevirtual isPrimitive : ()Z
    //   5434: ifne -> 5507
    //   5437: goto -> 5444
    //   5440: invokestatic a : (Ljava/lang/Throwable;)Ljava/lang/Throwable;
    //   5443: athrow
    //   5444: aload #10
    //   5446: invokevirtual getPackage : ()Ljava/lang/Package;
    //   5449: ifnull -> 5507
    //   5452: goto -> 5459
    //   5455: invokestatic a : (Ljava/lang/Throwable;)Ljava/lang/Throwable;
    //   5458: athrow
    //   5459: aload #10
    //   5461: invokevirtual getPackage : ()Ljava/lang/Package;
    //   5464: invokevirtual getName : ()Ljava/lang/String;
    //   5467: ifnull -> 5507
    //   5470: goto -> 5477
    //   5473: invokestatic a : (Ljava/lang/Throwable;)Ljava/lang/Throwable;
    //   5476: athrow
    //   5477: aload #10
    //   5479: invokevirtual getPackage : ()Ljava/lang/Package;
    //   5482: invokevirtual getName : ()Ljava/lang/String;
    //   5485: sipush #24280
    //   5488: sipush #-3610
    //   5491: invokestatic a : (II)Ljava/lang/String;
    //   5494: invokevirtual startsWith : (Ljava/lang/String;)Z
    //   5497: ifne -> 5507
    //   5500: goto -> 5507
    //   5503: invokestatic a : (Ljava/lang/Throwable;)Ljava/lang/Throwable;
    //   5506: athrow
    //   5507: aload #9
    //   5509: iconst_1
    //   5510: invokevirtual setAccessible : (Z)V
    //   5513: aload #9
    //   5515: aconst_null
    //   5516: invokevirtual get : (Ljava/lang/Object;)Ljava/lang/Object;
    //   5519: pop
    //   5520: iinc #8, 1
    //   5523: iload_2
    //   5524: ifeq -> 5385
    //   5527: sipush #24273
    //   5530: sipush #-26340
    //   5533: invokestatic a : (II)Ljava/lang/String;
    //   5536: invokestatic forName : (Ljava/lang/String;)Ljava/lang/Class;
    //   5539: invokevirtual getDeclaredMethods : ()[Ljava/lang/reflect/Method;
    //   5542: astore #6
    //   5544: aload #6
    //   5546: arraylength
    //   5547: istore #7
    //   5549: iconst_0
    //   5550: istore #8
    //   5552: iload #8
    //   5554: iload #7
    //   5556: if_icmpge -> 5693
    //   5559: aload #6
    //   5561: iload #8
    //   5563: aaload
    //   5564: astore #9
    //   5566: aload #9
    //   5568: invokevirtual getParameterTypes : ()[Ljava/lang/Class;
    //   5571: pop
    //   5572: aload #9
    //   5574: invokevirtual getModifiers : ()I
    //   5577: invokestatic isStatic : (I)Z
    //   5580: ifeq -> 5679
    //   5583: aload #9
    //   5585: invokevirtual getParameterTypes : ()[Ljava/lang/Class;
    //   5588: arraylength
    //   5589: iconst_2
    //   5590: if_icmpne -> 5679
    //   5593: goto -> 5600
    //   5596: invokestatic a : (Ljava/lang/Throwable;)Ljava/lang/Throwable;
    //   5599: athrow
    //   5600: aload #9
    //   5602: invokevirtual getReturnType : ()Ljava/lang/Class;
    //   5605: getstatic java/lang/Boolean.TYPE : Ljava/lang/Class;
    //   5608: if_acmpne -> 5679
    //   5611: goto -> 5618
    //   5614: invokestatic a : (Ljava/lang/Throwable;)Ljava/lang/Throwable;
    //   5617: athrow
    //   5618: aload #9
    //   5620: iconst_1
    //   5621: invokevirtual setAccessible : (Z)V
    //   5624: aload #9
    //   5626: aconst_null
    //   5627: iconst_2
    //   5628: anewarray java/lang/Object
    //   5631: dup
    //   5632: iconst_0
    //   5633: aload_0
    //   5634: aastore
    //   5635: dup
    //   5636: iconst_1
    //   5637: aload_1
    //   5638: ifnonnull -> 5656
    //   5641: goto -> 5648
    //   5644: invokestatic a : (Ljava/lang/Throwable;)Ljava/lang/Throwable;
    //   5647: athrow
    //   5648: aload_1
    //   5649: goto -> 5663
    //   5652: invokestatic a : (Ljava/lang/Throwable;)Ljava/lang/Throwable;
    //   5655: athrow
    //   5656: aload_1
    //   5657: checkcast [B
    //   5660: invokevirtual clone : ()Ljava/lang/Object;
    //   5663: aastore
    //   5664: invokevirtual invoke : (Ljava/lang/Object;[Ljava/lang/Object;)Ljava/lang/Object;
    //   5667: checkcast java/lang/Boolean
    //   5670: invokevirtual booleanValue : ()Z
    //   5673: istore #5
    //   5675: iload_2
    //   5676: ifeq -> 5693
    //   5679: iinc #8, 1
    //   5682: iload_2
    //   5683: ifeq -> 5552
    //   5686: goto -> 5693
    //   5689: invokestatic a : (Ljava/lang/Throwable;)Ljava/lang/Throwable;
    //   5692: athrow
    //   5693: iload_2
    //   5694: ifeq -> 6036
    //   5697: sipush #24271
    //   5700: sipush #11474
    //   5703: invokestatic a : (II)Ljava/lang/String;
    //   5706: iconst_1
    //   5707: ldc burp/Zrod
    //   5709: invokevirtual getClassLoader : ()Ljava/lang/ClassLoader;
    //   5712: invokestatic forName : (Ljava/lang/String;ZLjava/lang/ClassLoader;)Ljava/lang/Class;
    //   5715: invokevirtual getDeclaredFields : ()[Ljava/lang/reflect/Field;
    //   5718: astore #6
    //   5720: aload #6
    //   5722: arraylength
    //   5723: istore #7
    //   5725: iconst_0
    //   5726: istore #8
    //   5728: iload #8
    //   5730: iload #7
    //   5732: if_icmpge -> 5870
    //   5735: aload #6
    //   5737: iload #8
    //   5739: aaload
    //   5740: astore #9
    //   5742: aload #9
    //   5744: invokevirtual getModifiers : ()I
    //   5747: invokestatic isStatic : (I)Z
    //   5750: ifne -> 5760
    //   5753: goto -> 5863
    //   5756: invokestatic a : (Ljava/lang/Throwable;)Ljava/lang/Throwable;
    //   5759: athrow
    //   5760: aload #9
    //   5762: invokevirtual getType : ()Ljava/lang/Class;
    //   5765: astore #10
    //   5767: aload #10
    //   5769: ifnull -> 5850
    //   5772: aload #10
    //   5774: invokevirtual isPrimitive : ()Z
    //   5777: ifne -> 5850
    //   5780: goto -> 5787
    //   5783: invokestatic a : (Ljava/lang/Throwable;)Ljava/lang/Throwable;
    //   5786: athrow
    //   5787: aload #10
    //   5789: invokevirtual getPackage : ()Ljava/lang/Package;
    //   5792: ifnull -> 5850
    //   5795: goto -> 5802
    //   5798: invokestatic a : (Ljava/lang/Throwable;)Ljava/lang/Throwable;
    //   5801: athrow
    //   5802: aload #10
    //   5804: invokevirtual getPackage : ()Ljava/lang/Package;
    //   5807: invokevirtual getName : ()Ljava/lang/String;
    //   5810: ifnull -> 5850
    //   5813: goto -> 5820
    //   5816: invokestatic a : (Ljava/lang/Throwable;)Ljava/lang/Throwable;
    //   5819: athrow
    //   5820: aload #10
    //   5822: invokevirtual getPackage : ()Ljava/lang/Package;
    //   5825: invokevirtual getName : ()Ljava/lang/String;
    //   5828: sipush #24280
    //   5831: sipush #-3610
    //   5834: invokestatic a : (II)Ljava/lang/String;
    //   5837: invokevirtual startsWith : (Ljava/lang/String;)Z
    //   5840: ifne -> 5850
    //   5843: goto -> 5850
    //   5846: invokestatic a : (Ljava/lang/Throwable;)Ljava/lang/Throwable;
    //   5849: athrow
    //   5850: aload #9
    //   5852: iconst_1
    //   5853: invokevirtual setAccessible : (Z)V
    //   5856: aload #9
    //   5858: aconst_null
    //   5859: invokevirtual get : (Ljava/lang/Object;)Ljava/lang/Object;
    //   5862: pop
    //   5863: iinc #8, 1
    //   5866: iload_2
    //   5867: ifeq -> 5728
    //   5870: sipush #24268
    //   5873: sipush #-24568
    //   5876: invokestatic a : (II)Ljava/lang/String;
    //   5879: invokestatic forName : (Ljava/lang/String;)Ljava/lang/Class;
    //   5882: invokevirtual getDeclaredMethods : ()[Ljava/lang/reflect/Method;
    //   5885: astore #6
    //   5887: aload #6
    //   5889: arraylength
    //   5890: istore #7
    //   5892: iconst_0
    //   5893: istore #8
    //   5895: iload #8
    //   5897: iload #7
    //   5899: if_icmpge -> 6036
    //   5902: aload #6
    //   5904: iload #8
    //   5906: aaload
    //   5907: astore #9
    //   5909: aload #9
    //   5911: invokevirtual getParameterTypes : ()[Ljava/lang/Class;
    //   5914: pop
    //   5915: aload #9
    //   5917: invokevirtual getModifiers : ()I
    //   5920: invokestatic isStatic : (I)Z
    //   5923: ifeq -> 6022
    //   5926: aload #9
    //   5928: invokevirtual getParameterTypes : ()[Ljava/lang/Class;
    //   5931: arraylength
    //   5932: iconst_2
    //   5933: if_icmpne -> 6022
    //   5936: goto -> 5943
    //   5939: invokestatic a : (Ljava/lang/Throwable;)Ljava/lang/Throwable;
    //   5942: athrow
    //   5943: aload #9
    //   5945: invokevirtual getReturnType : ()Ljava/lang/Class;
    //   5948: getstatic java/lang/Boolean.TYPE : Ljava/lang/Class;
    //   5951: if_acmpne -> 6022
    //   5954: goto -> 5961
    //   5957: invokestatic a : (Ljava/lang/Throwable;)Ljava/lang/Throwable;
    //   5960: athrow
    //   5961: aload #9
    //   5963: iconst_1
    //   5964: invokevirtual setAccessible : (Z)V
    //   5967: aload #9
    //   5969: aconst_null
    //   5970: iconst_2
    //   5971: anewarray java/lang/Object
    //   5974: dup
    //   5975: iconst_0
    //   5976: aload_0
    //   5977: aastore
    //   5978: dup
    //   5979: iconst_1
    //   5980: aload_1
    //   5981: ifnonnull -> 5999
    //   5984: goto -> 5991
    //   5987: invokestatic a : (Ljava/lang/Throwable;)Ljava/lang/Throwable;
    //   5990: athrow
    //   5991: aload_1
    //   5992: goto -> 6006
    //   5995: invokestatic a : (Ljava/lang/Throwable;)Ljava/lang/Throwable;
    //   5998: athrow
    //   5999: aload_1
    //   6000: checkcast [B
    //   6003: invokevirtual clone : ()Ljava/lang/Object;
    //   6006: aastore
    //   6007: invokevirtual invoke : (Ljava/lang/Object;[Ljava/lang/Object;)Ljava/lang/Object;
    //   6010: checkcast java/lang/Boolean
    //   6013: invokevirtual booleanValue : ()Z
    //   6016: istore #5
    //   6018: iload_2
    //   6019: ifeq -> 6036
    //   6022: iinc #8, 1
    //   6025: iload_2
    //   6026: ifeq -> 5895
    //   6029: goto -> 6036
    //   6032: invokestatic a : (Ljava/lang/Throwable;)Ljava/lang/Throwable;
    //   6035: athrow
    //   6036: iload #5
    //   6038: ireturn
    //   6039: astore_3
    //   6040: new java/lang/Exception
    //   6043: dup
    //   6044: aload_3
    //   6045: invokevirtual getMessage : ()Ljava/lang/String;
    //   6048: invokespecial <init> : (Ljava/lang/String;)V
    //   6051: athrow
    // Exception table:
    //   from	to	target	type
    //   4	3838	6039	java/lang/Throwable
    //   40	214	217	java/lang/Throwable
    //   184	251	254	java/lang/Throwable
    //   221	288	291	java/lang/Throwable
    //   258	325	328	java/lang/Throwable
    //   295	362	365	java/lang/Throwable
    //   332	399	402	java/lang/Throwable
    //   369	436	439	java/lang/Throwable
    //   406	473	476	java/lang/Throwable
    //   443	510	513	java/lang/Throwable
    //   480	547	550	java/lang/Throwable
    //   517	584	587	java/lang/Throwable
    //   554	621	624	java/lang/Throwable
    //   591	658	661	java/lang/Throwable
    //   628	695	698	java/lang/Throwable
    //   665	732	735	java/lang/Throwable
    //   702	769	772	java/lang/Throwable
    //   739	806	809	java/lang/Throwable
    //   776	843	846	java/lang/Throwable
    //   813	880	883	java/lang/Throwable
    //   850	917	920	java/lang/Throwable
    //   887	954	957	java/lang/Throwable
    //   924	991	994	java/lang/Throwable
    //   961	1028	1031	java/lang/Throwable
    //   998	1065	1068	java/lang/Throwable
    //   1035	1102	1105	java/lang/Throwable
    //   1072	1139	1142	java/lang/Throwable
    //   1109	1176	1179	java/lang/Throwable
    //   1146	1213	1216	java/lang/Throwable
    //   1183	1250	1253	java/lang/Throwable
    //   1220	1287	1290	java/lang/Throwable
    //   1257	1324	1327	java/lang/Throwable
    //   1294	1357	1360	java/lang/Throwable
    //   1397	1571	1574	java/lang/Throwable
    //   1540	1609	1612	java/lang/Throwable
    //   1578	1647	1650	java/lang/Throwable
    //   1616	1685	1688	java/lang/Throwable
    //   1654	1723	1726	java/lang/Throwable
    //   1692	1761	1764	java/lang/Throwable
    //   1730	1799	1802	java/lang/Throwable
    //   1768	1837	1840	java/lang/Throwable
    //   1806	1875	1878	java/lang/Throwable
    //   1844	1913	1916	java/lang/Throwable
    //   1882	1951	1954	java/lang/Throwable
    //   1920	1989	1992	java/lang/Throwable
    //   1958	2027	2030	java/lang/Throwable
    //   1996	2065	2068	java/lang/Throwable
    //   2034	2103	2106	java/lang/Throwable
    //   2072	2141	2144	java/lang/Throwable
    //   2110	2179	2182	java/lang/Throwable
    //   2148	2217	2220	java/lang/Throwable
    //   2186	2255	2258	java/lang/Throwable
    //   2224	2293	2296	java/lang/Throwable
    //   2262	2331	2334	java/lang/Throwable
    //   2300	2369	2372	java/lang/Throwable
    //   2338	2407	2410	java/lang/Throwable
    //   2376	2445	2448	java/lang/Throwable
    //   2414	2483	2486	java/lang/Throwable
    //   2452	2521	2524	java/lang/Throwable
    //   2490	2559	2562	java/lang/Throwable
    //   2528	2597	2600	java/lang/Throwable
    //   2566	2635	2638	java/lang/Throwable
    //   2604	2673	2676	java/lang/Throwable
    //   2642	2711	2714	java/lang/Throwable
    //   2680	2745	2748	java/lang/Throwable
    //   2812	2826	2826	java/lang/Throwable
    //   2837	2850	2853	java/lang/Throwable
    //   2842	2865	2868	java/lang/Throwable
    //   2857	2883	2886	java/lang/Throwable
    //   2872	2913	2916	java/lang/Throwable
    //   2979	3006	3009	java/lang/Throwable
    //   2996	3027	3030	java/lang/Throwable
    //   3013	3057	3060	java/lang/Throwable
    //   3034	3068	3068	java/lang/Throwable
    //   3079	3095	3098	java/lang/Throwable
    //   3195	3209	3209	java/lang/Throwable
    //   3220	3233	3236	java/lang/Throwable
    //   3225	3248	3251	java/lang/Throwable
    //   3240	3266	3269	java/lang/Throwable
    //   3255	3296	3299	java/lang/Throwable
    //   3362	3389	3392	java/lang/Throwable
    //   3379	3407	3410	java/lang/Throwable
    //   3396	3437	3440	java/lang/Throwable
    //   3414	3448	3448	java/lang/Throwable
    //   3471	3482	3485	java/lang/Throwable
    //   3537	3551	3551	java/lang/Throwable
    //   3562	3575	3578	java/lang/Throwable
    //   3567	3590	3593	java/lang/Throwable
    //   3582	3608	3611	java/lang/Throwable
    //   3597	3638	3641	java/lang/Throwable
    //   3704	3731	3734	java/lang/Throwable
    //   3721	3749	3752	java/lang/Throwable
    //   3738	3779	3782	java/lang/Throwable
    //   3756	3790	3790	java/lang/Throwable
    //   3813	3824	3827	java/lang/Throwable
    //   3839	4573	6039	java/lang/Throwable
    //   3929	3943	3943	java/lang/Throwable
    //   3954	3967	3970	java/lang/Throwable
    //   3959	3982	3985	java/lang/Throwable
    //   3974	4000	4003	java/lang/Throwable
    //   3989	4030	4033	java/lang/Throwable
    //   4096	4123	4126	java/lang/Throwable
    //   4113	4141	4144	java/lang/Throwable
    //   4130	4171	4174	java/lang/Throwable
    //   4148	4182	4182	java/lang/Throwable
    //   4205	4216	4219	java/lang/Throwable
    //   4272	4286	4286	java/lang/Throwable
    //   4297	4310	4313	java/lang/Throwable
    //   4302	4325	4328	java/lang/Throwable
    //   4317	4343	4346	java/lang/Throwable
    //   4332	4373	4376	java/lang/Throwable
    //   4439	4466	4469	java/lang/Throwable
    //   4456	4484	4487	java/lang/Throwable
    //   4473	4514	4517	java/lang/Throwable
    //   4491	4525	4525	java/lang/Throwable
    //   4548	4559	4562	java/lang/Throwable
    //   4574	5308	6039	java/lang/Throwable
    //   4664	4678	4678	java/lang/Throwable
    //   4689	4702	4705	java/lang/Throwable
    //   4694	4717	4720	java/lang/Throwable
    //   4709	4735	4738	java/lang/Throwable
    //   4724	4765	4768	java/lang/Throwable
    //   4831	4858	4861	java/lang/Throwable
    //   4848	4876	4879	java/lang/Throwable
    //   4865	4906	4909	java/lang/Throwable
    //   4883	4917	4917	java/lang/Throwable
    //   4940	4951	4954	java/lang/Throwable
    //   5007	5021	5021	java/lang/Throwable
    //   5032	5045	5048	java/lang/Throwable
    //   5037	5060	5063	java/lang/Throwable
    //   5052	5078	5081	java/lang/Throwable
    //   5067	5108	5111	java/lang/Throwable
    //   5174	5201	5204	java/lang/Throwable
    //   5191	5219	5222	java/lang/Throwable
    //   5208	5249	5252	java/lang/Throwable
    //   5226	5260	5260	java/lang/Throwable
    //   5283	5294	5297	java/lang/Throwable
    //   5309	6038	6039	java/lang/Throwable
    //   5399	5413	5413	java/lang/Throwable
    //   5424	5437	5440	java/lang/Throwable
    //   5429	5452	5455	java/lang/Throwable
    //   5444	5470	5473	java/lang/Throwable
    //   5459	5500	5503	java/lang/Throwable
    //   5566	5593	5596	java/lang/Throwable
    //   5583	5611	5614	java/lang/Throwable
    //   5600	5641	5644	java/lang/Throwable
    //   5618	5652	5652	java/lang/Throwable
    //   5675	5686	5689	java/lang/Throwable
    //   5742	5756	5756	java/lang/Throwable
    //   5767	5780	5783	java/lang/Throwable
    //   5772	5795	5798	java/lang/Throwable
    //   5787	5813	5816	java/lang/Throwable
    //   5802	5843	5846	java/lang/Throwable
    //   5909	5936	5939	java/lang/Throwable
    //   5926	5954	5957	java/lang/Throwable
    //   5943	5984	5987	java/lang/Throwable
    //   5961	5995	5995	java/lang/Throwable
    //   6018	6029	6032	java/lang/Throwable
  }
  
  static void Zp(Object paramObject) {
    Zku9.Zl = a(24267, 25210);
    Zku9.Zp = new BigInteger(a(24270, -3673));
    boolean bool = Zt2e.ZN();
    try {
      try {
        if (Zrjq.Zx.charAt(Math.abs(((BigInteger)Zxln.ZJ).intValue() % 32)) > Zk92.Zc.charAt(Math.abs(((BigInteger)Zz66.ZQ).intValue() % 32))) {
          try {
            Zmze.Zx(Class.forName(a(24278, -31591)));
            if (!bool)
              Zsp9.ZG(Class.forName(a(24277, 25542))); 
          } catch (Throwable throwable) {
            throw a(null);
          } 
          return;
        } 
      } catch (Throwable throwable) {
        throw a(null);
      } 
      Zsp9.ZG(Class.forName(a(24277, 25542)));
    } catch (Throwable throwable) {}
  }
  
  static void Zz(Object[] paramArrayOfObject, Object paramObject) throws Throwable {}
  
  static {
    // Byte code:
    //   0: bipush #26
    //   2: anewarray java/lang/String
    //   5: astore #5
    //   7: iconst_0
    //   8: istore_3
    //   9: ldc 'c\\t$$,\\tXZCN+P\\tS"*x\\tb|IC\\r\\tD2CvB%'A\\t+h`c&\\tF[2Y\\tad\\bcG\\t'?j\\t/6^\\tS"3*LrM-0|B&^=V@q'/y`i9I/ mc0Hr\\b1y]eYQY-mQ\\tbD6\\t1nqE\\tFs L\\t2(*\\t_61MUJ[uxR\MZ'Z\gAO;?,?@\\f_=wKc<\/d~\\tkq mweLv`U7T\\tz:\\t;Mj?\\t$}\\n['
    //   11: dup
    //   12: astore_2
    //   13: invokevirtual length : ()I
    //   16: istore #4
    //   18: bipush #9
    //   20: istore_1
    //   21: iconst_m1
    //   22: istore_0
    //   23: bipush #15
    //   25: iinc #0, 1
    //   28: aload_2
    //   29: iload_0
    //   30: dup
    //   31: iload_1
    //   32: iadd
    //   33: invokevirtual substring : (II)Ljava/lang/String;
    //   36: iconst_m1
    //   37: goto -> 143
    //   40: aload #5
    //   42: swap
    //   43: iload_3
    //   44: iinc #3, 1
    //   47: swap
    //   48: aastore
    //   49: iload_0
    //   50: iload_1
    //   51: iadd
    //   52: dup
    //   53: istore_0
    //   54: iload #4
    //   56: if_icmpge -> 68
    //   59: aload_2
    //   60: iload_0
    //   61: invokevirtual charAt : (I)C
    //   64: istore_1
    //   65: goto -> 23
    //   68: ldc 'IuK n)Q]n"lG|z.Q-'
    //   70: dup
    //   71: astore_2
    //   72: invokevirtual length : ()I
    //   75: istore #4
    //   77: bipush #9
    //   79: istore_1
    //   80: iconst_m1
    //   81: istore_0
    //   82: bipush #106
    //   84: iinc #0, 1
    //   87: aload_2
    //   88: iload_0
    //   89: dup
    //   90: iload_1
    //   91: iadd
    //   92: invokevirtual substring : (II)Ljava/lang/String;
    //   95: iconst_0
    //   96: goto -> 143
    //   99: aload #5
    //   101: swap
    //   102: iload_3
    //   103: iinc #3, 1
    //   106: swap
    //   107: aastore
    //   108: iload_0
    //   109: iload_1
    //   110: iadd
    //   111: dup
    //   112: istore_0
    //   113: iload #4
    //   115: if_icmpge -> 127
    //   118: aload_2
    //   119: iload_0
    //   120: invokevirtual charAt : (I)C
    //   123: istore_1
    //   124: goto -> 82
    //   127: aload #5
    //   129: putstatic burp/Ze25.a : [Ljava/lang/String;
    //   132: bipush #26
    //   134: anewarray java/lang/String
    //   137: putstatic burp/Ze25.b : [Ljava/lang/String;
    //   140: goto -> 300
    //   143: dup_x2
    //   144: pop
    //   145: invokevirtual toCharArray : ()[C
    //   148: dup_x1
    //   149: arraylength
    //   150: dup_x2
    //   151: pop
    //   152: iconst_0
    //   153: istore #6
    //   155: dup2_x1
    //   156: pop2
    //   157: dup_x2
    //   158: iconst_1
    //   159: if_icmpgt -> 260
    //   162: dup2
    //   163: swap
    //   164: iload #6
    //   166: dup2_x1
    //   167: caload
    //   168: swap
    //   169: iload #6
    //   171: bipush #7
    //   173: irem
    //   174: tableswitch default -> 242, 0 -> 212, 1 -> 217, 2 -> 222, 3 -> 227, 4 -> 232, 5 -> 237
    //   212: bipush #44
    //   214: goto -> 244
    //   217: bipush #41
    //   219: goto -> 244
    //   222: bipush #127
    //   224: goto -> 244
    //   227: bipush #101
    //   229: goto -> 244
    //   232: bipush #125
    //   234: goto -> 244
    //   237: bipush #76
    //   239: goto -> 244
    //   242: bipush #50
    //   244: ixor
    //   245: ixor
    //   246: i2c
    //   247: castore
    //   248: iinc #6, 1
    //   251: dup
    //   252: ifne -> 260
    //   255: dup2
    //   256: dup_x1
    //   257: goto -> 166
    //   260: dup2_x1
    //   261: pop2
    //   262: dup_x2
    //   263: iload #6
    //   265: if_icmpgt -> 162
    //   268: pop
    //   269: new java/lang/String
    //   272: dup_x1
    //   273: swap
    //   274: invokespecial <init> : ([C)V
    //   277: invokevirtual intern : ()Ljava/lang/String;
    //   280: swap
    //   281: pop
    //   282: swap
    //   283: tableswitch default -> 40, 0 -> 99
    //   300: sipush #24262
    //   303: sipush #-10654
    //   306: invokestatic a : (II)Ljava/lang/String;
    //   309: putstatic burp/Ze25.Zp : Ljava/lang/String;
    //   312: new java/math/BigInteger
    //   315: dup
    //   316: sipush #24275
    //   319: sipush #27001
    //   322: invokestatic a : (II)Ljava/lang/String;
    //   325: invokespecial <init> : (Ljava/lang/String;)V
    //   328: putstatic burp/Ze25.ZW : Ljava/lang/Object;
    //   331: return
  }
  
  private static Throwable a(Throwable paramThrowable) {
    return paramThrowable;
  }
  
  private static String a(int paramInt1, int paramInt2) {
    int i = (paramInt1 ^ 0x5EDF) & 0xFFFF;
    if (b[i] == null) {
      char[] arrayOfChar = a[i].toCharArray();
      switch (arrayOfChar[0] & 0xFF) {
        case 0:
        
        case 1:
        
        case 2:
        
        case 3:
        
        case 4:
        
        case 5:
        
        case 6:
        
        case 7:
        
        case 8:
        
        case 9:
        
        case 10:
        
        case 11:
        
        case 12:
        
        case 13:
        
        case 14:
        
        case 15:
        
        case 16:
        
        case 17:
        
        case 18:
        
        case 19:
        
        case 20:
        
        case 21:
        
        case 22:
        
        case 23:
        
        case 24:
        
        case 25:
        
        case 26:
        
        case 27:
        
        case 28:
        
        case 29:
        
        case 30:
        
        case 31:
        
        case 32:
        
        case 33:
        
        case 34:
        
        case 35:
        
        case 36:
        
        case 37:
        
        case 38:
        
        case 39:
        
        case 40:
        
        case 41:
        
        case 42:
        
        case 43:
        
        case 44:
        
        case 45:
        
        case 46:
        
        case 47:
        
        case 48:
        
        case 49:
        
        case 50:
        
        case 51:
        
        case 52:
        
        case 53:
        
        case 54:
        
        case 55:
        
        case 56:
        
        case 57:
        
        case 58:
        
        case 59:
        
        case 60:
        
        case 61:
        
        case 62:
        
        case 63:
        
        case 64:
        
        case 65:
        
        case 66:
        
        case 67:
        
        case 68:
        
        case 69:
        
        case 70:
        
        case 71:
        
        case 72:
        
        case 73:
        
        case 74:
        
        case 75:
        
        case 76:
        
        case 77:
        
        case 78:
        
        case 79:
        
        case 80:
        
        case 81:
        
        case 82:
        
        case 83:
        
        case 84:
        
        case 85:
        
        case 86:
        
        case 87:
        
        case 88:
        
        case 89:
        
        case 90:
        
        case 91:
        
        case 92:
        
        case 93:
        
        case 94:
        
        case 95:
        
        case 96:
        
        case 97:
        
        case 98:
        
        case 99:
        
        case 100:
        
        case 101:
        
        case 102:
        
        case 103:
        
        case 104:
        
        case 105:
        
        case 106:
        
        case 107:
        
        case 108:
        
        case 109:
        
        case 110:
        
        case 111:
        
        case 112:
        
        case 113:
        
        case 114:
        
        case 115:
        
        case 116:
        
        case 117:
        
        case 118:
        
        case 119:
        
        case 120:
        
        case 121:
        
        case 122:
        
        case 123:
        
        case 124:
        
        case 125:
        
        case 126:
        
        case 127:
        
        case 128:
        
        case 129:
        
        case 130:
        
        case 131:
        
        case 132:
        
        case 133:
        
        case 134:
        
        case 135:
        
        case 136:
        
        case 137:
        
        case 138:
        
        case 139:
        
        case 140:
        
        case 141:
        
        case 142:
        
        case 143:
        
        case 144:
        
        case 145:
        
        case 146:
        
        case 147:
        
        case 148:
        
        case 149:
        
        case 150:
        
        case 151:
        
        case 152:
        
        case 153:
        
        case 154:
        
        case 155:
        
        case 156:
        
        case 157:
        
        case 158:
        
        case 159:
        
        case 160:
        
        case 161:
        
        case 162:
        
        case 163:
        
        case 164:
        
        case 165:
        
        case 166:
        
        case 167:
        
        case 168:
        
        case 169:
        
        case 170:
        
        case 171:
        
        case 172:
        
        case 173:
        
        case 174:
        
        case 175:
        
        case 176:
        
        case 177:
        
        case 178:
        
        case 179:
        
        case 180:
        
        case 181:
        
        case 182:
        
        case 183:
        
        case 184:
        
        case 185:
        
        case 186:
        
        case 187:
        
        case 188:
        
        case 189:
        
        case 190:
        
        case 191:
        
        case 192:
        
        case 193:
        
        case 194:
        
        case 195:
        
        case 196:
        
        case 197:
        
        case 198:
        
        case 199:
        
        case 200:
        
        case 201:
        
        case 202:
        
        case 203:
        
        case 204:
        
        case 205:
        
        case 206:
        
        case 207:
        
        case 208:
        
        case 209:
        
        case 210:
        
        case 211:
        
        case 212:
        
        case 213:
        
        case 214:
        
        case 215:
        
        case 216:
        
        case 217:
        
        case 218:
        
        case 219:
        
        case 220:
        
        case 221:
        
        case 222:
        
        case 223:
        
        case 224:
        
        case 225:
        
        case 226:
        
        case 227:
        
        case 228:
        
        case 229:
        
        case 230:
        
        case 231:
        
        case 232:
        
        case 233:
        
        case 234:
        
        case 235:
        
        case 236:
        
        case 237:
        
        case 238:
        
        case 239:
        
        case 240:
        
        case 241:
        
        case 242:
        
        case 243:
        
        case 244:
        
        case 245:
        
        case 246:
        
        case 247:
        
        case 248:
        
        case 249:
        
        case 250:
        
        case 251:
        
        case 252:
        
        case 253:
        
        case 254:
        
        default:
          break;
      } 
      char c = '';
      int j = (paramInt2 & 0xFF) - c;
      if (j < 0)
        j += 256; 
      int k = ((paramInt2 & 0xFFFF) >>> 8) - c;
      if (k < 0)
        k += 256; 
      for (byte b = 0; b < arrayOfChar.length; b++) {
        int m = b % 2;
        if (m == 0) {
          arrayOfChar[b] = (char)(arrayOfChar[b] ^ j);
          j = ((j >>> 3 | j << 5) ^ arrayOfChar[b]) & 0xFF;
        } else {
          arrayOfChar[b] = (char)(arrayOfChar[b] ^ k);
          k = ((k >>> 3 | k << 5) ^ arrayOfChar[b]) & 0xFF;
        } 
      } 
      b[i] = (new String(arrayOfChar)).intern();
    } 
    return b[i];
  }
}


/* Location:              C:\Program Files\BurpSuitePro\burpsuite_pro.jar!\burp\Ze25.class
 * Java compiler version: 21 (65.0)
 * JD-Core Version:       1.1.3
 */