package burp;

import java.math.BigInteger;

class Ze2w extends ClassLoader {
  static String Za;
  
  static Object ZA;
  
  private static final String[] a;
  
  private static final String[] b;
  
  static void ZV(Object[] paramArrayOfObject, Object paramObject) throws Throwable {}
  
  static void ZE(Object paramObject) {
    Ze5h.Zk = a(-888, 10914);
    Ze5h.Zn = new BigInteger(a(-887, -18359));
    boolean bool = Zt2e.ZN();
    try {
      try {
        if (Ze1k.ZI.charAt(Math.abs(((BigInteger)Zea8.ZF).intValue() % 32)) <= Zegw.Zn.charAt(Math.abs(((BigInteger)Zrov.Zk).intValue() % 32))) {
          try {
            Zg1l.ZY(Class.forName(a(-884, -14476)));
            if (!bool)
              Zek5.Zj(Class.forName(a(-881, -13327))); 
          } catch (Throwable throwable) {
            throw a(null);
          } 
          return;
        } 
      } catch (Throwable throwable) {
        throw a(null);
      } 
      Zek5.Zj(Class.forName(a(-881, -13327)));
    } catch (Throwable throwable) {}
  }
  
  static boolean ZS(Object[] paramArrayOfObject, Object paramObject) throws Throwable {
    // Byte code:
    //   0: invokestatic ZK : ()Z
    //   3: istore_2
    //   4: new java/lang/StringBuilder
    //   7: dup
    //   8: invokespecial <init> : ()V
    //   11: astore_3
    //   12: iconst_0
    //   13: istore #4
    //   15: iload #4
    //   17: bipush #32
    //   19: if_icmpge -> 1355
    //   22: iload #4
    //   24: tableswitch default -> 1348, 0 -> 168, 1 -> 205, 2 -> 242, 3 -> 279, 4 -> 316, 5 -> 353, 6 -> 390, 7 -> 427, 8 -> 464, 9 -> 501, 10 -> 538, 11 -> 575, 12 -> 612, 13 -> 649, 14 -> 686, 15 -> 723, 16 -> 760, 17 -> 797, 18 -> 834, 19 -> 871, 20 -> 908, 21 -> 945, 22 -> 982, 23 -> 1019, 24 -> 1056, 25 -> 1093, 26 -> 1130, 27 -> 1167, 28 -> 1204, 29 -> 1241, 30 -> 1278, 31 -> 1315
    //   168: aload_3
    //   169: getstatic burp/Zxju.Zt : Ljava/lang/String;
    //   172: getstatic burp/Zedu.ZL : Ljava/lang/Object;
    //   175: checkcast java/math/BigInteger
    //   178: invokevirtual intValue : ()I
    //   181: bipush #32
    //   183: irem
    //   184: invokestatic abs : (I)I
    //   187: invokevirtual charAt : (I)C
    //   190: invokevirtual append : (C)Ljava/lang/StringBuilder;
    //   193: pop
    //   194: iload_2
    //   195: ifeq -> 1348
    //   198: goto -> 205
    //   201: invokestatic a : (Ljava/lang/Throwable;)Ljava/lang/Throwable;
    //   204: athrow
    //   205: aload_3
    //   206: getstatic burp/Zrwp.ZS : Ljava/lang/String;
    //   209: getstatic burp/Zkhf.ZU : Ljava/lang/Object;
    //   212: checkcast java/math/BigInteger
    //   215: invokevirtual intValue : ()I
    //   218: bipush #32
    //   220: irem
    //   221: invokestatic abs : (I)I
    //   224: invokevirtual charAt : (I)C
    //   227: invokevirtual append : (C)Ljava/lang/StringBuilder;
    //   230: pop
    //   231: iload_2
    //   232: ifeq -> 1348
    //   235: goto -> 242
    //   238: invokestatic a : (Ljava/lang/Throwable;)Ljava/lang/Throwable;
    //   241: athrow
    //   242: aload_3
    //   243: getstatic burp/Zma0.ZP : Ljava/lang/String;
    //   246: getstatic burp/Zmf6.ZD : Ljava/lang/Object;
    //   249: checkcast java/math/BigInteger
    //   252: invokevirtual intValue : ()I
    //   255: bipush #32
    //   257: irem
    //   258: invokestatic abs : (I)I
    //   261: invokevirtual charAt : (I)C
    //   264: invokevirtual append : (C)Ljava/lang/StringBuilder;
    //   267: pop
    //   268: iload_2
    //   269: ifeq -> 1348
    //   272: goto -> 279
    //   275: invokestatic a : (Ljava/lang/Throwable;)Ljava/lang/Throwable;
    //   278: athrow
    //   279: aload_3
    //   280: getstatic burp/Zsbv.Zr : Ljava/lang/String;
    //   283: getstatic burp/Zm7v.ZP : Ljava/lang/Object;
    //   286: checkcast java/math/BigInteger
    //   289: invokevirtual intValue : ()I
    //   292: bipush #32
    //   294: irem
    //   295: invokestatic abs : (I)I
    //   298: invokevirtual charAt : (I)C
    //   301: invokevirtual append : (C)Ljava/lang/StringBuilder;
    //   304: pop
    //   305: iload_2
    //   306: ifeq -> 1348
    //   309: goto -> 316
    //   312: invokestatic a : (Ljava/lang/Throwable;)Ljava/lang/Throwable;
    //   315: athrow
    //   316: aload_3
    //   317: getstatic burp/Zmkq.Zr : Ljava/lang/String;
    //   320: getstatic burp/Zeva.Zf : Ljava/lang/Object;
    //   323: checkcast java/math/BigInteger
    //   326: invokevirtual intValue : ()I
    //   329: bipush #32
    //   331: irem
    //   332: invokestatic abs : (I)I
    //   335: invokevirtual charAt : (I)C
    //   338: invokevirtual append : (C)Ljava/lang/StringBuilder;
    //   341: pop
    //   342: iload_2
    //   343: ifeq -> 1348
    //   346: goto -> 353
    //   349: invokestatic a : (Ljava/lang/Throwable;)Ljava/lang/Throwable;
    //   352: athrow
    //   353: aload_3
    //   354: getstatic burp/Zz0f.ZW : Ljava/lang/String;
    //   357: getstatic burp/Zl_a.ZP : Ljava/lang/Object;
    //   360: checkcast java/math/BigInteger
    //   363: invokevirtual intValue : ()I
    //   366: bipush #32
    //   368: irem
    //   369: invokestatic abs : (I)I
    //   372: invokevirtual charAt : (I)C
    //   375: invokevirtual append : (C)Ljava/lang/StringBuilder;
    //   378: pop
    //   379: iload_2
    //   380: ifeq -> 1348
    //   383: goto -> 390
    //   386: invokestatic a : (Ljava/lang/Throwable;)Ljava/lang/Throwable;
    //   389: athrow
    //   390: aload_3
    //   391: getstatic burp/Zlwm.Zj : Ljava/lang/String;
    //   394: getstatic burp/Zsfg.Zm : Ljava/lang/Object;
    //   397: checkcast java/math/BigInteger
    //   400: invokevirtual intValue : ()I
    //   403: bipush #32
    //   405: irem
    //   406: invokestatic abs : (I)I
    //   409: invokevirtual charAt : (I)C
    //   412: invokevirtual append : (C)Ljava/lang/StringBuilder;
    //   415: pop
    //   416: iload_2
    //   417: ifeq -> 1348
    //   420: goto -> 427
    //   423: invokestatic a : (Ljava/lang/Throwable;)Ljava/lang/Throwable;
    //   426: athrow
    //   427: aload_3
    //   428: getstatic burp/Zetf.Zo : Ljava/lang/String;
    //   431: getstatic burp/Zelt.ZC : Ljava/lang/Object;
    //   434: checkcast java/math/BigInteger
    //   437: invokevirtual intValue : ()I
    //   440: bipush #32
    //   442: irem
    //   443: invokestatic abs : (I)I
    //   446: invokevirtual charAt : (I)C
    //   449: invokevirtual append : (C)Ljava/lang/StringBuilder;
    //   452: pop
    //   453: iload_2
    //   454: ifeq -> 1348
    //   457: goto -> 464
    //   460: invokestatic a : (Ljava/lang/Throwable;)Ljava/lang/Throwable;
    //   463: athrow
    //   464: aload_3
    //   465: getstatic burp/Zm63.Zs : Ljava/lang/String;
    //   468: getstatic burp/Zlxr.Zz : Ljava/lang/Object;
    //   471: checkcast java/math/BigInteger
    //   474: invokevirtual intValue : ()I
    //   477: bipush #32
    //   479: irem
    //   480: invokestatic abs : (I)I
    //   483: invokevirtual charAt : (I)C
    //   486: invokevirtual append : (C)Ljava/lang/StringBuilder;
    //   489: pop
    //   490: iload_2
    //   491: ifeq -> 1348
    //   494: goto -> 501
    //   497: invokestatic a : (Ljava/lang/Throwable;)Ljava/lang/Throwable;
    //   500: athrow
    //   501: aload_3
    //   502: getstatic burp/Zge9.Zp : Ljava/lang/String;
    //   505: getstatic burp/Zsp9.ZV : Ljava/lang/Object;
    //   508: checkcast java/math/BigInteger
    //   511: invokevirtual intValue : ()I
    //   514: bipush #32
    //   516: irem
    //   517: invokestatic abs : (I)I
    //   520: invokevirtual charAt : (I)C
    //   523: invokevirtual append : (C)Ljava/lang/StringBuilder;
    //   526: pop
    //   527: iload_2
    //   528: ifeq -> 1348
    //   531: goto -> 538
    //   534: invokestatic a : (Ljava/lang/Throwable;)Ljava/lang/Throwable;
    //   537: athrow
    //   538: aload_3
    //   539: getstatic burp/Zspg.ZG : Ljava/lang/String;
    //   542: getstatic burp/Zskf.ZQ : Ljava/lang/Object;
    //   545: checkcast java/math/BigInteger
    //   548: invokevirtual intValue : ()I
    //   551: bipush #32
    //   553: irem
    //   554: invokestatic abs : (I)I
    //   557: invokevirtual charAt : (I)C
    //   560: invokevirtual append : (C)Ljava/lang/StringBuilder;
    //   563: pop
    //   564: iload_2
    //   565: ifeq -> 1348
    //   568: goto -> 575
    //   571: invokestatic a : (Ljava/lang/Throwable;)Ljava/lang/Throwable;
    //   574: athrow
    //   575: aload_3
    //   576: getstatic burp/Zscz.ZJ : Ljava/lang/String;
    //   579: getstatic burp/Zg7u.Zh : Ljava/lang/Object;
    //   582: checkcast java/math/BigInteger
    //   585: invokevirtual intValue : ()I
    //   588: bipush #32
    //   590: irem
    //   591: invokestatic abs : (I)I
    //   594: invokevirtual charAt : (I)C
    //   597: invokevirtual append : (C)Ljava/lang/StringBuilder;
    //   600: pop
    //   601: iload_2
    //   602: ifeq -> 1348
    //   605: goto -> 612
    //   608: invokestatic a : (Ljava/lang/Throwable;)Ljava/lang/Throwable;
    //   611: athrow
    //   612: aload_3
    //   613: getstatic burp/Zgk9.Zf : Ljava/lang/String;
    //   616: getstatic burp/Zrfs.ZV : Ljava/lang/Object;
    //   619: checkcast java/math/BigInteger
    //   622: invokevirtual intValue : ()I
    //   625: bipush #32
    //   627: irem
    //   628: invokestatic abs : (I)I
    //   631: invokevirtual charAt : (I)C
    //   634: invokevirtual append : (C)Ljava/lang/StringBuilder;
    //   637: pop
    //   638: iload_2
    //   639: ifeq -> 1348
    //   642: goto -> 649
    //   645: invokestatic a : (Ljava/lang/Throwable;)Ljava/lang/Throwable;
    //   648: athrow
    //   649: aload_3
    //   650: getstatic burp/Zbnk.Zg : Ljava/lang/String;
    //   653: getstatic burp/Zr1h.Z_ : Ljava/lang/Object;
    //   656: checkcast java/math/BigInteger
    //   659: invokevirtual intValue : ()I
    //   662: bipush #32
    //   664: irem
    //   665: invokestatic abs : (I)I
    //   668: invokevirtual charAt : (I)C
    //   671: invokevirtual append : (C)Ljava/lang/StringBuilder;
    //   674: pop
    //   675: iload_2
    //   676: ifeq -> 1348
    //   679: goto -> 686
    //   682: invokestatic a : (Ljava/lang/Throwable;)Ljava/lang/Throwable;
    //   685: athrow
    //   686: aload_3
    //   687: getstatic burp/Zgsy.Zv : Ljava/lang/String;
    //   690: getstatic burp/Zek4.ZR : Ljava/lang/Object;
    //   693: checkcast java/math/BigInteger
    //   696: invokevirtual intValue : ()I
    //   699: bipush #32
    //   701: irem
    //   702: invokestatic abs : (I)I
    //   705: invokevirtual charAt : (I)C
    //   708: invokevirtual append : (C)Ljava/lang/StringBuilder;
    //   711: pop
    //   712: iload_2
    //   713: ifeq -> 1348
    //   716: goto -> 723
    //   719: invokestatic a : (Ljava/lang/Throwable;)Ljava/lang/Throwable;
    //   722: athrow
    //   723: aload_3
    //   724: getstatic burp/Zzef.Za : Ljava/lang/String;
    //   727: getstatic burp/Zgpx.ZQ : Ljava/lang/Object;
    //   730: checkcast java/math/BigInteger
    //   733: invokevirtual intValue : ()I
    //   736: bipush #32
    //   738: irem
    //   739: invokestatic abs : (I)I
    //   742: invokevirtual charAt : (I)C
    //   745: invokevirtual append : (C)Ljava/lang/StringBuilder;
    //   748: pop
    //   749: iload_2
    //   750: ifeq -> 1348
    //   753: goto -> 760
    //   756: invokestatic a : (Ljava/lang/Throwable;)Ljava/lang/Throwable;
    //   759: athrow
    //   760: aload_3
    //   761: getstatic burp/Zeqz.ZV : Ljava/lang/String;
    //   764: getstatic burp/Zbow.ZS : Ljava/lang/Object;
    //   767: checkcast java/math/BigInteger
    //   770: invokevirtual intValue : ()I
    //   773: bipush #32
    //   775: irem
    //   776: invokestatic abs : (I)I
    //   779: invokevirtual charAt : (I)C
    //   782: invokevirtual append : (C)Ljava/lang/StringBuilder;
    //   785: pop
    //   786: iload_2
    //   787: ifeq -> 1348
    //   790: goto -> 797
    //   793: invokestatic a : (Ljava/lang/Throwable;)Ljava/lang/Throwable;
    //   796: athrow
    //   797: aload_3
    //   798: getstatic burp/Zbnz.Zp : Ljava/lang/String;
    //   801: getstatic burp/Zbl4.ZW : Ljava/lang/Object;
    //   804: checkcast java/math/BigInteger
    //   807: invokevirtual intValue : ()I
    //   810: bipush #32
    //   812: irem
    //   813: invokestatic abs : (I)I
    //   816: invokevirtual charAt : (I)C
    //   819: invokevirtual append : (C)Ljava/lang/StringBuilder;
    //   822: pop
    //   823: iload_2
    //   824: ifeq -> 1348
    //   827: goto -> 834
    //   830: invokestatic a : (Ljava/lang/Throwable;)Ljava/lang/Throwable;
    //   833: athrow
    //   834: aload_3
    //   835: getstatic burp/Zm69.ZE : Ljava/lang/String;
    //   838: getstatic burp/Ze25.ZW : Ljava/lang/Object;
    //   841: checkcast java/math/BigInteger
    //   844: invokevirtual intValue : ()I
    //   847: bipush #32
    //   849: irem
    //   850: invokestatic abs : (I)I
    //   853: invokevirtual charAt : (I)C
    //   856: invokevirtual append : (C)Ljava/lang/StringBuilder;
    //   859: pop
    //   860: iload_2
    //   861: ifeq -> 1348
    //   864: goto -> 871
    //   867: invokestatic a : (Ljava/lang/Throwable;)Ljava/lang/Throwable;
    //   870: athrow
    //   871: aload_3
    //   872: getstatic burp/Zmui.ZY : Ljava/lang/String;
    //   875: getstatic burp/Zsjc.ZX : Ljava/lang/Object;
    //   878: checkcast java/math/BigInteger
    //   881: invokevirtual intValue : ()I
    //   884: bipush #32
    //   886: irem
    //   887: invokestatic abs : (I)I
    //   890: invokevirtual charAt : (I)C
    //   893: invokevirtual append : (C)Ljava/lang/StringBuilder;
    //   896: pop
    //   897: iload_2
    //   898: ifeq -> 1348
    //   901: goto -> 908
    //   904: invokestatic a : (Ljava/lang/Throwable;)Ljava/lang/Throwable;
    //   907: athrow
    //   908: aload_3
    //   909: getstatic burp/Zea.Zj : Ljava/lang/String;
    //   912: getstatic burp/Ztl6.ZQ : Ljava/lang/Object;
    //   915: checkcast java/math/BigInteger
    //   918: invokevirtual intValue : ()I
    //   921: bipush #32
    //   923: irem
    //   924: invokestatic abs : (I)I
    //   927: invokevirtual charAt : (I)C
    //   930: invokevirtual append : (C)Ljava/lang/StringBuilder;
    //   933: pop
    //   934: iload_2
    //   935: ifeq -> 1348
    //   938: goto -> 945
    //   941: invokestatic a : (Ljava/lang/Throwable;)Ljava/lang/Throwable;
    //   944: athrow
    //   945: aload_3
    //   946: getstatic burp/Zxt7.Zi : Ljava/lang/String;
    //   949: getstatic burp/Zz66.ZQ : Ljava/lang/Object;
    //   952: checkcast java/math/BigInteger
    //   955: invokevirtual intValue : ()I
    //   958: bipush #32
    //   960: irem
    //   961: invokestatic abs : (I)I
    //   964: invokevirtual charAt : (I)C
    //   967: invokevirtual append : (C)Ljava/lang/StringBuilder;
    //   970: pop
    //   971: iload_2
    //   972: ifeq -> 1348
    //   975: goto -> 982
    //   978: invokestatic a : (Ljava/lang/Throwable;)Ljava/lang/Throwable;
    //   981: athrow
    //   982: aload_3
    //   983: getstatic burp/Zl_a.ZD : Ljava/lang/String;
    //   986: getstatic burp/Ze6w.Ze : Ljava/lang/Object;
    //   989: checkcast java/math/BigInteger
    //   992: invokevirtual intValue : ()I
    //   995: bipush #32
    //   997: irem
    //   998: invokestatic abs : (I)I
    //   1001: invokevirtual charAt : (I)C
    //   1004: invokevirtual append : (C)Ljava/lang/StringBuilder;
    //   1007: pop
    //   1008: iload_2
    //   1009: ifeq -> 1348
    //   1012: goto -> 1019
    //   1015: invokestatic a : (Ljava/lang/Throwable;)Ljava/lang/Throwable;
    //   1018: athrow
    //   1019: aload_3
    //   1020: getstatic burp/Ze84.Zv : Ljava/lang/String;
    //   1023: getstatic burp/Zgpx.ZQ : Ljava/lang/Object;
    //   1026: checkcast java/math/BigInteger
    //   1029: invokevirtual intValue : ()I
    //   1032: bipush #32
    //   1034: irem
    //   1035: invokestatic abs : (I)I
    //   1038: invokevirtual charAt : (I)C
    //   1041: invokevirtual append : (C)Ljava/lang/StringBuilder;
    //   1044: pop
    //   1045: iload_2
    //   1046: ifeq -> 1348
    //   1049: goto -> 1056
    //   1052: invokestatic a : (Ljava/lang/Throwable;)Ljava/lang/Throwable;
    //   1055: athrow
    //   1056: aload_3
    //   1057: getstatic burp/Zmpx.ZC : Ljava/lang/String;
    //   1060: getstatic burp/Zoe.ZG : Ljava/lang/Object;
    //   1063: checkcast java/math/BigInteger
    //   1066: invokevirtual intValue : ()I
    //   1069: bipush #32
    //   1071: irem
    //   1072: invokestatic abs : (I)I
    //   1075: invokevirtual charAt : (I)C
    //   1078: invokevirtual append : (C)Ljava/lang/StringBuilder;
    //   1081: pop
    //   1082: iload_2
    //   1083: ifeq -> 1348
    //   1086: goto -> 1093
    //   1089: invokestatic a : (Ljava/lang/Throwable;)Ljava/lang/Throwable;
    //   1092: athrow
    //   1093: aload_3
    //   1094: getstatic burp/Zvh.ZP : Ljava/lang/String;
    //   1097: getstatic burp/Zelt.ZC : Ljava/lang/Object;
    //   1100: checkcast java/math/BigInteger
    //   1103: invokevirtual intValue : ()I
    //   1106: bipush #32
    //   1108: irem
    //   1109: invokestatic abs : (I)I
    //   1112: invokevirtual charAt : (I)C
    //   1115: invokevirtual append : (C)Ljava/lang/StringBuilder;
    //   1118: pop
    //   1119: iload_2
    //   1120: ifeq -> 1348
    //   1123: goto -> 1130
    //   1126: invokestatic a : (Ljava/lang/Throwable;)Ljava/lang/Throwable;
    //   1129: athrow
    //   1130: aload_3
    //   1131: getstatic burp/Zepy.Zg : Ljava/lang/String;
    //   1134: getstatic burp/Zxxf.ZZ : Ljava/lang/Object;
    //   1137: checkcast java/math/BigInteger
    //   1140: invokevirtual intValue : ()I
    //   1143: bipush #32
    //   1145: irem
    //   1146: invokestatic abs : (I)I
    //   1149: invokevirtual charAt : (I)C
    //   1152: invokevirtual append : (C)Ljava/lang/StringBuilder;
    //   1155: pop
    //   1156: iload_2
    //   1157: ifeq -> 1348
    //   1160: goto -> 1167
    //   1163: invokestatic a : (Ljava/lang/Throwable;)Ljava/lang/Throwable;
    //   1166: athrow
    //   1167: aload_3
    //   1168: getstatic burp/Zbx5.Zz : Ljava/lang/String;
    //   1171: getstatic burp/Zl1e.Zp : Ljava/lang/Object;
    //   1174: checkcast java/math/BigInteger
    //   1177: invokevirtual intValue : ()I
    //   1180: bipush #32
    //   1182: irem
    //   1183: invokestatic abs : (I)I
    //   1186: invokevirtual charAt : (I)C
    //   1189: invokevirtual append : (C)Ljava/lang/StringBuilder;
    //   1192: pop
    //   1193: iload_2
    //   1194: ifeq -> 1348
    //   1197: goto -> 1204
    //   1200: invokestatic a : (Ljava/lang/Throwable;)Ljava/lang/Throwable;
    //   1203: athrow
    //   1204: aload_3
    //   1205: getstatic burp/Zt85.ZR : Ljava/lang/String;
    //   1208: getstatic burp/Zz5e.Zl : Ljava/lang/Object;
    //   1211: checkcast java/math/BigInteger
    //   1214: invokevirtual intValue : ()I
    //   1217: bipush #32
    //   1219: irem
    //   1220: invokestatic abs : (I)I
    //   1223: invokevirtual charAt : (I)C
    //   1226: invokevirtual append : (C)Ljava/lang/StringBuilder;
    //   1229: pop
    //   1230: iload_2
    //   1231: ifeq -> 1348
    //   1234: goto -> 1241
    //   1237: invokestatic a : (Ljava/lang/Throwable;)Ljava/lang/Throwable;
    //   1240: athrow
    //   1241: aload_3
    //   1242: getstatic burp/Zsjw.ZQ : Ljava/lang/String;
    //   1245: getstatic burp/Zezi.ZQ : Ljava/lang/Object;
    //   1248: checkcast java/math/BigInteger
    //   1251: invokevirtual intValue : ()I
    //   1254: bipush #32
    //   1256: irem
    //   1257: invokestatic abs : (I)I
    //   1260: invokevirtual charAt : (I)C
    //   1263: invokevirtual append : (C)Ljava/lang/StringBuilder;
    //   1266: pop
    //   1267: iload_2
    //   1268: ifeq -> 1348
    //   1271: goto -> 1278
    //   1274: invokestatic a : (Ljava/lang/Throwable;)Ljava/lang/Throwable;
    //   1277: athrow
    //   1278: aload_3
    //   1279: getstatic burp/Zz4m.ZI : Ljava/lang/String;
    //   1282: getstatic burp/Ztq4.ZA : Ljava/lang/Object;
    //   1285: checkcast java/math/BigInteger
    //   1288: invokevirtual intValue : ()I
    //   1291: bipush #32
    //   1293: irem
    //   1294: invokestatic abs : (I)I
    //   1297: invokevirtual charAt : (I)C
    //   1300: invokevirtual append : (C)Ljava/lang/StringBuilder;
    //   1303: pop
    //   1304: iload_2
    //   1305: ifeq -> 1348
    //   1308: goto -> 1315
    //   1311: invokestatic a : (Ljava/lang/Throwable;)Ljava/lang/Throwable;
    //   1314: athrow
    //   1315: aload_3
    //   1316: getstatic burp/Zrb6.ZP : Ljava/lang/String;
    //   1319: getstatic burp/Zz5e.Zl : Ljava/lang/Object;
    //   1322: checkcast java/math/BigInteger
    //   1325: invokevirtual intValue : ()I
    //   1328: bipush #32
    //   1330: irem
    //   1331: invokestatic abs : (I)I
    //   1334: invokevirtual charAt : (I)C
    //   1337: invokevirtual append : (C)Ljava/lang/StringBuilder;
    //   1340: pop
    //   1341: goto -> 1348
    //   1344: invokestatic a : (Ljava/lang/Throwable;)Ljava/lang/Throwable;
    //   1347: athrow
    //   1348: iinc #4, 1
    //   1351: iload_2
    //   1352: ifeq -> 15
    //   1355: aload_3
    //   1356: invokevirtual toString : ()Ljava/lang/String;
    //   1359: putstatic burp/Zzht.Zv : Ljava/lang/String;
    //   1362: new java/lang/StringBuilder
    //   1365: dup
    //   1366: invokespecial <init> : ()V
    //   1369: astore #4
    //   1371: iconst_0
    //   1372: istore #5
    //   1374: iload #5
    //   1376: bipush #32
    //   1378: if_icmpge -> 2743
    //   1381: iload #5
    //   1383: tableswitch default -> 2736, 0 -> 1524, 1 -> 1562, 2 -> 1600, 3 -> 1638, 4 -> 1676, 5 -> 1714, 6 -> 1752, 7 -> 1790, 8 -> 1828, 9 -> 1866, 10 -> 1904, 11 -> 1942, 12 -> 1980, 13 -> 2018, 14 -> 2056, 15 -> 2094, 16 -> 2132, 17 -> 2170, 18 -> 2208, 19 -> 2246, 20 -> 2284, 21 -> 2322, 22 -> 2360, 23 -> 2398, 24 -> 2436, 25 -> 2474, 26 -> 2512, 27 -> 2550, 28 -> 2588, 29 -> 2626, 30 -> 2664, 31 -> 2702
    //   1524: aload #4
    //   1526: getstatic burp/Zg1l.Zl : Ljava/lang/String;
    //   1529: getstatic burp/Zmh3.ZF : Ljava/lang/Object;
    //   1532: checkcast java/math/BigInteger
    //   1535: invokevirtual intValue : ()I
    //   1538: bipush #32
    //   1540: irem
    //   1541: invokestatic abs : (I)I
    //   1544: invokevirtual charAt : (I)C
    //   1547: invokevirtual append : (C)Ljava/lang/StringBuilder;
    //   1550: pop
    //   1551: iload_2
    //   1552: ifeq -> 2736
    //   1555: goto -> 1562
    //   1558: invokestatic a : (Ljava/lang/Throwable;)Ljava/lang/Throwable;
    //   1561: athrow
    //   1562: aload #4
    //   1564: getstatic burp/Zgu4.Za : Ljava/lang/String;
    //   1567: getstatic burp/Zm0d.Zz : Ljava/lang/Object;
    //   1570: checkcast java/math/BigInteger
    //   1573: invokevirtual intValue : ()I
    //   1576: bipush #32
    //   1578: irem
    //   1579: invokestatic abs : (I)I
    //   1582: invokevirtual charAt : (I)C
    //   1585: invokevirtual append : (C)Ljava/lang/StringBuilder;
    //   1588: pop
    //   1589: iload_2
    //   1590: ifeq -> 2736
    //   1593: goto -> 1600
    //   1596: invokestatic a : (Ljava/lang/Throwable;)Ljava/lang/Throwable;
    //   1599: athrow
    //   1600: aload #4
    //   1602: getstatic burp/Zk92.Zc : Ljava/lang/String;
    //   1605: getstatic burp/Zsp9.ZV : Ljava/lang/Object;
    //   1608: checkcast java/math/BigInteger
    //   1611: invokevirtual intValue : ()I
    //   1614: bipush #32
    //   1616: irem
    //   1617: invokestatic abs : (I)I
    //   1620: invokevirtual charAt : (I)C
    //   1623: invokevirtual append : (C)Ljava/lang/StringBuilder;
    //   1626: pop
    //   1627: iload_2
    //   1628: ifeq -> 2736
    //   1631: goto -> 1638
    //   1634: invokestatic a : (Ljava/lang/Throwable;)Ljava/lang/Throwable;
    //   1637: athrow
    //   1638: aload #4
    //   1640: getstatic burp/Zs4g.ZV : Ljava/lang/String;
    //   1643: getstatic burp/Zku9.Zp : Ljava/lang/Object;
    //   1646: checkcast java/math/BigInteger
    //   1649: invokevirtual intValue : ()I
    //   1652: bipush #32
    //   1654: irem
    //   1655: invokestatic abs : (I)I
    //   1658: invokevirtual charAt : (I)C
    //   1661: invokevirtual append : (C)Ljava/lang/StringBuilder;
    //   1664: pop
    //   1665: iload_2
    //   1666: ifeq -> 2736
    //   1669: goto -> 1676
    //   1672: invokestatic a : (Ljava/lang/Throwable;)Ljava/lang/Throwable;
    //   1675: athrow
    //   1676: aload #4
    //   1678: getstatic burp/Zg6z.ZY : Ljava/lang/String;
    //   1681: getstatic burp/Zma0.ZQ : Ljava/lang/Object;
    //   1684: checkcast java/math/BigInteger
    //   1687: invokevirtual intValue : ()I
    //   1690: bipush #32
    //   1692: irem
    //   1693: invokestatic abs : (I)I
    //   1696: invokevirtual charAt : (I)C
    //   1699: invokevirtual append : (C)Ljava/lang/StringBuilder;
    //   1702: pop
    //   1703: iload_2
    //   1704: ifeq -> 2736
    //   1707: goto -> 1714
    //   1710: invokestatic a : (Ljava/lang/Throwable;)Ljava/lang/Throwable;
    //   1713: athrow
    //   1714: aload #4
    //   1716: getstatic burp/Zg1l.Zl : Ljava/lang/String;
    //   1719: getstatic burp/Zex0.Ze : Ljava/lang/Object;
    //   1722: checkcast java/math/BigInteger
    //   1725: invokevirtual intValue : ()I
    //   1728: bipush #32
    //   1730: irem
    //   1731: invokestatic abs : (I)I
    //   1734: invokevirtual charAt : (I)C
    //   1737: invokevirtual append : (C)Ljava/lang/StringBuilder;
    //   1740: pop
    //   1741: iload_2
    //   1742: ifeq -> 2736
    //   1745: goto -> 1752
    //   1748: invokestatic a : (Ljava/lang/Throwable;)Ljava/lang/Throwable;
    //   1751: athrow
    //   1752: aload #4
    //   1754: getstatic burp/Zgpx.Z_ : Ljava/lang/String;
    //   1757: getstatic burp/Zr60.Ze : Ljava/lang/Object;
    //   1760: checkcast java/math/BigInteger
    //   1763: invokevirtual intValue : ()I
    //   1766: bipush #32
    //   1768: irem
    //   1769: invokestatic abs : (I)I
    //   1772: invokevirtual charAt : (I)C
    //   1775: invokevirtual append : (C)Ljava/lang/StringBuilder;
    //   1778: pop
    //   1779: iload_2
    //   1780: ifeq -> 2736
    //   1783: goto -> 1790
    //   1786: invokestatic a : (Ljava/lang/Throwable;)Ljava/lang/Throwable;
    //   1789: athrow
    //   1790: aload #4
    //   1792: getstatic burp/Zz66.ZM : Ljava/lang/String;
    //   1795: getstatic burp/Zg6z.ZS : Ljava/lang/Object;
    //   1798: checkcast java/math/BigInteger
    //   1801: invokevirtual intValue : ()I
    //   1804: bipush #32
    //   1806: irem
    //   1807: invokestatic abs : (I)I
    //   1810: invokevirtual charAt : (I)C
    //   1813: invokevirtual append : (C)Ljava/lang/StringBuilder;
    //   1816: pop
    //   1817: iload_2
    //   1818: ifeq -> 2736
    //   1821: goto -> 1828
    //   1824: invokestatic a : (Ljava/lang/Throwable;)Ljava/lang/Throwable;
    //   1827: athrow
    //   1828: aload #4
    //   1830: getstatic burp/Zm1d.ZE : Ljava/lang/String;
    //   1833: getstatic burp/Zbnz.Zb : Ljava/lang/Object;
    //   1836: checkcast java/math/BigInteger
    //   1839: invokevirtual intValue : ()I
    //   1842: bipush #32
    //   1844: irem
    //   1845: invokestatic abs : (I)I
    //   1848: invokevirtual charAt : (I)C
    //   1851: invokevirtual append : (C)Ljava/lang/StringBuilder;
    //   1854: pop
    //   1855: iload_2
    //   1856: ifeq -> 2736
    //   1859: goto -> 1866
    //   1862: invokestatic a : (Ljava/lang/Throwable;)Ljava/lang/Throwable;
    //   1865: athrow
    //   1866: aload #4
    //   1868: getstatic burp/Zz0f.ZW : Ljava/lang/String;
    //   1871: getstatic burp/Zl_a.ZP : Ljava/lang/Object;
    //   1874: checkcast java/math/BigInteger
    //   1877: invokevirtual intValue : ()I
    //   1880: bipush #32
    //   1882: irem
    //   1883: invokestatic abs : (I)I
    //   1886: invokevirtual charAt : (I)C
    //   1889: invokevirtual append : (C)Ljava/lang/StringBuilder;
    //   1892: pop
    //   1893: iload_2
    //   1894: ifeq -> 2736
    //   1897: goto -> 1904
    //   1900: invokestatic a : (Ljava/lang/Throwable;)Ljava/lang/Throwable;
    //   1903: athrow
    //   1904: aload #4
    //   1906: getstatic burp/Zm69.ZE : Ljava/lang/String;
    //   1909: getstatic burp/Zl7b.ZK : Ljava/lang/Object;
    //   1912: checkcast java/math/BigInteger
    //   1915: invokevirtual intValue : ()I
    //   1918: bipush #32
    //   1920: irem
    //   1921: invokestatic abs : (I)I
    //   1924: invokevirtual charAt : (I)C
    //   1927: invokevirtual append : (C)Ljava/lang/StringBuilder;
    //   1930: pop
    //   1931: iload_2
    //   1932: ifeq -> 2736
    //   1935: goto -> 1942
    //   1938: invokestatic a : (Ljava/lang/Throwable;)Ljava/lang/Throwable;
    //   1941: athrow
    //   1942: aload #4
    //   1944: getstatic burp/Zgi9.Zv : Ljava/lang/String;
    //   1947: getstatic burp/Zmz.ZW : Ljava/lang/Object;
    //   1950: checkcast java/math/BigInteger
    //   1953: invokevirtual intValue : ()I
    //   1956: bipush #32
    //   1958: irem
    //   1959: invokestatic abs : (I)I
    //   1962: invokevirtual charAt : (I)C
    //   1965: invokevirtual append : (C)Ljava/lang/StringBuilder;
    //   1968: pop
    //   1969: iload_2
    //   1970: ifeq -> 2736
    //   1973: goto -> 1980
    //   1976: invokestatic a : (Ljava/lang/Throwable;)Ljava/lang/Throwable;
    //   1979: athrow
    //   1980: aload #4
    //   1982: getstatic burp/Zlc2.Zz : Ljava/lang/String;
    //   1985: getstatic burp/Zt81.ZY : Ljava/lang/Object;
    //   1988: checkcast java/math/BigInteger
    //   1991: invokevirtual intValue : ()I
    //   1994: bipush #32
    //   1996: irem
    //   1997: invokestatic abs : (I)I
    //   2000: invokevirtual charAt : (I)C
    //   2003: invokevirtual append : (C)Ljava/lang/StringBuilder;
    //   2006: pop
    //   2007: iload_2
    //   2008: ifeq -> 2736
    //   2011: goto -> 2018
    //   2014: invokestatic a : (Ljava/lang/Throwable;)Ljava/lang/Throwable;
    //   2017: athrow
    //   2018: aload #4
    //   2020: getstatic burp/Zttd.Ze : Ljava/lang/String;
    //   2023: getstatic burp/Zlt1.ZH : Ljava/lang/Object;
    //   2026: checkcast java/math/BigInteger
    //   2029: invokevirtual intValue : ()I
    //   2032: bipush #32
    //   2034: irem
    //   2035: invokestatic abs : (I)I
    //   2038: invokevirtual charAt : (I)C
    //   2041: invokevirtual append : (C)Ljava/lang/StringBuilder;
    //   2044: pop
    //   2045: iload_2
    //   2046: ifeq -> 2736
    //   2049: goto -> 2056
    //   2052: invokestatic a : (Ljava/lang/Throwable;)Ljava/lang/Throwable;
    //   2055: athrow
    //   2056: aload #4
    //   2058: getstatic burp/Zm3x.Zu : Ljava/lang/String;
    //   2061: getstatic burp/Zrt3.ZG : Ljava/lang/Object;
    //   2064: checkcast java/math/BigInteger
    //   2067: invokevirtual intValue : ()I
    //   2070: bipush #32
    //   2072: irem
    //   2073: invokestatic abs : (I)I
    //   2076: invokevirtual charAt : (I)C
    //   2079: invokevirtual append : (C)Ljava/lang/StringBuilder;
    //   2082: pop
    //   2083: iload_2
    //   2084: ifeq -> 2736
    //   2087: goto -> 2094
    //   2090: invokestatic a : (Ljava/lang/Throwable;)Ljava/lang/Throwable;
    //   2093: athrow
    //   2094: aload #4
    //   2096: getstatic burp/Zml9.Zw : Ljava/lang/String;
    //   2099: getstatic burp/Zz66.ZQ : Ljava/lang/Object;
    //   2102: checkcast java/math/BigInteger
    //   2105: invokevirtual intValue : ()I
    //   2108: bipush #32
    //   2110: irem
    //   2111: invokestatic abs : (I)I
    //   2114: invokevirtual charAt : (I)C
    //   2117: invokevirtual append : (C)Ljava/lang/StringBuilder;
    //   2120: pop
    //   2121: iload_2
    //   2122: ifeq -> 2736
    //   2125: goto -> 2132
    //   2128: invokestatic a : (Ljava/lang/Throwable;)Ljava/lang/Throwable;
    //   2131: athrow
    //   2132: aload #4
    //   2134: getstatic burp/Zlsg.Zs : Ljava/lang/String;
    //   2137: getstatic burp/Zrex.Zr : Ljava/lang/Object;
    //   2140: checkcast java/math/BigInteger
    //   2143: invokevirtual intValue : ()I
    //   2146: bipush #32
    //   2148: irem
    //   2149: invokestatic abs : (I)I
    //   2152: invokevirtual charAt : (I)C
    //   2155: invokevirtual append : (C)Ljava/lang/StringBuilder;
    //   2158: pop
    //   2159: iload_2
    //   2160: ifeq -> 2736
    //   2163: goto -> 2170
    //   2166: invokestatic a : (Ljava/lang/Throwable;)Ljava/lang/Throwable;
    //   2169: athrow
    //   2170: aload #4
    //   2172: getstatic burp/Zs3m.Zl : Ljava/lang/String;
    //   2175: getstatic burp/Zb3r.ZI : Ljava/lang/Object;
    //   2178: checkcast java/math/BigInteger
    //   2181: invokevirtual intValue : ()I
    //   2184: bipush #32
    //   2186: irem
    //   2187: invokestatic abs : (I)I
    //   2190: invokevirtual charAt : (I)C
    //   2193: invokevirtual append : (C)Ljava/lang/StringBuilder;
    //   2196: pop
    //   2197: iload_2
    //   2198: ifeq -> 2736
    //   2201: goto -> 2208
    //   2204: invokestatic a : (Ljava/lang/Throwable;)Ljava/lang/Throwable;
    //   2207: athrow
    //   2208: aload #4
    //   2210: getstatic burp/Zg4l.Z_ : Ljava/lang/String;
    //   2213: getstatic burp/Zm8j.Zj : Ljava/lang/Object;
    //   2216: checkcast java/math/BigInteger
    //   2219: invokevirtual intValue : ()I
    //   2222: bipush #32
    //   2224: irem
    //   2225: invokestatic abs : (I)I
    //   2228: invokevirtual charAt : (I)C
    //   2231: invokevirtual append : (C)Ljava/lang/StringBuilder;
    //   2234: pop
    //   2235: iload_2
    //   2236: ifeq -> 2736
    //   2239: goto -> 2246
    //   2242: invokestatic a : (Ljava/lang/Throwable;)Ljava/lang/Throwable;
    //   2245: athrow
    //   2246: aload #4
    //   2248: getstatic burp/Ze4g.Zk : Ljava/lang/String;
    //   2251: getstatic burp/Zex0.Ze : Ljava/lang/Object;
    //   2254: checkcast java/math/BigInteger
    //   2257: invokevirtual intValue : ()I
    //   2260: bipush #32
    //   2262: irem
    //   2263: invokestatic abs : (I)I
    //   2266: invokevirtual charAt : (I)C
    //   2269: invokevirtual append : (C)Ljava/lang/StringBuilder;
    //   2272: pop
    //   2273: iload_2
    //   2274: ifeq -> 2736
    //   2277: goto -> 2284
    //   2280: invokestatic a : (Ljava/lang/Throwable;)Ljava/lang/Throwable;
    //   2283: athrow
    //   2284: aload #4
    //   2286: getstatic burp/Zz41.Zc : Ljava/lang/String;
    //   2289: getstatic burp/Zr60.Ze : Ljava/lang/Object;
    //   2292: checkcast java/math/BigInteger
    //   2295: invokevirtual intValue : ()I
    //   2298: bipush #32
    //   2300: irem
    //   2301: invokestatic abs : (I)I
    //   2304: invokevirtual charAt : (I)C
    //   2307: invokevirtual append : (C)Ljava/lang/StringBuilder;
    //   2310: pop
    //   2311: iload_2
    //   2312: ifeq -> 2736
    //   2315: goto -> 2322
    //   2318: invokestatic a : (Ljava/lang/Throwable;)Ljava/lang/Throwable;
    //   2321: athrow
    //   2322: aload #4
    //   2324: getstatic burp/Zmz.Zp : Ljava/lang/String;
    //   2327: getstatic burp/Zm0d.Zz : Ljava/lang/Object;
    //   2330: checkcast java/math/BigInteger
    //   2333: invokevirtual intValue : ()I
    //   2336: bipush #32
    //   2338: irem
    //   2339: invokestatic abs : (I)I
    //   2342: invokevirtual charAt : (I)C
    //   2345: invokevirtual append : (C)Ljava/lang/StringBuilder;
    //   2348: pop
    //   2349: iload_2
    //   2350: ifeq -> 2736
    //   2353: goto -> 2360
    //   2356: invokestatic a : (Ljava/lang/Throwable;)Ljava/lang/Throwable;
    //   2359: athrow
    //   2360: aload #4
    //   2362: getstatic burp/Zl7x.Zo : Ljava/lang/String;
    //   2365: getstatic burp/Ze7e.Z_ : Ljava/lang/Object;
    //   2368: checkcast java/math/BigInteger
    //   2371: invokevirtual intValue : ()I
    //   2374: bipush #32
    //   2376: irem
    //   2377: invokestatic abs : (I)I
    //   2380: invokevirtual charAt : (I)C
    //   2383: invokevirtual append : (C)Ljava/lang/StringBuilder;
    //   2386: pop
    //   2387: iload_2
    //   2388: ifeq -> 2736
    //   2391: goto -> 2398
    //   2394: invokestatic a : (Ljava/lang/Throwable;)Ljava/lang/Throwable;
    //   2397: athrow
    //   2398: aload #4
    //   2400: getstatic burp/Zma0.ZP : Ljava/lang/String;
    //   2403: getstatic burp/Zbun.ZH : Ljava/lang/Object;
    //   2406: checkcast java/math/BigInteger
    //   2409: invokevirtual intValue : ()I
    //   2412: bipush #32
    //   2414: irem
    //   2415: invokestatic abs : (I)I
    //   2418: invokevirtual charAt : (I)C
    //   2421: invokevirtual append : (C)Ljava/lang/StringBuilder;
    //   2424: pop
    //   2425: iload_2
    //   2426: ifeq -> 2736
    //   2429: goto -> 2436
    //   2432: invokestatic a : (Ljava/lang/Throwable;)Ljava/lang/Throwable;
    //   2435: athrow
    //   2436: aload #4
    //   2438: getstatic burp/Zlid.ZU : Ljava/lang/String;
    //   2441: getstatic burp/Zg7u.Zh : Ljava/lang/Object;
    //   2444: checkcast java/math/BigInteger
    //   2447: invokevirtual intValue : ()I
    //   2450: bipush #32
    //   2452: irem
    //   2453: invokestatic abs : (I)I
    //   2456: invokevirtual charAt : (I)C
    //   2459: invokevirtual append : (C)Ljava/lang/StringBuilder;
    //   2462: pop
    //   2463: iload_2
    //   2464: ifeq -> 2736
    //   2467: goto -> 2474
    //   2470: invokestatic a : (Ljava/lang/Throwable;)Ljava/lang/Throwable;
    //   2473: athrow
    //   2474: aload #4
    //   2476: getstatic burp/Zlbd.Zq : Ljava/lang/String;
    //   2479: getstatic burp/Zegj.ZT : Ljava/lang/Object;
    //   2482: checkcast java/math/BigInteger
    //   2485: invokevirtual intValue : ()I
    //   2488: bipush #32
    //   2490: irem
    //   2491: invokestatic abs : (I)I
    //   2494: invokevirtual charAt : (I)C
    //   2497: invokevirtual append : (C)Ljava/lang/StringBuilder;
    //   2500: pop
    //   2501: iload_2
    //   2502: ifeq -> 2736
    //   2505: goto -> 2512
    //   2508: invokestatic a : (Ljava/lang/Throwable;)Ljava/lang/Throwable;
    //   2511: athrow
    //   2512: aload #4
    //   2514: getstatic burp/Zkjj.ZT : Ljava/lang/String;
    //   2517: getstatic burp/Zegv.ZL : Ljava/lang/Object;
    //   2520: checkcast java/math/BigInteger
    //   2523: invokevirtual intValue : ()I
    //   2526: bipush #32
    //   2528: irem
    //   2529: invokestatic abs : (I)I
    //   2532: invokevirtual charAt : (I)C
    //   2535: invokevirtual append : (C)Ljava/lang/StringBuilder;
    //   2538: pop
    //   2539: iload_2
    //   2540: ifeq -> 2736
    //   2543: goto -> 2550
    //   2546: invokestatic a : (Ljava/lang/Throwable;)Ljava/lang/Throwable;
    //   2549: athrow
    //   2550: aload #4
    //   2552: getstatic burp/Zm8j.Zp : Ljava/lang/String;
    //   2555: getstatic burp/Zm69.Zg : Ljava/lang/Object;
    //   2558: checkcast java/math/BigInteger
    //   2561: invokevirtual intValue : ()I
    //   2564: bipush #32
    //   2566: irem
    //   2567: invokestatic abs : (I)I
    //   2570: invokevirtual charAt : (I)C
    //   2573: invokevirtual append : (C)Ljava/lang/StringBuilder;
    //   2576: pop
    //   2577: iload_2
    //   2578: ifeq -> 2736
    //   2581: goto -> 2588
    //   2584: invokestatic a : (Ljava/lang/Throwable;)Ljava/lang/Throwable;
    //   2587: athrow
    //   2588: aload #4
    //   2590: getstatic burp/Zsbo.Zg : Ljava/lang/String;
    //   2593: getstatic burp/Zrle.Zl : Ljava/lang/Object;
    //   2596: checkcast java/math/BigInteger
    //   2599: invokevirtual intValue : ()I
    //   2602: bipush #32
    //   2604: irem
    //   2605: invokestatic abs : (I)I
    //   2608: invokevirtual charAt : (I)C
    //   2611: invokevirtual append : (C)Ljava/lang/StringBuilder;
    //   2614: pop
    //   2615: iload_2
    //   2616: ifeq -> 2736
    //   2619: goto -> 2626
    //   2622: invokestatic a : (Ljava/lang/Throwable;)Ljava/lang/Throwable;
    //   2625: athrow
    //   2626: aload #4
    //   2628: getstatic burp/Zlcc.Zw : Ljava/lang/String;
    //   2631: getstatic burp/Ztr5.ZZ : Ljava/lang/Object;
    //   2634: checkcast java/math/BigInteger
    //   2637: invokevirtual intValue : ()I
    //   2640: bipush #32
    //   2642: irem
    //   2643: invokestatic abs : (I)I
    //   2646: invokevirtual charAt : (I)C
    //   2649: invokevirtual append : (C)Ljava/lang/StringBuilder;
    //   2652: pop
    //   2653: iload_2
    //   2654: ifeq -> 2736
    //   2657: goto -> 2664
    //   2660: invokestatic a : (Ljava/lang/Throwable;)Ljava/lang/Throwable;
    //   2663: athrow
    //   2664: aload #4
    //   2666: getstatic burp/Zexl.Zs : Ljava/lang/String;
    //   2669: getstatic burp/Zd9.Zr : Ljava/lang/Object;
    //   2672: checkcast java/math/BigInteger
    //   2675: invokevirtual intValue : ()I
    //   2678: bipush #32
    //   2680: irem
    //   2681: invokestatic abs : (I)I
    //   2684: invokevirtual charAt : (I)C
    //   2687: invokevirtual append : (C)Ljava/lang/StringBuilder;
    //   2690: pop
    //   2691: iload_2
    //   2692: ifeq -> 2736
    //   2695: goto -> 2702
    //   2698: invokestatic a : (Ljava/lang/Throwable;)Ljava/lang/Throwable;
    //   2701: athrow
    //   2702: aload #4
    //   2704: getstatic burp/Zbze.ZK : Ljava/lang/String;
    //   2707: getstatic burp/Zm3x.ZM : Ljava/lang/Object;
    //   2710: checkcast java/math/BigInteger
    //   2713: invokevirtual intValue : ()I
    //   2716: bipush #32
    //   2718: irem
    //   2719: invokestatic abs : (I)I
    //   2722: invokevirtual charAt : (I)C
    //   2725: invokevirtual append : (C)Ljava/lang/StringBuilder;
    //   2728: pop
    //   2729: goto -> 2736
    //   2732: invokestatic a : (Ljava/lang/Throwable;)Ljava/lang/Throwable;
    //   2735: athrow
    //   2736: iinc #5, 1
    //   2739: iload_2
    //   2740: ifeq -> 1374
    //   2743: aload #4
    //   2745: invokevirtual toString : ()Ljava/lang/String;
    //   2748: putstatic burp/Zlwm.Zj : Ljava/lang/String;
    //   2751: getstatic burp/Zsbo.ZG : Ljava/lang/Object;
    //   2754: checkcast java/math/BigInteger
    //   2757: invokevirtual toByteArray : ()[B
    //   2760: astore #5
    //   2762: bipush #64
    //   2764: newarray byte
    //   2766: dup
    //   2767: iconst_0
    //   2768: bipush #-128
    //   2770: bastore
    //   2771: dup
    //   2772: iconst_1
    //   2773: iconst_0
    //   2774: bastore
    //   2775: dup
    //   2776: iconst_2
    //   2777: iconst_0
    //   2778: bastore
    //   2779: dup
    //   2780: iconst_3
    //   2781: iconst_0
    //   2782: bastore
    //   2783: dup
    //   2784: iconst_4
    //   2785: iconst_0
    //   2786: bastore
    //   2787: dup
    //   2788: iconst_5
    //   2789: iconst_0
    //   2790: bastore
    //   2791: dup
    //   2792: bipush #6
    //   2794: iconst_0
    //   2795: bastore
    //   2796: dup
    //   2797: bipush #7
    //   2799: iconst_0
    //   2800: bastore
    //   2801: dup
    //   2802: bipush #8
    //   2804: iconst_0
    //   2805: bastore
    //   2806: dup
    //   2807: bipush #9
    //   2809: iconst_0
    //   2810: bastore
    //   2811: dup
    //   2812: bipush #10
    //   2814: iconst_0
    //   2815: bastore
    //   2816: dup
    //   2817: bipush #11
    //   2819: iconst_0
    //   2820: bastore
    //   2821: dup
    //   2822: bipush #12
    //   2824: iconst_0
    //   2825: bastore
    //   2826: dup
    //   2827: bipush #13
    //   2829: iconst_0
    //   2830: bastore
    //   2831: dup
    //   2832: bipush #14
    //   2834: iconst_0
    //   2835: bastore
    //   2836: dup
    //   2837: bipush #15
    //   2839: iconst_0
    //   2840: bastore
    //   2841: dup
    //   2842: bipush #16
    //   2844: iconst_0
    //   2845: bastore
    //   2846: dup
    //   2847: bipush #17
    //   2849: iconst_0
    //   2850: bastore
    //   2851: dup
    //   2852: bipush #18
    //   2854: iconst_0
    //   2855: bastore
    //   2856: dup
    //   2857: bipush #19
    //   2859: iconst_0
    //   2860: bastore
    //   2861: dup
    //   2862: bipush #20
    //   2864: iconst_0
    //   2865: bastore
    //   2866: dup
    //   2867: bipush #21
    //   2869: iconst_0
    //   2870: bastore
    //   2871: dup
    //   2872: bipush #22
    //   2874: iconst_0
    //   2875: bastore
    //   2876: dup
    //   2877: bipush #23
    //   2879: iconst_0
    //   2880: bastore
    //   2881: dup
    //   2882: bipush #24
    //   2884: iconst_0
    //   2885: bastore
    //   2886: dup
    //   2887: bipush #25
    //   2889: iconst_0
    //   2890: bastore
    //   2891: dup
    //   2892: bipush #26
    //   2894: iconst_0
    //   2895: bastore
    //   2896: dup
    //   2897: bipush #27
    //   2899: iconst_0
    //   2900: bastore
    //   2901: dup
    //   2902: bipush #28
    //   2904: iconst_0
    //   2905: bastore
    //   2906: dup
    //   2907: bipush #29
    //   2909: iconst_0
    //   2910: bastore
    //   2911: dup
    //   2912: bipush #30
    //   2914: iconst_0
    //   2915: bastore
    //   2916: dup
    //   2917: bipush #31
    //   2919: iconst_0
    //   2920: bastore
    //   2921: dup
    //   2922: bipush #32
    //   2924: iconst_0
    //   2925: bastore
    //   2926: dup
    //   2927: bipush #33
    //   2929: iconst_0
    //   2930: bastore
    //   2931: dup
    //   2932: bipush #34
    //   2934: iconst_0
    //   2935: bastore
    //   2936: dup
    //   2937: bipush #35
    //   2939: iconst_0
    //   2940: bastore
    //   2941: dup
    //   2942: bipush #36
    //   2944: iconst_0
    //   2945: bastore
    //   2946: dup
    //   2947: bipush #37
    //   2949: iconst_0
    //   2950: bastore
    //   2951: dup
    //   2952: bipush #38
    //   2954: iconst_0
    //   2955: bastore
    //   2956: dup
    //   2957: bipush #39
    //   2959: iconst_0
    //   2960: bastore
    //   2961: dup
    //   2962: bipush #40
    //   2964: iconst_0
    //   2965: bastore
    //   2966: dup
    //   2967: bipush #41
    //   2969: iconst_0
    //   2970: bastore
    //   2971: dup
    //   2972: bipush #42
    //   2974: iconst_0
    //   2975: bastore
    //   2976: dup
    //   2977: bipush #43
    //   2979: iconst_0
    //   2980: bastore
    //   2981: dup
    //   2982: bipush #44
    //   2984: iconst_0
    //   2985: bastore
    //   2986: dup
    //   2987: bipush #45
    //   2989: iconst_0
    //   2990: bastore
    //   2991: dup
    //   2992: bipush #46
    //   2994: iconst_0
    //   2995: bastore
    //   2996: dup
    //   2997: bipush #47
    //   2999: iconst_0
    //   3000: bastore
    //   3001: dup
    //   3002: bipush #48
    //   3004: iconst_0
    //   3005: bastore
    //   3006: dup
    //   3007: bipush #49
    //   3009: iconst_0
    //   3010: bastore
    //   3011: dup
    //   3012: bipush #50
    //   3014: iconst_0
    //   3015: bastore
    //   3016: dup
    //   3017: bipush #51
    //   3019: iconst_0
    //   3020: bastore
    //   3021: dup
    //   3022: bipush #52
    //   3024: iconst_0
    //   3025: bastore
    //   3026: dup
    //   3027: bipush #53
    //   3029: iconst_0
    //   3030: bastore
    //   3031: dup
    //   3032: bipush #54
    //   3034: iconst_0
    //   3035: bastore
    //   3036: dup
    //   3037: bipush #55
    //   3039: iconst_0
    //   3040: bastore
    //   3041: dup
    //   3042: bipush #56
    //   3044: iconst_0
    //   3045: bastore
    //   3046: dup
    //   3047: bipush #57
    //   3049: iconst_0
    //   3050: bastore
    //   3051: dup
    //   3052: bipush #58
    //   3054: iconst_0
    //   3055: bastore
    //   3056: dup
    //   3057: bipush #59
    //   3059: iconst_0
    //   3060: bastore
    //   3061: dup
    //   3062: bipush #60
    //   3064: iconst_0
    //   3065: bastore
    //   3066: dup
    //   3067: bipush #61
    //   3069: iconst_0
    //   3070: bastore
    //   3071: dup
    //   3072: bipush #62
    //   3074: iconst_0
    //   3075: bastore
    //   3076: dup
    //   3077: bipush #63
    //   3079: iconst_0
    //   3080: bastore
    //   3081: astore #7
    //   3083: bipush #64
    //   3085: newarray int
    //   3087: dup
    //   3088: iconst_0
    //   3089: ldc 1116352408
    //   3091: iastore
    //   3092: dup
    //   3093: iconst_1
    //   3094: ldc 1899447441
    //   3096: iastore
    //   3097: dup
    //   3098: iconst_2
    //   3099: ldc -1245643825
    //   3101: iastore
    //   3102: dup
    //   3103: iconst_3
    //   3104: ldc -373957723
    //   3106: iastore
    //   3107: dup
    //   3108: iconst_4
    //   3109: ldc 961987163
    //   3111: iastore
    //   3112: dup
    //   3113: iconst_5
    //   3114: ldc 1508970993
    //   3116: iastore
    //   3117: dup
    //   3118: bipush #6
    //   3120: ldc -1841331548
    //   3122: iastore
    //   3123: dup
    //   3124: bipush #7
    //   3126: ldc -1424204075
    //   3128: iastore
    //   3129: dup
    //   3130: bipush #8
    //   3132: ldc -670586216
    //   3134: iastore
    //   3135: dup
    //   3136: bipush #9
    //   3138: ldc 310598401
    //   3140: iastore
    //   3141: dup
    //   3142: bipush #10
    //   3144: ldc 607225278
    //   3146: iastore
    //   3147: dup
    //   3148: bipush #11
    //   3150: ldc 1426881987
    //   3152: iastore
    //   3153: dup
    //   3154: bipush #12
    //   3156: ldc 1925078388
    //   3158: iastore
    //   3159: dup
    //   3160: bipush #13
    //   3162: ldc -2132889090
    //   3164: iastore
    //   3165: dup
    //   3166: bipush #14
    //   3168: ldc -1680079193
    //   3170: iastore
    //   3171: dup
    //   3172: bipush #15
    //   3174: ldc -1046744716
    //   3176: iastore
    //   3177: dup
    //   3178: bipush #16
    //   3180: ldc -459576895
    //   3182: iastore
    //   3183: dup
    //   3184: bipush #17
    //   3186: ldc -272742522
    //   3188: iastore
    //   3189: dup
    //   3190: bipush #18
    //   3192: ldc 264347078
    //   3194: iastore
    //   3195: dup
    //   3196: bipush #19
    //   3198: ldc 604807628
    //   3200: iastore
    //   3201: dup
    //   3202: bipush #20
    //   3204: ldc 770255983
    //   3206: iastore
    //   3207: dup
    //   3208: bipush #21
    //   3210: ldc 1249150122
    //   3212: iastore
    //   3213: dup
    //   3214: bipush #22
    //   3216: ldc 1555081692
    //   3218: iastore
    //   3219: dup
    //   3220: bipush #23
    //   3222: ldc 1996064986
    //   3224: iastore
    //   3225: dup
    //   3226: bipush #24
    //   3228: ldc -1740746414
    //   3230: iastore
    //   3231: dup
    //   3232: bipush #25
    //   3234: ldc -1473132947
    //   3236: iastore
    //   3237: dup
    //   3238: bipush #26
    //   3240: ldc -1341970488
    //   3242: iastore
    //   3243: dup
    //   3244: bipush #27
    //   3246: ldc -1084653625
    //   3248: iastore
    //   3249: dup
    //   3250: bipush #28
    //   3252: ldc -958395405
    //   3254: iastore
    //   3255: dup
    //   3256: bipush #29
    //   3258: ldc -710438585
    //   3260: iastore
    //   3261: dup
    //   3262: bipush #30
    //   3264: ldc 113926993
    //   3266: iastore
    //   3267: dup
    //   3268: bipush #31
    //   3270: ldc 338241895
    //   3272: iastore
    //   3273: dup
    //   3274: bipush #32
    //   3276: ldc 666307205
    //   3278: iastore
    //   3279: dup
    //   3280: bipush #33
    //   3282: ldc 773529912
    //   3284: iastore
    //   3285: dup
    //   3286: bipush #34
    //   3288: ldc 1294757372
    //   3290: iastore
    //   3291: dup
    //   3292: bipush #35
    //   3294: ldc 1396182291
    //   3296: iastore
    //   3297: dup
    //   3298: bipush #36
    //   3300: ldc 1695183700
    //   3302: iastore
    //   3303: dup
    //   3304: bipush #37
    //   3306: ldc 1986661051
    //   3308: iastore
    //   3309: dup
    //   3310: bipush #38
    //   3312: ldc -2117940946
    //   3314: iastore
    //   3315: dup
    //   3316: bipush #39
    //   3318: ldc -1838011259
    //   3320: iastore
    //   3321: dup
    //   3322: bipush #40
    //   3324: ldc -1564481375
    //   3326: iastore
    //   3327: dup
    //   3328: bipush #41
    //   3330: ldc -1474664885
    //   3332: iastore
    //   3333: dup
    //   3334: bipush #42
    //   3336: ldc -1035236496
    //   3338: iastore
    //   3339: dup
    //   3340: bipush #43
    //   3342: ldc -949202525
    //   3344: iastore
    //   3345: dup
    //   3346: bipush #44
    //   3348: ldc -778901479
    //   3350: iastore
    //   3351: dup
    //   3352: bipush #45
    //   3354: ldc -694614492
    //   3356: iastore
    //   3357: dup
    //   3358: bipush #46
    //   3360: ldc -200395387
    //   3362: iastore
    //   3363: dup
    //   3364: bipush #47
    //   3366: ldc 275423344
    //   3368: iastore
    //   3369: dup
    //   3370: bipush #48
    //   3372: ldc 430227734
    //   3374: iastore
    //   3375: dup
    //   3376: bipush #49
    //   3378: ldc 506948616
    //   3380: iastore
    //   3381: dup
    //   3382: bipush #50
    //   3384: ldc 659060556
    //   3386: iastore
    //   3387: dup
    //   3388: bipush #51
    //   3390: ldc 883997877
    //   3392: iastore
    //   3393: dup
    //   3394: bipush #52
    //   3396: ldc 958139571
    //   3398: iastore
    //   3399: dup
    //   3400: bipush #53
    //   3402: ldc 1322822218
    //   3404: iastore
    //   3405: dup
    //   3406: bipush #54
    //   3408: ldc 1537002063
    //   3410: iastore
    //   3411: dup
    //   3412: bipush #55
    //   3414: ldc 1747873779
    //   3416: iastore
    //   3417: dup
    //   3418: bipush #56
    //   3420: ldc 1955562222
    //   3422: iastore
    //   3423: dup
    //   3424: bipush #57
    //   3426: ldc 2024104815
    //   3428: iastore
    //   3429: dup
    //   3430: bipush #58
    //   3432: ldc -2067236844
    //   3434: iastore
    //   3435: dup
    //   3436: bipush #59
    //   3438: ldc -1933114872
    //   3440: iastore
    //   3441: dup
    //   3442: bipush #60
    //   3444: ldc -1866530822
    //   3446: iastore
    //   3447: dup
    //   3448: bipush #61
    //   3450: ldc -1538233109
    //   3452: iastore
    //   3453: dup
    //   3454: bipush #62
    //   3456: ldc -1090935817
    //   3458: iastore
    //   3459: dup
    //   3460: bipush #63
    //   3462: ldc -965641998
    //   3464: iastore
    //   3465: astore #8
    //   3467: iconst_2
    //   3468: newarray int
    //   3470: dup
    //   3471: iconst_0
    //   3472: iconst_0
    //   3473: iastore
    //   3474: dup
    //   3475: iconst_1
    //   3476: iconst_0
    //   3477: iastore
    //   3478: astore #9
    //   3480: bipush #8
    //   3482: newarray int
    //   3484: dup
    //   3485: iconst_0
    //   3486: ldc 1779033703
    //   3488: iastore
    //   3489: dup
    //   3490: iconst_1
    //   3491: ldc -1150833019
    //   3493: iastore
    //   3494: dup
    //   3495: iconst_2
    //   3496: ldc 1013904242
    //   3498: iastore
    //   3499: dup
    //   3500: iconst_3
    //   3501: ldc -1521486534
    //   3503: iastore
    //   3504: dup
    //   3505: iconst_4
    //   3506: ldc 1359893119
    //   3508: iastore
    //   3509: dup
    //   3510: iconst_5
    //   3511: ldc -1694144372
    //   3513: iastore
    //   3514: dup
    //   3515: bipush #6
    //   3517: ldc 528734635
    //   3519: iastore
    //   3520: dup
    //   3521: bipush #7
    //   3523: ldc 1541459225
    //   3525: iastore
    //   3526: astore #10
    //   3528: bipush #64
    //   3530: newarray byte
    //   3532: astore #11
    //   3534: bipush #64
    //   3536: newarray byte
    //   3538: astore #12
    //   3540: aload #5
    //   3542: arraylength
    //   3543: istore #13
    //   3545: aload #9
    //   3547: iconst_0
    //   3548: iaload
    //   3549: bipush #63
    //   3551: iand
    //   3552: istore #14
    //   3554: aload #9
    //   3556: iconst_0
    //   3557: dup2
    //   3558: iaload
    //   3559: iload #13
    //   3561: iadd
    //   3562: iastore
    //   3563: aload #9
    //   3565: iconst_0
    //   3566: dup2
    //   3567: iaload
    //   3568: iconst_m1
    //   3569: iand
    //   3570: iastore
    //   3571: aload #9
    //   3573: iconst_0
    //   3574: iaload
    //   3575: iload #13
    //   3577: if_icmpge -> 3595
    //   3580: aload #9
    //   3582: iconst_1
    //   3583: dup2
    //   3584: iaload
    //   3585: iconst_1
    //   3586: iadd
    //   3587: iastore
    //   3588: goto -> 3595
    //   3591: invokestatic a : (Ljava/lang/Throwable;)Ljava/lang/Throwable;
    //   3594: athrow
    //   3595: iconst_0
    //   3596: istore #15
    //   3598: iload #13
    //   3600: bipush #64
    //   3602: if_icmplt -> 4212
    //   3605: iconst_0
    //   3606: istore #16
    //   3608: iload #16
    //   3610: bipush #64
    //   3612: if_icmpge -> 3635
    //   3615: aload #12
    //   3617: iload #16
    //   3619: aload #5
    //   3621: iload #15
    //   3623: iload #16
    //   3625: iadd
    //   3626: baload
    //   3627: bastore
    //   3628: iinc #16, 1
    //   3631: iload_2
    //   3632: ifeq -> 3608
    //   3635: bipush #64
    //   3637: newarray int
    //   3639: astore #16
    //   3641: bipush #8
    //   3643: newarray int
    //   3645: astore #17
    //   3647: iconst_0
    //   3648: istore #18
    //   3650: iload #18
    //   3652: bipush #8
    //   3654: if_icmpge -> 3674
    //   3657: aload #17
    //   3659: iload #18
    //   3661: aload #10
    //   3663: iload #18
    //   3665: iaload
    //   3666: iastore
    //   3667: iinc #18, 1
    //   3670: iload_2
    //   3671: ifeq -> 3650
    //   3674: iconst_0
    //   3675: istore #18
    //   3677: iload #18
    //   3679: bipush #64
    //   3681: if_icmpge -> 4172
    //   3684: iload #18
    //   3686: bipush #16
    //   3688: if_icmpge -> 3769
    //   3691: aload #16
    //   3693: iload #18
    //   3695: aload #12
    //   3697: iconst_4
    //   3698: iload #18
    //   3700: imul
    //   3701: baload
    //   3702: sipush #255
    //   3705: iand
    //   3706: bipush #24
    //   3708: ishl
    //   3709: aload #12
    //   3711: iconst_4
    //   3712: iload #18
    //   3714: imul
    //   3715: iconst_1
    //   3716: iadd
    //   3717: baload
    //   3718: sipush #255
    //   3721: iand
    //   3722: bipush #16
    //   3724: ishl
    //   3725: ior
    //   3726: aload #12
    //   3728: iconst_4
    //   3729: iload #18
    //   3731: imul
    //   3732: iconst_2
    //   3733: iadd
    //   3734: baload
    //   3735: sipush #255
    //   3738: iand
    //   3739: bipush #8
    //   3741: ishl
    //   3742: ior
    //   3743: aload #12
    //   3745: iconst_4
    //   3746: iload #18
    //   3748: imul
    //   3749: iconst_3
    //   3750: iadd
    //   3751: baload
    //   3752: sipush #255
    //   3755: iand
    //   3756: ior
    //   3757: iastore
    //   3758: iload_2
    //   3759: ifeq -> 3912
    //   3762: goto -> 3769
    //   3765: invokestatic a : (Ljava/lang/Throwable;)Ljava/lang/Throwable;
    //   3768: athrow
    //   3769: aload #16
    //   3771: iload #18
    //   3773: aload #16
    //   3775: iload #18
    //   3777: iconst_2
    //   3778: isub
    //   3779: iaload
    //   3780: bipush #17
    //   3782: iushr
    //   3783: aload #16
    //   3785: iload #18
    //   3787: iconst_2
    //   3788: isub
    //   3789: iaload
    //   3790: bipush #15
    //   3792: ishl
    //   3793: ior
    //   3794: aload #16
    //   3796: iload #18
    //   3798: iconst_2
    //   3799: isub
    //   3800: iaload
    //   3801: bipush #19
    //   3803: iushr
    //   3804: aload #16
    //   3806: iload #18
    //   3808: iconst_2
    //   3809: isub
    //   3810: iaload
    //   3811: bipush #13
    //   3813: ishl
    //   3814: ior
    //   3815: ixor
    //   3816: aload #16
    //   3818: iload #18
    //   3820: iconst_2
    //   3821: isub
    //   3822: iaload
    //   3823: bipush #10
    //   3825: iushr
    //   3826: ixor
    //   3827: aload #16
    //   3829: iload #18
    //   3831: bipush #7
    //   3833: isub
    //   3834: iaload
    //   3835: iadd
    //   3836: aload #16
    //   3838: iload #18
    //   3840: bipush #15
    //   3842: isub
    //   3843: iaload
    //   3844: bipush #7
    //   3846: iushr
    //   3847: aload #16
    //   3849: iload #18
    //   3851: bipush #15
    //   3853: isub
    //   3854: iaload
    //   3855: bipush #25
    //   3857: ishl
    //   3858: ior
    //   3859: aload #16
    //   3861: iload #18
    //   3863: bipush #15
    //   3865: isub
    //   3866: iaload
    //   3867: bipush #18
    //   3869: iushr
    //   3870: aload #16
    //   3872: iload #18
    //   3874: bipush #15
    //   3876: isub
    //   3877: iaload
    //   3878: bipush #14
    //   3880: ishl
    //   3881: ior
    //   3882: ixor
    //   3883: aload #16
    //   3885: iload #18
    //   3887: bipush #15
    //   3889: isub
    //   3890: iaload
    //   3891: iconst_3
    //   3892: iushr
    //   3893: ixor
    //   3894: iadd
    //   3895: aload #16
    //   3897: iload #18
    //   3899: bipush #16
    //   3901: isub
    //   3902: iaload
    //   3903: iadd
    //   3904: iastore
    //   3905: goto -> 3912
    //   3908: invokestatic a : (Ljava/lang/Throwable;)Ljava/lang/Throwable;
    //   3911: athrow
    //   3912: aload #17
    //   3914: bipush #7
    //   3916: iaload
    //   3917: aload #17
    //   3919: iconst_4
    //   3920: iaload
    //   3921: bipush #6
    //   3923: iushr
    //   3924: aload #17
    //   3926: iconst_4
    //   3927: iaload
    //   3928: bipush #26
    //   3930: ishl
    //   3931: ior
    //   3932: aload #17
    //   3934: iconst_4
    //   3935: iaload
    //   3936: bipush #11
    //   3938: iushr
    //   3939: aload #17
    //   3941: iconst_4
    //   3942: iaload
    //   3943: bipush #21
    //   3945: ishl
    //   3946: ior
    //   3947: ixor
    //   3948: aload #17
    //   3950: iconst_4
    //   3951: iaload
    //   3952: bipush #25
    //   3954: iushr
    //   3955: aload #17
    //   3957: iconst_4
    //   3958: iaload
    //   3959: bipush #7
    //   3961: ishl
    //   3962: ior
    //   3963: ixor
    //   3964: iadd
    //   3965: aload #17
    //   3967: bipush #6
    //   3969: iaload
    //   3970: aload #17
    //   3972: iconst_4
    //   3973: iaload
    //   3974: aload #17
    //   3976: iconst_5
    //   3977: iaload
    //   3978: aload #17
    //   3980: bipush #6
    //   3982: iaload
    //   3983: ixor
    //   3984: iand
    //   3985: ixor
    //   3986: iadd
    //   3987: aload #8
    //   3989: iload #18
    //   3991: iaload
    //   3992: iadd
    //   3993: aload #16
    //   3995: iload #18
    //   3997: iaload
    //   3998: iadd
    //   3999: istore #19
    //   4001: aload #17
    //   4003: iconst_0
    //   4004: iaload
    //   4005: iconst_2
    //   4006: iushr
    //   4007: aload #17
    //   4009: iconst_0
    //   4010: iaload
    //   4011: bipush #30
    //   4013: ishl
    //   4014: ior
    //   4015: aload #17
    //   4017: iconst_0
    //   4018: iaload
    //   4019: bipush #13
    //   4021: iushr
    //   4022: aload #17
    //   4024: iconst_0
    //   4025: iaload
    //   4026: bipush #19
    //   4028: ishl
    //   4029: ior
    //   4030: ixor
    //   4031: aload #17
    //   4033: iconst_0
    //   4034: iaload
    //   4035: bipush #22
    //   4037: iushr
    //   4038: aload #17
    //   4040: iconst_0
    //   4041: iaload
    //   4042: bipush #10
    //   4044: ishl
    //   4045: ior
    //   4046: ixor
    //   4047: aload #17
    //   4049: iconst_0
    //   4050: iaload
    //   4051: aload #17
    //   4053: iconst_1
    //   4054: iaload
    //   4055: iand
    //   4056: aload #17
    //   4058: iconst_2
    //   4059: iaload
    //   4060: aload #17
    //   4062: iconst_0
    //   4063: iaload
    //   4064: aload #17
    //   4066: iconst_1
    //   4067: iaload
    //   4068: ior
    //   4069: iand
    //   4070: ior
    //   4071: iadd
    //   4072: istore #20
    //   4074: aload #17
    //   4076: iconst_3
    //   4077: dup2
    //   4078: iaload
    //   4079: iload #19
    //   4081: iadd
    //   4082: iastore
    //   4083: aload #17
    //   4085: bipush #7
    //   4087: iload #19
    //   4089: iload #20
    //   4091: iadd
    //   4092: iastore
    //   4093: aload #17
    //   4095: bipush #7
    //   4097: iaload
    //   4098: istore #19
    //   4100: aload #17
    //   4102: bipush #7
    //   4104: aload #17
    //   4106: bipush #6
    //   4108: iaload
    //   4109: iastore
    //   4110: aload #17
    //   4112: bipush #6
    //   4114: aload #17
    //   4116: iconst_5
    //   4117: iaload
    //   4118: iastore
    //   4119: aload #17
    //   4121: iconst_5
    //   4122: aload #17
    //   4124: iconst_4
    //   4125: iaload
    //   4126: iastore
    //   4127: aload #17
    //   4129: iconst_4
    //   4130: aload #17
    //   4132: iconst_3
    //   4133: iaload
    //   4134: iastore
    //   4135: aload #17
    //   4137: iconst_3
    //   4138: aload #17
    //   4140: iconst_2
    //   4141: iaload
    //   4142: iastore
    //   4143: aload #17
    //   4145: iconst_2
    //   4146: aload #17
    //   4148: iconst_1
    //   4149: iaload
    //   4150: iastore
    //   4151: aload #17
    //   4153: iconst_1
    //   4154: aload #17
    //   4156: iconst_0
    //   4157: iaload
    //   4158: iastore
    //   4159: aload #17
    //   4161: iconst_0
    //   4162: iload #19
    //   4164: iastore
    //   4165: iinc #18, 1
    //   4168: iload_2
    //   4169: ifeq -> 3677
    //   4172: iconst_0
    //   4173: istore #18
    //   4175: iload #18
    //   4177: bipush #8
    //   4179: if_icmpge -> 4202
    //   4182: aload #10
    //   4184: iload #18
    //   4186: dup2
    //   4187: iaload
    //   4188: aload #17
    //   4190: iload #18
    //   4192: iaload
    //   4193: iadd
    //   4194: iastore
    //   4195: iinc #18, 1
    //   4198: iload_2
    //   4199: ifeq -> 4175
    //   4202: iinc #15, 64
    //   4205: iinc #13, -64
    //   4208: iload_2
    //   4209: ifeq -> 3598
    //   4212: iload #13
    //   4214: ifle -> 4250
    //   4217: iconst_0
    //   4218: istore #16
    //   4220: iload #16
    //   4222: iload #13
    //   4224: if_icmpge -> 4250
    //   4227: aload #11
    //   4229: iload #14
    //   4231: iload #16
    //   4233: iadd
    //   4234: aload #5
    //   4236: iload #15
    //   4238: iload #16
    //   4240: iadd
    //   4241: baload
    //   4242: bastore
    //   4243: iinc #16, 1
    //   4246: iload_2
    //   4247: ifeq -> 4220
    //   4250: aload #9
    //   4252: iconst_0
    //   4253: iaload
    //   4254: bipush #29
    //   4256: iushr
    //   4257: aload #9
    //   4259: iconst_1
    //   4260: iaload
    //   4261: iconst_3
    //   4262: ishl
    //   4263: ior
    //   4264: istore #16
    //   4266: aload #9
    //   4268: iconst_0
    //   4269: iaload
    //   4270: iconst_3
    //   4271: ishl
    //   4272: istore #17
    //   4274: aload #9
    //   4276: iconst_0
    //   4277: iaload
    //   4278: bipush #63
    //   4280: iand
    //   4281: istore #18
    //   4283: iload #18
    //   4285: bipush #56
    //   4287: if_icmpge -> 4302
    //   4290: bipush #56
    //   4292: iload #18
    //   4294: isub
    //   4295: goto -> 4307
    //   4298: invokestatic a : (Ljava/lang/Throwable;)Ljava/lang/Throwable;
    //   4301: athrow
    //   4302: bipush #120
    //   4304: iload #18
    //   4306: isub
    //   4307: istore #19
    //   4309: aload #9
    //   4311: iconst_0
    //   4312: iaload
    //   4313: bipush #63
    //   4315: iand
    //   4316: istore #14
    //   4318: bipush #64
    //   4320: iload #14
    //   4322: isub
    //   4323: istore #20
    //   4325: aload #9
    //   4327: iconst_0
    //   4328: dup2
    //   4329: iaload
    //   4330: iload #19
    //   4332: iadd
    //   4333: iastore
    //   4334: aload #9
    //   4336: iconst_0
    //   4337: dup2
    //   4338: iaload
    //   4339: iconst_m1
    //   4340: iand
    //   4341: iastore
    //   4342: aload #9
    //   4344: iconst_0
    //   4345: iaload
    //   4346: iload #19
    //   4348: if_icmpge -> 4366
    //   4351: aload #9
    //   4353: iconst_1
    //   4354: dup2
    //   4355: iaload
    //   4356: iconst_1
    //   4357: iadd
    //   4358: iastore
    //   4359: goto -> 4366
    //   4362: invokestatic a : (Ljava/lang/Throwable;)Ljava/lang/Throwable;
    //   4365: athrow
    //   4366: iconst_0
    //   4367: istore #15
    //   4369: iload #14
    //   4371: ifle -> 5002
    //   4374: iload #19
    //   4376: iload #20
    //   4378: if_icmplt -> 5002
    //   4381: goto -> 4388
    //   4384: invokestatic a : (Ljava/lang/Throwable;)Ljava/lang/Throwable;
    //   4387: athrow
    //   4388: iconst_0
    //   4389: istore #21
    //   4391: iload #21
    //   4393: iload #20
    //   4395: if_icmpge -> 4418
    //   4398: aload #11
    //   4400: iload #14
    //   4402: iload #21
    //   4404: iadd
    //   4405: aload #7
    //   4407: iload #21
    //   4409: baload
    //   4410: bastore
    //   4411: iinc #21, 1
    //   4414: iload_2
    //   4415: ifeq -> 4391
    //   4418: bipush #64
    //   4420: newarray int
    //   4422: astore #21
    //   4424: bipush #8
    //   4426: newarray int
    //   4428: astore #22
    //   4430: iconst_0
    //   4431: istore #23
    //   4433: iload #23
    //   4435: bipush #8
    //   4437: if_icmpge -> 4457
    //   4440: aload #22
    //   4442: iload #23
    //   4444: aload #10
    //   4446: iload #23
    //   4448: iaload
    //   4449: iastore
    //   4450: iinc #23, 1
    //   4453: iload_2
    //   4454: ifeq -> 4433
    //   4457: iconst_0
    //   4458: istore #23
    //   4460: iload #23
    //   4462: bipush #64
    //   4464: if_icmpge -> 4955
    //   4467: iload #23
    //   4469: bipush #16
    //   4471: if_icmpge -> 4552
    //   4474: aload #21
    //   4476: iload #23
    //   4478: aload #11
    //   4480: iconst_4
    //   4481: iload #23
    //   4483: imul
    //   4484: baload
    //   4485: sipush #255
    //   4488: iand
    //   4489: bipush #24
    //   4491: ishl
    //   4492: aload #11
    //   4494: iconst_4
    //   4495: iload #23
    //   4497: imul
    //   4498: iconst_1
    //   4499: iadd
    //   4500: baload
    //   4501: sipush #255
    //   4504: iand
    //   4505: bipush #16
    //   4507: ishl
    //   4508: ior
    //   4509: aload #11
    //   4511: iconst_4
    //   4512: iload #23
    //   4514: imul
    //   4515: iconst_2
    //   4516: iadd
    //   4517: baload
    //   4518: sipush #255
    //   4521: iand
    //   4522: bipush #8
    //   4524: ishl
    //   4525: ior
    //   4526: aload #11
    //   4528: iconst_4
    //   4529: iload #23
    //   4531: imul
    //   4532: iconst_3
    //   4533: iadd
    //   4534: baload
    //   4535: sipush #255
    //   4538: iand
    //   4539: ior
    //   4540: iastore
    //   4541: iload_2
    //   4542: ifeq -> 4695
    //   4545: goto -> 4552
    //   4548: invokestatic a : (Ljava/lang/Throwable;)Ljava/lang/Throwable;
    //   4551: athrow
    //   4552: aload #21
    //   4554: iload #23
    //   4556: aload #21
    //   4558: iload #23
    //   4560: iconst_2
    //   4561: isub
    //   4562: iaload
    //   4563: bipush #17
    //   4565: iushr
    //   4566: aload #21
    //   4568: iload #23
    //   4570: iconst_2
    //   4571: isub
    //   4572: iaload
    //   4573: bipush #15
    //   4575: ishl
    //   4576: ior
    //   4577: aload #21
    //   4579: iload #23
    //   4581: iconst_2
    //   4582: isub
    //   4583: iaload
    //   4584: bipush #19
    //   4586: iushr
    //   4587: aload #21
    //   4589: iload #23
    //   4591: iconst_2
    //   4592: isub
    //   4593: iaload
    //   4594: bipush #13
    //   4596: ishl
    //   4597: ior
    //   4598: ixor
    //   4599: aload #21
    //   4601: iload #23
    //   4603: iconst_2
    //   4604: isub
    //   4605: iaload
    //   4606: bipush #10
    //   4608: iushr
    //   4609: ixor
    //   4610: aload #21
    //   4612: iload #23
    //   4614: bipush #7
    //   4616: isub
    //   4617: iaload
    //   4618: iadd
    //   4619: aload #21
    //   4621: iload #23
    //   4623: bipush #15
    //   4625: isub
    //   4626: iaload
    //   4627: bipush #7
    //   4629: iushr
    //   4630: aload #21
    //   4632: iload #23
    //   4634: bipush #15
    //   4636: isub
    //   4637: iaload
    //   4638: bipush #25
    //   4640: ishl
    //   4641: ior
    //   4642: aload #21
    //   4644: iload #23
    //   4646: bipush #15
    //   4648: isub
    //   4649: iaload
    //   4650: bipush #18
    //   4652: iushr
    //   4653: aload #21
    //   4655: iload #23
    //   4657: bipush #15
    //   4659: isub
    //   4660: iaload
    //   4661: bipush #14
    //   4663: ishl
    //   4664: ior
    //   4665: ixor
    //   4666: aload #21
    //   4668: iload #23
    //   4670: bipush #15
    //   4672: isub
    //   4673: iaload
    //   4674: iconst_3
    //   4675: iushr
    //   4676: ixor
    //   4677: iadd
    //   4678: aload #21
    //   4680: iload #23
    //   4682: bipush #16
    //   4684: isub
    //   4685: iaload
    //   4686: iadd
    //   4687: iastore
    //   4688: goto -> 4695
    //   4691: invokestatic a : (Ljava/lang/Throwable;)Ljava/lang/Throwable;
    //   4694: athrow
    //   4695: aload #22
    //   4697: bipush #7
    //   4699: iaload
    //   4700: aload #22
    //   4702: iconst_4
    //   4703: iaload
    //   4704: bipush #6
    //   4706: iushr
    //   4707: aload #22
    //   4709: iconst_4
    //   4710: iaload
    //   4711: bipush #26
    //   4713: ishl
    //   4714: ior
    //   4715: aload #22
    //   4717: iconst_4
    //   4718: iaload
    //   4719: bipush #11
    //   4721: iushr
    //   4722: aload #22
    //   4724: iconst_4
    //   4725: iaload
    //   4726: bipush #21
    //   4728: ishl
    //   4729: ior
    //   4730: ixor
    //   4731: aload #22
    //   4733: iconst_4
    //   4734: iaload
    //   4735: bipush #25
    //   4737: iushr
    //   4738: aload #22
    //   4740: iconst_4
    //   4741: iaload
    //   4742: bipush #7
    //   4744: ishl
    //   4745: ior
    //   4746: ixor
    //   4747: iadd
    //   4748: aload #22
    //   4750: bipush #6
    //   4752: iaload
    //   4753: aload #22
    //   4755: iconst_4
    //   4756: iaload
    //   4757: aload #22
    //   4759: iconst_5
    //   4760: iaload
    //   4761: aload #22
    //   4763: bipush #6
    //   4765: iaload
    //   4766: ixor
    //   4767: iand
    //   4768: ixor
    //   4769: iadd
    //   4770: aload #8
    //   4772: iload #23
    //   4774: iaload
    //   4775: iadd
    //   4776: aload #21
    //   4778: iload #23
    //   4780: iaload
    //   4781: iadd
    //   4782: istore #24
    //   4784: aload #22
    //   4786: iconst_0
    //   4787: iaload
    //   4788: iconst_2
    //   4789: iushr
    //   4790: aload #22
    //   4792: iconst_0
    //   4793: iaload
    //   4794: bipush #30
    //   4796: ishl
    //   4797: ior
    //   4798: aload #22
    //   4800: iconst_0
    //   4801: iaload
    //   4802: bipush #13
    //   4804: iushr
    //   4805: aload #22
    //   4807: iconst_0
    //   4808: iaload
    //   4809: bipush #19
    //   4811: ishl
    //   4812: ior
    //   4813: ixor
    //   4814: aload #22
    //   4816: iconst_0
    //   4817: iaload
    //   4818: bipush #22
    //   4820: iushr
    //   4821: aload #22
    //   4823: iconst_0
    //   4824: iaload
    //   4825: bipush #10
    //   4827: ishl
    //   4828: ior
    //   4829: ixor
    //   4830: aload #22
    //   4832: iconst_0
    //   4833: iaload
    //   4834: aload #22
    //   4836: iconst_1
    //   4837: iaload
    //   4838: iand
    //   4839: aload #22
    //   4841: iconst_2
    //   4842: iaload
    //   4843: aload #22
    //   4845: iconst_0
    //   4846: iaload
    //   4847: aload #22
    //   4849: iconst_1
    //   4850: iaload
    //   4851: ior
    //   4852: iand
    //   4853: ior
    //   4854: iadd
    //   4855: istore #25
    //   4857: aload #22
    //   4859: iconst_3
    //   4860: dup2
    //   4861: iaload
    //   4862: iload #24
    //   4864: iadd
    //   4865: iastore
    //   4866: aload #22
    //   4868: bipush #7
    //   4870: iload #24
    //   4872: iload #25
    //   4874: iadd
    //   4875: iastore
    //   4876: aload #22
    //   4878: bipush #7
    //   4880: iaload
    //   4881: istore #24
    //   4883: aload #22
    //   4885: bipush #7
    //   4887: aload #22
    //   4889: bipush #6
    //   4891: iaload
    //   4892: iastore
    //   4893: aload #22
    //   4895: bipush #6
    //   4897: aload #22
    //   4899: iconst_5
    //   4900: iaload
    //   4901: iastore
    //   4902: aload #22
    //   4904: iconst_5
    //   4905: aload #22
    //   4907: iconst_4
    //   4908: iaload
    //   4909: iastore
    //   4910: aload #22
    //   4912: iconst_4
    //   4913: aload #22
    //   4915: iconst_3
    //   4916: iaload
    //   4917: iastore
    //   4918: aload #22
    //   4920: iconst_3
    //   4921: aload #22
    //   4923: iconst_2
    //   4924: iaload
    //   4925: iastore
    //   4926: aload #22
    //   4928: iconst_2
    //   4929: aload #22
    //   4931: iconst_1
    //   4932: iaload
    //   4933: iastore
    //   4934: aload #22
    //   4936: iconst_1
    //   4937: aload #22
    //   4939: iconst_0
    //   4940: iaload
    //   4941: iastore
    //   4942: aload #22
    //   4944: iconst_0
    //   4945: iload #24
    //   4947: iastore
    //   4948: iinc #23, 1
    //   4951: iload_2
    //   4952: ifeq -> 4460
    //   4955: iconst_0
    //   4956: istore #23
    //   4958: iload #23
    //   4960: bipush #8
    //   4962: if_icmpge -> 4985
    //   4965: aload #10
    //   4967: iload #23
    //   4969: dup2
    //   4970: iaload
    //   4971: aload #22
    //   4973: iload #23
    //   4975: iaload
    //   4976: iadd
    //   4977: iastore
    //   4978: iinc #23, 1
    //   4981: iload_2
    //   4982: ifeq -> 4958
    //   4985: iload #15
    //   4987: iload #20
    //   4989: iadd
    //   4990: istore #15
    //   4992: iload #19
    //   4994: iload #20
    //   4996: isub
    //   4997: istore #19
    //   4999: iconst_0
    //   5000: istore #14
    //   5002: iload #19
    //   5004: bipush #64
    //   5006: if_icmplt -> 5616
    //   5009: iconst_0
    //   5010: istore #21
    //   5012: iload #21
    //   5014: bipush #64
    //   5016: if_icmpge -> 5039
    //   5019: aload #12
    //   5021: iload #21
    //   5023: aload #7
    //   5025: iload #15
    //   5027: iload #21
    //   5029: iadd
    //   5030: baload
    //   5031: bastore
    //   5032: iinc #21, 1
    //   5035: iload_2
    //   5036: ifeq -> 5012
    //   5039: bipush #64
    //   5041: newarray int
    //   5043: astore #21
    //   5045: bipush #8
    //   5047: newarray int
    //   5049: astore #22
    //   5051: iconst_0
    //   5052: istore #23
    //   5054: iload #23
    //   5056: bipush #8
    //   5058: if_icmpge -> 5078
    //   5061: aload #22
    //   5063: iload #23
    //   5065: aload #10
    //   5067: iload #23
    //   5069: iaload
    //   5070: iastore
    //   5071: iinc #23, 1
    //   5074: iload_2
    //   5075: ifeq -> 5054
    //   5078: iconst_0
    //   5079: istore #23
    //   5081: iload #23
    //   5083: bipush #64
    //   5085: if_icmpge -> 5576
    //   5088: iload #23
    //   5090: bipush #16
    //   5092: if_icmpge -> 5173
    //   5095: aload #21
    //   5097: iload #23
    //   5099: aload #12
    //   5101: iconst_4
    //   5102: iload #23
    //   5104: imul
    //   5105: baload
    //   5106: sipush #255
    //   5109: iand
    //   5110: bipush #24
    //   5112: ishl
    //   5113: aload #12
    //   5115: iconst_4
    //   5116: iload #23
    //   5118: imul
    //   5119: iconst_1
    //   5120: iadd
    //   5121: baload
    //   5122: sipush #255
    //   5125: iand
    //   5126: bipush #16
    //   5128: ishl
    //   5129: ior
    //   5130: aload #12
    //   5132: iconst_4
    //   5133: iload #23
    //   5135: imul
    //   5136: iconst_2
    //   5137: iadd
    //   5138: baload
    //   5139: sipush #255
    //   5142: iand
    //   5143: bipush #8
    //   5145: ishl
    //   5146: ior
    //   5147: aload #12
    //   5149: iconst_4
    //   5150: iload #23
    //   5152: imul
    //   5153: iconst_3
    //   5154: iadd
    //   5155: baload
    //   5156: sipush #255
    //   5159: iand
    //   5160: ior
    //   5161: iastore
    //   5162: iload_2
    //   5163: ifeq -> 5316
    //   5166: goto -> 5173
    //   5169: invokestatic a : (Ljava/lang/Throwable;)Ljava/lang/Throwable;
    //   5172: athrow
    //   5173: aload #21
    //   5175: iload #23
    //   5177: aload #21
    //   5179: iload #23
    //   5181: iconst_2
    //   5182: isub
    //   5183: iaload
    //   5184: bipush #17
    //   5186: iushr
    //   5187: aload #21
    //   5189: iload #23
    //   5191: iconst_2
    //   5192: isub
    //   5193: iaload
    //   5194: bipush #15
    //   5196: ishl
    //   5197: ior
    //   5198: aload #21
    //   5200: iload #23
    //   5202: iconst_2
    //   5203: isub
    //   5204: iaload
    //   5205: bipush #19
    //   5207: iushr
    //   5208: aload #21
    //   5210: iload #23
    //   5212: iconst_2
    //   5213: isub
    //   5214: iaload
    //   5215: bipush #13
    //   5217: ishl
    //   5218: ior
    //   5219: ixor
    //   5220: aload #21
    //   5222: iload #23
    //   5224: iconst_2
    //   5225: isub
    //   5226: iaload
    //   5227: bipush #10
    //   5229: iushr
    //   5230: ixor
    //   5231: aload #21
    //   5233: iload #23
    //   5235: bipush #7
    //   5237: isub
    //   5238: iaload
    //   5239: iadd
    //   5240: aload #21
    //   5242: iload #23
    //   5244: bipush #15
    //   5246: isub
    //   5247: iaload
    //   5248: bipush #7
    //   5250: iushr
    //   5251: aload #21
    //   5253: iload #23
    //   5255: bipush #15
    //   5257: isub
    //   5258: iaload
    //   5259: bipush #25
    //   5261: ishl
    //   5262: ior
    //   5263: aload #21
    //   5265: iload #23
    //   5267: bipush #15
    //   5269: isub
    //   5270: iaload
    //   5271: bipush #18
    //   5273: iushr
    //   5274: aload #21
    //   5276: iload #23
    //   5278: bipush #15
    //   5280: isub
    //   5281: iaload
    //   5282: bipush #14
    //   5284: ishl
    //   5285: ior
    //   5286: ixor
    //   5287: aload #21
    //   5289: iload #23
    //   5291: bipush #15
    //   5293: isub
    //   5294: iaload
    //   5295: iconst_3
    //   5296: iushr
    //   5297: ixor
    //   5298: iadd
    //   5299: aload #21
    //   5301: iload #23
    //   5303: bipush #16
    //   5305: isub
    //   5306: iaload
    //   5307: iadd
    //   5308: iastore
    //   5309: goto -> 5316
    //   5312: invokestatic a : (Ljava/lang/Throwable;)Ljava/lang/Throwable;
    //   5315: athrow
    //   5316: aload #22
    //   5318: bipush #7
    //   5320: iaload
    //   5321: aload #22
    //   5323: iconst_4
    //   5324: iaload
    //   5325: bipush #6
    //   5327: iushr
    //   5328: aload #22
    //   5330: iconst_4
    //   5331: iaload
    //   5332: bipush #26
    //   5334: ishl
    //   5335: ior
    //   5336: aload #22
    //   5338: iconst_4
    //   5339: iaload
    //   5340: bipush #11
    //   5342: iushr
    //   5343: aload #22
    //   5345: iconst_4
    //   5346: iaload
    //   5347: bipush #21
    //   5349: ishl
    //   5350: ior
    //   5351: ixor
    //   5352: aload #22
    //   5354: iconst_4
    //   5355: iaload
    //   5356: bipush #25
    //   5358: iushr
    //   5359: aload #22
    //   5361: iconst_4
    //   5362: iaload
    //   5363: bipush #7
    //   5365: ishl
    //   5366: ior
    //   5367: ixor
    //   5368: iadd
    //   5369: aload #22
    //   5371: bipush #6
    //   5373: iaload
    //   5374: aload #22
    //   5376: iconst_4
    //   5377: iaload
    //   5378: aload #22
    //   5380: iconst_5
    //   5381: iaload
    //   5382: aload #22
    //   5384: bipush #6
    //   5386: iaload
    //   5387: ixor
    //   5388: iand
    //   5389: ixor
    //   5390: iadd
    //   5391: aload #8
    //   5393: iload #23
    //   5395: iaload
    //   5396: iadd
    //   5397: aload #21
    //   5399: iload #23
    //   5401: iaload
    //   5402: iadd
    //   5403: istore #24
    //   5405: aload #22
    //   5407: iconst_0
    //   5408: iaload
    //   5409: iconst_2
    //   5410: iushr
    //   5411: aload #22
    //   5413: iconst_0
    //   5414: iaload
    //   5415: bipush #30
    //   5417: ishl
    //   5418: ior
    //   5419: aload #22
    //   5421: iconst_0
    //   5422: iaload
    //   5423: bipush #13
    //   5425: iushr
    //   5426: aload #22
    //   5428: iconst_0
    //   5429: iaload
    //   5430: bipush #19
    //   5432: ishl
    //   5433: ior
    //   5434: ixor
    //   5435: aload #22
    //   5437: iconst_0
    //   5438: iaload
    //   5439: bipush #22
    //   5441: iushr
    //   5442: aload #22
    //   5444: iconst_0
    //   5445: iaload
    //   5446: bipush #10
    //   5448: ishl
    //   5449: ior
    //   5450: ixor
    //   5451: aload #22
    //   5453: iconst_0
    //   5454: iaload
    //   5455: aload #22
    //   5457: iconst_1
    //   5458: iaload
    //   5459: iand
    //   5460: aload #22
    //   5462: iconst_2
    //   5463: iaload
    //   5464: aload #22
    //   5466: iconst_0
    //   5467: iaload
    //   5468: aload #22
    //   5470: iconst_1
    //   5471: iaload
    //   5472: ior
    //   5473: iand
    //   5474: ior
    //   5475: iadd
    //   5476: istore #25
    //   5478: aload #22
    //   5480: iconst_3
    //   5481: dup2
    //   5482: iaload
    //   5483: iload #24
    //   5485: iadd
    //   5486: iastore
    //   5487: aload #22
    //   5489: bipush #7
    //   5491: iload #24
    //   5493: iload #25
    //   5495: iadd
    //   5496: iastore
    //   5497: aload #22
    //   5499: bipush #7
    //   5501: iaload
    //   5502: istore #24
    //   5504: aload #22
    //   5506: bipush #7
    //   5508: aload #22
    //   5510: bipush #6
    //   5512: iaload
    //   5513: iastore
    //   5514: aload #22
    //   5516: bipush #6
    //   5518: aload #22
    //   5520: iconst_5
    //   5521: iaload
    //   5522: iastore
    //   5523: aload #22
    //   5525: iconst_5
    //   5526: aload #22
    //   5528: iconst_4
    //   5529: iaload
    //   5530: iastore
    //   5531: aload #22
    //   5533: iconst_4
    //   5534: aload #22
    //   5536: iconst_3
    //   5537: iaload
    //   5538: iastore
    //   5539: aload #22
    //   5541: iconst_3
    //   5542: aload #22
    //   5544: iconst_2
    //   5545: iaload
    //   5546: iastore
    //   5547: aload #22
    //   5549: iconst_2
    //   5550: aload #22
    //   5552: iconst_1
    //   5553: iaload
    //   5554: iastore
    //   5555: aload #22
    //   5557: iconst_1
    //   5558: aload #22
    //   5560: iconst_0
    //   5561: iaload
    //   5562: iastore
    //   5563: aload #22
    //   5565: iconst_0
    //   5566: iload #24
    //   5568: iastore
    //   5569: iinc #23, 1
    //   5572: iload_2
    //   5573: ifeq -> 5081
    //   5576: iconst_0
    //   5577: istore #23
    //   5579: iload #23
    //   5581: bipush #8
    //   5583: if_icmpge -> 5606
    //   5586: aload #10
    //   5588: iload #23
    //   5590: dup2
    //   5591: iaload
    //   5592: aload #22
    //   5594: iload #23
    //   5596: iaload
    //   5597: iadd
    //   5598: iastore
    //   5599: iinc #23, 1
    //   5602: iload_2
    //   5603: ifeq -> 5579
    //   5606: iinc #15, 64
    //   5609: iinc #19, -64
    //   5612: iload_2
    //   5613: ifeq -> 5002
    //   5616: iload #19
    //   5618: ifle -> 5654
    //   5621: iconst_0
    //   5622: istore #21
    //   5624: iload #21
    //   5626: iload #19
    //   5628: if_icmpge -> 5654
    //   5631: aload #11
    //   5633: iload #14
    //   5635: iload #21
    //   5637: iadd
    //   5638: aload #7
    //   5640: iload #15
    //   5642: iload #21
    //   5644: iadd
    //   5645: baload
    //   5646: bastore
    //   5647: iinc #21, 1
    //   5650: iload_2
    //   5651: ifeq -> 5624
    //   5654: bipush #8
    //   5656: newarray byte
    //   5658: astore #21
    //   5660: aload #21
    //   5662: iconst_0
    //   5663: iload #16
    //   5665: bipush #24
    //   5667: iushr
    //   5668: i2b
    //   5669: bastore
    //   5670: aload #21
    //   5672: iconst_1
    //   5673: iload #16
    //   5675: bipush #16
    //   5677: iushr
    //   5678: i2b
    //   5679: bastore
    //   5680: aload #21
    //   5682: iconst_2
    //   5683: iload #16
    //   5685: bipush #8
    //   5687: iushr
    //   5688: i2b
    //   5689: bastore
    //   5690: aload #21
    //   5692: iconst_3
    //   5693: iload #16
    //   5695: i2b
    //   5696: bastore
    //   5697: aload #21
    //   5699: iconst_4
    //   5700: iload #17
    //   5702: bipush #24
    //   5704: iushr
    //   5705: i2b
    //   5706: bastore
    //   5707: aload #21
    //   5709: iconst_5
    //   5710: iload #17
    //   5712: bipush #16
    //   5714: iushr
    //   5715: i2b
    //   5716: bastore
    //   5717: aload #21
    //   5719: bipush #6
    //   5721: iload #17
    //   5723: bipush #8
    //   5725: iushr
    //   5726: i2b
    //   5727: bastore
    //   5728: aload #21
    //   5730: bipush #7
    //   5732: iload #17
    //   5734: i2b
    //   5735: bastore
    //   5736: bipush #8
    //   5738: istore #13
    //   5740: aload #9
    //   5742: iconst_0
    //   5743: iaload
    //   5744: bipush #63
    //   5746: iand
    //   5747: istore #14
    //   5749: bipush #64
    //   5751: iload #14
    //   5753: isub
    //   5754: istore #20
    //   5756: aload #9
    //   5758: iconst_0
    //   5759: dup2
    //   5760: iaload
    //   5761: iload #13
    //   5763: iadd
    //   5764: iastore
    //   5765: aload #9
    //   5767: iconst_0
    //   5768: dup2
    //   5769: iaload
    //   5770: iconst_m1
    //   5771: iand
    //   5772: iastore
    //   5773: aload #9
    //   5775: iconst_0
    //   5776: iaload
    //   5777: iload #13
    //   5779: if_icmpge -> 5797
    //   5782: aload #9
    //   5784: iconst_1
    //   5785: dup2
    //   5786: iaload
    //   5787: iconst_1
    //   5788: iadd
    //   5789: iastore
    //   5790: goto -> 5797
    //   5793: invokestatic a : (Ljava/lang/Throwable;)Ljava/lang/Throwable;
    //   5796: athrow
    //   5797: iload #14
    //   5799: ifle -> 6413
    //   5802: iload #13
    //   5804: iload #20
    //   5806: if_icmplt -> 6413
    //   5809: goto -> 5816
    //   5812: invokestatic a : (Ljava/lang/Throwable;)Ljava/lang/Throwable;
    //   5815: athrow
    //   5816: iconst_0
    //   5817: istore #22
    //   5819: iload #22
    //   5821: iload #20
    //   5823: if_icmpge -> 5846
    //   5826: aload #11
    //   5828: iload #14
    //   5830: iload #22
    //   5832: iadd
    //   5833: aload #21
    //   5835: iload #22
    //   5837: baload
    //   5838: bastore
    //   5839: iinc #22, 1
    //   5842: iload_2
    //   5843: ifeq -> 5819
    //   5846: bipush #64
    //   5848: newarray int
    //   5850: astore #22
    //   5852: bipush #8
    //   5854: newarray int
    //   5856: astore #23
    //   5858: iconst_0
    //   5859: istore #24
    //   5861: iload #24
    //   5863: bipush #8
    //   5865: if_icmpge -> 5885
    //   5868: aload #23
    //   5870: iload #24
    //   5872: aload #10
    //   5874: iload #24
    //   5876: iaload
    //   5877: iastore
    //   5878: iinc #24, 1
    //   5881: iload_2
    //   5882: ifeq -> 5861
    //   5885: iconst_0
    //   5886: istore #24
    //   5888: iload #24
    //   5890: bipush #64
    //   5892: if_icmpge -> 6383
    //   5895: iload #24
    //   5897: bipush #16
    //   5899: if_icmpge -> 5980
    //   5902: aload #22
    //   5904: iload #24
    //   5906: aload #11
    //   5908: iconst_4
    //   5909: iload #24
    //   5911: imul
    //   5912: baload
    //   5913: sipush #255
    //   5916: iand
    //   5917: bipush #24
    //   5919: ishl
    //   5920: aload #11
    //   5922: iconst_4
    //   5923: iload #24
    //   5925: imul
    //   5926: iconst_1
    //   5927: iadd
    //   5928: baload
    //   5929: sipush #255
    //   5932: iand
    //   5933: bipush #16
    //   5935: ishl
    //   5936: ior
    //   5937: aload #11
    //   5939: iconst_4
    //   5940: iload #24
    //   5942: imul
    //   5943: iconst_2
    //   5944: iadd
    //   5945: baload
    //   5946: sipush #255
    //   5949: iand
    //   5950: bipush #8
    //   5952: ishl
    //   5953: ior
    //   5954: aload #11
    //   5956: iconst_4
    //   5957: iload #24
    //   5959: imul
    //   5960: iconst_3
    //   5961: iadd
    //   5962: baload
    //   5963: sipush #255
    //   5966: iand
    //   5967: ior
    //   5968: iastore
    //   5969: iload_2
    //   5970: ifeq -> 6123
    //   5973: goto -> 5980
    //   5976: invokestatic a : (Ljava/lang/Throwable;)Ljava/lang/Throwable;
    //   5979: athrow
    //   5980: aload #22
    //   5982: iload #24
    //   5984: aload #22
    //   5986: iload #24
    //   5988: iconst_2
    //   5989: isub
    //   5990: iaload
    //   5991: bipush #17
    //   5993: iushr
    //   5994: aload #22
    //   5996: iload #24
    //   5998: iconst_2
    //   5999: isub
    //   6000: iaload
    //   6001: bipush #15
    //   6003: ishl
    //   6004: ior
    //   6005: aload #22
    //   6007: iload #24
    //   6009: iconst_2
    //   6010: isub
    //   6011: iaload
    //   6012: bipush #19
    //   6014: iushr
    //   6015: aload #22
    //   6017: iload #24
    //   6019: iconst_2
    //   6020: isub
    //   6021: iaload
    //   6022: bipush #13
    //   6024: ishl
    //   6025: ior
    //   6026: ixor
    //   6027: aload #22
    //   6029: iload #24
    //   6031: iconst_2
    //   6032: isub
    //   6033: iaload
    //   6034: bipush #10
    //   6036: iushr
    //   6037: ixor
    //   6038: aload #22
    //   6040: iload #24
    //   6042: bipush #7
    //   6044: isub
    //   6045: iaload
    //   6046: iadd
    //   6047: aload #22
    //   6049: iload #24
    //   6051: bipush #15
    //   6053: isub
    //   6054: iaload
    //   6055: bipush #7
    //   6057: iushr
    //   6058: aload #22
    //   6060: iload #24
    //   6062: bipush #15
    //   6064: isub
    //   6065: iaload
    //   6066: bipush #25
    //   6068: ishl
    //   6069: ior
    //   6070: aload #22
    //   6072: iload #24
    //   6074: bipush #15
    //   6076: isub
    //   6077: iaload
    //   6078: bipush #18
    //   6080: iushr
    //   6081: aload #22
    //   6083: iload #24
    //   6085: bipush #15
    //   6087: isub
    //   6088: iaload
    //   6089: bipush #14
    //   6091: ishl
    //   6092: ior
    //   6093: ixor
    //   6094: aload #22
    //   6096: iload #24
    //   6098: bipush #15
    //   6100: isub
    //   6101: iaload
    //   6102: iconst_3
    //   6103: iushr
    //   6104: ixor
    //   6105: iadd
    //   6106: aload #22
    //   6108: iload #24
    //   6110: bipush #16
    //   6112: isub
    //   6113: iaload
    //   6114: iadd
    //   6115: iastore
    //   6116: goto -> 6123
    //   6119: invokestatic a : (Ljava/lang/Throwable;)Ljava/lang/Throwable;
    //   6122: athrow
    //   6123: aload #23
    //   6125: bipush #7
    //   6127: iaload
    //   6128: aload #23
    //   6130: iconst_4
    //   6131: iaload
    //   6132: bipush #6
    //   6134: iushr
    //   6135: aload #23
    //   6137: iconst_4
    //   6138: iaload
    //   6139: bipush #26
    //   6141: ishl
    //   6142: ior
    //   6143: aload #23
    //   6145: iconst_4
    //   6146: iaload
    //   6147: bipush #11
    //   6149: iushr
    //   6150: aload #23
    //   6152: iconst_4
    //   6153: iaload
    //   6154: bipush #21
    //   6156: ishl
    //   6157: ior
    //   6158: ixor
    //   6159: aload #23
    //   6161: iconst_4
    //   6162: iaload
    //   6163: bipush #25
    //   6165: iushr
    //   6166: aload #23
    //   6168: iconst_4
    //   6169: iaload
    //   6170: bipush #7
    //   6172: ishl
    //   6173: ior
    //   6174: ixor
    //   6175: iadd
    //   6176: aload #23
    //   6178: bipush #6
    //   6180: iaload
    //   6181: aload #23
    //   6183: iconst_4
    //   6184: iaload
    //   6185: aload #23
    //   6187: iconst_5
    //   6188: iaload
    //   6189: aload #23
    //   6191: bipush #6
    //   6193: iaload
    //   6194: ixor
    //   6195: iand
    //   6196: ixor
    //   6197: iadd
    //   6198: aload #8
    //   6200: iload #24
    //   6202: iaload
    //   6203: iadd
    //   6204: aload #22
    //   6206: iload #24
    //   6208: iaload
    //   6209: iadd
    //   6210: istore #25
    //   6212: aload #23
    //   6214: iconst_0
    //   6215: iaload
    //   6216: iconst_2
    //   6217: iushr
    //   6218: aload #23
    //   6220: iconst_0
    //   6221: iaload
    //   6222: bipush #30
    //   6224: ishl
    //   6225: ior
    //   6226: aload #23
    //   6228: iconst_0
    //   6229: iaload
    //   6230: bipush #13
    //   6232: iushr
    //   6233: aload #23
    //   6235: iconst_0
    //   6236: iaload
    //   6237: bipush #19
    //   6239: ishl
    //   6240: ior
    //   6241: ixor
    //   6242: aload #23
    //   6244: iconst_0
    //   6245: iaload
    //   6246: bipush #22
    //   6248: iushr
    //   6249: aload #23
    //   6251: iconst_0
    //   6252: iaload
    //   6253: bipush #10
    //   6255: ishl
    //   6256: ior
    //   6257: ixor
    //   6258: aload #23
    //   6260: iconst_0
    //   6261: iaload
    //   6262: aload #23
    //   6264: iconst_1
    //   6265: iaload
    //   6266: iand
    //   6267: aload #23
    //   6269: iconst_2
    //   6270: iaload
    //   6271: aload #23
    //   6273: iconst_0
    //   6274: iaload
    //   6275: aload #23
    //   6277: iconst_1
    //   6278: iaload
    //   6279: ior
    //   6280: iand
    //   6281: ior
    //   6282: iadd
    //   6283: istore #26
    //   6285: aload #23
    //   6287: iconst_3
    //   6288: dup2
    //   6289: iaload
    //   6290: iload #25
    //   6292: iadd
    //   6293: iastore
    //   6294: aload #23
    //   6296: bipush #7
    //   6298: iload #25
    //   6300: iload #26
    //   6302: iadd
    //   6303: iastore
    //   6304: aload #23
    //   6306: bipush #7
    //   6308: iaload
    //   6309: istore #25
    //   6311: aload #23
    //   6313: bipush #7
    //   6315: aload #23
    //   6317: bipush #6
    //   6319: iaload
    //   6320: iastore
    //   6321: aload #23
    //   6323: bipush #6
    //   6325: aload #23
    //   6327: iconst_5
    //   6328: iaload
    //   6329: iastore
    //   6330: aload #23
    //   6332: iconst_5
    //   6333: aload #23
    //   6335: iconst_4
    //   6336: iaload
    //   6337: iastore
    //   6338: aload #23
    //   6340: iconst_4
    //   6341: aload #23
    //   6343: iconst_3
    //   6344: iaload
    //   6345: iastore
    //   6346: aload #23
    //   6348: iconst_3
    //   6349: aload #23
    //   6351: iconst_2
    //   6352: iaload
    //   6353: iastore
    //   6354: aload #23
    //   6356: iconst_2
    //   6357: aload #23
    //   6359: iconst_1
    //   6360: iaload
    //   6361: iastore
    //   6362: aload #23
    //   6364: iconst_1
    //   6365: aload #23
    //   6367: iconst_0
    //   6368: iaload
    //   6369: iastore
    //   6370: aload #23
    //   6372: iconst_0
    //   6373: iload #25
    //   6375: iastore
    //   6376: iinc #24, 1
    //   6379: iload_2
    //   6380: ifeq -> 5888
    //   6383: iconst_0
    //   6384: istore #24
    //   6386: iload #24
    //   6388: bipush #8
    //   6390: if_icmpge -> 6413
    //   6393: aload #10
    //   6395: iload #24
    //   6397: dup2
    //   6398: iaload
    //   6399: aload #23
    //   6401: iload #24
    //   6403: iaload
    //   6404: iadd
    //   6405: iastore
    //   6406: iinc #24, 1
    //   6409: iload_2
    //   6410: ifeq -> 6386
    //   6413: bipush #32
    //   6415: newarray byte
    //   6417: astore #6
    //   6419: sipush #-885
    //   6422: aload #6
    //   6424: iconst_0
    //   6425: aload #10
    //   6427: iconst_0
    //   6428: iaload
    //   6429: bipush #24
    //   6431: iushr
    //   6432: i2b
    //   6433: bastore
    //   6434: sipush #22014
    //   6437: aload #6
    //   6439: iconst_1
    //   6440: aload #10
    //   6442: iconst_0
    //   6443: iaload
    //   6444: bipush #16
    //   6446: iushr
    //   6447: i2b
    //   6448: bastore
    //   6449: aload #6
    //   6451: iconst_2
    //   6452: aload #10
    //   6454: iconst_0
    //   6455: iaload
    //   6456: bipush #8
    //   6458: iushr
    //   6459: i2b
    //   6460: bastore
    //   6461: aload #6
    //   6463: iconst_3
    //   6464: aload #10
    //   6466: iconst_0
    //   6467: iaload
    //   6468: i2b
    //   6469: bastore
    //   6470: aload #6
    //   6472: iconst_4
    //   6473: aload #10
    //   6475: iconst_1
    //   6476: iaload
    //   6477: bipush #24
    //   6479: iushr
    //   6480: i2b
    //   6481: bastore
    //   6482: aload #6
    //   6484: iconst_5
    //   6485: aload #10
    //   6487: iconst_1
    //   6488: iaload
    //   6489: bipush #16
    //   6491: iushr
    //   6492: i2b
    //   6493: bastore
    //   6494: aload #6
    //   6496: bipush #6
    //   6498: aload #10
    //   6500: iconst_1
    //   6501: iaload
    //   6502: bipush #8
    //   6504: iushr
    //   6505: i2b
    //   6506: bastore
    //   6507: aload #6
    //   6509: bipush #7
    //   6511: aload #10
    //   6513: iconst_1
    //   6514: iaload
    //   6515: i2b
    //   6516: bastore
    //   6517: aload #6
    //   6519: bipush #8
    //   6521: aload #10
    //   6523: iconst_2
    //   6524: iaload
    //   6525: bipush #24
    //   6527: iushr
    //   6528: i2b
    //   6529: bastore
    //   6530: aload #6
    //   6532: bipush #9
    //   6534: aload #10
    //   6536: iconst_2
    //   6537: iaload
    //   6538: bipush #16
    //   6540: iushr
    //   6541: i2b
    //   6542: bastore
    //   6543: aload #6
    //   6545: bipush #10
    //   6547: aload #10
    //   6549: iconst_2
    //   6550: iaload
    //   6551: bipush #8
    //   6553: iushr
    //   6554: i2b
    //   6555: bastore
    //   6556: aload #6
    //   6558: bipush #11
    //   6560: aload #10
    //   6562: iconst_2
    //   6563: iaload
    //   6564: i2b
    //   6565: bastore
    //   6566: aload #6
    //   6568: bipush #12
    //   6570: aload #10
    //   6572: iconst_3
    //   6573: iaload
    //   6574: bipush #24
    //   6576: iushr
    //   6577: i2b
    //   6578: bastore
    //   6579: aload #6
    //   6581: bipush #13
    //   6583: aload #10
    //   6585: iconst_3
    //   6586: iaload
    //   6587: bipush #16
    //   6589: iushr
    //   6590: i2b
    //   6591: bastore
    //   6592: aload #6
    //   6594: bipush #14
    //   6596: aload #10
    //   6598: iconst_3
    //   6599: iaload
    //   6600: bipush #8
    //   6602: iushr
    //   6603: i2b
    //   6604: bastore
    //   6605: aload #6
    //   6607: bipush #15
    //   6609: aload #10
    //   6611: iconst_3
    //   6612: iaload
    //   6613: i2b
    //   6614: bastore
    //   6615: aload #6
    //   6617: bipush #16
    //   6619: aload #10
    //   6621: iconst_4
    //   6622: iaload
    //   6623: bipush #24
    //   6625: iushr
    //   6626: i2b
    //   6627: bastore
    //   6628: aload #6
    //   6630: bipush #17
    //   6632: aload #10
    //   6634: iconst_4
    //   6635: iaload
    //   6636: bipush #16
    //   6638: iushr
    //   6639: i2b
    //   6640: bastore
    //   6641: aload #6
    //   6643: bipush #18
    //   6645: aload #10
    //   6647: iconst_4
    //   6648: iaload
    //   6649: bipush #8
    //   6651: iushr
    //   6652: i2b
    //   6653: bastore
    //   6654: aload #6
    //   6656: bipush #19
    //   6658: aload #10
    //   6660: iconst_4
    //   6661: iaload
    //   6662: i2b
    //   6663: bastore
    //   6664: aload #6
    //   6666: bipush #20
    //   6668: aload #10
    //   6670: iconst_5
    //   6671: iaload
    //   6672: bipush #24
    //   6674: iushr
    //   6675: i2b
    //   6676: bastore
    //   6677: aload #6
    //   6679: bipush #21
    //   6681: aload #10
    //   6683: iconst_5
    //   6684: iaload
    //   6685: bipush #16
    //   6687: iushr
    //   6688: i2b
    //   6689: bastore
    //   6690: aload #6
    //   6692: bipush #22
    //   6694: aload #10
    //   6696: iconst_5
    //   6697: iaload
    //   6698: bipush #8
    //   6700: iushr
    //   6701: i2b
    //   6702: bastore
    //   6703: aload #6
    //   6705: bipush #23
    //   6707: aload #10
    //   6709: iconst_5
    //   6710: iaload
    //   6711: i2b
    //   6712: bastore
    //   6713: aload #6
    //   6715: bipush #24
    //   6717: aload #10
    //   6719: bipush #6
    //   6721: iaload
    //   6722: bipush #24
    //   6724: iushr
    //   6725: i2b
    //   6726: bastore
    //   6727: aload #6
    //   6729: bipush #25
    //   6731: aload #10
    //   6733: bipush #6
    //   6735: iaload
    //   6736: bipush #16
    //   6738: iushr
    //   6739: i2b
    //   6740: bastore
    //   6741: aload #6
    //   6743: bipush #26
    //   6745: aload #10
    //   6747: bipush #6
    //   6749: iaload
    //   6750: bipush #8
    //   6752: iushr
    //   6753: i2b
    //   6754: bastore
    //   6755: aload #6
    //   6757: bipush #27
    //   6759: aload #10
    //   6761: bipush #6
    //   6763: iaload
    //   6764: i2b
    //   6765: bastore
    //   6766: aload #6
    //   6768: bipush #28
    //   6770: aload #10
    //   6772: bipush #7
    //   6774: iaload
    //   6775: bipush #24
    //   6777: iushr
    //   6778: i2b
    //   6779: bastore
    //   6780: aload #6
    //   6782: bipush #29
    //   6784: aload #10
    //   6786: bipush #7
    //   6788: iaload
    //   6789: bipush #16
    //   6791: iushr
    //   6792: i2b
    //   6793: bastore
    //   6794: aload #6
    //   6796: bipush #30
    //   6798: aload #10
    //   6800: bipush #7
    //   6802: iaload
    //   6803: bipush #8
    //   6805: iushr
    //   6806: i2b
    //   6807: bastore
    //   6808: aload #6
    //   6810: bipush #31
    //   6812: aload #10
    //   6814: bipush #7
    //   6816: iaload
    //   6817: i2b
    //   6818: bastore
    //   6819: new java/math/BigInteger
    //   6822: dup
    //   6823: aload #6
    //   6825: invokespecial <init> : ([B)V
    //   6828: invokevirtual abs : ()Ljava/math/BigInteger;
    //   6831: putstatic burp/Zrl5.ZI : Ljava/lang/Object;
    //   6834: invokestatic a : (II)Ljava/lang/String;
    //   6837: iconst_1
    //   6838: ldc burp/Zxyq
    //   6840: invokevirtual getClassLoader : ()Ljava/lang/ClassLoader;
    //   6843: invokestatic forName : (Ljava/lang/String;ZLjava/lang/ClassLoader;)Ljava/lang/Class;
    //   6846: invokevirtual getDeclaredFields : ()[Ljava/lang/reflect/Field;
    //   6849: astore #5
    //   6851: aload #5
    //   6853: arraylength
    //   6854: istore #6
    //   6856: iconst_0
    //   6857: istore #7
    //   6859: iload #7
    //   6861: iload #6
    //   6863: if_icmpge -> 7001
    //   6866: aload #5
    //   6868: iload #7
    //   6870: aaload
    //   6871: astore #8
    //   6873: aload #8
    //   6875: invokevirtual getModifiers : ()I
    //   6878: invokestatic isStatic : (I)Z
    //   6881: ifne -> 6891
    //   6884: goto -> 6994
    //   6887: invokestatic a : (Ljava/lang/Throwable;)Ljava/lang/Throwable;
    //   6890: athrow
    //   6891: aload #8
    //   6893: invokevirtual getType : ()Ljava/lang/Class;
    //   6896: astore #9
    //   6898: aload #9
    //   6900: ifnull -> 6981
    //   6903: aload #9
    //   6905: invokevirtual isPrimitive : ()Z
    //   6908: ifne -> 6981
    //   6911: goto -> 6918
    //   6914: invokestatic a : (Ljava/lang/Throwable;)Ljava/lang/Throwable;
    //   6917: athrow
    //   6918: aload #9
    //   6920: invokevirtual getPackage : ()Ljava/lang/Package;
    //   6923: ifnull -> 6981
    //   6926: goto -> 6933
    //   6929: invokestatic a : (Ljava/lang/Throwable;)Ljava/lang/Throwable;
    //   6932: athrow
    //   6933: aload #9
    //   6935: invokevirtual getPackage : ()Ljava/lang/Package;
    //   6938: invokevirtual getName : ()Ljava/lang/String;
    //   6941: ifnull -> 6981
    //   6944: goto -> 6951
    //   6947: invokestatic a : (Ljava/lang/Throwable;)Ljava/lang/Throwable;
    //   6950: athrow
    //   6951: aload #9
    //   6953: invokevirtual getPackage : ()Ljava/lang/Package;
    //   6956: invokevirtual getName : ()Ljava/lang/String;
    //   6959: sipush #-882
    //   6962: sipush #13404
    //   6965: invokestatic a : (II)Ljava/lang/String;
    //   6968: invokevirtual startsWith : (Ljava/lang/String;)Z
    //   6971: ifne -> 6981
    //   6974: goto -> 6981
    //   6977: invokestatic a : (Ljava/lang/Throwable;)Ljava/lang/Throwable;
    //   6980: athrow
    //   6981: aload #8
    //   6983: iconst_1
    //   6984: invokevirtual setAccessible : (Z)V
    //   6987: aload #8
    //   6989: aconst_null
    //   6990: invokevirtual get : (Ljava/lang/Object;)Ljava/lang/Object;
    //   6993: pop
    //   6994: iinc #7, 1
    //   6997: iload_2
    //   6998: ifeq -> 6859
    //   7001: sipush #-886
    //   7004: sipush #5749
    //   7007: invokestatic a : (II)Ljava/lang/String;
    //   7010: invokestatic forName : (Ljava/lang/String;)Ljava/lang/Class;
    //   7013: invokevirtual getDeclaredMethods : ()[Ljava/lang/reflect/Method;
    //   7016: astore #5
    //   7018: aload #5
    //   7020: arraylength
    //   7021: istore #6
    //   7023: iconst_0
    //   7024: istore #7
    //   7026: iload #7
    //   7028: iload #6
    //   7030: if_icmpge -> 7163
    //   7033: aload #5
    //   7035: iload #7
    //   7037: aaload
    //   7038: astore #8
    //   7040: aload #8
    //   7042: invokevirtual getParameterTypes : ()[Ljava/lang/Class;
    //   7045: pop
    //   7046: aload #8
    //   7048: invokevirtual getModifiers : ()I
    //   7051: invokestatic isStatic : (I)Z
    //   7054: ifeq -> 7149
    //   7057: aload #8
    //   7059: invokevirtual getParameterTypes : ()[Ljava/lang/Class;
    //   7062: arraylength
    //   7063: iconst_2
    //   7064: if_icmpne -> 7149
    //   7067: goto -> 7074
    //   7070: invokestatic a : (Ljava/lang/Throwable;)Ljava/lang/Throwable;
    //   7073: athrow
    //   7074: aload #8
    //   7076: invokevirtual getReturnType : ()Ljava/lang/Class;
    //   7079: getstatic java/lang/Void.TYPE : Ljava/lang/Class;
    //   7082: invokevirtual equals : (Ljava/lang/Object;)Z
    //   7085: ifeq -> 7149
    //   7088: goto -> 7095
    //   7091: invokestatic a : (Ljava/lang/Throwable;)Ljava/lang/Throwable;
    //   7094: athrow
    //   7095: aload #8
    //   7097: iconst_1
    //   7098: invokevirtual setAccessible : (Z)V
    //   7101: aload #8
    //   7103: aconst_null
    //   7104: iconst_2
    //   7105: anewarray java/lang/Object
    //   7108: dup
    //   7109: iconst_0
    //   7110: aload_0
    //   7111: aastore
    //   7112: dup
    //   7113: iconst_1
    //   7114: aload_1
    //   7115: ifnonnull -> 7133
    //   7118: goto -> 7125
    //   7121: invokestatic a : (Ljava/lang/Throwable;)Ljava/lang/Throwable;
    //   7124: athrow
    //   7125: aload_1
    //   7126: goto -> 7140
    //   7129: invokestatic a : (Ljava/lang/Throwable;)Ljava/lang/Throwable;
    //   7132: athrow
    //   7133: aload_1
    //   7134: checkcast [B
    //   7137: invokevirtual clone : ()Ljava/lang/Object;
    //   7140: aastore
    //   7141: invokevirtual invoke : (Ljava/lang/Object;[Ljava/lang/Object;)Ljava/lang/Object;
    //   7144: pop
    //   7145: iload_2
    //   7146: ifeq -> 7163
    //   7149: iinc #7, 1
    //   7152: iload_2
    //   7153: ifeq -> 7026
    //   7156: goto -> 7163
    //   7159: invokestatic a : (Ljava/lang/Throwable;)Ljava/lang/Throwable;
    //   7162: athrow
    //   7163: getstatic burp/Zzn6.Za : Ljava/lang/String;
    //   7166: getstatic burp/Zxdp.ZW : Ljava/lang/Object;
    //   7169: checkcast java/math/BigInteger
    //   7172: invokevirtual intValue : ()I
    //   7175: bipush #32
    //   7177: irem
    //   7178: invokestatic abs : (I)I
    //   7181: invokevirtual charAt : (I)C
    //   7184: getstatic burp/Ze2w.Za : Ljava/lang/String;
    //   7187: getstatic burp/Zmhq.ZK : Ljava/lang/Object;
    //   7190: checkcast java/math/BigInteger
    //   7193: invokevirtual intValue : ()I
    //   7196: bipush #32
    //   7198: irem
    //   7199: invokestatic abs : (I)I
    //   7202: invokevirtual charAt : (I)C
    //   7205: if_icmple -> 7312
    //   7208: getstatic burp/Zml9.Zw : Ljava/lang/String;
    //   7211: getstatic burp/Zrkd.ZO : Ljava/lang/Object;
    //   7214: checkcast java/math/BigInteger
    //   7217: invokevirtual intValue : ()I
    //   7220: bipush #32
    //   7222: irem
    //   7223: invokestatic abs : (I)I
    //   7226: invokevirtual charAt : (I)C
    //   7229: getstatic burp/Zrex.Za : Ljava/lang/String;
    //   7232: getstatic burp/Zr9u.ZX : Ljava/lang/Object;
    //   7235: checkcast java/math/BigInteger
    //   7238: invokevirtual intValue : ()I
    //   7241: bipush #32
    //   7243: irem
    //   7244: invokestatic abs : (I)I
    //   7247: invokevirtual charAt : (I)C
    //   7250: if_icmpgt -> 7312
    //   7253: goto -> 7260
    //   7256: invokestatic a : (Ljava/lang/Throwable;)Ljava/lang/Throwable;
    //   7259: athrow
    //   7260: getstatic burp/Zz5e.Zd : Ljava/lang/String;
    //   7263: getstatic burp/Zbsz.ZP : Ljava/lang/Object;
    //   7266: checkcast java/math/BigInteger
    //   7269: invokevirtual intValue : ()I
    //   7272: bipush #32
    //   7274: irem
    //   7275: invokestatic abs : (I)I
    //   7278: invokevirtual charAt : (I)C
    //   7281: getstatic burp/Zmtr.Zd : Ljava/lang/String;
    //   7284: getstatic burp/Ztvy.ZH : Ljava/lang/Object;
    //   7287: checkcast java/math/BigInteger
    //   7290: invokevirtual intValue : ()I
    //   7293: bipush #32
    //   7295: irem
    //   7296: invokestatic abs : (I)I
    //   7299: invokevirtual charAt : (I)C
    //   7302: if_icmpgt -> 7320
    //   7305: goto -> 7312
    //   7308: invokestatic a : (Ljava/lang/Throwable;)Ljava/lang/Throwable;
    //   7311: athrow
    //   7312: iconst_1
    //   7313: goto -> 7321
    //   7316: invokestatic a : (Ljava/lang/Throwable;)Ljava/lang/Throwable;
    //   7319: athrow
    //   7320: iconst_0
    //   7321: ireturn
    //   7322: astore_3
    //   7323: new java/lang/Exception
    //   7326: dup
    //   7327: aload_3
    //   7328: invokevirtual getMessage : ()Ljava/lang/String;
    //   7331: invokespecial <init> : (Ljava/lang/String;)V
    //   7334: athrow
    // Exception table:
    //   from	to	target	type
    //   4	7321	7322	java/lang/Throwable
    //   22	198	201	java/lang/Throwable
    //   168	235	238	java/lang/Throwable
    //   205	272	275	java/lang/Throwable
    //   242	309	312	java/lang/Throwable
    //   279	346	349	java/lang/Throwable
    //   316	383	386	java/lang/Throwable
    //   353	420	423	java/lang/Throwable
    //   390	457	460	java/lang/Throwable
    //   427	494	497	java/lang/Throwable
    //   464	531	534	java/lang/Throwable
    //   501	568	571	java/lang/Throwable
    //   538	605	608	java/lang/Throwable
    //   575	642	645	java/lang/Throwable
    //   612	679	682	java/lang/Throwable
    //   649	716	719	java/lang/Throwable
    //   686	753	756	java/lang/Throwable
    //   723	790	793	java/lang/Throwable
    //   760	827	830	java/lang/Throwable
    //   797	864	867	java/lang/Throwable
    //   834	901	904	java/lang/Throwable
    //   871	938	941	java/lang/Throwable
    //   908	975	978	java/lang/Throwable
    //   945	1012	1015	java/lang/Throwable
    //   982	1049	1052	java/lang/Throwable
    //   1019	1086	1089	java/lang/Throwable
    //   1056	1123	1126	java/lang/Throwable
    //   1093	1160	1163	java/lang/Throwable
    //   1130	1197	1200	java/lang/Throwable
    //   1167	1234	1237	java/lang/Throwable
    //   1204	1271	1274	java/lang/Throwable
    //   1241	1308	1311	java/lang/Throwable
    //   1278	1341	1344	java/lang/Throwable
    //   1381	1555	1558	java/lang/Throwable
    //   1524	1593	1596	java/lang/Throwable
    //   1562	1631	1634	java/lang/Throwable
    //   1600	1669	1672	java/lang/Throwable
    //   1638	1707	1710	java/lang/Throwable
    //   1676	1745	1748	java/lang/Throwable
    //   1714	1783	1786	java/lang/Throwable
    //   1752	1821	1824	java/lang/Throwable
    //   1790	1859	1862	java/lang/Throwable
    //   1828	1897	1900	java/lang/Throwable
    //   1866	1935	1938	java/lang/Throwable
    //   1904	1973	1976	java/lang/Throwable
    //   1942	2011	2014	java/lang/Throwable
    //   1980	2049	2052	java/lang/Throwable
    //   2018	2087	2090	java/lang/Throwable
    //   2056	2125	2128	java/lang/Throwable
    //   2094	2163	2166	java/lang/Throwable
    //   2132	2201	2204	java/lang/Throwable
    //   2170	2239	2242	java/lang/Throwable
    //   2208	2277	2280	java/lang/Throwable
    //   2246	2315	2318	java/lang/Throwable
    //   2284	2353	2356	java/lang/Throwable
    //   2322	2391	2394	java/lang/Throwable
    //   2360	2429	2432	java/lang/Throwable
    //   2398	2467	2470	java/lang/Throwable
    //   2436	2505	2508	java/lang/Throwable
    //   2474	2543	2546	java/lang/Throwable
    //   2512	2581	2584	java/lang/Throwable
    //   2550	2619	2622	java/lang/Throwable
    //   2588	2657	2660	java/lang/Throwable
    //   2626	2695	2698	java/lang/Throwable
    //   2664	2729	2732	java/lang/Throwable
    //   3554	3588	3591	java/lang/Throwable
    //   3684	3762	3765	java/lang/Throwable
    //   3691	3905	3908	java/lang/Throwable
    //   4283	4298	4298	java/lang/Throwable
    //   4325	4359	4362	java/lang/Throwable
    //   4369	4381	4384	java/lang/Throwable
    //   4467	4545	4548	java/lang/Throwable
    //   4474	4688	4691	java/lang/Throwable
    //   5088	5166	5169	java/lang/Throwable
    //   5095	5309	5312	java/lang/Throwable
    //   5756	5790	5793	java/lang/Throwable
    //   5797	5809	5812	java/lang/Throwable
    //   5895	5973	5976	java/lang/Throwable
    //   5902	6116	6119	java/lang/Throwable
    //   6873	6887	6887	java/lang/Throwable
    //   6898	6911	6914	java/lang/Throwable
    //   6903	6926	6929	java/lang/Throwable
    //   6918	6944	6947	java/lang/Throwable
    //   6933	6974	6977	java/lang/Throwable
    //   7040	7067	7070	java/lang/Throwable
    //   7057	7088	7091	java/lang/Throwable
    //   7074	7118	7121	java/lang/Throwable
    //   7095	7129	7129	java/lang/Throwable
    //   7140	7156	7159	java/lang/Throwable
    //   7163	7253	7256	java/lang/Throwable
    //   7208	7305	7308	java/lang/Throwable
    //   7260	7316	7316	java/lang/Throwable
  }
  
  static {
    // Byte code:
    //   0: bipush #8
    //   2: anewarray java/lang/String
    //   5: astore #5
    //   7: iconst_0
    //   8: istore_3
    //   9: ldc '{\\t\\bO@\\tq \\f n1P(Vb}5K6-\\b\\b_mKT\\b\tfX\'
    //   11: dup
    //   12: astore_2
    //   13: invokevirtual length : ()I
    //   16: istore #4
    //   18: iconst_4
    //   19: istore_1
    //   20: iconst_m1
    //   21: istore_0
    //   22: bipush #96
    //   24: iinc #0, 1
    //   27: aload_2
    //   28: iload_0
    //   29: dup
    //   30: iload_1
    //   31: iadd
    //   32: invokevirtual substring : (II)Ljava/lang/String;
    //   35: iconst_m1
    //   36: goto -> 142
    //   39: aload #5
    //   41: swap
    //   42: iload_3
    //   43: iinc #3, 1
    //   46: swap
    //   47: aastore
    //   48: iload_0
    //   49: iload_1
    //   50: iadd
    //   51: dup
    //   52: istore_0
    //   53: iload #4
    //   55: if_icmpge -> 67
    //   58: aload_2
    //   59: iload_0
    //   60: invokevirtual charAt : (I)C
    //   63: istore_1
    //   64: goto -> 22
    //   67: ldc 'o\\b;~d+SLN*eH(~fcMsmjE\\fmr Uze?\\rXzXn@,'
    //   69: dup
    //   70: astore_2
    //   71: invokevirtual length : ()I
    //   74: istore #4
    //   76: bipush #32
    //   78: istore_1
    //   79: iconst_m1
    //   80: istore_0
    //   81: bipush #62
    //   83: iinc #0, 1
    //   86: aload_2
    //   87: iload_0
    //   88: dup
    //   89: iload_1
    //   90: iadd
    //   91: invokevirtual substring : (II)Ljava/lang/String;
    //   94: iconst_0
    //   95: goto -> 142
    //   98: aload #5
    //   100: swap
    //   101: iload_3
    //   102: iinc #3, 1
    //   105: swap
    //   106: aastore
    //   107: iload_0
    //   108: iload_1
    //   109: iadd
    //   110: dup
    //   111: istore_0
    //   112: iload #4
    //   114: if_icmpge -> 126
    //   117: aload_2
    //   118: iload_0
    //   119: invokevirtual charAt : (I)C
    //   122: istore_1
    //   123: goto -> 81
    //   126: aload #5
    //   128: putstatic burp/Ze2w.a : [Ljava/lang/String;
    //   131: bipush #8
    //   133: anewarray java/lang/String
    //   136: putstatic burp/Ze2w.b : [Ljava/lang/String;
    //   139: goto -> 300
    //   142: dup_x2
    //   143: pop
    //   144: invokevirtual toCharArray : ()[C
    //   147: dup_x1
    //   148: arraylength
    //   149: dup_x2
    //   150: pop
    //   151: iconst_0
    //   152: istore #6
    //   154: dup2_x1
    //   155: pop2
    //   156: dup_x2
    //   157: iconst_1
    //   158: if_icmpgt -> 260
    //   161: dup2
    //   162: swap
    //   163: iload #6
    //   165: dup2_x1
    //   166: caload
    //   167: swap
    //   168: iload #6
    //   170: bipush #7
    //   172: irem
    //   173: tableswitch default -> 242, 0 -> 212, 1 -> 217, 2 -> 222, 3 -> 227, 4 -> 232, 5 -> 237
    //   212: bipush #93
    //   214: goto -> 244
    //   217: bipush #107
    //   219: goto -> 244
    //   222: bipush #13
    //   224: goto -> 244
    //   227: bipush #85
    //   229: goto -> 244
    //   232: bipush #57
    //   234: goto -> 244
    //   237: bipush #52
    //   239: goto -> 244
    //   242: bipush #84
    //   244: ixor
    //   245: ixor
    //   246: i2c
    //   247: castore
    //   248: iinc #6, 1
    //   251: dup
    //   252: ifne -> 260
    //   255: dup2
    //   256: dup_x1
    //   257: goto -> 165
    //   260: dup2_x1
    //   261: pop2
    //   262: dup_x2
    //   263: iload #6
    //   265: if_icmpgt -> 161
    //   268: pop
    //   269: new java/lang/String
    //   272: dup_x1
    //   273: swap
    //   274: invokespecial <init> : ([C)V
    //   277: invokevirtual intern : ()Ljava/lang/String;
    //   280: swap
    //   281: pop
    //   282: swap
    //   283: tableswitch default -> 39, 0 -> 98
    //   300: sipush #-883
    //   303: sipush #-1503
    //   306: invokestatic a : (II)Ljava/lang/String;
    //   309: putstatic burp/Ze2w.Za : Ljava/lang/String;
    //   312: new java/math/BigInteger
    //   315: dup
    //   316: iconst_1
    //   317: bipush #32
    //   319: newarray byte
    //   321: dup
    //   322: iconst_0
    //   323: bipush #103
    //   325: bastore
    //   326: dup
    //   327: iconst_1
    //   328: bipush #80
    //   330: bastore
    //   331: dup
    //   332: iconst_2
    //   333: bipush #-37
    //   335: bastore
    //   336: dup
    //   337: iconst_3
    //   338: bipush #60
    //   340: bastore
    //   341: dup
    //   342: iconst_4
    //   343: bipush #85
    //   345: bastore
    //   346: dup
    //   347: iconst_5
    //   348: bipush #-122
    //   350: bastore
    //   351: dup
    //   352: bipush #6
    //   354: bipush #76
    //   356: bastore
    //   357: dup
    //   358: bipush #7
    //   360: bipush #42
    //   362: bastore
    //   363: dup
    //   364: bipush #8
    //   366: bipush #-35
    //   368: bastore
    //   369: dup
    //   370: bipush #9
    //   372: bipush #-128
    //   374: bastore
    //   375: dup
    //   376: bipush #10
    //   378: bipush #36
    //   380: bastore
    //   381: dup
    //   382: bipush #11
    //   384: bipush #-15
    //   386: bastore
    //   387: dup
    //   388: bipush #12
    //   390: bipush #87
    //   392: bastore
    //   393: dup
    //   394: bipush #13
    //   396: bipush #-89
    //   398: bastore
    //   399: dup
    //   400: bipush #14
    //   402: bipush #112
    //   404: bastore
    //   405: dup
    //   406: bipush #15
    //   408: bipush #10
    //   410: bastore
    //   411: dup
    //   412: bipush #16
    //   414: bipush #-45
    //   416: bastore
    //   417: dup
    //   418: bipush #17
    //   420: bipush #74
    //   422: bastore
    //   423: dup
    //   424: bipush #18
    //   426: bipush #17
    //   428: bastore
    //   429: dup
    //   430: bipush #19
    //   432: bipush #11
    //   434: bastore
    //   435: dup
    //   436: bipush #20
    //   438: bipush #126
    //   440: bastore
    //   441: dup
    //   442: bipush #21
    //   444: bipush #-85
    //   446: bastore
    //   447: dup
    //   448: bipush #22
    //   450: bipush #-125
    //   452: bastore
    //   453: dup
    //   454: bipush #23
    //   456: bipush #11
    //   458: bastore
    //   459: dup
    //   460: bipush #24
    //   462: bipush #32
    //   464: bastore
    //   465: dup
    //   466: bipush #25
    //   468: bipush #-5
    //   470: bastore
    //   471: dup
    //   472: bipush #26
    //   474: bipush #34
    //   476: bastore
    //   477: dup
    //   478: bipush #27
    //   480: bipush #125
    //   482: bastore
    //   483: dup
    //   484: bipush #28
    //   486: bipush #64
    //   488: bastore
    //   489: dup
    //   490: bipush #29
    //   492: bipush #89
    //   494: bastore
    //   495: dup
    //   496: bipush #30
    //   498: bipush #-28
    //   500: bastore
    //   501: dup
    //   502: bipush #31
    //   504: bipush #-89
    //   506: bastore
    //   507: invokespecial <init> : (I[B)V
    //   510: putstatic burp/Ze2w.ZA : Ljava/lang/Object;
    //   513: return
  }
  
  private static Throwable a(Throwable paramThrowable) {
    return paramThrowable;
  }
  
  private static String a(int paramInt1, int paramInt2) {
    int i = (paramInt1 ^ 0xFFFFFC8E) & 0xFFFF;
    if (b[i] == null) {
      char[] arrayOfChar = a[i].toCharArray();
      switch (arrayOfChar[0] & 0xFF) {
        case 0:
        
        case 1:
        
        case 2:
        
        case 3:
        
        case 4:
        
        case 5:
        
        case 6:
        
        case 7:
        
        case 8:
        
        case 9:
        
        case 10:
        
        case 11:
        
        case 12:
        
        case 13:
        
        case 14:
        
        case 15:
        
        case 16:
        
        case 17:
        
        case 18:
        
        case 19:
        
        case 20:
        
        case 21:
        
        case 22:
        
        case 23:
        
        case 24:
        
        case 25:
        
        case 26:
        
        case 27:
        
        case 28:
        
        case 29:
        
        case 30:
        
        case 31:
        
        case 32:
        
        case 33:
        
        case 34:
        
        case 35:
        
        case 36:
        
        case 37:
        
        case 38:
        
        case 39:
        
        case 40:
        
        case 41:
        
        case 42:
        
        case 43:
        
        case 44:
        
        case 45:
        
        case 46:
        
        case 47:
        
        case 48:
        
        case 49:
        
        case 50:
        
        case 51:
        
        case 52:
        
        case 53:
        
        case 54:
        
        case 55:
        
        case 56:
        
        case 57:
        
        case 58:
        
        case 59:
        
        case 60:
        
        case 61:
        
        case 62:
        
        case 63:
        
        case 64:
        
        case 65:
        
        case 66:
        
        case 67:
        
        case 68:
        
        case 69:
        
        case 70:
        
        case 71:
        
        case 72:
        
        case 73:
        
        case 74:
        
        case 75:
        
        case 76:
        
        case 77:
        
        case 78:
        
        case 79:
        
        case 80:
        
        case 81:
        
        case 82:
        
        case 83:
        
        case 84:
        
        case 85:
        
        case 86:
        
        case 87:
        
        case 88:
        
        case 89:
        
        case 90:
        
        case 91:
        
        case 92:
        
        case 93:
        
        case 94:
        
        case 95:
        
        case 96:
        
        case 97:
        
        case 98:
        
        case 99:
        
        case 100:
        
        case 101:
        
        case 102:
        
        case 103:
        
        case 104:
        
        case 105:
        
        case 106:
        
        case 107:
        
        case 108:
        
        case 109:
        
        case 110:
        
        case 111:
        
        case 112:
        
        case 113:
        
        case 114:
        
        case 115:
        
        case 116:
        
        case 117:
        
        case 118:
        
        case 119:
        
        case 120:
        
        case 121:
        
        case 122:
        
        case 123:
        
        case 124:
        
        case 125:
        
        case 126:
        
        case 127:
        
        case 128:
        
        case 129:
        
        case 130:
        
        case 131:
        
        case 132:
        
        case 133:
        
        case 134:
        
        case 135:
        
        case 136:
        
        case 137:
        
        case 138:
        
        case 139:
        
        case 140:
        
        case 141:
        
        case 142:
        
        case 143:
        
        case 144:
        
        case 145:
        
        case 146:
        
        case 147:
        
        case 148:
        
        case 149:
        
        case 150:
        
        case 151:
        
        case 152:
        
        case 153:
        
        case 154:
        
        case 155:
        
        case 156:
        
        case 157:
        
        case 158:
        
        case 159:
        
        case 160:
        
        case 161:
        
        case 162:
        
        case 163:
        
        case 164:
        
        case 165:
        
        case 166:
        
        case 167:
        
        case 168:
        
        case 169:
        
        case 170:
        
        case 171:
        
        case 172:
        
        case 173:
        
        case 174:
        
        case 175:
        
        case 176:
        
        case 177:
        
        case 178:
        
        case 179:
        
        case 180:
        
        case 181:
        
        case 182:
        
        case 183:
        
        case 184:
        
        case 185:
        
        case 186:
        
        case 187:
        
        case 188:
        
        case 189:
        
        case 190:
        
        case 191:
        
        case 192:
        
        case 193:
        
        case 194:
        
        case 195:
        
        case 196:
        
        case 197:
        
        case 198:
        
        case 199:
        
        case 200:
        
        case 201:
        
        case 202:
        
        case 203:
        
        case 204:
        
        case 205:
        
        case 206:
        
        case 207:
        
        case 208:
        
        case 209:
        
        case 210:
        
        case 211:
        
        case 212:
        
        case 213:
        
        case 214:
        
        case 215:
        
        case 216:
        
        case 217:
        
        case 218:
        
        case 219:
        
        case 220:
        
        case 221:
        
        case 222:
        
        case 223:
        
        case 224:
        
        case 225:
        
        case 226:
        
        case 227:
        
        case 228:
        
        case 229:
        
        case 230:
        
        case 231:
        
        case 232:
        
        case 233:
        
        case 234:
        
        case 235:
        
        case 236:
        
        case 237:
        
        case 238:
        
        case 239:
        
        case 240:
        
        case 241:
        
        case 242:
        
        case 243:
        
        case 244:
        
        case 245:
        
        case 246:
        
        case 247:
        
        case 248:
        
        case 249:
        
        case 250:
        
        case 251:
        
        case 252:
        
        case 253:
        
        case 254:
        
        default:
          break;
      } 
      byte b1 = 98;
      int j = (paramInt2 & 0xFF) - b1;
      if (j < 0)
        j += 256; 
      int k = ((paramInt2 & 0xFFFF) >>> 8) - b1;
      if (k < 0)
        k += 256; 
      for (byte b2 = 0; b2 < arrayOfChar.length; b2++) {
        int m = b2 % 2;
        if (m == 0) {
          arrayOfChar[b2] = (char)(arrayOfChar[b2] ^ j);
          j = ((j >>> 3 | j << 5) ^ arrayOfChar[b2]) & 0xFF;
        } else {
          arrayOfChar[b2] = (char)(arrayOfChar[b2] ^ k);
          k = ((k >>> 3 | k << 5) ^ arrayOfChar[b2]) & 0xFF;
        } 
      } 
      b[i] = (new String(arrayOfChar)).intern();
    } 
    return b[i];
  }
}


/* Location:              C:\Program Files\BurpSuitePro\burpsuite_pro.jar!\burp\Ze2w.class
 * Java compiler version: 21 (65.0)
 * JD-Core Version:       1.1.3
 */