package burp;

import java.math.BigInteger;

class Ze3d extends ClassLoader {
  static Object Ze;
  
  static String ZL;
  
  private static final String[] a;
  
  private static final String[] b;
  
  static boolean ZT(Object[] paramArrayOfObject, Object paramObject) throws Throwable {
    // Byte code:
    //   0: invokestatic ZN : ()Z
    //   3: istore_2
    //   4: new java/lang/StringBuilder
    //   7: dup
    //   8: invokespecial <init> : ()V
    //   11: astore_3
    //   12: iconst_0
    //   13: istore #4
    //   15: iload #4
    //   17: bipush #32
    //   19: if_icmpge -> 1355
    //   22: iload #4
    //   24: tableswitch default -> 1348, 0 -> 168, 1 -> 205, 2 -> 242, 3 -> 279, 4 -> 316, 5 -> 353, 6 -> 390, 7 -> 427, 8 -> 464, 9 -> 501, 10 -> 538, 11 -> 575, 12 -> 612, 13 -> 649, 14 -> 686, 15 -> 723, 16 -> 760, 17 -> 797, 18 -> 834, 19 -> 871, 20 -> 908, 21 -> 945, 22 -> 982, 23 -> 1019, 24 -> 1056, 25 -> 1093, 26 -> 1130, 27 -> 1167, 28 -> 1204, 29 -> 1241, 30 -> 1278, 31 -> 1315
    //   168: aload_3
    //   169: getstatic burp/Ze3d.ZL : Ljava/lang/String;
    //   172: getstatic burp/Zsm3.ZC : Ljava/lang/Object;
    //   175: checkcast java/math/BigInteger
    //   178: invokevirtual intValue : ()I
    //   181: bipush #32
    //   183: irem
    //   184: invokestatic abs : (I)I
    //   187: invokevirtual charAt : (I)C
    //   190: invokevirtual append : (C)Ljava/lang/StringBuilder;
    //   193: pop
    //   194: iload_2
    //   195: ifne -> 1348
    //   198: goto -> 205
    //   201: invokestatic a : (Ljava/lang/Throwable;)Ljava/lang/Throwable;
    //   204: athrow
    //   205: aload_3
    //   206: getstatic burp/Zeh9.ZF : Ljava/lang/String;
    //   209: getstatic burp/Zzk9.ZK : Ljava/lang/Object;
    //   212: checkcast java/math/BigInteger
    //   215: invokevirtual intValue : ()I
    //   218: bipush #32
    //   220: irem
    //   221: invokestatic abs : (I)I
    //   224: invokevirtual charAt : (I)C
    //   227: invokevirtual append : (C)Ljava/lang/StringBuilder;
    //   230: pop
    //   231: iload_2
    //   232: ifne -> 1348
    //   235: goto -> 242
    //   238: invokestatic a : (Ljava/lang/Throwable;)Ljava/lang/Throwable;
    //   241: athrow
    //   242: aload_3
    //   243: getstatic burp/Zkfz.Zs : Ljava/lang/String;
    //   246: getstatic burp/Zr0g.Zj : Ljava/lang/Object;
    //   249: checkcast java/math/BigInteger
    //   252: invokevirtual intValue : ()I
    //   255: bipush #32
    //   257: irem
    //   258: invokestatic abs : (I)I
    //   261: invokevirtual charAt : (I)C
    //   264: invokevirtual append : (C)Ljava/lang/StringBuilder;
    //   267: pop
    //   268: iload_2
    //   269: ifne -> 1348
    //   272: goto -> 279
    //   275: invokestatic a : (Ljava/lang/Throwable;)Ljava/lang/Throwable;
    //   278: athrow
    //   279: aload_3
    //   280: getstatic burp/Zsxm.Zq : Ljava/lang/String;
    //   283: getstatic burp/Zxl5.Zh : Ljava/lang/Object;
    //   286: checkcast java/math/BigInteger
    //   289: invokevirtual intValue : ()I
    //   292: bipush #32
    //   294: irem
    //   295: invokestatic abs : (I)I
    //   298: invokevirtual charAt : (I)C
    //   301: invokevirtual append : (C)Ljava/lang/StringBuilder;
    //   304: pop
    //   305: iload_2
    //   306: ifne -> 1348
    //   309: goto -> 316
    //   312: invokestatic a : (Ljava/lang/Throwable;)Ljava/lang/Throwable;
    //   315: athrow
    //   316: aload_3
    //   317: getstatic burp/Zmj4.ZM : Ljava/lang/String;
    //   320: getstatic burp/Zxzj.ZO : Ljava/lang/Object;
    //   323: checkcast java/math/BigInteger
    //   326: invokevirtual intValue : ()I
    //   329: bipush #32
    //   331: irem
    //   332: invokestatic abs : (I)I
    //   335: invokevirtual charAt : (I)C
    //   338: invokevirtual append : (C)Ljava/lang/StringBuilder;
    //   341: pop
    //   342: iload_2
    //   343: ifne -> 1348
    //   346: goto -> 353
    //   349: invokestatic a : (Ljava/lang/Throwable;)Ljava/lang/Throwable;
    //   352: athrow
    //   353: aload_3
    //   354: getstatic burp/Zsxm.Zq : Ljava/lang/String;
    //   357: getstatic burp/Zg99.ZZ : Ljava/lang/Object;
    //   360: checkcast java/math/BigInteger
    //   363: invokevirtual intValue : ()I
    //   366: bipush #32
    //   368: irem
    //   369: invokestatic abs : (I)I
    //   372: invokevirtual charAt : (I)C
    //   375: invokevirtual append : (C)Ljava/lang/StringBuilder;
    //   378: pop
    //   379: iload_2
    //   380: ifne -> 1348
    //   383: goto -> 390
    //   386: invokestatic a : (Ljava/lang/Throwable;)Ljava/lang/Throwable;
    //   389: athrow
    //   390: aload_3
    //   391: getstatic burp/Zter.ZE : Ljava/lang/String;
    //   394: getstatic burp/Zes_.ZJ : Ljava/lang/Object;
    //   397: checkcast java/math/BigInteger
    //   400: invokevirtual intValue : ()I
    //   403: bipush #32
    //   405: irem
    //   406: invokestatic abs : (I)I
    //   409: invokevirtual charAt : (I)C
    //   412: invokevirtual append : (C)Ljava/lang/StringBuilder;
    //   415: pop
    //   416: iload_2
    //   417: ifne -> 1348
    //   420: goto -> 427
    //   423: invokestatic a : (Ljava/lang/Throwable;)Ljava/lang/Throwable;
    //   426: athrow
    //   427: aload_3
    //   428: getstatic burp/Zkmx.Zg : Ljava/lang/String;
    //   431: getstatic burp/Zsxj.Zi : Ljava/lang/Object;
    //   434: checkcast java/math/BigInteger
    //   437: invokevirtual intValue : ()I
    //   440: bipush #32
    //   442: irem
    //   443: invokestatic abs : (I)I
    //   446: invokevirtual charAt : (I)C
    //   449: invokevirtual append : (C)Ljava/lang/StringBuilder;
    //   452: pop
    //   453: iload_2
    //   454: ifne -> 1348
    //   457: goto -> 464
    //   460: invokestatic a : (Ljava/lang/Throwable;)Ljava/lang/Throwable;
    //   463: athrow
    //   464: aload_3
    //   465: getstatic burp/Zsde.Zi : Ljava/lang/String;
    //   468: getstatic burp/Zsgl.Zn : Ljava/lang/Object;
    //   471: checkcast java/math/BigInteger
    //   474: invokevirtual intValue : ()I
    //   477: bipush #32
    //   479: irem
    //   480: invokestatic abs : (I)I
    //   483: invokevirtual charAt : (I)C
    //   486: invokevirtual append : (C)Ljava/lang/StringBuilder;
    //   489: pop
    //   490: iload_2
    //   491: ifne -> 1348
    //   494: goto -> 501
    //   497: invokestatic a : (Ljava/lang/Throwable;)Ljava/lang/Throwable;
    //   500: athrow
    //   501: aload_3
    //   502: getstatic burp/Zl2g.ZI : Ljava/lang/String;
    //   505: getstatic burp/Zk9s.ZY : Ljava/lang/Object;
    //   508: checkcast java/math/BigInteger
    //   511: invokevirtual intValue : ()I
    //   514: bipush #32
    //   516: irem
    //   517: invokestatic abs : (I)I
    //   520: invokevirtual charAt : (I)C
    //   523: invokevirtual append : (C)Ljava/lang/StringBuilder;
    //   526: pop
    //   527: iload_2
    //   528: ifne -> 1348
    //   531: goto -> 538
    //   534: invokestatic a : (Ljava/lang/Throwable;)Ljava/lang/Throwable;
    //   537: athrow
    //   538: aload_3
    //   539: getstatic burp/Zk8b.ZT : Ljava/lang/String;
    //   542: getstatic burp/Ztnw.Zt : Ljava/lang/Object;
    //   545: checkcast java/math/BigInteger
    //   548: invokevirtual intValue : ()I
    //   551: bipush #32
    //   553: irem
    //   554: invokestatic abs : (I)I
    //   557: invokevirtual charAt : (I)C
    //   560: invokevirtual append : (C)Ljava/lang/StringBuilder;
    //   563: pop
    //   564: iload_2
    //   565: ifne -> 1348
    //   568: goto -> 575
    //   571: invokestatic a : (Ljava/lang/Throwable;)Ljava/lang/Throwable;
    //   574: athrow
    //   575: aload_3
    //   576: getstatic burp/Zgss.Zc : Ljava/lang/String;
    //   579: getstatic burp/Zlos.Zk : Ljava/lang/Object;
    //   582: checkcast java/math/BigInteger
    //   585: invokevirtual intValue : ()I
    //   588: bipush #32
    //   590: irem
    //   591: invokestatic abs : (I)I
    //   594: invokevirtual charAt : (I)C
    //   597: invokevirtual append : (C)Ljava/lang/StringBuilder;
    //   600: pop
    //   601: iload_2
    //   602: ifne -> 1348
    //   605: goto -> 612
    //   608: invokestatic a : (Ljava/lang/Throwable;)Ljava/lang/Throwable;
    //   611: athrow
    //   612: aload_3
    //   613: getstatic burp/Ztbf.Zf : Ljava/lang/String;
    //   616: getstatic burp/Ztbf.Zv : Ljava/lang/Object;
    //   619: checkcast java/math/BigInteger
    //   622: invokevirtual intValue : ()I
    //   625: bipush #32
    //   627: irem
    //   628: invokestatic abs : (I)I
    //   631: invokevirtual charAt : (I)C
    //   634: invokevirtual append : (C)Ljava/lang/StringBuilder;
    //   637: pop
    //   638: iload_2
    //   639: ifne -> 1348
    //   642: goto -> 649
    //   645: invokestatic a : (Ljava/lang/Throwable;)Ljava/lang/Throwable;
    //   648: athrow
    //   649: aload_3
    //   650: getstatic burp/Zsde.Zi : Ljava/lang/String;
    //   653: getstatic burp/Zgmt.ZX : Ljava/lang/Object;
    //   656: checkcast java/math/BigInteger
    //   659: invokevirtual intValue : ()I
    //   662: bipush #32
    //   664: irem
    //   665: invokestatic abs : (I)I
    //   668: invokevirtual charAt : (I)C
    //   671: invokevirtual append : (C)Ljava/lang/StringBuilder;
    //   674: pop
    //   675: iload_2
    //   676: ifne -> 1348
    //   679: goto -> 686
    //   682: invokestatic a : (Ljava/lang/Throwable;)Ljava/lang/Throwable;
    //   685: athrow
    //   686: aload_3
    //   687: getstatic burp/Zg99.ZH : Ljava/lang/String;
    //   690: getstatic burp/Zx54.Zn : Ljava/lang/Object;
    //   693: checkcast java/math/BigInteger
    //   696: invokevirtual intValue : ()I
    //   699: bipush #32
    //   701: irem
    //   702: invokestatic abs : (I)I
    //   705: invokevirtual charAt : (I)C
    //   708: invokevirtual append : (C)Ljava/lang/StringBuilder;
    //   711: pop
    //   712: iload_2
    //   713: ifne -> 1348
    //   716: goto -> 723
    //   719: invokestatic a : (Ljava/lang/Throwable;)Ljava/lang/Throwable;
    //   722: athrow
    //   723: aload_3
    //   724: getstatic burp/Zein.ZN : Ljava/lang/String;
    //   727: getstatic burp/Zbsr.ZD : Ljava/lang/Object;
    //   730: checkcast java/math/BigInteger
    //   733: invokevirtual intValue : ()I
    //   736: bipush #32
    //   738: irem
    //   739: invokestatic abs : (I)I
    //   742: invokevirtual charAt : (I)C
    //   745: invokevirtual append : (C)Ljava/lang/StringBuilder;
    //   748: pop
    //   749: iload_2
    //   750: ifne -> 1348
    //   753: goto -> 760
    //   756: invokestatic a : (Ljava/lang/Throwable;)Ljava/lang/Throwable;
    //   759: athrow
    //   760: aload_3
    //   761: getstatic burp/Zb3z.Zi : Ljava/lang/String;
    //   764: getstatic burp/Zkmx.Zu : Ljava/lang/Object;
    //   767: checkcast java/math/BigInteger
    //   770: invokevirtual intValue : ()I
    //   773: bipush #32
    //   775: irem
    //   776: invokestatic abs : (I)I
    //   779: invokevirtual charAt : (I)C
    //   782: invokevirtual append : (C)Ljava/lang/StringBuilder;
    //   785: pop
    //   786: iload_2
    //   787: ifne -> 1348
    //   790: goto -> 797
    //   793: invokestatic a : (Ljava/lang/Throwable;)Ljava/lang/Throwable;
    //   796: athrow
    //   797: aload_3
    //   798: getstatic burp/Zgmt.Zu : Ljava/lang/String;
    //   801: getstatic burp/Zkig.ZK : Ljava/lang/Object;
    //   804: checkcast java/math/BigInteger
    //   807: invokevirtual intValue : ()I
    //   810: bipush #32
    //   812: irem
    //   813: invokestatic abs : (I)I
    //   816: invokevirtual charAt : (I)C
    //   819: invokevirtual append : (C)Ljava/lang/StringBuilder;
    //   822: pop
    //   823: iload_2
    //   824: ifne -> 1348
    //   827: goto -> 834
    //   830: invokestatic a : (Ljava/lang/Throwable;)Ljava/lang/Throwable;
    //   833: athrow
    //   834: aload_3
    //   835: getstatic burp/Zl88.Zd : Ljava/lang/String;
    //   838: getstatic burp/Zxwl.Ze : Ljava/lang/Object;
    //   841: checkcast java/math/BigInteger
    //   844: invokevirtual intValue : ()I
    //   847: bipush #32
    //   849: irem
    //   850: invokestatic abs : (I)I
    //   853: invokevirtual charAt : (I)C
    //   856: invokevirtual append : (C)Ljava/lang/StringBuilder;
    //   859: pop
    //   860: iload_2
    //   861: ifne -> 1348
    //   864: goto -> 871
    //   867: invokestatic a : (Ljava/lang/Throwable;)Ljava/lang/Throwable;
    //   870: athrow
    //   871: aload_3
    //   872: getstatic burp/Zb2s.Zq : Ljava/lang/String;
    //   875: getstatic burp/Zsxj.Zi : Ljava/lang/Object;
    //   878: checkcast java/math/BigInteger
    //   881: invokevirtual intValue : ()I
    //   884: bipush #32
    //   886: irem
    //   887: invokestatic abs : (I)I
    //   890: invokevirtual charAt : (I)C
    //   893: invokevirtual append : (C)Ljava/lang/StringBuilder;
    //   896: pop
    //   897: iload_2
    //   898: ifne -> 1348
    //   901: goto -> 908
    //   904: invokestatic a : (Ljava/lang/Throwable;)Ljava/lang/Throwable;
    //   907: athrow
    //   908: aload_3
    //   909: getstatic burp/Zbp.Z_ : Ljava/lang/String;
    //   912: getstatic burp/Zt4g.Zv : Ljava/lang/Object;
    //   915: checkcast java/math/BigInteger
    //   918: invokevirtual intValue : ()I
    //   921: bipush #32
    //   923: irem
    //   924: invokestatic abs : (I)I
    //   927: invokevirtual charAt : (I)C
    //   930: invokevirtual append : (C)Ljava/lang/StringBuilder;
    //   933: pop
    //   934: iload_2
    //   935: ifne -> 1348
    //   938: goto -> 945
    //   941: invokestatic a : (Ljava/lang/Throwable;)Ljava/lang/Throwable;
    //   944: athrow
    //   945: aload_3
    //   946: getstatic burp/Zg99.ZH : Ljava/lang/String;
    //   949: getstatic burp/Zd1.ZV : Ljava/lang/Object;
    //   952: checkcast java/math/BigInteger
    //   955: invokevirtual intValue : ()I
    //   958: bipush #32
    //   960: irem
    //   961: invokestatic abs : (I)I
    //   964: invokevirtual charAt : (I)C
    //   967: invokevirtual append : (C)Ljava/lang/StringBuilder;
    //   970: pop
    //   971: iload_2
    //   972: ifne -> 1348
    //   975: goto -> 982
    //   978: invokestatic a : (Ljava/lang/Throwable;)Ljava/lang/Throwable;
    //   981: athrow
    //   982: aload_3
    //   983: getstatic burp/Zsm3.Zl : Ljava/lang/String;
    //   986: getstatic burp/Zxyp.ZZ : Ljava/lang/Object;
    //   989: checkcast java/math/BigInteger
    //   992: invokevirtual intValue : ()I
    //   995: bipush #32
    //   997: irem
    //   998: invokestatic abs : (I)I
    //   1001: invokevirtual charAt : (I)C
    //   1004: invokevirtual append : (C)Ljava/lang/StringBuilder;
    //   1007: pop
    //   1008: iload_2
    //   1009: ifne -> 1348
    //   1012: goto -> 1019
    //   1015: invokestatic a : (Ljava/lang/Throwable;)Ljava/lang/Throwable;
    //   1018: athrow
    //   1019: aload_3
    //   1020: getstatic burp/Zlhm.Zx : Ljava/lang/String;
    //   1023: getstatic burp/Zm0s.Zl : Ljava/lang/Object;
    //   1026: checkcast java/math/BigInteger
    //   1029: invokevirtual intValue : ()I
    //   1032: bipush #32
    //   1034: irem
    //   1035: invokestatic abs : (I)I
    //   1038: invokevirtual charAt : (I)C
    //   1041: invokevirtual append : (C)Ljava/lang/StringBuilder;
    //   1044: pop
    //   1045: iload_2
    //   1046: ifne -> 1348
    //   1049: goto -> 1056
    //   1052: invokestatic a : (Ljava/lang/Throwable;)Ljava/lang/Throwable;
    //   1055: athrow
    //   1056: aload_3
    //   1057: getstatic burp/Zxl5.Zq : Ljava/lang/String;
    //   1060: getstatic burp/Zxso.ZF : Ljava/lang/Object;
    //   1063: checkcast java/math/BigInteger
    //   1066: invokevirtual intValue : ()I
    //   1069: bipush #32
    //   1071: irem
    //   1072: invokestatic abs : (I)I
    //   1075: invokevirtual charAt : (I)C
    //   1078: invokevirtual append : (C)Ljava/lang/StringBuilder;
    //   1081: pop
    //   1082: iload_2
    //   1083: ifne -> 1348
    //   1086: goto -> 1093
    //   1089: invokestatic a : (Ljava/lang/Throwable;)Ljava/lang/Throwable;
    //   1092: athrow
    //   1093: aload_3
    //   1094: getstatic burp/Zgmt.Zu : Ljava/lang/String;
    //   1097: getstatic burp/Zg99.ZZ : Ljava/lang/Object;
    //   1100: checkcast java/math/BigInteger
    //   1103: invokevirtual intValue : ()I
    //   1106: bipush #32
    //   1108: irem
    //   1109: invokestatic abs : (I)I
    //   1112: invokevirtual charAt : (I)C
    //   1115: invokevirtual append : (C)Ljava/lang/StringBuilder;
    //   1118: pop
    //   1119: iload_2
    //   1120: ifne -> 1348
    //   1123: goto -> 1130
    //   1126: invokestatic a : (Ljava/lang/Throwable;)Ljava/lang/Throwable;
    //   1129: athrow
    //   1130: aload_3
    //   1131: getstatic burp/Zl2g.ZI : Ljava/lang/String;
    //   1134: getstatic burp/Zbsr.ZD : Ljava/lang/Object;
    //   1137: checkcast java/math/BigInteger
    //   1140: invokevirtual intValue : ()I
    //   1143: bipush #32
    //   1145: irem
    //   1146: invokestatic abs : (I)I
    //   1149: invokevirtual charAt : (I)C
    //   1152: invokevirtual append : (C)Ljava/lang/StringBuilder;
    //   1155: pop
    //   1156: iload_2
    //   1157: ifne -> 1348
    //   1160: goto -> 1167
    //   1163: invokestatic a : (Ljava/lang/Throwable;)Ljava/lang/Throwable;
    //   1166: athrow
    //   1167: aload_3
    //   1168: getstatic burp/Zg_p.ZO : Ljava/lang/String;
    //   1171: getstatic burp/Zm0s.Zl : Ljava/lang/Object;
    //   1174: checkcast java/math/BigInteger
    //   1177: invokevirtual intValue : ()I
    //   1180: bipush #32
    //   1182: irem
    //   1183: invokestatic abs : (I)I
    //   1186: invokevirtual charAt : (I)C
    //   1189: invokevirtual append : (C)Ljava/lang/StringBuilder;
    //   1192: pop
    //   1193: iload_2
    //   1194: ifne -> 1348
    //   1197: goto -> 1204
    //   1200: invokestatic a : (Ljava/lang/Throwable;)Ljava/lang/Throwable;
    //   1203: athrow
    //   1204: aload_3
    //   1205: getstatic burp/Zxk9.Zx : Ljava/lang/String;
    //   1208: getstatic burp/Zd1.ZV : Ljava/lang/Object;
    //   1211: checkcast java/math/BigInteger
    //   1214: invokevirtual intValue : ()I
    //   1217: bipush #32
    //   1219: irem
    //   1220: invokestatic abs : (I)I
    //   1223: invokevirtual charAt : (I)C
    //   1226: invokevirtual append : (C)Ljava/lang/StringBuilder;
    //   1229: pop
    //   1230: iload_2
    //   1231: ifne -> 1348
    //   1234: goto -> 1241
    //   1237: invokestatic a : (Ljava/lang/Throwable;)Ljava/lang/Throwable;
    //   1240: athrow
    //   1241: aload_3
    //   1242: getstatic burp/Zsby.Zx : Ljava/lang/String;
    //   1245: getstatic burp/Zr0g.Zj : Ljava/lang/Object;
    //   1248: checkcast java/math/BigInteger
    //   1251: invokevirtual intValue : ()I
    //   1254: bipush #32
    //   1256: irem
    //   1257: invokestatic abs : (I)I
    //   1260: invokevirtual charAt : (I)C
    //   1263: invokevirtual append : (C)Ljava/lang/StringBuilder;
    //   1266: pop
    //   1267: iload_2
    //   1268: ifne -> 1348
    //   1271: goto -> 1278
    //   1274: invokestatic a : (Ljava/lang/Throwable;)Ljava/lang/Throwable;
    //   1277: athrow
    //   1278: aload_3
    //   1279: getstatic burp/Zes_.ZM : Ljava/lang/String;
    //   1282: getstatic burp/Zzk9.ZK : Ljava/lang/Object;
    //   1285: checkcast java/math/BigInteger
    //   1288: invokevirtual intValue : ()I
    //   1291: bipush #32
    //   1293: irem
    //   1294: invokestatic abs : (I)I
    //   1297: invokevirtual charAt : (I)C
    //   1300: invokevirtual append : (C)Ljava/lang/StringBuilder;
    //   1303: pop
    //   1304: iload_2
    //   1305: ifne -> 1348
    //   1308: goto -> 1315
    //   1311: invokestatic a : (Ljava/lang/Throwable;)Ljava/lang/Throwable;
    //   1314: athrow
    //   1315: aload_3
    //   1316: getstatic burp/Zxso.ZH : Ljava/lang/String;
    //   1319: getstatic burp/Zllw.ZW : Ljava/lang/Object;
    //   1322: checkcast java/math/BigInteger
    //   1325: invokevirtual intValue : ()I
    //   1328: bipush #32
    //   1330: irem
    //   1331: invokestatic abs : (I)I
    //   1334: invokevirtual charAt : (I)C
    //   1337: invokevirtual append : (C)Ljava/lang/StringBuilder;
    //   1340: pop
    //   1341: goto -> 1348
    //   1344: invokestatic a : (Ljava/lang/Throwable;)Ljava/lang/Throwable;
    //   1347: athrow
    //   1348: iinc #4, 1
    //   1351: iload_2
    //   1352: ifne -> 15
    //   1355: aload_3
    //   1356: invokevirtual toString : ()Ljava/lang/String;
    //   1359: putstatic burp/Zgss.Zc : Ljava/lang/String;
    //   1362: sipush #18094
    //   1365: getstatic burp/Zd1.ZV : Ljava/lang/Object;
    //   1368: checkcast java/math/BigInteger
    //   1371: getstatic burp/Zsgl.Zn : Ljava/lang/Object;
    //   1374: checkcast java/math/BigInteger
    //   1377: invokevirtual add : (Ljava/math/BigInteger;)Ljava/math/BigInteger;
    //   1380: putstatic burp/Zrnu.Zs : Ljava/lang/Object;
    //   1383: sipush #30371
    //   1386: invokestatic a : (II)Ljava/lang/String;
    //   1389: iconst_1
    //   1390: ldc burp/Zl8l
    //   1392: invokevirtual getClassLoader : ()Ljava/lang/ClassLoader;
    //   1395: invokestatic forName : (Ljava/lang/String;ZLjava/lang/ClassLoader;)Ljava/lang/Class;
    //   1398: invokevirtual getDeclaredFields : ()[Ljava/lang/reflect/Field;
    //   1401: astore #4
    //   1403: aload #4
    //   1405: arraylength
    //   1406: istore #5
    //   1408: iconst_0
    //   1409: istore #6
    //   1411: iload #6
    //   1413: iload #5
    //   1415: if_icmpge -> 1553
    //   1418: aload #4
    //   1420: iload #6
    //   1422: aaload
    //   1423: astore #7
    //   1425: aload #7
    //   1427: invokevirtual getModifiers : ()I
    //   1430: invokestatic isStatic : (I)Z
    //   1433: ifne -> 1443
    //   1436: goto -> 1546
    //   1439: invokestatic a : (Ljava/lang/Throwable;)Ljava/lang/Throwable;
    //   1442: athrow
    //   1443: aload #7
    //   1445: invokevirtual getType : ()Ljava/lang/Class;
    //   1448: astore #8
    //   1450: aload #8
    //   1452: ifnull -> 1533
    //   1455: aload #8
    //   1457: invokevirtual isPrimitive : ()Z
    //   1460: ifne -> 1533
    //   1463: goto -> 1470
    //   1466: invokestatic a : (Ljava/lang/Throwable;)Ljava/lang/Throwable;
    //   1469: athrow
    //   1470: aload #8
    //   1472: invokevirtual getPackage : ()Ljava/lang/Package;
    //   1475: ifnull -> 1533
    //   1478: goto -> 1485
    //   1481: invokestatic a : (Ljava/lang/Throwable;)Ljava/lang/Throwable;
    //   1484: athrow
    //   1485: aload #8
    //   1487: invokevirtual getPackage : ()Ljava/lang/Package;
    //   1490: invokevirtual getName : ()Ljava/lang/String;
    //   1493: ifnull -> 1533
    //   1496: goto -> 1503
    //   1499: invokestatic a : (Ljava/lang/Throwable;)Ljava/lang/Throwable;
    //   1502: athrow
    //   1503: aload #8
    //   1505: invokevirtual getPackage : ()Ljava/lang/Package;
    //   1508: invokevirtual getName : ()Ljava/lang/String;
    //   1511: sipush #18099
    //   1514: sipush #-28491
    //   1517: invokestatic a : (II)Ljava/lang/String;
    //   1520: invokevirtual startsWith : (Ljava/lang/String;)Z
    //   1523: ifne -> 1533
    //   1526: goto -> 1533
    //   1529: invokestatic a : (Ljava/lang/Throwable;)Ljava/lang/Throwable;
    //   1532: athrow
    //   1533: aload #7
    //   1535: iconst_1
    //   1536: invokevirtual setAccessible : (Z)V
    //   1539: aload #7
    //   1541: aconst_null
    //   1542: invokevirtual get : (Ljava/lang/Object;)Ljava/lang/Object;
    //   1545: pop
    //   1546: iinc #6, 1
    //   1549: iload_2
    //   1550: ifne -> 1411
    //   1553: sipush #18100
    //   1556: sipush #10006
    //   1559: invokestatic a : (II)Ljava/lang/String;
    //   1562: invokestatic forName : (Ljava/lang/String;)Ljava/lang/Class;
    //   1565: invokevirtual getDeclaredMethods : ()[Ljava/lang/reflect/Method;
    //   1568: astore #4
    //   1570: aload #4
    //   1572: arraylength
    //   1573: istore #5
    //   1575: iconst_0
    //   1576: istore #6
    //   1578: iload #6
    //   1580: iload #5
    //   1582: if_icmpge -> 1715
    //   1585: aload #4
    //   1587: iload #6
    //   1589: aaload
    //   1590: astore #7
    //   1592: aload #7
    //   1594: invokevirtual getParameterTypes : ()[Ljava/lang/Class;
    //   1597: pop
    //   1598: aload #7
    //   1600: invokevirtual getModifiers : ()I
    //   1603: invokestatic isStatic : (I)Z
    //   1606: ifeq -> 1701
    //   1609: aload #7
    //   1611: invokevirtual getParameterTypes : ()[Ljava/lang/Class;
    //   1614: arraylength
    //   1615: iconst_2
    //   1616: if_icmpne -> 1701
    //   1619: goto -> 1626
    //   1622: invokestatic a : (Ljava/lang/Throwable;)Ljava/lang/Throwable;
    //   1625: athrow
    //   1626: aload #7
    //   1628: invokevirtual getReturnType : ()Ljava/lang/Class;
    //   1631: getstatic java/lang/Void.TYPE : Ljava/lang/Class;
    //   1634: invokevirtual equals : (Ljava/lang/Object;)Z
    //   1637: ifeq -> 1701
    //   1640: goto -> 1647
    //   1643: invokestatic a : (Ljava/lang/Throwable;)Ljava/lang/Throwable;
    //   1646: athrow
    //   1647: aload #7
    //   1649: iconst_1
    //   1650: invokevirtual setAccessible : (Z)V
    //   1653: aload #7
    //   1655: aconst_null
    //   1656: iconst_2
    //   1657: anewarray java/lang/Object
    //   1660: dup
    //   1661: iconst_0
    //   1662: aload_0
    //   1663: aastore
    //   1664: dup
    //   1665: iconst_1
    //   1666: aload_1
    //   1667: ifnonnull -> 1685
    //   1670: goto -> 1677
    //   1673: invokestatic a : (Ljava/lang/Throwable;)Ljava/lang/Throwable;
    //   1676: athrow
    //   1677: aload_1
    //   1678: goto -> 1692
    //   1681: invokestatic a : (Ljava/lang/Throwable;)Ljava/lang/Throwable;
    //   1684: athrow
    //   1685: aload_1
    //   1686: checkcast [B
    //   1689: invokevirtual clone : ()Ljava/lang/Object;
    //   1692: aastore
    //   1693: invokevirtual invoke : (Ljava/lang/Object;[Ljava/lang/Object;)Ljava/lang/Object;
    //   1696: pop
    //   1697: iload_2
    //   1698: ifne -> 1715
    //   1701: iinc #6, 1
    //   1704: iload_2
    //   1705: ifne -> 1578
    //   1708: goto -> 1715
    //   1711: invokestatic a : (Ljava/lang/Throwable;)Ljava/lang/Throwable;
    //   1714: athrow
    //   1715: iconst_0
    //   1716: istore #4
    //   1718: getstatic burp/Zr0u.Z_ : Ljava/lang/String;
    //   1721: getstatic burp/Zl2q.Zg : Ljava/lang/Object;
    //   1724: checkcast java/math/BigInteger
    //   1727: invokevirtual intValue : ()I
    //   1730: bipush #32
    //   1732: irem
    //   1733: invokestatic abs : (I)I
    //   1736: invokevirtual charAt : (I)C
    //   1739: getstatic burp/Zg_p.ZO : Ljava/lang/String;
    //   1742: getstatic burp/Zzsq.Zh : Ljava/lang/Object;
    //   1745: checkcast java/math/BigInteger
    //   1748: invokevirtual intValue : ()I
    //   1751: bipush #32
    //   1753: irem
    //   1754: invokestatic abs : (I)I
    //   1757: invokevirtual charAt : (I)C
    //   1760: if_icmple -> 2105
    //   1763: sipush #18091
    //   1766: sipush #-9854
    //   1769: invokestatic a : (II)Ljava/lang/String;
    //   1772: iconst_1
    //   1773: ldc burp/Zlg1
    //   1775: invokevirtual getClassLoader : ()Ljava/lang/ClassLoader;
    //   1778: invokestatic forName : (Ljava/lang/String;ZLjava/lang/ClassLoader;)Ljava/lang/Class;
    //   1781: invokevirtual getDeclaredFields : ()[Ljava/lang/reflect/Field;
    //   1784: astore #5
    //   1786: aload #5
    //   1788: arraylength
    //   1789: istore #6
    //   1791: iconst_0
    //   1792: istore #7
    //   1794: iload #7
    //   1796: iload #6
    //   1798: if_icmpge -> 1936
    //   1801: aload #5
    //   1803: iload #7
    //   1805: aaload
    //   1806: astore #8
    //   1808: aload #8
    //   1810: invokevirtual getModifiers : ()I
    //   1813: invokestatic isStatic : (I)Z
    //   1816: ifne -> 1826
    //   1819: goto -> 1929
    //   1822: invokestatic a : (Ljava/lang/Throwable;)Ljava/lang/Throwable;
    //   1825: athrow
    //   1826: aload #8
    //   1828: invokevirtual getType : ()Ljava/lang/Class;
    //   1831: astore #9
    //   1833: aload #9
    //   1835: ifnull -> 1916
    //   1838: aload #9
    //   1840: invokevirtual isPrimitive : ()Z
    //   1843: ifne -> 1916
    //   1846: goto -> 1853
    //   1849: invokestatic a : (Ljava/lang/Throwable;)Ljava/lang/Throwable;
    //   1852: athrow
    //   1853: aload #9
    //   1855: invokevirtual getPackage : ()Ljava/lang/Package;
    //   1858: ifnull -> 1916
    //   1861: goto -> 1868
    //   1864: invokestatic a : (Ljava/lang/Throwable;)Ljava/lang/Throwable;
    //   1867: athrow
    //   1868: aload #9
    //   1870: invokevirtual getPackage : ()Ljava/lang/Package;
    //   1873: invokevirtual getName : ()Ljava/lang/String;
    //   1876: ifnull -> 1916
    //   1879: goto -> 1886
    //   1882: invokestatic a : (Ljava/lang/Throwable;)Ljava/lang/Throwable;
    //   1885: athrow
    //   1886: aload #9
    //   1888: invokevirtual getPackage : ()Ljava/lang/Package;
    //   1891: invokevirtual getName : ()Ljava/lang/String;
    //   1894: sipush #18087
    //   1897: sipush #24268
    //   1900: invokestatic a : (II)Ljava/lang/String;
    //   1903: invokevirtual startsWith : (Ljava/lang/String;)Z
    //   1906: ifne -> 1916
    //   1909: goto -> 1916
    //   1912: invokestatic a : (Ljava/lang/Throwable;)Ljava/lang/Throwable;
    //   1915: athrow
    //   1916: aload #8
    //   1918: iconst_1
    //   1919: invokevirtual setAccessible : (Z)V
    //   1922: aload #8
    //   1924: aconst_null
    //   1925: invokevirtual get : (Ljava/lang/Object;)Ljava/lang/Object;
    //   1928: pop
    //   1929: iinc #7, 1
    //   1932: iload_2
    //   1933: ifne -> 1794
    //   1936: sipush #18102
    //   1939: sipush #-19271
    //   1942: invokestatic a : (II)Ljava/lang/String;
    //   1945: invokestatic forName : (Ljava/lang/String;)Ljava/lang/Class;
    //   1948: invokevirtual getDeclaredMethods : ()[Ljava/lang/reflect/Method;
    //   1951: astore #5
    //   1953: aload #5
    //   1955: arraylength
    //   1956: istore #6
    //   1958: iconst_0
    //   1959: istore #7
    //   1961: iload #7
    //   1963: iload #6
    //   1965: if_icmpge -> 2102
    //   1968: aload #5
    //   1970: iload #7
    //   1972: aaload
    //   1973: astore #8
    //   1975: aload #8
    //   1977: invokevirtual getParameterTypes : ()[Ljava/lang/Class;
    //   1980: pop
    //   1981: aload #8
    //   1983: invokevirtual getModifiers : ()I
    //   1986: invokestatic isStatic : (I)Z
    //   1989: ifeq -> 2088
    //   1992: aload #8
    //   1994: invokevirtual getParameterTypes : ()[Ljava/lang/Class;
    //   1997: arraylength
    //   1998: iconst_2
    //   1999: if_icmpne -> 2088
    //   2002: goto -> 2009
    //   2005: invokestatic a : (Ljava/lang/Throwable;)Ljava/lang/Throwable;
    //   2008: athrow
    //   2009: aload #8
    //   2011: invokevirtual getReturnType : ()Ljava/lang/Class;
    //   2014: getstatic java/lang/Boolean.TYPE : Ljava/lang/Class;
    //   2017: if_acmpne -> 2088
    //   2020: goto -> 2027
    //   2023: invokestatic a : (Ljava/lang/Throwable;)Ljava/lang/Throwable;
    //   2026: athrow
    //   2027: aload #8
    //   2029: iconst_1
    //   2030: invokevirtual setAccessible : (Z)V
    //   2033: aload #8
    //   2035: aconst_null
    //   2036: iconst_2
    //   2037: anewarray java/lang/Object
    //   2040: dup
    //   2041: iconst_0
    //   2042: aload_0
    //   2043: aastore
    //   2044: dup
    //   2045: iconst_1
    //   2046: aload_1
    //   2047: ifnonnull -> 2065
    //   2050: goto -> 2057
    //   2053: invokestatic a : (Ljava/lang/Throwable;)Ljava/lang/Throwable;
    //   2056: athrow
    //   2057: aload_1
    //   2058: goto -> 2072
    //   2061: invokestatic a : (Ljava/lang/Throwable;)Ljava/lang/Throwable;
    //   2064: athrow
    //   2065: aload_1
    //   2066: checkcast [B
    //   2069: invokevirtual clone : ()Ljava/lang/Object;
    //   2072: aastore
    //   2073: invokevirtual invoke : (Ljava/lang/Object;[Ljava/lang/Object;)Ljava/lang/Object;
    //   2076: checkcast java/lang/Boolean
    //   2079: invokevirtual booleanValue : ()Z
    //   2082: istore #4
    //   2084: iload_2
    //   2085: ifne -> 2102
    //   2088: iinc #7, 1
    //   2091: iload_2
    //   2092: ifne -> 1961
    //   2095: goto -> 2102
    //   2098: invokestatic a : (Ljava/lang/Throwable;)Ljava/lang/Throwable;
    //   2101: athrow
    //   2102: goto -> 2444
    //   2105: sipush #18096
    //   2108: sipush #5983
    //   2111: invokestatic a : (II)Ljava/lang/String;
    //   2114: iconst_1
    //   2115: ldc burp/Zsqi
    //   2117: invokevirtual getClassLoader : ()Ljava/lang/ClassLoader;
    //   2120: invokestatic forName : (Ljava/lang/String;ZLjava/lang/ClassLoader;)Ljava/lang/Class;
    //   2123: invokevirtual getDeclaredFields : ()[Ljava/lang/reflect/Field;
    //   2126: astore #5
    //   2128: aload #5
    //   2130: arraylength
    //   2131: istore #6
    //   2133: iconst_0
    //   2134: istore #7
    //   2136: iload #7
    //   2138: iload #6
    //   2140: if_icmpge -> 2278
    //   2143: aload #5
    //   2145: iload #7
    //   2147: aaload
    //   2148: astore #8
    //   2150: aload #8
    //   2152: invokevirtual getModifiers : ()I
    //   2155: invokestatic isStatic : (I)Z
    //   2158: ifne -> 2168
    //   2161: goto -> 2271
    //   2164: invokestatic a : (Ljava/lang/Throwable;)Ljava/lang/Throwable;
    //   2167: athrow
    //   2168: aload #8
    //   2170: invokevirtual getType : ()Ljava/lang/Class;
    //   2173: astore #9
    //   2175: aload #9
    //   2177: ifnull -> 2258
    //   2180: aload #9
    //   2182: invokevirtual isPrimitive : ()Z
    //   2185: ifne -> 2258
    //   2188: goto -> 2195
    //   2191: invokestatic a : (Ljava/lang/Throwable;)Ljava/lang/Throwable;
    //   2194: athrow
    //   2195: aload #9
    //   2197: invokevirtual getPackage : ()Ljava/lang/Package;
    //   2200: ifnull -> 2258
    //   2203: goto -> 2210
    //   2206: invokestatic a : (Ljava/lang/Throwable;)Ljava/lang/Throwable;
    //   2209: athrow
    //   2210: aload #9
    //   2212: invokevirtual getPackage : ()Ljava/lang/Package;
    //   2215: invokevirtual getName : ()Ljava/lang/String;
    //   2218: ifnull -> 2258
    //   2221: goto -> 2228
    //   2224: invokestatic a : (Ljava/lang/Throwable;)Ljava/lang/Throwable;
    //   2227: athrow
    //   2228: aload #9
    //   2230: invokevirtual getPackage : ()Ljava/lang/Package;
    //   2233: invokevirtual getName : ()Ljava/lang/String;
    //   2236: sipush #18087
    //   2239: sipush #24268
    //   2242: invokestatic a : (II)Ljava/lang/String;
    //   2245: invokevirtual startsWith : (Ljava/lang/String;)Z
    //   2248: ifne -> 2258
    //   2251: goto -> 2258
    //   2254: invokestatic a : (Ljava/lang/Throwable;)Ljava/lang/Throwable;
    //   2257: athrow
    //   2258: aload #8
    //   2260: iconst_1
    //   2261: invokevirtual setAccessible : (Z)V
    //   2264: aload #8
    //   2266: aconst_null
    //   2267: invokevirtual get : (Ljava/lang/Object;)Ljava/lang/Object;
    //   2270: pop
    //   2271: iinc #7, 1
    //   2274: iload_2
    //   2275: ifne -> 2136
    //   2278: sipush #18101
    //   2281: sipush #-29124
    //   2284: invokestatic a : (II)Ljava/lang/String;
    //   2287: invokestatic forName : (Ljava/lang/String;)Ljava/lang/Class;
    //   2290: invokevirtual getDeclaredMethods : ()[Ljava/lang/reflect/Method;
    //   2293: astore #5
    //   2295: aload #5
    //   2297: arraylength
    //   2298: istore #6
    //   2300: iconst_0
    //   2301: istore #7
    //   2303: iload #7
    //   2305: iload #6
    //   2307: if_icmpge -> 2444
    //   2310: aload #5
    //   2312: iload #7
    //   2314: aaload
    //   2315: astore #8
    //   2317: aload #8
    //   2319: invokevirtual getParameterTypes : ()[Ljava/lang/Class;
    //   2322: pop
    //   2323: aload #8
    //   2325: invokevirtual getModifiers : ()I
    //   2328: invokestatic isStatic : (I)Z
    //   2331: ifeq -> 2430
    //   2334: aload #8
    //   2336: invokevirtual getParameterTypes : ()[Ljava/lang/Class;
    //   2339: arraylength
    //   2340: iconst_2
    //   2341: if_icmpne -> 2430
    //   2344: goto -> 2351
    //   2347: invokestatic a : (Ljava/lang/Throwable;)Ljava/lang/Throwable;
    //   2350: athrow
    //   2351: aload #8
    //   2353: invokevirtual getReturnType : ()Ljava/lang/Class;
    //   2356: getstatic java/lang/Boolean.TYPE : Ljava/lang/Class;
    //   2359: if_acmpne -> 2430
    //   2362: goto -> 2369
    //   2365: invokestatic a : (Ljava/lang/Throwable;)Ljava/lang/Throwable;
    //   2368: athrow
    //   2369: aload #8
    //   2371: iconst_1
    //   2372: invokevirtual setAccessible : (Z)V
    //   2375: aload #8
    //   2377: aconst_null
    //   2378: iconst_2
    //   2379: anewarray java/lang/Object
    //   2382: dup
    //   2383: iconst_0
    //   2384: aload_0
    //   2385: aastore
    //   2386: dup
    //   2387: iconst_1
    //   2388: aload_1
    //   2389: ifnonnull -> 2407
    //   2392: goto -> 2399
    //   2395: invokestatic a : (Ljava/lang/Throwable;)Ljava/lang/Throwable;
    //   2398: athrow
    //   2399: aload_1
    //   2400: goto -> 2414
    //   2403: invokestatic a : (Ljava/lang/Throwable;)Ljava/lang/Throwable;
    //   2406: athrow
    //   2407: aload_1
    //   2408: checkcast [B
    //   2411: invokevirtual clone : ()Ljava/lang/Object;
    //   2414: aastore
    //   2415: invokevirtual invoke : (Ljava/lang/Object;[Ljava/lang/Object;)Ljava/lang/Object;
    //   2418: checkcast java/lang/Boolean
    //   2421: invokevirtual booleanValue : ()Z
    //   2424: istore #4
    //   2426: iload_2
    //   2427: ifne -> 2444
    //   2430: iinc #7, 1
    //   2433: iload_2
    //   2434: ifne -> 2303
    //   2437: goto -> 2444
    //   2440: invokestatic a : (Ljava/lang/Throwable;)Ljava/lang/Throwable;
    //   2443: athrow
    //   2444: iload #4
    //   2446: ifeq -> 2452
    //   2449: iload #4
    //   2451: ireturn
    //   2452: getstatic burp/Ze3j.ZI : Ljava/lang/String;
    //   2455: getstatic burp/Zbp.ZD : Ljava/lang/Object;
    //   2458: checkcast java/math/BigInteger
    //   2461: invokevirtual intValue : ()I
    //   2464: bipush #32
    //   2466: irem
    //   2467: invokestatic abs : (I)I
    //   2470: invokevirtual charAt : (I)C
    //   2473: getstatic burp/Zg99.ZH : Ljava/lang/String;
    //   2476: getstatic burp/Zkfz.Zr : Ljava/lang/Object;
    //   2479: checkcast java/math/BigInteger
    //   2482: invokevirtual intValue : ()I
    //   2485: bipush #32
    //   2487: irem
    //   2488: invokestatic abs : (I)I
    //   2491: invokevirtual charAt : (I)C
    //   2494: if_icmple -> 2840
    //   2497: sipush #18080
    //   2500: sipush #22310
    //   2503: invokestatic a : (II)Ljava/lang/String;
    //   2506: iconst_1
    //   2507: ldc burp/Zkup
    //   2509: invokevirtual getClassLoader : ()Ljava/lang/ClassLoader;
    //   2512: invokestatic forName : (Ljava/lang/String;ZLjava/lang/ClassLoader;)Ljava/lang/Class;
    //   2515: invokevirtual getDeclaredFields : ()[Ljava/lang/reflect/Field;
    //   2518: astore #5
    //   2520: aload #5
    //   2522: arraylength
    //   2523: istore #6
    //   2525: iconst_0
    //   2526: istore #7
    //   2528: iload #7
    //   2530: iload #6
    //   2532: if_icmpge -> 2670
    //   2535: aload #5
    //   2537: iload #7
    //   2539: aaload
    //   2540: astore #8
    //   2542: aload #8
    //   2544: invokevirtual getModifiers : ()I
    //   2547: invokestatic isStatic : (I)Z
    //   2550: ifne -> 2560
    //   2553: goto -> 2663
    //   2556: invokestatic a : (Ljava/lang/Throwable;)Ljava/lang/Throwable;
    //   2559: athrow
    //   2560: aload #8
    //   2562: invokevirtual getType : ()Ljava/lang/Class;
    //   2565: astore #9
    //   2567: aload #9
    //   2569: ifnull -> 2650
    //   2572: aload #9
    //   2574: invokevirtual isPrimitive : ()Z
    //   2577: ifne -> 2650
    //   2580: goto -> 2587
    //   2583: invokestatic a : (Ljava/lang/Throwable;)Ljava/lang/Throwable;
    //   2586: athrow
    //   2587: aload #9
    //   2589: invokevirtual getPackage : ()Ljava/lang/Package;
    //   2592: ifnull -> 2650
    //   2595: goto -> 2602
    //   2598: invokestatic a : (Ljava/lang/Throwable;)Ljava/lang/Throwable;
    //   2601: athrow
    //   2602: aload #9
    //   2604: invokevirtual getPackage : ()Ljava/lang/Package;
    //   2607: invokevirtual getName : ()Ljava/lang/String;
    //   2610: ifnull -> 2650
    //   2613: goto -> 2620
    //   2616: invokestatic a : (Ljava/lang/Throwable;)Ljava/lang/Throwable;
    //   2619: athrow
    //   2620: aload #9
    //   2622: invokevirtual getPackage : ()Ljava/lang/Package;
    //   2625: invokevirtual getName : ()Ljava/lang/String;
    //   2628: sipush #18087
    //   2631: sipush #24268
    //   2634: invokestatic a : (II)Ljava/lang/String;
    //   2637: invokevirtual startsWith : (Ljava/lang/String;)Z
    //   2640: ifne -> 2650
    //   2643: goto -> 2650
    //   2646: invokestatic a : (Ljava/lang/Throwable;)Ljava/lang/Throwable;
    //   2649: athrow
    //   2650: aload #8
    //   2652: iconst_1
    //   2653: invokevirtual setAccessible : (Z)V
    //   2656: aload #8
    //   2658: aconst_null
    //   2659: invokevirtual get : (Ljava/lang/Object;)Ljava/lang/Object;
    //   2662: pop
    //   2663: iinc #7, 1
    //   2666: iload_2
    //   2667: ifne -> 2528
    //   2670: sipush #18083
    //   2673: sipush #-24763
    //   2676: invokestatic a : (II)Ljava/lang/String;
    //   2679: invokestatic forName : (Ljava/lang/String;)Ljava/lang/Class;
    //   2682: invokevirtual getDeclaredMethods : ()[Ljava/lang/reflect/Method;
    //   2685: astore #5
    //   2687: aload #5
    //   2689: arraylength
    //   2690: istore #6
    //   2692: iconst_0
    //   2693: istore #7
    //   2695: iload #7
    //   2697: iload #6
    //   2699: if_icmpge -> 2836
    //   2702: aload #5
    //   2704: iload #7
    //   2706: aaload
    //   2707: astore #8
    //   2709: aload #8
    //   2711: invokevirtual getParameterTypes : ()[Ljava/lang/Class;
    //   2714: pop
    //   2715: aload #8
    //   2717: invokevirtual getModifiers : ()I
    //   2720: invokestatic isStatic : (I)Z
    //   2723: ifeq -> 2822
    //   2726: aload #8
    //   2728: invokevirtual getParameterTypes : ()[Ljava/lang/Class;
    //   2731: arraylength
    //   2732: iconst_2
    //   2733: if_icmpne -> 2822
    //   2736: goto -> 2743
    //   2739: invokestatic a : (Ljava/lang/Throwable;)Ljava/lang/Throwable;
    //   2742: athrow
    //   2743: aload #8
    //   2745: invokevirtual getReturnType : ()Ljava/lang/Class;
    //   2748: getstatic java/lang/Boolean.TYPE : Ljava/lang/Class;
    //   2751: if_acmpne -> 2822
    //   2754: goto -> 2761
    //   2757: invokestatic a : (Ljava/lang/Throwable;)Ljava/lang/Throwable;
    //   2760: athrow
    //   2761: aload #8
    //   2763: iconst_1
    //   2764: invokevirtual setAccessible : (Z)V
    //   2767: aload #8
    //   2769: aconst_null
    //   2770: iconst_2
    //   2771: anewarray java/lang/Object
    //   2774: dup
    //   2775: iconst_0
    //   2776: aload_0
    //   2777: aastore
    //   2778: dup
    //   2779: iconst_1
    //   2780: aload_1
    //   2781: ifnonnull -> 2799
    //   2784: goto -> 2791
    //   2787: invokestatic a : (Ljava/lang/Throwable;)Ljava/lang/Throwable;
    //   2790: athrow
    //   2791: aload_1
    //   2792: goto -> 2806
    //   2795: invokestatic a : (Ljava/lang/Throwable;)Ljava/lang/Throwable;
    //   2798: athrow
    //   2799: aload_1
    //   2800: checkcast [B
    //   2803: invokevirtual clone : ()Ljava/lang/Object;
    //   2806: aastore
    //   2807: invokevirtual invoke : (Ljava/lang/Object;[Ljava/lang/Object;)Ljava/lang/Object;
    //   2810: checkcast java/lang/Boolean
    //   2813: invokevirtual booleanValue : ()Z
    //   2816: istore #4
    //   2818: iload_2
    //   2819: ifne -> 2836
    //   2822: iinc #7, 1
    //   2825: iload_2
    //   2826: ifne -> 2695
    //   2829: goto -> 2836
    //   2832: invokestatic a : (Ljava/lang/Throwable;)Ljava/lang/Throwable;
    //   2835: athrow
    //   2836: iload_2
    //   2837: ifne -> 3179
    //   2840: sipush #18081
    //   2843: sipush #-18210
    //   2846: invokestatic a : (II)Ljava/lang/String;
    //   2849: iconst_1
    //   2850: ldc burp/Zrod
    //   2852: invokevirtual getClassLoader : ()Ljava/lang/ClassLoader;
    //   2855: invokestatic forName : (Ljava/lang/String;ZLjava/lang/ClassLoader;)Ljava/lang/Class;
    //   2858: invokevirtual getDeclaredFields : ()[Ljava/lang/reflect/Field;
    //   2861: astore #5
    //   2863: aload #5
    //   2865: arraylength
    //   2866: istore #6
    //   2868: iconst_0
    //   2869: istore #7
    //   2871: iload #7
    //   2873: iload #6
    //   2875: if_icmpge -> 3013
    //   2878: aload #5
    //   2880: iload #7
    //   2882: aaload
    //   2883: astore #8
    //   2885: aload #8
    //   2887: invokevirtual getModifiers : ()I
    //   2890: invokestatic isStatic : (I)Z
    //   2893: ifne -> 2903
    //   2896: goto -> 3006
    //   2899: invokestatic a : (Ljava/lang/Throwable;)Ljava/lang/Throwable;
    //   2902: athrow
    //   2903: aload #8
    //   2905: invokevirtual getType : ()Ljava/lang/Class;
    //   2908: astore #9
    //   2910: aload #9
    //   2912: ifnull -> 2993
    //   2915: aload #9
    //   2917: invokevirtual isPrimitive : ()Z
    //   2920: ifne -> 2993
    //   2923: goto -> 2930
    //   2926: invokestatic a : (Ljava/lang/Throwable;)Ljava/lang/Throwable;
    //   2929: athrow
    //   2930: aload #9
    //   2932: invokevirtual getPackage : ()Ljava/lang/Package;
    //   2935: ifnull -> 2993
    //   2938: goto -> 2945
    //   2941: invokestatic a : (Ljava/lang/Throwable;)Ljava/lang/Throwable;
    //   2944: athrow
    //   2945: aload #9
    //   2947: invokevirtual getPackage : ()Ljava/lang/Package;
    //   2950: invokevirtual getName : ()Ljava/lang/String;
    //   2953: ifnull -> 2993
    //   2956: goto -> 2963
    //   2959: invokestatic a : (Ljava/lang/Throwable;)Ljava/lang/Throwable;
    //   2962: athrow
    //   2963: aload #9
    //   2965: invokevirtual getPackage : ()Ljava/lang/Package;
    //   2968: invokevirtual getName : ()Ljava/lang/String;
    //   2971: sipush #18087
    //   2974: sipush #24268
    //   2977: invokestatic a : (II)Ljava/lang/String;
    //   2980: invokevirtual startsWith : (Ljava/lang/String;)Z
    //   2983: ifne -> 2993
    //   2986: goto -> 2993
    //   2989: invokestatic a : (Ljava/lang/Throwable;)Ljava/lang/Throwable;
    //   2992: athrow
    //   2993: aload #8
    //   2995: iconst_1
    //   2996: invokevirtual setAccessible : (Z)V
    //   2999: aload #8
    //   3001: aconst_null
    //   3002: invokevirtual get : (Ljava/lang/Object;)Ljava/lang/Object;
    //   3005: pop
    //   3006: iinc #7, 1
    //   3009: iload_2
    //   3010: ifne -> 2871
    //   3013: sipush #18103
    //   3016: sipush #12801
    //   3019: invokestatic a : (II)Ljava/lang/String;
    //   3022: invokestatic forName : (Ljava/lang/String;)Ljava/lang/Class;
    //   3025: invokevirtual getDeclaredMethods : ()[Ljava/lang/reflect/Method;
    //   3028: astore #5
    //   3030: aload #5
    //   3032: arraylength
    //   3033: istore #6
    //   3035: iconst_0
    //   3036: istore #7
    //   3038: iload #7
    //   3040: iload #6
    //   3042: if_icmpge -> 3179
    //   3045: aload #5
    //   3047: iload #7
    //   3049: aaload
    //   3050: astore #8
    //   3052: aload #8
    //   3054: invokevirtual getParameterTypes : ()[Ljava/lang/Class;
    //   3057: pop
    //   3058: aload #8
    //   3060: invokevirtual getModifiers : ()I
    //   3063: invokestatic isStatic : (I)Z
    //   3066: ifeq -> 3165
    //   3069: aload #8
    //   3071: invokevirtual getParameterTypes : ()[Ljava/lang/Class;
    //   3074: arraylength
    //   3075: iconst_2
    //   3076: if_icmpne -> 3165
    //   3079: goto -> 3086
    //   3082: invokestatic a : (Ljava/lang/Throwable;)Ljava/lang/Throwable;
    //   3085: athrow
    //   3086: aload #8
    //   3088: invokevirtual getReturnType : ()Ljava/lang/Class;
    //   3091: getstatic java/lang/Boolean.TYPE : Ljava/lang/Class;
    //   3094: if_acmpne -> 3165
    //   3097: goto -> 3104
    //   3100: invokestatic a : (Ljava/lang/Throwable;)Ljava/lang/Throwable;
    //   3103: athrow
    //   3104: aload #8
    //   3106: iconst_1
    //   3107: invokevirtual setAccessible : (Z)V
    //   3110: aload #8
    //   3112: aconst_null
    //   3113: iconst_2
    //   3114: anewarray java/lang/Object
    //   3117: dup
    //   3118: iconst_0
    //   3119: aload_0
    //   3120: aastore
    //   3121: dup
    //   3122: iconst_1
    //   3123: aload_1
    //   3124: ifnonnull -> 3142
    //   3127: goto -> 3134
    //   3130: invokestatic a : (Ljava/lang/Throwable;)Ljava/lang/Throwable;
    //   3133: athrow
    //   3134: aload_1
    //   3135: goto -> 3149
    //   3138: invokestatic a : (Ljava/lang/Throwable;)Ljava/lang/Throwable;
    //   3141: athrow
    //   3142: aload_1
    //   3143: checkcast [B
    //   3146: invokevirtual clone : ()Ljava/lang/Object;
    //   3149: aastore
    //   3150: invokevirtual invoke : (Ljava/lang/Object;[Ljava/lang/Object;)Ljava/lang/Object;
    //   3153: checkcast java/lang/Boolean
    //   3156: invokevirtual booleanValue : ()Z
    //   3159: istore #4
    //   3161: iload_2
    //   3162: ifne -> 3179
    //   3165: iinc #7, 1
    //   3168: iload_2
    //   3169: ifne -> 3038
    //   3172: goto -> 3179
    //   3175: invokestatic a : (Ljava/lang/Throwable;)Ljava/lang/Throwable;
    //   3178: athrow
    //   3179: iload #4
    //   3181: ifeq -> 3187
    //   3184: iload #4
    //   3186: ireturn
    //   3187: getstatic burp/Zx54.Zs : Ljava/lang/String;
    //   3190: getstatic burp/Zx4w.Zp : Ljava/lang/Object;
    //   3193: checkcast java/math/BigInteger
    //   3196: invokevirtual intValue : ()I
    //   3199: bipush #32
    //   3201: irem
    //   3202: invokestatic abs : (I)I
    //   3205: invokevirtual charAt : (I)C
    //   3208: getstatic burp/Ztbf.Zf : Ljava/lang/String;
    //   3211: getstatic burp/Zk8b.ZK : Ljava/lang/Object;
    //   3214: checkcast java/math/BigInteger
    //   3217: invokevirtual intValue : ()I
    //   3220: bipush #32
    //   3222: irem
    //   3223: invokestatic abs : (I)I
    //   3226: invokevirtual charAt : (I)C
    //   3229: if_icmple -> 3575
    //   3232: sipush #18093
    //   3235: sipush #10456
    //   3238: invokestatic a : (II)Ljava/lang/String;
    //   3241: iconst_1
    //   3242: ldc burp/Zktq
    //   3244: invokevirtual getClassLoader : ()Ljava/lang/ClassLoader;
    //   3247: invokestatic forName : (Ljava/lang/String;ZLjava/lang/ClassLoader;)Ljava/lang/Class;
    //   3250: invokevirtual getDeclaredFields : ()[Ljava/lang/reflect/Field;
    //   3253: astore #5
    //   3255: aload #5
    //   3257: arraylength
    //   3258: istore #6
    //   3260: iconst_0
    //   3261: istore #7
    //   3263: iload #7
    //   3265: iload #6
    //   3267: if_icmpge -> 3405
    //   3270: aload #5
    //   3272: iload #7
    //   3274: aaload
    //   3275: astore #8
    //   3277: aload #8
    //   3279: invokevirtual getModifiers : ()I
    //   3282: invokestatic isStatic : (I)Z
    //   3285: ifne -> 3295
    //   3288: goto -> 3398
    //   3291: invokestatic a : (Ljava/lang/Throwable;)Ljava/lang/Throwable;
    //   3294: athrow
    //   3295: aload #8
    //   3297: invokevirtual getType : ()Ljava/lang/Class;
    //   3300: astore #9
    //   3302: aload #9
    //   3304: ifnull -> 3385
    //   3307: aload #9
    //   3309: invokevirtual isPrimitive : ()Z
    //   3312: ifne -> 3385
    //   3315: goto -> 3322
    //   3318: invokestatic a : (Ljava/lang/Throwable;)Ljava/lang/Throwable;
    //   3321: athrow
    //   3322: aload #9
    //   3324: invokevirtual getPackage : ()Ljava/lang/Package;
    //   3327: ifnull -> 3385
    //   3330: goto -> 3337
    //   3333: invokestatic a : (Ljava/lang/Throwable;)Ljava/lang/Throwable;
    //   3336: athrow
    //   3337: aload #9
    //   3339: invokevirtual getPackage : ()Ljava/lang/Package;
    //   3342: invokevirtual getName : ()Ljava/lang/String;
    //   3345: ifnull -> 3385
    //   3348: goto -> 3355
    //   3351: invokestatic a : (Ljava/lang/Throwable;)Ljava/lang/Throwable;
    //   3354: athrow
    //   3355: aload #9
    //   3357: invokevirtual getPackage : ()Ljava/lang/Package;
    //   3360: invokevirtual getName : ()Ljava/lang/String;
    //   3363: sipush #18087
    //   3366: sipush #24268
    //   3369: invokestatic a : (II)Ljava/lang/String;
    //   3372: invokevirtual startsWith : (Ljava/lang/String;)Z
    //   3375: ifne -> 3385
    //   3378: goto -> 3385
    //   3381: invokestatic a : (Ljava/lang/Throwable;)Ljava/lang/Throwable;
    //   3384: athrow
    //   3385: aload #8
    //   3387: iconst_1
    //   3388: invokevirtual setAccessible : (Z)V
    //   3391: aload #8
    //   3393: aconst_null
    //   3394: invokevirtual get : (Ljava/lang/Object;)Ljava/lang/Object;
    //   3397: pop
    //   3398: iinc #7, 1
    //   3401: iload_2
    //   3402: ifne -> 3263
    //   3405: sipush #18092
    //   3408: sipush #-26606
    //   3411: invokestatic a : (II)Ljava/lang/String;
    //   3414: invokestatic forName : (Ljava/lang/String;)Ljava/lang/Class;
    //   3417: invokevirtual getDeclaredMethods : ()[Ljava/lang/reflect/Method;
    //   3420: astore #5
    //   3422: aload #5
    //   3424: arraylength
    //   3425: istore #6
    //   3427: iconst_0
    //   3428: istore #7
    //   3430: iload #7
    //   3432: iload #6
    //   3434: if_icmpge -> 3571
    //   3437: aload #5
    //   3439: iload #7
    //   3441: aaload
    //   3442: astore #8
    //   3444: aload #8
    //   3446: invokevirtual getParameterTypes : ()[Ljava/lang/Class;
    //   3449: pop
    //   3450: aload #8
    //   3452: invokevirtual getModifiers : ()I
    //   3455: invokestatic isStatic : (I)Z
    //   3458: ifeq -> 3557
    //   3461: aload #8
    //   3463: invokevirtual getParameterTypes : ()[Ljava/lang/Class;
    //   3466: arraylength
    //   3467: iconst_2
    //   3468: if_icmpne -> 3557
    //   3471: goto -> 3478
    //   3474: invokestatic a : (Ljava/lang/Throwable;)Ljava/lang/Throwable;
    //   3477: athrow
    //   3478: aload #8
    //   3480: invokevirtual getReturnType : ()Ljava/lang/Class;
    //   3483: getstatic java/lang/Boolean.TYPE : Ljava/lang/Class;
    //   3486: if_acmpne -> 3557
    //   3489: goto -> 3496
    //   3492: invokestatic a : (Ljava/lang/Throwable;)Ljava/lang/Throwable;
    //   3495: athrow
    //   3496: aload #8
    //   3498: iconst_1
    //   3499: invokevirtual setAccessible : (Z)V
    //   3502: aload #8
    //   3504: aconst_null
    //   3505: iconst_2
    //   3506: anewarray java/lang/Object
    //   3509: dup
    //   3510: iconst_0
    //   3511: aload_0
    //   3512: aastore
    //   3513: dup
    //   3514: iconst_1
    //   3515: aload_1
    //   3516: ifnonnull -> 3534
    //   3519: goto -> 3526
    //   3522: invokestatic a : (Ljava/lang/Throwable;)Ljava/lang/Throwable;
    //   3525: athrow
    //   3526: aload_1
    //   3527: goto -> 3541
    //   3530: invokestatic a : (Ljava/lang/Throwable;)Ljava/lang/Throwable;
    //   3533: athrow
    //   3534: aload_1
    //   3535: checkcast [B
    //   3538: invokevirtual clone : ()Ljava/lang/Object;
    //   3541: aastore
    //   3542: invokevirtual invoke : (Ljava/lang/Object;[Ljava/lang/Object;)Ljava/lang/Object;
    //   3545: checkcast java/lang/Boolean
    //   3548: invokevirtual booleanValue : ()Z
    //   3551: istore #4
    //   3553: iload_2
    //   3554: ifne -> 3571
    //   3557: iinc #7, 1
    //   3560: iload_2
    //   3561: ifne -> 3430
    //   3564: goto -> 3571
    //   3567: invokestatic a : (Ljava/lang/Throwable;)Ljava/lang/Throwable;
    //   3570: athrow
    //   3571: iload_2
    //   3572: ifne -> 3914
    //   3575: sipush #18098
    //   3578: sipush #11631
    //   3581: invokestatic a : (II)Ljava/lang/String;
    //   3584: iconst_1
    //   3585: ldc burp/Ze5t
    //   3587: invokevirtual getClassLoader : ()Ljava/lang/ClassLoader;
    //   3590: invokestatic forName : (Ljava/lang/String;ZLjava/lang/ClassLoader;)Ljava/lang/Class;
    //   3593: invokevirtual getDeclaredFields : ()[Ljava/lang/reflect/Field;
    //   3596: astore #5
    //   3598: aload #5
    //   3600: arraylength
    //   3601: istore #6
    //   3603: iconst_0
    //   3604: istore #7
    //   3606: iload #7
    //   3608: iload #6
    //   3610: if_icmpge -> 3748
    //   3613: aload #5
    //   3615: iload #7
    //   3617: aaload
    //   3618: astore #8
    //   3620: aload #8
    //   3622: invokevirtual getModifiers : ()I
    //   3625: invokestatic isStatic : (I)Z
    //   3628: ifne -> 3638
    //   3631: goto -> 3741
    //   3634: invokestatic a : (Ljava/lang/Throwable;)Ljava/lang/Throwable;
    //   3637: athrow
    //   3638: aload #8
    //   3640: invokevirtual getType : ()Ljava/lang/Class;
    //   3643: astore #9
    //   3645: aload #9
    //   3647: ifnull -> 3728
    //   3650: aload #9
    //   3652: invokevirtual isPrimitive : ()Z
    //   3655: ifne -> 3728
    //   3658: goto -> 3665
    //   3661: invokestatic a : (Ljava/lang/Throwable;)Ljava/lang/Throwable;
    //   3664: athrow
    //   3665: aload #9
    //   3667: invokevirtual getPackage : ()Ljava/lang/Package;
    //   3670: ifnull -> 3728
    //   3673: goto -> 3680
    //   3676: invokestatic a : (Ljava/lang/Throwable;)Ljava/lang/Throwable;
    //   3679: athrow
    //   3680: aload #9
    //   3682: invokevirtual getPackage : ()Ljava/lang/Package;
    //   3685: invokevirtual getName : ()Ljava/lang/String;
    //   3688: ifnull -> 3728
    //   3691: goto -> 3698
    //   3694: invokestatic a : (Ljava/lang/Throwable;)Ljava/lang/Throwable;
    //   3697: athrow
    //   3698: aload #9
    //   3700: invokevirtual getPackage : ()Ljava/lang/Package;
    //   3703: invokevirtual getName : ()Ljava/lang/String;
    //   3706: sipush #18087
    //   3709: sipush #24268
    //   3712: invokestatic a : (II)Ljava/lang/String;
    //   3715: invokevirtual startsWith : (Ljava/lang/String;)Z
    //   3718: ifne -> 3728
    //   3721: goto -> 3728
    //   3724: invokestatic a : (Ljava/lang/Throwable;)Ljava/lang/Throwable;
    //   3727: athrow
    //   3728: aload #8
    //   3730: iconst_1
    //   3731: invokevirtual setAccessible : (Z)V
    //   3734: aload #8
    //   3736: aconst_null
    //   3737: invokevirtual get : (Ljava/lang/Object;)Ljava/lang/Object;
    //   3740: pop
    //   3741: iinc #7, 1
    //   3744: iload_2
    //   3745: ifne -> 3606
    //   3748: sipush #18090
    //   3751: sipush #8844
    //   3754: invokestatic a : (II)Ljava/lang/String;
    //   3757: invokestatic forName : (Ljava/lang/String;)Ljava/lang/Class;
    //   3760: invokevirtual getDeclaredMethods : ()[Ljava/lang/reflect/Method;
    //   3763: astore #5
    //   3765: aload #5
    //   3767: arraylength
    //   3768: istore #6
    //   3770: iconst_0
    //   3771: istore #7
    //   3773: iload #7
    //   3775: iload #6
    //   3777: if_icmpge -> 3914
    //   3780: aload #5
    //   3782: iload #7
    //   3784: aaload
    //   3785: astore #8
    //   3787: aload #8
    //   3789: invokevirtual getParameterTypes : ()[Ljava/lang/Class;
    //   3792: pop
    //   3793: aload #8
    //   3795: invokevirtual getModifiers : ()I
    //   3798: invokestatic isStatic : (I)Z
    //   3801: ifeq -> 3900
    //   3804: aload #8
    //   3806: invokevirtual getParameterTypes : ()[Ljava/lang/Class;
    //   3809: arraylength
    //   3810: iconst_2
    //   3811: if_icmpne -> 3900
    //   3814: goto -> 3821
    //   3817: invokestatic a : (Ljava/lang/Throwable;)Ljava/lang/Throwable;
    //   3820: athrow
    //   3821: aload #8
    //   3823: invokevirtual getReturnType : ()Ljava/lang/Class;
    //   3826: getstatic java/lang/Boolean.TYPE : Ljava/lang/Class;
    //   3829: if_acmpne -> 3900
    //   3832: goto -> 3839
    //   3835: invokestatic a : (Ljava/lang/Throwable;)Ljava/lang/Throwable;
    //   3838: athrow
    //   3839: aload #8
    //   3841: iconst_1
    //   3842: invokevirtual setAccessible : (Z)V
    //   3845: aload #8
    //   3847: aconst_null
    //   3848: iconst_2
    //   3849: anewarray java/lang/Object
    //   3852: dup
    //   3853: iconst_0
    //   3854: aload_0
    //   3855: aastore
    //   3856: dup
    //   3857: iconst_1
    //   3858: aload_1
    //   3859: ifnonnull -> 3877
    //   3862: goto -> 3869
    //   3865: invokestatic a : (Ljava/lang/Throwable;)Ljava/lang/Throwable;
    //   3868: athrow
    //   3869: aload_1
    //   3870: goto -> 3884
    //   3873: invokestatic a : (Ljava/lang/Throwable;)Ljava/lang/Throwable;
    //   3876: athrow
    //   3877: aload_1
    //   3878: checkcast [B
    //   3881: invokevirtual clone : ()Ljava/lang/Object;
    //   3884: aastore
    //   3885: invokevirtual invoke : (Ljava/lang/Object;[Ljava/lang/Object;)Ljava/lang/Object;
    //   3888: checkcast java/lang/Boolean
    //   3891: invokevirtual booleanValue : ()Z
    //   3894: istore #4
    //   3896: iload_2
    //   3897: ifne -> 3914
    //   3900: iinc #7, 1
    //   3903: iload_2
    //   3904: ifne -> 3773
    //   3907: goto -> 3914
    //   3910: invokestatic a : (Ljava/lang/Throwable;)Ljava/lang/Throwable;
    //   3913: athrow
    //   3914: iload #4
    //   3916: ifeq -> 3922
    //   3919: iload #4
    //   3921: ireturn
    //   3922: getstatic burp/Zg7z.Zf : Ljava/lang/String;
    //   3925: getstatic burp/Zxfu.ZA : Ljava/lang/Object;
    //   3928: checkcast java/math/BigInteger
    //   3931: invokevirtual intValue : ()I
    //   3934: bipush #32
    //   3936: irem
    //   3937: invokestatic abs : (I)I
    //   3940: invokevirtual charAt : (I)C
    //   3943: getstatic burp/Zl_k.Zw : Ljava/lang/String;
    //   3946: getstatic burp/Ztbf.Zv : Ljava/lang/Object;
    //   3949: checkcast java/math/BigInteger
    //   3952: invokevirtual intValue : ()I
    //   3955: bipush #32
    //   3957: irem
    //   3958: invokestatic abs : (I)I
    //   3961: invokevirtual charAt : (I)C
    //   3964: if_icmple -> 4310
    //   3967: sipush #18088
    //   3970: sipush #-32582
    //   3973: invokestatic a : (II)Ljava/lang/String;
    //   3976: iconst_1
    //   3977: ldc burp/Zbqk
    //   3979: invokevirtual getClassLoader : ()Ljava/lang/ClassLoader;
    //   3982: invokestatic forName : (Ljava/lang/String;ZLjava/lang/ClassLoader;)Ljava/lang/Class;
    //   3985: invokevirtual getDeclaredFields : ()[Ljava/lang/reflect/Field;
    //   3988: astore #5
    //   3990: aload #5
    //   3992: arraylength
    //   3993: istore #6
    //   3995: iconst_0
    //   3996: istore #7
    //   3998: iload #7
    //   4000: iload #6
    //   4002: if_icmpge -> 4140
    //   4005: aload #5
    //   4007: iload #7
    //   4009: aaload
    //   4010: astore #8
    //   4012: aload #8
    //   4014: invokevirtual getModifiers : ()I
    //   4017: invokestatic isStatic : (I)Z
    //   4020: ifne -> 4030
    //   4023: goto -> 4133
    //   4026: invokestatic a : (Ljava/lang/Throwable;)Ljava/lang/Throwable;
    //   4029: athrow
    //   4030: aload #8
    //   4032: invokevirtual getType : ()Ljava/lang/Class;
    //   4035: astore #9
    //   4037: aload #9
    //   4039: ifnull -> 4120
    //   4042: aload #9
    //   4044: invokevirtual isPrimitive : ()Z
    //   4047: ifne -> 4120
    //   4050: goto -> 4057
    //   4053: invokestatic a : (Ljava/lang/Throwable;)Ljava/lang/Throwable;
    //   4056: athrow
    //   4057: aload #9
    //   4059: invokevirtual getPackage : ()Ljava/lang/Package;
    //   4062: ifnull -> 4120
    //   4065: goto -> 4072
    //   4068: invokestatic a : (Ljava/lang/Throwable;)Ljava/lang/Throwable;
    //   4071: athrow
    //   4072: aload #9
    //   4074: invokevirtual getPackage : ()Ljava/lang/Package;
    //   4077: invokevirtual getName : ()Ljava/lang/String;
    //   4080: ifnull -> 4120
    //   4083: goto -> 4090
    //   4086: invokestatic a : (Ljava/lang/Throwable;)Ljava/lang/Throwable;
    //   4089: athrow
    //   4090: aload #9
    //   4092: invokevirtual getPackage : ()Ljava/lang/Package;
    //   4095: invokevirtual getName : ()Ljava/lang/String;
    //   4098: sipush #18087
    //   4101: sipush #24268
    //   4104: invokestatic a : (II)Ljava/lang/String;
    //   4107: invokevirtual startsWith : (Ljava/lang/String;)Z
    //   4110: ifne -> 4120
    //   4113: goto -> 4120
    //   4116: invokestatic a : (Ljava/lang/Throwable;)Ljava/lang/Throwable;
    //   4119: athrow
    //   4120: aload #8
    //   4122: iconst_1
    //   4123: invokevirtual setAccessible : (Z)V
    //   4126: aload #8
    //   4128: aconst_null
    //   4129: invokevirtual get : (Ljava/lang/Object;)Ljava/lang/Object;
    //   4132: pop
    //   4133: iinc #7, 1
    //   4136: iload_2
    //   4137: ifne -> 3998
    //   4140: sipush #18110
    //   4143: sipush #24867
    //   4146: invokestatic a : (II)Ljava/lang/String;
    //   4149: invokestatic forName : (Ljava/lang/String;)Ljava/lang/Class;
    //   4152: invokevirtual getDeclaredMethods : ()[Ljava/lang/reflect/Method;
    //   4155: astore #5
    //   4157: aload #5
    //   4159: arraylength
    //   4160: istore #6
    //   4162: iconst_0
    //   4163: istore #7
    //   4165: iload #7
    //   4167: iload #6
    //   4169: if_icmpge -> 4306
    //   4172: aload #5
    //   4174: iload #7
    //   4176: aaload
    //   4177: astore #8
    //   4179: aload #8
    //   4181: invokevirtual getParameterTypes : ()[Ljava/lang/Class;
    //   4184: pop
    //   4185: aload #8
    //   4187: invokevirtual getModifiers : ()I
    //   4190: invokestatic isStatic : (I)Z
    //   4193: ifeq -> 4292
    //   4196: aload #8
    //   4198: invokevirtual getParameterTypes : ()[Ljava/lang/Class;
    //   4201: arraylength
    //   4202: iconst_2
    //   4203: if_icmpne -> 4292
    //   4206: goto -> 4213
    //   4209: invokestatic a : (Ljava/lang/Throwable;)Ljava/lang/Throwable;
    //   4212: athrow
    //   4213: aload #8
    //   4215: invokevirtual getReturnType : ()Ljava/lang/Class;
    //   4218: getstatic java/lang/Boolean.TYPE : Ljava/lang/Class;
    //   4221: if_acmpne -> 4292
    //   4224: goto -> 4231
    //   4227: invokestatic a : (Ljava/lang/Throwable;)Ljava/lang/Throwable;
    //   4230: athrow
    //   4231: aload #8
    //   4233: iconst_1
    //   4234: invokevirtual setAccessible : (Z)V
    //   4237: aload #8
    //   4239: aconst_null
    //   4240: iconst_2
    //   4241: anewarray java/lang/Object
    //   4244: dup
    //   4245: iconst_0
    //   4246: aload_0
    //   4247: aastore
    //   4248: dup
    //   4249: iconst_1
    //   4250: aload_1
    //   4251: ifnonnull -> 4269
    //   4254: goto -> 4261
    //   4257: invokestatic a : (Ljava/lang/Throwable;)Ljava/lang/Throwable;
    //   4260: athrow
    //   4261: aload_1
    //   4262: goto -> 4276
    //   4265: invokestatic a : (Ljava/lang/Throwable;)Ljava/lang/Throwable;
    //   4268: athrow
    //   4269: aload_1
    //   4270: checkcast [B
    //   4273: invokevirtual clone : ()Ljava/lang/Object;
    //   4276: aastore
    //   4277: invokevirtual invoke : (Ljava/lang/Object;[Ljava/lang/Object;)Ljava/lang/Object;
    //   4280: checkcast java/lang/Boolean
    //   4283: invokevirtual booleanValue : ()Z
    //   4286: istore #4
    //   4288: iload_2
    //   4289: ifne -> 4306
    //   4292: iinc #7, 1
    //   4295: iload_2
    //   4296: ifne -> 4165
    //   4299: goto -> 4306
    //   4302: invokestatic a : (Ljava/lang/Throwable;)Ljava/lang/Throwable;
    //   4305: athrow
    //   4306: iload_2
    //   4307: ifne -> 4649
    //   4310: sipush #18089
    //   4313: sipush #-11039
    //   4316: invokestatic a : (II)Ljava/lang/String;
    //   4319: iconst_1
    //   4320: ldc burp/Ztpg
    //   4322: invokevirtual getClassLoader : ()Ljava/lang/ClassLoader;
    //   4325: invokestatic forName : (Ljava/lang/String;ZLjava/lang/ClassLoader;)Ljava/lang/Class;
    //   4328: invokevirtual getDeclaredFields : ()[Ljava/lang/reflect/Field;
    //   4331: astore #5
    //   4333: aload #5
    //   4335: arraylength
    //   4336: istore #6
    //   4338: iconst_0
    //   4339: istore #7
    //   4341: iload #7
    //   4343: iload #6
    //   4345: if_icmpge -> 4483
    //   4348: aload #5
    //   4350: iload #7
    //   4352: aaload
    //   4353: astore #8
    //   4355: aload #8
    //   4357: invokevirtual getModifiers : ()I
    //   4360: invokestatic isStatic : (I)Z
    //   4363: ifne -> 4373
    //   4366: goto -> 4476
    //   4369: invokestatic a : (Ljava/lang/Throwable;)Ljava/lang/Throwable;
    //   4372: athrow
    //   4373: aload #8
    //   4375: invokevirtual getType : ()Ljava/lang/Class;
    //   4378: astore #9
    //   4380: aload #9
    //   4382: ifnull -> 4463
    //   4385: aload #9
    //   4387: invokevirtual isPrimitive : ()Z
    //   4390: ifne -> 4463
    //   4393: goto -> 4400
    //   4396: invokestatic a : (Ljava/lang/Throwable;)Ljava/lang/Throwable;
    //   4399: athrow
    //   4400: aload #9
    //   4402: invokevirtual getPackage : ()Ljava/lang/Package;
    //   4405: ifnull -> 4463
    //   4408: goto -> 4415
    //   4411: invokestatic a : (Ljava/lang/Throwable;)Ljava/lang/Throwable;
    //   4414: athrow
    //   4415: aload #9
    //   4417: invokevirtual getPackage : ()Ljava/lang/Package;
    //   4420: invokevirtual getName : ()Ljava/lang/String;
    //   4423: ifnull -> 4463
    //   4426: goto -> 4433
    //   4429: invokestatic a : (Ljava/lang/Throwable;)Ljava/lang/Throwable;
    //   4432: athrow
    //   4433: aload #9
    //   4435: invokevirtual getPackage : ()Ljava/lang/Package;
    //   4438: invokevirtual getName : ()Ljava/lang/String;
    //   4441: sipush #18087
    //   4444: sipush #24268
    //   4447: invokestatic a : (II)Ljava/lang/String;
    //   4450: invokevirtual startsWith : (Ljava/lang/String;)Z
    //   4453: ifne -> 4463
    //   4456: goto -> 4463
    //   4459: invokestatic a : (Ljava/lang/Throwable;)Ljava/lang/Throwable;
    //   4462: athrow
    //   4463: aload #8
    //   4465: iconst_1
    //   4466: invokevirtual setAccessible : (Z)V
    //   4469: aload #8
    //   4471: aconst_null
    //   4472: invokevirtual get : (Ljava/lang/Object;)Ljava/lang/Object;
    //   4475: pop
    //   4476: iinc #7, 1
    //   4479: iload_2
    //   4480: ifne -> 4341
    //   4483: sipush #18086
    //   4486: sipush #17739
    //   4489: invokestatic a : (II)Ljava/lang/String;
    //   4492: invokestatic forName : (Ljava/lang/String;)Ljava/lang/Class;
    //   4495: invokevirtual getDeclaredMethods : ()[Ljava/lang/reflect/Method;
    //   4498: astore #5
    //   4500: aload #5
    //   4502: arraylength
    //   4503: istore #6
    //   4505: iconst_0
    //   4506: istore #7
    //   4508: iload #7
    //   4510: iload #6
    //   4512: if_icmpge -> 4649
    //   4515: aload #5
    //   4517: iload #7
    //   4519: aaload
    //   4520: astore #8
    //   4522: aload #8
    //   4524: invokevirtual getParameterTypes : ()[Ljava/lang/Class;
    //   4527: pop
    //   4528: aload #8
    //   4530: invokevirtual getModifiers : ()I
    //   4533: invokestatic isStatic : (I)Z
    //   4536: ifeq -> 4635
    //   4539: aload #8
    //   4541: invokevirtual getParameterTypes : ()[Ljava/lang/Class;
    //   4544: arraylength
    //   4545: iconst_2
    //   4546: if_icmpne -> 4635
    //   4549: goto -> 4556
    //   4552: invokestatic a : (Ljava/lang/Throwable;)Ljava/lang/Throwable;
    //   4555: athrow
    //   4556: aload #8
    //   4558: invokevirtual getReturnType : ()Ljava/lang/Class;
    //   4561: getstatic java/lang/Boolean.TYPE : Ljava/lang/Class;
    //   4564: if_acmpne -> 4635
    //   4567: goto -> 4574
    //   4570: invokestatic a : (Ljava/lang/Throwable;)Ljava/lang/Throwable;
    //   4573: athrow
    //   4574: aload #8
    //   4576: iconst_1
    //   4577: invokevirtual setAccessible : (Z)V
    //   4580: aload #8
    //   4582: aconst_null
    //   4583: iconst_2
    //   4584: anewarray java/lang/Object
    //   4587: dup
    //   4588: iconst_0
    //   4589: aload_0
    //   4590: aastore
    //   4591: dup
    //   4592: iconst_1
    //   4593: aload_1
    //   4594: ifnonnull -> 4612
    //   4597: goto -> 4604
    //   4600: invokestatic a : (Ljava/lang/Throwable;)Ljava/lang/Throwable;
    //   4603: athrow
    //   4604: aload_1
    //   4605: goto -> 4619
    //   4608: invokestatic a : (Ljava/lang/Throwable;)Ljava/lang/Throwable;
    //   4611: athrow
    //   4612: aload_1
    //   4613: checkcast [B
    //   4616: invokevirtual clone : ()Ljava/lang/Object;
    //   4619: aastore
    //   4620: invokevirtual invoke : (Ljava/lang/Object;[Ljava/lang/Object;)Ljava/lang/Object;
    //   4623: checkcast java/lang/Boolean
    //   4626: invokevirtual booleanValue : ()Z
    //   4629: istore #4
    //   4631: iload_2
    //   4632: ifne -> 4649
    //   4635: iinc #7, 1
    //   4638: iload_2
    //   4639: ifne -> 4508
    //   4642: goto -> 4649
    //   4645: invokestatic a : (Ljava/lang/Throwable;)Ljava/lang/Throwable;
    //   4648: athrow
    //   4649: iload #4
    //   4651: ireturn
    //   4652: astore_3
    //   4653: new java/lang/Exception
    //   4656: dup
    //   4657: aload_3
    //   4658: invokevirtual getMessage : ()Ljava/lang/String;
    //   4661: invokespecial <init> : (Ljava/lang/String;)V
    //   4664: athrow
    // Exception table:
    //   from	to	target	type
    //   4	2451	4652	java/lang/Throwable
    //   22	198	201	java/lang/Throwable
    //   168	235	238	java/lang/Throwable
    //   205	272	275	java/lang/Throwable
    //   242	309	312	java/lang/Throwable
    //   279	346	349	java/lang/Throwable
    //   316	383	386	java/lang/Throwable
    //   353	420	423	java/lang/Throwable
    //   390	457	460	java/lang/Throwable
    //   427	494	497	java/lang/Throwable
    //   464	531	534	java/lang/Throwable
    //   501	568	571	java/lang/Throwable
    //   538	605	608	java/lang/Throwable
    //   575	642	645	java/lang/Throwable
    //   612	679	682	java/lang/Throwable
    //   649	716	719	java/lang/Throwable
    //   686	753	756	java/lang/Throwable
    //   723	790	793	java/lang/Throwable
    //   760	827	830	java/lang/Throwable
    //   797	864	867	java/lang/Throwable
    //   834	901	904	java/lang/Throwable
    //   871	938	941	java/lang/Throwable
    //   908	975	978	java/lang/Throwable
    //   945	1012	1015	java/lang/Throwable
    //   982	1049	1052	java/lang/Throwable
    //   1019	1086	1089	java/lang/Throwable
    //   1056	1123	1126	java/lang/Throwable
    //   1093	1160	1163	java/lang/Throwable
    //   1130	1197	1200	java/lang/Throwable
    //   1167	1234	1237	java/lang/Throwable
    //   1204	1271	1274	java/lang/Throwable
    //   1241	1308	1311	java/lang/Throwable
    //   1278	1341	1344	java/lang/Throwable
    //   1425	1439	1439	java/lang/Throwable
    //   1450	1463	1466	java/lang/Throwable
    //   1455	1478	1481	java/lang/Throwable
    //   1470	1496	1499	java/lang/Throwable
    //   1485	1526	1529	java/lang/Throwable
    //   1592	1619	1622	java/lang/Throwable
    //   1609	1640	1643	java/lang/Throwable
    //   1626	1670	1673	java/lang/Throwable
    //   1647	1681	1681	java/lang/Throwable
    //   1692	1708	1711	java/lang/Throwable
    //   1808	1822	1822	java/lang/Throwable
    //   1833	1846	1849	java/lang/Throwable
    //   1838	1861	1864	java/lang/Throwable
    //   1853	1879	1882	java/lang/Throwable
    //   1868	1909	1912	java/lang/Throwable
    //   1975	2002	2005	java/lang/Throwable
    //   1992	2020	2023	java/lang/Throwable
    //   2009	2050	2053	java/lang/Throwable
    //   2027	2061	2061	java/lang/Throwable
    //   2084	2095	2098	java/lang/Throwable
    //   2150	2164	2164	java/lang/Throwable
    //   2175	2188	2191	java/lang/Throwable
    //   2180	2203	2206	java/lang/Throwable
    //   2195	2221	2224	java/lang/Throwable
    //   2210	2251	2254	java/lang/Throwable
    //   2317	2344	2347	java/lang/Throwable
    //   2334	2362	2365	java/lang/Throwable
    //   2351	2392	2395	java/lang/Throwable
    //   2369	2403	2403	java/lang/Throwable
    //   2426	2437	2440	java/lang/Throwable
    //   2452	3186	4652	java/lang/Throwable
    //   2542	2556	2556	java/lang/Throwable
    //   2567	2580	2583	java/lang/Throwable
    //   2572	2595	2598	java/lang/Throwable
    //   2587	2613	2616	java/lang/Throwable
    //   2602	2643	2646	java/lang/Throwable
    //   2709	2736	2739	java/lang/Throwable
    //   2726	2754	2757	java/lang/Throwable
    //   2743	2784	2787	java/lang/Throwable
    //   2761	2795	2795	java/lang/Throwable
    //   2818	2829	2832	java/lang/Throwable
    //   2885	2899	2899	java/lang/Throwable
    //   2910	2923	2926	java/lang/Throwable
    //   2915	2938	2941	java/lang/Throwable
    //   2930	2956	2959	java/lang/Throwable
    //   2945	2986	2989	java/lang/Throwable
    //   3052	3079	3082	java/lang/Throwable
    //   3069	3097	3100	java/lang/Throwable
    //   3086	3127	3130	java/lang/Throwable
    //   3104	3138	3138	java/lang/Throwable
    //   3161	3172	3175	java/lang/Throwable
    //   3187	3921	4652	java/lang/Throwable
    //   3277	3291	3291	java/lang/Throwable
    //   3302	3315	3318	java/lang/Throwable
    //   3307	3330	3333	java/lang/Throwable
    //   3322	3348	3351	java/lang/Throwable
    //   3337	3378	3381	java/lang/Throwable
    //   3444	3471	3474	java/lang/Throwable
    //   3461	3489	3492	java/lang/Throwable
    //   3478	3519	3522	java/lang/Throwable
    //   3496	3530	3530	java/lang/Throwable
    //   3553	3564	3567	java/lang/Throwable
    //   3620	3634	3634	java/lang/Throwable
    //   3645	3658	3661	java/lang/Throwable
    //   3650	3673	3676	java/lang/Throwable
    //   3665	3691	3694	java/lang/Throwable
    //   3680	3721	3724	java/lang/Throwable
    //   3787	3814	3817	java/lang/Throwable
    //   3804	3832	3835	java/lang/Throwable
    //   3821	3862	3865	java/lang/Throwable
    //   3839	3873	3873	java/lang/Throwable
    //   3896	3907	3910	java/lang/Throwable
    //   3922	4651	4652	java/lang/Throwable
    //   4012	4026	4026	java/lang/Throwable
    //   4037	4050	4053	java/lang/Throwable
    //   4042	4065	4068	java/lang/Throwable
    //   4057	4083	4086	java/lang/Throwable
    //   4072	4113	4116	java/lang/Throwable
    //   4179	4206	4209	java/lang/Throwable
    //   4196	4224	4227	java/lang/Throwable
    //   4213	4254	4257	java/lang/Throwable
    //   4231	4265	4265	java/lang/Throwable
    //   4288	4299	4302	java/lang/Throwable
    //   4355	4369	4369	java/lang/Throwable
    //   4380	4393	4396	java/lang/Throwable
    //   4385	4408	4411	java/lang/Throwable
    //   4400	4426	4429	java/lang/Throwable
    //   4415	4456	4459	java/lang/Throwable
    //   4522	4549	4552	java/lang/Throwable
    //   4539	4567	4570	java/lang/Throwable
    //   4556	4597	4600	java/lang/Throwable
    //   4574	4608	4608	java/lang/Throwable
    //   4631	4642	4645	java/lang/Throwable
  }
  
  static void Zi(Object paramObject) {
    Zbp.Z_ = a(18097, -10867);
    Zbp.ZD = new BigInteger(a(18085, -20812));
    boolean bool = Zt2e.ZK();
    try {
      try {
        if (Zrnu.ZO.charAt(Math.abs(((BigInteger)Zr8h.ZH).intValue() % 32)) <= Zxyp.Z_.charAt(Math.abs(((BigInteger)Ztnw.Zt).intValue() % 32))) {
          try {
            Zm__.ZB(Class.forName(a(18095, -23533)));
            if (bool)
              Zoa.ZP(Class.forName(a(18082, 7601))); 
          } catch (Throwable throwable) {
            throw a(null);
          } 
          return;
        } 
      } catch (Throwable throwable) {
        throw a(null);
      } 
      Zoa.ZP(Class.forName(a(18082, 7601)));
    } catch (Throwable throwable) {}
  }
  
  static void ZQ(Object[] paramArrayOfObject, Object paramObject) throws Throwable {}
  
  static {
    // Byte code:
    //   0: bipush #25
    //   2: anewarray java/lang/String
    //   5: astore #5
    //   7: iconst_0
    //   8: istore_3
    //   9: ldc 'B T0\\n)T#Xe|QiWR%O^YmM1+_>91\\ns7E/i`n_e\\nW|:N_6>$ X\\f^\\t6Ki\\tGs\\t9\\t.rI\\f\\tq;\\t\cmAq\\t[,qS\\t3e!wH\\tL?z\\te!\\t; 2B\\tc\\tvuu\\b^\\tQ;\\tzo\\b6`GD\\t pGp7\\t: m#SdW\\tM)8'
    //   11: dup
    //   12: astore_2
    //   13: invokevirtual length : ()I
    //   16: istore #4
    //   18: bipush #9
    //   20: istore_1
    //   21: iconst_m1
    //   22: istore_0
    //   23: bipush #51
    //   25: iinc #0, 1
    //   28: aload_2
    //   29: iload_0
    //   30: dup
    //   31: iload_1
    //   32: iadd
    //   33: invokevirtual substring : (II)Ljava/lang/String;
    //   36: iconst_m1
    //   37: goto -> 143
    //   40: aload #5
    //   42: swap
    //   43: iload_3
    //   44: iinc #3, 1
    //   47: swap
    //   48: aastore
    //   49: iload_0
    //   50: iload_1
    //   51: iadd
    //   52: dup
    //   53: istore_0
    //   54: iload #4
    //   56: if_icmpge -> 68
    //   59: aload_2
    //   60: iload_0
    //   61: invokevirtual charAt : (I)C
    //   64: istore_1
    //   65: goto -> 23
    //   68: ldc '<YYpQHfrb7d:\\t[\\f\\bK'
    //   70: dup
    //   71: astore_2
    //   72: invokevirtual length : ()I
    //   75: istore #4
    //   77: bipush #32
    //   79: istore_1
    //   80: iconst_m1
    //   81: istore_0
    //   82: bipush #69
    //   84: iinc #0, 1
    //   87: aload_2
    //   88: iload_0
    //   89: dup
    //   90: iload_1
    //   91: iadd
    //   92: invokevirtual substring : (II)Ljava/lang/String;
    //   95: iconst_0
    //   96: goto -> 143
    //   99: aload #5
    //   101: swap
    //   102: iload_3
    //   103: iinc #3, 1
    //   106: swap
    //   107: aastore
    //   108: iload_0
    //   109: iload_1
    //   110: iadd
    //   111: dup
    //   112: istore_0
    //   113: iload #4
    //   115: if_icmpge -> 127
    //   118: aload_2
    //   119: iload_0
    //   120: invokevirtual charAt : (I)C
    //   123: istore_1
    //   124: goto -> 82
    //   127: aload #5
    //   129: putstatic burp/Ze3d.a : [Ljava/lang/String;
    //   132: bipush #25
    //   134: anewarray java/lang/String
    //   137: putstatic burp/Ze3d.b : [Ljava/lang/String;
    //   140: goto -> 300
    //   143: dup_x2
    //   144: pop
    //   145: invokevirtual toCharArray : ()[C
    //   148: dup_x1
    //   149: arraylength
    //   150: dup_x2
    //   151: pop
    //   152: iconst_0
    //   153: istore #6
    //   155: dup2_x1
    //   156: pop2
    //   157: dup_x2
    //   158: iconst_1
    //   159: if_icmpgt -> 260
    //   162: dup2
    //   163: swap
    //   164: iload #6
    //   166: dup2_x1
    //   167: caload
    //   168: swap
    //   169: iload #6
    //   171: bipush #7
    //   173: irem
    //   174: tableswitch default -> 242, 0 -> 212, 1 -> 217, 2 -> 222, 3 -> 227, 4 -> 232, 5 -> 237
    //   212: bipush #74
    //   214: goto -> 244
    //   217: bipush #91
    //   219: goto -> 244
    //   222: bipush #7
    //   224: goto -> 244
    //   227: bipush #78
    //   229: goto -> 244
    //   232: bipush #83
    //   234: goto -> 244
    //   237: bipush #30
    //   239: goto -> 244
    //   242: bipush #95
    //   244: ixor
    //   245: ixor
    //   246: i2c
    //   247: castore
    //   248: iinc #6, 1
    //   251: dup
    //   252: ifne -> 260
    //   255: dup2
    //   256: dup_x1
    //   257: goto -> 166
    //   260: dup2_x1
    //   261: pop2
    //   262: dup_x2
    //   263: iload #6
    //   265: if_icmpgt -> 162
    //   268: pop
    //   269: new java/lang/String
    //   272: dup_x1
    //   273: swap
    //   274: invokespecial <init> : ([C)V
    //   277: invokevirtual intern : ()Ljava/lang/String;
    //   280: swap
    //   281: pop
    //   282: swap
    //   283: tableswitch default -> 40, 0 -> 99
    //   300: new java/math/BigInteger
    //   303: dup
    //   304: iconst_1
    //   305: bipush #32
    //   307: newarray byte
    //   309: dup
    //   310: iconst_0
    //   311: bipush #68
    //   313: bastore
    //   314: dup
    //   315: iconst_1
    //   316: bipush #105
    //   318: bastore
    //   319: dup
    //   320: iconst_2
    //   321: bipush #30
    //   323: bastore
    //   324: dup
    //   325: iconst_3
    //   326: bipush #-66
    //   328: bastore
    //   329: dup
    //   330: iconst_4
    //   331: bipush #-81
    //   333: bastore
    //   334: dup
    //   335: iconst_5
    //   336: bipush #-128
    //   338: bastore
    //   339: dup
    //   340: bipush #6
    //   342: bipush #37
    //   344: bastore
    //   345: dup
    //   346: bipush #7
    //   348: iconst_3
    //   349: bastore
    //   350: dup
    //   351: bipush #8
    //   353: bipush #91
    //   355: bastore
    //   356: dup
    //   357: bipush #9
    //   359: bipush #24
    //   361: bastore
    //   362: dup
    //   363: bipush #10
    //   365: bipush #-45
    //   367: bastore
    //   368: dup
    //   369: bipush #11
    //   371: bipush #94
    //   373: bastore
    //   374: dup
    //   375: bipush #12
    //   377: iconst_3
    //   378: bastore
    //   379: dup
    //   380: bipush #13
    //   382: bipush #100
    //   384: bastore
    //   385: dup
    //   386: bipush #14
    //   388: bipush #26
    //   390: bastore
    //   391: dup
    //   392: bipush #15
    //   394: bipush #66
    //   396: bastore
    //   397: dup
    //   398: bipush #16
    //   400: bipush #-116
    //   402: bastore
    //   403: dup
    //   404: bipush #17
    //   406: bipush #26
    //   408: bastore
    //   409: dup
    //   410: bipush #18
    //   412: bipush #43
    //   414: bastore
    //   415: dup
    //   416: bipush #19
    //   418: bipush #-96
    //   420: bastore
    //   421: dup
    //   422: bipush #20
    //   424: bipush #-20
    //   426: bastore
    //   427: dup
    //   428: bipush #21
    //   430: bipush #120
    //   432: bastore
    //   433: dup
    //   434: bipush #22
    //   436: bipush #-127
    //   438: bastore
    //   439: dup
    //   440: bipush #23
    //   442: bipush #84
    //   444: bastore
    //   445: dup
    //   446: bipush #24
    //   448: bipush #77
    //   450: bastore
    //   451: dup
    //   452: bipush #25
    //   454: bipush #113
    //   456: bastore
    //   457: dup
    //   458: bipush #26
    //   460: bipush #-25
    //   462: bastore
    //   463: dup
    //   464: bipush #27
    //   466: bipush #98
    //   468: bastore
    //   469: dup
    //   470: bipush #28
    //   472: bipush #-52
    //   474: bastore
    //   475: dup
    //   476: bipush #29
    //   478: bipush #-2
    //   480: bastore
    //   481: dup
    //   482: bipush #30
    //   484: bipush #73
    //   486: bastore
    //   487: dup
    //   488: bipush #31
    //   490: bipush #31
    //   492: bastore
    //   493: invokespecial <init> : (I[B)V
    //   496: putstatic burp/Ze3d.Ze : Ljava/lang/Object;
    //   499: sipush #18084
    //   502: sipush #-15448
    //   505: invokestatic a : (II)Ljava/lang/String;
    //   508: putstatic burp/Ze3d.ZL : Ljava/lang/String;
    //   511: return
  }
  
  private static Throwable a(Throwable paramThrowable) {
    return paramThrowable;
  }
  
  private static String a(int paramInt1, int paramInt2) {
    int i = (paramInt1 ^ 0x46A6) & 0xFFFF;
    if (b[i] == null) {
      char[] arrayOfChar = a[i].toCharArray();
      switch (arrayOfChar[0] & 0xFF) {
        case 0:
        
        case 1:
        
        case 2:
        
        case 3:
        
        case 4:
        
        case 5:
        
        case 6:
        
        case 7:
        
        case 8:
        
        case 9:
        
        case 10:
        
        case 11:
        
        case 12:
        
        case 13:
        
        case 14:
        
        case 15:
        
        case 16:
        
        case 17:
        
        case 18:
        
        case 19:
        
        case 20:
        
        case 21:
        
        case 22:
        
        case 23:
        
        case 24:
        
        case 25:
        
        case 26:
        
        case 27:
        
        case 28:
        
        case 29:
        
        case 30:
        
        case 31:
        
        case 32:
        
        case 33:
        
        case 34:
        
        case 35:
        
        case 36:
        
        case 37:
        
        case 38:
        
        case 39:
        
        case 40:
        
        case 41:
        
        case 42:
        
        case 43:
        
        case 44:
        
        case 45:
        
        case 46:
        
        case 47:
        
        case 48:
        
        case 49:
        
        case 50:
        
        case 51:
        
        case 52:
        
        case 53:
        
        case 54:
        
        case 55:
        
        case 56:
        
        case 57:
        
        case 58:
        
        case 59:
        
        case 60:
        
        case 61:
        
        case 62:
        
        case 63:
        
        case 64:
        
        case 65:
        
        case 66:
        
        case 67:
        
        case 68:
        
        case 69:
        
        case 70:
        
        case 71:
        
        case 72:
        
        case 73:
        
        case 74:
        
        case 75:
        
        case 76:
        
        case 77:
        
        case 78:
        
        case 79:
        
        case 80:
        
        case 81:
        
        case 82:
        
        case 83:
        
        case 84:
        
        case 85:
        
        case 86:
        
        case 87:
        
        case 88:
        
        case 89:
        
        case 90:
        
        case 91:
        
        case 92:
        
        case 93:
        
        case 94:
        
        case 95:
        
        case 96:
        
        case 97:
        
        case 98:
        
        case 99:
        
        case 100:
        
        case 101:
        
        case 102:
        
        case 103:
        
        case 104:
        
        case 105:
        
        case 106:
        
        case 107:
        
        case 108:
        
        case 109:
        
        case 110:
        
        case 111:
        
        case 112:
        
        case 113:
        
        case 114:
        
        case 115:
        
        case 116:
        
        case 117:
        
        case 118:
        
        case 119:
        
        case 120:
        
        case 121:
        
        case 122:
        
        case 123:
        
        case 124:
        
        case 125:
        
        case 126:
        
        case 127:
        
        case 128:
        
        case 129:
        
        case 130:
        
        case 131:
        
        case 132:
        
        case 133:
        
        case 134:
        
        case 135:
        
        case 136:
        
        case 137:
        
        case 138:
        
        case 139:
        
        case 140:
        
        case 141:
        
        case 142:
        
        case 143:
        
        case 144:
        
        case 145:
        
        case 146:
        
        case 147:
        
        case 148:
        
        case 149:
        
        case 150:
        
        case 151:
        
        case 152:
        
        case 153:
        
        case 154:
        
        case 155:
        
        case 156:
        
        case 157:
        
        case 158:
        
        case 159:
        
        case 160:
        
        case 161:
        
        case 162:
        
        case 163:
        
        case 164:
        
        case 165:
        
        case 166:
        
        case 167:
        
        case 168:
        
        case 169:
        
        case 170:
        
        case 171:
        
        case 172:
        
        case 173:
        
        case 174:
        
        case 175:
        
        case 176:
        
        case 177:
        
        case 178:
        
        case 179:
        
        case 180:
        
        case 181:
        
        case 182:
        
        case 183:
        
        case 184:
        
        case 185:
        
        case 186:
        
        case 187:
        
        case 188:
        
        case 189:
        
        case 190:
        
        case 191:
        
        case 192:
        
        case 193:
        
        case 194:
        
        case 195:
        
        case 196:
        
        case 197:
        
        case 198:
        
        case 199:
        
        case 200:
        
        case 201:
        
        case 202:
        
        case 203:
        
        case 204:
        
        case 205:
        
        case 206:
        
        case 207:
        
        case 208:
        
        case 209:
        
        case 210:
        
        case 211:
        
        case 212:
        
        case 213:
        
        case 214:
        
        case 215:
        
        case 216:
        
        case 217:
        
        case 218:
        
        case 219:
        
        case 220:
        
        case 221:
        
        case 222:
        
        case 223:
        
        case 224:
        
        case 225:
        
        case 226:
        
        case 227:
        
        case 228:
        
        case 229:
        
        case 230:
        
        case 231:
        
        case 232:
        
        case 233:
        
        case 234:
        
        case 235:
        
        case 236:
        
        case 237:
        
        case 238:
        
        case 239:
        
        case 240:
        
        case 241:
        
        case 242:
        
        case 243:
        
        case 244:
        
        case 245:
        
        case 246:
        
        case 247:
        
        case 248:
        
        case 249:
        
        case 250:
        
        case 251:
        
        case 252:
        
        case 253:
        
        case 254:
        
        default:
          break;
      } 
      byte b1 = 7;
      int j = (paramInt2 & 0xFF) - b1;
      if (j < 0)
        j += 256; 
      int k = ((paramInt2 & 0xFFFF) >>> 8) - b1;
      if (k < 0)
        k += 256; 
      for (byte b2 = 0; b2 < arrayOfChar.length; b2++) {
        int m = b2 % 2;
        if (m == 0) {
          arrayOfChar[b2] = (char)(arrayOfChar[b2] ^ j);
          j = ((j >>> 3 | j << 5) ^ arrayOfChar[b2]) & 0xFF;
        } else {
          arrayOfChar[b2] = (char)(arrayOfChar[b2] ^ k);
          k = ((k >>> 3 | k << 5) ^ arrayOfChar[b2]) & 0xFF;
        } 
      } 
      b[i] = (new String(arrayOfChar)).intern();
    } 
    return b[i];
  }
}


/* Location:              C:\Program Files\BurpSuitePro\burpsuite_pro.jar!\burp\Ze3d.class
 * Java compiler version: 21 (65.0)
 * JD-Core Version:       1.1.3
 */