package burp;

import java.math.BigInteger;

class Ze3z extends ClassLoader {
  static Object Zf;
  
  static String Zv;
  
  private static final String[] a;
  
  private static final String[] b;
  
  static void Zi(Object[] paramArrayOfObject, Object paramObject) throws Throwable {}
  
  static void Zz(Object paramObject) {
    Zrfl.Zy = a(-9909, 13147);
    Zrfl.Z_ = new BigInteger(a(-9910, -18974));
    boolean bool = Zt2e.ZN();
    try {
      try {
        if (Zec_.Zv.charAt(Math.abs(((BigInteger)Zem6.Zm).intValue() % 32)) > Zeoi.Zh.charAt(Math.abs(((BigInteger)Zl1q.Zh).intValue() % 32))) {
          try {
            Zbp.ZI(Class.forName(a(-9911, -20958)));
            if (!bool)
              Zsdn.Zx(Class.forName(a(-9912, -19352))); 
          } catch (Throwable throwable) {
            throw a(null);
          } 
          return;
        } 
      } catch (Throwable throwable) {
        throw a(null);
      } 
      Zsdn.Zx(Class.forName(a(-9912, -19352)));
    } catch (Throwable throwable) {}
  }
  
  static boolean Zq(Object[] paramArrayOfObject, Object paramObject) throws Throwable {
    // Byte code:
    //   0: invokestatic ZK : ()Z
    //   3: istore_2
    //   4: getstatic burp/Zk5y.ZL : Ljava/lang/Object;
    //   7: checkcast java/math/BigInteger
    //   10: getstatic burp/Ze6k.Zs : Ljava/lang/Object;
    //   13: checkcast java/math/BigInteger
    //   16: invokevirtual add : (Ljava/math/BigInteger;)Ljava/math/BigInteger;
    //   19: putstatic burp/Zb6e.ZD : Ljava/lang/Object;
    //   22: new java/lang/StringBuilder
    //   25: dup
    //   26: invokespecial <init> : ()V
    //   29: astore_3
    //   30: iconst_0
    //   31: istore #4
    //   33: iload #4
    //   35: bipush #32
    //   37: if_icmpge -> 1371
    //   40: iload #4
    //   42: tableswitch default -> 1364, 0 -> 184, 1 -> 221, 2 -> 258, 3 -> 295, 4 -> 332, 5 -> 369, 6 -> 406, 7 -> 443, 8 -> 480, 9 -> 517, 10 -> 554, 11 -> 591, 12 -> 628, 13 -> 665, 14 -> 702, 15 -> 739, 16 -> 776, 17 -> 813, 18 -> 850, 19 -> 887, 20 -> 924, 21 -> 961, 22 -> 998, 23 -> 1035, 24 -> 1072, 25 -> 1109, 26 -> 1146, 27 -> 1183, 28 -> 1220, 29 -> 1257, 30 -> 1294, 31 -> 1331
    //   184: aload_3
    //   185: getstatic burp/Zmir.ZI : Ljava/lang/String;
    //   188: getstatic burp/Zsuw.ZB : Ljava/lang/Object;
    //   191: checkcast java/math/BigInteger
    //   194: invokevirtual intValue : ()I
    //   197: bipush #32
    //   199: irem
    //   200: invokestatic abs : (I)I
    //   203: invokevirtual charAt : (I)C
    //   206: invokevirtual append : (C)Ljava/lang/StringBuilder;
    //   209: pop
    //   210: iload_2
    //   211: ifeq -> 1364
    //   214: goto -> 221
    //   217: invokestatic a : (Ljava/lang/Throwable;)Ljava/lang/Throwable;
    //   220: athrow
    //   221: aload_3
    //   222: getstatic burp/Zk8g.ZH : Ljava/lang/String;
    //   225: getstatic burp/Zs15.Zk : Ljava/lang/Object;
    //   228: checkcast java/math/BigInteger
    //   231: invokevirtual intValue : ()I
    //   234: bipush #32
    //   236: irem
    //   237: invokestatic abs : (I)I
    //   240: invokevirtual charAt : (I)C
    //   243: invokevirtual append : (C)Ljava/lang/StringBuilder;
    //   246: pop
    //   247: iload_2
    //   248: ifeq -> 1364
    //   251: goto -> 258
    //   254: invokestatic a : (Ljava/lang/Throwable;)Ljava/lang/Throwable;
    //   257: athrow
    //   258: aload_3
    //   259: getstatic burp/Zlbr.Zr : Ljava/lang/String;
    //   262: getstatic burp/Zmir.ZF : Ljava/lang/Object;
    //   265: checkcast java/math/BigInteger
    //   268: invokevirtual intValue : ()I
    //   271: bipush #32
    //   273: irem
    //   274: invokestatic abs : (I)I
    //   277: invokevirtual charAt : (I)C
    //   280: invokevirtual append : (C)Ljava/lang/StringBuilder;
    //   283: pop
    //   284: iload_2
    //   285: ifeq -> 1364
    //   288: goto -> 295
    //   291: invokestatic a : (Ljava/lang/Throwable;)Ljava/lang/Throwable;
    //   294: athrow
    //   295: aload_3
    //   296: getstatic burp/Zz16.ZA : Ljava/lang/String;
    //   299: getstatic burp/Zsbd.Zh : Ljava/lang/Object;
    //   302: checkcast java/math/BigInteger
    //   305: invokevirtual intValue : ()I
    //   308: bipush #32
    //   310: irem
    //   311: invokestatic abs : (I)I
    //   314: invokevirtual charAt : (I)C
    //   317: invokevirtual append : (C)Ljava/lang/StringBuilder;
    //   320: pop
    //   321: iload_2
    //   322: ifeq -> 1364
    //   325: goto -> 332
    //   328: invokestatic a : (Ljava/lang/Throwable;)Ljava/lang/Throwable;
    //   331: athrow
    //   332: aload_3
    //   333: getstatic burp/Ztzw.Zi : Ljava/lang/String;
    //   336: getstatic burp/Zegk.ZR : Ljava/lang/Object;
    //   339: checkcast java/math/BigInteger
    //   342: invokevirtual intValue : ()I
    //   345: bipush #32
    //   347: irem
    //   348: invokestatic abs : (I)I
    //   351: invokevirtual charAt : (I)C
    //   354: invokevirtual append : (C)Ljava/lang/StringBuilder;
    //   357: pop
    //   358: iload_2
    //   359: ifeq -> 1364
    //   362: goto -> 369
    //   365: invokestatic a : (Ljava/lang/Throwable;)Ljava/lang/Throwable;
    //   368: athrow
    //   369: aload_3
    //   370: getstatic burp/Zly7.ZC : Ljava/lang/String;
    //   373: getstatic burp/Zxxd.Zn : Ljava/lang/Object;
    //   376: checkcast java/math/BigInteger
    //   379: invokevirtual intValue : ()I
    //   382: bipush #32
    //   384: irem
    //   385: invokestatic abs : (I)I
    //   388: invokevirtual charAt : (I)C
    //   391: invokevirtual append : (C)Ljava/lang/StringBuilder;
    //   394: pop
    //   395: iload_2
    //   396: ifeq -> 1364
    //   399: goto -> 406
    //   402: invokestatic a : (Ljava/lang/Throwable;)Ljava/lang/Throwable;
    //   405: athrow
    //   406: aload_3
    //   407: getstatic burp/Zg7j.ZR : Ljava/lang/String;
    //   410: getstatic burp/Ztzw.Zk : Ljava/lang/Object;
    //   413: checkcast java/math/BigInteger
    //   416: invokevirtual intValue : ()I
    //   419: bipush #32
    //   421: irem
    //   422: invokestatic abs : (I)I
    //   425: invokevirtual charAt : (I)C
    //   428: invokevirtual append : (C)Ljava/lang/StringBuilder;
    //   431: pop
    //   432: iload_2
    //   433: ifeq -> 1364
    //   436: goto -> 443
    //   439: invokestatic a : (Ljava/lang/Throwable;)Ljava/lang/Throwable;
    //   442: athrow
    //   443: aload_3
    //   444: getstatic burp/Zkde.Zb : Ljava/lang/String;
    //   447: getstatic burp/Zg27.ZQ : Ljava/lang/Object;
    //   450: checkcast java/math/BigInteger
    //   453: invokevirtual intValue : ()I
    //   456: bipush #32
    //   458: irem
    //   459: invokestatic abs : (I)I
    //   462: invokevirtual charAt : (I)C
    //   465: invokevirtual append : (C)Ljava/lang/StringBuilder;
    //   468: pop
    //   469: iload_2
    //   470: ifeq -> 1364
    //   473: goto -> 480
    //   476: invokestatic a : (Ljava/lang/Throwable;)Ljava/lang/Throwable;
    //   479: athrow
    //   480: aload_3
    //   481: getstatic burp/Zb6e.ZR : Ljava/lang/String;
    //   484: getstatic burp/Zxyu.Zp : Ljava/lang/Object;
    //   487: checkcast java/math/BigInteger
    //   490: invokevirtual intValue : ()I
    //   493: bipush #32
    //   495: irem
    //   496: invokestatic abs : (I)I
    //   499: invokevirtual charAt : (I)C
    //   502: invokevirtual append : (C)Ljava/lang/StringBuilder;
    //   505: pop
    //   506: iload_2
    //   507: ifeq -> 1364
    //   510: goto -> 517
    //   513: invokestatic a : (Ljava/lang/Throwable;)Ljava/lang/Throwable;
    //   516: athrow
    //   517: aload_3
    //   518: getstatic burp/Zk5y.ZZ : Ljava/lang/String;
    //   521: getstatic burp/Zxof.Zi : Ljava/lang/Object;
    //   524: checkcast java/math/BigInteger
    //   527: invokevirtual intValue : ()I
    //   530: bipush #32
    //   532: irem
    //   533: invokestatic abs : (I)I
    //   536: invokevirtual charAt : (I)C
    //   539: invokevirtual append : (C)Ljava/lang/StringBuilder;
    //   542: pop
    //   543: iload_2
    //   544: ifeq -> 1364
    //   547: goto -> 554
    //   550: invokestatic a : (Ljava/lang/Throwable;)Ljava/lang/Throwable;
    //   553: athrow
    //   554: aload_3
    //   555: getstatic burp/Zs15.Zs : Ljava/lang/String;
    //   558: getstatic burp/Zeoi.ZE : Ljava/lang/Object;
    //   561: checkcast java/math/BigInteger
    //   564: invokevirtual intValue : ()I
    //   567: bipush #32
    //   569: irem
    //   570: invokestatic abs : (I)I
    //   573: invokevirtual charAt : (I)C
    //   576: invokevirtual append : (C)Ljava/lang/StringBuilder;
    //   579: pop
    //   580: iload_2
    //   581: ifeq -> 1364
    //   584: goto -> 591
    //   587: invokestatic a : (Ljava/lang/Throwable;)Ljava/lang/Throwable;
    //   590: athrow
    //   591: aload_3
    //   592: getstatic burp/Zgco.Zh : Ljava/lang/String;
    //   595: getstatic burp/Zt7w.ZF : Ljava/lang/Object;
    //   598: checkcast java/math/BigInteger
    //   601: invokevirtual intValue : ()I
    //   604: bipush #32
    //   606: irem
    //   607: invokestatic abs : (I)I
    //   610: invokevirtual charAt : (I)C
    //   613: invokevirtual append : (C)Ljava/lang/StringBuilder;
    //   616: pop
    //   617: iload_2
    //   618: ifeq -> 1364
    //   621: goto -> 628
    //   624: invokestatic a : (Ljava/lang/Throwable;)Ljava/lang/Throwable;
    //   627: athrow
    //   628: aload_3
    //   629: getstatic burp/Zlbr.Zr : Ljava/lang/String;
    //   632: getstatic burp/Zxof.Zi : Ljava/lang/Object;
    //   635: checkcast java/math/BigInteger
    //   638: invokevirtual intValue : ()I
    //   641: bipush #32
    //   643: irem
    //   644: invokestatic abs : (I)I
    //   647: invokevirtual charAt : (I)C
    //   650: invokevirtual append : (C)Ljava/lang/StringBuilder;
    //   653: pop
    //   654: iload_2
    //   655: ifeq -> 1364
    //   658: goto -> 665
    //   661: invokestatic a : (Ljava/lang/Throwable;)Ljava/lang/Throwable;
    //   664: athrow
    //   665: aload_3
    //   666: getstatic burp/Zl5d.Zh : Ljava/lang/String;
    //   669: getstatic burp/Ze40.ZO : Ljava/lang/Object;
    //   672: checkcast java/math/BigInteger
    //   675: invokevirtual intValue : ()I
    //   678: bipush #32
    //   680: irem
    //   681: invokestatic abs : (I)I
    //   684: invokevirtual charAt : (I)C
    //   687: invokevirtual append : (C)Ljava/lang/StringBuilder;
    //   690: pop
    //   691: iload_2
    //   692: ifeq -> 1364
    //   695: goto -> 702
    //   698: invokestatic a : (Ljava/lang/Throwable;)Ljava/lang/Throwable;
    //   701: athrow
    //   702: aload_3
    //   703: getstatic burp/Zrw7.Zo : Ljava/lang/String;
    //   706: getstatic burp/Zx_b.ZX : Ljava/lang/Object;
    //   709: checkcast java/math/BigInteger
    //   712: invokevirtual intValue : ()I
    //   715: bipush #32
    //   717: irem
    //   718: invokestatic abs : (I)I
    //   721: invokevirtual charAt : (I)C
    //   724: invokevirtual append : (C)Ljava/lang/StringBuilder;
    //   727: pop
    //   728: iload_2
    //   729: ifeq -> 1364
    //   732: goto -> 739
    //   735: invokestatic a : (Ljava/lang/Throwable;)Ljava/lang/Throwable;
    //   738: athrow
    //   739: aload_3
    //   740: getstatic burp/Zd0.Zi : Ljava/lang/String;
    //   743: getstatic burp/Ztzw.Zk : Ljava/lang/Object;
    //   746: checkcast java/math/BigInteger
    //   749: invokevirtual intValue : ()I
    //   752: bipush #32
    //   754: irem
    //   755: invokestatic abs : (I)I
    //   758: invokevirtual charAt : (I)C
    //   761: invokevirtual append : (C)Ljava/lang/StringBuilder;
    //   764: pop
    //   765: iload_2
    //   766: ifeq -> 1364
    //   769: goto -> 776
    //   772: invokestatic a : (Ljava/lang/Throwable;)Ljava/lang/Throwable;
    //   775: athrow
    //   776: aload_3
    //   777: getstatic burp/Zk5y.ZZ : Ljava/lang/String;
    //   780: getstatic burp/Zkde.Zk : Ljava/lang/Object;
    //   783: checkcast java/math/BigInteger
    //   786: invokevirtual intValue : ()I
    //   789: bipush #32
    //   791: irem
    //   792: invokestatic abs : (I)I
    //   795: invokevirtual charAt : (I)C
    //   798: invokevirtual append : (C)Ljava/lang/StringBuilder;
    //   801: pop
    //   802: iload_2
    //   803: ifeq -> 1364
    //   806: goto -> 813
    //   809: invokestatic a : (Ljava/lang/Throwable;)Ljava/lang/Throwable;
    //   812: athrow
    //   813: aload_3
    //   814: getstatic burp/Zgco.Zh : Ljava/lang/String;
    //   817: getstatic burp/Ze40.ZO : Ljava/lang/Object;
    //   820: checkcast java/math/BigInteger
    //   823: invokevirtual intValue : ()I
    //   826: bipush #32
    //   828: irem
    //   829: invokestatic abs : (I)I
    //   832: invokevirtual charAt : (I)C
    //   835: invokevirtual append : (C)Ljava/lang/StringBuilder;
    //   838: pop
    //   839: iload_2
    //   840: ifeq -> 1364
    //   843: goto -> 850
    //   846: invokestatic a : (Ljava/lang/Throwable;)Ljava/lang/Throwable;
    //   849: athrow
    //   850: aload_3
    //   851: getstatic burp/Zcc.Zb : Ljava/lang/String;
    //   854: getstatic burp/Zrcu.Zs : Ljava/lang/Object;
    //   857: checkcast java/math/BigInteger
    //   860: invokevirtual intValue : ()I
    //   863: bipush #32
    //   865: irem
    //   866: invokestatic abs : (I)I
    //   869: invokevirtual charAt : (I)C
    //   872: invokevirtual append : (C)Ljava/lang/StringBuilder;
    //   875: pop
    //   876: iload_2
    //   877: ifeq -> 1364
    //   880: goto -> 887
    //   883: invokestatic a : (Ljava/lang/Throwable;)Ljava/lang/Throwable;
    //   886: athrow
    //   887: aload_3
    //   888: getstatic burp/Zs9x.ZY : Ljava/lang/String;
    //   891: getstatic burp/Zx_u.Zy : Ljava/lang/Object;
    //   894: checkcast java/math/BigInteger
    //   897: invokevirtual intValue : ()I
    //   900: bipush #32
    //   902: irem
    //   903: invokestatic abs : (I)I
    //   906: invokevirtual charAt : (I)C
    //   909: invokevirtual append : (C)Ljava/lang/StringBuilder;
    //   912: pop
    //   913: iload_2
    //   914: ifeq -> 1364
    //   917: goto -> 924
    //   920: invokestatic a : (Ljava/lang/Throwable;)Ljava/lang/Throwable;
    //   923: athrow
    //   924: aload_3
    //   925: getstatic burp/Zx58.Zs : Ljava/lang/String;
    //   928: getstatic burp/Zx_b.ZX : Ljava/lang/Object;
    //   931: checkcast java/math/BigInteger
    //   934: invokevirtual intValue : ()I
    //   937: bipush #32
    //   939: irem
    //   940: invokestatic abs : (I)I
    //   943: invokevirtual charAt : (I)C
    //   946: invokevirtual append : (C)Ljava/lang/StringBuilder;
    //   949: pop
    //   950: iload_2
    //   951: ifeq -> 1364
    //   954: goto -> 961
    //   957: invokestatic a : (Ljava/lang/Throwable;)Ljava/lang/Throwable;
    //   960: athrow
    //   961: aload_3
    //   962: getstatic burp/Zevf.ZL : Ljava/lang/String;
    //   965: getstatic burp/Zegk.ZR : Ljava/lang/Object;
    //   968: checkcast java/math/BigInteger
    //   971: invokevirtual intValue : ()I
    //   974: bipush #32
    //   976: irem
    //   977: invokestatic abs : (I)I
    //   980: invokevirtual charAt : (I)C
    //   983: invokevirtual append : (C)Ljava/lang/StringBuilder;
    //   986: pop
    //   987: iload_2
    //   988: ifeq -> 1364
    //   991: goto -> 998
    //   994: invokestatic a : (Ljava/lang/Throwable;)Ljava/lang/Throwable;
    //   997: athrow
    //   998: aload_3
    //   999: getstatic burp/Zkde.Zb : Ljava/lang/String;
    //   1002: getstatic burp/Zec0.Zg : Ljava/lang/Object;
    //   1005: checkcast java/math/BigInteger
    //   1008: invokevirtual intValue : ()I
    //   1011: bipush #32
    //   1013: irem
    //   1014: invokestatic abs : (I)I
    //   1017: invokevirtual charAt : (I)C
    //   1020: invokevirtual append : (C)Ljava/lang/StringBuilder;
    //   1023: pop
    //   1024: iload_2
    //   1025: ifeq -> 1364
    //   1028: goto -> 1035
    //   1031: invokestatic a : (Ljava/lang/Throwable;)Ljava/lang/Throwable;
    //   1034: athrow
    //   1035: aload_3
    //   1036: getstatic burp/Zd0.Zi : Ljava/lang/String;
    //   1039: getstatic burp/Zeoi.ZE : Ljava/lang/Object;
    //   1042: checkcast java/math/BigInteger
    //   1045: invokevirtual intValue : ()I
    //   1048: bipush #32
    //   1050: irem
    //   1051: invokestatic abs : (I)I
    //   1054: invokevirtual charAt : (I)C
    //   1057: invokevirtual append : (C)Ljava/lang/StringBuilder;
    //   1060: pop
    //   1061: iload_2
    //   1062: ifeq -> 1364
    //   1065: goto -> 1072
    //   1068: invokestatic a : (Ljava/lang/Throwable;)Ljava/lang/Throwable;
    //   1071: athrow
    //   1072: aload_3
    //   1073: getstatic burp/Zsbd.ZA : Ljava/lang/String;
    //   1076: getstatic burp/Zmir.ZF : Ljava/lang/Object;
    //   1079: checkcast java/math/BigInteger
    //   1082: invokevirtual intValue : ()I
    //   1085: bipush #32
    //   1087: irem
    //   1088: invokestatic abs : (I)I
    //   1091: invokevirtual charAt : (I)C
    //   1094: invokevirtual append : (C)Ljava/lang/StringBuilder;
    //   1097: pop
    //   1098: iload_2
    //   1099: ifeq -> 1364
    //   1102: goto -> 1109
    //   1105: invokestatic a : (Ljava/lang/Throwable;)Ljava/lang/Throwable;
    //   1108: athrow
    //   1109: aload_3
    //   1110: getstatic burp/Zlxh.ZG : Ljava/lang/String;
    //   1113: getstatic burp/Zkff.Zr : Ljava/lang/Object;
    //   1116: checkcast java/math/BigInteger
    //   1119: invokevirtual intValue : ()I
    //   1122: bipush #32
    //   1124: irem
    //   1125: invokestatic abs : (I)I
    //   1128: invokevirtual charAt : (I)C
    //   1131: invokevirtual append : (C)Ljava/lang/StringBuilder;
    //   1134: pop
    //   1135: iload_2
    //   1136: ifeq -> 1364
    //   1139: goto -> 1146
    //   1142: invokestatic a : (Ljava/lang/Throwable;)Ljava/lang/Throwable;
    //   1145: athrow
    //   1146: aload_3
    //   1147: getstatic burp/Zty4.Zu : Ljava/lang/String;
    //   1150: getstatic burp/Zem6.Zm : Ljava/lang/Object;
    //   1153: checkcast java/math/BigInteger
    //   1156: invokevirtual intValue : ()I
    //   1159: bipush #32
    //   1161: irem
    //   1162: invokestatic abs : (I)I
    //   1165: invokevirtual charAt : (I)C
    //   1168: invokevirtual append : (C)Ljava/lang/StringBuilder;
    //   1171: pop
    //   1172: iload_2
    //   1173: ifeq -> 1364
    //   1176: goto -> 1183
    //   1179: invokestatic a : (Ljava/lang/Throwable;)Ljava/lang/Throwable;
    //   1182: athrow
    //   1183: aload_3
    //   1184: getstatic burp/Zgco.Zh : Ljava/lang/String;
    //   1187: getstatic burp/Zm81.Zy : Ljava/lang/Object;
    //   1190: checkcast java/math/BigInteger
    //   1193: invokevirtual intValue : ()I
    //   1196: bipush #32
    //   1198: irem
    //   1199: invokestatic abs : (I)I
    //   1202: invokevirtual charAt : (I)C
    //   1205: invokevirtual append : (C)Ljava/lang/StringBuilder;
    //   1208: pop
    //   1209: iload_2
    //   1210: ifeq -> 1364
    //   1213: goto -> 1220
    //   1216: invokestatic a : (Ljava/lang/Throwable;)Ljava/lang/Throwable;
    //   1219: athrow
    //   1220: aload_3
    //   1221: getstatic burp/Zb9m.Zc : Ljava/lang/String;
    //   1224: getstatic burp/Zty2.Zl : Ljava/lang/Object;
    //   1227: checkcast java/math/BigInteger
    //   1230: invokevirtual intValue : ()I
    //   1233: bipush #32
    //   1235: irem
    //   1236: invokestatic abs : (I)I
    //   1239: invokevirtual charAt : (I)C
    //   1242: invokevirtual append : (C)Ljava/lang/StringBuilder;
    //   1245: pop
    //   1246: iload_2
    //   1247: ifeq -> 1364
    //   1250: goto -> 1257
    //   1253: invokestatic a : (Ljava/lang/Throwable;)Ljava/lang/Throwable;
    //   1256: athrow
    //   1257: aload_3
    //   1258: getstatic burp/Zsyu.ZJ : Ljava/lang/String;
    //   1261: getstatic burp/Zd0.ZT : Ljava/lang/Object;
    //   1264: checkcast java/math/BigInteger
    //   1267: invokevirtual intValue : ()I
    //   1270: bipush #32
    //   1272: irem
    //   1273: invokestatic abs : (I)I
    //   1276: invokevirtual charAt : (I)C
    //   1279: invokevirtual append : (C)Ljava/lang/StringBuilder;
    //   1282: pop
    //   1283: iload_2
    //   1284: ifeq -> 1364
    //   1287: goto -> 1294
    //   1290: invokestatic a : (Ljava/lang/Throwable;)Ljava/lang/Throwable;
    //   1293: athrow
    //   1294: aload_3
    //   1295: getstatic burp/Zsqi.Zs : Ljava/lang/String;
    //   1298: getstatic burp/Zex5.Zb : Ljava/lang/Object;
    //   1301: checkcast java/math/BigInteger
    //   1304: invokevirtual intValue : ()I
    //   1307: bipush #32
    //   1309: irem
    //   1310: invokestatic abs : (I)I
    //   1313: invokevirtual charAt : (I)C
    //   1316: invokevirtual append : (C)Ljava/lang/StringBuilder;
    //   1319: pop
    //   1320: iload_2
    //   1321: ifeq -> 1364
    //   1324: goto -> 1331
    //   1327: invokestatic a : (Ljava/lang/Throwable;)Ljava/lang/Throwable;
    //   1330: athrow
    //   1331: aload_3
    //   1332: getstatic burp/Zgde.Zr : Ljava/lang/String;
    //   1335: getstatic burp/Zec_.ZN : Ljava/lang/Object;
    //   1338: checkcast java/math/BigInteger
    //   1341: invokevirtual intValue : ()I
    //   1344: bipush #32
    //   1346: irem
    //   1347: invokestatic abs : (I)I
    //   1350: invokevirtual charAt : (I)C
    //   1353: invokevirtual append : (C)Ljava/lang/StringBuilder;
    //   1356: pop
    //   1357: goto -> 1364
    //   1360: invokestatic a : (Ljava/lang/Throwable;)Ljava/lang/Throwable;
    //   1363: athrow
    //   1364: iinc #4, 1
    //   1367: iload_2
    //   1368: ifeq -> 33
    //   1371: aload_3
    //   1372: invokevirtual toString : ()Ljava/lang/String;
    //   1375: putstatic burp/Zm81.ZY : Ljava/lang/String;
    //   1378: getstatic burp/Zkff.Zr : Ljava/lang/Object;
    //   1381: checkcast java/math/BigInteger
    //   1384: invokevirtual toByteArray : ()[B
    //   1387: astore #4
    //   1389: bipush #32
    //   1391: newarray int
    //   1393: dup
    //   1394: iconst_0
    //   1395: ldc 943331329
    //   1397: iastore
    //   1398: dup
    //   1399: iconst_1
    //   1400: ldc 170788368
    //   1402: iastore
    //   1403: dup
    //   1404: iconst_2
    //   1405: ldc 1008414755
    //   1407: iastore
    //   1408: dup
    //   1409: iconst_3
    //   1410: ldc 187049985
    //   1412: iastore
    //   1413: dup
    //   1414: iconst_4
    //   1415: ldc 1010368540
    //   1417: iastore
    //   1418: dup
    //   1419: iconst_5
    //   1420: ldc 220604441
    //   1422: iastore
    //   1423: dup
    //   1424: bipush #6
    //   1426: ldc 940377620
    //   1428: iastore
    //   1429: dup
    //   1430: bipush #7
    //   1432: ldc 255209728
    //   1434: iastore
    //   1435: dup
    //   1436: bipush #8
    //   1438: ldc 689771012
    //   1440: iastore
    //   1441: dup
    //   1442: bipush #9
    //   1444: ldc 221709344
    //   1446: iastore
    //   1447: dup
    //   1448: bipush #10
    //   1450: ldc 957157408
    //   1452: iastore
    //   1453: dup
    //   1454: bipush #11
    //   1456: ldc 892536332
    //   1458: iastore
    //   1459: dup
    //   1460: bipush #12
    //   1462: ldc 722417666
    //   1464: iastore
    //   1465: dup
    //   1466: bipush #13
    //   1468: ldc 1026621720
    //   1470: iastore
    //   1471: dup
    //   1472: bipush #14
    //   1474: ldc 655302664
    //   1476: iastore
    //   1477: dup
    //   1478: bipush #15
    //   1480: ldc 890966315
    //   1482: iastore
    //   1483: dup
    //   1484: bipush #16
    //   1486: ldc 187632156
    //   1488: iastore
    //   1489: dup
    //   1490: bipush #17
    //   1492: ldc 874189824
    //   1494: iastore
    //   1495: dup
    //   1496: bipush #18
    //   1498: ldc 254150144
    //   1500: iastore
    //   1501: dup
    //   1502: bipush #19
    //   1504: ldc 924386310
    //   1506: iastore
    //   1507: dup
    //   1508: bipush #20
    //   1510: ldc 121057538
    //   1512: iastore
    //   1513: dup
    //   1514: bipush #21
    //   1516: ldc 840500228
    //   1518: iastore
    //   1519: dup
    //   1520: bipush #22
    //   1522: ldc 389160971
    //   1524: iastore
    //   1525: dup
    //   1526: bipush #23
    //   1528: ldc 907870729
    //   1530: iastore
    //   1531: dup
    //   1532: bipush #24
    //   1534: ldc 389426184
    //   1536: iastore
    //   1537: dup
    //   1538: bipush #25
    //   1540: ldc 973875457
    //   1542: iastore
    //   1543: dup
    //   1544: bipush #26
    //   1546: ldc 372376604
    //   1548: iastore
    //   1549: dup
    //   1550: bipush #27
    //   1552: ldc 707731490
    //   1554: iastore
    //   1555: dup
    //   1556: bipush #28
    //   1558: ldc 1043334948
    //   1560: iastore
    //   1561: dup
    //   1562: bipush #29
    //   1564: ldc 439222784
    //   1566: iastore
    //   1567: dup
    //   1568: bipush #30
    //   1570: ldc 876216579
    //   1572: iastore
    //   1573: dup
    //   1574: bipush #31
    //   1576: ldc 455999525
    //   1578: iastore
    //   1579: astore #6
    //   1581: bipush #8
    //   1583: aload #4
    //   1585: arraylength
    //   1586: bipush #8
    //   1588: irem
    //   1589: isub
    //   1590: istore #7
    //   1592: aload #4
    //   1594: arraylength
    //   1595: iload #7
    //   1597: iadd
    //   1598: newarray byte
    //   1600: astore #8
    //   1602: iconst_0
    //   1603: istore #9
    //   1605: iload #9
    //   1607: aload #4
    //   1609: arraylength
    //   1610: if_icmpge -> 1630
    //   1613: aload #8
    //   1615: iload #9
    //   1617: aload #4
    //   1619: iload #9
    //   1621: baload
    //   1622: bastore
    //   1623: iinc #9, 1
    //   1626: iload_2
    //   1627: ifeq -> 1605
    //   1630: aload #4
    //   1632: arraylength
    //   1633: istore #9
    //   1635: iload #9
    //   1637: aload #8
    //   1639: arraylength
    //   1640: if_icmpge -> 1658
    //   1643: aload #8
    //   1645: iload #9
    //   1647: iload #7
    //   1649: i2b
    //   1650: bastore
    //   1651: iinc #9, 1
    //   1654: iload_2
    //   1655: ifeq -> 1635
    //   1658: aload #8
    //   1660: astore #4
    //   1662: bipush #64
    //   1664: newarray int
    //   1666: dup
    //   1667: iconst_0
    //   1668: ldc 16843776
    //   1670: iastore
    //   1671: dup
    //   1672: iconst_1
    //   1673: iconst_0
    //   1674: iastore
    //   1675: dup
    //   1676: iconst_2
    //   1677: ldc 65536
    //   1679: iastore
    //   1680: dup
    //   1681: iconst_3
    //   1682: ldc 16843780
    //   1684: iastore
    //   1685: dup
    //   1686: iconst_4
    //   1687: ldc 16842756
    //   1689: iastore
    //   1690: dup
    //   1691: iconst_5
    //   1692: ldc 66564
    //   1694: iastore
    //   1695: dup
    //   1696: bipush #6
    //   1698: iconst_4
    //   1699: iastore
    //   1700: dup
    //   1701: bipush #7
    //   1703: ldc 65536
    //   1705: iastore
    //   1706: dup
    //   1707: bipush #8
    //   1709: sipush #1024
    //   1712: iastore
    //   1713: dup
    //   1714: bipush #9
    //   1716: ldc 16843776
    //   1718: iastore
    //   1719: dup
    //   1720: bipush #10
    //   1722: ldc 16843780
    //   1724: iastore
    //   1725: dup
    //   1726: bipush #11
    //   1728: sipush #1024
    //   1731: iastore
    //   1732: dup
    //   1733: bipush #12
    //   1735: ldc 16778244
    //   1737: iastore
    //   1738: dup
    //   1739: bipush #13
    //   1741: ldc 16842756
    //   1743: iastore
    //   1744: dup
    //   1745: bipush #14
    //   1747: ldc 16777216
    //   1749: iastore
    //   1750: dup
    //   1751: bipush #15
    //   1753: iconst_4
    //   1754: iastore
    //   1755: dup
    //   1756: bipush #16
    //   1758: sipush #1028
    //   1761: iastore
    //   1762: dup
    //   1763: bipush #17
    //   1765: ldc 16778240
    //   1767: iastore
    //   1768: dup
    //   1769: bipush #18
    //   1771: ldc 16778240
    //   1773: iastore
    //   1774: dup
    //   1775: bipush #19
    //   1777: ldc 66560
    //   1779: iastore
    //   1780: dup
    //   1781: bipush #20
    //   1783: ldc 66560
    //   1785: iastore
    //   1786: dup
    //   1787: bipush #21
    //   1789: ldc 16842752
    //   1791: iastore
    //   1792: dup
    //   1793: bipush #22
    //   1795: ldc 16842752
    //   1797: iastore
    //   1798: dup
    //   1799: bipush #23
    //   1801: ldc 16778244
    //   1803: iastore
    //   1804: dup
    //   1805: bipush #24
    //   1807: ldc 65540
    //   1809: iastore
    //   1810: dup
    //   1811: bipush #25
    //   1813: ldc 16777220
    //   1815: iastore
    //   1816: dup
    //   1817: bipush #26
    //   1819: ldc 16777220
    //   1821: iastore
    //   1822: dup
    //   1823: bipush #27
    //   1825: ldc 65540
    //   1827: iastore
    //   1828: dup
    //   1829: bipush #28
    //   1831: iconst_0
    //   1832: iastore
    //   1833: dup
    //   1834: bipush #29
    //   1836: sipush #1028
    //   1839: iastore
    //   1840: dup
    //   1841: bipush #30
    //   1843: ldc 66564
    //   1845: iastore
    //   1846: dup
    //   1847: bipush #31
    //   1849: ldc 16777216
    //   1851: iastore
    //   1852: dup
    //   1853: bipush #32
    //   1855: ldc 65536
    //   1857: iastore
    //   1858: dup
    //   1859: bipush #33
    //   1861: ldc 16843780
    //   1863: iastore
    //   1864: dup
    //   1865: bipush #34
    //   1867: iconst_4
    //   1868: iastore
    //   1869: dup
    //   1870: bipush #35
    //   1872: ldc 16842752
    //   1874: iastore
    //   1875: dup
    //   1876: bipush #36
    //   1878: ldc 16843776
    //   1880: iastore
    //   1881: dup
    //   1882: bipush #37
    //   1884: ldc 16777216
    //   1886: iastore
    //   1887: dup
    //   1888: bipush #38
    //   1890: ldc 16777216
    //   1892: iastore
    //   1893: dup
    //   1894: bipush #39
    //   1896: sipush #1024
    //   1899: iastore
    //   1900: dup
    //   1901: bipush #40
    //   1903: ldc 16842756
    //   1905: iastore
    //   1906: dup
    //   1907: bipush #41
    //   1909: ldc 65536
    //   1911: iastore
    //   1912: dup
    //   1913: bipush #42
    //   1915: ldc 66560
    //   1917: iastore
    //   1918: dup
    //   1919: bipush #43
    //   1921: ldc 16777220
    //   1923: iastore
    //   1924: dup
    //   1925: bipush #44
    //   1927: sipush #1024
    //   1930: iastore
    //   1931: dup
    //   1932: bipush #45
    //   1934: iconst_4
    //   1935: iastore
    //   1936: dup
    //   1937: bipush #46
    //   1939: ldc 16778244
    //   1941: iastore
    //   1942: dup
    //   1943: bipush #47
    //   1945: ldc 66564
    //   1947: iastore
    //   1948: dup
    //   1949: bipush #48
    //   1951: ldc 16843780
    //   1953: iastore
    //   1954: dup
    //   1955: bipush #49
    //   1957: ldc 65540
    //   1959: iastore
    //   1960: dup
    //   1961: bipush #50
    //   1963: ldc 16842752
    //   1965: iastore
    //   1966: dup
    //   1967: bipush #51
    //   1969: ldc 16778244
    //   1971: iastore
    //   1972: dup
    //   1973: bipush #52
    //   1975: ldc 16777220
    //   1977: iastore
    //   1978: dup
    //   1979: bipush #53
    //   1981: sipush #1028
    //   1984: iastore
    //   1985: dup
    //   1986: bipush #54
    //   1988: ldc 66564
    //   1990: iastore
    //   1991: dup
    //   1992: bipush #55
    //   1994: ldc 16843776
    //   1996: iastore
    //   1997: dup
    //   1998: bipush #56
    //   2000: sipush #1028
    //   2003: iastore
    //   2004: dup
    //   2005: bipush #57
    //   2007: ldc 16778240
    //   2009: iastore
    //   2010: dup
    //   2011: bipush #58
    //   2013: ldc 16778240
    //   2015: iastore
    //   2016: dup
    //   2017: bipush #59
    //   2019: iconst_0
    //   2020: iastore
    //   2021: dup
    //   2022: bipush #60
    //   2024: ldc 65540
    //   2026: iastore
    //   2027: dup
    //   2028: bipush #61
    //   2030: ldc 66560
    //   2032: iastore
    //   2033: dup
    //   2034: bipush #62
    //   2036: iconst_0
    //   2037: iastore
    //   2038: dup
    //   2039: bipush #63
    //   2041: ldc 16842756
    //   2043: iastore
    //   2044: astore #9
    //   2046: bipush #64
    //   2048: newarray int
    //   2050: dup
    //   2051: iconst_0
    //   2052: ldc -2146402272
    //   2054: iastore
    //   2055: dup
    //   2056: iconst_1
    //   2057: ldc -2147450880
    //   2059: iastore
    //   2060: dup
    //   2061: iconst_2
    //   2062: ldc 32768
    //   2064: iastore
    //   2065: dup
    //   2066: iconst_3
    //   2067: ldc 1081376
    //   2069: iastore
    //   2070: dup
    //   2071: iconst_4
    //   2072: ldc 1048576
    //   2074: iastore
    //   2075: dup
    //   2076: iconst_5
    //   2077: bipush #32
    //   2079: iastore
    //   2080: dup
    //   2081: bipush #6
    //   2083: ldc -2146435040
    //   2085: iastore
    //   2086: dup
    //   2087: bipush #7
    //   2089: ldc -2147450848
    //   2091: iastore
    //   2092: dup
    //   2093: bipush #8
    //   2095: ldc -2147483616
    //   2097: iastore
    //   2098: dup
    //   2099: bipush #9
    //   2101: ldc -2146402272
    //   2103: iastore
    //   2104: dup
    //   2105: bipush #10
    //   2107: ldc -2146402304
    //   2109: iastore
    //   2110: dup
    //   2111: bipush #11
    //   2113: ldc -2147483648
    //   2115: iastore
    //   2116: dup
    //   2117: bipush #12
    //   2119: ldc -2147450880
    //   2121: iastore
    //   2122: dup
    //   2123: bipush #13
    //   2125: ldc 1048576
    //   2127: iastore
    //   2128: dup
    //   2129: bipush #14
    //   2131: bipush #32
    //   2133: iastore
    //   2134: dup
    //   2135: bipush #15
    //   2137: ldc -2146435040
    //   2139: iastore
    //   2140: dup
    //   2141: bipush #16
    //   2143: ldc 1081344
    //   2145: iastore
    //   2146: dup
    //   2147: bipush #17
    //   2149: ldc 1048608
    //   2151: iastore
    //   2152: dup
    //   2153: bipush #18
    //   2155: ldc -2147450848
    //   2157: iastore
    //   2158: dup
    //   2159: bipush #19
    //   2161: iconst_0
    //   2162: iastore
    //   2163: dup
    //   2164: bipush #20
    //   2166: ldc -2147483648
    //   2168: iastore
    //   2169: dup
    //   2170: bipush #21
    //   2172: ldc 32768
    //   2174: iastore
    //   2175: dup
    //   2176: bipush #22
    //   2178: ldc 1081376
    //   2180: iastore
    //   2181: dup
    //   2182: bipush #23
    //   2184: ldc -2146435072
    //   2186: iastore
    //   2187: dup
    //   2188: bipush #24
    //   2190: ldc 1048608
    //   2192: iastore
    //   2193: dup
    //   2194: bipush #25
    //   2196: ldc -2147483616
    //   2198: iastore
    //   2199: dup
    //   2200: bipush #26
    //   2202: iconst_0
    //   2203: iastore
    //   2204: dup
    //   2205: bipush #27
    //   2207: ldc 1081344
    //   2209: iastore
    //   2210: dup
    //   2211: bipush #28
    //   2213: ldc 32800
    //   2215: iastore
    //   2216: dup
    //   2217: bipush #29
    //   2219: ldc -2146402304
    //   2221: iastore
    //   2222: dup
    //   2223: bipush #30
    //   2225: ldc -2146435072
    //   2227: iastore
    //   2228: dup
    //   2229: bipush #31
    //   2231: ldc 32800
    //   2233: iastore
    //   2234: dup
    //   2235: bipush #32
    //   2237: iconst_0
    //   2238: iastore
    //   2239: dup
    //   2240: bipush #33
    //   2242: ldc 1081376
    //   2244: iastore
    //   2245: dup
    //   2246: bipush #34
    //   2248: ldc -2146435040
    //   2250: iastore
    //   2251: dup
    //   2252: bipush #35
    //   2254: ldc 1048576
    //   2256: iastore
    //   2257: dup
    //   2258: bipush #36
    //   2260: ldc -2147450848
    //   2262: iastore
    //   2263: dup
    //   2264: bipush #37
    //   2266: ldc -2146435072
    //   2268: iastore
    //   2269: dup
    //   2270: bipush #38
    //   2272: ldc -2146402304
    //   2274: iastore
    //   2275: dup
    //   2276: bipush #39
    //   2278: ldc 32768
    //   2280: iastore
    //   2281: dup
    //   2282: bipush #40
    //   2284: ldc -2146435072
    //   2286: iastore
    //   2287: dup
    //   2288: bipush #41
    //   2290: ldc -2147450880
    //   2292: iastore
    //   2293: dup
    //   2294: bipush #42
    //   2296: bipush #32
    //   2298: iastore
    //   2299: dup
    //   2300: bipush #43
    //   2302: ldc -2146402272
    //   2304: iastore
    //   2305: dup
    //   2306: bipush #44
    //   2308: ldc 1081376
    //   2310: iastore
    //   2311: dup
    //   2312: bipush #45
    //   2314: bipush #32
    //   2316: iastore
    //   2317: dup
    //   2318: bipush #46
    //   2320: ldc 32768
    //   2322: iastore
    //   2323: dup
    //   2324: bipush #47
    //   2326: ldc -2147483648
    //   2328: iastore
    //   2329: dup
    //   2330: bipush #48
    //   2332: ldc 32800
    //   2334: iastore
    //   2335: dup
    //   2336: bipush #49
    //   2338: ldc -2146402304
    //   2340: iastore
    //   2341: dup
    //   2342: bipush #50
    //   2344: ldc 1048576
    //   2346: iastore
    //   2347: dup
    //   2348: bipush #51
    //   2350: ldc -2147483616
    //   2352: iastore
    //   2353: dup
    //   2354: bipush #52
    //   2356: ldc 1048608
    //   2358: iastore
    //   2359: dup
    //   2360: bipush #53
    //   2362: ldc -2147450848
    //   2364: iastore
    //   2365: dup
    //   2366: bipush #54
    //   2368: ldc -2147483616
    //   2370: iastore
    //   2371: dup
    //   2372: bipush #55
    //   2374: ldc 1048608
    //   2376: iastore
    //   2377: dup
    //   2378: bipush #56
    //   2380: ldc 1081344
    //   2382: iastore
    //   2383: dup
    //   2384: bipush #57
    //   2386: iconst_0
    //   2387: iastore
    //   2388: dup
    //   2389: bipush #58
    //   2391: ldc -2147450880
    //   2393: iastore
    //   2394: dup
    //   2395: bipush #59
    //   2397: ldc 32800
    //   2399: iastore
    //   2400: dup
    //   2401: bipush #60
    //   2403: ldc -2147483648
    //   2405: iastore
    //   2406: dup
    //   2407: bipush #61
    //   2409: ldc -2146435040
    //   2411: iastore
    //   2412: dup
    //   2413: bipush #62
    //   2415: ldc -2146402272
    //   2417: iastore
    //   2418: dup
    //   2419: bipush #63
    //   2421: ldc 1081344
    //   2423: iastore
    //   2424: astore #10
    //   2426: bipush #64
    //   2428: newarray int
    //   2430: dup
    //   2431: iconst_0
    //   2432: sipush #520
    //   2435: iastore
    //   2436: dup
    //   2437: iconst_1
    //   2438: ldc 134349312
    //   2440: iastore
    //   2441: dup
    //   2442: iconst_2
    //   2443: iconst_0
    //   2444: iastore
    //   2445: dup
    //   2446: iconst_3
    //   2447: ldc 134348808
    //   2449: iastore
    //   2450: dup
    //   2451: iconst_4
    //   2452: ldc 134218240
    //   2454: iastore
    //   2455: dup
    //   2456: iconst_5
    //   2457: iconst_0
    //   2458: iastore
    //   2459: dup
    //   2460: bipush #6
    //   2462: ldc 131592
    //   2464: iastore
    //   2465: dup
    //   2466: bipush #7
    //   2468: ldc 134218240
    //   2470: iastore
    //   2471: dup
    //   2472: bipush #8
    //   2474: ldc 131080
    //   2476: iastore
    //   2477: dup
    //   2478: bipush #9
    //   2480: ldc 134217736
    //   2482: iastore
    //   2483: dup
    //   2484: bipush #10
    //   2486: ldc 134217736
    //   2488: iastore
    //   2489: dup
    //   2490: bipush #11
    //   2492: ldc 131072
    //   2494: iastore
    //   2495: dup
    //   2496: bipush #12
    //   2498: ldc 134349320
    //   2500: iastore
    //   2501: dup
    //   2502: bipush #13
    //   2504: ldc 131080
    //   2506: iastore
    //   2507: dup
    //   2508: bipush #14
    //   2510: ldc 134348800
    //   2512: iastore
    //   2513: dup
    //   2514: bipush #15
    //   2516: sipush #520
    //   2519: iastore
    //   2520: dup
    //   2521: bipush #16
    //   2523: ldc 134217728
    //   2525: iastore
    //   2526: dup
    //   2527: bipush #17
    //   2529: bipush #8
    //   2531: iastore
    //   2532: dup
    //   2533: bipush #18
    //   2535: ldc 134349312
    //   2537: iastore
    //   2538: dup
    //   2539: bipush #19
    //   2541: sipush #512
    //   2544: iastore
    //   2545: dup
    //   2546: bipush #20
    //   2548: ldc 131584
    //   2550: iastore
    //   2551: dup
    //   2552: bipush #21
    //   2554: ldc 134348800
    //   2556: iastore
    //   2557: dup
    //   2558: bipush #22
    //   2560: ldc 134348808
    //   2562: iastore
    //   2563: dup
    //   2564: bipush #23
    //   2566: ldc 131592
    //   2568: iastore
    //   2569: dup
    //   2570: bipush #24
    //   2572: ldc 134218248
    //   2574: iastore
    //   2575: dup
    //   2576: bipush #25
    //   2578: ldc 131584
    //   2580: iastore
    //   2581: dup
    //   2582: bipush #26
    //   2584: ldc 131072
    //   2586: iastore
    //   2587: dup
    //   2588: bipush #27
    //   2590: ldc 134218248
    //   2592: iastore
    //   2593: dup
    //   2594: bipush #28
    //   2596: bipush #8
    //   2598: iastore
    //   2599: dup
    //   2600: bipush #29
    //   2602: ldc 134349320
    //   2604: iastore
    //   2605: dup
    //   2606: bipush #30
    //   2608: sipush #512
    //   2611: iastore
    //   2612: dup
    //   2613: bipush #31
    //   2615: ldc 134217728
    //   2617: iastore
    //   2618: dup
    //   2619: bipush #32
    //   2621: ldc 134349312
    //   2623: iastore
    //   2624: dup
    //   2625: bipush #33
    //   2627: ldc 134217728
    //   2629: iastore
    //   2630: dup
    //   2631: bipush #34
    //   2633: ldc 131080
    //   2635: iastore
    //   2636: dup
    //   2637: bipush #35
    //   2639: sipush #520
    //   2642: iastore
    //   2643: dup
    //   2644: bipush #36
    //   2646: ldc 131072
    //   2648: iastore
    //   2649: dup
    //   2650: bipush #37
    //   2652: ldc 134349312
    //   2654: iastore
    //   2655: dup
    //   2656: bipush #38
    //   2658: ldc 134218240
    //   2660: iastore
    //   2661: dup
    //   2662: bipush #39
    //   2664: iconst_0
    //   2665: iastore
    //   2666: dup
    //   2667: bipush #40
    //   2669: sipush #512
    //   2672: iastore
    //   2673: dup
    //   2674: bipush #41
    //   2676: ldc 131080
    //   2678: iastore
    //   2679: dup
    //   2680: bipush #42
    //   2682: ldc 134349320
    //   2684: iastore
    //   2685: dup
    //   2686: bipush #43
    //   2688: ldc 134218240
    //   2690: iastore
    //   2691: dup
    //   2692: bipush #44
    //   2694: ldc 134217736
    //   2696: iastore
    //   2697: dup
    //   2698: bipush #45
    //   2700: sipush #512
    //   2703: iastore
    //   2704: dup
    //   2705: bipush #46
    //   2707: iconst_0
    //   2708: iastore
    //   2709: dup
    //   2710: bipush #47
    //   2712: ldc 134348808
    //   2714: iastore
    //   2715: dup
    //   2716: bipush #48
    //   2718: ldc 134218248
    //   2720: iastore
    //   2721: dup
    //   2722: bipush #49
    //   2724: ldc 131072
    //   2726: iastore
    //   2727: dup
    //   2728: bipush #50
    //   2730: ldc 134217728
    //   2732: iastore
    //   2733: dup
    //   2734: bipush #51
    //   2736: ldc 134349320
    //   2738: iastore
    //   2739: dup
    //   2740: bipush #52
    //   2742: bipush #8
    //   2744: iastore
    //   2745: dup
    //   2746: bipush #53
    //   2748: ldc 131592
    //   2750: iastore
    //   2751: dup
    //   2752: bipush #54
    //   2754: ldc 131584
    //   2756: iastore
    //   2757: dup
    //   2758: bipush #55
    //   2760: ldc 134217736
    //   2762: iastore
    //   2763: dup
    //   2764: bipush #56
    //   2766: ldc 134348800
    //   2768: iastore
    //   2769: dup
    //   2770: bipush #57
    //   2772: ldc 134218248
    //   2774: iastore
    //   2775: dup
    //   2776: bipush #58
    //   2778: sipush #520
    //   2781: iastore
    //   2782: dup
    //   2783: bipush #59
    //   2785: ldc 134348800
    //   2787: iastore
    //   2788: dup
    //   2789: bipush #60
    //   2791: ldc 131592
    //   2793: iastore
    //   2794: dup
    //   2795: bipush #61
    //   2797: bipush #8
    //   2799: iastore
    //   2800: dup
    //   2801: bipush #62
    //   2803: ldc 134348808
    //   2805: iastore
    //   2806: dup
    //   2807: bipush #63
    //   2809: ldc 131584
    //   2811: iastore
    //   2812: astore #11
    //   2814: bipush #64
    //   2816: newarray int
    //   2818: dup
    //   2819: iconst_0
    //   2820: ldc 8396801
    //   2822: iastore
    //   2823: dup
    //   2824: iconst_1
    //   2825: sipush #8321
    //   2828: iastore
    //   2829: dup
    //   2830: iconst_2
    //   2831: sipush #8321
    //   2834: iastore
    //   2835: dup
    //   2836: iconst_3
    //   2837: sipush #128
    //   2840: iastore
    //   2841: dup
    //   2842: iconst_4
    //   2843: ldc 8396928
    //   2845: iastore
    //   2846: dup
    //   2847: iconst_5
    //   2848: ldc 8388737
    //   2850: iastore
    //   2851: dup
    //   2852: bipush #6
    //   2854: ldc 8388609
    //   2856: iastore
    //   2857: dup
    //   2858: bipush #7
    //   2860: sipush #8193
    //   2863: iastore
    //   2864: dup
    //   2865: bipush #8
    //   2867: iconst_0
    //   2868: iastore
    //   2869: dup
    //   2870: bipush #9
    //   2872: ldc 8396800
    //   2874: iastore
    //   2875: dup
    //   2876: bipush #10
    //   2878: ldc 8396800
    //   2880: iastore
    //   2881: dup
    //   2882: bipush #11
    //   2884: ldc 8396929
    //   2886: iastore
    //   2887: dup
    //   2888: bipush #12
    //   2890: sipush #129
    //   2893: iastore
    //   2894: dup
    //   2895: bipush #13
    //   2897: iconst_0
    //   2898: iastore
    //   2899: dup
    //   2900: bipush #14
    //   2902: ldc 8388736
    //   2904: iastore
    //   2905: dup
    //   2906: bipush #15
    //   2908: ldc 8388609
    //   2910: iastore
    //   2911: dup
    //   2912: bipush #16
    //   2914: iconst_1
    //   2915: iastore
    //   2916: dup
    //   2917: bipush #17
    //   2919: sipush #8192
    //   2922: iastore
    //   2923: dup
    //   2924: bipush #18
    //   2926: ldc 8388608
    //   2928: iastore
    //   2929: dup
    //   2930: bipush #19
    //   2932: ldc 8396801
    //   2934: iastore
    //   2935: dup
    //   2936: bipush #20
    //   2938: sipush #128
    //   2941: iastore
    //   2942: dup
    //   2943: bipush #21
    //   2945: ldc 8388608
    //   2947: iastore
    //   2948: dup
    //   2949: bipush #22
    //   2951: sipush #8193
    //   2954: iastore
    //   2955: dup
    //   2956: bipush #23
    //   2958: sipush #8320
    //   2961: iastore
    //   2962: dup
    //   2963: bipush #24
    //   2965: ldc 8388737
    //   2967: iastore
    //   2968: dup
    //   2969: bipush #25
    //   2971: iconst_1
    //   2972: iastore
    //   2973: dup
    //   2974: bipush #26
    //   2976: sipush #8320
    //   2979: iastore
    //   2980: dup
    //   2981: bipush #27
    //   2983: ldc 8388736
    //   2985: iastore
    //   2986: dup
    //   2987: bipush #28
    //   2989: sipush #8192
    //   2992: iastore
    //   2993: dup
    //   2994: bipush #29
    //   2996: ldc 8396928
    //   2998: iastore
    //   2999: dup
    //   3000: bipush #30
    //   3002: ldc 8396929
    //   3004: iastore
    //   3005: dup
    //   3006: bipush #31
    //   3008: sipush #129
    //   3011: iastore
    //   3012: dup
    //   3013: bipush #32
    //   3015: ldc 8388736
    //   3017: iastore
    //   3018: dup
    //   3019: bipush #33
    //   3021: ldc 8388609
    //   3023: iastore
    //   3024: dup
    //   3025: bipush #34
    //   3027: ldc 8396800
    //   3029: iastore
    //   3030: dup
    //   3031: bipush #35
    //   3033: ldc 8396929
    //   3035: iastore
    //   3036: dup
    //   3037: bipush #36
    //   3039: sipush #129
    //   3042: iastore
    //   3043: dup
    //   3044: bipush #37
    //   3046: iconst_0
    //   3047: iastore
    //   3048: dup
    //   3049: bipush #38
    //   3051: iconst_0
    //   3052: iastore
    //   3053: dup
    //   3054: bipush #39
    //   3056: ldc 8396800
    //   3058: iastore
    //   3059: dup
    //   3060: bipush #40
    //   3062: sipush #8320
    //   3065: iastore
    //   3066: dup
    //   3067: bipush #41
    //   3069: ldc 8388736
    //   3071: iastore
    //   3072: dup
    //   3073: bipush #42
    //   3075: ldc 8388737
    //   3077: iastore
    //   3078: dup
    //   3079: bipush #43
    //   3081: iconst_1
    //   3082: iastore
    //   3083: dup
    //   3084: bipush #44
    //   3086: ldc 8396801
    //   3088: iastore
    //   3089: dup
    //   3090: bipush #45
    //   3092: sipush #8321
    //   3095: iastore
    //   3096: dup
    //   3097: bipush #46
    //   3099: sipush #8321
    //   3102: iastore
    //   3103: dup
    //   3104: bipush #47
    //   3106: sipush #128
    //   3109: iastore
    //   3110: dup
    //   3111: bipush #48
    //   3113: ldc 8396929
    //   3115: iastore
    //   3116: dup
    //   3117: bipush #49
    //   3119: sipush #129
    //   3122: iastore
    //   3123: dup
    //   3124: bipush #50
    //   3126: iconst_1
    //   3127: iastore
    //   3128: dup
    //   3129: bipush #51
    //   3131: sipush #8192
    //   3134: iastore
    //   3135: dup
    //   3136: bipush #52
    //   3138: ldc 8388609
    //   3140: iastore
    //   3141: dup
    //   3142: bipush #53
    //   3144: sipush #8193
    //   3147: iastore
    //   3148: dup
    //   3149: bipush #54
    //   3151: ldc 8396928
    //   3153: iastore
    //   3154: dup
    //   3155: bipush #55
    //   3157: ldc 8388737
    //   3159: iastore
    //   3160: dup
    //   3161: bipush #56
    //   3163: sipush #8193
    //   3166: iastore
    //   3167: dup
    //   3168: bipush #57
    //   3170: sipush #8320
    //   3173: iastore
    //   3174: dup
    //   3175: bipush #58
    //   3177: ldc 8388608
    //   3179: iastore
    //   3180: dup
    //   3181: bipush #59
    //   3183: ldc 8396801
    //   3185: iastore
    //   3186: dup
    //   3187: bipush #60
    //   3189: sipush #128
    //   3192: iastore
    //   3193: dup
    //   3194: bipush #61
    //   3196: ldc 8388608
    //   3198: iastore
    //   3199: dup
    //   3200: bipush #62
    //   3202: sipush #8192
    //   3205: iastore
    //   3206: dup
    //   3207: bipush #63
    //   3209: ldc 8396928
    //   3211: iastore
    //   3212: astore #12
    //   3214: bipush #64
    //   3216: newarray int
    //   3218: dup
    //   3219: iconst_0
    //   3220: sipush #256
    //   3223: iastore
    //   3224: dup
    //   3225: iconst_1
    //   3226: ldc 34078976
    //   3228: iastore
    //   3229: dup
    //   3230: iconst_2
    //   3231: ldc 34078720
    //   3233: iastore
    //   3234: dup
    //   3235: iconst_3
    //   3236: ldc 1107296512
    //   3238: iastore
    //   3239: dup
    //   3240: iconst_4
    //   3241: ldc 524288
    //   3243: iastore
    //   3244: dup
    //   3245: iconst_5
    //   3246: sipush #256
    //   3249: iastore
    //   3250: dup
    //   3251: bipush #6
    //   3253: ldc 1073741824
    //   3255: iastore
    //   3256: dup
    //   3257: bipush #7
    //   3259: ldc 34078720
    //   3261: iastore
    //   3262: dup
    //   3263: bipush #8
    //   3265: ldc 1074266368
    //   3267: iastore
    //   3268: dup
    //   3269: bipush #9
    //   3271: ldc 524288
    //   3273: iastore
    //   3274: dup
    //   3275: bipush #10
    //   3277: ldc 33554688
    //   3279: iastore
    //   3280: dup
    //   3281: bipush #11
    //   3283: ldc 1074266368
    //   3285: iastore
    //   3286: dup
    //   3287: bipush #12
    //   3289: ldc 1107296512
    //   3291: iastore
    //   3292: dup
    //   3293: bipush #13
    //   3295: ldc 1107820544
    //   3297: iastore
    //   3298: dup
    //   3299: bipush #14
    //   3301: ldc 524544
    //   3303: iastore
    //   3304: dup
    //   3305: bipush #15
    //   3307: ldc 1073741824
    //   3309: iastore
    //   3310: dup
    //   3311: bipush #16
    //   3313: ldc 33554432
    //   3315: iastore
    //   3316: dup
    //   3317: bipush #17
    //   3319: ldc 1074266112
    //   3321: iastore
    //   3322: dup
    //   3323: bipush #18
    //   3325: ldc 1074266112
    //   3327: iastore
    //   3328: dup
    //   3329: bipush #19
    //   3331: iconst_0
    //   3332: iastore
    //   3333: dup
    //   3334: bipush #20
    //   3336: ldc 1073742080
    //   3338: iastore
    //   3339: dup
    //   3340: bipush #21
    //   3342: ldc 1107820800
    //   3344: iastore
    //   3345: dup
    //   3346: bipush #22
    //   3348: ldc 1107820800
    //   3350: iastore
    //   3351: dup
    //   3352: bipush #23
    //   3354: ldc 33554688
    //   3356: iastore
    //   3357: dup
    //   3358: bipush #24
    //   3360: ldc 1107820544
    //   3362: iastore
    //   3363: dup
    //   3364: bipush #25
    //   3366: ldc 1073742080
    //   3368: iastore
    //   3369: dup
    //   3370: bipush #26
    //   3372: iconst_0
    //   3373: iastore
    //   3374: dup
    //   3375: bipush #27
    //   3377: ldc 1107296256
    //   3379: iastore
    //   3380: dup
    //   3381: bipush #28
    //   3383: ldc 34078976
    //   3385: iastore
    //   3386: dup
    //   3387: bipush #29
    //   3389: ldc 33554432
    //   3391: iastore
    //   3392: dup
    //   3393: bipush #30
    //   3395: ldc 1107296256
    //   3397: iastore
    //   3398: dup
    //   3399: bipush #31
    //   3401: ldc 524544
    //   3403: iastore
    //   3404: dup
    //   3405: bipush #32
    //   3407: ldc 524288
    //   3409: iastore
    //   3410: dup
    //   3411: bipush #33
    //   3413: ldc 1107296512
    //   3415: iastore
    //   3416: dup
    //   3417: bipush #34
    //   3419: sipush #256
    //   3422: iastore
    //   3423: dup
    //   3424: bipush #35
    //   3426: ldc 33554432
    //   3428: iastore
    //   3429: dup
    //   3430: bipush #36
    //   3432: ldc 1073741824
    //   3434: iastore
    //   3435: dup
    //   3436: bipush #37
    //   3438: ldc 34078720
    //   3440: iastore
    //   3441: dup
    //   3442: bipush #38
    //   3444: ldc 1107296512
    //   3446: iastore
    //   3447: dup
    //   3448: bipush #39
    //   3450: ldc 1074266368
    //   3452: iastore
    //   3453: dup
    //   3454: bipush #40
    //   3456: ldc 33554688
    //   3458: iastore
    //   3459: dup
    //   3460: bipush #41
    //   3462: ldc 1073741824
    //   3464: iastore
    //   3465: dup
    //   3466: bipush #42
    //   3468: ldc 1107820544
    //   3470: iastore
    //   3471: dup
    //   3472: bipush #43
    //   3474: ldc 34078976
    //   3476: iastore
    //   3477: dup
    //   3478: bipush #44
    //   3480: ldc 1074266368
    //   3482: iastore
    //   3483: dup
    //   3484: bipush #45
    //   3486: sipush #256
    //   3489: iastore
    //   3490: dup
    //   3491: bipush #46
    //   3493: ldc 33554432
    //   3495: iastore
    //   3496: dup
    //   3497: bipush #47
    //   3499: ldc 1107820544
    //   3501: iastore
    //   3502: dup
    //   3503: bipush #48
    //   3505: ldc 1107820800
    //   3507: iastore
    //   3508: dup
    //   3509: bipush #49
    //   3511: ldc 524544
    //   3513: iastore
    //   3514: dup
    //   3515: bipush #50
    //   3517: ldc 1107296256
    //   3519: iastore
    //   3520: dup
    //   3521: bipush #51
    //   3523: ldc 1107820800
    //   3525: iastore
    //   3526: dup
    //   3527: bipush #52
    //   3529: ldc 34078720
    //   3531: iastore
    //   3532: dup
    //   3533: bipush #53
    //   3535: iconst_0
    //   3536: iastore
    //   3537: dup
    //   3538: bipush #54
    //   3540: ldc 1074266112
    //   3542: iastore
    //   3543: dup
    //   3544: bipush #55
    //   3546: ldc 1107296256
    //   3548: iastore
    //   3549: dup
    //   3550: bipush #56
    //   3552: ldc 524544
    //   3554: iastore
    //   3555: dup
    //   3556: bipush #57
    //   3558: ldc 33554688
    //   3560: iastore
    //   3561: dup
    //   3562: bipush #58
    //   3564: ldc 1073742080
    //   3566: iastore
    //   3567: dup
    //   3568: bipush #59
    //   3570: ldc 524288
    //   3572: iastore
    //   3573: dup
    //   3574: bipush #60
    //   3576: iconst_0
    //   3577: iastore
    //   3578: dup
    //   3579: bipush #61
    //   3581: ldc 1074266112
    //   3583: iastore
    //   3584: dup
    //   3585: bipush #62
    //   3587: ldc 34078976
    //   3589: iastore
    //   3590: dup
    //   3591: bipush #63
    //   3593: ldc 1073742080
    //   3595: iastore
    //   3596: astore #13
    //   3598: bipush #64
    //   3600: newarray int
    //   3602: dup
    //   3603: iconst_0
    //   3604: ldc 536870928
    //   3606: iastore
    //   3607: dup
    //   3608: iconst_1
    //   3609: ldc 541065216
    //   3611: iastore
    //   3612: dup
    //   3613: iconst_2
    //   3614: sipush #16384
    //   3617: iastore
    //   3618: dup
    //   3619: iconst_3
    //   3620: ldc 541081616
    //   3622: iastore
    //   3623: dup
    //   3624: iconst_4
    //   3625: ldc 541065216
    //   3627: iastore
    //   3628: dup
    //   3629: iconst_5
    //   3630: bipush #16
    //   3632: iastore
    //   3633: dup
    //   3634: bipush #6
    //   3636: ldc 541081616
    //   3638: iastore
    //   3639: dup
    //   3640: bipush #7
    //   3642: ldc 4194304
    //   3644: iastore
    //   3645: dup
    //   3646: bipush #8
    //   3648: ldc 536887296
    //   3650: iastore
    //   3651: dup
    //   3652: bipush #9
    //   3654: ldc 4210704
    //   3656: iastore
    //   3657: dup
    //   3658: bipush #10
    //   3660: ldc 4194304
    //   3662: iastore
    //   3663: dup
    //   3664: bipush #11
    //   3666: ldc 536870928
    //   3668: iastore
    //   3669: dup
    //   3670: bipush #12
    //   3672: ldc 4194320
    //   3674: iastore
    //   3675: dup
    //   3676: bipush #13
    //   3678: ldc 536887296
    //   3680: iastore
    //   3681: dup
    //   3682: bipush #14
    //   3684: ldc 536870912
    //   3686: iastore
    //   3687: dup
    //   3688: bipush #15
    //   3690: sipush #16400
    //   3693: iastore
    //   3694: dup
    //   3695: bipush #16
    //   3697: iconst_0
    //   3698: iastore
    //   3699: dup
    //   3700: bipush #17
    //   3702: ldc 4194320
    //   3704: iastore
    //   3705: dup
    //   3706: bipush #18
    //   3708: ldc 536887312
    //   3710: iastore
    //   3711: dup
    //   3712: bipush #19
    //   3714: sipush #16384
    //   3717: iastore
    //   3718: dup
    //   3719: bipush #20
    //   3721: ldc 4210688
    //   3723: iastore
    //   3724: dup
    //   3725: bipush #21
    //   3727: ldc 536887312
    //   3729: iastore
    //   3730: dup
    //   3731: bipush #22
    //   3733: bipush #16
    //   3735: iastore
    //   3736: dup
    //   3737: bipush #23
    //   3739: ldc 541065232
    //   3741: iastore
    //   3742: dup
    //   3743: bipush #24
    //   3745: ldc 541065232
    //   3747: iastore
    //   3748: dup
    //   3749: bipush #25
    //   3751: iconst_0
    //   3752: iastore
    //   3753: dup
    //   3754: bipush #26
    //   3756: ldc 4210704
    //   3758: iastore
    //   3759: dup
    //   3760: bipush #27
    //   3762: ldc 541081600
    //   3764: iastore
    //   3765: dup
    //   3766: bipush #28
    //   3768: sipush #16400
    //   3771: iastore
    //   3772: dup
    //   3773: bipush #29
    //   3775: ldc 4210688
    //   3777: iastore
    //   3778: dup
    //   3779: bipush #30
    //   3781: ldc 541081600
    //   3783: iastore
    //   3784: dup
    //   3785: bipush #31
    //   3787: ldc 536870912
    //   3789: iastore
    //   3790: dup
    //   3791: bipush #32
    //   3793: ldc 536887296
    //   3795: iastore
    //   3796: dup
    //   3797: bipush #33
    //   3799: bipush #16
    //   3801: iastore
    //   3802: dup
    //   3803: bipush #34
    //   3805: ldc 541065232
    //   3807: iastore
    //   3808: dup
    //   3809: bipush #35
    //   3811: ldc 4210688
    //   3813: iastore
    //   3814: dup
    //   3815: bipush #36
    //   3817: ldc 541081616
    //   3819: iastore
    //   3820: dup
    //   3821: bipush #37
    //   3823: ldc 4194304
    //   3825: iastore
    //   3826: dup
    //   3827: bipush #38
    //   3829: sipush #16400
    //   3832: iastore
    //   3833: dup
    //   3834: bipush #39
    //   3836: ldc 536870928
    //   3838: iastore
    //   3839: dup
    //   3840: bipush #40
    //   3842: ldc 4194304
    //   3844: iastore
    //   3845: dup
    //   3846: bipush #41
    //   3848: ldc 536887296
    //   3850: iastore
    //   3851: dup
    //   3852: bipush #42
    //   3854: ldc 536870912
    //   3856: iastore
    //   3857: dup
    //   3858: bipush #43
    //   3860: sipush #16400
    //   3863: iastore
    //   3864: dup
    //   3865: bipush #44
    //   3867: ldc 536870928
    //   3869: iastore
    //   3870: dup
    //   3871: bipush #45
    //   3873: ldc 541081616
    //   3875: iastore
    //   3876: dup
    //   3877: bipush #46
    //   3879: ldc 4210688
    //   3881: iastore
    //   3882: dup
    //   3883: bipush #47
    //   3885: ldc 541065216
    //   3887: iastore
    //   3888: dup
    //   3889: bipush #48
    //   3891: ldc 4210704
    //   3893: iastore
    //   3894: dup
    //   3895: bipush #49
    //   3897: ldc 541081600
    //   3899: iastore
    //   3900: dup
    //   3901: bipush #50
    //   3903: iconst_0
    //   3904: iastore
    //   3905: dup
    //   3906: bipush #51
    //   3908: ldc 541065232
    //   3910: iastore
    //   3911: dup
    //   3912: bipush #52
    //   3914: bipush #16
    //   3916: iastore
    //   3917: dup
    //   3918: bipush #53
    //   3920: sipush #16384
    //   3923: iastore
    //   3924: dup
    //   3925: bipush #54
    //   3927: ldc 541065216
    //   3929: iastore
    //   3930: dup
    //   3931: bipush #55
    //   3933: ldc 4210704
    //   3935: iastore
    //   3936: dup
    //   3937: bipush #56
    //   3939: sipush #16384
    //   3942: iastore
    //   3943: dup
    //   3944: bipush #57
    //   3946: ldc 4194320
    //   3948: iastore
    //   3949: dup
    //   3950: bipush #58
    //   3952: ldc 536887312
    //   3954: iastore
    //   3955: dup
    //   3956: bipush #59
    //   3958: iconst_0
    //   3959: iastore
    //   3960: dup
    //   3961: bipush #60
    //   3963: ldc 541081600
    //   3965: iastore
    //   3966: dup
    //   3967: bipush #61
    //   3969: ldc 536870912
    //   3971: iastore
    //   3972: dup
    //   3973: bipush #62
    //   3975: ldc 4194320
    //   3977: iastore
    //   3978: dup
    //   3979: bipush #63
    //   3981: ldc 536887312
    //   3983: iastore
    //   3984: astore #14
    //   3986: bipush #64
    //   3988: newarray int
    //   3990: dup
    //   3991: iconst_0
    //   3992: ldc 2097152
    //   3994: iastore
    //   3995: dup
    //   3996: iconst_1
    //   3997: ldc 69206018
    //   3999: iastore
    //   4000: dup
    //   4001: iconst_2
    //   4002: ldc 67110914
    //   4004: iastore
    //   4005: dup
    //   4006: iconst_3
    //   4007: iconst_0
    //   4008: iastore
    //   4009: dup
    //   4010: iconst_4
    //   4011: sipush #2048
    //   4014: iastore
    //   4015: dup
    //   4016: iconst_5
    //   4017: ldc 67110914
    //   4019: iastore
    //   4020: dup
    //   4021: bipush #6
    //   4023: ldc 2099202
    //   4025: iastore
    //   4026: dup
    //   4027: bipush #7
    //   4029: ldc 69208064
    //   4031: iastore
    //   4032: dup
    //   4033: bipush #8
    //   4035: ldc 69208066
    //   4037: iastore
    //   4038: dup
    //   4039: bipush #9
    //   4041: ldc 2097152
    //   4043: iastore
    //   4044: dup
    //   4045: bipush #10
    //   4047: iconst_0
    //   4048: iastore
    //   4049: dup
    //   4050: bipush #11
    //   4052: ldc 67108866
    //   4054: iastore
    //   4055: dup
    //   4056: bipush #12
    //   4058: iconst_2
    //   4059: iastore
    //   4060: dup
    //   4061: bipush #13
    //   4063: ldc 67108864
    //   4065: iastore
    //   4066: dup
    //   4067: bipush #14
    //   4069: ldc 69206018
    //   4071: iastore
    //   4072: dup
    //   4073: bipush #15
    //   4075: sipush #2050
    //   4078: iastore
    //   4079: dup
    //   4080: bipush #16
    //   4082: ldc 67110912
    //   4084: iastore
    //   4085: dup
    //   4086: bipush #17
    //   4088: ldc 2099202
    //   4090: iastore
    //   4091: dup
    //   4092: bipush #18
    //   4094: ldc 2097154
    //   4096: iastore
    //   4097: dup
    //   4098: bipush #19
    //   4100: ldc 67110912
    //   4102: iastore
    //   4103: dup
    //   4104: bipush #20
    //   4106: ldc 67108866
    //   4108: iastore
    //   4109: dup
    //   4110: bipush #21
    //   4112: ldc 69206016
    //   4114: iastore
    //   4115: dup
    //   4116: bipush #22
    //   4118: ldc 69208064
    //   4120: iastore
    //   4121: dup
    //   4122: bipush #23
    //   4124: ldc 2097154
    //   4126: iastore
    //   4127: dup
    //   4128: bipush #24
    //   4130: ldc 69206016
    //   4132: iastore
    //   4133: dup
    //   4134: bipush #25
    //   4136: sipush #2048
    //   4139: iastore
    //   4140: dup
    //   4141: bipush #26
    //   4143: sipush #2050
    //   4146: iastore
    //   4147: dup
    //   4148: bipush #27
    //   4150: ldc 69208066
    //   4152: iastore
    //   4153: dup
    //   4154: bipush #28
    //   4156: ldc 2099200
    //   4158: iastore
    //   4159: dup
    //   4160: bipush #29
    //   4162: iconst_2
    //   4163: iastore
    //   4164: dup
    //   4165: bipush #30
    //   4167: ldc 67108864
    //   4169: iastore
    //   4170: dup
    //   4171: bipush #31
    //   4173: ldc 2099200
    //   4175: iastore
    //   4176: dup
    //   4177: bipush #32
    //   4179: ldc 67108864
    //   4181: iastore
    //   4182: dup
    //   4183: bipush #33
    //   4185: ldc 2099200
    //   4187: iastore
    //   4188: dup
    //   4189: bipush #34
    //   4191: ldc 2097152
    //   4193: iastore
    //   4194: dup
    //   4195: bipush #35
    //   4197: ldc 67110914
    //   4199: iastore
    //   4200: dup
    //   4201: bipush #36
    //   4203: ldc 67110914
    //   4205: iastore
    //   4206: dup
    //   4207: bipush #37
    //   4209: ldc 69206018
    //   4211: iastore
    //   4212: dup
    //   4213: bipush #38
    //   4215: ldc 69206018
    //   4217: iastore
    //   4218: dup
    //   4219: bipush #39
    //   4221: iconst_2
    //   4222: iastore
    //   4223: dup
    //   4224: bipush #40
    //   4226: ldc 2097154
    //   4228: iastore
    //   4229: dup
    //   4230: bipush #41
    //   4232: ldc 67108864
    //   4234: iastore
    //   4235: dup
    //   4236: bipush #42
    //   4238: ldc 67110912
    //   4240: iastore
    //   4241: dup
    //   4242: bipush #43
    //   4244: ldc 2097152
    //   4246: iastore
    //   4247: dup
    //   4248: bipush #44
    //   4250: ldc 69208064
    //   4252: iastore
    //   4253: dup
    //   4254: bipush #45
    //   4256: sipush #2050
    //   4259: iastore
    //   4260: dup
    //   4261: bipush #46
    //   4263: ldc 2099202
    //   4265: iastore
    //   4266: dup
    //   4267: bipush #47
    //   4269: ldc 69208064
    //   4271: iastore
    //   4272: dup
    //   4273: bipush #48
    //   4275: sipush #2050
    //   4278: iastore
    //   4279: dup
    //   4280: bipush #49
    //   4282: ldc 67108866
    //   4284: iastore
    //   4285: dup
    //   4286: bipush #50
    //   4288: ldc 69208066
    //   4290: iastore
    //   4291: dup
    //   4292: bipush #51
    //   4294: ldc 69206016
    //   4296: iastore
    //   4297: dup
    //   4298: bipush #52
    //   4300: ldc 2099200
    //   4302: iastore
    //   4303: dup
    //   4304: bipush #53
    //   4306: iconst_0
    //   4307: iastore
    //   4308: dup
    //   4309: bipush #54
    //   4311: iconst_2
    //   4312: iastore
    //   4313: dup
    //   4314: bipush #55
    //   4316: ldc 69208066
    //   4318: iastore
    //   4319: dup
    //   4320: bipush #56
    //   4322: iconst_0
    //   4323: iastore
    //   4324: dup
    //   4325: bipush #57
    //   4327: ldc 2099202
    //   4329: iastore
    //   4330: dup
    //   4331: bipush #58
    //   4333: ldc 69206016
    //   4335: iastore
    //   4336: dup
    //   4337: bipush #59
    //   4339: sipush #2048
    //   4342: iastore
    //   4343: dup
    //   4344: bipush #60
    //   4346: ldc 67108866
    //   4348: iastore
    //   4349: dup
    //   4350: bipush #61
    //   4352: ldc 67110912
    //   4354: iastore
    //   4355: dup
    //   4356: bipush #62
    //   4358: sipush #2048
    //   4361: iastore
    //   4362: dup
    //   4363: bipush #63
    //   4365: ldc 2097154
    //   4367: iastore
    //   4368: astore #15
    //   4370: bipush #64
    //   4372: newarray int
    //   4374: dup
    //   4375: iconst_0
    //   4376: ldc 268439616
    //   4378: iastore
    //   4379: dup
    //   4380: iconst_1
    //   4381: sipush #4096
    //   4384: iastore
    //   4385: dup
    //   4386: iconst_2
    //   4387: ldc 262144
    //   4389: iastore
    //   4390: dup
    //   4391: iconst_3
    //   4392: ldc 268701760
    //   4394: iastore
    //   4395: dup
    //   4396: iconst_4
    //   4397: ldc 268435456
    //   4399: iastore
    //   4400: dup
    //   4401: iconst_5
    //   4402: ldc 268439616
    //   4404: iastore
    //   4405: dup
    //   4406: bipush #6
    //   4408: bipush #64
    //   4410: iastore
    //   4411: dup
    //   4412: bipush #7
    //   4414: ldc 268435456
    //   4416: iastore
    //   4417: dup
    //   4418: bipush #8
    //   4420: ldc 262208
    //   4422: iastore
    //   4423: dup
    //   4424: bipush #9
    //   4426: ldc 268697600
    //   4428: iastore
    //   4429: dup
    //   4430: bipush #10
    //   4432: ldc 268701760
    //   4434: iastore
    //   4435: dup
    //   4436: bipush #11
    //   4438: ldc 266240
    //   4440: iastore
    //   4441: dup
    //   4442: bipush #12
    //   4444: ldc 268701696
    //   4446: iastore
    //   4447: dup
    //   4448: bipush #13
    //   4450: ldc 266304
    //   4452: iastore
    //   4453: dup
    //   4454: bipush #14
    //   4456: sipush #4096
    //   4459: iastore
    //   4460: dup
    //   4461: bipush #15
    //   4463: bipush #64
    //   4465: iastore
    //   4466: dup
    //   4467: bipush #16
    //   4469: ldc 268697600
    //   4471: iastore
    //   4472: dup
    //   4473: bipush #17
    //   4475: ldc 268435520
    //   4477: iastore
    //   4478: dup
    //   4479: bipush #18
    //   4481: ldc 268439552
    //   4483: iastore
    //   4484: dup
    //   4485: bipush #19
    //   4487: sipush #4160
    //   4490: iastore
    //   4491: dup
    //   4492: bipush #20
    //   4494: ldc 266240
    //   4496: iastore
    //   4497: dup
    //   4498: bipush #21
    //   4500: ldc 262208
    //   4502: iastore
    //   4503: dup
    //   4504: bipush #22
    //   4506: ldc 268697664
    //   4508: iastore
    //   4509: dup
    //   4510: bipush #23
    //   4512: ldc 268701696
    //   4514: iastore
    //   4515: dup
    //   4516: bipush #24
    //   4518: sipush #4160
    //   4521: iastore
    //   4522: dup
    //   4523: bipush #25
    //   4525: iconst_0
    //   4526: iastore
    //   4527: dup
    //   4528: bipush #26
    //   4530: iconst_0
    //   4531: iastore
    //   4532: dup
    //   4533: bipush #27
    //   4535: ldc 268697664
    //   4537: iastore
    //   4538: dup
    //   4539: bipush #28
    //   4541: ldc 268435520
    //   4543: iastore
    //   4544: dup
    //   4545: bipush #29
    //   4547: ldc 268439552
    //   4549: iastore
    //   4550: dup
    //   4551: bipush #30
    //   4553: ldc 266304
    //   4555: iastore
    //   4556: dup
    //   4557: bipush #31
    //   4559: ldc 262144
    //   4561: iastore
    //   4562: dup
    //   4563: bipush #32
    //   4565: ldc 266304
    //   4567: iastore
    //   4568: dup
    //   4569: bipush #33
    //   4571: ldc 262144
    //   4573: iastore
    //   4574: dup
    //   4575: bipush #34
    //   4577: ldc 268701696
    //   4579: iastore
    //   4580: dup
    //   4581: bipush #35
    //   4583: sipush #4096
    //   4586: iastore
    //   4587: dup
    //   4588: bipush #36
    //   4590: bipush #64
    //   4592: iastore
    //   4593: dup
    //   4594: bipush #37
    //   4596: ldc 268697664
    //   4598: iastore
    //   4599: dup
    //   4600: bipush #38
    //   4602: sipush #4096
    //   4605: iastore
    //   4606: dup
    //   4607: bipush #39
    //   4609: ldc 266304
    //   4611: iastore
    //   4612: dup
    //   4613: bipush #40
    //   4615: ldc 268439552
    //   4617: iastore
    //   4618: dup
    //   4619: bipush #41
    //   4621: bipush #64
    //   4623: iastore
    //   4624: dup
    //   4625: bipush #42
    //   4627: ldc 268435520
    //   4629: iastore
    //   4630: dup
    //   4631: bipush #43
    //   4633: ldc 268697600
    //   4635: iastore
    //   4636: dup
    //   4637: bipush #44
    //   4639: ldc 268697664
    //   4641: iastore
    //   4642: dup
    //   4643: bipush #45
    //   4645: ldc 268435456
    //   4647: iastore
    //   4648: dup
    //   4649: bipush #46
    //   4651: ldc 262144
    //   4653: iastore
    //   4654: dup
    //   4655: bipush #47
    //   4657: ldc 268439616
    //   4659: iastore
    //   4660: dup
    //   4661: bipush #48
    //   4663: iconst_0
    //   4664: iastore
    //   4665: dup
    //   4666: bipush #49
    //   4668: ldc 268701760
    //   4670: iastore
    //   4671: dup
    //   4672: bipush #50
    //   4674: ldc 262208
    //   4676: iastore
    //   4677: dup
    //   4678: bipush #51
    //   4680: ldc 268435520
    //   4682: iastore
    //   4683: dup
    //   4684: bipush #52
    //   4686: ldc 268697600
    //   4688: iastore
    //   4689: dup
    //   4690: bipush #53
    //   4692: ldc 268439552
    //   4694: iastore
    //   4695: dup
    //   4696: bipush #54
    //   4698: ldc 268439616
    //   4700: iastore
    //   4701: dup
    //   4702: bipush #55
    //   4704: iconst_0
    //   4705: iastore
    //   4706: dup
    //   4707: bipush #56
    //   4709: ldc 268701760
    //   4711: iastore
    //   4712: dup
    //   4713: bipush #57
    //   4715: ldc 266240
    //   4717: iastore
    //   4718: dup
    //   4719: bipush #58
    //   4721: ldc 266240
    //   4723: iastore
    //   4724: dup
    //   4725: bipush #59
    //   4727: sipush #4160
    //   4730: iastore
    //   4731: dup
    //   4732: bipush #60
    //   4734: sipush #4160
    //   4737: iastore
    //   4738: dup
    //   4739: bipush #61
    //   4741: ldc 262208
    //   4743: iastore
    //   4744: dup
    //   4745: bipush #62
    //   4747: ldc 268435456
    //   4749: iastore
    //   4750: dup
    //   4751: bipush #63
    //   4753: ldc 268701696
    //   4755: iastore
    //   4756: astore #16
    //   4758: aload #4
    //   4760: arraylength
    //   4761: istore #17
    //   4763: iconst_2
    //   4764: newarray int
    //   4766: astore #18
    //   4768: iload #17
    //   4770: newarray byte
    //   4772: astore #5
    //   4774: iload #17
    //   4776: bipush #8
    //   4778: idiv
    //   4779: istore #19
    //   4781: iconst_0
    //   4782: istore #20
    //   4784: iload #20
    //   4786: iload #19
    //   4788: if_icmpge -> 5706
    //   4791: iload #20
    //   4793: bipush #8
    //   4795: imul
    //   4796: istore #21
    //   4798: iconst_0
    //   4799: istore #22
    //   4801: iload #22
    //   4803: iconst_2
    //   4804: if_icmpge -> 4893
    //   4807: aload #18
    //   4809: iload #22
    //   4811: aload #4
    //   4813: iload #21
    //   4815: iload #22
    //   4817: iconst_4
    //   4818: imul
    //   4819: iadd
    //   4820: baload
    //   4821: sipush #255
    //   4824: iand
    //   4825: bipush #24
    //   4827: ishl
    //   4828: aload #4
    //   4830: iload #21
    //   4832: iload #22
    //   4834: iconst_4
    //   4835: imul
    //   4836: iadd
    //   4837: iconst_1
    //   4838: iadd
    //   4839: baload
    //   4840: sipush #255
    //   4843: iand
    //   4844: bipush #16
    //   4846: ishl
    //   4847: ior
    //   4848: aload #4
    //   4850: iload #21
    //   4852: iload #22
    //   4854: iconst_4
    //   4855: imul
    //   4856: iadd
    //   4857: iconst_2
    //   4858: iadd
    //   4859: baload
    //   4860: sipush #255
    //   4863: iand
    //   4864: bipush #8
    //   4866: ishl
    //   4867: ior
    //   4868: aload #4
    //   4870: iload #21
    //   4872: iload #22
    //   4874: iconst_4
    //   4875: imul
    //   4876: iadd
    //   4877: iconst_3
    //   4878: iadd
    //   4879: baload
    //   4880: sipush #255
    //   4883: iand
    //   4884: ior
    //   4885: iastore
    //   4886: iinc #22, 1
    //   4889: iload_2
    //   4890: ifeq -> 4801
    //   4893: iconst_0
    //   4894: istore #27
    //   4896: aload #18
    //   4898: iconst_0
    //   4899: iaload
    //   4900: istore #25
    //   4902: aload #18
    //   4904: iconst_1
    //   4905: iaload
    //   4906: istore #24
    //   4908: iload #25
    //   4910: iconst_4
    //   4911: iushr
    //   4912: iload #24
    //   4914: ixor
    //   4915: ldc 252645135
    //   4917: iand
    //   4918: istore #23
    //   4920: iload #24
    //   4922: iload #23
    //   4924: ixor
    //   4925: istore #24
    //   4927: iload #25
    //   4929: iload #23
    //   4931: iconst_4
    //   4932: ishl
    //   4933: ixor
    //   4934: istore #25
    //   4936: iload #25
    //   4938: bipush #16
    //   4940: iushr
    //   4941: iload #24
    //   4943: ixor
    //   4944: ldc 65535
    //   4946: iand
    //   4947: istore #23
    //   4949: iload #24
    //   4951: iload #23
    //   4953: ixor
    //   4954: istore #24
    //   4956: iload #25
    //   4958: iload #23
    //   4960: bipush #16
    //   4962: ishl
    //   4963: ixor
    //   4964: istore #25
    //   4966: iload #24
    //   4968: iconst_2
    //   4969: iushr
    //   4970: iload #25
    //   4972: ixor
    //   4973: ldc 858993459
    //   4975: iand
    //   4976: istore #23
    //   4978: iload #25
    //   4980: iload #23
    //   4982: ixor
    //   4983: istore #25
    //   4985: iload #24
    //   4987: iload #23
    //   4989: iconst_2
    //   4990: ishl
    //   4991: ixor
    //   4992: istore #24
    //   4994: iload #24
    //   4996: bipush #8
    //   4998: iushr
    //   4999: iload #25
    //   5001: ixor
    //   5002: ldc 16711935
    //   5004: iand
    //   5005: istore #23
    //   5007: iload #25
    //   5009: iload #23
    //   5011: ixor
    //   5012: istore #25
    //   5014: iload #24
    //   5016: iload #23
    //   5018: bipush #8
    //   5020: ishl
    //   5021: ixor
    //   5022: istore #24
    //   5024: iload #24
    //   5026: iconst_1
    //   5027: ishl
    //   5028: iload #24
    //   5030: bipush #31
    //   5032: iushr
    //   5033: iconst_1
    //   5034: iand
    //   5035: ior
    //   5036: istore #24
    //   5038: iload #25
    //   5040: iload #24
    //   5042: ixor
    //   5043: ldc -1431655766
    //   5045: iand
    //   5046: istore #23
    //   5048: iload #25
    //   5050: iload #23
    //   5052: ixor
    //   5053: istore #25
    //   5055: iload #24
    //   5057: iload #23
    //   5059: ixor
    //   5060: istore #24
    //   5062: iload #25
    //   5064: iconst_1
    //   5065: ishl
    //   5066: iload #25
    //   5068: bipush #31
    //   5070: iushr
    //   5071: iconst_1
    //   5072: iand
    //   5073: ior
    //   5074: istore #25
    //   5076: iconst_0
    //   5077: istore #26
    //   5079: iload #26
    //   5081: bipush #8
    //   5083: if_icmpge -> 5421
    //   5086: iload #24
    //   5088: bipush #28
    //   5090: ishl
    //   5091: iload #24
    //   5093: iconst_4
    //   5094: iushr
    //   5095: ior
    //   5096: istore #23
    //   5098: iload #23
    //   5100: aload #6
    //   5102: iload #27
    //   5104: iinc #27, 1
    //   5107: iaload
    //   5108: ixor
    //   5109: istore #23
    //   5111: aload #15
    //   5113: iload #23
    //   5115: bipush #63
    //   5117: iand
    //   5118: iaload
    //   5119: istore #22
    //   5121: iload #22
    //   5123: aload #13
    //   5125: iload #23
    //   5127: bipush #8
    //   5129: iushr
    //   5130: bipush #63
    //   5132: iand
    //   5133: iaload
    //   5134: ior
    //   5135: istore #22
    //   5137: iload #22
    //   5139: aload #11
    //   5141: iload #23
    //   5143: bipush #16
    //   5145: iushr
    //   5146: bipush #63
    //   5148: iand
    //   5149: iaload
    //   5150: ior
    //   5151: istore #22
    //   5153: iload #22
    //   5155: aload #9
    //   5157: iload #23
    //   5159: bipush #24
    //   5161: iushr
    //   5162: bipush #63
    //   5164: iand
    //   5165: iaload
    //   5166: ior
    //   5167: istore #22
    //   5169: iload #24
    //   5171: aload #6
    //   5173: iload #27
    //   5175: iinc #27, 1
    //   5178: iaload
    //   5179: ixor
    //   5180: istore #23
    //   5182: iload #22
    //   5184: aload #16
    //   5186: iload #23
    //   5188: bipush #63
    //   5190: iand
    //   5191: iaload
    //   5192: ior
    //   5193: istore #22
    //   5195: iload #22
    //   5197: aload #14
    //   5199: iload #23
    //   5201: bipush #8
    //   5203: iushr
    //   5204: bipush #63
    //   5206: iand
    //   5207: iaload
    //   5208: ior
    //   5209: istore #22
    //   5211: iload #22
    //   5213: aload #12
    //   5215: iload #23
    //   5217: bipush #16
    //   5219: iushr
    //   5220: bipush #63
    //   5222: iand
    //   5223: iaload
    //   5224: ior
    //   5225: istore #22
    //   5227: iload #22
    //   5229: aload #10
    //   5231: iload #23
    //   5233: bipush #24
    //   5235: iushr
    //   5236: bipush #63
    //   5238: iand
    //   5239: iaload
    //   5240: ior
    //   5241: istore #22
    //   5243: iload #25
    //   5245: iload #22
    //   5247: ixor
    //   5248: istore #25
    //   5250: iload #25
    //   5252: bipush #28
    //   5254: ishl
    //   5255: iload #25
    //   5257: iconst_4
    //   5258: iushr
    //   5259: ior
    //   5260: istore #23
    //   5262: iload #23
    //   5264: aload #6
    //   5266: iload #27
    //   5268: iinc #27, 1
    //   5271: iaload
    //   5272: ixor
    //   5273: istore #23
    //   5275: aload #15
    //   5277: iload #23
    //   5279: bipush #63
    //   5281: iand
    //   5282: iaload
    //   5283: istore #22
    //   5285: iload #22
    //   5287: aload #13
    //   5289: iload #23
    //   5291: bipush #8
    //   5293: iushr
    //   5294: bipush #63
    //   5296: iand
    //   5297: iaload
    //   5298: ior
    //   5299: istore #22
    //   5301: iload #22
    //   5303: aload #11
    //   5305: iload #23
    //   5307: bipush #16
    //   5309: iushr
    //   5310: bipush #63
    //   5312: iand
    //   5313: iaload
    //   5314: ior
    //   5315: istore #22
    //   5317: iload #22
    //   5319: aload #9
    //   5321: iload #23
    //   5323: bipush #24
    //   5325: iushr
    //   5326: bipush #63
    //   5328: iand
    //   5329: iaload
    //   5330: ior
    //   5331: istore #22
    //   5333: iload #25
    //   5335: aload #6
    //   5337: iload #27
    //   5339: iinc #27, 1
    //   5342: iaload
    //   5343: ixor
    //   5344: istore #23
    //   5346: iload #22
    //   5348: aload #16
    //   5350: iload #23
    //   5352: bipush #63
    //   5354: iand
    //   5355: iaload
    //   5356: ior
    //   5357: istore #22
    //   5359: iload #22
    //   5361: aload #14
    //   5363: iload #23
    //   5365: bipush #8
    //   5367: iushr
    //   5368: bipush #63
    //   5370: iand
    //   5371: iaload
    //   5372: ior
    //   5373: istore #22
    //   5375: iload #22
    //   5377: aload #12
    //   5379: iload #23
    //   5381: bipush #16
    //   5383: iushr
    //   5384: bipush #63
    //   5386: iand
    //   5387: iaload
    //   5388: ior
    //   5389: istore #22
    //   5391: iload #22
    //   5393: aload #10
    //   5395: iload #23
    //   5397: bipush #24
    //   5399: iushr
    //   5400: bipush #63
    //   5402: iand
    //   5403: iaload
    //   5404: ior
    //   5405: istore #22
    //   5407: iload #24
    //   5409: iload #22
    //   5411: ixor
    //   5412: istore #24
    //   5414: iinc #26, 1
    //   5417: iload_2
    //   5418: ifeq -> 5079
    //   5421: iload #24
    //   5423: bipush #31
    //   5425: ishl
    //   5426: iload #24
    //   5428: iconst_1
    //   5429: iushr
    //   5430: ior
    //   5431: istore #24
    //   5433: iload #25
    //   5435: iload #24
    //   5437: ixor
    //   5438: ldc -1431655766
    //   5440: iand
    //   5441: istore #23
    //   5443: iload #25
    //   5445: iload #23
    //   5447: ixor
    //   5448: istore #25
    //   5450: iload #24
    //   5452: iload #23
    //   5454: ixor
    //   5455: istore #24
    //   5457: iload #25
    //   5459: bipush #31
    //   5461: ishl
    //   5462: iload #25
    //   5464: iconst_1
    //   5465: iushr
    //   5466: ior
    //   5467: istore #25
    //   5469: iload #25
    //   5471: bipush #8
    //   5473: iushr
    //   5474: iload #24
    //   5476: ixor
    //   5477: ldc 16711935
    //   5479: iand
    //   5480: istore #23
    //   5482: iload #24
    //   5484: iload #23
    //   5486: ixor
    //   5487: istore #24
    //   5489: iload #25
    //   5491: iload #23
    //   5493: bipush #8
    //   5495: ishl
    //   5496: ixor
    //   5497: istore #25
    //   5499: iload #25
    //   5501: iconst_2
    //   5502: iushr
    //   5503: iload #24
    //   5505: ixor
    //   5506: ldc 858993459
    //   5508: iand
    //   5509: istore #23
    //   5511: iload #24
    //   5513: iload #23
    //   5515: ixor
    //   5516: istore #24
    //   5518: iload #25
    //   5520: iload #23
    //   5522: iconst_2
    //   5523: ishl
    //   5524: ixor
    //   5525: istore #25
    //   5527: iload #24
    //   5529: bipush #16
    //   5531: iushr
    //   5532: iload #25
    //   5534: ixor
    //   5535: ldc 65535
    //   5537: iand
    //   5538: istore #23
    //   5540: iload #25
    //   5542: iload #23
    //   5544: ixor
    //   5545: istore #25
    //   5547: iload #24
    //   5549: iload #23
    //   5551: bipush #16
    //   5553: ishl
    //   5554: ixor
    //   5555: istore #24
    //   5557: iload #24
    //   5559: iconst_4
    //   5560: iushr
    //   5561: iload #25
    //   5563: ixor
    //   5564: ldc 252645135
    //   5566: iand
    //   5567: istore #23
    //   5569: iload #25
    //   5571: iload #23
    //   5573: ixor
    //   5574: istore #25
    //   5576: iload #24
    //   5578: iload #23
    //   5580: iconst_4
    //   5581: ishl
    //   5582: ixor
    //   5583: istore #24
    //   5585: aload #18
    //   5587: iconst_0
    //   5588: iload #24
    //   5590: iastore
    //   5591: aload #18
    //   5593: iconst_1
    //   5594: iload #25
    //   5596: iastore
    //   5597: iload #20
    //   5599: bipush #8
    //   5601: imul
    //   5602: istore #28
    //   5604: iconst_0
    //   5605: istore #29
    //   5607: iload #29
    //   5609: iconst_2
    //   5610: if_icmpge -> 5699
    //   5613: aload #5
    //   5615: iload #28
    //   5617: iload #29
    //   5619: iconst_4
    //   5620: imul
    //   5621: iadd
    //   5622: aload #18
    //   5624: iload #29
    //   5626: iaload
    //   5627: bipush #24
    //   5629: iushr
    //   5630: i2b
    //   5631: bastore
    //   5632: aload #5
    //   5634: iload #28
    //   5636: iload #29
    //   5638: iconst_4
    //   5639: imul
    //   5640: iadd
    //   5641: iconst_1
    //   5642: iadd
    //   5643: aload #18
    //   5645: iload #29
    //   5647: iaload
    //   5648: bipush #16
    //   5650: iushr
    //   5651: i2b
    //   5652: bastore
    //   5653: aload #5
    //   5655: iload #28
    //   5657: iload #29
    //   5659: iconst_4
    //   5660: imul
    //   5661: iadd
    //   5662: iconst_2
    //   5663: iadd
    //   5664: aload #18
    //   5666: iload #29
    //   5668: iaload
    //   5669: bipush #8
    //   5671: iushr
    //   5672: i2b
    //   5673: bastore
    //   5674: aload #5
    //   5676: iload #28
    //   5678: iload #29
    //   5680: iconst_4
    //   5681: imul
    //   5682: iadd
    //   5683: iconst_3
    //   5684: iadd
    //   5685: aload #18
    //   5687: iload #29
    //   5689: iaload
    //   5690: i2b
    //   5691: bastore
    //   5692: iinc #29, 1
    //   5695: iload_2
    //   5696: ifeq -> 5607
    //   5699: iinc #20, 1
    //   5702: iload_2
    //   5703: ifeq -> 4784
    //   5706: new java/math/BigInteger
    //   5709: dup
    //   5710: aload #5
    //   5712: invokespecial <init> : ([B)V
    //   5715: invokevirtual abs : ()Ljava/math/BigInteger;
    //   5718: putstatic burp/Zx_b.ZX : Ljava/lang/Object;
    //   5721: sipush #-9916
    //   5724: sipush #11988
    //   5727: invokestatic a : (II)Ljava/lang/String;
    //   5730: iconst_1
    //   5731: ldc burp/Zry9
    //   5733: invokevirtual getClassLoader : ()Ljava/lang/ClassLoader;
    //   5736: invokestatic forName : (Ljava/lang/String;ZLjava/lang/ClassLoader;)Ljava/lang/Class;
    //   5739: invokevirtual getDeclaredFields : ()[Ljava/lang/reflect/Field;
    //   5742: astore #4
    //   5744: aload #4
    //   5746: arraylength
    //   5747: istore #5
    //   5749: iconst_0
    //   5750: istore #6
    //   5752: iload #6
    //   5754: iload #5
    //   5756: if_icmpge -> 5894
    //   5759: aload #4
    //   5761: iload #6
    //   5763: aaload
    //   5764: astore #7
    //   5766: aload #7
    //   5768: invokevirtual getModifiers : ()I
    //   5771: invokestatic isStatic : (I)Z
    //   5774: ifne -> 5784
    //   5777: goto -> 5887
    //   5780: invokestatic a : (Ljava/lang/Throwable;)Ljava/lang/Throwable;
    //   5783: athrow
    //   5784: aload #7
    //   5786: invokevirtual getType : ()Ljava/lang/Class;
    //   5789: astore #8
    //   5791: aload #8
    //   5793: ifnull -> 5874
    //   5796: aload #8
    //   5798: invokevirtual isPrimitive : ()Z
    //   5801: ifne -> 5874
    //   5804: goto -> 5811
    //   5807: invokestatic a : (Ljava/lang/Throwable;)Ljava/lang/Throwable;
    //   5810: athrow
    //   5811: aload #8
    //   5813: invokevirtual getPackage : ()Ljava/lang/Package;
    //   5816: ifnull -> 5874
    //   5819: goto -> 5826
    //   5822: invokestatic a : (Ljava/lang/Throwable;)Ljava/lang/Throwable;
    //   5825: athrow
    //   5826: aload #8
    //   5828: invokevirtual getPackage : ()Ljava/lang/Package;
    //   5831: invokevirtual getName : ()Ljava/lang/String;
    //   5834: ifnull -> 5874
    //   5837: goto -> 5844
    //   5840: invokestatic a : (Ljava/lang/Throwable;)Ljava/lang/Throwable;
    //   5843: athrow
    //   5844: aload #8
    //   5846: invokevirtual getPackage : ()Ljava/lang/Package;
    //   5849: invokevirtual getName : ()Ljava/lang/String;
    //   5852: sipush #-9907
    //   5855: sipush #-7569
    //   5858: invokestatic a : (II)Ljava/lang/String;
    //   5861: invokevirtual startsWith : (Ljava/lang/String;)Z
    //   5864: ifne -> 5874
    //   5867: goto -> 5874
    //   5870: invokestatic a : (Ljava/lang/Throwable;)Ljava/lang/Throwable;
    //   5873: athrow
    //   5874: aload #7
    //   5876: iconst_1
    //   5877: invokevirtual setAccessible : (Z)V
    //   5880: aload #7
    //   5882: aconst_null
    //   5883: invokevirtual get : (Ljava/lang/Object;)Ljava/lang/Object;
    //   5886: pop
    //   5887: iinc #6, 1
    //   5890: iload_2
    //   5891: ifeq -> 5752
    //   5894: sipush #-9906
    //   5897: sipush #-31479
    //   5900: invokestatic a : (II)Ljava/lang/String;
    //   5903: invokestatic forName : (Ljava/lang/String;)Ljava/lang/Class;
    //   5906: invokevirtual getDeclaredMethods : ()[Ljava/lang/reflect/Method;
    //   5909: astore #4
    //   5911: aload #4
    //   5913: arraylength
    //   5914: istore #5
    //   5916: iconst_0
    //   5917: istore #6
    //   5919: iload #6
    //   5921: iload #5
    //   5923: if_icmpge -> 6056
    //   5926: aload #4
    //   5928: iload #6
    //   5930: aaload
    //   5931: astore #7
    //   5933: aload #7
    //   5935: invokevirtual getParameterTypes : ()[Ljava/lang/Class;
    //   5938: pop
    //   5939: aload #7
    //   5941: invokevirtual getModifiers : ()I
    //   5944: invokestatic isStatic : (I)Z
    //   5947: ifeq -> 6042
    //   5950: aload #7
    //   5952: invokevirtual getParameterTypes : ()[Ljava/lang/Class;
    //   5955: arraylength
    //   5956: iconst_2
    //   5957: if_icmpne -> 6042
    //   5960: goto -> 5967
    //   5963: invokestatic a : (Ljava/lang/Throwable;)Ljava/lang/Throwable;
    //   5966: athrow
    //   5967: aload #7
    //   5969: invokevirtual getReturnType : ()Ljava/lang/Class;
    //   5972: getstatic java/lang/Void.TYPE : Ljava/lang/Class;
    //   5975: invokevirtual equals : (Ljava/lang/Object;)Z
    //   5978: ifeq -> 6042
    //   5981: goto -> 5988
    //   5984: invokestatic a : (Ljava/lang/Throwable;)Ljava/lang/Throwable;
    //   5987: athrow
    //   5988: aload #7
    //   5990: iconst_1
    //   5991: invokevirtual setAccessible : (Z)V
    //   5994: aload #7
    //   5996: aconst_null
    //   5997: iconst_2
    //   5998: anewarray java/lang/Object
    //   6001: dup
    //   6002: iconst_0
    //   6003: aload_0
    //   6004: aastore
    //   6005: dup
    //   6006: iconst_1
    //   6007: aload_1
    //   6008: ifnonnull -> 6026
    //   6011: goto -> 6018
    //   6014: invokestatic a : (Ljava/lang/Throwable;)Ljava/lang/Throwable;
    //   6017: athrow
    //   6018: aload_1
    //   6019: goto -> 6033
    //   6022: invokestatic a : (Ljava/lang/Throwable;)Ljava/lang/Throwable;
    //   6025: athrow
    //   6026: aload_1
    //   6027: checkcast [B
    //   6030: invokevirtual clone : ()Ljava/lang/Object;
    //   6033: aastore
    //   6034: invokevirtual invoke : (Ljava/lang/Object;[Ljava/lang/Object;)Ljava/lang/Object;
    //   6037: pop
    //   6038: iload_2
    //   6039: ifeq -> 6056
    //   6042: iinc #6, 1
    //   6045: iload_2
    //   6046: ifeq -> 5919
    //   6049: goto -> 6056
    //   6052: invokestatic a : (Ljava/lang/Throwable;)Ljava/lang/Throwable;
    //   6055: athrow
    //   6056: getstatic burp/Zmsl.ZP : Ljava/lang/String;
    //   6059: getstatic burp/Zsuw.ZB : Ljava/lang/Object;
    //   6062: checkcast java/math/BigInteger
    //   6065: invokevirtual intValue : ()I
    //   6068: bipush #32
    //   6070: irem
    //   6071: invokestatic abs : (I)I
    //   6074: invokevirtual charAt : (I)C
    //   6077: getstatic burp/Zly7.ZC : Ljava/lang/String;
    //   6080: getstatic burp/Zt7w.ZF : Ljava/lang/Object;
    //   6083: checkcast java/math/BigInteger
    //   6086: invokevirtual intValue : ()I
    //   6089: bipush #32
    //   6091: irem
    //   6092: invokestatic abs : (I)I
    //   6095: invokevirtual charAt : (I)C
    //   6098: if_icmple -> 6213
    //   6101: getstatic burp/Zx_b.ZD : Ljava/lang/String;
    //   6104: getstatic burp/Zsbd.Zh : Ljava/lang/Object;
    //   6107: checkcast java/math/BigInteger
    //   6110: invokevirtual intValue : ()I
    //   6113: bipush #32
    //   6115: irem
    //   6116: invokestatic abs : (I)I
    //   6119: invokevirtual charAt : (I)C
    //   6122: getstatic burp/Zxxd.Za : Ljava/lang/String;
    //   6125: getstatic burp/Zmsl.ZB : Ljava/lang/Object;
    //   6128: checkcast java/math/BigInteger
    //   6131: invokevirtual intValue : ()I
    //   6134: bipush #32
    //   6136: irem
    //   6137: invokestatic abs : (I)I
    //   6140: invokevirtual charAt : (I)C
    //   6143: if_icmple -> 6213
    //   6146: goto -> 6153
    //   6149: invokestatic a : (Ljava/lang/Throwable;)Ljava/lang/Throwable;
    //   6152: athrow
    //   6153: getstatic burp/Zg7j.ZR : Ljava/lang/String;
    //   6156: getstatic burp/Zsqi.Zf : Ljava/lang/Object;
    //   6159: checkcast java/math/BigInteger
    //   6162: invokevirtual intValue : ()I
    //   6165: bipush #32
    //   6167: irem
    //   6168: invokestatic abs : (I)I
    //   6171: invokevirtual charAt : (I)C
    //   6174: getstatic burp/Zm4k.ZW : Ljava/lang/String;
    //   6177: getstatic burp/Zelz.Z_ : Ljava/lang/Object;
    //   6180: checkcast java/math/BigInteger
    //   6183: invokevirtual intValue : ()I
    //   6186: bipush #32
    //   6188: irem
    //   6189: invokestatic abs : (I)I
    //   6192: invokevirtual charAt : (I)C
    //   6195: if_icmple -> 6213
    //   6198: goto -> 6205
    //   6201: invokestatic a : (Ljava/lang/Throwable;)Ljava/lang/Throwable;
    //   6204: athrow
    //   6205: iconst_1
    //   6206: goto -> 6214
    //   6209: invokestatic a : (Ljava/lang/Throwable;)Ljava/lang/Throwable;
    //   6212: athrow
    //   6213: iconst_0
    //   6214: ireturn
    //   6215: astore_3
    //   6216: new java/lang/Exception
    //   6219: dup
    //   6220: aload_3
    //   6221: invokevirtual getMessage : ()Ljava/lang/String;
    //   6224: invokespecial <init> : (Ljava/lang/String;)V
    //   6227: athrow
    // Exception table:
    //   from	to	target	type
    //   4	6214	6215	java/lang/Throwable
    //   40	214	217	java/lang/Throwable
    //   184	251	254	java/lang/Throwable
    //   221	288	291	java/lang/Throwable
    //   258	325	328	java/lang/Throwable
    //   295	362	365	java/lang/Throwable
    //   332	399	402	java/lang/Throwable
    //   369	436	439	java/lang/Throwable
    //   406	473	476	java/lang/Throwable
    //   443	510	513	java/lang/Throwable
    //   480	547	550	java/lang/Throwable
    //   517	584	587	java/lang/Throwable
    //   554	621	624	java/lang/Throwable
    //   591	658	661	java/lang/Throwable
    //   628	695	698	java/lang/Throwable
    //   665	732	735	java/lang/Throwable
    //   702	769	772	java/lang/Throwable
    //   739	806	809	java/lang/Throwable
    //   776	843	846	java/lang/Throwable
    //   813	880	883	java/lang/Throwable
    //   850	917	920	java/lang/Throwable
    //   887	954	957	java/lang/Throwable
    //   924	991	994	java/lang/Throwable
    //   961	1028	1031	java/lang/Throwable
    //   998	1065	1068	java/lang/Throwable
    //   1035	1102	1105	java/lang/Throwable
    //   1072	1139	1142	java/lang/Throwable
    //   1109	1176	1179	java/lang/Throwable
    //   1146	1213	1216	java/lang/Throwable
    //   1183	1250	1253	java/lang/Throwable
    //   1220	1287	1290	java/lang/Throwable
    //   1257	1324	1327	java/lang/Throwable
    //   1294	1357	1360	java/lang/Throwable
    //   5766	5780	5780	java/lang/Throwable
    //   5791	5804	5807	java/lang/Throwable
    //   5796	5819	5822	java/lang/Throwable
    //   5811	5837	5840	java/lang/Throwable
    //   5826	5867	5870	java/lang/Throwable
    //   5933	5960	5963	java/lang/Throwable
    //   5950	5981	5984	java/lang/Throwable
    //   5967	6011	6014	java/lang/Throwable
    //   5988	6022	6022	java/lang/Throwable
    //   6033	6049	6052	java/lang/Throwable
    //   6056	6146	6149	java/lang/Throwable
    //   6101	6198	6201	java/lang/Throwable
    //   6153	6209	6209	java/lang/Throwable
  }
  
  static {
    // Byte code:
    //   0: bipush #9
    //   2: anewarray java/lang/String
    //   5: astore #5
    //   7: iconst_0
    //   8: istore_3
    //   9: ldc '4S\\tYW8"#Yv ts!c\\t!QGM\\berH<vrw/f@~+v\\r r(Q2S58S`,%:)vI\\tDk \\t\\btMMCJ\\nkOAL6~\\b'|>c+f'+*XLp:qh'
    //   11: dup
    //   12: astore_2
    //   13: invokevirtual length : ()I
    //   16: istore #4
    //   18: bipush #32
    //   20: istore_1
    //   21: iconst_m1
    //   22: istore_0
    //   23: bipush #119
    //   25: iinc #0, 1
    //   28: aload_2
    //   29: iload_0
    //   30: dup
    //   31: iload_1
    //   32: iadd
    //   33: invokevirtual substring : (II)Ljava/lang/String;
    //   36: iconst_m1
    //   37: goto -> 142
    //   40: aload #5
    //   42: swap
    //   43: iload_3
    //   44: iinc #3, 1
    //   47: swap
    //   48: aastore
    //   49: iload_0
    //   50: iload_1
    //   51: iadd
    //   52: dup
    //   53: istore_0
    //   54: iload #4
    //   56: if_icmpge -> 68
    //   59: aload_2
    //   60: iload_0
    //   61: invokevirtual charAt : (I)C
    //   64: istore_1
    //   65: goto -> 23
    //   68: ldc 'cWtx^#'DAIg8W!\\t;4'
    //   70: dup
    //   71: astore_2
    //   72: invokevirtual length : ()I
    //   75: istore #4
    //   77: bipush #32
    //   79: istore_1
    //   80: iconst_m1
    //   81: istore_0
    //   82: iconst_2
    //   83: iinc #0, 1
    //   86: aload_2
    //   87: iload_0
    //   88: dup
    //   89: iload_1
    //   90: iadd
    //   91: invokevirtual substring : (II)Ljava/lang/String;
    //   94: iconst_0
    //   95: goto -> 142
    //   98: aload #5
    //   100: swap
    //   101: iload_3
    //   102: iinc #3, 1
    //   105: swap
    //   106: aastore
    //   107: iload_0
    //   108: iload_1
    //   109: iadd
    //   110: dup
    //   111: istore_0
    //   112: iload #4
    //   114: if_icmpge -> 126
    //   117: aload_2
    //   118: iload_0
    //   119: invokevirtual charAt : (I)C
    //   122: istore_1
    //   123: goto -> 82
    //   126: aload #5
    //   128: putstatic burp/Ze3z.a : [Ljava/lang/String;
    //   131: bipush #9
    //   133: anewarray java/lang/String
    //   136: putstatic burp/Ze3z.b : [Ljava/lang/String;
    //   139: goto -> 300
    //   142: dup_x2
    //   143: pop
    //   144: invokevirtual toCharArray : ()[C
    //   147: dup_x1
    //   148: arraylength
    //   149: dup_x2
    //   150: pop
    //   151: iconst_0
    //   152: istore #6
    //   154: dup2_x1
    //   155: pop2
    //   156: dup_x2
    //   157: iconst_1
    //   158: if_icmpgt -> 260
    //   161: dup2
    //   162: swap
    //   163: iload #6
    //   165: dup2_x1
    //   166: caload
    //   167: swap
    //   168: iload #6
    //   170: bipush #7
    //   172: irem
    //   173: tableswitch default -> 242, 0 -> 212, 1 -> 217, 2 -> 222, 3 -> 227, 4 -> 232, 5 -> 237
    //   212: bipush #126
    //   214: goto -> 244
    //   217: bipush #66
    //   219: goto -> 244
    //   222: bipush #86
    //   224: goto -> 244
    //   227: bipush #61
    //   229: goto -> 244
    //   232: bipush #52
    //   234: goto -> 244
    //   237: bipush #71
    //   239: goto -> 244
    //   242: bipush #24
    //   244: ixor
    //   245: ixor
    //   246: i2c
    //   247: castore
    //   248: iinc #6, 1
    //   251: dup
    //   252: ifne -> 260
    //   255: dup2
    //   256: dup_x1
    //   257: goto -> 165
    //   260: dup2_x1
    //   261: pop2
    //   262: dup_x2
    //   263: iload #6
    //   265: if_icmpgt -> 161
    //   268: pop
    //   269: new java/lang/String
    //   272: dup_x1
    //   273: swap
    //   274: invokespecial <init> : ([C)V
    //   277: invokevirtual intern : ()Ljava/lang/String;
    //   280: swap
    //   281: pop
    //   282: swap
    //   283: tableswitch default -> 40, 0 -> 98
    //   300: new java/math/BigInteger
    //   303: dup
    //   304: sipush #-9905
    //   307: sipush #-17269
    //   310: invokestatic a : (II)Ljava/lang/String;
    //   313: invokespecial <init> : (Ljava/lang/String;)V
    //   316: putstatic burp/Ze3z.Zf : Ljava/lang/Object;
    //   319: sipush #-9908
    //   322: sipush #-13511
    //   325: invokestatic a : (II)Ljava/lang/String;
    //   328: putstatic burp/Ze3z.Zv : Ljava/lang/String;
    //   331: return
  }
  
  private static Throwable a(Throwable paramThrowable) {
    return paramThrowable;
  }
  
  private static String a(int paramInt1, int paramInt2) {
    int i = (paramInt1 ^ 0xFFFFD94C) & 0xFFFF;
    if (b[i] == null) {
      char[] arrayOfChar = a[i].toCharArray();
      switch (arrayOfChar[0] & 0xFF) {
        case 0:
        
        case 1:
        
        case 2:
        
        case 3:
        
        case 4:
        
        case 5:
        
        case 6:
        
        case 7:
        
        case 8:
        
        case 9:
        
        case 10:
        
        case 11:
        
        case 12:
        
        case 13:
        
        case 14:
        
        case 15:
        
        case 16:
        
        case 17:
        
        case 18:
        
        case 19:
        
        case 20:
        
        case 21:
        
        case 22:
        
        case 23:
        
        case 24:
        
        case 25:
        
        case 26:
        
        case 27:
        
        case 28:
        
        case 29:
        
        case 30:
        
        case 31:
        
        case 32:
        
        case 33:
        
        case 34:
        
        case 35:
        
        case 36:
        
        case 37:
        
        case 38:
        
        case 39:
        
        case 40:
        
        case 41:
        
        case 42:
        
        case 43:
        
        case 44:
        
        case 45:
        
        case 46:
        
        case 47:
        
        case 48:
        
        case 49:
        
        case 50:
        
        case 51:
        
        case 52:
        
        case 53:
        
        case 54:
        
        case 55:
        
        case 56:
        
        case 57:
        
        case 58:
        
        case 59:
        
        case 60:
        
        case 61:
        
        case 62:
        
        case 63:
        
        case 64:
        
        case 65:
        
        case 66:
        
        case 67:
        
        case 68:
        
        case 69:
        
        case 70:
        
        case 71:
        
        case 72:
        
        case 73:
        
        case 74:
        
        case 75:
        
        case 76:
        
        case 77:
        
        case 78:
        
        case 79:
        
        case 80:
        
        case 81:
        
        case 82:
        
        case 83:
        
        case 84:
        
        case 85:
        
        case 86:
        
        case 87:
        
        case 88:
        
        case 89:
        
        case 90:
        
        case 91:
        
        case 92:
        
        case 93:
        
        case 94:
        
        case 95:
        
        case 96:
        
        case 97:
        
        case 98:
        
        case 99:
        
        case 100:
        
        case 101:
        
        case 102:
        
        case 103:
        
        case 104:
        
        case 105:
        
        case 106:
        
        case 107:
        
        case 108:
        
        case 109:
        
        case 110:
        
        case 111:
        
        case 112:
        
        case 113:
        
        case 114:
        
        case 115:
        
        case 116:
        
        case 117:
        
        case 118:
        
        case 119:
        
        case 120:
        
        case 121:
        
        case 122:
        
        case 123:
        
        case 124:
        
        case 125:
        
        case 126:
        
        case 127:
        
        case 128:
        
        case 129:
        
        case 130:
        
        case 131:
        
        case 132:
        
        case 133:
        
        case 134:
        
        case 135:
        
        case 136:
        
        case 137:
        
        case 138:
        
        case 139:
        
        case 140:
        
        case 141:
        
        case 142:
        
        case 143:
        
        case 144:
        
        case 145:
        
        case 146:
        
        case 147:
        
        case 148:
        
        case 149:
        
        case 150:
        
        case 151:
        
        case 152:
        
        case 153:
        
        case 154:
        
        case 155:
        
        case 156:
        
        case 157:
        
        case 158:
        
        case 159:
        
        case 160:
        
        case 161:
        
        case 162:
        
        case 163:
        
        case 164:
        
        case 165:
        
        case 166:
        
        case 167:
        
        case 168:
        
        case 169:
        
        case 170:
        
        case 171:
        
        case 172:
        
        case 173:
        
        case 174:
        
        case 175:
        
        case 176:
        
        case 177:
        
        case 178:
        
        case 179:
        
        case 180:
        
        case 181:
        
        case 182:
        
        case 183:
        
        case 184:
        
        case 185:
        
        case 186:
        
        case 187:
        
        case 188:
        
        case 189:
        
        case 190:
        
        case 191:
        
        case 192:
        
        case 193:
        
        case 194:
        
        case 195:
        
        case 196:
        
        case 197:
        
        case 198:
        
        case 199:
        
        case 200:
        
        case 201:
        
        case 202:
        
        case 203:
        
        case 204:
        
        case 205:
        
        case 206:
        
        case 207:
        
        case 208:
        
        case 209:
        
        case 210:
        
        case 211:
        
        case 212:
        
        case 213:
        
        case 214:
        
        case 215:
        
        case 216:
        
        case 217:
        
        case 218:
        
        case 219:
        
        case 220:
        
        case 221:
        
        case 222:
        
        case 223:
        
        case 224:
        
        case 225:
        
        case 226:
        
        case 227:
        
        case 228:
        
        case 229:
        
        case 230:
        
        case 231:
        
        case 232:
        
        case 233:
        
        case 234:
        
        case 235:
        
        case 236:
        
        case 237:
        
        case 238:
        
        case 239:
        
        case 240:
        
        case 241:
        
        case 242:
        
        case 243:
        
        case 244:
        
        case 245:
        
        case 246:
        
        case 247:
        
        case 248:
        
        case 249:
        
        case 250:
        
        case 251:
        
        case 252:
        
        case 253:
        
        case 254:
        
        default:
          break;
      } 
      byte b1 = 6;
      int j = (paramInt2 & 0xFF) - b1;
      if (j < 0)
        j += 256; 
      int k = ((paramInt2 & 0xFFFF) >>> 8) - b1;
      if (k < 0)
        k += 256; 
      for (byte b2 = 0; b2 < arrayOfChar.length; b2++) {
        int m = b2 % 2;
        if (m == 0) {
          arrayOfChar[b2] = (char)(arrayOfChar[b2] ^ j);
          j = ((j >>> 3 | j << 5) ^ arrayOfChar[b2]) & 0xFF;
        } else {
          arrayOfChar[b2] = (char)(arrayOfChar[b2] ^ k);
          k = ((k >>> 3 | k << 5) ^ arrayOfChar[b2]) & 0xFF;
        } 
      } 
      b[i] = (new String(arrayOfChar)).intern();
    } 
    return b[i];
  }
}


/* Location:              C:\Program Files\BurpSuitePro\burpsuite_pro.jar!\burp\Ze3z.class
 * Java compiler version: 21 (65.0)
 * JD-Core Version:       1.1.3
 */