package burp;

import java.math.BigInteger;

class Ze57 extends ClassLoader {
  static Object ZR;
  
  static String ZV;
  
  private static final String[] a;
  
  private static final String[] b;
  
  static void Zz(Object[] paramArrayOfObject, Object paramObject) throws Throwable {}
  
  static void Z_(Object paramObject) {
    Zk88.ZZ = a(-14830, -8327);
    Zk88.ZX = new BigInteger(a(-14827, -26494));
    boolean bool = Zt2e.ZN();
    try {
      try {
        if (Zgja.Zb.charAt(Math.abs(((BigInteger)Zk88.ZX).intValue() % 32)) > Zkk2.ZI.charAt(Math.abs(((BigInteger)Zb6a.Zz).intValue() % 32))) {
          try {
            Zt5b.Zp(Class.forName(a(-14829, -18356)));
            if (!bool)
              Zza3.Zg(Class.forName(a(-14818, -16252))); 
          } catch (Throwable throwable) {
            throw a(null);
          } 
          return;
        } 
      } catch (Throwable throwable) {
        throw a(null);
      } 
      Zza3.Zg(Class.forName(a(-14818, -16252)));
    } catch (Throwable throwable) {}
  }
  
  static boolean ZS(Object[] paramArrayOfObject, Object paramObject) throws Throwable {
    // Byte code:
    //   0: invokestatic ZK : ()Z
    //   3: istore_2
    //   4: new java/lang/StringBuilder
    //   7: dup
    //   8: invokespecial <init> : ()V
    //   11: astore_3
    //   12: iconst_0
    //   13: istore #4
    //   15: iload #4
    //   17: bipush #32
    //   19: if_icmpge -> 1355
    //   22: iload #4
    //   24: tableswitch default -> 1348, 0 -> 168, 1 -> 205, 2 -> 242, 3 -> 279, 4 -> 316, 5 -> 353, 6 -> 390, 7 -> 427, 8 -> 464, 9 -> 501, 10 -> 538, 11 -> 575, 12 -> 612, 13 -> 649, 14 -> 686, 15 -> 723, 16 -> 760, 17 -> 797, 18 -> 834, 19 -> 871, 20 -> 908, 21 -> 945, 22 -> 982, 23 -> 1019, 24 -> 1056, 25 -> 1093, 26 -> 1130, 27 -> 1167, 28 -> 1204, 29 -> 1241, 30 -> 1278, 31 -> 1315
    //   168: aload_3
    //   169: getstatic burp/Zr8r.Zn : Ljava/lang/String;
    //   172: getstatic burp/Zgz1.ZX : Ljava/lang/Object;
    //   175: checkcast java/math/BigInteger
    //   178: invokevirtual intValue : ()I
    //   181: bipush #32
    //   183: irem
    //   184: invokestatic abs : (I)I
    //   187: invokevirtual charAt : (I)C
    //   190: invokevirtual append : (C)Ljava/lang/StringBuilder;
    //   193: pop
    //   194: iload_2
    //   195: ifeq -> 1348
    //   198: goto -> 205
    //   201: invokestatic a : (Ljava/lang/Throwable;)Ljava/lang/Throwable;
    //   204: athrow
    //   205: aload_3
    //   206: getstatic burp/Zsgj.ZN : Ljava/lang/String;
    //   209: getstatic burp/Zem6.Zm : Ljava/lang/Object;
    //   212: checkcast java/math/BigInteger
    //   215: invokevirtual intValue : ()I
    //   218: bipush #32
    //   220: irem
    //   221: invokestatic abs : (I)I
    //   224: invokevirtual charAt : (I)C
    //   227: invokevirtual append : (C)Ljava/lang/StringBuilder;
    //   230: pop
    //   231: iload_2
    //   232: ifeq -> 1348
    //   235: goto -> 242
    //   238: invokestatic a : (Ljava/lang/Throwable;)Ljava/lang/Throwable;
    //   241: athrow
    //   242: aload_3
    //   243: getstatic burp/Zr0g.Zf : Ljava/lang/String;
    //   246: getstatic burp/Zl1u.Zq : Ljava/lang/Object;
    //   249: checkcast java/math/BigInteger
    //   252: invokevirtual intValue : ()I
    //   255: bipush #32
    //   257: irem
    //   258: invokestatic abs : (I)I
    //   261: invokevirtual charAt : (I)C
    //   264: invokevirtual append : (C)Ljava/lang/StringBuilder;
    //   267: pop
    //   268: iload_2
    //   269: ifeq -> 1348
    //   272: goto -> 279
    //   275: invokestatic a : (Ljava/lang/Throwable;)Ljava/lang/Throwable;
    //   278: athrow
    //   279: aload_3
    //   280: getstatic burp/Zzr.Zp : Ljava/lang/String;
    //   283: getstatic burp/Zenr.ZA : Ljava/lang/Object;
    //   286: checkcast java/math/BigInteger
    //   289: invokevirtual intValue : ()I
    //   292: bipush #32
    //   294: irem
    //   295: invokestatic abs : (I)I
    //   298: invokevirtual charAt : (I)C
    //   301: invokevirtual append : (C)Ljava/lang/StringBuilder;
    //   304: pop
    //   305: iload_2
    //   306: ifeq -> 1348
    //   309: goto -> 316
    //   312: invokestatic a : (Ljava/lang/Throwable;)Ljava/lang/Throwable;
    //   315: athrow
    //   316: aload_3
    //   317: getstatic burp/Zst7.Zi : Ljava/lang/String;
    //   320: getstatic burp/Zsxm.Zv : Ljava/lang/Object;
    //   323: checkcast java/math/BigInteger
    //   326: invokevirtual intValue : ()I
    //   329: bipush #32
    //   331: irem
    //   332: invokestatic abs : (I)I
    //   335: invokevirtual charAt : (I)C
    //   338: invokevirtual append : (C)Ljava/lang/StringBuilder;
    //   341: pop
    //   342: iload_2
    //   343: ifeq -> 1348
    //   346: goto -> 353
    //   349: invokestatic a : (Ljava/lang/Throwable;)Ljava/lang/Throwable;
    //   352: athrow
    //   353: aload_3
    //   354: getstatic burp/Zr8h.Zk : Ljava/lang/String;
    //   357: getstatic burp/Zzmc.Zg : Ljava/lang/Object;
    //   360: checkcast java/math/BigInteger
    //   363: invokevirtual intValue : ()I
    //   366: bipush #32
    //   368: irem
    //   369: invokestatic abs : (I)I
    //   372: invokevirtual charAt : (I)C
    //   375: invokevirtual append : (C)Ljava/lang/StringBuilder;
    //   378: pop
    //   379: iload_2
    //   380: ifeq -> 1348
    //   383: goto -> 390
    //   386: invokestatic a : (Ljava/lang/Throwable;)Ljava/lang/Throwable;
    //   389: athrow
    //   390: aload_3
    //   391: getstatic burp/Zrml.Zt : Ljava/lang/String;
    //   394: getstatic burp/Zztx.ZM : Ljava/lang/Object;
    //   397: checkcast java/math/BigInteger
    //   400: invokevirtual intValue : ()I
    //   403: bipush #32
    //   405: irem
    //   406: invokestatic abs : (I)I
    //   409: invokevirtual charAt : (I)C
    //   412: invokevirtual append : (C)Ljava/lang/StringBuilder;
    //   415: pop
    //   416: iload_2
    //   417: ifeq -> 1348
    //   420: goto -> 427
    //   423: invokestatic a : (Ljava/lang/Throwable;)Ljava/lang/Throwable;
    //   426: athrow
    //   427: aload_3
    //   428: getstatic burp/Zgyk.ZB : Ljava/lang/String;
    //   431: getstatic burp/Zeh9.ZY : Ljava/lang/Object;
    //   434: checkcast java/math/BigInteger
    //   437: invokevirtual intValue : ()I
    //   440: bipush #32
    //   442: irem
    //   443: invokestatic abs : (I)I
    //   446: invokevirtual charAt : (I)C
    //   449: invokevirtual append : (C)Ljava/lang/StringBuilder;
    //   452: pop
    //   453: iload_2
    //   454: ifeq -> 1348
    //   457: goto -> 464
    //   460: invokestatic a : (Ljava/lang/Throwable;)Ljava/lang/Throwable;
    //   463: athrow
    //   464: aload_3
    //   465: getstatic burp/Zmr7.Zo : Ljava/lang/String;
    //   468: getstatic burp/Zkfz.Zr : Ljava/lang/Object;
    //   471: checkcast java/math/BigInteger
    //   474: invokevirtual intValue : ()I
    //   477: bipush #32
    //   479: irem
    //   480: invokestatic abs : (I)I
    //   483: invokevirtual charAt : (I)C
    //   486: invokevirtual append : (C)Ljava/lang/StringBuilder;
    //   489: pop
    //   490: iload_2
    //   491: ifeq -> 1348
    //   494: goto -> 501
    //   497: invokestatic a : (Ljava/lang/Throwable;)Ljava/lang/Throwable;
    //   500: athrow
    //   501: aload_3
    //   502: getstatic burp/Zm__.Zf : Ljava/lang/String;
    //   505: getstatic burp/Zlzs.ZL : Ljava/lang/Object;
    //   508: checkcast java/math/BigInteger
    //   511: invokevirtual intValue : ()I
    //   514: bipush #32
    //   516: irem
    //   517: invokestatic abs : (I)I
    //   520: invokevirtual charAt : (I)C
    //   523: invokevirtual append : (C)Ljava/lang/StringBuilder;
    //   526: pop
    //   527: iload_2
    //   528: ifeq -> 1348
    //   531: goto -> 538
    //   534: invokestatic a : (Ljava/lang/Throwable;)Ljava/lang/Throwable;
    //   537: athrow
    //   538: aload_3
    //   539: getstatic burp/Ztp.ZG : Ljava/lang/String;
    //   542: getstatic burp/Zez0.ZT : Ljava/lang/Object;
    //   545: checkcast java/math/BigInteger
    //   548: invokevirtual intValue : ()I
    //   551: bipush #32
    //   553: irem
    //   554: invokestatic abs : (I)I
    //   557: invokevirtual charAt : (I)C
    //   560: invokevirtual append : (C)Ljava/lang/StringBuilder;
    //   563: pop
    //   564: iload_2
    //   565: ifeq -> 1348
    //   568: goto -> 575
    //   571: invokestatic a : (Ljava/lang/Throwable;)Ljava/lang/Throwable;
    //   574: athrow
    //   575: aload_3
    //   576: getstatic burp/Zxjw.Zv : Ljava/lang/String;
    //   579: getstatic burp/Zvi.Zs : Ljava/lang/Object;
    //   582: checkcast java/math/BigInteger
    //   585: invokevirtual intValue : ()I
    //   588: bipush #32
    //   590: irem
    //   591: invokestatic abs : (I)I
    //   594: invokevirtual charAt : (I)C
    //   597: invokevirtual append : (C)Ljava/lang/StringBuilder;
    //   600: pop
    //   601: iload_2
    //   602: ifeq -> 1348
    //   605: goto -> 612
    //   608: invokestatic a : (Ljava/lang/Throwable;)Ljava/lang/Throwable;
    //   611: athrow
    //   612: aload_3
    //   613: getstatic burp/Zkvr.Zm : Ljava/lang/String;
    //   616: getstatic burp/Zzap.ZL : Ljava/lang/Object;
    //   619: checkcast java/math/BigInteger
    //   622: invokevirtual intValue : ()I
    //   625: bipush #32
    //   627: irem
    //   628: invokestatic abs : (I)I
    //   631: invokevirtual charAt : (I)C
    //   634: invokevirtual append : (C)Ljava/lang/StringBuilder;
    //   637: pop
    //   638: iload_2
    //   639: ifeq -> 1348
    //   642: goto -> 649
    //   645: invokestatic a : (Ljava/lang/Throwable;)Ljava/lang/Throwable;
    //   648: athrow
    //   649: aload_3
    //   650: getstatic burp/Zzxa.Zl : Ljava/lang/String;
    //   653: getstatic burp/Zsq6.ZS : Ljava/lang/Object;
    //   656: checkcast java/math/BigInteger
    //   659: invokevirtual intValue : ()I
    //   662: bipush #32
    //   664: irem
    //   665: invokestatic abs : (I)I
    //   668: invokevirtual charAt : (I)C
    //   671: invokevirtual append : (C)Ljava/lang/StringBuilder;
    //   674: pop
    //   675: iload_2
    //   676: ifeq -> 1348
    //   679: goto -> 686
    //   682: invokestatic a : (Ljava/lang/Throwable;)Ljava/lang/Throwable;
    //   685: athrow
    //   686: aload_3
    //   687: getstatic burp/Zgii.Ze : Ljava/lang/String;
    //   690: getstatic burp/Zrof.ZB : Ljava/lang/Object;
    //   693: checkcast java/math/BigInteger
    //   696: invokevirtual intValue : ()I
    //   699: bipush #32
    //   701: irem
    //   702: invokestatic abs : (I)I
    //   705: invokevirtual charAt : (I)C
    //   708: invokevirtual append : (C)Ljava/lang/StringBuilder;
    //   711: pop
    //   712: iload_2
    //   713: ifeq -> 1348
    //   716: goto -> 723
    //   719: invokestatic a : (Ljava/lang/Throwable;)Ljava/lang/Throwable;
    //   722: athrow
    //   723: aload_3
    //   724: getstatic burp/Zztz.Zp : Ljava/lang/String;
    //   727: getstatic burp/Zkaw.ZB : Ljava/lang/Object;
    //   730: checkcast java/math/BigInteger
    //   733: invokevirtual intValue : ()I
    //   736: bipush #32
    //   738: irem
    //   739: invokestatic abs : (I)I
    //   742: invokevirtual charAt : (I)C
    //   745: invokevirtual append : (C)Ljava/lang/StringBuilder;
    //   748: pop
    //   749: iload_2
    //   750: ifeq -> 1348
    //   753: goto -> 760
    //   756: invokestatic a : (Ljava/lang/Throwable;)Ljava/lang/Throwable;
    //   759: athrow
    //   760: aload_3
    //   761: getstatic burp/Ztmy.ZF : Ljava/lang/String;
    //   764: getstatic burp/Zl2q.Zg : Ljava/lang/Object;
    //   767: checkcast java/math/BigInteger
    //   770: invokevirtual intValue : ()I
    //   773: bipush #32
    //   775: irem
    //   776: invokestatic abs : (I)I
    //   779: invokevirtual charAt : (I)C
    //   782: invokevirtual append : (C)Ljava/lang/StringBuilder;
    //   785: pop
    //   786: iload_2
    //   787: ifeq -> 1348
    //   790: goto -> 797
    //   793: invokestatic a : (Ljava/lang/Throwable;)Ljava/lang/Throwable;
    //   796: athrow
    //   797: aload_3
    //   798: getstatic burp/Zzh0.ZK : Ljava/lang/String;
    //   801: getstatic burp/Zg4w.ZR : Ljava/lang/Object;
    //   804: checkcast java/math/BigInteger
    //   807: invokevirtual intValue : ()I
    //   810: bipush #32
    //   812: irem
    //   813: invokestatic abs : (I)I
    //   816: invokevirtual charAt : (I)C
    //   819: invokevirtual append : (C)Ljava/lang/StringBuilder;
    //   822: pop
    //   823: iload_2
    //   824: ifeq -> 1348
    //   827: goto -> 834
    //   830: invokestatic a : (Ljava/lang/Throwable;)Ljava/lang/Throwable;
    //   833: athrow
    //   834: aload_3
    //   835: getstatic burp/Zbow.Zr : Ljava/lang/String;
    //   838: getstatic burp/Zzc_.Zi : Ljava/lang/Object;
    //   841: checkcast java/math/BigInteger
    //   844: invokevirtual intValue : ()I
    //   847: bipush #32
    //   849: irem
    //   850: invokestatic abs : (I)I
    //   853: invokevirtual charAt : (I)C
    //   856: invokevirtual append : (C)Ljava/lang/StringBuilder;
    //   859: pop
    //   860: iload_2
    //   861: ifeq -> 1348
    //   864: goto -> 871
    //   867: invokestatic a : (Ljava/lang/Throwable;)Ljava/lang/Throwable;
    //   870: athrow
    //   871: aload_3
    //   872: getstatic burp/Zzs9.Zg : Ljava/lang/String;
    //   875: getstatic burp/Ztfr.Zr : Ljava/lang/Object;
    //   878: checkcast java/math/BigInteger
    //   881: invokevirtual intValue : ()I
    //   884: bipush #32
    //   886: irem
    //   887: invokestatic abs : (I)I
    //   890: invokevirtual charAt : (I)C
    //   893: invokevirtual append : (C)Ljava/lang/StringBuilder;
    //   896: pop
    //   897: iload_2
    //   898: ifeq -> 1348
    //   901: goto -> 908
    //   904: invokestatic a : (Ljava/lang/Throwable;)Ljava/lang/Throwable;
    //   907: athrow
    //   908: aload_3
    //   909: getstatic burp/Zty2.ZR : Ljava/lang/String;
    //   912: getstatic burp/Zbqo.Zb : Ljava/lang/Object;
    //   915: checkcast java/math/BigInteger
    //   918: invokevirtual intValue : ()I
    //   921: bipush #32
    //   923: irem
    //   924: invokestatic abs : (I)I
    //   927: invokevirtual charAt : (I)C
    //   930: invokevirtual append : (C)Ljava/lang/StringBuilder;
    //   933: pop
    //   934: iload_2
    //   935: ifeq -> 1348
    //   938: goto -> 945
    //   941: invokestatic a : (Ljava/lang/Throwable;)Ljava/lang/Throwable;
    //   944: athrow
    //   945: aload_3
    //   946: getstatic burp/Zkff.Zs : Ljava/lang/String;
    //   949: getstatic burp/Zk9s.ZY : Ljava/lang/Object;
    //   952: checkcast java/math/BigInteger
    //   955: invokevirtual intValue : ()I
    //   958: bipush #32
    //   960: irem
    //   961: invokestatic abs : (I)I
    //   964: invokevirtual charAt : (I)C
    //   967: invokevirtual append : (C)Ljava/lang/StringBuilder;
    //   970: pop
    //   971: iload_2
    //   972: ifeq -> 1348
    //   975: goto -> 982
    //   978: invokestatic a : (Ljava/lang/Throwable;)Ljava/lang/Throwable;
    //   981: athrow
    //   982: aload_3
    //   983: getstatic burp/Zz80.Ze : Ljava/lang/String;
    //   986: getstatic burp/Ze40.ZO : Ljava/lang/Object;
    //   989: checkcast java/math/BigInteger
    //   992: invokevirtual intValue : ()I
    //   995: bipush #32
    //   997: irem
    //   998: invokestatic abs : (I)I
    //   1001: invokevirtual charAt : (I)C
    //   1004: invokevirtual append : (C)Ljava/lang/StringBuilder;
    //   1007: pop
    //   1008: iload_2
    //   1009: ifeq -> 1348
    //   1012: goto -> 1019
    //   1015: invokestatic a : (Ljava/lang/Throwable;)Ljava/lang/Throwable;
    //   1018: athrow
    //   1019: aload_3
    //   1020: getstatic burp/Ztt0.Zl : Ljava/lang/String;
    //   1023: getstatic burp/Zelc.ZR : Ljava/lang/Object;
    //   1026: checkcast java/math/BigInteger
    //   1029: invokevirtual intValue : ()I
    //   1032: bipush #32
    //   1034: irem
    //   1035: invokestatic abs : (I)I
    //   1038: invokevirtual charAt : (I)C
    //   1041: invokevirtual append : (C)Ljava/lang/StringBuilder;
    //   1044: pop
    //   1045: iload_2
    //   1046: ifeq -> 1348
    //   1049: goto -> 1056
    //   1052: invokestatic a : (Ljava/lang/Throwable;)Ljava/lang/Throwable;
    //   1055: athrow
    //   1056: aload_3
    //   1057: getstatic burp/Zzri.ZL : Ljava/lang/String;
    //   1060: getstatic burp/Zkqx.ZW : Ljava/lang/Object;
    //   1063: checkcast java/math/BigInteger
    //   1066: invokevirtual intValue : ()I
    //   1069: bipush #32
    //   1071: irem
    //   1072: invokestatic abs : (I)I
    //   1075: invokevirtual charAt : (I)C
    //   1078: invokevirtual append : (C)Ljava/lang/StringBuilder;
    //   1081: pop
    //   1082: iload_2
    //   1083: ifeq -> 1348
    //   1086: goto -> 1093
    //   1089: invokestatic a : (Ljava/lang/Throwable;)Ljava/lang/Throwable;
    //   1092: athrow
    //   1093: aload_3
    //   1094: getstatic burp/Zgwu.Zd : Ljava/lang/String;
    //   1097: getstatic burp/Zsfj.ZL : Ljava/lang/Object;
    //   1100: checkcast java/math/BigInteger
    //   1103: invokevirtual intValue : ()I
    //   1106: bipush #32
    //   1108: irem
    //   1109: invokestatic abs : (I)I
    //   1112: invokevirtual charAt : (I)C
    //   1115: invokevirtual append : (C)Ljava/lang/StringBuilder;
    //   1118: pop
    //   1119: iload_2
    //   1120: ifeq -> 1348
    //   1123: goto -> 1130
    //   1126: invokestatic a : (Ljava/lang/Throwable;)Ljava/lang/Throwable;
    //   1129: athrow
    //   1130: aload_3
    //   1131: getstatic burp/Zgil.ZK : Ljava/lang/String;
    //   1134: getstatic burp/Ztfh.Zo : Ljava/lang/Object;
    //   1137: checkcast java/math/BigInteger
    //   1140: invokevirtual intValue : ()I
    //   1143: bipush #32
    //   1145: irem
    //   1146: invokestatic abs : (I)I
    //   1149: invokevirtual charAt : (I)C
    //   1152: invokevirtual append : (C)Ljava/lang/StringBuilder;
    //   1155: pop
    //   1156: iload_2
    //   1157: ifeq -> 1348
    //   1160: goto -> 1167
    //   1163: invokestatic a : (Ljava/lang/Throwable;)Ljava/lang/Throwable;
    //   1166: athrow
    //   1167: aload_3
    //   1168: getstatic burp/Zsf3.Zb : Ljava/lang/String;
    //   1171: getstatic burp/Zgqi.Zp : Ljava/lang/Object;
    //   1174: checkcast java/math/BigInteger
    //   1177: invokevirtual intValue : ()I
    //   1180: bipush #32
    //   1182: irem
    //   1183: invokestatic abs : (I)I
    //   1186: invokevirtual charAt : (I)C
    //   1189: invokevirtual append : (C)Ljava/lang/StringBuilder;
    //   1192: pop
    //   1193: iload_2
    //   1194: ifeq -> 1348
    //   1197: goto -> 1204
    //   1200: invokestatic a : (Ljava/lang/Throwable;)Ljava/lang/Throwable;
    //   1203: athrow
    //   1204: aload_3
    //   1205: getstatic burp/Zm3s.Ze : Ljava/lang/String;
    //   1208: getstatic burp/Zb38.ZC : Ljava/lang/Object;
    //   1211: checkcast java/math/BigInteger
    //   1214: invokevirtual intValue : ()I
    //   1217: bipush #32
    //   1219: irem
    //   1220: invokestatic abs : (I)I
    //   1223: invokevirtual charAt : (I)C
    //   1226: invokevirtual append : (C)Ljava/lang/StringBuilder;
    //   1229: pop
    //   1230: iload_2
    //   1231: ifeq -> 1348
    //   1234: goto -> 1241
    //   1237: invokestatic a : (Ljava/lang/Throwable;)Ljava/lang/Throwable;
    //   1240: athrow
    //   1241: aload_3
    //   1242: getstatic burp/Zbo7.ZZ : Ljava/lang/String;
    //   1245: getstatic burp/Zep8.Zs : Ljava/lang/Object;
    //   1248: checkcast java/math/BigInteger
    //   1251: invokevirtual intValue : ()I
    //   1254: bipush #32
    //   1256: irem
    //   1257: invokestatic abs : (I)I
    //   1260: invokevirtual charAt : (I)C
    //   1263: invokevirtual append : (C)Ljava/lang/StringBuilder;
    //   1266: pop
    //   1267: iload_2
    //   1268: ifeq -> 1348
    //   1271: goto -> 1278
    //   1274: invokestatic a : (Ljava/lang/Throwable;)Ljava/lang/Throwable;
    //   1277: athrow
    //   1278: aload_3
    //   1279: getstatic burp/Zcc.Zb : Ljava/lang/String;
    //   1282: getstatic burp/Zrbp.Z_ : Ljava/lang/Object;
    //   1285: checkcast java/math/BigInteger
    //   1288: invokevirtual intValue : ()I
    //   1291: bipush #32
    //   1293: irem
    //   1294: invokestatic abs : (I)I
    //   1297: invokevirtual charAt : (I)C
    //   1300: invokevirtual append : (C)Ljava/lang/StringBuilder;
    //   1303: pop
    //   1304: iload_2
    //   1305: ifeq -> 1348
    //   1308: goto -> 1315
    //   1311: invokestatic a : (Ljava/lang/Throwable;)Ljava/lang/Throwable;
    //   1314: athrow
    //   1315: aload_3
    //   1316: getstatic burp/Zlbt.ZE : Ljava/lang/String;
    //   1319: getstatic burp/Zbo2.ZQ : Ljava/lang/Object;
    //   1322: checkcast java/math/BigInteger
    //   1325: invokevirtual intValue : ()I
    //   1328: bipush #32
    //   1330: irem
    //   1331: invokestatic abs : (I)I
    //   1334: invokevirtual charAt : (I)C
    //   1337: invokevirtual append : (C)Ljava/lang/StringBuilder;
    //   1340: pop
    //   1341: goto -> 1348
    //   1344: invokestatic a : (Ljava/lang/Throwable;)Ljava/lang/Throwable;
    //   1347: athrow
    //   1348: iinc #4, 1
    //   1351: iload_2
    //   1352: ifeq -> 15
    //   1355: aload_3
    //   1356: invokevirtual toString : ()Ljava/lang/String;
    //   1359: putstatic burp/Zz80.Ze : Ljava/lang/String;
    //   1362: ldc2_w 8682522807148012
    //   1365: invokestatic currentTimeMillis : ()J
    //   1368: lxor
    //   1369: lstore #5
    //   1371: lload #5
    //   1373: ldc2_w 25214903917
    //   1376: lmul
    //   1377: ldc2_w 11
    //   1380: ladd
    //   1381: ldc2_w 281474976710655
    //   1384: land
    //   1385: lstore #5
    //   1387: lload #5
    //   1389: bipush #32
    //   1391: lshl
    //   1392: lstore #7
    //   1394: lload #5
    //   1396: ldc2_w 25214903917
    //   1399: lmul
    //   1400: ldc2_w 11
    //   1403: ladd
    //   1404: ldc2_w 281474976710655
    //   1407: land
    //   1408: lstore #5
    //   1410: lload #7
    //   1412: lload #5
    //   1414: ladd
    //   1415: lstore #7
    //   1417: bipush #16
    //   1419: newarray byte
    //   1421: dup
    //   1422: iconst_0
    //   1423: bipush #48
    //   1425: bastore
    //   1426: dup
    //   1427: iconst_1
    //   1428: bipush #49
    //   1430: bastore
    //   1431: dup
    //   1432: iconst_2
    //   1433: bipush #50
    //   1435: bastore
    //   1436: dup
    //   1437: iconst_3
    //   1438: bipush #51
    //   1440: bastore
    //   1441: dup
    //   1442: iconst_4
    //   1443: bipush #52
    //   1445: bastore
    //   1446: dup
    //   1447: iconst_5
    //   1448: bipush #53
    //   1450: bastore
    //   1451: dup
    //   1452: bipush #6
    //   1454: bipush #54
    //   1456: bastore
    //   1457: dup
    //   1458: bipush #7
    //   1460: bipush #55
    //   1462: bastore
    //   1463: dup
    //   1464: bipush #8
    //   1466: bipush #56
    //   1468: bastore
    //   1469: dup
    //   1470: bipush #9
    //   1472: bipush #57
    //   1474: bastore
    //   1475: dup
    //   1476: bipush #10
    //   1478: bipush #97
    //   1480: bastore
    //   1481: dup
    //   1482: bipush #11
    //   1484: bipush #98
    //   1486: bastore
    //   1487: dup
    //   1488: bipush #12
    //   1490: bipush #99
    //   1492: bastore
    //   1493: dup
    //   1494: bipush #13
    //   1496: bipush #100
    //   1498: bastore
    //   1499: dup
    //   1500: bipush #14
    //   1502: bipush #101
    //   1504: bastore
    //   1505: dup
    //   1506: bipush #15
    //   1508: bipush #102
    //   1510: bastore
    //   1511: astore #9
    //   1513: bipush #64
    //   1515: newarray byte
    //   1517: astore #10
    //   1519: bipush #64
    //   1521: istore #11
    //   1523: bipush #16
    //   1525: istore #12
    //   1527: iload #12
    //   1529: iconst_1
    //   1530: isub
    //   1531: i2l
    //   1532: lstore #13
    //   1534: aload #10
    //   1536: iinc #11, -1
    //   1539: iload #11
    //   1541: aload #9
    //   1543: lload #7
    //   1545: lload #13
    //   1547: land
    //   1548: l2i
    //   1549: baload
    //   1550: bastore
    //   1551: lload #7
    //   1553: iconst_4
    //   1554: lushr
    //   1555: lstore #7
    //   1557: lload #7
    //   1559: lconst_0
    //   1560: lcmp
    //   1561: ifne -> 1534
    //   1564: bipush #64
    //   1566: iload #11
    //   1568: isub
    //   1569: newarray byte
    //   1571: astore #4
    //   1573: iconst_0
    //   1574: istore #15
    //   1576: iload #15
    //   1578: aload #4
    //   1580: arraylength
    //   1581: if_icmpge -> 1604
    //   1584: aload #4
    //   1586: iload #15
    //   1588: aload #10
    //   1590: iload #11
    //   1592: iload #15
    //   1594: iadd
    //   1595: baload
    //   1596: bastore
    //   1597: iinc #15, 1
    //   1600: iload_2
    //   1601: ifeq -> 1576
    //   1604: aload #4
    //   1606: arraylength
    //   1607: bipush #10
    //   1609: if_icmplt -> 1371
    //   1612: new java/lang/StringBuilder
    //   1615: dup
    //   1616: invokespecial <init> : ()V
    //   1619: astore #4
    //   1621: iconst_0
    //   1622: istore #5
    //   1624: iload #5
    //   1626: bipush #32
    //   1628: if_icmpge -> 2995
    //   1631: iload #5
    //   1633: tableswitch default -> 2988, 0 -> 1776, 1 -> 1814, 2 -> 1852, 3 -> 1890, 4 -> 1928, 5 -> 1966, 6 -> 2004, 7 -> 2042, 8 -> 2080, 9 -> 2118, 10 -> 2156, 11 -> 2194, 12 -> 2232, 13 -> 2270, 14 -> 2308, 15 -> 2346, 16 -> 2384, 17 -> 2422, 18 -> 2460, 19 -> 2498, 20 -> 2536, 21 -> 2574, 22 -> 2612, 23 -> 2650, 24 -> 2688, 25 -> 2726, 26 -> 2764, 27 -> 2802, 28 -> 2840, 29 -> 2878, 30 -> 2916, 31 -> 2954
    //   1776: aload #4
    //   1778: getstatic burp/Zbj.ZD : Ljava/lang/String;
    //   1781: getstatic burp/Zgvl.ZK : Ljava/lang/Object;
    //   1784: checkcast java/math/BigInteger
    //   1787: invokevirtual intValue : ()I
    //   1790: bipush #32
    //   1792: irem
    //   1793: invokestatic abs : (I)I
    //   1796: invokevirtual charAt : (I)C
    //   1799: invokevirtual append : (C)Ljava/lang/StringBuilder;
    //   1802: pop
    //   1803: iload_2
    //   1804: ifeq -> 2988
    //   1807: goto -> 1814
    //   1810: invokestatic a : (Ljava/lang/Throwable;)Ljava/lang/Throwable;
    //   1813: athrow
    //   1814: aload #4
    //   1816: getstatic burp/Zgwh.Zq : Ljava/lang/String;
    //   1819: getstatic burp/Zbj.ZY : Ljava/lang/Object;
    //   1822: checkcast java/math/BigInteger
    //   1825: invokevirtual intValue : ()I
    //   1828: bipush #32
    //   1830: irem
    //   1831: invokestatic abs : (I)I
    //   1834: invokevirtual charAt : (I)C
    //   1837: invokevirtual append : (C)Ljava/lang/StringBuilder;
    //   1840: pop
    //   1841: iload_2
    //   1842: ifeq -> 2988
    //   1845: goto -> 1852
    //   1848: invokestatic a : (Ljava/lang/Throwable;)Ljava/lang/Throwable;
    //   1851: athrow
    //   1852: aload #4
    //   1854: getstatic burp/Zlnq.ZQ : Ljava/lang/String;
    //   1857: getstatic burp/Zxtn.ZY : Ljava/lang/Object;
    //   1860: checkcast java/math/BigInteger
    //   1863: invokevirtual intValue : ()I
    //   1866: bipush #32
    //   1868: irem
    //   1869: invokestatic abs : (I)I
    //   1872: invokevirtual charAt : (I)C
    //   1875: invokevirtual append : (C)Ljava/lang/StringBuilder;
    //   1878: pop
    //   1879: iload_2
    //   1880: ifeq -> 2988
    //   1883: goto -> 1890
    //   1886: invokestatic a : (Ljava/lang/Throwable;)Ljava/lang/Throwable;
    //   1889: athrow
    //   1890: aload #4
    //   1892: getstatic burp/Zzv.Zy : Ljava/lang/String;
    //   1895: getstatic burp/Zetv.ZI : Ljava/lang/Object;
    //   1898: checkcast java/math/BigInteger
    //   1901: invokevirtual intValue : ()I
    //   1904: bipush #32
    //   1906: irem
    //   1907: invokestatic abs : (I)I
    //   1910: invokevirtual charAt : (I)C
    //   1913: invokevirtual append : (C)Ljava/lang/StringBuilder;
    //   1916: pop
    //   1917: iload_2
    //   1918: ifeq -> 2988
    //   1921: goto -> 1928
    //   1924: invokestatic a : (Ljava/lang/Throwable;)Ljava/lang/Throwable;
    //   1927: athrow
    //   1928: aload #4
    //   1930: getstatic burp/Ztsj.ZU : Ljava/lang/String;
    //   1933: getstatic burp/Zztx.ZM : Ljava/lang/Object;
    //   1936: checkcast java/math/BigInteger
    //   1939: invokevirtual intValue : ()I
    //   1942: bipush #32
    //   1944: irem
    //   1945: invokestatic abs : (I)I
    //   1948: invokevirtual charAt : (I)C
    //   1951: invokevirtual append : (C)Ljava/lang/StringBuilder;
    //   1954: pop
    //   1955: iload_2
    //   1956: ifeq -> 2988
    //   1959: goto -> 1966
    //   1962: invokestatic a : (Ljava/lang/Throwable;)Ljava/lang/Throwable;
    //   1965: athrow
    //   1966: aload #4
    //   1968: getstatic burp/Zeqo.Zw : Ljava/lang/String;
    //   1971: getstatic burp/Zlhu.ZJ : Ljava/lang/Object;
    //   1974: checkcast java/math/BigInteger
    //   1977: invokevirtual intValue : ()I
    //   1980: bipush #32
    //   1982: irem
    //   1983: invokestatic abs : (I)I
    //   1986: invokevirtual charAt : (I)C
    //   1989: invokevirtual append : (C)Ljava/lang/StringBuilder;
    //   1992: pop
    //   1993: iload_2
    //   1994: ifeq -> 2988
    //   1997: goto -> 2004
    //   2000: invokestatic a : (Ljava/lang/Throwable;)Ljava/lang/Throwable;
    //   2003: athrow
    //   2004: aload #4
    //   2006: getstatic burp/Zlkm.ZH : Ljava/lang/String;
    //   2009: getstatic burp/Zgw0.ZM : Ljava/lang/Object;
    //   2012: checkcast java/math/BigInteger
    //   2015: invokevirtual intValue : ()I
    //   2018: bipush #32
    //   2020: irem
    //   2021: invokestatic abs : (I)I
    //   2024: invokevirtual charAt : (I)C
    //   2027: invokevirtual append : (C)Ljava/lang/StringBuilder;
    //   2030: pop
    //   2031: iload_2
    //   2032: ifeq -> 2988
    //   2035: goto -> 2042
    //   2038: invokestatic a : (Ljava/lang/Throwable;)Ljava/lang/Throwable;
    //   2041: athrow
    //   2042: aload #4
    //   2044: getstatic burp/Zgq_.ZQ : Ljava/lang/String;
    //   2047: getstatic burp/Ztdx.ZX : Ljava/lang/Object;
    //   2050: checkcast java/math/BigInteger
    //   2053: invokevirtual intValue : ()I
    //   2056: bipush #32
    //   2058: irem
    //   2059: invokestatic abs : (I)I
    //   2062: invokevirtual charAt : (I)C
    //   2065: invokevirtual append : (C)Ljava/lang/StringBuilder;
    //   2068: pop
    //   2069: iload_2
    //   2070: ifeq -> 2988
    //   2073: goto -> 2080
    //   2076: invokestatic a : (Ljava/lang/Throwable;)Ljava/lang/Throwable;
    //   2079: athrow
    //   2080: aload #4
    //   2082: getstatic burp/Zxzt.ZG : Ljava/lang/String;
    //   2085: getstatic burp/Zr04.ZB : Ljava/lang/Object;
    //   2088: checkcast java/math/BigInteger
    //   2091: invokevirtual intValue : ()I
    //   2094: bipush #32
    //   2096: irem
    //   2097: invokestatic abs : (I)I
    //   2100: invokevirtual charAt : (I)C
    //   2103: invokevirtual append : (C)Ljava/lang/StringBuilder;
    //   2106: pop
    //   2107: iload_2
    //   2108: ifeq -> 2988
    //   2111: goto -> 2118
    //   2114: invokestatic a : (Ljava/lang/Throwable;)Ljava/lang/Throwable;
    //   2117: athrow
    //   2118: aload #4
    //   2120: getstatic burp/Zry7.Z_ : Ljava/lang/String;
    //   2123: getstatic burp/Zsxj.Zi : Ljava/lang/Object;
    //   2126: checkcast java/math/BigInteger
    //   2129: invokevirtual intValue : ()I
    //   2132: bipush #32
    //   2134: irem
    //   2135: invokestatic abs : (I)I
    //   2138: invokevirtual charAt : (I)C
    //   2141: invokevirtual append : (C)Ljava/lang/StringBuilder;
    //   2144: pop
    //   2145: iload_2
    //   2146: ifeq -> 2988
    //   2149: goto -> 2156
    //   2152: invokestatic a : (Ljava/lang/Throwable;)Ljava/lang/Throwable;
    //   2155: athrow
    //   2156: aload #4
    //   2158: getstatic burp/Zrbp.Ze : Ljava/lang/String;
    //   2161: getstatic burp/Zgdj.ZT : Ljava/lang/Object;
    //   2164: checkcast java/math/BigInteger
    //   2167: invokevirtual intValue : ()I
    //   2170: bipush #32
    //   2172: irem
    //   2173: invokestatic abs : (I)I
    //   2176: invokevirtual charAt : (I)C
    //   2179: invokevirtual append : (C)Ljava/lang/StringBuilder;
    //   2182: pop
    //   2183: iload_2
    //   2184: ifeq -> 2988
    //   2187: goto -> 2194
    //   2190: invokestatic a : (Ljava/lang/Throwable;)Ljava/lang/Throwable;
    //   2193: athrow
    //   2194: aload #4
    //   2196: getstatic burp/Zxrd.ZF : Ljava/lang/String;
    //   2199: getstatic burp/Zb8v.ZA : Ljava/lang/Object;
    //   2202: checkcast java/math/BigInteger
    //   2205: invokevirtual intValue : ()I
    //   2208: bipush #32
    //   2210: irem
    //   2211: invokestatic abs : (I)I
    //   2214: invokevirtual charAt : (I)C
    //   2217: invokevirtual append : (C)Ljava/lang/StringBuilder;
    //   2220: pop
    //   2221: iload_2
    //   2222: ifeq -> 2988
    //   2225: goto -> 2232
    //   2228: invokestatic a : (Ljava/lang/Throwable;)Ljava/lang/Throwable;
    //   2231: athrow
    //   2232: aload #4
    //   2234: getstatic burp/Zvh.ZP : Ljava/lang/String;
    //   2237: getstatic burp/Zgre.ZD : Ljava/lang/Object;
    //   2240: checkcast java/math/BigInteger
    //   2243: invokevirtual intValue : ()I
    //   2246: bipush #32
    //   2248: irem
    //   2249: invokestatic abs : (I)I
    //   2252: invokevirtual charAt : (I)C
    //   2255: invokevirtual append : (C)Ljava/lang/StringBuilder;
    //   2258: pop
    //   2259: iload_2
    //   2260: ifeq -> 2988
    //   2263: goto -> 2270
    //   2266: invokestatic a : (Ljava/lang/Throwable;)Ljava/lang/Throwable;
    //   2269: athrow
    //   2270: aload #4
    //   2272: getstatic burp/Zsq5.ZA : Ljava/lang/String;
    //   2275: getstatic burp/Ztuj.Ze : Ljava/lang/Object;
    //   2278: checkcast java/math/BigInteger
    //   2281: invokevirtual intValue : ()I
    //   2284: bipush #32
    //   2286: irem
    //   2287: invokestatic abs : (I)I
    //   2290: invokevirtual charAt : (I)C
    //   2293: invokevirtual append : (C)Ljava/lang/StringBuilder;
    //   2296: pop
    //   2297: iload_2
    //   2298: ifeq -> 2988
    //   2301: goto -> 2308
    //   2304: invokestatic a : (Ljava/lang/Throwable;)Ljava/lang/Throwable;
    //   2307: athrow
    //   2308: aload #4
    //   2310: getstatic burp/Zzri.ZL : Ljava/lang/String;
    //   2313: getstatic burp/Zrd4.Ze : Ljava/lang/Object;
    //   2316: checkcast java/math/BigInteger
    //   2319: invokevirtual intValue : ()I
    //   2322: bipush #32
    //   2324: irem
    //   2325: invokestatic abs : (I)I
    //   2328: invokevirtual charAt : (I)C
    //   2331: invokevirtual append : (C)Ljava/lang/StringBuilder;
    //   2334: pop
    //   2335: iload_2
    //   2336: ifeq -> 2988
    //   2339: goto -> 2346
    //   2342: invokestatic a : (Ljava/lang/Throwable;)Ljava/lang/Throwable;
    //   2345: athrow
    //   2346: aload #4
    //   2348: getstatic burp/Zedz.Zh : Ljava/lang/String;
    //   2351: getstatic burp/Zgdt.Zb : Ljava/lang/Object;
    //   2354: checkcast java/math/BigInteger
    //   2357: invokevirtual intValue : ()I
    //   2360: bipush #32
    //   2362: irem
    //   2363: invokestatic abs : (I)I
    //   2366: invokevirtual charAt : (I)C
    //   2369: invokevirtual append : (C)Ljava/lang/StringBuilder;
    //   2372: pop
    //   2373: iload_2
    //   2374: ifeq -> 2988
    //   2377: goto -> 2384
    //   2380: invokestatic a : (Ljava/lang/Throwable;)Ljava/lang/Throwable;
    //   2383: athrow
    //   2384: aload #4
    //   2386: getstatic burp/Zeuz.Zb : Ljava/lang/String;
    //   2389: getstatic burp/Zkk6.Zb : Ljava/lang/Object;
    //   2392: checkcast java/math/BigInteger
    //   2395: invokevirtual intValue : ()I
    //   2398: bipush #32
    //   2400: irem
    //   2401: invokestatic abs : (I)I
    //   2404: invokevirtual charAt : (I)C
    //   2407: invokevirtual append : (C)Ljava/lang/StringBuilder;
    //   2410: pop
    //   2411: iload_2
    //   2412: ifeq -> 2988
    //   2415: goto -> 2422
    //   2418: invokestatic a : (Ljava/lang/Throwable;)Ljava/lang/Throwable;
    //   2421: athrow
    //   2422: aload #4
    //   2424: getstatic burp/Ze3t.ZG : Ljava/lang/String;
    //   2427: getstatic burp/Zmwx.Zk : Ljava/lang/Object;
    //   2430: checkcast java/math/BigInteger
    //   2433: invokevirtual intValue : ()I
    //   2436: bipush #32
    //   2438: irem
    //   2439: invokestatic abs : (I)I
    //   2442: invokevirtual charAt : (I)C
    //   2445: invokevirtual append : (C)Ljava/lang/StringBuilder;
    //   2448: pop
    //   2449: iload_2
    //   2450: ifeq -> 2988
    //   2453: goto -> 2460
    //   2456: invokestatic a : (Ljava/lang/Throwable;)Ljava/lang/Throwable;
    //   2459: athrow
    //   2460: aload #4
    //   2462: getstatic burp/Zegw.Zn : Ljava/lang/String;
    //   2465: getstatic burp/Zrj3.ZA : Ljava/lang/Object;
    //   2468: checkcast java/math/BigInteger
    //   2471: invokevirtual intValue : ()I
    //   2474: bipush #32
    //   2476: irem
    //   2477: invokestatic abs : (I)I
    //   2480: invokevirtual charAt : (I)C
    //   2483: invokevirtual append : (C)Ljava/lang/StringBuilder;
    //   2486: pop
    //   2487: iload_2
    //   2488: ifeq -> 2988
    //   2491: goto -> 2498
    //   2494: invokestatic a : (Ljava/lang/Throwable;)Ljava/lang/Throwable;
    //   2497: athrow
    //   2498: aload #4
    //   2500: getstatic burp/Ztgt.ZQ : Ljava/lang/String;
    //   2503: getstatic burp/Zs4v.ZB : Ljava/lang/Object;
    //   2506: checkcast java/math/BigInteger
    //   2509: invokevirtual intValue : ()I
    //   2512: bipush #32
    //   2514: irem
    //   2515: invokestatic abs : (I)I
    //   2518: invokevirtual charAt : (I)C
    //   2521: invokevirtual append : (C)Ljava/lang/StringBuilder;
    //   2524: pop
    //   2525: iload_2
    //   2526: ifeq -> 2988
    //   2529: goto -> 2536
    //   2532: invokestatic a : (Ljava/lang/Throwable;)Ljava/lang/Throwable;
    //   2535: athrow
    //   2536: aload #4
    //   2538: getstatic burp/Zsx6.ZJ : Ljava/lang/String;
    //   2541: getstatic burp/Zt7x.ZE : Ljava/lang/Object;
    //   2544: checkcast java/math/BigInteger
    //   2547: invokevirtual intValue : ()I
    //   2550: bipush #32
    //   2552: irem
    //   2553: invokestatic abs : (I)I
    //   2556: invokevirtual charAt : (I)C
    //   2559: invokevirtual append : (C)Ljava/lang/StringBuilder;
    //   2562: pop
    //   2563: iload_2
    //   2564: ifeq -> 2988
    //   2567: goto -> 2574
    //   2570: invokestatic a : (Ljava/lang/Throwable;)Ljava/lang/Throwable;
    //   2573: athrow
    //   2574: aload #4
    //   2576: getstatic burp/Zm52.Ze : Ljava/lang/String;
    //   2579: getstatic burp/Zgw0.ZM : Ljava/lang/Object;
    //   2582: checkcast java/math/BigInteger
    //   2585: invokevirtual intValue : ()I
    //   2588: bipush #32
    //   2590: irem
    //   2591: invokestatic abs : (I)I
    //   2594: invokevirtual charAt : (I)C
    //   2597: invokevirtual append : (C)Ljava/lang/StringBuilder;
    //   2600: pop
    //   2601: iload_2
    //   2602: ifeq -> 2988
    //   2605: goto -> 2612
    //   2608: invokestatic a : (Ljava/lang/Throwable;)Ljava/lang/Throwable;
    //   2611: athrow
    //   2612: aload #4
    //   2614: getstatic burp/Zgzv.Zy : Ljava/lang/String;
    //   2617: getstatic burp/Zb3p.Zx : Ljava/lang/Object;
    //   2620: checkcast java/math/BigInteger
    //   2623: invokevirtual intValue : ()I
    //   2626: bipush #32
    //   2628: irem
    //   2629: invokestatic abs : (I)I
    //   2632: invokevirtual charAt : (I)C
    //   2635: invokevirtual append : (C)Ljava/lang/StringBuilder;
    //   2638: pop
    //   2639: iload_2
    //   2640: ifeq -> 2988
    //   2643: goto -> 2650
    //   2646: invokestatic a : (Ljava/lang/Throwable;)Ljava/lang/Throwable;
    //   2649: athrow
    //   2650: aload #4
    //   2652: getstatic burp/Ze7y.Zm : Ljava/lang/String;
    //   2655: getstatic burp/Zrpy.ZG : Ljava/lang/Object;
    //   2658: checkcast java/math/BigInteger
    //   2661: invokevirtual intValue : ()I
    //   2664: bipush #32
    //   2666: irem
    //   2667: invokestatic abs : (I)I
    //   2670: invokevirtual charAt : (I)C
    //   2673: invokevirtual append : (C)Ljava/lang/StringBuilder;
    //   2676: pop
    //   2677: iload_2
    //   2678: ifeq -> 2988
    //   2681: goto -> 2688
    //   2684: invokestatic a : (Ljava/lang/Throwable;)Ljava/lang/Throwable;
    //   2687: athrow
    //   2688: aload #4
    //   2690: getstatic burp/Zzvr.Zc : Ljava/lang/String;
    //   2693: getstatic burp/Zxzv.Zg : Ljava/lang/Object;
    //   2696: checkcast java/math/BigInteger
    //   2699: invokevirtual intValue : ()I
    //   2702: bipush #32
    //   2704: irem
    //   2705: invokestatic abs : (I)I
    //   2708: invokevirtual charAt : (I)C
    //   2711: invokevirtual append : (C)Ljava/lang/StringBuilder;
    //   2714: pop
    //   2715: iload_2
    //   2716: ifeq -> 2988
    //   2719: goto -> 2726
    //   2722: invokestatic a : (Ljava/lang/Throwable;)Ljava/lang/Throwable;
    //   2725: athrow
    //   2726: aload #4
    //   2728: getstatic burp/Zlbt.ZE : Ljava/lang/String;
    //   2731: getstatic burp/Zgb9.Zb : Ljava/lang/Object;
    //   2734: checkcast java/math/BigInteger
    //   2737: invokevirtual intValue : ()I
    //   2740: bipush #32
    //   2742: irem
    //   2743: invokestatic abs : (I)I
    //   2746: invokevirtual charAt : (I)C
    //   2749: invokevirtual append : (C)Ljava/lang/StringBuilder;
    //   2752: pop
    //   2753: iload_2
    //   2754: ifeq -> 2988
    //   2757: goto -> 2764
    //   2760: invokestatic a : (Ljava/lang/Throwable;)Ljava/lang/Throwable;
    //   2763: athrow
    //   2764: aload #4
    //   2766: getstatic burp/Zry0.Zz : Ljava/lang/String;
    //   2769: getstatic burp/Zb0s.Zv : Ljava/lang/Object;
    //   2772: checkcast java/math/BigInteger
    //   2775: invokevirtual intValue : ()I
    //   2778: bipush #32
    //   2780: irem
    //   2781: invokestatic abs : (I)I
    //   2784: invokevirtual charAt : (I)C
    //   2787: invokevirtual append : (C)Ljava/lang/StringBuilder;
    //   2790: pop
    //   2791: iload_2
    //   2792: ifeq -> 2988
    //   2795: goto -> 2802
    //   2798: invokestatic a : (Ljava/lang/Throwable;)Ljava/lang/Throwable;
    //   2801: athrow
    //   2802: aload #4
    //   2804: getstatic burp/Zsde.Zi : Ljava/lang/String;
    //   2807: getstatic burp/Zs_3.ZZ : Ljava/lang/Object;
    //   2810: checkcast java/math/BigInteger
    //   2813: invokevirtual intValue : ()I
    //   2816: bipush #32
    //   2818: irem
    //   2819: invokestatic abs : (I)I
    //   2822: invokevirtual charAt : (I)C
    //   2825: invokevirtual append : (C)Ljava/lang/StringBuilder;
    //   2828: pop
    //   2829: iload_2
    //   2830: ifeq -> 2988
    //   2833: goto -> 2840
    //   2836: invokestatic a : (Ljava/lang/Throwable;)Ljava/lang/Throwable;
    //   2839: athrow
    //   2840: aload #4
    //   2842: getstatic burp/Zk7w.ZB : Ljava/lang/String;
    //   2845: getstatic burp/Zebj.Zf : Ljava/lang/Object;
    //   2848: checkcast java/math/BigInteger
    //   2851: invokevirtual intValue : ()I
    //   2854: bipush #32
    //   2856: irem
    //   2857: invokestatic abs : (I)I
    //   2860: invokevirtual charAt : (I)C
    //   2863: invokevirtual append : (C)Ljava/lang/StringBuilder;
    //   2866: pop
    //   2867: iload_2
    //   2868: ifeq -> 2988
    //   2871: goto -> 2878
    //   2874: invokestatic a : (Ljava/lang/Throwable;)Ljava/lang/Throwable;
    //   2877: athrow
    //   2878: aload #4
    //   2880: getstatic burp/Zgw7.ZN : Ljava/lang/String;
    //   2883: getstatic burp/Zb4m.Zp : Ljava/lang/Object;
    //   2886: checkcast java/math/BigInteger
    //   2889: invokevirtual intValue : ()I
    //   2892: bipush #32
    //   2894: irem
    //   2895: invokestatic abs : (I)I
    //   2898: invokevirtual charAt : (I)C
    //   2901: invokevirtual append : (C)Ljava/lang/StringBuilder;
    //   2904: pop
    //   2905: iload_2
    //   2906: ifeq -> 2988
    //   2909: goto -> 2916
    //   2912: invokestatic a : (Ljava/lang/Throwable;)Ljava/lang/Throwable;
    //   2915: athrow
    //   2916: aload #4
    //   2918: getstatic burp/Zer1.ZV : Ljava/lang/String;
    //   2921: getstatic burp/Zezn.Zh : Ljava/lang/Object;
    //   2924: checkcast java/math/BigInteger
    //   2927: invokevirtual intValue : ()I
    //   2930: bipush #32
    //   2932: irem
    //   2933: invokestatic abs : (I)I
    //   2936: invokevirtual charAt : (I)C
    //   2939: invokevirtual append : (C)Ljava/lang/StringBuilder;
    //   2942: pop
    //   2943: iload_2
    //   2944: ifeq -> 2988
    //   2947: goto -> 2954
    //   2950: invokestatic a : (Ljava/lang/Throwable;)Ljava/lang/Throwable;
    //   2953: athrow
    //   2954: aload #4
    //   2956: getstatic burp/Zevc.ZF : Ljava/lang/String;
    //   2959: getstatic burp/Zlh2.Zc : Ljava/lang/Object;
    //   2962: checkcast java/math/BigInteger
    //   2965: invokevirtual intValue : ()I
    //   2968: bipush #32
    //   2970: irem
    //   2971: invokestatic abs : (I)I
    //   2974: invokevirtual charAt : (I)C
    //   2977: invokevirtual append : (C)Ljava/lang/StringBuilder;
    //   2980: pop
    //   2981: goto -> 2988
    //   2984: invokestatic a : (Ljava/lang/Throwable;)Ljava/lang/Throwable;
    //   2987: athrow
    //   2988: iinc #5, 1
    //   2991: iload_2
    //   2992: ifeq -> 1624
    //   2995: aload #4
    //   2997: invokevirtual toString : ()Ljava/lang/String;
    //   3000: putstatic burp/Zb9k.Za : Ljava/lang/String;
    //   3003: sipush #-14825
    //   3006: sipush #29269
    //   3009: invokestatic a : (II)Ljava/lang/String;
    //   3012: iconst_1
    //   3013: ldc burp/Zezi
    //   3015: invokevirtual getClassLoader : ()Ljava/lang/ClassLoader;
    //   3018: invokestatic forName : (Ljava/lang/String;ZLjava/lang/ClassLoader;)Ljava/lang/Class;
    //   3021: invokevirtual getDeclaredFields : ()[Ljava/lang/reflect/Field;
    //   3024: astore #5
    //   3026: aload #5
    //   3028: arraylength
    //   3029: istore #6
    //   3031: iconst_0
    //   3032: istore #7
    //   3034: iload #7
    //   3036: iload #6
    //   3038: if_icmpge -> 3176
    //   3041: aload #5
    //   3043: iload #7
    //   3045: aaload
    //   3046: astore #8
    //   3048: aload #8
    //   3050: invokevirtual getModifiers : ()I
    //   3053: invokestatic isStatic : (I)Z
    //   3056: ifne -> 3066
    //   3059: goto -> 3169
    //   3062: invokestatic a : (Ljava/lang/Throwable;)Ljava/lang/Throwable;
    //   3065: athrow
    //   3066: aload #8
    //   3068: invokevirtual getType : ()Ljava/lang/Class;
    //   3071: astore #9
    //   3073: aload #9
    //   3075: ifnull -> 3156
    //   3078: aload #9
    //   3080: invokevirtual isPrimitive : ()Z
    //   3083: ifne -> 3156
    //   3086: goto -> 3093
    //   3089: invokestatic a : (Ljava/lang/Throwable;)Ljava/lang/Throwable;
    //   3092: athrow
    //   3093: aload #9
    //   3095: invokevirtual getPackage : ()Ljava/lang/Package;
    //   3098: ifnull -> 3156
    //   3101: goto -> 3108
    //   3104: invokestatic a : (Ljava/lang/Throwable;)Ljava/lang/Throwable;
    //   3107: athrow
    //   3108: aload #9
    //   3110: invokevirtual getPackage : ()Ljava/lang/Package;
    //   3113: invokevirtual getName : ()Ljava/lang/String;
    //   3116: ifnull -> 3156
    //   3119: goto -> 3126
    //   3122: invokestatic a : (Ljava/lang/Throwable;)Ljava/lang/Throwable;
    //   3125: athrow
    //   3126: aload #9
    //   3128: invokevirtual getPackage : ()Ljava/lang/Package;
    //   3131: invokevirtual getName : ()Ljava/lang/String;
    //   3134: sipush #-14828
    //   3137: sipush #27733
    //   3140: invokestatic a : (II)Ljava/lang/String;
    //   3143: invokevirtual startsWith : (Ljava/lang/String;)Z
    //   3146: ifne -> 3156
    //   3149: goto -> 3156
    //   3152: invokestatic a : (Ljava/lang/Throwable;)Ljava/lang/Throwable;
    //   3155: athrow
    //   3156: aload #8
    //   3158: iconst_1
    //   3159: invokevirtual setAccessible : (Z)V
    //   3162: aload #8
    //   3164: aconst_null
    //   3165: invokevirtual get : (Ljava/lang/Object;)Ljava/lang/Object;
    //   3168: pop
    //   3169: iinc #7, 1
    //   3172: iload_2
    //   3173: ifeq -> 3034
    //   3176: sipush #-14832
    //   3179: sipush #5563
    //   3182: invokestatic a : (II)Ljava/lang/String;
    //   3185: invokestatic forName : (Ljava/lang/String;)Ljava/lang/Class;
    //   3188: invokevirtual getDeclaredMethods : ()[Ljava/lang/reflect/Method;
    //   3191: astore #5
    //   3193: aload #5
    //   3195: arraylength
    //   3196: istore #6
    //   3198: iconst_0
    //   3199: istore #7
    //   3201: iload #7
    //   3203: iload #6
    //   3205: if_icmpge -> 3317
    //   3208: aload #5
    //   3210: iload #7
    //   3212: aaload
    //   3213: astore #8
    //   3215: aload #8
    //   3217: invokevirtual getParameterTypes : ()[Ljava/lang/Class;
    //   3220: pop
    //   3221: aload #8
    //   3223: invokevirtual getModifiers : ()I
    //   3226: invokestatic isStatic : (I)Z
    //   3229: ifeq -> 3303
    //   3232: aload #8
    //   3234: invokevirtual getParameterTypes : ()[Ljava/lang/Class;
    //   3237: arraylength
    //   3238: iconst_2
    //   3239: if_icmpne -> 3303
    //   3242: goto -> 3249
    //   3245: invokestatic a : (Ljava/lang/Throwable;)Ljava/lang/Throwable;
    //   3248: athrow
    //   3249: aload #8
    //   3251: invokevirtual getReturnType : ()Ljava/lang/Class;
    //   3254: getstatic java/lang/Boolean.TYPE : Ljava/lang/Class;
    //   3257: if_acmpne -> 3303
    //   3260: goto -> 3267
    //   3263: invokestatic a : (Ljava/lang/Throwable;)Ljava/lang/Throwable;
    //   3266: athrow
    //   3267: aload #8
    //   3269: iconst_1
    //   3270: invokevirtual setAccessible : (Z)V
    //   3273: aload #8
    //   3275: aconst_null
    //   3276: iconst_2
    //   3277: anewarray java/lang/Object
    //   3280: dup
    //   3281: iconst_0
    //   3282: aload_0
    //   3283: aastore
    //   3284: dup
    //   3285: iconst_1
    //   3286: aload_1
    //   3287: aastore
    //   3288: invokevirtual invoke : (Ljava/lang/Object;[Ljava/lang/Object;)Ljava/lang/Object;
    //   3291: pop
    //   3292: iload_2
    //   3293: ifeq -> 3317
    //   3296: goto -> 3303
    //   3299: invokestatic a : (Ljava/lang/Throwable;)Ljava/lang/Throwable;
    //   3302: athrow
    //   3303: iinc #7, 1
    //   3306: iload_2
    //   3307: ifeq -> 3201
    //   3310: goto -> 3317
    //   3313: invokestatic a : (Ljava/lang/Throwable;)Ljava/lang/Throwable;
    //   3316: athrow
    //   3317: sipush #-14831
    //   3320: sipush #-3329
    //   3323: invokestatic a : (II)Ljava/lang/String;
    //   3326: iconst_1
    //   3327: ldc burp/Zt7k
    //   3329: invokevirtual getClassLoader : ()Ljava/lang/ClassLoader;
    //   3332: invokestatic forName : (Ljava/lang/String;ZLjava/lang/ClassLoader;)Ljava/lang/Class;
    //   3335: invokevirtual getDeclaredFields : ()[Ljava/lang/reflect/Field;
    //   3338: astore #5
    //   3340: aload #5
    //   3342: arraylength
    //   3343: istore #6
    //   3345: iconst_0
    //   3346: istore #7
    //   3348: iload #7
    //   3350: iload #6
    //   3352: if_icmpge -> 3490
    //   3355: aload #5
    //   3357: iload #7
    //   3359: aaload
    //   3360: astore #8
    //   3362: aload #8
    //   3364: invokevirtual getModifiers : ()I
    //   3367: invokestatic isStatic : (I)Z
    //   3370: ifne -> 3380
    //   3373: goto -> 3483
    //   3376: invokestatic a : (Ljava/lang/Throwable;)Ljava/lang/Throwable;
    //   3379: athrow
    //   3380: aload #8
    //   3382: invokevirtual getType : ()Ljava/lang/Class;
    //   3385: astore #9
    //   3387: aload #9
    //   3389: ifnull -> 3470
    //   3392: aload #9
    //   3394: invokevirtual isPrimitive : ()Z
    //   3397: ifne -> 3470
    //   3400: goto -> 3407
    //   3403: invokestatic a : (Ljava/lang/Throwable;)Ljava/lang/Throwable;
    //   3406: athrow
    //   3407: aload #9
    //   3409: invokevirtual getPackage : ()Ljava/lang/Package;
    //   3412: ifnull -> 3470
    //   3415: goto -> 3422
    //   3418: invokestatic a : (Ljava/lang/Throwable;)Ljava/lang/Throwable;
    //   3421: athrow
    //   3422: aload #9
    //   3424: invokevirtual getPackage : ()Ljava/lang/Package;
    //   3427: invokevirtual getName : ()Ljava/lang/String;
    //   3430: ifnull -> 3470
    //   3433: goto -> 3440
    //   3436: invokestatic a : (Ljava/lang/Throwable;)Ljava/lang/Throwable;
    //   3439: athrow
    //   3440: aload #9
    //   3442: invokevirtual getPackage : ()Ljava/lang/Package;
    //   3445: invokevirtual getName : ()Ljava/lang/String;
    //   3448: sipush #-14822
    //   3451: sipush #1855
    //   3454: invokestatic a : (II)Ljava/lang/String;
    //   3457: invokevirtual startsWith : (Ljava/lang/String;)Z
    //   3460: ifne -> 3470
    //   3463: goto -> 3470
    //   3466: invokestatic a : (Ljava/lang/Throwable;)Ljava/lang/Throwable;
    //   3469: athrow
    //   3470: aload #8
    //   3472: iconst_1
    //   3473: invokevirtual setAccessible : (Z)V
    //   3476: aload #8
    //   3478: aconst_null
    //   3479: invokevirtual get : (Ljava/lang/Object;)Ljava/lang/Object;
    //   3482: pop
    //   3483: iinc #7, 1
    //   3486: iload_2
    //   3487: ifeq -> 3348
    //   3490: sipush #-14819
    //   3493: sipush #-26265
    //   3496: invokestatic a : (II)Ljava/lang/String;
    //   3499: invokestatic forName : (Ljava/lang/String;)Ljava/lang/Class;
    //   3502: invokevirtual getDeclaredMethods : ()[Ljava/lang/reflect/Method;
    //   3505: astore #5
    //   3507: aload #5
    //   3509: arraylength
    //   3510: istore #6
    //   3512: iconst_0
    //   3513: istore #7
    //   3515: iload #7
    //   3517: iload #6
    //   3519: if_icmpge -> 3652
    //   3522: aload #5
    //   3524: iload #7
    //   3526: aaload
    //   3527: astore #8
    //   3529: aload #8
    //   3531: invokevirtual getParameterTypes : ()[Ljava/lang/Class;
    //   3534: pop
    //   3535: aload #8
    //   3537: invokevirtual getModifiers : ()I
    //   3540: invokestatic isStatic : (I)Z
    //   3543: ifeq -> 3638
    //   3546: aload #8
    //   3548: invokevirtual getParameterTypes : ()[Ljava/lang/Class;
    //   3551: arraylength
    //   3552: iconst_2
    //   3553: if_icmpne -> 3638
    //   3556: goto -> 3563
    //   3559: invokestatic a : (Ljava/lang/Throwable;)Ljava/lang/Throwable;
    //   3562: athrow
    //   3563: aload #8
    //   3565: invokevirtual getReturnType : ()Ljava/lang/Class;
    //   3568: getstatic java/lang/Void.TYPE : Ljava/lang/Class;
    //   3571: invokevirtual equals : (Ljava/lang/Object;)Z
    //   3574: ifeq -> 3638
    //   3577: goto -> 3584
    //   3580: invokestatic a : (Ljava/lang/Throwable;)Ljava/lang/Throwable;
    //   3583: athrow
    //   3584: aload #8
    //   3586: iconst_1
    //   3587: invokevirtual setAccessible : (Z)V
    //   3590: aload #8
    //   3592: aconst_null
    //   3593: iconst_2
    //   3594: anewarray java/lang/Object
    //   3597: dup
    //   3598: iconst_0
    //   3599: aload_0
    //   3600: aastore
    //   3601: dup
    //   3602: iconst_1
    //   3603: aload_1
    //   3604: ifnonnull -> 3622
    //   3607: goto -> 3614
    //   3610: invokestatic a : (Ljava/lang/Throwable;)Ljava/lang/Throwable;
    //   3613: athrow
    //   3614: aload_1
    //   3615: goto -> 3629
    //   3618: invokestatic a : (Ljava/lang/Throwable;)Ljava/lang/Throwable;
    //   3621: athrow
    //   3622: aload_1
    //   3623: checkcast [B
    //   3626: invokevirtual clone : ()Ljava/lang/Object;
    //   3629: aastore
    //   3630: invokevirtual invoke : (Ljava/lang/Object;[Ljava/lang/Object;)Ljava/lang/Object;
    //   3633: pop
    //   3634: iload_2
    //   3635: ifeq -> 3652
    //   3638: iinc #7, 1
    //   3641: iload_2
    //   3642: ifeq -> 3515
    //   3645: goto -> 3652
    //   3648: invokestatic a : (Ljava/lang/Throwable;)Ljava/lang/Throwable;
    //   3651: athrow
    //   3652: getstatic burp/Zll8.ZE : Ljava/lang/Object;
    //   3655: checkcast java/math/BigInteger
    //   3658: invokevirtual toByteArray : ()[B
    //   3661: astore #5
    //   3663: new java/lang/StringBuilder
    //   3666: dup
    //   3667: invokespecial <init> : ()V
    //   3670: astore #7
    //   3672: aload #7
    //   3674: sipush #-14821
    //   3677: sipush #-17767
    //   3680: invokestatic a : (II)Ljava/lang/String;
    //   3683: invokevirtual append : (Ljava/lang/String;)Ljava/lang/StringBuilder;
    //   3686: pop
    //   3687: aload #5
    //   3689: astore #8
    //   3691: aload #8
    //   3693: arraylength
    //   3694: istore #9
    //   3696: iconst_0
    //   3697: istore #10
    //   3699: iload #10
    //   3701: iload #9
    //   3703: if_icmpge -> 3729
    //   3706: aload #8
    //   3708: iload #10
    //   3710: baload
    //   3711: istore #11
    //   3713: aload #7
    //   3715: iload #11
    //   3717: i2c
    //   3718: invokevirtual append : (C)Ljava/lang/StringBuilder;
    //   3721: pop
    //   3722: iinc #10, 1
    //   3725: iload_2
    //   3726: ifeq -> 3699
    //   3729: aload #7
    //   3731: sipush #-14826
    //   3734: sipush #-423
    //   3737: invokestatic a : (II)Ljava/lang/String;
    //   3740: ldc ''
    //   3742: invokestatic getProperty : (Ljava/lang/String;Ljava/lang/String;)Ljava/lang/String;
    //   3745: invokevirtual toLowerCase : ()Ljava/lang/String;
    //   3748: invokevirtual append : (Ljava/lang/String;)Ljava/lang/StringBuilder;
    //   3751: pop
    //   3752: aload #7
    //   3754: sipush #-14824
    //   3757: sipush #31516
    //   3760: invokestatic a : (II)Ljava/lang/String;
    //   3763: ldc ''
    //   3765: invokestatic getProperty : (Ljava/lang/String;Ljava/lang/String;)Ljava/lang/String;
    //   3768: invokevirtual toLowerCase : ()Ljava/lang/String;
    //   3771: invokevirtual append : (Ljava/lang/String;)Ljava/lang/StringBuilder;
    //   3774: pop
    //   3775: aload #7
    //   3777: invokevirtual toString : ()Ljava/lang/String;
    //   3780: invokevirtual getBytes : ()[B
    //   3783: astore #6
    //   3785: aload #6
    //   3787: astore #5
    //   3789: aload #5
    //   3791: arraylength
    //   3792: bipush #8
    //   3794: iadd
    //   3795: bipush #6
    //   3797: ishr
    //   3798: iconst_1
    //   3799: iadd
    //   3800: bipush #16
    //   3802: imul
    //   3803: newarray int
    //   3805: astore #7
    //   3807: iconst_0
    //   3808: istore #8
    //   3810: iload #8
    //   3812: aload #5
    //   3814: arraylength
    //   3815: if_icmpge -> 3859
    //   3818: aload #5
    //   3820: iload #8
    //   3822: baload
    //   3823: sipush #255
    //   3826: iand
    //   3827: istore #9
    //   3829: aload #7
    //   3831: iload #8
    //   3833: iconst_2
    //   3834: ishr
    //   3835: dup2
    //   3836: iaload
    //   3837: iload #9
    //   3839: bipush #24
    //   3841: iload #8
    //   3843: iconst_4
    //   3844: irem
    //   3845: bipush #8
    //   3847: imul
    //   3848: isub
    //   3849: ishl
    //   3850: ior
    //   3851: iastore
    //   3852: iinc #8, 1
    //   3855: iload_2
    //   3856: ifeq -> 3810
    //   3859: aload #7
    //   3861: iload #8
    //   3863: iconst_2
    //   3864: ishr
    //   3865: dup2
    //   3866: iaload
    //   3867: sipush #128
    //   3870: bipush #24
    //   3872: iload #8
    //   3874: iconst_4
    //   3875: irem
    //   3876: bipush #8
    //   3878: imul
    //   3879: isub
    //   3880: ishl
    //   3881: ior
    //   3882: iastore
    //   3883: aload #7
    //   3885: aload #7
    //   3887: arraylength
    //   3888: iconst_1
    //   3889: isub
    //   3890: aload #5
    //   3892: arraylength
    //   3893: bipush #8
    //   3895: imul
    //   3896: iastore
    //   3897: bipush #80
    //   3899: newarray int
    //   3901: astore #9
    //   3903: ldc 1732584193
    //   3905: istore #10
    //   3907: ldc -271733879
    //   3909: istore #11
    //   3911: ldc -1732584194
    //   3913: istore #12
    //   3915: ldc 271733878
    //   3917: istore #13
    //   3919: ldc -1009589776
    //   3921: istore #14
    //   3923: iconst_0
    //   3924: istore #8
    //   3926: iload #8
    //   3928: aload #7
    //   3930: arraylength
    //   3931: if_icmpge -> 4253
    //   3934: iload #10
    //   3936: istore #15
    //   3938: iload #11
    //   3940: istore #16
    //   3942: iload #12
    //   3944: istore #17
    //   3946: iload #13
    //   3948: istore #18
    //   3950: iload #14
    //   3952: istore #19
    //   3954: iconst_0
    //   3955: istore #20
    //   3957: iload #20
    //   3959: bipush #80
    //   3961: if_icmpge -> 4211
    //   3964: iload #20
    //   3966: bipush #16
    //   3968: if_icmpge -> 3995
    //   3971: aload #9
    //   3973: iload #20
    //   3975: aload #7
    //   3977: iload #8
    //   3979: iload #20
    //   3981: iadd
    //   3982: iaload
    //   3983: iastore
    //   3984: iload_2
    //   3985: ifeq -> 4050
    //   3988: goto -> 3995
    //   3991: invokestatic a : (Ljava/lang/Throwable;)Ljava/lang/Throwable;
    //   3994: athrow
    //   3995: aload #9
    //   3997: iload #20
    //   3999: iconst_3
    //   4000: isub
    //   4001: iaload
    //   4002: aload #9
    //   4004: iload #20
    //   4006: bipush #8
    //   4008: isub
    //   4009: iaload
    //   4010: ixor
    //   4011: aload #9
    //   4013: iload #20
    //   4015: bipush #14
    //   4017: isub
    //   4018: iaload
    //   4019: ixor
    //   4020: aload #9
    //   4022: iload #20
    //   4024: bipush #16
    //   4026: isub
    //   4027: iaload
    //   4028: ixor
    //   4029: istore #21
    //   4031: iload #21
    //   4033: iconst_1
    //   4034: ishl
    //   4035: iload #21
    //   4037: bipush #31
    //   4039: iushr
    //   4040: ior
    //   4041: istore #22
    //   4043: aload #9
    //   4045: iload #20
    //   4047: iload #22
    //   4049: iastore
    //   4050: iload #10
    //   4052: iconst_5
    //   4053: ishl
    //   4054: iload #10
    //   4056: bipush #27
    //   4058: iushr
    //   4059: ior
    //   4060: istore #21
    //   4062: iload #21
    //   4064: iload #14
    //   4066: iadd
    //   4067: aload #9
    //   4069: iload #20
    //   4071: iaload
    //   4072: iadd
    //   4073: iload #20
    //   4075: bipush #20
    //   4077: if_icmpge -> 4103
    //   4080: ldc 1518500249
    //   4082: iload #11
    //   4084: iload #12
    //   4086: iand
    //   4087: iload #11
    //   4089: iconst_m1
    //   4090: ixor
    //   4091: iload #13
    //   4093: iand
    //   4094: ior
    //   4095: iadd
    //   4096: goto -> 4173
    //   4099: invokestatic a : (Ljava/lang/Throwable;)Ljava/lang/Throwable;
    //   4102: athrow
    //   4103: iload #20
    //   4105: bipush #40
    //   4107: if_icmpge -> 4128
    //   4110: ldc 1859775393
    //   4112: iload #11
    //   4114: iload #12
    //   4116: ixor
    //   4117: iload #13
    //   4119: ixor
    //   4120: iadd
    //   4121: goto -> 4173
    //   4124: invokestatic a : (Ljava/lang/Throwable;)Ljava/lang/Throwable;
    //   4127: athrow
    //   4128: iload #20
    //   4130: bipush #60
    //   4132: if_icmpge -> 4162
    //   4135: ldc -1894007588
    //   4137: iload #11
    //   4139: iload #12
    //   4141: iand
    //   4142: iload #11
    //   4144: iload #13
    //   4146: iand
    //   4147: ior
    //   4148: iload #12
    //   4150: iload #13
    //   4152: iand
    //   4153: ior
    //   4154: iadd
    //   4155: goto -> 4173
    //   4158: invokestatic a : (Ljava/lang/Throwable;)Ljava/lang/Throwable;
    //   4161: athrow
    //   4162: ldc -899497514
    //   4164: iload #11
    //   4166: iload #12
    //   4168: ixor
    //   4169: iload #13
    //   4171: ixor
    //   4172: iadd
    //   4173: iadd
    //   4174: istore #22
    //   4176: iload #13
    //   4178: istore #14
    //   4180: iload #12
    //   4182: istore #13
    //   4184: iload #11
    //   4186: bipush #30
    //   4188: ishl
    //   4189: iload #11
    //   4191: iconst_2
    //   4192: iushr
    //   4193: ior
    //   4194: istore #12
    //   4196: iload #10
    //   4198: istore #11
    //   4200: iload #22
    //   4202: istore #10
    //   4204: iinc #20, 1
    //   4207: iload_2
    //   4208: ifeq -> 3957
    //   4211: iload #10
    //   4213: iload #15
    //   4215: iadd
    //   4216: istore #10
    //   4218: iload #11
    //   4220: iload #16
    //   4222: iadd
    //   4223: istore #11
    //   4225: iload #12
    //   4227: iload #17
    //   4229: iadd
    //   4230: istore #12
    //   4232: iload #13
    //   4234: iload #18
    //   4236: iadd
    //   4237: istore #13
    //   4239: iload #14
    //   4241: iload #19
    //   4243: iadd
    //   4244: istore #14
    //   4246: iinc #8, 16
    //   4249: iload_2
    //   4250: ifeq -> 3926
    //   4253: iconst_5
    //   4254: newarray int
    //   4256: dup
    //   4257: iconst_0
    //   4258: iload #10
    //   4260: iastore
    //   4261: dup
    //   4262: iconst_1
    //   4263: iload #11
    //   4265: iastore
    //   4266: dup
    //   4267: iconst_2
    //   4268: iload #12
    //   4270: iastore
    //   4271: dup
    //   4272: iconst_3
    //   4273: iload #13
    //   4275: iastore
    //   4276: dup
    //   4277: iconst_4
    //   4278: iload #14
    //   4280: iastore
    //   4281: astore #15
    //   4283: bipush #20
    //   4285: newarray byte
    //   4287: astore #16
    //   4289: iconst_0
    //   4290: istore #17
    //   4292: iload #17
    //   4294: bipush #20
    //   4296: if_icmpge -> 4337
    //   4299: aload #15
    //   4301: iload #17
    //   4303: iconst_4
    //   4304: idiv
    //   4305: iaload
    //   4306: istore #18
    //   4308: iconst_3
    //   4309: iload #17
    //   4311: iconst_4
    //   4312: irem
    //   4313: isub
    //   4314: bipush #8
    //   4316: imul
    //   4317: istore #19
    //   4319: aload #16
    //   4321: iload #17
    //   4323: iload #18
    //   4325: iload #19
    //   4327: iushr
    //   4328: i2b
    //   4329: bastore
    //   4330: iinc #17, 1
    //   4333: iload_2
    //   4334: ifeq -> 4292
    //   4337: aload #16
    //   4339: astore #6
    //   4341: getstatic burp/Ztzh.ZE : Ljava/lang/String;
    //   4344: getstatic burp/Ztsc.Zr : Ljava/lang/Object;
    //   4347: checkcast java/math/BigInteger
    //   4350: invokevirtual intValue : ()I
    //   4353: bipush #32
    //   4355: irem
    //   4356: invokestatic abs : (I)I
    //   4359: invokevirtual charAt : (I)C
    //   4362: getstatic burp/Zevc.ZF : Ljava/lang/String;
    //   4365: getstatic burp/Ztex.Z_ : Ljava/lang/Object;
    //   4368: checkcast java/math/BigInteger
    //   4371: invokevirtual intValue : ()I
    //   4374: bipush #32
    //   4376: irem
    //   4377: invokestatic abs : (I)I
    //   4380: invokevirtual charAt : (I)C
    //   4383: if_icmple -> 4490
    //   4386: getstatic burp/Zlna.Zo : Ljava/lang/String;
    //   4389: getstatic burp/Zr4z.ZH : Ljava/lang/Object;
    //   4392: checkcast java/math/BigInteger
    //   4395: invokevirtual intValue : ()I
    //   4398: bipush #32
    //   4400: irem
    //   4401: invokestatic abs : (I)I
    //   4404: invokevirtual charAt : (I)C
    //   4407: getstatic burp/Zmgl.Zh : Ljava/lang/String;
    //   4410: getstatic burp/Zs8y.ZG : Ljava/lang/Object;
    //   4413: checkcast java/math/BigInteger
    //   4416: invokevirtual intValue : ()I
    //   4419: bipush #32
    //   4421: irem
    //   4422: invokestatic abs : (I)I
    //   4425: invokevirtual charAt : (I)C
    //   4428: if_icmple -> 4490
    //   4431: goto -> 4438
    //   4434: invokestatic a : (Ljava/lang/Throwable;)Ljava/lang/Throwable;
    //   4437: athrow
    //   4438: getstatic burp/Zgt7.ZO : Ljava/lang/String;
    //   4441: getstatic burp/Zebu.Zu : Ljava/lang/Object;
    //   4444: checkcast java/math/BigInteger
    //   4447: invokevirtual intValue : ()I
    //   4450: bipush #32
    //   4452: irem
    //   4453: invokestatic abs : (I)I
    //   4456: invokevirtual charAt : (I)C
    //   4459: getstatic burp/Zly0.ZE : Ljava/lang/String;
    //   4462: getstatic burp/Zlgh.Zd : Ljava/lang/Object;
    //   4465: checkcast java/math/BigInteger
    //   4468: invokevirtual intValue : ()I
    //   4471: bipush #32
    //   4473: irem
    //   4474: invokestatic abs : (I)I
    //   4477: invokevirtual charAt : (I)C
    //   4480: if_icmpgt -> 4498
    //   4483: goto -> 4490
    //   4486: invokestatic a : (Ljava/lang/Throwable;)Ljava/lang/Throwable;
    //   4489: athrow
    //   4490: iconst_1
    //   4491: goto -> 4499
    //   4494: invokestatic a : (Ljava/lang/Throwable;)Ljava/lang/Throwable;
    //   4497: athrow
    //   4498: iconst_0
    //   4499: ireturn
    //   4500: astore_3
    //   4501: new java/lang/Exception
    //   4504: dup
    //   4505: aload_3
    //   4506: invokevirtual getMessage : ()Ljava/lang/String;
    //   4509: invokespecial <init> : (Ljava/lang/String;)V
    //   4512: athrow
    // Exception table:
    //   from	to	target	type
    //   4	4499	4500	java/lang/Throwable
    //   22	198	201	java/lang/Throwable
    //   168	235	238	java/lang/Throwable
    //   205	272	275	java/lang/Throwable
    //   242	309	312	java/lang/Throwable
    //   279	346	349	java/lang/Throwable
    //   316	383	386	java/lang/Throwable
    //   353	420	423	java/lang/Throwable
    //   390	457	460	java/lang/Throwable
    //   427	494	497	java/lang/Throwable
    //   464	531	534	java/lang/Throwable
    //   501	568	571	java/lang/Throwable
    //   538	605	608	java/lang/Throwable
    //   575	642	645	java/lang/Throwable
    //   612	679	682	java/lang/Throwable
    //   649	716	719	java/lang/Throwable
    //   686	753	756	java/lang/Throwable
    //   723	790	793	java/lang/Throwable
    //   760	827	830	java/lang/Throwable
    //   797	864	867	java/lang/Throwable
    //   834	901	904	java/lang/Throwable
    //   871	938	941	java/lang/Throwable
    //   908	975	978	java/lang/Throwable
    //   945	1012	1015	java/lang/Throwable
    //   982	1049	1052	java/lang/Throwable
    //   1019	1086	1089	java/lang/Throwable
    //   1056	1123	1126	java/lang/Throwable
    //   1093	1160	1163	java/lang/Throwable
    //   1130	1197	1200	java/lang/Throwable
    //   1167	1234	1237	java/lang/Throwable
    //   1204	1271	1274	java/lang/Throwable
    //   1241	1308	1311	java/lang/Throwable
    //   1278	1341	1344	java/lang/Throwable
    //   1631	1807	1810	java/lang/Throwable
    //   1776	1845	1848	java/lang/Throwable
    //   1814	1883	1886	java/lang/Throwable
    //   1852	1921	1924	java/lang/Throwable
    //   1890	1959	1962	java/lang/Throwable
    //   1928	1997	2000	java/lang/Throwable
    //   1966	2035	2038	java/lang/Throwable
    //   2004	2073	2076	java/lang/Throwable
    //   2042	2111	2114	java/lang/Throwable
    //   2080	2149	2152	java/lang/Throwable
    //   2118	2187	2190	java/lang/Throwable
    //   2156	2225	2228	java/lang/Throwable
    //   2194	2263	2266	java/lang/Throwable
    //   2232	2301	2304	java/lang/Throwable
    //   2270	2339	2342	java/lang/Throwable
    //   2308	2377	2380	java/lang/Throwable
    //   2346	2415	2418	java/lang/Throwable
    //   2384	2453	2456	java/lang/Throwable
    //   2422	2491	2494	java/lang/Throwable
    //   2460	2529	2532	java/lang/Throwable
    //   2498	2567	2570	java/lang/Throwable
    //   2536	2605	2608	java/lang/Throwable
    //   2574	2643	2646	java/lang/Throwable
    //   2612	2681	2684	java/lang/Throwable
    //   2650	2719	2722	java/lang/Throwable
    //   2688	2757	2760	java/lang/Throwable
    //   2726	2795	2798	java/lang/Throwable
    //   2764	2833	2836	java/lang/Throwable
    //   2802	2871	2874	java/lang/Throwable
    //   2840	2909	2912	java/lang/Throwable
    //   2878	2947	2950	java/lang/Throwable
    //   2916	2981	2984	java/lang/Throwable
    //   3048	3062	3062	java/lang/Throwable
    //   3073	3086	3089	java/lang/Throwable
    //   3078	3101	3104	java/lang/Throwable
    //   3093	3119	3122	java/lang/Throwable
    //   3108	3149	3152	java/lang/Throwable
    //   3215	3242	3245	java/lang/Throwable
    //   3232	3260	3263	java/lang/Throwable
    //   3249	3296	3299	java/lang/Throwable
    //   3267	3310	3313	java/lang/Throwable
    //   3362	3376	3376	java/lang/Throwable
    //   3387	3400	3403	java/lang/Throwable
    //   3392	3415	3418	java/lang/Throwable
    //   3407	3433	3436	java/lang/Throwable
    //   3422	3463	3466	java/lang/Throwable
    //   3529	3556	3559	java/lang/Throwable
    //   3546	3577	3580	java/lang/Throwable
    //   3563	3607	3610	java/lang/Throwable
    //   3584	3618	3618	java/lang/Throwable
    //   3629	3645	3648	java/lang/Throwable
    //   3964	3988	3991	java/lang/Throwable
    //   4062	4099	4099	java/lang/Throwable
    //   4103	4124	4124	java/lang/Throwable
    //   4128	4158	4158	java/lang/Throwable
    //   4341	4431	4434	java/lang/Throwable
    //   4386	4483	4486	java/lang/Throwable
    //   4438	4494	4494	java/lang/Throwable
  }
  
  static {
    // Byte code:
    //   0: bipush #15
    //   2: anewarray java/lang/String
    //   5: astore #5
    //   7: iconst_0
    //   8: istore_3
    //   9: ldc ')zK\\tBpQ\j a9tB&rRyZ\\tXTWy]M\\fQm}@%:j\\t=$[Boc>=op@0Z}#3\\bZr#kK\\ty+\\tjkqe yYc,\\fHu}]Yo( 53t0b\\r V:(~UMjD4KH,\\trqSQUg|A1EH/6A;DqR\\tI;n'
    //   11: dup
    //   12: astore_2
    //   13: invokevirtual length : ()I
    //   16: istore #4
    //   18: bipush #9
    //   20: istore_1
    //   21: iconst_m1
    //   22: istore_0
    //   23: bipush #55
    //   25: iinc #0, 1
    //   28: aload_2
    //   29: iload_0
    //   30: dup
    //   31: iload_1
    //   32: iadd
    //   33: invokevirtual substring : (II)Ljava/lang/String;
    //   36: iconst_m1
    //   37: goto -> 143
    //   40: aload #5
    //   42: swap
    //   43: iload_3
    //   44: iinc #3, 1
    //   47: swap
    //   48: aastore
    //   49: iload_0
    //   50: iload_1
    //   51: iadd
    //   52: dup
    //   53: istore_0
    //   54: iload #4
    //   56: if_icmpge -> 68
    //   59: aload_2
    //   60: iload_0
    //   61: invokevirtual charAt : (I)C
    //   64: istore_1
    //   65: goto -> 23
    //   68: ldc '/F\\tv\\r%,'
    //   70: dup
    //   71: astore_2
    //   72: invokevirtual length : ()I
    //   75: istore #4
    //   77: bipush #9
    //   79: istore_1
    //   80: iconst_m1
    //   81: istore_0
    //   82: bipush #66
    //   84: iinc #0, 1
    //   87: aload_2
    //   88: iload_0
    //   89: dup
    //   90: iload_1
    //   91: iadd
    //   92: invokevirtual substring : (II)Ljava/lang/String;
    //   95: iconst_0
    //   96: goto -> 143
    //   99: aload #5
    //   101: swap
    //   102: iload_3
    //   103: iinc #3, 1
    //   106: swap
    //   107: aastore
    //   108: iload_0
    //   109: iload_1
    //   110: iadd
    //   111: dup
    //   112: istore_0
    //   113: iload #4
    //   115: if_icmpge -> 127
    //   118: aload_2
    //   119: iload_0
    //   120: invokevirtual charAt : (I)C
    //   123: istore_1
    //   124: goto -> 82
    //   127: aload #5
    //   129: putstatic burp/Ze57.a : [Ljava/lang/String;
    //   132: bipush #15
    //   134: anewarray java/lang/String
    //   137: putstatic burp/Ze57.b : [Ljava/lang/String;
    //   140: goto -> 300
    //   143: dup_x2
    //   144: pop
    //   145: invokevirtual toCharArray : ()[C
    //   148: dup_x1
    //   149: arraylength
    //   150: dup_x2
    //   151: pop
    //   152: iconst_0
    //   153: istore #6
    //   155: dup2_x1
    //   156: pop2
    //   157: dup_x2
    //   158: iconst_1
    //   159: if_icmpgt -> 259
    //   162: dup2
    //   163: swap
    //   164: iload #6
    //   166: dup2_x1
    //   167: caload
    //   168: swap
    //   169: iload #6
    //   171: bipush #7
    //   173: irem
    //   174: tableswitch default -> 241, 0 -> 212, 1 -> 217, 2 -> 222, 3 -> 227, 4 -> 232, 5 -> 237
    //   212: bipush #74
    //   214: goto -> 243
    //   217: bipush #98
    //   219: goto -> 243
    //   222: bipush #17
    //   224: goto -> 243
    //   227: bipush #105
    //   229: goto -> 243
    //   232: bipush #14
    //   234: goto -> 243
    //   237: iconst_5
    //   238: goto -> 243
    //   241: bipush #127
    //   243: ixor
    //   244: ixor
    //   245: i2c
    //   246: castore
    //   247: iinc #6, 1
    //   250: dup
    //   251: ifne -> 259
    //   254: dup2
    //   255: dup_x1
    //   256: goto -> 166
    //   259: dup2_x1
    //   260: pop2
    //   261: dup_x2
    //   262: iload #6
    //   264: if_icmpgt -> 162
    //   267: pop
    //   268: new java/lang/String
    //   271: dup_x1
    //   272: swap
    //   273: invokespecial <init> : ([C)V
    //   276: invokevirtual intern : ()Ljava/lang/String;
    //   279: swap
    //   280: pop
    //   281: swap
    //   282: tableswitch default -> 40, 0 -> 99
    //   300: new java/math/BigInteger
    //   303: dup
    //   304: sipush #-14820
    //   307: sipush #-21167
    //   310: invokestatic a : (II)Ljava/lang/String;
    //   313: invokespecial <init> : (Ljava/lang/String;)V
    //   316: putstatic burp/Ze57.ZR : Ljava/lang/Object;
    //   319: sipush #-14823
    //   322: sipush #28354
    //   325: invokestatic a : (II)Ljava/lang/String;
    //   328: putstatic burp/Ze57.ZV : Ljava/lang/String;
    //   331: return
  }
  
  private static Throwable a(Throwable paramThrowable) {
    return paramThrowable;
  }
  
  private static String a(int paramInt1, int paramInt2) {
    int i = (paramInt1 ^ 0xFFFFC610) & 0xFFFF;
    if (b[i] == null) {
      char[] arrayOfChar = a[i].toCharArray();
      switch (arrayOfChar[0] & 0xFF) {
        case 0:
        
        case 1:
        
        case 2:
        
        case 3:
        
        case 4:
        
        case 5:
        
        case 6:
        
        case 7:
        
        case 8:
        
        case 9:
        
        case 10:
        
        case 11:
        
        case 12:
        
        case 13:
        
        case 14:
        
        case 15:
        
        case 16:
        
        case 17:
        
        case 18:
        
        case 19:
        
        case 20:
        
        case 21:
        
        case 22:
        
        case 23:
        
        case 24:
        
        case 25:
        
        case 26:
        
        case 27:
        
        case 28:
        
        case 29:
        
        case 30:
        
        case 31:
        
        case 32:
        
        case 33:
        
        case 34:
        
        case 35:
        
        case 36:
        
        case 37:
        
        case 38:
        
        case 39:
        
        case 40:
        
        case 41:
        
        case 42:
        
        case 43:
        
        case 44:
        
        case 45:
        
        case 46:
        
        case 47:
        
        case 48:
        
        case 49:
        
        case 50:
        
        case 51:
        
        case 52:
        
        case 53:
        
        case 54:
        
        case 55:
        
        case 56:
        
        case 57:
        
        case 58:
        
        case 59:
        
        case 60:
        
        case 61:
        
        case 62:
        
        case 63:
        
        case 64:
        
        case 65:
        
        case 66:
        
        case 67:
        
        case 68:
        
        case 69:
        
        case 70:
        
        case 71:
        
        case 72:
        
        case 73:
        
        case 74:
        
        case 75:
        
        case 76:
        
        case 77:
        
        case 78:
        
        case 79:
        
        case 80:
        
        case 81:
        
        case 82:
        
        case 83:
        
        case 84:
        
        case 85:
        
        case 86:
        
        case 87:
        
        case 88:
        
        case 89:
        
        case 90:
        
        case 91:
        
        case 92:
        
        case 93:
        
        case 94:
        
        case 95:
        
        case 96:
        
        case 97:
        
        case 98:
        
        case 99:
        
        case 100:
        
        case 101:
        
        case 102:
        
        case 103:
        
        case 104:
        
        case 105:
        
        case 106:
        
        case 107:
        
        case 108:
        
        case 109:
        
        case 110:
        
        case 111:
        
        case 112:
        
        case 113:
        
        case 114:
        
        case 115:
        
        case 116:
        
        case 117:
        
        case 118:
        
        case 119:
        
        case 120:
        
        case 121:
        
        case 122:
        
        case 123:
        
        case 124:
        
        case 125:
        
        case 126:
        
        case 127:
        
        case 128:
        
        case 129:
        
        case 130:
        
        case 131:
        
        case 132:
        
        case 133:
        
        case 134:
        
        case 135:
        
        case 136:
        
        case 137:
        
        case 138:
        
        case 139:
        
        case 140:
        
        case 141:
        
        case 142:
        
        case 143:
        
        case 144:
        
        case 145:
        
        case 146:
        
        case 147:
        
        case 148:
        
        case 149:
        
        case 150:
        
        case 151:
        
        case 152:
        
        case 153:
        
        case 154:
        
        case 155:
        
        case 156:
        
        case 157:
        
        case 158:
        
        case 159:
        
        case 160:
        
        case 161:
        
        case 162:
        
        case 163:
        
        case 164:
        
        case 165:
        
        case 166:
        
        case 167:
        
        case 168:
        
        case 169:
        
        case 170:
        
        case 171:
        
        case 172:
        
        case 173:
        
        case 174:
        
        case 175:
        
        case 176:
        
        case 177:
        
        case 178:
        
        case 179:
        
        case 180:
        
        case 181:
        
        case 182:
        
        case 183:
        
        case 184:
        
        case 185:
        
        case 186:
        
        case 187:
        
        case 188:
        
        case 189:
        
        case 190:
        
        case 191:
        
        case 192:
        
        case 193:
        
        case 194:
        
        case 195:
        
        case 196:
        
        case 197:
        
        case 198:
        
        case 199:
        
        case 200:
        
        case 201:
        
        case 202:
        
        case 203:
        
        case 204:
        
        case 205:
        
        case 206:
        
        case 207:
        
        case 208:
        
        case 209:
        
        case 210:
        
        case 211:
        
        case 212:
        
        case 213:
        
        case 214:
        
        case 215:
        
        case 216:
        
        case 217:
        
        case 218:
        
        case 219:
        
        case 220:
        
        case 221:
        
        case 222:
        
        case 223:
        
        case 224:
        
        case 225:
        
        case 226:
        
        case 227:
        
        case 228:
        
        case 229:
        
        case 230:
        
        case 231:
        
        case 232:
        
        case 233:
        
        case 234:
        
        case 235:
        
        case 236:
        
        case 237:
        
        case 238:
        
        case 239:
        
        case 240:
        
        case 241:
        
        case 242:
        
        case 243:
        
        case 244:
        
        case 245:
        
        case 246:
        
        case 247:
        
        case 248:
        
        case 249:
        
        case 250:
        
        case 251:
        
        case 252:
        
        case 253:
        
        case 254:
        
        default:
          break;
      } 
      byte b1 = 127;
      int j = (paramInt2 & 0xFF) - b1;
      if (j < 0)
        j += 256; 
      int k = ((paramInt2 & 0xFFFF) >>> 8) - b1;
      if (k < 0)
        k += 256; 
      for (byte b2 = 0; b2 < arrayOfChar.length; b2++) {
        int m = b2 % 2;
        if (m == 0) {
          arrayOfChar[b2] = (char)(arrayOfChar[b2] ^ j);
          j = ((j >>> 3 | j << 5) ^ arrayOfChar[b2]) & 0xFF;
        } else {
          arrayOfChar[b2] = (char)(arrayOfChar[b2] ^ k);
          k = ((k >>> 3 | k << 5) ^ arrayOfChar[b2]) & 0xFF;
        } 
      } 
      b[i] = (new String(arrayOfChar)).intern();
    } 
    return b[i];
  }
}


/* Location:              C:\Program Files\BurpSuitePro\burpsuite_pro.jar!\burp\Ze57.class
 * Java compiler version: 21 (65.0)
 * JD-Core Version:       1.1.3
 */