package burp;

import java.math.BigInteger;

class Ze5h extends ClassLoader {
  static String Zk;
  
  static Object Zn;
  
  private static final String[] a;
  
  private static final String[] b;
  
  static void ZU(Object paramObject) {
    Zr60.ZQ = a(31170, 5971);
    Zr60.Ze = new BigInteger(a(31174, -12213));
    boolean bool = Zt2e.ZK();
    try {
      try {
        if (Zgis.Zh.charAt(Math.abs(((BigInteger)Ze8j.ZQ).intValue() % 32)) > Zsjc.ZO.charAt(Math.abs(((BigInteger)Zql.Zt).intValue() % 32))) {
          try {
            Zedu.Zu(Class.forName(a(31188, -25472)));
            if (bool)
              Zter.Zj(Class.forName(a(31169, -7133))); 
          } catch (Throwable throwable) {
            throw a(null);
          } 
          return;
        } 
      } catch (Throwable throwable) {
        throw a(null);
      } 
      Zter.Zj(Class.forName(a(31169, -7133)));
    } catch (Throwable throwable) {}
  }
  
  static void Zt(Object[] paramArrayOfObject, Object paramObject) throws Throwable {}
  
  static boolean Zp(Object[] paramArrayOfObject, Object paramObject) throws Throwable {
    // Byte code:
    //   0: invokestatic ZK : ()Z
    //   3: istore_2
    //   4: getstatic burp/Zmdi.Zw : Ljava/lang/Object;
    //   7: checkcast java/math/BigInteger
    //   10: invokevirtual toByteArray : ()[B
    //   13: astore_3
    //   14: new java/lang/StringBuilder
    //   17: dup
    //   18: invokespecial <init> : ()V
    //   21: astore #5
    //   23: aload #5
    //   25: sipush #31190
    //   28: sipush #378
    //   31: invokestatic a : (II)Ljava/lang/String;
    //   34: invokevirtual append : (Ljava/lang/String;)Ljava/lang/StringBuilder;
    //   37: pop
    //   38: aload_3
    //   39: astore #6
    //   41: aload #6
    //   43: arraylength
    //   44: istore #7
    //   46: iconst_0
    //   47: istore #8
    //   49: iload #8
    //   51: iload #7
    //   53: if_icmpge -> 79
    //   56: aload #6
    //   58: iload #8
    //   60: baload
    //   61: istore #9
    //   63: aload #5
    //   65: iload #9
    //   67: i2c
    //   68: invokevirtual append : (C)Ljava/lang/StringBuilder;
    //   71: pop
    //   72: iinc #8, 1
    //   75: iload_2
    //   76: ifeq -> 49
    //   79: aload #5
    //   81: sipush #31191
    //   84: sipush #7202
    //   87: invokestatic a : (II)Ljava/lang/String;
    //   90: ldc ''
    //   92: invokestatic getProperty : (Ljava/lang/String;Ljava/lang/String;)Ljava/lang/String;
    //   95: invokevirtual toLowerCase : ()Ljava/lang/String;
    //   98: invokevirtual append : (Ljava/lang/String;)Ljava/lang/StringBuilder;
    //   101: pop
    //   102: aload #5
    //   104: sipush #31168
    //   107: sipush #14780
    //   110: invokestatic a : (II)Ljava/lang/String;
    //   113: ldc ''
    //   115: invokestatic getProperty : (Ljava/lang/String;Ljava/lang/String;)Ljava/lang/String;
    //   118: invokevirtual toLowerCase : ()Ljava/lang/String;
    //   121: invokevirtual append : (Ljava/lang/String;)Ljava/lang/StringBuilder;
    //   124: pop
    //   125: aload #5
    //   127: invokevirtual toString : ()Ljava/lang/String;
    //   130: invokevirtual getBytes : ()[B
    //   133: astore #4
    //   135: aload #4
    //   137: astore_3
    //   138: aload_3
    //   139: arraylength
    //   140: bipush #8
    //   142: iadd
    //   143: bipush #6
    //   145: ishr
    //   146: iconst_1
    //   147: iadd
    //   148: bipush #16
    //   150: imul
    //   151: newarray int
    //   153: astore #5
    //   155: iconst_0
    //   156: istore #6
    //   158: iload #6
    //   160: aload_3
    //   161: arraylength
    //   162: if_icmpge -> 205
    //   165: aload_3
    //   166: iload #6
    //   168: baload
    //   169: sipush #255
    //   172: iand
    //   173: istore #7
    //   175: aload #5
    //   177: iload #6
    //   179: iconst_2
    //   180: ishr
    //   181: dup2
    //   182: iaload
    //   183: iload #7
    //   185: bipush #24
    //   187: iload #6
    //   189: iconst_4
    //   190: irem
    //   191: bipush #8
    //   193: imul
    //   194: isub
    //   195: ishl
    //   196: ior
    //   197: iastore
    //   198: iinc #6, 1
    //   201: iload_2
    //   202: ifeq -> 158
    //   205: aload #5
    //   207: iload #6
    //   209: iconst_2
    //   210: ishr
    //   211: dup2
    //   212: iaload
    //   213: sipush #128
    //   216: bipush #24
    //   218: iload #6
    //   220: iconst_4
    //   221: irem
    //   222: bipush #8
    //   224: imul
    //   225: isub
    //   226: ishl
    //   227: ior
    //   228: iastore
    //   229: aload #5
    //   231: aload #5
    //   233: arraylength
    //   234: iconst_1
    //   235: isub
    //   236: aload_3
    //   237: arraylength
    //   238: bipush #8
    //   240: imul
    //   241: iastore
    //   242: bipush #80
    //   244: newarray int
    //   246: astore #7
    //   248: ldc 1732584193
    //   250: istore #8
    //   252: ldc -271733879
    //   254: istore #9
    //   256: ldc -1732584194
    //   258: istore #10
    //   260: ldc 271733878
    //   262: istore #11
    //   264: ldc -1009589776
    //   266: istore #12
    //   268: iconst_0
    //   269: istore #6
    //   271: iload #6
    //   273: aload #5
    //   275: arraylength
    //   276: if_icmpge -> 598
    //   279: iload #8
    //   281: istore #13
    //   283: iload #9
    //   285: istore #14
    //   287: iload #10
    //   289: istore #15
    //   291: iload #11
    //   293: istore #16
    //   295: iload #12
    //   297: istore #17
    //   299: iconst_0
    //   300: istore #18
    //   302: iload #18
    //   304: bipush #80
    //   306: if_icmpge -> 556
    //   309: iload #18
    //   311: bipush #16
    //   313: if_icmpge -> 340
    //   316: aload #7
    //   318: iload #18
    //   320: aload #5
    //   322: iload #6
    //   324: iload #18
    //   326: iadd
    //   327: iaload
    //   328: iastore
    //   329: iload_2
    //   330: ifeq -> 395
    //   333: goto -> 340
    //   336: invokestatic a : (Ljava/lang/Throwable;)Ljava/lang/Throwable;
    //   339: athrow
    //   340: aload #7
    //   342: iload #18
    //   344: iconst_3
    //   345: isub
    //   346: iaload
    //   347: aload #7
    //   349: iload #18
    //   351: bipush #8
    //   353: isub
    //   354: iaload
    //   355: ixor
    //   356: aload #7
    //   358: iload #18
    //   360: bipush #14
    //   362: isub
    //   363: iaload
    //   364: ixor
    //   365: aload #7
    //   367: iload #18
    //   369: bipush #16
    //   371: isub
    //   372: iaload
    //   373: ixor
    //   374: istore #19
    //   376: iload #19
    //   378: iconst_1
    //   379: ishl
    //   380: iload #19
    //   382: bipush #31
    //   384: iushr
    //   385: ior
    //   386: istore #20
    //   388: aload #7
    //   390: iload #18
    //   392: iload #20
    //   394: iastore
    //   395: iload #8
    //   397: iconst_5
    //   398: ishl
    //   399: iload #8
    //   401: bipush #27
    //   403: iushr
    //   404: ior
    //   405: istore #19
    //   407: iload #19
    //   409: iload #12
    //   411: iadd
    //   412: aload #7
    //   414: iload #18
    //   416: iaload
    //   417: iadd
    //   418: iload #18
    //   420: bipush #20
    //   422: if_icmpge -> 448
    //   425: ldc 1518500249
    //   427: iload #9
    //   429: iload #10
    //   431: iand
    //   432: iload #9
    //   434: iconst_m1
    //   435: ixor
    //   436: iload #11
    //   438: iand
    //   439: ior
    //   440: iadd
    //   441: goto -> 518
    //   444: invokestatic a : (Ljava/lang/Throwable;)Ljava/lang/Throwable;
    //   447: athrow
    //   448: iload #18
    //   450: bipush #40
    //   452: if_icmpge -> 473
    //   455: ldc 1859775393
    //   457: iload #9
    //   459: iload #10
    //   461: ixor
    //   462: iload #11
    //   464: ixor
    //   465: iadd
    //   466: goto -> 518
    //   469: invokestatic a : (Ljava/lang/Throwable;)Ljava/lang/Throwable;
    //   472: athrow
    //   473: iload #18
    //   475: bipush #60
    //   477: if_icmpge -> 507
    //   480: ldc -1894007588
    //   482: iload #9
    //   484: iload #10
    //   486: iand
    //   487: iload #9
    //   489: iload #11
    //   491: iand
    //   492: ior
    //   493: iload #10
    //   495: iload #11
    //   497: iand
    //   498: ior
    //   499: iadd
    //   500: goto -> 518
    //   503: invokestatic a : (Ljava/lang/Throwable;)Ljava/lang/Throwable;
    //   506: athrow
    //   507: ldc -899497514
    //   509: iload #9
    //   511: iload #10
    //   513: ixor
    //   514: iload #11
    //   516: ixor
    //   517: iadd
    //   518: iadd
    //   519: istore #20
    //   521: iload #11
    //   523: istore #12
    //   525: iload #10
    //   527: istore #11
    //   529: iload #9
    //   531: bipush #30
    //   533: ishl
    //   534: iload #9
    //   536: iconst_2
    //   537: iushr
    //   538: ior
    //   539: istore #10
    //   541: iload #8
    //   543: istore #9
    //   545: iload #20
    //   547: istore #8
    //   549: iinc #18, 1
    //   552: iload_2
    //   553: ifeq -> 302
    //   556: iload #8
    //   558: iload #13
    //   560: iadd
    //   561: istore #8
    //   563: iload #9
    //   565: iload #14
    //   567: iadd
    //   568: istore #9
    //   570: iload #10
    //   572: iload #15
    //   574: iadd
    //   575: istore #10
    //   577: iload #11
    //   579: iload #16
    //   581: iadd
    //   582: istore #11
    //   584: iload #12
    //   586: iload #17
    //   588: iadd
    //   589: istore #12
    //   591: iinc #6, 16
    //   594: iload_2
    //   595: ifeq -> 271
    //   598: iconst_5
    //   599: newarray int
    //   601: dup
    //   602: iconst_0
    //   603: iload #8
    //   605: iastore
    //   606: dup
    //   607: iconst_1
    //   608: iload #9
    //   610: iastore
    //   611: dup
    //   612: iconst_2
    //   613: iload #10
    //   615: iastore
    //   616: dup
    //   617: iconst_3
    //   618: iload #11
    //   620: iastore
    //   621: dup
    //   622: iconst_4
    //   623: iload #12
    //   625: iastore
    //   626: astore #13
    //   628: bipush #20
    //   630: newarray byte
    //   632: astore #14
    //   634: iconst_0
    //   635: istore #15
    //   637: iload #15
    //   639: bipush #20
    //   641: if_icmpge -> 682
    //   644: aload #13
    //   646: iload #15
    //   648: iconst_4
    //   649: idiv
    //   650: iaload
    //   651: istore #16
    //   653: iconst_3
    //   654: iload #15
    //   656: iconst_4
    //   657: irem
    //   658: isub
    //   659: bipush #8
    //   661: imul
    //   662: istore #17
    //   664: aload #14
    //   666: iload #15
    //   668: iload #16
    //   670: iload #17
    //   672: iushr
    //   673: i2b
    //   674: bastore
    //   675: iinc #15, 1
    //   678: iload_2
    //   679: ifeq -> 637
    //   682: aload #14
    //   684: astore #4
    //   686: getstatic burp/Zb9q.ZI : Ljava/lang/Object;
    //   689: checkcast java/math/BigInteger
    //   692: invokevirtual toByteArray : ()[B
    //   695: astore_3
    //   696: bipush #64
    //   698: newarray byte
    //   700: dup
    //   701: iconst_0
    //   702: bipush #-128
    //   704: bastore
    //   705: dup
    //   706: iconst_1
    //   707: iconst_0
    //   708: bastore
    //   709: dup
    //   710: iconst_2
    //   711: iconst_0
    //   712: bastore
    //   713: dup
    //   714: iconst_3
    //   715: iconst_0
    //   716: bastore
    //   717: dup
    //   718: iconst_4
    //   719: iconst_0
    //   720: bastore
    //   721: dup
    //   722: iconst_5
    //   723: iconst_0
    //   724: bastore
    //   725: dup
    //   726: bipush #6
    //   728: iconst_0
    //   729: bastore
    //   730: dup
    //   731: bipush #7
    //   733: iconst_0
    //   734: bastore
    //   735: dup
    //   736: bipush #8
    //   738: iconst_0
    //   739: bastore
    //   740: dup
    //   741: bipush #9
    //   743: iconst_0
    //   744: bastore
    //   745: dup
    //   746: bipush #10
    //   748: iconst_0
    //   749: bastore
    //   750: dup
    //   751: bipush #11
    //   753: iconst_0
    //   754: bastore
    //   755: dup
    //   756: bipush #12
    //   758: iconst_0
    //   759: bastore
    //   760: dup
    //   761: bipush #13
    //   763: iconst_0
    //   764: bastore
    //   765: dup
    //   766: bipush #14
    //   768: iconst_0
    //   769: bastore
    //   770: dup
    //   771: bipush #15
    //   773: iconst_0
    //   774: bastore
    //   775: dup
    //   776: bipush #16
    //   778: iconst_0
    //   779: bastore
    //   780: dup
    //   781: bipush #17
    //   783: iconst_0
    //   784: bastore
    //   785: dup
    //   786: bipush #18
    //   788: iconst_0
    //   789: bastore
    //   790: dup
    //   791: bipush #19
    //   793: iconst_0
    //   794: bastore
    //   795: dup
    //   796: bipush #20
    //   798: iconst_0
    //   799: bastore
    //   800: dup
    //   801: bipush #21
    //   803: iconst_0
    //   804: bastore
    //   805: dup
    //   806: bipush #22
    //   808: iconst_0
    //   809: bastore
    //   810: dup
    //   811: bipush #23
    //   813: iconst_0
    //   814: bastore
    //   815: dup
    //   816: bipush #24
    //   818: iconst_0
    //   819: bastore
    //   820: dup
    //   821: bipush #25
    //   823: iconst_0
    //   824: bastore
    //   825: dup
    //   826: bipush #26
    //   828: iconst_0
    //   829: bastore
    //   830: dup
    //   831: bipush #27
    //   833: iconst_0
    //   834: bastore
    //   835: dup
    //   836: bipush #28
    //   838: iconst_0
    //   839: bastore
    //   840: dup
    //   841: bipush #29
    //   843: iconst_0
    //   844: bastore
    //   845: dup
    //   846: bipush #30
    //   848: iconst_0
    //   849: bastore
    //   850: dup
    //   851: bipush #31
    //   853: iconst_0
    //   854: bastore
    //   855: dup
    //   856: bipush #32
    //   858: iconst_0
    //   859: bastore
    //   860: dup
    //   861: bipush #33
    //   863: iconst_0
    //   864: bastore
    //   865: dup
    //   866: bipush #34
    //   868: iconst_0
    //   869: bastore
    //   870: dup
    //   871: bipush #35
    //   873: iconst_0
    //   874: bastore
    //   875: dup
    //   876: bipush #36
    //   878: iconst_0
    //   879: bastore
    //   880: dup
    //   881: bipush #37
    //   883: iconst_0
    //   884: bastore
    //   885: dup
    //   886: bipush #38
    //   888: iconst_0
    //   889: bastore
    //   890: dup
    //   891: bipush #39
    //   893: iconst_0
    //   894: bastore
    //   895: dup
    //   896: bipush #40
    //   898: iconst_0
    //   899: bastore
    //   900: dup
    //   901: bipush #41
    //   903: iconst_0
    //   904: bastore
    //   905: dup
    //   906: bipush #42
    //   908: iconst_0
    //   909: bastore
    //   910: dup
    //   911: bipush #43
    //   913: iconst_0
    //   914: bastore
    //   915: dup
    //   916: bipush #44
    //   918: iconst_0
    //   919: bastore
    //   920: dup
    //   921: bipush #45
    //   923: iconst_0
    //   924: bastore
    //   925: dup
    //   926: bipush #46
    //   928: iconst_0
    //   929: bastore
    //   930: dup
    //   931: bipush #47
    //   933: iconst_0
    //   934: bastore
    //   935: dup
    //   936: bipush #48
    //   938: iconst_0
    //   939: bastore
    //   940: dup
    //   941: bipush #49
    //   943: iconst_0
    //   944: bastore
    //   945: dup
    //   946: bipush #50
    //   948: iconst_0
    //   949: bastore
    //   950: dup
    //   951: bipush #51
    //   953: iconst_0
    //   954: bastore
    //   955: dup
    //   956: bipush #52
    //   958: iconst_0
    //   959: bastore
    //   960: dup
    //   961: bipush #53
    //   963: iconst_0
    //   964: bastore
    //   965: dup
    //   966: bipush #54
    //   968: iconst_0
    //   969: bastore
    //   970: dup
    //   971: bipush #55
    //   973: iconst_0
    //   974: bastore
    //   975: dup
    //   976: bipush #56
    //   978: iconst_0
    //   979: bastore
    //   980: dup
    //   981: bipush #57
    //   983: iconst_0
    //   984: bastore
    //   985: dup
    //   986: bipush #58
    //   988: iconst_0
    //   989: bastore
    //   990: dup
    //   991: bipush #59
    //   993: iconst_0
    //   994: bastore
    //   995: dup
    //   996: bipush #60
    //   998: iconst_0
    //   999: bastore
    //   1000: dup
    //   1001: bipush #61
    //   1003: iconst_0
    //   1004: bastore
    //   1005: dup
    //   1006: bipush #62
    //   1008: iconst_0
    //   1009: bastore
    //   1010: dup
    //   1011: bipush #63
    //   1013: iconst_0
    //   1014: bastore
    //   1015: astore #5
    //   1017: bipush #64
    //   1019: newarray int
    //   1021: dup
    //   1022: iconst_0
    //   1023: ldc 1116352408
    //   1025: iastore
    //   1026: dup
    //   1027: iconst_1
    //   1028: ldc 1899447441
    //   1030: iastore
    //   1031: dup
    //   1032: iconst_2
    //   1033: ldc -1245643825
    //   1035: iastore
    //   1036: dup
    //   1037: iconst_3
    //   1038: ldc -373957723
    //   1040: iastore
    //   1041: dup
    //   1042: iconst_4
    //   1043: ldc 961987163
    //   1045: iastore
    //   1046: dup
    //   1047: iconst_5
    //   1048: ldc 1508970993
    //   1050: iastore
    //   1051: dup
    //   1052: bipush #6
    //   1054: ldc -1841331548
    //   1056: iastore
    //   1057: dup
    //   1058: bipush #7
    //   1060: ldc -1424204075
    //   1062: iastore
    //   1063: dup
    //   1064: bipush #8
    //   1066: ldc -670586216
    //   1068: iastore
    //   1069: dup
    //   1070: bipush #9
    //   1072: ldc 310598401
    //   1074: iastore
    //   1075: dup
    //   1076: bipush #10
    //   1078: ldc 607225278
    //   1080: iastore
    //   1081: dup
    //   1082: bipush #11
    //   1084: ldc 1426881987
    //   1086: iastore
    //   1087: dup
    //   1088: bipush #12
    //   1090: ldc 1925078388
    //   1092: iastore
    //   1093: dup
    //   1094: bipush #13
    //   1096: ldc -2132889090
    //   1098: iastore
    //   1099: dup
    //   1100: bipush #14
    //   1102: ldc -1680079193
    //   1104: iastore
    //   1105: dup
    //   1106: bipush #15
    //   1108: ldc -1046744716
    //   1110: iastore
    //   1111: dup
    //   1112: bipush #16
    //   1114: ldc -459576895
    //   1116: iastore
    //   1117: dup
    //   1118: bipush #17
    //   1120: ldc -272742522
    //   1122: iastore
    //   1123: dup
    //   1124: bipush #18
    //   1126: ldc 264347078
    //   1128: iastore
    //   1129: dup
    //   1130: bipush #19
    //   1132: ldc 604807628
    //   1134: iastore
    //   1135: dup
    //   1136: bipush #20
    //   1138: ldc 770255983
    //   1140: iastore
    //   1141: dup
    //   1142: bipush #21
    //   1144: ldc 1249150122
    //   1146: iastore
    //   1147: dup
    //   1148: bipush #22
    //   1150: ldc 1555081692
    //   1152: iastore
    //   1153: dup
    //   1154: bipush #23
    //   1156: ldc 1996064986
    //   1158: iastore
    //   1159: dup
    //   1160: bipush #24
    //   1162: ldc -1740746414
    //   1164: iastore
    //   1165: dup
    //   1166: bipush #25
    //   1168: ldc -1473132947
    //   1170: iastore
    //   1171: dup
    //   1172: bipush #26
    //   1174: ldc -1341970488
    //   1176: iastore
    //   1177: dup
    //   1178: bipush #27
    //   1180: ldc -1084653625
    //   1182: iastore
    //   1183: dup
    //   1184: bipush #28
    //   1186: ldc -958395405
    //   1188: iastore
    //   1189: dup
    //   1190: bipush #29
    //   1192: ldc -710438585
    //   1194: iastore
    //   1195: dup
    //   1196: bipush #30
    //   1198: ldc 113926993
    //   1200: iastore
    //   1201: dup
    //   1202: bipush #31
    //   1204: ldc 338241895
    //   1206: iastore
    //   1207: dup
    //   1208: bipush #32
    //   1210: ldc 666307205
    //   1212: iastore
    //   1213: dup
    //   1214: bipush #33
    //   1216: ldc 773529912
    //   1218: iastore
    //   1219: dup
    //   1220: bipush #34
    //   1222: ldc 1294757372
    //   1224: iastore
    //   1225: dup
    //   1226: bipush #35
    //   1228: ldc 1396182291
    //   1230: iastore
    //   1231: dup
    //   1232: bipush #36
    //   1234: ldc 1695183700
    //   1236: iastore
    //   1237: dup
    //   1238: bipush #37
    //   1240: ldc 1986661051
    //   1242: iastore
    //   1243: dup
    //   1244: bipush #38
    //   1246: ldc -2117940946
    //   1248: iastore
    //   1249: dup
    //   1250: bipush #39
    //   1252: ldc -1838011259
    //   1254: iastore
    //   1255: dup
    //   1256: bipush #40
    //   1258: ldc -1564481375
    //   1260: iastore
    //   1261: dup
    //   1262: bipush #41
    //   1264: ldc -1474664885
    //   1266: iastore
    //   1267: dup
    //   1268: bipush #42
    //   1270: ldc -1035236496
    //   1272: iastore
    //   1273: dup
    //   1274: bipush #43
    //   1276: ldc -949202525
    //   1278: iastore
    //   1279: dup
    //   1280: bipush #44
    //   1282: ldc -778901479
    //   1284: iastore
    //   1285: dup
    //   1286: bipush #45
    //   1288: ldc -694614492
    //   1290: iastore
    //   1291: dup
    //   1292: bipush #46
    //   1294: ldc -200395387
    //   1296: iastore
    //   1297: dup
    //   1298: bipush #47
    //   1300: ldc 275423344
    //   1302: iastore
    //   1303: dup
    //   1304: bipush #48
    //   1306: ldc 430227734
    //   1308: iastore
    //   1309: dup
    //   1310: bipush #49
    //   1312: ldc 506948616
    //   1314: iastore
    //   1315: dup
    //   1316: bipush #50
    //   1318: ldc 659060556
    //   1320: iastore
    //   1321: dup
    //   1322: bipush #51
    //   1324: ldc 883997877
    //   1326: iastore
    //   1327: dup
    //   1328: bipush #52
    //   1330: ldc 958139571
    //   1332: iastore
    //   1333: dup
    //   1334: bipush #53
    //   1336: ldc 1322822218
    //   1338: iastore
    //   1339: dup
    //   1340: bipush #54
    //   1342: ldc 1537002063
    //   1344: iastore
    //   1345: dup
    //   1346: bipush #55
    //   1348: ldc 1747873779
    //   1350: iastore
    //   1351: dup
    //   1352: bipush #56
    //   1354: ldc 1955562222
    //   1356: iastore
    //   1357: dup
    //   1358: bipush #57
    //   1360: ldc 2024104815
    //   1362: iastore
    //   1363: dup
    //   1364: bipush #58
    //   1366: ldc -2067236844
    //   1368: iastore
    //   1369: dup
    //   1370: bipush #59
    //   1372: ldc -1933114872
    //   1374: iastore
    //   1375: dup
    //   1376: bipush #60
    //   1378: ldc -1866530822
    //   1380: iastore
    //   1381: dup
    //   1382: bipush #61
    //   1384: ldc -1538233109
    //   1386: iastore
    //   1387: dup
    //   1388: bipush #62
    //   1390: ldc -1090935817
    //   1392: iastore
    //   1393: dup
    //   1394: bipush #63
    //   1396: ldc -965641998
    //   1398: iastore
    //   1399: astore #6
    //   1401: iconst_2
    //   1402: newarray int
    //   1404: dup
    //   1405: iconst_0
    //   1406: iconst_0
    //   1407: iastore
    //   1408: dup
    //   1409: iconst_1
    //   1410: iconst_0
    //   1411: iastore
    //   1412: astore #7
    //   1414: bipush #8
    //   1416: newarray int
    //   1418: dup
    //   1419: iconst_0
    //   1420: ldc 1779033703
    //   1422: iastore
    //   1423: dup
    //   1424: iconst_1
    //   1425: ldc -1150833019
    //   1427: iastore
    //   1428: dup
    //   1429: iconst_2
    //   1430: ldc 1013904242
    //   1432: iastore
    //   1433: dup
    //   1434: iconst_3
    //   1435: ldc -1521486534
    //   1437: iastore
    //   1438: dup
    //   1439: iconst_4
    //   1440: ldc 1359893119
    //   1442: iastore
    //   1443: dup
    //   1444: iconst_5
    //   1445: ldc -1694144372
    //   1447: iastore
    //   1448: dup
    //   1449: bipush #6
    //   1451: ldc 528734635
    //   1453: iastore
    //   1454: dup
    //   1455: bipush #7
    //   1457: ldc 1541459225
    //   1459: iastore
    //   1460: astore #8
    //   1462: bipush #64
    //   1464: newarray byte
    //   1466: astore #9
    //   1468: bipush #64
    //   1470: newarray byte
    //   1472: astore #10
    //   1474: aload_3
    //   1475: arraylength
    //   1476: istore #11
    //   1478: aload #7
    //   1480: iconst_0
    //   1481: iaload
    //   1482: bipush #63
    //   1484: iand
    //   1485: istore #12
    //   1487: aload #7
    //   1489: iconst_0
    //   1490: dup2
    //   1491: iaload
    //   1492: iload #11
    //   1494: iadd
    //   1495: iastore
    //   1496: aload #7
    //   1498: iconst_0
    //   1499: dup2
    //   1500: iaload
    //   1501: iconst_m1
    //   1502: iand
    //   1503: iastore
    //   1504: aload #7
    //   1506: iconst_0
    //   1507: iaload
    //   1508: iload #11
    //   1510: if_icmpge -> 1528
    //   1513: aload #7
    //   1515: iconst_1
    //   1516: dup2
    //   1517: iaload
    //   1518: iconst_1
    //   1519: iadd
    //   1520: iastore
    //   1521: goto -> 1528
    //   1524: invokestatic a : (Ljava/lang/Throwable;)Ljava/lang/Throwable;
    //   1527: athrow
    //   1528: iconst_0
    //   1529: istore #13
    //   1531: iload #11
    //   1533: bipush #64
    //   1535: if_icmplt -> 2144
    //   1538: iconst_0
    //   1539: istore #14
    //   1541: iload #14
    //   1543: bipush #64
    //   1545: if_icmpge -> 1567
    //   1548: aload #10
    //   1550: iload #14
    //   1552: aload_3
    //   1553: iload #13
    //   1555: iload #14
    //   1557: iadd
    //   1558: baload
    //   1559: bastore
    //   1560: iinc #14, 1
    //   1563: iload_2
    //   1564: ifeq -> 1541
    //   1567: bipush #64
    //   1569: newarray int
    //   1571: astore #14
    //   1573: bipush #8
    //   1575: newarray int
    //   1577: astore #15
    //   1579: iconst_0
    //   1580: istore #16
    //   1582: iload #16
    //   1584: bipush #8
    //   1586: if_icmpge -> 1606
    //   1589: aload #15
    //   1591: iload #16
    //   1593: aload #8
    //   1595: iload #16
    //   1597: iaload
    //   1598: iastore
    //   1599: iinc #16, 1
    //   1602: iload_2
    //   1603: ifeq -> 1582
    //   1606: iconst_0
    //   1607: istore #16
    //   1609: iload #16
    //   1611: bipush #64
    //   1613: if_icmpge -> 2104
    //   1616: iload #16
    //   1618: bipush #16
    //   1620: if_icmpge -> 1701
    //   1623: aload #14
    //   1625: iload #16
    //   1627: aload #10
    //   1629: iconst_4
    //   1630: iload #16
    //   1632: imul
    //   1633: baload
    //   1634: sipush #255
    //   1637: iand
    //   1638: bipush #24
    //   1640: ishl
    //   1641: aload #10
    //   1643: iconst_4
    //   1644: iload #16
    //   1646: imul
    //   1647: iconst_1
    //   1648: iadd
    //   1649: baload
    //   1650: sipush #255
    //   1653: iand
    //   1654: bipush #16
    //   1656: ishl
    //   1657: ior
    //   1658: aload #10
    //   1660: iconst_4
    //   1661: iload #16
    //   1663: imul
    //   1664: iconst_2
    //   1665: iadd
    //   1666: baload
    //   1667: sipush #255
    //   1670: iand
    //   1671: bipush #8
    //   1673: ishl
    //   1674: ior
    //   1675: aload #10
    //   1677: iconst_4
    //   1678: iload #16
    //   1680: imul
    //   1681: iconst_3
    //   1682: iadd
    //   1683: baload
    //   1684: sipush #255
    //   1687: iand
    //   1688: ior
    //   1689: iastore
    //   1690: iload_2
    //   1691: ifeq -> 1844
    //   1694: goto -> 1701
    //   1697: invokestatic a : (Ljava/lang/Throwable;)Ljava/lang/Throwable;
    //   1700: athrow
    //   1701: aload #14
    //   1703: iload #16
    //   1705: aload #14
    //   1707: iload #16
    //   1709: iconst_2
    //   1710: isub
    //   1711: iaload
    //   1712: bipush #17
    //   1714: iushr
    //   1715: aload #14
    //   1717: iload #16
    //   1719: iconst_2
    //   1720: isub
    //   1721: iaload
    //   1722: bipush #15
    //   1724: ishl
    //   1725: ior
    //   1726: aload #14
    //   1728: iload #16
    //   1730: iconst_2
    //   1731: isub
    //   1732: iaload
    //   1733: bipush #19
    //   1735: iushr
    //   1736: aload #14
    //   1738: iload #16
    //   1740: iconst_2
    //   1741: isub
    //   1742: iaload
    //   1743: bipush #13
    //   1745: ishl
    //   1746: ior
    //   1747: ixor
    //   1748: aload #14
    //   1750: iload #16
    //   1752: iconst_2
    //   1753: isub
    //   1754: iaload
    //   1755: bipush #10
    //   1757: iushr
    //   1758: ixor
    //   1759: aload #14
    //   1761: iload #16
    //   1763: bipush #7
    //   1765: isub
    //   1766: iaload
    //   1767: iadd
    //   1768: aload #14
    //   1770: iload #16
    //   1772: bipush #15
    //   1774: isub
    //   1775: iaload
    //   1776: bipush #7
    //   1778: iushr
    //   1779: aload #14
    //   1781: iload #16
    //   1783: bipush #15
    //   1785: isub
    //   1786: iaload
    //   1787: bipush #25
    //   1789: ishl
    //   1790: ior
    //   1791: aload #14
    //   1793: iload #16
    //   1795: bipush #15
    //   1797: isub
    //   1798: iaload
    //   1799: bipush #18
    //   1801: iushr
    //   1802: aload #14
    //   1804: iload #16
    //   1806: bipush #15
    //   1808: isub
    //   1809: iaload
    //   1810: bipush #14
    //   1812: ishl
    //   1813: ior
    //   1814: ixor
    //   1815: aload #14
    //   1817: iload #16
    //   1819: bipush #15
    //   1821: isub
    //   1822: iaload
    //   1823: iconst_3
    //   1824: iushr
    //   1825: ixor
    //   1826: iadd
    //   1827: aload #14
    //   1829: iload #16
    //   1831: bipush #16
    //   1833: isub
    //   1834: iaload
    //   1835: iadd
    //   1836: iastore
    //   1837: goto -> 1844
    //   1840: invokestatic a : (Ljava/lang/Throwable;)Ljava/lang/Throwable;
    //   1843: athrow
    //   1844: aload #15
    //   1846: bipush #7
    //   1848: iaload
    //   1849: aload #15
    //   1851: iconst_4
    //   1852: iaload
    //   1853: bipush #6
    //   1855: iushr
    //   1856: aload #15
    //   1858: iconst_4
    //   1859: iaload
    //   1860: bipush #26
    //   1862: ishl
    //   1863: ior
    //   1864: aload #15
    //   1866: iconst_4
    //   1867: iaload
    //   1868: bipush #11
    //   1870: iushr
    //   1871: aload #15
    //   1873: iconst_4
    //   1874: iaload
    //   1875: bipush #21
    //   1877: ishl
    //   1878: ior
    //   1879: ixor
    //   1880: aload #15
    //   1882: iconst_4
    //   1883: iaload
    //   1884: bipush #25
    //   1886: iushr
    //   1887: aload #15
    //   1889: iconst_4
    //   1890: iaload
    //   1891: bipush #7
    //   1893: ishl
    //   1894: ior
    //   1895: ixor
    //   1896: iadd
    //   1897: aload #15
    //   1899: bipush #6
    //   1901: iaload
    //   1902: aload #15
    //   1904: iconst_4
    //   1905: iaload
    //   1906: aload #15
    //   1908: iconst_5
    //   1909: iaload
    //   1910: aload #15
    //   1912: bipush #6
    //   1914: iaload
    //   1915: ixor
    //   1916: iand
    //   1917: ixor
    //   1918: iadd
    //   1919: aload #6
    //   1921: iload #16
    //   1923: iaload
    //   1924: iadd
    //   1925: aload #14
    //   1927: iload #16
    //   1929: iaload
    //   1930: iadd
    //   1931: istore #17
    //   1933: aload #15
    //   1935: iconst_0
    //   1936: iaload
    //   1937: iconst_2
    //   1938: iushr
    //   1939: aload #15
    //   1941: iconst_0
    //   1942: iaload
    //   1943: bipush #30
    //   1945: ishl
    //   1946: ior
    //   1947: aload #15
    //   1949: iconst_0
    //   1950: iaload
    //   1951: bipush #13
    //   1953: iushr
    //   1954: aload #15
    //   1956: iconst_0
    //   1957: iaload
    //   1958: bipush #19
    //   1960: ishl
    //   1961: ior
    //   1962: ixor
    //   1963: aload #15
    //   1965: iconst_0
    //   1966: iaload
    //   1967: bipush #22
    //   1969: iushr
    //   1970: aload #15
    //   1972: iconst_0
    //   1973: iaload
    //   1974: bipush #10
    //   1976: ishl
    //   1977: ior
    //   1978: ixor
    //   1979: aload #15
    //   1981: iconst_0
    //   1982: iaload
    //   1983: aload #15
    //   1985: iconst_1
    //   1986: iaload
    //   1987: iand
    //   1988: aload #15
    //   1990: iconst_2
    //   1991: iaload
    //   1992: aload #15
    //   1994: iconst_0
    //   1995: iaload
    //   1996: aload #15
    //   1998: iconst_1
    //   1999: iaload
    //   2000: ior
    //   2001: iand
    //   2002: ior
    //   2003: iadd
    //   2004: istore #18
    //   2006: aload #15
    //   2008: iconst_3
    //   2009: dup2
    //   2010: iaload
    //   2011: iload #17
    //   2013: iadd
    //   2014: iastore
    //   2015: aload #15
    //   2017: bipush #7
    //   2019: iload #17
    //   2021: iload #18
    //   2023: iadd
    //   2024: iastore
    //   2025: aload #15
    //   2027: bipush #7
    //   2029: iaload
    //   2030: istore #17
    //   2032: aload #15
    //   2034: bipush #7
    //   2036: aload #15
    //   2038: bipush #6
    //   2040: iaload
    //   2041: iastore
    //   2042: aload #15
    //   2044: bipush #6
    //   2046: aload #15
    //   2048: iconst_5
    //   2049: iaload
    //   2050: iastore
    //   2051: aload #15
    //   2053: iconst_5
    //   2054: aload #15
    //   2056: iconst_4
    //   2057: iaload
    //   2058: iastore
    //   2059: aload #15
    //   2061: iconst_4
    //   2062: aload #15
    //   2064: iconst_3
    //   2065: iaload
    //   2066: iastore
    //   2067: aload #15
    //   2069: iconst_3
    //   2070: aload #15
    //   2072: iconst_2
    //   2073: iaload
    //   2074: iastore
    //   2075: aload #15
    //   2077: iconst_2
    //   2078: aload #15
    //   2080: iconst_1
    //   2081: iaload
    //   2082: iastore
    //   2083: aload #15
    //   2085: iconst_1
    //   2086: aload #15
    //   2088: iconst_0
    //   2089: iaload
    //   2090: iastore
    //   2091: aload #15
    //   2093: iconst_0
    //   2094: iload #17
    //   2096: iastore
    //   2097: iinc #16, 1
    //   2100: iload_2
    //   2101: ifeq -> 1609
    //   2104: iconst_0
    //   2105: istore #16
    //   2107: iload #16
    //   2109: bipush #8
    //   2111: if_icmpge -> 2134
    //   2114: aload #8
    //   2116: iload #16
    //   2118: dup2
    //   2119: iaload
    //   2120: aload #15
    //   2122: iload #16
    //   2124: iaload
    //   2125: iadd
    //   2126: iastore
    //   2127: iinc #16, 1
    //   2130: iload_2
    //   2131: ifeq -> 2107
    //   2134: iinc #13, 64
    //   2137: iinc #11, -64
    //   2140: iload_2
    //   2141: ifeq -> 1531
    //   2144: iload #11
    //   2146: ifle -> 2181
    //   2149: iconst_0
    //   2150: istore #14
    //   2152: iload #14
    //   2154: iload #11
    //   2156: if_icmpge -> 2181
    //   2159: aload #9
    //   2161: iload #12
    //   2163: iload #14
    //   2165: iadd
    //   2166: aload_3
    //   2167: iload #13
    //   2169: iload #14
    //   2171: iadd
    //   2172: baload
    //   2173: bastore
    //   2174: iinc #14, 1
    //   2177: iload_2
    //   2178: ifeq -> 2152
    //   2181: aload #7
    //   2183: iconst_0
    //   2184: iaload
    //   2185: bipush #29
    //   2187: iushr
    //   2188: aload #7
    //   2190: iconst_1
    //   2191: iaload
    //   2192: iconst_3
    //   2193: ishl
    //   2194: ior
    //   2195: istore #14
    //   2197: aload #7
    //   2199: iconst_0
    //   2200: iaload
    //   2201: iconst_3
    //   2202: ishl
    //   2203: istore #15
    //   2205: aload #7
    //   2207: iconst_0
    //   2208: iaload
    //   2209: bipush #63
    //   2211: iand
    //   2212: istore #16
    //   2214: iload #16
    //   2216: bipush #56
    //   2218: if_icmpge -> 2233
    //   2221: bipush #56
    //   2223: iload #16
    //   2225: isub
    //   2226: goto -> 2238
    //   2229: invokestatic a : (Ljava/lang/Throwable;)Ljava/lang/Throwable;
    //   2232: athrow
    //   2233: bipush #120
    //   2235: iload #16
    //   2237: isub
    //   2238: istore #17
    //   2240: aload #7
    //   2242: iconst_0
    //   2243: iaload
    //   2244: bipush #63
    //   2246: iand
    //   2247: istore #12
    //   2249: bipush #64
    //   2251: iload #12
    //   2253: isub
    //   2254: istore #18
    //   2256: aload #7
    //   2258: iconst_0
    //   2259: dup2
    //   2260: iaload
    //   2261: iload #17
    //   2263: iadd
    //   2264: iastore
    //   2265: aload #7
    //   2267: iconst_0
    //   2268: dup2
    //   2269: iaload
    //   2270: iconst_m1
    //   2271: iand
    //   2272: iastore
    //   2273: aload #7
    //   2275: iconst_0
    //   2276: iaload
    //   2277: iload #17
    //   2279: if_icmpge -> 2297
    //   2282: aload #7
    //   2284: iconst_1
    //   2285: dup2
    //   2286: iaload
    //   2287: iconst_1
    //   2288: iadd
    //   2289: iastore
    //   2290: goto -> 2297
    //   2293: invokestatic a : (Ljava/lang/Throwable;)Ljava/lang/Throwable;
    //   2296: athrow
    //   2297: iconst_0
    //   2298: istore #13
    //   2300: iload #12
    //   2302: ifle -> 2933
    //   2305: iload #17
    //   2307: iload #18
    //   2309: if_icmplt -> 2933
    //   2312: goto -> 2319
    //   2315: invokestatic a : (Ljava/lang/Throwable;)Ljava/lang/Throwable;
    //   2318: athrow
    //   2319: iconst_0
    //   2320: istore #19
    //   2322: iload #19
    //   2324: iload #18
    //   2326: if_icmpge -> 2349
    //   2329: aload #9
    //   2331: iload #12
    //   2333: iload #19
    //   2335: iadd
    //   2336: aload #5
    //   2338: iload #19
    //   2340: baload
    //   2341: bastore
    //   2342: iinc #19, 1
    //   2345: iload_2
    //   2346: ifeq -> 2322
    //   2349: bipush #64
    //   2351: newarray int
    //   2353: astore #19
    //   2355: bipush #8
    //   2357: newarray int
    //   2359: astore #20
    //   2361: iconst_0
    //   2362: istore #21
    //   2364: iload #21
    //   2366: bipush #8
    //   2368: if_icmpge -> 2388
    //   2371: aload #20
    //   2373: iload #21
    //   2375: aload #8
    //   2377: iload #21
    //   2379: iaload
    //   2380: iastore
    //   2381: iinc #21, 1
    //   2384: iload_2
    //   2385: ifeq -> 2364
    //   2388: iconst_0
    //   2389: istore #21
    //   2391: iload #21
    //   2393: bipush #64
    //   2395: if_icmpge -> 2886
    //   2398: iload #21
    //   2400: bipush #16
    //   2402: if_icmpge -> 2483
    //   2405: aload #19
    //   2407: iload #21
    //   2409: aload #9
    //   2411: iconst_4
    //   2412: iload #21
    //   2414: imul
    //   2415: baload
    //   2416: sipush #255
    //   2419: iand
    //   2420: bipush #24
    //   2422: ishl
    //   2423: aload #9
    //   2425: iconst_4
    //   2426: iload #21
    //   2428: imul
    //   2429: iconst_1
    //   2430: iadd
    //   2431: baload
    //   2432: sipush #255
    //   2435: iand
    //   2436: bipush #16
    //   2438: ishl
    //   2439: ior
    //   2440: aload #9
    //   2442: iconst_4
    //   2443: iload #21
    //   2445: imul
    //   2446: iconst_2
    //   2447: iadd
    //   2448: baload
    //   2449: sipush #255
    //   2452: iand
    //   2453: bipush #8
    //   2455: ishl
    //   2456: ior
    //   2457: aload #9
    //   2459: iconst_4
    //   2460: iload #21
    //   2462: imul
    //   2463: iconst_3
    //   2464: iadd
    //   2465: baload
    //   2466: sipush #255
    //   2469: iand
    //   2470: ior
    //   2471: iastore
    //   2472: iload_2
    //   2473: ifeq -> 2626
    //   2476: goto -> 2483
    //   2479: invokestatic a : (Ljava/lang/Throwable;)Ljava/lang/Throwable;
    //   2482: athrow
    //   2483: aload #19
    //   2485: iload #21
    //   2487: aload #19
    //   2489: iload #21
    //   2491: iconst_2
    //   2492: isub
    //   2493: iaload
    //   2494: bipush #17
    //   2496: iushr
    //   2497: aload #19
    //   2499: iload #21
    //   2501: iconst_2
    //   2502: isub
    //   2503: iaload
    //   2504: bipush #15
    //   2506: ishl
    //   2507: ior
    //   2508: aload #19
    //   2510: iload #21
    //   2512: iconst_2
    //   2513: isub
    //   2514: iaload
    //   2515: bipush #19
    //   2517: iushr
    //   2518: aload #19
    //   2520: iload #21
    //   2522: iconst_2
    //   2523: isub
    //   2524: iaload
    //   2525: bipush #13
    //   2527: ishl
    //   2528: ior
    //   2529: ixor
    //   2530: aload #19
    //   2532: iload #21
    //   2534: iconst_2
    //   2535: isub
    //   2536: iaload
    //   2537: bipush #10
    //   2539: iushr
    //   2540: ixor
    //   2541: aload #19
    //   2543: iload #21
    //   2545: bipush #7
    //   2547: isub
    //   2548: iaload
    //   2549: iadd
    //   2550: aload #19
    //   2552: iload #21
    //   2554: bipush #15
    //   2556: isub
    //   2557: iaload
    //   2558: bipush #7
    //   2560: iushr
    //   2561: aload #19
    //   2563: iload #21
    //   2565: bipush #15
    //   2567: isub
    //   2568: iaload
    //   2569: bipush #25
    //   2571: ishl
    //   2572: ior
    //   2573: aload #19
    //   2575: iload #21
    //   2577: bipush #15
    //   2579: isub
    //   2580: iaload
    //   2581: bipush #18
    //   2583: iushr
    //   2584: aload #19
    //   2586: iload #21
    //   2588: bipush #15
    //   2590: isub
    //   2591: iaload
    //   2592: bipush #14
    //   2594: ishl
    //   2595: ior
    //   2596: ixor
    //   2597: aload #19
    //   2599: iload #21
    //   2601: bipush #15
    //   2603: isub
    //   2604: iaload
    //   2605: iconst_3
    //   2606: iushr
    //   2607: ixor
    //   2608: iadd
    //   2609: aload #19
    //   2611: iload #21
    //   2613: bipush #16
    //   2615: isub
    //   2616: iaload
    //   2617: iadd
    //   2618: iastore
    //   2619: goto -> 2626
    //   2622: invokestatic a : (Ljava/lang/Throwable;)Ljava/lang/Throwable;
    //   2625: athrow
    //   2626: aload #20
    //   2628: bipush #7
    //   2630: iaload
    //   2631: aload #20
    //   2633: iconst_4
    //   2634: iaload
    //   2635: bipush #6
    //   2637: iushr
    //   2638: aload #20
    //   2640: iconst_4
    //   2641: iaload
    //   2642: bipush #26
    //   2644: ishl
    //   2645: ior
    //   2646: aload #20
    //   2648: iconst_4
    //   2649: iaload
    //   2650: bipush #11
    //   2652: iushr
    //   2653: aload #20
    //   2655: iconst_4
    //   2656: iaload
    //   2657: bipush #21
    //   2659: ishl
    //   2660: ior
    //   2661: ixor
    //   2662: aload #20
    //   2664: iconst_4
    //   2665: iaload
    //   2666: bipush #25
    //   2668: iushr
    //   2669: aload #20
    //   2671: iconst_4
    //   2672: iaload
    //   2673: bipush #7
    //   2675: ishl
    //   2676: ior
    //   2677: ixor
    //   2678: iadd
    //   2679: aload #20
    //   2681: bipush #6
    //   2683: iaload
    //   2684: aload #20
    //   2686: iconst_4
    //   2687: iaload
    //   2688: aload #20
    //   2690: iconst_5
    //   2691: iaload
    //   2692: aload #20
    //   2694: bipush #6
    //   2696: iaload
    //   2697: ixor
    //   2698: iand
    //   2699: ixor
    //   2700: iadd
    //   2701: aload #6
    //   2703: iload #21
    //   2705: iaload
    //   2706: iadd
    //   2707: aload #19
    //   2709: iload #21
    //   2711: iaload
    //   2712: iadd
    //   2713: istore #22
    //   2715: aload #20
    //   2717: iconst_0
    //   2718: iaload
    //   2719: iconst_2
    //   2720: iushr
    //   2721: aload #20
    //   2723: iconst_0
    //   2724: iaload
    //   2725: bipush #30
    //   2727: ishl
    //   2728: ior
    //   2729: aload #20
    //   2731: iconst_0
    //   2732: iaload
    //   2733: bipush #13
    //   2735: iushr
    //   2736: aload #20
    //   2738: iconst_0
    //   2739: iaload
    //   2740: bipush #19
    //   2742: ishl
    //   2743: ior
    //   2744: ixor
    //   2745: aload #20
    //   2747: iconst_0
    //   2748: iaload
    //   2749: bipush #22
    //   2751: iushr
    //   2752: aload #20
    //   2754: iconst_0
    //   2755: iaload
    //   2756: bipush #10
    //   2758: ishl
    //   2759: ior
    //   2760: ixor
    //   2761: aload #20
    //   2763: iconst_0
    //   2764: iaload
    //   2765: aload #20
    //   2767: iconst_1
    //   2768: iaload
    //   2769: iand
    //   2770: aload #20
    //   2772: iconst_2
    //   2773: iaload
    //   2774: aload #20
    //   2776: iconst_0
    //   2777: iaload
    //   2778: aload #20
    //   2780: iconst_1
    //   2781: iaload
    //   2782: ior
    //   2783: iand
    //   2784: ior
    //   2785: iadd
    //   2786: istore #23
    //   2788: aload #20
    //   2790: iconst_3
    //   2791: dup2
    //   2792: iaload
    //   2793: iload #22
    //   2795: iadd
    //   2796: iastore
    //   2797: aload #20
    //   2799: bipush #7
    //   2801: iload #22
    //   2803: iload #23
    //   2805: iadd
    //   2806: iastore
    //   2807: aload #20
    //   2809: bipush #7
    //   2811: iaload
    //   2812: istore #22
    //   2814: aload #20
    //   2816: bipush #7
    //   2818: aload #20
    //   2820: bipush #6
    //   2822: iaload
    //   2823: iastore
    //   2824: aload #20
    //   2826: bipush #6
    //   2828: aload #20
    //   2830: iconst_5
    //   2831: iaload
    //   2832: iastore
    //   2833: aload #20
    //   2835: iconst_5
    //   2836: aload #20
    //   2838: iconst_4
    //   2839: iaload
    //   2840: iastore
    //   2841: aload #20
    //   2843: iconst_4
    //   2844: aload #20
    //   2846: iconst_3
    //   2847: iaload
    //   2848: iastore
    //   2849: aload #20
    //   2851: iconst_3
    //   2852: aload #20
    //   2854: iconst_2
    //   2855: iaload
    //   2856: iastore
    //   2857: aload #20
    //   2859: iconst_2
    //   2860: aload #20
    //   2862: iconst_1
    //   2863: iaload
    //   2864: iastore
    //   2865: aload #20
    //   2867: iconst_1
    //   2868: aload #20
    //   2870: iconst_0
    //   2871: iaload
    //   2872: iastore
    //   2873: aload #20
    //   2875: iconst_0
    //   2876: iload #22
    //   2878: iastore
    //   2879: iinc #21, 1
    //   2882: iload_2
    //   2883: ifeq -> 2391
    //   2886: iconst_0
    //   2887: istore #21
    //   2889: iload #21
    //   2891: bipush #8
    //   2893: if_icmpge -> 2916
    //   2896: aload #8
    //   2898: iload #21
    //   2900: dup2
    //   2901: iaload
    //   2902: aload #20
    //   2904: iload #21
    //   2906: iaload
    //   2907: iadd
    //   2908: iastore
    //   2909: iinc #21, 1
    //   2912: iload_2
    //   2913: ifeq -> 2889
    //   2916: iload #13
    //   2918: iload #18
    //   2920: iadd
    //   2921: istore #13
    //   2923: iload #17
    //   2925: iload #18
    //   2927: isub
    //   2928: istore #17
    //   2930: iconst_0
    //   2931: istore #12
    //   2933: iload #17
    //   2935: bipush #64
    //   2937: if_icmplt -> 3547
    //   2940: iconst_0
    //   2941: istore #19
    //   2943: iload #19
    //   2945: bipush #64
    //   2947: if_icmpge -> 2970
    //   2950: aload #10
    //   2952: iload #19
    //   2954: aload #5
    //   2956: iload #13
    //   2958: iload #19
    //   2960: iadd
    //   2961: baload
    //   2962: bastore
    //   2963: iinc #19, 1
    //   2966: iload_2
    //   2967: ifeq -> 2943
    //   2970: bipush #64
    //   2972: newarray int
    //   2974: astore #19
    //   2976: bipush #8
    //   2978: newarray int
    //   2980: astore #20
    //   2982: iconst_0
    //   2983: istore #21
    //   2985: iload #21
    //   2987: bipush #8
    //   2989: if_icmpge -> 3009
    //   2992: aload #20
    //   2994: iload #21
    //   2996: aload #8
    //   2998: iload #21
    //   3000: iaload
    //   3001: iastore
    //   3002: iinc #21, 1
    //   3005: iload_2
    //   3006: ifeq -> 2985
    //   3009: iconst_0
    //   3010: istore #21
    //   3012: iload #21
    //   3014: bipush #64
    //   3016: if_icmpge -> 3507
    //   3019: iload #21
    //   3021: bipush #16
    //   3023: if_icmpge -> 3104
    //   3026: aload #19
    //   3028: iload #21
    //   3030: aload #10
    //   3032: iconst_4
    //   3033: iload #21
    //   3035: imul
    //   3036: baload
    //   3037: sipush #255
    //   3040: iand
    //   3041: bipush #24
    //   3043: ishl
    //   3044: aload #10
    //   3046: iconst_4
    //   3047: iload #21
    //   3049: imul
    //   3050: iconst_1
    //   3051: iadd
    //   3052: baload
    //   3053: sipush #255
    //   3056: iand
    //   3057: bipush #16
    //   3059: ishl
    //   3060: ior
    //   3061: aload #10
    //   3063: iconst_4
    //   3064: iload #21
    //   3066: imul
    //   3067: iconst_2
    //   3068: iadd
    //   3069: baload
    //   3070: sipush #255
    //   3073: iand
    //   3074: bipush #8
    //   3076: ishl
    //   3077: ior
    //   3078: aload #10
    //   3080: iconst_4
    //   3081: iload #21
    //   3083: imul
    //   3084: iconst_3
    //   3085: iadd
    //   3086: baload
    //   3087: sipush #255
    //   3090: iand
    //   3091: ior
    //   3092: iastore
    //   3093: iload_2
    //   3094: ifeq -> 3247
    //   3097: goto -> 3104
    //   3100: invokestatic a : (Ljava/lang/Throwable;)Ljava/lang/Throwable;
    //   3103: athrow
    //   3104: aload #19
    //   3106: iload #21
    //   3108: aload #19
    //   3110: iload #21
    //   3112: iconst_2
    //   3113: isub
    //   3114: iaload
    //   3115: bipush #17
    //   3117: iushr
    //   3118: aload #19
    //   3120: iload #21
    //   3122: iconst_2
    //   3123: isub
    //   3124: iaload
    //   3125: bipush #15
    //   3127: ishl
    //   3128: ior
    //   3129: aload #19
    //   3131: iload #21
    //   3133: iconst_2
    //   3134: isub
    //   3135: iaload
    //   3136: bipush #19
    //   3138: iushr
    //   3139: aload #19
    //   3141: iload #21
    //   3143: iconst_2
    //   3144: isub
    //   3145: iaload
    //   3146: bipush #13
    //   3148: ishl
    //   3149: ior
    //   3150: ixor
    //   3151: aload #19
    //   3153: iload #21
    //   3155: iconst_2
    //   3156: isub
    //   3157: iaload
    //   3158: bipush #10
    //   3160: iushr
    //   3161: ixor
    //   3162: aload #19
    //   3164: iload #21
    //   3166: bipush #7
    //   3168: isub
    //   3169: iaload
    //   3170: iadd
    //   3171: aload #19
    //   3173: iload #21
    //   3175: bipush #15
    //   3177: isub
    //   3178: iaload
    //   3179: bipush #7
    //   3181: iushr
    //   3182: aload #19
    //   3184: iload #21
    //   3186: bipush #15
    //   3188: isub
    //   3189: iaload
    //   3190: bipush #25
    //   3192: ishl
    //   3193: ior
    //   3194: aload #19
    //   3196: iload #21
    //   3198: bipush #15
    //   3200: isub
    //   3201: iaload
    //   3202: bipush #18
    //   3204: iushr
    //   3205: aload #19
    //   3207: iload #21
    //   3209: bipush #15
    //   3211: isub
    //   3212: iaload
    //   3213: bipush #14
    //   3215: ishl
    //   3216: ior
    //   3217: ixor
    //   3218: aload #19
    //   3220: iload #21
    //   3222: bipush #15
    //   3224: isub
    //   3225: iaload
    //   3226: iconst_3
    //   3227: iushr
    //   3228: ixor
    //   3229: iadd
    //   3230: aload #19
    //   3232: iload #21
    //   3234: bipush #16
    //   3236: isub
    //   3237: iaload
    //   3238: iadd
    //   3239: iastore
    //   3240: goto -> 3247
    //   3243: invokestatic a : (Ljava/lang/Throwable;)Ljava/lang/Throwable;
    //   3246: athrow
    //   3247: aload #20
    //   3249: bipush #7
    //   3251: iaload
    //   3252: aload #20
    //   3254: iconst_4
    //   3255: iaload
    //   3256: bipush #6
    //   3258: iushr
    //   3259: aload #20
    //   3261: iconst_4
    //   3262: iaload
    //   3263: bipush #26
    //   3265: ishl
    //   3266: ior
    //   3267: aload #20
    //   3269: iconst_4
    //   3270: iaload
    //   3271: bipush #11
    //   3273: iushr
    //   3274: aload #20
    //   3276: iconst_4
    //   3277: iaload
    //   3278: bipush #21
    //   3280: ishl
    //   3281: ior
    //   3282: ixor
    //   3283: aload #20
    //   3285: iconst_4
    //   3286: iaload
    //   3287: bipush #25
    //   3289: iushr
    //   3290: aload #20
    //   3292: iconst_4
    //   3293: iaload
    //   3294: bipush #7
    //   3296: ishl
    //   3297: ior
    //   3298: ixor
    //   3299: iadd
    //   3300: aload #20
    //   3302: bipush #6
    //   3304: iaload
    //   3305: aload #20
    //   3307: iconst_4
    //   3308: iaload
    //   3309: aload #20
    //   3311: iconst_5
    //   3312: iaload
    //   3313: aload #20
    //   3315: bipush #6
    //   3317: iaload
    //   3318: ixor
    //   3319: iand
    //   3320: ixor
    //   3321: iadd
    //   3322: aload #6
    //   3324: iload #21
    //   3326: iaload
    //   3327: iadd
    //   3328: aload #19
    //   3330: iload #21
    //   3332: iaload
    //   3333: iadd
    //   3334: istore #22
    //   3336: aload #20
    //   3338: iconst_0
    //   3339: iaload
    //   3340: iconst_2
    //   3341: iushr
    //   3342: aload #20
    //   3344: iconst_0
    //   3345: iaload
    //   3346: bipush #30
    //   3348: ishl
    //   3349: ior
    //   3350: aload #20
    //   3352: iconst_0
    //   3353: iaload
    //   3354: bipush #13
    //   3356: iushr
    //   3357: aload #20
    //   3359: iconst_0
    //   3360: iaload
    //   3361: bipush #19
    //   3363: ishl
    //   3364: ior
    //   3365: ixor
    //   3366: aload #20
    //   3368: iconst_0
    //   3369: iaload
    //   3370: bipush #22
    //   3372: iushr
    //   3373: aload #20
    //   3375: iconst_0
    //   3376: iaload
    //   3377: bipush #10
    //   3379: ishl
    //   3380: ior
    //   3381: ixor
    //   3382: aload #20
    //   3384: iconst_0
    //   3385: iaload
    //   3386: aload #20
    //   3388: iconst_1
    //   3389: iaload
    //   3390: iand
    //   3391: aload #20
    //   3393: iconst_2
    //   3394: iaload
    //   3395: aload #20
    //   3397: iconst_0
    //   3398: iaload
    //   3399: aload #20
    //   3401: iconst_1
    //   3402: iaload
    //   3403: ior
    //   3404: iand
    //   3405: ior
    //   3406: iadd
    //   3407: istore #23
    //   3409: aload #20
    //   3411: iconst_3
    //   3412: dup2
    //   3413: iaload
    //   3414: iload #22
    //   3416: iadd
    //   3417: iastore
    //   3418: aload #20
    //   3420: bipush #7
    //   3422: iload #22
    //   3424: iload #23
    //   3426: iadd
    //   3427: iastore
    //   3428: aload #20
    //   3430: bipush #7
    //   3432: iaload
    //   3433: istore #22
    //   3435: aload #20
    //   3437: bipush #7
    //   3439: aload #20
    //   3441: bipush #6
    //   3443: iaload
    //   3444: iastore
    //   3445: aload #20
    //   3447: bipush #6
    //   3449: aload #20
    //   3451: iconst_5
    //   3452: iaload
    //   3453: iastore
    //   3454: aload #20
    //   3456: iconst_5
    //   3457: aload #20
    //   3459: iconst_4
    //   3460: iaload
    //   3461: iastore
    //   3462: aload #20
    //   3464: iconst_4
    //   3465: aload #20
    //   3467: iconst_3
    //   3468: iaload
    //   3469: iastore
    //   3470: aload #20
    //   3472: iconst_3
    //   3473: aload #20
    //   3475: iconst_2
    //   3476: iaload
    //   3477: iastore
    //   3478: aload #20
    //   3480: iconst_2
    //   3481: aload #20
    //   3483: iconst_1
    //   3484: iaload
    //   3485: iastore
    //   3486: aload #20
    //   3488: iconst_1
    //   3489: aload #20
    //   3491: iconst_0
    //   3492: iaload
    //   3493: iastore
    //   3494: aload #20
    //   3496: iconst_0
    //   3497: iload #22
    //   3499: iastore
    //   3500: iinc #21, 1
    //   3503: iload_2
    //   3504: ifeq -> 3012
    //   3507: iconst_0
    //   3508: istore #21
    //   3510: iload #21
    //   3512: bipush #8
    //   3514: if_icmpge -> 3537
    //   3517: aload #8
    //   3519: iload #21
    //   3521: dup2
    //   3522: iaload
    //   3523: aload #20
    //   3525: iload #21
    //   3527: iaload
    //   3528: iadd
    //   3529: iastore
    //   3530: iinc #21, 1
    //   3533: iload_2
    //   3534: ifeq -> 3510
    //   3537: iinc #13, 64
    //   3540: iinc #17, -64
    //   3543: iload_2
    //   3544: ifeq -> 2933
    //   3547: iload #17
    //   3549: ifle -> 3585
    //   3552: iconst_0
    //   3553: istore #19
    //   3555: iload #19
    //   3557: iload #17
    //   3559: if_icmpge -> 3585
    //   3562: aload #9
    //   3564: iload #12
    //   3566: iload #19
    //   3568: iadd
    //   3569: aload #5
    //   3571: iload #13
    //   3573: iload #19
    //   3575: iadd
    //   3576: baload
    //   3577: bastore
    //   3578: iinc #19, 1
    //   3581: iload_2
    //   3582: ifeq -> 3555
    //   3585: bipush #8
    //   3587: newarray byte
    //   3589: astore #19
    //   3591: aload #19
    //   3593: iconst_0
    //   3594: iload #14
    //   3596: bipush #24
    //   3598: iushr
    //   3599: i2b
    //   3600: bastore
    //   3601: aload #19
    //   3603: iconst_1
    //   3604: iload #14
    //   3606: bipush #16
    //   3608: iushr
    //   3609: i2b
    //   3610: bastore
    //   3611: aload #19
    //   3613: iconst_2
    //   3614: iload #14
    //   3616: bipush #8
    //   3618: iushr
    //   3619: i2b
    //   3620: bastore
    //   3621: aload #19
    //   3623: iconst_3
    //   3624: iload #14
    //   3626: i2b
    //   3627: bastore
    //   3628: aload #19
    //   3630: iconst_4
    //   3631: iload #15
    //   3633: bipush #24
    //   3635: iushr
    //   3636: i2b
    //   3637: bastore
    //   3638: aload #19
    //   3640: iconst_5
    //   3641: iload #15
    //   3643: bipush #16
    //   3645: iushr
    //   3646: i2b
    //   3647: bastore
    //   3648: aload #19
    //   3650: bipush #6
    //   3652: iload #15
    //   3654: bipush #8
    //   3656: iushr
    //   3657: i2b
    //   3658: bastore
    //   3659: aload #19
    //   3661: bipush #7
    //   3663: iload #15
    //   3665: i2b
    //   3666: bastore
    //   3667: bipush #8
    //   3669: istore #11
    //   3671: aload #7
    //   3673: iconst_0
    //   3674: iaload
    //   3675: bipush #63
    //   3677: iand
    //   3678: istore #12
    //   3680: bipush #64
    //   3682: iload #12
    //   3684: isub
    //   3685: istore #18
    //   3687: aload #7
    //   3689: iconst_0
    //   3690: dup2
    //   3691: iaload
    //   3692: iload #11
    //   3694: iadd
    //   3695: iastore
    //   3696: aload #7
    //   3698: iconst_0
    //   3699: dup2
    //   3700: iaload
    //   3701: iconst_m1
    //   3702: iand
    //   3703: iastore
    //   3704: aload #7
    //   3706: iconst_0
    //   3707: iaload
    //   3708: iload #11
    //   3710: if_icmpge -> 3728
    //   3713: aload #7
    //   3715: iconst_1
    //   3716: dup2
    //   3717: iaload
    //   3718: iconst_1
    //   3719: iadd
    //   3720: iastore
    //   3721: goto -> 3728
    //   3724: invokestatic a : (Ljava/lang/Throwable;)Ljava/lang/Throwable;
    //   3727: athrow
    //   3728: iload #12
    //   3730: ifle -> 4344
    //   3733: iload #11
    //   3735: iload #18
    //   3737: if_icmplt -> 4344
    //   3740: goto -> 3747
    //   3743: invokestatic a : (Ljava/lang/Throwable;)Ljava/lang/Throwable;
    //   3746: athrow
    //   3747: iconst_0
    //   3748: istore #20
    //   3750: iload #20
    //   3752: iload #18
    //   3754: if_icmpge -> 3777
    //   3757: aload #9
    //   3759: iload #12
    //   3761: iload #20
    //   3763: iadd
    //   3764: aload #19
    //   3766: iload #20
    //   3768: baload
    //   3769: bastore
    //   3770: iinc #20, 1
    //   3773: iload_2
    //   3774: ifeq -> 3750
    //   3777: bipush #64
    //   3779: newarray int
    //   3781: astore #20
    //   3783: bipush #8
    //   3785: newarray int
    //   3787: astore #21
    //   3789: iconst_0
    //   3790: istore #22
    //   3792: iload #22
    //   3794: bipush #8
    //   3796: if_icmpge -> 3816
    //   3799: aload #21
    //   3801: iload #22
    //   3803: aload #8
    //   3805: iload #22
    //   3807: iaload
    //   3808: iastore
    //   3809: iinc #22, 1
    //   3812: iload_2
    //   3813: ifeq -> 3792
    //   3816: iconst_0
    //   3817: istore #22
    //   3819: iload #22
    //   3821: bipush #64
    //   3823: if_icmpge -> 4314
    //   3826: iload #22
    //   3828: bipush #16
    //   3830: if_icmpge -> 3911
    //   3833: aload #20
    //   3835: iload #22
    //   3837: aload #9
    //   3839: iconst_4
    //   3840: iload #22
    //   3842: imul
    //   3843: baload
    //   3844: sipush #255
    //   3847: iand
    //   3848: bipush #24
    //   3850: ishl
    //   3851: aload #9
    //   3853: iconst_4
    //   3854: iload #22
    //   3856: imul
    //   3857: iconst_1
    //   3858: iadd
    //   3859: baload
    //   3860: sipush #255
    //   3863: iand
    //   3864: bipush #16
    //   3866: ishl
    //   3867: ior
    //   3868: aload #9
    //   3870: iconst_4
    //   3871: iload #22
    //   3873: imul
    //   3874: iconst_2
    //   3875: iadd
    //   3876: baload
    //   3877: sipush #255
    //   3880: iand
    //   3881: bipush #8
    //   3883: ishl
    //   3884: ior
    //   3885: aload #9
    //   3887: iconst_4
    //   3888: iload #22
    //   3890: imul
    //   3891: iconst_3
    //   3892: iadd
    //   3893: baload
    //   3894: sipush #255
    //   3897: iand
    //   3898: ior
    //   3899: iastore
    //   3900: iload_2
    //   3901: ifeq -> 4054
    //   3904: goto -> 3911
    //   3907: invokestatic a : (Ljava/lang/Throwable;)Ljava/lang/Throwable;
    //   3910: athrow
    //   3911: aload #20
    //   3913: iload #22
    //   3915: aload #20
    //   3917: iload #22
    //   3919: iconst_2
    //   3920: isub
    //   3921: iaload
    //   3922: bipush #17
    //   3924: iushr
    //   3925: aload #20
    //   3927: iload #22
    //   3929: iconst_2
    //   3930: isub
    //   3931: iaload
    //   3932: bipush #15
    //   3934: ishl
    //   3935: ior
    //   3936: aload #20
    //   3938: iload #22
    //   3940: iconst_2
    //   3941: isub
    //   3942: iaload
    //   3943: bipush #19
    //   3945: iushr
    //   3946: aload #20
    //   3948: iload #22
    //   3950: iconst_2
    //   3951: isub
    //   3952: iaload
    //   3953: bipush #13
    //   3955: ishl
    //   3956: ior
    //   3957: ixor
    //   3958: aload #20
    //   3960: iload #22
    //   3962: iconst_2
    //   3963: isub
    //   3964: iaload
    //   3965: bipush #10
    //   3967: iushr
    //   3968: ixor
    //   3969: aload #20
    //   3971: iload #22
    //   3973: bipush #7
    //   3975: isub
    //   3976: iaload
    //   3977: iadd
    //   3978: aload #20
    //   3980: iload #22
    //   3982: bipush #15
    //   3984: isub
    //   3985: iaload
    //   3986: bipush #7
    //   3988: iushr
    //   3989: aload #20
    //   3991: iload #22
    //   3993: bipush #15
    //   3995: isub
    //   3996: iaload
    //   3997: bipush #25
    //   3999: ishl
    //   4000: ior
    //   4001: aload #20
    //   4003: iload #22
    //   4005: bipush #15
    //   4007: isub
    //   4008: iaload
    //   4009: bipush #18
    //   4011: iushr
    //   4012: aload #20
    //   4014: iload #22
    //   4016: bipush #15
    //   4018: isub
    //   4019: iaload
    //   4020: bipush #14
    //   4022: ishl
    //   4023: ior
    //   4024: ixor
    //   4025: aload #20
    //   4027: iload #22
    //   4029: bipush #15
    //   4031: isub
    //   4032: iaload
    //   4033: iconst_3
    //   4034: iushr
    //   4035: ixor
    //   4036: iadd
    //   4037: aload #20
    //   4039: iload #22
    //   4041: bipush #16
    //   4043: isub
    //   4044: iaload
    //   4045: iadd
    //   4046: iastore
    //   4047: goto -> 4054
    //   4050: invokestatic a : (Ljava/lang/Throwable;)Ljava/lang/Throwable;
    //   4053: athrow
    //   4054: aload #21
    //   4056: bipush #7
    //   4058: iaload
    //   4059: aload #21
    //   4061: iconst_4
    //   4062: iaload
    //   4063: bipush #6
    //   4065: iushr
    //   4066: aload #21
    //   4068: iconst_4
    //   4069: iaload
    //   4070: bipush #26
    //   4072: ishl
    //   4073: ior
    //   4074: aload #21
    //   4076: iconst_4
    //   4077: iaload
    //   4078: bipush #11
    //   4080: iushr
    //   4081: aload #21
    //   4083: iconst_4
    //   4084: iaload
    //   4085: bipush #21
    //   4087: ishl
    //   4088: ior
    //   4089: ixor
    //   4090: aload #21
    //   4092: iconst_4
    //   4093: iaload
    //   4094: bipush #25
    //   4096: iushr
    //   4097: aload #21
    //   4099: iconst_4
    //   4100: iaload
    //   4101: bipush #7
    //   4103: ishl
    //   4104: ior
    //   4105: ixor
    //   4106: iadd
    //   4107: aload #21
    //   4109: bipush #6
    //   4111: iaload
    //   4112: aload #21
    //   4114: iconst_4
    //   4115: iaload
    //   4116: aload #21
    //   4118: iconst_5
    //   4119: iaload
    //   4120: aload #21
    //   4122: bipush #6
    //   4124: iaload
    //   4125: ixor
    //   4126: iand
    //   4127: ixor
    //   4128: iadd
    //   4129: aload #6
    //   4131: iload #22
    //   4133: iaload
    //   4134: iadd
    //   4135: aload #20
    //   4137: iload #22
    //   4139: iaload
    //   4140: iadd
    //   4141: istore #23
    //   4143: aload #21
    //   4145: iconst_0
    //   4146: iaload
    //   4147: iconst_2
    //   4148: iushr
    //   4149: aload #21
    //   4151: iconst_0
    //   4152: iaload
    //   4153: bipush #30
    //   4155: ishl
    //   4156: ior
    //   4157: aload #21
    //   4159: iconst_0
    //   4160: iaload
    //   4161: bipush #13
    //   4163: iushr
    //   4164: aload #21
    //   4166: iconst_0
    //   4167: iaload
    //   4168: bipush #19
    //   4170: ishl
    //   4171: ior
    //   4172: ixor
    //   4173: aload #21
    //   4175: iconst_0
    //   4176: iaload
    //   4177: bipush #22
    //   4179: iushr
    //   4180: aload #21
    //   4182: iconst_0
    //   4183: iaload
    //   4184: bipush #10
    //   4186: ishl
    //   4187: ior
    //   4188: ixor
    //   4189: aload #21
    //   4191: iconst_0
    //   4192: iaload
    //   4193: aload #21
    //   4195: iconst_1
    //   4196: iaload
    //   4197: iand
    //   4198: aload #21
    //   4200: iconst_2
    //   4201: iaload
    //   4202: aload #21
    //   4204: iconst_0
    //   4205: iaload
    //   4206: aload #21
    //   4208: iconst_1
    //   4209: iaload
    //   4210: ior
    //   4211: iand
    //   4212: ior
    //   4213: iadd
    //   4214: istore #24
    //   4216: aload #21
    //   4218: iconst_3
    //   4219: dup2
    //   4220: iaload
    //   4221: iload #23
    //   4223: iadd
    //   4224: iastore
    //   4225: aload #21
    //   4227: bipush #7
    //   4229: iload #23
    //   4231: iload #24
    //   4233: iadd
    //   4234: iastore
    //   4235: aload #21
    //   4237: bipush #7
    //   4239: iaload
    //   4240: istore #23
    //   4242: aload #21
    //   4244: bipush #7
    //   4246: aload #21
    //   4248: bipush #6
    //   4250: iaload
    //   4251: iastore
    //   4252: aload #21
    //   4254: bipush #6
    //   4256: aload #21
    //   4258: iconst_5
    //   4259: iaload
    //   4260: iastore
    //   4261: aload #21
    //   4263: iconst_5
    //   4264: aload #21
    //   4266: iconst_4
    //   4267: iaload
    //   4268: iastore
    //   4269: aload #21
    //   4271: iconst_4
    //   4272: aload #21
    //   4274: iconst_3
    //   4275: iaload
    //   4276: iastore
    //   4277: aload #21
    //   4279: iconst_3
    //   4280: aload #21
    //   4282: iconst_2
    //   4283: iaload
    //   4284: iastore
    //   4285: aload #21
    //   4287: iconst_2
    //   4288: aload #21
    //   4290: iconst_1
    //   4291: iaload
    //   4292: iastore
    //   4293: aload #21
    //   4295: iconst_1
    //   4296: aload #21
    //   4298: iconst_0
    //   4299: iaload
    //   4300: iastore
    //   4301: aload #21
    //   4303: iconst_0
    //   4304: iload #23
    //   4306: iastore
    //   4307: iinc #22, 1
    //   4310: iload_2
    //   4311: ifeq -> 3819
    //   4314: iconst_0
    //   4315: istore #22
    //   4317: iload #22
    //   4319: bipush #8
    //   4321: if_icmpge -> 4344
    //   4324: aload #8
    //   4326: iload #22
    //   4328: dup2
    //   4329: iaload
    //   4330: aload #21
    //   4332: iload #22
    //   4334: iaload
    //   4335: iadd
    //   4336: iastore
    //   4337: iinc #22, 1
    //   4340: iload_2
    //   4341: ifeq -> 4317
    //   4344: bipush #32
    //   4346: newarray byte
    //   4348: astore #4
    //   4350: sipush #31194
    //   4353: aload #4
    //   4355: iconst_0
    //   4356: aload #8
    //   4358: iconst_0
    //   4359: iaload
    //   4360: bipush #24
    //   4362: iushr
    //   4363: i2b
    //   4364: bastore
    //   4365: sipush #-164
    //   4368: aload #4
    //   4370: iconst_1
    //   4371: aload #8
    //   4373: iconst_0
    //   4374: iaload
    //   4375: bipush #16
    //   4377: iushr
    //   4378: i2b
    //   4379: bastore
    //   4380: aload #4
    //   4382: iconst_2
    //   4383: aload #8
    //   4385: iconst_0
    //   4386: iaload
    //   4387: bipush #8
    //   4389: iushr
    //   4390: i2b
    //   4391: bastore
    //   4392: aload #4
    //   4394: iconst_3
    //   4395: aload #8
    //   4397: iconst_0
    //   4398: iaload
    //   4399: i2b
    //   4400: bastore
    //   4401: aload #4
    //   4403: iconst_4
    //   4404: aload #8
    //   4406: iconst_1
    //   4407: iaload
    //   4408: bipush #24
    //   4410: iushr
    //   4411: i2b
    //   4412: bastore
    //   4413: aload #4
    //   4415: iconst_5
    //   4416: aload #8
    //   4418: iconst_1
    //   4419: iaload
    //   4420: bipush #16
    //   4422: iushr
    //   4423: i2b
    //   4424: bastore
    //   4425: aload #4
    //   4427: bipush #6
    //   4429: aload #8
    //   4431: iconst_1
    //   4432: iaload
    //   4433: bipush #8
    //   4435: iushr
    //   4436: i2b
    //   4437: bastore
    //   4438: aload #4
    //   4440: bipush #7
    //   4442: aload #8
    //   4444: iconst_1
    //   4445: iaload
    //   4446: i2b
    //   4447: bastore
    //   4448: aload #4
    //   4450: bipush #8
    //   4452: aload #8
    //   4454: iconst_2
    //   4455: iaload
    //   4456: bipush #24
    //   4458: iushr
    //   4459: i2b
    //   4460: bastore
    //   4461: aload #4
    //   4463: bipush #9
    //   4465: aload #8
    //   4467: iconst_2
    //   4468: iaload
    //   4469: bipush #16
    //   4471: iushr
    //   4472: i2b
    //   4473: bastore
    //   4474: aload #4
    //   4476: bipush #10
    //   4478: aload #8
    //   4480: iconst_2
    //   4481: iaload
    //   4482: bipush #8
    //   4484: iushr
    //   4485: i2b
    //   4486: bastore
    //   4487: aload #4
    //   4489: bipush #11
    //   4491: aload #8
    //   4493: iconst_2
    //   4494: iaload
    //   4495: i2b
    //   4496: bastore
    //   4497: aload #4
    //   4499: bipush #12
    //   4501: aload #8
    //   4503: iconst_3
    //   4504: iaload
    //   4505: bipush #24
    //   4507: iushr
    //   4508: i2b
    //   4509: bastore
    //   4510: aload #4
    //   4512: bipush #13
    //   4514: aload #8
    //   4516: iconst_3
    //   4517: iaload
    //   4518: bipush #16
    //   4520: iushr
    //   4521: i2b
    //   4522: bastore
    //   4523: aload #4
    //   4525: bipush #14
    //   4527: aload #8
    //   4529: iconst_3
    //   4530: iaload
    //   4531: bipush #8
    //   4533: iushr
    //   4534: i2b
    //   4535: bastore
    //   4536: aload #4
    //   4538: bipush #15
    //   4540: aload #8
    //   4542: iconst_3
    //   4543: iaload
    //   4544: i2b
    //   4545: bastore
    //   4546: aload #4
    //   4548: bipush #16
    //   4550: aload #8
    //   4552: iconst_4
    //   4553: iaload
    //   4554: bipush #24
    //   4556: iushr
    //   4557: i2b
    //   4558: bastore
    //   4559: aload #4
    //   4561: bipush #17
    //   4563: aload #8
    //   4565: iconst_4
    //   4566: iaload
    //   4567: bipush #16
    //   4569: iushr
    //   4570: i2b
    //   4571: bastore
    //   4572: aload #4
    //   4574: bipush #18
    //   4576: aload #8
    //   4578: iconst_4
    //   4579: iaload
    //   4580: bipush #8
    //   4582: iushr
    //   4583: i2b
    //   4584: bastore
    //   4585: aload #4
    //   4587: bipush #19
    //   4589: aload #8
    //   4591: iconst_4
    //   4592: iaload
    //   4593: i2b
    //   4594: bastore
    //   4595: aload #4
    //   4597: bipush #20
    //   4599: aload #8
    //   4601: iconst_5
    //   4602: iaload
    //   4603: bipush #24
    //   4605: iushr
    //   4606: i2b
    //   4607: bastore
    //   4608: aload #4
    //   4610: bipush #21
    //   4612: aload #8
    //   4614: iconst_5
    //   4615: iaload
    //   4616: bipush #16
    //   4618: iushr
    //   4619: i2b
    //   4620: bastore
    //   4621: aload #4
    //   4623: bipush #22
    //   4625: aload #8
    //   4627: iconst_5
    //   4628: iaload
    //   4629: bipush #8
    //   4631: iushr
    //   4632: i2b
    //   4633: bastore
    //   4634: aload #4
    //   4636: bipush #23
    //   4638: aload #8
    //   4640: iconst_5
    //   4641: iaload
    //   4642: i2b
    //   4643: bastore
    //   4644: aload #4
    //   4646: bipush #24
    //   4648: aload #8
    //   4650: bipush #6
    //   4652: iaload
    //   4653: bipush #24
    //   4655: iushr
    //   4656: i2b
    //   4657: bastore
    //   4658: aload #4
    //   4660: bipush #25
    //   4662: aload #8
    //   4664: bipush #6
    //   4666: iaload
    //   4667: bipush #16
    //   4669: iushr
    //   4670: i2b
    //   4671: bastore
    //   4672: aload #4
    //   4674: bipush #26
    //   4676: aload #8
    //   4678: bipush #6
    //   4680: iaload
    //   4681: bipush #8
    //   4683: iushr
    //   4684: i2b
    //   4685: bastore
    //   4686: aload #4
    //   4688: bipush #27
    //   4690: aload #8
    //   4692: bipush #6
    //   4694: iaload
    //   4695: i2b
    //   4696: bastore
    //   4697: aload #4
    //   4699: bipush #28
    //   4701: aload #8
    //   4703: bipush #7
    //   4705: iaload
    //   4706: bipush #24
    //   4708: iushr
    //   4709: i2b
    //   4710: bastore
    //   4711: aload #4
    //   4713: bipush #29
    //   4715: aload #8
    //   4717: bipush #7
    //   4719: iaload
    //   4720: bipush #16
    //   4722: iushr
    //   4723: i2b
    //   4724: bastore
    //   4725: aload #4
    //   4727: bipush #30
    //   4729: aload #8
    //   4731: bipush #7
    //   4733: iaload
    //   4734: bipush #8
    //   4736: iushr
    //   4737: i2b
    //   4738: bastore
    //   4739: aload #4
    //   4741: bipush #31
    //   4743: aload #8
    //   4745: bipush #7
    //   4747: iaload
    //   4748: i2b
    //   4749: bastore
    //   4750: new java/math/BigInteger
    //   4753: dup
    //   4754: aload #4
    //   4756: invokespecial <init> : ([B)V
    //   4759: invokevirtual abs : ()Ljava/math/BigInteger;
    //   4762: putstatic burp/Zg0q.Zf : Ljava/lang/Object;
    //   4765: getstatic burp/Zxn4.Zx : Ljava/lang/Object;
    //   4768: checkcast java/math/BigInteger
    //   4771: getstatic burp/Zlw8.ZA : Ljava/lang/Object;
    //   4774: checkcast java/math/BigInteger
    //   4777: invokevirtual subtract : (Ljava/math/BigInteger;)Ljava/math/BigInteger;
    //   4780: putstatic burp/Zk8f.ZG : Ljava/lang/Object;
    //   4783: invokestatic a : (II)Ljava/lang/String;
    //   4786: iconst_1
    //   4787: ldc burp/Zsk4
    //   4789: invokevirtual getClassLoader : ()Ljava/lang/ClassLoader;
    //   4792: invokestatic forName : (Ljava/lang/String;ZLjava/lang/ClassLoader;)Ljava/lang/Class;
    //   4795: invokevirtual getDeclaredFields : ()[Ljava/lang/reflect/Field;
    //   4798: astore_3
    //   4799: aload_3
    //   4800: arraylength
    //   4801: istore #4
    //   4803: iconst_0
    //   4804: istore #5
    //   4806: iload #5
    //   4808: iload #4
    //   4810: if_icmpge -> 4947
    //   4813: aload_3
    //   4814: iload #5
    //   4816: aaload
    //   4817: astore #6
    //   4819: aload #6
    //   4821: invokevirtual getModifiers : ()I
    //   4824: invokestatic isStatic : (I)Z
    //   4827: ifne -> 4837
    //   4830: goto -> 4940
    //   4833: invokestatic a : (Ljava/lang/Throwable;)Ljava/lang/Throwable;
    //   4836: athrow
    //   4837: aload #6
    //   4839: invokevirtual getType : ()Ljava/lang/Class;
    //   4842: astore #7
    //   4844: aload #7
    //   4846: ifnull -> 4927
    //   4849: aload #7
    //   4851: invokevirtual isPrimitive : ()Z
    //   4854: ifne -> 4927
    //   4857: goto -> 4864
    //   4860: invokestatic a : (Ljava/lang/Throwable;)Ljava/lang/Throwable;
    //   4863: athrow
    //   4864: aload #7
    //   4866: invokevirtual getPackage : ()Ljava/lang/Package;
    //   4869: ifnull -> 4927
    //   4872: goto -> 4879
    //   4875: invokestatic a : (Ljava/lang/Throwable;)Ljava/lang/Throwable;
    //   4878: athrow
    //   4879: aload #7
    //   4881: invokevirtual getPackage : ()Ljava/lang/Package;
    //   4884: invokevirtual getName : ()Ljava/lang/String;
    //   4887: ifnull -> 4927
    //   4890: goto -> 4897
    //   4893: invokestatic a : (Ljava/lang/Throwable;)Ljava/lang/Throwable;
    //   4896: athrow
    //   4897: aload #7
    //   4899: invokevirtual getPackage : ()Ljava/lang/Package;
    //   4902: invokevirtual getName : ()Ljava/lang/String;
    //   4905: sipush #31177
    //   4908: sipush #24176
    //   4911: invokestatic a : (II)Ljava/lang/String;
    //   4914: invokevirtual startsWith : (Ljava/lang/String;)Z
    //   4917: ifne -> 4927
    //   4920: goto -> 4927
    //   4923: invokestatic a : (Ljava/lang/Throwable;)Ljava/lang/Throwable;
    //   4926: athrow
    //   4927: aload #6
    //   4929: iconst_1
    //   4930: invokevirtual setAccessible : (Z)V
    //   4933: aload #6
    //   4935: aconst_null
    //   4936: invokevirtual get : (Ljava/lang/Object;)Ljava/lang/Object;
    //   4939: pop
    //   4940: iinc #5, 1
    //   4943: iload_2
    //   4944: ifeq -> 4806
    //   4947: sipush #31196
    //   4950: sipush #-17071
    //   4953: invokestatic a : (II)Ljava/lang/String;
    //   4956: invokestatic forName : (Ljava/lang/String;)Ljava/lang/Class;
    //   4959: invokevirtual getDeclaredMethods : ()[Ljava/lang/reflect/Method;
    //   4962: astore_3
    //   4963: aload_3
    //   4964: arraylength
    //   4965: istore #4
    //   4967: iconst_0
    //   4968: istore #5
    //   4970: iload #5
    //   4972: iload #4
    //   4974: if_icmpge -> 5106
    //   4977: aload_3
    //   4978: iload #5
    //   4980: aaload
    //   4981: astore #6
    //   4983: aload #6
    //   4985: invokevirtual getParameterTypes : ()[Ljava/lang/Class;
    //   4988: pop
    //   4989: aload #6
    //   4991: invokevirtual getModifiers : ()I
    //   4994: invokestatic isStatic : (I)Z
    //   4997: ifeq -> 5092
    //   5000: aload #6
    //   5002: invokevirtual getParameterTypes : ()[Ljava/lang/Class;
    //   5005: arraylength
    //   5006: iconst_2
    //   5007: if_icmpne -> 5092
    //   5010: goto -> 5017
    //   5013: invokestatic a : (Ljava/lang/Throwable;)Ljava/lang/Throwable;
    //   5016: athrow
    //   5017: aload #6
    //   5019: invokevirtual getReturnType : ()Ljava/lang/Class;
    //   5022: getstatic java/lang/Void.TYPE : Ljava/lang/Class;
    //   5025: invokevirtual equals : (Ljava/lang/Object;)Z
    //   5028: ifeq -> 5092
    //   5031: goto -> 5038
    //   5034: invokestatic a : (Ljava/lang/Throwable;)Ljava/lang/Throwable;
    //   5037: athrow
    //   5038: aload #6
    //   5040: iconst_1
    //   5041: invokevirtual setAccessible : (Z)V
    //   5044: aload #6
    //   5046: aconst_null
    //   5047: iconst_2
    //   5048: anewarray java/lang/Object
    //   5051: dup
    //   5052: iconst_0
    //   5053: aload_0
    //   5054: aastore
    //   5055: dup
    //   5056: iconst_1
    //   5057: aload_1
    //   5058: ifnonnull -> 5076
    //   5061: goto -> 5068
    //   5064: invokestatic a : (Ljava/lang/Throwable;)Ljava/lang/Throwable;
    //   5067: athrow
    //   5068: aload_1
    //   5069: goto -> 5083
    //   5072: invokestatic a : (Ljava/lang/Throwable;)Ljava/lang/Throwable;
    //   5075: athrow
    //   5076: aload_1
    //   5077: checkcast [B
    //   5080: invokevirtual clone : ()Ljava/lang/Object;
    //   5083: aastore
    //   5084: invokevirtual invoke : (Ljava/lang/Object;[Ljava/lang/Object;)Ljava/lang/Object;
    //   5087: pop
    //   5088: iload_2
    //   5089: ifeq -> 5106
    //   5092: iinc #5, 1
    //   5095: iload_2
    //   5096: ifeq -> 4970
    //   5099: goto -> 5106
    //   5102: invokestatic a : (Ljava/lang/Throwable;)Ljava/lang/Throwable;
    //   5105: athrow
    //   5106: iconst_0
    //   5107: istore_3
    //   5108: getstatic burp/Zzre.Zr : Ljava/lang/String;
    //   5111: getstatic burp/Zse8.Zn : Ljava/lang/Object;
    //   5114: checkcast java/math/BigInteger
    //   5117: invokevirtual intValue : ()I
    //   5120: bipush #32
    //   5122: irem
    //   5123: invokestatic abs : (I)I
    //   5126: invokevirtual charAt : (I)C
    //   5129: getstatic burp/Zlcc.Zw : Ljava/lang/String;
    //   5132: getstatic burp/Zma0.ZQ : Ljava/lang/Object;
    //   5135: checkcast java/math/BigInteger
    //   5138: invokevirtual intValue : ()I
    //   5141: bipush #32
    //   5143: irem
    //   5144: invokestatic abs : (I)I
    //   5147: invokevirtual charAt : (I)C
    //   5150: if_icmpgt -> 5494
    //   5153: sipush #31176
    //   5156: sipush #-28656
    //   5159: invokestatic a : (II)Ljava/lang/String;
    //   5162: iconst_1
    //   5163: ldc burp/Zein
    //   5165: invokevirtual getClassLoader : ()Ljava/lang/ClassLoader;
    //   5168: invokestatic forName : (Ljava/lang/String;ZLjava/lang/ClassLoader;)Ljava/lang/Class;
    //   5171: invokevirtual getDeclaredFields : ()[Ljava/lang/reflect/Field;
    //   5174: astore #4
    //   5176: aload #4
    //   5178: arraylength
    //   5179: istore #5
    //   5181: iconst_0
    //   5182: istore #6
    //   5184: iload #6
    //   5186: iload #5
    //   5188: if_icmpge -> 5326
    //   5191: aload #4
    //   5193: iload #6
    //   5195: aaload
    //   5196: astore #7
    //   5198: aload #7
    //   5200: invokevirtual getModifiers : ()I
    //   5203: invokestatic isStatic : (I)Z
    //   5206: ifne -> 5216
    //   5209: goto -> 5319
    //   5212: invokestatic a : (Ljava/lang/Throwable;)Ljava/lang/Throwable;
    //   5215: athrow
    //   5216: aload #7
    //   5218: invokevirtual getType : ()Ljava/lang/Class;
    //   5221: astore #8
    //   5223: aload #8
    //   5225: ifnull -> 5306
    //   5228: aload #8
    //   5230: invokevirtual isPrimitive : ()Z
    //   5233: ifne -> 5306
    //   5236: goto -> 5243
    //   5239: invokestatic a : (Ljava/lang/Throwable;)Ljava/lang/Throwable;
    //   5242: athrow
    //   5243: aload #8
    //   5245: invokevirtual getPackage : ()Ljava/lang/Package;
    //   5248: ifnull -> 5306
    //   5251: goto -> 5258
    //   5254: invokestatic a : (Ljava/lang/Throwable;)Ljava/lang/Throwable;
    //   5257: athrow
    //   5258: aload #8
    //   5260: invokevirtual getPackage : ()Ljava/lang/Package;
    //   5263: invokevirtual getName : ()Ljava/lang/String;
    //   5266: ifnull -> 5306
    //   5269: goto -> 5276
    //   5272: invokestatic a : (Ljava/lang/Throwable;)Ljava/lang/Throwable;
    //   5275: athrow
    //   5276: aload #8
    //   5278: invokevirtual getPackage : ()Ljava/lang/Package;
    //   5281: invokevirtual getName : ()Ljava/lang/String;
    //   5284: sipush #31178
    //   5287: sipush #-21468
    //   5290: invokestatic a : (II)Ljava/lang/String;
    //   5293: invokevirtual startsWith : (Ljava/lang/String;)Z
    //   5296: ifne -> 5306
    //   5299: goto -> 5306
    //   5302: invokestatic a : (Ljava/lang/Throwable;)Ljava/lang/Throwable;
    //   5305: athrow
    //   5306: aload #7
    //   5308: iconst_1
    //   5309: invokevirtual setAccessible : (Z)V
    //   5312: aload #7
    //   5314: aconst_null
    //   5315: invokevirtual get : (Ljava/lang/Object;)Ljava/lang/Object;
    //   5318: pop
    //   5319: iinc #6, 1
    //   5322: iload_2
    //   5323: ifeq -> 5184
    //   5326: sipush #31198
    //   5329: sipush #32682
    //   5332: invokestatic a : (II)Ljava/lang/String;
    //   5335: invokestatic forName : (Ljava/lang/String;)Ljava/lang/Class;
    //   5338: invokevirtual getDeclaredMethods : ()[Ljava/lang/reflect/Method;
    //   5341: astore #4
    //   5343: aload #4
    //   5345: arraylength
    //   5346: istore #5
    //   5348: iconst_0
    //   5349: istore #6
    //   5351: iload #6
    //   5353: iload #5
    //   5355: if_icmpge -> 5491
    //   5358: aload #4
    //   5360: iload #6
    //   5362: aaload
    //   5363: astore #7
    //   5365: aload #7
    //   5367: invokevirtual getParameterTypes : ()[Ljava/lang/Class;
    //   5370: pop
    //   5371: aload #7
    //   5373: invokevirtual getModifiers : ()I
    //   5376: invokestatic isStatic : (I)Z
    //   5379: ifeq -> 5477
    //   5382: aload #7
    //   5384: invokevirtual getParameterTypes : ()[Ljava/lang/Class;
    //   5387: arraylength
    //   5388: iconst_2
    //   5389: if_icmpne -> 5477
    //   5392: goto -> 5399
    //   5395: invokestatic a : (Ljava/lang/Throwable;)Ljava/lang/Throwable;
    //   5398: athrow
    //   5399: aload #7
    //   5401: invokevirtual getReturnType : ()Ljava/lang/Class;
    //   5404: getstatic java/lang/Boolean.TYPE : Ljava/lang/Class;
    //   5407: if_acmpne -> 5477
    //   5410: goto -> 5417
    //   5413: invokestatic a : (Ljava/lang/Throwable;)Ljava/lang/Throwable;
    //   5416: athrow
    //   5417: aload #7
    //   5419: iconst_1
    //   5420: invokevirtual setAccessible : (Z)V
    //   5423: aload #7
    //   5425: aconst_null
    //   5426: iconst_2
    //   5427: anewarray java/lang/Object
    //   5430: dup
    //   5431: iconst_0
    //   5432: aload_0
    //   5433: aastore
    //   5434: dup
    //   5435: iconst_1
    //   5436: aload_1
    //   5437: ifnonnull -> 5455
    //   5440: goto -> 5447
    //   5443: invokestatic a : (Ljava/lang/Throwable;)Ljava/lang/Throwable;
    //   5446: athrow
    //   5447: aload_1
    //   5448: goto -> 5462
    //   5451: invokestatic a : (Ljava/lang/Throwable;)Ljava/lang/Throwable;
    //   5454: athrow
    //   5455: aload_1
    //   5456: checkcast [B
    //   5459: invokevirtual clone : ()Ljava/lang/Object;
    //   5462: aastore
    //   5463: invokevirtual invoke : (Ljava/lang/Object;[Ljava/lang/Object;)Ljava/lang/Object;
    //   5466: checkcast java/lang/Boolean
    //   5469: invokevirtual booleanValue : ()Z
    //   5472: istore_3
    //   5473: iload_2
    //   5474: ifeq -> 5491
    //   5477: iinc #6, 1
    //   5480: iload_2
    //   5481: ifeq -> 5351
    //   5484: goto -> 5491
    //   5487: invokestatic a : (Ljava/lang/Throwable;)Ljava/lang/Throwable;
    //   5490: athrow
    //   5491: goto -> 5832
    //   5494: sipush #31175
    //   5497: sipush #-24071
    //   5500: invokestatic a : (II)Ljava/lang/String;
    //   5503: iconst_1
    //   5504: ldc burp/Zg0j
    //   5506: invokevirtual getClassLoader : ()Ljava/lang/ClassLoader;
    //   5509: invokestatic forName : (Ljava/lang/String;ZLjava/lang/ClassLoader;)Ljava/lang/Class;
    //   5512: invokevirtual getDeclaredFields : ()[Ljava/lang/reflect/Field;
    //   5515: astore #4
    //   5517: aload #4
    //   5519: arraylength
    //   5520: istore #5
    //   5522: iconst_0
    //   5523: istore #6
    //   5525: iload #6
    //   5527: iload #5
    //   5529: if_icmpge -> 5667
    //   5532: aload #4
    //   5534: iload #6
    //   5536: aaload
    //   5537: astore #7
    //   5539: aload #7
    //   5541: invokevirtual getModifiers : ()I
    //   5544: invokestatic isStatic : (I)Z
    //   5547: ifne -> 5557
    //   5550: goto -> 5660
    //   5553: invokestatic a : (Ljava/lang/Throwable;)Ljava/lang/Throwable;
    //   5556: athrow
    //   5557: aload #7
    //   5559: invokevirtual getType : ()Ljava/lang/Class;
    //   5562: astore #8
    //   5564: aload #8
    //   5566: ifnull -> 5647
    //   5569: aload #8
    //   5571: invokevirtual isPrimitive : ()Z
    //   5574: ifne -> 5647
    //   5577: goto -> 5584
    //   5580: invokestatic a : (Ljava/lang/Throwable;)Ljava/lang/Throwable;
    //   5583: athrow
    //   5584: aload #8
    //   5586: invokevirtual getPackage : ()Ljava/lang/Package;
    //   5589: ifnull -> 5647
    //   5592: goto -> 5599
    //   5595: invokestatic a : (Ljava/lang/Throwable;)Ljava/lang/Throwable;
    //   5598: athrow
    //   5599: aload #8
    //   5601: invokevirtual getPackage : ()Ljava/lang/Package;
    //   5604: invokevirtual getName : ()Ljava/lang/String;
    //   5607: ifnull -> 5647
    //   5610: goto -> 5617
    //   5613: invokestatic a : (Ljava/lang/Throwable;)Ljava/lang/Throwable;
    //   5616: athrow
    //   5617: aload #8
    //   5619: invokevirtual getPackage : ()Ljava/lang/Package;
    //   5622: invokevirtual getName : ()Ljava/lang/String;
    //   5625: sipush #31178
    //   5628: sipush #-21468
    //   5631: invokestatic a : (II)Ljava/lang/String;
    //   5634: invokevirtual startsWith : (Ljava/lang/String;)Z
    //   5637: ifne -> 5647
    //   5640: goto -> 5647
    //   5643: invokestatic a : (Ljava/lang/Throwable;)Ljava/lang/Throwable;
    //   5646: athrow
    //   5647: aload #7
    //   5649: iconst_1
    //   5650: invokevirtual setAccessible : (Z)V
    //   5653: aload #7
    //   5655: aconst_null
    //   5656: invokevirtual get : (Ljava/lang/Object;)Ljava/lang/Object;
    //   5659: pop
    //   5660: iinc #6, 1
    //   5663: iload_2
    //   5664: ifeq -> 5525
    //   5667: sipush #31172
    //   5670: sipush #9569
    //   5673: invokestatic a : (II)Ljava/lang/String;
    //   5676: invokestatic forName : (Ljava/lang/String;)Ljava/lang/Class;
    //   5679: invokevirtual getDeclaredMethods : ()[Ljava/lang/reflect/Method;
    //   5682: astore #4
    //   5684: aload #4
    //   5686: arraylength
    //   5687: istore #5
    //   5689: iconst_0
    //   5690: istore #6
    //   5692: iload #6
    //   5694: iload #5
    //   5696: if_icmpge -> 5832
    //   5699: aload #4
    //   5701: iload #6
    //   5703: aaload
    //   5704: astore #7
    //   5706: aload #7
    //   5708: invokevirtual getParameterTypes : ()[Ljava/lang/Class;
    //   5711: pop
    //   5712: aload #7
    //   5714: invokevirtual getModifiers : ()I
    //   5717: invokestatic isStatic : (I)Z
    //   5720: ifeq -> 5818
    //   5723: aload #7
    //   5725: invokevirtual getParameterTypes : ()[Ljava/lang/Class;
    //   5728: arraylength
    //   5729: iconst_2
    //   5730: if_icmpne -> 5818
    //   5733: goto -> 5740
    //   5736: invokestatic a : (Ljava/lang/Throwable;)Ljava/lang/Throwable;
    //   5739: athrow
    //   5740: aload #7
    //   5742: invokevirtual getReturnType : ()Ljava/lang/Class;
    //   5745: getstatic java/lang/Boolean.TYPE : Ljava/lang/Class;
    //   5748: if_acmpne -> 5818
    //   5751: goto -> 5758
    //   5754: invokestatic a : (Ljava/lang/Throwable;)Ljava/lang/Throwable;
    //   5757: athrow
    //   5758: aload #7
    //   5760: iconst_1
    //   5761: invokevirtual setAccessible : (Z)V
    //   5764: aload #7
    //   5766: aconst_null
    //   5767: iconst_2
    //   5768: anewarray java/lang/Object
    //   5771: dup
    //   5772: iconst_0
    //   5773: aload_0
    //   5774: aastore
    //   5775: dup
    //   5776: iconst_1
    //   5777: aload_1
    //   5778: ifnonnull -> 5796
    //   5781: goto -> 5788
    //   5784: invokestatic a : (Ljava/lang/Throwable;)Ljava/lang/Throwable;
    //   5787: athrow
    //   5788: aload_1
    //   5789: goto -> 5803
    //   5792: invokestatic a : (Ljava/lang/Throwable;)Ljava/lang/Throwable;
    //   5795: athrow
    //   5796: aload_1
    //   5797: checkcast [B
    //   5800: invokevirtual clone : ()Ljava/lang/Object;
    //   5803: aastore
    //   5804: invokevirtual invoke : (Ljava/lang/Object;[Ljava/lang/Object;)Ljava/lang/Object;
    //   5807: checkcast java/lang/Boolean
    //   5810: invokevirtual booleanValue : ()Z
    //   5813: istore_3
    //   5814: iload_2
    //   5815: ifeq -> 5832
    //   5818: iinc #6, 1
    //   5821: iload_2
    //   5822: ifeq -> 5692
    //   5825: goto -> 5832
    //   5828: invokestatic a : (Ljava/lang/Throwable;)Ljava/lang/Throwable;
    //   5831: athrow
    //   5832: iload_3
    //   5833: ifeq -> 5838
    //   5836: iload_3
    //   5837: ireturn
    //   5838: getstatic burp/Zxt7.Zi : Ljava/lang/String;
    //   5841: getstatic burp/Zgei.ZN : Ljava/lang/Object;
    //   5844: checkcast java/math/BigInteger
    //   5847: invokevirtual intValue : ()I
    //   5850: bipush #32
    //   5852: irem
    //   5853: invokestatic abs : (I)I
    //   5856: invokevirtual charAt : (I)C
    //   5859: getstatic burp/Zrd3.Z_ : Ljava/lang/String;
    //   5862: getstatic burp/Ze7e.Z_ : Ljava/lang/Object;
    //   5865: checkcast java/math/BigInteger
    //   5868: invokevirtual intValue : ()I
    //   5871: bipush #32
    //   5873: irem
    //   5874: invokestatic abs : (I)I
    //   5877: invokevirtual charAt : (I)C
    //   5880: if_icmple -> 6225
    //   5883: sipush #31199
    //   5886: sipush #-11032
    //   5889: invokestatic a : (II)Ljava/lang/String;
    //   5892: iconst_1
    //   5893: ldc burp/Zrfh
    //   5895: invokevirtual getClassLoader : ()Ljava/lang/ClassLoader;
    //   5898: invokestatic forName : (Ljava/lang/String;ZLjava/lang/ClassLoader;)Ljava/lang/Class;
    //   5901: invokevirtual getDeclaredFields : ()[Ljava/lang/reflect/Field;
    //   5904: astore #4
    //   5906: aload #4
    //   5908: arraylength
    //   5909: istore #5
    //   5911: iconst_0
    //   5912: istore #6
    //   5914: iload #6
    //   5916: iload #5
    //   5918: if_icmpge -> 6056
    //   5921: aload #4
    //   5923: iload #6
    //   5925: aaload
    //   5926: astore #7
    //   5928: aload #7
    //   5930: invokevirtual getModifiers : ()I
    //   5933: invokestatic isStatic : (I)Z
    //   5936: ifne -> 5946
    //   5939: goto -> 6049
    //   5942: invokestatic a : (Ljava/lang/Throwable;)Ljava/lang/Throwable;
    //   5945: athrow
    //   5946: aload #7
    //   5948: invokevirtual getType : ()Ljava/lang/Class;
    //   5951: astore #8
    //   5953: aload #8
    //   5955: ifnull -> 6036
    //   5958: aload #8
    //   5960: invokevirtual isPrimitive : ()Z
    //   5963: ifne -> 6036
    //   5966: goto -> 5973
    //   5969: invokestatic a : (Ljava/lang/Throwable;)Ljava/lang/Throwable;
    //   5972: athrow
    //   5973: aload #8
    //   5975: invokevirtual getPackage : ()Ljava/lang/Package;
    //   5978: ifnull -> 6036
    //   5981: goto -> 5988
    //   5984: invokestatic a : (Ljava/lang/Throwable;)Ljava/lang/Throwable;
    //   5987: athrow
    //   5988: aload #8
    //   5990: invokevirtual getPackage : ()Ljava/lang/Package;
    //   5993: invokevirtual getName : ()Ljava/lang/String;
    //   5996: ifnull -> 6036
    //   5999: goto -> 6006
    //   6002: invokestatic a : (Ljava/lang/Throwable;)Ljava/lang/Throwable;
    //   6005: athrow
    //   6006: aload #8
    //   6008: invokevirtual getPackage : ()Ljava/lang/Package;
    //   6011: invokevirtual getName : ()Ljava/lang/String;
    //   6014: sipush #31178
    //   6017: sipush #-21468
    //   6020: invokestatic a : (II)Ljava/lang/String;
    //   6023: invokevirtual startsWith : (Ljava/lang/String;)Z
    //   6026: ifne -> 6036
    //   6029: goto -> 6036
    //   6032: invokestatic a : (Ljava/lang/Throwable;)Ljava/lang/Throwable;
    //   6035: athrow
    //   6036: aload #7
    //   6038: iconst_1
    //   6039: invokevirtual setAccessible : (Z)V
    //   6042: aload #7
    //   6044: aconst_null
    //   6045: invokevirtual get : (Ljava/lang/Object;)Ljava/lang/Object;
    //   6048: pop
    //   6049: iinc #6, 1
    //   6052: iload_2
    //   6053: ifeq -> 5914
    //   6056: sipush #31192
    //   6059: sipush #-19498
    //   6062: invokestatic a : (II)Ljava/lang/String;
    //   6065: invokestatic forName : (Ljava/lang/String;)Ljava/lang/Class;
    //   6068: invokevirtual getDeclaredMethods : ()[Ljava/lang/reflect/Method;
    //   6071: astore #4
    //   6073: aload #4
    //   6075: arraylength
    //   6076: istore #5
    //   6078: iconst_0
    //   6079: istore #6
    //   6081: iload #6
    //   6083: iload #5
    //   6085: if_icmpge -> 6221
    //   6088: aload #4
    //   6090: iload #6
    //   6092: aaload
    //   6093: astore #7
    //   6095: aload #7
    //   6097: invokevirtual getParameterTypes : ()[Ljava/lang/Class;
    //   6100: pop
    //   6101: aload #7
    //   6103: invokevirtual getModifiers : ()I
    //   6106: invokestatic isStatic : (I)Z
    //   6109: ifeq -> 6207
    //   6112: aload #7
    //   6114: invokevirtual getParameterTypes : ()[Ljava/lang/Class;
    //   6117: arraylength
    //   6118: iconst_2
    //   6119: if_icmpne -> 6207
    //   6122: goto -> 6129
    //   6125: invokestatic a : (Ljava/lang/Throwable;)Ljava/lang/Throwable;
    //   6128: athrow
    //   6129: aload #7
    //   6131: invokevirtual getReturnType : ()Ljava/lang/Class;
    //   6134: getstatic java/lang/Boolean.TYPE : Ljava/lang/Class;
    //   6137: if_acmpne -> 6207
    //   6140: goto -> 6147
    //   6143: invokestatic a : (Ljava/lang/Throwable;)Ljava/lang/Throwable;
    //   6146: athrow
    //   6147: aload #7
    //   6149: iconst_1
    //   6150: invokevirtual setAccessible : (Z)V
    //   6153: aload #7
    //   6155: aconst_null
    //   6156: iconst_2
    //   6157: anewarray java/lang/Object
    //   6160: dup
    //   6161: iconst_0
    //   6162: aload_0
    //   6163: aastore
    //   6164: dup
    //   6165: iconst_1
    //   6166: aload_1
    //   6167: ifnonnull -> 6185
    //   6170: goto -> 6177
    //   6173: invokestatic a : (Ljava/lang/Throwable;)Ljava/lang/Throwable;
    //   6176: athrow
    //   6177: aload_1
    //   6178: goto -> 6192
    //   6181: invokestatic a : (Ljava/lang/Throwable;)Ljava/lang/Throwable;
    //   6184: athrow
    //   6185: aload_1
    //   6186: checkcast [B
    //   6189: invokevirtual clone : ()Ljava/lang/Object;
    //   6192: aastore
    //   6193: invokevirtual invoke : (Ljava/lang/Object;[Ljava/lang/Object;)Ljava/lang/Object;
    //   6196: checkcast java/lang/Boolean
    //   6199: invokevirtual booleanValue : ()Z
    //   6202: istore_3
    //   6203: iload_2
    //   6204: ifeq -> 6221
    //   6207: iinc #6, 1
    //   6210: iload_2
    //   6211: ifeq -> 6081
    //   6214: goto -> 6221
    //   6217: invokestatic a : (Ljava/lang/Throwable;)Ljava/lang/Throwable;
    //   6220: athrow
    //   6221: iload_2
    //   6222: ifeq -> 6563
    //   6225: sipush #31179
    //   6228: sipush #-26838
    //   6231: invokestatic a : (II)Ljava/lang/String;
    //   6234: iconst_1
    //   6235: ldc burp/Ze0w
    //   6237: invokevirtual getClassLoader : ()Ljava/lang/ClassLoader;
    //   6240: invokestatic forName : (Ljava/lang/String;ZLjava/lang/ClassLoader;)Ljava/lang/Class;
    //   6243: invokevirtual getDeclaredFields : ()[Ljava/lang/reflect/Field;
    //   6246: astore #4
    //   6248: aload #4
    //   6250: arraylength
    //   6251: istore #5
    //   6253: iconst_0
    //   6254: istore #6
    //   6256: iload #6
    //   6258: iload #5
    //   6260: if_icmpge -> 6398
    //   6263: aload #4
    //   6265: iload #6
    //   6267: aaload
    //   6268: astore #7
    //   6270: aload #7
    //   6272: invokevirtual getModifiers : ()I
    //   6275: invokestatic isStatic : (I)Z
    //   6278: ifne -> 6288
    //   6281: goto -> 6391
    //   6284: invokestatic a : (Ljava/lang/Throwable;)Ljava/lang/Throwable;
    //   6287: athrow
    //   6288: aload #7
    //   6290: invokevirtual getType : ()Ljava/lang/Class;
    //   6293: astore #8
    //   6295: aload #8
    //   6297: ifnull -> 6378
    //   6300: aload #8
    //   6302: invokevirtual isPrimitive : ()Z
    //   6305: ifne -> 6378
    //   6308: goto -> 6315
    //   6311: invokestatic a : (Ljava/lang/Throwable;)Ljava/lang/Throwable;
    //   6314: athrow
    //   6315: aload #8
    //   6317: invokevirtual getPackage : ()Ljava/lang/Package;
    //   6320: ifnull -> 6378
    //   6323: goto -> 6330
    //   6326: invokestatic a : (Ljava/lang/Throwable;)Ljava/lang/Throwable;
    //   6329: athrow
    //   6330: aload #8
    //   6332: invokevirtual getPackage : ()Ljava/lang/Package;
    //   6335: invokevirtual getName : ()Ljava/lang/String;
    //   6338: ifnull -> 6378
    //   6341: goto -> 6348
    //   6344: invokestatic a : (Ljava/lang/Throwable;)Ljava/lang/Throwable;
    //   6347: athrow
    //   6348: aload #8
    //   6350: invokevirtual getPackage : ()Ljava/lang/Package;
    //   6353: invokevirtual getName : ()Ljava/lang/String;
    //   6356: sipush #31178
    //   6359: sipush #-21468
    //   6362: invokestatic a : (II)Ljava/lang/String;
    //   6365: invokevirtual startsWith : (Ljava/lang/String;)Z
    //   6368: ifne -> 6378
    //   6371: goto -> 6378
    //   6374: invokestatic a : (Ljava/lang/Throwable;)Ljava/lang/Throwable;
    //   6377: athrow
    //   6378: aload #7
    //   6380: iconst_1
    //   6381: invokevirtual setAccessible : (Z)V
    //   6384: aload #7
    //   6386: aconst_null
    //   6387: invokevirtual get : (Ljava/lang/Object;)Ljava/lang/Object;
    //   6390: pop
    //   6391: iinc #6, 1
    //   6394: iload_2
    //   6395: ifeq -> 6256
    //   6398: sipush #31171
    //   6401: sipush #-8728
    //   6404: invokestatic a : (II)Ljava/lang/String;
    //   6407: invokestatic forName : (Ljava/lang/String;)Ljava/lang/Class;
    //   6410: invokevirtual getDeclaredMethods : ()[Ljava/lang/reflect/Method;
    //   6413: astore #4
    //   6415: aload #4
    //   6417: arraylength
    //   6418: istore #5
    //   6420: iconst_0
    //   6421: istore #6
    //   6423: iload #6
    //   6425: iload #5
    //   6427: if_icmpge -> 6563
    //   6430: aload #4
    //   6432: iload #6
    //   6434: aaload
    //   6435: astore #7
    //   6437: aload #7
    //   6439: invokevirtual getParameterTypes : ()[Ljava/lang/Class;
    //   6442: pop
    //   6443: aload #7
    //   6445: invokevirtual getModifiers : ()I
    //   6448: invokestatic isStatic : (I)Z
    //   6451: ifeq -> 6549
    //   6454: aload #7
    //   6456: invokevirtual getParameterTypes : ()[Ljava/lang/Class;
    //   6459: arraylength
    //   6460: iconst_2
    //   6461: if_icmpne -> 6549
    //   6464: goto -> 6471
    //   6467: invokestatic a : (Ljava/lang/Throwable;)Ljava/lang/Throwable;
    //   6470: athrow
    //   6471: aload #7
    //   6473: invokevirtual getReturnType : ()Ljava/lang/Class;
    //   6476: getstatic java/lang/Boolean.TYPE : Ljava/lang/Class;
    //   6479: if_acmpne -> 6549
    //   6482: goto -> 6489
    //   6485: invokestatic a : (Ljava/lang/Throwable;)Ljava/lang/Throwable;
    //   6488: athrow
    //   6489: aload #7
    //   6491: iconst_1
    //   6492: invokevirtual setAccessible : (Z)V
    //   6495: aload #7
    //   6497: aconst_null
    //   6498: iconst_2
    //   6499: anewarray java/lang/Object
    //   6502: dup
    //   6503: iconst_0
    //   6504: aload_0
    //   6505: aastore
    //   6506: dup
    //   6507: iconst_1
    //   6508: aload_1
    //   6509: ifnonnull -> 6527
    //   6512: goto -> 6519
    //   6515: invokestatic a : (Ljava/lang/Throwable;)Ljava/lang/Throwable;
    //   6518: athrow
    //   6519: aload_1
    //   6520: goto -> 6534
    //   6523: invokestatic a : (Ljava/lang/Throwable;)Ljava/lang/Throwable;
    //   6526: athrow
    //   6527: aload_1
    //   6528: checkcast [B
    //   6531: invokevirtual clone : ()Ljava/lang/Object;
    //   6534: aastore
    //   6535: invokevirtual invoke : (Ljava/lang/Object;[Ljava/lang/Object;)Ljava/lang/Object;
    //   6538: checkcast java/lang/Boolean
    //   6541: invokevirtual booleanValue : ()Z
    //   6544: istore_3
    //   6545: iload_2
    //   6546: ifeq -> 6563
    //   6549: iinc #6, 1
    //   6552: iload_2
    //   6553: ifeq -> 6423
    //   6556: goto -> 6563
    //   6559: invokestatic a : (Ljava/lang/Throwable;)Ljava/lang/Throwable;
    //   6562: athrow
    //   6563: iload_3
    //   6564: ifeq -> 6569
    //   6567: iload_3
    //   6568: ireturn
    //   6569: getstatic burp/Zzmc.Zr : Ljava/lang/String;
    //   6572: getstatic burp/Zkdq.ZG : Ljava/lang/Object;
    //   6575: checkcast java/math/BigInteger
    //   6578: invokevirtual intValue : ()I
    //   6581: bipush #32
    //   6583: irem
    //   6584: invokestatic abs : (I)I
    //   6587: invokevirtual charAt : (I)C
    //   6590: getstatic burp/Ze1k.ZI : Ljava/lang/String;
    //   6593: getstatic burp/Zmkq.Zg : Ljava/lang/Object;
    //   6596: checkcast java/math/BigInteger
    //   6599: invokevirtual intValue : ()I
    //   6602: bipush #32
    //   6604: irem
    //   6605: invokestatic abs : (I)I
    //   6608: invokevirtual charAt : (I)C
    //   6611: if_icmple -> 6956
    //   6614: sipush #31189
    //   6617: sipush #-27434
    //   6620: invokestatic a : (II)Ljava/lang/String;
    //   6623: iconst_1
    //   6624: ldc burp/Zrxm
    //   6626: invokevirtual getClassLoader : ()Ljava/lang/ClassLoader;
    //   6629: invokestatic forName : (Ljava/lang/String;ZLjava/lang/ClassLoader;)Ljava/lang/Class;
    //   6632: invokevirtual getDeclaredFields : ()[Ljava/lang/reflect/Field;
    //   6635: astore #4
    //   6637: aload #4
    //   6639: arraylength
    //   6640: istore #5
    //   6642: iconst_0
    //   6643: istore #6
    //   6645: iload #6
    //   6647: iload #5
    //   6649: if_icmpge -> 6787
    //   6652: aload #4
    //   6654: iload #6
    //   6656: aaload
    //   6657: astore #7
    //   6659: aload #7
    //   6661: invokevirtual getModifiers : ()I
    //   6664: invokestatic isStatic : (I)Z
    //   6667: ifne -> 6677
    //   6670: goto -> 6780
    //   6673: invokestatic a : (Ljava/lang/Throwable;)Ljava/lang/Throwable;
    //   6676: athrow
    //   6677: aload #7
    //   6679: invokevirtual getType : ()Ljava/lang/Class;
    //   6682: astore #8
    //   6684: aload #8
    //   6686: ifnull -> 6767
    //   6689: aload #8
    //   6691: invokevirtual isPrimitive : ()Z
    //   6694: ifne -> 6767
    //   6697: goto -> 6704
    //   6700: invokestatic a : (Ljava/lang/Throwable;)Ljava/lang/Throwable;
    //   6703: athrow
    //   6704: aload #8
    //   6706: invokevirtual getPackage : ()Ljava/lang/Package;
    //   6709: ifnull -> 6767
    //   6712: goto -> 6719
    //   6715: invokestatic a : (Ljava/lang/Throwable;)Ljava/lang/Throwable;
    //   6718: athrow
    //   6719: aload #8
    //   6721: invokevirtual getPackage : ()Ljava/lang/Package;
    //   6724: invokevirtual getName : ()Ljava/lang/String;
    //   6727: ifnull -> 6767
    //   6730: goto -> 6737
    //   6733: invokestatic a : (Ljava/lang/Throwable;)Ljava/lang/Throwable;
    //   6736: athrow
    //   6737: aload #8
    //   6739: invokevirtual getPackage : ()Ljava/lang/Package;
    //   6742: invokevirtual getName : ()Ljava/lang/String;
    //   6745: sipush #31178
    //   6748: sipush #-21468
    //   6751: invokestatic a : (II)Ljava/lang/String;
    //   6754: invokevirtual startsWith : (Ljava/lang/String;)Z
    //   6757: ifne -> 6767
    //   6760: goto -> 6767
    //   6763: invokestatic a : (Ljava/lang/Throwable;)Ljava/lang/Throwable;
    //   6766: athrow
    //   6767: aload #7
    //   6769: iconst_1
    //   6770: invokevirtual setAccessible : (Z)V
    //   6773: aload #7
    //   6775: aconst_null
    //   6776: invokevirtual get : (Ljava/lang/Object;)Ljava/lang/Object;
    //   6779: pop
    //   6780: iinc #6, 1
    //   6783: iload_2
    //   6784: ifeq -> 6645
    //   6787: sipush #31180
    //   6790: sipush #-30894
    //   6793: invokestatic a : (II)Ljava/lang/String;
    //   6796: invokestatic forName : (Ljava/lang/String;)Ljava/lang/Class;
    //   6799: invokevirtual getDeclaredMethods : ()[Ljava/lang/reflect/Method;
    //   6802: astore #4
    //   6804: aload #4
    //   6806: arraylength
    //   6807: istore #5
    //   6809: iconst_0
    //   6810: istore #6
    //   6812: iload #6
    //   6814: iload #5
    //   6816: if_icmpge -> 6952
    //   6819: aload #4
    //   6821: iload #6
    //   6823: aaload
    //   6824: astore #7
    //   6826: aload #7
    //   6828: invokevirtual getParameterTypes : ()[Ljava/lang/Class;
    //   6831: pop
    //   6832: aload #7
    //   6834: invokevirtual getModifiers : ()I
    //   6837: invokestatic isStatic : (I)Z
    //   6840: ifeq -> 6938
    //   6843: aload #7
    //   6845: invokevirtual getParameterTypes : ()[Ljava/lang/Class;
    //   6848: arraylength
    //   6849: iconst_2
    //   6850: if_icmpne -> 6938
    //   6853: goto -> 6860
    //   6856: invokestatic a : (Ljava/lang/Throwable;)Ljava/lang/Throwable;
    //   6859: athrow
    //   6860: aload #7
    //   6862: invokevirtual getReturnType : ()Ljava/lang/Class;
    //   6865: getstatic java/lang/Boolean.TYPE : Ljava/lang/Class;
    //   6868: if_acmpne -> 6938
    //   6871: goto -> 6878
    //   6874: invokestatic a : (Ljava/lang/Throwable;)Ljava/lang/Throwable;
    //   6877: athrow
    //   6878: aload #7
    //   6880: iconst_1
    //   6881: invokevirtual setAccessible : (Z)V
    //   6884: aload #7
    //   6886: aconst_null
    //   6887: iconst_2
    //   6888: anewarray java/lang/Object
    //   6891: dup
    //   6892: iconst_0
    //   6893: aload_0
    //   6894: aastore
    //   6895: dup
    //   6896: iconst_1
    //   6897: aload_1
    //   6898: ifnonnull -> 6916
    //   6901: goto -> 6908
    //   6904: invokestatic a : (Ljava/lang/Throwable;)Ljava/lang/Throwable;
    //   6907: athrow
    //   6908: aload_1
    //   6909: goto -> 6923
    //   6912: invokestatic a : (Ljava/lang/Throwable;)Ljava/lang/Throwable;
    //   6915: athrow
    //   6916: aload_1
    //   6917: checkcast [B
    //   6920: invokevirtual clone : ()Ljava/lang/Object;
    //   6923: aastore
    //   6924: invokevirtual invoke : (Ljava/lang/Object;[Ljava/lang/Object;)Ljava/lang/Object;
    //   6927: checkcast java/lang/Boolean
    //   6930: invokevirtual booleanValue : ()Z
    //   6933: istore_3
    //   6934: iload_2
    //   6935: ifeq -> 6952
    //   6938: iinc #6, 1
    //   6941: iload_2
    //   6942: ifeq -> 6812
    //   6945: goto -> 6952
    //   6948: invokestatic a : (Ljava/lang/Throwable;)Ljava/lang/Throwable;
    //   6951: athrow
    //   6952: iload_2
    //   6953: ifeq -> 7294
    //   6956: sipush #31181
    //   6959: sipush #17401
    //   6962: invokestatic a : (II)Ljava/lang/String;
    //   6965: iconst_1
    //   6966: ldc burp/Zre1
    //   6968: invokevirtual getClassLoader : ()Ljava/lang/ClassLoader;
    //   6971: invokestatic forName : (Ljava/lang/String;ZLjava/lang/ClassLoader;)Ljava/lang/Class;
    //   6974: invokevirtual getDeclaredFields : ()[Ljava/lang/reflect/Field;
    //   6977: astore #4
    //   6979: aload #4
    //   6981: arraylength
    //   6982: istore #5
    //   6984: iconst_0
    //   6985: istore #6
    //   6987: iload #6
    //   6989: iload #5
    //   6991: if_icmpge -> 7129
    //   6994: aload #4
    //   6996: iload #6
    //   6998: aaload
    //   6999: astore #7
    //   7001: aload #7
    //   7003: invokevirtual getModifiers : ()I
    //   7006: invokestatic isStatic : (I)Z
    //   7009: ifne -> 7019
    //   7012: goto -> 7122
    //   7015: invokestatic a : (Ljava/lang/Throwable;)Ljava/lang/Throwable;
    //   7018: athrow
    //   7019: aload #7
    //   7021: invokevirtual getType : ()Ljava/lang/Class;
    //   7024: astore #8
    //   7026: aload #8
    //   7028: ifnull -> 7109
    //   7031: aload #8
    //   7033: invokevirtual isPrimitive : ()Z
    //   7036: ifne -> 7109
    //   7039: goto -> 7046
    //   7042: invokestatic a : (Ljava/lang/Throwable;)Ljava/lang/Throwable;
    //   7045: athrow
    //   7046: aload #8
    //   7048: invokevirtual getPackage : ()Ljava/lang/Package;
    //   7051: ifnull -> 7109
    //   7054: goto -> 7061
    //   7057: invokestatic a : (Ljava/lang/Throwable;)Ljava/lang/Throwable;
    //   7060: athrow
    //   7061: aload #8
    //   7063: invokevirtual getPackage : ()Ljava/lang/Package;
    //   7066: invokevirtual getName : ()Ljava/lang/String;
    //   7069: ifnull -> 7109
    //   7072: goto -> 7079
    //   7075: invokestatic a : (Ljava/lang/Throwable;)Ljava/lang/Throwable;
    //   7078: athrow
    //   7079: aload #8
    //   7081: invokevirtual getPackage : ()Ljava/lang/Package;
    //   7084: invokevirtual getName : ()Ljava/lang/String;
    //   7087: sipush #31178
    //   7090: sipush #-21468
    //   7093: invokestatic a : (II)Ljava/lang/String;
    //   7096: invokevirtual startsWith : (Ljava/lang/String;)Z
    //   7099: ifne -> 7109
    //   7102: goto -> 7109
    //   7105: invokestatic a : (Ljava/lang/Throwable;)Ljava/lang/Throwable;
    //   7108: athrow
    //   7109: aload #7
    //   7111: iconst_1
    //   7112: invokevirtual setAccessible : (Z)V
    //   7115: aload #7
    //   7117: aconst_null
    //   7118: invokevirtual get : (Ljava/lang/Object;)Ljava/lang/Object;
    //   7121: pop
    //   7122: iinc #6, 1
    //   7125: iload_2
    //   7126: ifeq -> 6987
    //   7129: sipush #31183
    //   7132: sipush #-30527
    //   7135: invokestatic a : (II)Ljava/lang/String;
    //   7138: invokestatic forName : (Ljava/lang/String;)Ljava/lang/Class;
    //   7141: invokevirtual getDeclaredMethods : ()[Ljava/lang/reflect/Method;
    //   7144: astore #4
    //   7146: aload #4
    //   7148: arraylength
    //   7149: istore #5
    //   7151: iconst_0
    //   7152: istore #6
    //   7154: iload #6
    //   7156: iload #5
    //   7158: if_icmpge -> 7294
    //   7161: aload #4
    //   7163: iload #6
    //   7165: aaload
    //   7166: astore #7
    //   7168: aload #7
    //   7170: invokevirtual getParameterTypes : ()[Ljava/lang/Class;
    //   7173: pop
    //   7174: aload #7
    //   7176: invokevirtual getModifiers : ()I
    //   7179: invokestatic isStatic : (I)Z
    //   7182: ifeq -> 7280
    //   7185: aload #7
    //   7187: invokevirtual getParameterTypes : ()[Ljava/lang/Class;
    //   7190: arraylength
    //   7191: iconst_2
    //   7192: if_icmpne -> 7280
    //   7195: goto -> 7202
    //   7198: invokestatic a : (Ljava/lang/Throwable;)Ljava/lang/Throwable;
    //   7201: athrow
    //   7202: aload #7
    //   7204: invokevirtual getReturnType : ()Ljava/lang/Class;
    //   7207: getstatic java/lang/Boolean.TYPE : Ljava/lang/Class;
    //   7210: if_acmpne -> 7280
    //   7213: goto -> 7220
    //   7216: invokestatic a : (Ljava/lang/Throwable;)Ljava/lang/Throwable;
    //   7219: athrow
    //   7220: aload #7
    //   7222: iconst_1
    //   7223: invokevirtual setAccessible : (Z)V
    //   7226: aload #7
    //   7228: aconst_null
    //   7229: iconst_2
    //   7230: anewarray java/lang/Object
    //   7233: dup
    //   7234: iconst_0
    //   7235: aload_0
    //   7236: aastore
    //   7237: dup
    //   7238: iconst_1
    //   7239: aload_1
    //   7240: ifnonnull -> 7258
    //   7243: goto -> 7250
    //   7246: invokestatic a : (Ljava/lang/Throwable;)Ljava/lang/Throwable;
    //   7249: athrow
    //   7250: aload_1
    //   7251: goto -> 7265
    //   7254: invokestatic a : (Ljava/lang/Throwable;)Ljava/lang/Throwable;
    //   7257: athrow
    //   7258: aload_1
    //   7259: checkcast [B
    //   7262: invokevirtual clone : ()Ljava/lang/Object;
    //   7265: aastore
    //   7266: invokevirtual invoke : (Ljava/lang/Object;[Ljava/lang/Object;)Ljava/lang/Object;
    //   7269: checkcast java/lang/Boolean
    //   7272: invokevirtual booleanValue : ()Z
    //   7275: istore_3
    //   7276: iload_2
    //   7277: ifeq -> 7294
    //   7280: iinc #6, 1
    //   7283: iload_2
    //   7284: ifeq -> 7154
    //   7287: goto -> 7294
    //   7290: invokestatic a : (Ljava/lang/Throwable;)Ljava/lang/Throwable;
    //   7293: athrow
    //   7294: iload_3
    //   7295: ifeq -> 7300
    //   7298: iload_3
    //   7299: ireturn
    //   7300: getstatic burp/Zld5.ZO : Ljava/lang/String;
    //   7303: getstatic burp/Zezi.ZQ : Ljava/lang/Object;
    //   7306: checkcast java/math/BigInteger
    //   7309: invokevirtual intValue : ()I
    //   7312: bipush #32
    //   7314: irem
    //   7315: invokestatic abs : (I)I
    //   7318: invokevirtual charAt : (I)C
    //   7321: getstatic burp/Zrn4.ZY : Ljava/lang/String;
    //   7324: getstatic burp/Zbli.Zo : Ljava/lang/Object;
    //   7327: checkcast java/math/BigInteger
    //   7330: invokevirtual intValue : ()I
    //   7333: bipush #32
    //   7335: irem
    //   7336: invokestatic abs : (I)I
    //   7339: invokevirtual charAt : (I)C
    //   7342: if_icmple -> 7687
    //   7345: sipush #31173
    //   7348: sipush #-25759
    //   7351: invokestatic a : (II)Ljava/lang/String;
    //   7354: iconst_1
    //   7355: ldc burp/Ztfr
    //   7357: invokevirtual getClassLoader : ()Ljava/lang/ClassLoader;
    //   7360: invokestatic forName : (Ljava/lang/String;ZLjava/lang/ClassLoader;)Ljava/lang/Class;
    //   7363: invokevirtual getDeclaredFields : ()[Ljava/lang/reflect/Field;
    //   7366: astore #4
    //   7368: aload #4
    //   7370: arraylength
    //   7371: istore #5
    //   7373: iconst_0
    //   7374: istore #6
    //   7376: iload #6
    //   7378: iload #5
    //   7380: if_icmpge -> 7518
    //   7383: aload #4
    //   7385: iload #6
    //   7387: aaload
    //   7388: astore #7
    //   7390: aload #7
    //   7392: invokevirtual getModifiers : ()I
    //   7395: invokestatic isStatic : (I)Z
    //   7398: ifne -> 7408
    //   7401: goto -> 7511
    //   7404: invokestatic a : (Ljava/lang/Throwable;)Ljava/lang/Throwable;
    //   7407: athrow
    //   7408: aload #7
    //   7410: invokevirtual getType : ()Ljava/lang/Class;
    //   7413: astore #8
    //   7415: aload #8
    //   7417: ifnull -> 7498
    //   7420: aload #8
    //   7422: invokevirtual isPrimitive : ()Z
    //   7425: ifne -> 7498
    //   7428: goto -> 7435
    //   7431: invokestatic a : (Ljava/lang/Throwable;)Ljava/lang/Throwable;
    //   7434: athrow
    //   7435: aload #8
    //   7437: invokevirtual getPackage : ()Ljava/lang/Package;
    //   7440: ifnull -> 7498
    //   7443: goto -> 7450
    //   7446: invokestatic a : (Ljava/lang/Throwable;)Ljava/lang/Throwable;
    //   7449: athrow
    //   7450: aload #8
    //   7452: invokevirtual getPackage : ()Ljava/lang/Package;
    //   7455: invokevirtual getName : ()Ljava/lang/String;
    //   7458: ifnull -> 7498
    //   7461: goto -> 7468
    //   7464: invokestatic a : (Ljava/lang/Throwable;)Ljava/lang/Throwable;
    //   7467: athrow
    //   7468: aload #8
    //   7470: invokevirtual getPackage : ()Ljava/lang/Package;
    //   7473: invokevirtual getName : ()Ljava/lang/String;
    //   7476: sipush #31178
    //   7479: sipush #-21468
    //   7482: invokestatic a : (II)Ljava/lang/String;
    //   7485: invokevirtual startsWith : (Ljava/lang/String;)Z
    //   7488: ifne -> 7498
    //   7491: goto -> 7498
    //   7494: invokestatic a : (Ljava/lang/Throwable;)Ljava/lang/Throwable;
    //   7497: athrow
    //   7498: aload #7
    //   7500: iconst_1
    //   7501: invokevirtual setAccessible : (Z)V
    //   7504: aload #7
    //   7506: aconst_null
    //   7507: invokevirtual get : (Ljava/lang/Object;)Ljava/lang/Object;
    //   7510: pop
    //   7511: iinc #6, 1
    //   7514: iload_2
    //   7515: ifeq -> 7376
    //   7518: sipush #31197
    //   7521: sipush #-8879
    //   7524: invokestatic a : (II)Ljava/lang/String;
    //   7527: invokestatic forName : (Ljava/lang/String;)Ljava/lang/Class;
    //   7530: invokevirtual getDeclaredMethods : ()[Ljava/lang/reflect/Method;
    //   7533: astore #4
    //   7535: aload #4
    //   7537: arraylength
    //   7538: istore #5
    //   7540: iconst_0
    //   7541: istore #6
    //   7543: iload #6
    //   7545: iload #5
    //   7547: if_icmpge -> 7683
    //   7550: aload #4
    //   7552: iload #6
    //   7554: aaload
    //   7555: astore #7
    //   7557: aload #7
    //   7559: invokevirtual getParameterTypes : ()[Ljava/lang/Class;
    //   7562: pop
    //   7563: aload #7
    //   7565: invokevirtual getModifiers : ()I
    //   7568: invokestatic isStatic : (I)Z
    //   7571: ifeq -> 7669
    //   7574: aload #7
    //   7576: invokevirtual getParameterTypes : ()[Ljava/lang/Class;
    //   7579: arraylength
    //   7580: iconst_2
    //   7581: if_icmpne -> 7669
    //   7584: goto -> 7591
    //   7587: invokestatic a : (Ljava/lang/Throwable;)Ljava/lang/Throwable;
    //   7590: athrow
    //   7591: aload #7
    //   7593: invokevirtual getReturnType : ()Ljava/lang/Class;
    //   7596: getstatic java/lang/Boolean.TYPE : Ljava/lang/Class;
    //   7599: if_acmpne -> 7669
    //   7602: goto -> 7609
    //   7605: invokestatic a : (Ljava/lang/Throwable;)Ljava/lang/Throwable;
    //   7608: athrow
    //   7609: aload #7
    //   7611: iconst_1
    //   7612: invokevirtual setAccessible : (Z)V
    //   7615: aload #7
    //   7617: aconst_null
    //   7618: iconst_2
    //   7619: anewarray java/lang/Object
    //   7622: dup
    //   7623: iconst_0
    //   7624: aload_0
    //   7625: aastore
    //   7626: dup
    //   7627: iconst_1
    //   7628: aload_1
    //   7629: ifnonnull -> 7647
    //   7632: goto -> 7639
    //   7635: invokestatic a : (Ljava/lang/Throwable;)Ljava/lang/Throwable;
    //   7638: athrow
    //   7639: aload_1
    //   7640: goto -> 7654
    //   7643: invokestatic a : (Ljava/lang/Throwable;)Ljava/lang/Throwable;
    //   7646: athrow
    //   7647: aload_1
    //   7648: checkcast [B
    //   7651: invokevirtual clone : ()Ljava/lang/Object;
    //   7654: aastore
    //   7655: invokevirtual invoke : (Ljava/lang/Object;[Ljava/lang/Object;)Ljava/lang/Object;
    //   7658: checkcast java/lang/Boolean
    //   7661: invokevirtual booleanValue : ()Z
    //   7664: istore_3
    //   7665: iload_2
    //   7666: ifeq -> 7683
    //   7669: iinc #6, 1
    //   7672: iload_2
    //   7673: ifeq -> 7543
    //   7676: goto -> 7683
    //   7679: invokestatic a : (Ljava/lang/Throwable;)Ljava/lang/Throwable;
    //   7682: athrow
    //   7683: iload_2
    //   7684: ifeq -> 8025
    //   7687: sipush #31193
    //   7690: sipush #17861
    //   7693: invokestatic a : (II)Ljava/lang/String;
    //   7696: iconst_1
    //   7697: ldc burp/Zzh1
    //   7699: invokevirtual getClassLoader : ()Ljava/lang/ClassLoader;
    //   7702: invokestatic forName : (Ljava/lang/String;ZLjava/lang/ClassLoader;)Ljava/lang/Class;
    //   7705: invokevirtual getDeclaredFields : ()[Ljava/lang/reflect/Field;
    //   7708: astore #4
    //   7710: aload #4
    //   7712: arraylength
    //   7713: istore #5
    //   7715: iconst_0
    //   7716: istore #6
    //   7718: iload #6
    //   7720: iload #5
    //   7722: if_icmpge -> 7860
    //   7725: aload #4
    //   7727: iload #6
    //   7729: aaload
    //   7730: astore #7
    //   7732: aload #7
    //   7734: invokevirtual getModifiers : ()I
    //   7737: invokestatic isStatic : (I)Z
    //   7740: ifne -> 7750
    //   7743: goto -> 7853
    //   7746: invokestatic a : (Ljava/lang/Throwable;)Ljava/lang/Throwable;
    //   7749: athrow
    //   7750: aload #7
    //   7752: invokevirtual getType : ()Ljava/lang/Class;
    //   7755: astore #8
    //   7757: aload #8
    //   7759: ifnull -> 7840
    //   7762: aload #8
    //   7764: invokevirtual isPrimitive : ()Z
    //   7767: ifne -> 7840
    //   7770: goto -> 7777
    //   7773: invokestatic a : (Ljava/lang/Throwable;)Ljava/lang/Throwable;
    //   7776: athrow
    //   7777: aload #8
    //   7779: invokevirtual getPackage : ()Ljava/lang/Package;
    //   7782: ifnull -> 7840
    //   7785: goto -> 7792
    //   7788: invokestatic a : (Ljava/lang/Throwable;)Ljava/lang/Throwable;
    //   7791: athrow
    //   7792: aload #8
    //   7794: invokevirtual getPackage : ()Ljava/lang/Package;
    //   7797: invokevirtual getName : ()Ljava/lang/String;
    //   7800: ifnull -> 7840
    //   7803: goto -> 7810
    //   7806: invokestatic a : (Ljava/lang/Throwable;)Ljava/lang/Throwable;
    //   7809: athrow
    //   7810: aload #8
    //   7812: invokevirtual getPackage : ()Ljava/lang/Package;
    //   7815: invokevirtual getName : ()Ljava/lang/String;
    //   7818: sipush #31178
    //   7821: sipush #-21468
    //   7824: invokestatic a : (II)Ljava/lang/String;
    //   7827: invokevirtual startsWith : (Ljava/lang/String;)Z
    //   7830: ifne -> 7840
    //   7833: goto -> 7840
    //   7836: invokestatic a : (Ljava/lang/Throwable;)Ljava/lang/Throwable;
    //   7839: athrow
    //   7840: aload #7
    //   7842: iconst_1
    //   7843: invokevirtual setAccessible : (Z)V
    //   7846: aload #7
    //   7848: aconst_null
    //   7849: invokevirtual get : (Ljava/lang/Object;)Ljava/lang/Object;
    //   7852: pop
    //   7853: iinc #6, 1
    //   7856: iload_2
    //   7857: ifeq -> 7718
    //   7860: sipush #31195
    //   7863: sipush #-1663
    //   7866: invokestatic a : (II)Ljava/lang/String;
    //   7869: invokestatic forName : (Ljava/lang/String;)Ljava/lang/Class;
    //   7872: invokevirtual getDeclaredMethods : ()[Ljava/lang/reflect/Method;
    //   7875: astore #4
    //   7877: aload #4
    //   7879: arraylength
    //   7880: istore #5
    //   7882: iconst_0
    //   7883: istore #6
    //   7885: iload #6
    //   7887: iload #5
    //   7889: if_icmpge -> 8025
    //   7892: aload #4
    //   7894: iload #6
    //   7896: aaload
    //   7897: astore #7
    //   7899: aload #7
    //   7901: invokevirtual getParameterTypes : ()[Ljava/lang/Class;
    //   7904: pop
    //   7905: aload #7
    //   7907: invokevirtual getModifiers : ()I
    //   7910: invokestatic isStatic : (I)Z
    //   7913: ifeq -> 8011
    //   7916: aload #7
    //   7918: invokevirtual getParameterTypes : ()[Ljava/lang/Class;
    //   7921: arraylength
    //   7922: iconst_2
    //   7923: if_icmpne -> 8011
    //   7926: goto -> 7933
    //   7929: invokestatic a : (Ljava/lang/Throwable;)Ljava/lang/Throwable;
    //   7932: athrow
    //   7933: aload #7
    //   7935: invokevirtual getReturnType : ()Ljava/lang/Class;
    //   7938: getstatic java/lang/Boolean.TYPE : Ljava/lang/Class;
    //   7941: if_acmpne -> 8011
    //   7944: goto -> 7951
    //   7947: invokestatic a : (Ljava/lang/Throwable;)Ljava/lang/Throwable;
    //   7950: athrow
    //   7951: aload #7
    //   7953: iconst_1
    //   7954: invokevirtual setAccessible : (Z)V
    //   7957: aload #7
    //   7959: aconst_null
    //   7960: iconst_2
    //   7961: anewarray java/lang/Object
    //   7964: dup
    //   7965: iconst_0
    //   7966: aload_0
    //   7967: aastore
    //   7968: dup
    //   7969: iconst_1
    //   7970: aload_1
    //   7971: ifnonnull -> 7989
    //   7974: goto -> 7981
    //   7977: invokestatic a : (Ljava/lang/Throwable;)Ljava/lang/Throwable;
    //   7980: athrow
    //   7981: aload_1
    //   7982: goto -> 7996
    //   7985: invokestatic a : (Ljava/lang/Throwable;)Ljava/lang/Throwable;
    //   7988: athrow
    //   7989: aload_1
    //   7990: checkcast [B
    //   7993: invokevirtual clone : ()Ljava/lang/Object;
    //   7996: aastore
    //   7997: invokevirtual invoke : (Ljava/lang/Object;[Ljava/lang/Object;)Ljava/lang/Object;
    //   8000: checkcast java/lang/Boolean
    //   8003: invokevirtual booleanValue : ()Z
    //   8006: istore_3
    //   8007: iload_2
    //   8008: ifeq -> 8025
    //   8011: iinc #6, 1
    //   8014: iload_2
    //   8015: ifeq -> 7885
    //   8018: goto -> 8025
    //   8021: invokestatic a : (Ljava/lang/Throwable;)Ljava/lang/Throwable;
    //   8024: athrow
    //   8025: iload_3
    //   8026: ireturn
    //   8027: astore_3
    //   8028: new java/lang/Exception
    //   8031: dup
    //   8032: aload_3
    //   8033: invokevirtual getMessage : ()Ljava/lang/String;
    //   8036: invokespecial <init> : (Ljava/lang/String;)V
    //   8039: athrow
    // Exception table:
    //   from	to	target	type
    //   4	5837	8027	java/lang/Throwable
    //   309	333	336	java/lang/Throwable
    //   407	444	444	java/lang/Throwable
    //   448	469	469	java/lang/Throwable
    //   473	503	503	java/lang/Throwable
    //   1487	1521	1524	java/lang/Throwable
    //   1616	1694	1697	java/lang/Throwable
    //   1623	1837	1840	java/lang/Throwable
    //   2214	2229	2229	java/lang/Throwable
    //   2256	2290	2293	java/lang/Throwable
    //   2300	2312	2315	java/lang/Throwable
    //   2398	2476	2479	java/lang/Throwable
    //   2405	2619	2622	java/lang/Throwable
    //   3019	3097	3100	java/lang/Throwable
    //   3026	3240	3243	java/lang/Throwable
    //   3687	3721	3724	java/lang/Throwable
    //   3728	3740	3743	java/lang/Throwable
    //   3826	3904	3907	java/lang/Throwable
    //   3833	4047	4050	java/lang/Throwable
    //   4819	4833	4833	java/lang/Throwable
    //   4844	4857	4860	java/lang/Throwable
    //   4849	4872	4875	java/lang/Throwable
    //   4864	4890	4893	java/lang/Throwable
    //   4879	4920	4923	java/lang/Throwable
    //   4983	5010	5013	java/lang/Throwable
    //   5000	5031	5034	java/lang/Throwable
    //   5017	5061	5064	java/lang/Throwable
    //   5038	5072	5072	java/lang/Throwable
    //   5083	5099	5102	java/lang/Throwable
    //   5198	5212	5212	java/lang/Throwable
    //   5223	5236	5239	java/lang/Throwable
    //   5228	5251	5254	java/lang/Throwable
    //   5243	5269	5272	java/lang/Throwable
    //   5258	5299	5302	java/lang/Throwable
    //   5365	5392	5395	java/lang/Throwable
    //   5382	5410	5413	java/lang/Throwable
    //   5399	5440	5443	java/lang/Throwable
    //   5417	5451	5451	java/lang/Throwable
    //   5473	5484	5487	java/lang/Throwable
    //   5539	5553	5553	java/lang/Throwable
    //   5564	5577	5580	java/lang/Throwable
    //   5569	5592	5595	java/lang/Throwable
    //   5584	5610	5613	java/lang/Throwable
    //   5599	5640	5643	java/lang/Throwable
    //   5706	5733	5736	java/lang/Throwable
    //   5723	5751	5754	java/lang/Throwable
    //   5740	5781	5784	java/lang/Throwable
    //   5758	5792	5792	java/lang/Throwable
    //   5814	5825	5828	java/lang/Throwable
    //   5838	6568	8027	java/lang/Throwable
    //   5928	5942	5942	java/lang/Throwable
    //   5953	5966	5969	java/lang/Throwable
    //   5958	5981	5984	java/lang/Throwable
    //   5973	5999	6002	java/lang/Throwable
    //   5988	6029	6032	java/lang/Throwable
    //   6095	6122	6125	java/lang/Throwable
    //   6112	6140	6143	java/lang/Throwable
    //   6129	6170	6173	java/lang/Throwable
    //   6147	6181	6181	java/lang/Throwable
    //   6203	6214	6217	java/lang/Throwable
    //   6270	6284	6284	java/lang/Throwable
    //   6295	6308	6311	java/lang/Throwable
    //   6300	6323	6326	java/lang/Throwable
    //   6315	6341	6344	java/lang/Throwable
    //   6330	6371	6374	java/lang/Throwable
    //   6437	6464	6467	java/lang/Throwable
    //   6454	6482	6485	java/lang/Throwable
    //   6471	6512	6515	java/lang/Throwable
    //   6489	6523	6523	java/lang/Throwable
    //   6545	6556	6559	java/lang/Throwable
    //   6569	7299	8027	java/lang/Throwable
    //   6659	6673	6673	java/lang/Throwable
    //   6684	6697	6700	java/lang/Throwable
    //   6689	6712	6715	java/lang/Throwable
    //   6704	6730	6733	java/lang/Throwable
    //   6719	6760	6763	java/lang/Throwable
    //   6826	6853	6856	java/lang/Throwable
    //   6843	6871	6874	java/lang/Throwable
    //   6860	6901	6904	java/lang/Throwable
    //   6878	6912	6912	java/lang/Throwable
    //   6934	6945	6948	java/lang/Throwable
    //   7001	7015	7015	java/lang/Throwable
    //   7026	7039	7042	java/lang/Throwable
    //   7031	7054	7057	java/lang/Throwable
    //   7046	7072	7075	java/lang/Throwable
    //   7061	7102	7105	java/lang/Throwable
    //   7168	7195	7198	java/lang/Throwable
    //   7185	7213	7216	java/lang/Throwable
    //   7202	7243	7246	java/lang/Throwable
    //   7220	7254	7254	java/lang/Throwable
    //   7276	7287	7290	java/lang/Throwable
    //   7300	8026	8027	java/lang/Throwable
    //   7390	7404	7404	java/lang/Throwable
    //   7415	7428	7431	java/lang/Throwable
    //   7420	7443	7446	java/lang/Throwable
    //   7435	7461	7464	java/lang/Throwable
    //   7450	7491	7494	java/lang/Throwable
    //   7557	7584	7587	java/lang/Throwable
    //   7574	7602	7605	java/lang/Throwable
    //   7591	7632	7635	java/lang/Throwable
    //   7609	7643	7643	java/lang/Throwable
    //   7665	7676	7679	java/lang/Throwable
    //   7732	7746	7746	java/lang/Throwable
    //   7757	7770	7773	java/lang/Throwable
    //   7762	7785	7788	java/lang/Throwable
    //   7777	7803	7806	java/lang/Throwable
    //   7792	7833	7836	java/lang/Throwable
    //   7899	7926	7929	java/lang/Throwable
    //   7916	7944	7947	java/lang/Throwable
    //   7933	7974	7977	java/lang/Throwable
    //   7951	7985	7985	java/lang/Throwable
    //   8007	8018	8021	java/lang/Throwable
  }
  
  static {
    // Byte code:
    //   0: bipush #28
    //   2: anewarray java/lang/String
    //   5: astore #5
    //   7: iconst_0
    //   8: istore_3
    //   9: ldc '8\\tyf!\\tTwoL ??=+uQle2} q\\b?\9stOD\\tgAB#A\\tFjKH\\t]\\t>*Y\\tM\\f# 4C\\tI=]sMVyw.mSZfG{H~fMV=Ux'1x/d 4VjQg<y!}:\\tR6d\\t_16/Q\\toVoOW e:?"f\\rfI~>H\\th|-\\tLf)\\boaM \\t\\t.|`j\\tcr_U\\tv!>eV\\tmx\\b,\\tcZQT\\t$Rn'
    //   11: dup
    //   12: astore_2
    //   13: invokevirtual length : ()I
    //   16: istore #4
    //   18: bipush #9
    //   20: istore_1
    //   21: iconst_m1
    //   22: istore_0
    //   23: bipush #116
    //   25: iinc #0, 1
    //   28: aload_2
    //   29: iload_0
    //   30: dup
    //   31: iload_1
    //   32: iadd
    //   33: invokevirtual substring : (II)Ljava/lang/String;
    //   36: iconst_m1
    //   37: goto -> 143
    //   40: aload #5
    //   42: swap
    //   43: iload_3
    //   44: iinc #3, 1
    //   47: swap
    //   48: aastore
    //   49: iload_0
    //   50: iload_1
    //   51: iadd
    //   52: dup
    //   53: istore_0
    //   54: iload #4
    //   56: if_icmpge -> 68
    //   59: aload_2
    //   60: iload_0
    //   61: invokevirtual charAt : (I)C
    //   64: istore_1
    //   65: goto -> 23
    //   68: ldc '/v Hf<:]HqM>W/ g.'
    //   70: dup
    //   71: astore_2
    //   72: invokevirtual length : ()I
    //   75: istore #4
    //   77: bipush #7
    //   79: istore_1
    //   80: iconst_m1
    //   81: istore_0
    //   82: bipush #125
    //   84: iinc #0, 1
    //   87: aload_2
    //   88: iload_0
    //   89: dup
    //   90: iload_1
    //   91: iadd
    //   92: invokevirtual substring : (II)Ljava/lang/String;
    //   95: iconst_0
    //   96: goto -> 143
    //   99: aload #5
    //   101: swap
    //   102: iload_3
    //   103: iinc #3, 1
    //   106: swap
    //   107: aastore
    //   108: iload_0
    //   109: iload_1
    //   110: iadd
    //   111: dup
    //   112: istore_0
    //   113: iload #4
    //   115: if_icmpge -> 127
    //   118: aload_2
    //   119: iload_0
    //   120: invokevirtual charAt : (I)C
    //   123: istore_1
    //   124: goto -> 82
    //   127: aload #5
    //   129: putstatic burp/Ze5h.a : [Ljava/lang/String;
    //   132: bipush #28
    //   134: anewarray java/lang/String
    //   137: putstatic burp/Ze5h.b : [Ljava/lang/String;
    //   140: goto -> 300
    //   143: dup_x2
    //   144: pop
    //   145: invokevirtual toCharArray : ()[C
    //   148: dup_x1
    //   149: arraylength
    //   150: dup_x2
    //   151: pop
    //   152: iconst_0
    //   153: istore #6
    //   155: dup2_x1
    //   156: pop2
    //   157: dup_x2
    //   158: iconst_1
    //   159: if_icmpgt -> 260
    //   162: dup2
    //   163: swap
    //   164: iload #6
    //   166: dup2_x1
    //   167: caload
    //   168: swap
    //   169: iload #6
    //   171: bipush #7
    //   173: irem
    //   174: tableswitch default -> 242, 0 -> 212, 1 -> 217, 2 -> 222, 3 -> 227, 4 -> 232, 5 -> 237
    //   212: bipush #18
    //   214: goto -> 244
    //   217: bipush #55
    //   219: goto -> 244
    //   222: bipush #11
    //   224: goto -> 244
    //   227: bipush #18
    //   229: goto -> 244
    //   232: bipush #108
    //   234: goto -> 244
    //   237: bipush #62
    //   239: goto -> 244
    //   242: bipush #20
    //   244: ixor
    //   245: ixor
    //   246: i2c
    //   247: castore
    //   248: iinc #6, 1
    //   251: dup
    //   252: ifne -> 260
    //   255: dup2
    //   256: dup_x1
    //   257: goto -> 166
    //   260: dup2_x1
    //   261: pop2
    //   262: dup_x2
    //   263: iload #6
    //   265: if_icmpgt -> 162
    //   268: pop
    //   269: new java/lang/String
    //   272: dup_x1
    //   273: swap
    //   274: invokespecial <init> : ([C)V
    //   277: invokevirtual intern : ()Ljava/lang/String;
    //   280: swap
    //   281: pop
    //   282: swap
    //   283: tableswitch default -> 40, 0 -> 99
    //   300: sipush #31182
    //   303: sipush #31278
    //   306: invokestatic a : (II)Ljava/lang/String;
    //   309: putstatic burp/Ze5h.Zk : Ljava/lang/String;
    //   312: new java/math/BigInteger
    //   315: dup
    //   316: iconst_1
    //   317: bipush #32
    //   319: newarray byte
    //   321: dup
    //   322: iconst_0
    //   323: bipush #90
    //   325: bastore
    //   326: dup
    //   327: iconst_1
    //   328: bipush #-78
    //   330: bastore
    //   331: dup
    //   332: iconst_2
    //   333: bipush #119
    //   335: bastore
    //   336: dup
    //   337: iconst_3
    //   338: iconst_4
    //   339: bastore
    //   340: dup
    //   341: iconst_4
    //   342: bipush #-122
    //   344: bastore
    //   345: dup
    //   346: iconst_5
    //   347: bipush #98
    //   349: bastore
    //   350: dup
    //   351: bipush #6
    //   353: bipush #-43
    //   355: bastore
    //   356: dup
    //   357: bipush #7
    //   359: bipush #118
    //   361: bastore
    //   362: dup
    //   363: bipush #8
    //   365: bipush #-69
    //   367: bastore
    //   368: dup
    //   369: bipush #9
    //   371: bipush #104
    //   373: bastore
    //   374: dup
    //   375: bipush #10
    //   377: bipush #103
    //   379: bastore
    //   380: dup
    //   381: bipush #11
    //   383: bipush #-91
    //   385: bastore
    //   386: dup
    //   387: bipush #12
    //   389: bipush #6
    //   391: bastore
    //   392: dup
    //   393: bipush #13
    //   395: bipush #16
    //   397: bastore
    //   398: dup
    //   399: bipush #14
    //   401: bipush #-33
    //   403: bastore
    //   404: dup
    //   405: bipush #15
    //   407: bipush #-112
    //   409: bastore
    //   410: dup
    //   411: bipush #16
    //   413: bipush #-19
    //   415: bastore
    //   416: dup
    //   417: bipush #17
    //   419: bipush #-21
    //   421: bastore
    //   422: dup
    //   423: bipush #18
    //   425: bipush #102
    //   427: bastore
    //   428: dup
    //   429: bipush #19
    //   431: bipush #-121
    //   433: bastore
    //   434: dup
    //   435: bipush #20
    //   437: bipush #-127
    //   439: bastore
    //   440: dup
    //   441: bipush #21
    //   443: bipush #-19
    //   445: bastore
    //   446: dup
    //   447: bipush #22
    //   449: bipush #-17
    //   451: bastore
    //   452: dup
    //   453: bipush #23
    //   455: bipush #73
    //   457: bastore
    //   458: dup
    //   459: bipush #24
    //   461: bipush #82
    //   463: bastore
    //   464: dup
    //   465: bipush #25
    //   467: bipush #-90
    //   469: bastore
    //   470: dup
    //   471: bipush #26
    //   473: bipush #125
    //   475: bastore
    //   476: dup
    //   477: bipush #27
    //   479: iconst_0
    //   480: bastore
    //   481: dup
    //   482: bipush #28
    //   484: bipush #61
    //   486: bastore
    //   487: dup
    //   488: bipush #29
    //   490: bipush #107
    //   492: bastore
    //   493: dup
    //   494: bipush #30
    //   496: bipush #97
    //   498: bastore
    //   499: dup
    //   500: bipush #31
    //   502: bipush #65
    //   504: bastore
    //   505: invokespecial <init> : (I[B)V
    //   508: putstatic burp/Ze5h.Zn : Ljava/lang/Object;
    //   511: return
  }
  
  private static Throwable a(Throwable paramThrowable) {
    return paramThrowable;
  }
  
  private static String a(int paramInt1, int paramInt2) {
    int i = (paramInt1 ^ 0x79CD) & 0xFFFF;
    if (b[i] == null) {
      char[] arrayOfChar = a[i].toCharArray();
      switch (arrayOfChar[0] & 0xFF) {
        case 0:
        
        case 1:
        
        case 2:
        
        case 3:
        
        case 4:
        
        case 5:
        
        case 6:
        
        case 7:
        
        case 8:
        
        case 9:
        
        case 10:
        
        case 11:
        
        case 12:
        
        case 13:
        
        case 14:
        
        case 15:
        
        case 16:
        
        case 17:
        
        case 18:
        
        case 19:
        
        case 20:
        
        case 21:
        
        case 22:
        
        case 23:
        
        case 24:
        
        case 25:
        
        case 26:
        
        case 27:
        
        case 28:
        
        case 29:
        
        case 30:
        
        case 31:
        
        case 32:
        
        case 33:
        
        case 34:
        
        case 35:
        
        case 36:
        
        case 37:
        
        case 38:
        
        case 39:
        
        case 40:
        
        case 41:
        
        case 42:
        
        case 43:
        
        case 44:
        
        case 45:
        
        case 46:
        
        case 47:
        
        case 48:
        
        case 49:
        
        case 50:
        
        case 51:
        
        case 52:
        
        case 53:
        
        case 54:
        
        case 55:
        
        case 56:
        
        case 57:
        
        case 58:
        
        case 59:
        
        case 60:
        
        case 61:
        
        case 62:
        
        case 63:
        
        case 64:
        
        case 65:
        
        case 66:
        
        case 67:
        
        case 68:
        
        case 69:
        
        case 70:
        
        case 71:
        
        case 72:
        
        case 73:
        
        case 74:
        
        case 75:
        
        case 76:
        
        case 77:
        
        case 78:
        
        case 79:
        
        case 80:
        
        case 81:
        
        case 82:
        
        case 83:
        
        case 84:
        
        case 85:
        
        case 86:
        
        case 87:
        
        case 88:
        
        case 89:
        
        case 90:
        
        case 91:
        
        case 92:
        
        case 93:
        
        case 94:
        
        case 95:
        
        case 96:
        
        case 97:
        
        case 98:
        
        case 99:
        
        case 100:
        
        case 101:
        
        case 102:
        
        case 103:
        
        case 104:
        
        case 105:
        
        case 106:
        
        case 107:
        
        case 108:
        
        case 109:
        
        case 110:
        
        case 111:
        
        case 112:
        
        case 113:
        
        case 114:
        
        case 115:
        
        case 116:
        
        case 117:
        
        case 118:
        
        case 119:
        
        case 120:
        
        case 121:
        
        case 122:
        
        case 123:
        
        case 124:
        
        case 125:
        
        case 126:
        
        case 127:
        
        case 128:
        
        case 129:
        
        case 130:
        
        case 131:
        
        case 132:
        
        case 133:
        
        case 134:
        
        case 135:
        
        case 136:
        
        case 137:
        
        case 138:
        
        case 139:
        
        case 140:
        
        case 141:
        
        case 142:
        
        case 143:
        
        case 144:
        
        case 145:
        
        case 146:
        
        case 147:
        
        case 148:
        
        case 149:
        
        case 150:
        
        case 151:
        
        case 152:
        
        case 153:
        
        case 154:
        
        case 155:
        
        case 156:
        
        case 157:
        
        case 158:
        
        case 159:
        
        case 160:
        
        case 161:
        
        case 162:
        
        case 163:
        
        case 164:
        
        case 165:
        
        case 166:
        
        case 167:
        
        case 168:
        
        case 169:
        
        case 170:
        
        case 171:
        
        case 172:
        
        case 173:
        
        case 174:
        
        case 175:
        
        case 176:
        
        case 177:
        
        case 178:
        
        case 179:
        
        case 180:
        
        case 181:
        
        case 182:
        
        case 183:
        
        case 184:
        
        case 185:
        
        case 186:
        
        case 187:
        
        case 188:
        
        case 189:
        
        case 190:
        
        case 191:
        
        case 192:
        
        case 193:
        
        case 194:
        
        case 195:
        
        case 196:
        
        case 197:
        
        case 198:
        
        case 199:
        
        case 200:
        
        case 201:
        
        case 202:
        
        case 203:
        
        case 204:
        
        case 205:
        
        case 206:
        
        case 207:
        
        case 208:
        
        case 209:
        
        case 210:
        
        case 211:
        
        case 212:
        
        case 213:
        
        case 214:
        
        case 215:
        
        case 216:
        
        case 217:
        
        case 218:
        
        case 219:
        
        case 220:
        
        case 221:
        
        case 222:
        
        case 223:
        
        case 224:
        
        case 225:
        
        case 226:
        
        case 227:
        
        case 228:
        
        case 229:
        
        case 230:
        
        case 231:
        
        case 232:
        
        case 233:
        
        case 234:
        
        case 235:
        
        case 236:
        
        case 237:
        
        case 238:
        
        case 239:
        
        case 240:
        
        case 241:
        
        case 242:
        
        case 243:
        
        case 244:
        
        case 245:
        
        case 246:
        
        case 247:
        
        case 248:
        
        case 249:
        
        case 250:
        
        case 251:
        
        case 252:
        
        case 253:
        
        case 254:
        
        default:
          break;
      } 
      char c = '';
      int j = (paramInt2 & 0xFF) - c;
      if (j < 0)
        j += 256; 
      int k = ((paramInt2 & 0xFFFF) >>> 8) - c;
      if (k < 0)
        k += 256; 
      for (byte b = 0; b < arrayOfChar.length; b++) {
        int m = b % 2;
        if (m == 0) {
          arrayOfChar[b] = (char)(arrayOfChar[b] ^ j);
          j = ((j >>> 3 | j << 5) ^ arrayOfChar[b]) & 0xFF;
        } else {
          arrayOfChar[b] = (char)(arrayOfChar[b] ^ k);
          k = ((k >>> 3 | k << 5) ^ arrayOfChar[b]) & 0xFF;
        } 
      } 
      b[i] = (new String(arrayOfChar)).intern();
    } 
    return b[i];
  }
}


/* Location:              C:\Program Files\BurpSuitePro\burpsuite_pro.jar!\burp\Ze5h.class
 * Java compiler version: 21 (65.0)
 * JD-Core Version:       1.1.3
 */