package burp;

import java.math.BigInteger;

class Ze6d extends ClassLoader {
  static Object Zw;
  
  static String Zx;
  
  private static final String[] a;
  
  private static final String[] b;
  
  static void ZI(Object[] paramArrayOfObject, Object paramObject) throws Throwable {}
  
  static void Zp(Object paramObject) {
    Zgzv.Zy = a(7228, 32519);
    Zgzv.Zb = new BigInteger(a(7216, -30215));
    boolean bool = Zt2e.ZK();
    try {
      try {
        if (Zs8q.Zs.charAt(Math.abs(((BigInteger)Zxjk.Zk).intValue() % 32)) <= Zxg7.Zi.charAt(Math.abs(((BigInteger)Zefo.ZW).intValue() % 32))) {
          try {
            Zlh8.ZM(Class.forName(a(7220, -25173)));
            if (bool)
              Zegw.ZT(Class.forName(a(7222, 8377))); 
          } catch (Throwable throwable) {
            throw a(null);
          } 
          return;
        } 
      } catch (Throwable throwable) {
        throw a(null);
      } 
      Zegw.ZT(Class.forName(a(7222, 8377)));
    } catch (Throwable throwable) {}
  }
  
  static boolean Zj(Object[] paramArrayOfObject, Object paramObject) throws Throwable {
    // Byte code:
    //   0: invokestatic ZK : ()Z
    //   3: istore_2
    //   4: getstatic burp/Zs0_.Zu : Ljava/lang/Object;
    //   7: checkcast java/math/BigInteger
    //   10: invokevirtual toByteArray : ()[B
    //   13: astore_3
    //   14: bipush #64
    //   16: newarray byte
    //   18: dup
    //   19: iconst_0
    //   20: bipush #-128
    //   22: bastore
    //   23: dup
    //   24: iconst_1
    //   25: iconst_0
    //   26: bastore
    //   27: dup
    //   28: iconst_2
    //   29: iconst_0
    //   30: bastore
    //   31: dup
    //   32: iconst_3
    //   33: iconst_0
    //   34: bastore
    //   35: dup
    //   36: iconst_4
    //   37: iconst_0
    //   38: bastore
    //   39: dup
    //   40: iconst_5
    //   41: iconst_0
    //   42: bastore
    //   43: dup
    //   44: bipush #6
    //   46: iconst_0
    //   47: bastore
    //   48: dup
    //   49: bipush #7
    //   51: iconst_0
    //   52: bastore
    //   53: dup
    //   54: bipush #8
    //   56: iconst_0
    //   57: bastore
    //   58: dup
    //   59: bipush #9
    //   61: iconst_0
    //   62: bastore
    //   63: dup
    //   64: bipush #10
    //   66: iconst_0
    //   67: bastore
    //   68: dup
    //   69: bipush #11
    //   71: iconst_0
    //   72: bastore
    //   73: dup
    //   74: bipush #12
    //   76: iconst_0
    //   77: bastore
    //   78: dup
    //   79: bipush #13
    //   81: iconst_0
    //   82: bastore
    //   83: dup
    //   84: bipush #14
    //   86: iconst_0
    //   87: bastore
    //   88: dup
    //   89: bipush #15
    //   91: iconst_0
    //   92: bastore
    //   93: dup
    //   94: bipush #16
    //   96: iconst_0
    //   97: bastore
    //   98: dup
    //   99: bipush #17
    //   101: iconst_0
    //   102: bastore
    //   103: dup
    //   104: bipush #18
    //   106: iconst_0
    //   107: bastore
    //   108: dup
    //   109: bipush #19
    //   111: iconst_0
    //   112: bastore
    //   113: dup
    //   114: bipush #20
    //   116: iconst_0
    //   117: bastore
    //   118: dup
    //   119: bipush #21
    //   121: iconst_0
    //   122: bastore
    //   123: dup
    //   124: bipush #22
    //   126: iconst_0
    //   127: bastore
    //   128: dup
    //   129: bipush #23
    //   131: iconst_0
    //   132: bastore
    //   133: dup
    //   134: bipush #24
    //   136: iconst_0
    //   137: bastore
    //   138: dup
    //   139: bipush #25
    //   141: iconst_0
    //   142: bastore
    //   143: dup
    //   144: bipush #26
    //   146: iconst_0
    //   147: bastore
    //   148: dup
    //   149: bipush #27
    //   151: iconst_0
    //   152: bastore
    //   153: dup
    //   154: bipush #28
    //   156: iconst_0
    //   157: bastore
    //   158: dup
    //   159: bipush #29
    //   161: iconst_0
    //   162: bastore
    //   163: dup
    //   164: bipush #30
    //   166: iconst_0
    //   167: bastore
    //   168: dup
    //   169: bipush #31
    //   171: iconst_0
    //   172: bastore
    //   173: dup
    //   174: bipush #32
    //   176: iconst_0
    //   177: bastore
    //   178: dup
    //   179: bipush #33
    //   181: iconst_0
    //   182: bastore
    //   183: dup
    //   184: bipush #34
    //   186: iconst_0
    //   187: bastore
    //   188: dup
    //   189: bipush #35
    //   191: iconst_0
    //   192: bastore
    //   193: dup
    //   194: bipush #36
    //   196: iconst_0
    //   197: bastore
    //   198: dup
    //   199: bipush #37
    //   201: iconst_0
    //   202: bastore
    //   203: dup
    //   204: bipush #38
    //   206: iconst_0
    //   207: bastore
    //   208: dup
    //   209: bipush #39
    //   211: iconst_0
    //   212: bastore
    //   213: dup
    //   214: bipush #40
    //   216: iconst_0
    //   217: bastore
    //   218: dup
    //   219: bipush #41
    //   221: iconst_0
    //   222: bastore
    //   223: dup
    //   224: bipush #42
    //   226: iconst_0
    //   227: bastore
    //   228: dup
    //   229: bipush #43
    //   231: iconst_0
    //   232: bastore
    //   233: dup
    //   234: bipush #44
    //   236: iconst_0
    //   237: bastore
    //   238: dup
    //   239: bipush #45
    //   241: iconst_0
    //   242: bastore
    //   243: dup
    //   244: bipush #46
    //   246: iconst_0
    //   247: bastore
    //   248: dup
    //   249: bipush #47
    //   251: iconst_0
    //   252: bastore
    //   253: dup
    //   254: bipush #48
    //   256: iconst_0
    //   257: bastore
    //   258: dup
    //   259: bipush #49
    //   261: iconst_0
    //   262: bastore
    //   263: dup
    //   264: bipush #50
    //   266: iconst_0
    //   267: bastore
    //   268: dup
    //   269: bipush #51
    //   271: iconst_0
    //   272: bastore
    //   273: dup
    //   274: bipush #52
    //   276: iconst_0
    //   277: bastore
    //   278: dup
    //   279: bipush #53
    //   281: iconst_0
    //   282: bastore
    //   283: dup
    //   284: bipush #54
    //   286: iconst_0
    //   287: bastore
    //   288: dup
    //   289: bipush #55
    //   291: iconst_0
    //   292: bastore
    //   293: dup
    //   294: bipush #56
    //   296: iconst_0
    //   297: bastore
    //   298: dup
    //   299: bipush #57
    //   301: iconst_0
    //   302: bastore
    //   303: dup
    //   304: bipush #58
    //   306: iconst_0
    //   307: bastore
    //   308: dup
    //   309: bipush #59
    //   311: iconst_0
    //   312: bastore
    //   313: dup
    //   314: bipush #60
    //   316: iconst_0
    //   317: bastore
    //   318: dup
    //   319: bipush #61
    //   321: iconst_0
    //   322: bastore
    //   323: dup
    //   324: bipush #62
    //   326: iconst_0
    //   327: bastore
    //   328: dup
    //   329: bipush #63
    //   331: iconst_0
    //   332: bastore
    //   333: astore #5
    //   335: bipush #64
    //   337: newarray int
    //   339: dup
    //   340: iconst_0
    //   341: ldc 1116352408
    //   343: iastore
    //   344: dup
    //   345: iconst_1
    //   346: ldc 1899447441
    //   348: iastore
    //   349: dup
    //   350: iconst_2
    //   351: ldc -1245643825
    //   353: iastore
    //   354: dup
    //   355: iconst_3
    //   356: ldc -373957723
    //   358: iastore
    //   359: dup
    //   360: iconst_4
    //   361: ldc 961987163
    //   363: iastore
    //   364: dup
    //   365: iconst_5
    //   366: ldc 1508970993
    //   368: iastore
    //   369: dup
    //   370: bipush #6
    //   372: ldc -1841331548
    //   374: iastore
    //   375: dup
    //   376: bipush #7
    //   378: ldc -1424204075
    //   380: iastore
    //   381: dup
    //   382: bipush #8
    //   384: ldc -670586216
    //   386: iastore
    //   387: dup
    //   388: bipush #9
    //   390: ldc 310598401
    //   392: iastore
    //   393: dup
    //   394: bipush #10
    //   396: ldc 607225278
    //   398: iastore
    //   399: dup
    //   400: bipush #11
    //   402: ldc 1426881987
    //   404: iastore
    //   405: dup
    //   406: bipush #12
    //   408: ldc 1925078388
    //   410: iastore
    //   411: dup
    //   412: bipush #13
    //   414: ldc -2132889090
    //   416: iastore
    //   417: dup
    //   418: bipush #14
    //   420: ldc -1680079193
    //   422: iastore
    //   423: dup
    //   424: bipush #15
    //   426: ldc -1046744716
    //   428: iastore
    //   429: dup
    //   430: bipush #16
    //   432: ldc -459576895
    //   434: iastore
    //   435: dup
    //   436: bipush #17
    //   438: ldc -272742522
    //   440: iastore
    //   441: dup
    //   442: bipush #18
    //   444: ldc 264347078
    //   446: iastore
    //   447: dup
    //   448: bipush #19
    //   450: ldc 604807628
    //   452: iastore
    //   453: dup
    //   454: bipush #20
    //   456: ldc 770255983
    //   458: iastore
    //   459: dup
    //   460: bipush #21
    //   462: ldc 1249150122
    //   464: iastore
    //   465: dup
    //   466: bipush #22
    //   468: ldc 1555081692
    //   470: iastore
    //   471: dup
    //   472: bipush #23
    //   474: ldc 1996064986
    //   476: iastore
    //   477: dup
    //   478: bipush #24
    //   480: ldc -1740746414
    //   482: iastore
    //   483: dup
    //   484: bipush #25
    //   486: ldc -1473132947
    //   488: iastore
    //   489: dup
    //   490: bipush #26
    //   492: ldc -1341970488
    //   494: iastore
    //   495: dup
    //   496: bipush #27
    //   498: ldc -1084653625
    //   500: iastore
    //   501: dup
    //   502: bipush #28
    //   504: ldc -958395405
    //   506: iastore
    //   507: dup
    //   508: bipush #29
    //   510: ldc -710438585
    //   512: iastore
    //   513: dup
    //   514: bipush #30
    //   516: ldc 113926993
    //   518: iastore
    //   519: dup
    //   520: bipush #31
    //   522: ldc 338241895
    //   524: iastore
    //   525: dup
    //   526: bipush #32
    //   528: ldc 666307205
    //   530: iastore
    //   531: dup
    //   532: bipush #33
    //   534: ldc 773529912
    //   536: iastore
    //   537: dup
    //   538: bipush #34
    //   540: ldc 1294757372
    //   542: iastore
    //   543: dup
    //   544: bipush #35
    //   546: ldc 1396182291
    //   548: iastore
    //   549: dup
    //   550: bipush #36
    //   552: ldc 1695183700
    //   554: iastore
    //   555: dup
    //   556: bipush #37
    //   558: ldc 1986661051
    //   560: iastore
    //   561: dup
    //   562: bipush #38
    //   564: ldc -2117940946
    //   566: iastore
    //   567: dup
    //   568: bipush #39
    //   570: ldc -1838011259
    //   572: iastore
    //   573: dup
    //   574: bipush #40
    //   576: ldc -1564481375
    //   578: iastore
    //   579: dup
    //   580: bipush #41
    //   582: ldc -1474664885
    //   584: iastore
    //   585: dup
    //   586: bipush #42
    //   588: ldc -1035236496
    //   590: iastore
    //   591: dup
    //   592: bipush #43
    //   594: ldc -949202525
    //   596: iastore
    //   597: dup
    //   598: bipush #44
    //   600: ldc -778901479
    //   602: iastore
    //   603: dup
    //   604: bipush #45
    //   606: ldc -694614492
    //   608: iastore
    //   609: dup
    //   610: bipush #46
    //   612: ldc -200395387
    //   614: iastore
    //   615: dup
    //   616: bipush #47
    //   618: ldc 275423344
    //   620: iastore
    //   621: dup
    //   622: bipush #48
    //   624: ldc 430227734
    //   626: iastore
    //   627: dup
    //   628: bipush #49
    //   630: ldc 506948616
    //   632: iastore
    //   633: dup
    //   634: bipush #50
    //   636: ldc 659060556
    //   638: iastore
    //   639: dup
    //   640: bipush #51
    //   642: ldc 883997877
    //   644: iastore
    //   645: dup
    //   646: bipush #52
    //   648: ldc 958139571
    //   650: iastore
    //   651: dup
    //   652: bipush #53
    //   654: ldc 1322822218
    //   656: iastore
    //   657: dup
    //   658: bipush #54
    //   660: ldc 1537002063
    //   662: iastore
    //   663: dup
    //   664: bipush #55
    //   666: ldc 1747873779
    //   668: iastore
    //   669: dup
    //   670: bipush #56
    //   672: ldc 1955562222
    //   674: iastore
    //   675: dup
    //   676: bipush #57
    //   678: ldc 2024104815
    //   680: iastore
    //   681: dup
    //   682: bipush #58
    //   684: ldc -2067236844
    //   686: iastore
    //   687: dup
    //   688: bipush #59
    //   690: ldc -1933114872
    //   692: iastore
    //   693: dup
    //   694: bipush #60
    //   696: ldc -1866530822
    //   698: iastore
    //   699: dup
    //   700: bipush #61
    //   702: ldc -1538233109
    //   704: iastore
    //   705: dup
    //   706: bipush #62
    //   708: ldc -1090935817
    //   710: iastore
    //   711: dup
    //   712: bipush #63
    //   714: ldc -965641998
    //   716: iastore
    //   717: astore #6
    //   719: iconst_2
    //   720: newarray int
    //   722: dup
    //   723: iconst_0
    //   724: iconst_0
    //   725: iastore
    //   726: dup
    //   727: iconst_1
    //   728: iconst_0
    //   729: iastore
    //   730: astore #7
    //   732: bipush #8
    //   734: newarray int
    //   736: dup
    //   737: iconst_0
    //   738: ldc 1779033703
    //   740: iastore
    //   741: dup
    //   742: iconst_1
    //   743: ldc -1150833019
    //   745: iastore
    //   746: dup
    //   747: iconst_2
    //   748: ldc 1013904242
    //   750: iastore
    //   751: dup
    //   752: iconst_3
    //   753: ldc -1521486534
    //   755: iastore
    //   756: dup
    //   757: iconst_4
    //   758: ldc 1359893119
    //   760: iastore
    //   761: dup
    //   762: iconst_5
    //   763: ldc -1694144372
    //   765: iastore
    //   766: dup
    //   767: bipush #6
    //   769: ldc 528734635
    //   771: iastore
    //   772: dup
    //   773: bipush #7
    //   775: ldc 1541459225
    //   777: iastore
    //   778: astore #8
    //   780: bipush #64
    //   782: newarray byte
    //   784: astore #9
    //   786: bipush #64
    //   788: newarray byte
    //   790: astore #10
    //   792: aload_3
    //   793: arraylength
    //   794: istore #11
    //   796: aload #7
    //   798: iconst_0
    //   799: iaload
    //   800: bipush #63
    //   802: iand
    //   803: istore #12
    //   805: aload #7
    //   807: iconst_0
    //   808: dup2
    //   809: iaload
    //   810: iload #11
    //   812: iadd
    //   813: iastore
    //   814: aload #7
    //   816: iconst_0
    //   817: dup2
    //   818: iaload
    //   819: iconst_m1
    //   820: iand
    //   821: iastore
    //   822: aload #7
    //   824: iconst_0
    //   825: iaload
    //   826: iload #11
    //   828: if_icmpge -> 846
    //   831: aload #7
    //   833: iconst_1
    //   834: dup2
    //   835: iaload
    //   836: iconst_1
    //   837: iadd
    //   838: iastore
    //   839: goto -> 846
    //   842: invokestatic a : (Ljava/lang/Throwable;)Ljava/lang/Throwable;
    //   845: athrow
    //   846: iconst_0
    //   847: istore #13
    //   849: iload #11
    //   851: bipush #64
    //   853: if_icmplt -> 1462
    //   856: iconst_0
    //   857: istore #14
    //   859: iload #14
    //   861: bipush #64
    //   863: if_icmpge -> 885
    //   866: aload #10
    //   868: iload #14
    //   870: aload_3
    //   871: iload #13
    //   873: iload #14
    //   875: iadd
    //   876: baload
    //   877: bastore
    //   878: iinc #14, 1
    //   881: iload_2
    //   882: ifeq -> 859
    //   885: bipush #64
    //   887: newarray int
    //   889: astore #14
    //   891: bipush #8
    //   893: newarray int
    //   895: astore #15
    //   897: iconst_0
    //   898: istore #16
    //   900: iload #16
    //   902: bipush #8
    //   904: if_icmpge -> 924
    //   907: aload #15
    //   909: iload #16
    //   911: aload #8
    //   913: iload #16
    //   915: iaload
    //   916: iastore
    //   917: iinc #16, 1
    //   920: iload_2
    //   921: ifeq -> 900
    //   924: iconst_0
    //   925: istore #16
    //   927: iload #16
    //   929: bipush #64
    //   931: if_icmpge -> 1422
    //   934: iload #16
    //   936: bipush #16
    //   938: if_icmpge -> 1019
    //   941: aload #14
    //   943: iload #16
    //   945: aload #10
    //   947: iconst_4
    //   948: iload #16
    //   950: imul
    //   951: baload
    //   952: sipush #255
    //   955: iand
    //   956: bipush #24
    //   958: ishl
    //   959: aload #10
    //   961: iconst_4
    //   962: iload #16
    //   964: imul
    //   965: iconst_1
    //   966: iadd
    //   967: baload
    //   968: sipush #255
    //   971: iand
    //   972: bipush #16
    //   974: ishl
    //   975: ior
    //   976: aload #10
    //   978: iconst_4
    //   979: iload #16
    //   981: imul
    //   982: iconst_2
    //   983: iadd
    //   984: baload
    //   985: sipush #255
    //   988: iand
    //   989: bipush #8
    //   991: ishl
    //   992: ior
    //   993: aload #10
    //   995: iconst_4
    //   996: iload #16
    //   998: imul
    //   999: iconst_3
    //   1000: iadd
    //   1001: baload
    //   1002: sipush #255
    //   1005: iand
    //   1006: ior
    //   1007: iastore
    //   1008: iload_2
    //   1009: ifeq -> 1162
    //   1012: goto -> 1019
    //   1015: invokestatic a : (Ljava/lang/Throwable;)Ljava/lang/Throwable;
    //   1018: athrow
    //   1019: aload #14
    //   1021: iload #16
    //   1023: aload #14
    //   1025: iload #16
    //   1027: iconst_2
    //   1028: isub
    //   1029: iaload
    //   1030: bipush #17
    //   1032: iushr
    //   1033: aload #14
    //   1035: iload #16
    //   1037: iconst_2
    //   1038: isub
    //   1039: iaload
    //   1040: bipush #15
    //   1042: ishl
    //   1043: ior
    //   1044: aload #14
    //   1046: iload #16
    //   1048: iconst_2
    //   1049: isub
    //   1050: iaload
    //   1051: bipush #19
    //   1053: iushr
    //   1054: aload #14
    //   1056: iload #16
    //   1058: iconst_2
    //   1059: isub
    //   1060: iaload
    //   1061: bipush #13
    //   1063: ishl
    //   1064: ior
    //   1065: ixor
    //   1066: aload #14
    //   1068: iload #16
    //   1070: iconst_2
    //   1071: isub
    //   1072: iaload
    //   1073: bipush #10
    //   1075: iushr
    //   1076: ixor
    //   1077: aload #14
    //   1079: iload #16
    //   1081: bipush #7
    //   1083: isub
    //   1084: iaload
    //   1085: iadd
    //   1086: aload #14
    //   1088: iload #16
    //   1090: bipush #15
    //   1092: isub
    //   1093: iaload
    //   1094: bipush #7
    //   1096: iushr
    //   1097: aload #14
    //   1099: iload #16
    //   1101: bipush #15
    //   1103: isub
    //   1104: iaload
    //   1105: bipush #25
    //   1107: ishl
    //   1108: ior
    //   1109: aload #14
    //   1111: iload #16
    //   1113: bipush #15
    //   1115: isub
    //   1116: iaload
    //   1117: bipush #18
    //   1119: iushr
    //   1120: aload #14
    //   1122: iload #16
    //   1124: bipush #15
    //   1126: isub
    //   1127: iaload
    //   1128: bipush #14
    //   1130: ishl
    //   1131: ior
    //   1132: ixor
    //   1133: aload #14
    //   1135: iload #16
    //   1137: bipush #15
    //   1139: isub
    //   1140: iaload
    //   1141: iconst_3
    //   1142: iushr
    //   1143: ixor
    //   1144: iadd
    //   1145: aload #14
    //   1147: iload #16
    //   1149: bipush #16
    //   1151: isub
    //   1152: iaload
    //   1153: iadd
    //   1154: iastore
    //   1155: goto -> 1162
    //   1158: invokestatic a : (Ljava/lang/Throwable;)Ljava/lang/Throwable;
    //   1161: athrow
    //   1162: aload #15
    //   1164: bipush #7
    //   1166: iaload
    //   1167: aload #15
    //   1169: iconst_4
    //   1170: iaload
    //   1171: bipush #6
    //   1173: iushr
    //   1174: aload #15
    //   1176: iconst_4
    //   1177: iaload
    //   1178: bipush #26
    //   1180: ishl
    //   1181: ior
    //   1182: aload #15
    //   1184: iconst_4
    //   1185: iaload
    //   1186: bipush #11
    //   1188: iushr
    //   1189: aload #15
    //   1191: iconst_4
    //   1192: iaload
    //   1193: bipush #21
    //   1195: ishl
    //   1196: ior
    //   1197: ixor
    //   1198: aload #15
    //   1200: iconst_4
    //   1201: iaload
    //   1202: bipush #25
    //   1204: iushr
    //   1205: aload #15
    //   1207: iconst_4
    //   1208: iaload
    //   1209: bipush #7
    //   1211: ishl
    //   1212: ior
    //   1213: ixor
    //   1214: iadd
    //   1215: aload #15
    //   1217: bipush #6
    //   1219: iaload
    //   1220: aload #15
    //   1222: iconst_4
    //   1223: iaload
    //   1224: aload #15
    //   1226: iconst_5
    //   1227: iaload
    //   1228: aload #15
    //   1230: bipush #6
    //   1232: iaload
    //   1233: ixor
    //   1234: iand
    //   1235: ixor
    //   1236: iadd
    //   1237: aload #6
    //   1239: iload #16
    //   1241: iaload
    //   1242: iadd
    //   1243: aload #14
    //   1245: iload #16
    //   1247: iaload
    //   1248: iadd
    //   1249: istore #17
    //   1251: aload #15
    //   1253: iconst_0
    //   1254: iaload
    //   1255: iconst_2
    //   1256: iushr
    //   1257: aload #15
    //   1259: iconst_0
    //   1260: iaload
    //   1261: bipush #30
    //   1263: ishl
    //   1264: ior
    //   1265: aload #15
    //   1267: iconst_0
    //   1268: iaload
    //   1269: bipush #13
    //   1271: iushr
    //   1272: aload #15
    //   1274: iconst_0
    //   1275: iaload
    //   1276: bipush #19
    //   1278: ishl
    //   1279: ior
    //   1280: ixor
    //   1281: aload #15
    //   1283: iconst_0
    //   1284: iaload
    //   1285: bipush #22
    //   1287: iushr
    //   1288: aload #15
    //   1290: iconst_0
    //   1291: iaload
    //   1292: bipush #10
    //   1294: ishl
    //   1295: ior
    //   1296: ixor
    //   1297: aload #15
    //   1299: iconst_0
    //   1300: iaload
    //   1301: aload #15
    //   1303: iconst_1
    //   1304: iaload
    //   1305: iand
    //   1306: aload #15
    //   1308: iconst_2
    //   1309: iaload
    //   1310: aload #15
    //   1312: iconst_0
    //   1313: iaload
    //   1314: aload #15
    //   1316: iconst_1
    //   1317: iaload
    //   1318: ior
    //   1319: iand
    //   1320: ior
    //   1321: iadd
    //   1322: istore #18
    //   1324: aload #15
    //   1326: iconst_3
    //   1327: dup2
    //   1328: iaload
    //   1329: iload #17
    //   1331: iadd
    //   1332: iastore
    //   1333: aload #15
    //   1335: bipush #7
    //   1337: iload #17
    //   1339: iload #18
    //   1341: iadd
    //   1342: iastore
    //   1343: aload #15
    //   1345: bipush #7
    //   1347: iaload
    //   1348: istore #17
    //   1350: aload #15
    //   1352: bipush #7
    //   1354: aload #15
    //   1356: bipush #6
    //   1358: iaload
    //   1359: iastore
    //   1360: aload #15
    //   1362: bipush #6
    //   1364: aload #15
    //   1366: iconst_5
    //   1367: iaload
    //   1368: iastore
    //   1369: aload #15
    //   1371: iconst_5
    //   1372: aload #15
    //   1374: iconst_4
    //   1375: iaload
    //   1376: iastore
    //   1377: aload #15
    //   1379: iconst_4
    //   1380: aload #15
    //   1382: iconst_3
    //   1383: iaload
    //   1384: iastore
    //   1385: aload #15
    //   1387: iconst_3
    //   1388: aload #15
    //   1390: iconst_2
    //   1391: iaload
    //   1392: iastore
    //   1393: aload #15
    //   1395: iconst_2
    //   1396: aload #15
    //   1398: iconst_1
    //   1399: iaload
    //   1400: iastore
    //   1401: aload #15
    //   1403: iconst_1
    //   1404: aload #15
    //   1406: iconst_0
    //   1407: iaload
    //   1408: iastore
    //   1409: aload #15
    //   1411: iconst_0
    //   1412: iload #17
    //   1414: iastore
    //   1415: iinc #16, 1
    //   1418: iload_2
    //   1419: ifeq -> 927
    //   1422: iconst_0
    //   1423: istore #16
    //   1425: iload #16
    //   1427: bipush #8
    //   1429: if_icmpge -> 1452
    //   1432: aload #8
    //   1434: iload #16
    //   1436: dup2
    //   1437: iaload
    //   1438: aload #15
    //   1440: iload #16
    //   1442: iaload
    //   1443: iadd
    //   1444: iastore
    //   1445: iinc #16, 1
    //   1448: iload_2
    //   1449: ifeq -> 1425
    //   1452: iinc #13, 64
    //   1455: iinc #11, -64
    //   1458: iload_2
    //   1459: ifeq -> 849
    //   1462: iload #11
    //   1464: ifle -> 1499
    //   1467: iconst_0
    //   1468: istore #14
    //   1470: iload #14
    //   1472: iload #11
    //   1474: if_icmpge -> 1499
    //   1477: aload #9
    //   1479: iload #12
    //   1481: iload #14
    //   1483: iadd
    //   1484: aload_3
    //   1485: iload #13
    //   1487: iload #14
    //   1489: iadd
    //   1490: baload
    //   1491: bastore
    //   1492: iinc #14, 1
    //   1495: iload_2
    //   1496: ifeq -> 1470
    //   1499: aload #7
    //   1501: iconst_0
    //   1502: iaload
    //   1503: bipush #29
    //   1505: iushr
    //   1506: aload #7
    //   1508: iconst_1
    //   1509: iaload
    //   1510: iconst_3
    //   1511: ishl
    //   1512: ior
    //   1513: istore #14
    //   1515: aload #7
    //   1517: iconst_0
    //   1518: iaload
    //   1519: iconst_3
    //   1520: ishl
    //   1521: istore #15
    //   1523: aload #7
    //   1525: iconst_0
    //   1526: iaload
    //   1527: bipush #63
    //   1529: iand
    //   1530: istore #16
    //   1532: iload #16
    //   1534: bipush #56
    //   1536: if_icmpge -> 1551
    //   1539: bipush #56
    //   1541: iload #16
    //   1543: isub
    //   1544: goto -> 1556
    //   1547: invokestatic a : (Ljava/lang/Throwable;)Ljava/lang/Throwable;
    //   1550: athrow
    //   1551: bipush #120
    //   1553: iload #16
    //   1555: isub
    //   1556: istore #17
    //   1558: aload #7
    //   1560: iconst_0
    //   1561: iaload
    //   1562: bipush #63
    //   1564: iand
    //   1565: istore #12
    //   1567: bipush #64
    //   1569: iload #12
    //   1571: isub
    //   1572: istore #18
    //   1574: aload #7
    //   1576: iconst_0
    //   1577: dup2
    //   1578: iaload
    //   1579: iload #17
    //   1581: iadd
    //   1582: iastore
    //   1583: aload #7
    //   1585: iconst_0
    //   1586: dup2
    //   1587: iaload
    //   1588: iconst_m1
    //   1589: iand
    //   1590: iastore
    //   1591: aload #7
    //   1593: iconst_0
    //   1594: iaload
    //   1595: iload #17
    //   1597: if_icmpge -> 1615
    //   1600: aload #7
    //   1602: iconst_1
    //   1603: dup2
    //   1604: iaload
    //   1605: iconst_1
    //   1606: iadd
    //   1607: iastore
    //   1608: goto -> 1615
    //   1611: invokestatic a : (Ljava/lang/Throwable;)Ljava/lang/Throwable;
    //   1614: athrow
    //   1615: iconst_0
    //   1616: istore #13
    //   1618: iload #12
    //   1620: ifle -> 2251
    //   1623: iload #17
    //   1625: iload #18
    //   1627: if_icmplt -> 2251
    //   1630: goto -> 1637
    //   1633: invokestatic a : (Ljava/lang/Throwable;)Ljava/lang/Throwable;
    //   1636: athrow
    //   1637: iconst_0
    //   1638: istore #19
    //   1640: iload #19
    //   1642: iload #18
    //   1644: if_icmpge -> 1667
    //   1647: aload #9
    //   1649: iload #12
    //   1651: iload #19
    //   1653: iadd
    //   1654: aload #5
    //   1656: iload #19
    //   1658: baload
    //   1659: bastore
    //   1660: iinc #19, 1
    //   1663: iload_2
    //   1664: ifeq -> 1640
    //   1667: bipush #64
    //   1669: newarray int
    //   1671: astore #19
    //   1673: bipush #8
    //   1675: newarray int
    //   1677: astore #20
    //   1679: iconst_0
    //   1680: istore #21
    //   1682: iload #21
    //   1684: bipush #8
    //   1686: if_icmpge -> 1706
    //   1689: aload #20
    //   1691: iload #21
    //   1693: aload #8
    //   1695: iload #21
    //   1697: iaload
    //   1698: iastore
    //   1699: iinc #21, 1
    //   1702: iload_2
    //   1703: ifeq -> 1682
    //   1706: iconst_0
    //   1707: istore #21
    //   1709: iload #21
    //   1711: bipush #64
    //   1713: if_icmpge -> 2204
    //   1716: iload #21
    //   1718: bipush #16
    //   1720: if_icmpge -> 1801
    //   1723: aload #19
    //   1725: iload #21
    //   1727: aload #9
    //   1729: iconst_4
    //   1730: iload #21
    //   1732: imul
    //   1733: baload
    //   1734: sipush #255
    //   1737: iand
    //   1738: bipush #24
    //   1740: ishl
    //   1741: aload #9
    //   1743: iconst_4
    //   1744: iload #21
    //   1746: imul
    //   1747: iconst_1
    //   1748: iadd
    //   1749: baload
    //   1750: sipush #255
    //   1753: iand
    //   1754: bipush #16
    //   1756: ishl
    //   1757: ior
    //   1758: aload #9
    //   1760: iconst_4
    //   1761: iload #21
    //   1763: imul
    //   1764: iconst_2
    //   1765: iadd
    //   1766: baload
    //   1767: sipush #255
    //   1770: iand
    //   1771: bipush #8
    //   1773: ishl
    //   1774: ior
    //   1775: aload #9
    //   1777: iconst_4
    //   1778: iload #21
    //   1780: imul
    //   1781: iconst_3
    //   1782: iadd
    //   1783: baload
    //   1784: sipush #255
    //   1787: iand
    //   1788: ior
    //   1789: iastore
    //   1790: iload_2
    //   1791: ifeq -> 1944
    //   1794: goto -> 1801
    //   1797: invokestatic a : (Ljava/lang/Throwable;)Ljava/lang/Throwable;
    //   1800: athrow
    //   1801: aload #19
    //   1803: iload #21
    //   1805: aload #19
    //   1807: iload #21
    //   1809: iconst_2
    //   1810: isub
    //   1811: iaload
    //   1812: bipush #17
    //   1814: iushr
    //   1815: aload #19
    //   1817: iload #21
    //   1819: iconst_2
    //   1820: isub
    //   1821: iaload
    //   1822: bipush #15
    //   1824: ishl
    //   1825: ior
    //   1826: aload #19
    //   1828: iload #21
    //   1830: iconst_2
    //   1831: isub
    //   1832: iaload
    //   1833: bipush #19
    //   1835: iushr
    //   1836: aload #19
    //   1838: iload #21
    //   1840: iconst_2
    //   1841: isub
    //   1842: iaload
    //   1843: bipush #13
    //   1845: ishl
    //   1846: ior
    //   1847: ixor
    //   1848: aload #19
    //   1850: iload #21
    //   1852: iconst_2
    //   1853: isub
    //   1854: iaload
    //   1855: bipush #10
    //   1857: iushr
    //   1858: ixor
    //   1859: aload #19
    //   1861: iload #21
    //   1863: bipush #7
    //   1865: isub
    //   1866: iaload
    //   1867: iadd
    //   1868: aload #19
    //   1870: iload #21
    //   1872: bipush #15
    //   1874: isub
    //   1875: iaload
    //   1876: bipush #7
    //   1878: iushr
    //   1879: aload #19
    //   1881: iload #21
    //   1883: bipush #15
    //   1885: isub
    //   1886: iaload
    //   1887: bipush #25
    //   1889: ishl
    //   1890: ior
    //   1891: aload #19
    //   1893: iload #21
    //   1895: bipush #15
    //   1897: isub
    //   1898: iaload
    //   1899: bipush #18
    //   1901: iushr
    //   1902: aload #19
    //   1904: iload #21
    //   1906: bipush #15
    //   1908: isub
    //   1909: iaload
    //   1910: bipush #14
    //   1912: ishl
    //   1913: ior
    //   1914: ixor
    //   1915: aload #19
    //   1917: iload #21
    //   1919: bipush #15
    //   1921: isub
    //   1922: iaload
    //   1923: iconst_3
    //   1924: iushr
    //   1925: ixor
    //   1926: iadd
    //   1927: aload #19
    //   1929: iload #21
    //   1931: bipush #16
    //   1933: isub
    //   1934: iaload
    //   1935: iadd
    //   1936: iastore
    //   1937: goto -> 1944
    //   1940: invokestatic a : (Ljava/lang/Throwable;)Ljava/lang/Throwable;
    //   1943: athrow
    //   1944: aload #20
    //   1946: bipush #7
    //   1948: iaload
    //   1949: aload #20
    //   1951: iconst_4
    //   1952: iaload
    //   1953: bipush #6
    //   1955: iushr
    //   1956: aload #20
    //   1958: iconst_4
    //   1959: iaload
    //   1960: bipush #26
    //   1962: ishl
    //   1963: ior
    //   1964: aload #20
    //   1966: iconst_4
    //   1967: iaload
    //   1968: bipush #11
    //   1970: iushr
    //   1971: aload #20
    //   1973: iconst_4
    //   1974: iaload
    //   1975: bipush #21
    //   1977: ishl
    //   1978: ior
    //   1979: ixor
    //   1980: aload #20
    //   1982: iconst_4
    //   1983: iaload
    //   1984: bipush #25
    //   1986: iushr
    //   1987: aload #20
    //   1989: iconst_4
    //   1990: iaload
    //   1991: bipush #7
    //   1993: ishl
    //   1994: ior
    //   1995: ixor
    //   1996: iadd
    //   1997: aload #20
    //   1999: bipush #6
    //   2001: iaload
    //   2002: aload #20
    //   2004: iconst_4
    //   2005: iaload
    //   2006: aload #20
    //   2008: iconst_5
    //   2009: iaload
    //   2010: aload #20
    //   2012: bipush #6
    //   2014: iaload
    //   2015: ixor
    //   2016: iand
    //   2017: ixor
    //   2018: iadd
    //   2019: aload #6
    //   2021: iload #21
    //   2023: iaload
    //   2024: iadd
    //   2025: aload #19
    //   2027: iload #21
    //   2029: iaload
    //   2030: iadd
    //   2031: istore #22
    //   2033: aload #20
    //   2035: iconst_0
    //   2036: iaload
    //   2037: iconst_2
    //   2038: iushr
    //   2039: aload #20
    //   2041: iconst_0
    //   2042: iaload
    //   2043: bipush #30
    //   2045: ishl
    //   2046: ior
    //   2047: aload #20
    //   2049: iconst_0
    //   2050: iaload
    //   2051: bipush #13
    //   2053: iushr
    //   2054: aload #20
    //   2056: iconst_0
    //   2057: iaload
    //   2058: bipush #19
    //   2060: ishl
    //   2061: ior
    //   2062: ixor
    //   2063: aload #20
    //   2065: iconst_0
    //   2066: iaload
    //   2067: bipush #22
    //   2069: iushr
    //   2070: aload #20
    //   2072: iconst_0
    //   2073: iaload
    //   2074: bipush #10
    //   2076: ishl
    //   2077: ior
    //   2078: ixor
    //   2079: aload #20
    //   2081: iconst_0
    //   2082: iaload
    //   2083: aload #20
    //   2085: iconst_1
    //   2086: iaload
    //   2087: iand
    //   2088: aload #20
    //   2090: iconst_2
    //   2091: iaload
    //   2092: aload #20
    //   2094: iconst_0
    //   2095: iaload
    //   2096: aload #20
    //   2098: iconst_1
    //   2099: iaload
    //   2100: ior
    //   2101: iand
    //   2102: ior
    //   2103: iadd
    //   2104: istore #23
    //   2106: aload #20
    //   2108: iconst_3
    //   2109: dup2
    //   2110: iaload
    //   2111: iload #22
    //   2113: iadd
    //   2114: iastore
    //   2115: aload #20
    //   2117: bipush #7
    //   2119: iload #22
    //   2121: iload #23
    //   2123: iadd
    //   2124: iastore
    //   2125: aload #20
    //   2127: bipush #7
    //   2129: iaload
    //   2130: istore #22
    //   2132: aload #20
    //   2134: bipush #7
    //   2136: aload #20
    //   2138: bipush #6
    //   2140: iaload
    //   2141: iastore
    //   2142: aload #20
    //   2144: bipush #6
    //   2146: aload #20
    //   2148: iconst_5
    //   2149: iaload
    //   2150: iastore
    //   2151: aload #20
    //   2153: iconst_5
    //   2154: aload #20
    //   2156: iconst_4
    //   2157: iaload
    //   2158: iastore
    //   2159: aload #20
    //   2161: iconst_4
    //   2162: aload #20
    //   2164: iconst_3
    //   2165: iaload
    //   2166: iastore
    //   2167: aload #20
    //   2169: iconst_3
    //   2170: aload #20
    //   2172: iconst_2
    //   2173: iaload
    //   2174: iastore
    //   2175: aload #20
    //   2177: iconst_2
    //   2178: aload #20
    //   2180: iconst_1
    //   2181: iaload
    //   2182: iastore
    //   2183: aload #20
    //   2185: iconst_1
    //   2186: aload #20
    //   2188: iconst_0
    //   2189: iaload
    //   2190: iastore
    //   2191: aload #20
    //   2193: iconst_0
    //   2194: iload #22
    //   2196: iastore
    //   2197: iinc #21, 1
    //   2200: iload_2
    //   2201: ifeq -> 1709
    //   2204: iconst_0
    //   2205: istore #21
    //   2207: iload #21
    //   2209: bipush #8
    //   2211: if_icmpge -> 2234
    //   2214: aload #8
    //   2216: iload #21
    //   2218: dup2
    //   2219: iaload
    //   2220: aload #20
    //   2222: iload #21
    //   2224: iaload
    //   2225: iadd
    //   2226: iastore
    //   2227: iinc #21, 1
    //   2230: iload_2
    //   2231: ifeq -> 2207
    //   2234: iload #13
    //   2236: iload #18
    //   2238: iadd
    //   2239: istore #13
    //   2241: iload #17
    //   2243: iload #18
    //   2245: isub
    //   2246: istore #17
    //   2248: iconst_0
    //   2249: istore #12
    //   2251: iload #17
    //   2253: bipush #64
    //   2255: if_icmplt -> 2865
    //   2258: iconst_0
    //   2259: istore #19
    //   2261: iload #19
    //   2263: bipush #64
    //   2265: if_icmpge -> 2288
    //   2268: aload #10
    //   2270: iload #19
    //   2272: aload #5
    //   2274: iload #13
    //   2276: iload #19
    //   2278: iadd
    //   2279: baload
    //   2280: bastore
    //   2281: iinc #19, 1
    //   2284: iload_2
    //   2285: ifeq -> 2261
    //   2288: bipush #64
    //   2290: newarray int
    //   2292: astore #19
    //   2294: bipush #8
    //   2296: newarray int
    //   2298: astore #20
    //   2300: iconst_0
    //   2301: istore #21
    //   2303: iload #21
    //   2305: bipush #8
    //   2307: if_icmpge -> 2327
    //   2310: aload #20
    //   2312: iload #21
    //   2314: aload #8
    //   2316: iload #21
    //   2318: iaload
    //   2319: iastore
    //   2320: iinc #21, 1
    //   2323: iload_2
    //   2324: ifeq -> 2303
    //   2327: iconst_0
    //   2328: istore #21
    //   2330: iload #21
    //   2332: bipush #64
    //   2334: if_icmpge -> 2825
    //   2337: iload #21
    //   2339: bipush #16
    //   2341: if_icmpge -> 2422
    //   2344: aload #19
    //   2346: iload #21
    //   2348: aload #10
    //   2350: iconst_4
    //   2351: iload #21
    //   2353: imul
    //   2354: baload
    //   2355: sipush #255
    //   2358: iand
    //   2359: bipush #24
    //   2361: ishl
    //   2362: aload #10
    //   2364: iconst_4
    //   2365: iload #21
    //   2367: imul
    //   2368: iconst_1
    //   2369: iadd
    //   2370: baload
    //   2371: sipush #255
    //   2374: iand
    //   2375: bipush #16
    //   2377: ishl
    //   2378: ior
    //   2379: aload #10
    //   2381: iconst_4
    //   2382: iload #21
    //   2384: imul
    //   2385: iconst_2
    //   2386: iadd
    //   2387: baload
    //   2388: sipush #255
    //   2391: iand
    //   2392: bipush #8
    //   2394: ishl
    //   2395: ior
    //   2396: aload #10
    //   2398: iconst_4
    //   2399: iload #21
    //   2401: imul
    //   2402: iconst_3
    //   2403: iadd
    //   2404: baload
    //   2405: sipush #255
    //   2408: iand
    //   2409: ior
    //   2410: iastore
    //   2411: iload_2
    //   2412: ifeq -> 2565
    //   2415: goto -> 2422
    //   2418: invokestatic a : (Ljava/lang/Throwable;)Ljava/lang/Throwable;
    //   2421: athrow
    //   2422: aload #19
    //   2424: iload #21
    //   2426: aload #19
    //   2428: iload #21
    //   2430: iconst_2
    //   2431: isub
    //   2432: iaload
    //   2433: bipush #17
    //   2435: iushr
    //   2436: aload #19
    //   2438: iload #21
    //   2440: iconst_2
    //   2441: isub
    //   2442: iaload
    //   2443: bipush #15
    //   2445: ishl
    //   2446: ior
    //   2447: aload #19
    //   2449: iload #21
    //   2451: iconst_2
    //   2452: isub
    //   2453: iaload
    //   2454: bipush #19
    //   2456: iushr
    //   2457: aload #19
    //   2459: iload #21
    //   2461: iconst_2
    //   2462: isub
    //   2463: iaload
    //   2464: bipush #13
    //   2466: ishl
    //   2467: ior
    //   2468: ixor
    //   2469: aload #19
    //   2471: iload #21
    //   2473: iconst_2
    //   2474: isub
    //   2475: iaload
    //   2476: bipush #10
    //   2478: iushr
    //   2479: ixor
    //   2480: aload #19
    //   2482: iload #21
    //   2484: bipush #7
    //   2486: isub
    //   2487: iaload
    //   2488: iadd
    //   2489: aload #19
    //   2491: iload #21
    //   2493: bipush #15
    //   2495: isub
    //   2496: iaload
    //   2497: bipush #7
    //   2499: iushr
    //   2500: aload #19
    //   2502: iload #21
    //   2504: bipush #15
    //   2506: isub
    //   2507: iaload
    //   2508: bipush #25
    //   2510: ishl
    //   2511: ior
    //   2512: aload #19
    //   2514: iload #21
    //   2516: bipush #15
    //   2518: isub
    //   2519: iaload
    //   2520: bipush #18
    //   2522: iushr
    //   2523: aload #19
    //   2525: iload #21
    //   2527: bipush #15
    //   2529: isub
    //   2530: iaload
    //   2531: bipush #14
    //   2533: ishl
    //   2534: ior
    //   2535: ixor
    //   2536: aload #19
    //   2538: iload #21
    //   2540: bipush #15
    //   2542: isub
    //   2543: iaload
    //   2544: iconst_3
    //   2545: iushr
    //   2546: ixor
    //   2547: iadd
    //   2548: aload #19
    //   2550: iload #21
    //   2552: bipush #16
    //   2554: isub
    //   2555: iaload
    //   2556: iadd
    //   2557: iastore
    //   2558: goto -> 2565
    //   2561: invokestatic a : (Ljava/lang/Throwable;)Ljava/lang/Throwable;
    //   2564: athrow
    //   2565: aload #20
    //   2567: bipush #7
    //   2569: iaload
    //   2570: aload #20
    //   2572: iconst_4
    //   2573: iaload
    //   2574: bipush #6
    //   2576: iushr
    //   2577: aload #20
    //   2579: iconst_4
    //   2580: iaload
    //   2581: bipush #26
    //   2583: ishl
    //   2584: ior
    //   2585: aload #20
    //   2587: iconst_4
    //   2588: iaload
    //   2589: bipush #11
    //   2591: iushr
    //   2592: aload #20
    //   2594: iconst_4
    //   2595: iaload
    //   2596: bipush #21
    //   2598: ishl
    //   2599: ior
    //   2600: ixor
    //   2601: aload #20
    //   2603: iconst_4
    //   2604: iaload
    //   2605: bipush #25
    //   2607: iushr
    //   2608: aload #20
    //   2610: iconst_4
    //   2611: iaload
    //   2612: bipush #7
    //   2614: ishl
    //   2615: ior
    //   2616: ixor
    //   2617: iadd
    //   2618: aload #20
    //   2620: bipush #6
    //   2622: iaload
    //   2623: aload #20
    //   2625: iconst_4
    //   2626: iaload
    //   2627: aload #20
    //   2629: iconst_5
    //   2630: iaload
    //   2631: aload #20
    //   2633: bipush #6
    //   2635: iaload
    //   2636: ixor
    //   2637: iand
    //   2638: ixor
    //   2639: iadd
    //   2640: aload #6
    //   2642: iload #21
    //   2644: iaload
    //   2645: iadd
    //   2646: aload #19
    //   2648: iload #21
    //   2650: iaload
    //   2651: iadd
    //   2652: istore #22
    //   2654: aload #20
    //   2656: iconst_0
    //   2657: iaload
    //   2658: iconst_2
    //   2659: iushr
    //   2660: aload #20
    //   2662: iconst_0
    //   2663: iaload
    //   2664: bipush #30
    //   2666: ishl
    //   2667: ior
    //   2668: aload #20
    //   2670: iconst_0
    //   2671: iaload
    //   2672: bipush #13
    //   2674: iushr
    //   2675: aload #20
    //   2677: iconst_0
    //   2678: iaload
    //   2679: bipush #19
    //   2681: ishl
    //   2682: ior
    //   2683: ixor
    //   2684: aload #20
    //   2686: iconst_0
    //   2687: iaload
    //   2688: bipush #22
    //   2690: iushr
    //   2691: aload #20
    //   2693: iconst_0
    //   2694: iaload
    //   2695: bipush #10
    //   2697: ishl
    //   2698: ior
    //   2699: ixor
    //   2700: aload #20
    //   2702: iconst_0
    //   2703: iaload
    //   2704: aload #20
    //   2706: iconst_1
    //   2707: iaload
    //   2708: iand
    //   2709: aload #20
    //   2711: iconst_2
    //   2712: iaload
    //   2713: aload #20
    //   2715: iconst_0
    //   2716: iaload
    //   2717: aload #20
    //   2719: iconst_1
    //   2720: iaload
    //   2721: ior
    //   2722: iand
    //   2723: ior
    //   2724: iadd
    //   2725: istore #23
    //   2727: aload #20
    //   2729: iconst_3
    //   2730: dup2
    //   2731: iaload
    //   2732: iload #22
    //   2734: iadd
    //   2735: iastore
    //   2736: aload #20
    //   2738: bipush #7
    //   2740: iload #22
    //   2742: iload #23
    //   2744: iadd
    //   2745: iastore
    //   2746: aload #20
    //   2748: bipush #7
    //   2750: iaload
    //   2751: istore #22
    //   2753: aload #20
    //   2755: bipush #7
    //   2757: aload #20
    //   2759: bipush #6
    //   2761: iaload
    //   2762: iastore
    //   2763: aload #20
    //   2765: bipush #6
    //   2767: aload #20
    //   2769: iconst_5
    //   2770: iaload
    //   2771: iastore
    //   2772: aload #20
    //   2774: iconst_5
    //   2775: aload #20
    //   2777: iconst_4
    //   2778: iaload
    //   2779: iastore
    //   2780: aload #20
    //   2782: iconst_4
    //   2783: aload #20
    //   2785: iconst_3
    //   2786: iaload
    //   2787: iastore
    //   2788: aload #20
    //   2790: iconst_3
    //   2791: aload #20
    //   2793: iconst_2
    //   2794: iaload
    //   2795: iastore
    //   2796: aload #20
    //   2798: iconst_2
    //   2799: aload #20
    //   2801: iconst_1
    //   2802: iaload
    //   2803: iastore
    //   2804: aload #20
    //   2806: iconst_1
    //   2807: aload #20
    //   2809: iconst_0
    //   2810: iaload
    //   2811: iastore
    //   2812: aload #20
    //   2814: iconst_0
    //   2815: iload #22
    //   2817: iastore
    //   2818: iinc #21, 1
    //   2821: iload_2
    //   2822: ifeq -> 2330
    //   2825: iconst_0
    //   2826: istore #21
    //   2828: iload #21
    //   2830: bipush #8
    //   2832: if_icmpge -> 2855
    //   2835: aload #8
    //   2837: iload #21
    //   2839: dup2
    //   2840: iaload
    //   2841: aload #20
    //   2843: iload #21
    //   2845: iaload
    //   2846: iadd
    //   2847: iastore
    //   2848: iinc #21, 1
    //   2851: iload_2
    //   2852: ifeq -> 2828
    //   2855: iinc #13, 64
    //   2858: iinc #17, -64
    //   2861: iload_2
    //   2862: ifeq -> 2251
    //   2865: iload #17
    //   2867: ifle -> 2903
    //   2870: iconst_0
    //   2871: istore #19
    //   2873: iload #19
    //   2875: iload #17
    //   2877: if_icmpge -> 2903
    //   2880: aload #9
    //   2882: iload #12
    //   2884: iload #19
    //   2886: iadd
    //   2887: aload #5
    //   2889: iload #13
    //   2891: iload #19
    //   2893: iadd
    //   2894: baload
    //   2895: bastore
    //   2896: iinc #19, 1
    //   2899: iload_2
    //   2900: ifeq -> 2873
    //   2903: bipush #8
    //   2905: newarray byte
    //   2907: astore #19
    //   2909: aload #19
    //   2911: iconst_0
    //   2912: iload #14
    //   2914: bipush #24
    //   2916: iushr
    //   2917: i2b
    //   2918: bastore
    //   2919: aload #19
    //   2921: iconst_1
    //   2922: iload #14
    //   2924: bipush #16
    //   2926: iushr
    //   2927: i2b
    //   2928: bastore
    //   2929: aload #19
    //   2931: iconst_2
    //   2932: iload #14
    //   2934: bipush #8
    //   2936: iushr
    //   2937: i2b
    //   2938: bastore
    //   2939: aload #19
    //   2941: iconst_3
    //   2942: iload #14
    //   2944: i2b
    //   2945: bastore
    //   2946: aload #19
    //   2948: iconst_4
    //   2949: iload #15
    //   2951: bipush #24
    //   2953: iushr
    //   2954: i2b
    //   2955: bastore
    //   2956: aload #19
    //   2958: iconst_5
    //   2959: iload #15
    //   2961: bipush #16
    //   2963: iushr
    //   2964: i2b
    //   2965: bastore
    //   2966: aload #19
    //   2968: bipush #6
    //   2970: iload #15
    //   2972: bipush #8
    //   2974: iushr
    //   2975: i2b
    //   2976: bastore
    //   2977: aload #19
    //   2979: bipush #7
    //   2981: iload #15
    //   2983: i2b
    //   2984: bastore
    //   2985: bipush #8
    //   2987: istore #11
    //   2989: aload #7
    //   2991: iconst_0
    //   2992: iaload
    //   2993: bipush #63
    //   2995: iand
    //   2996: istore #12
    //   2998: bipush #64
    //   3000: iload #12
    //   3002: isub
    //   3003: istore #18
    //   3005: aload #7
    //   3007: iconst_0
    //   3008: dup2
    //   3009: iaload
    //   3010: iload #11
    //   3012: iadd
    //   3013: iastore
    //   3014: aload #7
    //   3016: iconst_0
    //   3017: dup2
    //   3018: iaload
    //   3019: iconst_m1
    //   3020: iand
    //   3021: iastore
    //   3022: aload #7
    //   3024: iconst_0
    //   3025: iaload
    //   3026: iload #11
    //   3028: if_icmpge -> 3046
    //   3031: aload #7
    //   3033: iconst_1
    //   3034: dup2
    //   3035: iaload
    //   3036: iconst_1
    //   3037: iadd
    //   3038: iastore
    //   3039: goto -> 3046
    //   3042: invokestatic a : (Ljava/lang/Throwable;)Ljava/lang/Throwable;
    //   3045: athrow
    //   3046: iload #12
    //   3048: ifle -> 3662
    //   3051: iload #11
    //   3053: iload #18
    //   3055: if_icmplt -> 3662
    //   3058: goto -> 3065
    //   3061: invokestatic a : (Ljava/lang/Throwable;)Ljava/lang/Throwable;
    //   3064: athrow
    //   3065: iconst_0
    //   3066: istore #20
    //   3068: iload #20
    //   3070: iload #18
    //   3072: if_icmpge -> 3095
    //   3075: aload #9
    //   3077: iload #12
    //   3079: iload #20
    //   3081: iadd
    //   3082: aload #19
    //   3084: iload #20
    //   3086: baload
    //   3087: bastore
    //   3088: iinc #20, 1
    //   3091: iload_2
    //   3092: ifeq -> 3068
    //   3095: bipush #64
    //   3097: newarray int
    //   3099: astore #20
    //   3101: bipush #8
    //   3103: newarray int
    //   3105: astore #21
    //   3107: iconst_0
    //   3108: istore #22
    //   3110: iload #22
    //   3112: bipush #8
    //   3114: if_icmpge -> 3134
    //   3117: aload #21
    //   3119: iload #22
    //   3121: aload #8
    //   3123: iload #22
    //   3125: iaload
    //   3126: iastore
    //   3127: iinc #22, 1
    //   3130: iload_2
    //   3131: ifeq -> 3110
    //   3134: iconst_0
    //   3135: istore #22
    //   3137: iload #22
    //   3139: bipush #64
    //   3141: if_icmpge -> 3632
    //   3144: iload #22
    //   3146: bipush #16
    //   3148: if_icmpge -> 3229
    //   3151: aload #20
    //   3153: iload #22
    //   3155: aload #9
    //   3157: iconst_4
    //   3158: iload #22
    //   3160: imul
    //   3161: baload
    //   3162: sipush #255
    //   3165: iand
    //   3166: bipush #24
    //   3168: ishl
    //   3169: aload #9
    //   3171: iconst_4
    //   3172: iload #22
    //   3174: imul
    //   3175: iconst_1
    //   3176: iadd
    //   3177: baload
    //   3178: sipush #255
    //   3181: iand
    //   3182: bipush #16
    //   3184: ishl
    //   3185: ior
    //   3186: aload #9
    //   3188: iconst_4
    //   3189: iload #22
    //   3191: imul
    //   3192: iconst_2
    //   3193: iadd
    //   3194: baload
    //   3195: sipush #255
    //   3198: iand
    //   3199: bipush #8
    //   3201: ishl
    //   3202: ior
    //   3203: aload #9
    //   3205: iconst_4
    //   3206: iload #22
    //   3208: imul
    //   3209: iconst_3
    //   3210: iadd
    //   3211: baload
    //   3212: sipush #255
    //   3215: iand
    //   3216: ior
    //   3217: iastore
    //   3218: iload_2
    //   3219: ifeq -> 3372
    //   3222: goto -> 3229
    //   3225: invokestatic a : (Ljava/lang/Throwable;)Ljava/lang/Throwable;
    //   3228: athrow
    //   3229: aload #20
    //   3231: iload #22
    //   3233: aload #20
    //   3235: iload #22
    //   3237: iconst_2
    //   3238: isub
    //   3239: iaload
    //   3240: bipush #17
    //   3242: iushr
    //   3243: aload #20
    //   3245: iload #22
    //   3247: iconst_2
    //   3248: isub
    //   3249: iaload
    //   3250: bipush #15
    //   3252: ishl
    //   3253: ior
    //   3254: aload #20
    //   3256: iload #22
    //   3258: iconst_2
    //   3259: isub
    //   3260: iaload
    //   3261: bipush #19
    //   3263: iushr
    //   3264: aload #20
    //   3266: iload #22
    //   3268: iconst_2
    //   3269: isub
    //   3270: iaload
    //   3271: bipush #13
    //   3273: ishl
    //   3274: ior
    //   3275: ixor
    //   3276: aload #20
    //   3278: iload #22
    //   3280: iconst_2
    //   3281: isub
    //   3282: iaload
    //   3283: bipush #10
    //   3285: iushr
    //   3286: ixor
    //   3287: aload #20
    //   3289: iload #22
    //   3291: bipush #7
    //   3293: isub
    //   3294: iaload
    //   3295: iadd
    //   3296: aload #20
    //   3298: iload #22
    //   3300: bipush #15
    //   3302: isub
    //   3303: iaload
    //   3304: bipush #7
    //   3306: iushr
    //   3307: aload #20
    //   3309: iload #22
    //   3311: bipush #15
    //   3313: isub
    //   3314: iaload
    //   3315: bipush #25
    //   3317: ishl
    //   3318: ior
    //   3319: aload #20
    //   3321: iload #22
    //   3323: bipush #15
    //   3325: isub
    //   3326: iaload
    //   3327: bipush #18
    //   3329: iushr
    //   3330: aload #20
    //   3332: iload #22
    //   3334: bipush #15
    //   3336: isub
    //   3337: iaload
    //   3338: bipush #14
    //   3340: ishl
    //   3341: ior
    //   3342: ixor
    //   3343: aload #20
    //   3345: iload #22
    //   3347: bipush #15
    //   3349: isub
    //   3350: iaload
    //   3351: iconst_3
    //   3352: iushr
    //   3353: ixor
    //   3354: iadd
    //   3355: aload #20
    //   3357: iload #22
    //   3359: bipush #16
    //   3361: isub
    //   3362: iaload
    //   3363: iadd
    //   3364: iastore
    //   3365: goto -> 3372
    //   3368: invokestatic a : (Ljava/lang/Throwable;)Ljava/lang/Throwable;
    //   3371: athrow
    //   3372: aload #21
    //   3374: bipush #7
    //   3376: iaload
    //   3377: aload #21
    //   3379: iconst_4
    //   3380: iaload
    //   3381: bipush #6
    //   3383: iushr
    //   3384: aload #21
    //   3386: iconst_4
    //   3387: iaload
    //   3388: bipush #26
    //   3390: ishl
    //   3391: ior
    //   3392: aload #21
    //   3394: iconst_4
    //   3395: iaload
    //   3396: bipush #11
    //   3398: iushr
    //   3399: aload #21
    //   3401: iconst_4
    //   3402: iaload
    //   3403: bipush #21
    //   3405: ishl
    //   3406: ior
    //   3407: ixor
    //   3408: aload #21
    //   3410: iconst_4
    //   3411: iaload
    //   3412: bipush #25
    //   3414: iushr
    //   3415: aload #21
    //   3417: iconst_4
    //   3418: iaload
    //   3419: bipush #7
    //   3421: ishl
    //   3422: ior
    //   3423: ixor
    //   3424: iadd
    //   3425: aload #21
    //   3427: bipush #6
    //   3429: iaload
    //   3430: aload #21
    //   3432: iconst_4
    //   3433: iaload
    //   3434: aload #21
    //   3436: iconst_5
    //   3437: iaload
    //   3438: aload #21
    //   3440: bipush #6
    //   3442: iaload
    //   3443: ixor
    //   3444: iand
    //   3445: ixor
    //   3446: iadd
    //   3447: aload #6
    //   3449: iload #22
    //   3451: iaload
    //   3452: iadd
    //   3453: aload #20
    //   3455: iload #22
    //   3457: iaload
    //   3458: iadd
    //   3459: istore #23
    //   3461: aload #21
    //   3463: iconst_0
    //   3464: iaload
    //   3465: iconst_2
    //   3466: iushr
    //   3467: aload #21
    //   3469: iconst_0
    //   3470: iaload
    //   3471: bipush #30
    //   3473: ishl
    //   3474: ior
    //   3475: aload #21
    //   3477: iconst_0
    //   3478: iaload
    //   3479: bipush #13
    //   3481: iushr
    //   3482: aload #21
    //   3484: iconst_0
    //   3485: iaload
    //   3486: bipush #19
    //   3488: ishl
    //   3489: ior
    //   3490: ixor
    //   3491: aload #21
    //   3493: iconst_0
    //   3494: iaload
    //   3495: bipush #22
    //   3497: iushr
    //   3498: aload #21
    //   3500: iconst_0
    //   3501: iaload
    //   3502: bipush #10
    //   3504: ishl
    //   3505: ior
    //   3506: ixor
    //   3507: aload #21
    //   3509: iconst_0
    //   3510: iaload
    //   3511: aload #21
    //   3513: iconst_1
    //   3514: iaload
    //   3515: iand
    //   3516: aload #21
    //   3518: iconst_2
    //   3519: iaload
    //   3520: aload #21
    //   3522: iconst_0
    //   3523: iaload
    //   3524: aload #21
    //   3526: iconst_1
    //   3527: iaload
    //   3528: ior
    //   3529: iand
    //   3530: ior
    //   3531: iadd
    //   3532: istore #24
    //   3534: aload #21
    //   3536: iconst_3
    //   3537: dup2
    //   3538: iaload
    //   3539: iload #23
    //   3541: iadd
    //   3542: iastore
    //   3543: aload #21
    //   3545: bipush #7
    //   3547: iload #23
    //   3549: iload #24
    //   3551: iadd
    //   3552: iastore
    //   3553: aload #21
    //   3555: bipush #7
    //   3557: iaload
    //   3558: istore #23
    //   3560: aload #21
    //   3562: bipush #7
    //   3564: aload #21
    //   3566: bipush #6
    //   3568: iaload
    //   3569: iastore
    //   3570: aload #21
    //   3572: bipush #6
    //   3574: aload #21
    //   3576: iconst_5
    //   3577: iaload
    //   3578: iastore
    //   3579: aload #21
    //   3581: iconst_5
    //   3582: aload #21
    //   3584: iconst_4
    //   3585: iaload
    //   3586: iastore
    //   3587: aload #21
    //   3589: iconst_4
    //   3590: aload #21
    //   3592: iconst_3
    //   3593: iaload
    //   3594: iastore
    //   3595: aload #21
    //   3597: iconst_3
    //   3598: aload #21
    //   3600: iconst_2
    //   3601: iaload
    //   3602: iastore
    //   3603: aload #21
    //   3605: iconst_2
    //   3606: aload #21
    //   3608: iconst_1
    //   3609: iaload
    //   3610: iastore
    //   3611: aload #21
    //   3613: iconst_1
    //   3614: aload #21
    //   3616: iconst_0
    //   3617: iaload
    //   3618: iastore
    //   3619: aload #21
    //   3621: iconst_0
    //   3622: iload #23
    //   3624: iastore
    //   3625: iinc #22, 1
    //   3628: iload_2
    //   3629: ifeq -> 3137
    //   3632: iconst_0
    //   3633: istore #22
    //   3635: iload #22
    //   3637: bipush #8
    //   3639: if_icmpge -> 3662
    //   3642: aload #8
    //   3644: iload #22
    //   3646: dup2
    //   3647: iaload
    //   3648: aload #21
    //   3650: iload #22
    //   3652: iaload
    //   3653: iadd
    //   3654: iastore
    //   3655: iinc #22, 1
    //   3658: iload_2
    //   3659: ifeq -> 3635
    //   3662: bipush #32
    //   3664: newarray byte
    //   3666: astore #4
    //   3668: aload #4
    //   3670: iconst_0
    //   3671: aload #8
    //   3673: iconst_0
    //   3674: iaload
    //   3675: bipush #24
    //   3677: iushr
    //   3678: i2b
    //   3679: bastore
    //   3680: aload #4
    //   3682: iconst_1
    //   3683: aload #8
    //   3685: iconst_0
    //   3686: iaload
    //   3687: bipush #16
    //   3689: iushr
    //   3690: i2b
    //   3691: bastore
    //   3692: aload #4
    //   3694: iconst_2
    //   3695: aload #8
    //   3697: iconst_0
    //   3698: iaload
    //   3699: bipush #8
    //   3701: iushr
    //   3702: i2b
    //   3703: bastore
    //   3704: aload #4
    //   3706: iconst_3
    //   3707: aload #8
    //   3709: iconst_0
    //   3710: iaload
    //   3711: i2b
    //   3712: bastore
    //   3713: aload #4
    //   3715: iconst_4
    //   3716: aload #8
    //   3718: iconst_1
    //   3719: iaload
    //   3720: bipush #24
    //   3722: iushr
    //   3723: i2b
    //   3724: bastore
    //   3725: aload #4
    //   3727: iconst_5
    //   3728: aload #8
    //   3730: iconst_1
    //   3731: iaload
    //   3732: bipush #16
    //   3734: iushr
    //   3735: i2b
    //   3736: bastore
    //   3737: aload #4
    //   3739: bipush #6
    //   3741: aload #8
    //   3743: iconst_1
    //   3744: iaload
    //   3745: bipush #8
    //   3747: iushr
    //   3748: i2b
    //   3749: bastore
    //   3750: aload #4
    //   3752: bipush #7
    //   3754: aload #8
    //   3756: iconst_1
    //   3757: iaload
    //   3758: i2b
    //   3759: bastore
    //   3760: aload #4
    //   3762: bipush #8
    //   3764: aload #8
    //   3766: iconst_2
    //   3767: iaload
    //   3768: bipush #24
    //   3770: iushr
    //   3771: i2b
    //   3772: bastore
    //   3773: aload #4
    //   3775: bipush #9
    //   3777: aload #8
    //   3779: iconst_2
    //   3780: iaload
    //   3781: bipush #16
    //   3783: iushr
    //   3784: i2b
    //   3785: bastore
    //   3786: aload #4
    //   3788: bipush #10
    //   3790: aload #8
    //   3792: iconst_2
    //   3793: iaload
    //   3794: bipush #8
    //   3796: iushr
    //   3797: i2b
    //   3798: bastore
    //   3799: aload #4
    //   3801: bipush #11
    //   3803: aload #8
    //   3805: iconst_2
    //   3806: iaload
    //   3807: i2b
    //   3808: bastore
    //   3809: aload #4
    //   3811: bipush #12
    //   3813: aload #8
    //   3815: iconst_3
    //   3816: iaload
    //   3817: bipush #24
    //   3819: iushr
    //   3820: i2b
    //   3821: bastore
    //   3822: aload #4
    //   3824: bipush #13
    //   3826: aload #8
    //   3828: iconst_3
    //   3829: iaload
    //   3830: bipush #16
    //   3832: iushr
    //   3833: i2b
    //   3834: bastore
    //   3835: aload #4
    //   3837: bipush #14
    //   3839: aload #8
    //   3841: iconst_3
    //   3842: iaload
    //   3843: bipush #8
    //   3845: iushr
    //   3846: i2b
    //   3847: bastore
    //   3848: aload #4
    //   3850: bipush #15
    //   3852: aload #8
    //   3854: iconst_3
    //   3855: iaload
    //   3856: i2b
    //   3857: bastore
    //   3858: aload #4
    //   3860: bipush #16
    //   3862: aload #8
    //   3864: iconst_4
    //   3865: iaload
    //   3866: bipush #24
    //   3868: iushr
    //   3869: i2b
    //   3870: bastore
    //   3871: aload #4
    //   3873: bipush #17
    //   3875: aload #8
    //   3877: iconst_4
    //   3878: iaload
    //   3879: bipush #16
    //   3881: iushr
    //   3882: i2b
    //   3883: bastore
    //   3884: aload #4
    //   3886: bipush #18
    //   3888: aload #8
    //   3890: iconst_4
    //   3891: iaload
    //   3892: bipush #8
    //   3894: iushr
    //   3895: i2b
    //   3896: bastore
    //   3897: aload #4
    //   3899: bipush #19
    //   3901: aload #8
    //   3903: iconst_4
    //   3904: iaload
    //   3905: i2b
    //   3906: bastore
    //   3907: aload #4
    //   3909: bipush #20
    //   3911: aload #8
    //   3913: iconst_5
    //   3914: iaload
    //   3915: bipush #24
    //   3917: iushr
    //   3918: i2b
    //   3919: bastore
    //   3920: aload #4
    //   3922: bipush #21
    //   3924: aload #8
    //   3926: iconst_5
    //   3927: iaload
    //   3928: bipush #16
    //   3930: iushr
    //   3931: i2b
    //   3932: bastore
    //   3933: aload #4
    //   3935: bipush #22
    //   3937: aload #8
    //   3939: iconst_5
    //   3940: iaload
    //   3941: bipush #8
    //   3943: iushr
    //   3944: i2b
    //   3945: bastore
    //   3946: aload #4
    //   3948: bipush #23
    //   3950: aload #8
    //   3952: iconst_5
    //   3953: iaload
    //   3954: i2b
    //   3955: bastore
    //   3956: aload #4
    //   3958: bipush #24
    //   3960: aload #8
    //   3962: bipush #6
    //   3964: iaload
    //   3965: bipush #24
    //   3967: iushr
    //   3968: i2b
    //   3969: bastore
    //   3970: aload #4
    //   3972: bipush #25
    //   3974: aload #8
    //   3976: bipush #6
    //   3978: iaload
    //   3979: bipush #16
    //   3981: iushr
    //   3982: i2b
    //   3983: bastore
    //   3984: aload #4
    //   3986: bipush #26
    //   3988: aload #8
    //   3990: bipush #6
    //   3992: iaload
    //   3993: bipush #8
    //   3995: iushr
    //   3996: i2b
    //   3997: bastore
    //   3998: aload #4
    //   4000: bipush #27
    //   4002: aload #8
    //   4004: bipush #6
    //   4006: iaload
    //   4007: i2b
    //   4008: bastore
    //   4009: aload #4
    //   4011: bipush #28
    //   4013: aload #8
    //   4015: bipush #7
    //   4017: iaload
    //   4018: bipush #24
    //   4020: iushr
    //   4021: i2b
    //   4022: bastore
    //   4023: aload #4
    //   4025: bipush #29
    //   4027: aload #8
    //   4029: bipush #7
    //   4031: iaload
    //   4032: bipush #16
    //   4034: iushr
    //   4035: i2b
    //   4036: bastore
    //   4037: aload #4
    //   4039: bipush #30
    //   4041: aload #8
    //   4043: bipush #7
    //   4045: iaload
    //   4046: bipush #8
    //   4048: iushr
    //   4049: i2b
    //   4050: bastore
    //   4051: aload #4
    //   4053: bipush #31
    //   4055: aload #8
    //   4057: bipush #7
    //   4059: iaload
    //   4060: i2b
    //   4061: bastore
    //   4062: new java/math/BigInteger
    //   4065: dup
    //   4066: aload #4
    //   4068: invokespecial <init> : ([B)V
    //   4071: invokevirtual abs : ()Ljava/math/BigInteger;
    //   4074: putstatic burp/Zevr.ZG : Ljava/lang/Object;
    //   4077: getstatic burp/Zg_5.ZA : Ljava/lang/Object;
    //   4080: checkcast java/math/BigInteger
    //   4083: getstatic burp/Zkc8.ZW : Ljava/lang/Object;
    //   4086: checkcast java/math/BigInteger
    //   4089: invokevirtual subtract : (Ljava/math/BigInteger;)Ljava/math/BigInteger;
    //   4092: putstatic burp/Zl8f.ZA : Ljava/lang/Object;
    //   4095: getstatic burp/Zs2n.ZK : Ljava/lang/Object;
    //   4098: checkcast java/math/BigInteger
    //   4101: invokevirtual toByteArray : ()[B
    //   4104: astore_3
    //   4105: bipush #32
    //   4107: newarray int
    //   4109: dup
    //   4110: iconst_0
    //   4111: ldc 876216579
    //   4113: iastore
    //   4114: dup
    //   4115: iconst_1
    //   4116: ldc 455999525
    //   4118: iastore
    //   4119: dup
    //   4120: iconst_2
    //   4121: ldc 1043334948
    //   4123: iastore
    //   4124: dup
    //   4125: iconst_3
    //   4126: ldc 439222784
    //   4128: iastore
    //   4129: dup
    //   4130: iconst_4
    //   4131: ldc 372376604
    //   4133: iastore
    //   4134: dup
    //   4135: iconst_5
    //   4136: ldc 707731490
    //   4138: iastore
    //   4139: dup
    //   4140: bipush #6
    //   4142: ldc 389426184
    //   4144: iastore
    //   4145: dup
    //   4146: bipush #7
    //   4148: ldc 973875457
    //   4150: iastore
    //   4151: dup
    //   4152: bipush #8
    //   4154: ldc 389160971
    //   4156: iastore
    //   4157: dup
    //   4158: bipush #9
    //   4160: ldc 907870729
    //   4162: iastore
    //   4163: dup
    //   4164: bipush #10
    //   4166: ldc 121057538
    //   4168: iastore
    //   4169: dup
    //   4170: bipush #11
    //   4172: ldc 840500228
    //   4174: iastore
    //   4175: dup
    //   4176: bipush #12
    //   4178: ldc 254150144
    //   4180: iastore
    //   4181: dup
    //   4182: bipush #13
    //   4184: ldc 924386310
    //   4186: iastore
    //   4187: dup
    //   4188: bipush #14
    //   4190: ldc 187632156
    //   4192: iastore
    //   4193: dup
    //   4194: bipush #15
    //   4196: ldc 874189824
    //   4198: iastore
    //   4199: dup
    //   4200: bipush #16
    //   4202: ldc 655302664
    //   4204: iastore
    //   4205: dup
    //   4206: bipush #17
    //   4208: ldc 890966315
    //   4210: iastore
    //   4211: dup
    //   4212: bipush #18
    //   4214: ldc 722417666
    //   4216: iastore
    //   4217: dup
    //   4218: bipush #19
    //   4220: ldc 1026621720
    //   4222: iastore
    //   4223: dup
    //   4224: bipush #20
    //   4226: ldc 957157408
    //   4228: iastore
    //   4229: dup
    //   4230: bipush #21
    //   4232: ldc 892536332
    //   4234: iastore
    //   4235: dup
    //   4236: bipush #22
    //   4238: ldc 689771012
    //   4240: iastore
    //   4241: dup
    //   4242: bipush #23
    //   4244: ldc 221709344
    //   4246: iastore
    //   4247: dup
    //   4248: bipush #24
    //   4250: ldc 940377620
    //   4252: iastore
    //   4253: dup
    //   4254: bipush #25
    //   4256: ldc 255209728
    //   4258: iastore
    //   4259: dup
    //   4260: bipush #26
    //   4262: ldc 1010368540
    //   4264: iastore
    //   4265: dup
    //   4266: bipush #27
    //   4268: ldc 220604441
    //   4270: iastore
    //   4271: dup
    //   4272: bipush #28
    //   4274: ldc 1008414755
    //   4276: iastore
    //   4277: dup
    //   4278: bipush #29
    //   4280: ldc 187049985
    //   4282: iastore
    //   4283: dup
    //   4284: bipush #30
    //   4286: ldc 943331329
    //   4288: iastore
    //   4289: dup
    //   4290: bipush #31
    //   4292: ldc 170788368
    //   4294: iastore
    //   4295: astore #5
    //   4297: bipush #64
    //   4299: newarray int
    //   4301: dup
    //   4302: iconst_0
    //   4303: ldc 16843776
    //   4305: iastore
    //   4306: dup
    //   4307: iconst_1
    //   4308: iconst_0
    //   4309: iastore
    //   4310: dup
    //   4311: iconst_2
    //   4312: ldc 65536
    //   4314: iastore
    //   4315: dup
    //   4316: iconst_3
    //   4317: ldc 16843780
    //   4319: iastore
    //   4320: dup
    //   4321: iconst_4
    //   4322: ldc 16842756
    //   4324: iastore
    //   4325: dup
    //   4326: iconst_5
    //   4327: ldc 66564
    //   4329: iastore
    //   4330: dup
    //   4331: bipush #6
    //   4333: iconst_4
    //   4334: iastore
    //   4335: dup
    //   4336: bipush #7
    //   4338: ldc 65536
    //   4340: iastore
    //   4341: dup
    //   4342: bipush #8
    //   4344: sipush #1024
    //   4347: iastore
    //   4348: dup
    //   4349: bipush #9
    //   4351: ldc 16843776
    //   4353: iastore
    //   4354: dup
    //   4355: bipush #10
    //   4357: ldc 16843780
    //   4359: iastore
    //   4360: dup
    //   4361: bipush #11
    //   4363: sipush #1024
    //   4366: iastore
    //   4367: dup
    //   4368: bipush #12
    //   4370: ldc 16778244
    //   4372: iastore
    //   4373: dup
    //   4374: bipush #13
    //   4376: ldc 16842756
    //   4378: iastore
    //   4379: dup
    //   4380: bipush #14
    //   4382: ldc 16777216
    //   4384: iastore
    //   4385: dup
    //   4386: bipush #15
    //   4388: iconst_4
    //   4389: iastore
    //   4390: dup
    //   4391: bipush #16
    //   4393: sipush #1028
    //   4396: iastore
    //   4397: dup
    //   4398: bipush #17
    //   4400: ldc 16778240
    //   4402: iastore
    //   4403: dup
    //   4404: bipush #18
    //   4406: ldc 16778240
    //   4408: iastore
    //   4409: dup
    //   4410: bipush #19
    //   4412: ldc 66560
    //   4414: iastore
    //   4415: dup
    //   4416: bipush #20
    //   4418: ldc 66560
    //   4420: iastore
    //   4421: dup
    //   4422: bipush #21
    //   4424: ldc 16842752
    //   4426: iastore
    //   4427: dup
    //   4428: bipush #22
    //   4430: ldc 16842752
    //   4432: iastore
    //   4433: dup
    //   4434: bipush #23
    //   4436: ldc 16778244
    //   4438: iastore
    //   4439: dup
    //   4440: bipush #24
    //   4442: ldc 65540
    //   4444: iastore
    //   4445: dup
    //   4446: bipush #25
    //   4448: ldc 16777220
    //   4450: iastore
    //   4451: dup
    //   4452: bipush #26
    //   4454: ldc 16777220
    //   4456: iastore
    //   4457: dup
    //   4458: bipush #27
    //   4460: ldc 65540
    //   4462: iastore
    //   4463: dup
    //   4464: bipush #28
    //   4466: iconst_0
    //   4467: iastore
    //   4468: dup
    //   4469: bipush #29
    //   4471: sipush #1028
    //   4474: iastore
    //   4475: dup
    //   4476: bipush #30
    //   4478: ldc 66564
    //   4480: iastore
    //   4481: dup
    //   4482: bipush #31
    //   4484: ldc 16777216
    //   4486: iastore
    //   4487: dup
    //   4488: bipush #32
    //   4490: ldc 65536
    //   4492: iastore
    //   4493: dup
    //   4494: bipush #33
    //   4496: ldc 16843780
    //   4498: iastore
    //   4499: dup
    //   4500: bipush #34
    //   4502: iconst_4
    //   4503: iastore
    //   4504: dup
    //   4505: bipush #35
    //   4507: ldc 16842752
    //   4509: iastore
    //   4510: dup
    //   4511: bipush #36
    //   4513: ldc 16843776
    //   4515: iastore
    //   4516: dup
    //   4517: bipush #37
    //   4519: ldc 16777216
    //   4521: iastore
    //   4522: dup
    //   4523: bipush #38
    //   4525: ldc 16777216
    //   4527: iastore
    //   4528: dup
    //   4529: bipush #39
    //   4531: sipush #1024
    //   4534: iastore
    //   4535: dup
    //   4536: bipush #40
    //   4538: ldc 16842756
    //   4540: iastore
    //   4541: dup
    //   4542: bipush #41
    //   4544: ldc 65536
    //   4546: iastore
    //   4547: dup
    //   4548: bipush #42
    //   4550: ldc 66560
    //   4552: iastore
    //   4553: dup
    //   4554: bipush #43
    //   4556: ldc 16777220
    //   4558: iastore
    //   4559: dup
    //   4560: bipush #44
    //   4562: sipush #1024
    //   4565: iastore
    //   4566: dup
    //   4567: bipush #45
    //   4569: iconst_4
    //   4570: iastore
    //   4571: dup
    //   4572: bipush #46
    //   4574: ldc 16778244
    //   4576: iastore
    //   4577: dup
    //   4578: bipush #47
    //   4580: ldc 66564
    //   4582: iastore
    //   4583: dup
    //   4584: bipush #48
    //   4586: ldc 16843780
    //   4588: iastore
    //   4589: dup
    //   4590: bipush #49
    //   4592: ldc 65540
    //   4594: iastore
    //   4595: dup
    //   4596: bipush #50
    //   4598: ldc 16842752
    //   4600: iastore
    //   4601: dup
    //   4602: bipush #51
    //   4604: ldc 16778244
    //   4606: iastore
    //   4607: dup
    //   4608: bipush #52
    //   4610: ldc 16777220
    //   4612: iastore
    //   4613: dup
    //   4614: bipush #53
    //   4616: sipush #1028
    //   4619: iastore
    //   4620: dup
    //   4621: bipush #54
    //   4623: ldc 66564
    //   4625: iastore
    //   4626: dup
    //   4627: bipush #55
    //   4629: ldc 16843776
    //   4631: iastore
    //   4632: dup
    //   4633: bipush #56
    //   4635: sipush #1028
    //   4638: iastore
    //   4639: dup
    //   4640: bipush #57
    //   4642: ldc 16778240
    //   4644: iastore
    //   4645: dup
    //   4646: bipush #58
    //   4648: ldc 16778240
    //   4650: iastore
    //   4651: dup
    //   4652: bipush #59
    //   4654: iconst_0
    //   4655: iastore
    //   4656: dup
    //   4657: bipush #60
    //   4659: ldc 65540
    //   4661: iastore
    //   4662: dup
    //   4663: bipush #61
    //   4665: ldc 66560
    //   4667: iastore
    //   4668: dup
    //   4669: bipush #62
    //   4671: iconst_0
    //   4672: iastore
    //   4673: dup
    //   4674: bipush #63
    //   4676: ldc 16842756
    //   4678: iastore
    //   4679: astore #6
    //   4681: bipush #64
    //   4683: newarray int
    //   4685: dup
    //   4686: iconst_0
    //   4687: ldc -2146402272
    //   4689: iastore
    //   4690: dup
    //   4691: iconst_1
    //   4692: ldc -2147450880
    //   4694: iastore
    //   4695: dup
    //   4696: iconst_2
    //   4697: ldc 32768
    //   4699: iastore
    //   4700: dup
    //   4701: iconst_3
    //   4702: ldc 1081376
    //   4704: iastore
    //   4705: dup
    //   4706: iconst_4
    //   4707: ldc 1048576
    //   4709: iastore
    //   4710: dup
    //   4711: iconst_5
    //   4712: bipush #32
    //   4714: iastore
    //   4715: dup
    //   4716: bipush #6
    //   4718: ldc -2146435040
    //   4720: iastore
    //   4721: dup
    //   4722: bipush #7
    //   4724: ldc -2147450848
    //   4726: iastore
    //   4727: dup
    //   4728: bipush #8
    //   4730: ldc -2147483616
    //   4732: iastore
    //   4733: dup
    //   4734: bipush #9
    //   4736: ldc -2146402272
    //   4738: iastore
    //   4739: dup
    //   4740: bipush #10
    //   4742: ldc -2146402304
    //   4744: iastore
    //   4745: dup
    //   4746: bipush #11
    //   4748: ldc -2147483648
    //   4750: iastore
    //   4751: dup
    //   4752: bipush #12
    //   4754: ldc -2147450880
    //   4756: iastore
    //   4757: dup
    //   4758: bipush #13
    //   4760: ldc 1048576
    //   4762: iastore
    //   4763: dup
    //   4764: bipush #14
    //   4766: bipush #32
    //   4768: iastore
    //   4769: dup
    //   4770: bipush #15
    //   4772: ldc -2146435040
    //   4774: iastore
    //   4775: dup
    //   4776: bipush #16
    //   4778: ldc 1081344
    //   4780: iastore
    //   4781: dup
    //   4782: bipush #17
    //   4784: ldc 1048608
    //   4786: iastore
    //   4787: dup
    //   4788: bipush #18
    //   4790: ldc -2147450848
    //   4792: iastore
    //   4793: dup
    //   4794: bipush #19
    //   4796: iconst_0
    //   4797: iastore
    //   4798: dup
    //   4799: bipush #20
    //   4801: ldc -2147483648
    //   4803: iastore
    //   4804: dup
    //   4805: bipush #21
    //   4807: ldc 32768
    //   4809: iastore
    //   4810: dup
    //   4811: bipush #22
    //   4813: ldc 1081376
    //   4815: iastore
    //   4816: dup
    //   4817: bipush #23
    //   4819: ldc -2146435072
    //   4821: iastore
    //   4822: dup
    //   4823: bipush #24
    //   4825: ldc 1048608
    //   4827: iastore
    //   4828: dup
    //   4829: bipush #25
    //   4831: ldc -2147483616
    //   4833: iastore
    //   4834: dup
    //   4835: bipush #26
    //   4837: iconst_0
    //   4838: iastore
    //   4839: dup
    //   4840: bipush #27
    //   4842: ldc 1081344
    //   4844: iastore
    //   4845: dup
    //   4846: bipush #28
    //   4848: ldc 32800
    //   4850: iastore
    //   4851: dup
    //   4852: bipush #29
    //   4854: ldc -2146402304
    //   4856: iastore
    //   4857: dup
    //   4858: bipush #30
    //   4860: ldc -2146435072
    //   4862: iastore
    //   4863: dup
    //   4864: bipush #31
    //   4866: ldc 32800
    //   4868: iastore
    //   4869: dup
    //   4870: bipush #32
    //   4872: iconst_0
    //   4873: iastore
    //   4874: dup
    //   4875: bipush #33
    //   4877: ldc 1081376
    //   4879: iastore
    //   4880: dup
    //   4881: bipush #34
    //   4883: ldc -2146435040
    //   4885: iastore
    //   4886: dup
    //   4887: bipush #35
    //   4889: ldc 1048576
    //   4891: iastore
    //   4892: dup
    //   4893: bipush #36
    //   4895: ldc -2147450848
    //   4897: iastore
    //   4898: dup
    //   4899: bipush #37
    //   4901: ldc -2146435072
    //   4903: iastore
    //   4904: dup
    //   4905: bipush #38
    //   4907: ldc -2146402304
    //   4909: iastore
    //   4910: dup
    //   4911: bipush #39
    //   4913: ldc 32768
    //   4915: iastore
    //   4916: dup
    //   4917: bipush #40
    //   4919: ldc -2146435072
    //   4921: iastore
    //   4922: dup
    //   4923: bipush #41
    //   4925: ldc -2147450880
    //   4927: iastore
    //   4928: dup
    //   4929: bipush #42
    //   4931: bipush #32
    //   4933: iastore
    //   4934: dup
    //   4935: bipush #43
    //   4937: ldc -2146402272
    //   4939: iastore
    //   4940: dup
    //   4941: bipush #44
    //   4943: ldc 1081376
    //   4945: iastore
    //   4946: dup
    //   4947: bipush #45
    //   4949: bipush #32
    //   4951: iastore
    //   4952: dup
    //   4953: bipush #46
    //   4955: ldc 32768
    //   4957: iastore
    //   4958: dup
    //   4959: bipush #47
    //   4961: ldc -2147483648
    //   4963: iastore
    //   4964: dup
    //   4965: bipush #48
    //   4967: ldc 32800
    //   4969: iastore
    //   4970: dup
    //   4971: bipush #49
    //   4973: ldc -2146402304
    //   4975: iastore
    //   4976: dup
    //   4977: bipush #50
    //   4979: ldc 1048576
    //   4981: iastore
    //   4982: dup
    //   4983: bipush #51
    //   4985: ldc -2147483616
    //   4987: iastore
    //   4988: dup
    //   4989: bipush #52
    //   4991: ldc 1048608
    //   4993: iastore
    //   4994: dup
    //   4995: bipush #53
    //   4997: ldc -2147450848
    //   4999: iastore
    //   5000: dup
    //   5001: bipush #54
    //   5003: ldc -2147483616
    //   5005: iastore
    //   5006: dup
    //   5007: bipush #55
    //   5009: ldc 1048608
    //   5011: iastore
    //   5012: dup
    //   5013: bipush #56
    //   5015: ldc 1081344
    //   5017: iastore
    //   5018: dup
    //   5019: bipush #57
    //   5021: iconst_0
    //   5022: iastore
    //   5023: dup
    //   5024: bipush #58
    //   5026: ldc -2147450880
    //   5028: iastore
    //   5029: dup
    //   5030: bipush #59
    //   5032: ldc 32800
    //   5034: iastore
    //   5035: dup
    //   5036: bipush #60
    //   5038: ldc -2147483648
    //   5040: iastore
    //   5041: dup
    //   5042: bipush #61
    //   5044: ldc -2146435040
    //   5046: iastore
    //   5047: dup
    //   5048: bipush #62
    //   5050: ldc -2146402272
    //   5052: iastore
    //   5053: dup
    //   5054: bipush #63
    //   5056: ldc 1081344
    //   5058: iastore
    //   5059: astore #7
    //   5061: bipush #64
    //   5063: newarray int
    //   5065: dup
    //   5066: iconst_0
    //   5067: sipush #520
    //   5070: iastore
    //   5071: dup
    //   5072: iconst_1
    //   5073: ldc 134349312
    //   5075: iastore
    //   5076: dup
    //   5077: iconst_2
    //   5078: iconst_0
    //   5079: iastore
    //   5080: dup
    //   5081: iconst_3
    //   5082: ldc 134348808
    //   5084: iastore
    //   5085: dup
    //   5086: iconst_4
    //   5087: ldc 134218240
    //   5089: iastore
    //   5090: dup
    //   5091: iconst_5
    //   5092: iconst_0
    //   5093: iastore
    //   5094: dup
    //   5095: bipush #6
    //   5097: ldc 131592
    //   5099: iastore
    //   5100: dup
    //   5101: bipush #7
    //   5103: ldc 134218240
    //   5105: iastore
    //   5106: dup
    //   5107: bipush #8
    //   5109: ldc 131080
    //   5111: iastore
    //   5112: dup
    //   5113: bipush #9
    //   5115: ldc 134217736
    //   5117: iastore
    //   5118: dup
    //   5119: bipush #10
    //   5121: ldc 134217736
    //   5123: iastore
    //   5124: dup
    //   5125: bipush #11
    //   5127: ldc 131072
    //   5129: iastore
    //   5130: dup
    //   5131: bipush #12
    //   5133: ldc 134349320
    //   5135: iastore
    //   5136: dup
    //   5137: bipush #13
    //   5139: ldc 131080
    //   5141: iastore
    //   5142: dup
    //   5143: bipush #14
    //   5145: ldc 134348800
    //   5147: iastore
    //   5148: dup
    //   5149: bipush #15
    //   5151: sipush #520
    //   5154: iastore
    //   5155: dup
    //   5156: bipush #16
    //   5158: ldc 134217728
    //   5160: iastore
    //   5161: dup
    //   5162: bipush #17
    //   5164: bipush #8
    //   5166: iastore
    //   5167: dup
    //   5168: bipush #18
    //   5170: ldc 134349312
    //   5172: iastore
    //   5173: dup
    //   5174: bipush #19
    //   5176: sipush #512
    //   5179: iastore
    //   5180: dup
    //   5181: bipush #20
    //   5183: ldc 131584
    //   5185: iastore
    //   5186: dup
    //   5187: bipush #21
    //   5189: ldc 134348800
    //   5191: iastore
    //   5192: dup
    //   5193: bipush #22
    //   5195: ldc 134348808
    //   5197: iastore
    //   5198: dup
    //   5199: bipush #23
    //   5201: ldc 131592
    //   5203: iastore
    //   5204: dup
    //   5205: bipush #24
    //   5207: ldc 134218248
    //   5209: iastore
    //   5210: dup
    //   5211: bipush #25
    //   5213: ldc 131584
    //   5215: iastore
    //   5216: dup
    //   5217: bipush #26
    //   5219: ldc 131072
    //   5221: iastore
    //   5222: dup
    //   5223: bipush #27
    //   5225: ldc 134218248
    //   5227: iastore
    //   5228: dup
    //   5229: bipush #28
    //   5231: bipush #8
    //   5233: iastore
    //   5234: dup
    //   5235: bipush #29
    //   5237: ldc 134349320
    //   5239: iastore
    //   5240: dup
    //   5241: bipush #30
    //   5243: sipush #512
    //   5246: iastore
    //   5247: dup
    //   5248: bipush #31
    //   5250: ldc 134217728
    //   5252: iastore
    //   5253: dup
    //   5254: bipush #32
    //   5256: ldc 134349312
    //   5258: iastore
    //   5259: dup
    //   5260: bipush #33
    //   5262: ldc 134217728
    //   5264: iastore
    //   5265: dup
    //   5266: bipush #34
    //   5268: ldc 131080
    //   5270: iastore
    //   5271: dup
    //   5272: bipush #35
    //   5274: sipush #520
    //   5277: iastore
    //   5278: dup
    //   5279: bipush #36
    //   5281: ldc 131072
    //   5283: iastore
    //   5284: dup
    //   5285: bipush #37
    //   5287: ldc 134349312
    //   5289: iastore
    //   5290: dup
    //   5291: bipush #38
    //   5293: ldc 134218240
    //   5295: iastore
    //   5296: dup
    //   5297: bipush #39
    //   5299: iconst_0
    //   5300: iastore
    //   5301: dup
    //   5302: bipush #40
    //   5304: sipush #512
    //   5307: iastore
    //   5308: dup
    //   5309: bipush #41
    //   5311: ldc 131080
    //   5313: iastore
    //   5314: dup
    //   5315: bipush #42
    //   5317: ldc 134349320
    //   5319: iastore
    //   5320: dup
    //   5321: bipush #43
    //   5323: ldc 134218240
    //   5325: iastore
    //   5326: dup
    //   5327: bipush #44
    //   5329: ldc 134217736
    //   5331: iastore
    //   5332: dup
    //   5333: bipush #45
    //   5335: sipush #512
    //   5338: iastore
    //   5339: dup
    //   5340: bipush #46
    //   5342: iconst_0
    //   5343: iastore
    //   5344: dup
    //   5345: bipush #47
    //   5347: ldc 134348808
    //   5349: iastore
    //   5350: dup
    //   5351: bipush #48
    //   5353: ldc 134218248
    //   5355: iastore
    //   5356: dup
    //   5357: bipush #49
    //   5359: ldc 131072
    //   5361: iastore
    //   5362: dup
    //   5363: bipush #50
    //   5365: ldc 134217728
    //   5367: iastore
    //   5368: dup
    //   5369: bipush #51
    //   5371: ldc 134349320
    //   5373: iastore
    //   5374: dup
    //   5375: bipush #52
    //   5377: bipush #8
    //   5379: iastore
    //   5380: dup
    //   5381: bipush #53
    //   5383: ldc 131592
    //   5385: iastore
    //   5386: dup
    //   5387: bipush #54
    //   5389: ldc 131584
    //   5391: iastore
    //   5392: dup
    //   5393: bipush #55
    //   5395: ldc 134217736
    //   5397: iastore
    //   5398: dup
    //   5399: bipush #56
    //   5401: ldc 134348800
    //   5403: iastore
    //   5404: dup
    //   5405: bipush #57
    //   5407: ldc 134218248
    //   5409: iastore
    //   5410: dup
    //   5411: bipush #58
    //   5413: sipush #520
    //   5416: iastore
    //   5417: dup
    //   5418: bipush #59
    //   5420: ldc 134348800
    //   5422: iastore
    //   5423: dup
    //   5424: bipush #60
    //   5426: ldc 131592
    //   5428: iastore
    //   5429: dup
    //   5430: bipush #61
    //   5432: bipush #8
    //   5434: iastore
    //   5435: dup
    //   5436: bipush #62
    //   5438: ldc 134348808
    //   5440: iastore
    //   5441: dup
    //   5442: bipush #63
    //   5444: ldc 131584
    //   5446: iastore
    //   5447: astore #8
    //   5449: bipush #64
    //   5451: newarray int
    //   5453: dup
    //   5454: iconst_0
    //   5455: ldc 8396801
    //   5457: iastore
    //   5458: dup
    //   5459: iconst_1
    //   5460: sipush #8321
    //   5463: iastore
    //   5464: dup
    //   5465: iconst_2
    //   5466: sipush #8321
    //   5469: iastore
    //   5470: dup
    //   5471: iconst_3
    //   5472: sipush #128
    //   5475: iastore
    //   5476: dup
    //   5477: iconst_4
    //   5478: ldc 8396928
    //   5480: iastore
    //   5481: dup
    //   5482: iconst_5
    //   5483: ldc 8388737
    //   5485: iastore
    //   5486: dup
    //   5487: bipush #6
    //   5489: ldc 8388609
    //   5491: iastore
    //   5492: dup
    //   5493: bipush #7
    //   5495: sipush #8193
    //   5498: iastore
    //   5499: dup
    //   5500: bipush #8
    //   5502: iconst_0
    //   5503: iastore
    //   5504: dup
    //   5505: bipush #9
    //   5507: ldc 8396800
    //   5509: iastore
    //   5510: dup
    //   5511: bipush #10
    //   5513: ldc 8396800
    //   5515: iastore
    //   5516: dup
    //   5517: bipush #11
    //   5519: ldc 8396929
    //   5521: iastore
    //   5522: dup
    //   5523: bipush #12
    //   5525: sipush #129
    //   5528: iastore
    //   5529: dup
    //   5530: bipush #13
    //   5532: iconst_0
    //   5533: iastore
    //   5534: dup
    //   5535: bipush #14
    //   5537: ldc 8388736
    //   5539: iastore
    //   5540: dup
    //   5541: bipush #15
    //   5543: ldc 8388609
    //   5545: iastore
    //   5546: dup
    //   5547: bipush #16
    //   5549: iconst_1
    //   5550: iastore
    //   5551: dup
    //   5552: bipush #17
    //   5554: sipush #8192
    //   5557: iastore
    //   5558: dup
    //   5559: bipush #18
    //   5561: ldc 8388608
    //   5563: iastore
    //   5564: dup
    //   5565: bipush #19
    //   5567: ldc 8396801
    //   5569: iastore
    //   5570: dup
    //   5571: bipush #20
    //   5573: sipush #128
    //   5576: iastore
    //   5577: dup
    //   5578: bipush #21
    //   5580: ldc 8388608
    //   5582: iastore
    //   5583: dup
    //   5584: bipush #22
    //   5586: sipush #8193
    //   5589: iastore
    //   5590: dup
    //   5591: bipush #23
    //   5593: sipush #8320
    //   5596: iastore
    //   5597: dup
    //   5598: bipush #24
    //   5600: ldc 8388737
    //   5602: iastore
    //   5603: dup
    //   5604: bipush #25
    //   5606: iconst_1
    //   5607: iastore
    //   5608: dup
    //   5609: bipush #26
    //   5611: sipush #8320
    //   5614: iastore
    //   5615: dup
    //   5616: bipush #27
    //   5618: ldc 8388736
    //   5620: iastore
    //   5621: dup
    //   5622: bipush #28
    //   5624: sipush #8192
    //   5627: iastore
    //   5628: dup
    //   5629: bipush #29
    //   5631: ldc 8396928
    //   5633: iastore
    //   5634: dup
    //   5635: bipush #30
    //   5637: ldc 8396929
    //   5639: iastore
    //   5640: dup
    //   5641: bipush #31
    //   5643: sipush #129
    //   5646: iastore
    //   5647: dup
    //   5648: bipush #32
    //   5650: ldc 8388736
    //   5652: iastore
    //   5653: dup
    //   5654: bipush #33
    //   5656: ldc 8388609
    //   5658: iastore
    //   5659: dup
    //   5660: bipush #34
    //   5662: ldc 8396800
    //   5664: iastore
    //   5665: dup
    //   5666: bipush #35
    //   5668: ldc 8396929
    //   5670: iastore
    //   5671: dup
    //   5672: bipush #36
    //   5674: sipush #129
    //   5677: iastore
    //   5678: dup
    //   5679: bipush #37
    //   5681: iconst_0
    //   5682: iastore
    //   5683: dup
    //   5684: bipush #38
    //   5686: iconst_0
    //   5687: iastore
    //   5688: dup
    //   5689: bipush #39
    //   5691: ldc 8396800
    //   5693: iastore
    //   5694: dup
    //   5695: bipush #40
    //   5697: sipush #8320
    //   5700: iastore
    //   5701: dup
    //   5702: bipush #41
    //   5704: ldc 8388736
    //   5706: iastore
    //   5707: dup
    //   5708: bipush #42
    //   5710: ldc 8388737
    //   5712: iastore
    //   5713: dup
    //   5714: bipush #43
    //   5716: iconst_1
    //   5717: iastore
    //   5718: dup
    //   5719: bipush #44
    //   5721: ldc 8396801
    //   5723: iastore
    //   5724: dup
    //   5725: bipush #45
    //   5727: sipush #8321
    //   5730: iastore
    //   5731: dup
    //   5732: bipush #46
    //   5734: sipush #8321
    //   5737: iastore
    //   5738: dup
    //   5739: bipush #47
    //   5741: sipush #128
    //   5744: iastore
    //   5745: dup
    //   5746: bipush #48
    //   5748: ldc 8396929
    //   5750: iastore
    //   5751: dup
    //   5752: bipush #49
    //   5754: sipush #129
    //   5757: iastore
    //   5758: dup
    //   5759: bipush #50
    //   5761: iconst_1
    //   5762: iastore
    //   5763: dup
    //   5764: bipush #51
    //   5766: sipush #8192
    //   5769: iastore
    //   5770: dup
    //   5771: bipush #52
    //   5773: ldc 8388609
    //   5775: iastore
    //   5776: dup
    //   5777: bipush #53
    //   5779: sipush #8193
    //   5782: iastore
    //   5783: dup
    //   5784: bipush #54
    //   5786: ldc 8396928
    //   5788: iastore
    //   5789: dup
    //   5790: bipush #55
    //   5792: ldc 8388737
    //   5794: iastore
    //   5795: dup
    //   5796: bipush #56
    //   5798: sipush #8193
    //   5801: iastore
    //   5802: dup
    //   5803: bipush #57
    //   5805: sipush #8320
    //   5808: iastore
    //   5809: dup
    //   5810: bipush #58
    //   5812: ldc 8388608
    //   5814: iastore
    //   5815: dup
    //   5816: bipush #59
    //   5818: ldc 8396801
    //   5820: iastore
    //   5821: dup
    //   5822: bipush #60
    //   5824: sipush #128
    //   5827: iastore
    //   5828: dup
    //   5829: bipush #61
    //   5831: ldc 8388608
    //   5833: iastore
    //   5834: dup
    //   5835: bipush #62
    //   5837: sipush #8192
    //   5840: iastore
    //   5841: dup
    //   5842: bipush #63
    //   5844: ldc 8396928
    //   5846: iastore
    //   5847: astore #9
    //   5849: bipush #64
    //   5851: newarray int
    //   5853: dup
    //   5854: iconst_0
    //   5855: sipush #256
    //   5858: iastore
    //   5859: dup
    //   5860: iconst_1
    //   5861: ldc 34078976
    //   5863: iastore
    //   5864: dup
    //   5865: iconst_2
    //   5866: ldc 34078720
    //   5868: iastore
    //   5869: dup
    //   5870: iconst_3
    //   5871: ldc 1107296512
    //   5873: iastore
    //   5874: dup
    //   5875: iconst_4
    //   5876: ldc 524288
    //   5878: iastore
    //   5879: dup
    //   5880: iconst_5
    //   5881: sipush #256
    //   5884: iastore
    //   5885: dup
    //   5886: bipush #6
    //   5888: ldc 1073741824
    //   5890: iastore
    //   5891: dup
    //   5892: bipush #7
    //   5894: ldc 34078720
    //   5896: iastore
    //   5897: dup
    //   5898: bipush #8
    //   5900: ldc 1074266368
    //   5902: iastore
    //   5903: dup
    //   5904: bipush #9
    //   5906: ldc 524288
    //   5908: iastore
    //   5909: dup
    //   5910: bipush #10
    //   5912: ldc 33554688
    //   5914: iastore
    //   5915: dup
    //   5916: bipush #11
    //   5918: ldc 1074266368
    //   5920: iastore
    //   5921: dup
    //   5922: bipush #12
    //   5924: ldc 1107296512
    //   5926: iastore
    //   5927: dup
    //   5928: bipush #13
    //   5930: ldc 1107820544
    //   5932: iastore
    //   5933: dup
    //   5934: bipush #14
    //   5936: ldc 524544
    //   5938: iastore
    //   5939: dup
    //   5940: bipush #15
    //   5942: ldc 1073741824
    //   5944: iastore
    //   5945: dup
    //   5946: bipush #16
    //   5948: ldc 33554432
    //   5950: iastore
    //   5951: dup
    //   5952: bipush #17
    //   5954: ldc 1074266112
    //   5956: iastore
    //   5957: dup
    //   5958: bipush #18
    //   5960: ldc 1074266112
    //   5962: iastore
    //   5963: dup
    //   5964: bipush #19
    //   5966: iconst_0
    //   5967: iastore
    //   5968: dup
    //   5969: bipush #20
    //   5971: ldc 1073742080
    //   5973: iastore
    //   5974: dup
    //   5975: bipush #21
    //   5977: ldc 1107820800
    //   5979: iastore
    //   5980: dup
    //   5981: bipush #22
    //   5983: ldc 1107820800
    //   5985: iastore
    //   5986: dup
    //   5987: bipush #23
    //   5989: ldc 33554688
    //   5991: iastore
    //   5992: dup
    //   5993: bipush #24
    //   5995: ldc 1107820544
    //   5997: iastore
    //   5998: dup
    //   5999: bipush #25
    //   6001: ldc 1073742080
    //   6003: iastore
    //   6004: dup
    //   6005: bipush #26
    //   6007: iconst_0
    //   6008: iastore
    //   6009: dup
    //   6010: bipush #27
    //   6012: ldc 1107296256
    //   6014: iastore
    //   6015: dup
    //   6016: bipush #28
    //   6018: ldc 34078976
    //   6020: iastore
    //   6021: dup
    //   6022: bipush #29
    //   6024: ldc 33554432
    //   6026: iastore
    //   6027: dup
    //   6028: bipush #30
    //   6030: ldc 1107296256
    //   6032: iastore
    //   6033: dup
    //   6034: bipush #31
    //   6036: ldc 524544
    //   6038: iastore
    //   6039: dup
    //   6040: bipush #32
    //   6042: ldc 524288
    //   6044: iastore
    //   6045: dup
    //   6046: bipush #33
    //   6048: ldc 1107296512
    //   6050: iastore
    //   6051: dup
    //   6052: bipush #34
    //   6054: sipush #256
    //   6057: iastore
    //   6058: dup
    //   6059: bipush #35
    //   6061: ldc 33554432
    //   6063: iastore
    //   6064: dup
    //   6065: bipush #36
    //   6067: ldc 1073741824
    //   6069: iastore
    //   6070: dup
    //   6071: bipush #37
    //   6073: ldc 34078720
    //   6075: iastore
    //   6076: dup
    //   6077: bipush #38
    //   6079: ldc 1107296512
    //   6081: iastore
    //   6082: dup
    //   6083: bipush #39
    //   6085: ldc 1074266368
    //   6087: iastore
    //   6088: dup
    //   6089: bipush #40
    //   6091: ldc 33554688
    //   6093: iastore
    //   6094: dup
    //   6095: bipush #41
    //   6097: ldc 1073741824
    //   6099: iastore
    //   6100: dup
    //   6101: bipush #42
    //   6103: ldc 1107820544
    //   6105: iastore
    //   6106: dup
    //   6107: bipush #43
    //   6109: ldc 34078976
    //   6111: iastore
    //   6112: dup
    //   6113: bipush #44
    //   6115: ldc 1074266368
    //   6117: iastore
    //   6118: dup
    //   6119: bipush #45
    //   6121: sipush #256
    //   6124: iastore
    //   6125: dup
    //   6126: bipush #46
    //   6128: ldc 33554432
    //   6130: iastore
    //   6131: dup
    //   6132: bipush #47
    //   6134: ldc 1107820544
    //   6136: iastore
    //   6137: dup
    //   6138: bipush #48
    //   6140: ldc 1107820800
    //   6142: iastore
    //   6143: dup
    //   6144: bipush #49
    //   6146: ldc 524544
    //   6148: iastore
    //   6149: dup
    //   6150: bipush #50
    //   6152: ldc 1107296256
    //   6154: iastore
    //   6155: dup
    //   6156: bipush #51
    //   6158: ldc 1107820800
    //   6160: iastore
    //   6161: dup
    //   6162: bipush #52
    //   6164: ldc 34078720
    //   6166: iastore
    //   6167: dup
    //   6168: bipush #53
    //   6170: iconst_0
    //   6171: iastore
    //   6172: dup
    //   6173: bipush #54
    //   6175: ldc 1074266112
    //   6177: iastore
    //   6178: dup
    //   6179: bipush #55
    //   6181: ldc 1107296256
    //   6183: iastore
    //   6184: dup
    //   6185: bipush #56
    //   6187: ldc 524544
    //   6189: iastore
    //   6190: dup
    //   6191: bipush #57
    //   6193: ldc 33554688
    //   6195: iastore
    //   6196: dup
    //   6197: bipush #58
    //   6199: ldc 1073742080
    //   6201: iastore
    //   6202: dup
    //   6203: bipush #59
    //   6205: ldc 524288
    //   6207: iastore
    //   6208: dup
    //   6209: bipush #60
    //   6211: iconst_0
    //   6212: iastore
    //   6213: dup
    //   6214: bipush #61
    //   6216: ldc 1074266112
    //   6218: iastore
    //   6219: dup
    //   6220: bipush #62
    //   6222: ldc 34078976
    //   6224: iastore
    //   6225: dup
    //   6226: bipush #63
    //   6228: ldc 1073742080
    //   6230: iastore
    //   6231: astore #10
    //   6233: bipush #64
    //   6235: newarray int
    //   6237: dup
    //   6238: iconst_0
    //   6239: ldc 536870928
    //   6241: iastore
    //   6242: dup
    //   6243: iconst_1
    //   6244: ldc 541065216
    //   6246: iastore
    //   6247: dup
    //   6248: iconst_2
    //   6249: sipush #16384
    //   6252: iastore
    //   6253: dup
    //   6254: iconst_3
    //   6255: ldc 541081616
    //   6257: iastore
    //   6258: dup
    //   6259: iconst_4
    //   6260: ldc 541065216
    //   6262: iastore
    //   6263: dup
    //   6264: iconst_5
    //   6265: bipush #16
    //   6267: iastore
    //   6268: dup
    //   6269: bipush #6
    //   6271: ldc 541081616
    //   6273: iastore
    //   6274: dup
    //   6275: bipush #7
    //   6277: ldc 4194304
    //   6279: iastore
    //   6280: dup
    //   6281: bipush #8
    //   6283: ldc 536887296
    //   6285: iastore
    //   6286: dup
    //   6287: bipush #9
    //   6289: ldc 4210704
    //   6291: iastore
    //   6292: dup
    //   6293: bipush #10
    //   6295: ldc 4194304
    //   6297: iastore
    //   6298: dup
    //   6299: bipush #11
    //   6301: ldc 536870928
    //   6303: iastore
    //   6304: dup
    //   6305: bipush #12
    //   6307: ldc 4194320
    //   6309: iastore
    //   6310: dup
    //   6311: bipush #13
    //   6313: ldc 536887296
    //   6315: iastore
    //   6316: dup
    //   6317: bipush #14
    //   6319: ldc 536870912
    //   6321: iastore
    //   6322: dup
    //   6323: bipush #15
    //   6325: sipush #16400
    //   6328: iastore
    //   6329: dup
    //   6330: bipush #16
    //   6332: iconst_0
    //   6333: iastore
    //   6334: dup
    //   6335: bipush #17
    //   6337: ldc 4194320
    //   6339: iastore
    //   6340: dup
    //   6341: bipush #18
    //   6343: ldc 536887312
    //   6345: iastore
    //   6346: dup
    //   6347: bipush #19
    //   6349: sipush #16384
    //   6352: iastore
    //   6353: dup
    //   6354: bipush #20
    //   6356: ldc 4210688
    //   6358: iastore
    //   6359: dup
    //   6360: bipush #21
    //   6362: ldc 536887312
    //   6364: iastore
    //   6365: dup
    //   6366: bipush #22
    //   6368: bipush #16
    //   6370: iastore
    //   6371: dup
    //   6372: bipush #23
    //   6374: ldc 541065232
    //   6376: iastore
    //   6377: dup
    //   6378: bipush #24
    //   6380: ldc 541065232
    //   6382: iastore
    //   6383: dup
    //   6384: bipush #25
    //   6386: iconst_0
    //   6387: iastore
    //   6388: dup
    //   6389: bipush #26
    //   6391: ldc 4210704
    //   6393: iastore
    //   6394: dup
    //   6395: bipush #27
    //   6397: ldc 541081600
    //   6399: iastore
    //   6400: dup
    //   6401: bipush #28
    //   6403: sipush #16400
    //   6406: iastore
    //   6407: dup
    //   6408: bipush #29
    //   6410: ldc 4210688
    //   6412: iastore
    //   6413: dup
    //   6414: bipush #30
    //   6416: ldc 541081600
    //   6418: iastore
    //   6419: dup
    //   6420: bipush #31
    //   6422: ldc 536870912
    //   6424: iastore
    //   6425: dup
    //   6426: bipush #32
    //   6428: ldc 536887296
    //   6430: iastore
    //   6431: dup
    //   6432: bipush #33
    //   6434: bipush #16
    //   6436: iastore
    //   6437: dup
    //   6438: bipush #34
    //   6440: ldc 541065232
    //   6442: iastore
    //   6443: dup
    //   6444: bipush #35
    //   6446: ldc 4210688
    //   6448: iastore
    //   6449: dup
    //   6450: bipush #36
    //   6452: ldc 541081616
    //   6454: iastore
    //   6455: dup
    //   6456: bipush #37
    //   6458: ldc 4194304
    //   6460: iastore
    //   6461: dup
    //   6462: bipush #38
    //   6464: sipush #16400
    //   6467: iastore
    //   6468: dup
    //   6469: bipush #39
    //   6471: ldc 536870928
    //   6473: iastore
    //   6474: dup
    //   6475: bipush #40
    //   6477: ldc 4194304
    //   6479: iastore
    //   6480: dup
    //   6481: bipush #41
    //   6483: ldc 536887296
    //   6485: iastore
    //   6486: dup
    //   6487: bipush #42
    //   6489: ldc 536870912
    //   6491: iastore
    //   6492: dup
    //   6493: bipush #43
    //   6495: sipush #16400
    //   6498: iastore
    //   6499: dup
    //   6500: bipush #44
    //   6502: ldc 536870928
    //   6504: iastore
    //   6505: dup
    //   6506: bipush #45
    //   6508: ldc 541081616
    //   6510: iastore
    //   6511: dup
    //   6512: bipush #46
    //   6514: ldc 4210688
    //   6516: iastore
    //   6517: dup
    //   6518: bipush #47
    //   6520: ldc 541065216
    //   6522: iastore
    //   6523: dup
    //   6524: bipush #48
    //   6526: ldc 4210704
    //   6528: iastore
    //   6529: dup
    //   6530: bipush #49
    //   6532: ldc 541081600
    //   6534: iastore
    //   6535: dup
    //   6536: bipush #50
    //   6538: iconst_0
    //   6539: iastore
    //   6540: dup
    //   6541: bipush #51
    //   6543: ldc 541065232
    //   6545: iastore
    //   6546: dup
    //   6547: bipush #52
    //   6549: bipush #16
    //   6551: iastore
    //   6552: dup
    //   6553: bipush #53
    //   6555: sipush #16384
    //   6558: iastore
    //   6559: dup
    //   6560: bipush #54
    //   6562: ldc 541065216
    //   6564: iastore
    //   6565: dup
    //   6566: bipush #55
    //   6568: ldc 4210704
    //   6570: iastore
    //   6571: dup
    //   6572: bipush #56
    //   6574: sipush #16384
    //   6577: iastore
    //   6578: dup
    //   6579: bipush #57
    //   6581: ldc 4194320
    //   6583: iastore
    //   6584: dup
    //   6585: bipush #58
    //   6587: ldc 536887312
    //   6589: iastore
    //   6590: dup
    //   6591: bipush #59
    //   6593: iconst_0
    //   6594: iastore
    //   6595: dup
    //   6596: bipush #60
    //   6598: ldc 541081600
    //   6600: iastore
    //   6601: dup
    //   6602: bipush #61
    //   6604: ldc 536870912
    //   6606: iastore
    //   6607: dup
    //   6608: bipush #62
    //   6610: ldc 4194320
    //   6612: iastore
    //   6613: dup
    //   6614: bipush #63
    //   6616: ldc 536887312
    //   6618: iastore
    //   6619: astore #11
    //   6621: bipush #64
    //   6623: newarray int
    //   6625: dup
    //   6626: iconst_0
    //   6627: ldc 2097152
    //   6629: iastore
    //   6630: dup
    //   6631: iconst_1
    //   6632: ldc 69206018
    //   6634: iastore
    //   6635: dup
    //   6636: iconst_2
    //   6637: ldc 67110914
    //   6639: iastore
    //   6640: dup
    //   6641: iconst_3
    //   6642: iconst_0
    //   6643: iastore
    //   6644: dup
    //   6645: iconst_4
    //   6646: sipush #2048
    //   6649: iastore
    //   6650: dup
    //   6651: iconst_5
    //   6652: ldc 67110914
    //   6654: iastore
    //   6655: dup
    //   6656: bipush #6
    //   6658: ldc 2099202
    //   6660: iastore
    //   6661: dup
    //   6662: bipush #7
    //   6664: ldc 69208064
    //   6666: iastore
    //   6667: dup
    //   6668: bipush #8
    //   6670: ldc 69208066
    //   6672: iastore
    //   6673: dup
    //   6674: bipush #9
    //   6676: ldc 2097152
    //   6678: iastore
    //   6679: dup
    //   6680: bipush #10
    //   6682: iconst_0
    //   6683: iastore
    //   6684: dup
    //   6685: bipush #11
    //   6687: ldc 67108866
    //   6689: iastore
    //   6690: dup
    //   6691: bipush #12
    //   6693: iconst_2
    //   6694: iastore
    //   6695: dup
    //   6696: bipush #13
    //   6698: ldc 67108864
    //   6700: iastore
    //   6701: dup
    //   6702: bipush #14
    //   6704: ldc 69206018
    //   6706: iastore
    //   6707: dup
    //   6708: bipush #15
    //   6710: sipush #2050
    //   6713: iastore
    //   6714: dup
    //   6715: bipush #16
    //   6717: ldc 67110912
    //   6719: iastore
    //   6720: dup
    //   6721: bipush #17
    //   6723: ldc 2099202
    //   6725: iastore
    //   6726: dup
    //   6727: bipush #18
    //   6729: ldc 2097154
    //   6731: iastore
    //   6732: dup
    //   6733: bipush #19
    //   6735: ldc 67110912
    //   6737: iastore
    //   6738: dup
    //   6739: bipush #20
    //   6741: ldc 67108866
    //   6743: iastore
    //   6744: dup
    //   6745: bipush #21
    //   6747: ldc 69206016
    //   6749: iastore
    //   6750: dup
    //   6751: bipush #22
    //   6753: ldc 69208064
    //   6755: iastore
    //   6756: dup
    //   6757: bipush #23
    //   6759: ldc 2097154
    //   6761: iastore
    //   6762: dup
    //   6763: bipush #24
    //   6765: ldc 69206016
    //   6767: iastore
    //   6768: dup
    //   6769: bipush #25
    //   6771: sipush #2048
    //   6774: iastore
    //   6775: dup
    //   6776: bipush #26
    //   6778: sipush #2050
    //   6781: iastore
    //   6782: dup
    //   6783: bipush #27
    //   6785: ldc 69208066
    //   6787: iastore
    //   6788: dup
    //   6789: bipush #28
    //   6791: ldc 2099200
    //   6793: iastore
    //   6794: dup
    //   6795: bipush #29
    //   6797: iconst_2
    //   6798: iastore
    //   6799: dup
    //   6800: bipush #30
    //   6802: ldc 67108864
    //   6804: iastore
    //   6805: dup
    //   6806: bipush #31
    //   6808: ldc 2099200
    //   6810: iastore
    //   6811: dup
    //   6812: bipush #32
    //   6814: ldc 67108864
    //   6816: iastore
    //   6817: dup
    //   6818: bipush #33
    //   6820: ldc 2099200
    //   6822: iastore
    //   6823: dup
    //   6824: bipush #34
    //   6826: ldc 2097152
    //   6828: iastore
    //   6829: dup
    //   6830: bipush #35
    //   6832: ldc 67110914
    //   6834: iastore
    //   6835: dup
    //   6836: bipush #36
    //   6838: ldc 67110914
    //   6840: iastore
    //   6841: dup
    //   6842: bipush #37
    //   6844: ldc 69206018
    //   6846: iastore
    //   6847: dup
    //   6848: bipush #38
    //   6850: ldc 69206018
    //   6852: iastore
    //   6853: dup
    //   6854: bipush #39
    //   6856: iconst_2
    //   6857: iastore
    //   6858: dup
    //   6859: bipush #40
    //   6861: ldc 2097154
    //   6863: iastore
    //   6864: dup
    //   6865: bipush #41
    //   6867: ldc 67108864
    //   6869: iastore
    //   6870: dup
    //   6871: bipush #42
    //   6873: ldc 67110912
    //   6875: iastore
    //   6876: dup
    //   6877: bipush #43
    //   6879: ldc 2097152
    //   6881: iastore
    //   6882: dup
    //   6883: bipush #44
    //   6885: ldc 69208064
    //   6887: iastore
    //   6888: dup
    //   6889: bipush #45
    //   6891: sipush #2050
    //   6894: iastore
    //   6895: dup
    //   6896: bipush #46
    //   6898: ldc 2099202
    //   6900: iastore
    //   6901: dup
    //   6902: bipush #47
    //   6904: ldc 69208064
    //   6906: iastore
    //   6907: dup
    //   6908: bipush #48
    //   6910: sipush #2050
    //   6913: iastore
    //   6914: dup
    //   6915: bipush #49
    //   6917: ldc 67108866
    //   6919: iastore
    //   6920: dup
    //   6921: bipush #50
    //   6923: ldc 69208066
    //   6925: iastore
    //   6926: dup
    //   6927: bipush #51
    //   6929: ldc 69206016
    //   6931: iastore
    //   6932: dup
    //   6933: bipush #52
    //   6935: ldc 2099200
    //   6937: iastore
    //   6938: dup
    //   6939: bipush #53
    //   6941: iconst_0
    //   6942: iastore
    //   6943: dup
    //   6944: bipush #54
    //   6946: iconst_2
    //   6947: iastore
    //   6948: dup
    //   6949: bipush #55
    //   6951: ldc 69208066
    //   6953: iastore
    //   6954: dup
    //   6955: bipush #56
    //   6957: iconst_0
    //   6958: iastore
    //   6959: dup
    //   6960: bipush #57
    //   6962: ldc 2099202
    //   6964: iastore
    //   6965: dup
    //   6966: bipush #58
    //   6968: ldc 69206016
    //   6970: iastore
    //   6971: dup
    //   6972: bipush #59
    //   6974: sipush #2048
    //   6977: iastore
    //   6978: dup
    //   6979: bipush #60
    //   6981: ldc 67108866
    //   6983: iastore
    //   6984: dup
    //   6985: bipush #61
    //   6987: ldc 67110912
    //   6989: iastore
    //   6990: dup
    //   6991: bipush #62
    //   6993: sipush #2048
    //   6996: iastore
    //   6997: dup
    //   6998: bipush #63
    //   7000: ldc 2097154
    //   7002: iastore
    //   7003: astore #12
    //   7005: bipush #64
    //   7007: newarray int
    //   7009: dup
    //   7010: iconst_0
    //   7011: ldc 268439616
    //   7013: iastore
    //   7014: dup
    //   7015: iconst_1
    //   7016: sipush #4096
    //   7019: iastore
    //   7020: dup
    //   7021: iconst_2
    //   7022: ldc 262144
    //   7024: iastore
    //   7025: dup
    //   7026: iconst_3
    //   7027: ldc 268701760
    //   7029: iastore
    //   7030: dup
    //   7031: iconst_4
    //   7032: ldc 268435456
    //   7034: iastore
    //   7035: dup
    //   7036: iconst_5
    //   7037: ldc 268439616
    //   7039: iastore
    //   7040: dup
    //   7041: bipush #6
    //   7043: bipush #64
    //   7045: iastore
    //   7046: dup
    //   7047: bipush #7
    //   7049: ldc 268435456
    //   7051: iastore
    //   7052: dup
    //   7053: bipush #8
    //   7055: ldc 262208
    //   7057: iastore
    //   7058: dup
    //   7059: bipush #9
    //   7061: ldc 268697600
    //   7063: iastore
    //   7064: dup
    //   7065: bipush #10
    //   7067: ldc 268701760
    //   7069: iastore
    //   7070: dup
    //   7071: bipush #11
    //   7073: ldc 266240
    //   7075: iastore
    //   7076: dup
    //   7077: bipush #12
    //   7079: ldc 268701696
    //   7081: iastore
    //   7082: dup
    //   7083: bipush #13
    //   7085: ldc 266304
    //   7087: iastore
    //   7088: dup
    //   7089: bipush #14
    //   7091: sipush #4096
    //   7094: iastore
    //   7095: dup
    //   7096: bipush #15
    //   7098: bipush #64
    //   7100: iastore
    //   7101: dup
    //   7102: bipush #16
    //   7104: ldc 268697600
    //   7106: iastore
    //   7107: dup
    //   7108: bipush #17
    //   7110: ldc 268435520
    //   7112: iastore
    //   7113: dup
    //   7114: bipush #18
    //   7116: ldc 268439552
    //   7118: iastore
    //   7119: dup
    //   7120: bipush #19
    //   7122: sipush #4160
    //   7125: iastore
    //   7126: dup
    //   7127: bipush #20
    //   7129: ldc 266240
    //   7131: iastore
    //   7132: dup
    //   7133: bipush #21
    //   7135: ldc 262208
    //   7137: iastore
    //   7138: dup
    //   7139: bipush #22
    //   7141: ldc 268697664
    //   7143: iastore
    //   7144: dup
    //   7145: bipush #23
    //   7147: ldc 268701696
    //   7149: iastore
    //   7150: dup
    //   7151: bipush #24
    //   7153: sipush #4160
    //   7156: iastore
    //   7157: dup
    //   7158: bipush #25
    //   7160: iconst_0
    //   7161: iastore
    //   7162: dup
    //   7163: bipush #26
    //   7165: iconst_0
    //   7166: iastore
    //   7167: dup
    //   7168: bipush #27
    //   7170: ldc 268697664
    //   7172: iastore
    //   7173: dup
    //   7174: bipush #28
    //   7176: ldc 268435520
    //   7178: iastore
    //   7179: dup
    //   7180: bipush #29
    //   7182: ldc 268439552
    //   7184: iastore
    //   7185: dup
    //   7186: bipush #30
    //   7188: ldc 266304
    //   7190: iastore
    //   7191: dup
    //   7192: bipush #31
    //   7194: ldc 262144
    //   7196: iastore
    //   7197: dup
    //   7198: bipush #32
    //   7200: ldc 266304
    //   7202: iastore
    //   7203: dup
    //   7204: bipush #33
    //   7206: ldc 262144
    //   7208: iastore
    //   7209: dup
    //   7210: bipush #34
    //   7212: ldc 268701696
    //   7214: iastore
    //   7215: dup
    //   7216: bipush #35
    //   7218: sipush #4096
    //   7221: iastore
    //   7222: dup
    //   7223: bipush #36
    //   7225: bipush #64
    //   7227: iastore
    //   7228: dup
    //   7229: bipush #37
    //   7231: ldc 268697664
    //   7233: iastore
    //   7234: dup
    //   7235: bipush #38
    //   7237: sipush #4096
    //   7240: iastore
    //   7241: dup
    //   7242: bipush #39
    //   7244: ldc 266304
    //   7246: iastore
    //   7247: dup
    //   7248: bipush #40
    //   7250: ldc 268439552
    //   7252: iastore
    //   7253: dup
    //   7254: bipush #41
    //   7256: bipush #64
    //   7258: iastore
    //   7259: dup
    //   7260: bipush #42
    //   7262: ldc 268435520
    //   7264: iastore
    //   7265: dup
    //   7266: bipush #43
    //   7268: ldc 268697600
    //   7270: iastore
    //   7271: dup
    //   7272: bipush #44
    //   7274: ldc 268697664
    //   7276: iastore
    //   7277: dup
    //   7278: bipush #45
    //   7280: ldc 268435456
    //   7282: iastore
    //   7283: dup
    //   7284: bipush #46
    //   7286: ldc 262144
    //   7288: iastore
    //   7289: dup
    //   7290: bipush #47
    //   7292: ldc 268439616
    //   7294: iastore
    //   7295: dup
    //   7296: bipush #48
    //   7298: iconst_0
    //   7299: iastore
    //   7300: dup
    //   7301: bipush #49
    //   7303: ldc 268701760
    //   7305: iastore
    //   7306: dup
    //   7307: bipush #50
    //   7309: ldc 262208
    //   7311: iastore
    //   7312: dup
    //   7313: bipush #51
    //   7315: ldc 268435520
    //   7317: iastore
    //   7318: dup
    //   7319: bipush #52
    //   7321: ldc 268697600
    //   7323: iastore
    //   7324: dup
    //   7325: bipush #53
    //   7327: ldc 268439552
    //   7329: iastore
    //   7330: dup
    //   7331: bipush #54
    //   7333: ldc 268439616
    //   7335: iastore
    //   7336: dup
    //   7337: bipush #55
    //   7339: iconst_0
    //   7340: iastore
    //   7341: dup
    //   7342: bipush #56
    //   7344: ldc 268701760
    //   7346: iastore
    //   7347: dup
    //   7348: bipush #57
    //   7350: ldc 266240
    //   7352: iastore
    //   7353: dup
    //   7354: bipush #58
    //   7356: ldc 266240
    //   7358: iastore
    //   7359: dup
    //   7360: bipush #59
    //   7362: sipush #4160
    //   7365: iastore
    //   7366: dup
    //   7367: bipush #60
    //   7369: sipush #4160
    //   7372: iastore
    //   7373: dup
    //   7374: bipush #61
    //   7376: ldc 262208
    //   7378: iastore
    //   7379: dup
    //   7380: bipush #62
    //   7382: ldc 268435456
    //   7384: iastore
    //   7385: dup
    //   7386: bipush #63
    //   7388: ldc 268701696
    //   7390: iastore
    //   7391: astore #13
    //   7393: aload_3
    //   7394: arraylength
    //   7395: istore #14
    //   7397: iload #14
    //   7399: bipush #8
    //   7401: irem
    //   7402: ifeq -> 7426
    //   7405: new java/lang/Exception
    //   7408: dup
    //   7409: sipush #7217
    //   7412: sipush #26517
    //   7415: invokestatic a : (II)Ljava/lang/String;
    //   7418: invokespecial <init> : (Ljava/lang/String;)V
    //   7421: athrow
    //   7422: invokestatic a : (Ljava/lang/Throwable;)Ljava/lang/Throwable;
    //   7425: athrow
    //   7426: iconst_2
    //   7427: newarray int
    //   7429: astore #15
    //   7431: iload #14
    //   7433: newarray byte
    //   7435: astore #16
    //   7437: iload #14
    //   7439: bipush #8
    //   7441: idiv
    //   7442: istore #17
    //   7444: iconst_0
    //   7445: istore #18
    //   7447: iload #18
    //   7449: iload #17
    //   7451: if_icmpge -> 8365
    //   7454: iload #18
    //   7456: bipush #8
    //   7458: imul
    //   7459: istore #19
    //   7461: iconst_0
    //   7462: istore #20
    //   7464: iload #20
    //   7466: iconst_2
    //   7467: if_icmpge -> 7552
    //   7470: aload #15
    //   7472: iload #20
    //   7474: aload_3
    //   7475: iload #19
    //   7477: iload #20
    //   7479: iconst_4
    //   7480: imul
    //   7481: iadd
    //   7482: baload
    //   7483: sipush #255
    //   7486: iand
    //   7487: bipush #24
    //   7489: ishl
    //   7490: aload_3
    //   7491: iload #19
    //   7493: iload #20
    //   7495: iconst_4
    //   7496: imul
    //   7497: iadd
    //   7498: iconst_1
    //   7499: iadd
    //   7500: baload
    //   7501: sipush #255
    //   7504: iand
    //   7505: bipush #16
    //   7507: ishl
    //   7508: ior
    //   7509: aload_3
    //   7510: iload #19
    //   7512: iload #20
    //   7514: iconst_4
    //   7515: imul
    //   7516: iadd
    //   7517: iconst_2
    //   7518: iadd
    //   7519: baload
    //   7520: sipush #255
    //   7523: iand
    //   7524: bipush #8
    //   7526: ishl
    //   7527: ior
    //   7528: aload_3
    //   7529: iload #19
    //   7531: iload #20
    //   7533: iconst_4
    //   7534: imul
    //   7535: iadd
    //   7536: iconst_3
    //   7537: iadd
    //   7538: baload
    //   7539: sipush #255
    //   7542: iand
    //   7543: ior
    //   7544: iastore
    //   7545: iinc #20, 1
    //   7548: iload_2
    //   7549: ifeq -> 7464
    //   7552: iconst_0
    //   7553: istore #25
    //   7555: aload #15
    //   7557: iconst_0
    //   7558: iaload
    //   7559: istore #23
    //   7561: aload #15
    //   7563: iconst_1
    //   7564: iaload
    //   7565: istore #22
    //   7567: iload #23
    //   7569: iconst_4
    //   7570: iushr
    //   7571: iload #22
    //   7573: ixor
    //   7574: ldc 252645135
    //   7576: iand
    //   7577: istore #21
    //   7579: iload #22
    //   7581: iload #21
    //   7583: ixor
    //   7584: istore #22
    //   7586: iload #23
    //   7588: iload #21
    //   7590: iconst_4
    //   7591: ishl
    //   7592: ixor
    //   7593: istore #23
    //   7595: iload #23
    //   7597: bipush #16
    //   7599: iushr
    //   7600: iload #22
    //   7602: ixor
    //   7603: ldc 65535
    //   7605: iand
    //   7606: istore #21
    //   7608: iload #22
    //   7610: iload #21
    //   7612: ixor
    //   7613: istore #22
    //   7615: iload #23
    //   7617: iload #21
    //   7619: bipush #16
    //   7621: ishl
    //   7622: ixor
    //   7623: istore #23
    //   7625: iload #22
    //   7627: iconst_2
    //   7628: iushr
    //   7629: iload #23
    //   7631: ixor
    //   7632: ldc 858993459
    //   7634: iand
    //   7635: istore #21
    //   7637: iload #23
    //   7639: iload #21
    //   7641: ixor
    //   7642: istore #23
    //   7644: iload #22
    //   7646: iload #21
    //   7648: iconst_2
    //   7649: ishl
    //   7650: ixor
    //   7651: istore #22
    //   7653: iload #22
    //   7655: bipush #8
    //   7657: iushr
    //   7658: iload #23
    //   7660: ixor
    //   7661: ldc 16711935
    //   7663: iand
    //   7664: istore #21
    //   7666: iload #23
    //   7668: iload #21
    //   7670: ixor
    //   7671: istore #23
    //   7673: iload #22
    //   7675: iload #21
    //   7677: bipush #8
    //   7679: ishl
    //   7680: ixor
    //   7681: istore #22
    //   7683: iload #22
    //   7685: iconst_1
    //   7686: ishl
    //   7687: iload #22
    //   7689: bipush #31
    //   7691: iushr
    //   7692: iconst_1
    //   7693: iand
    //   7694: ior
    //   7695: istore #22
    //   7697: iload #23
    //   7699: iload #22
    //   7701: ixor
    //   7702: ldc -1431655766
    //   7704: iand
    //   7705: istore #21
    //   7707: iload #23
    //   7709: iload #21
    //   7711: ixor
    //   7712: istore #23
    //   7714: iload #22
    //   7716: iload #21
    //   7718: ixor
    //   7719: istore #22
    //   7721: iload #23
    //   7723: iconst_1
    //   7724: ishl
    //   7725: iload #23
    //   7727: bipush #31
    //   7729: iushr
    //   7730: iconst_1
    //   7731: iand
    //   7732: ior
    //   7733: istore #23
    //   7735: iconst_0
    //   7736: istore #24
    //   7738: iload #24
    //   7740: bipush #8
    //   7742: if_icmpge -> 8080
    //   7745: iload #22
    //   7747: bipush #28
    //   7749: ishl
    //   7750: iload #22
    //   7752: iconst_4
    //   7753: iushr
    //   7754: ior
    //   7755: istore #21
    //   7757: iload #21
    //   7759: aload #5
    //   7761: iload #25
    //   7763: iinc #25, 1
    //   7766: iaload
    //   7767: ixor
    //   7768: istore #21
    //   7770: aload #12
    //   7772: iload #21
    //   7774: bipush #63
    //   7776: iand
    //   7777: iaload
    //   7778: istore #20
    //   7780: iload #20
    //   7782: aload #10
    //   7784: iload #21
    //   7786: bipush #8
    //   7788: iushr
    //   7789: bipush #63
    //   7791: iand
    //   7792: iaload
    //   7793: ior
    //   7794: istore #20
    //   7796: iload #20
    //   7798: aload #8
    //   7800: iload #21
    //   7802: bipush #16
    //   7804: iushr
    //   7805: bipush #63
    //   7807: iand
    //   7808: iaload
    //   7809: ior
    //   7810: istore #20
    //   7812: iload #20
    //   7814: aload #6
    //   7816: iload #21
    //   7818: bipush #24
    //   7820: iushr
    //   7821: bipush #63
    //   7823: iand
    //   7824: iaload
    //   7825: ior
    //   7826: istore #20
    //   7828: iload #22
    //   7830: aload #5
    //   7832: iload #25
    //   7834: iinc #25, 1
    //   7837: iaload
    //   7838: ixor
    //   7839: istore #21
    //   7841: iload #20
    //   7843: aload #13
    //   7845: iload #21
    //   7847: bipush #63
    //   7849: iand
    //   7850: iaload
    //   7851: ior
    //   7852: istore #20
    //   7854: iload #20
    //   7856: aload #11
    //   7858: iload #21
    //   7860: bipush #8
    //   7862: iushr
    //   7863: bipush #63
    //   7865: iand
    //   7866: iaload
    //   7867: ior
    //   7868: istore #20
    //   7870: iload #20
    //   7872: aload #9
    //   7874: iload #21
    //   7876: bipush #16
    //   7878: iushr
    //   7879: bipush #63
    //   7881: iand
    //   7882: iaload
    //   7883: ior
    //   7884: istore #20
    //   7886: iload #20
    //   7888: aload #7
    //   7890: iload #21
    //   7892: bipush #24
    //   7894: iushr
    //   7895: bipush #63
    //   7897: iand
    //   7898: iaload
    //   7899: ior
    //   7900: istore #20
    //   7902: iload #23
    //   7904: iload #20
    //   7906: ixor
    //   7907: istore #23
    //   7909: iload #23
    //   7911: bipush #28
    //   7913: ishl
    //   7914: iload #23
    //   7916: iconst_4
    //   7917: iushr
    //   7918: ior
    //   7919: istore #21
    //   7921: iload #21
    //   7923: aload #5
    //   7925: iload #25
    //   7927: iinc #25, 1
    //   7930: iaload
    //   7931: ixor
    //   7932: istore #21
    //   7934: aload #12
    //   7936: iload #21
    //   7938: bipush #63
    //   7940: iand
    //   7941: iaload
    //   7942: istore #20
    //   7944: iload #20
    //   7946: aload #10
    //   7948: iload #21
    //   7950: bipush #8
    //   7952: iushr
    //   7953: bipush #63
    //   7955: iand
    //   7956: iaload
    //   7957: ior
    //   7958: istore #20
    //   7960: iload #20
    //   7962: aload #8
    //   7964: iload #21
    //   7966: bipush #16
    //   7968: iushr
    //   7969: bipush #63
    //   7971: iand
    //   7972: iaload
    //   7973: ior
    //   7974: istore #20
    //   7976: iload #20
    //   7978: aload #6
    //   7980: iload #21
    //   7982: bipush #24
    //   7984: iushr
    //   7985: bipush #63
    //   7987: iand
    //   7988: iaload
    //   7989: ior
    //   7990: istore #20
    //   7992: iload #23
    //   7994: aload #5
    //   7996: iload #25
    //   7998: iinc #25, 1
    //   8001: iaload
    //   8002: ixor
    //   8003: istore #21
    //   8005: iload #20
    //   8007: aload #13
    //   8009: iload #21
    //   8011: bipush #63
    //   8013: iand
    //   8014: iaload
    //   8015: ior
    //   8016: istore #20
    //   8018: iload #20
    //   8020: aload #11
    //   8022: iload #21
    //   8024: bipush #8
    //   8026: iushr
    //   8027: bipush #63
    //   8029: iand
    //   8030: iaload
    //   8031: ior
    //   8032: istore #20
    //   8034: iload #20
    //   8036: aload #9
    //   8038: iload #21
    //   8040: bipush #16
    //   8042: iushr
    //   8043: bipush #63
    //   8045: iand
    //   8046: iaload
    //   8047: ior
    //   8048: istore #20
    //   8050: iload #20
    //   8052: aload #7
    //   8054: iload #21
    //   8056: bipush #24
    //   8058: iushr
    //   8059: bipush #63
    //   8061: iand
    //   8062: iaload
    //   8063: ior
    //   8064: istore #20
    //   8066: iload #22
    //   8068: iload #20
    //   8070: ixor
    //   8071: istore #22
    //   8073: iinc #24, 1
    //   8076: iload_2
    //   8077: ifeq -> 7738
    //   8080: iload #22
    //   8082: bipush #31
    //   8084: ishl
    //   8085: iload #22
    //   8087: iconst_1
    //   8088: iushr
    //   8089: ior
    //   8090: istore #22
    //   8092: iload #23
    //   8094: iload #22
    //   8096: ixor
    //   8097: ldc -1431655766
    //   8099: iand
    //   8100: istore #21
    //   8102: iload #23
    //   8104: iload #21
    //   8106: ixor
    //   8107: istore #23
    //   8109: iload #22
    //   8111: iload #21
    //   8113: ixor
    //   8114: istore #22
    //   8116: iload #23
    //   8118: bipush #31
    //   8120: ishl
    //   8121: iload #23
    //   8123: iconst_1
    //   8124: iushr
    //   8125: ior
    //   8126: istore #23
    //   8128: iload #23
    //   8130: bipush #8
    //   8132: iushr
    //   8133: iload #22
    //   8135: ixor
    //   8136: ldc 16711935
    //   8138: iand
    //   8139: istore #21
    //   8141: iload #22
    //   8143: iload #21
    //   8145: ixor
    //   8146: istore #22
    //   8148: iload #23
    //   8150: iload #21
    //   8152: bipush #8
    //   8154: ishl
    //   8155: ixor
    //   8156: istore #23
    //   8158: iload #23
    //   8160: iconst_2
    //   8161: iushr
    //   8162: iload #22
    //   8164: ixor
    //   8165: ldc 858993459
    //   8167: iand
    //   8168: istore #21
    //   8170: iload #22
    //   8172: iload #21
    //   8174: ixor
    //   8175: istore #22
    //   8177: iload #23
    //   8179: iload #21
    //   8181: iconst_2
    //   8182: ishl
    //   8183: ixor
    //   8184: istore #23
    //   8186: iload #22
    //   8188: bipush #16
    //   8190: iushr
    //   8191: iload #23
    //   8193: ixor
    //   8194: ldc 65535
    //   8196: iand
    //   8197: istore #21
    //   8199: iload #23
    //   8201: iload #21
    //   8203: ixor
    //   8204: istore #23
    //   8206: iload #22
    //   8208: iload #21
    //   8210: bipush #16
    //   8212: ishl
    //   8213: ixor
    //   8214: istore #22
    //   8216: iload #22
    //   8218: iconst_4
    //   8219: iushr
    //   8220: iload #23
    //   8222: ixor
    //   8223: ldc 252645135
    //   8225: iand
    //   8226: istore #21
    //   8228: iload #23
    //   8230: iload #21
    //   8232: ixor
    //   8233: istore #23
    //   8235: iload #22
    //   8237: iload #21
    //   8239: iconst_4
    //   8240: ishl
    //   8241: ixor
    //   8242: istore #22
    //   8244: aload #15
    //   8246: iconst_0
    //   8247: iload #22
    //   8249: iastore
    //   8250: aload #15
    //   8252: iconst_1
    //   8253: iload #23
    //   8255: iastore
    //   8256: iload #18
    //   8258: bipush #8
    //   8260: imul
    //   8261: istore #26
    //   8263: iconst_0
    //   8264: istore #27
    //   8266: iload #27
    //   8268: iconst_2
    //   8269: if_icmpge -> 8358
    //   8272: aload #16
    //   8274: iload #26
    //   8276: iload #27
    //   8278: iconst_4
    //   8279: imul
    //   8280: iadd
    //   8281: aload #15
    //   8283: iload #27
    //   8285: iaload
    //   8286: bipush #24
    //   8288: iushr
    //   8289: i2b
    //   8290: bastore
    //   8291: aload #16
    //   8293: iload #26
    //   8295: iload #27
    //   8297: iconst_4
    //   8298: imul
    //   8299: iadd
    //   8300: iconst_1
    //   8301: iadd
    //   8302: aload #15
    //   8304: iload #27
    //   8306: iaload
    //   8307: bipush #16
    //   8309: iushr
    //   8310: i2b
    //   8311: bastore
    //   8312: aload #16
    //   8314: iload #26
    //   8316: iload #27
    //   8318: iconst_4
    //   8319: imul
    //   8320: iadd
    //   8321: iconst_2
    //   8322: iadd
    //   8323: aload #15
    //   8325: iload #27
    //   8327: iaload
    //   8328: bipush #8
    //   8330: iushr
    //   8331: i2b
    //   8332: bastore
    //   8333: aload #16
    //   8335: iload #26
    //   8337: iload #27
    //   8339: iconst_4
    //   8340: imul
    //   8341: iadd
    //   8342: iconst_3
    //   8343: iadd
    //   8344: aload #15
    //   8346: iload #27
    //   8348: iaload
    //   8349: i2b
    //   8350: bastore
    //   8351: iinc #27, 1
    //   8354: iload_2
    //   8355: ifeq -> 8266
    //   8358: iinc #18, 1
    //   8361: iload_2
    //   8362: ifeq -> 7447
    //   8365: aload #16
    //   8367: aload #16
    //   8369: arraylength
    //   8370: iconst_1
    //   8371: isub
    //   8372: baload
    //   8373: istore #18
    //   8375: aload #16
    //   8377: arraylength
    //   8378: iload #18
    //   8380: isub
    //   8381: newarray byte
    //   8383: astore #4
    //   8385: aload #16
    //   8387: arraylength
    //   8388: aload #4
    //   8390: arraylength
    //   8391: if_icmpge -> 8415
    //   8394: new java/lang/Exception
    //   8397: dup
    //   8398: sipush #7229
    //   8401: sipush #-13391
    //   8404: invokestatic a : (II)Ljava/lang/String;
    //   8407: invokespecial <init> : (Ljava/lang/String;)V
    //   8410: athrow
    //   8411: invokestatic a : (Ljava/lang/Throwable;)Ljava/lang/Throwable;
    //   8414: athrow
    //   8415: iconst_0
    //   8416: istore #19
    //   8418: iload #19
    //   8420: aload #4
    //   8422: arraylength
    //   8423: if_icmpge -> 8443
    //   8426: aload #4
    //   8428: iload #19
    //   8430: aload #16
    //   8432: iload #19
    //   8434: baload
    //   8435: bastore
    //   8436: iinc #19, 1
    //   8439: iload_2
    //   8440: ifeq -> 8418
    //   8443: new java/math/BigInteger
    //   8446: dup
    //   8447: aload #4
    //   8449: invokespecial <init> : ([B)V
    //   8452: invokevirtual abs : ()Ljava/math/BigInteger;
    //   8455: putstatic burp/Zb8y.ZI : Ljava/lang/Object;
    //   8458: sipush #7221
    //   8461: sipush #-2567
    //   8464: invokestatic a : (II)Ljava/lang/String;
    //   8467: iconst_1
    //   8468: ldc burp/Zli5
    //   8470: invokevirtual getClassLoader : ()Ljava/lang/ClassLoader;
    //   8473: invokestatic forName : (Ljava/lang/String;ZLjava/lang/ClassLoader;)Ljava/lang/Class;
    //   8476: invokevirtual getDeclaredFields : ()[Ljava/lang/reflect/Field;
    //   8479: astore_3
    //   8480: aload_3
    //   8481: arraylength
    //   8482: istore #4
    //   8484: iconst_0
    //   8485: istore #5
    //   8487: iload #5
    //   8489: iload #4
    //   8491: if_icmpge -> 8628
    //   8494: aload_3
    //   8495: iload #5
    //   8497: aaload
    //   8498: astore #6
    //   8500: aload #6
    //   8502: invokevirtual getModifiers : ()I
    //   8505: invokestatic isStatic : (I)Z
    //   8508: ifne -> 8518
    //   8511: goto -> 8621
    //   8514: invokestatic a : (Ljava/lang/Throwable;)Ljava/lang/Throwable;
    //   8517: athrow
    //   8518: aload #6
    //   8520: invokevirtual getType : ()Ljava/lang/Class;
    //   8523: astore #7
    //   8525: aload #7
    //   8527: ifnull -> 8608
    //   8530: aload #7
    //   8532: invokevirtual isPrimitive : ()Z
    //   8535: ifne -> 8608
    //   8538: goto -> 8545
    //   8541: invokestatic a : (Ljava/lang/Throwable;)Ljava/lang/Throwable;
    //   8544: athrow
    //   8545: aload #7
    //   8547: invokevirtual getPackage : ()Ljava/lang/Package;
    //   8550: ifnull -> 8608
    //   8553: goto -> 8560
    //   8556: invokestatic a : (Ljava/lang/Throwable;)Ljava/lang/Throwable;
    //   8559: athrow
    //   8560: aload #7
    //   8562: invokevirtual getPackage : ()Ljava/lang/Package;
    //   8565: invokevirtual getName : ()Ljava/lang/String;
    //   8568: ifnull -> 8608
    //   8571: goto -> 8578
    //   8574: invokestatic a : (Ljava/lang/Throwable;)Ljava/lang/Throwable;
    //   8577: athrow
    //   8578: aload #7
    //   8580: invokevirtual getPackage : ()Ljava/lang/Package;
    //   8583: invokevirtual getName : ()Ljava/lang/String;
    //   8586: sipush #7223
    //   8589: sipush #6060
    //   8592: invokestatic a : (II)Ljava/lang/String;
    //   8595: invokevirtual startsWith : (Ljava/lang/String;)Z
    //   8598: ifne -> 8608
    //   8601: goto -> 8608
    //   8604: invokestatic a : (Ljava/lang/Throwable;)Ljava/lang/Throwable;
    //   8607: athrow
    //   8608: aload #6
    //   8610: iconst_1
    //   8611: invokevirtual setAccessible : (Z)V
    //   8614: aload #6
    //   8616: aconst_null
    //   8617: invokevirtual get : (Ljava/lang/Object;)Ljava/lang/Object;
    //   8620: pop
    //   8621: iinc #5, 1
    //   8624: iload_2
    //   8625: ifeq -> 8487
    //   8628: sipush #7231
    //   8631: sipush #21365
    //   8634: invokestatic a : (II)Ljava/lang/String;
    //   8637: invokestatic forName : (Ljava/lang/String;)Ljava/lang/Class;
    //   8640: invokevirtual getDeclaredMethods : ()[Ljava/lang/reflect/Method;
    //   8643: astore_3
    //   8644: aload_3
    //   8645: arraylength
    //   8646: istore #4
    //   8648: iconst_0
    //   8649: istore #5
    //   8651: iload #5
    //   8653: iload #4
    //   8655: if_icmpge -> 8787
    //   8658: aload_3
    //   8659: iload #5
    //   8661: aaload
    //   8662: astore #6
    //   8664: aload #6
    //   8666: invokevirtual getParameterTypes : ()[Ljava/lang/Class;
    //   8669: pop
    //   8670: aload #6
    //   8672: invokevirtual getModifiers : ()I
    //   8675: invokestatic isStatic : (I)Z
    //   8678: ifeq -> 8773
    //   8681: aload #6
    //   8683: invokevirtual getParameterTypes : ()[Ljava/lang/Class;
    //   8686: arraylength
    //   8687: iconst_2
    //   8688: if_icmpne -> 8773
    //   8691: goto -> 8698
    //   8694: invokestatic a : (Ljava/lang/Throwable;)Ljava/lang/Throwable;
    //   8697: athrow
    //   8698: aload #6
    //   8700: invokevirtual getReturnType : ()Ljava/lang/Class;
    //   8703: getstatic java/lang/Void.TYPE : Ljava/lang/Class;
    //   8706: invokevirtual equals : (Ljava/lang/Object;)Z
    //   8709: ifeq -> 8773
    //   8712: goto -> 8719
    //   8715: invokestatic a : (Ljava/lang/Throwable;)Ljava/lang/Throwable;
    //   8718: athrow
    //   8719: aload #6
    //   8721: iconst_1
    //   8722: invokevirtual setAccessible : (Z)V
    //   8725: aload #6
    //   8727: aconst_null
    //   8728: iconst_2
    //   8729: anewarray java/lang/Object
    //   8732: dup
    //   8733: iconst_0
    //   8734: aload_0
    //   8735: aastore
    //   8736: dup
    //   8737: iconst_1
    //   8738: aload_1
    //   8739: ifnonnull -> 8757
    //   8742: goto -> 8749
    //   8745: invokestatic a : (Ljava/lang/Throwable;)Ljava/lang/Throwable;
    //   8748: athrow
    //   8749: aload_1
    //   8750: goto -> 8764
    //   8753: invokestatic a : (Ljava/lang/Throwable;)Ljava/lang/Throwable;
    //   8756: athrow
    //   8757: aload_1
    //   8758: checkcast [B
    //   8761: invokevirtual clone : ()Ljava/lang/Object;
    //   8764: aastore
    //   8765: invokevirtual invoke : (Ljava/lang/Object;[Ljava/lang/Object;)Ljava/lang/Object;
    //   8768: pop
    //   8769: iload_2
    //   8770: ifeq -> 8787
    //   8773: iinc #5, 1
    //   8776: iload_2
    //   8777: ifeq -> 8651
    //   8780: goto -> 8787
    //   8783: invokestatic a : (Ljava/lang/Throwable;)Ljava/lang/Throwable;
    //   8786: athrow
    //   8787: getstatic burp/Zmj8.ZL : Ljava/lang/String;
    //   8790: getstatic burp/Zzgh.ZV : Ljava/lang/Object;
    //   8793: checkcast java/math/BigInteger
    //   8796: invokevirtual intValue : ()I
    //   8799: bipush #32
    //   8801: irem
    //   8802: invokestatic abs : (I)I
    //   8805: invokevirtual charAt : (I)C
    //   8808: getstatic burp/Zt98.Zh : Ljava/lang/String;
    //   8811: getstatic burp/Zlhq.Zw : Ljava/lang/Object;
    //   8814: checkcast java/math/BigInteger
    //   8817: invokevirtual intValue : ()I
    //   8820: bipush #32
    //   8822: irem
    //   8823: invokestatic abs : (I)I
    //   8826: invokevirtual charAt : (I)C
    //   8829: if_icmpgt -> 8944
    //   8832: getstatic burp/Zx6d.ZP : Ljava/lang/String;
    //   8835: getstatic burp/Zs_3.ZZ : Ljava/lang/Object;
    //   8838: checkcast java/math/BigInteger
    //   8841: invokevirtual intValue : ()I
    //   8844: bipush #32
    //   8846: irem
    //   8847: invokestatic abs : (I)I
    //   8850: invokevirtual charAt : (I)C
    //   8853: getstatic burp/Zxjv.ZF : Ljava/lang/String;
    //   8856: getstatic burp/Zg6f.Zl : Ljava/lang/Object;
    //   8859: checkcast java/math/BigInteger
    //   8862: invokevirtual intValue : ()I
    //   8865: bipush #32
    //   8867: irem
    //   8868: invokestatic abs : (I)I
    //   8871: invokevirtual charAt : (I)C
    //   8874: if_icmpgt -> 8944
    //   8877: goto -> 8884
    //   8880: invokestatic a : (Ljava/lang/Throwable;)Ljava/lang/Throwable;
    //   8883: athrow
    //   8884: getstatic burp/Zb4a.Zi : Ljava/lang/String;
    //   8887: getstatic burp/Ze_t.Za : Ljava/lang/Object;
    //   8890: checkcast java/math/BigInteger
    //   8893: invokevirtual intValue : ()I
    //   8896: bipush #32
    //   8898: irem
    //   8899: invokestatic abs : (I)I
    //   8902: invokevirtual charAt : (I)C
    //   8905: getstatic burp/Ztex.Zx : Ljava/lang/String;
    //   8908: getstatic burp/Zgzv.Zb : Ljava/lang/Object;
    //   8911: checkcast java/math/BigInteger
    //   8914: invokevirtual intValue : ()I
    //   8917: bipush #32
    //   8919: irem
    //   8920: invokestatic abs : (I)I
    //   8923: invokevirtual charAt : (I)C
    //   8926: if_icmpgt -> 8944
    //   8929: goto -> 8936
    //   8932: invokestatic a : (Ljava/lang/Throwable;)Ljava/lang/Throwable;
    //   8935: athrow
    //   8936: iconst_1
    //   8937: goto -> 8945
    //   8940: invokestatic a : (Ljava/lang/Throwable;)Ljava/lang/Throwable;
    //   8943: athrow
    //   8944: iconst_0
    //   8945: ireturn
    //   8946: astore_3
    //   8947: new java/lang/Exception
    //   8950: dup
    //   8951: aload_3
    //   8952: invokevirtual getMessage : ()Ljava/lang/String;
    //   8955: invokespecial <init> : (Ljava/lang/String;)V
    //   8958: athrow
    // Exception table:
    //   from	to	target	type
    //   4	8945	8946	java/lang/Throwable
    //   805	839	842	java/lang/Throwable
    //   934	1012	1015	java/lang/Throwable
    //   941	1155	1158	java/lang/Throwable
    //   1532	1547	1547	java/lang/Throwable
    //   1574	1608	1611	java/lang/Throwable
    //   1618	1630	1633	java/lang/Throwable
    //   1716	1794	1797	java/lang/Throwable
    //   1723	1937	1940	java/lang/Throwable
    //   2337	2415	2418	java/lang/Throwable
    //   2344	2558	2561	java/lang/Throwable
    //   3005	3039	3042	java/lang/Throwable
    //   3046	3058	3061	java/lang/Throwable
    //   3144	3222	3225	java/lang/Throwable
    //   3151	3365	3368	java/lang/Throwable
    //   7397	7422	7422	java/lang/Throwable
    //   8385	8411	8411	java/lang/Throwable
    //   8500	8514	8514	java/lang/Throwable
    //   8525	8538	8541	java/lang/Throwable
    //   8530	8553	8556	java/lang/Throwable
    //   8545	8571	8574	java/lang/Throwable
    //   8560	8601	8604	java/lang/Throwable
    //   8664	8691	8694	java/lang/Throwable
    //   8681	8712	8715	java/lang/Throwable
    //   8698	8742	8745	java/lang/Throwable
    //   8719	8753	8753	java/lang/Throwable
    //   8764	8780	8783	java/lang/Throwable
    //   8787	8877	8880	java/lang/Throwable
    //   8832	8929	8932	java/lang/Throwable
    //   8884	8940	8940	java/lang/Throwable
  }
  
  static {
    // Byte code:
    //   0: bipush #11
    //   2: anewarray java/lang/String
    //   5: astore #5
    //   7: iconst_0
    //   8: istore_3
    //   9: ldc 'C7qD\\tVz]<g|x*j\\t`p_E\\r,h5I\MephMvva0qG\\n7m?]3L\\r|\\r!hUc0G\k3$\\t'oy2< Y`\\rs#6? sO8FM0/\\f#D|1"!W*BNwgJ[s/v8\%$Ec {A6uiLd6o)PK&@p'
    //   11: dup
    //   12: astore_2
    //   13: invokevirtual length : ()I
    //   16: istore #4
    //   18: bipush #9
    //   20: istore_1
    //   21: iconst_m1
    //   22: istore_0
    //   23: bipush #88
    //   25: iinc #0, 1
    //   28: aload_2
    //   29: iload_0
    //   30: dup
    //   31: iload_1
    //   32: iadd
    //   33: invokevirtual substring : (II)Ljava/lang/String;
    //   36: iconst_m1
    //   37: goto -> 143
    //   40: aload #5
    //   42: swap
    //   43: iload_3
    //   44: iinc #3, 1
    //   47: swap
    //   48: aastore
    //   49: iload_0
    //   50: iload_1
    //   51: iadd
    //   52: dup
    //   53: istore_0
    //   54: iload #4
    //   56: if_icmpge -> 68
    //   59: aload_2
    //   60: iload_0
    //   61: invokevirtual charAt : (I)C
    //   64: istore_1
    //   65: goto -> 23
    //   68: ldc ']Am"P\\t<mT#'
    //   70: dup
    //   71: astore_2
    //   72: invokevirtual length : ()I
    //   75: istore #4
    //   77: bipush #32
    //   79: istore_1
    //   80: iconst_m1
    //   81: istore_0
    //   82: bipush #98
    //   84: iinc #0, 1
    //   87: aload_2
    //   88: iload_0
    //   89: dup
    //   90: iload_1
    //   91: iadd
    //   92: invokevirtual substring : (II)Ljava/lang/String;
    //   95: iconst_0
    //   96: goto -> 143
    //   99: aload #5
    //   101: swap
    //   102: iload_3
    //   103: iinc #3, 1
    //   106: swap
    //   107: aastore
    //   108: iload_0
    //   109: iload_1
    //   110: iadd
    //   111: dup
    //   112: istore_0
    //   113: iload #4
    //   115: if_icmpge -> 127
    //   118: aload_2
    //   119: iload_0
    //   120: invokevirtual charAt : (I)C
    //   123: istore_1
    //   124: goto -> 82
    //   127: aload #5
    //   129: putstatic burp/Ze6d.a : [Ljava/lang/String;
    //   132: bipush #11
    //   134: anewarray java/lang/String
    //   137: putstatic burp/Ze6d.b : [Ljava/lang/String;
    //   140: goto -> 300
    //   143: dup_x2
    //   144: pop
    //   145: invokevirtual toCharArray : ()[C
    //   148: dup_x1
    //   149: arraylength
    //   150: dup_x2
    //   151: pop
    //   152: iconst_0
    //   153: istore #6
    //   155: dup2_x1
    //   156: pop2
    //   157: dup_x2
    //   158: iconst_1
    //   159: if_icmpgt -> 260
    //   162: dup2
    //   163: swap
    //   164: iload #6
    //   166: dup2_x1
    //   167: caload
    //   168: swap
    //   169: iload #6
    //   171: bipush #7
    //   173: irem
    //   174: tableswitch default -> 242, 0 -> 212, 1 -> 217, 2 -> 222, 3 -> 227, 4 -> 232, 5 -> 237
    //   212: bipush #47
    //   214: goto -> 244
    //   217: bipush #98
    //   219: goto -> 244
    //   222: bipush #125
    //   224: goto -> 244
    //   227: bipush #62
    //   229: goto -> 244
    //   232: bipush #121
    //   234: goto -> 244
    //   237: bipush #111
    //   239: goto -> 244
    //   242: bipush #30
    //   244: ixor
    //   245: ixor
    //   246: i2c
    //   247: castore
    //   248: iinc #6, 1
    //   251: dup
    //   252: ifne -> 260
    //   255: dup2
    //   256: dup_x1
    //   257: goto -> 166
    //   260: dup2_x1
    //   261: pop2
    //   262: dup_x2
    //   263: iload #6
    //   265: if_icmpgt -> 162
    //   268: pop
    //   269: new java/lang/String
    //   272: dup_x1
    //   273: swap
    //   274: invokespecial <init> : ([C)V
    //   277: invokevirtual intern : ()Ljava/lang/String;
    //   280: swap
    //   281: pop
    //   282: swap
    //   283: tableswitch default -> 40, 0 -> 99
    //   300: new java/math/BigInteger
    //   303: dup
    //   304: sipush #7218
    //   307: sipush #15314
    //   310: invokestatic a : (II)Ljava/lang/String;
    //   313: invokespecial <init> : (Ljava/lang/String;)V
    //   316: putstatic burp/Ze6d.Zw : Ljava/lang/Object;
    //   319: sipush #7219
    //   322: sipush #11019
    //   325: invokestatic a : (II)Ljava/lang/String;
    //   328: putstatic burp/Ze6d.Zx : Ljava/lang/String;
    //   331: return
  }
  
  private static Throwable a(Throwable paramThrowable) {
    return paramThrowable;
  }
  
  private static String a(int paramInt1, int paramInt2) {
    int i = (paramInt1 ^ 0x1C35) & 0xFFFF;
    if (b[i] == null) {
      char[] arrayOfChar = a[i].toCharArray();
      switch (arrayOfChar[0] & 0xFF) {
        case 0:
        
        case 1:
        
        case 2:
        
        case 3:
        
        case 4:
        
        case 5:
        
        case 6:
        
        case 7:
        
        case 8:
        
        case 9:
        
        case 10:
        
        case 11:
        
        case 12:
        
        case 13:
        
        case 14:
        
        case 15:
        
        case 16:
        
        case 17:
        
        case 18:
        
        case 19:
        
        case 20:
        
        case 21:
        
        case 22:
        
        case 23:
        
        case 24:
        
        case 25:
        
        case 26:
        
        case 27:
        
        case 28:
        
        case 29:
        
        case 30:
        
        case 31:
        
        case 32:
        
        case 33:
        
        case 34:
        
        case 35:
        
        case 36:
        
        case 37:
        
        case 38:
        
        case 39:
        
        case 40:
        
        case 41:
        
        case 42:
        
        case 43:
        
        case 44:
        
        case 45:
        
        case 46:
        
        case 47:
        
        case 48:
        
        case 49:
        
        case 50:
        
        case 51:
        
        case 52:
        
        case 53:
        
        case 54:
        
        case 55:
        
        case 56:
        
        case 57:
        
        case 58:
        
        case 59:
        
        case 60:
        
        case 61:
        
        case 62:
        
        case 63:
        
        case 64:
        
        case 65:
        
        case 66:
        
        case 67:
        
        case 68:
        
        case 69:
        
        case 70:
        
        case 71:
        
        case 72:
        
        case 73:
        
        case 74:
        
        case 75:
        
        case 76:
        
        case 77:
        
        case 78:
        
        case 79:
        
        case 80:
        
        case 81:
        
        case 82:
        
        case 83:
        
        case 84:
        
        case 85:
        
        case 86:
        
        case 87:
        
        case 88:
        
        case 89:
        
        case 90:
        
        case 91:
        
        case 92:
        
        case 93:
        
        case 94:
        
        case 95:
        
        case 96:
        
        case 97:
        
        case 98:
        
        case 99:
        
        case 100:
        
        case 101:
        
        case 102:
        
        case 103:
        
        case 104:
        
        case 105:
        
        case 106:
        
        case 107:
        
        case 108:
        
        case 109:
        
        case 110:
        
        case 111:
        
        case 112:
        
        case 113:
        
        case 114:
        
        case 115:
        
        case 116:
        
        case 117:
        
        case 118:
        
        case 119:
        
        case 120:
        
        case 121:
        
        case 122:
        
        case 123:
        
        case 124:
        
        case 125:
        
        case 126:
        
        case 127:
        
        case 128:
        
        case 129:
        
        case 130:
        
        case 131:
        
        case 132:
        
        case 133:
        
        case 134:
        
        case 135:
        
        case 136:
        
        case 137:
        
        case 138:
        
        case 139:
        
        case 140:
        
        case 141:
        
        case 142:
        
        case 143:
        
        case 144:
        
        case 145:
        
        case 146:
        
        case 147:
        
        case 148:
        
        case 149:
        
        case 150:
        
        case 151:
        
        case 152:
        
        case 153:
        
        case 154:
        
        case 155:
        
        case 156:
        
        case 157:
        
        case 158:
        
        case 159:
        
        case 160:
        
        case 161:
        
        case 162:
        
        case 163:
        
        case 164:
        
        case 165:
        
        case 166:
        
        case 167:
        
        case 168:
        
        case 169:
        
        case 170:
        
        case 171:
        
        case 172:
        
        case 173:
        
        case 174:
        
        case 175:
        
        case 176:
        
        case 177:
        
        case 178:
        
        case 179:
        
        case 180:
        
        case 181:
        
        case 182:
        
        case 183:
        
        case 184:
        
        case 185:
        
        case 186:
        
        case 187:
        
        case 188:
        
        case 189:
        
        case 190:
        
        case 191:
        
        case 192:
        
        case 193:
        
        case 194:
        
        case 195:
        
        case 196:
        
        case 197:
        
        case 198:
        
        case 199:
        
        case 200:
        
        case 201:
        
        case 202:
        
        case 203:
        
        case 204:
        
        case 205:
        
        case 206:
        
        case 207:
        
        case 208:
        
        case 209:
        
        case 210:
        
        case 211:
        
        case 212:
        
        case 213:
        
        case 214:
        
        case 215:
        
        case 216:
        
        case 217:
        
        case 218:
        
        case 219:
        
        case 220:
        
        case 221:
        
        case 222:
        
        case 223:
        
        case 224:
        
        case 225:
        
        case 226:
        
        case 227:
        
        case 228:
        
        case 229:
        
        case 230:
        
        case 231:
        
        case 232:
        
        case 233:
        
        case 234:
        
        case 235:
        
        case 236:
        
        case 237:
        
        case 238:
        
        case 239:
        
        case 240:
        
        case 241:
        
        case 242:
        
        case 243:
        
        case 244:
        
        case 245:
        
        case 246:
        
        case 247:
        
        case 248:
        
        case 249:
        
        case 250:
        
        case 251:
        
        case 252:
        
        case 253:
        
        case 254:
        
        default:
          break;
      } 
      byte b1 = 0;
      int j = (paramInt2 & 0xFF) - b1;
      if (j < 0)
        j += 256; 
      int k = ((paramInt2 & 0xFFFF) >>> 8) - b1;
      if (k < 0)
        k += 256; 
      for (byte b2 = 0; b2 < arrayOfChar.length; b2++) {
        int m = b2 % 2;
        if (m == 0) {
          arrayOfChar[b2] = (char)(arrayOfChar[b2] ^ j);
          j = ((j >>> 3 | j << 5) ^ arrayOfChar[b2]) & 0xFF;
        } else {
          arrayOfChar[b2] = (char)(arrayOfChar[b2] ^ k);
          k = ((k >>> 3 | k << 5) ^ arrayOfChar[b2]) & 0xFF;
        } 
      } 
      b[i] = (new String(arrayOfChar)).intern();
    } 
    return b[i];
  }
}


/* Location:              C:\Program Files\BurpSuitePro\burpsuite_pro.jar!\burp\Ze6d.class
 * Java compiler version: 21 (65.0)
 * JD-Core Version:       1.1.3
 */