package burp;

import java.math.BigInteger;

class Ze6k extends ClassLoader {
  static String ZM;
  
  static Object Zs;
  
  private static final String[] a;
  
  private static final String[] b;
  
  static void Zx(Object[] paramArrayOfObject, Object paramObject) throws Throwable {}
  
  static boolean Za(Object[] paramArrayOfObject, Object paramObject) throws Throwable {
    // Byte code:
    //   0: invokestatic ZK : ()Z
    //   3: istore_2
    //   4: new java/lang/StringBuilder
    //   7: dup
    //   8: invokespecial <init> : ()V
    //   11: astore_3
    //   12: iconst_0
    //   13: istore #4
    //   15: iload #4
    //   17: bipush #32
    //   19: if_icmpge -> 1355
    //   22: iload #4
    //   24: tableswitch default -> 1348, 0 -> 168, 1 -> 205, 2 -> 242, 3 -> 279, 4 -> 316, 5 -> 353, 6 -> 390, 7 -> 427, 8 -> 464, 9 -> 501, 10 -> 538, 11 -> 575, 12 -> 612, 13 -> 649, 14 -> 686, 15 -> 723, 16 -> 760, 17 -> 797, 18 -> 834, 19 -> 871, 20 -> 908, 21 -> 945, 22 -> 982, 23 -> 1019, 24 -> 1056, 25 -> 1093, 26 -> 1130, 27 -> 1167, 28 -> 1204, 29 -> 1241, 30 -> 1278, 31 -> 1315
    //   168: aload_3
    //   169: getstatic burp/Zxxd.Za : Ljava/lang/String;
    //   172: getstatic burp/Zsbd.Zh : Ljava/lang/Object;
    //   175: checkcast java/math/BigInteger
    //   178: invokevirtual intValue : ()I
    //   181: bipush #32
    //   183: irem
    //   184: invokestatic abs : (I)I
    //   187: invokevirtual charAt : (I)C
    //   190: invokevirtual append : (C)Ljava/lang/StringBuilder;
    //   193: pop
    //   194: iload_2
    //   195: ifeq -> 1348
    //   198: goto -> 205
    //   201: invokestatic a : (Ljava/lang/Throwable;)Ljava/lang/Throwable;
    //   204: athrow
    //   205: aload_3
    //   206: getstatic burp/Zl4v.ZD : Ljava/lang/String;
    //   209: getstatic burp/Zm1l.Za : Ljava/lang/Object;
    //   212: checkcast java/math/BigInteger
    //   215: invokevirtual intValue : ()I
    //   218: bipush #32
    //   220: irem
    //   221: invokestatic abs : (I)I
    //   224: invokevirtual charAt : (I)C
    //   227: invokevirtual append : (C)Ljava/lang/StringBuilder;
    //   230: pop
    //   231: iload_2
    //   232: ifeq -> 1348
    //   235: goto -> 242
    //   238: invokestatic a : (Ljava/lang/Throwable;)Ljava/lang/Throwable;
    //   241: athrow
    //   242: aload_3
    //   243: getstatic burp/Ztvp.ZZ : Ljava/lang/String;
    //   246: getstatic burp/Zm_w.ZW : Ljava/lang/Object;
    //   249: checkcast java/math/BigInteger
    //   252: invokevirtual intValue : ()I
    //   255: bipush #32
    //   257: irem
    //   258: invokestatic abs : (I)I
    //   261: invokevirtual charAt : (I)C
    //   264: invokevirtual append : (C)Ljava/lang/StringBuilder;
    //   267: pop
    //   268: iload_2
    //   269: ifeq -> 1348
    //   272: goto -> 279
    //   275: invokestatic a : (Ljava/lang/Throwable;)Ljava/lang/Throwable;
    //   278: athrow
    //   279: aload_3
    //   280: getstatic burp/Zmir.ZI : Ljava/lang/String;
    //   283: getstatic burp/Ztfr.Zr : Ljava/lang/Object;
    //   286: checkcast java/math/BigInteger
    //   289: invokevirtual intValue : ()I
    //   292: bipush #32
    //   294: irem
    //   295: invokestatic abs : (I)I
    //   298: invokevirtual charAt : (I)C
    //   301: invokevirtual append : (C)Ljava/lang/StringBuilder;
    //   304: pop
    //   305: iload_2
    //   306: ifeq -> 1348
    //   309: goto -> 316
    //   312: invokestatic a : (Ljava/lang/Throwable;)Ljava/lang/Throwable;
    //   315: athrow
    //   316: aload_3
    //   317: getstatic burp/Zxyu.ZM : Ljava/lang/String;
    //   320: getstatic burp/Zkff.Zr : Ljava/lang/Object;
    //   323: checkcast java/math/BigInteger
    //   326: invokevirtual intValue : ()I
    //   329: bipush #32
    //   331: irem
    //   332: invokestatic abs : (I)I
    //   335: invokevirtual charAt : (I)C
    //   338: invokevirtual append : (C)Ljava/lang/StringBuilder;
    //   341: pop
    //   342: iload_2
    //   343: ifeq -> 1348
    //   346: goto -> 353
    //   349: invokestatic a : (Ljava/lang/Throwable;)Ljava/lang/Throwable;
    //   352: athrow
    //   353: aload_3
    //   354: getstatic burp/Zsmn.Zo : Ljava/lang/String;
    //   357: getstatic burp/Zgco.Zx : Ljava/lang/Object;
    //   360: checkcast java/math/BigInteger
    //   363: invokevirtual intValue : ()I
    //   366: bipush #32
    //   368: irem
    //   369: invokestatic abs : (I)I
    //   372: invokevirtual charAt : (I)C
    //   375: invokevirtual append : (C)Ljava/lang/StringBuilder;
    //   378: pop
    //   379: iload_2
    //   380: ifeq -> 1348
    //   383: goto -> 390
    //   386: invokestatic a : (Ljava/lang/Throwable;)Ljava/lang/Throwable;
    //   389: athrow
    //   390: aload_3
    //   391: getstatic burp/Zxof.Zs : Ljava/lang/String;
    //   394: getstatic burp/Zl1n.ZM : Ljava/lang/Object;
    //   397: checkcast java/math/BigInteger
    //   400: invokevirtual intValue : ()I
    //   403: bipush #32
    //   405: irem
    //   406: invokestatic abs : (I)I
    //   409: invokevirtual charAt : (I)C
    //   412: invokevirtual append : (C)Ljava/lang/StringBuilder;
    //   415: pop
    //   416: iload_2
    //   417: ifeq -> 1348
    //   420: goto -> 427
    //   423: invokestatic a : (Ljava/lang/Throwable;)Ljava/lang/Throwable;
    //   426: athrow
    //   427: aload_3
    //   428: getstatic burp/Zboa.Zq : Ljava/lang/String;
    //   431: getstatic burp/Zrfl.Z_ : Ljava/lang/Object;
    //   434: checkcast java/math/BigInteger
    //   437: invokevirtual intValue : ()I
    //   440: bipush #32
    //   442: irem
    //   443: invokestatic abs : (I)I
    //   446: invokevirtual charAt : (I)C
    //   449: invokevirtual append : (C)Ljava/lang/StringBuilder;
    //   452: pop
    //   453: iload_2
    //   454: ifeq -> 1348
    //   457: goto -> 464
    //   460: invokestatic a : (Ljava/lang/Throwable;)Ljava/lang/Throwable;
    //   463: athrow
    //   464: aload_3
    //   465: getstatic burp/Zm1l.Zp : Ljava/lang/String;
    //   468: getstatic burp/Zbu.ZW : Ljava/lang/Object;
    //   471: checkcast java/math/BigInteger
    //   474: invokevirtual intValue : ()I
    //   477: bipush #32
    //   479: irem
    //   480: invokestatic abs : (I)I
    //   483: invokevirtual charAt : (I)C
    //   486: invokevirtual append : (C)Ljava/lang/StringBuilder;
    //   489: pop
    //   490: iload_2
    //   491: ifeq -> 1348
    //   494: goto -> 501
    //   497: invokestatic a : (Ljava/lang/Throwable;)Ljava/lang/Throwable;
    //   500: athrow
    //   501: aload_3
    //   502: getstatic burp/Zd0.Zi : Ljava/lang/String;
    //   505: getstatic burp/Zty4.ZQ : Ljava/lang/Object;
    //   508: checkcast java/math/BigInteger
    //   511: invokevirtual intValue : ()I
    //   514: bipush #32
    //   516: irem
    //   517: invokestatic abs : (I)I
    //   520: invokevirtual charAt : (I)C
    //   523: invokevirtual append : (C)Ljava/lang/StringBuilder;
    //   526: pop
    //   527: iload_2
    //   528: ifeq -> 1348
    //   531: goto -> 538
    //   534: invokestatic a : (Ljava/lang/Throwable;)Ljava/lang/Throwable;
    //   537: athrow
    //   538: aload_3
    //   539: getstatic burp/Zrw7.Zo : Ljava/lang/String;
    //   542: getstatic burp/Zgco.Zx : Ljava/lang/Object;
    //   545: checkcast java/math/BigInteger
    //   548: invokevirtual intValue : ()I
    //   551: bipush #32
    //   553: irem
    //   554: invokestatic abs : (I)I
    //   557: invokevirtual charAt : (I)C
    //   560: invokevirtual append : (C)Ljava/lang/StringBuilder;
    //   563: pop
    //   564: iload_2
    //   565: ifeq -> 1348
    //   568: goto -> 575
    //   571: invokestatic a : (Ljava/lang/Throwable;)Ljava/lang/Throwable;
    //   574: athrow
    //   575: aload_3
    //   576: getstatic burp/Zb9m.Zc : Ljava/lang/String;
    //   579: getstatic burp/Zex5.Zb : Ljava/lang/Object;
    //   582: checkcast java/math/BigInteger
    //   585: invokevirtual intValue : ()I
    //   588: bipush #32
    //   590: irem
    //   591: invokestatic abs : (I)I
    //   594: invokevirtual charAt : (I)C
    //   597: invokevirtual append : (C)Ljava/lang/StringBuilder;
    //   600: pop
    //   601: iload_2
    //   602: ifeq -> 1348
    //   605: goto -> 612
    //   608: invokestatic a : (Ljava/lang/Throwable;)Ljava/lang/Throwable;
    //   611: athrow
    //   612: aload_3
    //   613: getstatic burp/Zly7.ZC : Ljava/lang/String;
    //   616: getstatic burp/Zrw7.ZV : Ljava/lang/Object;
    //   619: checkcast java/math/BigInteger
    //   622: invokevirtual intValue : ()I
    //   625: bipush #32
    //   627: irem
    //   628: invokestatic abs : (I)I
    //   631: invokevirtual charAt : (I)C
    //   634: invokevirtual append : (C)Ljava/lang/StringBuilder;
    //   637: pop
    //   638: iload_2
    //   639: ifeq -> 1348
    //   642: goto -> 649
    //   645: invokestatic a : (Ljava/lang/Throwable;)Ljava/lang/Throwable;
    //   648: athrow
    //   649: aload_3
    //   650: getstatic burp/Zxof.Zs : Ljava/lang/String;
    //   653: getstatic burp/Zelz.Z_ : Ljava/lang/Object;
    //   656: checkcast java/math/BigInteger
    //   659: invokevirtual intValue : ()I
    //   662: bipush #32
    //   664: irem
    //   665: invokestatic abs : (I)I
    //   668: invokevirtual charAt : (I)C
    //   671: invokevirtual append : (C)Ljava/lang/StringBuilder;
    //   674: pop
    //   675: iload_2
    //   676: ifeq -> 1348
    //   679: goto -> 686
    //   682: invokestatic a : (Ljava/lang/Throwable;)Ljava/lang/Throwable;
    //   685: athrow
    //   686: aload_3
    //   687: getstatic burp/Zl5d.Zh : Ljava/lang/String;
    //   690: getstatic burp/Zl6e.Zo : Ljava/lang/Object;
    //   693: checkcast java/math/BigInteger
    //   696: invokevirtual intValue : ()I
    //   699: bipush #32
    //   701: irem
    //   702: invokestatic abs : (I)I
    //   705: invokevirtual charAt : (I)C
    //   708: invokevirtual append : (C)Ljava/lang/StringBuilder;
    //   711: pop
    //   712: iload_2
    //   713: ifeq -> 1348
    //   716: goto -> 723
    //   719: invokestatic a : (Ljava/lang/Throwable;)Ljava/lang/Throwable;
    //   722: athrow
    //   723: aload_3
    //   724: getstatic burp/Zrw7.Zo : Ljava/lang/String;
    //   727: getstatic burp/Zgde.ZG : Ljava/lang/Object;
    //   730: checkcast java/math/BigInteger
    //   733: invokevirtual intValue : ()I
    //   736: bipush #32
    //   738: irem
    //   739: invokestatic abs : (I)I
    //   742: invokevirtual charAt : (I)C
    //   745: invokevirtual append : (C)Ljava/lang/StringBuilder;
    //   748: pop
    //   749: iload_2
    //   750: ifeq -> 1348
    //   753: goto -> 760
    //   756: invokestatic a : (Ljava/lang/Throwable;)Ljava/lang/Throwable;
    //   759: athrow
    //   760: aload_3
    //   761: getstatic burp/Zgco.Zh : Ljava/lang/String;
    //   764: getstatic burp/Ztzw.Zk : Ljava/lang/Object;
    //   767: checkcast java/math/BigInteger
    //   770: invokevirtual intValue : ()I
    //   773: bipush #32
    //   775: irem
    //   776: invokestatic abs : (I)I
    //   779: invokevirtual charAt : (I)C
    //   782: invokevirtual append : (C)Ljava/lang/StringBuilder;
    //   785: pop
    //   786: iload_2
    //   787: ifeq -> 1348
    //   790: goto -> 797
    //   793: invokestatic a : (Ljava/lang/Throwable;)Ljava/lang/Throwable;
    //   796: athrow
    //   797: aload_3
    //   798: getstatic burp/Zec_.Zv : Ljava/lang/String;
    //   801: getstatic burp/Zex5.Zb : Ljava/lang/Object;
    //   804: checkcast java/math/BigInteger
    //   807: invokevirtual intValue : ()I
    //   810: bipush #32
    //   812: irem
    //   813: invokestatic abs : (I)I
    //   816: invokevirtual charAt : (I)C
    //   819: invokevirtual append : (C)Ljava/lang/StringBuilder;
    //   822: pop
    //   823: iload_2
    //   824: ifeq -> 1348
    //   827: goto -> 834
    //   830: invokestatic a : (Ljava/lang/Throwable;)Ljava/lang/Throwable;
    //   833: athrow
    //   834: aload_3
    //   835: getstatic burp/Zrfl.Zy : Ljava/lang/String;
    //   838: getstatic burp/Zd0.ZT : Ljava/lang/Object;
    //   841: checkcast java/math/BigInteger
    //   844: invokevirtual intValue : ()I
    //   847: bipush #32
    //   849: irem
    //   850: invokestatic abs : (I)I
    //   853: invokevirtual charAt : (I)C
    //   856: invokevirtual append : (C)Ljava/lang/StringBuilder;
    //   859: pop
    //   860: iload_2
    //   861: ifeq -> 1348
    //   864: goto -> 871
    //   867: invokestatic a : (Ljava/lang/Throwable;)Ljava/lang/Throwable;
    //   870: athrow
    //   871: aload_3
    //   872: getstatic burp/Zgfm.ZE : Ljava/lang/String;
    //   875: getstatic burp/Zgfm.ZV : Ljava/lang/Object;
    //   878: checkcast java/math/BigInteger
    //   881: invokevirtual intValue : ()I
    //   884: bipush #32
    //   886: irem
    //   887: invokestatic abs : (I)I
    //   890: invokevirtual charAt : (I)C
    //   893: invokevirtual append : (C)Ljava/lang/StringBuilder;
    //   896: pop
    //   897: iload_2
    //   898: ifeq -> 1348
    //   901: goto -> 908
    //   904: invokestatic a : (Ljava/lang/Throwable;)Ljava/lang/Throwable;
    //   907: athrow
    //   908: aload_3
    //   909: getstatic burp/Zrfl.Zy : Ljava/lang/String;
    //   912: getstatic burp/Zcc.Zd : Ljava/lang/Object;
    //   915: checkcast java/math/BigInteger
    //   918: invokevirtual intValue : ()I
    //   921: bipush #32
    //   923: irem
    //   924: invokestatic abs : (I)I
    //   927: invokevirtual charAt : (I)C
    //   930: invokevirtual append : (C)Ljava/lang/StringBuilder;
    //   933: pop
    //   934: iload_2
    //   935: ifeq -> 1348
    //   938: goto -> 945
    //   941: invokestatic a : (Ljava/lang/Throwable;)Ljava/lang/Throwable;
    //   944: athrow
    //   945: aload_3
    //   946: getstatic burp/Zec0.Zk : Ljava/lang/String;
    //   949: getstatic burp/Zg2z.ZU : Ljava/lang/Object;
    //   952: checkcast java/math/BigInteger
    //   955: invokevirtual intValue : ()I
    //   958: bipush #32
    //   960: irem
    //   961: invokestatic abs : (I)I
    //   964: invokevirtual charAt : (I)C
    //   967: invokevirtual append : (C)Ljava/lang/StringBuilder;
    //   970: pop
    //   971: iload_2
    //   972: ifeq -> 1348
    //   975: goto -> 982
    //   978: invokestatic a : (Ljava/lang/Throwable;)Ljava/lang/Throwable;
    //   981: athrow
    //   982: aload_3
    //   983: getstatic burp/Zx_b.ZD : Ljava/lang/String;
    //   986: getstatic burp/Ze08.ZJ : Ljava/lang/Object;
    //   989: checkcast java/math/BigInteger
    //   992: invokevirtual intValue : ()I
    //   995: bipush #32
    //   997: irem
    //   998: invokestatic abs : (I)I
    //   1001: invokevirtual charAt : (I)C
    //   1004: invokevirtual append : (C)Ljava/lang/StringBuilder;
    //   1007: pop
    //   1008: iload_2
    //   1009: ifeq -> 1348
    //   1012: goto -> 1019
    //   1015: invokestatic a : (Ljava/lang/Throwable;)Ljava/lang/Throwable;
    //   1018: athrow
    //   1019: aload_3
    //   1020: getstatic burp/Zsdn.Zf : Ljava/lang/String;
    //   1023: getstatic burp/Zxjm.Zn : Ljava/lang/Object;
    //   1026: checkcast java/math/BigInteger
    //   1029: invokevirtual intValue : ()I
    //   1032: bipush #32
    //   1034: irem
    //   1035: invokestatic abs : (I)I
    //   1038: invokevirtual charAt : (I)C
    //   1041: invokevirtual append : (C)Ljava/lang/StringBuilder;
    //   1044: pop
    //   1045: iload_2
    //   1046: ifeq -> 1348
    //   1049: goto -> 1056
    //   1052: invokestatic a : (Ljava/lang/Throwable;)Ljava/lang/Throwable;
    //   1055: athrow
    //   1056: aload_3
    //   1057: getstatic burp/Zcc.Zb : Ljava/lang/String;
    //   1060: getstatic burp/Zl6e.Zo : Ljava/lang/Object;
    //   1063: checkcast java/math/BigInteger
    //   1066: invokevirtual intValue : ()I
    //   1069: bipush #32
    //   1071: irem
    //   1072: invokestatic abs : (I)I
    //   1075: invokevirtual charAt : (I)C
    //   1078: invokevirtual append : (C)Ljava/lang/StringBuilder;
    //   1081: pop
    //   1082: iload_2
    //   1083: ifeq -> 1348
    //   1086: goto -> 1093
    //   1089: invokestatic a : (Ljava/lang/Throwable;)Ljava/lang/Throwable;
    //   1092: athrow
    //   1093: aload_3
    //   1094: getstatic burp/Zboa.Zq : Ljava/lang/String;
    //   1097: getstatic burp/Zlbr.Zp : Ljava/lang/Object;
    //   1100: checkcast java/math/BigInteger
    //   1103: invokevirtual intValue : ()I
    //   1106: bipush #32
    //   1108: irem
    //   1109: invokestatic abs : (I)I
    //   1112: invokevirtual charAt : (I)C
    //   1115: invokevirtual append : (C)Ljava/lang/StringBuilder;
    //   1118: pop
    //   1119: iload_2
    //   1120: ifeq -> 1348
    //   1123: goto -> 1130
    //   1126: invokestatic a : (Ljava/lang/Throwable;)Ljava/lang/Throwable;
    //   1129: athrow
    //   1130: aload_3
    //   1131: getstatic burp/Zrw7.Zo : Ljava/lang/String;
    //   1134: getstatic burp/Zsuw.ZB : Ljava/lang/Object;
    //   1137: checkcast java/math/BigInteger
    //   1140: invokevirtual intValue : ()I
    //   1143: bipush #32
    //   1145: irem
    //   1146: invokestatic abs : (I)I
    //   1149: invokevirtual charAt : (I)C
    //   1152: invokevirtual append : (C)Ljava/lang/StringBuilder;
    //   1155: pop
    //   1156: iload_2
    //   1157: ifeq -> 1348
    //   1160: goto -> 1167
    //   1163: invokestatic a : (Ljava/lang/Throwable;)Ljava/lang/Throwable;
    //   1166: athrow
    //   1167: aload_3
    //   1168: getstatic burp/Zlbr.Zr : Ljava/lang/String;
    //   1171: getstatic burp/Zgfm.ZV : Ljava/lang/Object;
    //   1174: checkcast java/math/BigInteger
    //   1177: invokevirtual intValue : ()I
    //   1180: bipush #32
    //   1182: irem
    //   1183: invokestatic abs : (I)I
    //   1186: invokevirtual charAt : (I)C
    //   1189: invokevirtual append : (C)Ljava/lang/StringBuilder;
    //   1192: pop
    //   1193: iload_2
    //   1194: ifeq -> 1348
    //   1197: goto -> 1204
    //   1200: invokestatic a : (Ljava/lang/Throwable;)Ljava/lang/Throwable;
    //   1203: athrow
    //   1204: aload_3
    //   1205: getstatic burp/Zgco.Zh : Ljava/lang/String;
    //   1208: getstatic burp/Zty2.Zl : Ljava/lang/Object;
    //   1211: checkcast java/math/BigInteger
    //   1214: invokevirtual intValue : ()I
    //   1217: bipush #32
    //   1219: irem
    //   1220: invokestatic abs : (I)I
    //   1223: invokevirtual charAt : (I)C
    //   1226: invokevirtual append : (C)Ljava/lang/StringBuilder;
    //   1229: pop
    //   1230: iload_2
    //   1231: ifeq -> 1348
    //   1234: goto -> 1241
    //   1237: invokestatic a : (Ljava/lang/Throwable;)Ljava/lang/Throwable;
    //   1240: athrow
    //   1241: aload_3
    //   1242: getstatic burp/Zs15.Zs : Ljava/lang/String;
    //   1245: getstatic burp/Zkff.Zr : Ljava/lang/Object;
    //   1248: checkcast java/math/BigInteger
    //   1251: invokevirtual intValue : ()I
    //   1254: bipush #32
    //   1256: irem
    //   1257: invokestatic abs : (I)I
    //   1260: invokevirtual charAt : (I)C
    //   1263: invokevirtual append : (C)Ljava/lang/StringBuilder;
    //   1266: pop
    //   1267: iload_2
    //   1268: ifeq -> 1348
    //   1271: goto -> 1278
    //   1274: invokestatic a : (Ljava/lang/Throwable;)Ljava/lang/Throwable;
    //   1277: athrow
    //   1278: aload_3
    //   1279: getstatic burp/Zry9.ZW : Ljava/lang/String;
    //   1282: getstatic burp/Zrcu.Zs : Ljava/lang/Object;
    //   1285: checkcast java/math/BigInteger
    //   1288: invokevirtual intValue : ()I
    //   1291: bipush #32
    //   1293: irem
    //   1294: invokestatic abs : (I)I
    //   1297: invokevirtual charAt : (I)C
    //   1300: invokevirtual append : (C)Ljava/lang/StringBuilder;
    //   1303: pop
    //   1304: iload_2
    //   1305: ifeq -> 1348
    //   1308: goto -> 1315
    //   1311: invokestatic a : (Ljava/lang/Throwable;)Ljava/lang/Throwable;
    //   1314: athrow
    //   1315: aload_3
    //   1316: getstatic burp/Zl6e.ZC : Ljava/lang/String;
    //   1319: getstatic burp/Zkde.Zk : Ljava/lang/Object;
    //   1322: checkcast java/math/BigInteger
    //   1325: invokevirtual intValue : ()I
    //   1328: bipush #32
    //   1330: irem
    //   1331: invokestatic abs : (I)I
    //   1334: invokevirtual charAt : (I)C
    //   1337: invokevirtual append : (C)Ljava/lang/StringBuilder;
    //   1340: pop
    //   1341: goto -> 1348
    //   1344: invokestatic a : (Ljava/lang/Throwable;)Ljava/lang/Throwable;
    //   1347: athrow
    //   1348: iinc #4, 1
    //   1351: iload_2
    //   1352: ifeq -> 15
    //   1355: aload_3
    //   1356: invokevirtual toString : ()Ljava/lang/String;
    //   1359: putstatic burp/Zsyu.ZJ : Ljava/lang/String;
    //   1362: sipush #7756
    //   1365: getstatic burp/Ze6k.Zs : Ljava/lang/Object;
    //   1368: checkcast java/math/BigInteger
    //   1371: getstatic burp/Zx_u.Zy : Ljava/lang/Object;
    //   1374: checkcast java/math/BigInteger
    //   1377: invokevirtual add : (Ljava/math/BigInteger;)Ljava/math/BigInteger;
    //   1380: putstatic burp/Zxyu.Zp : Ljava/lang/Object;
    //   1383: sipush #8370
    //   1386: invokestatic a : (II)Ljava/lang/String;
    //   1389: iconst_1
    //   1390: ldc burp/Zes_
    //   1392: invokevirtual getClassLoader : ()Ljava/lang/ClassLoader;
    //   1395: invokestatic forName : (Ljava/lang/String;ZLjava/lang/ClassLoader;)Ljava/lang/Class;
    //   1398: invokevirtual getDeclaredFields : ()[Ljava/lang/reflect/Field;
    //   1401: astore #4
    //   1403: aload #4
    //   1405: arraylength
    //   1406: istore #5
    //   1408: iconst_0
    //   1409: istore #6
    //   1411: iload #6
    //   1413: iload #5
    //   1415: if_icmpge -> 1553
    //   1418: aload #4
    //   1420: iload #6
    //   1422: aaload
    //   1423: astore #7
    //   1425: aload #7
    //   1427: invokevirtual getModifiers : ()I
    //   1430: invokestatic isStatic : (I)Z
    //   1433: ifne -> 1443
    //   1436: goto -> 1546
    //   1439: invokestatic a : (Ljava/lang/Throwable;)Ljava/lang/Throwable;
    //   1442: athrow
    //   1443: aload #7
    //   1445: invokevirtual getType : ()Ljava/lang/Class;
    //   1448: astore #8
    //   1450: aload #8
    //   1452: ifnull -> 1533
    //   1455: aload #8
    //   1457: invokevirtual isPrimitive : ()Z
    //   1460: ifne -> 1533
    //   1463: goto -> 1470
    //   1466: invokestatic a : (Ljava/lang/Throwable;)Ljava/lang/Throwable;
    //   1469: athrow
    //   1470: aload #8
    //   1472: invokevirtual getPackage : ()Ljava/lang/Package;
    //   1475: ifnull -> 1533
    //   1478: goto -> 1485
    //   1481: invokestatic a : (Ljava/lang/Throwable;)Ljava/lang/Throwable;
    //   1484: athrow
    //   1485: aload #8
    //   1487: invokevirtual getPackage : ()Ljava/lang/Package;
    //   1490: invokevirtual getName : ()Ljava/lang/String;
    //   1493: ifnull -> 1533
    //   1496: goto -> 1503
    //   1499: invokestatic a : (Ljava/lang/Throwable;)Ljava/lang/Throwable;
    //   1502: athrow
    //   1503: aload #8
    //   1505: invokevirtual getPackage : ()Ljava/lang/Package;
    //   1508: invokevirtual getName : ()Ljava/lang/String;
    //   1511: sipush #7755
    //   1514: sipush #9237
    //   1517: invokestatic a : (II)Ljava/lang/String;
    //   1520: invokevirtual startsWith : (Ljava/lang/String;)Z
    //   1523: ifne -> 1533
    //   1526: goto -> 1533
    //   1529: invokestatic a : (Ljava/lang/Throwable;)Ljava/lang/Throwable;
    //   1532: athrow
    //   1533: aload #7
    //   1535: iconst_1
    //   1536: invokevirtual setAccessible : (Z)V
    //   1539: aload #7
    //   1541: aconst_null
    //   1542: invokevirtual get : (Ljava/lang/Object;)Ljava/lang/Object;
    //   1545: pop
    //   1546: iinc #6, 1
    //   1549: iload_2
    //   1550: ifeq -> 1411
    //   1553: sipush #7759
    //   1556: sipush #-4600
    //   1559: invokestatic a : (II)Ljava/lang/String;
    //   1562: invokestatic forName : (Ljava/lang/String;)Ljava/lang/Class;
    //   1565: invokevirtual getDeclaredMethods : ()[Ljava/lang/reflect/Method;
    //   1568: astore #4
    //   1570: aload #4
    //   1572: arraylength
    //   1573: istore #5
    //   1575: iconst_0
    //   1576: istore #6
    //   1578: iload #6
    //   1580: iload #5
    //   1582: if_icmpge -> 1715
    //   1585: aload #4
    //   1587: iload #6
    //   1589: aaload
    //   1590: astore #7
    //   1592: aload #7
    //   1594: invokevirtual getParameterTypes : ()[Ljava/lang/Class;
    //   1597: pop
    //   1598: aload #7
    //   1600: invokevirtual getModifiers : ()I
    //   1603: invokestatic isStatic : (I)Z
    //   1606: ifeq -> 1701
    //   1609: aload #7
    //   1611: invokevirtual getParameterTypes : ()[Ljava/lang/Class;
    //   1614: arraylength
    //   1615: iconst_2
    //   1616: if_icmpne -> 1701
    //   1619: goto -> 1626
    //   1622: invokestatic a : (Ljava/lang/Throwable;)Ljava/lang/Throwable;
    //   1625: athrow
    //   1626: aload #7
    //   1628: invokevirtual getReturnType : ()Ljava/lang/Class;
    //   1631: getstatic java/lang/Void.TYPE : Ljava/lang/Class;
    //   1634: invokevirtual equals : (Ljava/lang/Object;)Z
    //   1637: ifeq -> 1701
    //   1640: goto -> 1647
    //   1643: invokestatic a : (Ljava/lang/Throwable;)Ljava/lang/Throwable;
    //   1646: athrow
    //   1647: aload #7
    //   1649: iconst_1
    //   1650: invokevirtual setAccessible : (Z)V
    //   1653: aload #7
    //   1655: aconst_null
    //   1656: iconst_2
    //   1657: anewarray java/lang/Object
    //   1660: dup
    //   1661: iconst_0
    //   1662: aload_0
    //   1663: aastore
    //   1664: dup
    //   1665: iconst_1
    //   1666: aload_1
    //   1667: ifnonnull -> 1685
    //   1670: goto -> 1677
    //   1673: invokestatic a : (Ljava/lang/Throwable;)Ljava/lang/Throwable;
    //   1676: athrow
    //   1677: aload_1
    //   1678: goto -> 1692
    //   1681: invokestatic a : (Ljava/lang/Throwable;)Ljava/lang/Throwable;
    //   1684: athrow
    //   1685: aload_1
    //   1686: checkcast [B
    //   1689: invokevirtual clone : ()Ljava/lang/Object;
    //   1692: aastore
    //   1693: invokevirtual invoke : (Ljava/lang/Object;[Ljava/lang/Object;)Ljava/lang/Object;
    //   1696: pop
    //   1697: iload_2
    //   1698: ifeq -> 1715
    //   1701: iinc #6, 1
    //   1704: iload_2
    //   1705: ifeq -> 1578
    //   1708: goto -> 1715
    //   1711: invokestatic a : (Ljava/lang/Throwable;)Ljava/lang/Throwable;
    //   1714: athrow
    //   1715: getstatic burp/Zs15.Zk : Ljava/lang/Object;
    //   1718: checkcast java/math/BigInteger
    //   1721: invokevirtual intValue : ()I
    //   1724: i2l
    //   1725: invokestatic currentTimeMillis : ()J
    //   1728: ladd
    //   1729: getstatic burp/Zgr4.ZL : Ljava/lang/Object;
    //   1732: checkcast java/math/BigInteger
    //   1735: invokevirtual intValue : ()I
    //   1738: i2l
    //   1739: lcmp
    //   1740: ifge -> 2078
    //   1743: sipush #7759
    //   1746: sipush #-4600
    //   1749: invokestatic a : (II)Ljava/lang/String;
    //   1752: iconst_1
    //   1753: ldc burp/Zltp
    //   1755: invokevirtual getClassLoader : ()Ljava/lang/ClassLoader;
    //   1758: invokestatic forName : (Ljava/lang/String;ZLjava/lang/ClassLoader;)Ljava/lang/Class;
    //   1761: invokevirtual getDeclaredFields : ()[Ljava/lang/reflect/Field;
    //   1764: astore #4
    //   1766: aload #4
    //   1768: arraylength
    //   1769: istore #5
    //   1771: iconst_0
    //   1772: istore #6
    //   1774: iload #6
    //   1776: iload #5
    //   1778: if_icmpge -> 1916
    //   1781: aload #4
    //   1783: iload #6
    //   1785: aaload
    //   1786: astore #7
    //   1788: aload #7
    //   1790: invokevirtual getModifiers : ()I
    //   1793: invokestatic isStatic : (I)Z
    //   1796: ifne -> 1806
    //   1799: goto -> 1909
    //   1802: invokestatic a : (Ljava/lang/Throwable;)Ljava/lang/Throwable;
    //   1805: athrow
    //   1806: aload #7
    //   1808: invokevirtual getType : ()Ljava/lang/Class;
    //   1811: astore #8
    //   1813: aload #8
    //   1815: ifnull -> 1896
    //   1818: aload #8
    //   1820: invokevirtual isPrimitive : ()Z
    //   1823: ifne -> 1896
    //   1826: goto -> 1833
    //   1829: invokestatic a : (Ljava/lang/Throwable;)Ljava/lang/Throwable;
    //   1832: athrow
    //   1833: aload #8
    //   1835: invokevirtual getPackage : ()Ljava/lang/Package;
    //   1838: ifnull -> 1896
    //   1841: goto -> 1848
    //   1844: invokestatic a : (Ljava/lang/Throwable;)Ljava/lang/Throwable;
    //   1847: athrow
    //   1848: aload #8
    //   1850: invokevirtual getPackage : ()Ljava/lang/Package;
    //   1853: invokevirtual getName : ()Ljava/lang/String;
    //   1856: ifnull -> 1896
    //   1859: goto -> 1866
    //   1862: invokestatic a : (Ljava/lang/Throwable;)Ljava/lang/Throwable;
    //   1865: athrow
    //   1866: aload #8
    //   1868: invokevirtual getPackage : ()Ljava/lang/Package;
    //   1871: invokevirtual getName : ()Ljava/lang/String;
    //   1874: sipush #7758
    //   1877: sipush #7097
    //   1880: invokestatic a : (II)Ljava/lang/String;
    //   1883: invokevirtual startsWith : (Ljava/lang/String;)Z
    //   1886: ifne -> 1896
    //   1889: goto -> 1896
    //   1892: invokestatic a : (Ljava/lang/Throwable;)Ljava/lang/Throwable;
    //   1895: athrow
    //   1896: aload #7
    //   1898: iconst_1
    //   1899: invokevirtual setAccessible : (Z)V
    //   1902: aload #7
    //   1904: aconst_null
    //   1905: invokevirtual get : (Ljava/lang/Object;)Ljava/lang/Object;
    //   1908: pop
    //   1909: iinc #6, 1
    //   1912: iload_2
    //   1913: ifeq -> 1774
    //   1916: sipush #7759
    //   1919: sipush #-4600
    //   1922: invokestatic a : (II)Ljava/lang/String;
    //   1925: invokestatic forName : (Ljava/lang/String;)Ljava/lang/Class;
    //   1928: invokevirtual getDeclaredMethods : ()[Ljava/lang/reflect/Method;
    //   1931: astore #4
    //   1933: aload #4
    //   1935: arraylength
    //   1936: istore #5
    //   1938: iconst_0
    //   1939: istore #6
    //   1941: iload #6
    //   1943: iload #5
    //   1945: if_icmpge -> 2078
    //   1948: aload #4
    //   1950: iload #6
    //   1952: aaload
    //   1953: astore #7
    //   1955: aload #7
    //   1957: invokevirtual getParameterTypes : ()[Ljava/lang/Class;
    //   1960: pop
    //   1961: aload #7
    //   1963: invokevirtual getModifiers : ()I
    //   1966: invokestatic isStatic : (I)Z
    //   1969: ifeq -> 2064
    //   1972: aload #7
    //   1974: invokevirtual getParameterTypes : ()[Ljava/lang/Class;
    //   1977: arraylength
    //   1978: iconst_2
    //   1979: if_icmpne -> 2064
    //   1982: goto -> 1989
    //   1985: invokestatic a : (Ljava/lang/Throwable;)Ljava/lang/Throwable;
    //   1988: athrow
    //   1989: aload #7
    //   1991: invokevirtual getReturnType : ()Ljava/lang/Class;
    //   1994: getstatic java/lang/Void.TYPE : Ljava/lang/Class;
    //   1997: invokevirtual equals : (Ljava/lang/Object;)Z
    //   2000: ifeq -> 2064
    //   2003: goto -> 2010
    //   2006: invokestatic a : (Ljava/lang/Throwable;)Ljava/lang/Throwable;
    //   2009: athrow
    //   2010: aload #7
    //   2012: iconst_1
    //   2013: invokevirtual setAccessible : (Z)V
    //   2016: aload #7
    //   2018: aconst_null
    //   2019: iconst_2
    //   2020: anewarray java/lang/Object
    //   2023: dup
    //   2024: iconst_0
    //   2025: aload_0
    //   2026: aastore
    //   2027: dup
    //   2028: iconst_1
    //   2029: aload_1
    //   2030: ifnonnull -> 2048
    //   2033: goto -> 2040
    //   2036: invokestatic a : (Ljava/lang/Throwable;)Ljava/lang/Throwable;
    //   2039: athrow
    //   2040: aload_1
    //   2041: goto -> 2055
    //   2044: invokestatic a : (Ljava/lang/Throwable;)Ljava/lang/Throwable;
    //   2047: athrow
    //   2048: aload_1
    //   2049: checkcast [B
    //   2052: invokevirtual clone : ()Ljava/lang/Object;
    //   2055: aastore
    //   2056: invokevirtual invoke : (Ljava/lang/Object;[Ljava/lang/Object;)Ljava/lang/Object;
    //   2059: pop
    //   2060: iload_2
    //   2061: ifeq -> 2078
    //   2064: iinc #6, 1
    //   2067: iload_2
    //   2068: ifeq -> 1941
    //   2071: goto -> 2078
    //   2074: invokestatic a : (Ljava/lang/Throwable;)Ljava/lang/Throwable;
    //   2077: athrow
    //   2078: getstatic burp/Zelz.ZK : Ljava/lang/String;
    //   2081: getstatic burp/Zlbr.Zp : Ljava/lang/Object;
    //   2084: checkcast java/math/BigInteger
    //   2087: invokevirtual intValue : ()I
    //   2090: bipush #32
    //   2092: irem
    //   2093: invokestatic abs : (I)I
    //   2096: invokevirtual charAt : (I)C
    //   2099: getstatic burp/Zgfm.ZE : Ljava/lang/String;
    //   2102: getstatic burp/Zeoi.ZE : Ljava/lang/Object;
    //   2105: checkcast java/math/BigInteger
    //   2108: invokevirtual intValue : ()I
    //   2111: bipush #32
    //   2113: irem
    //   2114: invokestatic abs : (I)I
    //   2117: invokevirtual charAt : (I)C
    //   2120: if_icmpgt -> 2227
    //   2123: getstatic burp/Zxxd.Za : Ljava/lang/String;
    //   2126: getstatic burp/Zegk.ZR : Ljava/lang/Object;
    //   2129: checkcast java/math/BigInteger
    //   2132: invokevirtual intValue : ()I
    //   2135: bipush #32
    //   2137: irem
    //   2138: invokestatic abs : (I)I
    //   2141: invokevirtual charAt : (I)C
    //   2144: getstatic burp/Zztx.Zg : Ljava/lang/String;
    //   2147: getstatic burp/Zd8.Zs : Ljava/lang/Object;
    //   2150: checkcast java/math/BigInteger
    //   2153: invokevirtual intValue : ()I
    //   2156: bipush #32
    //   2158: irem
    //   2159: invokestatic abs : (I)I
    //   2162: invokevirtual charAt : (I)C
    //   2165: if_icmple -> 2227
    //   2168: goto -> 2175
    //   2171: invokestatic a : (Ljava/lang/Throwable;)Ljava/lang/Throwable;
    //   2174: athrow
    //   2175: getstatic burp/Zsbd.ZA : Ljava/lang/String;
    //   2178: getstatic burp/Zm_w.ZW : Ljava/lang/Object;
    //   2181: checkcast java/math/BigInteger
    //   2184: invokevirtual intValue : ()I
    //   2187: bipush #32
    //   2189: irem
    //   2190: invokestatic abs : (I)I
    //   2193: invokevirtual charAt : (I)C
    //   2196: getstatic burp/Zx_u.Z_ : Ljava/lang/String;
    //   2199: getstatic burp/Zmir.ZF : Ljava/lang/Object;
    //   2202: checkcast java/math/BigInteger
    //   2205: invokevirtual intValue : ()I
    //   2208: bipush #32
    //   2210: irem
    //   2211: invokestatic abs : (I)I
    //   2214: invokevirtual charAt : (I)C
    //   2217: if_icmpgt -> 2235
    //   2220: goto -> 2227
    //   2223: invokestatic a : (Ljava/lang/Throwable;)Ljava/lang/Throwable;
    //   2226: athrow
    //   2227: iconst_1
    //   2228: goto -> 2236
    //   2231: invokestatic a : (Ljava/lang/Throwable;)Ljava/lang/Throwable;
    //   2234: athrow
    //   2235: iconst_0
    //   2236: ireturn
    //   2237: astore_3
    //   2238: new java/lang/Exception
    //   2241: dup
    //   2242: aload_3
    //   2243: invokevirtual getMessage : ()Ljava/lang/String;
    //   2246: invokespecial <init> : (Ljava/lang/String;)V
    //   2249: athrow
    // Exception table:
    //   from	to	target	type
    //   4	2236	2237	java/lang/Throwable
    //   22	198	201	java/lang/Throwable
    //   168	235	238	java/lang/Throwable
    //   205	272	275	java/lang/Throwable
    //   242	309	312	java/lang/Throwable
    //   279	346	349	java/lang/Throwable
    //   316	383	386	java/lang/Throwable
    //   353	420	423	java/lang/Throwable
    //   390	457	460	java/lang/Throwable
    //   427	494	497	java/lang/Throwable
    //   464	531	534	java/lang/Throwable
    //   501	568	571	java/lang/Throwable
    //   538	605	608	java/lang/Throwable
    //   575	642	645	java/lang/Throwable
    //   612	679	682	java/lang/Throwable
    //   649	716	719	java/lang/Throwable
    //   686	753	756	java/lang/Throwable
    //   723	790	793	java/lang/Throwable
    //   760	827	830	java/lang/Throwable
    //   797	864	867	java/lang/Throwable
    //   834	901	904	java/lang/Throwable
    //   871	938	941	java/lang/Throwable
    //   908	975	978	java/lang/Throwable
    //   945	1012	1015	java/lang/Throwable
    //   982	1049	1052	java/lang/Throwable
    //   1019	1086	1089	java/lang/Throwable
    //   1056	1123	1126	java/lang/Throwable
    //   1093	1160	1163	java/lang/Throwable
    //   1130	1197	1200	java/lang/Throwable
    //   1167	1234	1237	java/lang/Throwable
    //   1204	1271	1274	java/lang/Throwable
    //   1241	1308	1311	java/lang/Throwable
    //   1278	1341	1344	java/lang/Throwable
    //   1425	1439	1439	java/lang/Throwable
    //   1450	1463	1466	java/lang/Throwable
    //   1455	1478	1481	java/lang/Throwable
    //   1470	1496	1499	java/lang/Throwable
    //   1485	1526	1529	java/lang/Throwable
    //   1592	1619	1622	java/lang/Throwable
    //   1609	1640	1643	java/lang/Throwable
    //   1626	1670	1673	java/lang/Throwable
    //   1647	1681	1681	java/lang/Throwable
    //   1692	1708	1711	java/lang/Throwable
    //   1788	1802	1802	java/lang/Throwable
    //   1813	1826	1829	java/lang/Throwable
    //   1818	1841	1844	java/lang/Throwable
    //   1833	1859	1862	java/lang/Throwable
    //   1848	1889	1892	java/lang/Throwable
    //   1955	1982	1985	java/lang/Throwable
    //   1972	2003	2006	java/lang/Throwable
    //   1989	2033	2036	java/lang/Throwable
    //   2010	2044	2044	java/lang/Throwable
    //   2055	2071	2074	java/lang/Throwable
    //   2078	2168	2171	java/lang/Throwable
    //   2123	2220	2223	java/lang/Throwable
    //   2175	2231	2231	java/lang/Throwable
  }
  
  static void ZA(Object paramObject) {
    Zt7w.Zi = a(7751, -423);
    Zt7w.ZF = new BigInteger(a(7754, 2923));
    boolean bool = Zt2e.ZK();
    try {
      try {
        if (Ztzw.Zi.charAt(Math.abs(((BigInteger)Zm4k.Zm).intValue() % 32)) <= Zgde.Zr.charAt(Math.abs(((BigInteger)Zrfl.Z_).intValue() % 32))) {
          try {
            Zmd.Zq(Class.forName(a(7750, 30191)));
            if (bool)
              Zr3j.Zc(Class.forName(a(7753, -17497))); 
          } catch (Throwable throwable) {
            throw a(null);
          } 
          return;
        } 
      } catch (Throwable throwable) {
        throw a(null);
      } 
      Zr3j.Zc(Class.forName(a(7753, -17497)));
    } catch (Throwable throwable) {}
  }
  
  static {
    // Byte code:
    //   0: bipush #10
    //   2: anewarray java/lang/String
    //   5: astore #5
    //   7: iconst_0
    //   8: istore_3
    //   9: ldc 'RÃŽÂb\\tÃ¯Ã‡8CÂ»ÃœÂ”Â’1\\tE9mÂœ'ÃÃ­Â› ÃŽÂ°EÂŠuÂšÃ’5Ã¡Â“#Ã«Ã¿]Â‡!!ÂœÃÃ¿G\\rsM\\tÂ¶Ã¹Ã4Â¢0rÃžÃŸÃ–Â©Â¬ NÃœÂ£ ÂŽÃ gÃˆÃ•ÂžÃ‚BÃ¿]Ã‹%Â‰6Ã´Ã„tV}Â˜u-M6Ã±G>ÃžmAÂ›Ã¨Â„Ã¨Ã¬Â” Ã/Â¹Ã‘Ã‹ÂšÂ¶Ã¯CÂœcrÂ©ÃµMÂ—aI$ÃœÃ¶ÃœÃ¤-Â„$Ã¤Ã²_Ã€u"]Â–Â¦ACÂ»Ã¨ÃˆKwÃ’SÃŒÂ¤ÂŠNQ^Ã¸jÃ‰Ã–;Â© bxÃŽÃ"JÃ˜ÂœqÃƒÃ»ÂµmÃ¼Ã¹Â…Â>VÃ¢AÂ›BÃŒÂ³\\t}jÃšÃ±Ã¯Ã‰Ã¼'
    //   11: dup
    //   12: astore_2
    //   13: invokevirtual length : ()I
    //   16: istore #4
    //   18: iconst_4
    //   19: istore_1
    //   20: iconst_m1
    //   21: istore_0
    //   22: bipush #35
    //   24: iinc #0, 1
    //   27: aload_2
    //   28: iload_0
    //   29: dup
    //   30: iload_1
    //   31: iadd
    //   32: invokevirtual substring : (II)Ljava/lang/String;
    //   35: iconst_m1
    //   36: goto -> 142
    //   39: aload #5
    //   41: swap
    //   42: iload_3
    //   43: iinc #3, 1
    //   46: swap
    //   47: aastore
    //   48: iload_0
    //   49: iload_1
    //   50: iadd
    //   51: dup
    //   52: istore_0
    //   53: iload #4
    //   55: if_icmpge -> 67
    //   58: aload_2
    //   59: iload_0
    //   60: invokevirtual charAt : (I)C
    //   63: istore_1
    //   64: goto -> 22
    //   67: ldc 'Â¶2Ã¾Â½h[H 4ÃŒÃ¡"Ã¸gÂ€Ã—CJÂ©Ã¹Ã¨Ãž"Ã Ã¹Ã°e\Ã³Â†rB+Â˜Ã‹Â•^'
    //   69: dup
    //   70: astore_2
    //   71: invokevirtual length : ()I
    //   74: istore #4
    //   76: bipush #9
    //   78: istore_1
    //   79: iconst_m1
    //   80: istore_0
    //   81: bipush #105
    //   83: iinc #0, 1
    //   86: aload_2
    //   87: iload_0
    //   88: dup
    //   89: iload_1
    //   90: iadd
    //   91: invokevirtual substring : (II)Ljava/lang/String;
    //   94: iconst_0
    //   95: goto -> 142
    //   98: aload #5
    //   100: swap
    //   101: iload_3
    //   102: iinc #3, 1
    //   105: swap
    //   106: aastore
    //   107: iload_0
    //   108: iload_1
    //   109: iadd
    //   110: dup
    //   111: istore_0
    //   112: iload #4
    //   114: if_icmpge -> 126
    //   117: aload_2
    //   118: iload_0
    //   119: invokevirtual charAt : (I)C
    //   122: istore_1
    //   123: goto -> 81
    //   126: aload #5
    //   128: putstatic burp/Ze6k.a : [Ljava/lang/String;
    //   131: bipush #10
    //   133: anewarray java/lang/String
    //   136: putstatic burp/Ze6k.b : [Ljava/lang/String;
    //   139: goto -> 300
    //   142: dup_x2
    //   143: pop
    //   144: invokevirtual toCharArray : ()[C
    //   147: dup_x1
    //   148: arraylength
    //   149: dup_x2
    //   150: pop
    //   151: iconst_0
    //   152: istore #6
    //   154: dup2_x1
    //   155: pop2
    //   156: dup_x2
    //   157: iconst_1
    //   158: if_icmpgt -> 259
    //   161: dup2
    //   162: swap
    //   163: iload #6
    //   165: dup2_x1
    //   166: caload
    //   167: swap
    //   168: iload #6
    //   170: bipush #7
    //   172: irem
    //   173: tableswitch default -> 241, 0 -> 212, 1 -> 217, 2 -> 222, 3 -> 227, 4 -> 232, 5 -> 236
    //   212: bipush #12
    //   214: goto -> 243
    //   217: bipush #25
    //   219: goto -> 243
    //   222: bipush #95
    //   224: goto -> 243
    //   227: bipush #116
    //   229: goto -> 243
    //   232: iconst_2
    //   233: goto -> 243
    //   236: bipush #89
    //   238: goto -> 243
    //   241: bipush #119
    //   243: ixor
    //   244: ixor
    //   245: i2c
    //   246: castore
    //   247: iinc #6, 1
    //   250: dup
    //   251: ifne -> 259
    //   254: dup2
    //   255: dup_x1
    //   256: goto -> 165
    //   259: dup2_x1
    //   260: pop2
    //   261: dup_x2
    //   262: iload #6
    //   264: if_icmpgt -> 161
    //   267: pop
    //   268: new java/lang/String
    //   271: dup_x1
    //   272: swap
    //   273: invokespecial <init> : ([C)V
    //   276: invokevirtual intern : ()Ljava/lang/String;
    //   279: swap
    //   280: pop
    //   281: swap
    //   282: tableswitch default -> 39, 0 -> 98
    //   300: sipush #7757
    //   303: sipush #18537
    //   306: invokestatic a : (II)Ljava/lang/String;
    //   309: putstatic burp/Ze6k.ZM : Ljava/lang/String;
    //   312: new java/math/BigInteger
    //   315: dup
    //   316: sipush #7752
    //   319: sipush #-12041
    //   322: invokestatic a : (II)Ljava/lang/String;
    //   325: invokespecial <init> : (Ljava/lang/String;)V
    //   328: putstatic burp/Ze6k.Zs : Ljava/lang/Object;
    //   331: return
  }
  
  private static Throwable a(Throwable paramThrowable) {
    return paramThrowable;
  }
  
  private static String a(int paramInt1, int paramInt2) {
    int i = (paramInt1 ^ 0x1E4E) & 0xFFFF;
    if (b[i] == null) {
      char[] arrayOfChar = a[i].toCharArray();
      switch (arrayOfChar[0] & 0xFF) {
        case 0:
        
        case 1:
        
        case 2:
        
        case 3:
        
        case 4:
        
        case 5:
        
        case 6:
        
        case 7:
        
        case 8:
        
        case 9:
        
        case 10:
        
        case 11:
        
        case 12:
        
        case 13:
        
        case 14:
        
        case 15:
        
        case 16:
        
        case 17:
        
        case 18:
        
        case 19:
        
        case 20:
        
        case 21:
        
        case 22:
        
        case 23:
        
        case 24:
        
        case 25:
        
        case 26:
        
        case 27:
        
        case 28:
        
        case 29:
        
        case 30:
        
        case 31:
        
        case 32:
        
        case 33:
        
        case 34:
        
        case 35:
        
        case 36:
        
        case 37:
        
        case 38:
        
        case 39:
        
        case 40:
        
        case 41:
        
        case 42:
        
        case 43:
        
        case 44:
        
        case 45:
        
        case 46:
        
        case 47:
        
        case 48:
        
        case 49:
        
        case 50:
        
        case 51:
        
        case 52:
        
        case 53:
        
        case 54:
        
        case 55:
        
        case 56:
        
        case 57:
        
        case 58:
        
        case 59:
        
        case 60:
        
        case 61:
        
        case 62:
        
        case 63:
        
        case 64:
        
        case 65:
        
        case 66:
        
        case 67:
        
        case 68:
        
        case 69:
        
        case 70:
        
        case 71:
        
        case 72:
        
        case 73:
        
        case 74:
        
        case 75:
        
        case 76:
        
        case 77:
        
        case 78:
        
        case 79:
        
        case 80:
        
        case 81:
        
        case 82:
        
        case 83:
        
        case 84:
        
        case 85:
        
        case 86:
        
        case 87:
        
        case 88:
        
        case 89:
        
        case 90:
        
        case 91:
        
        case 92:
        
        case 93:
        
        case 94:
        
        case 95:
        
        case 96:
        
        case 97:
        
        case 98:
        
        case 99:
        
        case 100:
        
        case 101:
        
        case 102:
        
        case 103:
        
        case 104:
        
        case 105:
        
        case 106:
        
        case 107:
        
        case 108:
        
        case 109:
        
        case 110:
        
        case 111:
        
        case 112:
        
        case 113:
        
        case 114:
        
        case 115:
        
        case 116:
        
        case 117:
        
        case 118:
        
        case 119:
        
        case 120:
        
        case 121:
        
        case 122:
        
        case 123:
        
        case 124:
        
        case 125:
        
        case 126:
        
        case 127:
        
        case 128:
        
        case 129:
        
        case 130:
        
        case 131:
        
        case 132:
        
        case 133:
        
        case 134:
        
        case 135:
        
        case 136:
        
        case 137:
        
        case 138:
        
        case 139:
        
        case 140:
        
        case 141:
        
        case 142:
        
        case 143:
        
        case 144:
        
        case 145:
        
        case 146:
        
        case 147:
        
        case 148:
        
        case 149:
        
        case 150:
        
        case 151:
        
        case 152:
        
        case 153:
        
        case 154:
        
        case 155:
        
        case 156:
        
        case 157:
        
        case 158:
        
        case 159:
        
        case 160:
        
        case 161:
        
        case 162:
        
        case 163:
        
        case 164:
        
        case 165:
        
        case 166:
        
        case 167:
        
        case 168:
        
        case 169:
        
        case 170:
        
        case 171:
        
        case 172:
        
        case 173:
        
        case 174:
        
        case 175:
        
        case 176:
        
        case 177:
        
        case 178:
        
        case 179:
        
        case 180:
        
        case 181:
        
        case 182:
        
        case 183:
        
        case 184:
        
        case 185:
        
        case 186:
        
        case 187:
        
        case 188:
        
        case 189:
        
        case 190:
        
        case 191:
        
        case 192:
        
        case 193:
        
        case 194:
        
        case 195:
        
        case 196:
        
        case 197:
        
        case 198:
        
        case 199:
        
        case 200:
        
        case 201:
        
        case 202:
        
        case 203:
        
        case 204:
        
        case 205:
        
        case 206:
        
        case 207:
        
        case 208:
        
        case 209:
        
        case 210:
        
        case 211:
        
        case 212:
        
        case 213:
        
        case 214:
        
        case 215:
        
        case 216:
        
        case 217:
        
        case 218:
        
        case 219:
        
        case 220:
        
        case 221:
        
        case 222:
        
        case 223:
        
        case 224:
        
        case 225:
        
        case 226:
        
        case 227:
        
        case 228:
        
        case 229:
        
        case 230:
        
        case 231:
        
        case 232:
        
        case 233:
        
        case 234:
        
        case 235:
        
        case 236:
        
        case 237:
        
        case 238:
        
        case 239:
        
        case 240:
        
        case 241:
        
        case 242:
        
        case 243:
        
        case 244:
        
        case 245:
        
        case 246:
        
        case 247:
        
        case 248:
        
        case 249:
        
        case 250:
        
        case 251:
        
        case 252:
        
        case 253:
        
        case 254:
        
        default:
          break;
      } 
      byte b1 = 27;
      int j = (paramInt2 & 0xFF) - b1;
      if (j < 0)
        j += 256; 
      int k = ((paramInt2 & 0xFFFF) >>> 8) - b1;
      if (k < 0)
        k += 256; 
      for (byte b2 = 0; b2 < arrayOfChar.length; b2++) {
        int m = b2 % 2;
        if (m == 0) {
          arrayOfChar[b2] = (char)(arrayOfChar[b2] ^ j);
          j = ((j >>> 3 | j << 5) ^ arrayOfChar[b2]) & 0xFF;
        } else {
          arrayOfChar[b2] = (char)(arrayOfChar[b2] ^ k);
          k = ((k >>> 3 | k << 5) ^ arrayOfChar[b2]) & 0xFF;
        } 
      } 
      b[i] = (new String(arrayOfChar)).intern();
    } 
    return b[i];
  }
}


/* Location:              C:\Program Files\BurpSuitePro\burpsuite_pro.jar!\burp\Ze6k.class
 * Java compiler version: 21 (65.0)
 * JD-Core Version:       1.1.3
 */