package burp;

import java.math.BigInteger;

class Ze_b extends ClassLoader {
  static String ZX;
  
  static Object Zp;
  
  private static final String[] a;
  
  private static final String[] b;
  
  static void Zo(Object[] paramArrayOfObject, Object paramObject) throws Throwable {}
  
  static boolean ZR(Object[] paramArrayOfObject, Object paramObject) throws Throwable {
    // Byte code:
    //   0: invokestatic ZK : ()Z
    //   3: istore_2
    //   4: sipush #15039
    //   7: sipush #25481
    //   10: invokestatic a : (II)Ljava/lang/String;
    //   13: invokestatic forName : (Ljava/lang/String;)Ljava/lang/Class;
    //   16: invokestatic ZU : (Ljava/lang/Object;)V
    //   19: new java/lang/StringBuilder
    //   22: dup
    //   23: invokespecial <init> : ()V
    //   26: astore_3
    //   27: iconst_0
    //   28: istore #4
    //   30: iload #4
    //   32: bipush #32
    //   34: if_icmpge -> 1367
    //   37: iload #4
    //   39: tableswitch default -> 1360, 0 -> 180, 1 -> 217, 2 -> 254, 3 -> 291, 4 -> 328, 5 -> 365, 6 -> 402, 7 -> 439, 8 -> 476, 9 -> 513, 10 -> 550, 11 -> 587, 12 -> 624, 13 -> 661, 14 -> 698, 15 -> 735, 16 -> 772, 17 -> 809, 18 -> 846, 19 -> 883, 20 -> 920, 21 -> 957, 22 -> 994, 23 -> 1031, 24 -> 1068, 25 -> 1105, 26 -> 1142, 27 -> 1179, 28 -> 1216, 29 -> 1253, 30 -> 1290, 31 -> 1327
    //   180: aload_3
    //   181: getstatic burp/Zbu.ZV : Ljava/lang/String;
    //   184: getstatic burp/Zl2t.ZS : Ljava/lang/Object;
    //   187: checkcast java/math/BigInteger
    //   190: invokevirtual intValue : ()I
    //   193: bipush #32
    //   195: irem
    //   196: invokestatic abs : (I)I
    //   199: invokevirtual charAt : (I)C
    //   202: invokevirtual append : (C)Ljava/lang/StringBuilder;
    //   205: pop
    //   206: iload_2
    //   207: ifeq -> 1360
    //   210: goto -> 217
    //   213: invokestatic a : (Ljava/lang/Throwable;)Ljava/lang/Throwable;
    //   216: athrow
    //   217: aload_3
    //   218: getstatic burp/Zsin.ZC : Ljava/lang/String;
    //   221: getstatic burp/Zg68.Zs : Ljava/lang/Object;
    //   224: checkcast java/math/BigInteger
    //   227: invokevirtual intValue : ()I
    //   230: bipush #32
    //   232: irem
    //   233: invokestatic abs : (I)I
    //   236: invokevirtual charAt : (I)C
    //   239: invokevirtual append : (C)Ljava/lang/StringBuilder;
    //   242: pop
    //   243: iload_2
    //   244: ifeq -> 1360
    //   247: goto -> 254
    //   250: invokestatic a : (Ljava/lang/Throwable;)Ljava/lang/Throwable;
    //   253: athrow
    //   254: aload_3
    //   255: getstatic burp/Zd8.ZK : Ljava/lang/String;
    //   258: getstatic burp/Zer1.ZL : Ljava/lang/Object;
    //   261: checkcast java/math/BigInteger
    //   264: invokevirtual intValue : ()I
    //   267: bipush #32
    //   269: irem
    //   270: invokestatic abs : (I)I
    //   273: invokevirtual charAt : (I)C
    //   276: invokevirtual append : (C)Ljava/lang/StringBuilder;
    //   279: pop
    //   280: iload_2
    //   281: ifeq -> 1360
    //   284: goto -> 291
    //   287: invokestatic a : (Ljava/lang/Throwable;)Ljava/lang/Throwable;
    //   290: athrow
    //   291: aload_3
    //   292: getstatic burp/Zep8.ZC : Ljava/lang/String;
    //   295: getstatic burp/Zb8_.ZT : Ljava/lang/Object;
    //   298: checkcast java/math/BigInteger
    //   301: invokevirtual intValue : ()I
    //   304: bipush #32
    //   306: irem
    //   307: invokestatic abs : (I)I
    //   310: invokevirtual charAt : (I)C
    //   313: invokevirtual append : (C)Ljava/lang/StringBuilder;
    //   316: pop
    //   317: iload_2
    //   318: ifeq -> 1360
    //   321: goto -> 328
    //   324: invokestatic a : (Ljava/lang/Throwable;)Ljava/lang/Throwable;
    //   327: athrow
    //   328: aload_3
    //   329: getstatic burp/Zlbr.Zr : Ljava/lang/String;
    //   332: getstatic burp/Ztv8.ZS : Ljava/lang/Object;
    //   335: checkcast java/math/BigInteger
    //   338: invokevirtual intValue : ()I
    //   341: bipush #32
    //   343: irem
    //   344: invokestatic abs : (I)I
    //   347: invokevirtual charAt : (I)C
    //   350: invokevirtual append : (C)Ljava/lang/StringBuilder;
    //   353: pop
    //   354: iload_2
    //   355: ifeq -> 1360
    //   358: goto -> 365
    //   361: invokestatic a : (Ljava/lang/Throwable;)Ljava/lang/Throwable;
    //   364: athrow
    //   365: aload_3
    //   366: getstatic burp/Zl7k.ZX : Ljava/lang/String;
    //   369: getstatic burp/Zs5y.Zd : Ljava/lang/Object;
    //   372: checkcast java/math/BigInteger
    //   375: invokevirtual intValue : ()I
    //   378: bipush #32
    //   380: irem
    //   381: invokestatic abs : (I)I
    //   384: invokevirtual charAt : (I)C
    //   387: invokevirtual append : (C)Ljava/lang/StringBuilder;
    //   390: pop
    //   391: iload_2
    //   392: ifeq -> 1360
    //   395: goto -> 402
    //   398: invokestatic a : (Ljava/lang/Throwable;)Ljava/lang/Throwable;
    //   401: athrow
    //   402: aload_3
    //   403: getstatic burp/Zrhp.ZQ : Ljava/lang/String;
    //   406: getstatic burp/Zs56.ZC : Ljava/lang/Object;
    //   409: checkcast java/math/BigInteger
    //   412: invokevirtual intValue : ()I
    //   415: bipush #32
    //   417: irem
    //   418: invokestatic abs : (I)I
    //   421: invokevirtual charAt : (I)C
    //   424: invokevirtual append : (C)Ljava/lang/StringBuilder;
    //   427: pop
    //   428: iload_2
    //   429: ifeq -> 1360
    //   432: goto -> 439
    //   435: invokestatic a : (Ljava/lang/Throwable;)Ljava/lang/Throwable;
    //   438: athrow
    //   439: aload_3
    //   440: getstatic burp/Zl2g.ZI : Ljava/lang/String;
    //   443: getstatic burp/Zmtr.Zv : Ljava/lang/Object;
    //   446: checkcast java/math/BigInteger
    //   449: invokevirtual intValue : ()I
    //   452: bipush #32
    //   454: irem
    //   455: invokestatic abs : (I)I
    //   458: invokevirtual charAt : (I)C
    //   461: invokevirtual append : (C)Ljava/lang/StringBuilder;
    //   464: pop
    //   465: iload_2
    //   466: ifeq -> 1360
    //   469: goto -> 476
    //   472: invokestatic a : (Ljava/lang/Throwable;)Ljava/lang/Throwable;
    //   475: athrow
    //   476: aload_3
    //   477: getstatic burp/Zebu.ZI : Ljava/lang/String;
    //   480: getstatic burp/Zrnw.ZN : Ljava/lang/Object;
    //   483: checkcast java/math/BigInteger
    //   486: invokevirtual intValue : ()I
    //   489: bipush #32
    //   491: irem
    //   492: invokestatic abs : (I)I
    //   495: invokevirtual charAt : (I)C
    //   498: invokevirtual append : (C)Ljava/lang/StringBuilder;
    //   501: pop
    //   502: iload_2
    //   503: ifeq -> 1360
    //   506: goto -> 513
    //   509: invokestatic a : (Ljava/lang/Throwable;)Ljava/lang/Throwable;
    //   512: athrow
    //   513: aload_3
    //   514: getstatic burp/Zb20.ZL : Ljava/lang/String;
    //   517: getstatic burp/Zlh2.Zc : Ljava/lang/Object;
    //   520: checkcast java/math/BigInteger
    //   523: invokevirtual intValue : ()I
    //   526: bipush #32
    //   528: irem
    //   529: invokestatic abs : (I)I
    //   532: invokevirtual charAt : (I)C
    //   535: invokevirtual append : (C)Ljava/lang/StringBuilder;
    //   538: pop
    //   539: iload_2
    //   540: ifeq -> 1360
    //   543: goto -> 550
    //   546: invokestatic a : (Ljava/lang/Throwable;)Ljava/lang/Throwable;
    //   549: athrow
    //   550: aload_3
    //   551: getstatic burp/Zbsc.Zp : Ljava/lang/String;
    //   554: getstatic burp/Zevf.Zu : Ljava/lang/Object;
    //   557: checkcast java/math/BigInteger
    //   560: invokevirtual intValue : ()I
    //   563: bipush #32
    //   565: irem
    //   566: invokestatic abs : (I)I
    //   569: invokevirtual charAt : (I)C
    //   572: invokevirtual append : (C)Ljava/lang/StringBuilder;
    //   575: pop
    //   576: iload_2
    //   577: ifeq -> 1360
    //   580: goto -> 587
    //   583: invokestatic a : (Ljava/lang/Throwable;)Ljava/lang/Throwable;
    //   586: athrow
    //   587: aload_3
    //   588: getstatic burp/Zr5k.Zq : Ljava/lang/String;
    //   591: getstatic burp/Zx4k.ZE : Ljava/lang/Object;
    //   594: checkcast java/math/BigInteger
    //   597: invokevirtual intValue : ()I
    //   600: bipush #32
    //   602: irem
    //   603: invokestatic abs : (I)I
    //   606: invokevirtual charAt : (I)C
    //   609: invokevirtual append : (C)Ljava/lang/StringBuilder;
    //   612: pop
    //   613: iload_2
    //   614: ifeq -> 1360
    //   617: goto -> 624
    //   620: invokestatic a : (Ljava/lang/Throwable;)Ljava/lang/Throwable;
    //   623: athrow
    //   624: aload_3
    //   625: getstatic burp/Ze57.ZV : Ljava/lang/String;
    //   628: getstatic burp/Ztip.Zc : Ljava/lang/Object;
    //   631: checkcast java/math/BigInteger
    //   634: invokevirtual intValue : ()I
    //   637: bipush #32
    //   639: irem
    //   640: invokestatic abs : (I)I
    //   643: invokevirtual charAt : (I)C
    //   646: invokevirtual append : (C)Ljava/lang/StringBuilder;
    //   649: pop
    //   650: iload_2
    //   651: ifeq -> 1360
    //   654: goto -> 661
    //   657: invokestatic a : (Ljava/lang/Throwable;)Ljava/lang/Throwable;
    //   660: athrow
    //   661: aload_3
    //   662: getstatic burp/Zkul.ZJ : Ljava/lang/String;
    //   665: getstatic burp/Zlfi.ZV : Ljava/lang/Object;
    //   668: checkcast java/math/BigInteger
    //   671: invokevirtual intValue : ()I
    //   674: bipush #32
    //   676: irem
    //   677: invokestatic abs : (I)I
    //   680: invokevirtual charAt : (I)C
    //   683: invokevirtual append : (C)Ljava/lang/StringBuilder;
    //   686: pop
    //   687: iload_2
    //   688: ifeq -> 1360
    //   691: goto -> 698
    //   694: invokestatic a : (Ljava/lang/Throwable;)Ljava/lang/Throwable;
    //   697: athrow
    //   698: aload_3
    //   699: getstatic burp/Zram.Ze : Ljava/lang/String;
    //   702: getstatic burp/Zf.Zh : Ljava/lang/Object;
    //   705: checkcast java/math/BigInteger
    //   708: invokevirtual intValue : ()I
    //   711: bipush #32
    //   713: irem
    //   714: invokestatic abs : (I)I
    //   717: invokevirtual charAt : (I)C
    //   720: invokevirtual append : (C)Ljava/lang/StringBuilder;
    //   723: pop
    //   724: iload_2
    //   725: ifeq -> 1360
    //   728: goto -> 735
    //   731: invokestatic a : (Ljava/lang/Throwable;)Ljava/lang/Throwable;
    //   734: athrow
    //   735: aload_3
    //   736: getstatic burp/Zsvh.ZV : Ljava/lang/String;
    //   739: getstatic burp/Zlpn.ZU : Ljava/lang/Object;
    //   742: checkcast java/math/BigInteger
    //   745: invokevirtual intValue : ()I
    //   748: bipush #32
    //   750: irem
    //   751: invokestatic abs : (I)I
    //   754: invokevirtual charAt : (I)C
    //   757: invokevirtual append : (C)Ljava/lang/StringBuilder;
    //   760: pop
    //   761: iload_2
    //   762: ifeq -> 1360
    //   765: goto -> 772
    //   768: invokestatic a : (Ljava/lang/Throwable;)Ljava/lang/Throwable;
    //   771: athrow
    //   772: aload_3
    //   773: getstatic burp/Zzqj.Zk : Ljava/lang/String;
    //   776: getstatic burp/Zb6a.Zz : Ljava/lang/Object;
    //   779: checkcast java/math/BigInteger
    //   782: invokevirtual intValue : ()I
    //   785: bipush #32
    //   787: irem
    //   788: invokestatic abs : (I)I
    //   791: invokevirtual charAt : (I)C
    //   794: invokevirtual append : (C)Ljava/lang/StringBuilder;
    //   797: pop
    //   798: iload_2
    //   799: ifeq -> 1360
    //   802: goto -> 809
    //   805: invokestatic a : (Ljava/lang/Throwable;)Ljava/lang/Throwable;
    //   808: athrow
    //   809: aload_3
    //   810: getstatic burp/Zer.Zp : Ljava/lang/String;
    //   813: getstatic burp/Zle4.Zh : Ljava/lang/Object;
    //   816: checkcast java/math/BigInteger
    //   819: invokevirtual intValue : ()I
    //   822: bipush #32
    //   824: irem
    //   825: invokestatic abs : (I)I
    //   828: invokevirtual charAt : (I)C
    //   831: invokevirtual append : (C)Ljava/lang/StringBuilder;
    //   834: pop
    //   835: iload_2
    //   836: ifeq -> 1360
    //   839: goto -> 846
    //   842: invokestatic a : (Ljava/lang/Throwable;)Ljava/lang/Throwable;
    //   845: athrow
    //   846: aload_3
    //   847: getstatic burp/Zb8_.ZP : Ljava/lang/String;
    //   850: getstatic burp/Zer1.ZL : Ljava/lang/Object;
    //   853: checkcast java/math/BigInteger
    //   856: invokevirtual intValue : ()I
    //   859: bipush #32
    //   861: irem
    //   862: invokestatic abs : (I)I
    //   865: invokevirtual charAt : (I)C
    //   868: invokevirtual append : (C)Ljava/lang/StringBuilder;
    //   871: pop
    //   872: iload_2
    //   873: ifeq -> 1360
    //   876: goto -> 883
    //   879: invokestatic a : (Ljava/lang/Throwable;)Ljava/lang/Throwable;
    //   882: athrow
    //   883: aload_3
    //   884: getstatic burp/Zs56.ZW : Ljava/lang/String;
    //   887: getstatic burp/Zzmw.ZS : Ljava/lang/Object;
    //   890: checkcast java/math/BigInteger
    //   893: invokevirtual intValue : ()I
    //   896: bipush #32
    //   898: irem
    //   899: invokestatic abs : (I)I
    //   902: invokevirtual charAt : (I)C
    //   905: invokevirtual append : (C)Ljava/lang/StringBuilder;
    //   908: pop
    //   909: iload_2
    //   910: ifeq -> 1360
    //   913: goto -> 920
    //   916: invokestatic a : (Ljava/lang/Throwable;)Ljava/lang/Throwable;
    //   919: athrow
    //   920: aload_3
    //   921: getstatic burp/Zrug.Zq : Ljava/lang/String;
    //   924: getstatic burp/Zepm.Zp : Ljava/lang/Object;
    //   927: checkcast java/math/BigInteger
    //   930: invokevirtual intValue : ()I
    //   933: bipush #32
    //   935: irem
    //   936: invokestatic abs : (I)I
    //   939: invokevirtual charAt : (I)C
    //   942: invokevirtual append : (C)Ljava/lang/StringBuilder;
    //   945: pop
    //   946: iload_2
    //   947: ifeq -> 1360
    //   950: goto -> 957
    //   953: invokestatic a : (Ljava/lang/Throwable;)Ljava/lang/Throwable;
    //   956: athrow
    //   957: aload_3
    //   958: getstatic burp/Ztc2.Zr : Ljava/lang/String;
    //   961: getstatic burp/Zkq9.Ze : Ljava/lang/Object;
    //   964: checkcast java/math/BigInteger
    //   967: invokevirtual intValue : ()I
    //   970: bipush #32
    //   972: irem
    //   973: invokestatic abs : (I)I
    //   976: invokevirtual charAt : (I)C
    //   979: invokevirtual append : (C)Ljava/lang/StringBuilder;
    //   982: pop
    //   983: iload_2
    //   984: ifeq -> 1360
    //   987: goto -> 994
    //   990: invokestatic a : (Ljava/lang/Throwable;)Ljava/lang/Throwable;
    //   993: athrow
    //   994: aload_3
    //   995: getstatic burp/Ztcv.Zl : Ljava/lang/String;
    //   998: getstatic burp/Zscf.ZG : Ljava/lang/Object;
    //   1001: checkcast java/math/BigInteger
    //   1004: invokevirtual intValue : ()I
    //   1007: bipush #32
    //   1009: irem
    //   1010: invokestatic abs : (I)I
    //   1013: invokevirtual charAt : (I)C
    //   1016: invokevirtual append : (C)Ljava/lang/StringBuilder;
    //   1019: pop
    //   1020: iload_2
    //   1021: ifeq -> 1360
    //   1024: goto -> 1031
    //   1027: invokestatic a : (Ljava/lang/Throwable;)Ljava/lang/Throwable;
    //   1030: athrow
    //   1031: aload_3
    //   1032: getstatic burp/Ztkh.ZP : Ljava/lang/String;
    //   1035: getstatic burp/Ze08.ZJ : Ljava/lang/Object;
    //   1038: checkcast java/math/BigInteger
    //   1041: invokevirtual intValue : ()I
    //   1044: bipush #32
    //   1046: irem
    //   1047: invokestatic abs : (I)I
    //   1050: invokevirtual charAt : (I)C
    //   1053: invokevirtual append : (C)Ljava/lang/StringBuilder;
    //   1056: pop
    //   1057: iload_2
    //   1058: ifeq -> 1360
    //   1061: goto -> 1068
    //   1064: invokestatic a : (Ljava/lang/Throwable;)Ljava/lang/Throwable;
    //   1067: athrow
    //   1068: aload_3
    //   1069: getstatic burp/Zx5w.Zq : Ljava/lang/String;
    //   1072: getstatic burp/Zz0j.Zn : Ljava/lang/Object;
    //   1075: checkcast java/math/BigInteger
    //   1078: invokevirtual intValue : ()I
    //   1081: bipush #32
    //   1083: irem
    //   1084: invokestatic abs : (I)I
    //   1087: invokevirtual charAt : (I)C
    //   1090: invokevirtual append : (C)Ljava/lang/StringBuilder;
    //   1093: pop
    //   1094: iload_2
    //   1095: ifeq -> 1360
    //   1098: goto -> 1105
    //   1101: invokestatic a : (Ljava/lang/Throwable;)Ljava/lang/Throwable;
    //   1104: athrow
    //   1105: aload_3
    //   1106: getstatic burp/Zb9q.Zk : Ljava/lang/String;
    //   1109: getstatic burp/Ztmy.ZH : Ljava/lang/Object;
    //   1112: checkcast java/math/BigInteger
    //   1115: invokevirtual intValue : ()I
    //   1118: bipush #32
    //   1120: irem
    //   1121: invokestatic abs : (I)I
    //   1124: invokevirtual charAt : (I)C
    //   1127: invokevirtual append : (C)Ljava/lang/StringBuilder;
    //   1130: pop
    //   1131: iload_2
    //   1132: ifeq -> 1360
    //   1135: goto -> 1142
    //   1138: invokestatic a : (Ljava/lang/Throwable;)Ljava/lang/Throwable;
    //   1141: athrow
    //   1142: aload_3
    //   1143: getstatic burp/Zlno.ZM : Ljava/lang/String;
    //   1146: getstatic burp/Zt5a.Zs : Ljava/lang/Object;
    //   1149: checkcast java/math/BigInteger
    //   1152: invokevirtual intValue : ()I
    //   1155: bipush #32
    //   1157: irem
    //   1158: invokestatic abs : (I)I
    //   1161: invokevirtual charAt : (I)C
    //   1164: invokevirtual append : (C)Ljava/lang/StringBuilder;
    //   1167: pop
    //   1168: iload_2
    //   1169: ifeq -> 1360
    //   1172: goto -> 1179
    //   1175: invokestatic a : (Ljava/lang/Throwable;)Ljava/lang/Throwable;
    //   1178: athrow
    //   1179: aload_3
    //   1180: getstatic burp/Zmt_.ZH : Ljava/lang/String;
    //   1183: getstatic burp/Zg4d.Zm : Ljava/lang/Object;
    //   1186: checkcast java/math/BigInteger
    //   1189: invokevirtual intValue : ()I
    //   1192: bipush #32
    //   1194: irem
    //   1195: invokestatic abs : (I)I
    //   1198: invokevirtual charAt : (I)C
    //   1201: invokevirtual append : (C)Ljava/lang/StringBuilder;
    //   1204: pop
    //   1205: iload_2
    //   1206: ifeq -> 1360
    //   1209: goto -> 1216
    //   1212: invokestatic a : (Ljava/lang/Throwable;)Ljava/lang/Throwable;
    //   1215: athrow
    //   1216: aload_3
    //   1217: getstatic burp/Zgx6.ZX : Ljava/lang/String;
    //   1220: getstatic burp/Zb_u.Zp : Ljava/lang/Object;
    //   1223: checkcast java/math/BigInteger
    //   1226: invokevirtual intValue : ()I
    //   1229: bipush #32
    //   1231: irem
    //   1232: invokestatic abs : (I)I
    //   1235: invokevirtual charAt : (I)C
    //   1238: invokevirtual append : (C)Ljava/lang/StringBuilder;
    //   1241: pop
    //   1242: iload_2
    //   1243: ifeq -> 1360
    //   1246: goto -> 1253
    //   1249: invokestatic a : (Ljava/lang/Throwable;)Ljava/lang/Throwable;
    //   1252: athrow
    //   1253: aload_3
    //   1254: getstatic burp/Zrt9.Zc : Ljava/lang/String;
    //   1257: getstatic burp/Zzi_.Zf : Ljava/lang/Object;
    //   1260: checkcast java/math/BigInteger
    //   1263: invokevirtual intValue : ()I
    //   1266: bipush #32
    //   1268: irem
    //   1269: invokestatic abs : (I)I
    //   1272: invokevirtual charAt : (I)C
    //   1275: invokevirtual append : (C)Ljava/lang/StringBuilder;
    //   1278: pop
    //   1279: iload_2
    //   1280: ifeq -> 1360
    //   1283: goto -> 1290
    //   1286: invokestatic a : (Ljava/lang/Throwable;)Ljava/lang/Throwable;
    //   1289: athrow
    //   1290: aload_3
    //   1291: getstatic burp/Zes_.ZM : Ljava/lang/String;
    //   1294: getstatic burp/Zlfg.Zv : Ljava/lang/Object;
    //   1297: checkcast java/math/BigInteger
    //   1300: invokevirtual intValue : ()I
    //   1303: bipush #32
    //   1305: irem
    //   1306: invokestatic abs : (I)I
    //   1309: invokevirtual charAt : (I)C
    //   1312: invokevirtual append : (C)Ljava/lang/StringBuilder;
    //   1315: pop
    //   1316: iload_2
    //   1317: ifeq -> 1360
    //   1320: goto -> 1327
    //   1323: invokestatic a : (Ljava/lang/Throwable;)Ljava/lang/Throwable;
    //   1326: athrow
    //   1327: aload_3
    //   1328: getstatic burp/Zzo5.ZX : Ljava/lang/String;
    //   1331: getstatic burp/Zkjr.Zw : Ljava/lang/Object;
    //   1334: checkcast java/math/BigInteger
    //   1337: invokevirtual intValue : ()I
    //   1340: bipush #32
    //   1342: irem
    //   1343: invokestatic abs : (I)I
    //   1346: invokevirtual charAt : (I)C
    //   1349: invokevirtual append : (C)Ljava/lang/StringBuilder;
    //   1352: pop
    //   1353: goto -> 1360
    //   1356: invokestatic a : (Ljava/lang/Throwable;)Ljava/lang/Throwable;
    //   1359: athrow
    //   1360: iinc #4, 1
    //   1363: iload_2
    //   1364: ifeq -> 30
    //   1367: aload_3
    //   1368: invokevirtual toString : ()Ljava/lang/String;
    //   1371: putstatic burp/Zetv.ZE : Ljava/lang/String;
    //   1374: new java/lang/StringBuilder
    //   1377: dup
    //   1378: invokespecial <init> : ()V
    //   1381: astore #4
    //   1383: iconst_0
    //   1384: istore #5
    //   1386: iload #5
    //   1388: bipush #32
    //   1390: if_icmpge -> 2755
    //   1393: iload #5
    //   1395: tableswitch default -> 2748, 0 -> 1536, 1 -> 1574, 2 -> 1612, 3 -> 1650, 4 -> 1688, 5 -> 1726, 6 -> 1764, 7 -> 1802, 8 -> 1840, 9 -> 1878, 10 -> 1916, 11 -> 1954, 12 -> 1992, 13 -> 2030, 14 -> 2068, 15 -> 2106, 16 -> 2144, 17 -> 2182, 18 -> 2220, 19 -> 2258, 20 -> 2296, 21 -> 2334, 22 -> 2372, 23 -> 2410, 24 -> 2448, 25 -> 2486, 26 -> 2524, 27 -> 2562, 28 -> 2600, 29 -> 2638, 30 -> 2676, 31 -> 2714
    //   1536: aload #4
    //   1538: getstatic burp/Ze57.ZV : Ljava/lang/String;
    //   1541: getstatic burp/Zec_.ZN : Ljava/lang/Object;
    //   1544: checkcast java/math/BigInteger
    //   1547: invokevirtual intValue : ()I
    //   1550: bipush #32
    //   1552: irem
    //   1553: invokestatic abs : (I)I
    //   1556: invokevirtual charAt : (I)C
    //   1559: invokevirtual append : (C)Ljava/lang/StringBuilder;
    //   1562: pop
    //   1563: iload_2
    //   1564: ifeq -> 2748
    //   1567: goto -> 1574
    //   1570: invokestatic a : (Ljava/lang/Throwable;)Ljava/lang/Throwable;
    //   1573: athrow
    //   1574: aload #4
    //   1576: getstatic burp/Zlwm.Zj : Ljava/lang/String;
    //   1579: getstatic burp/Ztpg.Z_ : Ljava/lang/Object;
    //   1582: checkcast java/math/BigInteger
    //   1585: invokevirtual intValue : ()I
    //   1588: bipush #32
    //   1590: irem
    //   1591: invokestatic abs : (I)I
    //   1594: invokevirtual charAt : (I)C
    //   1597: invokevirtual append : (C)Ljava/lang/StringBuilder;
    //   1600: pop
    //   1601: iload_2
    //   1602: ifeq -> 2748
    //   1605: goto -> 1612
    //   1608: invokestatic a : (Ljava/lang/Throwable;)Ljava/lang/Throwable;
    //   1611: athrow
    //   1612: aload #4
    //   1614: getstatic burp/Zm81.ZY : Ljava/lang/String;
    //   1617: getstatic burp/Zblv.Zf : Ljava/lang/Object;
    //   1620: checkcast java/math/BigInteger
    //   1623: invokevirtual intValue : ()I
    //   1626: bipush #32
    //   1628: irem
    //   1629: invokestatic abs : (I)I
    //   1632: invokevirtual charAt : (I)C
    //   1635: invokevirtual append : (C)Ljava/lang/StringBuilder;
    //   1638: pop
    //   1639: iload_2
    //   1640: ifeq -> 2748
    //   1643: goto -> 1650
    //   1646: invokestatic a : (Ljava/lang/Throwable;)Ljava/lang/Throwable;
    //   1649: athrow
    //   1650: aload #4
    //   1652: getstatic burp/Zel.Zi : Ljava/lang/String;
    //   1655: getstatic burp/Zml2.Zo : Ljava/lang/Object;
    //   1658: checkcast java/math/BigInteger
    //   1661: invokevirtual intValue : ()I
    //   1664: bipush #32
    //   1666: irem
    //   1667: invokestatic abs : (I)I
    //   1670: invokevirtual charAt : (I)C
    //   1673: invokevirtual append : (C)Ljava/lang/StringBuilder;
    //   1676: pop
    //   1677: iload_2
    //   1678: ifeq -> 2748
    //   1681: goto -> 1688
    //   1684: invokestatic a : (Ljava/lang/Throwable;)Ljava/lang/Throwable;
    //   1687: athrow
    //   1688: aload #4
    //   1690: getstatic burp/Zgnp.ZL : Ljava/lang/String;
    //   1693: getstatic burp/Zxee.Zj : Ljava/lang/Object;
    //   1696: checkcast java/math/BigInteger
    //   1699: invokevirtual intValue : ()I
    //   1702: bipush #32
    //   1704: irem
    //   1705: invokestatic abs : (I)I
    //   1708: invokevirtual charAt : (I)C
    //   1711: invokevirtual append : (C)Ljava/lang/StringBuilder;
    //   1714: pop
    //   1715: iload_2
    //   1716: ifeq -> 2748
    //   1719: goto -> 1726
    //   1722: invokestatic a : (Ljava/lang/Throwable;)Ljava/lang/Throwable;
    //   1725: athrow
    //   1726: aload #4
    //   1728: getstatic burp/Zenq.ZG : Ljava/lang/String;
    //   1731: getstatic burp/Zx_x.Zi : Ljava/lang/Object;
    //   1734: checkcast java/math/BigInteger
    //   1737: invokevirtual intValue : ()I
    //   1740: bipush #32
    //   1742: irem
    //   1743: invokestatic abs : (I)I
    //   1746: invokevirtual charAt : (I)C
    //   1749: invokevirtual append : (C)Ljava/lang/StringBuilder;
    //   1752: pop
    //   1753: iload_2
    //   1754: ifeq -> 2748
    //   1757: goto -> 1764
    //   1760: invokestatic a : (Ljava/lang/Throwable;)Ljava/lang/Throwable;
    //   1763: athrow
    //   1764: aload #4
    //   1766: getstatic burp/Zx4y.Zh : Ljava/lang/String;
    //   1769: getstatic burp/Zr3j.ZT : Ljava/lang/Object;
    //   1772: checkcast java/math/BigInteger
    //   1775: invokevirtual intValue : ()I
    //   1778: bipush #32
    //   1780: irem
    //   1781: invokestatic abs : (I)I
    //   1784: invokevirtual charAt : (I)C
    //   1787: invokevirtual append : (C)Ljava/lang/StringBuilder;
    //   1790: pop
    //   1791: iload_2
    //   1792: ifeq -> 2748
    //   1795: goto -> 1802
    //   1798: invokestatic a : (Ljava/lang/Throwable;)Ljava/lang/Throwable;
    //   1801: athrow
    //   1802: aload #4
    //   1804: getstatic burp/Zl3n.Zy : Ljava/lang/String;
    //   1807: getstatic burp/Zgyc.ZT : Ljava/lang/Object;
    //   1810: checkcast java/math/BigInteger
    //   1813: invokevirtual intValue : ()I
    //   1816: bipush #32
    //   1818: irem
    //   1819: invokestatic abs : (I)I
    //   1822: invokevirtual charAt : (I)C
    //   1825: invokevirtual append : (C)Ljava/lang/StringBuilder;
    //   1828: pop
    //   1829: iload_2
    //   1830: ifeq -> 2748
    //   1833: goto -> 1840
    //   1836: invokestatic a : (Ljava/lang/Throwable;)Ljava/lang/Throwable;
    //   1839: athrow
    //   1840: aload #4
    //   1842: getstatic burp/Zmir.ZI : Ljava/lang/String;
    //   1845: getstatic burp/Zrw7.ZV : Ljava/lang/Object;
    //   1848: checkcast java/math/BigInteger
    //   1851: invokevirtual intValue : ()I
    //   1854: bipush #32
    //   1856: irem
    //   1857: invokestatic abs : (I)I
    //   1860: invokevirtual charAt : (I)C
    //   1863: invokevirtual append : (C)Ljava/lang/StringBuilder;
    //   1866: pop
    //   1867: iload_2
    //   1868: ifeq -> 2748
    //   1871: goto -> 1878
    //   1874: invokestatic a : (Ljava/lang/Throwable;)Ljava/lang/Throwable;
    //   1877: athrow
    //   1878: aload #4
    //   1880: getstatic burp/Zrd4.Zg : Ljava/lang/String;
    //   1883: getstatic burp/Zrc0.Zz : Ljava/lang/Object;
    //   1886: checkcast java/math/BigInteger
    //   1889: invokevirtual intValue : ()I
    //   1892: bipush #32
    //   1894: irem
    //   1895: invokestatic abs : (I)I
    //   1898: invokevirtual charAt : (I)C
    //   1901: invokevirtual append : (C)Ljava/lang/StringBuilder;
    //   1904: pop
    //   1905: iload_2
    //   1906: ifeq -> 2748
    //   1909: goto -> 1916
    //   1912: invokestatic a : (Ljava/lang/Throwable;)Ljava/lang/Throwable;
    //   1915: athrow
    //   1916: aload #4
    //   1918: getstatic burp/Zsq6.Zm : Ljava/lang/String;
    //   1921: getstatic burp/Zlwm.Ze : Ljava/lang/Object;
    //   1924: checkcast java/math/BigInteger
    //   1927: invokevirtual intValue : ()I
    //   1930: bipush #32
    //   1932: irem
    //   1933: invokestatic abs : (I)I
    //   1936: invokevirtual charAt : (I)C
    //   1939: invokevirtual append : (C)Ljava/lang/StringBuilder;
    //   1942: pop
    //   1943: iload_2
    //   1944: ifeq -> 2748
    //   1947: goto -> 1954
    //   1950: invokestatic a : (Ljava/lang/Throwable;)Ljava/lang/Throwable;
    //   1953: athrow
    //   1954: aload #4
    //   1956: getstatic burp/Zsm3.Zl : Ljava/lang/String;
    //   1959: getstatic burp/Zml.ZR : Ljava/lang/Object;
    //   1962: checkcast java/math/BigInteger
    //   1965: invokevirtual intValue : ()I
    //   1968: bipush #32
    //   1970: irem
    //   1971: invokestatic abs : (I)I
    //   1974: invokevirtual charAt : (I)C
    //   1977: invokevirtual append : (C)Ljava/lang/StringBuilder;
    //   1980: pop
    //   1981: iload_2
    //   1982: ifeq -> 2748
    //   1985: goto -> 1992
    //   1988: invokestatic a : (Ljava/lang/Throwable;)Ljava/lang/Throwable;
    //   1991: athrow
    //   1992: aload #4
    //   1994: getstatic burp/Zkk2.ZI : Ljava/lang/String;
    //   1997: getstatic burp/Ze_l.ZX : Ljava/lang/Object;
    //   2000: checkcast java/math/BigInteger
    //   2003: invokevirtual intValue : ()I
    //   2006: bipush #32
    //   2008: irem
    //   2009: invokestatic abs : (I)I
    //   2012: invokevirtual charAt : (I)C
    //   2015: invokevirtual append : (C)Ljava/lang/StringBuilder;
    //   2018: pop
    //   2019: iload_2
    //   2020: ifeq -> 2748
    //   2023: goto -> 2030
    //   2026: invokestatic a : (Ljava/lang/Throwable;)Ljava/lang/Throwable;
    //   2029: athrow
    //   2030: aload #4
    //   2032: getstatic burp/Zsf3.Zb : Ljava/lang/String;
    //   2035: getstatic burp/Ztip.Zc : Ljava/lang/Object;
    //   2038: checkcast java/math/BigInteger
    //   2041: invokevirtual intValue : ()I
    //   2044: bipush #32
    //   2046: irem
    //   2047: invokestatic abs : (I)I
    //   2050: invokevirtual charAt : (I)C
    //   2053: invokevirtual append : (C)Ljava/lang/StringBuilder;
    //   2056: pop
    //   2057: iload_2
    //   2058: ifeq -> 2748
    //   2061: goto -> 2068
    //   2064: invokestatic a : (Ljava/lang/Throwable;)Ljava/lang/Throwable;
    //   2067: athrow
    //   2068: aload #4
    //   2070: getstatic burp/Zmuj.ZG : Ljava/lang/String;
    //   2073: getstatic burp/Zg_5.ZA : Ljava/lang/Object;
    //   2076: checkcast java/math/BigInteger
    //   2079: invokevirtual intValue : ()I
    //   2082: bipush #32
    //   2084: irem
    //   2085: invokestatic abs : (I)I
    //   2088: invokevirtual charAt : (I)C
    //   2091: invokevirtual append : (C)Ljava/lang/StringBuilder;
    //   2094: pop
    //   2095: iload_2
    //   2096: ifeq -> 2748
    //   2099: goto -> 2106
    //   2102: invokestatic a : (Ljava/lang/Throwable;)Ljava/lang/Throwable;
    //   2105: athrow
    //   2106: aload #4
    //   2108: getstatic burp/Zli5.Zq : Ljava/lang/String;
    //   2111: getstatic burp/Zg1l.Zg : Ljava/lang/Object;
    //   2114: checkcast java/math/BigInteger
    //   2117: invokevirtual intValue : ()I
    //   2120: bipush #32
    //   2122: irem
    //   2123: invokestatic abs : (I)I
    //   2126: invokevirtual charAt : (I)C
    //   2129: invokevirtual append : (C)Ljava/lang/StringBuilder;
    //   2132: pop
    //   2133: iload_2
    //   2134: ifeq -> 2748
    //   2137: goto -> 2144
    //   2140: invokestatic a : (Ljava/lang/Throwable;)Ljava/lang/Throwable;
    //   2143: athrow
    //   2144: aload #4
    //   2146: getstatic burp/Zrye.Za : Ljava/lang/String;
    //   2149: getstatic burp/Zrx5.ZE : Ljava/lang/Object;
    //   2152: checkcast java/math/BigInteger
    //   2155: invokevirtual intValue : ()I
    //   2158: bipush #32
    //   2160: irem
    //   2161: invokestatic abs : (I)I
    //   2164: invokevirtual charAt : (I)C
    //   2167: invokevirtual append : (C)Ljava/lang/StringBuilder;
    //   2170: pop
    //   2171: iload_2
    //   2172: ifeq -> 2748
    //   2175: goto -> 2182
    //   2178: invokestatic a : (Ljava/lang/Throwable;)Ljava/lang/Throwable;
    //   2181: athrow
    //   2182: aload #4
    //   2184: getstatic burp/Zzvr.Zc : Ljava/lang/String;
    //   2187: getstatic burp/Zgd7.ZZ : Ljava/lang/Object;
    //   2190: checkcast java/math/BigInteger
    //   2193: invokevirtual intValue : ()I
    //   2196: bipush #32
    //   2198: irem
    //   2199: invokestatic abs : (I)I
    //   2202: invokevirtual charAt : (I)C
    //   2205: invokevirtual append : (C)Ljava/lang/StringBuilder;
    //   2208: pop
    //   2209: iload_2
    //   2210: ifeq -> 2748
    //   2213: goto -> 2220
    //   2216: invokestatic a : (Ljava/lang/Throwable;)Ljava/lang/Throwable;
    //   2219: athrow
    //   2220: aload #4
    //   2222: getstatic burp/Zeor.Zj : Ljava/lang/String;
    //   2225: getstatic burp/Zr04.ZB : Ljava/lang/Object;
    //   2228: checkcast java/math/BigInteger
    //   2231: invokevirtual intValue : ()I
    //   2234: bipush #32
    //   2236: irem
    //   2237: invokestatic abs : (I)I
    //   2240: invokevirtual charAt : (I)C
    //   2243: invokevirtual append : (C)Ljava/lang/StringBuilder;
    //   2246: pop
    //   2247: iload_2
    //   2248: ifeq -> 2748
    //   2251: goto -> 2258
    //   2254: invokestatic a : (Ljava/lang/Throwable;)Ljava/lang/Throwable;
    //   2257: athrow
    //   2258: aload #4
    //   2260: getstatic burp/Zm6g.ZG : Ljava/lang/String;
    //   2263: getstatic burp/Zr9p.ZC : Ljava/lang/Object;
    //   2266: checkcast java/math/BigInteger
    //   2269: invokevirtual intValue : ()I
    //   2272: bipush #32
    //   2274: irem
    //   2275: invokestatic abs : (I)I
    //   2278: invokevirtual charAt : (I)C
    //   2281: invokevirtual append : (C)Ljava/lang/StringBuilder;
    //   2284: pop
    //   2285: iload_2
    //   2286: ifeq -> 2748
    //   2289: goto -> 2296
    //   2292: invokestatic a : (Ljava/lang/Throwable;)Ljava/lang/Throwable;
    //   2295: athrow
    //   2296: aload #4
    //   2298: getstatic burp/Zlb6.ZP : Ljava/lang/String;
    //   2301: getstatic burp/Zl50.ZV : Ljava/lang/Object;
    //   2304: checkcast java/math/BigInteger
    //   2307: invokevirtual intValue : ()I
    //   2310: bipush #32
    //   2312: irem
    //   2313: invokestatic abs : (I)I
    //   2316: invokevirtual charAt : (I)C
    //   2319: invokevirtual append : (C)Ljava/lang/StringBuilder;
    //   2322: pop
    //   2323: iload_2
    //   2324: ifeq -> 2748
    //   2327: goto -> 2334
    //   2330: invokestatic a : (Ljava/lang/Throwable;)Ljava/lang/Throwable;
    //   2333: athrow
    //   2334: aload #4
    //   2336: getstatic burp/Zkm0.ZL : Ljava/lang/String;
    //   2339: getstatic burp/Zevc.Zm : Ljava/lang/Object;
    //   2342: checkcast java/math/BigInteger
    //   2345: invokevirtual intValue : ()I
    //   2348: bipush #32
    //   2350: irem
    //   2351: invokestatic abs : (I)I
    //   2354: invokevirtual charAt : (I)C
    //   2357: invokevirtual append : (C)Ljava/lang/StringBuilder;
    //   2360: pop
    //   2361: iload_2
    //   2362: ifeq -> 2748
    //   2365: goto -> 2372
    //   2368: invokestatic a : (Ljava/lang/Throwable;)Ljava/lang/Throwable;
    //   2371: athrow
    //   2372: aload #4
    //   2374: getstatic burp/Zg_i.ZW : Ljava/lang/String;
    //   2377: getstatic burp/Zsin.Za : Ljava/lang/Object;
    //   2380: checkcast java/math/BigInteger
    //   2383: invokevirtual intValue : ()I
    //   2386: bipush #32
    //   2388: irem
    //   2389: invokestatic abs : (I)I
    //   2392: invokevirtual charAt : (I)C
    //   2395: invokevirtual append : (C)Ljava/lang/StringBuilder;
    //   2398: pop
    //   2399: iload_2
    //   2400: ifeq -> 2748
    //   2403: goto -> 2410
    //   2406: invokestatic a : (Ljava/lang/Throwable;)Ljava/lang/Throwable;
    //   2409: athrow
    //   2410: aload #4
    //   2412: getstatic burp/Zlr2.ZV : Ljava/lang/String;
    //   2415: getstatic burp/Zz7j.ZR : Ljava/lang/Object;
    //   2418: checkcast java/math/BigInteger
    //   2421: invokevirtual intValue : ()I
    //   2424: bipush #32
    //   2426: irem
    //   2427: invokestatic abs : (I)I
    //   2430: invokevirtual charAt : (I)C
    //   2433: invokevirtual append : (C)Ljava/lang/StringBuilder;
    //   2436: pop
    //   2437: iload_2
    //   2438: ifeq -> 2748
    //   2441: goto -> 2448
    //   2444: invokestatic a : (Ljava/lang/Throwable;)Ljava/lang/Throwable;
    //   2447: athrow
    //   2448: aload #4
    //   2450: getstatic burp/Zr_y.Zb : Ljava/lang/String;
    //   2453: getstatic burp/Zmt_.Zl : Ljava/lang/Object;
    //   2456: checkcast java/math/BigInteger
    //   2459: invokevirtual intValue : ()I
    //   2462: bipush #32
    //   2464: irem
    //   2465: invokestatic abs : (I)I
    //   2468: invokevirtual charAt : (I)C
    //   2471: invokevirtual append : (C)Ljava/lang/StringBuilder;
    //   2474: pop
    //   2475: iload_2
    //   2476: ifeq -> 2748
    //   2479: goto -> 2486
    //   2482: invokestatic a : (Ljava/lang/Throwable;)Ljava/lang/Throwable;
    //   2485: athrow
    //   2486: aload #4
    //   2488: getstatic burp/Zx5w.Zq : Ljava/lang/String;
    //   2491: getstatic burp/Zkqx.ZW : Ljava/lang/Object;
    //   2494: checkcast java/math/BigInteger
    //   2497: invokevirtual intValue : ()I
    //   2500: bipush #32
    //   2502: irem
    //   2503: invokestatic abs : (I)I
    //   2506: invokevirtual charAt : (I)C
    //   2509: invokevirtual append : (C)Ljava/lang/StringBuilder;
    //   2512: pop
    //   2513: iload_2
    //   2514: ifeq -> 2748
    //   2517: goto -> 2524
    //   2520: invokestatic a : (Ljava/lang/Throwable;)Ljava/lang/Throwable;
    //   2523: athrow
    //   2524: aload #4
    //   2526: getstatic burp/Zbsr.Zq : Ljava/lang/String;
    //   2529: getstatic burp/Zlxh.ZU : Ljava/lang/Object;
    //   2532: checkcast java/math/BigInteger
    //   2535: invokevirtual intValue : ()I
    //   2538: bipush #32
    //   2540: irem
    //   2541: invokestatic abs : (I)I
    //   2544: invokevirtual charAt : (I)C
    //   2547: invokevirtual append : (C)Ljava/lang/StringBuilder;
    //   2550: pop
    //   2551: iload_2
    //   2552: ifeq -> 2748
    //   2555: goto -> 2562
    //   2558: invokestatic a : (Ljava/lang/Throwable;)Ljava/lang/Throwable;
    //   2561: athrow
    //   2562: aload #4
    //   2564: getstatic burp/Zs_3.ZC : Ljava/lang/String;
    //   2567: getstatic burp/Zlc5.ZH : Ljava/lang/Object;
    //   2570: checkcast java/math/BigInteger
    //   2573: invokevirtual intValue : ()I
    //   2576: bipush #32
    //   2578: irem
    //   2579: invokestatic abs : (I)I
    //   2582: invokevirtual charAt : (I)C
    //   2585: invokevirtual append : (C)Ljava/lang/StringBuilder;
    //   2588: pop
    //   2589: iload_2
    //   2590: ifeq -> 2748
    //   2593: goto -> 2600
    //   2596: invokestatic a : (Ljava/lang/Throwable;)Ljava/lang/Throwable;
    //   2599: athrow
    //   2600: aload #4
    //   2602: getstatic burp/Zlpl.ZO : Ljava/lang/String;
    //   2605: getstatic burp/Zm5p.Ze : Ljava/lang/Object;
    //   2608: checkcast java/math/BigInteger
    //   2611: invokevirtual intValue : ()I
    //   2614: bipush #32
    //   2616: irem
    //   2617: invokestatic abs : (I)I
    //   2620: invokevirtual charAt : (I)C
    //   2623: invokevirtual append : (C)Ljava/lang/StringBuilder;
    //   2626: pop
    //   2627: iload_2
    //   2628: ifeq -> 2748
    //   2631: goto -> 2638
    //   2634: invokestatic a : (Ljava/lang/Throwable;)Ljava/lang/Throwable;
    //   2637: athrow
    //   2638: aload #4
    //   2640: getstatic burp/Zero.ZL : Ljava/lang/String;
    //   2643: getstatic burp/Zsot.ZJ : Ljava/lang/Object;
    //   2646: checkcast java/math/BigInteger
    //   2649: invokevirtual intValue : ()I
    //   2652: bipush #32
    //   2654: irem
    //   2655: invokestatic abs : (I)I
    //   2658: invokevirtual charAt : (I)C
    //   2661: invokevirtual append : (C)Ljava/lang/StringBuilder;
    //   2664: pop
    //   2665: iload_2
    //   2666: ifeq -> 2748
    //   2669: goto -> 2676
    //   2672: invokestatic a : (Ljava/lang/Throwable;)Ljava/lang/Throwable;
    //   2675: athrow
    //   2676: aload #4
    //   2678: getstatic burp/Zsxm.Zq : Ljava/lang/String;
    //   2681: getstatic burp/Zr_w.ZK : Ljava/lang/Object;
    //   2684: checkcast java/math/BigInteger
    //   2687: invokevirtual intValue : ()I
    //   2690: bipush #32
    //   2692: irem
    //   2693: invokestatic abs : (I)I
    //   2696: invokevirtual charAt : (I)C
    //   2699: invokevirtual append : (C)Ljava/lang/StringBuilder;
    //   2702: pop
    //   2703: iload_2
    //   2704: ifeq -> 2748
    //   2707: goto -> 2714
    //   2710: invokestatic a : (Ljava/lang/Throwable;)Ljava/lang/Throwable;
    //   2713: athrow
    //   2714: aload #4
    //   2716: getstatic burp/Zzgh.Zn : Ljava/lang/String;
    //   2719: getstatic burp/Zemp.Zr : Ljava/lang/Object;
    //   2722: checkcast java/math/BigInteger
    //   2725: invokevirtual intValue : ()I
    //   2728: bipush #32
    //   2730: irem
    //   2731: invokestatic abs : (I)I
    //   2734: invokevirtual charAt : (I)C
    //   2737: invokevirtual append : (C)Ljava/lang/StringBuilder;
    //   2740: pop
    //   2741: goto -> 2748
    //   2744: invokestatic a : (Ljava/lang/Throwable;)Ljava/lang/Throwable;
    //   2747: athrow
    //   2748: iinc #5, 1
    //   2751: iload_2
    //   2752: ifeq -> 1386
    //   2755: aload #4
    //   2757: invokevirtual toString : ()Ljava/lang/String;
    //   2760: putstatic burp/Zl8s.Zn : Ljava/lang/String;
    //   2763: sipush #15026
    //   2766: sipush #-11325
    //   2769: invokestatic a : (II)Ljava/lang/String;
    //   2772: iconst_1
    //   2773: ldc burp/Zlp8
    //   2775: invokevirtual getClassLoader : ()Ljava/lang/ClassLoader;
    //   2778: invokestatic forName : (Ljava/lang/String;ZLjava/lang/ClassLoader;)Ljava/lang/Class;
    //   2781: invokevirtual getDeclaredFields : ()[Ljava/lang/reflect/Field;
    //   2784: astore #5
    //   2786: aload #5
    //   2788: arraylength
    //   2789: istore #6
    //   2791: iconst_0
    //   2792: istore #7
    //   2794: iload #7
    //   2796: iload #6
    //   2798: if_icmpge -> 2936
    //   2801: aload #5
    //   2803: iload #7
    //   2805: aaload
    //   2806: astore #8
    //   2808: aload #8
    //   2810: invokevirtual getModifiers : ()I
    //   2813: invokestatic isStatic : (I)Z
    //   2816: ifne -> 2826
    //   2819: goto -> 2929
    //   2822: invokestatic a : (Ljava/lang/Throwable;)Ljava/lang/Throwable;
    //   2825: athrow
    //   2826: aload #8
    //   2828: invokevirtual getType : ()Ljava/lang/Class;
    //   2831: astore #9
    //   2833: aload #9
    //   2835: ifnull -> 2916
    //   2838: aload #9
    //   2840: invokevirtual isPrimitive : ()Z
    //   2843: ifne -> 2916
    //   2846: goto -> 2853
    //   2849: invokestatic a : (Ljava/lang/Throwable;)Ljava/lang/Throwable;
    //   2852: athrow
    //   2853: aload #9
    //   2855: invokevirtual getPackage : ()Ljava/lang/Package;
    //   2858: ifnull -> 2916
    //   2861: goto -> 2868
    //   2864: invokestatic a : (Ljava/lang/Throwable;)Ljava/lang/Throwable;
    //   2867: athrow
    //   2868: aload #9
    //   2870: invokevirtual getPackage : ()Ljava/lang/Package;
    //   2873: invokevirtual getName : ()Ljava/lang/String;
    //   2876: ifnull -> 2916
    //   2879: goto -> 2886
    //   2882: invokestatic a : (Ljava/lang/Throwable;)Ljava/lang/Throwable;
    //   2885: athrow
    //   2886: aload #9
    //   2888: invokevirtual getPackage : ()Ljava/lang/Package;
    //   2891: invokevirtual getName : ()Ljava/lang/String;
    //   2894: sipush #15036
    //   2897: sipush #17845
    //   2900: invokestatic a : (II)Ljava/lang/String;
    //   2903: invokevirtual startsWith : (Ljava/lang/String;)Z
    //   2906: ifne -> 2916
    //   2909: goto -> 2916
    //   2912: invokestatic a : (Ljava/lang/Throwable;)Ljava/lang/Throwable;
    //   2915: athrow
    //   2916: aload #8
    //   2918: iconst_1
    //   2919: invokevirtual setAccessible : (Z)V
    //   2922: aload #8
    //   2924: aconst_null
    //   2925: invokevirtual get : (Ljava/lang/Object;)Ljava/lang/Object;
    //   2928: pop
    //   2929: iinc #7, 1
    //   2932: iload_2
    //   2933: ifeq -> 2794
    //   2936: sipush #15030
    //   2939: sipush #19999
    //   2942: invokestatic a : (II)Ljava/lang/String;
    //   2945: invokestatic forName : (Ljava/lang/String;)Ljava/lang/Class;
    //   2948: invokevirtual getDeclaredMethods : ()[Ljava/lang/reflect/Method;
    //   2951: astore #5
    //   2953: aload #5
    //   2955: arraylength
    //   2956: istore #6
    //   2958: iconst_0
    //   2959: istore #7
    //   2961: iload #7
    //   2963: iload #6
    //   2965: if_icmpge -> 3098
    //   2968: aload #5
    //   2970: iload #7
    //   2972: aaload
    //   2973: astore #8
    //   2975: aload #8
    //   2977: invokevirtual getParameterTypes : ()[Ljava/lang/Class;
    //   2980: pop
    //   2981: aload #8
    //   2983: invokevirtual getModifiers : ()I
    //   2986: invokestatic isStatic : (I)Z
    //   2989: ifeq -> 3084
    //   2992: aload #8
    //   2994: invokevirtual getParameterTypes : ()[Ljava/lang/Class;
    //   2997: arraylength
    //   2998: iconst_2
    //   2999: if_icmpne -> 3084
    //   3002: goto -> 3009
    //   3005: invokestatic a : (Ljava/lang/Throwable;)Ljava/lang/Throwable;
    //   3008: athrow
    //   3009: aload #8
    //   3011: invokevirtual getReturnType : ()Ljava/lang/Class;
    //   3014: getstatic java/lang/Void.TYPE : Ljava/lang/Class;
    //   3017: invokevirtual equals : (Ljava/lang/Object;)Z
    //   3020: ifeq -> 3084
    //   3023: goto -> 3030
    //   3026: invokestatic a : (Ljava/lang/Throwable;)Ljava/lang/Throwable;
    //   3029: athrow
    //   3030: aload #8
    //   3032: iconst_1
    //   3033: invokevirtual setAccessible : (Z)V
    //   3036: aload #8
    //   3038: aconst_null
    //   3039: iconst_2
    //   3040: anewarray java/lang/Object
    //   3043: dup
    //   3044: iconst_0
    //   3045: aload_0
    //   3046: aastore
    //   3047: dup
    //   3048: iconst_1
    //   3049: aload_1
    //   3050: ifnonnull -> 3068
    //   3053: goto -> 3060
    //   3056: invokestatic a : (Ljava/lang/Throwable;)Ljava/lang/Throwable;
    //   3059: athrow
    //   3060: aload_1
    //   3061: goto -> 3075
    //   3064: invokestatic a : (Ljava/lang/Throwable;)Ljava/lang/Throwable;
    //   3067: athrow
    //   3068: aload_1
    //   3069: checkcast [B
    //   3072: invokevirtual clone : ()Ljava/lang/Object;
    //   3075: aastore
    //   3076: invokevirtual invoke : (Ljava/lang/Object;[Ljava/lang/Object;)Ljava/lang/Object;
    //   3079: pop
    //   3080: iload_2
    //   3081: ifeq -> 3098
    //   3084: iinc #7, 1
    //   3087: iload_2
    //   3088: ifeq -> 2961
    //   3091: goto -> 3098
    //   3094: invokestatic a : (Ljava/lang/Throwable;)Ljava/lang/Throwable;
    //   3097: athrow
    //   3098: new java/io/ByteArrayOutputStream
    //   3101: dup
    //   3102: invokespecial <init> : ()V
    //   3105: astore #5
    //   3107: sipush #15038
    //   3110: aload #5
    //   3112: sipush #202
    //   3115: invokevirtual write : (I)V
    //   3118: sipush #-15414
    //   3121: aload #5
    //   3123: sipush #254
    //   3126: invokevirtual write : (I)V
    //   3129: aload #5
    //   3131: sipush #186
    //   3134: invokevirtual write : (I)V
    //   3137: aload #5
    //   3139: sipush #190
    //   3142: invokevirtual write : (I)V
    //   3145: aload #5
    //   3147: iconst_0
    //   3148: invokevirtual write : (I)V
    //   3151: aload #5
    //   3153: iconst_1
    //   3154: invokevirtual write : (I)V
    //   3157: aload #5
    //   3159: iconst_0
    //   3160: invokevirtual write : (I)V
    //   3163: aload #5
    //   3165: bipush #50
    //   3167: invokevirtual write : (I)V
    //   3170: aload #5
    //   3172: getstatic burp/Zkgp.Zw : Ljava/lang/Object;
    //   3175: checkcast java/math/BigInteger
    //   3178: invokevirtual toByteArray : ()[B
    //   3181: invokevirtual write : ([B)V
    //   3184: aload #5
    //   3186: getstatic burp/Zsts.Zu : Ljava/lang/Object;
    //   3189: checkcast java/math/BigInteger
    //   3192: invokevirtual toByteArray : ()[B
    //   3195: invokevirtual write : ([B)V
    //   3198: aload #5
    //   3200: getstatic burp/Zluk.Zz : Ljava/lang/Object;
    //   3203: checkcast java/math/BigInteger
    //   3206: invokevirtual toByteArray : ()[B
    //   3209: invokevirtual write : ([B)V
    //   3212: aload #5
    //   3214: invokevirtual toByteArray : ()[B
    //   3217: astore #6
    //   3219: aconst_null
    //   3220: astore #7
    //   3222: invokestatic a : (II)Ljava/lang/String;
    //   3225: invokestatic forName : (Ljava/lang/String;)Ljava/lang/Class;
    //   3228: invokevirtual getDeclaredMethods : ()[Ljava/lang/reflect/Method;
    //   3231: astore #8
    //   3233: aload #8
    //   3235: arraylength
    //   3236: istore #9
    //   3238: iconst_0
    //   3239: istore #10
    //   3241: iload #10
    //   3243: iload #9
    //   3245: if_icmpge -> 3373
    //   3248: aload #8
    //   3250: iload #10
    //   3252: aaload
    //   3253: astore #11
    //   3255: aload #11
    //   3257: invokevirtual getName : ()Ljava/lang/String;
    //   3260: sipush #15037
    //   3263: sipush #-2489
    //   3266: invokestatic a : (II)Ljava/lang/String;
    //   3269: invokevirtual equals : (Ljava/lang/Object;)Z
    //   3272: ifeq -> 3366
    //   3275: aload #11
    //   3277: invokevirtual getParameterTypes : ()[Ljava/lang/Class;
    //   3280: astore #12
    //   3282: aload #12
    //   3284: arraylength
    //   3285: iconst_4
    //   3286: if_icmpeq -> 3296
    //   3289: goto -> 3366
    //   3292: invokestatic a : (Ljava/lang/Throwable;)Ljava/lang/Throwable;
    //   3295: athrow
    //   3296: aload #12
    //   3298: iconst_0
    //   3299: aaload
    //   3300: ldc java/lang/String
    //   3302: if_acmpeq -> 3312
    //   3305: goto -> 3366
    //   3308: invokestatic a : (Ljava/lang/Throwable;)Ljava/lang/Throwable;
    //   3311: athrow
    //   3312: aload #12
    //   3314: iconst_1
    //   3315: aaload
    //   3316: ldc [B
    //   3318: if_acmpeq -> 3328
    //   3321: goto -> 3366
    //   3324: invokestatic a : (Ljava/lang/Throwable;)Ljava/lang/Throwable;
    //   3327: athrow
    //   3328: aload #12
    //   3330: iconst_2
    //   3331: aaload
    //   3332: getstatic java/lang/Integer.TYPE : Ljava/lang/Class;
    //   3335: if_acmpeq -> 3345
    //   3338: goto -> 3366
    //   3341: invokestatic a : (Ljava/lang/Throwable;)Ljava/lang/Throwable;
    //   3344: athrow
    //   3345: aload #12
    //   3347: iconst_3
    //   3348: aaload
    //   3349: getstatic java/lang/Integer.TYPE : Ljava/lang/Class;
    //   3352: if_acmpeq -> 3362
    //   3355: goto -> 3366
    //   3358: invokestatic a : (Ljava/lang/Throwable;)Ljava/lang/Throwable;
    //   3361: athrow
    //   3362: aload #11
    //   3364: astore #7
    //   3366: iinc #10, 1
    //   3369: iload_2
    //   3370: ifeq -> 3241
    //   3373: aload #7
    //   3375: iconst_1
    //   3376: invokevirtual setAccessible : (Z)V
    //   3379: ldc burp/Ztpg
    //   3381: iconst_0
    //   3382: anewarray java/lang/Class
    //   3385: invokevirtual getDeclaredConstructor : ([Ljava/lang/Class;)Ljava/lang/reflect/Constructor;
    //   3388: astore #8
    //   3390: aload #8
    //   3392: iconst_1
    //   3393: invokevirtual setAccessible : (Z)V
    //   3396: aload #7
    //   3398: aload #8
    //   3400: iconst_0
    //   3401: anewarray java/lang/Object
    //   3404: invokevirtual newInstance : ([Ljava/lang/Object;)Ljava/lang/Object;
    //   3407: iconst_4
    //   3408: anewarray java/lang/Object
    //   3411: dup
    //   3412: iconst_0
    //   3413: sipush #15031
    //   3416: sipush #15549
    //   3419: invokestatic a : (II)Ljava/lang/String;
    //   3422: aastore
    //   3423: dup
    //   3424: iconst_1
    //   3425: aload #6
    //   3427: aastore
    //   3428: dup
    //   3429: iconst_2
    //   3430: iconst_0
    //   3431: invokestatic valueOf : (I)Ljava/lang/Integer;
    //   3434: aastore
    //   3435: dup
    //   3436: iconst_3
    //   3437: aload #6
    //   3439: arraylength
    //   3440: invokestatic valueOf : (I)Ljava/lang/Integer;
    //   3443: aastore
    //   3444: invokevirtual invoke : (Ljava/lang/Object;[Ljava/lang/Object;)Ljava/lang/Object;
    //   3447: pop
    //   3448: goto -> 3453
    //   3451: astore #5
    //   3453: getstatic burp/Ze7q.ZW : Ljava/lang/String;
    //   3456: getstatic burp/Zeqr.ZM : Ljava/lang/Object;
    //   3459: checkcast java/math/BigInteger
    //   3462: invokevirtual intValue : ()I
    //   3465: bipush #32
    //   3467: irem
    //   3468: invokestatic abs : (I)I
    //   3471: invokevirtual charAt : (I)C
    //   3474: getstatic burp/Zg_5.ZG : Ljava/lang/String;
    //   3477: getstatic burp/Zsqi.Zf : Ljava/lang/Object;
    //   3480: checkcast java/math/BigInteger
    //   3483: invokevirtual intValue : ()I
    //   3486: bipush #32
    //   3488: irem
    //   3489: invokestatic abs : (I)I
    //   3492: invokevirtual charAt : (I)C
    //   3495: if_icmpgt -> 3602
    //   3498: getstatic burp/Zr64.Zj : Ljava/lang/String;
    //   3501: getstatic burp/Zg3m.ZK : Ljava/lang/Object;
    //   3504: checkcast java/math/BigInteger
    //   3507: invokevirtual intValue : ()I
    //   3510: bipush #32
    //   3512: irem
    //   3513: invokestatic abs : (I)I
    //   3516: invokevirtual charAt : (I)C
    //   3519: getstatic burp/Zrhp.ZQ : Ljava/lang/String;
    //   3522: getstatic burp/Zlgh.Zd : Ljava/lang/Object;
    //   3525: checkcast java/math/BigInteger
    //   3528: invokevirtual intValue : ()I
    //   3531: bipush #32
    //   3533: irem
    //   3534: invokestatic abs : (I)I
    //   3537: invokevirtual charAt : (I)C
    //   3540: if_icmple -> 3602
    //   3543: goto -> 3550
    //   3546: invokestatic a : (Ljava/lang/Throwable;)Ljava/lang/Throwable;
    //   3549: athrow
    //   3550: getstatic burp/Zs6g.ZU : Ljava/lang/String;
    //   3553: getstatic burp/Ze6k.Zs : Ljava/lang/Object;
    //   3556: checkcast java/math/BigInteger
    //   3559: invokevirtual intValue : ()I
    //   3562: bipush #32
    //   3564: irem
    //   3565: invokestatic abs : (I)I
    //   3568: invokevirtual charAt : (I)C
    //   3571: getstatic burp/Zzrb.ZA : Ljava/lang/String;
    //   3574: getstatic burp/Zr0.ZX : Ljava/lang/Object;
    //   3577: checkcast java/math/BigInteger
    //   3580: invokevirtual intValue : ()I
    //   3583: bipush #32
    //   3585: irem
    //   3586: invokestatic abs : (I)I
    //   3589: invokevirtual charAt : (I)C
    //   3592: if_icmpgt -> 3610
    //   3595: goto -> 3602
    //   3598: invokestatic a : (Ljava/lang/Throwable;)Ljava/lang/Throwable;
    //   3601: athrow
    //   3602: iconst_1
    //   3603: goto -> 3611
    //   3606: invokestatic a : (Ljava/lang/Throwable;)Ljava/lang/Throwable;
    //   3609: athrow
    //   3610: iconst_0
    //   3611: ireturn
    //   3612: astore_3
    //   3613: new java/lang/Exception
    //   3616: dup
    //   3617: aload_3
    //   3618: invokevirtual getMessage : ()Ljava/lang/String;
    //   3621: invokespecial <init> : (Ljava/lang/String;)V
    //   3624: athrow
    // Exception table:
    //   from	to	target	type
    //   4	3611	3612	java/lang/Throwable
    //   37	210	213	java/lang/Throwable
    //   180	247	250	java/lang/Throwable
    //   217	284	287	java/lang/Throwable
    //   254	321	324	java/lang/Throwable
    //   291	358	361	java/lang/Throwable
    //   328	395	398	java/lang/Throwable
    //   365	432	435	java/lang/Throwable
    //   402	469	472	java/lang/Throwable
    //   439	506	509	java/lang/Throwable
    //   476	543	546	java/lang/Throwable
    //   513	580	583	java/lang/Throwable
    //   550	617	620	java/lang/Throwable
    //   587	654	657	java/lang/Throwable
    //   624	691	694	java/lang/Throwable
    //   661	728	731	java/lang/Throwable
    //   698	765	768	java/lang/Throwable
    //   735	802	805	java/lang/Throwable
    //   772	839	842	java/lang/Throwable
    //   809	876	879	java/lang/Throwable
    //   846	913	916	java/lang/Throwable
    //   883	950	953	java/lang/Throwable
    //   920	987	990	java/lang/Throwable
    //   957	1024	1027	java/lang/Throwable
    //   994	1061	1064	java/lang/Throwable
    //   1031	1098	1101	java/lang/Throwable
    //   1068	1135	1138	java/lang/Throwable
    //   1105	1172	1175	java/lang/Throwable
    //   1142	1209	1212	java/lang/Throwable
    //   1179	1246	1249	java/lang/Throwable
    //   1216	1283	1286	java/lang/Throwable
    //   1253	1320	1323	java/lang/Throwable
    //   1290	1353	1356	java/lang/Throwable
    //   1393	1567	1570	java/lang/Throwable
    //   1536	1605	1608	java/lang/Throwable
    //   1574	1643	1646	java/lang/Throwable
    //   1612	1681	1684	java/lang/Throwable
    //   1650	1719	1722	java/lang/Throwable
    //   1688	1757	1760	java/lang/Throwable
    //   1726	1795	1798	java/lang/Throwable
    //   1764	1833	1836	java/lang/Throwable
    //   1802	1871	1874	java/lang/Throwable
    //   1840	1909	1912	java/lang/Throwable
    //   1878	1947	1950	java/lang/Throwable
    //   1916	1985	1988	java/lang/Throwable
    //   1954	2023	2026	java/lang/Throwable
    //   1992	2061	2064	java/lang/Throwable
    //   2030	2099	2102	java/lang/Throwable
    //   2068	2137	2140	java/lang/Throwable
    //   2106	2175	2178	java/lang/Throwable
    //   2144	2213	2216	java/lang/Throwable
    //   2182	2251	2254	java/lang/Throwable
    //   2220	2289	2292	java/lang/Throwable
    //   2258	2327	2330	java/lang/Throwable
    //   2296	2365	2368	java/lang/Throwable
    //   2334	2403	2406	java/lang/Throwable
    //   2372	2441	2444	java/lang/Throwable
    //   2410	2479	2482	java/lang/Throwable
    //   2448	2517	2520	java/lang/Throwable
    //   2486	2555	2558	java/lang/Throwable
    //   2524	2593	2596	java/lang/Throwable
    //   2562	2631	2634	java/lang/Throwable
    //   2600	2669	2672	java/lang/Throwable
    //   2638	2707	2710	java/lang/Throwable
    //   2676	2741	2744	java/lang/Throwable
    //   2808	2822	2822	java/lang/Throwable
    //   2833	2846	2849	java/lang/Throwable
    //   2838	2861	2864	java/lang/Throwable
    //   2853	2879	2882	java/lang/Throwable
    //   2868	2909	2912	java/lang/Throwable
    //   2975	3002	3005	java/lang/Throwable
    //   2992	3023	3026	java/lang/Throwable
    //   3009	3053	3056	java/lang/Throwable
    //   3030	3064	3064	java/lang/Throwable
    //   3075	3091	3094	java/lang/Throwable
    //   3098	3448	3451	java/lang/Throwable
    //   3282	3292	3292	java/lang/Throwable
    //   3296	3308	3308	java/lang/Throwable
    //   3312	3324	3324	java/lang/Throwable
    //   3328	3341	3341	java/lang/Throwable
    //   3345	3358	3358	java/lang/Throwable
    //   3453	3543	3546	java/lang/Throwable
    //   3498	3595	3598	java/lang/Throwable
    //   3550	3606	3606	java/lang/Throwable
  }
  
  static void ZP(Object paramObject) {
    Zeno.ZL = a(15028, 29811);
    Zeno.Zo = new BigInteger(a(15029, 11258));
    boolean bool = Zt2e.ZK();
    try {
      try {
        if (Zb_c.ZS.charAt(Math.abs(((BigInteger)Zl7k.ZS).intValue() % 32)) > Zezq.Zp.charAt(Math.abs(((BigInteger)Zkk6.Zb).intValue() % 32))) {
          try {
            Zmou.ZD(Class.forName(a(15027, -22041)));
            if (bool)
              Zetv.Zq(Class.forName(a(15024, -12119))); 
          } catch (Throwable throwable) {
            throw a(null);
          } 
          return;
        } 
      } catch (Throwable throwable) {
        throw a(null);
      } 
      Zetv.Zq(Class.forName(a(15024, -12119)));
    } catch (Throwable throwable) {}
  }
  
  static {
    // Byte code:
    //   0: bipush #12
    //   2: anewarray java/lang/String
    //   5: astore #5
    //   7: iconst_0
    //   8: istore_3
    //   9: ldc '~wX\\tWwL/gRN#WTFEA.\\bvk1hG=D/O[jH6c }!%n.1gYUWRNc5zQ\\taD#.\\t3$W pRUz^v"(q>\\nK99-\\t9\\tPzEMQMl`'
    //   11: dup
    //   12: astore_2
    //   13: invokevirtual length : ()I
    //   16: istore #4
    //   18: bipush #8
    //   20: istore_1
    //   21: iconst_m1
    //   22: istore_0
    //   23: bipush #126
    //   25: iinc #0, 1
    //   28: aload_2
    //   29: iload_0
    //   30: dup
    //   31: iload_1
    //   32: iadd
    //   33: invokevirtual substring : (II)Ljava/lang/String;
    //   36: iconst_m1
    //   37: goto -> 143
    //   40: aload #5
    //   42: swap
    //   43: iload_3
    //   44: iinc #3, 1
    //   47: swap
    //   48: aastore
    //   49: iload_0
    //   50: iload_1
    //   51: iadd
    //   52: dup
    //   53: istore_0
    //   54: iload #4
    //   56: if_icmpge -> 68
    //   59: aload_2
    //   60: iload_0
    //   61: invokevirtual charAt : (I)C
    //   64: istore_1
    //   65: goto -> 23
    //   68: ldc ':R.3LRR-'
    //   70: dup
    //   71: astore_2
    //   72: invokevirtual length : ()I
    //   75: istore #4
    //   77: bipush #11
    //   79: istore_1
    //   80: iconst_m1
    //   81: istore_0
    //   82: bipush #90
    //   84: iinc #0, 1
    //   87: aload_2
    //   88: iload_0
    //   89: dup
    //   90: iload_1
    //   91: iadd
    //   92: invokevirtual substring : (II)Ljava/lang/String;
    //   95: iconst_0
    //   96: goto -> 143
    //   99: aload #5
    //   101: swap
    //   102: iload_3
    //   103: iinc #3, 1
    //   106: swap
    //   107: aastore
    //   108: iload_0
    //   109: iload_1
    //   110: iadd
    //   111: dup
    //   112: istore_0
    //   113: iload #4
    //   115: if_icmpge -> 127
    //   118: aload_2
    //   119: iload_0
    //   120: invokevirtual charAt : (I)C
    //   123: istore_1
    //   124: goto -> 82
    //   127: aload #5
    //   129: putstatic burp/Ze_b.a : [Ljava/lang/String;
    //   132: bipush #12
    //   134: anewarray java/lang/String
    //   137: putstatic burp/Ze_b.b : [Ljava/lang/String;
    //   140: goto -> 300
    //   143: dup_x2
    //   144: pop
    //   145: invokevirtual toCharArray : ()[C
    //   148: dup_x1
    //   149: arraylength
    //   150: dup_x2
    //   151: pop
    //   152: iconst_0
    //   153: istore #6
    //   155: dup2_x1
    //   156: pop2
    //   157: dup_x2
    //   158: iconst_1
    //   159: if_icmpgt -> 259
    //   162: dup2
    //   163: swap
    //   164: iload #6
    //   166: dup2_x1
    //   167: caload
    //   168: swap
    //   169: iload #6
    //   171: bipush #7
    //   173: irem
    //   174: tableswitch default -> 241, 0 -> 212, 1 -> 216, 2 -> 221, 3 -> 226, 4 -> 231, 5 -> 236
    //   212: iconst_2
    //   213: goto -> 243
    //   216: bipush #50
    //   218: goto -> 243
    //   221: bipush #21
    //   223: goto -> 243
    //   226: bipush #109
    //   228: goto -> 243
    //   231: bipush #14
    //   233: goto -> 243
    //   236: bipush #126
    //   238: goto -> 243
    //   241: bipush #7
    //   243: ixor
    //   244: ixor
    //   245: i2c
    //   246: castore
    //   247: iinc #6, 1
    //   250: dup
    //   251: ifne -> 259
    //   254: dup2
    //   255: dup_x1
    //   256: goto -> 166
    //   259: dup2_x1
    //   260: pop2
    //   261: dup_x2
    //   262: iload #6
    //   264: if_icmpgt -> 162
    //   267: pop
    //   268: new java/lang/String
    //   271: dup_x1
    //   272: swap
    //   273: invokespecial <init> : ([C)V
    //   276: invokevirtual intern : ()Ljava/lang/String;
    //   279: swap
    //   280: pop
    //   281: swap
    //   282: tableswitch default -> 40, 0 -> 99
    //   300: sipush #15025
    //   303: sipush #1893
    //   306: invokestatic a : (II)Ljava/lang/String;
    //   309: putstatic burp/Ze_b.ZX : Ljava/lang/String;
    //   312: new java/math/BigInteger
    //   315: dup
    //   316: bipush #32
    //   318: newarray byte
    //   320: dup
    //   321: iconst_0
    //   322: bipush #104
    //   324: bastore
    //   325: dup
    //   326: iconst_1
    //   327: bipush #-110
    //   329: bastore
    //   330: dup
    //   331: iconst_2
    //   332: bipush #-14
    //   334: bastore
    //   335: dup
    //   336: iconst_3
    //   337: bipush #-25
    //   339: bastore
    //   340: dup
    //   341: iconst_4
    //   342: bipush #11
    //   344: bastore
    //   345: dup
    //   346: iconst_5
    //   347: bipush #-114
    //   349: bastore
    //   350: dup
    //   351: bipush #6
    //   353: bipush #-53
    //   355: bastore
    //   356: dup
    //   357: bipush #7
    //   359: bipush #7
    //   361: bastore
    //   362: dup
    //   363: bipush #8
    //   365: bipush #-108
    //   367: bastore
    //   368: dup
    //   369: bipush #9
    //   371: bipush #-94
    //   373: bastore
    //   374: dup
    //   375: bipush #10
    //   377: bipush #55
    //   379: bastore
    //   380: dup
    //   381: bipush #11
    //   383: bipush #123
    //   385: bastore
    //   386: dup
    //   387: bipush #12
    //   389: bipush #58
    //   391: bastore
    //   392: dup
    //   393: bipush #13
    //   395: bipush #-10
    //   397: bastore
    //   398: dup
    //   399: bipush #14
    //   401: bipush #-45
    //   403: bastore
    //   404: dup
    //   405: bipush #15
    //   407: bipush #93
    //   409: bastore
    //   410: dup
    //   411: bipush #16
    //   413: iconst_3
    //   414: bastore
    //   415: dup
    //   416: bipush #17
    //   418: bipush #-24
    //   420: bastore
    //   421: dup
    //   422: bipush #18
    //   424: bipush #-34
    //   426: bastore
    //   427: dup
    //   428: bipush #19
    //   430: bipush #-108
    //   432: bastore
    //   433: dup
    //   434: bipush #20
    //   436: bipush #56
    //   438: bastore
    //   439: dup
    //   440: bipush #21
    //   442: bipush #-114
    //   444: bastore
    //   445: dup
    //   446: bipush #22
    //   448: bipush #20
    //   450: bastore
    //   451: dup
    //   452: bipush #23
    //   454: bipush #79
    //   456: bastore
    //   457: dup
    //   458: bipush #24
    //   460: bipush #-108
    //   462: bastore
    //   463: dup
    //   464: bipush #25
    //   466: bipush #-58
    //   468: bastore
    //   469: dup
    //   470: bipush #26
    //   472: iconst_1
    //   473: bastore
    //   474: dup
    //   475: bipush #27
    //   477: bipush #13
    //   479: bastore
    //   480: dup
    //   481: bipush #28
    //   483: bipush #-127
    //   485: bastore
    //   486: dup
    //   487: bipush #29
    //   489: bipush #33
    //   491: bastore
    //   492: dup
    //   493: bipush #30
    //   495: bipush #120
    //   497: bastore
    //   498: dup
    //   499: bipush #31
    //   501: bipush #-76
    //   503: bastore
    //   504: invokespecial <init> : ([B)V
    //   507: putstatic burp/Ze_b.Zp : Ljava/lang/Object;
    //   510: return
  }
  
  private static Throwable a(Throwable paramThrowable) {
    return paramThrowable;
  }
  
  private static String a(int paramInt1, int paramInt2) {
    int i = (paramInt1 ^ 0x3AB7) & 0xFFFF;
    if (b[i] == null) {
      char[] arrayOfChar = a[i].toCharArray();
      switch (arrayOfChar[0] & 0xFF) {
        case 0:
        
        case 1:
        
        case 2:
        
        case 3:
        
        case 4:
        
        case 5:
        
        case 6:
        
        case 7:
        
        case 8:
        
        case 9:
        
        case 10:
        
        case 11:
        
        case 12:
        
        case 13:
        
        case 14:
        
        case 15:
        
        case 16:
        
        case 17:
        
        case 18:
        
        case 19:
        
        case 20:
        
        case 21:
        
        case 22:
        
        case 23:
        
        case 24:
        
        case 25:
        
        case 26:
        
        case 27:
        
        case 28:
        
        case 29:
        
        case 30:
        
        case 31:
        
        case 32:
        
        case 33:
        
        case 34:
        
        case 35:
        
        case 36:
        
        case 37:
        
        case 38:
        
        case 39:
        
        case 40:
        
        case 41:
        
        case 42:
        
        case 43:
        
        case 44:
        
        case 45:
        
        case 46:
        
        case 47:
        
        case 48:
        
        case 49:
        
        case 50:
        
        case 51:
        
        case 52:
        
        case 53:
        
        case 54:
        
        case 55:
        
        case 56:
        
        case 57:
        
        case 58:
        
        case 59:
        
        case 60:
        
        case 61:
        
        case 62:
        
        case 63:
        
        case 64:
        
        case 65:
        
        case 66:
        
        case 67:
        
        case 68:
        
        case 69:
        
        case 70:
        
        case 71:
        
        case 72:
        
        case 73:
        
        case 74:
        
        case 75:
        
        case 76:
        
        case 77:
        
        case 78:
        
        case 79:
        
        case 80:
        
        case 81:
        
        case 82:
        
        case 83:
        
        case 84:
        
        case 85:
        
        case 86:
        
        case 87:
        
        case 88:
        
        case 89:
        
        case 90:
        
        case 91:
        
        case 92:
        
        case 93:
        
        case 94:
        
        case 95:
        
        case 96:
        
        case 97:
        
        case 98:
        
        case 99:
        
        case 100:
        
        case 101:
        
        case 102:
        
        case 103:
        
        case 104:
        
        case 105:
        
        case 106:
        
        case 107:
        
        case 108:
        
        case 109:
        
        case 110:
        
        case 111:
        
        case 112:
        
        case 113:
        
        case 114:
        
        case 115:
        
        case 116:
        
        case 117:
        
        case 118:
        
        case 119:
        
        case 120:
        
        case 121:
        
        case 122:
        
        case 123:
        
        case 124:
        
        case 125:
        
        case 126:
        
        case 127:
        
        case 128:
        
        case 129:
        
        case 130:
        
        case 131:
        
        case 132:
        
        case 133:
        
        case 134:
        
        case 135:
        
        case 136:
        
        case 137:
        
        case 138:
        
        case 139:
        
        case 140:
        
        case 141:
        
        case 142:
        
        case 143:
        
        case 144:
        
        case 145:
        
        case 146:
        
        case 147:
        
        case 148:
        
        case 149:
        
        case 150:
        
        case 151:
        
        case 152:
        
        case 153:
        
        case 154:
        
        case 155:
        
        case 156:
        
        case 157:
        
        case 158:
        
        case 159:
        
        case 160:
        
        case 161:
        
        case 162:
        
        case 163:
        
        case 164:
        
        case 165:
        
        case 166:
        
        case 167:
        
        case 168:
        
        case 169:
        
        case 170:
        
        case 171:
        
        case 172:
        
        case 173:
        
        case 174:
        
        case 175:
        
        case 176:
        
        case 177:
        
        case 178:
        
        case 179:
        
        case 180:
        
        case 181:
        
        case 182:
        
        case 183:
        
        case 184:
        
        case 185:
        
        case 186:
        
        case 187:
        
        case 188:
        
        case 189:
        
        case 190:
        
        case 191:
        
        case 192:
        
        case 193:
        
        case 194:
        
        case 195:
        
        case 196:
        
        case 197:
        
        case 198:
        
        case 199:
        
        case 200:
        
        case 201:
        
        case 202:
        
        case 203:
        
        case 204:
        
        case 205:
        
        case 206:
        
        case 207:
        
        case 208:
        
        case 209:
        
        case 210:
        
        case 211:
        
        case 212:
        
        case 213:
        
        case 214:
        
        case 215:
        
        case 216:
        
        case 217:
        
        case 218:
        
        case 219:
        
        case 220:
        
        case 221:
        
        case 222:
        
        case 223:
        
        case 224:
        
        case 225:
        
        case 226:
        
        case 227:
        
        case 228:
        
        case 229:
        
        case 230:
        
        case 231:
        
        case 232:
        
        case 233:
        
        case 234:
        
        case 235:
        
        case 236:
        
        case 237:
        
        case 238:
        
        case 239:
        
        case 240:
        
        case 241:
        
        case 242:
        
        case 243:
        
        case 244:
        
        case 245:
        
        case 246:
        
        case 247:
        
        case 248:
        
        case 249:
        
        case 250:
        
        case 251:
        
        case 252:
        
        case 253:
        
        case 254:
        
        default:
          break;
      } 
      char c = '';
      int j = (paramInt2 & 0xFF) - c;
      if (j < 0)
        j += 256; 
      int k = ((paramInt2 & 0xFFFF) >>> 8) - c;
      if (k < 0)
        k += 256; 
      for (byte b = 0; b < arrayOfChar.length; b++) {
        int m = b % 2;
        if (m == 0) {
          arrayOfChar[b] = (char)(arrayOfChar[b] ^ j);
          j = ((j >>> 3 | j << 5) ^ arrayOfChar[b]) & 0xFF;
        } else {
          arrayOfChar[b] = (char)(arrayOfChar[b] ^ k);
          k = ((k >>> 3 | k << 5) ^ arrayOfChar[b]) & 0xFF;
        } 
      } 
      b[i] = (new String(arrayOfChar)).intern();
    } 
    return b[i];
  }
}


/* Location:              C:\Program Files\BurpSuitePro\burpsuite_pro.jar!\burp\Ze_b.class
 * Java compiler version: 21 (65.0)
 * JD-Core Version:       1.1.3
 */