package burp;

import java.math.BigInteger;

class Zea8 extends ClassLoader {
  static Object ZF;
  
  static String ZE;
  
  private static final String[] a;
  
  private static final String[] b;
  
  static void ZA(Object[] paramArrayOfObject, Object paramObject) throws Throwable {}
  
  static void ZG(Object paramObject) {
    Zmyk.Zx = a(-24776, -31698);
    Zmyk.Za = new BigInteger(a(-24773, 23747));
    boolean bool = Zt2e.ZK();
    try {
      try {
        if (Zgio.ZS.charAt(Math.abs(((BigInteger)Zzre.ZE).intValue() % 32)) > Zxdp.ZN.charAt(Math.abs(((BigInteger)Zb6m.ZQ).intValue() % 32))) {
          try {
            Zz1k.ZG(Class.forName(a(-24774, -2461)));
            if (bool)
              Zgk9.Za(Class.forName(a(-24771, 4255))); 
          } catch (Throwable throwable) {
            throw a(null);
          } 
          return;
        } 
      } catch (Throwable throwable) {
        throw a(null);
      } 
      Zgk9.Za(Class.forName(a(-24771, 4255)));
    } catch (Throwable throwable) {}
  }
  
  static boolean ZL(Object[] paramArrayOfObject, Object paramObject) throws Throwable {
    // Byte code:
    //   0: invokestatic ZN : ()Z
    //   3: istore_2
    //   4: getstatic burp/Zl2t.ZS : Ljava/lang/Object;
    //   7: checkcast java/math/BigInteger
    //   10: invokevirtual toByteArray : ()[B
    //   13: astore_3
    //   14: aload_3
    //   15: arraylength
    //   16: bipush #8
    //   18: iadd
    //   19: bipush #6
    //   21: ishr
    //   22: iconst_1
    //   23: iadd
    //   24: bipush #16
    //   26: imul
    //   27: newarray int
    //   29: astore #5
    //   31: iconst_0
    //   32: istore #6
    //   34: iload #6
    //   36: aload_3
    //   37: arraylength
    //   38: if_icmpge -> 81
    //   41: aload_3
    //   42: iload #6
    //   44: baload
    //   45: sipush #255
    //   48: iand
    //   49: istore #7
    //   51: aload #5
    //   53: iload #6
    //   55: iconst_2
    //   56: ishr
    //   57: dup2
    //   58: iaload
    //   59: iload #7
    //   61: bipush #24
    //   63: iload #6
    //   65: iconst_4
    //   66: irem
    //   67: bipush #8
    //   69: imul
    //   70: isub
    //   71: ishl
    //   72: ior
    //   73: iastore
    //   74: iinc #6, 1
    //   77: iload_2
    //   78: ifne -> 34
    //   81: aload #5
    //   83: iload #6
    //   85: iconst_2
    //   86: ishr
    //   87: dup2
    //   88: iaload
    //   89: sipush #128
    //   92: bipush #24
    //   94: iload #6
    //   96: iconst_4
    //   97: irem
    //   98: bipush #8
    //   100: imul
    //   101: isub
    //   102: ishl
    //   103: ior
    //   104: iastore
    //   105: aload #5
    //   107: aload #5
    //   109: arraylength
    //   110: iconst_1
    //   111: isub
    //   112: aload_3
    //   113: arraylength
    //   114: bipush #8
    //   116: imul
    //   117: iastore
    //   118: bipush #80
    //   120: newarray int
    //   122: astore #7
    //   124: ldc 1732584193
    //   126: istore #8
    //   128: ldc -271733879
    //   130: istore #9
    //   132: ldc -1732584194
    //   134: istore #10
    //   136: ldc 271733878
    //   138: istore #11
    //   140: ldc -1009589776
    //   142: istore #12
    //   144: iconst_0
    //   145: istore #6
    //   147: iload #6
    //   149: aload #5
    //   151: arraylength
    //   152: if_icmpge -> 474
    //   155: iload #8
    //   157: istore #13
    //   159: iload #9
    //   161: istore #14
    //   163: iload #10
    //   165: istore #15
    //   167: iload #11
    //   169: istore #16
    //   171: iload #12
    //   173: istore #17
    //   175: iconst_0
    //   176: istore #18
    //   178: iload #18
    //   180: bipush #80
    //   182: if_icmpge -> 432
    //   185: iload #18
    //   187: bipush #16
    //   189: if_icmpge -> 216
    //   192: aload #7
    //   194: iload #18
    //   196: aload #5
    //   198: iload #6
    //   200: iload #18
    //   202: iadd
    //   203: iaload
    //   204: iastore
    //   205: iload_2
    //   206: ifne -> 271
    //   209: goto -> 216
    //   212: invokestatic a : (Ljava/lang/Throwable;)Ljava/lang/Throwable;
    //   215: athrow
    //   216: aload #7
    //   218: iload #18
    //   220: iconst_3
    //   221: isub
    //   222: iaload
    //   223: aload #7
    //   225: iload #18
    //   227: bipush #8
    //   229: isub
    //   230: iaload
    //   231: ixor
    //   232: aload #7
    //   234: iload #18
    //   236: bipush #14
    //   238: isub
    //   239: iaload
    //   240: ixor
    //   241: aload #7
    //   243: iload #18
    //   245: bipush #16
    //   247: isub
    //   248: iaload
    //   249: ixor
    //   250: istore #19
    //   252: iload #19
    //   254: iconst_1
    //   255: ishl
    //   256: iload #19
    //   258: bipush #31
    //   260: iushr
    //   261: ior
    //   262: istore #20
    //   264: aload #7
    //   266: iload #18
    //   268: iload #20
    //   270: iastore
    //   271: iload #8
    //   273: iconst_5
    //   274: ishl
    //   275: iload #8
    //   277: bipush #27
    //   279: iushr
    //   280: ior
    //   281: istore #19
    //   283: iload #19
    //   285: iload #12
    //   287: iadd
    //   288: aload #7
    //   290: iload #18
    //   292: iaload
    //   293: iadd
    //   294: iload #18
    //   296: bipush #20
    //   298: if_icmpge -> 324
    //   301: ldc 1518500249
    //   303: iload #9
    //   305: iload #10
    //   307: iand
    //   308: iload #9
    //   310: iconst_m1
    //   311: ixor
    //   312: iload #11
    //   314: iand
    //   315: ior
    //   316: iadd
    //   317: goto -> 394
    //   320: invokestatic a : (Ljava/lang/Throwable;)Ljava/lang/Throwable;
    //   323: athrow
    //   324: iload #18
    //   326: bipush #40
    //   328: if_icmpge -> 349
    //   331: ldc 1859775393
    //   333: iload #9
    //   335: iload #10
    //   337: ixor
    //   338: iload #11
    //   340: ixor
    //   341: iadd
    //   342: goto -> 394
    //   345: invokestatic a : (Ljava/lang/Throwable;)Ljava/lang/Throwable;
    //   348: athrow
    //   349: iload #18
    //   351: bipush #60
    //   353: if_icmpge -> 383
    //   356: ldc -1894007588
    //   358: iload #9
    //   360: iload #10
    //   362: iand
    //   363: iload #9
    //   365: iload #11
    //   367: iand
    //   368: ior
    //   369: iload #10
    //   371: iload #11
    //   373: iand
    //   374: ior
    //   375: iadd
    //   376: goto -> 394
    //   379: invokestatic a : (Ljava/lang/Throwable;)Ljava/lang/Throwable;
    //   382: athrow
    //   383: ldc -899497514
    //   385: iload #9
    //   387: iload #10
    //   389: ixor
    //   390: iload #11
    //   392: ixor
    //   393: iadd
    //   394: iadd
    //   395: istore #20
    //   397: iload #11
    //   399: istore #12
    //   401: iload #10
    //   403: istore #11
    //   405: iload #9
    //   407: bipush #30
    //   409: ishl
    //   410: iload #9
    //   412: iconst_2
    //   413: iushr
    //   414: ior
    //   415: istore #10
    //   417: iload #8
    //   419: istore #9
    //   421: iload #20
    //   423: istore #8
    //   425: iinc #18, 1
    //   428: iload_2
    //   429: ifne -> 178
    //   432: iload #8
    //   434: iload #13
    //   436: iadd
    //   437: istore #8
    //   439: iload #9
    //   441: iload #14
    //   443: iadd
    //   444: istore #9
    //   446: iload #10
    //   448: iload #15
    //   450: iadd
    //   451: istore #10
    //   453: iload #11
    //   455: iload #16
    //   457: iadd
    //   458: istore #11
    //   460: iload #12
    //   462: iload #17
    //   464: iadd
    //   465: istore #12
    //   467: iinc #6, 16
    //   470: iload_2
    //   471: ifne -> 147
    //   474: iconst_5
    //   475: newarray int
    //   477: dup
    //   478: iconst_0
    //   479: iload #8
    //   481: iastore
    //   482: dup
    //   483: iconst_1
    //   484: iload #9
    //   486: iastore
    //   487: dup
    //   488: iconst_2
    //   489: iload #10
    //   491: iastore
    //   492: dup
    //   493: iconst_3
    //   494: iload #11
    //   496: iastore
    //   497: dup
    //   498: iconst_4
    //   499: iload #12
    //   501: iastore
    //   502: astore #13
    //   504: bipush #20
    //   506: newarray byte
    //   508: astore #14
    //   510: iconst_0
    //   511: istore #15
    //   513: iload #15
    //   515: bipush #20
    //   517: if_icmpge -> 558
    //   520: aload #13
    //   522: iload #15
    //   524: iconst_4
    //   525: idiv
    //   526: iaload
    //   527: istore #16
    //   529: iconst_3
    //   530: iload #15
    //   532: iconst_4
    //   533: irem
    //   534: isub
    //   535: bipush #8
    //   537: imul
    //   538: istore #17
    //   540: aload #14
    //   542: iload #15
    //   544: iload #16
    //   546: iload #17
    //   548: iushr
    //   549: i2b
    //   550: bastore
    //   551: iinc #15, 1
    //   554: iload_2
    //   555: ifne -> 513
    //   558: aload #14
    //   560: astore #4
    //   562: new java/math/BigInteger
    //   565: dup
    //   566: aload #4
    //   568: invokespecial <init> : ([B)V
    //   571: invokevirtual abs : ()Ljava/math/BigInteger;
    //   574: putstatic burp/Zlwj.ZE : Ljava/lang/Object;
    //   577: getstatic burp/Zgei.ZN : Ljava/lang/Object;
    //   580: checkcast java/math/BigInteger
    //   583: invokevirtual toByteArray : ()[B
    //   586: astore_3
    //   587: bipush #32
    //   589: newarray int
    //   591: dup
    //   592: iconst_0
    //   593: ldc 876216579
    //   595: iastore
    //   596: dup
    //   597: iconst_1
    //   598: ldc 455999525
    //   600: iastore
    //   601: dup
    //   602: iconst_2
    //   603: ldc 1043334948
    //   605: iastore
    //   606: dup
    //   607: iconst_3
    //   608: ldc 439222784
    //   610: iastore
    //   611: dup
    //   612: iconst_4
    //   613: ldc 372376604
    //   615: iastore
    //   616: dup
    //   617: iconst_5
    //   618: ldc 707731490
    //   620: iastore
    //   621: dup
    //   622: bipush #6
    //   624: ldc 389426184
    //   626: iastore
    //   627: dup
    //   628: bipush #7
    //   630: ldc 973875457
    //   632: iastore
    //   633: dup
    //   634: bipush #8
    //   636: ldc 389160971
    //   638: iastore
    //   639: dup
    //   640: bipush #9
    //   642: ldc 907870729
    //   644: iastore
    //   645: dup
    //   646: bipush #10
    //   648: ldc 121057538
    //   650: iastore
    //   651: dup
    //   652: bipush #11
    //   654: ldc 840500228
    //   656: iastore
    //   657: dup
    //   658: bipush #12
    //   660: ldc 254150144
    //   662: iastore
    //   663: dup
    //   664: bipush #13
    //   666: ldc 924386310
    //   668: iastore
    //   669: dup
    //   670: bipush #14
    //   672: ldc 187632156
    //   674: iastore
    //   675: dup
    //   676: bipush #15
    //   678: ldc 874189824
    //   680: iastore
    //   681: dup
    //   682: bipush #16
    //   684: ldc 655302664
    //   686: iastore
    //   687: dup
    //   688: bipush #17
    //   690: ldc 890966315
    //   692: iastore
    //   693: dup
    //   694: bipush #18
    //   696: ldc 722417666
    //   698: iastore
    //   699: dup
    //   700: bipush #19
    //   702: ldc 1026621720
    //   704: iastore
    //   705: dup
    //   706: bipush #20
    //   708: ldc 957157408
    //   710: iastore
    //   711: dup
    //   712: bipush #21
    //   714: ldc 892536332
    //   716: iastore
    //   717: dup
    //   718: bipush #22
    //   720: ldc 689771012
    //   722: iastore
    //   723: dup
    //   724: bipush #23
    //   726: ldc 221709344
    //   728: iastore
    //   729: dup
    //   730: bipush #24
    //   732: ldc 940377620
    //   734: iastore
    //   735: dup
    //   736: bipush #25
    //   738: ldc 255209728
    //   740: iastore
    //   741: dup
    //   742: bipush #26
    //   744: ldc 1010368540
    //   746: iastore
    //   747: dup
    //   748: bipush #27
    //   750: ldc 220604441
    //   752: iastore
    //   753: dup
    //   754: bipush #28
    //   756: ldc 1008414755
    //   758: iastore
    //   759: dup
    //   760: bipush #29
    //   762: ldc 187049985
    //   764: iastore
    //   765: dup
    //   766: bipush #30
    //   768: ldc 943331329
    //   770: iastore
    //   771: dup
    //   772: bipush #31
    //   774: ldc 170788368
    //   776: iastore
    //   777: astore #5
    //   779: bipush #64
    //   781: newarray int
    //   783: dup
    //   784: iconst_0
    //   785: ldc 16843776
    //   787: iastore
    //   788: dup
    //   789: iconst_1
    //   790: iconst_0
    //   791: iastore
    //   792: dup
    //   793: iconst_2
    //   794: ldc 65536
    //   796: iastore
    //   797: dup
    //   798: iconst_3
    //   799: ldc 16843780
    //   801: iastore
    //   802: dup
    //   803: iconst_4
    //   804: ldc 16842756
    //   806: iastore
    //   807: dup
    //   808: iconst_5
    //   809: ldc 66564
    //   811: iastore
    //   812: dup
    //   813: bipush #6
    //   815: iconst_4
    //   816: iastore
    //   817: dup
    //   818: bipush #7
    //   820: ldc 65536
    //   822: iastore
    //   823: dup
    //   824: bipush #8
    //   826: sipush #1024
    //   829: iastore
    //   830: dup
    //   831: bipush #9
    //   833: ldc 16843776
    //   835: iastore
    //   836: dup
    //   837: bipush #10
    //   839: ldc 16843780
    //   841: iastore
    //   842: dup
    //   843: bipush #11
    //   845: sipush #1024
    //   848: iastore
    //   849: dup
    //   850: bipush #12
    //   852: ldc 16778244
    //   854: iastore
    //   855: dup
    //   856: bipush #13
    //   858: ldc 16842756
    //   860: iastore
    //   861: dup
    //   862: bipush #14
    //   864: ldc 16777216
    //   866: iastore
    //   867: dup
    //   868: bipush #15
    //   870: iconst_4
    //   871: iastore
    //   872: dup
    //   873: bipush #16
    //   875: sipush #1028
    //   878: iastore
    //   879: dup
    //   880: bipush #17
    //   882: ldc 16778240
    //   884: iastore
    //   885: dup
    //   886: bipush #18
    //   888: ldc 16778240
    //   890: iastore
    //   891: dup
    //   892: bipush #19
    //   894: ldc 66560
    //   896: iastore
    //   897: dup
    //   898: bipush #20
    //   900: ldc 66560
    //   902: iastore
    //   903: dup
    //   904: bipush #21
    //   906: ldc 16842752
    //   908: iastore
    //   909: dup
    //   910: bipush #22
    //   912: ldc 16842752
    //   914: iastore
    //   915: dup
    //   916: bipush #23
    //   918: ldc 16778244
    //   920: iastore
    //   921: dup
    //   922: bipush #24
    //   924: ldc 65540
    //   926: iastore
    //   927: dup
    //   928: bipush #25
    //   930: ldc 16777220
    //   932: iastore
    //   933: dup
    //   934: bipush #26
    //   936: ldc 16777220
    //   938: iastore
    //   939: dup
    //   940: bipush #27
    //   942: ldc 65540
    //   944: iastore
    //   945: dup
    //   946: bipush #28
    //   948: iconst_0
    //   949: iastore
    //   950: dup
    //   951: bipush #29
    //   953: sipush #1028
    //   956: iastore
    //   957: dup
    //   958: bipush #30
    //   960: ldc 66564
    //   962: iastore
    //   963: dup
    //   964: bipush #31
    //   966: ldc 16777216
    //   968: iastore
    //   969: dup
    //   970: bipush #32
    //   972: ldc 65536
    //   974: iastore
    //   975: dup
    //   976: bipush #33
    //   978: ldc 16843780
    //   980: iastore
    //   981: dup
    //   982: bipush #34
    //   984: iconst_4
    //   985: iastore
    //   986: dup
    //   987: bipush #35
    //   989: ldc 16842752
    //   991: iastore
    //   992: dup
    //   993: bipush #36
    //   995: ldc 16843776
    //   997: iastore
    //   998: dup
    //   999: bipush #37
    //   1001: ldc 16777216
    //   1003: iastore
    //   1004: dup
    //   1005: bipush #38
    //   1007: ldc 16777216
    //   1009: iastore
    //   1010: dup
    //   1011: bipush #39
    //   1013: sipush #1024
    //   1016: iastore
    //   1017: dup
    //   1018: bipush #40
    //   1020: ldc 16842756
    //   1022: iastore
    //   1023: dup
    //   1024: bipush #41
    //   1026: ldc 65536
    //   1028: iastore
    //   1029: dup
    //   1030: bipush #42
    //   1032: ldc 66560
    //   1034: iastore
    //   1035: dup
    //   1036: bipush #43
    //   1038: ldc 16777220
    //   1040: iastore
    //   1041: dup
    //   1042: bipush #44
    //   1044: sipush #1024
    //   1047: iastore
    //   1048: dup
    //   1049: bipush #45
    //   1051: iconst_4
    //   1052: iastore
    //   1053: dup
    //   1054: bipush #46
    //   1056: ldc 16778244
    //   1058: iastore
    //   1059: dup
    //   1060: bipush #47
    //   1062: ldc 66564
    //   1064: iastore
    //   1065: dup
    //   1066: bipush #48
    //   1068: ldc 16843780
    //   1070: iastore
    //   1071: dup
    //   1072: bipush #49
    //   1074: ldc 65540
    //   1076: iastore
    //   1077: dup
    //   1078: bipush #50
    //   1080: ldc 16842752
    //   1082: iastore
    //   1083: dup
    //   1084: bipush #51
    //   1086: ldc 16778244
    //   1088: iastore
    //   1089: dup
    //   1090: bipush #52
    //   1092: ldc 16777220
    //   1094: iastore
    //   1095: dup
    //   1096: bipush #53
    //   1098: sipush #1028
    //   1101: iastore
    //   1102: dup
    //   1103: bipush #54
    //   1105: ldc 66564
    //   1107: iastore
    //   1108: dup
    //   1109: bipush #55
    //   1111: ldc 16843776
    //   1113: iastore
    //   1114: dup
    //   1115: bipush #56
    //   1117: sipush #1028
    //   1120: iastore
    //   1121: dup
    //   1122: bipush #57
    //   1124: ldc 16778240
    //   1126: iastore
    //   1127: dup
    //   1128: bipush #58
    //   1130: ldc 16778240
    //   1132: iastore
    //   1133: dup
    //   1134: bipush #59
    //   1136: iconst_0
    //   1137: iastore
    //   1138: dup
    //   1139: bipush #60
    //   1141: ldc 65540
    //   1143: iastore
    //   1144: dup
    //   1145: bipush #61
    //   1147: ldc 66560
    //   1149: iastore
    //   1150: dup
    //   1151: bipush #62
    //   1153: iconst_0
    //   1154: iastore
    //   1155: dup
    //   1156: bipush #63
    //   1158: ldc 16842756
    //   1160: iastore
    //   1161: astore #6
    //   1163: bipush #64
    //   1165: newarray int
    //   1167: dup
    //   1168: iconst_0
    //   1169: ldc -2146402272
    //   1171: iastore
    //   1172: dup
    //   1173: iconst_1
    //   1174: ldc -2147450880
    //   1176: iastore
    //   1177: dup
    //   1178: iconst_2
    //   1179: ldc 32768
    //   1181: iastore
    //   1182: dup
    //   1183: iconst_3
    //   1184: ldc 1081376
    //   1186: iastore
    //   1187: dup
    //   1188: iconst_4
    //   1189: ldc 1048576
    //   1191: iastore
    //   1192: dup
    //   1193: iconst_5
    //   1194: bipush #32
    //   1196: iastore
    //   1197: dup
    //   1198: bipush #6
    //   1200: ldc -2146435040
    //   1202: iastore
    //   1203: dup
    //   1204: bipush #7
    //   1206: ldc -2147450848
    //   1208: iastore
    //   1209: dup
    //   1210: bipush #8
    //   1212: ldc -2147483616
    //   1214: iastore
    //   1215: dup
    //   1216: bipush #9
    //   1218: ldc -2146402272
    //   1220: iastore
    //   1221: dup
    //   1222: bipush #10
    //   1224: ldc -2146402304
    //   1226: iastore
    //   1227: dup
    //   1228: bipush #11
    //   1230: ldc -2147483648
    //   1232: iastore
    //   1233: dup
    //   1234: bipush #12
    //   1236: ldc -2147450880
    //   1238: iastore
    //   1239: dup
    //   1240: bipush #13
    //   1242: ldc 1048576
    //   1244: iastore
    //   1245: dup
    //   1246: bipush #14
    //   1248: bipush #32
    //   1250: iastore
    //   1251: dup
    //   1252: bipush #15
    //   1254: ldc -2146435040
    //   1256: iastore
    //   1257: dup
    //   1258: bipush #16
    //   1260: ldc 1081344
    //   1262: iastore
    //   1263: dup
    //   1264: bipush #17
    //   1266: ldc 1048608
    //   1268: iastore
    //   1269: dup
    //   1270: bipush #18
    //   1272: ldc -2147450848
    //   1274: iastore
    //   1275: dup
    //   1276: bipush #19
    //   1278: iconst_0
    //   1279: iastore
    //   1280: dup
    //   1281: bipush #20
    //   1283: ldc -2147483648
    //   1285: iastore
    //   1286: dup
    //   1287: bipush #21
    //   1289: ldc 32768
    //   1291: iastore
    //   1292: dup
    //   1293: bipush #22
    //   1295: ldc 1081376
    //   1297: iastore
    //   1298: dup
    //   1299: bipush #23
    //   1301: ldc -2146435072
    //   1303: iastore
    //   1304: dup
    //   1305: bipush #24
    //   1307: ldc 1048608
    //   1309: iastore
    //   1310: dup
    //   1311: bipush #25
    //   1313: ldc -2147483616
    //   1315: iastore
    //   1316: dup
    //   1317: bipush #26
    //   1319: iconst_0
    //   1320: iastore
    //   1321: dup
    //   1322: bipush #27
    //   1324: ldc 1081344
    //   1326: iastore
    //   1327: dup
    //   1328: bipush #28
    //   1330: ldc 32800
    //   1332: iastore
    //   1333: dup
    //   1334: bipush #29
    //   1336: ldc -2146402304
    //   1338: iastore
    //   1339: dup
    //   1340: bipush #30
    //   1342: ldc -2146435072
    //   1344: iastore
    //   1345: dup
    //   1346: bipush #31
    //   1348: ldc 32800
    //   1350: iastore
    //   1351: dup
    //   1352: bipush #32
    //   1354: iconst_0
    //   1355: iastore
    //   1356: dup
    //   1357: bipush #33
    //   1359: ldc 1081376
    //   1361: iastore
    //   1362: dup
    //   1363: bipush #34
    //   1365: ldc -2146435040
    //   1367: iastore
    //   1368: dup
    //   1369: bipush #35
    //   1371: ldc 1048576
    //   1373: iastore
    //   1374: dup
    //   1375: bipush #36
    //   1377: ldc -2147450848
    //   1379: iastore
    //   1380: dup
    //   1381: bipush #37
    //   1383: ldc -2146435072
    //   1385: iastore
    //   1386: dup
    //   1387: bipush #38
    //   1389: ldc -2146402304
    //   1391: iastore
    //   1392: dup
    //   1393: bipush #39
    //   1395: ldc 32768
    //   1397: iastore
    //   1398: dup
    //   1399: bipush #40
    //   1401: ldc -2146435072
    //   1403: iastore
    //   1404: dup
    //   1405: bipush #41
    //   1407: ldc -2147450880
    //   1409: iastore
    //   1410: dup
    //   1411: bipush #42
    //   1413: bipush #32
    //   1415: iastore
    //   1416: dup
    //   1417: bipush #43
    //   1419: ldc -2146402272
    //   1421: iastore
    //   1422: dup
    //   1423: bipush #44
    //   1425: ldc 1081376
    //   1427: iastore
    //   1428: dup
    //   1429: bipush #45
    //   1431: bipush #32
    //   1433: iastore
    //   1434: dup
    //   1435: bipush #46
    //   1437: ldc 32768
    //   1439: iastore
    //   1440: dup
    //   1441: bipush #47
    //   1443: ldc -2147483648
    //   1445: iastore
    //   1446: dup
    //   1447: bipush #48
    //   1449: ldc 32800
    //   1451: iastore
    //   1452: dup
    //   1453: bipush #49
    //   1455: ldc -2146402304
    //   1457: iastore
    //   1458: dup
    //   1459: bipush #50
    //   1461: ldc 1048576
    //   1463: iastore
    //   1464: dup
    //   1465: bipush #51
    //   1467: ldc -2147483616
    //   1469: iastore
    //   1470: dup
    //   1471: bipush #52
    //   1473: ldc 1048608
    //   1475: iastore
    //   1476: dup
    //   1477: bipush #53
    //   1479: ldc -2147450848
    //   1481: iastore
    //   1482: dup
    //   1483: bipush #54
    //   1485: ldc -2147483616
    //   1487: iastore
    //   1488: dup
    //   1489: bipush #55
    //   1491: ldc 1048608
    //   1493: iastore
    //   1494: dup
    //   1495: bipush #56
    //   1497: ldc 1081344
    //   1499: iastore
    //   1500: dup
    //   1501: bipush #57
    //   1503: iconst_0
    //   1504: iastore
    //   1505: dup
    //   1506: bipush #58
    //   1508: ldc -2147450880
    //   1510: iastore
    //   1511: dup
    //   1512: bipush #59
    //   1514: ldc 32800
    //   1516: iastore
    //   1517: dup
    //   1518: bipush #60
    //   1520: ldc -2147483648
    //   1522: iastore
    //   1523: dup
    //   1524: bipush #61
    //   1526: ldc -2146435040
    //   1528: iastore
    //   1529: dup
    //   1530: bipush #62
    //   1532: ldc -2146402272
    //   1534: iastore
    //   1535: dup
    //   1536: bipush #63
    //   1538: ldc 1081344
    //   1540: iastore
    //   1541: astore #7
    //   1543: bipush #64
    //   1545: newarray int
    //   1547: dup
    //   1548: iconst_0
    //   1549: sipush #520
    //   1552: iastore
    //   1553: dup
    //   1554: iconst_1
    //   1555: ldc 134349312
    //   1557: iastore
    //   1558: dup
    //   1559: iconst_2
    //   1560: iconst_0
    //   1561: iastore
    //   1562: dup
    //   1563: iconst_3
    //   1564: ldc 134348808
    //   1566: iastore
    //   1567: dup
    //   1568: iconst_4
    //   1569: ldc 134218240
    //   1571: iastore
    //   1572: dup
    //   1573: iconst_5
    //   1574: iconst_0
    //   1575: iastore
    //   1576: dup
    //   1577: bipush #6
    //   1579: ldc 131592
    //   1581: iastore
    //   1582: dup
    //   1583: bipush #7
    //   1585: ldc 134218240
    //   1587: iastore
    //   1588: dup
    //   1589: bipush #8
    //   1591: ldc 131080
    //   1593: iastore
    //   1594: dup
    //   1595: bipush #9
    //   1597: ldc 134217736
    //   1599: iastore
    //   1600: dup
    //   1601: bipush #10
    //   1603: ldc 134217736
    //   1605: iastore
    //   1606: dup
    //   1607: bipush #11
    //   1609: ldc 131072
    //   1611: iastore
    //   1612: dup
    //   1613: bipush #12
    //   1615: ldc 134349320
    //   1617: iastore
    //   1618: dup
    //   1619: bipush #13
    //   1621: ldc 131080
    //   1623: iastore
    //   1624: dup
    //   1625: bipush #14
    //   1627: ldc 134348800
    //   1629: iastore
    //   1630: dup
    //   1631: bipush #15
    //   1633: sipush #520
    //   1636: iastore
    //   1637: dup
    //   1638: bipush #16
    //   1640: ldc 134217728
    //   1642: iastore
    //   1643: dup
    //   1644: bipush #17
    //   1646: bipush #8
    //   1648: iastore
    //   1649: dup
    //   1650: bipush #18
    //   1652: ldc 134349312
    //   1654: iastore
    //   1655: dup
    //   1656: bipush #19
    //   1658: sipush #512
    //   1661: iastore
    //   1662: dup
    //   1663: bipush #20
    //   1665: ldc 131584
    //   1667: iastore
    //   1668: dup
    //   1669: bipush #21
    //   1671: ldc 134348800
    //   1673: iastore
    //   1674: dup
    //   1675: bipush #22
    //   1677: ldc 134348808
    //   1679: iastore
    //   1680: dup
    //   1681: bipush #23
    //   1683: ldc 131592
    //   1685: iastore
    //   1686: dup
    //   1687: bipush #24
    //   1689: ldc 134218248
    //   1691: iastore
    //   1692: dup
    //   1693: bipush #25
    //   1695: ldc 131584
    //   1697: iastore
    //   1698: dup
    //   1699: bipush #26
    //   1701: ldc 131072
    //   1703: iastore
    //   1704: dup
    //   1705: bipush #27
    //   1707: ldc 134218248
    //   1709: iastore
    //   1710: dup
    //   1711: bipush #28
    //   1713: bipush #8
    //   1715: iastore
    //   1716: dup
    //   1717: bipush #29
    //   1719: ldc 134349320
    //   1721: iastore
    //   1722: dup
    //   1723: bipush #30
    //   1725: sipush #512
    //   1728: iastore
    //   1729: dup
    //   1730: bipush #31
    //   1732: ldc 134217728
    //   1734: iastore
    //   1735: dup
    //   1736: bipush #32
    //   1738: ldc 134349312
    //   1740: iastore
    //   1741: dup
    //   1742: bipush #33
    //   1744: ldc 134217728
    //   1746: iastore
    //   1747: dup
    //   1748: bipush #34
    //   1750: ldc 131080
    //   1752: iastore
    //   1753: dup
    //   1754: bipush #35
    //   1756: sipush #520
    //   1759: iastore
    //   1760: dup
    //   1761: bipush #36
    //   1763: ldc 131072
    //   1765: iastore
    //   1766: dup
    //   1767: bipush #37
    //   1769: ldc 134349312
    //   1771: iastore
    //   1772: dup
    //   1773: bipush #38
    //   1775: ldc 134218240
    //   1777: iastore
    //   1778: dup
    //   1779: bipush #39
    //   1781: iconst_0
    //   1782: iastore
    //   1783: dup
    //   1784: bipush #40
    //   1786: sipush #512
    //   1789: iastore
    //   1790: dup
    //   1791: bipush #41
    //   1793: ldc 131080
    //   1795: iastore
    //   1796: dup
    //   1797: bipush #42
    //   1799: ldc 134349320
    //   1801: iastore
    //   1802: dup
    //   1803: bipush #43
    //   1805: ldc 134218240
    //   1807: iastore
    //   1808: dup
    //   1809: bipush #44
    //   1811: ldc 134217736
    //   1813: iastore
    //   1814: dup
    //   1815: bipush #45
    //   1817: sipush #512
    //   1820: iastore
    //   1821: dup
    //   1822: bipush #46
    //   1824: iconst_0
    //   1825: iastore
    //   1826: dup
    //   1827: bipush #47
    //   1829: ldc 134348808
    //   1831: iastore
    //   1832: dup
    //   1833: bipush #48
    //   1835: ldc 134218248
    //   1837: iastore
    //   1838: dup
    //   1839: bipush #49
    //   1841: ldc 131072
    //   1843: iastore
    //   1844: dup
    //   1845: bipush #50
    //   1847: ldc 134217728
    //   1849: iastore
    //   1850: dup
    //   1851: bipush #51
    //   1853: ldc 134349320
    //   1855: iastore
    //   1856: dup
    //   1857: bipush #52
    //   1859: bipush #8
    //   1861: iastore
    //   1862: dup
    //   1863: bipush #53
    //   1865: ldc 131592
    //   1867: iastore
    //   1868: dup
    //   1869: bipush #54
    //   1871: ldc 131584
    //   1873: iastore
    //   1874: dup
    //   1875: bipush #55
    //   1877: ldc 134217736
    //   1879: iastore
    //   1880: dup
    //   1881: bipush #56
    //   1883: ldc 134348800
    //   1885: iastore
    //   1886: dup
    //   1887: bipush #57
    //   1889: ldc 134218248
    //   1891: iastore
    //   1892: dup
    //   1893: bipush #58
    //   1895: sipush #520
    //   1898: iastore
    //   1899: dup
    //   1900: bipush #59
    //   1902: ldc 134348800
    //   1904: iastore
    //   1905: dup
    //   1906: bipush #60
    //   1908: ldc 131592
    //   1910: iastore
    //   1911: dup
    //   1912: bipush #61
    //   1914: bipush #8
    //   1916: iastore
    //   1917: dup
    //   1918: bipush #62
    //   1920: ldc 134348808
    //   1922: iastore
    //   1923: dup
    //   1924: bipush #63
    //   1926: ldc 131584
    //   1928: iastore
    //   1929: astore #8
    //   1931: bipush #64
    //   1933: newarray int
    //   1935: dup
    //   1936: iconst_0
    //   1937: ldc 8396801
    //   1939: iastore
    //   1940: dup
    //   1941: iconst_1
    //   1942: sipush #8321
    //   1945: iastore
    //   1946: dup
    //   1947: iconst_2
    //   1948: sipush #8321
    //   1951: iastore
    //   1952: dup
    //   1953: iconst_3
    //   1954: sipush #128
    //   1957: iastore
    //   1958: dup
    //   1959: iconst_4
    //   1960: ldc 8396928
    //   1962: iastore
    //   1963: dup
    //   1964: iconst_5
    //   1965: ldc 8388737
    //   1967: iastore
    //   1968: dup
    //   1969: bipush #6
    //   1971: ldc 8388609
    //   1973: iastore
    //   1974: dup
    //   1975: bipush #7
    //   1977: sipush #8193
    //   1980: iastore
    //   1981: dup
    //   1982: bipush #8
    //   1984: iconst_0
    //   1985: iastore
    //   1986: dup
    //   1987: bipush #9
    //   1989: ldc 8396800
    //   1991: iastore
    //   1992: dup
    //   1993: bipush #10
    //   1995: ldc 8396800
    //   1997: iastore
    //   1998: dup
    //   1999: bipush #11
    //   2001: ldc 8396929
    //   2003: iastore
    //   2004: dup
    //   2005: bipush #12
    //   2007: sipush #129
    //   2010: iastore
    //   2011: dup
    //   2012: bipush #13
    //   2014: iconst_0
    //   2015: iastore
    //   2016: dup
    //   2017: bipush #14
    //   2019: ldc 8388736
    //   2021: iastore
    //   2022: dup
    //   2023: bipush #15
    //   2025: ldc 8388609
    //   2027: iastore
    //   2028: dup
    //   2029: bipush #16
    //   2031: iconst_1
    //   2032: iastore
    //   2033: dup
    //   2034: bipush #17
    //   2036: sipush #8192
    //   2039: iastore
    //   2040: dup
    //   2041: bipush #18
    //   2043: ldc 8388608
    //   2045: iastore
    //   2046: dup
    //   2047: bipush #19
    //   2049: ldc 8396801
    //   2051: iastore
    //   2052: dup
    //   2053: bipush #20
    //   2055: sipush #128
    //   2058: iastore
    //   2059: dup
    //   2060: bipush #21
    //   2062: ldc 8388608
    //   2064: iastore
    //   2065: dup
    //   2066: bipush #22
    //   2068: sipush #8193
    //   2071: iastore
    //   2072: dup
    //   2073: bipush #23
    //   2075: sipush #8320
    //   2078: iastore
    //   2079: dup
    //   2080: bipush #24
    //   2082: ldc 8388737
    //   2084: iastore
    //   2085: dup
    //   2086: bipush #25
    //   2088: iconst_1
    //   2089: iastore
    //   2090: dup
    //   2091: bipush #26
    //   2093: sipush #8320
    //   2096: iastore
    //   2097: dup
    //   2098: bipush #27
    //   2100: ldc 8388736
    //   2102: iastore
    //   2103: dup
    //   2104: bipush #28
    //   2106: sipush #8192
    //   2109: iastore
    //   2110: dup
    //   2111: bipush #29
    //   2113: ldc 8396928
    //   2115: iastore
    //   2116: dup
    //   2117: bipush #30
    //   2119: ldc 8396929
    //   2121: iastore
    //   2122: dup
    //   2123: bipush #31
    //   2125: sipush #129
    //   2128: iastore
    //   2129: dup
    //   2130: bipush #32
    //   2132: ldc 8388736
    //   2134: iastore
    //   2135: dup
    //   2136: bipush #33
    //   2138: ldc 8388609
    //   2140: iastore
    //   2141: dup
    //   2142: bipush #34
    //   2144: ldc 8396800
    //   2146: iastore
    //   2147: dup
    //   2148: bipush #35
    //   2150: ldc 8396929
    //   2152: iastore
    //   2153: dup
    //   2154: bipush #36
    //   2156: sipush #129
    //   2159: iastore
    //   2160: dup
    //   2161: bipush #37
    //   2163: iconst_0
    //   2164: iastore
    //   2165: dup
    //   2166: bipush #38
    //   2168: iconst_0
    //   2169: iastore
    //   2170: dup
    //   2171: bipush #39
    //   2173: ldc 8396800
    //   2175: iastore
    //   2176: dup
    //   2177: bipush #40
    //   2179: sipush #8320
    //   2182: iastore
    //   2183: dup
    //   2184: bipush #41
    //   2186: ldc 8388736
    //   2188: iastore
    //   2189: dup
    //   2190: bipush #42
    //   2192: ldc 8388737
    //   2194: iastore
    //   2195: dup
    //   2196: bipush #43
    //   2198: iconst_1
    //   2199: iastore
    //   2200: dup
    //   2201: bipush #44
    //   2203: ldc 8396801
    //   2205: iastore
    //   2206: dup
    //   2207: bipush #45
    //   2209: sipush #8321
    //   2212: iastore
    //   2213: dup
    //   2214: bipush #46
    //   2216: sipush #8321
    //   2219: iastore
    //   2220: dup
    //   2221: bipush #47
    //   2223: sipush #128
    //   2226: iastore
    //   2227: dup
    //   2228: bipush #48
    //   2230: ldc 8396929
    //   2232: iastore
    //   2233: dup
    //   2234: bipush #49
    //   2236: sipush #129
    //   2239: iastore
    //   2240: dup
    //   2241: bipush #50
    //   2243: iconst_1
    //   2244: iastore
    //   2245: dup
    //   2246: bipush #51
    //   2248: sipush #8192
    //   2251: iastore
    //   2252: dup
    //   2253: bipush #52
    //   2255: ldc 8388609
    //   2257: iastore
    //   2258: dup
    //   2259: bipush #53
    //   2261: sipush #8193
    //   2264: iastore
    //   2265: dup
    //   2266: bipush #54
    //   2268: ldc 8396928
    //   2270: iastore
    //   2271: dup
    //   2272: bipush #55
    //   2274: ldc 8388737
    //   2276: iastore
    //   2277: dup
    //   2278: bipush #56
    //   2280: sipush #8193
    //   2283: iastore
    //   2284: dup
    //   2285: bipush #57
    //   2287: sipush #8320
    //   2290: iastore
    //   2291: dup
    //   2292: bipush #58
    //   2294: ldc 8388608
    //   2296: iastore
    //   2297: dup
    //   2298: bipush #59
    //   2300: ldc 8396801
    //   2302: iastore
    //   2303: dup
    //   2304: bipush #60
    //   2306: sipush #128
    //   2309: iastore
    //   2310: dup
    //   2311: bipush #61
    //   2313: ldc 8388608
    //   2315: iastore
    //   2316: dup
    //   2317: bipush #62
    //   2319: sipush #8192
    //   2322: iastore
    //   2323: dup
    //   2324: bipush #63
    //   2326: ldc 8396928
    //   2328: iastore
    //   2329: astore #9
    //   2331: bipush #64
    //   2333: newarray int
    //   2335: dup
    //   2336: iconst_0
    //   2337: sipush #256
    //   2340: iastore
    //   2341: dup
    //   2342: iconst_1
    //   2343: ldc 34078976
    //   2345: iastore
    //   2346: dup
    //   2347: iconst_2
    //   2348: ldc 34078720
    //   2350: iastore
    //   2351: dup
    //   2352: iconst_3
    //   2353: ldc 1107296512
    //   2355: iastore
    //   2356: dup
    //   2357: iconst_4
    //   2358: ldc 524288
    //   2360: iastore
    //   2361: dup
    //   2362: iconst_5
    //   2363: sipush #256
    //   2366: iastore
    //   2367: dup
    //   2368: bipush #6
    //   2370: ldc 1073741824
    //   2372: iastore
    //   2373: dup
    //   2374: bipush #7
    //   2376: ldc 34078720
    //   2378: iastore
    //   2379: dup
    //   2380: bipush #8
    //   2382: ldc 1074266368
    //   2384: iastore
    //   2385: dup
    //   2386: bipush #9
    //   2388: ldc 524288
    //   2390: iastore
    //   2391: dup
    //   2392: bipush #10
    //   2394: ldc 33554688
    //   2396: iastore
    //   2397: dup
    //   2398: bipush #11
    //   2400: ldc 1074266368
    //   2402: iastore
    //   2403: dup
    //   2404: bipush #12
    //   2406: ldc 1107296512
    //   2408: iastore
    //   2409: dup
    //   2410: bipush #13
    //   2412: ldc 1107820544
    //   2414: iastore
    //   2415: dup
    //   2416: bipush #14
    //   2418: ldc 524544
    //   2420: iastore
    //   2421: dup
    //   2422: bipush #15
    //   2424: ldc 1073741824
    //   2426: iastore
    //   2427: dup
    //   2428: bipush #16
    //   2430: ldc 33554432
    //   2432: iastore
    //   2433: dup
    //   2434: bipush #17
    //   2436: ldc 1074266112
    //   2438: iastore
    //   2439: dup
    //   2440: bipush #18
    //   2442: ldc 1074266112
    //   2444: iastore
    //   2445: dup
    //   2446: bipush #19
    //   2448: iconst_0
    //   2449: iastore
    //   2450: dup
    //   2451: bipush #20
    //   2453: ldc 1073742080
    //   2455: iastore
    //   2456: dup
    //   2457: bipush #21
    //   2459: ldc 1107820800
    //   2461: iastore
    //   2462: dup
    //   2463: bipush #22
    //   2465: ldc 1107820800
    //   2467: iastore
    //   2468: dup
    //   2469: bipush #23
    //   2471: ldc 33554688
    //   2473: iastore
    //   2474: dup
    //   2475: bipush #24
    //   2477: ldc 1107820544
    //   2479: iastore
    //   2480: dup
    //   2481: bipush #25
    //   2483: ldc 1073742080
    //   2485: iastore
    //   2486: dup
    //   2487: bipush #26
    //   2489: iconst_0
    //   2490: iastore
    //   2491: dup
    //   2492: bipush #27
    //   2494: ldc 1107296256
    //   2496: iastore
    //   2497: dup
    //   2498: bipush #28
    //   2500: ldc 34078976
    //   2502: iastore
    //   2503: dup
    //   2504: bipush #29
    //   2506: ldc 33554432
    //   2508: iastore
    //   2509: dup
    //   2510: bipush #30
    //   2512: ldc 1107296256
    //   2514: iastore
    //   2515: dup
    //   2516: bipush #31
    //   2518: ldc 524544
    //   2520: iastore
    //   2521: dup
    //   2522: bipush #32
    //   2524: ldc 524288
    //   2526: iastore
    //   2527: dup
    //   2528: bipush #33
    //   2530: ldc 1107296512
    //   2532: iastore
    //   2533: dup
    //   2534: bipush #34
    //   2536: sipush #256
    //   2539: iastore
    //   2540: dup
    //   2541: bipush #35
    //   2543: ldc 33554432
    //   2545: iastore
    //   2546: dup
    //   2547: bipush #36
    //   2549: ldc 1073741824
    //   2551: iastore
    //   2552: dup
    //   2553: bipush #37
    //   2555: ldc 34078720
    //   2557: iastore
    //   2558: dup
    //   2559: bipush #38
    //   2561: ldc 1107296512
    //   2563: iastore
    //   2564: dup
    //   2565: bipush #39
    //   2567: ldc 1074266368
    //   2569: iastore
    //   2570: dup
    //   2571: bipush #40
    //   2573: ldc 33554688
    //   2575: iastore
    //   2576: dup
    //   2577: bipush #41
    //   2579: ldc 1073741824
    //   2581: iastore
    //   2582: dup
    //   2583: bipush #42
    //   2585: ldc 1107820544
    //   2587: iastore
    //   2588: dup
    //   2589: bipush #43
    //   2591: ldc 34078976
    //   2593: iastore
    //   2594: dup
    //   2595: bipush #44
    //   2597: ldc 1074266368
    //   2599: iastore
    //   2600: dup
    //   2601: bipush #45
    //   2603: sipush #256
    //   2606: iastore
    //   2607: dup
    //   2608: bipush #46
    //   2610: ldc 33554432
    //   2612: iastore
    //   2613: dup
    //   2614: bipush #47
    //   2616: ldc 1107820544
    //   2618: iastore
    //   2619: dup
    //   2620: bipush #48
    //   2622: ldc 1107820800
    //   2624: iastore
    //   2625: dup
    //   2626: bipush #49
    //   2628: ldc 524544
    //   2630: iastore
    //   2631: dup
    //   2632: bipush #50
    //   2634: ldc 1107296256
    //   2636: iastore
    //   2637: dup
    //   2638: bipush #51
    //   2640: ldc 1107820800
    //   2642: iastore
    //   2643: dup
    //   2644: bipush #52
    //   2646: ldc 34078720
    //   2648: iastore
    //   2649: dup
    //   2650: bipush #53
    //   2652: iconst_0
    //   2653: iastore
    //   2654: dup
    //   2655: bipush #54
    //   2657: ldc 1074266112
    //   2659: iastore
    //   2660: dup
    //   2661: bipush #55
    //   2663: ldc 1107296256
    //   2665: iastore
    //   2666: dup
    //   2667: bipush #56
    //   2669: ldc 524544
    //   2671: iastore
    //   2672: dup
    //   2673: bipush #57
    //   2675: ldc 33554688
    //   2677: iastore
    //   2678: dup
    //   2679: bipush #58
    //   2681: ldc 1073742080
    //   2683: iastore
    //   2684: dup
    //   2685: bipush #59
    //   2687: ldc 524288
    //   2689: iastore
    //   2690: dup
    //   2691: bipush #60
    //   2693: iconst_0
    //   2694: iastore
    //   2695: dup
    //   2696: bipush #61
    //   2698: ldc 1074266112
    //   2700: iastore
    //   2701: dup
    //   2702: bipush #62
    //   2704: ldc 34078976
    //   2706: iastore
    //   2707: dup
    //   2708: bipush #63
    //   2710: ldc 1073742080
    //   2712: iastore
    //   2713: astore #10
    //   2715: bipush #64
    //   2717: newarray int
    //   2719: dup
    //   2720: iconst_0
    //   2721: ldc 536870928
    //   2723: iastore
    //   2724: dup
    //   2725: iconst_1
    //   2726: ldc 541065216
    //   2728: iastore
    //   2729: dup
    //   2730: iconst_2
    //   2731: sipush #16384
    //   2734: iastore
    //   2735: dup
    //   2736: iconst_3
    //   2737: ldc 541081616
    //   2739: iastore
    //   2740: dup
    //   2741: iconst_4
    //   2742: ldc 541065216
    //   2744: iastore
    //   2745: dup
    //   2746: iconst_5
    //   2747: bipush #16
    //   2749: iastore
    //   2750: dup
    //   2751: bipush #6
    //   2753: ldc 541081616
    //   2755: iastore
    //   2756: dup
    //   2757: bipush #7
    //   2759: ldc 4194304
    //   2761: iastore
    //   2762: dup
    //   2763: bipush #8
    //   2765: ldc 536887296
    //   2767: iastore
    //   2768: dup
    //   2769: bipush #9
    //   2771: ldc 4210704
    //   2773: iastore
    //   2774: dup
    //   2775: bipush #10
    //   2777: ldc 4194304
    //   2779: iastore
    //   2780: dup
    //   2781: bipush #11
    //   2783: ldc 536870928
    //   2785: iastore
    //   2786: dup
    //   2787: bipush #12
    //   2789: ldc 4194320
    //   2791: iastore
    //   2792: dup
    //   2793: bipush #13
    //   2795: ldc 536887296
    //   2797: iastore
    //   2798: dup
    //   2799: bipush #14
    //   2801: ldc 536870912
    //   2803: iastore
    //   2804: dup
    //   2805: bipush #15
    //   2807: sipush #16400
    //   2810: iastore
    //   2811: dup
    //   2812: bipush #16
    //   2814: iconst_0
    //   2815: iastore
    //   2816: dup
    //   2817: bipush #17
    //   2819: ldc 4194320
    //   2821: iastore
    //   2822: dup
    //   2823: bipush #18
    //   2825: ldc 536887312
    //   2827: iastore
    //   2828: dup
    //   2829: bipush #19
    //   2831: sipush #16384
    //   2834: iastore
    //   2835: dup
    //   2836: bipush #20
    //   2838: ldc 4210688
    //   2840: iastore
    //   2841: dup
    //   2842: bipush #21
    //   2844: ldc 536887312
    //   2846: iastore
    //   2847: dup
    //   2848: bipush #22
    //   2850: bipush #16
    //   2852: iastore
    //   2853: dup
    //   2854: bipush #23
    //   2856: ldc 541065232
    //   2858: iastore
    //   2859: dup
    //   2860: bipush #24
    //   2862: ldc 541065232
    //   2864: iastore
    //   2865: dup
    //   2866: bipush #25
    //   2868: iconst_0
    //   2869: iastore
    //   2870: dup
    //   2871: bipush #26
    //   2873: ldc 4210704
    //   2875: iastore
    //   2876: dup
    //   2877: bipush #27
    //   2879: ldc 541081600
    //   2881: iastore
    //   2882: dup
    //   2883: bipush #28
    //   2885: sipush #16400
    //   2888: iastore
    //   2889: dup
    //   2890: bipush #29
    //   2892: ldc 4210688
    //   2894: iastore
    //   2895: dup
    //   2896: bipush #30
    //   2898: ldc 541081600
    //   2900: iastore
    //   2901: dup
    //   2902: bipush #31
    //   2904: ldc 536870912
    //   2906: iastore
    //   2907: dup
    //   2908: bipush #32
    //   2910: ldc 536887296
    //   2912: iastore
    //   2913: dup
    //   2914: bipush #33
    //   2916: bipush #16
    //   2918: iastore
    //   2919: dup
    //   2920: bipush #34
    //   2922: ldc 541065232
    //   2924: iastore
    //   2925: dup
    //   2926: bipush #35
    //   2928: ldc 4210688
    //   2930: iastore
    //   2931: dup
    //   2932: bipush #36
    //   2934: ldc 541081616
    //   2936: iastore
    //   2937: dup
    //   2938: bipush #37
    //   2940: ldc 4194304
    //   2942: iastore
    //   2943: dup
    //   2944: bipush #38
    //   2946: sipush #16400
    //   2949: iastore
    //   2950: dup
    //   2951: bipush #39
    //   2953: ldc 536870928
    //   2955: iastore
    //   2956: dup
    //   2957: bipush #40
    //   2959: ldc 4194304
    //   2961: iastore
    //   2962: dup
    //   2963: bipush #41
    //   2965: ldc 536887296
    //   2967: iastore
    //   2968: dup
    //   2969: bipush #42
    //   2971: ldc 536870912
    //   2973: iastore
    //   2974: dup
    //   2975: bipush #43
    //   2977: sipush #16400
    //   2980: iastore
    //   2981: dup
    //   2982: bipush #44
    //   2984: ldc 536870928
    //   2986: iastore
    //   2987: dup
    //   2988: bipush #45
    //   2990: ldc 541081616
    //   2992: iastore
    //   2993: dup
    //   2994: bipush #46
    //   2996: ldc 4210688
    //   2998: iastore
    //   2999: dup
    //   3000: bipush #47
    //   3002: ldc 541065216
    //   3004: iastore
    //   3005: dup
    //   3006: bipush #48
    //   3008: ldc 4210704
    //   3010: iastore
    //   3011: dup
    //   3012: bipush #49
    //   3014: ldc 541081600
    //   3016: iastore
    //   3017: dup
    //   3018: bipush #50
    //   3020: iconst_0
    //   3021: iastore
    //   3022: dup
    //   3023: bipush #51
    //   3025: ldc 541065232
    //   3027: iastore
    //   3028: dup
    //   3029: bipush #52
    //   3031: bipush #16
    //   3033: iastore
    //   3034: dup
    //   3035: bipush #53
    //   3037: sipush #16384
    //   3040: iastore
    //   3041: dup
    //   3042: bipush #54
    //   3044: ldc 541065216
    //   3046: iastore
    //   3047: dup
    //   3048: bipush #55
    //   3050: ldc 4210704
    //   3052: iastore
    //   3053: dup
    //   3054: bipush #56
    //   3056: sipush #16384
    //   3059: iastore
    //   3060: dup
    //   3061: bipush #57
    //   3063: ldc 4194320
    //   3065: iastore
    //   3066: dup
    //   3067: bipush #58
    //   3069: ldc 536887312
    //   3071: iastore
    //   3072: dup
    //   3073: bipush #59
    //   3075: iconst_0
    //   3076: iastore
    //   3077: dup
    //   3078: bipush #60
    //   3080: ldc 541081600
    //   3082: iastore
    //   3083: dup
    //   3084: bipush #61
    //   3086: ldc 536870912
    //   3088: iastore
    //   3089: dup
    //   3090: bipush #62
    //   3092: ldc 4194320
    //   3094: iastore
    //   3095: dup
    //   3096: bipush #63
    //   3098: ldc 536887312
    //   3100: iastore
    //   3101: astore #11
    //   3103: bipush #64
    //   3105: newarray int
    //   3107: dup
    //   3108: iconst_0
    //   3109: ldc 2097152
    //   3111: iastore
    //   3112: dup
    //   3113: iconst_1
    //   3114: ldc 69206018
    //   3116: iastore
    //   3117: dup
    //   3118: iconst_2
    //   3119: ldc 67110914
    //   3121: iastore
    //   3122: dup
    //   3123: iconst_3
    //   3124: iconst_0
    //   3125: iastore
    //   3126: dup
    //   3127: iconst_4
    //   3128: sipush #2048
    //   3131: iastore
    //   3132: dup
    //   3133: iconst_5
    //   3134: ldc 67110914
    //   3136: iastore
    //   3137: dup
    //   3138: bipush #6
    //   3140: ldc 2099202
    //   3142: iastore
    //   3143: dup
    //   3144: bipush #7
    //   3146: ldc 69208064
    //   3148: iastore
    //   3149: dup
    //   3150: bipush #8
    //   3152: ldc 69208066
    //   3154: iastore
    //   3155: dup
    //   3156: bipush #9
    //   3158: ldc 2097152
    //   3160: iastore
    //   3161: dup
    //   3162: bipush #10
    //   3164: iconst_0
    //   3165: iastore
    //   3166: dup
    //   3167: bipush #11
    //   3169: ldc 67108866
    //   3171: iastore
    //   3172: dup
    //   3173: bipush #12
    //   3175: iconst_2
    //   3176: iastore
    //   3177: dup
    //   3178: bipush #13
    //   3180: ldc 67108864
    //   3182: iastore
    //   3183: dup
    //   3184: bipush #14
    //   3186: ldc 69206018
    //   3188: iastore
    //   3189: dup
    //   3190: bipush #15
    //   3192: sipush #2050
    //   3195: iastore
    //   3196: dup
    //   3197: bipush #16
    //   3199: ldc 67110912
    //   3201: iastore
    //   3202: dup
    //   3203: bipush #17
    //   3205: ldc 2099202
    //   3207: iastore
    //   3208: dup
    //   3209: bipush #18
    //   3211: ldc 2097154
    //   3213: iastore
    //   3214: dup
    //   3215: bipush #19
    //   3217: ldc 67110912
    //   3219: iastore
    //   3220: dup
    //   3221: bipush #20
    //   3223: ldc 67108866
    //   3225: iastore
    //   3226: dup
    //   3227: bipush #21
    //   3229: ldc 69206016
    //   3231: iastore
    //   3232: dup
    //   3233: bipush #22
    //   3235: ldc 69208064
    //   3237: iastore
    //   3238: dup
    //   3239: bipush #23
    //   3241: ldc 2097154
    //   3243: iastore
    //   3244: dup
    //   3245: bipush #24
    //   3247: ldc 69206016
    //   3249: iastore
    //   3250: dup
    //   3251: bipush #25
    //   3253: sipush #2048
    //   3256: iastore
    //   3257: dup
    //   3258: bipush #26
    //   3260: sipush #2050
    //   3263: iastore
    //   3264: dup
    //   3265: bipush #27
    //   3267: ldc 69208066
    //   3269: iastore
    //   3270: dup
    //   3271: bipush #28
    //   3273: ldc 2099200
    //   3275: iastore
    //   3276: dup
    //   3277: bipush #29
    //   3279: iconst_2
    //   3280: iastore
    //   3281: dup
    //   3282: bipush #30
    //   3284: ldc 67108864
    //   3286: iastore
    //   3287: dup
    //   3288: bipush #31
    //   3290: ldc 2099200
    //   3292: iastore
    //   3293: dup
    //   3294: bipush #32
    //   3296: ldc 67108864
    //   3298: iastore
    //   3299: dup
    //   3300: bipush #33
    //   3302: ldc 2099200
    //   3304: iastore
    //   3305: dup
    //   3306: bipush #34
    //   3308: ldc 2097152
    //   3310: iastore
    //   3311: dup
    //   3312: bipush #35
    //   3314: ldc 67110914
    //   3316: iastore
    //   3317: dup
    //   3318: bipush #36
    //   3320: ldc 67110914
    //   3322: iastore
    //   3323: dup
    //   3324: bipush #37
    //   3326: ldc 69206018
    //   3328: iastore
    //   3329: dup
    //   3330: bipush #38
    //   3332: ldc 69206018
    //   3334: iastore
    //   3335: dup
    //   3336: bipush #39
    //   3338: iconst_2
    //   3339: iastore
    //   3340: dup
    //   3341: bipush #40
    //   3343: ldc 2097154
    //   3345: iastore
    //   3346: dup
    //   3347: bipush #41
    //   3349: ldc 67108864
    //   3351: iastore
    //   3352: dup
    //   3353: bipush #42
    //   3355: ldc 67110912
    //   3357: iastore
    //   3358: dup
    //   3359: bipush #43
    //   3361: ldc 2097152
    //   3363: iastore
    //   3364: dup
    //   3365: bipush #44
    //   3367: ldc 69208064
    //   3369: iastore
    //   3370: dup
    //   3371: bipush #45
    //   3373: sipush #2050
    //   3376: iastore
    //   3377: dup
    //   3378: bipush #46
    //   3380: ldc 2099202
    //   3382: iastore
    //   3383: dup
    //   3384: bipush #47
    //   3386: ldc 69208064
    //   3388: iastore
    //   3389: dup
    //   3390: bipush #48
    //   3392: sipush #2050
    //   3395: iastore
    //   3396: dup
    //   3397: bipush #49
    //   3399: ldc 67108866
    //   3401: iastore
    //   3402: dup
    //   3403: bipush #50
    //   3405: ldc 69208066
    //   3407: iastore
    //   3408: dup
    //   3409: bipush #51
    //   3411: ldc 69206016
    //   3413: iastore
    //   3414: dup
    //   3415: bipush #52
    //   3417: ldc 2099200
    //   3419: iastore
    //   3420: dup
    //   3421: bipush #53
    //   3423: iconst_0
    //   3424: iastore
    //   3425: dup
    //   3426: bipush #54
    //   3428: iconst_2
    //   3429: iastore
    //   3430: dup
    //   3431: bipush #55
    //   3433: ldc 69208066
    //   3435: iastore
    //   3436: dup
    //   3437: bipush #56
    //   3439: iconst_0
    //   3440: iastore
    //   3441: dup
    //   3442: bipush #57
    //   3444: ldc 2099202
    //   3446: iastore
    //   3447: dup
    //   3448: bipush #58
    //   3450: ldc 69206016
    //   3452: iastore
    //   3453: dup
    //   3454: bipush #59
    //   3456: sipush #2048
    //   3459: iastore
    //   3460: dup
    //   3461: bipush #60
    //   3463: ldc 67108866
    //   3465: iastore
    //   3466: dup
    //   3467: bipush #61
    //   3469: ldc 67110912
    //   3471: iastore
    //   3472: dup
    //   3473: bipush #62
    //   3475: sipush #2048
    //   3478: iastore
    //   3479: dup
    //   3480: bipush #63
    //   3482: ldc 2097154
    //   3484: iastore
    //   3485: astore #12
    //   3487: bipush #64
    //   3489: newarray int
    //   3491: dup
    //   3492: iconst_0
    //   3493: ldc 268439616
    //   3495: iastore
    //   3496: dup
    //   3497: iconst_1
    //   3498: sipush #4096
    //   3501: iastore
    //   3502: dup
    //   3503: iconst_2
    //   3504: ldc 262144
    //   3506: iastore
    //   3507: dup
    //   3508: iconst_3
    //   3509: ldc 268701760
    //   3511: iastore
    //   3512: dup
    //   3513: iconst_4
    //   3514: ldc 268435456
    //   3516: iastore
    //   3517: dup
    //   3518: iconst_5
    //   3519: ldc 268439616
    //   3521: iastore
    //   3522: dup
    //   3523: bipush #6
    //   3525: bipush #64
    //   3527: iastore
    //   3528: dup
    //   3529: bipush #7
    //   3531: ldc 268435456
    //   3533: iastore
    //   3534: dup
    //   3535: bipush #8
    //   3537: ldc 262208
    //   3539: iastore
    //   3540: dup
    //   3541: bipush #9
    //   3543: ldc 268697600
    //   3545: iastore
    //   3546: dup
    //   3547: bipush #10
    //   3549: ldc 268701760
    //   3551: iastore
    //   3552: dup
    //   3553: bipush #11
    //   3555: ldc 266240
    //   3557: iastore
    //   3558: dup
    //   3559: bipush #12
    //   3561: ldc 268701696
    //   3563: iastore
    //   3564: dup
    //   3565: bipush #13
    //   3567: ldc 266304
    //   3569: iastore
    //   3570: dup
    //   3571: bipush #14
    //   3573: sipush #4096
    //   3576: iastore
    //   3577: dup
    //   3578: bipush #15
    //   3580: bipush #64
    //   3582: iastore
    //   3583: dup
    //   3584: bipush #16
    //   3586: ldc 268697600
    //   3588: iastore
    //   3589: dup
    //   3590: bipush #17
    //   3592: ldc 268435520
    //   3594: iastore
    //   3595: dup
    //   3596: bipush #18
    //   3598: ldc 268439552
    //   3600: iastore
    //   3601: dup
    //   3602: bipush #19
    //   3604: sipush #4160
    //   3607: iastore
    //   3608: dup
    //   3609: bipush #20
    //   3611: ldc 266240
    //   3613: iastore
    //   3614: dup
    //   3615: bipush #21
    //   3617: ldc 262208
    //   3619: iastore
    //   3620: dup
    //   3621: bipush #22
    //   3623: ldc 268697664
    //   3625: iastore
    //   3626: dup
    //   3627: bipush #23
    //   3629: ldc 268701696
    //   3631: iastore
    //   3632: dup
    //   3633: bipush #24
    //   3635: sipush #4160
    //   3638: iastore
    //   3639: dup
    //   3640: bipush #25
    //   3642: iconst_0
    //   3643: iastore
    //   3644: dup
    //   3645: bipush #26
    //   3647: iconst_0
    //   3648: iastore
    //   3649: dup
    //   3650: bipush #27
    //   3652: ldc 268697664
    //   3654: iastore
    //   3655: dup
    //   3656: bipush #28
    //   3658: ldc 268435520
    //   3660: iastore
    //   3661: dup
    //   3662: bipush #29
    //   3664: ldc 268439552
    //   3666: iastore
    //   3667: dup
    //   3668: bipush #30
    //   3670: ldc 266304
    //   3672: iastore
    //   3673: dup
    //   3674: bipush #31
    //   3676: ldc 262144
    //   3678: iastore
    //   3679: dup
    //   3680: bipush #32
    //   3682: ldc 266304
    //   3684: iastore
    //   3685: dup
    //   3686: bipush #33
    //   3688: ldc 262144
    //   3690: iastore
    //   3691: dup
    //   3692: bipush #34
    //   3694: ldc 268701696
    //   3696: iastore
    //   3697: dup
    //   3698: bipush #35
    //   3700: sipush #4096
    //   3703: iastore
    //   3704: dup
    //   3705: bipush #36
    //   3707: bipush #64
    //   3709: iastore
    //   3710: dup
    //   3711: bipush #37
    //   3713: ldc 268697664
    //   3715: iastore
    //   3716: dup
    //   3717: bipush #38
    //   3719: sipush #4096
    //   3722: iastore
    //   3723: dup
    //   3724: bipush #39
    //   3726: ldc 266304
    //   3728: iastore
    //   3729: dup
    //   3730: bipush #40
    //   3732: ldc 268439552
    //   3734: iastore
    //   3735: dup
    //   3736: bipush #41
    //   3738: bipush #64
    //   3740: iastore
    //   3741: dup
    //   3742: bipush #42
    //   3744: ldc 268435520
    //   3746: iastore
    //   3747: dup
    //   3748: bipush #43
    //   3750: ldc 268697600
    //   3752: iastore
    //   3753: dup
    //   3754: bipush #44
    //   3756: ldc 268697664
    //   3758: iastore
    //   3759: dup
    //   3760: bipush #45
    //   3762: ldc 268435456
    //   3764: iastore
    //   3765: dup
    //   3766: bipush #46
    //   3768: ldc 262144
    //   3770: iastore
    //   3771: dup
    //   3772: bipush #47
    //   3774: ldc 268439616
    //   3776: iastore
    //   3777: dup
    //   3778: bipush #48
    //   3780: iconst_0
    //   3781: iastore
    //   3782: dup
    //   3783: bipush #49
    //   3785: ldc 268701760
    //   3787: iastore
    //   3788: dup
    //   3789: bipush #50
    //   3791: ldc 262208
    //   3793: iastore
    //   3794: dup
    //   3795: bipush #51
    //   3797: ldc 268435520
    //   3799: iastore
    //   3800: dup
    //   3801: bipush #52
    //   3803: ldc 268697600
    //   3805: iastore
    //   3806: dup
    //   3807: bipush #53
    //   3809: ldc 268439552
    //   3811: iastore
    //   3812: dup
    //   3813: bipush #54
    //   3815: ldc 268439616
    //   3817: iastore
    //   3818: dup
    //   3819: bipush #55
    //   3821: iconst_0
    //   3822: iastore
    //   3823: dup
    //   3824: bipush #56
    //   3826: ldc 268701760
    //   3828: iastore
    //   3829: dup
    //   3830: bipush #57
    //   3832: ldc 266240
    //   3834: iastore
    //   3835: dup
    //   3836: bipush #58
    //   3838: ldc 266240
    //   3840: iastore
    //   3841: dup
    //   3842: bipush #59
    //   3844: sipush #4160
    //   3847: iastore
    //   3848: dup
    //   3849: bipush #60
    //   3851: sipush #4160
    //   3854: iastore
    //   3855: dup
    //   3856: bipush #61
    //   3858: ldc 262208
    //   3860: iastore
    //   3861: dup
    //   3862: bipush #62
    //   3864: ldc 268435456
    //   3866: iastore
    //   3867: dup
    //   3868: bipush #63
    //   3870: ldc 268701696
    //   3872: iastore
    //   3873: astore #13
    //   3875: aload_3
    //   3876: arraylength
    //   3877: istore #14
    //   3879: iload #14
    //   3881: bipush #8
    //   3883: irem
    //   3884: ifeq -> 3908
    //   3887: new java/lang/Exception
    //   3890: dup
    //   3891: sipush #-24770
    //   3894: sipush #16014
    //   3897: invokestatic a : (II)Ljava/lang/String;
    //   3900: invokespecial <init> : (Ljava/lang/String;)V
    //   3903: athrow
    //   3904: invokestatic a : (Ljava/lang/Throwable;)Ljava/lang/Throwable;
    //   3907: athrow
    //   3908: iconst_2
    //   3909: newarray int
    //   3911: astore #15
    //   3913: iload #14
    //   3915: newarray byte
    //   3917: astore #16
    //   3919: iload #14
    //   3921: bipush #8
    //   3923: idiv
    //   3924: istore #17
    //   3926: iconst_0
    //   3927: istore #18
    //   3929: iload #18
    //   3931: iload #17
    //   3933: if_icmpge -> 4847
    //   3936: iload #18
    //   3938: bipush #8
    //   3940: imul
    //   3941: istore #19
    //   3943: iconst_0
    //   3944: istore #20
    //   3946: iload #20
    //   3948: iconst_2
    //   3949: if_icmpge -> 4034
    //   3952: aload #15
    //   3954: iload #20
    //   3956: aload_3
    //   3957: iload #19
    //   3959: iload #20
    //   3961: iconst_4
    //   3962: imul
    //   3963: iadd
    //   3964: baload
    //   3965: sipush #255
    //   3968: iand
    //   3969: bipush #24
    //   3971: ishl
    //   3972: aload_3
    //   3973: iload #19
    //   3975: iload #20
    //   3977: iconst_4
    //   3978: imul
    //   3979: iadd
    //   3980: iconst_1
    //   3981: iadd
    //   3982: baload
    //   3983: sipush #255
    //   3986: iand
    //   3987: bipush #16
    //   3989: ishl
    //   3990: ior
    //   3991: aload_3
    //   3992: iload #19
    //   3994: iload #20
    //   3996: iconst_4
    //   3997: imul
    //   3998: iadd
    //   3999: iconst_2
    //   4000: iadd
    //   4001: baload
    //   4002: sipush #255
    //   4005: iand
    //   4006: bipush #8
    //   4008: ishl
    //   4009: ior
    //   4010: aload_3
    //   4011: iload #19
    //   4013: iload #20
    //   4015: iconst_4
    //   4016: imul
    //   4017: iadd
    //   4018: iconst_3
    //   4019: iadd
    //   4020: baload
    //   4021: sipush #255
    //   4024: iand
    //   4025: ior
    //   4026: iastore
    //   4027: iinc #20, 1
    //   4030: iload_2
    //   4031: ifne -> 3946
    //   4034: iconst_0
    //   4035: istore #25
    //   4037: aload #15
    //   4039: iconst_0
    //   4040: iaload
    //   4041: istore #23
    //   4043: aload #15
    //   4045: iconst_1
    //   4046: iaload
    //   4047: istore #22
    //   4049: iload #23
    //   4051: iconst_4
    //   4052: iushr
    //   4053: iload #22
    //   4055: ixor
    //   4056: ldc 252645135
    //   4058: iand
    //   4059: istore #21
    //   4061: iload #22
    //   4063: iload #21
    //   4065: ixor
    //   4066: istore #22
    //   4068: iload #23
    //   4070: iload #21
    //   4072: iconst_4
    //   4073: ishl
    //   4074: ixor
    //   4075: istore #23
    //   4077: iload #23
    //   4079: bipush #16
    //   4081: iushr
    //   4082: iload #22
    //   4084: ixor
    //   4085: ldc 65535
    //   4087: iand
    //   4088: istore #21
    //   4090: iload #22
    //   4092: iload #21
    //   4094: ixor
    //   4095: istore #22
    //   4097: iload #23
    //   4099: iload #21
    //   4101: bipush #16
    //   4103: ishl
    //   4104: ixor
    //   4105: istore #23
    //   4107: iload #22
    //   4109: iconst_2
    //   4110: iushr
    //   4111: iload #23
    //   4113: ixor
    //   4114: ldc 858993459
    //   4116: iand
    //   4117: istore #21
    //   4119: iload #23
    //   4121: iload #21
    //   4123: ixor
    //   4124: istore #23
    //   4126: iload #22
    //   4128: iload #21
    //   4130: iconst_2
    //   4131: ishl
    //   4132: ixor
    //   4133: istore #22
    //   4135: iload #22
    //   4137: bipush #8
    //   4139: iushr
    //   4140: iload #23
    //   4142: ixor
    //   4143: ldc 16711935
    //   4145: iand
    //   4146: istore #21
    //   4148: iload #23
    //   4150: iload #21
    //   4152: ixor
    //   4153: istore #23
    //   4155: iload #22
    //   4157: iload #21
    //   4159: bipush #8
    //   4161: ishl
    //   4162: ixor
    //   4163: istore #22
    //   4165: iload #22
    //   4167: iconst_1
    //   4168: ishl
    //   4169: iload #22
    //   4171: bipush #31
    //   4173: iushr
    //   4174: iconst_1
    //   4175: iand
    //   4176: ior
    //   4177: istore #22
    //   4179: iload #23
    //   4181: iload #22
    //   4183: ixor
    //   4184: ldc -1431655766
    //   4186: iand
    //   4187: istore #21
    //   4189: iload #23
    //   4191: iload #21
    //   4193: ixor
    //   4194: istore #23
    //   4196: iload #22
    //   4198: iload #21
    //   4200: ixor
    //   4201: istore #22
    //   4203: iload #23
    //   4205: iconst_1
    //   4206: ishl
    //   4207: iload #23
    //   4209: bipush #31
    //   4211: iushr
    //   4212: iconst_1
    //   4213: iand
    //   4214: ior
    //   4215: istore #23
    //   4217: iconst_0
    //   4218: istore #24
    //   4220: iload #24
    //   4222: bipush #8
    //   4224: if_icmpge -> 4562
    //   4227: iload #22
    //   4229: bipush #28
    //   4231: ishl
    //   4232: iload #22
    //   4234: iconst_4
    //   4235: iushr
    //   4236: ior
    //   4237: istore #21
    //   4239: iload #21
    //   4241: aload #5
    //   4243: iload #25
    //   4245: iinc #25, 1
    //   4248: iaload
    //   4249: ixor
    //   4250: istore #21
    //   4252: aload #12
    //   4254: iload #21
    //   4256: bipush #63
    //   4258: iand
    //   4259: iaload
    //   4260: istore #20
    //   4262: iload #20
    //   4264: aload #10
    //   4266: iload #21
    //   4268: bipush #8
    //   4270: iushr
    //   4271: bipush #63
    //   4273: iand
    //   4274: iaload
    //   4275: ior
    //   4276: istore #20
    //   4278: iload #20
    //   4280: aload #8
    //   4282: iload #21
    //   4284: bipush #16
    //   4286: iushr
    //   4287: bipush #63
    //   4289: iand
    //   4290: iaload
    //   4291: ior
    //   4292: istore #20
    //   4294: iload #20
    //   4296: aload #6
    //   4298: iload #21
    //   4300: bipush #24
    //   4302: iushr
    //   4303: bipush #63
    //   4305: iand
    //   4306: iaload
    //   4307: ior
    //   4308: istore #20
    //   4310: iload #22
    //   4312: aload #5
    //   4314: iload #25
    //   4316: iinc #25, 1
    //   4319: iaload
    //   4320: ixor
    //   4321: istore #21
    //   4323: iload #20
    //   4325: aload #13
    //   4327: iload #21
    //   4329: bipush #63
    //   4331: iand
    //   4332: iaload
    //   4333: ior
    //   4334: istore #20
    //   4336: iload #20
    //   4338: aload #11
    //   4340: iload #21
    //   4342: bipush #8
    //   4344: iushr
    //   4345: bipush #63
    //   4347: iand
    //   4348: iaload
    //   4349: ior
    //   4350: istore #20
    //   4352: iload #20
    //   4354: aload #9
    //   4356: iload #21
    //   4358: bipush #16
    //   4360: iushr
    //   4361: bipush #63
    //   4363: iand
    //   4364: iaload
    //   4365: ior
    //   4366: istore #20
    //   4368: iload #20
    //   4370: aload #7
    //   4372: iload #21
    //   4374: bipush #24
    //   4376: iushr
    //   4377: bipush #63
    //   4379: iand
    //   4380: iaload
    //   4381: ior
    //   4382: istore #20
    //   4384: iload #23
    //   4386: iload #20
    //   4388: ixor
    //   4389: istore #23
    //   4391: iload #23
    //   4393: bipush #28
    //   4395: ishl
    //   4396: iload #23
    //   4398: iconst_4
    //   4399: iushr
    //   4400: ior
    //   4401: istore #21
    //   4403: iload #21
    //   4405: aload #5
    //   4407: iload #25
    //   4409: iinc #25, 1
    //   4412: iaload
    //   4413: ixor
    //   4414: istore #21
    //   4416: aload #12
    //   4418: iload #21
    //   4420: bipush #63
    //   4422: iand
    //   4423: iaload
    //   4424: istore #20
    //   4426: iload #20
    //   4428: aload #10
    //   4430: iload #21
    //   4432: bipush #8
    //   4434: iushr
    //   4435: bipush #63
    //   4437: iand
    //   4438: iaload
    //   4439: ior
    //   4440: istore #20
    //   4442: iload #20
    //   4444: aload #8
    //   4446: iload #21
    //   4448: bipush #16
    //   4450: iushr
    //   4451: bipush #63
    //   4453: iand
    //   4454: iaload
    //   4455: ior
    //   4456: istore #20
    //   4458: iload #20
    //   4460: aload #6
    //   4462: iload #21
    //   4464: bipush #24
    //   4466: iushr
    //   4467: bipush #63
    //   4469: iand
    //   4470: iaload
    //   4471: ior
    //   4472: istore #20
    //   4474: iload #23
    //   4476: aload #5
    //   4478: iload #25
    //   4480: iinc #25, 1
    //   4483: iaload
    //   4484: ixor
    //   4485: istore #21
    //   4487: iload #20
    //   4489: aload #13
    //   4491: iload #21
    //   4493: bipush #63
    //   4495: iand
    //   4496: iaload
    //   4497: ior
    //   4498: istore #20
    //   4500: iload #20
    //   4502: aload #11
    //   4504: iload #21
    //   4506: bipush #8
    //   4508: iushr
    //   4509: bipush #63
    //   4511: iand
    //   4512: iaload
    //   4513: ior
    //   4514: istore #20
    //   4516: iload #20
    //   4518: aload #9
    //   4520: iload #21
    //   4522: bipush #16
    //   4524: iushr
    //   4525: bipush #63
    //   4527: iand
    //   4528: iaload
    //   4529: ior
    //   4530: istore #20
    //   4532: iload #20
    //   4534: aload #7
    //   4536: iload #21
    //   4538: bipush #24
    //   4540: iushr
    //   4541: bipush #63
    //   4543: iand
    //   4544: iaload
    //   4545: ior
    //   4546: istore #20
    //   4548: iload #22
    //   4550: iload #20
    //   4552: ixor
    //   4553: istore #22
    //   4555: iinc #24, 1
    //   4558: iload_2
    //   4559: ifne -> 4220
    //   4562: iload #22
    //   4564: bipush #31
    //   4566: ishl
    //   4567: iload #22
    //   4569: iconst_1
    //   4570: iushr
    //   4571: ior
    //   4572: istore #22
    //   4574: iload #23
    //   4576: iload #22
    //   4578: ixor
    //   4579: ldc -1431655766
    //   4581: iand
    //   4582: istore #21
    //   4584: iload #23
    //   4586: iload #21
    //   4588: ixor
    //   4589: istore #23
    //   4591: iload #22
    //   4593: iload #21
    //   4595: ixor
    //   4596: istore #22
    //   4598: iload #23
    //   4600: bipush #31
    //   4602: ishl
    //   4603: iload #23
    //   4605: iconst_1
    //   4606: iushr
    //   4607: ior
    //   4608: istore #23
    //   4610: iload #23
    //   4612: bipush #8
    //   4614: iushr
    //   4615: iload #22
    //   4617: ixor
    //   4618: ldc 16711935
    //   4620: iand
    //   4621: istore #21
    //   4623: iload #22
    //   4625: iload #21
    //   4627: ixor
    //   4628: istore #22
    //   4630: iload #23
    //   4632: iload #21
    //   4634: bipush #8
    //   4636: ishl
    //   4637: ixor
    //   4638: istore #23
    //   4640: iload #23
    //   4642: iconst_2
    //   4643: iushr
    //   4644: iload #22
    //   4646: ixor
    //   4647: ldc 858993459
    //   4649: iand
    //   4650: istore #21
    //   4652: iload #22
    //   4654: iload #21
    //   4656: ixor
    //   4657: istore #22
    //   4659: iload #23
    //   4661: iload #21
    //   4663: iconst_2
    //   4664: ishl
    //   4665: ixor
    //   4666: istore #23
    //   4668: iload #22
    //   4670: bipush #16
    //   4672: iushr
    //   4673: iload #23
    //   4675: ixor
    //   4676: ldc 65535
    //   4678: iand
    //   4679: istore #21
    //   4681: iload #23
    //   4683: iload #21
    //   4685: ixor
    //   4686: istore #23
    //   4688: iload #22
    //   4690: iload #21
    //   4692: bipush #16
    //   4694: ishl
    //   4695: ixor
    //   4696: istore #22
    //   4698: iload #22
    //   4700: iconst_4
    //   4701: iushr
    //   4702: iload #23
    //   4704: ixor
    //   4705: ldc 252645135
    //   4707: iand
    //   4708: istore #21
    //   4710: iload #23
    //   4712: iload #21
    //   4714: ixor
    //   4715: istore #23
    //   4717: iload #22
    //   4719: iload #21
    //   4721: iconst_4
    //   4722: ishl
    //   4723: ixor
    //   4724: istore #22
    //   4726: aload #15
    //   4728: iconst_0
    //   4729: iload #22
    //   4731: iastore
    //   4732: aload #15
    //   4734: iconst_1
    //   4735: iload #23
    //   4737: iastore
    //   4738: iload #18
    //   4740: bipush #8
    //   4742: imul
    //   4743: istore #26
    //   4745: iconst_0
    //   4746: istore #27
    //   4748: iload #27
    //   4750: iconst_2
    //   4751: if_icmpge -> 4840
    //   4754: aload #16
    //   4756: iload #26
    //   4758: iload #27
    //   4760: iconst_4
    //   4761: imul
    //   4762: iadd
    //   4763: aload #15
    //   4765: iload #27
    //   4767: iaload
    //   4768: bipush #24
    //   4770: iushr
    //   4771: i2b
    //   4772: bastore
    //   4773: aload #16
    //   4775: iload #26
    //   4777: iload #27
    //   4779: iconst_4
    //   4780: imul
    //   4781: iadd
    //   4782: iconst_1
    //   4783: iadd
    //   4784: aload #15
    //   4786: iload #27
    //   4788: iaload
    //   4789: bipush #16
    //   4791: iushr
    //   4792: i2b
    //   4793: bastore
    //   4794: aload #16
    //   4796: iload #26
    //   4798: iload #27
    //   4800: iconst_4
    //   4801: imul
    //   4802: iadd
    //   4803: iconst_2
    //   4804: iadd
    //   4805: aload #15
    //   4807: iload #27
    //   4809: iaload
    //   4810: bipush #8
    //   4812: iushr
    //   4813: i2b
    //   4814: bastore
    //   4815: aload #16
    //   4817: iload #26
    //   4819: iload #27
    //   4821: iconst_4
    //   4822: imul
    //   4823: iadd
    //   4824: iconst_3
    //   4825: iadd
    //   4826: aload #15
    //   4828: iload #27
    //   4830: iaload
    //   4831: i2b
    //   4832: bastore
    //   4833: iinc #27, 1
    //   4836: iload_2
    //   4837: ifne -> 4748
    //   4840: iinc #18, 1
    //   4843: iload_2
    //   4844: ifne -> 3929
    //   4847: aload #16
    //   4849: aload #16
    //   4851: arraylength
    //   4852: iconst_1
    //   4853: isub
    //   4854: baload
    //   4855: istore #18
    //   4857: aload #16
    //   4859: arraylength
    //   4860: iload #18
    //   4862: isub
    //   4863: newarray byte
    //   4865: astore #4
    //   4867: aload #16
    //   4869: arraylength
    //   4870: aload #4
    //   4872: arraylength
    //   4873: if_icmpge -> 4897
    //   4876: new java/lang/Exception
    //   4879: dup
    //   4880: sipush #-24772
    //   4883: sipush #-31032
    //   4886: invokestatic a : (II)Ljava/lang/String;
    //   4889: invokespecial <init> : (Ljava/lang/String;)V
    //   4892: athrow
    //   4893: invokestatic a : (Ljava/lang/Throwable;)Ljava/lang/Throwable;
    //   4896: athrow
    //   4897: iconst_0
    //   4898: istore #19
    //   4900: iload #19
    //   4902: aload #4
    //   4904: arraylength
    //   4905: if_icmpge -> 4925
    //   4908: aload #4
    //   4910: iload #19
    //   4912: aload #16
    //   4914: iload #19
    //   4916: baload
    //   4917: bastore
    //   4918: iinc #19, 1
    //   4921: iload_2
    //   4922: ifne -> 4900
    //   4925: new java/math/BigInteger
    //   4928: dup
    //   4929: aload #4
    //   4931: invokespecial <init> : ([B)V
    //   4934: invokevirtual abs : ()Ljava/math/BigInteger;
    //   4937: putstatic burp/Ztzj.Zv : Ljava/lang/Object;
    //   4940: sipush #-24769
    //   4943: getstatic burp/Ze5h.Zn : Ljava/lang/Object;
    //   4946: checkcast java/math/BigInteger
    //   4949: getstatic burp/Zscz.ZN : Ljava/lang/Object;
    //   4952: checkcast java/math/BigInteger
    //   4955: invokevirtual subtract : (Ljava/math/BigInteger;)Ljava/math/BigInteger;
    //   4958: putstatic burp/Zm3x.ZM : Ljava/lang/Object;
    //   4961: sipush #-31978
    //   4964: invokestatic a : (II)Ljava/lang/String;
    //   4967: iconst_1
    //   4968: ldc burp/Zly0
    //   4970: invokevirtual getClassLoader : ()Ljava/lang/ClassLoader;
    //   4973: invokestatic forName : (Ljava/lang/String;ZLjava/lang/ClassLoader;)Ljava/lang/Class;
    //   4976: invokevirtual getDeclaredFields : ()[Ljava/lang/reflect/Field;
    //   4979: astore_3
    //   4980: aload_3
    //   4981: arraylength
    //   4982: istore #4
    //   4984: iconst_0
    //   4985: istore #5
    //   4987: iload #5
    //   4989: iload #4
    //   4991: if_icmpge -> 5128
    //   4994: aload_3
    //   4995: iload #5
    //   4997: aaload
    //   4998: astore #6
    //   5000: aload #6
    //   5002: invokevirtual getModifiers : ()I
    //   5005: invokestatic isStatic : (I)Z
    //   5008: ifne -> 5018
    //   5011: goto -> 5121
    //   5014: invokestatic a : (Ljava/lang/Throwable;)Ljava/lang/Throwable;
    //   5017: athrow
    //   5018: aload #6
    //   5020: invokevirtual getType : ()Ljava/lang/Class;
    //   5023: astore #7
    //   5025: aload #7
    //   5027: ifnull -> 5108
    //   5030: aload #7
    //   5032: invokevirtual isPrimitive : ()Z
    //   5035: ifne -> 5108
    //   5038: goto -> 5045
    //   5041: invokestatic a : (Ljava/lang/Throwable;)Ljava/lang/Throwable;
    //   5044: athrow
    //   5045: aload #7
    //   5047: invokevirtual getPackage : ()Ljava/lang/Package;
    //   5050: ifnull -> 5108
    //   5053: goto -> 5060
    //   5056: invokestatic a : (Ljava/lang/Throwable;)Ljava/lang/Throwable;
    //   5059: athrow
    //   5060: aload #7
    //   5062: invokevirtual getPackage : ()Ljava/lang/Package;
    //   5065: invokevirtual getName : ()Ljava/lang/String;
    //   5068: ifnull -> 5108
    //   5071: goto -> 5078
    //   5074: invokestatic a : (Ljava/lang/Throwable;)Ljava/lang/Throwable;
    //   5077: athrow
    //   5078: aload #7
    //   5080: invokevirtual getPackage : ()Ljava/lang/Package;
    //   5083: invokevirtual getName : ()Ljava/lang/String;
    //   5086: sipush #-24775
    //   5089: sipush #23914
    //   5092: invokestatic a : (II)Ljava/lang/String;
    //   5095: invokevirtual startsWith : (Ljava/lang/String;)Z
    //   5098: ifne -> 5108
    //   5101: goto -> 5108
    //   5104: invokestatic a : (Ljava/lang/Throwable;)Ljava/lang/Throwable;
    //   5107: athrow
    //   5108: aload #6
    //   5110: iconst_1
    //   5111: invokevirtual setAccessible : (Z)V
    //   5114: aload #6
    //   5116: aconst_null
    //   5117: invokevirtual get : (Ljava/lang/Object;)Ljava/lang/Object;
    //   5120: pop
    //   5121: iinc #5, 1
    //   5124: iload_2
    //   5125: ifne -> 4987
    //   5128: sipush #-24777
    //   5131: sipush #-15738
    //   5134: invokestatic a : (II)Ljava/lang/String;
    //   5137: invokestatic forName : (Ljava/lang/String;)Ljava/lang/Class;
    //   5140: invokevirtual getDeclaredMethods : ()[Ljava/lang/reflect/Method;
    //   5143: astore_3
    //   5144: aload_3
    //   5145: arraylength
    //   5146: istore #4
    //   5148: iconst_0
    //   5149: istore #5
    //   5151: iload #5
    //   5153: iload #4
    //   5155: if_icmpge -> 5287
    //   5158: aload_3
    //   5159: iload #5
    //   5161: aaload
    //   5162: astore #6
    //   5164: aload #6
    //   5166: invokevirtual getParameterTypes : ()[Ljava/lang/Class;
    //   5169: pop
    //   5170: aload #6
    //   5172: invokevirtual getModifiers : ()I
    //   5175: invokestatic isStatic : (I)Z
    //   5178: ifeq -> 5273
    //   5181: aload #6
    //   5183: invokevirtual getParameterTypes : ()[Ljava/lang/Class;
    //   5186: arraylength
    //   5187: iconst_2
    //   5188: if_icmpne -> 5273
    //   5191: goto -> 5198
    //   5194: invokestatic a : (Ljava/lang/Throwable;)Ljava/lang/Throwable;
    //   5197: athrow
    //   5198: aload #6
    //   5200: invokevirtual getReturnType : ()Ljava/lang/Class;
    //   5203: getstatic java/lang/Void.TYPE : Ljava/lang/Class;
    //   5206: invokevirtual equals : (Ljava/lang/Object;)Z
    //   5209: ifeq -> 5273
    //   5212: goto -> 5219
    //   5215: invokestatic a : (Ljava/lang/Throwable;)Ljava/lang/Throwable;
    //   5218: athrow
    //   5219: aload #6
    //   5221: iconst_1
    //   5222: invokevirtual setAccessible : (Z)V
    //   5225: aload #6
    //   5227: aconst_null
    //   5228: iconst_2
    //   5229: anewarray java/lang/Object
    //   5232: dup
    //   5233: iconst_0
    //   5234: aload_0
    //   5235: aastore
    //   5236: dup
    //   5237: iconst_1
    //   5238: aload_1
    //   5239: ifnonnull -> 5257
    //   5242: goto -> 5249
    //   5245: invokestatic a : (Ljava/lang/Throwable;)Ljava/lang/Throwable;
    //   5248: athrow
    //   5249: aload_1
    //   5250: goto -> 5264
    //   5253: invokestatic a : (Ljava/lang/Throwable;)Ljava/lang/Throwable;
    //   5256: athrow
    //   5257: aload_1
    //   5258: checkcast [B
    //   5261: invokevirtual clone : ()Ljava/lang/Object;
    //   5264: aastore
    //   5265: invokevirtual invoke : (Ljava/lang/Object;[Ljava/lang/Object;)Ljava/lang/Object;
    //   5268: pop
    //   5269: iload_2
    //   5270: ifne -> 5287
    //   5273: iinc #5, 1
    //   5276: iload_2
    //   5277: ifne -> 5151
    //   5280: goto -> 5287
    //   5283: invokestatic a : (Ljava/lang/Throwable;)Ljava/lang/Throwable;
    //   5286: athrow
    //   5287: getstatic burp/Zrex.Zr : Ljava/lang/Object;
    //   5290: checkcast java/math/BigInteger
    //   5293: invokevirtual toByteArray : ()[B
    //   5296: astore_3
    //   5297: aload_3
    //   5298: arraylength
    //   5299: iconst_2
    //   5300: iadd
    //   5301: newarray byte
    //   5303: astore #5
    //   5305: iconst_0
    //   5306: istore #6
    //   5308: iload #6
    //   5310: aload_3
    //   5311: arraylength
    //   5312: if_icmpge -> 5331
    //   5315: aload #5
    //   5317: iload #6
    //   5319: aload_3
    //   5320: iload #6
    //   5322: baload
    //   5323: bastore
    //   5324: iinc #6, 1
    //   5327: iload_2
    //   5328: ifne -> 5308
    //   5331: aload #5
    //   5333: arraylength
    //   5334: iconst_3
    //   5335: idiv
    //   5336: iconst_4
    //   5337: imul
    //   5338: newarray byte
    //   5340: astore #4
    //   5342: iconst_0
    //   5343: istore #6
    //   5345: iconst_0
    //   5346: istore #7
    //   5348: iload #6
    //   5350: aload_3
    //   5351: arraylength
    //   5352: if_icmpge -> 5463
    //   5355: aload #4
    //   5357: iload #7
    //   5359: aload #5
    //   5361: iload #6
    //   5363: baload
    //   5364: iconst_2
    //   5365: iushr
    //   5366: bipush #63
    //   5368: iand
    //   5369: i2b
    //   5370: bastore
    //   5371: aload #4
    //   5373: iload #7
    //   5375: iconst_1
    //   5376: iadd
    //   5377: aload #5
    //   5379: iload #6
    //   5381: iconst_1
    //   5382: iadd
    //   5383: baload
    //   5384: iconst_4
    //   5385: iushr
    //   5386: bipush #15
    //   5388: iand
    //   5389: aload #5
    //   5391: iload #6
    //   5393: baload
    //   5394: iconst_4
    //   5395: ishl
    //   5396: bipush #63
    //   5398: iand
    //   5399: ior
    //   5400: i2b
    //   5401: bastore
    //   5402: aload #4
    //   5404: iload #7
    //   5406: iconst_2
    //   5407: iadd
    //   5408: aload #5
    //   5410: iload #6
    //   5412: iconst_2
    //   5413: iadd
    //   5414: baload
    //   5415: bipush #6
    //   5417: iushr
    //   5418: iconst_3
    //   5419: iand
    //   5420: aload #5
    //   5422: iload #6
    //   5424: iconst_1
    //   5425: iadd
    //   5426: baload
    //   5427: iconst_2
    //   5428: ishl
    //   5429: bipush #63
    //   5431: iand
    //   5432: ior
    //   5433: i2b
    //   5434: bastore
    //   5435: aload #4
    //   5437: iload #7
    //   5439: iconst_3
    //   5440: iadd
    //   5441: aload #5
    //   5443: iload #6
    //   5445: iconst_2
    //   5446: iadd
    //   5447: baload
    //   5448: bipush #63
    //   5450: iand
    //   5451: i2b
    //   5452: bastore
    //   5453: iinc #6, 3
    //   5456: iinc #7, 4
    //   5459: iload_2
    //   5460: ifne -> 5348
    //   5463: iconst_0
    //   5464: istore #6
    //   5466: iload #6
    //   5468: aload #4
    //   5470: arraylength
    //   5471: if_icmpge -> 5655
    //   5474: aload #4
    //   5476: iload #6
    //   5478: baload
    //   5479: bipush #26
    //   5481: if_icmpge -> 5509
    //   5484: aload #4
    //   5486: iload #6
    //   5488: aload #4
    //   5490: iload #6
    //   5492: baload
    //   5493: bipush #65
    //   5495: iadd
    //   5496: i2b
    //   5497: bastore
    //   5498: iload_2
    //   5499: ifne -> 5648
    //   5502: goto -> 5509
    //   5505: invokestatic a : (Ljava/lang/Throwable;)Ljava/lang/Throwable;
    //   5508: athrow
    //   5509: aload #4
    //   5511: iload #6
    //   5513: baload
    //   5514: bipush #52
    //   5516: if_icmpge -> 5554
    //   5519: goto -> 5526
    //   5522: invokestatic a : (Ljava/lang/Throwable;)Ljava/lang/Throwable;
    //   5525: athrow
    //   5526: aload #4
    //   5528: iload #6
    //   5530: aload #4
    //   5532: iload #6
    //   5534: baload
    //   5535: bipush #97
    //   5537: iadd
    //   5538: bipush #26
    //   5540: isub
    //   5541: i2b
    //   5542: bastore
    //   5543: iload_2
    //   5544: ifne -> 5648
    //   5547: goto -> 5554
    //   5550: invokestatic a : (Ljava/lang/Throwable;)Ljava/lang/Throwable;
    //   5553: athrow
    //   5554: aload #4
    //   5556: iload #6
    //   5558: baload
    //   5559: bipush #62
    //   5561: if_icmpge -> 5599
    //   5564: goto -> 5571
    //   5567: invokestatic a : (Ljava/lang/Throwable;)Ljava/lang/Throwable;
    //   5570: athrow
    //   5571: aload #4
    //   5573: iload #6
    //   5575: aload #4
    //   5577: iload #6
    //   5579: baload
    //   5580: bipush #48
    //   5582: iadd
    //   5583: bipush #52
    //   5585: isub
    //   5586: i2b
    //   5587: bastore
    //   5588: iload_2
    //   5589: ifne -> 5648
    //   5592: goto -> 5599
    //   5595: invokestatic a : (Ljava/lang/Throwable;)Ljava/lang/Throwable;
    //   5598: athrow
    //   5599: aload #4
    //   5601: iload #6
    //   5603: baload
    //   5604: bipush #63
    //   5606: if_icmpge -> 5634
    //   5609: goto -> 5616
    //   5612: invokestatic a : (Ljava/lang/Throwable;)Ljava/lang/Throwable;
    //   5615: athrow
    //   5616: aload #4
    //   5618: iload #6
    //   5620: bipush #43
    //   5622: bastore
    //   5623: iload_2
    //   5624: ifne -> 5648
    //   5627: goto -> 5634
    //   5630: invokestatic a : (Ljava/lang/Throwable;)Ljava/lang/Throwable;
    //   5633: athrow
    //   5634: aload #4
    //   5636: iload #6
    //   5638: bipush #47
    //   5640: bastore
    //   5641: goto -> 5648
    //   5644: invokestatic a : (Ljava/lang/Throwable;)Ljava/lang/Throwable;
    //   5647: athrow
    //   5648: iinc #6, 1
    //   5651: iload_2
    //   5652: ifne -> 5466
    //   5655: aload #4
    //   5657: arraylength
    //   5658: iconst_1
    //   5659: isub
    //   5660: istore #6
    //   5662: iload #6
    //   5664: aload_3
    //   5665: arraylength
    //   5666: iconst_4
    //   5667: imul
    //   5668: iconst_3
    //   5669: idiv
    //   5670: if_icmple -> 5687
    //   5673: aload #4
    //   5675: iload #6
    //   5677: bipush #61
    //   5679: bastore
    //   5680: iinc #6, -1
    //   5683: iload_2
    //   5684: ifne -> 5662
    //   5687: getstatic burp/Zrt3.Zu : Ljava/lang/String;
    //   5690: getstatic burp/Zg0q.Zf : Ljava/lang/Object;
    //   5693: checkcast java/math/BigInteger
    //   5696: invokevirtual intValue : ()I
    //   5699: bipush #32
    //   5701: irem
    //   5702: invokestatic abs : (I)I
    //   5705: invokevirtual charAt : (I)C
    //   5708: getstatic burp/Zrtp.Zq : Ljava/lang/String;
    //   5711: getstatic burp/Zrkd.ZO : Ljava/lang/Object;
    //   5714: checkcast java/math/BigInteger
    //   5717: invokevirtual intValue : ()I
    //   5720: bipush #32
    //   5722: irem
    //   5723: invokestatic abs : (I)I
    //   5726: invokevirtual charAt : (I)C
    //   5729: if_icmple -> 5844
    //   5732: getstatic burp/Zst7.Zi : Ljava/lang/String;
    //   5735: getstatic burp/Ztvy.ZH : Ljava/lang/Object;
    //   5738: checkcast java/math/BigInteger
    //   5741: invokevirtual intValue : ()I
    //   5744: bipush #32
    //   5746: irem
    //   5747: invokestatic abs : (I)I
    //   5750: invokevirtual charAt : (I)C
    //   5753: getstatic burp/Zt6z.ZL : Ljava/lang/String;
    //   5756: getstatic burp/Zs0h.ZU : Ljava/lang/Object;
    //   5759: checkcast java/math/BigInteger
    //   5762: invokevirtual intValue : ()I
    //   5765: bipush #32
    //   5767: irem
    //   5768: invokestatic abs : (I)I
    //   5771: invokevirtual charAt : (I)C
    //   5774: if_icmple -> 5844
    //   5777: goto -> 5784
    //   5780: invokestatic a : (Ljava/lang/Throwable;)Ljava/lang/Throwable;
    //   5783: athrow
    //   5784: getstatic burp/Zxp1.Zg : Ljava/lang/String;
    //   5787: getstatic burp/Zzii.ZO : Ljava/lang/Object;
    //   5790: checkcast java/math/BigInteger
    //   5793: invokevirtual intValue : ()I
    //   5796: bipush #32
    //   5798: irem
    //   5799: invokestatic abs : (I)I
    //   5802: invokevirtual charAt : (I)C
    //   5805: getstatic burp/Zk9q.Zk : Ljava/lang/String;
    //   5808: getstatic burp/Zk92.Zn : Ljava/lang/Object;
    //   5811: checkcast java/math/BigInteger
    //   5814: invokevirtual intValue : ()I
    //   5817: bipush #32
    //   5819: irem
    //   5820: invokestatic abs : (I)I
    //   5823: invokevirtual charAt : (I)C
    //   5826: if_icmple -> 5844
    //   5829: goto -> 5836
    //   5832: invokestatic a : (Ljava/lang/Throwable;)Ljava/lang/Throwable;
    //   5835: athrow
    //   5836: iconst_1
    //   5837: goto -> 5845
    //   5840: invokestatic a : (Ljava/lang/Throwable;)Ljava/lang/Throwable;
    //   5843: athrow
    //   5844: iconst_0
    //   5845: ireturn
    //   5846: astore_3
    //   5847: new java/lang/Exception
    //   5850: dup
    //   5851: aload_3
    //   5852: invokevirtual getMessage : ()Ljava/lang/String;
    //   5855: invokespecial <init> : (Ljava/lang/String;)V
    //   5858: athrow
    // Exception table:
    //   from	to	target	type
    //   4	5845	5846	java/lang/Throwable
    //   185	209	212	java/lang/Throwable
    //   283	320	320	java/lang/Throwable
    //   324	345	345	java/lang/Throwable
    //   349	379	379	java/lang/Throwable
    //   3879	3904	3904	java/lang/Throwable
    //   4867	4893	4893	java/lang/Throwable
    //   5000	5014	5014	java/lang/Throwable
    //   5025	5038	5041	java/lang/Throwable
    //   5030	5053	5056	java/lang/Throwable
    //   5045	5071	5074	java/lang/Throwable
    //   5060	5101	5104	java/lang/Throwable
    //   5164	5191	5194	java/lang/Throwable
    //   5181	5212	5215	java/lang/Throwable
    //   5198	5242	5245	java/lang/Throwable
    //   5219	5253	5253	java/lang/Throwable
    //   5264	5280	5283	java/lang/Throwable
    //   5474	5502	5505	java/lang/Throwable
    //   5484	5519	5522	java/lang/Throwable
    //   5509	5547	5550	java/lang/Throwable
    //   5526	5564	5567	java/lang/Throwable
    //   5554	5592	5595	java/lang/Throwable
    //   5571	5609	5612	java/lang/Throwable
    //   5599	5627	5630	java/lang/Throwable
    //   5616	5641	5644	java/lang/Throwable
    //   5687	5777	5780	java/lang/Throwable
    //   5732	5829	5832	java/lang/Throwable
    //   5784	5840	5840	java/lang/Throwable
  }
  
  static {
    // Byte code:
    //   0: bipush #10
    //   2: anewarray java/lang/String
    //   5: astore #5
    //   7: iconst_0
    //   8: istore_3
    //   9: ldc 'zHkS](h\\tZ i?jB4:5* 1k-f\\t_Yu\\f\\t0FYL~2g7o3\\nGxEI;b< uX;=8T+|+dbHx(4DK ;mk\\nIiAVg/'
    //   11: dup
    //   12: astore_2
    //   13: invokevirtual length : ()I
    //   16: istore #4
    //   18: bipush #19
    //   20: istore_1
    //   21: iconst_m1
    //   22: istore_0
    //   23: bipush #98
    //   25: iinc #0, 1
    //   28: aload_2
    //   29: iload_0
    //   30: dup
    //   31: iload_1
    //   32: iadd
    //   33: invokevirtual substring : (II)Ljava/lang/String;
    //   36: iconst_m1
    //   37: goto -> 143
    //   40: aload #5
    //   42: swap
    //   43: iload_3
    //   44: iinc #3, 1
    //   47: swap
    //   48: aastore
    //   49: iload_0
    //   50: iload_1
    //   51: iadd
    //   52: dup
    //   53: istore_0
    //   54: iload #4
    //   56: if_icmpge -> 68
    //   59: aload_2
    //   60: iload_0
    //   61: invokevirtual charAt : (I)C
    //   64: istore_1
    //   65: goto -> 23
    //   68: ldc '+$>`J _\\n|xfw#`6\\t_\\t)'
    //   70: dup
    //   71: astore_2
    //   72: invokevirtual length : ()I
    //   75: istore #4
    //   77: bipush #32
    //   79: istore_1
    //   80: iconst_m1
    //   81: istore_0
    //   82: bipush #62
    //   84: iinc #0, 1
    //   87: aload_2
    //   88: iload_0
    //   89: dup
    //   90: iload_1
    //   91: iadd
    //   92: invokevirtual substring : (II)Ljava/lang/String;
    //   95: iconst_0
    //   96: goto -> 143
    //   99: aload #5
    //   101: swap
    //   102: iload_3
    //   103: iinc #3, 1
    //   106: swap
    //   107: aastore
    //   108: iload_0
    //   109: iload_1
    //   110: iadd
    //   111: dup
    //   112: istore_0
    //   113: iload #4
    //   115: if_icmpge -> 127
    //   118: aload_2
    //   119: iload_0
    //   120: invokevirtual charAt : (I)C
    //   123: istore_1
    //   124: goto -> 82
    //   127: aload #5
    //   129: putstatic burp/Zea8.a : [Ljava/lang/String;
    //   132: bipush #10
    //   134: anewarray java/lang/String
    //   137: putstatic burp/Zea8.b : [Ljava/lang/String;
    //   140: goto -> 300
    //   143: dup_x2
    //   144: pop
    //   145: invokevirtual toCharArray : ()[C
    //   148: dup_x1
    //   149: arraylength
    //   150: dup_x2
    //   151: pop
    //   152: iconst_0
    //   153: istore #6
    //   155: dup2_x1
    //   156: pop2
    //   157: dup_x2
    //   158: iconst_1
    //   159: if_icmpgt -> 260
    //   162: dup2
    //   163: swap
    //   164: iload #6
    //   166: dup2_x1
    //   167: caload
    //   168: swap
    //   169: iload #6
    //   171: bipush #7
    //   173: irem
    //   174: tableswitch default -> 242, 0 -> 212, 1 -> 217, 2 -> 222, 3 -> 227, 4 -> 232, 5 -> 237
    //   212: bipush #25
    //   214: goto -> 244
    //   217: bipush #14
    //   219: goto -> 244
    //   222: bipush #17
    //   224: goto -> 244
    //   227: bipush #113
    //   229: goto -> 244
    //   232: bipush #124
    //   234: goto -> 244
    //   237: bipush #77
    //   239: goto -> 244
    //   242: bipush #121
    //   244: ixor
    //   245: ixor
    //   246: i2c
    //   247: castore
    //   248: iinc #6, 1
    //   251: dup
    //   252: ifne -> 260
    //   255: dup2
    //   256: dup_x1
    //   257: goto -> 166
    //   260: dup2_x1
    //   261: pop2
    //   262: dup_x2
    //   263: iload #6
    //   265: if_icmpgt -> 162
    //   268: pop
    //   269: new java/lang/String
    //   272: dup_x1
    //   273: swap
    //   274: invokespecial <init> : ([C)V
    //   277: invokevirtual intern : ()Ljava/lang/String;
    //   280: swap
    //   281: pop
    //   282: swap
    //   283: tableswitch default -> 40, 0 -> 99
    //   300: new java/math/BigInteger
    //   303: dup
    //   304: bipush #32
    //   306: newarray byte
    //   308: dup
    //   309: iconst_0
    //   310: bipush #62
    //   312: bastore
    //   313: dup
    //   314: iconst_1
    //   315: bipush #13
    //   317: bastore
    //   318: dup
    //   319: iconst_2
    //   320: bipush #57
    //   322: bastore
    //   323: dup
    //   324: iconst_3
    //   325: bipush #-16
    //   327: bastore
    //   328: dup
    //   329: iconst_4
    //   330: bipush #76
    //   332: bastore
    //   333: dup
    //   334: iconst_5
    //   335: bipush #-95
    //   337: bastore
    //   338: dup
    //   339: bipush #6
    //   341: bipush #114
    //   343: bastore
    //   344: dup
    //   345: bipush #7
    //   347: iconst_3
    //   348: bastore
    //   349: dup
    //   350: bipush #8
    //   352: bipush #24
    //   354: bastore
    //   355: dup
    //   356: bipush #9
    //   358: bipush #6
    //   360: bastore
    //   361: dup
    //   362: bipush #10
    //   364: bipush #-73
    //   366: bastore
    //   367: dup
    //   368: bipush #11
    //   370: bipush #-77
    //   372: bastore
    //   373: dup
    //   374: bipush #12
    //   376: bipush #7
    //   378: bastore
    //   379: dup
    //   380: bipush #13
    //   382: bipush #118
    //   384: bastore
    //   385: dup
    //   386: bipush #14
    //   388: bipush #-97
    //   390: bastore
    //   391: dup
    //   392: bipush #15
    //   394: bipush #89
    //   396: bastore
    //   397: dup
    //   398: bipush #16
    //   400: bipush #-21
    //   402: bastore
    //   403: dup
    //   404: bipush #17
    //   406: bipush #-13
    //   408: bastore
    //   409: dup
    //   410: bipush #18
    //   412: bipush #-32
    //   414: bastore
    //   415: dup
    //   416: bipush #19
    //   418: bipush #-42
    //   420: bastore
    //   421: dup
    //   422: bipush #20
    //   424: bipush #42
    //   426: bastore
    //   427: dup
    //   428: bipush #21
    //   430: iconst_3
    //   431: bastore
    //   432: dup
    //   433: bipush #22
    //   435: bipush #88
    //   437: bastore
    //   438: dup
    //   439: bipush #23
    //   441: bipush #-110
    //   443: bastore
    //   444: dup
    //   445: bipush #24
    //   447: bipush #102
    //   449: bastore
    //   450: dup
    //   451: bipush #25
    //   453: bipush #59
    //   455: bastore
    //   456: dup
    //   457: bipush #26
    //   459: bipush #104
    //   461: bastore
    //   462: dup
    //   463: bipush #27
    //   465: bipush #-78
    //   467: bastore
    //   468: dup
    //   469: bipush #28
    //   471: bipush #10
    //   473: bastore
    //   474: dup
    //   475: bipush #29
    //   477: bipush #122
    //   479: bastore
    //   480: dup
    //   481: bipush #30
    //   483: bipush #26
    //   485: bastore
    //   486: dup
    //   487: bipush #31
    //   489: bipush #45
    //   491: bastore
    //   492: invokespecial <init> : ([B)V
    //   495: putstatic burp/Zea8.ZF : Ljava/lang/Object;
    //   498: sipush #-24778
    //   501: sipush #12965
    //   504: invokestatic a : (II)Ljava/lang/String;
    //   507: putstatic burp/Zea8.ZE : Ljava/lang/String;
    //   510: return
  }
  
  private static Throwable a(Throwable paramThrowable) {
    return paramThrowable;
  }
  
  private static String a(int paramInt1, int paramInt2) {
    int i = (paramInt1 ^ 0xFFFF9F3E) & 0xFFFF;
    if (b[i] == null) {
      char[] arrayOfChar = a[i].toCharArray();
      switch (arrayOfChar[0] & 0xFF) {
        case 0:
        
        case 1:
        
        case 2:
        
        case 3:
        
        case 4:
        
        case 5:
        
        case 6:
        
        case 7:
        
        case 8:
        
        case 9:
        
        case 10:
        
        case 11:
        
        case 12:
        
        case 13:
        
        case 14:
        
        case 15:
        
        case 16:
        
        case 17:
        
        case 18:
        
        case 19:
        
        case 20:
        
        case 21:
        
        case 22:
        
        case 23:
        
        case 24:
        
        case 25:
        
        case 26:
        
        case 27:
        
        case 28:
        
        case 29:
        
        case 30:
        
        case 31:
        
        case 32:
        
        case 33:
        
        case 34:
        
        case 35:
        
        case 36:
        
        case 37:
        
        case 38:
        
        case 39:
        
        case 40:
        
        case 41:
        
        case 42:
        
        case 43:
        
        case 44:
        
        case 45:
        
        case 46:
        
        case 47:
        
        case 48:
        
        case 49:
        
        case 50:
        
        case 51:
        
        case 52:
        
        case 53:
        
        case 54:
        
        case 55:
        
        case 56:
        
        case 57:
        
        case 58:
        
        case 59:
        
        case 60:
        
        case 61:
        
        case 62:
        
        case 63:
        
        case 64:
        
        case 65:
        
        case 66:
        
        case 67:
        
        case 68:
        
        case 69:
        
        case 70:
        
        case 71:
        
        case 72:
        
        case 73:
        
        case 74:
        
        case 75:
        
        case 76:
        
        case 77:
        
        case 78:
        
        case 79:
        
        case 80:
        
        case 81:
        
        case 82:
        
        case 83:
        
        case 84:
        
        case 85:
        
        case 86:
        
        case 87:
        
        case 88:
        
        case 89:
        
        case 90:
        
        case 91:
        
        case 92:
        
        case 93:
        
        case 94:
        
        case 95:
        
        case 96:
        
        case 97:
        
        case 98:
        
        case 99:
        
        case 100:
        
        case 101:
        
        case 102:
        
        case 103:
        
        case 104:
        
        case 105:
        
        case 106:
        
        case 107:
        
        case 108:
        
        case 109:
        
        case 110:
        
        case 111:
        
        case 112:
        
        case 113:
        
        case 114:
        
        case 115:
        
        case 116:
        
        case 117:
        
        case 118:
        
        case 119:
        
        case 120:
        
        case 121:
        
        case 122:
        
        case 123:
        
        case 124:
        
        case 125:
        
        case 126:
        
        case 127:
        
        case 128:
        
        case 129:
        
        case 130:
        
        case 131:
        
        case 132:
        
        case 133:
        
        case 134:
        
        case 135:
        
        case 136:
        
        case 137:
        
        case 138:
        
        case 139:
        
        case 140:
        
        case 141:
        
        case 142:
        
        case 143:
        
        case 144:
        
        case 145:
        
        case 146:
        
        case 147:
        
        case 148:
        
        case 149:
        
        case 150:
        
        case 151:
        
        case 152:
        
        case 153:
        
        case 154:
        
        case 155:
        
        case 156:
        
        case 157:
        
        case 158:
        
        case 159:
        
        case 160:
        
        case 161:
        
        case 162:
        
        case 163:
        
        case 164:
        
        case 165:
        
        case 166:
        
        case 167:
        
        case 168:
        
        case 169:
        
        case 170:
        
        case 171:
        
        case 172:
        
        case 173:
        
        case 174:
        
        case 175:
        
        case 176:
        
        case 177:
        
        case 178:
        
        case 179:
        
        case 180:
        
        case 181:
        
        case 182:
        
        case 183:
        
        case 184:
        
        case 185:
        
        case 186:
        
        case 187:
        
        case 188:
        
        case 189:
        
        case 190:
        
        case 191:
        
        case 192:
        
        case 193:
        
        case 194:
        
        case 195:
        
        case 196:
        
        case 197:
        
        case 198:
        
        case 199:
        
        case 200:
        
        case 201:
        
        case 202:
        
        case 203:
        
        case 204:
        
        case 205:
        
        case 206:
        
        case 207:
        
        case 208:
        
        case 209:
        
        case 210:
        
        case 211:
        
        case 212:
        
        case 213:
        
        case 214:
        
        case 215:
        
        case 216:
        
        case 217:
        
        case 218:
        
        case 219:
        
        case 220:
        
        case 221:
        
        case 222:
        
        case 223:
        
        case 224:
        
        case 225:
        
        case 226:
        
        case 227:
        
        case 228:
        
        case 229:
        
        case 230:
        
        case 231:
        
        case 232:
        
        case 233:
        
        case 234:
        
        case 235:
        
        case 236:
        
        case 237:
        
        case 238:
        
        case 239:
        
        case 240:
        
        case 241:
        
        case 242:
        
        case 243:
        
        case 244:
        
        case 245:
        
        case 246:
        
        case 247:
        
        case 248:
        
        case 249:
        
        case 250:
        
        case 251:
        
        case 252:
        
        case 253:
        
        case 254:
        
        default:
          break;
      } 
      char c = '';
      int j = (paramInt2 & 0xFF) - c;
      if (j < 0)
        j += 256; 
      int k = ((paramInt2 & 0xFFFF) >>> 8) - c;
      if (k < 0)
        k += 256; 
      for (byte b = 0; b < arrayOfChar.length; b++) {
        int m = b % 2;
        if (m == 0) {
          arrayOfChar[b] = (char)(arrayOfChar[b] ^ j);
          j = ((j >>> 3 | j << 5) ^ arrayOfChar[b]) & 0xFF;
        } else {
          arrayOfChar[b] = (char)(arrayOfChar[b] ^ k);
          k = ((k >>> 3 | k << 5) ^ arrayOfChar[b]) & 0xFF;
        } 
      } 
      b[i] = (new String(arrayOfChar)).intern();
    } 
    return b[i];
  }
}


/* Location:              C:\Program Files\BurpSuitePro\burpsuite_pro.jar!\burp\Zea8.class
 * Java compiler version: 21 (65.0)
 * JD-Core Version:       1.1.3
 */