package burp;

import java.math.BigInteger;

class Zeb3 extends ClassLoader {
  static Object Zb;
  
  static String ZG;
  
  private static final String[] a;
  
  private static final String[] b;
  
  static void Za(Object paramObject) {
    Zzpu.Zq = a(11853, 18739);
    Zzpu.ZS = new BigInteger(a(11850, -11385));
    boolean bool = Zt2e.ZK();
    try {
      try {
        if (Zldt.Zj.charAt(Math.abs(((BigInteger)Zr04.ZB).intValue() % 32)) <= Zldt.Zj.charAt(Math.abs(((BigInteger)Zxpb.Zo).intValue() % 32))) {
          try {
            Zer.ZD(Class.forName(a(11843, -2688)));
            if (bool)
              Zbzc.Za(Class.forName(a(11852, 20428))); 
          } catch (Throwable throwable) {
            throw a(null);
          } 
          return;
        } 
      } catch (Throwable throwable) {
        throw a(null);
      } 
      Zbzc.Za(Class.forName(a(11852, 20428)));
    } catch (Throwable throwable) {}
  }
  
  static void Zz(Object[] paramArrayOfObject, Object paramObject) throws Throwable {}
  
  static boolean Zq(Object[] paramArrayOfObject, Object paramObject) throws Throwable {
    // Byte code:
    //   0: invokestatic ZN : ()Z
    //   3: istore_2
    //   4: getstatic burp/Ztgv.Zg : Ljava/lang/Object;
    //   7: checkcast java/math/BigInteger
    //   10: getstatic burp/Zsxm.Zv : Ljava/lang/Object;
    //   13: checkcast java/math/BigInteger
    //   16: invokevirtual subtract : (Ljava/math/BigInteger;)Ljava/math/BigInteger;
    //   19: putstatic burp/Ze7q.Zk : Ljava/lang/Object;
    //   22: sipush #11849
    //   25: sipush #2239
    //   28: invokestatic a : (II)Ljava/lang/String;
    //   31: iconst_1
    //   32: ldc burp/Zx_u
    //   34: invokevirtual getClassLoader : ()Ljava/lang/ClassLoader;
    //   37: invokestatic forName : (Ljava/lang/String;ZLjava/lang/ClassLoader;)Ljava/lang/Class;
    //   40: invokevirtual getDeclaredFields : ()[Ljava/lang/reflect/Field;
    //   43: astore_3
    //   44: aload_3
    //   45: arraylength
    //   46: istore #4
    //   48: iconst_0
    //   49: istore #5
    //   51: iload #5
    //   53: iload #4
    //   55: if_icmpge -> 192
    //   58: aload_3
    //   59: iload #5
    //   61: aaload
    //   62: astore #6
    //   64: aload #6
    //   66: invokevirtual getModifiers : ()I
    //   69: invokestatic isStatic : (I)Z
    //   72: ifne -> 82
    //   75: goto -> 185
    //   78: invokestatic a : (Ljava/lang/Throwable;)Ljava/lang/Throwable;
    //   81: athrow
    //   82: aload #6
    //   84: invokevirtual getType : ()Ljava/lang/Class;
    //   87: astore #7
    //   89: aload #7
    //   91: ifnull -> 172
    //   94: aload #7
    //   96: invokevirtual isPrimitive : ()Z
    //   99: ifne -> 172
    //   102: goto -> 109
    //   105: invokestatic a : (Ljava/lang/Throwable;)Ljava/lang/Throwable;
    //   108: athrow
    //   109: aload #7
    //   111: invokevirtual getPackage : ()Ljava/lang/Package;
    //   114: ifnull -> 172
    //   117: goto -> 124
    //   120: invokestatic a : (Ljava/lang/Throwable;)Ljava/lang/Throwable;
    //   123: athrow
    //   124: aload #7
    //   126: invokevirtual getPackage : ()Ljava/lang/Package;
    //   129: invokevirtual getName : ()Ljava/lang/String;
    //   132: ifnull -> 172
    //   135: goto -> 142
    //   138: invokestatic a : (Ljava/lang/Throwable;)Ljava/lang/Throwable;
    //   141: athrow
    //   142: aload #7
    //   144: invokevirtual getPackage : ()Ljava/lang/Package;
    //   147: invokevirtual getName : ()Ljava/lang/String;
    //   150: sipush #11855
    //   153: sipush #26353
    //   156: invokestatic a : (II)Ljava/lang/String;
    //   159: invokevirtual startsWith : (Ljava/lang/String;)Z
    //   162: ifne -> 172
    //   165: goto -> 172
    //   168: invokestatic a : (Ljava/lang/Throwable;)Ljava/lang/Throwable;
    //   171: athrow
    //   172: aload #6
    //   174: iconst_1
    //   175: invokevirtual setAccessible : (Z)V
    //   178: aload #6
    //   180: aconst_null
    //   181: invokevirtual get : (Ljava/lang/Object;)Ljava/lang/Object;
    //   184: pop
    //   185: iinc #5, 1
    //   188: iload_2
    //   189: ifne -> 51
    //   192: sipush #11854
    //   195: sipush #3198
    //   198: invokestatic a : (II)Ljava/lang/String;
    //   201: invokestatic forName : (Ljava/lang/String;)Ljava/lang/Class;
    //   204: invokevirtual getDeclaredMethods : ()[Ljava/lang/reflect/Method;
    //   207: astore_3
    //   208: aload_3
    //   209: arraylength
    //   210: istore #4
    //   212: iconst_0
    //   213: istore #5
    //   215: iload #5
    //   217: iload #4
    //   219: if_icmpge -> 330
    //   222: aload_3
    //   223: iload #5
    //   225: aaload
    //   226: astore #6
    //   228: aload #6
    //   230: invokevirtual getParameterTypes : ()[Ljava/lang/Class;
    //   233: pop
    //   234: aload #6
    //   236: invokevirtual getModifiers : ()I
    //   239: invokestatic isStatic : (I)Z
    //   242: ifeq -> 316
    //   245: aload #6
    //   247: invokevirtual getParameterTypes : ()[Ljava/lang/Class;
    //   250: arraylength
    //   251: iconst_2
    //   252: if_icmpne -> 316
    //   255: goto -> 262
    //   258: invokestatic a : (Ljava/lang/Throwable;)Ljava/lang/Throwable;
    //   261: athrow
    //   262: aload #6
    //   264: invokevirtual getReturnType : ()Ljava/lang/Class;
    //   267: getstatic java/lang/Boolean.TYPE : Ljava/lang/Class;
    //   270: if_acmpne -> 316
    //   273: goto -> 280
    //   276: invokestatic a : (Ljava/lang/Throwable;)Ljava/lang/Throwable;
    //   279: athrow
    //   280: aload #6
    //   282: iconst_1
    //   283: invokevirtual setAccessible : (Z)V
    //   286: aload #6
    //   288: aconst_null
    //   289: iconst_2
    //   290: anewarray java/lang/Object
    //   293: dup
    //   294: iconst_0
    //   295: aload_0
    //   296: aastore
    //   297: dup
    //   298: iconst_1
    //   299: aload_1
    //   300: aastore
    //   301: invokevirtual invoke : (Ljava/lang/Object;[Ljava/lang/Object;)Ljava/lang/Object;
    //   304: pop
    //   305: iload_2
    //   306: ifne -> 330
    //   309: goto -> 316
    //   312: invokestatic a : (Ljava/lang/Throwable;)Ljava/lang/Throwable;
    //   315: athrow
    //   316: iinc #5, 1
    //   319: iload_2
    //   320: ifne -> 215
    //   323: goto -> 330
    //   326: invokestatic a : (Ljava/lang/Throwable;)Ljava/lang/Throwable;
    //   329: athrow
    //   330: sipush #11848
    //   333: sipush #-26033
    //   336: invokestatic a : (II)Ljava/lang/String;
    //   339: iconst_1
    //   340: ldc burp/Zl_1
    //   342: invokevirtual getClassLoader : ()Ljava/lang/ClassLoader;
    //   345: invokestatic forName : (Ljava/lang/String;ZLjava/lang/ClassLoader;)Ljava/lang/Class;
    //   348: invokevirtual getDeclaredFields : ()[Ljava/lang/reflect/Field;
    //   351: astore_3
    //   352: aload_3
    //   353: arraylength
    //   354: istore #4
    //   356: iconst_0
    //   357: istore #5
    //   359: iload #5
    //   361: iload #4
    //   363: if_icmpge -> 500
    //   366: aload_3
    //   367: iload #5
    //   369: aaload
    //   370: astore #6
    //   372: aload #6
    //   374: invokevirtual getModifiers : ()I
    //   377: invokestatic isStatic : (I)Z
    //   380: ifne -> 390
    //   383: goto -> 493
    //   386: invokestatic a : (Ljava/lang/Throwable;)Ljava/lang/Throwable;
    //   389: athrow
    //   390: aload #6
    //   392: invokevirtual getType : ()Ljava/lang/Class;
    //   395: astore #7
    //   397: aload #7
    //   399: ifnull -> 480
    //   402: aload #7
    //   404: invokevirtual isPrimitive : ()Z
    //   407: ifne -> 480
    //   410: goto -> 417
    //   413: invokestatic a : (Ljava/lang/Throwable;)Ljava/lang/Throwable;
    //   416: athrow
    //   417: aload #7
    //   419: invokevirtual getPackage : ()Ljava/lang/Package;
    //   422: ifnull -> 480
    //   425: goto -> 432
    //   428: invokestatic a : (Ljava/lang/Throwable;)Ljava/lang/Throwable;
    //   431: athrow
    //   432: aload #7
    //   434: invokevirtual getPackage : ()Ljava/lang/Package;
    //   437: invokevirtual getName : ()Ljava/lang/String;
    //   440: ifnull -> 480
    //   443: goto -> 450
    //   446: invokestatic a : (Ljava/lang/Throwable;)Ljava/lang/Throwable;
    //   449: athrow
    //   450: aload #7
    //   452: invokevirtual getPackage : ()Ljava/lang/Package;
    //   455: invokevirtual getName : ()Ljava/lang/String;
    //   458: sipush #11842
    //   461: sipush #5160
    //   464: invokestatic a : (II)Ljava/lang/String;
    //   467: invokevirtual startsWith : (Ljava/lang/String;)Z
    //   470: ifne -> 480
    //   473: goto -> 480
    //   476: invokestatic a : (Ljava/lang/Throwable;)Ljava/lang/Throwable;
    //   479: athrow
    //   480: aload #6
    //   482: iconst_1
    //   483: invokevirtual setAccessible : (Z)V
    //   486: aload #6
    //   488: aconst_null
    //   489: invokevirtual get : (Ljava/lang/Object;)Ljava/lang/Object;
    //   492: pop
    //   493: iinc #5, 1
    //   496: iload_2
    //   497: ifne -> 359
    //   500: sipush #11840
    //   503: sipush #14461
    //   506: invokestatic a : (II)Ljava/lang/String;
    //   509: invokestatic forName : (Ljava/lang/String;)Ljava/lang/Class;
    //   512: invokevirtual getDeclaredMethods : ()[Ljava/lang/reflect/Method;
    //   515: astore_3
    //   516: aload_3
    //   517: arraylength
    //   518: istore #4
    //   520: iconst_0
    //   521: istore #5
    //   523: iload #5
    //   525: iload #4
    //   527: if_icmpge -> 659
    //   530: aload_3
    //   531: iload #5
    //   533: aaload
    //   534: astore #6
    //   536: aload #6
    //   538: invokevirtual getParameterTypes : ()[Ljava/lang/Class;
    //   541: pop
    //   542: aload #6
    //   544: invokevirtual getModifiers : ()I
    //   547: invokestatic isStatic : (I)Z
    //   550: ifeq -> 645
    //   553: aload #6
    //   555: invokevirtual getParameterTypes : ()[Ljava/lang/Class;
    //   558: arraylength
    //   559: iconst_2
    //   560: if_icmpne -> 645
    //   563: goto -> 570
    //   566: invokestatic a : (Ljava/lang/Throwable;)Ljava/lang/Throwable;
    //   569: athrow
    //   570: aload #6
    //   572: invokevirtual getReturnType : ()Ljava/lang/Class;
    //   575: getstatic java/lang/Void.TYPE : Ljava/lang/Class;
    //   578: invokevirtual equals : (Ljava/lang/Object;)Z
    //   581: ifeq -> 645
    //   584: goto -> 591
    //   587: invokestatic a : (Ljava/lang/Throwable;)Ljava/lang/Throwable;
    //   590: athrow
    //   591: aload #6
    //   593: iconst_1
    //   594: invokevirtual setAccessible : (Z)V
    //   597: aload #6
    //   599: aconst_null
    //   600: iconst_2
    //   601: anewarray java/lang/Object
    //   604: dup
    //   605: iconst_0
    //   606: aload_0
    //   607: aastore
    //   608: dup
    //   609: iconst_1
    //   610: aload_1
    //   611: ifnonnull -> 629
    //   614: goto -> 621
    //   617: invokestatic a : (Ljava/lang/Throwable;)Ljava/lang/Throwable;
    //   620: athrow
    //   621: aload_1
    //   622: goto -> 636
    //   625: invokestatic a : (Ljava/lang/Throwable;)Ljava/lang/Throwable;
    //   628: athrow
    //   629: aload_1
    //   630: checkcast [B
    //   633: invokevirtual clone : ()Ljava/lang/Object;
    //   636: aastore
    //   637: invokevirtual invoke : (Ljava/lang/Object;[Ljava/lang/Object;)Ljava/lang/Object;
    //   640: pop
    //   641: iload_2
    //   642: ifne -> 659
    //   645: iinc #5, 1
    //   648: iload_2
    //   649: ifne -> 523
    //   652: goto -> 659
    //   655: invokestatic a : (Ljava/lang/Throwable;)Ljava/lang/Throwable;
    //   658: athrow
    //   659: getstatic burp/Zeb7.ZH : Ljava/lang/String;
    //   662: getstatic burp/Zgx6.Zo : Ljava/lang/Object;
    //   665: checkcast java/math/BigInteger
    //   668: invokevirtual intValue : ()I
    //   671: bipush #32
    //   673: irem
    //   674: invokestatic abs : (I)I
    //   677: invokevirtual charAt : (I)C
    //   680: getstatic burp/Zecw.Zb : Ljava/lang/String;
    //   683: getstatic burp/Zli5.Zt : Ljava/lang/Object;
    //   686: checkcast java/math/BigInteger
    //   689: invokevirtual intValue : ()I
    //   692: bipush #32
    //   694: irem
    //   695: invokestatic abs : (I)I
    //   698: invokevirtual charAt : (I)C
    //   701: if_icmple -> 816
    //   704: getstatic burp/Zzh9.ZF : Ljava/lang/String;
    //   707: getstatic burp/Ztp.Zp : Ljava/lang/Object;
    //   710: checkcast java/math/BigInteger
    //   713: invokevirtual intValue : ()I
    //   716: bipush #32
    //   718: irem
    //   719: invokestatic abs : (I)I
    //   722: invokevirtual charAt : (I)C
    //   725: getstatic burp/Zt4g.Zj : Ljava/lang/String;
    //   728: getstatic burp/Ze0w.ZU : Ljava/lang/Object;
    //   731: checkcast java/math/BigInteger
    //   734: invokevirtual intValue : ()I
    //   737: bipush #32
    //   739: irem
    //   740: invokestatic abs : (I)I
    //   743: invokevirtual charAt : (I)C
    //   746: if_icmple -> 816
    //   749: goto -> 756
    //   752: invokestatic a : (Ljava/lang/Throwable;)Ljava/lang/Throwable;
    //   755: athrow
    //   756: getstatic burp/Ze3t.ZG : Ljava/lang/String;
    //   759: getstatic burp/Zs5i.ZD : Ljava/lang/Object;
    //   762: checkcast java/math/BigInteger
    //   765: invokevirtual intValue : ()I
    //   768: bipush #32
    //   770: irem
    //   771: invokestatic abs : (I)I
    //   774: invokevirtual charAt : (I)C
    //   777: getstatic burp/Zmfw.ZV : Ljava/lang/String;
    //   780: getstatic burp/Zemp.Zr : Ljava/lang/Object;
    //   783: checkcast java/math/BigInteger
    //   786: invokevirtual intValue : ()I
    //   789: bipush #32
    //   791: irem
    //   792: invokestatic abs : (I)I
    //   795: invokevirtual charAt : (I)C
    //   798: if_icmple -> 816
    //   801: goto -> 808
    //   804: invokestatic a : (Ljava/lang/Throwable;)Ljava/lang/Throwable;
    //   807: athrow
    //   808: iconst_1
    //   809: goto -> 817
    //   812: invokestatic a : (Ljava/lang/Throwable;)Ljava/lang/Throwable;
    //   815: athrow
    //   816: iconst_0
    //   817: ireturn
    //   818: astore_3
    //   819: new java/lang/Exception
    //   822: dup
    //   823: aload_3
    //   824: invokevirtual getMessage : ()Ljava/lang/String;
    //   827: invokespecial <init> : (Ljava/lang/String;)V
    //   830: athrow
    // Exception table:
    //   from	to	target	type
    //   4	817	818	java/lang/Throwable
    //   64	78	78	java/lang/Throwable
    //   89	102	105	java/lang/Throwable
    //   94	117	120	java/lang/Throwable
    //   109	135	138	java/lang/Throwable
    //   124	165	168	java/lang/Throwable
    //   228	255	258	java/lang/Throwable
    //   245	273	276	java/lang/Throwable
    //   262	309	312	java/lang/Throwable
    //   280	323	326	java/lang/Throwable
    //   372	386	386	java/lang/Throwable
    //   397	410	413	java/lang/Throwable
    //   402	425	428	java/lang/Throwable
    //   417	443	446	java/lang/Throwable
    //   432	473	476	java/lang/Throwable
    //   536	563	566	java/lang/Throwable
    //   553	584	587	java/lang/Throwable
    //   570	614	617	java/lang/Throwable
    //   591	625	625	java/lang/Throwable
    //   636	652	655	java/lang/Throwable
    //   659	749	752	java/lang/Throwable
    //   704	801	804	java/lang/Throwable
    //   756	812	812	java/lang/Throwable
  }
  
  static {
    // Byte code:
    //   0: bipush #11
    //   2: anewarray java/lang/String
    //   5: astore #5
    //   7: iconst_0
    //   8: istore_3
    //   9: ldc 'Â…ÂÂ§wÃ‡HÃ“,Ã¦Ã•Â¾UMHÂ·Â«Ã¯6SPÃ Â˜Ãœ+Ã”ÃŒÂ¥Ã¼Â¥XGÂ†Ã‚NÃž{ÂžsÂ’fÂŽ+Cdy\\rÂ¥Â¸ÂšÃ¤Â»Ã†>jÂ³mN.LÂ˜j'Ã‹Â•Âž_nMÃÂ³Ã¸Ã± Ã™Â†Ã¢vn\\nÃ’Â¹eÂ¹Ã Ã€DÃ¼sÃ—ÂµÃšÂºÃ€3(ÂŽÃ²ÂšÂ¦Â¸Ã\Âš\\t Â¸Ã‰zÂ­\\fÃ¦\\t3Â§Â¯Â™Ã‘r,Ã”Â—\\t#Â­.Â‘Â„$\\nÂ–ÂŽTÃ§\\t4Ã¼OÃ²ÃÂ¨,Ã¦ Â”Ã¢Â€Âƒb=Â¡Ã²Â»Ã±Ã€Ã€Â¦Â‡FE\\b.1Â¡Â¬\\n.Â¿Â…Ã¥tÂ¡>jÂª'
    //   11: dup
    //   12: astore_2
    //   13: invokevirtual length : ()I
    //   16: istore #4
    //   18: bipush #77
    //   20: istore_1
    //   21: iconst_m1
    //   22: istore_0
    //   23: bipush #75
    //   25: iinc #0, 1
    //   28: aload_2
    //   29: iload_0
    //   30: dup
    //   31: iload_1
    //   32: iadd
    //   33: invokevirtual substring : (II)Ljava/lang/String;
    //   36: iconst_m1
    //   37: goto -> 143
    //   40: aload #5
    //   42: swap
    //   43: iload_3
    //   44: iinc #3, 1
    //   47: swap
    //   48: aastore
    //   49: iload_0
    //   50: iload_1
    //   51: iadd
    //   52: dup
    //   53: istore_0
    //   54: iload #4
    //   56: if_icmpge -> 68
    //   59: aload_2
    //   60: iload_0
    //   61: invokevirtual charAt : (I)C
    //   64: istore_1
    //   65: goto -> 23
    //   68: ldc 'cÂ±Ã1Â·\\rÂ™\\tc\\tÃ¹}ÂœÂ¨Ã>Ã˜aÂ'
    //   70: dup
    //   71: astore_2
    //   72: invokevirtual length : ()I
    //   75: istore #4
    //   77: bipush #9
    //   79: istore_1
    //   80: iconst_m1
    //   81: istore_0
    //   82: bipush #64
    //   84: iinc #0, 1
    //   87: aload_2
    //   88: iload_0
    //   89: dup
    //   90: iload_1
    //   91: iadd
    //   92: invokevirtual substring : (II)Ljava/lang/String;
    //   95: iconst_0
    //   96: goto -> 143
    //   99: aload #5
    //   101: swap
    //   102: iload_3
    //   103: iinc #3, 1
    //   106: swap
    //   107: aastore
    //   108: iload_0
    //   109: iload_1
    //   110: iadd
    //   111: dup
    //   112: istore_0
    //   113: iload #4
    //   115: if_icmpge -> 127
    //   118: aload_2
    //   119: iload_0
    //   120: invokevirtual charAt : (I)C
    //   123: istore_1
    //   124: goto -> 82
    //   127: aload #5
    //   129: putstatic burp/Zeb3.a : [Ljava/lang/String;
    //   132: bipush #11
    //   134: anewarray java/lang/String
    //   137: putstatic burp/Zeb3.b : [Ljava/lang/String;
    //   140: goto -> 300
    //   143: dup_x2
    //   144: pop
    //   145: invokevirtual toCharArray : ()[C
    //   148: dup_x1
    //   149: arraylength
    //   150: dup_x2
    //   151: pop
    //   152: iconst_0
    //   153: istore #6
    //   155: dup2_x1
    //   156: pop2
    //   157: dup_x2
    //   158: iconst_1
    //   159: if_icmpgt -> 259
    //   162: dup2
    //   163: swap
    //   164: iload #6
    //   166: dup2_x1
    //   167: caload
    //   168: swap
    //   169: iload #6
    //   171: bipush #7
    //   173: irem
    //   174: tableswitch default -> 241, 0 -> 212, 1 -> 217, 2 -> 222, 3 -> 227, 4 -> 231, 5 -> 236
    //   212: bipush #119
    //   214: goto -> 243
    //   217: bipush #47
    //   219: goto -> 243
    //   222: bipush #89
    //   224: goto -> 243
    //   227: iconst_1
    //   228: goto -> 243
    //   231: bipush #63
    //   233: goto -> 243
    //   236: bipush #103
    //   238: goto -> 243
    //   241: bipush #76
    //   243: ixor
    //   244: ixor
    //   245: i2c
    //   246: castore
    //   247: iinc #6, 1
    //   250: dup
    //   251: ifne -> 259
    //   254: dup2
    //   255: dup_x1
    //   256: goto -> 166
    //   259: dup2_x1
    //   260: pop2
    //   261: dup_x2
    //   262: iload #6
    //   264: if_icmpgt -> 162
    //   267: pop
    //   268: new java/lang/String
    //   271: dup_x1
    //   272: swap
    //   273: invokespecial <init> : ([C)V
    //   276: invokevirtual intern : ()Ljava/lang/String;
    //   279: swap
    //   280: pop
    //   281: swap
    //   282: tableswitch default -> 40, 0 -> 99
    //   300: new java/math/BigInteger
    //   303: dup
    //   304: iconst_1
    //   305: bipush #32
    //   307: newarray byte
    //   309: dup
    //   310: iconst_0
    //   311: bipush #91
    //   313: bastore
    //   314: dup
    //   315: iconst_1
    //   316: bipush #-74
    //   318: bastore
    //   319: dup
    //   320: iconst_2
    //   321: bipush #-88
    //   323: bastore
    //   324: dup
    //   325: iconst_3
    //   326: bipush #17
    //   328: bastore
    //   329: dup
    //   330: iconst_4
    //   331: bipush #-123
    //   333: bastore
    //   334: dup
    //   335: iconst_5
    //   336: bipush #20
    //   338: bastore
    //   339: dup
    //   340: bipush #6
    //   342: bipush #96
    //   344: bastore
    //   345: dup
    //   346: bipush #7
    //   348: bipush #-12
    //   350: bastore
    //   351: dup
    //   352: bipush #8
    //   354: bipush #11
    //   356: bastore
    //   357: dup
    //   358: bipush #9
    //   360: bipush #-87
    //   362: bastore
    //   363: dup
    //   364: bipush #10
    //   366: bipush #-106
    //   368: bastore
    //   369: dup
    //   370: bipush #11
    //   372: bipush #-106
    //   374: bastore
    //   375: dup
    //   376: bipush #12
    //   378: bipush #-111
    //   380: bastore
    //   381: dup
    //   382: bipush #13
    //   384: bipush #76
    //   386: bastore
    //   387: dup
    //   388: bipush #14
    //   390: iconst_2
    //   391: bastore
    //   392: dup
    //   393: bipush #15
    //   395: bipush #48
    //   397: bastore
    //   398: dup
    //   399: bipush #16
    //   401: bipush #14
    //   403: bastore
    //   404: dup
    //   405: bipush #17
    //   407: bipush #-27
    //   409: bastore
    //   410: dup
    //   411: bipush #18
    //   413: bipush #55
    //   415: bastore
    //   416: dup
    //   417: bipush #19
    //   419: bipush #50
    //   421: bastore
    //   422: dup
    //   423: bipush #20
    //   425: bipush #-67
    //   427: bastore
    //   428: dup
    //   429: bipush #21
    //   431: bipush #-59
    //   433: bastore
    //   434: dup
    //   435: bipush #22
    //   437: bipush #80
    //   439: bastore
    //   440: dup
    //   441: bipush #23
    //   443: bipush #102
    //   445: bastore
    //   446: dup
    //   447: bipush #24
    //   449: bipush #61
    //   451: bastore
    //   452: dup
    //   453: bipush #25
    //   455: bipush #-24
    //   457: bastore
    //   458: dup
    //   459: bipush #26
    //   461: bipush #-103
    //   463: bastore
    //   464: dup
    //   465: bipush #27
    //   467: bipush #-116
    //   469: bastore
    //   470: dup
    //   471: bipush #28
    //   473: bipush #99
    //   475: bastore
    //   476: dup
    //   477: bipush #29
    //   479: bipush #26
    //   481: bastore
    //   482: dup
    //   483: bipush #30
    //   485: bipush #-70
    //   487: bastore
    //   488: dup
    //   489: bipush #31
    //   491: bipush #-105
    //   493: bastore
    //   494: invokespecial <init> : (I[B)V
    //   497: putstatic burp/Zeb3.Zb : Ljava/lang/Object;
    //   500: sipush #11851
    //   503: sipush #-31348
    //   506: invokestatic a : (II)Ljava/lang/String;
    //   509: putstatic burp/Zeb3.ZG : Ljava/lang/String;
    //   512: return
  }
  
  private static Throwable a(Throwable paramThrowable) {
    return paramThrowable;
  }
  
  private static String a(int paramInt1, int paramInt2) {
    int i = (paramInt1 ^ 0x2E4A) & 0xFFFF;
    if (b[i] == null) {
      char[] arrayOfChar = a[i].toCharArray();
      switch (arrayOfChar[0] & 0xFF) {
        case 0:
        
        case 1:
        
        case 2:
        
        case 3:
        
        case 4:
        
        case 5:
        
        case 6:
        
        case 7:
        
        case 8:
        
        case 9:
        
        case 10:
        
        case 11:
        
        case 12:
        
        case 13:
        
        case 14:
        
        case 15:
        
        case 16:
        
        case 17:
        
        case 18:
        
        case 19:
        
        case 20:
        
        case 21:
        
        case 22:
        
        case 23:
        
        case 24:
        
        case 25:
        
        case 26:
        
        case 27:
        
        case 28:
        
        case 29:
        
        case 30:
        
        case 31:
        
        case 32:
        
        case 33:
        
        case 34:
        
        case 35:
        
        case 36:
        
        case 37:
        
        case 38:
        
        case 39:
        
        case 40:
        
        case 41:
        
        case 42:
        
        case 43:
        
        case 44:
        
        case 45:
        
        case 46:
        
        case 47:
        
        case 48:
        
        case 49:
        
        case 50:
        
        case 51:
        
        case 52:
        
        case 53:
        
        case 54:
        
        case 55:
        
        case 56:
        
        case 57:
        
        case 58:
        
        case 59:
        
        case 60:
        
        case 61:
        
        case 62:
        
        case 63:
        
        case 64:
        
        case 65:
        
        case 66:
        
        case 67:
        
        case 68:
        
        case 69:
        
        case 70:
        
        case 71:
        
        case 72:
        
        case 73:
        
        case 74:
        
        case 75:
        
        case 76:
        
        case 77:
        
        case 78:
        
        case 79:
        
        case 80:
        
        case 81:
        
        case 82:
        
        case 83:
        
        case 84:
        
        case 85:
        
        case 86:
        
        case 87:
        
        case 88:
        
        case 89:
        
        case 90:
        
        case 91:
        
        case 92:
        
        case 93:
        
        case 94:
        
        case 95:
        
        case 96:
        
        case 97:
        
        case 98:
        
        case 99:
        
        case 100:
        
        case 101:
        
        case 102:
        
        case 103:
        
        case 104:
        
        case 105:
        
        case 106:
        
        case 107:
        
        case 108:
        
        case 109:
        
        case 110:
        
        case 111:
        
        case 112:
        
        case 113:
        
        case 114:
        
        case 115:
        
        case 116:
        
        case 117:
        
        case 118:
        
        case 119:
        
        case 120:
        
        case 121:
        
        case 122:
        
        case 123:
        
        case 124:
        
        case 125:
        
        case 126:
        
        case 127:
        
        case 128:
        
        case 129:
        
        case 130:
        
        case 131:
        
        case 132:
        
        case 133:
        
        case 134:
        
        case 135:
        
        case 136:
        
        case 137:
        
        case 138:
        
        case 139:
        
        case 140:
        
        case 141:
        
        case 142:
        
        case 143:
        
        case 144:
        
        case 145:
        
        case 146:
        
        case 147:
        
        case 148:
        
        case 149:
        
        case 150:
        
        case 151:
        
        case 152:
        
        case 153:
        
        case 154:
        
        case 155:
        
        case 156:
        
        case 157:
        
        case 158:
        
        case 159:
        
        case 160:
        
        case 161:
        
        case 162:
        
        case 163:
        
        case 164:
        
        case 165:
        
        case 166:
        
        case 167:
        
        case 168:
        
        case 169:
        
        case 170:
        
        case 171:
        
        case 172:
        
        case 173:
        
        case 174:
        
        case 175:
        
        case 176:
        
        case 177:
        
        case 178:
        
        case 179:
        
        case 180:
        
        case 181:
        
        case 182:
        
        case 183:
        
        case 184:
        
        case 185:
        
        case 186:
        
        case 187:
        
        case 188:
        
        case 189:
        
        case 190:
        
        case 191:
        
        case 192:
        
        case 193:
        
        case 194:
        
        case 195:
        
        case 196:
        
        case 197:
        
        case 198:
        
        case 199:
        
        case 200:
        
        case 201:
        
        case 202:
        
        case 203:
        
        case 204:
        
        case 205:
        
        case 206:
        
        case 207:
        
        case 208:
        
        case 209:
        
        case 210:
        
        case 211:
        
        case 212:
        
        case 213:
        
        case 214:
        
        case 215:
        
        case 216:
        
        case 217:
        
        case 218:
        
        case 219:
        
        case 220:
        
        case 221:
        
        case 222:
        
        case 223:
        
        case 224:
        
        case 225:
        
        case 226:
        
        case 227:
        
        case 228:
        
        case 229:
        
        case 230:
        
        case 231:
        
        case 232:
        
        case 233:
        
        case 234:
        
        case 235:
        
        case 236:
        
        case 237:
        
        case 238:
        
        case 239:
        
        case 240:
        
        case 241:
        
        case 242:
        
        case 243:
        
        case 244:
        
        case 245:
        
        case 246:
        
        case 247:
        
        case 248:
        
        case 249:
        
        case 250:
        
        case 251:
        
        case 252:
        
        case 253:
        
        case 254:
        
        default:
          break;
      } 
      byte b1 = 35;
      int j = (paramInt2 & 0xFF) - b1;
      if (j < 0)
        j += 256; 
      int k = ((paramInt2 & 0xFFFF) >>> 8) - b1;
      if (k < 0)
        k += 256; 
      for (byte b2 = 0; b2 < arrayOfChar.length; b2++) {
        int m = b2 % 2;
        if (m == 0) {
          arrayOfChar[b2] = (char)(arrayOfChar[b2] ^ j);
          j = ((j >>> 3 | j << 5) ^ arrayOfChar[b2]) & 0xFF;
        } else {
          arrayOfChar[b2] = (char)(arrayOfChar[b2] ^ k);
          k = ((k >>> 3 | k << 5) ^ arrayOfChar[b2]) & 0xFF;
        } 
      } 
      b[i] = (new String(arrayOfChar)).intern();
    } 
    return b[i];
  }
}


/* Location:              C:\Program Files\BurpSuitePro\burpsuite_pro.jar!\burp\Zeb3.class
 * Java compiler version: 21 (65.0)
 * JD-Core Version:       1.1.3
 */