package burp;

import java.math.BigInteger;

class Zedz extends ClassLoader {
  static Object Za;
  
  static String Zh;
  
  private static final String[] a;
  
  private static final String[] b;
  
  static boolean ZF(Object[] paramArrayOfObject, Object paramObject) throws Throwable {
    // Byte code:
    //   0: invokestatic ZN : ()Z
    //   3: istore_2
    //   4: getstatic burp/Zsby.ZZ : Ljava/lang/Object;
    //   7: checkcast java/math/BigInteger
    //   10: getstatic burp/Ze7q.Zk : Ljava/lang/Object;
    //   13: checkcast java/math/BigInteger
    //   16: invokevirtual subtract : (Ljava/math/BigInteger;)Ljava/math/BigInteger;
    //   19: putstatic burp/Zein.Zb : Ljava/lang/Object;
    //   22: new java/lang/StringBuilder
    //   25: dup
    //   26: invokespecial <init> : ()V
    //   29: astore_3
    //   30: iconst_0
    //   31: istore #4
    //   33: iload #4
    //   35: bipush #32
    //   37: if_icmpge -> 1371
    //   40: iload #4
    //   42: tableswitch default -> 1364, 0 -> 184, 1 -> 221, 2 -> 258, 3 -> 295, 4 -> 332, 5 -> 369, 6 -> 406, 7 -> 443, 8 -> 480, 9 -> 517, 10 -> 554, 11 -> 591, 12 -> 628, 13 -> 665, 14 -> 702, 15 -> 739, 16 -> 776, 17 -> 813, 18 -> 850, 19 -> 887, 20 -> 924, 21 -> 961, 22 -> 998, 23 -> 1035, 24 -> 1072, 25 -> 1109, 26 -> 1146, 27 -> 1183, 28 -> 1220, 29 -> 1257, 30 -> 1294, 31 -> 1331
    //   184: aload_3
    //   185: getstatic burp/Zxso.ZH : Ljava/lang/String;
    //   188: getstatic burp/Zsby.ZZ : Ljava/lang/Object;
    //   191: checkcast java/math/BigInteger
    //   194: invokevirtual intValue : ()I
    //   197: bipush #32
    //   199: irem
    //   200: invokestatic abs : (I)I
    //   203: invokevirtual charAt : (I)C
    //   206: invokevirtual append : (C)Ljava/lang/StringBuilder;
    //   209: pop
    //   210: iload_2
    //   211: ifne -> 1364
    //   214: goto -> 221
    //   217: invokestatic a : (Ljava/lang/Throwable;)Ljava/lang/Throwable;
    //   220: athrow
    //   221: aload_3
    //   222: getstatic burp/Zr0g.Zf : Ljava/lang/String;
    //   225: getstatic burp/Ztuj.Ze : Ljava/lang/Object;
    //   228: checkcast java/math/BigInteger
    //   231: invokevirtual intValue : ()I
    //   234: bipush #32
    //   236: irem
    //   237: invokestatic abs : (I)I
    //   240: invokevirtual charAt : (I)C
    //   243: invokevirtual append : (C)Ljava/lang/StringBuilder;
    //   246: pop
    //   247: iload_2
    //   248: ifne -> 1364
    //   251: goto -> 258
    //   254: invokestatic a : (Ljava/lang/Throwable;)Ljava/lang/Throwable;
    //   257: athrow
    //   258: aload_3
    //   259: getstatic burp/Zsm3.Zl : Ljava/lang/String;
    //   262: getstatic burp/Zzsq.Zh : Ljava/lang/Object;
    //   265: checkcast java/math/BigInteger
    //   268: invokevirtual intValue : ()I
    //   271: bipush #32
    //   273: irem
    //   274: invokestatic abs : (I)I
    //   277: invokevirtual charAt : (I)C
    //   280: invokevirtual append : (C)Ljava/lang/StringBuilder;
    //   283: pop
    //   284: iload_2
    //   285: ifne -> 1364
    //   288: goto -> 295
    //   291: invokestatic a : (Ljava/lang/Throwable;)Ljava/lang/Throwable;
    //   294: athrow
    //   295: aload_3
    //   296: getstatic burp/Ztnw.Zr : Ljava/lang/String;
    //   299: getstatic burp/Zxzd.ZD : Ljava/lang/Object;
    //   302: checkcast java/math/BigInteger
    //   305: invokevirtual intValue : ()I
    //   308: bipush #32
    //   310: irem
    //   311: invokestatic abs : (I)I
    //   314: invokevirtual charAt : (I)C
    //   317: invokevirtual append : (C)Ljava/lang/StringBuilder;
    //   320: pop
    //   321: iload_2
    //   322: ifne -> 1364
    //   325: goto -> 332
    //   328: invokestatic a : (Ljava/lang/Throwable;)Ljava/lang/Throwable;
    //   331: athrow
    //   332: aload_3
    //   333: getstatic burp/Zbsr.Zq : Ljava/lang/String;
    //   336: getstatic burp/Zsde.Zx : Ljava/lang/Object;
    //   339: checkcast java/math/BigInteger
    //   342: invokevirtual intValue : ()I
    //   345: bipush #32
    //   347: irem
    //   348: invokestatic abs : (I)I
    //   351: invokevirtual charAt : (I)C
    //   354: invokevirtual append : (C)Ljava/lang/StringBuilder;
    //   357: pop
    //   358: iload_2
    //   359: ifne -> 1364
    //   362: goto -> 369
    //   365: invokestatic a : (Ljava/lang/Throwable;)Ljava/lang/Throwable;
    //   368: athrow
    //   369: aload_3
    //   370: getstatic burp/Zshq.Zi : Ljava/lang/String;
    //   373: getstatic burp/Zl_u.ZR : Ljava/lang/Object;
    //   376: checkcast java/math/BigInteger
    //   379: invokevirtual intValue : ()I
    //   382: bipush #32
    //   384: irem
    //   385: invokestatic abs : (I)I
    //   388: invokevirtual charAt : (I)C
    //   391: invokevirtual append : (C)Ljava/lang/StringBuilder;
    //   394: pop
    //   395: iload_2
    //   396: ifne -> 1364
    //   399: goto -> 406
    //   402: invokestatic a : (Ljava/lang/Throwable;)Ljava/lang/Throwable;
    //   405: athrow
    //   406: aload_3
    //   407: getstatic burp/Ze13.Zg : Ljava/lang/String;
    //   410: getstatic burp/Ztbf.Zv : Ljava/lang/Object;
    //   413: checkcast java/math/BigInteger
    //   416: invokevirtual intValue : ()I
    //   419: bipush #32
    //   421: irem
    //   422: invokestatic abs : (I)I
    //   425: invokevirtual charAt : (I)C
    //   428: invokevirtual append : (C)Ljava/lang/StringBuilder;
    //   431: pop
    //   432: iload_2
    //   433: ifne -> 1364
    //   436: goto -> 443
    //   439: invokestatic a : (Ljava/lang/Throwable;)Ljava/lang/Throwable;
    //   442: athrow
    //   443: aload_3
    //   444: getstatic burp/Zedz.Zh : Ljava/lang/String;
    //   447: getstatic burp/Zrbp.Z_ : Ljava/lang/Object;
    //   450: checkcast java/math/BigInteger
    //   453: invokevirtual intValue : ()I
    //   456: bipush #32
    //   458: irem
    //   459: invokestatic abs : (I)I
    //   462: invokevirtual charAt : (I)C
    //   465: invokevirtual append : (C)Ljava/lang/StringBuilder;
    //   468: pop
    //   469: iload_2
    //   470: ifne -> 1364
    //   473: goto -> 480
    //   476: invokestatic a : (Ljava/lang/Throwable;)Ljava/lang/Throwable;
    //   479: athrow
    //   480: aload_3
    //   481: getstatic burp/Zx54.Zs : Ljava/lang/String;
    //   484: getstatic burp/Zein.Zb : Ljava/lang/Object;
    //   487: checkcast java/math/BigInteger
    //   490: invokevirtual intValue : ()I
    //   493: bipush #32
    //   495: irem
    //   496: invokestatic abs : (I)I
    //   499: invokevirtual charAt : (I)C
    //   502: invokevirtual append : (C)Ljava/lang/StringBuilder;
    //   505: pop
    //   506: iload_2
    //   507: ifne -> 1364
    //   510: goto -> 517
    //   513: invokestatic a : (Ljava/lang/Throwable;)Ljava/lang/Throwable;
    //   516: athrow
    //   517: aload_3
    //   518: getstatic burp/Zsby.Zx : Ljava/lang/String;
    //   521: getstatic burp/Zes_.ZJ : Ljava/lang/Object;
    //   524: checkcast java/math/BigInteger
    //   527: invokevirtual intValue : ()I
    //   530: bipush #32
    //   532: irem
    //   533: invokestatic abs : (I)I
    //   536: invokevirtual charAt : (I)C
    //   539: invokevirtual append : (C)Ljava/lang/StringBuilder;
    //   542: pop
    //   543: iload_2
    //   544: ifne -> 1364
    //   547: goto -> 554
    //   550: invokestatic a : (Ljava/lang/Throwable;)Ljava/lang/Throwable;
    //   553: athrow
    //   554: aload_3
    //   555: getstatic burp/Zsde.Zi : Ljava/lang/String;
    //   558: getstatic burp/Zr0g.Zj : Ljava/lang/Object;
    //   561: checkcast java/math/BigInteger
    //   564: invokevirtual intValue : ()I
    //   567: bipush #32
    //   569: irem
    //   570: invokestatic abs : (I)I
    //   573: invokevirtual charAt : (I)C
    //   576: invokevirtual append : (C)Ljava/lang/StringBuilder;
    //   579: pop
    //   580: iload_2
    //   581: ifne -> 1364
    //   584: goto -> 591
    //   587: invokestatic a : (Ljava/lang/Throwable;)Ljava/lang/Throwable;
    //   590: athrow
    //   591: aload_3
    //   592: getstatic burp/Zxzd.ZM : Ljava/lang/String;
    //   595: getstatic burp/Zzsq.Zh : Ljava/lang/Object;
    //   598: checkcast java/math/BigInteger
    //   601: invokevirtual intValue : ()I
    //   604: bipush #32
    //   606: irem
    //   607: invokestatic abs : (I)I
    //   610: invokevirtual charAt : (I)C
    //   613: invokevirtual append : (C)Ljava/lang/StringBuilder;
    //   616: pop
    //   617: iload_2
    //   618: ifne -> 1364
    //   621: goto -> 628
    //   624: invokestatic a : (Ljava/lang/Throwable;)Ljava/lang/Throwable;
    //   627: athrow
    //   628: aload_3
    //   629: getstatic burp/Zgmt.Zu : Ljava/lang/String;
    //   632: getstatic burp/Zeh9.ZY : Ljava/lang/Object;
    //   635: checkcast java/math/BigInteger
    //   638: invokevirtual intValue : ()I
    //   641: bipush #32
    //   643: irem
    //   644: invokestatic abs : (I)I
    //   647: invokevirtual charAt : (I)C
    //   650: invokevirtual append : (C)Ljava/lang/StringBuilder;
    //   653: pop
    //   654: iload_2
    //   655: ifne -> 1364
    //   658: goto -> 665
    //   661: invokestatic a : (Ljava/lang/Throwable;)Ljava/lang/Throwable;
    //   664: athrow
    //   665: aload_3
    //   666: getstatic burp/Zxfu.Zo : Ljava/lang/String;
    //   669: getstatic burp/Zxk9.ZI : Ljava/lang/Object;
    //   672: checkcast java/math/BigInteger
    //   675: invokevirtual intValue : ()I
    //   678: bipush #32
    //   680: irem
    //   681: invokestatic abs : (I)I
    //   684: invokevirtual charAt : (I)C
    //   687: invokevirtual append : (C)Ljava/lang/StringBuilder;
    //   690: pop
    //   691: iload_2
    //   692: ifne -> 1364
    //   695: goto -> 702
    //   698: invokestatic a : (Ljava/lang/Throwable;)Ljava/lang/Throwable;
    //   701: athrow
    //   702: aload_3
    //   703: getstatic burp/Zx54.Zs : Ljava/lang/String;
    //   706: getstatic burp/Zr0g.Zj : Ljava/lang/Object;
    //   709: checkcast java/math/BigInteger
    //   712: invokevirtual intValue : ()I
    //   715: bipush #32
    //   717: irem
    //   718: invokestatic abs : (I)I
    //   721: invokevirtual charAt : (I)C
    //   724: invokevirtual append : (C)Ljava/lang/StringBuilder;
    //   727: pop
    //   728: iload_2
    //   729: ifne -> 1364
    //   732: goto -> 739
    //   735: invokestatic a : (Ljava/lang/Throwable;)Ljava/lang/Throwable;
    //   738: athrow
    //   739: aload_3
    //   740: getstatic burp/Zd1.ZN : Ljava/lang/String;
    //   743: getstatic burp/Zlv6.ZN : Ljava/lang/Object;
    //   746: checkcast java/math/BigInteger
    //   749: invokevirtual intValue : ()I
    //   752: bipush #32
    //   754: irem
    //   755: invokestatic abs : (I)I
    //   758: invokevirtual charAt : (I)C
    //   761: invokevirtual append : (C)Ljava/lang/StringBuilder;
    //   764: pop
    //   765: iload_2
    //   766: ifne -> 1364
    //   769: goto -> 776
    //   772: invokestatic a : (Ljava/lang/Throwable;)Ljava/lang/Throwable;
    //   775: athrow
    //   776: aload_3
    //   777: getstatic burp/Zxzd.ZM : Ljava/lang/String;
    //   780: getstatic burp/Zl2g.ZG : Ljava/lang/Object;
    //   783: checkcast java/math/BigInteger
    //   786: invokevirtual intValue : ()I
    //   789: bipush #32
    //   791: irem
    //   792: invokestatic abs : (I)I
    //   795: invokevirtual charAt : (I)C
    //   798: invokevirtual append : (C)Ljava/lang/StringBuilder;
    //   801: pop
    //   802: iload_2
    //   803: ifne -> 1364
    //   806: goto -> 813
    //   809: invokestatic a : (Ljava/lang/Throwable;)Ljava/lang/Throwable;
    //   812: athrow
    //   813: aload_3
    //   814: getstatic burp/Zb3z.Zi : Ljava/lang/String;
    //   817: getstatic burp/Zxso.ZF : Ljava/lang/Object;
    //   820: checkcast java/math/BigInteger
    //   823: invokevirtual intValue : ()I
    //   826: bipush #32
    //   828: irem
    //   829: invokestatic abs : (I)I
    //   832: invokevirtual charAt : (I)C
    //   835: invokevirtual append : (C)Ljava/lang/StringBuilder;
    //   838: pop
    //   839: iload_2
    //   840: ifne -> 1364
    //   843: goto -> 850
    //   846: invokestatic a : (Ljava/lang/Throwable;)Ljava/lang/Throwable;
    //   849: athrow
    //   850: aload_3
    //   851: getstatic burp/Zb2s.Zq : Ljava/lang/String;
    //   854: getstatic burp/Zb2s.Ze : Ljava/lang/Object;
    //   857: checkcast java/math/BigInteger
    //   860: invokevirtual intValue : ()I
    //   863: bipush #32
    //   865: irem
    //   866: invokestatic abs : (I)I
    //   869: invokevirtual charAt : (I)C
    //   872: invokevirtual append : (C)Ljava/lang/StringBuilder;
    //   875: pop
    //   876: iload_2
    //   877: ifne -> 1364
    //   880: goto -> 887
    //   883: invokestatic a : (Ljava/lang/Throwable;)Ljava/lang/Throwable;
    //   886: athrow
    //   887: aload_3
    //   888: getstatic burp/Ztuj.Zk : Ljava/lang/String;
    //   891: getstatic burp/Zxk9.ZI : Ljava/lang/Object;
    //   894: checkcast java/math/BigInteger
    //   897: invokevirtual intValue : ()I
    //   900: bipush #32
    //   902: irem
    //   903: invokestatic abs : (I)I
    //   906: invokevirtual charAt : (I)C
    //   909: invokevirtual append : (C)Ljava/lang/StringBuilder;
    //   912: pop
    //   913: iload_2
    //   914: ifne -> 1364
    //   917: goto -> 924
    //   920: invokestatic a : (Ljava/lang/Throwable;)Ljava/lang/Throwable;
    //   923: athrow
    //   924: aload_3
    //   925: getstatic burp/Zkmx.Zg : Ljava/lang/String;
    //   928: getstatic burp/Zter.Zc : Ljava/lang/Object;
    //   931: checkcast java/math/BigInteger
    //   934: invokevirtual intValue : ()I
    //   937: bipush #32
    //   939: irem
    //   940: invokestatic abs : (I)I
    //   943: invokevirtual charAt : (I)C
    //   946: invokevirtual append : (C)Ljava/lang/StringBuilder;
    //   949: pop
    //   950: iload_2
    //   951: ifne -> 1364
    //   954: goto -> 961
    //   957: invokestatic a : (Ljava/lang/Throwable;)Ljava/lang/Throwable;
    //   960: athrow
    //   961: aload_3
    //   962: getstatic burp/Zsde.Zi : Ljava/lang/String;
    //   965: getstatic burp/Zd1.ZV : Ljava/lang/Object;
    //   968: checkcast java/math/BigInteger
    //   971: invokevirtual intValue : ()I
    //   974: bipush #32
    //   976: irem
    //   977: invokestatic abs : (I)I
    //   980: invokevirtual charAt : (I)C
    //   983: invokevirtual append : (C)Ljava/lang/StringBuilder;
    //   986: pop
    //   987: iload_2
    //   988: ifne -> 1364
    //   991: goto -> 998
    //   994: invokestatic a : (Ljava/lang/Throwable;)Ljava/lang/Throwable;
    //   997: athrow
    //   998: aload_3
    //   999: getstatic burp/Zm0s.Zm : Ljava/lang/String;
    //   1002: getstatic burp/Zrnu.Zs : Ljava/lang/Object;
    //   1005: checkcast java/math/BigInteger
    //   1008: invokevirtual intValue : ()I
    //   1011: bipush #32
    //   1013: irem
    //   1014: invokestatic abs : (I)I
    //   1017: invokevirtual charAt : (I)C
    //   1020: invokevirtual append : (C)Ljava/lang/StringBuilder;
    //   1023: pop
    //   1024: iload_2
    //   1025: ifne -> 1364
    //   1028: goto -> 1035
    //   1031: invokestatic a : (Ljava/lang/Throwable;)Ljava/lang/Throwable;
    //   1034: athrow
    //   1035: aload_3
    //   1036: getstatic burp/Ze13.Zg : Ljava/lang/String;
    //   1039: getstatic burp/Zsde.Zx : Ljava/lang/Object;
    //   1042: checkcast java/math/BigInteger
    //   1045: invokevirtual intValue : ()I
    //   1048: bipush #32
    //   1050: irem
    //   1051: invokestatic abs : (I)I
    //   1054: invokevirtual charAt : (I)C
    //   1057: invokevirtual append : (C)Ljava/lang/StringBuilder;
    //   1060: pop
    //   1061: iload_2
    //   1062: ifne -> 1364
    //   1065: goto -> 1072
    //   1068: invokestatic a : (Ljava/lang/Throwable;)Ljava/lang/Throwable;
    //   1071: athrow
    //   1072: aload_3
    //   1073: getstatic burp/Zg_p.ZO : Ljava/lang/String;
    //   1076: getstatic burp/Zg7p.Zb : Ljava/lang/Object;
    //   1079: checkcast java/math/BigInteger
    //   1082: invokevirtual intValue : ()I
    //   1085: bipush #32
    //   1087: irem
    //   1088: invokestatic abs : (I)I
    //   1091: invokevirtual charAt : (I)C
    //   1094: invokevirtual append : (C)Ljava/lang/StringBuilder;
    //   1097: pop
    //   1098: iload_2
    //   1099: ifne -> 1364
    //   1102: goto -> 1109
    //   1105: invokestatic a : (Ljava/lang/Throwable;)Ljava/lang/Throwable;
    //   1108: athrow
    //   1109: aload_3
    //   1110: getstatic burp/Zzk9.Zb : Ljava/lang/String;
    //   1113: getstatic burp/Zxk9.ZI : Ljava/lang/Object;
    //   1116: checkcast java/math/BigInteger
    //   1119: invokevirtual intValue : ()I
    //   1122: bipush #32
    //   1124: irem
    //   1125: invokestatic abs : (I)I
    //   1128: invokevirtual charAt : (I)C
    //   1131: invokevirtual append : (C)Ljava/lang/StringBuilder;
    //   1134: pop
    //   1135: iload_2
    //   1136: ifne -> 1364
    //   1139: goto -> 1146
    //   1142: invokestatic a : (Ljava/lang/Throwable;)Ljava/lang/Throwable;
    //   1145: athrow
    //   1146: aload_3
    //   1147: getstatic burp/Zxfu.Zo : Ljava/lang/String;
    //   1150: getstatic burp/Zg_p.Zx : Ljava/lang/Object;
    //   1153: checkcast java/math/BigInteger
    //   1156: invokevirtual intValue : ()I
    //   1159: bipush #32
    //   1161: irem
    //   1162: invokestatic abs : (I)I
    //   1165: invokevirtual charAt : (I)C
    //   1168: invokevirtual append : (C)Ljava/lang/StringBuilder;
    //   1171: pop
    //   1172: iload_2
    //   1173: ifne -> 1364
    //   1176: goto -> 1183
    //   1179: invokestatic a : (Ljava/lang/Throwable;)Ljava/lang/Throwable;
    //   1182: athrow
    //   1183: aload_3
    //   1184: getstatic burp/Zsxm.Zq : Ljava/lang/String;
    //   1187: getstatic burp/Zxo6.Zw : Ljava/lang/Object;
    //   1190: checkcast java/math/BigInteger
    //   1193: invokevirtual intValue : ()I
    //   1196: bipush #32
    //   1198: irem
    //   1199: invokestatic abs : (I)I
    //   1202: invokevirtual charAt : (I)C
    //   1205: invokevirtual append : (C)Ljava/lang/StringBuilder;
    //   1208: pop
    //   1209: iload_2
    //   1210: ifne -> 1364
    //   1213: goto -> 1220
    //   1216: invokestatic a : (Ljava/lang/Throwable;)Ljava/lang/Throwable;
    //   1219: athrow
    //   1220: aload_3
    //   1221: getstatic burp/Ztuj.Zk : Ljava/lang/String;
    //   1224: getstatic burp/Zt4g.Zv : Ljava/lang/Object;
    //   1227: checkcast java/math/BigInteger
    //   1230: invokevirtual intValue : ()I
    //   1233: bipush #32
    //   1235: irem
    //   1236: invokestatic abs : (I)I
    //   1239: invokevirtual charAt : (I)C
    //   1242: invokevirtual append : (C)Ljava/lang/StringBuilder;
    //   1245: pop
    //   1246: iload_2
    //   1247: ifne -> 1364
    //   1250: goto -> 1257
    //   1253: invokestatic a : (Ljava/lang/Throwable;)Ljava/lang/Throwable;
    //   1256: athrow
    //   1257: aload_3
    //   1258: getstatic burp/Zrbp.Ze : Ljava/lang/String;
    //   1261: getstatic burp/Zod.ZP : Ljava/lang/Object;
    //   1264: checkcast java/math/BigInteger
    //   1267: invokevirtual intValue : ()I
    //   1270: bipush #32
    //   1272: irem
    //   1273: invokestatic abs : (I)I
    //   1276: invokevirtual charAt : (I)C
    //   1279: invokevirtual append : (C)Ljava/lang/StringBuilder;
    //   1282: pop
    //   1283: iload_2
    //   1284: ifne -> 1364
    //   1287: goto -> 1294
    //   1290: invokestatic a : (Ljava/lang/Throwable;)Ljava/lang/Throwable;
    //   1293: athrow
    //   1294: aload_3
    //   1295: getstatic burp/Zg99.ZH : Ljava/lang/String;
    //   1298: getstatic burp/Zz1k.ZP : Ljava/lang/Object;
    //   1301: checkcast java/math/BigInteger
    //   1304: invokevirtual intValue : ()I
    //   1307: bipush #32
    //   1309: irem
    //   1310: invokestatic abs : (I)I
    //   1313: invokevirtual charAt : (I)C
    //   1316: invokevirtual append : (C)Ljava/lang/StringBuilder;
    //   1319: pop
    //   1320: iload_2
    //   1321: ifne -> 1364
    //   1324: goto -> 1331
    //   1327: invokestatic a : (Ljava/lang/Throwable;)Ljava/lang/Throwable;
    //   1330: athrow
    //   1331: aload_3
    //   1332: getstatic burp/Zg99.ZH : Ljava/lang/String;
    //   1335: getstatic burp/Zb8v.ZA : Ljava/lang/Object;
    //   1338: checkcast java/math/BigInteger
    //   1341: invokevirtual intValue : ()I
    //   1344: bipush #32
    //   1346: irem
    //   1347: invokestatic abs : (I)I
    //   1350: invokevirtual charAt : (I)C
    //   1353: invokevirtual append : (C)Ljava/lang/StringBuilder;
    //   1356: pop
    //   1357: goto -> 1364
    //   1360: invokestatic a : (Ljava/lang/Throwable;)Ljava/lang/Throwable;
    //   1363: athrow
    //   1364: iinc #4, 1
    //   1367: iload_2
    //   1368: ifne -> 33
    //   1371: aload_3
    //   1372: invokevirtual toString : ()Ljava/lang/String;
    //   1375: putstatic burp/Zg7z.Zf : Ljava/lang/String;
    //   1378: sipush #-31456
    //   1381: getstatic burp/Zzk9.ZK : Ljava/lang/Object;
    //   1384: checkcast java/math/BigInteger
    //   1387: getstatic burp/Zsm3.ZC : Ljava/lang/Object;
    //   1390: checkcast java/math/BigInteger
    //   1393: invokevirtual add : (Ljava/math/BigInteger;)Ljava/math/BigInteger;
    //   1396: putstatic burp/Zxo6.Zw : Ljava/lang/Object;
    //   1399: sipush #18489
    //   1402: invokestatic a : (II)Ljava/lang/String;
    //   1405: iconst_1
    //   1406: ldc burp/Zl8f
    //   1408: invokevirtual getClassLoader : ()Ljava/lang/ClassLoader;
    //   1411: invokestatic forName : (Ljava/lang/String;ZLjava/lang/ClassLoader;)Ljava/lang/Class;
    //   1414: invokevirtual getDeclaredFields : ()[Ljava/lang/reflect/Field;
    //   1417: astore #4
    //   1419: aload #4
    //   1421: arraylength
    //   1422: istore #5
    //   1424: iconst_0
    //   1425: istore #6
    //   1427: iload #6
    //   1429: iload #5
    //   1431: if_icmpge -> 1569
    //   1434: aload #4
    //   1436: iload #6
    //   1438: aaload
    //   1439: astore #7
    //   1441: aload #7
    //   1443: invokevirtual getModifiers : ()I
    //   1446: invokestatic isStatic : (I)Z
    //   1449: ifne -> 1459
    //   1452: goto -> 1562
    //   1455: invokestatic a : (Ljava/lang/Throwable;)Ljava/lang/Throwable;
    //   1458: athrow
    //   1459: aload #7
    //   1461: invokevirtual getType : ()Ljava/lang/Class;
    //   1464: astore #8
    //   1466: aload #8
    //   1468: ifnull -> 1549
    //   1471: aload #8
    //   1473: invokevirtual isPrimitive : ()Z
    //   1476: ifne -> 1549
    //   1479: goto -> 1486
    //   1482: invokestatic a : (Ljava/lang/Throwable;)Ljava/lang/Throwable;
    //   1485: athrow
    //   1486: aload #8
    //   1488: invokevirtual getPackage : ()Ljava/lang/Package;
    //   1491: ifnull -> 1549
    //   1494: goto -> 1501
    //   1497: invokestatic a : (Ljava/lang/Throwable;)Ljava/lang/Throwable;
    //   1500: athrow
    //   1501: aload #8
    //   1503: invokevirtual getPackage : ()Ljava/lang/Package;
    //   1506: invokevirtual getName : ()Ljava/lang/String;
    //   1509: ifnull -> 1549
    //   1512: goto -> 1519
    //   1515: invokestatic a : (Ljava/lang/Throwable;)Ljava/lang/Throwable;
    //   1518: athrow
    //   1519: aload #8
    //   1521: invokevirtual getPackage : ()Ljava/lang/Package;
    //   1524: invokevirtual getName : ()Ljava/lang/String;
    //   1527: sipush #-31450
    //   1530: sipush #6934
    //   1533: invokestatic a : (II)Ljava/lang/String;
    //   1536: invokevirtual startsWith : (Ljava/lang/String;)Z
    //   1539: ifne -> 1549
    //   1542: goto -> 1549
    //   1545: invokestatic a : (Ljava/lang/Throwable;)Ljava/lang/Throwable;
    //   1548: athrow
    //   1549: aload #7
    //   1551: iconst_1
    //   1552: invokevirtual setAccessible : (Z)V
    //   1555: aload #7
    //   1557: aconst_null
    //   1558: invokevirtual get : (Ljava/lang/Object;)Ljava/lang/Object;
    //   1561: pop
    //   1562: iinc #6, 1
    //   1565: iload_2
    //   1566: ifne -> 1427
    //   1569: sipush #-31455
    //   1572: sipush #12538
    //   1575: invokestatic a : (II)Ljava/lang/String;
    //   1578: invokestatic forName : (Ljava/lang/String;)Ljava/lang/Class;
    //   1581: invokevirtual getDeclaredMethods : ()[Ljava/lang/reflect/Method;
    //   1584: astore #4
    //   1586: aload #4
    //   1588: arraylength
    //   1589: istore #5
    //   1591: iconst_0
    //   1592: istore #6
    //   1594: iload #6
    //   1596: iload #5
    //   1598: if_icmpge -> 1731
    //   1601: aload #4
    //   1603: iload #6
    //   1605: aaload
    //   1606: astore #7
    //   1608: aload #7
    //   1610: invokevirtual getParameterTypes : ()[Ljava/lang/Class;
    //   1613: pop
    //   1614: aload #7
    //   1616: invokevirtual getModifiers : ()I
    //   1619: invokestatic isStatic : (I)Z
    //   1622: ifeq -> 1717
    //   1625: aload #7
    //   1627: invokevirtual getParameterTypes : ()[Ljava/lang/Class;
    //   1630: arraylength
    //   1631: iconst_2
    //   1632: if_icmpne -> 1717
    //   1635: goto -> 1642
    //   1638: invokestatic a : (Ljava/lang/Throwable;)Ljava/lang/Throwable;
    //   1641: athrow
    //   1642: aload #7
    //   1644: invokevirtual getReturnType : ()Ljava/lang/Class;
    //   1647: getstatic java/lang/Void.TYPE : Ljava/lang/Class;
    //   1650: invokevirtual equals : (Ljava/lang/Object;)Z
    //   1653: ifeq -> 1717
    //   1656: goto -> 1663
    //   1659: invokestatic a : (Ljava/lang/Throwable;)Ljava/lang/Throwable;
    //   1662: athrow
    //   1663: aload #7
    //   1665: iconst_1
    //   1666: invokevirtual setAccessible : (Z)V
    //   1669: aload #7
    //   1671: aconst_null
    //   1672: iconst_2
    //   1673: anewarray java/lang/Object
    //   1676: dup
    //   1677: iconst_0
    //   1678: aload_0
    //   1679: aastore
    //   1680: dup
    //   1681: iconst_1
    //   1682: aload_1
    //   1683: ifnonnull -> 1701
    //   1686: goto -> 1693
    //   1689: invokestatic a : (Ljava/lang/Throwable;)Ljava/lang/Throwable;
    //   1692: athrow
    //   1693: aload_1
    //   1694: goto -> 1708
    //   1697: invokestatic a : (Ljava/lang/Throwable;)Ljava/lang/Throwable;
    //   1700: athrow
    //   1701: aload_1
    //   1702: checkcast [B
    //   1705: invokevirtual clone : ()Ljava/lang/Object;
    //   1708: aastore
    //   1709: invokevirtual invoke : (Ljava/lang/Object;[Ljava/lang/Object;)Ljava/lang/Object;
    //   1712: pop
    //   1713: iload_2
    //   1714: ifne -> 1731
    //   1717: iinc #6, 1
    //   1720: iload_2
    //   1721: ifne -> 1594
    //   1724: goto -> 1731
    //   1727: invokestatic a : (Ljava/lang/Throwable;)Ljava/lang/Throwable;
    //   1730: athrow
    //   1731: getstatic burp/Zzqj.Zk : Ljava/lang/String;
    //   1734: getstatic burp/Zsgl.Zn : Ljava/lang/Object;
    //   1737: checkcast java/math/BigInteger
    //   1740: invokevirtual intValue : ()I
    //   1743: bipush #32
    //   1745: irem
    //   1746: invokestatic abs : (I)I
    //   1749: invokevirtual charAt : (I)C
    //   1752: getstatic burp/Zrbp.Ze : Ljava/lang/String;
    //   1755: getstatic burp/Zl2q.Zg : Ljava/lang/Object;
    //   1758: checkcast java/math/BigInteger
    //   1761: invokevirtual intValue : ()I
    //   1764: bipush #32
    //   1766: irem
    //   1767: invokestatic abs : (I)I
    //   1770: invokevirtual charAt : (I)C
    //   1773: if_icmple -> 1880
    //   1776: getstatic burp/Zx54.Zs : Ljava/lang/String;
    //   1779: getstatic burp/Zzsq.Zh : Ljava/lang/Object;
    //   1782: checkcast java/math/BigInteger
    //   1785: invokevirtual intValue : ()I
    //   1788: bipush #32
    //   1790: irem
    //   1791: invokestatic abs : (I)I
    //   1794: invokevirtual charAt : (I)C
    //   1797: getstatic burp/Zxwl.Zu : Ljava/lang/String;
    //   1800: getstatic burp/Zshq.ZK : Ljava/lang/Object;
    //   1803: checkcast java/math/BigInteger
    //   1806: invokevirtual intValue : ()I
    //   1809: bipush #32
    //   1811: irem
    //   1812: invokestatic abs : (I)I
    //   1815: invokevirtual charAt : (I)C
    //   1818: if_icmpgt -> 1880
    //   1821: goto -> 1828
    //   1824: invokestatic a : (Ljava/lang/Throwable;)Ljava/lang/Throwable;
    //   1827: athrow
    //   1828: getstatic burp/Zl_u.Zc : Ljava/lang/String;
    //   1831: getstatic burp/Zlhm.ZT : Ljava/lang/Object;
    //   1834: checkcast java/math/BigInteger
    //   1837: invokevirtual intValue : ()I
    //   1840: bipush #32
    //   1842: irem
    //   1843: invokestatic abs : (I)I
    //   1846: invokevirtual charAt : (I)C
    //   1849: getstatic burp/Zkbf.Zv : Ljava/lang/String;
    //   1852: getstatic burp/Zzip.ZW : Ljava/lang/Object;
    //   1855: checkcast java/math/BigInteger
    //   1858: invokevirtual intValue : ()I
    //   1861: bipush #32
    //   1863: irem
    //   1864: invokestatic abs : (I)I
    //   1867: invokevirtual charAt : (I)C
    //   1870: if_icmpgt -> 1888
    //   1873: goto -> 1880
    //   1876: invokestatic a : (Ljava/lang/Throwable;)Ljava/lang/Throwable;
    //   1879: athrow
    //   1880: iconst_1
    //   1881: goto -> 1889
    //   1884: invokestatic a : (Ljava/lang/Throwable;)Ljava/lang/Throwable;
    //   1887: athrow
    //   1888: iconst_0
    //   1889: ireturn
    //   1890: astore_3
    //   1891: new java/lang/Exception
    //   1894: dup
    //   1895: aload_3
    //   1896: invokevirtual getMessage : ()Ljava/lang/String;
    //   1899: invokespecial <init> : (Ljava/lang/String;)V
    //   1902: athrow
    // Exception table:
    //   from	to	target	type
    //   4	1889	1890	java/lang/Throwable
    //   40	214	217	java/lang/Throwable
    //   184	251	254	java/lang/Throwable
    //   221	288	291	java/lang/Throwable
    //   258	325	328	java/lang/Throwable
    //   295	362	365	java/lang/Throwable
    //   332	399	402	java/lang/Throwable
    //   369	436	439	java/lang/Throwable
    //   406	473	476	java/lang/Throwable
    //   443	510	513	java/lang/Throwable
    //   480	547	550	java/lang/Throwable
    //   517	584	587	java/lang/Throwable
    //   554	621	624	java/lang/Throwable
    //   591	658	661	java/lang/Throwable
    //   628	695	698	java/lang/Throwable
    //   665	732	735	java/lang/Throwable
    //   702	769	772	java/lang/Throwable
    //   739	806	809	java/lang/Throwable
    //   776	843	846	java/lang/Throwable
    //   813	880	883	java/lang/Throwable
    //   850	917	920	java/lang/Throwable
    //   887	954	957	java/lang/Throwable
    //   924	991	994	java/lang/Throwable
    //   961	1028	1031	java/lang/Throwable
    //   998	1065	1068	java/lang/Throwable
    //   1035	1102	1105	java/lang/Throwable
    //   1072	1139	1142	java/lang/Throwable
    //   1109	1176	1179	java/lang/Throwable
    //   1146	1213	1216	java/lang/Throwable
    //   1183	1250	1253	java/lang/Throwable
    //   1220	1287	1290	java/lang/Throwable
    //   1257	1324	1327	java/lang/Throwable
    //   1294	1357	1360	java/lang/Throwable
    //   1441	1455	1455	java/lang/Throwable
    //   1466	1479	1482	java/lang/Throwable
    //   1471	1494	1497	java/lang/Throwable
    //   1486	1512	1515	java/lang/Throwable
    //   1501	1542	1545	java/lang/Throwable
    //   1608	1635	1638	java/lang/Throwable
    //   1625	1656	1659	java/lang/Throwable
    //   1642	1686	1689	java/lang/Throwable
    //   1663	1697	1697	java/lang/Throwable
    //   1708	1724	1727	java/lang/Throwable
    //   1731	1821	1824	java/lang/Throwable
    //   1776	1873	1876	java/lang/Throwable
    //   1828	1884	1884	java/lang/Throwable
  }
  
  static void ZJ(Object[] paramArrayOfObject, Object paramObject) throws Throwable {}
  
  static void Zp(Object paramObject) {
    Zzk9.Zb = a(-31451, -23143);
    Zzk9.ZK = new BigInteger(a(-31449, -13079));
    boolean bool = Zt2e.ZN();
    try {
      try {
        if (Zgss.Zc.charAt(Math.abs(((BigInteger)Zxso.ZF).intValue() % 32)) <= Zl2q.ZI.charAt(Math.abs(((BigInteger)Zr0g.Zj).intValue() % 32))) {
          try {
            Zbo7.Zv(Class.forName(a(-31453, -9535)));
            if (!bool)
              Ztap.Zp(Class.forName(a(-31446, 4119))); 
          } catch (Throwable throwable) {
            throw a(null);
          } 
          return;
        } 
      } catch (Throwable throwable) {
        throw a(null);
      } 
      Ztap.Zp(Class.forName(a(-31446, 4119)));
    } catch (Throwable throwable) {}
  }
  
  static {
    // Byte code:
    //   0: bipush #9
    //   2: anewarray java/lang/String
    //   5: astore #5
    //   7: iconst_0
    //   8: istore_3
    //   9: ldc 'GÃ­Â¿ Â‰Ã Ã…Â Ã‘VwnÃ¼L=Â"Ã‡uÃšÂ±Ã®Ã»Â’~\\b6T\\rcÃ®NÃ’\\tÃ“Â½Â±2Ã´IÂ¢,\\tÃ½ÃŽt\LÂ„ÂµÂ•Ã½Â½Ã|Â½M=Â¿pÃ²TÃ’ Â«$Â®Â—|>Ã»R\\ndÃ½e>Â˜Â”!Âº3y)7SzÃ…Ã±Â£YÃŽ\\njD%Ã»Ã¨#\\tAQÃ“Ã‘7Ã„6Ã™tÂŠiÂŽ-ztZÃ¿Ã¦ÃŒÃ”wk<)ÂŸÂŽPMÃ™Ã·-5ÂªÂ˜Ã¥Ã€Ã‡,~{yÃŸM Â‹\\tÃÃ•Ã—R1 pÃ´rÂ»&Ã²TÂŽÂ—*Ã®\\rK3Â»Â¡ÂˆÂ´ra!Â•Â5Ã„;ÂAgÃ¡%Â¸pÃÃ¡Â Ã¯Â®P`Â '
    //   11: dup
    //   12: astore_2
    //   13: invokevirtual length : ()I
    //   16: istore #4
    //   18: bipush #32
    //   20: istore_1
    //   21: iconst_m1
    //   22: istore_0
    //   23: bipush #69
    //   25: iinc #0, 1
    //   28: aload_2
    //   29: iload_0
    //   30: dup
    //   31: iload_1
    //   32: iadd
    //   33: invokevirtual substring : (II)Ljava/lang/String;
    //   36: iconst_m1
    //   37: goto -> 143
    //   40: aload #5
    //   42: swap
    //   43: iload_3
    //   44: iinc #3, 1
    //   47: swap
    //   48: aastore
    //   49: iload_0
    //   50: iload_1
    //   51: iadd
    //   52: dup
    //   53: istore_0
    //   54: iload #4
    //   56: if_icmpge -> 68
    //   59: aload_2
    //   60: iload_0
    //   61: invokevirtual charAt : (I)C
    //   64: istore_1
    //   65: goto -> 23
    //   68: ldc '=0Ã¹\\f>sÂ¸Â‡Â¸JÂ¦ ÂŽÃÃ’[Ã•Â‡ Â•Â¾oerÃƒÃÂ„YÂ€gÂ¢\\t\\t]ÃÃžPÂ†Ã·'
    //   70: dup
    //   71: astore_2
    //   72: invokevirtual length : ()I
    //   75: istore #4
    //   77: bipush #32
    //   79: istore_1
    //   80: iconst_m1
    //   81: istore_0
    //   82: bipush #80
    //   84: iinc #0, 1
    //   87: aload_2
    //   88: iload_0
    //   89: dup
    //   90: iload_1
    //   91: iadd
    //   92: invokevirtual substring : (II)Ljava/lang/String;
    //   95: iconst_0
    //   96: goto -> 143
    //   99: aload #5
    //   101: swap
    //   102: iload_3
    //   103: iinc #3, 1
    //   106: swap
    //   107: aastore
    //   108: iload_0
    //   109: iload_1
    //   110: iadd
    //   111: dup
    //   112: istore_0
    //   113: iload #4
    //   115: if_icmpge -> 127
    //   118: aload_2
    //   119: iload_0
    //   120: invokevirtual charAt : (I)C
    //   123: istore_1
    //   124: goto -> 82
    //   127: aload #5
    //   129: putstatic burp/Zedz.a : [Ljava/lang/String;
    //   132: bipush #9
    //   134: anewarray java/lang/String
    //   137: putstatic burp/Zedz.b : [Ljava/lang/String;
    //   140: goto -> 300
    //   143: dup_x2
    //   144: pop
    //   145: invokevirtual toCharArray : ()[C
    //   148: dup_x1
    //   149: arraylength
    //   150: dup_x2
    //   151: pop
    //   152: iconst_0
    //   153: istore #6
    //   155: dup2_x1
    //   156: pop2
    //   157: dup_x2
    //   158: iconst_1
    //   159: if_icmpgt -> 259
    //   162: dup2
    //   163: swap
    //   164: iload #6
    //   166: dup2_x1
    //   167: caload
    //   168: swap
    //   169: iload #6
    //   171: bipush #7
    //   173: irem
    //   174: tableswitch default -> 241, 0 -> 212, 1 -> 217, 2 -> 222, 3 -> 227, 4 -> 231, 5 -> 236
    //   212: bipush #80
    //   214: goto -> 243
    //   217: bipush #62
    //   219: goto -> 243
    //   222: bipush #112
    //   224: goto -> 243
    //   227: iconst_4
    //   228: goto -> 243
    //   231: bipush #51
    //   233: goto -> 243
    //   236: bipush #70
    //   238: goto -> 243
    //   241: bipush #38
    //   243: ixor
    //   244: ixor
    //   245: i2c
    //   246: castore
    //   247: iinc #6, 1
    //   250: dup
    //   251: ifne -> 259
    //   254: dup2
    //   255: dup_x1
    //   256: goto -> 166
    //   259: dup2_x1
    //   260: pop2
    //   261: dup_x2
    //   262: iload #6
    //   264: if_icmpgt -> 162
    //   267: pop
    //   268: new java/lang/String
    //   271: dup_x1
    //   272: swap
    //   273: invokespecial <init> : ([C)V
    //   276: invokevirtual intern : ()Ljava/lang/String;
    //   279: swap
    //   280: pop
    //   281: swap
    //   282: tableswitch default -> 40, 0 -> 99
    //   300: new java/math/BigInteger
    //   303: dup
    //   304: sipush #-31452
    //   307: sipush #-27953
    //   310: invokestatic a : (II)Ljava/lang/String;
    //   313: invokespecial <init> : (Ljava/lang/String;)V
    //   316: putstatic burp/Zedz.Za : Ljava/lang/Object;
    //   319: sipush #-31454
    //   322: sipush #-2713
    //   325: invokestatic a : (II)Ljava/lang/String;
    //   328: putstatic burp/Zedz.Zh : Ljava/lang/String;
    //   331: return
  }
  
  private static Throwable a(Throwable paramThrowable) {
    return paramThrowable;
  }
  
  private static String a(int paramInt1, int paramInt2) {
    int i = (paramInt1 ^ 0xFFFF8522) & 0xFFFF;
    if (b[i] == null) {
      char[] arrayOfChar = a[i].toCharArray();
      switch (arrayOfChar[0] & 0xFF) {
        case 0:
        
        case 1:
        
        case 2:
        
        case 3:
        
        case 4:
        
        case 5:
        
        case 6:
        
        case 7:
        
        case 8:
        
        case 9:
        
        case 10:
        
        case 11:
        
        case 12:
        
        case 13:
        
        case 14:
        
        case 15:
        
        case 16:
        
        case 17:
        
        case 18:
        
        case 19:
        
        case 20:
        
        case 21:
        
        case 22:
        
        case 23:
        
        case 24:
        
        case 25:
        
        case 26:
        
        case 27:
        
        case 28:
        
        case 29:
        
        case 30:
        
        case 31:
        
        case 32:
        
        case 33:
        
        case 34:
        
        case 35:
        
        case 36:
        
        case 37:
        
        case 38:
        
        case 39:
        
        case 40:
        
        case 41:
        
        case 42:
        
        case 43:
        
        case 44:
        
        case 45:
        
        case 46:
        
        case 47:
        
        case 48:
        
        case 49:
        
        case 50:
        
        case 51:
        
        case 52:
        
        case 53:
        
        case 54:
        
        case 55:
        
        case 56:
        
        case 57:
        
        case 58:
        
        case 59:
        
        case 60:
        
        case 61:
        
        case 62:
        
        case 63:
        
        case 64:
        
        case 65:
        
        case 66:
        
        case 67:
        
        case 68:
        
        case 69:
        
        case 70:
        
        case 71:
        
        case 72:
        
        case 73:
        
        case 74:
        
        case 75:
        
        case 76:
        
        case 77:
        
        case 78:
        
        case 79:
        
        case 80:
        
        case 81:
        
        case 82:
        
        case 83:
        
        case 84:
        
        case 85:
        
        case 86:
        
        case 87:
        
        case 88:
        
        case 89:
        
        case 90:
        
        case 91:
        
        case 92:
        
        case 93:
        
        case 94:
        
        case 95:
        
        case 96:
        
        case 97:
        
        case 98:
        
        case 99:
        
        case 100:
        
        case 101:
        
        case 102:
        
        case 103:
        
        case 104:
        
        case 105:
        
        case 106:
        
        case 107:
        
        case 108:
        
        case 109:
        
        case 110:
        
        case 111:
        
        case 112:
        
        case 113:
        
        case 114:
        
        case 115:
        
        case 116:
        
        case 117:
        
        case 118:
        
        case 119:
        
        case 120:
        
        case 121:
        
        case 122:
        
        case 123:
        
        case 124:
        
        case 125:
        
        case 126:
        
        case 127:
        
        case 128:
        
        case 129:
        
        case 130:
        
        case 131:
        
        case 132:
        
        case 133:
        
        case 134:
        
        case 135:
        
        case 136:
        
        case 137:
        
        case 138:
        
        case 139:
        
        case 140:
        
        case 141:
        
        case 142:
        
        case 143:
        
        case 144:
        
        case 145:
        
        case 146:
        
        case 147:
        
        case 148:
        
        case 149:
        
        case 150:
        
        case 151:
        
        case 152:
        
        case 153:
        
        case 154:
        
        case 155:
        
        case 156:
        
        case 157:
        
        case 158:
        
        case 159:
        
        case 160:
        
        case 161:
        
        case 162:
        
        case 163:
        
        case 164:
        
        case 165:
        
        case 166:
        
        case 167:
        
        case 168:
        
        case 169:
        
        case 170:
        
        case 171:
        
        case 172:
        
        case 173:
        
        case 174:
        
        case 175:
        
        case 176:
        
        case 177:
        
        case 178:
        
        case 179:
        
        case 180:
        
        case 181:
        
        case 182:
        
        case 183:
        
        case 184:
        
        case 185:
        
        case 186:
        
        case 187:
        
        case 188:
        
        case 189:
        
        case 190:
        
        case 191:
        
        case 192:
        
        case 193:
        
        case 194:
        
        case 195:
        
        case 196:
        
        case 197:
        
        case 198:
        
        case 199:
        
        case 200:
        
        case 201:
        
        case 202:
        
        case 203:
        
        case 204:
        
        case 205:
        
        case 206:
        
        case 207:
        
        case 208:
        
        case 209:
        
        case 210:
        
        case 211:
        
        case 212:
        
        case 213:
        
        case 214:
        
        case 215:
        
        case 216:
        
        case 217:
        
        case 218:
        
        case 219:
        
        case 220:
        
        case 221:
        
        case 222:
        
        case 223:
        
        case 224:
        
        case 225:
        
        case 226:
        
        case 227:
        
        case 228:
        
        case 229:
        
        case 230:
        
        case 231:
        
        case 232:
        
        case 233:
        
        case 234:
        
        case 235:
        
        case 236:
        
        case 237:
        
        case 238:
        
        case 239:
        
        case 240:
        
        case 241:
        
        case 242:
        
        case 243:
        
        case 244:
        
        case 245:
        
        case 246:
        
        case 247:
        
        case 248:
        
        case 249:
        
        case 250:
        
        case 251:
        
        case 252:
        
        case 253:
        
        case 254:
        
        default:
          break;
      } 
      char c = 'Ã¡';
      int j = (paramInt2 & 0xFF) - c;
      if (j < 0)
        j += 256; 
      int k = ((paramInt2 & 0xFFFF) >>> 8) - c;
      if (k < 0)
        k += 256; 
      for (byte b = 0; b < arrayOfChar.length; b++) {
        int m = b % 2;
        if (m == 0) {
          arrayOfChar[b] = (char)(arrayOfChar[b] ^ j);
          j = ((j >>> 3 | j << 5) ^ arrayOfChar[b]) & 0xFF;
        } else {
          arrayOfChar[b] = (char)(arrayOfChar[b] ^ k);
          k = ((k >>> 3 | k << 5) ^ arrayOfChar[b]) & 0xFF;
        } 
      } 
      b[i] = (new String(arrayOfChar)).intern();
    } 
    return b[i];
  }
}


/* Location:              C:\Program Files\BurpSuitePro\burpsuite_pro.jar!\burp\Zedz.class
 * Java compiler version: 21 (65.0)
 * JD-Core Version:       1.1.3
 */