package burp;

import java.math.BigInteger;

class Zefn extends ClassLoader {
  static String Ze;
  
  static Object ZJ;
  
  private static final String[] a;
  
  private static final String[] b;
  
  static boolean Zu(Object[] paramArrayOfObject, Object paramObject) throws Throwable {
    // Byte code:
    //   0: invokestatic ZK : ()Z
    //   3: istore_2
    //   4: new java/lang/StringBuilder
    //   7: dup
    //   8: invokespecial <init> : ()V
    //   11: astore_3
    //   12: iconst_0
    //   13: istore #4
    //   15: iload #4
    //   17: bipush #32
    //   19: if_icmpge -> 1355
    //   22: iload #4
    //   24: tableswitch default -> 1348, 0 -> 168, 1 -> 205, 2 -> 242, 3 -> 279, 4 -> 316, 5 -> 353, 6 -> 390, 7 -> 427, 8 -> 464, 9 -> 501, 10 -> 538, 11 -> 575, 12 -> 612, 13 -> 649, 14 -> 686, 15 -> 723, 16 -> 760, 17 -> 797, 18 -> 834, 19 -> 871, 20 -> 908, 21 -> 945, 22 -> 982, 23 -> 1019, 24 -> 1056, 25 -> 1093, 26 -> 1130, 27 -> 1167, 28 -> 1204, 29 -> 1241, 30 -> 1278, 31 -> 1315
    //   168: aload_3
    //   169: getstatic burp/Zkfb.ZV : Ljava/lang/String;
    //   172: getstatic burp/Ze_e.Za : Ljava/lang/Object;
    //   175: checkcast java/math/BigInteger
    //   178: invokevirtual intValue : ()I
    //   181: bipush #32
    //   183: irem
    //   184: invokestatic abs : (I)I
    //   187: invokevirtual charAt : (I)C
    //   190: invokevirtual append : (C)Ljava/lang/StringBuilder;
    //   193: pop
    //   194: iload_2
    //   195: ifeq -> 1348
    //   198: goto -> 205
    //   201: invokestatic a : (Ljava/lang/Throwable;)Ljava/lang/Throwable;
    //   204: athrow
    //   205: aload_3
    //   206: getstatic burp/Zg_6.Zc : Ljava/lang/String;
    //   209: getstatic burp/Zmec.ZY : Ljava/lang/Object;
    //   212: checkcast java/math/BigInteger
    //   215: invokevirtual intValue : ()I
    //   218: bipush #32
    //   220: irem
    //   221: invokestatic abs : (I)I
    //   224: invokevirtual charAt : (I)C
    //   227: invokevirtual append : (C)Ljava/lang/StringBuilder;
    //   230: pop
    //   231: iload_2
    //   232: ifeq -> 1348
    //   235: goto -> 242
    //   238: invokestatic a : (Ljava/lang/Throwable;)Ljava/lang/Throwable;
    //   241: athrow
    //   242: aload_3
    //   243: getstatic burp/Zg3m.Za : Ljava/lang/String;
    //   246: getstatic burp/Zm14.ZZ : Ljava/lang/Object;
    //   249: checkcast java/math/BigInteger
    //   252: invokevirtual intValue : ()I
    //   255: bipush #32
    //   257: irem
    //   258: invokestatic abs : (I)I
    //   261: invokevirtual charAt : (I)C
    //   264: invokevirtual append : (C)Ljava/lang/StringBuilder;
    //   267: pop
    //   268: iload_2
    //   269: ifeq -> 1348
    //   272: goto -> 279
    //   275: invokestatic a : (Ljava/lang/Throwable;)Ljava/lang/Throwable;
    //   278: athrow
    //   279: aload_3
    //   280: getstatic burp/Zkfb.ZV : Ljava/lang/String;
    //   283: getstatic burp/Ztw4.ZF : Ljava/lang/Object;
    //   286: checkcast java/math/BigInteger
    //   289: invokevirtual intValue : ()I
    //   292: bipush #32
    //   294: irem
    //   295: invokestatic abs : (I)I
    //   298: invokevirtual charAt : (I)C
    //   301: invokevirtual append : (C)Ljava/lang/StringBuilder;
    //   304: pop
    //   305: iload_2
    //   306: ifeq -> 1348
    //   309: goto -> 316
    //   312: invokestatic a : (Ljava/lang/Throwable;)Ljava/lang/Throwable;
    //   315: athrow
    //   316: aload_3
    //   317: getstatic burp/Zeju.ZR : Ljava/lang/String;
    //   320: getstatic burp/Zm14.ZZ : Ljava/lang/Object;
    //   323: checkcast java/math/BigInteger
    //   326: invokevirtual intValue : ()I
    //   329: bipush #32
    //   331: irem
    //   332: invokestatic abs : (I)I
    //   335: invokevirtual charAt : (I)C
    //   338: invokevirtual append : (C)Ljava/lang/StringBuilder;
    //   341: pop
    //   342: iload_2
    //   343: ifeq -> 1348
    //   346: goto -> 353
    //   349: invokestatic a : (Ljava/lang/Throwable;)Ljava/lang/Throwable;
    //   352: athrow
    //   353: aload_3
    //   354: getstatic burp/Zrxf.ZG : Ljava/lang/String;
    //   357: getstatic burp/Zml2.Zo : Ljava/lang/Object;
    //   360: checkcast java/math/BigInteger
    //   363: invokevirtual intValue : ()I
    //   366: bipush #32
    //   368: irem
    //   369: invokestatic abs : (I)I
    //   372: invokevirtual charAt : (I)C
    //   375: invokevirtual append : (C)Ljava/lang/StringBuilder;
    //   378: pop
    //   379: iload_2
    //   380: ifeq -> 1348
    //   383: goto -> 390
    //   386: invokestatic a : (Ljava/lang/Throwable;)Ljava/lang/Throwable;
    //   389: athrow
    //   390: aload_3
    //   391: getstatic burp/Zt5a.Zl : Ljava/lang/String;
    //   394: getstatic burp/Zso7.ZB : Ljava/lang/Object;
    //   397: checkcast java/math/BigInteger
    //   400: invokevirtual intValue : ()I
    //   403: bipush #32
    //   405: irem
    //   406: invokestatic abs : (I)I
    //   409: invokevirtual charAt : (I)C
    //   412: invokevirtual append : (C)Ljava/lang/StringBuilder;
    //   415: pop
    //   416: iload_2
    //   417: ifeq -> 1348
    //   420: goto -> 427
    //   423: invokestatic a : (Ljava/lang/Throwable;)Ljava/lang/Throwable;
    //   426: athrow
    //   427: aload_3
    //   428: getstatic burp/Zzxa.Zl : Ljava/lang/String;
    //   431: getstatic burp/Zspk.ZF : Ljava/lang/Object;
    //   434: checkcast java/math/BigInteger
    //   437: invokevirtual intValue : ()I
    //   440: bipush #32
    //   442: irem
    //   443: invokestatic abs : (I)I
    //   446: invokevirtual charAt : (I)C
    //   449: invokevirtual append : (C)Ljava/lang/StringBuilder;
    //   452: pop
    //   453: iload_2
    //   454: ifeq -> 1348
    //   457: goto -> 464
    //   460: invokestatic a : (Ljava/lang/Throwable;)Ljava/lang/Throwable;
    //   463: athrow
    //   464: aload_3
    //   465: getstatic burp/Zeju.ZR : Ljava/lang/String;
    //   468: getstatic burp/Zrh1.ZF : Ljava/lang/Object;
    //   471: checkcast java/math/BigInteger
    //   474: invokevirtual intValue : ()I
    //   477: bipush #32
    //   479: irem
    //   480: invokestatic abs : (I)I
    //   483: invokevirtual charAt : (I)C
    //   486: invokevirtual append : (C)Ljava/lang/StringBuilder;
    //   489: pop
    //   490: iload_2
    //   491: ifeq -> 1348
    //   494: goto -> 501
    //   497: invokestatic a : (Ljava/lang/Throwable;)Ljava/lang/Throwable;
    //   500: athrow
    //   501: aload_3
    //   502: getstatic burp/Zlhu.ZC : Ljava/lang/String;
    //   505: getstatic burp/Zktq.Zn : Ljava/lang/Object;
    //   508: checkcast java/math/BigInteger
    //   511: invokevirtual intValue : ()I
    //   514: bipush #32
    //   516: irem
    //   517: invokestatic abs : (I)I
    //   520: invokevirtual charAt : (I)C
    //   523: invokevirtual append : (C)Ljava/lang/StringBuilder;
    //   526: pop
    //   527: iload_2
    //   528: ifeq -> 1348
    //   531: goto -> 538
    //   534: invokestatic a : (Ljava/lang/Throwable;)Ljava/lang/Throwable;
    //   537: athrow
    //   538: aload_3
    //   539: getstatic burp/Zenq.ZG : Ljava/lang/String;
    //   542: getstatic burp/Ztdg.ZE : Ljava/lang/Object;
    //   545: checkcast java/math/BigInteger
    //   548: invokevirtual intValue : ()I
    //   551: bipush #32
    //   553: irem
    //   554: invokestatic abs : (I)I
    //   557: invokevirtual charAt : (I)C
    //   560: invokevirtual append : (C)Ljava/lang/StringBuilder;
    //   563: pop
    //   564: iload_2
    //   565: ifeq -> 1348
    //   568: goto -> 575
    //   571: invokestatic a : (Ljava/lang/Throwable;)Ljava/lang/Throwable;
    //   574: athrow
    //   575: aload_3
    //   576: getstatic burp/Ztdg.ZS : Ljava/lang/String;
    //   579: getstatic burp/Zth8.Zk : Ljava/lang/Object;
    //   582: checkcast java/math/BigInteger
    //   585: invokevirtual intValue : ()I
    //   588: bipush #32
    //   590: irem
    //   591: invokestatic abs : (I)I
    //   594: invokevirtual charAt : (I)C
    //   597: invokevirtual append : (C)Ljava/lang/StringBuilder;
    //   600: pop
    //   601: iload_2
    //   602: ifeq -> 1348
    //   605: goto -> 612
    //   608: invokestatic a : (Ljava/lang/Throwable;)Ljava/lang/Throwable;
    //   611: athrow
    //   612: aload_3
    //   613: getstatic burp/Zsf4.ZA : Ljava/lang/String;
    //   616: getstatic burp/Zrfh.ZJ : Ljava/lang/Object;
    //   619: checkcast java/math/BigInteger
    //   622: invokevirtual intValue : ()I
    //   625: bipush #32
    //   627: irem
    //   628: invokestatic abs : (I)I
    //   631: invokevirtual charAt : (I)C
    //   634: invokevirtual append : (C)Ljava/lang/StringBuilder;
    //   637: pop
    //   638: iload_2
    //   639: ifeq -> 1348
    //   642: goto -> 649
    //   645: invokestatic a : (Ljava/lang/Throwable;)Ljava/lang/Throwable;
    //   648: athrow
    //   649: aload_3
    //   650: getstatic burp/Zt5a.Zl : Ljava/lang/String;
    //   653: getstatic burp/Zmh0.Zt : Ljava/lang/Object;
    //   656: checkcast java/math/BigInteger
    //   659: invokevirtual intValue : ()I
    //   662: bipush #32
    //   664: irem
    //   665: invokestatic abs : (I)I
    //   668: invokevirtual charAt : (I)C
    //   671: invokevirtual append : (C)Ljava/lang/StringBuilder;
    //   674: pop
    //   675: iload_2
    //   676: ifeq -> 1348
    //   679: goto -> 686
    //   682: invokestatic a : (Ljava/lang/Throwable;)Ljava/lang/Throwable;
    //   685: athrow
    //   686: aload_3
    //   687: getstatic burp/Zeqw.Zw : Ljava/lang/String;
    //   690: getstatic burp/Zecm.ZJ : Ljava/lang/Object;
    //   693: checkcast java/math/BigInteger
    //   696: invokevirtual intValue : ()I
    //   699: bipush #32
    //   701: irem
    //   702: invokestatic abs : (I)I
    //   705: invokevirtual charAt : (I)C
    //   708: invokevirtual append : (C)Ljava/lang/StringBuilder;
    //   711: pop
    //   712: iload_2
    //   713: ifeq -> 1348
    //   716: goto -> 723
    //   719: invokestatic a : (Ljava/lang/Throwable;)Ljava/lang/Throwable;
    //   722: athrow
    //   723: aload_3
    //   724: getstatic burp/Zbxa.ZY : Ljava/lang/String;
    //   727: getstatic burp/Zmly.ZT : Ljava/lang/Object;
    //   730: checkcast java/math/BigInteger
    //   733: invokevirtual intValue : ()I
    //   736: bipush #32
    //   738: irem
    //   739: invokestatic abs : (I)I
    //   742: invokevirtual charAt : (I)C
    //   745: invokevirtual append : (C)Ljava/lang/StringBuilder;
    //   748: pop
    //   749: iload_2
    //   750: ifeq -> 1348
    //   753: goto -> 760
    //   756: invokestatic a : (Ljava/lang/Throwable;)Ljava/lang/Throwable;
    //   759: athrow
    //   760: aload_3
    //   761: getstatic burp/Zrct.ZT : Ljava/lang/String;
    //   764: getstatic burp/Zewq.ZO : Ljava/lang/Object;
    //   767: checkcast java/math/BigInteger
    //   770: invokevirtual intValue : ()I
    //   773: bipush #32
    //   775: irem
    //   776: invokestatic abs : (I)I
    //   779: invokevirtual charAt : (I)C
    //   782: invokevirtual append : (C)Ljava/lang/StringBuilder;
    //   785: pop
    //   786: iload_2
    //   787: ifeq -> 1348
    //   790: goto -> 797
    //   793: invokestatic a : (Ljava/lang/Throwable;)Ljava/lang/Throwable;
    //   796: athrow
    //   797: aload_3
    //   798: getstatic burp/Ztdg.ZS : Ljava/lang/String;
    //   801: getstatic burp/Zgl2.ZS : Ljava/lang/Object;
    //   804: checkcast java/math/BigInteger
    //   807: invokevirtual intValue : ()I
    //   810: bipush #32
    //   812: irem
    //   813: invokestatic abs : (I)I
    //   816: invokevirtual charAt : (I)C
    //   819: invokevirtual append : (C)Ljava/lang/StringBuilder;
    //   822: pop
    //   823: iload_2
    //   824: ifeq -> 1348
    //   827: goto -> 834
    //   830: invokestatic a : (Ljava/lang/Throwable;)Ljava/lang/Throwable;
    //   833: athrow
    //   834: aload_3
    //   835: getstatic burp/Zr4z.Zw : Ljava/lang/String;
    //   838: getstatic burp/Zewq.ZO : Ljava/lang/Object;
    //   841: checkcast java/math/BigInteger
    //   844: invokevirtual intValue : ()I
    //   847: bipush #32
    //   849: irem
    //   850: invokestatic abs : (I)I
    //   853: invokevirtual charAt : (I)C
    //   856: invokevirtual append : (C)Ljava/lang/StringBuilder;
    //   859: pop
    //   860: iload_2
    //   861: ifeq -> 1348
    //   864: goto -> 871
    //   867: invokestatic a : (Ljava/lang/Throwable;)Ljava/lang/Throwable;
    //   870: athrow
    //   871: aload_3
    //   872: getstatic burp/Zecm.Zv : Ljava/lang/String;
    //   875: getstatic burp/Zrnw.ZN : Ljava/lang/Object;
    //   878: checkcast java/math/BigInteger
    //   881: invokevirtual intValue : ()I
    //   884: bipush #32
    //   886: irem
    //   887: invokestatic abs : (I)I
    //   890: invokevirtual charAt : (I)C
    //   893: invokevirtual append : (C)Ljava/lang/StringBuilder;
    //   896: pop
    //   897: iload_2
    //   898: ifeq -> 1348
    //   901: goto -> 908
    //   904: invokestatic a : (Ljava/lang/Throwable;)Ljava/lang/Throwable;
    //   907: athrow
    //   908: aload_3
    //   909: getstatic burp/Zkfb.ZV : Ljava/lang/String;
    //   912: getstatic burp/Zrxf.ZS : Ljava/lang/Object;
    //   915: checkcast java/math/BigInteger
    //   918: invokevirtual intValue : ()I
    //   921: bipush #32
    //   923: irem
    //   924: invokestatic abs : (I)I
    //   927: invokevirtual charAt : (I)C
    //   930: invokevirtual append : (C)Ljava/lang/StringBuilder;
    //   933: pop
    //   934: iload_2
    //   935: ifeq -> 1348
    //   938: goto -> 945
    //   941: invokestatic a : (Ljava/lang/Throwable;)Ljava/lang/Throwable;
    //   944: athrow
    //   945: aload_3
    //   946: getstatic burp/Zm14.ZE : Ljava/lang/String;
    //   949: getstatic burp/Ze_e.Za : Ljava/lang/Object;
    //   952: checkcast java/math/BigInteger
    //   955: invokevirtual intValue : ()I
    //   958: bipush #32
    //   960: irem
    //   961: invokestatic abs : (I)I
    //   964: invokevirtual charAt : (I)C
    //   967: invokevirtual append : (C)Ljava/lang/StringBuilder;
    //   970: pop
    //   971: iload_2
    //   972: ifeq -> 1348
    //   975: goto -> 982
    //   978: invokestatic a : (Ljava/lang/Throwable;)Ljava/lang/Throwable;
    //   981: athrow
    //   982: aload_3
    //   983: getstatic burp/Zkc5.ZH : Ljava/lang/String;
    //   986: getstatic burp/Zzoc.Zx : Ljava/lang/Object;
    //   989: checkcast java/math/BigInteger
    //   992: invokevirtual intValue : ()I
    //   995: bipush #32
    //   997: irem
    //   998: invokestatic abs : (I)I
    //   1001: invokevirtual charAt : (I)C
    //   1004: invokevirtual append : (C)Ljava/lang/StringBuilder;
    //   1007: pop
    //   1008: iload_2
    //   1009: ifeq -> 1348
    //   1012: goto -> 1019
    //   1015: invokestatic a : (Ljava/lang/Throwable;)Ljava/lang/Throwable;
    //   1018: athrow
    //   1019: aload_3
    //   1020: getstatic burp/Zmec.Zi : Ljava/lang/String;
    //   1023: getstatic burp/Ze_e.Za : Ljava/lang/Object;
    //   1026: checkcast java/math/BigInteger
    //   1029: invokevirtual intValue : ()I
    //   1032: bipush #32
    //   1034: irem
    //   1035: invokestatic abs : (I)I
    //   1038: invokevirtual charAt : (I)C
    //   1041: invokevirtual append : (C)Ljava/lang/StringBuilder;
    //   1044: pop
    //   1045: iload_2
    //   1046: ifeq -> 1348
    //   1049: goto -> 1056
    //   1052: invokestatic a : (Ljava/lang/Throwable;)Ljava/lang/Throwable;
    //   1055: athrow
    //   1056: aload_3
    //   1057: getstatic burp/Zsot.Zb : Ljava/lang/String;
    //   1060: getstatic burp/Zefn.ZJ : Ljava/lang/Object;
    //   1063: checkcast java/math/BigInteger
    //   1066: invokevirtual intValue : ()I
    //   1069: bipush #32
    //   1071: irem
    //   1072: invokestatic abs : (I)I
    //   1075: invokevirtual charAt : (I)C
    //   1078: invokevirtual append : (C)Ljava/lang/StringBuilder;
    //   1081: pop
    //   1082: iload_2
    //   1083: ifeq -> 1348
    //   1086: goto -> 1093
    //   1089: invokestatic a : (Ljava/lang/Throwable;)Ljava/lang/Throwable;
    //   1092: athrow
    //   1093: aload_3
    //   1094: getstatic burp/Zzh9.ZF : Ljava/lang/String;
    //   1097: getstatic burp/Zgs6.Za : Ljava/lang/Object;
    //   1100: checkcast java/math/BigInteger
    //   1103: invokevirtual intValue : ()I
    //   1106: bipush #32
    //   1108: irem
    //   1109: invokestatic abs : (I)I
    //   1112: invokevirtual charAt : (I)C
    //   1115: invokevirtual append : (C)Ljava/lang/StringBuilder;
    //   1118: pop
    //   1119: iload_2
    //   1120: ifeq -> 1348
    //   1123: goto -> 1130
    //   1126: invokestatic a : (Ljava/lang/Throwable;)Ljava/lang/Throwable;
    //   1129: athrow
    //   1130: aload_3
    //   1131: getstatic burp/Ztsc.ZL : Ljava/lang/String;
    //   1134: getstatic burp/Zlhu.ZJ : Ljava/lang/Object;
    //   1137: checkcast java/math/BigInteger
    //   1140: invokevirtual intValue : ()I
    //   1143: bipush #32
    //   1145: irem
    //   1146: invokestatic abs : (I)I
    //   1149: invokevirtual charAt : (I)C
    //   1152: invokevirtual append : (C)Ljava/lang/StringBuilder;
    //   1155: pop
    //   1156: iload_2
    //   1157: ifeq -> 1348
    //   1160: goto -> 1167
    //   1163: invokestatic a : (Ljava/lang/Throwable;)Ljava/lang/Throwable;
    //   1166: athrow
    //   1167: aload_3
    //   1168: getstatic burp/Zr9j.Zc : Ljava/lang/String;
    //   1171: getstatic burp/Zlhu.ZJ : Ljava/lang/Object;
    //   1174: checkcast java/math/BigInteger
    //   1177: invokevirtual intValue : ()I
    //   1180: bipush #32
    //   1182: irem
    //   1183: invokestatic abs : (I)I
    //   1186: invokevirtual charAt : (I)C
    //   1189: invokevirtual append : (C)Ljava/lang/StringBuilder;
    //   1192: pop
    //   1193: iload_2
    //   1194: ifeq -> 1348
    //   1197: goto -> 1204
    //   1200: invokestatic a : (Ljava/lang/Throwable;)Ljava/lang/Throwable;
    //   1203: athrow
    //   1204: aload_3
    //   1205: getstatic burp/Zg1k.Ze : Ljava/lang/String;
    //   1208: getstatic burp/Zgl2.ZS : Ljava/lang/Object;
    //   1211: checkcast java/math/BigInteger
    //   1214: invokevirtual intValue : ()I
    //   1217: bipush #32
    //   1219: irem
    //   1220: invokestatic abs : (I)I
    //   1223: invokevirtual charAt : (I)C
    //   1226: invokevirtual append : (C)Ljava/lang/StringBuilder;
    //   1229: pop
    //   1230: iload_2
    //   1231: ifeq -> 1348
    //   1234: goto -> 1241
    //   1237: invokestatic a : (Ljava/lang/Throwable;)Ljava/lang/Throwable;
    //   1240: athrow
    //   1241: aload_3
    //   1242: getstatic burp/Zb8_.ZP : Ljava/lang/String;
    //   1245: getstatic burp/Zrp3.Zd : Ljava/lang/Object;
    //   1248: checkcast java/math/BigInteger
    //   1251: invokevirtual intValue : ()I
    //   1254: bipush #32
    //   1256: irem
    //   1257: invokestatic abs : (I)I
    //   1260: invokevirtual charAt : (I)C
    //   1263: invokevirtual append : (C)Ljava/lang/StringBuilder;
    //   1266: pop
    //   1267: iload_2
    //   1268: ifeq -> 1348
    //   1271: goto -> 1278
    //   1274: invokestatic a : (Ljava/lang/Throwable;)Ljava/lang/Throwable;
    //   1277: athrow
    //   1278: aload_3
    //   1279: getstatic burp/Zl5.ZE : Ljava/lang/String;
    //   1282: getstatic burp/Zs5i.ZD : Ljava/lang/Object;
    //   1285: checkcast java/math/BigInteger
    //   1288: invokevirtual intValue : ()I
    //   1291: bipush #32
    //   1293: irem
    //   1294: invokestatic abs : (I)I
    //   1297: invokevirtual charAt : (I)C
    //   1300: invokevirtual append : (C)Ljava/lang/StringBuilder;
    //   1303: pop
    //   1304: iload_2
    //   1305: ifeq -> 1348
    //   1308: goto -> 1315
    //   1311: invokestatic a : (Ljava/lang/Throwable;)Ljava/lang/Throwable;
    //   1314: athrow
    //   1315: aload_3
    //   1316: getstatic burp/Zl6z.ZL : Ljava/lang/String;
    //   1319: getstatic burp/Zm14.ZZ : Ljava/lang/Object;
    //   1322: checkcast java/math/BigInteger
    //   1325: invokevirtual intValue : ()I
    //   1328: bipush #32
    //   1330: irem
    //   1331: invokestatic abs : (I)I
    //   1334: invokevirtual charAt : (I)C
    //   1337: invokevirtual append : (C)Ljava/lang/StringBuilder;
    //   1340: pop
    //   1341: goto -> 1348
    //   1344: invokestatic a : (Ljava/lang/Throwable;)Ljava/lang/Throwable;
    //   1347: athrow
    //   1348: iinc #4, 1
    //   1351: iload_2
    //   1352: ifeq -> 15
    //   1355: aload_3
    //   1356: invokevirtual toString : ()Ljava/lang/String;
    //   1359: putstatic burp/Zb8_.ZP : Ljava/lang/String;
    //   1362: getstatic burp/Zzb2.ZW : Ljava/lang/Object;
    //   1365: checkcast java/math/BigInteger
    //   1368: invokevirtual toByteArray : ()[B
    //   1371: astore #4
    //   1373: aload #4
    //   1375: arraylength
    //   1376: bipush #8
    //   1378: iadd
    //   1379: bipush #6
    //   1381: ishr
    //   1382: iconst_1
    //   1383: iadd
    //   1384: bipush #16
    //   1386: imul
    //   1387: newarray int
    //   1389: astore #6
    //   1391: iconst_0
    //   1392: istore #7
    //   1394: iload #7
    //   1396: aload #4
    //   1398: arraylength
    //   1399: if_icmpge -> 1443
    //   1402: aload #4
    //   1404: iload #7
    //   1406: baload
    //   1407: sipush #255
    //   1410: iand
    //   1411: istore #8
    //   1413: aload #6
    //   1415: iload #7
    //   1417: iconst_2
    //   1418: ishr
    //   1419: dup2
    //   1420: iaload
    //   1421: iload #8
    //   1423: bipush #24
    //   1425: iload #7
    //   1427: iconst_4
    //   1428: irem
    //   1429: bipush #8
    //   1431: imul
    //   1432: isub
    //   1433: ishl
    //   1434: ior
    //   1435: iastore
    //   1436: iinc #7, 1
    //   1439: iload_2
    //   1440: ifeq -> 1394
    //   1443: aload #6
    //   1445: iload #7
    //   1447: iconst_2
    //   1448: ishr
    //   1449: dup2
    //   1450: iaload
    //   1451: sipush #128
    //   1454: bipush #24
    //   1456: iload #7
    //   1458: iconst_4
    //   1459: irem
    //   1460: bipush #8
    //   1462: imul
    //   1463: isub
    //   1464: ishl
    //   1465: ior
    //   1466: iastore
    //   1467: aload #6
    //   1469: aload #6
    //   1471: arraylength
    //   1472: iconst_1
    //   1473: isub
    //   1474: aload #4
    //   1476: arraylength
    //   1477: bipush #8
    //   1479: imul
    //   1480: iastore
    //   1481: bipush #80
    //   1483: newarray int
    //   1485: astore #8
    //   1487: ldc 1732584193
    //   1489: istore #9
    //   1491: ldc -271733879
    //   1493: istore #10
    //   1495: ldc -1732584194
    //   1497: istore #11
    //   1499: ldc 271733878
    //   1501: istore #12
    //   1503: ldc -1009589776
    //   1505: istore #13
    //   1507: iconst_0
    //   1508: istore #7
    //   1510: iload #7
    //   1512: aload #6
    //   1514: arraylength
    //   1515: if_icmpge -> 1837
    //   1518: iload #9
    //   1520: istore #14
    //   1522: iload #10
    //   1524: istore #15
    //   1526: iload #11
    //   1528: istore #16
    //   1530: iload #12
    //   1532: istore #17
    //   1534: iload #13
    //   1536: istore #18
    //   1538: iconst_0
    //   1539: istore #19
    //   1541: iload #19
    //   1543: bipush #80
    //   1545: if_icmpge -> 1795
    //   1548: iload #19
    //   1550: bipush #16
    //   1552: if_icmpge -> 1579
    //   1555: aload #8
    //   1557: iload #19
    //   1559: aload #6
    //   1561: iload #7
    //   1563: iload #19
    //   1565: iadd
    //   1566: iaload
    //   1567: iastore
    //   1568: iload_2
    //   1569: ifeq -> 1634
    //   1572: goto -> 1579
    //   1575: invokestatic a : (Ljava/lang/Throwable;)Ljava/lang/Throwable;
    //   1578: athrow
    //   1579: aload #8
    //   1581: iload #19
    //   1583: iconst_3
    //   1584: isub
    //   1585: iaload
    //   1586: aload #8
    //   1588: iload #19
    //   1590: bipush #8
    //   1592: isub
    //   1593: iaload
    //   1594: ixor
    //   1595: aload #8
    //   1597: iload #19
    //   1599: bipush #14
    //   1601: isub
    //   1602: iaload
    //   1603: ixor
    //   1604: aload #8
    //   1606: iload #19
    //   1608: bipush #16
    //   1610: isub
    //   1611: iaload
    //   1612: ixor
    //   1613: istore #20
    //   1615: iload #20
    //   1617: iconst_1
    //   1618: ishl
    //   1619: iload #20
    //   1621: bipush #31
    //   1623: iushr
    //   1624: ior
    //   1625: istore #21
    //   1627: aload #8
    //   1629: iload #19
    //   1631: iload #21
    //   1633: iastore
    //   1634: iload #9
    //   1636: iconst_5
    //   1637: ishl
    //   1638: iload #9
    //   1640: bipush #27
    //   1642: iushr
    //   1643: ior
    //   1644: istore #20
    //   1646: iload #20
    //   1648: iload #13
    //   1650: iadd
    //   1651: aload #8
    //   1653: iload #19
    //   1655: iaload
    //   1656: iadd
    //   1657: iload #19
    //   1659: bipush #20
    //   1661: if_icmpge -> 1687
    //   1664: ldc 1518500249
    //   1666: iload #10
    //   1668: iload #11
    //   1670: iand
    //   1671: iload #10
    //   1673: iconst_m1
    //   1674: ixor
    //   1675: iload #12
    //   1677: iand
    //   1678: ior
    //   1679: iadd
    //   1680: goto -> 1757
    //   1683: invokestatic a : (Ljava/lang/Throwable;)Ljava/lang/Throwable;
    //   1686: athrow
    //   1687: iload #19
    //   1689: bipush #40
    //   1691: if_icmpge -> 1712
    //   1694: ldc 1859775393
    //   1696: iload #10
    //   1698: iload #11
    //   1700: ixor
    //   1701: iload #12
    //   1703: ixor
    //   1704: iadd
    //   1705: goto -> 1757
    //   1708: invokestatic a : (Ljava/lang/Throwable;)Ljava/lang/Throwable;
    //   1711: athrow
    //   1712: iload #19
    //   1714: bipush #60
    //   1716: if_icmpge -> 1746
    //   1719: ldc -1894007588
    //   1721: iload #10
    //   1723: iload #11
    //   1725: iand
    //   1726: iload #10
    //   1728: iload #12
    //   1730: iand
    //   1731: ior
    //   1732: iload #11
    //   1734: iload #12
    //   1736: iand
    //   1737: ior
    //   1738: iadd
    //   1739: goto -> 1757
    //   1742: invokestatic a : (Ljava/lang/Throwable;)Ljava/lang/Throwable;
    //   1745: athrow
    //   1746: ldc -899497514
    //   1748: iload #10
    //   1750: iload #11
    //   1752: ixor
    //   1753: iload #12
    //   1755: ixor
    //   1756: iadd
    //   1757: iadd
    //   1758: istore #21
    //   1760: iload #12
    //   1762: istore #13
    //   1764: iload #11
    //   1766: istore #12
    //   1768: iload #10
    //   1770: bipush #30
    //   1772: ishl
    //   1773: iload #10
    //   1775: iconst_2
    //   1776: iushr
    //   1777: ior
    //   1778: istore #11
    //   1780: iload #9
    //   1782: istore #10
    //   1784: iload #21
    //   1786: istore #9
    //   1788: iinc #19, 1
    //   1791: iload_2
    //   1792: ifeq -> 1541
    //   1795: iload #9
    //   1797: iload #14
    //   1799: iadd
    //   1800: istore #9
    //   1802: iload #10
    //   1804: iload #15
    //   1806: iadd
    //   1807: istore #10
    //   1809: iload #11
    //   1811: iload #16
    //   1813: iadd
    //   1814: istore #11
    //   1816: iload #12
    //   1818: iload #17
    //   1820: iadd
    //   1821: istore #12
    //   1823: iload #13
    //   1825: iload #18
    //   1827: iadd
    //   1828: istore #13
    //   1830: iinc #7, 16
    //   1833: iload_2
    //   1834: ifeq -> 1510
    //   1837: iconst_5
    //   1838: newarray int
    //   1840: dup
    //   1841: iconst_0
    //   1842: iload #9
    //   1844: iastore
    //   1845: dup
    //   1846: iconst_1
    //   1847: iload #10
    //   1849: iastore
    //   1850: dup
    //   1851: iconst_2
    //   1852: iload #11
    //   1854: iastore
    //   1855: dup
    //   1856: iconst_3
    //   1857: iload #12
    //   1859: iastore
    //   1860: dup
    //   1861: iconst_4
    //   1862: iload #13
    //   1864: iastore
    //   1865: astore #14
    //   1867: bipush #20
    //   1869: newarray byte
    //   1871: astore #15
    //   1873: iconst_0
    //   1874: istore #16
    //   1876: iload #16
    //   1878: bipush #20
    //   1880: if_icmpge -> 1921
    //   1883: aload #14
    //   1885: iload #16
    //   1887: iconst_4
    //   1888: idiv
    //   1889: iaload
    //   1890: istore #17
    //   1892: iconst_3
    //   1893: iload #16
    //   1895: iconst_4
    //   1896: irem
    //   1897: isub
    //   1898: bipush #8
    //   1900: imul
    //   1901: istore #18
    //   1903: aload #15
    //   1905: iload #16
    //   1907: iload #17
    //   1909: iload #18
    //   1911: iushr
    //   1912: i2b
    //   1913: bastore
    //   1914: iinc #16, 1
    //   1917: iload_2
    //   1918: ifeq -> 1876
    //   1921: aload #15
    //   1923: astore #5
    //   1925: sipush #-4854
    //   1928: new java/math/BigInteger
    //   1931: dup
    //   1932: aload #5
    //   1934: invokespecial <init> : ([B)V
    //   1937: invokevirtual abs : ()Ljava/math/BigInteger;
    //   1940: putstatic burp/Zr8r.ZR : Ljava/lang/Object;
    //   1943: sipush #-14880
    //   1946: invokestatic a : (II)Ljava/lang/String;
    //   1949: iconst_1
    //   1950: ldc burp/Zeyd
    //   1952: invokevirtual getClassLoader : ()Ljava/lang/ClassLoader;
    //   1955: invokestatic forName : (Ljava/lang/String;ZLjava/lang/ClassLoader;)Ljava/lang/Class;
    //   1958: invokevirtual getDeclaredFields : ()[Ljava/lang/reflect/Field;
    //   1961: astore #4
    //   1963: aload #4
    //   1965: arraylength
    //   1966: istore #5
    //   1968: iconst_0
    //   1969: istore #6
    //   1971: iload #6
    //   1973: iload #5
    //   1975: if_icmpge -> 2113
    //   1978: aload #4
    //   1980: iload #6
    //   1982: aaload
    //   1983: astore #7
    //   1985: aload #7
    //   1987: invokevirtual getModifiers : ()I
    //   1990: invokestatic isStatic : (I)Z
    //   1993: ifne -> 2003
    //   1996: goto -> 2106
    //   1999: invokestatic a : (Ljava/lang/Throwable;)Ljava/lang/Throwable;
    //   2002: athrow
    //   2003: aload #7
    //   2005: invokevirtual getType : ()Ljava/lang/Class;
    //   2008: astore #8
    //   2010: aload #8
    //   2012: ifnull -> 2093
    //   2015: aload #8
    //   2017: invokevirtual isPrimitive : ()Z
    //   2020: ifne -> 2093
    //   2023: goto -> 2030
    //   2026: invokestatic a : (Ljava/lang/Throwable;)Ljava/lang/Throwable;
    //   2029: athrow
    //   2030: aload #8
    //   2032: invokevirtual getPackage : ()Ljava/lang/Package;
    //   2035: ifnull -> 2093
    //   2038: goto -> 2045
    //   2041: invokestatic a : (Ljava/lang/Throwable;)Ljava/lang/Throwable;
    //   2044: athrow
    //   2045: aload #8
    //   2047: invokevirtual getPackage : ()Ljava/lang/Package;
    //   2050: invokevirtual getName : ()Ljava/lang/String;
    //   2053: ifnull -> 2093
    //   2056: goto -> 2063
    //   2059: invokestatic a : (Ljava/lang/Throwable;)Ljava/lang/Throwable;
    //   2062: athrow
    //   2063: aload #8
    //   2065: invokevirtual getPackage : ()Ljava/lang/Package;
    //   2068: invokevirtual getName : ()Ljava/lang/String;
    //   2071: sipush #-4849
    //   2074: sipush #24903
    //   2077: invokestatic a : (II)Ljava/lang/String;
    //   2080: invokevirtual startsWith : (Ljava/lang/String;)Z
    //   2083: ifne -> 2093
    //   2086: goto -> 2093
    //   2089: invokestatic a : (Ljava/lang/Throwable;)Ljava/lang/Throwable;
    //   2092: athrow
    //   2093: aload #7
    //   2095: iconst_1
    //   2096: invokevirtual setAccessible : (Z)V
    //   2099: aload #7
    //   2101: aconst_null
    //   2102: invokevirtual get : (Ljava/lang/Object;)Ljava/lang/Object;
    //   2105: pop
    //   2106: iinc #6, 1
    //   2109: iload_2
    //   2110: ifeq -> 1971
    //   2113: sipush #-4853
    //   2116: sipush #30102
    //   2119: invokestatic a : (II)Ljava/lang/String;
    //   2122: invokestatic forName : (Ljava/lang/String;)Ljava/lang/Class;
    //   2125: invokevirtual getDeclaredMethods : ()[Ljava/lang/reflect/Method;
    //   2128: astore #4
    //   2130: aload #4
    //   2132: arraylength
    //   2133: istore #5
    //   2135: iconst_0
    //   2136: istore #6
    //   2138: iload #6
    //   2140: iload #5
    //   2142: if_icmpge -> 2275
    //   2145: aload #4
    //   2147: iload #6
    //   2149: aaload
    //   2150: astore #7
    //   2152: aload #7
    //   2154: invokevirtual getParameterTypes : ()[Ljava/lang/Class;
    //   2157: pop
    //   2158: aload #7
    //   2160: invokevirtual getModifiers : ()I
    //   2163: invokestatic isStatic : (I)Z
    //   2166: ifeq -> 2261
    //   2169: aload #7
    //   2171: invokevirtual getParameterTypes : ()[Ljava/lang/Class;
    //   2174: arraylength
    //   2175: iconst_2
    //   2176: if_icmpne -> 2261
    //   2179: goto -> 2186
    //   2182: invokestatic a : (Ljava/lang/Throwable;)Ljava/lang/Throwable;
    //   2185: athrow
    //   2186: aload #7
    //   2188: invokevirtual getReturnType : ()Ljava/lang/Class;
    //   2191: getstatic java/lang/Void.TYPE : Ljava/lang/Class;
    //   2194: invokevirtual equals : (Ljava/lang/Object;)Z
    //   2197: ifeq -> 2261
    //   2200: goto -> 2207
    //   2203: invokestatic a : (Ljava/lang/Throwable;)Ljava/lang/Throwable;
    //   2206: athrow
    //   2207: aload #7
    //   2209: iconst_1
    //   2210: invokevirtual setAccessible : (Z)V
    //   2213: aload #7
    //   2215: aconst_null
    //   2216: iconst_2
    //   2217: anewarray java/lang/Object
    //   2220: dup
    //   2221: iconst_0
    //   2222: aload_0
    //   2223: aastore
    //   2224: dup
    //   2225: iconst_1
    //   2226: aload_1
    //   2227: ifnonnull -> 2245
    //   2230: goto -> 2237
    //   2233: invokestatic a : (Ljava/lang/Throwable;)Ljava/lang/Throwable;
    //   2236: athrow
    //   2237: aload_1
    //   2238: goto -> 2252
    //   2241: invokestatic a : (Ljava/lang/Throwable;)Ljava/lang/Throwable;
    //   2244: athrow
    //   2245: aload_1
    //   2246: checkcast [B
    //   2249: invokevirtual clone : ()Ljava/lang/Object;
    //   2252: aastore
    //   2253: invokevirtual invoke : (Ljava/lang/Object;[Ljava/lang/Object;)Ljava/lang/Object;
    //   2256: pop
    //   2257: iload_2
    //   2258: ifeq -> 2275
    //   2261: iinc #6, 1
    //   2264: iload_2
    //   2265: ifeq -> 2138
    //   2268: goto -> 2275
    //   2271: invokestatic a : (Ljava/lang/Throwable;)Ljava/lang/Throwable;
    //   2274: athrow
    //   2275: getstatic burp/Zgl2.Zw : Ljava/lang/String;
    //   2278: getstatic burp/Zbzj.Zz : Ljava/lang/Object;
    //   2281: checkcast java/math/BigInteger
    //   2284: invokevirtual intValue : ()I
    //   2287: bipush #32
    //   2289: irem
    //   2290: invokestatic abs : (I)I
    //   2293: invokevirtual charAt : (I)C
    //   2296: getstatic burp/Zg_6.Zc : Ljava/lang/String;
    //   2299: getstatic burp/Zlzs.ZL : Ljava/lang/Object;
    //   2302: checkcast java/math/BigInteger
    //   2305: invokevirtual intValue : ()I
    //   2308: bipush #32
    //   2310: irem
    //   2311: invokestatic abs : (I)I
    //   2314: invokevirtual charAt : (I)C
    //   2317: if_icmpgt -> 2424
    //   2320: getstatic burp/Zktq.Zc : Ljava/lang/String;
    //   2323: getstatic burp/Zg_6.ZU : Ljava/lang/Object;
    //   2326: checkcast java/math/BigInteger
    //   2329: invokevirtual intValue : ()I
    //   2332: bipush #32
    //   2334: irem
    //   2335: invokestatic abs : (I)I
    //   2338: invokevirtual charAt : (I)C
    //   2341: getstatic burp/Zz8o.Zo : Ljava/lang/String;
    //   2344: getstatic burp/Zz5l.Zb : Ljava/lang/Object;
    //   2347: checkcast java/math/BigInteger
    //   2350: invokevirtual intValue : ()I
    //   2353: bipush #32
    //   2355: irem
    //   2356: invokestatic abs : (I)I
    //   2359: invokevirtual charAt : (I)C
    //   2362: if_icmple -> 2424
    //   2365: goto -> 2372
    //   2368: invokestatic a : (Ljava/lang/Throwable;)Ljava/lang/Throwable;
    //   2371: athrow
    //   2372: getstatic burp/Zecm.Zv : Ljava/lang/String;
    //   2375: getstatic burp/Ztpg.Z_ : Ljava/lang/Object;
    //   2378: checkcast java/math/BigInteger
    //   2381: invokevirtual intValue : ()I
    //   2384: bipush #32
    //   2386: irem
    //   2387: invokestatic abs : (I)I
    //   2390: invokevirtual charAt : (I)C
    //   2393: getstatic burp/Zzh9.ZF : Ljava/lang/String;
    //   2396: getstatic burp/Zz8o.Zg : Ljava/lang/Object;
    //   2399: checkcast java/math/BigInteger
    //   2402: invokevirtual intValue : ()I
    //   2405: bipush #32
    //   2407: irem
    //   2408: invokestatic abs : (I)I
    //   2411: invokevirtual charAt : (I)C
    //   2414: if_icmpgt -> 2432
    //   2417: goto -> 2424
    //   2420: invokestatic a : (Ljava/lang/Throwable;)Ljava/lang/Throwable;
    //   2423: athrow
    //   2424: iconst_1
    //   2425: goto -> 2433
    //   2428: invokestatic a : (Ljava/lang/Throwable;)Ljava/lang/Throwable;
    //   2431: athrow
    //   2432: iconst_0
    //   2433: ireturn
    //   2434: astore_3
    //   2435: new java/lang/Exception
    //   2438: dup
    //   2439: aload_3
    //   2440: invokevirtual getMessage : ()Ljava/lang/String;
    //   2443: invokespecial <init> : (Ljava/lang/String;)V
    //   2446: athrow
    // Exception table:
    //   from	to	target	type
    //   4	2433	2434	java/lang/Throwable
    //   22	198	201	java/lang/Throwable
    //   168	235	238	java/lang/Throwable
    //   205	272	275	java/lang/Throwable
    //   242	309	312	java/lang/Throwable
    //   279	346	349	java/lang/Throwable
    //   316	383	386	java/lang/Throwable
    //   353	420	423	java/lang/Throwable
    //   390	457	460	java/lang/Throwable
    //   427	494	497	java/lang/Throwable
    //   464	531	534	java/lang/Throwable
    //   501	568	571	java/lang/Throwable
    //   538	605	608	java/lang/Throwable
    //   575	642	645	java/lang/Throwable
    //   612	679	682	java/lang/Throwable
    //   649	716	719	java/lang/Throwable
    //   686	753	756	java/lang/Throwable
    //   723	790	793	java/lang/Throwable
    //   760	827	830	java/lang/Throwable
    //   797	864	867	java/lang/Throwable
    //   834	901	904	java/lang/Throwable
    //   871	938	941	java/lang/Throwable
    //   908	975	978	java/lang/Throwable
    //   945	1012	1015	java/lang/Throwable
    //   982	1049	1052	java/lang/Throwable
    //   1019	1086	1089	java/lang/Throwable
    //   1056	1123	1126	java/lang/Throwable
    //   1093	1160	1163	java/lang/Throwable
    //   1130	1197	1200	java/lang/Throwable
    //   1167	1234	1237	java/lang/Throwable
    //   1204	1271	1274	java/lang/Throwable
    //   1241	1308	1311	java/lang/Throwable
    //   1278	1341	1344	java/lang/Throwable
    //   1548	1572	1575	java/lang/Throwable
    //   1646	1683	1683	java/lang/Throwable
    //   1687	1708	1708	java/lang/Throwable
    //   1712	1742	1742	java/lang/Throwable
    //   1985	1999	1999	java/lang/Throwable
    //   2010	2023	2026	java/lang/Throwable
    //   2015	2038	2041	java/lang/Throwable
    //   2030	2056	2059	java/lang/Throwable
    //   2045	2086	2089	java/lang/Throwable
    //   2152	2179	2182	java/lang/Throwable
    //   2169	2200	2203	java/lang/Throwable
    //   2186	2230	2233	java/lang/Throwable
    //   2207	2241	2241	java/lang/Throwable
    //   2252	2268	2271	java/lang/Throwable
    //   2275	2365	2368	java/lang/Throwable
    //   2320	2417	2420	java/lang/Throwable
    //   2372	2428	2428	java/lang/Throwable
  }
  
  static void Zy(Object[] paramArrayOfObject, Object paramObject) throws Throwable {}
  
  static void Zn(Object paramObject) {
    Zg3m.Za = a(-4856, -32453);
    Zg3m.ZK = new BigInteger(a(-4852, -12543));
    boolean bool = Zt2e.ZN();
    try {
      try {
        if (Zl15.ZI.charAt(Math.abs(((BigInteger)Zmfw.ZS).intValue() % 32)) <= Zs5i.ZJ.charAt(Math.abs(((BigInteger)Zrxf.ZS).intValue() % 32))) {
          try {
            Zz35.ZB(Class.forName(a(-4851, 32519)));
            if (!bool)
              Zro_.Zd(Class.forName(a(-4855, -10867))); 
          } catch (Throwable throwable) {
            throw a(null);
          } 
          return;
        } 
      } catch (Throwable throwable) {
        throw a(null);
      } 
      Zro_.Zd(Class.forName(a(-4855, -10867)));
    } catch (Throwable throwable) {}
  }
  
  static {
    // Byte code:
    //   0: bipush #8
    //   2: anewarray java/lang/String
    //   5: astore #5
    //   7: iconst_0
    //   8: istore_3
    //   9: ldc 'v$3Ã©Â§ÂŽuÂ¿\\t'mÃ€Ã¢Â«Ãj Ã•-ÃŠ6Â¢8ÃšÂŽÃ°cÃ˜Â€zÃ½|Ã§Â¿?Â®Ã¦Â¯tÃ…Ã‹Â„Â®Â›Ã±Ã…ÂŠ\\t/Â¿Âˆ6Â¢^=( !Ã¾^*{OÂµ}\\fÃ½Â«BÂ˜NÃYÂ”SÂÂŸÂµÃ¶Â€Ã‡Ãˆ*ÂžÃ¹jÃ‚ '
    //   11: dup
    //   12: astore_2
    //   13: invokevirtual length : ()I
    //   16: istore #4
    //   18: bipush #9
    //   20: istore_1
    //   21: iconst_m1
    //   22: istore_0
    //   23: bipush #123
    //   25: iinc #0, 1
    //   28: aload_2
    //   29: iload_0
    //   30: dup
    //   31: iload_1
    //   32: iadd
    //   33: invokevirtual substring : (II)Ljava/lang/String;
    //   36: iconst_m1
    //   37: goto -> 143
    //   40: aload #5
    //   42: swap
    //   43: iload_3
    //   44: iinc #3, 1
    //   47: swap
    //   48: aastore
    //   49: iload_0
    //   50: iload_1
    //   51: iadd
    //   52: dup
    //   53: istore_0
    //   54: iload #4
    //   56: if_icmpge -> 68
    //   59: aload_2
    //   60: iload_0
    //   61: invokevirtual charAt : (I)C
    //   64: istore_1
    //   65: goto -> 23
    //   68: ldc '~Ãˆv\\fCÃ Â€||Ã¿Â½Â˜zeÂ‹yÃ¬@^hOÃ‰Ã´Â¤?QÂ¢l"Â¬DÃ»1Â¯EÂ—(RÂ•:Ã†-\!Â˜Ã‘uÂ¼Ã£Ã°Â3[Ã¤)~ÂˆyÃ„J?hÂ…ÂƒÂƒÃ‰2QÂ \\tÃ¥ÂŠÂ¥Ã¤so{ÂŒ'
    //   70: dup
    //   71: astore_2
    //   72: invokevirtual length : ()I
    //   75: istore #4
    //   77: bipush #77
    //   79: istore_1
    //   80: iconst_m1
    //   81: istore_0
    //   82: bipush #73
    //   84: iinc #0, 1
    //   87: aload_2
    //   88: iload_0
    //   89: dup
    //   90: iload_1
    //   91: iadd
    //   92: invokevirtual substring : (II)Ljava/lang/String;
    //   95: iconst_0
    //   96: goto -> 143
    //   99: aload #5
    //   101: swap
    //   102: iload_3
    //   103: iinc #3, 1
    //   106: swap
    //   107: aastore
    //   108: iload_0
    //   109: iload_1
    //   110: iadd
    //   111: dup
    //   112: istore_0
    //   113: iload #4
    //   115: if_icmpge -> 127
    //   118: aload_2
    //   119: iload_0
    //   120: invokevirtual charAt : (I)C
    //   123: istore_1
    //   124: goto -> 82
    //   127: aload #5
    //   129: putstatic burp/Zefn.a : [Ljava/lang/String;
    //   132: bipush #8
    //   134: anewarray java/lang/String
    //   137: putstatic burp/Zefn.b : [Ljava/lang/String;
    //   140: goto -> 300
    //   143: dup_x2
    //   144: pop
    //   145: invokevirtual toCharArray : ()[C
    //   148: dup_x1
    //   149: arraylength
    //   150: dup_x2
    //   151: pop
    //   152: iconst_0
    //   153: istore #6
    //   155: dup2_x1
    //   156: pop2
    //   157: dup_x2
    //   158: iconst_1
    //   159: if_icmpgt -> 260
    //   162: dup2
    //   163: swap
    //   164: iload #6
    //   166: dup2_x1
    //   167: caload
    //   168: swap
    //   169: iload #6
    //   171: bipush #7
    //   173: irem
    //   174: tableswitch default -> 242, 0 -> 212, 1 -> 217, 2 -> 222, 3 -> 227, 4 -> 232, 5 -> 237
    //   212: bipush #14
    //   214: goto -> 244
    //   217: bipush #108
    //   219: goto -> 244
    //   222: bipush #116
    //   224: goto -> 244
    //   227: bipush #95
    //   229: goto -> 244
    //   232: bipush #73
    //   234: goto -> 244
    //   237: bipush #104
    //   239: goto -> 244
    //   242: bipush #37
    //   244: ixor
    //   245: ixor
    //   246: i2c
    //   247: castore
    //   248: iinc #6, 1
    //   251: dup
    //   252: ifne -> 260
    //   255: dup2
    //   256: dup_x1
    //   257: goto -> 166
    //   260: dup2_x1
    //   261: pop2
    //   262: dup_x2
    //   263: iload #6
    //   265: if_icmpgt -> 162
    //   268: pop
    //   269: new java/lang/String
    //   272: dup_x1
    //   273: swap
    //   274: invokespecial <init> : ([C)V
    //   277: invokevirtual intern : ()Ljava/lang/String;
    //   280: swap
    //   281: pop
    //   282: swap
    //   283: tableswitch default -> 40, 0 -> 99
    //   300: sipush #-4850
    //   303: sipush #9852
    //   306: invokestatic a : (II)Ljava/lang/String;
    //   309: putstatic burp/Zefn.Ze : Ljava/lang/String;
    //   312: new java/math/BigInteger
    //   315: dup
    //   316: iconst_1
    //   317: bipush #32
    //   319: newarray byte
    //   321: dup
    //   322: iconst_0
    //   323: bipush #33
    //   325: bastore
    //   326: dup
    //   327: iconst_1
    //   328: bipush #79
    //   330: bastore
    //   331: dup
    //   332: iconst_2
    //   333: bipush #117
    //   335: bastore
    //   336: dup
    //   337: iconst_3
    //   338: bipush #105
    //   340: bastore
    //   341: dup
    //   342: iconst_4
    //   343: iconst_m1
    //   344: bastore
    //   345: dup
    //   346: iconst_5
    //   347: bipush #72
    //   349: bastore
    //   350: dup
    //   351: bipush #6
    //   353: bipush #7
    //   355: bastore
    //   356: dup
    //   357: bipush #7
    //   359: iconst_m1
    //   360: bastore
    //   361: dup
    //   362: bipush #8
    //   364: bipush #65
    //   366: bastore
    //   367: dup
    //   368: bipush #9
    //   370: bipush #109
    //   372: bastore
    //   373: dup
    //   374: bipush #10
    //   376: bipush #9
    //   378: bastore
    //   379: dup
    //   380: bipush #11
    //   382: bipush #120
    //   384: bastore
    //   385: dup
    //   386: bipush #12
    //   388: bipush #98
    //   390: bastore
    //   391: dup
    //   392: bipush #13
    //   394: bipush #91
    //   396: bastore
    //   397: dup
    //   398: bipush #14
    //   400: bipush #-34
    //   402: bastore
    //   403: dup
    //   404: bipush #15
    //   406: iconst_0
    //   407: bastore
    //   408: dup
    //   409: bipush #16
    //   411: bipush #78
    //   413: bastore
    //   414: dup
    //   415: bipush #17
    //   417: bipush #-59
    //   419: bastore
    //   420: dup
    //   421: bipush #18
    //   423: bipush #71
    //   425: bastore
    //   426: dup
    //   427: bipush #19
    //   429: bipush #-72
    //   431: bastore
    //   432: dup
    //   433: bipush #20
    //   435: bipush #-2
    //   437: bastore
    //   438: dup
    //   439: bipush #21
    //   441: bipush #-23
    //   443: bastore
    //   444: dup
    //   445: bipush #22
    //   447: bipush #53
    //   449: bastore
    //   450: dup
    //   451: bipush #23
    //   453: bipush #-70
    //   455: bastore
    //   456: dup
    //   457: bipush #24
    //   459: bipush #-47
    //   461: bastore
    //   462: dup
    //   463: bipush #25
    //   465: bipush #-42
    //   467: bastore
    //   468: dup
    //   469: bipush #26
    //   471: bipush #84
    //   473: bastore
    //   474: dup
    //   475: bipush #27
    //   477: bipush #-20
    //   479: bastore
    //   480: dup
    //   481: bipush #28
    //   483: bipush #67
    //   485: bastore
    //   486: dup
    //   487: bipush #29
    //   489: bipush #-112
    //   491: bastore
    //   492: dup
    //   493: bipush #30
    //   495: bipush #32
    //   497: bastore
    //   498: dup
    //   499: bipush #31
    //   501: bipush #74
    //   503: bastore
    //   504: invokespecial <init> : (I[B)V
    //   507: putstatic burp/Zefn.ZJ : Ljava/lang/Object;
    //   510: return
  }
  
  private static Throwable a(Throwable paramThrowable) {
    return paramThrowable;
  }
  
  private static String a(int paramInt1, int paramInt2) {
    int i = (paramInt1 ^ 0xFFFFED0A) & 0xFFFF;
    if (b[i] == null) {
      char[] arrayOfChar = a[i].toCharArray();
      switch (arrayOfChar[0] & 0xFF) {
        case 0:
        
        case 1:
        
        case 2:
        
        case 3:
        
        case 4:
        
        case 5:
        
        case 6:
        
        case 7:
        
        case 8:
        
        case 9:
        
        case 10:
        
        case 11:
        
        case 12:
        
        case 13:
        
        case 14:
        
        case 15:
        
        case 16:
        
        case 17:
        
        case 18:
        
        case 19:
        
        case 20:
        
        case 21:
        
        case 22:
        
        case 23:
        
        case 24:
        
        case 25:
        
        case 26:
        
        case 27:
        
        case 28:
        
        case 29:
        
        case 30:
        
        case 31:
        
        case 32:
        
        case 33:
        
        case 34:
        
        case 35:
        
        case 36:
        
        case 37:
        
        case 38:
        
        case 39:
        
        case 40:
        
        case 41:
        
        case 42:
        
        case 43:
        
        case 44:
        
        case 45:
        
        case 46:
        
        case 47:
        
        case 48:
        
        case 49:
        
        case 50:
        
        case 51:
        
        case 52:
        
        case 53:
        
        case 54:
        
        case 55:
        
        case 56:
        
        case 57:
        
        case 58:
        
        case 59:
        
        case 60:
        
        case 61:
        
        case 62:
        
        case 63:
        
        case 64:
        
        case 65:
        
        case 66:
        
        case 67:
        
        case 68:
        
        case 69:
        
        case 70:
        
        case 71:
        
        case 72:
        
        case 73:
        
        case 74:
        
        case 75:
        
        case 76:
        
        case 77:
        
        case 78:
        
        case 79:
        
        case 80:
        
        case 81:
        
        case 82:
        
        case 83:
        
        case 84:
        
        case 85:
        
        case 86:
        
        case 87:
        
        case 88:
        
        case 89:
        
        case 90:
        
        case 91:
        
        case 92:
        
        case 93:
        
        case 94:
        
        case 95:
        
        case 96:
        
        case 97:
        
        case 98:
        
        case 99:
        
        case 100:
        
        case 101:
        
        case 102:
        
        case 103:
        
        case 104:
        
        case 105:
        
        case 106:
        
        case 107:
        
        case 108:
        
        case 109:
        
        case 110:
        
        case 111:
        
        case 112:
        
        case 113:
        
        case 114:
        
        case 115:
        
        case 116:
        
        case 117:
        
        case 118:
        
        case 119:
        
        case 120:
        
        case 121:
        
        case 122:
        
        case 123:
        
        case 124:
        
        case 125:
        
        case 126:
        
        case 127:
        
        case 128:
        
        case 129:
        
        case 130:
        
        case 131:
        
        case 132:
        
        case 133:
        
        case 134:
        
        case 135:
        
        case 136:
        
        case 137:
        
        case 138:
        
        case 139:
        
        case 140:
        
        case 141:
        
        case 142:
        
        case 143:
        
        case 144:
        
        case 145:
        
        case 146:
        
        case 147:
        
        case 148:
        
        case 149:
        
        case 150:
        
        case 151:
        
        case 152:
        
        case 153:
        
        case 154:
        
        case 155:
        
        case 156:
        
        case 157:
        
        case 158:
        
        case 159:
        
        case 160:
        
        case 161:
        
        case 162:
        
        case 163:
        
        case 164:
        
        case 165:
        
        case 166:
        
        case 167:
        
        case 168:
        
        case 169:
        
        case 170:
        
        case 171:
        
        case 172:
        
        case 173:
        
        case 174:
        
        case 175:
        
        case 176:
        
        case 177:
        
        case 178:
        
        case 179:
        
        case 180:
        
        case 181:
        
        case 182:
        
        case 183:
        
        case 184:
        
        case 185:
        
        case 186:
        
        case 187:
        
        case 188:
        
        case 189:
        
        case 190:
        
        case 191:
        
        case 192:
        
        case 193:
        
        case 194:
        
        case 195:
        
        case 196:
        
        case 197:
        
        case 198:
        
        case 199:
        
        case 200:
        
        case 201:
        
        case 202:
        
        case 203:
        
        case 204:
        
        case 205:
        
        case 206:
        
        case 207:
        
        case 208:
        
        case 209:
        
        case 210:
        
        case 211:
        
        case 212:
        
        case 213:
        
        case 214:
        
        case 215:
        
        case 216:
        
        case 217:
        
        case 218:
        
        case 219:
        
        case 220:
        
        case 221:
        
        case 222:
        
        case 223:
        
        case 224:
        
        case 225:
        
        case 226:
        
        case 227:
        
        case 228:
        
        case 229:
        
        case 230:
        
        case 231:
        
        case 232:
        
        case 233:
        
        case 234:
        
        case 235:
        
        case 236:
        
        case 237:
        
        case 238:
        
        case 239:
        
        case 240:
        
        case 241:
        
        case 242:
        
        case 243:
        
        case 244:
        
        case 245:
        
        case 246:
        
        case 247:
        
        case 248:
        
        case 249:
        
        case 250:
        
        case 251:
        
        case 252:
        
        case 253:
        
        case 254:
        
        default:
          break;
      } 
      char c = 'Â¼';
      int j = (paramInt2 & 0xFF) - c;
      if (j < 0)
        j += 256; 
      int k = ((paramInt2 & 0xFFFF) >>> 8) - c;
      if (k < 0)
        k += 256; 
      for (byte b = 0; b < arrayOfChar.length; b++) {
        int m = b % 2;
        if (m == 0) {
          arrayOfChar[b] = (char)(arrayOfChar[b] ^ j);
          j = ((j >>> 3 | j << 5) ^ arrayOfChar[b]) & 0xFF;
        } else {
          arrayOfChar[b] = (char)(arrayOfChar[b] ^ k);
          k = ((k >>> 3 | k << 5) ^ arrayOfChar[b]) & 0xFF;
        } 
      } 
      b[i] = (new String(arrayOfChar)).intern();
    } 
    return b[i];
  }
}


/* Location:              C:\Program Files\BurpSuitePro\burpsuite_pro.jar!\burp\Zefn.class
 * Java compiler version: 21 (65.0)
 * JD-Core Version:       1.1.3
 */