package burp;

import java.math.BigInteger;

class Zefo extends ClassLoader {
  static String Zb;
  
  static Object ZW;
  
  private static final String[] a;
  
  private static final String[] b;
  
  static void Zv(Object[] paramArrayOfObject, Object paramObject) throws Throwable {}
  
  static void ZT(Object paramObject) {
    Zre5.ZR = a(-5081, 4908);
    Zre5.Zo = new BigInteger(a(-5083, 3398));
    boolean bool = Zt2e.ZK();
    try {
      try {
        if (Zlh8.ZY.charAt(Math.abs(((BigInteger)Zeqg.Zm).intValue() % 32)) > Zstb.Zd.charAt(Math.abs(((BigInteger)Zvo3.Ze).intValue() % 32))) {
          try {
            Zg_5.Zg(Class.forName(a(-5078, 21352)));
            if (bool)
              Zko9.ZX(Class.forName(a(-5087, -30559))); 
          } catch (Throwable throwable) {
            throw a(null);
          } 
          return;
        } 
      } catch (Throwable throwable) {
        throw a(null);
      } 
      Zko9.ZX(Class.forName(a(-5087, -30559)));
    } catch (Throwable throwable) {}
  }
  
  static boolean Zn(Object[] paramArrayOfObject, Object paramObject) throws Throwable {
    // Byte code:
    //   0: invokestatic ZK : ()Z
    //   3: istore_2
    //   4: new java/lang/StringBuilder
    //   7: dup
    //   8: invokespecial <init> : ()V
    //   11: astore_3
    //   12: iconst_0
    //   13: istore #4
    //   15: iload #4
    //   17: bipush #32
    //   19: if_icmpge -> 1355
    //   22: iload #4
    //   24: tableswitch default -> 1348, 0 -> 168, 1 -> 205, 2 -> 242, 3 -> 279, 4 -> 316, 5 -> 353, 6 -> 390, 7 -> 427, 8 -> 464, 9 -> 501, 10 -> 538, 11 -> 575, 12 -> 612, 13 -> 649, 14 -> 686, 15 -> 723, 16 -> 760, 17 -> 797, 18 -> 834, 19 -> 871, 20 -> 908, 21 -> 945, 22 -> 982, 23 -> 1019, 24 -> 1056, 25 -> 1093, 26 -> 1130, 27 -> 1167, 28 -> 1204, 29 -> 1241, 30 -> 1278, 31 -> 1315
    //   168: aload_3
    //   169: getstatic burp/Zmhi.ZQ : Ljava/lang/String;
    //   172: getstatic burp/Zsxo.Za : Ljava/lang/Object;
    //   175: checkcast java/math/BigInteger
    //   178: invokevirtual intValue : ()I
    //   181: bipush #32
    //   183: irem
    //   184: invokestatic abs : (I)I
    //   187: invokevirtual charAt : (I)C
    //   190: invokevirtual append : (C)Ljava/lang/StringBuilder;
    //   193: pop
    //   194: iload_2
    //   195: ifeq -> 1348
    //   198: goto -> 205
    //   201: invokestatic a : (Ljava/lang/Throwable;)Ljava/lang/Throwable;
    //   204: athrow
    //   205: aload_3
    //   206: getstatic burp/Zlnm.ZL : Ljava/lang/String;
    //   209: getstatic burp/Zel.ZB : Ljava/lang/Object;
    //   212: checkcast java/math/BigInteger
    //   215: invokevirtual intValue : ()I
    //   218: bipush #32
    //   220: irem
    //   221: invokestatic abs : (I)I
    //   224: invokevirtual charAt : (I)C
    //   227: invokevirtual append : (C)Ljava/lang/StringBuilder;
    //   230: pop
    //   231: iload_2
    //   232: ifeq -> 1348
    //   235: goto -> 242
    //   238: invokestatic a : (Ljava/lang/Throwable;)Ljava/lang/Throwable;
    //   241: athrow
    //   242: aload_3
    //   243: getstatic burp/Zr48.ZG : Ljava/lang/String;
    //   246: getstatic burp/Zkjr.Zw : Ljava/lang/Object;
    //   249: checkcast java/math/BigInteger
    //   252: invokevirtual intValue : ()I
    //   255: bipush #32
    //   257: irem
    //   258: invokestatic abs : (I)I
    //   261: invokevirtual charAt : (I)C
    //   264: invokevirtual append : (C)Ljava/lang/StringBuilder;
    //   267: pop
    //   268: iload_2
    //   269: ifeq -> 1348
    //   272: goto -> 279
    //   275: invokestatic a : (Ljava/lang/Throwable;)Ljava/lang/Throwable;
    //   278: athrow
    //   279: aload_3
    //   280: getstatic burp/Zram.Ze : Ljava/lang/String;
    //   283: getstatic burp/Zz0w.ZF : Ljava/lang/Object;
    //   286: checkcast java/math/BigInteger
    //   289: invokevirtual intValue : ()I
    //   292: bipush #32
    //   294: irem
    //   295: invokestatic abs : (I)I
    //   298: invokevirtual charAt : (I)C
    //   301: invokevirtual append : (C)Ljava/lang/StringBuilder;
    //   304: pop
    //   305: iload_2
    //   306: ifeq -> 1348
    //   309: goto -> 316
    //   312: invokestatic a : (Ljava/lang/Throwable;)Ljava/lang/Throwable;
    //   315: athrow
    //   316: aload_3
    //   317: getstatic burp/Zs8y.Zr : Ljava/lang/String;
    //   320: getstatic burp/Zsxo.Za : Ljava/lang/Object;
    //   323: checkcast java/math/BigInteger
    //   326: invokevirtual intValue : ()I
    //   329: bipush #32
    //   331: irem
    //   332: invokestatic abs : (I)I
    //   335: invokevirtual charAt : (I)C
    //   338: invokevirtual append : (C)Ljava/lang/StringBuilder;
    //   341: pop
    //   342: iload_2
    //   343: ifeq -> 1348
    //   346: goto -> 353
    //   349: invokestatic a : (Ljava/lang/Throwable;)Ljava/lang/Throwable;
    //   352: athrow
    //   353: aload_3
    //   354: getstatic burp/Zzo5.ZX : Ljava/lang/String;
    //   357: getstatic burp/Zm8v.ZU : Ljava/lang/Object;
    //   360: checkcast java/math/BigInteger
    //   363: invokevirtual intValue : ()I
    //   366: bipush #32
    //   368: irem
    //   369: invokestatic abs : (I)I
    //   372: invokevirtual charAt : (I)C
    //   375: invokevirtual append : (C)Ljava/lang/StringBuilder;
    //   378: pop
    //   379: iload_2
    //   380: ifeq -> 1348
    //   383: goto -> 390
    //   386: invokestatic a : (Ljava/lang/Throwable;)Ljava/lang/Throwable;
    //   389: athrow
    //   390: aload_3
    //   391: getstatic burp/Zlnm.ZL : Ljava/lang/String;
    //   394: getstatic burp/Ztkh.Zh : Ljava/lang/Object;
    //   397: checkcast java/math/BigInteger
    //   400: invokevirtual intValue : ()I
    //   403: bipush #32
    //   405: irem
    //   406: invokestatic abs : (I)I
    //   409: invokevirtual charAt : (I)C
    //   412: invokevirtual append : (C)Ljava/lang/StringBuilder;
    //   415: pop
    //   416: iload_2
    //   417: ifeq -> 1348
    //   420: goto -> 427
    //   423: invokestatic a : (Ljava/lang/Throwable;)Ljava/lang/Throwable;
    //   426: athrow
    //   427: aload_3
    //   428: getstatic burp/Zlx5.ZP : Ljava/lang/String;
    //   431: getstatic burp/Zrva.ZE : Ljava/lang/Object;
    //   434: checkcast java/math/BigInteger
    //   437: invokevirtual intValue : ()I
    //   440: bipush #32
    //   442: irem
    //   443: invokestatic abs : (I)I
    //   446: invokevirtual charAt : (I)C
    //   449: invokevirtual append : (C)Ljava/lang/StringBuilder;
    //   452: pop
    //   453: iload_2
    //   454: ifeq -> 1348
    //   457: goto -> 464
    //   460: invokestatic a : (Ljava/lang/Throwable;)Ljava/lang/Throwable;
    //   463: athrow
    //   464: aload_3
    //   465: getstatic burp/Zel.Zi : Ljava/lang/String;
    //   468: getstatic burp/Zzyr.Za : Ljava/lang/Object;
    //   471: checkcast java/math/BigInteger
    //   474: invokevirtual intValue : ()I
    //   477: bipush #32
    //   479: irem
    //   480: invokestatic abs : (I)I
    //   483: invokevirtual charAt : (I)C
    //   486: invokevirtual append : (C)Ljava/lang/StringBuilder;
    //   489: pop
    //   490: iload_2
    //   491: ifeq -> 1348
    //   494: goto -> 501
    //   497: invokestatic a : (Ljava/lang/Throwable;)Ljava/lang/Throwable;
    //   500: athrow
    //   501: aload_3
    //   502: getstatic burp/Ztex.Zx : Ljava/lang/String;
    //   505: getstatic burp/Zr2i.ZD : Ljava/lang/Object;
    //   508: checkcast java/math/BigInteger
    //   511: invokevirtual intValue : ()I
    //   514: bipush #32
    //   516: irem
    //   517: invokestatic abs : (I)I
    //   520: invokevirtual charAt : (I)C
    //   523: invokevirtual append : (C)Ljava/lang/StringBuilder;
    //   526: pop
    //   527: iload_2
    //   528: ifeq -> 1348
    //   531: goto -> 538
    //   534: invokestatic a : (Ljava/lang/Throwable;)Ljava/lang/Throwable;
    //   537: athrow
    //   538: aload_3
    //   539: getstatic burp/Ztj5.Zt : Ljava/lang/String;
    //   542: getstatic burp/Zkll.Zl : Ljava/lang/Object;
    //   545: checkcast java/math/BigInteger
    //   548: invokevirtual intValue : ()I
    //   551: bipush #32
    //   553: irem
    //   554: invokestatic abs : (I)I
    //   557: invokevirtual charAt : (I)C
    //   560: invokevirtual append : (C)Ljava/lang/StringBuilder;
    //   563: pop
    //   564: iload_2
    //   565: ifeq -> 1348
    //   568: goto -> 575
    //   571: invokestatic a : (Ljava/lang/Throwable;)Ljava/lang/Throwable;
    //   574: athrow
    //   575: aload_3
    //   576: getstatic burp/Zt9_.Zf : Ljava/lang/String;
    //   579: getstatic burp/Zre5.Zo : Ljava/lang/Object;
    //   582: checkcast java/math/BigInteger
    //   585: invokevirtual intValue : ()I
    //   588: bipush #32
    //   590: irem
    //   591: invokestatic abs : (I)I
    //   594: invokevirtual charAt : (I)C
    //   597: invokevirtual append : (C)Ljava/lang/StringBuilder;
    //   600: pop
    //   601: iload_2
    //   602: ifeq -> 1348
    //   605: goto -> 612
    //   608: invokestatic a : (Ljava/lang/Throwable;)Ljava/lang/Throwable;
    //   611: athrow
    //   612: aload_3
    //   613: getstatic burp/Zmhi.ZQ : Ljava/lang/String;
    //   616: getstatic burp/Zlhq.Zw : Ljava/lang/Object;
    //   619: checkcast java/math/BigInteger
    //   622: invokevirtual intValue : ()I
    //   625: bipush #32
    //   627: irem
    //   628: invokestatic abs : (I)I
    //   631: invokevirtual charAt : (I)C
    //   634: invokevirtual append : (C)Ljava/lang/StringBuilder;
    //   637: pop
    //   638: iload_2
    //   639: ifeq -> 1348
    //   642: goto -> 649
    //   645: invokestatic a : (Ljava/lang/Throwable;)Ljava/lang/Throwable;
    //   648: athrow
    //   649: aload_3
    //   650: getstatic burp/Zgnp.ZL : Ljava/lang/String;
    //   653: getstatic burp/Zs0_.Zu : Ljava/lang/Object;
    //   656: checkcast java/math/BigInteger
    //   659: invokevirtual intValue : ()I
    //   662: bipush #32
    //   664: irem
    //   665: invokestatic abs : (I)I
    //   668: invokevirtual charAt : (I)C
    //   671: invokevirtual append : (C)Ljava/lang/StringBuilder;
    //   674: pop
    //   675: iload_2
    //   676: ifeq -> 1348
    //   679: goto -> 686
    //   682: invokestatic a : (Ljava/lang/Throwable;)Ljava/lang/Throwable;
    //   685: athrow
    //   686: aload_3
    //   687: getstatic burp/Zlhq.Zl : Ljava/lang/String;
    //   690: getstatic burp/Zmsn.Zk : Ljava/lang/Object;
    //   693: checkcast java/math/BigInteger
    //   696: invokevirtual intValue : ()I
    //   699: bipush #32
    //   701: irem
    //   702: invokestatic abs : (I)I
    //   705: invokevirtual charAt : (I)C
    //   708: invokevirtual append : (C)Ljava/lang/StringBuilder;
    //   711: pop
    //   712: iload_2
    //   713: ifeq -> 1348
    //   716: goto -> 723
    //   719: invokestatic a : (Ljava/lang/Throwable;)Ljava/lang/Throwable;
    //   722: athrow
    //   723: aload_3
    //   724: getstatic burp/Zkll.ZX : Ljava/lang/String;
    //   727: getstatic burp/Zefo.ZW : Ljava/lang/Object;
    //   730: checkcast java/math/BigInteger
    //   733: invokevirtual intValue : ()I
    //   736: bipush #32
    //   738: irem
    //   739: invokestatic abs : (I)I
    //   742: invokevirtual charAt : (I)C
    //   745: invokevirtual append : (C)Ljava/lang/StringBuilder;
    //   748: pop
    //   749: iload_2
    //   750: ifeq -> 1348
    //   753: goto -> 760
    //   756: invokestatic a : (Ljava/lang/Throwable;)Ljava/lang/Throwable;
    //   759: athrow
    //   760: aload_3
    //   761: getstatic burp/Zsxo.ZW : Ljava/lang/String;
    //   764: getstatic burp/Zlo5.Zf : Ljava/lang/Object;
    //   767: checkcast java/math/BigInteger
    //   770: invokevirtual intValue : ()I
    //   773: bipush #32
    //   775: irem
    //   776: invokestatic abs : (I)I
    //   779: invokevirtual charAt : (I)C
    //   782: invokevirtual append : (C)Ljava/lang/StringBuilder;
    //   785: pop
    //   786: iload_2
    //   787: ifeq -> 1348
    //   790: goto -> 797
    //   793: invokestatic a : (Ljava/lang/Throwable;)Ljava/lang/Throwable;
    //   796: athrow
    //   797: aload_3
    //   798: getstatic burp/Zm3p.ZE : Ljava/lang/String;
    //   801: getstatic burp/Zzox.Zq : Ljava/lang/Object;
    //   804: checkcast java/math/BigInteger
    //   807: invokevirtual intValue : ()I
    //   810: bipush #32
    //   812: irem
    //   813: invokestatic abs : (I)I
    //   816: invokevirtual charAt : (I)C
    //   819: invokevirtual append : (C)Ljava/lang/StringBuilder;
    //   822: pop
    //   823: iload_2
    //   824: ifeq -> 1348
    //   827: goto -> 834
    //   830: invokestatic a : (Ljava/lang/Throwable;)Ljava/lang/Throwable;
    //   833: athrow
    //   834: aload_3
    //   835: getstatic burp/Zeqg.Zh : Ljava/lang/String;
    //   838: getstatic burp/Zeb7.ZJ : Ljava/lang/Object;
    //   841: checkcast java/math/BigInteger
    //   844: invokevirtual intValue : ()I
    //   847: bipush #32
    //   849: irem
    //   850: invokestatic abs : (I)I
    //   853: invokevirtual charAt : (I)C
    //   856: invokevirtual append : (C)Ljava/lang/StringBuilder;
    //   859: pop
    //   860: iload_2
    //   861: ifeq -> 1348
    //   864: goto -> 871
    //   867: invokestatic a : (Ljava/lang/Throwable;)Ljava/lang/Throwable;
    //   870: athrow
    //   871: aload_3
    //   872: getstatic burp/Zgnp.ZL : Ljava/lang/String;
    //   875: getstatic burp/Zkm0.ZI : Ljava/lang/Object;
    //   878: checkcast java/math/BigInteger
    //   881: invokevirtual intValue : ()I
    //   884: bipush #32
    //   886: irem
    //   887: invokestatic abs : (I)I
    //   890: invokevirtual charAt : (I)C
    //   893: invokevirtual append : (C)Ljava/lang/StringBuilder;
    //   896: pop
    //   897: iload_2
    //   898: ifeq -> 1348
    //   901: goto -> 908
    //   904: invokestatic a : (Ljava/lang/Throwable;)Ljava/lang/Throwable;
    //   907: athrow
    //   908: aload_3
    //   909: getstatic burp/Zzc_.Zg : Ljava/lang/String;
    //   912: getstatic burp/Zzo5.Zf : Ljava/lang/Object;
    //   915: checkcast java/math/BigInteger
    //   918: invokevirtual intValue : ()I
    //   921: bipush #32
    //   923: irem
    //   924: invokestatic abs : (I)I
    //   927: invokevirtual charAt : (I)C
    //   930: invokevirtual append : (C)Ljava/lang/StringBuilder;
    //   933: pop
    //   934: iload_2
    //   935: ifeq -> 1348
    //   938: goto -> 945
    //   941: invokestatic a : (Ljava/lang/Throwable;)Ljava/lang/Throwable;
    //   944: athrow
    //   945: aload_3
    //   946: getstatic burp/Ze64.ZM : Ljava/lang/String;
    //   949: getstatic burp/Zmsn.Zk : Ljava/lang/Object;
    //   952: checkcast java/math/BigInteger
    //   955: invokevirtual intValue : ()I
    //   958: bipush #32
    //   960: irem
    //   961: invokestatic abs : (I)I
    //   964: invokevirtual charAt : (I)C
    //   967: invokevirtual append : (C)Ljava/lang/StringBuilder;
    //   970: pop
    //   971: iload_2
    //   972: ifeq -> 1348
    //   975: goto -> 982
    //   978: invokestatic a : (Ljava/lang/Throwable;)Ljava/lang/Throwable;
    //   981: athrow
    //   982: aload_3
    //   983: getstatic burp/Zztk.Zf : Ljava/lang/String;
    //   986: getstatic burp/Zt9_.ZN : Ljava/lang/Object;
    //   989: checkcast java/math/BigInteger
    //   992: invokevirtual intValue : ()I
    //   995: bipush #32
    //   997: irem
    //   998: invokestatic abs : (I)I
    //   1001: invokevirtual charAt : (I)C
    //   1004: invokevirtual append : (C)Ljava/lang/StringBuilder;
    //   1007: pop
    //   1008: iload_2
    //   1009: ifeq -> 1348
    //   1012: goto -> 1019
    //   1015: invokestatic a : (Ljava/lang/Throwable;)Ljava/lang/Throwable;
    //   1018: athrow
    //   1019: aload_3
    //   1020: getstatic burp/Ztfh.ZU : Ljava/lang/String;
    //   1023: getstatic burp/Zmyg.Zj : Ljava/lang/Object;
    //   1026: checkcast java/math/BigInteger
    //   1029: invokevirtual intValue : ()I
    //   1032: bipush #32
    //   1034: irem
    //   1035: invokestatic abs : (I)I
    //   1038: invokevirtual charAt : (I)C
    //   1041: invokevirtual append : (C)Ljava/lang/StringBuilder;
    //   1044: pop
    //   1045: iload_2
    //   1046: ifeq -> 1348
    //   1049: goto -> 1056
    //   1052: invokestatic a : (Ljava/lang/Throwable;)Ljava/lang/Throwable;
    //   1055: athrow
    //   1056: aload_3
    //   1057: getstatic burp/Zlh8.ZY : Ljava/lang/String;
    //   1060: getstatic burp/Zs83.ZT : Ljava/lang/Object;
    //   1063: checkcast java/math/BigInteger
    //   1066: invokevirtual intValue : ()I
    //   1069: bipush #32
    //   1071: irem
    //   1072: invokestatic abs : (I)I
    //   1075: invokevirtual charAt : (I)C
    //   1078: invokevirtual append : (C)Ljava/lang/StringBuilder;
    //   1081: pop
    //   1082: iload_2
    //   1083: ifeq -> 1348
    //   1086: goto -> 1093
    //   1089: invokestatic a : (Ljava/lang/Throwable;)Ljava/lang/Throwable;
    //   1092: athrow
    //   1093: aload_3
    //   1094: getstatic burp/Zs00.Zv : Ljava/lang/String;
    //   1097: getstatic burp/Zmj8.Zz : Ljava/lang/Object;
    //   1100: checkcast java/math/BigInteger
    //   1103: invokevirtual intValue : ()I
    //   1106: bipush #32
    //   1108: irem
    //   1109: invokestatic abs : (I)I
    //   1112: invokevirtual charAt : (I)C
    //   1115: invokevirtual append : (C)Ljava/lang/StringBuilder;
    //   1118: pop
    //   1119: iload_2
    //   1120: ifeq -> 1348
    //   1123: goto -> 1130
    //   1126: invokestatic a : (Ljava/lang/Throwable;)Ljava/lang/Throwable;
    //   1129: athrow
    //   1130: aload_3
    //   1131: getstatic burp/Zlo5.ZJ : Ljava/lang/String;
    //   1134: getstatic burp/Zlem.ZI : Ljava/lang/Object;
    //   1137: checkcast java/math/BigInteger
    //   1140: invokevirtual intValue : ()I
    //   1143: bipush #32
    //   1145: irem
    //   1146: invokestatic abs : (I)I
    //   1149: invokevirtual charAt : (I)C
    //   1152: invokevirtual append : (C)Ljava/lang/StringBuilder;
    //   1155: pop
    //   1156: iload_2
    //   1157: ifeq -> 1348
    //   1160: goto -> 1167
    //   1163: invokestatic a : (Ljava/lang/Throwable;)Ljava/lang/Throwable;
    //   1166: athrow
    //   1167: aload_3
    //   1168: getstatic burp/Zkm0.ZL : Ljava/lang/String;
    //   1171: getstatic burp/Zlem.ZI : Ljava/lang/Object;
    //   1174: checkcast java/math/BigInteger
    //   1177: invokevirtual intValue : ()I
    //   1180: bipush #32
    //   1182: irem
    //   1183: invokestatic abs : (I)I
    //   1186: invokevirtual charAt : (I)C
    //   1189: invokevirtual append : (C)Ljava/lang/StringBuilder;
    //   1192: pop
    //   1193: iload_2
    //   1194: ifeq -> 1348
    //   1197: goto -> 1204
    //   1200: invokestatic a : (Ljava/lang/Throwable;)Ljava/lang/Throwable;
    //   1203: athrow
    //   1204: aload_3
    //   1205: getstatic burp/Zk7e.ZP : Ljava/lang/String;
    //   1208: getstatic burp/Zlpj.Zc : Ljava/lang/Object;
    //   1211: checkcast java/math/BigInteger
    //   1214: invokevirtual intValue : ()I
    //   1217: bipush #32
    //   1219: irem
    //   1220: invokestatic abs : (I)I
    //   1223: invokevirtual charAt : (I)C
    //   1226: invokevirtual append : (C)Ljava/lang/StringBuilder;
    //   1229: pop
    //   1230: iload_2
    //   1231: ifeq -> 1348
    //   1234: goto -> 1241
    //   1237: invokestatic a : (Ljava/lang/Throwable;)Ljava/lang/Throwable;
    //   1240: athrow
    //   1241: aload_3
    //   1242: getstatic burp/Zsj5.Zn : Ljava/lang/String;
    //   1245: getstatic burp/Zlvb.ZN : Ljava/lang/Object;
    //   1248: checkcast java/math/BigInteger
    //   1251: invokevirtual intValue : ()I
    //   1254: bipush #32
    //   1256: irem
    //   1257: invokestatic abs : (I)I
    //   1260: invokevirtual charAt : (I)C
    //   1263: invokevirtual append : (C)Ljava/lang/StringBuilder;
    //   1266: pop
    //   1267: iload_2
    //   1268: ifeq -> 1348
    //   1271: goto -> 1278
    //   1274: invokestatic a : (Ljava/lang/Throwable;)Ljava/lang/Throwable;
    //   1277: athrow
    //   1278: aload_3
    //   1279: getstatic burp/Zs34.Zq : Ljava/lang/String;
    //   1282: getstatic burp/Ztdd.ZD : Ljava/lang/Object;
    //   1285: checkcast java/math/BigInteger
    //   1288: invokevirtual intValue : ()I
    //   1291: bipush #32
    //   1293: irem
    //   1294: invokestatic abs : (I)I
    //   1297: invokevirtual charAt : (I)C
    //   1300: invokevirtual append : (C)Ljava/lang/StringBuilder;
    //   1303: pop
    //   1304: iload_2
    //   1305: ifeq -> 1348
    //   1308: goto -> 1315
    //   1311: invokestatic a : (Ljava/lang/Throwable;)Ljava/lang/Throwable;
    //   1314: athrow
    //   1315: aload_3
    //   1316: getstatic burp/Zeoy.ZS : Ljava/lang/String;
    //   1319: getstatic burp/Zkll.Zl : Ljava/lang/Object;
    //   1322: checkcast java/math/BigInteger
    //   1325: invokevirtual intValue : ()I
    //   1328: bipush #32
    //   1330: irem
    //   1331: invokestatic abs : (I)I
    //   1334: invokevirtual charAt : (I)C
    //   1337: invokevirtual append : (C)Ljava/lang/StringBuilder;
    //   1340: pop
    //   1341: goto -> 1348
    //   1344: invokestatic a : (Ljava/lang/Throwable;)Ljava/lang/Throwable;
    //   1347: athrow
    //   1348: iinc #4, 1
    //   1351: iload_2
    //   1352: ifeq -> 15
    //   1355: aload_3
    //   1356: invokevirtual toString : ()Ljava/lang/String;
    //   1359: putstatic burp/Zvo3.Z_ : Ljava/lang/String;
    //   1362: getstatic burp/Zmsn.Zk : Ljava/lang/Object;
    //   1365: checkcast java/math/BigInteger
    //   1368: invokevirtual toByteArray : ()[B
    //   1371: astore #4
    //   1373: aload #4
    //   1375: arraylength
    //   1376: bipush #8
    //   1378: iadd
    //   1379: bipush #6
    //   1381: ishr
    //   1382: iconst_1
    //   1383: iadd
    //   1384: bipush #16
    //   1386: imul
    //   1387: newarray int
    //   1389: astore #6
    //   1391: iconst_0
    //   1392: istore #7
    //   1394: iload #7
    //   1396: aload #4
    //   1398: arraylength
    //   1399: if_icmpge -> 1443
    //   1402: aload #4
    //   1404: iload #7
    //   1406: baload
    //   1407: sipush #255
    //   1410: iand
    //   1411: istore #8
    //   1413: aload #6
    //   1415: iload #7
    //   1417: iconst_2
    //   1418: ishr
    //   1419: dup2
    //   1420: iaload
    //   1421: iload #8
    //   1423: bipush #24
    //   1425: iload #7
    //   1427: iconst_4
    //   1428: irem
    //   1429: bipush #8
    //   1431: imul
    //   1432: isub
    //   1433: ishl
    //   1434: ior
    //   1435: iastore
    //   1436: iinc #7, 1
    //   1439: iload_2
    //   1440: ifeq -> 1394
    //   1443: aload #6
    //   1445: iload #7
    //   1447: iconst_2
    //   1448: ishr
    //   1449: dup2
    //   1450: iaload
    //   1451: sipush #128
    //   1454: bipush #24
    //   1456: iload #7
    //   1458: iconst_4
    //   1459: irem
    //   1460: bipush #8
    //   1462: imul
    //   1463: isub
    //   1464: ishl
    //   1465: ior
    //   1466: iastore
    //   1467: aload #6
    //   1469: aload #6
    //   1471: arraylength
    //   1472: iconst_1
    //   1473: isub
    //   1474: aload #4
    //   1476: arraylength
    //   1477: bipush #8
    //   1479: imul
    //   1480: iastore
    //   1481: bipush #80
    //   1483: newarray int
    //   1485: astore #8
    //   1487: ldc 1732584193
    //   1489: istore #9
    //   1491: ldc -271733879
    //   1493: istore #10
    //   1495: ldc -1732584194
    //   1497: istore #11
    //   1499: ldc 271733878
    //   1501: istore #12
    //   1503: ldc -1009589776
    //   1505: istore #13
    //   1507: iconst_0
    //   1508: istore #7
    //   1510: iload #7
    //   1512: aload #6
    //   1514: arraylength
    //   1515: if_icmpge -> 1837
    //   1518: iload #9
    //   1520: istore #14
    //   1522: iload #10
    //   1524: istore #15
    //   1526: iload #11
    //   1528: istore #16
    //   1530: iload #12
    //   1532: istore #17
    //   1534: iload #13
    //   1536: istore #18
    //   1538: iconst_0
    //   1539: istore #19
    //   1541: iload #19
    //   1543: bipush #80
    //   1545: if_icmpge -> 1795
    //   1548: iload #19
    //   1550: bipush #16
    //   1552: if_icmpge -> 1579
    //   1555: aload #8
    //   1557: iload #19
    //   1559: aload #6
    //   1561: iload #7
    //   1563: iload #19
    //   1565: iadd
    //   1566: iaload
    //   1567: iastore
    //   1568: iload_2
    //   1569: ifeq -> 1634
    //   1572: goto -> 1579
    //   1575: invokestatic a : (Ljava/lang/Throwable;)Ljava/lang/Throwable;
    //   1578: athrow
    //   1579: aload #8
    //   1581: iload #19
    //   1583: iconst_3
    //   1584: isub
    //   1585: iaload
    //   1586: aload #8
    //   1588: iload #19
    //   1590: bipush #8
    //   1592: isub
    //   1593: iaload
    //   1594: ixor
    //   1595: aload #8
    //   1597: iload #19
    //   1599: bipush #14
    //   1601: isub
    //   1602: iaload
    //   1603: ixor
    //   1604: aload #8
    //   1606: iload #19
    //   1608: bipush #16
    //   1610: isub
    //   1611: iaload
    //   1612: ixor
    //   1613: istore #20
    //   1615: iload #20
    //   1617: iconst_1
    //   1618: ishl
    //   1619: iload #20
    //   1621: bipush #31
    //   1623: iushr
    //   1624: ior
    //   1625: istore #21
    //   1627: aload #8
    //   1629: iload #19
    //   1631: iload #21
    //   1633: iastore
    //   1634: iload #9
    //   1636: iconst_5
    //   1637: ishl
    //   1638: iload #9
    //   1640: bipush #27
    //   1642: iushr
    //   1643: ior
    //   1644: istore #20
    //   1646: iload #20
    //   1648: iload #13
    //   1650: iadd
    //   1651: aload #8
    //   1653: iload #19
    //   1655: iaload
    //   1656: iadd
    //   1657: iload #19
    //   1659: bipush #20
    //   1661: if_icmpge -> 1687
    //   1664: ldc 1518500249
    //   1666: iload #10
    //   1668: iload #11
    //   1670: iand
    //   1671: iload #10
    //   1673: iconst_m1
    //   1674: ixor
    //   1675: iload #12
    //   1677: iand
    //   1678: ior
    //   1679: iadd
    //   1680: goto -> 1757
    //   1683: invokestatic a : (Ljava/lang/Throwable;)Ljava/lang/Throwable;
    //   1686: athrow
    //   1687: iload #19
    //   1689: bipush #40
    //   1691: if_icmpge -> 1712
    //   1694: ldc 1859775393
    //   1696: iload #10
    //   1698: iload #11
    //   1700: ixor
    //   1701: iload #12
    //   1703: ixor
    //   1704: iadd
    //   1705: goto -> 1757
    //   1708: invokestatic a : (Ljava/lang/Throwable;)Ljava/lang/Throwable;
    //   1711: athrow
    //   1712: iload #19
    //   1714: bipush #60
    //   1716: if_icmpge -> 1746
    //   1719: ldc -1894007588
    //   1721: iload #10
    //   1723: iload #11
    //   1725: iand
    //   1726: iload #10
    //   1728: iload #12
    //   1730: iand
    //   1731: ior
    //   1732: iload #11
    //   1734: iload #12
    //   1736: iand
    //   1737: ior
    //   1738: iadd
    //   1739: goto -> 1757
    //   1742: invokestatic a : (Ljava/lang/Throwable;)Ljava/lang/Throwable;
    //   1745: athrow
    //   1746: ldc -899497514
    //   1748: iload #10
    //   1750: iload #11
    //   1752: ixor
    //   1753: iload #12
    //   1755: ixor
    //   1756: iadd
    //   1757: iadd
    //   1758: istore #21
    //   1760: iload #12
    //   1762: istore #13
    //   1764: iload #11
    //   1766: istore #12
    //   1768: iload #10
    //   1770: bipush #30
    //   1772: ishl
    //   1773: iload #10
    //   1775: iconst_2
    //   1776: iushr
    //   1777: ior
    //   1778: istore #11
    //   1780: iload #9
    //   1782: istore #10
    //   1784: iload #21
    //   1786: istore #9
    //   1788: iinc #19, 1
    //   1791: iload_2
    //   1792: ifeq -> 1541
    //   1795: iload #9
    //   1797: iload #14
    //   1799: iadd
    //   1800: istore #9
    //   1802: iload #10
    //   1804: iload #15
    //   1806: iadd
    //   1807: istore #10
    //   1809: iload #11
    //   1811: iload #16
    //   1813: iadd
    //   1814: istore #11
    //   1816: iload #12
    //   1818: iload #17
    //   1820: iadd
    //   1821: istore #12
    //   1823: iload #13
    //   1825: iload #18
    //   1827: iadd
    //   1828: istore #13
    //   1830: iinc #7, 16
    //   1833: iload_2
    //   1834: ifeq -> 1510
    //   1837: iconst_5
    //   1838: newarray int
    //   1840: dup
    //   1841: iconst_0
    //   1842: iload #9
    //   1844: iastore
    //   1845: dup
    //   1846: iconst_1
    //   1847: iload #10
    //   1849: iastore
    //   1850: dup
    //   1851: iconst_2
    //   1852: iload #11
    //   1854: iastore
    //   1855: dup
    //   1856: iconst_3
    //   1857: iload #12
    //   1859: iastore
    //   1860: dup
    //   1861: iconst_4
    //   1862: iload #13
    //   1864: iastore
    //   1865: astore #14
    //   1867: bipush #20
    //   1869: newarray byte
    //   1871: astore #15
    //   1873: iconst_0
    //   1874: istore #16
    //   1876: iload #16
    //   1878: bipush #20
    //   1880: if_icmpge -> 1921
    //   1883: aload #14
    //   1885: iload #16
    //   1887: iconst_4
    //   1888: idiv
    //   1889: iaload
    //   1890: istore #17
    //   1892: iconst_3
    //   1893: iload #16
    //   1895: iconst_4
    //   1896: irem
    //   1897: isub
    //   1898: bipush #8
    //   1900: imul
    //   1901: istore #18
    //   1903: aload #15
    //   1905: iload #16
    //   1907: iload #17
    //   1909: iload #18
    //   1911: iushr
    //   1912: i2b
    //   1913: bastore
    //   1914: iinc #16, 1
    //   1917: iload_2
    //   1918: ifeq -> 1876
    //   1921: aload #15
    //   1923: astore #5
    //   1925: new java/math/BigInteger
    //   1928: dup
    //   1929: aload #5
    //   1931: invokespecial <init> : ([B)V
    //   1934: invokevirtual abs : ()Ljava/math/BigInteger;
    //   1937: putstatic burp/Zs0_.Zu : Ljava/lang/Object;
    //   1940: getstatic burp/Zkm0.ZI : Ljava/lang/Object;
    //   1943: checkcast java/math/BigInteger
    //   1946: invokevirtual toByteArray : ()[B
    //   1949: astore #4
    //   1951: new java/lang/StringBuilder
    //   1954: dup
    //   1955: invokespecial <init> : ()V
    //   1958: astore #6
    //   1960: aload #6
    //   1962: sipush #-5088
    //   1965: sipush #12641
    //   1968: invokestatic a : (II)Ljava/lang/String;
    //   1971: invokevirtual append : (Ljava/lang/String;)Ljava/lang/StringBuilder;
    //   1974: pop
    //   1975: aload #4
    //   1977: astore #7
    //   1979: aload #7
    //   1981: arraylength
    //   1982: istore #8
    //   1984: iconst_0
    //   1985: istore #9
    //   1987: iload #9
    //   1989: iload #8
    //   1991: if_icmpge -> 2017
    //   1994: aload #7
    //   1996: iload #9
    //   1998: baload
    //   1999: istore #10
    //   2001: aload #6
    //   2003: iload #10
    //   2005: i2c
    //   2006: invokevirtual append : (C)Ljava/lang/StringBuilder;
    //   2009: pop
    //   2010: iinc #9, 1
    //   2013: iload_2
    //   2014: ifeq -> 1987
    //   2017: aload #6
    //   2019: sipush #-5082
    //   2022: sipush #-19468
    //   2025: invokestatic a : (II)Ljava/lang/String;
    //   2028: ldc ''
    //   2030: invokestatic getProperty : (Ljava/lang/String;Ljava/lang/String;)Ljava/lang/String;
    //   2033: invokevirtual toLowerCase : ()Ljava/lang/String;
    //   2036: invokevirtual append : (Ljava/lang/String;)Ljava/lang/StringBuilder;
    //   2039: pop
    //   2040: aload #6
    //   2042: sipush #-5074
    //   2045: sipush #-31796
    //   2048: invokestatic a : (II)Ljava/lang/String;
    //   2051: ldc ''
    //   2053: invokestatic getProperty : (Ljava/lang/String;Ljava/lang/String;)Ljava/lang/String;
    //   2056: invokevirtual toLowerCase : ()Ljava/lang/String;
    //   2059: invokevirtual append : (Ljava/lang/String;)Ljava/lang/StringBuilder;
    //   2062: pop
    //   2063: aload #6
    //   2065: invokevirtual toString : ()Ljava/lang/String;
    //   2068: invokevirtual getBytes : ()[B
    //   2071: astore #5
    //   2073: aload #5
    //   2075: astore #4
    //   2077: aload #4
    //   2079: arraylength
    //   2080: bipush #8
    //   2082: iadd
    //   2083: bipush #6
    //   2085: ishr
    //   2086: iconst_1
    //   2087: iadd
    //   2088: bipush #16
    //   2090: imul
    //   2091: newarray int
    //   2093: astore #6
    //   2095: iconst_0
    //   2096: istore #7
    //   2098: iload #7
    //   2100: aload #4
    //   2102: arraylength
    //   2103: if_icmpge -> 2147
    //   2106: aload #4
    //   2108: iload #7
    //   2110: baload
    //   2111: sipush #255
    //   2114: iand
    //   2115: istore #8
    //   2117: aload #6
    //   2119: iload #7
    //   2121: iconst_2
    //   2122: ishr
    //   2123: dup2
    //   2124: iaload
    //   2125: iload #8
    //   2127: bipush #24
    //   2129: iload #7
    //   2131: iconst_4
    //   2132: irem
    //   2133: bipush #8
    //   2135: imul
    //   2136: isub
    //   2137: ishl
    //   2138: ior
    //   2139: iastore
    //   2140: iinc #7, 1
    //   2143: iload_2
    //   2144: ifeq -> 2098
    //   2147: aload #6
    //   2149: iload #7
    //   2151: iconst_2
    //   2152: ishr
    //   2153: dup2
    //   2154: iaload
    //   2155: sipush #128
    //   2158: bipush #24
    //   2160: iload #7
    //   2162: iconst_4
    //   2163: irem
    //   2164: bipush #8
    //   2166: imul
    //   2167: isub
    //   2168: ishl
    //   2169: ior
    //   2170: iastore
    //   2171: aload #6
    //   2173: aload #6
    //   2175: arraylength
    //   2176: iconst_1
    //   2177: isub
    //   2178: aload #4
    //   2180: arraylength
    //   2181: bipush #8
    //   2183: imul
    //   2184: iastore
    //   2185: bipush #80
    //   2187: newarray int
    //   2189: astore #8
    //   2191: ldc 1732584193
    //   2193: istore #9
    //   2195: ldc -271733879
    //   2197: istore #10
    //   2199: ldc -1732584194
    //   2201: istore #11
    //   2203: ldc 271733878
    //   2205: istore #12
    //   2207: ldc -1009589776
    //   2209: istore #13
    //   2211: iconst_0
    //   2212: istore #7
    //   2214: iload #7
    //   2216: aload #6
    //   2218: arraylength
    //   2219: if_icmpge -> 2541
    //   2222: iload #9
    //   2224: istore #14
    //   2226: iload #10
    //   2228: istore #15
    //   2230: iload #11
    //   2232: istore #16
    //   2234: iload #12
    //   2236: istore #17
    //   2238: iload #13
    //   2240: istore #18
    //   2242: iconst_0
    //   2243: istore #19
    //   2245: iload #19
    //   2247: bipush #80
    //   2249: if_icmpge -> 2499
    //   2252: iload #19
    //   2254: bipush #16
    //   2256: if_icmpge -> 2283
    //   2259: aload #8
    //   2261: iload #19
    //   2263: aload #6
    //   2265: iload #7
    //   2267: iload #19
    //   2269: iadd
    //   2270: iaload
    //   2271: iastore
    //   2272: iload_2
    //   2273: ifeq -> 2338
    //   2276: goto -> 2283
    //   2279: invokestatic a : (Ljava/lang/Throwable;)Ljava/lang/Throwable;
    //   2282: athrow
    //   2283: aload #8
    //   2285: iload #19
    //   2287: iconst_3
    //   2288: isub
    //   2289: iaload
    //   2290: aload #8
    //   2292: iload #19
    //   2294: bipush #8
    //   2296: isub
    //   2297: iaload
    //   2298: ixor
    //   2299: aload #8
    //   2301: iload #19
    //   2303: bipush #14
    //   2305: isub
    //   2306: iaload
    //   2307: ixor
    //   2308: aload #8
    //   2310: iload #19
    //   2312: bipush #16
    //   2314: isub
    //   2315: iaload
    //   2316: ixor
    //   2317: istore #20
    //   2319: iload #20
    //   2321: iconst_1
    //   2322: ishl
    //   2323: iload #20
    //   2325: bipush #31
    //   2327: iushr
    //   2328: ior
    //   2329: istore #21
    //   2331: aload #8
    //   2333: iload #19
    //   2335: iload #21
    //   2337: iastore
    //   2338: iload #9
    //   2340: iconst_5
    //   2341: ishl
    //   2342: iload #9
    //   2344: bipush #27
    //   2346: iushr
    //   2347: ior
    //   2348: istore #20
    //   2350: iload #20
    //   2352: iload #13
    //   2354: iadd
    //   2355: aload #8
    //   2357: iload #19
    //   2359: iaload
    //   2360: iadd
    //   2361: iload #19
    //   2363: bipush #20
    //   2365: if_icmpge -> 2391
    //   2368: ldc 1518500249
    //   2370: iload #10
    //   2372: iload #11
    //   2374: iand
    //   2375: iload #10
    //   2377: iconst_m1
    //   2378: ixor
    //   2379: iload #12
    //   2381: iand
    //   2382: ior
    //   2383: iadd
    //   2384: goto -> 2461
    //   2387: invokestatic a : (Ljava/lang/Throwable;)Ljava/lang/Throwable;
    //   2390: athrow
    //   2391: iload #19
    //   2393: bipush #40
    //   2395: if_icmpge -> 2416
    //   2398: ldc 1859775393
    //   2400: iload #10
    //   2402: iload #11
    //   2404: ixor
    //   2405: iload #12
    //   2407: ixor
    //   2408: iadd
    //   2409: goto -> 2461
    //   2412: invokestatic a : (Ljava/lang/Throwable;)Ljava/lang/Throwable;
    //   2415: athrow
    //   2416: iload #19
    //   2418: bipush #60
    //   2420: if_icmpge -> 2450
    //   2423: ldc -1894007588
    //   2425: iload #10
    //   2427: iload #11
    //   2429: iand
    //   2430: iload #10
    //   2432: iload #12
    //   2434: iand
    //   2435: ior
    //   2436: iload #11
    //   2438: iload #12
    //   2440: iand
    //   2441: ior
    //   2442: iadd
    //   2443: goto -> 2461
    //   2446: invokestatic a : (Ljava/lang/Throwable;)Ljava/lang/Throwable;
    //   2449: athrow
    //   2450: ldc -899497514
    //   2452: iload #10
    //   2454: iload #11
    //   2456: ixor
    //   2457: iload #12
    //   2459: ixor
    //   2460: iadd
    //   2461: iadd
    //   2462: istore #21
    //   2464: iload #12
    //   2466: istore #13
    //   2468: iload #11
    //   2470: istore #12
    //   2472: iload #10
    //   2474: bipush #30
    //   2476: ishl
    //   2477: iload #10
    //   2479: iconst_2
    //   2480: iushr
    //   2481: ior
    //   2482: istore #11
    //   2484: iload #9
    //   2486: istore #10
    //   2488: iload #21
    //   2490: istore #9
    //   2492: iinc #19, 1
    //   2495: iload_2
    //   2496: ifeq -> 2245
    //   2499: iload #9
    //   2501: iload #14
    //   2503: iadd
    //   2504: istore #9
    //   2506: iload #10
    //   2508: iload #15
    //   2510: iadd
    //   2511: istore #10
    //   2513: iload #11
    //   2515: iload #16
    //   2517: iadd
    //   2518: istore #11
    //   2520: iload #12
    //   2522: iload #17
    //   2524: iadd
    //   2525: istore #12
    //   2527: iload #13
    //   2529: iload #18
    //   2531: iadd
    //   2532: istore #13
    //   2534: iinc #7, 16
    //   2537: iload_2
    //   2538: ifeq -> 2214
    //   2541: iconst_5
    //   2542: newarray int
    //   2544: dup
    //   2545: iconst_0
    //   2546: iload #9
    //   2548: iastore
    //   2549: dup
    //   2550: iconst_1
    //   2551: iload #10
    //   2553: iastore
    //   2554: dup
    //   2555: iconst_2
    //   2556: iload #11
    //   2558: iastore
    //   2559: dup
    //   2560: iconst_3
    //   2561: iload #12
    //   2563: iastore
    //   2564: dup
    //   2565: iconst_4
    //   2566: iload #13
    //   2568: iastore
    //   2569: astore #14
    //   2571: bipush #20
    //   2573: newarray byte
    //   2575: astore #15
    //   2577: iconst_0
    //   2578: istore #16
    //   2580: iload #16
    //   2582: bipush #20
    //   2584: if_icmpge -> 2625
    //   2587: aload #14
    //   2589: iload #16
    //   2591: iconst_4
    //   2592: idiv
    //   2593: iaload
    //   2594: istore #17
    //   2596: iconst_3
    //   2597: iload #16
    //   2599: iconst_4
    //   2600: irem
    //   2601: isub
    //   2602: bipush #8
    //   2604: imul
    //   2605: istore #18
    //   2607: aload #15
    //   2609: iload #16
    //   2611: iload #17
    //   2613: iload #18
    //   2615: iushr
    //   2616: i2b
    //   2617: bastore
    //   2618: iinc #16, 1
    //   2621: iload_2
    //   2622: ifeq -> 2580
    //   2625: aload #15
    //   2627: astore #5
    //   2629: sipush #-5073
    //   2632: sipush #25894
    //   2635: invokestatic a : (II)Ljava/lang/String;
    //   2638: iconst_1
    //   2639: ldc burp/Zmh0
    //   2641: invokevirtual getClassLoader : ()Ljava/lang/ClassLoader;
    //   2644: invokestatic forName : (Ljava/lang/String;ZLjava/lang/ClassLoader;)Ljava/lang/Class;
    //   2647: invokevirtual getDeclaredFields : ()[Ljava/lang/reflect/Field;
    //   2650: astore #4
    //   2652: aload #4
    //   2654: arraylength
    //   2655: istore #5
    //   2657: iconst_0
    //   2658: istore #6
    //   2660: iload #6
    //   2662: iload #5
    //   2664: if_icmpge -> 2802
    //   2667: aload #4
    //   2669: iload #6
    //   2671: aaload
    //   2672: astore #7
    //   2674: aload #7
    //   2676: invokevirtual getModifiers : ()I
    //   2679: invokestatic isStatic : (I)Z
    //   2682: ifne -> 2692
    //   2685: goto -> 2795
    //   2688: invokestatic a : (Ljava/lang/Throwable;)Ljava/lang/Throwable;
    //   2691: athrow
    //   2692: aload #7
    //   2694: invokevirtual getType : ()Ljava/lang/Class;
    //   2697: astore #8
    //   2699: aload #8
    //   2701: ifnull -> 2782
    //   2704: aload #8
    //   2706: invokevirtual isPrimitive : ()Z
    //   2709: ifne -> 2782
    //   2712: goto -> 2719
    //   2715: invokestatic a : (Ljava/lang/Throwable;)Ljava/lang/Throwable;
    //   2718: athrow
    //   2719: aload #8
    //   2721: invokevirtual getPackage : ()Ljava/lang/Package;
    //   2724: ifnull -> 2782
    //   2727: goto -> 2734
    //   2730: invokestatic a : (Ljava/lang/Throwable;)Ljava/lang/Throwable;
    //   2733: athrow
    //   2734: aload #8
    //   2736: invokevirtual getPackage : ()Ljava/lang/Package;
    //   2739: invokevirtual getName : ()Ljava/lang/String;
    //   2742: ifnull -> 2782
    //   2745: goto -> 2752
    //   2748: invokestatic a : (Ljava/lang/Throwable;)Ljava/lang/Throwable;
    //   2751: athrow
    //   2752: aload #8
    //   2754: invokevirtual getPackage : ()Ljava/lang/Package;
    //   2757: invokevirtual getName : ()Ljava/lang/String;
    //   2760: sipush #-5086
    //   2763: sipush #28502
    //   2766: invokestatic a : (II)Ljava/lang/String;
    //   2769: invokevirtual startsWith : (Ljava/lang/String;)Z
    //   2772: ifne -> 2782
    //   2775: goto -> 2782
    //   2778: invokestatic a : (Ljava/lang/Throwable;)Ljava/lang/Throwable;
    //   2781: athrow
    //   2782: aload #7
    //   2784: iconst_1
    //   2785: invokevirtual setAccessible : (Z)V
    //   2788: aload #7
    //   2790: aconst_null
    //   2791: invokevirtual get : (Ljava/lang/Object;)Ljava/lang/Object;
    //   2794: pop
    //   2795: iinc #6, 1
    //   2798: iload_2
    //   2799: ifeq -> 2660
    //   2802: sipush #-5076
    //   2805: sipush #5821
    //   2808: invokestatic a : (II)Ljava/lang/String;
    //   2811: invokestatic forName : (Ljava/lang/String;)Ljava/lang/Class;
    //   2814: invokevirtual getDeclaredMethods : ()[Ljava/lang/reflect/Method;
    //   2817: astore #4
    //   2819: aload #4
    //   2821: arraylength
    //   2822: istore #5
    //   2824: iconst_0
    //   2825: istore #6
    //   2827: iload #6
    //   2829: iload #5
    //   2831: if_icmpge -> 2964
    //   2834: aload #4
    //   2836: iload #6
    //   2838: aaload
    //   2839: astore #7
    //   2841: aload #7
    //   2843: invokevirtual getParameterTypes : ()[Ljava/lang/Class;
    //   2846: pop
    //   2847: aload #7
    //   2849: invokevirtual getModifiers : ()I
    //   2852: invokestatic isStatic : (I)Z
    //   2855: ifeq -> 2950
    //   2858: aload #7
    //   2860: invokevirtual getParameterTypes : ()[Ljava/lang/Class;
    //   2863: arraylength
    //   2864: iconst_2
    //   2865: if_icmpne -> 2950
    //   2868: goto -> 2875
    //   2871: invokestatic a : (Ljava/lang/Throwable;)Ljava/lang/Throwable;
    //   2874: athrow
    //   2875: aload #7
    //   2877: invokevirtual getReturnType : ()Ljava/lang/Class;
    //   2880: getstatic java/lang/Void.TYPE : Ljava/lang/Class;
    //   2883: invokevirtual equals : (Ljava/lang/Object;)Z
    //   2886: ifeq -> 2950
    //   2889: goto -> 2896
    //   2892: invokestatic a : (Ljava/lang/Throwable;)Ljava/lang/Throwable;
    //   2895: athrow
    //   2896: aload #7
    //   2898: iconst_1
    //   2899: invokevirtual setAccessible : (Z)V
    //   2902: aload #7
    //   2904: aconst_null
    //   2905: iconst_2
    //   2906: anewarray java/lang/Object
    //   2909: dup
    //   2910: iconst_0
    //   2911: aload_0
    //   2912: aastore
    //   2913: dup
    //   2914: iconst_1
    //   2915: aload_1
    //   2916: ifnonnull -> 2934
    //   2919: goto -> 2926
    //   2922: invokestatic a : (Ljava/lang/Throwable;)Ljava/lang/Throwable;
    //   2925: athrow
    //   2926: aload_1
    //   2927: goto -> 2941
    //   2930: invokestatic a : (Ljava/lang/Throwable;)Ljava/lang/Throwable;
    //   2933: athrow
    //   2934: aload_1
    //   2935: checkcast [B
    //   2938: invokevirtual clone : ()Ljava/lang/Object;
    //   2941: aastore
    //   2942: invokevirtual invoke : (Ljava/lang/Object;[Ljava/lang/Object;)Ljava/lang/Object;
    //   2945: pop
    //   2946: iload_2
    //   2947: ifeq -> 2964
    //   2950: iinc #6, 1
    //   2953: iload_2
    //   2954: ifeq -> 2827
    //   2957: goto -> 2964
    //   2960: invokestatic a : (Ljava/lang/Throwable;)Ljava/lang/Throwable;
    //   2963: athrow
    //   2964: getstatic burp/Zlnm.Zn : Ljava/lang/Object;
    //   2967: checkcast java/math/BigInteger
    //   2970: invokevirtual toByteArray : ()[B
    //   2973: astore #4
    //   2975: bipush #32
    //   2977: newarray int
    //   2979: dup
    //   2980: iconst_0
    //   2981: ldc 876216579
    //   2983: iastore
    //   2984: dup
    //   2985: iconst_1
    //   2986: ldc 455999525
    //   2988: iastore
    //   2989: dup
    //   2990: iconst_2
    //   2991: ldc 1043334948
    //   2993: iastore
    //   2994: dup
    //   2995: iconst_3
    //   2996: ldc 439222784
    //   2998: iastore
    //   2999: dup
    //   3000: iconst_4
    //   3001: ldc 372376604
    //   3003: iastore
    //   3004: dup
    //   3005: iconst_5
    //   3006: ldc 707731490
    //   3008: iastore
    //   3009: dup
    //   3010: bipush #6
    //   3012: ldc 389426184
    //   3014: iastore
    //   3015: dup
    //   3016: bipush #7
    //   3018: ldc 973875457
    //   3020: iastore
    //   3021: dup
    //   3022: bipush #8
    //   3024: ldc 389160971
    //   3026: iastore
    //   3027: dup
    //   3028: bipush #9
    //   3030: ldc 907870729
    //   3032: iastore
    //   3033: dup
    //   3034: bipush #10
    //   3036: ldc 121057538
    //   3038: iastore
    //   3039: dup
    //   3040: bipush #11
    //   3042: ldc 840500228
    //   3044: iastore
    //   3045: dup
    //   3046: bipush #12
    //   3048: ldc 254150144
    //   3050: iastore
    //   3051: dup
    //   3052: bipush #13
    //   3054: ldc 924386310
    //   3056: iastore
    //   3057: dup
    //   3058: bipush #14
    //   3060: ldc 187632156
    //   3062: iastore
    //   3063: dup
    //   3064: bipush #15
    //   3066: ldc 874189824
    //   3068: iastore
    //   3069: dup
    //   3070: bipush #16
    //   3072: ldc 655302664
    //   3074: iastore
    //   3075: dup
    //   3076: bipush #17
    //   3078: ldc 890966315
    //   3080: iastore
    //   3081: dup
    //   3082: bipush #18
    //   3084: ldc 722417666
    //   3086: iastore
    //   3087: dup
    //   3088: bipush #19
    //   3090: ldc 1026621720
    //   3092: iastore
    //   3093: dup
    //   3094: bipush #20
    //   3096: ldc 957157408
    //   3098: iastore
    //   3099: dup
    //   3100: bipush #21
    //   3102: ldc 892536332
    //   3104: iastore
    //   3105: dup
    //   3106: bipush #22
    //   3108: ldc 689771012
    //   3110: iastore
    //   3111: dup
    //   3112: bipush #23
    //   3114: ldc 221709344
    //   3116: iastore
    //   3117: dup
    //   3118: bipush #24
    //   3120: ldc 940377620
    //   3122: iastore
    //   3123: dup
    //   3124: bipush #25
    //   3126: ldc 255209728
    //   3128: iastore
    //   3129: dup
    //   3130: bipush #26
    //   3132: ldc 1010368540
    //   3134: iastore
    //   3135: dup
    //   3136: bipush #27
    //   3138: ldc 220604441
    //   3140: iastore
    //   3141: dup
    //   3142: bipush #28
    //   3144: ldc 1008414755
    //   3146: iastore
    //   3147: dup
    //   3148: bipush #29
    //   3150: ldc 187049985
    //   3152: iastore
    //   3153: dup
    //   3154: bipush #30
    //   3156: ldc 943331329
    //   3158: iastore
    //   3159: dup
    //   3160: bipush #31
    //   3162: ldc 170788368
    //   3164: iastore
    //   3165: astore #6
    //   3167: bipush #64
    //   3169: newarray int
    //   3171: dup
    //   3172: iconst_0
    //   3173: ldc 16843776
    //   3175: iastore
    //   3176: dup
    //   3177: iconst_1
    //   3178: iconst_0
    //   3179: iastore
    //   3180: dup
    //   3181: iconst_2
    //   3182: ldc 65536
    //   3184: iastore
    //   3185: dup
    //   3186: iconst_3
    //   3187: ldc 16843780
    //   3189: iastore
    //   3190: dup
    //   3191: iconst_4
    //   3192: ldc 16842756
    //   3194: iastore
    //   3195: dup
    //   3196: iconst_5
    //   3197: ldc 66564
    //   3199: iastore
    //   3200: dup
    //   3201: bipush #6
    //   3203: iconst_4
    //   3204: iastore
    //   3205: dup
    //   3206: bipush #7
    //   3208: ldc 65536
    //   3210: iastore
    //   3211: dup
    //   3212: bipush #8
    //   3214: sipush #1024
    //   3217: iastore
    //   3218: dup
    //   3219: bipush #9
    //   3221: ldc 16843776
    //   3223: iastore
    //   3224: dup
    //   3225: bipush #10
    //   3227: ldc 16843780
    //   3229: iastore
    //   3230: dup
    //   3231: bipush #11
    //   3233: sipush #1024
    //   3236: iastore
    //   3237: dup
    //   3238: bipush #12
    //   3240: ldc 16778244
    //   3242: iastore
    //   3243: dup
    //   3244: bipush #13
    //   3246: ldc 16842756
    //   3248: iastore
    //   3249: dup
    //   3250: bipush #14
    //   3252: ldc 16777216
    //   3254: iastore
    //   3255: dup
    //   3256: bipush #15
    //   3258: iconst_4
    //   3259: iastore
    //   3260: dup
    //   3261: bipush #16
    //   3263: sipush #1028
    //   3266: iastore
    //   3267: dup
    //   3268: bipush #17
    //   3270: ldc 16778240
    //   3272: iastore
    //   3273: dup
    //   3274: bipush #18
    //   3276: ldc 16778240
    //   3278: iastore
    //   3279: dup
    //   3280: bipush #19
    //   3282: ldc 66560
    //   3284: iastore
    //   3285: dup
    //   3286: bipush #20
    //   3288: ldc 66560
    //   3290: iastore
    //   3291: dup
    //   3292: bipush #21
    //   3294: ldc 16842752
    //   3296: iastore
    //   3297: dup
    //   3298: bipush #22
    //   3300: ldc 16842752
    //   3302: iastore
    //   3303: dup
    //   3304: bipush #23
    //   3306: ldc 16778244
    //   3308: iastore
    //   3309: dup
    //   3310: bipush #24
    //   3312: ldc 65540
    //   3314: iastore
    //   3315: dup
    //   3316: bipush #25
    //   3318: ldc 16777220
    //   3320: iastore
    //   3321: dup
    //   3322: bipush #26
    //   3324: ldc 16777220
    //   3326: iastore
    //   3327: dup
    //   3328: bipush #27
    //   3330: ldc 65540
    //   3332: iastore
    //   3333: dup
    //   3334: bipush #28
    //   3336: iconst_0
    //   3337: iastore
    //   3338: dup
    //   3339: bipush #29
    //   3341: sipush #1028
    //   3344: iastore
    //   3345: dup
    //   3346: bipush #30
    //   3348: ldc 66564
    //   3350: iastore
    //   3351: dup
    //   3352: bipush #31
    //   3354: ldc 16777216
    //   3356: iastore
    //   3357: dup
    //   3358: bipush #32
    //   3360: ldc 65536
    //   3362: iastore
    //   3363: dup
    //   3364: bipush #33
    //   3366: ldc 16843780
    //   3368: iastore
    //   3369: dup
    //   3370: bipush #34
    //   3372: iconst_4
    //   3373: iastore
    //   3374: dup
    //   3375: bipush #35
    //   3377: ldc 16842752
    //   3379: iastore
    //   3380: dup
    //   3381: bipush #36
    //   3383: ldc 16843776
    //   3385: iastore
    //   3386: dup
    //   3387: bipush #37
    //   3389: ldc 16777216
    //   3391: iastore
    //   3392: dup
    //   3393: bipush #38
    //   3395: ldc 16777216
    //   3397: iastore
    //   3398: dup
    //   3399: bipush #39
    //   3401: sipush #1024
    //   3404: iastore
    //   3405: dup
    //   3406: bipush #40
    //   3408: ldc 16842756
    //   3410: iastore
    //   3411: dup
    //   3412: bipush #41
    //   3414: ldc 65536
    //   3416: iastore
    //   3417: dup
    //   3418: bipush #42
    //   3420: ldc 66560
    //   3422: iastore
    //   3423: dup
    //   3424: bipush #43
    //   3426: ldc 16777220
    //   3428: iastore
    //   3429: dup
    //   3430: bipush #44
    //   3432: sipush #1024
    //   3435: iastore
    //   3436: dup
    //   3437: bipush #45
    //   3439: iconst_4
    //   3440: iastore
    //   3441: dup
    //   3442: bipush #46
    //   3444: ldc 16778244
    //   3446: iastore
    //   3447: dup
    //   3448: bipush #47
    //   3450: ldc 66564
    //   3452: iastore
    //   3453: dup
    //   3454: bipush #48
    //   3456: ldc 16843780
    //   3458: iastore
    //   3459: dup
    //   3460: bipush #49
    //   3462: ldc 65540
    //   3464: iastore
    //   3465: dup
    //   3466: bipush #50
    //   3468: ldc 16842752
    //   3470: iastore
    //   3471: dup
    //   3472: bipush #51
    //   3474: ldc 16778244
    //   3476: iastore
    //   3477: dup
    //   3478: bipush #52
    //   3480: ldc 16777220
    //   3482: iastore
    //   3483: dup
    //   3484: bipush #53
    //   3486: sipush #1028
    //   3489: iastore
    //   3490: dup
    //   3491: bipush #54
    //   3493: ldc 66564
    //   3495: iastore
    //   3496: dup
    //   3497: bipush #55
    //   3499: ldc 16843776
    //   3501: iastore
    //   3502: dup
    //   3503: bipush #56
    //   3505: sipush #1028
    //   3508: iastore
    //   3509: dup
    //   3510: bipush #57
    //   3512: ldc 16778240
    //   3514: iastore
    //   3515: dup
    //   3516: bipush #58
    //   3518: ldc 16778240
    //   3520: iastore
    //   3521: dup
    //   3522: bipush #59
    //   3524: iconst_0
    //   3525: iastore
    //   3526: dup
    //   3527: bipush #60
    //   3529: ldc 65540
    //   3531: iastore
    //   3532: dup
    //   3533: bipush #61
    //   3535: ldc 66560
    //   3537: iastore
    //   3538: dup
    //   3539: bipush #62
    //   3541: iconst_0
    //   3542: iastore
    //   3543: dup
    //   3544: bipush #63
    //   3546: ldc 16842756
    //   3548: iastore
    //   3549: astore #7
    //   3551: bipush #64
    //   3553: newarray int
    //   3555: dup
    //   3556: iconst_0
    //   3557: ldc -2146402272
    //   3559: iastore
    //   3560: dup
    //   3561: iconst_1
    //   3562: ldc -2147450880
    //   3564: iastore
    //   3565: dup
    //   3566: iconst_2
    //   3567: ldc 32768
    //   3569: iastore
    //   3570: dup
    //   3571: iconst_3
    //   3572: ldc 1081376
    //   3574: iastore
    //   3575: dup
    //   3576: iconst_4
    //   3577: ldc 1048576
    //   3579: iastore
    //   3580: dup
    //   3581: iconst_5
    //   3582: bipush #32
    //   3584: iastore
    //   3585: dup
    //   3586: bipush #6
    //   3588: ldc -2146435040
    //   3590: iastore
    //   3591: dup
    //   3592: bipush #7
    //   3594: ldc -2147450848
    //   3596: iastore
    //   3597: dup
    //   3598: bipush #8
    //   3600: ldc -2147483616
    //   3602: iastore
    //   3603: dup
    //   3604: bipush #9
    //   3606: ldc -2146402272
    //   3608: iastore
    //   3609: dup
    //   3610: bipush #10
    //   3612: ldc -2146402304
    //   3614: iastore
    //   3615: dup
    //   3616: bipush #11
    //   3618: ldc -2147483648
    //   3620: iastore
    //   3621: dup
    //   3622: bipush #12
    //   3624: ldc -2147450880
    //   3626: iastore
    //   3627: dup
    //   3628: bipush #13
    //   3630: ldc 1048576
    //   3632: iastore
    //   3633: dup
    //   3634: bipush #14
    //   3636: bipush #32
    //   3638: iastore
    //   3639: dup
    //   3640: bipush #15
    //   3642: ldc -2146435040
    //   3644: iastore
    //   3645: dup
    //   3646: bipush #16
    //   3648: ldc 1081344
    //   3650: iastore
    //   3651: dup
    //   3652: bipush #17
    //   3654: ldc 1048608
    //   3656: iastore
    //   3657: dup
    //   3658: bipush #18
    //   3660: ldc -2147450848
    //   3662: iastore
    //   3663: dup
    //   3664: bipush #19
    //   3666: iconst_0
    //   3667: iastore
    //   3668: dup
    //   3669: bipush #20
    //   3671: ldc -2147483648
    //   3673: iastore
    //   3674: dup
    //   3675: bipush #21
    //   3677: ldc 32768
    //   3679: iastore
    //   3680: dup
    //   3681: bipush #22
    //   3683: ldc 1081376
    //   3685: iastore
    //   3686: dup
    //   3687: bipush #23
    //   3689: ldc -2146435072
    //   3691: iastore
    //   3692: dup
    //   3693: bipush #24
    //   3695: ldc 1048608
    //   3697: iastore
    //   3698: dup
    //   3699: bipush #25
    //   3701: ldc -2147483616
    //   3703: iastore
    //   3704: dup
    //   3705: bipush #26
    //   3707: iconst_0
    //   3708: iastore
    //   3709: dup
    //   3710: bipush #27
    //   3712: ldc 1081344
    //   3714: iastore
    //   3715: dup
    //   3716: bipush #28
    //   3718: ldc 32800
    //   3720: iastore
    //   3721: dup
    //   3722: bipush #29
    //   3724: ldc -2146402304
    //   3726: iastore
    //   3727: dup
    //   3728: bipush #30
    //   3730: ldc -2146435072
    //   3732: iastore
    //   3733: dup
    //   3734: bipush #31
    //   3736: ldc 32800
    //   3738: iastore
    //   3739: dup
    //   3740: bipush #32
    //   3742: iconst_0
    //   3743: iastore
    //   3744: dup
    //   3745: bipush #33
    //   3747: ldc 1081376
    //   3749: iastore
    //   3750: dup
    //   3751: bipush #34
    //   3753: ldc -2146435040
    //   3755: iastore
    //   3756: dup
    //   3757: bipush #35
    //   3759: ldc 1048576
    //   3761: iastore
    //   3762: dup
    //   3763: bipush #36
    //   3765: ldc -2147450848
    //   3767: iastore
    //   3768: dup
    //   3769: bipush #37
    //   3771: ldc -2146435072
    //   3773: iastore
    //   3774: dup
    //   3775: bipush #38
    //   3777: ldc -2146402304
    //   3779: iastore
    //   3780: dup
    //   3781: bipush #39
    //   3783: ldc 32768
    //   3785: iastore
    //   3786: dup
    //   3787: bipush #40
    //   3789: ldc -2146435072
    //   3791: iastore
    //   3792: dup
    //   3793: bipush #41
    //   3795: ldc -2147450880
    //   3797: iastore
    //   3798: dup
    //   3799: bipush #42
    //   3801: bipush #32
    //   3803: iastore
    //   3804: dup
    //   3805: bipush #43
    //   3807: ldc -2146402272
    //   3809: iastore
    //   3810: dup
    //   3811: bipush #44
    //   3813: ldc 1081376
    //   3815: iastore
    //   3816: dup
    //   3817: bipush #45
    //   3819: bipush #32
    //   3821: iastore
    //   3822: dup
    //   3823: bipush #46
    //   3825: ldc 32768
    //   3827: iastore
    //   3828: dup
    //   3829: bipush #47
    //   3831: ldc -2147483648
    //   3833: iastore
    //   3834: dup
    //   3835: bipush #48
    //   3837: ldc 32800
    //   3839: iastore
    //   3840: dup
    //   3841: bipush #49
    //   3843: ldc -2146402304
    //   3845: iastore
    //   3846: dup
    //   3847: bipush #50
    //   3849: ldc 1048576
    //   3851: iastore
    //   3852: dup
    //   3853: bipush #51
    //   3855: ldc -2147483616
    //   3857: iastore
    //   3858: dup
    //   3859: bipush #52
    //   3861: ldc 1048608
    //   3863: iastore
    //   3864: dup
    //   3865: bipush #53
    //   3867: ldc -2147450848
    //   3869: iastore
    //   3870: dup
    //   3871: bipush #54
    //   3873: ldc -2147483616
    //   3875: iastore
    //   3876: dup
    //   3877: bipush #55
    //   3879: ldc 1048608
    //   3881: iastore
    //   3882: dup
    //   3883: bipush #56
    //   3885: ldc 1081344
    //   3887: iastore
    //   3888: dup
    //   3889: bipush #57
    //   3891: iconst_0
    //   3892: iastore
    //   3893: dup
    //   3894: bipush #58
    //   3896: ldc -2147450880
    //   3898: iastore
    //   3899: dup
    //   3900: bipush #59
    //   3902: ldc 32800
    //   3904: iastore
    //   3905: dup
    //   3906: bipush #60
    //   3908: ldc -2147483648
    //   3910: iastore
    //   3911: dup
    //   3912: bipush #61
    //   3914: ldc -2146435040
    //   3916: iastore
    //   3917: dup
    //   3918: bipush #62
    //   3920: ldc -2146402272
    //   3922: iastore
    //   3923: dup
    //   3924: bipush #63
    //   3926: ldc 1081344
    //   3928: iastore
    //   3929: astore #8
    //   3931: bipush #64
    //   3933: newarray int
    //   3935: dup
    //   3936: iconst_0
    //   3937: sipush #520
    //   3940: iastore
    //   3941: dup
    //   3942: iconst_1
    //   3943: ldc 134349312
    //   3945: iastore
    //   3946: dup
    //   3947: iconst_2
    //   3948: iconst_0
    //   3949: iastore
    //   3950: dup
    //   3951: iconst_3
    //   3952: ldc 134348808
    //   3954: iastore
    //   3955: dup
    //   3956: iconst_4
    //   3957: ldc 134218240
    //   3959: iastore
    //   3960: dup
    //   3961: iconst_5
    //   3962: iconst_0
    //   3963: iastore
    //   3964: dup
    //   3965: bipush #6
    //   3967: ldc 131592
    //   3969: iastore
    //   3970: dup
    //   3971: bipush #7
    //   3973: ldc 134218240
    //   3975: iastore
    //   3976: dup
    //   3977: bipush #8
    //   3979: ldc 131080
    //   3981: iastore
    //   3982: dup
    //   3983: bipush #9
    //   3985: ldc 134217736
    //   3987: iastore
    //   3988: dup
    //   3989: bipush #10
    //   3991: ldc 134217736
    //   3993: iastore
    //   3994: dup
    //   3995: bipush #11
    //   3997: ldc 131072
    //   3999: iastore
    //   4000: dup
    //   4001: bipush #12
    //   4003: ldc 134349320
    //   4005: iastore
    //   4006: dup
    //   4007: bipush #13
    //   4009: ldc 131080
    //   4011: iastore
    //   4012: dup
    //   4013: bipush #14
    //   4015: ldc 134348800
    //   4017: iastore
    //   4018: dup
    //   4019: bipush #15
    //   4021: sipush #520
    //   4024: iastore
    //   4025: dup
    //   4026: bipush #16
    //   4028: ldc 134217728
    //   4030: iastore
    //   4031: dup
    //   4032: bipush #17
    //   4034: bipush #8
    //   4036: iastore
    //   4037: dup
    //   4038: bipush #18
    //   4040: ldc 134349312
    //   4042: iastore
    //   4043: dup
    //   4044: bipush #19
    //   4046: sipush #512
    //   4049: iastore
    //   4050: dup
    //   4051: bipush #20
    //   4053: ldc 131584
    //   4055: iastore
    //   4056: dup
    //   4057: bipush #21
    //   4059: ldc 134348800
    //   4061: iastore
    //   4062: dup
    //   4063: bipush #22
    //   4065: ldc 134348808
    //   4067: iastore
    //   4068: dup
    //   4069: bipush #23
    //   4071: ldc 131592
    //   4073: iastore
    //   4074: dup
    //   4075: bipush #24
    //   4077: ldc 134218248
    //   4079: iastore
    //   4080: dup
    //   4081: bipush #25
    //   4083: ldc 131584
    //   4085: iastore
    //   4086: dup
    //   4087: bipush #26
    //   4089: ldc 131072
    //   4091: iastore
    //   4092: dup
    //   4093: bipush #27
    //   4095: ldc 134218248
    //   4097: iastore
    //   4098: dup
    //   4099: bipush #28
    //   4101: bipush #8
    //   4103: iastore
    //   4104: dup
    //   4105: bipush #29
    //   4107: ldc 134349320
    //   4109: iastore
    //   4110: dup
    //   4111: bipush #30
    //   4113: sipush #512
    //   4116: iastore
    //   4117: dup
    //   4118: bipush #31
    //   4120: ldc 134217728
    //   4122: iastore
    //   4123: dup
    //   4124: bipush #32
    //   4126: ldc 134349312
    //   4128: iastore
    //   4129: dup
    //   4130: bipush #33
    //   4132: ldc 134217728
    //   4134: iastore
    //   4135: dup
    //   4136: bipush #34
    //   4138: ldc 131080
    //   4140: iastore
    //   4141: dup
    //   4142: bipush #35
    //   4144: sipush #520
    //   4147: iastore
    //   4148: dup
    //   4149: bipush #36
    //   4151: ldc 131072
    //   4153: iastore
    //   4154: dup
    //   4155: bipush #37
    //   4157: ldc 134349312
    //   4159: iastore
    //   4160: dup
    //   4161: bipush #38
    //   4163: ldc 134218240
    //   4165: iastore
    //   4166: dup
    //   4167: bipush #39
    //   4169: iconst_0
    //   4170: iastore
    //   4171: dup
    //   4172: bipush #40
    //   4174: sipush #512
    //   4177: iastore
    //   4178: dup
    //   4179: bipush #41
    //   4181: ldc 131080
    //   4183: iastore
    //   4184: dup
    //   4185: bipush #42
    //   4187: ldc 134349320
    //   4189: iastore
    //   4190: dup
    //   4191: bipush #43
    //   4193: ldc 134218240
    //   4195: iastore
    //   4196: dup
    //   4197: bipush #44
    //   4199: ldc 134217736
    //   4201: iastore
    //   4202: dup
    //   4203: bipush #45
    //   4205: sipush #512
    //   4208: iastore
    //   4209: dup
    //   4210: bipush #46
    //   4212: iconst_0
    //   4213: iastore
    //   4214: dup
    //   4215: bipush #47
    //   4217: ldc 134348808
    //   4219: iastore
    //   4220: dup
    //   4221: bipush #48
    //   4223: ldc 134218248
    //   4225: iastore
    //   4226: dup
    //   4227: bipush #49
    //   4229: ldc 131072
    //   4231: iastore
    //   4232: dup
    //   4233: bipush #50
    //   4235: ldc 134217728
    //   4237: iastore
    //   4238: dup
    //   4239: bipush #51
    //   4241: ldc 134349320
    //   4243: iastore
    //   4244: dup
    //   4245: bipush #52
    //   4247: bipush #8
    //   4249: iastore
    //   4250: dup
    //   4251: bipush #53
    //   4253: ldc 131592
    //   4255: iastore
    //   4256: dup
    //   4257: bipush #54
    //   4259: ldc 131584
    //   4261: iastore
    //   4262: dup
    //   4263: bipush #55
    //   4265: ldc 134217736
    //   4267: iastore
    //   4268: dup
    //   4269: bipush #56
    //   4271: ldc 134348800
    //   4273: iastore
    //   4274: dup
    //   4275: bipush #57
    //   4277: ldc 134218248
    //   4279: iastore
    //   4280: dup
    //   4281: bipush #58
    //   4283: sipush #520
    //   4286: iastore
    //   4287: dup
    //   4288: bipush #59
    //   4290: ldc 134348800
    //   4292: iastore
    //   4293: dup
    //   4294: bipush #60
    //   4296: ldc 131592
    //   4298: iastore
    //   4299: dup
    //   4300: bipush #61
    //   4302: bipush #8
    //   4304: iastore
    //   4305: dup
    //   4306: bipush #62
    //   4308: ldc 134348808
    //   4310: iastore
    //   4311: dup
    //   4312: bipush #63
    //   4314: ldc 131584
    //   4316: iastore
    //   4317: astore #9
    //   4319: bipush #64
    //   4321: newarray int
    //   4323: dup
    //   4324: iconst_0
    //   4325: ldc 8396801
    //   4327: iastore
    //   4328: dup
    //   4329: iconst_1
    //   4330: sipush #8321
    //   4333: iastore
    //   4334: dup
    //   4335: iconst_2
    //   4336: sipush #8321
    //   4339: iastore
    //   4340: dup
    //   4341: iconst_3
    //   4342: sipush #128
    //   4345: iastore
    //   4346: dup
    //   4347: iconst_4
    //   4348: ldc 8396928
    //   4350: iastore
    //   4351: dup
    //   4352: iconst_5
    //   4353: ldc 8388737
    //   4355: iastore
    //   4356: dup
    //   4357: bipush #6
    //   4359: ldc 8388609
    //   4361: iastore
    //   4362: dup
    //   4363: bipush #7
    //   4365: sipush #8193
    //   4368: iastore
    //   4369: dup
    //   4370: bipush #8
    //   4372: iconst_0
    //   4373: iastore
    //   4374: dup
    //   4375: bipush #9
    //   4377: ldc 8396800
    //   4379: iastore
    //   4380: dup
    //   4381: bipush #10
    //   4383: ldc 8396800
    //   4385: iastore
    //   4386: dup
    //   4387: bipush #11
    //   4389: ldc 8396929
    //   4391: iastore
    //   4392: dup
    //   4393: bipush #12
    //   4395: sipush #129
    //   4398: iastore
    //   4399: dup
    //   4400: bipush #13
    //   4402: iconst_0
    //   4403: iastore
    //   4404: dup
    //   4405: bipush #14
    //   4407: ldc 8388736
    //   4409: iastore
    //   4410: dup
    //   4411: bipush #15
    //   4413: ldc 8388609
    //   4415: iastore
    //   4416: dup
    //   4417: bipush #16
    //   4419: iconst_1
    //   4420: iastore
    //   4421: dup
    //   4422: bipush #17
    //   4424: sipush #8192
    //   4427: iastore
    //   4428: dup
    //   4429: bipush #18
    //   4431: ldc 8388608
    //   4433: iastore
    //   4434: dup
    //   4435: bipush #19
    //   4437: ldc 8396801
    //   4439: iastore
    //   4440: dup
    //   4441: bipush #20
    //   4443: sipush #128
    //   4446: iastore
    //   4447: dup
    //   4448: bipush #21
    //   4450: ldc 8388608
    //   4452: iastore
    //   4453: dup
    //   4454: bipush #22
    //   4456: sipush #8193
    //   4459: iastore
    //   4460: dup
    //   4461: bipush #23
    //   4463: sipush #8320
    //   4466: iastore
    //   4467: dup
    //   4468: bipush #24
    //   4470: ldc 8388737
    //   4472: iastore
    //   4473: dup
    //   4474: bipush #25
    //   4476: iconst_1
    //   4477: iastore
    //   4478: dup
    //   4479: bipush #26
    //   4481: sipush #8320
    //   4484: iastore
    //   4485: dup
    //   4486: bipush #27
    //   4488: ldc 8388736
    //   4490: iastore
    //   4491: dup
    //   4492: bipush #28
    //   4494: sipush #8192
    //   4497: iastore
    //   4498: dup
    //   4499: bipush #29
    //   4501: ldc 8396928
    //   4503: iastore
    //   4504: dup
    //   4505: bipush #30
    //   4507: ldc 8396929
    //   4509: iastore
    //   4510: dup
    //   4511: bipush #31
    //   4513: sipush #129
    //   4516: iastore
    //   4517: dup
    //   4518: bipush #32
    //   4520: ldc 8388736
    //   4522: iastore
    //   4523: dup
    //   4524: bipush #33
    //   4526: ldc 8388609
    //   4528: iastore
    //   4529: dup
    //   4530: bipush #34
    //   4532: ldc 8396800
    //   4534: iastore
    //   4535: dup
    //   4536: bipush #35
    //   4538: ldc 8396929
    //   4540: iastore
    //   4541: dup
    //   4542: bipush #36
    //   4544: sipush #129
    //   4547: iastore
    //   4548: dup
    //   4549: bipush #37
    //   4551: iconst_0
    //   4552: iastore
    //   4553: dup
    //   4554: bipush #38
    //   4556: iconst_0
    //   4557: iastore
    //   4558: dup
    //   4559: bipush #39
    //   4561: ldc 8396800
    //   4563: iastore
    //   4564: dup
    //   4565: bipush #40
    //   4567: sipush #8320
    //   4570: iastore
    //   4571: dup
    //   4572: bipush #41
    //   4574: ldc 8388736
    //   4576: iastore
    //   4577: dup
    //   4578: bipush #42
    //   4580: ldc 8388737
    //   4582: iastore
    //   4583: dup
    //   4584: bipush #43
    //   4586: iconst_1
    //   4587: iastore
    //   4588: dup
    //   4589: bipush #44
    //   4591: ldc 8396801
    //   4593: iastore
    //   4594: dup
    //   4595: bipush #45
    //   4597: sipush #8321
    //   4600: iastore
    //   4601: dup
    //   4602: bipush #46
    //   4604: sipush #8321
    //   4607: iastore
    //   4608: dup
    //   4609: bipush #47
    //   4611: sipush #128
    //   4614: iastore
    //   4615: dup
    //   4616: bipush #48
    //   4618: ldc 8396929
    //   4620: iastore
    //   4621: dup
    //   4622: bipush #49
    //   4624: sipush #129
    //   4627: iastore
    //   4628: dup
    //   4629: bipush #50
    //   4631: iconst_1
    //   4632: iastore
    //   4633: dup
    //   4634: bipush #51
    //   4636: sipush #8192
    //   4639: iastore
    //   4640: dup
    //   4641: bipush #52
    //   4643: ldc 8388609
    //   4645: iastore
    //   4646: dup
    //   4647: bipush #53
    //   4649: sipush #8193
    //   4652: iastore
    //   4653: dup
    //   4654: bipush #54
    //   4656: ldc 8396928
    //   4658: iastore
    //   4659: dup
    //   4660: bipush #55
    //   4662: ldc 8388737
    //   4664: iastore
    //   4665: dup
    //   4666: bipush #56
    //   4668: sipush #8193
    //   4671: iastore
    //   4672: dup
    //   4673: bipush #57
    //   4675: sipush #8320
    //   4678: iastore
    //   4679: dup
    //   4680: bipush #58
    //   4682: ldc 8388608
    //   4684: iastore
    //   4685: dup
    //   4686: bipush #59
    //   4688: ldc 8396801
    //   4690: iastore
    //   4691: dup
    //   4692: bipush #60
    //   4694: sipush #128
    //   4697: iastore
    //   4698: dup
    //   4699: bipush #61
    //   4701: ldc 8388608
    //   4703: iastore
    //   4704: dup
    //   4705: bipush #62
    //   4707: sipush #8192
    //   4710: iastore
    //   4711: dup
    //   4712: bipush #63
    //   4714: ldc 8396928
    //   4716: iastore
    //   4717: astore #10
    //   4719: bipush #64
    //   4721: newarray int
    //   4723: dup
    //   4724: iconst_0
    //   4725: sipush #256
    //   4728: iastore
    //   4729: dup
    //   4730: iconst_1
    //   4731: ldc 34078976
    //   4733: iastore
    //   4734: dup
    //   4735: iconst_2
    //   4736: ldc 34078720
    //   4738: iastore
    //   4739: dup
    //   4740: iconst_3
    //   4741: ldc 1107296512
    //   4743: iastore
    //   4744: dup
    //   4745: iconst_4
    //   4746: ldc 524288
    //   4748: iastore
    //   4749: dup
    //   4750: iconst_5
    //   4751: sipush #256
    //   4754: iastore
    //   4755: dup
    //   4756: bipush #6
    //   4758: ldc 1073741824
    //   4760: iastore
    //   4761: dup
    //   4762: bipush #7
    //   4764: ldc 34078720
    //   4766: iastore
    //   4767: dup
    //   4768: bipush #8
    //   4770: ldc 1074266368
    //   4772: iastore
    //   4773: dup
    //   4774: bipush #9
    //   4776: ldc 524288
    //   4778: iastore
    //   4779: dup
    //   4780: bipush #10
    //   4782: ldc 33554688
    //   4784: iastore
    //   4785: dup
    //   4786: bipush #11
    //   4788: ldc 1074266368
    //   4790: iastore
    //   4791: dup
    //   4792: bipush #12
    //   4794: ldc 1107296512
    //   4796: iastore
    //   4797: dup
    //   4798: bipush #13
    //   4800: ldc 1107820544
    //   4802: iastore
    //   4803: dup
    //   4804: bipush #14
    //   4806: ldc 524544
    //   4808: iastore
    //   4809: dup
    //   4810: bipush #15
    //   4812: ldc 1073741824
    //   4814: iastore
    //   4815: dup
    //   4816: bipush #16
    //   4818: ldc 33554432
    //   4820: iastore
    //   4821: dup
    //   4822: bipush #17
    //   4824: ldc 1074266112
    //   4826: iastore
    //   4827: dup
    //   4828: bipush #18
    //   4830: ldc 1074266112
    //   4832: iastore
    //   4833: dup
    //   4834: bipush #19
    //   4836: iconst_0
    //   4837: iastore
    //   4838: dup
    //   4839: bipush #20
    //   4841: ldc 1073742080
    //   4843: iastore
    //   4844: dup
    //   4845: bipush #21
    //   4847: ldc 1107820800
    //   4849: iastore
    //   4850: dup
    //   4851: bipush #22
    //   4853: ldc 1107820800
    //   4855: iastore
    //   4856: dup
    //   4857: bipush #23
    //   4859: ldc 33554688
    //   4861: iastore
    //   4862: dup
    //   4863: bipush #24
    //   4865: ldc 1107820544
    //   4867: iastore
    //   4868: dup
    //   4869: bipush #25
    //   4871: ldc 1073742080
    //   4873: iastore
    //   4874: dup
    //   4875: bipush #26
    //   4877: iconst_0
    //   4878: iastore
    //   4879: dup
    //   4880: bipush #27
    //   4882: ldc 1107296256
    //   4884: iastore
    //   4885: dup
    //   4886: bipush #28
    //   4888: ldc 34078976
    //   4890: iastore
    //   4891: dup
    //   4892: bipush #29
    //   4894: ldc 33554432
    //   4896: iastore
    //   4897: dup
    //   4898: bipush #30
    //   4900: ldc 1107296256
    //   4902: iastore
    //   4903: dup
    //   4904: bipush #31
    //   4906: ldc 524544
    //   4908: iastore
    //   4909: dup
    //   4910: bipush #32
    //   4912: ldc 524288
    //   4914: iastore
    //   4915: dup
    //   4916: bipush #33
    //   4918: ldc 1107296512
    //   4920: iastore
    //   4921: dup
    //   4922: bipush #34
    //   4924: sipush #256
    //   4927: iastore
    //   4928: dup
    //   4929: bipush #35
    //   4931: ldc 33554432
    //   4933: iastore
    //   4934: dup
    //   4935: bipush #36
    //   4937: ldc 1073741824
    //   4939: iastore
    //   4940: dup
    //   4941: bipush #37
    //   4943: ldc 34078720
    //   4945: iastore
    //   4946: dup
    //   4947: bipush #38
    //   4949: ldc 1107296512
    //   4951: iastore
    //   4952: dup
    //   4953: bipush #39
    //   4955: ldc 1074266368
    //   4957: iastore
    //   4958: dup
    //   4959: bipush #40
    //   4961: ldc 33554688
    //   4963: iastore
    //   4964: dup
    //   4965: bipush #41
    //   4967: ldc 1073741824
    //   4969: iastore
    //   4970: dup
    //   4971: bipush #42
    //   4973: ldc 1107820544
    //   4975: iastore
    //   4976: dup
    //   4977: bipush #43
    //   4979: ldc 34078976
    //   4981: iastore
    //   4982: dup
    //   4983: bipush #44
    //   4985: ldc 1074266368
    //   4987: iastore
    //   4988: dup
    //   4989: bipush #45
    //   4991: sipush #256
    //   4994: iastore
    //   4995: dup
    //   4996: bipush #46
    //   4998: ldc 33554432
    //   5000: iastore
    //   5001: dup
    //   5002: bipush #47
    //   5004: ldc 1107820544
    //   5006: iastore
    //   5007: dup
    //   5008: bipush #48
    //   5010: ldc 1107820800
    //   5012: iastore
    //   5013: dup
    //   5014: bipush #49
    //   5016: ldc 524544
    //   5018: iastore
    //   5019: dup
    //   5020: bipush #50
    //   5022: ldc 1107296256
    //   5024: iastore
    //   5025: dup
    //   5026: bipush #51
    //   5028: ldc 1107820800
    //   5030: iastore
    //   5031: dup
    //   5032: bipush #52
    //   5034: ldc 34078720
    //   5036: iastore
    //   5037: dup
    //   5038: bipush #53
    //   5040: iconst_0
    //   5041: iastore
    //   5042: dup
    //   5043: bipush #54
    //   5045: ldc 1074266112
    //   5047: iastore
    //   5048: dup
    //   5049: bipush #55
    //   5051: ldc 1107296256
    //   5053: iastore
    //   5054: dup
    //   5055: bipush #56
    //   5057: ldc 524544
    //   5059: iastore
    //   5060: dup
    //   5061: bipush #57
    //   5063: ldc 33554688
    //   5065: iastore
    //   5066: dup
    //   5067: bipush #58
    //   5069: ldc 1073742080
    //   5071: iastore
    //   5072: dup
    //   5073: bipush #59
    //   5075: ldc 524288
    //   5077: iastore
    //   5078: dup
    //   5079: bipush #60
    //   5081: iconst_0
    //   5082: iastore
    //   5083: dup
    //   5084: bipush #61
    //   5086: ldc 1074266112
    //   5088: iastore
    //   5089: dup
    //   5090: bipush #62
    //   5092: ldc 34078976
    //   5094: iastore
    //   5095: dup
    //   5096: bipush #63
    //   5098: ldc 1073742080
    //   5100: iastore
    //   5101: astore #11
    //   5103: bipush #64
    //   5105: newarray int
    //   5107: dup
    //   5108: iconst_0
    //   5109: ldc 536870928
    //   5111: iastore
    //   5112: dup
    //   5113: iconst_1
    //   5114: ldc 541065216
    //   5116: iastore
    //   5117: dup
    //   5118: iconst_2
    //   5119: sipush #16384
    //   5122: iastore
    //   5123: dup
    //   5124: iconst_3
    //   5125: ldc 541081616
    //   5127: iastore
    //   5128: dup
    //   5129: iconst_4
    //   5130: ldc 541065216
    //   5132: iastore
    //   5133: dup
    //   5134: iconst_5
    //   5135: bipush #16
    //   5137: iastore
    //   5138: dup
    //   5139: bipush #6
    //   5141: ldc 541081616
    //   5143: iastore
    //   5144: dup
    //   5145: bipush #7
    //   5147: ldc 4194304
    //   5149: iastore
    //   5150: dup
    //   5151: bipush #8
    //   5153: ldc 536887296
    //   5155: iastore
    //   5156: dup
    //   5157: bipush #9
    //   5159: ldc 4210704
    //   5161: iastore
    //   5162: dup
    //   5163: bipush #10
    //   5165: ldc 4194304
    //   5167: iastore
    //   5168: dup
    //   5169: bipush #11
    //   5171: ldc 536870928
    //   5173: iastore
    //   5174: dup
    //   5175: bipush #12
    //   5177: ldc 4194320
    //   5179: iastore
    //   5180: dup
    //   5181: bipush #13
    //   5183: ldc 536887296
    //   5185: iastore
    //   5186: dup
    //   5187: bipush #14
    //   5189: ldc 536870912
    //   5191: iastore
    //   5192: dup
    //   5193: bipush #15
    //   5195: sipush #16400
    //   5198: iastore
    //   5199: dup
    //   5200: bipush #16
    //   5202: iconst_0
    //   5203: iastore
    //   5204: dup
    //   5205: bipush #17
    //   5207: ldc 4194320
    //   5209: iastore
    //   5210: dup
    //   5211: bipush #18
    //   5213: ldc 536887312
    //   5215: iastore
    //   5216: dup
    //   5217: bipush #19
    //   5219: sipush #16384
    //   5222: iastore
    //   5223: dup
    //   5224: bipush #20
    //   5226: ldc 4210688
    //   5228: iastore
    //   5229: dup
    //   5230: bipush #21
    //   5232: ldc 536887312
    //   5234: iastore
    //   5235: dup
    //   5236: bipush #22
    //   5238: bipush #16
    //   5240: iastore
    //   5241: dup
    //   5242: bipush #23
    //   5244: ldc 541065232
    //   5246: iastore
    //   5247: dup
    //   5248: bipush #24
    //   5250: ldc 541065232
    //   5252: iastore
    //   5253: dup
    //   5254: bipush #25
    //   5256: iconst_0
    //   5257: iastore
    //   5258: dup
    //   5259: bipush #26
    //   5261: ldc 4210704
    //   5263: iastore
    //   5264: dup
    //   5265: bipush #27
    //   5267: ldc 541081600
    //   5269: iastore
    //   5270: dup
    //   5271: bipush #28
    //   5273: sipush #16400
    //   5276: iastore
    //   5277: dup
    //   5278: bipush #29
    //   5280: ldc 4210688
    //   5282: iastore
    //   5283: dup
    //   5284: bipush #30
    //   5286: ldc 541081600
    //   5288: iastore
    //   5289: dup
    //   5290: bipush #31
    //   5292: ldc 536870912
    //   5294: iastore
    //   5295: dup
    //   5296: bipush #32
    //   5298: ldc 536887296
    //   5300: iastore
    //   5301: dup
    //   5302: bipush #33
    //   5304: bipush #16
    //   5306: iastore
    //   5307: dup
    //   5308: bipush #34
    //   5310: ldc 541065232
    //   5312: iastore
    //   5313: dup
    //   5314: bipush #35
    //   5316: ldc 4210688
    //   5318: iastore
    //   5319: dup
    //   5320: bipush #36
    //   5322: ldc 541081616
    //   5324: iastore
    //   5325: dup
    //   5326: bipush #37
    //   5328: ldc 4194304
    //   5330: iastore
    //   5331: dup
    //   5332: bipush #38
    //   5334: sipush #16400
    //   5337: iastore
    //   5338: dup
    //   5339: bipush #39
    //   5341: ldc 536870928
    //   5343: iastore
    //   5344: dup
    //   5345: bipush #40
    //   5347: ldc 4194304
    //   5349: iastore
    //   5350: dup
    //   5351: bipush #41
    //   5353: ldc 536887296
    //   5355: iastore
    //   5356: dup
    //   5357: bipush #42
    //   5359: ldc 536870912
    //   5361: iastore
    //   5362: dup
    //   5363: bipush #43
    //   5365: sipush #16400
    //   5368: iastore
    //   5369: dup
    //   5370: bipush #44
    //   5372: ldc 536870928
    //   5374: iastore
    //   5375: dup
    //   5376: bipush #45
    //   5378: ldc 541081616
    //   5380: iastore
    //   5381: dup
    //   5382: bipush #46
    //   5384: ldc 4210688
    //   5386: iastore
    //   5387: dup
    //   5388: bipush #47
    //   5390: ldc 541065216
    //   5392: iastore
    //   5393: dup
    //   5394: bipush #48
    //   5396: ldc 4210704
    //   5398: iastore
    //   5399: dup
    //   5400: bipush #49
    //   5402: ldc 541081600
    //   5404: iastore
    //   5405: dup
    //   5406: bipush #50
    //   5408: iconst_0
    //   5409: iastore
    //   5410: dup
    //   5411: bipush #51
    //   5413: ldc 541065232
    //   5415: iastore
    //   5416: dup
    //   5417: bipush #52
    //   5419: bipush #16
    //   5421: iastore
    //   5422: dup
    //   5423: bipush #53
    //   5425: sipush #16384
    //   5428: iastore
    //   5429: dup
    //   5430: bipush #54
    //   5432: ldc 541065216
    //   5434: iastore
    //   5435: dup
    //   5436: bipush #55
    //   5438: ldc 4210704
    //   5440: iastore
    //   5441: dup
    //   5442: bipush #56
    //   5444: sipush #16384
    //   5447: iastore
    //   5448: dup
    //   5449: bipush #57
    //   5451: ldc 4194320
    //   5453: iastore
    //   5454: dup
    //   5455: bipush #58
    //   5457: ldc 536887312
    //   5459: iastore
    //   5460: dup
    //   5461: bipush #59
    //   5463: iconst_0
    //   5464: iastore
    //   5465: dup
    //   5466: bipush #60
    //   5468: ldc 541081600
    //   5470: iastore
    //   5471: dup
    //   5472: bipush #61
    //   5474: ldc 536870912
    //   5476: iastore
    //   5477: dup
    //   5478: bipush #62
    //   5480: ldc 4194320
    //   5482: iastore
    //   5483: dup
    //   5484: bipush #63
    //   5486: ldc 536887312
    //   5488: iastore
    //   5489: astore #12
    //   5491: bipush #64
    //   5493: newarray int
    //   5495: dup
    //   5496: iconst_0
    //   5497: ldc 2097152
    //   5499: iastore
    //   5500: dup
    //   5501: iconst_1
    //   5502: ldc 69206018
    //   5504: iastore
    //   5505: dup
    //   5506: iconst_2
    //   5507: ldc 67110914
    //   5509: iastore
    //   5510: dup
    //   5511: iconst_3
    //   5512: iconst_0
    //   5513: iastore
    //   5514: dup
    //   5515: iconst_4
    //   5516: sipush #2048
    //   5519: iastore
    //   5520: dup
    //   5521: iconst_5
    //   5522: ldc 67110914
    //   5524: iastore
    //   5525: dup
    //   5526: bipush #6
    //   5528: ldc 2099202
    //   5530: iastore
    //   5531: dup
    //   5532: bipush #7
    //   5534: ldc 69208064
    //   5536: iastore
    //   5537: dup
    //   5538: bipush #8
    //   5540: ldc 69208066
    //   5542: iastore
    //   5543: dup
    //   5544: bipush #9
    //   5546: ldc 2097152
    //   5548: iastore
    //   5549: dup
    //   5550: bipush #10
    //   5552: iconst_0
    //   5553: iastore
    //   5554: dup
    //   5555: bipush #11
    //   5557: ldc 67108866
    //   5559: iastore
    //   5560: dup
    //   5561: bipush #12
    //   5563: iconst_2
    //   5564: iastore
    //   5565: dup
    //   5566: bipush #13
    //   5568: ldc 67108864
    //   5570: iastore
    //   5571: dup
    //   5572: bipush #14
    //   5574: ldc 69206018
    //   5576: iastore
    //   5577: dup
    //   5578: bipush #15
    //   5580: sipush #2050
    //   5583: iastore
    //   5584: dup
    //   5585: bipush #16
    //   5587: ldc 67110912
    //   5589: iastore
    //   5590: dup
    //   5591: bipush #17
    //   5593: ldc 2099202
    //   5595: iastore
    //   5596: dup
    //   5597: bipush #18
    //   5599: ldc 2097154
    //   5601: iastore
    //   5602: dup
    //   5603: bipush #19
    //   5605: ldc 67110912
    //   5607: iastore
    //   5608: dup
    //   5609: bipush #20
    //   5611: ldc 67108866
    //   5613: iastore
    //   5614: dup
    //   5615: bipush #21
    //   5617: ldc 69206016
    //   5619: iastore
    //   5620: dup
    //   5621: bipush #22
    //   5623: ldc 69208064
    //   5625: iastore
    //   5626: dup
    //   5627: bipush #23
    //   5629: ldc 2097154
    //   5631: iastore
    //   5632: dup
    //   5633: bipush #24
    //   5635: ldc 69206016
    //   5637: iastore
    //   5638: dup
    //   5639: bipush #25
    //   5641: sipush #2048
    //   5644: iastore
    //   5645: dup
    //   5646: bipush #26
    //   5648: sipush #2050
    //   5651: iastore
    //   5652: dup
    //   5653: bipush #27
    //   5655: ldc 69208066
    //   5657: iastore
    //   5658: dup
    //   5659: bipush #28
    //   5661: ldc 2099200
    //   5663: iastore
    //   5664: dup
    //   5665: bipush #29
    //   5667: iconst_2
    //   5668: iastore
    //   5669: dup
    //   5670: bipush #30
    //   5672: ldc 67108864
    //   5674: iastore
    //   5675: dup
    //   5676: bipush #31
    //   5678: ldc 2099200
    //   5680: iastore
    //   5681: dup
    //   5682: bipush #32
    //   5684: ldc 67108864
    //   5686: iastore
    //   5687: dup
    //   5688: bipush #33
    //   5690: ldc 2099200
    //   5692: iastore
    //   5693: dup
    //   5694: bipush #34
    //   5696: ldc 2097152
    //   5698: iastore
    //   5699: dup
    //   5700: bipush #35
    //   5702: ldc 67110914
    //   5704: iastore
    //   5705: dup
    //   5706: bipush #36
    //   5708: ldc 67110914
    //   5710: iastore
    //   5711: dup
    //   5712: bipush #37
    //   5714: ldc 69206018
    //   5716: iastore
    //   5717: dup
    //   5718: bipush #38
    //   5720: ldc 69206018
    //   5722: iastore
    //   5723: dup
    //   5724: bipush #39
    //   5726: iconst_2
    //   5727: iastore
    //   5728: dup
    //   5729: bipush #40
    //   5731: ldc 2097154
    //   5733: iastore
    //   5734: dup
    //   5735: bipush #41
    //   5737: ldc 67108864
    //   5739: iastore
    //   5740: dup
    //   5741: bipush #42
    //   5743: ldc 67110912
    //   5745: iastore
    //   5746: dup
    //   5747: bipush #43
    //   5749: ldc 2097152
    //   5751: iastore
    //   5752: dup
    //   5753: bipush #44
    //   5755: ldc 69208064
    //   5757: iastore
    //   5758: dup
    //   5759: bipush #45
    //   5761: sipush #2050
    //   5764: iastore
    //   5765: dup
    //   5766: bipush #46
    //   5768: ldc 2099202
    //   5770: iastore
    //   5771: dup
    //   5772: bipush #47
    //   5774: ldc 69208064
    //   5776: iastore
    //   5777: dup
    //   5778: bipush #48
    //   5780: sipush #2050
    //   5783: iastore
    //   5784: dup
    //   5785: bipush #49
    //   5787: ldc 67108866
    //   5789: iastore
    //   5790: dup
    //   5791: bipush #50
    //   5793: ldc 69208066
    //   5795: iastore
    //   5796: dup
    //   5797: bipush #51
    //   5799: ldc 69206016
    //   5801: iastore
    //   5802: dup
    //   5803: bipush #52
    //   5805: ldc 2099200
    //   5807: iastore
    //   5808: dup
    //   5809: bipush #53
    //   5811: iconst_0
    //   5812: iastore
    //   5813: dup
    //   5814: bipush #54
    //   5816: iconst_2
    //   5817: iastore
    //   5818: dup
    //   5819: bipush #55
    //   5821: ldc 69208066
    //   5823: iastore
    //   5824: dup
    //   5825: bipush #56
    //   5827: iconst_0
    //   5828: iastore
    //   5829: dup
    //   5830: bipush #57
    //   5832: ldc 2099202
    //   5834: iastore
    //   5835: dup
    //   5836: bipush #58
    //   5838: ldc 69206016
    //   5840: iastore
    //   5841: dup
    //   5842: bipush #59
    //   5844: sipush #2048
    //   5847: iastore
    //   5848: dup
    //   5849: bipush #60
    //   5851: ldc 67108866
    //   5853: iastore
    //   5854: dup
    //   5855: bipush #61
    //   5857: ldc 67110912
    //   5859: iastore
    //   5860: dup
    //   5861: bipush #62
    //   5863: sipush #2048
    //   5866: iastore
    //   5867: dup
    //   5868: bipush #63
    //   5870: ldc 2097154
    //   5872: iastore
    //   5873: astore #13
    //   5875: bipush #64
    //   5877: newarray int
    //   5879: dup
    //   5880: iconst_0
    //   5881: ldc 268439616
    //   5883: iastore
    //   5884: dup
    //   5885: iconst_1
    //   5886: sipush #4096
    //   5889: iastore
    //   5890: dup
    //   5891: iconst_2
    //   5892: ldc 262144
    //   5894: iastore
    //   5895: dup
    //   5896: iconst_3
    //   5897: ldc 268701760
    //   5899: iastore
    //   5900: dup
    //   5901: iconst_4
    //   5902: ldc 268435456
    //   5904: iastore
    //   5905: dup
    //   5906: iconst_5
    //   5907: ldc 268439616
    //   5909: iastore
    //   5910: dup
    //   5911: bipush #6
    //   5913: bipush #64
    //   5915: iastore
    //   5916: dup
    //   5917: bipush #7
    //   5919: ldc 268435456
    //   5921: iastore
    //   5922: dup
    //   5923: bipush #8
    //   5925: ldc 262208
    //   5927: iastore
    //   5928: dup
    //   5929: bipush #9
    //   5931: ldc 268697600
    //   5933: iastore
    //   5934: dup
    //   5935: bipush #10
    //   5937: ldc 268701760
    //   5939: iastore
    //   5940: dup
    //   5941: bipush #11
    //   5943: ldc 266240
    //   5945: iastore
    //   5946: dup
    //   5947: bipush #12
    //   5949: ldc 268701696
    //   5951: iastore
    //   5952: dup
    //   5953: bipush #13
    //   5955: ldc 266304
    //   5957: iastore
    //   5958: dup
    //   5959: bipush #14
    //   5961: sipush #4096
    //   5964: iastore
    //   5965: dup
    //   5966: bipush #15
    //   5968: bipush #64
    //   5970: iastore
    //   5971: dup
    //   5972: bipush #16
    //   5974: ldc 268697600
    //   5976: iastore
    //   5977: dup
    //   5978: bipush #17
    //   5980: ldc 268435520
    //   5982: iastore
    //   5983: dup
    //   5984: bipush #18
    //   5986: ldc 268439552
    //   5988: iastore
    //   5989: dup
    //   5990: bipush #19
    //   5992: sipush #4160
    //   5995: iastore
    //   5996: dup
    //   5997: bipush #20
    //   5999: ldc 266240
    //   6001: iastore
    //   6002: dup
    //   6003: bipush #21
    //   6005: ldc 262208
    //   6007: iastore
    //   6008: dup
    //   6009: bipush #22
    //   6011: ldc 268697664
    //   6013: iastore
    //   6014: dup
    //   6015: bipush #23
    //   6017: ldc 268701696
    //   6019: iastore
    //   6020: dup
    //   6021: bipush #24
    //   6023: sipush #4160
    //   6026: iastore
    //   6027: dup
    //   6028: bipush #25
    //   6030: iconst_0
    //   6031: iastore
    //   6032: dup
    //   6033: bipush #26
    //   6035: iconst_0
    //   6036: iastore
    //   6037: dup
    //   6038: bipush #27
    //   6040: ldc 268697664
    //   6042: iastore
    //   6043: dup
    //   6044: bipush #28
    //   6046: ldc 268435520
    //   6048: iastore
    //   6049: dup
    //   6050: bipush #29
    //   6052: ldc 268439552
    //   6054: iastore
    //   6055: dup
    //   6056: bipush #30
    //   6058: ldc 266304
    //   6060: iastore
    //   6061: dup
    //   6062: bipush #31
    //   6064: ldc 262144
    //   6066: iastore
    //   6067: dup
    //   6068: bipush #32
    //   6070: ldc 266304
    //   6072: iastore
    //   6073: dup
    //   6074: bipush #33
    //   6076: ldc 262144
    //   6078: iastore
    //   6079: dup
    //   6080: bipush #34
    //   6082: ldc 268701696
    //   6084: iastore
    //   6085: dup
    //   6086: bipush #35
    //   6088: sipush #4096
    //   6091: iastore
    //   6092: dup
    //   6093: bipush #36
    //   6095: bipush #64
    //   6097: iastore
    //   6098: dup
    //   6099: bipush #37
    //   6101: ldc 268697664
    //   6103: iastore
    //   6104: dup
    //   6105: bipush #38
    //   6107: sipush #4096
    //   6110: iastore
    //   6111: dup
    //   6112: bipush #39
    //   6114: ldc 266304
    //   6116: iastore
    //   6117: dup
    //   6118: bipush #40
    //   6120: ldc 268439552
    //   6122: iastore
    //   6123: dup
    //   6124: bipush #41
    //   6126: bipush #64
    //   6128: iastore
    //   6129: dup
    //   6130: bipush #42
    //   6132: ldc 268435520
    //   6134: iastore
    //   6135: dup
    //   6136: bipush #43
    //   6138: ldc 268697600
    //   6140: iastore
    //   6141: dup
    //   6142: bipush #44
    //   6144: ldc 268697664
    //   6146: iastore
    //   6147: dup
    //   6148: bipush #45
    //   6150: ldc 268435456
    //   6152: iastore
    //   6153: dup
    //   6154: bipush #46
    //   6156: ldc 262144
    //   6158: iastore
    //   6159: dup
    //   6160: bipush #47
    //   6162: ldc 268439616
    //   6164: iastore
    //   6165: dup
    //   6166: bipush #48
    //   6168: iconst_0
    //   6169: iastore
    //   6170: dup
    //   6171: bipush #49
    //   6173: ldc 268701760
    //   6175: iastore
    //   6176: dup
    //   6177: bipush #50
    //   6179: ldc 262208
    //   6181: iastore
    //   6182: dup
    //   6183: bipush #51
    //   6185: ldc 268435520
    //   6187: iastore
    //   6188: dup
    //   6189: bipush #52
    //   6191: ldc 268697600
    //   6193: iastore
    //   6194: dup
    //   6195: bipush #53
    //   6197: ldc 268439552
    //   6199: iastore
    //   6200: dup
    //   6201: bipush #54
    //   6203: ldc 268439616
    //   6205: iastore
    //   6206: dup
    //   6207: bipush #55
    //   6209: iconst_0
    //   6210: iastore
    //   6211: dup
    //   6212: bipush #56
    //   6214: ldc 268701760
    //   6216: iastore
    //   6217: dup
    //   6218: bipush #57
    //   6220: ldc 266240
    //   6222: iastore
    //   6223: dup
    //   6224: bipush #58
    //   6226: ldc 266240
    //   6228: iastore
    //   6229: dup
    //   6230: bipush #59
    //   6232: sipush #4160
    //   6235: iastore
    //   6236: dup
    //   6237: bipush #60
    //   6239: sipush #4160
    //   6242: iastore
    //   6243: dup
    //   6244: bipush #61
    //   6246: ldc 262208
    //   6248: iastore
    //   6249: dup
    //   6250: bipush #62
    //   6252: ldc 268435456
    //   6254: iastore
    //   6255: dup
    //   6256: bipush #63
    //   6258: ldc 268701696
    //   6260: iastore
    //   6261: astore #14
    //   6263: aload #4
    //   6265: arraylength
    //   6266: istore #15
    //   6268: iload #15
    //   6270: bipush #8
    //   6272: irem
    //   6273: ifeq -> 6297
    //   6276: new java/lang/Exception
    //   6279: dup
    //   6280: sipush #-5075
    //   6283: sipush #-4854
    //   6286: invokestatic a : (II)Ljava/lang/String;
    //   6289: invokespecial <init> : (Ljava/lang/String;)V
    //   6292: athrow
    //   6293: invokestatic a : (Ljava/lang/Throwable;)Ljava/lang/Throwable;
    //   6296: athrow
    //   6297: iconst_2
    //   6298: newarray int
    //   6300: astore #16
    //   6302: iload #15
    //   6304: newarray byte
    //   6306: astore #17
    //   6308: iload #15
    //   6310: bipush #8
    //   6312: idiv
    //   6313: istore #18
    //   6315: iconst_0
    //   6316: istore #19
    //   6318: iload #19
    //   6320: iload #18
    //   6322: if_icmpge -> 7240
    //   6325: iload #19
    //   6327: bipush #8
    //   6329: imul
    //   6330: istore #20
    //   6332: iconst_0
    //   6333: istore #21
    //   6335: iload #21
    //   6337: iconst_2
    //   6338: if_icmpge -> 6427
    //   6341: aload #16
    //   6343: iload #21
    //   6345: aload #4
    //   6347: iload #20
    //   6349: iload #21
    //   6351: iconst_4
    //   6352: imul
    //   6353: iadd
    //   6354: baload
    //   6355: sipush #255
    //   6358: iand
    //   6359: bipush #24
    //   6361: ishl
    //   6362: aload #4
    //   6364: iload #20
    //   6366: iload #21
    //   6368: iconst_4
    //   6369: imul
    //   6370: iadd
    //   6371: iconst_1
    //   6372: iadd
    //   6373: baload
    //   6374: sipush #255
    //   6377: iand
    //   6378: bipush #16
    //   6380: ishl
    //   6381: ior
    //   6382: aload #4
    //   6384: iload #20
    //   6386: iload #21
    //   6388: iconst_4
    //   6389: imul
    //   6390: iadd
    //   6391: iconst_2
    //   6392: iadd
    //   6393: baload
    //   6394: sipush #255
    //   6397: iand
    //   6398: bipush #8
    //   6400: ishl
    //   6401: ior
    //   6402: aload #4
    //   6404: iload #20
    //   6406: iload #21
    //   6408: iconst_4
    //   6409: imul
    //   6410: iadd
    //   6411: iconst_3
    //   6412: iadd
    //   6413: baload
    //   6414: sipush #255
    //   6417: iand
    //   6418: ior
    //   6419: iastore
    //   6420: iinc #21, 1
    //   6423: iload_2
    //   6424: ifeq -> 6335
    //   6427: iconst_0
    //   6428: istore #26
    //   6430: aload #16
    //   6432: iconst_0
    //   6433: iaload
    //   6434: istore #24
    //   6436: aload #16
    //   6438: iconst_1
    //   6439: iaload
    //   6440: istore #23
    //   6442: iload #24
    //   6444: iconst_4
    //   6445: iushr
    //   6446: iload #23
    //   6448: ixor
    //   6449: ldc 252645135
    //   6451: iand
    //   6452: istore #22
    //   6454: iload #23
    //   6456: iload #22
    //   6458: ixor
    //   6459: istore #23
    //   6461: iload #24
    //   6463: iload #22
    //   6465: iconst_4
    //   6466: ishl
    //   6467: ixor
    //   6468: istore #24
    //   6470: iload #24
    //   6472: bipush #16
    //   6474: iushr
    //   6475: iload #23
    //   6477: ixor
    //   6478: ldc 65535
    //   6480: iand
    //   6481: istore #22
    //   6483: iload #23
    //   6485: iload #22
    //   6487: ixor
    //   6488: istore #23
    //   6490: iload #24
    //   6492: iload #22
    //   6494: bipush #16
    //   6496: ishl
    //   6497: ixor
    //   6498: istore #24
    //   6500: iload #23
    //   6502: iconst_2
    //   6503: iushr
    //   6504: iload #24
    //   6506: ixor
    //   6507: ldc 858993459
    //   6509: iand
    //   6510: istore #22
    //   6512: iload #24
    //   6514: iload #22
    //   6516: ixor
    //   6517: istore #24
    //   6519: iload #23
    //   6521: iload #22
    //   6523: iconst_2
    //   6524: ishl
    //   6525: ixor
    //   6526: istore #23
    //   6528: iload #23
    //   6530: bipush #8
    //   6532: iushr
    //   6533: iload #24
    //   6535: ixor
    //   6536: ldc 16711935
    //   6538: iand
    //   6539: istore #22
    //   6541: iload #24
    //   6543: iload #22
    //   6545: ixor
    //   6546: istore #24
    //   6548: iload #23
    //   6550: iload #22
    //   6552: bipush #8
    //   6554: ishl
    //   6555: ixor
    //   6556: istore #23
    //   6558: iload #23
    //   6560: iconst_1
    //   6561: ishl
    //   6562: iload #23
    //   6564: bipush #31
    //   6566: iushr
    //   6567: iconst_1
    //   6568: iand
    //   6569: ior
    //   6570: istore #23
    //   6572: iload #24
    //   6574: iload #23
    //   6576: ixor
    //   6577: ldc -1431655766
    //   6579: iand
    //   6580: istore #22
    //   6582: iload #24
    //   6584: iload #22
    //   6586: ixor
    //   6587: istore #24
    //   6589: iload #23
    //   6591: iload #22
    //   6593: ixor
    //   6594: istore #23
    //   6596: iload #24
    //   6598: iconst_1
    //   6599: ishl
    //   6600: iload #24
    //   6602: bipush #31
    //   6604: iushr
    //   6605: iconst_1
    //   6606: iand
    //   6607: ior
    //   6608: istore #24
    //   6610: iconst_0
    //   6611: istore #25
    //   6613: iload #25
    //   6615: bipush #8
    //   6617: if_icmpge -> 6955
    //   6620: iload #23
    //   6622: bipush #28
    //   6624: ishl
    //   6625: iload #23
    //   6627: iconst_4
    //   6628: iushr
    //   6629: ior
    //   6630: istore #22
    //   6632: iload #22
    //   6634: aload #6
    //   6636: iload #26
    //   6638: iinc #26, 1
    //   6641: iaload
    //   6642: ixor
    //   6643: istore #22
    //   6645: aload #13
    //   6647: iload #22
    //   6649: bipush #63
    //   6651: iand
    //   6652: iaload
    //   6653: istore #21
    //   6655: iload #21
    //   6657: aload #11
    //   6659: iload #22
    //   6661: bipush #8
    //   6663: iushr
    //   6664: bipush #63
    //   6666: iand
    //   6667: iaload
    //   6668: ior
    //   6669: istore #21
    //   6671: iload #21
    //   6673: aload #9
    //   6675: iload #22
    //   6677: bipush #16
    //   6679: iushr
    //   6680: bipush #63
    //   6682: iand
    //   6683: iaload
    //   6684: ior
    //   6685: istore #21
    //   6687: iload #21
    //   6689: aload #7
    //   6691: iload #22
    //   6693: bipush #24
    //   6695: iushr
    //   6696: bipush #63
    //   6698: iand
    //   6699: iaload
    //   6700: ior
    //   6701: istore #21
    //   6703: iload #23
    //   6705: aload #6
    //   6707: iload #26
    //   6709: iinc #26, 1
    //   6712: iaload
    //   6713: ixor
    //   6714: istore #22
    //   6716: iload #21
    //   6718: aload #14
    //   6720: iload #22
    //   6722: bipush #63
    //   6724: iand
    //   6725: iaload
    //   6726: ior
    //   6727: istore #21
    //   6729: iload #21
    //   6731: aload #12
    //   6733: iload #22
    //   6735: bipush #8
    //   6737: iushr
    //   6738: bipush #63
    //   6740: iand
    //   6741: iaload
    //   6742: ior
    //   6743: istore #21
    //   6745: iload #21
    //   6747: aload #10
    //   6749: iload #22
    //   6751: bipush #16
    //   6753: iushr
    //   6754: bipush #63
    //   6756: iand
    //   6757: iaload
    //   6758: ior
    //   6759: istore #21
    //   6761: iload #21
    //   6763: aload #8
    //   6765: iload #22
    //   6767: bipush #24
    //   6769: iushr
    //   6770: bipush #63
    //   6772: iand
    //   6773: iaload
    //   6774: ior
    //   6775: istore #21
    //   6777: iload #24
    //   6779: iload #21
    //   6781: ixor
    //   6782: istore #24
    //   6784: iload #24
    //   6786: bipush #28
    //   6788: ishl
    //   6789: iload #24
    //   6791: iconst_4
    //   6792: iushr
    //   6793: ior
    //   6794: istore #22
    //   6796: iload #22
    //   6798: aload #6
    //   6800: iload #26
    //   6802: iinc #26, 1
    //   6805: iaload
    //   6806: ixor
    //   6807: istore #22
    //   6809: aload #13
    //   6811: iload #22
    //   6813: bipush #63
    //   6815: iand
    //   6816: iaload
    //   6817: istore #21
    //   6819: iload #21
    //   6821: aload #11
    //   6823: iload #22
    //   6825: bipush #8
    //   6827: iushr
    //   6828: bipush #63
    //   6830: iand
    //   6831: iaload
    //   6832: ior
    //   6833: istore #21
    //   6835: iload #21
    //   6837: aload #9
    //   6839: iload #22
    //   6841: bipush #16
    //   6843: iushr
    //   6844: bipush #63
    //   6846: iand
    //   6847: iaload
    //   6848: ior
    //   6849: istore #21
    //   6851: iload #21
    //   6853: aload #7
    //   6855: iload #22
    //   6857: bipush #24
    //   6859: iushr
    //   6860: bipush #63
    //   6862: iand
    //   6863: iaload
    //   6864: ior
    //   6865: istore #21
    //   6867: iload #24
    //   6869: aload #6
    //   6871: iload #26
    //   6873: iinc #26, 1
    //   6876: iaload
    //   6877: ixor
    //   6878: istore #22
    //   6880: iload #21
    //   6882: aload #14
    //   6884: iload #22
    //   6886: bipush #63
    //   6888: iand
    //   6889: iaload
    //   6890: ior
    //   6891: istore #21
    //   6893: iload #21
    //   6895: aload #12
    //   6897: iload #22
    //   6899: bipush #8
    //   6901: iushr
    //   6902: bipush #63
    //   6904: iand
    //   6905: iaload
    //   6906: ior
    //   6907: istore #21
    //   6909: iload #21
    //   6911: aload #10
    //   6913: iload #22
    //   6915: bipush #16
    //   6917: iushr
    //   6918: bipush #63
    //   6920: iand
    //   6921: iaload
    //   6922: ior
    //   6923: istore #21
    //   6925: iload #21
    //   6927: aload #8
    //   6929: iload #22
    //   6931: bipush #24
    //   6933: iushr
    //   6934: bipush #63
    //   6936: iand
    //   6937: iaload
    //   6938: ior
    //   6939: istore #21
    //   6941: iload #23
    //   6943: iload #21
    //   6945: ixor
    //   6946: istore #23
    //   6948: iinc #25, 1
    //   6951: iload_2
    //   6952: ifeq -> 6613
    //   6955: iload #23
    //   6957: bipush #31
    //   6959: ishl
    //   6960: iload #23
    //   6962: iconst_1
    //   6963: iushr
    //   6964: ior
    //   6965: istore #23
    //   6967: iload #24
    //   6969: iload #23
    //   6971: ixor
    //   6972: ldc -1431655766
    //   6974: iand
    //   6975: istore #22
    //   6977: iload #24
    //   6979: iload #22
    //   6981: ixor
    //   6982: istore #24
    //   6984: iload #23
    //   6986: iload #22
    //   6988: ixor
    //   6989: istore #23
    //   6991: iload #24
    //   6993: bipush #31
    //   6995: ishl
    //   6996: iload #24
    //   6998: iconst_1
    //   6999: iushr
    //   7000: ior
    //   7001: istore #24
    //   7003: iload #24
    //   7005: bipush #8
    //   7007: iushr
    //   7008: iload #23
    //   7010: ixor
    //   7011: ldc 16711935
    //   7013: iand
    //   7014: istore #22
    //   7016: iload #23
    //   7018: iload #22
    //   7020: ixor
    //   7021: istore #23
    //   7023: iload #24
    //   7025: iload #22
    //   7027: bipush #8
    //   7029: ishl
    //   7030: ixor
    //   7031: istore #24
    //   7033: iload #24
    //   7035: iconst_2
    //   7036: iushr
    //   7037: iload #23
    //   7039: ixor
    //   7040: ldc 858993459
    //   7042: iand
    //   7043: istore #22
    //   7045: iload #23
    //   7047: iload #22
    //   7049: ixor
    //   7050: istore #23
    //   7052: iload #24
    //   7054: iload #22
    //   7056: iconst_2
    //   7057: ishl
    //   7058: ixor
    //   7059: istore #24
    //   7061: iload #23
    //   7063: bipush #16
    //   7065: iushr
    //   7066: iload #24
    //   7068: ixor
    //   7069: ldc 65535
    //   7071: iand
    //   7072: istore #22
    //   7074: iload #24
    //   7076: iload #22
    //   7078: ixor
    //   7079: istore #24
    //   7081: iload #23
    //   7083: iload #22
    //   7085: bipush #16
    //   7087: ishl
    //   7088: ixor
    //   7089: istore #23
    //   7091: iload #23
    //   7093: iconst_4
    //   7094: iushr
    //   7095: iload #24
    //   7097: ixor
    //   7098: ldc 252645135
    //   7100: iand
    //   7101: istore #22
    //   7103: iload #24
    //   7105: iload #22
    //   7107: ixor
    //   7108: istore #24
    //   7110: iload #23
    //   7112: iload #22
    //   7114: iconst_4
    //   7115: ishl
    //   7116: ixor
    //   7117: istore #23
    //   7119: aload #16
    //   7121: iconst_0
    //   7122: iload #23
    //   7124: iastore
    //   7125: aload #16
    //   7127: iconst_1
    //   7128: iload #24
    //   7130: iastore
    //   7131: iload #19
    //   7133: bipush #8
    //   7135: imul
    //   7136: istore #27
    //   7138: iconst_0
    //   7139: istore #28
    //   7141: iload #28
    //   7143: iconst_2
    //   7144: if_icmpge -> 7233
    //   7147: aload #17
    //   7149: iload #27
    //   7151: iload #28
    //   7153: iconst_4
    //   7154: imul
    //   7155: iadd
    //   7156: aload #16
    //   7158: iload #28
    //   7160: iaload
    //   7161: bipush #24
    //   7163: iushr
    //   7164: i2b
    //   7165: bastore
    //   7166: aload #17
    //   7168: iload #27
    //   7170: iload #28
    //   7172: iconst_4
    //   7173: imul
    //   7174: iadd
    //   7175: iconst_1
    //   7176: iadd
    //   7177: aload #16
    //   7179: iload #28
    //   7181: iaload
    //   7182: bipush #16
    //   7184: iushr
    //   7185: i2b
    //   7186: bastore
    //   7187: aload #17
    //   7189: iload #27
    //   7191: iload #28
    //   7193: iconst_4
    //   7194: imul
    //   7195: iadd
    //   7196: iconst_2
    //   7197: iadd
    //   7198: aload #16
    //   7200: iload #28
    //   7202: iaload
    //   7203: bipush #8
    //   7205: iushr
    //   7206: i2b
    //   7207: bastore
    //   7208: aload #17
    //   7210: iload #27
    //   7212: iload #28
    //   7214: iconst_4
    //   7215: imul
    //   7216: iadd
    //   7217: iconst_3
    //   7218: iadd
    //   7219: aload #16
    //   7221: iload #28
    //   7223: iaload
    //   7224: i2b
    //   7225: bastore
    //   7226: iinc #28, 1
    //   7229: iload_2
    //   7230: ifeq -> 7141
    //   7233: iinc #19, 1
    //   7236: iload_2
    //   7237: ifeq -> 6318
    //   7240: aload #17
    //   7242: aload #17
    //   7244: arraylength
    //   7245: iconst_1
    //   7246: isub
    //   7247: baload
    //   7248: istore #19
    //   7250: aload #17
    //   7252: arraylength
    //   7253: iload #19
    //   7255: isub
    //   7256: newarray byte
    //   7258: astore #5
    //   7260: aload #17
    //   7262: arraylength
    //   7263: aload #5
    //   7265: arraylength
    //   7266: if_icmpge -> 7290
    //   7269: new java/lang/Exception
    //   7272: dup
    //   7273: sipush #-5084
    //   7276: sipush #9492
    //   7279: invokestatic a : (II)Ljava/lang/String;
    //   7282: invokespecial <init> : (Ljava/lang/String;)V
    //   7285: athrow
    //   7286: invokestatic a : (Ljava/lang/Throwable;)Ljava/lang/Throwable;
    //   7289: athrow
    //   7290: iconst_0
    //   7291: istore #20
    //   7293: iload #20
    //   7295: aload #5
    //   7297: arraylength
    //   7298: if_icmpge -> 7318
    //   7301: aload #5
    //   7303: iload #20
    //   7305: aload #17
    //   7307: iload #20
    //   7309: baload
    //   7310: bastore
    //   7311: iinc #20, 1
    //   7314: iload_2
    //   7315: ifeq -> 7293
    //   7318: getstatic burp/Ze_t.ZZ : Ljava/lang/String;
    //   7321: getstatic burp/Zgnp.Zm : Ljava/lang/Object;
    //   7324: checkcast java/math/BigInteger
    //   7327: invokevirtual intValue : ()I
    //   7330: bipush #32
    //   7332: irem
    //   7333: invokestatic abs : (I)I
    //   7336: invokevirtual charAt : (I)C
    //   7339: getstatic burp/Zsj5.Zn : Ljava/lang/String;
    //   7342: getstatic burp/Zlck.Zr : Ljava/lang/Object;
    //   7345: checkcast java/math/BigInteger
    //   7348: invokevirtual intValue : ()I
    //   7351: bipush #32
    //   7353: irem
    //   7354: invokestatic abs : (I)I
    //   7357: invokevirtual charAt : (I)C
    //   7360: if_icmpgt -> 7467
    //   7363: getstatic burp/Zgpp.Zm : Ljava/lang/String;
    //   7366: getstatic burp/Ztkh.Zh : Ljava/lang/Object;
    //   7369: checkcast java/math/BigInteger
    //   7372: invokevirtual intValue : ()I
    //   7375: bipush #32
    //   7377: irem
    //   7378: invokestatic abs : (I)I
    //   7381: invokevirtual charAt : (I)C
    //   7384: getstatic burp/Zs75.Zn : Ljava/lang/String;
    //   7387: getstatic burp/Zza8.Zh : Ljava/lang/Object;
    //   7390: checkcast java/math/BigInteger
    //   7393: invokevirtual intValue : ()I
    //   7396: bipush #32
    //   7398: irem
    //   7399: invokestatic abs : (I)I
    //   7402: invokevirtual charAt : (I)C
    //   7405: if_icmpgt -> 7467
    //   7408: goto -> 7415
    //   7411: invokestatic a : (Ljava/lang/Throwable;)Ljava/lang/Throwable;
    //   7414: athrow
    //   7415: getstatic burp/Zel.Zi : Ljava/lang/String;
    //   7418: getstatic burp/Zt9_.ZN : Ljava/lang/Object;
    //   7421: checkcast java/math/BigInteger
    //   7424: invokevirtual intValue : ()I
    //   7427: bipush #32
    //   7429: irem
    //   7430: invokestatic abs : (I)I
    //   7433: invokevirtual charAt : (I)C
    //   7436: getstatic burp/Ze6d.Zx : Ljava/lang/String;
    //   7439: getstatic burp/Ztsu.Zr : Ljava/lang/Object;
    //   7442: checkcast java/math/BigInteger
    //   7445: invokevirtual intValue : ()I
    //   7448: bipush #32
    //   7450: irem
    //   7451: invokestatic abs : (I)I
    //   7454: invokevirtual charAt : (I)C
    //   7457: if_icmpgt -> 7475
    //   7460: goto -> 7467
    //   7463: invokestatic a : (Ljava/lang/Throwable;)Ljava/lang/Throwable;
    //   7466: athrow
    //   7467: iconst_1
    //   7468: goto -> 7476
    //   7471: invokestatic a : (Ljava/lang/Throwable;)Ljava/lang/Throwable;
    //   7474: athrow
    //   7475: iconst_0
    //   7476: ireturn
    //   7477: astore_3
    //   7478: new java/lang/Exception
    //   7481: dup
    //   7482: aload_3
    //   7483: invokevirtual getMessage : ()Ljava/lang/String;
    //   7486: invokespecial <init> : (Ljava/lang/String;)V
    //   7489: athrow
    // Exception table:
    //   from	to	target	type
    //   4	7476	7477	java/lang/Throwable
    //   22	198	201	java/lang/Throwable
    //   168	235	238	java/lang/Throwable
    //   205	272	275	java/lang/Throwable
    //   242	309	312	java/lang/Throwable
    //   279	346	349	java/lang/Throwable
    //   316	383	386	java/lang/Throwable
    //   353	420	423	java/lang/Throwable
    //   390	457	460	java/lang/Throwable
    //   427	494	497	java/lang/Throwable
    //   464	531	534	java/lang/Throwable
    //   501	568	571	java/lang/Throwable
    //   538	605	608	java/lang/Throwable
    //   575	642	645	java/lang/Throwable
    //   612	679	682	java/lang/Throwable
    //   649	716	719	java/lang/Throwable
    //   686	753	756	java/lang/Throwable
    //   723	790	793	java/lang/Throwable
    //   760	827	830	java/lang/Throwable
    //   797	864	867	java/lang/Throwable
    //   834	901	904	java/lang/Throwable
    //   871	938	941	java/lang/Throwable
    //   908	975	978	java/lang/Throwable
    //   945	1012	1015	java/lang/Throwable
    //   982	1049	1052	java/lang/Throwable
    //   1019	1086	1089	java/lang/Throwable
    //   1056	1123	1126	java/lang/Throwable
    //   1093	1160	1163	java/lang/Throwable
    //   1130	1197	1200	java/lang/Throwable
    //   1167	1234	1237	java/lang/Throwable
    //   1204	1271	1274	java/lang/Throwable
    //   1241	1308	1311	java/lang/Throwable
    //   1278	1341	1344	java/lang/Throwable
    //   1548	1572	1575	java/lang/Throwable
    //   1646	1683	1683	java/lang/Throwable
    //   1687	1708	1708	java/lang/Throwable
    //   1712	1742	1742	java/lang/Throwable
    //   2252	2276	2279	java/lang/Throwable
    //   2350	2387	2387	java/lang/Throwable
    //   2391	2412	2412	java/lang/Throwable
    //   2416	2446	2446	java/lang/Throwable
    //   2674	2688	2688	java/lang/Throwable
    //   2699	2712	2715	java/lang/Throwable
    //   2704	2727	2730	java/lang/Throwable
    //   2719	2745	2748	java/lang/Throwable
    //   2734	2775	2778	java/lang/Throwable
    //   2841	2868	2871	java/lang/Throwable
    //   2858	2889	2892	java/lang/Throwable
    //   2875	2919	2922	java/lang/Throwable
    //   2896	2930	2930	java/lang/Throwable
    //   2941	2957	2960	java/lang/Throwable
    //   6268	6293	6293	java/lang/Throwable
    //   7260	7286	7286	java/lang/Throwable
    //   7318	7408	7411	java/lang/Throwable
    //   7363	7460	7463	java/lang/Throwable
    //   7415	7471	7471	java/lang/Throwable
  }
  
  static {
    // Byte code:
    //   0: bipush #13
    //   2: anewarray java/lang/String
    //   5: astore #5
    //   7: iconst_0
    //   8: istore_3
    //   9: ldc '&b80 SZOOm*XwGr=  gucJ]*_MyT;<t+jH\:SNW5a<y;x6[l7W]NDx kT\#a_XRn9fP.e zD2Q'2}Hc~\\tf\\t'\\\t?Q;cPx\\t)*baF2\\tqi/'
    //   11: dup
    //   12: astore_2
    //   13: invokevirtual length : ()I
    //   16: istore #4
    //   18: bipush #7
    //   20: istore_1
    //   21: iconst_m1
    //   22: istore_0
    //   23: bipush #62
    //   25: iinc #0, 1
    //   28: aload_2
    //   29: iload_0
    //   30: dup
    //   31: iload_1
    //   32: iadd
    //   33: invokevirtual substring : (II)Ljava/lang/String;
    //   36: iconst_m1
    //   37: goto -> 143
    //   40: aload #5
    //   42: swap
    //   43: iload_3
    //   44: iinc #3, 1
    //   47: swap
    //   48: aastore
    //   49: iload_0
    //   50: iload_1
    //   51: iadd
    //   52: dup
    //   53: istore_0
    //   54: iload #4
    //   56: if_icmpge -> 68
    //   59: aload_2
    //   60: iload_0
    //   61: invokevirtual charAt : (I)C
    //   64: istore_1
    //   65: goto -> 23
    //   68: ldc '*r|;d=y\\t1n#]'
    //   70: dup
    //   71: astore_2
    //   72: invokevirtual length : ()I
    //   75: istore #4
    //   77: bipush #19
    //   79: istore_1
    //   80: iconst_m1
    //   81: istore_0
    //   82: bipush #60
    //   84: iinc #0, 1
    //   87: aload_2
    //   88: iload_0
    //   89: dup
    //   90: iload_1
    //   91: iadd
    //   92: invokevirtual substring : (II)Ljava/lang/String;
    //   95: iconst_0
    //   96: goto -> 143
    //   99: aload #5
    //   101: swap
    //   102: iload_3
    //   103: iinc #3, 1
    //   106: swap
    //   107: aastore
    //   108: iload_0
    //   109: iload_1
    //   110: iadd
    //   111: dup
    //   112: istore_0
    //   113: iload #4
    //   115: if_icmpge -> 127
    //   118: aload_2
    //   119: iload_0
    //   120: invokevirtual charAt : (I)C
    //   123: istore_1
    //   124: goto -> 82
    //   127: aload #5
    //   129: putstatic burp/Zefo.a : [Ljava/lang/String;
    //   132: bipush #13
    //   134: anewarray java/lang/String
    //   137: putstatic burp/Zefo.b : [Ljava/lang/String;
    //   140: goto -> 300
    //   143: dup_x2
    //   144: pop
    //   145: invokevirtual toCharArray : ()[C
    //   148: dup_x1
    //   149: arraylength
    //   150: dup_x2
    //   151: pop
    //   152: iconst_0
    //   153: istore #6
    //   155: dup2_x1
    //   156: pop2
    //   157: dup_x2
    //   158: iconst_1
    //   159: if_icmpgt -> 259
    //   162: dup2
    //   163: swap
    //   164: iload #6
    //   166: dup2_x1
    //   167: caload
    //   168: swap
    //   169: iload #6
    //   171: bipush #7
    //   173: irem
    //   174: tableswitch default -> 241, 0 -> 212, 1 -> 217, 2 -> 221, 3 -> 226, 4 -> 231, 5 -> 236
    //   212: bipush #86
    //   214: goto -> 243
    //   217: iconst_3
    //   218: goto -> 243
    //   221: bipush #40
    //   223: goto -> 243
    //   226: bipush #22
    //   228: goto -> 243
    //   231: bipush #10
    //   233: goto -> 243
    //   236: bipush #117
    //   238: goto -> 243
    //   241: bipush #54
    //   243: ixor
    //   244: ixor
    //   245: i2c
    //   246: castore
    //   247: iinc #6, 1
    //   250: dup
    //   251: ifne -> 259
    //   254: dup2
    //   255: dup_x1
    //   256: goto -> 166
    //   259: dup2_x1
    //   260: pop2
    //   261: dup_x2
    //   262: iload #6
    //   264: if_icmpgt -> 162
    //   267: pop
    //   268: new java/lang/String
    //   271: dup_x1
    //   272: swap
    //   273: invokespecial <init> : ([C)V
    //   276: invokevirtual intern : ()Ljava/lang/String;
    //   279: swap
    //   280: pop
    //   281: swap
    //   282: tableswitch default -> 40, 0 -> 99
    //   300: sipush #-5085
    //   303: sipush #-18228
    //   306: invokestatic a : (II)Ljava/lang/String;
    //   309: putstatic burp/Zefo.Zb : Ljava/lang/String;
    //   312: new java/math/BigInteger
    //   315: dup
    //   316: bipush #32
    //   318: newarray byte
    //   320: dup
    //   321: iconst_0
    //   322: iconst_3
    //   323: bastore
    //   324: dup
    //   325: iconst_1
    //   326: iconst_4
    //   327: bastore
    //   328: dup
    //   329: iconst_2
    //   330: bipush #-93
    //   332: bastore
    //   333: dup
    //   334: iconst_3
    //   335: bipush #-51
    //   337: bastore
    //   338: dup
    //   339: iconst_4
    //   340: bipush #-74
    //   342: bastore
    //   343: dup
    //   344: iconst_5
    //   345: bipush #-95
    //   347: bastore
    //   348: dup
    //   349: bipush #6
    //   351: bipush #98
    //   353: bastore
    //   354: dup
    //   355: bipush #7
    //   357: bipush #90
    //   359: bastore
    //   360: dup
    //   361: bipush #8
    //   363: bipush #-68
    //   365: bastore
    //   366: dup
    //   367: bipush #9
    //   369: bipush #10
    //   371: bastore
    //   372: dup
    //   373: bipush #10
    //   375: bipush #78
    //   377: bastore
    //   378: dup
    //   379: bipush #11
    //   381: bipush #51
    //   383: bastore
    //   384: dup
    //   385: bipush #12
    //   387: bipush #-90
    //   389: bastore
    //   390: dup
    //   391: bipush #13
    //   393: bipush #-12
    //   395: bastore
    //   396: dup
    //   397: bipush #14
    //   399: bipush #11
    //   401: bastore
    //   402: dup
    //   403: bipush #15
    //   405: bipush #-55
    //   407: bastore
    //   408: dup
    //   409: bipush #16
    //   411: bipush #30
    //   413: bastore
    //   414: dup
    //   415: bipush #17
    //   417: bipush #-50
    //   419: bastore
    //   420: dup
    //   421: bipush #18
    //   423: bipush #49
    //   425: bastore
    //   426: dup
    //   427: bipush #19
    //   429: bipush #-63
    //   431: bastore
    //   432: dup
    //   433: bipush #20
    //   435: bipush #82
    //   437: bastore
    //   438: dup
    //   439: bipush #21
    //   441: bipush #-104
    //   443: bastore
    //   444: dup
    //   445: bipush #22
    //   447: bipush #54
    //   449: bastore
    //   450: dup
    //   451: bipush #23
    //   453: bipush #-74
    //   455: bastore
    //   456: dup
    //   457: bipush #24
    //   459: bipush #-6
    //   461: bastore
    //   462: dup
    //   463: bipush #25
    //   465: bipush #-126
    //   467: bastore
    //   468: dup
    //   469: bipush #26
    //   471: bipush #82
    //   473: bastore
    //   474: dup
    //   475: bipush #27
    //   477: bipush #-115
    //   479: bastore
    //   480: dup
    //   481: bipush #28
    //   483: bipush #-81
    //   485: bastore
    //   486: dup
    //   487: bipush #29
    //   489: bipush #-81
    //   491: bastore
    //   492: dup
    //   493: bipush #30
    //   495: bipush #102
    //   497: bastore
    //   498: dup
    //   499: bipush #31
    //   501: bipush #-47
    //   503: bastore
    //   504: invokespecial <init> : ([B)V
    //   507: putstatic burp/Zefo.ZW : Ljava/lang/Object;
    //   510: return
  }
  
  private static Throwable a(Throwable paramThrowable) {
    return paramThrowable;
  }
  
  private static String a(int paramInt1, int paramInt2) {
    int i = (paramInt1 ^ 0xFFFFEC26) & 0xFFFF;
    if (b[i] == null) {
      char[] arrayOfChar = a[i].toCharArray();
      switch (arrayOfChar[0] & 0xFF) {
        case 0:
        
        case 1:
        
        case 2:
        
        case 3:
        
        case 4:
        
        case 5:
        
        case 6:
        
        case 7:
        
        case 8:
        
        case 9:
        
        case 10:
        
        case 11:
        
        case 12:
        
        case 13:
        
        case 14:
        
        case 15:
        
        case 16:
        
        case 17:
        
        case 18:
        
        case 19:
        
        case 20:
        
        case 21:
        
        case 22:
        
        case 23:
        
        case 24:
        
        case 25:
        
        case 26:
        
        case 27:
        
        case 28:
        
        case 29:
        
        case 30:
        
        case 31:
        
        case 32:
        
        case 33:
        
        case 34:
        
        case 35:
        
        case 36:
        
        case 37:
        
        case 38:
        
        case 39:
        
        case 40:
        
        case 41:
        
        case 42:
        
        case 43:
        
        case 44:
        
        case 45:
        
        case 46:
        
        case 47:
        
        case 48:
        
        case 49:
        
        case 50:
        
        case 51:
        
        case 52:
        
        case 53:
        
        case 54:
        
        case 55:
        
        case 56:
        
        case 57:
        
        case 58:
        
        case 59:
        
        case 60:
        
        case 61:
        
        case 62:
        
        case 63:
        
        case 64:
        
        case 65:
        
        case 66:
        
        case 67:
        
        case 68:
        
        case 69:
        
        case 70:
        
        case 71:
        
        case 72:
        
        case 73:
        
        case 74:
        
        case 75:
        
        case 76:
        
        case 77:
        
        case 78:
        
        case 79:
        
        case 80:
        
        case 81:
        
        case 82:
        
        case 83:
        
        case 84:
        
        case 85:
        
        case 86:
        
        case 87:
        
        case 88:
        
        case 89:
        
        case 90:
        
        case 91:
        
        case 92:
        
        case 93:
        
        case 94:
        
        case 95:
        
        case 96:
        
        case 97:
        
        case 98:
        
        case 99:
        
        case 100:
        
        case 101:
        
        case 102:
        
        case 103:
        
        case 104:
        
        case 105:
        
        case 106:
        
        case 107:
        
        case 108:
        
        case 109:
        
        case 110:
        
        case 111:
        
        case 112:
        
        case 113:
        
        case 114:
        
        case 115:
        
        case 116:
        
        case 117:
        
        case 118:
        
        case 119:
        
        case 120:
        
        case 121:
        
        case 122:
        
        case 123:
        
        case 124:
        
        case 125:
        
        case 126:
        
        case 127:
        
        case 128:
        
        case 129:
        
        case 130:
        
        case 131:
        
        case 132:
        
        case 133:
        
        case 134:
        
        case 135:
        
        case 136:
        
        case 137:
        
        case 138:
        
        case 139:
        
        case 140:
        
        case 141:
        
        case 142:
        
        case 143:
        
        case 144:
        
        case 145:
        
        case 146:
        
        case 147:
        
        case 148:
        
        case 149:
        
        case 150:
        
        case 151:
        
        case 152:
        
        case 153:
        
        case 154:
        
        case 155:
        
        case 156:
        
        case 157:
        
        case 158:
        
        case 159:
        
        case 160:
        
        case 161:
        
        case 162:
        
        case 163:
        
        case 164:
        
        case 165:
        
        case 166:
        
        case 167:
        
        case 168:
        
        case 169:
        
        case 170:
        
        case 171:
        
        case 172:
        
        case 173:
        
        case 174:
        
        case 175:
        
        case 176:
        
        case 177:
        
        case 178:
        
        case 179:
        
        case 180:
        
        case 181:
        
        case 182:
        
        case 183:
        
        case 184:
        
        case 185:
        
        case 186:
        
        case 187:
        
        case 188:
        
        case 189:
        
        case 190:
        
        case 191:
        
        case 192:
        
        case 193:
        
        case 194:
        
        case 195:
        
        case 196:
        
        case 197:
        
        case 198:
        
        case 199:
        
        case 200:
        
        case 201:
        
        case 202:
        
        case 203:
        
        case 204:
        
        case 205:
        
        case 206:
        
        case 207:
        
        case 208:
        
        case 209:
        
        case 210:
        
        case 211:
        
        case 212:
        
        case 213:
        
        case 214:
        
        case 215:
        
        case 216:
        
        case 217:
        
        case 218:
        
        case 219:
        
        case 220:
        
        case 221:
        
        case 222:
        
        case 223:
        
        case 224:
        
        case 225:
        
        case 226:
        
        case 227:
        
        case 228:
        
        case 229:
        
        case 230:
        
        case 231:
        
        case 232:
        
        case 233:
        
        case 234:
        
        case 235:
        
        case 236:
        
        case 237:
        
        case 238:
        
        case 239:
        
        case 240:
        
        case 241:
        
        case 242:
        
        case 243:
        
        case 244:
        
        case 245:
        
        case 246:
        
        case 247:
        
        case 248:
        
        case 249:
        
        case 250:
        
        case 251:
        
        case 252:
        
        case 253:
        
        case 254:
        
        default:
          break;
      } 
      char c = '';
      int j = (paramInt2 & 0xFF) - c;
      if (j < 0)
        j += 256; 
      int k = ((paramInt2 & 0xFFFF) >>> 8) - c;
      if (k < 0)
        k += 256; 
      for (byte b = 0; b < arrayOfChar.length; b++) {
        int m = b % 2;
        if (m == 0) {
          arrayOfChar[b] = (char)(arrayOfChar[b] ^ j);
          j = ((j >>> 3 | j << 5) ^ arrayOfChar[b]) & 0xFF;
        } else {
          arrayOfChar[b] = (char)(arrayOfChar[b] ^ k);
          k = ((k >>> 3 | k << 5) ^ arrayOfChar[b]) & 0xFF;
        } 
      } 
      b[i] = (new String(arrayOfChar)).intern();
    } 
    return b[i];
  }
}


/* Location:              C:\Program Files\BurpSuitePro\burpsuite_pro.jar!\burp\Zefo.class
 * Java compiler version: 21 (65.0)
 * JD-Core Version:       1.1.3
 */