package burp;

import burp.api.montoya.MontoyaApi;
import burp.api.montoya.internal.MontoyaObjectFactory;
import burp.api.montoya.utilities.Utilities;
import java.util.Objects;

class Zejw {
  private final Zz0n Zw;
  
  private final Zt4u Zx;
  
  private final Zgbj ZJ;
  
  private final Zt8u ZK;
  
  private final Zxgc ZB;
  
  private final Zgzy ZL;
  
  private final Zerg ZD;
  
  private final Ztwv Zn;
  
  private final Zr_4 ZZ;
  
  private final Zr_4 Zh;
  
  private final Zbnt ZF;
  
  private final Zslu ZC;
  
  private final Zee5 ZM;
  
  private final Zm6x Zt;
  
  private final Zgb6 Zg;
  
  private final Zkh3 Zc;
  
  private final Zskl Zm;
  
  private final Zlxz ZY;
  
  private final Zm37 Zq;
  
  private final Ztcy Zy;
  
  private final Zbiv ZU;
  
  private final Zrny Zi;
  
  private final Zzg2 Zk;
  
  private final Zkl6 ZH;
  
  private final Zr1m ZG;
  
  private final Zsuv ZN;
  
  private final Zm5z Zl;
  
  private final Zxlq ZX;
  
  private final Zzls ZP;
  
  private final Zgj2 Zs;
  
  private final Zgs1 ZE;
  
  private final Zskh ZR;
  
  private final Zzpk Zz;
  
  private final Zb4u Za;
  
  private final Zrag ZO;
  
  private final Zdy ZI;
  
  private final MontoyaObjectFactory Zp;
  
  private final Utilities ZA;
  
  private static final String[] a;
  
  private static final String[] b;
  
  Zejw(Zz0n paramZz0n, Zt4u paramZt4u, Zgbj paramZgbj, Zt8u paramZt8u, Zxgc paramZxgc, Zgzy paramZgzy, Zerg paramZerg, Ztwv paramZtwv, Zr_4 paramZr_41, Zr_4 paramZr_42, Zbnt paramZbnt, Zslu paramZslu, Zlxz paramZlxz, Zm37 paramZm37, Ztcy paramZtcy, Zbiv paramZbiv, Zrny paramZrny, Zzg2 paramZzg2, Zkl6 paramZkl6, Zr1m paramZr1m, Zsuv paramZsuv, Zm5z paramZm5z, Zxlq paramZxlq, Zzls paramZzls, Zgj2 paramZgj2, Zgs1 paramZgs1, Zskh paramZskh, Zzpk paramZzpk, Zb4u paramZb4u, Zs0n paramZs0n, Zkh3 paramZkh3, Zrag paramZrag, Zgb6 paramZgb6, MontoyaObjectFactory paramMontoyaObjectFactory, Zm6x paramZm6x) {
    this.Zw = paramZz0n;
    this.Zx = paramZt4u;
    this.ZJ = paramZgbj;
    this.ZK = paramZt8u;
    this.ZB = paramZxgc;
    this.ZL = paramZgzy;
    this.ZD = paramZerg;
    this.Zn = paramZtwv;
    this.ZZ = paramZr_41;
    this.Zh = paramZr_42;
    this.ZF = paramZbnt;
    this.ZC = paramZslu;
    this.ZY = paramZlxz;
    this.Zq = paramZm37;
    this.Zy = paramZtcy;
    this.ZU = paramZbiv;
    this.Zi = paramZrny;
    this.Zk = paramZzg2;
    this.ZH = paramZkl6;
    this.ZG = paramZr1m;
    this.ZN = paramZsuv;
    this.Zl = paramZm5z;
    this.ZX = paramZxlq;
    this.ZP = paramZzls;
    this.Zs = paramZgj2;
    this.ZE = paramZgs1;
    this.ZR = paramZskh;
    this.Zz = paramZzpk;
    this.Za = paramZb4u;
    this.Zm = paramZs0n;
    this.Zp = paramMontoyaObjectFactory;
    this.Zc = paramZkh3;
    this.ZO = paramZrag;
    this.Zg = paramZgb6;
    this.ZI = new Zdy(paramZgb6);
    this.ZM = new Zee5(paramZz0n.ZM(), paramZz0n.ZR());
    this.Zt = paramZm6x;
    this.ZA = (new Zzss(paramMontoyaObjectFactory)).ZN();
  }
  
  Zgvo Zy(Zlz3 paramZlz3, Zeu1 paramZeu1) {
    Zbz2 zbz2 = new Zbz2(paramZlz3.ZC, this.ZK);
    Zxdn zxdn = new Zxdn(this.ZR, paramZeu1);
    Zmz6 zmz6 = Zh();
    Zzxi zzxi = this.Zw.Zr();
    Objects.requireNonNull(paramZeu1);
    Ze2 ze2 = new Ze2(this.ZR, paramZeu1::ZN);
    int i = Zl9.ZK();
    Zmz4 zmz4 = new Zmz4(zxdn, new Zzw_(paramZlz3, this.ZF, this.ZC, ze2), new Zs01(paramZlz3, this.ZX, this.ZP, this.Zs, ze2, new Zl8u(this.ZB), new Zzww(paramZlz3), this.ZI), new Zzf(this.ZF, new Zx5a(this.ZL.Zh().Zz()), paramZlz3, ze2, this.Zm, this.Za, this.ZH.ZH()), new Zgfn(paramZlz3.ZC, this.Zx.ZN().Zvo(), zbz2, this.ZF, this.ZZ, this.Zh, this.ZH.ZH(), this.ZC), new Zeqv(this.ZD.ZJ(), paramZlz3, ze2, this.Zm), new Zz3a(this.ZU, this.ZH, this.ZF, this.ZZ, this.ZN, this.Zq, this.Zy, paramZlz3, this.Zl, ze2, this.ZD.Zk(), this.Zm, new Zg6g(this.ZD.ZM()), this.Zt), this.ZA, new Zzr4(this.ZF, this.ZD.Zm()), new Zth9(this.ZD.ZH()), new Zc5(this.ZF, paramZlz3, ze2, this.ZD.Zg()), new Zr01(this.ZD.ZA(), this.Zi, zmz6, this.Zh, this.ZF, this.Zn, this.ZH, paramZeu1, this.Zm, this.Zt), new Zsz_(this.ZY, new Zkam(this.ZD.ZC()), this.Zg, this.ZF, this.ZZ, this.Zm), new Zboj(this.ZD.Za()), new Ztuy(zxdn, this.ZJ, zzxi, this.ZG, this.ZE, this.ZO), new Zl3k(paramZeu1, paramZlz3, this.Zz, this.ZM, ze2), new Zk5l(paramZlz3, ze2, new Zzus(this.Zc, this.ZF, new Ze2b(this.Zw.ZU()), this.Zm, this.Zp, this.ZH.ZH())), new Zm9f(this.ZF, this.ZD.Ze()), new Zxxu(this.Zx.ZN()));
    MontoyaApi montoyaApi = ze2.<MontoyaApi>Zk(zmz4, MontoyaApi.class);
    MontoyaObjectFactory montoyaObjectFactory = ze2.<MontoyaObjectFactory>Zk(this.Zp, MontoyaObjectFactory.class);
    if (i == 0)
      Zbqc.Zr(new Zbqc[5]); 
    return new Zgvo(montoyaApi, montoyaObjectFactory);
  }
  
  private Zmz6 Zh() {
    Zb4g zb4g = this.Zh.<Zb4g>ZH(new Zkie(0));
    Zx_7 zx_7 = Zx_7.ZM(this.Zh);
    Zmj1 zmj1 = this.ZZ.<Zmj1>ZH(new Zmo1(Zz5.ZO.Zf()));
    Zz1i zz1i = this.Zh.<Zz1i>ZH(new Zbuf(zx_7, zmj1));
    Zr5h zr5h = this.Zh.<Zr5h>ZH(new Zs21(0, Zg1j.Zo(), a(30122, 23896), a(30123, -11587), zz1i, zb4g, null));
    Zkq4 zkq4 = Zkq4.Zk(zz1i, false);
    Ztos<Zt3y> ztos = new Ztos<>(Zt1o.Zn());
    ztos.ZE(Zt1o.Zt, zr5h::lambda$buildExtensionIssueReporter$1);
    return this.Zk.Zy(zr5h, zkq4, (Ztos)ztos, this.Zi);
  }
  
  private static void lambda$buildExtensionIssueReporter$1(Zr5h paramZr5h, Zxr8 paramZxr8) {
    paramZxr8.ZP(paramZr5h::lambda$buildExtensionIssueReporter$0);
  }
  
  private static void lambda$buildExtensionIssueReporter$0(Zr5h paramZr5h, Zebg paramZebg) {
    Zefk zefk = paramZr5h.Zdm().ZHD();
    zefk.ZbB(paramZebg.ZaK());
    zefk.Zbp(paramZebg.ZaU());
    zefk.Zb8(paramZebg.Za8());
    zefk.ZbO(paramZebg.Zab());
  }
  
  static {
    // Byte code:
    //   0: iconst_2
    //   1: anewarray java/lang/String
    //   4: astore #5
    //   6: iconst_0
    //   7: istore_3
    //   8: ldc '?fìj^ÔgqppßPè¾Lü|²âÑø\\n¶$ëoe»¼'
    //   10: dup
    //   11: astore_2
    //   12: invokevirtual length : ()I
    //   15: istore #4
    //   17: bipush #20
    //   19: istore_1
    //   20: iconst_m1
    //   21: istore_0
    //   22: bipush #10
    //   24: iinc #0, 1
    //   27: aload_2
    //   28: iload_0
    //   29: dup
    //   30: iload_1
    //   31: iadd
    //   32: invokevirtual substring : (II)Ljava/lang/String;
    //   35: iconst_m1
    //   36: goto -> 82
    //   39: aload #5
    //   41: swap
    //   42: iload_3
    //   43: iinc #3, 1
    //   46: swap
    //   47: aastore
    //   48: iload_0
    //   49: iload_1
    //   50: iadd
    //   51: dup
    //   52: istore_0
    //   53: iload #4
    //   55: if_icmpge -> 67
    //   58: aload_2
    //   59: iload_0
    //   60: invokevirtual charAt : (I)C
    //   63: istore_1
    //   64: goto -> 22
    //   67: aload #5
    //   69: putstatic burp/Zejw.a : [Ljava/lang/String;
    //   72: iconst_2
    //   73: anewarray java/lang/String
    //   76: putstatic burp/Zejw.b : [Ljava/lang/String;
    //   79: goto -> 227
    //   82: dup_x2
    //   83: pop
    //   84: invokevirtual toCharArray : ()[C
    //   87: dup_x1
    //   88: arraylength
    //   89: dup_x2
    //   90: pop
    //   91: iconst_0
    //   92: istore #6
    //   94: dup2_x1
    //   95: pop2
    //   96: dup_x2
    //   97: iconst_1
    //   98: if_icmpgt -> 200
    //   101: dup2
    //   102: swap
    //   103: iload #6
    //   105: dup2_x1
    //   106: caload
    //   107: swap
    //   108: iload #6
    //   110: bipush #7
    //   112: irem
    //   113: tableswitch default -> 182, 0 -> 152, 1 -> 157, 2 -> 162, 3 -> 167, 4 -> 172, 5 -> 177
    //   152: bipush #31
    //   154: goto -> 184
    //   157: bipush #39
    //   159: goto -> 184
    //   162: bipush #41
    //   164: goto -> 184
    //   167: bipush #12
    //   169: goto -> 184
    //   172: bipush #82
    //   174: goto -> 184
    //   177: bipush #9
    //   179: goto -> 184
    //   182: bipush #59
    //   184: ixor
    //   185: ixor
    //   186: i2c
    //   187: castore
    //   188: iinc #6, 1
    //   191: dup
    //   192: ifne -> 200
    //   195: dup2
    //   196: dup_x1
    //   197: goto -> 105
    //   200: dup2_x1
    //   201: pop2
    //   202: dup_x2
    //   203: iload #6
    //   205: if_icmpgt -> 101
    //   208: pop
    //   209: new java/lang/String
    //   212: dup_x1
    //   213: swap
    //   214: invokespecial <init> : ([C)V
    //   217: invokevirtual intern : ()Ljava/lang/String;
    //   220: swap
    //   221: pop
    //   222: swap
    //   223: pop
    //   224: goto -> 39
    //   227: return
  }
  
  private static String a(int paramInt1, int paramInt2) {
    int i = (paramInt1 ^ 0x75AA) & 0xFFFF;
    if (b[i] == null) {
      char[] arrayOfChar = a[i].toCharArray();
      switch (arrayOfChar[0] & 0xFF) {
        case 0:
        
        case 1:
        
        case 2:
        
        case 3:
        
        case 4:
        
        case 5:
        
        case 6:
        
        case 7:
        
        case 8:
        
        case 9:
        
        case 10:
        
        case 11:
        
        case 12:
        
        case 13:
        
        case 14:
        
        case 15:
        
        case 16:
        
        case 17:
        
        case 18:
        
        case 19:
        
        case 20:
        
        case 21:
        
        case 22:
        
        case 23:
        
        case 24:
        
        case 25:
        
        case 26:
        
        case 27:
        
        case 28:
        
        case 29:
        
        case 30:
        
        case 31:
        
        case 32:
        
        case 33:
        
        case 34:
        
        case 35:
        
        case 36:
        
        case 37:
        
        case 38:
        
        case 39:
        
        case 40:
        
        case 41:
        
        case 42:
        
        case 43:
        
        case 44:
        
        case 45:
        
        case 46:
        
        case 47:
        
        case 48:
        
        case 49:
        
        case 50:
        
        case 51:
        
        case 52:
        
        case 53:
        
        case 54:
        
        case 55:
        
        case 56:
        
        case 57:
        
        case 58:
        
        case 59:
        
        case 60:
        
        case 61:
        
        case 62:
        
        case 63:
        
        case 64:
        
        case 65:
        
        case 66:
        
        case 67:
        
        case 68:
        
        case 69:
        
        case 70:
        
        case 71:
        
        case 72:
        
        case 73:
        
        case 74:
        
        case 75:
        
        case 76:
        
        case 77:
        
        case 78:
        
        case 79:
        
        case 80:
        
        case 81:
        
        case 82:
        
        case 83:
        
        case 84:
        
        case 85:
        
        case 86:
        
        case 87:
        
        case 88:
        
        case 89:
        
        case 90:
        
        case 91:
        
        case 92:
        
        case 93:
        
        case 94:
        
        case 95:
        
        case 96:
        
        case 97:
        
        case 98:
        
        case 99:
        
        case 100:
        
        case 101:
        
        case 102:
        
        case 103:
        
        case 104:
        
        case 105:
        
        case 106:
        
        case 107:
        
        case 108:
        
        case 109:
        
        case 110:
        
        case 111:
        
        case 112:
        
        case 113:
        
        case 114:
        
        case 115:
        
        case 116:
        
        case 117:
        
        case 118:
        
        case 119:
        
        case 120:
        
        case 121:
        
        case 122:
        
        case 123:
        
        case 124:
        
        case 125:
        
        case 126:
        
        case 127:
        
        case 128:
        
        case 129:
        
        case 130:
        
        case 131:
        
        case 132:
        
        case 133:
        
        case 134:
        
        case 135:
        
        case 136:
        
        case 137:
        
        case 138:
        
        case 139:
        
        case 140:
        
        case 141:
        
        case 142:
        
        case 143:
        
        case 144:
        
        case 145:
        
        case 146:
        
        case 147:
        
        case 148:
        
        case 149:
        
        case 150:
        
        case 151:
        
        case 152:
        
        case 153:
        
        case 154:
        
        case 155:
        
        case 156:
        
        case 157:
        
        case 158:
        
        case 159:
        
        case 160:
        
        case 161:
        
        case 162:
        
        case 163:
        
        case 164:
        
        case 165:
        
        case 166:
        
        case 167:
        
        case 168:
        
        case 169:
        
        case 170:
        
        case 171:
        
        case 172:
        
        case 173:
        
        case 174:
        
        case 175:
        
        case 176:
        
        case 177:
        
        case 178:
        
        case 179:
        
        case 180:
        
        case 181:
        
        case 182:
        
        case 183:
        
        case 184:
        
        case 185:
        
        case 186:
        
        case 187:
        
        case 188:
        
        case 189:
        
        case 190:
        
        case 191:
        
        case 192:
        
        case 193:
        
        case 194:
        
        case 195:
        
        case 196:
        
        case 197:
        
        case 198:
        
        case 199:
        
        case 200:
        
        case 201:
        
        case 202:
        
        case 203:
        
        case 204:
        
        case 205:
        
        case 206:
        
        case 207:
        
        case 208:
        
        case 209:
        
        case 210:
        
        case 211:
        
        case 212:
        
        case 213:
        
        case 214:
        
        case 215:
        
        case 216:
        
        case 217:
        
        case 218:
        
        case 219:
        
        case 220:
        
        case 221:
        
        case 222:
        
        case 223:
        
        case 224:
        
        case 225:
        
        case 226:
        
        case 227:
        
        case 228:
        
        case 229:
        
        case 230:
        
        case 231:
        
        case 232:
        
        case 233:
        
        case 234:
        
        case 235:
        
        case 236:
        
        case 237:
        
        case 238:
        
        case 239:
        
        case 240:
        
        case 241:
        
        case 242:
        
        case 243:
        
        case 244:
        
        case 245:
        
        case 246:
        
        case 247:
        
        case 248:
        
        case 249:
        
        case 250:
        
        case 251:
        
        case 252:
        
        case 253:
        
        case 254:
        
        default:
          break;
      } 
      byte b1 = 86;
      int j = (paramInt2 & 0xFF) - b1;
      if (j < 0)
        j += 256; 
      int k = ((paramInt2 & 0xFFFF) >>> 8) - b1;
      if (k < 0)
        k += 256; 
      for (byte b2 = 0; b2 < arrayOfChar.length; b2++) {
        int m = b2 % 2;
        if (m == 0) {
          arrayOfChar[b2] = (char)(arrayOfChar[b2] ^ j);
          j = ((j >>> 3 | j << 5) ^ arrayOfChar[b2]) & 0xFF;
        } else {
          arrayOfChar[b2] = (char)(arrayOfChar[b2] ^ k);
          k = ((k >>> 3 | k << 5) ^ arrayOfChar[b2]) & 0xFF;
        } 
      } 
      b[i] = (new String(arrayOfChar)).intern();
    } 
    return b[i];
  }
}


/* Location:              C:\Program Files\BurpSuitePro\burpsuite_pro.jar!\burp\Zejw.class
 * Java compiler version: 21 (65.0)
 * JD-Core Version:       1.1.3
 */