package burp;

import java.math.BigInteger;

class Zek4 extends ClassLoader {
  static Object ZR;
  
  static String Zo;
  
  private static final String[] a;
  
  private static final String[] b;
  
  static void Zh(Object[] paramArrayOfObject, Object paramObject) throws Throwable {}
  
  static void ZQ(Object paramObject) {
    Zr02.ZG = a(27768, 28782);
    Zr02.ZB = new BigInteger(a(27771, -3211));
    boolean bool = Zt2e.ZK();
    try {
      try {
        if (Zewr.ZW.charAt(Math.abs(((BigInteger)Zrl5.ZI).intValue() % 32)) <= Zr17.Zu.charAt(Math.abs(((BigInteger)Zx4u.Zn).intValue() % 32))) {
          try {
            Zztx.ZR(Class.forName(a(27769, 21771)));
            if (bool)
              Zxp1.Zq(Class.forName(a(27770, 31964))); 
          } catch (Throwable throwable) {
            throw a(null);
          } 
          return;
        } 
      } catch (Throwable throwable) {
        throw a(null);
      } 
      Zxp1.Zq(Class.forName(a(27770, 31964)));
    } catch (Throwable throwable) {}
  }
  
  static boolean ZB(Object[] paramArrayOfObject, Object paramObject) throws Throwable {
    // Byte code:
    //   0: invokestatic ZK : ()Z
    //   3: istore_2
    //   4: new java/lang/StringBuilder
    //   7: dup
    //   8: invokespecial <init> : ()V
    //   11: astore_3
    //   12: iconst_0
    //   13: istore #4
    //   15: iload #4
    //   17: bipush #32
    //   19: if_icmpge -> 1355
    //   22: iload #4
    //   24: tableswitch default -> 1348, 0 -> 168, 1 -> 205, 2 -> 242, 3 -> 279, 4 -> 316, 5 -> 353, 6 -> 390, 7 -> 427, 8 -> 464, 9 -> 501, 10 -> 538, 11 -> 575, 12 -> 612, 13 -> 649, 14 -> 686, 15 -> 723, 16 -> 760, 17 -> 797, 18 -> 834, 19 -> 871, 20 -> 908, 21 -> 945, 22 -> 982, 23 -> 1019, 24 -> 1056, 25 -> 1093, 26 -> 1130, 27 -> 1167, 28 -> 1204, 29 -> 1241, 30 -> 1278, 31 -> 1315
    //   168: aload_3
    //   169: getstatic burp/Zeig.Zg : Ljava/lang/String;
    //   172: getstatic burp/Zbwj.ZW : Ljava/lang/Object;
    //   175: checkcast java/math/BigInteger
    //   178: invokevirtual intValue : ()I
    //   181: bipush #32
    //   183: irem
    //   184: invokestatic abs : (I)I
    //   187: invokevirtual charAt : (I)C
    //   190: invokevirtual append : (C)Ljava/lang/StringBuilder;
    //   193: pop
    //   194: iload_2
    //   195: ifeq -> 1348
    //   198: goto -> 205
    //   201: invokestatic a : (Ljava/lang/Throwable;)Ljava/lang/Throwable;
    //   204: athrow
    //   205: aload_3
    //   206: getstatic burp/Zmz.Zp : Ljava/lang/String;
    //   209: getstatic burp/Zrzg.ZA : Ljava/lang/Object;
    //   212: checkcast java/math/BigInteger
    //   215: invokevirtual intValue : ()I
    //   218: bipush #32
    //   220: irem
    //   221: invokestatic abs : (I)I
    //   224: invokevirtual charAt : (I)C
    //   227: invokevirtual append : (C)Ljava/lang/StringBuilder;
    //   230: pop
    //   231: iload_2
    //   232: ifeq -> 1348
    //   235: goto -> 242
    //   238: invokestatic a : (Ljava/lang/Throwable;)Ljava/lang/Throwable;
    //   241: athrow
    //   242: aload_3
    //   243: getstatic burp/Zry1.Zk : Ljava/lang/String;
    //   246: getstatic burp/Ztvy.ZH : Ljava/lang/Object;
    //   249: checkcast java/math/BigInteger
    //   252: invokevirtual intValue : ()I
    //   255: bipush #32
    //   257: irem
    //   258: invokestatic abs : (I)I
    //   261: invokevirtual charAt : (I)C
    //   264: invokevirtual append : (C)Ljava/lang/StringBuilder;
    //   267: pop
    //   268: iload_2
    //   269: ifeq -> 1348
    //   272: goto -> 279
    //   275: invokestatic a : (Ljava/lang/Throwable;)Ljava/lang/Throwable;
    //   278: athrow
    //   279: aload_3
    //   280: getstatic burp/Zbli.ZW : Ljava/lang/String;
    //   283: getstatic burp/Zgu4.Zs : Ljava/lang/Object;
    //   286: checkcast java/math/BigInteger
    //   289: invokevirtual intValue : ()I
    //   292: bipush #32
    //   294: irem
    //   295: invokestatic abs : (I)I
    //   298: invokevirtual charAt : (I)C
    //   301: invokevirtual append : (C)Ljava/lang/StringBuilder;
    //   304: pop
    //   305: iload_2
    //   306: ifeq -> 1348
    //   309: goto -> 316
    //   312: invokestatic a : (Ljava/lang/Throwable;)Ljava/lang/Throwable;
    //   315: athrow
    //   316: aload_3
    //   317: getstatic burp/Zos.Za : Ljava/lang/String;
    //   320: getstatic burp/Ztle.ZP : Ljava/lang/Object;
    //   323: checkcast java/math/BigInteger
    //   326: invokevirtual intValue : ()I
    //   329: bipush #32
    //   331: irem
    //   332: invokestatic abs : (I)I
    //   335: invokevirtual charAt : (I)C
    //   338: invokevirtual append : (C)Ljava/lang/StringBuilder;
    //   341: pop
    //   342: iload_2
    //   343: ifeq -> 1348
    //   346: goto -> 353
    //   349: invokestatic a : (Ljava/lang/Throwable;)Ljava/lang/Throwable;
    //   352: athrow
    //   353: aload_3
    //   354: getstatic burp/Zkdq.ZZ : Ljava/lang/String;
    //   357: getstatic burp/Zb0q.ZK : Ljava/lang/Object;
    //   360: checkcast java/math/BigInteger
    //   363: invokevirtual intValue : ()I
    //   366: bipush #32
    //   368: irem
    //   369: invokestatic abs : (I)I
    //   372: invokevirtual charAt : (I)C
    //   375: invokevirtual append : (C)Ljava/lang/StringBuilder;
    //   378: pop
    //   379: iload_2
    //   380: ifeq -> 1348
    //   383: goto -> 390
    //   386: invokestatic a : (Ljava/lang/Throwable;)Ljava/lang/Throwable;
    //   389: athrow
    //   390: aload_3
    //   391: getstatic burp/Ztq4.Zb : Ljava/lang/String;
    //   394: getstatic burp/Zr36.Za : Ljava/lang/Object;
    //   397: checkcast java/math/BigInteger
    //   400: invokevirtual intValue : ()I
    //   403: bipush #32
    //   405: irem
    //   406: invokestatic abs : (I)I
    //   409: invokevirtual charAt : (I)C
    //   412: invokevirtual append : (C)Ljava/lang/StringBuilder;
    //   415: pop
    //   416: iload_2
    //   417: ifeq -> 1348
    //   420: goto -> 427
    //   423: invokestatic a : (Ljava/lang/Throwable;)Ljava/lang/Throwable;
    //   426: athrow
    //   427: aload_3
    //   428: getstatic burp/Zg4l.Z_ : Ljava/lang/String;
    //   431: getstatic burp/Zeub.ZD : Ljava/lang/Object;
    //   434: checkcast java/math/BigInteger
    //   437: invokevirtual intValue : ()I
    //   440: bipush #32
    //   442: irem
    //   443: invokestatic abs : (I)I
    //   446: invokevirtual charAt : (I)C
    //   449: invokevirtual append : (C)Ljava/lang/StringBuilder;
    //   452: pop
    //   453: iload_2
    //   454: ifeq -> 1348
    //   457: goto -> 464
    //   460: invokestatic a : (Ljava/lang/Throwable;)Ljava/lang/Throwable;
    //   463: athrow
    //   464: aload_3
    //   465: getstatic burp/Zka9.ZM : Ljava/lang/String;
    //   468: getstatic burp/Zzgb.ZG : Ljava/lang/Object;
    //   471: checkcast java/math/BigInteger
    //   474: invokevirtual intValue : ()I
    //   477: bipush #32
    //   479: irem
    //   480: invokestatic abs : (I)I
    //   483: invokevirtual charAt : (I)C
    //   486: invokevirtual append : (C)Ljava/lang/StringBuilder;
    //   489: pop
    //   490: iload_2
    //   491: ifeq -> 1348
    //   494: goto -> 501
    //   497: invokestatic a : (Ljava/lang/Throwable;)Ljava/lang/Throwable;
    //   500: athrow
    //   501: aload_3
    //   502: getstatic burp/Zbwj.ZP : Ljava/lang/String;
    //   505: getstatic burp/Zz0b.ZT : Ljava/lang/Object;
    //   508: checkcast java/math/BigInteger
    //   511: invokevirtual intValue : ()I
    //   514: bipush #32
    //   516: irem
    //   517: invokestatic abs : (I)I
    //   520: invokevirtual charAt : (I)C
    //   523: invokevirtual append : (C)Ljava/lang/StringBuilder;
    //   526: pop
    //   527: iload_2
    //   528: ifeq -> 1348
    //   531: goto -> 538
    //   534: invokestatic a : (Ljava/lang/Throwable;)Ljava/lang/Throwable;
    //   537: athrow
    //   538: aload_3
    //   539: getstatic burp/Zmyk.Zx : Ljava/lang/String;
    //   542: getstatic burp/Zrom.ZF : Ljava/lang/Object;
    //   545: checkcast java/math/BigInteger
    //   548: invokevirtual intValue : ()I
    //   551: bipush #32
    //   553: irem
    //   554: invokestatic abs : (I)I
    //   557: invokevirtual charAt : (I)C
    //   560: invokevirtual append : (C)Ljava/lang/StringBuilder;
    //   563: pop
    //   564: iload_2
    //   565: ifeq -> 1348
    //   568: goto -> 575
    //   571: invokestatic a : (Ljava/lang/Throwable;)Ljava/lang/Throwable;
    //   574: athrow
    //   575: aload_3
    //   576: getstatic burp/Znu.ZF : Ljava/lang/String;
    //   579: getstatic burp/Zos.ZB : Ljava/lang/Object;
    //   582: checkcast java/math/BigInteger
    //   585: invokevirtual intValue : ()I
    //   588: bipush #32
    //   590: irem
    //   591: invokestatic abs : (I)I
    //   594: invokevirtual charAt : (I)C
    //   597: invokevirtual append : (C)Ljava/lang/StringBuilder;
    //   600: pop
    //   601: iload_2
    //   602: ifeq -> 1348
    //   605: goto -> 612
    //   608: invokestatic a : (Ljava/lang/Throwable;)Ljava/lang/Throwable;
    //   611: athrow
    //   612: aload_3
    //   613: getstatic burp/Zlbd.Zq : Ljava/lang/String;
    //   616: getstatic burp/Zspg.ZJ : Ljava/lang/Object;
    //   619: checkcast java/math/BigInteger
    //   622: invokevirtual intValue : ()I
    //   625: bipush #32
    //   627: irem
    //   628: invokestatic abs : (I)I
    //   631: invokevirtual charAt : (I)C
    //   634: invokevirtual append : (C)Ljava/lang/StringBuilder;
    //   637: pop
    //   638: iload_2
    //   639: ifeq -> 1348
    //   642: goto -> 649
    //   645: invokestatic a : (Ljava/lang/Throwable;)Ljava/lang/Throwable;
    //   648: athrow
    //   649: aload_3
    //   650: getstatic burp/Zx63.ZT : Ljava/lang/String;
    //   653: getstatic burp/Zlf7.ZE : Ljava/lang/Object;
    //   656: checkcast java/math/BigInteger
    //   659: invokevirtual intValue : ()I
    //   662: bipush #32
    //   664: irem
    //   665: invokestatic abs : (I)I
    //   668: invokevirtual charAt : (I)C
    //   671: invokevirtual append : (C)Ljava/lang/StringBuilder;
    //   674: pop
    //   675: iload_2
    //   676: ifeq -> 1348
    //   679: goto -> 686
    //   682: invokestatic a : (Ljava/lang/Throwable;)Ljava/lang/Throwable;
    //   685: athrow
    //   686: aload_3
    //   687: getstatic burp/Zkjj.ZT : Ljava/lang/String;
    //   690: getstatic burp/Zlo0.Zu : Ljava/lang/Object;
    //   693: checkcast java/math/BigInteger
    //   696: invokevirtual intValue : ()I
    //   699: bipush #32
    //   701: irem
    //   702: invokestatic abs : (I)I
    //   705: invokevirtual charAt : (I)C
    //   708: invokevirtual append : (C)Ljava/lang/StringBuilder;
    //   711: pop
    //   712: iload_2
    //   713: ifeq -> 1348
    //   716: goto -> 723
    //   719: invokestatic a : (Ljava/lang/Throwable;)Ljava/lang/Throwable;
    //   722: athrow
    //   723: aload_3
    //   724: getstatic burp/Zl7x.Zo : Ljava/lang/String;
    //   727: getstatic burp/Zgei.ZN : Ljava/lang/Object;
    //   730: checkcast java/math/BigInteger
    //   733: invokevirtual intValue : ()I
    //   736: bipush #32
    //   738: irem
    //   739: invokestatic abs : (I)I
    //   742: invokevirtual charAt : (I)C
    //   745: invokevirtual append : (C)Ljava/lang/StringBuilder;
    //   748: pop
    //   749: iload_2
    //   750: ifeq -> 1348
    //   753: goto -> 760
    //   756: invokestatic a : (Ljava/lang/Throwable;)Ljava/lang/Throwable;
    //   759: athrow
    //   760: aload_3
    //   761: getstatic burp/Ze4a.Zm : Ljava/lang/String;
    //   764: getstatic burp/Zkql.Zl : Ljava/lang/Object;
    //   767: checkcast java/math/BigInteger
    //   770: invokevirtual intValue : ()I
    //   773: bipush #32
    //   775: irem
    //   776: invokestatic abs : (I)I
    //   779: invokevirtual charAt : (I)C
    //   782: invokevirtual append : (C)Ljava/lang/StringBuilder;
    //   785: pop
    //   786: iload_2
    //   787: ifeq -> 1348
    //   790: goto -> 797
    //   793: invokestatic a : (Ljava/lang/Throwable;)Ljava/lang/Throwable;
    //   796: athrow
    //   797: aload_3
    //   798: getstatic burp/Zgsb.ZM : Ljava/lang/String;
    //   801: getstatic burp/Zegj.ZT : Ljava/lang/Object;
    //   804: checkcast java/math/BigInteger
    //   807: invokevirtual intValue : ()I
    //   810: bipush #32
    //   812: irem
    //   813: invokestatic abs : (I)I
    //   816: invokevirtual charAt : (I)C
    //   819: invokevirtual append : (C)Ljava/lang/StringBuilder;
    //   822: pop
    //   823: iload_2
    //   824: ifeq -> 1348
    //   827: goto -> 834
    //   830: invokestatic a : (Ljava/lang/Throwable;)Ljava/lang/Throwable;
    //   833: athrow
    //   834: aload_3
    //   835: getstatic burp/Zrnt.Zy : Ljava/lang/String;
    //   838: getstatic burp/Zb6m.ZQ : Ljava/lang/Object;
    //   841: checkcast java/math/BigInteger
    //   844: invokevirtual intValue : ()I
    //   847: bipush #32
    //   849: irem
    //   850: invokestatic abs : (I)I
    //   853: invokevirtual charAt : (I)C
    //   856: invokevirtual append : (C)Ljava/lang/StringBuilder;
    //   859: pop
    //   860: iload_2
    //   861: ifeq -> 1348
    //   864: goto -> 871
    //   867: invokestatic a : (Ljava/lang/Throwable;)Ljava/lang/Throwable;
    //   870: athrow
    //   871: aload_3
    //   872: getstatic burp/Zk5k.Zx : Ljava/lang/String;
    //   875: getstatic burp/Zrt3.ZG : Ljava/lang/Object;
    //   878: checkcast java/math/BigInteger
    //   881: invokevirtual intValue : ()I
    //   884: bipush #32
    //   886: irem
    //   887: invokestatic abs : (I)I
    //   890: invokevirtual charAt : (I)C
    //   893: invokevirtual append : (C)Ljava/lang/StringBuilder;
    //   896: pop
    //   897: iload_2
    //   898: ifeq -> 1348
    //   901: goto -> 908
    //   904: invokestatic a : (Ljava/lang/Throwable;)Ljava/lang/Throwable;
    //   907: athrow
    //   908: aload_3
    //   909: getstatic burp/Zt6z.ZL : Ljava/lang/String;
    //   912: getstatic burp/Zl7b.ZK : Ljava/lang/Object;
    //   915: checkcast java/math/BigInteger
    //   918: invokevirtual intValue : ()I
    //   921: bipush #32
    //   923: irem
    //   924: invokestatic abs : (I)I
    //   927: invokevirtual charAt : (I)C
    //   930: invokevirtual append : (C)Ljava/lang/StringBuilder;
    //   933: pop
    //   934: iload_2
    //   935: ifeq -> 1348
    //   938: goto -> 945
    //   941: invokestatic a : (Ljava/lang/Throwable;)Ljava/lang/Throwable;
    //   944: athrow
    //   945: aload_3
    //   946: getstatic burp/Zk8f.ZV : Ljava/lang/String;
    //   949: getstatic burp/Zsn9.Zg : Ljava/lang/Object;
    //   952: checkcast java/math/BigInteger
    //   955: invokevirtual intValue : ()I
    //   958: bipush #32
    //   960: irem
    //   961: invokestatic abs : (I)I
    //   964: invokevirtual charAt : (I)C
    //   967: invokevirtual append : (C)Ljava/lang/StringBuilder;
    //   970: pop
    //   971: iload_2
    //   972: ifeq -> 1348
    //   975: goto -> 982
    //   978: invokestatic a : (Ljava/lang/Throwable;)Ljava/lang/Throwable;
    //   981: athrow
    //   982: aload_3
    //   983: getstatic burp/Zbun.ZS : Ljava/lang/String;
    //   986: getstatic burp/Zgpx.ZQ : Ljava/lang/Object;
    //   989: checkcast java/math/BigInteger
    //   992: invokevirtual intValue : ()I
    //   995: bipush #32
    //   997: irem
    //   998: invokestatic abs : (I)I
    //   1001: invokevirtual charAt : (I)C
    //   1004: invokevirtual append : (C)Ljava/lang/StringBuilder;
    //   1007: pop
    //   1008: iload_2
    //   1009: ifeq -> 1348
    //   1012: goto -> 1019
    //   1015: invokestatic a : (Ljava/lang/Throwable;)Ljava/lang/Throwable;
    //   1018: athrow
    //   1019: aload_3
    //   1020: getstatic burp/Zrfa.ZT : Ljava/lang/String;
    //   1023: getstatic burp/Zrt3.ZG : Ljava/lang/Object;
    //   1026: checkcast java/math/BigInteger
    //   1029: invokevirtual intValue : ()I
    //   1032: bipush #32
    //   1034: irem
    //   1035: invokestatic abs : (I)I
    //   1038: invokevirtual charAt : (I)C
    //   1041: invokevirtual append : (C)Ljava/lang/StringBuilder;
    //   1044: pop
    //   1045: iload_2
    //   1046: ifeq -> 1348
    //   1049: goto -> 1056
    //   1052: invokestatic a : (Ljava/lang/Throwable;)Ljava/lang/Throwable;
    //   1055: athrow
    //   1056: aload_3
    //   1057: getstatic burp/Zbx4.ZS : Ljava/lang/String;
    //   1060: getstatic burp/Zrfa.Zj : Ljava/lang/Object;
    //   1063: checkcast java/math/BigInteger
    //   1066: invokevirtual intValue : ()I
    //   1069: bipush #32
    //   1071: irem
    //   1072: invokestatic abs : (I)I
    //   1075: invokevirtual charAt : (I)C
    //   1078: invokevirtual append : (C)Ljava/lang/StringBuilder;
    //   1081: pop
    //   1082: iload_2
    //   1083: ifeq -> 1348
    //   1086: goto -> 1093
    //   1089: invokestatic a : (Ljava/lang/Throwable;)Ljava/lang/Throwable;
    //   1092: athrow
    //   1093: aload_3
    //   1094: getstatic burp/Zgrz.Zu : Ljava/lang/String;
    //   1097: getstatic burp/Zl3j.ZY : Ljava/lang/Object;
    //   1100: checkcast java/math/BigInteger
    //   1103: invokevirtual intValue : ()I
    //   1106: bipush #32
    //   1108: irem
    //   1109: invokestatic abs : (I)I
    //   1112: invokevirtual charAt : (I)C
    //   1115: invokevirtual append : (C)Ljava/lang/StringBuilder;
    //   1118: pop
    //   1119: iload_2
    //   1120: ifeq -> 1348
    //   1123: goto -> 1130
    //   1126: invokestatic a : (Ljava/lang/Throwable;)Ljava/lang/Throwable;
    //   1129: athrow
    //   1130: aload_3
    //   1131: getstatic burp/Zr_x.ZF : Ljava/lang/String;
    //   1134: getstatic burp/Zl1e.Zp : Ljava/lang/Object;
    //   1137: checkcast java/math/BigInteger
    //   1140: invokevirtual intValue : ()I
    //   1143: bipush #32
    //   1145: irem
    //   1146: invokestatic abs : (I)I
    //   1149: invokevirtual charAt : (I)C
    //   1152: invokevirtual append : (C)Ljava/lang/StringBuilder;
    //   1155: pop
    //   1156: iload_2
    //   1157: ifeq -> 1348
    //   1160: goto -> 1167
    //   1163: invokestatic a : (Ljava/lang/Throwable;)Ljava/lang/Throwable;
    //   1166: athrow
    //   1167: aload_3
    //   1168: getstatic burp/Zkjj.ZT : Ljava/lang/String;
    //   1171: getstatic burp/Zebc.Zr : Ljava/lang/Object;
    //   1174: checkcast java/math/BigInteger
    //   1177: invokevirtual intValue : ()I
    //   1180: bipush #32
    //   1182: irem
    //   1183: invokestatic abs : (I)I
    //   1186: invokevirtual charAt : (I)C
    //   1189: invokevirtual append : (C)Ljava/lang/StringBuilder;
    //   1192: pop
    //   1193: iload_2
    //   1194: ifeq -> 1348
    //   1197: goto -> 1204
    //   1200: invokestatic a : (Ljava/lang/Throwable;)Ljava/lang/Throwable;
    //   1203: athrow
    //   1204: aload_3
    //   1205: getstatic burp/Zbow.Zr : Ljava/lang/String;
    //   1208: getstatic burp/Zsbo.ZG : Ljava/lang/Object;
    //   1211: checkcast java/math/BigInteger
    //   1214: invokevirtual intValue : ()I
    //   1217: bipush #32
    //   1219: irem
    //   1220: invokestatic abs : (I)I
    //   1223: invokevirtual charAt : (I)C
    //   1226: invokevirtual append : (C)Ljava/lang/StringBuilder;
    //   1229: pop
    //   1230: iload_2
    //   1231: ifeq -> 1348
    //   1234: goto -> 1241
    //   1237: invokestatic a : (Ljava/lang/Throwable;)Ljava/lang/Throwable;
    //   1240: athrow
    //   1241: aload_3
    //   1242: getstatic burp/Zxju.Zt : Ljava/lang/String;
    //   1245: getstatic burp/Zlxr.Zz : Ljava/lang/Object;
    //   1248: checkcast java/math/BigInteger
    //   1251: invokevirtual intValue : ()I
    //   1254: bipush #32
    //   1256: irem
    //   1257: invokestatic abs : (I)I
    //   1260: invokevirtual charAt : (I)C
    //   1263: invokevirtual append : (C)Ljava/lang/StringBuilder;
    //   1266: pop
    //   1267: iload_2
    //   1268: ifeq -> 1348
    //   1271: goto -> 1278
    //   1274: invokestatic a : (Ljava/lang/Throwable;)Ljava/lang/Throwable;
    //   1277: athrow
    //   1278: aload_3
    //   1279: getstatic burp/Zmf6.Zn : Ljava/lang/String;
    //   1282: getstatic burp/Zz41.Zv : Ljava/lang/Object;
    //   1285: checkcast java/math/BigInteger
    //   1288: invokevirtual intValue : ()I
    //   1291: bipush #32
    //   1293: irem
    //   1294: invokestatic abs : (I)I
    //   1297: invokevirtual charAt : (I)C
    //   1300: invokevirtual append : (C)Ljava/lang/StringBuilder;
    //   1303: pop
    //   1304: iload_2
    //   1305: ifeq -> 1348
    //   1308: goto -> 1315
    //   1311: invokestatic a : (Ljava/lang/Throwable;)Ljava/lang/Throwable;
    //   1314: athrow
    //   1315: aload_3
    //   1316: getstatic burp/Zrym.ZX : Ljava/lang/String;
    //   1319: getstatic burp/Zbwj.ZW : Ljava/lang/Object;
    //   1322: checkcast java/math/BigInteger
    //   1325: invokevirtual intValue : ()I
    //   1328: bipush #32
    //   1330: irem
    //   1331: invokestatic abs : (I)I
    //   1334: invokevirtual charAt : (I)C
    //   1337: invokevirtual append : (C)Ljava/lang/StringBuilder;
    //   1340: pop
    //   1341: goto -> 1348
    //   1344: invokestatic a : (Ljava/lang/Throwable;)Ljava/lang/Throwable;
    //   1347: athrow
    //   1348: iinc #4, 1
    //   1351: iload_2
    //   1352: ifeq -> 15
    //   1355: aload_3
    //   1356: invokevirtual toString : ()Ljava/lang/String;
    //   1359: putstatic burp/Zrqe.ZB : Ljava/lang/String;
    //   1362: getstatic burp/Znu.Zf : Ljava/lang/Object;
    //   1365: checkcast java/math/BigInteger
    //   1368: invokevirtual toByteArray : ()[B
    //   1371: astore #4
    //   1373: iconst_0
    //   1374: istore #6
    //   1376: iconst_0
    //   1377: istore #7
    //   1379: iload #7
    //   1381: aload #4
    //   1383: arraylength
    //   1384: if_icmpge -> 1530
    //   1387: aload #4
    //   1389: iload #7
    //   1391: baload
    //   1392: istore #8
    //   1394: iload #8
    //   1396: bipush #48
    //   1398: if_icmplt -> 1415
    //   1401: iload #8
    //   1403: bipush #57
    //   1405: if_icmple -> 1513
    //   1408: goto -> 1415
    //   1411: invokestatic a : (Ljava/lang/Throwable;)Ljava/lang/Throwable;
    //   1414: athrow
    //   1415: iload #8
    //   1417: bipush #65
    //   1419: if_icmplt -> 1443
    //   1422: goto -> 1429
    //   1425: invokestatic a : (Ljava/lang/Throwable;)Ljava/lang/Throwable;
    //   1428: athrow
    //   1429: iload #8
    //   1431: bipush #90
    //   1433: if_icmple -> 1513
    //   1436: goto -> 1443
    //   1439: invokestatic a : (Ljava/lang/Throwable;)Ljava/lang/Throwable;
    //   1442: athrow
    //   1443: iload #8
    //   1445: bipush #97
    //   1447: if_icmplt -> 1471
    //   1450: goto -> 1457
    //   1453: invokestatic a : (Ljava/lang/Throwable;)Ljava/lang/Throwable;
    //   1456: athrow
    //   1457: iload #8
    //   1459: bipush #122
    //   1461: if_icmple -> 1513
    //   1464: goto -> 1471
    //   1467: invokestatic a : (Ljava/lang/Throwable;)Ljava/lang/Throwable;
    //   1470: athrow
    //   1471: iload #8
    //   1473: bipush #43
    //   1475: if_icmpeq -> 1513
    //   1478: goto -> 1485
    //   1481: invokestatic a : (Ljava/lang/Throwable;)Ljava/lang/Throwable;
    //   1484: athrow
    //   1485: iload #8
    //   1487: bipush #47
    //   1489: if_icmpeq -> 1513
    //   1492: goto -> 1499
    //   1495: invokestatic a : (Ljava/lang/Throwable;)Ljava/lang/Throwable;
    //   1498: athrow
    //   1499: iload #8
    //   1501: bipush #61
    //   1503: if_icmpne -> 1523
    //   1506: goto -> 1513
    //   1509: invokestatic a : (Ljava/lang/Throwable;)Ljava/lang/Throwable;
    //   1512: athrow
    //   1513: iinc #6, 1
    //   1516: goto -> 1523
    //   1519: invokestatic a : (Ljava/lang/Throwable;)Ljava/lang/Throwable;
    //   1522: athrow
    //   1523: iinc #7, 1
    //   1526: iload_2
    //   1527: ifeq -> 1379
    //   1530: iload #6
    //   1532: newarray byte
    //   1534: astore #7
    //   1536: iconst_0
    //   1537: istore #8
    //   1539: iconst_0
    //   1540: istore #9
    //   1542: iload #9
    //   1544: aload #4
    //   1546: arraylength
    //   1547: if_icmpge -> 1700
    //   1550: aload #4
    //   1552: iload #9
    //   1554: baload
    //   1555: istore #10
    //   1557: iload #10
    //   1559: bipush #48
    //   1561: if_icmplt -> 1578
    //   1564: iload #10
    //   1566: bipush #57
    //   1568: if_icmple -> 1676
    //   1571: goto -> 1578
    //   1574: invokestatic a : (Ljava/lang/Throwable;)Ljava/lang/Throwable;
    //   1577: athrow
    //   1578: iload #10
    //   1580: bipush #65
    //   1582: if_icmplt -> 1606
    //   1585: goto -> 1592
    //   1588: invokestatic a : (Ljava/lang/Throwable;)Ljava/lang/Throwable;
    //   1591: athrow
    //   1592: iload #10
    //   1594: bipush #90
    //   1596: if_icmple -> 1676
    //   1599: goto -> 1606
    //   1602: invokestatic a : (Ljava/lang/Throwable;)Ljava/lang/Throwable;
    //   1605: athrow
    //   1606: iload #10
    //   1608: bipush #97
    //   1610: if_icmplt -> 1634
    //   1613: goto -> 1620
    //   1616: invokestatic a : (Ljava/lang/Throwable;)Ljava/lang/Throwable;
    //   1619: athrow
    //   1620: iload #10
    //   1622: bipush #122
    //   1624: if_icmple -> 1676
    //   1627: goto -> 1634
    //   1630: invokestatic a : (Ljava/lang/Throwable;)Ljava/lang/Throwable;
    //   1633: athrow
    //   1634: iload #10
    //   1636: bipush #43
    //   1638: if_icmpeq -> 1676
    //   1641: goto -> 1648
    //   1644: invokestatic a : (Ljava/lang/Throwable;)Ljava/lang/Throwable;
    //   1647: athrow
    //   1648: iload #10
    //   1650: bipush #47
    //   1652: if_icmpeq -> 1676
    //   1655: goto -> 1662
    //   1658: invokestatic a : (Ljava/lang/Throwable;)Ljava/lang/Throwable;
    //   1661: athrow
    //   1662: iload #10
    //   1664: bipush #61
    //   1666: if_icmpne -> 1693
    //   1669: goto -> 1676
    //   1672: invokestatic a : (Ljava/lang/Throwable;)Ljava/lang/Throwable;
    //   1675: athrow
    //   1676: aload #7
    //   1678: iload #8
    //   1680: iload #10
    //   1682: bastore
    //   1683: iinc #8, 1
    //   1686: goto -> 1693
    //   1689: invokestatic a : (Ljava/lang/Throwable;)Ljava/lang/Throwable;
    //   1692: athrow
    //   1693: iinc #9, 1
    //   1696: iload_2
    //   1697: ifeq -> 1542
    //   1700: aload #7
    //   1702: astore #5
    //   1704: aload #5
    //   1706: astore #4
    //   1708: aload #4
    //   1710: arraylength
    //   1711: istore #6
    //   1713: aload #4
    //   1715: iload #6
    //   1717: iconst_1
    //   1718: isub
    //   1719: baload
    //   1720: bipush #61
    //   1722: if_icmpne -> 1732
    //   1725: iinc #6, -1
    //   1728: iload_2
    //   1729: ifeq -> 1713
    //   1732: iload #6
    //   1734: aload #4
    //   1736: arraylength
    //   1737: iconst_4
    //   1738: idiv
    //   1739: isub
    //   1740: newarray byte
    //   1742: astore #7
    //   1744: iconst_0
    //   1745: istore #8
    //   1747: iload #8
    //   1749: aload #4
    //   1751: arraylength
    //   1752: if_icmpge -> 2032
    //   1755: aload #4
    //   1757: iload #8
    //   1759: baload
    //   1760: bipush #61
    //   1762: if_icmpne -> 1782
    //   1765: aload #4
    //   1767: iload #8
    //   1769: iconst_0
    //   1770: bastore
    //   1771: iload_2
    //   1772: ifeq -> 2025
    //   1775: goto -> 1782
    //   1778: invokestatic a : (Ljava/lang/Throwable;)Ljava/lang/Throwable;
    //   1781: athrow
    //   1782: aload #4
    //   1784: iload #8
    //   1786: baload
    //   1787: bipush #47
    //   1789: if_icmpne -> 1817
    //   1792: goto -> 1799
    //   1795: invokestatic a : (Ljava/lang/Throwable;)Ljava/lang/Throwable;
    //   1798: athrow
    //   1799: aload #4
    //   1801: iload #8
    //   1803: bipush #63
    //   1805: bastore
    //   1806: iload_2
    //   1807: ifeq -> 2025
    //   1810: goto -> 1817
    //   1813: invokestatic a : (Ljava/lang/Throwable;)Ljava/lang/Throwable;
    //   1816: athrow
    //   1817: aload #4
    //   1819: iload #8
    //   1821: baload
    //   1822: bipush #43
    //   1824: if_icmpne -> 1852
    //   1827: goto -> 1834
    //   1830: invokestatic a : (Ljava/lang/Throwable;)Ljava/lang/Throwable;
    //   1833: athrow
    //   1834: aload #4
    //   1836: iload #8
    //   1838: bipush #62
    //   1840: bastore
    //   1841: iload_2
    //   1842: ifeq -> 2025
    //   1845: goto -> 1852
    //   1848: invokestatic a : (Ljava/lang/Throwable;)Ljava/lang/Throwable;
    //   1851: athrow
    //   1852: aload #4
    //   1854: iload #8
    //   1856: baload
    //   1857: bipush #48
    //   1859: if_icmplt -> 1911
    //   1862: goto -> 1869
    //   1865: invokestatic a : (Ljava/lang/Throwable;)Ljava/lang/Throwable;
    //   1868: athrow
    //   1869: aload #4
    //   1871: iload #8
    //   1873: baload
    //   1874: bipush #57
    //   1876: if_icmpgt -> 1911
    //   1879: goto -> 1886
    //   1882: invokestatic a : (Ljava/lang/Throwable;)Ljava/lang/Throwable;
    //   1885: athrow
    //   1886: aload #4
    //   1888: iload #8
    //   1890: aload #4
    //   1892: iload #8
    //   1894: baload
    //   1895: bipush #-4
    //   1897: isub
    //   1898: i2b
    //   1899: bastore
    //   1900: iload_2
    //   1901: ifeq -> 2025
    //   1904: goto -> 1911
    //   1907: invokestatic a : (Ljava/lang/Throwable;)Ljava/lang/Throwable;
    //   1910: athrow
    //   1911: aload #4
    //   1913: iload #8
    //   1915: baload
    //   1916: bipush #97
    //   1918: if_icmplt -> 1970
    //   1921: goto -> 1928
    //   1924: invokestatic a : (Ljava/lang/Throwable;)Ljava/lang/Throwable;
    //   1927: athrow
    //   1928: aload #4
    //   1930: iload #8
    //   1932: baload
    //   1933: bipush #122
    //   1935: if_icmpgt -> 1970
    //   1938: goto -> 1945
    //   1941: invokestatic a : (Ljava/lang/Throwable;)Ljava/lang/Throwable;
    //   1944: athrow
    //   1945: aload #4
    //   1947: iload #8
    //   1949: aload #4
    //   1951: iload #8
    //   1953: baload
    //   1954: bipush #71
    //   1956: isub
    //   1957: i2b
    //   1958: bastore
    //   1959: iload_2
    //   1960: ifeq -> 2025
    //   1963: goto -> 1970
    //   1966: invokestatic a : (Ljava/lang/Throwable;)Ljava/lang/Throwable;
    //   1969: athrow
    //   1970: aload #4
    //   1972: iload #8
    //   1974: baload
    //   1975: bipush #65
    //   1977: if_icmplt -> 2025
    //   1980: goto -> 1987
    //   1983: invokestatic a : (Ljava/lang/Throwable;)Ljava/lang/Throwable;
    //   1986: athrow
    //   1987: aload #4
    //   1989: iload #8
    //   1991: baload
    //   1992: bipush #90
    //   1994: if_icmpgt -> 2025
    //   1997: goto -> 2004
    //   2000: invokestatic a : (Ljava/lang/Throwable;)Ljava/lang/Throwable;
    //   2003: athrow
    //   2004: aload #4
    //   2006: iload #8
    //   2008: aload #4
    //   2010: iload #8
    //   2012: baload
    //   2013: bipush #65
    //   2015: isub
    //   2016: i2b
    //   2017: bastore
    //   2018: goto -> 2025
    //   2021: invokestatic a : (Ljava/lang/Throwable;)Ljava/lang/Throwable;
    //   2024: athrow
    //   2025: iinc #8, 1
    //   2028: iload_2
    //   2029: ifeq -> 1747
    //   2032: iconst_0
    //   2033: istore #8
    //   2035: iconst_0
    //   2036: istore #9
    //   2038: iload #9
    //   2040: aload #7
    //   2042: arraylength
    //   2043: iconst_2
    //   2044: isub
    //   2045: if_icmpge -> 2154
    //   2048: aload #7
    //   2050: iload #9
    //   2052: aload #4
    //   2054: iload #8
    //   2056: baload
    //   2057: iconst_2
    //   2058: ishl
    //   2059: sipush #255
    //   2062: iand
    //   2063: aload #4
    //   2065: iload #8
    //   2067: iconst_1
    //   2068: iadd
    //   2069: baload
    //   2070: iconst_4
    //   2071: iushr
    //   2072: iconst_3
    //   2073: iand
    //   2074: ior
    //   2075: i2b
    //   2076: bastore
    //   2077: aload #7
    //   2079: iload #9
    //   2081: iconst_1
    //   2082: iadd
    //   2083: aload #4
    //   2085: iload #8
    //   2087: iconst_1
    //   2088: iadd
    //   2089: baload
    //   2090: iconst_4
    //   2091: ishl
    //   2092: sipush #255
    //   2095: iand
    //   2096: aload #4
    //   2098: iload #8
    //   2100: iconst_2
    //   2101: iadd
    //   2102: baload
    //   2103: iconst_2
    //   2104: iushr
    //   2105: bipush #15
    //   2107: iand
    //   2108: ior
    //   2109: i2b
    //   2110: bastore
    //   2111: aload #7
    //   2113: iload #9
    //   2115: iconst_2
    //   2116: iadd
    //   2117: aload #4
    //   2119: iload #8
    //   2121: iconst_2
    //   2122: iadd
    //   2123: baload
    //   2124: bipush #6
    //   2126: ishl
    //   2127: sipush #255
    //   2130: iand
    //   2131: aload #4
    //   2133: iload #8
    //   2135: iconst_3
    //   2136: iadd
    //   2137: baload
    //   2138: bipush #63
    //   2140: iand
    //   2141: ior
    //   2142: i2b
    //   2143: bastore
    //   2144: iinc #8, 4
    //   2147: iinc #9, 3
    //   2150: iload_2
    //   2151: ifeq -> 2038
    //   2154: iload #9
    //   2156: aload #7
    //   2158: arraylength
    //   2159: if_icmpge -> 2198
    //   2162: aload #7
    //   2164: iload #9
    //   2166: aload #4
    //   2168: iload #8
    //   2170: baload
    //   2171: iconst_2
    //   2172: ishl
    //   2173: sipush #255
    //   2176: iand
    //   2177: aload #4
    //   2179: iload #8
    //   2181: iconst_1
    //   2182: iadd
    //   2183: baload
    //   2184: iconst_4
    //   2185: iushr
    //   2186: iconst_3
    //   2187: iand
    //   2188: ior
    //   2189: i2b
    //   2190: bastore
    //   2191: goto -> 2198
    //   2194: invokestatic a : (Ljava/lang/Throwable;)Ljava/lang/Throwable;
    //   2197: athrow
    //   2198: iinc #9, 1
    //   2201: iload #9
    //   2203: aload #7
    //   2205: arraylength
    //   2206: if_icmpge -> 2248
    //   2209: aload #7
    //   2211: iload #9
    //   2213: aload #4
    //   2215: iload #8
    //   2217: iconst_1
    //   2218: iadd
    //   2219: baload
    //   2220: iconst_4
    //   2221: ishl
    //   2222: sipush #255
    //   2225: iand
    //   2226: aload #4
    //   2228: iload #8
    //   2230: iconst_2
    //   2231: iadd
    //   2232: baload
    //   2233: iconst_2
    //   2234: iushr
    //   2235: bipush #15
    //   2237: iand
    //   2238: ior
    //   2239: i2b
    //   2240: bastore
    //   2241: goto -> 2248
    //   2244: invokestatic a : (Ljava/lang/Throwable;)Ljava/lang/Throwable;
    //   2247: athrow
    //   2248: aload #7
    //   2250: astore #5
    //   2252: sipush #27775
    //   2255: new java/math/BigInteger
    //   2258: dup
    //   2259: aload #5
    //   2261: invokespecial <init> : ([B)V
    //   2264: invokevirtual abs : ()Ljava/math/BigInteger;
    //   2267: putstatic burp/Zd9.Zr : Ljava/lang/Object;
    //   2270: sipush #-22216
    //   2273: invokestatic a : (II)Ljava/lang/String;
    //   2276: iconst_1
    //   2277: ldc burp/Zep8
    //   2279: invokevirtual getClassLoader : ()Ljava/lang/ClassLoader;
    //   2282: invokestatic forName : (Ljava/lang/String;ZLjava/lang/ClassLoader;)Ljava/lang/Class;
    //   2285: invokevirtual getDeclaredFields : ()[Ljava/lang/reflect/Field;
    //   2288: astore #4
    //   2290: aload #4
    //   2292: arraylength
    //   2293: istore #5
    //   2295: iconst_0
    //   2296: istore #6
    //   2298: iload #6
    //   2300: iload #5
    //   2302: if_icmpge -> 2440
    //   2305: aload #4
    //   2307: iload #6
    //   2309: aaload
    //   2310: astore #7
    //   2312: aload #7
    //   2314: invokevirtual getModifiers : ()I
    //   2317: invokestatic isStatic : (I)Z
    //   2320: ifne -> 2330
    //   2323: goto -> 2433
    //   2326: invokestatic a : (Ljava/lang/Throwable;)Ljava/lang/Throwable;
    //   2329: athrow
    //   2330: aload #7
    //   2332: invokevirtual getType : ()Ljava/lang/Class;
    //   2335: astore #8
    //   2337: aload #8
    //   2339: ifnull -> 2420
    //   2342: aload #8
    //   2344: invokevirtual isPrimitive : ()Z
    //   2347: ifne -> 2420
    //   2350: goto -> 2357
    //   2353: invokestatic a : (Ljava/lang/Throwable;)Ljava/lang/Throwable;
    //   2356: athrow
    //   2357: aload #8
    //   2359: invokevirtual getPackage : ()Ljava/lang/Package;
    //   2362: ifnull -> 2420
    //   2365: goto -> 2372
    //   2368: invokestatic a : (Ljava/lang/Throwable;)Ljava/lang/Throwable;
    //   2371: athrow
    //   2372: aload #8
    //   2374: invokevirtual getPackage : ()Ljava/lang/Package;
    //   2377: invokevirtual getName : ()Ljava/lang/String;
    //   2380: ifnull -> 2420
    //   2383: goto -> 2390
    //   2386: invokestatic a : (Ljava/lang/Throwable;)Ljava/lang/Throwable;
    //   2389: athrow
    //   2390: aload #8
    //   2392: invokevirtual getPackage : ()Ljava/lang/Package;
    //   2395: invokevirtual getName : ()Ljava/lang/String;
    //   2398: sipush #27774
    //   2401: sipush #13986
    //   2404: invokestatic a : (II)Ljava/lang/String;
    //   2407: invokevirtual startsWith : (Ljava/lang/String;)Z
    //   2410: ifne -> 2420
    //   2413: goto -> 2420
    //   2416: invokestatic a : (Ljava/lang/Throwable;)Ljava/lang/Throwable;
    //   2419: athrow
    //   2420: aload #7
    //   2422: iconst_1
    //   2423: invokevirtual setAccessible : (Z)V
    //   2426: aload #7
    //   2428: aconst_null
    //   2429: invokevirtual get : (Ljava/lang/Object;)Ljava/lang/Object;
    //   2432: pop
    //   2433: iinc #6, 1
    //   2436: iload_2
    //   2437: ifeq -> 2298
    //   2440: sipush #27772
    //   2443: sipush #-20168
    //   2446: invokestatic a : (II)Ljava/lang/String;
    //   2449: invokestatic forName : (Ljava/lang/String;)Ljava/lang/Class;
    //   2452: invokevirtual getDeclaredMethods : ()[Ljava/lang/reflect/Method;
    //   2455: astore #4
    //   2457: aload #4
    //   2459: arraylength
    //   2460: istore #5
    //   2462: iconst_0
    //   2463: istore #6
    //   2465: iload #6
    //   2467: iload #5
    //   2469: if_icmpge -> 2602
    //   2472: aload #4
    //   2474: iload #6
    //   2476: aaload
    //   2477: astore #7
    //   2479: aload #7
    //   2481: invokevirtual getParameterTypes : ()[Ljava/lang/Class;
    //   2484: pop
    //   2485: aload #7
    //   2487: invokevirtual getModifiers : ()I
    //   2490: invokestatic isStatic : (I)Z
    //   2493: ifeq -> 2588
    //   2496: aload #7
    //   2498: invokevirtual getParameterTypes : ()[Ljava/lang/Class;
    //   2501: arraylength
    //   2502: iconst_2
    //   2503: if_icmpne -> 2588
    //   2506: goto -> 2513
    //   2509: invokestatic a : (Ljava/lang/Throwable;)Ljava/lang/Throwable;
    //   2512: athrow
    //   2513: aload #7
    //   2515: invokevirtual getReturnType : ()Ljava/lang/Class;
    //   2518: getstatic java/lang/Void.TYPE : Ljava/lang/Class;
    //   2521: invokevirtual equals : (Ljava/lang/Object;)Z
    //   2524: ifeq -> 2588
    //   2527: goto -> 2534
    //   2530: invokestatic a : (Ljava/lang/Throwable;)Ljava/lang/Throwable;
    //   2533: athrow
    //   2534: aload #7
    //   2536: iconst_1
    //   2537: invokevirtual setAccessible : (Z)V
    //   2540: aload #7
    //   2542: aconst_null
    //   2543: iconst_2
    //   2544: anewarray java/lang/Object
    //   2547: dup
    //   2548: iconst_0
    //   2549: aload_0
    //   2550: aastore
    //   2551: dup
    //   2552: iconst_1
    //   2553: aload_1
    //   2554: ifnonnull -> 2572
    //   2557: goto -> 2564
    //   2560: invokestatic a : (Ljava/lang/Throwable;)Ljava/lang/Throwable;
    //   2563: athrow
    //   2564: aload_1
    //   2565: goto -> 2579
    //   2568: invokestatic a : (Ljava/lang/Throwable;)Ljava/lang/Throwable;
    //   2571: athrow
    //   2572: aload_1
    //   2573: checkcast [B
    //   2576: invokevirtual clone : ()Ljava/lang/Object;
    //   2579: aastore
    //   2580: invokevirtual invoke : (Ljava/lang/Object;[Ljava/lang/Object;)Ljava/lang/Object;
    //   2583: pop
    //   2584: iload_2
    //   2585: ifeq -> 2602
    //   2588: iinc #6, 1
    //   2591: iload_2
    //   2592: ifeq -> 2465
    //   2595: goto -> 2602
    //   2598: invokestatic a : (Ljava/lang/Throwable;)Ljava/lang/Throwable;
    //   2601: athrow
    //   2602: getstatic burp/Zql.Zf : Ljava/lang/String;
    //   2605: getstatic burp/Zx4u.Zn : Ljava/lang/Object;
    //   2608: checkcast java/math/BigInteger
    //   2611: invokevirtual intValue : ()I
    //   2614: bipush #32
    //   2616: irem
    //   2617: invokestatic abs : (I)I
    //   2620: invokevirtual charAt : (I)C
    //   2623: getstatic burp/Zscf.Zu : Ljava/lang/String;
    //   2626: getstatic burp/Zb2u.ZY : Ljava/lang/Object;
    //   2629: checkcast java/math/BigInteger
    //   2632: invokevirtual intValue : ()I
    //   2635: bipush #32
    //   2637: irem
    //   2638: invokestatic abs : (I)I
    //   2641: invokevirtual charAt : (I)C
    //   2644: if_icmple -> 2751
    //   2647: getstatic burp/Zegv.ZA : Ljava/lang/String;
    //   2650: getstatic burp/Zzna.ZD : Ljava/lang/Object;
    //   2653: checkcast java/math/BigInteger
    //   2656: invokevirtual intValue : ()I
    //   2659: bipush #32
    //   2661: irem
    //   2662: invokestatic abs : (I)I
    //   2665: invokevirtual charAt : (I)C
    //   2668: getstatic burp/Zlab.Zp : Ljava/lang/String;
    //   2671: getstatic burp/Zrip.ZB : Ljava/lang/Object;
    //   2674: checkcast java/math/BigInteger
    //   2677: invokevirtual intValue : ()I
    //   2680: bipush #32
    //   2682: irem
    //   2683: invokestatic abs : (I)I
    //   2686: invokevirtual charAt : (I)C
    //   2689: if_icmpgt -> 2751
    //   2692: goto -> 2699
    //   2695: invokestatic a : (Ljava/lang/Throwable;)Ljava/lang/Throwable;
    //   2698: athrow
    //   2699: getstatic burp/Zrom.ZD : Ljava/lang/String;
    //   2702: getstatic burp/Zxzv.Zg : Ljava/lang/Object;
    //   2705: checkcast java/math/BigInteger
    //   2708: invokevirtual intValue : ()I
    //   2711: bipush #32
    //   2713: irem
    //   2714: invokestatic abs : (I)I
    //   2717: invokevirtual charAt : (I)C
    //   2720: getstatic burp/Zrye.Za : Ljava/lang/String;
    //   2723: getstatic burp/Zt5t.Za : Ljava/lang/Object;
    //   2726: checkcast java/math/BigInteger
    //   2729: invokevirtual intValue : ()I
    //   2732: bipush #32
    //   2734: irem
    //   2735: invokestatic abs : (I)I
    //   2738: invokevirtual charAt : (I)C
    //   2741: if_icmple -> 2759
    //   2744: goto -> 2751
    //   2747: invokestatic a : (Ljava/lang/Throwable;)Ljava/lang/Throwable;
    //   2750: athrow
    //   2751: iconst_1
    //   2752: goto -> 2760
    //   2755: invokestatic a : (Ljava/lang/Throwable;)Ljava/lang/Throwable;
    //   2758: athrow
    //   2759: iconst_0
    //   2760: ireturn
    //   2761: astore_3
    //   2762: new java/lang/Exception
    //   2765: dup
    //   2766: aload_3
    //   2767: invokevirtual getMessage : ()Ljava/lang/String;
    //   2770: invokespecial <init> : (Ljava/lang/String;)V
    //   2773: athrow
    // Exception table:
    //   from	to	target	type
    //   4	2760	2761	java/lang/Throwable
    //   22	198	201	java/lang/Throwable
    //   168	235	238	java/lang/Throwable
    //   205	272	275	java/lang/Throwable
    //   242	309	312	java/lang/Throwable
    //   279	346	349	java/lang/Throwable
    //   316	383	386	java/lang/Throwable
    //   353	420	423	java/lang/Throwable
    //   390	457	460	java/lang/Throwable
    //   427	494	497	java/lang/Throwable
    //   464	531	534	java/lang/Throwable
    //   501	568	571	java/lang/Throwable
    //   538	605	608	java/lang/Throwable
    //   575	642	645	java/lang/Throwable
    //   612	679	682	java/lang/Throwable
    //   649	716	719	java/lang/Throwable
    //   686	753	756	java/lang/Throwable
    //   723	790	793	java/lang/Throwable
    //   760	827	830	java/lang/Throwable
    //   797	864	867	java/lang/Throwable
    //   834	901	904	java/lang/Throwable
    //   871	938	941	java/lang/Throwable
    //   908	975	978	java/lang/Throwable
    //   945	1012	1015	java/lang/Throwable
    //   982	1049	1052	java/lang/Throwable
    //   1019	1086	1089	java/lang/Throwable
    //   1056	1123	1126	java/lang/Throwable
    //   1093	1160	1163	java/lang/Throwable
    //   1130	1197	1200	java/lang/Throwable
    //   1167	1234	1237	java/lang/Throwable
    //   1204	1271	1274	java/lang/Throwable
    //   1241	1308	1311	java/lang/Throwable
    //   1278	1341	1344	java/lang/Throwable
    //   1394	1408	1411	java/lang/Throwable
    //   1401	1422	1425	java/lang/Throwable
    //   1415	1436	1439	java/lang/Throwable
    //   1429	1450	1453	java/lang/Throwable
    //   1443	1464	1467	java/lang/Throwable
    //   1457	1478	1481	java/lang/Throwable
    //   1471	1492	1495	java/lang/Throwable
    //   1485	1506	1509	java/lang/Throwable
    //   1499	1516	1519	java/lang/Throwable
    //   1557	1571	1574	java/lang/Throwable
    //   1564	1585	1588	java/lang/Throwable
    //   1578	1599	1602	java/lang/Throwable
    //   1592	1613	1616	java/lang/Throwable
    //   1606	1627	1630	java/lang/Throwable
    //   1620	1641	1644	java/lang/Throwable
    //   1634	1655	1658	java/lang/Throwable
    //   1648	1669	1672	java/lang/Throwable
    //   1662	1686	1689	java/lang/Throwable
    //   1755	1775	1778	java/lang/Throwable
    //   1765	1792	1795	java/lang/Throwable
    //   1782	1810	1813	java/lang/Throwable
    //   1799	1827	1830	java/lang/Throwable
    //   1817	1845	1848	java/lang/Throwable
    //   1834	1862	1865	java/lang/Throwable
    //   1852	1879	1882	java/lang/Throwable
    //   1869	1904	1907	java/lang/Throwable
    //   1886	1921	1924	java/lang/Throwable
    //   1911	1938	1941	java/lang/Throwable
    //   1928	1963	1966	java/lang/Throwable
    //   1945	1980	1983	java/lang/Throwable
    //   1970	1997	2000	java/lang/Throwable
    //   1987	2018	2021	java/lang/Throwable
    //   2154	2191	2194	java/lang/Throwable
    //   2198	2241	2244	java/lang/Throwable
    //   2312	2326	2326	java/lang/Throwable
    //   2337	2350	2353	java/lang/Throwable
    //   2342	2365	2368	java/lang/Throwable
    //   2357	2383	2386	java/lang/Throwable
    //   2372	2413	2416	java/lang/Throwable
    //   2479	2506	2509	java/lang/Throwable
    //   2496	2527	2530	java/lang/Throwable
    //   2513	2557	2560	java/lang/Throwable
    //   2534	2568	2568	java/lang/Throwable
    //   2579	2595	2598	java/lang/Throwable
    //   2602	2692	2695	java/lang/Throwable
    //   2647	2744	2747	java/lang/Throwable
    //   2699	2755	2755	java/lang/Throwable
  }
  
  static {
    // Byte code:
    //   0: bipush #9
    //   2: anewarray java/lang/String
    //   5: astore #5
    //   7: iconst_0
    //   8: istore_3
    //   9: ldc '\\rÃ›ÃXLÃ¥ncÂÂ·Ã³ÃŸdVÃ¤yÃ¾Ã£Ã½8Ã¶Â˜U|ÃºÂŒ\\tÂœJOÃŒ8Â±Â¦~\\t7j:ÃˆÂ–?dqLSÂˆ[Ã…>O#Â³UcÂŸÂÃ‚wÃ»WÃ«ÃºÃ…^OÂ¾Ã'AÂµÂƒÂŒÃƒÃ¬Â„LÂ¶9zY<Â‹Ã›ÂƒÂ®Ã®Ã /Â<@\Â»XÂ£ÃœÂnaÃ^Â´Â±OÂ¶rvu:Ã¹Ã‹\\tHÂ‘ÂƒÃ®Ãµ\\fÂŸ|Â• SÃ¿Q"Â®Ã€Ã¿Ã¦Â˜Ã§hÂ¡IÂ‚Ã¼Â¨Ã·ÃŸÃ„%Â¼Â±)s^ÃˆÂš:Ã¸Â•\'
    //   11: dup
    //   12: astore_2
    //   13: invokevirtual length : ()I
    //   16: istore #4
    //   18: bipush #32
    //   20: istore_1
    //   21: iconst_m1
    //   22: istore_0
    //   23: bipush #100
    //   25: iinc #0, 1
    //   28: aload_2
    //   29: iload_0
    //   30: dup
    //   31: iload_1
    //   32: iadd
    //   33: invokevirtual substring : (II)Ljava/lang/String;
    //   36: iconst_m1
    //   37: goto -> 143
    //   40: aload #5
    //   42: swap
    //   43: iload_3
    //   44: iinc #3, 1
    //   47: swap
    //   48: aastore
    //   49: iload_0
    //   50: iload_1
    //   51: iadd
    //   52: dup
    //   53: istore_0
    //   54: iload #4
    //   56: if_icmpge -> 68
    //   59: aload_2
    //   60: iload_0
    //   61: invokevirtual charAt : (I)C
    //   64: istore_1
    //   65: goto -> 23
    //   68: ldc 'nÂ¯Â¥Ã‹Ã“JÂ¹VÂ³MÃŠÂ·C7Ã“(Â¡ÃƒÃ²j,OÂ»Â¿Ã€ NÃ¶\\nÃ§Ã±Â­Ã¬ÃÃ§Â”ÃbÃ‚Ã™Ã¬"Â¡Ã—Ã‡hk?Ã‹ÂŸ\\bÃ„4FÃ´ÂŠÂ£fÂ£TLÃœÃ£nÂ³Ã¹Ãk>Â°&QÃµ3Ã½QÂŠÂ›Â Ã®%Â³'
    //   70: dup
    //   71: astore_2
    //   72: invokevirtual length : ()I
    //   75: istore #4
    //   77: bipush #9
    //   79: istore_1
    //   80: iconst_m1
    //   81: istore_0
    //   82: bipush #66
    //   84: iinc #0, 1
    //   87: aload_2
    //   88: iload_0
    //   89: dup
    //   90: iload_1
    //   91: iadd
    //   92: invokevirtual substring : (II)Ljava/lang/String;
    //   95: iconst_0
    //   96: goto -> 143
    //   99: aload #5
    //   101: swap
    //   102: iload_3
    //   103: iinc #3, 1
    //   106: swap
    //   107: aastore
    //   108: iload_0
    //   109: iload_1
    //   110: iadd
    //   111: dup
    //   112: istore_0
    //   113: iload #4
    //   115: if_icmpge -> 127
    //   118: aload_2
    //   119: iload_0
    //   120: invokevirtual charAt : (I)C
    //   123: istore_1
    //   124: goto -> 82
    //   127: aload #5
    //   129: putstatic burp/Zek4.a : [Ljava/lang/String;
    //   132: bipush #9
    //   134: anewarray java/lang/String
    //   137: putstatic burp/Zek4.b : [Ljava/lang/String;
    //   140: goto -> 300
    //   143: dup_x2
    //   144: pop
    //   145: invokevirtual toCharArray : ()[C
    //   148: dup_x1
    //   149: arraylength
    //   150: dup_x2
    //   151: pop
    //   152: iconst_0
    //   153: istore #6
    //   155: dup2_x1
    //   156: pop2
    //   157: dup_x2
    //   158: iconst_1
    //   159: if_icmpgt -> 260
    //   162: dup2
    //   163: swap
    //   164: iload #6
    //   166: dup2_x1
    //   167: caload
    //   168: swap
    //   169: iload #6
    //   171: bipush #7
    //   173: irem
    //   174: tableswitch default -> 242, 0 -> 212, 1 -> 217, 2 -> 222, 3 -> 227, 4 -> 232, 5 -> 237
    //   212: bipush #112
    //   214: goto -> 244
    //   217: bipush #55
    //   219: goto -> 244
    //   222: bipush #48
    //   224: goto -> 244
    //   227: bipush #121
    //   229: goto -> 244
    //   232: bipush #121
    //   234: goto -> 244
    //   237: bipush #50
    //   239: goto -> 244
    //   242: bipush #97
    //   244: ixor
    //   245: ixor
    //   246: i2c
    //   247: castore
    //   248: iinc #6, 1
    //   251: dup
    //   252: ifne -> 260
    //   255: dup2
    //   256: dup_x1
    //   257: goto -> 166
    //   260: dup2_x1
    //   261: pop2
    //   262: dup_x2
    //   263: iload #6
    //   265: if_icmpgt -> 162
    //   268: pop
    //   269: new java/lang/String
    //   272: dup_x1
    //   273: swap
    //   274: invokespecial <init> : ([C)V
    //   277: invokevirtual intern : ()Ljava/lang/String;
    //   280: swap
    //   281: pop
    //   282: swap
    //   283: tableswitch default -> 40, 0 -> 99
    //   300: new java/math/BigInteger
    //   303: dup
    //   304: sipush #27760
    //   307: sipush #-20344
    //   310: invokestatic a : (II)Ljava/lang/String;
    //   313: invokespecial <init> : (Ljava/lang/String;)V
    //   316: putstatic burp/Zek4.ZR : Ljava/lang/Object;
    //   319: sipush #27773
    //   322: sipush #-12937
    //   325: invokestatic a : (II)Ljava/lang/String;
    //   328: putstatic burp/Zek4.Zo : Ljava/lang/String;
    //   331: return
  }
  
  private static Throwable a(Throwable paramThrowable) {
    return paramThrowable;
  }
  
  private static String a(int paramInt1, int paramInt2) {
    int i = (paramInt1 ^ 0x6C78) & 0xFFFF;
    if (b[i] == null) {
      char[] arrayOfChar = a[i].toCharArray();
      switch (arrayOfChar[0] & 0xFF) {
        case 0:
        
        case 1:
        
        case 2:
        
        case 3:
        
        case 4:
        
        case 5:
        
        case 6:
        
        case 7:
        
        case 8:
        
        case 9:
        
        case 10:
        
        case 11:
        
        case 12:
        
        case 13:
        
        case 14:
        
        case 15:
        
        case 16:
        
        case 17:
        
        case 18:
        
        case 19:
        
        case 20:
        
        case 21:
        
        case 22:
        
        case 23:
        
        case 24:
        
        case 25:
        
        case 26:
        
        case 27:
        
        case 28:
        
        case 29:
        
        case 30:
        
        case 31:
        
        case 32:
        
        case 33:
        
        case 34:
        
        case 35:
        
        case 36:
        
        case 37:
        
        case 38:
        
        case 39:
        
        case 40:
        
        case 41:
        
        case 42:
        
        case 43:
        
        case 44:
        
        case 45:
        
        case 46:
        
        case 47:
        
        case 48:
        
        case 49:
        
        case 50:
        
        case 51:
        
        case 52:
        
        case 53:
        
        case 54:
        
        case 55:
        
        case 56:
        
        case 57:
        
        case 58:
        
        case 59:
        
        case 60:
        
        case 61:
        
        case 62:
        
        case 63:
        
        case 64:
        
        case 65:
        
        case 66:
        
        case 67:
        
        case 68:
        
        case 69:
        
        case 70:
        
        case 71:
        
        case 72:
        
        case 73:
        
        case 74:
        
        case 75:
        
        case 76:
        
        case 77:
        
        case 78:
        
        case 79:
        
        case 80:
        
        case 81:
        
        case 82:
        
        case 83:
        
        case 84:
        
        case 85:
        
        case 86:
        
        case 87:
        
        case 88:
        
        case 89:
        
        case 90:
        
        case 91:
        
        case 92:
        
        case 93:
        
        case 94:
        
        case 95:
        
        case 96:
        
        case 97:
        
        case 98:
        
        case 99:
        
        case 100:
        
        case 101:
        
        case 102:
        
        case 103:
        
        case 104:
        
        case 105:
        
        case 106:
        
        case 107:
        
        case 108:
        
        case 109:
        
        case 110:
        
        case 111:
        
        case 112:
        
        case 113:
        
        case 114:
        
        case 115:
        
        case 116:
        
        case 117:
        
        case 118:
        
        case 119:
        
        case 120:
        
        case 121:
        
        case 122:
        
        case 123:
        
        case 124:
        
        case 125:
        
        case 126:
        
        case 127:
        
        case 128:
        
        case 129:
        
        case 130:
        
        case 131:
        
        case 132:
        
        case 133:
        
        case 134:
        
        case 135:
        
        case 136:
        
        case 137:
        
        case 138:
        
        case 139:
        
        case 140:
        
        case 141:
        
        case 142:
        
        case 143:
        
        case 144:
        
        case 145:
        
        case 146:
        
        case 147:
        
        case 148:
        
        case 149:
        
        case 150:
        
        case 151:
        
        case 152:
        
        case 153:
        
        case 154:
        
        case 155:
        
        case 156:
        
        case 157:
        
        case 158:
        
        case 159:
        
        case 160:
        
        case 161:
        
        case 162:
        
        case 163:
        
        case 164:
        
        case 165:
        
        case 166:
        
        case 167:
        
        case 168:
        
        case 169:
        
        case 170:
        
        case 171:
        
        case 172:
        
        case 173:
        
        case 174:
        
        case 175:
        
        case 176:
        
        case 177:
        
        case 178:
        
        case 179:
        
        case 180:
        
        case 181:
        
        case 182:
        
        case 183:
        
        case 184:
        
        case 185:
        
        case 186:
        
        case 187:
        
        case 188:
        
        case 189:
        
        case 190:
        
        case 191:
        
        case 192:
        
        case 193:
        
        case 194:
        
        case 195:
        
        case 196:
        
        case 197:
        
        case 198:
        
        case 199:
        
        case 200:
        
        case 201:
        
        case 202:
        
        case 203:
        
        case 204:
        
        case 205:
        
        case 206:
        
        case 207:
        
        case 208:
        
        case 209:
        
        case 210:
        
        case 211:
        
        case 212:
        
        case 213:
        
        case 214:
        
        case 215:
        
        case 216:
        
        case 217:
        
        case 218:
        
        case 219:
        
        case 220:
        
        case 221:
        
        case 222:
        
        case 223:
        
        case 224:
        
        case 225:
        
        case 226:
        
        case 227:
        
        case 228:
        
        case 229:
        
        case 230:
        
        case 231:
        
        case 232:
        
        case 233:
        
        case 234:
        
        case 235:
        
        case 236:
        
        case 237:
        
        case 238:
        
        case 239:
        
        case 240:
        
        case 241:
        
        case 242:
        
        case 243:
        
        case 244:
        
        case 245:
        
        case 246:
        
        case 247:
        
        case 248:
        
        case 249:
        
        case 250:
        
        case 251:
        
        case 252:
        
        case 253:
        
        case 254:
        
        default:
          break;
      } 
      byte b1 = 35;
      int j = (paramInt2 & 0xFF) - b1;
      if (j < 0)
        j += 256; 
      int k = ((paramInt2 & 0xFFFF) >>> 8) - b1;
      if (k < 0)
        k += 256; 
      for (byte b2 = 0; b2 < arrayOfChar.length; b2++) {
        int m = b2 % 2;
        if (m == 0) {
          arrayOfChar[b2] = (char)(arrayOfChar[b2] ^ j);
          j = ((j >>> 3 | j << 5) ^ arrayOfChar[b2]) & 0xFF;
        } else {
          arrayOfChar[b2] = (char)(arrayOfChar[b2] ^ k);
          k = ((k >>> 3 | k << 5) ^ arrayOfChar[b2]) & 0xFF;
        } 
      } 
      b[i] = (new String(arrayOfChar)).intern();
    } 
    return b[i];
  }
}


/* Location:              C:\Program Files\BurpSuitePro\burpsuite_pro.jar!\burp\Zek4.class
 * Java compiler version: 21 (65.0)
 * JD-Core Version:       1.1.3
 */