package burp;

import java.math.BigInteger;

class Zekj extends ClassLoader {
  static String ZD;
  
  static Object Zi;
  
  private static final String[] a;
  
  private static final String[] b;
  
  static void Zo(Object[] paramArrayOfObject, Object paramObject) throws Throwable {}
  
  static void Zv(Object paramObject) {
    Zb4d.ZS = a(17044, -3538);
    Zb4d.Ze = new BigInteger(1, new byte[] { 
          42, 106, -60, -71, -26, -25, -102, 82, 65, 67, 
          -10, 56, 117, 10, -92, -94, 72, -119, 72, 79, 
          -36, 124, 57, 33, -42, 114, 44, 116, 40, -107, 
          125, -17 });
    boolean bool = Zt2e.ZK();
    try {
      try {
        if (Zboa.Zq.charAt(Math.abs(((BigInteger)Zm14.ZZ).intValue() % 32)) > Zstf.ZZ.charAt(Math.abs(((BigInteger)Zl39.ZA).intValue() % 32))) {
          try {
            Zsbd.Zj(Class.forName(a(17047, 19518)));
            if (bool)
              Zmcb.Za(Class.forName(a(17042, 210))); 
          } catch (Throwable throwable) {
            throw a(null);
          } 
          return;
        } 
      } catch (Throwable throwable) {
        throw a(null);
      } 
      Zmcb.Za(Class.forName(a(17042, 210)));
    } catch (Throwable throwable) {}
  }
  
  static boolean ZS(Object[] paramArrayOfObject, Object paramObject) throws Throwable {
    // Byte code:
    //   0: invokestatic ZN : ()Z
    //   3: istore_2
    //   4: new java/lang/StringBuilder
    //   7: dup
    //   8: invokespecial <init> : ()V
    //   11: astore_3
    //   12: iconst_0
    //   13: istore #4
    //   15: iload #4
    //   17: bipush #32
    //   19: if_icmpge -> 1355
    //   22: iload #4
    //   24: tableswitch default -> 1348, 0 -> 168, 1 -> 205, 2 -> 242, 3 -> 279, 4 -> 316, 5 -> 353, 6 -> 390, 7 -> 427, 8 -> 464, 9 -> 501, 10 -> 538, 11 -> 575, 12 -> 612, 13 -> 649, 14 -> 686, 15 -> 723, 16 -> 760, 17 -> 797, 18 -> 834, 19 -> 871, 20 -> 908, 21 -> 945, 22 -> 982, 23 -> 1019, 24 -> 1056, 25 -> 1093, 26 -> 1130, 27 -> 1167, 28 -> 1204, 29 -> 1241, 30 -> 1278, 31 -> 1315
    //   168: aload_3
    //   169: getstatic burp/Zz66.ZM : Ljava/lang/String;
    //   172: getstatic burp/Zb2u.ZY : Ljava/lang/Object;
    //   175: checkcast java/math/BigInteger
    //   178: invokevirtual intValue : ()I
    //   181: bipush #32
    //   183: irem
    //   184: invokestatic abs : (I)I
    //   187: invokevirtual charAt : (I)C
    //   190: invokevirtual append : (C)Ljava/lang/StringBuilder;
    //   193: pop
    //   194: iload_2
    //   195: ifne -> 1348
    //   198: goto -> 205
    //   201: invokestatic a : (Ljava/lang/Throwable;)Ljava/lang/Throwable;
    //   204: athrow
    //   205: aload_3
    //   206: getstatic burp/Zt9f.Zg : Ljava/lang/String;
    //   209: getstatic burp/Ze8j.ZQ : Ljava/lang/Object;
    //   212: checkcast java/math/BigInteger
    //   215: invokevirtual intValue : ()I
    //   218: bipush #32
    //   220: irem
    //   221: invokestatic abs : (I)I
    //   224: invokevirtual charAt : (I)C
    //   227: invokevirtual append : (C)Ljava/lang/StringBuilder;
    //   230: pop
    //   231: iload_2
    //   232: ifne -> 1348
    //   235: goto -> 242
    //   238: invokestatic a : (Ljava/lang/Throwable;)Ljava/lang/Throwable;
    //   241: athrow
    //   242: aload_3
    //   243: getstatic burp/Zm0d.ZV : Ljava/lang/String;
    //   246: getstatic burp/Zmig.Zh : Ljava/lang/Object;
    //   249: checkcast java/math/BigInteger
    //   252: invokevirtual intValue : ()I
    //   255: bipush #32
    //   257: irem
    //   258: invokestatic abs : (I)I
    //   261: invokevirtual charAt : (I)C
    //   264: invokevirtual append : (C)Ljava/lang/StringBuilder;
    //   267: pop
    //   268: iload_2
    //   269: ifne -> 1348
    //   272: goto -> 279
    //   275: invokestatic a : (Ljava/lang/Throwable;)Ljava/lang/Throwable;
    //   278: athrow
    //   279: aload_3
    //   280: getstatic burp/Zos.Za : Ljava/lang/String;
    //   283: getstatic burp/Zlsg.ZD : Ljava/lang/Object;
    //   286: checkcast java/math/BigInteger
    //   289: invokevirtual intValue : ()I
    //   292: bipush #32
    //   294: irem
    //   295: invokestatic abs : (I)I
    //   298: invokevirtual charAt : (I)C
    //   301: invokevirtual append : (C)Ljava/lang/StringBuilder;
    //   304: pop
    //   305: iload_2
    //   306: ifne -> 1348
    //   309: goto -> 316
    //   312: invokestatic a : (Ljava/lang/Throwable;)Ljava/lang/Throwable;
    //   315: athrow
    //   316: aload_3
    //   317: getstatic burp/Zeub.ZT : Ljava/lang/String;
    //   320: getstatic burp/Zegv.ZL : Ljava/lang/Object;
    //   323: checkcast java/math/BigInteger
    //   326: invokevirtual intValue : ()I
    //   329: bipush #32
    //   331: irem
    //   332: invokestatic abs : (I)I
    //   335: invokevirtual charAt : (I)C
    //   338: invokevirtual append : (C)Ljava/lang/StringBuilder;
    //   341: pop
    //   342: iload_2
    //   343: ifne -> 1348
    //   346: goto -> 353
    //   349: invokestatic a : (Ljava/lang/Throwable;)Ljava/lang/Throwable;
    //   352: athrow
    //   353: aload_3
    //   354: getstatic burp/Zeva.Zo : Ljava/lang/String;
    //   357: getstatic burp/Zso.ZA : Ljava/lang/Object;
    //   360: checkcast java/math/BigInteger
    //   363: invokevirtual intValue : ()I
    //   366: bipush #32
    //   368: irem
    //   369: invokestatic abs : (I)I
    //   372: invokevirtual charAt : (I)C
    //   375: invokevirtual append : (C)Ljava/lang/StringBuilder;
    //   378: pop
    //   379: iload_2
    //   380: ifne -> 1348
    //   383: goto -> 390
    //   386: invokestatic a : (Ljava/lang/Throwable;)Ljava/lang/Throwable;
    //   389: athrow
    //   390: aload_3
    //   391: getstatic burp/Zmzj.Zb : Ljava/lang/String;
    //   394: getstatic burp/Zexl.ZG : Ljava/lang/Object;
    //   397: checkcast java/math/BigInteger
    //   400: invokevirtual intValue : ()I
    //   403: bipush #32
    //   405: irem
    //   406: invokestatic abs : (I)I
    //   409: invokevirtual charAt : (I)C
    //   412: invokevirtual append : (C)Ljava/lang/StringBuilder;
    //   415: pop
    //   416: iload_2
    //   417: ifne -> 1348
    //   420: goto -> 427
    //   423: invokestatic a : (Ljava/lang/Throwable;)Ljava/lang/Throwable;
    //   426: athrow
    //   427: aload_3
    //   428: getstatic burp/Zlbd.Zq : Ljava/lang/String;
    //   431: getstatic burp/Zrd2.Zt : Ljava/lang/Object;
    //   434: checkcast java/math/BigInteger
    //   437: invokevirtual intValue : ()I
    //   440: bipush #32
    //   442: irem
    //   443: invokestatic abs : (I)I
    //   446: invokevirtual charAt : (I)C
    //   449: invokevirtual append : (C)Ljava/lang/StringBuilder;
    //   452: pop
    //   453: iload_2
    //   454: ifne -> 1348
    //   457: goto -> 464
    //   460: invokestatic a : (Ljava/lang/Throwable;)Ljava/lang/Throwable;
    //   463: athrow
    //   464: aload_3
    //   465: getstatic burp/Zsn9.Zp : Ljava/lang/String;
    //   468: getstatic burp/Zm69.Zg : Ljava/lang/Object;
    //   471: checkcast java/math/BigInteger
    //   474: invokevirtual intValue : ()I
    //   477: bipush #32
    //   479: irem
    //   480: invokestatic abs : (I)I
    //   483: invokevirtual charAt : (I)C
    //   486: invokevirtual append : (C)Ljava/lang/StringBuilder;
    //   489: pop
    //   490: iload_2
    //   491: ifne -> 1348
    //   494: goto -> 501
    //   497: invokestatic a : (Ljava/lang/Throwable;)Ljava/lang/Throwable;
    //   500: athrow
    //   501: aload_3
    //   502: getstatic burp/Zsvd.ZB : Ljava/lang/String;
    //   505: getstatic burp/Zrym.Zk : Ljava/lang/Object;
    //   508: checkcast java/math/BigInteger
    //   511: invokevirtual intValue : ()I
    //   514: bipush #32
    //   516: irem
    //   517: invokestatic abs : (I)I
    //   520: invokevirtual charAt : (I)C
    //   523: invokevirtual append : (C)Ljava/lang/StringBuilder;
    //   526: pop
    //   527: iload_2
    //   528: ifne -> 1348
    //   531: goto -> 538
    //   534: invokestatic a : (Ljava/lang/Throwable;)Ljava/lang/Throwable;
    //   537: athrow
    //   538: aload_3
    //   539: getstatic burp/Zzyb.Zh : Ljava/lang/String;
    //   542: getstatic burp/Zeig.ZA : Ljava/lang/Object;
    //   545: checkcast java/math/BigInteger
    //   548: invokevirtual intValue : ()I
    //   551: bipush #32
    //   553: irem
    //   554: invokestatic abs : (I)I
    //   557: invokevirtual charAt : (I)C
    //   560: invokevirtual append : (C)Ljava/lang/StringBuilder;
    //   563: pop
    //   564: iload_2
    //   565: ifne -> 1348
    //   568: goto -> 575
    //   571: invokestatic a : (Ljava/lang/Throwable;)Ljava/lang/Throwable;
    //   574: athrow
    //   575: aload_3
    //   576: getstatic burp/Zes.ZW : Ljava/lang/String;
    //   579: getstatic burp/Zgtx.Z_ : Ljava/lang/Object;
    //   582: checkcast java/math/BigInteger
    //   585: invokevirtual intValue : ()I
    //   588: bipush #32
    //   590: irem
    //   591: invokestatic abs : (I)I
    //   594: invokevirtual charAt : (I)C
    //   597: invokevirtual append : (C)Ljava/lang/StringBuilder;
    //   600: pop
    //   601: iload_2
    //   602: ifne -> 1348
    //   605: goto -> 612
    //   608: invokestatic a : (Ljava/lang/Throwable;)Ljava/lang/Throwable;
    //   611: athrow
    //   612: aload_3
    //   613: getstatic burp/Zzl4.ZT : Ljava/lang/String;
    //   616: getstatic burp/Zrom.ZF : Ljava/lang/Object;
    //   619: checkcast java/math/BigInteger
    //   622: invokevirtual intValue : ()I
    //   625: bipush #32
    //   627: irem
    //   628: invokestatic abs : (I)I
    //   631: invokevirtual charAt : (I)C
    //   634: invokevirtual append : (C)Ljava/lang/StringBuilder;
    //   637: pop
    //   638: iload_2
    //   639: ifne -> 1348
    //   642: goto -> 649
    //   645: invokestatic a : (Ljava/lang/Throwable;)Ljava/lang/Throwable;
    //   648: athrow
    //   649: aload_3
    //   650: getstatic burp/Zrtp.Zq : Ljava/lang/String;
    //   653: getstatic burp/Zt7x.ZE : Ljava/lang/Object;
    //   656: checkcast java/math/BigInteger
    //   659: invokevirtual intValue : ()I
    //   662: bipush #32
    //   664: irem
    //   665: invokestatic abs : (I)I
    //   668: invokevirtual charAt : (I)C
    //   671: invokevirtual append : (C)Ljava/lang/StringBuilder;
    //   674: pop
    //   675: iload_2
    //   676: ifne -> 1348
    //   679: goto -> 686
    //   682: invokestatic a : (Ljava/lang/Throwable;)Ljava/lang/Throwable;
    //   685: athrow
    //   686: aload_3
    //   687: getstatic burp/Zzmc.Zr : Ljava/lang/String;
    //   690: getstatic burp/Zgsy.ZC : Ljava/lang/Object;
    //   693: checkcast java/math/BigInteger
    //   696: invokevirtual intValue : ()I
    //   699: bipush #32
    //   701: irem
    //   702: invokestatic abs : (I)I
    //   705: invokevirtual charAt : (I)C
    //   708: invokevirtual append : (C)Ljava/lang/StringBuilder;
    //   711: pop
    //   712: iload_2
    //   713: ifne -> 1348
    //   716: goto -> 723
    //   719: invokestatic a : (Ljava/lang/Throwable;)Ljava/lang/Throwable;
    //   722: athrow
    //   723: aload_3
    //   724: getstatic burp/Zegw.Zn : Ljava/lang/String;
    //   727: getstatic burp/Zg6z.ZS : Ljava/lang/Object;
    //   730: checkcast java/math/BigInteger
    //   733: invokevirtual intValue : ()I
    //   736: bipush #32
    //   738: irem
    //   739: invokestatic abs : (I)I
    //   742: invokevirtual charAt : (I)C
    //   745: invokevirtual append : (C)Ljava/lang/StringBuilder;
    //   748: pop
    //   749: iload_2
    //   750: ifne -> 1348
    //   753: goto -> 760
    //   756: invokestatic a : (Ljava/lang/Throwable;)Ljava/lang/Throwable;
    //   759: athrow
    //   760: aload_3
    //   761: getstatic burp/Zrym.ZX : Ljava/lang/String;
    //   764: getstatic burp/Zgsb.Zl : Ljava/lang/Object;
    //   767: checkcast java/math/BigInteger
    //   770: invokevirtual intValue : ()I
    //   773: bipush #32
    //   775: irem
    //   776: invokestatic abs : (I)I
    //   779: invokevirtual charAt : (I)C
    //   782: invokevirtual append : (C)Ljava/lang/StringBuilder;
    //   785: pop
    //   786: iload_2
    //   787: ifne -> 1348
    //   790: goto -> 797
    //   793: invokestatic a : (Ljava/lang/Throwable;)Ljava/lang/Throwable;
    //   796: athrow
    //   797: aload_3
    //   798: getstatic burp/Zg0f.Zd : Ljava/lang/String;
    //   801: getstatic burp/Zlwj.ZE : Ljava/lang/Object;
    //   804: checkcast java/math/BigInteger
    //   807: invokevirtual intValue : ()I
    //   810: bipush #32
    //   812: irem
    //   813: invokestatic abs : (I)I
    //   816: invokevirtual charAt : (I)C
    //   819: invokevirtual append : (C)Ljava/lang/StringBuilder;
    //   822: pop
    //   823: iload_2
    //   824: ifne -> 1348
    //   827: goto -> 834
    //   830: invokestatic a : (Ljava/lang/Throwable;)Ljava/lang/Throwable;
    //   833: athrow
    //   834: aload_3
    //   835: getstatic burp/Zma0.ZP : Ljava/lang/String;
    //   838: getstatic burp/Zb_1.ZK : Ljava/lang/Object;
    //   841: checkcast java/math/BigInteger
    //   844: invokevirtual intValue : ()I
    //   847: bipush #32
    //   849: irem
    //   850: invokestatic abs : (I)I
    //   853: invokevirtual charAt : (I)C
    //   856: invokevirtual append : (C)Ljava/lang/StringBuilder;
    //   859: pop
    //   860: iload_2
    //   861: ifne -> 1348
    //   864: goto -> 871
    //   867: invokestatic a : (Ljava/lang/Throwable;)Ljava/lang/Throwable;
    //   870: athrow
    //   871: aload_3
    //   872: getstatic burp/Zrip.Zy : Ljava/lang/String;
    //   875: getstatic burp/Zs8w.ZW : Ljava/lang/Object;
    //   878: checkcast java/math/BigInteger
    //   881: invokevirtual intValue : ()I
    //   884: bipush #32
    //   886: irem
    //   887: invokestatic abs : (I)I
    //   890: invokevirtual charAt : (I)C
    //   893: invokevirtual append : (C)Ljava/lang/StringBuilder;
    //   896: pop
    //   897: iload_2
    //   898: ifne -> 1348
    //   901: goto -> 908
    //   904: invokestatic a : (Ljava/lang/Throwable;)Ljava/lang/Throwable;
    //   907: athrow
    //   908: aload_3
    //   909: getstatic burp/Zrd2.Zj : Ljava/lang/String;
    //   912: getstatic burp/Zzre.ZE : Ljava/lang/Object;
    //   915: checkcast java/math/BigInteger
    //   918: invokevirtual intValue : ()I
    //   921: bipush #32
    //   923: irem
    //   924: invokestatic abs : (I)I
    //   927: invokevirtual charAt : (I)C
    //   930: invokevirtual append : (C)Ljava/lang/StringBuilder;
    //   933: pop
    //   934: iload_2
    //   935: ifne -> 1348
    //   938: goto -> 945
    //   941: invokestatic a : (Ljava/lang/Throwable;)Ljava/lang/Throwable;
    //   944: athrow
    //   945: aload_3
    //   946: getstatic burp/Zzts.Zk : Ljava/lang/String;
    //   949: getstatic burp/Zlbd.ZU : Ljava/lang/Object;
    //   952: checkcast java/math/BigInteger
    //   955: invokevirtual intValue : ()I
    //   958: bipush #32
    //   960: irem
    //   961: invokestatic abs : (I)I
    //   964: invokevirtual charAt : (I)C
    //   967: invokevirtual append : (C)Ljava/lang/StringBuilder;
    //   970: pop
    //   971: iload_2
    //   972: ifne -> 1348
    //   975: goto -> 982
    //   978: invokestatic a : (Ljava/lang/Throwable;)Ljava/lang/Throwable;
    //   981: athrow
    //   982: aload_3
    //   983: getstatic burp/Zg1l.Zl : Ljava/lang/String;
    //   986: getstatic burp/Zlcc.ZP : Ljava/lang/Object;
    //   989: checkcast java/math/BigInteger
    //   992: invokevirtual intValue : ()I
    //   995: bipush #32
    //   997: irem
    //   998: invokestatic abs : (I)I
    //   1001: invokevirtual charAt : (I)C
    //   1004: invokevirtual append : (C)Ljava/lang/StringBuilder;
    //   1007: pop
    //   1008: iload_2
    //   1009: ifne -> 1348
    //   1012: goto -> 1019
    //   1015: invokestatic a : (Ljava/lang/Throwable;)Ljava/lang/Throwable;
    //   1018: athrow
    //   1019: aload_3
    //   1020: getstatic burp/Zku9.Zl : Ljava/lang/String;
    //   1023: getstatic burp/Zr9u.ZX : Ljava/lang/Object;
    //   1026: checkcast java/math/BigInteger
    //   1029: invokevirtual intValue : ()I
    //   1032: bipush #32
    //   1034: irem
    //   1035: invokestatic abs : (I)I
    //   1038: invokevirtual charAt : (I)C
    //   1041: invokevirtual append : (C)Ljava/lang/StringBuilder;
    //   1044: pop
    //   1045: iload_2
    //   1046: ifne -> 1348
    //   1049: goto -> 1056
    //   1052: invokestatic a : (Ljava/lang/Throwable;)Ljava/lang/Throwable;
    //   1055: athrow
    //   1056: aload_3
    //   1057: getstatic burp/Zej8.ZP : Ljava/lang/String;
    //   1060: getstatic burp/Zmig.Zh : Ljava/lang/Object;
    //   1063: checkcast java/math/BigInteger
    //   1066: invokevirtual intValue : ()I
    //   1069: bipush #32
    //   1071: irem
    //   1072: invokestatic abs : (I)I
    //   1075: invokevirtual charAt : (I)C
    //   1078: invokevirtual append : (C)Ljava/lang/StringBuilder;
    //   1081: pop
    //   1082: iload_2
    //   1083: ifne -> 1348
    //   1086: goto -> 1093
    //   1089: invokestatic a : (Ljava/lang/Throwable;)Ljava/lang/Throwable;
    //   1092: athrow
    //   1093: aload_3
    //   1094: getstatic burp/Zm8j.Zp : Ljava/lang/String;
    //   1097: getstatic burp/Zxdp.ZW : Ljava/lang/Object;
    //   1100: checkcast java/math/BigInteger
    //   1103: invokevirtual intValue : ()I
    //   1106: bipush #32
    //   1108: irem
    //   1109: invokestatic abs : (I)I
    //   1112: invokevirtual charAt : (I)C
    //   1115: invokevirtual append : (C)Ljava/lang/StringBuilder;
    //   1118: pop
    //   1119: iload_2
    //   1120: ifne -> 1348
    //   1123: goto -> 1130
    //   1126: invokestatic a : (Ljava/lang/Throwable;)Ljava/lang/Throwable;
    //   1129: athrow
    //   1130: aload_3
    //   1131: getstatic burp/Zenr.Z_ : Ljava/lang/String;
    //   1134: getstatic burp/Zsbv.Zl : Ljava/lang/Object;
    //   1137: checkcast java/math/BigInteger
    //   1140: invokevirtual intValue : ()I
    //   1143: bipush #32
    //   1145: irem
    //   1146: invokestatic abs : (I)I
    //   1149: invokevirtual charAt : (I)C
    //   1152: invokevirtual append : (C)Ljava/lang/StringBuilder;
    //   1155: pop
    //   1156: iload_2
    //   1157: ifne -> 1348
    //   1160: goto -> 1167
    //   1163: invokestatic a : (Ljava/lang/Throwable;)Ljava/lang/Throwable;
    //   1166: athrow
    //   1167: aload_3
    //   1168: getstatic burp/Zd9.Ze : Ljava/lang/String;
    //   1171: getstatic burp/Ze2k.ZK : Ljava/lang/Object;
    //   1174: checkcast java/math/BigInteger
    //   1177: invokevirtual intValue : ()I
    //   1180: bipush #32
    //   1182: irem
    //   1183: invokestatic abs : (I)I
    //   1186: invokevirtual charAt : (I)C
    //   1189: invokevirtual append : (C)Ljava/lang/StringBuilder;
    //   1192: pop
    //   1193: iload_2
    //   1194: ifne -> 1348
    //   1197: goto -> 1204
    //   1200: invokestatic a : (Ljava/lang/Throwable;)Ljava/lang/Throwable;
    //   1203: athrow
    //   1204: aload_3
    //   1205: getstatic burp/Zz0f.ZW : Ljava/lang/String;
    //   1208: getstatic burp/Zrqe.ZX : Ljava/lang/Object;
    //   1211: checkcast java/math/BigInteger
    //   1214: invokevirtual intValue : ()I
    //   1217: bipush #32
    //   1219: irem
    //   1220: invokestatic abs : (I)I
    //   1223: invokevirtual charAt : (I)C
    //   1226: invokevirtual append : (C)Ljava/lang/StringBuilder;
    //   1229: pop
    //   1230: iload_2
    //   1231: ifne -> 1348
    //   1234: goto -> 1241
    //   1237: invokestatic a : (Ljava/lang/Throwable;)Ljava/lang/Throwable;
    //   1240: athrow
    //   1241: aload_3
    //   1242: getstatic burp/Zv8d.Zi : Ljava/lang/String;
    //   1245: getstatic burp/Zlcc.ZP : Ljava/lang/Object;
    //   1248: checkcast java/math/BigInteger
    //   1251: invokevirtual intValue : ()I
    //   1254: bipush #32
    //   1256: irem
    //   1257: invokestatic abs : (I)I
    //   1260: invokevirtual charAt : (I)C
    //   1263: invokevirtual append : (C)Ljava/lang/StringBuilder;
    //   1266: pop
    //   1267: iload_2
    //   1268: ifne -> 1348
    //   1271: goto -> 1278
    //   1274: invokestatic a : (Ljava/lang/Throwable;)Ljava/lang/Throwable;
    //   1277: athrow
    //   1278: aload_3
    //   1279: getstatic burp/Zr1h.ZS : Ljava/lang/String;
    //   1282: getstatic burp/Zreu.Zi : Ljava/lang/Object;
    //   1285: checkcast java/math/BigInteger
    //   1288: invokevirtual intValue : ()I
    //   1291: bipush #32
    //   1293: irem
    //   1294: invokestatic abs : (I)I
    //   1297: invokevirtual charAt : (I)C
    //   1300: invokevirtual append : (C)Ljava/lang/StringBuilder;
    //   1303: pop
    //   1304: iload_2
    //   1305: ifne -> 1348
    //   1308: goto -> 1315
    //   1311: invokestatic a : (Ljava/lang/Throwable;)Ljava/lang/Throwable;
    //   1314: athrow
    //   1315: aload_3
    //   1316: getstatic burp/Zlw8.Zs : Ljava/lang/String;
    //   1319: getstatic burp/Zzah.Za : Ljava/lang/Object;
    //   1322: checkcast java/math/BigInteger
    //   1325: invokevirtual intValue : ()I
    //   1328: bipush #32
    //   1330: irem
    //   1331: invokestatic abs : (I)I
    //   1334: invokevirtual charAt : (I)C
    //   1337: invokevirtual append : (C)Ljava/lang/StringBuilder;
    //   1340: pop
    //   1341: goto -> 1348
    //   1344: invokestatic a : (Ljava/lang/Throwable;)Ljava/lang/Throwable;
    //   1347: athrow
    //   1348: iinc #4, 1
    //   1351: iload_2
    //   1352: ifne -> 15
    //   1355: sipush #17043
    //   1358: sipush #31868
    //   1361: invokestatic a : (II)Ljava/lang/String;
    //   1364: invokestatic forName : (Ljava/lang/String;)Ljava/lang/Class;
    //   1367: invokevirtual getDeclaredFields : ()[Ljava/lang/reflect/Field;
    //   1370: astore #4
    //   1372: aload #4
    //   1374: arraylength
    //   1375: istore #5
    //   1377: iconst_0
    //   1378: istore #6
    //   1380: iload #6
    //   1382: iload #5
    //   1384: if_icmpge -> 1461
    //   1387: aload #4
    //   1389: iload #6
    //   1391: aaload
    //   1392: astore #7
    //   1394: aload #7
    //   1396: invokevirtual getType : ()Ljava/lang/Class;
    //   1399: ldc java/lang/String
    //   1401: invokevirtual equals : (Ljava/lang/Object;)Z
    //   1404: ifeq -> 1447
    //   1407: aload #7
    //   1409: iconst_1
    //   1410: invokevirtual setAccessible : (Z)V
    //   1413: aload #7
    //   1415: aconst_null
    //   1416: aload #7
    //   1418: aconst_null
    //   1419: invokevirtual get : (Ljava/lang/Object;)Ljava/lang/Object;
    //   1422: checkcast java/lang/String
    //   1425: getstatic burp/Zekj.ZD : Ljava/lang/String;
    //   1428: <illegal opcode> makeConcatWithConstants : (Ljava/lang/String;Ljava/lang/String;)Ljava/lang/String;
    //   1433: invokevirtual set : (Ljava/lang/Object;Ljava/lang/Object;)V
    //   1436: iload_2
    //   1437: ifne -> 1461
    //   1440: goto -> 1447
    //   1443: invokestatic a : (Ljava/lang/Throwable;)Ljava/lang/Throwable;
    //   1446: athrow
    //   1447: iinc #6, 1
    //   1450: iload_2
    //   1451: ifne -> 1380
    //   1454: goto -> 1461
    //   1457: invokestatic a : (Ljava/lang/Throwable;)Ljava/lang/Throwable;
    //   1460: athrow
    //   1461: sipush #17045
    //   1464: sipush #-21851
    //   1467: invokestatic a : (II)Ljava/lang/String;
    //   1470: iconst_1
    //   1471: ldc burp/Ztvn
    //   1473: invokevirtual getClassLoader : ()Ljava/lang/ClassLoader;
    //   1476: invokestatic forName : (Ljava/lang/String;ZLjava/lang/ClassLoader;)Ljava/lang/Class;
    //   1479: invokevirtual getDeclaredFields : ()[Ljava/lang/reflect/Field;
    //   1482: astore #4
    //   1484: aload #4
    //   1486: arraylength
    //   1487: istore #5
    //   1489: iconst_0
    //   1490: istore #6
    //   1492: iload #6
    //   1494: iload #5
    //   1496: if_icmpge -> 1634
    //   1499: aload #4
    //   1501: iload #6
    //   1503: aaload
    //   1504: astore #7
    //   1506: aload #7
    //   1508: invokevirtual getModifiers : ()I
    //   1511: invokestatic isStatic : (I)Z
    //   1514: ifne -> 1524
    //   1517: goto -> 1627
    //   1520: invokestatic a : (Ljava/lang/Throwable;)Ljava/lang/Throwable;
    //   1523: athrow
    //   1524: aload #7
    //   1526: invokevirtual getType : ()Ljava/lang/Class;
    //   1529: astore #8
    //   1531: aload #8
    //   1533: ifnull -> 1614
    //   1536: aload #8
    //   1538: invokevirtual isPrimitive : ()Z
    //   1541: ifne -> 1614
    //   1544: goto -> 1551
    //   1547: invokestatic a : (Ljava/lang/Throwable;)Ljava/lang/Throwable;
    //   1550: athrow
    //   1551: aload #8
    //   1553: invokevirtual getPackage : ()Ljava/lang/Package;
    //   1556: ifnull -> 1614
    //   1559: goto -> 1566
    //   1562: invokestatic a : (Ljava/lang/Throwable;)Ljava/lang/Throwable;
    //   1565: athrow
    //   1566: aload #8
    //   1568: invokevirtual getPackage : ()Ljava/lang/Package;
    //   1571: invokevirtual getName : ()Ljava/lang/String;
    //   1574: ifnull -> 1614
    //   1577: goto -> 1584
    //   1580: invokestatic a : (Ljava/lang/Throwable;)Ljava/lang/Throwable;
    //   1583: athrow
    //   1584: aload #8
    //   1586: invokevirtual getPackage : ()Ljava/lang/Package;
    //   1589: invokevirtual getName : ()Ljava/lang/String;
    //   1592: sipush #17052
    //   1595: sipush #10328
    //   1598: invokestatic a : (II)Ljava/lang/String;
    //   1601: invokevirtual startsWith : (Ljava/lang/String;)Z
    //   1604: ifne -> 1614
    //   1607: goto -> 1614
    //   1610: invokestatic a : (Ljava/lang/Throwable;)Ljava/lang/Throwable;
    //   1613: athrow
    //   1614: aload #7
    //   1616: iconst_1
    //   1617: invokevirtual setAccessible : (Z)V
    //   1620: aload #7
    //   1622: aconst_null
    //   1623: invokevirtual get : (Ljava/lang/Object;)Ljava/lang/Object;
    //   1626: pop
    //   1627: iinc #6, 1
    //   1630: iload_2
    //   1631: ifne -> 1492
    //   1634: sipush #17040
    //   1637: sipush #-22847
    //   1640: invokestatic a : (II)Ljava/lang/String;
    //   1643: invokestatic forName : (Ljava/lang/String;)Ljava/lang/Class;
    //   1646: invokevirtual getDeclaredMethods : ()[Ljava/lang/reflect/Method;
    //   1649: astore #4
    //   1651: aload #4
    //   1653: arraylength
    //   1654: istore #5
    //   1656: iconst_0
    //   1657: istore #6
    //   1659: iload #6
    //   1661: iload #5
    //   1663: if_icmpge -> 1796
    //   1666: aload #4
    //   1668: iload #6
    //   1670: aaload
    //   1671: astore #7
    //   1673: aload #7
    //   1675: invokevirtual getParameterTypes : ()[Ljava/lang/Class;
    //   1678: pop
    //   1679: aload #7
    //   1681: invokevirtual getModifiers : ()I
    //   1684: invokestatic isStatic : (I)Z
    //   1687: ifeq -> 1782
    //   1690: aload #7
    //   1692: invokevirtual getParameterTypes : ()[Ljava/lang/Class;
    //   1695: arraylength
    //   1696: iconst_2
    //   1697: if_icmpne -> 1782
    //   1700: goto -> 1707
    //   1703: invokestatic a : (Ljava/lang/Throwable;)Ljava/lang/Throwable;
    //   1706: athrow
    //   1707: aload #7
    //   1709: invokevirtual getReturnType : ()Ljava/lang/Class;
    //   1712: getstatic java/lang/Void.TYPE : Ljava/lang/Class;
    //   1715: invokevirtual equals : (Ljava/lang/Object;)Z
    //   1718: ifeq -> 1782
    //   1721: goto -> 1728
    //   1724: invokestatic a : (Ljava/lang/Throwable;)Ljava/lang/Throwable;
    //   1727: athrow
    //   1728: aload #7
    //   1730: iconst_1
    //   1731: invokevirtual setAccessible : (Z)V
    //   1734: aload #7
    //   1736: aconst_null
    //   1737: iconst_2
    //   1738: anewarray java/lang/Object
    //   1741: dup
    //   1742: iconst_0
    //   1743: aload_0
    //   1744: aastore
    //   1745: dup
    //   1746: iconst_1
    //   1747: aload_1
    //   1748: ifnonnull -> 1766
    //   1751: goto -> 1758
    //   1754: invokestatic a : (Ljava/lang/Throwable;)Ljava/lang/Throwable;
    //   1757: athrow
    //   1758: aload_1
    //   1759: goto -> 1773
    //   1762: invokestatic a : (Ljava/lang/Throwable;)Ljava/lang/Throwable;
    //   1765: athrow
    //   1766: aload_1
    //   1767: checkcast [B
    //   1770: invokevirtual clone : ()Ljava/lang/Object;
    //   1773: aastore
    //   1774: invokevirtual invoke : (Ljava/lang/Object;[Ljava/lang/Object;)Ljava/lang/Object;
    //   1777: pop
    //   1778: iload_2
    //   1779: ifne -> 1796
    //   1782: iinc #6, 1
    //   1785: iload_2
    //   1786: ifne -> 1659
    //   1789: goto -> 1796
    //   1792: invokestatic a : (Ljava/lang/Throwable;)Ljava/lang/Throwable;
    //   1795: athrow
    //   1796: getstatic burp/Zr2q.ZA : Ljava/lang/String;
    //   1799: getstatic burp/Zt5t.Za : Ljava/lang/Object;
    //   1802: checkcast java/math/BigInteger
    //   1805: invokevirtual intValue : ()I
    //   1808: bipush #32
    //   1810: irem
    //   1811: invokestatic abs : (I)I
    //   1814: invokevirtual charAt : (I)C
    //   1817: getstatic burp/Zxy6.ZR : Ljava/lang/String;
    //   1820: getstatic burp/Zml9.ZH : Ljava/lang/Object;
    //   1823: checkcast java/math/BigInteger
    //   1826: invokevirtual intValue : ()I
    //   1829: bipush #32
    //   1831: irem
    //   1832: invokestatic abs : (I)I
    //   1835: invokevirtual charAt : (I)C
    //   1838: if_icmple -> 1945
    //   1841: getstatic burp/Zt7x.Zu : Ljava/lang/String;
    //   1844: getstatic burp/Zxzv.Zg : Ljava/lang/Object;
    //   1847: checkcast java/math/BigInteger
    //   1850: invokevirtual intValue : ()I
    //   1853: bipush #32
    //   1855: irem
    //   1856: invokestatic abs : (I)I
    //   1859: invokevirtual charAt : (I)C
    //   1862: getstatic burp/Zlxr.ZS : Ljava/lang/String;
    //   1865: getstatic burp/Zzc9.ZZ : Ljava/lang/Object;
    //   1868: checkcast java/math/BigInteger
    //   1871: invokevirtual intValue : ()I
    //   1874: bipush #32
    //   1876: irem
    //   1877: invokestatic abs : (I)I
    //   1880: invokevirtual charAt : (I)C
    //   1883: if_icmple -> 1945
    //   1886: goto -> 1893
    //   1889: invokestatic a : (Ljava/lang/Throwable;)Ljava/lang/Throwable;
    //   1892: athrow
    //   1893: getstatic burp/Zmh3.Zy : Ljava/lang/String;
    //   1896: getstatic burp/Ze84.Zj : Ljava/lang/Object;
    //   1899: checkcast java/math/BigInteger
    //   1902: invokevirtual intValue : ()I
    //   1905: bipush #32
    //   1907: irem
    //   1908: invokestatic abs : (I)I
    //   1911: invokevirtual charAt : (I)C
    //   1914: getstatic burp/Zr1t.Ze : Ljava/lang/String;
    //   1917: getstatic burp/Ztq4.ZA : Ljava/lang/Object;
    //   1920: checkcast java/math/BigInteger
    //   1923: invokevirtual intValue : ()I
    //   1926: bipush #32
    //   1928: irem
    //   1929: invokestatic abs : (I)I
    //   1932: invokevirtual charAt : (I)C
    //   1935: if_icmpgt -> 1953
    //   1938: goto -> 1945
    //   1941: invokestatic a : (Ljava/lang/Throwable;)Ljava/lang/Throwable;
    //   1944: athrow
    //   1945: iconst_1
    //   1946: goto -> 1954
    //   1949: invokestatic a : (Ljava/lang/Throwable;)Ljava/lang/Throwable;
    //   1952: athrow
    //   1953: iconst_0
    //   1954: ireturn
    //   1955: astore_3
    //   1956: new java/lang/Exception
    //   1959: dup
    //   1960: aload_3
    //   1961: invokevirtual getMessage : ()Ljava/lang/String;
    //   1964: invokespecial <init> : (Ljava/lang/String;)V
    //   1967: athrow
    // Exception table:
    //   from	to	target	type
    //   4	1954	1955	java/lang/Throwable
    //   22	198	201	java/lang/Throwable
    //   168	235	238	java/lang/Throwable
    //   205	272	275	java/lang/Throwable
    //   242	309	312	java/lang/Throwable
    //   279	346	349	java/lang/Throwable
    //   316	383	386	java/lang/Throwable
    //   353	420	423	java/lang/Throwable
    //   390	457	460	java/lang/Throwable
    //   427	494	497	java/lang/Throwable
    //   464	531	534	java/lang/Throwable
    //   501	568	571	java/lang/Throwable
    //   538	605	608	java/lang/Throwable
    //   575	642	645	java/lang/Throwable
    //   612	679	682	java/lang/Throwable
    //   649	716	719	java/lang/Throwable
    //   686	753	756	java/lang/Throwable
    //   723	790	793	java/lang/Throwable
    //   760	827	830	java/lang/Throwable
    //   797	864	867	java/lang/Throwable
    //   834	901	904	java/lang/Throwable
    //   871	938	941	java/lang/Throwable
    //   908	975	978	java/lang/Throwable
    //   945	1012	1015	java/lang/Throwable
    //   982	1049	1052	java/lang/Throwable
    //   1019	1086	1089	java/lang/Throwable
    //   1056	1123	1126	java/lang/Throwable
    //   1093	1160	1163	java/lang/Throwable
    //   1130	1197	1200	java/lang/Throwable
    //   1167	1234	1237	java/lang/Throwable
    //   1204	1271	1274	java/lang/Throwable
    //   1241	1308	1311	java/lang/Throwable
    //   1278	1341	1344	java/lang/Throwable
    //   1394	1440	1443	java/lang/Throwable
    //   1407	1454	1457	java/lang/Throwable
    //   1506	1520	1520	java/lang/Throwable
    //   1531	1544	1547	java/lang/Throwable
    //   1536	1559	1562	java/lang/Throwable
    //   1551	1577	1580	java/lang/Throwable
    //   1566	1607	1610	java/lang/Throwable
    //   1673	1700	1703	java/lang/Throwable
    //   1690	1721	1724	java/lang/Throwable
    //   1707	1751	1754	java/lang/Throwable
    //   1728	1762	1762	java/lang/Throwable
    //   1773	1789	1792	java/lang/Throwable
    //   1796	1886	1889	java/lang/Throwable
    //   1841	1938	1941	java/lang/Throwable
    //   1893	1949	1949	java/lang/Throwable
  }
  
  static {
    // Byte code:
    //   0: bipush #9
    //   2: anewarray java/lang/String
    //   5: astore #5
    //   7: iconst_0
    //   8: istore_3
    //   9: ldc '¨@~uÅÞTWQ%øä½ç\\tTêïèñ'YIÌ\\bF¦ªëKÕ'
    //   11: dup
    //   12: astore_2
    //   13: invokevirtual length : ()I
    //   16: istore #4
    //   18: bipush #32
    //   20: istore_1
    //   21: iconst_m1
    //   22: istore_0
    //   23: bipush #66
    //   25: iinc #0, 1
    //   28: aload_2
    //   29: iload_0
    //   30: dup
    //   31: iload_1
    //   32: iadd
    //   33: invokevirtual substring : (II)Ljava/lang/String;
    //   36: iconst_m1
    //   37: goto -> 203
    //   40: aload #5
    //   42: swap
    //   43: iload_3
    //   44: iinc #3, 1
    //   47: swap
    //   48: aastore
    //   49: iload_0
    //   50: iload_1
    //   51: iadd
    //   52: dup
    //   53: istore_0
    //   54: iload #4
    //   56: if_icmpge -> 68
    //   59: aload_2
    //   60: iload_0
    //   61: invokevirtual charAt : (I)C
    //   64: istore_1
    //   65: goto -> 23
    //   68: ldc 'êÎz¶2>Mè¾Ò^Ò~M¾Ö0.±¯·Ó\³>Æ²6¿§ÆþÜðöº©\\bó¡{*è£Ñ_èMÖÀþú'á¸²VKÊ(Od¾¹¿x^®ï]BÓæ²zôKª:I`ØN¼KþÉ)aÎèWêöÎ6~ïaúIhP__QWOå%ÄÄDvA A7Ûø±S0ö¹>Å·s²gÙWý¬ù®ò¥±Ù|?Ø¤[ ¹ ¹b~oütòãDo³:£Øïiñóry)ëïìüÝ"þcéM¨yC¿%ÈE0}Ê?×9`¶>¼P¸ÍÒ¸¯5ñ,÷Ñ3åGÄu¯\\bï±Z[_l×_»u\ÆTY-¦\\t÷Pnï×«\\fôáïÛ';Øk§w>yJàh,k²H©~Id*e9;¤\\fpä -õmÈ>Â\\tIhÝ>Bq\ø¬eÌÞ\\núm²K~ÖÎ]¸Dõ´ÙÁ1³½õF@°r9@orþÊÐT]b)nx¡{gýµ·ç7¹k-¯øö`á¶1¶1)<ÙS9!Ës"Øå}U¨±Ýt¬³wNüEI?´r`kÙ²R»Þa£ëOLÓ©yÎ¤  \\b:<Ë!Té$`CÛ\ÚêIÌc7úÔW´Ñ1Ó7ä\g'{ ïóT2]B©ã«*S\\f5&,kY=)À)B£Öþ`Hô±\\ncæßÕó;°Ñâ^oûXÇå9\\n^ÆUÂAWRêoÃß£zi§Á¬tÍÖ³Ôø«Ã(Ô«½ßÛßyàzÃ¨AÁÁµ§5\\t Ç)WiNCýøZÕÄ7%ÂÑ!\\tó>lb«.53¬P%éoJmt}al}ù;jg½ÁO`«®ë»ÿÙ¹\\t¯Ì½7>TÅ¥ê¿(zC¸ÇsG\\r:±]iôOÝ-Ë|pë>uè^'®gA!®`ªé·Lã<>oD4¼öÝeÒìÒ'X¬ö}tèÂERó)æøàÍáíýÚÞ9Oç:ð\\f´³¸ß9"fé±¥Oæ¹+%6+Ï[¹ÁiFìÀG½1K£ý_!Fµ¸ãN+¿kwo¯fOz~¶Å2(·Òþ@×È%òÂ)öÇÞFS|§%npÁI½Z)ÕsLí¹Ú]ÍvU?_ÍjÚ¤Ùõ*½Ä"HxÑì¼ÿã(8öÅ#ôf*Gyl·¯8æ8'z°Ë 5é¯K:äÞ¼ï\\fÿpNÍ­.BJ|ÛCvp@ÆAOÕC·\\tk¥X8ØBq*ÆsÈÞM·ÍØPÉ=#ýò©¸ñ(¬,éyy²a1¿ ÚPiæ²|0u¾ãÎ¹\\tD\\b¤è<xvÖÔÚmã}kùýrÍ`ÁÖîJSµ¤þð'ÛÝWB¨aá°æaK\\fåøµJ:úT%"pF_º²ù~]b#ô¬W8Ñ;cU²;Kc¦2ôä¢úÿèÌì=O£Æ£ÖQ±¢,pTv\TÝi¢F¤ÍÞF!æ-Õ"Í>ò¶""7½*m¥oªÔMóiÏÏ\\tG{§UçtÏ7J¿Ònö5Âç\\be~âî¯Êëé¢TP\\t1Í`@1Æºà¯¬å<t,-(ï×8tÍWoÿæ´ ôK&zØÇ!ÛÍª;ÝDµUÜêçªQE°aVg/¿&"½,Y¶1^Ñy¼¥í%N^é#SJ8d«¶ûìÍ*T¤Í@Í¬Åäá_¥B,;þ,û^3g§<û\\r@ª¡ÖxCdj KK»^j¦Ã÷Ø¦8½Ú&Go: \\rb£hÞ)5;Ø²yÚã~9hhT=!6wÆ§ô²Ðº²_ÝUPOÔxô¯/¤mnµÕpoy+9uAþQ^¤{{zbpqNùÿÇÖ,¿ð8.ºï¼@Þ×l,ÜHò4Z¦òDYr©é´~`ã(E¼M³ÉiÑ5þeR°"ÂØKhL0É=Æ÷e¹âz½]BËÏð^²\\bsº?*½u©xNÛÅkÙ§¦ïù+ÇsôdÑ=_Rë}¨r.²Ð4çú¬Ôº.þ*²:\s'Táê¶v)>ö\\bà(ÒtfØæwá½,_Á_ B\\t<¿¥\\nxàçJJÌäQWàìÊ?`¹rn ;ÓÈH4¤ÎhÄíÑ¶ðAÄAÙæÀ« lÕ{KªD#>_­ÃÂBªÈMµ²fPl´´s+ùpýÿ)öÓ5:ÔètqsÁl§½ãjØzÅé¼ómEÉcýÑ|r»þ.q\\t^+§KN-eyIÖý\\t`ÓaFHº¯3ìï:vñËøy^GW76ÔÈ,"®Í¸8rô¬¯\\f[ø_AÒ¢zXàªõ6>,yGí\\bñ*òñHL\\b´¹nÌ3òúÅ³êI¸ULâÀàµnÒth÷oàýÈ&»¶ìfPÏ\\fNP.½Ø?©}@tÊ3 ×ïÐÏ§å+Å¯»¨ÓöÇàõNdßàð4uª\\rg,þW>a!vE!­/×bbVq°Àéöz] UÛmfãzÐ¥%CR~¢Ïyü\\rHç²BãÃ.\\r£®ÌhK]]ÇìUüí\\r£ÓVC¡ó¬Û¨0¸Öõ¯¦TÉ!ó6a×Ãõl\\tdò2\\fBý@UN5"EIúÎ7ýÊpüh.àá©7&&öApNÞ»×>(h~ÖÚDïÝÒ¼ní ï 7Jæ:ÛºÚ {OÈ tã;»ùJP÷èüvn¯YðýÏ¨FWPSþ\\f\ñB­ùS% f¦¥|\/áH=ãÌR,µoªz\\f$QQ#BÉî¸°»Ó¡¤ñõÎv@ù,óË8¬P\\t7rßTãN_x_>ÁYºµî®´0z½sZë þ<6m§ó)Ñî³ß­SoÛþ\\tÌ[Èw¹µ7¨¶fÃxw-¬»-®Fìye®÷Ì_¨ÚDM ©ieÕz«\\n`Jª}°ªÕçñåËîXLä½4²Rsî<Õp¹yÎnµ±z\\bu³ÕZìN'ß8{@=áñ7Lø·` Z^Á;­ªÖå¡1ðjOBÌFL¢êfÛ2è&^êö'²ëÅ;"Ùu{uÇ&]Ñ+Îøt`®VHà )¥ÍÖ¨1\\bEw+×EWðÊ±¤x(Ù£H"Ëg¡³J5káÑlo¶X4\8°Ù.ö`ÒÐ ÏvÔ´DQ[ÌËãôWýbhQ)5ÛX°Á+µ\Ã#\\tÔWE-é£G\\r¾öÁ)ÿì4±+g`,sÞï B²PïH @ßÙì\\b¨\\r¡¶$eÃ¦]9þÝi°2gÁ~\\\t°×Ë@cWý]¾ìïí1jö¹ó]h=;>rmFHÒ$ImMmÖÞS³\\r É)®­±ÃnÇ¢ú úûýzßMÿo ÷RB1än©Ey²°®i .§u­0f2ÀVÎá#»éD½Vw§¦`ªUÓçé÷Âr°oÿ+SwE?Þ¹cf\\nWúÙrçÆ xTÓ)ï rSÚ_5H½²Ï&¢ÔLíÎÊ7ÛéEOzñîZÔåùï¸e­nO§ye\!Aöa^¿BîÛu¿?¯åcîÚ8i#ÑíhÄxäÂ&&>F*ÔÍ¦ò1Ú*E^,8kFvej¼´KÇD®1ýÏÐöñ°4«53cuè=K°õÜ¬ì²#Ü¬òVgdÿOyC¦V'äb%¦fIÛ·m©ÏÇºôïLâYó&Êú W¾I´IãÂqÓ¬ÄÑææ®vj#çtHJ§h5c88Î.;pMm¦¾Q?Õ\\f+J$Gúêæ° <üD|k¿ Æè¬Èå¡ÞRû§VèÔÏVcÍ8'¯w¢ÌûVmwäéÒfÿ_\R2&Ø!Û8kåm-öã\\tìÝ¾k2üû1ÝMç=Ý9ëR H.ñãè:G ð/ÌeÝr»RÏF\E\\t¿>S_LÐHG>éX«\\fÚn/L×úÆ·ÀúP·lô¨w<ÙöÙêÀ3 bQ¡\\fïÜ?/à-9nÏÉH8-¡ãWH#cEUý¸Ï*Aãò6£¬ãæÂ¤ Uò\\tBÓç¼~BfîG\\f\\fcaØ/åÂ½ù¹ùnÑzûn\\rqüä¢JÐ£o\\f¨Û¢çÙBLbÁÑ±K0@ÜÄ¢Cv@z´£æ»ÙXPîPbÆ_©BGÜ6ÐÃk_ÛðÓtö·µñý}®Wôg¼uTÛ¢ªí.ÑÝ6=øÀSí¤6Â*CÈI#¢Ù kNGD¡cÏ5ã~³\\tïv1O¨dò®aqÆvTA$D¿Ã©He³p 4qTÂ¼¶&ôÞNKMÏµNG°­ZP2\\t¬Z\\tÎ~Óý<Ùrr(­æï1Â&N×ë ê© tíñe;ÐBáv³:³ÀOtøsWýXÁ©(}uEÄRqÆIj¿7;îÜ-k }ªùåJÔÑ]£ ë|ªÔ"ó\\bË[|&´¬kì©mô+e~¯¾Az?\\nï\\rcûK°E!~ãÜ¨ÿÎ' >¬AÉ×¸Åý`Ó&Qÿó¢b I¾d,8Øf=§5î­^OS¥ %]¡0b¬5Ì£Oìà÷:ÕqWÎ»)Ú£Î;L_ÄïOt£h]ÏîãÊln`Q«*|Y¿.Dlªvå\\t¡PëQü"vTÚ( Í¼0BGáX}¥3ÔL/)ÝÀYBùì=9HNøØ¦+?g\\fqààÕóÖ®Þzµb«Ì\\b¢lQíÂÀ%f°x3)ÿ@æ¸ô¶ë¾/³svàÂ­÷gÍó¨yaÔóo6qÑ\\r_òß^Ìm¢1¯4s^8#u~Ø~@*V1t(+@µn¸)tZÀnåcqvd`ÿg]¹d\\n¤ÞÄ9°ÜHQÄ`\\tÄÙ®7K¬kâ·çº©0ÒËÜ¹^ájéWéxwl±PZ%©ü:OææD;ÙÝKpØçQÅáµ>8Ë¹Ö\\t.JE[ô)Ô÷Qv.O\ÂaReÅ(è+a«¶¨vA~mHÍÜòS¸P3 Öá+³oãc Ú®nsîÈª£\\fË3Ê-Áz\¢1´nëèº3Â=ÔkÕü¿ÏÑ°cu@}[C8ªÒûk9}-ª,áÖKÿ'¬Íu²WðìsöÔ'?ÂÈPY"¯à¹îUµdÑÄâ8-\\t2qÓíMLlUùq\\rÓÉÐ½7ÏÆëÛ}3ÉtQ~Û$CÖÝuá&d0Á2²ÿ­)²!\\b¬æ^åè"êç1í¼P'FÀ&»>þäY¶ö3ñ¡Äì5FþÈQ±wñ¶õG¾eY;ÜÀªÿ+lô\¿jraì<²U<àù°Õ#Ð.÷Íè:ºG×¸ø=NYEßØ;BêøÜ&)z0ÚhT£ÌIhA_ÉéG:Ô]2¥}m³GÔ#½\\n`/2 °CCåeVO& ¼ñö³\@µÍhp æO3?8±D¦ 3ùºØ¦º¡ÿWÁ¨j_5a°ál,RzÓS©i7Ê¶áÊIÝJ{µ°nÞÝôÞsØÇ²(Ù\\fíjiôÞõá\\t¾Uîì:ÎàS®yf#bü7qò­AÞý¸¸\\b½öCÐ\\bÙëìñADÜ<Yí)QELÀ9pmH~Î¯ùlk_d3L zOÚrf2GÛÃMLèLn%8Aoj¹«õNç1YýnºrË¯Ü×Aw< øÛ¼ÃÕÐ£î¸k^ÁEÉMúù(ËD(Geñ¤ëOmü/\\tL<ûoT.TÁU·dL;kr"yü? ô2cjã`¼xÐáSXqwù2N<f´ óð5 |ûâ@M»èîÖ`BÝt;ùd-n*é#%»wXë¨c²èÙÐðB¢o;.VØ$á;íR\\tÍÈaCú]ö9×*{äTÁKÈaý)YlØ³8VæJã'äô'bdì*Fr¾Jùµä(seô"sÔÅ\#¤cºwïuDjã>´+­´ GÕ_V`$çS6NÐ\\f+h6Éx±Í«R&FÏLÅá÷ÂÌ¥¹þá7UôálßU©Ô¬)¶¯©0ÚL{ÙE kÔiô¾0eõpÚá ©`?FiÛÕÜÒ»=NòvrÂOÇ¬§nn7Ñ=¬ç0sxíTÕ¼4|\\bnµKZR«ÝÓgSûÛ¶ ·.`Õr¶J¤¯aÆ,4k}FÉÕ°ïíê&±¢¶r}>¨0J1þ%iQF÷^>E`w·#±\\t/âx"-«.wupúÜÐjk5Ø5ZÎ;:AxO*ß¢íÑw$RÌYÖ9<Å¦ò¤_<wìü1n%mÔã¨ôoM±\\tèñøüýJô´âaô8óOsój$Ól¨wØÕë-Ð&Òd=f?¬Û5ÊÙê8´3÷Ï¢ç(ë¤<\\füÓ"µU6[ñò~í2%á:a{vÆÕú6ìÉøÛÃ\\rÎ±­OU|¡b]ú»<¼aþ ?bê¤ÔÓldC77í1ôÑZeÏÆõmdê~m4æýKÞÒF°ÀwVEW,·ü©ný\\bÃßã&Ã xî@ÂiR­QçRªý cÏ:#RPqR^î6¯h¾ko&í'¾beµ`LX¯Pùý·I$Ê°ÀÄNÕ$íïÃ÷Sì& qßØô;_M Ù|cuÁ8¾áWN¾Ò¹ÎoÒf-¤ÁÊü(Kçà3qm¥\÷o-\\tòõ>)ÒaØr¦úRK\\fUå¢o}¶vPAèi¿±Z,ÍïKt½Ìªèfª,ÖãàèëÐKÛÛQRVïÄ*²ò>í!îi\\nE`/x$l¯®Æ¡|HS¥#NôºûD¥u@ßõH(Êà§A>)P¦ü9ñû%øêåBR£þy&y£sfCbÏìR¯FÔ§Úkæ}d+g~õM`Q¹¬ÇcK5Hc\\b QlõK/ÝÇÌGº<Y¥3åkßâ¤ $ÈÔÊûêcÃPsæå¿©xÁDÇö°ê§*@\\nå~Yßx\\r@¯GbÙd½ü·\î7 x¯:¦\\tâRB.MØ­I³WWOél{¶;|9`ZQ6º4##°\\r÷ÖXÒ«»²¼Í÷H41r^ùµèÊR}²«àh^mÈ!®.dÙ_¹Ì=væ¦=å ¸oÃ¡ÒnXÖUk$<âÜEj|6ä~\\fÓVç 3dMEîv®$~ÍuÌükjð¸Kæ*þ3§\\txi\\nÍíaqþ%Ãáp%â²BÈÉ¹4éþÓS0JIÇZêàÃ£ÓääèÄý´Bù¥¹Äóï¤®£ËqÉþ$R÷1Í§rK/Ä6Åªæ2ìº´\\rU8[ä^D×Ä¬ÁìTvÀ°\\reÈ3Ríkºöêçæä M¯Ð¾ãö¤\\f¿Àí¸å&.d^`ß?L¸(åÎ¨7u>Ç§U¨ûóÖ¨¼3°jWÌ5gÎ#D­ÐNüâ°¹b#ë°Õ£-Ü{\\bã}QüÙü^A°%þ2®ãuTú¼¦åÇh¾á¡BÝ&^¶+ÿo¹\^ +çyáØên(ÒÂä&´´@lPÿ¦¬=»ÃåU=ÞZoµ2J1ÐÍÍõn±ásÆío_£û¡º££Hß´>AKÅbV|ªcçAÌ`µÑíÙàaàn¥vn­áGÖÔ+!o\\rf®g!w¥ÓçÒaÑ{ñGb9\\tÌ~H#'÷Ow=TjhòákÂ®Q3­ÎICßÁIÍÃnÙ¬j ±éwê8_B°ò&ýþ¡RìÃWÚW;QÙø¦È¡uCMNbap.*X¡â|e{ Â¸À²ô(\\rìÁsx·¡\\rTòRãÎÄv¸K:]b\\nÛþ¬Ösù+®R¼uÎÊÆ/ÿ$Ø0snc=Pw*]Ô'òë\\tË¦kÌgª\\tÛ&Íié´ït³1ñµæ\\r[BÐE¹Øõñò¥%¬¥í¾ôj\\bÅ¡¤UøRöKÿHì³úß\ÚoN72zVô;IRY×5HöÍw9É8¡¤¹Ò'ºð¡§\Í)ô ¹µ/ó$F:x?7c@8®ÂË+hi«$êË®¥HÅ¶ð;\\n\\rkûHC3Lc[Ôq¿¥¦°³*O¦ Å4ÈÑÅ\\tE®ª@_0Ìq\\t(ùÖçÍÀ|¥1X7¦\\fèüÀMÃ-Îu]¦ÔuQ4Dü³£Ü+òodC¤üEÙc¨L³ö¢ù,çe.ñÍV:u{Íä£ôóL9Ô&óÝxý#.ØäiÊÀÔ®»à÷<©´2¸DÚ«a\\bL2¤öNÖUÉIà×²s¢û`X`u.K^g\\rµOÌàSÌS¼;W´ü{þ¡O¨d«û_7vo¿ëÞ§Í9þ94©ÍUAe-ËÆ+=?ú0{¶u:îM¬²M¬2i×«ÝU}°"ÁÚ\\r¼Óåµ\\$eáÕ¾~Ò\\rù²vÌW\\tïåbø±8.v4ÔÇ«\\t/-ø&hÈBÀ@´(³ÔæÄ\È·E;4VmØ\ÜÒQå¦RÐIüÆyã'Î÷6>ÃJXÈ¬©kÄ 8Ø&Ú²¡=ybÍBgr¬Ùc¬XVZ*½¯®²7çÚ2âHcÌµzìÜçìë$ºÿq~"wÁÌô/r/ÊH[Ä¡(?t9:FÙñº:íP´H»´ô®:9\é¢xÍ9ÈËü<lì½Z,Á_i&WXõÇ TÚæv©]Ïß[oÐ¬Ø¥^_ÀcÝ¼Î÷<Ë)­Am&èX¥å¾OËË¶8ø¾Mêþ¾ÑV>¾\\ra»¿çÔWýÀî·»CØ?®·MîÆ\\r?2¨`6[?Ñ+${gÓ»vn¤eJÆ\\bÁKr¨Q$¶báå£«+Ò©¯×eB(jèýRî»í.i 0òë>ôrÿ@:V-ÇÜrdBkÉcw[ô£dá7Èã§Ús%\\f×£ióHë#P§ØCQá=,ÊkéTIÏÔg[½e`¡òARÌs<¼ÝºîÉb9«ma§çêR,]âO^gX«KÙb¼)èìBdÍ3Ç¥½­µ\\tÃA¬±ÄÓ"ï\\bcÎdÅEÛ,I¦ 6ºÖbWÎ_ÞHKtAÿøN=^\\t÷¹íÆFxò±t×IèøSA AÁ5÷åâ0Ï\\n»n:VÉ?ñúÆkÙ443+7«æSBp×^gÞ¿¶v)&oÑ#S®&÷\ÉXÜp*ç¯Î´"9®ó¾('ßUèØÛ>Ãå¤ÜP½ËA#V,ûd\\r°MRRHLþkO2\\t±)e.EªZ¹çf(uðì7eeWU¼Ö(M #É¢öQBmËØKº\ø~àÏº§ÿÿ¦*q¯àKíÑìÛ{û#Ñûõ·Ê5\{ÊÊý]^X#}Eûc>ÃÃoõ l­Å\\råªØ¢ºCwr¢[m[ïQ«òÏÏòÖ+ìÌq×¬°(´Hi%ÅÌU[íõIn{¹ÅâXÈÆÞ"A4¯H âûÝ@IÒnaÑ}VÏ)FGÄ"!w3Úwý\\bL¥M=Þô®sLa/­fý¢a²]DìxÜýGÕåà\\fç^h­UÊ ¢Ð8+µs6:!"fJQè(XûQÅ¸­?AO¼¯¾6siÈÛ§Gjó$@\\röøé\\fâ\\\rõ4,ÝJxLdûÎR fÄMp ê¯Ã ¢?ÂX¢HÓ3¦Äübék·äÎ8g\\f*°rÓBÜ.Ìí\\f2aHojYmòé²!{3&Ö<'+v°y|þçýKtrËðíÙñ£ÿg¥{¨ü{À·g,ÒV¦\\nô W/4¹9pyöÚÓqC­ñx'÷¢ì{¶Èïà²É7ï3Ì'øBÚSªò¥ 2>3ã¹xÑrÖà%rKµnó#á<ßzVíÆÚ\ÂAeÃp«g'¼ª6:z)ÛÎÃî½Ú;Ë7dVøe\½áYìÄ?k¹]ÏMÔDl:û¦ùI²Í&Àk··½Ï±/}îE;AÇç±_iG¹¸Á>MYÍïVÏZ°8±\\b·Zö:5#%W­ec\\nSbIÔ òÅn,÷~·YØðOHÓAùö1kË¡Å½Íã½Nê#ªf#kÀ}¾ñ«tgüÖ¥s't\\bq31Ï(µÎÐ"¬|\\f°dÃH­È±B­uÂQâà§ñ§K"ÇÌ_Í*vN¸ù+ïDb77¼6yÏ}½¾@\\rh&\\tHÑÃé]Èg]*!à8Ðy<õyüçv2ÿøG@èÌ³D²> ¸wi½d¬épßù±¨-î:Ý¥ê®eiÃò^e©Å+ú\\fZ«næ;oÜÛÆÕÓÌÒVSë¸©¥êÕÿì¦H®÷\\baÖ=ûHÀÀ]REcºbäØ^ßóziíÙ·[|nÔâÄ£áRëå\\rttÉ]4»Q&Ç!()×_0tvÚhc£LC·§¿ñÞ\\\f¼»Îýh|/uÏ³hö GÈ,¹^fuþC§<p.Þ*eéeO$Uó\òóFß;Q.£`>Ï²­!q^êèö~IííSFRºgBdIVFÚî¬x9IFi[¿WÔe-zG¾µ´Ißø;6¼6k%âÌ  \DW,Ó:uNÓJj³éÚRnzY\\b½aI[cÐ\\t\ô»þ:VÕ)Ü¯qÆtQ)ó[©"Þ-ú·A+ /ãvâ>1Mîf¬ñ©òÐó_#ÚÛ).uû\\tÇç@Ê(#§ª«I×Y¤äGýû~ë;ÙR¨¯Ü,x×²(nÓþã{^aµåÔÎPò}C/\\tÚb)ÈÀ¥IãÄT8`Þ\\f{YÔ=¸ÌRØq¯¬Èã>Ê×b\\fG«÷0f~´ª{K*¼JºRÔxücâV_°Ù]BåÇQ«59]{Ã}FIdF5²¥tbÎZEa0AËég¬sõàØÑød]áö|Z¢!)º{ð"b[ÿ7Éër°UÒ@oã§]j»´'8³Ã¸ÔBº6´4dÿ÷däÃÆ«þ,üùºÿ`ÍK¯ääë1]|Â2OU(êà\\n!cÐAå¡A.4¸¤»O¡<¡Ò»r¡ôSÆô\\bëùsv7¢ºÏ(.Gh&ûÞ|Ü6D_·r­ý~³eI êÛ+V0MåHÐóê\\fÀú¸Oî®ïôÜ¨Òù¡¸1]k©Ûò¼­ Ý+hõ>ÈNµÁ"%Å3pâ´IÕðBZ¯/<\\fû5Bjê°h\\fÙ_§ ²ÓF(8Cò¼?0@nµ¬VOéßOC>r­Ï×\\bÙ4ZÕý9>Fy³sÞïÏÝµN.-ÿgë±]ÉÄ¾¼apëAG3 Þüw(?âA(ÑB6ØÚÀzC6Ï\\tÎÅ»@#©Zñ*>£e+@¡`j>m1\\na½Ç²,¨·ï-·înùüôh?÷<1Ê,>ª¢éw/\\rð&Ð?\\täÙ"ÎÍ8¥á±_+¥Ó®¯¥¡5¹j0ä3z|3/5Â hæ áÑª¡m`SØØD¦_K+\\bÚ\BéÌERük4Z¼£ý-¸ÄÓÎ^Ü~ÎQgð$Ô.ÖÇ¾:ôVqîáòZ¸dõÔ¿Ò}íH_PEt?ÍNÌìeIÌ¾ÿET:è%»Çÿ¶qÌÝ\\f\\rSÆìgZ-ùÖ÷ftTùÙÓßk Gn>¡ò%ÒØ[í^VDn.Dö\\fß\\nYª%2µ÷#·Hwd£6x,<ßøÂ]&|dØ­\\t«ü]¼÷LCä<÷|¹ØF&Óý­¥""ö:=/ËeÃùÖ ¤|,I=RTAO-òû¬S«D,V½¸ò&°s\\réyÏýÁi´Å´¶AON»»\ ³yÛdþ:Èö¢M¹Ú+[ÅrÇ'3ßÒy%<=´  ?öìô`o³Ñ\MÄ­hZÐ¯¸s]uvaY'­rÊ!ß^eëK~}Ã+qÓ\\nÒ\\nðÂ¦¥±NzAä«}Z£b¡üþÌÕT\\nwëCÄ?Ø´¼é|ö4¾¬s«6ê\\t¦þgQd6ê¯B¼ \ÀL1Úp.DüFÈjÚµj·ë¤ß<Ô¿Ù$8Àß;/÷%!×ôµ<k+d¿À,ô,U`©¼c\\nÓ@ëÆF×4Lö%ZNgÀJþ½T³¬þ=öÒ®ÈÂ®·ÂÎv@á»WµðäÏR#ìºâë6è¨¤ÓÓb\\fùK(s|ªü¹iß{æ ÐðsEºt8qÝbüxÒ¥JV½ÆÿCFÿ°r²Vè^ÆræÐñm ûâülª`DEDÙô^ËwvðÖ\\n¬g8µQÍ`ý²hàÓ¶*Ç>Üí5R\\fPü¥ëæ¨rôè\ÐååTqnEbse0¸B[6óÙ´#iü?:9QVøE=!®oYB]{ÃãÐ"ß_Ï&Àøð÷ªÜ×h/Õ¼/6WJX\\t'¼·ñõX*ýñè\\b!xR\Jù ÑÑÎG"xøCh\\f°-Áw5^Lþä¯ÉaÑ¢2uï±ä?`ÏÃ4¾úÄ¡rùß÷2bo¥r-KÕÛJy"(|`|Öÿd(\\t÷Ð«4õ*0dç6ê7m$ÜÑ&ÄÌ¹çÙò?¹Z\\fÞ mÆ%¶Ôp®¹ì®Ð6ÿV AWËÞ(ã«MµªnçåÃµfLþSþ¹]À*öêáóÍC,\\b§=~Ïâ¨áJ/?7e:øÂ}­ÉSÓWEî0åxn0e¯³%DÂré^¹Üãçò\\f»d{KÝtFV\·Ev\\b·Êw"4ª'Æ1hþ½JîIG4\\tÿRëWëÑñ:ÕbO\\tÀÇx1ß\\n[Ac[²À[.± Z¡e`¸÷Ä®ÂYUßqÈcû_Tíu¤xÝ\\bÁpM¿ qOÕp§\\nHÏû®ÇKGúG!¤?Ï* ë5O)AðIJÑ¶yïäêïÞ×½¸û²z¡íuÚ\\r>Ö)qÁ¦S«d^\\b8NÅa$rÁ'Zzÿ¦k\\fÉQÉëÔj@0*:-Xp¬¢-a,®òPWÆåÅSô8Íåó\\tÞul÷zÉZå¾A¨1|&À/¸7aE·X§pj_à«ç«ûu'é.hfµ[Èácgt¥Æo¸ò£äç#Õ7K¨*¢úáR&#Cã$àB7JK!>ÁiÊA\\rgxQÑ;ÕEé¾g,SVYù×.áñ´CP«VÐy·;úG×«Ô`u_®Èä®¢×«UÆúÈ×éðôYFSè:z§ÁÁÏvÍ¹O¹VÄ_x9§¢É9\\tQ*EsÛÿ³¥(çj±ÉÓ|ÿôy«óI/ë4zQ_éàäÅqÛªëK=)]»PafáÈ¬íÌÄ²ªUØQA@(êFSÏ¯UG}ÃÐ¸ÁÆ3Ð["ýÅß,À ÷\\t]ø"D$b!BG\\n©®ÖAS¯ú]²Ó¹N<¡\\nLß<¡±fÖÛíV°DBÉÙÜ=r}C"E rÞa"'6 FÏñF|3¬ràü×Ô\\f©hìT<EÃí¡·Á+4ØÁ\¿ú/Ó7Ú<à3T«çF>¤ ïÉ#hÍwm9Ã#·xë6¸vÿä,íììq!¥\\fþ9Ú>¦¯~5³q}XÍkt³Èï[nàcPý>m;s$UÄõÉµqó%Þ´ÿÅx¹®ÈÇ¬ëÓ&ÝÒÎâA¥`½¶JLZ\\rìñÙâ}áeMåHAß®¼FíàÊ¶K]½t/¦cÉã%ã§òßÕ÷Õû¶äZðÑàj¬ÆD©»2­C¬TÔò²ÚO*&nöK&ê>98ßí§ÑtpCLÅ\\f!æ5:­<¼Ê²&m©%÷*ìã-f¥ÉüY#¡Ù¡\\nIßªP©Ê"ÙY|Óc#­O£C°.ûY ülvb¥¯Xï wæ~í¾Oèëpk&ëi ?elobñI©ZçÓD~}ô`ÅÖÛàúüéÇ]¢¿^x>²ôçP{óé<5Í¬re zOÊní/ôÎ¯qhO1ÿÓ¢.®¢/¤ñ1ñtÜ\UoZ­RxHd¤Ò-¼±ÛåíÕ\\t7e g×¼ !¾iâÀûFZ­Z/K3Ñ3H+Í¬NP×~{&UÓR0àG?^`ðâFh^o¹T¸\\níêóÊª¥²QGÑð°>Ú§µÑ×sk¹ÀKHÕUG-ÛTÔ <.Vê!o¥ÝÁ=5¥¡»À_V½%¢Iu\\r¯ºð/lmdq¼#à_lx·LÒ¶:øóO¨-JrýðÏf_GLI±ñþDµ\\bkøê>óÆÆÝ\gÖÕäü2ÖÚ_IªJYðóåõ¦ÑUÓ"%?°!#±ðü¹ÒfpÉ!L{&Õ¶\\b>Òð4t+\\n5,\\rÙ!vtK¯ÒAïðßqïý¼ìfäÃËÞS5ò½8nmÝëúSaøMtTÙý£Hå´.ÚËi{Ë)Ò?Qä¸¹'ê¡þüí`mççÇ\\fió{1îJbª¨Ë:è$$Å9Çk¬YËIl¬¯.¯Ý=oÂúsmêPâØ?ÕH7½eÀ÷ûcXÓ¸Ó\\r¨X×¿}!\\t{ÆÜ\\rL\\rÀcn54ZßÃ^ùHÀööb;/£z4ù RbD ÀÌa­òI± fÈp-á\\rÑ£rßS7F@åwaA]ó½èl\\n8¿Ñ¾Pì!üÅ\nÉjo­½v[{O%§}xýWOîÈ9w*iDÙýDÑÚR#r=VQ0Ë§­ð¤%rv{Ó´Å @¨,«þd×_Bõdr!\\fuW?sF'zi16Á02QkS¢GO a¢µIOñûÑzj)ýkjGîsìÑi¥¨Í.zikrÔá3Ù+k$-«1â³sO\\bS°'$b-&âØ<hbáú6kIJbªySap¬´OPä¶GµÈeÐÅ£\\t¾¢Ê{Ýâ):FÂØôO¤·3¯\\rhö\\n²uqF(!O(EúæýÛr!7q4±0û;.#VS¹_­¡ð8@Ñþ+Xtëþ%¾¯XªKÓg!åê Ê­½~2¯68Ê\\tB£!ÈtÉFBµ¶x5P\\nVÓ:±5p \\nl}§<dã\\tÝyjûF&í"¥û\\fÇkyQ2^¦Úuxì s»D4ðiÐ|Ô]OyÓ7ïo,hÐû:"ìÕïvCiæY;ÝÎ@oga©Sdx°\\nñ\\bo*s]à¢\\r³íy0ìm¸ð-´Ôº:8Çtv/5¢ñNñÒ§ØÌyr`¡q0Êåq.#³Åp7Úxª÷ýP¥pjnõáRØv+]@[°,íoÔ»üe{f»Å­*7ö{×SÁZgº12\\f'÷EÒý]{æc?Imâ\\nSó´ÿ¥µS¾Ó·|dCÜN¸Æºö\Ï¹ÝËùÇl?Ä¥?j7J¸'È:¬úAe '$¦wÇ*Y§Ì©Æk%ùÚûF«{¬ú;°õÓ ±\\b©MîôoÆ\\bÁ´#Å£¢4ÅFÐKÔÃZè+Î¤ÛL¯Y+¿y?B¹\\tÜÊf*åÑgTY;FþÈ? Þ¨NWõ7ßßdõ+RÓÿº|`µjY@D[ÂüKò=²×÷~«"\\n\\n|Á@mÔ1ÁäÔ£2®Ìã";âEÜ0Ý¿=$ÕdlåT·YÉèb*Kxa×(Ô:³hf>-u$ì;¢^æÍæ¿®Ç£íi`²¾r(Õ LNm:aÇ6Xe¦\\tüq=ØdÐY3Zd6Ò!]t¥£p>¡/¼QÆsâ¡s{bjübOÃá¿ñËúhE]×N0MÅA¤?L«ìÑC$µßÅ\´uÇÛÊÖhÅ³çíÞõZ ©ëÄ5|dFRF¢*|¦\\nrëÞP\\fÑ¥øÇu8ÊJõ¬h\~Hô»5dÄ´S÷iðr§\\ndWÂµ ¾`ñ¿dýÉZÁG\\né{5é³­¨§{éüé°rwì³¦-[ÁÐýRÖbñ±Òÿ<è(ø³¶X¨OëXº Ílèµ2¾Ý$¹Ï³mÊÆË0ë,yö(!ÙÏëq.øöQ G2*¼CÔy½¨>'ºF0ìfÑ¡«P£b"Öµ¼iLÅÁ*zp£²;t5RôçYÀ_Y§2'¯îi>`\\b!hñnÔ¤Uï$<`­ýã{ý¬÷àæ+Á§¢øï~#\\bó&v+Üøº¾è©F^ Æ7\\n$w¸ú£yU-¤¥ÉÉ%ñ^zÅç0`äU+"6A9ÃúúoÞý1'}²rù JËY.1·àOóJïòÞ~lPD]ÈbEnÓliûFPÛjÍ®yÿ[:§÷ÄrC\\fT jlÆËÆò|¯x3\\b°\\rÚ(½ÿË>,ªÅè¥º\\nlÊê%möz äïìXLôK`¢ÉÌ¬ÏÙ2JÅÇKTdWÚÂ¶@:@+ËuoÆÉ×KÁJÔdÇ:Öègÿ£H ~FëÍÍ÷Î¶§_¹;G³³ú¿ÄËSJòä#yÓíÖ¹Xsy;ïB\ßvð&÷ü"oM\@ðH¤êð[¦mTüÑ2±6=+ò/·Ì2+ÈÒÅ 2ªÞkhÕ³]ûã\\r¡vá®d§*éÔEÎ'gSÀ²AmT¢],]«\\n¶º°SRæfñÉuÜyXº{ÙT¦×Ê!©%7¥S{¦Db%×\\t÷\\rü) RËê\ëÙ¨§AL¾7\8¦ñ¸ö,¸õÐ¶û:¤½§Ç,V\\f9³iåcREiêºßý*õ§¨ÐInû©¿ª¥çëïÊkð ¥U^Ð6}?m<¿Î@ãïQ³4 ú'âsû FÍ]tN¢Ùlè&rmG£Bò§6ð£L\÷*õ÷Â']u¡Z÷\ÔÙ+Éû)Ö¨\\t}v*eä=á×Õk8¢¾CIë-h(U,kqpÏCèÕ§(1@Ï\\f\\fÉpúCkj\\fæ!LJqú:·ÂòÕ3¤ öÊò±Ôðì¬|þ(S¥[åòê)Ó\\fgÞþ£Ý:õö?ÜmeÌr!PRpp?´zP·«\\tåUêê\\r³QÖü©Áe~¥3wJëlj9ôÉ ±.|Û·Îö¼1YdÉAõ4*²0üÚ²BÙÎ­J6Z®·ÿ0\\n²ìe¢&É"UØÚ>¦¨B«líËGÖà0Kjlons¨Ik'îð¡w&0É?V÷ã¨:$ü.p%Ç¬Ïã´îô]ýò£ÕüXìP"Êù¸¥S eû}ãN1\\t],ê!­\\noåe§ùSTj'(ÞÞÊZ=kËö¸É\3¦wÎ¿ï9JÄpÞ]â³¥7ÕÈTýÃ^ïæ[C,é®:Ðöw%ÓÏ¹ù^nF©b¢A©Âæ{í¢­*ãbì|Çòòõ>yqä1$´ÿÄ¶YãÞ2v^â"Òîï8ñÿåßëv!¯t2äIÏ\\rÅÖµ=àè!õ]Ö¶>à ô½/ ¤Ô:hú÷xËq\\bÉåuòAN&nÄ»~á\\tBØ0¾y\\b¡~/ÍíiÆ±a+°«]a!ªæ¾§ó®¸ÝòrY\\nOJÏ²¡8û|Ù%y¦)û.Mn\\fÃJG/ä¬û}Ø8@tðÒ&_>à:/àQ `¾è±úë-FHÎ¥@Â5|ÿ¤%Ñn¹«TY×Zp£d\\nYgAå]¨QæzÃ3]{fpæBPJòN¼ÙÚË°o}ÓÁi,EÌ*dªstxqª2¹VðeËä\\npÔKÊÙyaÚ-¾úÙilE{!O3èÔùÔÛA Ëý1ÜÝ¬r3R#8Ñ¼­Éz8Éôkê>ë+ïÍ5°3$+®*~¶ÄUÎm`Ç[+PÌ¦÷rRÖ6êinòE©'Ö!ú 45åtoÂB;\\t}ÄWYO$óh¼ÆHKb?B+ÃÌB¤]ÃEK³|[cqk%Âéé±aÌB(rd[vX¸LB!¨r«$aKmí\\t æ×©2nÔ÷U\\bD^sV;\\rK<h4¾k¦ýB ¿²×ºùù\\nùÆ!j]5õym¸,D^<Ï¶O_£Ýu`UõºaÐöQó»¦$®XAý,3XpU` rÒü!³(qÿ´Ör\\bÖ%6ïlÙÍÉ²,ÊÔ_\\tYÄUeý$HfÈxCqsàKµ×Ük¹s¼b¹ÍwB±"ú#§²ÿd>ï=!½óé·0aXoNò'Ú,ÛäãE^Êï(Ý¤8zs6<v> OÎÎÜÊLdmáXó×Z£3ñÈO¥ÅãØ|½ N)8q¢ELíwìþû91V­jÝÜHS|8§JÀ¬Â8;\\r?-·º*yl´µ{K\\t7Ýz0ðyJDØrüûÞ¢ECRzøûüY*ueûí×Fß>(æ7SlªKÜ¸Éh76 -ÉQßí§³R½ùF®ÂÕ­m{Ü¤-ôÂÒ1nµ¦\\bt)gÝÈ³ÑtLÐ(ôoÜoRUÏàXf\\nc¨@×s<êOcÜÇLôç9¦\\t'²ë3ø¯¾JêæÛ© ùsRz¬UÍ9%sg£õ36ln@»éÂ£\\n§Ä&¯û5½teZÊùÖÂOÑRi\\níÐ|Dõ¬)ÞõáÿýâÌåjbÏ¥¹J1Ä«L÷\\b©Ïb°àÙbZ%Ûô¢£6¶"§ØlvCÃf)\\but5ZE©± <³µ~`\\n1Ú©ð\\r®s¹¤ÒÆÔÒVç¬|Lnoá¿é¡È6\\n¥"f£%"¬_¯¥Ô¼¦÷KuÅÙjúªCC£grÇÎ® ¯½Ë/QâS2\\rÉÅGámZ>èÛÉ>É¹°U¤/¿ÒCÂN®27[\\rKÛË[$:zîÔmPò>ÿLÈHN:ËÈ+Þ5à/áß<wËä%9²\\n`Ç½;Fwp²6·ÿD[ÑàÁu=]Ñ9Æ;bÅÌÃ9)>|õ<;l¾ X¿¤8&u)BÒ´mkFº´³3°.vM{écÖºm]ÿ+=¨h¿ß#+Æ¨¿¢J@×áµ?/d»«*¯6ªóXºRy:Å[äë¬ÂFÏfiðý~AÆ¾£Ê!&ÄNÁ:ðï¾ É^æ¯oU¥Âm0ò7ä/ÏÀ< þwGmè#»í;éð¬°ÅîòÒ¼XCp4B\\f³ÅLç¢BßÕ­Ì}÷¹©Ð¥Ú´×¸\\tg½ÛÏ$èôi³NU-ûnRPÃfïÊÙ­O¶ùûo1\\r<WxÈÿ/ôïL4\\bmòx6ÏE#¾g¼ëÝVÜ-~ça·SíO<gn_ü¶ÆòôEµ÷P\\f9ÀÆ$7yµ¾0îPeTÌcf ê°ãéæ{1-\\f°Üv©rÈ>ïÉ1[0M4m´=Q»0Úõ²ÑÒÒ³2å8ÄI}¨VèC»>ÓN>³\\fMëü¬!§S¾5OÐÒqYk"ë©84¯\\tâæ»²«¡îÑ@Æ:Ý`DÕfµ"[xTóÐÎZw c,N´xèQø@,qÎ°ò©\ {tëÍ0Ô+¢%xO_=`{dMÚd±\a1{¸v¨X¦åLÜÈ&Äê^Ýx:8´ÆóI³Xl/ÐY+±©°nÈîRêz¥2@qÑ\\r1".üñ]]©«Ï\\n@\\b3Ôda»XöÐPØOí$óe7N(p^iM D1¥wñ%ºo*X9¾W}ÞzâgFäq÷ä¾3þ-Ë¥[¢¼¡Oo©g0(5ûÊÍ²­e¦«\\b@ûÉ¸Îv!õFG=?Xöå1>uHEáë«tE7z¶6*orÓ6\\r¢í2¿¦O,iä\\bÅ¬wVv¼Éª±+ãC`æZh9è\\r¢Å0Ú§3q}Sá±Ú$ÅöbÛûù[pHu{Etä¤\\reò<Ô¦lªî3X/6!H.èp\\tSÃNc/ßÓÉ\\t2õ¶£ÌÜé»ÀCäç8@G8Tqí4±òf£;!Àûw,½Â7TaÁ4îË[Ï¨_¡Æßùæ(±Ññÿ!ßÅ¤Ih¸%/t@ê^K4ý$,Z½C`ú\2\\f .¼j[ëÉß¥«^Fi{sW9tFÙ!ÀÙ\\bÃ¡/ñï=HgV­¯\\tÝV9'ólÚ\\f9Z$ 0(Ó!UÏq¡69Ü7Ê3¯£«IÐ)e°?/ãù-_Òöÿ5*Õ¸´íRVÚºDkÑÔl"qË¨ì­*7\\tvÑlj¹üZ}1IOà5¦}2´%ÜÎUènÚN*üaLÜ\!ÜÇúbØ¨y÷åb¨oÀ?³b%µTj\\f©J¼¿ªÜôêûËÏ÷ÏKð=9A¡!§P"«ÜÞWîdÂB0úßPå§V/ÝÐ9UÑTYÿFäð·&y\\tO¥H`^¾ð9åQ ¾±,²ÐÔ;ÚÉjfíÓÒ¥\\r^×Î¢UÚðÝE¼\\r2\\bÊK­_weUYzÏ²¸U\\r!ªþÕÊ[«¶aY\Cäç±ï¶m~èÊu¾o+÷v­\\r8A2þËÚf80×]\i.pØ=W/ ÔÀw¾¦+\\r#Ã¹°âoö9Ùª6¶\\nYK®uJ¶}Äfä?éßa4;ÿwõ¸6dÑ:VlvO¨Ö¨R;à-,÷õ:yÈK£Á¶¿öëª·á·º¹ûY+g#¬Yá,ç(«EË¢¡Gí°3¸F!§m¤z>eí*@*òÄá¸â9é?TBÊLó+_J2Ý`ÛgÍ¶yÊôþÉU°h@`Î±Q\\r\\r&±ßßhÍ'¯öÌ?6¥]ÀmâEzF¹´¹ëtKì°TæÉo²åsRÁ£Dí¤:a=£lÙ Ë[Xl¾w&FU¨Gzè»õäUm.iBùL0V.@èbåyç5\\tóÁ´  $ä÷MLñ#÷»rÛ6«g·í$âq a6I>35 æßÊJ2ÎP<\\nB@\ ïéQg\\b?¼aIá¿8\\n&CæKÐÏ6V>Wfàè3K-¼;\\tÞ@áVBVÞN~ÜèIKÎAÃì½RçèQ"Î²opK ÊË}JßÆz66@]ÊH^^Ë¢y³\\tkC/Îå¯13Pw_Ïy0{õ\\t?ÍÂ*ûã-T#\\b,µð\\b.±ì3Ûb"ÉBÛoæM}B7VÛ²öí¨2D/O§Ó"ÿÞù¥$Ös!éÑÓÔD\\rM\\n!BÿãÅªN3uÄ®cªÁF Nô÷P^¨ÞùÇ¨p|-"6fÖÙåÇ¸ûÉthTÅTz1Áû§~tà 89Úg`èÌMîZ\\bÿ÷Ì]fÑfÁÆYeþ«%ä÷`òÞ1®¥Ì¦¸® æJÁSZ¸÷h¢v<öÙÙÝj¯áºÖü\\füãÚ-Uªk7§¾Ð§xt.käüö?3o»ÎÕÞsw unTÉ#ôFzO\\f\\f¿û5¤yxôF¼¯L,1Ü?,×gõlÄ~¨·ÁBsÊ5·w?ÒÕ2<rß$<ÎHí<ç¢ûeï»¶\2mtúë4ª!*/%\\fwÅgärNØÛ/hÈÕÎB¹CÃ^H~?¸¦$Bh¹«ÄìZÅåÑzRÏâü'¾ýdÜº¶¥û¦{Øã±é¤çòU±ch@h;ÂÕ°ImÄÃ)LH-È{,7q`Eßc9ÌÅwû\\n[ß°È%ü¶÷µ©\\bÏ±6è«.Ã}ß°}æ8ZÆAs¤_\î¾' ¥¦L}$@ÂâÆ£Ý5£j>0ØÔK0D! ®\\fSÇ>[Dãî\\bøësÝÞ\\nky~õ§ :q£­ê;Ìx³ôµM_ºÃÞÃö(ýÛ¸ÆíÄñqÖÚ½¥àCáÊ8òoCâÝ»û¥ëüpx¬ ðiª\\bÚ6WjÖÇþ;·þYÀ3GyJY!É¾{Än\\nÍ9w__¬d£2$x$ñý÷jàu)eÛÁiZTëÙfEáÉäâà{¨*=Ó©Q±¢*t±MU¾Ncãé½DÑÔÃÃûóÐÆÙF"ÑÙ§bðÒÂ2òÇv"ÝÉJÖ zdòéµ&;Zx¹ç[pÛZDsàÑ±¶ËòìÜÔÖüaã/ÊöEä_¬»¦ðZè¤qD½1cy FF &Wöu÷5Z?ûiC1!½ASKvCï«CT¢®íñ\`tö3¯pÌVÌá´ BQõÕºSðü~UwóÄûd\VïTÉ$ë°¨\\fîTÝ@¥KIðxo\\tR­=ùÁ4y3áBdBÎä3¶bçÛ6¬Ðdàíi/7s+\\b¿ß@¸v¯þx>·hw¾ôÜ\\fÊµÈâsë\\tD;2¢¼>N´Xî¦\ÃûQÙ#õ!¸¯«.Ü1l{?I!Z~¬ÕÙ}Bý\\r$ÛFÄàyÀA¡áËdeþ3Õ|,\\tØ³ëêÒ.¦ÎIä#6Gl©j÷ØXú"ÅçNLúåÚyO=Ã|ýýºjü/ý)Jl­íÄ_=ÙåÑ»~¾ë:Ôlº<«\\f¾7@Ðýº`¥5¤N5"ºgÿÄ_ºTæ"¾ ;UÉ:5zZSÃ3£¡q¸¨é¿çA½èlÍ*ùm\\bÃµ £;Mn¿Hb`¨ë°júÙß¿þ&Y'¼ÛhüµºBMç´rGéÆÈI'ÌÊNö»UñÖkÛ\\nÖmPwíØc­xpÕ&óFýÚ\\bÆA 'Þ7/Û"²P+Fw\\fÄj(:nÌm)O¿\\r°nüÒ¤U÷ËÎBüè|t}¶¾KúmôZ\\tÔ´%¼HöÑÒ>¼®mñ2d³ß}fðTßÐ±<$½\\rÅÅAÝ\\b®s$óA%Çc¾ÅÍïQ/ÿ¥c:oøUrFzh:äMþpê\¿¾¯Þ­\\b6B\\rÍüÀVê'mÓ,)]Ûçñ¯é»\\fk9³÷eoCé ¼ÄØUs|Ç¸Ø"´ø¸*Pä½ ðÖl ÀJ nÖQØÀ±â¥Öz¦×°þ&¸»(ÉãÞL`­±C·h¼µ1Á&"È¸±k`a <ø&ÂÖVÇÍ1ÉýªF±æî¢DnS¸YÚø)§jÛ§l\\nq~²³ÕQF÷+tgD@^+Ìn<òJöËµÇEÒ|¤mcMzI»u¢¢MeU¶Ü£(6äoG÷¥?[½4©ï^Ø}óåPæMEK<e¥¸"âZ%3^ëÝ(:&ZK©ÜèÇó¹ é¿q`£èKeuÕö¾8NAí.Ï.:à.p4áß>ÖUú¥8ðÅÇ¨¢´AüÒî:lP$§?siÛlyn]Xqåf=lE­#p¥/ïÅOtNeÊ)\«µ#Ì/°°7tdI[8v¶{ ê[+Peíy?[,gyÌQöZ­á°v¸ÚD¸r³±Iò\\f1¢±¹§yóøÕóÛÑ)z÷/çbÉÖº9aWÐ;ôåNªWeµÇVtÌ.*)G³f1UÛ*{@Ï\\reëö»gï#Ñ(Y¯'µKéÛ"X·å-¢td£^KQÒ°f¼¼kZ±/?exEc<+ËÏ».#3l:Zçó%n¾*ôif¢6Á×WÿÄÏÌ]Ñ4tÕã`ëaî!b"@FãÐó'ë]©úè/+xN9{ÿBHtæ(|JfÐ5¤\©±!RTNKSGõB_Ä¿Rhm&pÕZÖ±×B­aZ*2Ð¼®¸õw|P$qIÿ¥Á*Òx£¡æyû)¼À)Ý«\m0ãb ],ÛõQ20^ö½Ïº³ÞuÚ#­M1ö8¸)\\bË^\\ttßv\\bi)wEoú{GZoy¨áqøt¡bÏ;Kæy/~Ôm:\\t½ù¸rí]ô®£ª¼ÇÌÈ9e<¬½ Á[<PÚ×è"Ëöì*¶îÆ]ÿ}È¸8¹ê8pu%®hªpFs¸/FdgÁ1Õý© ùÙ»+8fiGm¿Ã.E¦ÅÏtK,E«m]V-ñí¬f «ªëºzgàÍÛÁÞ¡CÎs³ÉBÓ¨dÑ°\(Éá¿öóc:Ñ?}>kì:/b§ë\\bö-hÉ4 d©¯6qMeOtñíYõ³6¦btþ1%é¨Ü³<\\biî\\fDl¬¬«Ç3\\b0 V²tW»1kØÃÞ}÷M_C³2òØºQ>iãkÄxÚ[X\\b¦u¦8p F~Úÿ{-.NìHXJøiU~®$íÍx÷4þvÚß(8ÀåÇQÆ¬F­îÛê/_-\\fc±ëÐ?¿GÌ¹ÒÝ¸¨ôµ®_á´Qäè.)Cªa£êh?hz st»QAçºÆ;z=g%2ËZ÷se=jàFL§Ã½æ#I;þÙøÝa|eâj{® \\b'Ýh-E÷SÄT}pVöEÕ<H¡´x®#xXë\\rm'\\b»ÌKGª§èÎ¢f#ZhEÎbÄËtË[M¥XcBv}æq##ít»eVN;wn`$ï½Ã'bk°;@#ÛMÝèZ®\\fKÏf.ãFvn àg]9ZHÙ1eÿ\~Ú#¢öy["ÃfÍ ³ªÔÿW¹«à^¶\\b?"ÕìgJRªû\\tBÿ\\tB¨TX¹9±³×«e9$xBSû)¼à]ø;ÉÐnÆü~[´ôq?.³±»ò, ÇÈ·÷ávûÜE¿4FÎn³'ß¼\\tæ¦µfö*s|\\bºp"ô\\fá*Pèãv¸|Àf£ª¸Ydù¼~F`&Àçh;LæuZKäÿ×EóÞ ý×@æùùm²üÙg\\bÎ²Eê;@Û{±«¶ÏX5½UèêÖ,HàÎcË\\f#°JÊ5òûøîãÚU¥d*´ä~¹_1Ä®£ßªl7]! RÕÕBA TQwÉxZÕJfòb =¶®65â¯ÚÕÄ|:wÏ:Ï)ªy(:ßC"÷FvJF\\tHzP®;r:3Tõí\\bä9¹òr:+Kpè\\náàUÙO¶äýýOo:¾ç°iZ*-Pq$7ýÚ@õ@+½¸ò¥®yÇm¿â]Y<3àõ\\nËuô'ãÕx©[cMÊ¢(ò©údüÑ@Ä¦ÓYºlwJj×ÌW¹îZ)j°×v?êö×\\fòµVvÞÏÃÝmôeq§%2\\bstèG \\n2cLÆ/p}¡ý.ÌYtðûâ{n}LPãðfÊ:ÿÿOóK!\ËámùlÀ$Í§CótÒâ }Bõ^bÍã67üÒ@ª6(ÔS°¹íªÒÚÕkl¼espÐð¸z}äÄ*¼ÜBµ1-c_³°ïÛS¼«§¹ô/\Ø<YÀxU}GGIÄÂ\\ndM®" "ñý_§?ë?&¡óëêÆÈeè<ßÍsYðI¬æ/\\tOIøÌ&ló³älàÔ&bÈ®ùm\\ráþ&s#0tÝÙön¦s\EtP¬îîÊX"«dÝ½yu2çñµ[aý\\f`ÿ±Àå¼"ÃRêFS[Ø<nÇ¶ªw"gCä {pIQµY¦}>Ô¨=&¬9C«m3ÕaÛnx«¿ÍÇ4K§aàiû)7$p6×æi´¬öâ@Gd¯l?ïï\éÃuämuBåøHÜj¿¦Zd\\rù{º´÷+¹Ñçpó\\tÈÞÄê\\tÖ)ê»xÜuÂLÉê9¶3¦¶²ÛÛðdÍ¸¹~#(¿@såÕûY\SI¹Ù{÷\\bé\\bJnRnZvDééÒlùëâXÐ\\feGÃ¾Í×ºz%Pqÿíyô%©(ÜI+Ìø¸ëDäþýáã@G8¸÷ìüU\\bÎª)`ûSÑ6]Hú¸òÌýwgUÂ»ºö¯2¬+ªIñA\\fáBkäÇ\\tÌ]B(PúFØþ¥frP)×wZã;P»n[m8GqÕy¾ÒæÉÞRTeÅõ\\rÑ©c*"0Í1MâTô073 îtñ\\rÕ¾éIã».z­}Ç£BúG\\bp 5q\\b2 ö!<ëR ç\ad}ÒaÏ'*r|fZ ûûßEP0Äô3¥£¾Å2 DÿxÓ`)\\bPVRSb"ÏêXà<sNzv:ÖFKc©°W4qãð/2C¡ß¹Ä+z0%¯$U¦ðsþ¾\[}|q?ÄáðèÜS5R÷=iDL á{D×µ¹î0æ- D×ZDÌø&BZÝÊ6*¨öjµD/Ý'¾µ5sNâH£¾VòÒÿÂOÃ±"¦P§Øó v±FÚ­WË¡ÍãXAÄ"U]:5¼cTêZ+Ì@%A9ûEêêÆ¾ÈLÖ18Bø.!²Ñ&|£%¹4ÿ ¦«7êÝ"àAZÎD´î¯ùñr¢¦K7²^ì»Æ¿¯iZîþþÑ$þHAîýÏG¸@§Z@:¹ÁÏîúÖì[±HùÔAÑ¡íÊ±ó¤Vïâ+ü­¸vÎß$ÊÀø\\f\\rU/J<ºõþ·fó® ÐÿoÚbÍ^ÌU®¦CÉÞMåâFjè0éþJb;¤Þzæ<½µt£Oú/Y9E$­4 ^ÛÛ5ær¨ó9-&ãöhS.99iW0k'à\\rof PùHÀN ââ·þsé¥BI -1ãSF§@È|­°xùTñDðïG<6ÿâ«ê|ÞeE¯¤ÚÞiFÏïÃÔ=l÷eOÕ0¨ïë*Xõ¢Â$-PËK}Ã`<}_!­ ··§x#Ö&Ó\9,ß~n.-òCjósÞ40ÉO?B1.v.²×Ü\^ú(þUrMã¤@J6Ë?Ö¢Ì¬Àø¶G¹êá#\/ôÀsS`ÒçØA°8vX¿k ±5È!tëü«vq~ö£`^Q¬1»8 Q¡ÅÛ¿k§E)O\\rôÓÄH·mø­µ`&-Ë 2Áp&xá.¶à 7­ä=1û¸ü¾gWÛÒ#=efä<q¦¾sî}3Cî<¯¨K nD²èÄ¸Ê2ò2v6¸ {\BÁ;:lÔ\\r²ÑÒ@¦ÎgK¾¿D=`Ðîú3ïJ\\b8·z\\f¡>SP:ò\\tPñÈ`w\\t8h56wV9¿S`AÊõD6!B¢uþyk"`aKÆV¸Óõ§(É¾ámÃHÏXrÜ0Ü&×VÏp~*êÑkÉÛëÑ\\fAÊÆ*­ÓëÈÔü\\f ­Ç±SþX¼¦'¢cäÊã¤ sÔW<³¦óðæ4×©ö6_\=k:f|¸hÛ[¨B°\\nÃ×©wÐÍÙMÞû,< t=©uàjÃ),¡*J¥¥HMÒ¿âÆ¯Ù¢o¶Ô=Ö½¿$%Ïp<Dé;Ã«KÃ|²,{ªÿ]e <42éµ¹0Â¥e îá^£9¾Õ<Û û~^¦g`%Ä÷âGÁíY£#¯®¹ÎûT9¨hh¿¤GÞè\\bWûÂb1ñ1N^_{¤jn «¦5:cDó.hàÈýûZÇ°A}½²~ÒIØ-]Tc\¡7Pýl7ûgy¡aktEÓD!$BUõ;é½ÇÎkÏ|üQ³,;ÇÓ.¤Å·Ý"6CÅ'ù<Ý®¬»åp²}\\tò8¦jãx!zvØLÑà\$j"ÎÈrNÉ$Y(þÙ\\né&`ëÑïS Ä(X¢ÕÂW¦9DGa¹e öè=\9òµú».pàðÑuY;.8qþ)Ý%»õ#zÌF£ÆHÖo'H\\rÚKÆ6Ó³ÿ~ói©tÉE\\t±sðµç&©O®t¯¯røAÆÍÛÞÜ\\tV¤3XsD:.tÒ9ÅpXàóönlS¡jaÁ+g\\nORµ£ïÉ¹VÙ»Í»Q?q\\bÈi^"Êhaüiºæ9´J£?]Ôõ%"c¬(OwÇx¾ïYªH^¨5Ä­ãÓÒwX(ÎüÐU«vWG¶^Û¦A¶Ïä­q©ÝL+rëFkØbÓ0áUÉú½©÷¡ 'µ;t°/óÅXYØWs¯¡E¦&ò+'5¥âzØoòäOBWúiÜ$>¶?¬í0û»¥>ØU3hàAÅwZi!Nh·BNSi°M&\nDOÅîÚ!fõýøYöÜÏý|Wæ<ä"\\\bWYêäüZÝÔ·FìÒHc='Í3kïíSÐÖ\\fÇÉSÉ/ätå(¥1g1BªSE«0ÞÐ©!ÇAé)`ñK!}\\tbðWo;× º«ý_¯(U·çD¤Ùÿ\\tÊ&é¢ç^DÓfT®gYí²D$]ÏÔà_^xÑîùôÄrXÅW1Sû)d®QdVÃÅÅë&ù3âÊpjoÀm=¯u¬T+u ác>9Â4á±=U±ü>\\bë{|¸æ®9ÐrüZ°16±¶S¼/PÖ'ß1á®\\b§{Kn½¸=»aÌÆ'þNg¨¢øc3ï¦,êãP_õñ^Üj·Kæ¼MÃÓk:î¯2[DøýDö²\\fä9Õýûôv¸[+Ci*>Ü:¸î¢Äú¦ýÇVKöfKé¹=ÍIE.æ´ýò¶j'Xg²BÝH)X:4Ñ¿ýÑÊóºDU,l8â3,zOr;Ò~²iì¥`2Ìï|!ËµuÞ.Hë`ìï>²öÙ|Ò\\nõ=n¢Ñí(Ô»¿\\bm»GëÂ%\\b áµÈ´ËRÁ°Â®ûWCOIF>yu¯hÚ3yÔËÎgx4OÿD¬-¶½Pødyýe5¡Âñ³Uð\i¼c$üjD¾CÇL\\f ³så#_ 1´5ÇF0ò\\fÈÊÿ*g¾#VA xÁÕ6äq')ËÏLY.KÆª¦uÊ]ßóºªü\\tQ_æ\\fn{³¬3!=Ès8ºz¥iB°×ç$oÊÀS»2©ÞÏ°xyZ<\\nálEö(ß\\rø»ûúËS«ôÝq$Nx(¾¥.W\\n·þ3Úõ+x$=`Z»pZpx.\\r ùzOÏÇÇÒZæÚ.Y±0µïÎ%,\\t¦ä³¤wò1 6ñAeK¼;jàh`E.³Èqbö¹-b#ø¤ÌÓ7fÖZ0ìl ZÖ:Ï§ùQÔ7Å~'v~|áê²ÙtsàwpBÍ.å²nãÿiz~Fë#º¡¸å[-y]©{!¦lµécbi ÆÌ67¾ øF-XoÙ {æ¸îþ»RÏJxòôÖò¬v:US&ïìÏ­+Y}F\\fA=/¿ð¾EkÔæ½ÓLæï\\bÏào\\bZZ¡]èLC1ö;ð-\\bMõT|&B{Ýù\\td¿Ö2øª4Ø\\r°AgQQ¬&Z;dÂ]8V§ÜVöûªÓ[øº\+ý>q¨ä1×*uÓ?÷fSÌ§!\\tßeã³E`¾Ú9â\\b7â-5Và½Æ`³Òí\\rï>ºu WÖðÂ`MËPÏ3»Ü)"r²ÛÎÿ3;u§(å9:ÅLHóáí¶ wî¾´x³hô_Üµ.)ß~ßÇ¯ÂýZ=Íi}{¦#Q>IyaUªeë¼åÞ°«}Ák"â»ÇE»ª¶®,Çù5`¤n?\\t*sµCw¨åµßÒUß¼ñ ±Ìa¹kz]~Uº¾Sþà/eb¨bÄáÒöÓ¸¦dDÒýÂ}]ÌîMïq?~J86]ÆÔ\\nõ 3Eµ?õJä8TýÝò#¹7YEÝ14Ñ\\t½±n{j+@íhÇ¢Þas¡fJ8«ga'g¢CÆÛãâÈØ¡üGK±ÆÊìºÂjÙFÍÕø` ÄtÕK!)æ·µ©üÁ¼,Dýwu¢Øà»/÷!ªÚû`×ö;Å9Ù$`ÙÑ­JhÌ¾ájÑbË@Û}×mÂ8Ñ(MÛYko>8~\N¸ÔAÌÔ#;Ö\\fQIò'A¸Ñö \\t¸UFÓ_äÒwF ¿á©)Õÿ\\tß,bìÿ)>Tý>K»ÄÜ¨¹åpXµ»ûsç^¹H4óJ1ß­Å\\r·AÊÃà®ÆÇ¹#±Ð¡;æP«À±Àì÷ØJ©w[ýî3)C±eox¼E«aÃbÖÍùÈú>jS¯½>_\\b× í]äQDRÅÒ*L_¢éëÅóO¹éwï.âP5Bc¾Ý8: bZN^>:ÖKaqþÆ:è]ñô«m_ke~,Ô:õ¸³ú-Ù²§R¯Ñ÷¼q­©)<o³'N¬¯&®Æ94¶WXëÛHÖA÷Îë¨¢îîÜl»Ñ!â>wU¨À"ÍéivöóG[õ\HÀA]fõqú_$ýÚzvfèç¶ß2ß\\bÜtÛ\\bh×pÂf\\nÁYÂëÉo8\7£Fue õÍÆf:0Hu4¤Å8$0fpý)¹¸Ù(|]É<m-f¶k±ª\¦÷÷^ò¢òþ¿­ÈÕ bõ[k|mDîÙ­¬±¢~7m¡ÊÞ¶Þ(j³8Í\\b?Ùp¢NÔ9\\t)ZN¤Ëï*{X÷*v´cb*|\\r''¹\\fPFX¯¨7Àõ(¾ëë÷Ù¨-ÖÅ"Çï©îßÖÀ]Ùàil?v?Ì=5xË­dc4väSdíß`_NÔ××Ø çÕ®!ÑË/¬BOZa\\f­¡öÀ®ÝÚÊvô½<´M¥JrÖ-j$'chtdývJíÙÄ ãDhéEç¶ê©DÆº6`Ðý 1±Ú¦R¿·¨÷È.ý,\\bú*)éM?<Ò£6ÀÂ-þ"9ÌÖºñx<n|+Gu°2Ô÷:£ãÙ^Êä1´@­[¸Ñë:P!ó=©çF!%MÝJ¶ÖîR|àÛw¬£1åØÕí¾\\nÀÇú(ï§¼OÜ6º®Aª,Ú\\b>½bNQwpî9½A\\bë²µb&õGDïYÀ8$g:_Êç'Ûñ¬\\nê¾dÊÀ~!&\öùwà¡=fÖÉTtbb-54ç:FúzùÈ6QÈôñi¯¾Y\\tóÃÉYv9Âãø©Â}NÆÓXÆÜtö¨M À\\rQ?Nþ+:_µ[ömt*9ÐF O½Æ=à÷D¸ägÁ¡Â|ÁýS2;vÉ"#`í»olÐJÕ^_àdZ1Å\\n\\t=Â¬¡=g\\fÈ¶±2¼Cª&ØFÍ¶ud9cé£õ]ôø«ë"0íë(¼'ÖRç=\\n#©.vêMWõb99°ÖÜ·¾»¿¦Â×zÉx³Wíc+Ç\Í.ÍÙIí»ét\\b,Ú°´ÄïÂq×~ÜõH¨#ª²Âj±é'ÊÀø´AÃ\\n\\rbèµÎc´Pl·Ì\\t¼ê[TíÆ¸HqzeD(µðN$BûW#[s²®´fR&½5­«b^nØª·T¹rj)vcJ? \Êî¿3³4ÛÑkVö²)"\\nrÚa ®â u^sHÀcíbÊ¼ÍÕ¥,~RIk#»Ò½2À !ts·f¼Û\\b µF; \\fQMÄpºÛ\\r%ÀlBÓ¥-ò§ø¡nÃÐ¥¡süÇ6\û\üîVýò~ÔóWT±"ù*Ã·È6 B±'ú6,\\tÒÌ\\tGS\\t¿"p Þ½lÁä:ÚNZM¸½34Ð½7ÿá\\fäÅç7BÑ47ßE7ÔÔ\\fWdgÑ9gØóbÍØÊ\\n}q®rfåªz £J"³)A;v®ôõ;LB!0é V÷eÝ¢úÍU\\rÛ.FIF9x»gd-ê[%¢é«%b$5Ðö,Î5ó'(at+¨+ÚÈ¶2Õ¨ÿ#C÷ûÝÏ*ÿ/y4q5+û5:C}åÄ}Ïþ/r´`wHW[w¤rz^ÃÉo§ÀpÂJÙÿaZ5hqW¡·Âµò»»³åÿ\\fH2$%­ã¯wTE&æ ©¥úç(D(°$?ys¹hî T:FÞ½·âò²¬1ÿuÿöÚ6Ã\\b±Uâ¤ù5ÃíM²ÕL¹Åo+án=u£ ÕZÛvwX®®Zû¬Ì£\«¡^jHÄËÉ§^÷ÿK%m=üä9»éÎWÊ>Ê·$Ãó`ð°[]RÕ¤>ñ ÷gÉËaáöÀ]ó-p;hàµø5f=¦KîLQÛ'ßÄ¨ã:k%_âÖ3µCââÅ:Sú!åÈÜd´éõC­"ÒDeáëø¸ÕH±<C¡kª(Au0TCÁJ$¸®\\nþýSt¯#kaX^{# .ÓÑyë__ä¿ªrî&dåÖðbújVÁhA+âÚÇ¶0È××}ôHMí bÔtBDø,Ôt\\b+1.T{Y×ø+àgFéq±Ä¾p\\fD8PÕbòØÞ_ô¡ýú9ÇuÇø&RdkÊrÄ}U)Èi4ûö¶±¶Xø¦íÐ'0ú Zmå×«¬\\b³@?ÁXjIyûn+hzÀ~ÐíD$ agÄ/g:²ð·xõ¸¯\\b' jP¼q7^j¼²KGó4ÒtY¶>ä¨L\Ê´[ìõ¸ä@Õd3Co°V=Ùèøº£Á²¶c¾laóG¾},×X\#=µ¼x±=¹½§N\\r\\b)`·ñ1ÔuÆ#Ã¿(ám2(ò@\\tB{Ð9vÌ#ØÀ¾$àch'¯ÎW\\nµpH\\fc!ÞëÿöFkÜ@×µèk¾Â9ÆYêÎ¶;ÐÎÃªrÌ$ãÕÑ!òhoãlXa|¼ÃMIf,(ÈôûÁÓù,l~\\bEFve|¡p'\\b­vsê?|7Ä] M!Id"p,åXähnk.©æd»ë/6É¬H¾Òw{fÔÞ?£Àêý5+%®<ÓLõæ.À'|9=¨Þ)#ÊlÚUsé`¾â\\rDôJ(%9FÑe ñcü³æ)pwêìà\\bAYq÷ða^æÎf±ÌåÊÔB¯ªÑ&7¥6*¥ñÁÂ-çËzÑÉ}w¢5eö¼~aA¨nÌL8<jÚVZkçnz$\\t`ü}\\t¥<Pe&ÍÕÎ!>¯Æ·äÎ=XÕ@ç´¡buKÊ[Í¯áí»®²QT¯KÂeyTìß+ºTzN9ÝYÓHdâZ,·âkª¼§[ÂËI£¨·ü¯ ßMtD´³fy1ÌËKXþ­\\f?t$Ý4Öß)ZÀ!Ù¬ex#~ójÑhÛÞôÏ\\fC àÑkærÙØÏZ£rZþÉµ\T5f2ÇÅ·z@K¶~3.¢åÊêg(Ê·Ø¿õ\\f?Ò]+Ea.TDHQR±|>?ÆÜF\\tÊFV³fË²¼ÐüÙ~v­¬B±îãð= ùEçÈßÁz¾kÓÛm®íÕðÑÐF*[qÐ}zË/ÏjR'!1nsÿò~ê\\bÖtÍ/[£ttE&!uÀÔâï8ÄXhx§ Y®f³ªdãcJxgFÏ§%ÿÚÖ,¬\$tò¢¢¸á÷{¯ÎÀm³nºf&øh$YyKÜ|+ê ëó¯ÁÛ&YGáÕ4Ù+*:U¦ÿçvXó'@6 ¯FZÇÒfemDÅoÑmþ\\n%O¥¿ÑÈ-V Ê\\rD¬ÿ°·&· C ¡ü~`ÔÛn5ò½mteÜâèÈqÍJªÛÉû¾4Öêq¼,ëö\\n_6ý3Ýr »Iê»ê.ýv3©cªs``µÈ¡· Ípçº¬Lf"f ~æ%´S¡óZ¢Sÿ!ÏôCP0^Á`¾ºm1=ÜcqðýJ£åºÍïWilY³TÒ(¿p4ËcäbÊAxIâ6,m«ù¹]ó já*{àÿ û|n9ð´Ý&õ×G\\n4l~o\\nêÐo½ÓIcïçººÈKÅ>ëÏXâ\\t­·<÷Ê`·¥5y¿ýáPºåØµßbeTÀUÕ1¯"ßv¢Î%^\\t{;qª×=G9§Éb>(ËþªÛW~¸@à`O£Ákj½|È*ôx¼?ýPà©Û^.¯ï¯Vè©³.çr\\rÆÃàb+³ k¢p¬¹Í æ-Å;iS­KÓÀÑu\\tñhrkø±APyåaÉô`Hÿ9¶P¿S`A{ëj|¯þjDIT§ó¶Ù1ÙúüÿÓ.A¾m2|J 9#zðbÄôR.À³)ïsª*ºêêüK¡«ÌwÆ*=îªh\\rÈHñÊ+bb¶àË\QáÈN}¤¼V<Ù jóÙ-kG(Ñ {ÒÐªâ­]ì`Â¥ÔMK¾ÐÀÙø±·Ð\\ftöÆ05É-òÚ[^ÖÜ0P3Ó«j&/ÿç>U~øAk§4\\tYçkáÃÇKÄ»JÏú÷ähñôÁusBüÃÕû:Ã\\n\\r\{g.æFÉaXZ³yßi¶xûäOÔÓï>]kÝ»è¾dÔùë[6¼àñ*kð,oÿ04å-Ó`ú½=¯Oò\\f.JáAì>Ê/¡ëíüÕT6ca\\b+¾ï¥{d7$þÑØzÙ>Nâ!m»úzãª\\f*x/IÏ¨.»ä±|w`ùîýbºà#b$¢¸fìñöüÜc ppfíOè*·¦°N*O\à·§ëä<9ü¼îÓ­xöÌÅw÷÷14ÂBí(õ±ùç©åÜáIÀ@Á¬eûOt%WÅXâ(ºÑ à»éñ¼jå¶Î\\b¿_#ÂóóNØã©ÿa,'º+¶Â6T3Å×RÓ6\\fKêð\\rHÀ^dP×Rúâ¡¿É¦fÀg!y>?B¾PÎäpÉ¥¤IòÅæâ¥æ:+g\\r/iát*G'<ß¡1¶Ì+s¡µYRÖ6Ñöý6ÕÓÜå¡}'ÁÄ\\bñ¸z9vK]CùÑô}³ÆNy÷}¤kÑÑ8<«¹_oÞ½ÂGø2¨ÿ3dv.»Ü{¦\\n¬¢´Ø=«¯t<îÌö­×ÔùEË2iG\\b¦­ÍqQÛó&Vàþt²\ÎB9(â^ä6#?Îñ0YÅ²áÜ×ð¦ÃÕ;yU\\b{¿ÚaÚ÷ÜwBâ mÕWéRÓWÇ_M´¼ô©Àÿ_wÏÉÛ¹ ©ª÷ú3b<Ô ô°1;Û þoøÊ¨Í¯ÊÁ(fùàñêW²\\fÏåæCpµÑK°@×ôQØ_eçææÖqÉ*+ÊL·Iù\\r}[³%ì¨(£RÓ®V\\r0utYdHØAÝ¯] Ù#Çå¯[Y2NTgóÙ»Lª¥¸£l\\bjª,YcyÝ·i®\SÍ¯dÙP9'xª4Q,=W@eØ}~Ï|ÎÖk1)Ç\\rºOUmÉ±î\\nb¤²ÊnXün?ÿYX¥«sÆÕ¾Zè,Ðd\\rßvtÑ*ÑH-yÿòÙöwÙ)8B×WMÒw=Pk%çÀÿºdªÆðú¶qëÔÍïL-hÃ Ïá)ê/:\\f9Ù\\r×æãÁO&ÿ¡òl¥a>tò*i'¢ÎÁK×«]ú÷Î×´£¦\\nð4Ù"õÞE\FE½ºß:,Ò³-|ô`¬hÅ\\tÔZIKVëÛ÷êºÙ½÷K\\b\\r<d2§á¾#o¥KéOWùä¨ÿÒ°a)Ñ2e^¾ÙùêõNÌ\\n½\\b6á¥/õ*Çs;A¶uÞ<²>×SëXÀV\ÌøÐV©Öæò·' ípXß\\b#¸îNìm]ã2¥ûôb8wx:1ZÒ~¼÷`o1ýD7´©·ÍKD%MLé#CÎ®kØôÕð!á(pW^ÓH -oãïÌµ&$OzYvK"#Hë3½í§Q6ý·ê´Qëç,Áõ"EªW¬NV+M×AúâÉa~y´;÷i¾ø\\fOþÂ½|²Úì»ÿ-ä¦µºxÅûÌ[{,àð<¾¾²h}\êGÌ¢(¬Ì>áðÐEX9ÊAæ¼Lk±Ð·ë %k\\fëÀx¶ãýZ³A6ô \\bâWÅµñÆWüÇÂg³q§-("*1Ö³ô¡´X¨#¡LÐáµ;o·$dþºzµöGðÂqÆÑ\\\tA¬K~d]Vl«Eôa¾äü1ÇUþ¹?¢Wü)Ì ¶=?ÙC­8ì#$Z»V¶6,KÈóvý+4!åu>2ÕDX´àÿi\±Á*.@Ìy³@_u;ì"GæpínrªRõý¯élþ8|T1Çdí2?×L×¿f¹FÿN>ÄöÌUªºfÈû6ª¤L\\b}jxebOQEz]©ÜèIÝª§)ï¡ÑzW?åÞ÷ÆÌ¡7´³ÄtûèÞÌ0ÛÐÅÀ@ÄªlÓv'RÑ¦r¾ø¥|[5ð\MxÎ=5.Îñ$F1¤_tzÕ&Þwq*Qíz ^QúO£?éå?yÌ¥m\\bmÊíùA£Ñ?1kF}y`e#\\ný<Ýýw[j|D'Ü+WMÎD­jÑ}óß=~µ&¢lNÙXõëtÁBçÉÇ7l)|Z^Ì\-69Ï5ãé6M5÷vûø^ý$Ô´&øâø§ÞM¹ _VvRët"ÂZ\\bãîÔò\\rØIÖV½õ?kÃ½C\\bµ\\fgÛÝgjûë m}íyJ,\`áà§¬ãAôêþ_62TêNÉÖ¦Ó_ÑïòýE\\b¥eÜ\Z:¶\\trm?ÌÂJöÂ4KL­PW\\t5®×ÔNÅï ïeuéß\\r%O;ó7Û(vòk-ç dÏè`Ç;R÷nÒòñ:»¼ÿâR¼½Ë;ÁA"¿O^*ôÅH[Ã`Xµäyÿ<­|#çÆQÌç+ OÁ{\\n¯ëÛ.Âµ"ÖMU×»c#üI/kÆ´ÐNÑÆäðNJv¿È$ÜÑpÏ¶"2ÍsÔ'}H¹Ûöýä9¥mn®ò'ÙÞ§ùæioºiEjð£ÉíÑ_. F@æ±8~¡0ºXõX°º¤¤ÝÃu¬ÆÃÙuçÃÿHÑx¾ªYUiãüá¶'Ò&Â¯Zùæ¿Ö¡~Êm«u5\¯]kÊÉÛ=!8çß}QíÌ8 §³ì²Æ\\tAòEï'&ßÙÿ·3ìÎpeùQ\\fÄÑ£3¤ÆêÊÜ¿¶b+hÊAæHÈúâFÀõË²ï]×gÏãË¨´9·4õ-;¬¸<[¼;&.ræçÝõûÈ°½ÆøI¢±¡Èùw³eyÍAü&`k ¤JÙtßCKüÆ¶ü4ü&Çøx¦\\ní9¬ë·C{¬Êr.ø Ú«1-#¢tû£â­è¥?-hÝeqÏ.Í-c²±²¿ßV`Èáet¼ÉöÍ©¢}ù"½Qs`êTwÀï½\\ré\\ts]76ÌÀ77N/]xÊ¬¢(8Cëz¨¬B¯¸n?YëÚýí]!§Ìs}Ùp·?R±y|yÜ@KIìzi¢ÿÞKìY©Ü`3Ávnì#Q°¦ym{ 1QïßÔWVé~}º;3©Ádò×|ÄY1?;­B±sî`§mRòÁ¤ÚÕO+3Ð©Ôå%,÷¤+Á|QÆmµa&RDc%ið_)¹uy|a¨fi(7ÂNÿfÞHP!ÇHe'bÆEDÛø³/x:.y!ª»º\\bSq <mæhH²\\r¹) .êë½÷ÚDÜ$²RºHfF  O×BX(H«\\r }ãèÐó)Ç©üo¥¡kCã`ñ¬%fc,ÝF*äÿøÄ.ÎRêxÑÌð+nÑ¤×6'\\r:T^UP\\b¬\\b¹vY»¸­eeD ¸h%[×°¬A³E;2RWL¤ÅF°¿Ý|º7js\\t6JAKmbúô²¿KKTéÉ>´Ñðe8óIxuº¦ ¯×#¬¬ÿwË¦ðbz,{Þ_èa¯tyE9û»¼à®å9©<²u]¶Õ8ÍØ¤=ß3Úª¶ÓÉ{è·ñ·pEc}1ÉDqy6À_çBé;Ì6RûÌI\\fÅUCäVIfì¾F~Oc1F_~ÐBmÜÏ=Ô,ahªx=äÁ'N©ãó*J #N íå³ÔÃÄ±¤O#DxI¬Dd¿41Ïª#ËÌµZÎiÏýæd!E3íVEs¤mzRtr\\në:È [bî×à¤\\fâëðQßs%:uá¨4è^´ÔcA)ÓêpÝÎÒ|i¬ Ð¸X$1ã«¥¹=\\n¤.@«8¿d¿\\nÉ`Å=<oÖÞÉbÞ|«$¨\\t»ÇSÄØ\\fëQÛÂÙG³ëCÎéOPnb®{_¯ÁQ^GèÞ`Ã>k`¼Û$ÄÇã`xd¯å×ÍÌÈV\\nèr£¯×"¼5_~ßØQ\\nÏe9ágÐ.}þ`L'Ãólpò\\r÷Þ´¶SJ¥S¨þzG*'÷åá¹À&óiÆåå\\b7û[È`©VtHnH6çëýâÙØGZ>ñ\\rOë:\\rì6\ ¾\ÊÂIk<±»¦ñ\\f¢Ò¾¾/DLXµ³ÏãøÐâ6²`H¹"ó[À\\rÏPK.¤5lÿ±mË§}3~º0ÕªRwæxá`o}µ·î¥N7µì%ö]õ­s®È&»w/ùTäUpòîØ£Û:sÆË c\\rÂ6hf\\tïO>I××ê3q?\\bÌ¬¢ï¤/©4þ¥2¸EbòSædsKÞ§´þâË¹0üSÑ>½Êl8=éPuÏXh»|ÜhYÔÖÜEÎa/ÆÞås»Æ,#¹'}xö»§AbÇ{ëÅÇ/ýá¯àà'p±ÖÄºuæçõ¯$Im]ÉV¢É])Ûíç°þBâIi*öÉu<<ì'3R¥¤\\fÇ®C´(ÃüÊqÅÁÈì¯öe! ºpÀs÷jÀ"XÀø{jVÊÜ½Ä+µ¦{£îkQ5-÷Â{\b°îFée=[¥°ô#Í²Â[ç{«¢/ø²>Ù.~müac²äZì½¤:m,%í%abTÂÆ=ÓÝÚÌ°6ÑOìm+zã¥æ´Ýû}q«O·ÉÏºäù+ÅÇÊ;ßÎ÷üÈì9eL¤Ó37jn0Í<ó­´(Ùpiò/ë@±YÙ/-ñúæ'
    //   70: dup
    //   71: astore_2
    //   72: invokevirtual length : ()I
    //   75: istore #4
    //   77: sipush #32767
    //   80: istore_1
    //   81: iconst_m1
    //   82: istore_0
    //   83: bipush #12
    //   85: iinc #0, 1
    //   88: aload_2
    //   89: iload_0
    //   90: dup
    //   91: iload_1
    //   92: iadd
    //   93: invokevirtual substring : (II)Ljava/lang/String;
    //   96: iconst_0
    //   97: goto -> 203
    //   100: aload #5
    //   102: swap
    //   103: iload_3
    //   104: iinc #3, 1
    //   107: swap
    //   108: aastore
    //   109: iload_0
    //   110: iload_1
    //   111: iadd
    //   112: dup
    //   113: istore_0
    //   114: iload #4
    //   116: if_icmpge -> 128
    //   119: aload_2
    //   120: iload_0
    //   121: invokevirtual charAt : (I)C
    //   124: istore_1
    //   125: goto -> 83
    //   128: ldc '¢íÎüÜ¬»\\b"yý3þ2⋡`Äd=t2ÆçÀH6¡\\t`ó>Í:Gu#0UZÓ¯Xi6fä±oËö&É%dÁe&x>[\\b½¥&Èî}I`¶hþÈ`Ú_Qma>69öÉÔ`³­¶ÚyA>îÖ\\tSñ£ *\\fó'°îLEòU±9x¥-ØºEºTvûÕh z#?K>'ªAãät²+}ÞÖ«A¨c,ö¿%o ¸ïc\\fóç¡±<Oì<édä¦Y"¢S=áÑ-E#l¡½ueU1%¡=üZQ¨r±e©I1OvÉ};¥BL*æÛÀëê0NÐ2&ãØ©pgÆr6ÆÝß¯8×{qá[)×z6B³HÞ/ßÚõ "¶&0êRâJ¸bë\\f-´©éÁDÈÉÔÓ-¸f½J>âý<ònÓr«±`O;Þ»â­u Æ±æ**.ðOCW\\f´°5AÃ,_TêÝ-^Sa6o>0õÑÏ³êñ\ÚGÏ3U0xx ÊjÎ*ü6îáâÌ&°õà×JYÞ­öÉ¥æ/aÂÂn½ÅI°}åT3¤6îûWÊøÍ6<úYæ;H².Î÷×ì°­\\bV¾Ô¶U.sÈ±pWyQ!>ï8ÌVôtÅ¸ Ç_Ðdñu¾OO¥ÃJgÅk\\b}ÍUf¢öô Ü®%·>öº=½ã/£Ü#BGúõ4O4`q?äó $§Â³û¥SØiÇÊÙu¼Õ ùc}%v2ËLmÈõì( ¤{ÂïNÓ¾fÙâóÕäÜ-F÷=ÚE-±:G94®)â^oYÁ¡)Æ¯îZËÁÎÇïÒM6þ\\fÇé(zScIkûø eg¹ Z+q{(rD`iÏ¬#mEÞ÷·h ?H?¼T\\b$C¸®ãÐ$§¬x~È|Â£MìßqÙÌ*õë1Þá&ÊM=¦õkr\\ncxw´ó©¾ä³£UC}\\nuKïÐ¬_Ë>iì|V'£'¥5-±¼rÈø^uîÛî=Eü¸;+d<B\\b¸ñ-/ïÀ+!!ËÚë3Åõð¬:0qÇnýÿ4O~Án#5Ìüwâf*²{^¥`PâÀeÑ£@Q ¡ÈÇ±a5àûøÜè:yj÷bp¡ºÕûÞoÿ'©WVOÙh]#{©¥kWIìQÆðëJV°*ö1ü^,µüØ®!$·#QÎXZÚÂr¤z_5×ÁÎ\\nFÁ)ÈßMö£¢À6ÍD±ìÿ+òð²6/{î>-Ïn\\bÍ5Ä)×Ä<Úà­[QN{kÎX¡îê»>TRsö´Þ­\\fKÅ\\b¿VÎ¢ËBöGQÙ°E§¿àpÊÃÌt£ª»ÚÊ[¹ßBà2_ä3Ü@¨9Í×ÔñE¿\\fê}_©Êt·ÄM¥KÓQrÌâÈçõð° úÎæGðÍìÜD(E«itx;\\fKDÚôc2ÈØAtêËfòZ»2ßúnõ9r°õDËby÷5í>ðã1'Ú(\\f}¿I¯'7KDÝènRa9=\\\r/¸Â²*èãÝ¾FÕÞ¸¸o¥ÿ-JØéáIÓ¢xCËCFÿä#ðj+.1|üQÒÙ¤Ã¶YøaHp9¤+èÖ® £seÏÝÅbòÔÆ<{^{ÄÑ°?YBlk°V¾w®:Ë)XýzÄÜeÔüC)V´¬¾*pïr=¨%üF'Õ©ðàwxï%òb×a«!ìù\\nÅ¼Ê=Øè4Ñ;B!/q4cfBÃQ½FtçÉZ\\b^S«À­d3GÁø3T98Ñ_ -2l\\rÒ+ÓXTs`äÀcý»bj EBUÖÅ °JNSø¹öê»f%ßj</,ãfYâ]·êJsÕQe2J=:ì9Õ@AwQZYQ³ë¶<äòJ,{?bq¦67ÿ@Þ\b[ö¦Aë3<vÀ=?×YjÕÄtÇéÀn§Ûdøâ<5/Ú¿Î=~ß.Zé$¨[çó4Ó:Gé>EÍÆu±$Gß®óc÷GÄÔò£î<2Þ,hO\\n=âqÂXã63Éå"e¦Ðk½n\½¬$y¯vD¾%¢ä·`£Ú§ÏT´ér3Â¬*½¾Ü¿ýl*ÙM\\r ÜZy4S­µ Ö>C£±ù6ûAï£CbÊ×\\fÎVâ8´17úò~LÓÖû¨\\bkvz<à~@{½è+ÆH¬ã{¹7Ê.<)¬¾pYÇhgbØ8CÛ^Ðá}d­©e]Jøë_¿öC+ä[¯\CyäÐ(â¶"mÁ¹>³ê§)!_{èwþué(Sï@MHê§¨0cÎñaöaìýa1> ¨c¿Û£ëp¥NzÓ}øaûÂéG@*pßË ßÚ­«\\bX'-úß|ï8Mià¥¼ÚtÏÏ¢Ç\\r(h4­Å3»Ökå-~\\b¶úÔO®¾»T¥N]®ËÒø«Õá¯ÔmÀ½¸øÂÈ«9©8W7ZL}?5%ÃÀlgÐúDÆÈJ1hfz'úÁ\\tÒÉ/Ì±ÏÛ·Éï/F#£{0Aïuû¸²"Ä7d~Þi &'.Vç\\rCC!µCmÒyCq·íéê HþmmîKÛj4ZâÄó\\t pjñk¦Ãáá£uúÿüC Nâ)¯ÚÆ<26*ûh ìjó%CYnt*ÅÁ9EM³Ø&tFB´ÇªOia2v¶ÿÌPcLÜ»¼>E6Ænizà:É#ø}ëö/ÎÐ,3LÊSCý¤óØüµ1º»&ê&WçÄv°Zn¨Ñ`ÖÍz#G\ç}#°©'öÖÿÔ§\\fHYxìa¥*« GXênÏ-Ùú2p\\bâ$Ìã{bèñËtõäÒM è\\rª¿xÓ-ÀçéÒHtÃçåI|pÁ)e]ö1Í ¸Õ}\\tZõn5:µâèE³X$ßL1©>në;°(aûôÌEeà®Kù¢w ¤MÿtåFG:ºØhRÀXé|Ût£·©Ö½,ø¯«oéHJë¬M¯9ª¼½×8¥g=Ù í¨"FX&ÿÑ;<Äì[EcMÌÎqÌJ8cP¬ÙéÖW`9ÙK¶ÂXj³`pJäöÓîë\\rÓó%|\\t%Ñ=ÕÞK%ÍV½SÚ;>ÅãÙÀ¦Çbâ²l\\rÆ\ÏJÖØé°YF{8`ÓÓôBúyæQ[Åx°Ð\\fç}æýuÝ¶½¦Éz'òÎ¡A°_hØZÙûOáÇ'!Bj\\t ¦Ñ¢aé\\f±ßø\&qh&¥qñ* 7l7Za;Sá§b³lÞ]\1QÈ~T4Ðõ¯L#'iÇ~î-M&$ÑU¶lÂÛî½ï]:¤ÖYú¿¨W'Ìê^imyçzÒ PñÛìäéA!5ezÛ¤ Ý>Å®}Y'¨{ë!ÜV7%ÿcaüíeâ_~Ú{6{ò`æFÂáiÆJí¾='ñô\\fo80m·)ºæÍqjwvùý,aES¿Í,Fù%äyynwfI(â¡â<¾ìRm»¹Ñ,.Å³+%ãG&&÷ÉpÊ¾»ºö¬ÂÅ>ÍùÔ*îAk\\tS[ôP èéÜà¬\\tòø94%äûo#1Å×¼°y,«2ajÊ¼dögi¢\\f¢âÍ!²÷59ð'`Í<Ù÷ñ$[Cd(×ºÁOãÛe¡¨À}±=Ð®HÌø<xù]âÃÂÏãÿw0´æ#%JLTH!f\\t\\t3/é\\rh{ÅwèÇÃ]HrØoVtuÇj©nV³Î­ÕÍ°ôðìpLÐè:½´¿%RYn±s¹¨U4dV+i£Yµ&\\bjå¯WÁb®æÞê´t\\t3óÕ)Úàëà'èZûÔ³nø\\bo³îªMÀö\\rÅeªEÖ§Ú­.°8&-éKc×©tÖ·r²ÙãÃ\\r¼p±Vë\\tbÎ/ìÿ)Ø=\\b ÅM{§æÃ¡Hæã2²Ê³tT2ÄØÌæA§b5Ü®/Iÿ\\b_²Ï~cD#¤*ºØ-ïPü5ZçÊµ=¹*?Xó9XØeòpÀàà£Øáj(Í^Å¬ã2,ë]EÉáë¥7â8ËÿàÁbí}Ê¢D ÂðÅ8ê3ÁdKCmÔ«<`lÄ  Cí#ÓÊ¯¦¬ i×ÆWg¬Þ{Åp=ÓÖóy}1rÜúp~lô§ºÕ!l%¶ó z$fJr³Ákiu¨QßK&¥ß\\f¯Ã?lÄÔbëlQß|dùÃ\\tàé'\\fN°±{rXZ7úÑº®ìÞR*îÔx´w­»,­ËNbo\\n7Û~³Kåº¡ÉN§ÔTÌåúÈ!1¤:û_ÌJºÃÀv«ëH*tÔôW(WlR\\rËv'váfßJÎùÅDD:È¹Â8ûGÊ¨¢pO¸øí8£»dvä6ñC=¶¨ä`÷Õ\\r·Îãß¿ìN85Ó4f>àÇ4F«.ÌÃ£lý<i÷þeu'\\b(æ5zHÓ9Þ Ööq+(Eç¥¶À&²êè¥âýKkV/z_11mìââ7w]Wµ\\né*ÊßÕJ?=93Ûé7Ç}Î_82¸´%z_COKL¤\,\\r@åýW³çh3êYÒõB<<ùé ¢^HÊýZ.üÁæh«!2AÜ3ºÚÐÇÀÕqÖCº/r%q@8XøÖ \\nTZ |zÀy¢l'ã/P³ÁÂGKÛõ¿ÏÆ$@\\f¢ÝJîRÎQ'n³â>Å`8OcÚ´L°øÐõ#îRµ¦'ó£nûó¸ âXu<o±4JzÁsó/x%Uc7Ëã0À5f(r²@SÁLçK6<äSz@Nl>¡±¬¯ÿÓ*¾è÷vX0kå¹³W\\n×dñÛ\\rd­WýK>&»uÖ²çþûA¿µKÈ,È|±§â´Þ9.ú2z¶8Pd´\\bs)¬d5Þ÷Û}B7dÚSG5ìu=üÚ8¯ÃKát¹\\r}½SíöLÈÆp@×Y6äïÎØûxnBJ3vÕ(ÿüó74²yØ¶W D v\\nÍQéáàÁõ©ü³¤åºa÷ã·ÎZî¼ç©Ìü){Æi~1t$a~\\tÏXÉ8âÖ¡¢yýe¢f«®u²C@voîñl@3:`)\\f#ØJ\ÄÎkNïË8vPW7¢v)V~W-â3°6P&â\\r;ÝrHÇ«g¢¯é§<ÁwòYuG/@·Cà$¤·Ñä¬Ð,'àÍàb§-0|(ãé}ÃóÞËâ%*ÜÀÕT|¢ÀÏH¾r\NV~Ù?Ç§"e,hy9`q ^«c\\rô*ÎXû8d)Õ³\\t\O¶Ý²±¯®êÔmkG-­EÙ9'KëËíàAFgutßäyFÑÜdv´òò`ëâ®={kä¶H¤ý9I¶å\zë§\\téadS\\fË¿-©;wmç¢¥,¶Ê&»Zm<ËÝ3ý¯L-þ±ÿ@26ÂtûæQ}ÎÂÃ\\tý¢ÇO,]§@mç{ZóÃ\e~¡8'ááIUçhQÞ­ÿÈ[gHzR30æºv¶ÎÇób¤cìBJ.¼6i6-!*@ÄéK°¾´uMð[Q{9vµW¶ýù¡Í\\tIÄÿ}¢TÉ@ßw]¼´5öþÃNªWvxoó«ì»øé\\b³xXWØAÚw´BÕVÓµõê'÷/ã'°/\\fhªU?ü{®rÚ¹C.×bÜ*ª4ò¦ÌÐd&1HúÔN+iQ²£o,VÚÌb#PfcbBÝ5ï¨ßÒs/#5õ ¦ÓÅUnoV¿\\t5U}Vµ\\b\ÃSÏ°^óÓk\\fjèCh0¡hï&¤ØKèooòj¬[r©R$XoDý+dhtÇ¼²ÏÉz¾¯v®oÓm$|\\bS<ÖZãtà1Í°kÌ:øTt(aÕ´´õ,¶së"Ø"ß\\b°Ä+ºÃ°xgÛ3Ëdÿ{=,Üw.×2æ[\\bñÙ(ÒQö^¢åw~÷z"JsÅXrXuND»Emi7'j?axEÝìFêiÒtµè&Úpüú&Ë4ûDÎôûj@fW°»«ÀV¯\\rA«\yGzG`ü¥íûk¼öJ×Ó:.PmùYÃ\\fzfäLù/(çÜd¯ð7üÔÚÏÃÜuS\? 8ìi»ä\\t2lìN*ÌB±äK"hDBw(^I &¾hcòW¬Üã_<1ðWü-1U-q4\\tÑ´=pì¿?`_=ºæþnkCvØ|DZ¹@4=aRMÒÏuµë¿0¦7)¹1ã.Ê¦§o&3^`·ó°MkíEø)×Rô´ù\\f Ï¤çeÔÒÚ]JWØºçÿBÐÿ.¡\\tï« Eöàð¸\\bFùPZtðªúQÔâï¡ÃÅVD=z²]I?¸ÆMEª£Üo\d:Èþ¯äV02è»T(þGeù,(5,?êøCpK³ZL;hiìs`¤Òûo÷1Ï7BòY{ÈRn\\r­Y¿\\fFÃb*§)Í|{òÈ :Æ\\tâþD\\f×Ü×[\~QY%måèå×^Îmqç<ì <HÐq¡óØ]¾(¼ct¨¹®ïz2nøæùþ9C2¿ÒJ;=Þßåú]Ï¬¥j?P?ò¦ÍË7ÆS'Ìy×ìvëh¿¿SyõõaWDÎÓ?ÊÀ-?Y\\fÂoº?Ã¿\\n[`ÿ\È[ç0l´|½(»À$Â2­ÕkªF°Fà¢2íÉJ¡ÔI]hf£\\r´më2é\±E­ø;\\fæÃ®!ïNþ×ië¸;ÿÃ,¶©vÌï.ÚsJÿ\\b®PM =}Ë^"5èÏRI'(óY6w)ùøãÃ¾Ù{/vd©ó\\n.ØRÃºËOÁª¢hx7úw;¢ò´¤\\f*ÇýRØÀ×(#¡¸2ýWêhAÀsZJil'z,V/·S½XÚ4Ä/·i£aQ*ÖTßÃÙãÒ9-åëì¹äýÉ/§õÑ:q0:N¬´¶x±ñ oOö7«®2÷«Aû©:[oÿoG\\tTëGc¼*;áäÊCXOþ+¿c>ô×ªdTb±á {ñvéê}ãy9í¤ýÆÙ.Nh¨ñi§¾i¨{+saÃ2åÃ¦¥9ðÈñý ?5&^]õ´¶\Ecc|=y¡qÁ®hr=\\t8·Õé¸´ãyî3*á¤uð©'BZ®ùÖæP¿:Ýªà-Ó¬aY/PoÓØ£XNá­ðJª×É½ýbïÃPì_ ý@ýV"âK$+B2Y>\\r@ÿöÊà±÷t`ÐåIò¸Vi+YEkþ¨÷ÙOR=èKú¯ØQÛùÞ Ð¶JÈ MM¡í¨êÂ_H0^cCýÇÅH3_"ûWØºzÉiÞtõg6¶-Ó \\faýNJnjÿ¦-`þ­®ÕÛ9#0!Û£©T-|ÇXÝÒr¦\\rÄÿ]ù¼ÝÈ|P>à°fý1?D.bÛC´)Q®&­ôÂ*.óÆ³²ájØ¢f¥Þ¯,zêÜGÏGígQºÐ¹ÌçT|rDÂÔþg?âw?¦\\r£;Õ$Ó¢õ±"¥eÈ!Úö,¯a;&NGRDfÙDð°ÏdºDàt~ìE³ð½ô³ò!Fm±@<¯«tãÄVÙô|üQÄzþÀNpVh¦[RYyIÚ¥½±WSÔÎ/!í]À3ç%²È"bV3ÇòÆsÓÃ4=%Me$4¨K-¬THvëÅ«¸&OÉóØ( 'ªù\\fDø09ÕÔ8YùíÀ,ÌÎ¶Æàë\\r\\fL­ô°Z·ãQ+b3=+Ø¾rªª¨àM"uqzÌ¡æÞ9æ8«1X4Þ%!¬+ùî,òú¾\\reÐfÔðÍÎoëÚö{+Në-x¨Ú¿êz¿ñÏ)ô7æPøûÍë£\\fâ«#°9Îÿv3hqyõÂ7Æ\\nÃPôKW}4Ù^9eäÌBÐV¬bæH\ux9)ya9ÅÝËÈ-\\nrùg`DÕð"ù,u¤m¥ò» Ctlo° *áÈ<©'ßÃÁÃÌ&qã\\fZx¨·Qt÷ H ^U,þÍ{Ä»´ûHPõE?ïm^Ï)fYþÊ®ç_tÖ8ÅRLKtfL/ûSiÚ8fR]înKÀÛTWxèw°Ùsnré)«#ÛÑ\\tîùÎÖuqçT¼þ'çªXîþ¨výíø'VJ:+þÄZ6¿bÑ.É/þà+ fW'lK6}4Öâq{Mð±Ùfõ'u¤¹Sy!ÜÉNX¬2°2C>.ÊÜTØ¿°¥y¦,\\rÅ1bS·o÷ð ä J»È!<I¢x÷ëVÊÏ×°¾WKÙ¹H&\\r¦æ=/Ã},ýÐb¨ÆÑAe-ï1-[|\\rEI3^Êet¦2¬K_Bõû*»#á#Eýäíªé*A+[ÂüÏfou2\\nFé@4Ë0:`\\r,ZÛTab^ÑBjúÄÀò\¯¯AN#.EîVòåµMÖ­Büë©ÆùBdwÛ}®¿øÊl.Ri®S¡ÌvûW¯cÃ?þÇü¨!\\nþÉGIë¾c}&þ¶ÀÜã¿(î¤ygxÉ1ì#÷ìÈîÄ[Ã[*pB6up@bÖ°¯¤K¯Êô¶=ºBßKýã· )`ô¶t%³]¾½µKo@ùùJÊzDþÒ ][?'.Ò$\\b\\rµ4OÓäà°\\t½sº¡) jàÔ¾ÄÒÝ;6NFÄ kl[Ê¿{|/ZL´_àqvÃ²ôND³/Ct õtW&uLI[:ì£hsÜ&ùvd»Ì{¾,AA2Á1=8U(íÏ1@`Ï\\n9¥m '(Ûè%d¡ª²`Å)hvðÛ³ù(£¿ô`GT1f2ÒæeZÛBÌ²¦´/¶ò¾¤X5RyãÒöivr»«;-R\\bVúgK¸ :öE`Qoç §øxE-éM|6z?úúæUÚ°­dÌ ZÄyêL¢_¨¤zq¾;§DO©ZD-Rï°g\´±¸+U°ñ 3Üù2³^µó3Aýi³79¸V¦0ñ45ð!u`Æ#rVË:-7âÉ®§êb³l*u òü9¦½°ðk"ð Õ­xF[í²«ËX¹x  )BÃ&|Ä#ÙvtàÛ2kÿtFd¦æc2\\b0èf_Úòj¬½Iî?ÝÆDfä·Ý}~\\t¨nGÆµàL¾`:òU8$ÖùÎ{¯Ï-½Â¦!ÂÔ¤TM( ÁýGòlX mpXæí³OR.dUí+»VúÅYï<6YÂù7Ûøj¯ÊØ±),CoIÖhöÜáÕ¹Gä@è_àÝ%t\\f\\bÀÚù`³:s&|Ò¾-Ð¿(\\tÖäü7@dõÏýyÒlëqíjÆÉÐ/D.´t1ROoÁ{kj; *F=ÅÜñ±Æ=IfBÇ{TL6í¶wìGtsý2?~Âò sJ1Çù¥ÞRå¸¸ÕN³[õ\\fgDEûÄ}·æ­ß½uÞ$>wSPW¼'uWr£V®×ðÌ·çÚÏÆëð`\\nþ§tºÀn¾ð/JwÈ\\rWÞÉHøé/ .Ù_ñõyAe°Öi%CäøuJ¢àKÈ©ý+g¬ñ\\bfÄÆ¡¾¶8*H"XEªbv ^¸~ôZ'2³KêÀ#@;Z+'ù5Òã0Òë?G.\\f×E±ÔáÑEbý?1R§1ü\\n|â£[î®ò2?m&dÆ¼Ã(nk®;ßØ ~×¥ÿ±k~bê ûí¥15±·ÑÐL¦ÿwi\\fÌÌ¥*ï.à¥ñÊÈ\\nôè*)Zµ²Á1IYXEsbçT­òHOliGÖSÙçfW±)g²ÀHÆæø'ï{\2!muD¤7 Ò\É¿ñõò-\oðÓ9ÃÉ¾ñû¨ _qgÄrâÚiÆß§:Út\\t1)¾)ÂÁù§?³¶küO\\f¥û{lxÆÖù\Q%Câ8úÄUMgPMã¸`IÕý[èpE:Ép\\r²òÞ »Ùt«Ï?ìÈR\\fÃ¶hÐ7ÉfÄé\\bBâ%ýWÒ²:¢¹4-6WÌ"%#\\tª»>Å<þuu¸Ó0GªªnÐfÆp®ÀªéeVËE.mNkG\\nÐ»ëõÇYn>d:ÏçúØ\8*6^ÙcEµ§\/ø<62xÕÂÖ:ñ@}Û_l²&öÇñïÂ¿¾NÁK_Z3ÝchMsEÛñû\]+«â¥î\\b)§ÑêFôÆ%ù0gÎ¶Ø´¿sÃxêÚá£\\tnÀöøc|¶£ÁíÒ§rX3¸×õÛãÄÚ\\rJº°U9¬ëÂ2[²ßÆìFm³¥øsí×Â¬ò ãu÷µW[¨Zsºeì§ya«5Àñ"añpYqÛÛkôÏõi3Úý\\nÒ KÜêîÔ¡ÌìÚWÌyX<o"ý^½b"lWxâ"­\\fÐ£Vg'W®6ÏdØ¿÷úYª±¾¯I>ëÜè<P´ât\\fpüÃ¼ÂÁ^%ãnÿ\\t'3]zê&ò\\tê¬äÝeøóv³j'
    //   130: dup
    //   131: astore_2
    //   132: invokevirtual length : ()I
    //   135: istore #4
    //   137: bipush #9
    //   139: istore_1
    //   140: iconst_m1
    //   141: istore_0
    //   142: bipush #50
    //   144: iinc #0, 1
    //   147: aload_2
    //   148: iload_0
    //   149: dup
    //   150: iload_1
    //   151: iadd
    //   152: invokevirtual substring : (II)Ljava/lang/String;
    //   155: iconst_1
    //   156: goto -> 203
    //   159: aload #5
    //   161: swap
    //   162: iload_3
    //   163: iinc #3, 1
    //   166: swap
    //   167: aastore
    //   168: iload_0
    //   169: iload_1
    //   170: iadd
    //   171: dup
    //   172: istore_0
    //   173: iload #4
    //   175: if_icmpge -> 187
    //   178: aload_2
    //   179: iload_0
    //   180: invokevirtual charAt : (I)C
    //   183: istore_1
    //   184: goto -> 142
    //   187: aload #5
    //   189: putstatic burp/Zekj.a : [Ljava/lang/String;
    //   192: bipush #9
    //   194: anewarray java/lang/String
    //   197: putstatic burp/Zekj.b : [Ljava/lang/String;
    //   200: goto -> 364
    //   203: dup_x2
    //   204: pop
    //   205: invokevirtual toCharArray : ()[C
    //   208: dup_x1
    //   209: arraylength
    //   210: dup_x2
    //   211: pop
    //   212: iconst_0
    //   213: istore #6
    //   215: dup2_x1
    //   216: pop2
    //   217: dup_x2
    //   218: iconst_1
    //   219: if_icmpgt -> 320
    //   222: dup2
    //   223: swap
    //   224: iload #6
    //   226: dup2_x1
    //   227: caload
    //   228: swap
    //   229: iload #6
    //   231: bipush #7
    //   233: irem
    //   234: tableswitch default -> 302, 0 -> 272, 1 -> 277, 2 -> 282, 3 -> 287, 4 -> 292, 5 -> 297
    //   272: bipush #76
    //   274: goto -> 304
    //   277: bipush #29
    //   279: goto -> 304
    //   282: bipush #24
    //   284: goto -> 304
    //   287: bipush #96
    //   289: goto -> 304
    //   292: bipush #36
    //   294: goto -> 304
    //   297: bipush #8
    //   299: goto -> 304
    //   302: bipush #34
    //   304: ixor
    //   305: ixor
    //   306: i2c
    //   307: castore
    //   308: iinc #6, 1
    //   311: dup
    //   312: ifne -> 320
    //   315: dup2
    //   316: dup_x1
    //   317: goto -> 226
    //   320: dup2_x1
    //   321: pop2
    //   322: dup_x2
    //   323: iload #6
    //   325: if_icmpgt -> 222
    //   328: pop
    //   329: new java/lang/String
    //   332: dup_x1
    //   333: swap
    //   334: invokespecial <init> : ([C)V
    //   337: invokevirtual intern : ()Ljava/lang/String;
    //   340: swap
    //   341: pop
    //   342: swap
    //   343: tableswitch default -> 40, 0 -> 100, 1 -> 159
    //   364: sipush #17046
    //   367: sipush #7158
    //   370: invokestatic a : (II)Ljava/lang/String;
    //   373: putstatic burp/Zekj.ZD : Ljava/lang/String;
    //   376: getstatic burp/Zekj.ZD : Ljava/lang/String;
    //   379: sipush #17041
    //   382: sipush #5301
    //   385: invokestatic a : (II)Ljava/lang/String;
    //   388: <illegal opcode> makeConcatWithConstants : (Ljava/lang/String;Ljava/lang/String;)Ljava/lang/String;
    //   393: putstatic burp/Zekj.ZD : Ljava/lang/String;
    //   396: new java/math/BigInteger
    //   399: dup
    //   400: bipush #32
    //   402: newarray byte
    //   404: dup
    //   405: iconst_0
    //   406: bipush #106
    //   408: bastore
    //   409: dup
    //   410: iconst_1
    //   411: bipush #-119
    //   413: bastore
    //   414: dup
    //   415: iconst_2
    //   416: bipush #-94
    //   418: bastore
    //   419: dup
    //   420: iconst_3
    //   421: bipush #45
    //   423: bastore
    //   424: dup
    //   425: iconst_4
    //   426: bipush #-42
    //   428: bastore
    //   429: dup
    //   430: iconst_5
    //   431: iconst_0
    //   432: bastore
    //   433: dup
    //   434: bipush #6
    //   436: bipush #41
    //   438: bastore
    //   439: dup
    //   440: bipush #7
    //   442: bipush #83
    //   444: bastore
    //   445: dup
    //   446: bipush #8
    //   448: bipush #-8
    //   450: bastore
    //   451: dup
    //   452: bipush #9
    //   454: bipush #98
    //   456: bastore
    //   457: dup
    //   458: bipush #10
    //   460: bipush #-98
    //   462: bastore
    //   463: dup
    //   464: bipush #11
    //   466: bipush #101
    //   468: bastore
    //   469: dup
    //   470: bipush #12
    //   472: bipush #103
    //   474: bastore
    //   475: dup
    //   476: bipush #13
    //   478: bipush #103
    //   480: bastore
    //   481: dup
    //   482: bipush #14
    //   484: bipush #-105
    //   486: bastore
    //   487: dup
    //   488: bipush #15
    //   490: bipush #27
    //   492: bastore
    //   493: dup
    //   494: bipush #16
    //   496: bipush #-100
    //   498: bastore
    //   499: dup
    //   500: bipush #17
    //   502: bipush #-64
    //   504: bastore
    //   505: dup
    //   506: bipush #18
    //   508: bipush #-88
    //   510: bastore
    //   511: dup
    //   512: bipush #19
    //   514: bipush #-5
    //   516: bastore
    //   517: dup
    //   518: bipush #20
    //   520: bipush #-70
    //   522: bastore
    //   523: dup
    //   524: bipush #21
    //   526: bipush #-39
    //   528: bastore
    //   529: dup
    //   530: bipush #22
    //   532: bipush #126
    //   534: bastore
    //   535: dup
    //   536: bipush #23
    //   538: bipush #14
    //   540: bastore
    //   541: dup
    //   542: bipush #24
    //   544: bipush #-61
    //   546: bastore
    //   547: dup
    //   548: bipush #25
    //   550: bipush #39
    //   552: bastore
    //   553: dup
    //   554: bipush #26
    //   556: bipush #-128
    //   558: bastore
    //   559: dup
    //   560: bipush #27
    //   562: bipush #-100
    //   564: bastore
    //   565: dup
    //   566: bipush #28
    //   568: bipush #55
    //   570: bastore
    //   571: dup
    //   572: bipush #29
    //   574: bipush #119
    //   576: bastore
    //   577: dup
    //   578: bipush #30
    //   580: bipush #60
    //   582: bastore
    //   583: dup
    //   584: bipush #31
    //   586: bipush #121
    //   588: bastore
    //   589: invokespecial <init> : ([B)V
    //   592: putstatic burp/Zekj.Zi : Ljava/lang/Object;
    //   595: return
  }
  
  private static Throwable a(Throwable paramThrowable) {
    return paramThrowable;
  }
  
  private static String a(int paramInt1, int paramInt2) {
    int i = (paramInt1 ^ 0x4294) & 0xFFFF;
    if (b[i] == null) {
      char[] arrayOfChar = a[i].toCharArray();
      switch (arrayOfChar[0] & 0xFF) {
        case 0:
        
        case 1:
        
        case 2:
        
        case 3:
        
        case 4:
        
        case 5:
        
        case 6:
        
        case 7:
        
        case 8:
        
        case 9:
        
        case 10:
        
        case 11:
        
        case 12:
        
        case 13:
        
        case 14:
        
        case 15:
        
        case 16:
        
        case 17:
        
        case 18:
        
        case 19:
        
        case 20:
        
        case 21:
        
        case 22:
        
        case 23:
        
        case 24:
        
        case 25:
        
        case 26:
        
        case 27:
        
        case 28:
        
        case 29:
        
        case 30:
        
        case 31:
        
        case 32:
        
        case 33:
        
        case 34:
        
        case 35:
        
        case 36:
        
        case 37:
        
        case 38:
        
        case 39:
        
        case 40:
        
        case 41:
        
        case 42:
        
        case 43:
        
        case 44:
        
        case 45:
        
        case 46:
        
        case 47:
        
        case 48:
        
        case 49:
        
        case 50:
        
        case 51:
        
        case 52:
        
        case 53:
        
        case 54:
        
        case 55:
        
        case 56:
        
        case 57:
        
        case 58:
        
        case 59:
        
        case 60:
        
        case 61:
        
        case 62:
        
        case 63:
        
        case 64:
        
        case 65:
        
        case 66:
        
        case 67:
        
        case 68:
        
        case 69:
        
        case 70:
        
        case 71:
        
        case 72:
        
        case 73:
        
        case 74:
        
        case 75:
        
        case 76:
        
        case 77:
        
        case 78:
        
        case 79:
        
        case 80:
        
        case 81:
        
        case 82:
        
        case 83:
        
        case 84:
        
        case 85:
        
        case 86:
        
        case 87:
        
        case 88:
        
        case 89:
        
        case 90:
        
        case 91:
        
        case 92:
        
        case 93:
        
        case 94:
        
        case 95:
        
        case 96:
        
        case 97:
        
        case 98:
        
        case 99:
        
        case 100:
        
        case 101:
        
        case 102:
        
        case 103:
        
        case 104:
        
        case 105:
        
        case 106:
        
        case 107:
        
        case 108:
        
        case 109:
        
        case 110:
        
        case 111:
        
        case 112:
        
        case 113:
        
        case 114:
        
        case 115:
        
        case 116:
        
        case 117:
        
        case 118:
        
        case 119:
        
        case 120:
        
        case 121:
        
        case 122:
        
        case 123:
        
        case 124:
        
        case 125:
        
        case 126:
        
        case 127:
        
        case 128:
        
        case 129:
        
        case 130:
        
        case 131:
        
        case 132:
        
        case 133:
        
        case 134:
        
        case 135:
        
        case 136:
        
        case 137:
        
        case 138:
        
        case 139:
        
        case 140:
        
        case 141:
        
        case 142:
        
        case 143:
        
        case 144:
        
        case 145:
        
        case 146:
        
        case 147:
        
        case 148:
        
        case 149:
        
        case 150:
        
        case 151:
        
        case 152:
        
        case 153:
        
        case 154:
        
        case 155:
        
        case 156:
        
        case 157:
        
        case 158:
        
        case 159:
        
        case 160:
        
        case 161:
        
        case 162:
        
        case 163:
        
        case 164:
        
        case 165:
        
        case 166:
        
        case 167:
        
        case 168:
        
        case 169:
        
        case 170:
        
        case 171:
        
        case 172:
        
        case 173:
        
        case 174:
        
        case 175:
        
        case 176:
        
        case 177:
        
        case 178:
        
        case 179:
        
        case 180:
        
        case 181:
        
        case 182:
        
        case 183:
        
        case 184:
        
        case 185:
        
        case 186:
        
        case 187:
        
        case 188:
        
        case 189:
        
        case 190:
        
        case 191:
        
        case 192:
        
        case 193:
        
        case 194:
        
        case 195:
        
        case 196:
        
        case 197:
        
        case 198:
        
        case 199:
        
        case 200:
        
        case 201:
        
        case 202:
        
        case 203:
        
        case 204:
        
        case 205:
        
        case 206:
        
        case 207:
        
        case 208:
        
        case 209:
        
        case 210:
        
        case 211:
        
        case 212:
        
        case 213:
        
        case 214:
        
        case 215:
        
        case 216:
        
        case 217:
        
        case 218:
        
        case 219:
        
        case 220:
        
        case 221:
        
        case 222:
        
        case 223:
        
        case 224:
        
        case 225:
        
        case 226:
        
        case 227:
        
        case 228:
        
        case 229:
        
        case 230:
        
        case 231:
        
        case 232:
        
        case 233:
        
        case 234:
        
        case 235:
        
        case 236:
        
        case 237:
        
        case 238:
        
        case 239:
        
        case 240:
        
        case 241:
        
        case 242:
        
        case 243:
        
        case 244:
        
        case 245:
        
        case 246:
        
        case 247:
        
        case 248:
        
        case 249:
        
        case 250:
        
        case 251:
        
        case 252:
        
        case 253:
        
        case 254:
        
        default:
          break;
      } 
      byte b1 = 112;
      int j = (paramInt2 & 0xFF) - b1;
      if (j < 0)
        j += 256; 
      int k = ((paramInt2 & 0xFFFF) >>> 8) - b1;
      if (k < 0)
        k += 256; 
      for (byte b2 = 0; b2 < arrayOfChar.length; b2++) {
        int m = b2 % 2;
        if (m == 0) {
          arrayOfChar[b2] = (char)(arrayOfChar[b2] ^ j);
          j = ((j >>> 3 | j << 5) ^ arrayOfChar[b2]) & 0xFF;
        } else {
          arrayOfChar[b2] = (char)(arrayOfChar[b2] ^ k);
          k = ((k >>> 3 | k << 5) ^ arrayOfChar[b2]) & 0xFF;
        } 
      } 
      b[i] = (new String(arrayOfChar)).intern();
    } 
    return b[i];
  }
}


/* Location:              C:\Program Files\BurpSuitePro\burpsuite_pro.jar!\burp\Zekj.class
 * Java compiler version: 21 (65.0)
 * JD-Core Version:       1.1.3
 */