package burp;

import java.math.BigInteger;

class Zem extends ClassLoader {
  static String Zr;
  
  static Object Zo;
  
  private static final String[] a;
  
  private static final String[] b;
  
  static void ZB(Object paramObject) {
    Zmdi.ZA = a(-5941, -4889);
    Zmdi.Zw = new BigInteger(new byte[] { 
          87, -77, -108, -101, 101, 27, 121, 5, 62, 98, 
          75, -119, -92, -75, -104, -60, -15, -17, -79, 89, 
          -108, -20, 49, 52, -62, 52, 125, -45, -125, 53, 
          46, -109 });
    boolean bool = Zt2e.ZK();
    try {
      try {
        if (Zs0h.ZX.charAt(Math.abs(((BigInteger)Zzpj.ZI).intValue() % 32)) <= Zrhp.ZQ.charAt(Math.abs(((BigInteger)Ze5f.Zh).intValue() % 32))) {
          try {
            Zdm.Zw(Class.forName(a(-5940, -13387)));
            if (bool)
              Zoa.ZP(Class.forName(a(-5942, 861))); 
          } catch (Throwable throwable) {
            throw a(null);
          } 
          return;
        } 
      } catch (Throwable throwable) {
        throw a(null);
      } 
      Zoa.ZP(Class.forName(a(-5942, 861)));
    } catch (Throwable throwable) {}
  }
  
  static boolean Zd(Object[] paramArrayOfObject, Object paramObject) throws Throwable {
    // Byte code:
    //   0: invokestatic ZK : ()Z
    //   3: istore_2
    //   4: sipush #-5943
    //   7: sipush #28173
    //   10: invokestatic a : (II)Ljava/lang/String;
    //   13: invokestatic forName : (Ljava/lang/String;)Ljava/lang/Class;
    //   16: invokevirtual getDeclaredFields : ()[Ljava/lang/reflect/Field;
    //   19: astore_3
    //   20: aload_3
    //   21: arraylength
    //   22: istore #4
    //   24: iconst_0
    //   25: istore #5
    //   27: iload #5
    //   29: iload #4
    //   31: if_icmpge -> 107
    //   34: aload_3
    //   35: iload #5
    //   37: aaload
    //   38: astore #6
    //   40: aload #6
    //   42: invokevirtual getType : ()Ljava/lang/Class;
    //   45: ldc java/lang/String
    //   47: invokevirtual equals : (Ljava/lang/Object;)Z
    //   50: ifeq -> 93
    //   53: aload #6
    //   55: iconst_1
    //   56: invokevirtual setAccessible : (Z)V
    //   59: aload #6
    //   61: aconst_null
    //   62: aload #6
    //   64: aconst_null
    //   65: invokevirtual get : (Ljava/lang/Object;)Ljava/lang/Object;
    //   68: checkcast java/lang/String
    //   71: getstatic burp/Zem.Zr : Ljava/lang/String;
    //   74: <illegal opcode> makeConcatWithConstants : (Ljava/lang/String;Ljava/lang/String;)Ljava/lang/String;
    //   79: invokevirtual set : (Ljava/lang/Object;Ljava/lang/Object;)V
    //   82: iload_2
    //   83: ifeq -> 107
    //   86: goto -> 93
    //   89: invokestatic a : (Ljava/lang/Throwable;)Ljava/lang/Throwable;
    //   92: athrow
    //   93: iinc #5, 1
    //   96: iload_2
    //   97: ifeq -> 27
    //   100: goto -> 107
    //   103: invokestatic a : (Ljava/lang/Throwable;)Ljava/lang/Throwable;
    //   106: athrow
    //   107: sipush #-5938
    //   110: sipush #10105
    //   113: invokestatic a : (II)Ljava/lang/String;
    //   116: iconst_1
    //   117: ldc burp/Zrcx
    //   119: invokevirtual getClassLoader : ()Ljava/lang/ClassLoader;
    //   122: invokestatic forName : (Ljava/lang/String;ZLjava/lang/ClassLoader;)Ljava/lang/Class;
    //   125: invokevirtual getDeclaredFields : ()[Ljava/lang/reflect/Field;
    //   128: astore_3
    //   129: aload_3
    //   130: arraylength
    //   131: istore #4
    //   133: iconst_0
    //   134: istore #5
    //   136: iload #5
    //   138: iload #4
    //   140: if_icmpge -> 277
    //   143: aload_3
    //   144: iload #5
    //   146: aaload
    //   147: astore #6
    //   149: aload #6
    //   151: invokevirtual getModifiers : ()I
    //   154: invokestatic isStatic : (I)Z
    //   157: ifne -> 167
    //   160: goto -> 270
    //   163: invokestatic a : (Ljava/lang/Throwable;)Ljava/lang/Throwable;
    //   166: athrow
    //   167: aload #6
    //   169: invokevirtual getType : ()Ljava/lang/Class;
    //   172: astore #7
    //   174: aload #7
    //   176: ifnull -> 257
    //   179: aload #7
    //   181: invokevirtual isPrimitive : ()Z
    //   184: ifne -> 257
    //   187: goto -> 194
    //   190: invokestatic a : (Ljava/lang/Throwable;)Ljava/lang/Throwable;
    //   193: athrow
    //   194: aload #7
    //   196: invokevirtual getPackage : ()Ljava/lang/Package;
    //   199: ifnull -> 257
    //   202: goto -> 209
    //   205: invokestatic a : (Ljava/lang/Throwable;)Ljava/lang/Throwable;
    //   208: athrow
    //   209: aload #7
    //   211: invokevirtual getPackage : ()Ljava/lang/Package;
    //   214: invokevirtual getName : ()Ljava/lang/String;
    //   217: ifnull -> 257
    //   220: goto -> 227
    //   223: invokestatic a : (Ljava/lang/Throwable;)Ljava/lang/Throwable;
    //   226: athrow
    //   227: aload #7
    //   229: invokevirtual getPackage : ()Ljava/lang/Package;
    //   232: invokevirtual getName : ()Ljava/lang/String;
    //   235: sipush #-5937
    //   238: sipush #-218
    //   241: invokestatic a : (II)Ljava/lang/String;
    //   244: invokevirtual startsWith : (Ljava/lang/String;)Z
    //   247: ifne -> 257
    //   250: goto -> 257
    //   253: invokestatic a : (Ljava/lang/Throwable;)Ljava/lang/Throwable;
    //   256: athrow
    //   257: aload #6
    //   259: iconst_1
    //   260: invokevirtual setAccessible : (Z)V
    //   263: aload #6
    //   265: aconst_null
    //   266: invokevirtual get : (Ljava/lang/Object;)Ljava/lang/Object;
    //   269: pop
    //   270: iinc #5, 1
    //   273: iload_2
    //   274: ifeq -> 136
    //   277: sipush #-5944
    //   280: sipush #-1802
    //   283: invokestatic a : (II)Ljava/lang/String;
    //   286: invokestatic forName : (Ljava/lang/String;)Ljava/lang/Class;
    //   289: invokevirtual getDeclaredMethods : ()[Ljava/lang/reflect/Method;
    //   292: astore_3
    //   293: aload_3
    //   294: arraylength
    //   295: istore #4
    //   297: iconst_0
    //   298: istore #5
    //   300: iload #5
    //   302: iload #4
    //   304: if_icmpge -> 436
    //   307: aload_3
    //   308: iload #5
    //   310: aaload
    //   311: astore #6
    //   313: aload #6
    //   315: invokevirtual getParameterTypes : ()[Ljava/lang/Class;
    //   318: pop
    //   319: aload #6
    //   321: invokevirtual getModifiers : ()I
    //   324: invokestatic isStatic : (I)Z
    //   327: ifeq -> 422
    //   330: aload #6
    //   332: invokevirtual getParameterTypes : ()[Ljava/lang/Class;
    //   335: arraylength
    //   336: iconst_2
    //   337: if_icmpne -> 422
    //   340: goto -> 347
    //   343: invokestatic a : (Ljava/lang/Throwable;)Ljava/lang/Throwable;
    //   346: athrow
    //   347: aload #6
    //   349: invokevirtual getReturnType : ()Ljava/lang/Class;
    //   352: getstatic java/lang/Void.TYPE : Ljava/lang/Class;
    //   355: invokevirtual equals : (Ljava/lang/Object;)Z
    //   358: ifeq -> 422
    //   361: goto -> 368
    //   364: invokestatic a : (Ljava/lang/Throwable;)Ljava/lang/Throwable;
    //   367: athrow
    //   368: aload #6
    //   370: iconst_1
    //   371: invokevirtual setAccessible : (Z)V
    //   374: aload #6
    //   376: aconst_null
    //   377: iconst_2
    //   378: anewarray java/lang/Object
    //   381: dup
    //   382: iconst_0
    //   383: aload_0
    //   384: aastore
    //   385: dup
    //   386: iconst_1
    //   387: aload_1
    //   388: ifnonnull -> 406
    //   391: goto -> 398
    //   394: invokestatic a : (Ljava/lang/Throwable;)Ljava/lang/Throwable;
    //   397: athrow
    //   398: aload_1
    //   399: goto -> 413
    //   402: invokestatic a : (Ljava/lang/Throwable;)Ljava/lang/Throwable;
    //   405: athrow
    //   406: aload_1
    //   407: checkcast [B
    //   410: invokevirtual clone : ()Ljava/lang/Object;
    //   413: aastore
    //   414: invokevirtual invoke : (Ljava/lang/Object;[Ljava/lang/Object;)Ljava/lang/Object;
    //   417: pop
    //   418: iload_2
    //   419: ifeq -> 436
    //   422: iinc #5, 1
    //   425: iload_2
    //   426: ifeq -> 300
    //   429: goto -> 436
    //   432: invokestatic a : (Ljava/lang/Throwable;)Ljava/lang/Throwable;
    //   435: athrow
    //   436: getstatic burp/Zry1.Zk : Ljava/lang/String;
    //   439: getstatic burp/Zkjj.Zh : Ljava/lang/Object;
    //   442: checkcast java/math/BigInteger
    //   445: invokevirtual intValue : ()I
    //   448: bipush #32
    //   450: irem
    //   451: invokestatic abs : (I)I
    //   454: invokevirtual charAt : (I)C
    //   457: getstatic burp/Zs3m.Zl : Ljava/lang/String;
    //   460: getstatic burp/Zly9.Zz : Ljava/lang/Object;
    //   463: checkcast java/math/BigInteger
    //   466: invokevirtual intValue : ()I
    //   469: bipush #32
    //   471: irem
    //   472: invokestatic abs : (I)I
    //   475: invokevirtual charAt : (I)C
    //   478: if_icmpgt -> 585
    //   481: getstatic burp/Zzc9.Zv : Ljava/lang/String;
    //   484: getstatic burp/Zzef.Zw : Ljava/lang/Object;
    //   487: checkcast java/math/BigInteger
    //   490: invokevirtual intValue : ()I
    //   493: bipush #32
    //   495: irem
    //   496: invokestatic abs : (I)I
    //   499: invokevirtual charAt : (I)C
    //   502: getstatic burp/Zbow.Zr : Ljava/lang/String;
    //   505: getstatic burp/Zsjw.Zw : Ljava/lang/Object;
    //   508: checkcast java/math/BigInteger
    //   511: invokevirtual intValue : ()I
    //   514: bipush #32
    //   516: irem
    //   517: invokestatic abs : (I)I
    //   520: invokevirtual charAt : (I)C
    //   523: if_icmpgt -> 585
    //   526: goto -> 533
    //   529: invokestatic a : (Ljava/lang/Throwable;)Ljava/lang/Throwable;
    //   532: athrow
    //   533: getstatic burp/Zmig.ZR : Ljava/lang/String;
    //   536: getstatic burp/Zgrz.ZX : Ljava/lang/Object;
    //   539: checkcast java/math/BigInteger
    //   542: invokevirtual intValue : ()I
    //   545: bipush #32
    //   547: irem
    //   548: invokestatic abs : (I)I
    //   551: invokevirtual charAt : (I)C
    //   554: getstatic burp/Zrb6.ZP : Ljava/lang/String;
    //   557: getstatic burp/Zsp9.ZV : Ljava/lang/Object;
    //   560: checkcast java/math/BigInteger
    //   563: invokevirtual intValue : ()I
    //   566: bipush #32
    //   568: irem
    //   569: invokestatic abs : (I)I
    //   572: invokevirtual charAt : (I)C
    //   575: if_icmple -> 593
    //   578: goto -> 585
    //   581: invokestatic a : (Ljava/lang/Throwable;)Ljava/lang/Throwable;
    //   584: athrow
    //   585: iconst_1
    //   586: goto -> 594
    //   589: invokestatic a : (Ljava/lang/Throwable;)Ljava/lang/Throwable;
    //   592: athrow
    //   593: iconst_0
    //   594: ireturn
    //   595: astore_3
    //   596: new java/lang/Exception
    //   599: dup
    //   600: aload_3
    //   601: invokevirtual getMessage : ()Ljava/lang/String;
    //   604: invokespecial <init> : (Ljava/lang/String;)V
    //   607: athrow
    // Exception table:
    //   from	to	target	type
    //   4	594	595	java/lang/Throwable
    //   40	86	89	java/lang/Throwable
    //   53	100	103	java/lang/Throwable
    //   149	163	163	java/lang/Throwable
    //   174	187	190	java/lang/Throwable
    //   179	202	205	java/lang/Throwable
    //   194	220	223	java/lang/Throwable
    //   209	250	253	java/lang/Throwable
    //   313	340	343	java/lang/Throwable
    //   330	361	364	java/lang/Throwable
    //   347	391	394	java/lang/Throwable
    //   368	402	402	java/lang/Throwable
    //   413	429	432	java/lang/Throwable
    //   436	526	529	java/lang/Throwable
    //   481	578	581	java/lang/Throwable
    //   533	589	589	java/lang/Throwable
  }
  
  static void ZV(Object[] paramArrayOfObject, Object paramObject) throws Throwable {}
  
  static {
    // Byte code:
    //   0: bipush #9
    //   2: anewarray java/lang/String
    //   5: astore #5
    //   7: iconst_0
    //   8: istore_3
    //   9: ldc 'Ø·+\2Sq'\\tÆÿÌÏq ü½⋡~ý­#8ä{ûÿ·6eê¥m^IÊöP\.®BrðD6°G(L!r»³DK\hÞí±+ÒXÓþò[ç° !)µÐRE¸\\nôôF^-ÛÏá>t_Ðþ`Kh®Qûøfêbkf×/{à½Üñ|mìj¿m@ê¨]*Ñ2=Sq9J(1§IîÏ©RµJ¤|ü7ÆÏØ>îÍT<O¦üûBºÈµ+æî\\néCV²ç\\\rH\\nÃú0½!É^ig_¬×[+û×ndëK"ç9ÀÌëIq(ÛÏUªí¥h¡o¸)Ëðÿ$JC:MÖt¿ñòÀ´grgkXÚ^£ÒÔCÝ:nÒú¸ç_~Õ"%ãðtñRÒÞ«tpðqÙHk¹ù·ËfIiûÛRÐ·(ïKh¿£åÒ*è"¥¡Q2\\fjCÃ2U ÿßWSq\\r¬É.tÉGoðç}ÒÜú-¿Ôâ&!;ló ³<k %)f\É´¬ÎØ/aHðÄ6¡Ê»ó¦°7=½O¨íg\Aºø§<ç/N1Ù\\txÅ\\b Þô>ÜÁß!Þ|Q­M\KþT;äoç=ÇðÈ{AEâ¶0×Ì5#«Wº,\\n_L*ÖÛþ Ö"9Â?Ìw]søÈ0EÜqªkOnFÞª/@º°Q9>x¯Ù¾¯ûå«°{/t4Ñ}<çÂgÁìåubVcöÃ¾õ¼¶¨cZÊäU§âÆÈÂÑ?Ñ¹ÑeÂa\\rü!÷:~KíÚ~ú½¢rCr2Í¢l7u¹°Uj,p±]êi8õH?ô·`ôñ¤ÙÇVSµÿ¸¹Ä\@¿Ro¥9e/ùò­V]\\fr] }ºRÌ K7YÄ¹ÞµÖìJÚaÊË§ÖO403Æ#ã©¼OXÿÿ/àX}[rôÈ§¥eºÈUß1.a¾® Åï\µÒ´M@+v<|ù-×klçz)Á\\nÜ^Î¥.ì´¹°¸ø´¦*JE>wx{àÆ¿¶¿\\fx1N¦ÇAÆE-YïñõsØ±«&=Ìm¦zÈ1J¤ñË]ûGf+øý|fá\\nC ÑMîsM±U¿Û©B\\t9âòÛû)K:ÀL,^æÒ\\bf?Ú~_N$kP­<êrü1nY×º5Elõwh+AòÛù¡¥xÍÝ^þªÛgÝHÿ+;ó*©ÊÖC³µÂ%ßÛÍ8FÚ]1ÈüjÆ4³ñ5E_ÌÀ^{`\\t^8«ýdÇ\\r§w\\r8þ5!øó2gy1U\\raEe4FJL¯÷H±}¸ÞhZèzFx`ZÙÝ®w8;?äUJ¾!~Ðw¼/L±ÈPg<'#¢>Y¯èUåzbÉ:öÉ_D~ÈË¡»¢}/,Ý§Èòr0#DÝ,ÃÉuQd#IDa¸Øn@_î1Æ\\tp4®gÙö?EòX=Ô&ã#M>k·5¹\\fþHÿRÏ±.Ç%>õ´KÏîL¤y{D£ð§ú\8~´Nn»OµZ>A,¼,[>\\bÜ1$,Y¢Jà>Æ'y·0T×\\nv¾ßÌ}/«Ñ³Þ¼9|±w1¦%"§DNºÆX~ûÊì@Kå&9ë<B÷ø\\bÊÚ@Þá 6ú6Âx­wô¹(«±CÞ°F_Ïx$Ùøm1-2nèªláåR¸²uJWZÍ¹\ø8Òkg¢xëÂM»÷)_ÓáX¿\\füÜgvf·&Òó~î (ÖÌìí2°(¦RÒö¸¿«9×°Z´Ë°ÿdqcÚzÁiÏþµáþÖÉ`´¨=nEx.ûÏ0|É#1äC|5ò>¶ÆÜ.üã<B\\fwÄÖÚí:¼\U]çøzB³w¹UîK®êÇüo?¶iºe"Ô7~bö/\\tºä×£ªÀBð<>ñÇD»¹Û\¡yoÄ'Çí©sß©LÌµàjæ[JI5¿"{6wòùC½BüÊF&X&MDûi¹§i<æzë¢v}-õ»Ý»µç"¿³ßê\\f!¡[uÅçÐÓ»Ð*N«zR!Uþzåb"0vÐ8pµP òóv¡¸é0¿Í ÿ^S¸Æ0iUkðTo³lB¡¯k¸%k¹,çý@RâIÖsKD<dôo²²ÖDÑû±@ûtØ¦£åÖ9×¾0E\\n+ÅVÛVtZQßÖ7jWª@õìYI\\n*®5ßK³Mó(æï=ÎE[mé4$>{ST:å©Ýb¬ÃvI!±LOî'Ä Ëêr_G\\b>õâÙ­e-¥TbOlÂ¨T®³ÜDóG@æ_qÝ_¨_¹ciPËßË i@êD»òbÚ(l:ø.Pî>ïçËS£þ#úæ+<ëXýå#R£$¢åÂ]v~D¾ÛIûN%-°q&l7Ð9Äb¯q­z ô(S§\\rÎF¾ÑãM\\tàOÝixÌzÇ²&É¯^ÇäØht¨3Ê×Ùµ¯',ô=ÖDð9¿Íÿ2É(ù;Ä)Ô¶³9¿ø.éö) £Å["¨'jGtY­`Á± Výu  J4!+:üy\\t3ãÑØº%^*HrÚaHü«^õb»¦d)©:)¾°rç7ýÑA´òªuá<¡ænÃt½?YÅs.\\b`nóõLy«ÃÓp_ôHÑÑ¾ âËü ýïñ¼íH@Ô`¸ë%$|Ë Ù;æV,¼©Ð®aÎ\\r]ì\\tn¸?SÄRC]ô¬ªªE\\nö¾\\rí³OtªåáßÔm?hÿ²ªáT¾ÔË= 9<Põô,úÍà\xùepÑ×hÍ\\f¨³×|"\¦èô<$¬|yº]þKeR~· ³@ÒÔóûk^iëÊÖzÝ9âºû£Í¬ _VÀu9hñîÁ\\b>Ã!zÑ)­´MWwÂï8ÎúWnv¶^«\\bwÓ\\tõÕúÖ8Go»¥ÁU¿«p;±²ÌdyÊþEQ(Ù´Û6·CÓÀåbßx-ÛLªçû×<Ã|@RÈAâp^ÅÙõM÷WÝ»"8\ÆêòhËõë£ÖSê=¼É[[:¤^\ô~-\\rcµo+ä+D°¬sBt?G©p0_Ðg#^é(ò¡í\\tÏåÇ¥¯´¤2Zyß`7Å»ÓÀÛq* ¥Ì±ÊÕ)ãh¦`÷ã½s1\\tæl&ìïÁïê=ÎÎÏöÙûM¤ DöIò¯[ú\\bÁA]&üküW%üttpJ[. ß(s,Ô¨¥«¯%xUvØ@}\aÝDñÀeeçS"Æú«ë\\t¾·y!&Åóa¡L¶ÅÝG"ÛXQ¶°zâùJpdÅôd¾9t¤Æ8Òâo)ò}ZÉ¨ÈåÕ{8ÈÝ8äsæ÷C(8Â~õîMÿQ@éÀø|[]xB»òÏÍhÈR\\\fõ:ò&p¦Ä.%¼ÂhÜ4â%ã^KnÒõdqLtÆ¬¾ÌÊ}îlá\­«|¾­åêÀF /ÀÐ÷.J#G$W- ê7T7\\rkúô´ìF,\\tÆôë£3a%¢^*àÿ\\nB.2m-dØþü1øà½Fî\\nR+Q8®\\rÞököò[ºè"&ä\Mà6Ìò 313×¨1×ÿª¢±R42á5ïëË8Æ[+Æó¢òp [( ÀÊõ3möÇ&uq{A':ÁÊÌ©«äDw:zfq¨ú*¾nUjC^?uø~£ß þWÂ ÄGªB&]ù$1t±}ÜU®ó¡(ÅWÜÒJ¯ÁhÇîR´ìgR^Kº,Ômt{´Ä|rÖÂ¬ÔtÕmcÊªüßÒ¯È¬îüNRB°ÄôpunjzK4dØ©¬9ºb¸.¤HsºaÛ²VaáÆÞE\=[¥?fK4nG»µåE®y¶\\fåM¿²õlî8²°¹¥âá\\t|¯ÿt¦¡èØEÏ6À<i@¯\\f¹gí½TÀj·×õÚ§ch?oèØÜÐ\\r&é|ÉðÎ½¦AþùHV"(mkRºuJjñzðG)}.èvÏ|©vqÓ¸e-x'%ÿ·~íM2)û×¹\\r?mÞj¸¼f}KbÔ ¨Ñ71^içM¼YÄØ¿±®¸S{°Õ¹ê»3§ÚA\\tKYßñ\\r 9¡(ßä¸/î\ñ|³<¥úípMW×üj¯w$eä L/êÂlS¶¡ð0µBÓA\)ÞVýô<4îjsÍq*ÈLô^åfÅmLã£ÄÈ_ª¸¡Ó´ëø&i´ §SØ3Úaj¸6ãä 2&®©T^ð"]Mkm³´hÕÓ\\bÀ2)A»½BR)}ø»¥ä¼F½Â¼ÚØ"e*ÜË\\fX¬/é&6Ñ¤q¿jJ¿|ÆMy\\f\h1ï{/±ñy¢0×ÖrñÆÔ8.­=høcÙeNñrK<ª+Ö9éû*ü`AGn5ö\\b ®Ôg*q,}ôîÍ¶\\bì@ÒÆîÉÜgÊîs¼¦ç·öÃ[ÅÄß+Ù>U?Ãí¡R6aSV6s¦£Çý oÂ{W\ûçs°Lx]ö0a²¶\\t¿§OÄn~±8äå}¤]öéã\\b,ìC¦¾ç«.ãÐNM"ÚÎ]2Õ­*¤¯p-tÏìð¶øgi"H< z:èIª³;uþoQíþÜYVø6¾ÑÀé2ðû¾ç?å;GEê[w®7\\tkÌ\\rM`ü¬ËºÅ6ì¶ÎÛ8®*º\\bqý\\t~w³!\\r{Þâ×<ì´«®²C¶yKÌzm¾ÛÖâu%åé-.ìÂÆsåf\\r&0P5¼=i3BØµÀÓbþ¼+ÎÛkâ³®8ä;3L¸cMàwËÏó¨ÿ@ua]Â-·°&-0Æ­Ýüå@íI\\fÌq$v²~Èù¨§³ÏËÞaýSZ´Ícî`U¾ZVùí(«â²V>©Â:GÈi»®NUpR³c­(ê­^g#ÍOÙ,R00(®³Mi®ÉE\\bQ±5_ß\\b\\fgáµà¦mEÊ¿ÚÛdÛÅ#P ¸§åî;ªéëñå\\nk1"µ!õÕê²åæjaL«µK1¶ÍÅÿÃC¾Ç¦eé91×§ppåÕRÄÞxyWIy*=j¡×Ð 4¶¡R/i\\f]¼¢gàU®\\fÃ¦ßÈ0ËV¤B\\fÎ4tí (Êêoº4X½ÞÓ±¬Öâ×Äü%*ý<£ýAúb´üx+ê)ÃÏ×bv_qÔõ\\rü¼¾ö¼LëO¸æ®rHÅWúÝ ßÎó¿<.¾é°oÈdA9gO\\bönÙ jôú»îÐ}ÄV®´_é}¦ÊÛ¹çÝúçÎæCÎèá¹\ð§8éq¯Ñ¸RJw\{m3\\bÔ4¹8¨ÇH¥~5X&SV\\t.ÝÐ8øÆç²:á"ðGúºæ{ç ØùÈþÂ¼ EîÉÁí°Â×cÂX·oizyè~ÑF¤­§¥Ê^;)½|·æ2öÆç¨ä²ºËÔºÛ>m]ja°ÀÞì%r(1Ø""¡¡ ­üüüÕAêù¡m¡\\r§zD)ºþ¢±yÃÊ}ü+£(ÏSC¿T¯ñÓÖºDJº5ûÃ©wÿä;JzßÌ*Ù¿UÆ"«ÃVT»¼øµ@YÅÚ¯´÷üÇñþÚ @\\b¿"þf+Z®M[Ò8QñVq`n¿5ÌÆKÂÍøýb'gõËjöõÆ>8>\\f$Ý"¢:¢^¾V¨íl'îå¾¿§þè>µ·Ò¨ÙÿgÞúÄòµQû¯XðÚU¢oiÀ3 ¡qÆñU>´!çæÅ(41øgÍ»úìõN¯ õ&ø¶P§wè(èÓ"éeEÚûk3Þï(?ÓÒ%7tw67=áoíéa`\\f\\b×¢îÜcªJ1§vu²y8Q7ú3,ãî½¤Ööý#]ý;¢ÇÒs1ó.Bu÷äWòlÖ Lµ³u¦ttHÞó 'Ð§$]¹xé%ÅÉjÀ¨"¬BÆ¦XòV'4Ãq *Âåû¬T³QPÛdêîFJÖªÛ³àwÉdô\\n($rÊ£IÝÍI=LÃöë;VVç üóÿlËWß]"Âi)»KñËÛ?KÙ\\bcRDÜôJ]1TWø9Gv¢þÀ¤Òç¤1øéR\\tîöjÚÏÏ`Ë\\b&-AGýh\\të ».Ø_"f&{¸®Ãµã¼§bbü;&T°uýð¨òB(OêÌ¬=}rÎï­5YZn ¬\\fóþ2'þ\FX}ÄÑzîf´m»ah|6^aZr*ù¾Ek#7å£«ý;ì°Z7a2$þÅÛ «©¹'®{þÁùsF"nûGJ\\fêa¬y¥'¡bÒçVßQ¡±ÄLÞì <uü\\fëÎÈWïÔ¦ÐÙ¨¸¤yèÙÒÚB+×`\\t¼´OuY_rnFpi¡8[¢x:þä»©ÆSâÐ3îX7Þ²¾í_j¤xiµá5Üg4mÅYcdÝw¢T¯í«J×)ÆêQÂ­À>ì\\thdÙkÃ·ê¨ê+k³cÝúé¯CÜ$¿?­zóþÖ^ýô­~)îy)A¡%ûHpÉ8r×M7s½NKÈÙ¬8\\r¾î¶ ,IjÝÑI5¡|!mt.ìø AnN9ög\\n·{m~)T¶T`V«¡C¥M~ð5Çv|Ëñ ï¨OTÂ¨þ1TXDBì ã|8\\n#Fâ§Yæ©l¿ü*uÜ\\bèÚå)Òä¹ö=Â!¿ÛIU-TTBð°dÙv'¡ØÞÜ¿É5E_Cåÿ;íçNÒ!ïÊ­¯fÿ­w3·ÎCÙÂ¦§zý¢&¢Gäf¡õ-ÅÅ´éÔg@Ý`N«\\b_é\\rõÅ[·U}wþÅ-×úÝ4bdÁ<òÐç~ÄÖl`0Å`Ê$QgPµ_TÜ$·FXÜ\\n&~ú¥P^åñK!\\n4ZÊ0Ü¤ò¬6[Gqó¾<<ãÂ¾a`Ã$Y4HäQfª¶­Õñà$s½íB9@£ß§qMÎ¤©Çóû}zÞt9YH¬åÇü2Õ:yÑ`(H¼Xíí[<Élýþ"ùqÞg;\\nµ·^üïãÖ®?nÁÒûg¸ÕJ6J¦XÊrî*OÂçMGÎ\\r×Ê1VnFäV ØÔÏòA­X4óþü^fùS|ÖÎ åLeæÕfB\\rw\\rÅè+WIÐòñ+m1ÉP´0uLÀ>¢ío;oê¡;4ic-áïë?ÕÙ| Læ*ÂÕ*É¯\/¯w7§hx7qgõiY\\twË`{f»ÍE¹¢Òÿøfð´Èd0kõå=­'5¦PH±7ª§4MÆ§svÃÖQ6Gë¯p¦ZÕøæEÒÔ°·0U$\\bh¯¡¼ó_4ÙzÄkP¦ÛUóõ>e_{9Mä<@mD!³¹ç\\bX"í4VPb»æÌoß´p(Ôì}¡Ò¶^°0°ôMö»lvóÉégÑs)@ÄÃÝ°=Ä«5[÷¦Å÷Î>>MWÍS:4ßÝrÞÛxò\\r¨\\tÃ~«­â× ÐX*HÂ«höê\²1+\\feLæñØ¾«¿îïáÜ®nÞn=-U0&°­áÌ²n1ÿ}IO;ð£ô>BønST8]ñ2ù.®á¯Åõ©ðt?ÀµÕÒD"ßÇ/¡`|ó<JäÔ©eÙ&u¥D¿ÇðÇè°òÁsè§¢2d%ZÖj>/}¡òÜ³ ãeQ¯ÀÁ·£^\\fÐ@R­ôþ&×ÙÅ©ªÇeñ·a!ùÀr¾È±äU×m¼\\rU ñëÇÝ¼ ìÄÔW; ÁU`çæâ $g×¶µo¸yf½á²K\õ®¶Kñ\\rvcMñDÉ6¨`9°0JW0ôóæ;\\t¿Ao§¸è©z~¹ÆÚÊ-6kß\\nÊå¾e<#ÚÏåTYòb ?Qì[)DÂ2±ØÌPtV={K|l.[¢6ðëw{Ú¯B# #\\fñ@ycò0[W°WÛ fÕ\\r\\f;e¶«\\fbg´Þ¾ß][|wv;:+y.É}ÉE½8ß±ÓÃíÃe4è]UgJÈËÔí£¼þÅÇB\\b±$Ôß\\t5¬%ûDeAÕAËPÓ©DZ8@HµÓsÜV"Íl-ï|JõùÅæ0K#>^'vIXÌgÒðA~e7<"2pÖç @;×æA'gÚJ#Õl²è&bØüzÒÄ¼yMZ÷Ìþ.¡Xãê(¸|ÑþaPsºº?F¤*;Ö/ÿÙ§»8·5*y¿¯=.¬Jr[]9¤ûÛ]|¼\\t½AW}-Sÿ[ëw0;Ä!³õÄõ0=!ìU×®p%\\nCÞBW\\r.ÛrXt\\nÈh|¼¡wªÍf\\t¢OcÀÏBä4_þ=\\bÝÑ½Ðùt»MOQ*è<­-*hþSßBÂ [Ox¸â[ññd$¸¢±?àvw¥Î0xÊòK±º\\r29oï<b'Ã]; )³øÙ#'>HØ(£êÇÙæ4hÆø^OÜÔÛ?\\f=b¨èRwØ\\tµ«©ô÷¬)YT®×O"Ð©,Õ\\thåä##îV;m"4¨ÈN´2ñÊ:nÄÏaýJÓÄ3«vÁ×IWCòmâUâ,ÙñÎ¶)=RX[KN4Î­\\f½ã"\\ri¹*JK>ªGkeCÝ6Ã}xvâÁVì²Pä®t¾êDè8yÙI9%NîüÕÃ\\fûñ;è­¿\\tsMgbhÙÛÕ}âæo|×Ã¼ÂÍf²nY\\t/}-£¥=\\nöfÁ¯D¸»ÏNµè´|m¼Em¿4µVÏî%°£ó,8É\\nÂ"êùÑYöð×J!ZÝçïÑ¨ÏWÆÙò¹?à² ¾cÂKJ/MPü¿<¦XQ\_Ûî$¸\\râÄ%:ÄôÇuÒ¶äéÆ\\f}Có8Ïlë°«ôÐM(óMd@b¿{ÏünRTmøúðþç}ô`>ÁÀ!%#û°7l"ÞÅõþdrÜ\\fYÑt¨}Ñà²ßynò@´Cýe\\fmSnl,ÎOMK²Ì©Ð»kýí½LH1haÔÑ[Â¶Kb¨¬®LñdíMfÊn×7&pôêÈ²ç­¯CLÌ?ðÆCè?ãÎÊòPW|·êkJm"³ÑÄCÕb©&*)õÑgå2ã'®p)¾20l%9Çf«6Áïuõ¥;yPk{cT<Ó(>z Óóël õu1À<B¶¨mlçK:5M§=\\rßï;îË{)âf³Y*éñá åÜ\\t\\n9O#-¿²ö7´Ä¬CÄ#Â;Ð²]L´¼C×b1v$Ý£MÀJF/>f#aÞ{¡ï\\taóÞÖ\\bò7Mô`®Ëh*>§é#A[oAnI7QÎ¥IÑ¾ªK:[èp"¦z16ã§ÉÒÛÌÞNì-)^Ò¸¹:iù_Û)ë\\rÓêhÇ¬wXÀ¶\"SÜ¨ï!/5nØ¼÷âÄnÕjwíå;JjûÂkÀÊuÚQmB8©¹Ò7NÇçÔ«Só,­¥úÞ4:xXA\\rZÉýÖ¾m¨¨ru,\·º¾ß´ï¦ë³IÓ£¦ÚáBXfÐ!å^ûliîq¶\\báSÅ{k»¼ÞÇ\\bx±êºó=cD¿Ñ,´®ô\\r°?ü¿õ{©Pá²©Ó ·Ër!£=µúâMÔDÜ·÷Ag®6H0ÇujROij&Ù5JÀãúC Î÷aü^µY®ú7Ï\\f¬ãmrÍç¯U¤b×u2ÏQâoO=\\tS9ÝSÒHrä*ò\\r\\tköq\\fVÊ(\\bÑg¿>EZÁKì_5s}\\rþ&[¿è7}û¼ú67ûx®ãðvò6KÚrÁOCî\çÂÂËX¢ÑpWµ Ë~P0mØXøH²ôCPØúÓ|WÃrN»§ðÌwi\\n^ÜnÔ¨F6Q±5ÖuðdÕtåO>ÚIBe&ñ,§4tÑYHaÈIð+±Ó\\fÖÃÒö<X¡(ª6d¤£M¼µ)fÃb5»hi:U<yµqëF>Qye;!ri+ãósdÃøÈªâý]fhZßË)vÝÙ{¦u4ò©Ý`±Ì2)à`@ØÅ1ó0 ©YOçØNq¼ª4J9ÉçsXÆÓ0ôwhê$\\nÉyë¿à+[7þ%ÌD\\n7eâZµ!µ9_¶wÂXAô§ñü¾¦r\\rz®ü2Ðü5ÊDs]Ó³¿ fûµá\\t@dÖå½DS½ÕîuÂóuçÑyQF\\bQ[<ImÇ5LE\\tQsüïkµ%×®^Ò\\r¥*ÓXØ(¸¡áÄdNý+ÂÌ{Ö¿:6ýT*R­x`¯í&©7ð)ðtEÕ\ô=]8ôÝ\rüN·7%+R(¦ØhKéCÎ§cte|÷¼©ëXQÍ¦Ç"/O°@ë¶ìiSåÀ\\t¯%Ê²xÒ}ZO8ÓhÂø"3vÓi×<ò<äo\\n*Î =êDÆ9·Î¼`v­ ¹>vEdóÉÙ2÷¥­ë¿1Ù\\b®ª *°\\t«RazÄ§w5 ::wâÅàÃ·öMgf[.¼`?ý<µp¸b?;\\torù~×'egt'
    //   11: dup
    //   12: astore_2
    //   13: invokevirtual length : ()I
    //   16: istore #4
    //   18: bipush #9
    //   20: istore_1
    //   21: iconst_m1
    //   22: istore_0
    //   23: bipush #109
    //   25: iinc #0, 1
    //   28: aload_2
    //   29: iload_0
    //   30: dup
    //   31: iload_1
    //   32: iadd
    //   33: invokevirtual substring : (II)Ljava/lang/String;
    //   36: iconst_m1
    //   37: goto -> 203
    //   40: aload #5
    //   42: swap
    //   43: iload_3
    //   44: iinc #3, 1
    //   47: swap
    //   48: aastore
    //   49: iload_0
    //   50: iload_1
    //   51: iadd
    //   52: dup
    //   53: istore_0
    //   54: iload #4
    //   56: if_icmpge -> 68
    //   59: aload_2
    //   60: iload_0
    //   61: invokevirtual charAt : (I)C
    //   64: istore_1
    //   65: goto -> 23
    //   68: ldc 'øg\\rh%á1'
    //   70: dup
    //   71: astore_2
    //   72: invokevirtual length : ()I
    //   75: istore #4
    //   77: bipush #9
    //   79: istore_1
    //   80: iconst_m1
    //   81: istore_0
    //   82: bipush #13
    //   84: iinc #0, 1
    //   87: aload_2
    //   88: iload_0
    //   89: dup
    //   90: iload_1
    //   91: iadd
    //   92: invokevirtual substring : (II)Ljava/lang/String;
    //   95: iconst_0
    //   96: goto -> 203
    //   99: aload #5
    //   101: swap
    //   102: iload_3
    //   103: iinc #3, 1
    //   106: swap
    //   107: aastore
    //   108: iload_0
    //   109: iload_1
    //   110: iadd
    //   111: dup
    //   112: istore_0
    //   113: iload #4
    //   115: if_icmpge -> 127
    //   118: aload_2
    //   119: iload_0
    //   120: invokevirtual charAt : (I)C
    //   123: istore_1
    //   124: goto -> 82
    //   127: ldc '^ò%Á~M=¾fÓs8Ë\\b°Ã&]¢Ôþ¹H²BÄÜåçòUuB(¸\\rýhCß\\r.PÁZö°u´+²¹ýP¼üm±Ö­q\Í°}þ±{)úZèÀzmè§"pÐº¡{IsX&8×¦ÆâäÙôª2K!´·Õ*¸Ó)óÆ5­Ó²Øzÿ)iöÿCÿ\#øUÜÅógU\\r§õ"4Ù3ÂX]«ÈTsOQ&û8ð«q (9â\\tåü³ÜûxOËtì×ÎÇx;a4ÿÏ²$K-æßb¿òwáù\\b\\nÍ)óûd4Ýb²"üoÿñviI  ÂíÀÜÍN@×c8£"xNÚ\\fhi£Ñ3¦¾G:%Ïyù$²6(ã8_bªy{ÌX(/éÄú1ã¡íÖÜB÷tmXf}±þ.`­Õkt¸&ZºJûÇHKuUÄÏè®î eC*Oô9Á¹^Úä®îr\\fs´üM,b{(?{¨añ\2*\\n9\\feMÒ+É?íouê+lÐjëý¯ËNI/æÓ2N©ÊfÜä\\bF %÷l(ÅkU¹UÏF¸°X°õWÉ¾wZ~ÌyOÆ9¡ëïX÷â)ùÖ]åù³3bË¢¶Tì¶qZ¾r3pÂ2\\rPCÇa8%hcc÷åYÜúØdMprât1"êðËø·r-îHñËr¬?YÏíÔ7ÈIhRbè;gØ)ÇboèÙÿãm$Iq¾Å±8}t×!KÄZ¨H8ó·û ýßrïüDìyG°£é³ä§Ï"äºK½ÜÞìÇ\\t¿GÆµP«V· _/6F¥$~½ß)Ç¿+ª>Â¡6 å"qwujý°UàUUfJê(11Ò"ø"M/Q,^\\t¼MC~w£h;\\nV: Î\\tÿÂE¬¬Éê9yRæO'¨©cÚÔL/Ù=ãH(@\\bª&Ãß#T{ÓWWa52 ^ñW4fR÷ð1§.×»7­¶¾CñG&*×7W´ÝI¡%1o_ÃØ`Æª^¿­\\nXÙÒÎK§«9ð¶2L210ÉVDWaF¥C@ñó¡ÏÅ~|D°¡IIS¡àrÎl¨Çã¨Q¨Êøíêo8!¤\%6L4ËÅì;ôÏ¾>³hen½)éªåSÜ´8 Â1^\\fE«d§1@ü>K4´Z+2¤Òì0âÀÛZ#ÅÍ]Ñq\\t!C[11¬)\:èêÁ8³ÉÎÒþ_6Dµi}OÕ[ÒJ¬8)£¨Ü(á{qaOqXd¦HV4Õ3P²=µ¢;w%pÁóY¦cëýêßî¯û<xzÐF±ÛgçñÓË;­uX¯;f©ËÊEvÊÒ1®£¶¿BÆö³4H§ú{Qk0ð)Â¨8ñ³²óuí¥_DH¼_x6>×(§_Äú3¾z2DéP[D²ÙéÌÎ¥¥f+Ð)ÛýHd^rqsbà®BBWþ\M÷eÂmÝÁç\\tnä³ªaäì0 Z>B©Æ8¥mêûº)N£pTÀBÍO~¡U7x^çòE³o\\ráE9ÞBBÕÉ8é!Å\\rK6;Ì¡°÷M@ïPÏ­â1å¦ïÙ#ðøáÆ¤°k-dn!óõNÁd>\\nGÚ ÉÀÊR#ôå+üÛ®»ÙüW'þßÔ.ze¿ë©Gkk3ÚÑ%½I4®A[~ê@º$ä_KÏ©HÙLB=à®¤Úîî5hÄ:üé®ß¢,*l p|ªoê-ÂðZx\íìXlw³7îTÑÑsªó{xE½[vÂDDAW\\níéJ]Ïêeb¢ßº'´Û¸\\rDanp:Ù6bD1Ð¦ÕñE!+X«ý_ _³ÿ©ËiZºÒ¶öôÑ"Yÿ«~ãÅùwk>+ÓØò,'*\\n­zè¡h8L3Ø)@PµÃcñö÷ÓHú qHZ#¶:àL.Mdd<7¶¸é2J3 GMòKïÉËÓSÇÒ£þz[ØWc§Q$Ä|ÈFýÇÞÚïóÛÞpO¹¶Ë\\bl#R©;-²{ãHººÎô·s?Öá §\\tÊ¼ÝÅÙ{>æ¨øgCL½¶C]ÿ#\\r¼ýÂ?rÅèTçÖn>Í}*h"\\f6°s ÉÕ&YÔ$¥ä0sSØ|°4Í?<ýæ RÉãFÈÑv8;yçsöq¥õ'@áðî1s¨²i³¸ýcÁãÝlÞäÐÖìÚÌ4¨ãÎÎ·`ÄXq³ÊÕæRS÷É5Å¤tðjl/\\f4f§WÐ»Î5ÅÿçÆÕ`åØ2b¨\\bÈj\\f©Ìv®¦×%D-ÿo³½BÃRRx¿<BS7Ü-jt¬â\\nu|?>Â$aMÞât¿P×lÍoºDÒ}Ou]/\zp?¸SÙ{Ææê¨50O¡ýVÑ¯\\b¬)@ÎÅÈ\ 4V\\t×¼$q·ìÆ1\Lw\\fäº'[©ÖVÈù U52¥,y¦KEøæeÝºkQH©GJ?«ôâ®,ØdºÎ¶ËoþÖ9tÑÕr\\t1uè¯¤èÌ¢Èðk\\bÚ(GÅ¤[ÂÇÞ{tn§/«B\í0Ôâàm¢úá¤ü;¡¶ûtñigDCÂ¾Ý±õG6pÉþTº=ßq³¡A£IÚd#«Âþ%\\tr²lç;í¼õïÅøÏWéêÐËvòRÜÔ]äh4©Ig×ø\\tIµ/ëvBüOÖìé¥åÒÎíår«üJZðWU¢ÝZ×A@ä¯ÁYw´bÈU_2º ÿL±Wã2tÔ9<\ãP)ÂFìVæùÃýÇàZÌI1¤Ós©o.°ùm#'òúÙ()Å«&s³÷/¹ÈsèwÂ¯¢¶o¾s"_ûÒ¥éÀ¤PÈ3y®8Öt-*.áL,ô¿Óµ÷ðR©*Ãzû©uc'´û7`½êû"ÆÂ±ÇQ{mþ-¼]]é-ÿ\\bhØÒÞ¡Ë(r\\t©¾íáXNê@Kd|øª-`"ôtºÿ4-ØA¬õþ¢·ì\\nH° QtG²Þ»ðUj9Åm°Ó à¼jíÌ¯î2ÎÆ9xX4äÛõÂÔünuÍ'qxèÉ{Còe×qm,îN;ÞÄx¤cO|BÏÝ'âlsõm>7D:%É/±Í4*º Å330ï@d*aýú>£AÛ.þÊÚzÀî¸Á&PCfë¡å \\rjF}RæTÒ(|á&vE¤ÍÀÒê;\\fP$Àg\\t)®m<ìÁìù-³xÆË:yPExæí4=HþøiµÜ[¦úp<RLÚ¼byjÿÖ÷+mÊ±NÚµ®=­,×YE!bò£ðM¨»æ³gº]Áºj²Úh¼¼¬\\f\\r¼mèïdd<Qñ>\\r'3P3èdâxÔ\\b© \\rR±MË=àÃrÆx[oH÷e¬5Óeq²Ó±¹C¹lâwÁ&Ñ!<?÷'õ·Æ4ö5Z¨ÀTÍòî$¯b´R!ñÛôyk¢]J DÈïÇ[#)\\r0,#Ýi½\\t!\\bi p«Ïí\\ræú2:¤C(,vG\\rÇ$¾ÒóVRÔ;xðí»RïÇ¹ or Ï½Hª[·ü>zvôZvà­9H´£ÒøTpÜåf¯ÛÃAöýÂqÔÁ(%Ôë\¼<ø~÷Ü}h$þî2©Ê,\\t}\\nYã£y¡C\\r:Z/þW+\ògªÉ%Lg"ÖnÑÂàºZàÚ!Ðc'û½Ô8¸õ¶\\fãX-¨QOqf.(»37B×s£ñÜz¯­×TÔÃUÖ-+XueN'¼81Îa¾r×+HØ9jÀ7Ñ×}ÛU«¨6%ÁaJBuÿÑÖã¿é© =Ò WïÏF xº÷£{k±$t)F]×qo¡~=®Y[kØÐÞ8ë[ÈÖú\\tÍeíùa)ÔvåÔ´«CzÍ#cD!Dý5=,Ë ò×Gh?\\rQÁ\\n¥¢ò\\tµf±õ©Í×ÜPZ=Ý Ç<X`5{4è»£cW°s¹Æsmýiçc´ÍÁð~øÑ"¥f³àz9Æzùë¯k´újh6ìðÀ¥\\fæÖ§¾¼ýH=2xìz½#MçÀHë:z û[çºóyxäJÂNGáCÆåëx©;©>.2ÕÂ4ÜÜÃùeRÁ{á´ý°ï¯Ñ»À2 ªgµ¢Ý&A\\bHÆpx¡dñ0²yZ`Oý¸@µH±ów`áH®Ò=ÛÍB^|fm(HÆ\\f=âN\\nÑÓÚâuüØO:u<ÕðB¥zR½¼ºsã4¯½ª<ÕJÔÚÿJûuF´ñýy¹cÚwYl.ý®áªqLqæU0i<E~QeËlMnÍ:Õ?:R»©~)-ÝÊ%E3^Ö°¾Ø@R/\\t«§O\i;?pMSOé\\rÎè@EcùªuÀ¨oúðÑDj¸$pæÎj°íAËò!@«Ô\\fhýÅÁ"KLB"ÍÛ,ÔÍÀÉú¿b&ôäsË½ÖíÍ´B?Öåì!{éâ¨¿P°´ÿ¤ÄÈ ×ÎòØXÐ4hEì«xÎ;ýAJyªJá÷ºëÄZGÐ®F!Ô(Õß´Nóª$@^zhþ»K,RmÖtD/øöbµA¾NRL°Ô+kÌ+õ± ÁÏß´v¡1ÿKghðR½%aèÄ÷ÏVã¦çâe-kd4½{ô±Ç1|æi:Î ÄwUÔ¹é G\\n.\\f`Çì\\fâíÛºUÃIº£D0`Iq·Ê;wÇ»®Pû§ßîxVàOèÍRÁìÄ\\fmµÉÌt¡mÉT³t{¿~\\râdw¿¬aÒù0gëÛÿàb¯0£~ü'e|82÷BñGàÔ÷=Êp} Ð0»ajp²Â}ÑçphÈ¼´uU {´5&å2ÌÑ%IÐ­*ñ\\r6ÞûçTþÉ\\r¨Òyö\\r);¤Ôä85¸Íï½»VA¿è§úg=}íå¯+fkès^± V·ÅøMÔ-±P¬¡È\\r¨.(Í_ÓpQbêN#a½cEÖu¸r:a©uäB¨[x3£ø?àQ¼âp\\n¨Ð¾Í]¥ïú Pi9ÈAÙñµ.;½Dâ8\\b=Ò[®#þ¿Áë[fSiØd;t1ÉÍllýyáâï#¬¢ÛÚCOú9D\\bdìn¬AlùZäùK\\t\\bÙwT\\\n-pØYCäi\\n±( Åh/;:¼èß#ò\\nG)¿Ó_­ïä­£6ÜõU>¡§ãöôàDpmå½«1ô½W~B"Â »ôY)HrQ;O5[wÊßøË`\\t^×¼/ ¸·¸.Åþ-p<PgTÅpxÌau²7¯udÛÃÓJºüÅXÅ\\n«Öhò¹ ËÔõþì'Õws3\\ttQÕÒZ~ä½èâö4Q%3J,SKã ¬\\r£þ_1<X\\n5\\bÊ\\bjqÈÛOÇË%Ójía;DQ-G?mû§Üþ5] £×ãü"Õç:ÃÝL|üÞÎ#Q³Î¨t0÷h¤6uid®5^!*uÃMËã²/"¾Å¶Ú!ÞI·»xúÚ»¡Ocº]I/øj/DÇV·q(>ë! )}ª]o £ZÑ0oÄÔU~Ot`\mßÈ­üã69°·òöDPu@Ù³ÿ<Êd[yþ¯ÆðOöN¹ÿnqe5È[ðe´wÈ:F`òÌå®YJqCDëÏ{nd}t)\\rÉë|RßµµÀÚ¬£f]p=fÕð¼Ù%9¨íEQ('BwöfÄw>8B¯*Ï£ðª½[ûØ&ïª°ºp,r2ô)AÍ×g9¯OÓ ât/ÖÿB UìG·T4* §íÊ#hîvÞ{ TÔ äb}aúÎ>¦M¼ï¯F¦¬:HÉ!ê\\b &ÀÚþS·¨ï;1LNÏ` _vø\\f9ÏÅîºSµ0ÂÏÿ\idôúÙîl;êÔ¬mï\\biÍ=;<ísñaÂÒæãË#§\\fµpOó÷IûãA+TZò*O#â03P`âE2j\\tèð£ÿ¬Xv\\føÃ¹µ6÷«F§Qtsy%¿büÅüÅy`KÖC-ðYöO¢5©ï¦®Qí±RÆç,SG{ô² íp÷<ës4Å jq\\tþ®ã'©ìjGýðTZ²Ë?'4Ö\\nØ+ê*MÛF)\\n®»´³tNõtã÷AöÃhSà«VJAüI£Æºù,Á$[y®oê£\\fûq¦l\\roâ×qFö'L*ð9ÓÚË_;¡¥»ËÕ2Ád°=PÁq=:ÕE±7Pçû%µ/t\\tÂÒÉv£ºû ëêõÌ\\fdÚòÈ\\fL#}å1ofÏå¦Á®°>Â BÖ§×GBwéR&+c°þµ§I\\bë¼6´ç¨Å+ÞE3A÷yàqÚLeù×auqòB3<Å±}lÆ JTP?a H¹½í.¼pJÒôáÛÍó0,ÚëÒÙ2>ï"ÜüyÆUÏs8§®.°N½ë9 ×À~ä Z\\fÂm",Âs)æÜßGTÕ^Y%±®I7Û]ÎïÊñ\äfÞ¾þ4.æ¯b k¿ÓðodF8\\nñ´Bý¥&Ì"ï!1g\\tJ%Zí {ÊH7×\\rK\\fHr@Ô|´×Jw)\\n4ê÷]{ü'¢RºÀO­p½ <Ù¶*94·PõL%È:Á>Ý¹øïy³ö'aß^Ôý£-8´ù\\n\\fcQÿ&&ùSý?ôÖàq»ÓC·õ÷s}¬Gñ¸Ü[±Ò@ÂM\\fÊÅ6ZRªÚe´þôâ:GWfµ[_c¾ëºF\\nyva«§Ý¡øD¢* g;UáUÜ0ªqG³Îèh1\\bA5þÄXÊ²aJEA*a_[pwV·Ç\©/q(¦w£\\tÍ¯@3°/m·§÷AåCÿÆ[¦år_È¦$ód!\\nÈþØ®¤5\Á] ðØ§z¥{ÅÍØk÷ÒL]¯1Bëºvª=ÌiN¬/G\\t0³P¡y½v_(íÐàVØå%µÙ¾(×§½ ´^^z!Ó³¤ÀÓëLÂéf¥sªÞPã²~?¯2¶ÿç°zà×VæÀÓÚúë²;ü4|ávqÄMÜFv©\\nÓØÜ\\fËu71³6P¢%æ¤ä^À4 ¼\\fÞ©µÂ@Þ/ÁëQª1Ù´Ç;V9>kÎ?Àg.â©ôkLj¬`±AÝîày~ê|*âø(ÿÀgù7¾àn­éÍçNIFKmG_Ð£à¿<ÅsWË+aû£¯,µçVÏû?>Æ¸mÙV£Â£/¨!ò:Ü}üxV/?´4¤míï(ðo0ð=ËU@ñlCàë~ÛÓ|Ì¤ËCÿ!e) ßÄ¿ÖCÙEÕ¨üÈv³-ÐÈ52³¢@öÐ89¥3\\t¹omTÜÒµ\\fMúOïý.«¶Í`éiÛí\\b¦4Iw½ËuÃ|\\b/<2Í=9ëþ¼¶­ ÔÜäRà'Û÷(q)RXÌô©1º\\tî¼-­Ë\\reÖ&5Â]¹É°AyÌßÿjÈ8¤¢J=-jlºVPs°ñ*(nüï«PC3Trä?@Vo§ª:ã|¢F¹îòYª¼yÌ[øL=°ã¯ë§£ßøèÅ#¢J\\n9·)¶xÂ$ÖH$\\fc½~^¸ÿ|ÒS.4ó`'QYV^ùhêÄÝN¤Ô²HÆu}{p\\n\|ÖÂóí¸Ü×üãoaátSTÖÖE_öEsfoK)×RÚz£LÉcYÉÇ÷Õ@¢sº3+NÏGZoÔoMX!ev  wÌ~(õ}»)À!=áR3=±\\roxFüh}¨MÒ%%8û×9iKf\\rkÏlêÉG'I&øø5Ñp\áDðwÆ:àäÅYlï\\t¥b.ò|âm°$åðP:)IOêå,nCÇú(\\rûrÔ{ÿÕ-Õ£WgE&Æ+\\b_³jþ5g]©ù)óö%µc· »ÉsÁ_ìôÈµ4Ý`fª.Sÿ¾FaûçQáqF§C·ó³ÿ¨Ï^yùPB]Y3Ctâ¡ªTsë]y,8aÖ{D^~ô/â>­Ì,×6Ô@"\\bà·KRßµõXpeï×f2UQ:!ðÖFáÊc3_\\bbß;ÜÖs¯X" jô{¶^3hàÈ¦êëÈîP¾5©PD*ÝZ×{ù©S#²%ìÒ+îÂômã-}TqGÛÙhýøÀ©ðÝ¨¼©Á­{n¢0¡Ø\\fR5Ûî×ÊÑká9(9'½Yâ\\b;gY«\\bzD|jIG&ßó6-'í¬ÄÉã+ ©â,q6ÀÐPd÷ÛÚ#ßèèõPÉNä´1u²Y{¾½ÄÜ=ÇI¢)]° :RàWOjé[_ÒU¨Fch¡þô,­ffíHfÕ {ZxD<R\\t¾¡ìVFÉ³}ê!¤S¢\\f03=íe¸®/àOôÙ&ü·jEÎ[ÝkL°°»Q¹¼ÀY)í£ÌíâLH\\t\\r-¢jÜÝQÌÓ&ß ®õ³EÖã;jxý^Ljéº=àã%5L¦íÆ°A«67»êõ-výA u¯ §óRÇ>èçýì½Ôál=ÃÅp¶ß+ØT4ÓPæo*ÒÃD±8ú,Ñ3¹o\\rL&lÜxÜX>XíQ £×£"\\t¡L|ÂYGûHv0ÄÜJ½yÍ+ÓN\\rÄ>å?mË¨ õY­=VÒíQ^V:\\ö^[W×YesÏãõiê ô×<¹ßÙHÀJKö3I(Ú(æ?\\tñô"²¯zÃ=ùA­Ä:0&¥^R¤ tKÒEG\\fÃ³ûM~ueÛ$9²coÿ*mb¨®)`]¼È#;Ü>L}wNi:¸p3ì?!FÖÛîÎK:¾LÉi¶Apõú_ã^ð¹Kv^ÙÉäåª%b%N!Co%uÿGÃ¼ÔòÞÀËµb'É$ÛAºPP4$s¢¯ÂÈsSs¯T²fxJëidXVBôÅ\\\r¬c{`xÃS9Å,!â`Ï2WIÝ\\nýåªs+«^¢í\\rÚYßïðûE!Ê}äïB@]¤lfÐ©§vÿMÃÂ@0¢iÈfé0ÈÜã>ZÎo§Ñ<"¥ @TèQ(0v¯8øÐ<CEþ|RPÔ8L>[çE(»Eç"Löÿrî¿Eð"íC»ù:övhZÿ#¢bpaò÷9Û+fs#q±¾±\\f]uhZÚ3(4\\nñ#©µ3Æ8Y&6\\nìÅÅfW<nXÜ©8§4°«'¨"¹;Ð>³³P³qdô]oåG¾Ci*kt{¸ºNÊ2\\r\\bßüebÏE;\û~7&fh©0¶iØý[ÛNKíwÍ\\tKg4ôAzÅoD ¶"&¤>úE(~GàK51T.ýÐÞ QÐ(%ß7£³SU\zÛ!¸7³QÁiï{!«C±? </cdÆY¨ ö:=µ\\r¶½­ò,îçÊÐ9¾³³¶7'VæcAbz]$eØ>Fkúpýèì¥ÓÆlºÆ¸­M¡\\tTnC*¼Å/âEàFèÖµY¨WÐ[°2\\r!¡iäDmÛïMVÈ×TÀ\\f[_qfµÔÈfÖma)E;ËsÛÜ~æØ\\fú C*ô¥ßSXp½Ïeø\\nDï\\t òöP«8%[3í0\\ræÅóKzm¹¥3õ5YÐCiìê^øÏ\\nâúÕÏðá,½ÞÞß$LS"ÒècmáZz²ûX8\\t0G=,ÖNÇÛ)úLnX7:çb¡TR¬ÈÏÿ\\r)¬ä\\f´btU05ÒÉ×2â¦Ní\\nÉ?àìUÿ;§Í0<²Ñá¨âÕ>\3ÝÅdÊdGûR)¬6þ°±²¹¤+ðuõÔÎÏ*Ïúo×gIºôê2¥xDÔVðÚ«ÞHq©({(ÕkHZxàÙ±êl{ªùA õ­ó ïðöð¿¹6Üt\\rïHJÎ°Ì5î}£CÎéÄ§]üâYï\\bö?vÓ¡Ý%a8a _±ll0F"þè\\bÓ Ùìû:s\ó+K\\n9ÆõàS\\t¢Òzo@éÅÅAÕªËü[à??ÐáµaüLÕ¼]ÁÛ.Þdk=FQ×Å¿|ÑoÿêQ©GGöÁÆ4 Ñ±]à8¨Ö\\bÐðú9`<é-:×>ã\\t*öÎléÞÀå­6ÏÇGW}+ \\nõlóßñ>78Ø#E~NF®í\\tÒ³\\rly%6%us¨%Oc0ÀÌPËB¶×|yC:CWý^q~å£ÏÂnªÂ_Ñzy}¤½J[Ñªsli@Èÿ­TöÕâc!Î©6Í¬þØ¥sN|´¡Jò%(TTi+Þ\\rcÞaêÊ¼\\tvi2hÙ+J$ö&&QÇjy7ÐÚF5Ä\\b±yT¶3`nê£¦»ÌG?¹ÚnhÕànÊ\\n6ëz+M³CêäK ÜºL¥kïjFQ\\nue|n7R×a+ö Ö²Ã£§ÂeKØU=Ã>¬\\f]¿õYå-6ÿ(Iá¿g&º½L"0ìßCZ¿¨áýwÞávÛ>¿L+ÖH¡\\fC¬ÇÿjO¶$~ ñp.t3ÜºÞðéÚfÂað([Üªhe£sÃçdäÀ×J¿f÷¦º¹.©¤øæ9óÂ-½¾,Ä¨£Q¯ÈßÊM¡«bEuÓ%ç~<©^Òµ("²g@m÷è ¬ËvÐöTßÐC~Ðé'Þïý£Ñ&°CJ»Á\\táOH3©§ÖÏÇÉÓwìeJ'[Å0O°CXåNâ ÓzÞWÙuiF©Fì²²blésAñz¨Ék¹}Ê®\\t×¢ûQ¨òàM^¿D+¬2­3e°W´ÉmORfi+Mî¹½h\\b`2\\bkK³ª¾×8ºNÏÿ |½;¡ôþTI8üXÁ&Î¤\TNÂ×Þ§»f"åÔ:sßÀ¶$¥¼ÚjÁÀì­]Ø´á½Ù4àDfy.¸®æîË/OëÞÜÙr²ðcÎÓäÖ6 ®9 qko¹þ¶Ô¹¥#íUÍåø^I]V,Ó}Öí/¬ý\\r­ü \\nä^¹h*ù3mæñÒcôcÝ2z±u\\rV¡òú Ëç¢h:ï4<ÈñF*.Qa¬¼ól¨Ü)iÇ$ÄÏ³çâsÎ ±ð9%FWC¤/q>°ËTÂºÓ!o¿B>\÷G¹hñF|7\\t>@Y9h(Û·ªyp'CºK5«ç@$°Ê\\b Îæ5Þët* 5«PþF¬dO¦ô7péF]ÖDáÀ÷®8#¥æRol¥ÿ)èDÆ8ma'ù¥3'¾Çaß¬`â%ý«ò¼IAw$Î;e¨a$Ú ¸á[á§Ò3bøÐ7íSÞíÏ«yãîéDá{³çuÌé+f[ªUj;Sýbi®sì9U£Õ/dGÞ ´ÐgYzíÿ¾9,ZÙ¬ïC÷¨'óò.twFõ#D¼óÌ\\raR2á_=ékbõ{FEv­D%´Q¬ºP¸4Ð·/"ÄAo>¸ÝVyïyk\\rWªô3x\\no1F}ÃùÛç\\b£m v~tpÀÏKa®ºêÃÏèó1¬Û|ð/5"/§U¯¬î<ÄmvS{Ò&¼¸{·æÁóMPthÚÜµéíÑÓÈBzL)óg¨É/<\\t¹+XOTà>R¥N¿¶<ç(>d÷:C(ãò($µìhºMáÊ¼[¥ZPGãèÔÇ¿ÄpÎµ½ãwG_LgInørCF0£OË¾£ôÓIÞ;©±cÃþª,*±giÊÊð>òdb©vq`®FHôSnô&\\nÀ>\\f.ª´E»§xÅ1²ÖÒ½zé{ª,°¯ÁÇre^Q¯ªLá´cbr{2j-!\\r®\\t/aÕo³Q}ÒsÜûí4ØÇ¬2åêïÛOØD 5\Ë²iq"d\\fFÜ)\\r9Øhlû¼B¨ü\\b,ã 1ÇIù{\\f«Edà6ªêß«ö¶m"/Û¸;%\\rÌÃoe{ÿºJ°&~ÔhnðØàP\\n³TÁ2Ýg9i¯µ­Ñ*åµÖoýÔ\\fWK8\\rì65"Jg(©õ\\rão¿h!öÅåD°#¯+þÒ¬R eH;ÅPîâØ³d¢xÔWÜëÓÄ<'\\tO¡ÌVl!fyº\Ê\\bk=wF`%+u,-`A¹fW@|ûT\\f×ËþÉñ*õhç{=Gýjv«òA6ó mÛt*çJ=ô¦ËÍ*¡sÄ¹=A}7MjQ+ÛµÂa­õËÁ3b® \\foûVz·mØhkÖæ²ºg,Iÿ¯¬Ä"¤Ò"Ü¥þ«=_IÅºµÕ//yöáò²9Òë%üzAG§½DãÝ°úñÜã´aÀäG~×!$üÐ[Hn+m,¯¬YF ¨PÌttn:.BâN½AcCµ>¤x9Xà*J¨»·Ü.³¥wVëã_ùûÃ@ÑxRqn¼£7Ñ/Î­k3\\rRLF¼L®Ï7`Ãà;éÃØåÛÉ÷â[êßéåØreA_Rï¥ñÒÏêE:u®¡·cõãRm½çIÂÅö{Ðñ¶Ô°\ó{j. W\\t¿OwÛ_ÎNÅA`»#i 5%`#}ÜÔ ÓÝ3°oVÓ¬ôn?<½:Jè×ÄØ¯$DkØzÁÁ¼Tíèc^Ö9~+ È<Ê}Z.þÚ&U×áMY}GôÌ«O)©+MePÚ½\¦ ÞûÓLQ)cN§ÿ¡\\b0n\\t%Fì$¨ÌF×}ýÔ«JÆAñTü&Ó»}oh9Z µaïVn¨ï§àÅÛW }éôëÂùÉ°qý¡Á\\tî#pÛAµß¡ÜÐ^òYÔ*g¦»Ê×Ü%¹&Hæºu§¿°.ß¾<P ¿6t.æ¤Ù¯ÅÀ~êÐ¤ÄNí¾{¤ñÝ»òÕ¾aÜa*RªÅ´½YsÕ5vÅHsl[jk\\r²pTl¹W¨{M£ ö9ü#lÍ^?þ:c­1APÂ!¿8O8kfÕYtü`üsCyXH#îíÚ\\f$a×R 1]ºÂÍO[p¹ÁòáÎ°mÓ4gù{skftçtîà) Ær?o5\i5%Í¥VM£dÇ·§º@¾ÔiÍ=ÈA@úúüz;MÞxz5¾rLúôRÑíD¸á |¼iß9ä/>«ËÁ~&ëEÄäÅÆâ×°Ñõ'±Óì:lóCËî*¶cíÑ:£¿Úb\\f®÷\\fxèºÙo§êl¨×Üò4\\nQ­¥\\t'³Î-àrQ¥Øß­*ìdB¹Ú`ûe·*¶jùï¯üJ5~Qa£¦*v%v]H¹h¶;¸¿&ò2Nõs`(¨S,N0P]ÎµÔ"5?ÊÜÇ+Û®Q¯p°0VS¬\\nxôÖ°Ê¬³'íÔ[UÕY :÷&óòPK~ÕÙ²á'`ÂÊÛò=öØ!Q·}dAs ÷\\bÒPxcàªzÝÜíöu{Ìví±anJL«æL\\f|r^3¡Ax%Î·C<½z`î^Ç7«©,ù'(åÿ%$(Øû¤P£:á¹ýÚ;©ÞòSæäö[Âã\\tç³.Å/zDÏê´éÞ¤ªÊHÎC\\r`sßÏQØ»a7{nTöRÔæÔrþíNÍ ¼ËMf¥à?)ÌCd\\n¼Dèë@³à©·þ*O$¼Ô²[ YÁ®Kà©£=%iAWµTk¶hÏümòÛ]» DÐ³9ÒEå bÞ¥Ôà­á¾Zs«¬aOq\\rã¨þæ<\\t)I}òÅ÷¶uñ1®od-¼¶¤òPug> \\b·MîçX ÕÏ¥Îsãå=´^«mk¾qÞ1ñÄãù5¯vÐ÷ì4±¹0-®¤Ï(ýþZÂ#+ÐI­'äãÏÒ]Üÿûÿh5å±ß·"el)kÌkË£B8ÄÓO\\tÅ±ÌÛ²¹p·» \\bñ2YÈÁ^Jr®©DûY3äùzÐÏsô@íµ(}MÈõäØ¿tMõ-d²:|U~ðrª5m¼ÎM®£oìIß¬M!¤c¥ $Áãv>Ï¥×"ì¹c©?îÉô¢Â¥\\r-¸ãYyÛ¤Ö§åU;åIÃµ^ð@ÐÀÜUNU2GO¥Hv'wä\\r)ü§õ0,×»¥Y1]'ÕÚlQ÷ãÑCmÃÂÝíë9c¨1NÄq\\rC3­v÷sê¶\\b3'QÀ½tm¦\\bÿH*­yÅú\tYUÂÐ«wÎü<>×næ\\tóø·s¶lc$g_üí´tw©'Pd½ÃÐî®\oËaa»ÜZ¹ólgÓ©Å0bÞ2O>È£®,á".õï¢\\bêèØ·Ü#Ò·Î´cÁRnß§"WÌ6t[Whÿãý"Òà^Iª [7ÍÕ:õGvWÂ:³ >_àk IX\\fã¹ÚhÚç·Ù5eÌ 7ÄCqL5\'âòòÜ¹3%YªuÏ§ðíü¿õ \\f:]r(_f;2&ËdXñ%1é\\bUR:¬ÃÇÂò¹b!Aq÷HËzx5óÊã»¯oBUQÈ0)ë»Öï{Îp\\n§Jª?\\tFùõ¡äëíÆEÂtBïÆ«U&ó%Tþ·\\tîX\\b¤o%/¼WoÓ èW³9@&©Åä1l\\n[·í"/Péä?¶-5ªrUtt#­¡Ì xe¹VñÔë|¹üQ1,äô}8¼°/ÄÛwIÛç'Vî£ÇMàä Ö}BëÍE±Rq6ý¿G:¤ÓG±áEr9¢V<K2²Önßf\\nêRÀªæd gã©÷¦Ä[VgÐZ±\\t5î°9¹x(rMüo 6ÚDÐn}¤£Ï±Cäß_¬­YÆ5OøæG g»³ï--O[^È®;Wùæ\´\\t%µ ^çè`ô-àxßõ%ÆhËtú'Ìç±E¢ÅbBýK²{3@9¬l+\\b-¸±L6e\\t=c^î\ôSèy©p³spv½,ÃùE^ÌFàÑ5ß5`úB/#î£/ íü=küØtÎ¹%sg¾|*Ñvl]¹(q²3ªÙéÔp,ln\\nEý­¹ÍSî´~ª¿;©ÁS;»T P£Uþxç`JF±·-jqYÀ{Wì'åÜWsTO!Vp}ð)I«ÒñGMÄÁêéïwHºoÔ}©Gçe¤EØß7@Ð²|³§é¸¿s=öÅ½[ÇÄ¢ÇÅÃ°z°Ã àDîN8#å?|\nï-Ó^ÍJ[®À¡ãAhì=Ðî{¶ûUSÅÉì»Ì*w\\tFÛnTohÓ3í³uá9È)rJ%1õâ¾fÄíû7à£ ø Ð~A+D5Û5ÃhÁ·ø¡ Ó-ãêßK¥A\\b»ð\\b´:âr<ÅlÔf¨q;õÎ4lúÒfîÒÄô0%nÁt.Í _èÖY÷¬¾?ãÇµA'ò<>aRL®wCÔî©ðY¥ØîÎ|CiÂàÏq¥:*}ßÊè\\nt  Ô\\fåÃ¡°ØDGS;E$r901sa\\r}¶°9j/f´M5+ß=LåxÍÇ\\fJ´xG¤E{ã^rKØeÌLxDe7ê(»Þ}¸9I¡å¸¤×CÞÐ¶ÊÜæ*ñy_)}}AAoXòÑo¢ÐùÜg4ÚíííÕk_P"ùu°9£³Þ§÷~xcF²/3m¨vnp²åäíNÇt¿R¦"\\n¨èÞªBÔ¥Òñ«<j]êæÖ?øã\\tÂKÛc¢w9Ú®laÎì\\n}Ó¥AFF+ñÈeÀÑ£%Ïnpì3úÕWÅâXÅÁþZEN­|è4gº±ÝA,Ï¦kâ|¼ßä#£aúC¼Ì°ñÓ¹¸F1/*nýøR\ÏÛ=R&üñðEû³Öå`jA­ÏV ã_,Qe«?ÂsõQ-ÈõSÛé§âLÚÕ<Ðæµè#°ÕÄxTºâT402ªhüïðÌwMk-ÌÕ>HÀgLæ¯ÛO- ¶²c@ÿ¡Î»NÇÅÍíãé",\`L·@CÒg=^¼q#QozÙÅRÅT3ÓÀ¿ÛÅ£0êFøûªXÔâJOy´æ9¯þìÜïdòÔ×Í\Eõìx»óÞm¡RÏ,èHÉÖô&I§ùN%FU\\rPÛIA?¨Q[+øS!è\\tgØL\\nø÷VÚ-Óí=e}ÌFZ*aC#%ïFsÊ5PºG±üÌ}âoÄÂÅ{é\\fõµ>i6Ç^ÍÖ«ñýëñºçw¥C¡¼³£ÛÒ)ôø½;§¡nDÕ!L3\\nbâjUÝLP6S`¢í×´5ñçÌõºôÍ¥½¾ýíÒ-eUæt_ÊW.é_Ð¡HðaÄ>uìÕ[üà×./½ÆðçÍ¤F\TuVùË[/Vl å¸ßñ÷5µNºùÖòlúk\&ñ+ÈñQ¿9Õæ±GHç`Gß\\tõÙxGÐ@¥ö(b!¸ñ°ç*WE¯ºë¡ÂPþý_5åïiï%g,\\b@êÈá\\nhèq¦Ë³\\bl­I\[[Ò ïC¸z{\\f¨_$As«|¶O¬Xxß)¹YZ¤.¿ªu½äk;Ù5`«ÅÍ¤¥é0é¹>ÑY/-üôcÚü\\fGµ]Éò{¤0íí26ã¦j¶mãxñ¿DÂgãxËØ`¨·¿»,`^ÐÐÃäÈWØø\\tØÌ°iÁ÷Ü`$RE¾ü¤WAÃûþEÚMnËÊO5,W\\tÎHwÒ°H&Q¹·oõ ¬ãö&p\\tÃB~M:`Æf²Çµ®b_ö+V9û"zsæj:Þ¤VÓHìàäÚZfkk¹äóëäXU,Pz¶e¾v{tÙ e1Uj:E}ÒGfÚ*¨ÿ¬ÄdO\\f¾BÀÛ»MÇ¡ðv#Ù>¥×Îµf^Ô­×ÈtàÇòPmÚXryI>Ëßª¤\\fýÇl[¨êF6}&&¢Zh@$«¹SÂOD¢Ãp:aÞ¼ ~TZòÜà± ÷X<s¢]N\\f_L4¢ÓÕ®1m½z>BB¤Ë'IBp_¢¶ [8¤YÀ$ïþ+7ýb:m²Ä5Z©¾N¤0è`·\I r>s¯3BÿÍ<ZUã'äû_\\r>\\rþ¿³é¯tÛ¥Xö`Jª¡$öù&#r{pP"¹#Ê~^Z°ÂjÐãqxüçJJä¿ä,²»ëKåèàtÂl¤929*`ÝìééA\\t×<èôÕå«¤¼Ü´¢SN_àÜtÌæÓ*×Âåõ-./Jï'+X0ýÅHµ~·,Ë+ÿmSY>®Gÿ`d+ÀR­´5ôú!è³`×ÚØMw2ßã>àÆÂÒºÎÖH\\b,Ù=á?¶á6·%õÖä?;ßþ._[æoLðao»i¦\\r´ñP XèÍ¢ nÆ({áüì\ò\\rðIý=îI}VíÕçºÄV&,~¶¡d?!X Çíx3¥F?æÐJ5Ù\\t,²^%"ùV;Hü\\rjãs®$³S_Û¿y:á÷[}ëiÕ]Ü­ rË:æ7æ½a²î±ù¢ß[Ô#Ï×7©g.Ó;ânJ^±Æï¿nÛãF:eÛò?@î:«Û¢ÂÕs}¶N¤*¹RëÄØZ\æWRàpv/ûê9.hª?î[Þ·Ï<É!;Søÿ·¼Ç/Gýý3ý©¡f}^»þHu\\nÙQÖÃ/Às6I÷é9sÆsÅµé4Ôý­¦<\\f£ôziÔ|¥|UòZ»T}#yþ+þª¯\\fEDÎµ{ÖfL´æ{ FÙ¸OßøMpYd ®ë:«(·å±]\\rËø V±´ GbgßÅ~[Ï»7"cÊ'»ö»&+\ïy¾±=·Rëò©8,kmÕx\\r¥Ðd&3¬01\\b'BäÝÐV¡ùæ¿ÜVE<4®\\rU|ðÊÜüW?¼[Á\\f~4ïgP\\tåPztmö±ªj9hðTÒ4ïÐNg}LÀïº2¼¤P@T±DpÖÀ+\\t­ÝrãÂRß]³õ &-Ï)éëyþ¹³³©ÇhÿëÂú­æ¸hzkÔµÂäÒúw:ý\\b\\f ÑºÏïÀ¯×XTÞK>ö.Nówg[íPB5Ó9EóLÁ·jV4JàØ+¨km?ÜF/ÌWNÐ²ZL¥ÕaR¿5ý¹öjâüÀ @;jÓW´åfÚO\\b³l9êY2G"F¥q\\nmº\\tge®o³N»ù!?°y"³2$o©ÎH},¢Ù'uëÜt\\b ¡eoTÒj¨[$ë¢§|¾Å@×¸&"MøLÄñ}Åã¾Ìºd1¢Ê2_8ãïúCÊ%r,»ºæÞ¾E=¬Áã8´1'fI½`3ªÚÊú÷h§­v·Y8öo3áöàá@m *vÊ|ú\\r*¬ê¡#@|é çäPd<èwaT÷×ã1s¢Q5}§Ñi¼Ð¢ÝF1ÕÅ}ð^Ð¨\r'i­w9{¶¾#è ­,0H×Áê¦0\\rÃoÚQºÇäxd|9¿àþ4¨j§#ÖÉq6*sòaÙ¯ÁDD·Mì·5°òìXD6¤â÷*\\rÿÿmð+["²oo%[£ØæL«~ÏÓo%ÁÎÍmaæ¸ñCXm²À<Û1ÿÄèë, HýÌ%tB\\nj,I/ [1yV@ÊÀ²1gðæÝn°åt}ñ§Akø)/L×gò\\n:£¡â·øÓ¿é@l²&^j\\roð*qÑ÷ÇkE½-Á=[E¤vs]Î¾@b7+ø{*ÝUÏ;C1©£Ô3ÒµH·?9á7NbÐÄGÊYÎEÐUâSjdÂQZWçÆ<¾`h,Ô¨öÏ¸;öBÞ@c2ï½\\t¸ÈÊMw¨ ÅôØ)[ô\\nþG0²jÃe÷l6%zÕI?\\tÈów½7j×âÐØ.m~Käaz,7gÅÙê\\n¿Lª»÷¥óç¶gÚI^[ât~þvHí±'éÑ:ïËÌ¯ HHÎÝmI@ÜNáTÐ`"k¬æj\\f,N±\\rÖä\\t,8ßcsÒ>\\r}_U >}®=¹QáéFQ±sÙ%»(Â#º¶5ÜWôåKÀ*D\\b±ã©z Ù<GÀo®Wf/úààºÈ7ë\\rõ¾Öà¼[ÂtO6^YÍ}åG£3^Ô=öà¾Ü$ÿ\\bÍk8 B£Û÷øÔ®7âÊO¡dÕ>Hà(^À?®¿$¢½6l§íïT%¹ëpæÕµ/wðßkÕ;Zd¸4 b6þ)ý¤øïa5ó/½º¨·zß÷m}n³Ô¦Px\#ÉGu{­ï\\bã"ns ÍÊPººOL¢?IÎýA$pÖ¹Hþ¥ïð7¡ë±ed2ß~îI¾¾1ØÂöAZ<mlôX&­D1~ïä_¸Ó²0óXéþé;ìqÐps6½®í&ãøJ9UÀÍ¯®ãpWoE¹PÈ/Yÿ¥ú1ÿqr~ ZÔ¥ëpÁÙ]Ùþ¾í=ê¿ÔºúÞþ'Àä¶ÛZ\\f|?-K¿¡:ÛÝî írÒ¡/ÿ£\\rqùY8û³ªçÇ:à7Æ ÔÓ"ÝmÔh[Ðy§¹È¾þ@ç¶r)Pþ ZT+¶?MÞÒIG0í#¸Sí¦Ó­C3÷3VM|Â<}I¢|^½npñ°ìý!áEu!LÍ|¹1øg¨úÁ¤åÍ«ì<\\beÖQd¥7ëR©ÝÔcÜn3D^%^/ÒÑZ XÌ¿e¼Ì/%t_¤P¢:¤#Ø9^UqªVèÖÇ>·ÞaÃ¡kÃþøWFPiþco¼?ðÉè;~_UC%¥|c¹Í©Æ*ò·¹\\t¿¿la£è]úÕô£¦ÆïãÙÞMçÒ<:Úé¢^GôÓoÜ®LjÓW¨¹{ dF(C[Â4K7L~6ÑùàéPUûH$¦ÙLßÃj.)x\\nGA9\\f;+çlÕ$¼w ÝPrZ{Ë8ØcïGÏ:Xûk,«EC£sÍë\\ncëh¾ò 4G\\t­xP³èpf¾T(É?¿oy7ú©VÒO³Í(ÉÅ&#6jå\\fK«Ñ3¿Ã`òÒÊ¶dÔ©*(½(Ã¹L0õêêV>\\nð<+Ýf+z­éíëA\\r=CEK¶Üüª:×0ç¾:0#`xlå%õV÷é·¥Õò\\n·?ÞÆ XÌ(Kn¦oìÖ[û½ó°ÔsÜ|"X7WpgÊÅbyBóM/tÖÑÂÊ\\bHÁÀøk( ø?íRdJkµ,\\fxÌè¦øaoGZ¹ÃÕç]\ÐâJ\\bãHýòãÌØ6NÚÀ'ûÜ`Å7:ÏÙ\\n^9{ÅÆøwÌÇñ_o_SÈ(&oC×FÈ^E}\LÕÖ[´ GÈ]&xQ?¶þ^á¤Ryü¾fáÂ³]À×_¬TÞ<]§1ô{×WYè[(ßµü>\\r"È\\t%õG;ðcÃÙyt®~­L?À9Ë¨µõ©Ôp×YÞ^\\tÌåm¥$êu!¦}ÕUÓÑ¢H`EG3YJ*§á}zï§L0²\\n°@«>¢£`Â®d]\\tù@øØK\\fÆóÓ»£5Y±` Rs½Ëõº)þd=Y=ðm+Y3#¤s{ÎCÚ\o§fÆB?1_çét;Ü[b4p¯5ÏmçÙ<Hä6|9i¬ù°E^ËG¶Âfhí}`Yðéya7!­Mù( OêðkÙÅîØsþ2§à%p¶$FÆ&{ñÕmQF5%¹1täÎíÙ8Àfõ<9·:Õ½<~\\tòQADtá ¸M÷Ål Û\\f8RQ{µµ¯;î×]´½C¥gTá³]ýGÄby±$6r_îcº¿ü~í1XÈ>®} îÕ·-éWÊ°g3æ®Û)E0Óÿ «ã2F¾:¼Á|ãRæliÿüN®*C£ÿ(X\\fkc~ò"DÐtFt°-§(cäæ+Þ+ä=%ÁëßHb·b´|ÑiVzºÒ°:ïiËh¬ÄoY²Ì`×iIÿv$úe}#mßN\\nYZ&rÝÃÚÎoÌ44Ô¿OâM)ÿpiXwÎ~\\t/©¹-a%µïÜØ~¸O¥ãwh=\ÎhÍ\W+ÇqúÍX±¶»kÈæ_©}.ÔÛ¡L;×ÜòÎcâûxypc' ÚH½[7Vêh© ß%Ø¯ïV¢½å|×?¼(µ)\\tTC\\t=Á¾Ç´ÙÓá®×Â7ËïJã´ó\\rcÄM,5¼Lî²"õ7`,dÈëaqñÂÒTêS6èõýmòÙ¡(iÐ¯«2t¨»õ#)g.F÷»\\bßé1Bf_®ßµ§ñV¿Ì$-¢ñ¾<vó\ÌAÈQ¼¡°£3*_XË&yoJ<%±&<TRàOý~°7fÅÆÜYk=\\t^z¬©ÏÂ/ÃZULº¥>Ýë2Ò×9þuñJ+tå©/Ti è£¡ÆhôÝ,çW9¡ï9¹ÖGPvu²«hC¤ÇsA·áTÿë.CWU^íÃr& ØNJ¿zxÊ\\n¦Ù¸3(slÜð â]ÔÙt×ÆXËY|>6YÞÛc[ôÅÆäe\\bcfÓGë¤ÕäáXÒ4µßÎLþÐ;«S#Â$}´ ÓrÊ6OÔþæÐ}?à/9p º}J7®§SqêÑÒþîão´s\$á¢Ñ±½¦µÌÜ½ã*­Nª-«sÏëÙ8µ¿H2±Üú+øá{+@¸\\rUÊ¿Ë×£kmuH5:ìq Ùõ21®7´ª\\nøÙgb÷D LÆëÝ ÝµLyh«ù÷pãä/Ú%¿ûí` æv¢ú6~¸÷½mÕZk&\\nZa9ÖFóÂÞ³×yB(a ºy]ÈzAÀ¥tSíM1ýÎEhîÙÂâ¤Ljæâ«Zwq3h(¯y<Aßý²ëJf½ë!hÂûm¡ÿhµÙlèír1%\\bhµØÆÒ.ÕI±­:sI|× ¬6É}6oçÛ[Ë¯iI\y¬§£:×ù=[ûF¼ÞvtöÚ½\\n{Kï´ 7|²K+|Íq¼|Ó8¬wFå«ç»ål§D5¹X¥æ³ÈE±³)¹xöÏµ±OÕæOÿÆs¨Fd~ò:ïòý)bìä\\tûÈxê¥ðÕ7$áË­:3Ýìn)ËwÛs[Öm§«]\\b`¹jõsGU¼ÑHL[éê.%²±oÍò ¿,ÇÅ#â(ÓÖêÆ@_äQ8²Æã§Oø,ôhwqòÔk´«\?B´ÓÊIDOñ:³ºÙ@è;ËVQç*%IRy®gë\\bþ~.\Õ²Æv î:u%X<ÉÑdm#°¨ªQºûHB^¿Öå¬+_Àcù?ÛV9ÎdÒ1ùpÖWÓv~Qb¤H:Ç»Àµ+ï¡ì¬ÐÚ§if ß&qÅXåî±vZZ|&£\\rDe²>ÔòTÅty»7¸ÛöìííãTXJCá¾\\fèb®BP¿gFÄvy?É£jao\\få(Ð­+5oÅÂs^Q\\b´¡P\\t||¥%Puds2¥1Ñî2lµaJårR`(HcYSü±KîíI^ÀmêìN3a§jÝ"þ×®PZ6¥AóÔÿ$&+zéAÌV¿%'ØååUø8#eæ}YÆó[ªF0´'*¥y4X[zd6?ÝÙãÝè<b9Ýt8Æo4Æ5¾üùàµKÃî°»4ã+Cöî½<6¥*Í+#Ü×G¼\\r¡q-\\nïÇº´Ô@mPð['MÄ¡Ê÷/1;î%6ËÐÛbòGOÝñäx£Eþ?uTA­'NìÁ´2¢ÁWpXq}ÏÙYB-çDh\\nÍZï¸ÌÍYòÎ½íªxìú~»5ÉÈ$+M×mÒÅMs¨!@Ï#ó´ê6ÎUî*ÜÏ U)Ód¥ÊMª¬ù¿ñ17±¿ÁZØe{¦aEçDÈheAÃ¦|ÊSÍê«?"gQ³´ÁeJ¨WÙ`í½E\\fÓõ;»ã9{­UH,\\b#²"½}"ÆÖÉtµ9Í¥ÌÄ4×eTCÁÙÚPÏÕTÑO»ú\\tRF°|\\n8¥«´Y ³Ñ¸²¦\\rW×\»â-Y¢u)U;nE50Jv@^\\fÞä¿Óá[÷æÂsé¶ï·¯hÊö}8 i®t¾îwt^Ä¿±ÑaEÔõ²{ã~¬±\\nks~Eï£¬?á^ùo3?½bs-dê\\tÃÎ-ÈÇ\\bËÊco°l@'z´ªTÔ`ükY+/Ä³óª:ÖLµ§C`ïK( å«ÈNgY0 .ÄFzÈugD~«néÓf¤×\É Áõuâ¹0g9,¬ÈK+)Çûi ¶ª%¹ónÓlåÌlµ_ºg\\nNÀ%Kú¸ÿ6Ë?QD­½Gd\\tëuÚ¼:=×,¥Å6\\fa×îþzÀtvåznÌ·â Òû Ki--BmüÇÀbØIÀ ÞÐòN5¹Ö¤¿BqÉnÚAûéùhN,yQçþ2bÌhÙÜ,@©5bM?F ¢ºy¾+.jv~RH Jã$âäÜÖïk!ª*ÓêHóz·×Íeh0xtOÆZËCß}/#ñ v*ãã©ýÀ:÷.¬Ä£ÎV9j!¸Àû\\nÜ^³ç-Ì>j¢7aKï%\\b2¾a\\téüÿ¢~\\f?\\bnc:á=\\rYç<¶d:\\bÈ\\fiÅ6ÐòÁãÔzo}·½ó¨èå¶6nD6Ùg¶rÎ\\f$óc3A-Ê$ÙIÁ$hÂ¸­Þ-ìS#t\\b°b½ÀËj7+èZ&ò©Ý ûr[Ï'ò·ºì¸¬ý5ð_ß´Eï(Ïl¤:Â´Sï[t2¼¾èÏCyd9d7X²B£\\nR÷Mp¯Ãú(°¹Û5ß­nD¶ýÎ;$àãÛbüs$ÛÙï@ÀÒà¢ÍÎûìîw±ïìS}mM_äºêBÙæÄÌ÷ü©QÛºæº2MóqB1Ë×#\\rJU¯UfUm\\r³p­;7bÞ^:þ¢dwàÑ¦Ä"'5~u.¦~XÖÀe4$/Â°ª`-~~ÎNqì2ªLW`c\\bõÝ·+Úq}ÀU@Eq*V>&1³¥·­ê«¼y,kÝ{vèýËmDÐ}¼Üoe­þ(</Wt\\b?ìSP£ {<ëMÍsÉÖ´[t½æê|)\\rcÛ,'µ©ÿËôIÃô¸\\rÚïwM*Ü)ERE\\ti@FÓðWêÕîÜ®tNíy§â]o=LÌßN#/mçAÊ¶Q\\\nÌÌkì85"o[VlÌçöÕFÖÄÈÉ[\\r«¢G¸\\b?ÌHÞ¥¼Aõ3l®{;cð¶»ÏPï]«@täpâÍúÅLÑ©kUùWqgò\\tFËhëÆËQÜüù»^XøüÎðïÞÓê3ëÏÉ÷~íaUãb0®@-ÔÜ¦G"iÂTLY]$r^Y?%Þ¬Bë6û\\t":Òÿ#gXC(»cQÝAºÿRëcÄi×ÀÌÉB"¼ý\\tóìÕz%Ä\\b³¾Fs*õßï¶üp>ù¥¹·ªé¾Ç¯ÀH´;×§cOPàµú½øßÜÌ·c"åx×êh("ªyUÒ"¨M'êB*ÐZrm¿f=ª¤+L¾¥¯¼HÀµhH òÔMÑ\\tÛø! ÿì-JUiüý`ÀOè´·6"lîÿLU]/ îWnüÈ3rlaiGÐ¹ðåYèÏONoC.\¶\\tétQý¼D\\b~þ´\\bË~ê~yöý ýÝLÝÔ/îê"Nµ4û[ÇÔ¨åX§³=¢x:§ÚÑ`¤l×¯&T¯cÖ ¦ð£ïïñTfC%é²­)X{xQÿeÙ`uj©ÏLõ\\t\\b2á(vÐYòÌæàÌ`rçcÐ.mÆ§go»ËûK´"¡×±Z«EIsD°hä2èñ7Oî×úPF&qÌ.ÁLÅ~|[°ëÑ'ì\\rËð¹Q2©øÀ¦Ú!S½¡WY*j¤¨á§2 ÞÉ²¡Sa¶¸/Ñ:©¼(k·icí«ªÚ@'OD×±RíÓÔw¿x.Î0´Ï6©!,@½7å¸çLCÖòJ[þSûNWg\_¼Gâ¾Yÿ&Öuïºüm¾´£c¨êø3l&²pÒíw0xaÝË$+ôÚ`xð¾6õa:ù¦É5±ecH]<?ð5~@[±Qj=?ßâ"mYkJIþ+¤];ÊócÁôµ\\t£ä%\\fÐæV-\\bQÍüigÐ+ðµ¸iì{Ç6Qa ø#Ê¤Çö*æNþ\\rÂ6Ì`ñÙÊ2Á\\fuÞã³­kÖTaÇ½ØøH~B2¨c<RÜ['û´!mDËÿ¬ôkÚöÛyNÿ'¼ùÙ¸ôYhp[$]KôáÚ¦\\rGÍb9MÎ;^0[fÑf¼j7ìí8àLÔZm \\r_ÞgÍªºæøàPb&wÑmQßµNH¤ýmJ*öî¹Á%H×ÿ#Xêt®å;db:u,s ~¯¥3¾b3ÎvÜ¢\\fMt®]uózÖ,\\rIB"¯âÛÙdÝbguTÐòþä²êÎ>;\\b¹æ¤¯¦Yn´ÓpÀd}©mvÜã®.ZÆª bªwáØÑÅ¸¨eµºëÌ7÷ïÍ²(¯3ûéz4$ûKr?-&jYªu\\bÿ[±Í®ðáA§©Î¶""K­´¢ÃsØ9­G¨tR¥KØ´j¯øÊhGÅí[ÖÜÆ-6t^."²|»}ßAÜ`r½þQüyR0øò<½æ¼íu°Ü5lp?jf½1=¢}_tãR¹Ýu_»TVíKNkýgV+©öìS´Q¾.\\b7ì·SkèõÍiR-ÁÛH¿éÎ@õu§ôj~ñíªGÝÂ$11îXÇ¶[Ä[;eÌ­[ð§t½upìQÿÈß.à4¿½:7çÿ)U#òçòBëúWåYy}0þ¹;äIGÂ\\f&]ÿ@#pâ§\\nã@£§%f/»ú¬u'XLqIïÀ^èa?iP¾T;ÎPõF®)ggBo6X¾³_Æ1WhYÞ  ªu-QTµ@GÞöß@æð`XX}Ë?ëÅ×DA0vÔÁ «äòL!À]³=>Úýß\\br-o\\nbÒI)íðé\\tÿ¥fbáÕîEÞ¬du3]õÄ}C_ªÝÆ#ý|O0³òÂ·²-1Éu\\rñÄÒgÝ¤NïOB·eªzjg[ÇüHh)aÝ®Ë1¤\QâÕü«NX»\kíÎÓVkW^3]Â+äÃc;¥KÁt|YÖÿ÷/rØËìÐðLÊÌ\\fª^ÓÿÚ¶¥ v=ÆQ[RV·joÉ{Dñç©@nþñO1ÊVìÂX5ñk@ÚÚÛà1ämKQ\ü+5÷1òõwÀX\ûn7û$É×Î¥w\\b\\th­ßÙ¹ß¡XÊ¸ôêOVom\\\tÛA¬Ð%À¬Ó _à&¯§ãîpV¡êO°üÇ¸"X·z(ÃËíujº®U 7#[¡ä¥ÅÐ¨aKô$}ô]+¢WêûÿR­OÃ´ÁzDôíD<Ê° ~/§áRÌÎB¯+<#öN/ºP(óK»)µíèTä+R\\t£Ëp\\bû~Àic<çÃÊêq!pHÄ;Ê!YàýlnêÐ¡h:5ô"P°q?äº|ø´þcÑ>\\b¨õ+µ89­XËbìíÿ(Ö°ÍIÓw³ZÃyöp[T±ù$(³"ñÂëÄë\ØóoçáÑ= ?÷»iÛ$`;è¬T¢iùtsðê#²ÑiÀ_ápï2¡Õ<=G\\fÓ?ðÁb´º8»ÿ,å¦Á;Fwy³iYÞ 2­ÜÜÙÜ¦MûxOvVZ;eZN(°\\nÍj;Ëçßç¿Gâ@»mb²áQ÷×µ=Æ£X¤<·xÁýaC×w/B¤\\f$´ç+>'ß²_C«÷Æz1HJ}Ø·yâsDÛDqëüvÓ*£Ô°ò$¨ïÏzY§­Á±}/6~BOóÈuqEö¶Úw³OßæzlýLOÅ5³Ô­<~îL~-æbaö~\\tñsU¼ÇéP \\f\\b`[î£; þÖ7,1å=\\n±°øzÈÃ©Fh]0[^çEó*J¤z%¼Ö/4J:üfÖ\\fi~]ÙWöRnÌ¤üCâû¢b 'qa÷ã*Uÿ)jMWàðÚ¶Ó°|ÆÇzk­Jºÿcù!¨WÊ£XOò#Û]Dai6¾õ_Ccñi¹\wYéQD|FaL]T{W>ú`Éj(êx­P=p·¨wîÞ5e1ûMKPfL?æ>n«÷ N,Ðàç ­yB±:=¿báG^e,å]±ôÏ³öÉý_7\\r ï×6Ï.µ§@ðÄ¿BI-ü«ÁwÀ`¨\\fhxÈPpëPèÈGêV'Øýý]£8=W¸5ÔóýÄ÷æê¬°2\\bå\\fäOPN³Ü¨&¬´|`m­{j"òùÁ¦{«?=¨*dXúígT\¾æ£Rg1Øú?9Êÿ[;ðÚÈ8QDü;ñ} \\f£c[åG@£VsC)Bc~Ëùx¼¶.6Zësl`ÅmoY$A\î\\nR(@$ñ*z­÷k}+û.wgßæ<ÙÝµ¶øñÄt\\n^äÎ\\fn¸LòÝpÓ,9ßÉ÷«ªKù V4HÒW¹:X·öI£8&8CÃÑÍÏ~qkWîÝð!\\byü Ô/ù1æ\ ¾+×Ñ"#WtYlYEýÆCFÍ}×*¨±MÀ/LaÅ¶)ït×ø*+\\f)!DÑ÷$¥Ùå\\tµÕÌwwç_µé¤kDÖuÖ¥Ga3¼²ÚÚôuêtg}juê·a\¿¹$«}aDK~¹7Öz&GÞ% È))HÆ«ÂÅ¦ëËÉFÏÕòÂSð,(ÙÝæB5\\nöè%~ùhêxVö).Ò@Ãü"ÌÇ{ç\\n]^Jàðd\\f[PR¹Sý/»"|?Ë×æ\\r++o`+ëbêÂþËk ²¦-lI~Wlf_a*n8õÒBSåG|îj&ÐB2YÙIsÅÙ ùòÆçáÖ±üÐÏMÔú×¬bÛ ³¶ñÀºâÈî ºµ\C>qýöB[!Jñã2K¤8V¶4=á¿Õh&·1rËÁmºz\\r6Ù¤1öu-W5eã\\nïqp$sAÖ,®8v¦áð£pÞÿ­WÂKdmMÈgÝ<;nü¶å§Aß§èVêS§ùé1¶CâÞFæ ÀûFHÇ2ÙIÇoC¦Þ1Õ¯vÃZ¤öz¹ÃxQ<wZ¬F%\\t÷Ä|PdsÛ?LsÙ¾õ¢m\\tÞO*=hX?ÓPÀc3ÿ\ÈezÌò|¶°£JÔ ä¡&Í¥b¯zÅI¬¤+zÓUÚ«ÌÇî¸âÏå'£)ÃßA2-\\bó¯ClÔ%ø~wYª;®\\f£úEB+©^?ý65÷1?ÔqÅÑï»:¥é]4×.Ë­FDH³û_¤yB\\nÉ±CµÖ3J¢a9aw÷yKï#0.ãã<mém¢q­Ö:°$,á0¾úý\\feýþÆ DÜEVÙ"B·OÛÇþ9XLôöE\ÙcC^svY*Ø¦¢LW.v")ÂG½¶Æ:HyISñî»WØÒ¹6ÉÂû«e®d¿$@DP¿Kì.H$ÀÜü&Ü¶â-­&ÖTcïT1^»'\\rzñ¶úYÒ<<,~=ÿb`U¹?]f?tÌ,#aüÿ3gô8Ó_ò`(fCÁ·I±·)nÐ÷f¦éÔr\\t½\\béo¶Ã¼d®®ª!ÕLÜ:Âqîø>ræ{ ï«Yñ|ô&ÔÃäG}æm¸@KÃçH,Fî \\fód%ê°wÇ?êi7o°ß@Ó_E×¶;ýM²239Ö/ý¡¸>GåL©Ú/q\\t³}?>G;pªæjýË=ðíã)ðIÞ£¿ëÒÈ\\n%ÉAVòL·B4ÐÚKÔ¤)ït¡ÿd/DLfªÀ&O³ß¿`ÕÏÔëýq;¦øÀÍðÆ\\tjLíÏibc,/kfð\\t+Õ§{Ý<Ü= e\Ùfþ]ËÎÝÕ¢9?IVÉÐÄ#²òõÜè\\bÈ¼í°àÛÓÚÖ°´tg'C´ AÃg$:OÊ\\n£$Át¾!ÿ·«wDYµâE<åþÃc&lÛËFe=ð\\th\\foWmæ¦ÜÐAþnÅdóBÜYÆ iµòðíìùVXdX>ç6NóÇ3âíýWÌ¼¥ÚßåhìRÁÝW²\\bÏ}85,'\\bßW6.p¬ùPëµ¯ãÚ§iãsÅ&ðÐõäúo£\\füÂÌ#,/TÏúKQ©_BAÖ+kWÂC 2Q`ÊÎü.{©ÁËÆÈëgå3KPÿLÅø¾òl÷Ýwáô¦âQéUíY¼Æ}ÀÌ×»J0<ã¡ÐØ|þ?LWÕµlÉ\\býµS»¬}s8*Úüì)#>W*¶¨Bb¢{á¥«»qFÌwr$<¹Î-æ9Ô \\ràèC¨t;å}Kj®Zl§Ó¶Î¦RWÀÖ´¶éõrÛ,Ìk×Þª&¥¤²þ\\b\\tóòºi¶Íq¹ë&· ñKm)®[ýD S¦Sf} sònVeøæº·O3=q#ÂíPy8¯8º[ r}óµ¤8`¸YÑþÇpõN×¬+tV\\nÙìk°¸ÊÕP,°ôâÊhYÂ³"}ü¤åþ¬þ%ÕsFY!ß4Û-Äè=ü+Lç\\bu-cPG1·íNÃyC\\b0N9»à4Îdkw÷¦àÿæGcP÷ÃÔèjvÃ^pó®zhU"#¸ S{è±Ac\\n§xûÃ#ùUF">ðÑWÙívì³\Ò=Ê7bywôò°*DxM÷1UYe0æ°¶å«Ç}jí]Ð5Ø;ìÇÒk,Vll;\\b¼ éU\\f(î7?ïµÆoæÅiZÌÈ5o´}ÄùÍ{ÔÚ?½WÝüå'õµS D¶b{iwuÆXZ[ì?"Y"ðÈ$1 ^lärÅÏ9mà*ð\\r`Ã¶®tAöGa¬¾Ë¨u¢­J\&ºª^ÿ,óC²¥V (;\\rB»ÞSÆdswìöYy¿e/Ì'«Ç3À¨[[ûv­äVmQmBNØÐ å¡vnR·òB030ùÛm1éWÚ²\'ZRóýv\\bñÐÞztõZ~ó{D=LlgM3êüÛífå«>ì¶{¯Öòq4)$\\t$@è99trÏÌ"x¹«PEøÞë¼0®2½b¯£/«½3ü{\\tDÍÑK¥hü°dñ`ÒG'ÈûD 9RcO89s¸ÔA¤âª]ÌZ *]ï¢/1MvTCwXLUö]\\rnÑ:ÎàªÐmÏñ«íQäg6R²°Ø?b4O¶D SÛóÙÚ¿ÍâÇò·²\\r1z/#¬Cfç7ºÕ.k\\nÚ,zoÜÊþãîËÑ\\bê´í/%*ë9Rµ_£öònh¤Ö;³<yÃ$Ú{¶Äû´h¶X¸Ruà¬j÷>ËxX¢ÕÈáB%%2ÅR¾ÇÖmí®¼|æÊIÎÌ"îª¶¨Å"¬¤ø5Ií·ÒÅÜ)©;UúË¶DÐkBÇÑì¨ö X.+vÜQÃ1þ?çwþAîUTSùä¬îH±ÉX"8UÁ´ö®ÌJ¤EeJÞ\\r!`!øaP¹l{¶ñCágÃYá °ðv£{ù¼"ò[T9h£,_´éùÇuÑ¶ð\\bÃØ$,BÇ!÷òOÞf@åsn~äôâÕKO\\nLi«îÄÏ44uçfé\\ffôØzmçqPs\\nÃÙ#fÙ_·bu²¹Ò N¡¤.{³\\n3>¤àJpÙÛGt=DgMÇã.!¨¬ßøôK\\b VÇÝ¿ A¼ÊcX`ó·uwâ6LÜ<:Ù¯Ou2I!RnPÃ^\º]ÅîDv¨0õïu¨{QNÎ8C½è¹ö²Ûí,ÁÎè<´]öÆFN+@uøóËyø|ÃÚEm¨ÀxµI:ï?!Í¬Ñÿb²\`ã(wi\\tf¡ÄÄ&£9I±¿ò¾Ð°µ72}{Þ×µ{¾)oHÕNÙmRlIBË\q$RWã©ñÌýVMµöýY\\r;6Õ5KßÊwÈ-'úRv4÷*&Íê>[ÈêÙb\\rÃtÜûÄi¶çNnÿ3ÌaaCþ×Qþy6ù=R×ÉûÇÆÌÁ¹RÑ^¤¦¨×ÜX¿qÜÆùëW·ZíyGsÃ¾q´]kHÕ'Óeõe=¸,p\\bb·/þ=µúÈbpèÚJÏ¶?ÇÁøX&0Ï¦b:¯{þ©iDÜ]g=©pÆÓÝ<~Ó\ößáºÎ?á a'=«èçÅ 0 Õ¶\\nÅ[]T;Ï¸&¥¾\#ÏÒ´ìHuÒ:²4.Ãá§GLôêF~%ñ¹50ìÖà·D]A·Á°\\tóÌOpÒ[>^gD6Í\\bX<Û9Ï:ÐÿÝ~,:Ô\\f³s]0îJy\\rNS%ºS²ß-Â4PÁÐUe¬Â\\fÚ¬zø ßøpÖïUi\\rÅ-ü«èÚß:ßÑ-îÿ2d.àzâ<ßñÇÞÅê&$êlÇJ[OKZÜ?]vLèø'ÌôÃó»äÀÑÏ.¾\\rÍB[±bx\\nÆ`Ô`(Q?;yµ\\fnY[ÿ.HÖäbö2;®9³{NÛ0>[xQÿ:æ*3¥ñ1ÖvìÜèç)+MäÛ5Ç#¢5ÊÏh?¹ ®ò°TÍâ ckò*§S­¶2çùÄâðàìÄøgÜ1fÿ¨´RÙoWÆÄµè®kmÍ$A÷Êm\\nvôOYÁPaûÐQ^$ª¨fH]<Ú\\tÝæ 9ü^ðF¡z|úã¯¼Ài¨ÑÞg\\fT ûéª8 8©³ü\\n»iòÍ\Þ×½ÍCWiÀvSBÞ;H¶+åt9ÆÄÀXB2\\fÅ¼îØ|eÑ|k'Ìù®-ÑsÍYÃµá|J×{Êu]+\\rý¾»¸m;wá¹ÕÂ'\\tÒ×:·ü*D4bszsìWlô¶)\\n<Ô<ÄÎW> V!íCx"Æ½ú×=CÉËÑ#aèèþ'ÊïG<G¢¦g£[q´ÃÏP¿äêç&gçÓÎtâØ×óÑñí1yHÆ§ ë#EB­"1ØñZe³ú²"M=Wì?;,þzkðêV¬«±ÙP_ïÓ%x¸nÊ:%Ï\\t#Ã*GõB®zj@ÓÓ¤Ë{?ù ºÅFÌ+[5Î`Õí,I¢ÄrñAè¼è$MÒJIA2.ÏRÉÇ#'¦CB°â6=|Ek­¦7rmÃÌwTT=l*]«®íàlx£ñOÑ­% ýÚ·åDäiÿrí3yÔ²»¥jÁèÕ,ÕP¶º\\n6Ìò}ÄK#J\\tÁë(~:$ý^Kú>Ì\\t¬|Ò¡ôl|y#)ß^x$!Êº\\f\\bì^öôB$ÿè7MæÒ®O)§Û.%Yo~ÏE\\nC¥²u \\t=>ú,ó]ð¶Ù¦ªt^&bÃK%-®»¯¥NéVWH£"rÝ®îèë¨xvb]ÚÊrîDQNR`*1R>ËH¼¸Úm]*Óq¨ÞeyQ¼÷}6,e¡-]ÎèLvµvØO(8¿þÏI\\r\\taàè/*fÚÄôäM5ÚsÈÁ÷ [{ìÝàï#Çi@5|çÀÀ.!DðNçì6'ell²»ÙQ7o ÉìÓãèJãz{·É\ð_T»%aÅÄË§`Ôf3d¼~mUr3èkL;­Ma7~¨*ÓE¦2è^ÝRd\\tðb{ô\\bÁáF`fít\\n²Ãº\º´9!j¨i)ïààg0Ökåæ\\töMyF#,Èïtä[ØÜ\\t¦ìXu9@£sùý!kbø¸GÜæéAyfÅ¢?pÃ[é&LW®qË*lÙðu­\\nÝ%aÇjïÌàT«xhT7ÛYrñ?2g¯[jÂS/1ØNB>];5ÌðÍ@îøµ«Gzø¤VW*8yæGOµÒsrZ¯i@`6?ø?a^Ï\\f¦>c_ùëÍw¥xåvNÊÇOXªÌÇåµã¯5_»Éz¢ÆßØËØUvÙ_¯' ©¦FFc¤ò°×Ãwþûò¯VÙXOpcÂ0ûçä¹âì-®¤Lóæ1\\tAzg'Ù@ÑÄöÃgD{òa·µðÜ¨~Gôÿ`t¦VåL(o1 °¨Á«qsÏcápå«6y|P½úØe:»Íø\\rÕwMÃÀìpþ»VÿQ¬wl9>,§ª\\t¨ï*+Ó£Õ4ÞT¢,µïi-[>$\\táB¤n7VWÞØ±ù>D»\\ruIbñØ½ßÏÏe¾ãD8¯¼úS(Ý½45%!ÙÄ¥S<ÃÆy!É¦ð*Yî¸¢w0tÕ"lës{»§±¾ã¸ßõ/¢×fáûsþqÌQÆq\\fÅÉþù*#k.Ô\\nbGúìWz=cG{uâ>#(ÄÔ:PÜ\\n_Ý<\\rÉ+x8CTýãk8ÓáÚYcuðØzLÃåï6OÈo$\\n2å.q5'¼1iþãv½Ë~Gù@\\rAÒë¤rNÅûØsÝçlÞbàVxÍÚ­2l§õvM+#möó$âìkY$0ýÍæÔð@ËSl]8©]¬3mQôÁdÏ"Q{eàÎ6 sbµ>Usµ#Øæ=L·¬Î|:i]¬¤¿H³þ+dLXH4<ïÝ£/Ñ1~«+kø2*<×$Ó" ýÚÙ¦d\\bó43YÄZu{êØQü9Ã$ÿZ×¶Î8C]E2çR­;£¼m{ß?g@ÝÓ;È4.p"²jUf¹I^î\\b,ÈQ9óm?,.¼¤ÓÍ+ú ÁôÍ\\fæñi\\bÓcd/ó¶ó+lîcfÝWXµÚ[(é8NñN*m<¡÷áÎÖÇ½Ì¾½Pã ]­ë~JeÝ.µ#eaô4^n®FsFT=?_~Ôø~\Ð^ùfMµKéÅÛpä%ÌTò©Yò>¬ä²ªJÖd¯_'¶\\tù;=¸Â½ïæOqhîQ.Àò!û×èìó¡¬àí7A®ÆAÅëh@ù<Y7êì·ö|å=ì4D^çp®¶Ê­}0uô3?Ü÷æÀ×9)?ÍO' 8r»L î·¯8;\¢Þ¯gý_Ôÿõ`R}ãIï«(À¦ðÅ\\f-Ûåôg¹h«±¾eããÓ|é0M0°DáÏÈ.ê¸sIätfò}o®Æ ÊÐôµÔ0¤3¼Ïq¨?ä¡¢ÐpPcþZuùøâÀ\ó8ù qX®Ú7ÂP)Û>\\nØÑú~2|u"J6â\\r»Ô\\bî»êÖÄÝÕMÛÑãÂÝ7äUB$Zþç¸N\\tI>Ê¿¥C?¶V}^h¤Å¸ÃÓÆøt:ËÍ0­&ë=½ù&4ÓìÜjÕÇh¸à£UMqh#sTÀkuäcÒüúOìºNM\\f¸f¼³s¡Qà  ¿ú`¿õ7V5l=¦ÉÀIFæ 9¼Iß\\bìÚB5}ÿx{ópË%Su[f5ã£jðfZE*ª¬Ùõ³|¡+ñL"O·"/$ðPaG§*8\\nuÚÛí(TÚ¾çáYé@TÌJûV"ä¥»}k+ûÐ ÈF«ÿ-»¯Dé& |æPr'3}èÑÏìÔ¢ÊÔÞÎCkìC²©¡¢h¢6«ÌÅÇ&4OÎÍ?:ÐmÐ\\f&È§L¶ª7È²¿"Ä@x¼wß(\\t~§ö8ú¾Èæ~~"RÆ¨v¬#Ý¡¨Mûüÿ¢gðLUÖF;þHò%ûkµ9¿uê.ïÎÒX UçL¦û³w*þÄwbæ<ä$ú÷iÆo«1kÂzá.Ê_å=½è´Õ\\r¢_â3åäòÅTx:B /£´@göÑ0Á±ÝõÄÊ;þºCïlm;Ð¸0Aò¤C|Ú¤mÚ\\fµø¯Âì§ã¾q]VoÍl³>ÞL¼ÿ`²­ñ»=×2Ò¢dÁÔ<o³QY(10ÒØG:tËûVVËÍKL6Æv~jCò\\bÄ«òÉÃWMòK²ñK5¢ÚLÑ)AüÖ¥d¢:¬µ7êä<-¥ÒW¶,"ûÙAhA@°ãU+Ó"D ¢|ã)ª8Ñ­ùZ ÈpûÌGÃTqRiï1Ã¢±Ë¡Ã¿ìÝ¡OÖ!âÞ¤\\fì­)}I¨«ðUúÿãp=ís6OµCº)9?>úÿÞ7Ä¥6Mª}ÛÚ-r2ûÏÊö-4´ãsµñÖ-1ùq¼E¹Ó3_\\rp -i$®ª¡ÚWJ6/3ØZü Z1ô@2L÷\\fc^T`í[[4À½a{t«Ø¸L¿Å\\bèM%9¾g^ÐÿÚÛáwbÁE¥HôÔðÊzÜØXAmlÔ$ -kåj&wÅ®}¥}BWÿ^.QÒB:Mÿ:ÄT±\\rõáÙ>%{ü<!¬PµS;¶h×Qûë^Xû&K­ìOrZfX`8KÎèíÎó"mY§WÇæºZ(Óí7)Þu$lùÄ´ !8ü¿ªv:+ïÕüÀv,Ï ÿLK\\t8ibàÊsÍm\\byÙv§ÒÈ«Y.\\nì÷,H\\f­¢áÆ;3-iB¨£ÛtTqÜ¤eÔñ~!bT¯á\\nûÚ)aÎW "Y_ c¯R¨ä}ÁHÓ$Ýß$\\tR5jÐWÃa¿\ñh¹RûwÒGá;gµQ¿1j±·<ËÍr3Jr­$­b}ÿ l»¤³é»µÂ8Æ ¶ü¤#{ÞE´ÍÇjX8ÜzbÄ9@uï(è9\\nÐ¡øaDØQùþÈ\\tuôB3  àü÷ù\ÿ.ÊUeJ2Ú.hwiBÈ«û9Iîí«\@µrøy¥²ë¨Ãà£÷B)Âªóß¬ÙNÐ¢¡=Æ\\nÇH`CÓ«(LYT%¤kY' ð|r¼>FÅcT\\fr2`)ôdf&õ2.ï#5ªri²¾G®m1ó=$_õÀ®Ãp>cµðYÖUÐð3ù!·ôóßÒs0DJØÑ³ É5bø%U$®à c7·ñÿÊ^z:M{0UÖ'.ï¾O%Cä¦ k.C\\tÏ8Å­+¶]ù+\\r¨WÅ£¸r¬´ÝJ×`ÊaºMaa2ÕYP¾Ê»!z¶£~MãtgïDCÁb=ªÚ\\b¶ú-*®¼6FÍûç­ä2hÎ?1øC¾w6Å?÷ð#Ë\\t¨ÖZz\\n4YÎG4bIW©dÆVÀY¬]ØÞ­ÚEçIí`\\b@Å«4à(É©cK·Q#Ömw. 6Åù~g½&¨ç!=iôÐ}×ICvu DvFqÅãq¿³"ém@ÄÎkæ}ÃVÏ~dKvö|gèM\w-é"rRjÖeæJ²»ü{¨Ds9a©ß-:Þýxc[· e.Dñ-âÚÆíÒ¾*ú¦¡[qÍ½l;omhª±_¬:äa³\\béo+çïù1ß5%vÉØGj°Kz¸«íæÐ\\nÊfmz·r>R<vËWÑ¸¥lHË²2à£ýEíißLÜ ¨Iþx\\f:@ígYßÀOÞÃ!!÷Û¡¹Â-B%K¼Ñ_Ø-Ï..KGøñotÿê ¾ðüQ\\f?¸«2ã??×Z÷Y-!<§S÷BRc®®Ä8$]ïÜæø\\t¹e5zzÚ3 \\rh&4y\\b¶ÒÎJ@s&yò+ÍÀ%-\×H5Í»TIJ}tÈtùôéjéûëe_0Úx4kZëÔe{7 îÑþ9XOÍn!fÐÉRÞv²#+§ãòÝÀÖüð¢ÜLfP°]Ï;Üy½ÿÍñÄ -uL³*LÐ4ùÀ1s¸Ùá¼ç-0?N×ÿ§È¨qCjÓõ¯ý}ý³ÿ)# ­C^ms#¤±­@`T¿Ov\\b'wN@|¡:c}Xí-ú2³W>Os>ï2ÅÖàÒÜÝÇ9#-)àußo8ºnJ¤:G'åòÊÅ=Àb£Z,Ka\+n\\n0\\n=m9Aü:$4UÓÏçJàÿÄ©X\\féâÖÞ:ÕóëìqÝ\\n2Á[´xk½N\\rSÖ×uÍ°Bº\\bÿhÙPÎ'\\t©¥f°mêp7¡Ê¹lãÕ?¹¸ÒDóÐÓNg×1vVòn7gÕ¿2'ªäT§èzE_tãA÷g&»Ý0E@+|ã´N\\f>Û¬õ©'ØÃ¡IºO/ôÞY.#.á-zã/\\tß¦bÅÃæÉÊ7ô¥òc±å ß1BaRþ×0W`ùVEñÏ÷±pâ$½)»7®óè¹gc¶ò]+È"qi¬ýü'O©HDêL¦ÂÝHwëüM.Ä$)ØÊ<ýfÔXEo\\f.ìLÛ@\\f¿%Ôs3s\\tPö1ýÍÀN»5^U¦5{NAªÙ.Wî4»SB¥óûø\\f}G®vãP8j\\f³à½^{/pàeØ+wÛ=3Wâ\-$$Íí?×x|WqÜ¶n`K\\n»ëéâ¯(\\tq2Iy!{Lz ?1Gm¸>&NRÙ¸Hbªu8ê\\bÇcÉêcÅ¥NÄ!,m:¯æ¢y&_$ä¨*s°ï¡$°3öGézwê.#²b®ÍíÐ»ÍZmwç Zi;=8æ%M¶Oß¨ÍÅÝX ù¨ ¶Xo\\rýj´<ÊâªÐöH0ÓöFôôÿóû+2ïav\\fBqr5\\rÇ¯#ã[-¹9$<1+@U:~å]¥ëäXA}0ÐNQ\\bEN{ëj@td¶[Ò®íZÃUB&Èæ«|£´ñ¾­ÎkÛ\\b<ÖÎ&ì/ ´LaYJÓ6-_#AÚJ¸Ñ¨c°-¦³òïeÝ>á µèÚVö(»>°\\bI\\\n¤®º[R¯V«ho®#)Þü÷³ö±úê]¯1X©ÍÎÓ8³Ë/CúÄáv¾¦°¹·,¼·\\tÔ§Àúsñ£0Ê®shßNìz@\L\\bt<Áß÷%+#j^ÏfUOÖï% âyné«¾B\µW+Ò[êF¡Î ð¿!®uÄZU$LÝ³}ÀM±d.`INQLÔ2/ \\rÐeõÂóKÿÕÁ¾"0Í*ßc-TÎ7?¹"CU\\bº¦´ 1"$7YÁÙÁ©Ü¨4ðÖHtñAuqkL|`öZ¥øuÒBºMkmó¦¦ð[dÉ9âï©ù²ÅÓp¿qÎ"VÆ|V)J4,Ê#s:¢³ÂMÝ#îbRtûr9pP¨½(^úÓ'
    //   129: dup
    //   130: astore_2
    //   131: invokevirtual length : ()I
    //   134: istore #4
    //   136: sipush #32767
    //   139: istore_1
    //   140: iconst_m1
    //   141: istore_0
    //   142: bipush #94
    //   144: iinc #0, 1
    //   147: aload_2
    //   148: iload_0
    //   149: dup
    //   150: iload_1
    //   151: iadd
    //   152: invokevirtual substring : (II)Ljava/lang/String;
    //   155: iconst_1
    //   156: goto -> 203
    //   159: aload #5
    //   161: swap
    //   162: iload_3
    //   163: iinc #3, 1
    //   166: swap
    //   167: aastore
    //   168: iload_0
    //   169: iload_1
    //   170: iadd
    //   171: dup
    //   172: istore_0
    //   173: iload #4
    //   175: if_icmpge -> 187
    //   178: aload_2
    //   179: iload_0
    //   180: invokevirtual charAt : (I)C
    //   183: istore_1
    //   184: goto -> 142
    //   187: aload #5
    //   189: putstatic burp/Zem.a : [Ljava/lang/String;
    //   192: bipush #9
    //   194: anewarray java/lang/String
    //   197: putstatic burp/Zem.b : [Ljava/lang/String;
    //   200: goto -> 364
    //   203: dup_x2
    //   204: pop
    //   205: invokevirtual toCharArray : ()[C
    //   208: dup_x1
    //   209: arraylength
    //   210: dup_x2
    //   211: pop
    //   212: iconst_0
    //   213: istore #6
    //   215: dup2_x1
    //   216: pop2
    //   217: dup_x2
    //   218: iconst_1
    //   219: if_icmpgt -> 319
    //   222: dup2
    //   223: swap
    //   224: iload #6
    //   226: dup2_x1
    //   227: caload
    //   228: swap
    //   229: iload #6
    //   231: bipush #7
    //   233: irem
    //   234: tableswitch default -> 301, 0 -> 272, 1 -> 277, 2 -> 281, 3 -> 286, 4 -> 291, 5 -> 296
    //   272: bipush #7
    //   274: goto -> 303
    //   277: iconst_3
    //   278: goto -> 303
    //   281: bipush #104
    //   283: goto -> 303
    //   286: bipush #59
    //   288: goto -> 303
    //   291: bipush #55
    //   293: goto -> 303
    //   296: bipush #107
    //   298: goto -> 303
    //   301: bipush #55
    //   303: ixor
    //   304: ixor
    //   305: i2c
    //   306: castore
    //   307: iinc #6, 1
    //   310: dup
    //   311: ifne -> 319
    //   314: dup2
    //   315: dup_x1
    //   316: goto -> 226
    //   319: dup2_x1
    //   320: pop2
    //   321: dup_x2
    //   322: iload #6
    //   324: if_icmpgt -> 222
    //   327: pop
    //   328: new java/lang/String
    //   331: dup_x1
    //   332: swap
    //   333: invokespecial <init> : ([C)V
    //   336: invokevirtual intern : ()Ljava/lang/String;
    //   339: swap
    //   340: pop
    //   341: swap
    //   342: tableswitch default -> 40, 0 -> 99, 1 -> 159
    //   364: sipush #-5946
    //   367: sipush #5033
    //   370: invokestatic a : (II)Ljava/lang/String;
    //   373: putstatic burp/Zem.Zr : Ljava/lang/String;
    //   376: getstatic burp/Zem.Zr : Ljava/lang/String;
    //   379: sipush #-5939
    //   382: sipush #11489
    //   385: invokestatic a : (II)Ljava/lang/String;
    //   388: <illegal opcode> makeConcatWithConstants : (Ljava/lang/String;Ljava/lang/String;)Ljava/lang/String;
    //   393: putstatic burp/Zem.Zr : Ljava/lang/String;
    //   396: new java/math/BigInteger
    //   399: dup
    //   400: iconst_1
    //   401: bipush #32
    //   403: newarray byte
    //   405: dup
    //   406: iconst_0
    //   407: iconst_3
    //   408: bastore
    //   409: dup
    //   410: iconst_1
    //   411: bipush #-31
    //   413: bastore
    //   414: dup
    //   415: iconst_2
    //   416: bipush #87
    //   418: bastore
    //   419: dup
    //   420: iconst_3
    //   421: bipush #77
    //   423: bastore
    //   424: dup
    //   425: iconst_4
    //   426: bipush #11
    //   428: bastore
    //   429: dup
    //   430: iconst_5
    //   431: bipush #-120
    //   433: bastore
    //   434: dup
    //   435: bipush #6
    //   437: bipush #-86
    //   439: bastore
    //   440: dup
    //   441: bipush #7
    //   443: bipush #-98
    //   445: bastore
    //   446: dup
    //   447: bipush #8
    //   449: bipush #38
    //   451: bastore
    //   452: dup
    //   453: bipush #9
    //   455: bipush #-88
    //   457: bastore
    //   458: dup
    //   459: bipush #10
    //   461: bipush #-94
    //   463: bastore
    //   464: dup
    //   465: bipush #11
    //   467: bipush #-99
    //   469: bastore
    //   470: dup
    //   471: bipush #12
    //   473: bipush #77
    //   475: bastore
    //   476: dup
    //   477: bipush #13
    //   479: bipush #-108
    //   481: bastore
    //   482: dup
    //   483: bipush #14
    //   485: bipush #47
    //   487: bastore
    //   488: dup
    //   489: bipush #15
    //   491: bipush #102
    //   493: bastore
    //   494: dup
    //   495: bipush #16
    //   497: bipush #101
    //   499: bastore
    //   500: dup
    //   501: bipush #17
    //   503: bipush #121
    //   505: bastore
    //   506: dup
    //   507: bipush #18
    //   509: bipush #-24
    //   511: bastore
    //   512: dup
    //   513: bipush #19
    //   515: bipush #-55
    //   517: bastore
    //   518: dup
    //   519: bipush #20
    //   521: bipush #-36
    //   523: bastore
    //   524: dup
    //   525: bipush #21
    //   527: bipush #80
    //   529: bastore
    //   530: dup
    //   531: bipush #22
    //   533: bipush #-75
    //   535: bastore
    //   536: dup
    //   537: bipush #23
    //   539: bipush #105
    //   541: bastore
    //   542: dup
    //   543: bipush #24
    //   545: bipush #32
    //   547: bastore
    //   548: dup
    //   549: bipush #25
    //   551: bipush #-114
    //   553: bastore
    //   554: dup
    //   555: bipush #26
    //   557: bipush #-72
    //   559: bastore
    //   560: dup
    //   561: bipush #27
    //   563: bipush #15
    //   565: bastore
    //   566: dup
    //   567: bipush #28
    //   569: bipush #-19
    //   571: bastore
    //   572: dup
    //   573: bipush #29
    //   575: bipush #-127
    //   577: bastore
    //   578: dup
    //   579: bipush #30
    //   581: bipush #-10
    //   583: bastore
    //   584: dup
    //   585: bipush #31
    //   587: bipush #-45
    //   589: bastore
    //   590: invokespecial <init> : (I[B)V
    //   593: putstatic burp/Zem.Zo : Ljava/lang/Object;
    //   596: return
  }
  
  private static Throwable a(Throwable paramThrowable) {
    return paramThrowable;
  }
  
  private static String a(int paramInt1, int paramInt2) {
    int i = (paramInt1 ^ 0xFFFFE8CE) & 0xFFFF;
    if (b[i] == null) {
      char[] arrayOfChar = a[i].toCharArray();
      switch (arrayOfChar[0] & 0xFF) {
        case 0:
        
        case 1:
        
        case 2:
        
        case 3:
        
        case 4:
        
        case 5:
        
        case 6:
        
        case 7:
        
        case 8:
        
        case 9:
        
        case 10:
        
        case 11:
        
        case 12:
        
        case 13:
        
        case 14:
        
        case 15:
        
        case 16:
        
        case 17:
        
        case 18:
        
        case 19:
        
        case 20:
        
        case 21:
        
        case 22:
        
        case 23:
        
        case 24:
        
        case 25:
        
        case 26:
        
        case 27:
        
        case 28:
        
        case 29:
        
        case 30:
        
        case 31:
        
        case 32:
        
        case 33:
        
        case 34:
        
        case 35:
        
        case 36:
        
        case 37:
        
        case 38:
        
        case 39:
        
        case 40:
        
        case 41:
        
        case 42:
        
        case 43:
        
        case 44:
        
        case 45:
        
        case 46:
        
        case 47:
        
        case 48:
        
        case 49:
        
        case 50:
        
        case 51:
        
        case 52:
        
        case 53:
        
        case 54:
        
        case 55:
        
        case 56:
        
        case 57:
        
        case 58:
        
        case 59:
        
        case 60:
        
        case 61:
        
        case 62:
        
        case 63:
        
        case 64:
        
        case 65:
        
        case 66:
        
        case 67:
        
        case 68:
        
        case 69:
        
        case 70:
        
        case 71:
        
        case 72:
        
        case 73:
        
        case 74:
        
        case 75:
        
        case 76:
        
        case 77:
        
        case 78:
        
        case 79:
        
        case 80:
        
        case 81:
        
        case 82:
        
        case 83:
        
        case 84:
        
        case 85:
        
        case 86:
        
        case 87:
        
        case 88:
        
        case 89:
        
        case 90:
        
        case 91:
        
        case 92:
        
        case 93:
        
        case 94:
        
        case 95:
        
        case 96:
        
        case 97:
        
        case 98:
        
        case 99:
        
        case 100:
        
        case 101:
        
        case 102:
        
        case 103:
        
        case 104:
        
        case 105:
        
        case 106:
        
        case 107:
        
        case 108:
        
        case 109:
        
        case 110:
        
        case 111:
        
        case 112:
        
        case 113:
        
        case 114:
        
        case 115:
        
        case 116:
        
        case 117:
        
        case 118:
        
        case 119:
        
        case 120:
        
        case 121:
        
        case 122:
        
        case 123:
        
        case 124:
        
        case 125:
        
        case 126:
        
        case 127:
        
        case 128:
        
        case 129:
        
        case 130:
        
        case 131:
        
        case 132:
        
        case 133:
        
        case 134:
        
        case 135:
        
        case 136:
        
        case 137:
        
        case 138:
        
        case 139:
        
        case 140:
        
        case 141:
        
        case 142:
        
        case 143:
        
        case 144:
        
        case 145:
        
        case 146:
        
        case 147:
        
        case 148:
        
        case 149:
        
        case 150:
        
        case 151:
        
        case 152:
        
        case 153:
        
        case 154:
        
        case 155:
        
        case 156:
        
        case 157:
        
        case 158:
        
        case 159:
        
        case 160:
        
        case 161:
        
        case 162:
        
        case 163:
        
        case 164:
        
        case 165:
        
        case 166:
        
        case 167:
        
        case 168:
        
        case 169:
        
        case 170:
        
        case 171:
        
        case 172:
        
        case 173:
        
        case 174:
        
        case 175:
        
        case 176:
        
        case 177:
        
        case 178:
        
        case 179:
        
        case 180:
        
        case 181:
        
        case 182:
        
        case 183:
        
        case 184:
        
        case 185:
        
        case 186:
        
        case 187:
        
        case 188:
        
        case 189:
        
        case 190:
        
        case 191:
        
        case 192:
        
        case 193:
        
        case 194:
        
        case 195:
        
        case 196:
        
        case 197:
        
        case 198:
        
        case 199:
        
        case 200:
        
        case 201:
        
        case 202:
        
        case 203:
        
        case 204:
        
        case 205:
        
        case 206:
        
        case 207:
        
        case 208:
        
        case 209:
        
        case 210:
        
        case 211:
        
        case 212:
        
        case 213:
        
        case 214:
        
        case 215:
        
        case 216:
        
        case 217:
        
        case 218:
        
        case 219:
        
        case 220:
        
        case 221:
        
        case 222:
        
        case 223:
        
        case 224:
        
        case 225:
        
        case 226:
        
        case 227:
        
        case 228:
        
        case 229:
        
        case 230:
        
        case 231:
        
        case 232:
        
        case 233:
        
        case 234:
        
        case 235:
        
        case 236:
        
        case 237:
        
        case 238:
        
        case 239:
        
        case 240:
        
        case 241:
        
        case 242:
        
        case 243:
        
        case 244:
        
        case 245:
        
        case 246:
        
        case 247:
        
        case 248:
        
        case 249:
        
        case 250:
        
        case 251:
        
        case 252:
        
        case 253:
        
        case 254:
        
        default:
          break;
      } 
      byte b1 = 97;
      int j = (paramInt2 & 0xFF) - b1;
      if (j < 0)
        j += 256; 
      int k = ((paramInt2 & 0xFFFF) >>> 8) - b1;
      if (k < 0)
        k += 256; 
      for (byte b2 = 0; b2 < arrayOfChar.length; b2++) {
        int m = b2 % 2;
        if (m == 0) {
          arrayOfChar[b2] = (char)(arrayOfChar[b2] ^ j);
          j = ((j >>> 3 | j << 5) ^ arrayOfChar[b2]) & 0xFF;
        } else {
          arrayOfChar[b2] = (char)(arrayOfChar[b2] ^ k);
          k = ((k >>> 3 | k << 5) ^ arrayOfChar[b2]) & 0xFF;
        } 
      } 
      b[i] = (new String(arrayOfChar)).intern();
    } 
    return b[i];
  }
}


/* Location:              C:\Program Files\BurpSuitePro\burpsuite_pro.jar!\burp\Zem.class
 * Java compiler version: 21 (65.0)
 * JD-Core Version:       1.1.3
 */