package burp;

import java.math.BigInteger;

class Zenr extends ClassLoader {
  static Object ZA;
  
  static String Z_;
  
  private static final String[] a;
  
  private static final String[] b;
  
  static void Zx(Object paramObject) {
    Zxn4.ZQ = a(12692, 30319);
    Zxn4.Zx = new BigInteger(a(12675, -22494));
    boolean bool = Zt2e.ZN();
    try {
      try {
        if (Ztq4.Zb.charAt(Math.abs(((BigInteger)Zscz.ZN).intValue() % 32)) <= Zrkd.ZL.charAt(Math.abs(((BigInteger)Zql.Zt).intValue() % 32))) {
          try {
            Zb0q.ZS(Class.forName(a(12678, -3375)));
            if (!bool)
              Zgq_.Zv(Class.forName(a(12698, 12355))); 
          } catch (Throwable throwable) {
            throw a(null);
          } 
          return;
        } 
      } catch (Throwable throwable) {
        throw a(null);
      } 
      Zgq_.Zv(Class.forName(a(12698, 12355)));
    } catch (Throwable throwable) {}
  }
  
  static boolean ZH(Object[] paramArrayOfObject, Object paramObject) throws Throwable {
    // Byte code:
    //   0: invokestatic ZN : ()Z
    //   3: istore_2
    //   4: getstatic burp/Zkjj.Zh : Ljava/lang/Object;
    //   7: checkcast java/math/BigInteger
    //   10: invokevirtual toByteArray : ()[B
    //   13: astore_3
    //   14: bipush #64
    //   16: newarray byte
    //   18: dup
    //   19: iconst_0
    //   20: bipush #-128
    //   22: bastore
    //   23: dup
    //   24: iconst_1
    //   25: iconst_0
    //   26: bastore
    //   27: dup
    //   28: iconst_2
    //   29: iconst_0
    //   30: bastore
    //   31: dup
    //   32: iconst_3
    //   33: iconst_0
    //   34: bastore
    //   35: dup
    //   36: iconst_4
    //   37: iconst_0
    //   38: bastore
    //   39: dup
    //   40: iconst_5
    //   41: iconst_0
    //   42: bastore
    //   43: dup
    //   44: bipush #6
    //   46: iconst_0
    //   47: bastore
    //   48: dup
    //   49: bipush #7
    //   51: iconst_0
    //   52: bastore
    //   53: dup
    //   54: bipush #8
    //   56: iconst_0
    //   57: bastore
    //   58: dup
    //   59: bipush #9
    //   61: iconst_0
    //   62: bastore
    //   63: dup
    //   64: bipush #10
    //   66: iconst_0
    //   67: bastore
    //   68: dup
    //   69: bipush #11
    //   71: iconst_0
    //   72: bastore
    //   73: dup
    //   74: bipush #12
    //   76: iconst_0
    //   77: bastore
    //   78: dup
    //   79: bipush #13
    //   81: iconst_0
    //   82: bastore
    //   83: dup
    //   84: bipush #14
    //   86: iconst_0
    //   87: bastore
    //   88: dup
    //   89: bipush #15
    //   91: iconst_0
    //   92: bastore
    //   93: dup
    //   94: bipush #16
    //   96: iconst_0
    //   97: bastore
    //   98: dup
    //   99: bipush #17
    //   101: iconst_0
    //   102: bastore
    //   103: dup
    //   104: bipush #18
    //   106: iconst_0
    //   107: bastore
    //   108: dup
    //   109: bipush #19
    //   111: iconst_0
    //   112: bastore
    //   113: dup
    //   114: bipush #20
    //   116: iconst_0
    //   117: bastore
    //   118: dup
    //   119: bipush #21
    //   121: iconst_0
    //   122: bastore
    //   123: dup
    //   124: bipush #22
    //   126: iconst_0
    //   127: bastore
    //   128: dup
    //   129: bipush #23
    //   131: iconst_0
    //   132: bastore
    //   133: dup
    //   134: bipush #24
    //   136: iconst_0
    //   137: bastore
    //   138: dup
    //   139: bipush #25
    //   141: iconst_0
    //   142: bastore
    //   143: dup
    //   144: bipush #26
    //   146: iconst_0
    //   147: bastore
    //   148: dup
    //   149: bipush #27
    //   151: iconst_0
    //   152: bastore
    //   153: dup
    //   154: bipush #28
    //   156: iconst_0
    //   157: bastore
    //   158: dup
    //   159: bipush #29
    //   161: iconst_0
    //   162: bastore
    //   163: dup
    //   164: bipush #30
    //   166: iconst_0
    //   167: bastore
    //   168: dup
    //   169: bipush #31
    //   171: iconst_0
    //   172: bastore
    //   173: dup
    //   174: bipush #32
    //   176: iconst_0
    //   177: bastore
    //   178: dup
    //   179: bipush #33
    //   181: iconst_0
    //   182: bastore
    //   183: dup
    //   184: bipush #34
    //   186: iconst_0
    //   187: bastore
    //   188: dup
    //   189: bipush #35
    //   191: iconst_0
    //   192: bastore
    //   193: dup
    //   194: bipush #36
    //   196: iconst_0
    //   197: bastore
    //   198: dup
    //   199: bipush #37
    //   201: iconst_0
    //   202: bastore
    //   203: dup
    //   204: bipush #38
    //   206: iconst_0
    //   207: bastore
    //   208: dup
    //   209: bipush #39
    //   211: iconst_0
    //   212: bastore
    //   213: dup
    //   214: bipush #40
    //   216: iconst_0
    //   217: bastore
    //   218: dup
    //   219: bipush #41
    //   221: iconst_0
    //   222: bastore
    //   223: dup
    //   224: bipush #42
    //   226: iconst_0
    //   227: bastore
    //   228: dup
    //   229: bipush #43
    //   231: iconst_0
    //   232: bastore
    //   233: dup
    //   234: bipush #44
    //   236: iconst_0
    //   237: bastore
    //   238: dup
    //   239: bipush #45
    //   241: iconst_0
    //   242: bastore
    //   243: dup
    //   244: bipush #46
    //   246: iconst_0
    //   247: bastore
    //   248: dup
    //   249: bipush #47
    //   251: iconst_0
    //   252: bastore
    //   253: dup
    //   254: bipush #48
    //   256: iconst_0
    //   257: bastore
    //   258: dup
    //   259: bipush #49
    //   261: iconst_0
    //   262: bastore
    //   263: dup
    //   264: bipush #50
    //   266: iconst_0
    //   267: bastore
    //   268: dup
    //   269: bipush #51
    //   271: iconst_0
    //   272: bastore
    //   273: dup
    //   274: bipush #52
    //   276: iconst_0
    //   277: bastore
    //   278: dup
    //   279: bipush #53
    //   281: iconst_0
    //   282: bastore
    //   283: dup
    //   284: bipush #54
    //   286: iconst_0
    //   287: bastore
    //   288: dup
    //   289: bipush #55
    //   291: iconst_0
    //   292: bastore
    //   293: dup
    //   294: bipush #56
    //   296: iconst_0
    //   297: bastore
    //   298: dup
    //   299: bipush #57
    //   301: iconst_0
    //   302: bastore
    //   303: dup
    //   304: bipush #58
    //   306: iconst_0
    //   307: bastore
    //   308: dup
    //   309: bipush #59
    //   311: iconst_0
    //   312: bastore
    //   313: dup
    //   314: bipush #60
    //   316: iconst_0
    //   317: bastore
    //   318: dup
    //   319: bipush #61
    //   321: iconst_0
    //   322: bastore
    //   323: dup
    //   324: bipush #62
    //   326: iconst_0
    //   327: bastore
    //   328: dup
    //   329: bipush #63
    //   331: iconst_0
    //   332: bastore
    //   333: astore #5
    //   335: bipush #64
    //   337: newarray int
    //   339: dup
    //   340: iconst_0
    //   341: ldc 1116352408
    //   343: iastore
    //   344: dup
    //   345: iconst_1
    //   346: ldc 1899447441
    //   348: iastore
    //   349: dup
    //   350: iconst_2
    //   351: ldc -1245643825
    //   353: iastore
    //   354: dup
    //   355: iconst_3
    //   356: ldc -373957723
    //   358: iastore
    //   359: dup
    //   360: iconst_4
    //   361: ldc 961987163
    //   363: iastore
    //   364: dup
    //   365: iconst_5
    //   366: ldc 1508970993
    //   368: iastore
    //   369: dup
    //   370: bipush #6
    //   372: ldc -1841331548
    //   374: iastore
    //   375: dup
    //   376: bipush #7
    //   378: ldc -1424204075
    //   380: iastore
    //   381: dup
    //   382: bipush #8
    //   384: ldc -670586216
    //   386: iastore
    //   387: dup
    //   388: bipush #9
    //   390: ldc 310598401
    //   392: iastore
    //   393: dup
    //   394: bipush #10
    //   396: ldc 607225278
    //   398: iastore
    //   399: dup
    //   400: bipush #11
    //   402: ldc 1426881987
    //   404: iastore
    //   405: dup
    //   406: bipush #12
    //   408: ldc 1925078388
    //   410: iastore
    //   411: dup
    //   412: bipush #13
    //   414: ldc -2132889090
    //   416: iastore
    //   417: dup
    //   418: bipush #14
    //   420: ldc -1680079193
    //   422: iastore
    //   423: dup
    //   424: bipush #15
    //   426: ldc -1046744716
    //   428: iastore
    //   429: dup
    //   430: bipush #16
    //   432: ldc -459576895
    //   434: iastore
    //   435: dup
    //   436: bipush #17
    //   438: ldc -272742522
    //   440: iastore
    //   441: dup
    //   442: bipush #18
    //   444: ldc 264347078
    //   446: iastore
    //   447: dup
    //   448: bipush #19
    //   450: ldc 604807628
    //   452: iastore
    //   453: dup
    //   454: bipush #20
    //   456: ldc 770255983
    //   458: iastore
    //   459: dup
    //   460: bipush #21
    //   462: ldc 1249150122
    //   464: iastore
    //   465: dup
    //   466: bipush #22
    //   468: ldc 1555081692
    //   470: iastore
    //   471: dup
    //   472: bipush #23
    //   474: ldc 1996064986
    //   476: iastore
    //   477: dup
    //   478: bipush #24
    //   480: ldc -1740746414
    //   482: iastore
    //   483: dup
    //   484: bipush #25
    //   486: ldc -1473132947
    //   488: iastore
    //   489: dup
    //   490: bipush #26
    //   492: ldc -1341970488
    //   494: iastore
    //   495: dup
    //   496: bipush #27
    //   498: ldc -1084653625
    //   500: iastore
    //   501: dup
    //   502: bipush #28
    //   504: ldc -958395405
    //   506: iastore
    //   507: dup
    //   508: bipush #29
    //   510: ldc -710438585
    //   512: iastore
    //   513: dup
    //   514: bipush #30
    //   516: ldc 113926993
    //   518: iastore
    //   519: dup
    //   520: bipush #31
    //   522: ldc 338241895
    //   524: iastore
    //   525: dup
    //   526: bipush #32
    //   528: ldc 666307205
    //   530: iastore
    //   531: dup
    //   532: bipush #33
    //   534: ldc 773529912
    //   536: iastore
    //   537: dup
    //   538: bipush #34
    //   540: ldc 1294757372
    //   542: iastore
    //   543: dup
    //   544: bipush #35
    //   546: ldc 1396182291
    //   548: iastore
    //   549: dup
    //   550: bipush #36
    //   552: ldc 1695183700
    //   554: iastore
    //   555: dup
    //   556: bipush #37
    //   558: ldc 1986661051
    //   560: iastore
    //   561: dup
    //   562: bipush #38
    //   564: ldc -2117940946
    //   566: iastore
    //   567: dup
    //   568: bipush #39
    //   570: ldc -1838011259
    //   572: iastore
    //   573: dup
    //   574: bipush #40
    //   576: ldc -1564481375
    //   578: iastore
    //   579: dup
    //   580: bipush #41
    //   582: ldc -1474664885
    //   584: iastore
    //   585: dup
    //   586: bipush #42
    //   588: ldc -1035236496
    //   590: iastore
    //   591: dup
    //   592: bipush #43
    //   594: ldc -949202525
    //   596: iastore
    //   597: dup
    //   598: bipush #44
    //   600: ldc -778901479
    //   602: iastore
    //   603: dup
    //   604: bipush #45
    //   606: ldc -694614492
    //   608: iastore
    //   609: dup
    //   610: bipush #46
    //   612: ldc -200395387
    //   614: iastore
    //   615: dup
    //   616: bipush #47
    //   618: ldc 275423344
    //   620: iastore
    //   621: dup
    //   622: bipush #48
    //   624: ldc 430227734
    //   626: iastore
    //   627: dup
    //   628: bipush #49
    //   630: ldc 506948616
    //   632: iastore
    //   633: dup
    //   634: bipush #50
    //   636: ldc 659060556
    //   638: iastore
    //   639: dup
    //   640: bipush #51
    //   642: ldc 883997877
    //   644: iastore
    //   645: dup
    //   646: bipush #52
    //   648: ldc 958139571
    //   650: iastore
    //   651: dup
    //   652: bipush #53
    //   654: ldc 1322822218
    //   656: iastore
    //   657: dup
    //   658: bipush #54
    //   660: ldc 1537002063
    //   662: iastore
    //   663: dup
    //   664: bipush #55
    //   666: ldc 1747873779
    //   668: iastore
    //   669: dup
    //   670: bipush #56
    //   672: ldc 1955562222
    //   674: iastore
    //   675: dup
    //   676: bipush #57
    //   678: ldc 2024104815
    //   680: iastore
    //   681: dup
    //   682: bipush #58
    //   684: ldc -2067236844
    //   686: iastore
    //   687: dup
    //   688: bipush #59
    //   690: ldc -1933114872
    //   692: iastore
    //   693: dup
    //   694: bipush #60
    //   696: ldc -1866530822
    //   698: iastore
    //   699: dup
    //   700: bipush #61
    //   702: ldc -1538233109
    //   704: iastore
    //   705: dup
    //   706: bipush #62
    //   708: ldc -1090935817
    //   710: iastore
    //   711: dup
    //   712: bipush #63
    //   714: ldc -965641998
    //   716: iastore
    //   717: astore #6
    //   719: iconst_2
    //   720: newarray int
    //   722: dup
    //   723: iconst_0
    //   724: iconst_0
    //   725: iastore
    //   726: dup
    //   727: iconst_1
    //   728: iconst_0
    //   729: iastore
    //   730: astore #7
    //   732: bipush #8
    //   734: newarray int
    //   736: dup
    //   737: iconst_0
    //   738: ldc 1779033703
    //   740: iastore
    //   741: dup
    //   742: iconst_1
    //   743: ldc -1150833019
    //   745: iastore
    //   746: dup
    //   747: iconst_2
    //   748: ldc 1013904242
    //   750: iastore
    //   751: dup
    //   752: iconst_3
    //   753: ldc -1521486534
    //   755: iastore
    //   756: dup
    //   757: iconst_4
    //   758: ldc 1359893119
    //   760: iastore
    //   761: dup
    //   762: iconst_5
    //   763: ldc -1694144372
    //   765: iastore
    //   766: dup
    //   767: bipush #6
    //   769: ldc 528734635
    //   771: iastore
    //   772: dup
    //   773: bipush #7
    //   775: ldc 1541459225
    //   777: iastore
    //   778: astore #8
    //   780: bipush #64
    //   782: newarray byte
    //   784: astore #9
    //   786: bipush #64
    //   788: newarray byte
    //   790: astore #10
    //   792: aload_3
    //   793: arraylength
    //   794: istore #11
    //   796: aload #7
    //   798: iconst_0
    //   799: iaload
    //   800: bipush #63
    //   802: iand
    //   803: istore #12
    //   805: aload #7
    //   807: iconst_0
    //   808: dup2
    //   809: iaload
    //   810: iload #11
    //   812: iadd
    //   813: iastore
    //   814: aload #7
    //   816: iconst_0
    //   817: dup2
    //   818: iaload
    //   819: iconst_m1
    //   820: iand
    //   821: iastore
    //   822: aload #7
    //   824: iconst_0
    //   825: iaload
    //   826: iload #11
    //   828: if_icmpge -> 846
    //   831: aload #7
    //   833: iconst_1
    //   834: dup2
    //   835: iaload
    //   836: iconst_1
    //   837: iadd
    //   838: iastore
    //   839: goto -> 846
    //   842: invokestatic a : (Ljava/lang/Throwable;)Ljava/lang/Throwable;
    //   845: athrow
    //   846: iconst_0
    //   847: istore #13
    //   849: iload #11
    //   851: bipush #64
    //   853: if_icmplt -> 1462
    //   856: iconst_0
    //   857: istore #14
    //   859: iload #14
    //   861: bipush #64
    //   863: if_icmpge -> 885
    //   866: aload #10
    //   868: iload #14
    //   870: aload_3
    //   871: iload #13
    //   873: iload #14
    //   875: iadd
    //   876: baload
    //   877: bastore
    //   878: iinc #14, 1
    //   881: iload_2
    //   882: ifne -> 859
    //   885: bipush #64
    //   887: newarray int
    //   889: astore #14
    //   891: bipush #8
    //   893: newarray int
    //   895: astore #15
    //   897: iconst_0
    //   898: istore #16
    //   900: iload #16
    //   902: bipush #8
    //   904: if_icmpge -> 924
    //   907: aload #15
    //   909: iload #16
    //   911: aload #8
    //   913: iload #16
    //   915: iaload
    //   916: iastore
    //   917: iinc #16, 1
    //   920: iload_2
    //   921: ifne -> 900
    //   924: iconst_0
    //   925: istore #16
    //   927: iload #16
    //   929: bipush #64
    //   931: if_icmpge -> 1422
    //   934: iload #16
    //   936: bipush #16
    //   938: if_icmpge -> 1019
    //   941: aload #14
    //   943: iload #16
    //   945: aload #10
    //   947: iconst_4
    //   948: iload #16
    //   950: imul
    //   951: baload
    //   952: sipush #255
    //   955: iand
    //   956: bipush #24
    //   958: ishl
    //   959: aload #10
    //   961: iconst_4
    //   962: iload #16
    //   964: imul
    //   965: iconst_1
    //   966: iadd
    //   967: baload
    //   968: sipush #255
    //   971: iand
    //   972: bipush #16
    //   974: ishl
    //   975: ior
    //   976: aload #10
    //   978: iconst_4
    //   979: iload #16
    //   981: imul
    //   982: iconst_2
    //   983: iadd
    //   984: baload
    //   985: sipush #255
    //   988: iand
    //   989: bipush #8
    //   991: ishl
    //   992: ior
    //   993: aload #10
    //   995: iconst_4
    //   996: iload #16
    //   998: imul
    //   999: iconst_3
    //   1000: iadd
    //   1001: baload
    //   1002: sipush #255
    //   1005: iand
    //   1006: ior
    //   1007: iastore
    //   1008: iload_2
    //   1009: ifne -> 1162
    //   1012: goto -> 1019
    //   1015: invokestatic a : (Ljava/lang/Throwable;)Ljava/lang/Throwable;
    //   1018: athrow
    //   1019: aload #14
    //   1021: iload #16
    //   1023: aload #14
    //   1025: iload #16
    //   1027: iconst_2
    //   1028: isub
    //   1029: iaload
    //   1030: bipush #17
    //   1032: iushr
    //   1033: aload #14
    //   1035: iload #16
    //   1037: iconst_2
    //   1038: isub
    //   1039: iaload
    //   1040: bipush #15
    //   1042: ishl
    //   1043: ior
    //   1044: aload #14
    //   1046: iload #16
    //   1048: iconst_2
    //   1049: isub
    //   1050: iaload
    //   1051: bipush #19
    //   1053: iushr
    //   1054: aload #14
    //   1056: iload #16
    //   1058: iconst_2
    //   1059: isub
    //   1060: iaload
    //   1061: bipush #13
    //   1063: ishl
    //   1064: ior
    //   1065: ixor
    //   1066: aload #14
    //   1068: iload #16
    //   1070: iconst_2
    //   1071: isub
    //   1072: iaload
    //   1073: bipush #10
    //   1075: iushr
    //   1076: ixor
    //   1077: aload #14
    //   1079: iload #16
    //   1081: bipush #7
    //   1083: isub
    //   1084: iaload
    //   1085: iadd
    //   1086: aload #14
    //   1088: iload #16
    //   1090: bipush #15
    //   1092: isub
    //   1093: iaload
    //   1094: bipush #7
    //   1096: iushr
    //   1097: aload #14
    //   1099: iload #16
    //   1101: bipush #15
    //   1103: isub
    //   1104: iaload
    //   1105: bipush #25
    //   1107: ishl
    //   1108: ior
    //   1109: aload #14
    //   1111: iload #16
    //   1113: bipush #15
    //   1115: isub
    //   1116: iaload
    //   1117: bipush #18
    //   1119: iushr
    //   1120: aload #14
    //   1122: iload #16
    //   1124: bipush #15
    //   1126: isub
    //   1127: iaload
    //   1128: bipush #14
    //   1130: ishl
    //   1131: ior
    //   1132: ixor
    //   1133: aload #14
    //   1135: iload #16
    //   1137: bipush #15
    //   1139: isub
    //   1140: iaload
    //   1141: iconst_3
    //   1142: iushr
    //   1143: ixor
    //   1144: iadd
    //   1145: aload #14
    //   1147: iload #16
    //   1149: bipush #16
    //   1151: isub
    //   1152: iaload
    //   1153: iadd
    //   1154: iastore
    //   1155: goto -> 1162
    //   1158: invokestatic a : (Ljava/lang/Throwable;)Ljava/lang/Throwable;
    //   1161: athrow
    //   1162: aload #15
    //   1164: bipush #7
    //   1166: iaload
    //   1167: aload #15
    //   1169: iconst_4
    //   1170: iaload
    //   1171: bipush #6
    //   1173: iushr
    //   1174: aload #15
    //   1176: iconst_4
    //   1177: iaload
    //   1178: bipush #26
    //   1180: ishl
    //   1181: ior
    //   1182: aload #15
    //   1184: iconst_4
    //   1185: iaload
    //   1186: bipush #11
    //   1188: iushr
    //   1189: aload #15
    //   1191: iconst_4
    //   1192: iaload
    //   1193: bipush #21
    //   1195: ishl
    //   1196: ior
    //   1197: ixor
    //   1198: aload #15
    //   1200: iconst_4
    //   1201: iaload
    //   1202: bipush #25
    //   1204: iushr
    //   1205: aload #15
    //   1207: iconst_4
    //   1208: iaload
    //   1209: bipush #7
    //   1211: ishl
    //   1212: ior
    //   1213: ixor
    //   1214: iadd
    //   1215: aload #15
    //   1217: bipush #6
    //   1219: iaload
    //   1220: aload #15
    //   1222: iconst_4
    //   1223: iaload
    //   1224: aload #15
    //   1226: iconst_5
    //   1227: iaload
    //   1228: aload #15
    //   1230: bipush #6
    //   1232: iaload
    //   1233: ixor
    //   1234: iand
    //   1235: ixor
    //   1236: iadd
    //   1237: aload #6
    //   1239: iload #16
    //   1241: iaload
    //   1242: iadd
    //   1243: aload #14
    //   1245: iload #16
    //   1247: iaload
    //   1248: iadd
    //   1249: istore #17
    //   1251: aload #15
    //   1253: iconst_0
    //   1254: iaload
    //   1255: iconst_2
    //   1256: iushr
    //   1257: aload #15
    //   1259: iconst_0
    //   1260: iaload
    //   1261: bipush #30
    //   1263: ishl
    //   1264: ior
    //   1265: aload #15
    //   1267: iconst_0
    //   1268: iaload
    //   1269: bipush #13
    //   1271: iushr
    //   1272: aload #15
    //   1274: iconst_0
    //   1275: iaload
    //   1276: bipush #19
    //   1278: ishl
    //   1279: ior
    //   1280: ixor
    //   1281: aload #15
    //   1283: iconst_0
    //   1284: iaload
    //   1285: bipush #22
    //   1287: iushr
    //   1288: aload #15
    //   1290: iconst_0
    //   1291: iaload
    //   1292: bipush #10
    //   1294: ishl
    //   1295: ior
    //   1296: ixor
    //   1297: aload #15
    //   1299: iconst_0
    //   1300: iaload
    //   1301: aload #15
    //   1303: iconst_1
    //   1304: iaload
    //   1305: iand
    //   1306: aload #15
    //   1308: iconst_2
    //   1309: iaload
    //   1310: aload #15
    //   1312: iconst_0
    //   1313: iaload
    //   1314: aload #15
    //   1316: iconst_1
    //   1317: iaload
    //   1318: ior
    //   1319: iand
    //   1320: ior
    //   1321: iadd
    //   1322: istore #18
    //   1324: aload #15
    //   1326: iconst_3
    //   1327: dup2
    //   1328: iaload
    //   1329: iload #17
    //   1331: iadd
    //   1332: iastore
    //   1333: aload #15
    //   1335: bipush #7
    //   1337: iload #17
    //   1339: iload #18
    //   1341: iadd
    //   1342: iastore
    //   1343: aload #15
    //   1345: bipush #7
    //   1347: iaload
    //   1348: istore #17
    //   1350: aload #15
    //   1352: bipush #7
    //   1354: aload #15
    //   1356: bipush #6
    //   1358: iaload
    //   1359: iastore
    //   1360: aload #15
    //   1362: bipush #6
    //   1364: aload #15
    //   1366: iconst_5
    //   1367: iaload
    //   1368: iastore
    //   1369: aload #15
    //   1371: iconst_5
    //   1372: aload #15
    //   1374: iconst_4
    //   1375: iaload
    //   1376: iastore
    //   1377: aload #15
    //   1379: iconst_4
    //   1380: aload #15
    //   1382: iconst_3
    //   1383: iaload
    //   1384: iastore
    //   1385: aload #15
    //   1387: iconst_3
    //   1388: aload #15
    //   1390: iconst_2
    //   1391: iaload
    //   1392: iastore
    //   1393: aload #15
    //   1395: iconst_2
    //   1396: aload #15
    //   1398: iconst_1
    //   1399: iaload
    //   1400: iastore
    //   1401: aload #15
    //   1403: iconst_1
    //   1404: aload #15
    //   1406: iconst_0
    //   1407: iaload
    //   1408: iastore
    //   1409: aload #15
    //   1411: iconst_0
    //   1412: iload #17
    //   1414: iastore
    //   1415: iinc #16, 1
    //   1418: iload_2
    //   1419: ifne -> 927
    //   1422: iconst_0
    //   1423: istore #16
    //   1425: iload #16
    //   1427: bipush #8
    //   1429: if_icmpge -> 1452
    //   1432: aload #8
    //   1434: iload #16
    //   1436: dup2
    //   1437: iaload
    //   1438: aload #15
    //   1440: iload #16
    //   1442: iaload
    //   1443: iadd
    //   1444: iastore
    //   1445: iinc #16, 1
    //   1448: iload_2
    //   1449: ifne -> 1425
    //   1452: iinc #13, 64
    //   1455: iinc #11, -64
    //   1458: iload_2
    //   1459: ifne -> 849
    //   1462: iload #11
    //   1464: ifle -> 1499
    //   1467: iconst_0
    //   1468: istore #14
    //   1470: iload #14
    //   1472: iload #11
    //   1474: if_icmpge -> 1499
    //   1477: aload #9
    //   1479: iload #12
    //   1481: iload #14
    //   1483: iadd
    //   1484: aload_3
    //   1485: iload #13
    //   1487: iload #14
    //   1489: iadd
    //   1490: baload
    //   1491: bastore
    //   1492: iinc #14, 1
    //   1495: iload_2
    //   1496: ifne -> 1470
    //   1499: aload #7
    //   1501: iconst_0
    //   1502: iaload
    //   1503: bipush #29
    //   1505: iushr
    //   1506: aload #7
    //   1508: iconst_1
    //   1509: iaload
    //   1510: iconst_3
    //   1511: ishl
    //   1512: ior
    //   1513: istore #14
    //   1515: aload #7
    //   1517: iconst_0
    //   1518: iaload
    //   1519: iconst_3
    //   1520: ishl
    //   1521: istore #15
    //   1523: aload #7
    //   1525: iconst_0
    //   1526: iaload
    //   1527: bipush #63
    //   1529: iand
    //   1530: istore #16
    //   1532: iload #16
    //   1534: bipush #56
    //   1536: if_icmpge -> 1551
    //   1539: bipush #56
    //   1541: iload #16
    //   1543: isub
    //   1544: goto -> 1556
    //   1547: invokestatic a : (Ljava/lang/Throwable;)Ljava/lang/Throwable;
    //   1550: athrow
    //   1551: bipush #120
    //   1553: iload #16
    //   1555: isub
    //   1556: istore #17
    //   1558: aload #7
    //   1560: iconst_0
    //   1561: iaload
    //   1562: bipush #63
    //   1564: iand
    //   1565: istore #12
    //   1567: bipush #64
    //   1569: iload #12
    //   1571: isub
    //   1572: istore #18
    //   1574: aload #7
    //   1576: iconst_0
    //   1577: dup2
    //   1578: iaload
    //   1579: iload #17
    //   1581: iadd
    //   1582: iastore
    //   1583: aload #7
    //   1585: iconst_0
    //   1586: dup2
    //   1587: iaload
    //   1588: iconst_m1
    //   1589: iand
    //   1590: iastore
    //   1591: aload #7
    //   1593: iconst_0
    //   1594: iaload
    //   1595: iload #17
    //   1597: if_icmpge -> 1615
    //   1600: aload #7
    //   1602: iconst_1
    //   1603: dup2
    //   1604: iaload
    //   1605: iconst_1
    //   1606: iadd
    //   1607: iastore
    //   1608: goto -> 1615
    //   1611: invokestatic a : (Ljava/lang/Throwable;)Ljava/lang/Throwable;
    //   1614: athrow
    //   1615: iconst_0
    //   1616: istore #13
    //   1618: iload #12
    //   1620: ifle -> 2251
    //   1623: iload #17
    //   1625: iload #18
    //   1627: if_icmplt -> 2251
    //   1630: goto -> 1637
    //   1633: invokestatic a : (Ljava/lang/Throwable;)Ljava/lang/Throwable;
    //   1636: athrow
    //   1637: iconst_0
    //   1638: istore #19
    //   1640: iload #19
    //   1642: iload #18
    //   1644: if_icmpge -> 1667
    //   1647: aload #9
    //   1649: iload #12
    //   1651: iload #19
    //   1653: iadd
    //   1654: aload #5
    //   1656: iload #19
    //   1658: baload
    //   1659: bastore
    //   1660: iinc #19, 1
    //   1663: iload_2
    //   1664: ifne -> 1640
    //   1667: bipush #64
    //   1669: newarray int
    //   1671: astore #19
    //   1673: bipush #8
    //   1675: newarray int
    //   1677: astore #20
    //   1679: iconst_0
    //   1680: istore #21
    //   1682: iload #21
    //   1684: bipush #8
    //   1686: if_icmpge -> 1706
    //   1689: aload #20
    //   1691: iload #21
    //   1693: aload #8
    //   1695: iload #21
    //   1697: iaload
    //   1698: iastore
    //   1699: iinc #21, 1
    //   1702: iload_2
    //   1703: ifne -> 1682
    //   1706: iconst_0
    //   1707: istore #21
    //   1709: iload #21
    //   1711: bipush #64
    //   1713: if_icmpge -> 2204
    //   1716: iload #21
    //   1718: bipush #16
    //   1720: if_icmpge -> 1801
    //   1723: aload #19
    //   1725: iload #21
    //   1727: aload #9
    //   1729: iconst_4
    //   1730: iload #21
    //   1732: imul
    //   1733: baload
    //   1734: sipush #255
    //   1737: iand
    //   1738: bipush #24
    //   1740: ishl
    //   1741: aload #9
    //   1743: iconst_4
    //   1744: iload #21
    //   1746: imul
    //   1747: iconst_1
    //   1748: iadd
    //   1749: baload
    //   1750: sipush #255
    //   1753: iand
    //   1754: bipush #16
    //   1756: ishl
    //   1757: ior
    //   1758: aload #9
    //   1760: iconst_4
    //   1761: iload #21
    //   1763: imul
    //   1764: iconst_2
    //   1765: iadd
    //   1766: baload
    //   1767: sipush #255
    //   1770: iand
    //   1771: bipush #8
    //   1773: ishl
    //   1774: ior
    //   1775: aload #9
    //   1777: iconst_4
    //   1778: iload #21
    //   1780: imul
    //   1781: iconst_3
    //   1782: iadd
    //   1783: baload
    //   1784: sipush #255
    //   1787: iand
    //   1788: ior
    //   1789: iastore
    //   1790: iload_2
    //   1791: ifne -> 1944
    //   1794: goto -> 1801
    //   1797: invokestatic a : (Ljava/lang/Throwable;)Ljava/lang/Throwable;
    //   1800: athrow
    //   1801: aload #19
    //   1803: iload #21
    //   1805: aload #19
    //   1807: iload #21
    //   1809: iconst_2
    //   1810: isub
    //   1811: iaload
    //   1812: bipush #17
    //   1814: iushr
    //   1815: aload #19
    //   1817: iload #21
    //   1819: iconst_2
    //   1820: isub
    //   1821: iaload
    //   1822: bipush #15
    //   1824: ishl
    //   1825: ior
    //   1826: aload #19
    //   1828: iload #21
    //   1830: iconst_2
    //   1831: isub
    //   1832: iaload
    //   1833: bipush #19
    //   1835: iushr
    //   1836: aload #19
    //   1838: iload #21
    //   1840: iconst_2
    //   1841: isub
    //   1842: iaload
    //   1843: bipush #13
    //   1845: ishl
    //   1846: ior
    //   1847: ixor
    //   1848: aload #19
    //   1850: iload #21
    //   1852: iconst_2
    //   1853: isub
    //   1854: iaload
    //   1855: bipush #10
    //   1857: iushr
    //   1858: ixor
    //   1859: aload #19
    //   1861: iload #21
    //   1863: bipush #7
    //   1865: isub
    //   1866: iaload
    //   1867: iadd
    //   1868: aload #19
    //   1870: iload #21
    //   1872: bipush #15
    //   1874: isub
    //   1875: iaload
    //   1876: bipush #7
    //   1878: iushr
    //   1879: aload #19
    //   1881: iload #21
    //   1883: bipush #15
    //   1885: isub
    //   1886: iaload
    //   1887: bipush #25
    //   1889: ishl
    //   1890: ior
    //   1891: aload #19
    //   1893: iload #21
    //   1895: bipush #15
    //   1897: isub
    //   1898: iaload
    //   1899: bipush #18
    //   1901: iushr
    //   1902: aload #19
    //   1904: iload #21
    //   1906: bipush #15
    //   1908: isub
    //   1909: iaload
    //   1910: bipush #14
    //   1912: ishl
    //   1913: ior
    //   1914: ixor
    //   1915: aload #19
    //   1917: iload #21
    //   1919: bipush #15
    //   1921: isub
    //   1922: iaload
    //   1923: iconst_3
    //   1924: iushr
    //   1925: ixor
    //   1926: iadd
    //   1927: aload #19
    //   1929: iload #21
    //   1931: bipush #16
    //   1933: isub
    //   1934: iaload
    //   1935: iadd
    //   1936: iastore
    //   1937: goto -> 1944
    //   1940: invokestatic a : (Ljava/lang/Throwable;)Ljava/lang/Throwable;
    //   1943: athrow
    //   1944: aload #20
    //   1946: bipush #7
    //   1948: iaload
    //   1949: aload #20
    //   1951: iconst_4
    //   1952: iaload
    //   1953: bipush #6
    //   1955: iushr
    //   1956: aload #20
    //   1958: iconst_4
    //   1959: iaload
    //   1960: bipush #26
    //   1962: ishl
    //   1963: ior
    //   1964: aload #20
    //   1966: iconst_4
    //   1967: iaload
    //   1968: bipush #11
    //   1970: iushr
    //   1971: aload #20
    //   1973: iconst_4
    //   1974: iaload
    //   1975: bipush #21
    //   1977: ishl
    //   1978: ior
    //   1979: ixor
    //   1980: aload #20
    //   1982: iconst_4
    //   1983: iaload
    //   1984: bipush #25
    //   1986: iushr
    //   1987: aload #20
    //   1989: iconst_4
    //   1990: iaload
    //   1991: bipush #7
    //   1993: ishl
    //   1994: ior
    //   1995: ixor
    //   1996: iadd
    //   1997: aload #20
    //   1999: bipush #6
    //   2001: iaload
    //   2002: aload #20
    //   2004: iconst_4
    //   2005: iaload
    //   2006: aload #20
    //   2008: iconst_5
    //   2009: iaload
    //   2010: aload #20
    //   2012: bipush #6
    //   2014: iaload
    //   2015: ixor
    //   2016: iand
    //   2017: ixor
    //   2018: iadd
    //   2019: aload #6
    //   2021: iload #21
    //   2023: iaload
    //   2024: iadd
    //   2025: aload #19
    //   2027: iload #21
    //   2029: iaload
    //   2030: iadd
    //   2031: istore #22
    //   2033: aload #20
    //   2035: iconst_0
    //   2036: iaload
    //   2037: iconst_2
    //   2038: iushr
    //   2039: aload #20
    //   2041: iconst_0
    //   2042: iaload
    //   2043: bipush #30
    //   2045: ishl
    //   2046: ior
    //   2047: aload #20
    //   2049: iconst_0
    //   2050: iaload
    //   2051: bipush #13
    //   2053: iushr
    //   2054: aload #20
    //   2056: iconst_0
    //   2057: iaload
    //   2058: bipush #19
    //   2060: ishl
    //   2061: ior
    //   2062: ixor
    //   2063: aload #20
    //   2065: iconst_0
    //   2066: iaload
    //   2067: bipush #22
    //   2069: iushr
    //   2070: aload #20
    //   2072: iconst_0
    //   2073: iaload
    //   2074: bipush #10
    //   2076: ishl
    //   2077: ior
    //   2078: ixor
    //   2079: aload #20
    //   2081: iconst_0
    //   2082: iaload
    //   2083: aload #20
    //   2085: iconst_1
    //   2086: iaload
    //   2087: iand
    //   2088: aload #20
    //   2090: iconst_2
    //   2091: iaload
    //   2092: aload #20
    //   2094: iconst_0
    //   2095: iaload
    //   2096: aload #20
    //   2098: iconst_1
    //   2099: iaload
    //   2100: ior
    //   2101: iand
    //   2102: ior
    //   2103: iadd
    //   2104: istore #23
    //   2106: aload #20
    //   2108: iconst_3
    //   2109: dup2
    //   2110: iaload
    //   2111: iload #22
    //   2113: iadd
    //   2114: iastore
    //   2115: aload #20
    //   2117: bipush #7
    //   2119: iload #22
    //   2121: iload #23
    //   2123: iadd
    //   2124: iastore
    //   2125: aload #20
    //   2127: bipush #7
    //   2129: iaload
    //   2130: istore #22
    //   2132: aload #20
    //   2134: bipush #7
    //   2136: aload #20
    //   2138: bipush #6
    //   2140: iaload
    //   2141: iastore
    //   2142: aload #20
    //   2144: bipush #6
    //   2146: aload #20
    //   2148: iconst_5
    //   2149: iaload
    //   2150: iastore
    //   2151: aload #20
    //   2153: iconst_5
    //   2154: aload #20
    //   2156: iconst_4
    //   2157: iaload
    //   2158: iastore
    //   2159: aload #20
    //   2161: iconst_4
    //   2162: aload #20
    //   2164: iconst_3
    //   2165: iaload
    //   2166: iastore
    //   2167: aload #20
    //   2169: iconst_3
    //   2170: aload #20
    //   2172: iconst_2
    //   2173: iaload
    //   2174: iastore
    //   2175: aload #20
    //   2177: iconst_2
    //   2178: aload #20
    //   2180: iconst_1
    //   2181: iaload
    //   2182: iastore
    //   2183: aload #20
    //   2185: iconst_1
    //   2186: aload #20
    //   2188: iconst_0
    //   2189: iaload
    //   2190: iastore
    //   2191: aload #20
    //   2193: iconst_0
    //   2194: iload #22
    //   2196: iastore
    //   2197: iinc #21, 1
    //   2200: iload_2
    //   2201: ifne -> 1709
    //   2204: iconst_0
    //   2205: istore #21
    //   2207: iload #21
    //   2209: bipush #8
    //   2211: if_icmpge -> 2234
    //   2214: aload #8
    //   2216: iload #21
    //   2218: dup2
    //   2219: iaload
    //   2220: aload #20
    //   2222: iload #21
    //   2224: iaload
    //   2225: iadd
    //   2226: iastore
    //   2227: iinc #21, 1
    //   2230: iload_2
    //   2231: ifne -> 2207
    //   2234: iload #13
    //   2236: iload #18
    //   2238: iadd
    //   2239: istore #13
    //   2241: iload #17
    //   2243: iload #18
    //   2245: isub
    //   2246: istore #17
    //   2248: iconst_0
    //   2249: istore #12
    //   2251: iload #17
    //   2253: bipush #64
    //   2255: if_icmplt -> 2865
    //   2258: iconst_0
    //   2259: istore #19
    //   2261: iload #19
    //   2263: bipush #64
    //   2265: if_icmpge -> 2288
    //   2268: aload #10
    //   2270: iload #19
    //   2272: aload #5
    //   2274: iload #13
    //   2276: iload #19
    //   2278: iadd
    //   2279: baload
    //   2280: bastore
    //   2281: iinc #19, 1
    //   2284: iload_2
    //   2285: ifne -> 2261
    //   2288: bipush #64
    //   2290: newarray int
    //   2292: astore #19
    //   2294: bipush #8
    //   2296: newarray int
    //   2298: astore #20
    //   2300: iconst_0
    //   2301: istore #21
    //   2303: iload #21
    //   2305: bipush #8
    //   2307: if_icmpge -> 2327
    //   2310: aload #20
    //   2312: iload #21
    //   2314: aload #8
    //   2316: iload #21
    //   2318: iaload
    //   2319: iastore
    //   2320: iinc #21, 1
    //   2323: iload_2
    //   2324: ifne -> 2303
    //   2327: iconst_0
    //   2328: istore #21
    //   2330: iload #21
    //   2332: bipush #64
    //   2334: if_icmpge -> 2825
    //   2337: iload #21
    //   2339: bipush #16
    //   2341: if_icmpge -> 2422
    //   2344: aload #19
    //   2346: iload #21
    //   2348: aload #10
    //   2350: iconst_4
    //   2351: iload #21
    //   2353: imul
    //   2354: baload
    //   2355: sipush #255
    //   2358: iand
    //   2359: bipush #24
    //   2361: ishl
    //   2362: aload #10
    //   2364: iconst_4
    //   2365: iload #21
    //   2367: imul
    //   2368: iconst_1
    //   2369: iadd
    //   2370: baload
    //   2371: sipush #255
    //   2374: iand
    //   2375: bipush #16
    //   2377: ishl
    //   2378: ior
    //   2379: aload #10
    //   2381: iconst_4
    //   2382: iload #21
    //   2384: imul
    //   2385: iconst_2
    //   2386: iadd
    //   2387: baload
    //   2388: sipush #255
    //   2391: iand
    //   2392: bipush #8
    //   2394: ishl
    //   2395: ior
    //   2396: aload #10
    //   2398: iconst_4
    //   2399: iload #21
    //   2401: imul
    //   2402: iconst_3
    //   2403: iadd
    //   2404: baload
    //   2405: sipush #255
    //   2408: iand
    //   2409: ior
    //   2410: iastore
    //   2411: iload_2
    //   2412: ifne -> 2565
    //   2415: goto -> 2422
    //   2418: invokestatic a : (Ljava/lang/Throwable;)Ljava/lang/Throwable;
    //   2421: athrow
    //   2422: aload #19
    //   2424: iload #21
    //   2426: aload #19
    //   2428: iload #21
    //   2430: iconst_2
    //   2431: isub
    //   2432: iaload
    //   2433: bipush #17
    //   2435: iushr
    //   2436: aload #19
    //   2438: iload #21
    //   2440: iconst_2
    //   2441: isub
    //   2442: iaload
    //   2443: bipush #15
    //   2445: ishl
    //   2446: ior
    //   2447: aload #19
    //   2449: iload #21
    //   2451: iconst_2
    //   2452: isub
    //   2453: iaload
    //   2454: bipush #19
    //   2456: iushr
    //   2457: aload #19
    //   2459: iload #21
    //   2461: iconst_2
    //   2462: isub
    //   2463: iaload
    //   2464: bipush #13
    //   2466: ishl
    //   2467: ior
    //   2468: ixor
    //   2469: aload #19
    //   2471: iload #21
    //   2473: iconst_2
    //   2474: isub
    //   2475: iaload
    //   2476: bipush #10
    //   2478: iushr
    //   2479: ixor
    //   2480: aload #19
    //   2482: iload #21
    //   2484: bipush #7
    //   2486: isub
    //   2487: iaload
    //   2488: iadd
    //   2489: aload #19
    //   2491: iload #21
    //   2493: bipush #15
    //   2495: isub
    //   2496: iaload
    //   2497: bipush #7
    //   2499: iushr
    //   2500: aload #19
    //   2502: iload #21
    //   2504: bipush #15
    //   2506: isub
    //   2507: iaload
    //   2508: bipush #25
    //   2510: ishl
    //   2511: ior
    //   2512: aload #19
    //   2514: iload #21
    //   2516: bipush #15
    //   2518: isub
    //   2519: iaload
    //   2520: bipush #18
    //   2522: iushr
    //   2523: aload #19
    //   2525: iload #21
    //   2527: bipush #15
    //   2529: isub
    //   2530: iaload
    //   2531: bipush #14
    //   2533: ishl
    //   2534: ior
    //   2535: ixor
    //   2536: aload #19
    //   2538: iload #21
    //   2540: bipush #15
    //   2542: isub
    //   2543: iaload
    //   2544: iconst_3
    //   2545: iushr
    //   2546: ixor
    //   2547: iadd
    //   2548: aload #19
    //   2550: iload #21
    //   2552: bipush #16
    //   2554: isub
    //   2555: iaload
    //   2556: iadd
    //   2557: iastore
    //   2558: goto -> 2565
    //   2561: invokestatic a : (Ljava/lang/Throwable;)Ljava/lang/Throwable;
    //   2564: athrow
    //   2565: aload #20
    //   2567: bipush #7
    //   2569: iaload
    //   2570: aload #20
    //   2572: iconst_4
    //   2573: iaload
    //   2574: bipush #6
    //   2576: iushr
    //   2577: aload #20
    //   2579: iconst_4
    //   2580: iaload
    //   2581: bipush #26
    //   2583: ishl
    //   2584: ior
    //   2585: aload #20
    //   2587: iconst_4
    //   2588: iaload
    //   2589: bipush #11
    //   2591: iushr
    //   2592: aload #20
    //   2594: iconst_4
    //   2595: iaload
    //   2596: bipush #21
    //   2598: ishl
    //   2599: ior
    //   2600: ixor
    //   2601: aload #20
    //   2603: iconst_4
    //   2604: iaload
    //   2605: bipush #25
    //   2607: iushr
    //   2608: aload #20
    //   2610: iconst_4
    //   2611: iaload
    //   2612: bipush #7
    //   2614: ishl
    //   2615: ior
    //   2616: ixor
    //   2617: iadd
    //   2618: aload #20
    //   2620: bipush #6
    //   2622: iaload
    //   2623: aload #20
    //   2625: iconst_4
    //   2626: iaload
    //   2627: aload #20
    //   2629: iconst_5
    //   2630: iaload
    //   2631: aload #20
    //   2633: bipush #6
    //   2635: iaload
    //   2636: ixor
    //   2637: iand
    //   2638: ixor
    //   2639: iadd
    //   2640: aload #6
    //   2642: iload #21
    //   2644: iaload
    //   2645: iadd
    //   2646: aload #19
    //   2648: iload #21
    //   2650: iaload
    //   2651: iadd
    //   2652: istore #22
    //   2654: aload #20
    //   2656: iconst_0
    //   2657: iaload
    //   2658: iconst_2
    //   2659: iushr
    //   2660: aload #20
    //   2662: iconst_0
    //   2663: iaload
    //   2664: bipush #30
    //   2666: ishl
    //   2667: ior
    //   2668: aload #20
    //   2670: iconst_0
    //   2671: iaload
    //   2672: bipush #13
    //   2674: iushr
    //   2675: aload #20
    //   2677: iconst_0
    //   2678: iaload
    //   2679: bipush #19
    //   2681: ishl
    //   2682: ior
    //   2683: ixor
    //   2684: aload #20
    //   2686: iconst_0
    //   2687: iaload
    //   2688: bipush #22
    //   2690: iushr
    //   2691: aload #20
    //   2693: iconst_0
    //   2694: iaload
    //   2695: bipush #10
    //   2697: ishl
    //   2698: ior
    //   2699: ixor
    //   2700: aload #20
    //   2702: iconst_0
    //   2703: iaload
    //   2704: aload #20
    //   2706: iconst_1
    //   2707: iaload
    //   2708: iand
    //   2709: aload #20
    //   2711: iconst_2
    //   2712: iaload
    //   2713: aload #20
    //   2715: iconst_0
    //   2716: iaload
    //   2717: aload #20
    //   2719: iconst_1
    //   2720: iaload
    //   2721: ior
    //   2722: iand
    //   2723: ior
    //   2724: iadd
    //   2725: istore #23
    //   2727: aload #20
    //   2729: iconst_3
    //   2730: dup2
    //   2731: iaload
    //   2732: iload #22
    //   2734: iadd
    //   2735: iastore
    //   2736: aload #20
    //   2738: bipush #7
    //   2740: iload #22
    //   2742: iload #23
    //   2744: iadd
    //   2745: iastore
    //   2746: aload #20
    //   2748: bipush #7
    //   2750: iaload
    //   2751: istore #22
    //   2753: aload #20
    //   2755: bipush #7
    //   2757: aload #20
    //   2759: bipush #6
    //   2761: iaload
    //   2762: iastore
    //   2763: aload #20
    //   2765: bipush #6
    //   2767: aload #20
    //   2769: iconst_5
    //   2770: iaload
    //   2771: iastore
    //   2772: aload #20
    //   2774: iconst_5
    //   2775: aload #20
    //   2777: iconst_4
    //   2778: iaload
    //   2779: iastore
    //   2780: aload #20
    //   2782: iconst_4
    //   2783: aload #20
    //   2785: iconst_3
    //   2786: iaload
    //   2787: iastore
    //   2788: aload #20
    //   2790: iconst_3
    //   2791: aload #20
    //   2793: iconst_2
    //   2794: iaload
    //   2795: iastore
    //   2796: aload #20
    //   2798: iconst_2
    //   2799: aload #20
    //   2801: iconst_1
    //   2802: iaload
    //   2803: iastore
    //   2804: aload #20
    //   2806: iconst_1
    //   2807: aload #20
    //   2809: iconst_0
    //   2810: iaload
    //   2811: iastore
    //   2812: aload #20
    //   2814: iconst_0
    //   2815: iload #22
    //   2817: iastore
    //   2818: iinc #21, 1
    //   2821: iload_2
    //   2822: ifne -> 2330
    //   2825: iconst_0
    //   2826: istore #21
    //   2828: iload #21
    //   2830: bipush #8
    //   2832: if_icmpge -> 2855
    //   2835: aload #8
    //   2837: iload #21
    //   2839: dup2
    //   2840: iaload
    //   2841: aload #20
    //   2843: iload #21
    //   2845: iaload
    //   2846: iadd
    //   2847: iastore
    //   2848: iinc #21, 1
    //   2851: iload_2
    //   2852: ifne -> 2828
    //   2855: iinc #13, 64
    //   2858: iinc #17, -64
    //   2861: iload_2
    //   2862: ifne -> 2251
    //   2865: iload #17
    //   2867: ifle -> 2903
    //   2870: iconst_0
    //   2871: istore #19
    //   2873: iload #19
    //   2875: iload #17
    //   2877: if_icmpge -> 2903
    //   2880: aload #9
    //   2882: iload #12
    //   2884: iload #19
    //   2886: iadd
    //   2887: aload #5
    //   2889: iload #13
    //   2891: iload #19
    //   2893: iadd
    //   2894: baload
    //   2895: bastore
    //   2896: iinc #19, 1
    //   2899: iload_2
    //   2900: ifne -> 2873
    //   2903: bipush #8
    //   2905: newarray byte
    //   2907: astore #19
    //   2909: aload #19
    //   2911: iconst_0
    //   2912: iload #14
    //   2914: bipush #24
    //   2916: iushr
    //   2917: i2b
    //   2918: bastore
    //   2919: aload #19
    //   2921: iconst_1
    //   2922: iload #14
    //   2924: bipush #16
    //   2926: iushr
    //   2927: i2b
    //   2928: bastore
    //   2929: aload #19
    //   2931: iconst_2
    //   2932: iload #14
    //   2934: bipush #8
    //   2936: iushr
    //   2937: i2b
    //   2938: bastore
    //   2939: aload #19
    //   2941: iconst_3
    //   2942: iload #14
    //   2944: i2b
    //   2945: bastore
    //   2946: aload #19
    //   2948: iconst_4
    //   2949: iload #15
    //   2951: bipush #24
    //   2953: iushr
    //   2954: i2b
    //   2955: bastore
    //   2956: aload #19
    //   2958: iconst_5
    //   2959: iload #15
    //   2961: bipush #16
    //   2963: iushr
    //   2964: i2b
    //   2965: bastore
    //   2966: aload #19
    //   2968: bipush #6
    //   2970: iload #15
    //   2972: bipush #8
    //   2974: iushr
    //   2975: i2b
    //   2976: bastore
    //   2977: aload #19
    //   2979: bipush #7
    //   2981: iload #15
    //   2983: i2b
    //   2984: bastore
    //   2985: bipush #8
    //   2987: istore #11
    //   2989: aload #7
    //   2991: iconst_0
    //   2992: iaload
    //   2993: bipush #63
    //   2995: iand
    //   2996: istore #12
    //   2998: bipush #64
    //   3000: iload #12
    //   3002: isub
    //   3003: istore #18
    //   3005: aload #7
    //   3007: iconst_0
    //   3008: dup2
    //   3009: iaload
    //   3010: iload #11
    //   3012: iadd
    //   3013: iastore
    //   3014: aload #7
    //   3016: iconst_0
    //   3017: dup2
    //   3018: iaload
    //   3019: iconst_m1
    //   3020: iand
    //   3021: iastore
    //   3022: aload #7
    //   3024: iconst_0
    //   3025: iaload
    //   3026: iload #11
    //   3028: if_icmpge -> 3046
    //   3031: aload #7
    //   3033: iconst_1
    //   3034: dup2
    //   3035: iaload
    //   3036: iconst_1
    //   3037: iadd
    //   3038: iastore
    //   3039: goto -> 3046
    //   3042: invokestatic a : (Ljava/lang/Throwable;)Ljava/lang/Throwable;
    //   3045: athrow
    //   3046: iload #12
    //   3048: ifle -> 3662
    //   3051: iload #11
    //   3053: iload #18
    //   3055: if_icmplt -> 3662
    //   3058: goto -> 3065
    //   3061: invokestatic a : (Ljava/lang/Throwable;)Ljava/lang/Throwable;
    //   3064: athrow
    //   3065: iconst_0
    //   3066: istore #20
    //   3068: iload #20
    //   3070: iload #18
    //   3072: if_icmpge -> 3095
    //   3075: aload #9
    //   3077: iload #12
    //   3079: iload #20
    //   3081: iadd
    //   3082: aload #19
    //   3084: iload #20
    //   3086: baload
    //   3087: bastore
    //   3088: iinc #20, 1
    //   3091: iload_2
    //   3092: ifne -> 3068
    //   3095: bipush #64
    //   3097: newarray int
    //   3099: astore #20
    //   3101: bipush #8
    //   3103: newarray int
    //   3105: astore #21
    //   3107: iconst_0
    //   3108: istore #22
    //   3110: iload #22
    //   3112: bipush #8
    //   3114: if_icmpge -> 3134
    //   3117: aload #21
    //   3119: iload #22
    //   3121: aload #8
    //   3123: iload #22
    //   3125: iaload
    //   3126: iastore
    //   3127: iinc #22, 1
    //   3130: iload_2
    //   3131: ifne -> 3110
    //   3134: iconst_0
    //   3135: istore #22
    //   3137: iload #22
    //   3139: bipush #64
    //   3141: if_icmpge -> 3632
    //   3144: iload #22
    //   3146: bipush #16
    //   3148: if_icmpge -> 3229
    //   3151: aload #20
    //   3153: iload #22
    //   3155: aload #9
    //   3157: iconst_4
    //   3158: iload #22
    //   3160: imul
    //   3161: baload
    //   3162: sipush #255
    //   3165: iand
    //   3166: bipush #24
    //   3168: ishl
    //   3169: aload #9
    //   3171: iconst_4
    //   3172: iload #22
    //   3174: imul
    //   3175: iconst_1
    //   3176: iadd
    //   3177: baload
    //   3178: sipush #255
    //   3181: iand
    //   3182: bipush #16
    //   3184: ishl
    //   3185: ior
    //   3186: aload #9
    //   3188: iconst_4
    //   3189: iload #22
    //   3191: imul
    //   3192: iconst_2
    //   3193: iadd
    //   3194: baload
    //   3195: sipush #255
    //   3198: iand
    //   3199: bipush #8
    //   3201: ishl
    //   3202: ior
    //   3203: aload #9
    //   3205: iconst_4
    //   3206: iload #22
    //   3208: imul
    //   3209: iconst_3
    //   3210: iadd
    //   3211: baload
    //   3212: sipush #255
    //   3215: iand
    //   3216: ior
    //   3217: iastore
    //   3218: iload_2
    //   3219: ifne -> 3372
    //   3222: goto -> 3229
    //   3225: invokestatic a : (Ljava/lang/Throwable;)Ljava/lang/Throwable;
    //   3228: athrow
    //   3229: aload #20
    //   3231: iload #22
    //   3233: aload #20
    //   3235: iload #22
    //   3237: iconst_2
    //   3238: isub
    //   3239: iaload
    //   3240: bipush #17
    //   3242: iushr
    //   3243: aload #20
    //   3245: iload #22
    //   3247: iconst_2
    //   3248: isub
    //   3249: iaload
    //   3250: bipush #15
    //   3252: ishl
    //   3253: ior
    //   3254: aload #20
    //   3256: iload #22
    //   3258: iconst_2
    //   3259: isub
    //   3260: iaload
    //   3261: bipush #19
    //   3263: iushr
    //   3264: aload #20
    //   3266: iload #22
    //   3268: iconst_2
    //   3269: isub
    //   3270: iaload
    //   3271: bipush #13
    //   3273: ishl
    //   3274: ior
    //   3275: ixor
    //   3276: aload #20
    //   3278: iload #22
    //   3280: iconst_2
    //   3281: isub
    //   3282: iaload
    //   3283: bipush #10
    //   3285: iushr
    //   3286: ixor
    //   3287: aload #20
    //   3289: iload #22
    //   3291: bipush #7
    //   3293: isub
    //   3294: iaload
    //   3295: iadd
    //   3296: aload #20
    //   3298: iload #22
    //   3300: bipush #15
    //   3302: isub
    //   3303: iaload
    //   3304: bipush #7
    //   3306: iushr
    //   3307: aload #20
    //   3309: iload #22
    //   3311: bipush #15
    //   3313: isub
    //   3314: iaload
    //   3315: bipush #25
    //   3317: ishl
    //   3318: ior
    //   3319: aload #20
    //   3321: iload #22
    //   3323: bipush #15
    //   3325: isub
    //   3326: iaload
    //   3327: bipush #18
    //   3329: iushr
    //   3330: aload #20
    //   3332: iload #22
    //   3334: bipush #15
    //   3336: isub
    //   3337: iaload
    //   3338: bipush #14
    //   3340: ishl
    //   3341: ior
    //   3342: ixor
    //   3343: aload #20
    //   3345: iload #22
    //   3347: bipush #15
    //   3349: isub
    //   3350: iaload
    //   3351: iconst_3
    //   3352: iushr
    //   3353: ixor
    //   3354: iadd
    //   3355: aload #20
    //   3357: iload #22
    //   3359: bipush #16
    //   3361: isub
    //   3362: iaload
    //   3363: iadd
    //   3364: iastore
    //   3365: goto -> 3372
    //   3368: invokestatic a : (Ljava/lang/Throwable;)Ljava/lang/Throwable;
    //   3371: athrow
    //   3372: aload #21
    //   3374: bipush #7
    //   3376: iaload
    //   3377: aload #21
    //   3379: iconst_4
    //   3380: iaload
    //   3381: bipush #6
    //   3383: iushr
    //   3384: aload #21
    //   3386: iconst_4
    //   3387: iaload
    //   3388: bipush #26
    //   3390: ishl
    //   3391: ior
    //   3392: aload #21
    //   3394: iconst_4
    //   3395: iaload
    //   3396: bipush #11
    //   3398: iushr
    //   3399: aload #21
    //   3401: iconst_4
    //   3402: iaload
    //   3403: bipush #21
    //   3405: ishl
    //   3406: ior
    //   3407: ixor
    //   3408: aload #21
    //   3410: iconst_4
    //   3411: iaload
    //   3412: bipush #25
    //   3414: iushr
    //   3415: aload #21
    //   3417: iconst_4
    //   3418: iaload
    //   3419: bipush #7
    //   3421: ishl
    //   3422: ior
    //   3423: ixor
    //   3424: iadd
    //   3425: aload #21
    //   3427: bipush #6
    //   3429: iaload
    //   3430: aload #21
    //   3432: iconst_4
    //   3433: iaload
    //   3434: aload #21
    //   3436: iconst_5
    //   3437: iaload
    //   3438: aload #21
    //   3440: bipush #6
    //   3442: iaload
    //   3443: ixor
    //   3444: iand
    //   3445: ixor
    //   3446: iadd
    //   3447: aload #6
    //   3449: iload #22
    //   3451: iaload
    //   3452: iadd
    //   3453: aload #20
    //   3455: iload #22
    //   3457: iaload
    //   3458: iadd
    //   3459: istore #23
    //   3461: aload #21
    //   3463: iconst_0
    //   3464: iaload
    //   3465: iconst_2
    //   3466: iushr
    //   3467: aload #21
    //   3469: iconst_0
    //   3470: iaload
    //   3471: bipush #30
    //   3473: ishl
    //   3474: ior
    //   3475: aload #21
    //   3477: iconst_0
    //   3478: iaload
    //   3479: bipush #13
    //   3481: iushr
    //   3482: aload #21
    //   3484: iconst_0
    //   3485: iaload
    //   3486: bipush #19
    //   3488: ishl
    //   3489: ior
    //   3490: ixor
    //   3491: aload #21
    //   3493: iconst_0
    //   3494: iaload
    //   3495: bipush #22
    //   3497: iushr
    //   3498: aload #21
    //   3500: iconst_0
    //   3501: iaload
    //   3502: bipush #10
    //   3504: ishl
    //   3505: ior
    //   3506: ixor
    //   3507: aload #21
    //   3509: iconst_0
    //   3510: iaload
    //   3511: aload #21
    //   3513: iconst_1
    //   3514: iaload
    //   3515: iand
    //   3516: aload #21
    //   3518: iconst_2
    //   3519: iaload
    //   3520: aload #21
    //   3522: iconst_0
    //   3523: iaload
    //   3524: aload #21
    //   3526: iconst_1
    //   3527: iaload
    //   3528: ior
    //   3529: iand
    //   3530: ior
    //   3531: iadd
    //   3532: istore #24
    //   3534: aload #21
    //   3536: iconst_3
    //   3537: dup2
    //   3538: iaload
    //   3539: iload #23
    //   3541: iadd
    //   3542: iastore
    //   3543: aload #21
    //   3545: bipush #7
    //   3547: iload #23
    //   3549: iload #24
    //   3551: iadd
    //   3552: iastore
    //   3553: aload #21
    //   3555: bipush #7
    //   3557: iaload
    //   3558: istore #23
    //   3560: aload #21
    //   3562: bipush #7
    //   3564: aload #21
    //   3566: bipush #6
    //   3568: iaload
    //   3569: iastore
    //   3570: aload #21
    //   3572: bipush #6
    //   3574: aload #21
    //   3576: iconst_5
    //   3577: iaload
    //   3578: iastore
    //   3579: aload #21
    //   3581: iconst_5
    //   3582: aload #21
    //   3584: iconst_4
    //   3585: iaload
    //   3586: iastore
    //   3587: aload #21
    //   3589: iconst_4
    //   3590: aload #21
    //   3592: iconst_3
    //   3593: iaload
    //   3594: iastore
    //   3595: aload #21
    //   3597: iconst_3
    //   3598: aload #21
    //   3600: iconst_2
    //   3601: iaload
    //   3602: iastore
    //   3603: aload #21
    //   3605: iconst_2
    //   3606: aload #21
    //   3608: iconst_1
    //   3609: iaload
    //   3610: iastore
    //   3611: aload #21
    //   3613: iconst_1
    //   3614: aload #21
    //   3616: iconst_0
    //   3617: iaload
    //   3618: iastore
    //   3619: aload #21
    //   3621: iconst_0
    //   3622: iload #23
    //   3624: iastore
    //   3625: iinc #22, 1
    //   3628: iload_2
    //   3629: ifne -> 3137
    //   3632: iconst_0
    //   3633: istore #22
    //   3635: iload #22
    //   3637: bipush #8
    //   3639: if_icmpge -> 3662
    //   3642: aload #8
    //   3644: iload #22
    //   3646: dup2
    //   3647: iaload
    //   3648: aload #21
    //   3650: iload #22
    //   3652: iaload
    //   3653: iadd
    //   3654: iastore
    //   3655: iinc #22, 1
    //   3658: iload_2
    //   3659: ifne -> 3635
    //   3662: bipush #32
    //   3664: newarray byte
    //   3666: astore #4
    //   3668: aload #4
    //   3670: iconst_0
    //   3671: aload #8
    //   3673: iconst_0
    //   3674: iaload
    //   3675: bipush #24
    //   3677: iushr
    //   3678: i2b
    //   3679: bastore
    //   3680: aload #4
    //   3682: iconst_1
    //   3683: aload #8
    //   3685: iconst_0
    //   3686: iaload
    //   3687: bipush #16
    //   3689: iushr
    //   3690: i2b
    //   3691: bastore
    //   3692: aload #4
    //   3694: iconst_2
    //   3695: aload #8
    //   3697: iconst_0
    //   3698: iaload
    //   3699: bipush #8
    //   3701: iushr
    //   3702: i2b
    //   3703: bastore
    //   3704: aload #4
    //   3706: iconst_3
    //   3707: aload #8
    //   3709: iconst_0
    //   3710: iaload
    //   3711: i2b
    //   3712: bastore
    //   3713: aload #4
    //   3715: iconst_4
    //   3716: aload #8
    //   3718: iconst_1
    //   3719: iaload
    //   3720: bipush #24
    //   3722: iushr
    //   3723: i2b
    //   3724: bastore
    //   3725: aload #4
    //   3727: iconst_5
    //   3728: aload #8
    //   3730: iconst_1
    //   3731: iaload
    //   3732: bipush #16
    //   3734: iushr
    //   3735: i2b
    //   3736: bastore
    //   3737: aload #4
    //   3739: bipush #6
    //   3741: aload #8
    //   3743: iconst_1
    //   3744: iaload
    //   3745: bipush #8
    //   3747: iushr
    //   3748: i2b
    //   3749: bastore
    //   3750: aload #4
    //   3752: bipush #7
    //   3754: aload #8
    //   3756: iconst_1
    //   3757: iaload
    //   3758: i2b
    //   3759: bastore
    //   3760: aload #4
    //   3762: bipush #8
    //   3764: aload #8
    //   3766: iconst_2
    //   3767: iaload
    //   3768: bipush #24
    //   3770: iushr
    //   3771: i2b
    //   3772: bastore
    //   3773: aload #4
    //   3775: bipush #9
    //   3777: aload #8
    //   3779: iconst_2
    //   3780: iaload
    //   3781: bipush #16
    //   3783: iushr
    //   3784: i2b
    //   3785: bastore
    //   3786: aload #4
    //   3788: bipush #10
    //   3790: aload #8
    //   3792: iconst_2
    //   3793: iaload
    //   3794: bipush #8
    //   3796: iushr
    //   3797: i2b
    //   3798: bastore
    //   3799: aload #4
    //   3801: bipush #11
    //   3803: aload #8
    //   3805: iconst_2
    //   3806: iaload
    //   3807: i2b
    //   3808: bastore
    //   3809: aload #4
    //   3811: bipush #12
    //   3813: aload #8
    //   3815: iconst_3
    //   3816: iaload
    //   3817: bipush #24
    //   3819: iushr
    //   3820: i2b
    //   3821: bastore
    //   3822: aload #4
    //   3824: bipush #13
    //   3826: aload #8
    //   3828: iconst_3
    //   3829: iaload
    //   3830: bipush #16
    //   3832: iushr
    //   3833: i2b
    //   3834: bastore
    //   3835: aload #4
    //   3837: bipush #14
    //   3839: aload #8
    //   3841: iconst_3
    //   3842: iaload
    //   3843: bipush #8
    //   3845: iushr
    //   3846: i2b
    //   3847: bastore
    //   3848: aload #4
    //   3850: bipush #15
    //   3852: aload #8
    //   3854: iconst_3
    //   3855: iaload
    //   3856: i2b
    //   3857: bastore
    //   3858: aload #4
    //   3860: bipush #16
    //   3862: aload #8
    //   3864: iconst_4
    //   3865: iaload
    //   3866: bipush #24
    //   3868: iushr
    //   3869: i2b
    //   3870: bastore
    //   3871: aload #4
    //   3873: bipush #17
    //   3875: aload #8
    //   3877: iconst_4
    //   3878: iaload
    //   3879: bipush #16
    //   3881: iushr
    //   3882: i2b
    //   3883: bastore
    //   3884: aload #4
    //   3886: bipush #18
    //   3888: aload #8
    //   3890: iconst_4
    //   3891: iaload
    //   3892: bipush #8
    //   3894: iushr
    //   3895: i2b
    //   3896: bastore
    //   3897: aload #4
    //   3899: bipush #19
    //   3901: aload #8
    //   3903: iconst_4
    //   3904: iaload
    //   3905: i2b
    //   3906: bastore
    //   3907: aload #4
    //   3909: bipush #20
    //   3911: aload #8
    //   3913: iconst_5
    //   3914: iaload
    //   3915: bipush #24
    //   3917: iushr
    //   3918: i2b
    //   3919: bastore
    //   3920: aload #4
    //   3922: bipush #21
    //   3924: aload #8
    //   3926: iconst_5
    //   3927: iaload
    //   3928: bipush #16
    //   3930: iushr
    //   3931: i2b
    //   3932: bastore
    //   3933: aload #4
    //   3935: bipush #22
    //   3937: aload #8
    //   3939: iconst_5
    //   3940: iaload
    //   3941: bipush #8
    //   3943: iushr
    //   3944: i2b
    //   3945: bastore
    //   3946: aload #4
    //   3948: bipush #23
    //   3950: aload #8
    //   3952: iconst_5
    //   3953: iaload
    //   3954: i2b
    //   3955: bastore
    //   3956: aload #4
    //   3958: bipush #24
    //   3960: aload #8
    //   3962: bipush #6
    //   3964: iaload
    //   3965: bipush #24
    //   3967: iushr
    //   3968: i2b
    //   3969: bastore
    //   3970: aload #4
    //   3972: bipush #25
    //   3974: aload #8
    //   3976: bipush #6
    //   3978: iaload
    //   3979: bipush #16
    //   3981: iushr
    //   3982: i2b
    //   3983: bastore
    //   3984: aload #4
    //   3986: bipush #26
    //   3988: aload #8
    //   3990: bipush #6
    //   3992: iaload
    //   3993: bipush #8
    //   3995: iushr
    //   3996: i2b
    //   3997: bastore
    //   3998: aload #4
    //   4000: bipush #27
    //   4002: aload #8
    //   4004: bipush #6
    //   4006: iaload
    //   4007: i2b
    //   4008: bastore
    //   4009: aload #4
    //   4011: bipush #28
    //   4013: aload #8
    //   4015: bipush #7
    //   4017: iaload
    //   4018: bipush #24
    //   4020: iushr
    //   4021: i2b
    //   4022: bastore
    //   4023: aload #4
    //   4025: bipush #29
    //   4027: aload #8
    //   4029: bipush #7
    //   4031: iaload
    //   4032: bipush #16
    //   4034: iushr
    //   4035: i2b
    //   4036: bastore
    //   4037: aload #4
    //   4039: bipush #30
    //   4041: aload #8
    //   4043: bipush #7
    //   4045: iaload
    //   4046: bipush #8
    //   4048: iushr
    //   4049: i2b
    //   4050: bastore
    //   4051: aload #4
    //   4053: bipush #31
    //   4055: aload #8
    //   4057: bipush #7
    //   4059: iaload
    //   4060: i2b
    //   4061: bastore
    //   4062: new java/math/BigInteger
    //   4065: dup
    //   4066: aload #4
    //   4068: invokespecial <init> : ([B)V
    //   4071: invokevirtual abs : ()Ljava/math/BigInteger;
    //   4074: putstatic burp/Zlwc.ZG : Ljava/lang/Object;
    //   4077: new java/lang/StringBuilder
    //   4080: dup
    //   4081: invokespecial <init> : ()V
    //   4084: astore_3
    //   4085: iconst_0
    //   4086: istore #4
    //   4088: iload #4
    //   4090: bipush #32
    //   4092: if_icmpge -> 5427
    //   4095: iload #4
    //   4097: tableswitch default -> 5420, 0 -> 4240, 1 -> 4277, 2 -> 4314, 3 -> 4351, 4 -> 4388, 5 -> 4425, 6 -> 4462, 7 -> 4499, 8 -> 4536, 9 -> 4573, 10 -> 4610, 11 -> 4647, 12 -> 4684, 13 -> 4721, 14 -> 4758, 15 -> 4795, 16 -> 4832, 17 -> 4869, 18 -> 4906, 19 -> 4943, 20 -> 4980, 21 -> 5017, 22 -> 5054, 23 -> 5091, 24 -> 5128, 25 -> 5165, 26 -> 5202, 27 -> 5239, 28 -> 5276, 29 -> 5313, 30 -> 5350, 31 -> 5387
    //   4240: aload_3
    //   4241: getstatic burp/Zt0m.ZH : Ljava/lang/String;
    //   4244: getstatic burp/Zzef.Zw : Ljava/lang/Object;
    //   4247: checkcast java/math/BigInteger
    //   4250: invokevirtual intValue : ()I
    //   4253: bipush #32
    //   4255: irem
    //   4256: invokestatic abs : (I)I
    //   4259: invokevirtual charAt : (I)C
    //   4262: invokevirtual append : (C)Ljava/lang/StringBuilder;
    //   4265: pop
    //   4266: iload_2
    //   4267: ifne -> 5420
    //   4270: goto -> 4277
    //   4273: invokestatic a : (Ljava/lang/Throwable;)Ljava/lang/Throwable;
    //   4276: athrow
    //   4277: aload_3
    //   4278: getstatic burp/Zrov.ZU : Ljava/lang/String;
    //   4281: getstatic burp/Zrp2.Zw : Ljava/lang/Object;
    //   4284: checkcast java/math/BigInteger
    //   4287: invokevirtual intValue : ()I
    //   4290: bipush #32
    //   4292: irem
    //   4293: invokestatic abs : (I)I
    //   4296: invokevirtual charAt : (I)C
    //   4299: invokevirtual append : (C)Ljava/lang/StringBuilder;
    //   4302: pop
    //   4303: iload_2
    //   4304: ifne -> 5420
    //   4307: goto -> 4314
    //   4310: invokestatic a : (Ljava/lang/Throwable;)Ljava/lang/Throwable;
    //   4313: athrow
    //   4314: aload_3
    //   4315: getstatic burp/Zl3j.Zr : Ljava/lang/String;
    //   4318: getstatic burp/Zttd.Zi : Ljava/lang/Object;
    //   4321: checkcast java/math/BigInteger
    //   4324: invokevirtual intValue : ()I
    //   4327: bipush #32
    //   4329: irem
    //   4330: invokestatic abs : (I)I
    //   4333: invokevirtual charAt : (I)C
    //   4336: invokevirtual append : (C)Ljava/lang/StringBuilder;
    //   4339: pop
    //   4340: iload_2
    //   4341: ifne -> 5420
    //   4344: goto -> 4351
    //   4347: invokestatic a : (Ljava/lang/Throwable;)Ljava/lang/Throwable;
    //   4350: athrow
    //   4351: aload_3
    //   4352: getstatic burp/Zl1e.Z_ : Ljava/lang/String;
    //   4355: getstatic burp/Zzr8.ZC : Ljava/lang/Object;
    //   4358: checkcast java/math/BigInteger
    //   4361: invokevirtual intValue : ()I
    //   4364: bipush #32
    //   4366: irem
    //   4367: invokestatic abs : (I)I
    //   4370: invokevirtual charAt : (I)C
    //   4373: invokevirtual append : (C)Ljava/lang/StringBuilder;
    //   4376: pop
    //   4377: iload_2
    //   4378: ifne -> 5420
    //   4381: goto -> 4388
    //   4384: invokestatic a : (Ljava/lang/Throwable;)Ljava/lang/Throwable;
    //   4387: athrow
    //   4388: aload_3
    //   4389: getstatic burp/Zgu4.Za : Ljava/lang/String;
    //   4392: getstatic burp/Zesw.ZB : Ljava/lang/Object;
    //   4395: checkcast java/math/BigInteger
    //   4398: invokevirtual intValue : ()I
    //   4401: bipush #32
    //   4403: irem
    //   4404: invokestatic abs : (I)I
    //   4407: invokevirtual charAt : (I)C
    //   4410: invokevirtual append : (C)Ljava/lang/StringBuilder;
    //   4413: pop
    //   4414: iload_2
    //   4415: ifne -> 5420
    //   4418: goto -> 4425
    //   4421: invokestatic a : (Ljava/lang/Throwable;)Ljava/lang/Throwable;
    //   4424: athrow
    //   4425: aload_3
    //   4426: getstatic burp/Zz5e.Zd : Ljava/lang/String;
    //   4429: getstatic burp/Zmz.ZW : Ljava/lang/Object;
    //   4432: checkcast java/math/BigInteger
    //   4435: invokevirtual intValue : ()I
    //   4438: bipush #32
    //   4440: irem
    //   4441: invokestatic abs : (I)I
    //   4444: invokevirtual charAt : (I)C
    //   4447: invokevirtual append : (C)Ljava/lang/StringBuilder;
    //   4450: pop
    //   4451: iload_2
    //   4452: ifne -> 5420
    //   4455: goto -> 4462
    //   4458: invokestatic a : (Ljava/lang/Throwable;)Ljava/lang/Throwable;
    //   4461: athrow
    //   4462: aload_3
    //   4463: getstatic burp/Zsu2.Zq : Ljava/lang/String;
    //   4466: getstatic burp/Zzr8.ZC : Ljava/lang/Object;
    //   4469: checkcast java/math/BigInteger
    //   4472: invokevirtual intValue : ()I
    //   4475: bipush #32
    //   4477: irem
    //   4478: invokestatic abs : (I)I
    //   4481: invokevirtual charAt : (I)C
    //   4484: invokevirtual append : (C)Ljava/lang/StringBuilder;
    //   4487: pop
    //   4488: iload_2
    //   4489: ifne -> 5420
    //   4492: goto -> 4499
    //   4495: invokestatic a : (Ljava/lang/Throwable;)Ljava/lang/Throwable;
    //   4498: athrow
    //   4499: aload_3
    //   4500: getstatic burp/Zer1.ZV : Ljava/lang/String;
    //   4503: getstatic burp/Zb_1.ZK : Ljava/lang/Object;
    //   4506: checkcast java/math/BigInteger
    //   4509: invokevirtual intValue : ()I
    //   4512: bipush #32
    //   4514: irem
    //   4515: invokestatic abs : (I)I
    //   4518: invokevirtual charAt : (I)C
    //   4521: invokevirtual append : (C)Ljava/lang/StringBuilder;
    //   4524: pop
    //   4525: iload_2
    //   4526: ifne -> 5420
    //   4529: goto -> 4536
    //   4532: invokestatic a : (Ljava/lang/Throwable;)Ljava/lang/Throwable;
    //   4535: athrow
    //   4536: aload_3
    //   4537: getstatic burp/Zmkq.Zr : Ljava/lang/String;
    //   4540: getstatic burp/Zrt3.ZG : Ljava/lang/Object;
    //   4543: checkcast java/math/BigInteger
    //   4546: invokevirtual intValue : ()I
    //   4549: bipush #32
    //   4551: irem
    //   4552: invokestatic abs : (I)I
    //   4555: invokevirtual charAt : (I)C
    //   4558: invokevirtual append : (C)Ljava/lang/StringBuilder;
    //   4561: pop
    //   4562: iload_2
    //   4563: ifne -> 5420
    //   4566: goto -> 4573
    //   4569: invokestatic a : (Ljava/lang/Throwable;)Ljava/lang/Throwable;
    //   4572: athrow
    //   4573: aload_3
    //   4574: getstatic burp/Ztdl.ZK : Ljava/lang/String;
    //   4577: getstatic burp/Zmyk.Za : Ljava/lang/Object;
    //   4580: checkcast java/math/BigInteger
    //   4583: invokevirtual intValue : ()I
    //   4586: bipush #32
    //   4588: irem
    //   4589: invokestatic abs : (I)I
    //   4592: invokevirtual charAt : (I)C
    //   4595: invokevirtual append : (C)Ljava/lang/StringBuilder;
    //   4598: pop
    //   4599: iload_2
    //   4600: ifne -> 5420
    //   4603: goto -> 4610
    //   4606: invokestatic a : (Ljava/lang/Throwable;)Ljava/lang/Throwable;
    //   4609: athrow
    //   4610: aload_3
    //   4611: getstatic burp/Zlcc.Zw : Ljava/lang/String;
    //   4614: getstatic burp/Zrwp.Zk : Ljava/lang/Object;
    //   4617: checkcast java/math/BigInteger
    //   4620: invokevirtual intValue : ()I
    //   4623: bipush #32
    //   4625: irem
    //   4626: invokestatic abs : (I)I
    //   4629: invokevirtual charAt : (I)C
    //   4632: invokevirtual append : (C)Ljava/lang/StringBuilder;
    //   4635: pop
    //   4636: iload_2
    //   4637: ifne -> 5420
    //   4640: goto -> 4647
    //   4643: invokestatic a : (Ljava/lang/Throwable;)Ljava/lang/Throwable;
    //   4646: athrow
    //   4647: aload_3
    //   4648: getstatic burp/Zkeb.ZW : Ljava/lang/String;
    //   4651: getstatic burp/Zx4u.Zn : Ljava/lang/Object;
    //   4654: checkcast java/math/BigInteger
    //   4657: invokevirtual intValue : ()I
    //   4660: bipush #32
    //   4662: irem
    //   4663: invokestatic abs : (I)I
    //   4666: invokevirtual charAt : (I)C
    //   4669: invokevirtual append : (C)Ljava/lang/StringBuilder;
    //   4672: pop
    //   4673: iload_2
    //   4674: ifne -> 5420
    //   4677: goto -> 4684
    //   4680: invokestatic a : (Ljava/lang/Throwable;)Ljava/lang/Throwable;
    //   4683: athrow
    //   4684: aload_3
    //   4685: getstatic burp/Zepy.Zg : Ljava/lang/String;
    //   4688: getstatic burp/Zkca.ZQ : Ljava/lang/Object;
    //   4691: checkcast java/math/BigInteger
    //   4694: invokevirtual intValue : ()I
    //   4697: bipush #32
    //   4699: irem
    //   4700: invokestatic abs : (I)I
    //   4703: invokevirtual charAt : (I)C
    //   4706: invokevirtual append : (C)Ljava/lang/StringBuilder;
    //   4709: pop
    //   4710: iload_2
    //   4711: ifne -> 5420
    //   4714: goto -> 4721
    //   4717: invokestatic a : (Ljava/lang/Throwable;)Ljava/lang/Throwable;
    //   4720: athrow
    //   4721: aload_3
    //   4722: getstatic burp/Zk7o.Zb : Ljava/lang/String;
    //   4725: getstatic burp/Ze5h.Zn : Ljava/lang/Object;
    //   4728: checkcast java/math/BigInteger
    //   4731: invokevirtual intValue : ()I
    //   4734: bipush #32
    //   4736: irem
    //   4737: invokestatic abs : (I)I
    //   4740: invokevirtual charAt : (I)C
    //   4743: invokevirtual append : (C)Ljava/lang/StringBuilder;
    //   4746: pop
    //   4747: iload_2
    //   4748: ifne -> 5420
    //   4751: goto -> 4758
    //   4754: invokestatic a : (Ljava/lang/Throwable;)Ljava/lang/Throwable;
    //   4757: athrow
    //   4758: aload_3
    //   4759: getstatic burp/Zezi.Ze : Ljava/lang/String;
    //   4762: getstatic burp/Zrqi.Zb : Ljava/lang/Object;
    //   4765: checkcast java/math/BigInteger
    //   4768: invokevirtual intValue : ()I
    //   4771: bipush #32
    //   4773: irem
    //   4774: invokestatic abs : (I)I
    //   4777: invokevirtual charAt : (I)C
    //   4780: invokevirtual append : (C)Ljava/lang/StringBuilder;
    //   4783: pop
    //   4784: iload_2
    //   4785: ifne -> 5420
    //   4788: goto -> 4795
    //   4791: invokestatic a : (Ljava/lang/Throwable;)Ljava/lang/Throwable;
    //   4794: athrow
    //   4795: aload_3
    //   4796: getstatic burp/Zkkl.Zh : Ljava/lang/String;
    //   4799: getstatic burp/Zt81.ZY : Ljava/lang/Object;
    //   4802: checkcast java/math/BigInteger
    //   4805: invokevirtual intValue : ()I
    //   4808: bipush #32
    //   4810: irem
    //   4811: invokestatic abs : (I)I
    //   4814: invokevirtual charAt : (I)C
    //   4817: invokevirtual append : (C)Ljava/lang/StringBuilder;
    //   4820: pop
    //   4821: iload_2
    //   4822: ifne -> 5420
    //   4825: goto -> 4832
    //   4828: invokestatic a : (Ljava/lang/Throwable;)Ljava/lang/Throwable;
    //   4831: athrow
    //   4832: aload_3
    //   4833: getstatic burp/Ze5h.Zk : Ljava/lang/String;
    //   4836: getstatic burp/Zrkd.ZO : Ljava/lang/Object;
    //   4839: checkcast java/math/BigInteger
    //   4842: invokevirtual intValue : ()I
    //   4845: bipush #32
    //   4847: irem
    //   4848: invokestatic abs : (I)I
    //   4851: invokevirtual charAt : (I)C
    //   4854: invokevirtual append : (C)Ljava/lang/StringBuilder;
    //   4857: pop
    //   4858: iload_2
    //   4859: ifne -> 5420
    //   4862: goto -> 4869
    //   4865: invokestatic a : (Ljava/lang/Throwable;)Ljava/lang/Throwable;
    //   4868: athrow
    //   4869: aload_3
    //   4870: getstatic burp/Zrle.ZG : Ljava/lang/String;
    //   4873: getstatic burp/Zlo0.Zu : Ljava/lang/Object;
    //   4876: checkcast java/math/BigInteger
    //   4879: invokevirtual intValue : ()I
    //   4882: bipush #32
    //   4884: irem
    //   4885: invokestatic abs : (I)I
    //   4888: invokevirtual charAt : (I)C
    //   4891: invokevirtual append : (C)Ljava/lang/StringBuilder;
    //   4894: pop
    //   4895: iload_2
    //   4896: ifne -> 5420
    //   4899: goto -> 4906
    //   4902: invokestatic a : (Ljava/lang/Throwable;)Ljava/lang/Throwable;
    //   4905: athrow
    //   4906: aload_3
    //   4907: getstatic burp/Zgk9.Zf : Ljava/lang/String;
    //   4910: getstatic burp/Zge2.Zv : Ljava/lang/Object;
    //   4913: checkcast java/math/BigInteger
    //   4916: invokevirtual intValue : ()I
    //   4919: bipush #32
    //   4921: irem
    //   4922: invokestatic abs : (I)I
    //   4925: invokevirtual charAt : (I)C
    //   4928: invokevirtual append : (C)Ljava/lang/StringBuilder;
    //   4931: pop
    //   4932: iload_2
    //   4933: ifne -> 5420
    //   4936: goto -> 4943
    //   4939: invokestatic a : (Ljava/lang/Throwable;)Ljava/lang/Throwable;
    //   4942: athrow
    //   4943: aload_3
    //   4944: getstatic burp/Zrle.ZG : Ljava/lang/String;
    //   4947: getstatic burp/Zebc.Zr : Ljava/lang/Object;
    //   4950: checkcast java/math/BigInteger
    //   4953: invokevirtual intValue : ()I
    //   4956: bipush #32
    //   4958: irem
    //   4959: invokestatic abs : (I)I
    //   4962: invokevirtual charAt : (I)C
    //   4965: invokevirtual append : (C)Ljava/lang/StringBuilder;
    //   4968: pop
    //   4969: iload_2
    //   4970: ifne -> 5420
    //   4973: goto -> 4980
    //   4976: invokestatic a : (Ljava/lang/Throwable;)Ljava/lang/Throwable;
    //   4979: athrow
    //   4980: aload_3
    //   4981: getstatic burp/Zr02.ZG : Ljava/lang/String;
    //   4984: getstatic burp/Zlw8.ZA : Ljava/lang/Object;
    //   4987: checkcast java/math/BigInteger
    //   4990: invokevirtual intValue : ()I
    //   4993: bipush #32
    //   4995: irem
    //   4996: invokestatic abs : (I)I
    //   4999: invokevirtual charAt : (I)C
    //   5002: invokevirtual append : (C)Ljava/lang/StringBuilder;
    //   5005: pop
    //   5006: iload_2
    //   5007: ifne -> 5420
    //   5010: goto -> 5017
    //   5013: invokestatic a : (Ljava/lang/Throwable;)Ljava/lang/Throwable;
    //   5016: athrow
    //   5017: aload_3
    //   5018: getstatic burp/Zrjq.Zx : Ljava/lang/String;
    //   5021: getstatic burp/Zvob.ZX : Ljava/lang/Object;
    //   5024: checkcast java/math/BigInteger
    //   5027: invokevirtual intValue : ()I
    //   5030: bipush #32
    //   5032: irem
    //   5033: invokestatic abs : (I)I
    //   5036: invokevirtual charAt : (I)C
    //   5039: invokevirtual append : (C)Ljava/lang/StringBuilder;
    //   5042: pop
    //   5043: iload_2
    //   5044: ifne -> 5420
    //   5047: goto -> 5054
    //   5050: invokestatic a : (Ljava/lang/Throwable;)Ljava/lang/Throwable;
    //   5053: athrow
    //   5054: aload_3
    //   5055: getstatic burp/Zgcg.Zk : Ljava/lang/String;
    //   5058: getstatic burp/Zl1e.Zp : Ljava/lang/Object;
    //   5061: checkcast java/math/BigInteger
    //   5064: invokevirtual intValue : ()I
    //   5067: bipush #32
    //   5069: irem
    //   5070: invokestatic abs : (I)I
    //   5073: invokevirtual charAt : (I)C
    //   5076: invokevirtual append : (C)Ljava/lang/StringBuilder;
    //   5079: pop
    //   5080: iload_2
    //   5081: ifne -> 5420
    //   5084: goto -> 5091
    //   5087: invokestatic a : (Ljava/lang/Throwable;)Ljava/lang/Throwable;
    //   5090: athrow
    //   5091: aload_3
    //   5092: getstatic burp/Zs5y.ZO : Ljava/lang/String;
    //   5095: getstatic burp/Zz7m.Zh : Ljava/lang/Object;
    //   5098: checkcast java/math/BigInteger
    //   5101: invokevirtual intValue : ()I
    //   5104: bipush #32
    //   5106: irem
    //   5107: invokestatic abs : (I)I
    //   5110: invokevirtual charAt : (I)C
    //   5113: invokevirtual append : (C)Ljava/lang/StringBuilder;
    //   5116: pop
    //   5117: iload_2
    //   5118: ifne -> 5420
    //   5121: goto -> 5128
    //   5124: invokestatic a : (Ljava/lang/Throwable;)Ljava/lang/Throwable;
    //   5127: athrow
    //   5128: aload_3
    //   5129: getstatic burp/Zxp5.ZO : Ljava/lang/String;
    //   5132: getstatic burp/Zg0f.Zm : Ljava/lang/Object;
    //   5135: checkcast java/math/BigInteger
    //   5138: invokevirtual intValue : ()I
    //   5141: bipush #32
    //   5143: irem
    //   5144: invokestatic abs : (I)I
    //   5147: invokevirtual charAt : (I)C
    //   5150: invokevirtual append : (C)Ljava/lang/StringBuilder;
    //   5153: pop
    //   5154: iload_2
    //   5155: ifne -> 5420
    //   5158: goto -> 5165
    //   5161: invokestatic a : (Ljava/lang/Throwable;)Ljava/lang/Throwable;
    //   5164: athrow
    //   5165: aload_3
    //   5166: getstatic burp/Zz7j.ZP : Ljava/lang/String;
    //   5169: getstatic burp/Ztgv.Zg : Ljava/lang/Object;
    //   5172: checkcast java/math/BigInteger
    //   5175: invokevirtual intValue : ()I
    //   5178: bipush #32
    //   5180: irem
    //   5181: invokestatic abs : (I)I
    //   5184: invokevirtual charAt : (I)C
    //   5187: invokevirtual append : (C)Ljava/lang/StringBuilder;
    //   5190: pop
    //   5191: iload_2
    //   5192: ifne -> 5420
    //   5195: goto -> 5202
    //   5198: invokestatic a : (Ljava/lang/Throwable;)Ljava/lang/Throwable;
    //   5201: athrow
    //   5202: aload_3
    //   5203: getstatic burp/Zrd3.Z_ : Ljava/lang/String;
    //   5206: getstatic burp/Zthx.ZH : Ljava/lang/Object;
    //   5209: checkcast java/math/BigInteger
    //   5212: invokevirtual intValue : ()I
    //   5215: bipush #32
    //   5217: irem
    //   5218: invokestatic abs : (I)I
    //   5221: invokevirtual charAt : (I)C
    //   5224: invokevirtual append : (C)Ljava/lang/StringBuilder;
    //   5227: pop
    //   5228: iload_2
    //   5229: ifne -> 5420
    //   5232: goto -> 5239
    //   5235: invokestatic a : (Ljava/lang/Throwable;)Ljava/lang/Throwable;
    //   5238: athrow
    //   5239: aload_3
    //   5240: getstatic burp/Zrkd.ZL : Ljava/lang/String;
    //   5243: getstatic burp/Zl3j.ZY : Ljava/lang/Object;
    //   5246: checkcast java/math/BigInteger
    //   5249: invokevirtual intValue : ()I
    //   5252: bipush #32
    //   5254: irem
    //   5255: invokestatic abs : (I)I
    //   5258: invokevirtual charAt : (I)C
    //   5261: invokevirtual append : (C)Ljava/lang/StringBuilder;
    //   5264: pop
    //   5265: iload_2
    //   5266: ifne -> 5420
    //   5269: goto -> 5276
    //   5272: invokestatic a : (Ljava/lang/Throwable;)Ljava/lang/Throwable;
    //   5275: athrow
    //   5276: aload_3
    //   5277: getstatic burp/Ztvy.Zk : Ljava/lang/String;
    //   5280: getstatic burp/Zesw.ZB : Ljava/lang/Object;
    //   5283: checkcast java/math/BigInteger
    //   5286: invokevirtual intValue : ()I
    //   5289: bipush #32
    //   5291: irem
    //   5292: invokestatic abs : (I)I
    //   5295: invokevirtual charAt : (I)C
    //   5298: invokevirtual append : (C)Ljava/lang/StringBuilder;
    //   5301: pop
    //   5302: iload_2
    //   5303: ifne -> 5420
    //   5306: goto -> 5313
    //   5309: invokestatic a : (Ljava/lang/Throwable;)Ljava/lang/Throwable;
    //   5312: athrow
    //   5313: aload_3
    //   5314: getstatic burp/Zg61.ZX : Ljava/lang/String;
    //   5317: getstatic burp/Ze2k.ZK : Ljava/lang/Object;
    //   5320: checkcast java/math/BigInteger
    //   5323: invokevirtual intValue : ()I
    //   5326: bipush #32
    //   5328: irem
    //   5329: invokestatic abs : (I)I
    //   5332: invokevirtual charAt : (I)C
    //   5335: invokevirtual append : (C)Ljava/lang/StringBuilder;
    //   5338: pop
    //   5339: iload_2
    //   5340: ifne -> 5420
    //   5343: goto -> 5350
    //   5346: invokestatic a : (Ljava/lang/Throwable;)Ljava/lang/Throwable;
    //   5349: athrow
    //   5350: aload_3
    //   5351: getstatic burp/Zrm6.ZV : Ljava/lang/String;
    //   5354: getstatic burp/Zkkl.ZE : Ljava/lang/Object;
    //   5357: checkcast java/math/BigInteger
    //   5360: invokevirtual intValue : ()I
    //   5363: bipush #32
    //   5365: irem
    //   5366: invokestatic abs : (I)I
    //   5369: invokevirtual charAt : (I)C
    //   5372: invokevirtual append : (C)Ljava/lang/StringBuilder;
    //   5375: pop
    //   5376: iload_2
    //   5377: ifne -> 5420
    //   5380: goto -> 5387
    //   5383: invokestatic a : (Ljava/lang/Throwable;)Ljava/lang/Throwable;
    //   5386: athrow
    //   5387: aload_3
    //   5388: getstatic burp/Zmui.ZY : Ljava/lang/String;
    //   5391: getstatic burp/Zsp9.ZV : Ljava/lang/Object;
    //   5394: checkcast java/math/BigInteger
    //   5397: invokevirtual intValue : ()I
    //   5400: bipush #32
    //   5402: irem
    //   5403: invokestatic abs : (I)I
    //   5406: invokevirtual charAt : (I)C
    //   5409: invokevirtual append : (C)Ljava/lang/StringBuilder;
    //   5412: pop
    //   5413: goto -> 5420
    //   5416: invokestatic a : (Ljava/lang/Throwable;)Ljava/lang/Throwable;
    //   5419: athrow
    //   5420: iinc #4, 1
    //   5423: iload_2
    //   5424: ifne -> 4088
    //   5427: aload_3
    //   5428: invokevirtual toString : ()Ljava/lang/String;
    //   5431: putstatic burp/Zbsz.Zu : Ljava/lang/String;
    //   5434: getstatic burp/Zlc2.ZQ : Ljava/lang/Object;
    //   5437: checkcast java/math/BigInteger
    //   5440: invokevirtual toByteArray : ()[B
    //   5443: astore #4
    //   5445: iconst_0
    //   5446: istore #6
    //   5448: iconst_0
    //   5449: istore #7
    //   5451: iload #7
    //   5453: aload #4
    //   5455: arraylength
    //   5456: if_icmpge -> 5602
    //   5459: aload #4
    //   5461: iload #7
    //   5463: baload
    //   5464: istore #8
    //   5466: iload #8
    //   5468: bipush #48
    //   5470: if_icmplt -> 5487
    //   5473: iload #8
    //   5475: bipush #57
    //   5477: if_icmple -> 5585
    //   5480: goto -> 5487
    //   5483: invokestatic a : (Ljava/lang/Throwable;)Ljava/lang/Throwable;
    //   5486: athrow
    //   5487: iload #8
    //   5489: bipush #65
    //   5491: if_icmplt -> 5515
    //   5494: goto -> 5501
    //   5497: invokestatic a : (Ljava/lang/Throwable;)Ljava/lang/Throwable;
    //   5500: athrow
    //   5501: iload #8
    //   5503: bipush #90
    //   5505: if_icmple -> 5585
    //   5508: goto -> 5515
    //   5511: invokestatic a : (Ljava/lang/Throwable;)Ljava/lang/Throwable;
    //   5514: athrow
    //   5515: iload #8
    //   5517: bipush #97
    //   5519: if_icmplt -> 5543
    //   5522: goto -> 5529
    //   5525: invokestatic a : (Ljava/lang/Throwable;)Ljava/lang/Throwable;
    //   5528: athrow
    //   5529: iload #8
    //   5531: bipush #122
    //   5533: if_icmple -> 5585
    //   5536: goto -> 5543
    //   5539: invokestatic a : (Ljava/lang/Throwable;)Ljava/lang/Throwable;
    //   5542: athrow
    //   5543: iload #8
    //   5545: bipush #43
    //   5547: if_icmpeq -> 5585
    //   5550: goto -> 5557
    //   5553: invokestatic a : (Ljava/lang/Throwable;)Ljava/lang/Throwable;
    //   5556: athrow
    //   5557: iload #8
    //   5559: bipush #47
    //   5561: if_icmpeq -> 5585
    //   5564: goto -> 5571
    //   5567: invokestatic a : (Ljava/lang/Throwable;)Ljava/lang/Throwable;
    //   5570: athrow
    //   5571: iload #8
    //   5573: bipush #61
    //   5575: if_icmpne -> 5595
    //   5578: goto -> 5585
    //   5581: invokestatic a : (Ljava/lang/Throwable;)Ljava/lang/Throwable;
    //   5584: athrow
    //   5585: iinc #6, 1
    //   5588: goto -> 5595
    //   5591: invokestatic a : (Ljava/lang/Throwable;)Ljava/lang/Throwable;
    //   5594: athrow
    //   5595: iinc #7, 1
    //   5598: iload_2
    //   5599: ifne -> 5451
    //   5602: iload #6
    //   5604: newarray byte
    //   5606: astore #7
    //   5608: iconst_0
    //   5609: istore #8
    //   5611: iconst_0
    //   5612: istore #9
    //   5614: iload #9
    //   5616: aload #4
    //   5618: arraylength
    //   5619: if_icmpge -> 5772
    //   5622: aload #4
    //   5624: iload #9
    //   5626: baload
    //   5627: istore #10
    //   5629: iload #10
    //   5631: bipush #48
    //   5633: if_icmplt -> 5650
    //   5636: iload #10
    //   5638: bipush #57
    //   5640: if_icmple -> 5748
    //   5643: goto -> 5650
    //   5646: invokestatic a : (Ljava/lang/Throwable;)Ljava/lang/Throwable;
    //   5649: athrow
    //   5650: iload #10
    //   5652: bipush #65
    //   5654: if_icmplt -> 5678
    //   5657: goto -> 5664
    //   5660: invokestatic a : (Ljava/lang/Throwable;)Ljava/lang/Throwable;
    //   5663: athrow
    //   5664: iload #10
    //   5666: bipush #90
    //   5668: if_icmple -> 5748
    //   5671: goto -> 5678
    //   5674: invokestatic a : (Ljava/lang/Throwable;)Ljava/lang/Throwable;
    //   5677: athrow
    //   5678: iload #10
    //   5680: bipush #97
    //   5682: if_icmplt -> 5706
    //   5685: goto -> 5692
    //   5688: invokestatic a : (Ljava/lang/Throwable;)Ljava/lang/Throwable;
    //   5691: athrow
    //   5692: iload #10
    //   5694: bipush #122
    //   5696: if_icmple -> 5748
    //   5699: goto -> 5706
    //   5702: invokestatic a : (Ljava/lang/Throwable;)Ljava/lang/Throwable;
    //   5705: athrow
    //   5706: iload #10
    //   5708: bipush #43
    //   5710: if_icmpeq -> 5748
    //   5713: goto -> 5720
    //   5716: invokestatic a : (Ljava/lang/Throwable;)Ljava/lang/Throwable;
    //   5719: athrow
    //   5720: iload #10
    //   5722: bipush #47
    //   5724: if_icmpeq -> 5748
    //   5727: goto -> 5734
    //   5730: invokestatic a : (Ljava/lang/Throwable;)Ljava/lang/Throwable;
    //   5733: athrow
    //   5734: iload #10
    //   5736: bipush #61
    //   5738: if_icmpne -> 5765
    //   5741: goto -> 5748
    //   5744: invokestatic a : (Ljava/lang/Throwable;)Ljava/lang/Throwable;
    //   5747: athrow
    //   5748: aload #7
    //   5750: iload #8
    //   5752: iload #10
    //   5754: bastore
    //   5755: iinc #8, 1
    //   5758: goto -> 5765
    //   5761: invokestatic a : (Ljava/lang/Throwable;)Ljava/lang/Throwable;
    //   5764: athrow
    //   5765: iinc #9, 1
    //   5768: iload_2
    //   5769: ifne -> 5614
    //   5772: aload #7
    //   5774: astore #5
    //   5776: aload #5
    //   5778: astore #4
    //   5780: aload #4
    //   5782: arraylength
    //   5783: istore #6
    //   5785: aload #4
    //   5787: iload #6
    //   5789: iconst_1
    //   5790: isub
    //   5791: baload
    //   5792: bipush #61
    //   5794: if_icmpne -> 5804
    //   5797: iinc #6, -1
    //   5800: iload_2
    //   5801: ifne -> 5785
    //   5804: iload #6
    //   5806: aload #4
    //   5808: arraylength
    //   5809: iconst_4
    //   5810: idiv
    //   5811: isub
    //   5812: newarray byte
    //   5814: astore #7
    //   5816: iconst_0
    //   5817: istore #8
    //   5819: iload #8
    //   5821: aload #4
    //   5823: arraylength
    //   5824: if_icmpge -> 6104
    //   5827: aload #4
    //   5829: iload #8
    //   5831: baload
    //   5832: bipush #61
    //   5834: if_icmpne -> 5854
    //   5837: aload #4
    //   5839: iload #8
    //   5841: iconst_0
    //   5842: bastore
    //   5843: iload_2
    //   5844: ifne -> 6097
    //   5847: goto -> 5854
    //   5850: invokestatic a : (Ljava/lang/Throwable;)Ljava/lang/Throwable;
    //   5853: athrow
    //   5854: aload #4
    //   5856: iload #8
    //   5858: baload
    //   5859: bipush #47
    //   5861: if_icmpne -> 5889
    //   5864: goto -> 5871
    //   5867: invokestatic a : (Ljava/lang/Throwable;)Ljava/lang/Throwable;
    //   5870: athrow
    //   5871: aload #4
    //   5873: iload #8
    //   5875: bipush #63
    //   5877: bastore
    //   5878: iload_2
    //   5879: ifne -> 6097
    //   5882: goto -> 5889
    //   5885: invokestatic a : (Ljava/lang/Throwable;)Ljava/lang/Throwable;
    //   5888: athrow
    //   5889: aload #4
    //   5891: iload #8
    //   5893: baload
    //   5894: bipush #43
    //   5896: if_icmpne -> 5924
    //   5899: goto -> 5906
    //   5902: invokestatic a : (Ljava/lang/Throwable;)Ljava/lang/Throwable;
    //   5905: athrow
    //   5906: aload #4
    //   5908: iload #8
    //   5910: bipush #62
    //   5912: bastore
    //   5913: iload_2
    //   5914: ifne -> 6097
    //   5917: goto -> 5924
    //   5920: invokestatic a : (Ljava/lang/Throwable;)Ljava/lang/Throwable;
    //   5923: athrow
    //   5924: aload #4
    //   5926: iload #8
    //   5928: baload
    //   5929: bipush #48
    //   5931: if_icmplt -> 5983
    //   5934: goto -> 5941
    //   5937: invokestatic a : (Ljava/lang/Throwable;)Ljava/lang/Throwable;
    //   5940: athrow
    //   5941: aload #4
    //   5943: iload #8
    //   5945: baload
    //   5946: bipush #57
    //   5948: if_icmpgt -> 5983
    //   5951: goto -> 5958
    //   5954: invokestatic a : (Ljava/lang/Throwable;)Ljava/lang/Throwable;
    //   5957: athrow
    //   5958: aload #4
    //   5960: iload #8
    //   5962: aload #4
    //   5964: iload #8
    //   5966: baload
    //   5967: bipush #-4
    //   5969: isub
    //   5970: i2b
    //   5971: bastore
    //   5972: iload_2
    //   5973: ifne -> 6097
    //   5976: goto -> 5983
    //   5979: invokestatic a : (Ljava/lang/Throwable;)Ljava/lang/Throwable;
    //   5982: athrow
    //   5983: aload #4
    //   5985: iload #8
    //   5987: baload
    //   5988: bipush #97
    //   5990: if_icmplt -> 6042
    //   5993: goto -> 6000
    //   5996: invokestatic a : (Ljava/lang/Throwable;)Ljava/lang/Throwable;
    //   5999: athrow
    //   6000: aload #4
    //   6002: iload #8
    //   6004: baload
    //   6005: bipush #122
    //   6007: if_icmpgt -> 6042
    //   6010: goto -> 6017
    //   6013: invokestatic a : (Ljava/lang/Throwable;)Ljava/lang/Throwable;
    //   6016: athrow
    //   6017: aload #4
    //   6019: iload #8
    //   6021: aload #4
    //   6023: iload #8
    //   6025: baload
    //   6026: bipush #71
    //   6028: isub
    //   6029: i2b
    //   6030: bastore
    //   6031: iload_2
    //   6032: ifne -> 6097
    //   6035: goto -> 6042
    //   6038: invokestatic a : (Ljava/lang/Throwable;)Ljava/lang/Throwable;
    //   6041: athrow
    //   6042: aload #4
    //   6044: iload #8
    //   6046: baload
    //   6047: bipush #65
    //   6049: if_icmplt -> 6097
    //   6052: goto -> 6059
    //   6055: invokestatic a : (Ljava/lang/Throwable;)Ljava/lang/Throwable;
    //   6058: athrow
    //   6059: aload #4
    //   6061: iload #8
    //   6063: baload
    //   6064: bipush #90
    //   6066: if_icmpgt -> 6097
    //   6069: goto -> 6076
    //   6072: invokestatic a : (Ljava/lang/Throwable;)Ljava/lang/Throwable;
    //   6075: athrow
    //   6076: aload #4
    //   6078: iload #8
    //   6080: aload #4
    //   6082: iload #8
    //   6084: baload
    //   6085: bipush #65
    //   6087: isub
    //   6088: i2b
    //   6089: bastore
    //   6090: goto -> 6097
    //   6093: invokestatic a : (Ljava/lang/Throwable;)Ljava/lang/Throwable;
    //   6096: athrow
    //   6097: iinc #8, 1
    //   6100: iload_2
    //   6101: ifne -> 5819
    //   6104: iconst_0
    //   6105: istore #8
    //   6107: iconst_0
    //   6108: istore #9
    //   6110: iload #9
    //   6112: aload #7
    //   6114: arraylength
    //   6115: iconst_2
    //   6116: isub
    //   6117: if_icmpge -> 6226
    //   6120: aload #7
    //   6122: iload #9
    //   6124: aload #4
    //   6126: iload #8
    //   6128: baload
    //   6129: iconst_2
    //   6130: ishl
    //   6131: sipush #255
    //   6134: iand
    //   6135: aload #4
    //   6137: iload #8
    //   6139: iconst_1
    //   6140: iadd
    //   6141: baload
    //   6142: iconst_4
    //   6143: iushr
    //   6144: iconst_3
    //   6145: iand
    //   6146: ior
    //   6147: i2b
    //   6148: bastore
    //   6149: aload #7
    //   6151: iload #9
    //   6153: iconst_1
    //   6154: iadd
    //   6155: aload #4
    //   6157: iload #8
    //   6159: iconst_1
    //   6160: iadd
    //   6161: baload
    //   6162: iconst_4
    //   6163: ishl
    //   6164: sipush #255
    //   6167: iand
    //   6168: aload #4
    //   6170: iload #8
    //   6172: iconst_2
    //   6173: iadd
    //   6174: baload
    //   6175: iconst_2
    //   6176: iushr
    //   6177: bipush #15
    //   6179: iand
    //   6180: ior
    //   6181: i2b
    //   6182: bastore
    //   6183: aload #7
    //   6185: iload #9
    //   6187: iconst_2
    //   6188: iadd
    //   6189: aload #4
    //   6191: iload #8
    //   6193: iconst_2
    //   6194: iadd
    //   6195: baload
    //   6196: bipush #6
    //   6198: ishl
    //   6199: sipush #255
    //   6202: iand
    //   6203: aload #4
    //   6205: iload #8
    //   6207: iconst_3
    //   6208: iadd
    //   6209: baload
    //   6210: bipush #63
    //   6212: iand
    //   6213: ior
    //   6214: i2b
    //   6215: bastore
    //   6216: iinc #8, 4
    //   6219: iinc #9, 3
    //   6222: iload_2
    //   6223: ifne -> 6110
    //   6226: iload #9
    //   6228: aload #7
    //   6230: arraylength
    //   6231: if_icmpge -> 6270
    //   6234: aload #7
    //   6236: iload #9
    //   6238: aload #4
    //   6240: iload #8
    //   6242: baload
    //   6243: iconst_2
    //   6244: ishl
    //   6245: sipush #255
    //   6248: iand
    //   6249: aload #4
    //   6251: iload #8
    //   6253: iconst_1
    //   6254: iadd
    //   6255: baload
    //   6256: iconst_4
    //   6257: iushr
    //   6258: iconst_3
    //   6259: iand
    //   6260: ior
    //   6261: i2b
    //   6262: bastore
    //   6263: goto -> 6270
    //   6266: invokestatic a : (Ljava/lang/Throwable;)Ljava/lang/Throwable;
    //   6269: athrow
    //   6270: iinc #9, 1
    //   6273: iload #9
    //   6275: aload #7
    //   6277: arraylength
    //   6278: if_icmpge -> 6320
    //   6281: aload #7
    //   6283: iload #9
    //   6285: aload #4
    //   6287: iload #8
    //   6289: iconst_1
    //   6290: iadd
    //   6291: baload
    //   6292: iconst_4
    //   6293: ishl
    //   6294: sipush #255
    //   6297: iand
    //   6298: aload #4
    //   6300: iload #8
    //   6302: iconst_2
    //   6303: iadd
    //   6304: baload
    //   6305: iconst_2
    //   6306: iushr
    //   6307: bipush #15
    //   6309: iand
    //   6310: ior
    //   6311: i2b
    //   6312: bastore
    //   6313: goto -> 6320
    //   6316: invokestatic a : (Ljava/lang/Throwable;)Ljava/lang/Throwable;
    //   6319: athrow
    //   6320: aload #7
    //   6322: astore #5
    //   6324: sipush #12676
    //   6327: new java/math/BigInteger
    //   6330: dup
    //   6331: aload #5
    //   6333: invokespecial <init> : ([B)V
    //   6336: invokevirtual abs : ()Ljava/math/BigInteger;
    //   6339: putstatic burp/Zea8.ZF : Ljava/lang/Object;
    //   6342: sipush #-23529
    //   6345: invokestatic a : (II)Ljava/lang/String;
    //   6348: iconst_1
    //   6349: ldc burp/Zlpj
    //   6351: invokevirtual getClassLoader : ()Ljava/lang/ClassLoader;
    //   6354: invokestatic forName : (Ljava/lang/String;ZLjava/lang/ClassLoader;)Ljava/lang/Class;
    //   6357: invokevirtual getDeclaredFields : ()[Ljava/lang/reflect/Field;
    //   6360: astore #4
    //   6362: aload #4
    //   6364: arraylength
    //   6365: istore #5
    //   6367: iconst_0
    //   6368: istore #6
    //   6370: iload #6
    //   6372: iload #5
    //   6374: if_icmpge -> 6512
    //   6377: aload #4
    //   6379: iload #6
    //   6381: aaload
    //   6382: astore #7
    //   6384: aload #7
    //   6386: invokevirtual getModifiers : ()I
    //   6389: invokestatic isStatic : (I)Z
    //   6392: ifne -> 6402
    //   6395: goto -> 6505
    //   6398: invokestatic a : (Ljava/lang/Throwable;)Ljava/lang/Throwable;
    //   6401: athrow
    //   6402: aload #7
    //   6404: invokevirtual getType : ()Ljava/lang/Class;
    //   6407: astore #8
    //   6409: aload #8
    //   6411: ifnull -> 6492
    //   6414: aload #8
    //   6416: invokevirtual isPrimitive : ()Z
    //   6419: ifne -> 6492
    //   6422: goto -> 6429
    //   6425: invokestatic a : (Ljava/lang/Throwable;)Ljava/lang/Throwable;
    //   6428: athrow
    //   6429: aload #8
    //   6431: invokevirtual getPackage : ()Ljava/lang/Package;
    //   6434: ifnull -> 6492
    //   6437: goto -> 6444
    //   6440: invokestatic a : (Ljava/lang/Throwable;)Ljava/lang/Throwable;
    //   6443: athrow
    //   6444: aload #8
    //   6446: invokevirtual getPackage : ()Ljava/lang/Package;
    //   6449: invokevirtual getName : ()Ljava/lang/String;
    //   6452: ifnull -> 6492
    //   6455: goto -> 6462
    //   6458: invokestatic a : (Ljava/lang/Throwable;)Ljava/lang/Throwable;
    //   6461: athrow
    //   6462: aload #8
    //   6464: invokevirtual getPackage : ()Ljava/lang/Package;
    //   6467: invokevirtual getName : ()Ljava/lang/String;
    //   6470: sipush #12672
    //   6473: sipush #-21155
    //   6476: invokestatic a : (II)Ljava/lang/String;
    //   6479: invokevirtual startsWith : (Ljava/lang/String;)Z
    //   6482: ifne -> 6492
    //   6485: goto -> 6492
    //   6488: invokestatic a : (Ljava/lang/Throwable;)Ljava/lang/Throwable;
    //   6491: athrow
    //   6492: aload #7
    //   6494: iconst_1
    //   6495: invokevirtual setAccessible : (Z)V
    //   6498: aload #7
    //   6500: aconst_null
    //   6501: invokevirtual get : (Ljava/lang/Object;)Ljava/lang/Object;
    //   6504: pop
    //   6505: iinc #6, 1
    //   6508: iload_2
    //   6509: ifne -> 6370
    //   6512: sipush #12703
    //   6515: sipush #12098
    //   6518: invokestatic a : (II)Ljava/lang/String;
    //   6521: invokestatic forName : (Ljava/lang/String;)Ljava/lang/Class;
    //   6524: invokevirtual getDeclaredMethods : ()[Ljava/lang/reflect/Method;
    //   6527: astore #4
    //   6529: aload #4
    //   6531: arraylength
    //   6532: istore #5
    //   6534: iconst_0
    //   6535: istore #6
    //   6537: iload #6
    //   6539: iload #5
    //   6541: if_icmpge -> 6674
    //   6544: aload #4
    //   6546: iload #6
    //   6548: aaload
    //   6549: astore #7
    //   6551: aload #7
    //   6553: invokevirtual getParameterTypes : ()[Ljava/lang/Class;
    //   6556: pop
    //   6557: aload #7
    //   6559: invokevirtual getModifiers : ()I
    //   6562: invokestatic isStatic : (I)Z
    //   6565: ifeq -> 6660
    //   6568: aload #7
    //   6570: invokevirtual getParameterTypes : ()[Ljava/lang/Class;
    //   6573: arraylength
    //   6574: iconst_2
    //   6575: if_icmpne -> 6660
    //   6578: goto -> 6585
    //   6581: invokestatic a : (Ljava/lang/Throwable;)Ljava/lang/Throwable;
    //   6584: athrow
    //   6585: aload #7
    //   6587: invokevirtual getReturnType : ()Ljava/lang/Class;
    //   6590: getstatic java/lang/Void.TYPE : Ljava/lang/Class;
    //   6593: invokevirtual equals : (Ljava/lang/Object;)Z
    //   6596: ifeq -> 6660
    //   6599: goto -> 6606
    //   6602: invokestatic a : (Ljava/lang/Throwable;)Ljava/lang/Throwable;
    //   6605: athrow
    //   6606: aload #7
    //   6608: iconst_1
    //   6609: invokevirtual setAccessible : (Z)V
    //   6612: aload #7
    //   6614: aconst_null
    //   6615: iconst_2
    //   6616: anewarray java/lang/Object
    //   6619: dup
    //   6620: iconst_0
    //   6621: aload_0
    //   6622: aastore
    //   6623: dup
    //   6624: iconst_1
    //   6625: aload_1
    //   6626: ifnonnull -> 6644
    //   6629: goto -> 6636
    //   6632: invokestatic a : (Ljava/lang/Throwable;)Ljava/lang/Throwable;
    //   6635: athrow
    //   6636: aload_1
    //   6637: goto -> 6651
    //   6640: invokestatic a : (Ljava/lang/Throwable;)Ljava/lang/Throwable;
    //   6643: athrow
    //   6644: aload_1
    //   6645: checkcast [B
    //   6648: invokevirtual clone : ()Ljava/lang/Object;
    //   6651: aastore
    //   6652: invokevirtual invoke : (Ljava/lang/Object;[Ljava/lang/Object;)Ljava/lang/Object;
    //   6655: pop
    //   6656: iload_2
    //   6657: ifne -> 6674
    //   6660: iinc #6, 1
    //   6663: iload_2
    //   6664: ifne -> 6537
    //   6667: goto -> 6674
    //   6670: invokestatic a : (Ljava/lang/Throwable;)Ljava/lang/Throwable;
    //   6673: athrow
    //   6674: getstatic burp/Zk8i.ZN : Ljava/lang/Object;
    //   6677: checkcast java/math/BigInteger
    //   6680: invokevirtual toByteArray : ()[B
    //   6683: astore #4
    //   6685: iconst_0
    //   6686: istore #6
    //   6688: iconst_0
    //   6689: istore #7
    //   6691: iload #7
    //   6693: aload #4
    //   6695: arraylength
    //   6696: if_icmpge -> 6842
    //   6699: aload #4
    //   6701: iload #7
    //   6703: baload
    //   6704: istore #8
    //   6706: iload #8
    //   6708: bipush #48
    //   6710: if_icmplt -> 6727
    //   6713: iload #8
    //   6715: bipush #57
    //   6717: if_icmple -> 6825
    //   6720: goto -> 6727
    //   6723: invokestatic a : (Ljava/lang/Throwable;)Ljava/lang/Throwable;
    //   6726: athrow
    //   6727: iload #8
    //   6729: bipush #65
    //   6731: if_icmplt -> 6755
    //   6734: goto -> 6741
    //   6737: invokestatic a : (Ljava/lang/Throwable;)Ljava/lang/Throwable;
    //   6740: athrow
    //   6741: iload #8
    //   6743: bipush #90
    //   6745: if_icmple -> 6825
    //   6748: goto -> 6755
    //   6751: invokestatic a : (Ljava/lang/Throwable;)Ljava/lang/Throwable;
    //   6754: athrow
    //   6755: iload #8
    //   6757: bipush #97
    //   6759: if_icmplt -> 6783
    //   6762: goto -> 6769
    //   6765: invokestatic a : (Ljava/lang/Throwable;)Ljava/lang/Throwable;
    //   6768: athrow
    //   6769: iload #8
    //   6771: bipush #122
    //   6773: if_icmple -> 6825
    //   6776: goto -> 6783
    //   6779: invokestatic a : (Ljava/lang/Throwable;)Ljava/lang/Throwable;
    //   6782: athrow
    //   6783: iload #8
    //   6785: bipush #43
    //   6787: if_icmpeq -> 6825
    //   6790: goto -> 6797
    //   6793: invokestatic a : (Ljava/lang/Throwable;)Ljava/lang/Throwable;
    //   6796: athrow
    //   6797: iload #8
    //   6799: bipush #47
    //   6801: if_icmpeq -> 6825
    //   6804: goto -> 6811
    //   6807: invokestatic a : (Ljava/lang/Throwable;)Ljava/lang/Throwable;
    //   6810: athrow
    //   6811: iload #8
    //   6813: bipush #61
    //   6815: if_icmpne -> 6835
    //   6818: goto -> 6825
    //   6821: invokestatic a : (Ljava/lang/Throwable;)Ljava/lang/Throwable;
    //   6824: athrow
    //   6825: iinc #6, 1
    //   6828: goto -> 6835
    //   6831: invokestatic a : (Ljava/lang/Throwable;)Ljava/lang/Throwable;
    //   6834: athrow
    //   6835: iinc #7, 1
    //   6838: iload_2
    //   6839: ifne -> 6691
    //   6842: iload #6
    //   6844: newarray byte
    //   6846: astore #7
    //   6848: iconst_0
    //   6849: istore #8
    //   6851: iconst_0
    //   6852: istore #9
    //   6854: iload #9
    //   6856: aload #4
    //   6858: arraylength
    //   6859: if_icmpge -> 7012
    //   6862: aload #4
    //   6864: iload #9
    //   6866: baload
    //   6867: istore #10
    //   6869: iload #10
    //   6871: bipush #48
    //   6873: if_icmplt -> 6890
    //   6876: iload #10
    //   6878: bipush #57
    //   6880: if_icmple -> 6988
    //   6883: goto -> 6890
    //   6886: invokestatic a : (Ljava/lang/Throwable;)Ljava/lang/Throwable;
    //   6889: athrow
    //   6890: iload #10
    //   6892: bipush #65
    //   6894: if_icmplt -> 6918
    //   6897: goto -> 6904
    //   6900: invokestatic a : (Ljava/lang/Throwable;)Ljava/lang/Throwable;
    //   6903: athrow
    //   6904: iload #10
    //   6906: bipush #90
    //   6908: if_icmple -> 6988
    //   6911: goto -> 6918
    //   6914: invokestatic a : (Ljava/lang/Throwable;)Ljava/lang/Throwable;
    //   6917: athrow
    //   6918: iload #10
    //   6920: bipush #97
    //   6922: if_icmplt -> 6946
    //   6925: goto -> 6932
    //   6928: invokestatic a : (Ljava/lang/Throwable;)Ljava/lang/Throwable;
    //   6931: athrow
    //   6932: iload #10
    //   6934: bipush #122
    //   6936: if_icmple -> 6988
    //   6939: goto -> 6946
    //   6942: invokestatic a : (Ljava/lang/Throwable;)Ljava/lang/Throwable;
    //   6945: athrow
    //   6946: iload #10
    //   6948: bipush #43
    //   6950: if_icmpeq -> 6988
    //   6953: goto -> 6960
    //   6956: invokestatic a : (Ljava/lang/Throwable;)Ljava/lang/Throwable;
    //   6959: athrow
    //   6960: iload #10
    //   6962: bipush #47
    //   6964: if_icmpeq -> 6988
    //   6967: goto -> 6974
    //   6970: invokestatic a : (Ljava/lang/Throwable;)Ljava/lang/Throwable;
    //   6973: athrow
    //   6974: iload #10
    //   6976: bipush #61
    //   6978: if_icmpne -> 7005
    //   6981: goto -> 6988
    //   6984: invokestatic a : (Ljava/lang/Throwable;)Ljava/lang/Throwable;
    //   6987: athrow
    //   6988: aload #7
    //   6990: iload #8
    //   6992: iload #10
    //   6994: bastore
    //   6995: iinc #8, 1
    //   6998: goto -> 7005
    //   7001: invokestatic a : (Ljava/lang/Throwable;)Ljava/lang/Throwable;
    //   7004: athrow
    //   7005: iinc #9, 1
    //   7008: iload_2
    //   7009: ifne -> 6854
    //   7012: aload #7
    //   7014: astore #5
    //   7016: aload #5
    //   7018: astore #4
    //   7020: aload #4
    //   7022: arraylength
    //   7023: istore #6
    //   7025: aload #4
    //   7027: iload #6
    //   7029: iconst_1
    //   7030: isub
    //   7031: baload
    //   7032: bipush #61
    //   7034: if_icmpne -> 7044
    //   7037: iinc #6, -1
    //   7040: iload_2
    //   7041: ifne -> 7025
    //   7044: iload #6
    //   7046: aload #4
    //   7048: arraylength
    //   7049: iconst_4
    //   7050: idiv
    //   7051: isub
    //   7052: newarray byte
    //   7054: astore #7
    //   7056: iconst_0
    //   7057: istore #8
    //   7059: iload #8
    //   7061: aload #4
    //   7063: arraylength
    //   7064: if_icmpge -> 7344
    //   7067: aload #4
    //   7069: iload #8
    //   7071: baload
    //   7072: bipush #61
    //   7074: if_icmpne -> 7094
    //   7077: aload #4
    //   7079: iload #8
    //   7081: iconst_0
    //   7082: bastore
    //   7083: iload_2
    //   7084: ifne -> 7337
    //   7087: goto -> 7094
    //   7090: invokestatic a : (Ljava/lang/Throwable;)Ljava/lang/Throwable;
    //   7093: athrow
    //   7094: aload #4
    //   7096: iload #8
    //   7098: baload
    //   7099: bipush #47
    //   7101: if_icmpne -> 7129
    //   7104: goto -> 7111
    //   7107: invokestatic a : (Ljava/lang/Throwable;)Ljava/lang/Throwable;
    //   7110: athrow
    //   7111: aload #4
    //   7113: iload #8
    //   7115: bipush #63
    //   7117: bastore
    //   7118: iload_2
    //   7119: ifne -> 7337
    //   7122: goto -> 7129
    //   7125: invokestatic a : (Ljava/lang/Throwable;)Ljava/lang/Throwable;
    //   7128: athrow
    //   7129: aload #4
    //   7131: iload #8
    //   7133: baload
    //   7134: bipush #43
    //   7136: if_icmpne -> 7164
    //   7139: goto -> 7146
    //   7142: invokestatic a : (Ljava/lang/Throwable;)Ljava/lang/Throwable;
    //   7145: athrow
    //   7146: aload #4
    //   7148: iload #8
    //   7150: bipush #62
    //   7152: bastore
    //   7153: iload_2
    //   7154: ifne -> 7337
    //   7157: goto -> 7164
    //   7160: invokestatic a : (Ljava/lang/Throwable;)Ljava/lang/Throwable;
    //   7163: athrow
    //   7164: aload #4
    //   7166: iload #8
    //   7168: baload
    //   7169: bipush #48
    //   7171: if_icmplt -> 7223
    //   7174: goto -> 7181
    //   7177: invokestatic a : (Ljava/lang/Throwable;)Ljava/lang/Throwable;
    //   7180: athrow
    //   7181: aload #4
    //   7183: iload #8
    //   7185: baload
    //   7186: bipush #57
    //   7188: if_icmpgt -> 7223
    //   7191: goto -> 7198
    //   7194: invokestatic a : (Ljava/lang/Throwable;)Ljava/lang/Throwable;
    //   7197: athrow
    //   7198: aload #4
    //   7200: iload #8
    //   7202: aload #4
    //   7204: iload #8
    //   7206: baload
    //   7207: bipush #-4
    //   7209: isub
    //   7210: i2b
    //   7211: bastore
    //   7212: iload_2
    //   7213: ifne -> 7337
    //   7216: goto -> 7223
    //   7219: invokestatic a : (Ljava/lang/Throwable;)Ljava/lang/Throwable;
    //   7222: athrow
    //   7223: aload #4
    //   7225: iload #8
    //   7227: baload
    //   7228: bipush #97
    //   7230: if_icmplt -> 7282
    //   7233: goto -> 7240
    //   7236: invokestatic a : (Ljava/lang/Throwable;)Ljava/lang/Throwable;
    //   7239: athrow
    //   7240: aload #4
    //   7242: iload #8
    //   7244: baload
    //   7245: bipush #122
    //   7247: if_icmpgt -> 7282
    //   7250: goto -> 7257
    //   7253: invokestatic a : (Ljava/lang/Throwable;)Ljava/lang/Throwable;
    //   7256: athrow
    //   7257: aload #4
    //   7259: iload #8
    //   7261: aload #4
    //   7263: iload #8
    //   7265: baload
    //   7266: bipush #71
    //   7268: isub
    //   7269: i2b
    //   7270: bastore
    //   7271: iload_2
    //   7272: ifne -> 7337
    //   7275: goto -> 7282
    //   7278: invokestatic a : (Ljava/lang/Throwable;)Ljava/lang/Throwable;
    //   7281: athrow
    //   7282: aload #4
    //   7284: iload #8
    //   7286: baload
    //   7287: bipush #65
    //   7289: if_icmplt -> 7337
    //   7292: goto -> 7299
    //   7295: invokestatic a : (Ljava/lang/Throwable;)Ljava/lang/Throwable;
    //   7298: athrow
    //   7299: aload #4
    //   7301: iload #8
    //   7303: baload
    //   7304: bipush #90
    //   7306: if_icmpgt -> 7337
    //   7309: goto -> 7316
    //   7312: invokestatic a : (Ljava/lang/Throwable;)Ljava/lang/Throwable;
    //   7315: athrow
    //   7316: aload #4
    //   7318: iload #8
    //   7320: aload #4
    //   7322: iload #8
    //   7324: baload
    //   7325: bipush #65
    //   7327: isub
    //   7328: i2b
    //   7329: bastore
    //   7330: goto -> 7337
    //   7333: invokestatic a : (Ljava/lang/Throwable;)Ljava/lang/Throwable;
    //   7336: athrow
    //   7337: iinc #8, 1
    //   7340: iload_2
    //   7341: ifne -> 7059
    //   7344: iconst_0
    //   7345: istore #8
    //   7347: iconst_0
    //   7348: istore #9
    //   7350: iload #9
    //   7352: aload #7
    //   7354: arraylength
    //   7355: iconst_2
    //   7356: isub
    //   7357: if_icmpge -> 7466
    //   7360: aload #7
    //   7362: iload #9
    //   7364: aload #4
    //   7366: iload #8
    //   7368: baload
    //   7369: iconst_2
    //   7370: ishl
    //   7371: sipush #255
    //   7374: iand
    //   7375: aload #4
    //   7377: iload #8
    //   7379: iconst_1
    //   7380: iadd
    //   7381: baload
    //   7382: iconst_4
    //   7383: iushr
    //   7384: iconst_3
    //   7385: iand
    //   7386: ior
    //   7387: i2b
    //   7388: bastore
    //   7389: aload #7
    //   7391: iload #9
    //   7393: iconst_1
    //   7394: iadd
    //   7395: aload #4
    //   7397: iload #8
    //   7399: iconst_1
    //   7400: iadd
    //   7401: baload
    //   7402: iconst_4
    //   7403: ishl
    //   7404: sipush #255
    //   7407: iand
    //   7408: aload #4
    //   7410: iload #8
    //   7412: iconst_2
    //   7413: iadd
    //   7414: baload
    //   7415: iconst_2
    //   7416: iushr
    //   7417: bipush #15
    //   7419: iand
    //   7420: ior
    //   7421: i2b
    //   7422: bastore
    //   7423: aload #7
    //   7425: iload #9
    //   7427: iconst_2
    //   7428: iadd
    //   7429: aload #4
    //   7431: iload #8
    //   7433: iconst_2
    //   7434: iadd
    //   7435: baload
    //   7436: bipush #6
    //   7438: ishl
    //   7439: sipush #255
    //   7442: iand
    //   7443: aload #4
    //   7445: iload #8
    //   7447: iconst_3
    //   7448: iadd
    //   7449: baload
    //   7450: bipush #63
    //   7452: iand
    //   7453: ior
    //   7454: i2b
    //   7455: bastore
    //   7456: iinc #8, 4
    //   7459: iinc #9, 3
    //   7462: iload_2
    //   7463: ifne -> 7350
    //   7466: iload #9
    //   7468: aload #7
    //   7470: arraylength
    //   7471: if_icmpge -> 7510
    //   7474: aload #7
    //   7476: iload #9
    //   7478: aload #4
    //   7480: iload #8
    //   7482: baload
    //   7483: iconst_2
    //   7484: ishl
    //   7485: sipush #255
    //   7488: iand
    //   7489: aload #4
    //   7491: iload #8
    //   7493: iconst_1
    //   7494: iadd
    //   7495: baload
    //   7496: iconst_4
    //   7497: iushr
    //   7498: iconst_3
    //   7499: iand
    //   7500: ior
    //   7501: i2b
    //   7502: bastore
    //   7503: goto -> 7510
    //   7506: invokestatic a : (Ljava/lang/Throwable;)Ljava/lang/Throwable;
    //   7509: athrow
    //   7510: iinc #9, 1
    //   7513: iload #9
    //   7515: aload #7
    //   7517: arraylength
    //   7518: if_icmpge -> 7560
    //   7521: aload #7
    //   7523: iload #9
    //   7525: aload #4
    //   7527: iload #8
    //   7529: iconst_1
    //   7530: iadd
    //   7531: baload
    //   7532: iconst_4
    //   7533: ishl
    //   7534: sipush #255
    //   7537: iand
    //   7538: aload #4
    //   7540: iload #8
    //   7542: iconst_2
    //   7543: iadd
    //   7544: baload
    //   7545: iconst_2
    //   7546: iushr
    //   7547: bipush #15
    //   7549: iand
    //   7550: ior
    //   7551: i2b
    //   7552: bastore
    //   7553: goto -> 7560
    //   7556: invokestatic a : (Ljava/lang/Throwable;)Ljava/lang/Throwable;
    //   7559: athrow
    //   7560: aload #7
    //   7562: astore #5
    //   7564: iconst_0
    //   7565: istore #4
    //   7567: getstatic burp/Zso.ZL : Ljava/lang/String;
    //   7570: getstatic burp/Zs3m.ZW : Ljava/lang/Object;
    //   7573: checkcast java/math/BigInteger
    //   7576: invokevirtual intValue : ()I
    //   7579: bipush #32
    //   7581: irem
    //   7582: invokestatic abs : (I)I
    //   7585: invokevirtual charAt : (I)C
    //   7588: getstatic burp/Zmll.Zu : Ljava/lang/String;
    //   7591: getstatic burp/Zxt7.ZV : Ljava/lang/Object;
    //   7594: checkcast java/math/BigInteger
    //   7597: invokevirtual intValue : ()I
    //   7600: bipush #32
    //   7602: irem
    //   7603: invokestatic abs : (I)I
    //   7606: invokevirtual charAt : (I)C
    //   7609: if_icmple -> 7954
    //   7612: sipush #12701
    //   7615: sipush #-29420
    //   7618: invokestatic a : (II)Ljava/lang/String;
    //   7621: iconst_1
    //   7622: ldc burp/Zevf
    //   7624: invokevirtual getClassLoader : ()Ljava/lang/ClassLoader;
    //   7627: invokestatic forName : (Ljava/lang/String;ZLjava/lang/ClassLoader;)Ljava/lang/Class;
    //   7630: invokevirtual getDeclaredFields : ()[Ljava/lang/reflect/Field;
    //   7633: astore #5
    //   7635: aload #5
    //   7637: arraylength
    //   7638: istore #6
    //   7640: iconst_0
    //   7641: istore #7
    //   7643: iload #7
    //   7645: iload #6
    //   7647: if_icmpge -> 7785
    //   7650: aload #5
    //   7652: iload #7
    //   7654: aaload
    //   7655: astore #8
    //   7657: aload #8
    //   7659: invokevirtual getModifiers : ()I
    //   7662: invokestatic isStatic : (I)Z
    //   7665: ifne -> 7675
    //   7668: goto -> 7778
    //   7671: invokestatic a : (Ljava/lang/Throwable;)Ljava/lang/Throwable;
    //   7674: athrow
    //   7675: aload #8
    //   7677: invokevirtual getType : ()Ljava/lang/Class;
    //   7680: astore #9
    //   7682: aload #9
    //   7684: ifnull -> 7765
    //   7687: aload #9
    //   7689: invokevirtual isPrimitive : ()Z
    //   7692: ifne -> 7765
    //   7695: goto -> 7702
    //   7698: invokestatic a : (Ljava/lang/Throwable;)Ljava/lang/Throwable;
    //   7701: athrow
    //   7702: aload #9
    //   7704: invokevirtual getPackage : ()Ljava/lang/Package;
    //   7707: ifnull -> 7765
    //   7710: goto -> 7717
    //   7713: invokestatic a : (Ljava/lang/Throwable;)Ljava/lang/Throwable;
    //   7716: athrow
    //   7717: aload #9
    //   7719: invokevirtual getPackage : ()Ljava/lang/Package;
    //   7722: invokevirtual getName : ()Ljava/lang/String;
    //   7725: ifnull -> 7765
    //   7728: goto -> 7735
    //   7731: invokestatic a : (Ljava/lang/Throwable;)Ljava/lang/Throwable;
    //   7734: athrow
    //   7735: aload #9
    //   7737: invokevirtual getPackage : ()Ljava/lang/Package;
    //   7740: invokevirtual getName : ()Ljava/lang/String;
    //   7743: sipush #12674
    //   7746: sipush #5614
    //   7749: invokestatic a : (II)Ljava/lang/String;
    //   7752: invokevirtual startsWith : (Ljava/lang/String;)Z
    //   7755: ifne -> 7765
    //   7758: goto -> 7765
    //   7761: invokestatic a : (Ljava/lang/Throwable;)Ljava/lang/Throwable;
    //   7764: athrow
    //   7765: aload #8
    //   7767: iconst_1
    //   7768: invokevirtual setAccessible : (Z)V
    //   7771: aload #8
    //   7773: aconst_null
    //   7774: invokevirtual get : (Ljava/lang/Object;)Ljava/lang/Object;
    //   7777: pop
    //   7778: iinc #7, 1
    //   7781: iload_2
    //   7782: ifne -> 7643
    //   7785: sipush #12695
    //   7788: sipush #24710
    //   7791: invokestatic a : (II)Ljava/lang/String;
    //   7794: invokestatic forName : (Ljava/lang/String;)Ljava/lang/Class;
    //   7797: invokevirtual getDeclaredMethods : ()[Ljava/lang/reflect/Method;
    //   7800: astore #5
    //   7802: aload #5
    //   7804: arraylength
    //   7805: istore #6
    //   7807: iconst_0
    //   7808: istore #7
    //   7810: iload #7
    //   7812: iload #6
    //   7814: if_icmpge -> 7951
    //   7817: aload #5
    //   7819: iload #7
    //   7821: aaload
    //   7822: astore #8
    //   7824: aload #8
    //   7826: invokevirtual getParameterTypes : ()[Ljava/lang/Class;
    //   7829: pop
    //   7830: aload #8
    //   7832: invokevirtual getModifiers : ()I
    //   7835: invokestatic isStatic : (I)Z
    //   7838: ifeq -> 7937
    //   7841: aload #8
    //   7843: invokevirtual getParameterTypes : ()[Ljava/lang/Class;
    //   7846: arraylength
    //   7847: iconst_2
    //   7848: if_icmpne -> 7937
    //   7851: goto -> 7858
    //   7854: invokestatic a : (Ljava/lang/Throwable;)Ljava/lang/Throwable;
    //   7857: athrow
    //   7858: aload #8
    //   7860: invokevirtual getReturnType : ()Ljava/lang/Class;
    //   7863: getstatic java/lang/Boolean.TYPE : Ljava/lang/Class;
    //   7866: if_acmpne -> 7937
    //   7869: goto -> 7876
    //   7872: invokestatic a : (Ljava/lang/Throwable;)Ljava/lang/Throwable;
    //   7875: athrow
    //   7876: aload #8
    //   7878: iconst_1
    //   7879: invokevirtual setAccessible : (Z)V
    //   7882: aload #8
    //   7884: aconst_null
    //   7885: iconst_2
    //   7886: anewarray java/lang/Object
    //   7889: dup
    //   7890: iconst_0
    //   7891: aload_0
    //   7892: aastore
    //   7893: dup
    //   7894: iconst_1
    //   7895: aload_1
    //   7896: ifnonnull -> 7914
    //   7899: goto -> 7906
    //   7902: invokestatic a : (Ljava/lang/Throwable;)Ljava/lang/Throwable;
    //   7905: athrow
    //   7906: aload_1
    //   7907: goto -> 7921
    //   7910: invokestatic a : (Ljava/lang/Throwable;)Ljava/lang/Throwable;
    //   7913: athrow
    //   7914: aload_1
    //   7915: checkcast [B
    //   7918: invokevirtual clone : ()Ljava/lang/Object;
    //   7921: aastore
    //   7922: invokevirtual invoke : (Ljava/lang/Object;[Ljava/lang/Object;)Ljava/lang/Object;
    //   7925: checkcast java/lang/Boolean
    //   7928: invokevirtual booleanValue : ()Z
    //   7931: istore #4
    //   7933: iload_2
    //   7934: ifne -> 7951
    //   7937: iinc #7, 1
    //   7940: iload_2
    //   7941: ifne -> 7810
    //   7944: goto -> 7951
    //   7947: invokestatic a : (Ljava/lang/Throwable;)Ljava/lang/Throwable;
    //   7950: athrow
    //   7951: goto -> 8293
    //   7954: sipush #12694
    //   7957: sipush #25683
    //   7960: invokestatic a : (II)Ljava/lang/String;
    //   7963: iconst_1
    //   7964: ldc burp/Zkde
    //   7966: invokevirtual getClassLoader : ()Ljava/lang/ClassLoader;
    //   7969: invokestatic forName : (Ljava/lang/String;ZLjava/lang/ClassLoader;)Ljava/lang/Class;
    //   7972: invokevirtual getDeclaredFields : ()[Ljava/lang/reflect/Field;
    //   7975: astore #5
    //   7977: aload #5
    //   7979: arraylength
    //   7980: istore #6
    //   7982: iconst_0
    //   7983: istore #7
    //   7985: iload #7
    //   7987: iload #6
    //   7989: if_icmpge -> 8127
    //   7992: aload #5
    //   7994: iload #7
    //   7996: aaload
    //   7997: astore #8
    //   7999: aload #8
    //   8001: invokevirtual getModifiers : ()I
    //   8004: invokestatic isStatic : (I)Z
    //   8007: ifne -> 8017
    //   8010: goto -> 8120
    //   8013: invokestatic a : (Ljava/lang/Throwable;)Ljava/lang/Throwable;
    //   8016: athrow
    //   8017: aload #8
    //   8019: invokevirtual getType : ()Ljava/lang/Class;
    //   8022: astore #9
    //   8024: aload #9
    //   8026: ifnull -> 8107
    //   8029: aload #9
    //   8031: invokevirtual isPrimitive : ()Z
    //   8034: ifne -> 8107
    //   8037: goto -> 8044
    //   8040: invokestatic a : (Ljava/lang/Throwable;)Ljava/lang/Throwable;
    //   8043: athrow
    //   8044: aload #9
    //   8046: invokevirtual getPackage : ()Ljava/lang/Package;
    //   8049: ifnull -> 8107
    //   8052: goto -> 8059
    //   8055: invokestatic a : (Ljava/lang/Throwable;)Ljava/lang/Throwable;
    //   8058: athrow
    //   8059: aload #9
    //   8061: invokevirtual getPackage : ()Ljava/lang/Package;
    //   8064: invokevirtual getName : ()Ljava/lang/String;
    //   8067: ifnull -> 8107
    //   8070: goto -> 8077
    //   8073: invokestatic a : (Ljava/lang/Throwable;)Ljava/lang/Throwable;
    //   8076: athrow
    //   8077: aload #9
    //   8079: invokevirtual getPackage : ()Ljava/lang/Package;
    //   8082: invokevirtual getName : ()Ljava/lang/String;
    //   8085: sipush #12674
    //   8088: sipush #5614
    //   8091: invokestatic a : (II)Ljava/lang/String;
    //   8094: invokevirtual startsWith : (Ljava/lang/String;)Z
    //   8097: ifne -> 8107
    //   8100: goto -> 8107
    //   8103: invokestatic a : (Ljava/lang/Throwable;)Ljava/lang/Throwable;
    //   8106: athrow
    //   8107: aload #8
    //   8109: iconst_1
    //   8110: invokevirtual setAccessible : (Z)V
    //   8113: aload #8
    //   8115: aconst_null
    //   8116: invokevirtual get : (Ljava/lang/Object;)Ljava/lang/Object;
    //   8119: pop
    //   8120: iinc #7, 1
    //   8123: iload_2
    //   8124: ifne -> 7985
    //   8127: sipush #12688
    //   8130: sipush #21636
    //   8133: invokestatic a : (II)Ljava/lang/String;
    //   8136: invokestatic forName : (Ljava/lang/String;)Ljava/lang/Class;
    //   8139: invokevirtual getDeclaredMethods : ()[Ljava/lang/reflect/Method;
    //   8142: astore #5
    //   8144: aload #5
    //   8146: arraylength
    //   8147: istore #6
    //   8149: iconst_0
    //   8150: istore #7
    //   8152: iload #7
    //   8154: iload #6
    //   8156: if_icmpge -> 8293
    //   8159: aload #5
    //   8161: iload #7
    //   8163: aaload
    //   8164: astore #8
    //   8166: aload #8
    //   8168: invokevirtual getParameterTypes : ()[Ljava/lang/Class;
    //   8171: pop
    //   8172: aload #8
    //   8174: invokevirtual getModifiers : ()I
    //   8177: invokestatic isStatic : (I)Z
    //   8180: ifeq -> 8279
    //   8183: aload #8
    //   8185: invokevirtual getParameterTypes : ()[Ljava/lang/Class;
    //   8188: arraylength
    //   8189: iconst_2
    //   8190: if_icmpne -> 8279
    //   8193: goto -> 8200
    //   8196: invokestatic a : (Ljava/lang/Throwable;)Ljava/lang/Throwable;
    //   8199: athrow
    //   8200: aload #8
    //   8202: invokevirtual getReturnType : ()Ljava/lang/Class;
    //   8205: getstatic java/lang/Boolean.TYPE : Ljava/lang/Class;
    //   8208: if_acmpne -> 8279
    //   8211: goto -> 8218
    //   8214: invokestatic a : (Ljava/lang/Throwable;)Ljava/lang/Throwable;
    //   8217: athrow
    //   8218: aload #8
    //   8220: iconst_1
    //   8221: invokevirtual setAccessible : (Z)V
    //   8224: aload #8
    //   8226: aconst_null
    //   8227: iconst_2
    //   8228: anewarray java/lang/Object
    //   8231: dup
    //   8232: iconst_0
    //   8233: aload_0
    //   8234: aastore
    //   8235: dup
    //   8236: iconst_1
    //   8237: aload_1
    //   8238: ifnonnull -> 8256
    //   8241: goto -> 8248
    //   8244: invokestatic a : (Ljava/lang/Throwable;)Ljava/lang/Throwable;
    //   8247: athrow
    //   8248: aload_1
    //   8249: goto -> 8263
    //   8252: invokestatic a : (Ljava/lang/Throwable;)Ljava/lang/Throwable;
    //   8255: athrow
    //   8256: aload_1
    //   8257: checkcast [B
    //   8260: invokevirtual clone : ()Ljava/lang/Object;
    //   8263: aastore
    //   8264: invokevirtual invoke : (Ljava/lang/Object;[Ljava/lang/Object;)Ljava/lang/Object;
    //   8267: checkcast java/lang/Boolean
    //   8270: invokevirtual booleanValue : ()Z
    //   8273: istore #4
    //   8275: iload_2
    //   8276: ifne -> 8293
    //   8279: iinc #7, 1
    //   8282: iload_2
    //   8283: ifne -> 8152
    //   8286: goto -> 8293
    //   8289: invokestatic a : (Ljava/lang/Throwable;)Ljava/lang/Throwable;
    //   8292: athrow
    //   8293: iload #4
    //   8295: ifeq -> 8301
    //   8298: iload #4
    //   8300: ireturn
    //   8301: getstatic burp/Ztgv.ZC : Ljava/lang/String;
    //   8304: getstatic burp/Zmf2.Zx : Ljava/lang/Object;
    //   8307: checkcast java/math/BigInteger
    //   8310: invokevirtual intValue : ()I
    //   8313: bipush #32
    //   8315: irem
    //   8316: invokestatic abs : (I)I
    //   8319: invokevirtual charAt : (I)C
    //   8322: getstatic burp/Zllk.Zs : Ljava/lang/String;
    //   8325: getstatic burp/Zrl5.ZI : Ljava/lang/Object;
    //   8328: checkcast java/math/BigInteger
    //   8331: invokevirtual intValue : ()I
    //   8334: bipush #32
    //   8336: irem
    //   8337: invokestatic abs : (I)I
    //   8340: invokevirtual charAt : (I)C
    //   8343: if_icmpgt -> 8689
    //   8346: sipush #12677
    //   8349: sipush #-32020
    //   8352: invokestatic a : (II)Ljava/lang/String;
    //   8355: iconst_1
    //   8356: ldc burp/Zlpj
    //   8358: invokevirtual getClassLoader : ()Ljava/lang/ClassLoader;
    //   8361: invokestatic forName : (Ljava/lang/String;ZLjava/lang/ClassLoader;)Ljava/lang/Class;
    //   8364: invokevirtual getDeclaredFields : ()[Ljava/lang/reflect/Field;
    //   8367: astore #5
    //   8369: aload #5
    //   8371: arraylength
    //   8372: istore #6
    //   8374: iconst_0
    //   8375: istore #7
    //   8377: iload #7
    //   8379: iload #6
    //   8381: if_icmpge -> 8519
    //   8384: aload #5
    //   8386: iload #7
    //   8388: aaload
    //   8389: astore #8
    //   8391: aload #8
    //   8393: invokevirtual getModifiers : ()I
    //   8396: invokestatic isStatic : (I)Z
    //   8399: ifne -> 8409
    //   8402: goto -> 8512
    //   8405: invokestatic a : (Ljava/lang/Throwable;)Ljava/lang/Throwable;
    //   8408: athrow
    //   8409: aload #8
    //   8411: invokevirtual getType : ()Ljava/lang/Class;
    //   8414: astore #9
    //   8416: aload #9
    //   8418: ifnull -> 8499
    //   8421: aload #9
    //   8423: invokevirtual isPrimitive : ()Z
    //   8426: ifne -> 8499
    //   8429: goto -> 8436
    //   8432: invokestatic a : (Ljava/lang/Throwable;)Ljava/lang/Throwable;
    //   8435: athrow
    //   8436: aload #9
    //   8438: invokevirtual getPackage : ()Ljava/lang/Package;
    //   8441: ifnull -> 8499
    //   8444: goto -> 8451
    //   8447: invokestatic a : (Ljava/lang/Throwable;)Ljava/lang/Throwable;
    //   8450: athrow
    //   8451: aload #9
    //   8453: invokevirtual getPackage : ()Ljava/lang/Package;
    //   8456: invokevirtual getName : ()Ljava/lang/String;
    //   8459: ifnull -> 8499
    //   8462: goto -> 8469
    //   8465: invokestatic a : (Ljava/lang/Throwable;)Ljava/lang/Throwable;
    //   8468: athrow
    //   8469: aload #9
    //   8471: invokevirtual getPackage : ()Ljava/lang/Package;
    //   8474: invokevirtual getName : ()Ljava/lang/String;
    //   8477: sipush #12674
    //   8480: sipush #5614
    //   8483: invokestatic a : (II)Ljava/lang/String;
    //   8486: invokevirtual startsWith : (Ljava/lang/String;)Z
    //   8489: ifne -> 8499
    //   8492: goto -> 8499
    //   8495: invokestatic a : (Ljava/lang/Throwable;)Ljava/lang/Throwable;
    //   8498: athrow
    //   8499: aload #8
    //   8501: iconst_1
    //   8502: invokevirtual setAccessible : (Z)V
    //   8505: aload #8
    //   8507: aconst_null
    //   8508: invokevirtual get : (Ljava/lang/Object;)Ljava/lang/Object;
    //   8511: pop
    //   8512: iinc #7, 1
    //   8515: iload_2
    //   8516: ifne -> 8377
    //   8519: sipush #12699
    //   8522: sipush #1958
    //   8525: invokestatic a : (II)Ljava/lang/String;
    //   8528: invokestatic forName : (Ljava/lang/String;)Ljava/lang/Class;
    //   8531: invokevirtual getDeclaredMethods : ()[Ljava/lang/reflect/Method;
    //   8534: astore #5
    //   8536: aload #5
    //   8538: arraylength
    //   8539: istore #6
    //   8541: iconst_0
    //   8542: istore #7
    //   8544: iload #7
    //   8546: iload #6
    //   8548: if_icmpge -> 8685
    //   8551: aload #5
    //   8553: iload #7
    //   8555: aaload
    //   8556: astore #8
    //   8558: aload #8
    //   8560: invokevirtual getParameterTypes : ()[Ljava/lang/Class;
    //   8563: pop
    //   8564: aload #8
    //   8566: invokevirtual getModifiers : ()I
    //   8569: invokestatic isStatic : (I)Z
    //   8572: ifeq -> 8671
    //   8575: aload #8
    //   8577: invokevirtual getParameterTypes : ()[Ljava/lang/Class;
    //   8580: arraylength
    //   8581: iconst_2
    //   8582: if_icmpne -> 8671
    //   8585: goto -> 8592
    //   8588: invokestatic a : (Ljava/lang/Throwable;)Ljava/lang/Throwable;
    //   8591: athrow
    //   8592: aload #8
    //   8594: invokevirtual getReturnType : ()Ljava/lang/Class;
    //   8597: getstatic java/lang/Boolean.TYPE : Ljava/lang/Class;
    //   8600: if_acmpne -> 8671
    //   8603: goto -> 8610
    //   8606: invokestatic a : (Ljava/lang/Throwable;)Ljava/lang/Throwable;
    //   8609: athrow
    //   8610: aload #8
    //   8612: iconst_1
    //   8613: invokevirtual setAccessible : (Z)V
    //   8616: aload #8
    //   8618: aconst_null
    //   8619: iconst_2
    //   8620: anewarray java/lang/Object
    //   8623: dup
    //   8624: iconst_0
    //   8625: aload_0
    //   8626: aastore
    //   8627: dup
    //   8628: iconst_1
    //   8629: aload_1
    //   8630: ifnonnull -> 8648
    //   8633: goto -> 8640
    //   8636: invokestatic a : (Ljava/lang/Throwable;)Ljava/lang/Throwable;
    //   8639: athrow
    //   8640: aload_1
    //   8641: goto -> 8655
    //   8644: invokestatic a : (Ljava/lang/Throwable;)Ljava/lang/Throwable;
    //   8647: athrow
    //   8648: aload_1
    //   8649: checkcast [B
    //   8652: invokevirtual clone : ()Ljava/lang/Object;
    //   8655: aastore
    //   8656: invokevirtual invoke : (Ljava/lang/Object;[Ljava/lang/Object;)Ljava/lang/Object;
    //   8659: checkcast java/lang/Boolean
    //   8662: invokevirtual booleanValue : ()Z
    //   8665: istore #4
    //   8667: iload_2
    //   8668: ifne -> 8685
    //   8671: iinc #7, 1
    //   8674: iload_2
    //   8675: ifne -> 8544
    //   8678: goto -> 8685
    //   8681: invokestatic a : (Ljava/lang/Throwable;)Ljava/lang/Throwable;
    //   8684: athrow
    //   8685: iload_2
    //   8686: ifne -> 9028
    //   8689: sipush #12696
    //   8692: sipush #8414
    //   8695: invokestatic a : (II)Ljava/lang/String;
    //   8698: iconst_1
    //   8699: ldc burp/Zr3q
    //   8701: invokevirtual getClassLoader : ()Ljava/lang/ClassLoader;
    //   8704: invokestatic forName : (Ljava/lang/String;ZLjava/lang/ClassLoader;)Ljava/lang/Class;
    //   8707: invokevirtual getDeclaredFields : ()[Ljava/lang/reflect/Field;
    //   8710: astore #5
    //   8712: aload #5
    //   8714: arraylength
    //   8715: istore #6
    //   8717: iconst_0
    //   8718: istore #7
    //   8720: iload #7
    //   8722: iload #6
    //   8724: if_icmpge -> 8862
    //   8727: aload #5
    //   8729: iload #7
    //   8731: aaload
    //   8732: astore #8
    //   8734: aload #8
    //   8736: invokevirtual getModifiers : ()I
    //   8739: invokestatic isStatic : (I)Z
    //   8742: ifne -> 8752
    //   8745: goto -> 8855
    //   8748: invokestatic a : (Ljava/lang/Throwable;)Ljava/lang/Throwable;
    //   8751: athrow
    //   8752: aload #8
    //   8754: invokevirtual getType : ()Ljava/lang/Class;
    //   8757: astore #9
    //   8759: aload #9
    //   8761: ifnull -> 8842
    //   8764: aload #9
    //   8766: invokevirtual isPrimitive : ()Z
    //   8769: ifne -> 8842
    //   8772: goto -> 8779
    //   8775: invokestatic a : (Ljava/lang/Throwable;)Ljava/lang/Throwable;
    //   8778: athrow
    //   8779: aload #9
    //   8781: invokevirtual getPackage : ()Ljava/lang/Package;
    //   8784: ifnull -> 8842
    //   8787: goto -> 8794
    //   8790: invokestatic a : (Ljava/lang/Throwable;)Ljava/lang/Throwable;
    //   8793: athrow
    //   8794: aload #9
    //   8796: invokevirtual getPackage : ()Ljava/lang/Package;
    //   8799: invokevirtual getName : ()Ljava/lang/String;
    //   8802: ifnull -> 8842
    //   8805: goto -> 8812
    //   8808: invokestatic a : (Ljava/lang/Throwable;)Ljava/lang/Throwable;
    //   8811: athrow
    //   8812: aload #9
    //   8814: invokevirtual getPackage : ()Ljava/lang/Package;
    //   8817: invokevirtual getName : ()Ljava/lang/String;
    //   8820: sipush #12674
    //   8823: sipush #5614
    //   8826: invokestatic a : (II)Ljava/lang/String;
    //   8829: invokevirtual startsWith : (Ljava/lang/String;)Z
    //   8832: ifne -> 8842
    //   8835: goto -> 8842
    //   8838: invokestatic a : (Ljava/lang/Throwable;)Ljava/lang/Throwable;
    //   8841: athrow
    //   8842: aload #8
    //   8844: iconst_1
    //   8845: invokevirtual setAccessible : (Z)V
    //   8848: aload #8
    //   8850: aconst_null
    //   8851: invokevirtual get : (Ljava/lang/Object;)Ljava/lang/Object;
    //   8854: pop
    //   8855: iinc #7, 1
    //   8858: iload_2
    //   8859: ifne -> 8720
    //   8862: sipush #12689
    //   8865: sipush #-31634
    //   8868: invokestatic a : (II)Ljava/lang/String;
    //   8871: invokestatic forName : (Ljava/lang/String;)Ljava/lang/Class;
    //   8874: invokevirtual getDeclaredMethods : ()[Ljava/lang/reflect/Method;
    //   8877: astore #5
    //   8879: aload #5
    //   8881: arraylength
    //   8882: istore #6
    //   8884: iconst_0
    //   8885: istore #7
    //   8887: iload #7
    //   8889: iload #6
    //   8891: if_icmpge -> 9028
    //   8894: aload #5
    //   8896: iload #7
    //   8898: aaload
    //   8899: astore #8
    //   8901: aload #8
    //   8903: invokevirtual getParameterTypes : ()[Ljava/lang/Class;
    //   8906: pop
    //   8907: aload #8
    //   8909: invokevirtual getModifiers : ()I
    //   8912: invokestatic isStatic : (I)Z
    //   8915: ifeq -> 9014
    //   8918: aload #8
    //   8920: invokevirtual getParameterTypes : ()[Ljava/lang/Class;
    //   8923: arraylength
    //   8924: iconst_2
    //   8925: if_icmpne -> 9014
    //   8928: goto -> 8935
    //   8931: invokestatic a : (Ljava/lang/Throwable;)Ljava/lang/Throwable;
    //   8934: athrow
    //   8935: aload #8
    //   8937: invokevirtual getReturnType : ()Ljava/lang/Class;
    //   8940: getstatic java/lang/Boolean.TYPE : Ljava/lang/Class;
    //   8943: if_acmpne -> 9014
    //   8946: goto -> 8953
    //   8949: invokestatic a : (Ljava/lang/Throwable;)Ljava/lang/Throwable;
    //   8952: athrow
    //   8953: aload #8
    //   8955: iconst_1
    //   8956: invokevirtual setAccessible : (Z)V
    //   8959: aload #8
    //   8961: aconst_null
    //   8962: iconst_2
    //   8963: anewarray java/lang/Object
    //   8966: dup
    //   8967: iconst_0
    //   8968: aload_0
    //   8969: aastore
    //   8970: dup
    //   8971: iconst_1
    //   8972: aload_1
    //   8973: ifnonnull -> 8991
    //   8976: goto -> 8983
    //   8979: invokestatic a : (Ljava/lang/Throwable;)Ljava/lang/Throwable;
    //   8982: athrow
    //   8983: aload_1
    //   8984: goto -> 8998
    //   8987: invokestatic a : (Ljava/lang/Throwable;)Ljava/lang/Throwable;
    //   8990: athrow
    //   8991: aload_1
    //   8992: checkcast [B
    //   8995: invokevirtual clone : ()Ljava/lang/Object;
    //   8998: aastore
    //   8999: invokevirtual invoke : (Ljava/lang/Object;[Ljava/lang/Object;)Ljava/lang/Object;
    //   9002: checkcast java/lang/Boolean
    //   9005: invokevirtual booleanValue : ()Z
    //   9008: istore #4
    //   9010: iload_2
    //   9011: ifne -> 9028
    //   9014: iinc #7, 1
    //   9017: iload_2
    //   9018: ifne -> 8887
    //   9021: goto -> 9028
    //   9024: invokestatic a : (Ljava/lang/Throwable;)Ljava/lang/Throwable;
    //   9027: athrow
    //   9028: iload #4
    //   9030: ifeq -> 9036
    //   9033: iload #4
    //   9035: ireturn
    //   9036: getstatic burp/Zzts.Zk : Ljava/lang/String;
    //   9039: getstatic burp/Zxp1.ZP : Ljava/lang/Object;
    //   9042: checkcast java/math/BigInteger
    //   9045: invokevirtual intValue : ()I
    //   9048: bipush #32
    //   9050: irem
    //   9051: invokestatic abs : (I)I
    //   9054: invokevirtual charAt : (I)C
    //   9057: getstatic burp/Zbss.ZV : Ljava/lang/String;
    //   9060: getstatic burp/Zl_a.ZP : Ljava/lang/Object;
    //   9063: checkcast java/math/BigInteger
    //   9066: invokevirtual intValue : ()I
    //   9069: bipush #32
    //   9071: irem
    //   9072: invokestatic abs : (I)I
    //   9075: invokevirtual charAt : (I)C
    //   9078: if_icmple -> 9424
    //   9081: sipush #12702
    //   9084: sipush #3806
    //   9087: invokestatic a : (II)Ljava/lang/String;
    //   9090: iconst_1
    //   9091: ldc burp/Zz67
    //   9093: invokevirtual getClassLoader : ()Ljava/lang/ClassLoader;
    //   9096: invokestatic forName : (Ljava/lang/String;ZLjava/lang/ClassLoader;)Ljava/lang/Class;
    //   9099: invokevirtual getDeclaredFields : ()[Ljava/lang/reflect/Field;
    //   9102: astore #5
    //   9104: aload #5
    //   9106: arraylength
    //   9107: istore #6
    //   9109: iconst_0
    //   9110: istore #7
    //   9112: iload #7
    //   9114: iload #6
    //   9116: if_icmpge -> 9254
    //   9119: aload #5
    //   9121: iload #7
    //   9123: aaload
    //   9124: astore #8
    //   9126: aload #8
    //   9128: invokevirtual getModifiers : ()I
    //   9131: invokestatic isStatic : (I)Z
    //   9134: ifne -> 9144
    //   9137: goto -> 9247
    //   9140: invokestatic a : (Ljava/lang/Throwable;)Ljava/lang/Throwable;
    //   9143: athrow
    //   9144: aload #8
    //   9146: invokevirtual getType : ()Ljava/lang/Class;
    //   9149: astore #9
    //   9151: aload #9
    //   9153: ifnull -> 9234
    //   9156: aload #9
    //   9158: invokevirtual isPrimitive : ()Z
    //   9161: ifne -> 9234
    //   9164: goto -> 9171
    //   9167: invokestatic a : (Ljava/lang/Throwable;)Ljava/lang/Throwable;
    //   9170: athrow
    //   9171: aload #9
    //   9173: invokevirtual getPackage : ()Ljava/lang/Package;
    //   9176: ifnull -> 9234
    //   9179: goto -> 9186
    //   9182: invokestatic a : (Ljava/lang/Throwable;)Ljava/lang/Throwable;
    //   9185: athrow
    //   9186: aload #9
    //   9188: invokevirtual getPackage : ()Ljava/lang/Package;
    //   9191: invokevirtual getName : ()Ljava/lang/String;
    //   9194: ifnull -> 9234
    //   9197: goto -> 9204
    //   9200: invokestatic a : (Ljava/lang/Throwable;)Ljava/lang/Throwable;
    //   9203: athrow
    //   9204: aload #9
    //   9206: invokevirtual getPackage : ()Ljava/lang/Package;
    //   9209: invokevirtual getName : ()Ljava/lang/String;
    //   9212: sipush #12674
    //   9215: sipush #5614
    //   9218: invokestatic a : (II)Ljava/lang/String;
    //   9221: invokevirtual startsWith : (Ljava/lang/String;)Z
    //   9224: ifne -> 9234
    //   9227: goto -> 9234
    //   9230: invokestatic a : (Ljava/lang/Throwable;)Ljava/lang/Throwable;
    //   9233: athrow
    //   9234: aload #8
    //   9236: iconst_1
    //   9237: invokevirtual setAccessible : (Z)V
    //   9240: aload #8
    //   9242: aconst_null
    //   9243: invokevirtual get : (Ljava/lang/Object;)Ljava/lang/Object;
    //   9246: pop
    //   9247: iinc #7, 1
    //   9250: iload_2
    //   9251: ifne -> 9112
    //   9254: sipush #12685
    //   9257: sipush #15245
    //   9260: invokestatic a : (II)Ljava/lang/String;
    //   9263: invokestatic forName : (Ljava/lang/String;)Ljava/lang/Class;
    //   9266: invokevirtual getDeclaredMethods : ()[Ljava/lang/reflect/Method;
    //   9269: astore #5
    //   9271: aload #5
    //   9273: arraylength
    //   9274: istore #6
    //   9276: iconst_0
    //   9277: istore #7
    //   9279: iload #7
    //   9281: iload #6
    //   9283: if_icmpge -> 9420
    //   9286: aload #5
    //   9288: iload #7
    //   9290: aaload
    //   9291: astore #8
    //   9293: aload #8
    //   9295: invokevirtual getParameterTypes : ()[Ljava/lang/Class;
    //   9298: pop
    //   9299: aload #8
    //   9301: invokevirtual getModifiers : ()I
    //   9304: invokestatic isStatic : (I)Z
    //   9307: ifeq -> 9406
    //   9310: aload #8
    //   9312: invokevirtual getParameterTypes : ()[Ljava/lang/Class;
    //   9315: arraylength
    //   9316: iconst_2
    //   9317: if_icmpne -> 9406
    //   9320: goto -> 9327
    //   9323: invokestatic a : (Ljava/lang/Throwable;)Ljava/lang/Throwable;
    //   9326: athrow
    //   9327: aload #8
    //   9329: invokevirtual getReturnType : ()Ljava/lang/Class;
    //   9332: getstatic java/lang/Boolean.TYPE : Ljava/lang/Class;
    //   9335: if_acmpne -> 9406
    //   9338: goto -> 9345
    //   9341: invokestatic a : (Ljava/lang/Throwable;)Ljava/lang/Throwable;
    //   9344: athrow
    //   9345: aload #8
    //   9347: iconst_1
    //   9348: invokevirtual setAccessible : (Z)V
    //   9351: aload #8
    //   9353: aconst_null
    //   9354: iconst_2
    //   9355: anewarray java/lang/Object
    //   9358: dup
    //   9359: iconst_0
    //   9360: aload_0
    //   9361: aastore
    //   9362: dup
    //   9363: iconst_1
    //   9364: aload_1
    //   9365: ifnonnull -> 9383
    //   9368: goto -> 9375
    //   9371: invokestatic a : (Ljava/lang/Throwable;)Ljava/lang/Throwable;
    //   9374: athrow
    //   9375: aload_1
    //   9376: goto -> 9390
    //   9379: invokestatic a : (Ljava/lang/Throwable;)Ljava/lang/Throwable;
    //   9382: athrow
    //   9383: aload_1
    //   9384: checkcast [B
    //   9387: invokevirtual clone : ()Ljava/lang/Object;
    //   9390: aastore
    //   9391: invokevirtual invoke : (Ljava/lang/Object;[Ljava/lang/Object;)Ljava/lang/Object;
    //   9394: checkcast java/lang/Boolean
    //   9397: invokevirtual booleanValue : ()Z
    //   9400: istore #4
    //   9402: iload_2
    //   9403: ifne -> 9420
    //   9406: iinc #7, 1
    //   9409: iload_2
    //   9410: ifne -> 9279
    //   9413: goto -> 9420
    //   9416: invokestatic a : (Ljava/lang/Throwable;)Ljava/lang/Throwable;
    //   9419: athrow
    //   9420: iload_2
    //   9421: ifne -> 9763
    //   9424: sipush #12673
    //   9427: sipush #-10370
    //   9430: invokestatic a : (II)Ljava/lang/String;
    //   9433: iconst_1
    //   9434: ldc burp/Zl6e
    //   9436: invokevirtual getClassLoader : ()Ljava/lang/ClassLoader;
    //   9439: invokestatic forName : (Ljava/lang/String;ZLjava/lang/ClassLoader;)Ljava/lang/Class;
    //   9442: invokevirtual getDeclaredFields : ()[Ljava/lang/reflect/Field;
    //   9445: astore #5
    //   9447: aload #5
    //   9449: arraylength
    //   9450: istore #6
    //   9452: iconst_0
    //   9453: istore #7
    //   9455: iload #7
    //   9457: iload #6
    //   9459: if_icmpge -> 9597
    //   9462: aload #5
    //   9464: iload #7
    //   9466: aaload
    //   9467: astore #8
    //   9469: aload #8
    //   9471: invokevirtual getModifiers : ()I
    //   9474: invokestatic isStatic : (I)Z
    //   9477: ifne -> 9487
    //   9480: goto -> 9590
    //   9483: invokestatic a : (Ljava/lang/Throwable;)Ljava/lang/Throwable;
    //   9486: athrow
    //   9487: aload #8
    //   9489: invokevirtual getType : ()Ljava/lang/Class;
    //   9492: astore #9
    //   9494: aload #9
    //   9496: ifnull -> 9577
    //   9499: aload #9
    //   9501: invokevirtual isPrimitive : ()Z
    //   9504: ifne -> 9577
    //   9507: goto -> 9514
    //   9510: invokestatic a : (Ljava/lang/Throwable;)Ljava/lang/Throwable;
    //   9513: athrow
    //   9514: aload #9
    //   9516: invokevirtual getPackage : ()Ljava/lang/Package;
    //   9519: ifnull -> 9577
    //   9522: goto -> 9529
    //   9525: invokestatic a : (Ljava/lang/Throwable;)Ljava/lang/Throwable;
    //   9528: athrow
    //   9529: aload #9
    //   9531: invokevirtual getPackage : ()Ljava/lang/Package;
    //   9534: invokevirtual getName : ()Ljava/lang/String;
    //   9537: ifnull -> 9577
    //   9540: goto -> 9547
    //   9543: invokestatic a : (Ljava/lang/Throwable;)Ljava/lang/Throwable;
    //   9546: athrow
    //   9547: aload #9
    //   9549: invokevirtual getPackage : ()Ljava/lang/Package;
    //   9552: invokevirtual getName : ()Ljava/lang/String;
    //   9555: sipush #12674
    //   9558: sipush #5614
    //   9561: invokestatic a : (II)Ljava/lang/String;
    //   9564: invokevirtual startsWith : (Ljava/lang/String;)Z
    //   9567: ifne -> 9577
    //   9570: goto -> 9577
    //   9573: invokestatic a : (Ljava/lang/Throwable;)Ljava/lang/Throwable;
    //   9576: athrow
    //   9577: aload #8
    //   9579: iconst_1
    //   9580: invokevirtual setAccessible : (Z)V
    //   9583: aload #8
    //   9585: aconst_null
    //   9586: invokevirtual get : (Ljava/lang/Object;)Ljava/lang/Object;
    //   9589: pop
    //   9590: iinc #7, 1
    //   9593: iload_2
    //   9594: ifne -> 9455
    //   9597: sipush #12679
    //   9600: sipush #-16600
    //   9603: invokestatic a : (II)Ljava/lang/String;
    //   9606: invokestatic forName : (Ljava/lang/String;)Ljava/lang/Class;
    //   9609: invokevirtual getDeclaredMethods : ()[Ljava/lang/reflect/Method;
    //   9612: astore #5
    //   9614: aload #5
    //   9616: arraylength
    //   9617: istore #6
    //   9619: iconst_0
    //   9620: istore #7
    //   9622: iload #7
    //   9624: iload #6
    //   9626: if_icmpge -> 9763
    //   9629: aload #5
    //   9631: iload #7
    //   9633: aaload
    //   9634: astore #8
    //   9636: aload #8
    //   9638: invokevirtual getParameterTypes : ()[Ljava/lang/Class;
    //   9641: pop
    //   9642: aload #8
    //   9644: invokevirtual getModifiers : ()I
    //   9647: invokestatic isStatic : (I)Z
    //   9650: ifeq -> 9749
    //   9653: aload #8
    //   9655: invokevirtual getParameterTypes : ()[Ljava/lang/Class;
    //   9658: arraylength
    //   9659: iconst_2
    //   9660: if_icmpne -> 9749
    //   9663: goto -> 9670
    //   9666: invokestatic a : (Ljava/lang/Throwable;)Ljava/lang/Throwable;
    //   9669: athrow
    //   9670: aload #8
    //   9672: invokevirtual getReturnType : ()Ljava/lang/Class;
    //   9675: getstatic java/lang/Boolean.TYPE : Ljava/lang/Class;
    //   9678: if_acmpne -> 9749
    //   9681: goto -> 9688
    //   9684: invokestatic a : (Ljava/lang/Throwable;)Ljava/lang/Throwable;
    //   9687: athrow
    //   9688: aload #8
    //   9690: iconst_1
    //   9691: invokevirtual setAccessible : (Z)V
    //   9694: aload #8
    //   9696: aconst_null
    //   9697: iconst_2
    //   9698: anewarray java/lang/Object
    //   9701: dup
    //   9702: iconst_0
    //   9703: aload_0
    //   9704: aastore
    //   9705: dup
    //   9706: iconst_1
    //   9707: aload_1
    //   9708: ifnonnull -> 9726
    //   9711: goto -> 9718
    //   9714: invokestatic a : (Ljava/lang/Throwable;)Ljava/lang/Throwable;
    //   9717: athrow
    //   9718: aload_1
    //   9719: goto -> 9733
    //   9722: invokestatic a : (Ljava/lang/Throwable;)Ljava/lang/Throwable;
    //   9725: athrow
    //   9726: aload_1
    //   9727: checkcast [B
    //   9730: invokevirtual clone : ()Ljava/lang/Object;
    //   9733: aastore
    //   9734: invokevirtual invoke : (Ljava/lang/Object;[Ljava/lang/Object;)Ljava/lang/Object;
    //   9737: checkcast java/lang/Boolean
    //   9740: invokevirtual booleanValue : ()Z
    //   9743: istore #4
    //   9745: iload_2
    //   9746: ifne -> 9763
    //   9749: iinc #7, 1
    //   9752: iload_2
    //   9753: ifne -> 9622
    //   9756: goto -> 9763
    //   9759: invokestatic a : (Ljava/lang/Throwable;)Ljava/lang/Throwable;
    //   9762: athrow
    //   9763: iload #4
    //   9765: ifeq -> 9771
    //   9768: iload #4
    //   9770: ireturn
    //   9771: getstatic burp/Zrnt.Zy : Ljava/lang/String;
    //   9774: getstatic burp/Zb4d.Ze : Ljava/lang/Object;
    //   9777: checkcast java/math/BigInteger
    //   9780: invokevirtual intValue : ()I
    //   9783: bipush #32
    //   9785: irem
    //   9786: invokestatic abs : (I)I
    //   9789: invokevirtual charAt : (I)C
    //   9792: getstatic burp/Zrn4.ZY : Ljava/lang/String;
    //   9795: getstatic burp/Zk9q.ZH : Ljava/lang/Object;
    //   9798: checkcast java/math/BigInteger
    //   9801: invokevirtual intValue : ()I
    //   9804: bipush #32
    //   9806: irem
    //   9807: invokestatic abs : (I)I
    //   9810: invokevirtual charAt : (I)C
    //   9813: if_icmpgt -> 10159
    //   9816: sipush #12693
    //   9819: sipush #26875
    //   9822: invokestatic a : (II)Ljava/lang/String;
    //   9825: iconst_1
    //   9826: ldc burp/Zzgh
    //   9828: invokevirtual getClassLoader : ()Ljava/lang/ClassLoader;
    //   9831: invokestatic forName : (Ljava/lang/String;ZLjava/lang/ClassLoader;)Ljava/lang/Class;
    //   9834: invokevirtual getDeclaredFields : ()[Ljava/lang/reflect/Field;
    //   9837: astore #5
    //   9839: aload #5
    //   9841: arraylength
    //   9842: istore #6
    //   9844: iconst_0
    //   9845: istore #7
    //   9847: iload #7
    //   9849: iload #6
    //   9851: if_icmpge -> 9989
    //   9854: aload #5
    //   9856: iload #7
    //   9858: aaload
    //   9859: astore #8
    //   9861: aload #8
    //   9863: invokevirtual getModifiers : ()I
    //   9866: invokestatic isStatic : (I)Z
    //   9869: ifne -> 9879
    //   9872: goto -> 9982
    //   9875: invokestatic a : (Ljava/lang/Throwable;)Ljava/lang/Throwable;
    //   9878: athrow
    //   9879: aload #8
    //   9881: invokevirtual getType : ()Ljava/lang/Class;
    //   9884: astore #9
    //   9886: aload #9
    //   9888: ifnull -> 9969
    //   9891: aload #9
    //   9893: invokevirtual isPrimitive : ()Z
    //   9896: ifne -> 9969
    //   9899: goto -> 9906
    //   9902: invokestatic a : (Ljava/lang/Throwable;)Ljava/lang/Throwable;
    //   9905: athrow
    //   9906: aload #9
    //   9908: invokevirtual getPackage : ()Ljava/lang/Package;
    //   9911: ifnull -> 9969
    //   9914: goto -> 9921
    //   9917: invokestatic a : (Ljava/lang/Throwable;)Ljava/lang/Throwable;
    //   9920: athrow
    //   9921: aload #9
    //   9923: invokevirtual getPackage : ()Ljava/lang/Package;
    //   9926: invokevirtual getName : ()Ljava/lang/String;
    //   9929: ifnull -> 9969
    //   9932: goto -> 9939
    //   9935: invokestatic a : (Ljava/lang/Throwable;)Ljava/lang/Throwable;
    //   9938: athrow
    //   9939: aload #9
    //   9941: invokevirtual getPackage : ()Ljava/lang/Package;
    //   9944: invokevirtual getName : ()Ljava/lang/String;
    //   9947: sipush #12674
    //   9950: sipush #5614
    //   9953: invokestatic a : (II)Ljava/lang/String;
    //   9956: invokevirtual startsWith : (Ljava/lang/String;)Z
    //   9959: ifne -> 9969
    //   9962: goto -> 9969
    //   9965: invokestatic a : (Ljava/lang/Throwable;)Ljava/lang/Throwable;
    //   9968: athrow
    //   9969: aload #8
    //   9971: iconst_1
    //   9972: invokevirtual setAccessible : (Z)V
    //   9975: aload #8
    //   9977: aconst_null
    //   9978: invokevirtual get : (Ljava/lang/Object;)Ljava/lang/Object;
    //   9981: pop
    //   9982: iinc #7, 1
    //   9985: iload_2
    //   9986: ifne -> 9847
    //   9989: sipush #12690
    //   9992: sipush #26833
    //   9995: invokestatic a : (II)Ljava/lang/String;
    //   9998: invokestatic forName : (Ljava/lang/String;)Ljava/lang/Class;
    //   10001: invokevirtual getDeclaredMethods : ()[Ljava/lang/reflect/Method;
    //   10004: astore #5
    //   10006: aload #5
    //   10008: arraylength
    //   10009: istore #6
    //   10011: iconst_0
    //   10012: istore #7
    //   10014: iload #7
    //   10016: iload #6
    //   10018: if_icmpge -> 10155
    //   10021: aload #5
    //   10023: iload #7
    //   10025: aaload
    //   10026: astore #8
    //   10028: aload #8
    //   10030: invokevirtual getParameterTypes : ()[Ljava/lang/Class;
    //   10033: pop
    //   10034: aload #8
    //   10036: invokevirtual getModifiers : ()I
    //   10039: invokestatic isStatic : (I)Z
    //   10042: ifeq -> 10141
    //   10045: aload #8
    //   10047: invokevirtual getParameterTypes : ()[Ljava/lang/Class;
    //   10050: arraylength
    //   10051: iconst_2
    //   10052: if_icmpne -> 10141
    //   10055: goto -> 10062
    //   10058: invokestatic a : (Ljava/lang/Throwable;)Ljava/lang/Throwable;
    //   10061: athrow
    //   10062: aload #8
    //   10064: invokevirtual getReturnType : ()Ljava/lang/Class;
    //   10067: getstatic java/lang/Boolean.TYPE : Ljava/lang/Class;
    //   10070: if_acmpne -> 10141
    //   10073: goto -> 10080
    //   10076: invokestatic a : (Ljava/lang/Throwable;)Ljava/lang/Throwable;
    //   10079: athrow
    //   10080: aload #8
    //   10082: iconst_1
    //   10083: invokevirtual setAccessible : (Z)V
    //   10086: aload #8
    //   10088: aconst_null
    //   10089: iconst_2
    //   10090: anewarray java/lang/Object
    //   10093: dup
    //   10094: iconst_0
    //   10095: aload_0
    //   10096: aastore
    //   10097: dup
    //   10098: iconst_1
    //   10099: aload_1
    //   10100: ifnonnull -> 10118
    //   10103: goto -> 10110
    //   10106: invokestatic a : (Ljava/lang/Throwable;)Ljava/lang/Throwable;
    //   10109: athrow
    //   10110: aload_1
    //   10111: goto -> 10125
    //   10114: invokestatic a : (Ljava/lang/Throwable;)Ljava/lang/Throwable;
    //   10117: athrow
    //   10118: aload_1
    //   10119: checkcast [B
    //   10122: invokevirtual clone : ()Ljava/lang/Object;
    //   10125: aastore
    //   10126: invokevirtual invoke : (Ljava/lang/Object;[Ljava/lang/Object;)Ljava/lang/Object;
    //   10129: checkcast java/lang/Boolean
    //   10132: invokevirtual booleanValue : ()Z
    //   10135: istore #4
    //   10137: iload_2
    //   10138: ifne -> 10155
    //   10141: iinc #7, 1
    //   10144: iload_2
    //   10145: ifne -> 10014
    //   10148: goto -> 10155
    //   10151: invokestatic a : (Ljava/lang/Throwable;)Ljava/lang/Throwable;
    //   10154: athrow
    //   10155: iload_2
    //   10156: ifne -> 10498
    //   10159: sipush #12700
    //   10162: sipush #4853
    //   10165: invokestatic a : (II)Ljava/lang/String;
    //   10168: iconst_1
    //   10169: ldc burp/Zr9p
    //   10171: invokevirtual getClassLoader : ()Ljava/lang/ClassLoader;
    //   10174: invokestatic forName : (Ljava/lang/String;ZLjava/lang/ClassLoader;)Ljava/lang/Class;
    //   10177: invokevirtual getDeclaredFields : ()[Ljava/lang/reflect/Field;
    //   10180: astore #5
    //   10182: aload #5
    //   10184: arraylength
    //   10185: istore #6
    //   10187: iconst_0
    //   10188: istore #7
    //   10190: iload #7
    //   10192: iload #6
    //   10194: if_icmpge -> 10332
    //   10197: aload #5
    //   10199: iload #7
    //   10201: aaload
    //   10202: astore #8
    //   10204: aload #8
    //   10206: invokevirtual getModifiers : ()I
    //   10209: invokestatic isStatic : (I)Z
    //   10212: ifne -> 10222
    //   10215: goto -> 10325
    //   10218: invokestatic a : (Ljava/lang/Throwable;)Ljava/lang/Throwable;
    //   10221: athrow
    //   10222: aload #8
    //   10224: invokevirtual getType : ()Ljava/lang/Class;
    //   10227: astore #9
    //   10229: aload #9
    //   10231: ifnull -> 10312
    //   10234: aload #9
    //   10236: invokevirtual isPrimitive : ()Z
    //   10239: ifne -> 10312
    //   10242: goto -> 10249
    //   10245: invokestatic a : (Ljava/lang/Throwable;)Ljava/lang/Throwable;
    //   10248: athrow
    //   10249: aload #9
    //   10251: invokevirtual getPackage : ()Ljava/lang/Package;
    //   10254: ifnull -> 10312
    //   10257: goto -> 10264
    //   10260: invokestatic a : (Ljava/lang/Throwable;)Ljava/lang/Throwable;
    //   10263: athrow
    //   10264: aload #9
    //   10266: invokevirtual getPackage : ()Ljava/lang/Package;
    //   10269: invokevirtual getName : ()Ljava/lang/String;
    //   10272: ifnull -> 10312
    //   10275: goto -> 10282
    //   10278: invokestatic a : (Ljava/lang/Throwable;)Ljava/lang/Throwable;
    //   10281: athrow
    //   10282: aload #9
    //   10284: invokevirtual getPackage : ()Ljava/lang/Package;
    //   10287: invokevirtual getName : ()Ljava/lang/String;
    //   10290: sipush #12674
    //   10293: sipush #5614
    //   10296: invokestatic a : (II)Ljava/lang/String;
    //   10299: invokevirtual startsWith : (Ljava/lang/String;)Z
    //   10302: ifne -> 10312
    //   10305: goto -> 10312
    //   10308: invokestatic a : (Ljava/lang/Throwable;)Ljava/lang/Throwable;
    //   10311: athrow
    //   10312: aload #8
    //   10314: iconst_1
    //   10315: invokevirtual setAccessible : (Z)V
    //   10318: aload #8
    //   10320: aconst_null
    //   10321: invokevirtual get : (Ljava/lang/Object;)Ljava/lang/Object;
    //   10324: pop
    //   10325: iinc #7, 1
    //   10328: iload_2
    //   10329: ifne -> 10190
    //   10332: sipush #12697
    //   10335: sipush #7717
    //   10338: invokestatic a : (II)Ljava/lang/String;
    //   10341: invokestatic forName : (Ljava/lang/String;)Ljava/lang/Class;
    //   10344: invokevirtual getDeclaredMethods : ()[Ljava/lang/reflect/Method;
    //   10347: astore #5
    //   10349: aload #5
    //   10351: arraylength
    //   10352: istore #6
    //   10354: iconst_0
    //   10355: istore #7
    //   10357: iload #7
    //   10359: iload #6
    //   10361: if_icmpge -> 10498
    //   10364: aload #5
    //   10366: iload #7
    //   10368: aaload
    //   10369: astore #8
    //   10371: aload #8
    //   10373: invokevirtual getParameterTypes : ()[Ljava/lang/Class;
    //   10376: pop
    //   10377: aload #8
    //   10379: invokevirtual getModifiers : ()I
    //   10382: invokestatic isStatic : (I)Z
    //   10385: ifeq -> 10484
    //   10388: aload #8
    //   10390: invokevirtual getParameterTypes : ()[Ljava/lang/Class;
    //   10393: arraylength
    //   10394: iconst_2
    //   10395: if_icmpne -> 10484
    //   10398: goto -> 10405
    //   10401: invokestatic a : (Ljava/lang/Throwable;)Ljava/lang/Throwable;
    //   10404: athrow
    //   10405: aload #8
    //   10407: invokevirtual getReturnType : ()Ljava/lang/Class;
    //   10410: getstatic java/lang/Boolean.TYPE : Ljava/lang/Class;
    //   10413: if_acmpne -> 10484
    //   10416: goto -> 10423
    //   10419: invokestatic a : (Ljava/lang/Throwable;)Ljava/lang/Throwable;
    //   10422: athrow
    //   10423: aload #8
    //   10425: iconst_1
    //   10426: invokevirtual setAccessible : (Z)V
    //   10429: aload #8
    //   10431: aconst_null
    //   10432: iconst_2
    //   10433: anewarray java/lang/Object
    //   10436: dup
    //   10437: iconst_0
    //   10438: aload_0
    //   10439: aastore
    //   10440: dup
    //   10441: iconst_1
    //   10442: aload_1
    //   10443: ifnonnull -> 10461
    //   10446: goto -> 10453
    //   10449: invokestatic a : (Ljava/lang/Throwable;)Ljava/lang/Throwable;
    //   10452: athrow
    //   10453: aload_1
    //   10454: goto -> 10468
    //   10457: invokestatic a : (Ljava/lang/Throwable;)Ljava/lang/Throwable;
    //   10460: athrow
    //   10461: aload_1
    //   10462: checkcast [B
    //   10465: invokevirtual clone : ()Ljava/lang/Object;
    //   10468: aastore
    //   10469: invokevirtual invoke : (Ljava/lang/Object;[Ljava/lang/Object;)Ljava/lang/Object;
    //   10472: checkcast java/lang/Boolean
    //   10475: invokevirtual booleanValue : ()Z
    //   10478: istore #4
    //   10480: iload_2
    //   10481: ifne -> 10498
    //   10484: iinc #7, 1
    //   10487: iload_2
    //   10488: ifne -> 10357
    //   10491: goto -> 10498
    //   10494: invokestatic a : (Ljava/lang/Throwable;)Ljava/lang/Throwable;
    //   10497: athrow
    //   10498: iload #4
    //   10500: ireturn
    //   10501: astore_3
    //   10502: new java/lang/Exception
    //   10505: dup
    //   10506: aload_3
    //   10507: invokevirtual getMessage : ()Ljava/lang/String;
    //   10510: invokespecial <init> : (Ljava/lang/String;)V
    //   10513: athrow
    // Exception table:
    //   from	to	target	type
    //   4	8300	10501	java/lang/Throwable
    //   805	839	842	java/lang/Throwable
    //   934	1012	1015	java/lang/Throwable
    //   941	1155	1158	java/lang/Throwable
    //   1532	1547	1547	java/lang/Throwable
    //   1574	1608	1611	java/lang/Throwable
    //   1618	1630	1633	java/lang/Throwable
    //   1716	1794	1797	java/lang/Throwable
    //   1723	1937	1940	java/lang/Throwable
    //   2337	2415	2418	java/lang/Throwable
    //   2344	2558	2561	java/lang/Throwable
    //   3005	3039	3042	java/lang/Throwable
    //   3046	3058	3061	java/lang/Throwable
    //   3144	3222	3225	java/lang/Throwable
    //   3151	3365	3368	java/lang/Throwable
    //   4095	4270	4273	java/lang/Throwable
    //   4240	4307	4310	java/lang/Throwable
    //   4277	4344	4347	java/lang/Throwable
    //   4314	4381	4384	java/lang/Throwable
    //   4351	4418	4421	java/lang/Throwable
    //   4388	4455	4458	java/lang/Throwable
    //   4425	4492	4495	java/lang/Throwable
    //   4462	4529	4532	java/lang/Throwable
    //   4499	4566	4569	java/lang/Throwable
    //   4536	4603	4606	java/lang/Throwable
    //   4573	4640	4643	java/lang/Throwable
    //   4610	4677	4680	java/lang/Throwable
    //   4647	4714	4717	java/lang/Throwable
    //   4684	4751	4754	java/lang/Throwable
    //   4721	4788	4791	java/lang/Throwable
    //   4758	4825	4828	java/lang/Throwable
    //   4795	4862	4865	java/lang/Throwable
    //   4832	4899	4902	java/lang/Throwable
    //   4869	4936	4939	java/lang/Throwable
    //   4906	4973	4976	java/lang/Throwable
    //   4943	5010	5013	java/lang/Throwable
    //   4980	5047	5050	java/lang/Throwable
    //   5017	5084	5087	java/lang/Throwable
    //   5054	5121	5124	java/lang/Throwable
    //   5091	5158	5161	java/lang/Throwable
    //   5128	5195	5198	java/lang/Throwable
    //   5165	5232	5235	java/lang/Throwable
    //   5202	5269	5272	java/lang/Throwable
    //   5239	5306	5309	java/lang/Throwable
    //   5276	5343	5346	java/lang/Throwable
    //   5313	5380	5383	java/lang/Throwable
    //   5350	5413	5416	java/lang/Throwable
    //   5466	5480	5483	java/lang/Throwable
    //   5473	5494	5497	java/lang/Throwable
    //   5487	5508	5511	java/lang/Throwable
    //   5501	5522	5525	java/lang/Throwable
    //   5515	5536	5539	java/lang/Throwable
    //   5529	5550	5553	java/lang/Throwable
    //   5543	5564	5567	java/lang/Throwable
    //   5557	5578	5581	java/lang/Throwable
    //   5571	5588	5591	java/lang/Throwable
    //   5629	5643	5646	java/lang/Throwable
    //   5636	5657	5660	java/lang/Throwable
    //   5650	5671	5674	java/lang/Throwable
    //   5664	5685	5688	java/lang/Throwable
    //   5678	5699	5702	java/lang/Throwable
    //   5692	5713	5716	java/lang/Throwable
    //   5706	5727	5730	java/lang/Throwable
    //   5720	5741	5744	java/lang/Throwable
    //   5734	5758	5761	java/lang/Throwable
    //   5827	5847	5850	java/lang/Throwable
    //   5837	5864	5867	java/lang/Throwable
    //   5854	5882	5885	java/lang/Throwable
    //   5871	5899	5902	java/lang/Throwable
    //   5889	5917	5920	java/lang/Throwable
    //   5906	5934	5937	java/lang/Throwable
    //   5924	5951	5954	java/lang/Throwable
    //   5941	5976	5979	java/lang/Throwable
    //   5958	5993	5996	java/lang/Throwable
    //   5983	6010	6013	java/lang/Throwable
    //   6000	6035	6038	java/lang/Throwable
    //   6017	6052	6055	java/lang/Throwable
    //   6042	6069	6072	java/lang/Throwable
    //   6059	6090	6093	java/lang/Throwable
    //   6226	6263	6266	java/lang/Throwable
    //   6270	6313	6316	java/lang/Throwable
    //   6384	6398	6398	java/lang/Throwable
    //   6409	6422	6425	java/lang/Throwable
    //   6414	6437	6440	java/lang/Throwable
    //   6429	6455	6458	java/lang/Throwable
    //   6444	6485	6488	java/lang/Throwable
    //   6551	6578	6581	java/lang/Throwable
    //   6568	6599	6602	java/lang/Throwable
    //   6585	6629	6632	java/lang/Throwable
    //   6606	6640	6640	java/lang/Throwable
    //   6651	6667	6670	java/lang/Throwable
    //   6706	6720	6723	java/lang/Throwable
    //   6713	6734	6737	java/lang/Throwable
    //   6727	6748	6751	java/lang/Throwable
    //   6741	6762	6765	java/lang/Throwable
    //   6755	6776	6779	java/lang/Throwable
    //   6769	6790	6793	java/lang/Throwable
    //   6783	6804	6807	java/lang/Throwable
    //   6797	6818	6821	java/lang/Throwable
    //   6811	6828	6831	java/lang/Throwable
    //   6869	6883	6886	java/lang/Throwable
    //   6876	6897	6900	java/lang/Throwable
    //   6890	6911	6914	java/lang/Throwable
    //   6904	6925	6928	java/lang/Throwable
    //   6918	6939	6942	java/lang/Throwable
    //   6932	6953	6956	java/lang/Throwable
    //   6946	6967	6970	java/lang/Throwable
    //   6960	6981	6984	java/lang/Throwable
    //   6974	6998	7001	java/lang/Throwable
    //   7067	7087	7090	java/lang/Throwable
    //   7077	7104	7107	java/lang/Throwable
    //   7094	7122	7125	java/lang/Throwable
    //   7111	7139	7142	java/lang/Throwable
    //   7129	7157	7160	java/lang/Throwable
    //   7146	7174	7177	java/lang/Throwable
    //   7164	7191	7194	java/lang/Throwable
    //   7181	7216	7219	java/lang/Throwable
    //   7198	7233	7236	java/lang/Throwable
    //   7223	7250	7253	java/lang/Throwable
    //   7240	7275	7278	java/lang/Throwable
    //   7257	7292	7295	java/lang/Throwable
    //   7282	7309	7312	java/lang/Throwable
    //   7299	7330	7333	java/lang/Throwable
    //   7466	7503	7506	java/lang/Throwable
    //   7510	7553	7556	java/lang/Throwable
    //   7657	7671	7671	java/lang/Throwable
    //   7682	7695	7698	java/lang/Throwable
    //   7687	7710	7713	java/lang/Throwable
    //   7702	7728	7731	java/lang/Throwable
    //   7717	7758	7761	java/lang/Throwable
    //   7824	7851	7854	java/lang/Throwable
    //   7841	7869	7872	java/lang/Throwable
    //   7858	7899	7902	java/lang/Throwable
    //   7876	7910	7910	java/lang/Throwable
    //   7933	7944	7947	java/lang/Throwable
    //   7999	8013	8013	java/lang/Throwable
    //   8024	8037	8040	java/lang/Throwable
    //   8029	8052	8055	java/lang/Throwable
    //   8044	8070	8073	java/lang/Throwable
    //   8059	8100	8103	java/lang/Throwable
    //   8166	8193	8196	java/lang/Throwable
    //   8183	8211	8214	java/lang/Throwable
    //   8200	8241	8244	java/lang/Throwable
    //   8218	8252	8252	java/lang/Throwable
    //   8275	8286	8289	java/lang/Throwable
    //   8301	9035	10501	java/lang/Throwable
    //   8391	8405	8405	java/lang/Throwable
    //   8416	8429	8432	java/lang/Throwable
    //   8421	8444	8447	java/lang/Throwable
    //   8436	8462	8465	java/lang/Throwable
    //   8451	8492	8495	java/lang/Throwable
    //   8558	8585	8588	java/lang/Throwable
    //   8575	8603	8606	java/lang/Throwable
    //   8592	8633	8636	java/lang/Throwable
    //   8610	8644	8644	java/lang/Throwable
    //   8667	8678	8681	java/lang/Throwable
    //   8734	8748	8748	java/lang/Throwable
    //   8759	8772	8775	java/lang/Throwable
    //   8764	8787	8790	java/lang/Throwable
    //   8779	8805	8808	java/lang/Throwable
    //   8794	8835	8838	java/lang/Throwable
    //   8901	8928	8931	java/lang/Throwable
    //   8918	8946	8949	java/lang/Throwable
    //   8935	8976	8979	java/lang/Throwable
    //   8953	8987	8987	java/lang/Throwable
    //   9010	9021	9024	java/lang/Throwable
    //   9036	9770	10501	java/lang/Throwable
    //   9126	9140	9140	java/lang/Throwable
    //   9151	9164	9167	java/lang/Throwable
    //   9156	9179	9182	java/lang/Throwable
    //   9171	9197	9200	java/lang/Throwable
    //   9186	9227	9230	java/lang/Throwable
    //   9293	9320	9323	java/lang/Throwable
    //   9310	9338	9341	java/lang/Throwable
    //   9327	9368	9371	java/lang/Throwable
    //   9345	9379	9379	java/lang/Throwable
    //   9402	9413	9416	java/lang/Throwable
    //   9469	9483	9483	java/lang/Throwable
    //   9494	9507	9510	java/lang/Throwable
    //   9499	9522	9525	java/lang/Throwable
    //   9514	9540	9543	java/lang/Throwable
    //   9529	9570	9573	java/lang/Throwable
    //   9636	9663	9666	java/lang/Throwable
    //   9653	9681	9684	java/lang/Throwable
    //   9670	9711	9714	java/lang/Throwable
    //   9688	9722	9722	java/lang/Throwable
    //   9745	9756	9759	java/lang/Throwable
    //   9771	10500	10501	java/lang/Throwable
    //   9861	9875	9875	java/lang/Throwable
    //   9886	9899	9902	java/lang/Throwable
    //   9891	9914	9917	java/lang/Throwable
    //   9906	9932	9935	java/lang/Throwable
    //   9921	9962	9965	java/lang/Throwable
    //   10028	10055	10058	java/lang/Throwable
    //   10045	10073	10076	java/lang/Throwable
    //   10062	10103	10106	java/lang/Throwable
    //   10080	10114	10114	java/lang/Throwable
    //   10137	10148	10151	java/lang/Throwable
    //   10204	10218	10218	java/lang/Throwable
    //   10229	10242	10245	java/lang/Throwable
    //   10234	10257	10260	java/lang/Throwable
    //   10249	10275	10278	java/lang/Throwable
    //   10264	10305	10308	java/lang/Throwable
    //   10371	10398	10401	java/lang/Throwable
    //   10388	10416	10419	java/lang/Throwable
    //   10405	10446	10449	java/lang/Throwable
    //   10423	10457	10457	java/lang/Throwable
    //   10480	10491	10494	java/lang/Throwable
  }
  
  static void Zd(Object[] paramArrayOfObject, Object paramObject) throws Throwable {}
  
  static {
    // Byte code:
    //   0: bipush #25
    //   2: anewarray java/lang/String
    //   5: astore #5
    //   7: iconst_0
    //   8: istore_3
    //   9: ldc 'GIsq KFqv?UNrW4Ki\\n\\t~In`?_\\t|.7]?\\t'i_\\toV' /W!mNBQJ8}~RM\\t.d .\\t<p%O\\tsl46c\\t[GXSJ\\bZ'_\\t=mZ:\\tpZ\\tg$Ww\\taT1&\\tfB8@\\tbx\\t-]\\tVk7%\\t0N\\f ULN)\\tOZVOx"iFJ#8bsJ\\fwuM"K3-cZ'
    //   11: dup
    //   12: astore_2
    //   13: invokevirtual length : ()I
    //   16: istore #4
    //   18: bipush #9
    //   20: istore_1
    //   21: iconst_m1
    //   22: istore_0
    //   23: bipush #52
    //   25: iinc #0, 1
    //   28: aload_2
    //   29: iload_0
    //   30: dup
    //   31: iload_1
    //   32: iadd
    //   33: invokevirtual substring : (II)Ljava/lang/String;
    //   36: iconst_m1
    //   37: goto -> 142
    //   40: aload #5
    //   42: swap
    //   43: iload_3
    //   44: iinc #3, 1
    //   47: swap
    //   48: aastore
    //   49: iload_0
    //   50: iload_1
    //   51: iadd
    //   52: dup
    //   53: istore_0
    //   54: iload #4
    //   56: if_icmpge -> 68
    //   59: aload_2
    //   60: iload_0
    //   61: invokevirtual charAt : (I)C
    //   64: istore_1
    //   65: goto -> 23
    //   68: ldc '\\tn\\tdc{'
    //   70: dup
    //   71: astore_2
    //   72: invokevirtual length : ()I
    //   75: istore #4
    //   77: iconst_4
    //   78: istore_1
    //   79: iconst_m1
    //   80: istore_0
    //   81: bipush #66
    //   83: iinc #0, 1
    //   86: aload_2
    //   87: iload_0
    //   88: dup
    //   89: iload_1
    //   90: iadd
    //   91: invokevirtual substring : (II)Ljava/lang/String;
    //   94: iconst_0
    //   95: goto -> 142
    //   98: aload #5
    //   100: swap
    //   101: iload_3
    //   102: iinc #3, 1
    //   105: swap
    //   106: aastore
    //   107: iload_0
    //   108: iload_1
    //   109: iadd
    //   110: dup
    //   111: istore_0
    //   112: iload #4
    //   114: if_icmpge -> 126
    //   117: aload_2
    //   118: iload_0
    //   119: invokevirtual charAt : (I)C
    //   122: istore_1
    //   123: goto -> 81
    //   126: aload #5
    //   128: putstatic burp/Zenr.a : [Ljava/lang/String;
    //   131: bipush #25
    //   133: anewarray java/lang/String
    //   136: putstatic burp/Zenr.b : [Ljava/lang/String;
    //   139: goto -> 300
    //   142: dup_x2
    //   143: pop
    //   144: invokevirtual toCharArray : ()[C
    //   147: dup_x1
    //   148: arraylength
    //   149: dup_x2
    //   150: pop
    //   151: iconst_0
    //   152: istore #6
    //   154: dup2_x1
    //   155: pop2
    //   156: dup_x2
    //   157: iconst_1
    //   158: if_icmpgt -> 260
    //   161: dup2
    //   162: swap
    //   163: iload #6
    //   165: dup2_x1
    //   166: caload
    //   167: swap
    //   168: iload #6
    //   170: bipush #7
    //   172: irem
    //   173: tableswitch default -> 242, 0 -> 212, 1 -> 217, 2 -> 222, 3 -> 227, 4 -> 232, 5 -> 237
    //   212: bipush #75
    //   214: goto -> 244
    //   217: bipush #53
    //   219: goto -> 244
    //   222: bipush #38
    //   224: goto -> 244
    //   227: bipush #72
    //   229: goto -> 244
    //   232: bipush #62
    //   234: goto -> 244
    //   237: bipush #36
    //   239: goto -> 244
    //   242: bipush #30
    //   244: ixor
    //   245: ixor
    //   246: i2c
    //   247: castore
    //   248: iinc #6, 1
    //   251: dup
    //   252: ifne -> 260
    //   255: dup2
    //   256: dup_x1
    //   257: goto -> 165
    //   260: dup2_x1
    //   261: pop2
    //   262: dup_x2
    //   263: iload #6
    //   265: if_icmpgt -> 161
    //   268: pop
    //   269: new java/lang/String
    //   272: dup_x1
    //   273: swap
    //   274: invokespecial <init> : ([C)V
    //   277: invokevirtual intern : ()Ljava/lang/String;
    //   280: swap
    //   281: pop
    //   282: swap
    //   283: tableswitch default -> 40, 0 -> 98
    //   300: new java/math/BigInteger
    //   303: dup
    //   304: bipush #32
    //   306: newarray byte
    //   308: dup
    //   309: iconst_0
    //   310: bipush #55
    //   312: bastore
    //   313: dup
    //   314: iconst_1
    //   315: bipush #30
    //   317: bastore
    //   318: dup
    //   319: iconst_2
    //   320: bipush #-90
    //   322: bastore
    //   323: dup
    //   324: iconst_3
    //   325: bipush #68
    //   327: bastore
    //   328: dup
    //   329: iconst_4
    //   330: bipush #-8
    //   332: bastore
    //   333: dup
    //   334: iconst_5
    //   335: bipush #-59
    //   337: bastore
    //   338: dup
    //   339: bipush #6
    //   341: bipush #-92
    //   343: bastore
    //   344: dup
    //   345: bipush #7
    //   347: bipush #13
    //   349: bastore
    //   350: dup
    //   351: bipush #8
    //   353: bipush #27
    //   355: bastore
    //   356: dup
    //   357: bipush #9
    //   359: bipush #34
    //   361: bastore
    //   362: dup
    //   363: bipush #10
    //   365: bipush #-111
    //   367: bastore
    //   368: dup
    //   369: bipush #11
    //   371: bipush #-67
    //   373: bastore
    //   374: dup
    //   375: bipush #12
    //   377: bipush #-22
    //   379: bastore
    //   380: dup
    //   381: bipush #13
    //   383: bipush #-4
    //   385: bastore
    //   386: dup
    //   387: bipush #14
    //   389: bipush #-39
    //   391: bastore
    //   392: dup
    //   393: bipush #15
    //   395: bipush #-37
    //   397: bastore
    //   398: dup
    //   399: bipush #16
    //   401: bipush #-85
    //   403: bastore
    //   404: dup
    //   405: bipush #17
    //   407: bipush #-106
    //   409: bastore
    //   410: dup
    //   411: bipush #18
    //   413: bipush #21
    //   415: bastore
    //   416: dup
    //   417: bipush #19
    //   419: bipush #100
    //   421: bastore
    //   422: dup
    //   423: bipush #20
    //   425: bipush #-13
    //   427: bastore
    //   428: dup
    //   429: bipush #21
    //   431: bipush #-5
    //   433: bastore
    //   434: dup
    //   435: bipush #22
    //   437: bipush #71
    //   439: bastore
    //   440: dup
    //   441: bipush #23
    //   443: bipush #-99
    //   445: bastore
    //   446: dup
    //   447: bipush #24
    //   449: bipush #-65
    //   451: bastore
    //   452: dup
    //   453: bipush #25
    //   455: bipush #-67
    //   457: bastore
    //   458: dup
    //   459: bipush #26
    //   461: bipush #-109
    //   463: bastore
    //   464: dup
    //   465: bipush #27
    //   467: bipush #-55
    //   469: bastore
    //   470: dup
    //   471: bipush #28
    //   473: bipush #-4
    //   475: bastore
    //   476: dup
    //   477: bipush #29
    //   479: bipush #-115
    //   481: bastore
    //   482: dup
    //   483: bipush #30
    //   485: bipush #12
    //   487: bastore
    //   488: dup
    //   489: bipush #31
    //   491: bipush #-77
    //   493: bastore
    //   494: invokespecial <init> : ([B)V
    //   497: putstatic burp/Zenr.ZA : Ljava/lang/Object;
    //   500: sipush #12691
    //   503: sipush #12913
    //   506: invokestatic a : (II)Ljava/lang/String;
    //   509: putstatic burp/Zenr.Z_ : Ljava/lang/String;
    //   512: return
  }
  
  private static Throwable a(Throwable paramThrowable) {
    return paramThrowable;
  }
  
  private static String a(int paramInt1, int paramInt2) {
    int i = (paramInt1 ^ 0x3195) & 0xFFFF;
    if (b[i] == null) {
      char[] arrayOfChar = a[i].toCharArray();
      switch (arrayOfChar[0] & 0xFF) {
        case 0:
        
        case 1:
        
        case 2:
        
        case 3:
        
        case 4:
        
        case 5:
        
        case 6:
        
        case 7:
        
        case 8:
        
        case 9:
        
        case 10:
        
        case 11:
        
        case 12:
        
        case 13:
        
        case 14:
        
        case 15:
        
        case 16:
        
        case 17:
        
        case 18:
        
        case 19:
        
        case 20:
        
        case 21:
        
        case 22:
        
        case 23:
        
        case 24:
        
        case 25:
        
        case 26:
        
        case 27:
        
        case 28:
        
        case 29:
        
        case 30:
        
        case 31:
        
        case 32:
        
        case 33:
        
        case 34:
        
        case 35:
        
        case 36:
        
        case 37:
        
        case 38:
        
        case 39:
        
        case 40:
        
        case 41:
        
        case 42:
        
        case 43:
        
        case 44:
        
        case 45:
        
        case 46:
        
        case 47:
        
        case 48:
        
        case 49:
        
        case 50:
        
        case 51:
        
        case 52:
        
        case 53:
        
        case 54:
        
        case 55:
        
        case 56:
        
        case 57:
        
        case 58:
        
        case 59:
        
        case 60:
        
        case 61:
        
        case 62:
        
        case 63:
        
        case 64:
        
        case 65:
        
        case 66:
        
        case 67:
        
        case 68:
        
        case 69:
        
        case 70:
        
        case 71:
        
        case 72:
        
        case 73:
        
        case 74:
        
        case 75:
        
        case 76:
        
        case 77:
        
        case 78:
        
        case 79:
        
        case 80:
        
        case 81:
        
        case 82:
        
        case 83:
        
        case 84:
        
        case 85:
        
        case 86:
        
        case 87:
        
        case 88:
        
        case 89:
        
        case 90:
        
        case 91:
        
        case 92:
        
        case 93:
        
        case 94:
        
        case 95:
        
        case 96:
        
        case 97:
        
        case 98:
        
        case 99:
        
        case 100:
        
        case 101:
        
        case 102:
        
        case 103:
        
        case 104:
        
        case 105:
        
        case 106:
        
        case 107:
        
        case 108:
        
        case 109:
        
        case 110:
        
        case 111:
        
        case 112:
        
        case 113:
        
        case 114:
        
        case 115:
        
        case 116:
        
        case 117:
        
        case 118:
        
        case 119:
        
        case 120:
        
        case 121:
        
        case 122:
        
        case 123:
        
        case 124:
        
        case 125:
        
        case 126:
        
        case 127:
        
        case 128:
        
        case 129:
        
        case 130:
        
        case 131:
        
        case 132:
        
        case 133:
        
        case 134:
        
        case 135:
        
        case 136:
        
        case 137:
        
        case 138:
        
        case 139:
        
        case 140:
        
        case 141:
        
        case 142:
        
        case 143:
        
        case 144:
        
        case 145:
        
        case 146:
        
        case 147:
        
        case 148:
        
        case 149:
        
        case 150:
        
        case 151:
        
        case 152:
        
        case 153:
        
        case 154:
        
        case 155:
        
        case 156:
        
        case 157:
        
        case 158:
        
        case 159:
        
        case 160:
        
        case 161:
        
        case 162:
        
        case 163:
        
        case 164:
        
        case 165:
        
        case 166:
        
        case 167:
        
        case 168:
        
        case 169:
        
        case 170:
        
        case 171:
        
        case 172:
        
        case 173:
        
        case 174:
        
        case 175:
        
        case 176:
        
        case 177:
        
        case 178:
        
        case 179:
        
        case 180:
        
        case 181:
        
        case 182:
        
        case 183:
        
        case 184:
        
        case 185:
        
        case 186:
        
        case 187:
        
        case 188:
        
        case 189:
        
        case 190:
        
        case 191:
        
        case 192:
        
        case 193:
        
        case 194:
        
        case 195:
        
        case 196:
        
        case 197:
        
        case 198:
        
        case 199:
        
        case 200:
        
        case 201:
        
        case 202:
        
        case 203:
        
        case 204:
        
        case 205:
        
        case 206:
        
        case 207:
        
        case 208:
        
        case 209:
        
        case 210:
        
        case 211:
        
        case 212:
        
        case 213:
        
        case 214:
        
        case 215:
        
        case 216:
        
        case 217:
        
        case 218:
        
        case 219:
        
        case 220:
        
        case 221:
        
        case 222:
        
        case 223:
        
        case 224:
        
        case 225:
        
        case 226:
        
        case 227:
        
        case 228:
        
        case 229:
        
        case 230:
        
        case 231:
        
        case 232:
        
        case 233:
        
        case 234:
        
        case 235:
        
        case 236:
        
        case 237:
        
        case 238:
        
        case 239:
        
        case 240:
        
        case 241:
        
        case 242:
        
        case 243:
        
        case 244:
        
        case 245:
        
        case 246:
        
        case 247:
        
        case 248:
        
        case 249:
        
        case 250:
        
        case 251:
        
        case 252:
        
        case 253:
        
        case 254:
        
        default:
          break;
      } 
      byte b1 = 44;
      int j = (paramInt2 & 0xFF) - b1;
      if (j < 0)
        j += 256; 
      int k = ((paramInt2 & 0xFFFF) >>> 8) - b1;
      if (k < 0)
        k += 256; 
      for (byte b2 = 0; b2 < arrayOfChar.length; b2++) {
        int m = b2 % 2;
        if (m == 0) {
          arrayOfChar[b2] = (char)(arrayOfChar[b2] ^ j);
          j = ((j >>> 3 | j << 5) ^ arrayOfChar[b2]) & 0xFF;
        } else {
          arrayOfChar[b2] = (char)(arrayOfChar[b2] ^ k);
          k = ((k >>> 3 | k << 5) ^ arrayOfChar[b2]) & 0xFF;
        } 
      } 
      b[i] = (new String(arrayOfChar)).intern();
    } 
    return b[i];
  }
}


/* Location:              C:\Program Files\BurpSuitePro\burpsuite_pro.jar!\burp\Zenr.class
 * Java compiler version: 21 (65.0)
 * JD-Core Version:       1.1.3
 */