package burp;

import java.math.BigInteger;

class Zeoa extends ClassLoader {
  static String Zn;
  
  static Object ZF;
  
  private static final String[] a;
  
  private static final String[] b;
  
  static void ZS(Object paramObject) {
    Zm3s.Ze = a(-7833, -14393);
    Zm3s.ZW = new BigInteger(a(-7830, 8335));
    boolean bool = Zt2e.ZK();
    try {
      try {
        if (Zb8x.Zp.charAt(Math.abs(((BigInteger)Zxzt.ZY).intValue() % 32)) > Zx0t.Ze.charAt(Math.abs(((BigInteger)Zluk.Zz).intValue() % 32))) {
          try {
            Zz5h.Zb(Class.forName(a(-7834, 27731)));
            if (bool)
              Zera.ZU(Class.forName(a(-7829, -28620))); 
          } catch (Throwable throwable) {
            throw a(null);
          } 
          return;
        } 
      } catch (Throwable throwable) {
        throw a(null);
      } 
      Zera.ZU(Class.forName(a(-7829, -28620)));
    } catch (Throwable throwable) {}
  }
  
  static void ZF(Object[] paramArrayOfObject, Object paramObject) throws Throwable {}
  
  static boolean ZO(Object[] paramArrayOfObject, Object paramObject) throws Throwable {
    // Byte code:
    //   0: invokestatic ZN : ()Z
    //   3: istore_2
    //   4: new java/lang/StringBuilder
    //   7: dup
    //   8: invokespecial <init> : ()V
    //   11: astore_3
    //   12: iconst_0
    //   13: istore #4
    //   15: iload #4
    //   17: bipush #32
    //   19: if_icmpge -> 1355
    //   22: iload #4
    //   24: tableswitch default -> 1348, 0 -> 168, 1 -> 205, 2 -> 242, 3 -> 279, 4 -> 316, 5 -> 353, 6 -> 390, 7 -> 427, 8 -> 464, 9 -> 501, 10 -> 538, 11 -> 575, 12 -> 612, 13 -> 649, 14 -> 686, 15 -> 723, 16 -> 760, 17 -> 797, 18 -> 834, 19 -> 871, 20 -> 908, 21 -> 945, 22 -> 982, 23 -> 1019, 24 -> 1056, 25 -> 1093, 26 -> 1130, 27 -> 1167, 28 -> 1204, 29 -> 1241, 30 -> 1278, 31 -> 1315
    //   168: aload_3
    //   169: getstatic burp/Zrqd.Zk : Ljava/lang/String;
    //   172: getstatic burp/Zr64.ZN : Ljava/lang/Object;
    //   175: checkcast java/math/BigInteger
    //   178: invokevirtual intValue : ()I
    //   181: bipush #32
    //   183: irem
    //   184: invokestatic abs : (I)I
    //   187: invokevirtual charAt : (I)C
    //   190: invokevirtual append : (C)Ljava/lang/StringBuilder;
    //   193: pop
    //   194: iload_2
    //   195: ifne -> 1348
    //   198: goto -> 205
    //   201: invokestatic a : (Ljava/lang/Throwable;)Ljava/lang/Throwable;
    //   204: athrow
    //   205: aload_3
    //   206: getstatic burp/Zg_i.ZW : Ljava/lang/String;
    //   209: getstatic burp/Zr64.ZN : Ljava/lang/Object;
    //   212: checkcast java/math/BigInteger
    //   215: invokevirtual intValue : ()I
    //   218: bipush #32
    //   220: irem
    //   221: invokestatic abs : (I)I
    //   224: invokevirtual charAt : (I)C
    //   227: invokevirtual append : (C)Ljava/lang/StringBuilder;
    //   230: pop
    //   231: iload_2
    //   232: ifne -> 1348
    //   235: goto -> 242
    //   238: invokestatic a : (Ljava/lang/Throwable;)Ljava/lang/Throwable;
    //   241: athrow
    //   242: aload_3
    //   243: getstatic burp/Zm3s.Ze : Ljava/lang/String;
    //   246: getstatic burp/Zep1.ZW : Ljava/lang/Object;
    //   249: checkcast java/math/BigInteger
    //   252: invokevirtual intValue : ()I
    //   255: bipush #32
    //   257: irem
    //   258: invokestatic abs : (I)I
    //   261: invokevirtual charAt : (I)C
    //   264: invokevirtual append : (C)Ljava/lang/StringBuilder;
    //   267: pop
    //   268: iload_2
    //   269: ifne -> 1348
    //   272: goto -> 279
    //   275: invokestatic a : (Ljava/lang/Throwable;)Ljava/lang/Throwable;
    //   278: athrow
    //   279: aload_3
    //   280: getstatic burp/Ze0z.ZU : Ljava/lang/String;
    //   283: getstatic burp/Zrug.Zp : Ljava/lang/Object;
    //   286: checkcast java/math/BigInteger
    //   289: invokevirtual intValue : ()I
    //   292: bipush #32
    //   294: irem
    //   295: invokestatic abs : (I)I
    //   298: invokevirtual charAt : (I)C
    //   301: invokevirtual append : (C)Ljava/lang/StringBuilder;
    //   304: pop
    //   305: iload_2
    //   306: ifne -> 1348
    //   309: goto -> 316
    //   312: invokestatic a : (Ljava/lang/Throwable;)Ljava/lang/Throwable;
    //   315: athrow
    //   316: aload_3
    //   317: getstatic burp/Zxzt.ZG : Ljava/lang/String;
    //   320: getstatic burp/Zz5h.ZD : Ljava/lang/Object;
    //   323: checkcast java/math/BigInteger
    //   326: invokevirtual intValue : ()I
    //   329: bipush #32
    //   331: irem
    //   332: invokestatic abs : (I)I
    //   335: invokevirtual charAt : (I)C
    //   338: invokevirtual append : (C)Ljava/lang/StringBuilder;
    //   341: pop
    //   342: iload_2
    //   343: ifne -> 1348
    //   346: goto -> 353
    //   349: invokestatic a : (Ljava/lang/Throwable;)Ljava/lang/Throwable;
    //   352: athrow
    //   353: aload_3
    //   354: getstatic burp/Zgx6.ZX : Ljava/lang/String;
    //   357: getstatic burp/Zgk1.ZD : Ljava/lang/Object;
    //   360: checkcast java/math/BigInteger
    //   363: invokevirtual intValue : ()I
    //   366: bipush #32
    //   368: irem
    //   369: invokestatic abs : (I)I
    //   372: invokevirtual charAt : (I)C
    //   375: invokevirtual append : (C)Ljava/lang/StringBuilder;
    //   378: pop
    //   379: iload_2
    //   380: ifne -> 1348
    //   383: goto -> 390
    //   386: invokestatic a : (Ljava/lang/Throwable;)Ljava/lang/Throwable;
    //   389: athrow
    //   390: aload_3
    //   391: getstatic burp/Zr64.Zj : Ljava/lang/String;
    //   394: getstatic burp/Zz5h.ZD : Ljava/lang/Object;
    //   397: checkcast java/math/BigInteger
    //   400: invokevirtual intValue : ()I
    //   403: bipush #32
    //   405: irem
    //   406: invokestatic abs : (I)I
    //   409: invokevirtual charAt : (I)C
    //   412: invokevirtual append : (C)Ljava/lang/StringBuilder;
    //   415: pop
    //   416: iload_2
    //   417: ifne -> 1348
    //   420: goto -> 427
    //   423: invokestatic a : (Ljava/lang/Throwable;)Ljava/lang/Throwable;
    //   426: athrow
    //   427: aload_3
    //   428: getstatic burp/Zgl4.ZX : Ljava/lang/String;
    //   431: getstatic burp/Zss8.ZO : Ljava/lang/Object;
    //   434: checkcast java/math/BigInteger
    //   437: invokevirtual intValue : ()I
    //   440: bipush #32
    //   442: irem
    //   443: invokestatic abs : (I)I
    //   446: invokevirtual charAt : (I)C
    //   449: invokevirtual append : (C)Ljava/lang/StringBuilder;
    //   452: pop
    //   453: iload_2
    //   454: ifne -> 1348
    //   457: goto -> 464
    //   460: invokestatic a : (Ljava/lang/Throwable;)Ljava/lang/Throwable;
    //   463: athrow
    //   464: aload_3
    //   465: getstatic burp/Zg_y.ZF : Ljava/lang/String;
    //   468: getstatic burp/Zl8l.ZJ : Ljava/lang/Object;
    //   471: checkcast java/math/BigInteger
    //   474: invokevirtual intValue : ()I
    //   477: bipush #32
    //   479: irem
    //   480: invokestatic abs : (I)I
    //   483: invokevirtual charAt : (I)C
    //   486: invokevirtual append : (C)Ljava/lang/StringBuilder;
    //   489: pop
    //   490: iload_2
    //   491: ifne -> 1348
    //   494: goto -> 501
    //   497: invokestatic a : (Ljava/lang/Throwable;)Ljava/lang/Throwable;
    //   500: athrow
    //   501: aload_3
    //   502: getstatic burp/Zg_y.ZF : Ljava/lang/String;
    //   505: getstatic burp/Zgz2.Zs : Ljava/lang/Object;
    //   508: checkcast java/math/BigInteger
    //   511: invokevirtual intValue : ()I
    //   514: bipush #32
    //   516: irem
    //   517: invokestatic abs : (I)I
    //   520: invokevirtual charAt : (I)C
    //   523: invokevirtual append : (C)Ljava/lang/StringBuilder;
    //   526: pop
    //   527: iload_2
    //   528: ifne -> 1348
    //   531: goto -> 538
    //   534: invokestatic a : (Ljava/lang/Throwable;)Ljava/lang/Throwable;
    //   537: athrow
    //   538: aload_3
    //   539: getstatic burp/Zlhk.Zb : Ljava/lang/String;
    //   542: getstatic burp/Zgk1.ZD : Ljava/lang/Object;
    //   545: checkcast java/math/BigInteger
    //   548: invokevirtual intValue : ()I
    //   551: bipush #32
    //   553: irem
    //   554: invokestatic abs : (I)I
    //   557: invokevirtual charAt : (I)C
    //   560: invokevirtual append : (C)Ljava/lang/StringBuilder;
    //   563: pop
    //   564: iload_2
    //   565: ifne -> 1348
    //   568: goto -> 575
    //   571: invokestatic a : (Ljava/lang/Throwable;)Ljava/lang/Throwable;
    //   574: athrow
    //   575: aload_3
    //   576: getstatic burp/Zge1.Zx : Ljava/lang/String;
    //   579: getstatic burp/Zm7y.Zr : Ljava/lang/Object;
    //   582: checkcast java/math/BigInteger
    //   585: invokevirtual intValue : ()I
    //   588: bipush #32
    //   590: irem
    //   591: invokestatic abs : (I)I
    //   594: invokevirtual charAt : (I)C
    //   597: invokevirtual append : (C)Ljava/lang/StringBuilder;
    //   600: pop
    //   601: iload_2
    //   602: ifne -> 1348
    //   605: goto -> 612
    //   608: invokestatic a : (Ljava/lang/Throwable;)Ljava/lang/Throwable;
    //   611: athrow
    //   612: aload_3
    //   613: getstatic burp/Zmcb.Zl : Ljava/lang/String;
    //   616: getstatic burp/Zkw.ZY : Ljava/lang/Object;
    //   619: checkcast java/math/BigInteger
    //   622: invokevirtual intValue : ()I
    //   625: bipush #32
    //   627: irem
    //   628: invokestatic abs : (I)I
    //   631: invokevirtual charAt : (I)C
    //   634: invokevirtual append : (C)Ljava/lang/StringBuilder;
    //   637: pop
    //   638: iload_2
    //   639: ifne -> 1348
    //   642: goto -> 649
    //   645: invokestatic a : (Ljava/lang/Throwable;)Ljava/lang/Throwable;
    //   648: athrow
    //   649: aload_3
    //   650: getstatic burp/Zgz2.ZI : Ljava/lang/String;
    //   653: getstatic burp/Zgfq.Za : Ljava/lang/Object;
    //   656: checkcast java/math/BigInteger
    //   659: invokevirtual intValue : ()I
    //   662: bipush #32
    //   664: irem
    //   665: invokestatic abs : (I)I
    //   668: invokevirtual charAt : (I)C
    //   671: invokevirtual append : (C)Ljava/lang/StringBuilder;
    //   674: pop
    //   675: iload_2
    //   676: ifne -> 1348
    //   679: goto -> 686
    //   682: invokestatic a : (Ljava/lang/Throwable;)Ljava/lang/Throwable;
    //   685: athrow
    //   686: aload_3
    //   687: getstatic burp/Ztgt.ZQ : Ljava/lang/String;
    //   690: getstatic burp/Zg_i.ZQ : Ljava/lang/Object;
    //   693: checkcast java/math/BigInteger
    //   696: invokevirtual intValue : ()I
    //   699: bipush #32
    //   701: irem
    //   702: invokestatic abs : (I)I
    //   705: invokevirtual charAt : (I)C
    //   708: invokevirtual append : (C)Ljava/lang/StringBuilder;
    //   711: pop
    //   712: iload_2
    //   713: ifne -> 1348
    //   716: goto -> 723
    //   719: invokestatic a : (Ljava/lang/Throwable;)Ljava/lang/Throwable;
    //   722: athrow
    //   723: aload_3
    //   724: getstatic burp/Zm0v.Zd : Ljava/lang/String;
    //   727: getstatic burp/Zm3s.ZW : Ljava/lang/Object;
    //   730: checkcast java/math/BigInteger
    //   733: invokevirtual intValue : ()I
    //   736: bipush #32
    //   738: irem
    //   739: invokestatic abs : (I)I
    //   742: invokevirtual charAt : (I)C
    //   745: invokevirtual append : (C)Ljava/lang/StringBuilder;
    //   748: pop
    //   749: iload_2
    //   750: ifne -> 1348
    //   753: goto -> 760
    //   756: invokestatic a : (Ljava/lang/Throwable;)Ljava/lang/Throwable;
    //   759: athrow
    //   760: aload_3
    //   761: getstatic burp/Zmou.ZP : Ljava/lang/String;
    //   764: getstatic burp/Zss8.ZO : Ljava/lang/Object;
    //   767: checkcast java/math/BigInteger
    //   770: invokevirtual intValue : ()I
    //   773: bipush #32
    //   775: irem
    //   776: invokestatic abs : (I)I
    //   779: invokevirtual charAt : (I)C
    //   782: invokevirtual append : (C)Ljava/lang/StringBuilder;
    //   785: pop
    //   786: iload_2
    //   787: ifne -> 1348
    //   790: goto -> 797
    //   793: invokestatic a : (Ljava/lang/Throwable;)Ljava/lang/Throwable;
    //   796: athrow
    //   797: aload_3
    //   798: getstatic burp/Zmwx.ZB : Ljava/lang/String;
    //   801: getstatic burp/Zgx6.Zo : Ljava/lang/Object;
    //   804: checkcast java/math/BigInteger
    //   807: invokevirtual intValue : ()I
    //   810: bipush #32
    //   812: irem
    //   813: invokestatic abs : (I)I
    //   816: invokevirtual charAt : (I)C
    //   819: invokevirtual append : (C)Ljava/lang/StringBuilder;
    //   822: pop
    //   823: iload_2
    //   824: ifne -> 1348
    //   827: goto -> 834
    //   830: invokestatic a : (Ljava/lang/Throwable;)Ljava/lang/Throwable;
    //   833: athrow
    //   834: aload_3
    //   835: getstatic burp/Zgl4.ZX : Ljava/lang/String;
    //   838: getstatic burp/Zgk1.ZD : Ljava/lang/Object;
    //   841: checkcast java/math/BigInteger
    //   844: invokevirtual intValue : ()I
    //   847: bipush #32
    //   849: irem
    //   850: invokestatic abs : (I)I
    //   853: invokevirtual charAt : (I)C
    //   856: invokevirtual append : (C)Ljava/lang/StringBuilder;
    //   859: pop
    //   860: iload_2
    //   861: ifne -> 1348
    //   864: goto -> 871
    //   867: invokestatic a : (Ljava/lang/Throwable;)Ljava/lang/Throwable;
    //   870: athrow
    //   871: aload_3
    //   872: getstatic burp/Zg_i.ZW : Ljava/lang/String;
    //   875: getstatic burp/Zlqy.ZP : Ljava/lang/Object;
    //   878: checkcast java/math/BigInteger
    //   881: invokevirtual intValue : ()I
    //   884: bipush #32
    //   886: irem
    //   887: invokestatic abs : (I)I
    //   890: invokevirtual charAt : (I)C
    //   893: invokevirtual append : (C)Ljava/lang/StringBuilder;
    //   896: pop
    //   897: iload_2
    //   898: ifne -> 1348
    //   901: goto -> 908
    //   904: invokestatic a : (Ljava/lang/Throwable;)Ljava/lang/Throwable;
    //   907: athrow
    //   908: aload_3
    //   909: getstatic burp/Zxz_.Zb : Ljava/lang/String;
    //   912: getstatic burp/Zm54.ZS : Ljava/lang/Object;
    //   915: checkcast java/math/BigInteger
    //   918: invokevirtual intValue : ()I
    //   921: bipush #32
    //   923: irem
    //   924: invokestatic abs : (I)I
    //   927: invokevirtual charAt : (I)C
    //   930: invokevirtual append : (C)Ljava/lang/StringBuilder;
    //   933: pop
    //   934: iload_2
    //   935: ifne -> 1348
    //   938: goto -> 945
    //   941: invokestatic a : (Ljava/lang/Throwable;)Ljava/lang/Throwable;
    //   944: athrow
    //   945: aload_3
    //   946: getstatic burp/Zeyd.Zr : Ljava/lang/String;
    //   949: getstatic burp/Zep1.ZW : Ljava/lang/Object;
    //   952: checkcast java/math/BigInteger
    //   955: invokevirtual intValue : ()I
    //   958: bipush #32
    //   960: irem
    //   961: invokestatic abs : (I)I
    //   964: invokevirtual charAt : (I)C
    //   967: invokevirtual append : (C)Ljava/lang/StringBuilder;
    //   970: pop
    //   971: iload_2
    //   972: ifne -> 1348
    //   975: goto -> 982
    //   978: invokestatic a : (Ljava/lang/Throwable;)Ljava/lang/Throwable;
    //   981: athrow
    //   982: aload_3
    //   983: getstatic burp/Zeyd.Zr : Ljava/lang/String;
    //   986: getstatic burp/Ze6t.Zu : Ljava/lang/Object;
    //   989: checkcast java/math/BigInteger
    //   992: invokevirtual intValue : ()I
    //   995: bipush #32
    //   997: irem
    //   998: invokestatic abs : (I)I
    //   1001: invokevirtual charAt : (I)C
    //   1004: invokevirtual append : (C)Ljava/lang/StringBuilder;
    //   1007: pop
    //   1008: iload_2
    //   1009: ifne -> 1348
    //   1012: goto -> 1019
    //   1015: invokestatic a : (Ljava/lang/Throwable;)Ljava/lang/Throwable;
    //   1018: athrow
    //   1019: aload_3
    //   1020: getstatic burp/Zl55.Zp : Ljava/lang/String;
    //   1023: getstatic burp/Zgb9.Zb : Ljava/lang/Object;
    //   1026: checkcast java/math/BigInteger
    //   1029: invokevirtual intValue : ()I
    //   1032: bipush #32
    //   1034: irem
    //   1035: invokestatic abs : (I)I
    //   1038: invokevirtual charAt : (I)C
    //   1041: invokevirtual append : (C)Ljava/lang/StringBuilder;
    //   1044: pop
    //   1045: iload_2
    //   1046: ifne -> 1348
    //   1049: goto -> 1056
    //   1052: invokestatic a : (Ljava/lang/Throwable;)Ljava/lang/Throwable;
    //   1055: athrow
    //   1056: aload_3
    //   1057: getstatic burp/Zgz1.Zs : Ljava/lang/String;
    //   1060: getstatic burp/Ze0z.ZQ : Ljava/lang/Object;
    //   1063: checkcast java/math/BigInteger
    //   1066: invokevirtual intValue : ()I
    //   1069: bipush #32
    //   1071: irem
    //   1072: invokestatic abs : (I)I
    //   1075: invokevirtual charAt : (I)C
    //   1078: invokevirtual append : (C)Ljava/lang/StringBuilder;
    //   1081: pop
    //   1082: iload_2
    //   1083: ifne -> 1348
    //   1086: goto -> 1093
    //   1089: invokestatic a : (Ljava/lang/Throwable;)Ljava/lang/Throwable;
    //   1092: athrow
    //   1093: aload_3
    //   1094: getstatic burp/Zlqq.Za : Ljava/lang/String;
    //   1097: getstatic burp/Zgqp.Zf : Ljava/lang/Object;
    //   1100: checkcast java/math/BigInteger
    //   1103: invokevirtual intValue : ()I
    //   1106: bipush #32
    //   1108: irem
    //   1109: invokestatic abs : (I)I
    //   1112: invokevirtual charAt : (I)C
    //   1115: invokevirtual append : (C)Ljava/lang/StringBuilder;
    //   1118: pop
    //   1119: iload_2
    //   1120: ifne -> 1348
    //   1123: goto -> 1130
    //   1126: invokestatic a : (Ljava/lang/Throwable;)Ljava/lang/Throwable;
    //   1129: athrow
    //   1130: aload_3
    //   1131: getstatic burp/Zgb9.Zk : Ljava/lang/String;
    //   1134: getstatic burp/Zm0v.ZH : Ljava/lang/Object;
    //   1137: checkcast java/math/BigInteger
    //   1140: invokevirtual intValue : ()I
    //   1143: bipush #32
    //   1145: irem
    //   1146: invokestatic abs : (I)I
    //   1149: invokevirtual charAt : (I)C
    //   1152: invokevirtual append : (C)Ljava/lang/StringBuilder;
    //   1155: pop
    //   1156: iload_2
    //   1157: ifne -> 1348
    //   1160: goto -> 1167
    //   1163: invokestatic a : (Ljava/lang/Throwable;)Ljava/lang/Throwable;
    //   1166: athrow
    //   1167: aload_3
    //   1168: getstatic burp/Zeoa.Zn : Ljava/lang/String;
    //   1171: getstatic burp/Zsvh.Zv : Ljava/lang/Object;
    //   1174: checkcast java/math/BigInteger
    //   1177: invokevirtual intValue : ()I
    //   1180: bipush #32
    //   1182: irem
    //   1183: invokestatic abs : (I)I
    //   1186: invokevirtual charAt : (I)C
    //   1189: invokevirtual append : (C)Ljava/lang/StringBuilder;
    //   1192: pop
    //   1193: iload_2
    //   1194: ifne -> 1348
    //   1197: goto -> 1204
    //   1200: invokestatic a : (Ljava/lang/Throwable;)Ljava/lang/Throwable;
    //   1203: athrow
    //   1204: aload_3
    //   1205: getstatic burp/Zzi3.ZS : Ljava/lang/String;
    //   1208: getstatic burp/Zzuh.ZV : Ljava/lang/Object;
    //   1211: checkcast java/math/BigInteger
    //   1214: invokevirtual intValue : ()I
    //   1217: bipush #32
    //   1219: irem
    //   1220: invokestatic abs : (I)I
    //   1223: invokevirtual charAt : (I)C
    //   1226: invokevirtual append : (C)Ljava/lang/StringBuilder;
    //   1229: pop
    //   1230: iload_2
    //   1231: ifne -> 1348
    //   1234: goto -> 1241
    //   1237: invokestatic a : (Ljava/lang/Throwable;)Ljava/lang/Throwable;
    //   1240: athrow
    //   1241: aload_3
    //   1242: getstatic burp/Zlqy.ZZ : Ljava/lang/String;
    //   1245: getstatic burp/Zgil.ZG : Ljava/lang/Object;
    //   1248: checkcast java/math/BigInteger
    //   1251: invokevirtual intValue : ()I
    //   1254: bipush #32
    //   1256: irem
    //   1257: invokestatic abs : (I)I
    //   1260: invokevirtual charAt : (I)C
    //   1263: invokevirtual append : (C)Ljava/lang/StringBuilder;
    //   1266: pop
    //   1267: iload_2
    //   1268: ifne -> 1348
    //   1271: goto -> 1278
    //   1274: invokestatic a : (Ljava/lang/Throwable;)Ljava/lang/Throwable;
    //   1277: athrow
    //   1278: aload_3
    //   1279: getstatic burp/Zkby.Zf : Ljava/lang/String;
    //   1282: getstatic burp/Zsvh.Zv : Ljava/lang/Object;
    //   1285: checkcast java/math/BigInteger
    //   1288: invokevirtual intValue : ()I
    //   1291: bipush #32
    //   1293: irem
    //   1294: invokestatic abs : (I)I
    //   1297: invokevirtual charAt : (I)C
    //   1300: invokevirtual append : (C)Ljava/lang/StringBuilder;
    //   1303: pop
    //   1304: iload_2
    //   1305: ifne -> 1348
    //   1308: goto -> 1315
    //   1311: invokestatic a : (Ljava/lang/Throwable;)Ljava/lang/Throwable;
    //   1314: athrow
    //   1315: aload_3
    //   1316: getstatic burp/Zsq6.Zm : Ljava/lang/String;
    //   1319: getstatic burp/Zgqp.Zf : Ljava/lang/Object;
    //   1322: checkcast java/math/BigInteger
    //   1325: invokevirtual intValue : ()I
    //   1328: bipush #32
    //   1330: irem
    //   1331: invokestatic abs : (I)I
    //   1334: invokevirtual charAt : (I)C
    //   1337: invokevirtual append : (C)Ljava/lang/StringBuilder;
    //   1340: pop
    //   1341: goto -> 1348
    //   1344: invokestatic a : (Ljava/lang/Throwable;)Ljava/lang/Throwable;
    //   1347: athrow
    //   1348: iinc #4, 1
    //   1351: iload_2
    //   1352: ifne -> 15
    //   1355: aload_3
    //   1356: invokevirtual toString : ()Ljava/lang/String;
    //   1359: putstatic burp/Zg8.ZE : Ljava/lang/String;
    //   1362: new java/lang/StringBuilder
    //   1365: dup
    //   1366: invokespecial <init> : ()V
    //   1369: astore #4
    //   1371: iconst_0
    //   1372: istore #5
    //   1374: iload #5
    //   1376: bipush #32
    //   1378: if_icmpge -> 2743
    //   1381: iload #5
    //   1383: tableswitch default -> 2736, 0 -> 1524, 1 -> 1562, 2 -> 1600, 3 -> 1638, 4 -> 1676, 5 -> 1714, 6 -> 1752, 7 -> 1790, 8 -> 1828, 9 -> 1866, 10 -> 1904, 11 -> 1942, 12 -> 1980, 13 -> 2018, 14 -> 2056, 15 -> 2094, 16 -> 2132, 17 -> 2170, 18 -> 2208, 19 -> 2246, 20 -> 2284, 21 -> 2322, 22 -> 2360, 23 -> 2398, 24 -> 2436, 25 -> 2474, 26 -> 2512, 27 -> 2550, 28 -> 2588, 29 -> 2626, 30 -> 2664, 31 -> 2702
    //   1524: aload #4
    //   1526: getstatic burp/Zmpv.Zb : Ljava/lang/String;
    //   1529: getstatic burp/Zb1.Zf : Ljava/lang/Object;
    //   1532: checkcast java/math/BigInteger
    //   1535: invokevirtual intValue : ()I
    //   1538: bipush #32
    //   1540: irem
    //   1541: invokestatic abs : (I)I
    //   1544: invokevirtual charAt : (I)C
    //   1547: invokevirtual append : (C)Ljava/lang/StringBuilder;
    //   1550: pop
    //   1551: iload_2
    //   1552: ifne -> 2736
    //   1555: goto -> 1562
    //   1558: invokestatic a : (Ljava/lang/Throwable;)Ljava/lang/Throwable;
    //   1561: athrow
    //   1562: aload #4
    //   1564: getstatic burp/Zgh3.ZR : Ljava/lang/String;
    //   1567: getstatic burp/Zx0t.Zt : Ljava/lang/Object;
    //   1570: checkcast java/math/BigInteger
    //   1573: invokevirtual intValue : ()I
    //   1576: bipush #32
    //   1578: irem
    //   1579: invokestatic abs : (I)I
    //   1582: invokevirtual charAt : (I)C
    //   1585: invokevirtual append : (C)Ljava/lang/StringBuilder;
    //   1588: pop
    //   1589: iload_2
    //   1590: ifne -> 2736
    //   1593: goto -> 1600
    //   1596: invokestatic a : (Ljava/lang/Throwable;)Ljava/lang/Throwable;
    //   1599: athrow
    //   1600: aload #4
    //   1602: getstatic burp/Ztvn.ZU : Ljava/lang/String;
    //   1605: getstatic burp/Zrug.Zp : Ljava/lang/Object;
    //   1608: checkcast java/math/BigInteger
    //   1611: invokevirtual intValue : ()I
    //   1614: bipush #32
    //   1616: irem
    //   1617: invokestatic abs : (I)I
    //   1620: invokevirtual charAt : (I)C
    //   1623: invokevirtual append : (C)Ljava/lang/StringBuilder;
    //   1626: pop
    //   1627: iload_2
    //   1628: ifne -> 2736
    //   1631: goto -> 1638
    //   1634: invokestatic a : (Ljava/lang/Throwable;)Ljava/lang/Throwable;
    //   1637: athrow
    //   1638: aload #4
    //   1640: getstatic burp/Zrc0.ZL : Ljava/lang/String;
    //   1643: getstatic burp/Zlhk.ZD : Ljava/lang/Object;
    //   1646: checkcast java/math/BigInteger
    //   1649: invokevirtual intValue : ()I
    //   1652: bipush #32
    //   1654: irem
    //   1655: invokestatic abs : (I)I
    //   1658: invokevirtual charAt : (I)C
    //   1661: invokevirtual append : (C)Ljava/lang/StringBuilder;
    //   1664: pop
    //   1665: iload_2
    //   1666: ifne -> 2736
    //   1669: goto -> 1676
    //   1672: invokestatic a : (Ljava/lang/Throwable;)Ljava/lang/Throwable;
    //   1675: athrow
    //   1676: aload #4
    //   1678: getstatic burp/Zrdo.Zj : Ljava/lang/String;
    //   1681: getstatic burp/Zrdo.ZK : Ljava/lang/Object;
    //   1684: checkcast java/math/BigInteger
    //   1687: invokevirtual intValue : ()I
    //   1690: bipush #32
    //   1692: irem
    //   1693: invokestatic abs : (I)I
    //   1696: invokevirtual charAt : (I)C
    //   1699: invokevirtual append : (C)Ljava/lang/StringBuilder;
    //   1702: pop
    //   1703: iload_2
    //   1704: ifne -> 2736
    //   1707: goto -> 1714
    //   1710: invokestatic a : (Ljava/lang/Throwable;)Ljava/lang/Throwable;
    //   1713: athrow
    //   1714: aload #4
    //   1716: getstatic burp/Zxzt.ZG : Ljava/lang/String;
    //   1719: getstatic burp/Zss8.ZO : Ljava/lang/Object;
    //   1722: checkcast java/math/BigInteger
    //   1725: invokevirtual intValue : ()I
    //   1728: bipush #32
    //   1730: irem
    //   1731: invokestatic abs : (I)I
    //   1734: invokevirtual charAt : (I)C
    //   1737: invokevirtual append : (C)Ljava/lang/StringBuilder;
    //   1740: pop
    //   1741: iload_2
    //   1742: ifne -> 2736
    //   1745: goto -> 1752
    //   1748: invokestatic a : (Ljava/lang/Throwable;)Ljava/lang/Throwable;
    //   1751: athrow
    //   1752: aload #4
    //   1754: getstatic burp/Ze0z.ZU : Ljava/lang/String;
    //   1757: getstatic burp/Ztjh.ZU : Ljava/lang/Object;
    //   1760: checkcast java/math/BigInteger
    //   1763: invokevirtual intValue : ()I
    //   1766: bipush #32
    //   1768: irem
    //   1769: invokestatic abs : (I)I
    //   1772: invokevirtual charAt : (I)C
    //   1775: invokevirtual append : (C)Ljava/lang/StringBuilder;
    //   1778: pop
    //   1779: iload_2
    //   1780: ifne -> 2736
    //   1783: goto -> 1790
    //   1786: invokestatic a : (Ljava/lang/Throwable;)Ljava/lang/Throwable;
    //   1789: athrow
    //   1790: aload #4
    //   1792: getstatic burp/Zkor.Za : Ljava/lang/String;
    //   1795: getstatic burp/Zrdo.ZK : Ljava/lang/Object;
    //   1798: checkcast java/math/BigInteger
    //   1801: invokevirtual intValue : ()I
    //   1804: bipush #32
    //   1806: irem
    //   1807: invokestatic abs : (I)I
    //   1810: invokevirtual charAt : (I)C
    //   1813: invokevirtual append : (C)Ljava/lang/StringBuilder;
    //   1816: pop
    //   1817: iload_2
    //   1818: ifne -> 2736
    //   1821: goto -> 1828
    //   1824: invokestatic a : (Ljava/lang/Throwable;)Ljava/lang/Throwable;
    //   1827: athrow
    //   1828: aload #4
    //   1830: getstatic burp/Ze6t.ZR : Ljava/lang/String;
    //   1833: getstatic burp/Zss8.ZO : Ljava/lang/Object;
    //   1836: checkcast java/math/BigInteger
    //   1839: invokevirtual intValue : ()I
    //   1842: bipush #32
    //   1844: irem
    //   1845: invokestatic abs : (I)I
    //   1848: invokevirtual charAt : (I)C
    //   1851: invokevirtual append : (C)Ljava/lang/StringBuilder;
    //   1854: pop
    //   1855: iload_2
    //   1856: ifne -> 2736
    //   1859: goto -> 1866
    //   1862: invokestatic a : (Ljava/lang/Throwable;)Ljava/lang/Throwable;
    //   1865: athrow
    //   1866: aload #4
    //   1868: getstatic burp/Zxzt.ZG : Ljava/lang/String;
    //   1871: getstatic burp/Zl55.ZZ : Ljava/lang/Object;
    //   1874: checkcast java/math/BigInteger
    //   1877: invokevirtual intValue : ()I
    //   1880: bipush #32
    //   1882: irem
    //   1883: invokestatic abs : (I)I
    //   1886: invokevirtual charAt : (I)C
    //   1889: invokevirtual append : (C)Ljava/lang/StringBuilder;
    //   1892: pop
    //   1893: iload_2
    //   1894: ifne -> 2736
    //   1897: goto -> 1904
    //   1900: invokestatic a : (Ljava/lang/Throwable;)Ljava/lang/Throwable;
    //   1903: athrow
    //   1904: aload #4
    //   1906: getstatic burp/Zr_w.Zi : Ljava/lang/String;
    //   1909: getstatic burp/Zbu6.ZJ : Ljava/lang/Object;
    //   1912: checkcast java/math/BigInteger
    //   1915: invokevirtual intValue : ()I
    //   1918: bipush #32
    //   1920: irem
    //   1921: invokestatic abs : (I)I
    //   1924: invokevirtual charAt : (I)C
    //   1927: invokevirtual append : (C)Ljava/lang/StringBuilder;
    //   1930: pop
    //   1931: iload_2
    //   1932: ifne -> 2736
    //   1935: goto -> 1942
    //   1938: invokestatic a : (Ljava/lang/Throwable;)Ljava/lang/Throwable;
    //   1941: athrow
    //   1942: aload #4
    //   1944: getstatic burp/Zbu6.ZQ : Ljava/lang/String;
    //   1947: getstatic burp/Zvof.Zl : Ljava/lang/Object;
    //   1950: checkcast java/math/BigInteger
    //   1953: invokevirtual intValue : ()I
    //   1956: bipush #32
    //   1958: irem
    //   1959: invokestatic abs : (I)I
    //   1962: invokevirtual charAt : (I)C
    //   1965: invokevirtual append : (C)Ljava/lang/StringBuilder;
    //   1968: pop
    //   1969: iload_2
    //   1970: ifne -> 2736
    //   1973: goto -> 1980
    //   1976: invokestatic a : (Ljava/lang/Throwable;)Ljava/lang/Throwable;
    //   1979: athrow
    //   1980: aload #4
    //   1982: getstatic burp/Zm0v.Zd : Ljava/lang/String;
    //   1985: getstatic burp/Zz4r.ZQ : Ljava/lang/Object;
    //   1988: checkcast java/math/BigInteger
    //   1991: invokevirtual intValue : ()I
    //   1994: bipush #32
    //   1996: irem
    //   1997: invokestatic abs : (I)I
    //   2000: invokevirtual charAt : (I)C
    //   2003: invokevirtual append : (C)Ljava/lang/StringBuilder;
    //   2006: pop
    //   2007: iload_2
    //   2008: ifne -> 2736
    //   2011: goto -> 2018
    //   2014: invokestatic a : (Ljava/lang/Throwable;)Ljava/lang/Throwable;
    //   2017: athrow
    //   2018: aload #4
    //   2020: getstatic burp/Zltp.ZY : Ljava/lang/String;
    //   2023: getstatic burp/Zb9d.Ze : Ljava/lang/Object;
    //   2026: checkcast java/math/BigInteger
    //   2029: invokevirtual intValue : ()I
    //   2032: bipush #32
    //   2034: irem
    //   2035: invokestatic abs : (I)I
    //   2038: invokevirtual charAt : (I)C
    //   2041: invokevirtual append : (C)Ljava/lang/StringBuilder;
    //   2044: pop
    //   2045: iload_2
    //   2046: ifne -> 2736
    //   2049: goto -> 2056
    //   2052: invokestatic a : (Ljava/lang/Throwable;)Ljava/lang/Throwable;
    //   2055: athrow
    //   2056: aload #4
    //   2058: getstatic burp/Zb8x.Zp : Ljava/lang/String;
    //   2061: getstatic burp/Zssb.ZW : Ljava/lang/Object;
    //   2064: checkcast java/math/BigInteger
    //   2067: invokevirtual intValue : ()I
    //   2070: bipush #32
    //   2072: irem
    //   2073: invokestatic abs : (I)I
    //   2076: invokevirtual charAt : (I)C
    //   2079: invokevirtual append : (C)Ljava/lang/StringBuilder;
    //   2082: pop
    //   2083: iload_2
    //   2084: ifne -> 2736
    //   2087: goto -> 2094
    //   2090: invokestatic a : (Ljava/lang/Throwable;)Ljava/lang/Throwable;
    //   2093: athrow
    //   2094: aload #4
    //   2096: getstatic burp/Zep8.ZC : Ljava/lang/String;
    //   2099: getstatic burp/Zeoa.ZF : Ljava/lang/Object;
    //   2102: checkcast java/math/BigInteger
    //   2105: invokevirtual intValue : ()I
    //   2108: bipush #32
    //   2110: irem
    //   2111: invokestatic abs : (I)I
    //   2114: invokevirtual charAt : (I)C
    //   2117: invokevirtual append : (C)Ljava/lang/StringBuilder;
    //   2120: pop
    //   2121: iload_2
    //   2122: ifne -> 2736
    //   2125: goto -> 2132
    //   2128: invokestatic a : (Ljava/lang/Throwable;)Ljava/lang/Throwable;
    //   2131: athrow
    //   2132: aload #4
    //   2134: getstatic burp/Ze0z.ZU : Ljava/lang/String;
    //   2137: getstatic burp/Zr64.ZN : Ljava/lang/Object;
    //   2140: checkcast java/math/BigInteger
    //   2143: invokevirtual intValue : ()I
    //   2146: bipush #32
    //   2148: irem
    //   2149: invokestatic abs : (I)I
    //   2152: invokevirtual charAt : (I)C
    //   2155: invokevirtual append : (C)Ljava/lang/StringBuilder;
    //   2158: pop
    //   2159: iload_2
    //   2160: ifne -> 2736
    //   2163: goto -> 2170
    //   2166: invokestatic a : (Ljava/lang/Throwable;)Ljava/lang/Throwable;
    //   2169: athrow
    //   2170: aload #4
    //   2172: getstatic burp/Zzuh.ZX : Ljava/lang/String;
    //   2175: getstatic burp/Ztgt.ZU : Ljava/lang/Object;
    //   2178: checkcast java/math/BigInteger
    //   2181: invokevirtual intValue : ()I
    //   2184: bipush #32
    //   2186: irem
    //   2187: invokestatic abs : (I)I
    //   2190: invokevirtual charAt : (I)C
    //   2193: invokevirtual append : (C)Ljava/lang/StringBuilder;
    //   2196: pop
    //   2197: iload_2
    //   2198: ifne -> 2736
    //   2201: goto -> 2208
    //   2204: invokestatic a : (Ljava/lang/Throwable;)Ljava/lang/Throwable;
    //   2207: athrow
    //   2208: aload #4
    //   2210: getstatic burp/Ztvn.ZU : Ljava/lang/String;
    //   2213: getstatic burp/Zts_.ZH : Ljava/lang/Object;
    //   2216: checkcast java/math/BigInteger
    //   2219: invokevirtual intValue : ()I
    //   2222: bipush #32
    //   2224: irem
    //   2225: invokestatic abs : (I)I
    //   2228: invokevirtual charAt : (I)C
    //   2231: invokevirtual append : (C)Ljava/lang/StringBuilder;
    //   2234: pop
    //   2235: iload_2
    //   2236: ifne -> 2736
    //   2239: goto -> 2246
    //   2242: invokestatic a : (Ljava/lang/Throwable;)Ljava/lang/Throwable;
    //   2245: athrow
    //   2246: aload #4
    //   2248: getstatic burp/Zgz1.Zs : Ljava/lang/String;
    //   2251: getstatic burp/Zsji.Zg : Ljava/lang/Object;
    //   2254: checkcast java/math/BigInteger
    //   2257: invokevirtual intValue : ()I
    //   2260: bipush #32
    //   2262: irem
    //   2263: invokestatic abs : (I)I
    //   2266: invokevirtual charAt : (I)C
    //   2269: invokevirtual append : (C)Ljava/lang/StringBuilder;
    //   2272: pop
    //   2273: iload_2
    //   2274: ifne -> 2736
    //   2277: goto -> 2284
    //   2280: invokestatic a : (Ljava/lang/Throwable;)Ljava/lang/Throwable;
    //   2283: athrow
    //   2284: aload #4
    //   2286: getstatic burp/Zz80.Ze : Ljava/lang/String;
    //   2289: getstatic burp/Zzi3.ZJ : Ljava/lang/Object;
    //   2292: checkcast java/math/BigInteger
    //   2295: invokevirtual intValue : ()I
    //   2298: bipush #32
    //   2300: irem
    //   2301: invokestatic abs : (I)I
    //   2304: invokevirtual charAt : (I)C
    //   2307: invokevirtual append : (C)Ljava/lang/StringBuilder;
    //   2310: pop
    //   2311: iload_2
    //   2312: ifne -> 2736
    //   2315: goto -> 2322
    //   2318: invokestatic a : (Ljava/lang/Throwable;)Ljava/lang/Throwable;
    //   2321: athrow
    //   2322: aload #4
    //   2324: getstatic burp/Zb1.Z_ : Ljava/lang/String;
    //   2327: getstatic burp/Zx0t.Zt : Ljava/lang/Object;
    //   2330: checkcast java/math/BigInteger
    //   2333: invokevirtual intValue : ()I
    //   2336: bipush #32
    //   2338: irem
    //   2339: invokestatic abs : (I)I
    //   2342: invokevirtual charAt : (I)C
    //   2345: invokevirtual append : (C)Ljava/lang/StringBuilder;
    //   2348: pop
    //   2349: iload_2
    //   2350: ifne -> 2736
    //   2353: goto -> 2360
    //   2356: invokestatic a : (Ljava/lang/Throwable;)Ljava/lang/Throwable;
    //   2359: athrow
    //   2360: aload #4
    //   2362: getstatic burp/Zssb.ZY : Ljava/lang/String;
    //   2365: getstatic burp/Zl55.ZZ : Ljava/lang/Object;
    //   2368: checkcast java/math/BigInteger
    //   2371: invokevirtual intValue : ()I
    //   2374: bipush #32
    //   2376: irem
    //   2377: invokestatic abs : (I)I
    //   2380: invokevirtual charAt : (I)C
    //   2383: invokevirtual append : (C)Ljava/lang/StringBuilder;
    //   2386: pop
    //   2387: iload_2
    //   2388: ifne -> 2736
    //   2391: goto -> 2398
    //   2394: invokestatic a : (Ljava/lang/Throwable;)Ljava/lang/Throwable;
    //   2397: athrow
    //   2398: aload #4
    //   2400: getstatic burp/Zkw.ZU : Ljava/lang/String;
    //   2403: getstatic burp/Zbu6.ZJ : Ljava/lang/Object;
    //   2406: checkcast java/math/BigInteger
    //   2409: invokevirtual intValue : ()I
    //   2412: bipush #32
    //   2414: irem
    //   2415: invokestatic abs : (I)I
    //   2418: invokevirtual charAt : (I)C
    //   2421: invokevirtual append : (C)Ljava/lang/StringBuilder;
    //   2424: pop
    //   2425: iload_2
    //   2426: ifne -> 2736
    //   2429: goto -> 2436
    //   2432: invokestatic a : (Ljava/lang/Throwable;)Ljava/lang/Throwable;
    //   2435: athrow
    //   2436: aload #4
    //   2438: getstatic burp/Zgqp.ZA : Ljava/lang/String;
    //   2441: getstatic burp/Ze6t.Zu : Ljava/lang/Object;
    //   2444: checkcast java/math/BigInteger
    //   2447: invokevirtual intValue : ()I
    //   2450: bipush #32
    //   2452: irem
    //   2453: invokestatic abs : (I)I
    //   2456: invokevirtual charAt : (I)C
    //   2459: invokevirtual append : (C)Ljava/lang/StringBuilder;
    //   2462: pop
    //   2463: iload_2
    //   2464: ifne -> 2736
    //   2467: goto -> 2474
    //   2470: invokestatic a : (Ljava/lang/Throwable;)Ljava/lang/Throwable;
    //   2473: athrow
    //   2474: aload #4
    //   2476: getstatic burp/Zrqd.Zk : Ljava/lang/String;
    //   2479: getstatic burp/Zrqd.Zi : Ljava/lang/Object;
    //   2482: checkcast java/math/BigInteger
    //   2485: invokevirtual intValue : ()I
    //   2488: bipush #32
    //   2490: irem
    //   2491: invokestatic abs : (I)I
    //   2494: invokevirtual charAt : (I)C
    //   2497: invokevirtual append : (C)Ljava/lang/StringBuilder;
    //   2500: pop
    //   2501: iload_2
    //   2502: ifne -> 2736
    //   2505: goto -> 2512
    //   2508: invokestatic a : (Ljava/lang/Throwable;)Ljava/lang/Throwable;
    //   2511: athrow
    //   2512: aload #4
    //   2514: getstatic burp/Zrdo.Zj : Ljava/lang/String;
    //   2517: getstatic burp/Ztjh.ZU : Ljava/lang/Object;
    //   2520: checkcast java/math/BigInteger
    //   2523: invokevirtual intValue : ()I
    //   2526: bipush #32
    //   2528: irem
    //   2529: invokestatic abs : (I)I
    //   2532: invokevirtual charAt : (I)C
    //   2535: invokevirtual append : (C)Ljava/lang/StringBuilder;
    //   2538: pop
    //   2539: iload_2
    //   2540: ifne -> 2736
    //   2543: goto -> 2550
    //   2546: invokestatic a : (Ljava/lang/Throwable;)Ljava/lang/Throwable;
    //   2549: athrow
    //   2550: aload #4
    //   2552: getstatic burp/Zvof.ZR : Ljava/lang/String;
    //   2555: getstatic burp/Zeyd.Zl : Ljava/lang/Object;
    //   2558: checkcast java/math/BigInteger
    //   2561: invokevirtual intValue : ()I
    //   2564: bipush #32
    //   2566: irem
    //   2567: invokestatic abs : (I)I
    //   2570: invokevirtual charAt : (I)C
    //   2573: invokevirtual append : (C)Ljava/lang/StringBuilder;
    //   2576: pop
    //   2577: iload_2
    //   2578: ifne -> 2736
    //   2581: goto -> 2588
    //   2584: invokestatic a : (Ljava/lang/Throwable;)Ljava/lang/Throwable;
    //   2587: athrow
    //   2588: aload #4
    //   2590: getstatic burp/Zbf9.Zp : Ljava/lang/String;
    //   2593: getstatic burp/Zkw.ZY : Ljava/lang/Object;
    //   2596: checkcast java/math/BigInteger
    //   2599: invokevirtual intValue : ()I
    //   2602: bipush #32
    //   2604: irem
    //   2605: invokestatic abs : (I)I
    //   2608: invokevirtual charAt : (I)C
    //   2611: invokevirtual append : (C)Ljava/lang/StringBuilder;
    //   2614: pop
    //   2615: iload_2
    //   2616: ifne -> 2736
    //   2619: goto -> 2626
    //   2622: invokestatic a : (Ljava/lang/Throwable;)Ljava/lang/Throwable;
    //   2625: athrow
    //   2626: aload #4
    //   2628: getstatic burp/Zrc0.ZL : Ljava/lang/String;
    //   2631: getstatic burp/Zkor.Ze : Ljava/lang/Object;
    //   2634: checkcast java/math/BigInteger
    //   2637: invokevirtual intValue : ()I
    //   2640: bipush #32
    //   2642: irem
    //   2643: invokestatic abs : (I)I
    //   2646: invokevirtual charAt : (I)C
    //   2649: invokevirtual append : (C)Ljava/lang/StringBuilder;
    //   2652: pop
    //   2653: iload_2
    //   2654: ifne -> 2736
    //   2657: goto -> 2664
    //   2660: invokestatic a : (Ljava/lang/Throwable;)Ljava/lang/Throwable;
    //   2663: athrow
    //   2664: aload #4
    //   2666: getstatic burp/Zz4r.Zq : Ljava/lang/String;
    //   2669: getstatic burp/Zluk.Zz : Ljava/lang/Object;
    //   2672: checkcast java/math/BigInteger
    //   2675: invokevirtual intValue : ()I
    //   2678: bipush #32
    //   2680: irem
    //   2681: invokestatic abs : (I)I
    //   2684: invokevirtual charAt : (I)C
    //   2687: invokevirtual append : (C)Ljava/lang/StringBuilder;
    //   2690: pop
    //   2691: iload_2
    //   2692: ifne -> 2736
    //   2695: goto -> 2702
    //   2698: invokestatic a : (Ljava/lang/Throwable;)Ljava/lang/Throwable;
    //   2701: athrow
    //   2702: aload #4
    //   2704: getstatic burp/Zk52.ZL : Ljava/lang/String;
    //   2707: getstatic burp/Zg_i.ZQ : Ljava/lang/Object;
    //   2710: checkcast java/math/BigInteger
    //   2713: invokevirtual intValue : ()I
    //   2716: bipush #32
    //   2718: irem
    //   2719: invokestatic abs : (I)I
    //   2722: invokevirtual charAt : (I)C
    //   2725: invokevirtual append : (C)Ljava/lang/StringBuilder;
    //   2728: pop
    //   2729: goto -> 2736
    //   2732: invokestatic a : (Ljava/lang/Throwable;)Ljava/lang/Throwable;
    //   2735: athrow
    //   2736: iinc #5, 1
    //   2739: iload_2
    //   2740: ifne -> 1374
    //   2743: aload #4
    //   2745: invokevirtual toString : ()Ljava/lang/String;
    //   2748: putstatic burp/Zts_.Zx : Ljava/lang/String;
    //   2751: new java/lang/StringBuilder
    //   2754: dup
    //   2755: invokespecial <init> : ()V
    //   2758: astore #5
    //   2760: iconst_0
    //   2761: istore #6
    //   2763: iload #6
    //   2765: bipush #32
    //   2767: if_icmpge -> 4135
    //   2770: iload #6
    //   2772: tableswitch default -> 4128, 0 -> 2916, 1 -> 2954, 2 -> 2992, 3 -> 3030, 4 -> 3068, 5 -> 3106, 6 -> 3144, 7 -> 3182, 8 -> 3220, 9 -> 3258, 10 -> 3296, 11 -> 3334, 12 -> 3372, 13 -> 3410, 14 -> 3448, 15 -> 3486, 16 -> 3524, 17 -> 3562, 18 -> 3600, 19 -> 3638, 20 -> 3676, 21 -> 3714, 22 -> 3752, 23 -> 3790, 24 -> 3828, 25 -> 3866, 26 -> 3904, 27 -> 3942, 28 -> 3980, 29 -> 4018, 30 -> 4056, 31 -> 4094
    //   2916: aload #5
    //   2918: getstatic burp/Zg_y.ZF : Ljava/lang/String;
    //   2921: getstatic burp/Zb9d.Ze : Ljava/lang/Object;
    //   2924: checkcast java/math/BigInteger
    //   2927: invokevirtual intValue : ()I
    //   2930: bipush #32
    //   2932: irem
    //   2933: invokestatic abs : (I)I
    //   2936: invokevirtual charAt : (I)C
    //   2939: invokevirtual append : (C)Ljava/lang/StringBuilder;
    //   2942: pop
    //   2943: iload_2
    //   2944: ifne -> 4128
    //   2947: goto -> 2954
    //   2950: invokestatic a : (Ljava/lang/Throwable;)Ljava/lang/Throwable;
    //   2953: athrow
    //   2954: aload #5
    //   2956: getstatic burp/Zrdo.Zj : Ljava/lang/String;
    //   2959: getstatic burp/Zeoa.ZF : Ljava/lang/Object;
    //   2962: checkcast java/math/BigInteger
    //   2965: invokevirtual intValue : ()I
    //   2968: bipush #32
    //   2970: irem
    //   2971: invokestatic abs : (I)I
    //   2974: invokevirtual charAt : (I)C
    //   2977: invokevirtual append : (C)Ljava/lang/StringBuilder;
    //   2980: pop
    //   2981: iload_2
    //   2982: ifne -> 4128
    //   2985: goto -> 2992
    //   2988: invokestatic a : (Ljava/lang/Throwable;)Ljava/lang/Throwable;
    //   2991: athrow
    //   2992: aload #5
    //   2994: getstatic burp/Zk7b.ZE : Ljava/lang/String;
    //   2997: getstatic burp/Zep8.Zs : Ljava/lang/Object;
    //   3000: checkcast java/math/BigInteger
    //   3003: invokevirtual intValue : ()I
    //   3006: bipush #32
    //   3008: irem
    //   3009: invokestatic abs : (I)I
    //   3012: invokevirtual charAt : (I)C
    //   3015: invokevirtual append : (C)Ljava/lang/StringBuilder;
    //   3018: pop
    //   3019: iload_2
    //   3020: ifne -> 4128
    //   3023: goto -> 3030
    //   3026: invokestatic a : (Ljava/lang/Throwable;)Ljava/lang/Throwable;
    //   3029: athrow
    //   3030: aload #5
    //   3032: getstatic burp/Zgz1.Zs : Ljava/lang/String;
    //   3035: getstatic burp/Zlqq.ZV : Ljava/lang/Object;
    //   3038: checkcast java/math/BigInteger
    //   3041: invokevirtual intValue : ()I
    //   3044: bipush #32
    //   3046: irem
    //   3047: invokestatic abs : (I)I
    //   3050: invokevirtual charAt : (I)C
    //   3053: invokevirtual append : (C)Ljava/lang/StringBuilder;
    //   3056: pop
    //   3057: iload_2
    //   3058: ifne -> 4128
    //   3061: goto -> 3068
    //   3064: invokestatic a : (Ljava/lang/Throwable;)Ljava/lang/Throwable;
    //   3067: athrow
    //   3068: aload #5
    //   3070: getstatic burp/Zxti.ZD : Ljava/lang/String;
    //   3073: getstatic burp/Zx0t.Zt : Ljava/lang/Object;
    //   3076: checkcast java/math/BigInteger
    //   3079: invokevirtual intValue : ()I
    //   3082: bipush #32
    //   3084: irem
    //   3085: invokestatic abs : (I)I
    //   3088: invokevirtual charAt : (I)C
    //   3091: invokevirtual append : (C)Ljava/lang/StringBuilder;
    //   3094: pop
    //   3095: iload_2
    //   3096: ifne -> 4128
    //   3099: goto -> 3106
    //   3102: invokestatic a : (Ljava/lang/Throwable;)Ljava/lang/Throwable;
    //   3105: athrow
    //   3106: aload #5
    //   3108: getstatic burp/Zsn6.Zs : Ljava/lang/String;
    //   3111: getstatic burp/Zr_w.ZK : Ljava/lang/Object;
    //   3114: checkcast java/math/BigInteger
    //   3117: invokevirtual intValue : ()I
    //   3120: bipush #32
    //   3122: irem
    //   3123: invokestatic abs : (I)I
    //   3126: invokevirtual charAt : (I)C
    //   3129: invokevirtual append : (C)Ljava/lang/StringBuilder;
    //   3132: pop
    //   3133: iload_2
    //   3134: ifne -> 4128
    //   3137: goto -> 3144
    //   3140: invokestatic a : (Ljava/lang/Throwable;)Ljava/lang/Throwable;
    //   3143: athrow
    //   3144: aload #5
    //   3146: getstatic burp/Zrdo.Zj : Ljava/lang/String;
    //   3149: getstatic burp/Zzi3.ZJ : Ljava/lang/Object;
    //   3152: checkcast java/math/BigInteger
    //   3155: invokevirtual intValue : ()I
    //   3158: bipush #32
    //   3160: irem
    //   3161: invokestatic abs : (I)I
    //   3164: invokevirtual charAt : (I)C
    //   3167: invokevirtual append : (C)Ljava/lang/StringBuilder;
    //   3170: pop
    //   3171: iload_2
    //   3172: ifne -> 4128
    //   3175: goto -> 3182
    //   3178: invokestatic a : (Ljava/lang/Throwable;)Ljava/lang/Throwable;
    //   3181: athrow
    //   3182: aload #5
    //   3184: getstatic burp/Zlfg.Zb : Ljava/lang/String;
    //   3187: getstatic burp/Zxz_.Zv : Ljava/lang/Object;
    //   3190: checkcast java/math/BigInteger
    //   3193: invokevirtual intValue : ()I
    //   3196: bipush #32
    //   3198: irem
    //   3199: invokestatic abs : (I)I
    //   3202: invokevirtual charAt : (I)C
    //   3205: invokevirtual append : (C)Ljava/lang/StringBuilder;
    //   3208: pop
    //   3209: iload_2
    //   3210: ifne -> 4128
    //   3213: goto -> 3220
    //   3216: invokestatic a : (Ljava/lang/Throwable;)Ljava/lang/Throwable;
    //   3219: athrow
    //   3220: aload #5
    //   3222: getstatic burp/Zs4v.Za : Ljava/lang/String;
    //   3225: getstatic burp/Zts_.ZH : Ljava/lang/Object;
    //   3228: checkcast java/math/BigInteger
    //   3231: invokevirtual intValue : ()I
    //   3234: bipush #32
    //   3236: irem
    //   3237: invokestatic abs : (I)I
    //   3240: invokevirtual charAt : (I)C
    //   3243: invokevirtual append : (C)Ljava/lang/StringBuilder;
    //   3246: pop
    //   3247: iload_2
    //   3248: ifne -> 4128
    //   3251: goto -> 3258
    //   3254: invokestatic a : (Ljava/lang/Throwable;)Ljava/lang/Throwable;
    //   3257: athrow
    //   3258: aload #5
    //   3260: getstatic burp/Zstq.ZL : Ljava/lang/String;
    //   3263: getstatic burp/Zsn6.Zo : Ljava/lang/Object;
    //   3266: checkcast java/math/BigInteger
    //   3269: invokevirtual intValue : ()I
    //   3272: bipush #32
    //   3274: irem
    //   3275: invokestatic abs : (I)I
    //   3278: invokevirtual charAt : (I)C
    //   3281: invokevirtual append : (C)Ljava/lang/StringBuilder;
    //   3284: pop
    //   3285: iload_2
    //   3286: ifne -> 4128
    //   3289: goto -> 3296
    //   3292: invokestatic a : (Ljava/lang/Throwable;)Ljava/lang/Throwable;
    //   3295: athrow
    //   3296: aload #5
    //   3298: getstatic burp/Zvof.ZR : Ljava/lang/String;
    //   3301: getstatic burp/Zr_z.ZT : Ljava/lang/Object;
    //   3304: checkcast java/math/BigInteger
    //   3307: invokevirtual intValue : ()I
    //   3310: bipush #32
    //   3312: irem
    //   3313: invokestatic abs : (I)I
    //   3316: invokevirtual charAt : (I)C
    //   3319: invokevirtual append : (C)Ljava/lang/StringBuilder;
    //   3322: pop
    //   3323: iload_2
    //   3324: ifne -> 4128
    //   3327: goto -> 3334
    //   3330: invokestatic a : (Ljava/lang/Throwable;)Ljava/lang/Throwable;
    //   3333: athrow
    //   3334: aload #5
    //   3336: getstatic burp/Zss8.ZD : Ljava/lang/String;
    //   3339: getstatic burp/Zgil.ZG : Ljava/lang/Object;
    //   3342: checkcast java/math/BigInteger
    //   3345: invokevirtual intValue : ()I
    //   3348: bipush #32
    //   3350: irem
    //   3351: invokestatic abs : (I)I
    //   3354: invokevirtual charAt : (I)C
    //   3357: invokevirtual append : (C)Ljava/lang/StringBuilder;
    //   3360: pop
    //   3361: iload_2
    //   3362: ifne -> 4128
    //   3365: goto -> 3372
    //   3368: invokestatic a : (Ljava/lang/Throwable;)Ljava/lang/Throwable;
    //   3371: athrow
    //   3372: aload #5
    //   3374: getstatic burp/Zkor.Za : Ljava/lang/String;
    //   3377: getstatic burp/Zrqd.Zi : Ljava/lang/Object;
    //   3380: checkcast java/math/BigInteger
    //   3383: invokevirtual intValue : ()I
    //   3386: bipush #32
    //   3388: irem
    //   3389: invokestatic abs : (I)I
    //   3392: invokevirtual charAt : (I)C
    //   3395: invokevirtual append : (C)Ljava/lang/StringBuilder;
    //   3398: pop
    //   3399: iload_2
    //   3400: ifne -> 4128
    //   3403: goto -> 3410
    //   3406: invokestatic a : (Ljava/lang/Throwable;)Ljava/lang/Throwable;
    //   3409: athrow
    //   3410: aload #5
    //   3412: getstatic burp/Zebu.ZI : Ljava/lang/String;
    //   3415: getstatic burp/Zkup.Zf : Ljava/lang/Object;
    //   3418: checkcast java/math/BigInteger
    //   3421: invokevirtual intValue : ()I
    //   3424: bipush #32
    //   3426: irem
    //   3427: invokestatic abs : (I)I
    //   3430: invokevirtual charAt : (I)C
    //   3433: invokevirtual append : (C)Ljava/lang/StringBuilder;
    //   3436: pop
    //   3437: iload_2
    //   3438: ifne -> 4128
    //   3441: goto -> 3448
    //   3444: invokestatic a : (Ljava/lang/Throwable;)Ljava/lang/Throwable;
    //   3447: athrow
    //   3448: aload #5
    //   3450: getstatic burp/Zg3v.Zt : Ljava/lang/String;
    //   3453: getstatic burp/Zlqq.ZV : Ljava/lang/Object;
    //   3456: checkcast java/math/BigInteger
    //   3459: invokevirtual intValue : ()I
    //   3462: bipush #32
    //   3464: irem
    //   3465: invokestatic abs : (I)I
    //   3468: invokevirtual charAt : (I)C
    //   3471: invokevirtual append : (C)Ljava/lang/StringBuilder;
    //   3474: pop
    //   3475: iload_2
    //   3476: ifne -> 4128
    //   3479: goto -> 3486
    //   3482: invokestatic a : (Ljava/lang/Throwable;)Ljava/lang/Throwable;
    //   3485: athrow
    //   3486: aload #5
    //   3488: getstatic burp/Zmou.ZP : Ljava/lang/String;
    //   3491: getstatic burp/Zrug.Zp : Ljava/lang/Object;
    //   3494: checkcast java/math/BigInteger
    //   3497: invokevirtual intValue : ()I
    //   3500: bipush #32
    //   3502: irem
    //   3503: invokestatic abs : (I)I
    //   3506: invokevirtual charAt : (I)C
    //   3509: invokevirtual append : (C)Ljava/lang/StringBuilder;
    //   3512: pop
    //   3513: iload_2
    //   3514: ifne -> 4128
    //   3517: goto -> 3524
    //   3520: invokestatic a : (Ljava/lang/Throwable;)Ljava/lang/Throwable;
    //   3523: athrow
    //   3524: aload #5
    //   3526: getstatic burp/Zmcb.Zl : Ljava/lang/String;
    //   3529: getstatic burp/Zb9d.Ze : Ljava/lang/Object;
    //   3532: checkcast java/math/BigInteger
    //   3535: invokevirtual intValue : ()I
    //   3538: bipush #32
    //   3540: irem
    //   3541: invokestatic abs : (I)I
    //   3544: invokevirtual charAt : (I)C
    //   3547: invokevirtual append : (C)Ljava/lang/StringBuilder;
    //   3550: pop
    //   3551: iload_2
    //   3552: ifne -> 4128
    //   3555: goto -> 3562
    //   3558: invokestatic a : (Ljava/lang/Throwable;)Ljava/lang/Throwable;
    //   3561: athrow
    //   3562: aload #5
    //   3564: getstatic burp/Zmwx.ZB : Ljava/lang/String;
    //   3567: getstatic burp/Zgx6.Zo : Ljava/lang/Object;
    //   3570: checkcast java/math/BigInteger
    //   3573: invokevirtual intValue : ()I
    //   3576: bipush #32
    //   3578: irem
    //   3579: invokestatic abs : (I)I
    //   3582: invokevirtual charAt : (I)C
    //   3585: invokevirtual append : (C)Ljava/lang/StringBuilder;
    //   3588: pop
    //   3589: iload_2
    //   3590: ifne -> 4128
    //   3593: goto -> 3600
    //   3596: invokestatic a : (Ljava/lang/Throwable;)Ljava/lang/Throwable;
    //   3599: athrow
    //   3600: aload #5
    //   3602: getstatic burp/Zsq6.Zm : Ljava/lang/String;
    //   3605: getstatic burp/Zzx8.Zi : Ljava/lang/Object;
    //   3608: checkcast java/math/BigInteger
    //   3611: invokevirtual intValue : ()I
    //   3614: bipush #32
    //   3616: irem
    //   3617: invokestatic abs : (I)I
    //   3620: invokevirtual charAt : (I)C
    //   3623: invokevirtual append : (C)Ljava/lang/StringBuilder;
    //   3626: pop
    //   3627: iload_2
    //   3628: ifne -> 4128
    //   3631: goto -> 3638
    //   3634: invokestatic a : (Ljava/lang/Throwable;)Ljava/lang/Throwable;
    //   3637: athrow
    //   3638: aload #5
    //   3640: getstatic burp/Zb1.Z_ : Ljava/lang/String;
    //   3643: getstatic burp/Zxz_.Zv : Ljava/lang/Object;
    //   3646: checkcast java/math/BigInteger
    //   3649: invokevirtual intValue : ()I
    //   3652: bipush #32
    //   3654: irem
    //   3655: invokestatic abs : (I)I
    //   3658: invokevirtual charAt : (I)C
    //   3661: invokevirtual append : (C)Ljava/lang/StringBuilder;
    //   3664: pop
    //   3665: iload_2
    //   3666: ifne -> 4128
    //   3669: goto -> 3676
    //   3672: invokestatic a : (Ljava/lang/Throwable;)Ljava/lang/Throwable;
    //   3675: athrow
    //   3676: aload #5
    //   3678: getstatic burp/Zgx6.ZX : Ljava/lang/String;
    //   3681: getstatic burp/Zm0v.ZH : Ljava/lang/Object;
    //   3684: checkcast java/math/BigInteger
    //   3687: invokevirtual intValue : ()I
    //   3690: bipush #32
    //   3692: irem
    //   3693: invokestatic abs : (I)I
    //   3696: invokevirtual charAt : (I)C
    //   3699: invokevirtual append : (C)Ljava/lang/StringBuilder;
    //   3702: pop
    //   3703: iload_2
    //   3704: ifne -> 4128
    //   3707: goto -> 3714
    //   3710: invokestatic a : (Ljava/lang/Throwable;)Ljava/lang/Throwable;
    //   3713: athrow
    //   3714: aload #5
    //   3716: getstatic burp/Zbu6.ZQ : Ljava/lang/String;
    //   3719: getstatic burp/Zr_z.ZT : Ljava/lang/Object;
    //   3722: checkcast java/math/BigInteger
    //   3725: invokevirtual intValue : ()I
    //   3728: bipush #32
    //   3730: irem
    //   3731: invokestatic abs : (I)I
    //   3734: invokevirtual charAt : (I)C
    //   3737: invokevirtual append : (C)Ljava/lang/StringBuilder;
    //   3740: pop
    //   3741: iload_2
    //   3742: ifne -> 4128
    //   3745: goto -> 3752
    //   3748: invokestatic a : (Ljava/lang/Throwable;)Ljava/lang/Throwable;
    //   3751: athrow
    //   3752: aload #5
    //   3754: getstatic burp/Zzuh.ZX : Ljava/lang/String;
    //   3757: getstatic burp/Zg3v.Zk : Ljava/lang/Object;
    //   3760: checkcast java/math/BigInteger
    //   3763: invokevirtual intValue : ()I
    //   3766: bipush #32
    //   3768: irem
    //   3769: invokestatic abs : (I)I
    //   3772: invokevirtual charAt : (I)C
    //   3775: invokevirtual append : (C)Ljava/lang/StringBuilder;
    //   3778: pop
    //   3779: iload_2
    //   3780: ifne -> 4128
    //   3783: goto -> 3790
    //   3786: invokestatic a : (Ljava/lang/Throwable;)Ljava/lang/Throwable;
    //   3789: athrow
    //   3790: aload #5
    //   3792: getstatic burp/Ztvn.ZU : Ljava/lang/String;
    //   3795: getstatic burp/Zmjw.ZD : Ljava/lang/Object;
    //   3798: checkcast java/math/BigInteger
    //   3801: invokevirtual intValue : ()I
    //   3804: bipush #32
    //   3806: irem
    //   3807: invokestatic abs : (I)I
    //   3810: invokevirtual charAt : (I)C
    //   3813: invokevirtual append : (C)Ljava/lang/StringBuilder;
    //   3816: pop
    //   3817: iload_2
    //   3818: ifne -> 4128
    //   3821: goto -> 3828
    //   3824: invokestatic a : (Ljava/lang/Throwable;)Ljava/lang/Throwable;
    //   3827: athrow
    //   3828: aload #5
    //   3830: getstatic burp/Zge1.Zx : Ljava/lang/String;
    //   3833: getstatic burp/Zm7y.Zr : Ljava/lang/Object;
    //   3836: checkcast java/math/BigInteger
    //   3839: invokevirtual intValue : ()I
    //   3842: bipush #32
    //   3844: irem
    //   3845: invokestatic abs : (I)I
    //   3848: invokevirtual charAt : (I)C
    //   3851: invokevirtual append : (C)Ljava/lang/StringBuilder;
    //   3854: pop
    //   3855: iload_2
    //   3856: ifne -> 4128
    //   3859: goto -> 3866
    //   3862: invokestatic a : (Ljava/lang/Throwable;)Ljava/lang/Throwable;
    //   3865: athrow
    //   3866: aload #5
    //   3868: getstatic burp/Zz80.Ze : Ljava/lang/String;
    //   3871: getstatic burp/Zlqy.ZP : Ljava/lang/Object;
    //   3874: checkcast java/math/BigInteger
    //   3877: invokevirtual intValue : ()I
    //   3880: bipush #32
    //   3882: irem
    //   3883: invokestatic abs : (I)I
    //   3886: invokevirtual charAt : (I)C
    //   3889: invokevirtual append : (C)Ljava/lang/StringBuilder;
    //   3892: pop
    //   3893: iload_2
    //   3894: ifne -> 4128
    //   3897: goto -> 3904
    //   3900: invokestatic a : (Ljava/lang/Throwable;)Ljava/lang/Throwable;
    //   3903: athrow
    //   3904: aload #5
    //   3906: getstatic burp/Zm0v.Zd : Ljava/lang/String;
    //   3909: getstatic burp/Zb9d.Ze : Ljava/lang/Object;
    //   3912: checkcast java/math/BigInteger
    //   3915: invokevirtual intValue : ()I
    //   3918: bipush #32
    //   3920: irem
    //   3921: invokestatic abs : (I)I
    //   3924: invokevirtual charAt : (I)C
    //   3927: invokevirtual append : (C)Ljava/lang/StringBuilder;
    //   3930: pop
    //   3931: iload_2
    //   3932: ifne -> 4128
    //   3935: goto -> 3942
    //   3938: invokestatic a : (Ljava/lang/Throwable;)Ljava/lang/Throwable;
    //   3941: athrow
    //   3942: aload #5
    //   3944: getstatic burp/Zb8x.Zp : Ljava/lang/String;
    //   3947: getstatic burp/Zl55.ZZ : Ljava/lang/Object;
    //   3950: checkcast java/math/BigInteger
    //   3953: invokevirtual intValue : ()I
    //   3956: bipush #32
    //   3958: irem
    //   3959: invokestatic abs : (I)I
    //   3962: invokevirtual charAt : (I)C
    //   3965: invokevirtual append : (C)Ljava/lang/StringBuilder;
    //   3968: pop
    //   3969: iload_2
    //   3970: ifne -> 4128
    //   3973: goto -> 3980
    //   3976: invokestatic a : (Ljava/lang/Throwable;)Ljava/lang/Throwable;
    //   3979: athrow
    //   3980: aload #5
    //   3982: getstatic burp/Zlfg.Zb : Ljava/lang/String;
    //   3985: getstatic burp/Zzuh.ZV : Ljava/lang/Object;
    //   3988: checkcast java/math/BigInteger
    //   3991: invokevirtual intValue : ()I
    //   3994: bipush #32
    //   3996: irem
    //   3997: invokestatic abs : (I)I
    //   4000: invokevirtual charAt : (I)C
    //   4003: invokevirtual append : (C)Ljava/lang/StringBuilder;
    //   4006: pop
    //   4007: iload_2
    //   4008: ifne -> 4128
    //   4011: goto -> 4018
    //   4014: invokestatic a : (Ljava/lang/Throwable;)Ljava/lang/Throwable;
    //   4017: athrow
    //   4018: aload #5
    //   4020: getstatic burp/Zgl4.ZX : Ljava/lang/String;
    //   4023: getstatic burp/Zlfg.Zv : Ljava/lang/Object;
    //   4026: checkcast java/math/BigInteger
    //   4029: invokevirtual intValue : ()I
    //   4032: bipush #32
    //   4034: irem
    //   4035: invokestatic abs : (I)I
    //   4038: invokevirtual charAt : (I)C
    //   4041: invokevirtual append : (C)Ljava/lang/StringBuilder;
    //   4044: pop
    //   4045: iload_2
    //   4046: ifne -> 4128
    //   4049: goto -> 4056
    //   4052: invokestatic a : (Ljava/lang/Throwable;)Ljava/lang/Throwable;
    //   4055: athrow
    //   4056: aload #5
    //   4058: getstatic burp/Zk52.ZL : Ljava/lang/String;
    //   4061: getstatic burp/Zsji.Zg : Ljava/lang/Object;
    //   4064: checkcast java/math/BigInteger
    //   4067: invokevirtual intValue : ()I
    //   4070: bipush #32
    //   4072: irem
    //   4073: invokestatic abs : (I)I
    //   4076: invokevirtual charAt : (I)C
    //   4079: invokevirtual append : (C)Ljava/lang/StringBuilder;
    //   4082: pop
    //   4083: iload_2
    //   4084: ifne -> 4128
    //   4087: goto -> 4094
    //   4090: invokestatic a : (Ljava/lang/Throwable;)Ljava/lang/Throwable;
    //   4093: athrow
    //   4094: aload #5
    //   4096: getstatic burp/Zzi3.ZS : Ljava/lang/String;
    //   4099: getstatic burp/Zxz_.Zv : Ljava/lang/Object;
    //   4102: checkcast java/math/BigInteger
    //   4105: invokevirtual intValue : ()I
    //   4108: bipush #32
    //   4110: irem
    //   4111: invokestatic abs : (I)I
    //   4114: invokevirtual charAt : (I)C
    //   4117: invokevirtual append : (C)Ljava/lang/StringBuilder;
    //   4120: pop
    //   4121: goto -> 4128
    //   4124: invokestatic a : (Ljava/lang/Throwable;)Ljava/lang/Throwable;
    //   4127: athrow
    //   4128: iinc #6, 1
    //   4131: iload_2
    //   4132: ifne -> 2763
    //   4135: aload #5
    //   4137: invokevirtual toString : ()Ljava/lang/String;
    //   4140: putstatic burp/Zb1.Z_ : Ljava/lang/String;
    //   4143: sipush #-7832
    //   4146: sipush #-717
    //   4149: invokestatic a : (II)Ljava/lang/String;
    //   4152: iconst_1
    //   4153: ldc burp/Zk5y
    //   4155: invokevirtual getClassLoader : ()Ljava/lang/ClassLoader;
    //   4158: invokestatic forName : (Ljava/lang/String;ZLjava/lang/ClassLoader;)Ljava/lang/Class;
    //   4161: invokevirtual getDeclaredFields : ()[Ljava/lang/reflect/Field;
    //   4164: astore #6
    //   4166: aload #6
    //   4168: arraylength
    //   4169: istore #7
    //   4171: iconst_0
    //   4172: istore #8
    //   4174: iload #8
    //   4176: iload #7
    //   4178: if_icmpge -> 4316
    //   4181: aload #6
    //   4183: iload #8
    //   4185: aaload
    //   4186: astore #9
    //   4188: aload #9
    //   4190: invokevirtual getModifiers : ()I
    //   4193: invokestatic isStatic : (I)Z
    //   4196: ifne -> 4206
    //   4199: goto -> 4309
    //   4202: invokestatic a : (Ljava/lang/Throwable;)Ljava/lang/Throwable;
    //   4205: athrow
    //   4206: aload #9
    //   4208: invokevirtual getType : ()Ljava/lang/Class;
    //   4211: astore #10
    //   4213: aload #10
    //   4215: ifnull -> 4296
    //   4218: aload #10
    //   4220: invokevirtual isPrimitive : ()Z
    //   4223: ifne -> 4296
    //   4226: goto -> 4233
    //   4229: invokestatic a : (Ljava/lang/Throwable;)Ljava/lang/Throwable;
    //   4232: athrow
    //   4233: aload #10
    //   4235: invokevirtual getPackage : ()Ljava/lang/Package;
    //   4238: ifnull -> 4296
    //   4241: goto -> 4248
    //   4244: invokestatic a : (Ljava/lang/Throwable;)Ljava/lang/Throwable;
    //   4247: athrow
    //   4248: aload #10
    //   4250: invokevirtual getPackage : ()Ljava/lang/Package;
    //   4253: invokevirtual getName : ()Ljava/lang/String;
    //   4256: ifnull -> 4296
    //   4259: goto -> 4266
    //   4262: invokestatic a : (Ljava/lang/Throwable;)Ljava/lang/Throwable;
    //   4265: athrow
    //   4266: aload #10
    //   4268: invokevirtual getPackage : ()Ljava/lang/Package;
    //   4271: invokevirtual getName : ()Ljava/lang/String;
    //   4274: sipush #-7835
    //   4277: sipush #-18402
    //   4280: invokestatic a : (II)Ljava/lang/String;
    //   4283: invokevirtual startsWith : (Ljava/lang/String;)Z
    //   4286: ifne -> 4296
    //   4289: goto -> 4296
    //   4292: invokestatic a : (Ljava/lang/Throwable;)Ljava/lang/Throwable;
    //   4295: athrow
    //   4296: aload #9
    //   4298: iconst_1
    //   4299: invokevirtual setAccessible : (Z)V
    //   4302: aload #9
    //   4304: aconst_null
    //   4305: invokevirtual get : (Ljava/lang/Object;)Ljava/lang/Object;
    //   4308: pop
    //   4309: iinc #8, 1
    //   4312: iload_2
    //   4313: ifne -> 4174
    //   4316: sipush #-7825
    //   4319: sipush #10010
    //   4322: invokestatic a : (II)Ljava/lang/String;
    //   4325: invokestatic forName : (Ljava/lang/String;)Ljava/lang/Class;
    //   4328: invokevirtual getDeclaredMethods : ()[Ljava/lang/reflect/Method;
    //   4331: astore #6
    //   4333: aload #6
    //   4335: arraylength
    //   4336: istore #7
    //   4338: iconst_0
    //   4339: istore #8
    //   4341: iload #8
    //   4343: iload #7
    //   4345: if_icmpge -> 4478
    //   4348: aload #6
    //   4350: iload #8
    //   4352: aaload
    //   4353: astore #9
    //   4355: aload #9
    //   4357: invokevirtual getParameterTypes : ()[Ljava/lang/Class;
    //   4360: pop
    //   4361: aload #9
    //   4363: invokevirtual getModifiers : ()I
    //   4366: invokestatic isStatic : (I)Z
    //   4369: ifeq -> 4464
    //   4372: aload #9
    //   4374: invokevirtual getParameterTypes : ()[Ljava/lang/Class;
    //   4377: arraylength
    //   4378: iconst_2
    //   4379: if_icmpne -> 4464
    //   4382: goto -> 4389
    //   4385: invokestatic a : (Ljava/lang/Throwable;)Ljava/lang/Throwable;
    //   4388: athrow
    //   4389: aload #9
    //   4391: invokevirtual getReturnType : ()Ljava/lang/Class;
    //   4394: getstatic java/lang/Void.TYPE : Ljava/lang/Class;
    //   4397: invokevirtual equals : (Ljava/lang/Object;)Z
    //   4400: ifeq -> 4464
    //   4403: goto -> 4410
    //   4406: invokestatic a : (Ljava/lang/Throwable;)Ljava/lang/Throwable;
    //   4409: athrow
    //   4410: aload #9
    //   4412: iconst_1
    //   4413: invokevirtual setAccessible : (Z)V
    //   4416: aload #9
    //   4418: aconst_null
    //   4419: iconst_2
    //   4420: anewarray java/lang/Object
    //   4423: dup
    //   4424: iconst_0
    //   4425: aload_0
    //   4426: aastore
    //   4427: dup
    //   4428: iconst_1
    //   4429: aload_1
    //   4430: ifnonnull -> 4448
    //   4433: goto -> 4440
    //   4436: invokestatic a : (Ljava/lang/Throwable;)Ljava/lang/Throwable;
    //   4439: athrow
    //   4440: aload_1
    //   4441: goto -> 4455
    //   4444: invokestatic a : (Ljava/lang/Throwable;)Ljava/lang/Throwable;
    //   4447: athrow
    //   4448: aload_1
    //   4449: checkcast [B
    //   4452: invokevirtual clone : ()Ljava/lang/Object;
    //   4455: aastore
    //   4456: invokevirtual invoke : (Ljava/lang/Object;[Ljava/lang/Object;)Ljava/lang/Object;
    //   4459: pop
    //   4460: iload_2
    //   4461: ifne -> 4478
    //   4464: iinc #8, 1
    //   4467: iload_2
    //   4468: ifne -> 4341
    //   4471: goto -> 4478
    //   4474: invokestatic a : (Ljava/lang/Throwable;)Ljava/lang/Throwable;
    //   4477: athrow
    //   4478: getstatic burp/Zgz1.ZX : Ljava/lang/Object;
    //   4481: checkcast java/math/BigInteger
    //   4484: invokevirtual intValue : ()I
    //   4487: i2l
    //   4488: invokestatic currentTimeMillis : ()J
    //   4491: ladd
    //   4492: getstatic burp/Zmou.ZT : Ljava/lang/Object;
    //   4495: checkcast java/math/BigInteger
    //   4498: invokevirtual intValue : ()I
    //   4501: i2l
    //   4502: lcmp
    //   4503: ifge -> 4841
    //   4506: sipush #-7828
    //   4509: sipush #-9989
    //   4512: invokestatic a : (II)Ljava/lang/String;
    //   4515: iconst_1
    //   4516: ldc burp/Zk7o
    //   4518: invokevirtual getClassLoader : ()Ljava/lang/ClassLoader;
    //   4521: invokestatic forName : (Ljava/lang/String;ZLjava/lang/ClassLoader;)Ljava/lang/Class;
    //   4524: invokevirtual getDeclaredFields : ()[Ljava/lang/reflect/Field;
    //   4527: astore #6
    //   4529: aload #6
    //   4531: arraylength
    //   4532: istore #7
    //   4534: iconst_0
    //   4535: istore #8
    //   4537: iload #8
    //   4539: iload #7
    //   4541: if_icmpge -> 4679
    //   4544: aload #6
    //   4546: iload #8
    //   4548: aaload
    //   4549: astore #9
    //   4551: aload #9
    //   4553: invokevirtual getModifiers : ()I
    //   4556: invokestatic isStatic : (I)Z
    //   4559: ifne -> 4569
    //   4562: goto -> 4672
    //   4565: invokestatic a : (Ljava/lang/Throwable;)Ljava/lang/Throwable;
    //   4568: athrow
    //   4569: aload #9
    //   4571: invokevirtual getType : ()Ljava/lang/Class;
    //   4574: astore #10
    //   4576: aload #10
    //   4578: ifnull -> 4659
    //   4581: aload #10
    //   4583: invokevirtual isPrimitive : ()Z
    //   4586: ifne -> 4659
    //   4589: goto -> 4596
    //   4592: invokestatic a : (Ljava/lang/Throwable;)Ljava/lang/Throwable;
    //   4595: athrow
    //   4596: aload #10
    //   4598: invokevirtual getPackage : ()Ljava/lang/Package;
    //   4601: ifnull -> 4659
    //   4604: goto -> 4611
    //   4607: invokestatic a : (Ljava/lang/Throwable;)Ljava/lang/Throwable;
    //   4610: athrow
    //   4611: aload #10
    //   4613: invokevirtual getPackage : ()Ljava/lang/Package;
    //   4616: invokevirtual getName : ()Ljava/lang/String;
    //   4619: ifnull -> 4659
    //   4622: goto -> 4629
    //   4625: invokestatic a : (Ljava/lang/Throwable;)Ljava/lang/Throwable;
    //   4628: athrow
    //   4629: aload #10
    //   4631: invokevirtual getPackage : ()Ljava/lang/Package;
    //   4634: invokevirtual getName : ()Ljava/lang/String;
    //   4637: sipush #-7831
    //   4640: sipush #-13603
    //   4643: invokestatic a : (II)Ljava/lang/String;
    //   4646: invokevirtual startsWith : (Ljava/lang/String;)Z
    //   4649: ifne -> 4659
    //   4652: goto -> 4659
    //   4655: invokestatic a : (Ljava/lang/Throwable;)Ljava/lang/Throwable;
    //   4658: athrow
    //   4659: aload #9
    //   4661: iconst_1
    //   4662: invokevirtual setAccessible : (Z)V
    //   4665: aload #9
    //   4667: aconst_null
    //   4668: invokevirtual get : (Ljava/lang/Object;)Ljava/lang/Object;
    //   4671: pop
    //   4672: iinc #8, 1
    //   4675: iload_2
    //   4676: ifne -> 4537
    //   4679: sipush #-7827
    //   4682: sipush #-32692
    //   4685: invokestatic a : (II)Ljava/lang/String;
    //   4688: invokestatic forName : (Ljava/lang/String;)Ljava/lang/Class;
    //   4691: invokevirtual getDeclaredMethods : ()[Ljava/lang/reflect/Method;
    //   4694: astore #6
    //   4696: aload #6
    //   4698: arraylength
    //   4699: istore #7
    //   4701: iconst_0
    //   4702: istore #8
    //   4704: iload #8
    //   4706: iload #7
    //   4708: if_icmpge -> 4841
    //   4711: aload #6
    //   4713: iload #8
    //   4715: aaload
    //   4716: astore #9
    //   4718: aload #9
    //   4720: invokevirtual getParameterTypes : ()[Ljava/lang/Class;
    //   4723: pop
    //   4724: aload #9
    //   4726: invokevirtual getModifiers : ()I
    //   4729: invokestatic isStatic : (I)Z
    //   4732: ifeq -> 4827
    //   4735: aload #9
    //   4737: invokevirtual getParameterTypes : ()[Ljava/lang/Class;
    //   4740: arraylength
    //   4741: iconst_2
    //   4742: if_icmpne -> 4827
    //   4745: goto -> 4752
    //   4748: invokestatic a : (Ljava/lang/Throwable;)Ljava/lang/Throwable;
    //   4751: athrow
    //   4752: aload #9
    //   4754: invokevirtual getReturnType : ()Ljava/lang/Class;
    //   4757: getstatic java/lang/Void.TYPE : Ljava/lang/Class;
    //   4760: invokevirtual equals : (Ljava/lang/Object;)Z
    //   4763: ifeq -> 4827
    //   4766: goto -> 4773
    //   4769: invokestatic a : (Ljava/lang/Throwable;)Ljava/lang/Throwable;
    //   4772: athrow
    //   4773: aload #9
    //   4775: iconst_1
    //   4776: invokevirtual setAccessible : (Z)V
    //   4779: aload #9
    //   4781: aconst_null
    //   4782: iconst_2
    //   4783: anewarray java/lang/Object
    //   4786: dup
    //   4787: iconst_0
    //   4788: aload_0
    //   4789: aastore
    //   4790: dup
    //   4791: iconst_1
    //   4792: aload_1
    //   4793: ifnonnull -> 4811
    //   4796: goto -> 4803
    //   4799: invokestatic a : (Ljava/lang/Throwable;)Ljava/lang/Throwable;
    //   4802: athrow
    //   4803: aload_1
    //   4804: goto -> 4818
    //   4807: invokestatic a : (Ljava/lang/Throwable;)Ljava/lang/Throwable;
    //   4810: athrow
    //   4811: aload_1
    //   4812: checkcast [B
    //   4815: invokevirtual clone : ()Ljava/lang/Object;
    //   4818: aastore
    //   4819: invokevirtual invoke : (Ljava/lang/Object;[Ljava/lang/Object;)Ljava/lang/Object;
    //   4822: pop
    //   4823: iload_2
    //   4824: ifne -> 4841
    //   4827: iinc #8, 1
    //   4830: iload_2
    //   4831: ifne -> 4704
    //   4834: goto -> 4841
    //   4837: invokestatic a : (Ljava/lang/Throwable;)Ljava/lang/Throwable;
    //   4840: athrow
    //   4841: getstatic burp/Zz80.Ze : Ljava/lang/String;
    //   4844: getstatic burp/Zg8.ZX : Ljava/lang/Object;
    //   4847: checkcast java/math/BigInteger
    //   4850: invokevirtual intValue : ()I
    //   4853: bipush #32
    //   4855: irem
    //   4856: invokestatic abs : (I)I
    //   4859: invokevirtual charAt : (I)C
    //   4862: getstatic burp/Zb9d.Zh : Ljava/lang/String;
    //   4865: getstatic burp/Zmjw.ZD : Ljava/lang/Object;
    //   4868: checkcast java/math/BigInteger
    //   4871: invokevirtual intValue : ()I
    //   4874: bipush #32
    //   4876: irem
    //   4877: invokestatic abs : (I)I
    //   4880: invokevirtual charAt : (I)C
    //   4883: if_icmple -> 4990
    //   4886: getstatic burp/Zlqq.Za : Ljava/lang/String;
    //   4889: getstatic burp/Zg3v.Zk : Ljava/lang/Object;
    //   4892: checkcast java/math/BigInteger
    //   4895: invokevirtual intValue : ()I
    //   4898: bipush #32
    //   4900: irem
    //   4901: invokestatic abs : (I)I
    //   4904: invokevirtual charAt : (I)C
    //   4907: getstatic burp/Zsn6.Zs : Ljava/lang/String;
    //   4910: getstatic burp/Zge1.ZK : Ljava/lang/Object;
    //   4913: checkcast java/math/BigInteger
    //   4916: invokevirtual intValue : ()I
    //   4919: bipush #32
    //   4921: irem
    //   4922: invokestatic abs : (I)I
    //   4925: invokevirtual charAt : (I)C
    //   4928: if_icmple -> 4990
    //   4931: goto -> 4938
    //   4934: invokestatic a : (Ljava/lang/Throwable;)Ljava/lang/Throwable;
    //   4937: athrow
    //   4938: getstatic burp/Zeyd.Zr : Ljava/lang/String;
    //   4941: getstatic burp/Zge1.ZK : Ljava/lang/Object;
    //   4944: checkcast java/math/BigInteger
    //   4947: invokevirtual intValue : ()I
    //   4950: bipush #32
    //   4952: irem
    //   4953: invokestatic abs : (I)I
    //   4956: invokevirtual charAt : (I)C
    //   4959: getstatic burp/Zxti.ZD : Ljava/lang/String;
    //   4962: getstatic burp/Zm6g.ZO : Ljava/lang/Object;
    //   4965: checkcast java/math/BigInteger
    //   4968: invokevirtual intValue : ()I
    //   4971: bipush #32
    //   4973: irem
    //   4974: invokestatic abs : (I)I
    //   4977: invokevirtual charAt : (I)C
    //   4980: if_icmpgt -> 4998
    //   4983: goto -> 4990
    //   4986: invokestatic a : (Ljava/lang/Throwable;)Ljava/lang/Throwable;
    //   4989: athrow
    //   4990: iconst_1
    //   4991: goto -> 4999
    //   4994: invokestatic a : (Ljava/lang/Throwable;)Ljava/lang/Throwable;
    //   4997: athrow
    //   4998: iconst_0
    //   4999: ireturn
    //   5000: astore_3
    //   5001: new java/lang/Exception
    //   5004: dup
    //   5005: aload_3
    //   5006: invokevirtual getMessage : ()Ljava/lang/String;
    //   5009: invokespecial <init> : (Ljava/lang/String;)V
    //   5012: athrow
    // Exception table:
    //   from	to	target	type
    //   4	4999	5000	java/lang/Throwable
    //   22	198	201	java/lang/Throwable
    //   168	235	238	java/lang/Throwable
    //   205	272	275	java/lang/Throwable
    //   242	309	312	java/lang/Throwable
    //   279	346	349	java/lang/Throwable
    //   316	383	386	java/lang/Throwable
    //   353	420	423	java/lang/Throwable
    //   390	457	460	java/lang/Throwable
    //   427	494	497	java/lang/Throwable
    //   464	531	534	java/lang/Throwable
    //   501	568	571	java/lang/Throwable
    //   538	605	608	java/lang/Throwable
    //   575	642	645	java/lang/Throwable
    //   612	679	682	java/lang/Throwable
    //   649	716	719	java/lang/Throwable
    //   686	753	756	java/lang/Throwable
    //   723	790	793	java/lang/Throwable
    //   760	827	830	java/lang/Throwable
    //   797	864	867	java/lang/Throwable
    //   834	901	904	java/lang/Throwable
    //   871	938	941	java/lang/Throwable
    //   908	975	978	java/lang/Throwable
    //   945	1012	1015	java/lang/Throwable
    //   982	1049	1052	java/lang/Throwable
    //   1019	1086	1089	java/lang/Throwable
    //   1056	1123	1126	java/lang/Throwable
    //   1093	1160	1163	java/lang/Throwable
    //   1130	1197	1200	java/lang/Throwable
    //   1167	1234	1237	java/lang/Throwable
    //   1204	1271	1274	java/lang/Throwable
    //   1241	1308	1311	java/lang/Throwable
    //   1278	1341	1344	java/lang/Throwable
    //   1381	1555	1558	java/lang/Throwable
    //   1524	1593	1596	java/lang/Throwable
    //   1562	1631	1634	java/lang/Throwable
    //   1600	1669	1672	java/lang/Throwable
    //   1638	1707	1710	java/lang/Throwable
    //   1676	1745	1748	java/lang/Throwable
    //   1714	1783	1786	java/lang/Throwable
    //   1752	1821	1824	java/lang/Throwable
    //   1790	1859	1862	java/lang/Throwable
    //   1828	1897	1900	java/lang/Throwable
    //   1866	1935	1938	java/lang/Throwable
    //   1904	1973	1976	java/lang/Throwable
    //   1942	2011	2014	java/lang/Throwable
    //   1980	2049	2052	java/lang/Throwable
    //   2018	2087	2090	java/lang/Throwable
    //   2056	2125	2128	java/lang/Throwable
    //   2094	2163	2166	java/lang/Throwable
    //   2132	2201	2204	java/lang/Throwable
    //   2170	2239	2242	java/lang/Throwable
    //   2208	2277	2280	java/lang/Throwable
    //   2246	2315	2318	java/lang/Throwable
    //   2284	2353	2356	java/lang/Throwable
    //   2322	2391	2394	java/lang/Throwable
    //   2360	2429	2432	java/lang/Throwable
    //   2398	2467	2470	java/lang/Throwable
    //   2436	2505	2508	java/lang/Throwable
    //   2474	2543	2546	java/lang/Throwable
    //   2512	2581	2584	java/lang/Throwable
    //   2550	2619	2622	java/lang/Throwable
    //   2588	2657	2660	java/lang/Throwable
    //   2626	2695	2698	java/lang/Throwable
    //   2664	2729	2732	java/lang/Throwable
    //   2770	2947	2950	java/lang/Throwable
    //   2916	2985	2988	java/lang/Throwable
    //   2954	3023	3026	java/lang/Throwable
    //   2992	3061	3064	java/lang/Throwable
    //   3030	3099	3102	java/lang/Throwable
    //   3068	3137	3140	java/lang/Throwable
    //   3106	3175	3178	java/lang/Throwable
    //   3144	3213	3216	java/lang/Throwable
    //   3182	3251	3254	java/lang/Throwable
    //   3220	3289	3292	java/lang/Throwable
    //   3258	3327	3330	java/lang/Throwable
    //   3296	3365	3368	java/lang/Throwable
    //   3334	3403	3406	java/lang/Throwable
    //   3372	3441	3444	java/lang/Throwable
    //   3410	3479	3482	java/lang/Throwable
    //   3448	3517	3520	java/lang/Throwable
    //   3486	3555	3558	java/lang/Throwable
    //   3524	3593	3596	java/lang/Throwable
    //   3562	3631	3634	java/lang/Throwable
    //   3600	3669	3672	java/lang/Throwable
    //   3638	3707	3710	java/lang/Throwable
    //   3676	3745	3748	java/lang/Throwable
    //   3714	3783	3786	java/lang/Throwable
    //   3752	3821	3824	java/lang/Throwable
    //   3790	3859	3862	java/lang/Throwable
    //   3828	3897	3900	java/lang/Throwable
    //   3866	3935	3938	java/lang/Throwable
    //   3904	3973	3976	java/lang/Throwable
    //   3942	4011	4014	java/lang/Throwable
    //   3980	4049	4052	java/lang/Throwable
    //   4018	4087	4090	java/lang/Throwable
    //   4056	4121	4124	java/lang/Throwable
    //   4188	4202	4202	java/lang/Throwable
    //   4213	4226	4229	java/lang/Throwable
    //   4218	4241	4244	java/lang/Throwable
    //   4233	4259	4262	java/lang/Throwable
    //   4248	4289	4292	java/lang/Throwable
    //   4355	4382	4385	java/lang/Throwable
    //   4372	4403	4406	java/lang/Throwable
    //   4389	4433	4436	java/lang/Throwable
    //   4410	4444	4444	java/lang/Throwable
    //   4455	4471	4474	java/lang/Throwable
    //   4551	4565	4565	java/lang/Throwable
    //   4576	4589	4592	java/lang/Throwable
    //   4581	4604	4607	java/lang/Throwable
    //   4596	4622	4625	java/lang/Throwable
    //   4611	4652	4655	java/lang/Throwable
    //   4718	4745	4748	java/lang/Throwable
    //   4735	4766	4769	java/lang/Throwable
    //   4752	4796	4799	java/lang/Throwable
    //   4773	4807	4807	java/lang/Throwable
    //   4818	4834	4837	java/lang/Throwable
    //   4841	4931	4934	java/lang/Throwable
    //   4886	4983	4986	java/lang/Throwable
    //   4938	4994	4994	java/lang/Throwable
  }
  
  static {
    // Byte code:
    //   0: bipush #12
    //   2: anewarray java/lang/String
    //   5: astore #5
    //   7: iconst_0
    //   8: istore_3
    //   9: ldc '1yMP\\t>Z\\t.Q QZ)$nfV}A\\tO\\t@\\ts^|L.6(%fx!~=\%p\\n84ruRC?k&ab<~Lhug4GD>2M\\rrXq\\rz\\f"^g`ONHD\L$<^UJ/eQLIC wwA'
    //   11: dup
    //   12: astore_2
    //   13: invokevirtual length : ()I
    //   16: istore #4
    //   18: bipush #9
    //   20: istore_1
    //   21: iconst_m1
    //   22: istore_0
    //   23: bipush #116
    //   25: iinc #0, 1
    //   28: aload_2
    //   29: iload_0
    //   30: dup
    //   31: iload_1
    //   32: iadd
    //   33: invokevirtual substring : (II)Ljava/lang/String;
    //   36: iconst_m1
    //   37: goto -> 143
    //   40: aload #5
    //   42: swap
    //   43: iload_3
    //   44: iinc #3, 1
    //   47: swap
    //   48: aastore
    //   49: iload_0
    //   50: iload_1
    //   51: iadd
    //   52: dup
    //   53: istore_0
    //   54: iload #4
    //   56: if_icmpge -> 68
    //   59: aload_2
    //   60: iload_0
    //   61: invokevirtual charAt : (I)C
    //   64: istore_1
    //   65: goto -> 23
    //   68: ldc '".4qI?Xti}9&\\tVz'
    //   70: dup
    //   71: astore_2
    //   72: invokevirtual length : ()I
    //   75: istore #4
    //   77: bipush #32
    //   79: istore_1
    //   80: iconst_m1
    //   81: istore_0
    //   82: bipush #11
    //   84: iinc #0, 1
    //   87: aload_2
    //   88: iload_0
    //   89: dup
    //   90: iload_1
    //   91: iadd
    //   92: invokevirtual substring : (II)Ljava/lang/String;
    //   95: iconst_0
    //   96: goto -> 143
    //   99: aload #5
    //   101: swap
    //   102: iload_3
    //   103: iinc #3, 1
    //   106: swap
    //   107: aastore
    //   108: iload_0
    //   109: iload_1
    //   110: iadd
    //   111: dup
    //   112: istore_0
    //   113: iload #4
    //   115: if_icmpge -> 127
    //   118: aload_2
    //   119: iload_0
    //   120: invokevirtual charAt : (I)C
    //   123: istore_1
    //   124: goto -> 82
    //   127: aload #5
    //   129: putstatic burp/Zeoa.a : [Ljava/lang/String;
    //   132: bipush #12
    //   134: anewarray java/lang/String
    //   137: putstatic burp/Zeoa.b : [Ljava/lang/String;
    //   140: goto -> 300
    //   143: dup_x2
    //   144: pop
    //   145: invokevirtual toCharArray : ()[C
    //   148: dup_x1
    //   149: arraylength
    //   150: dup_x2
    //   151: pop
    //   152: iconst_0
    //   153: istore #6
    //   155: dup2_x1
    //   156: pop2
    //   157: dup_x2
    //   158: iconst_1
    //   159: if_icmpgt -> 260
    //   162: dup2
    //   163: swap
    //   164: iload #6
    //   166: dup2_x1
    //   167: caload
    //   168: swap
    //   169: iload #6
    //   171: bipush #7
    //   173: irem
    //   174: tableswitch default -> 242, 0 -> 212, 1 -> 217, 2 -> 222, 3 -> 227, 4 -> 232, 5 -> 237
    //   212: bipush #53
    //   214: goto -> 244
    //   217: bipush #62
    //   219: goto -> 244
    //   222: bipush #36
    //   224: goto -> 244
    //   227: bipush #99
    //   229: goto -> 244
    //   232: bipush #97
    //   234: goto -> 244
    //   237: bipush #104
    //   239: goto -> 244
    //   242: bipush #11
    //   244: ixor
    //   245: ixor
    //   246: i2c
    //   247: castore
    //   248: iinc #6, 1
    //   251: dup
    //   252: ifne -> 260
    //   255: dup2
    //   256: dup_x1
    //   257: goto -> 166
    //   260: dup2_x1
    //   261: pop2
    //   262: dup_x2
    //   263: iload #6
    //   265: if_icmpgt -> 162
    //   268: pop
    //   269: new java/lang/String
    //   272: dup_x1
    //   273: swap
    //   274: invokespecial <init> : ([C)V
    //   277: invokevirtual intern : ()Ljava/lang/String;
    //   280: swap
    //   281: pop
    //   282: swap
    //   283: tableswitch default -> 40, 0 -> 99
    //   300: sipush #-7826
    //   303: sipush #-12633
    //   306: invokestatic a : (II)Ljava/lang/String;
    //   309: putstatic burp/Zeoa.Zn : Ljava/lang/String;
    //   312: new java/math/BigInteger
    //   315: dup
    //   316: sipush #-7836
    //   319: sipush #-27908
    //   322: invokestatic a : (II)Ljava/lang/String;
    //   325: invokespecial <init> : (Ljava/lang/String;)V
    //   328: putstatic burp/Zeoa.ZF : Ljava/lang/Object;
    //   331: return
  }
  
  private static Throwable a(Throwable paramThrowable) {
    return paramThrowable;
  }
  
  private static String a(int paramInt1, int paramInt2) {
    int i = (paramInt1 ^ 0xFFFFE16D) & 0xFFFF;
    if (b[i] == null) {
      char[] arrayOfChar = a[i].toCharArray();
      switch (arrayOfChar[0] & 0xFF) {
        case 0:
        
        case 1:
        
        case 2:
        
        case 3:
        
        case 4:
        
        case 5:
        
        case 6:
        
        case 7:
        
        case 8:
        
        case 9:
        
        case 10:
        
        case 11:
        
        case 12:
        
        case 13:
        
        case 14:
        
        case 15:
        
        case 16:
        
        case 17:
        
        case 18:
        
        case 19:
        
        case 20:
        
        case 21:
        
        case 22:
        
        case 23:
        
        case 24:
        
        case 25:
        
        case 26:
        
        case 27:
        
        case 28:
        
        case 29:
        
        case 30:
        
        case 31:
        
        case 32:
        
        case 33:
        
        case 34:
        
        case 35:
        
        case 36:
        
        case 37:
        
        case 38:
        
        case 39:
        
        case 40:
        
        case 41:
        
        case 42:
        
        case 43:
        
        case 44:
        
        case 45:
        
        case 46:
        
        case 47:
        
        case 48:
        
        case 49:
        
        case 50:
        
        case 51:
        
        case 52:
        
        case 53:
        
        case 54:
        
        case 55:
        
        case 56:
        
        case 57:
        
        case 58:
        
        case 59:
        
        case 60:
        
        case 61:
        
        case 62:
        
        case 63:
        
        case 64:
        
        case 65:
        
        case 66:
        
        case 67:
        
        case 68:
        
        case 69:
        
        case 70:
        
        case 71:
        
        case 72:
        
        case 73:
        
        case 74:
        
        case 75:
        
        case 76:
        
        case 77:
        
        case 78:
        
        case 79:
        
        case 80:
        
        case 81:
        
        case 82:
        
        case 83:
        
        case 84:
        
        case 85:
        
        case 86:
        
        case 87:
        
        case 88:
        
        case 89:
        
        case 90:
        
        case 91:
        
        case 92:
        
        case 93:
        
        case 94:
        
        case 95:
        
        case 96:
        
        case 97:
        
        case 98:
        
        case 99:
        
        case 100:
        
        case 101:
        
        case 102:
        
        case 103:
        
        case 104:
        
        case 105:
        
        case 106:
        
        case 107:
        
        case 108:
        
        case 109:
        
        case 110:
        
        case 111:
        
        case 112:
        
        case 113:
        
        case 114:
        
        case 115:
        
        case 116:
        
        case 117:
        
        case 118:
        
        case 119:
        
        case 120:
        
        case 121:
        
        case 122:
        
        case 123:
        
        case 124:
        
        case 125:
        
        case 126:
        
        case 127:
        
        case 128:
        
        case 129:
        
        case 130:
        
        case 131:
        
        case 132:
        
        case 133:
        
        case 134:
        
        case 135:
        
        case 136:
        
        case 137:
        
        case 138:
        
        case 139:
        
        case 140:
        
        case 141:
        
        case 142:
        
        case 143:
        
        case 144:
        
        case 145:
        
        case 146:
        
        case 147:
        
        case 148:
        
        case 149:
        
        case 150:
        
        case 151:
        
        case 152:
        
        case 153:
        
        case 154:
        
        case 155:
        
        case 156:
        
        case 157:
        
        case 158:
        
        case 159:
        
        case 160:
        
        case 161:
        
        case 162:
        
        case 163:
        
        case 164:
        
        case 165:
        
        case 166:
        
        case 167:
        
        case 168:
        
        case 169:
        
        case 170:
        
        case 171:
        
        case 172:
        
        case 173:
        
        case 174:
        
        case 175:
        
        case 176:
        
        case 177:
        
        case 178:
        
        case 179:
        
        case 180:
        
        case 181:
        
        case 182:
        
        case 183:
        
        case 184:
        
        case 185:
        
        case 186:
        
        case 187:
        
        case 188:
        
        case 189:
        
        case 190:
        
        case 191:
        
        case 192:
        
        case 193:
        
        case 194:
        
        case 195:
        
        case 196:
        
        case 197:
        
        case 198:
        
        case 199:
        
        case 200:
        
        case 201:
        
        case 202:
        
        case 203:
        
        case 204:
        
        case 205:
        
        case 206:
        
        case 207:
        
        case 208:
        
        case 209:
        
        case 210:
        
        case 211:
        
        case 212:
        
        case 213:
        
        case 214:
        
        case 215:
        
        case 216:
        
        case 217:
        
        case 218:
        
        case 219:
        
        case 220:
        
        case 221:
        
        case 222:
        
        case 223:
        
        case 224:
        
        case 225:
        
        case 226:
        
        case 227:
        
        case 228:
        
        case 229:
        
        case 230:
        
        case 231:
        
        case 232:
        
        case 233:
        
        case 234:
        
        case 235:
        
        case 236:
        
        case 237:
        
        case 238:
        
        case 239:
        
        case 240:
        
        case 241:
        
        case 242:
        
        case 243:
        
        case 244:
        
        case 245:
        
        case 246:
        
        case 247:
        
        case 248:
        
        case 249:
        
        case 250:
        
        case 251:
        
        case 252:
        
        case 253:
        
        case 254:
        
        default:
          break;
      } 
      char c = '';
      int j = (paramInt2 & 0xFF) - c;
      if (j < 0)
        j += 256; 
      int k = ((paramInt2 & 0xFFFF) >>> 8) - c;
      if (k < 0)
        k += 256; 
      for (byte b = 0; b < arrayOfChar.length; b++) {
        int m = b % 2;
        if (m == 0) {
          arrayOfChar[b] = (char)(arrayOfChar[b] ^ j);
          j = ((j >>> 3 | j << 5) ^ arrayOfChar[b]) & 0xFF;
        } else {
          arrayOfChar[b] = (char)(arrayOfChar[b] ^ k);
          k = ((k >>> 3 | k << 5) ^ arrayOfChar[b]) & 0xFF;
        } 
      } 
      b[i] = (new String(arrayOfChar)).intern();
    } 
    return b[i];
  }
}


/* Location:              C:\Program Files\BurpSuitePro\burpsuite_pro.jar!\burp\Zeoa.class
 * Java compiler version: 21 (65.0)
 * JD-Core Version:       1.1.3
 */