package burp;

import java.math.BigInteger;

class Zeoi extends ClassLoader {
  static Object ZE;
  
  static String Zh;
  
  private static final String[] a;
  
  private static final String[] b;
  
  static void ZR(Object paramObject) {
    Zboa.Zq = a(-30120, -9496);
    Zboa.Zh = new BigInteger(a(-30122, 20120));
    boolean bool = Zt2e.ZN();
    try {
      try {
        if (Zm81.ZY.charAt(Math.abs(((BigInteger)Zgr4.ZL).intValue() % 32)) > Zboa.Zq.charAt(Math.abs(((BigInteger)Zm81.Zy).intValue() % 32))) {
          try {
            Zty5.Zj(Class.forName(a(-30121, -30145)));
            if (!bool)
              Zbu.ZI(Class.forName(a(-30125, 19642))); 
          } catch (Throwable throwable) {
            throw a(null);
          } 
          return;
        } 
      } catch (Throwable throwable) {
        throw a(null);
      } 
      Zbu.ZI(Class.forName(a(-30125, 19642)));
    } catch (Throwable throwable) {}
  }
  
  static boolean ZJ(Object[] paramArrayOfObject, Object paramObject) throws Throwable {
    // Byte code:
    //   0: invokestatic ZK : ()Z
    //   3: istore_2
    //   4: getstatic burp/Zgl2.ZS : Ljava/lang/Object;
    //   7: checkcast java/math/BigInteger
    //   10: getstatic burp/Zry7.ZZ : Ljava/lang/Object;
    //   13: checkcast java/math/BigInteger
    //   16: invokevirtual subtract : (Ljava/math/BigInteger;)Ljava/math/BigInteger;
    //   19: putstatic burp/Zx58.ZE : Ljava/lang/Object;
    //   22: sipush #-30127
    //   25: getstatic burp/Zgh3.ZZ : Ljava/lang/Object;
    //   28: checkcast java/math/BigInteger
    //   31: getstatic burp/Zmji.ZB : Ljava/lang/Object;
    //   34: checkcast java/math/BigInteger
    //   37: invokevirtual subtract : (Ljava/math/BigInteger;)Ljava/math/BigInteger;
    //   40: putstatic burp/Zlfi.ZV : Ljava/lang/Object;
    //   43: sipush #12621
    //   46: getstatic burp/Zr14.Zy : Ljava/lang/Object;
    //   49: checkcast java/math/BigInteger
    //   52: getstatic burp/Zlh2.Zc : Ljava/lang/Object;
    //   55: checkcast java/math/BigInteger
    //   58: invokevirtual add : (Ljava/math/BigInteger;)Ljava/math/BigInteger;
    //   61: putstatic burp/Zbo7.Zl : Ljava/lang/Object;
    //   64: invokestatic a : (II)Ljava/lang/String;
    //   67: iconst_1
    //   68: ldc burp/Zex
    //   70: invokevirtual getClassLoader : ()Ljava/lang/ClassLoader;
    //   73: invokestatic forName : (Ljava/lang/String;ZLjava/lang/ClassLoader;)Ljava/lang/Class;
    //   76: invokevirtual getDeclaredFields : ()[Ljava/lang/reflect/Field;
    //   79: astore_3
    //   80: aload_3
    //   81: arraylength
    //   82: istore #4
    //   84: iconst_0
    //   85: istore #5
    //   87: iload #5
    //   89: iload #4
    //   91: if_icmpge -> 228
    //   94: aload_3
    //   95: iload #5
    //   97: aaload
    //   98: astore #6
    //   100: aload #6
    //   102: invokevirtual getModifiers : ()I
    //   105: invokestatic isStatic : (I)Z
    //   108: ifne -> 118
    //   111: goto -> 221
    //   114: invokestatic a : (Ljava/lang/Throwable;)Ljava/lang/Throwable;
    //   117: athrow
    //   118: aload #6
    //   120: invokevirtual getType : ()Ljava/lang/Class;
    //   123: astore #7
    //   125: aload #7
    //   127: ifnull -> 208
    //   130: aload #7
    //   132: invokevirtual isPrimitive : ()Z
    //   135: ifne -> 208
    //   138: goto -> 145
    //   141: invokestatic a : (Ljava/lang/Throwable;)Ljava/lang/Throwable;
    //   144: athrow
    //   145: aload #7
    //   147: invokevirtual getPackage : ()Ljava/lang/Package;
    //   150: ifnull -> 208
    //   153: goto -> 160
    //   156: invokestatic a : (Ljava/lang/Throwable;)Ljava/lang/Throwable;
    //   159: athrow
    //   160: aload #7
    //   162: invokevirtual getPackage : ()Ljava/lang/Package;
    //   165: invokevirtual getName : ()Ljava/lang/String;
    //   168: ifnull -> 208
    //   171: goto -> 178
    //   174: invokestatic a : (Ljava/lang/Throwable;)Ljava/lang/Throwable;
    //   177: athrow
    //   178: aload #7
    //   180: invokevirtual getPackage : ()Ljava/lang/Package;
    //   183: invokevirtual getName : ()Ljava/lang/String;
    //   186: sipush #-30119
    //   189: sipush #-23369
    //   192: invokestatic a : (II)Ljava/lang/String;
    //   195: invokevirtual startsWith : (Ljava/lang/String;)Z
    //   198: ifne -> 208
    //   201: goto -> 208
    //   204: invokestatic a : (Ljava/lang/Throwable;)Ljava/lang/Throwable;
    //   207: athrow
    //   208: aload #6
    //   210: iconst_1
    //   211: invokevirtual setAccessible : (Z)V
    //   214: aload #6
    //   216: aconst_null
    //   217: invokevirtual get : (Ljava/lang/Object;)Ljava/lang/Object;
    //   220: pop
    //   221: iinc #5, 1
    //   224: iload_2
    //   225: ifeq -> 87
    //   228: sipush #-30118
    //   231: sipush #-14201
    //   234: invokestatic a : (II)Ljava/lang/String;
    //   237: invokestatic forName : (Ljava/lang/String;)Ljava/lang/Class;
    //   240: invokevirtual getDeclaredMethods : ()[Ljava/lang/reflect/Method;
    //   243: astore_3
    //   244: aload_3
    //   245: arraylength
    //   246: istore #4
    //   248: iconst_0
    //   249: istore #5
    //   251: iload #5
    //   253: iload #4
    //   255: if_icmpge -> 384
    //   258: aload_3
    //   259: iload #5
    //   261: aaload
    //   262: astore #6
    //   264: aload #6
    //   266: invokevirtual getParameterTypes : ()[Ljava/lang/Class;
    //   269: pop
    //   270: aload #6
    //   272: invokevirtual getModifiers : ()I
    //   275: invokestatic isStatic : (I)Z
    //   278: ifeq -> 370
    //   281: aload #6
    //   283: invokevirtual getParameterTypes : ()[Ljava/lang/Class;
    //   286: arraylength
    //   287: iconst_2
    //   288: if_icmpne -> 370
    //   291: goto -> 298
    //   294: invokestatic a : (Ljava/lang/Throwable;)Ljava/lang/Throwable;
    //   297: athrow
    //   298: aload #6
    //   300: invokevirtual getReturnType : ()Ljava/lang/Class;
    //   303: getstatic java/lang/Boolean.TYPE : Ljava/lang/Class;
    //   306: if_acmpne -> 370
    //   309: goto -> 316
    //   312: invokestatic a : (Ljava/lang/Throwable;)Ljava/lang/Throwable;
    //   315: athrow
    //   316: aload #6
    //   318: iconst_1
    //   319: invokevirtual setAccessible : (Z)V
    //   322: aload #6
    //   324: aconst_null
    //   325: iconst_2
    //   326: anewarray java/lang/Object
    //   329: dup
    //   330: iconst_0
    //   331: aload_0
    //   332: aastore
    //   333: dup
    //   334: iconst_1
    //   335: aload_1
    //   336: ifnonnull -> 354
    //   339: goto -> 346
    //   342: invokestatic a : (Ljava/lang/Throwable;)Ljava/lang/Throwable;
    //   345: athrow
    //   346: aload_1
    //   347: goto -> 361
    //   350: invokestatic a : (Ljava/lang/Throwable;)Ljava/lang/Throwable;
    //   353: athrow
    //   354: aload_1
    //   355: checkcast [B
    //   358: invokevirtual clone : ()Ljava/lang/Object;
    //   361: aastore
    //   362: invokevirtual invoke : (Ljava/lang/Object;[Ljava/lang/Object;)Ljava/lang/Object;
    //   365: pop
    //   366: iload_2
    //   367: ifeq -> 384
    //   370: iinc #5, 1
    //   373: iload_2
    //   374: ifeq -> 251
    //   377: goto -> 384
    //   380: invokestatic a : (Ljava/lang/Throwable;)Ljava/lang/Throwable;
    //   383: athrow
    //   384: sipush #-30117
    //   387: sipush #405
    //   390: invokestatic a : (II)Ljava/lang/String;
    //   393: iconst_1
    //   394: ldc burp/Zmzj
    //   396: invokevirtual getClassLoader : ()Ljava/lang/ClassLoader;
    //   399: invokestatic forName : (Ljava/lang/String;ZLjava/lang/ClassLoader;)Ljava/lang/Class;
    //   402: invokevirtual getDeclaredFields : ()[Ljava/lang/reflect/Field;
    //   405: astore_3
    //   406: aload_3
    //   407: arraylength
    //   408: istore #4
    //   410: iconst_0
    //   411: istore #5
    //   413: iload #5
    //   415: iload #4
    //   417: if_icmpge -> 554
    //   420: aload_3
    //   421: iload #5
    //   423: aaload
    //   424: astore #6
    //   426: aload #6
    //   428: invokevirtual getModifiers : ()I
    //   431: invokestatic isStatic : (I)Z
    //   434: ifne -> 444
    //   437: goto -> 547
    //   440: invokestatic a : (Ljava/lang/Throwable;)Ljava/lang/Throwable;
    //   443: athrow
    //   444: aload #6
    //   446: invokevirtual getType : ()Ljava/lang/Class;
    //   449: astore #7
    //   451: aload #7
    //   453: ifnull -> 534
    //   456: aload #7
    //   458: invokevirtual isPrimitive : ()Z
    //   461: ifne -> 534
    //   464: goto -> 471
    //   467: invokestatic a : (Ljava/lang/Throwable;)Ljava/lang/Throwable;
    //   470: athrow
    //   471: aload #7
    //   473: invokevirtual getPackage : ()Ljava/lang/Package;
    //   476: ifnull -> 534
    //   479: goto -> 486
    //   482: invokestatic a : (Ljava/lang/Throwable;)Ljava/lang/Throwable;
    //   485: athrow
    //   486: aload #7
    //   488: invokevirtual getPackage : ()Ljava/lang/Package;
    //   491: invokevirtual getName : ()Ljava/lang/String;
    //   494: ifnull -> 534
    //   497: goto -> 504
    //   500: invokestatic a : (Ljava/lang/Throwable;)Ljava/lang/Throwable;
    //   503: athrow
    //   504: aload #7
    //   506: invokevirtual getPackage : ()Ljava/lang/Package;
    //   509: invokevirtual getName : ()Ljava/lang/String;
    //   512: sipush #-30124
    //   515: sipush #12973
    //   518: invokestatic a : (II)Ljava/lang/String;
    //   521: invokevirtual startsWith : (Ljava/lang/String;)Z
    //   524: ifne -> 534
    //   527: goto -> 534
    //   530: invokestatic a : (Ljava/lang/Throwable;)Ljava/lang/Throwable;
    //   533: athrow
    //   534: aload #6
    //   536: iconst_1
    //   537: invokevirtual setAccessible : (Z)V
    //   540: aload #6
    //   542: aconst_null
    //   543: invokevirtual get : (Ljava/lang/Object;)Ljava/lang/Object;
    //   546: pop
    //   547: iinc #5, 1
    //   550: iload_2
    //   551: ifeq -> 413
    //   554: sipush #-30126
    //   557: sipush #27188
    //   560: invokestatic a : (II)Ljava/lang/String;
    //   563: invokestatic forName : (Ljava/lang/String;)Ljava/lang/Class;
    //   566: invokevirtual getDeclaredMethods : ()[Ljava/lang/reflect/Method;
    //   569: astore_3
    //   570: aload_3
    //   571: arraylength
    //   572: istore #4
    //   574: iconst_0
    //   575: istore #5
    //   577: iload #5
    //   579: iload #4
    //   581: if_icmpge -> 713
    //   584: aload_3
    //   585: iload #5
    //   587: aaload
    //   588: astore #6
    //   590: aload #6
    //   592: invokevirtual getParameterTypes : ()[Ljava/lang/Class;
    //   595: pop
    //   596: aload #6
    //   598: invokevirtual getModifiers : ()I
    //   601: invokestatic isStatic : (I)Z
    //   604: ifeq -> 699
    //   607: aload #6
    //   609: invokevirtual getParameterTypes : ()[Ljava/lang/Class;
    //   612: arraylength
    //   613: iconst_2
    //   614: if_icmpne -> 699
    //   617: goto -> 624
    //   620: invokestatic a : (Ljava/lang/Throwable;)Ljava/lang/Throwable;
    //   623: athrow
    //   624: aload #6
    //   626: invokevirtual getReturnType : ()Ljava/lang/Class;
    //   629: getstatic java/lang/Void.TYPE : Ljava/lang/Class;
    //   632: invokevirtual equals : (Ljava/lang/Object;)Z
    //   635: ifeq -> 699
    //   638: goto -> 645
    //   641: invokestatic a : (Ljava/lang/Throwable;)Ljava/lang/Throwable;
    //   644: athrow
    //   645: aload #6
    //   647: iconst_1
    //   648: invokevirtual setAccessible : (Z)V
    //   651: aload #6
    //   653: aconst_null
    //   654: iconst_2
    //   655: anewarray java/lang/Object
    //   658: dup
    //   659: iconst_0
    //   660: aload_0
    //   661: aastore
    //   662: dup
    //   663: iconst_1
    //   664: aload_1
    //   665: ifnonnull -> 683
    //   668: goto -> 675
    //   671: invokestatic a : (Ljava/lang/Throwable;)Ljava/lang/Throwable;
    //   674: athrow
    //   675: aload_1
    //   676: goto -> 690
    //   679: invokestatic a : (Ljava/lang/Throwable;)Ljava/lang/Throwable;
    //   682: athrow
    //   683: aload_1
    //   684: checkcast [B
    //   687: invokevirtual clone : ()Ljava/lang/Object;
    //   690: aastore
    //   691: invokevirtual invoke : (Ljava/lang/Object;[Ljava/lang/Object;)Ljava/lang/Object;
    //   694: pop
    //   695: iload_2
    //   696: ifeq -> 713
    //   699: iinc #5, 1
    //   702: iload_2
    //   703: ifeq -> 577
    //   706: goto -> 713
    //   709: invokestatic a : (Ljava/lang/Throwable;)Ljava/lang/Throwable;
    //   712: athrow
    //   713: getstatic burp/Zxxd.Zn : Ljava/lang/Object;
    //   716: checkcast java/math/BigInteger
    //   719: invokevirtual toByteArray : ()[B
    //   722: astore_3
    //   723: bipush #64
    //   725: newarray byte
    //   727: dup
    //   728: iconst_0
    //   729: bipush #-128
    //   731: bastore
    //   732: dup
    //   733: iconst_1
    //   734: iconst_0
    //   735: bastore
    //   736: dup
    //   737: iconst_2
    //   738: iconst_0
    //   739: bastore
    //   740: dup
    //   741: iconst_3
    //   742: iconst_0
    //   743: bastore
    //   744: dup
    //   745: iconst_4
    //   746: iconst_0
    //   747: bastore
    //   748: dup
    //   749: iconst_5
    //   750: iconst_0
    //   751: bastore
    //   752: dup
    //   753: bipush #6
    //   755: iconst_0
    //   756: bastore
    //   757: dup
    //   758: bipush #7
    //   760: iconst_0
    //   761: bastore
    //   762: dup
    //   763: bipush #8
    //   765: iconst_0
    //   766: bastore
    //   767: dup
    //   768: bipush #9
    //   770: iconst_0
    //   771: bastore
    //   772: dup
    //   773: bipush #10
    //   775: iconst_0
    //   776: bastore
    //   777: dup
    //   778: bipush #11
    //   780: iconst_0
    //   781: bastore
    //   782: dup
    //   783: bipush #12
    //   785: iconst_0
    //   786: bastore
    //   787: dup
    //   788: bipush #13
    //   790: iconst_0
    //   791: bastore
    //   792: dup
    //   793: bipush #14
    //   795: iconst_0
    //   796: bastore
    //   797: dup
    //   798: bipush #15
    //   800: iconst_0
    //   801: bastore
    //   802: dup
    //   803: bipush #16
    //   805: iconst_0
    //   806: bastore
    //   807: dup
    //   808: bipush #17
    //   810: iconst_0
    //   811: bastore
    //   812: dup
    //   813: bipush #18
    //   815: iconst_0
    //   816: bastore
    //   817: dup
    //   818: bipush #19
    //   820: iconst_0
    //   821: bastore
    //   822: dup
    //   823: bipush #20
    //   825: iconst_0
    //   826: bastore
    //   827: dup
    //   828: bipush #21
    //   830: iconst_0
    //   831: bastore
    //   832: dup
    //   833: bipush #22
    //   835: iconst_0
    //   836: bastore
    //   837: dup
    //   838: bipush #23
    //   840: iconst_0
    //   841: bastore
    //   842: dup
    //   843: bipush #24
    //   845: iconst_0
    //   846: bastore
    //   847: dup
    //   848: bipush #25
    //   850: iconst_0
    //   851: bastore
    //   852: dup
    //   853: bipush #26
    //   855: iconst_0
    //   856: bastore
    //   857: dup
    //   858: bipush #27
    //   860: iconst_0
    //   861: bastore
    //   862: dup
    //   863: bipush #28
    //   865: iconst_0
    //   866: bastore
    //   867: dup
    //   868: bipush #29
    //   870: iconst_0
    //   871: bastore
    //   872: dup
    //   873: bipush #30
    //   875: iconst_0
    //   876: bastore
    //   877: dup
    //   878: bipush #31
    //   880: iconst_0
    //   881: bastore
    //   882: dup
    //   883: bipush #32
    //   885: iconst_0
    //   886: bastore
    //   887: dup
    //   888: bipush #33
    //   890: iconst_0
    //   891: bastore
    //   892: dup
    //   893: bipush #34
    //   895: iconst_0
    //   896: bastore
    //   897: dup
    //   898: bipush #35
    //   900: iconst_0
    //   901: bastore
    //   902: dup
    //   903: bipush #36
    //   905: iconst_0
    //   906: bastore
    //   907: dup
    //   908: bipush #37
    //   910: iconst_0
    //   911: bastore
    //   912: dup
    //   913: bipush #38
    //   915: iconst_0
    //   916: bastore
    //   917: dup
    //   918: bipush #39
    //   920: iconst_0
    //   921: bastore
    //   922: dup
    //   923: bipush #40
    //   925: iconst_0
    //   926: bastore
    //   927: dup
    //   928: bipush #41
    //   930: iconst_0
    //   931: bastore
    //   932: dup
    //   933: bipush #42
    //   935: iconst_0
    //   936: bastore
    //   937: dup
    //   938: bipush #43
    //   940: iconst_0
    //   941: bastore
    //   942: dup
    //   943: bipush #44
    //   945: iconst_0
    //   946: bastore
    //   947: dup
    //   948: bipush #45
    //   950: iconst_0
    //   951: bastore
    //   952: dup
    //   953: bipush #46
    //   955: iconst_0
    //   956: bastore
    //   957: dup
    //   958: bipush #47
    //   960: iconst_0
    //   961: bastore
    //   962: dup
    //   963: bipush #48
    //   965: iconst_0
    //   966: bastore
    //   967: dup
    //   968: bipush #49
    //   970: iconst_0
    //   971: bastore
    //   972: dup
    //   973: bipush #50
    //   975: iconst_0
    //   976: bastore
    //   977: dup
    //   978: bipush #51
    //   980: iconst_0
    //   981: bastore
    //   982: dup
    //   983: bipush #52
    //   985: iconst_0
    //   986: bastore
    //   987: dup
    //   988: bipush #53
    //   990: iconst_0
    //   991: bastore
    //   992: dup
    //   993: bipush #54
    //   995: iconst_0
    //   996: bastore
    //   997: dup
    //   998: bipush #55
    //   1000: iconst_0
    //   1001: bastore
    //   1002: dup
    //   1003: bipush #56
    //   1005: iconst_0
    //   1006: bastore
    //   1007: dup
    //   1008: bipush #57
    //   1010: iconst_0
    //   1011: bastore
    //   1012: dup
    //   1013: bipush #58
    //   1015: iconst_0
    //   1016: bastore
    //   1017: dup
    //   1018: bipush #59
    //   1020: iconst_0
    //   1021: bastore
    //   1022: dup
    //   1023: bipush #60
    //   1025: iconst_0
    //   1026: bastore
    //   1027: dup
    //   1028: bipush #61
    //   1030: iconst_0
    //   1031: bastore
    //   1032: dup
    //   1033: bipush #62
    //   1035: iconst_0
    //   1036: bastore
    //   1037: dup
    //   1038: bipush #63
    //   1040: iconst_0
    //   1041: bastore
    //   1042: astore #5
    //   1044: bipush #64
    //   1046: newarray int
    //   1048: dup
    //   1049: iconst_0
    //   1050: ldc 1116352408
    //   1052: iastore
    //   1053: dup
    //   1054: iconst_1
    //   1055: ldc 1899447441
    //   1057: iastore
    //   1058: dup
    //   1059: iconst_2
    //   1060: ldc -1245643825
    //   1062: iastore
    //   1063: dup
    //   1064: iconst_3
    //   1065: ldc -373957723
    //   1067: iastore
    //   1068: dup
    //   1069: iconst_4
    //   1070: ldc 961987163
    //   1072: iastore
    //   1073: dup
    //   1074: iconst_5
    //   1075: ldc 1508970993
    //   1077: iastore
    //   1078: dup
    //   1079: bipush #6
    //   1081: ldc -1841331548
    //   1083: iastore
    //   1084: dup
    //   1085: bipush #7
    //   1087: ldc -1424204075
    //   1089: iastore
    //   1090: dup
    //   1091: bipush #8
    //   1093: ldc -670586216
    //   1095: iastore
    //   1096: dup
    //   1097: bipush #9
    //   1099: ldc 310598401
    //   1101: iastore
    //   1102: dup
    //   1103: bipush #10
    //   1105: ldc 607225278
    //   1107: iastore
    //   1108: dup
    //   1109: bipush #11
    //   1111: ldc 1426881987
    //   1113: iastore
    //   1114: dup
    //   1115: bipush #12
    //   1117: ldc 1925078388
    //   1119: iastore
    //   1120: dup
    //   1121: bipush #13
    //   1123: ldc -2132889090
    //   1125: iastore
    //   1126: dup
    //   1127: bipush #14
    //   1129: ldc -1680079193
    //   1131: iastore
    //   1132: dup
    //   1133: bipush #15
    //   1135: ldc -1046744716
    //   1137: iastore
    //   1138: dup
    //   1139: bipush #16
    //   1141: ldc -459576895
    //   1143: iastore
    //   1144: dup
    //   1145: bipush #17
    //   1147: ldc -272742522
    //   1149: iastore
    //   1150: dup
    //   1151: bipush #18
    //   1153: ldc 264347078
    //   1155: iastore
    //   1156: dup
    //   1157: bipush #19
    //   1159: ldc 604807628
    //   1161: iastore
    //   1162: dup
    //   1163: bipush #20
    //   1165: ldc 770255983
    //   1167: iastore
    //   1168: dup
    //   1169: bipush #21
    //   1171: ldc 1249150122
    //   1173: iastore
    //   1174: dup
    //   1175: bipush #22
    //   1177: ldc 1555081692
    //   1179: iastore
    //   1180: dup
    //   1181: bipush #23
    //   1183: ldc 1996064986
    //   1185: iastore
    //   1186: dup
    //   1187: bipush #24
    //   1189: ldc -1740746414
    //   1191: iastore
    //   1192: dup
    //   1193: bipush #25
    //   1195: ldc -1473132947
    //   1197: iastore
    //   1198: dup
    //   1199: bipush #26
    //   1201: ldc -1341970488
    //   1203: iastore
    //   1204: dup
    //   1205: bipush #27
    //   1207: ldc -1084653625
    //   1209: iastore
    //   1210: dup
    //   1211: bipush #28
    //   1213: ldc -958395405
    //   1215: iastore
    //   1216: dup
    //   1217: bipush #29
    //   1219: ldc -710438585
    //   1221: iastore
    //   1222: dup
    //   1223: bipush #30
    //   1225: ldc 113926993
    //   1227: iastore
    //   1228: dup
    //   1229: bipush #31
    //   1231: ldc 338241895
    //   1233: iastore
    //   1234: dup
    //   1235: bipush #32
    //   1237: ldc 666307205
    //   1239: iastore
    //   1240: dup
    //   1241: bipush #33
    //   1243: ldc 773529912
    //   1245: iastore
    //   1246: dup
    //   1247: bipush #34
    //   1249: ldc 1294757372
    //   1251: iastore
    //   1252: dup
    //   1253: bipush #35
    //   1255: ldc 1396182291
    //   1257: iastore
    //   1258: dup
    //   1259: bipush #36
    //   1261: ldc 1695183700
    //   1263: iastore
    //   1264: dup
    //   1265: bipush #37
    //   1267: ldc 1986661051
    //   1269: iastore
    //   1270: dup
    //   1271: bipush #38
    //   1273: ldc -2117940946
    //   1275: iastore
    //   1276: dup
    //   1277: bipush #39
    //   1279: ldc -1838011259
    //   1281: iastore
    //   1282: dup
    //   1283: bipush #40
    //   1285: ldc -1564481375
    //   1287: iastore
    //   1288: dup
    //   1289: bipush #41
    //   1291: ldc -1474664885
    //   1293: iastore
    //   1294: dup
    //   1295: bipush #42
    //   1297: ldc -1035236496
    //   1299: iastore
    //   1300: dup
    //   1301: bipush #43
    //   1303: ldc -949202525
    //   1305: iastore
    //   1306: dup
    //   1307: bipush #44
    //   1309: ldc -778901479
    //   1311: iastore
    //   1312: dup
    //   1313: bipush #45
    //   1315: ldc -694614492
    //   1317: iastore
    //   1318: dup
    //   1319: bipush #46
    //   1321: ldc -200395387
    //   1323: iastore
    //   1324: dup
    //   1325: bipush #47
    //   1327: ldc 275423344
    //   1329: iastore
    //   1330: dup
    //   1331: bipush #48
    //   1333: ldc 430227734
    //   1335: iastore
    //   1336: dup
    //   1337: bipush #49
    //   1339: ldc 506948616
    //   1341: iastore
    //   1342: dup
    //   1343: bipush #50
    //   1345: ldc 659060556
    //   1347: iastore
    //   1348: dup
    //   1349: bipush #51
    //   1351: ldc 883997877
    //   1353: iastore
    //   1354: dup
    //   1355: bipush #52
    //   1357: ldc 958139571
    //   1359: iastore
    //   1360: dup
    //   1361: bipush #53
    //   1363: ldc 1322822218
    //   1365: iastore
    //   1366: dup
    //   1367: bipush #54
    //   1369: ldc 1537002063
    //   1371: iastore
    //   1372: dup
    //   1373: bipush #55
    //   1375: ldc 1747873779
    //   1377: iastore
    //   1378: dup
    //   1379: bipush #56
    //   1381: ldc 1955562222
    //   1383: iastore
    //   1384: dup
    //   1385: bipush #57
    //   1387: ldc 2024104815
    //   1389: iastore
    //   1390: dup
    //   1391: bipush #58
    //   1393: ldc -2067236844
    //   1395: iastore
    //   1396: dup
    //   1397: bipush #59
    //   1399: ldc -1933114872
    //   1401: iastore
    //   1402: dup
    //   1403: bipush #60
    //   1405: ldc -1866530822
    //   1407: iastore
    //   1408: dup
    //   1409: bipush #61
    //   1411: ldc -1538233109
    //   1413: iastore
    //   1414: dup
    //   1415: bipush #62
    //   1417: ldc -1090935817
    //   1419: iastore
    //   1420: dup
    //   1421: bipush #63
    //   1423: ldc -965641998
    //   1425: iastore
    //   1426: astore #6
    //   1428: iconst_2
    //   1429: newarray int
    //   1431: dup
    //   1432: iconst_0
    //   1433: iconst_0
    //   1434: iastore
    //   1435: dup
    //   1436: iconst_1
    //   1437: iconst_0
    //   1438: iastore
    //   1439: astore #7
    //   1441: bipush #8
    //   1443: newarray int
    //   1445: dup
    //   1446: iconst_0
    //   1447: ldc 1779033703
    //   1449: iastore
    //   1450: dup
    //   1451: iconst_1
    //   1452: ldc -1150833019
    //   1454: iastore
    //   1455: dup
    //   1456: iconst_2
    //   1457: ldc 1013904242
    //   1459: iastore
    //   1460: dup
    //   1461: iconst_3
    //   1462: ldc -1521486534
    //   1464: iastore
    //   1465: dup
    //   1466: iconst_4
    //   1467: ldc 1359893119
    //   1469: iastore
    //   1470: dup
    //   1471: iconst_5
    //   1472: ldc -1694144372
    //   1474: iastore
    //   1475: dup
    //   1476: bipush #6
    //   1478: ldc 528734635
    //   1480: iastore
    //   1481: dup
    //   1482: bipush #7
    //   1484: ldc 1541459225
    //   1486: iastore
    //   1487: astore #8
    //   1489: bipush #64
    //   1491: newarray byte
    //   1493: astore #9
    //   1495: bipush #64
    //   1497: newarray byte
    //   1499: astore #10
    //   1501: aload_3
    //   1502: arraylength
    //   1503: istore #11
    //   1505: aload #7
    //   1507: iconst_0
    //   1508: iaload
    //   1509: bipush #63
    //   1511: iand
    //   1512: istore #12
    //   1514: aload #7
    //   1516: iconst_0
    //   1517: dup2
    //   1518: iaload
    //   1519: iload #11
    //   1521: iadd
    //   1522: iastore
    //   1523: aload #7
    //   1525: iconst_0
    //   1526: dup2
    //   1527: iaload
    //   1528: iconst_m1
    //   1529: iand
    //   1530: iastore
    //   1531: aload #7
    //   1533: iconst_0
    //   1534: iaload
    //   1535: iload #11
    //   1537: if_icmpge -> 1555
    //   1540: aload #7
    //   1542: iconst_1
    //   1543: dup2
    //   1544: iaload
    //   1545: iconst_1
    //   1546: iadd
    //   1547: iastore
    //   1548: goto -> 1555
    //   1551: invokestatic a : (Ljava/lang/Throwable;)Ljava/lang/Throwable;
    //   1554: athrow
    //   1555: iconst_0
    //   1556: istore #13
    //   1558: iload #11
    //   1560: bipush #64
    //   1562: if_icmplt -> 2171
    //   1565: iconst_0
    //   1566: istore #14
    //   1568: iload #14
    //   1570: bipush #64
    //   1572: if_icmpge -> 1594
    //   1575: aload #10
    //   1577: iload #14
    //   1579: aload_3
    //   1580: iload #13
    //   1582: iload #14
    //   1584: iadd
    //   1585: baload
    //   1586: bastore
    //   1587: iinc #14, 1
    //   1590: iload_2
    //   1591: ifeq -> 1568
    //   1594: bipush #64
    //   1596: newarray int
    //   1598: astore #14
    //   1600: bipush #8
    //   1602: newarray int
    //   1604: astore #15
    //   1606: iconst_0
    //   1607: istore #16
    //   1609: iload #16
    //   1611: bipush #8
    //   1613: if_icmpge -> 1633
    //   1616: aload #15
    //   1618: iload #16
    //   1620: aload #8
    //   1622: iload #16
    //   1624: iaload
    //   1625: iastore
    //   1626: iinc #16, 1
    //   1629: iload_2
    //   1630: ifeq -> 1609
    //   1633: iconst_0
    //   1634: istore #16
    //   1636: iload #16
    //   1638: bipush #64
    //   1640: if_icmpge -> 2131
    //   1643: iload #16
    //   1645: bipush #16
    //   1647: if_icmpge -> 1728
    //   1650: aload #14
    //   1652: iload #16
    //   1654: aload #10
    //   1656: iconst_4
    //   1657: iload #16
    //   1659: imul
    //   1660: baload
    //   1661: sipush #255
    //   1664: iand
    //   1665: bipush #24
    //   1667: ishl
    //   1668: aload #10
    //   1670: iconst_4
    //   1671: iload #16
    //   1673: imul
    //   1674: iconst_1
    //   1675: iadd
    //   1676: baload
    //   1677: sipush #255
    //   1680: iand
    //   1681: bipush #16
    //   1683: ishl
    //   1684: ior
    //   1685: aload #10
    //   1687: iconst_4
    //   1688: iload #16
    //   1690: imul
    //   1691: iconst_2
    //   1692: iadd
    //   1693: baload
    //   1694: sipush #255
    //   1697: iand
    //   1698: bipush #8
    //   1700: ishl
    //   1701: ior
    //   1702: aload #10
    //   1704: iconst_4
    //   1705: iload #16
    //   1707: imul
    //   1708: iconst_3
    //   1709: iadd
    //   1710: baload
    //   1711: sipush #255
    //   1714: iand
    //   1715: ior
    //   1716: iastore
    //   1717: iload_2
    //   1718: ifeq -> 1871
    //   1721: goto -> 1728
    //   1724: invokestatic a : (Ljava/lang/Throwable;)Ljava/lang/Throwable;
    //   1727: athrow
    //   1728: aload #14
    //   1730: iload #16
    //   1732: aload #14
    //   1734: iload #16
    //   1736: iconst_2
    //   1737: isub
    //   1738: iaload
    //   1739: bipush #17
    //   1741: iushr
    //   1742: aload #14
    //   1744: iload #16
    //   1746: iconst_2
    //   1747: isub
    //   1748: iaload
    //   1749: bipush #15
    //   1751: ishl
    //   1752: ior
    //   1753: aload #14
    //   1755: iload #16
    //   1757: iconst_2
    //   1758: isub
    //   1759: iaload
    //   1760: bipush #19
    //   1762: iushr
    //   1763: aload #14
    //   1765: iload #16
    //   1767: iconst_2
    //   1768: isub
    //   1769: iaload
    //   1770: bipush #13
    //   1772: ishl
    //   1773: ior
    //   1774: ixor
    //   1775: aload #14
    //   1777: iload #16
    //   1779: iconst_2
    //   1780: isub
    //   1781: iaload
    //   1782: bipush #10
    //   1784: iushr
    //   1785: ixor
    //   1786: aload #14
    //   1788: iload #16
    //   1790: bipush #7
    //   1792: isub
    //   1793: iaload
    //   1794: iadd
    //   1795: aload #14
    //   1797: iload #16
    //   1799: bipush #15
    //   1801: isub
    //   1802: iaload
    //   1803: bipush #7
    //   1805: iushr
    //   1806: aload #14
    //   1808: iload #16
    //   1810: bipush #15
    //   1812: isub
    //   1813: iaload
    //   1814: bipush #25
    //   1816: ishl
    //   1817: ior
    //   1818: aload #14
    //   1820: iload #16
    //   1822: bipush #15
    //   1824: isub
    //   1825: iaload
    //   1826: bipush #18
    //   1828: iushr
    //   1829: aload #14
    //   1831: iload #16
    //   1833: bipush #15
    //   1835: isub
    //   1836: iaload
    //   1837: bipush #14
    //   1839: ishl
    //   1840: ior
    //   1841: ixor
    //   1842: aload #14
    //   1844: iload #16
    //   1846: bipush #15
    //   1848: isub
    //   1849: iaload
    //   1850: iconst_3
    //   1851: iushr
    //   1852: ixor
    //   1853: iadd
    //   1854: aload #14
    //   1856: iload #16
    //   1858: bipush #16
    //   1860: isub
    //   1861: iaload
    //   1862: iadd
    //   1863: iastore
    //   1864: goto -> 1871
    //   1867: invokestatic a : (Ljava/lang/Throwable;)Ljava/lang/Throwable;
    //   1870: athrow
    //   1871: aload #15
    //   1873: bipush #7
    //   1875: iaload
    //   1876: aload #15
    //   1878: iconst_4
    //   1879: iaload
    //   1880: bipush #6
    //   1882: iushr
    //   1883: aload #15
    //   1885: iconst_4
    //   1886: iaload
    //   1887: bipush #26
    //   1889: ishl
    //   1890: ior
    //   1891: aload #15
    //   1893: iconst_4
    //   1894: iaload
    //   1895: bipush #11
    //   1897: iushr
    //   1898: aload #15
    //   1900: iconst_4
    //   1901: iaload
    //   1902: bipush #21
    //   1904: ishl
    //   1905: ior
    //   1906: ixor
    //   1907: aload #15
    //   1909: iconst_4
    //   1910: iaload
    //   1911: bipush #25
    //   1913: iushr
    //   1914: aload #15
    //   1916: iconst_4
    //   1917: iaload
    //   1918: bipush #7
    //   1920: ishl
    //   1921: ior
    //   1922: ixor
    //   1923: iadd
    //   1924: aload #15
    //   1926: bipush #6
    //   1928: iaload
    //   1929: aload #15
    //   1931: iconst_4
    //   1932: iaload
    //   1933: aload #15
    //   1935: iconst_5
    //   1936: iaload
    //   1937: aload #15
    //   1939: bipush #6
    //   1941: iaload
    //   1942: ixor
    //   1943: iand
    //   1944: ixor
    //   1945: iadd
    //   1946: aload #6
    //   1948: iload #16
    //   1950: iaload
    //   1951: iadd
    //   1952: aload #14
    //   1954: iload #16
    //   1956: iaload
    //   1957: iadd
    //   1958: istore #17
    //   1960: aload #15
    //   1962: iconst_0
    //   1963: iaload
    //   1964: iconst_2
    //   1965: iushr
    //   1966: aload #15
    //   1968: iconst_0
    //   1969: iaload
    //   1970: bipush #30
    //   1972: ishl
    //   1973: ior
    //   1974: aload #15
    //   1976: iconst_0
    //   1977: iaload
    //   1978: bipush #13
    //   1980: iushr
    //   1981: aload #15
    //   1983: iconst_0
    //   1984: iaload
    //   1985: bipush #19
    //   1987: ishl
    //   1988: ior
    //   1989: ixor
    //   1990: aload #15
    //   1992: iconst_0
    //   1993: iaload
    //   1994: bipush #22
    //   1996: iushr
    //   1997: aload #15
    //   1999: iconst_0
    //   2000: iaload
    //   2001: bipush #10
    //   2003: ishl
    //   2004: ior
    //   2005: ixor
    //   2006: aload #15
    //   2008: iconst_0
    //   2009: iaload
    //   2010: aload #15
    //   2012: iconst_1
    //   2013: iaload
    //   2014: iand
    //   2015: aload #15
    //   2017: iconst_2
    //   2018: iaload
    //   2019: aload #15
    //   2021: iconst_0
    //   2022: iaload
    //   2023: aload #15
    //   2025: iconst_1
    //   2026: iaload
    //   2027: ior
    //   2028: iand
    //   2029: ior
    //   2030: iadd
    //   2031: istore #18
    //   2033: aload #15
    //   2035: iconst_3
    //   2036: dup2
    //   2037: iaload
    //   2038: iload #17
    //   2040: iadd
    //   2041: iastore
    //   2042: aload #15
    //   2044: bipush #7
    //   2046: iload #17
    //   2048: iload #18
    //   2050: iadd
    //   2051: iastore
    //   2052: aload #15
    //   2054: bipush #7
    //   2056: iaload
    //   2057: istore #17
    //   2059: aload #15
    //   2061: bipush #7
    //   2063: aload #15
    //   2065: bipush #6
    //   2067: iaload
    //   2068: iastore
    //   2069: aload #15
    //   2071: bipush #6
    //   2073: aload #15
    //   2075: iconst_5
    //   2076: iaload
    //   2077: iastore
    //   2078: aload #15
    //   2080: iconst_5
    //   2081: aload #15
    //   2083: iconst_4
    //   2084: iaload
    //   2085: iastore
    //   2086: aload #15
    //   2088: iconst_4
    //   2089: aload #15
    //   2091: iconst_3
    //   2092: iaload
    //   2093: iastore
    //   2094: aload #15
    //   2096: iconst_3
    //   2097: aload #15
    //   2099: iconst_2
    //   2100: iaload
    //   2101: iastore
    //   2102: aload #15
    //   2104: iconst_2
    //   2105: aload #15
    //   2107: iconst_1
    //   2108: iaload
    //   2109: iastore
    //   2110: aload #15
    //   2112: iconst_1
    //   2113: aload #15
    //   2115: iconst_0
    //   2116: iaload
    //   2117: iastore
    //   2118: aload #15
    //   2120: iconst_0
    //   2121: iload #17
    //   2123: iastore
    //   2124: iinc #16, 1
    //   2127: iload_2
    //   2128: ifeq -> 1636
    //   2131: iconst_0
    //   2132: istore #16
    //   2134: iload #16
    //   2136: bipush #8
    //   2138: if_icmpge -> 2161
    //   2141: aload #8
    //   2143: iload #16
    //   2145: dup2
    //   2146: iaload
    //   2147: aload #15
    //   2149: iload #16
    //   2151: iaload
    //   2152: iadd
    //   2153: iastore
    //   2154: iinc #16, 1
    //   2157: iload_2
    //   2158: ifeq -> 2134
    //   2161: iinc #13, 64
    //   2164: iinc #11, -64
    //   2167: iload_2
    //   2168: ifeq -> 1558
    //   2171: iload #11
    //   2173: ifle -> 2208
    //   2176: iconst_0
    //   2177: istore #14
    //   2179: iload #14
    //   2181: iload #11
    //   2183: if_icmpge -> 2208
    //   2186: aload #9
    //   2188: iload #12
    //   2190: iload #14
    //   2192: iadd
    //   2193: aload_3
    //   2194: iload #13
    //   2196: iload #14
    //   2198: iadd
    //   2199: baload
    //   2200: bastore
    //   2201: iinc #14, 1
    //   2204: iload_2
    //   2205: ifeq -> 2179
    //   2208: aload #7
    //   2210: iconst_0
    //   2211: iaload
    //   2212: bipush #29
    //   2214: iushr
    //   2215: aload #7
    //   2217: iconst_1
    //   2218: iaload
    //   2219: iconst_3
    //   2220: ishl
    //   2221: ior
    //   2222: istore #14
    //   2224: aload #7
    //   2226: iconst_0
    //   2227: iaload
    //   2228: iconst_3
    //   2229: ishl
    //   2230: istore #15
    //   2232: aload #7
    //   2234: iconst_0
    //   2235: iaload
    //   2236: bipush #63
    //   2238: iand
    //   2239: istore #16
    //   2241: iload #16
    //   2243: bipush #56
    //   2245: if_icmpge -> 2260
    //   2248: bipush #56
    //   2250: iload #16
    //   2252: isub
    //   2253: goto -> 2265
    //   2256: invokestatic a : (Ljava/lang/Throwable;)Ljava/lang/Throwable;
    //   2259: athrow
    //   2260: bipush #120
    //   2262: iload #16
    //   2264: isub
    //   2265: istore #17
    //   2267: aload #7
    //   2269: iconst_0
    //   2270: iaload
    //   2271: bipush #63
    //   2273: iand
    //   2274: istore #12
    //   2276: bipush #64
    //   2278: iload #12
    //   2280: isub
    //   2281: istore #18
    //   2283: aload #7
    //   2285: iconst_0
    //   2286: dup2
    //   2287: iaload
    //   2288: iload #17
    //   2290: iadd
    //   2291: iastore
    //   2292: aload #7
    //   2294: iconst_0
    //   2295: dup2
    //   2296: iaload
    //   2297: iconst_m1
    //   2298: iand
    //   2299: iastore
    //   2300: aload #7
    //   2302: iconst_0
    //   2303: iaload
    //   2304: iload #17
    //   2306: if_icmpge -> 2324
    //   2309: aload #7
    //   2311: iconst_1
    //   2312: dup2
    //   2313: iaload
    //   2314: iconst_1
    //   2315: iadd
    //   2316: iastore
    //   2317: goto -> 2324
    //   2320: invokestatic a : (Ljava/lang/Throwable;)Ljava/lang/Throwable;
    //   2323: athrow
    //   2324: iconst_0
    //   2325: istore #13
    //   2327: iload #12
    //   2329: ifle -> 2960
    //   2332: iload #17
    //   2334: iload #18
    //   2336: if_icmplt -> 2960
    //   2339: goto -> 2346
    //   2342: invokestatic a : (Ljava/lang/Throwable;)Ljava/lang/Throwable;
    //   2345: athrow
    //   2346: iconst_0
    //   2347: istore #19
    //   2349: iload #19
    //   2351: iload #18
    //   2353: if_icmpge -> 2376
    //   2356: aload #9
    //   2358: iload #12
    //   2360: iload #19
    //   2362: iadd
    //   2363: aload #5
    //   2365: iload #19
    //   2367: baload
    //   2368: bastore
    //   2369: iinc #19, 1
    //   2372: iload_2
    //   2373: ifeq -> 2349
    //   2376: bipush #64
    //   2378: newarray int
    //   2380: astore #19
    //   2382: bipush #8
    //   2384: newarray int
    //   2386: astore #20
    //   2388: iconst_0
    //   2389: istore #21
    //   2391: iload #21
    //   2393: bipush #8
    //   2395: if_icmpge -> 2415
    //   2398: aload #20
    //   2400: iload #21
    //   2402: aload #8
    //   2404: iload #21
    //   2406: iaload
    //   2407: iastore
    //   2408: iinc #21, 1
    //   2411: iload_2
    //   2412: ifeq -> 2391
    //   2415: iconst_0
    //   2416: istore #21
    //   2418: iload #21
    //   2420: bipush #64
    //   2422: if_icmpge -> 2913
    //   2425: iload #21
    //   2427: bipush #16
    //   2429: if_icmpge -> 2510
    //   2432: aload #19
    //   2434: iload #21
    //   2436: aload #9
    //   2438: iconst_4
    //   2439: iload #21
    //   2441: imul
    //   2442: baload
    //   2443: sipush #255
    //   2446: iand
    //   2447: bipush #24
    //   2449: ishl
    //   2450: aload #9
    //   2452: iconst_4
    //   2453: iload #21
    //   2455: imul
    //   2456: iconst_1
    //   2457: iadd
    //   2458: baload
    //   2459: sipush #255
    //   2462: iand
    //   2463: bipush #16
    //   2465: ishl
    //   2466: ior
    //   2467: aload #9
    //   2469: iconst_4
    //   2470: iload #21
    //   2472: imul
    //   2473: iconst_2
    //   2474: iadd
    //   2475: baload
    //   2476: sipush #255
    //   2479: iand
    //   2480: bipush #8
    //   2482: ishl
    //   2483: ior
    //   2484: aload #9
    //   2486: iconst_4
    //   2487: iload #21
    //   2489: imul
    //   2490: iconst_3
    //   2491: iadd
    //   2492: baload
    //   2493: sipush #255
    //   2496: iand
    //   2497: ior
    //   2498: iastore
    //   2499: iload_2
    //   2500: ifeq -> 2653
    //   2503: goto -> 2510
    //   2506: invokestatic a : (Ljava/lang/Throwable;)Ljava/lang/Throwable;
    //   2509: athrow
    //   2510: aload #19
    //   2512: iload #21
    //   2514: aload #19
    //   2516: iload #21
    //   2518: iconst_2
    //   2519: isub
    //   2520: iaload
    //   2521: bipush #17
    //   2523: iushr
    //   2524: aload #19
    //   2526: iload #21
    //   2528: iconst_2
    //   2529: isub
    //   2530: iaload
    //   2531: bipush #15
    //   2533: ishl
    //   2534: ior
    //   2535: aload #19
    //   2537: iload #21
    //   2539: iconst_2
    //   2540: isub
    //   2541: iaload
    //   2542: bipush #19
    //   2544: iushr
    //   2545: aload #19
    //   2547: iload #21
    //   2549: iconst_2
    //   2550: isub
    //   2551: iaload
    //   2552: bipush #13
    //   2554: ishl
    //   2555: ior
    //   2556: ixor
    //   2557: aload #19
    //   2559: iload #21
    //   2561: iconst_2
    //   2562: isub
    //   2563: iaload
    //   2564: bipush #10
    //   2566: iushr
    //   2567: ixor
    //   2568: aload #19
    //   2570: iload #21
    //   2572: bipush #7
    //   2574: isub
    //   2575: iaload
    //   2576: iadd
    //   2577: aload #19
    //   2579: iload #21
    //   2581: bipush #15
    //   2583: isub
    //   2584: iaload
    //   2585: bipush #7
    //   2587: iushr
    //   2588: aload #19
    //   2590: iload #21
    //   2592: bipush #15
    //   2594: isub
    //   2595: iaload
    //   2596: bipush #25
    //   2598: ishl
    //   2599: ior
    //   2600: aload #19
    //   2602: iload #21
    //   2604: bipush #15
    //   2606: isub
    //   2607: iaload
    //   2608: bipush #18
    //   2610: iushr
    //   2611: aload #19
    //   2613: iload #21
    //   2615: bipush #15
    //   2617: isub
    //   2618: iaload
    //   2619: bipush #14
    //   2621: ishl
    //   2622: ior
    //   2623: ixor
    //   2624: aload #19
    //   2626: iload #21
    //   2628: bipush #15
    //   2630: isub
    //   2631: iaload
    //   2632: iconst_3
    //   2633: iushr
    //   2634: ixor
    //   2635: iadd
    //   2636: aload #19
    //   2638: iload #21
    //   2640: bipush #16
    //   2642: isub
    //   2643: iaload
    //   2644: iadd
    //   2645: iastore
    //   2646: goto -> 2653
    //   2649: invokestatic a : (Ljava/lang/Throwable;)Ljava/lang/Throwable;
    //   2652: athrow
    //   2653: aload #20
    //   2655: bipush #7
    //   2657: iaload
    //   2658: aload #20
    //   2660: iconst_4
    //   2661: iaload
    //   2662: bipush #6
    //   2664: iushr
    //   2665: aload #20
    //   2667: iconst_4
    //   2668: iaload
    //   2669: bipush #26
    //   2671: ishl
    //   2672: ior
    //   2673: aload #20
    //   2675: iconst_4
    //   2676: iaload
    //   2677: bipush #11
    //   2679: iushr
    //   2680: aload #20
    //   2682: iconst_4
    //   2683: iaload
    //   2684: bipush #21
    //   2686: ishl
    //   2687: ior
    //   2688: ixor
    //   2689: aload #20
    //   2691: iconst_4
    //   2692: iaload
    //   2693: bipush #25
    //   2695: iushr
    //   2696: aload #20
    //   2698: iconst_4
    //   2699: iaload
    //   2700: bipush #7
    //   2702: ishl
    //   2703: ior
    //   2704: ixor
    //   2705: iadd
    //   2706: aload #20
    //   2708: bipush #6
    //   2710: iaload
    //   2711: aload #20
    //   2713: iconst_4
    //   2714: iaload
    //   2715: aload #20
    //   2717: iconst_5
    //   2718: iaload
    //   2719: aload #20
    //   2721: bipush #6
    //   2723: iaload
    //   2724: ixor
    //   2725: iand
    //   2726: ixor
    //   2727: iadd
    //   2728: aload #6
    //   2730: iload #21
    //   2732: iaload
    //   2733: iadd
    //   2734: aload #19
    //   2736: iload #21
    //   2738: iaload
    //   2739: iadd
    //   2740: istore #22
    //   2742: aload #20
    //   2744: iconst_0
    //   2745: iaload
    //   2746: iconst_2
    //   2747: iushr
    //   2748: aload #20
    //   2750: iconst_0
    //   2751: iaload
    //   2752: bipush #30
    //   2754: ishl
    //   2755: ior
    //   2756: aload #20
    //   2758: iconst_0
    //   2759: iaload
    //   2760: bipush #13
    //   2762: iushr
    //   2763: aload #20
    //   2765: iconst_0
    //   2766: iaload
    //   2767: bipush #19
    //   2769: ishl
    //   2770: ior
    //   2771: ixor
    //   2772: aload #20
    //   2774: iconst_0
    //   2775: iaload
    //   2776: bipush #22
    //   2778: iushr
    //   2779: aload #20
    //   2781: iconst_0
    //   2782: iaload
    //   2783: bipush #10
    //   2785: ishl
    //   2786: ior
    //   2787: ixor
    //   2788: aload #20
    //   2790: iconst_0
    //   2791: iaload
    //   2792: aload #20
    //   2794: iconst_1
    //   2795: iaload
    //   2796: iand
    //   2797: aload #20
    //   2799: iconst_2
    //   2800: iaload
    //   2801: aload #20
    //   2803: iconst_0
    //   2804: iaload
    //   2805: aload #20
    //   2807: iconst_1
    //   2808: iaload
    //   2809: ior
    //   2810: iand
    //   2811: ior
    //   2812: iadd
    //   2813: istore #23
    //   2815: aload #20
    //   2817: iconst_3
    //   2818: dup2
    //   2819: iaload
    //   2820: iload #22
    //   2822: iadd
    //   2823: iastore
    //   2824: aload #20
    //   2826: bipush #7
    //   2828: iload #22
    //   2830: iload #23
    //   2832: iadd
    //   2833: iastore
    //   2834: aload #20
    //   2836: bipush #7
    //   2838: iaload
    //   2839: istore #22
    //   2841: aload #20
    //   2843: bipush #7
    //   2845: aload #20
    //   2847: bipush #6
    //   2849: iaload
    //   2850: iastore
    //   2851: aload #20
    //   2853: bipush #6
    //   2855: aload #20
    //   2857: iconst_5
    //   2858: iaload
    //   2859: iastore
    //   2860: aload #20
    //   2862: iconst_5
    //   2863: aload #20
    //   2865: iconst_4
    //   2866: iaload
    //   2867: iastore
    //   2868: aload #20
    //   2870: iconst_4
    //   2871: aload #20
    //   2873: iconst_3
    //   2874: iaload
    //   2875: iastore
    //   2876: aload #20
    //   2878: iconst_3
    //   2879: aload #20
    //   2881: iconst_2
    //   2882: iaload
    //   2883: iastore
    //   2884: aload #20
    //   2886: iconst_2
    //   2887: aload #20
    //   2889: iconst_1
    //   2890: iaload
    //   2891: iastore
    //   2892: aload #20
    //   2894: iconst_1
    //   2895: aload #20
    //   2897: iconst_0
    //   2898: iaload
    //   2899: iastore
    //   2900: aload #20
    //   2902: iconst_0
    //   2903: iload #22
    //   2905: iastore
    //   2906: iinc #21, 1
    //   2909: iload_2
    //   2910: ifeq -> 2418
    //   2913: iconst_0
    //   2914: istore #21
    //   2916: iload #21
    //   2918: bipush #8
    //   2920: if_icmpge -> 2943
    //   2923: aload #8
    //   2925: iload #21
    //   2927: dup2
    //   2928: iaload
    //   2929: aload #20
    //   2931: iload #21
    //   2933: iaload
    //   2934: iadd
    //   2935: iastore
    //   2936: iinc #21, 1
    //   2939: iload_2
    //   2940: ifeq -> 2916
    //   2943: iload #13
    //   2945: iload #18
    //   2947: iadd
    //   2948: istore #13
    //   2950: iload #17
    //   2952: iload #18
    //   2954: isub
    //   2955: istore #17
    //   2957: iconst_0
    //   2958: istore #12
    //   2960: iload #17
    //   2962: bipush #64
    //   2964: if_icmplt -> 3574
    //   2967: iconst_0
    //   2968: istore #19
    //   2970: iload #19
    //   2972: bipush #64
    //   2974: if_icmpge -> 2997
    //   2977: aload #10
    //   2979: iload #19
    //   2981: aload #5
    //   2983: iload #13
    //   2985: iload #19
    //   2987: iadd
    //   2988: baload
    //   2989: bastore
    //   2990: iinc #19, 1
    //   2993: iload_2
    //   2994: ifeq -> 2970
    //   2997: bipush #64
    //   2999: newarray int
    //   3001: astore #19
    //   3003: bipush #8
    //   3005: newarray int
    //   3007: astore #20
    //   3009: iconst_0
    //   3010: istore #21
    //   3012: iload #21
    //   3014: bipush #8
    //   3016: if_icmpge -> 3036
    //   3019: aload #20
    //   3021: iload #21
    //   3023: aload #8
    //   3025: iload #21
    //   3027: iaload
    //   3028: iastore
    //   3029: iinc #21, 1
    //   3032: iload_2
    //   3033: ifeq -> 3012
    //   3036: iconst_0
    //   3037: istore #21
    //   3039: iload #21
    //   3041: bipush #64
    //   3043: if_icmpge -> 3534
    //   3046: iload #21
    //   3048: bipush #16
    //   3050: if_icmpge -> 3131
    //   3053: aload #19
    //   3055: iload #21
    //   3057: aload #10
    //   3059: iconst_4
    //   3060: iload #21
    //   3062: imul
    //   3063: baload
    //   3064: sipush #255
    //   3067: iand
    //   3068: bipush #24
    //   3070: ishl
    //   3071: aload #10
    //   3073: iconst_4
    //   3074: iload #21
    //   3076: imul
    //   3077: iconst_1
    //   3078: iadd
    //   3079: baload
    //   3080: sipush #255
    //   3083: iand
    //   3084: bipush #16
    //   3086: ishl
    //   3087: ior
    //   3088: aload #10
    //   3090: iconst_4
    //   3091: iload #21
    //   3093: imul
    //   3094: iconst_2
    //   3095: iadd
    //   3096: baload
    //   3097: sipush #255
    //   3100: iand
    //   3101: bipush #8
    //   3103: ishl
    //   3104: ior
    //   3105: aload #10
    //   3107: iconst_4
    //   3108: iload #21
    //   3110: imul
    //   3111: iconst_3
    //   3112: iadd
    //   3113: baload
    //   3114: sipush #255
    //   3117: iand
    //   3118: ior
    //   3119: iastore
    //   3120: iload_2
    //   3121: ifeq -> 3274
    //   3124: goto -> 3131
    //   3127: invokestatic a : (Ljava/lang/Throwable;)Ljava/lang/Throwable;
    //   3130: athrow
    //   3131: aload #19
    //   3133: iload #21
    //   3135: aload #19
    //   3137: iload #21
    //   3139: iconst_2
    //   3140: isub
    //   3141: iaload
    //   3142: bipush #17
    //   3144: iushr
    //   3145: aload #19
    //   3147: iload #21
    //   3149: iconst_2
    //   3150: isub
    //   3151: iaload
    //   3152: bipush #15
    //   3154: ishl
    //   3155: ior
    //   3156: aload #19
    //   3158: iload #21
    //   3160: iconst_2
    //   3161: isub
    //   3162: iaload
    //   3163: bipush #19
    //   3165: iushr
    //   3166: aload #19
    //   3168: iload #21
    //   3170: iconst_2
    //   3171: isub
    //   3172: iaload
    //   3173: bipush #13
    //   3175: ishl
    //   3176: ior
    //   3177: ixor
    //   3178: aload #19
    //   3180: iload #21
    //   3182: iconst_2
    //   3183: isub
    //   3184: iaload
    //   3185: bipush #10
    //   3187: iushr
    //   3188: ixor
    //   3189: aload #19
    //   3191: iload #21
    //   3193: bipush #7
    //   3195: isub
    //   3196: iaload
    //   3197: iadd
    //   3198: aload #19
    //   3200: iload #21
    //   3202: bipush #15
    //   3204: isub
    //   3205: iaload
    //   3206: bipush #7
    //   3208: iushr
    //   3209: aload #19
    //   3211: iload #21
    //   3213: bipush #15
    //   3215: isub
    //   3216: iaload
    //   3217: bipush #25
    //   3219: ishl
    //   3220: ior
    //   3221: aload #19
    //   3223: iload #21
    //   3225: bipush #15
    //   3227: isub
    //   3228: iaload
    //   3229: bipush #18
    //   3231: iushr
    //   3232: aload #19
    //   3234: iload #21
    //   3236: bipush #15
    //   3238: isub
    //   3239: iaload
    //   3240: bipush #14
    //   3242: ishl
    //   3243: ior
    //   3244: ixor
    //   3245: aload #19
    //   3247: iload #21
    //   3249: bipush #15
    //   3251: isub
    //   3252: iaload
    //   3253: iconst_3
    //   3254: iushr
    //   3255: ixor
    //   3256: iadd
    //   3257: aload #19
    //   3259: iload #21
    //   3261: bipush #16
    //   3263: isub
    //   3264: iaload
    //   3265: iadd
    //   3266: iastore
    //   3267: goto -> 3274
    //   3270: invokestatic a : (Ljava/lang/Throwable;)Ljava/lang/Throwable;
    //   3273: athrow
    //   3274: aload #20
    //   3276: bipush #7
    //   3278: iaload
    //   3279: aload #20
    //   3281: iconst_4
    //   3282: iaload
    //   3283: bipush #6
    //   3285: iushr
    //   3286: aload #20
    //   3288: iconst_4
    //   3289: iaload
    //   3290: bipush #26
    //   3292: ishl
    //   3293: ior
    //   3294: aload #20
    //   3296: iconst_4
    //   3297: iaload
    //   3298: bipush #11
    //   3300: iushr
    //   3301: aload #20
    //   3303: iconst_4
    //   3304: iaload
    //   3305: bipush #21
    //   3307: ishl
    //   3308: ior
    //   3309: ixor
    //   3310: aload #20
    //   3312: iconst_4
    //   3313: iaload
    //   3314: bipush #25
    //   3316: iushr
    //   3317: aload #20
    //   3319: iconst_4
    //   3320: iaload
    //   3321: bipush #7
    //   3323: ishl
    //   3324: ior
    //   3325: ixor
    //   3326: iadd
    //   3327: aload #20
    //   3329: bipush #6
    //   3331: iaload
    //   3332: aload #20
    //   3334: iconst_4
    //   3335: iaload
    //   3336: aload #20
    //   3338: iconst_5
    //   3339: iaload
    //   3340: aload #20
    //   3342: bipush #6
    //   3344: iaload
    //   3345: ixor
    //   3346: iand
    //   3347: ixor
    //   3348: iadd
    //   3349: aload #6
    //   3351: iload #21
    //   3353: iaload
    //   3354: iadd
    //   3355: aload #19
    //   3357: iload #21
    //   3359: iaload
    //   3360: iadd
    //   3361: istore #22
    //   3363: aload #20
    //   3365: iconst_0
    //   3366: iaload
    //   3367: iconst_2
    //   3368: iushr
    //   3369: aload #20
    //   3371: iconst_0
    //   3372: iaload
    //   3373: bipush #30
    //   3375: ishl
    //   3376: ior
    //   3377: aload #20
    //   3379: iconst_0
    //   3380: iaload
    //   3381: bipush #13
    //   3383: iushr
    //   3384: aload #20
    //   3386: iconst_0
    //   3387: iaload
    //   3388: bipush #19
    //   3390: ishl
    //   3391: ior
    //   3392: ixor
    //   3393: aload #20
    //   3395: iconst_0
    //   3396: iaload
    //   3397: bipush #22
    //   3399: iushr
    //   3400: aload #20
    //   3402: iconst_0
    //   3403: iaload
    //   3404: bipush #10
    //   3406: ishl
    //   3407: ior
    //   3408: ixor
    //   3409: aload #20
    //   3411: iconst_0
    //   3412: iaload
    //   3413: aload #20
    //   3415: iconst_1
    //   3416: iaload
    //   3417: iand
    //   3418: aload #20
    //   3420: iconst_2
    //   3421: iaload
    //   3422: aload #20
    //   3424: iconst_0
    //   3425: iaload
    //   3426: aload #20
    //   3428: iconst_1
    //   3429: iaload
    //   3430: ior
    //   3431: iand
    //   3432: ior
    //   3433: iadd
    //   3434: istore #23
    //   3436: aload #20
    //   3438: iconst_3
    //   3439: dup2
    //   3440: iaload
    //   3441: iload #22
    //   3443: iadd
    //   3444: iastore
    //   3445: aload #20
    //   3447: bipush #7
    //   3449: iload #22
    //   3451: iload #23
    //   3453: iadd
    //   3454: iastore
    //   3455: aload #20
    //   3457: bipush #7
    //   3459: iaload
    //   3460: istore #22
    //   3462: aload #20
    //   3464: bipush #7
    //   3466: aload #20
    //   3468: bipush #6
    //   3470: iaload
    //   3471: iastore
    //   3472: aload #20
    //   3474: bipush #6
    //   3476: aload #20
    //   3478: iconst_5
    //   3479: iaload
    //   3480: iastore
    //   3481: aload #20
    //   3483: iconst_5
    //   3484: aload #20
    //   3486: iconst_4
    //   3487: iaload
    //   3488: iastore
    //   3489: aload #20
    //   3491: iconst_4
    //   3492: aload #20
    //   3494: iconst_3
    //   3495: iaload
    //   3496: iastore
    //   3497: aload #20
    //   3499: iconst_3
    //   3500: aload #20
    //   3502: iconst_2
    //   3503: iaload
    //   3504: iastore
    //   3505: aload #20
    //   3507: iconst_2
    //   3508: aload #20
    //   3510: iconst_1
    //   3511: iaload
    //   3512: iastore
    //   3513: aload #20
    //   3515: iconst_1
    //   3516: aload #20
    //   3518: iconst_0
    //   3519: iaload
    //   3520: iastore
    //   3521: aload #20
    //   3523: iconst_0
    //   3524: iload #22
    //   3526: iastore
    //   3527: iinc #21, 1
    //   3530: iload_2
    //   3531: ifeq -> 3039
    //   3534: iconst_0
    //   3535: istore #21
    //   3537: iload #21
    //   3539: bipush #8
    //   3541: if_icmpge -> 3564
    //   3544: aload #8
    //   3546: iload #21
    //   3548: dup2
    //   3549: iaload
    //   3550: aload #20
    //   3552: iload #21
    //   3554: iaload
    //   3555: iadd
    //   3556: iastore
    //   3557: iinc #21, 1
    //   3560: iload_2
    //   3561: ifeq -> 3537
    //   3564: iinc #13, 64
    //   3567: iinc #17, -64
    //   3570: iload_2
    //   3571: ifeq -> 2960
    //   3574: iload #17
    //   3576: ifle -> 3612
    //   3579: iconst_0
    //   3580: istore #19
    //   3582: iload #19
    //   3584: iload #17
    //   3586: if_icmpge -> 3612
    //   3589: aload #9
    //   3591: iload #12
    //   3593: iload #19
    //   3595: iadd
    //   3596: aload #5
    //   3598: iload #13
    //   3600: iload #19
    //   3602: iadd
    //   3603: baload
    //   3604: bastore
    //   3605: iinc #19, 1
    //   3608: iload_2
    //   3609: ifeq -> 3582
    //   3612: bipush #8
    //   3614: newarray byte
    //   3616: astore #19
    //   3618: aload #19
    //   3620: iconst_0
    //   3621: iload #14
    //   3623: bipush #24
    //   3625: iushr
    //   3626: i2b
    //   3627: bastore
    //   3628: aload #19
    //   3630: iconst_1
    //   3631: iload #14
    //   3633: bipush #16
    //   3635: iushr
    //   3636: i2b
    //   3637: bastore
    //   3638: aload #19
    //   3640: iconst_2
    //   3641: iload #14
    //   3643: bipush #8
    //   3645: iushr
    //   3646: i2b
    //   3647: bastore
    //   3648: aload #19
    //   3650: iconst_3
    //   3651: iload #14
    //   3653: i2b
    //   3654: bastore
    //   3655: aload #19
    //   3657: iconst_4
    //   3658: iload #15
    //   3660: bipush #24
    //   3662: iushr
    //   3663: i2b
    //   3664: bastore
    //   3665: aload #19
    //   3667: iconst_5
    //   3668: iload #15
    //   3670: bipush #16
    //   3672: iushr
    //   3673: i2b
    //   3674: bastore
    //   3675: aload #19
    //   3677: bipush #6
    //   3679: iload #15
    //   3681: bipush #8
    //   3683: iushr
    //   3684: i2b
    //   3685: bastore
    //   3686: aload #19
    //   3688: bipush #7
    //   3690: iload #15
    //   3692: i2b
    //   3693: bastore
    //   3694: bipush #8
    //   3696: istore #11
    //   3698: aload #7
    //   3700: iconst_0
    //   3701: iaload
    //   3702: bipush #63
    //   3704: iand
    //   3705: istore #12
    //   3707: bipush #64
    //   3709: iload #12
    //   3711: isub
    //   3712: istore #18
    //   3714: aload #7
    //   3716: iconst_0
    //   3717: dup2
    //   3718: iaload
    //   3719: iload #11
    //   3721: iadd
    //   3722: iastore
    //   3723: aload #7
    //   3725: iconst_0
    //   3726: dup2
    //   3727: iaload
    //   3728: iconst_m1
    //   3729: iand
    //   3730: iastore
    //   3731: aload #7
    //   3733: iconst_0
    //   3734: iaload
    //   3735: iload #11
    //   3737: if_icmpge -> 3755
    //   3740: aload #7
    //   3742: iconst_1
    //   3743: dup2
    //   3744: iaload
    //   3745: iconst_1
    //   3746: iadd
    //   3747: iastore
    //   3748: goto -> 3755
    //   3751: invokestatic a : (Ljava/lang/Throwable;)Ljava/lang/Throwable;
    //   3754: athrow
    //   3755: iload #12
    //   3757: ifle -> 4371
    //   3760: iload #11
    //   3762: iload #18
    //   3764: if_icmplt -> 4371
    //   3767: goto -> 3774
    //   3770: invokestatic a : (Ljava/lang/Throwable;)Ljava/lang/Throwable;
    //   3773: athrow
    //   3774: iconst_0
    //   3775: istore #20
    //   3777: iload #20
    //   3779: iload #18
    //   3781: if_icmpge -> 3804
    //   3784: aload #9
    //   3786: iload #12
    //   3788: iload #20
    //   3790: iadd
    //   3791: aload #19
    //   3793: iload #20
    //   3795: baload
    //   3796: bastore
    //   3797: iinc #20, 1
    //   3800: iload_2
    //   3801: ifeq -> 3777
    //   3804: bipush #64
    //   3806: newarray int
    //   3808: astore #20
    //   3810: bipush #8
    //   3812: newarray int
    //   3814: astore #21
    //   3816: iconst_0
    //   3817: istore #22
    //   3819: iload #22
    //   3821: bipush #8
    //   3823: if_icmpge -> 3843
    //   3826: aload #21
    //   3828: iload #22
    //   3830: aload #8
    //   3832: iload #22
    //   3834: iaload
    //   3835: iastore
    //   3836: iinc #22, 1
    //   3839: iload_2
    //   3840: ifeq -> 3819
    //   3843: iconst_0
    //   3844: istore #22
    //   3846: iload #22
    //   3848: bipush #64
    //   3850: if_icmpge -> 4341
    //   3853: iload #22
    //   3855: bipush #16
    //   3857: if_icmpge -> 3938
    //   3860: aload #20
    //   3862: iload #22
    //   3864: aload #9
    //   3866: iconst_4
    //   3867: iload #22
    //   3869: imul
    //   3870: baload
    //   3871: sipush #255
    //   3874: iand
    //   3875: bipush #24
    //   3877: ishl
    //   3878: aload #9
    //   3880: iconst_4
    //   3881: iload #22
    //   3883: imul
    //   3884: iconst_1
    //   3885: iadd
    //   3886: baload
    //   3887: sipush #255
    //   3890: iand
    //   3891: bipush #16
    //   3893: ishl
    //   3894: ior
    //   3895: aload #9
    //   3897: iconst_4
    //   3898: iload #22
    //   3900: imul
    //   3901: iconst_2
    //   3902: iadd
    //   3903: baload
    //   3904: sipush #255
    //   3907: iand
    //   3908: bipush #8
    //   3910: ishl
    //   3911: ior
    //   3912: aload #9
    //   3914: iconst_4
    //   3915: iload #22
    //   3917: imul
    //   3918: iconst_3
    //   3919: iadd
    //   3920: baload
    //   3921: sipush #255
    //   3924: iand
    //   3925: ior
    //   3926: iastore
    //   3927: iload_2
    //   3928: ifeq -> 4081
    //   3931: goto -> 3938
    //   3934: invokestatic a : (Ljava/lang/Throwable;)Ljava/lang/Throwable;
    //   3937: athrow
    //   3938: aload #20
    //   3940: iload #22
    //   3942: aload #20
    //   3944: iload #22
    //   3946: iconst_2
    //   3947: isub
    //   3948: iaload
    //   3949: bipush #17
    //   3951: iushr
    //   3952: aload #20
    //   3954: iload #22
    //   3956: iconst_2
    //   3957: isub
    //   3958: iaload
    //   3959: bipush #15
    //   3961: ishl
    //   3962: ior
    //   3963: aload #20
    //   3965: iload #22
    //   3967: iconst_2
    //   3968: isub
    //   3969: iaload
    //   3970: bipush #19
    //   3972: iushr
    //   3973: aload #20
    //   3975: iload #22
    //   3977: iconst_2
    //   3978: isub
    //   3979: iaload
    //   3980: bipush #13
    //   3982: ishl
    //   3983: ior
    //   3984: ixor
    //   3985: aload #20
    //   3987: iload #22
    //   3989: iconst_2
    //   3990: isub
    //   3991: iaload
    //   3992: bipush #10
    //   3994: iushr
    //   3995: ixor
    //   3996: aload #20
    //   3998: iload #22
    //   4000: bipush #7
    //   4002: isub
    //   4003: iaload
    //   4004: iadd
    //   4005: aload #20
    //   4007: iload #22
    //   4009: bipush #15
    //   4011: isub
    //   4012: iaload
    //   4013: bipush #7
    //   4015: iushr
    //   4016: aload #20
    //   4018: iload #22
    //   4020: bipush #15
    //   4022: isub
    //   4023: iaload
    //   4024: bipush #25
    //   4026: ishl
    //   4027: ior
    //   4028: aload #20
    //   4030: iload #22
    //   4032: bipush #15
    //   4034: isub
    //   4035: iaload
    //   4036: bipush #18
    //   4038: iushr
    //   4039: aload #20
    //   4041: iload #22
    //   4043: bipush #15
    //   4045: isub
    //   4046: iaload
    //   4047: bipush #14
    //   4049: ishl
    //   4050: ior
    //   4051: ixor
    //   4052: aload #20
    //   4054: iload #22
    //   4056: bipush #15
    //   4058: isub
    //   4059: iaload
    //   4060: iconst_3
    //   4061: iushr
    //   4062: ixor
    //   4063: iadd
    //   4064: aload #20
    //   4066: iload #22
    //   4068: bipush #16
    //   4070: isub
    //   4071: iaload
    //   4072: iadd
    //   4073: iastore
    //   4074: goto -> 4081
    //   4077: invokestatic a : (Ljava/lang/Throwable;)Ljava/lang/Throwable;
    //   4080: athrow
    //   4081: aload #21
    //   4083: bipush #7
    //   4085: iaload
    //   4086: aload #21
    //   4088: iconst_4
    //   4089: iaload
    //   4090: bipush #6
    //   4092: iushr
    //   4093: aload #21
    //   4095: iconst_4
    //   4096: iaload
    //   4097: bipush #26
    //   4099: ishl
    //   4100: ior
    //   4101: aload #21
    //   4103: iconst_4
    //   4104: iaload
    //   4105: bipush #11
    //   4107: iushr
    //   4108: aload #21
    //   4110: iconst_4
    //   4111: iaload
    //   4112: bipush #21
    //   4114: ishl
    //   4115: ior
    //   4116: ixor
    //   4117: aload #21
    //   4119: iconst_4
    //   4120: iaload
    //   4121: bipush #25
    //   4123: iushr
    //   4124: aload #21
    //   4126: iconst_4
    //   4127: iaload
    //   4128: bipush #7
    //   4130: ishl
    //   4131: ior
    //   4132: ixor
    //   4133: iadd
    //   4134: aload #21
    //   4136: bipush #6
    //   4138: iaload
    //   4139: aload #21
    //   4141: iconst_4
    //   4142: iaload
    //   4143: aload #21
    //   4145: iconst_5
    //   4146: iaload
    //   4147: aload #21
    //   4149: bipush #6
    //   4151: iaload
    //   4152: ixor
    //   4153: iand
    //   4154: ixor
    //   4155: iadd
    //   4156: aload #6
    //   4158: iload #22
    //   4160: iaload
    //   4161: iadd
    //   4162: aload #20
    //   4164: iload #22
    //   4166: iaload
    //   4167: iadd
    //   4168: istore #23
    //   4170: aload #21
    //   4172: iconst_0
    //   4173: iaload
    //   4174: iconst_2
    //   4175: iushr
    //   4176: aload #21
    //   4178: iconst_0
    //   4179: iaload
    //   4180: bipush #30
    //   4182: ishl
    //   4183: ior
    //   4184: aload #21
    //   4186: iconst_0
    //   4187: iaload
    //   4188: bipush #13
    //   4190: iushr
    //   4191: aload #21
    //   4193: iconst_0
    //   4194: iaload
    //   4195: bipush #19
    //   4197: ishl
    //   4198: ior
    //   4199: ixor
    //   4200: aload #21
    //   4202: iconst_0
    //   4203: iaload
    //   4204: bipush #22
    //   4206: iushr
    //   4207: aload #21
    //   4209: iconst_0
    //   4210: iaload
    //   4211: bipush #10
    //   4213: ishl
    //   4214: ior
    //   4215: ixor
    //   4216: aload #21
    //   4218: iconst_0
    //   4219: iaload
    //   4220: aload #21
    //   4222: iconst_1
    //   4223: iaload
    //   4224: iand
    //   4225: aload #21
    //   4227: iconst_2
    //   4228: iaload
    //   4229: aload #21
    //   4231: iconst_0
    //   4232: iaload
    //   4233: aload #21
    //   4235: iconst_1
    //   4236: iaload
    //   4237: ior
    //   4238: iand
    //   4239: ior
    //   4240: iadd
    //   4241: istore #24
    //   4243: aload #21
    //   4245: iconst_3
    //   4246: dup2
    //   4247: iaload
    //   4248: iload #23
    //   4250: iadd
    //   4251: iastore
    //   4252: aload #21
    //   4254: bipush #7
    //   4256: iload #23
    //   4258: iload #24
    //   4260: iadd
    //   4261: iastore
    //   4262: aload #21
    //   4264: bipush #7
    //   4266: iaload
    //   4267: istore #23
    //   4269: aload #21
    //   4271: bipush #7
    //   4273: aload #21
    //   4275: bipush #6
    //   4277: iaload
    //   4278: iastore
    //   4279: aload #21
    //   4281: bipush #6
    //   4283: aload #21
    //   4285: iconst_5
    //   4286: iaload
    //   4287: iastore
    //   4288: aload #21
    //   4290: iconst_5
    //   4291: aload #21
    //   4293: iconst_4
    //   4294: iaload
    //   4295: iastore
    //   4296: aload #21
    //   4298: iconst_4
    //   4299: aload #21
    //   4301: iconst_3
    //   4302: iaload
    //   4303: iastore
    //   4304: aload #21
    //   4306: iconst_3
    //   4307: aload #21
    //   4309: iconst_2
    //   4310: iaload
    //   4311: iastore
    //   4312: aload #21
    //   4314: iconst_2
    //   4315: aload #21
    //   4317: iconst_1
    //   4318: iaload
    //   4319: iastore
    //   4320: aload #21
    //   4322: iconst_1
    //   4323: aload #21
    //   4325: iconst_0
    //   4326: iaload
    //   4327: iastore
    //   4328: aload #21
    //   4330: iconst_0
    //   4331: iload #23
    //   4333: iastore
    //   4334: iinc #22, 1
    //   4337: iload_2
    //   4338: ifeq -> 3846
    //   4341: iconst_0
    //   4342: istore #22
    //   4344: iload #22
    //   4346: bipush #8
    //   4348: if_icmpge -> 4371
    //   4351: aload #8
    //   4353: iload #22
    //   4355: dup2
    //   4356: iaload
    //   4357: aload #21
    //   4359: iload #22
    //   4361: iaload
    //   4362: iadd
    //   4363: iastore
    //   4364: iinc #22, 1
    //   4367: iload_2
    //   4368: ifeq -> 4344
    //   4371: bipush #32
    //   4373: newarray byte
    //   4375: astore #4
    //   4377: aload #4
    //   4379: iconst_0
    //   4380: aload #8
    //   4382: iconst_0
    //   4383: iaload
    //   4384: bipush #24
    //   4386: iushr
    //   4387: i2b
    //   4388: bastore
    //   4389: aload #4
    //   4391: iconst_1
    //   4392: aload #8
    //   4394: iconst_0
    //   4395: iaload
    //   4396: bipush #16
    //   4398: iushr
    //   4399: i2b
    //   4400: bastore
    //   4401: aload #4
    //   4403: iconst_2
    //   4404: aload #8
    //   4406: iconst_0
    //   4407: iaload
    //   4408: bipush #8
    //   4410: iushr
    //   4411: i2b
    //   4412: bastore
    //   4413: aload #4
    //   4415: iconst_3
    //   4416: aload #8
    //   4418: iconst_0
    //   4419: iaload
    //   4420: i2b
    //   4421: bastore
    //   4422: aload #4
    //   4424: iconst_4
    //   4425: aload #8
    //   4427: iconst_1
    //   4428: iaload
    //   4429: bipush #24
    //   4431: iushr
    //   4432: i2b
    //   4433: bastore
    //   4434: aload #4
    //   4436: iconst_5
    //   4437: aload #8
    //   4439: iconst_1
    //   4440: iaload
    //   4441: bipush #16
    //   4443: iushr
    //   4444: i2b
    //   4445: bastore
    //   4446: aload #4
    //   4448: bipush #6
    //   4450: aload #8
    //   4452: iconst_1
    //   4453: iaload
    //   4454: bipush #8
    //   4456: iushr
    //   4457: i2b
    //   4458: bastore
    //   4459: aload #4
    //   4461: bipush #7
    //   4463: aload #8
    //   4465: iconst_1
    //   4466: iaload
    //   4467: i2b
    //   4468: bastore
    //   4469: aload #4
    //   4471: bipush #8
    //   4473: aload #8
    //   4475: iconst_2
    //   4476: iaload
    //   4477: bipush #24
    //   4479: iushr
    //   4480: i2b
    //   4481: bastore
    //   4482: aload #4
    //   4484: bipush #9
    //   4486: aload #8
    //   4488: iconst_2
    //   4489: iaload
    //   4490: bipush #16
    //   4492: iushr
    //   4493: i2b
    //   4494: bastore
    //   4495: aload #4
    //   4497: bipush #10
    //   4499: aload #8
    //   4501: iconst_2
    //   4502: iaload
    //   4503: bipush #8
    //   4505: iushr
    //   4506: i2b
    //   4507: bastore
    //   4508: aload #4
    //   4510: bipush #11
    //   4512: aload #8
    //   4514: iconst_2
    //   4515: iaload
    //   4516: i2b
    //   4517: bastore
    //   4518: aload #4
    //   4520: bipush #12
    //   4522: aload #8
    //   4524: iconst_3
    //   4525: iaload
    //   4526: bipush #24
    //   4528: iushr
    //   4529: i2b
    //   4530: bastore
    //   4531: aload #4
    //   4533: bipush #13
    //   4535: aload #8
    //   4537: iconst_3
    //   4538: iaload
    //   4539: bipush #16
    //   4541: iushr
    //   4542: i2b
    //   4543: bastore
    //   4544: aload #4
    //   4546: bipush #14
    //   4548: aload #8
    //   4550: iconst_3
    //   4551: iaload
    //   4552: bipush #8
    //   4554: iushr
    //   4555: i2b
    //   4556: bastore
    //   4557: aload #4
    //   4559: bipush #15
    //   4561: aload #8
    //   4563: iconst_3
    //   4564: iaload
    //   4565: i2b
    //   4566: bastore
    //   4567: aload #4
    //   4569: bipush #16
    //   4571: aload #8
    //   4573: iconst_4
    //   4574: iaload
    //   4575: bipush #24
    //   4577: iushr
    //   4578: i2b
    //   4579: bastore
    //   4580: aload #4
    //   4582: bipush #17
    //   4584: aload #8
    //   4586: iconst_4
    //   4587: iaload
    //   4588: bipush #16
    //   4590: iushr
    //   4591: i2b
    //   4592: bastore
    //   4593: aload #4
    //   4595: bipush #18
    //   4597: aload #8
    //   4599: iconst_4
    //   4600: iaload
    //   4601: bipush #8
    //   4603: iushr
    //   4604: i2b
    //   4605: bastore
    //   4606: aload #4
    //   4608: bipush #19
    //   4610: aload #8
    //   4612: iconst_4
    //   4613: iaload
    //   4614: i2b
    //   4615: bastore
    //   4616: aload #4
    //   4618: bipush #20
    //   4620: aload #8
    //   4622: iconst_5
    //   4623: iaload
    //   4624: bipush #24
    //   4626: iushr
    //   4627: i2b
    //   4628: bastore
    //   4629: aload #4
    //   4631: bipush #21
    //   4633: aload #8
    //   4635: iconst_5
    //   4636: iaload
    //   4637: bipush #16
    //   4639: iushr
    //   4640: i2b
    //   4641: bastore
    //   4642: aload #4
    //   4644: bipush #22
    //   4646: aload #8
    //   4648: iconst_5
    //   4649: iaload
    //   4650: bipush #8
    //   4652: iushr
    //   4653: i2b
    //   4654: bastore
    //   4655: aload #4
    //   4657: bipush #23
    //   4659: aload #8
    //   4661: iconst_5
    //   4662: iaload
    //   4663: i2b
    //   4664: bastore
    //   4665: aload #4
    //   4667: bipush #24
    //   4669: aload #8
    //   4671: bipush #6
    //   4673: iaload
    //   4674: bipush #24
    //   4676: iushr
    //   4677: i2b
    //   4678: bastore
    //   4679: aload #4
    //   4681: bipush #25
    //   4683: aload #8
    //   4685: bipush #6
    //   4687: iaload
    //   4688: bipush #16
    //   4690: iushr
    //   4691: i2b
    //   4692: bastore
    //   4693: aload #4
    //   4695: bipush #26
    //   4697: aload #8
    //   4699: bipush #6
    //   4701: iaload
    //   4702: bipush #8
    //   4704: iushr
    //   4705: i2b
    //   4706: bastore
    //   4707: aload #4
    //   4709: bipush #27
    //   4711: aload #8
    //   4713: bipush #6
    //   4715: iaload
    //   4716: i2b
    //   4717: bastore
    //   4718: aload #4
    //   4720: bipush #28
    //   4722: aload #8
    //   4724: bipush #7
    //   4726: iaload
    //   4727: bipush #24
    //   4729: iushr
    //   4730: i2b
    //   4731: bastore
    //   4732: aload #4
    //   4734: bipush #29
    //   4736: aload #8
    //   4738: bipush #7
    //   4740: iaload
    //   4741: bipush #16
    //   4743: iushr
    //   4744: i2b
    //   4745: bastore
    //   4746: aload #4
    //   4748: bipush #30
    //   4750: aload #8
    //   4752: bipush #7
    //   4754: iaload
    //   4755: bipush #8
    //   4757: iushr
    //   4758: i2b
    //   4759: bastore
    //   4760: aload #4
    //   4762: bipush #31
    //   4764: aload #8
    //   4766: bipush #7
    //   4768: iaload
    //   4769: i2b
    //   4770: bastore
    //   4771: getstatic burp/Zlc5.Z_ : Ljava/lang/String;
    //   4774: getstatic burp/Zsm3.ZC : Ljava/lang/Object;
    //   4777: checkcast java/math/BigInteger
    //   4780: invokevirtual intValue : ()I
    //   4783: bipush #32
    //   4785: irem
    //   4786: invokestatic abs : (I)I
    //   4789: invokevirtual charAt : (I)C
    //   4792: getstatic burp/Zva.Zi : Ljava/lang/String;
    //   4795: getstatic burp/Zry9.Zw : Ljava/lang/Object;
    //   4798: checkcast java/math/BigInteger
    //   4801: invokevirtual intValue : ()I
    //   4804: bipush #32
    //   4806: irem
    //   4807: invokestatic abs : (I)I
    //   4810: invokevirtual charAt : (I)C
    //   4813: if_icmpgt -> 4920
    //   4816: getstatic burp/Zmd.Zf : Ljava/lang/String;
    //   4819: getstatic burp/Zg7z.ZV : Ljava/lang/Object;
    //   4822: checkcast java/math/BigInteger
    //   4825: invokevirtual intValue : ()I
    //   4828: bipush #32
    //   4830: irem
    //   4831: invokestatic abs : (I)I
    //   4834: invokevirtual charAt : (I)C
    //   4837: getstatic burp/Zm14.ZE : Ljava/lang/String;
    //   4840: getstatic burp/Zr_w.ZK : Ljava/lang/Object;
    //   4843: checkcast java/math/BigInteger
    //   4846: invokevirtual intValue : ()I
    //   4849: bipush #32
    //   4851: irem
    //   4852: invokestatic abs : (I)I
    //   4855: invokevirtual charAt : (I)C
    //   4858: if_icmple -> 4920
    //   4861: goto -> 4868
    //   4864: invokestatic a : (Ljava/lang/Throwable;)Ljava/lang/Throwable;
    //   4867: athrow
    //   4868: getstatic burp/Zbnb.Zd : Ljava/lang/String;
    //   4871: getstatic burp/Zmcq.Zh : Ljava/lang/Object;
    //   4874: checkcast java/math/BigInteger
    //   4877: invokevirtual intValue : ()I
    //   4880: bipush #32
    //   4882: irem
    //   4883: invokestatic abs : (I)I
    //   4886: invokevirtual charAt : (I)C
    //   4889: getstatic burp/Zbzj.Zw : Ljava/lang/String;
    //   4892: getstatic burp/Zgdj.ZT : Ljava/lang/Object;
    //   4895: checkcast java/math/BigInteger
    //   4898: invokevirtual intValue : ()I
    //   4901: bipush #32
    //   4903: irem
    //   4904: invokestatic abs : (I)I
    //   4907: invokevirtual charAt : (I)C
    //   4910: if_icmpgt -> 4928
    //   4913: goto -> 4920
    //   4916: invokestatic a : (Ljava/lang/Throwable;)Ljava/lang/Throwable;
    //   4919: athrow
    //   4920: iconst_1
    //   4921: goto -> 4929
    //   4924: invokestatic a : (Ljava/lang/Throwable;)Ljava/lang/Throwable;
    //   4927: athrow
    //   4928: iconst_0
    //   4929: ireturn
    //   4930: astore_3
    //   4931: new java/lang/Exception
    //   4934: dup
    //   4935: aload_3
    //   4936: invokevirtual getMessage : ()Ljava/lang/String;
    //   4939: invokespecial <init> : (Ljava/lang/String;)V
    //   4942: athrow
    // Exception table:
    //   from	to	target	type
    //   4	4929	4930	java/lang/Throwable
    //   100	114	114	java/lang/Throwable
    //   125	138	141	java/lang/Throwable
    //   130	153	156	java/lang/Throwable
    //   145	171	174	java/lang/Throwable
    //   160	201	204	java/lang/Throwable
    //   264	291	294	java/lang/Throwable
    //   281	309	312	java/lang/Throwable
    //   298	339	342	java/lang/Throwable
    //   316	350	350	java/lang/Throwable
    //   361	377	380	java/lang/Throwable
    //   426	440	440	java/lang/Throwable
    //   451	464	467	java/lang/Throwable
    //   456	479	482	java/lang/Throwable
    //   471	497	500	java/lang/Throwable
    //   486	527	530	java/lang/Throwable
    //   590	617	620	java/lang/Throwable
    //   607	638	641	java/lang/Throwable
    //   624	668	671	java/lang/Throwable
    //   645	679	679	java/lang/Throwable
    //   690	706	709	java/lang/Throwable
    //   1514	1548	1551	java/lang/Throwable
    //   1643	1721	1724	java/lang/Throwable
    //   1650	1864	1867	java/lang/Throwable
    //   2241	2256	2256	java/lang/Throwable
    //   2283	2317	2320	java/lang/Throwable
    //   2327	2339	2342	java/lang/Throwable
    //   2425	2503	2506	java/lang/Throwable
    //   2432	2646	2649	java/lang/Throwable
    //   3046	3124	3127	java/lang/Throwable
    //   3053	3267	3270	java/lang/Throwable
    //   3714	3748	3751	java/lang/Throwable
    //   3755	3767	3770	java/lang/Throwable
    //   3853	3931	3934	java/lang/Throwable
    //   3860	4074	4077	java/lang/Throwable
    //   4377	4861	4864	java/lang/Throwable
    //   4816	4913	4916	java/lang/Throwable
    //   4868	4924	4924	java/lang/Throwable
  }
  
  static void ZQ(Object[] paramArrayOfObject, Object paramObject) throws Throwable {}
  
  static {
    // Byte code:
    //   0: bipush #12
    //   2: anewarray java/lang/String
    //   5: astore #5
    //   7: iconst_0
    //   8: istore_3
    //   9: ldc 'Lw\\t+\\tGM^3\\b:fn5xm)w4?>TV[\\n&V*[.-4\\t\0NP:M7!xF^AmUha!:eW .ubjHg(KF$hx-+ e9<_G:V>7b\W\\\t~p\\nN#\\tqN\\fD\\nv'
    //   11: dup
    //   12: astore_2
    //   13: invokevirtual length : ()I
    //   16: istore #4
    //   18: bipush #9
    //   20: istore_1
    //   21: iconst_m1
    //   22: istore_0
    //   23: bipush #60
    //   25: iinc #0, 1
    //   28: aload_2
    //   29: iload_0
    //   30: dup
    //   31: iload_1
    //   32: iadd
    //   33: invokevirtual substring : (II)Ljava/lang/String;
    //   36: iconst_m1
    //   37: goto -> 142
    //   40: aload #5
    //   42: swap
    //   43: iload_3
    //   44: iinc #3, 1
    //   47: swap
    //   48: aastore
    //   49: iload_0
    //   50: iload_1
    //   51: iadd
    //   52: dup
    //   53: istore_0
    //   54: iload #4
    //   56: if_icmpge -> 68
    //   59: aload_2
    //   60: iload_0
    //   61: invokevirtual charAt : (I)C
    //   64: istore_1
    //   65: goto -> 23
    //   68: ldc 'y .-;NN@0eJ'
    //   70: dup
    //   71: astore_2
    //   72: invokevirtual length : ()I
    //   75: istore #4
    //   77: iconst_4
    //   78: istore_1
    //   79: iconst_m1
    //   80: istore_0
    //   81: bipush #98
    //   83: iinc #0, 1
    //   86: aload_2
    //   87: iload_0
    //   88: dup
    //   89: iload_1
    //   90: iadd
    //   91: invokevirtual substring : (II)Ljava/lang/String;
    //   94: iconst_0
    //   95: goto -> 142
    //   98: aload #5
    //   100: swap
    //   101: iload_3
    //   102: iinc #3, 1
    //   105: swap
    //   106: aastore
    //   107: iload_0
    //   108: iload_1
    //   109: iadd
    //   110: dup
    //   111: istore_0
    //   112: iload #4
    //   114: if_icmpge -> 126
    //   117: aload_2
    //   118: iload_0
    //   119: invokevirtual charAt : (I)C
    //   122: istore_1
    //   123: goto -> 81
    //   126: aload #5
    //   128: putstatic burp/Zeoi.a : [Ljava/lang/String;
    //   131: bipush #12
    //   133: anewarray java/lang/String
    //   136: putstatic burp/Zeoi.b : [Ljava/lang/String;
    //   139: goto -> 300
    //   142: dup_x2
    //   143: pop
    //   144: invokevirtual toCharArray : ()[C
    //   147: dup_x1
    //   148: arraylength
    //   149: dup_x2
    //   150: pop
    //   151: iconst_0
    //   152: istore #6
    //   154: dup2_x1
    //   155: pop2
    //   156: dup_x2
    //   157: iconst_1
    //   158: if_icmpgt -> 260
    //   161: dup2
    //   162: swap
    //   163: iload #6
    //   165: dup2_x1
    //   166: caload
    //   167: swap
    //   168: iload #6
    //   170: bipush #7
    //   172: irem
    //   173: tableswitch default -> 242, 0 -> 212, 1 -> 217, 2 -> 222, 3 -> 227, 4 -> 232, 5 -> 237
    //   212: bipush #14
    //   214: goto -> 244
    //   217: bipush #101
    //   219: goto -> 244
    //   222: bipush #16
    //   224: goto -> 244
    //   227: bipush #121
    //   229: goto -> 244
    //   232: bipush #74
    //   234: goto -> 244
    //   237: bipush #117
    //   239: goto -> 244
    //   242: bipush #35
    //   244: ixor
    //   245: ixor
    //   246: i2c
    //   247: castore
    //   248: iinc #6, 1
    //   251: dup
    //   252: ifne -> 260
    //   255: dup2
    //   256: dup_x1
    //   257: goto -> 165
    //   260: dup2_x1
    //   261: pop2
    //   262: dup_x2
    //   263: iload #6
    //   265: if_icmpgt -> 161
    //   268: pop
    //   269: new java/lang/String
    //   272: dup_x1
    //   273: swap
    //   274: invokespecial <init> : ([C)V
    //   277: invokevirtual intern : ()Ljava/lang/String;
    //   280: swap
    //   281: pop
    //   282: swap
    //   283: tableswitch default -> 40, 0 -> 98
    //   300: new java/math/BigInteger
    //   303: dup
    //   304: sipush #-30128
    //   307: sipush #31636
    //   310: invokestatic a : (II)Ljava/lang/String;
    //   313: invokespecial <init> : (Ljava/lang/String;)V
    //   316: putstatic burp/Zeoi.ZE : Ljava/lang/Object;
    //   319: sipush #-30123
    //   322: sipush #17941
    //   325: invokestatic a : (II)Ljava/lang/String;
    //   328: putstatic burp/Zeoi.Zh : Ljava/lang/String;
    //   331: return
  }
  
  private static Throwable a(Throwable paramThrowable) {
    return paramThrowable;
  }
  
  private static String a(int paramInt1, int paramInt2) {
    int i = (paramInt1 ^ 0xFFFF8A53) & 0xFFFF;
    if (b[i] == null) {
      char[] arrayOfChar = a[i].toCharArray();
      switch (arrayOfChar[0] & 0xFF) {
        case 0:
        
        case 1:
        
        case 2:
        
        case 3:
        
        case 4:
        
        case 5:
        
        case 6:
        
        case 7:
        
        case 8:
        
        case 9:
        
        case 10:
        
        case 11:
        
        case 12:
        
        case 13:
        
        case 14:
        
        case 15:
        
        case 16:
        
        case 17:
        
        case 18:
        
        case 19:
        
        case 20:
        
        case 21:
        
        case 22:
        
        case 23:
        
        case 24:
        
        case 25:
        
        case 26:
        
        case 27:
        
        case 28:
        
        case 29:
        
        case 30:
        
        case 31:
        
        case 32:
        
        case 33:
        
        case 34:
        
        case 35:
        
        case 36:
        
        case 37:
        
        case 38:
        
        case 39:
        
        case 40:
        
        case 41:
        
        case 42:
        
        case 43:
        
        case 44:
        
        case 45:
        
        case 46:
        
        case 47:
        
        case 48:
        
        case 49:
        
        case 50:
        
        case 51:
        
        case 52:
        
        case 53:
        
        case 54:
        
        case 55:
        
        case 56:
        
        case 57:
        
        case 58:
        
        case 59:
        
        case 60:
        
        case 61:
        
        case 62:
        
        case 63:
        
        case 64:
        
        case 65:
        
        case 66:
        
        case 67:
        
        case 68:
        
        case 69:
        
        case 70:
        
        case 71:
        
        case 72:
        
        case 73:
        
        case 74:
        
        case 75:
        
        case 76:
        
        case 77:
        
        case 78:
        
        case 79:
        
        case 80:
        
        case 81:
        
        case 82:
        
        case 83:
        
        case 84:
        
        case 85:
        
        case 86:
        
        case 87:
        
        case 88:
        
        case 89:
        
        case 90:
        
        case 91:
        
        case 92:
        
        case 93:
        
        case 94:
        
        case 95:
        
        case 96:
        
        case 97:
        
        case 98:
        
        case 99:
        
        case 100:
        
        case 101:
        
        case 102:
        
        case 103:
        
        case 104:
        
        case 105:
        
        case 106:
        
        case 107:
        
        case 108:
        
        case 109:
        
        case 110:
        
        case 111:
        
        case 112:
        
        case 113:
        
        case 114:
        
        case 115:
        
        case 116:
        
        case 117:
        
        case 118:
        
        case 119:
        
        case 120:
        
        case 121:
        
        case 122:
        
        case 123:
        
        case 124:
        
        case 125:
        
        case 126:
        
        case 127:
        
        case 128:
        
        case 129:
        
        case 130:
        
        case 131:
        
        case 132:
        
        case 133:
        
        case 134:
        
        case 135:
        
        case 136:
        
        case 137:
        
        case 138:
        
        case 139:
        
        case 140:
        
        case 141:
        
        case 142:
        
        case 143:
        
        case 144:
        
        case 145:
        
        case 146:
        
        case 147:
        
        case 148:
        
        case 149:
        
        case 150:
        
        case 151:
        
        case 152:
        
        case 153:
        
        case 154:
        
        case 155:
        
        case 156:
        
        case 157:
        
        case 158:
        
        case 159:
        
        case 160:
        
        case 161:
        
        case 162:
        
        case 163:
        
        case 164:
        
        case 165:
        
        case 166:
        
        case 167:
        
        case 168:
        
        case 169:
        
        case 170:
        
        case 171:
        
        case 172:
        
        case 173:
        
        case 174:
        
        case 175:
        
        case 176:
        
        case 177:
        
        case 178:
        
        case 179:
        
        case 180:
        
        case 181:
        
        case 182:
        
        case 183:
        
        case 184:
        
        case 185:
        
        case 186:
        
        case 187:
        
        case 188:
        
        case 189:
        
        case 190:
        
        case 191:
        
        case 192:
        
        case 193:
        
        case 194:
        
        case 195:
        
        case 196:
        
        case 197:
        
        case 198:
        
        case 199:
        
        case 200:
        
        case 201:
        
        case 202:
        
        case 203:
        
        case 204:
        
        case 205:
        
        case 206:
        
        case 207:
        
        case 208:
        
        case 209:
        
        case 210:
        
        case 211:
        
        case 212:
        
        case 213:
        
        case 214:
        
        case 215:
        
        case 216:
        
        case 217:
        
        case 218:
        
        case 219:
        
        case 220:
        
        case 221:
        
        case 222:
        
        case 223:
        
        case 224:
        
        case 225:
        
        case 226:
        
        case 227:
        
        case 228:
        
        case 229:
        
        case 230:
        
        case 231:
        
        case 232:
        
        case 233:
        
        case 234:
        
        case 235:
        
        case 236:
        
        case 237:
        
        case 238:
        
        case 239:
        
        case 240:
        
        case 241:
        
        case 242:
        
        case 243:
        
        case 244:
        
        case 245:
        
        case 246:
        
        case 247:
        
        case 248:
        
        case 249:
        
        case 250:
        
        case 251:
        
        case 252:
        
        case 253:
        
        case 254:
        
        default:
          break;
      } 
      byte b1 = 86;
      int j = (paramInt2 & 0xFF) - b1;
      if (j < 0)
        j += 256; 
      int k = ((paramInt2 & 0xFFFF) >>> 8) - b1;
      if (k < 0)
        k += 256; 
      for (byte b2 = 0; b2 < arrayOfChar.length; b2++) {
        int m = b2 % 2;
        if (m == 0) {
          arrayOfChar[b2] = (char)(arrayOfChar[b2] ^ j);
          j = ((j >>> 3 | j << 5) ^ arrayOfChar[b2]) & 0xFF;
        } else {
          arrayOfChar[b2] = (char)(arrayOfChar[b2] ^ k);
          k = ((k >>> 3 | k << 5) ^ arrayOfChar[b2]) & 0xFF;
        } 
      } 
      b[i] = (new String(arrayOfChar)).intern();
    } 
    return b[i];
  }
}


/* Location:              C:\Program Files\BurpSuitePro\burpsuite_pro.jar!\burp\Zeoi.class
 * Java compiler version: 21 (65.0)
 * JD-Core Version:       1.1.3
 */