package burp;

import java.math.BigInteger;

class Zep8 extends ClassLoader {
  static String ZC;
  
  static Object Zs;
  
  private static final String[] a;
  
  private static final String[] b;
  
  static void ZN(Object paramObject) {
    Zgz1.Zs = a(-31915, -10874);
    Zgz1.ZX = new BigInteger(a(-31924, 17876));
    boolean bool = Zt2e.ZK();
    try {
      try {
        if (Zgl4.ZX.charAt(Math.abs(((BigInteger)Zr64.ZN).intValue() % 32)) <= Zvof.ZR.charAt(Math.abs(((BigInteger)Zgl4.Zb).intValue() % 32))) {
          try {
            Zk7b.ZX(Class.forName(a(-31929, -16415)));
            if (bool)
              Zd0.Zx(Class.forName(a(-31933, -10562))); 
          } catch (Throwable throwable) {
            throw a(null);
          } 
          return;
        } 
      } catch (Throwable throwable) {
        throw a(null);
      } 
      Zd0.Zx(Class.forName(a(-31933, -10562)));
    } catch (Throwable throwable) {}
  }
  
  static void ZX(Object[] paramArrayOfObject, Object paramObject) throws Throwable {}
  
  static boolean Zm(Object[] paramArrayOfObject, Object paramObject) throws Throwable {
    // Byte code:
    //   0: invokestatic ZK : ()Z
    //   3: istore_2
    //   4: getstatic burp/Zluk.Zz : Ljava/lang/Object;
    //   7: checkcast java/math/BigInteger
    //   10: invokevirtual toByteArray : ()[B
    //   13: astore_3
    //   14: bipush #64
    //   16: newarray byte
    //   18: dup
    //   19: iconst_0
    //   20: bipush #-128
    //   22: bastore
    //   23: dup
    //   24: iconst_1
    //   25: iconst_0
    //   26: bastore
    //   27: dup
    //   28: iconst_2
    //   29: iconst_0
    //   30: bastore
    //   31: dup
    //   32: iconst_3
    //   33: iconst_0
    //   34: bastore
    //   35: dup
    //   36: iconst_4
    //   37: iconst_0
    //   38: bastore
    //   39: dup
    //   40: iconst_5
    //   41: iconst_0
    //   42: bastore
    //   43: dup
    //   44: bipush #6
    //   46: iconst_0
    //   47: bastore
    //   48: dup
    //   49: bipush #7
    //   51: iconst_0
    //   52: bastore
    //   53: dup
    //   54: bipush #8
    //   56: iconst_0
    //   57: bastore
    //   58: dup
    //   59: bipush #9
    //   61: iconst_0
    //   62: bastore
    //   63: dup
    //   64: bipush #10
    //   66: iconst_0
    //   67: bastore
    //   68: dup
    //   69: bipush #11
    //   71: iconst_0
    //   72: bastore
    //   73: dup
    //   74: bipush #12
    //   76: iconst_0
    //   77: bastore
    //   78: dup
    //   79: bipush #13
    //   81: iconst_0
    //   82: bastore
    //   83: dup
    //   84: bipush #14
    //   86: iconst_0
    //   87: bastore
    //   88: dup
    //   89: bipush #15
    //   91: iconst_0
    //   92: bastore
    //   93: dup
    //   94: bipush #16
    //   96: iconst_0
    //   97: bastore
    //   98: dup
    //   99: bipush #17
    //   101: iconst_0
    //   102: bastore
    //   103: dup
    //   104: bipush #18
    //   106: iconst_0
    //   107: bastore
    //   108: dup
    //   109: bipush #19
    //   111: iconst_0
    //   112: bastore
    //   113: dup
    //   114: bipush #20
    //   116: iconst_0
    //   117: bastore
    //   118: dup
    //   119: bipush #21
    //   121: iconst_0
    //   122: bastore
    //   123: dup
    //   124: bipush #22
    //   126: iconst_0
    //   127: bastore
    //   128: dup
    //   129: bipush #23
    //   131: iconst_0
    //   132: bastore
    //   133: dup
    //   134: bipush #24
    //   136: iconst_0
    //   137: bastore
    //   138: dup
    //   139: bipush #25
    //   141: iconst_0
    //   142: bastore
    //   143: dup
    //   144: bipush #26
    //   146: iconst_0
    //   147: bastore
    //   148: dup
    //   149: bipush #27
    //   151: iconst_0
    //   152: bastore
    //   153: dup
    //   154: bipush #28
    //   156: iconst_0
    //   157: bastore
    //   158: dup
    //   159: bipush #29
    //   161: iconst_0
    //   162: bastore
    //   163: dup
    //   164: bipush #30
    //   166: iconst_0
    //   167: bastore
    //   168: dup
    //   169: bipush #31
    //   171: iconst_0
    //   172: bastore
    //   173: dup
    //   174: bipush #32
    //   176: iconst_0
    //   177: bastore
    //   178: dup
    //   179: bipush #33
    //   181: iconst_0
    //   182: bastore
    //   183: dup
    //   184: bipush #34
    //   186: iconst_0
    //   187: bastore
    //   188: dup
    //   189: bipush #35
    //   191: iconst_0
    //   192: bastore
    //   193: dup
    //   194: bipush #36
    //   196: iconst_0
    //   197: bastore
    //   198: dup
    //   199: bipush #37
    //   201: iconst_0
    //   202: bastore
    //   203: dup
    //   204: bipush #38
    //   206: iconst_0
    //   207: bastore
    //   208: dup
    //   209: bipush #39
    //   211: iconst_0
    //   212: bastore
    //   213: dup
    //   214: bipush #40
    //   216: iconst_0
    //   217: bastore
    //   218: dup
    //   219: bipush #41
    //   221: iconst_0
    //   222: bastore
    //   223: dup
    //   224: bipush #42
    //   226: iconst_0
    //   227: bastore
    //   228: dup
    //   229: bipush #43
    //   231: iconst_0
    //   232: bastore
    //   233: dup
    //   234: bipush #44
    //   236: iconst_0
    //   237: bastore
    //   238: dup
    //   239: bipush #45
    //   241: iconst_0
    //   242: bastore
    //   243: dup
    //   244: bipush #46
    //   246: iconst_0
    //   247: bastore
    //   248: dup
    //   249: bipush #47
    //   251: iconst_0
    //   252: bastore
    //   253: dup
    //   254: bipush #48
    //   256: iconst_0
    //   257: bastore
    //   258: dup
    //   259: bipush #49
    //   261: iconst_0
    //   262: bastore
    //   263: dup
    //   264: bipush #50
    //   266: iconst_0
    //   267: bastore
    //   268: dup
    //   269: bipush #51
    //   271: iconst_0
    //   272: bastore
    //   273: dup
    //   274: bipush #52
    //   276: iconst_0
    //   277: bastore
    //   278: dup
    //   279: bipush #53
    //   281: iconst_0
    //   282: bastore
    //   283: dup
    //   284: bipush #54
    //   286: iconst_0
    //   287: bastore
    //   288: dup
    //   289: bipush #55
    //   291: iconst_0
    //   292: bastore
    //   293: dup
    //   294: bipush #56
    //   296: iconst_0
    //   297: bastore
    //   298: dup
    //   299: bipush #57
    //   301: iconst_0
    //   302: bastore
    //   303: dup
    //   304: bipush #58
    //   306: iconst_0
    //   307: bastore
    //   308: dup
    //   309: bipush #59
    //   311: iconst_0
    //   312: bastore
    //   313: dup
    //   314: bipush #60
    //   316: iconst_0
    //   317: bastore
    //   318: dup
    //   319: bipush #61
    //   321: iconst_0
    //   322: bastore
    //   323: dup
    //   324: bipush #62
    //   326: iconst_0
    //   327: bastore
    //   328: dup
    //   329: bipush #63
    //   331: iconst_0
    //   332: bastore
    //   333: astore #5
    //   335: bipush #64
    //   337: newarray int
    //   339: dup
    //   340: iconst_0
    //   341: ldc 1116352408
    //   343: iastore
    //   344: dup
    //   345: iconst_1
    //   346: ldc 1899447441
    //   348: iastore
    //   349: dup
    //   350: iconst_2
    //   351: ldc -1245643825
    //   353: iastore
    //   354: dup
    //   355: iconst_3
    //   356: ldc -373957723
    //   358: iastore
    //   359: dup
    //   360: iconst_4
    //   361: ldc 961987163
    //   363: iastore
    //   364: dup
    //   365: iconst_5
    //   366: ldc 1508970993
    //   368: iastore
    //   369: dup
    //   370: bipush #6
    //   372: ldc -1841331548
    //   374: iastore
    //   375: dup
    //   376: bipush #7
    //   378: ldc -1424204075
    //   380: iastore
    //   381: dup
    //   382: bipush #8
    //   384: ldc -670586216
    //   386: iastore
    //   387: dup
    //   388: bipush #9
    //   390: ldc 310598401
    //   392: iastore
    //   393: dup
    //   394: bipush #10
    //   396: ldc 607225278
    //   398: iastore
    //   399: dup
    //   400: bipush #11
    //   402: ldc 1426881987
    //   404: iastore
    //   405: dup
    //   406: bipush #12
    //   408: ldc 1925078388
    //   410: iastore
    //   411: dup
    //   412: bipush #13
    //   414: ldc -2132889090
    //   416: iastore
    //   417: dup
    //   418: bipush #14
    //   420: ldc -1680079193
    //   422: iastore
    //   423: dup
    //   424: bipush #15
    //   426: ldc -1046744716
    //   428: iastore
    //   429: dup
    //   430: bipush #16
    //   432: ldc -459576895
    //   434: iastore
    //   435: dup
    //   436: bipush #17
    //   438: ldc -272742522
    //   440: iastore
    //   441: dup
    //   442: bipush #18
    //   444: ldc 264347078
    //   446: iastore
    //   447: dup
    //   448: bipush #19
    //   450: ldc 604807628
    //   452: iastore
    //   453: dup
    //   454: bipush #20
    //   456: ldc 770255983
    //   458: iastore
    //   459: dup
    //   460: bipush #21
    //   462: ldc 1249150122
    //   464: iastore
    //   465: dup
    //   466: bipush #22
    //   468: ldc 1555081692
    //   470: iastore
    //   471: dup
    //   472: bipush #23
    //   474: ldc 1996064986
    //   476: iastore
    //   477: dup
    //   478: bipush #24
    //   480: ldc -1740746414
    //   482: iastore
    //   483: dup
    //   484: bipush #25
    //   486: ldc -1473132947
    //   488: iastore
    //   489: dup
    //   490: bipush #26
    //   492: ldc -1341970488
    //   494: iastore
    //   495: dup
    //   496: bipush #27
    //   498: ldc -1084653625
    //   500: iastore
    //   501: dup
    //   502: bipush #28
    //   504: ldc -958395405
    //   506: iastore
    //   507: dup
    //   508: bipush #29
    //   510: ldc -710438585
    //   512: iastore
    //   513: dup
    //   514: bipush #30
    //   516: ldc 113926993
    //   518: iastore
    //   519: dup
    //   520: bipush #31
    //   522: ldc 338241895
    //   524: iastore
    //   525: dup
    //   526: bipush #32
    //   528: ldc 666307205
    //   530: iastore
    //   531: dup
    //   532: bipush #33
    //   534: ldc 773529912
    //   536: iastore
    //   537: dup
    //   538: bipush #34
    //   540: ldc 1294757372
    //   542: iastore
    //   543: dup
    //   544: bipush #35
    //   546: ldc 1396182291
    //   548: iastore
    //   549: dup
    //   550: bipush #36
    //   552: ldc 1695183700
    //   554: iastore
    //   555: dup
    //   556: bipush #37
    //   558: ldc 1986661051
    //   560: iastore
    //   561: dup
    //   562: bipush #38
    //   564: ldc -2117940946
    //   566: iastore
    //   567: dup
    //   568: bipush #39
    //   570: ldc -1838011259
    //   572: iastore
    //   573: dup
    //   574: bipush #40
    //   576: ldc -1564481375
    //   578: iastore
    //   579: dup
    //   580: bipush #41
    //   582: ldc -1474664885
    //   584: iastore
    //   585: dup
    //   586: bipush #42
    //   588: ldc -1035236496
    //   590: iastore
    //   591: dup
    //   592: bipush #43
    //   594: ldc -949202525
    //   596: iastore
    //   597: dup
    //   598: bipush #44
    //   600: ldc -778901479
    //   602: iastore
    //   603: dup
    //   604: bipush #45
    //   606: ldc -694614492
    //   608: iastore
    //   609: dup
    //   610: bipush #46
    //   612: ldc -200395387
    //   614: iastore
    //   615: dup
    //   616: bipush #47
    //   618: ldc 275423344
    //   620: iastore
    //   621: dup
    //   622: bipush #48
    //   624: ldc 430227734
    //   626: iastore
    //   627: dup
    //   628: bipush #49
    //   630: ldc 506948616
    //   632: iastore
    //   633: dup
    //   634: bipush #50
    //   636: ldc 659060556
    //   638: iastore
    //   639: dup
    //   640: bipush #51
    //   642: ldc 883997877
    //   644: iastore
    //   645: dup
    //   646: bipush #52
    //   648: ldc 958139571
    //   650: iastore
    //   651: dup
    //   652: bipush #53
    //   654: ldc 1322822218
    //   656: iastore
    //   657: dup
    //   658: bipush #54
    //   660: ldc 1537002063
    //   662: iastore
    //   663: dup
    //   664: bipush #55
    //   666: ldc 1747873779
    //   668: iastore
    //   669: dup
    //   670: bipush #56
    //   672: ldc 1955562222
    //   674: iastore
    //   675: dup
    //   676: bipush #57
    //   678: ldc 2024104815
    //   680: iastore
    //   681: dup
    //   682: bipush #58
    //   684: ldc -2067236844
    //   686: iastore
    //   687: dup
    //   688: bipush #59
    //   690: ldc -1933114872
    //   692: iastore
    //   693: dup
    //   694: bipush #60
    //   696: ldc -1866530822
    //   698: iastore
    //   699: dup
    //   700: bipush #61
    //   702: ldc -1538233109
    //   704: iastore
    //   705: dup
    //   706: bipush #62
    //   708: ldc -1090935817
    //   710: iastore
    //   711: dup
    //   712: bipush #63
    //   714: ldc -965641998
    //   716: iastore
    //   717: astore #6
    //   719: iconst_2
    //   720: newarray int
    //   722: dup
    //   723: iconst_0
    //   724: iconst_0
    //   725: iastore
    //   726: dup
    //   727: iconst_1
    //   728: iconst_0
    //   729: iastore
    //   730: astore #7
    //   732: bipush #8
    //   734: newarray int
    //   736: dup
    //   737: iconst_0
    //   738: ldc 1779033703
    //   740: iastore
    //   741: dup
    //   742: iconst_1
    //   743: ldc -1150833019
    //   745: iastore
    //   746: dup
    //   747: iconst_2
    //   748: ldc 1013904242
    //   750: iastore
    //   751: dup
    //   752: iconst_3
    //   753: ldc -1521486534
    //   755: iastore
    //   756: dup
    //   757: iconst_4
    //   758: ldc 1359893119
    //   760: iastore
    //   761: dup
    //   762: iconst_5
    //   763: ldc -1694144372
    //   765: iastore
    //   766: dup
    //   767: bipush #6
    //   769: ldc 528734635
    //   771: iastore
    //   772: dup
    //   773: bipush #7
    //   775: ldc 1541459225
    //   777: iastore
    //   778: astore #8
    //   780: bipush #64
    //   782: newarray byte
    //   784: astore #9
    //   786: bipush #64
    //   788: newarray byte
    //   790: astore #10
    //   792: aload_3
    //   793: arraylength
    //   794: istore #11
    //   796: aload #7
    //   798: iconst_0
    //   799: iaload
    //   800: bipush #63
    //   802: iand
    //   803: istore #12
    //   805: aload #7
    //   807: iconst_0
    //   808: dup2
    //   809: iaload
    //   810: iload #11
    //   812: iadd
    //   813: iastore
    //   814: aload #7
    //   816: iconst_0
    //   817: dup2
    //   818: iaload
    //   819: iconst_m1
    //   820: iand
    //   821: iastore
    //   822: aload #7
    //   824: iconst_0
    //   825: iaload
    //   826: iload #11
    //   828: if_icmpge -> 846
    //   831: aload #7
    //   833: iconst_1
    //   834: dup2
    //   835: iaload
    //   836: iconst_1
    //   837: iadd
    //   838: iastore
    //   839: goto -> 846
    //   842: invokestatic a : (Ljava/lang/Throwable;)Ljava/lang/Throwable;
    //   845: athrow
    //   846: iconst_0
    //   847: istore #13
    //   849: iload #11
    //   851: bipush #64
    //   853: if_icmplt -> 1462
    //   856: iconst_0
    //   857: istore #14
    //   859: iload #14
    //   861: bipush #64
    //   863: if_icmpge -> 885
    //   866: aload #10
    //   868: iload #14
    //   870: aload_3
    //   871: iload #13
    //   873: iload #14
    //   875: iadd
    //   876: baload
    //   877: bastore
    //   878: iinc #14, 1
    //   881: iload_2
    //   882: ifeq -> 859
    //   885: bipush #64
    //   887: newarray int
    //   889: astore #14
    //   891: bipush #8
    //   893: newarray int
    //   895: astore #15
    //   897: iconst_0
    //   898: istore #16
    //   900: iload #16
    //   902: bipush #8
    //   904: if_icmpge -> 924
    //   907: aload #15
    //   909: iload #16
    //   911: aload #8
    //   913: iload #16
    //   915: iaload
    //   916: iastore
    //   917: iinc #16, 1
    //   920: iload_2
    //   921: ifeq -> 900
    //   924: iconst_0
    //   925: istore #16
    //   927: iload #16
    //   929: bipush #64
    //   931: if_icmpge -> 1422
    //   934: iload #16
    //   936: bipush #16
    //   938: if_icmpge -> 1019
    //   941: aload #14
    //   943: iload #16
    //   945: aload #10
    //   947: iconst_4
    //   948: iload #16
    //   950: imul
    //   951: baload
    //   952: sipush #255
    //   955: iand
    //   956: bipush #24
    //   958: ishl
    //   959: aload #10
    //   961: iconst_4
    //   962: iload #16
    //   964: imul
    //   965: iconst_1
    //   966: iadd
    //   967: baload
    //   968: sipush #255
    //   971: iand
    //   972: bipush #16
    //   974: ishl
    //   975: ior
    //   976: aload #10
    //   978: iconst_4
    //   979: iload #16
    //   981: imul
    //   982: iconst_2
    //   983: iadd
    //   984: baload
    //   985: sipush #255
    //   988: iand
    //   989: bipush #8
    //   991: ishl
    //   992: ior
    //   993: aload #10
    //   995: iconst_4
    //   996: iload #16
    //   998: imul
    //   999: iconst_3
    //   1000: iadd
    //   1001: baload
    //   1002: sipush #255
    //   1005: iand
    //   1006: ior
    //   1007: iastore
    //   1008: iload_2
    //   1009: ifeq -> 1162
    //   1012: goto -> 1019
    //   1015: invokestatic a : (Ljava/lang/Throwable;)Ljava/lang/Throwable;
    //   1018: athrow
    //   1019: aload #14
    //   1021: iload #16
    //   1023: aload #14
    //   1025: iload #16
    //   1027: iconst_2
    //   1028: isub
    //   1029: iaload
    //   1030: bipush #17
    //   1032: iushr
    //   1033: aload #14
    //   1035: iload #16
    //   1037: iconst_2
    //   1038: isub
    //   1039: iaload
    //   1040: bipush #15
    //   1042: ishl
    //   1043: ior
    //   1044: aload #14
    //   1046: iload #16
    //   1048: iconst_2
    //   1049: isub
    //   1050: iaload
    //   1051: bipush #19
    //   1053: iushr
    //   1054: aload #14
    //   1056: iload #16
    //   1058: iconst_2
    //   1059: isub
    //   1060: iaload
    //   1061: bipush #13
    //   1063: ishl
    //   1064: ior
    //   1065: ixor
    //   1066: aload #14
    //   1068: iload #16
    //   1070: iconst_2
    //   1071: isub
    //   1072: iaload
    //   1073: bipush #10
    //   1075: iushr
    //   1076: ixor
    //   1077: aload #14
    //   1079: iload #16
    //   1081: bipush #7
    //   1083: isub
    //   1084: iaload
    //   1085: iadd
    //   1086: aload #14
    //   1088: iload #16
    //   1090: bipush #15
    //   1092: isub
    //   1093: iaload
    //   1094: bipush #7
    //   1096: iushr
    //   1097: aload #14
    //   1099: iload #16
    //   1101: bipush #15
    //   1103: isub
    //   1104: iaload
    //   1105: bipush #25
    //   1107: ishl
    //   1108: ior
    //   1109: aload #14
    //   1111: iload #16
    //   1113: bipush #15
    //   1115: isub
    //   1116: iaload
    //   1117: bipush #18
    //   1119: iushr
    //   1120: aload #14
    //   1122: iload #16
    //   1124: bipush #15
    //   1126: isub
    //   1127: iaload
    //   1128: bipush #14
    //   1130: ishl
    //   1131: ior
    //   1132: ixor
    //   1133: aload #14
    //   1135: iload #16
    //   1137: bipush #15
    //   1139: isub
    //   1140: iaload
    //   1141: iconst_3
    //   1142: iushr
    //   1143: ixor
    //   1144: iadd
    //   1145: aload #14
    //   1147: iload #16
    //   1149: bipush #16
    //   1151: isub
    //   1152: iaload
    //   1153: iadd
    //   1154: iastore
    //   1155: goto -> 1162
    //   1158: invokestatic a : (Ljava/lang/Throwable;)Ljava/lang/Throwable;
    //   1161: athrow
    //   1162: aload #15
    //   1164: bipush #7
    //   1166: iaload
    //   1167: aload #15
    //   1169: iconst_4
    //   1170: iaload
    //   1171: bipush #6
    //   1173: iushr
    //   1174: aload #15
    //   1176: iconst_4
    //   1177: iaload
    //   1178: bipush #26
    //   1180: ishl
    //   1181: ior
    //   1182: aload #15
    //   1184: iconst_4
    //   1185: iaload
    //   1186: bipush #11
    //   1188: iushr
    //   1189: aload #15
    //   1191: iconst_4
    //   1192: iaload
    //   1193: bipush #21
    //   1195: ishl
    //   1196: ior
    //   1197: ixor
    //   1198: aload #15
    //   1200: iconst_4
    //   1201: iaload
    //   1202: bipush #25
    //   1204: iushr
    //   1205: aload #15
    //   1207: iconst_4
    //   1208: iaload
    //   1209: bipush #7
    //   1211: ishl
    //   1212: ior
    //   1213: ixor
    //   1214: iadd
    //   1215: aload #15
    //   1217: bipush #6
    //   1219: iaload
    //   1220: aload #15
    //   1222: iconst_4
    //   1223: iaload
    //   1224: aload #15
    //   1226: iconst_5
    //   1227: iaload
    //   1228: aload #15
    //   1230: bipush #6
    //   1232: iaload
    //   1233: ixor
    //   1234: iand
    //   1235: ixor
    //   1236: iadd
    //   1237: aload #6
    //   1239: iload #16
    //   1241: iaload
    //   1242: iadd
    //   1243: aload #14
    //   1245: iload #16
    //   1247: iaload
    //   1248: iadd
    //   1249: istore #17
    //   1251: aload #15
    //   1253: iconst_0
    //   1254: iaload
    //   1255: iconst_2
    //   1256: iushr
    //   1257: aload #15
    //   1259: iconst_0
    //   1260: iaload
    //   1261: bipush #30
    //   1263: ishl
    //   1264: ior
    //   1265: aload #15
    //   1267: iconst_0
    //   1268: iaload
    //   1269: bipush #13
    //   1271: iushr
    //   1272: aload #15
    //   1274: iconst_0
    //   1275: iaload
    //   1276: bipush #19
    //   1278: ishl
    //   1279: ior
    //   1280: ixor
    //   1281: aload #15
    //   1283: iconst_0
    //   1284: iaload
    //   1285: bipush #22
    //   1287: iushr
    //   1288: aload #15
    //   1290: iconst_0
    //   1291: iaload
    //   1292: bipush #10
    //   1294: ishl
    //   1295: ior
    //   1296: ixor
    //   1297: aload #15
    //   1299: iconst_0
    //   1300: iaload
    //   1301: aload #15
    //   1303: iconst_1
    //   1304: iaload
    //   1305: iand
    //   1306: aload #15
    //   1308: iconst_2
    //   1309: iaload
    //   1310: aload #15
    //   1312: iconst_0
    //   1313: iaload
    //   1314: aload #15
    //   1316: iconst_1
    //   1317: iaload
    //   1318: ior
    //   1319: iand
    //   1320: ior
    //   1321: iadd
    //   1322: istore #18
    //   1324: aload #15
    //   1326: iconst_3
    //   1327: dup2
    //   1328: iaload
    //   1329: iload #17
    //   1331: iadd
    //   1332: iastore
    //   1333: aload #15
    //   1335: bipush #7
    //   1337: iload #17
    //   1339: iload #18
    //   1341: iadd
    //   1342: iastore
    //   1343: aload #15
    //   1345: bipush #7
    //   1347: iaload
    //   1348: istore #17
    //   1350: aload #15
    //   1352: bipush #7
    //   1354: aload #15
    //   1356: bipush #6
    //   1358: iaload
    //   1359: iastore
    //   1360: aload #15
    //   1362: bipush #6
    //   1364: aload #15
    //   1366: iconst_5
    //   1367: iaload
    //   1368: iastore
    //   1369: aload #15
    //   1371: iconst_5
    //   1372: aload #15
    //   1374: iconst_4
    //   1375: iaload
    //   1376: iastore
    //   1377: aload #15
    //   1379: iconst_4
    //   1380: aload #15
    //   1382: iconst_3
    //   1383: iaload
    //   1384: iastore
    //   1385: aload #15
    //   1387: iconst_3
    //   1388: aload #15
    //   1390: iconst_2
    //   1391: iaload
    //   1392: iastore
    //   1393: aload #15
    //   1395: iconst_2
    //   1396: aload #15
    //   1398: iconst_1
    //   1399: iaload
    //   1400: iastore
    //   1401: aload #15
    //   1403: iconst_1
    //   1404: aload #15
    //   1406: iconst_0
    //   1407: iaload
    //   1408: iastore
    //   1409: aload #15
    //   1411: iconst_0
    //   1412: iload #17
    //   1414: iastore
    //   1415: iinc #16, 1
    //   1418: iload_2
    //   1419: ifeq -> 927
    //   1422: iconst_0
    //   1423: istore #16
    //   1425: iload #16
    //   1427: bipush #8
    //   1429: if_icmpge -> 1452
    //   1432: aload #8
    //   1434: iload #16
    //   1436: dup2
    //   1437: iaload
    //   1438: aload #15
    //   1440: iload #16
    //   1442: iaload
    //   1443: iadd
    //   1444: iastore
    //   1445: iinc #16, 1
    //   1448: iload_2
    //   1449: ifeq -> 1425
    //   1452: iinc #13, 64
    //   1455: iinc #11, -64
    //   1458: iload_2
    //   1459: ifeq -> 849
    //   1462: iload #11
    //   1464: ifle -> 1499
    //   1467: iconst_0
    //   1468: istore #14
    //   1470: iload #14
    //   1472: iload #11
    //   1474: if_icmpge -> 1499
    //   1477: aload #9
    //   1479: iload #12
    //   1481: iload #14
    //   1483: iadd
    //   1484: aload_3
    //   1485: iload #13
    //   1487: iload #14
    //   1489: iadd
    //   1490: baload
    //   1491: bastore
    //   1492: iinc #14, 1
    //   1495: iload_2
    //   1496: ifeq -> 1470
    //   1499: aload #7
    //   1501: iconst_0
    //   1502: iaload
    //   1503: bipush #29
    //   1505: iushr
    //   1506: aload #7
    //   1508: iconst_1
    //   1509: iaload
    //   1510: iconst_3
    //   1511: ishl
    //   1512: ior
    //   1513: istore #14
    //   1515: aload #7
    //   1517: iconst_0
    //   1518: iaload
    //   1519: iconst_3
    //   1520: ishl
    //   1521: istore #15
    //   1523: aload #7
    //   1525: iconst_0
    //   1526: iaload
    //   1527: bipush #63
    //   1529: iand
    //   1530: istore #16
    //   1532: iload #16
    //   1534: bipush #56
    //   1536: if_icmpge -> 1551
    //   1539: bipush #56
    //   1541: iload #16
    //   1543: isub
    //   1544: goto -> 1556
    //   1547: invokestatic a : (Ljava/lang/Throwable;)Ljava/lang/Throwable;
    //   1550: athrow
    //   1551: bipush #120
    //   1553: iload #16
    //   1555: isub
    //   1556: istore #17
    //   1558: aload #7
    //   1560: iconst_0
    //   1561: iaload
    //   1562: bipush #63
    //   1564: iand
    //   1565: istore #12
    //   1567: bipush #64
    //   1569: iload #12
    //   1571: isub
    //   1572: istore #18
    //   1574: aload #7
    //   1576: iconst_0
    //   1577: dup2
    //   1578: iaload
    //   1579: iload #17
    //   1581: iadd
    //   1582: iastore
    //   1583: aload #7
    //   1585: iconst_0
    //   1586: dup2
    //   1587: iaload
    //   1588: iconst_m1
    //   1589: iand
    //   1590: iastore
    //   1591: aload #7
    //   1593: iconst_0
    //   1594: iaload
    //   1595: iload #17
    //   1597: if_icmpge -> 1615
    //   1600: aload #7
    //   1602: iconst_1
    //   1603: dup2
    //   1604: iaload
    //   1605: iconst_1
    //   1606: iadd
    //   1607: iastore
    //   1608: goto -> 1615
    //   1611: invokestatic a : (Ljava/lang/Throwable;)Ljava/lang/Throwable;
    //   1614: athrow
    //   1615: iconst_0
    //   1616: istore #13
    //   1618: iload #12
    //   1620: ifle -> 2251
    //   1623: iload #17
    //   1625: iload #18
    //   1627: if_icmplt -> 2251
    //   1630: goto -> 1637
    //   1633: invokestatic a : (Ljava/lang/Throwable;)Ljava/lang/Throwable;
    //   1636: athrow
    //   1637: iconst_0
    //   1638: istore #19
    //   1640: iload #19
    //   1642: iload #18
    //   1644: if_icmpge -> 1667
    //   1647: aload #9
    //   1649: iload #12
    //   1651: iload #19
    //   1653: iadd
    //   1654: aload #5
    //   1656: iload #19
    //   1658: baload
    //   1659: bastore
    //   1660: iinc #19, 1
    //   1663: iload_2
    //   1664: ifeq -> 1640
    //   1667: bipush #64
    //   1669: newarray int
    //   1671: astore #19
    //   1673: bipush #8
    //   1675: newarray int
    //   1677: astore #20
    //   1679: iconst_0
    //   1680: istore #21
    //   1682: iload #21
    //   1684: bipush #8
    //   1686: if_icmpge -> 1706
    //   1689: aload #20
    //   1691: iload #21
    //   1693: aload #8
    //   1695: iload #21
    //   1697: iaload
    //   1698: iastore
    //   1699: iinc #21, 1
    //   1702: iload_2
    //   1703: ifeq -> 1682
    //   1706: iconst_0
    //   1707: istore #21
    //   1709: iload #21
    //   1711: bipush #64
    //   1713: if_icmpge -> 2204
    //   1716: iload #21
    //   1718: bipush #16
    //   1720: if_icmpge -> 1801
    //   1723: aload #19
    //   1725: iload #21
    //   1727: aload #9
    //   1729: iconst_4
    //   1730: iload #21
    //   1732: imul
    //   1733: baload
    //   1734: sipush #255
    //   1737: iand
    //   1738: bipush #24
    //   1740: ishl
    //   1741: aload #9
    //   1743: iconst_4
    //   1744: iload #21
    //   1746: imul
    //   1747: iconst_1
    //   1748: iadd
    //   1749: baload
    //   1750: sipush #255
    //   1753: iand
    //   1754: bipush #16
    //   1756: ishl
    //   1757: ior
    //   1758: aload #9
    //   1760: iconst_4
    //   1761: iload #21
    //   1763: imul
    //   1764: iconst_2
    //   1765: iadd
    //   1766: baload
    //   1767: sipush #255
    //   1770: iand
    //   1771: bipush #8
    //   1773: ishl
    //   1774: ior
    //   1775: aload #9
    //   1777: iconst_4
    //   1778: iload #21
    //   1780: imul
    //   1781: iconst_3
    //   1782: iadd
    //   1783: baload
    //   1784: sipush #255
    //   1787: iand
    //   1788: ior
    //   1789: iastore
    //   1790: iload_2
    //   1791: ifeq -> 1944
    //   1794: goto -> 1801
    //   1797: invokestatic a : (Ljava/lang/Throwable;)Ljava/lang/Throwable;
    //   1800: athrow
    //   1801: aload #19
    //   1803: iload #21
    //   1805: aload #19
    //   1807: iload #21
    //   1809: iconst_2
    //   1810: isub
    //   1811: iaload
    //   1812: bipush #17
    //   1814: iushr
    //   1815: aload #19
    //   1817: iload #21
    //   1819: iconst_2
    //   1820: isub
    //   1821: iaload
    //   1822: bipush #15
    //   1824: ishl
    //   1825: ior
    //   1826: aload #19
    //   1828: iload #21
    //   1830: iconst_2
    //   1831: isub
    //   1832: iaload
    //   1833: bipush #19
    //   1835: iushr
    //   1836: aload #19
    //   1838: iload #21
    //   1840: iconst_2
    //   1841: isub
    //   1842: iaload
    //   1843: bipush #13
    //   1845: ishl
    //   1846: ior
    //   1847: ixor
    //   1848: aload #19
    //   1850: iload #21
    //   1852: iconst_2
    //   1853: isub
    //   1854: iaload
    //   1855: bipush #10
    //   1857: iushr
    //   1858: ixor
    //   1859: aload #19
    //   1861: iload #21
    //   1863: bipush #7
    //   1865: isub
    //   1866: iaload
    //   1867: iadd
    //   1868: aload #19
    //   1870: iload #21
    //   1872: bipush #15
    //   1874: isub
    //   1875: iaload
    //   1876: bipush #7
    //   1878: iushr
    //   1879: aload #19
    //   1881: iload #21
    //   1883: bipush #15
    //   1885: isub
    //   1886: iaload
    //   1887: bipush #25
    //   1889: ishl
    //   1890: ior
    //   1891: aload #19
    //   1893: iload #21
    //   1895: bipush #15
    //   1897: isub
    //   1898: iaload
    //   1899: bipush #18
    //   1901: iushr
    //   1902: aload #19
    //   1904: iload #21
    //   1906: bipush #15
    //   1908: isub
    //   1909: iaload
    //   1910: bipush #14
    //   1912: ishl
    //   1913: ior
    //   1914: ixor
    //   1915: aload #19
    //   1917: iload #21
    //   1919: bipush #15
    //   1921: isub
    //   1922: iaload
    //   1923: iconst_3
    //   1924: iushr
    //   1925: ixor
    //   1926: iadd
    //   1927: aload #19
    //   1929: iload #21
    //   1931: bipush #16
    //   1933: isub
    //   1934: iaload
    //   1935: iadd
    //   1936: iastore
    //   1937: goto -> 1944
    //   1940: invokestatic a : (Ljava/lang/Throwable;)Ljava/lang/Throwable;
    //   1943: athrow
    //   1944: aload #20
    //   1946: bipush #7
    //   1948: iaload
    //   1949: aload #20
    //   1951: iconst_4
    //   1952: iaload
    //   1953: bipush #6
    //   1955: iushr
    //   1956: aload #20
    //   1958: iconst_4
    //   1959: iaload
    //   1960: bipush #26
    //   1962: ishl
    //   1963: ior
    //   1964: aload #20
    //   1966: iconst_4
    //   1967: iaload
    //   1968: bipush #11
    //   1970: iushr
    //   1971: aload #20
    //   1973: iconst_4
    //   1974: iaload
    //   1975: bipush #21
    //   1977: ishl
    //   1978: ior
    //   1979: ixor
    //   1980: aload #20
    //   1982: iconst_4
    //   1983: iaload
    //   1984: bipush #25
    //   1986: iushr
    //   1987: aload #20
    //   1989: iconst_4
    //   1990: iaload
    //   1991: bipush #7
    //   1993: ishl
    //   1994: ior
    //   1995: ixor
    //   1996: iadd
    //   1997: aload #20
    //   1999: bipush #6
    //   2001: iaload
    //   2002: aload #20
    //   2004: iconst_4
    //   2005: iaload
    //   2006: aload #20
    //   2008: iconst_5
    //   2009: iaload
    //   2010: aload #20
    //   2012: bipush #6
    //   2014: iaload
    //   2015: ixor
    //   2016: iand
    //   2017: ixor
    //   2018: iadd
    //   2019: aload #6
    //   2021: iload #21
    //   2023: iaload
    //   2024: iadd
    //   2025: aload #19
    //   2027: iload #21
    //   2029: iaload
    //   2030: iadd
    //   2031: istore #22
    //   2033: aload #20
    //   2035: iconst_0
    //   2036: iaload
    //   2037: iconst_2
    //   2038: iushr
    //   2039: aload #20
    //   2041: iconst_0
    //   2042: iaload
    //   2043: bipush #30
    //   2045: ishl
    //   2046: ior
    //   2047: aload #20
    //   2049: iconst_0
    //   2050: iaload
    //   2051: bipush #13
    //   2053: iushr
    //   2054: aload #20
    //   2056: iconst_0
    //   2057: iaload
    //   2058: bipush #19
    //   2060: ishl
    //   2061: ior
    //   2062: ixor
    //   2063: aload #20
    //   2065: iconst_0
    //   2066: iaload
    //   2067: bipush #22
    //   2069: iushr
    //   2070: aload #20
    //   2072: iconst_0
    //   2073: iaload
    //   2074: bipush #10
    //   2076: ishl
    //   2077: ior
    //   2078: ixor
    //   2079: aload #20
    //   2081: iconst_0
    //   2082: iaload
    //   2083: aload #20
    //   2085: iconst_1
    //   2086: iaload
    //   2087: iand
    //   2088: aload #20
    //   2090: iconst_2
    //   2091: iaload
    //   2092: aload #20
    //   2094: iconst_0
    //   2095: iaload
    //   2096: aload #20
    //   2098: iconst_1
    //   2099: iaload
    //   2100: ior
    //   2101: iand
    //   2102: ior
    //   2103: iadd
    //   2104: istore #23
    //   2106: aload #20
    //   2108: iconst_3
    //   2109: dup2
    //   2110: iaload
    //   2111: iload #22
    //   2113: iadd
    //   2114: iastore
    //   2115: aload #20
    //   2117: bipush #7
    //   2119: iload #22
    //   2121: iload #23
    //   2123: iadd
    //   2124: iastore
    //   2125: aload #20
    //   2127: bipush #7
    //   2129: iaload
    //   2130: istore #22
    //   2132: aload #20
    //   2134: bipush #7
    //   2136: aload #20
    //   2138: bipush #6
    //   2140: iaload
    //   2141: iastore
    //   2142: aload #20
    //   2144: bipush #6
    //   2146: aload #20
    //   2148: iconst_5
    //   2149: iaload
    //   2150: iastore
    //   2151: aload #20
    //   2153: iconst_5
    //   2154: aload #20
    //   2156: iconst_4
    //   2157: iaload
    //   2158: iastore
    //   2159: aload #20
    //   2161: iconst_4
    //   2162: aload #20
    //   2164: iconst_3
    //   2165: iaload
    //   2166: iastore
    //   2167: aload #20
    //   2169: iconst_3
    //   2170: aload #20
    //   2172: iconst_2
    //   2173: iaload
    //   2174: iastore
    //   2175: aload #20
    //   2177: iconst_2
    //   2178: aload #20
    //   2180: iconst_1
    //   2181: iaload
    //   2182: iastore
    //   2183: aload #20
    //   2185: iconst_1
    //   2186: aload #20
    //   2188: iconst_0
    //   2189: iaload
    //   2190: iastore
    //   2191: aload #20
    //   2193: iconst_0
    //   2194: iload #22
    //   2196: iastore
    //   2197: iinc #21, 1
    //   2200: iload_2
    //   2201: ifeq -> 1709
    //   2204: iconst_0
    //   2205: istore #21
    //   2207: iload #21
    //   2209: bipush #8
    //   2211: if_icmpge -> 2234
    //   2214: aload #8
    //   2216: iload #21
    //   2218: dup2
    //   2219: iaload
    //   2220: aload #20
    //   2222: iload #21
    //   2224: iaload
    //   2225: iadd
    //   2226: iastore
    //   2227: iinc #21, 1
    //   2230: iload_2
    //   2231: ifeq -> 2207
    //   2234: iload #13
    //   2236: iload #18
    //   2238: iadd
    //   2239: istore #13
    //   2241: iload #17
    //   2243: iload #18
    //   2245: isub
    //   2246: istore #17
    //   2248: iconst_0
    //   2249: istore #12
    //   2251: iload #17
    //   2253: bipush #64
    //   2255: if_icmplt -> 2865
    //   2258: iconst_0
    //   2259: istore #19
    //   2261: iload #19
    //   2263: bipush #64
    //   2265: if_icmpge -> 2288
    //   2268: aload #10
    //   2270: iload #19
    //   2272: aload #5
    //   2274: iload #13
    //   2276: iload #19
    //   2278: iadd
    //   2279: baload
    //   2280: bastore
    //   2281: iinc #19, 1
    //   2284: iload_2
    //   2285: ifeq -> 2261
    //   2288: bipush #64
    //   2290: newarray int
    //   2292: astore #19
    //   2294: bipush #8
    //   2296: newarray int
    //   2298: astore #20
    //   2300: iconst_0
    //   2301: istore #21
    //   2303: iload #21
    //   2305: bipush #8
    //   2307: if_icmpge -> 2327
    //   2310: aload #20
    //   2312: iload #21
    //   2314: aload #8
    //   2316: iload #21
    //   2318: iaload
    //   2319: iastore
    //   2320: iinc #21, 1
    //   2323: iload_2
    //   2324: ifeq -> 2303
    //   2327: iconst_0
    //   2328: istore #21
    //   2330: iload #21
    //   2332: bipush #64
    //   2334: if_icmpge -> 2825
    //   2337: iload #21
    //   2339: bipush #16
    //   2341: if_icmpge -> 2422
    //   2344: aload #19
    //   2346: iload #21
    //   2348: aload #10
    //   2350: iconst_4
    //   2351: iload #21
    //   2353: imul
    //   2354: baload
    //   2355: sipush #255
    //   2358: iand
    //   2359: bipush #24
    //   2361: ishl
    //   2362: aload #10
    //   2364: iconst_4
    //   2365: iload #21
    //   2367: imul
    //   2368: iconst_1
    //   2369: iadd
    //   2370: baload
    //   2371: sipush #255
    //   2374: iand
    //   2375: bipush #16
    //   2377: ishl
    //   2378: ior
    //   2379: aload #10
    //   2381: iconst_4
    //   2382: iload #21
    //   2384: imul
    //   2385: iconst_2
    //   2386: iadd
    //   2387: baload
    //   2388: sipush #255
    //   2391: iand
    //   2392: bipush #8
    //   2394: ishl
    //   2395: ior
    //   2396: aload #10
    //   2398: iconst_4
    //   2399: iload #21
    //   2401: imul
    //   2402: iconst_3
    //   2403: iadd
    //   2404: baload
    //   2405: sipush #255
    //   2408: iand
    //   2409: ior
    //   2410: iastore
    //   2411: iload_2
    //   2412: ifeq -> 2565
    //   2415: goto -> 2422
    //   2418: invokestatic a : (Ljava/lang/Throwable;)Ljava/lang/Throwable;
    //   2421: athrow
    //   2422: aload #19
    //   2424: iload #21
    //   2426: aload #19
    //   2428: iload #21
    //   2430: iconst_2
    //   2431: isub
    //   2432: iaload
    //   2433: bipush #17
    //   2435: iushr
    //   2436: aload #19
    //   2438: iload #21
    //   2440: iconst_2
    //   2441: isub
    //   2442: iaload
    //   2443: bipush #15
    //   2445: ishl
    //   2446: ior
    //   2447: aload #19
    //   2449: iload #21
    //   2451: iconst_2
    //   2452: isub
    //   2453: iaload
    //   2454: bipush #19
    //   2456: iushr
    //   2457: aload #19
    //   2459: iload #21
    //   2461: iconst_2
    //   2462: isub
    //   2463: iaload
    //   2464: bipush #13
    //   2466: ishl
    //   2467: ior
    //   2468: ixor
    //   2469: aload #19
    //   2471: iload #21
    //   2473: iconst_2
    //   2474: isub
    //   2475: iaload
    //   2476: bipush #10
    //   2478: iushr
    //   2479: ixor
    //   2480: aload #19
    //   2482: iload #21
    //   2484: bipush #7
    //   2486: isub
    //   2487: iaload
    //   2488: iadd
    //   2489: aload #19
    //   2491: iload #21
    //   2493: bipush #15
    //   2495: isub
    //   2496: iaload
    //   2497: bipush #7
    //   2499: iushr
    //   2500: aload #19
    //   2502: iload #21
    //   2504: bipush #15
    //   2506: isub
    //   2507: iaload
    //   2508: bipush #25
    //   2510: ishl
    //   2511: ior
    //   2512: aload #19
    //   2514: iload #21
    //   2516: bipush #15
    //   2518: isub
    //   2519: iaload
    //   2520: bipush #18
    //   2522: iushr
    //   2523: aload #19
    //   2525: iload #21
    //   2527: bipush #15
    //   2529: isub
    //   2530: iaload
    //   2531: bipush #14
    //   2533: ishl
    //   2534: ior
    //   2535: ixor
    //   2536: aload #19
    //   2538: iload #21
    //   2540: bipush #15
    //   2542: isub
    //   2543: iaload
    //   2544: iconst_3
    //   2545: iushr
    //   2546: ixor
    //   2547: iadd
    //   2548: aload #19
    //   2550: iload #21
    //   2552: bipush #16
    //   2554: isub
    //   2555: iaload
    //   2556: iadd
    //   2557: iastore
    //   2558: goto -> 2565
    //   2561: invokestatic a : (Ljava/lang/Throwable;)Ljava/lang/Throwable;
    //   2564: athrow
    //   2565: aload #20
    //   2567: bipush #7
    //   2569: iaload
    //   2570: aload #20
    //   2572: iconst_4
    //   2573: iaload
    //   2574: bipush #6
    //   2576: iushr
    //   2577: aload #20
    //   2579: iconst_4
    //   2580: iaload
    //   2581: bipush #26
    //   2583: ishl
    //   2584: ior
    //   2585: aload #20
    //   2587: iconst_4
    //   2588: iaload
    //   2589: bipush #11
    //   2591: iushr
    //   2592: aload #20
    //   2594: iconst_4
    //   2595: iaload
    //   2596: bipush #21
    //   2598: ishl
    //   2599: ior
    //   2600: ixor
    //   2601: aload #20
    //   2603: iconst_4
    //   2604: iaload
    //   2605: bipush #25
    //   2607: iushr
    //   2608: aload #20
    //   2610: iconst_4
    //   2611: iaload
    //   2612: bipush #7
    //   2614: ishl
    //   2615: ior
    //   2616: ixor
    //   2617: iadd
    //   2618: aload #20
    //   2620: bipush #6
    //   2622: iaload
    //   2623: aload #20
    //   2625: iconst_4
    //   2626: iaload
    //   2627: aload #20
    //   2629: iconst_5
    //   2630: iaload
    //   2631: aload #20
    //   2633: bipush #6
    //   2635: iaload
    //   2636: ixor
    //   2637: iand
    //   2638: ixor
    //   2639: iadd
    //   2640: aload #6
    //   2642: iload #21
    //   2644: iaload
    //   2645: iadd
    //   2646: aload #19
    //   2648: iload #21
    //   2650: iaload
    //   2651: iadd
    //   2652: istore #22
    //   2654: aload #20
    //   2656: iconst_0
    //   2657: iaload
    //   2658: iconst_2
    //   2659: iushr
    //   2660: aload #20
    //   2662: iconst_0
    //   2663: iaload
    //   2664: bipush #30
    //   2666: ishl
    //   2667: ior
    //   2668: aload #20
    //   2670: iconst_0
    //   2671: iaload
    //   2672: bipush #13
    //   2674: iushr
    //   2675: aload #20
    //   2677: iconst_0
    //   2678: iaload
    //   2679: bipush #19
    //   2681: ishl
    //   2682: ior
    //   2683: ixor
    //   2684: aload #20
    //   2686: iconst_0
    //   2687: iaload
    //   2688: bipush #22
    //   2690: iushr
    //   2691: aload #20
    //   2693: iconst_0
    //   2694: iaload
    //   2695: bipush #10
    //   2697: ishl
    //   2698: ior
    //   2699: ixor
    //   2700: aload #20
    //   2702: iconst_0
    //   2703: iaload
    //   2704: aload #20
    //   2706: iconst_1
    //   2707: iaload
    //   2708: iand
    //   2709: aload #20
    //   2711: iconst_2
    //   2712: iaload
    //   2713: aload #20
    //   2715: iconst_0
    //   2716: iaload
    //   2717: aload #20
    //   2719: iconst_1
    //   2720: iaload
    //   2721: ior
    //   2722: iand
    //   2723: ior
    //   2724: iadd
    //   2725: istore #23
    //   2727: aload #20
    //   2729: iconst_3
    //   2730: dup2
    //   2731: iaload
    //   2732: iload #22
    //   2734: iadd
    //   2735: iastore
    //   2736: aload #20
    //   2738: bipush #7
    //   2740: iload #22
    //   2742: iload #23
    //   2744: iadd
    //   2745: iastore
    //   2746: aload #20
    //   2748: bipush #7
    //   2750: iaload
    //   2751: istore #22
    //   2753: aload #20
    //   2755: bipush #7
    //   2757: aload #20
    //   2759: bipush #6
    //   2761: iaload
    //   2762: iastore
    //   2763: aload #20
    //   2765: bipush #6
    //   2767: aload #20
    //   2769: iconst_5
    //   2770: iaload
    //   2771: iastore
    //   2772: aload #20
    //   2774: iconst_5
    //   2775: aload #20
    //   2777: iconst_4
    //   2778: iaload
    //   2779: iastore
    //   2780: aload #20
    //   2782: iconst_4
    //   2783: aload #20
    //   2785: iconst_3
    //   2786: iaload
    //   2787: iastore
    //   2788: aload #20
    //   2790: iconst_3
    //   2791: aload #20
    //   2793: iconst_2
    //   2794: iaload
    //   2795: iastore
    //   2796: aload #20
    //   2798: iconst_2
    //   2799: aload #20
    //   2801: iconst_1
    //   2802: iaload
    //   2803: iastore
    //   2804: aload #20
    //   2806: iconst_1
    //   2807: aload #20
    //   2809: iconst_0
    //   2810: iaload
    //   2811: iastore
    //   2812: aload #20
    //   2814: iconst_0
    //   2815: iload #22
    //   2817: iastore
    //   2818: iinc #21, 1
    //   2821: iload_2
    //   2822: ifeq -> 2330
    //   2825: iconst_0
    //   2826: istore #21
    //   2828: iload #21
    //   2830: bipush #8
    //   2832: if_icmpge -> 2855
    //   2835: aload #8
    //   2837: iload #21
    //   2839: dup2
    //   2840: iaload
    //   2841: aload #20
    //   2843: iload #21
    //   2845: iaload
    //   2846: iadd
    //   2847: iastore
    //   2848: iinc #21, 1
    //   2851: iload_2
    //   2852: ifeq -> 2828
    //   2855: iinc #13, 64
    //   2858: iinc #17, -64
    //   2861: iload_2
    //   2862: ifeq -> 2251
    //   2865: iload #17
    //   2867: ifle -> 2903
    //   2870: iconst_0
    //   2871: istore #19
    //   2873: iload #19
    //   2875: iload #17
    //   2877: if_icmpge -> 2903
    //   2880: aload #9
    //   2882: iload #12
    //   2884: iload #19
    //   2886: iadd
    //   2887: aload #5
    //   2889: iload #13
    //   2891: iload #19
    //   2893: iadd
    //   2894: baload
    //   2895: bastore
    //   2896: iinc #19, 1
    //   2899: iload_2
    //   2900: ifeq -> 2873
    //   2903: bipush #8
    //   2905: newarray byte
    //   2907: astore #19
    //   2909: aload #19
    //   2911: iconst_0
    //   2912: iload #14
    //   2914: bipush #24
    //   2916: iushr
    //   2917: i2b
    //   2918: bastore
    //   2919: aload #19
    //   2921: iconst_1
    //   2922: iload #14
    //   2924: bipush #16
    //   2926: iushr
    //   2927: i2b
    //   2928: bastore
    //   2929: aload #19
    //   2931: iconst_2
    //   2932: iload #14
    //   2934: bipush #8
    //   2936: iushr
    //   2937: i2b
    //   2938: bastore
    //   2939: aload #19
    //   2941: iconst_3
    //   2942: iload #14
    //   2944: i2b
    //   2945: bastore
    //   2946: aload #19
    //   2948: iconst_4
    //   2949: iload #15
    //   2951: bipush #24
    //   2953: iushr
    //   2954: i2b
    //   2955: bastore
    //   2956: aload #19
    //   2958: iconst_5
    //   2959: iload #15
    //   2961: bipush #16
    //   2963: iushr
    //   2964: i2b
    //   2965: bastore
    //   2966: aload #19
    //   2968: bipush #6
    //   2970: iload #15
    //   2972: bipush #8
    //   2974: iushr
    //   2975: i2b
    //   2976: bastore
    //   2977: aload #19
    //   2979: bipush #7
    //   2981: iload #15
    //   2983: i2b
    //   2984: bastore
    //   2985: bipush #8
    //   2987: istore #11
    //   2989: aload #7
    //   2991: iconst_0
    //   2992: iaload
    //   2993: bipush #63
    //   2995: iand
    //   2996: istore #12
    //   2998: bipush #64
    //   3000: iload #12
    //   3002: isub
    //   3003: istore #18
    //   3005: aload #7
    //   3007: iconst_0
    //   3008: dup2
    //   3009: iaload
    //   3010: iload #11
    //   3012: iadd
    //   3013: iastore
    //   3014: aload #7
    //   3016: iconst_0
    //   3017: dup2
    //   3018: iaload
    //   3019: iconst_m1
    //   3020: iand
    //   3021: iastore
    //   3022: aload #7
    //   3024: iconst_0
    //   3025: iaload
    //   3026: iload #11
    //   3028: if_icmpge -> 3046
    //   3031: aload #7
    //   3033: iconst_1
    //   3034: dup2
    //   3035: iaload
    //   3036: iconst_1
    //   3037: iadd
    //   3038: iastore
    //   3039: goto -> 3046
    //   3042: invokestatic a : (Ljava/lang/Throwable;)Ljava/lang/Throwable;
    //   3045: athrow
    //   3046: iload #12
    //   3048: ifle -> 3662
    //   3051: iload #11
    //   3053: iload #18
    //   3055: if_icmplt -> 3662
    //   3058: goto -> 3065
    //   3061: invokestatic a : (Ljava/lang/Throwable;)Ljava/lang/Throwable;
    //   3064: athrow
    //   3065: iconst_0
    //   3066: istore #20
    //   3068: iload #20
    //   3070: iload #18
    //   3072: if_icmpge -> 3095
    //   3075: aload #9
    //   3077: iload #12
    //   3079: iload #20
    //   3081: iadd
    //   3082: aload #19
    //   3084: iload #20
    //   3086: baload
    //   3087: bastore
    //   3088: iinc #20, 1
    //   3091: iload_2
    //   3092: ifeq -> 3068
    //   3095: bipush #64
    //   3097: newarray int
    //   3099: astore #20
    //   3101: bipush #8
    //   3103: newarray int
    //   3105: astore #21
    //   3107: iconst_0
    //   3108: istore #22
    //   3110: iload #22
    //   3112: bipush #8
    //   3114: if_icmpge -> 3134
    //   3117: aload #21
    //   3119: iload #22
    //   3121: aload #8
    //   3123: iload #22
    //   3125: iaload
    //   3126: iastore
    //   3127: iinc #22, 1
    //   3130: iload_2
    //   3131: ifeq -> 3110
    //   3134: iconst_0
    //   3135: istore #22
    //   3137: iload #22
    //   3139: bipush #64
    //   3141: if_icmpge -> 3632
    //   3144: iload #22
    //   3146: bipush #16
    //   3148: if_icmpge -> 3229
    //   3151: aload #20
    //   3153: iload #22
    //   3155: aload #9
    //   3157: iconst_4
    //   3158: iload #22
    //   3160: imul
    //   3161: baload
    //   3162: sipush #255
    //   3165: iand
    //   3166: bipush #24
    //   3168: ishl
    //   3169: aload #9
    //   3171: iconst_4
    //   3172: iload #22
    //   3174: imul
    //   3175: iconst_1
    //   3176: iadd
    //   3177: baload
    //   3178: sipush #255
    //   3181: iand
    //   3182: bipush #16
    //   3184: ishl
    //   3185: ior
    //   3186: aload #9
    //   3188: iconst_4
    //   3189: iload #22
    //   3191: imul
    //   3192: iconst_2
    //   3193: iadd
    //   3194: baload
    //   3195: sipush #255
    //   3198: iand
    //   3199: bipush #8
    //   3201: ishl
    //   3202: ior
    //   3203: aload #9
    //   3205: iconst_4
    //   3206: iload #22
    //   3208: imul
    //   3209: iconst_3
    //   3210: iadd
    //   3211: baload
    //   3212: sipush #255
    //   3215: iand
    //   3216: ior
    //   3217: iastore
    //   3218: iload_2
    //   3219: ifeq -> 3372
    //   3222: goto -> 3229
    //   3225: invokestatic a : (Ljava/lang/Throwable;)Ljava/lang/Throwable;
    //   3228: athrow
    //   3229: aload #20
    //   3231: iload #22
    //   3233: aload #20
    //   3235: iload #22
    //   3237: iconst_2
    //   3238: isub
    //   3239: iaload
    //   3240: bipush #17
    //   3242: iushr
    //   3243: aload #20
    //   3245: iload #22
    //   3247: iconst_2
    //   3248: isub
    //   3249: iaload
    //   3250: bipush #15
    //   3252: ishl
    //   3253: ior
    //   3254: aload #20
    //   3256: iload #22
    //   3258: iconst_2
    //   3259: isub
    //   3260: iaload
    //   3261: bipush #19
    //   3263: iushr
    //   3264: aload #20
    //   3266: iload #22
    //   3268: iconst_2
    //   3269: isub
    //   3270: iaload
    //   3271: bipush #13
    //   3273: ishl
    //   3274: ior
    //   3275: ixor
    //   3276: aload #20
    //   3278: iload #22
    //   3280: iconst_2
    //   3281: isub
    //   3282: iaload
    //   3283: bipush #10
    //   3285: iushr
    //   3286: ixor
    //   3287: aload #20
    //   3289: iload #22
    //   3291: bipush #7
    //   3293: isub
    //   3294: iaload
    //   3295: iadd
    //   3296: aload #20
    //   3298: iload #22
    //   3300: bipush #15
    //   3302: isub
    //   3303: iaload
    //   3304: bipush #7
    //   3306: iushr
    //   3307: aload #20
    //   3309: iload #22
    //   3311: bipush #15
    //   3313: isub
    //   3314: iaload
    //   3315: bipush #25
    //   3317: ishl
    //   3318: ior
    //   3319: aload #20
    //   3321: iload #22
    //   3323: bipush #15
    //   3325: isub
    //   3326: iaload
    //   3327: bipush #18
    //   3329: iushr
    //   3330: aload #20
    //   3332: iload #22
    //   3334: bipush #15
    //   3336: isub
    //   3337: iaload
    //   3338: bipush #14
    //   3340: ishl
    //   3341: ior
    //   3342: ixor
    //   3343: aload #20
    //   3345: iload #22
    //   3347: bipush #15
    //   3349: isub
    //   3350: iaload
    //   3351: iconst_3
    //   3352: iushr
    //   3353: ixor
    //   3354: iadd
    //   3355: aload #20
    //   3357: iload #22
    //   3359: bipush #16
    //   3361: isub
    //   3362: iaload
    //   3363: iadd
    //   3364: iastore
    //   3365: goto -> 3372
    //   3368: invokestatic a : (Ljava/lang/Throwable;)Ljava/lang/Throwable;
    //   3371: athrow
    //   3372: aload #21
    //   3374: bipush #7
    //   3376: iaload
    //   3377: aload #21
    //   3379: iconst_4
    //   3380: iaload
    //   3381: bipush #6
    //   3383: iushr
    //   3384: aload #21
    //   3386: iconst_4
    //   3387: iaload
    //   3388: bipush #26
    //   3390: ishl
    //   3391: ior
    //   3392: aload #21
    //   3394: iconst_4
    //   3395: iaload
    //   3396: bipush #11
    //   3398: iushr
    //   3399: aload #21
    //   3401: iconst_4
    //   3402: iaload
    //   3403: bipush #21
    //   3405: ishl
    //   3406: ior
    //   3407: ixor
    //   3408: aload #21
    //   3410: iconst_4
    //   3411: iaload
    //   3412: bipush #25
    //   3414: iushr
    //   3415: aload #21
    //   3417: iconst_4
    //   3418: iaload
    //   3419: bipush #7
    //   3421: ishl
    //   3422: ior
    //   3423: ixor
    //   3424: iadd
    //   3425: aload #21
    //   3427: bipush #6
    //   3429: iaload
    //   3430: aload #21
    //   3432: iconst_4
    //   3433: iaload
    //   3434: aload #21
    //   3436: iconst_5
    //   3437: iaload
    //   3438: aload #21
    //   3440: bipush #6
    //   3442: iaload
    //   3443: ixor
    //   3444: iand
    //   3445: ixor
    //   3446: iadd
    //   3447: aload #6
    //   3449: iload #22
    //   3451: iaload
    //   3452: iadd
    //   3453: aload #20
    //   3455: iload #22
    //   3457: iaload
    //   3458: iadd
    //   3459: istore #23
    //   3461: aload #21
    //   3463: iconst_0
    //   3464: iaload
    //   3465: iconst_2
    //   3466: iushr
    //   3467: aload #21
    //   3469: iconst_0
    //   3470: iaload
    //   3471: bipush #30
    //   3473: ishl
    //   3474: ior
    //   3475: aload #21
    //   3477: iconst_0
    //   3478: iaload
    //   3479: bipush #13
    //   3481: iushr
    //   3482: aload #21
    //   3484: iconst_0
    //   3485: iaload
    //   3486: bipush #19
    //   3488: ishl
    //   3489: ior
    //   3490: ixor
    //   3491: aload #21
    //   3493: iconst_0
    //   3494: iaload
    //   3495: bipush #22
    //   3497: iushr
    //   3498: aload #21
    //   3500: iconst_0
    //   3501: iaload
    //   3502: bipush #10
    //   3504: ishl
    //   3505: ior
    //   3506: ixor
    //   3507: aload #21
    //   3509: iconst_0
    //   3510: iaload
    //   3511: aload #21
    //   3513: iconst_1
    //   3514: iaload
    //   3515: iand
    //   3516: aload #21
    //   3518: iconst_2
    //   3519: iaload
    //   3520: aload #21
    //   3522: iconst_0
    //   3523: iaload
    //   3524: aload #21
    //   3526: iconst_1
    //   3527: iaload
    //   3528: ior
    //   3529: iand
    //   3530: ior
    //   3531: iadd
    //   3532: istore #24
    //   3534: aload #21
    //   3536: iconst_3
    //   3537: dup2
    //   3538: iaload
    //   3539: iload #23
    //   3541: iadd
    //   3542: iastore
    //   3543: aload #21
    //   3545: bipush #7
    //   3547: iload #23
    //   3549: iload #24
    //   3551: iadd
    //   3552: iastore
    //   3553: aload #21
    //   3555: bipush #7
    //   3557: iaload
    //   3558: istore #23
    //   3560: aload #21
    //   3562: bipush #7
    //   3564: aload #21
    //   3566: bipush #6
    //   3568: iaload
    //   3569: iastore
    //   3570: aload #21
    //   3572: bipush #6
    //   3574: aload #21
    //   3576: iconst_5
    //   3577: iaload
    //   3578: iastore
    //   3579: aload #21
    //   3581: iconst_5
    //   3582: aload #21
    //   3584: iconst_4
    //   3585: iaload
    //   3586: iastore
    //   3587: aload #21
    //   3589: iconst_4
    //   3590: aload #21
    //   3592: iconst_3
    //   3593: iaload
    //   3594: iastore
    //   3595: aload #21
    //   3597: iconst_3
    //   3598: aload #21
    //   3600: iconst_2
    //   3601: iaload
    //   3602: iastore
    //   3603: aload #21
    //   3605: iconst_2
    //   3606: aload #21
    //   3608: iconst_1
    //   3609: iaload
    //   3610: iastore
    //   3611: aload #21
    //   3613: iconst_1
    //   3614: aload #21
    //   3616: iconst_0
    //   3617: iaload
    //   3618: iastore
    //   3619: aload #21
    //   3621: iconst_0
    //   3622: iload #23
    //   3624: iastore
    //   3625: iinc #22, 1
    //   3628: iload_2
    //   3629: ifeq -> 3137
    //   3632: iconst_0
    //   3633: istore #22
    //   3635: iload #22
    //   3637: bipush #8
    //   3639: if_icmpge -> 3662
    //   3642: aload #8
    //   3644: iload #22
    //   3646: dup2
    //   3647: iaload
    //   3648: aload #21
    //   3650: iload #22
    //   3652: iaload
    //   3653: iadd
    //   3654: iastore
    //   3655: iinc #22, 1
    //   3658: iload_2
    //   3659: ifeq -> 3635
    //   3662: bipush #32
    //   3664: newarray byte
    //   3666: astore #4
    //   3668: sipush #-31916
    //   3671: aload #4
    //   3673: iconst_0
    //   3674: aload #8
    //   3676: iconst_0
    //   3677: iaload
    //   3678: bipush #24
    //   3680: iushr
    //   3681: i2b
    //   3682: bastore
    //   3683: sipush #-14011
    //   3686: aload #4
    //   3688: iconst_1
    //   3689: aload #8
    //   3691: iconst_0
    //   3692: iaload
    //   3693: bipush #16
    //   3695: iushr
    //   3696: i2b
    //   3697: bastore
    //   3698: aload #4
    //   3700: iconst_2
    //   3701: aload #8
    //   3703: iconst_0
    //   3704: iaload
    //   3705: bipush #8
    //   3707: iushr
    //   3708: i2b
    //   3709: bastore
    //   3710: aload #4
    //   3712: iconst_3
    //   3713: aload #8
    //   3715: iconst_0
    //   3716: iaload
    //   3717: i2b
    //   3718: bastore
    //   3719: aload #4
    //   3721: iconst_4
    //   3722: aload #8
    //   3724: iconst_1
    //   3725: iaload
    //   3726: bipush #24
    //   3728: iushr
    //   3729: i2b
    //   3730: bastore
    //   3731: aload #4
    //   3733: iconst_5
    //   3734: aload #8
    //   3736: iconst_1
    //   3737: iaload
    //   3738: bipush #16
    //   3740: iushr
    //   3741: i2b
    //   3742: bastore
    //   3743: aload #4
    //   3745: bipush #6
    //   3747: aload #8
    //   3749: iconst_1
    //   3750: iaload
    //   3751: bipush #8
    //   3753: iushr
    //   3754: i2b
    //   3755: bastore
    //   3756: aload #4
    //   3758: bipush #7
    //   3760: aload #8
    //   3762: iconst_1
    //   3763: iaload
    //   3764: i2b
    //   3765: bastore
    //   3766: aload #4
    //   3768: bipush #8
    //   3770: aload #8
    //   3772: iconst_2
    //   3773: iaload
    //   3774: bipush #24
    //   3776: iushr
    //   3777: i2b
    //   3778: bastore
    //   3779: aload #4
    //   3781: bipush #9
    //   3783: aload #8
    //   3785: iconst_2
    //   3786: iaload
    //   3787: bipush #16
    //   3789: iushr
    //   3790: i2b
    //   3791: bastore
    //   3792: aload #4
    //   3794: bipush #10
    //   3796: aload #8
    //   3798: iconst_2
    //   3799: iaload
    //   3800: bipush #8
    //   3802: iushr
    //   3803: i2b
    //   3804: bastore
    //   3805: aload #4
    //   3807: bipush #11
    //   3809: aload #8
    //   3811: iconst_2
    //   3812: iaload
    //   3813: i2b
    //   3814: bastore
    //   3815: aload #4
    //   3817: bipush #12
    //   3819: aload #8
    //   3821: iconst_3
    //   3822: iaload
    //   3823: bipush #24
    //   3825: iushr
    //   3826: i2b
    //   3827: bastore
    //   3828: aload #4
    //   3830: bipush #13
    //   3832: aload #8
    //   3834: iconst_3
    //   3835: iaload
    //   3836: bipush #16
    //   3838: iushr
    //   3839: i2b
    //   3840: bastore
    //   3841: aload #4
    //   3843: bipush #14
    //   3845: aload #8
    //   3847: iconst_3
    //   3848: iaload
    //   3849: bipush #8
    //   3851: iushr
    //   3852: i2b
    //   3853: bastore
    //   3854: aload #4
    //   3856: bipush #15
    //   3858: aload #8
    //   3860: iconst_3
    //   3861: iaload
    //   3862: i2b
    //   3863: bastore
    //   3864: aload #4
    //   3866: bipush #16
    //   3868: aload #8
    //   3870: iconst_4
    //   3871: iaload
    //   3872: bipush #24
    //   3874: iushr
    //   3875: i2b
    //   3876: bastore
    //   3877: aload #4
    //   3879: bipush #17
    //   3881: aload #8
    //   3883: iconst_4
    //   3884: iaload
    //   3885: bipush #16
    //   3887: iushr
    //   3888: i2b
    //   3889: bastore
    //   3890: aload #4
    //   3892: bipush #18
    //   3894: aload #8
    //   3896: iconst_4
    //   3897: iaload
    //   3898: bipush #8
    //   3900: iushr
    //   3901: i2b
    //   3902: bastore
    //   3903: aload #4
    //   3905: bipush #19
    //   3907: aload #8
    //   3909: iconst_4
    //   3910: iaload
    //   3911: i2b
    //   3912: bastore
    //   3913: aload #4
    //   3915: bipush #20
    //   3917: aload #8
    //   3919: iconst_5
    //   3920: iaload
    //   3921: bipush #24
    //   3923: iushr
    //   3924: i2b
    //   3925: bastore
    //   3926: aload #4
    //   3928: bipush #21
    //   3930: aload #8
    //   3932: iconst_5
    //   3933: iaload
    //   3934: bipush #16
    //   3936: iushr
    //   3937: i2b
    //   3938: bastore
    //   3939: aload #4
    //   3941: bipush #22
    //   3943: aload #8
    //   3945: iconst_5
    //   3946: iaload
    //   3947: bipush #8
    //   3949: iushr
    //   3950: i2b
    //   3951: bastore
    //   3952: aload #4
    //   3954: bipush #23
    //   3956: aload #8
    //   3958: iconst_5
    //   3959: iaload
    //   3960: i2b
    //   3961: bastore
    //   3962: aload #4
    //   3964: bipush #24
    //   3966: aload #8
    //   3968: bipush #6
    //   3970: iaload
    //   3971: bipush #24
    //   3973: iushr
    //   3974: i2b
    //   3975: bastore
    //   3976: aload #4
    //   3978: bipush #25
    //   3980: aload #8
    //   3982: bipush #6
    //   3984: iaload
    //   3985: bipush #16
    //   3987: iushr
    //   3988: i2b
    //   3989: bastore
    //   3990: aload #4
    //   3992: bipush #26
    //   3994: aload #8
    //   3996: bipush #6
    //   3998: iaload
    //   3999: bipush #8
    //   4001: iushr
    //   4002: i2b
    //   4003: bastore
    //   4004: aload #4
    //   4006: bipush #27
    //   4008: aload #8
    //   4010: bipush #6
    //   4012: iaload
    //   4013: i2b
    //   4014: bastore
    //   4015: aload #4
    //   4017: bipush #28
    //   4019: aload #8
    //   4021: bipush #7
    //   4023: iaload
    //   4024: bipush #24
    //   4026: iushr
    //   4027: i2b
    //   4028: bastore
    //   4029: aload #4
    //   4031: bipush #29
    //   4033: aload #8
    //   4035: bipush #7
    //   4037: iaload
    //   4038: bipush #16
    //   4040: iushr
    //   4041: i2b
    //   4042: bastore
    //   4043: aload #4
    //   4045: bipush #30
    //   4047: aload #8
    //   4049: bipush #7
    //   4051: iaload
    //   4052: bipush #8
    //   4054: iushr
    //   4055: i2b
    //   4056: bastore
    //   4057: aload #4
    //   4059: bipush #31
    //   4061: aload #8
    //   4063: bipush #7
    //   4065: iaload
    //   4066: i2b
    //   4067: bastore
    //   4068: new java/math/BigInteger
    //   4071: dup
    //   4072: aload #4
    //   4074: invokespecial <init> : ([B)V
    //   4077: invokevirtual abs : ()Ljava/math/BigInteger;
    //   4080: putstatic burp/Ze6t.Zu : Ljava/lang/Object;
    //   4083: invokestatic a : (II)Ljava/lang/String;
    //   4086: iconst_1
    //   4087: ldc burp/Zrcy
    //   4089: invokevirtual getClassLoader : ()Ljava/lang/ClassLoader;
    //   4092: invokestatic forName : (Ljava/lang/String;ZLjava/lang/ClassLoader;)Ljava/lang/Class;
    //   4095: invokevirtual getDeclaredFields : ()[Ljava/lang/reflect/Field;
    //   4098: astore_3
    //   4099: aload_3
    //   4100: arraylength
    //   4101: istore #4
    //   4103: iconst_0
    //   4104: istore #5
    //   4106: iload #5
    //   4108: iload #4
    //   4110: if_icmpge -> 4247
    //   4113: aload_3
    //   4114: iload #5
    //   4116: aaload
    //   4117: astore #6
    //   4119: aload #6
    //   4121: invokevirtual getModifiers : ()I
    //   4124: invokestatic isStatic : (I)Z
    //   4127: ifne -> 4137
    //   4130: goto -> 4240
    //   4133: invokestatic a : (Ljava/lang/Throwable;)Ljava/lang/Throwable;
    //   4136: athrow
    //   4137: aload #6
    //   4139: invokevirtual getType : ()Ljava/lang/Class;
    //   4142: astore #7
    //   4144: aload #7
    //   4146: ifnull -> 4227
    //   4149: aload #7
    //   4151: invokevirtual isPrimitive : ()Z
    //   4154: ifne -> 4227
    //   4157: goto -> 4164
    //   4160: invokestatic a : (Ljava/lang/Throwable;)Ljava/lang/Throwable;
    //   4163: athrow
    //   4164: aload #7
    //   4166: invokevirtual getPackage : ()Ljava/lang/Package;
    //   4169: ifnull -> 4227
    //   4172: goto -> 4179
    //   4175: invokestatic a : (Ljava/lang/Throwable;)Ljava/lang/Throwable;
    //   4178: athrow
    //   4179: aload #7
    //   4181: invokevirtual getPackage : ()Ljava/lang/Package;
    //   4184: invokevirtual getName : ()Ljava/lang/String;
    //   4187: ifnull -> 4227
    //   4190: goto -> 4197
    //   4193: invokestatic a : (Ljava/lang/Throwable;)Ljava/lang/Throwable;
    //   4196: athrow
    //   4197: aload #7
    //   4199: invokevirtual getPackage : ()Ljava/lang/Package;
    //   4202: invokevirtual getName : ()Ljava/lang/String;
    //   4205: sipush #-31910
    //   4208: sipush #-740
    //   4211: invokestatic a : (II)Ljava/lang/String;
    //   4214: invokevirtual startsWith : (Ljava/lang/String;)Z
    //   4217: ifne -> 4227
    //   4220: goto -> 4227
    //   4223: invokestatic a : (Ljava/lang/Throwable;)Ljava/lang/Throwable;
    //   4226: athrow
    //   4227: aload #6
    //   4229: iconst_1
    //   4230: invokevirtual setAccessible : (Z)V
    //   4233: aload #6
    //   4235: aconst_null
    //   4236: invokevirtual get : (Ljava/lang/Object;)Ljava/lang/Object;
    //   4239: pop
    //   4240: iinc #5, 1
    //   4243: iload_2
    //   4244: ifeq -> 4106
    //   4247: sipush #-31925
    //   4250: sipush #5830
    //   4253: invokestatic a : (II)Ljava/lang/String;
    //   4256: invokestatic forName : (Ljava/lang/String;)Ljava/lang/Class;
    //   4259: invokevirtual getDeclaredMethods : ()[Ljava/lang/reflect/Method;
    //   4262: astore_3
    //   4263: aload_3
    //   4264: arraylength
    //   4265: istore #4
    //   4267: iconst_0
    //   4268: istore #5
    //   4270: iload #5
    //   4272: iload #4
    //   4274: if_icmpge -> 4406
    //   4277: aload_3
    //   4278: iload #5
    //   4280: aaload
    //   4281: astore #6
    //   4283: aload #6
    //   4285: invokevirtual getParameterTypes : ()[Ljava/lang/Class;
    //   4288: pop
    //   4289: aload #6
    //   4291: invokevirtual getModifiers : ()I
    //   4294: invokestatic isStatic : (I)Z
    //   4297: ifeq -> 4392
    //   4300: aload #6
    //   4302: invokevirtual getParameterTypes : ()[Ljava/lang/Class;
    //   4305: arraylength
    //   4306: iconst_2
    //   4307: if_icmpne -> 4392
    //   4310: goto -> 4317
    //   4313: invokestatic a : (Ljava/lang/Throwable;)Ljava/lang/Throwable;
    //   4316: athrow
    //   4317: aload #6
    //   4319: invokevirtual getReturnType : ()Ljava/lang/Class;
    //   4322: getstatic java/lang/Void.TYPE : Ljava/lang/Class;
    //   4325: invokevirtual equals : (Ljava/lang/Object;)Z
    //   4328: ifeq -> 4392
    //   4331: goto -> 4338
    //   4334: invokestatic a : (Ljava/lang/Throwable;)Ljava/lang/Throwable;
    //   4337: athrow
    //   4338: aload #6
    //   4340: iconst_1
    //   4341: invokevirtual setAccessible : (Z)V
    //   4344: aload #6
    //   4346: aconst_null
    //   4347: iconst_2
    //   4348: anewarray java/lang/Object
    //   4351: dup
    //   4352: iconst_0
    //   4353: aload_0
    //   4354: aastore
    //   4355: dup
    //   4356: iconst_1
    //   4357: aload_1
    //   4358: ifnonnull -> 4376
    //   4361: goto -> 4368
    //   4364: invokestatic a : (Ljava/lang/Throwable;)Ljava/lang/Throwable;
    //   4367: athrow
    //   4368: aload_1
    //   4369: goto -> 4383
    //   4372: invokestatic a : (Ljava/lang/Throwable;)Ljava/lang/Throwable;
    //   4375: athrow
    //   4376: aload_1
    //   4377: checkcast [B
    //   4380: invokevirtual clone : ()Ljava/lang/Object;
    //   4383: aastore
    //   4384: invokevirtual invoke : (Ljava/lang/Object;[Ljava/lang/Object;)Ljava/lang/Object;
    //   4387: pop
    //   4388: iload_2
    //   4389: ifeq -> 4406
    //   4392: iinc #5, 1
    //   4395: iload_2
    //   4396: ifeq -> 4270
    //   4399: goto -> 4406
    //   4402: invokestatic a : (Ljava/lang/Throwable;)Ljava/lang/Throwable;
    //   4405: athrow
    //   4406: iconst_0
    //   4407: istore_3
    //   4408: getstatic burp/Zg8.ZE : Ljava/lang/String;
    //   4411: getstatic burp/Zb8x.Zz : Ljava/lang/Object;
    //   4414: checkcast java/math/BigInteger
    //   4417: invokevirtual intValue : ()I
    //   4420: bipush #32
    //   4422: irem
    //   4423: invokestatic abs : (I)I
    //   4426: invokevirtual charAt : (I)C
    //   4429: getstatic burp/Zlfg.Zb : Ljava/lang/String;
    //   4432: getstatic burp/Zgz2.Zs : Ljava/lang/Object;
    //   4435: checkcast java/math/BigInteger
    //   4438: invokevirtual intValue : ()I
    //   4441: bipush #32
    //   4443: irem
    //   4444: invokestatic abs : (I)I
    //   4447: invokevirtual charAt : (I)C
    //   4450: if_icmpgt -> 4794
    //   4453: sipush #-31932
    //   4456: sipush #-4031
    //   4459: invokestatic a : (II)Ljava/lang/String;
    //   4462: iconst_1
    //   4463: ldc burp/Zs56
    //   4465: invokevirtual getClassLoader : ()Ljava/lang/ClassLoader;
    //   4468: invokestatic forName : (Ljava/lang/String;ZLjava/lang/ClassLoader;)Ljava/lang/Class;
    //   4471: invokevirtual getDeclaredFields : ()[Ljava/lang/reflect/Field;
    //   4474: astore #4
    //   4476: aload #4
    //   4478: arraylength
    //   4479: istore #5
    //   4481: iconst_0
    //   4482: istore #6
    //   4484: iload #6
    //   4486: iload #5
    //   4488: if_icmpge -> 4626
    //   4491: aload #4
    //   4493: iload #6
    //   4495: aaload
    //   4496: astore #7
    //   4498: aload #7
    //   4500: invokevirtual getModifiers : ()I
    //   4503: invokestatic isStatic : (I)Z
    //   4506: ifne -> 4516
    //   4509: goto -> 4619
    //   4512: invokestatic a : (Ljava/lang/Throwable;)Ljava/lang/Throwable;
    //   4515: athrow
    //   4516: aload #7
    //   4518: invokevirtual getType : ()Ljava/lang/Class;
    //   4521: astore #8
    //   4523: aload #8
    //   4525: ifnull -> 4606
    //   4528: aload #8
    //   4530: invokevirtual isPrimitive : ()Z
    //   4533: ifne -> 4606
    //   4536: goto -> 4543
    //   4539: invokestatic a : (Ljava/lang/Throwable;)Ljava/lang/Throwable;
    //   4542: athrow
    //   4543: aload #8
    //   4545: invokevirtual getPackage : ()Ljava/lang/Package;
    //   4548: ifnull -> 4606
    //   4551: goto -> 4558
    //   4554: invokestatic a : (Ljava/lang/Throwable;)Ljava/lang/Throwable;
    //   4557: athrow
    //   4558: aload #8
    //   4560: invokevirtual getPackage : ()Ljava/lang/Package;
    //   4563: invokevirtual getName : ()Ljava/lang/String;
    //   4566: ifnull -> 4606
    //   4569: goto -> 4576
    //   4572: invokestatic a : (Ljava/lang/Throwable;)Ljava/lang/Throwable;
    //   4575: athrow
    //   4576: aload #8
    //   4578: invokevirtual getPackage : ()Ljava/lang/Package;
    //   4581: invokevirtual getName : ()Ljava/lang/String;
    //   4584: sipush #-31935
    //   4587: sipush #25870
    //   4590: invokestatic a : (II)Ljava/lang/String;
    //   4593: invokevirtual startsWith : (Ljava/lang/String;)Z
    //   4596: ifne -> 4606
    //   4599: goto -> 4606
    //   4602: invokestatic a : (Ljava/lang/Throwable;)Ljava/lang/Throwable;
    //   4605: athrow
    //   4606: aload #7
    //   4608: iconst_1
    //   4609: invokevirtual setAccessible : (Z)V
    //   4612: aload #7
    //   4614: aconst_null
    //   4615: invokevirtual get : (Ljava/lang/Object;)Ljava/lang/Object;
    //   4618: pop
    //   4619: iinc #6, 1
    //   4622: iload_2
    //   4623: ifeq -> 4484
    //   4626: sipush #-31926
    //   4629: sipush #-10923
    //   4632: invokestatic a : (II)Ljava/lang/String;
    //   4635: invokestatic forName : (Ljava/lang/String;)Ljava/lang/Class;
    //   4638: invokevirtual getDeclaredMethods : ()[Ljava/lang/reflect/Method;
    //   4641: astore #4
    //   4643: aload #4
    //   4645: arraylength
    //   4646: istore #5
    //   4648: iconst_0
    //   4649: istore #6
    //   4651: iload #6
    //   4653: iload #5
    //   4655: if_icmpge -> 4791
    //   4658: aload #4
    //   4660: iload #6
    //   4662: aaload
    //   4663: astore #7
    //   4665: aload #7
    //   4667: invokevirtual getParameterTypes : ()[Ljava/lang/Class;
    //   4670: pop
    //   4671: aload #7
    //   4673: invokevirtual getModifiers : ()I
    //   4676: invokestatic isStatic : (I)Z
    //   4679: ifeq -> 4777
    //   4682: aload #7
    //   4684: invokevirtual getParameterTypes : ()[Ljava/lang/Class;
    //   4687: arraylength
    //   4688: iconst_2
    //   4689: if_icmpne -> 4777
    //   4692: goto -> 4699
    //   4695: invokestatic a : (Ljava/lang/Throwable;)Ljava/lang/Throwable;
    //   4698: athrow
    //   4699: aload #7
    //   4701: invokevirtual getReturnType : ()Ljava/lang/Class;
    //   4704: getstatic java/lang/Boolean.TYPE : Ljava/lang/Class;
    //   4707: if_acmpne -> 4777
    //   4710: goto -> 4717
    //   4713: invokestatic a : (Ljava/lang/Throwable;)Ljava/lang/Throwable;
    //   4716: athrow
    //   4717: aload #7
    //   4719: iconst_1
    //   4720: invokevirtual setAccessible : (Z)V
    //   4723: aload #7
    //   4725: aconst_null
    //   4726: iconst_2
    //   4727: anewarray java/lang/Object
    //   4730: dup
    //   4731: iconst_0
    //   4732: aload_0
    //   4733: aastore
    //   4734: dup
    //   4735: iconst_1
    //   4736: aload_1
    //   4737: ifnonnull -> 4755
    //   4740: goto -> 4747
    //   4743: invokestatic a : (Ljava/lang/Throwable;)Ljava/lang/Throwable;
    //   4746: athrow
    //   4747: aload_1
    //   4748: goto -> 4762
    //   4751: invokestatic a : (Ljava/lang/Throwable;)Ljava/lang/Throwable;
    //   4754: athrow
    //   4755: aload_1
    //   4756: checkcast [B
    //   4759: invokevirtual clone : ()Ljava/lang/Object;
    //   4762: aastore
    //   4763: invokevirtual invoke : (Ljava/lang/Object;[Ljava/lang/Object;)Ljava/lang/Object;
    //   4766: checkcast java/lang/Boolean
    //   4769: invokevirtual booleanValue : ()Z
    //   4772: istore_3
    //   4773: iload_2
    //   4774: ifeq -> 4791
    //   4777: iinc #6, 1
    //   4780: iload_2
    //   4781: ifeq -> 4651
    //   4784: goto -> 4791
    //   4787: invokestatic a : (Ljava/lang/Throwable;)Ljava/lang/Throwable;
    //   4790: athrow
    //   4791: goto -> 5132
    //   4794: sipush #-31927
    //   4797: sipush #-2249
    //   4800: invokestatic a : (II)Ljava/lang/String;
    //   4803: iconst_1
    //   4804: ldc burp/Ztt0
    //   4806: invokevirtual getClassLoader : ()Ljava/lang/ClassLoader;
    //   4809: invokestatic forName : (Ljava/lang/String;ZLjava/lang/ClassLoader;)Ljava/lang/Class;
    //   4812: invokevirtual getDeclaredFields : ()[Ljava/lang/reflect/Field;
    //   4815: astore #4
    //   4817: aload #4
    //   4819: arraylength
    //   4820: istore #5
    //   4822: iconst_0
    //   4823: istore #6
    //   4825: iload #6
    //   4827: iload #5
    //   4829: if_icmpge -> 4967
    //   4832: aload #4
    //   4834: iload #6
    //   4836: aaload
    //   4837: astore #7
    //   4839: aload #7
    //   4841: invokevirtual getModifiers : ()I
    //   4844: invokestatic isStatic : (I)Z
    //   4847: ifne -> 4857
    //   4850: goto -> 4960
    //   4853: invokestatic a : (Ljava/lang/Throwable;)Ljava/lang/Throwable;
    //   4856: athrow
    //   4857: aload #7
    //   4859: invokevirtual getType : ()Ljava/lang/Class;
    //   4862: astore #8
    //   4864: aload #8
    //   4866: ifnull -> 4947
    //   4869: aload #8
    //   4871: invokevirtual isPrimitive : ()Z
    //   4874: ifne -> 4947
    //   4877: goto -> 4884
    //   4880: invokestatic a : (Ljava/lang/Throwable;)Ljava/lang/Throwable;
    //   4883: athrow
    //   4884: aload #8
    //   4886: invokevirtual getPackage : ()Ljava/lang/Package;
    //   4889: ifnull -> 4947
    //   4892: goto -> 4899
    //   4895: invokestatic a : (Ljava/lang/Throwable;)Ljava/lang/Throwable;
    //   4898: athrow
    //   4899: aload #8
    //   4901: invokevirtual getPackage : ()Ljava/lang/Package;
    //   4904: invokevirtual getName : ()Ljava/lang/String;
    //   4907: ifnull -> 4947
    //   4910: goto -> 4917
    //   4913: invokestatic a : (Ljava/lang/Throwable;)Ljava/lang/Throwable;
    //   4916: athrow
    //   4917: aload #8
    //   4919: invokevirtual getPackage : ()Ljava/lang/Package;
    //   4922: invokevirtual getName : ()Ljava/lang/String;
    //   4925: sipush #-31935
    //   4928: sipush #25870
    //   4931: invokestatic a : (II)Ljava/lang/String;
    //   4934: invokevirtual startsWith : (Ljava/lang/String;)Z
    //   4937: ifne -> 4947
    //   4940: goto -> 4947
    //   4943: invokestatic a : (Ljava/lang/Throwable;)Ljava/lang/Throwable;
    //   4946: athrow
    //   4947: aload #7
    //   4949: iconst_1
    //   4950: invokevirtual setAccessible : (Z)V
    //   4953: aload #7
    //   4955: aconst_null
    //   4956: invokevirtual get : (Ljava/lang/Object;)Ljava/lang/Object;
    //   4959: pop
    //   4960: iinc #6, 1
    //   4963: iload_2
    //   4964: ifeq -> 4825
    //   4967: sipush #-31905
    //   4970: sipush #27594
    //   4973: invokestatic a : (II)Ljava/lang/String;
    //   4976: invokestatic forName : (Ljava/lang/String;)Ljava/lang/Class;
    //   4979: invokevirtual getDeclaredMethods : ()[Ljava/lang/reflect/Method;
    //   4982: astore #4
    //   4984: aload #4
    //   4986: arraylength
    //   4987: istore #5
    //   4989: iconst_0
    //   4990: istore #6
    //   4992: iload #6
    //   4994: iload #5
    //   4996: if_icmpge -> 5132
    //   4999: aload #4
    //   5001: iload #6
    //   5003: aaload
    //   5004: astore #7
    //   5006: aload #7
    //   5008: invokevirtual getParameterTypes : ()[Ljava/lang/Class;
    //   5011: pop
    //   5012: aload #7
    //   5014: invokevirtual getModifiers : ()I
    //   5017: invokestatic isStatic : (I)Z
    //   5020: ifeq -> 5118
    //   5023: aload #7
    //   5025: invokevirtual getParameterTypes : ()[Ljava/lang/Class;
    //   5028: arraylength
    //   5029: iconst_2
    //   5030: if_icmpne -> 5118
    //   5033: goto -> 5040
    //   5036: invokestatic a : (Ljava/lang/Throwable;)Ljava/lang/Throwable;
    //   5039: athrow
    //   5040: aload #7
    //   5042: invokevirtual getReturnType : ()Ljava/lang/Class;
    //   5045: getstatic java/lang/Boolean.TYPE : Ljava/lang/Class;
    //   5048: if_acmpne -> 5118
    //   5051: goto -> 5058
    //   5054: invokestatic a : (Ljava/lang/Throwable;)Ljava/lang/Throwable;
    //   5057: athrow
    //   5058: aload #7
    //   5060: iconst_1
    //   5061: invokevirtual setAccessible : (Z)V
    //   5064: aload #7
    //   5066: aconst_null
    //   5067: iconst_2
    //   5068: anewarray java/lang/Object
    //   5071: dup
    //   5072: iconst_0
    //   5073: aload_0
    //   5074: aastore
    //   5075: dup
    //   5076: iconst_1
    //   5077: aload_1
    //   5078: ifnonnull -> 5096
    //   5081: goto -> 5088
    //   5084: invokestatic a : (Ljava/lang/Throwable;)Ljava/lang/Throwable;
    //   5087: athrow
    //   5088: aload_1
    //   5089: goto -> 5103
    //   5092: invokestatic a : (Ljava/lang/Throwable;)Ljava/lang/Throwable;
    //   5095: athrow
    //   5096: aload_1
    //   5097: checkcast [B
    //   5100: invokevirtual clone : ()Ljava/lang/Object;
    //   5103: aastore
    //   5104: invokevirtual invoke : (Ljava/lang/Object;[Ljava/lang/Object;)Ljava/lang/Object;
    //   5107: checkcast java/lang/Boolean
    //   5110: invokevirtual booleanValue : ()Z
    //   5113: istore_3
    //   5114: iload_2
    //   5115: ifeq -> 5132
    //   5118: iinc #6, 1
    //   5121: iload_2
    //   5122: ifeq -> 4992
    //   5125: goto -> 5132
    //   5128: invokestatic a : (Ljava/lang/Throwable;)Ljava/lang/Throwable;
    //   5131: athrow
    //   5132: iload_3
    //   5133: ifeq -> 5138
    //   5136: iload_3
    //   5137: ireturn
    //   5138: getstatic burp/Zmwx.ZB : Ljava/lang/String;
    //   5141: getstatic burp/Zrqd.Zi : Ljava/lang/Object;
    //   5144: checkcast java/math/BigInteger
    //   5147: invokevirtual intValue : ()I
    //   5150: bipush #32
    //   5152: irem
    //   5153: invokestatic abs : (I)I
    //   5156: invokevirtual charAt : (I)C
    //   5159: getstatic burp/Zlfg.Zb : Ljava/lang/String;
    //   5162: getstatic burp/Zeoa.ZF : Ljava/lang/Object;
    //   5165: checkcast java/math/BigInteger
    //   5168: invokevirtual intValue : ()I
    //   5171: bipush #32
    //   5173: irem
    //   5174: invokestatic abs : (I)I
    //   5177: invokevirtual charAt : (I)C
    //   5180: if_icmple -> 5525
    //   5183: sipush #-31909
    //   5186: sipush #-23077
    //   5189: invokestatic a : (II)Ljava/lang/String;
    //   5192: iconst_1
    //   5193: ldc burp/Ztgt
    //   5195: invokevirtual getClassLoader : ()Ljava/lang/ClassLoader;
    //   5198: invokestatic forName : (Ljava/lang/String;ZLjava/lang/ClassLoader;)Ljava/lang/Class;
    //   5201: invokevirtual getDeclaredFields : ()[Ljava/lang/reflect/Field;
    //   5204: astore #4
    //   5206: aload #4
    //   5208: arraylength
    //   5209: istore #5
    //   5211: iconst_0
    //   5212: istore #6
    //   5214: iload #6
    //   5216: iload #5
    //   5218: if_icmpge -> 5356
    //   5221: aload #4
    //   5223: iload #6
    //   5225: aaload
    //   5226: astore #7
    //   5228: aload #7
    //   5230: invokevirtual getModifiers : ()I
    //   5233: invokestatic isStatic : (I)Z
    //   5236: ifne -> 5246
    //   5239: goto -> 5349
    //   5242: invokestatic a : (Ljava/lang/Throwable;)Ljava/lang/Throwable;
    //   5245: athrow
    //   5246: aload #7
    //   5248: invokevirtual getType : ()Ljava/lang/Class;
    //   5251: astore #8
    //   5253: aload #8
    //   5255: ifnull -> 5336
    //   5258: aload #8
    //   5260: invokevirtual isPrimitive : ()Z
    //   5263: ifne -> 5336
    //   5266: goto -> 5273
    //   5269: invokestatic a : (Ljava/lang/Throwable;)Ljava/lang/Throwable;
    //   5272: athrow
    //   5273: aload #8
    //   5275: invokevirtual getPackage : ()Ljava/lang/Package;
    //   5278: ifnull -> 5336
    //   5281: goto -> 5288
    //   5284: invokestatic a : (Ljava/lang/Throwable;)Ljava/lang/Throwable;
    //   5287: athrow
    //   5288: aload #8
    //   5290: invokevirtual getPackage : ()Ljava/lang/Package;
    //   5293: invokevirtual getName : ()Ljava/lang/String;
    //   5296: ifnull -> 5336
    //   5299: goto -> 5306
    //   5302: invokestatic a : (Ljava/lang/Throwable;)Ljava/lang/Throwable;
    //   5305: athrow
    //   5306: aload #8
    //   5308: invokevirtual getPackage : ()Ljava/lang/Package;
    //   5311: invokevirtual getName : ()Ljava/lang/String;
    //   5314: sipush #-31935
    //   5317: sipush #25870
    //   5320: invokestatic a : (II)Ljava/lang/String;
    //   5323: invokevirtual startsWith : (Ljava/lang/String;)Z
    //   5326: ifne -> 5336
    //   5329: goto -> 5336
    //   5332: invokestatic a : (Ljava/lang/Throwable;)Ljava/lang/Throwable;
    //   5335: athrow
    //   5336: aload #7
    //   5338: iconst_1
    //   5339: invokevirtual setAccessible : (Z)V
    //   5342: aload #7
    //   5344: aconst_null
    //   5345: invokevirtual get : (Ljava/lang/Object;)Ljava/lang/Object;
    //   5348: pop
    //   5349: iinc #6, 1
    //   5352: iload_2
    //   5353: ifeq -> 5214
    //   5356: sipush #-31930
    //   5359: sipush #20798
    //   5362: invokestatic a : (II)Ljava/lang/String;
    //   5365: invokestatic forName : (Ljava/lang/String;)Ljava/lang/Class;
    //   5368: invokevirtual getDeclaredMethods : ()[Ljava/lang/reflect/Method;
    //   5371: astore #4
    //   5373: aload #4
    //   5375: arraylength
    //   5376: istore #5
    //   5378: iconst_0
    //   5379: istore #6
    //   5381: iload #6
    //   5383: iload #5
    //   5385: if_icmpge -> 5521
    //   5388: aload #4
    //   5390: iload #6
    //   5392: aaload
    //   5393: astore #7
    //   5395: aload #7
    //   5397: invokevirtual getParameterTypes : ()[Ljava/lang/Class;
    //   5400: pop
    //   5401: aload #7
    //   5403: invokevirtual getModifiers : ()I
    //   5406: invokestatic isStatic : (I)Z
    //   5409: ifeq -> 5507
    //   5412: aload #7
    //   5414: invokevirtual getParameterTypes : ()[Ljava/lang/Class;
    //   5417: arraylength
    //   5418: iconst_2
    //   5419: if_icmpne -> 5507
    //   5422: goto -> 5429
    //   5425: invokestatic a : (Ljava/lang/Throwable;)Ljava/lang/Throwable;
    //   5428: athrow
    //   5429: aload #7
    //   5431: invokevirtual getReturnType : ()Ljava/lang/Class;
    //   5434: getstatic java/lang/Boolean.TYPE : Ljava/lang/Class;
    //   5437: if_acmpne -> 5507
    //   5440: goto -> 5447
    //   5443: invokestatic a : (Ljava/lang/Throwable;)Ljava/lang/Throwable;
    //   5446: athrow
    //   5447: aload #7
    //   5449: iconst_1
    //   5450: invokevirtual setAccessible : (Z)V
    //   5453: aload #7
    //   5455: aconst_null
    //   5456: iconst_2
    //   5457: anewarray java/lang/Object
    //   5460: dup
    //   5461: iconst_0
    //   5462: aload_0
    //   5463: aastore
    //   5464: dup
    //   5465: iconst_1
    //   5466: aload_1
    //   5467: ifnonnull -> 5485
    //   5470: goto -> 5477
    //   5473: invokestatic a : (Ljava/lang/Throwable;)Ljava/lang/Throwable;
    //   5476: athrow
    //   5477: aload_1
    //   5478: goto -> 5492
    //   5481: invokestatic a : (Ljava/lang/Throwable;)Ljava/lang/Throwable;
    //   5484: athrow
    //   5485: aload_1
    //   5486: checkcast [B
    //   5489: invokevirtual clone : ()Ljava/lang/Object;
    //   5492: aastore
    //   5493: invokevirtual invoke : (Ljava/lang/Object;[Ljava/lang/Object;)Ljava/lang/Object;
    //   5496: checkcast java/lang/Boolean
    //   5499: invokevirtual booleanValue : ()Z
    //   5502: istore_3
    //   5503: iload_2
    //   5504: ifeq -> 5521
    //   5507: iinc #6, 1
    //   5510: iload_2
    //   5511: ifeq -> 5381
    //   5514: goto -> 5521
    //   5517: invokestatic a : (Ljava/lang/Throwable;)Ljava/lang/Throwable;
    //   5520: athrow
    //   5521: iload_2
    //   5522: ifeq -> 5863
    //   5525: sipush #-31936
    //   5528: sipush #-27512
    //   5531: invokestatic a : (II)Ljava/lang/String;
    //   5534: iconst_1
    //   5535: ldc burp/Zsgl
    //   5537: invokevirtual getClassLoader : ()Ljava/lang/ClassLoader;
    //   5540: invokestatic forName : (Ljava/lang/String;ZLjava/lang/ClassLoader;)Ljava/lang/Class;
    //   5543: invokevirtual getDeclaredFields : ()[Ljava/lang/reflect/Field;
    //   5546: astore #4
    //   5548: aload #4
    //   5550: arraylength
    //   5551: istore #5
    //   5553: iconst_0
    //   5554: istore #6
    //   5556: iload #6
    //   5558: iload #5
    //   5560: if_icmpge -> 5698
    //   5563: aload #4
    //   5565: iload #6
    //   5567: aaload
    //   5568: astore #7
    //   5570: aload #7
    //   5572: invokevirtual getModifiers : ()I
    //   5575: invokestatic isStatic : (I)Z
    //   5578: ifne -> 5588
    //   5581: goto -> 5691
    //   5584: invokestatic a : (Ljava/lang/Throwable;)Ljava/lang/Throwable;
    //   5587: athrow
    //   5588: aload #7
    //   5590: invokevirtual getType : ()Ljava/lang/Class;
    //   5593: astore #8
    //   5595: aload #8
    //   5597: ifnull -> 5678
    //   5600: aload #8
    //   5602: invokevirtual isPrimitive : ()Z
    //   5605: ifne -> 5678
    //   5608: goto -> 5615
    //   5611: invokestatic a : (Ljava/lang/Throwable;)Ljava/lang/Throwable;
    //   5614: athrow
    //   5615: aload #8
    //   5617: invokevirtual getPackage : ()Ljava/lang/Package;
    //   5620: ifnull -> 5678
    //   5623: goto -> 5630
    //   5626: invokestatic a : (Ljava/lang/Throwable;)Ljava/lang/Throwable;
    //   5629: athrow
    //   5630: aload #8
    //   5632: invokevirtual getPackage : ()Ljava/lang/Package;
    //   5635: invokevirtual getName : ()Ljava/lang/String;
    //   5638: ifnull -> 5678
    //   5641: goto -> 5648
    //   5644: invokestatic a : (Ljava/lang/Throwable;)Ljava/lang/Throwable;
    //   5647: athrow
    //   5648: aload #8
    //   5650: invokevirtual getPackage : ()Ljava/lang/Package;
    //   5653: invokevirtual getName : ()Ljava/lang/String;
    //   5656: sipush #-31935
    //   5659: sipush #25870
    //   5662: invokestatic a : (II)Ljava/lang/String;
    //   5665: invokevirtual startsWith : (Ljava/lang/String;)Z
    //   5668: ifne -> 5678
    //   5671: goto -> 5678
    //   5674: invokestatic a : (Ljava/lang/Throwable;)Ljava/lang/Throwable;
    //   5677: athrow
    //   5678: aload #7
    //   5680: iconst_1
    //   5681: invokevirtual setAccessible : (Z)V
    //   5684: aload #7
    //   5686: aconst_null
    //   5687: invokevirtual get : (Ljava/lang/Object;)Ljava/lang/Object;
    //   5690: pop
    //   5691: iinc #6, 1
    //   5694: iload_2
    //   5695: ifeq -> 5556
    //   5698: sipush #-31911
    //   5701: sipush #-1259
    //   5704: invokestatic a : (II)Ljava/lang/String;
    //   5707: invokestatic forName : (Ljava/lang/String;)Ljava/lang/Class;
    //   5710: invokevirtual getDeclaredMethods : ()[Ljava/lang/reflect/Method;
    //   5713: astore #4
    //   5715: aload #4
    //   5717: arraylength
    //   5718: istore #5
    //   5720: iconst_0
    //   5721: istore #6
    //   5723: iload #6
    //   5725: iload #5
    //   5727: if_icmpge -> 5863
    //   5730: aload #4
    //   5732: iload #6
    //   5734: aaload
    //   5735: astore #7
    //   5737: aload #7
    //   5739: invokevirtual getParameterTypes : ()[Ljava/lang/Class;
    //   5742: pop
    //   5743: aload #7
    //   5745: invokevirtual getModifiers : ()I
    //   5748: invokestatic isStatic : (I)Z
    //   5751: ifeq -> 5849
    //   5754: aload #7
    //   5756: invokevirtual getParameterTypes : ()[Ljava/lang/Class;
    //   5759: arraylength
    //   5760: iconst_2
    //   5761: if_icmpne -> 5849
    //   5764: goto -> 5771
    //   5767: invokestatic a : (Ljava/lang/Throwable;)Ljava/lang/Throwable;
    //   5770: athrow
    //   5771: aload #7
    //   5773: invokevirtual getReturnType : ()Ljava/lang/Class;
    //   5776: getstatic java/lang/Boolean.TYPE : Ljava/lang/Class;
    //   5779: if_acmpne -> 5849
    //   5782: goto -> 5789
    //   5785: invokestatic a : (Ljava/lang/Throwable;)Ljava/lang/Throwable;
    //   5788: athrow
    //   5789: aload #7
    //   5791: iconst_1
    //   5792: invokevirtual setAccessible : (Z)V
    //   5795: aload #7
    //   5797: aconst_null
    //   5798: iconst_2
    //   5799: anewarray java/lang/Object
    //   5802: dup
    //   5803: iconst_0
    //   5804: aload_0
    //   5805: aastore
    //   5806: dup
    //   5807: iconst_1
    //   5808: aload_1
    //   5809: ifnonnull -> 5827
    //   5812: goto -> 5819
    //   5815: invokestatic a : (Ljava/lang/Throwable;)Ljava/lang/Throwable;
    //   5818: athrow
    //   5819: aload_1
    //   5820: goto -> 5834
    //   5823: invokestatic a : (Ljava/lang/Throwable;)Ljava/lang/Throwable;
    //   5826: athrow
    //   5827: aload_1
    //   5828: checkcast [B
    //   5831: invokevirtual clone : ()Ljava/lang/Object;
    //   5834: aastore
    //   5835: invokevirtual invoke : (Ljava/lang/Object;[Ljava/lang/Object;)Ljava/lang/Object;
    //   5838: checkcast java/lang/Boolean
    //   5841: invokevirtual booleanValue : ()Z
    //   5844: istore_3
    //   5845: iload_2
    //   5846: ifeq -> 5863
    //   5849: iinc #6, 1
    //   5852: iload_2
    //   5853: ifeq -> 5723
    //   5856: goto -> 5863
    //   5859: invokestatic a : (Ljava/lang/Throwable;)Ljava/lang/Throwable;
    //   5862: athrow
    //   5863: iload_3
    //   5864: ifeq -> 5869
    //   5867: iload_3
    //   5868: ireturn
    //   5869: getstatic burp/Zz4r.Zq : Ljava/lang/String;
    //   5872: getstatic burp/Zssb.ZW : Ljava/lang/Object;
    //   5875: checkcast java/math/BigInteger
    //   5878: invokevirtual intValue : ()I
    //   5881: bipush #32
    //   5883: irem
    //   5884: invokestatic abs : (I)I
    //   5887: invokevirtual charAt : (I)C
    //   5890: getstatic burp/Zrc0.ZL : Ljava/lang/String;
    //   5893: getstatic burp/Zz80.ZR : Ljava/lang/Object;
    //   5896: checkcast java/math/BigInteger
    //   5899: invokevirtual intValue : ()I
    //   5902: bipush #32
    //   5904: irem
    //   5905: invokestatic abs : (I)I
    //   5908: invokevirtual charAt : (I)C
    //   5911: if_icmple -> 6256
    //   5914: sipush #-31912
    //   5917: sipush #22573
    //   5920: invokestatic a : (II)Ljava/lang/String;
    //   5923: iconst_1
    //   5924: ldc burp/Zr14
    //   5926: invokevirtual getClassLoader : ()Ljava/lang/ClassLoader;
    //   5929: invokestatic forName : (Ljava/lang/String;ZLjava/lang/ClassLoader;)Ljava/lang/Class;
    //   5932: invokevirtual getDeclaredFields : ()[Ljava/lang/reflect/Field;
    //   5935: astore #4
    //   5937: aload #4
    //   5939: arraylength
    //   5940: istore #5
    //   5942: iconst_0
    //   5943: istore #6
    //   5945: iload #6
    //   5947: iload #5
    //   5949: if_icmpge -> 6087
    //   5952: aload #4
    //   5954: iload #6
    //   5956: aaload
    //   5957: astore #7
    //   5959: aload #7
    //   5961: invokevirtual getModifiers : ()I
    //   5964: invokestatic isStatic : (I)Z
    //   5967: ifne -> 5977
    //   5970: goto -> 6080
    //   5973: invokestatic a : (Ljava/lang/Throwable;)Ljava/lang/Throwable;
    //   5976: athrow
    //   5977: aload #7
    //   5979: invokevirtual getType : ()Ljava/lang/Class;
    //   5982: astore #8
    //   5984: aload #8
    //   5986: ifnull -> 6067
    //   5989: aload #8
    //   5991: invokevirtual isPrimitive : ()Z
    //   5994: ifne -> 6067
    //   5997: goto -> 6004
    //   6000: invokestatic a : (Ljava/lang/Throwable;)Ljava/lang/Throwable;
    //   6003: athrow
    //   6004: aload #8
    //   6006: invokevirtual getPackage : ()Ljava/lang/Package;
    //   6009: ifnull -> 6067
    //   6012: goto -> 6019
    //   6015: invokestatic a : (Ljava/lang/Throwable;)Ljava/lang/Throwable;
    //   6018: athrow
    //   6019: aload #8
    //   6021: invokevirtual getPackage : ()Ljava/lang/Package;
    //   6024: invokevirtual getName : ()Ljava/lang/String;
    //   6027: ifnull -> 6067
    //   6030: goto -> 6037
    //   6033: invokestatic a : (Ljava/lang/Throwable;)Ljava/lang/Throwable;
    //   6036: athrow
    //   6037: aload #8
    //   6039: invokevirtual getPackage : ()Ljava/lang/Package;
    //   6042: invokevirtual getName : ()Ljava/lang/String;
    //   6045: sipush #-31935
    //   6048: sipush #25870
    //   6051: invokestatic a : (II)Ljava/lang/String;
    //   6054: invokevirtual startsWith : (Ljava/lang/String;)Z
    //   6057: ifne -> 6067
    //   6060: goto -> 6067
    //   6063: invokestatic a : (Ljava/lang/Throwable;)Ljava/lang/Throwable;
    //   6066: athrow
    //   6067: aload #7
    //   6069: iconst_1
    //   6070: invokevirtual setAccessible : (Z)V
    //   6073: aload #7
    //   6075: aconst_null
    //   6076: invokevirtual get : (Ljava/lang/Object;)Ljava/lang/Object;
    //   6079: pop
    //   6080: iinc #6, 1
    //   6083: iload_2
    //   6084: ifeq -> 5945
    //   6087: sipush #-31934
    //   6090: sipush #-6881
    //   6093: invokestatic a : (II)Ljava/lang/String;
    //   6096: invokestatic forName : (Ljava/lang/String;)Ljava/lang/Class;
    //   6099: invokevirtual getDeclaredMethods : ()[Ljava/lang/reflect/Method;
    //   6102: astore #4
    //   6104: aload #4
    //   6106: arraylength
    //   6107: istore #5
    //   6109: iconst_0
    //   6110: istore #6
    //   6112: iload #6
    //   6114: iload #5
    //   6116: if_icmpge -> 6252
    //   6119: aload #4
    //   6121: iload #6
    //   6123: aaload
    //   6124: astore #7
    //   6126: aload #7
    //   6128: invokevirtual getParameterTypes : ()[Ljava/lang/Class;
    //   6131: pop
    //   6132: aload #7
    //   6134: invokevirtual getModifiers : ()I
    //   6137: invokestatic isStatic : (I)Z
    //   6140: ifeq -> 6238
    //   6143: aload #7
    //   6145: invokevirtual getParameterTypes : ()[Ljava/lang/Class;
    //   6148: arraylength
    //   6149: iconst_2
    //   6150: if_icmpne -> 6238
    //   6153: goto -> 6160
    //   6156: invokestatic a : (Ljava/lang/Throwable;)Ljava/lang/Throwable;
    //   6159: athrow
    //   6160: aload #7
    //   6162: invokevirtual getReturnType : ()Ljava/lang/Class;
    //   6165: getstatic java/lang/Boolean.TYPE : Ljava/lang/Class;
    //   6168: if_acmpne -> 6238
    //   6171: goto -> 6178
    //   6174: invokestatic a : (Ljava/lang/Throwable;)Ljava/lang/Throwable;
    //   6177: athrow
    //   6178: aload #7
    //   6180: iconst_1
    //   6181: invokevirtual setAccessible : (Z)V
    //   6184: aload #7
    //   6186: aconst_null
    //   6187: iconst_2
    //   6188: anewarray java/lang/Object
    //   6191: dup
    //   6192: iconst_0
    //   6193: aload_0
    //   6194: aastore
    //   6195: dup
    //   6196: iconst_1
    //   6197: aload_1
    //   6198: ifnonnull -> 6216
    //   6201: goto -> 6208
    //   6204: invokestatic a : (Ljava/lang/Throwable;)Ljava/lang/Throwable;
    //   6207: athrow
    //   6208: aload_1
    //   6209: goto -> 6223
    //   6212: invokestatic a : (Ljava/lang/Throwable;)Ljava/lang/Throwable;
    //   6215: athrow
    //   6216: aload_1
    //   6217: checkcast [B
    //   6220: invokevirtual clone : ()Ljava/lang/Object;
    //   6223: aastore
    //   6224: invokevirtual invoke : (Ljava/lang/Object;[Ljava/lang/Object;)Ljava/lang/Object;
    //   6227: checkcast java/lang/Boolean
    //   6230: invokevirtual booleanValue : ()Z
    //   6233: istore_3
    //   6234: iload_2
    //   6235: ifeq -> 6252
    //   6238: iinc #6, 1
    //   6241: iload_2
    //   6242: ifeq -> 6112
    //   6245: goto -> 6252
    //   6248: invokestatic a : (Ljava/lang/Throwable;)Ljava/lang/Throwable;
    //   6251: athrow
    //   6252: iload_2
    //   6253: ifeq -> 6594
    //   6256: sipush #-31908
    //   6259: sipush #1342
    //   6262: invokestatic a : (II)Ljava/lang/String;
    //   6265: iconst_1
    //   6266: ldc burp/Zsn6
    //   6268: invokevirtual getClassLoader : ()Ljava/lang/ClassLoader;
    //   6271: invokestatic forName : (Ljava/lang/String;ZLjava/lang/ClassLoader;)Ljava/lang/Class;
    //   6274: invokevirtual getDeclaredFields : ()[Ljava/lang/reflect/Field;
    //   6277: astore #4
    //   6279: aload #4
    //   6281: arraylength
    //   6282: istore #5
    //   6284: iconst_0
    //   6285: istore #6
    //   6287: iload #6
    //   6289: iload #5
    //   6291: if_icmpge -> 6429
    //   6294: aload #4
    //   6296: iload #6
    //   6298: aaload
    //   6299: astore #7
    //   6301: aload #7
    //   6303: invokevirtual getModifiers : ()I
    //   6306: invokestatic isStatic : (I)Z
    //   6309: ifne -> 6319
    //   6312: goto -> 6422
    //   6315: invokestatic a : (Ljava/lang/Throwable;)Ljava/lang/Throwable;
    //   6318: athrow
    //   6319: aload #7
    //   6321: invokevirtual getType : ()Ljava/lang/Class;
    //   6324: astore #8
    //   6326: aload #8
    //   6328: ifnull -> 6409
    //   6331: aload #8
    //   6333: invokevirtual isPrimitive : ()Z
    //   6336: ifne -> 6409
    //   6339: goto -> 6346
    //   6342: invokestatic a : (Ljava/lang/Throwable;)Ljava/lang/Throwable;
    //   6345: athrow
    //   6346: aload #8
    //   6348: invokevirtual getPackage : ()Ljava/lang/Package;
    //   6351: ifnull -> 6409
    //   6354: goto -> 6361
    //   6357: invokestatic a : (Ljava/lang/Throwable;)Ljava/lang/Throwable;
    //   6360: athrow
    //   6361: aload #8
    //   6363: invokevirtual getPackage : ()Ljava/lang/Package;
    //   6366: invokevirtual getName : ()Ljava/lang/String;
    //   6369: ifnull -> 6409
    //   6372: goto -> 6379
    //   6375: invokestatic a : (Ljava/lang/Throwable;)Ljava/lang/Throwable;
    //   6378: athrow
    //   6379: aload #8
    //   6381: invokevirtual getPackage : ()Ljava/lang/Package;
    //   6384: invokevirtual getName : ()Ljava/lang/String;
    //   6387: sipush #-31935
    //   6390: sipush #25870
    //   6393: invokestatic a : (II)Ljava/lang/String;
    //   6396: invokevirtual startsWith : (Ljava/lang/String;)Z
    //   6399: ifne -> 6409
    //   6402: goto -> 6409
    //   6405: invokestatic a : (Ljava/lang/Throwable;)Ljava/lang/Throwable;
    //   6408: athrow
    //   6409: aload #7
    //   6411: iconst_1
    //   6412: invokevirtual setAccessible : (Z)V
    //   6415: aload #7
    //   6417: aconst_null
    //   6418: invokevirtual get : (Ljava/lang/Object;)Ljava/lang/Object;
    //   6421: pop
    //   6422: iinc #6, 1
    //   6425: iload_2
    //   6426: ifeq -> 6287
    //   6429: sipush #-31906
    //   6432: sipush #21551
    //   6435: invokestatic a : (II)Ljava/lang/String;
    //   6438: invokestatic forName : (Ljava/lang/String;)Ljava/lang/Class;
    //   6441: invokevirtual getDeclaredMethods : ()[Ljava/lang/reflect/Method;
    //   6444: astore #4
    //   6446: aload #4
    //   6448: arraylength
    //   6449: istore #5
    //   6451: iconst_0
    //   6452: istore #6
    //   6454: iload #6
    //   6456: iload #5
    //   6458: if_icmpge -> 6594
    //   6461: aload #4
    //   6463: iload #6
    //   6465: aaload
    //   6466: astore #7
    //   6468: aload #7
    //   6470: invokevirtual getParameterTypes : ()[Ljava/lang/Class;
    //   6473: pop
    //   6474: aload #7
    //   6476: invokevirtual getModifiers : ()I
    //   6479: invokestatic isStatic : (I)Z
    //   6482: ifeq -> 6580
    //   6485: aload #7
    //   6487: invokevirtual getParameterTypes : ()[Ljava/lang/Class;
    //   6490: arraylength
    //   6491: iconst_2
    //   6492: if_icmpne -> 6580
    //   6495: goto -> 6502
    //   6498: invokestatic a : (Ljava/lang/Throwable;)Ljava/lang/Throwable;
    //   6501: athrow
    //   6502: aload #7
    //   6504: invokevirtual getReturnType : ()Ljava/lang/Class;
    //   6507: getstatic java/lang/Boolean.TYPE : Ljava/lang/Class;
    //   6510: if_acmpne -> 6580
    //   6513: goto -> 6520
    //   6516: invokestatic a : (Ljava/lang/Throwable;)Ljava/lang/Throwable;
    //   6519: athrow
    //   6520: aload #7
    //   6522: iconst_1
    //   6523: invokevirtual setAccessible : (Z)V
    //   6526: aload #7
    //   6528: aconst_null
    //   6529: iconst_2
    //   6530: anewarray java/lang/Object
    //   6533: dup
    //   6534: iconst_0
    //   6535: aload_0
    //   6536: aastore
    //   6537: dup
    //   6538: iconst_1
    //   6539: aload_1
    //   6540: ifnonnull -> 6558
    //   6543: goto -> 6550
    //   6546: invokestatic a : (Ljava/lang/Throwable;)Ljava/lang/Throwable;
    //   6549: athrow
    //   6550: aload_1
    //   6551: goto -> 6565
    //   6554: invokestatic a : (Ljava/lang/Throwable;)Ljava/lang/Throwable;
    //   6557: athrow
    //   6558: aload_1
    //   6559: checkcast [B
    //   6562: invokevirtual clone : ()Ljava/lang/Object;
    //   6565: aastore
    //   6566: invokevirtual invoke : (Ljava/lang/Object;[Ljava/lang/Object;)Ljava/lang/Object;
    //   6569: checkcast java/lang/Boolean
    //   6572: invokevirtual booleanValue : ()Z
    //   6575: istore_3
    //   6576: iload_2
    //   6577: ifeq -> 6594
    //   6580: iinc #6, 1
    //   6583: iload_2
    //   6584: ifeq -> 6454
    //   6587: goto -> 6594
    //   6590: invokestatic a : (Ljava/lang/Throwable;)Ljava/lang/Throwable;
    //   6593: athrow
    //   6594: iload_3
    //   6595: ifeq -> 6600
    //   6598: iload_3
    //   6599: ireturn
    //   6600: getstatic burp/Zgb9.Zk : Ljava/lang/String;
    //   6603: getstatic burp/Zgz1.ZX : Ljava/lang/Object;
    //   6606: checkcast java/math/BigInteger
    //   6609: invokevirtual intValue : ()I
    //   6612: bipush #32
    //   6614: irem
    //   6615: invokestatic abs : (I)I
    //   6618: invokevirtual charAt : (I)C
    //   6621: getstatic burp/Zgmo.Zr : Ljava/lang/String;
    //   6624: getstatic burp/Zxti.ZJ : Ljava/lang/Object;
    //   6627: checkcast java/math/BigInteger
    //   6630: invokevirtual intValue : ()I
    //   6633: bipush #32
    //   6635: irem
    //   6636: invokestatic abs : (I)I
    //   6639: invokevirtual charAt : (I)C
    //   6642: if_icmple -> 6987
    //   6645: sipush #-31907
    //   6648: sipush #-3895
    //   6651: invokestatic a : (II)Ljava/lang/String;
    //   6654: iconst_1
    //   6655: ldc burp/Zlb6
    //   6657: invokevirtual getClassLoader : ()Ljava/lang/ClassLoader;
    //   6660: invokestatic forName : (Ljava/lang/String;ZLjava/lang/ClassLoader;)Ljava/lang/Class;
    //   6663: invokevirtual getDeclaredFields : ()[Ljava/lang/reflect/Field;
    //   6666: astore #4
    //   6668: aload #4
    //   6670: arraylength
    //   6671: istore #5
    //   6673: iconst_0
    //   6674: istore #6
    //   6676: iload #6
    //   6678: iload #5
    //   6680: if_icmpge -> 6818
    //   6683: aload #4
    //   6685: iload #6
    //   6687: aaload
    //   6688: astore #7
    //   6690: aload #7
    //   6692: invokevirtual getModifiers : ()I
    //   6695: invokestatic isStatic : (I)Z
    //   6698: ifne -> 6708
    //   6701: goto -> 6811
    //   6704: invokestatic a : (Ljava/lang/Throwable;)Ljava/lang/Throwable;
    //   6707: athrow
    //   6708: aload #7
    //   6710: invokevirtual getType : ()Ljava/lang/Class;
    //   6713: astore #8
    //   6715: aload #8
    //   6717: ifnull -> 6798
    //   6720: aload #8
    //   6722: invokevirtual isPrimitive : ()Z
    //   6725: ifne -> 6798
    //   6728: goto -> 6735
    //   6731: invokestatic a : (Ljava/lang/Throwable;)Ljava/lang/Throwable;
    //   6734: athrow
    //   6735: aload #8
    //   6737: invokevirtual getPackage : ()Ljava/lang/Package;
    //   6740: ifnull -> 6798
    //   6743: goto -> 6750
    //   6746: invokestatic a : (Ljava/lang/Throwable;)Ljava/lang/Throwable;
    //   6749: athrow
    //   6750: aload #8
    //   6752: invokevirtual getPackage : ()Ljava/lang/Package;
    //   6755: invokevirtual getName : ()Ljava/lang/String;
    //   6758: ifnull -> 6798
    //   6761: goto -> 6768
    //   6764: invokestatic a : (Ljava/lang/Throwable;)Ljava/lang/Throwable;
    //   6767: athrow
    //   6768: aload #8
    //   6770: invokevirtual getPackage : ()Ljava/lang/Package;
    //   6773: invokevirtual getName : ()Ljava/lang/String;
    //   6776: sipush #-31935
    //   6779: sipush #25870
    //   6782: invokestatic a : (II)Ljava/lang/String;
    //   6785: invokevirtual startsWith : (Ljava/lang/String;)Z
    //   6788: ifne -> 6798
    //   6791: goto -> 6798
    //   6794: invokestatic a : (Ljava/lang/Throwable;)Ljava/lang/Throwable;
    //   6797: athrow
    //   6798: aload #7
    //   6800: iconst_1
    //   6801: invokevirtual setAccessible : (Z)V
    //   6804: aload #7
    //   6806: aconst_null
    //   6807: invokevirtual get : (Ljava/lang/Object;)Ljava/lang/Object;
    //   6810: pop
    //   6811: iinc #6, 1
    //   6814: iload_2
    //   6815: ifeq -> 6676
    //   6818: sipush #-31922
    //   6821: sipush #-14842
    //   6824: invokestatic a : (II)Ljava/lang/String;
    //   6827: invokestatic forName : (Ljava/lang/String;)Ljava/lang/Class;
    //   6830: invokevirtual getDeclaredMethods : ()[Ljava/lang/reflect/Method;
    //   6833: astore #4
    //   6835: aload #4
    //   6837: arraylength
    //   6838: istore #5
    //   6840: iconst_0
    //   6841: istore #6
    //   6843: iload #6
    //   6845: iload #5
    //   6847: if_icmpge -> 6983
    //   6850: aload #4
    //   6852: iload #6
    //   6854: aaload
    //   6855: astore #7
    //   6857: aload #7
    //   6859: invokevirtual getParameterTypes : ()[Ljava/lang/Class;
    //   6862: pop
    //   6863: aload #7
    //   6865: invokevirtual getModifiers : ()I
    //   6868: invokestatic isStatic : (I)Z
    //   6871: ifeq -> 6969
    //   6874: aload #7
    //   6876: invokevirtual getParameterTypes : ()[Ljava/lang/Class;
    //   6879: arraylength
    //   6880: iconst_2
    //   6881: if_icmpne -> 6969
    //   6884: goto -> 6891
    //   6887: invokestatic a : (Ljava/lang/Throwable;)Ljava/lang/Throwable;
    //   6890: athrow
    //   6891: aload #7
    //   6893: invokevirtual getReturnType : ()Ljava/lang/Class;
    //   6896: getstatic java/lang/Boolean.TYPE : Ljava/lang/Class;
    //   6899: if_acmpne -> 6969
    //   6902: goto -> 6909
    //   6905: invokestatic a : (Ljava/lang/Throwable;)Ljava/lang/Throwable;
    //   6908: athrow
    //   6909: aload #7
    //   6911: iconst_1
    //   6912: invokevirtual setAccessible : (Z)V
    //   6915: aload #7
    //   6917: aconst_null
    //   6918: iconst_2
    //   6919: anewarray java/lang/Object
    //   6922: dup
    //   6923: iconst_0
    //   6924: aload_0
    //   6925: aastore
    //   6926: dup
    //   6927: iconst_1
    //   6928: aload_1
    //   6929: ifnonnull -> 6947
    //   6932: goto -> 6939
    //   6935: invokestatic a : (Ljava/lang/Throwable;)Ljava/lang/Throwable;
    //   6938: athrow
    //   6939: aload_1
    //   6940: goto -> 6954
    //   6943: invokestatic a : (Ljava/lang/Throwable;)Ljava/lang/Throwable;
    //   6946: athrow
    //   6947: aload_1
    //   6948: checkcast [B
    //   6951: invokevirtual clone : ()Ljava/lang/Object;
    //   6954: aastore
    //   6955: invokevirtual invoke : (Ljava/lang/Object;[Ljava/lang/Object;)Ljava/lang/Object;
    //   6958: checkcast java/lang/Boolean
    //   6961: invokevirtual booleanValue : ()Z
    //   6964: istore_3
    //   6965: iload_2
    //   6966: ifeq -> 6983
    //   6969: iinc #6, 1
    //   6972: iload_2
    //   6973: ifeq -> 6843
    //   6976: goto -> 6983
    //   6979: invokestatic a : (Ljava/lang/Throwable;)Ljava/lang/Throwable;
    //   6982: athrow
    //   6983: iload_2
    //   6984: ifeq -> 7325
    //   6987: sipush #-31923
    //   6990: sipush #19704
    //   6993: invokestatic a : (II)Ljava/lang/String;
    //   6996: iconst_1
    //   6997: ldc burp/Zgvl
    //   6999: invokevirtual getClassLoader : ()Ljava/lang/ClassLoader;
    //   7002: invokestatic forName : (Ljava/lang/String;ZLjava/lang/ClassLoader;)Ljava/lang/Class;
    //   7005: invokevirtual getDeclaredFields : ()[Ljava/lang/reflect/Field;
    //   7008: astore #4
    //   7010: aload #4
    //   7012: arraylength
    //   7013: istore #5
    //   7015: iconst_0
    //   7016: istore #6
    //   7018: iload #6
    //   7020: iload #5
    //   7022: if_icmpge -> 7160
    //   7025: aload #4
    //   7027: iload #6
    //   7029: aaload
    //   7030: astore #7
    //   7032: aload #7
    //   7034: invokevirtual getModifiers : ()I
    //   7037: invokestatic isStatic : (I)Z
    //   7040: ifne -> 7050
    //   7043: goto -> 7153
    //   7046: invokestatic a : (Ljava/lang/Throwable;)Ljava/lang/Throwable;
    //   7049: athrow
    //   7050: aload #7
    //   7052: invokevirtual getType : ()Ljava/lang/Class;
    //   7055: astore #8
    //   7057: aload #8
    //   7059: ifnull -> 7140
    //   7062: aload #8
    //   7064: invokevirtual isPrimitive : ()Z
    //   7067: ifne -> 7140
    //   7070: goto -> 7077
    //   7073: invokestatic a : (Ljava/lang/Throwable;)Ljava/lang/Throwable;
    //   7076: athrow
    //   7077: aload #8
    //   7079: invokevirtual getPackage : ()Ljava/lang/Package;
    //   7082: ifnull -> 7140
    //   7085: goto -> 7092
    //   7088: invokestatic a : (Ljava/lang/Throwable;)Ljava/lang/Throwable;
    //   7091: athrow
    //   7092: aload #8
    //   7094: invokevirtual getPackage : ()Ljava/lang/Package;
    //   7097: invokevirtual getName : ()Ljava/lang/String;
    //   7100: ifnull -> 7140
    //   7103: goto -> 7110
    //   7106: invokestatic a : (Ljava/lang/Throwable;)Ljava/lang/Throwable;
    //   7109: athrow
    //   7110: aload #8
    //   7112: invokevirtual getPackage : ()Ljava/lang/Package;
    //   7115: invokevirtual getName : ()Ljava/lang/String;
    //   7118: sipush #-31935
    //   7121: sipush #25870
    //   7124: invokestatic a : (II)Ljava/lang/String;
    //   7127: invokevirtual startsWith : (Ljava/lang/String;)Z
    //   7130: ifne -> 7140
    //   7133: goto -> 7140
    //   7136: invokestatic a : (Ljava/lang/Throwable;)Ljava/lang/Throwable;
    //   7139: athrow
    //   7140: aload #7
    //   7142: iconst_1
    //   7143: invokevirtual setAccessible : (Z)V
    //   7146: aload #7
    //   7148: aconst_null
    //   7149: invokevirtual get : (Ljava/lang/Object;)Ljava/lang/Object;
    //   7152: pop
    //   7153: iinc #6, 1
    //   7156: iload_2
    //   7157: ifeq -> 7018
    //   7160: sipush #-31921
    //   7163: sipush #30507
    //   7166: invokestatic a : (II)Ljava/lang/String;
    //   7169: invokestatic forName : (Ljava/lang/String;)Ljava/lang/Class;
    //   7172: invokevirtual getDeclaredMethods : ()[Ljava/lang/reflect/Method;
    //   7175: astore #4
    //   7177: aload #4
    //   7179: arraylength
    //   7180: istore #5
    //   7182: iconst_0
    //   7183: istore #6
    //   7185: iload #6
    //   7187: iload #5
    //   7189: if_icmpge -> 7325
    //   7192: aload #4
    //   7194: iload #6
    //   7196: aaload
    //   7197: astore #7
    //   7199: aload #7
    //   7201: invokevirtual getParameterTypes : ()[Ljava/lang/Class;
    //   7204: pop
    //   7205: aload #7
    //   7207: invokevirtual getModifiers : ()I
    //   7210: invokestatic isStatic : (I)Z
    //   7213: ifeq -> 7311
    //   7216: aload #7
    //   7218: invokevirtual getParameterTypes : ()[Ljava/lang/Class;
    //   7221: arraylength
    //   7222: iconst_2
    //   7223: if_icmpne -> 7311
    //   7226: goto -> 7233
    //   7229: invokestatic a : (Ljava/lang/Throwable;)Ljava/lang/Throwable;
    //   7232: athrow
    //   7233: aload #7
    //   7235: invokevirtual getReturnType : ()Ljava/lang/Class;
    //   7238: getstatic java/lang/Boolean.TYPE : Ljava/lang/Class;
    //   7241: if_acmpne -> 7311
    //   7244: goto -> 7251
    //   7247: invokestatic a : (Ljava/lang/Throwable;)Ljava/lang/Throwable;
    //   7250: athrow
    //   7251: aload #7
    //   7253: iconst_1
    //   7254: invokevirtual setAccessible : (Z)V
    //   7257: aload #7
    //   7259: aconst_null
    //   7260: iconst_2
    //   7261: anewarray java/lang/Object
    //   7264: dup
    //   7265: iconst_0
    //   7266: aload_0
    //   7267: aastore
    //   7268: dup
    //   7269: iconst_1
    //   7270: aload_1
    //   7271: ifnonnull -> 7289
    //   7274: goto -> 7281
    //   7277: invokestatic a : (Ljava/lang/Throwable;)Ljava/lang/Throwable;
    //   7280: athrow
    //   7281: aload_1
    //   7282: goto -> 7296
    //   7285: invokestatic a : (Ljava/lang/Throwable;)Ljava/lang/Throwable;
    //   7288: athrow
    //   7289: aload_1
    //   7290: checkcast [B
    //   7293: invokevirtual clone : ()Ljava/lang/Object;
    //   7296: aastore
    //   7297: invokevirtual invoke : (Ljava/lang/Object;[Ljava/lang/Object;)Ljava/lang/Object;
    //   7300: checkcast java/lang/Boolean
    //   7303: invokevirtual booleanValue : ()Z
    //   7306: istore_3
    //   7307: iload_2
    //   7308: ifeq -> 7325
    //   7311: iinc #6, 1
    //   7314: iload_2
    //   7315: ifeq -> 7185
    //   7318: goto -> 7325
    //   7321: invokestatic a : (Ljava/lang/Throwable;)Ljava/lang/Throwable;
    //   7324: athrow
    //   7325: iload_3
    //   7326: ireturn
    //   7327: astore_3
    //   7328: new java/lang/Exception
    //   7331: dup
    //   7332: aload_3
    //   7333: invokevirtual getMessage : ()Ljava/lang/String;
    //   7336: invokespecial <init> : (Ljava/lang/String;)V
    //   7339: athrow
    // Exception table:
    //   from	to	target	type
    //   4	5137	7327	java/lang/Throwable
    //   805	839	842	java/lang/Throwable
    //   934	1012	1015	java/lang/Throwable
    //   941	1155	1158	java/lang/Throwable
    //   1532	1547	1547	java/lang/Throwable
    //   1574	1608	1611	java/lang/Throwable
    //   1618	1630	1633	java/lang/Throwable
    //   1716	1794	1797	java/lang/Throwable
    //   1723	1937	1940	java/lang/Throwable
    //   2337	2415	2418	java/lang/Throwable
    //   2344	2558	2561	java/lang/Throwable
    //   3005	3039	3042	java/lang/Throwable
    //   3046	3058	3061	java/lang/Throwable
    //   3144	3222	3225	java/lang/Throwable
    //   3151	3365	3368	java/lang/Throwable
    //   4119	4133	4133	java/lang/Throwable
    //   4144	4157	4160	java/lang/Throwable
    //   4149	4172	4175	java/lang/Throwable
    //   4164	4190	4193	java/lang/Throwable
    //   4179	4220	4223	java/lang/Throwable
    //   4283	4310	4313	java/lang/Throwable
    //   4300	4331	4334	java/lang/Throwable
    //   4317	4361	4364	java/lang/Throwable
    //   4338	4372	4372	java/lang/Throwable
    //   4383	4399	4402	java/lang/Throwable
    //   4498	4512	4512	java/lang/Throwable
    //   4523	4536	4539	java/lang/Throwable
    //   4528	4551	4554	java/lang/Throwable
    //   4543	4569	4572	java/lang/Throwable
    //   4558	4599	4602	java/lang/Throwable
    //   4665	4692	4695	java/lang/Throwable
    //   4682	4710	4713	java/lang/Throwable
    //   4699	4740	4743	java/lang/Throwable
    //   4717	4751	4751	java/lang/Throwable
    //   4773	4784	4787	java/lang/Throwable
    //   4839	4853	4853	java/lang/Throwable
    //   4864	4877	4880	java/lang/Throwable
    //   4869	4892	4895	java/lang/Throwable
    //   4884	4910	4913	java/lang/Throwable
    //   4899	4940	4943	java/lang/Throwable
    //   5006	5033	5036	java/lang/Throwable
    //   5023	5051	5054	java/lang/Throwable
    //   5040	5081	5084	java/lang/Throwable
    //   5058	5092	5092	java/lang/Throwable
    //   5114	5125	5128	java/lang/Throwable
    //   5138	5868	7327	java/lang/Throwable
    //   5228	5242	5242	java/lang/Throwable
    //   5253	5266	5269	java/lang/Throwable
    //   5258	5281	5284	java/lang/Throwable
    //   5273	5299	5302	java/lang/Throwable
    //   5288	5329	5332	java/lang/Throwable
    //   5395	5422	5425	java/lang/Throwable
    //   5412	5440	5443	java/lang/Throwable
    //   5429	5470	5473	java/lang/Throwable
    //   5447	5481	5481	java/lang/Throwable
    //   5503	5514	5517	java/lang/Throwable
    //   5570	5584	5584	java/lang/Throwable
    //   5595	5608	5611	java/lang/Throwable
    //   5600	5623	5626	java/lang/Throwable
    //   5615	5641	5644	java/lang/Throwable
    //   5630	5671	5674	java/lang/Throwable
    //   5737	5764	5767	java/lang/Throwable
    //   5754	5782	5785	java/lang/Throwable
    //   5771	5812	5815	java/lang/Throwable
    //   5789	5823	5823	java/lang/Throwable
    //   5845	5856	5859	java/lang/Throwable
    //   5869	6599	7327	java/lang/Throwable
    //   5959	5973	5973	java/lang/Throwable
    //   5984	5997	6000	java/lang/Throwable
    //   5989	6012	6015	java/lang/Throwable
    //   6004	6030	6033	java/lang/Throwable
    //   6019	6060	6063	java/lang/Throwable
    //   6126	6153	6156	java/lang/Throwable
    //   6143	6171	6174	java/lang/Throwable
    //   6160	6201	6204	java/lang/Throwable
    //   6178	6212	6212	java/lang/Throwable
    //   6234	6245	6248	java/lang/Throwable
    //   6301	6315	6315	java/lang/Throwable
    //   6326	6339	6342	java/lang/Throwable
    //   6331	6354	6357	java/lang/Throwable
    //   6346	6372	6375	java/lang/Throwable
    //   6361	6402	6405	java/lang/Throwable
    //   6468	6495	6498	java/lang/Throwable
    //   6485	6513	6516	java/lang/Throwable
    //   6502	6543	6546	java/lang/Throwable
    //   6520	6554	6554	java/lang/Throwable
    //   6576	6587	6590	java/lang/Throwable
    //   6600	7326	7327	java/lang/Throwable
    //   6690	6704	6704	java/lang/Throwable
    //   6715	6728	6731	java/lang/Throwable
    //   6720	6743	6746	java/lang/Throwable
    //   6735	6761	6764	java/lang/Throwable
    //   6750	6791	6794	java/lang/Throwable
    //   6857	6884	6887	java/lang/Throwable
    //   6874	6902	6905	java/lang/Throwable
    //   6891	6932	6935	java/lang/Throwable
    //   6909	6943	6943	java/lang/Throwable
    //   6965	6976	6979	java/lang/Throwable
    //   7032	7046	7046	java/lang/Throwable
    //   7057	7070	7073	java/lang/Throwable
    //   7062	7085	7088	java/lang/Throwable
    //   7077	7103	7106	java/lang/Throwable
    //   7092	7133	7136	java/lang/Throwable
    //   7199	7226	7229	java/lang/Throwable
    //   7216	7244	7247	java/lang/Throwable
    //   7233	7274	7277	java/lang/Throwable
    //   7251	7285	7285	java/lang/Throwable
    //   7307	7318	7321	java/lang/Throwable
  }
  
  static {
    // Byte code:
    //   0: bipush #26
    //   2: anewarray java/lang/String
    //   5: astore #5
    //   7: iconst_0
    //   8: istore_3
    //   9: ldc 'W""$Jj0@#6=&sO)DBar\\tY@ZRBT#b05\\tIhR\\tn.%^\\tLaT@M^3Sq=$vu4L#Q&|y6#)lf\\bUtG9x(P/r\\tM\\rA\\td<d\\tfus1~\\tl g; oE 7)e\mg,+w\\t\(4nH3\\tbD`"=`[\\b,c:&N=\\tqnx\\t\\t\\t|\\b\\tyQq+\\t_ThbU|M\\t.sUF\\bFQ}L6B\\teHab'
    //   11: dup
    //   12: astore_2
    //   13: invokevirtual length : ()I
    //   16: istore #4
    //   18: bipush #77
    //   20: istore_1
    //   21: iconst_m1
    //   22: istore_0
    //   23: iconst_4
    //   24: iinc #0, 1
    //   27: aload_2
    //   28: iload_0
    //   29: dup
    //   30: iload_1
    //   31: iadd
    //   32: invokevirtual substring : (II)Ljava/lang/String;
    //   35: iconst_m1
    //   36: goto -> 142
    //   39: aload #5
    //   41: swap
    //   42: iload_3
    //   43: iinc #3, 1
    //   46: swap
    //   47: aastore
    //   48: iload_0
    //   49: iload_1
    //   50: iadd
    //   51: dup
    //   52: istore_0
    //   53: iload #4
    //   55: if_icmpge -> 67
    //   58: aload_2
    //   59: iload_0
    //   60: invokevirtual charAt : (I)C
    //   63: istore_1
    //   64: goto -> 23
    //   67: ldc 'X5 dZMej9-:\\nf'
    //   69: dup
    //   70: astore_2
    //   71: invokevirtual length : ()I
    //   74: istore #4
    //   76: bipush #9
    //   78: istore_1
    //   79: iconst_m1
    //   80: istore_0
    //   81: bipush #16
    //   83: iinc #0, 1
    //   86: aload_2
    //   87: iload_0
    //   88: dup
    //   89: iload_1
    //   90: iadd
    //   91: invokevirtual substring : (II)Ljava/lang/String;
    //   94: iconst_0
    //   95: goto -> 142
    //   98: aload #5
    //   100: swap
    //   101: iload_3
    //   102: iinc #3, 1
    //   105: swap
    //   106: aastore
    //   107: iload_0
    //   108: iload_1
    //   109: iadd
    //   110: dup
    //   111: istore_0
    //   112: iload #4
    //   114: if_icmpge -> 126
    //   117: aload_2
    //   118: iload_0
    //   119: invokevirtual charAt : (I)C
    //   122: istore_1
    //   123: goto -> 81
    //   126: aload #5
    //   128: putstatic burp/Zep8.a : [Ljava/lang/String;
    //   131: bipush #26
    //   133: anewarray java/lang/String
    //   136: putstatic burp/Zep8.b : [Ljava/lang/String;
    //   139: goto -> 300
    //   142: dup_x2
    //   143: pop
    //   144: invokevirtual toCharArray : ()[C
    //   147: dup_x1
    //   148: arraylength
    //   149: dup_x2
    //   150: pop
    //   151: iconst_0
    //   152: istore #6
    //   154: dup2_x1
    //   155: pop2
    //   156: dup_x2
    //   157: iconst_1
    //   158: if_icmpgt -> 260
    //   161: dup2
    //   162: swap
    //   163: iload #6
    //   165: dup2_x1
    //   166: caload
    //   167: swap
    //   168: iload #6
    //   170: bipush #7
    //   172: irem
    //   173: tableswitch default -> 242, 0 -> 212, 1 -> 217, 2 -> 222, 3 -> 227, 4 -> 232, 5 -> 237
    //   212: bipush #40
    //   214: goto -> 244
    //   217: bipush #124
    //   219: goto -> 244
    //   222: bipush #98
    //   224: goto -> 244
    //   227: bipush #63
    //   229: goto -> 244
    //   232: bipush #50
    //   234: goto -> 244
    //   237: bipush #31
    //   239: goto -> 244
    //   242: bipush #117
    //   244: ixor
    //   245: ixor
    //   246: i2c
    //   247: castore
    //   248: iinc #6, 1
    //   251: dup
    //   252: ifne -> 260
    //   255: dup2
    //   256: dup_x1
    //   257: goto -> 165
    //   260: dup2_x1
    //   261: pop2
    //   262: dup_x2
    //   263: iload #6
    //   265: if_icmpgt -> 161
    //   268: pop
    //   269: new java/lang/String
    //   272: dup_x1
    //   273: swap
    //   274: invokespecial <init> : ([C)V
    //   277: invokevirtual intern : ()Ljava/lang/String;
    //   280: swap
    //   281: pop
    //   282: swap
    //   283: tableswitch default -> 39, 0 -> 98
    //   300: sipush #-31931
    //   303: sipush #-14952
    //   306: invokestatic a : (II)Ljava/lang/String;
    //   309: putstatic burp/Zep8.ZC : Ljava/lang/String;
    //   312: new java/math/BigInteger
    //   315: dup
    //   316: sipush #-31928
    //   319: sipush #-30564
    //   322: invokestatic a : (II)Ljava/lang/String;
    //   325: invokespecial <init> : (Ljava/lang/String;)V
    //   328: putstatic burp/Zep8.Zs : Ljava/lang/Object;
    //   331: return
  }
  
  private static Throwable a(Throwable paramThrowable) {
    return paramThrowable;
  }
  
  private static String a(int paramInt1, int paramInt2) {
    int i = (paramInt1 ^ 0xFFFF834C) & 0xFFFF;
    if (b[i] == null) {
      char[] arrayOfChar = a[i].toCharArray();
      switch (arrayOfChar[0] & 0xFF) {
        case 0:
        
        case 1:
        
        case 2:
        
        case 3:
        
        case 4:
        
        case 5:
        
        case 6:
        
        case 7:
        
        case 8:
        
        case 9:
        
        case 10:
        
        case 11:
        
        case 12:
        
        case 13:
        
        case 14:
        
        case 15:
        
        case 16:
        
        case 17:
        
        case 18:
        
        case 19:
        
        case 20:
        
        case 21:
        
        case 22:
        
        case 23:
        
        case 24:
        
        case 25:
        
        case 26:
        
        case 27:
        
        case 28:
        
        case 29:
        
        case 30:
        
        case 31:
        
        case 32:
        
        case 33:
        
        case 34:
        
        case 35:
        
        case 36:
        
        case 37:
        
        case 38:
        
        case 39:
        
        case 40:
        
        case 41:
        
        case 42:
        
        case 43:
        
        case 44:
        
        case 45:
        
        case 46:
        
        case 47:
        
        case 48:
        
        case 49:
        
        case 50:
        
        case 51:
        
        case 52:
        
        case 53:
        
        case 54:
        
        case 55:
        
        case 56:
        
        case 57:
        
        case 58:
        
        case 59:
        
        case 60:
        
        case 61:
        
        case 62:
        
        case 63:
        
        case 64:
        
        case 65:
        
        case 66:
        
        case 67:
        
        case 68:
        
        case 69:
        
        case 70:
        
        case 71:
        
        case 72:
        
        case 73:
        
        case 74:
        
        case 75:
        
        case 76:
        
        case 77:
        
        case 78:
        
        case 79:
        
        case 80:
        
        case 81:
        
        case 82:
        
        case 83:
        
        case 84:
        
        case 85:
        
        case 86:
        
        case 87:
        
        case 88:
        
        case 89:
        
        case 90:
        
        case 91:
        
        case 92:
        
        case 93:
        
        case 94:
        
        case 95:
        
        case 96:
        
        case 97:
        
        case 98:
        
        case 99:
        
        case 100:
        
        case 101:
        
        case 102:
        
        case 103:
        
        case 104:
        
        case 105:
        
        case 106:
        
        case 107:
        
        case 108:
        
        case 109:
        
        case 110:
        
        case 111:
        
        case 112:
        
        case 113:
        
        case 114:
        
        case 115:
        
        case 116:
        
        case 117:
        
        case 118:
        
        case 119:
        
        case 120:
        
        case 121:
        
        case 122:
        
        case 123:
        
        case 124:
        
        case 125:
        
        case 126:
        
        case 127:
        
        case 128:
        
        case 129:
        
        case 130:
        
        case 131:
        
        case 132:
        
        case 133:
        
        case 134:
        
        case 135:
        
        case 136:
        
        case 137:
        
        case 138:
        
        case 139:
        
        case 140:
        
        case 141:
        
        case 142:
        
        case 143:
        
        case 144:
        
        case 145:
        
        case 146:
        
        case 147:
        
        case 148:
        
        case 149:
        
        case 150:
        
        case 151:
        
        case 152:
        
        case 153:
        
        case 154:
        
        case 155:
        
        case 156:
        
        case 157:
        
        case 158:
        
        case 159:
        
        case 160:
        
        case 161:
        
        case 162:
        
        case 163:
        
        case 164:
        
        case 165:
        
        case 166:
        
        case 167:
        
        case 168:
        
        case 169:
        
        case 170:
        
        case 171:
        
        case 172:
        
        case 173:
        
        case 174:
        
        case 175:
        
        case 176:
        
        case 177:
        
        case 178:
        
        case 179:
        
        case 180:
        
        case 181:
        
        case 182:
        
        case 183:
        
        case 184:
        
        case 185:
        
        case 186:
        
        case 187:
        
        case 188:
        
        case 189:
        
        case 190:
        
        case 191:
        
        case 192:
        
        case 193:
        
        case 194:
        
        case 195:
        
        case 196:
        
        case 197:
        
        case 198:
        
        case 199:
        
        case 200:
        
        case 201:
        
        case 202:
        
        case 203:
        
        case 204:
        
        case 205:
        
        case 206:
        
        case 207:
        
        case 208:
        
        case 209:
        
        case 210:
        
        case 211:
        
        case 212:
        
        case 213:
        
        case 214:
        
        case 215:
        
        case 216:
        
        case 217:
        
        case 218:
        
        case 219:
        
        case 220:
        
        case 221:
        
        case 222:
        
        case 223:
        
        case 224:
        
        case 225:
        
        case 226:
        
        case 227:
        
        case 228:
        
        case 229:
        
        case 230:
        
        case 231:
        
        case 232:
        
        case 233:
        
        case 234:
        
        case 235:
        
        case 236:
        
        case 237:
        
        case 238:
        
        case 239:
        
        case 240:
        
        case 241:
        
        case 242:
        
        case 243:
        
        case 244:
        
        case 245:
        
        case 246:
        
        case 247:
        
        case 248:
        
        case 249:
        
        case 250:
        
        case 251:
        
        case 252:
        
        case 253:
        
        case 254:
        
        default:
          break;
      } 
      char c = '';
      int j = (paramInt2 & 0xFF) - c;
      if (j < 0)
        j += 256; 
      int k = ((paramInt2 & 0xFFFF) >>> 8) - c;
      if (k < 0)
        k += 256; 
      for (byte b = 0; b < arrayOfChar.length; b++) {
        int m = b % 2;
        if (m == 0) {
          arrayOfChar[b] = (char)(arrayOfChar[b] ^ j);
          j = ((j >>> 3 | j << 5) ^ arrayOfChar[b]) & 0xFF;
        } else {
          arrayOfChar[b] = (char)(arrayOfChar[b] ^ k);
          k = ((k >>> 3 | k << 5) ^ arrayOfChar[b]) & 0xFF;
        } 
      } 
      b[i] = (new String(arrayOfChar)).intern();
    } 
    return b[i];
  }
}


/* Location:              C:\Program Files\BurpSuitePro\burpsuite_pro.jar!\burp\Zep8.class
 * Java compiler version: 21 (65.0)
 * JD-Core Version:       1.1.3
 */