package burp;

import java.math.BigInteger;

class Zeqr extends ClassLoader {
  static Object ZM;
  
  static String Zb;
  
  private static final String[] a;
  
  private static final String[] b;
  
  static boolean ZT(Object[] paramArrayOfObject, Object paramObject) throws Throwable {
    // Byte code:
    //   0: invokestatic ZK : ()Z
    //   3: istore_2
    //   4: getstatic burp/Zs8q.ZI : Ljava/lang/Object;
    //   7: checkcast java/math/BigInteger
    //   10: getstatic burp/Zs33.ZT : Ljava/lang/Object;
    //   13: checkcast java/math/BigInteger
    //   16: invokevirtual add : (Ljava/math/BigInteger;)Ljava/math/BigInteger;
    //   19: putstatic burp/Zrcu.Zs : Ljava/lang/Object;
    //   22: getstatic burp/Zgre.ZD : Ljava/lang/Object;
    //   25: checkcast java/math/BigInteger
    //   28: getstatic burp/Ztap.ZK : Ljava/lang/Object;
    //   31: checkcast java/math/BigInteger
    //   34: invokevirtual add : (Ljava/math/BigInteger;)Ljava/math/BigInteger;
    //   37: putstatic burp/Zep8.Zs : Ljava/lang/Object;
    //   40: new java/lang/StringBuilder
    //   43: dup
    //   44: invokespecial <init> : ()V
    //   47: astore_3
    //   48: iconst_0
    //   49: istore #4
    //   51: iload #4
    //   53: bipush #32
    //   55: if_icmpge -> 1391
    //   58: iload #4
    //   60: tableswitch default -> 1384, 0 -> 204, 1 -> 241, 2 -> 278, 3 -> 315, 4 -> 352, 5 -> 389, 6 -> 426, 7 -> 463, 8 -> 500, 9 -> 537, 10 -> 574, 11 -> 611, 12 -> 648, 13 -> 685, 14 -> 722, 15 -> 759, 16 -> 796, 17 -> 833, 18 -> 870, 19 -> 907, 20 -> 944, 21 -> 981, 22 -> 1018, 23 -> 1055, 24 -> 1092, 25 -> 1129, 26 -> 1166, 27 -> 1203, 28 -> 1240, 29 -> 1277, 30 -> 1314, 31 -> 1351
    //   204: aload_3
    //   205: getstatic burp/Zmjr.Zc : Ljava/lang/String;
    //   208: getstatic burp/Zrvb.ZD : Ljava/lang/Object;
    //   211: checkcast java/math/BigInteger
    //   214: invokevirtual intValue : ()I
    //   217: bipush #32
    //   219: irem
    //   220: invokestatic abs : (I)I
    //   223: invokevirtual charAt : (I)C
    //   226: invokevirtual append : (C)Ljava/lang/StringBuilder;
    //   229: pop
    //   230: iload_2
    //   231: ifeq -> 1384
    //   234: goto -> 241
    //   237: invokestatic a : (Ljava/lang/Throwable;)Ljava/lang/Throwable;
    //   240: athrow
    //   241: aload_3
    //   242: getstatic burp/Zxo7.Zl : Ljava/lang/String;
    //   245: getstatic burp/Zmha.ZM : Ljava/lang/Object;
    //   248: checkcast java/math/BigInteger
    //   251: invokevirtual intValue : ()I
    //   254: bipush #32
    //   256: irem
    //   257: invokestatic abs : (I)I
    //   260: invokevirtual charAt : (I)C
    //   263: invokevirtual append : (C)Ljava/lang/StringBuilder;
    //   266: pop
    //   267: iload_2
    //   268: ifeq -> 1384
    //   271: goto -> 278
    //   274: invokestatic a : (Ljava/lang/Throwable;)Ljava/lang/Throwable;
    //   277: athrow
    //   278: aload_3
    //   279: getstatic burp/Zxoa.Z_ : Ljava/lang/String;
    //   282: getstatic burp/Zly0.ZB : Ljava/lang/Object;
    //   285: checkcast java/math/BigInteger
    //   288: invokevirtual intValue : ()I
    //   291: bipush #32
    //   293: irem
    //   294: invokestatic abs : (I)I
    //   297: invokevirtual charAt : (I)C
    //   300: invokevirtual append : (C)Ljava/lang/StringBuilder;
    //   303: pop
    //   304: iload_2
    //   305: ifeq -> 1384
    //   308: goto -> 315
    //   311: invokestatic a : (Ljava/lang/Throwable;)Ljava/lang/Throwable;
    //   314: athrow
    //   315: aload_3
    //   316: getstatic burp/Zex.Zn : Ljava/lang/String;
    //   319: getstatic burp/Zg97.Zc : Ljava/lang/Object;
    //   322: checkcast java/math/BigInteger
    //   325: invokevirtual intValue : ()I
    //   328: bipush #32
    //   330: irem
    //   331: invokestatic abs : (I)I
    //   334: invokevirtual charAt : (I)C
    //   337: invokevirtual append : (C)Ljava/lang/StringBuilder;
    //   340: pop
    //   341: iload_2
    //   342: ifeq -> 1384
    //   345: goto -> 352
    //   348: invokestatic a : (Ljava/lang/Throwable;)Ljava/lang/Throwable;
    //   351: athrow
    //   352: aload_3
    //   353: getstatic burp/Zs5i.ZJ : Ljava/lang/String;
    //   356: getstatic burp/Zejj.Zy : Ljava/lang/Object;
    //   359: checkcast java/math/BigInteger
    //   362: invokevirtual intValue : ()I
    //   365: bipush #32
    //   367: irem
    //   368: invokestatic abs : (I)I
    //   371: invokevirtual charAt : (I)C
    //   374: invokevirtual append : (C)Ljava/lang/StringBuilder;
    //   377: pop
    //   378: iload_2
    //   379: ifeq -> 1384
    //   382: goto -> 389
    //   385: invokestatic a : (Ljava/lang/Throwable;)Ljava/lang/Throwable;
    //   388: athrow
    //   389: aload_3
    //   390: getstatic burp/Zz35.ZH : Ljava/lang/String;
    //   393: getstatic burp/Zst7.ZI : Ljava/lang/Object;
    //   396: checkcast java/math/BigInteger
    //   399: invokevirtual intValue : ()I
    //   402: bipush #32
    //   404: irem
    //   405: invokestatic abs : (I)I
    //   408: invokevirtual charAt : (I)C
    //   411: invokevirtual append : (C)Ljava/lang/StringBuilder;
    //   414: pop
    //   415: iload_2
    //   416: ifeq -> 1384
    //   419: goto -> 426
    //   422: invokestatic a : (Ljava/lang/Throwable;)Ljava/lang/Throwable;
    //   425: athrow
    //   426: aload_3
    //   427: getstatic burp/Zzok.ZC : Ljava/lang/String;
    //   430: getstatic burp/Ztid.ZL : Ljava/lang/Object;
    //   433: checkcast java/math/BigInteger
    //   436: invokevirtual intValue : ()I
    //   439: bipush #32
    //   441: irem
    //   442: invokestatic abs : (I)I
    //   445: invokevirtual charAt : (I)C
    //   448: invokevirtual append : (C)Ljava/lang/StringBuilder;
    //   451: pop
    //   452: iload_2
    //   453: ifeq -> 1384
    //   456: goto -> 463
    //   459: invokestatic a : (Ljava/lang/Throwable;)Ljava/lang/Throwable;
    //   462: athrow
    //   463: aload_3
    //   464: getstatic burp/Zs5y.ZO : Ljava/lang/String;
    //   467: getstatic burp/Zkup.Zf : Ljava/lang/Object;
    //   470: checkcast java/math/BigInteger
    //   473: invokevirtual intValue : ()I
    //   476: bipush #32
    //   478: irem
    //   479: invokestatic abs : (I)I
    //   482: invokevirtual charAt : (I)C
    //   485: invokevirtual append : (C)Ljava/lang/StringBuilder;
    //   488: pop
    //   489: iload_2
    //   490: ifeq -> 1384
    //   493: goto -> 500
    //   496: invokestatic a : (Ljava/lang/Throwable;)Ljava/lang/Throwable;
    //   499: athrow
    //   500: aload_3
    //   501: getstatic burp/Zefn.Ze : Ljava/lang/String;
    //   504: getstatic burp/Zzuh.ZV : Ljava/lang/Object;
    //   507: checkcast java/math/BigInteger
    //   510: invokevirtual intValue : ()I
    //   513: bipush #32
    //   515: irem
    //   516: invokestatic abs : (I)I
    //   519: invokevirtual charAt : (I)C
    //   522: invokevirtual append : (C)Ljava/lang/StringBuilder;
    //   525: pop
    //   526: iload_2
    //   527: ifeq -> 1384
    //   530: goto -> 537
    //   533: invokestatic a : (Ljava/lang/Throwable;)Ljava/lang/Throwable;
    //   536: athrow
    //   537: aload_3
    //   538: getstatic burp/Zgd7.Zs : Ljava/lang/String;
    //   541: getstatic burp/Zsej.ZT : Ljava/lang/Object;
    //   544: checkcast java/math/BigInteger
    //   547: invokevirtual intValue : ()I
    //   550: bipush #32
    //   552: irem
    //   553: invokestatic abs : (I)I
    //   556: invokevirtual charAt : (I)C
    //   559: invokevirtual append : (C)Ljava/lang/StringBuilder;
    //   562: pop
    //   563: iload_2
    //   564: ifeq -> 1384
    //   567: goto -> 574
    //   570: invokestatic a : (Ljava/lang/Throwable;)Ljava/lang/Throwable;
    //   573: athrow
    //   574: aload_3
    //   575: getstatic burp/Zewo.ZM : Ljava/lang/String;
    //   578: getstatic burp/Zmuj.ZH : Ljava/lang/Object;
    //   581: checkcast java/math/BigInteger
    //   584: invokevirtual intValue : ()I
    //   587: bipush #32
    //   589: irem
    //   590: invokestatic abs : (I)I
    //   593: invokevirtual charAt : (I)C
    //   596: invokevirtual append : (C)Ljava/lang/StringBuilder;
    //   599: pop
    //   600: iload_2
    //   601: ifeq -> 1384
    //   604: goto -> 611
    //   607: invokestatic a : (Ljava/lang/Throwable;)Ljava/lang/Throwable;
    //   610: athrow
    //   611: aload_3
    //   612: getstatic burp/Zeig.Zg : Ljava/lang/String;
    //   615: getstatic burp/Zltp.ZT : Ljava/lang/Object;
    //   618: checkcast java/math/BigInteger
    //   621: invokevirtual intValue : ()I
    //   624: bipush #32
    //   626: irem
    //   627: invokestatic abs : (I)I
    //   630: invokevirtual charAt : (I)C
    //   633: invokevirtual append : (C)Ljava/lang/StringBuilder;
    //   636: pop
    //   637: iload_2
    //   638: ifeq -> 1384
    //   641: goto -> 648
    //   644: invokestatic a : (Ljava/lang/Throwable;)Ljava/lang/Throwable;
    //   647: athrow
    //   648: aload_3
    //   649: getstatic burp/Zmjr.Zc : Ljava/lang/String;
    //   652: getstatic burp/Zgde.ZG : Ljava/lang/Object;
    //   655: checkcast java/math/BigInteger
    //   658: invokevirtual intValue : ()I
    //   661: bipush #32
    //   663: irem
    //   664: invokestatic abs : (I)I
    //   667: invokevirtual charAt : (I)C
    //   670: invokevirtual append : (C)Ljava/lang/StringBuilder;
    //   673: pop
    //   674: iload_2
    //   675: ifeq -> 1384
    //   678: goto -> 685
    //   681: invokestatic a : (Ljava/lang/Throwable;)Ljava/lang/Throwable;
    //   684: athrow
    //   685: aload_3
    //   686: getstatic burp/Zr8r.Zn : Ljava/lang/String;
    //   689: getstatic burp/Zbqk.ZT : Ljava/lang/Object;
    //   692: checkcast java/math/BigInteger
    //   695: invokevirtual intValue : ()I
    //   698: bipush #32
    //   700: irem
    //   701: invokestatic abs : (I)I
    //   704: invokevirtual charAt : (I)C
    //   707: invokevirtual append : (C)Ljava/lang/StringBuilder;
    //   710: pop
    //   711: iload_2
    //   712: ifeq -> 1384
    //   715: goto -> 722
    //   718: invokestatic a : (Ljava/lang/Throwable;)Ljava/lang/Throwable;
    //   721: athrow
    //   722: aload_3
    //   723: getstatic burp/Zl3n.Zy : Ljava/lang/String;
    //   726: getstatic burp/Zl1u.Zq : Ljava/lang/Object;
    //   729: checkcast java/math/BigInteger
    //   732: invokevirtual intValue : ()I
    //   735: bipush #32
    //   737: irem
    //   738: invokestatic abs : (I)I
    //   741: invokevirtual charAt : (I)C
    //   744: invokevirtual append : (C)Ljava/lang/StringBuilder;
    //   747: pop
    //   748: iload_2
    //   749: ifeq -> 1384
    //   752: goto -> 759
    //   755: invokestatic a : (Ljava/lang/Throwable;)Ljava/lang/Throwable;
    //   758: athrow
    //   759: aload_3
    //   760: getstatic burp/Zejj.ZQ : Ljava/lang/String;
    //   763: getstatic burp/Zg7z.ZV : Ljava/lang/Object;
    //   766: checkcast java/math/BigInteger
    //   769: invokevirtual intValue : ()I
    //   772: bipush #32
    //   774: irem
    //   775: invokestatic abs : (I)I
    //   778: invokevirtual charAt : (I)C
    //   781: invokevirtual append : (C)Ljava/lang/StringBuilder;
    //   784: pop
    //   785: iload_2
    //   786: ifeq -> 1384
    //   789: goto -> 796
    //   792: invokestatic a : (Ljava/lang/Throwable;)Ljava/lang/Throwable;
    //   795: athrow
    //   796: aload_3
    //   797: getstatic burp/Zl2g.ZI : Ljava/lang/String;
    //   800: getstatic burp/Zxee.Zj : Ljava/lang/Object;
    //   803: checkcast java/math/BigInteger
    //   806: invokevirtual intValue : ()I
    //   809: bipush #32
    //   811: irem
    //   812: invokestatic abs : (I)I
    //   815: invokevirtual charAt : (I)C
    //   818: invokevirtual append : (C)Ljava/lang/StringBuilder;
    //   821: pop
    //   822: iload_2
    //   823: ifeq -> 1384
    //   826: goto -> 833
    //   829: invokestatic a : (Ljava/lang/Throwable;)Ljava/lang/Throwable;
    //   832: athrow
    //   833: aload_3
    //   834: getstatic burp/Zr_k.Zu : Ljava/lang/String;
    //   837: getstatic burp/Zrfl.Z_ : Ljava/lang/Object;
    //   840: checkcast java/math/BigInteger
    //   843: invokevirtual intValue : ()I
    //   846: bipush #32
    //   848: irem
    //   849: invokestatic abs : (I)I
    //   852: invokevirtual charAt : (I)C
    //   855: invokevirtual append : (C)Ljava/lang/StringBuilder;
    //   858: pop
    //   859: iload_2
    //   860: ifeq -> 1384
    //   863: goto -> 870
    //   866: invokestatic a : (Ljava/lang/Throwable;)Ljava/lang/Throwable;
    //   869: athrow
    //   870: aload_3
    //   871: getstatic burp/Zzoi.ZR : Ljava/lang/String;
    //   874: getstatic burp/Zxf8.Zz : Ljava/lang/Object;
    //   877: checkcast java/math/BigInteger
    //   880: invokevirtual intValue : ()I
    //   883: bipush #32
    //   885: irem
    //   886: invokestatic abs : (I)I
    //   889: invokevirtual charAt : (I)C
    //   892: invokevirtual append : (C)Ljava/lang/StringBuilder;
    //   895: pop
    //   896: iload_2
    //   897: ifeq -> 1384
    //   900: goto -> 907
    //   903: invokestatic a : (Ljava/lang/Throwable;)Ljava/lang/Throwable;
    //   906: athrow
    //   907: aload_3
    //   908: getstatic burp/Zzai.Zy : Ljava/lang/String;
    //   911: getstatic burp/Zsuw.ZB : Ljava/lang/Object;
    //   914: checkcast java/math/BigInteger
    //   917: invokevirtual intValue : ()I
    //   920: bipush #32
    //   922: irem
    //   923: invokestatic abs : (I)I
    //   926: invokevirtual charAt : (I)C
    //   929: invokevirtual append : (C)Ljava/lang/StringBuilder;
    //   932: pop
    //   933: iload_2
    //   934: ifeq -> 1384
    //   937: goto -> 944
    //   940: invokestatic a : (Ljava/lang/Throwable;)Ljava/lang/Throwable;
    //   943: athrow
    //   944: aload_3
    //   945: getstatic burp/Zm8i.Z_ : Ljava/lang/String;
    //   948: getstatic burp/Zttj.ZF : Ljava/lang/Object;
    //   951: checkcast java/math/BigInteger
    //   954: invokevirtual intValue : ()I
    //   957: bipush #32
    //   959: irem
    //   960: invokestatic abs : (I)I
    //   963: invokevirtual charAt : (I)C
    //   966: invokevirtual append : (C)Ljava/lang/StringBuilder;
    //   969: pop
    //   970: iload_2
    //   971: ifeq -> 1384
    //   974: goto -> 981
    //   977: invokestatic a : (Ljava/lang/Throwable;)Ljava/lang/Throwable;
    //   980: athrow
    //   981: aload_3
    //   982: getstatic burp/Zz75.ZT : Ljava/lang/String;
    //   985: getstatic burp/Zgds.Z_ : Ljava/lang/Object;
    //   988: checkcast java/math/BigInteger
    //   991: invokevirtual intValue : ()I
    //   994: bipush #32
    //   996: irem
    //   997: invokestatic abs : (I)I
    //   1000: invokevirtual charAt : (I)C
    //   1003: invokevirtual append : (C)Ljava/lang/StringBuilder;
    //   1006: pop
    //   1007: iload_2
    //   1008: ifeq -> 1384
    //   1011: goto -> 1018
    //   1014: invokestatic a : (Ljava/lang/Throwable;)Ljava/lang/Throwable;
    //   1017: athrow
    //   1018: aload_3
    //   1019: getstatic burp/Zgw0.ZL : Ljava/lang/String;
    //   1022: getstatic burp/Zz5d.Zk : Ljava/lang/Object;
    //   1025: checkcast java/math/BigInteger
    //   1028: invokevirtual intValue : ()I
    //   1031: bipush #32
    //   1033: irem
    //   1034: invokestatic abs : (I)I
    //   1037: invokevirtual charAt : (I)C
    //   1040: invokevirtual append : (C)Ljava/lang/StringBuilder;
    //   1043: pop
    //   1044: iload_2
    //   1045: ifeq -> 1384
    //   1048: goto -> 1055
    //   1051: invokestatic a : (Ljava/lang/Throwable;)Ljava/lang/Throwable;
    //   1054: athrow
    //   1055: aload_3
    //   1056: getstatic burp/Zsn6.Zs : Ljava/lang/String;
    //   1059: getstatic burp/Zr1t.ZP : Ljava/lang/Object;
    //   1062: checkcast java/math/BigInteger
    //   1065: invokevirtual intValue : ()I
    //   1068: bipush #32
    //   1070: irem
    //   1071: invokestatic abs : (I)I
    //   1074: invokevirtual charAt : (I)C
    //   1077: invokevirtual append : (C)Ljava/lang/StringBuilder;
    //   1080: pop
    //   1081: iload_2
    //   1082: ifeq -> 1384
    //   1085: goto -> 1092
    //   1088: invokestatic a : (Ljava/lang/Throwable;)Ljava/lang/Throwable;
    //   1091: athrow
    //   1092: aload_3
    //   1093: getstatic burp/Zspk.ZA : Ljava/lang/String;
    //   1096: getstatic burp/Zb0s.Zv : Ljava/lang/Object;
    //   1099: checkcast java/math/BigInteger
    //   1102: invokevirtual intValue : ()I
    //   1105: bipush #32
    //   1107: irem
    //   1108: invokestatic abs : (I)I
    //   1111: invokevirtual charAt : (I)C
    //   1114: invokevirtual append : (C)Ljava/lang/StringBuilder;
    //   1117: pop
    //   1118: iload_2
    //   1119: ifeq -> 1384
    //   1122: goto -> 1129
    //   1125: invokestatic a : (Ljava/lang/Throwable;)Ljava/lang/Throwable;
    //   1128: athrow
    //   1129: aload_3
    //   1130: getstatic burp/Zx0t.Ze : Ljava/lang/String;
    //   1133: getstatic burp/Zmlr.Zh : Ljava/lang/Object;
    //   1136: checkcast java/math/BigInteger
    //   1139: invokevirtual intValue : ()I
    //   1142: bipush #32
    //   1144: irem
    //   1145: invokestatic abs : (I)I
    //   1148: invokevirtual charAt : (I)C
    //   1151: invokevirtual append : (C)Ljava/lang/StringBuilder;
    //   1154: pop
    //   1155: iload_2
    //   1156: ifeq -> 1384
    //   1159: goto -> 1166
    //   1162: invokestatic a : (Ljava/lang/Throwable;)Ljava/lang/Throwable;
    //   1165: athrow
    //   1166: aload_3
    //   1167: getstatic burp/Zem6.Zp : Ljava/lang/String;
    //   1170: getstatic burp/Zshq.ZK : Ljava/lang/Object;
    //   1173: checkcast java/math/BigInteger
    //   1176: invokevirtual intValue : ()I
    //   1179: bipush #32
    //   1181: irem
    //   1182: invokestatic abs : (I)I
    //   1185: invokevirtual charAt : (I)C
    //   1188: invokevirtual append : (C)Ljava/lang/StringBuilder;
    //   1191: pop
    //   1192: iload_2
    //   1193: ifeq -> 1384
    //   1196: goto -> 1203
    //   1199: invokestatic a : (Ljava/lang/Throwable;)Ljava/lang/Throwable;
    //   1202: athrow
    //   1203: aload_3
    //   1204: getstatic burp/Zxn5.ZI : Ljava/lang/String;
    //   1207: getstatic burp/Zbxa.ZS : Ljava/lang/Object;
    //   1210: checkcast java/math/BigInteger
    //   1213: invokevirtual intValue : ()I
    //   1216: bipush #32
    //   1218: irem
    //   1219: invokestatic abs : (I)I
    //   1222: invokevirtual charAt : (I)C
    //   1225: invokevirtual append : (C)Ljava/lang/StringBuilder;
    //   1228: pop
    //   1229: iload_2
    //   1230: ifeq -> 1384
    //   1233: goto -> 1240
    //   1236: invokestatic a : (Ljava/lang/Throwable;)Ljava/lang/Throwable;
    //   1239: athrow
    //   1240: aload_3
    //   1241: getstatic burp/Zm3x.Zu : Ljava/lang/String;
    //   1244: getstatic burp/Zrdy.Zt : Ljava/lang/Object;
    //   1247: checkcast java/math/BigInteger
    //   1250: invokevirtual intValue : ()I
    //   1253: bipush #32
    //   1255: irem
    //   1256: invokestatic abs : (I)I
    //   1259: invokevirtual charAt : (I)C
    //   1262: invokevirtual append : (C)Ljava/lang/StringBuilder;
    //   1265: pop
    //   1266: iload_2
    //   1267: ifeq -> 1384
    //   1270: goto -> 1277
    //   1273: invokestatic a : (Ljava/lang/Throwable;)Ljava/lang/Throwable;
    //   1276: athrow
    //   1277: aload_3
    //   1278: getstatic burp/Zlsw.ZE : Ljava/lang/String;
    //   1281: getstatic burp/Zg4k.ZE : Ljava/lang/Object;
    //   1284: checkcast java/math/BigInteger
    //   1287: invokevirtual intValue : ()I
    //   1290: bipush #32
    //   1292: irem
    //   1293: invokestatic abs : (I)I
    //   1296: invokevirtual charAt : (I)C
    //   1299: invokevirtual append : (C)Ljava/lang/StringBuilder;
    //   1302: pop
    //   1303: iload_2
    //   1304: ifeq -> 1384
    //   1307: goto -> 1314
    //   1310: invokestatic a : (Ljava/lang/Throwable;)Ljava/lang/Throwable;
    //   1313: athrow
    //   1314: aload_3
    //   1315: getstatic burp/Ze0z.ZU : Ljava/lang/String;
    //   1318: getstatic burp/Zex.ZO : Ljava/lang/Object;
    //   1321: checkcast java/math/BigInteger
    //   1324: invokevirtual intValue : ()I
    //   1327: bipush #32
    //   1329: irem
    //   1330: invokestatic abs : (I)I
    //   1333: invokevirtual charAt : (I)C
    //   1336: invokevirtual append : (C)Ljava/lang/StringBuilder;
    //   1339: pop
    //   1340: iload_2
    //   1341: ifeq -> 1384
    //   1344: goto -> 1351
    //   1347: invokestatic a : (Ljava/lang/Throwable;)Ljava/lang/Throwable;
    //   1350: athrow
    //   1351: aload_3
    //   1352: getstatic burp/Ze57.ZV : Ljava/lang/String;
    //   1355: getstatic burp/Zsn6.Zo : Ljava/lang/Object;
    //   1358: checkcast java/math/BigInteger
    //   1361: invokevirtual intValue : ()I
    //   1364: bipush #32
    //   1366: irem
    //   1367: invokestatic abs : (I)I
    //   1370: invokevirtual charAt : (I)C
    //   1373: invokevirtual append : (C)Ljava/lang/StringBuilder;
    //   1376: pop
    //   1377: goto -> 1384
    //   1380: invokestatic a : (Ljava/lang/Throwable;)Ljava/lang/Throwable;
    //   1383: athrow
    //   1384: iinc #4, 1
    //   1387: iload_2
    //   1388: ifeq -> 51
    //   1391: aload_3
    //   1392: invokevirtual toString : ()Ljava/lang/String;
    //   1395: putstatic burp/Zgyk.ZB : Ljava/lang/String;
    //   1398: sipush #-10050
    //   1401: sipush #-27077
    //   1404: invokestatic a : (II)Ljava/lang/String;
    //   1407: iconst_1
    //   1408: ldc burp/Zeqr
    //   1410: invokevirtual getClassLoader : ()Ljava/lang/ClassLoader;
    //   1413: invokestatic forName : (Ljava/lang/String;ZLjava/lang/ClassLoader;)Ljava/lang/Class;
    //   1416: invokevirtual getDeclaredFields : ()[Ljava/lang/reflect/Field;
    //   1419: astore #4
    //   1421: aload #4
    //   1423: arraylength
    //   1424: istore #5
    //   1426: iconst_0
    //   1427: istore #6
    //   1429: iload #6
    //   1431: iload #5
    //   1433: if_icmpge -> 1571
    //   1436: aload #4
    //   1438: iload #6
    //   1440: aaload
    //   1441: astore #7
    //   1443: aload #7
    //   1445: invokevirtual getModifiers : ()I
    //   1448: invokestatic isStatic : (I)Z
    //   1451: ifne -> 1461
    //   1454: goto -> 1564
    //   1457: invokestatic a : (Ljava/lang/Throwable;)Ljava/lang/Throwable;
    //   1460: athrow
    //   1461: aload #7
    //   1463: invokevirtual getType : ()Ljava/lang/Class;
    //   1466: astore #8
    //   1468: aload #8
    //   1470: ifnull -> 1551
    //   1473: aload #8
    //   1475: invokevirtual isPrimitive : ()Z
    //   1478: ifne -> 1551
    //   1481: goto -> 1488
    //   1484: invokestatic a : (Ljava/lang/Throwable;)Ljava/lang/Throwable;
    //   1487: athrow
    //   1488: aload #8
    //   1490: invokevirtual getPackage : ()Ljava/lang/Package;
    //   1493: ifnull -> 1551
    //   1496: goto -> 1503
    //   1499: invokestatic a : (Ljava/lang/Throwable;)Ljava/lang/Throwable;
    //   1502: athrow
    //   1503: aload #8
    //   1505: invokevirtual getPackage : ()Ljava/lang/Package;
    //   1508: invokevirtual getName : ()Ljava/lang/String;
    //   1511: ifnull -> 1551
    //   1514: goto -> 1521
    //   1517: invokestatic a : (Ljava/lang/Throwable;)Ljava/lang/Throwable;
    //   1520: athrow
    //   1521: aload #8
    //   1523: invokevirtual getPackage : ()Ljava/lang/Package;
    //   1526: invokevirtual getName : ()Ljava/lang/String;
    //   1529: sipush #-10072
    //   1532: sipush #16673
    //   1535: invokestatic a : (II)Ljava/lang/String;
    //   1538: invokevirtual startsWith : (Ljava/lang/String;)Z
    //   1541: ifne -> 1551
    //   1544: goto -> 1551
    //   1547: invokestatic a : (Ljava/lang/Throwable;)Ljava/lang/Throwable;
    //   1550: athrow
    //   1551: aload #7
    //   1553: iconst_1
    //   1554: invokevirtual setAccessible : (Z)V
    //   1557: aload #7
    //   1559: aconst_null
    //   1560: invokevirtual get : (Ljava/lang/Object;)Ljava/lang/Object;
    //   1563: pop
    //   1564: iinc #6, 1
    //   1567: iload_2
    //   1568: ifeq -> 1429
    //   1571: sipush #-10065
    //   1574: sipush #-32695
    //   1577: invokestatic a : (II)Ljava/lang/String;
    //   1580: invokestatic forName : (Ljava/lang/String;)Ljava/lang/Class;
    //   1583: invokevirtual getDeclaredMethods : ()[Ljava/lang/reflect/Method;
    //   1586: astore #4
    //   1588: aload #4
    //   1590: arraylength
    //   1591: istore #5
    //   1593: iconst_0
    //   1594: istore #6
    //   1596: iload #6
    //   1598: iload #5
    //   1600: if_icmpge -> 1712
    //   1603: aload #4
    //   1605: iload #6
    //   1607: aaload
    //   1608: astore #7
    //   1610: aload #7
    //   1612: invokevirtual getParameterTypes : ()[Ljava/lang/Class;
    //   1615: pop
    //   1616: aload #7
    //   1618: invokevirtual getModifiers : ()I
    //   1621: invokestatic isStatic : (I)Z
    //   1624: ifeq -> 1698
    //   1627: aload #7
    //   1629: invokevirtual getParameterTypes : ()[Ljava/lang/Class;
    //   1632: arraylength
    //   1633: iconst_2
    //   1634: if_icmpne -> 1698
    //   1637: goto -> 1644
    //   1640: invokestatic a : (Ljava/lang/Throwable;)Ljava/lang/Throwable;
    //   1643: athrow
    //   1644: aload #7
    //   1646: invokevirtual getReturnType : ()Ljava/lang/Class;
    //   1649: getstatic java/lang/Boolean.TYPE : Ljava/lang/Class;
    //   1652: if_acmpne -> 1698
    //   1655: goto -> 1662
    //   1658: invokestatic a : (Ljava/lang/Throwable;)Ljava/lang/Throwable;
    //   1661: athrow
    //   1662: aload #7
    //   1664: iconst_1
    //   1665: invokevirtual setAccessible : (Z)V
    //   1668: aload #7
    //   1670: aconst_null
    //   1671: iconst_2
    //   1672: anewarray java/lang/Object
    //   1675: dup
    //   1676: iconst_0
    //   1677: aload_0
    //   1678: aastore
    //   1679: dup
    //   1680: iconst_1
    //   1681: aload_1
    //   1682: aastore
    //   1683: invokevirtual invoke : (Ljava/lang/Object;[Ljava/lang/Object;)Ljava/lang/Object;
    //   1686: pop
    //   1687: iload_2
    //   1688: ifeq -> 1712
    //   1691: goto -> 1698
    //   1694: invokestatic a : (Ljava/lang/Throwable;)Ljava/lang/Throwable;
    //   1697: athrow
    //   1698: iinc #6, 1
    //   1701: iload_2
    //   1702: ifeq -> 1596
    //   1705: goto -> 1712
    //   1708: invokestatic a : (Ljava/lang/Throwable;)Ljava/lang/Throwable;
    //   1711: athrow
    //   1712: sipush #-10067
    //   1715: sipush #19621
    //   1718: invokestatic a : (II)Ljava/lang/String;
    //   1721: iconst_1
    //   1722: ldc burp/Zxso
    //   1724: invokevirtual getClassLoader : ()Ljava/lang/ClassLoader;
    //   1727: invokestatic forName : (Ljava/lang/String;ZLjava/lang/ClassLoader;)Ljava/lang/Class;
    //   1730: invokevirtual getDeclaredFields : ()[Ljava/lang/reflect/Field;
    //   1733: astore #4
    //   1735: aload #4
    //   1737: arraylength
    //   1738: istore #5
    //   1740: iconst_0
    //   1741: istore #6
    //   1743: iload #6
    //   1745: iload #5
    //   1747: if_icmpge -> 1885
    //   1750: aload #4
    //   1752: iload #6
    //   1754: aaload
    //   1755: astore #7
    //   1757: aload #7
    //   1759: invokevirtual getModifiers : ()I
    //   1762: invokestatic isStatic : (I)Z
    //   1765: ifne -> 1775
    //   1768: goto -> 1878
    //   1771: invokestatic a : (Ljava/lang/Throwable;)Ljava/lang/Throwable;
    //   1774: athrow
    //   1775: aload #7
    //   1777: invokevirtual getType : ()Ljava/lang/Class;
    //   1780: astore #8
    //   1782: aload #8
    //   1784: ifnull -> 1865
    //   1787: aload #8
    //   1789: invokevirtual isPrimitive : ()Z
    //   1792: ifne -> 1865
    //   1795: goto -> 1802
    //   1798: invokestatic a : (Ljava/lang/Throwable;)Ljava/lang/Throwable;
    //   1801: athrow
    //   1802: aload #8
    //   1804: invokevirtual getPackage : ()Ljava/lang/Package;
    //   1807: ifnull -> 1865
    //   1810: goto -> 1817
    //   1813: invokestatic a : (Ljava/lang/Throwable;)Ljava/lang/Throwable;
    //   1816: athrow
    //   1817: aload #8
    //   1819: invokevirtual getPackage : ()Ljava/lang/Package;
    //   1822: invokevirtual getName : ()Ljava/lang/String;
    //   1825: ifnull -> 1865
    //   1828: goto -> 1835
    //   1831: invokestatic a : (Ljava/lang/Throwable;)Ljava/lang/Throwable;
    //   1834: athrow
    //   1835: aload #8
    //   1837: invokevirtual getPackage : ()Ljava/lang/Package;
    //   1840: invokevirtual getName : ()Ljava/lang/String;
    //   1843: sipush #-10057
    //   1846: sipush #-11276
    //   1849: invokestatic a : (II)Ljava/lang/String;
    //   1852: invokevirtual startsWith : (Ljava/lang/String;)Z
    //   1855: ifne -> 1865
    //   1858: goto -> 1865
    //   1861: invokestatic a : (Ljava/lang/Throwable;)Ljava/lang/Throwable;
    //   1864: athrow
    //   1865: aload #7
    //   1867: iconst_1
    //   1868: invokevirtual setAccessible : (Z)V
    //   1871: aload #7
    //   1873: aconst_null
    //   1874: invokevirtual get : (Ljava/lang/Object;)Ljava/lang/Object;
    //   1877: pop
    //   1878: iinc #6, 1
    //   1881: iload_2
    //   1882: ifeq -> 1743
    //   1885: sipush #-10079
    //   1888: sipush #23865
    //   1891: invokestatic a : (II)Ljava/lang/String;
    //   1894: invokestatic forName : (Ljava/lang/String;)Ljava/lang/Class;
    //   1897: invokevirtual getDeclaredMethods : ()[Ljava/lang/reflect/Method;
    //   1900: astore #4
    //   1902: aload #4
    //   1904: arraylength
    //   1905: istore #5
    //   1907: iconst_0
    //   1908: istore #6
    //   1910: iload #6
    //   1912: iload #5
    //   1914: if_icmpge -> 2047
    //   1917: aload #4
    //   1919: iload #6
    //   1921: aaload
    //   1922: astore #7
    //   1924: aload #7
    //   1926: invokevirtual getParameterTypes : ()[Ljava/lang/Class;
    //   1929: pop
    //   1930: aload #7
    //   1932: invokevirtual getModifiers : ()I
    //   1935: invokestatic isStatic : (I)Z
    //   1938: ifeq -> 2033
    //   1941: aload #7
    //   1943: invokevirtual getParameterTypes : ()[Ljava/lang/Class;
    //   1946: arraylength
    //   1947: iconst_2
    //   1948: if_icmpne -> 2033
    //   1951: goto -> 1958
    //   1954: invokestatic a : (Ljava/lang/Throwable;)Ljava/lang/Throwable;
    //   1957: athrow
    //   1958: aload #7
    //   1960: invokevirtual getReturnType : ()Ljava/lang/Class;
    //   1963: getstatic java/lang/Void.TYPE : Ljava/lang/Class;
    //   1966: invokevirtual equals : (Ljava/lang/Object;)Z
    //   1969: ifeq -> 2033
    //   1972: goto -> 1979
    //   1975: invokestatic a : (Ljava/lang/Throwable;)Ljava/lang/Throwable;
    //   1978: athrow
    //   1979: aload #7
    //   1981: iconst_1
    //   1982: invokevirtual setAccessible : (Z)V
    //   1985: aload #7
    //   1987: aconst_null
    //   1988: iconst_2
    //   1989: anewarray java/lang/Object
    //   1992: dup
    //   1993: iconst_0
    //   1994: aload_0
    //   1995: aastore
    //   1996: dup
    //   1997: iconst_1
    //   1998: aload_1
    //   1999: ifnonnull -> 2017
    //   2002: goto -> 2009
    //   2005: invokestatic a : (Ljava/lang/Throwable;)Ljava/lang/Throwable;
    //   2008: athrow
    //   2009: aload_1
    //   2010: goto -> 2024
    //   2013: invokestatic a : (Ljava/lang/Throwable;)Ljava/lang/Throwable;
    //   2016: athrow
    //   2017: aload_1
    //   2018: checkcast [B
    //   2021: invokevirtual clone : ()Ljava/lang/Object;
    //   2024: aastore
    //   2025: invokevirtual invoke : (Ljava/lang/Object;[Ljava/lang/Object;)Ljava/lang/Object;
    //   2028: pop
    //   2029: iload_2
    //   2030: ifeq -> 2047
    //   2033: iinc #6, 1
    //   2036: iload_2
    //   2037: ifeq -> 1910
    //   2040: goto -> 2047
    //   2043: invokestatic a : (Ljava/lang/Throwable;)Ljava/lang/Throwable;
    //   2046: athrow
    //   2047: iconst_0
    //   2048: istore #4
    //   2050: getstatic burp/Zg27.ZP : Ljava/lang/String;
    //   2053: getstatic burp/Zlxh.ZU : Ljava/lang/Object;
    //   2056: checkcast java/math/BigInteger
    //   2059: invokevirtual intValue : ()I
    //   2062: bipush #32
    //   2064: irem
    //   2065: invokestatic abs : (I)I
    //   2068: invokevirtual charAt : (I)C
    //   2071: getstatic burp/Zmy3.ZP : Ljava/lang/String;
    //   2074: getstatic burp/Zd0.ZT : Ljava/lang/Object;
    //   2077: checkcast java/math/BigInteger
    //   2080: invokevirtual intValue : ()I
    //   2083: bipush #32
    //   2085: irem
    //   2086: invokestatic abs : (I)I
    //   2089: invokevirtual charAt : (I)C
    //   2092: if_icmple -> 2437
    //   2095: sipush #-10058
    //   2098: sipush #17281
    //   2101: invokestatic a : (II)Ljava/lang/String;
    //   2104: iconst_1
    //   2105: ldc burp/Zs5i
    //   2107: invokevirtual getClassLoader : ()Ljava/lang/ClassLoader;
    //   2110: invokestatic forName : (Ljava/lang/String;ZLjava/lang/ClassLoader;)Ljava/lang/Class;
    //   2113: invokevirtual getDeclaredFields : ()[Ljava/lang/reflect/Field;
    //   2116: astore #5
    //   2118: aload #5
    //   2120: arraylength
    //   2121: istore #6
    //   2123: iconst_0
    //   2124: istore #7
    //   2126: iload #7
    //   2128: iload #6
    //   2130: if_icmpge -> 2268
    //   2133: aload #5
    //   2135: iload #7
    //   2137: aaload
    //   2138: astore #8
    //   2140: aload #8
    //   2142: invokevirtual getModifiers : ()I
    //   2145: invokestatic isStatic : (I)Z
    //   2148: ifne -> 2158
    //   2151: goto -> 2261
    //   2154: invokestatic a : (Ljava/lang/Throwable;)Ljava/lang/Throwable;
    //   2157: athrow
    //   2158: aload #8
    //   2160: invokevirtual getType : ()Ljava/lang/Class;
    //   2163: astore #9
    //   2165: aload #9
    //   2167: ifnull -> 2248
    //   2170: aload #9
    //   2172: invokevirtual isPrimitive : ()Z
    //   2175: ifne -> 2248
    //   2178: goto -> 2185
    //   2181: invokestatic a : (Ljava/lang/Throwable;)Ljava/lang/Throwable;
    //   2184: athrow
    //   2185: aload #9
    //   2187: invokevirtual getPackage : ()Ljava/lang/Package;
    //   2190: ifnull -> 2248
    //   2193: goto -> 2200
    //   2196: invokestatic a : (Ljava/lang/Throwable;)Ljava/lang/Throwable;
    //   2199: athrow
    //   2200: aload #9
    //   2202: invokevirtual getPackage : ()Ljava/lang/Package;
    //   2205: invokevirtual getName : ()Ljava/lang/String;
    //   2208: ifnull -> 2248
    //   2211: goto -> 2218
    //   2214: invokestatic a : (Ljava/lang/Throwable;)Ljava/lang/Throwable;
    //   2217: athrow
    //   2218: aload #9
    //   2220: invokevirtual getPackage : ()Ljava/lang/Package;
    //   2223: invokevirtual getName : ()Ljava/lang/String;
    //   2226: sipush #-10057
    //   2229: sipush #-11276
    //   2232: invokestatic a : (II)Ljava/lang/String;
    //   2235: invokevirtual startsWith : (Ljava/lang/String;)Z
    //   2238: ifne -> 2248
    //   2241: goto -> 2248
    //   2244: invokestatic a : (Ljava/lang/Throwable;)Ljava/lang/Throwable;
    //   2247: athrow
    //   2248: aload #8
    //   2250: iconst_1
    //   2251: invokevirtual setAccessible : (Z)V
    //   2254: aload #8
    //   2256: aconst_null
    //   2257: invokevirtual get : (Ljava/lang/Object;)Ljava/lang/Object;
    //   2260: pop
    //   2261: iinc #7, 1
    //   2264: iload_2
    //   2265: ifeq -> 2126
    //   2268: sipush #-10049
    //   2271: sipush #-8047
    //   2274: invokestatic a : (II)Ljava/lang/String;
    //   2277: invokestatic forName : (Ljava/lang/String;)Ljava/lang/Class;
    //   2280: invokevirtual getDeclaredMethods : ()[Ljava/lang/reflect/Method;
    //   2283: astore #5
    //   2285: aload #5
    //   2287: arraylength
    //   2288: istore #6
    //   2290: iconst_0
    //   2291: istore #7
    //   2293: iload #7
    //   2295: iload #6
    //   2297: if_icmpge -> 2434
    //   2300: aload #5
    //   2302: iload #7
    //   2304: aaload
    //   2305: astore #8
    //   2307: aload #8
    //   2309: invokevirtual getParameterTypes : ()[Ljava/lang/Class;
    //   2312: pop
    //   2313: aload #8
    //   2315: invokevirtual getModifiers : ()I
    //   2318: invokestatic isStatic : (I)Z
    //   2321: ifeq -> 2420
    //   2324: aload #8
    //   2326: invokevirtual getParameterTypes : ()[Ljava/lang/Class;
    //   2329: arraylength
    //   2330: iconst_2
    //   2331: if_icmpne -> 2420
    //   2334: goto -> 2341
    //   2337: invokestatic a : (Ljava/lang/Throwable;)Ljava/lang/Throwable;
    //   2340: athrow
    //   2341: aload #8
    //   2343: invokevirtual getReturnType : ()Ljava/lang/Class;
    //   2346: getstatic java/lang/Boolean.TYPE : Ljava/lang/Class;
    //   2349: if_acmpne -> 2420
    //   2352: goto -> 2359
    //   2355: invokestatic a : (Ljava/lang/Throwable;)Ljava/lang/Throwable;
    //   2358: athrow
    //   2359: aload #8
    //   2361: iconst_1
    //   2362: invokevirtual setAccessible : (Z)V
    //   2365: aload #8
    //   2367: aconst_null
    //   2368: iconst_2
    //   2369: anewarray java/lang/Object
    //   2372: dup
    //   2373: iconst_0
    //   2374: aload_0
    //   2375: aastore
    //   2376: dup
    //   2377: iconst_1
    //   2378: aload_1
    //   2379: ifnonnull -> 2397
    //   2382: goto -> 2389
    //   2385: invokestatic a : (Ljava/lang/Throwable;)Ljava/lang/Throwable;
    //   2388: athrow
    //   2389: aload_1
    //   2390: goto -> 2404
    //   2393: invokestatic a : (Ljava/lang/Throwable;)Ljava/lang/Throwable;
    //   2396: athrow
    //   2397: aload_1
    //   2398: checkcast [B
    //   2401: invokevirtual clone : ()Ljava/lang/Object;
    //   2404: aastore
    //   2405: invokevirtual invoke : (Ljava/lang/Object;[Ljava/lang/Object;)Ljava/lang/Object;
    //   2408: checkcast java/lang/Boolean
    //   2411: invokevirtual booleanValue : ()Z
    //   2414: istore #4
    //   2416: iload_2
    //   2417: ifeq -> 2434
    //   2420: iinc #7, 1
    //   2423: iload_2
    //   2424: ifeq -> 2293
    //   2427: goto -> 2434
    //   2430: invokestatic a : (Ljava/lang/Throwable;)Ljava/lang/Throwable;
    //   2433: athrow
    //   2434: goto -> 2776
    //   2437: sipush #-10056
    //   2440: sipush #15707
    //   2443: invokestatic a : (II)Ljava/lang/String;
    //   2446: iconst_1
    //   2447: ldc burp/Zms1
    //   2449: invokevirtual getClassLoader : ()Ljava/lang/ClassLoader;
    //   2452: invokestatic forName : (Ljava/lang/String;ZLjava/lang/ClassLoader;)Ljava/lang/Class;
    //   2455: invokevirtual getDeclaredFields : ()[Ljava/lang/reflect/Field;
    //   2458: astore #5
    //   2460: aload #5
    //   2462: arraylength
    //   2463: istore #6
    //   2465: iconst_0
    //   2466: istore #7
    //   2468: iload #7
    //   2470: iload #6
    //   2472: if_icmpge -> 2610
    //   2475: aload #5
    //   2477: iload #7
    //   2479: aaload
    //   2480: astore #8
    //   2482: aload #8
    //   2484: invokevirtual getModifiers : ()I
    //   2487: invokestatic isStatic : (I)Z
    //   2490: ifne -> 2500
    //   2493: goto -> 2603
    //   2496: invokestatic a : (Ljava/lang/Throwable;)Ljava/lang/Throwable;
    //   2499: athrow
    //   2500: aload #8
    //   2502: invokevirtual getType : ()Ljava/lang/Class;
    //   2505: astore #9
    //   2507: aload #9
    //   2509: ifnull -> 2590
    //   2512: aload #9
    //   2514: invokevirtual isPrimitive : ()Z
    //   2517: ifne -> 2590
    //   2520: goto -> 2527
    //   2523: invokestatic a : (Ljava/lang/Throwable;)Ljava/lang/Throwable;
    //   2526: athrow
    //   2527: aload #9
    //   2529: invokevirtual getPackage : ()Ljava/lang/Package;
    //   2532: ifnull -> 2590
    //   2535: goto -> 2542
    //   2538: invokestatic a : (Ljava/lang/Throwable;)Ljava/lang/Throwable;
    //   2541: athrow
    //   2542: aload #9
    //   2544: invokevirtual getPackage : ()Ljava/lang/Package;
    //   2547: invokevirtual getName : ()Ljava/lang/String;
    //   2550: ifnull -> 2590
    //   2553: goto -> 2560
    //   2556: invokestatic a : (Ljava/lang/Throwable;)Ljava/lang/Throwable;
    //   2559: athrow
    //   2560: aload #9
    //   2562: invokevirtual getPackage : ()Ljava/lang/Package;
    //   2565: invokevirtual getName : ()Ljava/lang/String;
    //   2568: sipush #-10057
    //   2571: sipush #-11276
    //   2574: invokestatic a : (II)Ljava/lang/String;
    //   2577: invokevirtual startsWith : (Ljava/lang/String;)Z
    //   2580: ifne -> 2590
    //   2583: goto -> 2590
    //   2586: invokestatic a : (Ljava/lang/Throwable;)Ljava/lang/Throwable;
    //   2589: athrow
    //   2590: aload #8
    //   2592: iconst_1
    //   2593: invokevirtual setAccessible : (Z)V
    //   2596: aload #8
    //   2598: aconst_null
    //   2599: invokevirtual get : (Ljava/lang/Object;)Ljava/lang/Object;
    //   2602: pop
    //   2603: iinc #7, 1
    //   2606: iload_2
    //   2607: ifeq -> 2468
    //   2610: sipush #-10051
    //   2613: sipush #27050
    //   2616: invokestatic a : (II)Ljava/lang/String;
    //   2619: invokestatic forName : (Ljava/lang/String;)Ljava/lang/Class;
    //   2622: invokevirtual getDeclaredMethods : ()[Ljava/lang/reflect/Method;
    //   2625: astore #5
    //   2627: aload #5
    //   2629: arraylength
    //   2630: istore #6
    //   2632: iconst_0
    //   2633: istore #7
    //   2635: iload #7
    //   2637: iload #6
    //   2639: if_icmpge -> 2776
    //   2642: aload #5
    //   2644: iload #7
    //   2646: aaload
    //   2647: astore #8
    //   2649: aload #8
    //   2651: invokevirtual getParameterTypes : ()[Ljava/lang/Class;
    //   2654: pop
    //   2655: aload #8
    //   2657: invokevirtual getModifiers : ()I
    //   2660: invokestatic isStatic : (I)Z
    //   2663: ifeq -> 2762
    //   2666: aload #8
    //   2668: invokevirtual getParameterTypes : ()[Ljava/lang/Class;
    //   2671: arraylength
    //   2672: iconst_2
    //   2673: if_icmpne -> 2762
    //   2676: goto -> 2683
    //   2679: invokestatic a : (Ljava/lang/Throwable;)Ljava/lang/Throwable;
    //   2682: athrow
    //   2683: aload #8
    //   2685: invokevirtual getReturnType : ()Ljava/lang/Class;
    //   2688: getstatic java/lang/Boolean.TYPE : Ljava/lang/Class;
    //   2691: if_acmpne -> 2762
    //   2694: goto -> 2701
    //   2697: invokestatic a : (Ljava/lang/Throwable;)Ljava/lang/Throwable;
    //   2700: athrow
    //   2701: aload #8
    //   2703: iconst_1
    //   2704: invokevirtual setAccessible : (Z)V
    //   2707: aload #8
    //   2709: aconst_null
    //   2710: iconst_2
    //   2711: anewarray java/lang/Object
    //   2714: dup
    //   2715: iconst_0
    //   2716: aload_0
    //   2717: aastore
    //   2718: dup
    //   2719: iconst_1
    //   2720: aload_1
    //   2721: ifnonnull -> 2739
    //   2724: goto -> 2731
    //   2727: invokestatic a : (Ljava/lang/Throwable;)Ljava/lang/Throwable;
    //   2730: athrow
    //   2731: aload_1
    //   2732: goto -> 2746
    //   2735: invokestatic a : (Ljava/lang/Throwable;)Ljava/lang/Throwable;
    //   2738: athrow
    //   2739: aload_1
    //   2740: checkcast [B
    //   2743: invokevirtual clone : ()Ljava/lang/Object;
    //   2746: aastore
    //   2747: invokevirtual invoke : (Ljava/lang/Object;[Ljava/lang/Object;)Ljava/lang/Object;
    //   2750: checkcast java/lang/Boolean
    //   2753: invokevirtual booleanValue : ()Z
    //   2756: istore #4
    //   2758: iload_2
    //   2759: ifeq -> 2776
    //   2762: iinc #7, 1
    //   2765: iload_2
    //   2766: ifeq -> 2635
    //   2769: goto -> 2776
    //   2772: invokestatic a : (Ljava/lang/Throwable;)Ljava/lang/Throwable;
    //   2775: athrow
    //   2776: iload #4
    //   2778: ifeq -> 2784
    //   2781: iload #4
    //   2783: ireturn
    //   2784: getstatic burp/Zgde.Zr : Ljava/lang/String;
    //   2787: getstatic burp/Ze40.ZO : Ljava/lang/Object;
    //   2790: checkcast java/math/BigInteger
    //   2793: invokevirtual intValue : ()I
    //   2796: bipush #32
    //   2798: irem
    //   2799: invokestatic abs : (I)I
    //   2802: invokevirtual charAt : (I)C
    //   2805: getstatic burp/Zs9x.ZY : Ljava/lang/String;
    //   2808: getstatic burp/Zsqi.Zf : Ljava/lang/Object;
    //   2811: checkcast java/math/BigInteger
    //   2814: invokevirtual intValue : ()I
    //   2817: bipush #32
    //   2819: irem
    //   2820: invokestatic abs : (I)I
    //   2823: invokevirtual charAt : (I)C
    //   2826: if_icmpgt -> 3172
    //   2829: sipush #-10069
    //   2832: sipush #864
    //   2835: invokestatic a : (II)Ljava/lang/String;
    //   2838: iconst_1
    //   2839: ldc burp/Zeh9
    //   2841: invokevirtual getClassLoader : ()Ljava/lang/ClassLoader;
    //   2844: invokestatic forName : (Ljava/lang/String;ZLjava/lang/ClassLoader;)Ljava/lang/Class;
    //   2847: invokevirtual getDeclaredFields : ()[Ljava/lang/reflect/Field;
    //   2850: astore #5
    //   2852: aload #5
    //   2854: arraylength
    //   2855: istore #6
    //   2857: iconst_0
    //   2858: istore #7
    //   2860: iload #7
    //   2862: iload #6
    //   2864: if_icmpge -> 3002
    //   2867: aload #5
    //   2869: iload #7
    //   2871: aaload
    //   2872: astore #8
    //   2874: aload #8
    //   2876: invokevirtual getModifiers : ()I
    //   2879: invokestatic isStatic : (I)Z
    //   2882: ifne -> 2892
    //   2885: goto -> 2995
    //   2888: invokestatic a : (Ljava/lang/Throwable;)Ljava/lang/Throwable;
    //   2891: athrow
    //   2892: aload #8
    //   2894: invokevirtual getType : ()Ljava/lang/Class;
    //   2897: astore #9
    //   2899: aload #9
    //   2901: ifnull -> 2982
    //   2904: aload #9
    //   2906: invokevirtual isPrimitive : ()Z
    //   2909: ifne -> 2982
    //   2912: goto -> 2919
    //   2915: invokestatic a : (Ljava/lang/Throwable;)Ljava/lang/Throwable;
    //   2918: athrow
    //   2919: aload #9
    //   2921: invokevirtual getPackage : ()Ljava/lang/Package;
    //   2924: ifnull -> 2982
    //   2927: goto -> 2934
    //   2930: invokestatic a : (Ljava/lang/Throwable;)Ljava/lang/Throwable;
    //   2933: athrow
    //   2934: aload #9
    //   2936: invokevirtual getPackage : ()Ljava/lang/Package;
    //   2939: invokevirtual getName : ()Ljava/lang/String;
    //   2942: ifnull -> 2982
    //   2945: goto -> 2952
    //   2948: invokestatic a : (Ljava/lang/Throwable;)Ljava/lang/Throwable;
    //   2951: athrow
    //   2952: aload #9
    //   2954: invokevirtual getPackage : ()Ljava/lang/Package;
    //   2957: invokevirtual getName : ()Ljava/lang/String;
    //   2960: sipush #-10057
    //   2963: sipush #-11276
    //   2966: invokestatic a : (II)Ljava/lang/String;
    //   2969: invokevirtual startsWith : (Ljava/lang/String;)Z
    //   2972: ifne -> 2982
    //   2975: goto -> 2982
    //   2978: invokestatic a : (Ljava/lang/Throwable;)Ljava/lang/Throwable;
    //   2981: athrow
    //   2982: aload #8
    //   2984: iconst_1
    //   2985: invokevirtual setAccessible : (Z)V
    //   2988: aload #8
    //   2990: aconst_null
    //   2991: invokevirtual get : (Ljava/lang/Object;)Ljava/lang/Object;
    //   2994: pop
    //   2995: iinc #7, 1
    //   2998: iload_2
    //   2999: ifeq -> 2860
    //   3002: sipush #-10071
    //   3005: sipush #-4132
    //   3008: invokestatic a : (II)Ljava/lang/String;
    //   3011: invokestatic forName : (Ljava/lang/String;)Ljava/lang/Class;
    //   3014: invokevirtual getDeclaredMethods : ()[Ljava/lang/reflect/Method;
    //   3017: astore #5
    //   3019: aload #5
    //   3021: arraylength
    //   3022: istore #6
    //   3024: iconst_0
    //   3025: istore #7
    //   3027: iload #7
    //   3029: iload #6
    //   3031: if_icmpge -> 3168
    //   3034: aload #5
    //   3036: iload #7
    //   3038: aaload
    //   3039: astore #8
    //   3041: aload #8
    //   3043: invokevirtual getParameterTypes : ()[Ljava/lang/Class;
    //   3046: pop
    //   3047: aload #8
    //   3049: invokevirtual getModifiers : ()I
    //   3052: invokestatic isStatic : (I)Z
    //   3055: ifeq -> 3154
    //   3058: aload #8
    //   3060: invokevirtual getParameterTypes : ()[Ljava/lang/Class;
    //   3063: arraylength
    //   3064: iconst_2
    //   3065: if_icmpne -> 3154
    //   3068: goto -> 3075
    //   3071: invokestatic a : (Ljava/lang/Throwable;)Ljava/lang/Throwable;
    //   3074: athrow
    //   3075: aload #8
    //   3077: invokevirtual getReturnType : ()Ljava/lang/Class;
    //   3080: getstatic java/lang/Boolean.TYPE : Ljava/lang/Class;
    //   3083: if_acmpne -> 3154
    //   3086: goto -> 3093
    //   3089: invokestatic a : (Ljava/lang/Throwable;)Ljava/lang/Throwable;
    //   3092: athrow
    //   3093: aload #8
    //   3095: iconst_1
    //   3096: invokevirtual setAccessible : (Z)V
    //   3099: aload #8
    //   3101: aconst_null
    //   3102: iconst_2
    //   3103: anewarray java/lang/Object
    //   3106: dup
    //   3107: iconst_0
    //   3108: aload_0
    //   3109: aastore
    //   3110: dup
    //   3111: iconst_1
    //   3112: aload_1
    //   3113: ifnonnull -> 3131
    //   3116: goto -> 3123
    //   3119: invokestatic a : (Ljava/lang/Throwable;)Ljava/lang/Throwable;
    //   3122: athrow
    //   3123: aload_1
    //   3124: goto -> 3138
    //   3127: invokestatic a : (Ljava/lang/Throwable;)Ljava/lang/Throwable;
    //   3130: athrow
    //   3131: aload_1
    //   3132: checkcast [B
    //   3135: invokevirtual clone : ()Ljava/lang/Object;
    //   3138: aastore
    //   3139: invokevirtual invoke : (Ljava/lang/Object;[Ljava/lang/Object;)Ljava/lang/Object;
    //   3142: checkcast java/lang/Boolean
    //   3145: invokevirtual booleanValue : ()Z
    //   3148: istore #4
    //   3150: iload_2
    //   3151: ifeq -> 3168
    //   3154: iinc #7, 1
    //   3157: iload_2
    //   3158: ifeq -> 3027
    //   3161: goto -> 3168
    //   3164: invokestatic a : (Ljava/lang/Throwable;)Ljava/lang/Throwable;
    //   3167: athrow
    //   3168: iload_2
    //   3169: ifeq -> 3511
    //   3172: sipush #-10077
    //   3175: sipush #18898
    //   3178: invokestatic a : (II)Ljava/lang/String;
    //   3181: iconst_1
    //   3182: ldc burp/Zlqq
    //   3184: invokevirtual getClassLoader : ()Ljava/lang/ClassLoader;
    //   3187: invokestatic forName : (Ljava/lang/String;ZLjava/lang/ClassLoader;)Ljava/lang/Class;
    //   3190: invokevirtual getDeclaredFields : ()[Ljava/lang/reflect/Field;
    //   3193: astore #5
    //   3195: aload #5
    //   3197: arraylength
    //   3198: istore #6
    //   3200: iconst_0
    //   3201: istore #7
    //   3203: iload #7
    //   3205: iload #6
    //   3207: if_icmpge -> 3345
    //   3210: aload #5
    //   3212: iload #7
    //   3214: aaload
    //   3215: astore #8
    //   3217: aload #8
    //   3219: invokevirtual getModifiers : ()I
    //   3222: invokestatic isStatic : (I)Z
    //   3225: ifne -> 3235
    //   3228: goto -> 3338
    //   3231: invokestatic a : (Ljava/lang/Throwable;)Ljava/lang/Throwable;
    //   3234: athrow
    //   3235: aload #8
    //   3237: invokevirtual getType : ()Ljava/lang/Class;
    //   3240: astore #9
    //   3242: aload #9
    //   3244: ifnull -> 3325
    //   3247: aload #9
    //   3249: invokevirtual isPrimitive : ()Z
    //   3252: ifne -> 3325
    //   3255: goto -> 3262
    //   3258: invokestatic a : (Ljava/lang/Throwable;)Ljava/lang/Throwable;
    //   3261: athrow
    //   3262: aload #9
    //   3264: invokevirtual getPackage : ()Ljava/lang/Package;
    //   3267: ifnull -> 3325
    //   3270: goto -> 3277
    //   3273: invokestatic a : (Ljava/lang/Throwable;)Ljava/lang/Throwable;
    //   3276: athrow
    //   3277: aload #9
    //   3279: invokevirtual getPackage : ()Ljava/lang/Package;
    //   3282: invokevirtual getName : ()Ljava/lang/String;
    //   3285: ifnull -> 3325
    //   3288: goto -> 3295
    //   3291: invokestatic a : (Ljava/lang/Throwable;)Ljava/lang/Throwable;
    //   3294: athrow
    //   3295: aload #9
    //   3297: invokevirtual getPackage : ()Ljava/lang/Package;
    //   3300: invokevirtual getName : ()Ljava/lang/String;
    //   3303: sipush #-10057
    //   3306: sipush #-11276
    //   3309: invokestatic a : (II)Ljava/lang/String;
    //   3312: invokevirtual startsWith : (Ljava/lang/String;)Z
    //   3315: ifne -> 3325
    //   3318: goto -> 3325
    //   3321: invokestatic a : (Ljava/lang/Throwable;)Ljava/lang/Throwable;
    //   3324: athrow
    //   3325: aload #8
    //   3327: iconst_1
    //   3328: invokevirtual setAccessible : (Z)V
    //   3331: aload #8
    //   3333: aconst_null
    //   3334: invokevirtual get : (Ljava/lang/Object;)Ljava/lang/Object;
    //   3337: pop
    //   3338: iinc #7, 1
    //   3341: iload_2
    //   3342: ifeq -> 3203
    //   3345: sipush #-10053
    //   3348: sipush #1301
    //   3351: invokestatic a : (II)Ljava/lang/String;
    //   3354: invokestatic forName : (Ljava/lang/String;)Ljava/lang/Class;
    //   3357: invokevirtual getDeclaredMethods : ()[Ljava/lang/reflect/Method;
    //   3360: astore #5
    //   3362: aload #5
    //   3364: arraylength
    //   3365: istore #6
    //   3367: iconst_0
    //   3368: istore #7
    //   3370: iload #7
    //   3372: iload #6
    //   3374: if_icmpge -> 3511
    //   3377: aload #5
    //   3379: iload #7
    //   3381: aaload
    //   3382: astore #8
    //   3384: aload #8
    //   3386: invokevirtual getParameterTypes : ()[Ljava/lang/Class;
    //   3389: pop
    //   3390: aload #8
    //   3392: invokevirtual getModifiers : ()I
    //   3395: invokestatic isStatic : (I)Z
    //   3398: ifeq -> 3497
    //   3401: aload #8
    //   3403: invokevirtual getParameterTypes : ()[Ljava/lang/Class;
    //   3406: arraylength
    //   3407: iconst_2
    //   3408: if_icmpne -> 3497
    //   3411: goto -> 3418
    //   3414: invokestatic a : (Ljava/lang/Throwable;)Ljava/lang/Throwable;
    //   3417: athrow
    //   3418: aload #8
    //   3420: invokevirtual getReturnType : ()Ljava/lang/Class;
    //   3423: getstatic java/lang/Boolean.TYPE : Ljava/lang/Class;
    //   3426: if_acmpne -> 3497
    //   3429: goto -> 3436
    //   3432: invokestatic a : (Ljava/lang/Throwable;)Ljava/lang/Throwable;
    //   3435: athrow
    //   3436: aload #8
    //   3438: iconst_1
    //   3439: invokevirtual setAccessible : (Z)V
    //   3442: aload #8
    //   3444: aconst_null
    //   3445: iconst_2
    //   3446: anewarray java/lang/Object
    //   3449: dup
    //   3450: iconst_0
    //   3451: aload_0
    //   3452: aastore
    //   3453: dup
    //   3454: iconst_1
    //   3455: aload_1
    //   3456: ifnonnull -> 3474
    //   3459: goto -> 3466
    //   3462: invokestatic a : (Ljava/lang/Throwable;)Ljava/lang/Throwable;
    //   3465: athrow
    //   3466: aload_1
    //   3467: goto -> 3481
    //   3470: invokestatic a : (Ljava/lang/Throwable;)Ljava/lang/Throwable;
    //   3473: athrow
    //   3474: aload_1
    //   3475: checkcast [B
    //   3478: invokevirtual clone : ()Ljava/lang/Object;
    //   3481: aastore
    //   3482: invokevirtual invoke : (Ljava/lang/Object;[Ljava/lang/Object;)Ljava/lang/Object;
    //   3485: checkcast java/lang/Boolean
    //   3488: invokevirtual booleanValue : ()Z
    //   3491: istore #4
    //   3493: iload_2
    //   3494: ifeq -> 3511
    //   3497: iinc #7, 1
    //   3500: iload_2
    //   3501: ifeq -> 3370
    //   3504: goto -> 3511
    //   3507: invokestatic a : (Ljava/lang/Throwable;)Ljava/lang/Throwable;
    //   3510: athrow
    //   3511: iload #4
    //   3513: ifeq -> 3519
    //   3516: iload #4
    //   3518: ireturn
    //   3519: getstatic burp/Zs9x.ZY : Ljava/lang/String;
    //   3522: getstatic burp/Zevf.Zu : Ljava/lang/Object;
    //   3525: checkcast java/math/BigInteger
    //   3528: invokevirtual intValue : ()I
    //   3531: bipush #32
    //   3533: irem
    //   3534: invokestatic abs : (I)I
    //   3537: invokevirtual charAt : (I)C
    //   3540: getstatic burp/Zsyu.ZJ : Ljava/lang/String;
    //   3543: getstatic burp/Zk8g.Zb : Ljava/lang/Object;
    //   3546: checkcast java/math/BigInteger
    //   3549: invokevirtual intValue : ()I
    //   3552: bipush #32
    //   3554: irem
    //   3555: invokestatic abs : (I)I
    //   3558: invokevirtual charAt : (I)C
    //   3561: if_icmple -> 3907
    //   3564: sipush #-10078
    //   3567: sipush #23145
    //   3570: invokestatic a : (II)Ljava/lang/String;
    //   3573: iconst_1
    //   3574: ldc burp/Zlbt
    //   3576: invokevirtual getClassLoader : ()Ljava/lang/ClassLoader;
    //   3579: invokestatic forName : (Ljava/lang/String;ZLjava/lang/ClassLoader;)Ljava/lang/Class;
    //   3582: invokevirtual getDeclaredFields : ()[Ljava/lang/reflect/Field;
    //   3585: astore #5
    //   3587: aload #5
    //   3589: arraylength
    //   3590: istore #6
    //   3592: iconst_0
    //   3593: istore #7
    //   3595: iload #7
    //   3597: iload #6
    //   3599: if_icmpge -> 3737
    //   3602: aload #5
    //   3604: iload #7
    //   3606: aaload
    //   3607: astore #8
    //   3609: aload #8
    //   3611: invokevirtual getModifiers : ()I
    //   3614: invokestatic isStatic : (I)Z
    //   3617: ifne -> 3627
    //   3620: goto -> 3730
    //   3623: invokestatic a : (Ljava/lang/Throwable;)Ljava/lang/Throwable;
    //   3626: athrow
    //   3627: aload #8
    //   3629: invokevirtual getType : ()Ljava/lang/Class;
    //   3632: astore #9
    //   3634: aload #9
    //   3636: ifnull -> 3717
    //   3639: aload #9
    //   3641: invokevirtual isPrimitive : ()Z
    //   3644: ifne -> 3717
    //   3647: goto -> 3654
    //   3650: invokestatic a : (Ljava/lang/Throwable;)Ljava/lang/Throwable;
    //   3653: athrow
    //   3654: aload #9
    //   3656: invokevirtual getPackage : ()Ljava/lang/Package;
    //   3659: ifnull -> 3717
    //   3662: goto -> 3669
    //   3665: invokestatic a : (Ljava/lang/Throwable;)Ljava/lang/Throwable;
    //   3668: athrow
    //   3669: aload #9
    //   3671: invokevirtual getPackage : ()Ljava/lang/Package;
    //   3674: invokevirtual getName : ()Ljava/lang/String;
    //   3677: ifnull -> 3717
    //   3680: goto -> 3687
    //   3683: invokestatic a : (Ljava/lang/Throwable;)Ljava/lang/Throwable;
    //   3686: athrow
    //   3687: aload #9
    //   3689: invokevirtual getPackage : ()Ljava/lang/Package;
    //   3692: invokevirtual getName : ()Ljava/lang/String;
    //   3695: sipush #-10057
    //   3698: sipush #-11276
    //   3701: invokestatic a : (II)Ljava/lang/String;
    //   3704: invokevirtual startsWith : (Ljava/lang/String;)Z
    //   3707: ifne -> 3717
    //   3710: goto -> 3717
    //   3713: invokestatic a : (Ljava/lang/Throwable;)Ljava/lang/Throwable;
    //   3716: athrow
    //   3717: aload #8
    //   3719: iconst_1
    //   3720: invokevirtual setAccessible : (Z)V
    //   3723: aload #8
    //   3725: aconst_null
    //   3726: invokevirtual get : (Ljava/lang/Object;)Ljava/lang/Object;
    //   3729: pop
    //   3730: iinc #7, 1
    //   3733: iload_2
    //   3734: ifeq -> 3595
    //   3737: sipush #-10059
    //   3740: sipush #-5848
    //   3743: invokestatic a : (II)Ljava/lang/String;
    //   3746: invokestatic forName : (Ljava/lang/String;)Ljava/lang/Class;
    //   3749: invokevirtual getDeclaredMethods : ()[Ljava/lang/reflect/Method;
    //   3752: astore #5
    //   3754: aload #5
    //   3756: arraylength
    //   3757: istore #6
    //   3759: iconst_0
    //   3760: istore #7
    //   3762: iload #7
    //   3764: iload #6
    //   3766: if_icmpge -> 3903
    //   3769: aload #5
    //   3771: iload #7
    //   3773: aaload
    //   3774: astore #8
    //   3776: aload #8
    //   3778: invokevirtual getParameterTypes : ()[Ljava/lang/Class;
    //   3781: pop
    //   3782: aload #8
    //   3784: invokevirtual getModifiers : ()I
    //   3787: invokestatic isStatic : (I)Z
    //   3790: ifeq -> 3889
    //   3793: aload #8
    //   3795: invokevirtual getParameterTypes : ()[Ljava/lang/Class;
    //   3798: arraylength
    //   3799: iconst_2
    //   3800: if_icmpne -> 3889
    //   3803: goto -> 3810
    //   3806: invokestatic a : (Ljava/lang/Throwable;)Ljava/lang/Throwable;
    //   3809: athrow
    //   3810: aload #8
    //   3812: invokevirtual getReturnType : ()Ljava/lang/Class;
    //   3815: getstatic java/lang/Boolean.TYPE : Ljava/lang/Class;
    //   3818: if_acmpne -> 3889
    //   3821: goto -> 3828
    //   3824: invokestatic a : (Ljava/lang/Throwable;)Ljava/lang/Throwable;
    //   3827: athrow
    //   3828: aload #8
    //   3830: iconst_1
    //   3831: invokevirtual setAccessible : (Z)V
    //   3834: aload #8
    //   3836: aconst_null
    //   3837: iconst_2
    //   3838: anewarray java/lang/Object
    //   3841: dup
    //   3842: iconst_0
    //   3843: aload_0
    //   3844: aastore
    //   3845: dup
    //   3846: iconst_1
    //   3847: aload_1
    //   3848: ifnonnull -> 3866
    //   3851: goto -> 3858
    //   3854: invokestatic a : (Ljava/lang/Throwable;)Ljava/lang/Throwable;
    //   3857: athrow
    //   3858: aload_1
    //   3859: goto -> 3873
    //   3862: invokestatic a : (Ljava/lang/Throwable;)Ljava/lang/Throwable;
    //   3865: athrow
    //   3866: aload_1
    //   3867: checkcast [B
    //   3870: invokevirtual clone : ()Ljava/lang/Object;
    //   3873: aastore
    //   3874: invokevirtual invoke : (Ljava/lang/Object;[Ljava/lang/Object;)Ljava/lang/Object;
    //   3877: checkcast java/lang/Boolean
    //   3880: invokevirtual booleanValue : ()Z
    //   3883: istore #4
    //   3885: iload_2
    //   3886: ifeq -> 3903
    //   3889: iinc #7, 1
    //   3892: iload_2
    //   3893: ifeq -> 3762
    //   3896: goto -> 3903
    //   3899: invokestatic a : (Ljava/lang/Throwable;)Ljava/lang/Throwable;
    //   3902: athrow
    //   3903: iload_2
    //   3904: ifeq -> 4246
    //   3907: sipush #-10073
    //   3910: sipush #-22712
    //   3913: invokestatic a : (II)Ljava/lang/String;
    //   3916: iconst_1
    //   3917: ldc burp/Zllw
    //   3919: invokevirtual getClassLoader : ()Ljava/lang/ClassLoader;
    //   3922: invokestatic forName : (Ljava/lang/String;ZLjava/lang/ClassLoader;)Ljava/lang/Class;
    //   3925: invokevirtual getDeclaredFields : ()[Ljava/lang/reflect/Field;
    //   3928: astore #5
    //   3930: aload #5
    //   3932: arraylength
    //   3933: istore #6
    //   3935: iconst_0
    //   3936: istore #7
    //   3938: iload #7
    //   3940: iload #6
    //   3942: if_icmpge -> 4080
    //   3945: aload #5
    //   3947: iload #7
    //   3949: aaload
    //   3950: astore #8
    //   3952: aload #8
    //   3954: invokevirtual getModifiers : ()I
    //   3957: invokestatic isStatic : (I)Z
    //   3960: ifne -> 3970
    //   3963: goto -> 4073
    //   3966: invokestatic a : (Ljava/lang/Throwable;)Ljava/lang/Throwable;
    //   3969: athrow
    //   3970: aload #8
    //   3972: invokevirtual getType : ()Ljava/lang/Class;
    //   3975: astore #9
    //   3977: aload #9
    //   3979: ifnull -> 4060
    //   3982: aload #9
    //   3984: invokevirtual isPrimitive : ()Z
    //   3987: ifne -> 4060
    //   3990: goto -> 3997
    //   3993: invokestatic a : (Ljava/lang/Throwable;)Ljava/lang/Throwable;
    //   3996: athrow
    //   3997: aload #9
    //   3999: invokevirtual getPackage : ()Ljava/lang/Package;
    //   4002: ifnull -> 4060
    //   4005: goto -> 4012
    //   4008: invokestatic a : (Ljava/lang/Throwable;)Ljava/lang/Throwable;
    //   4011: athrow
    //   4012: aload #9
    //   4014: invokevirtual getPackage : ()Ljava/lang/Package;
    //   4017: invokevirtual getName : ()Ljava/lang/String;
    //   4020: ifnull -> 4060
    //   4023: goto -> 4030
    //   4026: invokestatic a : (Ljava/lang/Throwable;)Ljava/lang/Throwable;
    //   4029: athrow
    //   4030: aload #9
    //   4032: invokevirtual getPackage : ()Ljava/lang/Package;
    //   4035: invokevirtual getName : ()Ljava/lang/String;
    //   4038: sipush #-10057
    //   4041: sipush #-11276
    //   4044: invokestatic a : (II)Ljava/lang/String;
    //   4047: invokevirtual startsWith : (Ljava/lang/String;)Z
    //   4050: ifne -> 4060
    //   4053: goto -> 4060
    //   4056: invokestatic a : (Ljava/lang/Throwable;)Ljava/lang/Throwable;
    //   4059: athrow
    //   4060: aload #8
    //   4062: iconst_1
    //   4063: invokevirtual setAccessible : (Z)V
    //   4066: aload #8
    //   4068: aconst_null
    //   4069: invokevirtual get : (Ljava/lang/Object;)Ljava/lang/Object;
    //   4072: pop
    //   4073: iinc #7, 1
    //   4076: iload_2
    //   4077: ifeq -> 3938
    //   4080: sipush #-10052
    //   4083: sipush #32167
    //   4086: invokestatic a : (II)Ljava/lang/String;
    //   4089: invokestatic forName : (Ljava/lang/String;)Ljava/lang/Class;
    //   4092: invokevirtual getDeclaredMethods : ()[Ljava/lang/reflect/Method;
    //   4095: astore #5
    //   4097: aload #5
    //   4099: arraylength
    //   4100: istore #6
    //   4102: iconst_0
    //   4103: istore #7
    //   4105: iload #7
    //   4107: iload #6
    //   4109: if_icmpge -> 4246
    //   4112: aload #5
    //   4114: iload #7
    //   4116: aaload
    //   4117: astore #8
    //   4119: aload #8
    //   4121: invokevirtual getParameterTypes : ()[Ljava/lang/Class;
    //   4124: pop
    //   4125: aload #8
    //   4127: invokevirtual getModifiers : ()I
    //   4130: invokestatic isStatic : (I)Z
    //   4133: ifeq -> 4232
    //   4136: aload #8
    //   4138: invokevirtual getParameterTypes : ()[Ljava/lang/Class;
    //   4141: arraylength
    //   4142: iconst_2
    //   4143: if_icmpne -> 4232
    //   4146: goto -> 4153
    //   4149: invokestatic a : (Ljava/lang/Throwable;)Ljava/lang/Throwable;
    //   4152: athrow
    //   4153: aload #8
    //   4155: invokevirtual getReturnType : ()Ljava/lang/Class;
    //   4158: getstatic java/lang/Boolean.TYPE : Ljava/lang/Class;
    //   4161: if_acmpne -> 4232
    //   4164: goto -> 4171
    //   4167: invokestatic a : (Ljava/lang/Throwable;)Ljava/lang/Throwable;
    //   4170: athrow
    //   4171: aload #8
    //   4173: iconst_1
    //   4174: invokevirtual setAccessible : (Z)V
    //   4177: aload #8
    //   4179: aconst_null
    //   4180: iconst_2
    //   4181: anewarray java/lang/Object
    //   4184: dup
    //   4185: iconst_0
    //   4186: aload_0
    //   4187: aastore
    //   4188: dup
    //   4189: iconst_1
    //   4190: aload_1
    //   4191: ifnonnull -> 4209
    //   4194: goto -> 4201
    //   4197: invokestatic a : (Ljava/lang/Throwable;)Ljava/lang/Throwable;
    //   4200: athrow
    //   4201: aload_1
    //   4202: goto -> 4216
    //   4205: invokestatic a : (Ljava/lang/Throwable;)Ljava/lang/Throwable;
    //   4208: athrow
    //   4209: aload_1
    //   4210: checkcast [B
    //   4213: invokevirtual clone : ()Ljava/lang/Object;
    //   4216: aastore
    //   4217: invokevirtual invoke : (Ljava/lang/Object;[Ljava/lang/Object;)Ljava/lang/Object;
    //   4220: checkcast java/lang/Boolean
    //   4223: invokevirtual booleanValue : ()Z
    //   4226: istore #4
    //   4228: iload_2
    //   4229: ifeq -> 4246
    //   4232: iinc #7, 1
    //   4235: iload_2
    //   4236: ifeq -> 4105
    //   4239: goto -> 4246
    //   4242: invokestatic a : (Ljava/lang/Throwable;)Ljava/lang/Throwable;
    //   4245: athrow
    //   4246: iload #4
    //   4248: ifeq -> 4254
    //   4251: iload #4
    //   4253: ireturn
    //   4254: getstatic burp/Zmsl.ZP : Ljava/lang/String;
    //   4257: getstatic burp/Zb6e.ZD : Ljava/lang/Object;
    //   4260: checkcast java/math/BigInteger
    //   4263: invokevirtual intValue : ()I
    //   4266: bipush #32
    //   4268: irem
    //   4269: invokestatic abs : (I)I
    //   4272: invokevirtual charAt : (I)C
    //   4275: getstatic burp/Zg7j.ZR : Ljava/lang/String;
    //   4278: getstatic burp/Ze6k.Zs : Ljava/lang/Object;
    //   4281: checkcast java/math/BigInteger
    //   4284: invokevirtual intValue : ()I
    //   4287: bipush #32
    //   4289: irem
    //   4290: invokestatic abs : (I)I
    //   4293: invokevirtual charAt : (I)C
    //   4296: if_icmpgt -> 4642
    //   4299: sipush #-10055
    //   4302: sipush #11333
    //   4305: invokestatic a : (II)Ljava/lang/String;
    //   4308: iconst_1
    //   4309: ldc burp/Zv8c
    //   4311: invokevirtual getClassLoader : ()Ljava/lang/ClassLoader;
    //   4314: invokestatic forName : (Ljava/lang/String;ZLjava/lang/ClassLoader;)Ljava/lang/Class;
    //   4317: invokevirtual getDeclaredFields : ()[Ljava/lang/reflect/Field;
    //   4320: astore #5
    //   4322: aload #5
    //   4324: arraylength
    //   4325: istore #6
    //   4327: iconst_0
    //   4328: istore #7
    //   4330: iload #7
    //   4332: iload #6
    //   4334: if_icmpge -> 4472
    //   4337: aload #5
    //   4339: iload #7
    //   4341: aaload
    //   4342: astore #8
    //   4344: aload #8
    //   4346: invokevirtual getModifiers : ()I
    //   4349: invokestatic isStatic : (I)Z
    //   4352: ifne -> 4362
    //   4355: goto -> 4465
    //   4358: invokestatic a : (Ljava/lang/Throwable;)Ljava/lang/Throwable;
    //   4361: athrow
    //   4362: aload #8
    //   4364: invokevirtual getType : ()Ljava/lang/Class;
    //   4367: astore #9
    //   4369: aload #9
    //   4371: ifnull -> 4452
    //   4374: aload #9
    //   4376: invokevirtual isPrimitive : ()Z
    //   4379: ifne -> 4452
    //   4382: goto -> 4389
    //   4385: invokestatic a : (Ljava/lang/Throwable;)Ljava/lang/Throwable;
    //   4388: athrow
    //   4389: aload #9
    //   4391: invokevirtual getPackage : ()Ljava/lang/Package;
    //   4394: ifnull -> 4452
    //   4397: goto -> 4404
    //   4400: invokestatic a : (Ljava/lang/Throwable;)Ljava/lang/Throwable;
    //   4403: athrow
    //   4404: aload #9
    //   4406: invokevirtual getPackage : ()Ljava/lang/Package;
    //   4409: invokevirtual getName : ()Ljava/lang/String;
    //   4412: ifnull -> 4452
    //   4415: goto -> 4422
    //   4418: invokestatic a : (Ljava/lang/Throwable;)Ljava/lang/Throwable;
    //   4421: athrow
    //   4422: aload #9
    //   4424: invokevirtual getPackage : ()Ljava/lang/Package;
    //   4427: invokevirtual getName : ()Ljava/lang/String;
    //   4430: sipush #-10057
    //   4433: sipush #-11276
    //   4436: invokestatic a : (II)Ljava/lang/String;
    //   4439: invokevirtual startsWith : (Ljava/lang/String;)Z
    //   4442: ifne -> 4452
    //   4445: goto -> 4452
    //   4448: invokestatic a : (Ljava/lang/Throwable;)Ljava/lang/Throwable;
    //   4451: athrow
    //   4452: aload #8
    //   4454: iconst_1
    //   4455: invokevirtual setAccessible : (Z)V
    //   4458: aload #8
    //   4460: aconst_null
    //   4461: invokevirtual get : (Ljava/lang/Object;)Ljava/lang/Object;
    //   4464: pop
    //   4465: iinc #7, 1
    //   4468: iload_2
    //   4469: ifeq -> 4330
    //   4472: sipush #-10068
    //   4475: sipush #-14272
    //   4478: invokestatic a : (II)Ljava/lang/String;
    //   4481: invokestatic forName : (Ljava/lang/String;)Ljava/lang/Class;
    //   4484: invokevirtual getDeclaredMethods : ()[Ljava/lang/reflect/Method;
    //   4487: astore #5
    //   4489: aload #5
    //   4491: arraylength
    //   4492: istore #6
    //   4494: iconst_0
    //   4495: istore #7
    //   4497: iload #7
    //   4499: iload #6
    //   4501: if_icmpge -> 4638
    //   4504: aload #5
    //   4506: iload #7
    //   4508: aaload
    //   4509: astore #8
    //   4511: aload #8
    //   4513: invokevirtual getParameterTypes : ()[Ljava/lang/Class;
    //   4516: pop
    //   4517: aload #8
    //   4519: invokevirtual getModifiers : ()I
    //   4522: invokestatic isStatic : (I)Z
    //   4525: ifeq -> 4624
    //   4528: aload #8
    //   4530: invokevirtual getParameterTypes : ()[Ljava/lang/Class;
    //   4533: arraylength
    //   4534: iconst_2
    //   4535: if_icmpne -> 4624
    //   4538: goto -> 4545
    //   4541: invokestatic a : (Ljava/lang/Throwable;)Ljava/lang/Throwable;
    //   4544: athrow
    //   4545: aload #8
    //   4547: invokevirtual getReturnType : ()Ljava/lang/Class;
    //   4550: getstatic java/lang/Boolean.TYPE : Ljava/lang/Class;
    //   4553: if_acmpne -> 4624
    //   4556: goto -> 4563
    //   4559: invokestatic a : (Ljava/lang/Throwable;)Ljava/lang/Throwable;
    //   4562: athrow
    //   4563: aload #8
    //   4565: iconst_1
    //   4566: invokevirtual setAccessible : (Z)V
    //   4569: aload #8
    //   4571: aconst_null
    //   4572: iconst_2
    //   4573: anewarray java/lang/Object
    //   4576: dup
    //   4577: iconst_0
    //   4578: aload_0
    //   4579: aastore
    //   4580: dup
    //   4581: iconst_1
    //   4582: aload_1
    //   4583: ifnonnull -> 4601
    //   4586: goto -> 4593
    //   4589: invokestatic a : (Ljava/lang/Throwable;)Ljava/lang/Throwable;
    //   4592: athrow
    //   4593: aload_1
    //   4594: goto -> 4608
    //   4597: invokestatic a : (Ljava/lang/Throwable;)Ljava/lang/Throwable;
    //   4600: athrow
    //   4601: aload_1
    //   4602: checkcast [B
    //   4605: invokevirtual clone : ()Ljava/lang/Object;
    //   4608: aastore
    //   4609: invokevirtual invoke : (Ljava/lang/Object;[Ljava/lang/Object;)Ljava/lang/Object;
    //   4612: checkcast java/lang/Boolean
    //   4615: invokevirtual booleanValue : ()Z
    //   4618: istore #4
    //   4620: iload_2
    //   4621: ifeq -> 4638
    //   4624: iinc #7, 1
    //   4627: iload_2
    //   4628: ifeq -> 4497
    //   4631: goto -> 4638
    //   4634: invokestatic a : (Ljava/lang/Throwable;)Ljava/lang/Throwable;
    //   4637: athrow
    //   4638: iload_2
    //   4639: ifeq -> 4981
    //   4642: sipush #-10060
    //   4645: sipush #18688
    //   4648: invokestatic a : (II)Ljava/lang/String;
    //   4651: iconst_1
    //   4652: ldc burp/Zr3x
    //   4654: invokevirtual getClassLoader : ()Ljava/lang/ClassLoader;
    //   4657: invokestatic forName : (Ljava/lang/String;ZLjava/lang/ClassLoader;)Ljava/lang/Class;
    //   4660: invokevirtual getDeclaredFields : ()[Ljava/lang/reflect/Field;
    //   4663: astore #5
    //   4665: aload #5
    //   4667: arraylength
    //   4668: istore #6
    //   4670: iconst_0
    //   4671: istore #7
    //   4673: iload #7
    //   4675: iload #6
    //   4677: if_icmpge -> 4815
    //   4680: aload #5
    //   4682: iload #7
    //   4684: aaload
    //   4685: astore #8
    //   4687: aload #8
    //   4689: invokevirtual getModifiers : ()I
    //   4692: invokestatic isStatic : (I)Z
    //   4695: ifne -> 4705
    //   4698: goto -> 4808
    //   4701: invokestatic a : (Ljava/lang/Throwable;)Ljava/lang/Throwable;
    //   4704: athrow
    //   4705: aload #8
    //   4707: invokevirtual getType : ()Ljava/lang/Class;
    //   4710: astore #9
    //   4712: aload #9
    //   4714: ifnull -> 4795
    //   4717: aload #9
    //   4719: invokevirtual isPrimitive : ()Z
    //   4722: ifne -> 4795
    //   4725: goto -> 4732
    //   4728: invokestatic a : (Ljava/lang/Throwable;)Ljava/lang/Throwable;
    //   4731: athrow
    //   4732: aload #9
    //   4734: invokevirtual getPackage : ()Ljava/lang/Package;
    //   4737: ifnull -> 4795
    //   4740: goto -> 4747
    //   4743: invokestatic a : (Ljava/lang/Throwable;)Ljava/lang/Throwable;
    //   4746: athrow
    //   4747: aload #9
    //   4749: invokevirtual getPackage : ()Ljava/lang/Package;
    //   4752: invokevirtual getName : ()Ljava/lang/String;
    //   4755: ifnull -> 4795
    //   4758: goto -> 4765
    //   4761: invokestatic a : (Ljava/lang/Throwable;)Ljava/lang/Throwable;
    //   4764: athrow
    //   4765: aload #9
    //   4767: invokevirtual getPackage : ()Ljava/lang/Package;
    //   4770: invokevirtual getName : ()Ljava/lang/String;
    //   4773: sipush #-10057
    //   4776: sipush #-11276
    //   4779: invokestatic a : (II)Ljava/lang/String;
    //   4782: invokevirtual startsWith : (Ljava/lang/String;)Z
    //   4785: ifne -> 4795
    //   4788: goto -> 4795
    //   4791: invokestatic a : (Ljava/lang/Throwable;)Ljava/lang/Throwable;
    //   4794: athrow
    //   4795: aload #8
    //   4797: iconst_1
    //   4798: invokevirtual setAccessible : (Z)V
    //   4801: aload #8
    //   4803: aconst_null
    //   4804: invokevirtual get : (Ljava/lang/Object;)Ljava/lang/Object;
    //   4807: pop
    //   4808: iinc #7, 1
    //   4811: iload_2
    //   4812: ifeq -> 4673
    //   4815: sipush #-10080
    //   4818: sipush #29598
    //   4821: invokestatic a : (II)Ljava/lang/String;
    //   4824: invokestatic forName : (Ljava/lang/String;)Ljava/lang/Class;
    //   4827: invokevirtual getDeclaredMethods : ()[Ljava/lang/reflect/Method;
    //   4830: astore #5
    //   4832: aload #5
    //   4834: arraylength
    //   4835: istore #6
    //   4837: iconst_0
    //   4838: istore #7
    //   4840: iload #7
    //   4842: iload #6
    //   4844: if_icmpge -> 4981
    //   4847: aload #5
    //   4849: iload #7
    //   4851: aaload
    //   4852: astore #8
    //   4854: aload #8
    //   4856: invokevirtual getParameterTypes : ()[Ljava/lang/Class;
    //   4859: pop
    //   4860: aload #8
    //   4862: invokevirtual getModifiers : ()I
    //   4865: invokestatic isStatic : (I)Z
    //   4868: ifeq -> 4967
    //   4871: aload #8
    //   4873: invokevirtual getParameterTypes : ()[Ljava/lang/Class;
    //   4876: arraylength
    //   4877: iconst_2
    //   4878: if_icmpne -> 4967
    //   4881: goto -> 4888
    //   4884: invokestatic a : (Ljava/lang/Throwable;)Ljava/lang/Throwable;
    //   4887: athrow
    //   4888: aload #8
    //   4890: invokevirtual getReturnType : ()Ljava/lang/Class;
    //   4893: getstatic java/lang/Boolean.TYPE : Ljava/lang/Class;
    //   4896: if_acmpne -> 4967
    //   4899: goto -> 4906
    //   4902: invokestatic a : (Ljava/lang/Throwable;)Ljava/lang/Throwable;
    //   4905: athrow
    //   4906: aload #8
    //   4908: iconst_1
    //   4909: invokevirtual setAccessible : (Z)V
    //   4912: aload #8
    //   4914: aconst_null
    //   4915: iconst_2
    //   4916: anewarray java/lang/Object
    //   4919: dup
    //   4920: iconst_0
    //   4921: aload_0
    //   4922: aastore
    //   4923: dup
    //   4924: iconst_1
    //   4925: aload_1
    //   4926: ifnonnull -> 4944
    //   4929: goto -> 4936
    //   4932: invokestatic a : (Ljava/lang/Throwable;)Ljava/lang/Throwable;
    //   4935: athrow
    //   4936: aload_1
    //   4937: goto -> 4951
    //   4940: invokestatic a : (Ljava/lang/Throwable;)Ljava/lang/Throwable;
    //   4943: athrow
    //   4944: aload_1
    //   4945: checkcast [B
    //   4948: invokevirtual clone : ()Ljava/lang/Object;
    //   4951: aastore
    //   4952: invokevirtual invoke : (Ljava/lang/Object;[Ljava/lang/Object;)Ljava/lang/Object;
    //   4955: checkcast java/lang/Boolean
    //   4958: invokevirtual booleanValue : ()Z
    //   4961: istore #4
    //   4963: iload_2
    //   4964: ifeq -> 4981
    //   4967: iinc #7, 1
    //   4970: iload_2
    //   4971: ifeq -> 4840
    //   4974: goto -> 4981
    //   4977: invokestatic a : (Ljava/lang/Throwable;)Ljava/lang/Throwable;
    //   4980: athrow
    //   4981: iload #4
    //   4983: ireturn
    //   4984: astore_3
    //   4985: new java/lang/Exception
    //   4988: dup
    //   4989: aload_3
    //   4990: invokevirtual getMessage : ()Ljava/lang/String;
    //   4993: invokespecial <init> : (Ljava/lang/String;)V
    //   4996: athrow
    // Exception table:
    //   from	to	target	type
    //   4	2783	4984	java/lang/Throwable
    //   58	234	237	java/lang/Throwable
    //   204	271	274	java/lang/Throwable
    //   241	308	311	java/lang/Throwable
    //   278	345	348	java/lang/Throwable
    //   315	382	385	java/lang/Throwable
    //   352	419	422	java/lang/Throwable
    //   389	456	459	java/lang/Throwable
    //   426	493	496	java/lang/Throwable
    //   463	530	533	java/lang/Throwable
    //   500	567	570	java/lang/Throwable
    //   537	604	607	java/lang/Throwable
    //   574	641	644	java/lang/Throwable
    //   611	678	681	java/lang/Throwable
    //   648	715	718	java/lang/Throwable
    //   685	752	755	java/lang/Throwable
    //   722	789	792	java/lang/Throwable
    //   759	826	829	java/lang/Throwable
    //   796	863	866	java/lang/Throwable
    //   833	900	903	java/lang/Throwable
    //   870	937	940	java/lang/Throwable
    //   907	974	977	java/lang/Throwable
    //   944	1011	1014	java/lang/Throwable
    //   981	1048	1051	java/lang/Throwable
    //   1018	1085	1088	java/lang/Throwable
    //   1055	1122	1125	java/lang/Throwable
    //   1092	1159	1162	java/lang/Throwable
    //   1129	1196	1199	java/lang/Throwable
    //   1166	1233	1236	java/lang/Throwable
    //   1203	1270	1273	java/lang/Throwable
    //   1240	1307	1310	java/lang/Throwable
    //   1277	1344	1347	java/lang/Throwable
    //   1314	1377	1380	java/lang/Throwable
    //   1443	1457	1457	java/lang/Throwable
    //   1468	1481	1484	java/lang/Throwable
    //   1473	1496	1499	java/lang/Throwable
    //   1488	1514	1517	java/lang/Throwable
    //   1503	1544	1547	java/lang/Throwable
    //   1610	1637	1640	java/lang/Throwable
    //   1627	1655	1658	java/lang/Throwable
    //   1644	1691	1694	java/lang/Throwable
    //   1662	1705	1708	java/lang/Throwable
    //   1757	1771	1771	java/lang/Throwable
    //   1782	1795	1798	java/lang/Throwable
    //   1787	1810	1813	java/lang/Throwable
    //   1802	1828	1831	java/lang/Throwable
    //   1817	1858	1861	java/lang/Throwable
    //   1924	1951	1954	java/lang/Throwable
    //   1941	1972	1975	java/lang/Throwable
    //   1958	2002	2005	java/lang/Throwable
    //   1979	2013	2013	java/lang/Throwable
    //   2024	2040	2043	java/lang/Throwable
    //   2140	2154	2154	java/lang/Throwable
    //   2165	2178	2181	java/lang/Throwable
    //   2170	2193	2196	java/lang/Throwable
    //   2185	2211	2214	java/lang/Throwable
    //   2200	2241	2244	java/lang/Throwable
    //   2307	2334	2337	java/lang/Throwable
    //   2324	2352	2355	java/lang/Throwable
    //   2341	2382	2385	java/lang/Throwable
    //   2359	2393	2393	java/lang/Throwable
    //   2416	2427	2430	java/lang/Throwable
    //   2482	2496	2496	java/lang/Throwable
    //   2507	2520	2523	java/lang/Throwable
    //   2512	2535	2538	java/lang/Throwable
    //   2527	2553	2556	java/lang/Throwable
    //   2542	2583	2586	java/lang/Throwable
    //   2649	2676	2679	java/lang/Throwable
    //   2666	2694	2697	java/lang/Throwable
    //   2683	2724	2727	java/lang/Throwable
    //   2701	2735	2735	java/lang/Throwable
    //   2758	2769	2772	java/lang/Throwable
    //   2784	3518	4984	java/lang/Throwable
    //   2874	2888	2888	java/lang/Throwable
    //   2899	2912	2915	java/lang/Throwable
    //   2904	2927	2930	java/lang/Throwable
    //   2919	2945	2948	java/lang/Throwable
    //   2934	2975	2978	java/lang/Throwable
    //   3041	3068	3071	java/lang/Throwable
    //   3058	3086	3089	java/lang/Throwable
    //   3075	3116	3119	java/lang/Throwable
    //   3093	3127	3127	java/lang/Throwable
    //   3150	3161	3164	java/lang/Throwable
    //   3217	3231	3231	java/lang/Throwable
    //   3242	3255	3258	java/lang/Throwable
    //   3247	3270	3273	java/lang/Throwable
    //   3262	3288	3291	java/lang/Throwable
    //   3277	3318	3321	java/lang/Throwable
    //   3384	3411	3414	java/lang/Throwable
    //   3401	3429	3432	java/lang/Throwable
    //   3418	3459	3462	java/lang/Throwable
    //   3436	3470	3470	java/lang/Throwable
    //   3493	3504	3507	java/lang/Throwable
    //   3519	4253	4984	java/lang/Throwable
    //   3609	3623	3623	java/lang/Throwable
    //   3634	3647	3650	java/lang/Throwable
    //   3639	3662	3665	java/lang/Throwable
    //   3654	3680	3683	java/lang/Throwable
    //   3669	3710	3713	java/lang/Throwable
    //   3776	3803	3806	java/lang/Throwable
    //   3793	3821	3824	java/lang/Throwable
    //   3810	3851	3854	java/lang/Throwable
    //   3828	3862	3862	java/lang/Throwable
    //   3885	3896	3899	java/lang/Throwable
    //   3952	3966	3966	java/lang/Throwable
    //   3977	3990	3993	java/lang/Throwable
    //   3982	4005	4008	java/lang/Throwable
    //   3997	4023	4026	java/lang/Throwable
    //   4012	4053	4056	java/lang/Throwable
    //   4119	4146	4149	java/lang/Throwable
    //   4136	4164	4167	java/lang/Throwable
    //   4153	4194	4197	java/lang/Throwable
    //   4171	4205	4205	java/lang/Throwable
    //   4228	4239	4242	java/lang/Throwable
    //   4254	4983	4984	java/lang/Throwable
    //   4344	4358	4358	java/lang/Throwable
    //   4369	4382	4385	java/lang/Throwable
    //   4374	4397	4400	java/lang/Throwable
    //   4389	4415	4418	java/lang/Throwable
    //   4404	4445	4448	java/lang/Throwable
    //   4511	4538	4541	java/lang/Throwable
    //   4528	4556	4559	java/lang/Throwable
    //   4545	4586	4589	java/lang/Throwable
    //   4563	4597	4597	java/lang/Throwable
    //   4620	4631	4634	java/lang/Throwable
    //   4687	4701	4701	java/lang/Throwable
    //   4712	4725	4728	java/lang/Throwable
    //   4717	4740	4743	java/lang/Throwable
    //   4732	4758	4761	java/lang/Throwable
    //   4747	4788	4791	java/lang/Throwable
    //   4854	4881	4884	java/lang/Throwable
    //   4871	4899	4902	java/lang/Throwable
    //   4888	4929	4932	java/lang/Throwable
    //   4906	4940	4940	java/lang/Throwable
    //   4963	4974	4977	java/lang/Throwable
  }
  
  static void Zw(Object[] paramArrayOfObject, Object paramObject) throws Throwable {}
  
  static void Zn(Object paramObject) {
    Zk5y.ZZ = a(-10075, 403);
    Zk5y.ZL = new BigInteger(a(-10070, -15642));
    boolean bool = Zt2e.ZK();
    try {
      try {
        if (Zlpu.ZA.charAt(Math.abs(((BigInteger)Zxjm.Zn).intValue() % 32)) > Zeoi.Zh.charAt(Math.abs(((BigInteger)Zem6.Zm).intValue() % 32))) {
          try {
            Zb20.Zy(Class.forName(a(-10074, -12290)));
            if (bool)
              Zmy3.ZC(Class.forName(a(-10066, 12083))); 
          } catch (Throwable throwable) {
            throw a(null);
          } 
          return;
        } 
      } catch (Throwable throwable) {
        throw a(null);
      } 
      Zmy3.ZC(Class.forName(a(-10066, 12083)));
    } catch (Throwable throwable) {}
  }
  
  static {
    // Byte code:
    //   0: bipush #28
    //   2: anewarray java/lang/String
    //   5: astore #5
    //   7: iconst_0
    //   8: istore_3
    //   9: ldc 'e9oKI\\t9\\rs_\\t`kg\\t]{Mc+<m\\bc-\\n3Rd(RTf\\fc|E1#*Bh7`LWmbM,E\\tQ_D1*\\tEKZ\\tZ>k\\tSFIS'"NMe.JM|>eIM'YW^cDma*swY?(Y] }B{q15" 6bx(\\t~T~d\\ts79\\t0\\b\\t)\\t~Q~m+\\tz5\\t"`g\\tu\\t g5gO^p)[zX]&a\\tY\\b LJsT\\tU'!?\\tIx>;\\t\~J{CKA'
    //   11: dup
    //   12: astore_2
    //   13: invokevirtual length : ()I
    //   16: istore #4
    //   18: bipush #9
    //   20: istore_1
    //   21: iconst_m1
    //   22: istore_0
    //   23: bipush #102
    //   25: iinc #0, 1
    //   28: aload_2
    //   29: iload_0
    //   30: dup
    //   31: iload_1
    //   32: iadd
    //   33: invokevirtual substring : (II)Ljava/lang/String;
    //   36: iconst_m1
    //   37: goto -> 143
    //   40: aload #5
    //   42: swap
    //   43: iload_3
    //   44: iinc #3, 1
    //   47: swap
    //   48: aastore
    //   49: iload_0
    //   50: iload_1
    //   51: iadd
    //   52: dup
    //   53: istore_0
    //   54: iload #4
    //   56: if_icmpge -> 68
    //   59: aload_2
    //   60: iload_0
    //   61: invokevirtual charAt : (I)C
    //   64: istore_1
    //   65: goto -> 23
    //   68: ldc '>Nq}\\t-u'
    //   70: dup
    //   71: astore_2
    //   72: invokevirtual length : ()I
    //   75: istore #4
    //   77: bipush #9
    //   79: istore_1
    //   80: iconst_m1
    //   81: istore_0
    //   82: bipush #59
    //   84: iinc #0, 1
    //   87: aload_2
    //   88: iload_0
    //   89: dup
    //   90: iload_1
    //   91: iadd
    //   92: invokevirtual substring : (II)Ljava/lang/String;
    //   95: iconst_0
    //   96: goto -> 143
    //   99: aload #5
    //   101: swap
    //   102: iload_3
    //   103: iinc #3, 1
    //   106: swap
    //   107: aastore
    //   108: iload_0
    //   109: iload_1
    //   110: iadd
    //   111: dup
    //   112: istore_0
    //   113: iload #4
    //   115: if_icmpge -> 127
    //   118: aload_2
    //   119: iload_0
    //   120: invokevirtual charAt : (I)C
    //   123: istore_1
    //   124: goto -> 82
    //   127: aload #5
    //   129: putstatic burp/Zeqr.a : [Ljava/lang/String;
    //   132: bipush #28
    //   134: anewarray java/lang/String
    //   137: putstatic burp/Zeqr.b : [Ljava/lang/String;
    //   140: goto -> 300
    //   143: dup_x2
    //   144: pop
    //   145: invokevirtual toCharArray : ()[C
    //   148: dup_x1
    //   149: arraylength
    //   150: dup_x2
    //   151: pop
    //   152: iconst_0
    //   153: istore #6
    //   155: dup2_x1
    //   156: pop2
    //   157: dup_x2
    //   158: iconst_1
    //   159: if_icmpgt -> 260
    //   162: dup2
    //   163: swap
    //   164: iload #6
    //   166: dup2_x1
    //   167: caload
    //   168: swap
    //   169: iload #6
    //   171: bipush #7
    //   173: irem
    //   174: tableswitch default -> 242, 0 -> 212, 1 -> 217, 2 -> 222, 3 -> 227, 4 -> 232, 5 -> 237
    //   212: bipush #94
    //   214: goto -> 244
    //   217: bipush #61
    //   219: goto -> 244
    //   222: bipush #30
    //   224: goto -> 244
    //   227: bipush #61
    //   229: goto -> 244
    //   232: bipush #117
    //   234: goto -> 244
    //   237: bipush #97
    //   239: goto -> 244
    //   242: bipush #40
    //   244: ixor
    //   245: ixor
    //   246: i2c
    //   247: castore
    //   248: iinc #6, 1
    //   251: dup
    //   252: ifne -> 260
    //   255: dup2
    //   256: dup_x1
    //   257: goto -> 166
    //   260: dup2_x1
    //   261: pop2
    //   262: dup_x2
    //   263: iload #6
    //   265: if_icmpgt -> 162
    //   268: pop
    //   269: new java/lang/String
    //   272: dup_x1
    //   273: swap
    //   274: invokespecial <init> : ([C)V
    //   277: invokevirtual intern : ()Ljava/lang/String;
    //   280: swap
    //   281: pop
    //   282: swap
    //   283: tableswitch default -> 40, 0 -> 99
    //   300: new java/math/BigInteger
    //   303: dup
    //   304: sipush #-10076
    //   307: sipush #-18848
    //   310: invokestatic a : (II)Ljava/lang/String;
    //   313: invokespecial <init> : (Ljava/lang/String;)V
    //   316: putstatic burp/Zeqr.ZM : Ljava/lang/Object;
    //   319: sipush #-10054
    //   322: sipush #2552
    //   325: invokestatic a : (II)Ljava/lang/String;
    //   328: putstatic burp/Zeqr.Zb : Ljava/lang/String;
    //   331: return
  }
  
  private static Throwable a(Throwable paramThrowable) {
    return paramThrowable;
  }
  
  private static String a(int paramInt1, int paramInt2) {
    int i = (paramInt1 ^ 0xFFFFD8AE) & 0xFFFF;
    if (b[i] == null) {
      char[] arrayOfChar = a[i].toCharArray();
      switch (arrayOfChar[0] & 0xFF) {
        case 0:
        
        case 1:
        
        case 2:
        
        case 3:
        
        case 4:
        
        case 5:
        
        case 6:
        
        case 7:
        
        case 8:
        
        case 9:
        
        case 10:
        
        case 11:
        
        case 12:
        
        case 13:
        
        case 14:
        
        case 15:
        
        case 16:
        
        case 17:
        
        case 18:
        
        case 19:
        
        case 20:
        
        case 21:
        
        case 22:
        
        case 23:
        
        case 24:
        
        case 25:
        
        case 26:
        
        case 27:
        
        case 28:
        
        case 29:
        
        case 30:
        
        case 31:
        
        case 32:
        
        case 33:
        
        case 34:
        
        case 35:
        
        case 36:
        
        case 37:
        
        case 38:
        
        case 39:
        
        case 40:
        
        case 41:
        
        case 42:
        
        case 43:
        
        case 44:
        
        case 45:
        
        case 46:
        
        case 47:
        
        case 48:
        
        case 49:
        
        case 50:
        
        case 51:
        
        case 52:
        
        case 53:
        
        case 54:
        
        case 55:
        
        case 56:
        
        case 57:
        
        case 58:
        
        case 59:
        
        case 60:
        
        case 61:
        
        case 62:
        
        case 63:
        
        case 64:
        
        case 65:
        
        case 66:
        
        case 67:
        
        case 68:
        
        case 69:
        
        case 70:
        
        case 71:
        
        case 72:
        
        case 73:
        
        case 74:
        
        case 75:
        
        case 76:
        
        case 77:
        
        case 78:
        
        case 79:
        
        case 80:
        
        case 81:
        
        case 82:
        
        case 83:
        
        case 84:
        
        case 85:
        
        case 86:
        
        case 87:
        
        case 88:
        
        case 89:
        
        case 90:
        
        case 91:
        
        case 92:
        
        case 93:
        
        case 94:
        
        case 95:
        
        case 96:
        
        case 97:
        
        case 98:
        
        case 99:
        
        case 100:
        
        case 101:
        
        case 102:
        
        case 103:
        
        case 104:
        
        case 105:
        
        case 106:
        
        case 107:
        
        case 108:
        
        case 109:
        
        case 110:
        
        case 111:
        
        case 112:
        
        case 113:
        
        case 114:
        
        case 115:
        
        case 116:
        
        case 117:
        
        case 118:
        
        case 119:
        
        case 120:
        
        case 121:
        
        case 122:
        
        case 123:
        
        case 124:
        
        case 125:
        
        case 126:
        
        case 127:
        
        case 128:
        
        case 129:
        
        case 130:
        
        case 131:
        
        case 132:
        
        case 133:
        
        case 134:
        
        case 135:
        
        case 136:
        
        case 137:
        
        case 138:
        
        case 139:
        
        case 140:
        
        case 141:
        
        case 142:
        
        case 143:
        
        case 144:
        
        case 145:
        
        case 146:
        
        case 147:
        
        case 148:
        
        case 149:
        
        case 150:
        
        case 151:
        
        case 152:
        
        case 153:
        
        case 154:
        
        case 155:
        
        case 156:
        
        case 157:
        
        case 158:
        
        case 159:
        
        case 160:
        
        case 161:
        
        case 162:
        
        case 163:
        
        case 164:
        
        case 165:
        
        case 166:
        
        case 167:
        
        case 168:
        
        case 169:
        
        case 170:
        
        case 171:
        
        case 172:
        
        case 173:
        
        case 174:
        
        case 175:
        
        case 176:
        
        case 177:
        
        case 178:
        
        case 179:
        
        case 180:
        
        case 181:
        
        case 182:
        
        case 183:
        
        case 184:
        
        case 185:
        
        case 186:
        
        case 187:
        
        case 188:
        
        case 189:
        
        case 190:
        
        case 191:
        
        case 192:
        
        case 193:
        
        case 194:
        
        case 195:
        
        case 196:
        
        case 197:
        
        case 198:
        
        case 199:
        
        case 200:
        
        case 201:
        
        case 202:
        
        case 203:
        
        case 204:
        
        case 205:
        
        case 206:
        
        case 207:
        
        case 208:
        
        case 209:
        
        case 210:
        
        case 211:
        
        case 212:
        
        case 213:
        
        case 214:
        
        case 215:
        
        case 216:
        
        case 217:
        
        case 218:
        
        case 219:
        
        case 220:
        
        case 221:
        
        case 222:
        
        case 223:
        
        case 224:
        
        case 225:
        
        case 226:
        
        case 227:
        
        case 228:
        
        case 229:
        
        case 230:
        
        case 231:
        
        case 232:
        
        case 233:
        
        case 234:
        
        case 235:
        
        case 236:
        
        case 237:
        
        case 238:
        
        case 239:
        
        case 240:
        
        case 241:
        
        case 242:
        
        case 243:
        
        case 244:
        
        case 245:
        
        case 246:
        
        case 247:
        
        case 248:
        
        case 249:
        
        case 250:
        
        case 251:
        
        case 252:
        
        case 253:
        
        case 254:
        
        default:
          break;
      } 
      byte b1 = 25;
      int j = (paramInt2 & 0xFF) - b1;
      if (j < 0)
        j += 256; 
      int k = ((paramInt2 & 0xFFFF) >>> 8) - b1;
      if (k < 0)
        k += 256; 
      for (byte b2 = 0; b2 < arrayOfChar.length; b2++) {
        int m = b2 % 2;
        if (m == 0) {
          arrayOfChar[b2] = (char)(arrayOfChar[b2] ^ j);
          j = ((j >>> 3 | j << 5) ^ arrayOfChar[b2]) & 0xFF;
        } else {
          arrayOfChar[b2] = (char)(arrayOfChar[b2] ^ k);
          k = ((k >>> 3 | k << 5) ^ arrayOfChar[b2]) & 0xFF;
        } 
      } 
      b[i] = (new String(arrayOfChar)).intern();
    } 
    return b[i];
  }
}


/* Location:              C:\Program Files\BurpSuitePro\burpsuite_pro.jar!\burp\Zeqr.class
 * Java compiler version: 21 (65.0)
 * JD-Core Version:       1.1.3
 */