package burp;

import java.math.BigInteger;

class Zera extends ClassLoader {
  static Object Zy;
  
  static String Zn;
  
  private static final String[] a;
  
  private static final String[] b;
  
  static void ZU(Object paramObject) {
    Ze8i.ZM = a(-10440, 4948);
    Ze8i.Zq = new BigInteger(a(-10438, -23213));
    boolean bool = Zt2e.ZN();
    try {
      try {
        if (Ze69.ZA.charAt(Math.abs(((BigInteger)Zkt7.ZY).intValue() % 32)) <= Ze69.ZA.charAt(Math.abs(((BigInteger)Ze8i.Zq).intValue() % 32))) {
          try {
            Zgja.ZL(Class.forName(a(-10435, -9957)));
            if (!bool)
              Zlx5.ZS(Class.forName(a(-10436, -15895))); 
          } catch (Throwable throwable) {
            throw a(null);
          } 
          return;
        } 
      } catch (Throwable throwable) {
        throw a(null);
      } 
      Zlx5.ZS(Class.forName(a(-10436, -15895)));
    } catch (Throwable throwable) {}
  }
  
  static boolean ZQ(Object[] paramArrayOfObject, Object paramObject) throws Throwable {
    // Byte code:
    //   0: invokestatic ZN : ()Z
    //   3: istore_2
    //   4: new java/lang/StringBuilder
    //   7: dup
    //   8: invokespecial <init> : ()V
    //   11: astore_3
    //   12: iconst_0
    //   13: istore #4
    //   15: iload #4
    //   17: bipush #32
    //   19: if_icmpge -> 1355
    //   22: iload #4
    //   24: tableswitch default -> 1348, 0 -> 168, 1 -> 205, 2 -> 242, 3 -> 279, 4 -> 316, 5 -> 353, 6 -> 390, 7 -> 427, 8 -> 464, 9 -> 501, 10 -> 538, 11 -> 575, 12 -> 612, 13 -> 649, 14 -> 686, 15 -> 723, 16 -> 760, 17 -> 797, 18 -> 834, 19 -> 871, 20 -> 908, 21 -> 945, 22 -> 982, 23 -> 1019, 24 -> 1056, 25 -> 1093, 26 -> 1130, 27 -> 1167, 28 -> 1204, 29 -> 1241, 30 -> 1278, 31 -> 1315
    //   168: aload_3
    //   169: getstatic burp/Zt9_.Zf : Ljava/lang/String;
    //   172: getstatic burp/Zzgh.ZV : Ljava/lang/Object;
    //   175: checkcast java/math/BigInteger
    //   178: invokevirtual intValue : ()I
    //   181: bipush #32
    //   183: irem
    //   184: invokestatic abs : (I)I
    //   187: invokevirtual charAt : (I)C
    //   190: invokevirtual append : (C)Ljava/lang/StringBuilder;
    //   193: pop
    //   194: iload_2
    //   195: ifne -> 1348
    //   198: goto -> 205
    //   201: invokestatic a : (Ljava/lang/Throwable;)Ljava/lang/Throwable;
    //   204: athrow
    //   205: aload_3
    //   206: getstatic burp/Zgq_.ZQ : Ljava/lang/String;
    //   209: getstatic burp/Zlf0.ZC : Ljava/lang/Object;
    //   212: checkcast java/math/BigInteger
    //   215: invokevirtual intValue : ()I
    //   218: bipush #32
    //   220: irem
    //   221: invokestatic abs : (I)I
    //   224: invokevirtual charAt : (I)C
    //   227: invokevirtual append : (C)Ljava/lang/StringBuilder;
    //   230: pop
    //   231: iload_2
    //   232: ifne -> 1348
    //   235: goto -> 242
    //   238: invokestatic a : (Ljava/lang/Throwable;)Ljava/lang/Throwable;
    //   241: athrow
    //   242: aload_3
    //   243: getstatic burp/Zs8s.Za : Ljava/lang/String;
    //   246: getstatic burp/Zzoi.ZI : Ljava/lang/Object;
    //   249: checkcast java/math/BigInteger
    //   252: invokevirtual intValue : ()I
    //   255: bipush #32
    //   257: irem
    //   258: invokestatic abs : (I)I
    //   261: invokevirtual charAt : (I)C
    //   264: invokevirtual append : (C)Ljava/lang/StringBuilder;
    //   267: pop
    //   268: iload_2
    //   269: ifne -> 1348
    //   272: goto -> 279
    //   275: invokestatic a : (Ljava/lang/Throwable;)Ljava/lang/Throwable;
    //   278: athrow
    //   279: aload_3
    //   280: getstatic burp/Zrhp.ZQ : Ljava/lang/String;
    //   283: getstatic burp/Zlem.ZI : Ljava/lang/Object;
    //   286: checkcast java/math/BigInteger
    //   289: invokevirtual intValue : ()I
    //   292: bipush #32
    //   294: irem
    //   295: invokestatic abs : (I)I
    //   298: invokevirtual charAt : (I)C
    //   301: invokevirtual append : (C)Ljava/lang/StringBuilder;
    //   304: pop
    //   305: iload_2
    //   306: ifne -> 1348
    //   309: goto -> 316
    //   312: invokestatic a : (Ljava/lang/Throwable;)Ljava/lang/Throwable;
    //   315: athrow
    //   316: aload_3
    //   317: getstatic burp/Zera.Zn : Ljava/lang/String;
    //   320: getstatic burp/Zlx5.Zp : Ljava/lang/Object;
    //   323: checkcast java/math/BigInteger
    //   326: invokevirtual intValue : ()I
    //   329: bipush #32
    //   331: irem
    //   332: invokestatic abs : (I)I
    //   335: invokevirtual charAt : (I)C
    //   338: invokevirtual append : (C)Ljava/lang/StringBuilder;
    //   341: pop
    //   342: iload_2
    //   343: ifne -> 1348
    //   346: goto -> 353
    //   349: invokestatic a : (Ljava/lang/Throwable;)Ljava/lang/Throwable;
    //   352: athrow
    //   353: aload_3
    //   354: getstatic burp/Zsqy.Zo : Ljava/lang/String;
    //   357: getstatic burp/Zrcy.Zr : Ljava/lang/Object;
    //   360: checkcast java/math/BigInteger
    //   363: invokevirtual intValue : ()I
    //   366: bipush #32
    //   368: irem
    //   369: invokestatic abs : (I)I
    //   372: invokevirtual charAt : (I)C
    //   375: invokevirtual append : (C)Ljava/lang/StringBuilder;
    //   378: pop
    //   379: iload_2
    //   380: ifne -> 1348
    //   383: goto -> 390
    //   386: invokestatic a : (Ljava/lang/Throwable;)Ljava/lang/Throwable;
    //   389: athrow
    //   390: aload_3
    //   391: getstatic burp/Zv8c.ZO : Ljava/lang/String;
    //   394: getstatic burp/Zlck.Zr : Ljava/lang/Object;
    //   397: checkcast java/math/BigInteger
    //   400: invokevirtual intValue : ()I
    //   403: bipush #32
    //   405: irem
    //   406: invokestatic abs : (I)I
    //   409: invokevirtual charAt : (I)C
    //   412: invokevirtual append : (C)Ljava/lang/StringBuilder;
    //   415: pop
    //   416: iload_2
    //   417: ifne -> 1348
    //   420: goto -> 427
    //   423: invokestatic a : (Ljava/lang/Throwable;)Ljava/lang/Throwable;
    //   426: athrow
    //   427: aload_3
    //   428: getstatic burp/Zgzv.Zy : Ljava/lang/String;
    //   431: getstatic burp/Ztlz.ZW : Ljava/lang/Object;
    //   434: checkcast java/math/BigInteger
    //   437: invokevirtual intValue : ()I
    //   440: bipush #32
    //   442: irem
    //   443: invokestatic abs : (I)I
    //   446: invokevirtual charAt : (I)C
    //   449: invokevirtual append : (C)Ljava/lang/StringBuilder;
    //   452: pop
    //   453: iload_2
    //   454: ifne -> 1348
    //   457: goto -> 464
    //   460: invokestatic a : (Ljava/lang/Throwable;)Ljava/lang/Throwable;
    //   463: athrow
    //   464: aload_3
    //   465: getstatic burp/Zgq_.ZQ : Ljava/lang/String;
    //   468: getstatic burp/Zzo5.Zf : Ljava/lang/Object;
    //   471: checkcast java/math/BigInteger
    //   474: invokevirtual intValue : ()I
    //   477: bipush #32
    //   479: irem
    //   480: invokestatic abs : (I)I
    //   483: invokevirtual charAt : (I)C
    //   486: invokevirtual append : (C)Ljava/lang/StringBuilder;
    //   489: pop
    //   490: iload_2
    //   491: ifne -> 1348
    //   494: goto -> 501
    //   497: invokestatic a : (Ljava/lang/Throwable;)Ljava/lang/Throwable;
    //   500: athrow
    //   501: aload_3
    //   502: getstatic burp/Zsxh.Z_ : Ljava/lang/String;
    //   505: getstatic burp/Zkll.Zl : Ljava/lang/Object;
    //   508: checkcast java/math/BigInteger
    //   511: invokevirtual intValue : ()I
    //   514: bipush #32
    //   516: irem
    //   517: invokestatic abs : (I)I
    //   520: invokevirtual charAt : (I)C
    //   523: invokevirtual append : (C)Ljava/lang/StringBuilder;
    //   526: pop
    //   527: iload_2
    //   528: ifne -> 1348
    //   531: goto -> 538
    //   534: invokestatic a : (Ljava/lang/Throwable;)Ljava/lang/Throwable;
    //   537: athrow
    //   538: aload_3
    //   539: getstatic burp/Zz75.ZT : Ljava/lang/String;
    //   542: getstatic burp/Zkll.Zl : Ljava/lang/Object;
    //   545: checkcast java/math/BigInteger
    //   548: invokevirtual intValue : ()I
    //   551: bipush #32
    //   553: irem
    //   554: invokestatic abs : (I)I
    //   557: invokevirtual charAt : (I)C
    //   560: invokevirtual append : (C)Ljava/lang/StringBuilder;
    //   563: pop
    //   564: iload_2
    //   565: ifne -> 1348
    //   568: goto -> 575
    //   571: invokestatic a : (Ljava/lang/Throwable;)Ljava/lang/Throwable;
    //   574: athrow
    //   575: aload_3
    //   576: getstatic burp/Zre5.ZR : Ljava/lang/String;
    //   579: getstatic burp/Zs2n.ZK : Ljava/lang/Object;
    //   582: checkcast java/math/BigInteger
    //   585: invokevirtual intValue : ()I
    //   588: bipush #32
    //   590: irem
    //   591: invokestatic abs : (I)I
    //   594: invokevirtual charAt : (I)C
    //   597: invokevirtual append : (C)Ljava/lang/StringBuilder;
    //   600: pop
    //   601: iload_2
    //   602: ifne -> 1348
    //   605: goto -> 612
    //   608: invokestatic a : (Ljava/lang/Throwable;)Ljava/lang/Throwable;
    //   611: athrow
    //   612: aload_3
    //   613: getstatic burp/Zz20.ZX : Ljava/lang/String;
    //   616: getstatic burp/Zrtc.Zr : Ljava/lang/Object;
    //   619: checkcast java/math/BigInteger
    //   622: invokevirtual intValue : ()I
    //   625: bipush #32
    //   627: irem
    //   628: invokestatic abs : (I)I
    //   631: invokevirtual charAt : (I)C
    //   634: invokevirtual append : (C)Ljava/lang/StringBuilder;
    //   637: pop
    //   638: iload_2
    //   639: ifne -> 1348
    //   642: goto -> 649
    //   645: invokestatic a : (Ljava/lang/Throwable;)Ljava/lang/Throwable;
    //   648: athrow
    //   649: aload_3
    //   650: getstatic burp/Zli5.Zq : Ljava/lang/String;
    //   653: getstatic burp/Zr2i.ZD : Ljava/lang/Object;
    //   656: checkcast java/math/BigInteger
    //   659: invokevirtual intValue : ()I
    //   662: bipush #32
    //   664: irem
    //   665: invokestatic abs : (I)I
    //   668: invokevirtual charAt : (I)C
    //   671: invokevirtual append : (C)Ljava/lang/StringBuilder;
    //   674: pop
    //   675: iload_2
    //   676: ifne -> 1348
    //   679: goto -> 686
    //   682: invokestatic a : (Ljava/lang/Throwable;)Ljava/lang/Throwable;
    //   685: athrow
    //   686: aload_3
    //   687: getstatic burp/Zre5.ZR : Ljava/lang/String;
    //   690: getstatic burp/Zess.Zj : Ljava/lang/Object;
    //   693: checkcast java/math/BigInteger
    //   696: invokevirtual intValue : ()I
    //   699: bipush #32
    //   701: irem
    //   702: invokestatic abs : (I)I
    //   705: invokevirtual charAt : (I)C
    //   708: invokevirtual append : (C)Ljava/lang/StringBuilder;
    //   711: pop
    //   712: iload_2
    //   713: ifne -> 1348
    //   716: goto -> 723
    //   719: invokestatic a : (Ljava/lang/Throwable;)Ljava/lang/Throwable;
    //   722: athrow
    //   723: aload_3
    //   724: getstatic burp/Zzr5.Zg : Ljava/lang/String;
    //   727: getstatic burp/Ze82.ZR : Ljava/lang/Object;
    //   730: checkcast java/math/BigInteger
    //   733: invokevirtual intValue : ()I
    //   736: bipush #32
    //   738: irem
    //   739: invokestatic abs : (I)I
    //   742: invokevirtual charAt : (I)C
    //   745: invokevirtual append : (C)Ljava/lang/StringBuilder;
    //   748: pop
    //   749: iload_2
    //   750: ifne -> 1348
    //   753: goto -> 760
    //   756: invokestatic a : (Ljava/lang/Throwable;)Ljava/lang/Throwable;
    //   759: athrow
    //   760: aload_3
    //   761: getstatic burp/Zt0t.ZR : Ljava/lang/String;
    //   764: getstatic burp/Zke7.Zj : Ljava/lang/Object;
    //   767: checkcast java/math/BigInteger
    //   770: invokevirtual intValue : ()I
    //   773: bipush #32
    //   775: irem
    //   776: invokestatic abs : (I)I
    //   779: invokevirtual charAt : (I)C
    //   782: invokevirtual append : (C)Ljava/lang/StringBuilder;
    //   785: pop
    //   786: iload_2
    //   787: ifne -> 1348
    //   790: goto -> 797
    //   793: invokestatic a : (Ljava/lang/Throwable;)Ljava/lang/Throwable;
    //   796: athrow
    //   797: aload_3
    //   798: getstatic burp/Zlpj.Zj : Ljava/lang/String;
    //   801: getstatic burp/Zs75.Zo : Ljava/lang/Object;
    //   804: checkcast java/math/BigInteger
    //   807: invokevirtual intValue : ()I
    //   810: bipush #32
    //   812: irem
    //   813: invokestatic abs : (I)I
    //   816: invokevirtual charAt : (I)C
    //   819: invokevirtual append : (C)Ljava/lang/StringBuilder;
    //   822: pop
    //   823: iload_2
    //   824: ifne -> 1348
    //   827: goto -> 834
    //   830: invokestatic a : (Ljava/lang/Throwable;)Ljava/lang/Throwable;
    //   833: athrow
    //   834: aload_3
    //   835: getstatic burp/Zl8f.ZK : Ljava/lang/String;
    //   838: getstatic burp/Zix.ZO : Ljava/lang/Object;
    //   841: checkcast java/math/BigInteger
    //   844: invokevirtual intValue : ()I
    //   847: bipush #32
    //   849: irem
    //   850: invokestatic abs : (I)I
    //   853: invokevirtual charAt : (I)C
    //   856: invokevirtual append : (C)Ljava/lang/StringBuilder;
    //   859: pop
    //   860: iload_2
    //   861: ifne -> 1348
    //   864: goto -> 871
    //   867: invokestatic a : (Ljava/lang/Throwable;)Ljava/lang/Throwable;
    //   870: athrow
    //   871: aload_3
    //   872: getstatic burp/Zrpu.Zy : Ljava/lang/String;
    //   875: getstatic burp/Zs8q.ZI : Ljava/lang/Object;
    //   878: checkcast java/math/BigInteger
    //   881: invokevirtual intValue : ()I
    //   884: bipush #32
    //   886: irem
    //   887: invokestatic abs : (I)I
    //   890: invokevirtual charAt : (I)C
    //   893: invokevirtual append : (C)Ljava/lang/StringBuilder;
    //   896: pop
    //   897: iload_2
    //   898: ifne -> 1348
    //   901: goto -> 908
    //   904: invokestatic a : (Ljava/lang/Throwable;)Ljava/lang/Throwable;
    //   907: athrow
    //   908: aload_3
    //   909: getstatic burp/Zr2i.Z_ : Ljava/lang/String;
    //   912: getstatic burp/Zsqy.ZV : Ljava/lang/Object;
    //   915: checkcast java/math/BigInteger
    //   918: invokevirtual intValue : ()I
    //   921: bipush #32
    //   923: irem
    //   924: invokestatic abs : (I)I
    //   927: invokevirtual charAt : (I)C
    //   930: invokevirtual append : (C)Ljava/lang/StringBuilder;
    //   933: pop
    //   934: iload_2
    //   935: ifne -> 1348
    //   938: goto -> 945
    //   941: invokestatic a : (Ljava/lang/Throwable;)Ljava/lang/Throwable;
    //   944: athrow
    //   945: aload_3
    //   946: getstatic burp/Zt0t.ZR : Ljava/lang/String;
    //   949: getstatic burp/Zm7x.Zv : Ljava/lang/Object;
    //   952: checkcast java/math/BigInteger
    //   955: invokevirtual intValue : ()I
    //   958: bipush #32
    //   960: irem
    //   961: invokestatic abs : (I)I
    //   964: invokevirtual charAt : (I)C
    //   967: invokevirtual append : (C)Ljava/lang/StringBuilder;
    //   970: pop
    //   971: iload_2
    //   972: ifne -> 1348
    //   975: goto -> 982
    //   978: invokestatic a : (Ljava/lang/Throwable;)Ljava/lang/Throwable;
    //   981: athrow
    //   982: aload_3
    //   983: getstatic burp/Zkjr.Zg : Ljava/lang/String;
    //   986: getstatic burp/Zlf0.ZC : Ljava/lang/Object;
    //   989: checkcast java/math/BigInteger
    //   992: invokevirtual intValue : ()I
    //   995: bipush #32
    //   997: irem
    //   998: invokestatic abs : (I)I
    //   1001: invokevirtual charAt : (I)C
    //   1004: invokevirtual append : (C)Ljava/lang/StringBuilder;
    //   1007: pop
    //   1008: iload_2
    //   1009: ifne -> 1348
    //   1012: goto -> 1019
    //   1015: invokestatic a : (Ljava/lang/Throwable;)Ljava/lang/Throwable;
    //   1018: athrow
    //   1019: aload_3
    //   1020: getstatic burp/Zlf0.ZS : Ljava/lang/String;
    //   1023: getstatic burp/Zex.ZO : Ljava/lang/Object;
    //   1026: checkcast java/math/BigInteger
    //   1029: invokevirtual intValue : ()I
    //   1032: bipush #32
    //   1034: irem
    //   1035: invokestatic abs : (I)I
    //   1038: invokevirtual charAt : (I)C
    //   1041: invokevirtual append : (C)Ljava/lang/StringBuilder;
    //   1044: pop
    //   1045: iload_2
    //   1046: ifne -> 1348
    //   1049: goto -> 1056
    //   1052: invokestatic a : (Ljava/lang/Throwable;)Ljava/lang/Throwable;
    //   1055: athrow
    //   1056: aload_3
    //   1057: getstatic burp/Ze82.Zx : Ljava/lang/String;
    //   1060: getstatic burp/Zs75.Zo : Ljava/lang/Object;
    //   1063: checkcast java/math/BigInteger
    //   1066: invokevirtual intValue : ()I
    //   1069: bipush #32
    //   1071: irem
    //   1072: invokestatic abs : (I)I
    //   1075: invokevirtual charAt : (I)C
    //   1078: invokevirtual append : (C)Ljava/lang/StringBuilder;
    //   1081: pop
    //   1082: iload_2
    //   1083: ifne -> 1348
    //   1086: goto -> 1093
    //   1089: invokestatic a : (Ljava/lang/Throwable;)Ljava/lang/Throwable;
    //   1092: athrow
    //   1093: aload_3
    //   1094: getstatic burp/Zxn5.ZI : Ljava/lang/String;
    //   1097: getstatic burp/Zzgh.ZV : Ljava/lang/Object;
    //   1100: checkcast java/math/BigInteger
    //   1103: invokevirtual intValue : ()I
    //   1106: bipush #32
    //   1108: irem
    //   1109: invokestatic abs : (I)I
    //   1112: invokevirtual charAt : (I)C
    //   1115: invokevirtual append : (C)Ljava/lang/StringBuilder;
    //   1118: pop
    //   1119: iload_2
    //   1120: ifne -> 1348
    //   1123: goto -> 1130
    //   1126: invokestatic a : (Ljava/lang/Throwable;)Ljava/lang/Throwable;
    //   1129: athrow
    //   1130: aload_3
    //   1131: getstatic burp/Zl50.Zm : Ljava/lang/String;
    //   1134: getstatic burp/Zlhq.Zw : Ljava/lang/Object;
    //   1137: checkcast java/math/BigInteger
    //   1140: invokevirtual intValue : ()I
    //   1143: bipush #32
    //   1145: irem
    //   1146: invokestatic abs : (I)I
    //   1149: invokevirtual charAt : (I)C
    //   1152: invokevirtual append : (C)Ljava/lang/StringBuilder;
    //   1155: pop
    //   1156: iload_2
    //   1157: ifne -> 1348
    //   1160: goto -> 1167
    //   1163: invokestatic a : (Ljava/lang/Throwable;)Ljava/lang/Throwable;
    //   1166: athrow
    //   1167: aload_3
    //   1168: getstatic burp/Zqp.ZX : Ljava/lang/String;
    //   1171: getstatic burp/Zb.ZV : Ljava/lang/Object;
    //   1174: checkcast java/math/BigInteger
    //   1177: invokevirtual intValue : ()I
    //   1180: bipush #32
    //   1182: irem
    //   1183: invokestatic abs : (I)I
    //   1186: invokevirtual charAt : (I)C
    //   1189: invokevirtual append : (C)Ljava/lang/StringBuilder;
    //   1192: pop
    //   1193: iload_2
    //   1194: ifne -> 1348
    //   1197: goto -> 1204
    //   1200: invokestatic a : (Ljava/lang/Throwable;)Ljava/lang/Throwable;
    //   1203: athrow
    //   1204: aload_3
    //   1205: getstatic burp/Zx6d.ZP : Ljava/lang/String;
    //   1208: getstatic burp/Zeb7.ZJ : Ljava/lang/Object;
    //   1211: checkcast java/math/BigInteger
    //   1214: invokevirtual intValue : ()I
    //   1217: bipush #32
    //   1219: irem
    //   1220: invokestatic abs : (I)I
    //   1223: invokevirtual charAt : (I)C
    //   1226: invokevirtual append : (C)Ljava/lang/StringBuilder;
    //   1229: pop
    //   1230: iload_2
    //   1231: ifne -> 1348
    //   1234: goto -> 1241
    //   1237: invokestatic a : (Ljava/lang/Throwable;)Ljava/lang/Throwable;
    //   1240: athrow
    //   1241: aload_3
    //   1242: getstatic burp/Zxe.ZD : Ljava/lang/String;
    //   1245: getstatic burp/Zgqi.Zp : Ljava/lang/Object;
    //   1248: checkcast java/math/BigInteger
    //   1251: invokevirtual intValue : ()I
    //   1254: bipush #32
    //   1256: irem
    //   1257: invokestatic abs : (I)I
    //   1260: invokevirtual charAt : (I)C
    //   1263: invokevirtual append : (C)Ljava/lang/StringBuilder;
    //   1266: pop
    //   1267: iload_2
    //   1268: ifne -> 1348
    //   1271: goto -> 1278
    //   1274: invokestatic a : (Ljava/lang/Throwable;)Ljava/lang/Throwable;
    //   1277: athrow
    //   1278: aload_3
    //   1279: getstatic burp/Zlrm.Zt : Ljava/lang/String;
    //   1282: getstatic burp/Zltz.Zg : Ljava/lang/Object;
    //   1285: checkcast java/math/BigInteger
    //   1288: invokevirtual intValue : ()I
    //   1291: bipush #32
    //   1293: irem
    //   1294: invokestatic abs : (I)I
    //   1297: invokevirtual charAt : (I)C
    //   1300: invokevirtual append : (C)Ljava/lang/StringBuilder;
    //   1303: pop
    //   1304: iload_2
    //   1305: ifne -> 1348
    //   1308: goto -> 1315
    //   1311: invokestatic a : (Ljava/lang/Throwable;)Ljava/lang/Throwable;
    //   1314: athrow
    //   1315: aload_3
    //   1316: getstatic burp/Zrcy.Zq : Ljava/lang/String;
    //   1319: getstatic burp/Zm52.ZR : Ljava/lang/Object;
    //   1322: checkcast java/math/BigInteger
    //   1325: invokevirtual intValue : ()I
    //   1328: bipush #32
    //   1330: irem
    //   1331: invokestatic abs : (I)I
    //   1334: invokevirtual charAt : (I)C
    //   1337: invokevirtual append : (C)Ljava/lang/StringBuilder;
    //   1340: pop
    //   1341: goto -> 1348
    //   1344: invokestatic a : (Ljava/lang/Throwable;)Ljava/lang/Throwable;
    //   1347: athrow
    //   1348: iinc #4, 1
    //   1351: iload_2
    //   1352: ifne -> 15
    //   1355: aload_3
    //   1356: invokevirtual toString : ()Ljava/lang/String;
    //   1359: putstatic burp/Zr2i.Z_ : Ljava/lang/String;
    //   1362: sipush #-10437
    //   1365: getstatic burp/Zeuc.Zd : Ljava/lang/Object;
    //   1368: checkcast java/math/BigInteger
    //   1371: getstatic burp/Ze5t.Zc : Ljava/lang/Object;
    //   1374: checkcast java/math/BigInteger
    //   1377: invokevirtual subtract : (Ljava/math/BigInteger;)Ljava/math/BigInteger;
    //   1380: putstatic burp/Zlr.ZK : Ljava/lang/Object;
    //   1383: sipush #20739
    //   1386: invokestatic a : (II)Ljava/lang/String;
    //   1389: iconst_1
    //   1390: ldc burp/Zlvb
    //   1392: invokevirtual getClassLoader : ()Ljava/lang/ClassLoader;
    //   1395: invokestatic forName : (Ljava/lang/String;ZLjava/lang/ClassLoader;)Ljava/lang/Class;
    //   1398: invokevirtual getDeclaredFields : ()[Ljava/lang/reflect/Field;
    //   1401: astore #4
    //   1403: aload #4
    //   1405: arraylength
    //   1406: istore #5
    //   1408: iconst_0
    //   1409: istore #6
    //   1411: iload #6
    //   1413: iload #5
    //   1415: if_icmpge -> 1553
    //   1418: aload #4
    //   1420: iload #6
    //   1422: aaload
    //   1423: astore #7
    //   1425: aload #7
    //   1427: invokevirtual getModifiers : ()I
    //   1430: invokestatic isStatic : (I)Z
    //   1433: ifne -> 1443
    //   1436: goto -> 1546
    //   1439: invokestatic a : (Ljava/lang/Throwable;)Ljava/lang/Throwable;
    //   1442: athrow
    //   1443: aload #7
    //   1445: invokevirtual getType : ()Ljava/lang/Class;
    //   1448: astore #8
    //   1450: aload #8
    //   1452: ifnull -> 1533
    //   1455: aload #8
    //   1457: invokevirtual isPrimitive : ()Z
    //   1460: ifne -> 1533
    //   1463: goto -> 1470
    //   1466: invokestatic a : (Ljava/lang/Throwable;)Ljava/lang/Throwable;
    //   1469: athrow
    //   1470: aload #8
    //   1472: invokevirtual getPackage : ()Ljava/lang/Package;
    //   1475: ifnull -> 1533
    //   1478: goto -> 1485
    //   1481: invokestatic a : (Ljava/lang/Throwable;)Ljava/lang/Throwable;
    //   1484: athrow
    //   1485: aload #8
    //   1487: invokevirtual getPackage : ()Ljava/lang/Package;
    //   1490: invokevirtual getName : ()Ljava/lang/String;
    //   1493: ifnull -> 1533
    //   1496: goto -> 1503
    //   1499: invokestatic a : (Ljava/lang/Throwable;)Ljava/lang/Throwable;
    //   1502: athrow
    //   1503: aload #8
    //   1505: invokevirtual getPackage : ()Ljava/lang/Package;
    //   1508: invokevirtual getName : ()Ljava/lang/String;
    //   1511: sipush #-10434
    //   1514: sipush #-17770
    //   1517: invokestatic a : (II)Ljava/lang/String;
    //   1520: invokevirtual startsWith : (Ljava/lang/String;)Z
    //   1523: ifne -> 1533
    //   1526: goto -> 1533
    //   1529: invokestatic a : (Ljava/lang/Throwable;)Ljava/lang/Throwable;
    //   1532: athrow
    //   1533: aload #7
    //   1535: iconst_1
    //   1536: invokevirtual setAccessible : (Z)V
    //   1539: aload #7
    //   1541: aconst_null
    //   1542: invokevirtual get : (Ljava/lang/Object;)Ljava/lang/Object;
    //   1545: pop
    //   1546: iinc #6, 1
    //   1549: iload_2
    //   1550: ifne -> 1411
    //   1553: sipush #-10433
    //   1556: sipush #28068
    //   1559: invokestatic a : (II)Ljava/lang/String;
    //   1562: invokestatic forName : (Ljava/lang/String;)Ljava/lang/Class;
    //   1565: invokevirtual getDeclaredMethods : ()[Ljava/lang/reflect/Method;
    //   1568: astore #4
    //   1570: aload #4
    //   1572: arraylength
    //   1573: istore #5
    //   1575: iconst_0
    //   1576: istore #6
    //   1578: iload #6
    //   1580: iload #5
    //   1582: if_icmpge -> 1715
    //   1585: aload #4
    //   1587: iload #6
    //   1589: aaload
    //   1590: astore #7
    //   1592: aload #7
    //   1594: invokevirtual getParameterTypes : ()[Ljava/lang/Class;
    //   1597: pop
    //   1598: aload #7
    //   1600: invokevirtual getModifiers : ()I
    //   1603: invokestatic isStatic : (I)Z
    //   1606: ifeq -> 1701
    //   1609: aload #7
    //   1611: invokevirtual getParameterTypes : ()[Ljava/lang/Class;
    //   1614: arraylength
    //   1615: iconst_2
    //   1616: if_icmpne -> 1701
    //   1619: goto -> 1626
    //   1622: invokestatic a : (Ljava/lang/Throwable;)Ljava/lang/Throwable;
    //   1625: athrow
    //   1626: aload #7
    //   1628: invokevirtual getReturnType : ()Ljava/lang/Class;
    //   1631: getstatic java/lang/Void.TYPE : Ljava/lang/Class;
    //   1634: invokevirtual equals : (Ljava/lang/Object;)Z
    //   1637: ifeq -> 1701
    //   1640: goto -> 1647
    //   1643: invokestatic a : (Ljava/lang/Throwable;)Ljava/lang/Throwable;
    //   1646: athrow
    //   1647: aload #7
    //   1649: iconst_1
    //   1650: invokevirtual setAccessible : (Z)V
    //   1653: aload #7
    //   1655: aconst_null
    //   1656: iconst_2
    //   1657: anewarray java/lang/Object
    //   1660: dup
    //   1661: iconst_0
    //   1662: aload_0
    //   1663: aastore
    //   1664: dup
    //   1665: iconst_1
    //   1666: aload_1
    //   1667: ifnonnull -> 1685
    //   1670: goto -> 1677
    //   1673: invokestatic a : (Ljava/lang/Throwable;)Ljava/lang/Throwable;
    //   1676: athrow
    //   1677: aload_1
    //   1678: goto -> 1692
    //   1681: invokestatic a : (Ljava/lang/Throwable;)Ljava/lang/Throwable;
    //   1684: athrow
    //   1685: aload_1
    //   1686: checkcast [B
    //   1689: invokevirtual clone : ()Ljava/lang/Object;
    //   1692: aastore
    //   1693: invokevirtual invoke : (Ljava/lang/Object;[Ljava/lang/Object;)Ljava/lang/Object;
    //   1696: pop
    //   1697: iload_2
    //   1698: ifne -> 1715
    //   1701: iinc #6, 1
    //   1704: iload_2
    //   1705: ifne -> 1578
    //   1708: goto -> 1715
    //   1711: invokestatic a : (Ljava/lang/Throwable;)Ljava/lang/Throwable;
    //   1714: athrow
    //   1715: getstatic burp/Zeb7.ZJ : Ljava/lang/Object;
    //   1718: checkcast java/math/BigInteger
    //   1721: invokevirtual toByteArray : ()[B
    //   1724: astore #4
    //   1726: bipush #64
    //   1728: newarray byte
    //   1730: dup
    //   1731: iconst_0
    //   1732: bipush #-128
    //   1734: bastore
    //   1735: dup
    //   1736: iconst_1
    //   1737: iconst_0
    //   1738: bastore
    //   1739: dup
    //   1740: iconst_2
    //   1741: iconst_0
    //   1742: bastore
    //   1743: dup
    //   1744: iconst_3
    //   1745: iconst_0
    //   1746: bastore
    //   1747: dup
    //   1748: iconst_4
    //   1749: iconst_0
    //   1750: bastore
    //   1751: dup
    //   1752: iconst_5
    //   1753: iconst_0
    //   1754: bastore
    //   1755: dup
    //   1756: bipush #6
    //   1758: iconst_0
    //   1759: bastore
    //   1760: dup
    //   1761: bipush #7
    //   1763: iconst_0
    //   1764: bastore
    //   1765: dup
    //   1766: bipush #8
    //   1768: iconst_0
    //   1769: bastore
    //   1770: dup
    //   1771: bipush #9
    //   1773: iconst_0
    //   1774: bastore
    //   1775: dup
    //   1776: bipush #10
    //   1778: iconst_0
    //   1779: bastore
    //   1780: dup
    //   1781: bipush #11
    //   1783: iconst_0
    //   1784: bastore
    //   1785: dup
    //   1786: bipush #12
    //   1788: iconst_0
    //   1789: bastore
    //   1790: dup
    //   1791: bipush #13
    //   1793: iconst_0
    //   1794: bastore
    //   1795: dup
    //   1796: bipush #14
    //   1798: iconst_0
    //   1799: bastore
    //   1800: dup
    //   1801: bipush #15
    //   1803: iconst_0
    //   1804: bastore
    //   1805: dup
    //   1806: bipush #16
    //   1808: iconst_0
    //   1809: bastore
    //   1810: dup
    //   1811: bipush #17
    //   1813: iconst_0
    //   1814: bastore
    //   1815: dup
    //   1816: bipush #18
    //   1818: iconst_0
    //   1819: bastore
    //   1820: dup
    //   1821: bipush #19
    //   1823: iconst_0
    //   1824: bastore
    //   1825: dup
    //   1826: bipush #20
    //   1828: iconst_0
    //   1829: bastore
    //   1830: dup
    //   1831: bipush #21
    //   1833: iconst_0
    //   1834: bastore
    //   1835: dup
    //   1836: bipush #22
    //   1838: iconst_0
    //   1839: bastore
    //   1840: dup
    //   1841: bipush #23
    //   1843: iconst_0
    //   1844: bastore
    //   1845: dup
    //   1846: bipush #24
    //   1848: iconst_0
    //   1849: bastore
    //   1850: dup
    //   1851: bipush #25
    //   1853: iconst_0
    //   1854: bastore
    //   1855: dup
    //   1856: bipush #26
    //   1858: iconst_0
    //   1859: bastore
    //   1860: dup
    //   1861: bipush #27
    //   1863: iconst_0
    //   1864: bastore
    //   1865: dup
    //   1866: bipush #28
    //   1868: iconst_0
    //   1869: bastore
    //   1870: dup
    //   1871: bipush #29
    //   1873: iconst_0
    //   1874: bastore
    //   1875: dup
    //   1876: bipush #30
    //   1878: iconst_0
    //   1879: bastore
    //   1880: dup
    //   1881: bipush #31
    //   1883: iconst_0
    //   1884: bastore
    //   1885: dup
    //   1886: bipush #32
    //   1888: iconst_0
    //   1889: bastore
    //   1890: dup
    //   1891: bipush #33
    //   1893: iconst_0
    //   1894: bastore
    //   1895: dup
    //   1896: bipush #34
    //   1898: iconst_0
    //   1899: bastore
    //   1900: dup
    //   1901: bipush #35
    //   1903: iconst_0
    //   1904: bastore
    //   1905: dup
    //   1906: bipush #36
    //   1908: iconst_0
    //   1909: bastore
    //   1910: dup
    //   1911: bipush #37
    //   1913: iconst_0
    //   1914: bastore
    //   1915: dup
    //   1916: bipush #38
    //   1918: iconst_0
    //   1919: bastore
    //   1920: dup
    //   1921: bipush #39
    //   1923: iconst_0
    //   1924: bastore
    //   1925: dup
    //   1926: bipush #40
    //   1928: iconst_0
    //   1929: bastore
    //   1930: dup
    //   1931: bipush #41
    //   1933: iconst_0
    //   1934: bastore
    //   1935: dup
    //   1936: bipush #42
    //   1938: iconst_0
    //   1939: bastore
    //   1940: dup
    //   1941: bipush #43
    //   1943: iconst_0
    //   1944: bastore
    //   1945: dup
    //   1946: bipush #44
    //   1948: iconst_0
    //   1949: bastore
    //   1950: dup
    //   1951: bipush #45
    //   1953: iconst_0
    //   1954: bastore
    //   1955: dup
    //   1956: bipush #46
    //   1958: iconst_0
    //   1959: bastore
    //   1960: dup
    //   1961: bipush #47
    //   1963: iconst_0
    //   1964: bastore
    //   1965: dup
    //   1966: bipush #48
    //   1968: iconst_0
    //   1969: bastore
    //   1970: dup
    //   1971: bipush #49
    //   1973: iconst_0
    //   1974: bastore
    //   1975: dup
    //   1976: bipush #50
    //   1978: iconst_0
    //   1979: bastore
    //   1980: dup
    //   1981: bipush #51
    //   1983: iconst_0
    //   1984: bastore
    //   1985: dup
    //   1986: bipush #52
    //   1988: iconst_0
    //   1989: bastore
    //   1990: dup
    //   1991: bipush #53
    //   1993: iconst_0
    //   1994: bastore
    //   1995: dup
    //   1996: bipush #54
    //   1998: iconst_0
    //   1999: bastore
    //   2000: dup
    //   2001: bipush #55
    //   2003: iconst_0
    //   2004: bastore
    //   2005: dup
    //   2006: bipush #56
    //   2008: iconst_0
    //   2009: bastore
    //   2010: dup
    //   2011: bipush #57
    //   2013: iconst_0
    //   2014: bastore
    //   2015: dup
    //   2016: bipush #58
    //   2018: iconst_0
    //   2019: bastore
    //   2020: dup
    //   2021: bipush #59
    //   2023: iconst_0
    //   2024: bastore
    //   2025: dup
    //   2026: bipush #60
    //   2028: iconst_0
    //   2029: bastore
    //   2030: dup
    //   2031: bipush #61
    //   2033: iconst_0
    //   2034: bastore
    //   2035: dup
    //   2036: bipush #62
    //   2038: iconst_0
    //   2039: bastore
    //   2040: dup
    //   2041: bipush #63
    //   2043: iconst_0
    //   2044: bastore
    //   2045: astore #6
    //   2047: bipush #64
    //   2049: newarray int
    //   2051: dup
    //   2052: iconst_0
    //   2053: ldc 1116352408
    //   2055: iastore
    //   2056: dup
    //   2057: iconst_1
    //   2058: ldc 1899447441
    //   2060: iastore
    //   2061: dup
    //   2062: iconst_2
    //   2063: ldc -1245643825
    //   2065: iastore
    //   2066: dup
    //   2067: iconst_3
    //   2068: ldc -373957723
    //   2070: iastore
    //   2071: dup
    //   2072: iconst_4
    //   2073: ldc 961987163
    //   2075: iastore
    //   2076: dup
    //   2077: iconst_5
    //   2078: ldc 1508970993
    //   2080: iastore
    //   2081: dup
    //   2082: bipush #6
    //   2084: ldc -1841331548
    //   2086: iastore
    //   2087: dup
    //   2088: bipush #7
    //   2090: ldc -1424204075
    //   2092: iastore
    //   2093: dup
    //   2094: bipush #8
    //   2096: ldc -670586216
    //   2098: iastore
    //   2099: dup
    //   2100: bipush #9
    //   2102: ldc 310598401
    //   2104: iastore
    //   2105: dup
    //   2106: bipush #10
    //   2108: ldc 607225278
    //   2110: iastore
    //   2111: dup
    //   2112: bipush #11
    //   2114: ldc 1426881987
    //   2116: iastore
    //   2117: dup
    //   2118: bipush #12
    //   2120: ldc 1925078388
    //   2122: iastore
    //   2123: dup
    //   2124: bipush #13
    //   2126: ldc -2132889090
    //   2128: iastore
    //   2129: dup
    //   2130: bipush #14
    //   2132: ldc -1680079193
    //   2134: iastore
    //   2135: dup
    //   2136: bipush #15
    //   2138: ldc -1046744716
    //   2140: iastore
    //   2141: dup
    //   2142: bipush #16
    //   2144: ldc -459576895
    //   2146: iastore
    //   2147: dup
    //   2148: bipush #17
    //   2150: ldc -272742522
    //   2152: iastore
    //   2153: dup
    //   2154: bipush #18
    //   2156: ldc 264347078
    //   2158: iastore
    //   2159: dup
    //   2160: bipush #19
    //   2162: ldc 604807628
    //   2164: iastore
    //   2165: dup
    //   2166: bipush #20
    //   2168: ldc 770255983
    //   2170: iastore
    //   2171: dup
    //   2172: bipush #21
    //   2174: ldc 1249150122
    //   2176: iastore
    //   2177: dup
    //   2178: bipush #22
    //   2180: ldc 1555081692
    //   2182: iastore
    //   2183: dup
    //   2184: bipush #23
    //   2186: ldc 1996064986
    //   2188: iastore
    //   2189: dup
    //   2190: bipush #24
    //   2192: ldc -1740746414
    //   2194: iastore
    //   2195: dup
    //   2196: bipush #25
    //   2198: ldc -1473132947
    //   2200: iastore
    //   2201: dup
    //   2202: bipush #26
    //   2204: ldc -1341970488
    //   2206: iastore
    //   2207: dup
    //   2208: bipush #27
    //   2210: ldc -1084653625
    //   2212: iastore
    //   2213: dup
    //   2214: bipush #28
    //   2216: ldc -958395405
    //   2218: iastore
    //   2219: dup
    //   2220: bipush #29
    //   2222: ldc -710438585
    //   2224: iastore
    //   2225: dup
    //   2226: bipush #30
    //   2228: ldc 113926993
    //   2230: iastore
    //   2231: dup
    //   2232: bipush #31
    //   2234: ldc 338241895
    //   2236: iastore
    //   2237: dup
    //   2238: bipush #32
    //   2240: ldc 666307205
    //   2242: iastore
    //   2243: dup
    //   2244: bipush #33
    //   2246: ldc 773529912
    //   2248: iastore
    //   2249: dup
    //   2250: bipush #34
    //   2252: ldc 1294757372
    //   2254: iastore
    //   2255: dup
    //   2256: bipush #35
    //   2258: ldc 1396182291
    //   2260: iastore
    //   2261: dup
    //   2262: bipush #36
    //   2264: ldc 1695183700
    //   2266: iastore
    //   2267: dup
    //   2268: bipush #37
    //   2270: ldc 1986661051
    //   2272: iastore
    //   2273: dup
    //   2274: bipush #38
    //   2276: ldc -2117940946
    //   2278: iastore
    //   2279: dup
    //   2280: bipush #39
    //   2282: ldc -1838011259
    //   2284: iastore
    //   2285: dup
    //   2286: bipush #40
    //   2288: ldc -1564481375
    //   2290: iastore
    //   2291: dup
    //   2292: bipush #41
    //   2294: ldc -1474664885
    //   2296: iastore
    //   2297: dup
    //   2298: bipush #42
    //   2300: ldc -1035236496
    //   2302: iastore
    //   2303: dup
    //   2304: bipush #43
    //   2306: ldc -949202525
    //   2308: iastore
    //   2309: dup
    //   2310: bipush #44
    //   2312: ldc -778901479
    //   2314: iastore
    //   2315: dup
    //   2316: bipush #45
    //   2318: ldc -694614492
    //   2320: iastore
    //   2321: dup
    //   2322: bipush #46
    //   2324: ldc -200395387
    //   2326: iastore
    //   2327: dup
    //   2328: bipush #47
    //   2330: ldc 275423344
    //   2332: iastore
    //   2333: dup
    //   2334: bipush #48
    //   2336: ldc 430227734
    //   2338: iastore
    //   2339: dup
    //   2340: bipush #49
    //   2342: ldc 506948616
    //   2344: iastore
    //   2345: dup
    //   2346: bipush #50
    //   2348: ldc 659060556
    //   2350: iastore
    //   2351: dup
    //   2352: bipush #51
    //   2354: ldc 883997877
    //   2356: iastore
    //   2357: dup
    //   2358: bipush #52
    //   2360: ldc 958139571
    //   2362: iastore
    //   2363: dup
    //   2364: bipush #53
    //   2366: ldc 1322822218
    //   2368: iastore
    //   2369: dup
    //   2370: bipush #54
    //   2372: ldc 1537002063
    //   2374: iastore
    //   2375: dup
    //   2376: bipush #55
    //   2378: ldc 1747873779
    //   2380: iastore
    //   2381: dup
    //   2382: bipush #56
    //   2384: ldc 1955562222
    //   2386: iastore
    //   2387: dup
    //   2388: bipush #57
    //   2390: ldc 2024104815
    //   2392: iastore
    //   2393: dup
    //   2394: bipush #58
    //   2396: ldc -2067236844
    //   2398: iastore
    //   2399: dup
    //   2400: bipush #59
    //   2402: ldc -1933114872
    //   2404: iastore
    //   2405: dup
    //   2406: bipush #60
    //   2408: ldc -1866530822
    //   2410: iastore
    //   2411: dup
    //   2412: bipush #61
    //   2414: ldc -1538233109
    //   2416: iastore
    //   2417: dup
    //   2418: bipush #62
    //   2420: ldc -1090935817
    //   2422: iastore
    //   2423: dup
    //   2424: bipush #63
    //   2426: ldc -965641998
    //   2428: iastore
    //   2429: astore #7
    //   2431: iconst_2
    //   2432: newarray int
    //   2434: dup
    //   2435: iconst_0
    //   2436: iconst_0
    //   2437: iastore
    //   2438: dup
    //   2439: iconst_1
    //   2440: iconst_0
    //   2441: iastore
    //   2442: astore #8
    //   2444: bipush #8
    //   2446: newarray int
    //   2448: dup
    //   2449: iconst_0
    //   2450: ldc 1779033703
    //   2452: iastore
    //   2453: dup
    //   2454: iconst_1
    //   2455: ldc -1150833019
    //   2457: iastore
    //   2458: dup
    //   2459: iconst_2
    //   2460: ldc 1013904242
    //   2462: iastore
    //   2463: dup
    //   2464: iconst_3
    //   2465: ldc -1521486534
    //   2467: iastore
    //   2468: dup
    //   2469: iconst_4
    //   2470: ldc 1359893119
    //   2472: iastore
    //   2473: dup
    //   2474: iconst_5
    //   2475: ldc -1694144372
    //   2477: iastore
    //   2478: dup
    //   2479: bipush #6
    //   2481: ldc 528734635
    //   2483: iastore
    //   2484: dup
    //   2485: bipush #7
    //   2487: ldc 1541459225
    //   2489: iastore
    //   2490: astore #9
    //   2492: bipush #64
    //   2494: newarray byte
    //   2496: astore #10
    //   2498: bipush #64
    //   2500: newarray byte
    //   2502: astore #11
    //   2504: aload #4
    //   2506: arraylength
    //   2507: istore #12
    //   2509: aload #8
    //   2511: iconst_0
    //   2512: iaload
    //   2513: bipush #63
    //   2515: iand
    //   2516: istore #13
    //   2518: aload #8
    //   2520: iconst_0
    //   2521: dup2
    //   2522: iaload
    //   2523: iload #12
    //   2525: iadd
    //   2526: iastore
    //   2527: aload #8
    //   2529: iconst_0
    //   2530: dup2
    //   2531: iaload
    //   2532: iconst_m1
    //   2533: iand
    //   2534: iastore
    //   2535: aload #8
    //   2537: iconst_0
    //   2538: iaload
    //   2539: iload #12
    //   2541: if_icmpge -> 2559
    //   2544: aload #8
    //   2546: iconst_1
    //   2547: dup2
    //   2548: iaload
    //   2549: iconst_1
    //   2550: iadd
    //   2551: iastore
    //   2552: goto -> 2559
    //   2555: invokestatic a : (Ljava/lang/Throwable;)Ljava/lang/Throwable;
    //   2558: athrow
    //   2559: iconst_0
    //   2560: istore #14
    //   2562: iload #12
    //   2564: bipush #64
    //   2566: if_icmplt -> 3176
    //   2569: iconst_0
    //   2570: istore #15
    //   2572: iload #15
    //   2574: bipush #64
    //   2576: if_icmpge -> 2599
    //   2579: aload #11
    //   2581: iload #15
    //   2583: aload #4
    //   2585: iload #14
    //   2587: iload #15
    //   2589: iadd
    //   2590: baload
    //   2591: bastore
    //   2592: iinc #15, 1
    //   2595: iload_2
    //   2596: ifne -> 2572
    //   2599: bipush #64
    //   2601: newarray int
    //   2603: astore #15
    //   2605: bipush #8
    //   2607: newarray int
    //   2609: astore #16
    //   2611: iconst_0
    //   2612: istore #17
    //   2614: iload #17
    //   2616: bipush #8
    //   2618: if_icmpge -> 2638
    //   2621: aload #16
    //   2623: iload #17
    //   2625: aload #9
    //   2627: iload #17
    //   2629: iaload
    //   2630: iastore
    //   2631: iinc #17, 1
    //   2634: iload_2
    //   2635: ifne -> 2614
    //   2638: iconst_0
    //   2639: istore #17
    //   2641: iload #17
    //   2643: bipush #64
    //   2645: if_icmpge -> 3136
    //   2648: iload #17
    //   2650: bipush #16
    //   2652: if_icmpge -> 2733
    //   2655: aload #15
    //   2657: iload #17
    //   2659: aload #11
    //   2661: iconst_4
    //   2662: iload #17
    //   2664: imul
    //   2665: baload
    //   2666: sipush #255
    //   2669: iand
    //   2670: bipush #24
    //   2672: ishl
    //   2673: aload #11
    //   2675: iconst_4
    //   2676: iload #17
    //   2678: imul
    //   2679: iconst_1
    //   2680: iadd
    //   2681: baload
    //   2682: sipush #255
    //   2685: iand
    //   2686: bipush #16
    //   2688: ishl
    //   2689: ior
    //   2690: aload #11
    //   2692: iconst_4
    //   2693: iload #17
    //   2695: imul
    //   2696: iconst_2
    //   2697: iadd
    //   2698: baload
    //   2699: sipush #255
    //   2702: iand
    //   2703: bipush #8
    //   2705: ishl
    //   2706: ior
    //   2707: aload #11
    //   2709: iconst_4
    //   2710: iload #17
    //   2712: imul
    //   2713: iconst_3
    //   2714: iadd
    //   2715: baload
    //   2716: sipush #255
    //   2719: iand
    //   2720: ior
    //   2721: iastore
    //   2722: iload_2
    //   2723: ifne -> 2876
    //   2726: goto -> 2733
    //   2729: invokestatic a : (Ljava/lang/Throwable;)Ljava/lang/Throwable;
    //   2732: athrow
    //   2733: aload #15
    //   2735: iload #17
    //   2737: aload #15
    //   2739: iload #17
    //   2741: iconst_2
    //   2742: isub
    //   2743: iaload
    //   2744: bipush #17
    //   2746: iushr
    //   2747: aload #15
    //   2749: iload #17
    //   2751: iconst_2
    //   2752: isub
    //   2753: iaload
    //   2754: bipush #15
    //   2756: ishl
    //   2757: ior
    //   2758: aload #15
    //   2760: iload #17
    //   2762: iconst_2
    //   2763: isub
    //   2764: iaload
    //   2765: bipush #19
    //   2767: iushr
    //   2768: aload #15
    //   2770: iload #17
    //   2772: iconst_2
    //   2773: isub
    //   2774: iaload
    //   2775: bipush #13
    //   2777: ishl
    //   2778: ior
    //   2779: ixor
    //   2780: aload #15
    //   2782: iload #17
    //   2784: iconst_2
    //   2785: isub
    //   2786: iaload
    //   2787: bipush #10
    //   2789: iushr
    //   2790: ixor
    //   2791: aload #15
    //   2793: iload #17
    //   2795: bipush #7
    //   2797: isub
    //   2798: iaload
    //   2799: iadd
    //   2800: aload #15
    //   2802: iload #17
    //   2804: bipush #15
    //   2806: isub
    //   2807: iaload
    //   2808: bipush #7
    //   2810: iushr
    //   2811: aload #15
    //   2813: iload #17
    //   2815: bipush #15
    //   2817: isub
    //   2818: iaload
    //   2819: bipush #25
    //   2821: ishl
    //   2822: ior
    //   2823: aload #15
    //   2825: iload #17
    //   2827: bipush #15
    //   2829: isub
    //   2830: iaload
    //   2831: bipush #18
    //   2833: iushr
    //   2834: aload #15
    //   2836: iload #17
    //   2838: bipush #15
    //   2840: isub
    //   2841: iaload
    //   2842: bipush #14
    //   2844: ishl
    //   2845: ior
    //   2846: ixor
    //   2847: aload #15
    //   2849: iload #17
    //   2851: bipush #15
    //   2853: isub
    //   2854: iaload
    //   2855: iconst_3
    //   2856: iushr
    //   2857: ixor
    //   2858: iadd
    //   2859: aload #15
    //   2861: iload #17
    //   2863: bipush #16
    //   2865: isub
    //   2866: iaload
    //   2867: iadd
    //   2868: iastore
    //   2869: goto -> 2876
    //   2872: invokestatic a : (Ljava/lang/Throwable;)Ljava/lang/Throwable;
    //   2875: athrow
    //   2876: aload #16
    //   2878: bipush #7
    //   2880: iaload
    //   2881: aload #16
    //   2883: iconst_4
    //   2884: iaload
    //   2885: bipush #6
    //   2887: iushr
    //   2888: aload #16
    //   2890: iconst_4
    //   2891: iaload
    //   2892: bipush #26
    //   2894: ishl
    //   2895: ior
    //   2896: aload #16
    //   2898: iconst_4
    //   2899: iaload
    //   2900: bipush #11
    //   2902: iushr
    //   2903: aload #16
    //   2905: iconst_4
    //   2906: iaload
    //   2907: bipush #21
    //   2909: ishl
    //   2910: ior
    //   2911: ixor
    //   2912: aload #16
    //   2914: iconst_4
    //   2915: iaload
    //   2916: bipush #25
    //   2918: iushr
    //   2919: aload #16
    //   2921: iconst_4
    //   2922: iaload
    //   2923: bipush #7
    //   2925: ishl
    //   2926: ior
    //   2927: ixor
    //   2928: iadd
    //   2929: aload #16
    //   2931: bipush #6
    //   2933: iaload
    //   2934: aload #16
    //   2936: iconst_4
    //   2937: iaload
    //   2938: aload #16
    //   2940: iconst_5
    //   2941: iaload
    //   2942: aload #16
    //   2944: bipush #6
    //   2946: iaload
    //   2947: ixor
    //   2948: iand
    //   2949: ixor
    //   2950: iadd
    //   2951: aload #7
    //   2953: iload #17
    //   2955: iaload
    //   2956: iadd
    //   2957: aload #15
    //   2959: iload #17
    //   2961: iaload
    //   2962: iadd
    //   2963: istore #18
    //   2965: aload #16
    //   2967: iconst_0
    //   2968: iaload
    //   2969: iconst_2
    //   2970: iushr
    //   2971: aload #16
    //   2973: iconst_0
    //   2974: iaload
    //   2975: bipush #30
    //   2977: ishl
    //   2978: ior
    //   2979: aload #16
    //   2981: iconst_0
    //   2982: iaload
    //   2983: bipush #13
    //   2985: iushr
    //   2986: aload #16
    //   2988: iconst_0
    //   2989: iaload
    //   2990: bipush #19
    //   2992: ishl
    //   2993: ior
    //   2994: ixor
    //   2995: aload #16
    //   2997: iconst_0
    //   2998: iaload
    //   2999: bipush #22
    //   3001: iushr
    //   3002: aload #16
    //   3004: iconst_0
    //   3005: iaload
    //   3006: bipush #10
    //   3008: ishl
    //   3009: ior
    //   3010: ixor
    //   3011: aload #16
    //   3013: iconst_0
    //   3014: iaload
    //   3015: aload #16
    //   3017: iconst_1
    //   3018: iaload
    //   3019: iand
    //   3020: aload #16
    //   3022: iconst_2
    //   3023: iaload
    //   3024: aload #16
    //   3026: iconst_0
    //   3027: iaload
    //   3028: aload #16
    //   3030: iconst_1
    //   3031: iaload
    //   3032: ior
    //   3033: iand
    //   3034: ior
    //   3035: iadd
    //   3036: istore #19
    //   3038: aload #16
    //   3040: iconst_3
    //   3041: dup2
    //   3042: iaload
    //   3043: iload #18
    //   3045: iadd
    //   3046: iastore
    //   3047: aload #16
    //   3049: bipush #7
    //   3051: iload #18
    //   3053: iload #19
    //   3055: iadd
    //   3056: iastore
    //   3057: aload #16
    //   3059: bipush #7
    //   3061: iaload
    //   3062: istore #18
    //   3064: aload #16
    //   3066: bipush #7
    //   3068: aload #16
    //   3070: bipush #6
    //   3072: iaload
    //   3073: iastore
    //   3074: aload #16
    //   3076: bipush #6
    //   3078: aload #16
    //   3080: iconst_5
    //   3081: iaload
    //   3082: iastore
    //   3083: aload #16
    //   3085: iconst_5
    //   3086: aload #16
    //   3088: iconst_4
    //   3089: iaload
    //   3090: iastore
    //   3091: aload #16
    //   3093: iconst_4
    //   3094: aload #16
    //   3096: iconst_3
    //   3097: iaload
    //   3098: iastore
    //   3099: aload #16
    //   3101: iconst_3
    //   3102: aload #16
    //   3104: iconst_2
    //   3105: iaload
    //   3106: iastore
    //   3107: aload #16
    //   3109: iconst_2
    //   3110: aload #16
    //   3112: iconst_1
    //   3113: iaload
    //   3114: iastore
    //   3115: aload #16
    //   3117: iconst_1
    //   3118: aload #16
    //   3120: iconst_0
    //   3121: iaload
    //   3122: iastore
    //   3123: aload #16
    //   3125: iconst_0
    //   3126: iload #18
    //   3128: iastore
    //   3129: iinc #17, 1
    //   3132: iload_2
    //   3133: ifne -> 2641
    //   3136: iconst_0
    //   3137: istore #17
    //   3139: iload #17
    //   3141: bipush #8
    //   3143: if_icmpge -> 3166
    //   3146: aload #9
    //   3148: iload #17
    //   3150: dup2
    //   3151: iaload
    //   3152: aload #16
    //   3154: iload #17
    //   3156: iaload
    //   3157: iadd
    //   3158: iastore
    //   3159: iinc #17, 1
    //   3162: iload_2
    //   3163: ifne -> 3139
    //   3166: iinc #14, 64
    //   3169: iinc #12, -64
    //   3172: iload_2
    //   3173: ifne -> 2562
    //   3176: iload #12
    //   3178: ifle -> 3214
    //   3181: iconst_0
    //   3182: istore #15
    //   3184: iload #15
    //   3186: iload #12
    //   3188: if_icmpge -> 3214
    //   3191: aload #10
    //   3193: iload #13
    //   3195: iload #15
    //   3197: iadd
    //   3198: aload #4
    //   3200: iload #14
    //   3202: iload #15
    //   3204: iadd
    //   3205: baload
    //   3206: bastore
    //   3207: iinc #15, 1
    //   3210: iload_2
    //   3211: ifne -> 3184
    //   3214: aload #8
    //   3216: iconst_0
    //   3217: iaload
    //   3218: bipush #29
    //   3220: iushr
    //   3221: aload #8
    //   3223: iconst_1
    //   3224: iaload
    //   3225: iconst_3
    //   3226: ishl
    //   3227: ior
    //   3228: istore #15
    //   3230: aload #8
    //   3232: iconst_0
    //   3233: iaload
    //   3234: iconst_3
    //   3235: ishl
    //   3236: istore #16
    //   3238: aload #8
    //   3240: iconst_0
    //   3241: iaload
    //   3242: bipush #63
    //   3244: iand
    //   3245: istore #17
    //   3247: iload #17
    //   3249: bipush #56
    //   3251: if_icmpge -> 3266
    //   3254: bipush #56
    //   3256: iload #17
    //   3258: isub
    //   3259: goto -> 3271
    //   3262: invokestatic a : (Ljava/lang/Throwable;)Ljava/lang/Throwable;
    //   3265: athrow
    //   3266: bipush #120
    //   3268: iload #17
    //   3270: isub
    //   3271: istore #18
    //   3273: aload #8
    //   3275: iconst_0
    //   3276: iaload
    //   3277: bipush #63
    //   3279: iand
    //   3280: istore #13
    //   3282: bipush #64
    //   3284: iload #13
    //   3286: isub
    //   3287: istore #19
    //   3289: aload #8
    //   3291: iconst_0
    //   3292: dup2
    //   3293: iaload
    //   3294: iload #18
    //   3296: iadd
    //   3297: iastore
    //   3298: aload #8
    //   3300: iconst_0
    //   3301: dup2
    //   3302: iaload
    //   3303: iconst_m1
    //   3304: iand
    //   3305: iastore
    //   3306: aload #8
    //   3308: iconst_0
    //   3309: iaload
    //   3310: iload #18
    //   3312: if_icmpge -> 3330
    //   3315: aload #8
    //   3317: iconst_1
    //   3318: dup2
    //   3319: iaload
    //   3320: iconst_1
    //   3321: iadd
    //   3322: iastore
    //   3323: goto -> 3330
    //   3326: invokestatic a : (Ljava/lang/Throwable;)Ljava/lang/Throwable;
    //   3329: athrow
    //   3330: iconst_0
    //   3331: istore #14
    //   3333: iload #13
    //   3335: ifle -> 3966
    //   3338: iload #18
    //   3340: iload #19
    //   3342: if_icmplt -> 3966
    //   3345: goto -> 3352
    //   3348: invokestatic a : (Ljava/lang/Throwable;)Ljava/lang/Throwable;
    //   3351: athrow
    //   3352: iconst_0
    //   3353: istore #20
    //   3355: iload #20
    //   3357: iload #19
    //   3359: if_icmpge -> 3382
    //   3362: aload #10
    //   3364: iload #13
    //   3366: iload #20
    //   3368: iadd
    //   3369: aload #6
    //   3371: iload #20
    //   3373: baload
    //   3374: bastore
    //   3375: iinc #20, 1
    //   3378: iload_2
    //   3379: ifne -> 3355
    //   3382: bipush #64
    //   3384: newarray int
    //   3386: astore #20
    //   3388: bipush #8
    //   3390: newarray int
    //   3392: astore #21
    //   3394: iconst_0
    //   3395: istore #22
    //   3397: iload #22
    //   3399: bipush #8
    //   3401: if_icmpge -> 3421
    //   3404: aload #21
    //   3406: iload #22
    //   3408: aload #9
    //   3410: iload #22
    //   3412: iaload
    //   3413: iastore
    //   3414: iinc #22, 1
    //   3417: iload_2
    //   3418: ifne -> 3397
    //   3421: iconst_0
    //   3422: istore #22
    //   3424: iload #22
    //   3426: bipush #64
    //   3428: if_icmpge -> 3919
    //   3431: iload #22
    //   3433: bipush #16
    //   3435: if_icmpge -> 3516
    //   3438: aload #20
    //   3440: iload #22
    //   3442: aload #10
    //   3444: iconst_4
    //   3445: iload #22
    //   3447: imul
    //   3448: baload
    //   3449: sipush #255
    //   3452: iand
    //   3453: bipush #24
    //   3455: ishl
    //   3456: aload #10
    //   3458: iconst_4
    //   3459: iload #22
    //   3461: imul
    //   3462: iconst_1
    //   3463: iadd
    //   3464: baload
    //   3465: sipush #255
    //   3468: iand
    //   3469: bipush #16
    //   3471: ishl
    //   3472: ior
    //   3473: aload #10
    //   3475: iconst_4
    //   3476: iload #22
    //   3478: imul
    //   3479: iconst_2
    //   3480: iadd
    //   3481: baload
    //   3482: sipush #255
    //   3485: iand
    //   3486: bipush #8
    //   3488: ishl
    //   3489: ior
    //   3490: aload #10
    //   3492: iconst_4
    //   3493: iload #22
    //   3495: imul
    //   3496: iconst_3
    //   3497: iadd
    //   3498: baload
    //   3499: sipush #255
    //   3502: iand
    //   3503: ior
    //   3504: iastore
    //   3505: iload_2
    //   3506: ifne -> 3659
    //   3509: goto -> 3516
    //   3512: invokestatic a : (Ljava/lang/Throwable;)Ljava/lang/Throwable;
    //   3515: athrow
    //   3516: aload #20
    //   3518: iload #22
    //   3520: aload #20
    //   3522: iload #22
    //   3524: iconst_2
    //   3525: isub
    //   3526: iaload
    //   3527: bipush #17
    //   3529: iushr
    //   3530: aload #20
    //   3532: iload #22
    //   3534: iconst_2
    //   3535: isub
    //   3536: iaload
    //   3537: bipush #15
    //   3539: ishl
    //   3540: ior
    //   3541: aload #20
    //   3543: iload #22
    //   3545: iconst_2
    //   3546: isub
    //   3547: iaload
    //   3548: bipush #19
    //   3550: iushr
    //   3551: aload #20
    //   3553: iload #22
    //   3555: iconst_2
    //   3556: isub
    //   3557: iaload
    //   3558: bipush #13
    //   3560: ishl
    //   3561: ior
    //   3562: ixor
    //   3563: aload #20
    //   3565: iload #22
    //   3567: iconst_2
    //   3568: isub
    //   3569: iaload
    //   3570: bipush #10
    //   3572: iushr
    //   3573: ixor
    //   3574: aload #20
    //   3576: iload #22
    //   3578: bipush #7
    //   3580: isub
    //   3581: iaload
    //   3582: iadd
    //   3583: aload #20
    //   3585: iload #22
    //   3587: bipush #15
    //   3589: isub
    //   3590: iaload
    //   3591: bipush #7
    //   3593: iushr
    //   3594: aload #20
    //   3596: iload #22
    //   3598: bipush #15
    //   3600: isub
    //   3601: iaload
    //   3602: bipush #25
    //   3604: ishl
    //   3605: ior
    //   3606: aload #20
    //   3608: iload #22
    //   3610: bipush #15
    //   3612: isub
    //   3613: iaload
    //   3614: bipush #18
    //   3616: iushr
    //   3617: aload #20
    //   3619: iload #22
    //   3621: bipush #15
    //   3623: isub
    //   3624: iaload
    //   3625: bipush #14
    //   3627: ishl
    //   3628: ior
    //   3629: ixor
    //   3630: aload #20
    //   3632: iload #22
    //   3634: bipush #15
    //   3636: isub
    //   3637: iaload
    //   3638: iconst_3
    //   3639: iushr
    //   3640: ixor
    //   3641: iadd
    //   3642: aload #20
    //   3644: iload #22
    //   3646: bipush #16
    //   3648: isub
    //   3649: iaload
    //   3650: iadd
    //   3651: iastore
    //   3652: goto -> 3659
    //   3655: invokestatic a : (Ljava/lang/Throwable;)Ljava/lang/Throwable;
    //   3658: athrow
    //   3659: aload #21
    //   3661: bipush #7
    //   3663: iaload
    //   3664: aload #21
    //   3666: iconst_4
    //   3667: iaload
    //   3668: bipush #6
    //   3670: iushr
    //   3671: aload #21
    //   3673: iconst_4
    //   3674: iaload
    //   3675: bipush #26
    //   3677: ishl
    //   3678: ior
    //   3679: aload #21
    //   3681: iconst_4
    //   3682: iaload
    //   3683: bipush #11
    //   3685: iushr
    //   3686: aload #21
    //   3688: iconst_4
    //   3689: iaload
    //   3690: bipush #21
    //   3692: ishl
    //   3693: ior
    //   3694: ixor
    //   3695: aload #21
    //   3697: iconst_4
    //   3698: iaload
    //   3699: bipush #25
    //   3701: iushr
    //   3702: aload #21
    //   3704: iconst_4
    //   3705: iaload
    //   3706: bipush #7
    //   3708: ishl
    //   3709: ior
    //   3710: ixor
    //   3711: iadd
    //   3712: aload #21
    //   3714: bipush #6
    //   3716: iaload
    //   3717: aload #21
    //   3719: iconst_4
    //   3720: iaload
    //   3721: aload #21
    //   3723: iconst_5
    //   3724: iaload
    //   3725: aload #21
    //   3727: bipush #6
    //   3729: iaload
    //   3730: ixor
    //   3731: iand
    //   3732: ixor
    //   3733: iadd
    //   3734: aload #7
    //   3736: iload #22
    //   3738: iaload
    //   3739: iadd
    //   3740: aload #20
    //   3742: iload #22
    //   3744: iaload
    //   3745: iadd
    //   3746: istore #23
    //   3748: aload #21
    //   3750: iconst_0
    //   3751: iaload
    //   3752: iconst_2
    //   3753: iushr
    //   3754: aload #21
    //   3756: iconst_0
    //   3757: iaload
    //   3758: bipush #30
    //   3760: ishl
    //   3761: ior
    //   3762: aload #21
    //   3764: iconst_0
    //   3765: iaload
    //   3766: bipush #13
    //   3768: iushr
    //   3769: aload #21
    //   3771: iconst_0
    //   3772: iaload
    //   3773: bipush #19
    //   3775: ishl
    //   3776: ior
    //   3777: ixor
    //   3778: aload #21
    //   3780: iconst_0
    //   3781: iaload
    //   3782: bipush #22
    //   3784: iushr
    //   3785: aload #21
    //   3787: iconst_0
    //   3788: iaload
    //   3789: bipush #10
    //   3791: ishl
    //   3792: ior
    //   3793: ixor
    //   3794: aload #21
    //   3796: iconst_0
    //   3797: iaload
    //   3798: aload #21
    //   3800: iconst_1
    //   3801: iaload
    //   3802: iand
    //   3803: aload #21
    //   3805: iconst_2
    //   3806: iaload
    //   3807: aload #21
    //   3809: iconst_0
    //   3810: iaload
    //   3811: aload #21
    //   3813: iconst_1
    //   3814: iaload
    //   3815: ior
    //   3816: iand
    //   3817: ior
    //   3818: iadd
    //   3819: istore #24
    //   3821: aload #21
    //   3823: iconst_3
    //   3824: dup2
    //   3825: iaload
    //   3826: iload #23
    //   3828: iadd
    //   3829: iastore
    //   3830: aload #21
    //   3832: bipush #7
    //   3834: iload #23
    //   3836: iload #24
    //   3838: iadd
    //   3839: iastore
    //   3840: aload #21
    //   3842: bipush #7
    //   3844: iaload
    //   3845: istore #23
    //   3847: aload #21
    //   3849: bipush #7
    //   3851: aload #21
    //   3853: bipush #6
    //   3855: iaload
    //   3856: iastore
    //   3857: aload #21
    //   3859: bipush #6
    //   3861: aload #21
    //   3863: iconst_5
    //   3864: iaload
    //   3865: iastore
    //   3866: aload #21
    //   3868: iconst_5
    //   3869: aload #21
    //   3871: iconst_4
    //   3872: iaload
    //   3873: iastore
    //   3874: aload #21
    //   3876: iconst_4
    //   3877: aload #21
    //   3879: iconst_3
    //   3880: iaload
    //   3881: iastore
    //   3882: aload #21
    //   3884: iconst_3
    //   3885: aload #21
    //   3887: iconst_2
    //   3888: iaload
    //   3889: iastore
    //   3890: aload #21
    //   3892: iconst_2
    //   3893: aload #21
    //   3895: iconst_1
    //   3896: iaload
    //   3897: iastore
    //   3898: aload #21
    //   3900: iconst_1
    //   3901: aload #21
    //   3903: iconst_0
    //   3904: iaload
    //   3905: iastore
    //   3906: aload #21
    //   3908: iconst_0
    //   3909: iload #23
    //   3911: iastore
    //   3912: iinc #22, 1
    //   3915: iload_2
    //   3916: ifne -> 3424
    //   3919: iconst_0
    //   3920: istore #22
    //   3922: iload #22
    //   3924: bipush #8
    //   3926: if_icmpge -> 3949
    //   3929: aload #9
    //   3931: iload #22
    //   3933: dup2
    //   3934: iaload
    //   3935: aload #21
    //   3937: iload #22
    //   3939: iaload
    //   3940: iadd
    //   3941: iastore
    //   3942: iinc #22, 1
    //   3945: iload_2
    //   3946: ifne -> 3922
    //   3949: iload #14
    //   3951: iload #19
    //   3953: iadd
    //   3954: istore #14
    //   3956: iload #18
    //   3958: iload #19
    //   3960: isub
    //   3961: istore #18
    //   3963: iconst_0
    //   3964: istore #13
    //   3966: iload #18
    //   3968: bipush #64
    //   3970: if_icmplt -> 4580
    //   3973: iconst_0
    //   3974: istore #20
    //   3976: iload #20
    //   3978: bipush #64
    //   3980: if_icmpge -> 4003
    //   3983: aload #11
    //   3985: iload #20
    //   3987: aload #6
    //   3989: iload #14
    //   3991: iload #20
    //   3993: iadd
    //   3994: baload
    //   3995: bastore
    //   3996: iinc #20, 1
    //   3999: iload_2
    //   4000: ifne -> 3976
    //   4003: bipush #64
    //   4005: newarray int
    //   4007: astore #20
    //   4009: bipush #8
    //   4011: newarray int
    //   4013: astore #21
    //   4015: iconst_0
    //   4016: istore #22
    //   4018: iload #22
    //   4020: bipush #8
    //   4022: if_icmpge -> 4042
    //   4025: aload #21
    //   4027: iload #22
    //   4029: aload #9
    //   4031: iload #22
    //   4033: iaload
    //   4034: iastore
    //   4035: iinc #22, 1
    //   4038: iload_2
    //   4039: ifne -> 4018
    //   4042: iconst_0
    //   4043: istore #22
    //   4045: iload #22
    //   4047: bipush #64
    //   4049: if_icmpge -> 4540
    //   4052: iload #22
    //   4054: bipush #16
    //   4056: if_icmpge -> 4137
    //   4059: aload #20
    //   4061: iload #22
    //   4063: aload #11
    //   4065: iconst_4
    //   4066: iload #22
    //   4068: imul
    //   4069: baload
    //   4070: sipush #255
    //   4073: iand
    //   4074: bipush #24
    //   4076: ishl
    //   4077: aload #11
    //   4079: iconst_4
    //   4080: iload #22
    //   4082: imul
    //   4083: iconst_1
    //   4084: iadd
    //   4085: baload
    //   4086: sipush #255
    //   4089: iand
    //   4090: bipush #16
    //   4092: ishl
    //   4093: ior
    //   4094: aload #11
    //   4096: iconst_4
    //   4097: iload #22
    //   4099: imul
    //   4100: iconst_2
    //   4101: iadd
    //   4102: baload
    //   4103: sipush #255
    //   4106: iand
    //   4107: bipush #8
    //   4109: ishl
    //   4110: ior
    //   4111: aload #11
    //   4113: iconst_4
    //   4114: iload #22
    //   4116: imul
    //   4117: iconst_3
    //   4118: iadd
    //   4119: baload
    //   4120: sipush #255
    //   4123: iand
    //   4124: ior
    //   4125: iastore
    //   4126: iload_2
    //   4127: ifne -> 4280
    //   4130: goto -> 4137
    //   4133: invokestatic a : (Ljava/lang/Throwable;)Ljava/lang/Throwable;
    //   4136: athrow
    //   4137: aload #20
    //   4139: iload #22
    //   4141: aload #20
    //   4143: iload #22
    //   4145: iconst_2
    //   4146: isub
    //   4147: iaload
    //   4148: bipush #17
    //   4150: iushr
    //   4151: aload #20
    //   4153: iload #22
    //   4155: iconst_2
    //   4156: isub
    //   4157: iaload
    //   4158: bipush #15
    //   4160: ishl
    //   4161: ior
    //   4162: aload #20
    //   4164: iload #22
    //   4166: iconst_2
    //   4167: isub
    //   4168: iaload
    //   4169: bipush #19
    //   4171: iushr
    //   4172: aload #20
    //   4174: iload #22
    //   4176: iconst_2
    //   4177: isub
    //   4178: iaload
    //   4179: bipush #13
    //   4181: ishl
    //   4182: ior
    //   4183: ixor
    //   4184: aload #20
    //   4186: iload #22
    //   4188: iconst_2
    //   4189: isub
    //   4190: iaload
    //   4191: bipush #10
    //   4193: iushr
    //   4194: ixor
    //   4195: aload #20
    //   4197: iload #22
    //   4199: bipush #7
    //   4201: isub
    //   4202: iaload
    //   4203: iadd
    //   4204: aload #20
    //   4206: iload #22
    //   4208: bipush #15
    //   4210: isub
    //   4211: iaload
    //   4212: bipush #7
    //   4214: iushr
    //   4215: aload #20
    //   4217: iload #22
    //   4219: bipush #15
    //   4221: isub
    //   4222: iaload
    //   4223: bipush #25
    //   4225: ishl
    //   4226: ior
    //   4227: aload #20
    //   4229: iload #22
    //   4231: bipush #15
    //   4233: isub
    //   4234: iaload
    //   4235: bipush #18
    //   4237: iushr
    //   4238: aload #20
    //   4240: iload #22
    //   4242: bipush #15
    //   4244: isub
    //   4245: iaload
    //   4246: bipush #14
    //   4248: ishl
    //   4249: ior
    //   4250: ixor
    //   4251: aload #20
    //   4253: iload #22
    //   4255: bipush #15
    //   4257: isub
    //   4258: iaload
    //   4259: iconst_3
    //   4260: iushr
    //   4261: ixor
    //   4262: iadd
    //   4263: aload #20
    //   4265: iload #22
    //   4267: bipush #16
    //   4269: isub
    //   4270: iaload
    //   4271: iadd
    //   4272: iastore
    //   4273: goto -> 4280
    //   4276: invokestatic a : (Ljava/lang/Throwable;)Ljava/lang/Throwable;
    //   4279: athrow
    //   4280: aload #21
    //   4282: bipush #7
    //   4284: iaload
    //   4285: aload #21
    //   4287: iconst_4
    //   4288: iaload
    //   4289: bipush #6
    //   4291: iushr
    //   4292: aload #21
    //   4294: iconst_4
    //   4295: iaload
    //   4296: bipush #26
    //   4298: ishl
    //   4299: ior
    //   4300: aload #21
    //   4302: iconst_4
    //   4303: iaload
    //   4304: bipush #11
    //   4306: iushr
    //   4307: aload #21
    //   4309: iconst_4
    //   4310: iaload
    //   4311: bipush #21
    //   4313: ishl
    //   4314: ior
    //   4315: ixor
    //   4316: aload #21
    //   4318: iconst_4
    //   4319: iaload
    //   4320: bipush #25
    //   4322: iushr
    //   4323: aload #21
    //   4325: iconst_4
    //   4326: iaload
    //   4327: bipush #7
    //   4329: ishl
    //   4330: ior
    //   4331: ixor
    //   4332: iadd
    //   4333: aload #21
    //   4335: bipush #6
    //   4337: iaload
    //   4338: aload #21
    //   4340: iconst_4
    //   4341: iaload
    //   4342: aload #21
    //   4344: iconst_5
    //   4345: iaload
    //   4346: aload #21
    //   4348: bipush #6
    //   4350: iaload
    //   4351: ixor
    //   4352: iand
    //   4353: ixor
    //   4354: iadd
    //   4355: aload #7
    //   4357: iload #22
    //   4359: iaload
    //   4360: iadd
    //   4361: aload #20
    //   4363: iload #22
    //   4365: iaload
    //   4366: iadd
    //   4367: istore #23
    //   4369: aload #21
    //   4371: iconst_0
    //   4372: iaload
    //   4373: iconst_2
    //   4374: iushr
    //   4375: aload #21
    //   4377: iconst_0
    //   4378: iaload
    //   4379: bipush #30
    //   4381: ishl
    //   4382: ior
    //   4383: aload #21
    //   4385: iconst_0
    //   4386: iaload
    //   4387: bipush #13
    //   4389: iushr
    //   4390: aload #21
    //   4392: iconst_0
    //   4393: iaload
    //   4394: bipush #19
    //   4396: ishl
    //   4397: ior
    //   4398: ixor
    //   4399: aload #21
    //   4401: iconst_0
    //   4402: iaload
    //   4403: bipush #22
    //   4405: iushr
    //   4406: aload #21
    //   4408: iconst_0
    //   4409: iaload
    //   4410: bipush #10
    //   4412: ishl
    //   4413: ior
    //   4414: ixor
    //   4415: aload #21
    //   4417: iconst_0
    //   4418: iaload
    //   4419: aload #21
    //   4421: iconst_1
    //   4422: iaload
    //   4423: iand
    //   4424: aload #21
    //   4426: iconst_2
    //   4427: iaload
    //   4428: aload #21
    //   4430: iconst_0
    //   4431: iaload
    //   4432: aload #21
    //   4434: iconst_1
    //   4435: iaload
    //   4436: ior
    //   4437: iand
    //   4438: ior
    //   4439: iadd
    //   4440: istore #24
    //   4442: aload #21
    //   4444: iconst_3
    //   4445: dup2
    //   4446: iaload
    //   4447: iload #23
    //   4449: iadd
    //   4450: iastore
    //   4451: aload #21
    //   4453: bipush #7
    //   4455: iload #23
    //   4457: iload #24
    //   4459: iadd
    //   4460: iastore
    //   4461: aload #21
    //   4463: bipush #7
    //   4465: iaload
    //   4466: istore #23
    //   4468: aload #21
    //   4470: bipush #7
    //   4472: aload #21
    //   4474: bipush #6
    //   4476: iaload
    //   4477: iastore
    //   4478: aload #21
    //   4480: bipush #6
    //   4482: aload #21
    //   4484: iconst_5
    //   4485: iaload
    //   4486: iastore
    //   4487: aload #21
    //   4489: iconst_5
    //   4490: aload #21
    //   4492: iconst_4
    //   4493: iaload
    //   4494: iastore
    //   4495: aload #21
    //   4497: iconst_4
    //   4498: aload #21
    //   4500: iconst_3
    //   4501: iaload
    //   4502: iastore
    //   4503: aload #21
    //   4505: iconst_3
    //   4506: aload #21
    //   4508: iconst_2
    //   4509: iaload
    //   4510: iastore
    //   4511: aload #21
    //   4513: iconst_2
    //   4514: aload #21
    //   4516: iconst_1
    //   4517: iaload
    //   4518: iastore
    //   4519: aload #21
    //   4521: iconst_1
    //   4522: aload #21
    //   4524: iconst_0
    //   4525: iaload
    //   4526: iastore
    //   4527: aload #21
    //   4529: iconst_0
    //   4530: iload #23
    //   4532: iastore
    //   4533: iinc #22, 1
    //   4536: iload_2
    //   4537: ifne -> 4045
    //   4540: iconst_0
    //   4541: istore #22
    //   4543: iload #22
    //   4545: bipush #8
    //   4547: if_icmpge -> 4570
    //   4550: aload #9
    //   4552: iload #22
    //   4554: dup2
    //   4555: iaload
    //   4556: aload #21
    //   4558: iload #22
    //   4560: iaload
    //   4561: iadd
    //   4562: iastore
    //   4563: iinc #22, 1
    //   4566: iload_2
    //   4567: ifne -> 4543
    //   4570: iinc #14, 64
    //   4573: iinc #18, -64
    //   4576: iload_2
    //   4577: ifne -> 3966
    //   4580: iload #18
    //   4582: ifle -> 4618
    //   4585: iconst_0
    //   4586: istore #20
    //   4588: iload #20
    //   4590: iload #18
    //   4592: if_icmpge -> 4618
    //   4595: aload #10
    //   4597: iload #13
    //   4599: iload #20
    //   4601: iadd
    //   4602: aload #6
    //   4604: iload #14
    //   4606: iload #20
    //   4608: iadd
    //   4609: baload
    //   4610: bastore
    //   4611: iinc #20, 1
    //   4614: iload_2
    //   4615: ifne -> 4588
    //   4618: bipush #8
    //   4620: newarray byte
    //   4622: astore #20
    //   4624: aload #20
    //   4626: iconst_0
    //   4627: iload #15
    //   4629: bipush #24
    //   4631: iushr
    //   4632: i2b
    //   4633: bastore
    //   4634: aload #20
    //   4636: iconst_1
    //   4637: iload #15
    //   4639: bipush #16
    //   4641: iushr
    //   4642: i2b
    //   4643: bastore
    //   4644: aload #20
    //   4646: iconst_2
    //   4647: iload #15
    //   4649: bipush #8
    //   4651: iushr
    //   4652: i2b
    //   4653: bastore
    //   4654: aload #20
    //   4656: iconst_3
    //   4657: iload #15
    //   4659: i2b
    //   4660: bastore
    //   4661: aload #20
    //   4663: iconst_4
    //   4664: iload #16
    //   4666: bipush #24
    //   4668: iushr
    //   4669: i2b
    //   4670: bastore
    //   4671: aload #20
    //   4673: iconst_5
    //   4674: iload #16
    //   4676: bipush #16
    //   4678: iushr
    //   4679: i2b
    //   4680: bastore
    //   4681: aload #20
    //   4683: bipush #6
    //   4685: iload #16
    //   4687: bipush #8
    //   4689: iushr
    //   4690: i2b
    //   4691: bastore
    //   4692: aload #20
    //   4694: bipush #7
    //   4696: iload #16
    //   4698: i2b
    //   4699: bastore
    //   4700: bipush #8
    //   4702: istore #12
    //   4704: aload #8
    //   4706: iconst_0
    //   4707: iaload
    //   4708: bipush #63
    //   4710: iand
    //   4711: istore #13
    //   4713: bipush #64
    //   4715: iload #13
    //   4717: isub
    //   4718: istore #19
    //   4720: aload #8
    //   4722: iconst_0
    //   4723: dup2
    //   4724: iaload
    //   4725: iload #12
    //   4727: iadd
    //   4728: iastore
    //   4729: aload #8
    //   4731: iconst_0
    //   4732: dup2
    //   4733: iaload
    //   4734: iconst_m1
    //   4735: iand
    //   4736: iastore
    //   4737: aload #8
    //   4739: iconst_0
    //   4740: iaload
    //   4741: iload #12
    //   4743: if_icmpge -> 4761
    //   4746: aload #8
    //   4748: iconst_1
    //   4749: dup2
    //   4750: iaload
    //   4751: iconst_1
    //   4752: iadd
    //   4753: iastore
    //   4754: goto -> 4761
    //   4757: invokestatic a : (Ljava/lang/Throwable;)Ljava/lang/Throwable;
    //   4760: athrow
    //   4761: iload #13
    //   4763: ifle -> 5377
    //   4766: iload #12
    //   4768: iload #19
    //   4770: if_icmplt -> 5377
    //   4773: goto -> 4780
    //   4776: invokestatic a : (Ljava/lang/Throwable;)Ljava/lang/Throwable;
    //   4779: athrow
    //   4780: iconst_0
    //   4781: istore #21
    //   4783: iload #21
    //   4785: iload #19
    //   4787: if_icmpge -> 4810
    //   4790: aload #10
    //   4792: iload #13
    //   4794: iload #21
    //   4796: iadd
    //   4797: aload #20
    //   4799: iload #21
    //   4801: baload
    //   4802: bastore
    //   4803: iinc #21, 1
    //   4806: iload_2
    //   4807: ifne -> 4783
    //   4810: bipush #64
    //   4812: newarray int
    //   4814: astore #21
    //   4816: bipush #8
    //   4818: newarray int
    //   4820: astore #22
    //   4822: iconst_0
    //   4823: istore #23
    //   4825: iload #23
    //   4827: bipush #8
    //   4829: if_icmpge -> 4849
    //   4832: aload #22
    //   4834: iload #23
    //   4836: aload #9
    //   4838: iload #23
    //   4840: iaload
    //   4841: iastore
    //   4842: iinc #23, 1
    //   4845: iload_2
    //   4846: ifne -> 4825
    //   4849: iconst_0
    //   4850: istore #23
    //   4852: iload #23
    //   4854: bipush #64
    //   4856: if_icmpge -> 5347
    //   4859: iload #23
    //   4861: bipush #16
    //   4863: if_icmpge -> 4944
    //   4866: aload #21
    //   4868: iload #23
    //   4870: aload #10
    //   4872: iconst_4
    //   4873: iload #23
    //   4875: imul
    //   4876: baload
    //   4877: sipush #255
    //   4880: iand
    //   4881: bipush #24
    //   4883: ishl
    //   4884: aload #10
    //   4886: iconst_4
    //   4887: iload #23
    //   4889: imul
    //   4890: iconst_1
    //   4891: iadd
    //   4892: baload
    //   4893: sipush #255
    //   4896: iand
    //   4897: bipush #16
    //   4899: ishl
    //   4900: ior
    //   4901: aload #10
    //   4903: iconst_4
    //   4904: iload #23
    //   4906: imul
    //   4907: iconst_2
    //   4908: iadd
    //   4909: baload
    //   4910: sipush #255
    //   4913: iand
    //   4914: bipush #8
    //   4916: ishl
    //   4917: ior
    //   4918: aload #10
    //   4920: iconst_4
    //   4921: iload #23
    //   4923: imul
    //   4924: iconst_3
    //   4925: iadd
    //   4926: baload
    //   4927: sipush #255
    //   4930: iand
    //   4931: ior
    //   4932: iastore
    //   4933: iload_2
    //   4934: ifne -> 5087
    //   4937: goto -> 4944
    //   4940: invokestatic a : (Ljava/lang/Throwable;)Ljava/lang/Throwable;
    //   4943: athrow
    //   4944: aload #21
    //   4946: iload #23
    //   4948: aload #21
    //   4950: iload #23
    //   4952: iconst_2
    //   4953: isub
    //   4954: iaload
    //   4955: bipush #17
    //   4957: iushr
    //   4958: aload #21
    //   4960: iload #23
    //   4962: iconst_2
    //   4963: isub
    //   4964: iaload
    //   4965: bipush #15
    //   4967: ishl
    //   4968: ior
    //   4969: aload #21
    //   4971: iload #23
    //   4973: iconst_2
    //   4974: isub
    //   4975: iaload
    //   4976: bipush #19
    //   4978: iushr
    //   4979: aload #21
    //   4981: iload #23
    //   4983: iconst_2
    //   4984: isub
    //   4985: iaload
    //   4986: bipush #13
    //   4988: ishl
    //   4989: ior
    //   4990: ixor
    //   4991: aload #21
    //   4993: iload #23
    //   4995: iconst_2
    //   4996: isub
    //   4997: iaload
    //   4998: bipush #10
    //   5000: iushr
    //   5001: ixor
    //   5002: aload #21
    //   5004: iload #23
    //   5006: bipush #7
    //   5008: isub
    //   5009: iaload
    //   5010: iadd
    //   5011: aload #21
    //   5013: iload #23
    //   5015: bipush #15
    //   5017: isub
    //   5018: iaload
    //   5019: bipush #7
    //   5021: iushr
    //   5022: aload #21
    //   5024: iload #23
    //   5026: bipush #15
    //   5028: isub
    //   5029: iaload
    //   5030: bipush #25
    //   5032: ishl
    //   5033: ior
    //   5034: aload #21
    //   5036: iload #23
    //   5038: bipush #15
    //   5040: isub
    //   5041: iaload
    //   5042: bipush #18
    //   5044: iushr
    //   5045: aload #21
    //   5047: iload #23
    //   5049: bipush #15
    //   5051: isub
    //   5052: iaload
    //   5053: bipush #14
    //   5055: ishl
    //   5056: ior
    //   5057: ixor
    //   5058: aload #21
    //   5060: iload #23
    //   5062: bipush #15
    //   5064: isub
    //   5065: iaload
    //   5066: iconst_3
    //   5067: iushr
    //   5068: ixor
    //   5069: iadd
    //   5070: aload #21
    //   5072: iload #23
    //   5074: bipush #16
    //   5076: isub
    //   5077: iaload
    //   5078: iadd
    //   5079: iastore
    //   5080: goto -> 5087
    //   5083: invokestatic a : (Ljava/lang/Throwable;)Ljava/lang/Throwable;
    //   5086: athrow
    //   5087: aload #22
    //   5089: bipush #7
    //   5091: iaload
    //   5092: aload #22
    //   5094: iconst_4
    //   5095: iaload
    //   5096: bipush #6
    //   5098: iushr
    //   5099: aload #22
    //   5101: iconst_4
    //   5102: iaload
    //   5103: bipush #26
    //   5105: ishl
    //   5106: ior
    //   5107: aload #22
    //   5109: iconst_4
    //   5110: iaload
    //   5111: bipush #11
    //   5113: iushr
    //   5114: aload #22
    //   5116: iconst_4
    //   5117: iaload
    //   5118: bipush #21
    //   5120: ishl
    //   5121: ior
    //   5122: ixor
    //   5123: aload #22
    //   5125: iconst_4
    //   5126: iaload
    //   5127: bipush #25
    //   5129: iushr
    //   5130: aload #22
    //   5132: iconst_4
    //   5133: iaload
    //   5134: bipush #7
    //   5136: ishl
    //   5137: ior
    //   5138: ixor
    //   5139: iadd
    //   5140: aload #22
    //   5142: bipush #6
    //   5144: iaload
    //   5145: aload #22
    //   5147: iconst_4
    //   5148: iaload
    //   5149: aload #22
    //   5151: iconst_5
    //   5152: iaload
    //   5153: aload #22
    //   5155: bipush #6
    //   5157: iaload
    //   5158: ixor
    //   5159: iand
    //   5160: ixor
    //   5161: iadd
    //   5162: aload #7
    //   5164: iload #23
    //   5166: iaload
    //   5167: iadd
    //   5168: aload #21
    //   5170: iload #23
    //   5172: iaload
    //   5173: iadd
    //   5174: istore #24
    //   5176: aload #22
    //   5178: iconst_0
    //   5179: iaload
    //   5180: iconst_2
    //   5181: iushr
    //   5182: aload #22
    //   5184: iconst_0
    //   5185: iaload
    //   5186: bipush #30
    //   5188: ishl
    //   5189: ior
    //   5190: aload #22
    //   5192: iconst_0
    //   5193: iaload
    //   5194: bipush #13
    //   5196: iushr
    //   5197: aload #22
    //   5199: iconst_0
    //   5200: iaload
    //   5201: bipush #19
    //   5203: ishl
    //   5204: ior
    //   5205: ixor
    //   5206: aload #22
    //   5208: iconst_0
    //   5209: iaload
    //   5210: bipush #22
    //   5212: iushr
    //   5213: aload #22
    //   5215: iconst_0
    //   5216: iaload
    //   5217: bipush #10
    //   5219: ishl
    //   5220: ior
    //   5221: ixor
    //   5222: aload #22
    //   5224: iconst_0
    //   5225: iaload
    //   5226: aload #22
    //   5228: iconst_1
    //   5229: iaload
    //   5230: iand
    //   5231: aload #22
    //   5233: iconst_2
    //   5234: iaload
    //   5235: aload #22
    //   5237: iconst_0
    //   5238: iaload
    //   5239: aload #22
    //   5241: iconst_1
    //   5242: iaload
    //   5243: ior
    //   5244: iand
    //   5245: ior
    //   5246: iadd
    //   5247: istore #25
    //   5249: aload #22
    //   5251: iconst_3
    //   5252: dup2
    //   5253: iaload
    //   5254: iload #24
    //   5256: iadd
    //   5257: iastore
    //   5258: aload #22
    //   5260: bipush #7
    //   5262: iload #24
    //   5264: iload #25
    //   5266: iadd
    //   5267: iastore
    //   5268: aload #22
    //   5270: bipush #7
    //   5272: iaload
    //   5273: istore #24
    //   5275: aload #22
    //   5277: bipush #7
    //   5279: aload #22
    //   5281: bipush #6
    //   5283: iaload
    //   5284: iastore
    //   5285: aload #22
    //   5287: bipush #6
    //   5289: aload #22
    //   5291: iconst_5
    //   5292: iaload
    //   5293: iastore
    //   5294: aload #22
    //   5296: iconst_5
    //   5297: aload #22
    //   5299: iconst_4
    //   5300: iaload
    //   5301: iastore
    //   5302: aload #22
    //   5304: iconst_4
    //   5305: aload #22
    //   5307: iconst_3
    //   5308: iaload
    //   5309: iastore
    //   5310: aload #22
    //   5312: iconst_3
    //   5313: aload #22
    //   5315: iconst_2
    //   5316: iaload
    //   5317: iastore
    //   5318: aload #22
    //   5320: iconst_2
    //   5321: aload #22
    //   5323: iconst_1
    //   5324: iaload
    //   5325: iastore
    //   5326: aload #22
    //   5328: iconst_1
    //   5329: aload #22
    //   5331: iconst_0
    //   5332: iaload
    //   5333: iastore
    //   5334: aload #22
    //   5336: iconst_0
    //   5337: iload #24
    //   5339: iastore
    //   5340: iinc #23, 1
    //   5343: iload_2
    //   5344: ifne -> 4852
    //   5347: iconst_0
    //   5348: istore #23
    //   5350: iload #23
    //   5352: bipush #8
    //   5354: if_icmpge -> 5377
    //   5357: aload #9
    //   5359: iload #23
    //   5361: dup2
    //   5362: iaload
    //   5363: aload #22
    //   5365: iload #23
    //   5367: iaload
    //   5368: iadd
    //   5369: iastore
    //   5370: iinc #23, 1
    //   5373: iload_2
    //   5374: ifne -> 5350
    //   5377: bipush #32
    //   5379: newarray byte
    //   5381: astore #5
    //   5383: aload #5
    //   5385: iconst_0
    //   5386: aload #9
    //   5388: iconst_0
    //   5389: iaload
    //   5390: bipush #24
    //   5392: iushr
    //   5393: i2b
    //   5394: bastore
    //   5395: aload #5
    //   5397: iconst_1
    //   5398: aload #9
    //   5400: iconst_0
    //   5401: iaload
    //   5402: bipush #16
    //   5404: iushr
    //   5405: i2b
    //   5406: bastore
    //   5407: aload #5
    //   5409: iconst_2
    //   5410: aload #9
    //   5412: iconst_0
    //   5413: iaload
    //   5414: bipush #8
    //   5416: iushr
    //   5417: i2b
    //   5418: bastore
    //   5419: aload #5
    //   5421: iconst_3
    //   5422: aload #9
    //   5424: iconst_0
    //   5425: iaload
    //   5426: i2b
    //   5427: bastore
    //   5428: aload #5
    //   5430: iconst_4
    //   5431: aload #9
    //   5433: iconst_1
    //   5434: iaload
    //   5435: bipush #24
    //   5437: iushr
    //   5438: i2b
    //   5439: bastore
    //   5440: aload #5
    //   5442: iconst_5
    //   5443: aload #9
    //   5445: iconst_1
    //   5446: iaload
    //   5447: bipush #16
    //   5449: iushr
    //   5450: i2b
    //   5451: bastore
    //   5452: aload #5
    //   5454: bipush #6
    //   5456: aload #9
    //   5458: iconst_1
    //   5459: iaload
    //   5460: bipush #8
    //   5462: iushr
    //   5463: i2b
    //   5464: bastore
    //   5465: aload #5
    //   5467: bipush #7
    //   5469: aload #9
    //   5471: iconst_1
    //   5472: iaload
    //   5473: i2b
    //   5474: bastore
    //   5475: aload #5
    //   5477: bipush #8
    //   5479: aload #9
    //   5481: iconst_2
    //   5482: iaload
    //   5483: bipush #24
    //   5485: iushr
    //   5486: i2b
    //   5487: bastore
    //   5488: aload #5
    //   5490: bipush #9
    //   5492: aload #9
    //   5494: iconst_2
    //   5495: iaload
    //   5496: bipush #16
    //   5498: iushr
    //   5499: i2b
    //   5500: bastore
    //   5501: aload #5
    //   5503: bipush #10
    //   5505: aload #9
    //   5507: iconst_2
    //   5508: iaload
    //   5509: bipush #8
    //   5511: iushr
    //   5512: i2b
    //   5513: bastore
    //   5514: aload #5
    //   5516: bipush #11
    //   5518: aload #9
    //   5520: iconst_2
    //   5521: iaload
    //   5522: i2b
    //   5523: bastore
    //   5524: aload #5
    //   5526: bipush #12
    //   5528: aload #9
    //   5530: iconst_3
    //   5531: iaload
    //   5532: bipush #24
    //   5534: iushr
    //   5535: i2b
    //   5536: bastore
    //   5537: aload #5
    //   5539: bipush #13
    //   5541: aload #9
    //   5543: iconst_3
    //   5544: iaload
    //   5545: bipush #16
    //   5547: iushr
    //   5548: i2b
    //   5549: bastore
    //   5550: aload #5
    //   5552: bipush #14
    //   5554: aload #9
    //   5556: iconst_3
    //   5557: iaload
    //   5558: bipush #8
    //   5560: iushr
    //   5561: i2b
    //   5562: bastore
    //   5563: aload #5
    //   5565: bipush #15
    //   5567: aload #9
    //   5569: iconst_3
    //   5570: iaload
    //   5571: i2b
    //   5572: bastore
    //   5573: aload #5
    //   5575: bipush #16
    //   5577: aload #9
    //   5579: iconst_4
    //   5580: iaload
    //   5581: bipush #24
    //   5583: iushr
    //   5584: i2b
    //   5585: bastore
    //   5586: aload #5
    //   5588: bipush #17
    //   5590: aload #9
    //   5592: iconst_4
    //   5593: iaload
    //   5594: bipush #16
    //   5596: iushr
    //   5597: i2b
    //   5598: bastore
    //   5599: aload #5
    //   5601: bipush #18
    //   5603: aload #9
    //   5605: iconst_4
    //   5606: iaload
    //   5607: bipush #8
    //   5609: iushr
    //   5610: i2b
    //   5611: bastore
    //   5612: aload #5
    //   5614: bipush #19
    //   5616: aload #9
    //   5618: iconst_4
    //   5619: iaload
    //   5620: i2b
    //   5621: bastore
    //   5622: aload #5
    //   5624: bipush #20
    //   5626: aload #9
    //   5628: iconst_5
    //   5629: iaload
    //   5630: bipush #24
    //   5632: iushr
    //   5633: i2b
    //   5634: bastore
    //   5635: aload #5
    //   5637: bipush #21
    //   5639: aload #9
    //   5641: iconst_5
    //   5642: iaload
    //   5643: bipush #16
    //   5645: iushr
    //   5646: i2b
    //   5647: bastore
    //   5648: aload #5
    //   5650: bipush #22
    //   5652: aload #9
    //   5654: iconst_5
    //   5655: iaload
    //   5656: bipush #8
    //   5658: iushr
    //   5659: i2b
    //   5660: bastore
    //   5661: aload #5
    //   5663: bipush #23
    //   5665: aload #9
    //   5667: iconst_5
    //   5668: iaload
    //   5669: i2b
    //   5670: bastore
    //   5671: aload #5
    //   5673: bipush #24
    //   5675: aload #9
    //   5677: bipush #6
    //   5679: iaload
    //   5680: bipush #24
    //   5682: iushr
    //   5683: i2b
    //   5684: bastore
    //   5685: aload #5
    //   5687: bipush #25
    //   5689: aload #9
    //   5691: bipush #6
    //   5693: iaload
    //   5694: bipush #16
    //   5696: iushr
    //   5697: i2b
    //   5698: bastore
    //   5699: aload #5
    //   5701: bipush #26
    //   5703: aload #9
    //   5705: bipush #6
    //   5707: iaload
    //   5708: bipush #8
    //   5710: iushr
    //   5711: i2b
    //   5712: bastore
    //   5713: aload #5
    //   5715: bipush #27
    //   5717: aload #9
    //   5719: bipush #6
    //   5721: iaload
    //   5722: i2b
    //   5723: bastore
    //   5724: aload #5
    //   5726: bipush #28
    //   5728: aload #9
    //   5730: bipush #7
    //   5732: iaload
    //   5733: bipush #24
    //   5735: iushr
    //   5736: i2b
    //   5737: bastore
    //   5738: aload #5
    //   5740: bipush #29
    //   5742: aload #9
    //   5744: bipush #7
    //   5746: iaload
    //   5747: bipush #16
    //   5749: iushr
    //   5750: i2b
    //   5751: bastore
    //   5752: aload #5
    //   5754: bipush #30
    //   5756: aload #9
    //   5758: bipush #7
    //   5760: iaload
    //   5761: bipush #8
    //   5763: iushr
    //   5764: i2b
    //   5765: bastore
    //   5766: aload #5
    //   5768: bipush #31
    //   5770: aload #9
    //   5772: bipush #7
    //   5774: iaload
    //   5775: i2b
    //   5776: bastore
    //   5777: getstatic burp/Ze69.ZA : Ljava/lang/String;
    //   5780: getstatic burp/Zlhy.ZN : Ljava/lang/Object;
    //   5783: checkcast java/math/BigInteger
    //   5786: invokevirtual intValue : ()I
    //   5789: bipush #32
    //   5791: irem
    //   5792: invokestatic abs : (I)I
    //   5795: invokevirtual charAt : (I)C
    //   5798: getstatic burp/Zkb_.ZR : Ljava/lang/String;
    //   5801: getstatic burp/Zlnm.Zn : Ljava/lang/Object;
    //   5804: checkcast java/math/BigInteger
    //   5807: invokevirtual intValue : ()I
    //   5810: bipush #32
    //   5812: irem
    //   5813: invokestatic abs : (I)I
    //   5816: invokevirtual charAt : (I)C
    //   5819: if_icmpgt -> 5926
    //   5822: getstatic burp/Zm52.Ze : Ljava/lang/String;
    //   5825: getstatic burp/Zztn.ZO : Ljava/lang/Object;
    //   5828: checkcast java/math/BigInteger
    //   5831: invokevirtual intValue : ()I
    //   5834: bipush #32
    //   5836: irem
    //   5837: invokestatic abs : (I)I
    //   5840: invokevirtual charAt : (I)C
    //   5843: getstatic burp/Ze8m.Zx : Ljava/lang/String;
    //   5846: getstatic burp/Ze54.Zx : Ljava/lang/Object;
    //   5849: checkcast java/math/BigInteger
    //   5852: invokevirtual intValue : ()I
    //   5855: bipush #32
    //   5857: irem
    //   5858: invokestatic abs : (I)I
    //   5861: invokevirtual charAt : (I)C
    //   5864: if_icmple -> 5926
    //   5867: goto -> 5874
    //   5870: invokestatic a : (Ljava/lang/Throwable;)Ljava/lang/Throwable;
    //   5873: athrow
    //   5874: getstatic burp/Zltz.Za : Ljava/lang/String;
    //   5877: getstatic burp/Zz2e.Zm : Ljava/lang/Object;
    //   5880: checkcast java/math/BigInteger
    //   5883: invokevirtual intValue : ()I
    //   5886: bipush #32
    //   5888: irem
    //   5889: invokestatic abs : (I)I
    //   5892: invokevirtual charAt : (I)C
    //   5895: getstatic burp/Zlx5.ZP : Ljava/lang/String;
    //   5898: getstatic burp/Zlrm.ZM : Ljava/lang/Object;
    //   5901: checkcast java/math/BigInteger
    //   5904: invokevirtual intValue : ()I
    //   5907: bipush #32
    //   5909: irem
    //   5910: invokestatic abs : (I)I
    //   5913: invokevirtual charAt : (I)C
    //   5916: if_icmple -> 5934
    //   5919: goto -> 5926
    //   5922: invokestatic a : (Ljava/lang/Throwable;)Ljava/lang/Throwable;
    //   5925: athrow
    //   5926: iconst_1
    //   5927: goto -> 5935
    //   5930: invokestatic a : (Ljava/lang/Throwable;)Ljava/lang/Throwable;
    //   5933: athrow
    //   5934: iconst_0
    //   5935: ireturn
    //   5936: astore_3
    //   5937: new java/lang/Exception
    //   5940: dup
    //   5941: aload_3
    //   5942: invokevirtual getMessage : ()Ljava/lang/String;
    //   5945: invokespecial <init> : (Ljava/lang/String;)V
    //   5948: athrow
    // Exception table:
    //   from	to	target	type
    //   4	5935	5936	java/lang/Throwable
    //   22	198	201	java/lang/Throwable
    //   168	235	238	java/lang/Throwable
    //   205	272	275	java/lang/Throwable
    //   242	309	312	java/lang/Throwable
    //   279	346	349	java/lang/Throwable
    //   316	383	386	java/lang/Throwable
    //   353	420	423	java/lang/Throwable
    //   390	457	460	java/lang/Throwable
    //   427	494	497	java/lang/Throwable
    //   464	531	534	java/lang/Throwable
    //   501	568	571	java/lang/Throwable
    //   538	605	608	java/lang/Throwable
    //   575	642	645	java/lang/Throwable
    //   612	679	682	java/lang/Throwable
    //   649	716	719	java/lang/Throwable
    //   686	753	756	java/lang/Throwable
    //   723	790	793	java/lang/Throwable
    //   760	827	830	java/lang/Throwable
    //   797	864	867	java/lang/Throwable
    //   834	901	904	java/lang/Throwable
    //   871	938	941	java/lang/Throwable
    //   908	975	978	java/lang/Throwable
    //   945	1012	1015	java/lang/Throwable
    //   982	1049	1052	java/lang/Throwable
    //   1019	1086	1089	java/lang/Throwable
    //   1056	1123	1126	java/lang/Throwable
    //   1093	1160	1163	java/lang/Throwable
    //   1130	1197	1200	java/lang/Throwable
    //   1167	1234	1237	java/lang/Throwable
    //   1204	1271	1274	java/lang/Throwable
    //   1241	1308	1311	java/lang/Throwable
    //   1278	1341	1344	java/lang/Throwable
    //   1425	1439	1439	java/lang/Throwable
    //   1450	1463	1466	java/lang/Throwable
    //   1455	1478	1481	java/lang/Throwable
    //   1470	1496	1499	java/lang/Throwable
    //   1485	1526	1529	java/lang/Throwable
    //   1592	1619	1622	java/lang/Throwable
    //   1609	1640	1643	java/lang/Throwable
    //   1626	1670	1673	java/lang/Throwable
    //   1647	1681	1681	java/lang/Throwable
    //   1692	1708	1711	java/lang/Throwable
    //   2518	2552	2555	java/lang/Throwable
    //   2648	2726	2729	java/lang/Throwable
    //   2655	2869	2872	java/lang/Throwable
    //   3247	3262	3262	java/lang/Throwable
    //   3289	3323	3326	java/lang/Throwable
    //   3333	3345	3348	java/lang/Throwable
    //   3431	3509	3512	java/lang/Throwable
    //   3438	3652	3655	java/lang/Throwable
    //   4052	4130	4133	java/lang/Throwable
    //   4059	4273	4276	java/lang/Throwable
    //   4720	4754	4757	java/lang/Throwable
    //   4761	4773	4776	java/lang/Throwable
    //   4859	4937	4940	java/lang/Throwable
    //   4866	5080	5083	java/lang/Throwable
    //   5383	5867	5870	java/lang/Throwable
    //   5822	5919	5922	java/lang/Throwable
    //   5874	5930	5930	java/lang/Throwable
  }
  
  static void Ze(Object[] paramArrayOfObject, Object paramObject) throws Throwable {}
  
  static {
    // Byte code:
    //   0: bipush #8
    //   2: anewarray java/lang/String
    //   5: astore #5
    //   7: iconst_0
    //   8: istore_3
    //   9: ldc '/m?X9%Mpa5#$BN4SQ*JB8ooZ2XC)3Fr\\taF ZIeK!aM;r&"r [_:(L{'tc6s1Nz\\t\\r&A'
    //   11: dup
    //   12: astore_2
    //   13: invokevirtual length : ()I
    //   16: istore #4
    //   18: bipush #76
    //   20: istore_1
    //   21: iconst_m1
    //   22: istore_0
    //   23: bipush #60
    //   25: iinc #0, 1
    //   28: aload_2
    //   29: iload_0
    //   30: dup
    //   31: iload_1
    //   32: iadd
    //   33: invokevirtual substring : (II)Ljava/lang/String;
    //   36: iconst_m1
    //   37: goto -> 143
    //   40: aload #5
    //   42: swap
    //   43: iload_3
    //   44: iinc #3, 1
    //   47: swap
    //   48: aastore
    //   49: iload_0
    //   50: iload_1
    //   51: iadd
    //   52: dup
    //   53: istore_0
    //   54: iload #4
    //   56: if_icmpge -> 68
    //   59: aload_2
    //   60: iload_0
    //   61: invokevirtual charAt : (I)C
    //   64: istore_1
    //   65: goto -> 23
    //   68: ldc 'gUL\\tDah0'
    //   70: dup
    //   71: astore_2
    //   72: invokevirtual length : ()I
    //   75: istore #4
    //   77: bipush #9
    //   79: istore_1
    //   80: iconst_m1
    //   81: istore_0
    //   82: bipush #106
    //   84: iinc #0, 1
    //   87: aload_2
    //   88: iload_0
    //   89: dup
    //   90: iload_1
    //   91: iadd
    //   92: invokevirtual substring : (II)Ljava/lang/String;
    //   95: iconst_0
    //   96: goto -> 143
    //   99: aload #5
    //   101: swap
    //   102: iload_3
    //   103: iinc #3, 1
    //   106: swap
    //   107: aastore
    //   108: iload_0
    //   109: iload_1
    //   110: iadd
    //   111: dup
    //   112: istore_0
    //   113: iload #4
    //   115: if_icmpge -> 127
    //   118: aload_2
    //   119: iload_0
    //   120: invokevirtual charAt : (I)C
    //   123: istore_1
    //   124: goto -> 82
    //   127: aload #5
    //   129: putstatic burp/Zera.a : [Ljava/lang/String;
    //   132: bipush #8
    //   134: anewarray java/lang/String
    //   137: putstatic burp/Zera.b : [Ljava/lang/String;
    //   140: goto -> 300
    //   143: dup_x2
    //   144: pop
    //   145: invokevirtual toCharArray : ()[C
    //   148: dup_x1
    //   149: arraylength
    //   150: dup_x2
    //   151: pop
    //   152: iconst_0
    //   153: istore #6
    //   155: dup2_x1
    //   156: pop2
    //   157: dup_x2
    //   158: iconst_1
    //   159: if_icmpgt -> 260
    //   162: dup2
    //   163: swap
    //   164: iload #6
    //   166: dup2_x1
    //   167: caload
    //   168: swap
    //   169: iload #6
    //   171: bipush #7
    //   173: irem
    //   174: tableswitch default -> 242, 0 -> 212, 1 -> 217, 2 -> 222, 3 -> 227, 4 -> 232, 5 -> 237
    //   212: bipush #120
    //   214: goto -> 244
    //   217: bipush #119
    //   219: goto -> 244
    //   222: bipush #91
    //   224: goto -> 244
    //   227: bipush #80
    //   229: goto -> 244
    //   232: bipush #55
    //   234: goto -> 244
    //   237: bipush #77
    //   239: goto -> 244
    //   242: bipush #117
    //   244: ixor
    //   245: ixor
    //   246: i2c
    //   247: castore
    //   248: iinc #6, 1
    //   251: dup
    //   252: ifne -> 260
    //   255: dup2
    //   256: dup_x1
    //   257: goto -> 166
    //   260: dup2_x1
    //   261: pop2
    //   262: dup_x2
    //   263: iload #6
    //   265: if_icmpgt -> 162
    //   268: pop
    //   269: new java/lang/String
    //   272: dup_x1
    //   273: swap
    //   274: invokespecial <init> : ([C)V
    //   277: invokevirtual intern : ()Ljava/lang/String;
    //   280: swap
    //   281: pop
    //   282: swap
    //   283: tableswitch default -> 40, 0 -> 99
    //   300: new java/math/BigInteger
    //   303: dup
    //   304: iconst_1
    //   305: bipush #32
    //   307: newarray byte
    //   309: dup
    //   310: iconst_0
    //   311: bipush #11
    //   313: bastore
    //   314: dup
    //   315: iconst_1
    //   316: bipush #-93
    //   318: bastore
    //   319: dup
    //   320: iconst_2
    //   321: bipush #56
    //   323: bastore
    //   324: dup
    //   325: iconst_3
    //   326: bipush #-37
    //   328: bastore
    //   329: dup
    //   330: iconst_4
    //   331: bipush #18
    //   333: bastore
    //   334: dup
    //   335: iconst_5
    //   336: bipush #-115
    //   338: bastore
    //   339: dup
    //   340: bipush #6
    //   342: bipush #-53
    //   344: bastore
    //   345: dup
    //   346: bipush #7
    //   348: bipush #-54
    //   350: bastore
    //   351: dup
    //   352: bipush #8
    //   354: bipush #-81
    //   356: bastore
    //   357: dup
    //   358: bipush #9
    //   360: bipush #105
    //   362: bastore
    //   363: dup
    //   364: bipush #10
    //   366: bipush #-21
    //   368: bastore
    //   369: dup
    //   370: bipush #11
    //   372: bipush #-75
    //   374: bastore
    //   375: dup
    //   376: bipush #12
    //   378: bipush #-120
    //   380: bastore
    //   381: dup
    //   382: bipush #13
    //   384: bipush #-75
    //   386: bastore
    //   387: dup
    //   388: bipush #14
    //   390: bipush #-65
    //   392: bastore
    //   393: dup
    //   394: bipush #15
    //   396: bipush #-87
    //   398: bastore
    //   399: dup
    //   400: bipush #16
    //   402: bipush #37
    //   404: bastore
    //   405: dup
    //   406: bipush #17
    //   408: bipush #-19
    //   410: bastore
    //   411: dup
    //   412: bipush #18
    //   414: bipush #67
    //   416: bastore
    //   417: dup
    //   418: bipush #19
    //   420: bipush #51
    //   422: bastore
    //   423: dup
    //   424: bipush #20
    //   426: bipush #-77
    //   428: bastore
    //   429: dup
    //   430: bipush #21
    //   432: bipush #-110
    //   434: bastore
    //   435: dup
    //   436: bipush #22
    //   438: bipush #96
    //   440: bastore
    //   441: dup
    //   442: bipush #23
    //   444: bipush #52
    //   446: bastore
    //   447: dup
    //   448: bipush #24
    //   450: bipush #75
    //   452: bastore
    //   453: dup
    //   454: bipush #25
    //   456: bipush #-109
    //   458: bastore
    //   459: dup
    //   460: bipush #26
    //   462: bipush #-92
    //   464: bastore
    //   465: dup
    //   466: bipush #27
    //   468: bipush #21
    //   470: bastore
    //   471: dup
    //   472: bipush #28
    //   474: bipush #-72
    //   476: bastore
    //   477: dup
    //   478: bipush #29
    //   480: bipush #-3
    //   482: bastore
    //   483: dup
    //   484: bipush #30
    //   486: bipush #-72
    //   488: bastore
    //   489: dup
    //   490: bipush #31
    //   492: bipush #-92
    //   494: bastore
    //   495: invokespecial <init> : (I[B)V
    //   498: putstatic burp/Zera.Zy : Ljava/lang/Object;
    //   501: sipush #-10439
    //   504: sipush #7095
    //   507: invokestatic a : (II)Ljava/lang/String;
    //   510: putstatic burp/Zera.Zn : Ljava/lang/String;
    //   513: return
  }
  
  private static Throwable a(Throwable paramThrowable) {
    return paramThrowable;
  }
  
  private static String a(int paramInt1, int paramInt2) {
    int i = (paramInt1 ^ 0xFFFFD73A) & 0xFFFF;
    if (b[i] == null) {
      char[] arrayOfChar = a[i].toCharArray();
      switch (arrayOfChar[0] & 0xFF) {
        case 0:
        
        case 1:
        
        case 2:
        
        case 3:
        
        case 4:
        
        case 5:
        
        case 6:
        
        case 7:
        
        case 8:
        
        case 9:
        
        case 10:
        
        case 11:
        
        case 12:
        
        case 13:
        
        case 14:
        
        case 15:
        
        case 16:
        
        case 17:
        
        case 18:
        
        case 19:
        
        case 20:
        
        case 21:
        
        case 22:
        
        case 23:
        
        case 24:
        
        case 25:
        
        case 26:
        
        case 27:
        
        case 28:
        
        case 29:
        
        case 30:
        
        case 31:
        
        case 32:
        
        case 33:
        
        case 34:
        
        case 35:
        
        case 36:
        
        case 37:
        
        case 38:
        
        case 39:
        
        case 40:
        
        case 41:
        
        case 42:
        
        case 43:
        
        case 44:
        
        case 45:
        
        case 46:
        
        case 47:
        
        case 48:
        
        case 49:
        
        case 50:
        
        case 51:
        
        case 52:
        
        case 53:
        
        case 54:
        
        case 55:
        
        case 56:
        
        case 57:
        
        case 58:
        
        case 59:
        
        case 60:
        
        case 61:
        
        case 62:
        
        case 63:
        
        case 64:
        
        case 65:
        
        case 66:
        
        case 67:
        
        case 68:
        
        case 69:
        
        case 70:
        
        case 71:
        
        case 72:
        
        case 73:
        
        case 74:
        
        case 75:
        
        case 76:
        
        case 77:
        
        case 78:
        
        case 79:
        
        case 80:
        
        case 81:
        
        case 82:
        
        case 83:
        
        case 84:
        
        case 85:
        
        case 86:
        
        case 87:
        
        case 88:
        
        case 89:
        
        case 90:
        
        case 91:
        
        case 92:
        
        case 93:
        
        case 94:
        
        case 95:
        
        case 96:
        
        case 97:
        
        case 98:
        
        case 99:
        
        case 100:
        
        case 101:
        
        case 102:
        
        case 103:
        
        case 104:
        
        case 105:
        
        case 106:
        
        case 107:
        
        case 108:
        
        case 109:
        
        case 110:
        
        case 111:
        
        case 112:
        
        case 113:
        
        case 114:
        
        case 115:
        
        case 116:
        
        case 117:
        
        case 118:
        
        case 119:
        
        case 120:
        
        case 121:
        
        case 122:
        
        case 123:
        
        case 124:
        
        case 125:
        
        case 126:
        
        case 127:
        
        case 128:
        
        case 129:
        
        case 130:
        
        case 131:
        
        case 132:
        
        case 133:
        
        case 134:
        
        case 135:
        
        case 136:
        
        case 137:
        
        case 138:
        
        case 139:
        
        case 140:
        
        case 141:
        
        case 142:
        
        case 143:
        
        case 144:
        
        case 145:
        
        case 146:
        
        case 147:
        
        case 148:
        
        case 149:
        
        case 150:
        
        case 151:
        
        case 152:
        
        case 153:
        
        case 154:
        
        case 155:
        
        case 156:
        
        case 157:
        
        case 158:
        
        case 159:
        
        case 160:
        
        case 161:
        
        case 162:
        
        case 163:
        
        case 164:
        
        case 165:
        
        case 166:
        
        case 167:
        
        case 168:
        
        case 169:
        
        case 170:
        
        case 171:
        
        case 172:
        
        case 173:
        
        case 174:
        
        case 175:
        
        case 176:
        
        case 177:
        
        case 178:
        
        case 179:
        
        case 180:
        
        case 181:
        
        case 182:
        
        case 183:
        
        case 184:
        
        case 185:
        
        case 186:
        
        case 187:
        
        case 188:
        
        case 189:
        
        case 190:
        
        case 191:
        
        case 192:
        
        case 193:
        
        case 194:
        
        case 195:
        
        case 196:
        
        case 197:
        
        case 198:
        
        case 199:
        
        case 200:
        
        case 201:
        
        case 202:
        
        case 203:
        
        case 204:
        
        case 205:
        
        case 206:
        
        case 207:
        
        case 208:
        
        case 209:
        
        case 210:
        
        case 211:
        
        case 212:
        
        case 213:
        
        case 214:
        
        case 215:
        
        case 216:
        
        case 217:
        
        case 218:
        
        case 219:
        
        case 220:
        
        case 221:
        
        case 222:
        
        case 223:
        
        case 224:
        
        case 225:
        
        case 226:
        
        case 227:
        
        case 228:
        
        case 229:
        
        case 230:
        
        case 231:
        
        case 232:
        
        case 233:
        
        case 234:
        
        case 235:
        
        case 236:
        
        case 237:
        
        case 238:
        
        case 239:
        
        case 240:
        
        case 241:
        
        case 242:
        
        case 243:
        
        case 244:
        
        case 245:
        
        case 246:
        
        case 247:
        
        case 248:
        
        case 249:
        
        case 250:
        
        case 251:
        
        case 252:
        
        case 253:
        
        case 254:
        
        default:
          break;
      } 
      char c = '';
      int j = (paramInt2 & 0xFF) - c;
      if (j < 0)
        j += 256; 
      int k = ((paramInt2 & 0xFFFF) >>> 8) - c;
      if (k < 0)
        k += 256; 
      for (byte b = 0; b < arrayOfChar.length; b++) {
        int m = b % 2;
        if (m == 0) {
          arrayOfChar[b] = (char)(arrayOfChar[b] ^ j);
          j = ((j >>> 3 | j << 5) ^ arrayOfChar[b]) & 0xFF;
        } else {
          arrayOfChar[b] = (char)(arrayOfChar[b] ^ k);
          k = ((k >>> 3 | k << 5) ^ arrayOfChar[b]) & 0xFF;
        } 
      } 
      b[i] = (new String(arrayOfChar)).intern();
    } 
    return b[i];
  }
}


/* Location:              C:\Program Files\BurpSuitePro\burpsuite_pro.jar!\burp\Zera.class
 * Java compiler version: 21 (65.0)
 * JD-Core Version:       1.1.3
 */