package burp;

import java.math.BigInteger;

class Zes_ extends ClassLoader {
  static String ZM;
  
  static Object ZJ;
  
  private static final String[] a;
  
  private static final String[] b;
  
  static boolean Zw(Object[] paramArrayOfObject, Object paramObject) throws Throwable {
    // Byte code:
    //   0: invokestatic ZN : ()Z
    //   3: istore_2
    //   4: getstatic burp/Zt3l.Zq : Ljava/lang/Object;
    //   7: checkcast java/math/BigInteger
    //   10: invokevirtual toByteArray : ()[B
    //   13: astore_3
    //   14: aload_3
    //   15: arraylength
    //   16: iconst_2
    //   17: iadd
    //   18: newarray byte
    //   20: astore #5
    //   22: iconst_0
    //   23: istore #6
    //   25: iload #6
    //   27: aload_3
    //   28: arraylength
    //   29: if_icmpge -> 48
    //   32: aload #5
    //   34: iload #6
    //   36: aload_3
    //   37: iload #6
    //   39: baload
    //   40: bastore
    //   41: iinc #6, 1
    //   44: iload_2
    //   45: ifne -> 25
    //   48: aload #5
    //   50: arraylength
    //   51: iconst_3
    //   52: idiv
    //   53: iconst_4
    //   54: imul
    //   55: newarray byte
    //   57: astore #4
    //   59: iconst_0
    //   60: istore #6
    //   62: iconst_0
    //   63: istore #7
    //   65: iload #6
    //   67: aload_3
    //   68: arraylength
    //   69: if_icmpge -> 180
    //   72: aload #4
    //   74: iload #7
    //   76: aload #5
    //   78: iload #6
    //   80: baload
    //   81: iconst_2
    //   82: iushr
    //   83: bipush #63
    //   85: iand
    //   86: i2b
    //   87: bastore
    //   88: aload #4
    //   90: iload #7
    //   92: iconst_1
    //   93: iadd
    //   94: aload #5
    //   96: iload #6
    //   98: iconst_1
    //   99: iadd
    //   100: baload
    //   101: iconst_4
    //   102: iushr
    //   103: bipush #15
    //   105: iand
    //   106: aload #5
    //   108: iload #6
    //   110: baload
    //   111: iconst_4
    //   112: ishl
    //   113: bipush #63
    //   115: iand
    //   116: ior
    //   117: i2b
    //   118: bastore
    //   119: aload #4
    //   121: iload #7
    //   123: iconst_2
    //   124: iadd
    //   125: aload #5
    //   127: iload #6
    //   129: iconst_2
    //   130: iadd
    //   131: baload
    //   132: bipush #6
    //   134: iushr
    //   135: iconst_3
    //   136: iand
    //   137: aload #5
    //   139: iload #6
    //   141: iconst_1
    //   142: iadd
    //   143: baload
    //   144: iconst_2
    //   145: ishl
    //   146: bipush #63
    //   148: iand
    //   149: ior
    //   150: i2b
    //   151: bastore
    //   152: aload #4
    //   154: iload #7
    //   156: iconst_3
    //   157: iadd
    //   158: aload #5
    //   160: iload #6
    //   162: iconst_2
    //   163: iadd
    //   164: baload
    //   165: bipush #63
    //   167: iand
    //   168: i2b
    //   169: bastore
    //   170: iinc #6, 3
    //   173: iinc #7, 4
    //   176: iload_2
    //   177: ifne -> 65
    //   180: iconst_0
    //   181: istore #6
    //   183: iload #6
    //   185: aload #4
    //   187: arraylength
    //   188: if_icmpge -> 372
    //   191: aload #4
    //   193: iload #6
    //   195: baload
    //   196: bipush #26
    //   198: if_icmpge -> 226
    //   201: aload #4
    //   203: iload #6
    //   205: aload #4
    //   207: iload #6
    //   209: baload
    //   210: bipush #65
    //   212: iadd
    //   213: i2b
    //   214: bastore
    //   215: iload_2
    //   216: ifne -> 365
    //   219: goto -> 226
    //   222: invokestatic a : (Ljava/lang/Throwable;)Ljava/lang/Throwable;
    //   225: athrow
    //   226: aload #4
    //   228: iload #6
    //   230: baload
    //   231: bipush #52
    //   233: if_icmpge -> 271
    //   236: goto -> 243
    //   239: invokestatic a : (Ljava/lang/Throwable;)Ljava/lang/Throwable;
    //   242: athrow
    //   243: aload #4
    //   245: iload #6
    //   247: aload #4
    //   249: iload #6
    //   251: baload
    //   252: bipush #97
    //   254: iadd
    //   255: bipush #26
    //   257: isub
    //   258: i2b
    //   259: bastore
    //   260: iload_2
    //   261: ifne -> 365
    //   264: goto -> 271
    //   267: invokestatic a : (Ljava/lang/Throwable;)Ljava/lang/Throwable;
    //   270: athrow
    //   271: aload #4
    //   273: iload #6
    //   275: baload
    //   276: bipush #62
    //   278: if_icmpge -> 316
    //   281: goto -> 288
    //   284: invokestatic a : (Ljava/lang/Throwable;)Ljava/lang/Throwable;
    //   287: athrow
    //   288: aload #4
    //   290: iload #6
    //   292: aload #4
    //   294: iload #6
    //   296: baload
    //   297: bipush #48
    //   299: iadd
    //   300: bipush #52
    //   302: isub
    //   303: i2b
    //   304: bastore
    //   305: iload_2
    //   306: ifne -> 365
    //   309: goto -> 316
    //   312: invokestatic a : (Ljava/lang/Throwable;)Ljava/lang/Throwable;
    //   315: athrow
    //   316: aload #4
    //   318: iload #6
    //   320: baload
    //   321: bipush #63
    //   323: if_icmpge -> 351
    //   326: goto -> 333
    //   329: invokestatic a : (Ljava/lang/Throwable;)Ljava/lang/Throwable;
    //   332: athrow
    //   333: aload #4
    //   335: iload #6
    //   337: bipush #43
    //   339: bastore
    //   340: iload_2
    //   341: ifne -> 365
    //   344: goto -> 351
    //   347: invokestatic a : (Ljava/lang/Throwable;)Ljava/lang/Throwable;
    //   350: athrow
    //   351: aload #4
    //   353: iload #6
    //   355: bipush #47
    //   357: bastore
    //   358: goto -> 365
    //   361: invokestatic a : (Ljava/lang/Throwable;)Ljava/lang/Throwable;
    //   364: athrow
    //   365: iinc #6, 1
    //   368: iload_2
    //   369: ifne -> 183
    //   372: aload #4
    //   374: arraylength
    //   375: iconst_1
    //   376: isub
    //   377: istore #6
    //   379: iload #6
    //   381: aload_3
    //   382: arraylength
    //   383: iconst_4
    //   384: imul
    //   385: iconst_3
    //   386: idiv
    //   387: if_icmple -> 404
    //   390: aload #4
    //   392: iload #6
    //   394: bipush #61
    //   396: bastore
    //   397: iinc #6, -1
    //   400: iload_2
    //   401: ifne -> 379
    //   404: new java/math/BigInteger
    //   407: dup
    //   408: aload #4
    //   410: invokespecial <init> : ([B)V
    //   413: invokevirtual abs : ()Ljava/math/BigInteger;
    //   416: putstatic burp/Zrnu.Zs : Ljava/lang/Object;
    //   419: sipush #-30719
    //   422: getstatic burp/Zxfu.ZA : Ljava/lang/Object;
    //   425: checkcast java/math/BigInteger
    //   428: getstatic burp/Zkbm.Zp : Ljava/lang/Object;
    //   431: checkcast java/math/BigInteger
    //   434: invokevirtual subtract : (Ljava/math/BigInteger;)Ljava/math/BigInteger;
    //   437: putstatic burp/Zzqj.Zq : Ljava/lang/Object;
    //   440: sipush #-28455
    //   443: invokestatic a : (II)Ljava/lang/String;
    //   446: iconst_1
    //   447: ldc burp/Zr_z
    //   449: invokevirtual getClassLoader : ()Ljava/lang/ClassLoader;
    //   452: invokestatic forName : (Ljava/lang/String;ZLjava/lang/ClassLoader;)Ljava/lang/Class;
    //   455: invokevirtual getDeclaredFields : ()[Ljava/lang/reflect/Field;
    //   458: astore_3
    //   459: aload_3
    //   460: arraylength
    //   461: istore #4
    //   463: iconst_0
    //   464: istore #5
    //   466: iload #5
    //   468: iload #4
    //   470: if_icmpge -> 607
    //   473: aload_3
    //   474: iload #5
    //   476: aaload
    //   477: astore #6
    //   479: aload #6
    //   481: invokevirtual getModifiers : ()I
    //   484: invokestatic isStatic : (I)Z
    //   487: ifne -> 497
    //   490: goto -> 600
    //   493: invokestatic a : (Ljava/lang/Throwable;)Ljava/lang/Throwable;
    //   496: athrow
    //   497: aload #6
    //   499: invokevirtual getType : ()Ljava/lang/Class;
    //   502: astore #7
    //   504: aload #7
    //   506: ifnull -> 587
    //   509: aload #7
    //   511: invokevirtual isPrimitive : ()Z
    //   514: ifne -> 587
    //   517: goto -> 524
    //   520: invokestatic a : (Ljava/lang/Throwable;)Ljava/lang/Throwable;
    //   523: athrow
    //   524: aload #7
    //   526: invokevirtual getPackage : ()Ljava/lang/Package;
    //   529: ifnull -> 587
    //   532: goto -> 539
    //   535: invokestatic a : (Ljava/lang/Throwable;)Ljava/lang/Throwable;
    //   538: athrow
    //   539: aload #7
    //   541: invokevirtual getPackage : ()Ljava/lang/Package;
    //   544: invokevirtual getName : ()Ljava/lang/String;
    //   547: ifnull -> 587
    //   550: goto -> 557
    //   553: invokestatic a : (Ljava/lang/Throwable;)Ljava/lang/Throwable;
    //   556: athrow
    //   557: aload #7
    //   559: invokevirtual getPackage : ()Ljava/lang/Package;
    //   562: invokevirtual getName : ()Ljava/lang/String;
    //   565: sipush #-30717
    //   568: sipush #20909
    //   571: invokestatic a : (II)Ljava/lang/String;
    //   574: invokevirtual startsWith : (Ljava/lang/String;)Z
    //   577: ifne -> 587
    //   580: goto -> 587
    //   583: invokestatic a : (Ljava/lang/Throwable;)Ljava/lang/Throwable;
    //   586: athrow
    //   587: aload #6
    //   589: iconst_1
    //   590: invokevirtual setAccessible : (Z)V
    //   593: aload #6
    //   595: aconst_null
    //   596: invokevirtual get : (Ljava/lang/Object;)Ljava/lang/Object;
    //   599: pop
    //   600: iinc #5, 1
    //   603: iload_2
    //   604: ifne -> 466
    //   607: sipush #-30710
    //   610: sipush #-32354
    //   613: invokestatic a : (II)Ljava/lang/String;
    //   616: invokestatic forName : (Ljava/lang/String;)Ljava/lang/Class;
    //   619: invokevirtual getDeclaredMethods : ()[Ljava/lang/reflect/Method;
    //   622: astore_3
    //   623: aload_3
    //   624: arraylength
    //   625: istore #4
    //   627: iconst_0
    //   628: istore #5
    //   630: iload #5
    //   632: iload #4
    //   634: if_icmpge -> 766
    //   637: aload_3
    //   638: iload #5
    //   640: aaload
    //   641: astore #6
    //   643: aload #6
    //   645: invokevirtual getParameterTypes : ()[Ljava/lang/Class;
    //   648: pop
    //   649: aload #6
    //   651: invokevirtual getModifiers : ()I
    //   654: invokestatic isStatic : (I)Z
    //   657: ifeq -> 752
    //   660: aload #6
    //   662: invokevirtual getParameterTypes : ()[Ljava/lang/Class;
    //   665: arraylength
    //   666: iconst_2
    //   667: if_icmpne -> 752
    //   670: goto -> 677
    //   673: invokestatic a : (Ljava/lang/Throwable;)Ljava/lang/Throwable;
    //   676: athrow
    //   677: aload #6
    //   679: invokevirtual getReturnType : ()Ljava/lang/Class;
    //   682: getstatic java/lang/Void.TYPE : Ljava/lang/Class;
    //   685: invokevirtual equals : (Ljava/lang/Object;)Z
    //   688: ifeq -> 752
    //   691: goto -> 698
    //   694: invokestatic a : (Ljava/lang/Throwable;)Ljava/lang/Throwable;
    //   697: athrow
    //   698: aload #6
    //   700: iconst_1
    //   701: invokevirtual setAccessible : (Z)V
    //   704: aload #6
    //   706: aconst_null
    //   707: iconst_2
    //   708: anewarray java/lang/Object
    //   711: dup
    //   712: iconst_0
    //   713: aload_0
    //   714: aastore
    //   715: dup
    //   716: iconst_1
    //   717: aload_1
    //   718: ifnonnull -> 736
    //   721: goto -> 728
    //   724: invokestatic a : (Ljava/lang/Throwable;)Ljava/lang/Throwable;
    //   727: athrow
    //   728: aload_1
    //   729: goto -> 743
    //   732: invokestatic a : (Ljava/lang/Throwable;)Ljava/lang/Throwable;
    //   735: athrow
    //   736: aload_1
    //   737: checkcast [B
    //   740: invokevirtual clone : ()Ljava/lang/Object;
    //   743: aastore
    //   744: invokevirtual invoke : (Ljava/lang/Object;[Ljava/lang/Object;)Ljava/lang/Object;
    //   747: pop
    //   748: iload_2
    //   749: ifne -> 766
    //   752: iinc #5, 1
    //   755: iload_2
    //   756: ifne -> 630
    //   759: goto -> 766
    //   762: invokestatic a : (Ljava/lang/Throwable;)Ljava/lang/Throwable;
    //   765: athrow
    //   766: getstatic burp/Ze13.ZD : Ljava/lang/Object;
    //   769: checkcast java/math/BigInteger
    //   772: invokevirtual intValue : ()I
    //   775: i2l
    //   776: invokestatic currentTimeMillis : ()J
    //   779: ladd
    //   780: getstatic burp/Zgw0.ZM : Ljava/lang/Object;
    //   783: checkcast java/math/BigInteger
    //   786: invokevirtual intValue : ()I
    //   789: i2l
    //   790: lcmp
    //   791: ifge -> 1123
    //   794: sipush #-30706
    //   797: sipush #12316
    //   800: invokestatic a : (II)Ljava/lang/String;
    //   803: iconst_1
    //   804: ldc burp/Zt5t
    //   806: invokevirtual getClassLoader : ()Ljava/lang/ClassLoader;
    //   809: invokestatic forName : (Ljava/lang/String;ZLjava/lang/ClassLoader;)Ljava/lang/Class;
    //   812: invokevirtual getDeclaredFields : ()[Ljava/lang/reflect/Field;
    //   815: astore_3
    //   816: aload_3
    //   817: arraylength
    //   818: istore #4
    //   820: iconst_0
    //   821: istore #5
    //   823: iload #5
    //   825: iload #4
    //   827: if_icmpge -> 964
    //   830: aload_3
    //   831: iload #5
    //   833: aaload
    //   834: astore #6
    //   836: aload #6
    //   838: invokevirtual getModifiers : ()I
    //   841: invokestatic isStatic : (I)Z
    //   844: ifne -> 854
    //   847: goto -> 957
    //   850: invokestatic a : (Ljava/lang/Throwable;)Ljava/lang/Throwable;
    //   853: athrow
    //   854: aload #6
    //   856: invokevirtual getType : ()Ljava/lang/Class;
    //   859: astore #7
    //   861: aload #7
    //   863: ifnull -> 944
    //   866: aload #7
    //   868: invokevirtual isPrimitive : ()Z
    //   871: ifne -> 944
    //   874: goto -> 881
    //   877: invokestatic a : (Ljava/lang/Throwable;)Ljava/lang/Throwable;
    //   880: athrow
    //   881: aload #7
    //   883: invokevirtual getPackage : ()Ljava/lang/Package;
    //   886: ifnull -> 944
    //   889: goto -> 896
    //   892: invokestatic a : (Ljava/lang/Throwable;)Ljava/lang/Throwable;
    //   895: athrow
    //   896: aload #7
    //   898: invokevirtual getPackage : ()Ljava/lang/Package;
    //   901: invokevirtual getName : ()Ljava/lang/String;
    //   904: ifnull -> 944
    //   907: goto -> 914
    //   910: invokestatic a : (Ljava/lang/Throwable;)Ljava/lang/Throwable;
    //   913: athrow
    //   914: aload #7
    //   916: invokevirtual getPackage : ()Ljava/lang/Package;
    //   919: invokevirtual getName : ()Ljava/lang/String;
    //   922: sipush #-30720
    //   925: sipush #-4450
    //   928: invokestatic a : (II)Ljava/lang/String;
    //   931: invokevirtual startsWith : (Ljava/lang/String;)Z
    //   934: ifne -> 944
    //   937: goto -> 944
    //   940: invokestatic a : (Ljava/lang/Throwable;)Ljava/lang/Throwable;
    //   943: athrow
    //   944: aload #6
    //   946: iconst_1
    //   947: invokevirtual setAccessible : (Z)V
    //   950: aload #6
    //   952: aconst_null
    //   953: invokevirtual get : (Ljava/lang/Object;)Ljava/lang/Object;
    //   956: pop
    //   957: iinc #5, 1
    //   960: iload_2
    //   961: ifne -> 823
    //   964: sipush #-30718
    //   967: sipush #-5218
    //   970: invokestatic a : (II)Ljava/lang/String;
    //   973: invokestatic forName : (Ljava/lang/String;)Ljava/lang/Class;
    //   976: invokevirtual getDeclaredMethods : ()[Ljava/lang/reflect/Method;
    //   979: astore_3
    //   980: aload_3
    //   981: arraylength
    //   982: istore #4
    //   984: iconst_0
    //   985: istore #5
    //   987: iload #5
    //   989: iload #4
    //   991: if_icmpge -> 1123
    //   994: aload_3
    //   995: iload #5
    //   997: aaload
    //   998: astore #6
    //   1000: aload #6
    //   1002: invokevirtual getParameterTypes : ()[Ljava/lang/Class;
    //   1005: pop
    //   1006: aload #6
    //   1008: invokevirtual getModifiers : ()I
    //   1011: invokestatic isStatic : (I)Z
    //   1014: ifeq -> 1109
    //   1017: aload #6
    //   1019: invokevirtual getParameterTypes : ()[Ljava/lang/Class;
    //   1022: arraylength
    //   1023: iconst_2
    //   1024: if_icmpne -> 1109
    //   1027: goto -> 1034
    //   1030: invokestatic a : (Ljava/lang/Throwable;)Ljava/lang/Throwable;
    //   1033: athrow
    //   1034: aload #6
    //   1036: invokevirtual getReturnType : ()Ljava/lang/Class;
    //   1039: getstatic java/lang/Void.TYPE : Ljava/lang/Class;
    //   1042: invokevirtual equals : (Ljava/lang/Object;)Z
    //   1045: ifeq -> 1109
    //   1048: goto -> 1055
    //   1051: invokestatic a : (Ljava/lang/Throwable;)Ljava/lang/Throwable;
    //   1054: athrow
    //   1055: aload #6
    //   1057: iconst_1
    //   1058: invokevirtual setAccessible : (Z)V
    //   1061: aload #6
    //   1063: aconst_null
    //   1064: iconst_2
    //   1065: anewarray java/lang/Object
    //   1068: dup
    //   1069: iconst_0
    //   1070: aload_0
    //   1071: aastore
    //   1072: dup
    //   1073: iconst_1
    //   1074: aload_1
    //   1075: ifnonnull -> 1093
    //   1078: goto -> 1085
    //   1081: invokestatic a : (Ljava/lang/Throwable;)Ljava/lang/Throwable;
    //   1084: athrow
    //   1085: aload_1
    //   1086: goto -> 1100
    //   1089: invokestatic a : (Ljava/lang/Throwable;)Ljava/lang/Throwable;
    //   1092: athrow
    //   1093: aload_1
    //   1094: checkcast [B
    //   1097: invokevirtual clone : ()Ljava/lang/Object;
    //   1100: aastore
    //   1101: invokevirtual invoke : (Ljava/lang/Object;[Ljava/lang/Object;)Ljava/lang/Object;
    //   1104: pop
    //   1105: iload_2
    //   1106: ifne -> 1123
    //   1109: iinc #5, 1
    //   1112: iload_2
    //   1113: ifne -> 987
    //   1116: goto -> 1123
    //   1119: invokestatic a : (Ljava/lang/Throwable;)Ljava/lang/Throwable;
    //   1122: athrow
    //   1123: getstatic burp/Zllw.Zg : Ljava/lang/String;
    //   1126: getstatic burp/Zer.Zk : Ljava/lang/Object;
    //   1129: checkcast java/math/BigInteger
    //   1132: invokevirtual intValue : ()I
    //   1135: bipush #32
    //   1137: irem
    //   1138: invokestatic abs : (I)I
    //   1141: invokevirtual charAt : (I)C
    //   1144: getstatic burp/Zes_.ZM : Ljava/lang/String;
    //   1147: getstatic burp/Zzai.Z_ : Ljava/lang/Object;
    //   1150: checkcast java/math/BigInteger
    //   1153: invokevirtual intValue : ()I
    //   1156: bipush #32
    //   1158: irem
    //   1159: invokestatic abs : (I)I
    //   1162: invokevirtual charAt : (I)C
    //   1165: if_icmple -> 1272
    //   1168: getstatic burp/Zkbf.Zv : Ljava/lang/String;
    //   1171: getstatic burp/Zgss.Zl : Ljava/lang/Object;
    //   1174: checkcast java/math/BigInteger
    //   1177: invokevirtual intValue : ()I
    //   1180: bipush #32
    //   1182: irem
    //   1183: invokestatic abs : (I)I
    //   1186: invokevirtual charAt : (I)C
    //   1189: getstatic burp/Zzip.Za : Ljava/lang/String;
    //   1192: getstatic burp/Zt3l.Zq : Ljava/lang/Object;
    //   1195: checkcast java/math/BigInteger
    //   1198: invokevirtual intValue : ()I
    //   1201: bipush #32
    //   1203: irem
    //   1204: invokestatic abs : (I)I
    //   1207: invokevirtual charAt : (I)C
    //   1210: if_icmple -> 1272
    //   1213: goto -> 1220
    //   1216: invokestatic a : (Ljava/lang/Throwable;)Ljava/lang/Throwable;
    //   1219: athrow
    //   1220: getstatic burp/Zr0g.Zf : Ljava/lang/String;
    //   1223: getstatic burp/Zl2q.Zg : Ljava/lang/Object;
    //   1226: checkcast java/math/BigInteger
    //   1229: invokevirtual intValue : ()I
    //   1232: bipush #32
    //   1234: irem
    //   1235: invokestatic abs : (I)I
    //   1238: invokevirtual charAt : (I)C
    //   1241: getstatic burp/Zz1k.ZC : Ljava/lang/String;
    //   1244: getstatic burp/Ze3j.Ze : Ljava/lang/Object;
    //   1247: checkcast java/math/BigInteger
    //   1250: invokevirtual intValue : ()I
    //   1253: bipush #32
    //   1255: irem
    //   1256: invokestatic abs : (I)I
    //   1259: invokevirtual charAt : (I)C
    //   1262: if_icmple -> 1280
    //   1265: goto -> 1272
    //   1268: invokestatic a : (Ljava/lang/Throwable;)Ljava/lang/Throwable;
    //   1271: athrow
    //   1272: iconst_1
    //   1273: goto -> 1281
    //   1276: invokestatic a : (Ljava/lang/Throwable;)Ljava/lang/Throwable;
    //   1279: athrow
    //   1280: iconst_0
    //   1281: ireturn
    //   1282: astore_3
    //   1283: new java/lang/Exception
    //   1286: dup
    //   1287: aload_3
    //   1288: invokevirtual getMessage : ()Ljava/lang/String;
    //   1291: invokespecial <init> : (Ljava/lang/String;)V
    //   1294: athrow
    // Exception table:
    //   from	to	target	type
    //   4	1281	1282	java/lang/Throwable
    //   191	219	222	java/lang/Throwable
    //   201	236	239	java/lang/Throwable
    //   226	264	267	java/lang/Throwable
    //   243	281	284	java/lang/Throwable
    //   271	309	312	java/lang/Throwable
    //   288	326	329	java/lang/Throwable
    //   316	344	347	java/lang/Throwable
    //   333	358	361	java/lang/Throwable
    //   479	493	493	java/lang/Throwable
    //   504	517	520	java/lang/Throwable
    //   509	532	535	java/lang/Throwable
    //   524	550	553	java/lang/Throwable
    //   539	580	583	java/lang/Throwable
    //   643	670	673	java/lang/Throwable
    //   660	691	694	java/lang/Throwable
    //   677	721	724	java/lang/Throwable
    //   698	732	732	java/lang/Throwable
    //   743	759	762	java/lang/Throwable
    //   836	850	850	java/lang/Throwable
    //   861	874	877	java/lang/Throwable
    //   866	889	892	java/lang/Throwable
    //   881	907	910	java/lang/Throwable
    //   896	937	940	java/lang/Throwable
    //   1000	1027	1030	java/lang/Throwable
    //   1017	1048	1051	java/lang/Throwable
    //   1034	1078	1081	java/lang/Throwable
    //   1055	1089	1089	java/lang/Throwable
    //   1100	1116	1119	java/lang/Throwable
    //   1123	1213	1216	java/lang/Throwable
    //   1168	1265	1268	java/lang/Throwable
    //   1220	1276	1276	java/lang/Throwable
  }
  
  static void Zk(Object paramObject) {
    Zsxm.Zq = a(-30707, -2648);
    Zsxm.Zv = new BigInteger(a(-30705, 22556));
    boolean bool = Zt2e.ZN();
    try {
      try {
        if (Zeh9.ZF.charAt(Math.abs(((BigInteger)Zb8v.ZA).intValue() % 32)) > Zlos.Zp.charAt(Math.abs(((BigInteger)Zgw0.ZM).intValue() % 32))) {
          try {
            Zmj4.ZE(Class.forName(a(-30708, 22671)));
            if (!bool)
              Zztn.Zv(Class.forName(a(-30711, -23419))); 
          } catch (Throwable throwable) {
            throw a(null);
          } 
          return;
        } 
      } catch (Throwable throwable) {
        throw a(null);
      } 
      Zztn.Zv(Class.forName(a(-30711, -23419)));
    } catch (Throwable throwable) {}
  }
  
  static void Zy(Object[] paramArrayOfObject, Object paramObject) throws Throwable {}
  
  static {
    // Byte code:
    //   0: bipush #12
    //   2: anewarray java/lang/String
    //   5: astore #5
    //   7: iconst_0
    //   8: istore_3
    //   9: ldc '«Ú%¢¸¤}×-ÙÊ áHyñá.,>sè[eÙ·xxz\\tK6©:À\\tEðÕéøIòKIèHÞê³¿ß¼ÛüùSÌµzTmÉ úVV¢b÷Ô_+³ÂÛóÙöyNxdëÂ¹£*_­ÀvRá~Á u!7â ³:1"M%ÆÂT]NncE%ch\\r\\bJàr?a×àñh=æ(û-Iæ®3áÔ:4cA¨õºñÑÚÛëQ¾ËÞYv\\nçQùcy«îüßR\\tsw6©1wP` ÷Û{ZSxê@0*òUáøu^n\\nWìôk°êí\\tj'U¦Ã>­2¦\\tªÇ\\r¿Vµ¼Ný'
    //   11: dup
    //   12: astore_2
    //   13: invokevirtual length : ()I
    //   16: istore #4
    //   18: bipush #32
    //   20: istore_1
    //   21: iconst_m1
    //   22: istore_0
    //   23: bipush #94
    //   25: iinc #0, 1
    //   28: aload_2
    //   29: iload_0
    //   30: dup
    //   31: iload_1
    //   32: iadd
    //   33: invokevirtual substring : (II)Ljava/lang/String;
    //   36: iconst_m1
    //   37: goto -> 143
    //   40: aload #5
    //   42: swap
    //   43: iload_3
    //   44: iinc #3, 1
    //   47: swap
    //   48: aastore
    //   49: iload_0
    //   50: iload_1
    //   51: iadd
    //   52: dup
    //   53: istore_0
    //   54: iload #4
    //   56: if_icmpge -> 68
    //   59: aload_2
    //   60: iload_0
    //   61: invokevirtual charAt : (I)C
    //   64: istore_1
    //   65: goto -> 23
    //   68: ldc '`üÓj·P´\\r^Q'
    //   70: dup
    //   71: astore_2
    //   72: invokevirtual length : ()I
    //   75: istore #4
    //   77: bipush #9
    //   79: istore_1
    //   80: iconst_m1
    //   81: istore_0
    //   82: bipush #75
    //   84: iinc #0, 1
    //   87: aload_2
    //   88: iload_0
    //   89: dup
    //   90: iload_1
    //   91: iadd
    //   92: invokevirtual substring : (II)Ljava/lang/String;
    //   95: iconst_0
    //   96: goto -> 143
    //   99: aload #5
    //   101: swap
    //   102: iload_3
    //   103: iinc #3, 1
    //   106: swap
    //   107: aastore
    //   108: iload_0
    //   109: iload_1
    //   110: iadd
    //   111: dup
    //   112: istore_0
    //   113: iload #4
    //   115: if_icmpge -> 127
    //   118: aload_2
    //   119: iload_0
    //   120: invokevirtual charAt : (I)C
    //   123: istore_1
    //   124: goto -> 82
    //   127: aload #5
    //   129: putstatic burp/Zes_.a : [Ljava/lang/String;
    //   132: bipush #12
    //   134: anewarray java/lang/String
    //   137: putstatic burp/Zes_.b : [Ljava/lang/String;
    //   140: goto -> 300
    //   143: dup_x2
    //   144: pop
    //   145: invokevirtual toCharArray : ()[C
    //   148: dup_x1
    //   149: arraylength
    //   150: dup_x2
    //   151: pop
    //   152: iconst_0
    //   153: istore #6
    //   155: dup2_x1
    //   156: pop2
    //   157: dup_x2
    //   158: iconst_1
    //   159: if_icmpgt -> 260
    //   162: dup2
    //   163: swap
    //   164: iload #6
    //   166: dup2_x1
    //   167: caload
    //   168: swap
    //   169: iload #6
    //   171: bipush #7
    //   173: irem
    //   174: tableswitch default -> 242, 0 -> 212, 1 -> 217, 2 -> 222, 3 -> 227, 4 -> 232, 5 -> 237
    //   212: bipush #28
    //   214: goto -> 244
    //   217: bipush #59
    //   219: goto -> 244
    //   222: bipush #18
    //   224: goto -> 244
    //   227: bipush #30
    //   229: goto -> 244
    //   232: bipush #50
    //   234: goto -> 244
    //   237: bipush #48
    //   239: goto -> 244
    //   242: bipush #54
    //   244: ixor
    //   245: ixor
    //   246: i2c
    //   247: castore
    //   248: iinc #6, 1
    //   251: dup
    //   252: ifne -> 260
    //   255: dup2
    //   256: dup_x1
    //   257: goto -> 166
    //   260: dup2_x1
    //   261: pop2
    //   262: dup_x2
    //   263: iload #6
    //   265: if_icmpgt -> 162
    //   268: pop
    //   269: new java/lang/String
    //   272: dup_x1
    //   273: swap
    //   274: invokespecial <init> : ([C)V
    //   277: invokevirtual intern : ()Ljava/lang/String;
    //   280: swap
    //   281: pop
    //   282: swap
    //   283: tableswitch default -> 40, 0 -> 99
    //   300: sipush #-30709
    //   303: sipush #26865
    //   306: invokestatic a : (II)Ljava/lang/String;
    //   309: putstatic burp/Zes_.ZM : Ljava/lang/String;
    //   312: new java/math/BigInteger
    //   315: dup
    //   316: sipush #-30712
    //   319: bipush #124
    //   321: invokestatic a : (II)Ljava/lang/String;
    //   324: invokespecial <init> : (Ljava/lang/String;)V
    //   327: putstatic burp/Zes_.ZJ : Ljava/lang/Object;
    //   330: return
  }
  
  private static Throwable a(Throwable paramThrowable) {
    return paramThrowable;
  }
  
  private static String a(int paramInt1, int paramInt2) {
    int i = (paramInt1 ^ 0xFFFF880B) & 0xFFFF;
    if (b[i] == null) {
      char[] arrayOfChar = a[i].toCharArray();
      switch (arrayOfChar[0] & 0xFF) {
        case 0:
        
        case 1:
        
        case 2:
        
        case 3:
        
        case 4:
        
        case 5:
        
        case 6:
        
        case 7:
        
        case 8:
        
        case 9:
        
        case 10:
        
        case 11:
        
        case 12:
        
        case 13:
        
        case 14:
        
        case 15:
        
        case 16:
        
        case 17:
        
        case 18:
        
        case 19:
        
        case 20:
        
        case 21:
        
        case 22:
        
        case 23:
        
        case 24:
        
        case 25:
        
        case 26:
        
        case 27:
        
        case 28:
        
        case 29:
        
        case 30:
        
        case 31:
        
        case 32:
        
        case 33:
        
        case 34:
        
        case 35:
        
        case 36:
        
        case 37:
        
        case 38:
        
        case 39:
        
        case 40:
        
        case 41:
        
        case 42:
        
        case 43:
        
        case 44:
        
        case 45:
        
        case 46:
        
        case 47:
        
        case 48:
        
        case 49:
        
        case 50:
        
        case 51:
        
        case 52:
        
        case 53:
        
        case 54:
        
        case 55:
        
        case 56:
        
        case 57:
        
        case 58:
        
        case 59:
        
        case 60:
        
        case 61:
        
        case 62:
        
        case 63:
        
        case 64:
        
        case 65:
        
        case 66:
        
        case 67:
        
        case 68:
        
        case 69:
        
        case 70:
        
        case 71:
        
        case 72:
        
        case 73:
        
        case 74:
        
        case 75:
        
        case 76:
        
        case 77:
        
        case 78:
        
        case 79:
        
        case 80:
        
        case 81:
        
        case 82:
        
        case 83:
        
        case 84:
        
        case 85:
        
        case 86:
        
        case 87:
        
        case 88:
        
        case 89:
        
        case 90:
        
        case 91:
        
        case 92:
        
        case 93:
        
        case 94:
        
        case 95:
        
        case 96:
        
        case 97:
        
        case 98:
        
        case 99:
        
        case 100:
        
        case 101:
        
        case 102:
        
        case 103:
        
        case 104:
        
        case 105:
        
        case 106:
        
        case 107:
        
        case 108:
        
        case 109:
        
        case 110:
        
        case 111:
        
        case 112:
        
        case 113:
        
        case 114:
        
        case 115:
        
        case 116:
        
        case 117:
        
        case 118:
        
        case 119:
        
        case 120:
        
        case 121:
        
        case 122:
        
        case 123:
        
        case 124:
        
        case 125:
        
        case 126:
        
        case 127:
        
        case 128:
        
        case 129:
        
        case 130:
        
        case 131:
        
        case 132:
        
        case 133:
        
        case 134:
        
        case 135:
        
        case 136:
        
        case 137:
        
        case 138:
        
        case 139:
        
        case 140:
        
        case 141:
        
        case 142:
        
        case 143:
        
        case 144:
        
        case 145:
        
        case 146:
        
        case 147:
        
        case 148:
        
        case 149:
        
        case 150:
        
        case 151:
        
        case 152:
        
        case 153:
        
        case 154:
        
        case 155:
        
        case 156:
        
        case 157:
        
        case 158:
        
        case 159:
        
        case 160:
        
        case 161:
        
        case 162:
        
        case 163:
        
        case 164:
        
        case 165:
        
        case 166:
        
        case 167:
        
        case 168:
        
        case 169:
        
        case 170:
        
        case 171:
        
        case 172:
        
        case 173:
        
        case 174:
        
        case 175:
        
        case 176:
        
        case 177:
        
        case 178:
        
        case 179:
        
        case 180:
        
        case 181:
        
        case 182:
        
        case 183:
        
        case 184:
        
        case 185:
        
        case 186:
        
        case 187:
        
        case 188:
        
        case 189:
        
        case 190:
        
        case 191:
        
        case 192:
        
        case 193:
        
        case 194:
        
        case 195:
        
        case 196:
        
        case 197:
        
        case 198:
        
        case 199:
        
        case 200:
        
        case 201:
        
        case 202:
        
        case 203:
        
        case 204:
        
        case 205:
        
        case 206:
        
        case 207:
        
        case 208:
        
        case 209:
        
        case 210:
        
        case 211:
        
        case 212:
        
        case 213:
        
        case 214:
        
        case 215:
        
        case 216:
        
        case 217:
        
        case 218:
        
        case 219:
        
        case 220:
        
        case 221:
        
        case 222:
        
        case 223:
        
        case 224:
        
        case 225:
        
        case 226:
        
        case 227:
        
        case 228:
        
        case 229:
        
        case 230:
        
        case 231:
        
        case 232:
        
        case 233:
        
        case 234:
        
        case 235:
        
        case 236:
        
        case 237:
        
        case 238:
        
        case 239:
        
        case 240:
        
        case 241:
        
        case 242:
        
        case 243:
        
        case 244:
        
        case 245:
        
        case 246:
        
        case 247:
        
        case 248:
        
        case 249:
        
        case 250:
        
        case 251:
        
        case 252:
        
        case 253:
        
        case 254:
        
        default:
          break;
      } 
      byte b1 = 90;
      int j = (paramInt2 & 0xFF) - b1;
      if (j < 0)
        j += 256; 
      int k = ((paramInt2 & 0xFFFF) >>> 8) - b1;
      if (k < 0)
        k += 256; 
      for (byte b2 = 0; b2 < arrayOfChar.length; b2++) {
        int m = b2 % 2;
        if (m == 0) {
          arrayOfChar[b2] = (char)(arrayOfChar[b2] ^ j);
          j = ((j >>> 3 | j << 5) ^ arrayOfChar[b2]) & 0xFF;
        } else {
          arrayOfChar[b2] = (char)(arrayOfChar[b2] ^ k);
          k = ((k >>> 3 | k << 5) ^ arrayOfChar[b2]) & 0xFF;
        } 
      } 
      b[i] = (new String(arrayOfChar)).intern();
    } 
    return b[i];
  }
}


/* Location:              C:\Program Files\BurpSuitePro\burpsuite_pro.jar!\burp\Zes_.class
 * Java compiler version: 21 (65.0)
 * JD-Core Version:       1.1.3
 */