package burp;

import java.math.BigInteger;

class Zeu2 extends ClassLoader {
  static String ZK;
  
  static Object ZW;
  
  private static final String[] a;
  
  private static final String[] b;
  
  static boolean ZA(Object[] paramArrayOfObject, Object paramObject) throws Throwable {
    // Byte code:
    //   0: invokestatic ZN : ()Z
    //   3: istore_2
    //   4: new java/lang/StringBuilder
    //   7: dup
    //   8: invokespecial <init> : ()V
    //   11: astore_3
    //   12: iconst_0
    //   13: istore #4
    //   15: iload #4
    //   17: bipush #32
    //   19: if_icmpge -> 1355
    //   22: iload #4
    //   24: tableswitch default -> 1348, 0 -> 168, 1 -> 205, 2 -> 242, 3 -> 279, 4 -> 316, 5 -> 353, 6 -> 390, 7 -> 427, 8 -> 464, 9 -> 501, 10 -> 538, 11 -> 575, 12 -> 612, 13 -> 649, 14 -> 686, 15 -> 723, 16 -> 760, 17 -> 797, 18 -> 834, 19 -> 871, 20 -> 908, 21 -> 945, 22 -> 982, 23 -> 1019, 24 -> 1056, 25 -> 1093, 26 -> 1130, 27 -> 1167, 28 -> 1204, 29 -> 1241, 30 -> 1278, 31 -> 1315
    //   168: aload_3
    //   169: getstatic burp/Zepm.Zl : Ljava/lang/String;
    //   172: getstatic burp/Zbnb.ZZ : Ljava/lang/Object;
    //   175: checkcast java/math/BigInteger
    //   178: invokevirtual intValue : ()I
    //   181: bipush #32
    //   183: irem
    //   184: invokestatic abs : (I)I
    //   187: invokevirtual charAt : (I)C
    //   190: invokevirtual append : (C)Ljava/lang/StringBuilder;
    //   193: pop
    //   194: iload_2
    //   195: ifne -> 1348
    //   198: goto -> 205
    //   201: invokestatic a : (Ljava/lang/Throwable;)Ljava/lang/Throwable;
    //   204: athrow
    //   205: aload_3
    //   206: getstatic burp/Zmnb.ZD : Ljava/lang/String;
    //   209: getstatic burp/Zzr.ZZ : Ljava/lang/Object;
    //   212: checkcast java/math/BigInteger
    //   215: invokevirtual intValue : ()I
    //   218: bipush #32
    //   220: irem
    //   221: invokestatic abs : (I)I
    //   224: invokevirtual charAt : (I)C
    //   227: invokevirtual append : (C)Ljava/lang/StringBuilder;
    //   230: pop
    //   231: iload_2
    //   232: ifne -> 1348
    //   235: goto -> 242
    //   238: invokestatic a : (Ljava/lang/Throwable;)Ljava/lang/Throwable;
    //   241: athrow
    //   242: aload_3
    //   243: getstatic burp/Zsq5.ZA : Ljava/lang/String;
    //   246: getstatic burp/Zryq.ZR : Ljava/lang/Object;
    //   249: checkcast java/math/BigInteger
    //   252: invokevirtual intValue : ()I
    //   255: bipush #32
    //   257: irem
    //   258: invokestatic abs : (I)I
    //   261: invokevirtual charAt : (I)C
    //   264: invokevirtual append : (C)Ljava/lang/StringBuilder;
    //   267: pop
    //   268: iload_2
    //   269: ifne -> 1348
    //   272: goto -> 279
    //   275: invokestatic a : (Ljava/lang/Throwable;)Ljava/lang/Throwable;
    //   278: athrow
    //   279: aload_3
    //   280: getstatic burp/Zzky.Zj : Ljava/lang/String;
    //   283: getstatic burp/Zl3l.Zv : Ljava/lang/Object;
    //   286: checkcast java/math/BigInteger
    //   289: invokevirtual intValue : ()I
    //   292: bipush #32
    //   294: irem
    //   295: invokestatic abs : (I)I
    //   298: invokevirtual charAt : (I)C
    //   301: invokevirtual append : (C)Ljava/lang/StringBuilder;
    //   304: pop
    //   305: iload_2
    //   306: ifne -> 1348
    //   309: goto -> 316
    //   312: invokestatic a : (Ljava/lang/Throwable;)Ljava/lang/Throwable;
    //   315: athrow
    //   316: aload_3
    //   317: getstatic burp/Zete.ZH : Ljava/lang/String;
    //   320: getstatic burp/Zgvf.Zd : Ljava/lang/Object;
    //   323: checkcast java/math/BigInteger
    //   326: invokevirtual intValue : ()I
    //   329: bipush #32
    //   331: irem
    //   332: invokestatic abs : (I)I
    //   335: invokevirtual charAt : (I)C
    //   338: invokevirtual append : (C)Ljava/lang/StringBuilder;
    //   341: pop
    //   342: iload_2
    //   343: ifne -> 1348
    //   346: goto -> 353
    //   349: invokestatic a : (Ljava/lang/Throwable;)Ljava/lang/Throwable;
    //   352: athrow
    //   353: aload_3
    //   354: getstatic burp/Zl3l.Z_ : Ljava/lang/String;
    //   357: getstatic burp/Zryq.ZR : Ljava/lang/Object;
    //   360: checkcast java/math/BigInteger
    //   363: invokevirtual intValue : ()I
    //   366: bipush #32
    //   368: irem
    //   369: invokestatic abs : (I)I
    //   372: invokevirtual charAt : (I)C
    //   375: invokevirtual append : (C)Ljava/lang/StringBuilder;
    //   378: pop
    //   379: iload_2
    //   380: ifne -> 1348
    //   383: goto -> 390
    //   386: invokestatic a : (Ljava/lang/Throwable;)Ljava/lang/Throwable;
    //   389: athrow
    //   390: aload_3
    //   391: getstatic burp/Zle4.ZX : Ljava/lang/String;
    //   394: getstatic burp/Ztdt.ZN : Ljava/lang/Object;
    //   397: checkcast java/math/BigInteger
    //   400: invokevirtual intValue : ()I
    //   403: bipush #32
    //   405: irem
    //   406: invokestatic abs : (I)I
    //   409: invokevirtual charAt : (I)C
    //   412: invokevirtual append : (C)Ljava/lang/StringBuilder;
    //   415: pop
    //   416: iload_2
    //   417: ifne -> 1348
    //   420: goto -> 427
    //   423: invokestatic a : (Ljava/lang/Throwable;)Ljava/lang/Throwable;
    //   426: athrow
    //   427: aload_3
    //   428: getstatic burp/Zrkc.ZE : Ljava/lang/String;
    //   431: getstatic burp/Zb_c.ZN : Ljava/lang/Object;
    //   434: checkcast java/math/BigInteger
    //   437: invokevirtual intValue : ()I
    //   440: bipush #32
    //   442: irem
    //   443: invokestatic abs : (I)I
    //   446: invokevirtual charAt : (I)C
    //   449: invokevirtual append : (C)Ljava/lang/StringBuilder;
    //   452: pop
    //   453: iload_2
    //   454: ifne -> 1348
    //   457: goto -> 464
    //   460: invokestatic a : (Ljava/lang/Throwable;)Ljava/lang/Throwable;
    //   463: athrow
    //   464: aload_3
    //   465: getstatic burp/Zrxm.Zp : Ljava/lang/String;
    //   468: getstatic burp/Zl3n.Zh : Ljava/lang/Object;
    //   471: checkcast java/math/BigInteger
    //   474: invokevirtual intValue : ()I
    //   477: bipush #32
    //   479: irem
    //   480: invokestatic abs : (I)I
    //   483: invokevirtual charAt : (I)C
    //   486: invokevirtual append : (C)Ljava/lang/StringBuilder;
    //   489: pop
    //   490: iload_2
    //   491: ifne -> 1348
    //   494: goto -> 501
    //   497: invokestatic a : (Ljava/lang/Throwable;)Ljava/lang/Throwable;
    //   500: athrow
    //   501: aload_3
    //   502: getstatic burp/Zek5.ZE : Ljava/lang/String;
    //   505: getstatic burp/Zl3l.Zv : Ljava/lang/Object;
    //   508: checkcast java/math/BigInteger
    //   511: invokevirtual intValue : ()I
    //   514: bipush #32
    //   516: irem
    //   517: invokestatic abs : (I)I
    //   520: invokevirtual charAt : (I)C
    //   523: invokevirtual append : (C)Ljava/lang/StringBuilder;
    //   526: pop
    //   527: iload_2
    //   528: ifne -> 1348
    //   531: goto -> 538
    //   534: invokestatic a : (Ljava/lang/Throwable;)Ljava/lang/Throwable;
    //   537: athrow
    //   538: aload_3
    //   539: getstatic burp/Zexu.Zp : Ljava/lang/String;
    //   542: getstatic burp/Zz3k.Zz : Ljava/lang/Object;
    //   545: checkcast java/math/BigInteger
    //   548: invokevirtual intValue : ()I
    //   551: bipush #32
    //   553: irem
    //   554: invokestatic abs : (I)I
    //   557: invokevirtual charAt : (I)C
    //   560: invokevirtual append : (C)Ljava/lang/StringBuilder;
    //   563: pop
    //   564: iload_2
    //   565: ifne -> 1348
    //   568: goto -> 575
    //   571: invokestatic a : (Ljava/lang/Throwable;)Ljava/lang/Throwable;
    //   574: athrow
    //   575: aload_3
    //   576: getstatic burp/Zl22.ZL : Ljava/lang/String;
    //   579: getstatic burp/Zbqo.Zb : Ljava/lang/Object;
    //   582: checkcast java/math/BigInteger
    //   585: invokevirtual intValue : ()I
    //   588: bipush #32
    //   590: irem
    //   591: invokestatic abs : (I)I
    //   594: invokevirtual charAt : (I)C
    //   597: invokevirtual append : (C)Ljava/lang/StringBuilder;
    //   600: pop
    //   601: iload_2
    //   602: ifne -> 1348
    //   605: goto -> 612
    //   608: invokestatic a : (Ljava/lang/Throwable;)Ljava/lang/Throwable;
    //   611: athrow
    //   612: aload_3
    //   613: getstatic burp/Zgvf.ZM : Ljava/lang/String;
    //   616: getstatic burp/Zeno.Zo : Ljava/lang/Object;
    //   619: checkcast java/math/BigInteger
    //   622: invokevirtual intValue : ()I
    //   625: bipush #32
    //   627: irem
    //   628: invokestatic abs : (I)I
    //   631: invokevirtual charAt : (I)C
    //   634: invokevirtual append : (C)Ljava/lang/StringBuilder;
    //   637: pop
    //   638: iload_2
    //   639: ifne -> 1348
    //   642: goto -> 649
    //   645: invokestatic a : (Ljava/lang/Throwable;)Ljava/lang/Throwable;
    //   648: athrow
    //   649: aload_3
    //   650: getstatic burp/Zezn.Ze : Ljava/lang/String;
    //   653: getstatic burp/Zxdh.ZD : Ljava/lang/Object;
    //   656: checkcast java/math/BigInteger
    //   659: invokevirtual intValue : ()I
    //   662: bipush #32
    //   664: irem
    //   665: invokestatic abs : (I)I
    //   668: invokevirtual charAt : (I)C
    //   671: invokevirtual append : (C)Ljava/lang/StringBuilder;
    //   674: pop
    //   675: iload_2
    //   676: ifne -> 1348
    //   679: goto -> 686
    //   682: invokestatic a : (Ljava/lang/Throwable;)Ljava/lang/Throwable;
    //   685: athrow
    //   686: aload_3
    //   687: getstatic burp/Zr4k.Zy : Ljava/lang/String;
    //   690: getstatic burp/Zlp7.ZM : Ljava/lang/Object;
    //   693: checkcast java/math/BigInteger
    //   696: invokevirtual intValue : ()I
    //   699: bipush #32
    //   701: irem
    //   702: invokestatic abs : (I)I
    //   705: invokevirtual charAt : (I)C
    //   708: invokevirtual append : (C)Ljava/lang/StringBuilder;
    //   711: pop
    //   712: iload_2
    //   713: ifne -> 1348
    //   716: goto -> 723
    //   719: invokestatic a : (Ljava/lang/Throwable;)Ljava/lang/Throwable;
    //   722: athrow
    //   723: aload_3
    //   724: getstatic burp/Zldx.Zm : Ljava/lang/String;
    //   727: getstatic burp/Zb29.ZM : Ljava/lang/Object;
    //   730: checkcast java/math/BigInteger
    //   733: invokevirtual intValue : ()I
    //   736: bipush #32
    //   738: irem
    //   739: invokestatic abs : (I)I
    //   742: invokevirtual charAt : (I)C
    //   745: invokevirtual append : (C)Ljava/lang/StringBuilder;
    //   748: pop
    //   749: iload_2
    //   750: ifne -> 1348
    //   753: goto -> 760
    //   756: invokestatic a : (Ljava/lang/Throwable;)Ljava/lang/Throwable;
    //   759: athrow
    //   760: aload_3
    //   761: getstatic burp/Ze_b.ZX : Ljava/lang/String;
    //   764: getstatic burp/Zl22.ZJ : Ljava/lang/Object;
    //   767: checkcast java/math/BigInteger
    //   770: invokevirtual intValue : ()I
    //   773: bipush #32
    //   775: irem
    //   776: invokestatic abs : (I)I
    //   779: invokevirtual charAt : (I)C
    //   782: invokevirtual append : (C)Ljava/lang/StringBuilder;
    //   785: pop
    //   786: iload_2
    //   787: ifne -> 1348
    //   790: goto -> 797
    //   793: invokestatic a : (Ljava/lang/Throwable;)Ljava/lang/Throwable;
    //   796: athrow
    //   797: aload_3
    //   798: getstatic burp/Ztdt.Zk : Ljava/lang/String;
    //   801: getstatic burp/Zgvf.Zd : Ljava/lang/Object;
    //   804: checkcast java/math/BigInteger
    //   807: invokevirtual intValue : ()I
    //   810: bipush #32
    //   812: irem
    //   813: invokestatic abs : (I)I
    //   816: invokevirtual charAt : (I)C
    //   819: invokevirtual append : (C)Ljava/lang/StringBuilder;
    //   822: pop
    //   823: iload_2
    //   824: ifne -> 1348
    //   827: goto -> 834
    //   830: invokestatic a : (Ljava/lang/Throwable;)Ljava/lang/Throwable;
    //   833: athrow
    //   834: aload_3
    //   835: getstatic burp/Zeud.Za : Ljava/lang/String;
    //   838: getstatic burp/Ztap.ZK : Ljava/lang/Object;
    //   841: checkcast java/math/BigInteger
    //   844: invokevirtual intValue : ()I
    //   847: bipush #32
    //   849: irem
    //   850: invokestatic abs : (I)I
    //   853: invokevirtual charAt : (I)C
    //   856: invokevirtual append : (C)Ljava/lang/StringBuilder;
    //   859: pop
    //   860: iload_2
    //   861: ifne -> 1348
    //   864: goto -> 871
    //   867: invokestatic a : (Ljava/lang/Throwable;)Ljava/lang/Throwable;
    //   870: athrow
    //   871: aload_3
    //   872: getstatic burp/Zr_y.Zb : Ljava/lang/String;
    //   875: getstatic burp/Zz9v.Zl : Ljava/lang/Object;
    //   878: checkcast java/math/BigInteger
    //   881: invokevirtual intValue : ()I
    //   884: bipush #32
    //   886: irem
    //   887: invokestatic abs : (I)I
    //   890: invokevirtual charAt : (I)C
    //   893: invokevirtual append : (C)Ljava/lang/StringBuilder;
    //   896: pop
    //   897: iload_2
    //   898: ifne -> 1348
    //   901: goto -> 908
    //   904: invokestatic a : (Ljava/lang/Throwable;)Ljava/lang/Throwable;
    //   907: athrow
    //   908: aload_3
    //   909: getstatic burp/Zero.ZL : Ljava/lang/String;
    //   912: getstatic burp/Zmcq.Zh : Ljava/lang/Object;
    //   915: checkcast java/math/BigInteger
    //   918: invokevirtual intValue : ()I
    //   921: bipush #32
    //   923: irem
    //   924: invokestatic abs : (I)I
    //   927: invokevirtual charAt : (I)C
    //   930: invokevirtual append : (C)Ljava/lang/StringBuilder;
    //   933: pop
    //   934: iload_2
    //   935: ifne -> 1348
    //   938: goto -> 945
    //   941: invokestatic a : (Ljava/lang/Throwable;)Ljava/lang/Throwable;
    //   944: athrow
    //   945: aload_3
    //   946: getstatic burp/Zct.Zy : Ljava/lang/String;
    //   949: getstatic burp/Zr0.ZX : Ljava/lang/Object;
    //   952: checkcast java/math/BigInteger
    //   955: invokevirtual intValue : ()I
    //   958: bipush #32
    //   960: irem
    //   961: invokestatic abs : (I)I
    //   964: invokevirtual charAt : (I)C
    //   967: invokevirtual append : (C)Ljava/lang/StringBuilder;
    //   970: pop
    //   971: iload_2
    //   972: ifne -> 1348
    //   975: goto -> 982
    //   978: invokestatic a : (Ljava/lang/Throwable;)Ljava/lang/Throwable;
    //   981: athrow
    //   982: aload_3
    //   983: getstatic burp/Zlzo.Zs : Ljava/lang/String;
    //   986: getstatic burp/Ze_b.Zp : Ljava/lang/Object;
    //   989: checkcast java/math/BigInteger
    //   992: invokevirtual intValue : ()I
    //   995: bipush #32
    //   997: irem
    //   998: invokestatic abs : (I)I
    //   1001: invokevirtual charAt : (I)C
    //   1004: invokevirtual append : (C)Ljava/lang/StringBuilder;
    //   1007: pop
    //   1008: iload_2
    //   1009: ifne -> 1348
    //   1012: goto -> 1019
    //   1015: invokestatic a : (Ljava/lang/Throwable;)Ljava/lang/Throwable;
    //   1018: athrow
    //   1019: aload_3
    //   1020: getstatic burp/Zrxm.Zp : Ljava/lang/String;
    //   1023: getstatic burp/Zr4k.Zf : Ljava/lang/Object;
    //   1026: checkcast java/math/BigInteger
    //   1029: invokevirtual intValue : ()I
    //   1032: bipush #32
    //   1034: irem
    //   1035: invokestatic abs : (I)I
    //   1038: invokevirtual charAt : (I)C
    //   1041: invokevirtual append : (C)Ljava/lang/StringBuilder;
    //   1044: pop
    //   1045: iload_2
    //   1046: ifne -> 1348
    //   1049: goto -> 1056
    //   1052: invokestatic a : (Ljava/lang/Throwable;)Ljava/lang/Throwable;
    //   1055: athrow
    //   1056: aload_3
    //   1057: getstatic burp/Zmh5.Zh : Ljava/lang/String;
    //   1060: getstatic burp/Zry7.ZZ : Ljava/lang/Object;
    //   1063: checkcast java/math/BigInteger
    //   1066: invokevirtual intValue : ()I
    //   1069: bipush #32
    //   1071: irem
    //   1072: invokestatic abs : (I)I
    //   1075: invokevirtual charAt : (I)C
    //   1078: invokevirtual append : (C)Ljava/lang/StringBuilder;
    //   1081: pop
    //   1082: iload_2
    //   1083: ifne -> 1348
    //   1086: goto -> 1093
    //   1089: invokestatic a : (Ljava/lang/Throwable;)Ljava/lang/Throwable;
    //   1092: athrow
    //   1093: aload_3
    //   1094: getstatic burp/Zryq.Zb : Ljava/lang/String;
    //   1097: getstatic burp/Zmcq.Zh : Ljava/lang/Object;
    //   1100: checkcast java/math/BigInteger
    //   1103: invokevirtual intValue : ()I
    //   1106: bipush #32
    //   1108: irem
    //   1109: invokestatic abs : (I)I
    //   1112: invokevirtual charAt : (I)C
    //   1115: invokevirtual append : (C)Ljava/lang/StringBuilder;
    //   1118: pop
    //   1119: iload_2
    //   1120: ifne -> 1348
    //   1123: goto -> 1130
    //   1126: invokestatic a : (Ljava/lang/Throwable;)Ljava/lang/Throwable;
    //   1129: athrow
    //   1130: aload_3
    //   1131: getstatic burp/Ze_b.ZX : Ljava/lang/String;
    //   1134: getstatic burp/Zle4.Zh : Ljava/lang/Object;
    //   1137: checkcast java/math/BigInteger
    //   1140: invokevirtual intValue : ()I
    //   1143: bipush #32
    //   1145: irem
    //   1146: invokestatic abs : (I)I
    //   1149: invokevirtual charAt : (I)C
    //   1152: invokevirtual append : (C)Ljava/lang/StringBuilder;
    //   1155: pop
    //   1156: iload_2
    //   1157: ifne -> 1348
    //   1160: goto -> 1167
    //   1163: invokestatic a : (Ljava/lang/Throwable;)Ljava/lang/Throwable;
    //   1166: athrow
    //   1167: aload_3
    //   1168: getstatic burp/Zblj.Za : Ljava/lang/String;
    //   1171: getstatic burp/Zgkp.Zp : Ljava/lang/Object;
    //   1174: checkcast java/math/BigInteger
    //   1177: invokevirtual intValue : ()I
    //   1180: bipush #32
    //   1182: irem
    //   1183: invokestatic abs : (I)I
    //   1186: invokevirtual charAt : (I)C
    //   1189: invokevirtual append : (C)Ljava/lang/StringBuilder;
    //   1192: pop
    //   1193: iload_2
    //   1194: ifne -> 1348
    //   1197: goto -> 1204
    //   1200: invokestatic a : (Ljava/lang/Throwable;)Ljava/lang/Throwable;
    //   1203: athrow
    //   1204: aload_3
    //   1205: getstatic burp/Zle4.ZX : Ljava/lang/String;
    //   1208: getstatic burp/Zbnb.ZZ : Ljava/lang/Object;
    //   1211: checkcast java/math/BigInteger
    //   1214: invokevirtual intValue : ()I
    //   1217: bipush #32
    //   1219: irem
    //   1220: invokestatic abs : (I)I
    //   1223: invokevirtual charAt : (I)C
    //   1226: invokevirtual append : (C)Ljava/lang/StringBuilder;
    //   1229: pop
    //   1230: iload_2
    //   1231: ifne -> 1348
    //   1234: goto -> 1241
    //   1237: invokestatic a : (Ljava/lang/Throwable;)Ljava/lang/Throwable;
    //   1240: athrow
    //   1241: aload_3
    //   1242: getstatic burp/Zexu.Zp : Ljava/lang/String;
    //   1245: getstatic burp/Ztap.ZK : Ljava/lang/Object;
    //   1248: checkcast java/math/BigInteger
    //   1251: invokevirtual intValue : ()I
    //   1254: bipush #32
    //   1256: irem
    //   1257: invokestatic abs : (I)I
    //   1260: invokevirtual charAt : (I)C
    //   1263: invokevirtual append : (C)Ljava/lang/StringBuilder;
    //   1266: pop
    //   1267: iload_2
    //   1268: ifne -> 1348
    //   1271: goto -> 1278
    //   1274: invokestatic a : (Ljava/lang/Throwable;)Ljava/lang/Throwable;
    //   1277: athrow
    //   1278: aload_3
    //   1279: getstatic burp/Zz9v.Zv : Ljava/lang/String;
    //   1282: getstatic burp/Zs9k.ZX : Ljava/lang/Object;
    //   1285: checkcast java/math/BigInteger
    //   1288: invokevirtual intValue : ()I
    //   1291: bipush #32
    //   1293: irem
    //   1294: invokestatic abs : (I)I
    //   1297: invokevirtual charAt : (I)C
    //   1300: invokevirtual append : (C)Ljava/lang/StringBuilder;
    //   1303: pop
    //   1304: iload_2
    //   1305: ifne -> 1348
    //   1308: goto -> 1315
    //   1311: invokestatic a : (Ljava/lang/Throwable;)Ljava/lang/Throwable;
    //   1314: athrow
    //   1315: aload_3
    //   1316: getstatic burp/Zezn.Ze : Ljava/lang/String;
    //   1319: getstatic burp/Zx4k.ZE : Ljava/lang/Object;
    //   1322: checkcast java/math/BigInteger
    //   1325: invokevirtual intValue : ()I
    //   1328: bipush #32
    //   1330: irem
    //   1331: invokestatic abs : (I)I
    //   1334: invokevirtual charAt : (I)C
    //   1337: invokevirtual append : (C)Ljava/lang/StringBuilder;
    //   1340: pop
    //   1341: goto -> 1348
    //   1344: invokestatic a : (Ljava/lang/Throwable;)Ljava/lang/Throwable;
    //   1347: athrow
    //   1348: iinc #4, 1
    //   1351: iload_2
    //   1352: ifne -> 15
    //   1355: aload_3
    //   1356: invokevirtual toString : ()Ljava/lang/String;
    //   1359: putstatic burp/Zbqo.ZS : Ljava/lang/String;
    //   1362: new java/lang/StringBuilder
    //   1365: dup
    //   1366: invokespecial <init> : ()V
    //   1369: astore #4
    //   1371: iconst_0
    //   1372: istore #5
    //   1374: iload #5
    //   1376: bipush #32
    //   1378: if_icmpge -> 2743
    //   1381: iload #5
    //   1383: tableswitch default -> 2736, 0 -> 1524, 1 -> 1562, 2 -> 1600, 3 -> 1638, 4 -> 1676, 5 -> 1714, 6 -> 1752, 7 -> 1790, 8 -> 1828, 9 -> 1866, 10 -> 1904, 11 -> 1942, 12 -> 1980, 13 -> 2018, 14 -> 2056, 15 -> 2094, 16 -> 2132, 17 -> 2170, 18 -> 2208, 19 -> 2246, 20 -> 2284, 21 -> 2322, 22 -> 2360, 23 -> 2398, 24 -> 2436, 25 -> 2474, 26 -> 2512, 27 -> 2550, 28 -> 2588, 29 -> 2626, 30 -> 2664, 31 -> 2702
    //   1524: aload #4
    //   1526: getstatic burp/Ze_b.ZX : Ljava/lang/String;
    //   1529: getstatic burp/Zeud.Zs : Ljava/lang/Object;
    //   1532: checkcast java/math/BigInteger
    //   1535: invokevirtual intValue : ()I
    //   1538: bipush #32
    //   1540: irem
    //   1541: invokestatic abs : (I)I
    //   1544: invokevirtual charAt : (I)C
    //   1547: invokevirtual append : (C)Ljava/lang/StringBuilder;
    //   1550: pop
    //   1551: iload_2
    //   1552: ifne -> 2736
    //   1555: goto -> 1562
    //   1558: invokestatic a : (Ljava/lang/Throwable;)Ljava/lang/Throwable;
    //   1561: athrow
    //   1562: aload #4
    //   1564: getstatic burp/Zx4k.ZC : Ljava/lang/String;
    //   1567: getstatic burp/Zete.Zm : Ljava/lang/Object;
    //   1570: checkcast java/math/BigInteger
    //   1573: invokevirtual intValue : ()I
    //   1576: bipush #32
    //   1578: irem
    //   1579: invokestatic abs : (I)I
    //   1582: invokevirtual charAt : (I)C
    //   1585: invokevirtual append : (C)Ljava/lang/StringBuilder;
    //   1588: pop
    //   1589: iload_2
    //   1590: ifne -> 2736
    //   1593: goto -> 1600
    //   1596: invokestatic a : (Ljava/lang/Throwable;)Ljava/lang/Throwable;
    //   1599: athrow
    //   1600: aload #4
    //   1602: getstatic burp/Zkk6.ZP : Ljava/lang/String;
    //   1605: getstatic burp/Zz5s.Zg : Ljava/lang/Object;
    //   1608: checkcast java/math/BigInteger
    //   1611: invokevirtual intValue : ()I
    //   1614: bipush #32
    //   1616: irem
    //   1617: invokestatic abs : (I)I
    //   1620: invokevirtual charAt : (I)C
    //   1623: invokevirtual append : (C)Ljava/lang/StringBuilder;
    //   1626: pop
    //   1627: iload_2
    //   1628: ifne -> 2736
    //   1631: goto -> 1638
    //   1634: invokestatic a : (Ljava/lang/Throwable;)Ljava/lang/Throwable;
    //   1637: athrow
    //   1638: aload #4
    //   1640: getstatic burp/Zlhz.Zo : Ljava/lang/String;
    //   1643: getstatic burp/Zsun.ZP : Ljava/lang/Object;
    //   1646: checkcast java/math/BigInteger
    //   1649: invokevirtual intValue : ()I
    //   1652: bipush #32
    //   1654: irem
    //   1655: invokestatic abs : (I)I
    //   1658: invokevirtual charAt : (I)C
    //   1661: invokevirtual append : (C)Ljava/lang/StringBuilder;
    //   1664: pop
    //   1665: iload_2
    //   1666: ifne -> 2736
    //   1669: goto -> 1676
    //   1672: invokestatic a : (Ljava/lang/Throwable;)Ljava/lang/Throwable;
    //   1675: athrow
    //   1676: aload #4
    //   1678: getstatic burp/Zlg1.ZG : Ljava/lang/String;
    //   1681: getstatic burp/Zeno.Zo : Ljava/lang/Object;
    //   1684: checkcast java/math/BigInteger
    //   1687: invokevirtual intValue : ()I
    //   1690: bipush #32
    //   1692: irem
    //   1693: invokestatic abs : (I)I
    //   1696: invokevirtual charAt : (I)C
    //   1699: invokevirtual append : (C)Ljava/lang/StringBuilder;
    //   1702: pop
    //   1703: iload_2
    //   1704: ifne -> 2736
    //   1707: goto -> 1714
    //   1710: invokestatic a : (Ljava/lang/Throwable;)Ljava/lang/Throwable;
    //   1713: athrow
    //   1714: aload #4
    //   1716: getstatic burp/Zbnb.Zd : Ljava/lang/String;
    //   1719: getstatic burp/Zezn.Zh : Ljava/lang/Object;
    //   1722: checkcast java/math/BigInteger
    //   1725: invokevirtual intValue : ()I
    //   1728: bipush #32
    //   1730: irem
    //   1731: invokestatic abs : (I)I
    //   1734: invokevirtual charAt : (I)C
    //   1737: invokevirtual append : (C)Ljava/lang/StringBuilder;
    //   1740: pop
    //   1741: iload_2
    //   1742: ifne -> 2736
    //   1745: goto -> 1752
    //   1748: invokestatic a : (Ljava/lang/Throwable;)Ljava/lang/Throwable;
    //   1751: athrow
    //   1752: aload #4
    //   1754: getstatic burp/Zr9p.Za : Ljava/lang/String;
    //   1757: getstatic burp/Zz3k.Zz : Ljava/lang/Object;
    //   1760: checkcast java/math/BigInteger
    //   1763: invokevirtual intValue : ()I
    //   1766: bipush #32
    //   1768: irem
    //   1769: invokestatic abs : (I)I
    //   1772: invokevirtual charAt : (I)C
    //   1775: invokevirtual append : (C)Ljava/lang/StringBuilder;
    //   1778: pop
    //   1779: iload_2
    //   1780: ifne -> 2736
    //   1783: goto -> 1790
    //   1786: invokestatic a : (Ljava/lang/Throwable;)Ljava/lang/Throwable;
    //   1789: athrow
    //   1790: aload #4
    //   1792: getstatic burp/Zbnb.Zd : Ljava/lang/String;
    //   1795: getstatic burp/Zezq.Zu : Ljava/lang/Object;
    //   1798: checkcast java/math/BigInteger
    //   1801: invokevirtual intValue : ()I
    //   1804: bipush #32
    //   1806: irem
    //   1807: invokestatic abs : (I)I
    //   1810: invokevirtual charAt : (I)C
    //   1813: invokevirtual append : (C)Ljava/lang/StringBuilder;
    //   1816: pop
    //   1817: iload_2
    //   1818: ifne -> 2736
    //   1821: goto -> 1828
    //   1824: invokestatic a : (Ljava/lang/Throwable;)Ljava/lang/Throwable;
    //   1827: athrow
    //   1828: aload #4
    //   1830: getstatic burp/Zgvl.Zc : Ljava/lang/String;
    //   1833: getstatic burp/Zkaw.ZB : Ljava/lang/Object;
    //   1836: checkcast java/math/BigInteger
    //   1839: invokevirtual intValue : ()I
    //   1842: bipush #32
    //   1844: irem
    //   1845: invokestatic abs : (I)I
    //   1848: invokevirtual charAt : (I)C
    //   1851: invokevirtual append : (C)Ljava/lang/StringBuilder;
    //   1854: pop
    //   1855: iload_2
    //   1856: ifne -> 2736
    //   1859: goto -> 1866
    //   1862: invokestatic a : (Ljava/lang/Throwable;)Ljava/lang/Throwable;
    //   1865: athrow
    //   1866: aload #4
    //   1868: getstatic burp/Ze0w.ZT : Ljava/lang/String;
    //   1871: getstatic burp/Ztt0.ZF : Ljava/lang/Object;
    //   1874: checkcast java/math/BigInteger
    //   1877: invokevirtual intValue : ()I
    //   1880: bipush #32
    //   1882: irem
    //   1883: invokestatic abs : (I)I
    //   1886: invokevirtual charAt : (I)C
    //   1889: invokevirtual append : (C)Ljava/lang/StringBuilder;
    //   1892: pop
    //   1893: iload_2
    //   1894: ifne -> 2736
    //   1897: goto -> 1904
    //   1900: invokestatic a : (Ljava/lang/Throwable;)Ljava/lang/Throwable;
    //   1903: athrow
    //   1904: aload #4
    //   1906: getstatic burp/Zero.ZL : Ljava/lang/String;
    //   1909: getstatic burp/Zr0.ZX : Ljava/lang/Object;
    //   1912: checkcast java/math/BigInteger
    //   1915: invokevirtual intValue : ()I
    //   1918: bipush #32
    //   1920: irem
    //   1921: invokestatic abs : (I)I
    //   1924: invokevirtual charAt : (I)C
    //   1927: invokevirtual append : (C)Ljava/lang/StringBuilder;
    //   1930: pop
    //   1931: iload_2
    //   1932: ifne -> 2736
    //   1935: goto -> 1942
    //   1938: invokestatic a : (Ljava/lang/Throwable;)Ljava/lang/Throwable;
    //   1941: athrow
    //   1942: aload #4
    //   1944: getstatic burp/Ze0w.ZT : Ljava/lang/String;
    //   1947: getstatic burp/Zeu2.ZW : Ljava/lang/Object;
    //   1950: checkcast java/math/BigInteger
    //   1953: invokevirtual intValue : ()I
    //   1956: bipush #32
    //   1958: irem
    //   1959: invokestatic abs : (I)I
    //   1962: invokevirtual charAt : (I)C
    //   1965: invokevirtual append : (C)Ljava/lang/StringBuilder;
    //   1968: pop
    //   1969: iload_2
    //   1970: ifne -> 2736
    //   1973: goto -> 1980
    //   1976: invokestatic a : (Ljava/lang/Throwable;)Ljava/lang/Throwable;
    //   1979: athrow
    //   1980: aload #4
    //   1982: getstatic burp/Zrxm.Zp : Ljava/lang/String;
    //   1985: getstatic burp/Zsk2.ZD : Ljava/lang/Object;
    //   1988: checkcast java/math/BigInteger
    //   1991: invokevirtual intValue : ()I
    //   1994: bipush #32
    //   1996: irem
    //   1997: invokestatic abs : (I)I
    //   2000: invokevirtual charAt : (I)C
    //   2003: invokevirtual append : (C)Ljava/lang/StringBuilder;
    //   2006: pop
    //   2007: iload_2
    //   2008: ifne -> 2736
    //   2011: goto -> 2018
    //   2014: invokestatic a : (Ljava/lang/Throwable;)Ljava/lang/Throwable;
    //   2017: athrow
    //   2018: aload #4
    //   2020: getstatic burp/Zero.ZL : Ljava/lang/String;
    //   2023: getstatic burp/Zz9v.Zl : Ljava/lang/Object;
    //   2026: checkcast java/math/BigInteger
    //   2029: invokevirtual intValue : ()I
    //   2032: bipush #32
    //   2034: irem
    //   2035: invokestatic abs : (I)I
    //   2038: invokevirtual charAt : (I)C
    //   2041: invokevirtual append : (C)Ljava/lang/StringBuilder;
    //   2044: pop
    //   2045: iload_2
    //   2046: ifne -> 2736
    //   2049: goto -> 2056
    //   2052: invokestatic a : (Ljava/lang/Throwable;)Ljava/lang/Throwable;
    //   2055: athrow
    //   2056: aload #4
    //   2058: getstatic burp/Zrd0.Zk : Ljava/lang/String;
    //   2061: getstatic burp/Ztt0.ZF : Ljava/lang/Object;
    //   2064: checkcast java/math/BigInteger
    //   2067: invokevirtual intValue : ()I
    //   2070: bipush #32
    //   2072: irem
    //   2073: invokestatic abs : (I)I
    //   2076: invokevirtual charAt : (I)C
    //   2079: invokevirtual append : (C)Ljava/lang/StringBuilder;
    //   2082: pop
    //   2083: iload_2
    //   2084: ifne -> 2736
    //   2087: goto -> 2094
    //   2090: invokestatic a : (Ljava/lang/Throwable;)Ljava/lang/Throwable;
    //   2093: athrow
    //   2094: aload #4
    //   2096: getstatic burp/Zlxm.Zv : Ljava/lang/String;
    //   2099: getstatic burp/Zete.Zm : Ljava/lang/Object;
    //   2102: checkcast java/math/BigInteger
    //   2105: invokevirtual intValue : ()I
    //   2108: bipush #32
    //   2110: irem
    //   2111: invokestatic abs : (I)I
    //   2114: invokevirtual charAt : (I)C
    //   2117: invokevirtual append : (C)Ljava/lang/StringBuilder;
    //   2120: pop
    //   2121: iload_2
    //   2122: ifne -> 2736
    //   2125: goto -> 2132
    //   2128: invokestatic a : (Ljava/lang/Throwable;)Ljava/lang/Throwable;
    //   2131: athrow
    //   2132: aload #4
    //   2134: getstatic burp/Zgw7.ZN : Ljava/lang/String;
    //   2137: getstatic burp/Zs9k.ZX : Ljava/lang/Object;
    //   2140: checkcast java/math/BigInteger
    //   2143: invokevirtual intValue : ()I
    //   2146: bipush #32
    //   2148: irem
    //   2149: invokestatic abs : (I)I
    //   2152: invokevirtual charAt : (I)C
    //   2155: invokevirtual append : (C)Ljava/lang/StringBuilder;
    //   2158: pop
    //   2159: iload_2
    //   2160: ifne -> 2736
    //   2163: goto -> 2170
    //   2166: invokestatic a : (Ljava/lang/Throwable;)Ljava/lang/Throwable;
    //   2169: athrow
    //   2170: aload #4
    //   2172: getstatic burp/Zr0.ZH : Ljava/lang/String;
    //   2175: getstatic burp/Zb6b.ZU : Ljava/lang/Object;
    //   2178: checkcast java/math/BigInteger
    //   2181: invokevirtual intValue : ()I
    //   2184: bipush #32
    //   2186: irem
    //   2187: invokestatic abs : (I)I
    //   2190: invokevirtual charAt : (I)C
    //   2193: invokevirtual append : (C)Ljava/lang/StringBuilder;
    //   2196: pop
    //   2197: iload_2
    //   2198: ifne -> 2736
    //   2201: goto -> 2208
    //   2204: invokestatic a : (Ljava/lang/Throwable;)Ljava/lang/Throwable;
    //   2207: athrow
    //   2208: aload #4
    //   2210: getstatic burp/Zlg1.ZG : Ljava/lang/String;
    //   2213: getstatic burp/Zl22.ZJ : Ljava/lang/Object;
    //   2216: checkcast java/math/BigInteger
    //   2219: invokevirtual intValue : ()I
    //   2222: bipush #32
    //   2224: irem
    //   2225: invokestatic abs : (I)I
    //   2228: invokevirtual charAt : (I)C
    //   2231: invokevirtual append : (C)Ljava/lang/StringBuilder;
    //   2234: pop
    //   2235: iload_2
    //   2236: ifne -> 2736
    //   2239: goto -> 2246
    //   2242: invokestatic a : (Ljava/lang/Throwable;)Ljava/lang/Throwable;
    //   2245: athrow
    //   2246: aload #4
    //   2248: getstatic burp/Zgw7.ZN : Ljava/lang/String;
    //   2251: getstatic burp/Zgwh.Zl : Ljava/lang/Object;
    //   2254: checkcast java/math/BigInteger
    //   2257: invokevirtual intValue : ()I
    //   2260: bipush #32
    //   2262: irem
    //   2263: invokestatic abs : (I)I
    //   2266: invokevirtual charAt : (I)C
    //   2269: invokevirtual append : (C)Ljava/lang/StringBuilder;
    //   2272: pop
    //   2273: iload_2
    //   2274: ifne -> 2736
    //   2277: goto -> 2284
    //   2280: invokestatic a : (Ljava/lang/Throwable;)Ljava/lang/Throwable;
    //   2283: athrow
    //   2284: aload #4
    //   2286: getstatic burp/Zrj3.ZT : Ljava/lang/String;
    //   2289: getstatic burp/Ztmy.ZH : Ljava/lang/Object;
    //   2292: checkcast java/math/BigInteger
    //   2295: invokevirtual intValue : ()I
    //   2298: bipush #32
    //   2300: irem
    //   2301: invokestatic abs : (I)I
    //   2304: invokevirtual charAt : (I)C
    //   2307: invokevirtual append : (C)Ljava/lang/StringBuilder;
    //   2310: pop
    //   2311: iload_2
    //   2312: ifne -> 2736
    //   2315: goto -> 2322
    //   2318: invokestatic a : (Ljava/lang/Throwable;)Ljava/lang/Throwable;
    //   2321: athrow
    //   2322: aload #4
    //   2324: getstatic burp/Zlhz.Zo : Ljava/lang/String;
    //   2327: getstatic burp/Zgvf.Zd : Ljava/lang/Object;
    //   2330: checkcast java/math/BigInteger
    //   2333: invokevirtual intValue : ()I
    //   2336: bipush #32
    //   2338: irem
    //   2339: invokestatic abs : (I)I
    //   2342: invokevirtual charAt : (I)C
    //   2345: invokevirtual append : (C)Ljava/lang/StringBuilder;
    //   2348: pop
    //   2349: iload_2
    //   2350: ifne -> 2736
    //   2353: goto -> 2360
    //   2356: invokestatic a : (Ljava/lang/Throwable;)Ljava/lang/Throwable;
    //   2359: athrow
    //   2360: aload #4
    //   2362: getstatic burp/Ze_b.ZX : Ljava/lang/String;
    //   2365: getstatic burp/Zbnb.ZZ : Ljava/lang/Object;
    //   2368: checkcast java/math/BigInteger
    //   2371: invokevirtual intValue : ()I
    //   2374: bipush #32
    //   2376: irem
    //   2377: invokestatic abs : (I)I
    //   2380: invokevirtual charAt : (I)C
    //   2383: invokevirtual append : (C)Ljava/lang/StringBuilder;
    //   2386: pop
    //   2387: iload_2
    //   2388: ifne -> 2736
    //   2391: goto -> 2398
    //   2394: invokestatic a : (Ljava/lang/Throwable;)Ljava/lang/Throwable;
    //   2397: athrow
    //   2398: aload #4
    //   2400: getstatic burp/Ztt0.Zl : Ljava/lang/String;
    //   2403: getstatic burp/Zr_y.ZI : Ljava/lang/Object;
    //   2406: checkcast java/math/BigInteger
    //   2409: invokevirtual intValue : ()I
    //   2412: bipush #32
    //   2414: irem
    //   2415: invokestatic abs : (I)I
    //   2418: invokevirtual charAt : (I)C
    //   2421: invokevirtual append : (C)Ljava/lang/StringBuilder;
    //   2424: pop
    //   2425: iload_2
    //   2426: ifne -> 2736
    //   2429: goto -> 2436
    //   2432: invokestatic a : (Ljava/lang/Throwable;)Ljava/lang/Throwable;
    //   2435: athrow
    //   2436: aload #4
    //   2438: getstatic burp/Ztt0.Zl : Ljava/lang/String;
    //   2441: getstatic burp/Zgj5.ZO : Ljava/lang/Object;
    //   2444: checkcast java/math/BigInteger
    //   2447: invokevirtual intValue : ()I
    //   2450: bipush #32
    //   2452: irem
    //   2453: invokestatic abs : (I)I
    //   2456: invokevirtual charAt : (I)C
    //   2459: invokevirtual append : (C)Ljava/lang/StringBuilder;
    //   2462: pop
    //   2463: iload_2
    //   2464: ifne -> 2736
    //   2467: goto -> 2474
    //   2470: invokestatic a : (Ljava/lang/Throwable;)Ljava/lang/Throwable;
    //   2473: athrow
    //   2474: aload #4
    //   2476: getstatic burp/Zlzo.Zs : Ljava/lang/String;
    //   2479: getstatic burp/Zgj5.ZO : Ljava/lang/Object;
    //   2482: checkcast java/math/BigInteger
    //   2485: invokevirtual intValue : ()I
    //   2488: bipush #32
    //   2490: irem
    //   2491: invokestatic abs : (I)I
    //   2494: invokevirtual charAt : (I)C
    //   2497: invokevirtual append : (C)Ljava/lang/StringBuilder;
    //   2500: pop
    //   2501: iload_2
    //   2502: ifne -> 2736
    //   2505: goto -> 2512
    //   2508: invokestatic a : (Ljava/lang/Throwable;)Ljava/lang/Throwable;
    //   2511: athrow
    //   2512: aload #4
    //   2514: getstatic burp/Ztev.Zp : Ljava/lang/String;
    //   2517: getstatic burp/Zz5s.Zg : Ljava/lang/Object;
    //   2520: checkcast java/math/BigInteger
    //   2523: invokevirtual intValue : ()I
    //   2526: bipush #32
    //   2528: irem
    //   2529: invokestatic abs : (I)I
    //   2532: invokevirtual charAt : (I)C
    //   2535: invokevirtual append : (C)Ljava/lang/StringBuilder;
    //   2538: pop
    //   2539: iload_2
    //   2540: ifne -> 2736
    //   2543: goto -> 2550
    //   2546: invokestatic a : (Ljava/lang/Throwable;)Ljava/lang/Throwable;
    //   2549: athrow
    //   2550: aload #4
    //   2552: getstatic burp/Zxdh.Zj : Ljava/lang/String;
    //   2555: getstatic burp/Zm84.Zf : Ljava/lang/Object;
    //   2558: checkcast java/math/BigInteger
    //   2561: invokevirtual intValue : ()I
    //   2564: bipush #32
    //   2566: irem
    //   2567: invokestatic abs : (I)I
    //   2570: invokevirtual charAt : (I)C
    //   2573: invokevirtual append : (C)Ljava/lang/StringBuilder;
    //   2576: pop
    //   2577: iload_2
    //   2578: ifne -> 2736
    //   2581: goto -> 2588
    //   2584: invokestatic a : (Ljava/lang/Throwable;)Ljava/lang/Throwable;
    //   2587: athrow
    //   2588: aload #4
    //   2590: getstatic burp/Zxdh.Zj : Ljava/lang/String;
    //   2593: getstatic burp/Zz5s.Zg : Ljava/lang/Object;
    //   2596: checkcast java/math/BigInteger
    //   2599: invokevirtual intValue : ()I
    //   2602: bipush #32
    //   2604: irem
    //   2605: invokestatic abs : (I)I
    //   2608: invokevirtual charAt : (I)C
    //   2611: invokevirtual append : (C)Ljava/lang/StringBuilder;
    //   2614: pop
    //   2615: iload_2
    //   2616: ifne -> 2736
    //   2619: goto -> 2626
    //   2622: invokestatic a : (Ljava/lang/Throwable;)Ljava/lang/Throwable;
    //   2625: athrow
    //   2626: aload #4
    //   2628: getstatic burp/Zbqo.ZS : Ljava/lang/String;
    //   2631: getstatic burp/Zlhz.Zy : Ljava/lang/Object;
    //   2634: checkcast java/math/BigInteger
    //   2637: invokevirtual intValue : ()I
    //   2640: bipush #32
    //   2642: irem
    //   2643: invokestatic abs : (I)I
    //   2646: invokevirtual charAt : (I)C
    //   2649: invokevirtual append : (C)Ljava/lang/StringBuilder;
    //   2652: pop
    //   2653: iload_2
    //   2654: ifne -> 2736
    //   2657: goto -> 2664
    //   2660: invokestatic a : (Ljava/lang/Throwable;)Ljava/lang/Throwable;
    //   2663: athrow
    //   2664: aload #4
    //   2666: getstatic burp/Zgvl.Zc : Ljava/lang/String;
    //   2669: getstatic burp/Zero.ZE : Ljava/lang/Object;
    //   2672: checkcast java/math/BigInteger
    //   2675: invokevirtual intValue : ()I
    //   2678: bipush #32
    //   2680: irem
    //   2681: invokestatic abs : (I)I
    //   2684: invokevirtual charAt : (I)C
    //   2687: invokevirtual append : (C)Ljava/lang/StringBuilder;
    //   2690: pop
    //   2691: iload_2
    //   2692: ifne -> 2736
    //   2695: goto -> 2702
    //   2698: invokestatic a : (Ljava/lang/Throwable;)Ljava/lang/Throwable;
    //   2701: athrow
    //   2702: aload #4
    //   2704: getstatic burp/Zct.Zy : Ljava/lang/String;
    //   2707: getstatic burp/Zgyk.ZO : Ljava/lang/Object;
    //   2710: checkcast java/math/BigInteger
    //   2713: invokevirtual intValue : ()I
    //   2716: bipush #32
    //   2718: irem
    //   2719: invokestatic abs : (I)I
    //   2722: invokevirtual charAt : (I)C
    //   2725: invokevirtual append : (C)Ljava/lang/StringBuilder;
    //   2728: pop
    //   2729: goto -> 2736
    //   2732: invokestatic a : (Ljava/lang/Throwable;)Ljava/lang/Throwable;
    //   2735: athrow
    //   2736: iinc #5, 1
    //   2739: iload_2
    //   2740: ifne -> 1374
    //   2743: aload #4
    //   2745: invokevirtual toString : ()Ljava/lang/String;
    //   2748: putstatic burp/Zryq.Zb : Ljava/lang/String;
    //   2751: sipush #32752
    //   2754: getstatic burp/Zlp7.ZM : Ljava/lang/Object;
    //   2757: checkcast java/math/BigInteger
    //   2760: getstatic burp/Zl3n.Zh : Ljava/lang/Object;
    //   2763: checkcast java/math/BigInteger
    //   2766: invokevirtual add : (Ljava/math/BigInteger;)Ljava/math/BigInteger;
    //   2769: putstatic burp/Zx4k.ZE : Ljava/lang/Object;
    //   2772: sipush #12869
    //   2775: invokestatic a : (II)Ljava/lang/String;
    //   2778: iconst_1
    //   2779: ldc burp/Zzxs
    //   2781: invokevirtual getClassLoader : ()Ljava/lang/ClassLoader;
    //   2784: invokestatic forName : (Ljava/lang/String;ZLjava/lang/ClassLoader;)Ljava/lang/Class;
    //   2787: invokevirtual getDeclaredFields : ()[Ljava/lang/reflect/Field;
    //   2790: astore #5
    //   2792: aload #5
    //   2794: arraylength
    //   2795: istore #6
    //   2797: iconst_0
    //   2798: istore #7
    //   2800: iload #7
    //   2802: iload #6
    //   2804: if_icmpge -> 2942
    //   2807: aload #5
    //   2809: iload #7
    //   2811: aaload
    //   2812: astore #8
    //   2814: aload #8
    //   2816: invokevirtual getModifiers : ()I
    //   2819: invokestatic isStatic : (I)Z
    //   2822: ifne -> 2832
    //   2825: goto -> 2935
    //   2828: invokestatic a : (Ljava/lang/Throwable;)Ljava/lang/Throwable;
    //   2831: athrow
    //   2832: aload #8
    //   2834: invokevirtual getType : ()Ljava/lang/Class;
    //   2837: astore #9
    //   2839: aload #9
    //   2841: ifnull -> 2922
    //   2844: aload #9
    //   2846: invokevirtual isPrimitive : ()Z
    //   2849: ifne -> 2922
    //   2852: goto -> 2859
    //   2855: invokestatic a : (Ljava/lang/Throwable;)Ljava/lang/Throwable;
    //   2858: athrow
    //   2859: aload #9
    //   2861: invokevirtual getPackage : ()Ljava/lang/Package;
    //   2864: ifnull -> 2922
    //   2867: goto -> 2874
    //   2870: invokestatic a : (Ljava/lang/Throwable;)Ljava/lang/Throwable;
    //   2873: athrow
    //   2874: aload #9
    //   2876: invokevirtual getPackage : ()Ljava/lang/Package;
    //   2879: invokevirtual getName : ()Ljava/lang/String;
    //   2882: ifnull -> 2922
    //   2885: goto -> 2892
    //   2888: invokestatic a : (Ljava/lang/Throwable;)Ljava/lang/Throwable;
    //   2891: athrow
    //   2892: aload #9
    //   2894: invokevirtual getPackage : ()Ljava/lang/Package;
    //   2897: invokevirtual getName : ()Ljava/lang/String;
    //   2900: sipush #32742
    //   2903: sipush #19179
    //   2906: invokestatic a : (II)Ljava/lang/String;
    //   2909: invokevirtual startsWith : (Ljava/lang/String;)Z
    //   2912: ifne -> 2922
    //   2915: goto -> 2922
    //   2918: invokestatic a : (Ljava/lang/Throwable;)Ljava/lang/Throwable;
    //   2921: athrow
    //   2922: aload #8
    //   2924: iconst_1
    //   2925: invokevirtual setAccessible : (Z)V
    //   2928: aload #8
    //   2930: aconst_null
    //   2931: invokevirtual get : (Ljava/lang/Object;)Ljava/lang/Object;
    //   2934: pop
    //   2935: iinc #7, 1
    //   2938: iload_2
    //   2939: ifne -> 2800
    //   2942: sipush #32767
    //   2945: sipush #-1539
    //   2948: invokestatic a : (II)Ljava/lang/String;
    //   2951: invokestatic forName : (Ljava/lang/String;)Ljava/lang/Class;
    //   2954: invokevirtual getDeclaredMethods : ()[Ljava/lang/reflect/Method;
    //   2957: astore #5
    //   2959: aload #5
    //   2961: arraylength
    //   2962: istore #6
    //   2964: iconst_0
    //   2965: istore #7
    //   2967: iload #7
    //   2969: iload #6
    //   2971: if_icmpge -> 3104
    //   2974: aload #5
    //   2976: iload #7
    //   2978: aaload
    //   2979: astore #8
    //   2981: aload #8
    //   2983: invokevirtual getParameterTypes : ()[Ljava/lang/Class;
    //   2986: pop
    //   2987: aload #8
    //   2989: invokevirtual getModifiers : ()I
    //   2992: invokestatic isStatic : (I)Z
    //   2995: ifeq -> 3090
    //   2998: aload #8
    //   3000: invokevirtual getParameterTypes : ()[Ljava/lang/Class;
    //   3003: arraylength
    //   3004: iconst_2
    //   3005: if_icmpne -> 3090
    //   3008: goto -> 3015
    //   3011: invokestatic a : (Ljava/lang/Throwable;)Ljava/lang/Throwable;
    //   3014: athrow
    //   3015: aload #8
    //   3017: invokevirtual getReturnType : ()Ljava/lang/Class;
    //   3020: getstatic java/lang/Void.TYPE : Ljava/lang/Class;
    //   3023: invokevirtual equals : (Ljava/lang/Object;)Z
    //   3026: ifeq -> 3090
    //   3029: goto -> 3036
    //   3032: invokestatic a : (Ljava/lang/Throwable;)Ljava/lang/Throwable;
    //   3035: athrow
    //   3036: aload #8
    //   3038: iconst_1
    //   3039: invokevirtual setAccessible : (Z)V
    //   3042: aload #8
    //   3044: aconst_null
    //   3045: iconst_2
    //   3046: anewarray java/lang/Object
    //   3049: dup
    //   3050: iconst_0
    //   3051: aload_0
    //   3052: aastore
    //   3053: dup
    //   3054: iconst_1
    //   3055: aload_1
    //   3056: ifnonnull -> 3074
    //   3059: goto -> 3066
    //   3062: invokestatic a : (Ljava/lang/Throwable;)Ljava/lang/Throwable;
    //   3065: athrow
    //   3066: aload_1
    //   3067: goto -> 3081
    //   3070: invokestatic a : (Ljava/lang/Throwable;)Ljava/lang/Throwable;
    //   3073: athrow
    //   3074: aload_1
    //   3075: checkcast [B
    //   3078: invokevirtual clone : ()Ljava/lang/Object;
    //   3081: aastore
    //   3082: invokevirtual invoke : (Ljava/lang/Object;[Ljava/lang/Object;)Ljava/lang/Object;
    //   3085: pop
    //   3086: iload_2
    //   3087: ifne -> 3104
    //   3090: iinc #7, 1
    //   3093: iload_2
    //   3094: ifne -> 2967
    //   3097: goto -> 3104
    //   3100: invokestatic a : (Ljava/lang/Throwable;)Ljava/lang/Throwable;
    //   3103: athrow
    //   3104: iconst_0
    //   3105: istore #5
    //   3107: getstatic burp/Zgj5.ZH : Ljava/lang/String;
    //   3110: getstatic burp/Zxjw.ZU : Ljava/lang/Object;
    //   3113: checkcast java/math/BigInteger
    //   3116: invokevirtual intValue : ()I
    //   3119: bipush #32
    //   3121: irem
    //   3122: invokestatic abs : (I)I
    //   3125: invokevirtual charAt : (I)C
    //   3128: getstatic burp/Zryq.Zb : Ljava/lang/String;
    //   3131: getstatic burp/Ztev.Zr : Ljava/lang/Object;
    //   3134: checkcast java/math/BigInteger
    //   3137: invokevirtual intValue : ()I
    //   3140: bipush #32
    //   3142: irem
    //   3143: invokestatic abs : (I)I
    //   3146: invokevirtual charAt : (I)C
    //   3149: if_icmpgt -> 3494
    //   3152: sipush #32736
    //   3155: sipush #-9114
    //   3158: invokestatic a : (II)Ljava/lang/String;
    //   3161: iconst_1
    //   3162: ldc burp/Zmha
    //   3164: invokevirtual getClassLoader : ()Ljava/lang/ClassLoader;
    //   3167: invokestatic forName : (Ljava/lang/String;ZLjava/lang/ClassLoader;)Ljava/lang/Class;
    //   3170: invokevirtual getDeclaredFields : ()[Ljava/lang/reflect/Field;
    //   3173: astore #6
    //   3175: aload #6
    //   3177: arraylength
    //   3178: istore #7
    //   3180: iconst_0
    //   3181: istore #8
    //   3183: iload #8
    //   3185: iload #7
    //   3187: if_icmpge -> 3325
    //   3190: aload #6
    //   3192: iload #8
    //   3194: aaload
    //   3195: astore #9
    //   3197: aload #9
    //   3199: invokevirtual getModifiers : ()I
    //   3202: invokestatic isStatic : (I)Z
    //   3205: ifne -> 3215
    //   3208: goto -> 3318
    //   3211: invokestatic a : (Ljava/lang/Throwable;)Ljava/lang/Throwable;
    //   3214: athrow
    //   3215: aload #9
    //   3217: invokevirtual getType : ()Ljava/lang/Class;
    //   3220: astore #10
    //   3222: aload #10
    //   3224: ifnull -> 3305
    //   3227: aload #10
    //   3229: invokevirtual isPrimitive : ()Z
    //   3232: ifne -> 3305
    //   3235: goto -> 3242
    //   3238: invokestatic a : (Ljava/lang/Throwable;)Ljava/lang/Throwable;
    //   3241: athrow
    //   3242: aload #10
    //   3244: invokevirtual getPackage : ()Ljava/lang/Package;
    //   3247: ifnull -> 3305
    //   3250: goto -> 3257
    //   3253: invokestatic a : (Ljava/lang/Throwable;)Ljava/lang/Throwable;
    //   3256: athrow
    //   3257: aload #10
    //   3259: invokevirtual getPackage : ()Ljava/lang/Package;
    //   3262: invokevirtual getName : ()Ljava/lang/String;
    //   3265: ifnull -> 3305
    //   3268: goto -> 3275
    //   3271: invokestatic a : (Ljava/lang/Throwable;)Ljava/lang/Throwable;
    //   3274: athrow
    //   3275: aload #10
    //   3277: invokevirtual getPackage : ()Ljava/lang/Package;
    //   3280: invokevirtual getName : ()Ljava/lang/String;
    //   3283: sipush #32738
    //   3286: sipush #28487
    //   3289: invokestatic a : (II)Ljava/lang/String;
    //   3292: invokevirtual startsWith : (Ljava/lang/String;)Z
    //   3295: ifne -> 3305
    //   3298: goto -> 3305
    //   3301: invokestatic a : (Ljava/lang/Throwable;)Ljava/lang/Throwable;
    //   3304: athrow
    //   3305: aload #9
    //   3307: iconst_1
    //   3308: invokevirtual setAccessible : (Z)V
    //   3311: aload #9
    //   3313: aconst_null
    //   3314: invokevirtual get : (Ljava/lang/Object;)Ljava/lang/Object;
    //   3317: pop
    //   3318: iinc #8, 1
    //   3321: iload_2
    //   3322: ifne -> 3183
    //   3325: sipush #32751
    //   3328: sipush #18952
    //   3331: invokestatic a : (II)Ljava/lang/String;
    //   3334: invokestatic forName : (Ljava/lang/String;)Ljava/lang/Class;
    //   3337: invokevirtual getDeclaredMethods : ()[Ljava/lang/reflect/Method;
    //   3340: astore #6
    //   3342: aload #6
    //   3344: arraylength
    //   3345: istore #7
    //   3347: iconst_0
    //   3348: istore #8
    //   3350: iload #8
    //   3352: iload #7
    //   3354: if_icmpge -> 3491
    //   3357: aload #6
    //   3359: iload #8
    //   3361: aaload
    //   3362: astore #9
    //   3364: aload #9
    //   3366: invokevirtual getParameterTypes : ()[Ljava/lang/Class;
    //   3369: pop
    //   3370: aload #9
    //   3372: invokevirtual getModifiers : ()I
    //   3375: invokestatic isStatic : (I)Z
    //   3378: ifeq -> 3477
    //   3381: aload #9
    //   3383: invokevirtual getParameterTypes : ()[Ljava/lang/Class;
    //   3386: arraylength
    //   3387: iconst_2
    //   3388: if_icmpne -> 3477
    //   3391: goto -> 3398
    //   3394: invokestatic a : (Ljava/lang/Throwable;)Ljava/lang/Throwable;
    //   3397: athrow
    //   3398: aload #9
    //   3400: invokevirtual getReturnType : ()Ljava/lang/Class;
    //   3403: getstatic java/lang/Boolean.TYPE : Ljava/lang/Class;
    //   3406: if_acmpne -> 3477
    //   3409: goto -> 3416
    //   3412: invokestatic a : (Ljava/lang/Throwable;)Ljava/lang/Throwable;
    //   3415: athrow
    //   3416: aload #9
    //   3418: iconst_1
    //   3419: invokevirtual setAccessible : (Z)V
    //   3422: aload #9
    //   3424: aconst_null
    //   3425: iconst_2
    //   3426: anewarray java/lang/Object
    //   3429: dup
    //   3430: iconst_0
    //   3431: aload_0
    //   3432: aastore
    //   3433: dup
    //   3434: iconst_1
    //   3435: aload_1
    //   3436: ifnonnull -> 3454
    //   3439: goto -> 3446
    //   3442: invokestatic a : (Ljava/lang/Throwable;)Ljava/lang/Throwable;
    //   3445: athrow
    //   3446: aload_1
    //   3447: goto -> 3461
    //   3450: invokestatic a : (Ljava/lang/Throwable;)Ljava/lang/Throwable;
    //   3453: athrow
    //   3454: aload_1
    //   3455: checkcast [B
    //   3458: invokevirtual clone : ()Ljava/lang/Object;
    //   3461: aastore
    //   3462: invokevirtual invoke : (Ljava/lang/Object;[Ljava/lang/Object;)Ljava/lang/Object;
    //   3465: checkcast java/lang/Boolean
    //   3468: invokevirtual booleanValue : ()Z
    //   3471: istore #5
    //   3473: iload_2
    //   3474: ifne -> 3491
    //   3477: iinc #8, 1
    //   3480: iload_2
    //   3481: ifne -> 3350
    //   3484: goto -> 3491
    //   3487: invokestatic a : (Ljava/lang/Throwable;)Ljava/lang/Throwable;
    //   3490: athrow
    //   3491: goto -> 3833
    //   3494: sipush #32755
    //   3497: sipush #24840
    //   3500: invokestatic a : (II)Ljava/lang/String;
    //   3503: iconst_1
    //   3504: ldc burp/Zzsq
    //   3506: invokevirtual getClassLoader : ()Ljava/lang/ClassLoader;
    //   3509: invokestatic forName : (Ljava/lang/String;ZLjava/lang/ClassLoader;)Ljava/lang/Class;
    //   3512: invokevirtual getDeclaredFields : ()[Ljava/lang/reflect/Field;
    //   3515: astore #6
    //   3517: aload #6
    //   3519: arraylength
    //   3520: istore #7
    //   3522: iconst_0
    //   3523: istore #8
    //   3525: iload #8
    //   3527: iload #7
    //   3529: if_icmpge -> 3667
    //   3532: aload #6
    //   3534: iload #8
    //   3536: aaload
    //   3537: astore #9
    //   3539: aload #9
    //   3541: invokevirtual getModifiers : ()I
    //   3544: invokestatic isStatic : (I)Z
    //   3547: ifne -> 3557
    //   3550: goto -> 3660
    //   3553: invokestatic a : (Ljava/lang/Throwable;)Ljava/lang/Throwable;
    //   3556: athrow
    //   3557: aload #9
    //   3559: invokevirtual getType : ()Ljava/lang/Class;
    //   3562: astore #10
    //   3564: aload #10
    //   3566: ifnull -> 3647
    //   3569: aload #10
    //   3571: invokevirtual isPrimitive : ()Z
    //   3574: ifne -> 3647
    //   3577: goto -> 3584
    //   3580: invokestatic a : (Ljava/lang/Throwable;)Ljava/lang/Throwable;
    //   3583: athrow
    //   3584: aload #10
    //   3586: invokevirtual getPackage : ()Ljava/lang/Package;
    //   3589: ifnull -> 3647
    //   3592: goto -> 3599
    //   3595: invokestatic a : (Ljava/lang/Throwable;)Ljava/lang/Throwable;
    //   3598: athrow
    //   3599: aload #10
    //   3601: invokevirtual getPackage : ()Ljava/lang/Package;
    //   3604: invokevirtual getName : ()Ljava/lang/String;
    //   3607: ifnull -> 3647
    //   3610: goto -> 3617
    //   3613: invokestatic a : (Ljava/lang/Throwable;)Ljava/lang/Throwable;
    //   3616: athrow
    //   3617: aload #10
    //   3619: invokevirtual getPackage : ()Ljava/lang/Package;
    //   3622: invokevirtual getName : ()Ljava/lang/String;
    //   3625: sipush #32738
    //   3628: sipush #28487
    //   3631: invokestatic a : (II)Ljava/lang/String;
    //   3634: invokevirtual startsWith : (Ljava/lang/String;)Z
    //   3637: ifne -> 3647
    //   3640: goto -> 3647
    //   3643: invokestatic a : (Ljava/lang/Throwable;)Ljava/lang/Throwable;
    //   3646: athrow
    //   3647: aload #9
    //   3649: iconst_1
    //   3650: invokevirtual setAccessible : (Z)V
    //   3653: aload #9
    //   3655: aconst_null
    //   3656: invokevirtual get : (Ljava/lang/Object;)Ljava/lang/Object;
    //   3659: pop
    //   3660: iinc #8, 1
    //   3663: iload_2
    //   3664: ifne -> 3525
    //   3667: sipush #32739
    //   3670: sipush #-15696
    //   3673: invokestatic a : (II)Ljava/lang/String;
    //   3676: invokestatic forName : (Ljava/lang/String;)Ljava/lang/Class;
    //   3679: invokevirtual getDeclaredMethods : ()[Ljava/lang/reflect/Method;
    //   3682: astore #6
    //   3684: aload #6
    //   3686: arraylength
    //   3687: istore #7
    //   3689: iconst_0
    //   3690: istore #8
    //   3692: iload #8
    //   3694: iload #7
    //   3696: if_icmpge -> 3833
    //   3699: aload #6
    //   3701: iload #8
    //   3703: aaload
    //   3704: astore #9
    //   3706: aload #9
    //   3708: invokevirtual getParameterTypes : ()[Ljava/lang/Class;
    //   3711: pop
    //   3712: aload #9
    //   3714: invokevirtual getModifiers : ()I
    //   3717: invokestatic isStatic : (I)Z
    //   3720: ifeq -> 3819
    //   3723: aload #9
    //   3725: invokevirtual getParameterTypes : ()[Ljava/lang/Class;
    //   3728: arraylength
    //   3729: iconst_2
    //   3730: if_icmpne -> 3819
    //   3733: goto -> 3740
    //   3736: invokestatic a : (Ljava/lang/Throwable;)Ljava/lang/Throwable;
    //   3739: athrow
    //   3740: aload #9
    //   3742: invokevirtual getReturnType : ()Ljava/lang/Class;
    //   3745: getstatic java/lang/Boolean.TYPE : Ljava/lang/Class;
    //   3748: if_acmpne -> 3819
    //   3751: goto -> 3758
    //   3754: invokestatic a : (Ljava/lang/Throwable;)Ljava/lang/Throwable;
    //   3757: athrow
    //   3758: aload #9
    //   3760: iconst_1
    //   3761: invokevirtual setAccessible : (Z)V
    //   3764: aload #9
    //   3766: aconst_null
    //   3767: iconst_2
    //   3768: anewarray java/lang/Object
    //   3771: dup
    //   3772: iconst_0
    //   3773: aload_0
    //   3774: aastore
    //   3775: dup
    //   3776: iconst_1
    //   3777: aload_1
    //   3778: ifnonnull -> 3796
    //   3781: goto -> 3788
    //   3784: invokestatic a : (Ljava/lang/Throwable;)Ljava/lang/Throwable;
    //   3787: athrow
    //   3788: aload_1
    //   3789: goto -> 3803
    //   3792: invokestatic a : (Ljava/lang/Throwable;)Ljava/lang/Throwable;
    //   3795: athrow
    //   3796: aload_1
    //   3797: checkcast [B
    //   3800: invokevirtual clone : ()Ljava/lang/Object;
    //   3803: aastore
    //   3804: invokevirtual invoke : (Ljava/lang/Object;[Ljava/lang/Object;)Ljava/lang/Object;
    //   3807: checkcast java/lang/Boolean
    //   3810: invokevirtual booleanValue : ()Z
    //   3813: istore #5
    //   3815: iload_2
    //   3816: ifne -> 3833
    //   3819: iinc #8, 1
    //   3822: iload_2
    //   3823: ifne -> 3692
    //   3826: goto -> 3833
    //   3829: invokestatic a : (Ljava/lang/Throwable;)Ljava/lang/Throwable;
    //   3832: athrow
    //   3833: iload #5
    //   3835: ifeq -> 3841
    //   3838: iload #5
    //   3840: ireturn
    //   3841: getstatic burp/Zmcq.ZY : Ljava/lang/String;
    //   3844: getstatic burp/Zlg1.ZH : Ljava/lang/Object;
    //   3847: checkcast java/math/BigInteger
    //   3850: invokevirtual intValue : ()I
    //   3853: bipush #32
    //   3855: irem
    //   3856: invokestatic abs : (I)I
    //   3859: invokevirtual charAt : (I)C
    //   3862: getstatic burp/Zezq.Zp : Ljava/lang/String;
    //   3865: getstatic burp/Zeno.Zo : Ljava/lang/Object;
    //   3868: checkcast java/math/BigInteger
    //   3871: invokevirtual intValue : ()I
    //   3874: bipush #32
    //   3876: irem
    //   3877: invokestatic abs : (I)I
    //   3880: invokevirtual charAt : (I)C
    //   3883: if_icmple -> 4229
    //   3886: sipush #32761
    //   3889: sipush #-16869
    //   3892: invokestatic a : (II)Ljava/lang/String;
    //   3895: iconst_1
    //   3896: ldc burp/Ztw4
    //   3898: invokevirtual getClassLoader : ()Ljava/lang/ClassLoader;
    //   3901: invokestatic forName : (Ljava/lang/String;ZLjava/lang/ClassLoader;)Ljava/lang/Class;
    //   3904: invokevirtual getDeclaredFields : ()[Ljava/lang/reflect/Field;
    //   3907: astore #6
    //   3909: aload #6
    //   3911: arraylength
    //   3912: istore #7
    //   3914: iconst_0
    //   3915: istore #8
    //   3917: iload #8
    //   3919: iload #7
    //   3921: if_icmpge -> 4059
    //   3924: aload #6
    //   3926: iload #8
    //   3928: aaload
    //   3929: astore #9
    //   3931: aload #9
    //   3933: invokevirtual getModifiers : ()I
    //   3936: invokestatic isStatic : (I)Z
    //   3939: ifne -> 3949
    //   3942: goto -> 4052
    //   3945: invokestatic a : (Ljava/lang/Throwable;)Ljava/lang/Throwable;
    //   3948: athrow
    //   3949: aload #9
    //   3951: invokevirtual getType : ()Ljava/lang/Class;
    //   3954: astore #10
    //   3956: aload #10
    //   3958: ifnull -> 4039
    //   3961: aload #10
    //   3963: invokevirtual isPrimitive : ()Z
    //   3966: ifne -> 4039
    //   3969: goto -> 3976
    //   3972: invokestatic a : (Ljava/lang/Throwable;)Ljava/lang/Throwable;
    //   3975: athrow
    //   3976: aload #10
    //   3978: invokevirtual getPackage : ()Ljava/lang/Package;
    //   3981: ifnull -> 4039
    //   3984: goto -> 3991
    //   3987: invokestatic a : (Ljava/lang/Throwable;)Ljava/lang/Throwable;
    //   3990: athrow
    //   3991: aload #10
    //   3993: invokevirtual getPackage : ()Ljava/lang/Package;
    //   3996: invokevirtual getName : ()Ljava/lang/String;
    //   3999: ifnull -> 4039
    //   4002: goto -> 4009
    //   4005: invokestatic a : (Ljava/lang/Throwable;)Ljava/lang/Throwable;
    //   4008: athrow
    //   4009: aload #10
    //   4011: invokevirtual getPackage : ()Ljava/lang/Package;
    //   4014: invokevirtual getName : ()Ljava/lang/String;
    //   4017: sipush #32738
    //   4020: sipush #28487
    //   4023: invokestatic a : (II)Ljava/lang/String;
    //   4026: invokevirtual startsWith : (Ljava/lang/String;)Z
    //   4029: ifne -> 4039
    //   4032: goto -> 4039
    //   4035: invokestatic a : (Ljava/lang/Throwable;)Ljava/lang/Throwable;
    //   4038: athrow
    //   4039: aload #9
    //   4041: iconst_1
    //   4042: invokevirtual setAccessible : (Z)V
    //   4045: aload #9
    //   4047: aconst_null
    //   4048: invokevirtual get : (Ljava/lang/Object;)Ljava/lang/Object;
    //   4051: pop
    //   4052: iinc #8, 1
    //   4055: iload_2
    //   4056: ifne -> 3917
    //   4059: sipush #32766
    //   4062: sipush #-27066
    //   4065: invokestatic a : (II)Ljava/lang/String;
    //   4068: invokestatic forName : (Ljava/lang/String;)Ljava/lang/Class;
    //   4071: invokevirtual getDeclaredMethods : ()[Ljava/lang/reflect/Method;
    //   4074: astore #6
    //   4076: aload #6
    //   4078: arraylength
    //   4079: istore #7
    //   4081: iconst_0
    //   4082: istore #8
    //   4084: iload #8
    //   4086: iload #7
    //   4088: if_icmpge -> 4225
    //   4091: aload #6
    //   4093: iload #8
    //   4095: aaload
    //   4096: astore #9
    //   4098: aload #9
    //   4100: invokevirtual getParameterTypes : ()[Ljava/lang/Class;
    //   4103: pop
    //   4104: aload #9
    //   4106: invokevirtual getModifiers : ()I
    //   4109: invokestatic isStatic : (I)Z
    //   4112: ifeq -> 4211
    //   4115: aload #9
    //   4117: invokevirtual getParameterTypes : ()[Ljava/lang/Class;
    //   4120: arraylength
    //   4121: iconst_2
    //   4122: if_icmpne -> 4211
    //   4125: goto -> 4132
    //   4128: invokestatic a : (Ljava/lang/Throwable;)Ljava/lang/Throwable;
    //   4131: athrow
    //   4132: aload #9
    //   4134: invokevirtual getReturnType : ()Ljava/lang/Class;
    //   4137: getstatic java/lang/Boolean.TYPE : Ljava/lang/Class;
    //   4140: if_acmpne -> 4211
    //   4143: goto -> 4150
    //   4146: invokestatic a : (Ljava/lang/Throwable;)Ljava/lang/Throwable;
    //   4149: athrow
    //   4150: aload #9
    //   4152: iconst_1
    //   4153: invokevirtual setAccessible : (Z)V
    //   4156: aload #9
    //   4158: aconst_null
    //   4159: iconst_2
    //   4160: anewarray java/lang/Object
    //   4163: dup
    //   4164: iconst_0
    //   4165: aload_0
    //   4166: aastore
    //   4167: dup
    //   4168: iconst_1
    //   4169: aload_1
    //   4170: ifnonnull -> 4188
    //   4173: goto -> 4180
    //   4176: invokestatic a : (Ljava/lang/Throwable;)Ljava/lang/Throwable;
    //   4179: athrow
    //   4180: aload_1
    //   4181: goto -> 4195
    //   4184: invokestatic a : (Ljava/lang/Throwable;)Ljava/lang/Throwable;
    //   4187: athrow
    //   4188: aload_1
    //   4189: checkcast [B
    //   4192: invokevirtual clone : ()Ljava/lang/Object;
    //   4195: aastore
    //   4196: invokevirtual invoke : (Ljava/lang/Object;[Ljava/lang/Object;)Ljava/lang/Object;
    //   4199: checkcast java/lang/Boolean
    //   4202: invokevirtual booleanValue : ()Z
    //   4205: istore #5
    //   4207: iload_2
    //   4208: ifne -> 4225
    //   4211: iinc #8, 1
    //   4214: iload_2
    //   4215: ifne -> 4084
    //   4218: goto -> 4225
    //   4221: invokestatic a : (Ljava/lang/Throwable;)Ljava/lang/Throwable;
    //   4224: athrow
    //   4225: iload_2
    //   4226: ifne -> 4567
    //   4229: sipush #32740
    //   4232: sipush #31223
    //   4235: invokestatic a : (II)Ljava/lang/String;
    //   4238: iconst_1
    //   4239: ldc burp/Zrnw
    //   4241: invokevirtual getClassLoader : ()Ljava/lang/ClassLoader;
    //   4244: invokestatic forName : (Ljava/lang/String;ZLjava/lang/ClassLoader;)Ljava/lang/Class;
    //   4247: invokevirtual getDeclaredFields : ()[Ljava/lang/reflect/Field;
    //   4250: astore #6
    //   4252: aload #6
    //   4254: arraylength
    //   4255: istore #7
    //   4257: iconst_0
    //   4258: istore #8
    //   4260: iload #8
    //   4262: iload #7
    //   4264: if_icmpge -> 4402
    //   4267: aload #6
    //   4269: iload #8
    //   4271: aaload
    //   4272: astore #9
    //   4274: aload #9
    //   4276: invokevirtual getModifiers : ()I
    //   4279: invokestatic isStatic : (I)Z
    //   4282: ifne -> 4292
    //   4285: goto -> 4395
    //   4288: invokestatic a : (Ljava/lang/Throwable;)Ljava/lang/Throwable;
    //   4291: athrow
    //   4292: aload #9
    //   4294: invokevirtual getType : ()Ljava/lang/Class;
    //   4297: astore #10
    //   4299: aload #10
    //   4301: ifnull -> 4382
    //   4304: aload #10
    //   4306: invokevirtual isPrimitive : ()Z
    //   4309: ifne -> 4382
    //   4312: goto -> 4319
    //   4315: invokestatic a : (Ljava/lang/Throwable;)Ljava/lang/Throwable;
    //   4318: athrow
    //   4319: aload #10
    //   4321: invokevirtual getPackage : ()Ljava/lang/Package;
    //   4324: ifnull -> 4382
    //   4327: goto -> 4334
    //   4330: invokestatic a : (Ljava/lang/Throwable;)Ljava/lang/Throwable;
    //   4333: athrow
    //   4334: aload #10
    //   4336: invokevirtual getPackage : ()Ljava/lang/Package;
    //   4339: invokevirtual getName : ()Ljava/lang/String;
    //   4342: ifnull -> 4382
    //   4345: goto -> 4352
    //   4348: invokestatic a : (Ljava/lang/Throwable;)Ljava/lang/Throwable;
    //   4351: athrow
    //   4352: aload #10
    //   4354: invokevirtual getPackage : ()Ljava/lang/Package;
    //   4357: invokevirtual getName : ()Ljava/lang/String;
    //   4360: sipush #32738
    //   4363: sipush #28487
    //   4366: invokestatic a : (II)Ljava/lang/String;
    //   4369: invokevirtual startsWith : (Ljava/lang/String;)Z
    //   4372: ifne -> 4382
    //   4375: goto -> 4382
    //   4378: invokestatic a : (Ljava/lang/Throwable;)Ljava/lang/Throwable;
    //   4381: athrow
    //   4382: aload #9
    //   4384: iconst_1
    //   4385: invokevirtual setAccessible : (Z)V
    //   4388: aload #9
    //   4390: aconst_null
    //   4391: invokevirtual get : (Ljava/lang/Object;)Ljava/lang/Object;
    //   4394: pop
    //   4395: iinc #8, 1
    //   4398: iload_2
    //   4399: ifne -> 4260
    //   4402: sipush #32756
    //   4405: bipush #-10
    //   4407: invokestatic a : (II)Ljava/lang/String;
    //   4410: invokestatic forName : (Ljava/lang/String;)Ljava/lang/Class;
    //   4413: invokevirtual getDeclaredMethods : ()[Ljava/lang/reflect/Method;
    //   4416: astore #6
    //   4418: aload #6
    //   4420: arraylength
    //   4421: istore #7
    //   4423: iconst_0
    //   4424: istore #8
    //   4426: iload #8
    //   4428: iload #7
    //   4430: if_icmpge -> 4567
    //   4433: aload #6
    //   4435: iload #8
    //   4437: aaload
    //   4438: astore #9
    //   4440: aload #9
    //   4442: invokevirtual getParameterTypes : ()[Ljava/lang/Class;
    //   4445: pop
    //   4446: aload #9
    //   4448: invokevirtual getModifiers : ()I
    //   4451: invokestatic isStatic : (I)Z
    //   4454: ifeq -> 4553
    //   4457: aload #9
    //   4459: invokevirtual getParameterTypes : ()[Ljava/lang/Class;
    //   4462: arraylength
    //   4463: iconst_2
    //   4464: if_icmpne -> 4553
    //   4467: goto -> 4474
    //   4470: invokestatic a : (Ljava/lang/Throwable;)Ljava/lang/Throwable;
    //   4473: athrow
    //   4474: aload #9
    //   4476: invokevirtual getReturnType : ()Ljava/lang/Class;
    //   4479: getstatic java/lang/Boolean.TYPE : Ljava/lang/Class;
    //   4482: if_acmpne -> 4553
    //   4485: goto -> 4492
    //   4488: invokestatic a : (Ljava/lang/Throwable;)Ljava/lang/Throwable;
    //   4491: athrow
    //   4492: aload #9
    //   4494: iconst_1
    //   4495: invokevirtual setAccessible : (Z)V
    //   4498: aload #9
    //   4500: aconst_null
    //   4501: iconst_2
    //   4502: anewarray java/lang/Object
    //   4505: dup
    //   4506: iconst_0
    //   4507: aload_0
    //   4508: aastore
    //   4509: dup
    //   4510: iconst_1
    //   4511: aload_1
    //   4512: ifnonnull -> 4530
    //   4515: goto -> 4522
    //   4518: invokestatic a : (Ljava/lang/Throwable;)Ljava/lang/Throwable;
    //   4521: athrow
    //   4522: aload_1
    //   4523: goto -> 4537
    //   4526: invokestatic a : (Ljava/lang/Throwable;)Ljava/lang/Throwable;
    //   4529: athrow
    //   4530: aload_1
    //   4531: checkcast [B
    //   4534: invokevirtual clone : ()Ljava/lang/Object;
    //   4537: aastore
    //   4538: invokevirtual invoke : (Ljava/lang/Object;[Ljava/lang/Object;)Ljava/lang/Object;
    //   4541: checkcast java/lang/Boolean
    //   4544: invokevirtual booleanValue : ()Z
    //   4547: istore #5
    //   4549: iload_2
    //   4550: ifne -> 4567
    //   4553: iinc #8, 1
    //   4556: iload_2
    //   4557: ifne -> 4426
    //   4560: goto -> 4567
    //   4563: invokestatic a : (Ljava/lang/Throwable;)Ljava/lang/Throwable;
    //   4566: athrow
    //   4567: iload #5
    //   4569: ifeq -> 4575
    //   4572: iload #5
    //   4574: ireturn
    //   4575: getstatic burp/Zz3k.Zn : Ljava/lang/String;
    //   4578: getstatic burp/Zxdh.ZD : Ljava/lang/Object;
    //   4581: checkcast java/math/BigInteger
    //   4584: invokevirtual intValue : ()I
    //   4587: bipush #32
    //   4589: irem
    //   4590: invokestatic abs : (I)I
    //   4593: invokevirtual charAt : (I)C
    //   4596: getstatic burp/Zr_y.Zb : Ljava/lang/String;
    //   4599: getstatic burp/Ze0w.ZU : Ljava/lang/Object;
    //   4602: checkcast java/math/BigInteger
    //   4605: invokevirtual intValue : ()I
    //   4608: bipush #32
    //   4610: irem
    //   4611: invokestatic abs : (I)I
    //   4614: invokevirtual charAt : (I)C
    //   4617: if_icmpgt -> 4963
    //   4620: sipush #32741
    //   4623: sipush #14996
    //   4626: invokestatic a : (II)Ljava/lang/String;
    //   4629: iconst_1
    //   4630: ldc burp/Ztcv
    //   4632: invokevirtual getClassLoader : ()Ljava/lang/ClassLoader;
    //   4635: invokestatic forName : (Ljava/lang/String;ZLjava/lang/ClassLoader;)Ljava/lang/Class;
    //   4638: invokevirtual getDeclaredFields : ()[Ljava/lang/reflect/Field;
    //   4641: astore #6
    //   4643: aload #6
    //   4645: arraylength
    //   4646: istore #7
    //   4648: iconst_0
    //   4649: istore #8
    //   4651: iload #8
    //   4653: iload #7
    //   4655: if_icmpge -> 4793
    //   4658: aload #6
    //   4660: iload #8
    //   4662: aaload
    //   4663: astore #9
    //   4665: aload #9
    //   4667: invokevirtual getModifiers : ()I
    //   4670: invokestatic isStatic : (I)Z
    //   4673: ifne -> 4683
    //   4676: goto -> 4786
    //   4679: invokestatic a : (Ljava/lang/Throwable;)Ljava/lang/Throwable;
    //   4682: athrow
    //   4683: aload #9
    //   4685: invokevirtual getType : ()Ljava/lang/Class;
    //   4688: astore #10
    //   4690: aload #10
    //   4692: ifnull -> 4773
    //   4695: aload #10
    //   4697: invokevirtual isPrimitive : ()Z
    //   4700: ifne -> 4773
    //   4703: goto -> 4710
    //   4706: invokestatic a : (Ljava/lang/Throwable;)Ljava/lang/Throwable;
    //   4709: athrow
    //   4710: aload #10
    //   4712: invokevirtual getPackage : ()Ljava/lang/Package;
    //   4715: ifnull -> 4773
    //   4718: goto -> 4725
    //   4721: invokestatic a : (Ljava/lang/Throwable;)Ljava/lang/Throwable;
    //   4724: athrow
    //   4725: aload #10
    //   4727: invokevirtual getPackage : ()Ljava/lang/Package;
    //   4730: invokevirtual getName : ()Ljava/lang/String;
    //   4733: ifnull -> 4773
    //   4736: goto -> 4743
    //   4739: invokestatic a : (Ljava/lang/Throwable;)Ljava/lang/Throwable;
    //   4742: athrow
    //   4743: aload #10
    //   4745: invokevirtual getPackage : ()Ljava/lang/Package;
    //   4748: invokevirtual getName : ()Ljava/lang/String;
    //   4751: sipush #32738
    //   4754: sipush #28487
    //   4757: invokestatic a : (II)Ljava/lang/String;
    //   4760: invokevirtual startsWith : (Ljava/lang/String;)Z
    //   4763: ifne -> 4773
    //   4766: goto -> 4773
    //   4769: invokestatic a : (Ljava/lang/Throwable;)Ljava/lang/Throwable;
    //   4772: athrow
    //   4773: aload #9
    //   4775: iconst_1
    //   4776: invokevirtual setAccessible : (Z)V
    //   4779: aload #9
    //   4781: aconst_null
    //   4782: invokevirtual get : (Ljava/lang/Object;)Ljava/lang/Object;
    //   4785: pop
    //   4786: iinc #8, 1
    //   4789: iload_2
    //   4790: ifne -> 4651
    //   4793: sipush #32762
    //   4796: sipush #11357
    //   4799: invokestatic a : (II)Ljava/lang/String;
    //   4802: invokestatic forName : (Ljava/lang/String;)Ljava/lang/Class;
    //   4805: invokevirtual getDeclaredMethods : ()[Ljava/lang/reflect/Method;
    //   4808: astore #6
    //   4810: aload #6
    //   4812: arraylength
    //   4813: istore #7
    //   4815: iconst_0
    //   4816: istore #8
    //   4818: iload #8
    //   4820: iload #7
    //   4822: if_icmpge -> 4959
    //   4825: aload #6
    //   4827: iload #8
    //   4829: aaload
    //   4830: astore #9
    //   4832: aload #9
    //   4834: invokevirtual getParameterTypes : ()[Ljava/lang/Class;
    //   4837: pop
    //   4838: aload #9
    //   4840: invokevirtual getModifiers : ()I
    //   4843: invokestatic isStatic : (I)Z
    //   4846: ifeq -> 4945
    //   4849: aload #9
    //   4851: invokevirtual getParameterTypes : ()[Ljava/lang/Class;
    //   4854: arraylength
    //   4855: iconst_2
    //   4856: if_icmpne -> 4945
    //   4859: goto -> 4866
    //   4862: invokestatic a : (Ljava/lang/Throwable;)Ljava/lang/Throwable;
    //   4865: athrow
    //   4866: aload #9
    //   4868: invokevirtual getReturnType : ()Ljava/lang/Class;
    //   4871: getstatic java/lang/Boolean.TYPE : Ljava/lang/Class;
    //   4874: if_acmpne -> 4945
    //   4877: goto -> 4884
    //   4880: invokestatic a : (Ljava/lang/Throwable;)Ljava/lang/Throwable;
    //   4883: athrow
    //   4884: aload #9
    //   4886: iconst_1
    //   4887: invokevirtual setAccessible : (Z)V
    //   4890: aload #9
    //   4892: aconst_null
    //   4893: iconst_2
    //   4894: anewarray java/lang/Object
    //   4897: dup
    //   4898: iconst_0
    //   4899: aload_0
    //   4900: aastore
    //   4901: dup
    //   4902: iconst_1
    //   4903: aload_1
    //   4904: ifnonnull -> 4922
    //   4907: goto -> 4914
    //   4910: invokestatic a : (Ljava/lang/Throwable;)Ljava/lang/Throwable;
    //   4913: athrow
    //   4914: aload_1
    //   4915: goto -> 4929
    //   4918: invokestatic a : (Ljava/lang/Throwable;)Ljava/lang/Throwable;
    //   4921: athrow
    //   4922: aload_1
    //   4923: checkcast [B
    //   4926: invokevirtual clone : ()Ljava/lang/Object;
    //   4929: aastore
    //   4930: invokevirtual invoke : (Ljava/lang/Object;[Ljava/lang/Object;)Ljava/lang/Object;
    //   4933: checkcast java/lang/Boolean
    //   4936: invokevirtual booleanValue : ()Z
    //   4939: istore #5
    //   4941: iload_2
    //   4942: ifne -> 4959
    //   4945: iinc #8, 1
    //   4948: iload_2
    //   4949: ifne -> 4818
    //   4952: goto -> 4959
    //   4955: invokestatic a : (Ljava/lang/Throwable;)Ljava/lang/Throwable;
    //   4958: athrow
    //   4959: iload_2
    //   4960: ifne -> 5302
    //   4963: sipush #32753
    //   4966: sipush #15025
    //   4969: invokestatic a : (II)Ljava/lang/String;
    //   4972: iconst_1
    //   4973: ldc burp/Zt5b
    //   4975: invokevirtual getClassLoader : ()Ljava/lang/ClassLoader;
    //   4978: invokestatic forName : (Ljava/lang/String;ZLjava/lang/ClassLoader;)Ljava/lang/Class;
    //   4981: invokevirtual getDeclaredFields : ()[Ljava/lang/reflect/Field;
    //   4984: astore #6
    //   4986: aload #6
    //   4988: arraylength
    //   4989: istore #7
    //   4991: iconst_0
    //   4992: istore #8
    //   4994: iload #8
    //   4996: iload #7
    //   4998: if_icmpge -> 5136
    //   5001: aload #6
    //   5003: iload #8
    //   5005: aaload
    //   5006: astore #9
    //   5008: aload #9
    //   5010: invokevirtual getModifiers : ()I
    //   5013: invokestatic isStatic : (I)Z
    //   5016: ifne -> 5026
    //   5019: goto -> 5129
    //   5022: invokestatic a : (Ljava/lang/Throwable;)Ljava/lang/Throwable;
    //   5025: athrow
    //   5026: aload #9
    //   5028: invokevirtual getType : ()Ljava/lang/Class;
    //   5031: astore #10
    //   5033: aload #10
    //   5035: ifnull -> 5116
    //   5038: aload #10
    //   5040: invokevirtual isPrimitive : ()Z
    //   5043: ifne -> 5116
    //   5046: goto -> 5053
    //   5049: invokestatic a : (Ljava/lang/Throwable;)Ljava/lang/Throwable;
    //   5052: athrow
    //   5053: aload #10
    //   5055: invokevirtual getPackage : ()Ljava/lang/Package;
    //   5058: ifnull -> 5116
    //   5061: goto -> 5068
    //   5064: invokestatic a : (Ljava/lang/Throwable;)Ljava/lang/Throwable;
    //   5067: athrow
    //   5068: aload #10
    //   5070: invokevirtual getPackage : ()Ljava/lang/Package;
    //   5073: invokevirtual getName : ()Ljava/lang/String;
    //   5076: ifnull -> 5116
    //   5079: goto -> 5086
    //   5082: invokestatic a : (Ljava/lang/Throwable;)Ljava/lang/Throwable;
    //   5085: athrow
    //   5086: aload #10
    //   5088: invokevirtual getPackage : ()Ljava/lang/Package;
    //   5091: invokevirtual getName : ()Ljava/lang/String;
    //   5094: sipush #32738
    //   5097: sipush #28487
    //   5100: invokestatic a : (II)Ljava/lang/String;
    //   5103: invokevirtual startsWith : (Ljava/lang/String;)Z
    //   5106: ifne -> 5116
    //   5109: goto -> 5116
    //   5112: invokestatic a : (Ljava/lang/Throwable;)Ljava/lang/Throwable;
    //   5115: athrow
    //   5116: aload #9
    //   5118: iconst_1
    //   5119: invokevirtual setAccessible : (Z)V
    //   5122: aload #9
    //   5124: aconst_null
    //   5125: invokevirtual get : (Ljava/lang/Object;)Ljava/lang/Object;
    //   5128: pop
    //   5129: iinc #8, 1
    //   5132: iload_2
    //   5133: ifne -> 4994
    //   5136: sipush #32743
    //   5139: sipush #-15787
    //   5142: invokestatic a : (II)Ljava/lang/String;
    //   5145: invokestatic forName : (Ljava/lang/String;)Ljava/lang/Class;
    //   5148: invokevirtual getDeclaredMethods : ()[Ljava/lang/reflect/Method;
    //   5151: astore #6
    //   5153: aload #6
    //   5155: arraylength
    //   5156: istore #7
    //   5158: iconst_0
    //   5159: istore #8
    //   5161: iload #8
    //   5163: iload #7
    //   5165: if_icmpge -> 5302
    //   5168: aload #6
    //   5170: iload #8
    //   5172: aaload
    //   5173: astore #9
    //   5175: aload #9
    //   5177: invokevirtual getParameterTypes : ()[Ljava/lang/Class;
    //   5180: pop
    //   5181: aload #9
    //   5183: invokevirtual getModifiers : ()I
    //   5186: invokestatic isStatic : (I)Z
    //   5189: ifeq -> 5288
    //   5192: aload #9
    //   5194: invokevirtual getParameterTypes : ()[Ljava/lang/Class;
    //   5197: arraylength
    //   5198: iconst_2
    //   5199: if_icmpne -> 5288
    //   5202: goto -> 5209
    //   5205: invokestatic a : (Ljava/lang/Throwable;)Ljava/lang/Throwable;
    //   5208: athrow
    //   5209: aload #9
    //   5211: invokevirtual getReturnType : ()Ljava/lang/Class;
    //   5214: getstatic java/lang/Boolean.TYPE : Ljava/lang/Class;
    //   5217: if_acmpne -> 5288
    //   5220: goto -> 5227
    //   5223: invokestatic a : (Ljava/lang/Throwable;)Ljava/lang/Throwable;
    //   5226: athrow
    //   5227: aload #9
    //   5229: iconst_1
    //   5230: invokevirtual setAccessible : (Z)V
    //   5233: aload #9
    //   5235: aconst_null
    //   5236: iconst_2
    //   5237: anewarray java/lang/Object
    //   5240: dup
    //   5241: iconst_0
    //   5242: aload_0
    //   5243: aastore
    //   5244: dup
    //   5245: iconst_1
    //   5246: aload_1
    //   5247: ifnonnull -> 5265
    //   5250: goto -> 5257
    //   5253: invokestatic a : (Ljava/lang/Throwable;)Ljava/lang/Throwable;
    //   5256: athrow
    //   5257: aload_1
    //   5258: goto -> 5272
    //   5261: invokestatic a : (Ljava/lang/Throwable;)Ljava/lang/Throwable;
    //   5264: athrow
    //   5265: aload_1
    //   5266: checkcast [B
    //   5269: invokevirtual clone : ()Ljava/lang/Object;
    //   5272: aastore
    //   5273: invokevirtual invoke : (Ljava/lang/Object;[Ljava/lang/Object;)Ljava/lang/Object;
    //   5276: checkcast java/lang/Boolean
    //   5279: invokevirtual booleanValue : ()Z
    //   5282: istore #5
    //   5284: iload_2
    //   5285: ifne -> 5302
    //   5288: iinc #8, 1
    //   5291: iload_2
    //   5292: ifne -> 5161
    //   5295: goto -> 5302
    //   5298: invokestatic a : (Ljava/lang/Throwable;)Ljava/lang/Throwable;
    //   5301: athrow
    //   5302: iload #5
    //   5304: ifeq -> 5310
    //   5307: iload #5
    //   5309: ireturn
    //   5310: getstatic burp/Zezn.Ze : Ljava/lang/String;
    //   5313: getstatic burp/Zct.ZW : Ljava/lang/Object;
    //   5316: checkcast java/math/BigInteger
    //   5319: invokevirtual intValue : ()I
    //   5322: bipush #32
    //   5324: irem
    //   5325: invokestatic abs : (I)I
    //   5328: invokevirtual charAt : (I)C
    //   5331: getstatic burp/Zr4k.Zy : Ljava/lang/String;
    //   5334: getstatic burp/Zmnb.Zz : Ljava/lang/Object;
    //   5337: checkcast java/math/BigInteger
    //   5340: invokevirtual intValue : ()I
    //   5343: bipush #32
    //   5345: irem
    //   5346: invokestatic abs : (I)I
    //   5349: invokevirtual charAt : (I)C
    //   5352: if_icmple -> 5698
    //   5355: sipush #32758
    //   5358: sipush #-7815
    //   5361: invokestatic a : (II)Ljava/lang/String;
    //   5364: iconst_1
    //   5365: ldc burp/Zt7x
    //   5367: invokevirtual getClassLoader : ()Ljava/lang/ClassLoader;
    //   5370: invokestatic forName : (Ljava/lang/String;ZLjava/lang/ClassLoader;)Ljava/lang/Class;
    //   5373: invokevirtual getDeclaredFields : ()[Ljava/lang/reflect/Field;
    //   5376: astore #6
    //   5378: aload #6
    //   5380: arraylength
    //   5381: istore #7
    //   5383: iconst_0
    //   5384: istore #8
    //   5386: iload #8
    //   5388: iload #7
    //   5390: if_icmpge -> 5528
    //   5393: aload #6
    //   5395: iload #8
    //   5397: aaload
    //   5398: astore #9
    //   5400: aload #9
    //   5402: invokevirtual getModifiers : ()I
    //   5405: invokestatic isStatic : (I)Z
    //   5408: ifne -> 5418
    //   5411: goto -> 5521
    //   5414: invokestatic a : (Ljava/lang/Throwable;)Ljava/lang/Throwable;
    //   5417: athrow
    //   5418: aload #9
    //   5420: invokevirtual getType : ()Ljava/lang/Class;
    //   5423: astore #10
    //   5425: aload #10
    //   5427: ifnull -> 5508
    //   5430: aload #10
    //   5432: invokevirtual isPrimitive : ()Z
    //   5435: ifne -> 5508
    //   5438: goto -> 5445
    //   5441: invokestatic a : (Ljava/lang/Throwable;)Ljava/lang/Throwable;
    //   5444: athrow
    //   5445: aload #10
    //   5447: invokevirtual getPackage : ()Ljava/lang/Package;
    //   5450: ifnull -> 5508
    //   5453: goto -> 5460
    //   5456: invokestatic a : (Ljava/lang/Throwable;)Ljava/lang/Throwable;
    //   5459: athrow
    //   5460: aload #10
    //   5462: invokevirtual getPackage : ()Ljava/lang/Package;
    //   5465: invokevirtual getName : ()Ljava/lang/String;
    //   5468: ifnull -> 5508
    //   5471: goto -> 5478
    //   5474: invokestatic a : (Ljava/lang/Throwable;)Ljava/lang/Throwable;
    //   5477: athrow
    //   5478: aload #10
    //   5480: invokevirtual getPackage : ()Ljava/lang/Package;
    //   5483: invokevirtual getName : ()Ljava/lang/String;
    //   5486: sipush #32738
    //   5489: sipush #28487
    //   5492: invokestatic a : (II)Ljava/lang/String;
    //   5495: invokevirtual startsWith : (Ljava/lang/String;)Z
    //   5498: ifne -> 5508
    //   5501: goto -> 5508
    //   5504: invokestatic a : (Ljava/lang/Throwable;)Ljava/lang/Throwable;
    //   5507: athrow
    //   5508: aload #9
    //   5510: iconst_1
    //   5511: invokevirtual setAccessible : (Z)V
    //   5514: aload #9
    //   5516: aconst_null
    //   5517: invokevirtual get : (Ljava/lang/Object;)Ljava/lang/Object;
    //   5520: pop
    //   5521: iinc #8, 1
    //   5524: iload_2
    //   5525: ifne -> 5386
    //   5528: sipush #32760
    //   5531: sipush #8169
    //   5534: invokestatic a : (II)Ljava/lang/String;
    //   5537: invokestatic forName : (Ljava/lang/String;)Ljava/lang/Class;
    //   5540: invokevirtual getDeclaredMethods : ()[Ljava/lang/reflect/Method;
    //   5543: astore #6
    //   5545: aload #6
    //   5547: arraylength
    //   5548: istore #7
    //   5550: iconst_0
    //   5551: istore #8
    //   5553: iload #8
    //   5555: iload #7
    //   5557: if_icmpge -> 5694
    //   5560: aload #6
    //   5562: iload #8
    //   5564: aaload
    //   5565: astore #9
    //   5567: aload #9
    //   5569: invokevirtual getParameterTypes : ()[Ljava/lang/Class;
    //   5572: pop
    //   5573: aload #9
    //   5575: invokevirtual getModifiers : ()I
    //   5578: invokestatic isStatic : (I)Z
    //   5581: ifeq -> 5680
    //   5584: aload #9
    //   5586: invokevirtual getParameterTypes : ()[Ljava/lang/Class;
    //   5589: arraylength
    //   5590: iconst_2
    //   5591: if_icmpne -> 5680
    //   5594: goto -> 5601
    //   5597: invokestatic a : (Ljava/lang/Throwable;)Ljava/lang/Throwable;
    //   5600: athrow
    //   5601: aload #9
    //   5603: invokevirtual getReturnType : ()Ljava/lang/Class;
    //   5606: getstatic java/lang/Boolean.TYPE : Ljava/lang/Class;
    //   5609: if_acmpne -> 5680
    //   5612: goto -> 5619
    //   5615: invokestatic a : (Ljava/lang/Throwable;)Ljava/lang/Throwable;
    //   5618: athrow
    //   5619: aload #9
    //   5621: iconst_1
    //   5622: invokevirtual setAccessible : (Z)V
    //   5625: aload #9
    //   5627: aconst_null
    //   5628: iconst_2
    //   5629: anewarray java/lang/Object
    //   5632: dup
    //   5633: iconst_0
    //   5634: aload_0
    //   5635: aastore
    //   5636: dup
    //   5637: iconst_1
    //   5638: aload_1
    //   5639: ifnonnull -> 5657
    //   5642: goto -> 5649
    //   5645: invokestatic a : (Ljava/lang/Throwable;)Ljava/lang/Throwable;
    //   5648: athrow
    //   5649: aload_1
    //   5650: goto -> 5664
    //   5653: invokestatic a : (Ljava/lang/Throwable;)Ljava/lang/Throwable;
    //   5656: athrow
    //   5657: aload_1
    //   5658: checkcast [B
    //   5661: invokevirtual clone : ()Ljava/lang/Object;
    //   5664: aastore
    //   5665: invokevirtual invoke : (Ljava/lang/Object;[Ljava/lang/Object;)Ljava/lang/Object;
    //   5668: checkcast java/lang/Boolean
    //   5671: invokevirtual booleanValue : ()Z
    //   5674: istore #5
    //   5676: iload_2
    //   5677: ifne -> 5694
    //   5680: iinc #8, 1
    //   5683: iload_2
    //   5684: ifne -> 5553
    //   5687: goto -> 5694
    //   5690: invokestatic a : (Ljava/lang/Throwable;)Ljava/lang/Throwable;
    //   5693: athrow
    //   5694: iload_2
    //   5695: ifne -> 6037
    //   5698: sipush #32757
    //   5701: sipush #-16171
    //   5704: invokestatic a : (II)Ljava/lang/String;
    //   5707: iconst_1
    //   5708: ldc burp/Zejj
    //   5710: invokevirtual getClassLoader : ()Ljava/lang/ClassLoader;
    //   5713: invokestatic forName : (Ljava/lang/String;ZLjava/lang/ClassLoader;)Ljava/lang/Class;
    //   5716: invokevirtual getDeclaredFields : ()[Ljava/lang/reflect/Field;
    //   5719: astore #6
    //   5721: aload #6
    //   5723: arraylength
    //   5724: istore #7
    //   5726: iconst_0
    //   5727: istore #8
    //   5729: iload #8
    //   5731: iload #7
    //   5733: if_icmpge -> 5871
    //   5736: aload #6
    //   5738: iload #8
    //   5740: aaload
    //   5741: astore #9
    //   5743: aload #9
    //   5745: invokevirtual getModifiers : ()I
    //   5748: invokestatic isStatic : (I)Z
    //   5751: ifne -> 5761
    //   5754: goto -> 5864
    //   5757: invokestatic a : (Ljava/lang/Throwable;)Ljava/lang/Throwable;
    //   5760: athrow
    //   5761: aload #9
    //   5763: invokevirtual getType : ()Ljava/lang/Class;
    //   5766: astore #10
    //   5768: aload #10
    //   5770: ifnull -> 5851
    //   5773: aload #10
    //   5775: invokevirtual isPrimitive : ()Z
    //   5778: ifne -> 5851
    //   5781: goto -> 5788
    //   5784: invokestatic a : (Ljava/lang/Throwable;)Ljava/lang/Throwable;
    //   5787: athrow
    //   5788: aload #10
    //   5790: invokevirtual getPackage : ()Ljava/lang/Package;
    //   5793: ifnull -> 5851
    //   5796: goto -> 5803
    //   5799: invokestatic a : (Ljava/lang/Throwable;)Ljava/lang/Throwable;
    //   5802: athrow
    //   5803: aload #10
    //   5805: invokevirtual getPackage : ()Ljava/lang/Package;
    //   5808: invokevirtual getName : ()Ljava/lang/String;
    //   5811: ifnull -> 5851
    //   5814: goto -> 5821
    //   5817: invokestatic a : (Ljava/lang/Throwable;)Ljava/lang/Throwable;
    //   5820: athrow
    //   5821: aload #10
    //   5823: invokevirtual getPackage : ()Ljava/lang/Package;
    //   5826: invokevirtual getName : ()Ljava/lang/String;
    //   5829: sipush #32738
    //   5832: sipush #28487
    //   5835: invokestatic a : (II)Ljava/lang/String;
    //   5838: invokevirtual startsWith : (Ljava/lang/String;)Z
    //   5841: ifne -> 5851
    //   5844: goto -> 5851
    //   5847: invokestatic a : (Ljava/lang/Throwable;)Ljava/lang/Throwable;
    //   5850: athrow
    //   5851: aload #9
    //   5853: iconst_1
    //   5854: invokevirtual setAccessible : (Z)V
    //   5857: aload #9
    //   5859: aconst_null
    //   5860: invokevirtual get : (Ljava/lang/Object;)Ljava/lang/Object;
    //   5863: pop
    //   5864: iinc #8, 1
    //   5867: iload_2
    //   5868: ifne -> 5729
    //   5871: sipush #32763
    //   5874: sipush #-6670
    //   5877: invokestatic a : (II)Ljava/lang/String;
    //   5880: invokestatic forName : (Ljava/lang/String;)Ljava/lang/Class;
    //   5883: invokevirtual getDeclaredMethods : ()[Ljava/lang/reflect/Method;
    //   5886: astore #6
    //   5888: aload #6
    //   5890: arraylength
    //   5891: istore #7
    //   5893: iconst_0
    //   5894: istore #8
    //   5896: iload #8
    //   5898: iload #7
    //   5900: if_icmpge -> 6037
    //   5903: aload #6
    //   5905: iload #8
    //   5907: aaload
    //   5908: astore #9
    //   5910: aload #9
    //   5912: invokevirtual getParameterTypes : ()[Ljava/lang/Class;
    //   5915: pop
    //   5916: aload #9
    //   5918: invokevirtual getModifiers : ()I
    //   5921: invokestatic isStatic : (I)Z
    //   5924: ifeq -> 6023
    //   5927: aload #9
    //   5929: invokevirtual getParameterTypes : ()[Ljava/lang/Class;
    //   5932: arraylength
    //   5933: iconst_2
    //   5934: if_icmpne -> 6023
    //   5937: goto -> 5944
    //   5940: invokestatic a : (Ljava/lang/Throwable;)Ljava/lang/Throwable;
    //   5943: athrow
    //   5944: aload #9
    //   5946: invokevirtual getReturnType : ()Ljava/lang/Class;
    //   5949: getstatic java/lang/Boolean.TYPE : Ljava/lang/Class;
    //   5952: if_acmpne -> 6023
    //   5955: goto -> 5962
    //   5958: invokestatic a : (Ljava/lang/Throwable;)Ljava/lang/Throwable;
    //   5961: athrow
    //   5962: aload #9
    //   5964: iconst_1
    //   5965: invokevirtual setAccessible : (Z)V
    //   5968: aload #9
    //   5970: aconst_null
    //   5971: iconst_2
    //   5972: anewarray java/lang/Object
    //   5975: dup
    //   5976: iconst_0
    //   5977: aload_0
    //   5978: aastore
    //   5979: dup
    //   5980: iconst_1
    //   5981: aload_1
    //   5982: ifnonnull -> 6000
    //   5985: goto -> 5992
    //   5988: invokestatic a : (Ljava/lang/Throwable;)Ljava/lang/Throwable;
    //   5991: athrow
    //   5992: aload_1
    //   5993: goto -> 6007
    //   5996: invokestatic a : (Ljava/lang/Throwable;)Ljava/lang/Throwable;
    //   5999: athrow
    //   6000: aload_1
    //   6001: checkcast [B
    //   6004: invokevirtual clone : ()Ljava/lang/Object;
    //   6007: aastore
    //   6008: invokevirtual invoke : (Ljava/lang/Object;[Ljava/lang/Object;)Ljava/lang/Object;
    //   6011: checkcast java/lang/Boolean
    //   6014: invokevirtual booleanValue : ()Z
    //   6017: istore #5
    //   6019: iload_2
    //   6020: ifne -> 6037
    //   6023: iinc #8, 1
    //   6026: iload_2
    //   6027: ifne -> 5896
    //   6030: goto -> 6037
    //   6033: invokestatic a : (Ljava/lang/Throwable;)Ljava/lang/Throwable;
    //   6036: athrow
    //   6037: iload #5
    //   6039: ireturn
    //   6040: astore_3
    //   6041: new java/lang/Exception
    //   6044: dup
    //   6045: aload_3
    //   6046: invokevirtual getMessage : ()Ljava/lang/String;
    //   6049: invokespecial <init> : (Ljava/lang/String;)V
    //   6052: athrow
    // Exception table:
    //   from	to	target	type
    //   4	3840	6040	java/lang/Throwable
    //   22	198	201	java/lang/Throwable
    //   168	235	238	java/lang/Throwable
    //   205	272	275	java/lang/Throwable
    //   242	309	312	java/lang/Throwable
    //   279	346	349	java/lang/Throwable
    //   316	383	386	java/lang/Throwable
    //   353	420	423	java/lang/Throwable
    //   390	457	460	java/lang/Throwable
    //   427	494	497	java/lang/Throwable
    //   464	531	534	java/lang/Throwable
    //   501	568	571	java/lang/Throwable
    //   538	605	608	java/lang/Throwable
    //   575	642	645	java/lang/Throwable
    //   612	679	682	java/lang/Throwable
    //   649	716	719	java/lang/Throwable
    //   686	753	756	java/lang/Throwable
    //   723	790	793	java/lang/Throwable
    //   760	827	830	java/lang/Throwable
    //   797	864	867	java/lang/Throwable
    //   834	901	904	java/lang/Throwable
    //   871	938	941	java/lang/Throwable
    //   908	975	978	java/lang/Throwable
    //   945	1012	1015	java/lang/Throwable
    //   982	1049	1052	java/lang/Throwable
    //   1019	1086	1089	java/lang/Throwable
    //   1056	1123	1126	java/lang/Throwable
    //   1093	1160	1163	java/lang/Throwable
    //   1130	1197	1200	java/lang/Throwable
    //   1167	1234	1237	java/lang/Throwable
    //   1204	1271	1274	java/lang/Throwable
    //   1241	1308	1311	java/lang/Throwable
    //   1278	1341	1344	java/lang/Throwable
    //   1381	1555	1558	java/lang/Throwable
    //   1524	1593	1596	java/lang/Throwable
    //   1562	1631	1634	java/lang/Throwable
    //   1600	1669	1672	java/lang/Throwable
    //   1638	1707	1710	java/lang/Throwable
    //   1676	1745	1748	java/lang/Throwable
    //   1714	1783	1786	java/lang/Throwable
    //   1752	1821	1824	java/lang/Throwable
    //   1790	1859	1862	java/lang/Throwable
    //   1828	1897	1900	java/lang/Throwable
    //   1866	1935	1938	java/lang/Throwable
    //   1904	1973	1976	java/lang/Throwable
    //   1942	2011	2014	java/lang/Throwable
    //   1980	2049	2052	java/lang/Throwable
    //   2018	2087	2090	java/lang/Throwable
    //   2056	2125	2128	java/lang/Throwable
    //   2094	2163	2166	java/lang/Throwable
    //   2132	2201	2204	java/lang/Throwable
    //   2170	2239	2242	java/lang/Throwable
    //   2208	2277	2280	java/lang/Throwable
    //   2246	2315	2318	java/lang/Throwable
    //   2284	2353	2356	java/lang/Throwable
    //   2322	2391	2394	java/lang/Throwable
    //   2360	2429	2432	java/lang/Throwable
    //   2398	2467	2470	java/lang/Throwable
    //   2436	2505	2508	java/lang/Throwable
    //   2474	2543	2546	java/lang/Throwable
    //   2512	2581	2584	java/lang/Throwable
    //   2550	2619	2622	java/lang/Throwable
    //   2588	2657	2660	java/lang/Throwable
    //   2626	2695	2698	java/lang/Throwable
    //   2664	2729	2732	java/lang/Throwable
    //   2814	2828	2828	java/lang/Throwable
    //   2839	2852	2855	java/lang/Throwable
    //   2844	2867	2870	java/lang/Throwable
    //   2859	2885	2888	java/lang/Throwable
    //   2874	2915	2918	java/lang/Throwable
    //   2981	3008	3011	java/lang/Throwable
    //   2998	3029	3032	java/lang/Throwable
    //   3015	3059	3062	java/lang/Throwable
    //   3036	3070	3070	java/lang/Throwable
    //   3081	3097	3100	java/lang/Throwable
    //   3197	3211	3211	java/lang/Throwable
    //   3222	3235	3238	java/lang/Throwable
    //   3227	3250	3253	java/lang/Throwable
    //   3242	3268	3271	java/lang/Throwable
    //   3257	3298	3301	java/lang/Throwable
    //   3364	3391	3394	java/lang/Throwable
    //   3381	3409	3412	java/lang/Throwable
    //   3398	3439	3442	java/lang/Throwable
    //   3416	3450	3450	java/lang/Throwable
    //   3473	3484	3487	java/lang/Throwable
    //   3539	3553	3553	java/lang/Throwable
    //   3564	3577	3580	java/lang/Throwable
    //   3569	3592	3595	java/lang/Throwable
    //   3584	3610	3613	java/lang/Throwable
    //   3599	3640	3643	java/lang/Throwable
    //   3706	3733	3736	java/lang/Throwable
    //   3723	3751	3754	java/lang/Throwable
    //   3740	3781	3784	java/lang/Throwable
    //   3758	3792	3792	java/lang/Throwable
    //   3815	3826	3829	java/lang/Throwable
    //   3841	4574	6040	java/lang/Throwable
    //   3931	3945	3945	java/lang/Throwable
    //   3956	3969	3972	java/lang/Throwable
    //   3961	3984	3987	java/lang/Throwable
    //   3976	4002	4005	java/lang/Throwable
    //   3991	4032	4035	java/lang/Throwable
    //   4098	4125	4128	java/lang/Throwable
    //   4115	4143	4146	java/lang/Throwable
    //   4132	4173	4176	java/lang/Throwable
    //   4150	4184	4184	java/lang/Throwable
    //   4207	4218	4221	java/lang/Throwable
    //   4274	4288	4288	java/lang/Throwable
    //   4299	4312	4315	java/lang/Throwable
    //   4304	4327	4330	java/lang/Throwable
    //   4319	4345	4348	java/lang/Throwable
    //   4334	4375	4378	java/lang/Throwable
    //   4440	4467	4470	java/lang/Throwable
    //   4457	4485	4488	java/lang/Throwable
    //   4474	4515	4518	java/lang/Throwable
    //   4492	4526	4526	java/lang/Throwable
    //   4549	4560	4563	java/lang/Throwable
    //   4575	5309	6040	java/lang/Throwable
    //   4665	4679	4679	java/lang/Throwable
    //   4690	4703	4706	java/lang/Throwable
    //   4695	4718	4721	java/lang/Throwable
    //   4710	4736	4739	java/lang/Throwable
    //   4725	4766	4769	java/lang/Throwable
    //   4832	4859	4862	java/lang/Throwable
    //   4849	4877	4880	java/lang/Throwable
    //   4866	4907	4910	java/lang/Throwable
    //   4884	4918	4918	java/lang/Throwable
    //   4941	4952	4955	java/lang/Throwable
    //   5008	5022	5022	java/lang/Throwable
    //   5033	5046	5049	java/lang/Throwable
    //   5038	5061	5064	java/lang/Throwable
    //   5053	5079	5082	java/lang/Throwable
    //   5068	5109	5112	java/lang/Throwable
    //   5175	5202	5205	java/lang/Throwable
    //   5192	5220	5223	java/lang/Throwable
    //   5209	5250	5253	java/lang/Throwable
    //   5227	5261	5261	java/lang/Throwable
    //   5284	5295	5298	java/lang/Throwable
    //   5310	6039	6040	java/lang/Throwable
    //   5400	5414	5414	java/lang/Throwable
    //   5425	5438	5441	java/lang/Throwable
    //   5430	5453	5456	java/lang/Throwable
    //   5445	5471	5474	java/lang/Throwable
    //   5460	5501	5504	java/lang/Throwable
    //   5567	5594	5597	java/lang/Throwable
    //   5584	5612	5615	java/lang/Throwable
    //   5601	5642	5645	java/lang/Throwable
    //   5619	5653	5653	java/lang/Throwable
    //   5676	5687	5690	java/lang/Throwable
    //   5743	5757	5757	java/lang/Throwable
    //   5768	5781	5784	java/lang/Throwable
    //   5773	5796	5799	java/lang/Throwable
    //   5788	5814	5817	java/lang/Throwable
    //   5803	5844	5847	java/lang/Throwable
    //   5910	5937	5940	java/lang/Throwable
    //   5927	5955	5958	java/lang/Throwable
    //   5944	5985	5988	java/lang/Throwable
    //   5962	5996	5996	java/lang/Throwable
    //   6019	6030	6033	java/lang/Throwable
  }
  
  static void ZM(Object paramObject) {
    Zmnb.ZD = a(32759, -14597);
    Zmnb.Zz = new BigInteger(a(32754, 20111));
    boolean bool = Zt2e.ZK();
    try {
      try {
        if (Zsun.Zu.charAt(Math.abs(((BigInteger)Zexu.ZI).intValue() % 32)) <= Zlg1.ZG.charAt(Math.abs(((BigInteger)Zero.ZE).intValue() % 32))) {
          try {
            Zlp7.Zl(Class.forName(a(32764, -24502)));
            if (bool)
              Zkfb.Zr(Class.forName(a(32765, 13822))); 
          } catch (Throwable throwable) {
            throw a(null);
          } 
          return;
        } 
      } catch (Throwable throwable) {
        throw a(null);
      } 
      Zkfb.Zr(Class.forName(a(32765, 13822)));
    } catch (Throwable throwable) {}
  }
  
  static void ZB(Object[] paramArrayOfObject, Object paramObject) throws Throwable {}
  
  static {
    // Byte code:
    //   0: bipush #25
    //   2: anewarray java/lang/String
    //   5: astore #5
    //   7: iconst_0
    //   8: istore_3
    //   9: ldc '=:uH\Lg|m5$E\\tF Sx\\n\\t U\\to)\\t `M|E2TsNs(+,kLgB5DEouoQq_  \\bzc&RRg\\bqi-;&\\t-s\\\t>1m\\tBH \\t+dy.\\t/3a\\toxv~Y\\tS\\t4M\\t:E85;\\tTJU\\tm\\nKR|\\tMZtW\\tcVkn G ;Y]0o<K`3g'
    //   11: dup
    //   12: astore_2
    //   13: invokevirtual length : ()I
    //   16: istore #4
    //   18: bipush #32
    //   20: istore_1
    //   21: iconst_m1
    //   22: istore_0
    //   23: bipush #90
    //   25: iinc #0, 1
    //   28: aload_2
    //   29: iload_0
    //   30: dup
    //   31: iload_1
    //   32: iadd
    //   33: invokevirtual substring : (II)Ljava/lang/String;
    //   36: iconst_m1
    //   37: goto -> 143
    //   40: aload #5
    //   42: swap
    //   43: iload_3
    //   44: iinc #3, 1
    //   47: swap
    //   48: aastore
    //   49: iload_0
    //   50: iload_1
    //   51: iadd
    //   52: dup
    //   53: istore_0
    //   54: iload #4
    //   56: if_icmpge -> 68
    //   59: aload_2
    //   60: iload_0
    //   61: invokevirtual charAt : (I)C
    //   64: istore_1
    //   65: goto -> 23
    //   68: ldc '@>*W\\tLu>Q'
    //   70: dup
    //   71: astore_2
    //   72: invokevirtual length : ()I
    //   75: istore #4
    //   77: bipush #9
    //   79: istore_1
    //   80: iconst_m1
    //   81: istore_0
    //   82: bipush #15
    //   84: iinc #0, 1
    //   87: aload_2
    //   88: iload_0
    //   89: dup
    //   90: iload_1
    //   91: iadd
    //   92: invokevirtual substring : (II)Ljava/lang/String;
    //   95: iconst_0
    //   96: goto -> 143
    //   99: aload #5
    //   101: swap
    //   102: iload_3
    //   103: iinc #3, 1
    //   106: swap
    //   107: aastore
    //   108: iload_0
    //   109: iload_1
    //   110: iadd
    //   111: dup
    //   112: istore_0
    //   113: iload #4
    //   115: if_icmpge -> 127
    //   118: aload_2
    //   119: iload_0
    //   120: invokevirtual charAt : (I)C
    //   123: istore_1
    //   124: goto -> 82
    //   127: aload #5
    //   129: putstatic burp/Zeu2.a : [Ljava/lang/String;
    //   132: bipush #25
    //   134: anewarray java/lang/String
    //   137: putstatic burp/Zeu2.b : [Ljava/lang/String;
    //   140: goto -> 300
    //   143: dup_x2
    //   144: pop
    //   145: invokevirtual toCharArray : ()[C
    //   148: dup_x1
    //   149: arraylength
    //   150: dup_x2
    //   151: pop
    //   152: iconst_0
    //   153: istore #6
    //   155: dup2_x1
    //   156: pop2
    //   157: dup_x2
    //   158: iconst_1
    //   159: if_icmpgt -> 260
    //   162: dup2
    //   163: swap
    //   164: iload #6
    //   166: dup2_x1
    //   167: caload
    //   168: swap
    //   169: iload #6
    //   171: bipush #7
    //   173: irem
    //   174: tableswitch default -> 242, 0 -> 212, 1 -> 217, 2 -> 222, 3 -> 227, 4 -> 232, 5 -> 237
    //   212: bipush #37
    //   214: goto -> 244
    //   217: bipush #55
    //   219: goto -> 244
    //   222: bipush #63
    //   224: goto -> 244
    //   227: bipush #95
    //   229: goto -> 244
    //   232: bipush #127
    //   234: goto -> 244
    //   237: bipush #64
    //   239: goto -> 244
    //   242: bipush #107
    //   244: ixor
    //   245: ixor
    //   246: i2c
    //   247: castore
    //   248: iinc #6, 1
    //   251: dup
    //   252: ifne -> 260
    //   255: dup2
    //   256: dup_x1
    //   257: goto -> 166
    //   260: dup2_x1
    //   261: pop2
    //   262: dup_x2
    //   263: iload #6
    //   265: if_icmpgt -> 162
    //   268: pop
    //   269: new java/lang/String
    //   272: dup_x1
    //   273: swap
    //   274: invokespecial <init> : ([C)V
    //   277: invokevirtual intern : ()Ljava/lang/String;
    //   280: swap
    //   281: pop
    //   282: swap
    //   283: tableswitch default -> 40, 0 -> 99
    //   300: sipush #32737
    //   303: sipush #22344
    //   306: invokestatic a : (II)Ljava/lang/String;
    //   309: putstatic burp/Zeu2.ZK : Ljava/lang/String;
    //   312: new java/math/BigInteger
    //   315: dup
    //   316: iconst_1
    //   317: bipush #32
    //   319: newarray byte
    //   321: dup
    //   322: iconst_0
    //   323: bipush #37
    //   325: bastore
    //   326: dup
    //   327: iconst_1
    //   328: bipush #-37
    //   330: bastore
    //   331: dup
    //   332: iconst_2
    //   333: bipush #114
    //   335: bastore
    //   336: dup
    //   337: iconst_3
    //   338: bipush #-110
    //   340: bastore
    //   341: dup
    //   342: iconst_4
    //   343: bipush #-19
    //   345: bastore
    //   346: dup
    //   347: iconst_5
    //   348: bipush #34
    //   350: bastore
    //   351: dup
    //   352: bipush #6
    //   354: bipush #-77
    //   356: bastore
    //   357: dup
    //   358: bipush #7
    //   360: bipush #-75
    //   362: bastore
    //   363: dup
    //   364: bipush #8
    //   366: bipush #73
    //   368: bastore
    //   369: dup
    //   370: bipush #9
    //   372: bipush #-44
    //   374: bastore
    //   375: dup
    //   376: bipush #10
    //   378: bipush #-58
    //   380: bastore
    //   381: dup
    //   382: bipush #11
    //   384: bipush #-122
    //   386: bastore
    //   387: dup
    //   388: bipush #12
    //   390: bipush #-85
    //   392: bastore
    //   393: dup
    //   394: bipush #13
    //   396: bipush #-38
    //   398: bastore
    //   399: dup
    //   400: bipush #14
    //   402: bipush #95
    //   404: bastore
    //   405: dup
    //   406: bipush #15
    //   408: iconst_3
    //   409: bastore
    //   410: dup
    //   411: bipush #16
    //   413: bipush #-36
    //   415: bastore
    //   416: dup
    //   417: bipush #17
    //   419: bipush #-87
    //   421: bastore
    //   422: dup
    //   423: bipush #18
    //   425: bipush #-107
    //   427: bastore
    //   428: dup
    //   429: bipush #19
    //   431: bipush #100
    //   433: bastore
    //   434: dup
    //   435: bipush #20
    //   437: bipush #-128
    //   439: bastore
    //   440: dup
    //   441: bipush #21
    //   443: bipush #39
    //   445: bastore
    //   446: dup
    //   447: bipush #22
    //   449: bipush #-3
    //   451: bastore
    //   452: dup
    //   453: bipush #23
    //   455: bipush #-128
    //   457: bastore
    //   458: dup
    //   459: bipush #24
    //   461: bipush #-7
    //   463: bastore
    //   464: dup
    //   465: bipush #25
    //   467: bipush #119
    //   469: bastore
    //   470: dup
    //   471: bipush #26
    //   473: bipush #39
    //   475: bastore
    //   476: dup
    //   477: bipush #27
    //   479: bipush #-128
    //   481: bastore
    //   482: dup
    //   483: bipush #28
    //   485: bipush #74
    //   487: bastore
    //   488: dup
    //   489: bipush #29
    //   491: iconst_1
    //   492: bastore
    //   493: dup
    //   494: bipush #30
    //   496: bipush #21
    //   498: bastore
    //   499: dup
    //   500: bipush #31
    //   502: bipush #-125
    //   504: bastore
    //   505: invokespecial <init> : (I[B)V
    //   508: putstatic burp/Zeu2.ZW : Ljava/lang/Object;
    //   511: return
  }
  
  private static Throwable a(Throwable paramThrowable) {
    return paramThrowable;
  }
  
  private static String a(int paramInt1, int paramInt2) {
    int i = (paramInt1 ^ 0x7FF7) & 0xFFFF;
    if (b[i] == null) {
      char[] arrayOfChar = a[i].toCharArray();
      switch (arrayOfChar[0] & 0xFF) {
        case 0:
        
        case 1:
        
        case 2:
        
        case 3:
        
        case 4:
        
        case 5:
        
        case 6:
        
        case 7:
        
        case 8:
        
        case 9:
        
        case 10:
        
        case 11:
        
        case 12:
        
        case 13:
        
        case 14:
        
        case 15:
        
        case 16:
        
        case 17:
        
        case 18:
        
        case 19:
        
        case 20:
        
        case 21:
        
        case 22:
        
        case 23:
        
        case 24:
        
        case 25:
        
        case 26:
        
        case 27:
        
        case 28:
        
        case 29:
        
        case 30:
        
        case 31:
        
        case 32:
        
        case 33:
        
        case 34:
        
        case 35:
        
        case 36:
        
        case 37:
        
        case 38:
        
        case 39:
        
        case 40:
        
        case 41:
        
        case 42:
        
        case 43:
        
        case 44:
        
        case 45:
        
        case 46:
        
        case 47:
        
        case 48:
        
        case 49:
        
        case 50:
        
        case 51:
        
        case 52:
        
        case 53:
        
        case 54:
        
        case 55:
        
        case 56:
        
        case 57:
        
        case 58:
        
        case 59:
        
        case 60:
        
        case 61:
        
        case 62:
        
        case 63:
        
        case 64:
        
        case 65:
        
        case 66:
        
        case 67:
        
        case 68:
        
        case 69:
        
        case 70:
        
        case 71:
        
        case 72:
        
        case 73:
        
        case 74:
        
        case 75:
        
        case 76:
        
        case 77:
        
        case 78:
        
        case 79:
        
        case 80:
        
        case 81:
        
        case 82:
        
        case 83:
        
        case 84:
        
        case 85:
        
        case 86:
        
        case 87:
        
        case 88:
        
        case 89:
        
        case 90:
        
        case 91:
        
        case 92:
        
        case 93:
        
        case 94:
        
        case 95:
        
        case 96:
        
        case 97:
        
        case 98:
        
        case 99:
        
        case 100:
        
        case 101:
        
        case 102:
        
        case 103:
        
        case 104:
        
        case 105:
        
        case 106:
        
        case 107:
        
        case 108:
        
        case 109:
        
        case 110:
        
        case 111:
        
        case 112:
        
        case 113:
        
        case 114:
        
        case 115:
        
        case 116:
        
        case 117:
        
        case 118:
        
        case 119:
        
        case 120:
        
        case 121:
        
        case 122:
        
        case 123:
        
        case 124:
        
        case 125:
        
        case 126:
        
        case 127:
        
        case 128:
        
        case 129:
        
        case 130:
        
        case 131:
        
        case 132:
        
        case 133:
        
        case 134:
        
        case 135:
        
        case 136:
        
        case 137:
        
        case 138:
        
        case 139:
        
        case 140:
        
        case 141:
        
        case 142:
        
        case 143:
        
        case 144:
        
        case 145:
        
        case 146:
        
        case 147:
        
        case 148:
        
        case 149:
        
        case 150:
        
        case 151:
        
        case 152:
        
        case 153:
        
        case 154:
        
        case 155:
        
        case 156:
        
        case 157:
        
        case 158:
        
        case 159:
        
        case 160:
        
        case 161:
        
        case 162:
        
        case 163:
        
        case 164:
        
        case 165:
        
        case 166:
        
        case 167:
        
        case 168:
        
        case 169:
        
        case 170:
        
        case 171:
        
        case 172:
        
        case 173:
        
        case 174:
        
        case 175:
        
        case 176:
        
        case 177:
        
        case 178:
        
        case 179:
        
        case 180:
        
        case 181:
        
        case 182:
        
        case 183:
        
        case 184:
        
        case 185:
        
        case 186:
        
        case 187:
        
        case 188:
        
        case 189:
        
        case 190:
        
        case 191:
        
        case 192:
        
        case 193:
        
        case 194:
        
        case 195:
        
        case 196:
        
        case 197:
        
        case 198:
        
        case 199:
        
        case 200:
        
        case 201:
        
        case 202:
        
        case 203:
        
        case 204:
        
        case 205:
        
        case 206:
        
        case 207:
        
        case 208:
        
        case 209:
        
        case 210:
        
        case 211:
        
        case 212:
        
        case 213:
        
        case 214:
        
        case 215:
        
        case 216:
        
        case 217:
        
        case 218:
        
        case 219:
        
        case 220:
        
        case 221:
        
        case 222:
        
        case 223:
        
        case 224:
        
        case 225:
        
        case 226:
        
        case 227:
        
        case 228:
        
        case 229:
        
        case 230:
        
        case 231:
        
        case 232:
        
        case 233:
        
        case 234:
        
        case 235:
        
        case 236:
        
        case 237:
        
        case 238:
        
        case 239:
        
        case 240:
        
        case 241:
        
        case 242:
        
        case 243:
        
        case 244:
        
        case 245:
        
        case 246:
        
        case 247:
        
        case 248:
        
        case 249:
        
        case 250:
        
        case 251:
        
        case 252:
        
        case 253:
        
        case 254:
        
        default:
          break;
      } 
      byte b1 = 11;
      int j = (paramInt2 & 0xFF) - b1;
      if (j < 0)
        j += 256; 
      int k = ((paramInt2 & 0xFFFF) >>> 8) - b1;
      if (k < 0)
        k += 256; 
      for (byte b2 = 0; b2 < arrayOfChar.length; b2++) {
        int m = b2 % 2;
        if (m == 0) {
          arrayOfChar[b2] = (char)(arrayOfChar[b2] ^ j);
          j = ((j >>> 3 | j << 5) ^ arrayOfChar[b2]) & 0xFF;
        } else {
          arrayOfChar[b2] = (char)(arrayOfChar[b2] ^ k);
          k = ((k >>> 3 | k << 5) ^ arrayOfChar[b2]) & 0xFF;
        } 
      } 
      b[i] = (new String(arrayOfChar)).intern();
    } 
    return b[i];
  }
}


/* Location:              C:\Program Files\BurpSuitePro\burpsuite_pro.jar!\burp\Zeu2.class
 * Java compiler version: 21 (65.0)
 * JD-Core Version:       1.1.3
 */