package burp;

import java.util.List;

public class Zeu3 extends Zeus {
  Zeu3(Zl_v paramZl_v, List<Ztj1> paramList, Zxts paramZxts, Zbnt paramZbnt, Zr_4 paramZr_4, Zr1j paramZr1j) {
    super(paramZl_v, paramList, paramZxts, paramZbnt, paramZr_4, paramZr1j);
  }
  
  protected void Zd() {
    // Byte code:
    //   0: invokestatic Zk : ()[I
    //   3: astore_1
    //   4: getstatic burp/Zlxu.Zy : [I
    //   7: aload_0
    //   8: getfield ZD : Lburp/Zkcl;
    //   11: invokevirtual ordinal : ()I
    //   14: iaload
    //   15: tableswitch default -> 147, 1 -> 48, 2 -> 48, 3 -> 48, 4 -> 82, 5 -> 82
    //   48: aload_0
    //   49: getfield Zy : Lburp/Zl_v;
    //   52: iconst_1
    //   53: invokeinterface Zi : (I)V
    //   58: aload_0
    //   59: getfield Zy : Lburp/Zl_v;
    //   62: iconst_2
    //   63: invokeinterface Zi : (I)V
    //   68: aload_0
    //   69: getfield Zy : Lburp/Zl_v;
    //   72: iconst_3
    //   73: invokeinterface Zi : (I)V
    //   78: aload_1
    //   79: ifnonnull -> 161
    //   82: aload_0
    //   83: getfield ZW : Z
    //   86: ifeq -> 113
    //   89: aload_0
    //   90: getfield Zy : Lburp/Zl_v;
    //   93: iconst_1
    //   94: invokeinterface ZA : (I)V
    //   99: aload_0
    //   100: getfield Zy : Lburp/Zl_v;
    //   103: iconst_3
    //   104: invokeinterface ZA : (I)V
    //   109: aload_1
    //   110: ifnonnull -> 133
    //   113: aload_0
    //   114: getfield Zy : Lburp/Zl_v;
    //   117: iconst_1
    //   118: invokeinterface Zi : (I)V
    //   123: aload_0
    //   124: getfield Zy : Lburp/Zl_v;
    //   127: iconst_3
    //   128: invokeinterface Zi : (I)V
    //   133: aload_0
    //   134: getfield Zy : Lburp/Zl_v;
    //   137: iconst_2
    //   138: invokeinterface ZA : (I)V
    //   143: aload_1
    //   144: ifnonnull -> 161
    //   147: iconst_0
    //   148: getstatic net/portswigger/Zqf.Zk : Lnet/portswigger/Zqf;
    //   151: aload_0
    //   152: getfield ZD : Lburp/Zkcl;
    //   155: invokevirtual toString : ()Ljava/lang/String;
    //   158: invokestatic ZT : (ZLnet/portswigger/Zqf;Ljava/lang/String;)V
    //   161: return
  }
}


/* Location:              C:\Program Files\BurpSuitePro\burpsuite_pro.jar!\burp\Zeu3.class
 * Java compiler version: 21 (65.0)
 * JD-Core Version:       1.1.3
 */