package burp;

import java.math.BigInteger;

class Zeva extends ClassLoader {
  static String Zo;
  
  static Object Zf;
  
  private static final String[] a;
  
  private static final String[] b;
  
  static void ZK(Object[] paramArrayOfObject, Object paramObject) throws Throwable {}
  
  static boolean Zi(Object[] paramArrayOfObject, Object paramObject) throws Throwable {
    // Byte code:
    //   0: invokestatic ZN : ()Z
    //   3: istore_2
    //   4: ldc2_w 8682522807148012
    //   7: invokestatic currentTimeMillis : ()J
    //   10: lxor
    //   11: lstore #4
    //   13: lload #4
    //   15: ldc2_w 25214903917
    //   18: lmul
    //   19: ldc2_w 11
    //   22: ladd
    //   23: ldc2_w 281474976710655
    //   26: land
    //   27: lstore #4
    //   29: lload #4
    //   31: bipush #32
    //   33: lshl
    //   34: lstore #6
    //   36: lload #4
    //   38: ldc2_w 25214903917
    //   41: lmul
    //   42: ldc2_w 11
    //   45: ladd
    //   46: ldc2_w 281474976710655
    //   49: land
    //   50: lstore #4
    //   52: lload #6
    //   54: lload #4
    //   56: ladd
    //   57: lstore #6
    //   59: bipush #16
    //   61: newarray byte
    //   63: dup
    //   64: iconst_0
    //   65: bipush #48
    //   67: bastore
    //   68: dup
    //   69: iconst_1
    //   70: bipush #49
    //   72: bastore
    //   73: dup
    //   74: iconst_2
    //   75: bipush #50
    //   77: bastore
    //   78: dup
    //   79: iconst_3
    //   80: bipush #51
    //   82: bastore
    //   83: dup
    //   84: iconst_4
    //   85: bipush #52
    //   87: bastore
    //   88: dup
    //   89: iconst_5
    //   90: bipush #53
    //   92: bastore
    //   93: dup
    //   94: bipush #6
    //   96: bipush #54
    //   98: bastore
    //   99: dup
    //   100: bipush #7
    //   102: bipush #55
    //   104: bastore
    //   105: dup
    //   106: bipush #8
    //   108: bipush #56
    //   110: bastore
    //   111: dup
    //   112: bipush #9
    //   114: bipush #57
    //   116: bastore
    //   117: dup
    //   118: bipush #10
    //   120: bipush #97
    //   122: bastore
    //   123: dup
    //   124: bipush #11
    //   126: bipush #98
    //   128: bastore
    //   129: dup
    //   130: bipush #12
    //   132: bipush #99
    //   134: bastore
    //   135: dup
    //   136: bipush #13
    //   138: bipush #100
    //   140: bastore
    //   141: dup
    //   142: bipush #14
    //   144: bipush #101
    //   146: bastore
    //   147: dup
    //   148: bipush #15
    //   150: bipush #102
    //   152: bastore
    //   153: astore #8
    //   155: bipush #64
    //   157: newarray byte
    //   159: astore #9
    //   161: bipush #64
    //   163: istore #10
    //   165: bipush #16
    //   167: istore #11
    //   169: iload #11
    //   171: iconst_1
    //   172: isub
    //   173: i2l
    //   174: lstore #12
    //   176: aload #9
    //   178: iinc #10, -1
    //   181: iload #10
    //   183: aload #8
    //   185: lload #6
    //   187: lload #12
    //   189: land
    //   190: l2i
    //   191: baload
    //   192: bastore
    //   193: lload #6
    //   195: iconst_4
    //   196: lushr
    //   197: lstore #6
    //   199: lload #6
    //   201: lconst_0
    //   202: lcmp
    //   203: ifne -> 176
    //   206: bipush #64
    //   208: iload #10
    //   210: isub
    //   211: newarray byte
    //   213: astore_3
    //   214: iconst_0
    //   215: istore #14
    //   217: iload #14
    //   219: aload_3
    //   220: arraylength
    //   221: if_icmpge -> 243
    //   224: aload_3
    //   225: iload #14
    //   227: aload #9
    //   229: iload #10
    //   231: iload #14
    //   233: iadd
    //   234: baload
    //   235: bastore
    //   236: iinc #14, 1
    //   239: iload_2
    //   240: ifne -> 217
    //   243: aload_3
    //   244: arraylength
    //   245: bipush #10
    //   247: if_icmplt -> 13
    //   250: getstatic burp/Zsdl.Zx : Ljava/lang/Object;
    //   253: checkcast java/math/BigInteger
    //   256: invokevirtual toByteArray : ()[B
    //   259: astore_3
    //   260: bipush #32
    //   262: newarray int
    //   264: dup
    //   265: iconst_0
    //   266: ldc 876216579
    //   268: iastore
    //   269: dup
    //   270: iconst_1
    //   271: ldc 455999525
    //   273: iastore
    //   274: dup
    //   275: iconst_2
    //   276: ldc 1043334948
    //   278: iastore
    //   279: dup
    //   280: iconst_3
    //   281: ldc 439222784
    //   283: iastore
    //   284: dup
    //   285: iconst_4
    //   286: ldc 372376604
    //   288: iastore
    //   289: dup
    //   290: iconst_5
    //   291: ldc 707731490
    //   293: iastore
    //   294: dup
    //   295: bipush #6
    //   297: ldc 389426184
    //   299: iastore
    //   300: dup
    //   301: bipush #7
    //   303: ldc 973875457
    //   305: iastore
    //   306: dup
    //   307: bipush #8
    //   309: ldc 389160971
    //   311: iastore
    //   312: dup
    //   313: bipush #9
    //   315: ldc 907870729
    //   317: iastore
    //   318: dup
    //   319: bipush #10
    //   321: ldc 121057538
    //   323: iastore
    //   324: dup
    //   325: bipush #11
    //   327: ldc 840500228
    //   329: iastore
    //   330: dup
    //   331: bipush #12
    //   333: ldc 254150144
    //   335: iastore
    //   336: dup
    //   337: bipush #13
    //   339: ldc 924386310
    //   341: iastore
    //   342: dup
    //   343: bipush #14
    //   345: ldc 187632156
    //   347: iastore
    //   348: dup
    //   349: bipush #15
    //   351: ldc 874189824
    //   353: iastore
    //   354: dup
    //   355: bipush #16
    //   357: ldc 655302664
    //   359: iastore
    //   360: dup
    //   361: bipush #17
    //   363: ldc 890966315
    //   365: iastore
    //   366: dup
    //   367: bipush #18
    //   369: ldc 722417666
    //   371: iastore
    //   372: dup
    //   373: bipush #19
    //   375: ldc 1026621720
    //   377: iastore
    //   378: dup
    //   379: bipush #20
    //   381: ldc 957157408
    //   383: iastore
    //   384: dup
    //   385: bipush #21
    //   387: ldc 892536332
    //   389: iastore
    //   390: dup
    //   391: bipush #22
    //   393: ldc 689771012
    //   395: iastore
    //   396: dup
    //   397: bipush #23
    //   399: ldc 221709344
    //   401: iastore
    //   402: dup
    //   403: bipush #24
    //   405: ldc 940377620
    //   407: iastore
    //   408: dup
    //   409: bipush #25
    //   411: ldc 255209728
    //   413: iastore
    //   414: dup
    //   415: bipush #26
    //   417: ldc 1010368540
    //   419: iastore
    //   420: dup
    //   421: bipush #27
    //   423: ldc 220604441
    //   425: iastore
    //   426: dup
    //   427: bipush #28
    //   429: ldc 1008414755
    //   431: iastore
    //   432: dup
    //   433: bipush #29
    //   435: ldc 187049985
    //   437: iastore
    //   438: dup
    //   439: bipush #30
    //   441: ldc 943331329
    //   443: iastore
    //   444: dup
    //   445: bipush #31
    //   447: ldc 170788368
    //   449: iastore
    //   450: astore #5
    //   452: bipush #64
    //   454: newarray int
    //   456: dup
    //   457: iconst_0
    //   458: ldc 16843776
    //   460: iastore
    //   461: dup
    //   462: iconst_1
    //   463: iconst_0
    //   464: iastore
    //   465: dup
    //   466: iconst_2
    //   467: ldc 65536
    //   469: iastore
    //   470: dup
    //   471: iconst_3
    //   472: ldc 16843780
    //   474: iastore
    //   475: dup
    //   476: iconst_4
    //   477: ldc 16842756
    //   479: iastore
    //   480: dup
    //   481: iconst_5
    //   482: ldc 66564
    //   484: iastore
    //   485: dup
    //   486: bipush #6
    //   488: iconst_4
    //   489: iastore
    //   490: dup
    //   491: bipush #7
    //   493: ldc 65536
    //   495: iastore
    //   496: dup
    //   497: bipush #8
    //   499: sipush #1024
    //   502: iastore
    //   503: dup
    //   504: bipush #9
    //   506: ldc 16843776
    //   508: iastore
    //   509: dup
    //   510: bipush #10
    //   512: ldc 16843780
    //   514: iastore
    //   515: dup
    //   516: bipush #11
    //   518: sipush #1024
    //   521: iastore
    //   522: dup
    //   523: bipush #12
    //   525: ldc 16778244
    //   527: iastore
    //   528: dup
    //   529: bipush #13
    //   531: ldc 16842756
    //   533: iastore
    //   534: dup
    //   535: bipush #14
    //   537: ldc 16777216
    //   539: iastore
    //   540: dup
    //   541: bipush #15
    //   543: iconst_4
    //   544: iastore
    //   545: dup
    //   546: bipush #16
    //   548: sipush #1028
    //   551: iastore
    //   552: dup
    //   553: bipush #17
    //   555: ldc 16778240
    //   557: iastore
    //   558: dup
    //   559: bipush #18
    //   561: ldc 16778240
    //   563: iastore
    //   564: dup
    //   565: bipush #19
    //   567: ldc 66560
    //   569: iastore
    //   570: dup
    //   571: bipush #20
    //   573: ldc 66560
    //   575: iastore
    //   576: dup
    //   577: bipush #21
    //   579: ldc 16842752
    //   581: iastore
    //   582: dup
    //   583: bipush #22
    //   585: ldc 16842752
    //   587: iastore
    //   588: dup
    //   589: bipush #23
    //   591: ldc 16778244
    //   593: iastore
    //   594: dup
    //   595: bipush #24
    //   597: ldc 65540
    //   599: iastore
    //   600: dup
    //   601: bipush #25
    //   603: ldc 16777220
    //   605: iastore
    //   606: dup
    //   607: bipush #26
    //   609: ldc 16777220
    //   611: iastore
    //   612: dup
    //   613: bipush #27
    //   615: ldc 65540
    //   617: iastore
    //   618: dup
    //   619: bipush #28
    //   621: iconst_0
    //   622: iastore
    //   623: dup
    //   624: bipush #29
    //   626: sipush #1028
    //   629: iastore
    //   630: dup
    //   631: bipush #30
    //   633: ldc 66564
    //   635: iastore
    //   636: dup
    //   637: bipush #31
    //   639: ldc 16777216
    //   641: iastore
    //   642: dup
    //   643: bipush #32
    //   645: ldc 65536
    //   647: iastore
    //   648: dup
    //   649: bipush #33
    //   651: ldc 16843780
    //   653: iastore
    //   654: dup
    //   655: bipush #34
    //   657: iconst_4
    //   658: iastore
    //   659: dup
    //   660: bipush #35
    //   662: ldc 16842752
    //   664: iastore
    //   665: dup
    //   666: bipush #36
    //   668: ldc 16843776
    //   670: iastore
    //   671: dup
    //   672: bipush #37
    //   674: ldc 16777216
    //   676: iastore
    //   677: dup
    //   678: bipush #38
    //   680: ldc 16777216
    //   682: iastore
    //   683: dup
    //   684: bipush #39
    //   686: sipush #1024
    //   689: iastore
    //   690: dup
    //   691: bipush #40
    //   693: ldc 16842756
    //   695: iastore
    //   696: dup
    //   697: bipush #41
    //   699: ldc 65536
    //   701: iastore
    //   702: dup
    //   703: bipush #42
    //   705: ldc 66560
    //   707: iastore
    //   708: dup
    //   709: bipush #43
    //   711: ldc 16777220
    //   713: iastore
    //   714: dup
    //   715: bipush #44
    //   717: sipush #1024
    //   720: iastore
    //   721: dup
    //   722: bipush #45
    //   724: iconst_4
    //   725: iastore
    //   726: dup
    //   727: bipush #46
    //   729: ldc 16778244
    //   731: iastore
    //   732: dup
    //   733: bipush #47
    //   735: ldc 66564
    //   737: iastore
    //   738: dup
    //   739: bipush #48
    //   741: ldc 16843780
    //   743: iastore
    //   744: dup
    //   745: bipush #49
    //   747: ldc 65540
    //   749: iastore
    //   750: dup
    //   751: bipush #50
    //   753: ldc 16842752
    //   755: iastore
    //   756: dup
    //   757: bipush #51
    //   759: ldc 16778244
    //   761: iastore
    //   762: dup
    //   763: bipush #52
    //   765: ldc 16777220
    //   767: iastore
    //   768: dup
    //   769: bipush #53
    //   771: sipush #1028
    //   774: iastore
    //   775: dup
    //   776: bipush #54
    //   778: ldc 66564
    //   780: iastore
    //   781: dup
    //   782: bipush #55
    //   784: ldc 16843776
    //   786: iastore
    //   787: dup
    //   788: bipush #56
    //   790: sipush #1028
    //   793: iastore
    //   794: dup
    //   795: bipush #57
    //   797: ldc 16778240
    //   799: iastore
    //   800: dup
    //   801: bipush #58
    //   803: ldc 16778240
    //   805: iastore
    //   806: dup
    //   807: bipush #59
    //   809: iconst_0
    //   810: iastore
    //   811: dup
    //   812: bipush #60
    //   814: ldc 65540
    //   816: iastore
    //   817: dup
    //   818: bipush #61
    //   820: ldc 66560
    //   822: iastore
    //   823: dup
    //   824: bipush #62
    //   826: iconst_0
    //   827: iastore
    //   828: dup
    //   829: bipush #63
    //   831: ldc 16842756
    //   833: iastore
    //   834: astore #6
    //   836: bipush #64
    //   838: newarray int
    //   840: dup
    //   841: iconst_0
    //   842: ldc -2146402272
    //   844: iastore
    //   845: dup
    //   846: iconst_1
    //   847: ldc -2147450880
    //   849: iastore
    //   850: dup
    //   851: iconst_2
    //   852: ldc 32768
    //   854: iastore
    //   855: dup
    //   856: iconst_3
    //   857: ldc 1081376
    //   859: iastore
    //   860: dup
    //   861: iconst_4
    //   862: ldc 1048576
    //   864: iastore
    //   865: dup
    //   866: iconst_5
    //   867: bipush #32
    //   869: iastore
    //   870: dup
    //   871: bipush #6
    //   873: ldc -2146435040
    //   875: iastore
    //   876: dup
    //   877: bipush #7
    //   879: ldc -2147450848
    //   881: iastore
    //   882: dup
    //   883: bipush #8
    //   885: ldc -2147483616
    //   887: iastore
    //   888: dup
    //   889: bipush #9
    //   891: ldc -2146402272
    //   893: iastore
    //   894: dup
    //   895: bipush #10
    //   897: ldc -2146402304
    //   899: iastore
    //   900: dup
    //   901: bipush #11
    //   903: ldc -2147483648
    //   905: iastore
    //   906: dup
    //   907: bipush #12
    //   909: ldc -2147450880
    //   911: iastore
    //   912: dup
    //   913: bipush #13
    //   915: ldc 1048576
    //   917: iastore
    //   918: dup
    //   919: bipush #14
    //   921: bipush #32
    //   923: iastore
    //   924: dup
    //   925: bipush #15
    //   927: ldc -2146435040
    //   929: iastore
    //   930: dup
    //   931: bipush #16
    //   933: ldc 1081344
    //   935: iastore
    //   936: dup
    //   937: bipush #17
    //   939: ldc 1048608
    //   941: iastore
    //   942: dup
    //   943: bipush #18
    //   945: ldc -2147450848
    //   947: iastore
    //   948: dup
    //   949: bipush #19
    //   951: iconst_0
    //   952: iastore
    //   953: dup
    //   954: bipush #20
    //   956: ldc -2147483648
    //   958: iastore
    //   959: dup
    //   960: bipush #21
    //   962: ldc 32768
    //   964: iastore
    //   965: dup
    //   966: bipush #22
    //   968: ldc 1081376
    //   970: iastore
    //   971: dup
    //   972: bipush #23
    //   974: ldc -2146435072
    //   976: iastore
    //   977: dup
    //   978: bipush #24
    //   980: ldc 1048608
    //   982: iastore
    //   983: dup
    //   984: bipush #25
    //   986: ldc -2147483616
    //   988: iastore
    //   989: dup
    //   990: bipush #26
    //   992: iconst_0
    //   993: iastore
    //   994: dup
    //   995: bipush #27
    //   997: ldc 1081344
    //   999: iastore
    //   1000: dup
    //   1001: bipush #28
    //   1003: ldc 32800
    //   1005: iastore
    //   1006: dup
    //   1007: bipush #29
    //   1009: ldc -2146402304
    //   1011: iastore
    //   1012: dup
    //   1013: bipush #30
    //   1015: ldc -2146435072
    //   1017: iastore
    //   1018: dup
    //   1019: bipush #31
    //   1021: ldc 32800
    //   1023: iastore
    //   1024: dup
    //   1025: bipush #32
    //   1027: iconst_0
    //   1028: iastore
    //   1029: dup
    //   1030: bipush #33
    //   1032: ldc 1081376
    //   1034: iastore
    //   1035: dup
    //   1036: bipush #34
    //   1038: ldc -2146435040
    //   1040: iastore
    //   1041: dup
    //   1042: bipush #35
    //   1044: ldc 1048576
    //   1046: iastore
    //   1047: dup
    //   1048: bipush #36
    //   1050: ldc -2147450848
    //   1052: iastore
    //   1053: dup
    //   1054: bipush #37
    //   1056: ldc -2146435072
    //   1058: iastore
    //   1059: dup
    //   1060: bipush #38
    //   1062: ldc -2146402304
    //   1064: iastore
    //   1065: dup
    //   1066: bipush #39
    //   1068: ldc 32768
    //   1070: iastore
    //   1071: dup
    //   1072: bipush #40
    //   1074: ldc -2146435072
    //   1076: iastore
    //   1077: dup
    //   1078: bipush #41
    //   1080: ldc -2147450880
    //   1082: iastore
    //   1083: dup
    //   1084: bipush #42
    //   1086: bipush #32
    //   1088: iastore
    //   1089: dup
    //   1090: bipush #43
    //   1092: ldc -2146402272
    //   1094: iastore
    //   1095: dup
    //   1096: bipush #44
    //   1098: ldc 1081376
    //   1100: iastore
    //   1101: dup
    //   1102: bipush #45
    //   1104: bipush #32
    //   1106: iastore
    //   1107: dup
    //   1108: bipush #46
    //   1110: ldc 32768
    //   1112: iastore
    //   1113: dup
    //   1114: bipush #47
    //   1116: ldc -2147483648
    //   1118: iastore
    //   1119: dup
    //   1120: bipush #48
    //   1122: ldc 32800
    //   1124: iastore
    //   1125: dup
    //   1126: bipush #49
    //   1128: ldc -2146402304
    //   1130: iastore
    //   1131: dup
    //   1132: bipush #50
    //   1134: ldc 1048576
    //   1136: iastore
    //   1137: dup
    //   1138: bipush #51
    //   1140: ldc -2147483616
    //   1142: iastore
    //   1143: dup
    //   1144: bipush #52
    //   1146: ldc 1048608
    //   1148: iastore
    //   1149: dup
    //   1150: bipush #53
    //   1152: ldc -2147450848
    //   1154: iastore
    //   1155: dup
    //   1156: bipush #54
    //   1158: ldc -2147483616
    //   1160: iastore
    //   1161: dup
    //   1162: bipush #55
    //   1164: ldc 1048608
    //   1166: iastore
    //   1167: dup
    //   1168: bipush #56
    //   1170: ldc 1081344
    //   1172: iastore
    //   1173: dup
    //   1174: bipush #57
    //   1176: iconst_0
    //   1177: iastore
    //   1178: dup
    //   1179: bipush #58
    //   1181: ldc -2147450880
    //   1183: iastore
    //   1184: dup
    //   1185: bipush #59
    //   1187: ldc 32800
    //   1189: iastore
    //   1190: dup
    //   1191: bipush #60
    //   1193: ldc -2147483648
    //   1195: iastore
    //   1196: dup
    //   1197: bipush #61
    //   1199: ldc -2146435040
    //   1201: iastore
    //   1202: dup
    //   1203: bipush #62
    //   1205: ldc -2146402272
    //   1207: iastore
    //   1208: dup
    //   1209: bipush #63
    //   1211: ldc 1081344
    //   1213: iastore
    //   1214: astore #7
    //   1216: bipush #64
    //   1218: newarray int
    //   1220: dup
    //   1221: iconst_0
    //   1222: sipush #520
    //   1225: iastore
    //   1226: dup
    //   1227: iconst_1
    //   1228: ldc 134349312
    //   1230: iastore
    //   1231: dup
    //   1232: iconst_2
    //   1233: iconst_0
    //   1234: iastore
    //   1235: dup
    //   1236: iconst_3
    //   1237: ldc 134348808
    //   1239: iastore
    //   1240: dup
    //   1241: iconst_4
    //   1242: ldc 134218240
    //   1244: iastore
    //   1245: dup
    //   1246: iconst_5
    //   1247: iconst_0
    //   1248: iastore
    //   1249: dup
    //   1250: bipush #6
    //   1252: ldc 131592
    //   1254: iastore
    //   1255: dup
    //   1256: bipush #7
    //   1258: ldc 134218240
    //   1260: iastore
    //   1261: dup
    //   1262: bipush #8
    //   1264: ldc 131080
    //   1266: iastore
    //   1267: dup
    //   1268: bipush #9
    //   1270: ldc 134217736
    //   1272: iastore
    //   1273: dup
    //   1274: bipush #10
    //   1276: ldc 134217736
    //   1278: iastore
    //   1279: dup
    //   1280: bipush #11
    //   1282: ldc 131072
    //   1284: iastore
    //   1285: dup
    //   1286: bipush #12
    //   1288: ldc 134349320
    //   1290: iastore
    //   1291: dup
    //   1292: bipush #13
    //   1294: ldc 131080
    //   1296: iastore
    //   1297: dup
    //   1298: bipush #14
    //   1300: ldc 134348800
    //   1302: iastore
    //   1303: dup
    //   1304: bipush #15
    //   1306: sipush #520
    //   1309: iastore
    //   1310: dup
    //   1311: bipush #16
    //   1313: ldc 134217728
    //   1315: iastore
    //   1316: dup
    //   1317: bipush #17
    //   1319: bipush #8
    //   1321: iastore
    //   1322: dup
    //   1323: bipush #18
    //   1325: ldc 134349312
    //   1327: iastore
    //   1328: dup
    //   1329: bipush #19
    //   1331: sipush #512
    //   1334: iastore
    //   1335: dup
    //   1336: bipush #20
    //   1338: ldc 131584
    //   1340: iastore
    //   1341: dup
    //   1342: bipush #21
    //   1344: ldc 134348800
    //   1346: iastore
    //   1347: dup
    //   1348: bipush #22
    //   1350: ldc 134348808
    //   1352: iastore
    //   1353: dup
    //   1354: bipush #23
    //   1356: ldc 131592
    //   1358: iastore
    //   1359: dup
    //   1360: bipush #24
    //   1362: ldc 134218248
    //   1364: iastore
    //   1365: dup
    //   1366: bipush #25
    //   1368: ldc 131584
    //   1370: iastore
    //   1371: dup
    //   1372: bipush #26
    //   1374: ldc 131072
    //   1376: iastore
    //   1377: dup
    //   1378: bipush #27
    //   1380: ldc 134218248
    //   1382: iastore
    //   1383: dup
    //   1384: bipush #28
    //   1386: bipush #8
    //   1388: iastore
    //   1389: dup
    //   1390: bipush #29
    //   1392: ldc 134349320
    //   1394: iastore
    //   1395: dup
    //   1396: bipush #30
    //   1398: sipush #512
    //   1401: iastore
    //   1402: dup
    //   1403: bipush #31
    //   1405: ldc 134217728
    //   1407: iastore
    //   1408: dup
    //   1409: bipush #32
    //   1411: ldc 134349312
    //   1413: iastore
    //   1414: dup
    //   1415: bipush #33
    //   1417: ldc 134217728
    //   1419: iastore
    //   1420: dup
    //   1421: bipush #34
    //   1423: ldc 131080
    //   1425: iastore
    //   1426: dup
    //   1427: bipush #35
    //   1429: sipush #520
    //   1432: iastore
    //   1433: dup
    //   1434: bipush #36
    //   1436: ldc 131072
    //   1438: iastore
    //   1439: dup
    //   1440: bipush #37
    //   1442: ldc 134349312
    //   1444: iastore
    //   1445: dup
    //   1446: bipush #38
    //   1448: ldc 134218240
    //   1450: iastore
    //   1451: dup
    //   1452: bipush #39
    //   1454: iconst_0
    //   1455: iastore
    //   1456: dup
    //   1457: bipush #40
    //   1459: sipush #512
    //   1462: iastore
    //   1463: dup
    //   1464: bipush #41
    //   1466: ldc 131080
    //   1468: iastore
    //   1469: dup
    //   1470: bipush #42
    //   1472: ldc 134349320
    //   1474: iastore
    //   1475: dup
    //   1476: bipush #43
    //   1478: ldc 134218240
    //   1480: iastore
    //   1481: dup
    //   1482: bipush #44
    //   1484: ldc 134217736
    //   1486: iastore
    //   1487: dup
    //   1488: bipush #45
    //   1490: sipush #512
    //   1493: iastore
    //   1494: dup
    //   1495: bipush #46
    //   1497: iconst_0
    //   1498: iastore
    //   1499: dup
    //   1500: bipush #47
    //   1502: ldc 134348808
    //   1504: iastore
    //   1505: dup
    //   1506: bipush #48
    //   1508: ldc 134218248
    //   1510: iastore
    //   1511: dup
    //   1512: bipush #49
    //   1514: ldc 131072
    //   1516: iastore
    //   1517: dup
    //   1518: bipush #50
    //   1520: ldc 134217728
    //   1522: iastore
    //   1523: dup
    //   1524: bipush #51
    //   1526: ldc 134349320
    //   1528: iastore
    //   1529: dup
    //   1530: bipush #52
    //   1532: bipush #8
    //   1534: iastore
    //   1535: dup
    //   1536: bipush #53
    //   1538: ldc 131592
    //   1540: iastore
    //   1541: dup
    //   1542: bipush #54
    //   1544: ldc 131584
    //   1546: iastore
    //   1547: dup
    //   1548: bipush #55
    //   1550: ldc 134217736
    //   1552: iastore
    //   1553: dup
    //   1554: bipush #56
    //   1556: ldc 134348800
    //   1558: iastore
    //   1559: dup
    //   1560: bipush #57
    //   1562: ldc 134218248
    //   1564: iastore
    //   1565: dup
    //   1566: bipush #58
    //   1568: sipush #520
    //   1571: iastore
    //   1572: dup
    //   1573: bipush #59
    //   1575: ldc 134348800
    //   1577: iastore
    //   1578: dup
    //   1579: bipush #60
    //   1581: ldc 131592
    //   1583: iastore
    //   1584: dup
    //   1585: bipush #61
    //   1587: bipush #8
    //   1589: iastore
    //   1590: dup
    //   1591: bipush #62
    //   1593: ldc 134348808
    //   1595: iastore
    //   1596: dup
    //   1597: bipush #63
    //   1599: ldc 131584
    //   1601: iastore
    //   1602: astore #8
    //   1604: bipush #64
    //   1606: newarray int
    //   1608: dup
    //   1609: iconst_0
    //   1610: ldc 8396801
    //   1612: iastore
    //   1613: dup
    //   1614: iconst_1
    //   1615: sipush #8321
    //   1618: iastore
    //   1619: dup
    //   1620: iconst_2
    //   1621: sipush #8321
    //   1624: iastore
    //   1625: dup
    //   1626: iconst_3
    //   1627: sipush #128
    //   1630: iastore
    //   1631: dup
    //   1632: iconst_4
    //   1633: ldc 8396928
    //   1635: iastore
    //   1636: dup
    //   1637: iconst_5
    //   1638: ldc 8388737
    //   1640: iastore
    //   1641: dup
    //   1642: bipush #6
    //   1644: ldc 8388609
    //   1646: iastore
    //   1647: dup
    //   1648: bipush #7
    //   1650: sipush #8193
    //   1653: iastore
    //   1654: dup
    //   1655: bipush #8
    //   1657: iconst_0
    //   1658: iastore
    //   1659: dup
    //   1660: bipush #9
    //   1662: ldc 8396800
    //   1664: iastore
    //   1665: dup
    //   1666: bipush #10
    //   1668: ldc 8396800
    //   1670: iastore
    //   1671: dup
    //   1672: bipush #11
    //   1674: ldc 8396929
    //   1676: iastore
    //   1677: dup
    //   1678: bipush #12
    //   1680: sipush #129
    //   1683: iastore
    //   1684: dup
    //   1685: bipush #13
    //   1687: iconst_0
    //   1688: iastore
    //   1689: dup
    //   1690: bipush #14
    //   1692: ldc 8388736
    //   1694: iastore
    //   1695: dup
    //   1696: bipush #15
    //   1698: ldc 8388609
    //   1700: iastore
    //   1701: dup
    //   1702: bipush #16
    //   1704: iconst_1
    //   1705: iastore
    //   1706: dup
    //   1707: bipush #17
    //   1709: sipush #8192
    //   1712: iastore
    //   1713: dup
    //   1714: bipush #18
    //   1716: ldc 8388608
    //   1718: iastore
    //   1719: dup
    //   1720: bipush #19
    //   1722: ldc 8396801
    //   1724: iastore
    //   1725: dup
    //   1726: bipush #20
    //   1728: sipush #128
    //   1731: iastore
    //   1732: dup
    //   1733: bipush #21
    //   1735: ldc 8388608
    //   1737: iastore
    //   1738: dup
    //   1739: bipush #22
    //   1741: sipush #8193
    //   1744: iastore
    //   1745: dup
    //   1746: bipush #23
    //   1748: sipush #8320
    //   1751: iastore
    //   1752: dup
    //   1753: bipush #24
    //   1755: ldc 8388737
    //   1757: iastore
    //   1758: dup
    //   1759: bipush #25
    //   1761: iconst_1
    //   1762: iastore
    //   1763: dup
    //   1764: bipush #26
    //   1766: sipush #8320
    //   1769: iastore
    //   1770: dup
    //   1771: bipush #27
    //   1773: ldc 8388736
    //   1775: iastore
    //   1776: dup
    //   1777: bipush #28
    //   1779: sipush #8192
    //   1782: iastore
    //   1783: dup
    //   1784: bipush #29
    //   1786: ldc 8396928
    //   1788: iastore
    //   1789: dup
    //   1790: bipush #30
    //   1792: ldc 8396929
    //   1794: iastore
    //   1795: dup
    //   1796: bipush #31
    //   1798: sipush #129
    //   1801: iastore
    //   1802: dup
    //   1803: bipush #32
    //   1805: ldc 8388736
    //   1807: iastore
    //   1808: dup
    //   1809: bipush #33
    //   1811: ldc 8388609
    //   1813: iastore
    //   1814: dup
    //   1815: bipush #34
    //   1817: ldc 8396800
    //   1819: iastore
    //   1820: dup
    //   1821: bipush #35
    //   1823: ldc 8396929
    //   1825: iastore
    //   1826: dup
    //   1827: bipush #36
    //   1829: sipush #129
    //   1832: iastore
    //   1833: dup
    //   1834: bipush #37
    //   1836: iconst_0
    //   1837: iastore
    //   1838: dup
    //   1839: bipush #38
    //   1841: iconst_0
    //   1842: iastore
    //   1843: dup
    //   1844: bipush #39
    //   1846: ldc 8396800
    //   1848: iastore
    //   1849: dup
    //   1850: bipush #40
    //   1852: sipush #8320
    //   1855: iastore
    //   1856: dup
    //   1857: bipush #41
    //   1859: ldc 8388736
    //   1861: iastore
    //   1862: dup
    //   1863: bipush #42
    //   1865: ldc 8388737
    //   1867: iastore
    //   1868: dup
    //   1869: bipush #43
    //   1871: iconst_1
    //   1872: iastore
    //   1873: dup
    //   1874: bipush #44
    //   1876: ldc 8396801
    //   1878: iastore
    //   1879: dup
    //   1880: bipush #45
    //   1882: sipush #8321
    //   1885: iastore
    //   1886: dup
    //   1887: bipush #46
    //   1889: sipush #8321
    //   1892: iastore
    //   1893: dup
    //   1894: bipush #47
    //   1896: sipush #128
    //   1899: iastore
    //   1900: dup
    //   1901: bipush #48
    //   1903: ldc 8396929
    //   1905: iastore
    //   1906: dup
    //   1907: bipush #49
    //   1909: sipush #129
    //   1912: iastore
    //   1913: dup
    //   1914: bipush #50
    //   1916: iconst_1
    //   1917: iastore
    //   1918: dup
    //   1919: bipush #51
    //   1921: sipush #8192
    //   1924: iastore
    //   1925: dup
    //   1926: bipush #52
    //   1928: ldc 8388609
    //   1930: iastore
    //   1931: dup
    //   1932: bipush #53
    //   1934: sipush #8193
    //   1937: iastore
    //   1938: dup
    //   1939: bipush #54
    //   1941: ldc 8396928
    //   1943: iastore
    //   1944: dup
    //   1945: bipush #55
    //   1947: ldc 8388737
    //   1949: iastore
    //   1950: dup
    //   1951: bipush #56
    //   1953: sipush #8193
    //   1956: iastore
    //   1957: dup
    //   1958: bipush #57
    //   1960: sipush #8320
    //   1963: iastore
    //   1964: dup
    //   1965: bipush #58
    //   1967: ldc 8388608
    //   1969: iastore
    //   1970: dup
    //   1971: bipush #59
    //   1973: ldc 8396801
    //   1975: iastore
    //   1976: dup
    //   1977: bipush #60
    //   1979: sipush #128
    //   1982: iastore
    //   1983: dup
    //   1984: bipush #61
    //   1986: ldc 8388608
    //   1988: iastore
    //   1989: dup
    //   1990: bipush #62
    //   1992: sipush #8192
    //   1995: iastore
    //   1996: dup
    //   1997: bipush #63
    //   1999: ldc 8396928
    //   2001: iastore
    //   2002: astore #9
    //   2004: bipush #64
    //   2006: newarray int
    //   2008: dup
    //   2009: iconst_0
    //   2010: sipush #256
    //   2013: iastore
    //   2014: dup
    //   2015: iconst_1
    //   2016: ldc 34078976
    //   2018: iastore
    //   2019: dup
    //   2020: iconst_2
    //   2021: ldc 34078720
    //   2023: iastore
    //   2024: dup
    //   2025: iconst_3
    //   2026: ldc 1107296512
    //   2028: iastore
    //   2029: dup
    //   2030: iconst_4
    //   2031: ldc 524288
    //   2033: iastore
    //   2034: dup
    //   2035: iconst_5
    //   2036: sipush #256
    //   2039: iastore
    //   2040: dup
    //   2041: bipush #6
    //   2043: ldc 1073741824
    //   2045: iastore
    //   2046: dup
    //   2047: bipush #7
    //   2049: ldc 34078720
    //   2051: iastore
    //   2052: dup
    //   2053: bipush #8
    //   2055: ldc 1074266368
    //   2057: iastore
    //   2058: dup
    //   2059: bipush #9
    //   2061: ldc 524288
    //   2063: iastore
    //   2064: dup
    //   2065: bipush #10
    //   2067: ldc 33554688
    //   2069: iastore
    //   2070: dup
    //   2071: bipush #11
    //   2073: ldc 1074266368
    //   2075: iastore
    //   2076: dup
    //   2077: bipush #12
    //   2079: ldc 1107296512
    //   2081: iastore
    //   2082: dup
    //   2083: bipush #13
    //   2085: ldc 1107820544
    //   2087: iastore
    //   2088: dup
    //   2089: bipush #14
    //   2091: ldc 524544
    //   2093: iastore
    //   2094: dup
    //   2095: bipush #15
    //   2097: ldc 1073741824
    //   2099: iastore
    //   2100: dup
    //   2101: bipush #16
    //   2103: ldc 33554432
    //   2105: iastore
    //   2106: dup
    //   2107: bipush #17
    //   2109: ldc 1074266112
    //   2111: iastore
    //   2112: dup
    //   2113: bipush #18
    //   2115: ldc 1074266112
    //   2117: iastore
    //   2118: dup
    //   2119: bipush #19
    //   2121: iconst_0
    //   2122: iastore
    //   2123: dup
    //   2124: bipush #20
    //   2126: ldc 1073742080
    //   2128: iastore
    //   2129: dup
    //   2130: bipush #21
    //   2132: ldc 1107820800
    //   2134: iastore
    //   2135: dup
    //   2136: bipush #22
    //   2138: ldc 1107820800
    //   2140: iastore
    //   2141: dup
    //   2142: bipush #23
    //   2144: ldc 33554688
    //   2146: iastore
    //   2147: dup
    //   2148: bipush #24
    //   2150: ldc 1107820544
    //   2152: iastore
    //   2153: dup
    //   2154: bipush #25
    //   2156: ldc 1073742080
    //   2158: iastore
    //   2159: dup
    //   2160: bipush #26
    //   2162: iconst_0
    //   2163: iastore
    //   2164: dup
    //   2165: bipush #27
    //   2167: ldc 1107296256
    //   2169: iastore
    //   2170: dup
    //   2171: bipush #28
    //   2173: ldc 34078976
    //   2175: iastore
    //   2176: dup
    //   2177: bipush #29
    //   2179: ldc 33554432
    //   2181: iastore
    //   2182: dup
    //   2183: bipush #30
    //   2185: ldc 1107296256
    //   2187: iastore
    //   2188: dup
    //   2189: bipush #31
    //   2191: ldc 524544
    //   2193: iastore
    //   2194: dup
    //   2195: bipush #32
    //   2197: ldc 524288
    //   2199: iastore
    //   2200: dup
    //   2201: bipush #33
    //   2203: ldc 1107296512
    //   2205: iastore
    //   2206: dup
    //   2207: bipush #34
    //   2209: sipush #256
    //   2212: iastore
    //   2213: dup
    //   2214: bipush #35
    //   2216: ldc 33554432
    //   2218: iastore
    //   2219: dup
    //   2220: bipush #36
    //   2222: ldc 1073741824
    //   2224: iastore
    //   2225: dup
    //   2226: bipush #37
    //   2228: ldc 34078720
    //   2230: iastore
    //   2231: dup
    //   2232: bipush #38
    //   2234: ldc 1107296512
    //   2236: iastore
    //   2237: dup
    //   2238: bipush #39
    //   2240: ldc 1074266368
    //   2242: iastore
    //   2243: dup
    //   2244: bipush #40
    //   2246: ldc 33554688
    //   2248: iastore
    //   2249: dup
    //   2250: bipush #41
    //   2252: ldc 1073741824
    //   2254: iastore
    //   2255: dup
    //   2256: bipush #42
    //   2258: ldc 1107820544
    //   2260: iastore
    //   2261: dup
    //   2262: bipush #43
    //   2264: ldc 34078976
    //   2266: iastore
    //   2267: dup
    //   2268: bipush #44
    //   2270: ldc 1074266368
    //   2272: iastore
    //   2273: dup
    //   2274: bipush #45
    //   2276: sipush #256
    //   2279: iastore
    //   2280: dup
    //   2281: bipush #46
    //   2283: ldc 33554432
    //   2285: iastore
    //   2286: dup
    //   2287: bipush #47
    //   2289: ldc 1107820544
    //   2291: iastore
    //   2292: dup
    //   2293: bipush #48
    //   2295: ldc 1107820800
    //   2297: iastore
    //   2298: dup
    //   2299: bipush #49
    //   2301: ldc 524544
    //   2303: iastore
    //   2304: dup
    //   2305: bipush #50
    //   2307: ldc 1107296256
    //   2309: iastore
    //   2310: dup
    //   2311: bipush #51
    //   2313: ldc 1107820800
    //   2315: iastore
    //   2316: dup
    //   2317: bipush #52
    //   2319: ldc 34078720
    //   2321: iastore
    //   2322: dup
    //   2323: bipush #53
    //   2325: iconst_0
    //   2326: iastore
    //   2327: dup
    //   2328: bipush #54
    //   2330: ldc 1074266112
    //   2332: iastore
    //   2333: dup
    //   2334: bipush #55
    //   2336: ldc 1107296256
    //   2338: iastore
    //   2339: dup
    //   2340: bipush #56
    //   2342: ldc 524544
    //   2344: iastore
    //   2345: dup
    //   2346: bipush #57
    //   2348: ldc 33554688
    //   2350: iastore
    //   2351: dup
    //   2352: bipush #58
    //   2354: ldc 1073742080
    //   2356: iastore
    //   2357: dup
    //   2358: bipush #59
    //   2360: ldc 524288
    //   2362: iastore
    //   2363: dup
    //   2364: bipush #60
    //   2366: iconst_0
    //   2367: iastore
    //   2368: dup
    //   2369: bipush #61
    //   2371: ldc 1074266112
    //   2373: iastore
    //   2374: dup
    //   2375: bipush #62
    //   2377: ldc 34078976
    //   2379: iastore
    //   2380: dup
    //   2381: bipush #63
    //   2383: ldc 1073742080
    //   2385: iastore
    //   2386: astore #10
    //   2388: bipush #64
    //   2390: newarray int
    //   2392: dup
    //   2393: iconst_0
    //   2394: ldc 536870928
    //   2396: iastore
    //   2397: dup
    //   2398: iconst_1
    //   2399: ldc 541065216
    //   2401: iastore
    //   2402: dup
    //   2403: iconst_2
    //   2404: sipush #16384
    //   2407: iastore
    //   2408: dup
    //   2409: iconst_3
    //   2410: ldc 541081616
    //   2412: iastore
    //   2413: dup
    //   2414: iconst_4
    //   2415: ldc 541065216
    //   2417: iastore
    //   2418: dup
    //   2419: iconst_5
    //   2420: bipush #16
    //   2422: iastore
    //   2423: dup
    //   2424: bipush #6
    //   2426: ldc 541081616
    //   2428: iastore
    //   2429: dup
    //   2430: bipush #7
    //   2432: ldc 4194304
    //   2434: iastore
    //   2435: dup
    //   2436: bipush #8
    //   2438: ldc 536887296
    //   2440: iastore
    //   2441: dup
    //   2442: bipush #9
    //   2444: ldc 4210704
    //   2446: iastore
    //   2447: dup
    //   2448: bipush #10
    //   2450: ldc 4194304
    //   2452: iastore
    //   2453: dup
    //   2454: bipush #11
    //   2456: ldc 536870928
    //   2458: iastore
    //   2459: dup
    //   2460: bipush #12
    //   2462: ldc 4194320
    //   2464: iastore
    //   2465: dup
    //   2466: bipush #13
    //   2468: ldc 536887296
    //   2470: iastore
    //   2471: dup
    //   2472: bipush #14
    //   2474: ldc 536870912
    //   2476: iastore
    //   2477: dup
    //   2478: bipush #15
    //   2480: sipush #16400
    //   2483: iastore
    //   2484: dup
    //   2485: bipush #16
    //   2487: iconst_0
    //   2488: iastore
    //   2489: dup
    //   2490: bipush #17
    //   2492: ldc 4194320
    //   2494: iastore
    //   2495: dup
    //   2496: bipush #18
    //   2498: ldc 536887312
    //   2500: iastore
    //   2501: dup
    //   2502: bipush #19
    //   2504: sipush #16384
    //   2507: iastore
    //   2508: dup
    //   2509: bipush #20
    //   2511: ldc 4210688
    //   2513: iastore
    //   2514: dup
    //   2515: bipush #21
    //   2517: ldc 536887312
    //   2519: iastore
    //   2520: dup
    //   2521: bipush #22
    //   2523: bipush #16
    //   2525: iastore
    //   2526: dup
    //   2527: bipush #23
    //   2529: ldc 541065232
    //   2531: iastore
    //   2532: dup
    //   2533: bipush #24
    //   2535: ldc 541065232
    //   2537: iastore
    //   2538: dup
    //   2539: bipush #25
    //   2541: iconst_0
    //   2542: iastore
    //   2543: dup
    //   2544: bipush #26
    //   2546: ldc 4210704
    //   2548: iastore
    //   2549: dup
    //   2550: bipush #27
    //   2552: ldc 541081600
    //   2554: iastore
    //   2555: dup
    //   2556: bipush #28
    //   2558: sipush #16400
    //   2561: iastore
    //   2562: dup
    //   2563: bipush #29
    //   2565: ldc 4210688
    //   2567: iastore
    //   2568: dup
    //   2569: bipush #30
    //   2571: ldc 541081600
    //   2573: iastore
    //   2574: dup
    //   2575: bipush #31
    //   2577: ldc 536870912
    //   2579: iastore
    //   2580: dup
    //   2581: bipush #32
    //   2583: ldc 536887296
    //   2585: iastore
    //   2586: dup
    //   2587: bipush #33
    //   2589: bipush #16
    //   2591: iastore
    //   2592: dup
    //   2593: bipush #34
    //   2595: ldc 541065232
    //   2597: iastore
    //   2598: dup
    //   2599: bipush #35
    //   2601: ldc 4210688
    //   2603: iastore
    //   2604: dup
    //   2605: bipush #36
    //   2607: ldc 541081616
    //   2609: iastore
    //   2610: dup
    //   2611: bipush #37
    //   2613: ldc 4194304
    //   2615: iastore
    //   2616: dup
    //   2617: bipush #38
    //   2619: sipush #16400
    //   2622: iastore
    //   2623: dup
    //   2624: bipush #39
    //   2626: ldc 536870928
    //   2628: iastore
    //   2629: dup
    //   2630: bipush #40
    //   2632: ldc 4194304
    //   2634: iastore
    //   2635: dup
    //   2636: bipush #41
    //   2638: ldc 536887296
    //   2640: iastore
    //   2641: dup
    //   2642: bipush #42
    //   2644: ldc 536870912
    //   2646: iastore
    //   2647: dup
    //   2648: bipush #43
    //   2650: sipush #16400
    //   2653: iastore
    //   2654: dup
    //   2655: bipush #44
    //   2657: ldc 536870928
    //   2659: iastore
    //   2660: dup
    //   2661: bipush #45
    //   2663: ldc 541081616
    //   2665: iastore
    //   2666: dup
    //   2667: bipush #46
    //   2669: ldc 4210688
    //   2671: iastore
    //   2672: dup
    //   2673: bipush #47
    //   2675: ldc 541065216
    //   2677: iastore
    //   2678: dup
    //   2679: bipush #48
    //   2681: ldc 4210704
    //   2683: iastore
    //   2684: dup
    //   2685: bipush #49
    //   2687: ldc 541081600
    //   2689: iastore
    //   2690: dup
    //   2691: bipush #50
    //   2693: iconst_0
    //   2694: iastore
    //   2695: dup
    //   2696: bipush #51
    //   2698: ldc 541065232
    //   2700: iastore
    //   2701: dup
    //   2702: bipush #52
    //   2704: bipush #16
    //   2706: iastore
    //   2707: dup
    //   2708: bipush #53
    //   2710: sipush #16384
    //   2713: iastore
    //   2714: dup
    //   2715: bipush #54
    //   2717: ldc 541065216
    //   2719: iastore
    //   2720: dup
    //   2721: bipush #55
    //   2723: ldc 4210704
    //   2725: iastore
    //   2726: dup
    //   2727: bipush #56
    //   2729: sipush #16384
    //   2732: iastore
    //   2733: dup
    //   2734: bipush #57
    //   2736: ldc 4194320
    //   2738: iastore
    //   2739: dup
    //   2740: bipush #58
    //   2742: ldc 536887312
    //   2744: iastore
    //   2745: dup
    //   2746: bipush #59
    //   2748: iconst_0
    //   2749: iastore
    //   2750: dup
    //   2751: bipush #60
    //   2753: ldc 541081600
    //   2755: iastore
    //   2756: dup
    //   2757: bipush #61
    //   2759: ldc 536870912
    //   2761: iastore
    //   2762: dup
    //   2763: bipush #62
    //   2765: ldc 4194320
    //   2767: iastore
    //   2768: dup
    //   2769: bipush #63
    //   2771: ldc 536887312
    //   2773: iastore
    //   2774: astore #11
    //   2776: bipush #64
    //   2778: newarray int
    //   2780: dup
    //   2781: iconst_0
    //   2782: ldc 2097152
    //   2784: iastore
    //   2785: dup
    //   2786: iconst_1
    //   2787: ldc 69206018
    //   2789: iastore
    //   2790: dup
    //   2791: iconst_2
    //   2792: ldc 67110914
    //   2794: iastore
    //   2795: dup
    //   2796: iconst_3
    //   2797: iconst_0
    //   2798: iastore
    //   2799: dup
    //   2800: iconst_4
    //   2801: sipush #2048
    //   2804: iastore
    //   2805: dup
    //   2806: iconst_5
    //   2807: ldc 67110914
    //   2809: iastore
    //   2810: dup
    //   2811: bipush #6
    //   2813: ldc 2099202
    //   2815: iastore
    //   2816: dup
    //   2817: bipush #7
    //   2819: ldc 69208064
    //   2821: iastore
    //   2822: dup
    //   2823: bipush #8
    //   2825: ldc 69208066
    //   2827: iastore
    //   2828: dup
    //   2829: bipush #9
    //   2831: ldc 2097152
    //   2833: iastore
    //   2834: dup
    //   2835: bipush #10
    //   2837: iconst_0
    //   2838: iastore
    //   2839: dup
    //   2840: bipush #11
    //   2842: ldc 67108866
    //   2844: iastore
    //   2845: dup
    //   2846: bipush #12
    //   2848: iconst_2
    //   2849: iastore
    //   2850: dup
    //   2851: bipush #13
    //   2853: ldc 67108864
    //   2855: iastore
    //   2856: dup
    //   2857: bipush #14
    //   2859: ldc 69206018
    //   2861: iastore
    //   2862: dup
    //   2863: bipush #15
    //   2865: sipush #2050
    //   2868: iastore
    //   2869: dup
    //   2870: bipush #16
    //   2872: ldc 67110912
    //   2874: iastore
    //   2875: dup
    //   2876: bipush #17
    //   2878: ldc 2099202
    //   2880: iastore
    //   2881: dup
    //   2882: bipush #18
    //   2884: ldc 2097154
    //   2886: iastore
    //   2887: dup
    //   2888: bipush #19
    //   2890: ldc 67110912
    //   2892: iastore
    //   2893: dup
    //   2894: bipush #20
    //   2896: ldc 67108866
    //   2898: iastore
    //   2899: dup
    //   2900: bipush #21
    //   2902: ldc 69206016
    //   2904: iastore
    //   2905: dup
    //   2906: bipush #22
    //   2908: ldc 69208064
    //   2910: iastore
    //   2911: dup
    //   2912: bipush #23
    //   2914: ldc 2097154
    //   2916: iastore
    //   2917: dup
    //   2918: bipush #24
    //   2920: ldc 69206016
    //   2922: iastore
    //   2923: dup
    //   2924: bipush #25
    //   2926: sipush #2048
    //   2929: iastore
    //   2930: dup
    //   2931: bipush #26
    //   2933: sipush #2050
    //   2936: iastore
    //   2937: dup
    //   2938: bipush #27
    //   2940: ldc 69208066
    //   2942: iastore
    //   2943: dup
    //   2944: bipush #28
    //   2946: ldc 2099200
    //   2948: iastore
    //   2949: dup
    //   2950: bipush #29
    //   2952: iconst_2
    //   2953: iastore
    //   2954: dup
    //   2955: bipush #30
    //   2957: ldc 67108864
    //   2959: iastore
    //   2960: dup
    //   2961: bipush #31
    //   2963: ldc 2099200
    //   2965: iastore
    //   2966: dup
    //   2967: bipush #32
    //   2969: ldc 67108864
    //   2971: iastore
    //   2972: dup
    //   2973: bipush #33
    //   2975: ldc 2099200
    //   2977: iastore
    //   2978: dup
    //   2979: bipush #34
    //   2981: ldc 2097152
    //   2983: iastore
    //   2984: dup
    //   2985: bipush #35
    //   2987: ldc 67110914
    //   2989: iastore
    //   2990: dup
    //   2991: bipush #36
    //   2993: ldc 67110914
    //   2995: iastore
    //   2996: dup
    //   2997: bipush #37
    //   2999: ldc 69206018
    //   3001: iastore
    //   3002: dup
    //   3003: bipush #38
    //   3005: ldc 69206018
    //   3007: iastore
    //   3008: dup
    //   3009: bipush #39
    //   3011: iconst_2
    //   3012: iastore
    //   3013: dup
    //   3014: bipush #40
    //   3016: ldc 2097154
    //   3018: iastore
    //   3019: dup
    //   3020: bipush #41
    //   3022: ldc 67108864
    //   3024: iastore
    //   3025: dup
    //   3026: bipush #42
    //   3028: ldc 67110912
    //   3030: iastore
    //   3031: dup
    //   3032: bipush #43
    //   3034: ldc 2097152
    //   3036: iastore
    //   3037: dup
    //   3038: bipush #44
    //   3040: ldc 69208064
    //   3042: iastore
    //   3043: dup
    //   3044: bipush #45
    //   3046: sipush #2050
    //   3049: iastore
    //   3050: dup
    //   3051: bipush #46
    //   3053: ldc 2099202
    //   3055: iastore
    //   3056: dup
    //   3057: bipush #47
    //   3059: ldc 69208064
    //   3061: iastore
    //   3062: dup
    //   3063: bipush #48
    //   3065: sipush #2050
    //   3068: iastore
    //   3069: dup
    //   3070: bipush #49
    //   3072: ldc 67108866
    //   3074: iastore
    //   3075: dup
    //   3076: bipush #50
    //   3078: ldc 69208066
    //   3080: iastore
    //   3081: dup
    //   3082: bipush #51
    //   3084: ldc 69206016
    //   3086: iastore
    //   3087: dup
    //   3088: bipush #52
    //   3090: ldc 2099200
    //   3092: iastore
    //   3093: dup
    //   3094: bipush #53
    //   3096: iconst_0
    //   3097: iastore
    //   3098: dup
    //   3099: bipush #54
    //   3101: iconst_2
    //   3102: iastore
    //   3103: dup
    //   3104: bipush #55
    //   3106: ldc 69208066
    //   3108: iastore
    //   3109: dup
    //   3110: bipush #56
    //   3112: iconst_0
    //   3113: iastore
    //   3114: dup
    //   3115: bipush #57
    //   3117: ldc 2099202
    //   3119: iastore
    //   3120: dup
    //   3121: bipush #58
    //   3123: ldc 69206016
    //   3125: iastore
    //   3126: dup
    //   3127: bipush #59
    //   3129: sipush #2048
    //   3132: iastore
    //   3133: dup
    //   3134: bipush #60
    //   3136: ldc 67108866
    //   3138: iastore
    //   3139: dup
    //   3140: bipush #61
    //   3142: ldc 67110912
    //   3144: iastore
    //   3145: dup
    //   3146: bipush #62
    //   3148: sipush #2048
    //   3151: iastore
    //   3152: dup
    //   3153: bipush #63
    //   3155: ldc 2097154
    //   3157: iastore
    //   3158: astore #12
    //   3160: bipush #64
    //   3162: newarray int
    //   3164: dup
    //   3165: iconst_0
    //   3166: ldc 268439616
    //   3168: iastore
    //   3169: dup
    //   3170: iconst_1
    //   3171: sipush #4096
    //   3174: iastore
    //   3175: dup
    //   3176: iconst_2
    //   3177: ldc 262144
    //   3179: iastore
    //   3180: dup
    //   3181: iconst_3
    //   3182: ldc 268701760
    //   3184: iastore
    //   3185: dup
    //   3186: iconst_4
    //   3187: ldc 268435456
    //   3189: iastore
    //   3190: dup
    //   3191: iconst_5
    //   3192: ldc 268439616
    //   3194: iastore
    //   3195: dup
    //   3196: bipush #6
    //   3198: bipush #64
    //   3200: iastore
    //   3201: dup
    //   3202: bipush #7
    //   3204: ldc 268435456
    //   3206: iastore
    //   3207: dup
    //   3208: bipush #8
    //   3210: ldc 262208
    //   3212: iastore
    //   3213: dup
    //   3214: bipush #9
    //   3216: ldc 268697600
    //   3218: iastore
    //   3219: dup
    //   3220: bipush #10
    //   3222: ldc 268701760
    //   3224: iastore
    //   3225: dup
    //   3226: bipush #11
    //   3228: ldc 266240
    //   3230: iastore
    //   3231: dup
    //   3232: bipush #12
    //   3234: ldc 268701696
    //   3236: iastore
    //   3237: dup
    //   3238: bipush #13
    //   3240: ldc 266304
    //   3242: iastore
    //   3243: dup
    //   3244: bipush #14
    //   3246: sipush #4096
    //   3249: iastore
    //   3250: dup
    //   3251: bipush #15
    //   3253: bipush #64
    //   3255: iastore
    //   3256: dup
    //   3257: bipush #16
    //   3259: ldc 268697600
    //   3261: iastore
    //   3262: dup
    //   3263: bipush #17
    //   3265: ldc 268435520
    //   3267: iastore
    //   3268: dup
    //   3269: bipush #18
    //   3271: ldc 268439552
    //   3273: iastore
    //   3274: dup
    //   3275: bipush #19
    //   3277: sipush #4160
    //   3280: iastore
    //   3281: dup
    //   3282: bipush #20
    //   3284: ldc 266240
    //   3286: iastore
    //   3287: dup
    //   3288: bipush #21
    //   3290: ldc 262208
    //   3292: iastore
    //   3293: dup
    //   3294: bipush #22
    //   3296: ldc 268697664
    //   3298: iastore
    //   3299: dup
    //   3300: bipush #23
    //   3302: ldc 268701696
    //   3304: iastore
    //   3305: dup
    //   3306: bipush #24
    //   3308: sipush #4160
    //   3311: iastore
    //   3312: dup
    //   3313: bipush #25
    //   3315: iconst_0
    //   3316: iastore
    //   3317: dup
    //   3318: bipush #26
    //   3320: iconst_0
    //   3321: iastore
    //   3322: dup
    //   3323: bipush #27
    //   3325: ldc 268697664
    //   3327: iastore
    //   3328: dup
    //   3329: bipush #28
    //   3331: ldc 268435520
    //   3333: iastore
    //   3334: dup
    //   3335: bipush #29
    //   3337: ldc 268439552
    //   3339: iastore
    //   3340: dup
    //   3341: bipush #30
    //   3343: ldc 266304
    //   3345: iastore
    //   3346: dup
    //   3347: bipush #31
    //   3349: ldc 262144
    //   3351: iastore
    //   3352: dup
    //   3353: bipush #32
    //   3355: ldc 266304
    //   3357: iastore
    //   3358: dup
    //   3359: bipush #33
    //   3361: ldc 262144
    //   3363: iastore
    //   3364: dup
    //   3365: bipush #34
    //   3367: ldc 268701696
    //   3369: iastore
    //   3370: dup
    //   3371: bipush #35
    //   3373: sipush #4096
    //   3376: iastore
    //   3377: dup
    //   3378: bipush #36
    //   3380: bipush #64
    //   3382: iastore
    //   3383: dup
    //   3384: bipush #37
    //   3386: ldc 268697664
    //   3388: iastore
    //   3389: dup
    //   3390: bipush #38
    //   3392: sipush #4096
    //   3395: iastore
    //   3396: dup
    //   3397: bipush #39
    //   3399: ldc 266304
    //   3401: iastore
    //   3402: dup
    //   3403: bipush #40
    //   3405: ldc 268439552
    //   3407: iastore
    //   3408: dup
    //   3409: bipush #41
    //   3411: bipush #64
    //   3413: iastore
    //   3414: dup
    //   3415: bipush #42
    //   3417: ldc 268435520
    //   3419: iastore
    //   3420: dup
    //   3421: bipush #43
    //   3423: ldc 268697600
    //   3425: iastore
    //   3426: dup
    //   3427: bipush #44
    //   3429: ldc 268697664
    //   3431: iastore
    //   3432: dup
    //   3433: bipush #45
    //   3435: ldc 268435456
    //   3437: iastore
    //   3438: dup
    //   3439: bipush #46
    //   3441: ldc 262144
    //   3443: iastore
    //   3444: dup
    //   3445: bipush #47
    //   3447: ldc 268439616
    //   3449: iastore
    //   3450: dup
    //   3451: bipush #48
    //   3453: iconst_0
    //   3454: iastore
    //   3455: dup
    //   3456: bipush #49
    //   3458: ldc 268701760
    //   3460: iastore
    //   3461: dup
    //   3462: bipush #50
    //   3464: ldc 262208
    //   3466: iastore
    //   3467: dup
    //   3468: bipush #51
    //   3470: ldc 268435520
    //   3472: iastore
    //   3473: dup
    //   3474: bipush #52
    //   3476: ldc 268697600
    //   3478: iastore
    //   3479: dup
    //   3480: bipush #53
    //   3482: ldc 268439552
    //   3484: iastore
    //   3485: dup
    //   3486: bipush #54
    //   3488: ldc 268439616
    //   3490: iastore
    //   3491: dup
    //   3492: bipush #55
    //   3494: iconst_0
    //   3495: iastore
    //   3496: dup
    //   3497: bipush #56
    //   3499: ldc 268701760
    //   3501: iastore
    //   3502: dup
    //   3503: bipush #57
    //   3505: ldc 266240
    //   3507: iastore
    //   3508: dup
    //   3509: bipush #58
    //   3511: ldc 266240
    //   3513: iastore
    //   3514: dup
    //   3515: bipush #59
    //   3517: sipush #4160
    //   3520: iastore
    //   3521: dup
    //   3522: bipush #60
    //   3524: sipush #4160
    //   3527: iastore
    //   3528: dup
    //   3529: bipush #61
    //   3531: ldc 262208
    //   3533: iastore
    //   3534: dup
    //   3535: bipush #62
    //   3537: ldc 268435456
    //   3539: iastore
    //   3540: dup
    //   3541: bipush #63
    //   3543: ldc 268701696
    //   3545: iastore
    //   3546: astore #13
    //   3548: aload_3
    //   3549: arraylength
    //   3550: istore #14
    //   3552: iload #14
    //   3554: bipush #8
    //   3556: irem
    //   3557: ifeq -> 3581
    //   3560: new java/lang/Exception
    //   3563: dup
    //   3564: sipush #-23106
    //   3567: sipush #8135
    //   3570: invokestatic a : (II)Ljava/lang/String;
    //   3573: invokespecial <init> : (Ljava/lang/String;)V
    //   3576: athrow
    //   3577: invokestatic a : (Ljava/lang/Throwable;)Ljava/lang/Throwable;
    //   3580: athrow
    //   3581: iconst_2
    //   3582: newarray int
    //   3584: astore #15
    //   3586: iload #14
    //   3588: newarray byte
    //   3590: astore #16
    //   3592: iload #14
    //   3594: bipush #8
    //   3596: idiv
    //   3597: istore #17
    //   3599: iconst_0
    //   3600: istore #18
    //   3602: iload #18
    //   3604: iload #17
    //   3606: if_icmpge -> 4520
    //   3609: iload #18
    //   3611: bipush #8
    //   3613: imul
    //   3614: istore #19
    //   3616: iconst_0
    //   3617: istore #20
    //   3619: iload #20
    //   3621: iconst_2
    //   3622: if_icmpge -> 3707
    //   3625: aload #15
    //   3627: iload #20
    //   3629: aload_3
    //   3630: iload #19
    //   3632: iload #20
    //   3634: iconst_4
    //   3635: imul
    //   3636: iadd
    //   3637: baload
    //   3638: sipush #255
    //   3641: iand
    //   3642: bipush #24
    //   3644: ishl
    //   3645: aload_3
    //   3646: iload #19
    //   3648: iload #20
    //   3650: iconst_4
    //   3651: imul
    //   3652: iadd
    //   3653: iconst_1
    //   3654: iadd
    //   3655: baload
    //   3656: sipush #255
    //   3659: iand
    //   3660: bipush #16
    //   3662: ishl
    //   3663: ior
    //   3664: aload_3
    //   3665: iload #19
    //   3667: iload #20
    //   3669: iconst_4
    //   3670: imul
    //   3671: iadd
    //   3672: iconst_2
    //   3673: iadd
    //   3674: baload
    //   3675: sipush #255
    //   3678: iand
    //   3679: bipush #8
    //   3681: ishl
    //   3682: ior
    //   3683: aload_3
    //   3684: iload #19
    //   3686: iload #20
    //   3688: iconst_4
    //   3689: imul
    //   3690: iadd
    //   3691: iconst_3
    //   3692: iadd
    //   3693: baload
    //   3694: sipush #255
    //   3697: iand
    //   3698: ior
    //   3699: iastore
    //   3700: iinc #20, 1
    //   3703: iload_2
    //   3704: ifne -> 3619
    //   3707: iconst_0
    //   3708: istore #25
    //   3710: aload #15
    //   3712: iconst_0
    //   3713: iaload
    //   3714: istore #23
    //   3716: aload #15
    //   3718: iconst_1
    //   3719: iaload
    //   3720: istore #22
    //   3722: iload #23
    //   3724: iconst_4
    //   3725: iushr
    //   3726: iload #22
    //   3728: ixor
    //   3729: ldc 252645135
    //   3731: iand
    //   3732: istore #21
    //   3734: iload #22
    //   3736: iload #21
    //   3738: ixor
    //   3739: istore #22
    //   3741: iload #23
    //   3743: iload #21
    //   3745: iconst_4
    //   3746: ishl
    //   3747: ixor
    //   3748: istore #23
    //   3750: iload #23
    //   3752: bipush #16
    //   3754: iushr
    //   3755: iload #22
    //   3757: ixor
    //   3758: ldc 65535
    //   3760: iand
    //   3761: istore #21
    //   3763: iload #22
    //   3765: iload #21
    //   3767: ixor
    //   3768: istore #22
    //   3770: iload #23
    //   3772: iload #21
    //   3774: bipush #16
    //   3776: ishl
    //   3777: ixor
    //   3778: istore #23
    //   3780: iload #22
    //   3782: iconst_2
    //   3783: iushr
    //   3784: iload #23
    //   3786: ixor
    //   3787: ldc 858993459
    //   3789: iand
    //   3790: istore #21
    //   3792: iload #23
    //   3794: iload #21
    //   3796: ixor
    //   3797: istore #23
    //   3799: iload #22
    //   3801: iload #21
    //   3803: iconst_2
    //   3804: ishl
    //   3805: ixor
    //   3806: istore #22
    //   3808: iload #22
    //   3810: bipush #8
    //   3812: iushr
    //   3813: iload #23
    //   3815: ixor
    //   3816: ldc 16711935
    //   3818: iand
    //   3819: istore #21
    //   3821: iload #23
    //   3823: iload #21
    //   3825: ixor
    //   3826: istore #23
    //   3828: iload #22
    //   3830: iload #21
    //   3832: bipush #8
    //   3834: ishl
    //   3835: ixor
    //   3836: istore #22
    //   3838: iload #22
    //   3840: iconst_1
    //   3841: ishl
    //   3842: iload #22
    //   3844: bipush #31
    //   3846: iushr
    //   3847: iconst_1
    //   3848: iand
    //   3849: ior
    //   3850: istore #22
    //   3852: iload #23
    //   3854: iload #22
    //   3856: ixor
    //   3857: ldc -1431655766
    //   3859: iand
    //   3860: istore #21
    //   3862: iload #23
    //   3864: iload #21
    //   3866: ixor
    //   3867: istore #23
    //   3869: iload #22
    //   3871: iload #21
    //   3873: ixor
    //   3874: istore #22
    //   3876: iload #23
    //   3878: iconst_1
    //   3879: ishl
    //   3880: iload #23
    //   3882: bipush #31
    //   3884: iushr
    //   3885: iconst_1
    //   3886: iand
    //   3887: ior
    //   3888: istore #23
    //   3890: iconst_0
    //   3891: istore #24
    //   3893: iload #24
    //   3895: bipush #8
    //   3897: if_icmpge -> 4235
    //   3900: iload #22
    //   3902: bipush #28
    //   3904: ishl
    //   3905: iload #22
    //   3907: iconst_4
    //   3908: iushr
    //   3909: ior
    //   3910: istore #21
    //   3912: iload #21
    //   3914: aload #5
    //   3916: iload #25
    //   3918: iinc #25, 1
    //   3921: iaload
    //   3922: ixor
    //   3923: istore #21
    //   3925: aload #12
    //   3927: iload #21
    //   3929: bipush #63
    //   3931: iand
    //   3932: iaload
    //   3933: istore #20
    //   3935: iload #20
    //   3937: aload #10
    //   3939: iload #21
    //   3941: bipush #8
    //   3943: iushr
    //   3944: bipush #63
    //   3946: iand
    //   3947: iaload
    //   3948: ior
    //   3949: istore #20
    //   3951: iload #20
    //   3953: aload #8
    //   3955: iload #21
    //   3957: bipush #16
    //   3959: iushr
    //   3960: bipush #63
    //   3962: iand
    //   3963: iaload
    //   3964: ior
    //   3965: istore #20
    //   3967: iload #20
    //   3969: aload #6
    //   3971: iload #21
    //   3973: bipush #24
    //   3975: iushr
    //   3976: bipush #63
    //   3978: iand
    //   3979: iaload
    //   3980: ior
    //   3981: istore #20
    //   3983: iload #22
    //   3985: aload #5
    //   3987: iload #25
    //   3989: iinc #25, 1
    //   3992: iaload
    //   3993: ixor
    //   3994: istore #21
    //   3996: iload #20
    //   3998: aload #13
    //   4000: iload #21
    //   4002: bipush #63
    //   4004: iand
    //   4005: iaload
    //   4006: ior
    //   4007: istore #20
    //   4009: iload #20
    //   4011: aload #11
    //   4013: iload #21
    //   4015: bipush #8
    //   4017: iushr
    //   4018: bipush #63
    //   4020: iand
    //   4021: iaload
    //   4022: ior
    //   4023: istore #20
    //   4025: iload #20
    //   4027: aload #9
    //   4029: iload #21
    //   4031: bipush #16
    //   4033: iushr
    //   4034: bipush #63
    //   4036: iand
    //   4037: iaload
    //   4038: ior
    //   4039: istore #20
    //   4041: iload #20
    //   4043: aload #7
    //   4045: iload #21
    //   4047: bipush #24
    //   4049: iushr
    //   4050: bipush #63
    //   4052: iand
    //   4053: iaload
    //   4054: ior
    //   4055: istore #20
    //   4057: iload #23
    //   4059: iload #20
    //   4061: ixor
    //   4062: istore #23
    //   4064: iload #23
    //   4066: bipush #28
    //   4068: ishl
    //   4069: iload #23
    //   4071: iconst_4
    //   4072: iushr
    //   4073: ior
    //   4074: istore #21
    //   4076: iload #21
    //   4078: aload #5
    //   4080: iload #25
    //   4082: iinc #25, 1
    //   4085: iaload
    //   4086: ixor
    //   4087: istore #21
    //   4089: aload #12
    //   4091: iload #21
    //   4093: bipush #63
    //   4095: iand
    //   4096: iaload
    //   4097: istore #20
    //   4099: iload #20
    //   4101: aload #10
    //   4103: iload #21
    //   4105: bipush #8
    //   4107: iushr
    //   4108: bipush #63
    //   4110: iand
    //   4111: iaload
    //   4112: ior
    //   4113: istore #20
    //   4115: iload #20
    //   4117: aload #8
    //   4119: iload #21
    //   4121: bipush #16
    //   4123: iushr
    //   4124: bipush #63
    //   4126: iand
    //   4127: iaload
    //   4128: ior
    //   4129: istore #20
    //   4131: iload #20
    //   4133: aload #6
    //   4135: iload #21
    //   4137: bipush #24
    //   4139: iushr
    //   4140: bipush #63
    //   4142: iand
    //   4143: iaload
    //   4144: ior
    //   4145: istore #20
    //   4147: iload #23
    //   4149: aload #5
    //   4151: iload #25
    //   4153: iinc #25, 1
    //   4156: iaload
    //   4157: ixor
    //   4158: istore #21
    //   4160: iload #20
    //   4162: aload #13
    //   4164: iload #21
    //   4166: bipush #63
    //   4168: iand
    //   4169: iaload
    //   4170: ior
    //   4171: istore #20
    //   4173: iload #20
    //   4175: aload #11
    //   4177: iload #21
    //   4179: bipush #8
    //   4181: iushr
    //   4182: bipush #63
    //   4184: iand
    //   4185: iaload
    //   4186: ior
    //   4187: istore #20
    //   4189: iload #20
    //   4191: aload #9
    //   4193: iload #21
    //   4195: bipush #16
    //   4197: iushr
    //   4198: bipush #63
    //   4200: iand
    //   4201: iaload
    //   4202: ior
    //   4203: istore #20
    //   4205: iload #20
    //   4207: aload #7
    //   4209: iload #21
    //   4211: bipush #24
    //   4213: iushr
    //   4214: bipush #63
    //   4216: iand
    //   4217: iaload
    //   4218: ior
    //   4219: istore #20
    //   4221: iload #22
    //   4223: iload #20
    //   4225: ixor
    //   4226: istore #22
    //   4228: iinc #24, 1
    //   4231: iload_2
    //   4232: ifne -> 3893
    //   4235: iload #22
    //   4237: bipush #31
    //   4239: ishl
    //   4240: iload #22
    //   4242: iconst_1
    //   4243: iushr
    //   4244: ior
    //   4245: istore #22
    //   4247: iload #23
    //   4249: iload #22
    //   4251: ixor
    //   4252: ldc -1431655766
    //   4254: iand
    //   4255: istore #21
    //   4257: iload #23
    //   4259: iload #21
    //   4261: ixor
    //   4262: istore #23
    //   4264: iload #22
    //   4266: iload #21
    //   4268: ixor
    //   4269: istore #22
    //   4271: iload #23
    //   4273: bipush #31
    //   4275: ishl
    //   4276: iload #23
    //   4278: iconst_1
    //   4279: iushr
    //   4280: ior
    //   4281: istore #23
    //   4283: iload #23
    //   4285: bipush #8
    //   4287: iushr
    //   4288: iload #22
    //   4290: ixor
    //   4291: ldc 16711935
    //   4293: iand
    //   4294: istore #21
    //   4296: iload #22
    //   4298: iload #21
    //   4300: ixor
    //   4301: istore #22
    //   4303: iload #23
    //   4305: iload #21
    //   4307: bipush #8
    //   4309: ishl
    //   4310: ixor
    //   4311: istore #23
    //   4313: iload #23
    //   4315: iconst_2
    //   4316: iushr
    //   4317: iload #22
    //   4319: ixor
    //   4320: ldc 858993459
    //   4322: iand
    //   4323: istore #21
    //   4325: iload #22
    //   4327: iload #21
    //   4329: ixor
    //   4330: istore #22
    //   4332: iload #23
    //   4334: iload #21
    //   4336: iconst_2
    //   4337: ishl
    //   4338: ixor
    //   4339: istore #23
    //   4341: iload #22
    //   4343: bipush #16
    //   4345: iushr
    //   4346: iload #23
    //   4348: ixor
    //   4349: ldc 65535
    //   4351: iand
    //   4352: istore #21
    //   4354: iload #23
    //   4356: iload #21
    //   4358: ixor
    //   4359: istore #23
    //   4361: iload #22
    //   4363: iload #21
    //   4365: bipush #16
    //   4367: ishl
    //   4368: ixor
    //   4369: istore #22
    //   4371: iload #22
    //   4373: iconst_4
    //   4374: iushr
    //   4375: iload #23
    //   4377: ixor
    //   4378: ldc 252645135
    //   4380: iand
    //   4381: istore #21
    //   4383: iload #23
    //   4385: iload #21
    //   4387: ixor
    //   4388: istore #23
    //   4390: iload #22
    //   4392: iload #21
    //   4394: iconst_4
    //   4395: ishl
    //   4396: ixor
    //   4397: istore #22
    //   4399: aload #15
    //   4401: iconst_0
    //   4402: iload #22
    //   4404: iastore
    //   4405: aload #15
    //   4407: iconst_1
    //   4408: iload #23
    //   4410: iastore
    //   4411: iload #18
    //   4413: bipush #8
    //   4415: imul
    //   4416: istore #26
    //   4418: iconst_0
    //   4419: istore #27
    //   4421: iload #27
    //   4423: iconst_2
    //   4424: if_icmpge -> 4513
    //   4427: aload #16
    //   4429: iload #26
    //   4431: iload #27
    //   4433: iconst_4
    //   4434: imul
    //   4435: iadd
    //   4436: aload #15
    //   4438: iload #27
    //   4440: iaload
    //   4441: bipush #24
    //   4443: iushr
    //   4444: i2b
    //   4445: bastore
    //   4446: aload #16
    //   4448: iload #26
    //   4450: iload #27
    //   4452: iconst_4
    //   4453: imul
    //   4454: iadd
    //   4455: iconst_1
    //   4456: iadd
    //   4457: aload #15
    //   4459: iload #27
    //   4461: iaload
    //   4462: bipush #16
    //   4464: iushr
    //   4465: i2b
    //   4466: bastore
    //   4467: aload #16
    //   4469: iload #26
    //   4471: iload #27
    //   4473: iconst_4
    //   4474: imul
    //   4475: iadd
    //   4476: iconst_2
    //   4477: iadd
    //   4478: aload #15
    //   4480: iload #27
    //   4482: iaload
    //   4483: bipush #8
    //   4485: iushr
    //   4486: i2b
    //   4487: bastore
    //   4488: aload #16
    //   4490: iload #26
    //   4492: iload #27
    //   4494: iconst_4
    //   4495: imul
    //   4496: iadd
    //   4497: iconst_3
    //   4498: iadd
    //   4499: aload #15
    //   4501: iload #27
    //   4503: iaload
    //   4504: i2b
    //   4505: bastore
    //   4506: iinc #27, 1
    //   4509: iload_2
    //   4510: ifne -> 4421
    //   4513: iinc #18, 1
    //   4516: iload_2
    //   4517: ifne -> 3602
    //   4520: aload #16
    //   4522: aload #16
    //   4524: arraylength
    //   4525: iconst_1
    //   4526: isub
    //   4527: baload
    //   4528: istore #18
    //   4530: aload #16
    //   4532: arraylength
    //   4533: iload #18
    //   4535: isub
    //   4536: newarray byte
    //   4538: astore #4
    //   4540: aload #16
    //   4542: arraylength
    //   4543: aload #4
    //   4545: arraylength
    //   4546: if_icmpge -> 4570
    //   4549: new java/lang/Exception
    //   4552: dup
    //   4553: sipush #-23118
    //   4556: sipush #30114
    //   4559: invokestatic a : (II)Ljava/lang/String;
    //   4562: invokespecial <init> : (Ljava/lang/String;)V
    //   4565: athrow
    //   4566: invokestatic a : (Ljava/lang/Throwable;)Ljava/lang/Throwable;
    //   4569: athrow
    //   4570: iconst_0
    //   4571: istore #19
    //   4573: iload #19
    //   4575: aload #4
    //   4577: arraylength
    //   4578: if_icmpge -> 4598
    //   4581: aload #4
    //   4583: iload #19
    //   4585: aload #16
    //   4587: iload #19
    //   4589: baload
    //   4590: bastore
    //   4591: iinc #19, 1
    //   4594: iload_2
    //   4595: ifne -> 4573
    //   4598: new java/math/BigInteger
    //   4601: dup
    //   4602: aload #4
    //   4604: invokespecial <init> : ([B)V
    //   4607: invokevirtual abs : ()Ljava/math/BigInteger;
    //   4610: putstatic burp/Zt1h.Zb : Ljava/lang/Object;
    //   4613: getstatic burp/Zl7x.Za : Ljava/lang/Object;
    //   4616: checkcast java/math/BigInteger
    //   4619: invokevirtual toByteArray : ()[B
    //   4622: astore_3
    //   4623: aload_3
    //   4624: arraylength
    //   4625: bipush #8
    //   4627: iadd
    //   4628: bipush #6
    //   4630: ishr
    //   4631: iconst_1
    //   4632: iadd
    //   4633: bipush #16
    //   4635: imul
    //   4636: newarray int
    //   4638: astore #5
    //   4640: iconst_0
    //   4641: istore #6
    //   4643: iload #6
    //   4645: aload_3
    //   4646: arraylength
    //   4647: if_icmpge -> 4690
    //   4650: aload_3
    //   4651: iload #6
    //   4653: baload
    //   4654: sipush #255
    //   4657: iand
    //   4658: istore #7
    //   4660: aload #5
    //   4662: iload #6
    //   4664: iconst_2
    //   4665: ishr
    //   4666: dup2
    //   4667: iaload
    //   4668: iload #7
    //   4670: bipush #24
    //   4672: iload #6
    //   4674: iconst_4
    //   4675: irem
    //   4676: bipush #8
    //   4678: imul
    //   4679: isub
    //   4680: ishl
    //   4681: ior
    //   4682: iastore
    //   4683: iinc #6, 1
    //   4686: iload_2
    //   4687: ifne -> 4643
    //   4690: aload #5
    //   4692: iload #6
    //   4694: iconst_2
    //   4695: ishr
    //   4696: dup2
    //   4697: iaload
    //   4698: sipush #128
    //   4701: bipush #24
    //   4703: iload #6
    //   4705: iconst_4
    //   4706: irem
    //   4707: bipush #8
    //   4709: imul
    //   4710: isub
    //   4711: ishl
    //   4712: ior
    //   4713: iastore
    //   4714: aload #5
    //   4716: aload #5
    //   4718: arraylength
    //   4719: iconst_1
    //   4720: isub
    //   4721: aload_3
    //   4722: arraylength
    //   4723: bipush #8
    //   4725: imul
    //   4726: iastore
    //   4727: bipush #80
    //   4729: newarray int
    //   4731: astore #7
    //   4733: ldc 1732584193
    //   4735: istore #8
    //   4737: ldc -271733879
    //   4739: istore #9
    //   4741: ldc -1732584194
    //   4743: istore #10
    //   4745: ldc 271733878
    //   4747: istore #11
    //   4749: ldc -1009589776
    //   4751: istore #12
    //   4753: iconst_0
    //   4754: istore #6
    //   4756: iload #6
    //   4758: aload #5
    //   4760: arraylength
    //   4761: if_icmpge -> 5083
    //   4764: iload #8
    //   4766: istore #13
    //   4768: iload #9
    //   4770: istore #14
    //   4772: iload #10
    //   4774: istore #15
    //   4776: iload #11
    //   4778: istore #16
    //   4780: iload #12
    //   4782: istore #17
    //   4784: iconst_0
    //   4785: istore #18
    //   4787: iload #18
    //   4789: bipush #80
    //   4791: if_icmpge -> 5041
    //   4794: iload #18
    //   4796: bipush #16
    //   4798: if_icmpge -> 4825
    //   4801: aload #7
    //   4803: iload #18
    //   4805: aload #5
    //   4807: iload #6
    //   4809: iload #18
    //   4811: iadd
    //   4812: iaload
    //   4813: iastore
    //   4814: iload_2
    //   4815: ifne -> 4880
    //   4818: goto -> 4825
    //   4821: invokestatic a : (Ljava/lang/Throwable;)Ljava/lang/Throwable;
    //   4824: athrow
    //   4825: aload #7
    //   4827: iload #18
    //   4829: iconst_3
    //   4830: isub
    //   4831: iaload
    //   4832: aload #7
    //   4834: iload #18
    //   4836: bipush #8
    //   4838: isub
    //   4839: iaload
    //   4840: ixor
    //   4841: aload #7
    //   4843: iload #18
    //   4845: bipush #14
    //   4847: isub
    //   4848: iaload
    //   4849: ixor
    //   4850: aload #7
    //   4852: iload #18
    //   4854: bipush #16
    //   4856: isub
    //   4857: iaload
    //   4858: ixor
    //   4859: istore #19
    //   4861: iload #19
    //   4863: iconst_1
    //   4864: ishl
    //   4865: iload #19
    //   4867: bipush #31
    //   4869: iushr
    //   4870: ior
    //   4871: istore #20
    //   4873: aload #7
    //   4875: iload #18
    //   4877: iload #20
    //   4879: iastore
    //   4880: iload #8
    //   4882: iconst_5
    //   4883: ishl
    //   4884: iload #8
    //   4886: bipush #27
    //   4888: iushr
    //   4889: ior
    //   4890: istore #19
    //   4892: iload #19
    //   4894: iload #12
    //   4896: iadd
    //   4897: aload #7
    //   4899: iload #18
    //   4901: iaload
    //   4902: iadd
    //   4903: iload #18
    //   4905: bipush #20
    //   4907: if_icmpge -> 4933
    //   4910: ldc 1518500249
    //   4912: iload #9
    //   4914: iload #10
    //   4916: iand
    //   4917: iload #9
    //   4919: iconst_m1
    //   4920: ixor
    //   4921: iload #11
    //   4923: iand
    //   4924: ior
    //   4925: iadd
    //   4926: goto -> 5003
    //   4929: invokestatic a : (Ljava/lang/Throwable;)Ljava/lang/Throwable;
    //   4932: athrow
    //   4933: iload #18
    //   4935: bipush #40
    //   4937: if_icmpge -> 4958
    //   4940: ldc 1859775393
    //   4942: iload #9
    //   4944: iload #10
    //   4946: ixor
    //   4947: iload #11
    //   4949: ixor
    //   4950: iadd
    //   4951: goto -> 5003
    //   4954: invokestatic a : (Ljava/lang/Throwable;)Ljava/lang/Throwable;
    //   4957: athrow
    //   4958: iload #18
    //   4960: bipush #60
    //   4962: if_icmpge -> 4992
    //   4965: ldc -1894007588
    //   4967: iload #9
    //   4969: iload #10
    //   4971: iand
    //   4972: iload #9
    //   4974: iload #11
    //   4976: iand
    //   4977: ior
    //   4978: iload #10
    //   4980: iload #11
    //   4982: iand
    //   4983: ior
    //   4984: iadd
    //   4985: goto -> 5003
    //   4988: invokestatic a : (Ljava/lang/Throwable;)Ljava/lang/Throwable;
    //   4991: athrow
    //   4992: ldc -899497514
    //   4994: iload #9
    //   4996: iload #10
    //   4998: ixor
    //   4999: iload #11
    //   5001: ixor
    //   5002: iadd
    //   5003: iadd
    //   5004: istore #20
    //   5006: iload #11
    //   5008: istore #12
    //   5010: iload #10
    //   5012: istore #11
    //   5014: iload #9
    //   5016: bipush #30
    //   5018: ishl
    //   5019: iload #9
    //   5021: iconst_2
    //   5022: iushr
    //   5023: ior
    //   5024: istore #10
    //   5026: iload #8
    //   5028: istore #9
    //   5030: iload #20
    //   5032: istore #8
    //   5034: iinc #18, 1
    //   5037: iload_2
    //   5038: ifne -> 4787
    //   5041: iload #8
    //   5043: iload #13
    //   5045: iadd
    //   5046: istore #8
    //   5048: iload #9
    //   5050: iload #14
    //   5052: iadd
    //   5053: istore #9
    //   5055: iload #10
    //   5057: iload #15
    //   5059: iadd
    //   5060: istore #10
    //   5062: iload #11
    //   5064: iload #16
    //   5066: iadd
    //   5067: istore #11
    //   5069: iload #12
    //   5071: iload #17
    //   5073: iadd
    //   5074: istore #12
    //   5076: iinc #6, 16
    //   5079: iload_2
    //   5080: ifne -> 4756
    //   5083: iconst_5
    //   5084: newarray int
    //   5086: dup
    //   5087: iconst_0
    //   5088: iload #8
    //   5090: iastore
    //   5091: dup
    //   5092: iconst_1
    //   5093: iload #9
    //   5095: iastore
    //   5096: dup
    //   5097: iconst_2
    //   5098: iload #10
    //   5100: iastore
    //   5101: dup
    //   5102: iconst_3
    //   5103: iload #11
    //   5105: iastore
    //   5106: dup
    //   5107: iconst_4
    //   5108: iload #12
    //   5110: iastore
    //   5111: astore #13
    //   5113: bipush #20
    //   5115: newarray byte
    //   5117: astore #14
    //   5119: iconst_0
    //   5120: istore #15
    //   5122: iload #15
    //   5124: bipush #20
    //   5126: if_icmpge -> 5167
    //   5129: aload #13
    //   5131: iload #15
    //   5133: iconst_4
    //   5134: idiv
    //   5135: iaload
    //   5136: istore #16
    //   5138: iconst_3
    //   5139: iload #15
    //   5141: iconst_4
    //   5142: irem
    //   5143: isub
    //   5144: bipush #8
    //   5146: imul
    //   5147: istore #17
    //   5149: aload #14
    //   5151: iload #15
    //   5153: iload #16
    //   5155: iload #17
    //   5157: iushr
    //   5158: i2b
    //   5159: bastore
    //   5160: iinc #15, 1
    //   5163: iload_2
    //   5164: ifne -> 5122
    //   5167: aload #14
    //   5169: astore #4
    //   5171: sipush #-23108
    //   5174: new java/math/BigInteger
    //   5177: dup
    //   5178: aload #4
    //   5180: invokespecial <init> : ([B)V
    //   5183: invokevirtual abs : ()Ljava/math/BigInteger;
    //   5186: putstatic burp/Zbwj.ZW : Ljava/lang/Object;
    //   5189: sipush #2078
    //   5192: invokestatic a : (II)Ljava/lang/String;
    //   5195: iconst_1
    //   5196: ldc burp/Zva
    //   5198: invokevirtual getClassLoader : ()Ljava/lang/ClassLoader;
    //   5201: invokestatic forName : (Ljava/lang/String;ZLjava/lang/ClassLoader;)Ljava/lang/Class;
    //   5204: invokevirtual getDeclaredFields : ()[Ljava/lang/reflect/Field;
    //   5207: astore_3
    //   5208: aload_3
    //   5209: arraylength
    //   5210: istore #4
    //   5212: iconst_0
    //   5213: istore #5
    //   5215: iload #5
    //   5217: iload #4
    //   5219: if_icmpge -> 5356
    //   5222: aload_3
    //   5223: iload #5
    //   5225: aaload
    //   5226: astore #6
    //   5228: aload #6
    //   5230: invokevirtual getModifiers : ()I
    //   5233: invokestatic isStatic : (I)Z
    //   5236: ifne -> 5246
    //   5239: goto -> 5349
    //   5242: invokestatic a : (Ljava/lang/Throwable;)Ljava/lang/Throwable;
    //   5245: athrow
    //   5246: aload #6
    //   5248: invokevirtual getType : ()Ljava/lang/Class;
    //   5251: astore #7
    //   5253: aload #7
    //   5255: ifnull -> 5336
    //   5258: aload #7
    //   5260: invokevirtual isPrimitive : ()Z
    //   5263: ifne -> 5336
    //   5266: goto -> 5273
    //   5269: invokestatic a : (Ljava/lang/Throwable;)Ljava/lang/Throwable;
    //   5272: athrow
    //   5273: aload #7
    //   5275: invokevirtual getPackage : ()Ljava/lang/Package;
    //   5278: ifnull -> 5336
    //   5281: goto -> 5288
    //   5284: invokestatic a : (Ljava/lang/Throwable;)Ljava/lang/Throwable;
    //   5287: athrow
    //   5288: aload #7
    //   5290: invokevirtual getPackage : ()Ljava/lang/Package;
    //   5293: invokevirtual getName : ()Ljava/lang/String;
    //   5296: ifnull -> 5336
    //   5299: goto -> 5306
    //   5302: invokestatic a : (Ljava/lang/Throwable;)Ljava/lang/Throwable;
    //   5305: athrow
    //   5306: aload #7
    //   5308: invokevirtual getPackage : ()Ljava/lang/Package;
    //   5311: invokevirtual getName : ()Ljava/lang/String;
    //   5314: sipush #-23111
    //   5317: sipush #-4420
    //   5320: invokestatic a : (II)Ljava/lang/String;
    //   5323: invokevirtual startsWith : (Ljava/lang/String;)Z
    //   5326: ifne -> 5336
    //   5329: goto -> 5336
    //   5332: invokestatic a : (Ljava/lang/Throwable;)Ljava/lang/Throwable;
    //   5335: athrow
    //   5336: aload #6
    //   5338: iconst_1
    //   5339: invokevirtual setAccessible : (Z)V
    //   5342: aload #6
    //   5344: aconst_null
    //   5345: invokevirtual get : (Ljava/lang/Object;)Ljava/lang/Object;
    //   5348: pop
    //   5349: iinc #5, 1
    //   5352: iload_2
    //   5353: ifne -> 5215
    //   5356: sipush #-23113
    //   5359: sipush #18104
    //   5362: invokestatic a : (II)Ljava/lang/String;
    //   5365: invokestatic forName : (Ljava/lang/String;)Ljava/lang/Class;
    //   5368: invokevirtual getDeclaredMethods : ()[Ljava/lang/reflect/Method;
    //   5371: astore_3
    //   5372: aload_3
    //   5373: arraylength
    //   5374: istore #4
    //   5376: iconst_0
    //   5377: istore #5
    //   5379: iload #5
    //   5381: iload #4
    //   5383: if_icmpge -> 5515
    //   5386: aload_3
    //   5387: iload #5
    //   5389: aaload
    //   5390: astore #6
    //   5392: aload #6
    //   5394: invokevirtual getParameterTypes : ()[Ljava/lang/Class;
    //   5397: pop
    //   5398: aload #6
    //   5400: invokevirtual getModifiers : ()I
    //   5403: invokestatic isStatic : (I)Z
    //   5406: ifeq -> 5501
    //   5409: aload #6
    //   5411: invokevirtual getParameterTypes : ()[Ljava/lang/Class;
    //   5414: arraylength
    //   5415: iconst_2
    //   5416: if_icmpne -> 5501
    //   5419: goto -> 5426
    //   5422: invokestatic a : (Ljava/lang/Throwable;)Ljava/lang/Throwable;
    //   5425: athrow
    //   5426: aload #6
    //   5428: invokevirtual getReturnType : ()Ljava/lang/Class;
    //   5431: getstatic java/lang/Void.TYPE : Ljava/lang/Class;
    //   5434: invokevirtual equals : (Ljava/lang/Object;)Z
    //   5437: ifeq -> 5501
    //   5440: goto -> 5447
    //   5443: invokestatic a : (Ljava/lang/Throwable;)Ljava/lang/Throwable;
    //   5446: athrow
    //   5447: aload #6
    //   5449: iconst_1
    //   5450: invokevirtual setAccessible : (Z)V
    //   5453: aload #6
    //   5455: aconst_null
    //   5456: iconst_2
    //   5457: anewarray java/lang/Object
    //   5460: dup
    //   5461: iconst_0
    //   5462: aload_0
    //   5463: aastore
    //   5464: dup
    //   5465: iconst_1
    //   5466: aload_1
    //   5467: ifnonnull -> 5485
    //   5470: goto -> 5477
    //   5473: invokestatic a : (Ljava/lang/Throwable;)Ljava/lang/Throwable;
    //   5476: athrow
    //   5477: aload_1
    //   5478: goto -> 5492
    //   5481: invokestatic a : (Ljava/lang/Throwable;)Ljava/lang/Throwable;
    //   5484: athrow
    //   5485: aload_1
    //   5486: checkcast [B
    //   5489: invokevirtual clone : ()Ljava/lang/Object;
    //   5492: aastore
    //   5493: invokevirtual invoke : (Ljava/lang/Object;[Ljava/lang/Object;)Ljava/lang/Object;
    //   5496: pop
    //   5497: iload_2
    //   5498: ifne -> 5515
    //   5501: iinc #5, 1
    //   5504: iload_2
    //   5505: ifne -> 5379
    //   5508: goto -> 5515
    //   5511: invokestatic a : (Ljava/lang/Throwable;)Ljava/lang/Throwable;
    //   5514: athrow
    //   5515: getstatic burp/Zr1h.Z_ : Ljava/lang/Object;
    //   5518: checkcast java/math/BigInteger
    //   5521: invokevirtual intValue : ()I
    //   5524: i2l
    //   5525: invokestatic currentTimeMillis : ()J
    //   5528: ladd
    //   5529: getstatic burp/Zea8.ZF : Ljava/lang/Object;
    //   5532: checkcast java/math/BigInteger
    //   5535: invokevirtual intValue : ()I
    //   5538: i2l
    //   5539: lcmp
    //   5540: ifge -> 5872
    //   5543: sipush #-23115
    //   5546: sipush #7254
    //   5549: invokestatic a : (II)Ljava/lang/String;
    //   5552: iconst_1
    //   5553: ldc burp/Zz0b
    //   5555: invokevirtual getClassLoader : ()Ljava/lang/ClassLoader;
    //   5558: invokestatic forName : (Ljava/lang/String;ZLjava/lang/ClassLoader;)Ljava/lang/Class;
    //   5561: invokevirtual getDeclaredFields : ()[Ljava/lang/reflect/Field;
    //   5564: astore_3
    //   5565: aload_3
    //   5566: arraylength
    //   5567: istore #4
    //   5569: iconst_0
    //   5570: istore #5
    //   5572: iload #5
    //   5574: iload #4
    //   5576: if_icmpge -> 5713
    //   5579: aload_3
    //   5580: iload #5
    //   5582: aaload
    //   5583: astore #6
    //   5585: aload #6
    //   5587: invokevirtual getModifiers : ()I
    //   5590: invokestatic isStatic : (I)Z
    //   5593: ifne -> 5603
    //   5596: goto -> 5706
    //   5599: invokestatic a : (Ljava/lang/Throwable;)Ljava/lang/Throwable;
    //   5602: athrow
    //   5603: aload #6
    //   5605: invokevirtual getType : ()Ljava/lang/Class;
    //   5608: astore #7
    //   5610: aload #7
    //   5612: ifnull -> 5693
    //   5615: aload #7
    //   5617: invokevirtual isPrimitive : ()Z
    //   5620: ifne -> 5693
    //   5623: goto -> 5630
    //   5626: invokestatic a : (Ljava/lang/Throwable;)Ljava/lang/Throwable;
    //   5629: athrow
    //   5630: aload #7
    //   5632: invokevirtual getPackage : ()Ljava/lang/Package;
    //   5635: ifnull -> 5693
    //   5638: goto -> 5645
    //   5641: invokestatic a : (Ljava/lang/Throwable;)Ljava/lang/Throwable;
    //   5644: athrow
    //   5645: aload #7
    //   5647: invokevirtual getPackage : ()Ljava/lang/Package;
    //   5650: invokevirtual getName : ()Ljava/lang/String;
    //   5653: ifnull -> 5693
    //   5656: goto -> 5663
    //   5659: invokestatic a : (Ljava/lang/Throwable;)Ljava/lang/Throwable;
    //   5662: athrow
    //   5663: aload #7
    //   5665: invokevirtual getPackage : ()Ljava/lang/Package;
    //   5668: invokevirtual getName : ()Ljava/lang/String;
    //   5671: sipush #-23110
    //   5674: sipush #-28130
    //   5677: invokestatic a : (II)Ljava/lang/String;
    //   5680: invokevirtual startsWith : (Ljava/lang/String;)Z
    //   5683: ifne -> 5693
    //   5686: goto -> 5693
    //   5689: invokestatic a : (Ljava/lang/Throwable;)Ljava/lang/Throwable;
    //   5692: athrow
    //   5693: aload #6
    //   5695: iconst_1
    //   5696: invokevirtual setAccessible : (Z)V
    //   5699: aload #6
    //   5701: aconst_null
    //   5702: invokevirtual get : (Ljava/lang/Object;)Ljava/lang/Object;
    //   5705: pop
    //   5706: iinc #5, 1
    //   5709: iload_2
    //   5710: ifne -> 5572
    //   5713: sipush #-23117
    //   5716: sipush #22971
    //   5719: invokestatic a : (II)Ljava/lang/String;
    //   5722: invokestatic forName : (Ljava/lang/String;)Ljava/lang/Class;
    //   5725: invokevirtual getDeclaredMethods : ()[Ljava/lang/reflect/Method;
    //   5728: astore_3
    //   5729: aload_3
    //   5730: arraylength
    //   5731: istore #4
    //   5733: iconst_0
    //   5734: istore #5
    //   5736: iload #5
    //   5738: iload #4
    //   5740: if_icmpge -> 5872
    //   5743: aload_3
    //   5744: iload #5
    //   5746: aaload
    //   5747: astore #6
    //   5749: aload #6
    //   5751: invokevirtual getParameterTypes : ()[Ljava/lang/Class;
    //   5754: pop
    //   5755: aload #6
    //   5757: invokevirtual getModifiers : ()I
    //   5760: invokestatic isStatic : (I)Z
    //   5763: ifeq -> 5858
    //   5766: aload #6
    //   5768: invokevirtual getParameterTypes : ()[Ljava/lang/Class;
    //   5771: arraylength
    //   5772: iconst_2
    //   5773: if_icmpne -> 5858
    //   5776: goto -> 5783
    //   5779: invokestatic a : (Ljava/lang/Throwable;)Ljava/lang/Throwable;
    //   5782: athrow
    //   5783: aload #6
    //   5785: invokevirtual getReturnType : ()Ljava/lang/Class;
    //   5788: getstatic java/lang/Void.TYPE : Ljava/lang/Class;
    //   5791: invokevirtual equals : (Ljava/lang/Object;)Z
    //   5794: ifeq -> 5858
    //   5797: goto -> 5804
    //   5800: invokestatic a : (Ljava/lang/Throwable;)Ljava/lang/Throwable;
    //   5803: athrow
    //   5804: aload #6
    //   5806: iconst_1
    //   5807: invokevirtual setAccessible : (Z)V
    //   5810: aload #6
    //   5812: aconst_null
    //   5813: iconst_2
    //   5814: anewarray java/lang/Object
    //   5817: dup
    //   5818: iconst_0
    //   5819: aload_0
    //   5820: aastore
    //   5821: dup
    //   5822: iconst_1
    //   5823: aload_1
    //   5824: ifnonnull -> 5842
    //   5827: goto -> 5834
    //   5830: invokestatic a : (Ljava/lang/Throwable;)Ljava/lang/Throwable;
    //   5833: athrow
    //   5834: aload_1
    //   5835: goto -> 5849
    //   5838: invokestatic a : (Ljava/lang/Throwable;)Ljava/lang/Throwable;
    //   5841: athrow
    //   5842: aload_1
    //   5843: checkcast [B
    //   5846: invokevirtual clone : ()Ljava/lang/Object;
    //   5849: aastore
    //   5850: invokevirtual invoke : (Ljava/lang/Object;[Ljava/lang/Object;)Ljava/lang/Object;
    //   5853: pop
    //   5854: iload_2
    //   5855: ifne -> 5872
    //   5858: iinc #5, 1
    //   5861: iload_2
    //   5862: ifne -> 5736
    //   5865: goto -> 5872
    //   5868: invokestatic a : (Ljava/lang/Throwable;)Ljava/lang/Throwable;
    //   5871: athrow
    //   5872: sipush #-23120
    //   5875: sipush #8834
    //   5878: invokestatic a : (II)Ljava/lang/String;
    //   5881: iconst_1
    //   5882: ldc burp/Zzh9
    //   5884: invokevirtual getClassLoader : ()Ljava/lang/ClassLoader;
    //   5887: invokestatic forName : (Ljava/lang/String;ZLjava/lang/ClassLoader;)Ljava/lang/Class;
    //   5890: invokevirtual getDeclaredFields : ()[Ljava/lang/reflect/Field;
    //   5893: astore_3
    //   5894: aload_3
    //   5895: arraylength
    //   5896: istore #4
    //   5898: iconst_0
    //   5899: istore #5
    //   5901: iload #5
    //   5903: iload #4
    //   5905: if_icmpge -> 6042
    //   5908: aload_3
    //   5909: iload #5
    //   5911: aaload
    //   5912: astore #6
    //   5914: aload #6
    //   5916: invokevirtual getModifiers : ()I
    //   5919: invokestatic isStatic : (I)Z
    //   5922: ifne -> 5932
    //   5925: goto -> 6035
    //   5928: invokestatic a : (Ljava/lang/Throwable;)Ljava/lang/Throwable;
    //   5931: athrow
    //   5932: aload #6
    //   5934: invokevirtual getType : ()Ljava/lang/Class;
    //   5937: astore #7
    //   5939: aload #7
    //   5941: ifnull -> 6022
    //   5944: aload #7
    //   5946: invokevirtual isPrimitive : ()Z
    //   5949: ifne -> 6022
    //   5952: goto -> 5959
    //   5955: invokestatic a : (Ljava/lang/Throwable;)Ljava/lang/Throwable;
    //   5958: athrow
    //   5959: aload #7
    //   5961: invokevirtual getPackage : ()Ljava/lang/Package;
    //   5964: ifnull -> 6022
    //   5967: goto -> 5974
    //   5970: invokestatic a : (Ljava/lang/Throwable;)Ljava/lang/Throwable;
    //   5973: athrow
    //   5974: aload #7
    //   5976: invokevirtual getPackage : ()Ljava/lang/Package;
    //   5979: invokevirtual getName : ()Ljava/lang/String;
    //   5982: ifnull -> 6022
    //   5985: goto -> 5992
    //   5988: invokestatic a : (Ljava/lang/Throwable;)Ljava/lang/Throwable;
    //   5991: athrow
    //   5992: aload #7
    //   5994: invokevirtual getPackage : ()Ljava/lang/Package;
    //   5997: invokevirtual getName : ()Ljava/lang/String;
    //   6000: sipush #-23110
    //   6003: sipush #-28130
    //   6006: invokestatic a : (II)Ljava/lang/String;
    //   6009: invokevirtual startsWith : (Ljava/lang/String;)Z
    //   6012: ifne -> 6022
    //   6015: goto -> 6022
    //   6018: invokestatic a : (Ljava/lang/Throwable;)Ljava/lang/Throwable;
    //   6021: athrow
    //   6022: aload #6
    //   6024: iconst_1
    //   6025: invokevirtual setAccessible : (Z)V
    //   6028: aload #6
    //   6030: aconst_null
    //   6031: invokevirtual get : (Ljava/lang/Object;)Ljava/lang/Object;
    //   6034: pop
    //   6035: iinc #5, 1
    //   6038: iload_2
    //   6039: ifne -> 5901
    //   6042: sipush #-23112
    //   6045: sipush #-4885
    //   6048: invokestatic a : (II)Ljava/lang/String;
    //   6051: invokestatic forName : (Ljava/lang/String;)Ljava/lang/Class;
    //   6054: invokevirtual getDeclaredMethods : ()[Ljava/lang/reflect/Method;
    //   6057: astore_3
    //   6058: aload_3
    //   6059: arraylength
    //   6060: istore #4
    //   6062: iconst_0
    //   6063: istore #5
    //   6065: iload #5
    //   6067: iload #4
    //   6069: if_icmpge -> 6180
    //   6072: aload_3
    //   6073: iload #5
    //   6075: aaload
    //   6076: astore #6
    //   6078: aload #6
    //   6080: invokevirtual getParameterTypes : ()[Ljava/lang/Class;
    //   6083: pop
    //   6084: aload #6
    //   6086: invokevirtual getModifiers : ()I
    //   6089: invokestatic isStatic : (I)Z
    //   6092: ifeq -> 6166
    //   6095: aload #6
    //   6097: invokevirtual getParameterTypes : ()[Ljava/lang/Class;
    //   6100: arraylength
    //   6101: iconst_2
    //   6102: if_icmpne -> 6166
    //   6105: goto -> 6112
    //   6108: invokestatic a : (Ljava/lang/Throwable;)Ljava/lang/Throwable;
    //   6111: athrow
    //   6112: aload #6
    //   6114: invokevirtual getReturnType : ()Ljava/lang/Class;
    //   6117: getstatic java/lang/Boolean.TYPE : Ljava/lang/Class;
    //   6120: if_acmpne -> 6166
    //   6123: goto -> 6130
    //   6126: invokestatic a : (Ljava/lang/Throwable;)Ljava/lang/Throwable;
    //   6129: athrow
    //   6130: aload #6
    //   6132: iconst_1
    //   6133: invokevirtual setAccessible : (Z)V
    //   6136: aload #6
    //   6138: aconst_null
    //   6139: iconst_2
    //   6140: anewarray java/lang/Object
    //   6143: dup
    //   6144: iconst_0
    //   6145: aload_0
    //   6146: aastore
    //   6147: dup
    //   6148: iconst_1
    //   6149: aload_1
    //   6150: aastore
    //   6151: invokevirtual invoke : (Ljava/lang/Object;[Ljava/lang/Object;)Ljava/lang/Object;
    //   6154: pop
    //   6155: iload_2
    //   6156: ifne -> 6180
    //   6159: goto -> 6166
    //   6162: invokestatic a : (Ljava/lang/Throwable;)Ljava/lang/Throwable;
    //   6165: athrow
    //   6166: iinc #5, 1
    //   6169: iload_2
    //   6170: ifne -> 6065
    //   6173: goto -> 6180
    //   6176: invokestatic a : (Ljava/lang/Throwable;)Ljava/lang/Throwable;
    //   6179: athrow
    //   6180: getstatic burp/Zscf.Zu : Ljava/lang/String;
    //   6183: getstatic burp/Zmc_.Zj : Ljava/lang/Object;
    //   6186: checkcast java/math/BigInteger
    //   6189: invokevirtual intValue : ()I
    //   6192: bipush #32
    //   6194: irem
    //   6195: invokestatic abs : (I)I
    //   6198: invokevirtual charAt : (I)C
    //   6201: getstatic burp/Zzts.Zk : Ljava/lang/String;
    //   6204: getstatic burp/Zsp9.ZV : Ljava/lang/Object;
    //   6207: checkcast java/math/BigInteger
    //   6210: invokevirtual intValue : ()I
    //   6213: bipush #32
    //   6215: irem
    //   6216: invokestatic abs : (I)I
    //   6219: invokevirtual charAt : (I)C
    //   6222: if_icmpgt -> 6337
    //   6225: getstatic burp/Znu.ZF : Ljava/lang/String;
    //   6228: getstatic burp/Zs4g.ZC : Ljava/lang/Object;
    //   6231: checkcast java/math/BigInteger
    //   6234: invokevirtual intValue : ()I
    //   6237: bipush #32
    //   6239: irem
    //   6240: invokestatic abs : (I)I
    //   6243: invokevirtual charAt : (I)C
    //   6246: getstatic burp/Zkhf.Zb : Ljava/lang/String;
    //   6249: getstatic burp/Zenr.ZA : Ljava/lang/Object;
    //   6252: checkcast java/math/BigInteger
    //   6255: invokevirtual intValue : ()I
    //   6258: bipush #32
    //   6260: irem
    //   6261: invokestatic abs : (I)I
    //   6264: invokevirtual charAt : (I)C
    //   6267: if_icmple -> 6337
    //   6270: goto -> 6277
    //   6273: invokestatic a : (Ljava/lang/Throwable;)Ljava/lang/Throwable;
    //   6276: athrow
    //   6277: getstatic burp/Zk8i.ZS : Ljava/lang/String;
    //   6280: getstatic burp/Zt7x.ZE : Ljava/lang/Object;
    //   6283: checkcast java/math/BigInteger
    //   6286: invokevirtual intValue : ()I
    //   6289: bipush #32
    //   6291: irem
    //   6292: invokestatic abs : (I)I
    //   6295: invokevirtual charAt : (I)C
    //   6298: getstatic burp/Zkhf.Zb : Ljava/lang/String;
    //   6301: getstatic burp/Zxan.ZX : Ljava/lang/Object;
    //   6304: checkcast java/math/BigInteger
    //   6307: invokevirtual intValue : ()I
    //   6310: bipush #32
    //   6312: irem
    //   6313: invokestatic abs : (I)I
    //   6316: invokevirtual charAt : (I)C
    //   6319: if_icmple -> 6337
    //   6322: goto -> 6329
    //   6325: invokestatic a : (Ljava/lang/Throwable;)Ljava/lang/Throwable;
    //   6328: athrow
    //   6329: iconst_1
    //   6330: goto -> 6338
    //   6333: invokestatic a : (Ljava/lang/Throwable;)Ljava/lang/Throwable;
    //   6336: athrow
    //   6337: iconst_0
    //   6338: ireturn
    //   6339: astore_3
    //   6340: new java/lang/Exception
    //   6343: dup
    //   6344: aload_3
    //   6345: invokevirtual getMessage : ()Ljava/lang/String;
    //   6348: invokespecial <init> : (Ljava/lang/String;)V
    //   6351: athrow
    // Exception table:
    //   from	to	target	type
    //   4	6338	6339	java/lang/Throwable
    //   3552	3577	3577	java/lang/Throwable
    //   4540	4566	4566	java/lang/Throwable
    //   4794	4818	4821	java/lang/Throwable
    //   4892	4929	4929	java/lang/Throwable
    //   4933	4954	4954	java/lang/Throwable
    //   4958	4988	4988	java/lang/Throwable
    //   5228	5242	5242	java/lang/Throwable
    //   5253	5266	5269	java/lang/Throwable
    //   5258	5281	5284	java/lang/Throwable
    //   5273	5299	5302	java/lang/Throwable
    //   5288	5329	5332	java/lang/Throwable
    //   5392	5419	5422	java/lang/Throwable
    //   5409	5440	5443	java/lang/Throwable
    //   5426	5470	5473	java/lang/Throwable
    //   5447	5481	5481	java/lang/Throwable
    //   5492	5508	5511	java/lang/Throwable
    //   5585	5599	5599	java/lang/Throwable
    //   5610	5623	5626	java/lang/Throwable
    //   5615	5638	5641	java/lang/Throwable
    //   5630	5656	5659	java/lang/Throwable
    //   5645	5686	5689	java/lang/Throwable
    //   5749	5776	5779	java/lang/Throwable
    //   5766	5797	5800	java/lang/Throwable
    //   5783	5827	5830	java/lang/Throwable
    //   5804	5838	5838	java/lang/Throwable
    //   5849	5865	5868	java/lang/Throwable
    //   5914	5928	5928	java/lang/Throwable
    //   5939	5952	5955	java/lang/Throwable
    //   5944	5967	5970	java/lang/Throwable
    //   5959	5985	5988	java/lang/Throwable
    //   5974	6015	6018	java/lang/Throwable
    //   6078	6105	6108	java/lang/Throwable
    //   6095	6123	6126	java/lang/Throwable
    //   6112	6159	6162	java/lang/Throwable
    //   6130	6173	6176	java/lang/Throwable
    //   6180	6270	6273	java/lang/Throwable
    //   6225	6322	6325	java/lang/Throwable
    //   6277	6333	6333	java/lang/Throwable
  }
  
  static void Zj(Object paramObject) {
    Zlwm.Zj = a(-23119, 27596);
    Zlwm.Ze = new BigInteger(a(-23105, -31255));
    boolean bool = Zt2e.ZK();
    try {
      try {
        if (Zry1.Zk.charAt(Math.abs(((BigInteger)Zzmc.Zg).intValue() % 32)) <= Zrl5.ZG.charAt(Math.abs(((BigInteger)Zmui.Zz).intValue() % 32))) {
          try {
            Zmjr.ZM(Class.forName(a(-23109, 29666)));
            if (bool)
              Zgtx.ZO(Class.forName(a(-23114, 25053))); 
          } catch (Throwable throwable) {
            throw a(null);
          } 
          return;
        } 
      } catch (Throwable throwable) {
        throw a(null);
      } 
      Zgtx.ZO(Class.forName(a(-23114, 25053)));
    } catch (Throwable throwable) {}
  }
  
  static {
    // Byte code:
    //   0: bipush #16
    //   2: anewarray java/lang/String
    //   5: astore #5
    //   7: iconst_0
    //   8: istore_3
    //   9: ldc 'l\iM@!4s\\t"-p}[1`:m!s{?1\\rX# ]FXl*.D(?(|#s\\tFq#&\\tj\\bG8+ v <Y.?~OStx \\t#t^j'L\\t_3(\\t{cTmJ\\b@UM3J+~nuH_>v/bs_uMd83LQgX/WC\ci\\t.59\\tlcr2=vw8"=8~\\tl4'
    //   11: dup
    //   12: astore_2
    //   13: invokevirtual length : ()I
    //   16: istore #4
    //   18: bipush #19
    //   20: istore_1
    //   21: iconst_m1
    //   22: istore_0
    //   23: bipush #100
    //   25: iinc #0, 1
    //   28: aload_2
    //   29: iload_0
    //   30: dup
    //   31: iload_1
    //   32: iadd
    //   33: invokevirtual substring : (II)Ljava/lang/String;
    //   36: iconst_m1
    //   37: goto -> 143
    //   40: aload #5
    //   42: swap
    //   43: iload_3
    //   44: iinc #3, 1
    //   47: swap
    //   48: aastore
    //   49: iload_0
    //   50: iload_1
    //   51: iadd
    //   52: dup
    //   53: istore_0
    //   54: iload #4
    //   56: if_icmpge -> 68
    //   59: aload_2
    //   60: iload_0
    //   61: invokevirtual charAt : (I)C
    //   64: istore_1
    //   65: goto -> 23
    //   68: ldc '&Z]m8 sDV+O\\rd>nLI'
    //   70: dup
    //   71: astore_2
    //   72: invokevirtual length : ()I
    //   75: istore #4
    //   77: bipush #9
    //   79: istore_1
    //   80: iconst_m1
    //   81: istore_0
    //   82: bipush #34
    //   84: iinc #0, 1
    //   87: aload_2
    //   88: iload_0
    //   89: dup
    //   90: iload_1
    //   91: iadd
    //   92: invokevirtual substring : (II)Ljava/lang/String;
    //   95: iconst_0
    //   96: goto -> 143
    //   99: aload #5
    //   101: swap
    //   102: iload_3
    //   103: iinc #3, 1
    //   106: swap
    //   107: aastore
    //   108: iload_0
    //   109: iload_1
    //   110: iadd
    //   111: dup
    //   112: istore_0
    //   113: iload #4
    //   115: if_icmpge -> 127
    //   118: aload_2
    //   119: iload_0
    //   120: invokevirtual charAt : (I)C
    //   123: istore_1
    //   124: goto -> 82
    //   127: aload #5
    //   129: putstatic burp/Zeva.a : [Ljava/lang/String;
    //   132: bipush #16
    //   134: anewarray java/lang/String
    //   137: putstatic burp/Zeva.b : [Ljava/lang/String;
    //   140: goto -> 300
    //   143: dup_x2
    //   144: pop
    //   145: invokevirtual toCharArray : ()[C
    //   148: dup_x1
    //   149: arraylength
    //   150: dup_x2
    //   151: pop
    //   152: iconst_0
    //   153: istore #6
    //   155: dup2_x1
    //   156: pop2
    //   157: dup_x2
    //   158: iconst_1
    //   159: if_icmpgt -> 259
    //   162: dup2
    //   163: swap
    //   164: iload #6
    //   166: dup2_x1
    //   167: caload
    //   168: swap
    //   169: iload #6
    //   171: bipush #7
    //   173: irem
    //   174: tableswitch default -> 241, 0 -> 212, 1 -> 217, 2 -> 222, 3 -> 227, 4 -> 232, 5 -> 237
    //   212: bipush #116
    //   214: goto -> 243
    //   217: bipush #7
    //   219: goto -> 243
    //   222: bipush #42
    //   224: goto -> 243
    //   227: bipush #44
    //   229: goto -> 243
    //   232: bipush #111
    //   234: goto -> 243
    //   237: iconst_1
    //   238: goto -> 243
    //   241: bipush #110
    //   243: ixor
    //   244: ixor
    //   245: i2c
    //   246: castore
    //   247: iinc #6, 1
    //   250: dup
    //   251: ifne -> 259
    //   254: dup2
    //   255: dup_x1
    //   256: goto -> 166
    //   259: dup2_x1
    //   260: pop2
    //   261: dup_x2
    //   262: iload #6
    //   264: if_icmpgt -> 162
    //   267: pop
    //   268: new java/lang/String
    //   271: dup_x1
    //   272: swap
    //   273: invokespecial <init> : ([C)V
    //   276: invokevirtual intern : ()Ljava/lang/String;
    //   279: swap
    //   280: pop
    //   281: swap
    //   282: tableswitch default -> 40, 0 -> 99
    //   300: sipush #-23107
    //   303: sipush #14029
    //   306: invokestatic a : (II)Ljava/lang/String;
    //   309: putstatic burp/Zeva.Zo : Ljava/lang/String;
    //   312: new java/math/BigInteger
    //   315: dup
    //   316: sipush #-23116
    //   319: sipush #-6224
    //   322: invokestatic a : (II)Ljava/lang/String;
    //   325: invokespecial <init> : (Ljava/lang/String;)V
    //   328: putstatic burp/Zeva.Zf : Ljava/lang/Object;
    //   331: return
  }
  
  private static Throwable a(Throwable paramThrowable) {
    return paramThrowable;
  }
  
  private static String a(int paramInt1, int paramInt2) {
    int i = (paramInt1 ^ 0xFFFFA5BE) & 0xFFFF;
    if (b[i] == null) {
      char[] arrayOfChar = a[i].toCharArray();
      switch (arrayOfChar[0] & 0xFF) {
        case 0:
        
        case 1:
        
        case 2:
        
        case 3:
        
        case 4:
        
        case 5:
        
        case 6:
        
        case 7:
        
        case 8:
        
        case 9:
        
        case 10:
        
        case 11:
        
        case 12:
        
        case 13:
        
        case 14:
        
        case 15:
        
        case 16:
        
        case 17:
        
        case 18:
        
        case 19:
        
        case 20:
        
        case 21:
        
        case 22:
        
        case 23:
        
        case 24:
        
        case 25:
        
        case 26:
        
        case 27:
        
        case 28:
        
        case 29:
        
        case 30:
        
        case 31:
        
        case 32:
        
        case 33:
        
        case 34:
        
        case 35:
        
        case 36:
        
        case 37:
        
        case 38:
        
        case 39:
        
        case 40:
        
        case 41:
        
        case 42:
        
        case 43:
        
        case 44:
        
        case 45:
        
        case 46:
        
        case 47:
        
        case 48:
        
        case 49:
        
        case 50:
        
        case 51:
        
        case 52:
        
        case 53:
        
        case 54:
        
        case 55:
        
        case 56:
        
        case 57:
        
        case 58:
        
        case 59:
        
        case 60:
        
        case 61:
        
        case 62:
        
        case 63:
        
        case 64:
        
        case 65:
        
        case 66:
        
        case 67:
        
        case 68:
        
        case 69:
        
        case 70:
        
        case 71:
        
        case 72:
        
        case 73:
        
        case 74:
        
        case 75:
        
        case 76:
        
        case 77:
        
        case 78:
        
        case 79:
        
        case 80:
        
        case 81:
        
        case 82:
        
        case 83:
        
        case 84:
        
        case 85:
        
        case 86:
        
        case 87:
        
        case 88:
        
        case 89:
        
        case 90:
        
        case 91:
        
        case 92:
        
        case 93:
        
        case 94:
        
        case 95:
        
        case 96:
        
        case 97:
        
        case 98:
        
        case 99:
        
        case 100:
        
        case 101:
        
        case 102:
        
        case 103:
        
        case 104:
        
        case 105:
        
        case 106:
        
        case 107:
        
        case 108:
        
        case 109:
        
        case 110:
        
        case 111:
        
        case 112:
        
        case 113:
        
        case 114:
        
        case 115:
        
        case 116:
        
        case 117:
        
        case 118:
        
        case 119:
        
        case 120:
        
        case 121:
        
        case 122:
        
        case 123:
        
        case 124:
        
        case 125:
        
        case 126:
        
        case 127:
        
        case 128:
        
        case 129:
        
        case 130:
        
        case 131:
        
        case 132:
        
        case 133:
        
        case 134:
        
        case 135:
        
        case 136:
        
        case 137:
        
        case 138:
        
        case 139:
        
        case 140:
        
        case 141:
        
        case 142:
        
        case 143:
        
        case 144:
        
        case 145:
        
        case 146:
        
        case 147:
        
        case 148:
        
        case 149:
        
        case 150:
        
        case 151:
        
        case 152:
        
        case 153:
        
        case 154:
        
        case 155:
        
        case 156:
        
        case 157:
        
        case 158:
        
        case 159:
        
        case 160:
        
        case 161:
        
        case 162:
        
        case 163:
        
        case 164:
        
        case 165:
        
        case 166:
        
        case 167:
        
        case 168:
        
        case 169:
        
        case 170:
        
        case 171:
        
        case 172:
        
        case 173:
        
        case 174:
        
        case 175:
        
        case 176:
        
        case 177:
        
        case 178:
        
        case 179:
        
        case 180:
        
        case 181:
        
        case 182:
        
        case 183:
        
        case 184:
        
        case 185:
        
        case 186:
        
        case 187:
        
        case 188:
        
        case 189:
        
        case 190:
        
        case 191:
        
        case 192:
        
        case 193:
        
        case 194:
        
        case 195:
        
        case 196:
        
        case 197:
        
        case 198:
        
        case 199:
        
        case 200:
        
        case 201:
        
        case 202:
        
        case 203:
        
        case 204:
        
        case 205:
        
        case 206:
        
        case 207:
        
        case 208:
        
        case 209:
        
        case 210:
        
        case 211:
        
        case 212:
        
        case 213:
        
        case 214:
        
        case 215:
        
        case 216:
        
        case 217:
        
        case 218:
        
        case 219:
        
        case 220:
        
        case 221:
        
        case 222:
        
        case 223:
        
        case 224:
        
        case 225:
        
        case 226:
        
        case 227:
        
        case 228:
        
        case 229:
        
        case 230:
        
        case 231:
        
        case 232:
        
        case 233:
        
        case 234:
        
        case 235:
        
        case 236:
        
        case 237:
        
        case 238:
        
        case 239:
        
        case 240:
        
        case 241:
        
        case 242:
        
        case 243:
        
        case 244:
        
        case 245:
        
        case 246:
        
        case 247:
        
        case 248:
        
        case 249:
        
        case 250:
        
        case 251:
        
        case 252:
        
        case 253:
        
        case 254:
        
        default:
          break;
      } 
      byte b1 = 117;
      int j = (paramInt2 & 0xFF) - b1;
      if (j < 0)
        j += 256; 
      int k = ((paramInt2 & 0xFFFF) >>> 8) - b1;
      if (k < 0)
        k += 256; 
      for (byte b2 = 0; b2 < arrayOfChar.length; b2++) {
        int m = b2 % 2;
        if (m == 0) {
          arrayOfChar[b2] = (char)(arrayOfChar[b2] ^ j);
          j = ((j >>> 3 | j << 5) ^ arrayOfChar[b2]) & 0xFF;
        } else {
          arrayOfChar[b2] = (char)(arrayOfChar[b2] ^ k);
          k = ((k >>> 3 | k << 5) ^ arrayOfChar[b2]) & 0xFF;
        } 
      } 
      b[i] = (new String(arrayOfChar)).intern();
    } 
    return b[i];
  }
}


/* Location:              C:\Program Files\BurpSuitePro\burpsuite_pro.jar!\burp\Zeva.class
 * Java compiler version: 21 (65.0)
 * JD-Core Version:       1.1.3
 */