package burp;

public class Zew8 implements Zree {
  private final String Zs;
  
  private final String Zw;
  
  private final String ZN;
  
  private final Zrdb Zq;
  
  public Zew8(Zrdb paramZrdb) {
    // Byte code:
    //   0: aload_0
    //   1: invokespecial <init> : ()V
    //   4: invokestatic Za : ()Z
    //   7: aload_0
    //   8: aload_1
    //   9: putfield Zq : Lburp/Zrdb;
    //   12: istore_2
    //   13: aload_1
    //   14: instanceof burp/Zg72
    //   17: ifeq -> 59
    //   20: aload_1
    //   21: checkcast burp/Zg72
    //   24: astore_3
    //   25: aload_0
    //   26: aload_3
    //   27: invokeinterface ZZV : ()Ljava/lang/String;
    //   32: putfield Zs : Ljava/lang/String;
    //   35: aload_0
    //   36: aload_3
    //   37: invokeinterface ZZA : ()Ljava/lang/String;
    //   42: putfield Zw : Ljava/lang/String;
    //   45: aload_0
    //   46: aload_3
    //   47: invokeinterface ZZH : ()Ljava/lang/String;
    //   52: putfield ZN : Ljava/lang/String;
    //   55: iload_2
    //   56: ifeq -> 142
    //   59: aload_0
    //   60: aload_1
    //   61: invokeinterface ZaT : ()Lburp/Ztlj;
    //   66: getstatic burp/Ztz3.ISSUE_NAME : Lburp/Ztz3;
    //   69: invokevirtual ZJ : (Lburp/Ztz3;)Ljava/lang/String;
    //   72: invokestatic ZZ : (Ljava/lang/String;)Ljava/lang/String;
    //   75: putfield Zs : Ljava/lang/String;
    //   78: aload_0
    //   79: aload_1
    //   80: invokeinterface Za6 : ()Lburp/Zvs;
    //   85: getstatic burp/Zzu2.EXTENSION_GENERATED : Lburp/Zzu2;
    //   88: if_acmpne -> 106
    //   91: aload_1
    //   92: invokeinterface ZaT : ()Lburp/Ztlj;
    //   97: getstatic burp/Ztz3.ISSUE_DESCRIPTION : Lburp/Ztz3;
    //   100: invokevirtual ZJ : (Lburp/Ztz3;)Ljava/lang/String;
    //   103: goto -> 107
    //   106: aconst_null
    //   107: putfield Zw : Ljava/lang/String;
    //   110: aload_0
    //   111: aload_1
    //   112: invokeinterface Za6 : ()Lburp/Zvs;
    //   117: getstatic burp/Zzu2.EXTENSION_GENERATED : Lburp/Zzu2;
    //   120: if_acmpne -> 138
    //   123: aload_1
    //   124: invokeinterface ZaT : ()Lburp/Ztlj;
    //   129: getstatic burp/Ztz3.ISSUE_REMEDIATION : Lburp/Ztz3;
    //   132: invokevirtual ZJ : (Lburp/Ztz3;)Ljava/lang/String;
    //   135: goto -> 139
    //   138: aconst_null
    //   139: putfield ZN : Ljava/lang/String;
    //   142: invokestatic Zwu : ()[Lburp/Zbqc;
    //   145: ifnonnull -> 160
    //   148: iload_2
    //   149: ifeq -> 156
    //   152: iconst_0
    //   153: goto -> 157
    //   156: iconst_1
    //   157: invokestatic ZY : (Z)V
    //   160: return
  }
  
  public Zvs Za6() {
    return this.Zq.Za6();
  }
  
  public byte ZZ3() {
    return 1;
  }
  
  public String ZZV() {
    return Zmey.Z_(this.Zs);
  }
  
  public String ZZA() {
    return Zmey.Z_(this.Zw);
  }
  
  public String ZZH() {
    return Zmey.Z_(this.ZN);
  }
  
  public String ZZK() {
    return null;
  }
  
  public String ZZF() {
    return null;
  }
}


/* Location:              C:\Program Files\BurpSuitePro\burpsuite_pro.jar!\burp\Zew8.class
 * Java compiler version: 21 (65.0)
 * JD-Core Version:       1.1.3
 */