package burp;

import java.math.BigInteger;

class Zewo extends ClassLoader {
  static String ZM;
  
  static Object ZZ;
  
  private static final String[] a;
  
  private static final String[] b;
  
  static void Zc(Object[] paramArrayOfObject, Object paramObject) throws Throwable {}
  
  static void ZT(Object paramObject) {
    Zs33.ZX = a(-13684, -3086);
    Zs33.ZT = new BigInteger(a(-13687, 6200));
    boolean bool = Zt2e.ZN();
    try {
      try {
        if (Zkvr.Zm.charAt(Math.abs(((BigInteger)Zkvr.Zb).intValue() % 32)) <= Zgdt.Zd.charAt(Math.abs(((BigInteger)Zs36.Zs).intValue() % 32))) {
          try {
            Zl_9.Zi(Class.forName(a(-13681, -28234)));
            if (!bool)
              Zsot.Ze(Class.forName(a(-13686, 29624))); 
          } catch (Throwable throwable) {
            throw a(null);
          } 
          return;
        } 
      } catch (Throwable throwable) {
        throw a(null);
      } 
      Zsot.Ze(Class.forName(a(-13686, 29624)));
    } catch (Throwable throwable) {}
  }
  
  static boolean ZK(Object[] paramArrayOfObject, Object paramObject) throws Throwable {
    // Byte code:
    //   0: invokestatic ZN : ()Z
    //   3: istore_2
    //   4: getstatic burp/Zlc5.ZH : Ljava/lang/Object;
    //   7: checkcast java/math/BigInteger
    //   10: getstatic burp/Zeyt.ZR : Ljava/lang/Object;
    //   13: checkcast java/math/BigInteger
    //   16: invokevirtual add : (Ljava/math/BigInteger;)Ljava/math/BigInteger;
    //   19: putstatic burp/Zkul.Zb : Ljava/lang/Object;
    //   22: new java/io/ByteArrayOutputStream
    //   25: dup
    //   26: invokespecial <init> : ()V
    //   29: astore_3
    //   30: getstatic burp/Zl_9.ZP : Ljava/lang/String;
    //   33: astore #4
    //   35: iconst_0
    //   36: istore #5
    //   38: iload #5
    //   40: aload #4
    //   42: invokevirtual length : ()I
    //   45: if_icmpge -> 75
    //   48: aload_3
    //   49: aload #4
    //   51: iload #5
    //   53: iload #5
    //   55: iconst_2
    //   56: iadd
    //   57: invokevirtual substring : (II)Ljava/lang/String;
    //   60: bipush #16
    //   62: invokestatic parseInt : (Ljava/lang/String;I)I
    //   65: invokevirtual write : (I)V
    //   68: iinc #5, 2
    //   71: iload_2
    //   72: ifne -> 38
    //   75: aload_3
    //   76: invokevirtual toByteArray : ()[B
    //   79: astore #5
    //   81: getstatic burp/Zsgj.ZK : Ljava/lang/Object;
    //   84: checkcast java/math/BigInteger
    //   87: invokevirtual toByteArray : ()[B
    //   90: astore #6
    //   92: sipush #256
    //   95: newarray byte
    //   97: astore #8
    //   99: sipush #256
    //   102: newarray int
    //   104: astore #9
    //   106: sipush #256
    //   109: newarray int
    //   111: astore #10
    //   113: sipush #256
    //   116: newarray int
    //   118: astore #11
    //   120: sipush #256
    //   123: newarray int
    //   125: astore #12
    //   127: bipush #10
    //   129: newarray int
    //   131: astore #13
    //   133: sipush #283
    //   136: istore #14
    //   138: iconst_0
    //   139: istore #16
    //   141: iload #16
    //   143: sipush #256
    //   146: if_icmpge -> 380
    //   149: sipush #-13683
    //   152: sipush #-24075
    //   155: invokestatic a : (II)Ljava/lang/String;
    //   158: iload #16
    //   160: iconst_1
    //   161: iushr
    //   162: invokevirtual charAt : (I)C
    //   165: istore #25
    //   167: iload #16
    //   169: iconst_1
    //   170: iand
    //   171: ifne -> 186
    //   174: iload #25
    //   176: bipush #8
    //   178: iushr
    //   179: goto -> 188
    //   182: invokestatic a : (Ljava/lang/Throwable;)Ljava/lang/Throwable;
    //   185: athrow
    //   186: iload #25
    //   188: i2b
    //   189: sipush #255
    //   192: iand
    //   193: istore #15
    //   195: iload #16
    //   197: iconst_1
    //   198: ishl
    //   199: istore #17
    //   201: iload #17
    //   203: sipush #256
    //   206: if_icmplt -> 216
    //   209: iload #17
    //   211: iload #14
    //   213: ixor
    //   214: istore #17
    //   216: iload #17
    //   218: iconst_1
    //   219: ishl
    //   220: istore #18
    //   222: iload #18
    //   224: sipush #256
    //   227: if_icmplt -> 237
    //   230: iload #18
    //   232: iload #14
    //   234: ixor
    //   235: istore #18
    //   237: iload #18
    //   239: iconst_1
    //   240: ishl
    //   241: istore #19
    //   243: iload #19
    //   245: sipush #256
    //   248: if_icmplt -> 258
    //   251: iload #19
    //   253: iload #14
    //   255: ixor
    //   256: istore #19
    //   258: iload #19
    //   260: iload #16
    //   262: ixor
    //   263: istore #20
    //   265: iload #20
    //   267: iload #17
    //   269: ixor
    //   270: istore #21
    //   272: iload #20
    //   274: iload #18
    //   276: ixor
    //   277: istore #22
    //   279: iload #19
    //   281: iload #18
    //   283: ixor
    //   284: iload #17
    //   286: ixor
    //   287: istore #23
    //   289: aload #8
    //   291: iload #16
    //   293: iload #15
    //   295: i2b
    //   296: bastore
    //   297: aload #9
    //   299: iload #15
    //   301: iload #23
    //   303: bipush #24
    //   305: ishl
    //   306: iload #20
    //   308: bipush #16
    //   310: ishl
    //   311: ior
    //   312: iload #22
    //   314: bipush #8
    //   316: ishl
    //   317: ior
    //   318: iload #21
    //   320: ior
    //   321: dup
    //   322: istore #24
    //   324: iastore
    //   325: aload #10
    //   327: iload #15
    //   329: iload #24
    //   331: bipush #8
    //   333: iushr
    //   334: iload #24
    //   336: bipush #24
    //   338: ishl
    //   339: ior
    //   340: iastore
    //   341: aload #11
    //   343: iload #15
    //   345: iload #24
    //   347: bipush #16
    //   349: iushr
    //   350: iload #24
    //   352: bipush #16
    //   354: ishl
    //   355: ior
    //   356: iastore
    //   357: aload #12
    //   359: iload #15
    //   361: iload #24
    //   363: bipush #24
    //   365: iushr
    //   366: iload #24
    //   368: bipush #8
    //   370: ishl
    //   371: ior
    //   372: iastore
    //   373: iinc #16, 1
    //   376: iload_2
    //   377: ifne -> 141
    //   380: iconst_1
    //   381: istore #25
    //   383: aload #13
    //   385: iconst_0
    //   386: iload #25
    //   388: bipush #24
    //   390: ishl
    //   391: iastore
    //   392: iconst_1
    //   393: istore #26
    //   395: iload #26
    //   397: bipush #10
    //   399: if_icmpge -> 440
    //   402: iload #25
    //   404: iconst_1
    //   405: ishl
    //   406: istore #25
    //   408: iload #25
    //   410: sipush #256
    //   413: if_icmplt -> 423
    //   416: iload #25
    //   418: iload #14
    //   420: ixor
    //   421: istore #25
    //   423: aload #13
    //   425: iload #26
    //   427: iload #25
    //   429: bipush #24
    //   431: ishl
    //   432: iastore
    //   433: iinc #26, 1
    //   436: iload_2
    //   437: ifne -> 395
    //   440: iconst_4
    //   441: istore #26
    //   443: iload #26
    //   445: bipush #6
    //   447: iadd
    //   448: istore #27
    //   450: iconst_4
    //   451: iload #27
    //   453: iconst_1
    //   454: iadd
    //   455: imul
    //   456: istore #28
    //   458: iload #28
    //   460: newarray int
    //   462: astore #29
    //   464: iload #28
    //   466: newarray int
    //   468: astore #30
    //   470: iconst_0
    //   471: istore #25
    //   473: iconst_0
    //   474: istore #32
    //   476: iconst_0
    //   477: istore #33
    //   479: iload #32
    //   481: iload #26
    //   483: if_icmpge -> 551
    //   486: aload #29
    //   488: iload #32
    //   490: aload #5
    //   492: iload #33
    //   494: baload
    //   495: bipush #24
    //   497: ishl
    //   498: aload #5
    //   500: iload #33
    //   502: iconst_1
    //   503: iadd
    //   504: baload
    //   505: sipush #255
    //   508: iand
    //   509: bipush #16
    //   511: ishl
    //   512: ior
    //   513: aload #5
    //   515: iload #33
    //   517: iconst_2
    //   518: iadd
    //   519: baload
    //   520: sipush #255
    //   523: iand
    //   524: bipush #8
    //   526: ishl
    //   527: ior
    //   528: aload #5
    //   530: iload #33
    //   532: iconst_3
    //   533: iadd
    //   534: baload
    //   535: sipush #255
    //   538: iand
    //   539: ior
    //   540: iastore
    //   541: iinc #32, 1
    //   544: iinc #33, 4
    //   547: iload_2
    //   548: ifne -> 479
    //   551: iload #26
    //   553: istore #32
    //   555: iconst_0
    //   556: istore #33
    //   558: iload #32
    //   560: iload #28
    //   562: if_icmpge -> 689
    //   565: aload #29
    //   567: iload #32
    //   569: iconst_1
    //   570: isub
    //   571: iaload
    //   572: istore #31
    //   574: iload #33
    //   576: ifne -> 663
    //   579: iload #26
    //   581: istore #33
    //   583: aload #8
    //   585: iload #31
    //   587: bipush #16
    //   589: iushr
    //   590: sipush #255
    //   593: iand
    //   594: baload
    //   595: bipush #24
    //   597: ishl
    //   598: aload #8
    //   600: iload #31
    //   602: bipush #8
    //   604: iushr
    //   605: sipush #255
    //   608: iand
    //   609: baload
    //   610: sipush #255
    //   613: iand
    //   614: bipush #16
    //   616: ishl
    //   617: ior
    //   618: aload #8
    //   620: iload #31
    //   622: sipush #255
    //   625: iand
    //   626: baload
    //   627: sipush #255
    //   630: iand
    //   631: bipush #8
    //   633: ishl
    //   634: ior
    //   635: aload #8
    //   637: iload #31
    //   639: bipush #24
    //   641: iushr
    //   642: baload
    //   643: sipush #255
    //   646: iand
    //   647: ior
    //   648: istore #31
    //   650: iload #31
    //   652: aload #13
    //   654: iload #25
    //   656: iinc #25, 1
    //   659: iaload
    //   660: ixor
    //   661: istore #31
    //   663: aload #29
    //   665: iload #32
    //   667: aload #29
    //   669: iload #32
    //   671: iload #26
    //   673: isub
    //   674: iaload
    //   675: iload #31
    //   677: ixor
    //   678: iastore
    //   679: iinc #32, 1
    //   682: iinc #33, -1
    //   685: iload_2
    //   686: ifne -> 558
    //   689: iconst_0
    //   690: istore #32
    //   692: iconst_4
    //   693: iload #27
    //   695: imul
    //   696: istore #33
    //   698: aload #30
    //   700: iload #32
    //   702: aload #29
    //   704: iload #33
    //   706: iaload
    //   707: iastore
    //   708: aload #30
    //   710: iload #32
    //   712: iconst_1
    //   713: iadd
    //   714: aload #29
    //   716: iload #33
    //   718: iconst_1
    //   719: iadd
    //   720: iaload
    //   721: iastore
    //   722: aload #30
    //   724: iload #32
    //   726: iconst_2
    //   727: iadd
    //   728: aload #29
    //   730: iload #33
    //   732: iconst_2
    //   733: iadd
    //   734: iaload
    //   735: iastore
    //   736: aload #30
    //   738: iload #32
    //   740: iconst_3
    //   741: iadd
    //   742: aload #29
    //   744: iload #33
    //   746: iconst_3
    //   747: iadd
    //   748: iaload
    //   749: iastore
    //   750: iinc #32, 4
    //   753: iinc #33, -4
    //   756: iconst_1
    //   757: istore #35
    //   759: iload #35
    //   761: iload #27
    //   763: if_icmpge -> 1127
    //   766: aload #29
    //   768: iload #33
    //   770: iaload
    //   771: istore #34
    //   773: aload #30
    //   775: iload #32
    //   777: aload #9
    //   779: aload #8
    //   781: iload #34
    //   783: bipush #24
    //   785: iushr
    //   786: baload
    //   787: sipush #255
    //   790: iand
    //   791: iaload
    //   792: aload #10
    //   794: aload #8
    //   796: iload #34
    //   798: bipush #16
    //   800: iushr
    //   801: sipush #255
    //   804: iand
    //   805: baload
    //   806: sipush #255
    //   809: iand
    //   810: iaload
    //   811: ixor
    //   812: aload #11
    //   814: aload #8
    //   816: iload #34
    //   818: bipush #8
    //   820: iushr
    //   821: sipush #255
    //   824: iand
    //   825: baload
    //   826: sipush #255
    //   829: iand
    //   830: iaload
    //   831: ixor
    //   832: aload #12
    //   834: aload #8
    //   836: iload #34
    //   838: sipush #255
    //   841: iand
    //   842: baload
    //   843: sipush #255
    //   846: iand
    //   847: iaload
    //   848: ixor
    //   849: iastore
    //   850: aload #29
    //   852: iload #33
    //   854: iconst_1
    //   855: iadd
    //   856: iaload
    //   857: istore #34
    //   859: aload #30
    //   861: iload #32
    //   863: iconst_1
    //   864: iadd
    //   865: aload #9
    //   867: aload #8
    //   869: iload #34
    //   871: bipush #24
    //   873: iushr
    //   874: baload
    //   875: sipush #255
    //   878: iand
    //   879: iaload
    //   880: aload #10
    //   882: aload #8
    //   884: iload #34
    //   886: bipush #16
    //   888: iushr
    //   889: sipush #255
    //   892: iand
    //   893: baload
    //   894: sipush #255
    //   897: iand
    //   898: iaload
    //   899: ixor
    //   900: aload #11
    //   902: aload #8
    //   904: iload #34
    //   906: bipush #8
    //   908: iushr
    //   909: sipush #255
    //   912: iand
    //   913: baload
    //   914: sipush #255
    //   917: iand
    //   918: iaload
    //   919: ixor
    //   920: aload #12
    //   922: aload #8
    //   924: iload #34
    //   926: sipush #255
    //   929: iand
    //   930: baload
    //   931: sipush #255
    //   934: iand
    //   935: iaload
    //   936: ixor
    //   937: iastore
    //   938: aload #29
    //   940: iload #33
    //   942: iconst_2
    //   943: iadd
    //   944: iaload
    //   945: istore #34
    //   947: aload #30
    //   949: iload #32
    //   951: iconst_2
    //   952: iadd
    //   953: aload #9
    //   955: aload #8
    //   957: iload #34
    //   959: bipush #24
    //   961: iushr
    //   962: baload
    //   963: sipush #255
    //   966: iand
    //   967: iaload
    //   968: aload #10
    //   970: aload #8
    //   972: iload #34
    //   974: bipush #16
    //   976: iushr
    //   977: sipush #255
    //   980: iand
    //   981: baload
    //   982: sipush #255
    //   985: iand
    //   986: iaload
    //   987: ixor
    //   988: aload #11
    //   990: aload #8
    //   992: iload #34
    //   994: bipush #8
    //   996: iushr
    //   997: sipush #255
    //   1000: iand
    //   1001: baload
    //   1002: sipush #255
    //   1005: iand
    //   1006: iaload
    //   1007: ixor
    //   1008: aload #12
    //   1010: aload #8
    //   1012: iload #34
    //   1014: sipush #255
    //   1017: iand
    //   1018: baload
    //   1019: sipush #255
    //   1022: iand
    //   1023: iaload
    //   1024: ixor
    //   1025: iastore
    //   1026: aload #29
    //   1028: iload #33
    //   1030: iconst_3
    //   1031: iadd
    //   1032: iaload
    //   1033: istore #34
    //   1035: aload #30
    //   1037: iload #32
    //   1039: iconst_3
    //   1040: iadd
    //   1041: aload #9
    //   1043: aload #8
    //   1045: iload #34
    //   1047: bipush #24
    //   1049: iushr
    //   1050: baload
    //   1051: sipush #255
    //   1054: iand
    //   1055: iaload
    //   1056: aload #10
    //   1058: aload #8
    //   1060: iload #34
    //   1062: bipush #16
    //   1064: iushr
    //   1065: sipush #255
    //   1068: iand
    //   1069: baload
    //   1070: sipush #255
    //   1073: iand
    //   1074: iaload
    //   1075: ixor
    //   1076: aload #11
    //   1078: aload #8
    //   1080: iload #34
    //   1082: bipush #8
    //   1084: iushr
    //   1085: sipush #255
    //   1088: iand
    //   1089: baload
    //   1090: sipush #255
    //   1093: iand
    //   1094: iaload
    //   1095: ixor
    //   1096: aload #12
    //   1098: aload #8
    //   1100: iload #34
    //   1102: sipush #255
    //   1105: iand
    //   1106: baload
    //   1107: sipush #255
    //   1110: iand
    //   1111: iaload
    //   1112: ixor
    //   1113: iastore
    //   1114: iinc #32, 4
    //   1117: iinc #33, -4
    //   1120: iinc #35, 1
    //   1123: iload_2
    //   1124: ifne -> 759
    //   1127: aload #30
    //   1129: iload #32
    //   1131: aload #29
    //   1133: iload #33
    //   1135: iaload
    //   1136: iastore
    //   1137: aload #30
    //   1139: iload #32
    //   1141: iconst_1
    //   1142: iadd
    //   1143: aload #29
    //   1145: iload #33
    //   1147: iconst_1
    //   1148: iadd
    //   1149: iaload
    //   1150: iastore
    //   1151: aload #30
    //   1153: iload #32
    //   1155: iconst_2
    //   1156: iadd
    //   1157: aload #29
    //   1159: iload #33
    //   1161: iconst_2
    //   1162: iadd
    //   1163: iaload
    //   1164: iastore
    //   1165: aload #30
    //   1167: iload #32
    //   1169: iconst_3
    //   1170: iadd
    //   1171: aload #29
    //   1173: iload #33
    //   1175: iconst_3
    //   1176: iadd
    //   1177: iaload
    //   1178: iastore
    //   1179: iconst_0
    //   1180: newarray byte
    //   1182: astore #35
    //   1184: aload #6
    //   1186: arraylength
    //   1187: bipush #16
    //   1189: irem
    //   1190: ifeq -> 1214
    //   1193: new java/lang/Exception
    //   1196: dup
    //   1197: sipush #-13693
    //   1200: sipush #14009
    //   1203: invokestatic a : (II)Ljava/lang/String;
    //   1206: invokespecial <init> : (Ljava/lang/String;)V
    //   1209: athrow
    //   1210: invokestatic a : (Ljava/lang/Throwable;)Ljava/lang/Throwable;
    //   1213: athrow
    //   1214: bipush #10
    //   1216: istore #36
    //   1218: sipush #-13695
    //   1221: sipush #256
    //   1224: newarray byte
    //   1226: astore #37
    //   1228: sipush #-13007
    //   1231: sipush #256
    //   1234: newarray int
    //   1236: astore #38
    //   1238: sipush #256
    //   1241: newarray int
    //   1243: astore #39
    //   1245: sipush #256
    //   1248: newarray int
    //   1250: astore #40
    //   1252: sipush #256
    //   1255: newarray int
    //   1257: astore #41
    //   1259: sipush #283
    //   1262: istore #14
    //   1264: invokestatic a : (II)Ljava/lang/String;
    //   1267: astore #42
    //   1269: iconst_0
    //   1270: istore #16
    //   1272: iload #16
    //   1274: sipush #256
    //   1277: if_icmpge -> 1504
    //   1280: aload #42
    //   1282: iload #16
    //   1284: iconst_1
    //   1285: iushr
    //   1286: invokevirtual charAt : (I)C
    //   1289: istore #43
    //   1291: iload #16
    //   1293: iconst_1
    //   1294: iand
    //   1295: ifne -> 1310
    //   1298: iload #43
    //   1300: bipush #8
    //   1302: iushr
    //   1303: goto -> 1312
    //   1306: invokestatic a : (Ljava/lang/Throwable;)Ljava/lang/Throwable;
    //   1309: athrow
    //   1310: iload #43
    //   1312: i2b
    //   1313: sipush #255
    //   1316: iand
    //   1317: istore #15
    //   1319: iload #16
    //   1321: iconst_1
    //   1322: ishl
    //   1323: istore #17
    //   1325: iload #17
    //   1327: sipush #256
    //   1330: if_icmplt -> 1340
    //   1333: iload #17
    //   1335: iload #14
    //   1337: ixor
    //   1338: istore #17
    //   1340: iload #17
    //   1342: iconst_1
    //   1343: ishl
    //   1344: istore #18
    //   1346: iload #18
    //   1348: sipush #256
    //   1351: if_icmplt -> 1361
    //   1354: iload #18
    //   1356: iload #14
    //   1358: ixor
    //   1359: istore #18
    //   1361: iload #18
    //   1363: iconst_1
    //   1364: ishl
    //   1365: istore #19
    //   1367: iload #19
    //   1369: sipush #256
    //   1372: if_icmplt -> 1382
    //   1375: iload #19
    //   1377: iload #14
    //   1379: ixor
    //   1380: istore #19
    //   1382: iload #19
    //   1384: iload #16
    //   1386: ixor
    //   1387: istore #20
    //   1389: iload #20
    //   1391: iload #17
    //   1393: ixor
    //   1394: istore #21
    //   1396: iload #20
    //   1398: iload #18
    //   1400: ixor
    //   1401: istore #22
    //   1403: iload #19
    //   1405: iload #18
    //   1407: ixor
    //   1408: iload #17
    //   1410: ixor
    //   1411: istore #23
    //   1413: aload #37
    //   1415: iload #15
    //   1417: iload #16
    //   1419: i2b
    //   1420: bastore
    //   1421: aload #38
    //   1423: iload #15
    //   1425: iload #23
    //   1427: bipush #24
    //   1429: ishl
    //   1430: iload #20
    //   1432: bipush #16
    //   1434: ishl
    //   1435: ior
    //   1436: iload #22
    //   1438: bipush #8
    //   1440: ishl
    //   1441: ior
    //   1442: iload #21
    //   1444: ior
    //   1445: dup
    //   1446: istore #24
    //   1448: iastore
    //   1449: aload #39
    //   1451: iload #15
    //   1453: iload #24
    //   1455: bipush #8
    //   1457: iushr
    //   1458: iload #24
    //   1460: bipush #24
    //   1462: ishl
    //   1463: ior
    //   1464: iastore
    //   1465: aload #40
    //   1467: iload #15
    //   1469: iload #24
    //   1471: bipush #16
    //   1473: iushr
    //   1474: iload #24
    //   1476: bipush #16
    //   1478: ishl
    //   1479: ior
    //   1480: iastore
    //   1481: aload #41
    //   1483: iload #15
    //   1485: iload #24
    //   1487: bipush #24
    //   1489: iushr
    //   1490: iload #24
    //   1492: bipush #8
    //   1494: ishl
    //   1495: ior
    //   1496: iastore
    //   1497: iinc #16, 1
    //   1500: iload_2
    //   1501: ifne -> 1272
    //   1504: aload #6
    //   1506: arraylength
    //   1507: newarray byte
    //   1509: astore #43
    //   1511: iconst_0
    //   1512: istore #44
    //   1514: iload #44
    //   1516: aload #6
    //   1518: arraylength
    //   1519: bipush #16
    //   1521: idiv
    //   1522: if_icmpge -> 2436
    //   1525: bipush #16
    //   1527: newarray byte
    //   1529: astore #45
    //   1531: bipush #16
    //   1533: newarray byte
    //   1535: astore #46
    //   1537: iconst_0
    //   1538: istore #47
    //   1540: iload #47
    //   1542: bipush #16
    //   1544: if_icmpge -> 1570
    //   1547: aload #45
    //   1549: iload #47
    //   1551: aload #6
    //   1553: iload #47
    //   1555: iload #44
    //   1557: bipush #16
    //   1559: imul
    //   1560: iadd
    //   1561: baload
    //   1562: bastore
    //   1563: iinc #47, 1
    //   1566: iload_2
    //   1567: ifne -> 1540
    //   1570: iconst_0
    //   1571: istore #47
    //   1573: aload #45
    //   1575: iconst_0
    //   1576: baload
    //   1577: bipush #24
    //   1579: ishl
    //   1580: aload #45
    //   1582: iconst_1
    //   1583: baload
    //   1584: sipush #255
    //   1587: iand
    //   1588: bipush #16
    //   1590: ishl
    //   1591: ior
    //   1592: aload #45
    //   1594: iconst_2
    //   1595: baload
    //   1596: sipush #255
    //   1599: iand
    //   1600: bipush #8
    //   1602: ishl
    //   1603: ior
    //   1604: aload #45
    //   1606: iconst_3
    //   1607: baload
    //   1608: sipush #255
    //   1611: iand
    //   1612: ior
    //   1613: aload #30
    //   1615: iconst_0
    //   1616: iaload
    //   1617: ixor
    //   1618: istore #49
    //   1620: aload #45
    //   1622: iconst_4
    //   1623: baload
    //   1624: bipush #24
    //   1626: ishl
    //   1627: aload #45
    //   1629: iconst_5
    //   1630: baload
    //   1631: sipush #255
    //   1634: iand
    //   1635: bipush #16
    //   1637: ishl
    //   1638: ior
    //   1639: aload #45
    //   1641: bipush #6
    //   1643: baload
    //   1644: sipush #255
    //   1647: iand
    //   1648: bipush #8
    //   1650: ishl
    //   1651: ior
    //   1652: aload #45
    //   1654: bipush #7
    //   1656: baload
    //   1657: sipush #255
    //   1660: iand
    //   1661: ior
    //   1662: aload #30
    //   1664: iconst_1
    //   1665: iaload
    //   1666: ixor
    //   1667: istore #50
    //   1669: aload #45
    //   1671: bipush #8
    //   1673: baload
    //   1674: bipush #24
    //   1676: ishl
    //   1677: aload #45
    //   1679: bipush #9
    //   1681: baload
    //   1682: sipush #255
    //   1685: iand
    //   1686: bipush #16
    //   1688: ishl
    //   1689: ior
    //   1690: aload #45
    //   1692: bipush #10
    //   1694: baload
    //   1695: sipush #255
    //   1698: iand
    //   1699: bipush #8
    //   1701: ishl
    //   1702: ior
    //   1703: aload #45
    //   1705: bipush #11
    //   1707: baload
    //   1708: sipush #255
    //   1711: iand
    //   1712: ior
    //   1713: aload #30
    //   1715: iconst_2
    //   1716: iaload
    //   1717: ixor
    //   1718: istore #51
    //   1720: aload #45
    //   1722: bipush #12
    //   1724: baload
    //   1725: bipush #24
    //   1727: ishl
    //   1728: aload #45
    //   1730: bipush #13
    //   1732: baload
    //   1733: sipush #255
    //   1736: iand
    //   1737: bipush #16
    //   1739: ishl
    //   1740: ior
    //   1741: aload #45
    //   1743: bipush #14
    //   1745: baload
    //   1746: sipush #255
    //   1749: iand
    //   1750: bipush #8
    //   1752: ishl
    //   1753: ior
    //   1754: aload #45
    //   1756: bipush #15
    //   1758: baload
    //   1759: sipush #255
    //   1762: iand
    //   1763: ior
    //   1764: aload #30
    //   1766: iconst_3
    //   1767: iaload
    //   1768: ixor
    //   1769: istore #52
    //   1771: iconst_1
    //   1772: istore #53
    //   1774: iload #53
    //   1776: iload #36
    //   1778: if_icmpge -> 2021
    //   1781: iinc #47, 4
    //   1784: aload #38
    //   1786: iload #49
    //   1788: bipush #24
    //   1790: iushr
    //   1791: iaload
    //   1792: aload #39
    //   1794: iload #52
    //   1796: bipush #16
    //   1798: iushr
    //   1799: sipush #255
    //   1802: iand
    //   1803: iaload
    //   1804: ixor
    //   1805: aload #40
    //   1807: iload #51
    //   1809: bipush #8
    //   1811: iushr
    //   1812: sipush #255
    //   1815: iand
    //   1816: iaload
    //   1817: ixor
    //   1818: aload #41
    //   1820: iload #50
    //   1822: sipush #255
    //   1825: iand
    //   1826: iaload
    //   1827: ixor
    //   1828: aload #30
    //   1830: iload #47
    //   1832: iaload
    //   1833: ixor
    //   1834: istore #54
    //   1836: aload #38
    //   1838: iload #50
    //   1840: bipush #24
    //   1842: iushr
    //   1843: iaload
    //   1844: aload #39
    //   1846: iload #49
    //   1848: bipush #16
    //   1850: iushr
    //   1851: sipush #255
    //   1854: iand
    //   1855: iaload
    //   1856: ixor
    //   1857: aload #40
    //   1859: iload #52
    //   1861: bipush #8
    //   1863: iushr
    //   1864: sipush #255
    //   1867: iand
    //   1868: iaload
    //   1869: ixor
    //   1870: aload #41
    //   1872: iload #51
    //   1874: sipush #255
    //   1877: iand
    //   1878: iaload
    //   1879: ixor
    //   1880: aload #30
    //   1882: iload #47
    //   1884: iconst_1
    //   1885: iadd
    //   1886: iaload
    //   1887: ixor
    //   1888: istore #55
    //   1890: aload #38
    //   1892: iload #51
    //   1894: bipush #24
    //   1896: iushr
    //   1897: iaload
    //   1898: aload #39
    //   1900: iload #50
    //   1902: bipush #16
    //   1904: iushr
    //   1905: sipush #255
    //   1908: iand
    //   1909: iaload
    //   1910: ixor
    //   1911: aload #40
    //   1913: iload #49
    //   1915: bipush #8
    //   1917: iushr
    //   1918: sipush #255
    //   1921: iand
    //   1922: iaload
    //   1923: ixor
    //   1924: aload #41
    //   1926: iload #52
    //   1928: sipush #255
    //   1931: iand
    //   1932: iaload
    //   1933: ixor
    //   1934: aload #30
    //   1936: iload #47
    //   1938: iconst_2
    //   1939: iadd
    //   1940: iaload
    //   1941: ixor
    //   1942: istore #56
    //   1944: aload #38
    //   1946: iload #52
    //   1948: bipush #24
    //   1950: iushr
    //   1951: iaload
    //   1952: aload #39
    //   1954: iload #51
    //   1956: bipush #16
    //   1958: iushr
    //   1959: sipush #255
    //   1962: iand
    //   1963: iaload
    //   1964: ixor
    //   1965: aload #40
    //   1967: iload #50
    //   1969: bipush #8
    //   1971: iushr
    //   1972: sipush #255
    //   1975: iand
    //   1976: iaload
    //   1977: ixor
    //   1978: aload #41
    //   1980: iload #49
    //   1982: sipush #255
    //   1985: iand
    //   1986: iaload
    //   1987: ixor
    //   1988: aload #30
    //   1990: iload #47
    //   1992: iconst_3
    //   1993: iadd
    //   1994: iaload
    //   1995: ixor
    //   1996: istore #57
    //   1998: iload #54
    //   2000: istore #49
    //   2002: iload #55
    //   2004: istore #50
    //   2006: iload #56
    //   2008: istore #51
    //   2010: iload #57
    //   2012: istore #52
    //   2014: iinc #53, 1
    //   2017: iload_2
    //   2018: ifne -> 1774
    //   2021: iinc #47, 4
    //   2024: aload #30
    //   2026: iload #47
    //   2028: iaload
    //   2029: istore #48
    //   2031: aload #46
    //   2033: iconst_0
    //   2034: aload #37
    //   2036: iload #49
    //   2038: bipush #24
    //   2040: iushr
    //   2041: baload
    //   2042: iload #48
    //   2044: bipush #24
    //   2046: iushr
    //   2047: ixor
    //   2048: i2b
    //   2049: bastore
    //   2050: aload #46
    //   2052: iconst_1
    //   2053: aload #37
    //   2055: iload #52
    //   2057: bipush #16
    //   2059: iushr
    //   2060: sipush #255
    //   2063: iand
    //   2064: baload
    //   2065: iload #48
    //   2067: bipush #16
    //   2069: iushr
    //   2070: ixor
    //   2071: i2b
    //   2072: bastore
    //   2073: aload #46
    //   2075: iconst_2
    //   2076: aload #37
    //   2078: iload #51
    //   2080: bipush #8
    //   2082: iushr
    //   2083: sipush #255
    //   2086: iand
    //   2087: baload
    //   2088: iload #48
    //   2090: bipush #8
    //   2092: iushr
    //   2093: ixor
    //   2094: i2b
    //   2095: bastore
    //   2096: aload #46
    //   2098: iconst_3
    //   2099: aload #37
    //   2101: iload #50
    //   2103: sipush #255
    //   2106: iand
    //   2107: baload
    //   2108: iload #48
    //   2110: ixor
    //   2111: i2b
    //   2112: bastore
    //   2113: aload #30
    //   2115: iload #47
    //   2117: iconst_1
    //   2118: iadd
    //   2119: iaload
    //   2120: istore #48
    //   2122: aload #46
    //   2124: iconst_4
    //   2125: aload #37
    //   2127: iload #50
    //   2129: bipush #24
    //   2131: iushr
    //   2132: baload
    //   2133: iload #48
    //   2135: bipush #24
    //   2137: iushr
    //   2138: ixor
    //   2139: i2b
    //   2140: bastore
    //   2141: aload #46
    //   2143: iconst_5
    //   2144: aload #37
    //   2146: iload #49
    //   2148: bipush #16
    //   2150: iushr
    //   2151: sipush #255
    //   2154: iand
    //   2155: baload
    //   2156: iload #48
    //   2158: bipush #16
    //   2160: iushr
    //   2161: ixor
    //   2162: i2b
    //   2163: bastore
    //   2164: aload #46
    //   2166: bipush #6
    //   2168: aload #37
    //   2170: iload #52
    //   2172: bipush #8
    //   2174: iushr
    //   2175: sipush #255
    //   2178: iand
    //   2179: baload
    //   2180: iload #48
    //   2182: bipush #8
    //   2184: iushr
    //   2185: ixor
    //   2186: i2b
    //   2187: bastore
    //   2188: aload #46
    //   2190: bipush #7
    //   2192: aload #37
    //   2194: iload #51
    //   2196: sipush #255
    //   2199: iand
    //   2200: baload
    //   2201: iload #48
    //   2203: ixor
    //   2204: i2b
    //   2205: bastore
    //   2206: aload #30
    //   2208: iload #47
    //   2210: iconst_2
    //   2211: iadd
    //   2212: iaload
    //   2213: istore #48
    //   2215: aload #46
    //   2217: bipush #8
    //   2219: aload #37
    //   2221: iload #51
    //   2223: bipush #24
    //   2225: iushr
    //   2226: baload
    //   2227: iload #48
    //   2229: bipush #24
    //   2231: iushr
    //   2232: ixor
    //   2233: i2b
    //   2234: bastore
    //   2235: aload #46
    //   2237: bipush #9
    //   2239: aload #37
    //   2241: iload #50
    //   2243: bipush #16
    //   2245: iushr
    //   2246: sipush #255
    //   2249: iand
    //   2250: baload
    //   2251: iload #48
    //   2253: bipush #16
    //   2255: iushr
    //   2256: ixor
    //   2257: i2b
    //   2258: bastore
    //   2259: aload #46
    //   2261: bipush #10
    //   2263: aload #37
    //   2265: iload #49
    //   2267: bipush #8
    //   2269: iushr
    //   2270: sipush #255
    //   2273: iand
    //   2274: baload
    //   2275: iload #48
    //   2277: bipush #8
    //   2279: iushr
    //   2280: ixor
    //   2281: i2b
    //   2282: bastore
    //   2283: aload #46
    //   2285: bipush #11
    //   2287: aload #37
    //   2289: iload #52
    //   2291: sipush #255
    //   2294: iand
    //   2295: baload
    //   2296: iload #48
    //   2298: ixor
    //   2299: i2b
    //   2300: bastore
    //   2301: aload #30
    //   2303: iload #47
    //   2305: iconst_3
    //   2306: iadd
    //   2307: iaload
    //   2308: istore #48
    //   2310: aload #46
    //   2312: bipush #12
    //   2314: aload #37
    //   2316: iload #52
    //   2318: bipush #24
    //   2320: iushr
    //   2321: baload
    //   2322: iload #48
    //   2324: bipush #24
    //   2326: iushr
    //   2327: ixor
    //   2328: i2b
    //   2329: bastore
    //   2330: aload #46
    //   2332: bipush #13
    //   2334: aload #37
    //   2336: iload #51
    //   2338: bipush #16
    //   2340: iushr
    //   2341: sipush #255
    //   2344: iand
    //   2345: baload
    //   2346: iload #48
    //   2348: bipush #16
    //   2350: iushr
    //   2351: ixor
    //   2352: i2b
    //   2353: bastore
    //   2354: aload #46
    //   2356: bipush #14
    //   2358: aload #37
    //   2360: iload #50
    //   2362: bipush #8
    //   2364: iushr
    //   2365: sipush #255
    //   2368: iand
    //   2369: baload
    //   2370: iload #48
    //   2372: bipush #8
    //   2374: iushr
    //   2375: ixor
    //   2376: i2b
    //   2377: bastore
    //   2378: aload #46
    //   2380: bipush #15
    //   2382: aload #37
    //   2384: iload #49
    //   2386: sipush #255
    //   2389: iand
    //   2390: baload
    //   2391: iload #48
    //   2393: ixor
    //   2394: i2b
    //   2395: bastore
    //   2396: iconst_0
    //   2397: istore #53
    //   2399: iload #53
    //   2401: bipush #16
    //   2403: if_icmpge -> 2429
    //   2406: aload #43
    //   2408: iload #53
    //   2410: iload #44
    //   2412: bipush #16
    //   2414: imul
    //   2415: iadd
    //   2416: aload #46
    //   2418: iload #53
    //   2420: baload
    //   2421: bastore
    //   2422: iinc #53, 1
    //   2425: iload_2
    //   2426: ifne -> 2399
    //   2429: iinc #44, 1
    //   2432: iload_2
    //   2433: ifne -> 1514
    //   2436: aload #43
    //   2438: arraylength
    //   2439: ifle -> 2520
    //   2442: aload #43
    //   2444: aload #43
    //   2446: arraylength
    //   2447: iconst_1
    //   2448: isub
    //   2449: baload
    //   2450: istore #44
    //   2452: iload #44
    //   2454: bipush #16
    //   2456: if_icmple -> 2467
    //   2459: aload #43
    //   2461: astore #35
    //   2463: iload_2
    //   2464: ifne -> 2520
    //   2467: aload #43
    //   2469: arraylength
    //   2470: iload #44
    //   2472: isub
    //   2473: newarray byte
    //   2475: astore #35
    //   2477: iconst_0
    //   2478: istore #45
    //   2480: iload #45
    //   2482: aload #35
    //   2484: arraylength
    //   2485: if_icmpge -> 2520
    //   2488: iload #45
    //   2490: aload #43
    //   2492: arraylength
    //   2493: if_icmpge -> 2520
    //   2496: aload #35
    //   2498: iload #45
    //   2500: aload #43
    //   2502: iload #45
    //   2504: baload
    //   2505: bastore
    //   2506: iinc #45, 1
    //   2509: iload_2
    //   2510: ifne -> 2480
    //   2513: goto -> 2520
    //   2516: invokestatic a : (Ljava/lang/Throwable;)Ljava/lang/Throwable;
    //   2519: athrow
    //   2520: aload #35
    //   2522: astore #7
    //   2524: sipush #-13688
    //   2527: new java/math/BigInteger
    //   2530: dup
    //   2531: aload #7
    //   2533: invokespecial <init> : ([B)V
    //   2536: invokevirtual abs : ()Ljava/math/BigInteger;
    //   2539: putstatic burp/Zsin.Za : Ljava/lang/Object;
    //   2542: sipush #14528
    //   2545: invokestatic a : (II)Ljava/lang/String;
    //   2548: iconst_1
    //   2549: ldc burp/Zl_u
    //   2551: invokevirtual getClassLoader : ()Ljava/lang/ClassLoader;
    //   2554: invokestatic forName : (Ljava/lang/String;ZLjava/lang/ClassLoader;)Ljava/lang/Class;
    //   2557: invokevirtual getDeclaredFields : ()[Ljava/lang/reflect/Field;
    //   2560: astore_3
    //   2561: aload_3
    //   2562: arraylength
    //   2563: istore #4
    //   2565: iconst_0
    //   2566: istore #5
    //   2568: iload #5
    //   2570: iload #4
    //   2572: if_icmpge -> 2709
    //   2575: aload_3
    //   2576: iload #5
    //   2578: aaload
    //   2579: astore #6
    //   2581: aload #6
    //   2583: invokevirtual getModifiers : ()I
    //   2586: invokestatic isStatic : (I)Z
    //   2589: ifne -> 2599
    //   2592: goto -> 2702
    //   2595: invokestatic a : (Ljava/lang/Throwable;)Ljava/lang/Throwable;
    //   2598: athrow
    //   2599: aload #6
    //   2601: invokevirtual getType : ()Ljava/lang/Class;
    //   2604: astore #7
    //   2606: aload #7
    //   2608: ifnull -> 2689
    //   2611: aload #7
    //   2613: invokevirtual isPrimitive : ()Z
    //   2616: ifne -> 2689
    //   2619: goto -> 2626
    //   2622: invokestatic a : (Ljava/lang/Throwable;)Ljava/lang/Throwable;
    //   2625: athrow
    //   2626: aload #7
    //   2628: invokevirtual getPackage : ()Ljava/lang/Package;
    //   2631: ifnull -> 2689
    //   2634: goto -> 2641
    //   2637: invokestatic a : (Ljava/lang/Throwable;)Ljava/lang/Throwable;
    //   2640: athrow
    //   2641: aload #7
    //   2643: invokevirtual getPackage : ()Ljava/lang/Package;
    //   2646: invokevirtual getName : ()Ljava/lang/String;
    //   2649: ifnull -> 2689
    //   2652: goto -> 2659
    //   2655: invokestatic a : (Ljava/lang/Throwable;)Ljava/lang/Throwable;
    //   2658: athrow
    //   2659: aload #7
    //   2661: invokevirtual getPackage : ()Ljava/lang/Package;
    //   2664: invokevirtual getName : ()Ljava/lang/String;
    //   2667: sipush #-13694
    //   2670: sipush #-5871
    //   2673: invokestatic a : (II)Ljava/lang/String;
    //   2676: invokevirtual startsWith : (Ljava/lang/String;)Z
    //   2679: ifne -> 2689
    //   2682: goto -> 2689
    //   2685: invokestatic a : (Ljava/lang/Throwable;)Ljava/lang/Throwable;
    //   2688: athrow
    //   2689: aload #6
    //   2691: iconst_1
    //   2692: invokevirtual setAccessible : (Z)V
    //   2695: aload #6
    //   2697: aconst_null
    //   2698: invokevirtual get : (Ljava/lang/Object;)Ljava/lang/Object;
    //   2701: pop
    //   2702: iinc #5, 1
    //   2705: iload_2
    //   2706: ifne -> 2568
    //   2709: sipush #-13682
    //   2712: sipush #-29091
    //   2715: invokestatic a : (II)Ljava/lang/String;
    //   2718: invokestatic forName : (Ljava/lang/String;)Ljava/lang/Class;
    //   2721: invokevirtual getDeclaredMethods : ()[Ljava/lang/reflect/Method;
    //   2724: astore_3
    //   2725: aload_3
    //   2726: arraylength
    //   2727: istore #4
    //   2729: iconst_0
    //   2730: istore #5
    //   2732: iload #5
    //   2734: iload #4
    //   2736: if_icmpge -> 2868
    //   2739: aload_3
    //   2740: iload #5
    //   2742: aaload
    //   2743: astore #6
    //   2745: aload #6
    //   2747: invokevirtual getParameterTypes : ()[Ljava/lang/Class;
    //   2750: pop
    //   2751: aload #6
    //   2753: invokevirtual getModifiers : ()I
    //   2756: invokestatic isStatic : (I)Z
    //   2759: ifeq -> 2854
    //   2762: aload #6
    //   2764: invokevirtual getParameterTypes : ()[Ljava/lang/Class;
    //   2767: arraylength
    //   2768: iconst_2
    //   2769: if_icmpne -> 2854
    //   2772: goto -> 2779
    //   2775: invokestatic a : (Ljava/lang/Throwable;)Ljava/lang/Throwable;
    //   2778: athrow
    //   2779: aload #6
    //   2781: invokevirtual getReturnType : ()Ljava/lang/Class;
    //   2784: getstatic java/lang/Void.TYPE : Ljava/lang/Class;
    //   2787: invokevirtual equals : (Ljava/lang/Object;)Z
    //   2790: ifeq -> 2854
    //   2793: goto -> 2800
    //   2796: invokestatic a : (Ljava/lang/Throwable;)Ljava/lang/Throwable;
    //   2799: athrow
    //   2800: aload #6
    //   2802: iconst_1
    //   2803: invokevirtual setAccessible : (Z)V
    //   2806: aload #6
    //   2808: aconst_null
    //   2809: iconst_2
    //   2810: anewarray java/lang/Object
    //   2813: dup
    //   2814: iconst_0
    //   2815: aload_0
    //   2816: aastore
    //   2817: dup
    //   2818: iconst_1
    //   2819: aload_1
    //   2820: ifnonnull -> 2838
    //   2823: goto -> 2830
    //   2826: invokestatic a : (Ljava/lang/Throwable;)Ljava/lang/Throwable;
    //   2829: athrow
    //   2830: aload_1
    //   2831: goto -> 2845
    //   2834: invokestatic a : (Ljava/lang/Throwable;)Ljava/lang/Throwable;
    //   2837: athrow
    //   2838: aload_1
    //   2839: checkcast [B
    //   2842: invokevirtual clone : ()Ljava/lang/Object;
    //   2845: aastore
    //   2846: invokevirtual invoke : (Ljava/lang/Object;[Ljava/lang/Object;)Ljava/lang/Object;
    //   2849: pop
    //   2850: iload_2
    //   2851: ifne -> 2868
    //   2854: iinc #5, 1
    //   2857: iload_2
    //   2858: ifne -> 2732
    //   2861: goto -> 2868
    //   2864: invokestatic a : (Ljava/lang/Throwable;)Ljava/lang/Throwable;
    //   2867: athrow
    //   2868: getstatic burp/Zb3p.ZX : Ljava/lang/String;
    //   2871: getstatic burp/Zkul.Zb : Ljava/lang/Object;
    //   2874: checkcast java/math/BigInteger
    //   2877: invokevirtual intValue : ()I
    //   2880: bipush #32
    //   2882: irem
    //   2883: invokestatic abs : (I)I
    //   2886: invokevirtual charAt : (I)C
    //   2889: getstatic burp/Zewo.ZM : Ljava/lang/String;
    //   2892: getstatic burp/Zgdt.Zb : Ljava/lang/Object;
    //   2895: checkcast java/math/BigInteger
    //   2898: invokevirtual intValue : ()I
    //   2901: bipush #32
    //   2903: irem
    //   2904: invokestatic abs : (I)I
    //   2907: invokevirtual charAt : (I)C
    //   2910: if_icmple -> 3025
    //   2913: getstatic burp/Zz67.Zc : Ljava/lang/String;
    //   2916: getstatic burp/Zzvr.Z_ : Ljava/lang/Object;
    //   2919: checkcast java/math/BigInteger
    //   2922: invokevirtual intValue : ()I
    //   2925: bipush #32
    //   2927: irem
    //   2928: invokestatic abs : (I)I
    //   2931: invokevirtual charAt : (I)C
    //   2934: getstatic burp/Zly0.ZE : Ljava/lang/String;
    //   2937: getstatic burp/Zoa.ZI : Ljava/lang/Object;
    //   2940: checkcast java/math/BigInteger
    //   2943: invokevirtual intValue : ()I
    //   2946: bipush #32
    //   2948: irem
    //   2949: invokestatic abs : (I)I
    //   2952: invokevirtual charAt : (I)C
    //   2955: if_icmple -> 3025
    //   2958: goto -> 2965
    //   2961: invokestatic a : (Ljava/lang/Throwable;)Ljava/lang/Throwable;
    //   2964: athrow
    //   2965: getstatic burp/Zl1u.ZO : Ljava/lang/String;
    //   2968: getstatic burp/Zm06.ZU : Ljava/lang/Object;
    //   2971: checkcast java/math/BigInteger
    //   2974: invokevirtual intValue : ()I
    //   2977: bipush #32
    //   2979: irem
    //   2980: invokestatic abs : (I)I
    //   2983: invokevirtual charAt : (I)C
    //   2986: getstatic burp/Zmhx.ZD : Ljava/lang/String;
    //   2989: getstatic burp/Zlyf.Zm : Ljava/lang/Object;
    //   2992: checkcast java/math/BigInteger
    //   2995: invokevirtual intValue : ()I
    //   2998: bipush #32
    //   3000: irem
    //   3001: invokestatic abs : (I)I
    //   3004: invokevirtual charAt : (I)C
    //   3007: if_icmpgt -> 3025
    //   3010: goto -> 3017
    //   3013: invokestatic a : (Ljava/lang/Throwable;)Ljava/lang/Throwable;
    //   3016: athrow
    //   3017: iconst_1
    //   3018: goto -> 3026
    //   3021: invokestatic a : (Ljava/lang/Throwable;)Ljava/lang/Throwable;
    //   3024: athrow
    //   3025: iconst_0
    //   3026: ireturn
    //   3027: astore_3
    //   3028: new java/lang/Exception
    //   3031: dup
    //   3032: aload_3
    //   3033: invokevirtual getMessage : ()Ljava/lang/String;
    //   3036: invokespecial <init> : (Ljava/lang/String;)V
    //   3039: athrow
    // Exception table:
    //   from	to	target	type
    //   4	3026	3027	java/lang/Throwable
    //   167	182	182	java/lang/Throwable
    //   1184	1210	1210	java/lang/Throwable
    //   1291	1306	1306	java/lang/Throwable
    //   2488	2513	2516	java/lang/Throwable
    //   2581	2595	2595	java/lang/Throwable
    //   2606	2619	2622	java/lang/Throwable
    //   2611	2634	2637	java/lang/Throwable
    //   2626	2652	2655	java/lang/Throwable
    //   2641	2682	2685	java/lang/Throwable
    //   2745	2772	2775	java/lang/Throwable
    //   2762	2793	2796	java/lang/Throwable
    //   2779	2823	2826	java/lang/Throwable
    //   2800	2834	2834	java/lang/Throwable
    //   2845	2861	2864	java/lang/Throwable
    //   2868	2958	2961	java/lang/Throwable
    //   2913	3010	3013	java/lang/Throwable
    //   2965	3021	3021	java/lang/Throwable
  }
  
  static {
    // Byte code:
    //   0: bipush #12
    //   2: anewarray java/lang/String
    //   5: astore #5
    //   7: iconst_0
    //   8: istore_3
    //   9: ldc 'iÂ†`D1Â»h1 AÂµÃ‰M%Â—\\bÃ¼(Ã­Ã¬:Ã½4ÂÂ‚Ã«7Ã‚Ã³:&PQÂ§Â§Ãºt!\\tmÃÂÂˆT,Â»Ã·<MÃ¸P4Ã›Â€Ã˜Ã³aCÃš|\Ã‹FÂvvÂ®Â¾Â±Ã®P:Â„Ã½kÂ‹RÃ°kÂŸÃ“Ã¢Ã‰Ã§Ã˜Ã›Ã²)Ã‘8NlÃ—=Ã«Â¶y0ÂÂÃ¤Â„Â†vÂ¨Ã•<Â£Ã®Â‹$Â£Ã¼Ãš\\tGÃ¢ÃŠÃ¬Ã¼Â Â®fÂ\\tY6\\tvÂ„Ã³Â·f Ã¬Â†Â¦Â„Â©Â»Â‹Ã¹Ã£Â·RDÃ†Ã´Â§Â~VÂ‡Â£8Â”Ã’Ã†Â¿Ã‰Â€æ’çŸ¢ïŠ¼æ¾–ã€§æïº²ê®‹ìª°ì§Šïª†äŸŒêµ¯ê‰¸é°‡ç‹œë“é¾ãš ïŸ¸ã“‰î–»ç†¹ã‡“Ğ¨â¹á¢µÖ¶ß è‚´î¬•ë‰†à¥•â°á®—å«»åˆ£í˜†â§€â¼¶åÂŸâƒ¾ë†±æ¨‰ë¸¤ä©¨å¡Œí‚‡ê©„ä¦ã·ä—šÈƒå‚¸é¿¸å„ä¤é‹•ã œë²•?á‚ï‰ì·´áŒ£å¾Ÿä’µì¨ç»æ‹á¥»æ¨ä¾µâˆ¡é ä˜…ë¢?à¬ƒî€¬ã©½ä§®â˜ì‹ˆê³¿é…›î’³îœ³ã”è·‚ä»£æ°¨ï‘´æ—¸êº†ë©‹â•—á²¸ë’î£†ç“‹ä®´è¬–ç€‚ë•¿ä£³ï˜µæ„³å§è˜­áµœî†¤é¢æ§”è¹¯é¯‘èœ›ì¸’â¡¨è±•è¥šë¿‚äˆ¸ä‡¢â·ë‚¢ë¬ˆÃšÂ¶yfÃ˜'Ã¿[qqRvÂ…YTÂ´Ã£Ã¡'
    //   11: dup
    //   12: astore_2
    //   13: invokevirtual length : ()I
    //   16: istore #4
    //   18: bipush #9
    //   20: istore_1
    //   21: iconst_m1
    //   22: istore_0
    //   23: bipush #70
    //   25: iinc #0, 1
    //   28: aload_2
    //   29: iload_0
    //   30: dup
    //   31: iload_1
    //   32: iadd
    //   33: invokevirtual substring : (II)Ljava/lang/String;
    //   36: iconst_m1
    //   37: goto -> 143
    //   40: aload #5
    //   42: swap
    //   43: iload_3
    //   44: iinc #3, 1
    //   47: swap
    //   48: aastore
    //   49: iload_0
    //   50: iload_1
    //   51: iadd
    //   52: dup
    //   53: istore_0
    //   54: iload #4
    //   56: if_icmpge -> 68
    //   59: aload_2
    //   60: iload_0
    //   61: invokevirtual charAt : (I)C
    //   64: istore_1
    //   65: goto -> 23
    //   68: ldc 'ÃœÂˆÃ¸ÂšÃµ?ÃºxzÂŠ&Ã¸ÂMÃ„Ã»mÃ¾ÂœÂ£ÂŠÃ”<Q9Ã¹ÃƒÃ¶CÂƒ}Â„ÂƒqiuPÂ’NTÃ¡ÃŒÃÂ²Ã°Â±Ã•ÂµÂ‹ÃµqÂ¿Ã‚V%ÂtÂ“Ã<<q#Â«Â¨Ã”IÂ€æŒ‰ç©ïŠæ¾¦ã€ºæŸ‚ï¹ˆê¬¹ìª¶ì§…ï¨Ÿä´ê´…êˆ¶é°“ç‰ŒëˆéŒµãš‚ïŸˆã“”î—¤ç…ƒã…¡Ğ®â¶á ¬ÔŞŠèƒºî¬ë‹–à¦â±›á®µå«‹åˆ¾í™™â¤ºâ¾„å‰Ââ§ë„‰æ©£ë¹ªä©¼å£œíœê¨ä„ã‡ä—‡Éœå‚é½Šå„‰ä«é‰Œã¢¤ë³¿?á‚™ï™ì´¯á¨å¾½ä’…ìµçºæ“±á§‰æ®ä¾ºâŠ¸éƒ˜ä™¯ë£?à®“îƒ·ã¨¶ä§Œâ¨ì‹•ê² é†¡îîœµã›èµ›ä¹›æ±‚ïºæ—¬ê¸–ëªâ”œá²šë’¾î£›ç’”ä­è®¤ç€„ë•°ä¡ªïšæ…™åœ©è˜¹á·Œî…¿é£•æ§¶è¹Ÿé¯Œè„ì»¨â£šè±“è¥•ë½›äŠ€ä†ˆâ¶ƒë‚¶ë®˜'
    //   70: dup
    //   71: astore_2
    //   72: invokevirtual length : ()I
    //   75: istore #4
    //   77: bipush #77
    //   79: istore_1
    //   80: iconst_m1
    //   81: istore_0
    //   82: bipush #92
    //   84: iinc #0, 1
    //   87: aload_2
    //   88: iload_0
    //   89: dup
    //   90: iload_1
    //   91: iadd
    //   92: invokevirtual substring : (II)Ljava/lang/String;
    //   95: iconst_0
    //   96: goto -> 143
    //   99: aload #5
    //   101: swap
    //   102: iload_3
    //   103: iinc #3, 1
    //   106: swap
    //   107: aastore
    //   108: iload_0
    //   109: iload_1
    //   110: iadd
    //   111: dup
    //   112: istore_0
    //   113: iload #4
    //   115: if_icmpge -> 127
    //   118: aload_2
    //   119: iload_0
    //   120: invokevirtual charAt : (I)C
    //   123: istore_1
    //   124: goto -> 82
    //   127: aload #5
    //   129: putstatic burp/Zewo.a : [Ljava/lang/String;
    //   132: bipush #12
    //   134: anewarray java/lang/String
    //   137: putstatic burp/Zewo.b : [Ljava/lang/String;
    //   140: goto -> 300
    //   143: dup_x2
    //   144: pop
    //   145: invokevirtual toCharArray : ()[C
    //   148: dup_x1
    //   149: arraylength
    //   150: dup_x2
    //   151: pop
    //   152: iconst_0
    //   153: istore #6
    //   155: dup2_x1
    //   156: pop2
    //   157: dup_x2
    //   158: iconst_1
    //   159: if_icmpgt -> 260
    //   162: dup2
    //   163: swap
    //   164: iload #6
    //   166: dup2_x1
    //   167: caload
    //   168: swap
    //   169: iload #6
    //   171: bipush #7
    //   173: irem
    //   174: tableswitch default -> 242, 0 -> 212, 1 -> 217, 2 -> 222, 3 -> 227, 4 -> 232, 5 -> 237
    //   212: bipush #13
    //   214: goto -> 244
    //   217: bipush #78
    //   219: goto -> 244
    //   222: bipush #81
    //   224: goto -> 244
    //   227: bipush #92
    //   229: goto -> 244
    //   232: bipush #19
    //   234: goto -> 244
    //   237: bipush #28
    //   239: goto -> 244
    //   242: bipush #76
    //   244: ixor
    //   245: ixor
    //   246: i2c
    //   247: castore
    //   248: iinc #6, 1
    //   251: dup
    //   252: ifne -> 260
    //   255: dup2
    //   256: dup_x1
    //   257: goto -> 166
    //   260: dup2_x1
    //   261: pop2
    //   262: dup_x2
    //   263: iload #6
    //   265: if_icmpgt -> 162
    //   268: pop
    //   269: new java/lang/String
    //   272: dup_x1
    //   273: swap
    //   274: invokespecial <init> : ([C)V
    //   277: invokevirtual intern : ()Ljava/lang/String;
    //   280: swap
    //   281: pop
    //   282: swap
    //   283: tableswitch default -> 40, 0 -> 99
    //   300: sipush #-13685
    //   303: sipush #25413
    //   306: invokestatic a : (II)Ljava/lang/String;
    //   309: putstatic burp/Zewo.ZM : Ljava/lang/String;
    //   312: new java/math/BigInteger
    //   315: dup
    //   316: sipush #-13696
    //   319: sipush #25205
    //   322: invokestatic a : (II)Ljava/lang/String;
    //   325: invokespecial <init> : (Ljava/lang/String;)V
    //   328: putstatic burp/Zewo.ZZ : Ljava/lang/Object;
    //   331: return
  }
  
  private static Throwable a(Throwable paramThrowable) {
    return paramThrowable;
  }
  
  private static String a(int paramInt1, int paramInt2) {
    int i = (paramInt1 ^ 0xFFFFCA8A) & 0xFFFF;
    if (b[i] == null) {
      char[] arrayOfChar = a[i].toCharArray();
      switch (arrayOfChar[0] & 0xFF) {
        case 0:
        
        case 1:
        
        case 2:
        
        case 3:
        
        case 4:
        
        case 5:
        
        case 6:
        
        case 7:
        
        case 8:
        
        case 9:
        
        case 10:
        
        case 11:
        
        case 12:
        
        case 13:
        
        case 14:
        
        case 15:
        
        case 16:
        
        case 17:
        
        case 18:
        
        case 19:
        
        case 20:
        
        case 21:
        
        case 22:
        
        case 23:
        
        case 24:
        
        case 25:
        
        case 26:
        
        case 27:
        
        case 28:
        
        case 29:
        
        case 30:
        
        case 31:
        
        case 32:
        
        case 33:
        
        case 34:
        
        case 35:
        
        case 36:
        
        case 37:
        
        case 38:
        
        case 39:
        
        case 40:
        
        case 41:
        
        case 42:
        
        case 43:
        
        case 44:
        
        case 45:
        
        case 46:
        
        case 47:
        
        case 48:
        
        case 49:
        
        case 50:
        
        case 51:
        
        case 52:
        
        case 53:
        
        case 54:
        
        case 55:
        
        case 56:
        
        case 57:
        
        case 58:
        
        case 59:
        
        case 60:
        
        case 61:
        
        case 62:
        
        case 63:
        
        case 64:
        
        case 65:
        
        case 66:
        
        case 67:
        
        case 68:
        
        case 69:
        
        case 70:
        
        case 71:
        
        case 72:
        
        case 73:
        
        case 74:
        
        case 75:
        
        case 76:
        
        case 77:
        
        case 78:
        
        case 79:
        
        case 80:
        
        case 81:
        
        case 82:
        
        case 83:
        
        case 84:
        
        case 85:
        
        case 86:
        
        case 87:
        
        case 88:
        
        case 89:
        
        case 90:
        
        case 91:
        
        case 92:
        
        case 93:
        
        case 94:
        
        case 95:
        
        case 96:
        
        case 97:
        
        case 98:
        
        case 99:
        
        case 100:
        
        case 101:
        
        case 102:
        
        case 103:
        
        case 104:
        
        case 105:
        
        case 106:
        
        case 107:
        
        case 108:
        
        case 109:
        
        case 110:
        
        case 111:
        
        case 112:
        
        case 113:
        
        case 114:
        
        case 115:
        
        case 116:
        
        case 117:
        
        case 118:
        
        case 119:
        
        case 120:
        
        case 121:
        
        case 122:
        
        case 123:
        
        case 124:
        
        case 125:
        
        case 126:
        
        case 127:
        
        case 128:
        
        case 129:
        
        case 130:
        
        case 131:
        
        case 132:
        
        case 133:
        
        case 134:
        
        case 135:
        
        case 136:
        
        case 137:
        
        case 138:
        
        case 139:
        
        case 140:
        
        case 141:
        
        case 142:
        
        case 143:
        
        case 144:
        
        case 145:
        
        case 146:
        
        case 147:
        
        case 148:
        
        case 149:
        
        case 150:
        
        case 151:
        
        case 152:
        
        case 153:
        
        case 154:
        
        case 155:
        
        case 156:
        
        case 157:
        
        case 158:
        
        case 159:
        
        case 160:
        
        case 161:
        
        case 162:
        
        case 163:
        
        case 164:
        
        case 165:
        
        case 166:
        
        case 167:
        
        case 168:
        
        case 169:
        
        case 170:
        
        case 171:
        
        case 172:
        
        case 173:
        
        case 174:
        
        case 175:
        
        case 176:
        
        case 177:
        
        case 178:
        
        case 179:
        
        case 180:
        
        case 181:
        
        case 182:
        
        case 183:
        
        case 184:
        
        case 185:
        
        case 186:
        
        case 187:
        
        case 188:
        
        case 189:
        
        case 190:
        
        case 191:
        
        case 192:
        
        case 193:
        
        case 194:
        
        case 195:
        
        case 196:
        
        case 197:
        
        case 198:
        
        case 199:
        
        case 200:
        
        case 201:
        
        case 202:
        
        case 203:
        
        case 204:
        
        case 205:
        
        case 206:
        
        case 207:
        
        case 208:
        
        case 209:
        
        case 210:
        
        case 211:
        
        case 212:
        
        case 213:
        
        case 214:
        
        case 215:
        
        case 216:
        
        case 217:
        
        case 218:
        
        case 219:
        
        case 220:
        
        case 221:
        
        case 222:
        
        case 223:
        
        case 224:
        
        case 225:
        
        case 226:
        
        case 227:
        
        case 228:
        
        case 229:
        
        case 230:
        
        case 231:
        
        case 232:
        
        case 233:
        
        case 234:
        
        case 235:
        
        case 236:
        
        case 237:
        
        case 238:
        
        case 239:
        
        case 240:
        
        case 241:
        
        case 242:
        
        case 243:
        
        case 244:
        
        case 245:
        
        case 246:
        
        case 247:
        
        case 248:
        
        case 249:
        
        case 250:
        
        case 251:
        
        case 252:
        
        case 253:
        
        case 254:
        
        default:
          break;
      } 
      byte b1 = 88;
      int j = (paramInt2 & 0xFF) - b1;
      if (j < 0)
        j += 256; 
      int k = ((paramInt2 & 0xFFFF) >>> 8) - b1;
      if (k < 0)
        k += 256; 
      for (byte b2 = 0; b2 < arrayOfChar.length; b2++) {
        int m = b2 % 2;
        if (m == 0) {
          arrayOfChar[b2] = (char)(arrayOfChar[b2] ^ j);
          j = ((j >>> 3 | j << 5) ^ arrayOfChar[b2]) & 0xFF;
        } else {
          arrayOfChar[b2] = (char)(arrayOfChar[b2] ^ k);
          k = ((k >>> 3 | k << 5) ^ arrayOfChar[b2]) & 0xFF;
        } 
      } 
      b[i] = (new String(arrayOfChar)).intern();
    } 
    return b[i];
  }
}


/* Location:              C:\Program Files\BurpSuitePro\burpsuite_pro.jar!\burp\Zewo.class
 * Java compiler version: 21 (65.0)
 * JD-Core Version:       1.1.3
 */