package burp;

import java.math.BigInteger;

class Zex5 extends ClassLoader {
  static String Zh;
  
  static Object Zb;
  
  private static final String[] a;
  
  private static final String[] b;
  
  static void ZA(Object paramObject) {
    Zeoi.Zh = a(-20506, -14321);
    Zeoi.ZE = new BigInteger(a(-20507, 28329));
    boolean bool = Zt2e.ZN();
    try {
      try {
        if (Zlpu.ZA.charAt(Math.abs(((BigInteger)Zboa.Zh).intValue() % 32)) > Zlpu.ZA.charAt(Math.abs(((BigInteger)Zx_b.ZX).intValue() % 32))) {
          try {
            Zscf.ZV(Class.forName(a(-20508, -5935)));
            if (!bool)
              Zl1q.Zs(Class.forName(a(-20510, -28646))); 
          } catch (Throwable throwable) {
            throw a(null);
          } 
          return;
        } 
      } catch (Throwable throwable) {
        throw a(null);
      } 
      Zl1q.Zs(Class.forName(a(-20510, -28646)));
    } catch (Throwable throwable) {}
  }
  
  static void ZB(Object[] paramArrayOfObject, Object paramObject) throws Throwable {}
  
  static boolean ZJ(Object[] paramArrayOfObject, Object paramObject) throws Throwable {
    // Byte code:
    //   0: invokestatic ZN : ()Z
    //   3: istore_2
    //   4: getstatic burp/Zg7j.Zr : Ljava/lang/Object;
    //   7: checkcast java/math/BigInteger
    //   10: invokevirtual toByteArray : ()[B
    //   13: astore_3
    //   14: iconst_0
    //   15: istore #5
    //   17: iconst_0
    //   18: istore #6
    //   20: iload #6
    //   22: aload_3
    //   23: arraylength
    //   24: if_icmpge -> 169
    //   27: aload_3
    //   28: iload #6
    //   30: baload
    //   31: istore #7
    //   33: iload #7
    //   35: bipush #48
    //   37: if_icmplt -> 54
    //   40: iload #7
    //   42: bipush #57
    //   44: if_icmple -> 152
    //   47: goto -> 54
    //   50: invokestatic a : (Ljava/lang/Throwable;)Ljava/lang/Throwable;
    //   53: athrow
    //   54: iload #7
    //   56: bipush #65
    //   58: if_icmplt -> 82
    //   61: goto -> 68
    //   64: invokestatic a : (Ljava/lang/Throwable;)Ljava/lang/Throwable;
    //   67: athrow
    //   68: iload #7
    //   70: bipush #90
    //   72: if_icmple -> 152
    //   75: goto -> 82
    //   78: invokestatic a : (Ljava/lang/Throwable;)Ljava/lang/Throwable;
    //   81: athrow
    //   82: iload #7
    //   84: bipush #97
    //   86: if_icmplt -> 110
    //   89: goto -> 96
    //   92: invokestatic a : (Ljava/lang/Throwable;)Ljava/lang/Throwable;
    //   95: athrow
    //   96: iload #7
    //   98: bipush #122
    //   100: if_icmple -> 152
    //   103: goto -> 110
    //   106: invokestatic a : (Ljava/lang/Throwable;)Ljava/lang/Throwable;
    //   109: athrow
    //   110: iload #7
    //   112: bipush #43
    //   114: if_icmpeq -> 152
    //   117: goto -> 124
    //   120: invokestatic a : (Ljava/lang/Throwable;)Ljava/lang/Throwable;
    //   123: athrow
    //   124: iload #7
    //   126: bipush #47
    //   128: if_icmpeq -> 152
    //   131: goto -> 138
    //   134: invokestatic a : (Ljava/lang/Throwable;)Ljava/lang/Throwable;
    //   137: athrow
    //   138: iload #7
    //   140: bipush #61
    //   142: if_icmpne -> 162
    //   145: goto -> 152
    //   148: invokestatic a : (Ljava/lang/Throwable;)Ljava/lang/Throwable;
    //   151: athrow
    //   152: iinc #5, 1
    //   155: goto -> 162
    //   158: invokestatic a : (Ljava/lang/Throwable;)Ljava/lang/Throwable;
    //   161: athrow
    //   162: iinc #6, 1
    //   165: iload_2
    //   166: ifne -> 20
    //   169: iload #5
    //   171: newarray byte
    //   173: astore #6
    //   175: iconst_0
    //   176: istore #7
    //   178: iconst_0
    //   179: istore #8
    //   181: iload #8
    //   183: aload_3
    //   184: arraylength
    //   185: if_icmpge -> 337
    //   188: aload_3
    //   189: iload #8
    //   191: baload
    //   192: istore #9
    //   194: iload #9
    //   196: bipush #48
    //   198: if_icmplt -> 215
    //   201: iload #9
    //   203: bipush #57
    //   205: if_icmple -> 313
    //   208: goto -> 215
    //   211: invokestatic a : (Ljava/lang/Throwable;)Ljava/lang/Throwable;
    //   214: athrow
    //   215: iload #9
    //   217: bipush #65
    //   219: if_icmplt -> 243
    //   222: goto -> 229
    //   225: invokestatic a : (Ljava/lang/Throwable;)Ljava/lang/Throwable;
    //   228: athrow
    //   229: iload #9
    //   231: bipush #90
    //   233: if_icmple -> 313
    //   236: goto -> 243
    //   239: invokestatic a : (Ljava/lang/Throwable;)Ljava/lang/Throwable;
    //   242: athrow
    //   243: iload #9
    //   245: bipush #97
    //   247: if_icmplt -> 271
    //   250: goto -> 257
    //   253: invokestatic a : (Ljava/lang/Throwable;)Ljava/lang/Throwable;
    //   256: athrow
    //   257: iload #9
    //   259: bipush #122
    //   261: if_icmple -> 313
    //   264: goto -> 271
    //   267: invokestatic a : (Ljava/lang/Throwable;)Ljava/lang/Throwable;
    //   270: athrow
    //   271: iload #9
    //   273: bipush #43
    //   275: if_icmpeq -> 313
    //   278: goto -> 285
    //   281: invokestatic a : (Ljava/lang/Throwable;)Ljava/lang/Throwable;
    //   284: athrow
    //   285: iload #9
    //   287: bipush #47
    //   289: if_icmpeq -> 313
    //   292: goto -> 299
    //   295: invokestatic a : (Ljava/lang/Throwable;)Ljava/lang/Throwable;
    //   298: athrow
    //   299: iload #9
    //   301: bipush #61
    //   303: if_icmpne -> 330
    //   306: goto -> 313
    //   309: invokestatic a : (Ljava/lang/Throwable;)Ljava/lang/Throwable;
    //   312: athrow
    //   313: aload #6
    //   315: iload #7
    //   317: iload #9
    //   319: bastore
    //   320: iinc #7, 1
    //   323: goto -> 330
    //   326: invokestatic a : (Ljava/lang/Throwable;)Ljava/lang/Throwable;
    //   329: athrow
    //   330: iinc #8, 1
    //   333: iload_2
    //   334: ifne -> 181
    //   337: aload #6
    //   339: astore #4
    //   341: aload #4
    //   343: astore_3
    //   344: aload_3
    //   345: arraylength
    //   346: istore #5
    //   348: aload_3
    //   349: iload #5
    //   351: iconst_1
    //   352: isub
    //   353: baload
    //   354: bipush #61
    //   356: if_icmpne -> 366
    //   359: iinc #5, -1
    //   362: iload_2
    //   363: ifne -> 348
    //   366: iload #5
    //   368: aload_3
    //   369: arraylength
    //   370: iconst_4
    //   371: idiv
    //   372: isub
    //   373: newarray byte
    //   375: astore #6
    //   377: iconst_0
    //   378: istore #7
    //   380: iload #7
    //   382: aload_3
    //   383: arraylength
    //   384: if_icmpge -> 646
    //   387: aload_3
    //   388: iload #7
    //   390: baload
    //   391: bipush #61
    //   393: if_icmpne -> 412
    //   396: aload_3
    //   397: iload #7
    //   399: iconst_0
    //   400: bastore
    //   401: iload_2
    //   402: ifne -> 639
    //   405: goto -> 412
    //   408: invokestatic a : (Ljava/lang/Throwable;)Ljava/lang/Throwable;
    //   411: athrow
    //   412: aload_3
    //   413: iload #7
    //   415: baload
    //   416: bipush #47
    //   418: if_icmpne -> 445
    //   421: goto -> 428
    //   424: invokestatic a : (Ljava/lang/Throwable;)Ljava/lang/Throwable;
    //   427: athrow
    //   428: aload_3
    //   429: iload #7
    //   431: bipush #63
    //   433: bastore
    //   434: iload_2
    //   435: ifne -> 639
    //   438: goto -> 445
    //   441: invokestatic a : (Ljava/lang/Throwable;)Ljava/lang/Throwable;
    //   444: athrow
    //   445: aload_3
    //   446: iload #7
    //   448: baload
    //   449: bipush #43
    //   451: if_icmpne -> 478
    //   454: goto -> 461
    //   457: invokestatic a : (Ljava/lang/Throwable;)Ljava/lang/Throwable;
    //   460: athrow
    //   461: aload_3
    //   462: iload #7
    //   464: bipush #62
    //   466: bastore
    //   467: iload_2
    //   468: ifne -> 639
    //   471: goto -> 478
    //   474: invokestatic a : (Ljava/lang/Throwable;)Ljava/lang/Throwable;
    //   477: athrow
    //   478: aload_3
    //   479: iload #7
    //   481: baload
    //   482: bipush #48
    //   484: if_icmplt -> 533
    //   487: goto -> 494
    //   490: invokestatic a : (Ljava/lang/Throwable;)Ljava/lang/Throwable;
    //   493: athrow
    //   494: aload_3
    //   495: iload #7
    //   497: baload
    //   498: bipush #57
    //   500: if_icmpgt -> 533
    //   503: goto -> 510
    //   506: invokestatic a : (Ljava/lang/Throwable;)Ljava/lang/Throwable;
    //   509: athrow
    //   510: aload_3
    //   511: iload #7
    //   513: aload_3
    //   514: iload #7
    //   516: baload
    //   517: bipush #-4
    //   519: isub
    //   520: i2b
    //   521: bastore
    //   522: iload_2
    //   523: ifne -> 639
    //   526: goto -> 533
    //   529: invokestatic a : (Ljava/lang/Throwable;)Ljava/lang/Throwable;
    //   532: athrow
    //   533: aload_3
    //   534: iload #7
    //   536: baload
    //   537: bipush #97
    //   539: if_icmplt -> 588
    //   542: goto -> 549
    //   545: invokestatic a : (Ljava/lang/Throwable;)Ljava/lang/Throwable;
    //   548: athrow
    //   549: aload_3
    //   550: iload #7
    //   552: baload
    //   553: bipush #122
    //   555: if_icmpgt -> 588
    //   558: goto -> 565
    //   561: invokestatic a : (Ljava/lang/Throwable;)Ljava/lang/Throwable;
    //   564: athrow
    //   565: aload_3
    //   566: iload #7
    //   568: aload_3
    //   569: iload #7
    //   571: baload
    //   572: bipush #71
    //   574: isub
    //   575: i2b
    //   576: bastore
    //   577: iload_2
    //   578: ifne -> 639
    //   581: goto -> 588
    //   584: invokestatic a : (Ljava/lang/Throwable;)Ljava/lang/Throwable;
    //   587: athrow
    //   588: aload_3
    //   589: iload #7
    //   591: baload
    //   592: bipush #65
    //   594: if_icmplt -> 639
    //   597: goto -> 604
    //   600: invokestatic a : (Ljava/lang/Throwable;)Ljava/lang/Throwable;
    //   603: athrow
    //   604: aload_3
    //   605: iload #7
    //   607: baload
    //   608: bipush #90
    //   610: if_icmpgt -> 639
    //   613: goto -> 620
    //   616: invokestatic a : (Ljava/lang/Throwable;)Ljava/lang/Throwable;
    //   619: athrow
    //   620: aload_3
    //   621: iload #7
    //   623: aload_3
    //   624: iload #7
    //   626: baload
    //   627: bipush #65
    //   629: isub
    //   630: i2b
    //   631: bastore
    //   632: goto -> 639
    //   635: invokestatic a : (Ljava/lang/Throwable;)Ljava/lang/Throwable;
    //   638: athrow
    //   639: iinc #7, 1
    //   642: iload_2
    //   643: ifne -> 380
    //   646: iconst_0
    //   647: istore #7
    //   649: iconst_0
    //   650: istore #8
    //   652: iload #8
    //   654: aload #6
    //   656: arraylength
    //   657: iconst_2
    //   658: isub
    //   659: if_icmpge -> 762
    //   662: aload #6
    //   664: iload #8
    //   666: aload_3
    //   667: iload #7
    //   669: baload
    //   670: iconst_2
    //   671: ishl
    //   672: sipush #255
    //   675: iand
    //   676: aload_3
    //   677: iload #7
    //   679: iconst_1
    //   680: iadd
    //   681: baload
    //   682: iconst_4
    //   683: iushr
    //   684: iconst_3
    //   685: iand
    //   686: ior
    //   687: i2b
    //   688: bastore
    //   689: aload #6
    //   691: iload #8
    //   693: iconst_1
    //   694: iadd
    //   695: aload_3
    //   696: iload #7
    //   698: iconst_1
    //   699: iadd
    //   700: baload
    //   701: iconst_4
    //   702: ishl
    //   703: sipush #255
    //   706: iand
    //   707: aload_3
    //   708: iload #7
    //   710: iconst_2
    //   711: iadd
    //   712: baload
    //   713: iconst_2
    //   714: iushr
    //   715: bipush #15
    //   717: iand
    //   718: ior
    //   719: i2b
    //   720: bastore
    //   721: aload #6
    //   723: iload #8
    //   725: iconst_2
    //   726: iadd
    //   727: aload_3
    //   728: iload #7
    //   730: iconst_2
    //   731: iadd
    //   732: baload
    //   733: bipush #6
    //   735: ishl
    //   736: sipush #255
    //   739: iand
    //   740: aload_3
    //   741: iload #7
    //   743: iconst_3
    //   744: iadd
    //   745: baload
    //   746: bipush #63
    //   748: iand
    //   749: ior
    //   750: i2b
    //   751: bastore
    //   752: iinc #7, 4
    //   755: iinc #8, 3
    //   758: iload_2
    //   759: ifne -> 652
    //   762: iload #8
    //   764: aload #6
    //   766: arraylength
    //   767: if_icmpge -> 804
    //   770: aload #6
    //   772: iload #8
    //   774: aload_3
    //   775: iload #7
    //   777: baload
    //   778: iconst_2
    //   779: ishl
    //   780: sipush #255
    //   783: iand
    //   784: aload_3
    //   785: iload #7
    //   787: iconst_1
    //   788: iadd
    //   789: baload
    //   790: iconst_4
    //   791: iushr
    //   792: iconst_3
    //   793: iand
    //   794: ior
    //   795: i2b
    //   796: bastore
    //   797: goto -> 804
    //   800: invokestatic a : (Ljava/lang/Throwable;)Ljava/lang/Throwable;
    //   803: athrow
    //   804: iinc #8, 1
    //   807: iload #8
    //   809: aload #6
    //   811: arraylength
    //   812: if_icmpge -> 852
    //   815: aload #6
    //   817: iload #8
    //   819: aload_3
    //   820: iload #7
    //   822: iconst_1
    //   823: iadd
    //   824: baload
    //   825: iconst_4
    //   826: ishl
    //   827: sipush #255
    //   830: iand
    //   831: aload_3
    //   832: iload #7
    //   834: iconst_2
    //   835: iadd
    //   836: baload
    //   837: iconst_2
    //   838: iushr
    //   839: bipush #15
    //   841: iand
    //   842: ior
    //   843: i2b
    //   844: bastore
    //   845: goto -> 852
    //   848: invokestatic a : (Ljava/lang/Throwable;)Ljava/lang/Throwable;
    //   851: athrow
    //   852: aload #6
    //   854: astore #4
    //   856: new java/math/BigInteger
    //   859: dup
    //   860: aload #4
    //   862: invokespecial <init> : ([B)V
    //   865: invokevirtual abs : ()Ljava/math/BigInteger;
    //   868: putstatic burp/Zgco.Zx : Ljava/lang/Object;
    //   871: ldc2_w 8682522807148012
    //   874: invokestatic currentTimeMillis : ()J
    //   877: lxor
    //   878: lstore #4
    //   880: lload #4
    //   882: ldc2_w 25214903917
    //   885: lmul
    //   886: ldc2_w 11
    //   889: ladd
    //   890: ldc2_w 281474976710655
    //   893: land
    //   894: lstore #4
    //   896: lload #4
    //   898: bipush #32
    //   900: lshl
    //   901: lstore #6
    //   903: lload #4
    //   905: ldc2_w 25214903917
    //   908: lmul
    //   909: ldc2_w 11
    //   912: ladd
    //   913: ldc2_w 281474976710655
    //   916: land
    //   917: lstore #4
    //   919: lload #6
    //   921: lload #4
    //   923: ladd
    //   924: lstore #6
    //   926: bipush #16
    //   928: newarray byte
    //   930: dup
    //   931: iconst_0
    //   932: bipush #48
    //   934: bastore
    //   935: dup
    //   936: iconst_1
    //   937: bipush #49
    //   939: bastore
    //   940: dup
    //   941: iconst_2
    //   942: bipush #50
    //   944: bastore
    //   945: dup
    //   946: iconst_3
    //   947: bipush #51
    //   949: bastore
    //   950: dup
    //   951: iconst_4
    //   952: bipush #52
    //   954: bastore
    //   955: dup
    //   956: iconst_5
    //   957: bipush #53
    //   959: bastore
    //   960: dup
    //   961: bipush #6
    //   963: bipush #54
    //   965: bastore
    //   966: dup
    //   967: bipush #7
    //   969: bipush #55
    //   971: bastore
    //   972: dup
    //   973: bipush #8
    //   975: bipush #56
    //   977: bastore
    //   978: dup
    //   979: bipush #9
    //   981: bipush #57
    //   983: bastore
    //   984: dup
    //   985: bipush #10
    //   987: bipush #97
    //   989: bastore
    //   990: dup
    //   991: bipush #11
    //   993: bipush #98
    //   995: bastore
    //   996: dup
    //   997: bipush #12
    //   999: bipush #99
    //   1001: bastore
    //   1002: dup
    //   1003: bipush #13
    //   1005: bipush #100
    //   1007: bastore
    //   1008: dup
    //   1009: bipush #14
    //   1011: bipush #101
    //   1013: bastore
    //   1014: dup
    //   1015: bipush #15
    //   1017: bipush #102
    //   1019: bastore
    //   1020: astore #8
    //   1022: bipush #64
    //   1024: newarray byte
    //   1026: astore #9
    //   1028: bipush #64
    //   1030: istore #10
    //   1032: bipush #16
    //   1034: istore #11
    //   1036: iload #11
    //   1038: iconst_1
    //   1039: isub
    //   1040: i2l
    //   1041: lstore #12
    //   1043: aload #9
    //   1045: iinc #10, -1
    //   1048: iload #10
    //   1050: aload #8
    //   1052: lload #6
    //   1054: lload #12
    //   1056: land
    //   1057: l2i
    //   1058: baload
    //   1059: bastore
    //   1060: lload #6
    //   1062: iconst_4
    //   1063: lushr
    //   1064: lstore #6
    //   1066: lload #6
    //   1068: lconst_0
    //   1069: lcmp
    //   1070: ifne -> 1043
    //   1073: bipush #64
    //   1075: iload #10
    //   1077: isub
    //   1078: newarray byte
    //   1080: astore_3
    //   1081: iconst_0
    //   1082: istore #14
    //   1084: iload #14
    //   1086: aload_3
    //   1087: arraylength
    //   1088: if_icmpge -> 1110
    //   1091: aload_3
    //   1092: iload #14
    //   1094: aload #9
    //   1096: iload #10
    //   1098: iload #14
    //   1100: iadd
    //   1101: baload
    //   1102: bastore
    //   1103: iinc #14, 1
    //   1106: iload_2
    //   1107: ifne -> 1084
    //   1110: aload_3
    //   1111: arraylength
    //   1112: bipush #10
    //   1114: if_icmplt -> 880
    //   1117: new java/lang/StringBuilder
    //   1120: dup
    //   1121: invokespecial <init> : ()V
    //   1124: astore_3
    //   1125: iconst_0
    //   1126: istore #4
    //   1128: iload #4
    //   1130: bipush #32
    //   1132: if_icmpge -> 2467
    //   1135: iload #4
    //   1137: tableswitch default -> 2460, 0 -> 1280, 1 -> 1317, 2 -> 1354, 3 -> 1391, 4 -> 1428, 5 -> 1465, 6 -> 1502, 7 -> 1539, 8 -> 1576, 9 -> 1613, 10 -> 1650, 11 -> 1687, 12 -> 1724, 13 -> 1761, 14 -> 1798, 15 -> 1835, 16 -> 1872, 17 -> 1909, 18 -> 1946, 19 -> 1983, 20 -> 2020, 21 -> 2057, 22 -> 2094, 23 -> 2131, 24 -> 2168, 25 -> 2205, 26 -> 2242, 27 -> 2279, 28 -> 2316, 29 -> 2353, 30 -> 2390, 31 -> 2427
    //   1280: aload_3
    //   1281: getstatic burp/Zm_w.ZA : Ljava/lang/String;
    //   1284: getstatic burp/Ze08.ZJ : Ljava/lang/Object;
    //   1287: checkcast java/math/BigInteger
    //   1290: invokevirtual intValue : ()I
    //   1293: bipush #32
    //   1295: irem
    //   1296: invokestatic abs : (I)I
    //   1299: invokevirtual charAt : (I)C
    //   1302: invokevirtual append : (C)Ljava/lang/StringBuilder;
    //   1305: pop
    //   1306: iload_2
    //   1307: ifne -> 2460
    //   1310: goto -> 1317
    //   1313: invokestatic a : (Ljava/lang/Throwable;)Ljava/lang/Throwable;
    //   1316: athrow
    //   1317: aload_3
    //   1318: getstatic burp/Zlfi.Zg : Ljava/lang/String;
    //   1321: getstatic burp/Zd0.ZT : Ljava/lang/Object;
    //   1324: checkcast java/math/BigInteger
    //   1327: invokevirtual intValue : ()I
    //   1330: bipush #32
    //   1332: irem
    //   1333: invokestatic abs : (I)I
    //   1336: invokevirtual charAt : (I)C
    //   1339: invokevirtual append : (C)Ljava/lang/StringBuilder;
    //   1342: pop
    //   1343: iload_2
    //   1344: ifne -> 2460
    //   1347: goto -> 1354
    //   1350: invokestatic a : (Ljava/lang/Throwable;)Ljava/lang/Throwable;
    //   1353: athrow
    //   1354: aload_3
    //   1355: getstatic burp/Zt7w.Zi : Ljava/lang/String;
    //   1358: getstatic burp/Zm_w.ZW : Ljava/lang/Object;
    //   1361: checkcast java/math/BigInteger
    //   1364: invokevirtual intValue : ()I
    //   1367: bipush #32
    //   1369: irem
    //   1370: invokestatic abs : (I)I
    //   1373: invokevirtual charAt : (I)C
    //   1376: invokevirtual append : (C)Ljava/lang/StringBuilder;
    //   1379: pop
    //   1380: iload_2
    //   1381: ifne -> 2460
    //   1384: goto -> 1391
    //   1387: invokestatic a : (Ljava/lang/Throwable;)Ljava/lang/Throwable;
    //   1390: athrow
    //   1391: aload_3
    //   1392: getstatic burp/Zm81.ZY : Ljava/lang/String;
    //   1395: getstatic burp/Zxjm.Zn : Ljava/lang/Object;
    //   1398: checkcast java/math/BigInteger
    //   1401: invokevirtual intValue : ()I
    //   1404: bipush #32
    //   1406: irem
    //   1407: invokestatic abs : (I)I
    //   1410: invokevirtual charAt : (I)C
    //   1413: invokevirtual append : (C)Ljava/lang/StringBuilder;
    //   1416: pop
    //   1417: iload_2
    //   1418: ifne -> 2460
    //   1421: goto -> 1428
    //   1424: invokestatic a : (Ljava/lang/Throwable;)Ljava/lang/Throwable;
    //   1427: athrow
    //   1428: aload_3
    //   1429: getstatic burp/Zm_w.ZA : Ljava/lang/String;
    //   1432: getstatic burp/Zvi.Zs : Ljava/lang/Object;
    //   1435: checkcast java/math/BigInteger
    //   1438: invokevirtual intValue : ()I
    //   1441: bipush #32
    //   1443: irem
    //   1444: invokestatic abs : (I)I
    //   1447: invokevirtual charAt : (I)C
    //   1450: invokevirtual append : (C)Ljava/lang/StringBuilder;
    //   1453: pop
    //   1454: iload_2
    //   1455: ifne -> 2460
    //   1458: goto -> 1465
    //   1461: invokestatic a : (Ljava/lang/Throwable;)Ljava/lang/Throwable;
    //   1464: athrow
    //   1465: aload_3
    //   1466: getstatic burp/Zgfm.ZE : Ljava/lang/String;
    //   1469: getstatic burp/Zxjm.Zn : Ljava/lang/Object;
    //   1472: checkcast java/math/BigInteger
    //   1475: invokevirtual intValue : ()I
    //   1478: bipush #32
    //   1480: irem
    //   1481: invokestatic abs : (I)I
    //   1484: invokevirtual charAt : (I)C
    //   1487: invokevirtual append : (C)Ljava/lang/StringBuilder;
    //   1490: pop
    //   1491: iload_2
    //   1492: ifne -> 2460
    //   1495: goto -> 1502
    //   1498: invokestatic a : (Ljava/lang/Throwable;)Ljava/lang/Throwable;
    //   1501: athrow
    //   1502: aload_3
    //   1503: getstatic burp/Zx58.Zs : Ljava/lang/String;
    //   1506: getstatic burp/Zg2z.ZU : Ljava/lang/Object;
    //   1509: checkcast java/math/BigInteger
    //   1512: invokevirtual intValue : ()I
    //   1515: bipush #32
    //   1517: irem
    //   1518: invokestatic abs : (I)I
    //   1521: invokevirtual charAt : (I)C
    //   1524: invokevirtual append : (C)Ljava/lang/StringBuilder;
    //   1527: pop
    //   1528: iload_2
    //   1529: ifne -> 2460
    //   1532: goto -> 1539
    //   1535: invokestatic a : (Ljava/lang/Throwable;)Ljava/lang/Throwable;
    //   1538: athrow
    //   1539: aload_3
    //   1540: getstatic burp/Zgfm.ZE : Ljava/lang/String;
    //   1543: getstatic burp/Zec0.Zg : Ljava/lang/Object;
    //   1546: checkcast java/math/BigInteger
    //   1549: invokevirtual intValue : ()I
    //   1552: bipush #32
    //   1554: irem
    //   1555: invokestatic abs : (I)I
    //   1558: invokevirtual charAt : (I)C
    //   1561: invokevirtual append : (C)Ljava/lang/StringBuilder;
    //   1564: pop
    //   1565: iload_2
    //   1566: ifne -> 2460
    //   1569: goto -> 1576
    //   1572: invokestatic a : (Ljava/lang/Throwable;)Ljava/lang/Throwable;
    //   1575: athrow
    //   1576: aload_3
    //   1577: getstatic burp/Zm_w.ZA : Ljava/lang/String;
    //   1580: getstatic burp/Zgfm.ZV : Ljava/lang/Object;
    //   1583: checkcast java/math/BigInteger
    //   1586: invokevirtual intValue : ()I
    //   1589: bipush #32
    //   1591: irem
    //   1592: invokestatic abs : (I)I
    //   1595: invokevirtual charAt : (I)C
    //   1598: invokevirtual append : (C)Ljava/lang/StringBuilder;
    //   1601: pop
    //   1602: iload_2
    //   1603: ifne -> 2460
    //   1606: goto -> 1613
    //   1609: invokestatic a : (Ljava/lang/Throwable;)Ljava/lang/Throwable;
    //   1612: athrow
    //   1613: aload_3
    //   1614: getstatic burp/Zboa.Zq : Ljava/lang/String;
    //   1617: getstatic burp/Ze3z.Zf : Ljava/lang/Object;
    //   1620: checkcast java/math/BigInteger
    //   1623: invokevirtual intValue : ()I
    //   1626: bipush #32
    //   1628: irem
    //   1629: invokestatic abs : (I)I
    //   1632: invokevirtual charAt : (I)C
    //   1635: invokevirtual append : (C)Ljava/lang/StringBuilder;
    //   1638: pop
    //   1639: iload_2
    //   1640: ifne -> 2460
    //   1643: goto -> 1650
    //   1646: invokestatic a : (Ljava/lang/Throwable;)Ljava/lang/Throwable;
    //   1649: athrow
    //   1650: aload_3
    //   1651: getstatic burp/Zelz.ZK : Ljava/lang/String;
    //   1654: getstatic burp/Zm1l.Za : Ljava/lang/Object;
    //   1657: checkcast java/math/BigInteger
    //   1660: invokevirtual intValue : ()I
    //   1663: bipush #32
    //   1665: irem
    //   1666: invokestatic abs : (I)I
    //   1669: invokevirtual charAt : (I)C
    //   1672: invokevirtual append : (C)Ljava/lang/StringBuilder;
    //   1675: pop
    //   1676: iload_2
    //   1677: ifne -> 2460
    //   1680: goto -> 1687
    //   1683: invokestatic a : (Ljava/lang/Throwable;)Ljava/lang/Throwable;
    //   1686: athrow
    //   1687: aload_3
    //   1688: getstatic burp/Ztvp.ZZ : Ljava/lang/String;
    //   1691: getstatic burp/Zgco.Zx : Ljava/lang/Object;
    //   1694: checkcast java/math/BigInteger
    //   1697: invokevirtual intValue : ()I
    //   1700: bipush #32
    //   1702: irem
    //   1703: invokestatic abs : (I)I
    //   1706: invokevirtual charAt : (I)C
    //   1709: invokevirtual append : (C)Ljava/lang/StringBuilder;
    //   1712: pop
    //   1713: iload_2
    //   1714: ifne -> 2460
    //   1717: goto -> 1724
    //   1720: invokestatic a : (Ljava/lang/Throwable;)Ljava/lang/Throwable;
    //   1723: athrow
    //   1724: aload_3
    //   1725: getstatic burp/Ze08.Zh : Ljava/lang/String;
    //   1728: getstatic burp/Zsyu.Zj : Ljava/lang/Object;
    //   1731: checkcast java/math/BigInteger
    //   1734: invokevirtual intValue : ()I
    //   1737: bipush #32
    //   1739: irem
    //   1740: invokestatic abs : (I)I
    //   1743: invokevirtual charAt : (I)C
    //   1746: invokevirtual append : (C)Ljava/lang/StringBuilder;
    //   1749: pop
    //   1750: iload_2
    //   1751: ifne -> 2460
    //   1754: goto -> 1761
    //   1757: invokestatic a : (Ljava/lang/Throwable;)Ljava/lang/Throwable;
    //   1760: athrow
    //   1761: aload_3
    //   1762: getstatic burp/Zxjm.ZG : Ljava/lang/String;
    //   1765: getstatic burp/Zec_.ZN : Ljava/lang/Object;
    //   1768: checkcast java/math/BigInteger
    //   1771: invokevirtual intValue : ()I
    //   1774: bipush #32
    //   1776: irem
    //   1777: invokestatic abs : (I)I
    //   1780: invokevirtual charAt : (I)C
    //   1783: invokevirtual append : (C)Ljava/lang/StringBuilder;
    //   1786: pop
    //   1787: iload_2
    //   1788: ifne -> 2460
    //   1791: goto -> 1798
    //   1794: invokestatic a : (Ljava/lang/Throwable;)Ljava/lang/Throwable;
    //   1797: athrow
    //   1798: aload_3
    //   1799: getstatic burp/Zl6e.ZC : Ljava/lang/String;
    //   1802: getstatic burp/Zm_w.ZW : Ljava/lang/Object;
    //   1805: checkcast java/math/BigInteger
    //   1808: invokevirtual intValue : ()I
    //   1811: bipush #32
    //   1813: irem
    //   1814: invokestatic abs : (I)I
    //   1817: invokevirtual charAt : (I)C
    //   1820: invokevirtual append : (C)Ljava/lang/StringBuilder;
    //   1823: pop
    //   1824: iload_2
    //   1825: ifne -> 2460
    //   1828: goto -> 1835
    //   1831: invokestatic a : (Ljava/lang/Throwable;)Ljava/lang/Throwable;
    //   1834: athrow
    //   1835: aload_3
    //   1836: getstatic burp/Zsuw.ZK : Ljava/lang/String;
    //   1839: getstatic burp/Zboa.Zh : Ljava/lang/Object;
    //   1842: checkcast java/math/BigInteger
    //   1845: invokevirtual intValue : ()I
    //   1848: bipush #32
    //   1850: irem
    //   1851: invokestatic abs : (I)I
    //   1854: invokevirtual charAt : (I)C
    //   1857: invokevirtual append : (C)Ljava/lang/StringBuilder;
    //   1860: pop
    //   1861: iload_2
    //   1862: ifne -> 2460
    //   1865: goto -> 1872
    //   1868: invokestatic a : (Ljava/lang/Throwable;)Ljava/lang/Throwable;
    //   1871: athrow
    //   1872: aload_3
    //   1873: getstatic burp/Ztvp.ZZ : Ljava/lang/String;
    //   1876: getstatic burp/Zboa.Zh : Ljava/lang/Object;
    //   1879: checkcast java/math/BigInteger
    //   1882: invokevirtual intValue : ()I
    //   1885: bipush #32
    //   1887: irem
    //   1888: invokestatic abs : (I)I
    //   1891: invokevirtual charAt : (I)C
    //   1894: invokevirtual append : (C)Ljava/lang/StringBuilder;
    //   1897: pop
    //   1898: iload_2
    //   1899: ifne -> 2460
    //   1902: goto -> 1909
    //   1905: invokestatic a : (Ljava/lang/Throwable;)Ljava/lang/Throwable;
    //   1908: athrow
    //   1909: aload_3
    //   1910: getstatic burp/Zrw7.Zo : Ljava/lang/String;
    //   1913: getstatic burp/Zsyu.Zj : Ljava/lang/Object;
    //   1916: checkcast java/math/BigInteger
    //   1919: invokevirtual intValue : ()I
    //   1922: bipush #32
    //   1924: irem
    //   1925: invokestatic abs : (I)I
    //   1928: invokevirtual charAt : (I)C
    //   1931: invokevirtual append : (C)Ljava/lang/StringBuilder;
    //   1934: pop
    //   1935: iload_2
    //   1936: ifne -> 2460
    //   1939: goto -> 1946
    //   1942: invokestatic a : (Ljava/lang/Throwable;)Ljava/lang/Throwable;
    //   1945: athrow
    //   1946: aload_3
    //   1947: getstatic burp/Zxjm.ZG : Ljava/lang/String;
    //   1950: getstatic burp/Zx58.ZE : Ljava/lang/Object;
    //   1953: checkcast java/math/BigInteger
    //   1956: invokevirtual intValue : ()I
    //   1959: bipush #32
    //   1961: irem
    //   1962: invokestatic abs : (I)I
    //   1965: invokevirtual charAt : (I)C
    //   1968: invokevirtual append : (C)Ljava/lang/StringBuilder;
    //   1971: pop
    //   1972: iload_2
    //   1973: ifne -> 2460
    //   1976: goto -> 1983
    //   1979: invokestatic a : (Ljava/lang/Throwable;)Ljava/lang/Throwable;
    //   1982: athrow
    //   1983: aload_3
    //   1984: getstatic burp/Zg2z.ZE : Ljava/lang/String;
    //   1987: getstatic burp/Zl1q.Zh : Ljava/lang/Object;
    //   1990: checkcast java/math/BigInteger
    //   1993: invokevirtual intValue : ()I
    //   1996: bipush #32
    //   1998: irem
    //   1999: invokestatic abs : (I)I
    //   2002: invokevirtual charAt : (I)C
    //   2005: invokevirtual append : (C)Ljava/lang/StringBuilder;
    //   2008: pop
    //   2009: iload_2
    //   2010: ifne -> 2460
    //   2013: goto -> 2020
    //   2016: invokestatic a : (Ljava/lang/Throwable;)Ljava/lang/Throwable;
    //   2019: athrow
    //   2020: aload_3
    //   2021: getstatic burp/Zsuw.ZK : Ljava/lang/String;
    //   2024: getstatic burp/Zb6e.ZD : Ljava/lang/Object;
    //   2027: checkcast java/math/BigInteger
    //   2030: invokevirtual intValue : ()I
    //   2033: bipush #32
    //   2035: irem
    //   2036: invokestatic abs : (I)I
    //   2039: invokevirtual charAt : (I)C
    //   2042: invokevirtual append : (C)Ljava/lang/StringBuilder;
    //   2045: pop
    //   2046: iload_2
    //   2047: ifne -> 2460
    //   2050: goto -> 2057
    //   2053: invokestatic a : (Ljava/lang/Throwable;)Ljava/lang/Throwable;
    //   2056: athrow
    //   2057: aload_3
    //   2058: getstatic burp/Zegk.Ze : Ljava/lang/String;
    //   2061: getstatic burp/Zgco.Zx : Ljava/lang/Object;
    //   2064: checkcast java/math/BigInteger
    //   2067: invokevirtual intValue : ()I
    //   2070: bipush #32
    //   2072: irem
    //   2073: invokestatic abs : (I)I
    //   2076: invokevirtual charAt : (I)C
    //   2079: invokevirtual append : (C)Ljava/lang/StringBuilder;
    //   2082: pop
    //   2083: iload_2
    //   2084: ifne -> 2460
    //   2087: goto -> 2094
    //   2090: invokestatic a : (Ljava/lang/Throwable;)Ljava/lang/Throwable;
    //   2093: athrow
    //   2094: aload_3
    //   2095: getstatic burp/Ze7y.Zm : Ljava/lang/String;
    //   2098: getstatic burp/Zegk.ZR : Ljava/lang/Object;
    //   2101: checkcast java/math/BigInteger
    //   2104: invokevirtual intValue : ()I
    //   2107: bipush #32
    //   2109: irem
    //   2110: invokestatic abs : (I)I
    //   2113: invokevirtual charAt : (I)C
    //   2116: invokevirtual append : (C)Ljava/lang/StringBuilder;
    //   2119: pop
    //   2120: iload_2
    //   2121: ifne -> 2460
    //   2124: goto -> 2131
    //   2127: invokestatic a : (Ljava/lang/Throwable;)Ljava/lang/Throwable;
    //   2130: athrow
    //   2131: aload_3
    //   2132: getstatic burp/Zlpu.ZA : Ljava/lang/String;
    //   2135: getstatic burp/Zg7j.Zr : Ljava/lang/Object;
    //   2138: checkcast java/math/BigInteger
    //   2141: invokevirtual intValue : ()I
    //   2144: bipush #32
    //   2146: irem
    //   2147: invokestatic abs : (I)I
    //   2150: invokevirtual charAt : (I)C
    //   2153: invokevirtual append : (C)Ljava/lang/StringBuilder;
    //   2156: pop
    //   2157: iload_2
    //   2158: ifne -> 2460
    //   2161: goto -> 2168
    //   2164: invokestatic a : (Ljava/lang/Throwable;)Ljava/lang/Throwable;
    //   2167: athrow
    //   2168: aload_3
    //   2169: getstatic burp/Zeoi.Zh : Ljava/lang/String;
    //   2172: getstatic burp/Zg27.ZQ : Ljava/lang/Object;
    //   2175: checkcast java/math/BigInteger
    //   2178: invokevirtual intValue : ()I
    //   2181: bipush #32
    //   2183: irem
    //   2184: invokestatic abs : (I)I
    //   2187: invokevirtual charAt : (I)C
    //   2190: invokevirtual append : (C)Ljava/lang/StringBuilder;
    //   2193: pop
    //   2194: iload_2
    //   2195: ifne -> 2460
    //   2198: goto -> 2205
    //   2201: invokestatic a : (Ljava/lang/Throwable;)Ljava/lang/Throwable;
    //   2204: athrow
    //   2205: aload_3
    //   2206: getstatic burp/Zex5.Zh : Ljava/lang/String;
    //   2209: getstatic burp/Zxyu.Zp : Ljava/lang/Object;
    //   2212: checkcast java/math/BigInteger
    //   2215: invokevirtual intValue : ()I
    //   2218: bipush #32
    //   2220: irem
    //   2221: invokestatic abs : (I)I
    //   2224: invokevirtual charAt : (I)C
    //   2227: invokevirtual append : (C)Ljava/lang/StringBuilder;
    //   2230: pop
    //   2231: iload_2
    //   2232: ifne -> 2460
    //   2235: goto -> 2242
    //   2238: invokestatic a : (Ljava/lang/Throwable;)Ljava/lang/Throwable;
    //   2241: athrow
    //   2242: aload_3
    //   2243: getstatic burp/Zelz.ZK : Ljava/lang/String;
    //   2246: getstatic burp/Zsk4.Ze : Ljava/lang/Object;
    //   2249: checkcast java/math/BigInteger
    //   2252: invokevirtual intValue : ()I
    //   2255: bipush #32
    //   2257: irem
    //   2258: invokestatic abs : (I)I
    //   2261: invokevirtual charAt : (I)C
    //   2264: invokevirtual append : (C)Ljava/lang/StringBuilder;
    //   2267: pop
    //   2268: iload_2
    //   2269: ifne -> 2460
    //   2272: goto -> 2279
    //   2275: invokestatic a : (Ljava/lang/Throwable;)Ljava/lang/Throwable;
    //   2278: athrow
    //   2279: aload_3
    //   2280: getstatic burp/Zec_.Zv : Ljava/lang/String;
    //   2283: getstatic burp/Zsqi.Zf : Ljava/lang/Object;
    //   2286: checkcast java/math/BigInteger
    //   2289: invokevirtual intValue : ()I
    //   2292: bipush #32
    //   2294: irem
    //   2295: invokestatic abs : (I)I
    //   2298: invokevirtual charAt : (I)C
    //   2301: invokevirtual append : (C)Ljava/lang/StringBuilder;
    //   2304: pop
    //   2305: iload_2
    //   2306: ifne -> 2460
    //   2309: goto -> 2316
    //   2312: invokestatic a : (Ljava/lang/Throwable;)Ljava/lang/Throwable;
    //   2315: athrow
    //   2316: aload_3
    //   2317: getstatic burp/Zmpc.ZT : Ljava/lang/String;
    //   2320: getstatic burp/Zd8.Zs : Ljava/lang/Object;
    //   2323: checkcast java/math/BigInteger
    //   2326: invokevirtual intValue : ()I
    //   2329: bipush #32
    //   2331: irem
    //   2332: invokestatic abs : (I)I
    //   2335: invokevirtual charAt : (I)C
    //   2338: invokevirtual append : (C)Ljava/lang/StringBuilder;
    //   2341: pop
    //   2342: iload_2
    //   2343: ifne -> 2460
    //   2346: goto -> 2353
    //   2349: invokestatic a : (Ljava/lang/Throwable;)Ljava/lang/Throwable;
    //   2352: athrow
    //   2353: aload_3
    //   2354: getstatic burp/Zkde.Zb : Ljava/lang/String;
    //   2357: getstatic burp/Zty4.ZQ : Ljava/lang/Object;
    //   2360: checkcast java/math/BigInteger
    //   2363: invokevirtual intValue : ()I
    //   2366: bipush #32
    //   2368: irem
    //   2369: invokestatic abs : (I)I
    //   2372: invokevirtual charAt : (I)C
    //   2375: invokevirtual append : (C)Ljava/lang/StringBuilder;
    //   2378: pop
    //   2379: iload_2
    //   2380: ifne -> 2460
    //   2383: goto -> 2390
    //   2386: invokestatic a : (Ljava/lang/Throwable;)Ljava/lang/Throwable;
    //   2389: athrow
    //   2390: aload_3
    //   2391: getstatic burp/Zboa.Zq : Ljava/lang/String;
    //   2394: getstatic burp/Zgfm.ZV : Ljava/lang/Object;
    //   2397: checkcast java/math/BigInteger
    //   2400: invokevirtual intValue : ()I
    //   2403: bipush #32
    //   2405: irem
    //   2406: invokestatic abs : (I)I
    //   2409: invokevirtual charAt : (I)C
    //   2412: invokevirtual append : (C)Ljava/lang/StringBuilder;
    //   2415: pop
    //   2416: iload_2
    //   2417: ifne -> 2460
    //   2420: goto -> 2427
    //   2423: invokestatic a : (Ljava/lang/Throwable;)Ljava/lang/Throwable;
    //   2426: athrow
    //   2427: aload_3
    //   2428: getstatic burp/Zbu.ZV : Ljava/lang/String;
    //   2431: getstatic burp/Zrw7.ZV : Ljava/lang/Object;
    //   2434: checkcast java/math/BigInteger
    //   2437: invokevirtual intValue : ()I
    //   2440: bipush #32
    //   2442: irem
    //   2443: invokestatic abs : (I)I
    //   2446: invokevirtual charAt : (I)C
    //   2449: invokevirtual append : (C)Ljava/lang/StringBuilder;
    //   2452: pop
    //   2453: goto -> 2460
    //   2456: invokestatic a : (Ljava/lang/Throwable;)Ljava/lang/Throwable;
    //   2459: athrow
    //   2460: iinc #4, 1
    //   2463: iload_2
    //   2464: ifne -> 1128
    //   2467: aload_3
    //   2468: invokevirtual toString : ()Ljava/lang/String;
    //   2471: putstatic burp/Ztzw.Zi : Ljava/lang/String;
    //   2474: sipush #-20509
    //   2477: sipush #-18506
    //   2480: invokestatic a : (II)Ljava/lang/String;
    //   2483: iconst_1
    //   2484: ldc burp/Ztt0
    //   2486: invokevirtual getClassLoader : ()Ljava/lang/ClassLoader;
    //   2489: invokestatic forName : (Ljava/lang/String;ZLjava/lang/ClassLoader;)Ljava/lang/Class;
    //   2492: invokevirtual getDeclaredFields : ()[Ljava/lang/reflect/Field;
    //   2495: astore #4
    //   2497: aload #4
    //   2499: arraylength
    //   2500: istore #5
    //   2502: iconst_0
    //   2503: istore #6
    //   2505: iload #6
    //   2507: iload #5
    //   2509: if_icmpge -> 2647
    //   2512: aload #4
    //   2514: iload #6
    //   2516: aaload
    //   2517: astore #7
    //   2519: aload #7
    //   2521: invokevirtual getModifiers : ()I
    //   2524: invokestatic isStatic : (I)Z
    //   2527: ifne -> 2537
    //   2530: goto -> 2640
    //   2533: invokestatic a : (Ljava/lang/Throwable;)Ljava/lang/Throwable;
    //   2536: athrow
    //   2537: aload #7
    //   2539: invokevirtual getType : ()Ljava/lang/Class;
    //   2542: astore #8
    //   2544: aload #8
    //   2546: ifnull -> 2627
    //   2549: aload #8
    //   2551: invokevirtual isPrimitive : ()Z
    //   2554: ifne -> 2627
    //   2557: goto -> 2564
    //   2560: invokestatic a : (Ljava/lang/Throwable;)Ljava/lang/Throwable;
    //   2563: athrow
    //   2564: aload #8
    //   2566: invokevirtual getPackage : ()Ljava/lang/Package;
    //   2569: ifnull -> 2627
    //   2572: goto -> 2579
    //   2575: invokestatic a : (Ljava/lang/Throwable;)Ljava/lang/Throwable;
    //   2578: athrow
    //   2579: aload #8
    //   2581: invokevirtual getPackage : ()Ljava/lang/Package;
    //   2584: invokevirtual getName : ()Ljava/lang/String;
    //   2587: ifnull -> 2627
    //   2590: goto -> 2597
    //   2593: invokestatic a : (Ljava/lang/Throwable;)Ljava/lang/Throwable;
    //   2596: athrow
    //   2597: aload #8
    //   2599: invokevirtual getPackage : ()Ljava/lang/Package;
    //   2602: invokevirtual getName : ()Ljava/lang/String;
    //   2605: sipush #-20512
    //   2608: sipush #31002
    //   2611: invokestatic a : (II)Ljava/lang/String;
    //   2614: invokevirtual startsWith : (Ljava/lang/String;)Z
    //   2617: ifne -> 2627
    //   2620: goto -> 2627
    //   2623: invokestatic a : (Ljava/lang/Throwable;)Ljava/lang/Throwable;
    //   2626: athrow
    //   2627: aload #7
    //   2629: iconst_1
    //   2630: invokevirtual setAccessible : (Z)V
    //   2633: aload #7
    //   2635: aconst_null
    //   2636: invokevirtual get : (Ljava/lang/Object;)Ljava/lang/Object;
    //   2639: pop
    //   2640: iinc #6, 1
    //   2643: iload_2
    //   2644: ifne -> 2505
    //   2647: sipush #-20511
    //   2650: sipush #29933
    //   2653: invokestatic a : (II)Ljava/lang/String;
    //   2656: invokestatic forName : (Ljava/lang/String;)Ljava/lang/Class;
    //   2659: invokevirtual getDeclaredMethods : ()[Ljava/lang/reflect/Method;
    //   2662: astore #4
    //   2664: aload #4
    //   2666: arraylength
    //   2667: istore #5
    //   2669: iconst_0
    //   2670: istore #6
    //   2672: iload #6
    //   2674: iload #5
    //   2676: if_icmpge -> 2809
    //   2679: aload #4
    //   2681: iload #6
    //   2683: aaload
    //   2684: astore #7
    //   2686: aload #7
    //   2688: invokevirtual getParameterTypes : ()[Ljava/lang/Class;
    //   2691: pop
    //   2692: aload #7
    //   2694: invokevirtual getModifiers : ()I
    //   2697: invokestatic isStatic : (I)Z
    //   2700: ifeq -> 2795
    //   2703: aload #7
    //   2705: invokevirtual getParameterTypes : ()[Ljava/lang/Class;
    //   2708: arraylength
    //   2709: iconst_2
    //   2710: if_icmpne -> 2795
    //   2713: goto -> 2720
    //   2716: invokestatic a : (Ljava/lang/Throwable;)Ljava/lang/Throwable;
    //   2719: athrow
    //   2720: aload #7
    //   2722: invokevirtual getReturnType : ()Ljava/lang/Class;
    //   2725: getstatic java/lang/Void.TYPE : Ljava/lang/Class;
    //   2728: invokevirtual equals : (Ljava/lang/Object;)Z
    //   2731: ifeq -> 2795
    //   2734: goto -> 2741
    //   2737: invokestatic a : (Ljava/lang/Throwable;)Ljava/lang/Throwable;
    //   2740: athrow
    //   2741: aload #7
    //   2743: iconst_1
    //   2744: invokevirtual setAccessible : (Z)V
    //   2747: aload #7
    //   2749: aconst_null
    //   2750: iconst_2
    //   2751: anewarray java/lang/Object
    //   2754: dup
    //   2755: iconst_0
    //   2756: aload_0
    //   2757: aastore
    //   2758: dup
    //   2759: iconst_1
    //   2760: aload_1
    //   2761: ifnonnull -> 2779
    //   2764: goto -> 2771
    //   2767: invokestatic a : (Ljava/lang/Throwable;)Ljava/lang/Throwable;
    //   2770: athrow
    //   2771: aload_1
    //   2772: goto -> 2786
    //   2775: invokestatic a : (Ljava/lang/Throwable;)Ljava/lang/Throwable;
    //   2778: athrow
    //   2779: aload_1
    //   2780: checkcast [B
    //   2783: invokevirtual clone : ()Ljava/lang/Object;
    //   2786: aastore
    //   2787: invokevirtual invoke : (Ljava/lang/Object;[Ljava/lang/Object;)Ljava/lang/Object;
    //   2790: pop
    //   2791: iload_2
    //   2792: ifne -> 2809
    //   2795: iinc #6, 1
    //   2798: iload_2
    //   2799: ifne -> 2672
    //   2802: goto -> 2809
    //   2805: invokestatic a : (Ljava/lang/Throwable;)Ljava/lang/Throwable;
    //   2808: athrow
    //   2809: getstatic burp/Zlh2.Zc : Ljava/lang/Object;
    //   2812: checkcast java/math/BigInteger
    //   2815: invokevirtual toByteArray : ()[B
    //   2818: astore #4
    //   2820: iconst_0
    //   2821: istore #6
    //   2823: iconst_0
    //   2824: istore #7
    //   2826: iload #7
    //   2828: aload #4
    //   2830: arraylength
    //   2831: if_icmpge -> 2977
    //   2834: aload #4
    //   2836: iload #7
    //   2838: baload
    //   2839: istore #8
    //   2841: iload #8
    //   2843: bipush #48
    //   2845: if_icmplt -> 2862
    //   2848: iload #8
    //   2850: bipush #57
    //   2852: if_icmple -> 2960
    //   2855: goto -> 2862
    //   2858: invokestatic a : (Ljava/lang/Throwable;)Ljava/lang/Throwable;
    //   2861: athrow
    //   2862: iload #8
    //   2864: bipush #65
    //   2866: if_icmplt -> 2890
    //   2869: goto -> 2876
    //   2872: invokestatic a : (Ljava/lang/Throwable;)Ljava/lang/Throwable;
    //   2875: athrow
    //   2876: iload #8
    //   2878: bipush #90
    //   2880: if_icmple -> 2960
    //   2883: goto -> 2890
    //   2886: invokestatic a : (Ljava/lang/Throwable;)Ljava/lang/Throwable;
    //   2889: athrow
    //   2890: iload #8
    //   2892: bipush #97
    //   2894: if_icmplt -> 2918
    //   2897: goto -> 2904
    //   2900: invokestatic a : (Ljava/lang/Throwable;)Ljava/lang/Throwable;
    //   2903: athrow
    //   2904: iload #8
    //   2906: bipush #122
    //   2908: if_icmple -> 2960
    //   2911: goto -> 2918
    //   2914: invokestatic a : (Ljava/lang/Throwable;)Ljava/lang/Throwable;
    //   2917: athrow
    //   2918: iload #8
    //   2920: bipush #43
    //   2922: if_icmpeq -> 2960
    //   2925: goto -> 2932
    //   2928: invokestatic a : (Ljava/lang/Throwable;)Ljava/lang/Throwable;
    //   2931: athrow
    //   2932: iload #8
    //   2934: bipush #47
    //   2936: if_icmpeq -> 2960
    //   2939: goto -> 2946
    //   2942: invokestatic a : (Ljava/lang/Throwable;)Ljava/lang/Throwable;
    //   2945: athrow
    //   2946: iload #8
    //   2948: bipush #61
    //   2950: if_icmpne -> 2970
    //   2953: goto -> 2960
    //   2956: invokestatic a : (Ljava/lang/Throwable;)Ljava/lang/Throwable;
    //   2959: athrow
    //   2960: iinc #6, 1
    //   2963: goto -> 2970
    //   2966: invokestatic a : (Ljava/lang/Throwable;)Ljava/lang/Throwable;
    //   2969: athrow
    //   2970: iinc #7, 1
    //   2973: iload_2
    //   2974: ifne -> 2826
    //   2977: iload #6
    //   2979: newarray byte
    //   2981: astore #7
    //   2983: iconst_0
    //   2984: istore #8
    //   2986: iconst_0
    //   2987: istore #9
    //   2989: iload #9
    //   2991: aload #4
    //   2993: arraylength
    //   2994: if_icmpge -> 3147
    //   2997: aload #4
    //   2999: iload #9
    //   3001: baload
    //   3002: istore #10
    //   3004: iload #10
    //   3006: bipush #48
    //   3008: if_icmplt -> 3025
    //   3011: iload #10
    //   3013: bipush #57
    //   3015: if_icmple -> 3123
    //   3018: goto -> 3025
    //   3021: invokestatic a : (Ljava/lang/Throwable;)Ljava/lang/Throwable;
    //   3024: athrow
    //   3025: iload #10
    //   3027: bipush #65
    //   3029: if_icmplt -> 3053
    //   3032: goto -> 3039
    //   3035: invokestatic a : (Ljava/lang/Throwable;)Ljava/lang/Throwable;
    //   3038: athrow
    //   3039: iload #10
    //   3041: bipush #90
    //   3043: if_icmple -> 3123
    //   3046: goto -> 3053
    //   3049: invokestatic a : (Ljava/lang/Throwable;)Ljava/lang/Throwable;
    //   3052: athrow
    //   3053: iload #10
    //   3055: bipush #97
    //   3057: if_icmplt -> 3081
    //   3060: goto -> 3067
    //   3063: invokestatic a : (Ljava/lang/Throwable;)Ljava/lang/Throwable;
    //   3066: athrow
    //   3067: iload #10
    //   3069: bipush #122
    //   3071: if_icmple -> 3123
    //   3074: goto -> 3081
    //   3077: invokestatic a : (Ljava/lang/Throwable;)Ljava/lang/Throwable;
    //   3080: athrow
    //   3081: iload #10
    //   3083: bipush #43
    //   3085: if_icmpeq -> 3123
    //   3088: goto -> 3095
    //   3091: invokestatic a : (Ljava/lang/Throwable;)Ljava/lang/Throwable;
    //   3094: athrow
    //   3095: iload #10
    //   3097: bipush #47
    //   3099: if_icmpeq -> 3123
    //   3102: goto -> 3109
    //   3105: invokestatic a : (Ljava/lang/Throwable;)Ljava/lang/Throwable;
    //   3108: athrow
    //   3109: iload #10
    //   3111: bipush #61
    //   3113: if_icmpne -> 3140
    //   3116: goto -> 3123
    //   3119: invokestatic a : (Ljava/lang/Throwable;)Ljava/lang/Throwable;
    //   3122: athrow
    //   3123: aload #7
    //   3125: iload #8
    //   3127: iload #10
    //   3129: bastore
    //   3130: iinc #8, 1
    //   3133: goto -> 3140
    //   3136: invokestatic a : (Ljava/lang/Throwable;)Ljava/lang/Throwable;
    //   3139: athrow
    //   3140: iinc #9, 1
    //   3143: iload_2
    //   3144: ifne -> 2989
    //   3147: aload #7
    //   3149: astore #5
    //   3151: aload #5
    //   3153: astore #4
    //   3155: aload #4
    //   3157: arraylength
    //   3158: istore #6
    //   3160: aload #4
    //   3162: iload #6
    //   3164: iconst_1
    //   3165: isub
    //   3166: baload
    //   3167: bipush #61
    //   3169: if_icmpne -> 3179
    //   3172: iinc #6, -1
    //   3175: iload_2
    //   3176: ifne -> 3160
    //   3179: iload #6
    //   3181: aload #4
    //   3183: arraylength
    //   3184: iconst_4
    //   3185: idiv
    //   3186: isub
    //   3187: newarray byte
    //   3189: astore #7
    //   3191: iconst_0
    //   3192: istore #8
    //   3194: iload #8
    //   3196: aload #4
    //   3198: arraylength
    //   3199: if_icmpge -> 3479
    //   3202: aload #4
    //   3204: iload #8
    //   3206: baload
    //   3207: bipush #61
    //   3209: if_icmpne -> 3229
    //   3212: aload #4
    //   3214: iload #8
    //   3216: iconst_0
    //   3217: bastore
    //   3218: iload_2
    //   3219: ifne -> 3472
    //   3222: goto -> 3229
    //   3225: invokestatic a : (Ljava/lang/Throwable;)Ljava/lang/Throwable;
    //   3228: athrow
    //   3229: aload #4
    //   3231: iload #8
    //   3233: baload
    //   3234: bipush #47
    //   3236: if_icmpne -> 3264
    //   3239: goto -> 3246
    //   3242: invokestatic a : (Ljava/lang/Throwable;)Ljava/lang/Throwable;
    //   3245: athrow
    //   3246: aload #4
    //   3248: iload #8
    //   3250: bipush #63
    //   3252: bastore
    //   3253: iload_2
    //   3254: ifne -> 3472
    //   3257: goto -> 3264
    //   3260: invokestatic a : (Ljava/lang/Throwable;)Ljava/lang/Throwable;
    //   3263: athrow
    //   3264: aload #4
    //   3266: iload #8
    //   3268: baload
    //   3269: bipush #43
    //   3271: if_icmpne -> 3299
    //   3274: goto -> 3281
    //   3277: invokestatic a : (Ljava/lang/Throwable;)Ljava/lang/Throwable;
    //   3280: athrow
    //   3281: aload #4
    //   3283: iload #8
    //   3285: bipush #62
    //   3287: bastore
    //   3288: iload_2
    //   3289: ifne -> 3472
    //   3292: goto -> 3299
    //   3295: invokestatic a : (Ljava/lang/Throwable;)Ljava/lang/Throwable;
    //   3298: athrow
    //   3299: aload #4
    //   3301: iload #8
    //   3303: baload
    //   3304: bipush #48
    //   3306: if_icmplt -> 3358
    //   3309: goto -> 3316
    //   3312: invokestatic a : (Ljava/lang/Throwable;)Ljava/lang/Throwable;
    //   3315: athrow
    //   3316: aload #4
    //   3318: iload #8
    //   3320: baload
    //   3321: bipush #57
    //   3323: if_icmpgt -> 3358
    //   3326: goto -> 3333
    //   3329: invokestatic a : (Ljava/lang/Throwable;)Ljava/lang/Throwable;
    //   3332: athrow
    //   3333: aload #4
    //   3335: iload #8
    //   3337: aload #4
    //   3339: iload #8
    //   3341: baload
    //   3342: bipush #-4
    //   3344: isub
    //   3345: i2b
    //   3346: bastore
    //   3347: iload_2
    //   3348: ifne -> 3472
    //   3351: goto -> 3358
    //   3354: invokestatic a : (Ljava/lang/Throwable;)Ljava/lang/Throwable;
    //   3357: athrow
    //   3358: aload #4
    //   3360: iload #8
    //   3362: baload
    //   3363: bipush #97
    //   3365: if_icmplt -> 3417
    //   3368: goto -> 3375
    //   3371: invokestatic a : (Ljava/lang/Throwable;)Ljava/lang/Throwable;
    //   3374: athrow
    //   3375: aload #4
    //   3377: iload #8
    //   3379: baload
    //   3380: bipush #122
    //   3382: if_icmpgt -> 3417
    //   3385: goto -> 3392
    //   3388: invokestatic a : (Ljava/lang/Throwable;)Ljava/lang/Throwable;
    //   3391: athrow
    //   3392: aload #4
    //   3394: iload #8
    //   3396: aload #4
    //   3398: iload #8
    //   3400: baload
    //   3401: bipush #71
    //   3403: isub
    //   3404: i2b
    //   3405: bastore
    //   3406: iload_2
    //   3407: ifne -> 3472
    //   3410: goto -> 3417
    //   3413: invokestatic a : (Ljava/lang/Throwable;)Ljava/lang/Throwable;
    //   3416: athrow
    //   3417: aload #4
    //   3419: iload #8
    //   3421: baload
    //   3422: bipush #65
    //   3424: if_icmplt -> 3472
    //   3427: goto -> 3434
    //   3430: invokestatic a : (Ljava/lang/Throwable;)Ljava/lang/Throwable;
    //   3433: athrow
    //   3434: aload #4
    //   3436: iload #8
    //   3438: baload
    //   3439: bipush #90
    //   3441: if_icmpgt -> 3472
    //   3444: goto -> 3451
    //   3447: invokestatic a : (Ljava/lang/Throwable;)Ljava/lang/Throwable;
    //   3450: athrow
    //   3451: aload #4
    //   3453: iload #8
    //   3455: aload #4
    //   3457: iload #8
    //   3459: baload
    //   3460: bipush #65
    //   3462: isub
    //   3463: i2b
    //   3464: bastore
    //   3465: goto -> 3472
    //   3468: invokestatic a : (Ljava/lang/Throwable;)Ljava/lang/Throwable;
    //   3471: athrow
    //   3472: iinc #8, 1
    //   3475: iload_2
    //   3476: ifne -> 3194
    //   3479: iconst_0
    //   3480: istore #8
    //   3482: iconst_0
    //   3483: istore #9
    //   3485: iload #9
    //   3487: aload #7
    //   3489: arraylength
    //   3490: iconst_2
    //   3491: isub
    //   3492: if_icmpge -> 3601
    //   3495: aload #7
    //   3497: iload #9
    //   3499: aload #4
    //   3501: iload #8
    //   3503: baload
    //   3504: iconst_2
    //   3505: ishl
    //   3506: sipush #255
    //   3509: iand
    //   3510: aload #4
    //   3512: iload #8
    //   3514: iconst_1
    //   3515: iadd
    //   3516: baload
    //   3517: iconst_4
    //   3518: iushr
    //   3519: iconst_3
    //   3520: iand
    //   3521: ior
    //   3522: i2b
    //   3523: bastore
    //   3524: aload #7
    //   3526: iload #9
    //   3528: iconst_1
    //   3529: iadd
    //   3530: aload #4
    //   3532: iload #8
    //   3534: iconst_1
    //   3535: iadd
    //   3536: baload
    //   3537: iconst_4
    //   3538: ishl
    //   3539: sipush #255
    //   3542: iand
    //   3543: aload #4
    //   3545: iload #8
    //   3547: iconst_2
    //   3548: iadd
    //   3549: baload
    //   3550: iconst_2
    //   3551: iushr
    //   3552: bipush #15
    //   3554: iand
    //   3555: ior
    //   3556: i2b
    //   3557: bastore
    //   3558: aload #7
    //   3560: iload #9
    //   3562: iconst_2
    //   3563: iadd
    //   3564: aload #4
    //   3566: iload #8
    //   3568: iconst_2
    //   3569: iadd
    //   3570: baload
    //   3571: bipush #6
    //   3573: ishl
    //   3574: sipush #255
    //   3577: iand
    //   3578: aload #4
    //   3580: iload #8
    //   3582: iconst_3
    //   3583: iadd
    //   3584: baload
    //   3585: bipush #63
    //   3587: iand
    //   3588: ior
    //   3589: i2b
    //   3590: bastore
    //   3591: iinc #8, 4
    //   3594: iinc #9, 3
    //   3597: iload_2
    //   3598: ifne -> 3485
    //   3601: iload #9
    //   3603: aload #7
    //   3605: arraylength
    //   3606: if_icmpge -> 3645
    //   3609: aload #7
    //   3611: iload #9
    //   3613: aload #4
    //   3615: iload #8
    //   3617: baload
    //   3618: iconst_2
    //   3619: ishl
    //   3620: sipush #255
    //   3623: iand
    //   3624: aload #4
    //   3626: iload #8
    //   3628: iconst_1
    //   3629: iadd
    //   3630: baload
    //   3631: iconst_4
    //   3632: iushr
    //   3633: iconst_3
    //   3634: iand
    //   3635: ior
    //   3636: i2b
    //   3637: bastore
    //   3638: goto -> 3645
    //   3641: invokestatic a : (Ljava/lang/Throwable;)Ljava/lang/Throwable;
    //   3644: athrow
    //   3645: iinc #9, 1
    //   3648: iload #9
    //   3650: aload #7
    //   3652: arraylength
    //   3653: if_icmpge -> 3695
    //   3656: aload #7
    //   3658: iload #9
    //   3660: aload #4
    //   3662: iload #8
    //   3664: iconst_1
    //   3665: iadd
    //   3666: baload
    //   3667: iconst_4
    //   3668: ishl
    //   3669: sipush #255
    //   3672: iand
    //   3673: aload #4
    //   3675: iload #8
    //   3677: iconst_2
    //   3678: iadd
    //   3679: baload
    //   3680: iconst_2
    //   3681: iushr
    //   3682: bipush #15
    //   3684: iand
    //   3685: ior
    //   3686: i2b
    //   3687: bastore
    //   3688: goto -> 3695
    //   3691: invokestatic a : (Ljava/lang/Throwable;)Ljava/lang/Throwable;
    //   3694: athrow
    //   3695: aload #7
    //   3697: astore #5
    //   3699: getstatic burp/Zelz.ZK : Ljava/lang/String;
    //   3702: getstatic burp/Zly7.Zt : Ljava/lang/Object;
    //   3705: checkcast java/math/BigInteger
    //   3708: invokevirtual intValue : ()I
    //   3711: bipush #32
    //   3713: irem
    //   3714: invokestatic abs : (I)I
    //   3717: invokevirtual charAt : (I)C
    //   3720: getstatic burp/Zl1q.ZY : Ljava/lang/String;
    //   3723: getstatic burp/Zsqi.Zf : Ljava/lang/Object;
    //   3726: checkcast java/math/BigInteger
    //   3729: invokevirtual intValue : ()I
    //   3732: bipush #32
    //   3734: irem
    //   3735: invokestatic abs : (I)I
    //   3738: invokevirtual charAt : (I)C
    //   3741: if_icmple -> 3848
    //   3744: getstatic burp/Zegk.Ze : Ljava/lang/String;
    //   3747: getstatic burp/Zsmn.Zq : Ljava/lang/Object;
    //   3750: checkcast java/math/BigInteger
    //   3753: invokevirtual intValue : ()I
    //   3756: bipush #32
    //   3758: irem
    //   3759: invokestatic abs : (I)I
    //   3762: invokevirtual charAt : (I)C
    //   3765: getstatic burp/Zvi.ZR : Ljava/lang/String;
    //   3768: getstatic burp/Zry9.Zw : Ljava/lang/Object;
    //   3771: checkcast java/math/BigInteger
    //   3774: invokevirtual intValue : ()I
    //   3777: bipush #32
    //   3779: irem
    //   3780: invokestatic abs : (I)I
    //   3783: invokevirtual charAt : (I)C
    //   3786: if_icmpgt -> 3848
    //   3789: goto -> 3796
    //   3792: invokestatic a : (Ljava/lang/Throwable;)Ljava/lang/Throwable;
    //   3795: athrow
    //   3796: getstatic burp/Zelz.ZK : Ljava/lang/String;
    //   3799: getstatic burp/Zsx6.ZN : Ljava/lang/Object;
    //   3802: checkcast java/math/BigInteger
    //   3805: invokevirtual intValue : ()I
    //   3808: bipush #32
    //   3810: irem
    //   3811: invokestatic abs : (I)I
    //   3814: invokevirtual charAt : (I)C
    //   3817: getstatic burp/Zztx.Zg : Ljava/lang/String;
    //   3820: getstatic burp/Zsbd.Zh : Ljava/lang/Object;
    //   3823: checkcast java/math/BigInteger
    //   3826: invokevirtual intValue : ()I
    //   3829: bipush #32
    //   3831: irem
    //   3832: invokestatic abs : (I)I
    //   3835: invokevirtual charAt : (I)C
    //   3838: if_icmple -> 3856
    //   3841: goto -> 3848
    //   3844: invokestatic a : (Ljava/lang/Throwable;)Ljava/lang/Throwable;
    //   3847: athrow
    //   3848: iconst_1
    //   3849: goto -> 3857
    //   3852: invokestatic a : (Ljava/lang/Throwable;)Ljava/lang/Throwable;
    //   3855: athrow
    //   3856: iconst_0
    //   3857: ireturn
    //   3858: astore_3
    //   3859: new java/lang/Exception
    //   3862: dup
    //   3863: aload_3
    //   3864: invokevirtual getMessage : ()Ljava/lang/String;
    //   3867: invokespecial <init> : (Ljava/lang/String;)V
    //   3870: athrow
    // Exception table:
    //   from	to	target	type
    //   4	3857	3858	java/lang/Throwable
    //   33	47	50	java/lang/Throwable
    //   40	61	64	java/lang/Throwable
    //   54	75	78	java/lang/Throwable
    //   68	89	92	java/lang/Throwable
    //   82	103	106	java/lang/Throwable
    //   96	117	120	java/lang/Throwable
    //   110	131	134	java/lang/Throwable
    //   124	145	148	java/lang/Throwable
    //   138	155	158	java/lang/Throwable
    //   194	208	211	java/lang/Throwable
    //   201	222	225	java/lang/Throwable
    //   215	236	239	java/lang/Throwable
    //   229	250	253	java/lang/Throwable
    //   243	264	267	java/lang/Throwable
    //   257	278	281	java/lang/Throwable
    //   271	292	295	java/lang/Throwable
    //   285	306	309	java/lang/Throwable
    //   299	323	326	java/lang/Throwable
    //   387	405	408	java/lang/Throwable
    //   396	421	424	java/lang/Throwable
    //   412	438	441	java/lang/Throwable
    //   428	454	457	java/lang/Throwable
    //   445	471	474	java/lang/Throwable
    //   461	487	490	java/lang/Throwable
    //   478	503	506	java/lang/Throwable
    //   494	526	529	java/lang/Throwable
    //   510	542	545	java/lang/Throwable
    //   533	558	561	java/lang/Throwable
    //   549	581	584	java/lang/Throwable
    //   565	597	600	java/lang/Throwable
    //   588	613	616	java/lang/Throwable
    //   604	632	635	java/lang/Throwable
    //   762	797	800	java/lang/Throwable
    //   804	845	848	java/lang/Throwable
    //   1135	1310	1313	java/lang/Throwable
    //   1280	1347	1350	java/lang/Throwable
    //   1317	1384	1387	java/lang/Throwable
    //   1354	1421	1424	java/lang/Throwable
    //   1391	1458	1461	java/lang/Throwable
    //   1428	1495	1498	java/lang/Throwable
    //   1465	1532	1535	java/lang/Throwable
    //   1502	1569	1572	java/lang/Throwable
    //   1539	1606	1609	java/lang/Throwable
    //   1576	1643	1646	java/lang/Throwable
    //   1613	1680	1683	java/lang/Throwable
    //   1650	1717	1720	java/lang/Throwable
    //   1687	1754	1757	java/lang/Throwable
    //   1724	1791	1794	java/lang/Throwable
    //   1761	1828	1831	java/lang/Throwable
    //   1798	1865	1868	java/lang/Throwable
    //   1835	1902	1905	java/lang/Throwable
    //   1872	1939	1942	java/lang/Throwable
    //   1909	1976	1979	java/lang/Throwable
    //   1946	2013	2016	java/lang/Throwable
    //   1983	2050	2053	java/lang/Throwable
    //   2020	2087	2090	java/lang/Throwable
    //   2057	2124	2127	java/lang/Throwable
    //   2094	2161	2164	java/lang/Throwable
    //   2131	2198	2201	java/lang/Throwable
    //   2168	2235	2238	java/lang/Throwable
    //   2205	2272	2275	java/lang/Throwable
    //   2242	2309	2312	java/lang/Throwable
    //   2279	2346	2349	java/lang/Throwable
    //   2316	2383	2386	java/lang/Throwable
    //   2353	2420	2423	java/lang/Throwable
    //   2390	2453	2456	java/lang/Throwable
    //   2519	2533	2533	java/lang/Throwable
    //   2544	2557	2560	java/lang/Throwable
    //   2549	2572	2575	java/lang/Throwable
    //   2564	2590	2593	java/lang/Throwable
    //   2579	2620	2623	java/lang/Throwable
    //   2686	2713	2716	java/lang/Throwable
    //   2703	2734	2737	java/lang/Throwable
    //   2720	2764	2767	java/lang/Throwable
    //   2741	2775	2775	java/lang/Throwable
    //   2786	2802	2805	java/lang/Throwable
    //   2841	2855	2858	java/lang/Throwable
    //   2848	2869	2872	java/lang/Throwable
    //   2862	2883	2886	java/lang/Throwable
    //   2876	2897	2900	java/lang/Throwable
    //   2890	2911	2914	java/lang/Throwable
    //   2904	2925	2928	java/lang/Throwable
    //   2918	2939	2942	java/lang/Throwable
    //   2932	2953	2956	java/lang/Throwable
    //   2946	2963	2966	java/lang/Throwable
    //   3004	3018	3021	java/lang/Throwable
    //   3011	3032	3035	java/lang/Throwable
    //   3025	3046	3049	java/lang/Throwable
    //   3039	3060	3063	java/lang/Throwable
    //   3053	3074	3077	java/lang/Throwable
    //   3067	3088	3091	java/lang/Throwable
    //   3081	3102	3105	java/lang/Throwable
    //   3095	3116	3119	java/lang/Throwable
    //   3109	3133	3136	java/lang/Throwable
    //   3202	3222	3225	java/lang/Throwable
    //   3212	3239	3242	java/lang/Throwable
    //   3229	3257	3260	java/lang/Throwable
    //   3246	3274	3277	java/lang/Throwable
    //   3264	3292	3295	java/lang/Throwable
    //   3281	3309	3312	java/lang/Throwable
    //   3299	3326	3329	java/lang/Throwable
    //   3316	3351	3354	java/lang/Throwable
    //   3333	3368	3371	java/lang/Throwable
    //   3358	3385	3388	java/lang/Throwable
    //   3375	3410	3413	java/lang/Throwable
    //   3392	3427	3430	java/lang/Throwable
    //   3417	3444	3447	java/lang/Throwable
    //   3434	3465	3468	java/lang/Throwable
    //   3601	3638	3641	java/lang/Throwable
    //   3645	3688	3691	java/lang/Throwable
    //   3699	3789	3792	java/lang/Throwable
    //   3744	3841	3844	java/lang/Throwable
    //   3796	3852	3852	java/lang/Throwable
  }
  
  static {
    // Byte code:
    //   0: bipush #9
    //   2: anewarray java/lang/String
    //   5: astore #5
    //   7: iconst_0
    //   8: istore_3
    //   9: ldc 'ZHS$9Ow;0g]{jdV\\tSLIO\\t[EQGO-LQnK~{{e4aYB2N w\\\r5\\t_`:M\\nm3(bbV&%kh_g570kD/)SJt2%;H\\tA&F\\tWC\\tf`M!%{'
    //   11: dup
    //   12: astore_2
    //   13: invokevirtual length : ()I
    //   16: istore #4
    //   18: bipush #32
    //   20: istore_1
    //   21: iconst_m1
    //   22: istore_0
    //   23: bipush #37
    //   25: iinc #0, 1
    //   28: aload_2
    //   29: iload_0
    //   30: dup
    //   31: iload_1
    //   32: iadd
    //   33: invokevirtual substring : (II)Ljava/lang/String;
    //   36: iconst_m1
    //   37: goto -> 143
    //   40: aload #5
    //   42: swap
    //   43: iload_3
    //   44: iinc #3, 1
    //   47: swap
    //   48: aastore
    //   49: iload_0
    //   50: iload_1
    //   51: iadd
    //   52: dup
    //   53: istore_0
    //   54: iload #4
    //   56: if_icmpge -> 68
    //   59: aload_2
    //   60: iload_0
    //   61: invokevirtual charAt : (I)C
    //   64: istore_1
    //   65: goto -> 23
    //   68: ldc '0z< *XH]gB}%BB7".V/'
    //   70: dup
    //   71: astore_2
    //   72: invokevirtual length : ()I
    //   75: istore #4
    //   77: bipush #9
    //   79: istore_1
    //   80: iconst_m1
    //   81: istore_0
    //   82: bipush #31
    //   84: iinc #0, 1
    //   87: aload_2
    //   88: iload_0
    //   89: dup
    //   90: iload_1
    //   91: iadd
    //   92: invokevirtual substring : (II)Ljava/lang/String;
    //   95: iconst_0
    //   96: goto -> 143
    //   99: aload #5
    //   101: swap
    //   102: iload_3
    //   103: iinc #3, 1
    //   106: swap
    //   107: aastore
    //   108: iload_0
    //   109: iload_1
    //   110: iadd
    //   111: dup
    //   112: istore_0
    //   113: iload #4
    //   115: if_icmpge -> 127
    //   118: aload_2
    //   119: iload_0
    //   120: invokevirtual charAt : (I)C
    //   123: istore_1
    //   124: goto -> 82
    //   127: aload #5
    //   129: putstatic burp/Zex5.a : [Ljava/lang/String;
    //   132: bipush #9
    //   134: anewarray java/lang/String
    //   137: putstatic burp/Zex5.b : [Ljava/lang/String;
    //   140: goto -> 300
    //   143: dup_x2
    //   144: pop
    //   145: invokevirtual toCharArray : ()[C
    //   148: dup_x1
    //   149: arraylength
    //   150: dup_x2
    //   151: pop
    //   152: iconst_0
    //   153: istore #6
    //   155: dup2_x1
    //   156: pop2
    //   157: dup_x2
    //   158: iconst_1
    //   159: if_icmpgt -> 259
    //   162: dup2
    //   163: swap
    //   164: iload #6
    //   166: dup2_x1
    //   167: caload
    //   168: swap
    //   169: iload #6
    //   171: bipush #7
    //   173: irem
    //   174: tableswitch default -> 241, 0 -> 212, 1 -> 217, 2 -> 222, 3 -> 227, 4 -> 231, 5 -> 236
    //   212: bipush #21
    //   214: goto -> 243
    //   217: bipush #70
    //   219: goto -> 243
    //   222: bipush #126
    //   224: goto -> 243
    //   227: iconst_1
    //   228: goto -> 243
    //   231: bipush #82
    //   233: goto -> 243
    //   236: bipush #14
    //   238: goto -> 243
    //   241: bipush #33
    //   243: ixor
    //   244: ixor
    //   245: i2c
    //   246: castore
    //   247: iinc #6, 1
    //   250: dup
    //   251: ifne -> 259
    //   254: dup2
    //   255: dup_x1
    //   256: goto -> 166
    //   259: dup2_x1
    //   260: pop2
    //   261: dup_x2
    //   262: iload #6
    //   264: if_icmpgt -> 162
    //   267: pop
    //   268: new java/lang/String
    //   271: dup_x1
    //   272: swap
    //   273: invokespecial <init> : ([C)V
    //   276: invokevirtual intern : ()Ljava/lang/String;
    //   279: swap
    //   280: pop
    //   281: swap
    //   282: tableswitch default -> 40, 0 -> 99
    //   300: sipush #-20498
    //   303: sipush #-1746
    //   306: invokestatic a : (II)Ljava/lang/String;
    //   309: putstatic burp/Zex5.Zh : Ljava/lang/String;
    //   312: new java/math/BigInteger
    //   315: dup
    //   316: sipush #-20505
    //   319: sipush #-17570
    //   322: invokestatic a : (II)Ljava/lang/String;
    //   325: invokespecial <init> : (Ljava/lang/String;)V
    //   328: putstatic burp/Zex5.Zb : Ljava/lang/Object;
    //   331: return
  }
  
  private static Throwable a(Throwable paramThrowable) {
    return paramThrowable;
  }
  
  private static String a(int paramInt1, int paramInt2) {
    int i = (paramInt1 ^ 0xFFFFAFE6) & 0xFFFF;
    if (b[i] == null) {
      char[] arrayOfChar = a[i].toCharArray();
      switch (arrayOfChar[0] & 0xFF) {
        case 0:
        
        case 1:
        
        case 2:
        
        case 3:
        
        case 4:
        
        case 5:
        
        case 6:
        
        case 7:
        
        case 8:
        
        case 9:
        
        case 10:
        
        case 11:
        
        case 12:
        
        case 13:
        
        case 14:
        
        case 15:
        
        case 16:
        
        case 17:
        
        case 18:
        
        case 19:
        
        case 20:
        
        case 21:
        
        case 22:
        
        case 23:
        
        case 24:
        
        case 25:
        
        case 26:
        
        case 27:
        
        case 28:
        
        case 29:
        
        case 30:
        
        case 31:
        
        case 32:
        
        case 33:
        
        case 34:
        
        case 35:
        
        case 36:
        
        case 37:
        
        case 38:
        
        case 39:
        
        case 40:
        
        case 41:
        
        case 42:
        
        case 43:
        
        case 44:
        
        case 45:
        
        case 46:
        
        case 47:
        
        case 48:
        
        case 49:
        
        case 50:
        
        case 51:
        
        case 52:
        
        case 53:
        
        case 54:
        
        case 55:
        
        case 56:
        
        case 57:
        
        case 58:
        
        case 59:
        
        case 60:
        
        case 61:
        
        case 62:
        
        case 63:
        
        case 64:
        
        case 65:
        
        case 66:
        
        case 67:
        
        case 68:
        
        case 69:
        
        case 70:
        
        case 71:
        
        case 72:
        
        case 73:
        
        case 74:
        
        case 75:
        
        case 76:
        
        case 77:
        
        case 78:
        
        case 79:
        
        case 80:
        
        case 81:
        
        case 82:
        
        case 83:
        
        case 84:
        
        case 85:
        
        case 86:
        
        case 87:
        
        case 88:
        
        case 89:
        
        case 90:
        
        case 91:
        
        case 92:
        
        case 93:
        
        case 94:
        
        case 95:
        
        case 96:
        
        case 97:
        
        case 98:
        
        case 99:
        
        case 100:
        
        case 101:
        
        case 102:
        
        case 103:
        
        case 104:
        
        case 105:
        
        case 106:
        
        case 107:
        
        case 108:
        
        case 109:
        
        case 110:
        
        case 111:
        
        case 112:
        
        case 113:
        
        case 114:
        
        case 115:
        
        case 116:
        
        case 117:
        
        case 118:
        
        case 119:
        
        case 120:
        
        case 121:
        
        case 122:
        
        case 123:
        
        case 124:
        
        case 125:
        
        case 126:
        
        case 127:
        
        case 128:
        
        case 129:
        
        case 130:
        
        case 131:
        
        case 132:
        
        case 133:
        
        case 134:
        
        case 135:
        
        case 136:
        
        case 137:
        
        case 138:
        
        case 139:
        
        case 140:
        
        case 141:
        
        case 142:
        
        case 143:
        
        case 144:
        
        case 145:
        
        case 146:
        
        case 147:
        
        case 148:
        
        case 149:
        
        case 150:
        
        case 151:
        
        case 152:
        
        case 153:
        
        case 154:
        
        case 155:
        
        case 156:
        
        case 157:
        
        case 158:
        
        case 159:
        
        case 160:
        
        case 161:
        
        case 162:
        
        case 163:
        
        case 164:
        
        case 165:
        
        case 166:
        
        case 167:
        
        case 168:
        
        case 169:
        
        case 170:
        
        case 171:
        
        case 172:
        
        case 173:
        
        case 174:
        
        case 175:
        
        case 176:
        
        case 177:
        
        case 178:
        
        case 179:
        
        case 180:
        
        case 181:
        
        case 182:
        
        case 183:
        
        case 184:
        
        case 185:
        
        case 186:
        
        case 187:
        
        case 188:
        
        case 189:
        
        case 190:
        
        case 191:
        
        case 192:
        
        case 193:
        
        case 194:
        
        case 195:
        
        case 196:
        
        case 197:
        
        case 198:
        
        case 199:
        
        case 200:
        
        case 201:
        
        case 202:
        
        case 203:
        
        case 204:
        
        case 205:
        
        case 206:
        
        case 207:
        
        case 208:
        
        case 209:
        
        case 210:
        
        case 211:
        
        case 212:
        
        case 213:
        
        case 214:
        
        case 215:
        
        case 216:
        
        case 217:
        
        case 218:
        
        case 219:
        
        case 220:
        
        case 221:
        
        case 222:
        
        case 223:
        
        case 224:
        
        case 225:
        
        case 226:
        
        case 227:
        
        case 228:
        
        case 229:
        
        case 230:
        
        case 231:
        
        case 232:
        
        case 233:
        
        case 234:
        
        case 235:
        
        case 236:
        
        case 237:
        
        case 238:
        
        case 239:
        
        case 240:
        
        case 241:
        
        case 242:
        
        case 243:
        
        case 244:
        
        case 245:
        
        case 246:
        
        case 247:
        
        case 248:
        
        case 249:
        
        case 250:
        
        case 251:
        
        case 252:
        
        case 253:
        
        case 254:
        
        default:
          break;
      } 
      char c = '';
      int j = (paramInt2 & 0xFF) - c;
      if (j < 0)
        j += 256; 
      int k = ((paramInt2 & 0xFFFF) >>> 8) - c;
      if (k < 0)
        k += 256; 
      for (byte b = 0; b < arrayOfChar.length; b++) {
        int m = b % 2;
        if (m == 0) {
          arrayOfChar[b] = (char)(arrayOfChar[b] ^ j);
          j = ((j >>> 3 | j << 5) ^ arrayOfChar[b]) & 0xFF;
        } else {
          arrayOfChar[b] = (char)(arrayOfChar[b] ^ k);
          k = ((k >>> 3 | k << 5) ^ arrayOfChar[b]) & 0xFF;
        } 
      } 
      b[i] = (new String(arrayOfChar)).intern();
    } 
    return b[i];
  }
}


/* Location:              C:\Program Files\BurpSuitePro\burpsuite_pro.jar!\burp\Zex5.class
 * Java compiler version: 21 (65.0)
 * JD-Core Version:       1.1.3
 */