package burp;

public class Zexk extends Zexe<Zgcn> {
  public void ZI(Zgcn paramZgcn) {
    // Byte code:
    //   0: aload_1
    //   1: invokevirtual Zt : ()Lburp/Zgc0;
    //   4: astore_3
    //   5: aload_1
    //   6: invokevirtual ZU : ()Lburp/Zgc0;
    //   9: astore #4
    //   11: invokestatic ZK : ()Z
    //   14: aload_1
    //   15: invokevirtual ZI : ()Lburp/Zb3t;
    //   18: astore #5
    //   20: istore_2
    //   21: aload #4
    //   23: invokevirtual ZC : ()Ljava/util/List;
    //   26: invokeinterface size : ()I
    //   31: iconst_1
    //   32: if_icmpne -> 135
    //   35: aload #4
    //   37: invokevirtual ZC : ()Ljava/util/List;
    //   40: iconst_0
    //   41: invokeinterface get : (I)Ljava/lang/Object;
    //   46: checkcast burp/Zb3t
    //   49: astore #6
    //   51: aload #6
    //   53: invokestatic ZM : (Lburp/Zb3t;)Z
    //   56: ifeq -> 80
    //   59: aload_0
    //   60: aload_3
    //   61: aload #6
    //   63: checkcast burp/Zgcu
    //   66: invokevirtual Zb : (Lburp/Zb3t;Lburp/Zgcu;)V
    //   69: iload_2
    //   70: ifne -> 131
    //   73: iconst_2
    //   74: anewarray burp/Zbqc
    //   77: invokestatic Zr : ([Lburp/Zbqc;)V
    //   80: aload #6
    //   82: invokestatic ZZ : (Lburp/Zb3t;)Z
    //   85: ifeq -> 102
    //   88: aload_0
    //   89: aload_3
    //   90: aload #6
    //   92: checkcast burp/Zgc9
    //   95: invokevirtual Za : (Lburp/Zgc0;Lburp/Zgc9;)V
    //   98: iload_2
    //   99: ifne -> 131
    //   102: aload #6
    //   104: invokestatic Zc : (Lburp/Zesp;)Z
    //   107: ifeq -> 124
    //   110: aload_0
    //   111: aload_3
    //   112: aload #6
    //   114: checkcast burp/Zgcw
    //   117: invokevirtual ZJ : (Lburp/Zgc0;Lburp/Zgcw;)V
    //   120: iload_2
    //   121: ifne -> 131
    //   124: aload_0
    //   125: aload_3
    //   126: aload #4
    //   128: invokevirtual ZH : (Lburp/Zesp;Lburp/Zesp;)V
    //   131: iload_2
    //   132: ifne -> 142
    //   135: aload_0
    //   136: aload_3
    //   137: aload #4
    //   139: invokevirtual ZH : (Lburp/Zesp;Lburp/Zesp;)V
    //   142: aload_0
    //   143: aload_3
    //   144: aload_1
    //   145: invokevirtual ZH : (Lburp/Zesp;Lburp/Zesp;)V
    //   148: aload_0
    //   149: aload_1
    //   150: aload #5
    //   152: invokevirtual ZH : (Lburp/Zesp;Lburp/Zesp;)V
    //   155: return
  }
}


/* Location:              C:\Program Files\BurpSuitePro\burpsuite_pro.jar!\burp\Zexk.class
 * Java compiler version: 21 (65.0)
 * JD-Core Version:       1.1.3
 */