package burp;

import java.math.BigInteger;

class Zexl extends ClassLoader {
  static Object ZG;
  
  static String Zs;
  
  private static final String[] a;
  
  private static final String[] b;
  
  static void Zj(Object[] paramArrayOfObject, Object paramObject) throws Throwable {}
  
  static void Zx(Object paramObject) {
    Zsfj.Zg = a(-29222, 26934);
    Zsfj.ZL = new BigInteger(a(-29218, -27009));
    boolean bool = Zt2e.ZK();
    try {
      try {
        if (Zz66.ZM.charAt(Math.abs(((BigInteger)Zkjj.Zh).intValue() % 32)) > Zkkl.Zh.charAt(Math.abs(((BigInteger)Zb3l.Zl).intValue() % 32))) {
          try {
            Zgil.ZM(Class.forName(a(-29224, 32596)));
            if (bool)
              Zzh5.Zb(Class.forName(a(-29217, 6292))); 
          } catch (Throwable throwable) {
            throw a(null);
          } 
          return;
        } 
      } catch (Throwable throwable) {
        throw a(null);
      } 
      Zzh5.Zb(Class.forName(a(-29217, 6292)));
    } catch (Throwable throwable) {}
  }
  
  static boolean Z_(Object[] paramArrayOfObject, Object paramObject) throws Throwable {
    // Byte code:
    //   0: invokestatic ZK : ()Z
    //   3: istore_2
    //   4: new java/lang/StringBuilder
    //   7: dup
    //   8: invokespecial <init> : ()V
    //   11: astore_3
    //   12: iconst_0
    //   13: istore #4
    //   15: iload #4
    //   17: bipush #32
    //   19: if_icmpge -> 1355
    //   22: iload #4
    //   24: tableswitch default -> 1348, 0 -> 168, 1 -> 205, 2 -> 242, 3 -> 279, 4 -> 316, 5 -> 353, 6 -> 390, 7 -> 427, 8 -> 464, 9 -> 501, 10 -> 538, 11 -> 575, 12 -> 612, 13 -> 649, 14 -> 686, 15 -> 723, 16 -> 760, 17 -> 797, 18 -> 834, 19 -> 871, 20 -> 908, 21 -> 945, 22 -> 982, 23 -> 1019, 24 -> 1056, 25 -> 1093, 26 -> 1130, 27 -> 1167, 28 -> 1204, 29 -> 1241, 30 -> 1278, 31 -> 1315
    //   168: aload_3
    //   169: getstatic burp/Zebe.ZW : Ljava/lang/String;
    //   172: getstatic burp/Zlwj.ZE : Ljava/lang/Object;
    //   175: checkcast java/math/BigInteger
    //   178: invokevirtual intValue : ()I
    //   181: bipush #32
    //   183: irem
    //   184: invokestatic abs : (I)I
    //   187: invokevirtual charAt : (I)C
    //   190: invokevirtual append : (C)Ljava/lang/StringBuilder;
    //   193: pop
    //   194: iload_2
    //   195: ifeq -> 1348
    //   198: goto -> 205
    //   201: invokestatic a : (Ljava/lang/Throwable;)Ljava/lang/Throwable;
    //   204: athrow
    //   205: aload_3
    //   206: getstatic burp/Zzn6.Za : Ljava/lang/String;
    //   209: getstatic burp/Zlwc.ZG : Ljava/lang/Object;
    //   212: checkcast java/math/BigInteger
    //   215: invokevirtual intValue : ()I
    //   218: bipush #32
    //   220: irem
    //   221: invokestatic abs : (I)I
    //   224: invokevirtual charAt : (I)C
    //   227: invokevirtual append : (C)Ljava/lang/StringBuilder;
    //   230: pop
    //   231: iload_2
    //   232: ifeq -> 1348
    //   235: goto -> 242
    //   238: invokestatic a : (Ljava/lang/Throwable;)Ljava/lang/Throwable;
    //   241: athrow
    //   242: aload_3
    //   243: getstatic burp/Zmdf.Zo : Ljava/lang/String;
    //   246: getstatic burp/Zos.ZB : Ljava/lang/Object;
    //   249: checkcast java/math/BigInteger
    //   252: invokevirtual intValue : ()I
    //   255: bipush #32
    //   257: irem
    //   258: invokestatic abs : (I)I
    //   261: invokevirtual charAt : (I)C
    //   264: invokevirtual append : (C)Ljava/lang/StringBuilder;
    //   267: pop
    //   268: iload_2
    //   269: ifeq -> 1348
    //   272: goto -> 279
    //   275: invokestatic a : (Ljava/lang/Throwable;)Ljava/lang/Throwable;
    //   278: athrow
    //   279: aload_3
    //   280: getstatic burp/Ze2w.Za : Ljava/lang/String;
    //   283: getstatic burp/Zg7u.Zh : Ljava/lang/Object;
    //   286: checkcast java/math/BigInteger
    //   289: invokevirtual intValue : ()I
    //   292: bipush #32
    //   294: irem
    //   295: invokestatic abs : (I)I
    //   298: invokevirtual charAt : (I)C
    //   301: invokevirtual append : (C)Ljava/lang/StringBuilder;
    //   304: pop
    //   305: iload_2
    //   306: ifeq -> 1348
    //   309: goto -> 316
    //   312: invokestatic a : (Ljava/lang/Throwable;)Ljava/lang/Throwable;
    //   315: athrow
    //   316: aload_3
    //   317: getstatic burp/Zr36.Ze : Ljava/lang/String;
    //   320: getstatic burp/Zrfa.Zj : Ljava/lang/Object;
    //   323: checkcast java/math/BigInteger
    //   326: invokevirtual intValue : ()I
    //   329: bipush #32
    //   331: irem
    //   332: invokestatic abs : (I)I
    //   335: invokevirtual charAt : (I)C
    //   338: invokevirtual append : (C)Ljava/lang/StringBuilder;
    //   341: pop
    //   342: iload_2
    //   343: ifeq -> 1348
    //   346: goto -> 353
    //   349: invokestatic a : (Ljava/lang/Throwable;)Ljava/lang/Throwable;
    //   352: athrow
    //   353: aload_3
    //   354: getstatic burp/Zxcn.ZF : Ljava/lang/String;
    //   357: getstatic burp/Zs1k.Ze : Ljava/lang/Object;
    //   360: checkcast java/math/BigInteger
    //   363: invokevirtual intValue : ()I
    //   366: bipush #32
    //   368: irem
    //   369: invokestatic abs : (I)I
    //   372: invokevirtual charAt : (I)C
    //   375: invokevirtual append : (C)Ljava/lang/StringBuilder;
    //   378: pop
    //   379: iload_2
    //   380: ifeq -> 1348
    //   383: goto -> 390
    //   386: invokestatic a : (Ljava/lang/Throwable;)Ljava/lang/Throwable;
    //   389: athrow
    //   390: aload_3
    //   391: getstatic burp/Zzc9.Zv : Ljava/lang/String;
    //   394: getstatic burp/Zmzj.Zm : Ljava/lang/Object;
    //   397: checkcast java/math/BigInteger
    //   400: invokevirtual intValue : ()I
    //   403: bipush #32
    //   405: irem
    //   406: invokestatic abs : (I)I
    //   409: invokevirtual charAt : (I)C
    //   412: invokevirtual append : (C)Ljava/lang/StringBuilder;
    //   415: pop
    //   416: iload_2
    //   417: ifeq -> 1348
    //   420: goto -> 427
    //   423: invokestatic a : (Ljava/lang/Throwable;)Ljava/lang/Throwable;
    //   426: athrow
    //   427: aload_3
    //   428: getstatic burp/Zssc.ZR : Ljava/lang/String;
    //   431: getstatic burp/Zek4.ZR : Ljava/lang/Object;
    //   434: checkcast java/math/BigInteger
    //   437: invokevirtual intValue : ()I
    //   440: bipush #32
    //   442: irem
    //   443: invokestatic abs : (I)I
    //   446: invokevirtual charAt : (I)C
    //   449: invokevirtual append : (C)Ljava/lang/StringBuilder;
    //   452: pop
    //   453: iload_2
    //   454: ifeq -> 1348
    //   457: goto -> 464
    //   460: invokestatic a : (Ljava/lang/Throwable;)Ljava/lang/Throwable;
    //   463: athrow
    //   464: aload_3
    //   465: getstatic burp/Zlbd.Zq : Ljava/lang/String;
    //   468: getstatic burp/Zql.Zt : Ljava/lang/Object;
    //   471: checkcast java/math/BigInteger
    //   474: invokevirtual intValue : ()I
    //   477: bipush #32
    //   479: irem
    //   480: invokestatic abs : (I)I
    //   483: invokevirtual charAt : (I)C
    //   486: invokevirtual append : (C)Ljava/lang/StringBuilder;
    //   489: pop
    //   490: iload_2
    //   491: ifeq -> 1348
    //   494: goto -> 501
    //   497: invokestatic a : (Ljava/lang/Throwable;)Ljava/lang/Throwable;
    //   500: athrow
    //   501: aload_3
    //   502: getstatic burp/Ztnn.ZS : Ljava/lang/String;
    //   505: getstatic burp/Zs4g.ZC : Ljava/lang/Object;
    //   508: checkcast java/math/BigInteger
    //   511: invokevirtual intValue : ()I
    //   514: bipush #32
    //   516: irem
    //   517: invokestatic abs : (I)I
    //   520: invokevirtual charAt : (I)C
    //   523: invokevirtual append : (C)Ljava/lang/StringBuilder;
    //   526: pop
    //   527: iload_2
    //   528: ifeq -> 1348
    //   531: goto -> 538
    //   534: invokestatic a : (Ljava/lang/Throwable;)Ljava/lang/Throwable;
    //   537: athrow
    //   538: aload_3
    //   539: getstatic burp/Zg0q.Ze : Ljava/lang/String;
    //   542: getstatic burp/Ze4a.ZP : Ljava/lang/Object;
    //   545: checkcast java/math/BigInteger
    //   548: invokevirtual intValue : ()I
    //   551: bipush #32
    //   553: irem
    //   554: invokestatic abs : (I)I
    //   557: invokevirtual charAt : (I)C
    //   560: invokevirtual append : (C)Ljava/lang/StringBuilder;
    //   563: pop
    //   564: iload_2
    //   565: ifeq -> 1348
    //   568: goto -> 575
    //   571: invokestatic a : (Ljava/lang/Throwable;)Ljava/lang/Throwable;
    //   574: athrow
    //   575: aload_3
    //   576: getstatic burp/Zku9.Zl : Ljava/lang/String;
    //   579: getstatic burp/Zbx4.Zw : Ljava/lang/Object;
    //   582: checkcast java/math/BigInteger
    //   585: invokevirtual intValue : ()I
    //   588: bipush #32
    //   590: irem
    //   591: invokestatic abs : (I)I
    //   594: invokevirtual charAt : (I)C
    //   597: invokevirtual append : (C)Ljava/lang/StringBuilder;
    //   600: pop
    //   601: iload_2
    //   602: ifeq -> 1348
    //   605: goto -> 612
    //   608: invokestatic a : (Ljava/lang/Throwable;)Ljava/lang/Throwable;
    //   611: athrow
    //   612: aload_3
    //   613: getstatic burp/Zrm6.ZV : Ljava/lang/String;
    //   616: getstatic burp/Zrym.Zk : Ljava/lang/Object;
    //   619: checkcast java/math/BigInteger
    //   622: invokevirtual intValue : ()I
    //   625: bipush #32
    //   627: irem
    //   628: invokestatic abs : (I)I
    //   631: invokevirtual charAt : (I)C
    //   634: invokevirtual append : (C)Ljava/lang/StringBuilder;
    //   637: pop
    //   638: iload_2
    //   639: ifeq -> 1348
    //   642: goto -> 649
    //   645: invokestatic a : (Ljava/lang/Throwable;)Ljava/lang/Throwable;
    //   648: athrow
    //   649: aload_3
    //   650: getstatic burp/Zejz.Zd : Ljava/lang/String;
    //   653: getstatic burp/Zm83.Zl : Ljava/lang/Object;
    //   656: checkcast java/math/BigInteger
    //   659: invokevirtual intValue : ()I
    //   662: bipush #32
    //   664: irem
    //   665: invokestatic abs : (I)I
    //   668: invokevirtual charAt : (I)C
    //   671: invokevirtual append : (C)Ljava/lang/StringBuilder;
    //   674: pop
    //   675: iload_2
    //   676: ifeq -> 1348
    //   679: goto -> 686
    //   682: invokestatic a : (Ljava/lang/Throwable;)Ljava/lang/Throwable;
    //   685: athrow
    //   686: aload_3
    //   687: getstatic burp/Zkkl.Zh : Ljava/lang/String;
    //   690: getstatic burp/Ztvy.ZH : Ljava/lang/Object;
    //   693: checkcast java/math/BigInteger
    //   696: invokevirtual intValue : ()I
    //   699: bipush #32
    //   701: irem
    //   702: invokestatic abs : (I)I
    //   705: invokevirtual charAt : (I)C
    //   708: invokevirtual append : (C)Ljava/lang/StringBuilder;
    //   711: pop
    //   712: iload_2
    //   713: ifeq -> 1348
    //   716: goto -> 723
    //   719: invokestatic a : (Ljava/lang/Throwable;)Ljava/lang/Throwable;
    //   722: athrow
    //   723: aload_3
    //   724: getstatic burp/Zgi9.Zv : Ljava/lang/String;
    //   727: getstatic burp/Zz66.ZQ : Ljava/lang/Object;
    //   730: checkcast java/math/BigInteger
    //   733: invokevirtual intValue : ()I
    //   736: bipush #32
    //   738: irem
    //   739: invokestatic abs : (I)I
    //   742: invokevirtual charAt : (I)C
    //   745: invokevirtual append : (C)Ljava/lang/StringBuilder;
    //   748: pop
    //   749: iload_2
    //   750: ifeq -> 1348
    //   753: goto -> 760
    //   756: invokestatic a : (Ljava/lang/Throwable;)Ljava/lang/Throwable;
    //   759: athrow
    //   760: aload_3
    //   761: getstatic burp/Zea9.Zd : Ljava/lang/String;
    //   764: getstatic burp/Zb2n.ZR : Ljava/lang/Object;
    //   767: checkcast java/math/BigInteger
    //   770: invokevirtual intValue : ()I
    //   773: bipush #32
    //   775: irem
    //   776: invokestatic abs : (I)I
    //   779: invokevirtual charAt : (I)C
    //   782: invokevirtual append : (C)Ljava/lang/StringBuilder;
    //   785: pop
    //   786: iload_2
    //   787: ifeq -> 1348
    //   790: goto -> 797
    //   793: invokestatic a : (Ljava/lang/Throwable;)Ljava/lang/Throwable;
    //   796: athrow
    //   797: aload_3
    //   798: getstatic burp/Zlid.ZU : Ljava/lang/String;
    //   801: getstatic burp/Zge9.ZT : Ljava/lang/Object;
    //   804: checkcast java/math/BigInteger
    //   807: invokevirtual intValue : ()I
    //   810: bipush #32
    //   812: irem
    //   813: invokestatic abs : (I)I
    //   816: invokevirtual charAt : (I)C
    //   819: invokevirtual append : (C)Ljava/lang/StringBuilder;
    //   822: pop
    //   823: iload_2
    //   824: ifeq -> 1348
    //   827: goto -> 834
    //   830: invokestatic a : (Ljava/lang/Throwable;)Ljava/lang/Throwable;
    //   833: athrow
    //   834: aload_3
    //   835: getstatic burp/Zs0h.ZX : Ljava/lang/String;
    //   838: getstatic burp/Zegw.ZW : Ljava/lang/Object;
    //   841: checkcast java/math/BigInteger
    //   844: invokevirtual intValue : ()I
    //   847: bipush #32
    //   849: irem
    //   850: invokestatic abs : (I)I
    //   853: invokevirtual charAt : (I)C
    //   856: invokevirtual append : (C)Ljava/lang/StringBuilder;
    //   859: pop
    //   860: iload_2
    //   861: ifeq -> 1348
    //   864: goto -> 871
    //   867: invokestatic a : (Ljava/lang/Throwable;)Ljava/lang/Throwable;
    //   870: athrow
    //   871: aload_3
    //   872: getstatic burp/Zb3r.Zo : Ljava/lang/String;
    //   875: getstatic burp/Zesw.ZB : Ljava/lang/Object;
    //   878: checkcast java/math/BigInteger
    //   881: invokevirtual intValue : ()I
    //   884: bipush #32
    //   886: irem
    //   887: invokestatic abs : (I)I
    //   890: invokevirtual charAt : (I)C
    //   893: invokevirtual append : (C)Ljava/lang/StringBuilder;
    //   896: pop
    //   897: iload_2
    //   898: ifeq -> 1348
    //   901: goto -> 908
    //   904: invokestatic a : (Ljava/lang/Throwable;)Ljava/lang/Throwable;
    //   907: athrow
    //   908: aload_3
    //   909: getstatic burp/Zg4z.Zm : Ljava/lang/String;
    //   912: getstatic burp/Zgtx.Z_ : Ljava/lang/Object;
    //   915: checkcast java/math/BigInteger
    //   918: invokevirtual intValue : ()I
    //   921: bipush #32
    //   923: irem
    //   924: invokestatic abs : (I)I
    //   927: invokevirtual charAt : (I)C
    //   930: invokevirtual append : (C)Ljava/lang/StringBuilder;
    //   933: pop
    //   934: iload_2
    //   935: ifeq -> 1348
    //   938: goto -> 945
    //   941: invokestatic a : (Ljava/lang/Throwable;)Ljava/lang/Throwable;
    //   944: athrow
    //   945: aload_3
    //   946: getstatic burp/Zlab.Zp : Ljava/lang/String;
    //   949: getstatic burp/Zk7o.ZO : Ljava/lang/Object;
    //   952: checkcast java/math/BigInteger
    //   955: invokevirtual intValue : ()I
    //   958: bipush #32
    //   960: irem
    //   961: invokestatic abs : (I)I
    //   964: invokevirtual charAt : (I)C
    //   967: invokevirtual append : (C)Ljava/lang/StringBuilder;
    //   970: pop
    //   971: iload_2
    //   972: ifeq -> 1348
    //   975: goto -> 982
    //   978: invokestatic a : (Ljava/lang/Throwable;)Ljava/lang/Throwable;
    //   981: athrow
    //   982: aload_3
    //   983: getstatic burp/Zzi_.ZG : Ljava/lang/String;
    //   986: getstatic burp/Zrwp.Zk : Ljava/lang/Object;
    //   989: checkcast java/math/BigInteger
    //   992: invokevirtual intValue : ()I
    //   995: bipush #32
    //   997: irem
    //   998: invokestatic abs : (I)I
    //   1001: invokevirtual charAt : (I)C
    //   1004: invokevirtual append : (C)Ljava/lang/StringBuilder;
    //   1007: pop
    //   1008: iload_2
    //   1009: ifeq -> 1348
    //   1012: goto -> 1019
    //   1015: invokestatic a : (Ljava/lang/Throwable;)Ljava/lang/Throwable;
    //   1018: athrow
    //   1019: aload_3
    //   1020: getstatic burp/Zt8m.ZT : Ljava/lang/String;
    //   1023: getstatic burp/Zm83.Zl : Ljava/lang/Object;
    //   1026: checkcast java/math/BigInteger
    //   1029: invokevirtual intValue : ()I
    //   1032: bipush #32
    //   1034: irem
    //   1035: invokestatic abs : (I)I
    //   1038: invokevirtual charAt : (I)C
    //   1041: invokevirtual append : (C)Ljava/lang/StringBuilder;
    //   1044: pop
    //   1045: iload_2
    //   1046: ifeq -> 1348
    //   1049: goto -> 1056
    //   1052: invokestatic a : (Ljava/lang/Throwable;)Ljava/lang/Throwable;
    //   1055: athrow
    //   1056: aload_3
    //   1057: getstatic burp/Zg0f.Zd : Ljava/lang/String;
    //   1060: getstatic burp/Zxwf.Zi : Ljava/lang/Object;
    //   1063: checkcast java/math/BigInteger
    //   1066: invokevirtual intValue : ()I
    //   1069: bipush #32
    //   1071: irem
    //   1072: invokestatic abs : (I)I
    //   1075: invokevirtual charAt : (I)C
    //   1078: invokevirtual append : (C)Ljava/lang/StringBuilder;
    //   1081: pop
    //   1082: iload_2
    //   1083: ifeq -> 1348
    //   1086: goto -> 1093
    //   1089: invokestatic a : (Ljava/lang/Throwable;)Ljava/lang/Throwable;
    //   1092: athrow
    //   1093: aload_3
    //   1094: getstatic burp/Zssc.ZR : Ljava/lang/String;
    //   1097: getstatic burp/Ztq4.ZA : Ljava/lang/Object;
    //   1100: checkcast java/math/BigInteger
    //   1103: invokevirtual intValue : ()I
    //   1106: bipush #32
    //   1108: irem
    //   1109: invokestatic abs : (I)I
    //   1112: invokevirtual charAt : (I)C
    //   1115: invokevirtual append : (C)Ljava/lang/StringBuilder;
    //   1118: pop
    //   1119: iload_2
    //   1120: ifeq -> 1348
    //   1123: goto -> 1130
    //   1126: invokestatic a : (Ljava/lang/Throwable;)Ljava/lang/Throwable;
    //   1129: athrow
    //   1130: aload_3
    //   1131: getstatic burp/Zxcn.ZF : Ljava/lang/String;
    //   1134: getstatic burp/Zxxo.ZJ : Ljava/lang/Object;
    //   1137: checkcast java/math/BigInteger
    //   1140: invokevirtual intValue : ()I
    //   1143: bipush #32
    //   1145: irem
    //   1146: invokestatic abs : (I)I
    //   1149: invokevirtual charAt : (I)C
    //   1152: invokevirtual append : (C)Ljava/lang/StringBuilder;
    //   1155: pop
    //   1156: iload_2
    //   1157: ifeq -> 1348
    //   1160: goto -> 1167
    //   1163: invokestatic a : (Ljava/lang/Throwable;)Ljava/lang/Throwable;
    //   1166: athrow
    //   1167: aload_3
    //   1168: getstatic burp/Zxln.Zz : Ljava/lang/String;
    //   1171: getstatic burp/Zmui.Zz : Ljava/lang/Object;
    //   1174: checkcast java/math/BigInteger
    //   1177: invokevirtual intValue : ()I
    //   1180: bipush #32
    //   1182: irem
    //   1183: invokestatic abs : (I)I
    //   1186: invokevirtual charAt : (I)C
    //   1189: invokevirtual append : (C)Ljava/lang/StringBuilder;
    //   1192: pop
    //   1193: iload_2
    //   1194: ifeq -> 1348
    //   1197: goto -> 1204
    //   1200: invokestatic a : (Ljava/lang/Throwable;)Ljava/lang/Throwable;
    //   1203: athrow
    //   1204: aload_3
    //   1205: getstatic burp/Zrqe.ZB : Ljava/lang/String;
    //   1208: getstatic burp/Zttd.Zi : Ljava/lang/Object;
    //   1211: checkcast java/math/BigInteger
    //   1214: invokevirtual intValue : ()I
    //   1217: bipush #32
    //   1219: irem
    //   1220: invokestatic abs : (I)I
    //   1223: invokevirtual charAt : (I)C
    //   1226: invokevirtual append : (C)Ljava/lang/StringBuilder;
    //   1229: pop
    //   1230: iload_2
    //   1231: ifeq -> 1348
    //   1234: goto -> 1241
    //   1237: invokestatic a : (Ljava/lang/Throwable;)Ljava/lang/Throwable;
    //   1240: athrow
    //   1241: aload_3
    //   1242: getstatic burp/Zrgo.Z_ : Ljava/lang/String;
    //   1245: getstatic burp/Ze4w.Zd : Ljava/lang/Object;
    //   1248: checkcast java/math/BigInteger
    //   1251: invokevirtual intValue : ()I
    //   1254: bipush #32
    //   1256: irem
    //   1257: invokestatic abs : (I)I
    //   1260: invokevirtual charAt : (I)C
    //   1263: invokevirtual append : (C)Ljava/lang/StringBuilder;
    //   1266: pop
    //   1267: iload_2
    //   1268: ifeq -> 1348
    //   1271: goto -> 1278
    //   1274: invokestatic a : (Ljava/lang/Throwable;)Ljava/lang/Throwable;
    //   1277: athrow
    //   1278: aload_3
    //   1279: getstatic burp/Zxc0.Zh : Ljava/lang/String;
    //   1282: getstatic burp/Zl_a.ZP : Ljava/lang/Object;
    //   1285: checkcast java/math/BigInteger
    //   1288: invokevirtual intValue : ()I
    //   1291: bipush #32
    //   1293: irem
    //   1294: invokestatic abs : (I)I
    //   1297: invokevirtual charAt : (I)C
    //   1300: invokevirtual append : (C)Ljava/lang/StringBuilder;
    //   1303: pop
    //   1304: iload_2
    //   1305: ifeq -> 1348
    //   1308: goto -> 1315
    //   1311: invokestatic a : (Ljava/lang/Throwable;)Ljava/lang/Throwable;
    //   1314: athrow
    //   1315: aload_3
    //   1316: getstatic burp/Zes.ZW : Ljava/lang/String;
    //   1319: getstatic burp/Zk8f.ZG : Ljava/lang/Object;
    //   1322: checkcast java/math/BigInteger
    //   1325: invokevirtual intValue : ()I
    //   1328: bipush #32
    //   1330: irem
    //   1331: invokestatic abs : (I)I
    //   1334: invokevirtual charAt : (I)C
    //   1337: invokevirtual append : (C)Ljava/lang/StringBuilder;
    //   1340: pop
    //   1341: goto -> 1348
    //   1344: invokestatic a : (Ljava/lang/Throwable;)Ljava/lang/Throwable;
    //   1347: athrow
    //   1348: iinc #4, 1
    //   1351: iload_2
    //   1352: ifeq -> 15
    //   1355: aload_3
    //   1356: invokevirtual toString : ()Ljava/lang/String;
    //   1359: putstatic burp/Zgk9.Zf : Ljava/lang/String;
    //   1362: sipush #-29220
    //   1365: sipush #24919
    //   1368: invokestatic a : (II)Ljava/lang/String;
    //   1371: iconst_1
    //   1372: ldc burp/Zg_i
    //   1374: invokevirtual getClassLoader : ()Ljava/lang/ClassLoader;
    //   1377: invokestatic forName : (Ljava/lang/String;ZLjava/lang/ClassLoader;)Ljava/lang/Class;
    //   1380: invokevirtual getDeclaredFields : ()[Ljava/lang/reflect/Field;
    //   1383: astore #4
    //   1385: aload #4
    //   1387: arraylength
    //   1388: istore #5
    //   1390: iconst_0
    //   1391: istore #6
    //   1393: iload #6
    //   1395: iload #5
    //   1397: if_icmpge -> 1535
    //   1400: aload #4
    //   1402: iload #6
    //   1404: aaload
    //   1405: astore #7
    //   1407: aload #7
    //   1409: invokevirtual getModifiers : ()I
    //   1412: invokestatic isStatic : (I)Z
    //   1415: ifne -> 1425
    //   1418: goto -> 1528
    //   1421: invokestatic a : (Ljava/lang/Throwable;)Ljava/lang/Throwable;
    //   1424: athrow
    //   1425: aload #7
    //   1427: invokevirtual getType : ()Ljava/lang/Class;
    //   1430: astore #8
    //   1432: aload #8
    //   1434: ifnull -> 1515
    //   1437: aload #8
    //   1439: invokevirtual isPrimitive : ()Z
    //   1442: ifne -> 1515
    //   1445: goto -> 1452
    //   1448: invokestatic a : (Ljava/lang/Throwable;)Ljava/lang/Throwable;
    //   1451: athrow
    //   1452: aload #8
    //   1454: invokevirtual getPackage : ()Ljava/lang/Package;
    //   1457: ifnull -> 1515
    //   1460: goto -> 1467
    //   1463: invokestatic a : (Ljava/lang/Throwable;)Ljava/lang/Throwable;
    //   1466: athrow
    //   1467: aload #8
    //   1469: invokevirtual getPackage : ()Ljava/lang/Package;
    //   1472: invokevirtual getName : ()Ljava/lang/String;
    //   1475: ifnull -> 1515
    //   1478: goto -> 1485
    //   1481: invokestatic a : (Ljava/lang/Throwable;)Ljava/lang/Throwable;
    //   1484: athrow
    //   1485: aload #8
    //   1487: invokevirtual getPackage : ()Ljava/lang/Package;
    //   1490: invokevirtual getName : ()Ljava/lang/String;
    //   1493: sipush #-29225
    //   1496: sipush #2977
    //   1499: invokestatic a : (II)Ljava/lang/String;
    //   1502: invokevirtual startsWith : (Ljava/lang/String;)Z
    //   1505: ifne -> 1515
    //   1508: goto -> 1515
    //   1511: invokestatic a : (Ljava/lang/Throwable;)Ljava/lang/Throwable;
    //   1514: athrow
    //   1515: aload #7
    //   1517: iconst_1
    //   1518: invokevirtual setAccessible : (Z)V
    //   1521: aload #7
    //   1523: aconst_null
    //   1524: invokevirtual get : (Ljava/lang/Object;)Ljava/lang/Object;
    //   1527: pop
    //   1528: iinc #6, 1
    //   1531: iload_2
    //   1532: ifeq -> 1393
    //   1535: sipush #-29223
    //   1538: sipush #3138
    //   1541: invokestatic a : (II)Ljava/lang/String;
    //   1544: invokestatic forName : (Ljava/lang/String;)Ljava/lang/Class;
    //   1547: invokevirtual getDeclaredMethods : ()[Ljava/lang/reflect/Method;
    //   1550: astore #4
    //   1552: aload #4
    //   1554: arraylength
    //   1555: istore #5
    //   1557: iconst_0
    //   1558: istore #6
    //   1560: iload #6
    //   1562: iload #5
    //   1564: if_icmpge -> 1697
    //   1567: aload #4
    //   1569: iload #6
    //   1571: aaload
    //   1572: astore #7
    //   1574: aload #7
    //   1576: invokevirtual getParameterTypes : ()[Ljava/lang/Class;
    //   1579: pop
    //   1580: aload #7
    //   1582: invokevirtual getModifiers : ()I
    //   1585: invokestatic isStatic : (I)Z
    //   1588: ifeq -> 1683
    //   1591: aload #7
    //   1593: invokevirtual getParameterTypes : ()[Ljava/lang/Class;
    //   1596: arraylength
    //   1597: iconst_2
    //   1598: if_icmpne -> 1683
    //   1601: goto -> 1608
    //   1604: invokestatic a : (Ljava/lang/Throwable;)Ljava/lang/Throwable;
    //   1607: athrow
    //   1608: aload #7
    //   1610: invokevirtual getReturnType : ()Ljava/lang/Class;
    //   1613: getstatic java/lang/Void.TYPE : Ljava/lang/Class;
    //   1616: invokevirtual equals : (Ljava/lang/Object;)Z
    //   1619: ifeq -> 1683
    //   1622: goto -> 1629
    //   1625: invokestatic a : (Ljava/lang/Throwable;)Ljava/lang/Throwable;
    //   1628: athrow
    //   1629: aload #7
    //   1631: iconst_1
    //   1632: invokevirtual setAccessible : (Z)V
    //   1635: aload #7
    //   1637: aconst_null
    //   1638: iconst_2
    //   1639: anewarray java/lang/Object
    //   1642: dup
    //   1643: iconst_0
    //   1644: aload_0
    //   1645: aastore
    //   1646: dup
    //   1647: iconst_1
    //   1648: aload_1
    //   1649: ifnonnull -> 1667
    //   1652: goto -> 1659
    //   1655: invokestatic a : (Ljava/lang/Throwable;)Ljava/lang/Throwable;
    //   1658: athrow
    //   1659: aload_1
    //   1660: goto -> 1674
    //   1663: invokestatic a : (Ljava/lang/Throwable;)Ljava/lang/Throwable;
    //   1666: athrow
    //   1667: aload_1
    //   1668: checkcast [B
    //   1671: invokevirtual clone : ()Ljava/lang/Object;
    //   1674: aastore
    //   1675: invokevirtual invoke : (Ljava/lang/Object;[Ljava/lang/Object;)Ljava/lang/Object;
    //   1678: pop
    //   1679: iload_2
    //   1680: ifeq -> 1697
    //   1683: iinc #6, 1
    //   1686: iload_2
    //   1687: ifeq -> 1560
    //   1690: goto -> 1697
    //   1693: invokestatic a : (Ljava/lang/Throwable;)Ljava/lang/Throwable;
    //   1696: athrow
    //   1697: getstatic burp/Zeig.ZA : Ljava/lang/Object;
    //   1700: checkcast java/math/BigInteger
    //   1703: invokevirtual toByteArray : ()[B
    //   1706: astore #4
    //   1708: bipush #32
    //   1710: newarray int
    //   1712: dup
    //   1713: iconst_0
    //   1714: ldc 876216579
    //   1716: iastore
    //   1717: dup
    //   1718: iconst_1
    //   1719: ldc 455999525
    //   1721: iastore
    //   1722: dup
    //   1723: iconst_2
    //   1724: ldc 1043334948
    //   1726: iastore
    //   1727: dup
    //   1728: iconst_3
    //   1729: ldc 439222784
    //   1731: iastore
    //   1732: dup
    //   1733: iconst_4
    //   1734: ldc 372376604
    //   1736: iastore
    //   1737: dup
    //   1738: iconst_5
    //   1739: ldc 707731490
    //   1741: iastore
    //   1742: dup
    //   1743: bipush #6
    //   1745: ldc 389426184
    //   1747: iastore
    //   1748: dup
    //   1749: bipush #7
    //   1751: ldc 973875457
    //   1753: iastore
    //   1754: dup
    //   1755: bipush #8
    //   1757: ldc 389160971
    //   1759: iastore
    //   1760: dup
    //   1761: bipush #9
    //   1763: ldc 907870729
    //   1765: iastore
    //   1766: dup
    //   1767: bipush #10
    //   1769: ldc 121057538
    //   1771: iastore
    //   1772: dup
    //   1773: bipush #11
    //   1775: ldc 840500228
    //   1777: iastore
    //   1778: dup
    //   1779: bipush #12
    //   1781: ldc 254150144
    //   1783: iastore
    //   1784: dup
    //   1785: bipush #13
    //   1787: ldc 924386310
    //   1789: iastore
    //   1790: dup
    //   1791: bipush #14
    //   1793: ldc 187632156
    //   1795: iastore
    //   1796: dup
    //   1797: bipush #15
    //   1799: ldc 874189824
    //   1801: iastore
    //   1802: dup
    //   1803: bipush #16
    //   1805: ldc 655302664
    //   1807: iastore
    //   1808: dup
    //   1809: bipush #17
    //   1811: ldc 890966315
    //   1813: iastore
    //   1814: dup
    //   1815: bipush #18
    //   1817: ldc 722417666
    //   1819: iastore
    //   1820: dup
    //   1821: bipush #19
    //   1823: ldc 1026621720
    //   1825: iastore
    //   1826: dup
    //   1827: bipush #20
    //   1829: ldc 957157408
    //   1831: iastore
    //   1832: dup
    //   1833: bipush #21
    //   1835: ldc 892536332
    //   1837: iastore
    //   1838: dup
    //   1839: bipush #22
    //   1841: ldc 689771012
    //   1843: iastore
    //   1844: dup
    //   1845: bipush #23
    //   1847: ldc 221709344
    //   1849: iastore
    //   1850: dup
    //   1851: bipush #24
    //   1853: ldc 940377620
    //   1855: iastore
    //   1856: dup
    //   1857: bipush #25
    //   1859: ldc 255209728
    //   1861: iastore
    //   1862: dup
    //   1863: bipush #26
    //   1865: ldc 1010368540
    //   1867: iastore
    //   1868: dup
    //   1869: bipush #27
    //   1871: ldc 220604441
    //   1873: iastore
    //   1874: dup
    //   1875: bipush #28
    //   1877: ldc 1008414755
    //   1879: iastore
    //   1880: dup
    //   1881: bipush #29
    //   1883: ldc 187049985
    //   1885: iastore
    //   1886: dup
    //   1887: bipush #30
    //   1889: ldc 943331329
    //   1891: iastore
    //   1892: dup
    //   1893: bipush #31
    //   1895: ldc 170788368
    //   1897: iastore
    //   1898: astore #6
    //   1900: bipush #64
    //   1902: newarray int
    //   1904: dup
    //   1905: iconst_0
    //   1906: ldc 16843776
    //   1908: iastore
    //   1909: dup
    //   1910: iconst_1
    //   1911: iconst_0
    //   1912: iastore
    //   1913: dup
    //   1914: iconst_2
    //   1915: ldc 65536
    //   1917: iastore
    //   1918: dup
    //   1919: iconst_3
    //   1920: ldc 16843780
    //   1922: iastore
    //   1923: dup
    //   1924: iconst_4
    //   1925: ldc 16842756
    //   1927: iastore
    //   1928: dup
    //   1929: iconst_5
    //   1930: ldc 66564
    //   1932: iastore
    //   1933: dup
    //   1934: bipush #6
    //   1936: iconst_4
    //   1937: iastore
    //   1938: dup
    //   1939: bipush #7
    //   1941: ldc 65536
    //   1943: iastore
    //   1944: dup
    //   1945: bipush #8
    //   1947: sipush #1024
    //   1950: iastore
    //   1951: dup
    //   1952: bipush #9
    //   1954: ldc 16843776
    //   1956: iastore
    //   1957: dup
    //   1958: bipush #10
    //   1960: ldc 16843780
    //   1962: iastore
    //   1963: dup
    //   1964: bipush #11
    //   1966: sipush #1024
    //   1969: iastore
    //   1970: dup
    //   1971: bipush #12
    //   1973: ldc 16778244
    //   1975: iastore
    //   1976: dup
    //   1977: bipush #13
    //   1979: ldc 16842756
    //   1981: iastore
    //   1982: dup
    //   1983: bipush #14
    //   1985: ldc 16777216
    //   1987: iastore
    //   1988: dup
    //   1989: bipush #15
    //   1991: iconst_4
    //   1992: iastore
    //   1993: dup
    //   1994: bipush #16
    //   1996: sipush #1028
    //   1999: iastore
    //   2000: dup
    //   2001: bipush #17
    //   2003: ldc 16778240
    //   2005: iastore
    //   2006: dup
    //   2007: bipush #18
    //   2009: ldc 16778240
    //   2011: iastore
    //   2012: dup
    //   2013: bipush #19
    //   2015: ldc 66560
    //   2017: iastore
    //   2018: dup
    //   2019: bipush #20
    //   2021: ldc 66560
    //   2023: iastore
    //   2024: dup
    //   2025: bipush #21
    //   2027: ldc 16842752
    //   2029: iastore
    //   2030: dup
    //   2031: bipush #22
    //   2033: ldc 16842752
    //   2035: iastore
    //   2036: dup
    //   2037: bipush #23
    //   2039: ldc 16778244
    //   2041: iastore
    //   2042: dup
    //   2043: bipush #24
    //   2045: ldc 65540
    //   2047: iastore
    //   2048: dup
    //   2049: bipush #25
    //   2051: ldc 16777220
    //   2053: iastore
    //   2054: dup
    //   2055: bipush #26
    //   2057: ldc 16777220
    //   2059: iastore
    //   2060: dup
    //   2061: bipush #27
    //   2063: ldc 65540
    //   2065: iastore
    //   2066: dup
    //   2067: bipush #28
    //   2069: iconst_0
    //   2070: iastore
    //   2071: dup
    //   2072: bipush #29
    //   2074: sipush #1028
    //   2077: iastore
    //   2078: dup
    //   2079: bipush #30
    //   2081: ldc 66564
    //   2083: iastore
    //   2084: dup
    //   2085: bipush #31
    //   2087: ldc 16777216
    //   2089: iastore
    //   2090: dup
    //   2091: bipush #32
    //   2093: ldc 65536
    //   2095: iastore
    //   2096: dup
    //   2097: bipush #33
    //   2099: ldc 16843780
    //   2101: iastore
    //   2102: dup
    //   2103: bipush #34
    //   2105: iconst_4
    //   2106: iastore
    //   2107: dup
    //   2108: bipush #35
    //   2110: ldc 16842752
    //   2112: iastore
    //   2113: dup
    //   2114: bipush #36
    //   2116: ldc 16843776
    //   2118: iastore
    //   2119: dup
    //   2120: bipush #37
    //   2122: ldc 16777216
    //   2124: iastore
    //   2125: dup
    //   2126: bipush #38
    //   2128: ldc 16777216
    //   2130: iastore
    //   2131: dup
    //   2132: bipush #39
    //   2134: sipush #1024
    //   2137: iastore
    //   2138: dup
    //   2139: bipush #40
    //   2141: ldc 16842756
    //   2143: iastore
    //   2144: dup
    //   2145: bipush #41
    //   2147: ldc 65536
    //   2149: iastore
    //   2150: dup
    //   2151: bipush #42
    //   2153: ldc 66560
    //   2155: iastore
    //   2156: dup
    //   2157: bipush #43
    //   2159: ldc 16777220
    //   2161: iastore
    //   2162: dup
    //   2163: bipush #44
    //   2165: sipush #1024
    //   2168: iastore
    //   2169: dup
    //   2170: bipush #45
    //   2172: iconst_4
    //   2173: iastore
    //   2174: dup
    //   2175: bipush #46
    //   2177: ldc 16778244
    //   2179: iastore
    //   2180: dup
    //   2181: bipush #47
    //   2183: ldc 66564
    //   2185: iastore
    //   2186: dup
    //   2187: bipush #48
    //   2189: ldc 16843780
    //   2191: iastore
    //   2192: dup
    //   2193: bipush #49
    //   2195: ldc 65540
    //   2197: iastore
    //   2198: dup
    //   2199: bipush #50
    //   2201: ldc 16842752
    //   2203: iastore
    //   2204: dup
    //   2205: bipush #51
    //   2207: ldc 16778244
    //   2209: iastore
    //   2210: dup
    //   2211: bipush #52
    //   2213: ldc 16777220
    //   2215: iastore
    //   2216: dup
    //   2217: bipush #53
    //   2219: sipush #1028
    //   2222: iastore
    //   2223: dup
    //   2224: bipush #54
    //   2226: ldc 66564
    //   2228: iastore
    //   2229: dup
    //   2230: bipush #55
    //   2232: ldc 16843776
    //   2234: iastore
    //   2235: dup
    //   2236: bipush #56
    //   2238: sipush #1028
    //   2241: iastore
    //   2242: dup
    //   2243: bipush #57
    //   2245: ldc 16778240
    //   2247: iastore
    //   2248: dup
    //   2249: bipush #58
    //   2251: ldc 16778240
    //   2253: iastore
    //   2254: dup
    //   2255: bipush #59
    //   2257: iconst_0
    //   2258: iastore
    //   2259: dup
    //   2260: bipush #60
    //   2262: ldc 65540
    //   2264: iastore
    //   2265: dup
    //   2266: bipush #61
    //   2268: ldc 66560
    //   2270: iastore
    //   2271: dup
    //   2272: bipush #62
    //   2274: iconst_0
    //   2275: iastore
    //   2276: dup
    //   2277: bipush #63
    //   2279: ldc 16842756
    //   2281: iastore
    //   2282: astore #7
    //   2284: bipush #64
    //   2286: newarray int
    //   2288: dup
    //   2289: iconst_0
    //   2290: ldc -2146402272
    //   2292: iastore
    //   2293: dup
    //   2294: iconst_1
    //   2295: ldc -2147450880
    //   2297: iastore
    //   2298: dup
    //   2299: iconst_2
    //   2300: ldc 32768
    //   2302: iastore
    //   2303: dup
    //   2304: iconst_3
    //   2305: ldc 1081376
    //   2307: iastore
    //   2308: dup
    //   2309: iconst_4
    //   2310: ldc 1048576
    //   2312: iastore
    //   2313: dup
    //   2314: iconst_5
    //   2315: bipush #32
    //   2317: iastore
    //   2318: dup
    //   2319: bipush #6
    //   2321: ldc -2146435040
    //   2323: iastore
    //   2324: dup
    //   2325: bipush #7
    //   2327: ldc -2147450848
    //   2329: iastore
    //   2330: dup
    //   2331: bipush #8
    //   2333: ldc -2147483616
    //   2335: iastore
    //   2336: dup
    //   2337: bipush #9
    //   2339: ldc -2146402272
    //   2341: iastore
    //   2342: dup
    //   2343: bipush #10
    //   2345: ldc -2146402304
    //   2347: iastore
    //   2348: dup
    //   2349: bipush #11
    //   2351: ldc -2147483648
    //   2353: iastore
    //   2354: dup
    //   2355: bipush #12
    //   2357: ldc -2147450880
    //   2359: iastore
    //   2360: dup
    //   2361: bipush #13
    //   2363: ldc 1048576
    //   2365: iastore
    //   2366: dup
    //   2367: bipush #14
    //   2369: bipush #32
    //   2371: iastore
    //   2372: dup
    //   2373: bipush #15
    //   2375: ldc -2146435040
    //   2377: iastore
    //   2378: dup
    //   2379: bipush #16
    //   2381: ldc 1081344
    //   2383: iastore
    //   2384: dup
    //   2385: bipush #17
    //   2387: ldc 1048608
    //   2389: iastore
    //   2390: dup
    //   2391: bipush #18
    //   2393: ldc -2147450848
    //   2395: iastore
    //   2396: dup
    //   2397: bipush #19
    //   2399: iconst_0
    //   2400: iastore
    //   2401: dup
    //   2402: bipush #20
    //   2404: ldc -2147483648
    //   2406: iastore
    //   2407: dup
    //   2408: bipush #21
    //   2410: ldc 32768
    //   2412: iastore
    //   2413: dup
    //   2414: bipush #22
    //   2416: ldc 1081376
    //   2418: iastore
    //   2419: dup
    //   2420: bipush #23
    //   2422: ldc -2146435072
    //   2424: iastore
    //   2425: dup
    //   2426: bipush #24
    //   2428: ldc 1048608
    //   2430: iastore
    //   2431: dup
    //   2432: bipush #25
    //   2434: ldc -2147483616
    //   2436: iastore
    //   2437: dup
    //   2438: bipush #26
    //   2440: iconst_0
    //   2441: iastore
    //   2442: dup
    //   2443: bipush #27
    //   2445: ldc 1081344
    //   2447: iastore
    //   2448: dup
    //   2449: bipush #28
    //   2451: ldc 32800
    //   2453: iastore
    //   2454: dup
    //   2455: bipush #29
    //   2457: ldc -2146402304
    //   2459: iastore
    //   2460: dup
    //   2461: bipush #30
    //   2463: ldc -2146435072
    //   2465: iastore
    //   2466: dup
    //   2467: bipush #31
    //   2469: ldc 32800
    //   2471: iastore
    //   2472: dup
    //   2473: bipush #32
    //   2475: iconst_0
    //   2476: iastore
    //   2477: dup
    //   2478: bipush #33
    //   2480: ldc 1081376
    //   2482: iastore
    //   2483: dup
    //   2484: bipush #34
    //   2486: ldc -2146435040
    //   2488: iastore
    //   2489: dup
    //   2490: bipush #35
    //   2492: ldc 1048576
    //   2494: iastore
    //   2495: dup
    //   2496: bipush #36
    //   2498: ldc -2147450848
    //   2500: iastore
    //   2501: dup
    //   2502: bipush #37
    //   2504: ldc -2146435072
    //   2506: iastore
    //   2507: dup
    //   2508: bipush #38
    //   2510: ldc -2146402304
    //   2512: iastore
    //   2513: dup
    //   2514: bipush #39
    //   2516: ldc 32768
    //   2518: iastore
    //   2519: dup
    //   2520: bipush #40
    //   2522: ldc -2146435072
    //   2524: iastore
    //   2525: dup
    //   2526: bipush #41
    //   2528: ldc -2147450880
    //   2530: iastore
    //   2531: dup
    //   2532: bipush #42
    //   2534: bipush #32
    //   2536: iastore
    //   2537: dup
    //   2538: bipush #43
    //   2540: ldc -2146402272
    //   2542: iastore
    //   2543: dup
    //   2544: bipush #44
    //   2546: ldc 1081376
    //   2548: iastore
    //   2549: dup
    //   2550: bipush #45
    //   2552: bipush #32
    //   2554: iastore
    //   2555: dup
    //   2556: bipush #46
    //   2558: ldc 32768
    //   2560: iastore
    //   2561: dup
    //   2562: bipush #47
    //   2564: ldc -2147483648
    //   2566: iastore
    //   2567: dup
    //   2568: bipush #48
    //   2570: ldc 32800
    //   2572: iastore
    //   2573: dup
    //   2574: bipush #49
    //   2576: ldc -2146402304
    //   2578: iastore
    //   2579: dup
    //   2580: bipush #50
    //   2582: ldc 1048576
    //   2584: iastore
    //   2585: dup
    //   2586: bipush #51
    //   2588: ldc -2147483616
    //   2590: iastore
    //   2591: dup
    //   2592: bipush #52
    //   2594: ldc 1048608
    //   2596: iastore
    //   2597: dup
    //   2598: bipush #53
    //   2600: ldc -2147450848
    //   2602: iastore
    //   2603: dup
    //   2604: bipush #54
    //   2606: ldc -2147483616
    //   2608: iastore
    //   2609: dup
    //   2610: bipush #55
    //   2612: ldc 1048608
    //   2614: iastore
    //   2615: dup
    //   2616: bipush #56
    //   2618: ldc 1081344
    //   2620: iastore
    //   2621: dup
    //   2622: bipush #57
    //   2624: iconst_0
    //   2625: iastore
    //   2626: dup
    //   2627: bipush #58
    //   2629: ldc -2147450880
    //   2631: iastore
    //   2632: dup
    //   2633: bipush #59
    //   2635: ldc 32800
    //   2637: iastore
    //   2638: dup
    //   2639: bipush #60
    //   2641: ldc -2147483648
    //   2643: iastore
    //   2644: dup
    //   2645: bipush #61
    //   2647: ldc -2146435040
    //   2649: iastore
    //   2650: dup
    //   2651: bipush #62
    //   2653: ldc -2146402272
    //   2655: iastore
    //   2656: dup
    //   2657: bipush #63
    //   2659: ldc 1081344
    //   2661: iastore
    //   2662: astore #8
    //   2664: bipush #64
    //   2666: newarray int
    //   2668: dup
    //   2669: iconst_0
    //   2670: sipush #520
    //   2673: iastore
    //   2674: dup
    //   2675: iconst_1
    //   2676: ldc 134349312
    //   2678: iastore
    //   2679: dup
    //   2680: iconst_2
    //   2681: iconst_0
    //   2682: iastore
    //   2683: dup
    //   2684: iconst_3
    //   2685: ldc 134348808
    //   2687: iastore
    //   2688: dup
    //   2689: iconst_4
    //   2690: ldc 134218240
    //   2692: iastore
    //   2693: dup
    //   2694: iconst_5
    //   2695: iconst_0
    //   2696: iastore
    //   2697: dup
    //   2698: bipush #6
    //   2700: ldc 131592
    //   2702: iastore
    //   2703: dup
    //   2704: bipush #7
    //   2706: ldc 134218240
    //   2708: iastore
    //   2709: dup
    //   2710: bipush #8
    //   2712: ldc 131080
    //   2714: iastore
    //   2715: dup
    //   2716: bipush #9
    //   2718: ldc 134217736
    //   2720: iastore
    //   2721: dup
    //   2722: bipush #10
    //   2724: ldc 134217736
    //   2726: iastore
    //   2727: dup
    //   2728: bipush #11
    //   2730: ldc 131072
    //   2732: iastore
    //   2733: dup
    //   2734: bipush #12
    //   2736: ldc 134349320
    //   2738: iastore
    //   2739: dup
    //   2740: bipush #13
    //   2742: ldc 131080
    //   2744: iastore
    //   2745: dup
    //   2746: bipush #14
    //   2748: ldc 134348800
    //   2750: iastore
    //   2751: dup
    //   2752: bipush #15
    //   2754: sipush #520
    //   2757: iastore
    //   2758: dup
    //   2759: bipush #16
    //   2761: ldc 134217728
    //   2763: iastore
    //   2764: dup
    //   2765: bipush #17
    //   2767: bipush #8
    //   2769: iastore
    //   2770: dup
    //   2771: bipush #18
    //   2773: ldc 134349312
    //   2775: iastore
    //   2776: dup
    //   2777: bipush #19
    //   2779: sipush #512
    //   2782: iastore
    //   2783: dup
    //   2784: bipush #20
    //   2786: ldc 131584
    //   2788: iastore
    //   2789: dup
    //   2790: bipush #21
    //   2792: ldc 134348800
    //   2794: iastore
    //   2795: dup
    //   2796: bipush #22
    //   2798: ldc 134348808
    //   2800: iastore
    //   2801: dup
    //   2802: bipush #23
    //   2804: ldc 131592
    //   2806: iastore
    //   2807: dup
    //   2808: bipush #24
    //   2810: ldc 134218248
    //   2812: iastore
    //   2813: dup
    //   2814: bipush #25
    //   2816: ldc 131584
    //   2818: iastore
    //   2819: dup
    //   2820: bipush #26
    //   2822: ldc 131072
    //   2824: iastore
    //   2825: dup
    //   2826: bipush #27
    //   2828: ldc 134218248
    //   2830: iastore
    //   2831: dup
    //   2832: bipush #28
    //   2834: bipush #8
    //   2836: iastore
    //   2837: dup
    //   2838: bipush #29
    //   2840: ldc 134349320
    //   2842: iastore
    //   2843: dup
    //   2844: bipush #30
    //   2846: sipush #512
    //   2849: iastore
    //   2850: dup
    //   2851: bipush #31
    //   2853: ldc 134217728
    //   2855: iastore
    //   2856: dup
    //   2857: bipush #32
    //   2859: ldc 134349312
    //   2861: iastore
    //   2862: dup
    //   2863: bipush #33
    //   2865: ldc 134217728
    //   2867: iastore
    //   2868: dup
    //   2869: bipush #34
    //   2871: ldc 131080
    //   2873: iastore
    //   2874: dup
    //   2875: bipush #35
    //   2877: sipush #520
    //   2880: iastore
    //   2881: dup
    //   2882: bipush #36
    //   2884: ldc 131072
    //   2886: iastore
    //   2887: dup
    //   2888: bipush #37
    //   2890: ldc 134349312
    //   2892: iastore
    //   2893: dup
    //   2894: bipush #38
    //   2896: ldc 134218240
    //   2898: iastore
    //   2899: dup
    //   2900: bipush #39
    //   2902: iconst_0
    //   2903: iastore
    //   2904: dup
    //   2905: bipush #40
    //   2907: sipush #512
    //   2910: iastore
    //   2911: dup
    //   2912: bipush #41
    //   2914: ldc 131080
    //   2916: iastore
    //   2917: dup
    //   2918: bipush #42
    //   2920: ldc 134349320
    //   2922: iastore
    //   2923: dup
    //   2924: bipush #43
    //   2926: ldc 134218240
    //   2928: iastore
    //   2929: dup
    //   2930: bipush #44
    //   2932: ldc 134217736
    //   2934: iastore
    //   2935: dup
    //   2936: bipush #45
    //   2938: sipush #512
    //   2941: iastore
    //   2942: dup
    //   2943: bipush #46
    //   2945: iconst_0
    //   2946: iastore
    //   2947: dup
    //   2948: bipush #47
    //   2950: ldc 134348808
    //   2952: iastore
    //   2953: dup
    //   2954: bipush #48
    //   2956: ldc 134218248
    //   2958: iastore
    //   2959: dup
    //   2960: bipush #49
    //   2962: ldc 131072
    //   2964: iastore
    //   2965: dup
    //   2966: bipush #50
    //   2968: ldc 134217728
    //   2970: iastore
    //   2971: dup
    //   2972: bipush #51
    //   2974: ldc 134349320
    //   2976: iastore
    //   2977: dup
    //   2978: bipush #52
    //   2980: bipush #8
    //   2982: iastore
    //   2983: dup
    //   2984: bipush #53
    //   2986: ldc 131592
    //   2988: iastore
    //   2989: dup
    //   2990: bipush #54
    //   2992: ldc 131584
    //   2994: iastore
    //   2995: dup
    //   2996: bipush #55
    //   2998: ldc 134217736
    //   3000: iastore
    //   3001: dup
    //   3002: bipush #56
    //   3004: ldc 134348800
    //   3006: iastore
    //   3007: dup
    //   3008: bipush #57
    //   3010: ldc 134218248
    //   3012: iastore
    //   3013: dup
    //   3014: bipush #58
    //   3016: sipush #520
    //   3019: iastore
    //   3020: dup
    //   3021: bipush #59
    //   3023: ldc 134348800
    //   3025: iastore
    //   3026: dup
    //   3027: bipush #60
    //   3029: ldc 131592
    //   3031: iastore
    //   3032: dup
    //   3033: bipush #61
    //   3035: bipush #8
    //   3037: iastore
    //   3038: dup
    //   3039: bipush #62
    //   3041: ldc 134348808
    //   3043: iastore
    //   3044: dup
    //   3045: bipush #63
    //   3047: ldc 131584
    //   3049: iastore
    //   3050: astore #9
    //   3052: bipush #64
    //   3054: newarray int
    //   3056: dup
    //   3057: iconst_0
    //   3058: ldc 8396801
    //   3060: iastore
    //   3061: dup
    //   3062: iconst_1
    //   3063: sipush #8321
    //   3066: iastore
    //   3067: dup
    //   3068: iconst_2
    //   3069: sipush #8321
    //   3072: iastore
    //   3073: dup
    //   3074: iconst_3
    //   3075: sipush #128
    //   3078: iastore
    //   3079: dup
    //   3080: iconst_4
    //   3081: ldc 8396928
    //   3083: iastore
    //   3084: dup
    //   3085: iconst_5
    //   3086: ldc 8388737
    //   3088: iastore
    //   3089: dup
    //   3090: bipush #6
    //   3092: ldc 8388609
    //   3094: iastore
    //   3095: dup
    //   3096: bipush #7
    //   3098: sipush #8193
    //   3101: iastore
    //   3102: dup
    //   3103: bipush #8
    //   3105: iconst_0
    //   3106: iastore
    //   3107: dup
    //   3108: bipush #9
    //   3110: ldc 8396800
    //   3112: iastore
    //   3113: dup
    //   3114: bipush #10
    //   3116: ldc 8396800
    //   3118: iastore
    //   3119: dup
    //   3120: bipush #11
    //   3122: ldc 8396929
    //   3124: iastore
    //   3125: dup
    //   3126: bipush #12
    //   3128: sipush #129
    //   3131: iastore
    //   3132: dup
    //   3133: bipush #13
    //   3135: iconst_0
    //   3136: iastore
    //   3137: dup
    //   3138: bipush #14
    //   3140: ldc 8388736
    //   3142: iastore
    //   3143: dup
    //   3144: bipush #15
    //   3146: ldc 8388609
    //   3148: iastore
    //   3149: dup
    //   3150: bipush #16
    //   3152: iconst_1
    //   3153: iastore
    //   3154: dup
    //   3155: bipush #17
    //   3157: sipush #8192
    //   3160: iastore
    //   3161: dup
    //   3162: bipush #18
    //   3164: ldc 8388608
    //   3166: iastore
    //   3167: dup
    //   3168: bipush #19
    //   3170: ldc 8396801
    //   3172: iastore
    //   3173: dup
    //   3174: bipush #20
    //   3176: sipush #128
    //   3179: iastore
    //   3180: dup
    //   3181: bipush #21
    //   3183: ldc 8388608
    //   3185: iastore
    //   3186: dup
    //   3187: bipush #22
    //   3189: sipush #8193
    //   3192: iastore
    //   3193: dup
    //   3194: bipush #23
    //   3196: sipush #8320
    //   3199: iastore
    //   3200: dup
    //   3201: bipush #24
    //   3203: ldc 8388737
    //   3205: iastore
    //   3206: dup
    //   3207: bipush #25
    //   3209: iconst_1
    //   3210: iastore
    //   3211: dup
    //   3212: bipush #26
    //   3214: sipush #8320
    //   3217: iastore
    //   3218: dup
    //   3219: bipush #27
    //   3221: ldc 8388736
    //   3223: iastore
    //   3224: dup
    //   3225: bipush #28
    //   3227: sipush #8192
    //   3230: iastore
    //   3231: dup
    //   3232: bipush #29
    //   3234: ldc 8396928
    //   3236: iastore
    //   3237: dup
    //   3238: bipush #30
    //   3240: ldc 8396929
    //   3242: iastore
    //   3243: dup
    //   3244: bipush #31
    //   3246: sipush #129
    //   3249: iastore
    //   3250: dup
    //   3251: bipush #32
    //   3253: ldc 8388736
    //   3255: iastore
    //   3256: dup
    //   3257: bipush #33
    //   3259: ldc 8388609
    //   3261: iastore
    //   3262: dup
    //   3263: bipush #34
    //   3265: ldc 8396800
    //   3267: iastore
    //   3268: dup
    //   3269: bipush #35
    //   3271: ldc 8396929
    //   3273: iastore
    //   3274: dup
    //   3275: bipush #36
    //   3277: sipush #129
    //   3280: iastore
    //   3281: dup
    //   3282: bipush #37
    //   3284: iconst_0
    //   3285: iastore
    //   3286: dup
    //   3287: bipush #38
    //   3289: iconst_0
    //   3290: iastore
    //   3291: dup
    //   3292: bipush #39
    //   3294: ldc 8396800
    //   3296: iastore
    //   3297: dup
    //   3298: bipush #40
    //   3300: sipush #8320
    //   3303: iastore
    //   3304: dup
    //   3305: bipush #41
    //   3307: ldc 8388736
    //   3309: iastore
    //   3310: dup
    //   3311: bipush #42
    //   3313: ldc 8388737
    //   3315: iastore
    //   3316: dup
    //   3317: bipush #43
    //   3319: iconst_1
    //   3320: iastore
    //   3321: dup
    //   3322: bipush #44
    //   3324: ldc 8396801
    //   3326: iastore
    //   3327: dup
    //   3328: bipush #45
    //   3330: sipush #8321
    //   3333: iastore
    //   3334: dup
    //   3335: bipush #46
    //   3337: sipush #8321
    //   3340: iastore
    //   3341: dup
    //   3342: bipush #47
    //   3344: sipush #128
    //   3347: iastore
    //   3348: dup
    //   3349: bipush #48
    //   3351: ldc 8396929
    //   3353: iastore
    //   3354: dup
    //   3355: bipush #49
    //   3357: sipush #129
    //   3360: iastore
    //   3361: dup
    //   3362: bipush #50
    //   3364: iconst_1
    //   3365: iastore
    //   3366: dup
    //   3367: bipush #51
    //   3369: sipush #8192
    //   3372: iastore
    //   3373: dup
    //   3374: bipush #52
    //   3376: ldc 8388609
    //   3378: iastore
    //   3379: dup
    //   3380: bipush #53
    //   3382: sipush #8193
    //   3385: iastore
    //   3386: dup
    //   3387: bipush #54
    //   3389: ldc 8396928
    //   3391: iastore
    //   3392: dup
    //   3393: bipush #55
    //   3395: ldc 8388737
    //   3397: iastore
    //   3398: dup
    //   3399: bipush #56
    //   3401: sipush #8193
    //   3404: iastore
    //   3405: dup
    //   3406: bipush #57
    //   3408: sipush #8320
    //   3411: iastore
    //   3412: dup
    //   3413: bipush #58
    //   3415: ldc 8388608
    //   3417: iastore
    //   3418: dup
    //   3419: bipush #59
    //   3421: ldc 8396801
    //   3423: iastore
    //   3424: dup
    //   3425: bipush #60
    //   3427: sipush #128
    //   3430: iastore
    //   3431: dup
    //   3432: bipush #61
    //   3434: ldc 8388608
    //   3436: iastore
    //   3437: dup
    //   3438: bipush #62
    //   3440: sipush #8192
    //   3443: iastore
    //   3444: dup
    //   3445: bipush #63
    //   3447: ldc 8396928
    //   3449: iastore
    //   3450: astore #10
    //   3452: bipush #64
    //   3454: newarray int
    //   3456: dup
    //   3457: iconst_0
    //   3458: sipush #256
    //   3461: iastore
    //   3462: dup
    //   3463: iconst_1
    //   3464: ldc 34078976
    //   3466: iastore
    //   3467: dup
    //   3468: iconst_2
    //   3469: ldc 34078720
    //   3471: iastore
    //   3472: dup
    //   3473: iconst_3
    //   3474: ldc 1107296512
    //   3476: iastore
    //   3477: dup
    //   3478: iconst_4
    //   3479: ldc 524288
    //   3481: iastore
    //   3482: dup
    //   3483: iconst_5
    //   3484: sipush #256
    //   3487: iastore
    //   3488: dup
    //   3489: bipush #6
    //   3491: ldc 1073741824
    //   3493: iastore
    //   3494: dup
    //   3495: bipush #7
    //   3497: ldc 34078720
    //   3499: iastore
    //   3500: dup
    //   3501: bipush #8
    //   3503: ldc 1074266368
    //   3505: iastore
    //   3506: dup
    //   3507: bipush #9
    //   3509: ldc 524288
    //   3511: iastore
    //   3512: dup
    //   3513: bipush #10
    //   3515: ldc 33554688
    //   3517: iastore
    //   3518: dup
    //   3519: bipush #11
    //   3521: ldc 1074266368
    //   3523: iastore
    //   3524: dup
    //   3525: bipush #12
    //   3527: ldc 1107296512
    //   3529: iastore
    //   3530: dup
    //   3531: bipush #13
    //   3533: ldc 1107820544
    //   3535: iastore
    //   3536: dup
    //   3537: bipush #14
    //   3539: ldc 524544
    //   3541: iastore
    //   3542: dup
    //   3543: bipush #15
    //   3545: ldc 1073741824
    //   3547: iastore
    //   3548: dup
    //   3549: bipush #16
    //   3551: ldc 33554432
    //   3553: iastore
    //   3554: dup
    //   3555: bipush #17
    //   3557: ldc 1074266112
    //   3559: iastore
    //   3560: dup
    //   3561: bipush #18
    //   3563: ldc 1074266112
    //   3565: iastore
    //   3566: dup
    //   3567: bipush #19
    //   3569: iconst_0
    //   3570: iastore
    //   3571: dup
    //   3572: bipush #20
    //   3574: ldc 1073742080
    //   3576: iastore
    //   3577: dup
    //   3578: bipush #21
    //   3580: ldc 1107820800
    //   3582: iastore
    //   3583: dup
    //   3584: bipush #22
    //   3586: ldc 1107820800
    //   3588: iastore
    //   3589: dup
    //   3590: bipush #23
    //   3592: ldc 33554688
    //   3594: iastore
    //   3595: dup
    //   3596: bipush #24
    //   3598: ldc 1107820544
    //   3600: iastore
    //   3601: dup
    //   3602: bipush #25
    //   3604: ldc 1073742080
    //   3606: iastore
    //   3607: dup
    //   3608: bipush #26
    //   3610: iconst_0
    //   3611: iastore
    //   3612: dup
    //   3613: bipush #27
    //   3615: ldc 1107296256
    //   3617: iastore
    //   3618: dup
    //   3619: bipush #28
    //   3621: ldc 34078976
    //   3623: iastore
    //   3624: dup
    //   3625: bipush #29
    //   3627: ldc 33554432
    //   3629: iastore
    //   3630: dup
    //   3631: bipush #30
    //   3633: ldc 1107296256
    //   3635: iastore
    //   3636: dup
    //   3637: bipush #31
    //   3639: ldc 524544
    //   3641: iastore
    //   3642: dup
    //   3643: bipush #32
    //   3645: ldc 524288
    //   3647: iastore
    //   3648: dup
    //   3649: bipush #33
    //   3651: ldc 1107296512
    //   3653: iastore
    //   3654: dup
    //   3655: bipush #34
    //   3657: sipush #256
    //   3660: iastore
    //   3661: dup
    //   3662: bipush #35
    //   3664: ldc 33554432
    //   3666: iastore
    //   3667: dup
    //   3668: bipush #36
    //   3670: ldc 1073741824
    //   3672: iastore
    //   3673: dup
    //   3674: bipush #37
    //   3676: ldc 34078720
    //   3678: iastore
    //   3679: dup
    //   3680: bipush #38
    //   3682: ldc 1107296512
    //   3684: iastore
    //   3685: dup
    //   3686: bipush #39
    //   3688: ldc 1074266368
    //   3690: iastore
    //   3691: dup
    //   3692: bipush #40
    //   3694: ldc 33554688
    //   3696: iastore
    //   3697: dup
    //   3698: bipush #41
    //   3700: ldc 1073741824
    //   3702: iastore
    //   3703: dup
    //   3704: bipush #42
    //   3706: ldc 1107820544
    //   3708: iastore
    //   3709: dup
    //   3710: bipush #43
    //   3712: ldc 34078976
    //   3714: iastore
    //   3715: dup
    //   3716: bipush #44
    //   3718: ldc 1074266368
    //   3720: iastore
    //   3721: dup
    //   3722: bipush #45
    //   3724: sipush #256
    //   3727: iastore
    //   3728: dup
    //   3729: bipush #46
    //   3731: ldc 33554432
    //   3733: iastore
    //   3734: dup
    //   3735: bipush #47
    //   3737: ldc 1107820544
    //   3739: iastore
    //   3740: dup
    //   3741: bipush #48
    //   3743: ldc 1107820800
    //   3745: iastore
    //   3746: dup
    //   3747: bipush #49
    //   3749: ldc 524544
    //   3751: iastore
    //   3752: dup
    //   3753: bipush #50
    //   3755: ldc 1107296256
    //   3757: iastore
    //   3758: dup
    //   3759: bipush #51
    //   3761: ldc 1107820800
    //   3763: iastore
    //   3764: dup
    //   3765: bipush #52
    //   3767: ldc 34078720
    //   3769: iastore
    //   3770: dup
    //   3771: bipush #53
    //   3773: iconst_0
    //   3774: iastore
    //   3775: dup
    //   3776: bipush #54
    //   3778: ldc 1074266112
    //   3780: iastore
    //   3781: dup
    //   3782: bipush #55
    //   3784: ldc 1107296256
    //   3786: iastore
    //   3787: dup
    //   3788: bipush #56
    //   3790: ldc 524544
    //   3792: iastore
    //   3793: dup
    //   3794: bipush #57
    //   3796: ldc 33554688
    //   3798: iastore
    //   3799: dup
    //   3800: bipush #58
    //   3802: ldc 1073742080
    //   3804: iastore
    //   3805: dup
    //   3806: bipush #59
    //   3808: ldc 524288
    //   3810: iastore
    //   3811: dup
    //   3812: bipush #60
    //   3814: iconst_0
    //   3815: iastore
    //   3816: dup
    //   3817: bipush #61
    //   3819: ldc 1074266112
    //   3821: iastore
    //   3822: dup
    //   3823: bipush #62
    //   3825: ldc 34078976
    //   3827: iastore
    //   3828: dup
    //   3829: bipush #63
    //   3831: ldc 1073742080
    //   3833: iastore
    //   3834: astore #11
    //   3836: bipush #64
    //   3838: newarray int
    //   3840: dup
    //   3841: iconst_0
    //   3842: ldc 536870928
    //   3844: iastore
    //   3845: dup
    //   3846: iconst_1
    //   3847: ldc 541065216
    //   3849: iastore
    //   3850: dup
    //   3851: iconst_2
    //   3852: sipush #16384
    //   3855: iastore
    //   3856: dup
    //   3857: iconst_3
    //   3858: ldc 541081616
    //   3860: iastore
    //   3861: dup
    //   3862: iconst_4
    //   3863: ldc 541065216
    //   3865: iastore
    //   3866: dup
    //   3867: iconst_5
    //   3868: bipush #16
    //   3870: iastore
    //   3871: dup
    //   3872: bipush #6
    //   3874: ldc 541081616
    //   3876: iastore
    //   3877: dup
    //   3878: bipush #7
    //   3880: ldc 4194304
    //   3882: iastore
    //   3883: dup
    //   3884: bipush #8
    //   3886: ldc 536887296
    //   3888: iastore
    //   3889: dup
    //   3890: bipush #9
    //   3892: ldc 4210704
    //   3894: iastore
    //   3895: dup
    //   3896: bipush #10
    //   3898: ldc 4194304
    //   3900: iastore
    //   3901: dup
    //   3902: bipush #11
    //   3904: ldc 536870928
    //   3906: iastore
    //   3907: dup
    //   3908: bipush #12
    //   3910: ldc 4194320
    //   3912: iastore
    //   3913: dup
    //   3914: bipush #13
    //   3916: ldc 536887296
    //   3918: iastore
    //   3919: dup
    //   3920: bipush #14
    //   3922: ldc 536870912
    //   3924: iastore
    //   3925: dup
    //   3926: bipush #15
    //   3928: sipush #16400
    //   3931: iastore
    //   3932: dup
    //   3933: bipush #16
    //   3935: iconst_0
    //   3936: iastore
    //   3937: dup
    //   3938: bipush #17
    //   3940: ldc 4194320
    //   3942: iastore
    //   3943: dup
    //   3944: bipush #18
    //   3946: ldc 536887312
    //   3948: iastore
    //   3949: dup
    //   3950: bipush #19
    //   3952: sipush #16384
    //   3955: iastore
    //   3956: dup
    //   3957: bipush #20
    //   3959: ldc 4210688
    //   3961: iastore
    //   3962: dup
    //   3963: bipush #21
    //   3965: ldc 536887312
    //   3967: iastore
    //   3968: dup
    //   3969: bipush #22
    //   3971: bipush #16
    //   3973: iastore
    //   3974: dup
    //   3975: bipush #23
    //   3977: ldc 541065232
    //   3979: iastore
    //   3980: dup
    //   3981: bipush #24
    //   3983: ldc 541065232
    //   3985: iastore
    //   3986: dup
    //   3987: bipush #25
    //   3989: iconst_0
    //   3990: iastore
    //   3991: dup
    //   3992: bipush #26
    //   3994: ldc 4210704
    //   3996: iastore
    //   3997: dup
    //   3998: bipush #27
    //   4000: ldc 541081600
    //   4002: iastore
    //   4003: dup
    //   4004: bipush #28
    //   4006: sipush #16400
    //   4009: iastore
    //   4010: dup
    //   4011: bipush #29
    //   4013: ldc 4210688
    //   4015: iastore
    //   4016: dup
    //   4017: bipush #30
    //   4019: ldc 541081600
    //   4021: iastore
    //   4022: dup
    //   4023: bipush #31
    //   4025: ldc 536870912
    //   4027: iastore
    //   4028: dup
    //   4029: bipush #32
    //   4031: ldc 536887296
    //   4033: iastore
    //   4034: dup
    //   4035: bipush #33
    //   4037: bipush #16
    //   4039: iastore
    //   4040: dup
    //   4041: bipush #34
    //   4043: ldc 541065232
    //   4045: iastore
    //   4046: dup
    //   4047: bipush #35
    //   4049: ldc 4210688
    //   4051: iastore
    //   4052: dup
    //   4053: bipush #36
    //   4055: ldc 541081616
    //   4057: iastore
    //   4058: dup
    //   4059: bipush #37
    //   4061: ldc 4194304
    //   4063: iastore
    //   4064: dup
    //   4065: bipush #38
    //   4067: sipush #16400
    //   4070: iastore
    //   4071: dup
    //   4072: bipush #39
    //   4074: ldc 536870928
    //   4076: iastore
    //   4077: dup
    //   4078: bipush #40
    //   4080: ldc 4194304
    //   4082: iastore
    //   4083: dup
    //   4084: bipush #41
    //   4086: ldc 536887296
    //   4088: iastore
    //   4089: dup
    //   4090: bipush #42
    //   4092: ldc 536870912
    //   4094: iastore
    //   4095: dup
    //   4096: bipush #43
    //   4098: sipush #16400
    //   4101: iastore
    //   4102: dup
    //   4103: bipush #44
    //   4105: ldc 536870928
    //   4107: iastore
    //   4108: dup
    //   4109: bipush #45
    //   4111: ldc 541081616
    //   4113: iastore
    //   4114: dup
    //   4115: bipush #46
    //   4117: ldc 4210688
    //   4119: iastore
    //   4120: dup
    //   4121: bipush #47
    //   4123: ldc 541065216
    //   4125: iastore
    //   4126: dup
    //   4127: bipush #48
    //   4129: ldc 4210704
    //   4131: iastore
    //   4132: dup
    //   4133: bipush #49
    //   4135: ldc 541081600
    //   4137: iastore
    //   4138: dup
    //   4139: bipush #50
    //   4141: iconst_0
    //   4142: iastore
    //   4143: dup
    //   4144: bipush #51
    //   4146: ldc 541065232
    //   4148: iastore
    //   4149: dup
    //   4150: bipush #52
    //   4152: bipush #16
    //   4154: iastore
    //   4155: dup
    //   4156: bipush #53
    //   4158: sipush #16384
    //   4161: iastore
    //   4162: dup
    //   4163: bipush #54
    //   4165: ldc 541065216
    //   4167: iastore
    //   4168: dup
    //   4169: bipush #55
    //   4171: ldc 4210704
    //   4173: iastore
    //   4174: dup
    //   4175: bipush #56
    //   4177: sipush #16384
    //   4180: iastore
    //   4181: dup
    //   4182: bipush #57
    //   4184: ldc 4194320
    //   4186: iastore
    //   4187: dup
    //   4188: bipush #58
    //   4190: ldc 536887312
    //   4192: iastore
    //   4193: dup
    //   4194: bipush #59
    //   4196: iconst_0
    //   4197: iastore
    //   4198: dup
    //   4199: bipush #60
    //   4201: ldc 541081600
    //   4203: iastore
    //   4204: dup
    //   4205: bipush #61
    //   4207: ldc 536870912
    //   4209: iastore
    //   4210: dup
    //   4211: bipush #62
    //   4213: ldc 4194320
    //   4215: iastore
    //   4216: dup
    //   4217: bipush #63
    //   4219: ldc 536887312
    //   4221: iastore
    //   4222: astore #12
    //   4224: bipush #64
    //   4226: newarray int
    //   4228: dup
    //   4229: iconst_0
    //   4230: ldc 2097152
    //   4232: iastore
    //   4233: dup
    //   4234: iconst_1
    //   4235: ldc 69206018
    //   4237: iastore
    //   4238: dup
    //   4239: iconst_2
    //   4240: ldc 67110914
    //   4242: iastore
    //   4243: dup
    //   4244: iconst_3
    //   4245: iconst_0
    //   4246: iastore
    //   4247: dup
    //   4248: iconst_4
    //   4249: sipush #2048
    //   4252: iastore
    //   4253: dup
    //   4254: iconst_5
    //   4255: ldc 67110914
    //   4257: iastore
    //   4258: dup
    //   4259: bipush #6
    //   4261: ldc 2099202
    //   4263: iastore
    //   4264: dup
    //   4265: bipush #7
    //   4267: ldc 69208064
    //   4269: iastore
    //   4270: dup
    //   4271: bipush #8
    //   4273: ldc 69208066
    //   4275: iastore
    //   4276: dup
    //   4277: bipush #9
    //   4279: ldc 2097152
    //   4281: iastore
    //   4282: dup
    //   4283: bipush #10
    //   4285: iconst_0
    //   4286: iastore
    //   4287: dup
    //   4288: bipush #11
    //   4290: ldc 67108866
    //   4292: iastore
    //   4293: dup
    //   4294: bipush #12
    //   4296: iconst_2
    //   4297: iastore
    //   4298: dup
    //   4299: bipush #13
    //   4301: ldc 67108864
    //   4303: iastore
    //   4304: dup
    //   4305: bipush #14
    //   4307: ldc 69206018
    //   4309: iastore
    //   4310: dup
    //   4311: bipush #15
    //   4313: sipush #2050
    //   4316: iastore
    //   4317: dup
    //   4318: bipush #16
    //   4320: ldc 67110912
    //   4322: iastore
    //   4323: dup
    //   4324: bipush #17
    //   4326: ldc 2099202
    //   4328: iastore
    //   4329: dup
    //   4330: bipush #18
    //   4332: ldc 2097154
    //   4334: iastore
    //   4335: dup
    //   4336: bipush #19
    //   4338: ldc 67110912
    //   4340: iastore
    //   4341: dup
    //   4342: bipush #20
    //   4344: ldc 67108866
    //   4346: iastore
    //   4347: dup
    //   4348: bipush #21
    //   4350: ldc 69206016
    //   4352: iastore
    //   4353: dup
    //   4354: bipush #22
    //   4356: ldc 69208064
    //   4358: iastore
    //   4359: dup
    //   4360: bipush #23
    //   4362: ldc 2097154
    //   4364: iastore
    //   4365: dup
    //   4366: bipush #24
    //   4368: ldc 69206016
    //   4370: iastore
    //   4371: dup
    //   4372: bipush #25
    //   4374: sipush #2048
    //   4377: iastore
    //   4378: dup
    //   4379: bipush #26
    //   4381: sipush #2050
    //   4384: iastore
    //   4385: dup
    //   4386: bipush #27
    //   4388: ldc 69208066
    //   4390: iastore
    //   4391: dup
    //   4392: bipush #28
    //   4394: ldc 2099200
    //   4396: iastore
    //   4397: dup
    //   4398: bipush #29
    //   4400: iconst_2
    //   4401: iastore
    //   4402: dup
    //   4403: bipush #30
    //   4405: ldc 67108864
    //   4407: iastore
    //   4408: dup
    //   4409: bipush #31
    //   4411: ldc 2099200
    //   4413: iastore
    //   4414: dup
    //   4415: bipush #32
    //   4417: ldc 67108864
    //   4419: iastore
    //   4420: dup
    //   4421: bipush #33
    //   4423: ldc 2099200
    //   4425: iastore
    //   4426: dup
    //   4427: bipush #34
    //   4429: ldc 2097152
    //   4431: iastore
    //   4432: dup
    //   4433: bipush #35
    //   4435: ldc 67110914
    //   4437: iastore
    //   4438: dup
    //   4439: bipush #36
    //   4441: ldc 67110914
    //   4443: iastore
    //   4444: dup
    //   4445: bipush #37
    //   4447: ldc 69206018
    //   4449: iastore
    //   4450: dup
    //   4451: bipush #38
    //   4453: ldc 69206018
    //   4455: iastore
    //   4456: dup
    //   4457: bipush #39
    //   4459: iconst_2
    //   4460: iastore
    //   4461: dup
    //   4462: bipush #40
    //   4464: ldc 2097154
    //   4466: iastore
    //   4467: dup
    //   4468: bipush #41
    //   4470: ldc 67108864
    //   4472: iastore
    //   4473: dup
    //   4474: bipush #42
    //   4476: ldc 67110912
    //   4478: iastore
    //   4479: dup
    //   4480: bipush #43
    //   4482: ldc 2097152
    //   4484: iastore
    //   4485: dup
    //   4486: bipush #44
    //   4488: ldc 69208064
    //   4490: iastore
    //   4491: dup
    //   4492: bipush #45
    //   4494: sipush #2050
    //   4497: iastore
    //   4498: dup
    //   4499: bipush #46
    //   4501: ldc 2099202
    //   4503: iastore
    //   4504: dup
    //   4505: bipush #47
    //   4507: ldc 69208064
    //   4509: iastore
    //   4510: dup
    //   4511: bipush #48
    //   4513: sipush #2050
    //   4516: iastore
    //   4517: dup
    //   4518: bipush #49
    //   4520: ldc 67108866
    //   4522: iastore
    //   4523: dup
    //   4524: bipush #50
    //   4526: ldc 69208066
    //   4528: iastore
    //   4529: dup
    //   4530: bipush #51
    //   4532: ldc 69206016
    //   4534: iastore
    //   4535: dup
    //   4536: bipush #52
    //   4538: ldc 2099200
    //   4540: iastore
    //   4541: dup
    //   4542: bipush #53
    //   4544: iconst_0
    //   4545: iastore
    //   4546: dup
    //   4547: bipush #54
    //   4549: iconst_2
    //   4550: iastore
    //   4551: dup
    //   4552: bipush #55
    //   4554: ldc 69208066
    //   4556: iastore
    //   4557: dup
    //   4558: bipush #56
    //   4560: iconst_0
    //   4561: iastore
    //   4562: dup
    //   4563: bipush #57
    //   4565: ldc 2099202
    //   4567: iastore
    //   4568: dup
    //   4569: bipush #58
    //   4571: ldc 69206016
    //   4573: iastore
    //   4574: dup
    //   4575: bipush #59
    //   4577: sipush #2048
    //   4580: iastore
    //   4581: dup
    //   4582: bipush #60
    //   4584: ldc 67108866
    //   4586: iastore
    //   4587: dup
    //   4588: bipush #61
    //   4590: ldc 67110912
    //   4592: iastore
    //   4593: dup
    //   4594: bipush #62
    //   4596: sipush #2048
    //   4599: iastore
    //   4600: dup
    //   4601: bipush #63
    //   4603: ldc 2097154
    //   4605: iastore
    //   4606: astore #13
    //   4608: bipush #64
    //   4610: newarray int
    //   4612: dup
    //   4613: iconst_0
    //   4614: ldc 268439616
    //   4616: iastore
    //   4617: dup
    //   4618: iconst_1
    //   4619: sipush #4096
    //   4622: iastore
    //   4623: dup
    //   4624: iconst_2
    //   4625: ldc 262144
    //   4627: iastore
    //   4628: dup
    //   4629: iconst_3
    //   4630: ldc 268701760
    //   4632: iastore
    //   4633: dup
    //   4634: iconst_4
    //   4635: ldc 268435456
    //   4637: iastore
    //   4638: dup
    //   4639: iconst_5
    //   4640: ldc 268439616
    //   4642: iastore
    //   4643: dup
    //   4644: bipush #6
    //   4646: bipush #64
    //   4648: iastore
    //   4649: dup
    //   4650: bipush #7
    //   4652: ldc 268435456
    //   4654: iastore
    //   4655: dup
    //   4656: bipush #8
    //   4658: ldc 262208
    //   4660: iastore
    //   4661: dup
    //   4662: bipush #9
    //   4664: ldc 268697600
    //   4666: iastore
    //   4667: dup
    //   4668: bipush #10
    //   4670: ldc 268701760
    //   4672: iastore
    //   4673: dup
    //   4674: bipush #11
    //   4676: ldc 266240
    //   4678: iastore
    //   4679: dup
    //   4680: bipush #12
    //   4682: ldc 268701696
    //   4684: iastore
    //   4685: dup
    //   4686: bipush #13
    //   4688: ldc 266304
    //   4690: iastore
    //   4691: dup
    //   4692: bipush #14
    //   4694: sipush #4096
    //   4697: iastore
    //   4698: dup
    //   4699: bipush #15
    //   4701: bipush #64
    //   4703: iastore
    //   4704: dup
    //   4705: bipush #16
    //   4707: ldc 268697600
    //   4709: iastore
    //   4710: dup
    //   4711: bipush #17
    //   4713: ldc 268435520
    //   4715: iastore
    //   4716: dup
    //   4717: bipush #18
    //   4719: ldc 268439552
    //   4721: iastore
    //   4722: dup
    //   4723: bipush #19
    //   4725: sipush #4160
    //   4728: iastore
    //   4729: dup
    //   4730: bipush #20
    //   4732: ldc 266240
    //   4734: iastore
    //   4735: dup
    //   4736: bipush #21
    //   4738: ldc 262208
    //   4740: iastore
    //   4741: dup
    //   4742: bipush #22
    //   4744: ldc 268697664
    //   4746: iastore
    //   4747: dup
    //   4748: bipush #23
    //   4750: ldc 268701696
    //   4752: iastore
    //   4753: dup
    //   4754: bipush #24
    //   4756: sipush #4160
    //   4759: iastore
    //   4760: dup
    //   4761: bipush #25
    //   4763: iconst_0
    //   4764: iastore
    //   4765: dup
    //   4766: bipush #26
    //   4768: iconst_0
    //   4769: iastore
    //   4770: dup
    //   4771: bipush #27
    //   4773: ldc 268697664
    //   4775: iastore
    //   4776: dup
    //   4777: bipush #28
    //   4779: ldc 268435520
    //   4781: iastore
    //   4782: dup
    //   4783: bipush #29
    //   4785: ldc 268439552
    //   4787: iastore
    //   4788: dup
    //   4789: bipush #30
    //   4791: ldc 266304
    //   4793: iastore
    //   4794: dup
    //   4795: bipush #31
    //   4797: ldc 262144
    //   4799: iastore
    //   4800: dup
    //   4801: bipush #32
    //   4803: ldc 266304
    //   4805: iastore
    //   4806: dup
    //   4807: bipush #33
    //   4809: ldc 262144
    //   4811: iastore
    //   4812: dup
    //   4813: bipush #34
    //   4815: ldc 268701696
    //   4817: iastore
    //   4818: dup
    //   4819: bipush #35
    //   4821: sipush #4096
    //   4824: iastore
    //   4825: dup
    //   4826: bipush #36
    //   4828: bipush #64
    //   4830: iastore
    //   4831: dup
    //   4832: bipush #37
    //   4834: ldc 268697664
    //   4836: iastore
    //   4837: dup
    //   4838: bipush #38
    //   4840: sipush #4096
    //   4843: iastore
    //   4844: dup
    //   4845: bipush #39
    //   4847: ldc 266304
    //   4849: iastore
    //   4850: dup
    //   4851: bipush #40
    //   4853: ldc 268439552
    //   4855: iastore
    //   4856: dup
    //   4857: bipush #41
    //   4859: bipush #64
    //   4861: iastore
    //   4862: dup
    //   4863: bipush #42
    //   4865: ldc 268435520
    //   4867: iastore
    //   4868: dup
    //   4869: bipush #43
    //   4871: ldc 268697600
    //   4873: iastore
    //   4874: dup
    //   4875: bipush #44
    //   4877: ldc 268697664
    //   4879: iastore
    //   4880: dup
    //   4881: bipush #45
    //   4883: ldc 268435456
    //   4885: iastore
    //   4886: dup
    //   4887: bipush #46
    //   4889: ldc 262144
    //   4891: iastore
    //   4892: dup
    //   4893: bipush #47
    //   4895: ldc 268439616
    //   4897: iastore
    //   4898: dup
    //   4899: bipush #48
    //   4901: iconst_0
    //   4902: iastore
    //   4903: dup
    //   4904: bipush #49
    //   4906: ldc 268701760
    //   4908: iastore
    //   4909: dup
    //   4910: bipush #50
    //   4912: ldc 262208
    //   4914: iastore
    //   4915: dup
    //   4916: bipush #51
    //   4918: ldc 268435520
    //   4920: iastore
    //   4921: dup
    //   4922: bipush #52
    //   4924: ldc 268697600
    //   4926: iastore
    //   4927: dup
    //   4928: bipush #53
    //   4930: ldc 268439552
    //   4932: iastore
    //   4933: dup
    //   4934: bipush #54
    //   4936: ldc 268439616
    //   4938: iastore
    //   4939: dup
    //   4940: bipush #55
    //   4942: iconst_0
    //   4943: iastore
    //   4944: dup
    //   4945: bipush #56
    //   4947: ldc 268701760
    //   4949: iastore
    //   4950: dup
    //   4951: bipush #57
    //   4953: ldc 266240
    //   4955: iastore
    //   4956: dup
    //   4957: bipush #58
    //   4959: ldc 266240
    //   4961: iastore
    //   4962: dup
    //   4963: bipush #59
    //   4965: sipush #4160
    //   4968: iastore
    //   4969: dup
    //   4970: bipush #60
    //   4972: sipush #4160
    //   4975: iastore
    //   4976: dup
    //   4977: bipush #61
    //   4979: ldc 262208
    //   4981: iastore
    //   4982: dup
    //   4983: bipush #62
    //   4985: ldc 268435456
    //   4987: iastore
    //   4988: dup
    //   4989: bipush #63
    //   4991: ldc 268701696
    //   4993: iastore
    //   4994: astore #14
    //   4996: aload #4
    //   4998: arraylength
    //   4999: istore #15
    //   5001: iload #15
    //   5003: bipush #8
    //   5005: irem
    //   5006: ifeq -> 5030
    //   5009: new java/lang/Exception
    //   5012: dup
    //   5013: sipush #-29226
    //   5016: sipush #-8240
    //   5019: invokestatic a : (II)Ljava/lang/String;
    //   5022: invokespecial <init> : (Ljava/lang/String;)V
    //   5025: athrow
    //   5026: invokestatic a : (Ljava/lang/Throwable;)Ljava/lang/Throwable;
    //   5029: athrow
    //   5030: iconst_2
    //   5031: newarray int
    //   5033: astore #16
    //   5035: iload #15
    //   5037: newarray byte
    //   5039: astore #17
    //   5041: iload #15
    //   5043: bipush #8
    //   5045: idiv
    //   5046: istore #18
    //   5048: iconst_0
    //   5049: istore #19
    //   5051: iload #19
    //   5053: iload #18
    //   5055: if_icmpge -> 5973
    //   5058: iload #19
    //   5060: bipush #8
    //   5062: imul
    //   5063: istore #20
    //   5065: iconst_0
    //   5066: istore #21
    //   5068: iload #21
    //   5070: iconst_2
    //   5071: if_icmpge -> 5160
    //   5074: aload #16
    //   5076: iload #21
    //   5078: aload #4
    //   5080: iload #20
    //   5082: iload #21
    //   5084: iconst_4
    //   5085: imul
    //   5086: iadd
    //   5087: baload
    //   5088: sipush #255
    //   5091: iand
    //   5092: bipush #24
    //   5094: ishl
    //   5095: aload #4
    //   5097: iload #20
    //   5099: iload #21
    //   5101: iconst_4
    //   5102: imul
    //   5103: iadd
    //   5104: iconst_1
    //   5105: iadd
    //   5106: baload
    //   5107: sipush #255
    //   5110: iand
    //   5111: bipush #16
    //   5113: ishl
    //   5114: ior
    //   5115: aload #4
    //   5117: iload #20
    //   5119: iload #21
    //   5121: iconst_4
    //   5122: imul
    //   5123: iadd
    //   5124: iconst_2
    //   5125: iadd
    //   5126: baload
    //   5127: sipush #255
    //   5130: iand
    //   5131: bipush #8
    //   5133: ishl
    //   5134: ior
    //   5135: aload #4
    //   5137: iload #20
    //   5139: iload #21
    //   5141: iconst_4
    //   5142: imul
    //   5143: iadd
    //   5144: iconst_3
    //   5145: iadd
    //   5146: baload
    //   5147: sipush #255
    //   5150: iand
    //   5151: ior
    //   5152: iastore
    //   5153: iinc #21, 1
    //   5156: iload_2
    //   5157: ifeq -> 5068
    //   5160: iconst_0
    //   5161: istore #26
    //   5163: aload #16
    //   5165: iconst_0
    //   5166: iaload
    //   5167: istore #24
    //   5169: aload #16
    //   5171: iconst_1
    //   5172: iaload
    //   5173: istore #23
    //   5175: iload #24
    //   5177: iconst_4
    //   5178: iushr
    //   5179: iload #23
    //   5181: ixor
    //   5182: ldc 252645135
    //   5184: iand
    //   5185: istore #22
    //   5187: iload #23
    //   5189: iload #22
    //   5191: ixor
    //   5192: istore #23
    //   5194: iload #24
    //   5196: iload #22
    //   5198: iconst_4
    //   5199: ishl
    //   5200: ixor
    //   5201: istore #24
    //   5203: iload #24
    //   5205: bipush #16
    //   5207: iushr
    //   5208: iload #23
    //   5210: ixor
    //   5211: ldc 65535
    //   5213: iand
    //   5214: istore #22
    //   5216: iload #23
    //   5218: iload #22
    //   5220: ixor
    //   5221: istore #23
    //   5223: iload #24
    //   5225: iload #22
    //   5227: bipush #16
    //   5229: ishl
    //   5230: ixor
    //   5231: istore #24
    //   5233: iload #23
    //   5235: iconst_2
    //   5236: iushr
    //   5237: iload #24
    //   5239: ixor
    //   5240: ldc 858993459
    //   5242: iand
    //   5243: istore #22
    //   5245: iload #24
    //   5247: iload #22
    //   5249: ixor
    //   5250: istore #24
    //   5252: iload #23
    //   5254: iload #22
    //   5256: iconst_2
    //   5257: ishl
    //   5258: ixor
    //   5259: istore #23
    //   5261: iload #23
    //   5263: bipush #8
    //   5265: iushr
    //   5266: iload #24
    //   5268: ixor
    //   5269: ldc 16711935
    //   5271: iand
    //   5272: istore #22
    //   5274: iload #24
    //   5276: iload #22
    //   5278: ixor
    //   5279: istore #24
    //   5281: iload #23
    //   5283: iload #22
    //   5285: bipush #8
    //   5287: ishl
    //   5288: ixor
    //   5289: istore #23
    //   5291: iload #23
    //   5293: iconst_1
    //   5294: ishl
    //   5295: iload #23
    //   5297: bipush #31
    //   5299: iushr
    //   5300: iconst_1
    //   5301: iand
    //   5302: ior
    //   5303: istore #23
    //   5305: iload #24
    //   5307: iload #23
    //   5309: ixor
    //   5310: ldc -1431655766
    //   5312: iand
    //   5313: istore #22
    //   5315: iload #24
    //   5317: iload #22
    //   5319: ixor
    //   5320: istore #24
    //   5322: iload #23
    //   5324: iload #22
    //   5326: ixor
    //   5327: istore #23
    //   5329: iload #24
    //   5331: iconst_1
    //   5332: ishl
    //   5333: iload #24
    //   5335: bipush #31
    //   5337: iushr
    //   5338: iconst_1
    //   5339: iand
    //   5340: ior
    //   5341: istore #24
    //   5343: iconst_0
    //   5344: istore #25
    //   5346: iload #25
    //   5348: bipush #8
    //   5350: if_icmpge -> 5688
    //   5353: iload #23
    //   5355: bipush #28
    //   5357: ishl
    //   5358: iload #23
    //   5360: iconst_4
    //   5361: iushr
    //   5362: ior
    //   5363: istore #22
    //   5365: iload #22
    //   5367: aload #6
    //   5369: iload #26
    //   5371: iinc #26, 1
    //   5374: iaload
    //   5375: ixor
    //   5376: istore #22
    //   5378: aload #13
    //   5380: iload #22
    //   5382: bipush #63
    //   5384: iand
    //   5385: iaload
    //   5386: istore #21
    //   5388: iload #21
    //   5390: aload #11
    //   5392: iload #22
    //   5394: bipush #8
    //   5396: iushr
    //   5397: bipush #63
    //   5399: iand
    //   5400: iaload
    //   5401: ior
    //   5402: istore #21
    //   5404: iload #21
    //   5406: aload #9
    //   5408: iload #22
    //   5410: bipush #16
    //   5412: iushr
    //   5413: bipush #63
    //   5415: iand
    //   5416: iaload
    //   5417: ior
    //   5418: istore #21
    //   5420: iload #21
    //   5422: aload #7
    //   5424: iload #22
    //   5426: bipush #24
    //   5428: iushr
    //   5429: bipush #63
    //   5431: iand
    //   5432: iaload
    //   5433: ior
    //   5434: istore #21
    //   5436: iload #23
    //   5438: aload #6
    //   5440: iload #26
    //   5442: iinc #26, 1
    //   5445: iaload
    //   5446: ixor
    //   5447: istore #22
    //   5449: iload #21
    //   5451: aload #14
    //   5453: iload #22
    //   5455: bipush #63
    //   5457: iand
    //   5458: iaload
    //   5459: ior
    //   5460: istore #21
    //   5462: iload #21
    //   5464: aload #12
    //   5466: iload #22
    //   5468: bipush #8
    //   5470: iushr
    //   5471: bipush #63
    //   5473: iand
    //   5474: iaload
    //   5475: ior
    //   5476: istore #21
    //   5478: iload #21
    //   5480: aload #10
    //   5482: iload #22
    //   5484: bipush #16
    //   5486: iushr
    //   5487: bipush #63
    //   5489: iand
    //   5490: iaload
    //   5491: ior
    //   5492: istore #21
    //   5494: iload #21
    //   5496: aload #8
    //   5498: iload #22
    //   5500: bipush #24
    //   5502: iushr
    //   5503: bipush #63
    //   5505: iand
    //   5506: iaload
    //   5507: ior
    //   5508: istore #21
    //   5510: iload #24
    //   5512: iload #21
    //   5514: ixor
    //   5515: istore #24
    //   5517: iload #24
    //   5519: bipush #28
    //   5521: ishl
    //   5522: iload #24
    //   5524: iconst_4
    //   5525: iushr
    //   5526: ior
    //   5527: istore #22
    //   5529: iload #22
    //   5531: aload #6
    //   5533: iload #26
    //   5535: iinc #26, 1
    //   5538: iaload
    //   5539: ixor
    //   5540: istore #22
    //   5542: aload #13
    //   5544: iload #22
    //   5546: bipush #63
    //   5548: iand
    //   5549: iaload
    //   5550: istore #21
    //   5552: iload #21
    //   5554: aload #11
    //   5556: iload #22
    //   5558: bipush #8
    //   5560: iushr
    //   5561: bipush #63
    //   5563: iand
    //   5564: iaload
    //   5565: ior
    //   5566: istore #21
    //   5568: iload #21
    //   5570: aload #9
    //   5572: iload #22
    //   5574: bipush #16
    //   5576: iushr
    //   5577: bipush #63
    //   5579: iand
    //   5580: iaload
    //   5581: ior
    //   5582: istore #21
    //   5584: iload #21
    //   5586: aload #7
    //   5588: iload #22
    //   5590: bipush #24
    //   5592: iushr
    //   5593: bipush #63
    //   5595: iand
    //   5596: iaload
    //   5597: ior
    //   5598: istore #21
    //   5600: iload #24
    //   5602: aload #6
    //   5604: iload #26
    //   5606: iinc #26, 1
    //   5609: iaload
    //   5610: ixor
    //   5611: istore #22
    //   5613: iload #21
    //   5615: aload #14
    //   5617: iload #22
    //   5619: bipush #63
    //   5621: iand
    //   5622: iaload
    //   5623: ior
    //   5624: istore #21
    //   5626: iload #21
    //   5628: aload #12
    //   5630: iload #22
    //   5632: bipush #8
    //   5634: iushr
    //   5635: bipush #63
    //   5637: iand
    //   5638: iaload
    //   5639: ior
    //   5640: istore #21
    //   5642: iload #21
    //   5644: aload #10
    //   5646: iload #22
    //   5648: bipush #16
    //   5650: iushr
    //   5651: bipush #63
    //   5653: iand
    //   5654: iaload
    //   5655: ior
    //   5656: istore #21
    //   5658: iload #21
    //   5660: aload #8
    //   5662: iload #22
    //   5664: bipush #24
    //   5666: iushr
    //   5667: bipush #63
    //   5669: iand
    //   5670: iaload
    //   5671: ior
    //   5672: istore #21
    //   5674: iload #23
    //   5676: iload #21
    //   5678: ixor
    //   5679: istore #23
    //   5681: iinc #25, 1
    //   5684: iload_2
    //   5685: ifeq -> 5346
    //   5688: iload #23
    //   5690: bipush #31
    //   5692: ishl
    //   5693: iload #23
    //   5695: iconst_1
    //   5696: iushr
    //   5697: ior
    //   5698: istore #23
    //   5700: iload #24
    //   5702: iload #23
    //   5704: ixor
    //   5705: ldc -1431655766
    //   5707: iand
    //   5708: istore #22
    //   5710: iload #24
    //   5712: iload #22
    //   5714: ixor
    //   5715: istore #24
    //   5717: iload #23
    //   5719: iload #22
    //   5721: ixor
    //   5722: istore #23
    //   5724: iload #24
    //   5726: bipush #31
    //   5728: ishl
    //   5729: iload #24
    //   5731: iconst_1
    //   5732: iushr
    //   5733: ior
    //   5734: istore #24
    //   5736: iload #24
    //   5738: bipush #8
    //   5740: iushr
    //   5741: iload #23
    //   5743: ixor
    //   5744: ldc 16711935
    //   5746: iand
    //   5747: istore #22
    //   5749: iload #23
    //   5751: iload #22
    //   5753: ixor
    //   5754: istore #23
    //   5756: iload #24
    //   5758: iload #22
    //   5760: bipush #8
    //   5762: ishl
    //   5763: ixor
    //   5764: istore #24
    //   5766: iload #24
    //   5768: iconst_2
    //   5769: iushr
    //   5770: iload #23
    //   5772: ixor
    //   5773: ldc 858993459
    //   5775: iand
    //   5776: istore #22
    //   5778: iload #23
    //   5780: iload #22
    //   5782: ixor
    //   5783: istore #23
    //   5785: iload #24
    //   5787: iload #22
    //   5789: iconst_2
    //   5790: ishl
    //   5791: ixor
    //   5792: istore #24
    //   5794: iload #23
    //   5796: bipush #16
    //   5798: iushr
    //   5799: iload #24
    //   5801: ixor
    //   5802: ldc 65535
    //   5804: iand
    //   5805: istore #22
    //   5807: iload #24
    //   5809: iload #22
    //   5811: ixor
    //   5812: istore #24
    //   5814: iload #23
    //   5816: iload #22
    //   5818: bipush #16
    //   5820: ishl
    //   5821: ixor
    //   5822: istore #23
    //   5824: iload #23
    //   5826: iconst_4
    //   5827: iushr
    //   5828: iload #24
    //   5830: ixor
    //   5831: ldc 252645135
    //   5833: iand
    //   5834: istore #22
    //   5836: iload #24
    //   5838: iload #22
    //   5840: ixor
    //   5841: istore #24
    //   5843: iload #23
    //   5845: iload #22
    //   5847: iconst_4
    //   5848: ishl
    //   5849: ixor
    //   5850: istore #23
    //   5852: aload #16
    //   5854: iconst_0
    //   5855: iload #23
    //   5857: iastore
    //   5858: aload #16
    //   5860: iconst_1
    //   5861: iload #24
    //   5863: iastore
    //   5864: iload #19
    //   5866: bipush #8
    //   5868: imul
    //   5869: istore #27
    //   5871: iconst_0
    //   5872: istore #28
    //   5874: iload #28
    //   5876: iconst_2
    //   5877: if_icmpge -> 5966
    //   5880: aload #17
    //   5882: iload #27
    //   5884: iload #28
    //   5886: iconst_4
    //   5887: imul
    //   5888: iadd
    //   5889: aload #16
    //   5891: iload #28
    //   5893: iaload
    //   5894: bipush #24
    //   5896: iushr
    //   5897: i2b
    //   5898: bastore
    //   5899: aload #17
    //   5901: iload #27
    //   5903: iload #28
    //   5905: iconst_4
    //   5906: imul
    //   5907: iadd
    //   5908: iconst_1
    //   5909: iadd
    //   5910: aload #16
    //   5912: iload #28
    //   5914: iaload
    //   5915: bipush #16
    //   5917: iushr
    //   5918: i2b
    //   5919: bastore
    //   5920: aload #17
    //   5922: iload #27
    //   5924: iload #28
    //   5926: iconst_4
    //   5927: imul
    //   5928: iadd
    //   5929: iconst_2
    //   5930: iadd
    //   5931: aload #16
    //   5933: iload #28
    //   5935: iaload
    //   5936: bipush #8
    //   5938: iushr
    //   5939: i2b
    //   5940: bastore
    //   5941: aload #17
    //   5943: iload #27
    //   5945: iload #28
    //   5947: iconst_4
    //   5948: imul
    //   5949: iadd
    //   5950: iconst_3
    //   5951: iadd
    //   5952: aload #16
    //   5954: iload #28
    //   5956: iaload
    //   5957: i2b
    //   5958: bastore
    //   5959: iinc #28, 1
    //   5962: iload_2
    //   5963: ifeq -> 5874
    //   5966: iinc #19, 1
    //   5969: iload_2
    //   5970: ifeq -> 5051
    //   5973: aload #17
    //   5975: aload #17
    //   5977: arraylength
    //   5978: iconst_1
    //   5979: isub
    //   5980: baload
    //   5981: istore #19
    //   5983: aload #17
    //   5985: arraylength
    //   5986: iload #19
    //   5988: isub
    //   5989: newarray byte
    //   5991: astore #5
    //   5993: aload #17
    //   5995: arraylength
    //   5996: aload #5
    //   5998: arraylength
    //   5999: if_icmpge -> 6023
    //   6002: new java/lang/Exception
    //   6005: dup
    //   6006: sipush #-29219
    //   6009: sipush #24979
    //   6012: invokestatic a : (II)Ljava/lang/String;
    //   6015: invokespecial <init> : (Ljava/lang/String;)V
    //   6018: athrow
    //   6019: invokestatic a : (Ljava/lang/Throwable;)Ljava/lang/Throwable;
    //   6022: athrow
    //   6023: iconst_0
    //   6024: istore #20
    //   6026: iload #20
    //   6028: aload #5
    //   6030: arraylength
    //   6031: if_icmpge -> 6051
    //   6034: aload #5
    //   6036: iload #20
    //   6038: aload #17
    //   6040: iload #20
    //   6042: baload
    //   6043: bastore
    //   6044: iinc #20, 1
    //   6047: iload_2
    //   6048: ifeq -> 6026
    //   6051: getstatic burp/Zes.ZW : Ljava/lang/String;
    //   6054: getstatic burp/Zgei.ZN : Ljava/lang/Object;
    //   6057: checkcast java/math/BigInteger
    //   6060: invokevirtual intValue : ()I
    //   6063: bipush #32
    //   6065: irem
    //   6066: invokestatic abs : (I)I
    //   6069: invokevirtual charAt : (I)C
    //   6072: getstatic burp/Zscf.Zu : Ljava/lang/String;
    //   6075: getstatic burp/Ze7e.Z_ : Ljava/lang/Object;
    //   6078: checkcast java/math/BigInteger
    //   6081: invokevirtual intValue : ()I
    //   6084: bipush #32
    //   6086: irem
    //   6087: invokestatic abs : (I)I
    //   6090: invokevirtual charAt : (I)C
    //   6093: if_icmpgt -> 6208
    //   6096: getstatic burp/Zl_f.ZF : Ljava/lang/String;
    //   6099: getstatic burp/Zd9.Zr : Ljava/lang/Object;
    //   6102: checkcast java/math/BigInteger
    //   6105: invokevirtual intValue : ()I
    //   6108: bipush #32
    //   6110: irem
    //   6111: invokestatic abs : (I)I
    //   6114: invokevirtual charAt : (I)C
    //   6117: getstatic burp/Zm7v.ZX : Ljava/lang/String;
    //   6120: getstatic burp/Zm1d.ZS : Ljava/lang/Object;
    //   6123: checkcast java/math/BigInteger
    //   6126: invokevirtual intValue : ()I
    //   6129: bipush #32
    //   6131: irem
    //   6132: invokestatic abs : (I)I
    //   6135: invokevirtual charAt : (I)C
    //   6138: if_icmpgt -> 6208
    //   6141: goto -> 6148
    //   6144: invokestatic a : (Ljava/lang/Throwable;)Ljava/lang/Throwable;
    //   6147: athrow
    //   6148: getstatic burp/Zzna.Zi : Ljava/lang/String;
    //   6151: getstatic burp/Zlg2.ZO : Ljava/lang/Object;
    //   6154: checkcast java/math/BigInteger
    //   6157: invokevirtual intValue : ()I
    //   6160: bipush #32
    //   6162: irem
    //   6163: invokestatic abs : (I)I
    //   6166: invokevirtual charAt : (I)C
    //   6169: getstatic burp/Zbow.Zr : Ljava/lang/String;
    //   6172: getstatic burp/Zzmc.Zg : Ljava/lang/Object;
    //   6175: checkcast java/math/BigInteger
    //   6178: invokevirtual intValue : ()I
    //   6181: bipush #32
    //   6183: irem
    //   6184: invokestatic abs : (I)I
    //   6187: invokevirtual charAt : (I)C
    //   6190: if_icmpgt -> 6208
    //   6193: goto -> 6200
    //   6196: invokestatic a : (Ljava/lang/Throwable;)Ljava/lang/Throwable;
    //   6199: athrow
    //   6200: iconst_1
    //   6201: goto -> 6209
    //   6204: invokestatic a : (Ljava/lang/Throwable;)Ljava/lang/Throwable;
    //   6207: athrow
    //   6208: iconst_0
    //   6209: ireturn
    //   6210: astore_3
    //   6211: new java/lang/Exception
    //   6214: dup
    //   6215: aload_3
    //   6216: invokevirtual getMessage : ()Ljava/lang/String;
    //   6219: invokespecial <init> : (Ljava/lang/String;)V
    //   6222: athrow
    // Exception table:
    //   from	to	target	type
    //   4	6209	6210	java/lang/Throwable
    //   22	198	201	java/lang/Throwable
    //   168	235	238	java/lang/Throwable
    //   205	272	275	java/lang/Throwable
    //   242	309	312	java/lang/Throwable
    //   279	346	349	java/lang/Throwable
    //   316	383	386	java/lang/Throwable
    //   353	420	423	java/lang/Throwable
    //   390	457	460	java/lang/Throwable
    //   427	494	497	java/lang/Throwable
    //   464	531	534	java/lang/Throwable
    //   501	568	571	java/lang/Throwable
    //   538	605	608	java/lang/Throwable
    //   575	642	645	java/lang/Throwable
    //   612	679	682	java/lang/Throwable
    //   649	716	719	java/lang/Throwable
    //   686	753	756	java/lang/Throwable
    //   723	790	793	java/lang/Throwable
    //   760	827	830	java/lang/Throwable
    //   797	864	867	java/lang/Throwable
    //   834	901	904	java/lang/Throwable
    //   871	938	941	java/lang/Throwable
    //   908	975	978	java/lang/Throwable
    //   945	1012	1015	java/lang/Throwable
    //   982	1049	1052	java/lang/Throwable
    //   1019	1086	1089	java/lang/Throwable
    //   1056	1123	1126	java/lang/Throwable
    //   1093	1160	1163	java/lang/Throwable
    //   1130	1197	1200	java/lang/Throwable
    //   1167	1234	1237	java/lang/Throwable
    //   1204	1271	1274	java/lang/Throwable
    //   1241	1308	1311	java/lang/Throwable
    //   1278	1341	1344	java/lang/Throwable
    //   1407	1421	1421	java/lang/Throwable
    //   1432	1445	1448	java/lang/Throwable
    //   1437	1460	1463	java/lang/Throwable
    //   1452	1478	1481	java/lang/Throwable
    //   1467	1508	1511	java/lang/Throwable
    //   1574	1601	1604	java/lang/Throwable
    //   1591	1622	1625	java/lang/Throwable
    //   1608	1652	1655	java/lang/Throwable
    //   1629	1663	1663	java/lang/Throwable
    //   1674	1690	1693	java/lang/Throwable
    //   5001	5026	5026	java/lang/Throwable
    //   5993	6019	6019	java/lang/Throwable
    //   6051	6141	6144	java/lang/Throwable
    //   6096	6193	6196	java/lang/Throwable
    //   6148	6204	6204	java/lang/Throwable
  }
  
  static {
    // Byte code:
    //   0: bipush #10
    //   2: anewarray java/lang/String
    //   5: astore #5
    //   7: iconst_0
    //   8: istore_3
    //   9: ldc '\\tK@\\fmg3itg}g\\tyz}<3/NGx~\\b\\t2Ixg8rZP7JA+jhCNIyJ3<\\t_ ]p3xsyfJd:u]O/ tN*$n]jW(<H\\tB|8V\\tig'
    //   11: dup
    //   12: astore_2
    //   13: invokevirtual length : ()I
    //   16: istore #4
    //   18: bipush #9
    //   20: istore_1
    //   21: iconst_m1
    //   22: istore_0
    //   23: bipush #68
    //   25: iinc #0, 1
    //   28: aload_2
    //   29: iload_0
    //   30: dup
    //   31: iload_1
    //   32: iadd
    //   33: invokevirtual substring : (II)Ljava/lang/String;
    //   36: iconst_m1
    //   37: goto -> 142
    //   40: aload #5
    //   42: swap
    //   43: iload_3
    //   44: iinc #3, 1
    //   47: swap
    //   48: aastore
    //   49: iload_0
    //   50: iload_1
    //   51: iadd
    //   52: dup
    //   53: istore_0
    //   54: iload #4
    //   56: if_icmpge -> 68
    //   59: aload_2
    //   60: iload_0
    //   61: invokevirtual charAt : (I)C
    //   64: istore_1
    //   65: goto -> 23
    //   68: ldc 'o\\b,$F.{)'
    //   70: dup
    //   71: astore_2
    //   72: invokevirtual length : ()I
    //   75: istore #4
    //   77: iconst_4
    //   78: istore_1
    //   79: iconst_m1
    //   80: istore_0
    //   81: bipush #113
    //   83: iinc #0, 1
    //   86: aload_2
    //   87: iload_0
    //   88: dup
    //   89: iload_1
    //   90: iadd
    //   91: invokevirtual substring : (II)Ljava/lang/String;
    //   94: iconst_0
    //   95: goto -> 142
    //   98: aload #5
    //   100: swap
    //   101: iload_3
    //   102: iinc #3, 1
    //   105: swap
    //   106: aastore
    //   107: iload_0
    //   108: iload_1
    //   109: iadd
    //   110: dup
    //   111: istore_0
    //   112: iload #4
    //   114: if_icmpge -> 126
    //   117: aload_2
    //   118: iload_0
    //   119: invokevirtual charAt : (I)C
    //   122: istore_1
    //   123: goto -> 81
    //   126: aload #5
    //   128: putstatic burp/Zexl.a : [Ljava/lang/String;
    //   131: bipush #10
    //   133: anewarray java/lang/String
    //   136: putstatic burp/Zexl.b : [Ljava/lang/String;
    //   139: goto -> 300
    //   142: dup_x2
    //   143: pop
    //   144: invokevirtual toCharArray : ()[C
    //   147: dup_x1
    //   148: arraylength
    //   149: dup_x2
    //   150: pop
    //   151: iconst_0
    //   152: istore #6
    //   154: dup2_x1
    //   155: pop2
    //   156: dup_x2
    //   157: iconst_1
    //   158: if_icmpgt -> 260
    //   161: dup2
    //   162: swap
    //   163: iload #6
    //   165: dup2_x1
    //   166: caload
    //   167: swap
    //   168: iload #6
    //   170: bipush #7
    //   172: irem
    //   173: tableswitch default -> 242, 0 -> 212, 1 -> 217, 2 -> 222, 3 -> 227, 4 -> 232, 5 -> 237
    //   212: bipush #77
    //   214: goto -> 244
    //   217: bipush #58
    //   219: goto -> 244
    //   222: bipush #89
    //   224: goto -> 244
    //   227: bipush #20
    //   229: goto -> 244
    //   232: bipush #24
    //   234: goto -> 244
    //   237: bipush #89
    //   239: goto -> 244
    //   242: bipush #79
    //   244: ixor
    //   245: ixor
    //   246: i2c
    //   247: castore
    //   248: iinc #6, 1
    //   251: dup
    //   252: ifne -> 260
    //   255: dup2
    //   256: dup_x1
    //   257: goto -> 165
    //   260: dup2_x1
    //   261: pop2
    //   262: dup_x2
    //   263: iload #6
    //   265: if_icmpgt -> 161
    //   268: pop
    //   269: new java/lang/String
    //   272: dup_x1
    //   273: swap
    //   274: invokespecial <init> : ([C)V
    //   277: invokevirtual intern : ()Ljava/lang/String;
    //   280: swap
    //   281: pop
    //   282: swap
    //   283: tableswitch default -> 40, 0 -> 98
    //   300: new java/math/BigInteger
    //   303: dup
    //   304: iconst_1
    //   305: bipush #32
    //   307: newarray byte
    //   309: dup
    //   310: iconst_0
    //   311: bipush #27
    //   313: bastore
    //   314: dup
    //   315: iconst_1
    //   316: bipush #-33
    //   318: bastore
    //   319: dup
    //   320: iconst_2
    //   321: bipush #57
    //   323: bastore
    //   324: dup
    //   325: iconst_3
    //   326: bipush #33
    //   328: bastore
    //   329: dup
    //   330: iconst_4
    //   331: bipush #-53
    //   333: bastore
    //   334: dup
    //   335: iconst_5
    //   336: bipush #-13
    //   338: bastore
    //   339: dup
    //   340: bipush #6
    //   342: bipush #54
    //   344: bastore
    //   345: dup
    //   346: bipush #7
    //   348: bipush #99
    //   350: bastore
    //   351: dup
    //   352: bipush #8
    //   354: bipush #-118
    //   356: bastore
    //   357: dup
    //   358: bipush #9
    //   360: bipush #-36
    //   362: bastore
    //   363: dup
    //   364: bipush #10
    //   366: bipush #16
    //   368: bastore
    //   369: dup
    //   370: bipush #11
    //   372: bipush #48
    //   374: bastore
    //   375: dup
    //   376: bipush #12
    //   378: bipush #-79
    //   380: bastore
    //   381: dup
    //   382: bipush #13
    //   384: bipush #34
    //   386: bastore
    //   387: dup
    //   388: bipush #14
    //   390: bipush #65
    //   392: bastore
    //   393: dup
    //   394: bipush #15
    //   396: bipush #62
    //   398: bastore
    //   399: dup
    //   400: bipush #16
    //   402: bipush #44
    //   404: bastore
    //   405: dup
    //   406: bipush #17
    //   408: bipush #-85
    //   410: bastore
    //   411: dup
    //   412: bipush #18
    //   414: bipush #107
    //   416: bastore
    //   417: dup
    //   418: bipush #19
    //   420: bipush #114
    //   422: bastore
    //   423: dup
    //   424: bipush #20
    //   426: bipush #124
    //   428: bastore
    //   429: dup
    //   430: bipush #21
    //   432: bipush #24
    //   434: bastore
    //   435: dup
    //   436: bipush #22
    //   438: bipush #59
    //   440: bastore
    //   441: dup
    //   442: bipush #23
    //   444: bipush #106
    //   446: bastore
    //   447: dup
    //   448: bipush #24
    //   450: bipush #103
    //   452: bastore
    //   453: dup
    //   454: bipush #25
    //   456: bipush #-72
    //   458: bastore
    //   459: dup
    //   460: bipush #26
    //   462: bipush #91
    //   464: bastore
    //   465: dup
    //   466: bipush #27
    //   468: bipush #21
    //   470: bastore
    //   471: dup
    //   472: bipush #28
    //   474: iconst_4
    //   475: bastore
    //   476: dup
    //   477: bipush #29
    //   479: bipush #47
    //   481: bastore
    //   482: dup
    //   483: bipush #30
    //   485: bipush #-45
    //   487: bastore
    //   488: dup
    //   489: bipush #31
    //   491: bipush #10
    //   493: bastore
    //   494: invokespecial <init> : (I[B)V
    //   497: putstatic burp/Zexl.ZG : Ljava/lang/Object;
    //   500: sipush #-29221
    //   503: sipush #-30031
    //   506: invokestatic a : (II)Ljava/lang/String;
    //   509: putstatic burp/Zexl.Zs : Ljava/lang/String;
    //   512: return
  }
  
  private static Throwable a(Throwable paramThrowable) {
    return paramThrowable;
  }
  
  private static String a(int paramInt1, int paramInt2) {
    int i = (paramInt1 ^ 0xFFFF8DDF) & 0xFFFF;
    if (b[i] == null) {
      char[] arrayOfChar = a[i].toCharArray();
      switch (arrayOfChar[0] & 0xFF) {
        case 0:
        
        case 1:
        
        case 2:
        
        case 3:
        
        case 4:
        
        case 5:
        
        case 6:
        
        case 7:
        
        case 8:
        
        case 9:
        
        case 10:
        
        case 11:
        
        case 12:
        
        case 13:
        
        case 14:
        
        case 15:
        
        case 16:
        
        case 17:
        
        case 18:
        
        case 19:
        
        case 20:
        
        case 21:
        
        case 22:
        
        case 23:
        
        case 24:
        
        case 25:
        
        case 26:
        
        case 27:
        
        case 28:
        
        case 29:
        
        case 30:
        
        case 31:
        
        case 32:
        
        case 33:
        
        case 34:
        
        case 35:
        
        case 36:
        
        case 37:
        
        case 38:
        
        case 39:
        
        case 40:
        
        case 41:
        
        case 42:
        
        case 43:
        
        case 44:
        
        case 45:
        
        case 46:
        
        case 47:
        
        case 48:
        
        case 49:
        
        case 50:
        
        case 51:
        
        case 52:
        
        case 53:
        
        case 54:
        
        case 55:
        
        case 56:
        
        case 57:
        
        case 58:
        
        case 59:
        
        case 60:
        
        case 61:
        
        case 62:
        
        case 63:
        
        case 64:
        
        case 65:
        
        case 66:
        
        case 67:
        
        case 68:
        
        case 69:
        
        case 70:
        
        case 71:
        
        case 72:
        
        case 73:
        
        case 74:
        
        case 75:
        
        case 76:
        
        case 77:
        
        case 78:
        
        case 79:
        
        case 80:
        
        case 81:
        
        case 82:
        
        case 83:
        
        case 84:
        
        case 85:
        
        case 86:
        
        case 87:
        
        case 88:
        
        case 89:
        
        case 90:
        
        case 91:
        
        case 92:
        
        case 93:
        
        case 94:
        
        case 95:
        
        case 96:
        
        case 97:
        
        case 98:
        
        case 99:
        
        case 100:
        
        case 101:
        
        case 102:
        
        case 103:
        
        case 104:
        
        case 105:
        
        case 106:
        
        case 107:
        
        case 108:
        
        case 109:
        
        case 110:
        
        case 111:
        
        case 112:
        
        case 113:
        
        case 114:
        
        case 115:
        
        case 116:
        
        case 117:
        
        case 118:
        
        case 119:
        
        case 120:
        
        case 121:
        
        case 122:
        
        case 123:
        
        case 124:
        
        case 125:
        
        case 126:
        
        case 127:
        
        case 128:
        
        case 129:
        
        case 130:
        
        case 131:
        
        case 132:
        
        case 133:
        
        case 134:
        
        case 135:
        
        case 136:
        
        case 137:
        
        case 138:
        
        case 139:
        
        case 140:
        
        case 141:
        
        case 142:
        
        case 143:
        
        case 144:
        
        case 145:
        
        case 146:
        
        case 147:
        
        case 148:
        
        case 149:
        
        case 150:
        
        case 151:
        
        case 152:
        
        case 153:
        
        case 154:
        
        case 155:
        
        case 156:
        
        case 157:
        
        case 158:
        
        case 159:
        
        case 160:
        
        case 161:
        
        case 162:
        
        case 163:
        
        case 164:
        
        case 165:
        
        case 166:
        
        case 167:
        
        case 168:
        
        case 169:
        
        case 170:
        
        case 171:
        
        case 172:
        
        case 173:
        
        case 174:
        
        case 175:
        
        case 176:
        
        case 177:
        
        case 178:
        
        case 179:
        
        case 180:
        
        case 181:
        
        case 182:
        
        case 183:
        
        case 184:
        
        case 185:
        
        case 186:
        
        case 187:
        
        case 188:
        
        case 189:
        
        case 190:
        
        case 191:
        
        case 192:
        
        case 193:
        
        case 194:
        
        case 195:
        
        case 196:
        
        case 197:
        
        case 198:
        
        case 199:
        
        case 200:
        
        case 201:
        
        case 202:
        
        case 203:
        
        case 204:
        
        case 205:
        
        case 206:
        
        case 207:
        
        case 208:
        
        case 209:
        
        case 210:
        
        case 211:
        
        case 212:
        
        case 213:
        
        case 214:
        
        case 215:
        
        case 216:
        
        case 217:
        
        case 218:
        
        case 219:
        
        case 220:
        
        case 221:
        
        case 222:
        
        case 223:
        
        case 224:
        
        case 225:
        
        case 226:
        
        case 227:
        
        case 228:
        
        case 229:
        
        case 230:
        
        case 231:
        
        case 232:
        
        case 233:
        
        case 234:
        
        case 235:
        
        case 236:
        
        case 237:
        
        case 238:
        
        case 239:
        
        case 240:
        
        case 241:
        
        case 242:
        
        case 243:
        
        case 244:
        
        case 245:
        
        case 246:
        
        case 247:
        
        case 248:
        
        case 249:
        
        case 250:
        
        case 251:
        
        case 252:
        
        case 253:
        
        case 254:
        
        default:
          break;
      } 
      char c = '';
      int j = (paramInt2 & 0xFF) - c;
      if (j < 0)
        j += 256; 
      int k = ((paramInt2 & 0xFFFF) >>> 8) - c;
      if (k < 0)
        k += 256; 
      for (byte b = 0; b < arrayOfChar.length; b++) {
        int m = b % 2;
        if (m == 0) {
          arrayOfChar[b] = (char)(arrayOfChar[b] ^ j);
          j = ((j >>> 3 | j << 5) ^ arrayOfChar[b]) & 0xFF;
        } else {
          arrayOfChar[b] = (char)(arrayOfChar[b] ^ k);
          k = ((k >>> 3 | k << 5) ^ arrayOfChar[b]) & 0xFF;
        } 
      } 
      b[i] = (new String(arrayOfChar)).intern();
    } 
    return b[i];
  }
}


/* Location:              C:\Program Files\BurpSuitePro\burpsuite_pro.jar!\burp\Zexl.class
 * Java compiler version: 21 (65.0)
 * JD-Core Version:       1.1.3
 */