package burp;

import java.io.IOException;
import java.io.Reader;
import java.util.Deque;
import java.util.LinkedList;
import javax.swing.text.Segment;
import net.portswigger.Zah;
import net.portswigger.Zk_;

public class Zeyl extends Zeyj {
  private static final char[] Ze;
  
  private static final int[] ZD;
  
  private static final int[] ZY;
  
  private static final int[] ZL;
  
  private static final String[] ZK;
  
  private static final int[] ZX;
  
  private Reader Zp;
  
  private int ZA;
  
  private int ZN = 0;
  
  private char[] Z_;
  
  private int ZP;
  
  private int ZH;
  
  private int Zb;
  
  private int Zv;
  
  private int Zt;
  
  private boolean ZS = true;
  
  private boolean Zk;
  
  private final Deque<Integer> ZO = new LinkedList<>();
  
  private static final String[] a;
  
  private static final String[] b;
  
  private static int[] ZD() {
    int[] arrayOfInt = new int[670];
    int i = 0;
    i = Zc(a(-9377, -19718), i, arrayOfInt);
    return arrayOfInt;
  }
  
  private static int Zc(String paramString, int paramInt, int[] paramArrayOfint) {
    byte b = 0;
    int i = paramInt;
    int j = paramString.length();
    label12: while (b < j) {
      char c1 = paramString.charAt(b++);
      char c2 = paramString.charAt(b++);
      try {
        while (true) {
          paramArrayOfint[i++] = c2;
          if (--c1 <= '\000')
            continue label12; 
        } 
      } catch (ArrayIndexOutOfBoundsException arrayIndexOutOfBoundsException) {
        throw a(null);
      } 
    } 
    return i;
  }
  
  private static int[] Zp() {
    int[] arrayOfInt = new int[670];
    int i = 0;
    i = ZW(a(-9381, 24707), i, arrayOfInt);
    return arrayOfInt;
  }
  
  private static int ZW(String paramString, int paramInt, int[] paramArrayOfint) {
    byte b = 0;
    int i = paramInt;
    int j = paramString.length();
    while (b < j) {
      int k = paramString.charAt(b++) << 16;
      paramArrayOfint[i++] = k | paramString.charAt(b++);
    } 
    return i;
  }
  
  private static int[] Zn() {
    int[] arrayOfInt = new int[25488];
    int i = 0;
    i = ZU(a(-9380, 21726), i, arrayOfInt);
    return arrayOfInt;
  }
  
  private static int ZU(String paramString, int paramInt, int[] paramArrayOfint) {
    byte b = 0;
    int i = paramInt;
    int j = paramString.length();
    label12: while (b < j) {
      char c1 = paramString.charAt(b++);
      char c2 = paramString.charAt(b++);
      c2--;
      try {
        while (true) {
          paramArrayOfint[i++] = c2;
          if (--c1 <= '\000')
            continue label12; 
        } 
      } catch (ArrayIndexOutOfBoundsException arrayIndexOutOfBoundsException) {
        throw a(null);
      } 
    } 
    return i;
  }
  
  private static int[] Zb() {
    int[] arrayOfInt = new int[670];
    int i = 0;
    i = Zs(a(-9383, 21056), i, arrayOfInt);
    return arrayOfInt;
  }
  
  private static int Zs(String paramString, int paramInt, int[] paramArrayOfint) {
    byte b = 0;
    int i = paramInt;
    int j = paramString.length();
    label12: while (b < j) {
      char c1 = paramString.charAt(b++);
      char c2 = paramString.charAt(b++);
      try {
        while (true) {
          paramArrayOfint[i++] = c2;
          if (--c1 <= '\000')
            continue label12; 
        } 
      } catch (ArrayIndexOutOfBoundsException arrayIndexOutOfBoundsException) {
        throw a(null);
      } 
    } 
    return i;
  }
  
  private void Zj(int paramInt) {
    int i = this.Zv + this.ZM;
    Zq(this.Z_, this.Zv, this.ZP - 1, paramInt, i);
    this.Zv = this.ZP;
  }
  
  private void ZY(int paramInt1, int paramInt2, int paramInt3) {
    int i = paramInt1 + this.ZM;
    Zq(this.Z_, paramInt1, paramInt2, paramInt3, i);
  }
  
  public Ze7g Z_(int paramInt1, Segment paramSegment, Zska paramZska, int paramInt2) {
    // Byte code:
    //   0: aload_0
    //   1: invokevirtual ZS : ()V
    //   4: invokestatic Zd : ()Ljava/lang/String;
    //   7: aload_0
    //   8: aload_2
    //   9: getfield offset : I
    //   12: ineg
    //   13: iload #4
    //   15: iadd
    //   16: putfield ZM : I
    //   19: astore #5
    //   21: aload_3
    //   22: invokevirtual ZX : ()I
    //   25: istore #7
    //   27: iload #7
    //   29: lookupswitch default -> 88, 13 -> 56, 15 -> 72
    //   56: iconst_2
    //   57: istore #6
    //   59: aload_0
    //   60: aload_2
    //   61: getfield offset : I
    //   64: putfield ZJ : I
    //   67: aload #5
    //   69: ifnonnull -> 91
    //   72: iconst_4
    //   73: istore #6
    //   75: aload_0
    //   76: aload_2
    //   77: getfield offset : I
    //   80: putfield ZJ : I
    //   83: aload #5
    //   85: ifnonnull -> 91
    //   88: iconst_0
    //   89: istore #6
    //   91: aload_0
    //   92: aload_2
    //   93: putfield ZC : Ljavax/swing/text/Segment;
    //   96: aload_0
    //   97: aload_0
    //   98: getfield Zp : Ljava/io/Reader;
    //   101: invokevirtual Zt : (Ljava/io/Reader;)V
    //   104: aload_0
    //   105: getfield ZO : Ljava/util/Deque;
    //   108: invokeinterface isEmpty : ()Z
    //   113: ifne -> 136
    //   116: aload_0
    //   117: getfield ZO : Ljava/util/Deque;
    //   120: invokeinterface getFirst : ()Ljava/lang/Object;
    //   125: checkcast java/lang/Integer
    //   128: invokevirtual intValue : ()I
    //   131: iload #6
    //   133: if_icmpeq -> 154
    //   136: aload_0
    //   137: iload #6
    //   139: invokevirtual Zw : (I)V
    //   142: aload #5
    //   144: ifnonnull -> 167
    //   147: goto -> 154
    //   150: invokestatic a : (Ljava/lang/Exception;)Ljava/lang/Exception;
    //   153: athrow
    //   154: aload_0
    //   155: iload #6
    //   157: invokevirtual Zc : (I)V
    //   160: goto -> 167
    //   163: invokestatic a : (Ljava/lang/Exception;)Ljava/lang/Exception;
    //   166: athrow
    //   167: aload_0
    //   168: invokevirtual ZU : ()Lburp/Ze7g;
    //   171: areturn
    //   172: astore #8
    //   174: aload #8
    //   176: getstatic net/portswigger/Zk_.UNEXPECTED : Lnet/portswigger/Zk_;
    //   179: invokestatic Zl : (Ljava/lang/Throwable;Lnet/portswigger/Zk_;)V
    //   182: new burp/Ze7g
    //   185: dup
    //   186: invokespecial <init> : ()V
    //   189: areturn
    // Exception table:
    //   from	to	target	type
    //   96	171	172	java/io/IOException
    //   116	147	150	java/io/IOException
    //   136	160	163	java/io/IOException
  }
  
  private void Zw(int paramInt) {
    this.ZO.push(Integer.valueOf(paramInt));
    Zc(paramInt);
  }
  
  private void ZQ() {
    try {
      if (this.ZO.isEmpty())
        return; 
    } catch (ArrayIndexOutOfBoundsException arrayIndexOutOfBoundsException) {
      throw a(null);
    } 
    this.ZO.pop();
    Zc(((Integer)this.ZO.getFirst()).intValue());
  }
  
  private boolean Zm() {
    try {
    
    } catch (ArrayIndexOutOfBoundsException arrayIndexOutOfBoundsException) {
      throw a(null);
    } 
    return (this.Zb >= this.ZC.offset + this.ZC.count);
  }
  
  public final void Zt(Reader paramReader) {
    this.Z_ = this.ZC.array;
    this.Zv = this.ZC.offset;
    this.Zt = this.Zv + this.ZC.count - 1;
    this.Zb = this.ZP = this.ZH = this.ZC.offset;
    this.ZN = 0;
    this.Zp = paramReader;
    this.ZS = true;
    this.Zk = false;
  }
  
  private static char[] ZB(String paramString) {
    char[] arrayOfChar = new char[65536];
    byte b1 = 0;
    byte b2 = 0;
    label12: while (b1 < 126) {
      char c1 = paramString.charAt(b1++);
      char c2 = paramString.charAt(b1++);
      try {
        while (true) {
          arrayOfChar[b2++] = c2;
          if (--c1 <= '\000')
            continue label12; 
        } 
      } catch (ArrayIndexOutOfBoundsException arrayIndexOutOfBoundsException) {
        throw a(null);
      } 
    } 
    return arrayOfChar;
  }
  
  public final void Zc(int paramInt) {
    this.ZN = paramInt;
  }
  
  public final int Zg() {
    return this.ZP - this.Zv;
  }
  
  private void ZP(int paramInt) {
    String str;
    try {
      str = ZK[paramInt];
    } catch (ArrayIndexOutOfBoundsException arrayIndexOutOfBoundsException) {
      Zah.Zl(arrayIndexOutOfBoundsException, Zk_.UNEXPECTED);
      str = ZK[0];
    } 
    throw new Error(str);
  }
  
  public void Zh(int paramInt) {
    try {
      if (paramInt > Zg())
        ZP(2); 
    } catch (ArrayIndexOutOfBoundsException arrayIndexOutOfBoundsException) {
      throw a(null);
    } 
    this.ZP -= paramInt;
  }
  
  public Ze7g ZU() throws IOException {
    // Byte code:
    //   0: aload_0
    //   1: getfield Zt : I
    //   4: istore #6
    //   6: aload_0
    //   7: getfield Z_ : [C
    //   10: astore #7
    //   12: invokestatic Zd : ()Ljava/lang/String;
    //   15: getstatic burp/Zeyl.Ze : [C
    //   18: astore #8
    //   20: getstatic burp/Zeyl.ZL : [I
    //   23: astore #9
    //   25: getstatic burp/Zeyl.ZY : [I
    //   28: astore #10
    //   30: getstatic burp/Zeyl.ZX : [I
    //   33: astore #11
    //   35: astore_1
    //   36: aload_0
    //   37: getfield ZP : I
    //   40: istore #5
    //   42: iconst_m1
    //   43: istore_3
    //   44: aload_0
    //   45: aload_0
    //   46: iload #5
    //   48: dup_x1
    //   49: putfield Zv : I
    //   52: dup_x1
    //   53: putfield Zb : I
    //   56: istore #4
    //   58: aload_0
    //   59: aload_0
    //   60: getfield ZN : I
    //   63: putfield ZA : I
    //   66: iload #4
    //   68: iload #6
    //   70: if_icmpge -> 86
    //   73: aload #7
    //   75: iload #4
    //   77: iinc #4, 1
    //   80: caload
    //   81: istore_2
    //   82: aload_1
    //   83: ifnonnull -> 168
    //   86: aload_0
    //   87: getfield Zk : Z
    //   90: ifeq -> 106
    //   93: goto -> 100
    //   96: invokestatic a : (Ljava/lang/Exception;)Ljava/lang/Exception;
    //   99: athrow
    //   100: iconst_m1
    //   101: istore_2
    //   102: aload_1
    //   103: ifnonnull -> 251
    //   106: aload_0
    //   107: iload #4
    //   109: putfield Zb : I
    //   112: aload_0
    //   113: iload #5
    //   115: putfield ZP : I
    //   118: aload_0
    //   119: invokevirtual Zm : ()Z
    //   122: istore #12
    //   124: aload_0
    //   125: getfield Zb : I
    //   128: istore #4
    //   130: aload_0
    //   131: getfield ZP : I
    //   134: istore #5
    //   136: aload_0
    //   137: getfield Z_ : [C
    //   140: astore #7
    //   142: aload_0
    //   143: getfield Zt : I
    //   146: istore #6
    //   148: iload #12
    //   150: ifeq -> 159
    //   153: iconst_m1
    //   154: istore_2
    //   155: aload_1
    //   156: ifnonnull -> 251
    //   159: aload #7
    //   161: iload #4
    //   163: iinc #4, 1
    //   166: caload
    //   167: istore_2
    //   168: aload #9
    //   170: aload #10
    //   172: aload_0
    //   173: getfield ZA : I
    //   176: iaload
    //   177: aload #8
    //   179: iload_2
    //   180: caload
    //   181: iadd
    //   182: iaload
    //   183: istore #12
    //   185: iload #12
    //   187: iconst_m1
    //   188: if_icmpne -> 198
    //   191: goto -> 251
    //   194: invokestatic a : (Ljava/lang/Exception;)Ljava/lang/Exception;
    //   197: athrow
    //   198: aload_0
    //   199: iload #12
    //   201: putfield ZA : I
    //   204: aload #11
    //   206: aload_0
    //   207: getfield ZA : I
    //   210: iaload
    //   211: istore #13
    //   213: iload #13
    //   215: iconst_1
    //   216: iand
    //   217: iconst_1
    //   218: if_icmpne -> 247
    //   221: aload_0
    //   222: getfield ZA : I
    //   225: istore_3
    //   226: iload #4
    //   228: istore #5
    //   230: iload #13
    //   232: bipush #8
    //   234: iand
    //   235: bipush #8
    //   237: if_icmpne -> 247
    //   240: goto -> 251
    //   243: invokestatic a : (Ljava/lang/Exception;)Ljava/lang/Exception;
    //   246: athrow
    //   247: aload_1
    //   248: ifnonnull -> 66
    //   251: aload_0
    //   252: iload #5
    //   254: putfield ZP : I
    //   257: iload_3
    //   258: ifge -> 269
    //   261: iload_3
    //   262: goto -> 274
    //   265: invokestatic a : (Ljava/lang/Exception;)Ljava/lang/Exception;
    //   268: athrow
    //   269: getstatic burp/Zeyl.ZD : [I
    //   272: iload_3
    //   273: iaload
    //   274: tableswitch default -> 934, 1 -> 930, 2 -> 655, 3 -> 692, 4 -> 665, 5 -> 611, 6 -> 496, 7 -> 920, 8 -> 752, 9 -> 728, 10 -> 849, 11 -> 688, 12 -> 795, 13 -> 559, 14 -> 601, 15 -> 549, 16 -> 591, 17 -> 825, 18 -> 527, 19 -> 514, 20 -> 879, 21 -> 911, 22 -> 702, 23 -> 645, 24 -> 775, 25 -> 621, 26 -> 785, 27 -> 510, 28 -> 523, 29 -> 545, 30 -> 555, 31 -> 587, 32 -> 597, 33 -> 607, 34 -> 617, 35 -> 641, 36 -> 651, 37 -> 661, 38 -> 684, 39 -> 688, 40 -> 698, 41 -> 724, 42 -> 748, 43 -> 771, 44 -> 781, 45 -> 791, 46 -> 821, 47 -> 845, 48 -> 875, 49 -> 907, 50 -> 916, 51 -> 926, 52 -> 930
    //   496: aload_0
    //   497: invokevirtual Zf : ()Lburp/Zska;
    //   500: pop
    //   501: aload_0
    //   502: getfield Zz : Lburp/Ze7g;
    //   505: areturn
    //   506: invokestatic a : (Ljava/lang/Exception;)Ljava/lang/Exception;
    //   509: athrow
    //   510: aload_1
    //   511: ifnonnull -> 36
    //   514: aload_0
    //   515: iconst_1
    //   516: invokevirtual Zh : (I)V
    //   519: aload_0
    //   520: invokevirtual ZQ : ()V
    //   523: aload_1
    //   524: ifnonnull -> 36
    //   527: aload_0
    //   528: bipush #23
    //   530: invokevirtual Zj : (I)V
    //   533: aload_0
    //   534: aload_0
    //   535: getfield ZP : I
    //   538: putfield ZJ : I
    //   541: aload_0
    //   542: invokevirtual ZQ : ()V
    //   545: aload_1
    //   546: ifnonnull -> 36
    //   549: aload_0
    //   550: bipush #18
    //   552: invokevirtual Zj : (I)V
    //   555: aload_1
    //   556: ifnonnull -> 36
    //   559: aload_0
    //   560: aload_0
    //   561: getfield ZJ : I
    //   564: aload_0
    //   565: getfield Zv : I
    //   568: iconst_1
    //   569: isub
    //   570: bipush #15
    //   572: invokevirtual ZY : (III)V
    //   575: aload_0
    //   576: bipush #23
    //   578: invokevirtual Zj : (I)V
    //   581: aload_0
    //   582: bipush #6
    //   584: invokevirtual Zw : (I)V
    //   587: aload_1
    //   588: ifnonnull -> 36
    //   591: aload_0
    //   592: bipush #10
    //   594: invokevirtual Zj : (I)V
    //   597: aload_1
    //   598: ifnonnull -> 36
    //   601: aload_0
    //   602: bipush #23
    //   604: invokevirtual Zj : (I)V
    //   607: aload_1
    //   608: ifnonnull -> 36
    //   611: aload_0
    //   612: bipush #22
    //   614: invokevirtual Zj : (I)V
    //   617: aload_1
    //   618: ifnonnull -> 36
    //   621: aload_0
    //   622: aload_0
    //   623: getfield ZP : I
    //   626: putfield ZJ : I
    //   629: aload_0
    //   630: bipush #8
    //   632: invokevirtual Zj : (I)V
    //   635: aload_0
    //   636: bipush #8
    //   638: invokevirtual Zw : (I)V
    //   641: aload_1
    //   642: ifnonnull -> 36
    //   645: aload_0
    //   646: bipush #6
    //   648: invokevirtual Zj : (I)V
    //   651: aload_1
    //   652: ifnonnull -> 36
    //   655: aload_0
    //   656: bipush #23
    //   658: invokevirtual Zj : (I)V
    //   661: aload_1
    //   662: ifnonnull -> 36
    //   665: aload_0
    //   666: aload_0
    //   667: getfield ZP : I
    //   670: putfield ZJ : I
    //   673: aload_0
    //   674: bipush #13
    //   676: invokevirtual Zj : (I)V
    //   679: aload_0
    //   680: iconst_2
    //   681: invokevirtual Zw : (I)V
    //   684: aload_1
    //   685: ifnonnull -> 36
    //   688: aload_1
    //   689: ifnonnull -> 36
    //   692: aload_0
    //   693: bipush #21
    //   695: invokevirtual Zj : (I)V
    //   698: aload_1
    //   699: ifnonnull -> 36
    //   702: aload_0
    //   703: bipush #23
    //   705: invokevirtual Zj : (I)V
    //   708: aload_0
    //   709: aload_0
    //   710: getfield ZP : I
    //   713: putfield ZJ : I
    //   716: aload_0
    //   717: invokevirtual ZQ : ()V
    //   720: aload_0
    //   721: invokevirtual ZQ : ()V
    //   724: aload_1
    //   725: ifnonnull -> 36
    //   728: aload_0
    //   729: aload_0
    //   730: getfield ZP : I
    //   733: putfield ZJ : I
    //   736: aload_0
    //   737: bipush #23
    //   739: invokevirtual Zj : (I)V
    //   742: aload_0
    //   743: bipush #6
    //   745: invokevirtual Zw : (I)V
    //   748: aload_1
    //   749: ifnonnull -> 36
    //   752: aload_0
    //   753: aload_0
    //   754: getfield ZP : I
    //   757: putfield ZJ : I
    //   760: aload_0
    //   761: bipush #15
    //   763: invokevirtual Zj : (I)V
    //   766: aload_0
    //   767: iconst_4
    //   768: invokevirtual Zw : (I)V
    //   771: aload_1
    //   772: ifnonnull -> 36
    //   775: aload_0
    //   776: bipush #8
    //   778: invokevirtual Zj : (I)V
    //   781: aload_1
    //   782: ifnonnull -> 36
    //   785: aload_0
    //   786: bipush #20
    //   788: invokevirtual Zj : (I)V
    //   791: aload_1
    //   792: ifnonnull -> 36
    //   795: aload_0
    //   796: aload_0
    //   797: getfield ZJ : I
    //   800: aload_0
    //   801: getfield Zv : I
    //   804: iconst_1
    //   805: isub
    //   806: bipush #15
    //   808: invokevirtual ZY : (III)V
    //   811: aload_0
    //   812: bipush #15
    //   814: invokevirtual Zj : (I)V
    //   817: aload_0
    //   818: invokevirtual ZQ : ()V
    //   821: aload_1
    //   822: ifnonnull -> 36
    //   825: aload_0
    //   826: bipush #23
    //   828: invokevirtual Zj : (I)V
    //   831: aload_0
    //   832: aload_0
    //   833: getfield ZP : I
    //   836: putfield ZJ : I
    //   839: aload_0
    //   840: bipush #6
    //   842: invokevirtual Zw : (I)V
    //   845: aload_1
    //   846: ifnonnull -> 36
    //   849: aload_0
    //   850: aload_0
    //   851: getfield ZJ : I
    //   854: aload_0
    //   855: getfield Zv : I
    //   858: iconst_1
    //   859: isub
    //   860: bipush #13
    //   862: invokevirtual ZY : (III)V
    //   865: aload_0
    //   866: bipush #13
    //   868: invokevirtual Zj : (I)V
    //   871: aload_0
    //   872: invokevirtual ZQ : ()V
    //   875: aload_1
    //   876: ifnonnull -> 36
    //   879: aload_0
    //   880: aload_0
    //   881: getfield ZJ : I
    //   884: aload_0
    //   885: getfield Zv : I
    //   888: iconst_1
    //   889: isub
    //   890: bipush #22
    //   892: invokevirtual ZY : (III)V
    //   895: aload_0
    //   896: bipush #23
    //   898: invokevirtual Zj : (I)V
    //   901: aload_0
    //   902: bipush #10
    //   904: invokevirtual Zw : (I)V
    //   907: aload_1
    //   908: ifnonnull -> 36
    //   911: aload_0
    //   912: iconst_1
    //   913: invokevirtual Zj : (I)V
    //   916: aload_1
    //   917: ifnonnull -> 36
    //   920: aload_0
    //   921: bipush #24
    //   923: invokevirtual Zj : (I)V
    //   926: aload_1
    //   927: ifnonnull -> 36
    //   930: aload_1
    //   931: ifnonnull -> 36
    //   934: iload_2
    //   935: iconst_m1
    //   936: if_icmpne -> 1199
    //   939: aload_0
    //   940: getfield Zv : I
    //   943: aload_0
    //   944: getfield Zb : I
    //   947: if_icmpne -> 1199
    //   950: goto -> 957
    //   953: invokestatic a : (Ljava/lang/Exception;)Ljava/lang/Exception;
    //   956: athrow
    //   957: aload_0
    //   958: iconst_1
    //   959: putfield Zk : Z
    //   962: aload_0
    //   963: getfield ZN : I
    //   966: lookupswitch default -> 1197, 0 -> 1094, 2 -> 1172, 4 -> 1133, 6 -> 1158, 8 -> 1108, 10 -> 1076, 671 -> 1090, 672 -> 1104, 673 -> 1129, 674 -> 1154, 675 -> 1168, 676 -> 1193
    //   1072: invokestatic a : (Ljava/lang/Exception;)Ljava/lang/Exception;
    //   1075: athrow
    //   1076: aload_0
    //   1077: invokevirtual Zf : ()Lburp/Zska;
    //   1080: pop
    //   1081: aload_0
    //   1082: getfield Zz : Lburp/Ze7g;
    //   1085: areturn
    //   1086: invokestatic a : (Ljava/lang/Exception;)Ljava/lang/Exception;
    //   1089: athrow
    //   1090: aload_1
    //   1091: ifnonnull -> 36
    //   1094: aload_0
    //   1095: invokevirtual Zf : ()Lburp/Zska;
    //   1098: pop
    //   1099: aload_0
    //   1100: getfield Zz : Lburp/Ze7g;
    //   1103: areturn
    //   1104: aload_1
    //   1105: ifnonnull -> 36
    //   1108: aload_0
    //   1109: aload_0
    //   1110: getfield ZJ : I
    //   1113: aload_0
    //   1114: getfield Zv : I
    //   1117: iconst_1
    //   1118: isub
    //   1119: bipush #22
    //   1121: invokevirtual ZY : (III)V
    //   1124: aload_0
    //   1125: getfield Zz : Lburp/Ze7g;
    //   1128: areturn
    //   1129: aload_1
    //   1130: ifnonnull -> 36
    //   1133: aload_0
    //   1134: aload_0
    //   1135: getfield ZJ : I
    //   1138: aload_0
    //   1139: getfield Zv : I
    //   1142: iconst_1
    //   1143: isub
    //   1144: bipush #15
    //   1146: invokevirtual ZY : (III)V
    //   1149: aload_0
    //   1150: getfield Zz : Lburp/Ze7g;
    //   1153: areturn
    //   1154: aload_1
    //   1155: ifnonnull -> 36
    //   1158: aload_0
    //   1159: invokevirtual Zf : ()Lburp/Zska;
    //   1162: pop
    //   1163: aload_0
    //   1164: getfield Zz : Lburp/Ze7g;
    //   1167: areturn
    //   1168: aload_1
    //   1169: ifnonnull -> 36
    //   1172: aload_0
    //   1173: aload_0
    //   1174: getfield ZJ : I
    //   1177: aload_0
    //   1178: getfield Zv : I
    //   1181: iconst_1
    //   1182: isub
    //   1183: bipush #13
    //   1185: invokevirtual ZY : (III)V
    //   1188: aload_0
    //   1189: getfield Zz : Lburp/Ze7g;
    //   1192: areturn
    //   1193: aload_1
    //   1194: ifnonnull -> 36
    //   1197: aconst_null
    //   1198: areturn
    //   1199: aload_0
    //   1200: iconst_1
    //   1201: invokevirtual ZP : (I)V
    //   1204: goto -> 36
    // Exception table:
    //   from	to	target	type
    //   82	93	96	java/io/IOException
    //   185	194	194	java/io/IOException
    //   230	243	243	java/io/IOException
    //   251	265	265	java/io/IOException
    //   274	506	506	java/io/IOException
    //   934	950	953	java/io/IOException
    //   939	1072	1072	java/io/IOException
    //   957	1086	1086	java/io/IOException
  }
  
  static {
    // Byte code:
    //   0: bipush #8
    //   2: anewarray java/lang/String
    //   5: astore #5
    //   7: iconst_0
    //   8: istore_3
    //   9: ldc '»ÂQONÏª$ÖôÍö¯A.¹ãbB`»OæŃÊſƶvűªŌ6ƸEŷ¿ŖáʝçɢÚɣ?ʤȫΉuͥ¸ΙÌ͌¿ϜΥҡ¡Ѧ#ѲrЍѤշö֪½ֶ4Ԯׅ$ı_ơÍħÝۖØġؖ۰ı\\tơڗņó۷ý۰¨ƴؑ»ݙQ݈N߅ª݃Ö܈Íࢉ¯ࠀ.ǫãŮǟ`ĤƦæƴÊࢡࡩvƮªࢗ6ࢇEज¿ৗá৏çআÚঅ?঎ૄƺuķ¸ƁÌƷ¿ƕžĴ¡Ǧ#ਔr਻ૄૉö௃½௱4ଠா$ௐ_౓Í్Ý೩Øచధನම\\t෠ෑഌóജýĉ¨ฏ໐»ມQ໽NໍªྨÖ༃Íདྷ¯࿕.ཻãཐგ`ჵ၂æဌÊႤᇻvᄺªᅩ6ᄨEᅇ¿ቆáኛçኦÚሿ?ኳኅĨuጛ¸፴ÌᏗ¿ŝڙǈ¡ٻ#ŇrٯنܑöᎠ½ᎉ4ᓻᑉ$ᑲ_ᐓÍᐑÝࢎØᕴᖘ࢑ছ\\tᖐᗹᕫóᖞýᘻ¨ᙷᙗ»ᙉQᙸN៵ª᜷Ö៸Íឥ¯ĳ.ᝯãᠰᠠ`ᢉᣫæᡛÊƀƙvĮª᡹6᤺Eᤕ¿ᤜáᧀç᧝Úᩀ?ᩌᩪ᪵u᪶¸įÌᬼ¿ᮠ᭔ᮭ¡ᯑ#ǖrᬓᰯᲆöᰜ½ᱸ4ᱯᵥ$ᶝ_ᴈÍĸÝěØᵂᴊữẮ\\tḀừḩóỖýἲ¨Ŗᾣ»ἭQᾒNἂª⁷ÖₚÍ‏¯⁜.⁬ã⅐ℬ`℈⇛æ⅝Ê⇠ڱv⋙ª≙6∪E≃¿≊á⏆ç࠹Ú⌎?⏯⏸ǝuǕ¸ǓÌ⍳¿⒳⑐⒇¡␪#④r␧▩╖ö┆½┻4Ʒ┨$⚊_ƐÍ☟Ý⛍Ø⚼⛕✔⟑\\t⟯ǖ✆ó❙ý✥¨⠎ǖ»⡓Q⢧NĢªƕÖ⡾Í⣭¯⤲.⦗ã⧝⥳`ő⦆æĮÊ⫼⨬vǴªƂ6ƁEĜ¿ǭá⫤ç⫣Úƹ?⪻⪄⭸u⬟¸⭚Ì⯨¿⭌ⱳ⳧¡Ⳣ#چrⳋⲞⴎöⷧ½⵱4ⷴⶸ$ࣜ_ⶖÍ⸋ÝăØ⺱⻊⸝⺆\\t⾿⾲⽸ó⼊ý⼃¨ノり»やQほN〻ªゔÖㅺÍㅟ¯ㅒ.㇩ãㅬ㉷`㉧㋲æ㋤Ê㊛㌺v㍠ª㍌6㎮E㎱¿㍺á㓢ç㒫Ú㒸?㐡㒹㗽u㖉¸ŊÌ㗠¿㗕㗈㘈¡㘗#㛐r㚅㙱㘑ö㟺½㟰4㟢㜘$㜦_㢫Í㠰Ý㠨Ø㠀㡂ǆ㦟\\t㥀㥉㧃óűý㦒¨㤞㩮»ĺQ㩚N㪇ª㨋Ö㨁Í㮨¯Ĵ.㬟ã㯌ơ`㬕㯠æǢÊ㱥ſv㲒ª㰒6㱥EŘ¿㳵áŕçģÚ㳙?㷣㷓㶆u㶔¸㶷Ì㺙¿㹶㻠㸙¡㹡#㾂r㼃㾵㽝ö㿿½㼌4ډ䂭$䂢_䀍Í䂖Ý䂂Ø䅧ࢨ䅏䆲\\t䄋䄒䊞ó䈸ýŇ¨䊶䉉»䋨Q䈢N䎜ªļÖ䎫Í䏋¯䌺.䎂ã䒫ġ`䓥䒢æ䓮ÊŚ䑂vǅªƤ6䔕E䖴¿䖤áƻçǰÚŽ?䕳䗷䗰u䚴¸䚁Ì䙩¿䘚䘓䝕¡䟞#䞇r䝍䝎䠔ö䢤½ĩ4䠹ſ$䡆_䠉Í䠞Ý䤛ØǌƵǘ䥲\\tǇ䤵䦐ó䦏ýŻ¨䩁ĉ»ƨQ䨘N䨭ª䪠Ö䩖Í䭤¯䯟.䬮ãپہ`䮫䬑æ䭮Ê䱠䳻vࡂªࡐ6䰯E䳣¿䱞á䵄ç䵙ÚĤ?䶸ǢŰu䶐¸䴕Ì仫¿乚下乆¡京#仙r侖伥佩ö伛½俾4倕傔$僉_偤Í僿Ý儣Ø冏冁冨Ƥ\\tĝ儮击ó剪ý刟¨剝勨»勘Q叠N単ª叨ÖڅÍ厬¯厒.君ã呄ࣘ`哞吁æ吆Ê咋Ōv嗤ª嗾6ĎEǭ¿唃á唣ç喡Ú囏?嚽噔噲u噎¸坠Ì垿¿垶圼圞¡埍#堓r塵ħǹö壳½ť4塠堮$奊_妘Í夼Ý奏Ø奖娦媐ė\\tūŰ娢ó婣ý؈¨ٽ۔»威Q࢟N࣫ªࢨÖ媽Í嬝¯宴.寏ã寎ŉ`嬶尌æ岷Ê岭峨v屮ª崑6巉E嵉¿嶱á崗ç嵉Ú廰?幼庎廗u廘¸徔Ì彃¿彇张徻¡悛#性r惑恅惽ö悁½愥4懶慠$慏_愬Í找Ý抋Ø抒抪払挃\\t揓挻ōóۨý࢓~wáâxèO!)*\\fgÆûäkØ]Þ­ÓÚdò5ú£Se)(çËÊC¢R`\\fA±±9ObÖJáá¥wÄé®Á.äÃv< ÄÇ;òP/<8|uEíU1ô¨JîôÛ?\\b¤A7µÑ\\f³z8I\\tmtîú~6ø®ﾪ>vTRê\»¼ÓEÚ§¸Õ] r>ùÒÍù·»7<~-É~lï~WÀòTÀ\\t³/H­7jð)ÜÐ°5)°N¹GÀóuhº:3´äó¸5È\\f¼·ázÏÔö^Ãó÷1$\\b>øàæìz¢lÖ4¬}êjKù¾ÚGla¬Ø·9«wµȊy©O#SE³\\bU!Àhý%³òhJJ~hùÄ³H4±îq+\\nc2(F7kÑZ2}ÎSðö5éå¥âÔ\\r¬Vn\\bËe=¬äÉ?yÐû+¨yò)¦aÂo½MFýÊßfJ¯ø\\rüqê/kAÔLÞµ\\b°Ù!HÀ¼vòªT á¯®OÅØ-Rî«ÒÏ«¯çÊä¢Zo×¨®räA\¥ÙpøÎZì8ãÌ¥U´ÈÓ4ÔÑ\\b©Í·ÜßI¿ê³Asy8Z(`å,&²ðQKJ¦S4.¥t\\rºÝ¬»ãUhNoÃñ]\\t»î³ìÜB}ç,´¤'ëx(Eoh¿:eq»Ö¿#³50T¦-÷âxD(?A6Òk¦ö5½æWEÄx+Qv9tÆÉºzd(º«ýEßÊ¸t´Ü¤\\t9¨ôäüÝ²Z|ºUÊßøñ`ÐÎÑ¯%¤ßë\\f{`(n-àVÛCepWëÑÞO1³l"qµÜÓ÷;ð±æEÌþ\\fGaî8}|a´½ ÃêúÚ6²õé®Y\\to.©°vÂnbÕXÔnáÇqO"L( '¤Tè¾¨ÝpÀIã\\tË²d^¹E¯Gð98g1,l²`÷øg#è¤¾\\f¨WÇÁ\#JÎåîAóÏ^Ä¨eÓ«4TNØ>'ý'
    //   11: dup
    //   12: astore_2
    //   13: invokevirtual length : ()I
    //   16: istore #4
    //   18: sipush #1340
    //   21: istore_1
    //   22: iconst_m1
    //   23: istore_0
    //   24: bipush #75
    //   26: iinc #0, 1
    //   29: aload_2
    //   30: iload_0
    //   31: dup
    //   32: iload_1
    //   33: iadd
    //   34: invokevirtual substring : (II)Ljava/lang/String;
    //   37: iconst_m1
    //   38: goto -> 144
    //   41: aload #5
    //   43: swap
    //   44: iload_3
    //   45: iinc #3, 1
    //   48: swap
    //   49: aastore
    //   50: iload_0
    //   51: iload_1
    //   52: iadd
    //   53: dup
    //   54: istore_0
    //   55: iload #4
    //   57: if_icmpge -> 69
    //   60: aload_2
    //   61: iload_0
    //   62: invokevirtual charAt : (I)C
    //   65: istore_1
    //   66: goto -> 24
    //   69: ldc 'ICyQØ2#µOBÚF\\b÷¨cïù_À[5Çv·⤠FÆ,#ÅÅù(ê¢(Öá¬Àòâu6*ä[ªtWKx(kÐ)ÎxÀkü9tòÌä#+/~+i[8Ðû[i¾¨yHËÂß)Z:\\nÇC¦Ö4|Õ ­öÒbdÖ\\nÃ7ÓAákéNé$y`ÜªEôß­-vK[l{WI0*À<ÆÁGÙý;B¥¹÷úlü¥ó2E\\t`ÇÚ#èëÍ'MÐáéé${`Sªyôß-.kù;ÃÕù«"´äÐÇT%ÖèäëïÜJüRÙé(>Ûe\\bà%4nÁVFY_P]ÕôG%K¼5O±NçÀ¹.ÑÍjÆoK:RÔ&O#K® e\\r;¹Ïå­}O¢ÆöÂ\\nZ\\fí"vÔ°7BQU0ÚùcÁ»"â&Ó ¢ôðúæ.Èò7}Dm-ì7JüÚHç«b§DGù)éõ£@CWIõ*,þÅEÂ7·k:fë¬ÍÄi$0ô1OKÌbúÜeH:¥O^Ly,øÿâÿÇ"Êå,§×Rúæ¹6øª#O³>:mähô¬ñÖfM}õµ1ôÝ³s%<!ódqlHÙ¨TVÒ_}"¯Ð+sÀÌÑ<ô¸JÀRåé>ädq6nBÐR-ÆÌ; ÂEÊC|¿3{ôh-^´@¢´Iæ[ªÍ÷[@ùÝVo"ãm-\\bÜÃ>:Uú°âÁ&Å  ÷¿ï ØMµ§Ð!\øÌÛaû¡¹óòÿ­¼í mÔÊ[yS,êÕ<\\dúqÒÙRT\\tÒ´ 1 ÃÞ~µè$«¡/}A\\fÌ8D¢Î%í.Zf¤xû-'p4Ø@Dì`9ÄÄÚØíxt%÷CI­AGË°ÅÆÅøùÙ±Ø_e0¶üxÊØûtVÖv\\ny\6¼ þã}¾[ø?pµyPWî?Æ¿d';ù~\\b)hÕ¯ÛðÉÏô©/Giâ÷l(%ÓÔxÈ­v6Ú;p^¨@sþ)n¥R·z{ZÔ¾Ì!vÖÏÀS[OáüVÿÐ\\rµÖTåì5p¶A±ZVò,ÿWH£ä`xk®#w\\#úäÒúJRã\\tY¶>0ZÌ¾);P¿H ´s+|Dåb%~cpèn?lóBû(Õb)^ÑÁJ§ë^Tî6Èqy7Ý ¯ñ(B[Ô¼æQTï\YÈÔfé1ê2ø!ÖüòÆèpÉ"\\rÿÉçã^Øâñã&¨\\fÿe\\b+ñÂ\\rN½4äØZYîA\­ïÏÇØëÎÔúÐ×· ;³Èoågx¢I5é­Upp¯ª¶¿Aìü7\VÒ¿Mµð¶ÜÊáØª¿UÊå¶WyðÓ¡]q¼oÎ:qÔ2&¯6ï´'4@¯âIGGÊ¿YBÖø \\nÃ]\\tä¬ôPD«,6o[öôÙzûihéêÙ ·7{5úp²ì&ªC<Î%zW²Gæ<ôc4ÏHÁ]ó®ÈÑ.26T=Å9EÃÜ\\t~NH=ÉNZÔQ­¦Ü9¡uÂyB´#£Ï¸µ]óO®^ÈÒ.¼¬7Ãí6TýhÅ|E\\tNa¿â§îú°NlMD\\f ¢xØæÇT7`òM¯ÁX ¬m3íÇð²FêêDôn÷*\©âûF¨d`ådãà$T¦!ÕsE\\rBhí%/ÿ(Éø¼_HD'©uâß¡vÀ<[ßø+OÁçíYÊq ÇãoËNì6áÌdO\UÚåÜÕ=¦F¦i6;ÇÄ6ðqãv©ãÞ'H¼a5C0MÖÇÚÏ½T°ÌÌYÚ1ñàÃÛ÷_\\r¨ùï^ÎÛ|ÙFàAª2+ÏÁZÜ#´Î5\\t<3°áMð\\f~¸\\biþÊ|ç:e*yù¯gÂkðÏEÜÏÈñ$DSù²QBÓ'9¼³GÁ69JØ ¾¦që¼Ë­f®1|ÇU°fNÿ>ðvwhL®,Û=\\r\W($mLÂ«  ÐÂ\\t×Uf^g~Õ,mÿP©Ç]Ä&ñ4-`\\n¬åÇ_]©9=¬pïóÝÓ.0EØµ¬YZp Ù´µ¤PîØtÆÖd\\n;\~¼)þÂ}Æ4ä%YW$yL@«P ÚÂFÿX¾erîÜ`±çLm\\tÆla¥\\r©»û)°ÔUÛ8¬t|£}ÝË\\ný\\bmå:\å®È`CÄ­ÇL\\bAn\\nbDQ×â(\\b CÕÊ,·&R¬¿úbÓäâFDG*×hWt5$SËÈ0ºàmF:%å-Ïög[ö¼\\tæÜQ8ïo\È\\bÑð-×1\)M\\fñ=îÀ/V3)}3@|ßXöÜ}^ÇjªSwlX½bîxY©gâ÷¡\©AçÄ¤NDuÞ\Ù-Î@ ÎÎIÔ9O\\tµÁ`%WÆ}°\\ryw­>ÚYlÍäT>¼3 ã«o\\rNd¡-[æ3I¶¿÷ [¡ÉýD:\ï¶^2Cãû¹ÆñÕ§iÃ¡û½µö$\\t³ëîVù:5ûq×¸ç\\rË-j ±°¤Á£ÁØÒá3TÄå±äLæÅ¥^Ý2YiB´¯-æ[;ÍÅ]1À<ÏPì??%BåÚkAûÿfê3¸\\tµNO'^Òb¼XplÌ¼ÀÖå\\r®ÐUÌ7G;«Bâ$!¤¥òzKÃÒ]¾'·¼¼-ç4Aá.ÈEýÎÌ3V¯#R~¸C§68P'm¿Z¡e]¹\\t\\b½Ç áÅ(Yb/z²+W=RÖÊW?/òDôË»øbÃÿ¾r(Û_­ [OÞé#'ÚvC¿¤ík0ÕëÑÊoÏ¶O<?¬>`¯É/APÂCd7ôNElÁD/ ¼¢?û0ÇDæpËL 4¬;~G§L.ia4,1JSÍæb% ³U/}M>µ9\\n×¤ÊNûmVGvóyÑ6Æ í\\t°ÂYk1Åñ¤OÛdI¸³RØjKBÞx ªi:»Ákìqa`D~¤kéç&@kxZ"·æUy©½àZÓOJ^!KB1öeÃ÷OxþJìíû ¨zè«¾Ñ¿Äg²:@ûfÛjÙîËAÈ±kéÚ±^z¤mÌxIÙ4`±è¤ ²ÍóûìÂå'Æ<#x`±¨ø¦³Él¨ï·?S¦øöwÇî<>ïe\\n\\f6/ßÒ3VÄXÃ@Ëc»Ñ·ò36Ç©»mà}ÈMãƺÈõè_ñV$wSvQjB§'ƽfĒ×\\tÆC \\nocµ¹fáÑi\\rǋk¸`²NÄt3\\rgH(àjđv'ÓþMSÀ¥ºvòÌ&G§FČ*%|é×*Xé<ÛîRŌÝ¯¡"ã5+ µ,õÝ-kõŷ°>®EwaKû6e{YñŞì­í´m*°5!!MóÄu\\nrŒµNŁ ÀpcaEt^5Ö¿íÔÅ8zƩÍ\\f£V£»ú:ò(]0{VžÄuÇZ[îCOÞó©úÈñºĲ èÒÍæ¤¬£ä?à"MŐn¥ưR[®wÇ¹Dç?áþ9\\bÞ£ÄÑÙ¨îğp09NkqÈ-ǌjzÀR}ÌÆVz\\bê@Ïßãm«´ƚi ó|Üà²DêXêDõn×3Xƽ,õÖ9³Ô?tuþƠUnW*IA¹G°wÆ8ÅZiƍ¤Å1ú´âáFF5,!Èßv¡ƀâëgÄ`ñÃº6T-ÅŒ6"ëæõ÷oçÚ2­ä_ġ»­¯å"Í¹4CúÉ0z^ØÏŧûáãUÙ\\bò¤vxÚÛ`l®.÷ƷHÀ½@aØb÷ËßPX¯gÅǭf¿4THâÁ3>ÿÏÈŬ×ǻ_®.aÞ1«òKøË¼Ü\\tBĥ®ķr¹._gÅÈÉ7$ÿ³ßAAƭjûz¨dî~å§à+µ£Ɗxc\.\\få©.ß¤,xS¬Hǟ¿òC¾kÔ$ó"Üç>êU?Ɠ5ây¡È×2<dßY+ýxì8pŊ»K§Ì¶k{Ð¸`êèþ¹·ÐßŎ9Úö×·5Td/ÍwnôQIxǲúÊûVv£yi6 *ñç¬žÞEÉî ^§`üOÇz(İí¬ê0ÿÏZÑÙ!Eó³ÅÓ©ĻÕØlË1dV»MaBG£°ńÍ0Nû.Üó©z70îQêCğÁwD¬(Y¸ümbIïRÝǏ¯Y\\r1ª»Õsq¹4¡Q-ǺZtæ³+.Ù¿À÷qâĚ:m]z|>rJíÕ0ÕEâ6:ƣL=X©\\nf×/RF#ƐÈKô1Hö¤ÃÔĨPçGĺV\\ntÓ8`ÓÛasõĵ»Ë¡©(a÷«êÓ:Ù8¤ÒǇXÓ}÷gTÎ¯\\fàW|±}ÒƎç%%|æØa|H3í Ê\\bSĒ®§2\`/d'T¥ÝcÜòNƆ)gǁL­dZ÷âVHln.Æõ\\rǠn¬r6ÓØÐ9?òò>^5¹ƈƣ7u0»º'cÊjúZ\^ǖ}áàÛtµT~.í/hþÛp òàƸ¡äíÿ(B­õ©Äz|'+>cƸ·õ8Þ ¾i:ã«këqmŞM{ǵÝRV ?N5u}\\bÆ¢ÏW ?ǽ(Êdkª£¼Uµ@cºÍEqıƛ´üSu¼µ+%ëßã^}Y8ŵÊµzK¨ÊÛ1³ITq_þ=Âÿoxǁ±wKÓûçefūÛSó¯T­Éí¾mǷ0f¥´_gÃ~ÎÕ\\rmºPø©ĕ!Éòéâ ,3æCÍæ+BĶqÓÙ\SCJøÏEäè«ŖksÈ,8kºº-ªAö¶p¹\\rĤmvCÓrMÂÀº0òGÌ?t§2Ņ´Îä±>Yîsa¾Êjn«¤6Į(³¨lÂZ)¶¨uÐÆ»·4®ÿǳôÎ*°à´Õ3ôäHGí3ćÕ)«}£ÈòiiªDó*Ýà»Áƛôþ"tç@Àý:ç,Î$Ƽ£Nlbñùè\\nà¥¿ètƙIû­b¯{yàbÞé¯ï*Èǫ÷çÀý1ç,ä$Ví+aĒ{nÛ¬2hË®¼½6ØC'¸0ş#\\r&\\rÅ*_$<zMìƣ &¨Åþ¥¯rè¾Ì Wŉ=CÝ\EJ`&.CÔuÙÄĂ=±eîà`±Lm@\\t`Ìcŭ:?üý¨3|©-÷ ¿ HÞXżç=SÏÈ0ºà-F;4Å<ņÅjW=³ZûèºuöÁ`&ÜRǚJ»Wa#L£?n3}¾\\ntƻ)î9`çËZÛèÞIŭ\\rïÀ ÿ£1îìÿÅ*h+5ÃƐÇc%.6xÜ²L,ta-ÍüÖǢúà'þS¥Óvßi&7D1EƺI¹*_çÕÈÉw$÷³íAWǯºA±2áMÏ$ZA#r9Ð÷æƀ×(Nll/D@ ¢Iþ"ÉçPǰ¦9kñ½ª b%Öye9>EƸz\\tÜõ8poÆú\\bÑ'¢Óŵ§¦qâ¼áfJ1­ØÈtpƱÉm½°­!9MèßÄº\\n[¼ÉĂÆ¸bxeW:µZ¯|æ~vă¶0ÌÑNK4ä%YÌö× lŷþo¶HtÀ+0÷°äÂKCÌ1}ĥÍáåì p'QÇ)jðĻÑQ[×YGC8ļh3Ƙ1jÊKÿË\Ü\\tÜŔOßðŶúEú\\näúËééÑ&º`1èł¥½Ï/GY[ãìh;jÄå¶Ʃ\\tRã­{V§`Ö)07f´>ZƠÿnõÍÙ)ú¥»ÒÓOC{Ĺ¨Èy(Ý¯þâ§öæôĩpãÞjòhâëcdjÇºŝ¹Dëïªï$}\\tÉä,=/äÀ\\r£ƶh½L£,Lº¡i1iÕE^Ċs¸t\\f2.69AüörÉ]`lǝRñ9qÀFÖæ`6ÙÝíï~1Ů£%6ý{Òþ àz¸ýÖœe'þSH¥`v:&ïCáBď¦z9(FlÑqÜõl×]ƐâÇo¢¼<R]ë>FzÈƞá\\bhúwÑX ßÓà¿SôŽ)P°RÀNÄĨm`;®¥põi¼æiƠÝ¨ÓzSÖ2m[´\pâéþÿǸ¦_ñéãÀñ»ûÞÉé\ƣ°µM«\\f]xwØõæ ½ă;Æ·dëüJ ¥¦qå¼íĈ~ã#¾,ÁÝíkkp09$ǈ7íð\6({Ò§FWlc?ĸë f\\tÖV«×b_\\ryv5Tqś(QMB'H¼µGõ9ÁXÞ©8ę_\\t;W°ëþÞ³â{~¿PŠàuW\\f#$L?Ø3Ì}d\\r/ĆÆUlò[×Ì®Ö¼|5,ò\\nǈÓ§S¬]/½ägJñ\\t·ǅZ&¡av¾sÍÓn 0ä¥8ÜüôÅňnzÍU&¸µ£5ðq²WƘuÎ;±ÅYs¾fÊÕn\¤l6Oǳ°nØ×Ì-èX¨×}[À(@ØƗfä¥9îgõ~\\bÕÕm¡P©ôǏ$V½aMbËºßõX\\rñÑƷøÀÒå½yçÞ£i«Áƾs{Ë-ëg¾;­Qðv:¡ǹ'ÈA2·ÊQCc¿vy-ňBîµÙKcÕ¼\\r¸fñ¥Úúǰé\\r'v3¿zÐrð!]|>_QŮ*qGÖJìJÿû+¨~èq¾ĦÐ8xÑßæ ëÔ 9¡)¦\ŔQüoxNÁ¡ð[<3R¶ËÛNîĻs-Æ îH`Þv&*gáÚÿ¿Ļ4¸\\nÊvÕ§uVloÌNõUiøōê$Èì»ò^wY2Ô óüÜ³Ơ8Ë<cP»{âò6©mµ}bĭNþU¶t(+-÷ä¶KÍ1CǮÜm{ÃÓe\\nÆ~ál¡Əâ³ÕÒt2F)ê}Çò¡iǦí&´mxmëÙ©ÃZAưýk?wÐbsÌ²<5¸5ÀŁ±»D*lÉ1é +3C7Ũ°6Ë®O(øŖL¸ėtu>~pÒmÄd:-ŊÿfRÖ\\rÂ\Õ(mNÂ ÁÐƮl~ÿ¦Zvkx:¹ ãgBO.êźêÈfÏÙE[Ø'5¨¤B¦Ƅ\\\rFõ\\b#§±áà\Ky Ɨ©¬zM\\rþ¸>½ SbÎY5\\tƸøF#ÒÖÆ¿`/M²~1H4#ƨ\\b¼5( MBÚº½CAÙƖsß¥Å°5pcÍÉúÛÞĂÊ´3µ¯nÝ\\r:u[µ$ì¡ǶýåUj±ñNÏN"o-N²Íǻ±¹¿ÐÔ)RhÚØ@Í§î\\b´ũ?¨'W½WWÿ°ö~z£Ûƞ¢ê\\rò»¢û°ÔÛÙ¬nhķãkÉ;ÓÛaÌöJ( ôƥÖ'3?¨o}(u¤\\n×«~njǕ\f;iäÖ´H ÐµKÊrƉøñ«f£ÈiäªõóÝ&ºVÀũÕtsÔÍTÑBUjòÅÌî®Ć-TçAôÈcýÏ]TňI)¿?Àkq¢4¥!Ä^Ǚ7³[É¬Í¾i`01DOtK4űÄ¶.ÌN34ë%¸Ì¶ö! tƣ*,'yAºVM~Ø2ºåūwJ9ñòC _Öòyû4íHŧÞã¡Ó´^,éÝèkËp:9¸Ə²ªðÐ§I¦S)u¸MxèƕÓøÖÀw]RiïloZ÷Ý)¢ě«{«×Ó©Æåo¡ôx\\tèßđ¢ì'á±óxß`¸TZÊƓM8ánoúHwXißúà¢º÷ñŐ{©7ã6ÀÛhLà÷¾]r¨ōÚFÖÕÀØ]¹ilÀZÚ¥ǇD¸9µHQOú^BÒ¼brÞĢ&ÞF\\f¹|º,íóÒ==ßǅì¶êsÿ§ZÜÙ-!qó5Ó¢ǙâæèË@ÅÈÛuÙ\\r¥AǾ]VViEHÇ+ °ÄÀGŔ \@.JWôð#ÉÄ';@æ1Ňý/¤ø(]ld/N@ÆIGþÙǭÍ(OmKÂ@ ´Ð!=×AÆÐ2ůµ$¬SBµîÊ¢6xwƬùI@'ª-ð4¦)Ū:ª~\\rq3Q÷CXÊ¨ü\\rŨãsÒ½ÑyRç%ÞüOô¡©ËƈÜýYiÑ ³ŐA'ƣgÏþÛ® 6ļy\\bA¤jðÚ£l%. ­îÚ0ǛÝh 5MÏf6Ç¡j&ÐƝé7nóoÔÄ¿$â3<u\\tºÇ0Ą;V­Æ§©t¸èÒ\\bû«<PÑŘ7Y?7/ÈÍN®5Ç½xiǤ*q|Ytî/×ñ\Y(ó)ƟmÌp~hè©?2N¢Êƞë±JîÜ6&Ú¾3êÂ¿T2ƿÈ±¶,*\\tîº@¢QäLÇĦP<Ð%¾=\\r¼8Ûû¤PýLŉÜ­ØÌ¿è¸×5[(ªNƄÒÒÆ}Yf<äÞ*sr)HÖİ`=5Mp²²ù&ÃC£Îz´KÏ[Ƶ«Òú¸ÊÙó\»^§éø\\nûǍÂBír/óÿÃ(ø¤¼0ÿåýƬqòJiÅDw*,àÄOË®öǏ!Aú@ýg´nFzÕV,Øe¹źg(ÌN4¸{ÌñsQ-r2ġ'QÍwx&`æT\\tZ÷V¦ýSļÔ ÷Flu%YçXyå@Qƻñ1%;¾P[c¤ÎV|¦¹AàRč¶skÏ¯Ð­¦ec±uHIöĹ¡åá¦ë\\f\\fDj)"fYS½ƙ·7( SÝÏkÄwL9Úöø:ƘÿnFbtQþXÊ­ûÚÁÉíǓrC/J&õChuU-ƫÙ¦yFÒïL*&-'Ê¥ǳzã]f@úÇý:Ñ tÓŴ lƈ=ÕÚl1lVºM>eB\\tO³¸ƙÔ¯v\\b)¢ë<µèEGx>umıúÃ0Q^e~µøPvèlzǟ`÷_|HJaèC^0YÖZĿD7¸²SÏÛkÍwm9¶Úxø Ǝ¦xäWJ:õZÎ|^æm~jÀßě<¤ßsX cÜ¹8â×çË¡ǫ[äÎÞKfsq¹TÊnúi7Çƕõ:=]'{+Í§µa8¾ÐJĚº¢<"èmE½×«\\bÅsƞ4¥+Ó²h'i×èï¼WÔÏ\\rìuĂ¬²\\tB/Y=ðÖy=Ú'ðɅ-+e³¹ÊW)¢òýh¾Z@ȭÅR,\C¸J2SE\\nñ³ɠ¬)ýèÍz]ú+»Óurʦ¢¯Ȱýph¨$Ü\³ÒÀòÌBöxˎµØñ'%X{èh»dÔ*æ˫§»>9Ã­Hc¦:(˙IµG¡ªmè ¼nØ)s´Ñ29ʤëh¹ÿ^=ÜæÂðõåȆA´Ê4ý¯UI±ÊÏ¿"-Ãʸ1úȃyÈÙ×á2Sd2YýÏãÎʼ]¸²ÑÄMÓ\\rw(jñȘá£òniADç*>àËn®ÏȦ¨}bÀe@Øµ¯÷ȉk uLxY³6ñGWNHj¬J˪Àôîy~á§ô¼+Bµ«ȅï0nâ¢u\\fQõ7§ÑS¦Èuʮô3ø±ÈGäe?iÒË¡kȺaIJÔ8\\b±â´GkMÎlʥ4MÜñMîÀÒ/Ý3 Ãêµɒy*N¸.´þ©°N70>EðWɡOZ+î'OYó©¨Èñº?¹^ɞ\\fîÀº/Û´3TÃËê®GN?|ȂeøÅwjhñÝ¦(ãã ªʼ?Tý]hÚðÖ½ßBÊõ\\tȶ ¨û|Ú- zùHëÞf&hgéʟäËÄ¯HIYp¬3$Å\¼Ü¥ˠt²Ç06Èã<©ã26´ʟ*;%äûm©-ÑÃm4C˛ª³t0\\f%C|)Øò|ËȬ.ögtÅ«`7lÿûÇY˻q\\fæ§ÎY=Cb²íòþ´OÚȿV¸²jZÛÍêmA¶ga¹ɨÏåy pìF¡Q#-=ôȬ]ÞGú/-h%rmQE˕sxyMvf?ÐUWÂN*ôɑN°e¹¶ËZ¢öR{ý¶¥Fcʷ·sÌ¼°Ïª)â8E0No%O\\fɫÓ<Þ\\fdðq·ÙWT©Ò«ɤ:ó»ÛÕ²~qy4ûQd×(Yáɪ.ë«cÉqI®JsëÍØºȁîµ~x§ÇÚ+µ«½BȊ­6-\\bÖy'ËGÝ^LʛI\\nJ\S¼æþ} \\nUÓ}`0Û7ʫ^ô£<®;i·ëJJ¯ ¦ɟaÊHÞ &göÿ¬§$ʶ+ö\\f{#¦Áüª)Oñ>%:äï˄NÁØ`ÍÜÐç§>f¬˧B<9zªìõ³Ñ5b)êʼGÔoóHÜÀ>0°uÂ¼CÈyʶ) fpÂ~ªHA¯OV1Áqäɽ[aJ>\!Ã­5cÆ5* ɤ¿xl×Ï­DÒ5HÜWKÿUʹÒ#:~µC¢§36¾'wtüQȨÛ²jCïÂÔ}&´s9wÛ\\b ã}ʀ7vfGÐU¾Âãô?txÒȤPfVfH¿#_¤Küɿ\\t6Z,|sµµß¡ì1Ä5ȋg!Bk¯;z¯ë×/é3;®EȲuìé ¹eMQM\\rYKD ˭Ç÷|ãK> \\b¢Ãñ9¬ð&\\rȇSº?¡IùT"suBl˒ÔT]ÔÚgÖOB_³ÿ¦ʉkNÙ ¶sküÛ¯gîrÀș«%düZO÷ô©V\l).ÅȈ\\rÜ£fo¼_ßÉ£ì¤K2¢˪éÔä?Þuf´qATÕniKÇ˜õ:í]'8+¥§µ°a\\f¹VMɲU h@b\\n°ɂÛG[ßì;ðÄ»å¥ˡxD\\ruF\\rÉ\\b#W±ÿàNɼ©sí,ê8:ºU-*A#qw\\n˼êP=U¾°Îaû¶àÄ-ɒS/ð1´³]c\\fsµz[(âʖ§d[`Îùå"é~&3ȧmÝ`e».×m.±ÞyxG\\fɿ6¯S¼ø+°ê%¹ã v]3ɍ 2]\\tLIGó Ú&±-ô\\nÌ½Uȣ«2b=\\n9/ÃFÜ p{FɧfdÑ\\r^È»BÒ\\tÈöN·ɚ3wL, Ý¨k¢pM9ONk\\nʚÙÄ!OóÓc-/ýxoʣz&7f/iÍ¿í5j½°µʊIàsD¸X«õ'×BXë®sGʧ8ÜÑfÝofv˟®£¤w÷©çʖG ðXÈÛ¥fÄ>ÓE{j8ȸõFÖH=oiøåµgcÑȡ1'þ¦ivÜhéµÚQ˼î:]'+§§,µÒa=°µDɭ}û:jåçÙ v«×êo4Eˍú7ûN¨ÕdõÖå ¤à~Ô£ɨx\;.\\fÖ©Ø¤¯]Fȷx×}ymÇv^§hã%ɓÂêºû]~£ipãɊÉéU8R÷tstÍ*Ñ¦Uʓ|ï#à~+C\\f§#6Áª'Or>Wɘ|¸-xW-:Z[|æU~ȉ;¼Êf1ºʷÿê÷pÛÛn­­æG1ʙ¢k: R0Bâ.øÐü°ÞɕÂÛª÷A1Oä1ÝqlI;zʀ°ýÈª»ÿ^ÚwNY©2Ç ìðú¿˯­ÏÔÁë¸ðÛ5ÚªNNȏÃYíðwÊùqfdÇã]ÚÃýˈ¹å, *p¹ìôQ)hðˎÑÃ[7_#ÅFRQuõLZȾöOþ¢éxØjæ©Ô~ˆ\\fÈ*·Ðìɩ·â¡êSx*æßʈL9UUÊ²¥Ño0 ©p˭ÌßT´mþc¤Ï¶¡ä¶^˸}âùÁ­¯Ȇy®Õ¯£_7ÎzÌñʊ7¾Ã§=;>Go<ñq>FɦÐI¸ÿ\\fC.ò76De-¦7)ʉã=5ZAèæu ¥Á¡îTx=ɭr0»×Êæ#´|æɯoçBæ´PMÅzÄ\\n[V¼ȒÏeº8è_¡þ¿iË´ñʟZò¤9C5&®¬O£M7Cssøʻ¾=\\fè\\nÓ`fÛ×Ys(ɽ²ÔÃÂ®i\\f]s,z#(ÇÝþì¯ʆ71+¦²CÌAsýuisÜ/ȽUß¹ËÑìíç@«§Ì§ʿ6çÏæÎP°ÅqzöVPØˤjsXÌ¡°ª9âEíNf)¥ ȣV­ê¿ ¸´ôþ?°¤N\\n½ʿ¼q#GÁJñìÊt>ZÕP:¥!:ʳôä'XQ{Öè»IÔ>ï˸;ð.Q"B=ÿ÷/(ø\(-˨«ØÐYosî»fb-æ¦ɼ¯í§@xÀêÚJªIˠ"MwHµP9ÕÁÓÛØ=ȹòÂBtÿr§áÐY÷»ëDʕÙÂ/ývæHj¡((J¤!Õɷò6´¾§ôs÷È\º.QWZɺCüxÁJðã<YR>§Íøɟ¯vR÷ÕC¦¦p¹èùȔü?é±¸ùµýþð\\bWáʚÉÌ¬ñ7QÏrE[ú¹fÙ«Ñȣjl«ê¢O%i)Eàr½êô·íÿʝ÷1)ýÖÙÍ+ÔN8Òúöü3ɧÖ¨xÃßÄæè.Ñõ]sª9Ëˑ¼½ñPXÄPg(ÐÛÌÔÈf¶ʅa¾4ßS\½ñJÚêÿ5ÉÀ˲Ôotð)L\\fîC)÷òÊ!Ȱ½f+ÙÇÑùgõîXí©^ʷ¹d+ý*2æ´Ñùyg¸<ÃȌzòÓ7ßD2-nò{9»5l&+¢Ã˖ÂaúåãÜ\\fg7foæî\\bʀÎ¸¿ðÐ)ÒJxÚòCç_´ț>k©ÈwSk×oô:d©&ØɻÀ³z0Ã·+4rÇ/J~Uzɾ¥OÝ3Â\\n²ý\\bÍå¸Uµ§ʏ»lmz%>YJM¼0=E2E>ɕÐv1Ú<¹_²Uþ~ÃÔ71,ʕ*[Ë¯+JÊ'
    //   71: dup
    //   72: astore_2
    //   73: invokevirtual length : ()I
    //   76: istore #4
    //   78: bipush #29
    //   80: istore_1
    //   81: iconst_m1
    //   82: istore_0
    //   83: bipush #109
    //   85: iinc #0, 1
    //   88: aload_2
    //   89: iload_0
    //   90: dup
    //   91: iload_1
    //   92: iadd
    //   93: invokevirtual substring : (II)Ljava/lang/String;
    //   96: iconst_0
    //   97: goto -> 144
    //   100: aload #5
    //   102: swap
    //   103: iload_3
    //   104: iinc #3, 1
    //   107: swap
    //   108: aastore
    //   109: iload_0
    //   110: iload_1
    //   111: iadd
    //   112: dup
    //   113: istore_0
    //   114: iload #4
    //   116: if_icmpge -> 128
    //   119: aload_2
    //   120: iload_0
    //   121: invokevirtual charAt : (I)C
    //   124: istore_1
    //   125: goto -> 83
    //   128: aload #5
    //   130: putstatic burp/Zeyl.a : [Ljava/lang/String;
    //   133: bipush #8
    //   135: anewarray java/lang/String
    //   138: putstatic burp/Zeyl.b : [Ljava/lang/String;
    //   141: goto -> 300
    //   144: dup_x2
    //   145: pop
    //   146: invokevirtual toCharArray : ()[C
    //   149: dup_x1
    //   150: arraylength
    //   151: dup_x2
    //   152: pop
    //   153: iconst_0
    //   154: istore #6
    //   156: dup2_x1
    //   157: pop2
    //   158: dup_x2
    //   159: iconst_1
    //   160: if_icmpgt -> 259
    //   163: dup2
    //   164: swap
    //   165: iload #6
    //   167: dup2_x1
    //   168: caload
    //   169: swap
    //   170: iload #6
    //   172: bipush #7
    //   174: irem
    //   175: tableswitch default -> 242, 0 -> 212, 1 -> 217, 2 -> 222, 3 -> 227, 4 -> 232, 5 -> 237
    //   212: bipush #59
    //   214: goto -> 243
    //   217: bipush #33
    //   219: goto -> 243
    //   222: bipush #99
    //   224: goto -> 243
    //   227: bipush #17
    //   229: goto -> 243
    //   232: bipush #42
    //   234: goto -> 243
    //   237: bipush #22
    //   239: goto -> 243
    //   242: iconst_4
    //   243: ixor
    //   244: ixor
    //   245: i2c
    //   246: castore
    //   247: iinc #6, 1
    //   250: dup
    //   251: ifne -> 259
    //   254: dup2
    //   255: dup_x1
    //   256: goto -> 167
    //   259: dup2_x1
    //   260: pop2
    //   261: dup_x2
    //   262: iload #6
    //   264: if_icmpgt -> 163
    //   267: pop
    //   268: new java/lang/String
    //   271: dup_x1
    //   272: swap
    //   273: invokespecial <init> : ([C)V
    //   276: invokevirtual intern : ()Ljava/lang/String;
    //   279: swap
    //   280: pop
    //   281: swap
    //   282: tableswitch default -> 41, 0 -> 100
    //   300: sipush #-9382
    //   303: sipush #-3051
    //   306: invokestatic a : (II)Ljava/lang/String;
    //   309: invokestatic ZB : (Ljava/lang/String;)[C
    //   312: putstatic burp/Zeyl.Ze : [C
    //   315: invokestatic ZD : ()[I
    //   318: putstatic burp/Zeyl.ZD : [I
    //   321: invokestatic Zp : ()[I
    //   324: putstatic burp/Zeyl.ZY : [I
    //   327: invokestatic Zn : ()[I
    //   330: putstatic burp/Zeyl.ZL : [I
    //   333: iconst_3
    //   334: anewarray java/lang/String
    //   337: dup
    //   338: iconst_0
    //   339: sipush #-9379
    //   342: sipush #21565
    //   345: invokestatic a : (II)Ljava/lang/String;
    //   348: aastore
    //   349: dup
    //   350: iconst_1
    //   351: sipush #-9384
    //   354: sipush #-22991
    //   357: invokestatic a : (II)Ljava/lang/String;
    //   360: aastore
    //   361: dup
    //   362: iconst_2
    //   363: sipush #-9378
    //   366: sipush #3416
    //   369: invokestatic a : (II)Ljava/lang/String;
    //   372: aastore
    //   373: putstatic burp/Zeyl.ZK : [Ljava/lang/String;
    //   376: invokestatic Zb : ()[I
    //   379: putstatic burp/Zeyl.ZX : [I
    //   382: return
  }
  
  private static Exception a(Exception paramException) {
    return paramException;
  }
  
  private static String a(int paramInt1, int paramInt2) {
    int i = (paramInt1 ^ 0xFFFFDB5B) & 0xFFFF;
    if (b[i] == null) {
      char[] arrayOfChar = a[i].toCharArray();
      switch (arrayOfChar[0] & 0xFF) {
        case 0:
        
        case 1:
        
        case 2:
        
        case 3:
        
        case 4:
        
        case 5:
        
        case 6:
        
        case 7:
        
        case 8:
        
        case 9:
        
        case 10:
        
        case 11:
        
        case 12:
        
        case 13:
        
        case 14:
        
        case 15:
        
        case 16:
        
        case 17:
        
        case 18:
        
        case 19:
        
        case 20:
        
        case 21:
        
        case 22:
        
        case 23:
        
        case 24:
        
        case 25:
        
        case 26:
        
        case 27:
        
        case 28:
        
        case 29:
        
        case 30:
        
        case 31:
        
        case 32:
        
        case 33:
        
        case 34:
        
        case 35:
        
        case 36:
        
        case 37:
        
        case 38:
        
        case 39:
        
        case 40:
        
        case 41:
        
        case 42:
        
        case 43:
        
        case 44:
        
        case 45:
        
        case 46:
        
        case 47:
        
        case 48:
        
        case 49:
        
        case 50:
        
        case 51:
        
        case 52:
        
        case 53:
        
        case 54:
        
        case 55:
        
        case 56:
        
        case 57:
        
        case 58:
        
        case 59:
        
        case 60:
        
        case 61:
        
        case 62:
        
        case 63:
        
        case 64:
        
        case 65:
        
        case 66:
        
        case 67:
        
        case 68:
        
        case 69:
        
        case 70:
        
        case 71:
        
        case 72:
        
        case 73:
        
        case 74:
        
        case 75:
        
        case 76:
        
        case 77:
        
        case 78:
        
        case 79:
        
        case 80:
        
        case 81:
        
        case 82:
        
        case 83:
        
        case 84:
        
        case 85:
        
        case 86:
        
        case 87:
        
        case 88:
        
        case 89:
        
        case 90:
        
        case 91:
        
        case 92:
        
        case 93:
        
        case 94:
        
        case 95:
        
        case 96:
        
        case 97:
        
        case 98:
        
        case 99:
        
        case 100:
        
        case 101:
        
        case 102:
        
        case 103:
        
        case 104:
        
        case 105:
        
        case 106:
        
        case 107:
        
        case 108:
        
        case 109:
        
        case 110:
        
        case 111:
        
        case 112:
        
        case 113:
        
        case 114:
        
        case 115:
        
        case 116:
        
        case 117:
        
        case 118:
        
        case 119:
        
        case 120:
        
        case 121:
        
        case 122:
        
        case 123:
        
        case 124:
        
        case 125:
        
        case 126:
        
        case 127:
        
        case 128:
        
        case 129:
        
        case 130:
        
        case 131:
        
        case 132:
        
        case 133:
        
        case 134:
        
        case 135:
        
        case 136:
        
        case 137:
        
        case 138:
        
        case 139:
        
        case 140:
        
        case 141:
        
        case 142:
        
        case 143:
        
        case 144:
        
        case 145:
        
        case 146:
        
        case 147:
        
        case 148:
        
        case 149:
        
        case 150:
        
        case 151:
        
        case 152:
        
        case 153:
        
        case 154:
        
        case 155:
        
        case 156:
        
        case 157:
        
        case 158:
        
        case 159:
        
        case 160:
        
        case 161:
        
        case 162:
        
        case 163:
        
        case 164:
        
        case 165:
        
        case 166:
        
        case 167:
        
        case 168:
        
        case 169:
        
        case 170:
        
        case 171:
        
        case 172:
        
        case 173:
        
        case 174:
        
        case 175:
        
        case 176:
        
        case 177:
        
        case 178:
        
        case 179:
        
        case 180:
        
        case 181:
        
        case 182:
        
        case 183:
        
        case 184:
        
        case 185:
        
        case 186:
        
        case 187:
        
        case 188:
        
        case 189:
        
        case 190:
        
        case 191:
        
        case 192:
        
        case 193:
        
        case 194:
        
        case 195:
        
        case 196:
        
        case 197:
        
        case 198:
        
        case 199:
        
        case 200:
        
        case 201:
        
        case 202:
        
        case 203:
        
        case 204:
        
        case 205:
        
        case 206:
        
        case 207:
        
        case 208:
        
        case 209:
        
        case 210:
        
        case 211:
        
        case 212:
        
        case 213:
        
        case 214:
        
        case 215:
        
        case 216:
        
        case 217:
        
        case 218:
        
        case 219:
        
        case 220:
        
        case 221:
        
        case 222:
        
        case 223:
        
        case 224:
        
        case 225:
        
        case 226:
        
        case 227:
        
        case 228:
        
        case 229:
        
        case 230:
        
        case 231:
        
        case 232:
        
        case 233:
        
        case 234:
        
        case 235:
        
        case 236:
        
        case 237:
        
        case 238:
        
        case 239:
        
        case 240:
        
        case 241:
        
        case 242:
        
        case 243:
        
        case 244:
        
        case 245:
        
        case 246:
        
        case 247:
        
        case 248:
        
        case 249:
        
        case 250:
        
        case 251:
        
        case 252:
        
        case 253:
        
        case 254:
        
        default:
          break;
      } 
      char c = 'ª';
      int j = (paramInt2 & 0xFF) - c;
      if (j < 0)
        j += 256; 
      int k = ((paramInt2 & 0xFFFF) >>> 8) - c;
      if (k < 0)
        k += 256; 
      for (byte b = 0; b < arrayOfChar.length; b++) {
        int m = b % 2;
        if (m == 0) {
          arrayOfChar[b] = (char)(arrayOfChar[b] ^ j);
          j = ((j >>> 3 | j << 5) ^ arrayOfChar[b]) & 0xFF;
        } else {
          arrayOfChar[b] = (char)(arrayOfChar[b] ^ k);
          k = ((k >>> 3 | k << 5) ^ arrayOfChar[b]) & 0xFF;
        } 
      } 
      b[i] = (new String(arrayOfChar)).intern();
    } 
    return b[i];
  }
}


/* Location:              C:\Program Files\BurpSuitePro\burpsuite_pro.jar!\burp\Zeyl.class
 * Java compiler version: 21 (65.0)
 * JD-Core Version:       1.1.3
 */