package burp;

import java.math.BigInteger;

class Zeyt extends ClassLoader {
  static Object ZR;
  
  static String ZS;
  
  private static final String[] a;
  
  private static final String[] b;
  
  static void Zo(Object paramObject) {
    Zb3p.ZX = a(1650, 15313);
    Zb3p.Zx = new BigInteger(a(1648, -5065));
    boolean bool = Zt2e.ZK();
    try {
      try {
        if (Zxyq.Zr.charAt(Math.abs(((BigInteger)Zb3p.Zx).intValue() % 32)) > Ztte.ZD.charAt(Math.abs(((BigInteger)Zs9u.Zd).intValue() % 32))) {
          try {
            Zmec.ZX(Class.forName(a(1652, 2351)));
            if (bool)
              Zr3x.ZA(Class.forName(a(1653, 9956))); 
          } catch (Throwable throwable) {
            throw a(null);
          } 
          return;
        } 
      } catch (Throwable throwable) {
        throw a(null);
      } 
      Zr3x.ZA(Class.forName(a(1653, 9956)));
    } catch (Throwable throwable) {}
  }
  
  static boolean Zy(Object[] paramArrayOfObject, Object paramObject) throws Throwable {
    // Byte code:
    //   0: invokestatic ZK : ()Z
    //   3: istore_2
    //   4: new java/lang/StringBuilder
    //   7: dup
    //   8: invokespecial <init> : ()V
    //   11: astore_3
    //   12: iconst_0
    //   13: istore #4
    //   15: iload #4
    //   17: bipush #32
    //   19: if_icmpge -> 1355
    //   22: iload #4
    //   24: tableswitch default -> 1348, 0 -> 168, 1 -> 205, 2 -> 242, 3 -> 279, 4 -> 316, 5 -> 353, 6 -> 390, 7 -> 427, 8 -> 464, 9 -> 501, 10 -> 538, 11 -> 575, 12 -> 612, 13 -> 649, 14 -> 686, 15 -> 723, 16 -> 760, 17 -> 797, 18 -> 834, 19 -> 871, 20 -> 908, 21 -> 945, 22 -> 982, 23 -> 1019, 24 -> 1056, 25 -> 1093, 26 -> 1130, 27 -> 1167, 28 -> 1204, 29 -> 1241, 30 -> 1278, 31 -> 1315
    //   168: aload_3
    //   169: getstatic burp/Zewo.ZM : Ljava/lang/String;
    //   172: getstatic burp/Ztid.ZL : Ljava/lang/Object;
    //   175: checkcast java/math/BigInteger
    //   178: invokevirtual intValue : ()I
    //   181: bipush #32
    //   183: irem
    //   184: invokestatic abs : (I)I
    //   187: invokevirtual charAt : (I)C
    //   190: invokevirtual append : (C)Ljava/lang/StringBuilder;
    //   193: pop
    //   194: iload_2
    //   195: ifeq -> 1348
    //   198: goto -> 205
    //   201: invokestatic a : (Ljava/lang/Throwable;)Ljava/lang/Throwable;
    //   204: athrow
    //   205: aload_3
    //   206: getstatic burp/Zmiy.ZT : Ljava/lang/String;
    //   209: getstatic burp/Zb9k.Zi : Ljava/lang/Object;
    //   212: checkcast java/math/BigInteger
    //   215: invokevirtual intValue : ()I
    //   218: bipush #32
    //   220: irem
    //   221: invokestatic abs : (I)I
    //   224: invokevirtual charAt : (I)C
    //   227: invokevirtual append : (C)Ljava/lang/StringBuilder;
    //   230: pop
    //   231: iload_2
    //   232: ifeq -> 1348
    //   235: goto -> 242
    //   238: invokestatic a : (Ljava/lang/Throwable;)Ljava/lang/Throwable;
    //   241: athrow
    //   242: aload_3
    //   243: getstatic burp/Zxrd.ZF : Ljava/lang/String;
    //   246: getstatic burp/Zttj.ZF : Ljava/lang/Object;
    //   249: checkcast java/math/BigInteger
    //   252: invokevirtual intValue : ()I
    //   255: bipush #32
    //   257: irem
    //   258: invokestatic abs : (I)I
    //   261: invokevirtual charAt : (I)C
    //   264: invokevirtual append : (C)Ljava/lang/StringBuilder;
    //   267: pop
    //   268: iload_2
    //   269: ifeq -> 1348
    //   272: goto -> 279
    //   275: invokestatic a : (Ljava/lang/Throwable;)Ljava/lang/Throwable;
    //   278: athrow
    //   279: aload_3
    //   280: getstatic burp/Zls_.Zn : Ljava/lang/String;
    //   283: getstatic burp/Zttj.ZF : Ljava/lang/Object;
    //   286: checkcast java/math/BigInteger
    //   289: invokevirtual intValue : ()I
    //   292: bipush #32
    //   294: irem
    //   295: invokestatic abs : (I)I
    //   298: invokevirtual charAt : (I)C
    //   301: invokevirtual append : (C)Ljava/lang/StringBuilder;
    //   304: pop
    //   305: iload_2
    //   306: ifeq -> 1348
    //   309: goto -> 316
    //   312: invokestatic a : (Ljava/lang/Throwable;)Ljava/lang/Throwable;
    //   315: athrow
    //   316: aload_3
    //   317: getstatic burp/Zrvb.ZU : Ljava/lang/String;
    //   320: getstatic burp/Zr3x.Zb : Ljava/lang/Object;
    //   323: checkcast java/math/BigInteger
    //   326: invokevirtual intValue : ()I
    //   329: bipush #32
    //   331: irem
    //   332: invokestatic abs : (I)I
    //   335: invokevirtual charAt : (I)C
    //   338: invokevirtual append : (C)Ljava/lang/StringBuilder;
    //   341: pop
    //   342: iload_2
    //   343: ifeq -> 1348
    //   346: goto -> 353
    //   349: invokestatic a : (Ljava/lang/Throwable;)Ljava/lang/Throwable;
    //   352: athrow
    //   353: aload_3
    //   354: getstatic burp/Zty3.ZW : Ljava/lang/String;
    //   357: getstatic burp/Zei_.Za : Ljava/lang/Object;
    //   360: checkcast java/math/BigInteger
    //   363: invokevirtual intValue : ()I
    //   366: bipush #32
    //   368: irem
    //   369: invokestatic abs : (I)I
    //   372: invokevirtual charAt : (I)C
    //   375: invokevirtual append : (C)Ljava/lang/StringBuilder;
    //   378: pop
    //   379: iload_2
    //   380: ifeq -> 1348
    //   383: goto -> 390
    //   386: invokestatic a : (Ljava/lang/Throwable;)Ljava/lang/Throwable;
    //   389: athrow
    //   390: aload_3
    //   391: getstatic burp/Zlno.ZM : Ljava/lang/String;
    //   394: getstatic burp/Zkul.Zb : Ljava/lang/Object;
    //   397: checkcast java/math/BigInteger
    //   400: invokevirtual intValue : ()I
    //   403: bipush #32
    //   405: irem
    //   406: invokestatic abs : (I)I
    //   409: invokevirtual charAt : (I)C
    //   412: invokevirtual append : (C)Ljava/lang/StringBuilder;
    //   415: pop
    //   416: iload_2
    //   417: ifeq -> 1348
    //   420: goto -> 427
    //   423: invokestatic a : (Ljava/lang/Throwable;)Ljava/lang/Throwable;
    //   426: athrow
    //   427: aload_3
    //   428: getstatic burp/Zz58.ZT : Ljava/lang/String;
    //   431: getstatic burp/Ztte.ZR : Ljava/lang/Object;
    //   434: checkcast java/math/BigInteger
    //   437: invokevirtual intValue : ()I
    //   440: bipush #32
    //   442: irem
    //   443: invokestatic abs : (I)I
    //   446: invokevirtual charAt : (I)C
    //   449: invokevirtual append : (C)Ljava/lang/StringBuilder;
    //   452: pop
    //   453: iload_2
    //   454: ifeq -> 1348
    //   457: goto -> 464
    //   460: invokestatic a : (Ljava/lang/Throwable;)Ljava/lang/Throwable;
    //   463: athrow
    //   464: aload_3
    //   465: getstatic burp/Zkku.Zq : Ljava/lang/String;
    //   468: getstatic burp/Zxd0.Za : Ljava/lang/Object;
    //   471: checkcast java/math/BigInteger
    //   474: invokevirtual intValue : ()I
    //   477: bipush #32
    //   479: irem
    //   480: invokestatic abs : (I)I
    //   483: invokevirtual charAt : (I)C
    //   486: invokevirtual append : (C)Ljava/lang/StringBuilder;
    //   489: pop
    //   490: iload_2
    //   491: ifeq -> 1348
    //   494: goto -> 501
    //   497: invokestatic a : (Ljava/lang/Throwable;)Ljava/lang/Throwable;
    //   500: athrow
    //   501: aload_3
    //   502: getstatic burp/Zkv2.Z_ : Ljava/lang/String;
    //   505: getstatic burp/Zbxp.ZW : Ljava/lang/Object;
    //   508: checkcast java/math/BigInteger
    //   511: invokevirtual intValue : ()I
    //   514: bipush #32
    //   516: irem
    //   517: invokestatic abs : (I)I
    //   520: invokevirtual charAt : (I)C
    //   523: invokevirtual append : (C)Ljava/lang/StringBuilder;
    //   526: pop
    //   527: iload_2
    //   528: ifeq -> 1348
    //   531: goto -> 538
    //   534: invokestatic a : (Ljava/lang/Throwable;)Ljava/lang/Throwable;
    //   537: athrow
    //   538: aload_3
    //   539: getstatic burp/Zkku.Zq : Ljava/lang/String;
    //   542: getstatic burp/Ztpa.Zv : Ljava/lang/Object;
    //   545: checkcast java/math/BigInteger
    //   548: invokevirtual intValue : ()I
    //   551: bipush #32
    //   553: irem
    //   554: invokestatic abs : (I)I
    //   557: invokevirtual charAt : (I)C
    //   560: invokevirtual append : (C)Ljava/lang/StringBuilder;
    //   563: pop
    //   564: iload_2
    //   565: ifeq -> 1348
    //   568: goto -> 575
    //   571: invokestatic a : (Ljava/lang/Throwable;)Ljava/lang/Throwable;
    //   574: athrow
    //   575: aload_3
    //   576: getstatic burp/Zejg.ZP : Ljava/lang/String;
    //   579: getstatic burp/Zlyf.Zm : Ljava/lang/Object;
    //   582: checkcast java/math/BigInteger
    //   585: invokevirtual intValue : ()I
    //   588: bipush #32
    //   590: irem
    //   591: invokestatic abs : (I)I
    //   594: invokevirtual charAt : (I)C
    //   597: invokevirtual append : (C)Ljava/lang/StringBuilder;
    //   600: pop
    //   601: iload_2
    //   602: ifeq -> 1348
    //   605: goto -> 612
    //   608: invokestatic a : (Ljava/lang/Throwable;)Ljava/lang/Throwable;
    //   611: athrow
    //   612: aload_3
    //   613: getstatic burp/Zko9.Zf : Ljava/lang/String;
    //   616: getstatic burp/Zewo.ZZ : Ljava/lang/Object;
    //   619: checkcast java/math/BigInteger
    //   622: invokevirtual intValue : ()I
    //   625: bipush #32
    //   627: irem
    //   628: invokestatic abs : (I)I
    //   631: invokevirtual charAt : (I)C
    //   634: invokevirtual append : (C)Ljava/lang/StringBuilder;
    //   637: pop
    //   638: iload_2
    //   639: ifeq -> 1348
    //   642: goto -> 649
    //   645: invokestatic a : (Ljava/lang/Throwable;)Ljava/lang/Throwable;
    //   648: athrow
    //   649: aload_3
    //   650: getstatic burp/Zeyt.ZS : Ljava/lang/String;
    //   653: getstatic burp/Zewo.ZZ : Ljava/lang/Object;
    //   656: checkcast java/math/BigInteger
    //   659: invokevirtual intValue : ()I
    //   662: bipush #32
    //   664: irem
    //   665: invokestatic abs : (I)I
    //   668: invokevirtual charAt : (I)C
    //   671: invokevirtual append : (C)Ljava/lang/StringBuilder;
    //   674: pop
    //   675: iload_2
    //   676: ifeq -> 1348
    //   679: goto -> 686
    //   682: invokestatic a : (Ljava/lang/Throwable;)Ljava/lang/Throwable;
    //   685: athrow
    //   686: aload_3
    //   687: getstatic burp/Zxd0.Zc : Ljava/lang/String;
    //   690: getstatic burp/Ztpa.Zv : Ljava/lang/Object;
    //   693: checkcast java/math/BigInteger
    //   696: invokevirtual intValue : ()I
    //   699: bipush #32
    //   701: irem
    //   702: invokestatic abs : (I)I
    //   705: invokevirtual charAt : (I)C
    //   708: invokevirtual append : (C)Ljava/lang/StringBuilder;
    //   711: pop
    //   712: iload_2
    //   713: ifeq -> 1348
    //   716: goto -> 723
    //   719: invokestatic a : (Ljava/lang/Throwable;)Ljava/lang/Throwable;
    //   722: athrow
    //   723: aload_3
    //   724: getstatic burp/Zttj.ZN : Ljava/lang/String;
    //   727: getstatic burp/Zxn7.ZU : Ljava/lang/Object;
    //   730: checkcast java/math/BigInteger
    //   733: invokevirtual intValue : ()I
    //   736: bipush #32
    //   738: irem
    //   739: invokestatic abs : (I)I
    //   742: invokevirtual charAt : (I)C
    //   745: invokevirtual append : (C)Ljava/lang/StringBuilder;
    //   748: pop
    //   749: iload_2
    //   750: ifeq -> 1348
    //   753: goto -> 760
    //   756: invokestatic a : (Ljava/lang/Throwable;)Ljava/lang/Throwable;
    //   759: athrow
    //   760: aload_3
    //   761: getstatic burp/Zs_.ZC : Ljava/lang/String;
    //   764: getstatic burp/Zxrd.ZL : Ljava/lang/Object;
    //   767: checkcast java/math/BigInteger
    //   770: invokevirtual intValue : ()I
    //   773: bipush #32
    //   775: irem
    //   776: invokestatic abs : (I)I
    //   779: invokevirtual charAt : (I)C
    //   782: invokevirtual append : (C)Ljava/lang/StringBuilder;
    //   785: pop
    //   786: iload_2
    //   787: ifeq -> 1348
    //   790: goto -> 797
    //   793: invokestatic a : (Ljava/lang/Throwable;)Ljava/lang/Throwable;
    //   796: athrow
    //   797: aload_3
    //   798: getstatic burp/Zl1u.ZO : Ljava/lang/String;
    //   801: getstatic burp/Zttj.ZF : Ljava/lang/Object;
    //   804: checkcast java/math/BigInteger
    //   807: invokevirtual intValue : ()I
    //   810: bipush #32
    //   812: irem
    //   813: invokestatic abs : (I)I
    //   816: invokevirtual charAt : (I)C
    //   819: invokevirtual append : (C)Ljava/lang/StringBuilder;
    //   822: pop
    //   823: iload_2
    //   824: ifeq -> 1348
    //   827: goto -> 834
    //   830: invokestatic a : (Ljava/lang/Throwable;)Ljava/lang/Throwable;
    //   833: athrow
    //   834: aload_3
    //   835: getstatic burp/Zk7w.ZB : Ljava/lang/String;
    //   838: getstatic burp/Zs_.Zs : Ljava/lang/Object;
    //   841: checkcast java/math/BigInteger
    //   844: invokevirtual intValue : ()I
    //   847: bipush #32
    //   849: irem
    //   850: invokestatic abs : (I)I
    //   853: invokevirtual charAt : (I)C
    //   856: invokevirtual append : (C)Ljava/lang/StringBuilder;
    //   859: pop
    //   860: iload_2
    //   861: ifeq -> 1348
    //   864: goto -> 871
    //   867: invokestatic a : (Ljava/lang/Throwable;)Ljava/lang/Throwable;
    //   870: athrow
    //   871: aload_3
    //   872: getstatic burp/Ztd6.Zu : Ljava/lang/String;
    //   875: getstatic burp/Zs_.Zs : Ljava/lang/Object;
    //   878: checkcast java/math/BigInteger
    //   881: invokevirtual intValue : ()I
    //   884: bipush #32
    //   886: irem
    //   887: invokestatic abs : (I)I
    //   890: invokevirtual charAt : (I)C
    //   893: invokevirtual append : (C)Ljava/lang/StringBuilder;
    //   896: pop
    //   897: iload_2
    //   898: ifeq -> 1348
    //   901: goto -> 908
    //   904: invokestatic a : (Ljava/lang/Throwable;)Ljava/lang/Throwable;
    //   907: athrow
    //   908: aload_3
    //   909: getstatic burp/Zzc7.ZN : Ljava/lang/String;
    //   912: getstatic burp/Ztes.ZX : Ljava/lang/Object;
    //   915: checkcast java/math/BigInteger
    //   918: invokevirtual intValue : ()I
    //   921: bipush #32
    //   923: irem
    //   924: invokestatic abs : (I)I
    //   927: invokevirtual charAt : (I)C
    //   930: invokevirtual append : (C)Ljava/lang/StringBuilder;
    //   933: pop
    //   934: iload_2
    //   935: ifeq -> 1348
    //   938: goto -> 945
    //   941: invokestatic a : (Ljava/lang/Throwable;)Ljava/lang/Throwable;
    //   944: athrow
    //   945: aload_3
    //   946: getstatic burp/Zttj.ZN : Ljava/lang/String;
    //   949: getstatic burp/Zsin.Za : Ljava/lang/Object;
    //   952: checkcast java/math/BigInteger
    //   955: invokevirtual intValue : ()I
    //   958: bipush #32
    //   960: irem
    //   961: invokestatic abs : (I)I
    //   964: invokevirtual charAt : (I)C
    //   967: invokevirtual append : (C)Ljava/lang/StringBuilder;
    //   970: pop
    //   971: iload_2
    //   972: ifeq -> 1348
    //   975: goto -> 982
    //   978: invokestatic a : (Ljava/lang/Throwable;)Ljava/lang/Throwable;
    //   981: athrow
    //   982: aload_3
    //   983: getstatic burp/Zly0.ZE : Ljava/lang/String;
    //   986: getstatic burp/Zsej.ZT : Ljava/lang/Object;
    //   989: checkcast java/math/BigInteger
    //   992: invokevirtual intValue : ()I
    //   995: bipush #32
    //   997: irem
    //   998: invokestatic abs : (I)I
    //   1001: invokevirtual charAt : (I)C
    //   1004: invokevirtual append : (C)Ljava/lang/StringBuilder;
    //   1007: pop
    //   1008: iload_2
    //   1009: ifeq -> 1348
    //   1012: goto -> 1019
    //   1015: invokestatic a : (Ljava/lang/Throwable;)Ljava/lang/Throwable;
    //   1018: athrow
    //   1019: aload_3
    //   1020: getstatic burp/Zko9.Zf : Ljava/lang/String;
    //   1023: getstatic burp/Zs9u.Zd : Ljava/lang/Object;
    //   1026: checkcast java/math/BigInteger
    //   1029: invokevirtual intValue : ()I
    //   1032: bipush #32
    //   1034: irem
    //   1035: invokestatic abs : (I)I
    //   1038: invokevirtual charAt : (I)C
    //   1041: invokevirtual append : (C)Ljava/lang/StringBuilder;
    //   1044: pop
    //   1045: iload_2
    //   1046: ifeq -> 1348
    //   1049: goto -> 1056
    //   1052: invokestatic a : (Ljava/lang/Throwable;)Ljava/lang/Throwable;
    //   1055: athrow
    //   1056: aload_3
    //   1057: getstatic burp/Zblv.ZF : Ljava/lang/String;
    //   1060: getstatic burp/Zejg.ZR : Ljava/lang/Object;
    //   1063: checkcast java/math/BigInteger
    //   1066: invokevirtual intValue : ()I
    //   1069: bipush #32
    //   1071: irem
    //   1072: invokestatic abs : (I)I
    //   1075: invokevirtual charAt : (I)C
    //   1078: invokevirtual append : (C)Ljava/lang/StringBuilder;
    //   1081: pop
    //   1082: iload_2
    //   1083: ifeq -> 1348
    //   1086: goto -> 1093
    //   1089: invokestatic a : (Ljava/lang/Throwable;)Ljava/lang/Throwable;
    //   1092: athrow
    //   1093: aload_3
    //   1094: getstatic burp/Zz0j.Zf : Ljava/lang/String;
    //   1097: getstatic burp/Ze3t.Zp : Ljava/lang/Object;
    //   1100: checkcast java/math/BigInteger
    //   1103: invokevirtual intValue : ()I
    //   1106: bipush #32
    //   1108: irem
    //   1109: invokestatic abs : (I)I
    //   1112: invokevirtual charAt : (I)C
    //   1115: invokevirtual append : (C)Ljava/lang/StringBuilder;
    //   1118: pop
    //   1119: iload_2
    //   1120: ifeq -> 1348
    //   1123: goto -> 1130
    //   1126: invokestatic a : (Ljava/lang/Throwable;)Ljava/lang/Throwable;
    //   1129: athrow
    //   1130: aload_3
    //   1131: getstatic burp/Zz9p.ZC : Ljava/lang/String;
    //   1134: getstatic burp/Zljx.ZZ : Ljava/lang/Object;
    //   1137: checkcast java/math/BigInteger
    //   1140: invokevirtual intValue : ()I
    //   1143: bipush #32
    //   1145: irem
    //   1146: invokestatic abs : (I)I
    //   1149: invokevirtual charAt : (I)C
    //   1152: invokevirtual append : (C)Ljava/lang/StringBuilder;
    //   1155: pop
    //   1156: iload_2
    //   1157: ifeq -> 1348
    //   1160: goto -> 1167
    //   1163: invokestatic a : (Ljava/lang/Throwable;)Ljava/lang/Throwable;
    //   1166: athrow
    //   1167: aload_3
    //   1168: getstatic burp/Zbxp.ZS : Ljava/lang/String;
    //   1171: getstatic burp/Zls_.ZR : Ljava/lang/Object;
    //   1174: checkcast java/math/BigInteger
    //   1177: invokevirtual intValue : ()I
    //   1180: bipush #32
    //   1182: irem
    //   1183: invokestatic abs : (I)I
    //   1186: invokevirtual charAt : (I)C
    //   1189: invokevirtual append : (C)Ljava/lang/StringBuilder;
    //   1192: pop
    //   1193: iload_2
    //   1194: ifeq -> 1348
    //   1197: goto -> 1204
    //   1200: invokestatic a : (Ljava/lang/Throwable;)Ljava/lang/Throwable;
    //   1203: athrow
    //   1204: aload_3
    //   1205: getstatic burp/Zs36.Zr : Ljava/lang/String;
    //   1208: getstatic burp/Zzy5.ZG : Ljava/lang/Object;
    //   1211: checkcast java/math/BigInteger
    //   1214: invokevirtual intValue : ()I
    //   1217: bipush #32
    //   1219: irem
    //   1220: invokestatic abs : (I)I
    //   1223: invokevirtual charAt : (I)C
    //   1226: invokevirtual append : (C)Ljava/lang/StringBuilder;
    //   1229: pop
    //   1230: iload_2
    //   1231: ifeq -> 1348
    //   1234: goto -> 1241
    //   1237: invokestatic a : (Ljava/lang/Throwable;)Ljava/lang/Throwable;
    //   1240: athrow
    //   1241: aload_3
    //   1242: getstatic burp/Zbxp.ZS : Ljava/lang/String;
    //   1245: getstatic burp/Zljx.ZZ : Ljava/lang/Object;
    //   1248: checkcast java/math/BigInteger
    //   1251: invokevirtual intValue : ()I
    //   1254: bipush #32
    //   1256: irem
    //   1257: invokestatic abs : (I)I
    //   1260: invokevirtual charAt : (I)C
    //   1263: invokevirtual append : (C)Ljava/lang/StringBuilder;
    //   1266: pop
    //   1267: iload_2
    //   1268: ifeq -> 1348
    //   1271: goto -> 1278
    //   1274: invokestatic a : (Ljava/lang/Throwable;)Ljava/lang/Throwable;
    //   1277: athrow
    //   1278: aload_3
    //   1279: getstatic burp/Zxn7.ZG : Ljava/lang/String;
    //   1282: getstatic burp/Zmjr.ZU : Ljava/lang/Object;
    //   1285: checkcast java/math/BigInteger
    //   1288: invokevirtual intValue : ()I
    //   1291: bipush #32
    //   1293: irem
    //   1294: invokestatic abs : (I)I
    //   1297: invokevirtual charAt : (I)C
    //   1300: invokevirtual append : (C)Ljava/lang/StringBuilder;
    //   1303: pop
    //   1304: iload_2
    //   1305: ifeq -> 1348
    //   1308: goto -> 1315
    //   1311: invokestatic a : (Ljava/lang/Throwable;)Ljava/lang/Throwable;
    //   1314: athrow
    //   1315: aload_3
    //   1316: getstatic burp/Zl_9.ZP : Ljava/lang/String;
    //   1319: getstatic burp/Zzy5.ZG : Ljava/lang/Object;
    //   1322: checkcast java/math/BigInteger
    //   1325: invokevirtual intValue : ()I
    //   1328: bipush #32
    //   1330: irem
    //   1331: invokestatic abs : (I)I
    //   1334: invokevirtual charAt : (I)C
    //   1337: invokevirtual append : (C)Ljava/lang/StringBuilder;
    //   1340: pop
    //   1341: goto -> 1348
    //   1344: invokestatic a : (Ljava/lang/Throwable;)Ljava/lang/Throwable;
    //   1347: athrow
    //   1348: iinc #4, 1
    //   1351: iload_2
    //   1352: ifeq -> 15
    //   1355: aload_3
    //   1356: invokevirtual toString : ()Ljava/lang/String;
    //   1359: putstatic burp/Zkvr.Zm : Ljava/lang/String;
    //   1362: getstatic burp/Zmhx.ZQ : Ljava/lang/Object;
    //   1365: checkcast java/math/BigInteger
    //   1368: getstatic burp/Zm06.ZU : Ljava/lang/Object;
    //   1371: checkcast java/math/BigInteger
    //   1374: invokevirtual subtract : (Ljava/math/BigInteger;)Ljava/math/BigInteger;
    //   1377: putstatic burp/Zzvr.Z_ : Ljava/lang/Object;
    //   1380: getstatic burp/Zzc7.ZG : Ljava/lang/Object;
    //   1383: checkcast java/math/BigInteger
    //   1386: invokevirtual toByteArray : ()[B
    //   1389: astore #4
    //   1391: aload #4
    //   1393: arraylength
    //   1394: iconst_2
    //   1395: iadd
    //   1396: newarray byte
    //   1398: astore #6
    //   1400: iconst_0
    //   1401: istore #7
    //   1403: iload #7
    //   1405: aload #4
    //   1407: arraylength
    //   1408: if_icmpge -> 1428
    //   1411: aload #6
    //   1413: iload #7
    //   1415: aload #4
    //   1417: iload #7
    //   1419: baload
    //   1420: bastore
    //   1421: iinc #7, 1
    //   1424: iload_2
    //   1425: ifeq -> 1403
    //   1428: aload #6
    //   1430: arraylength
    //   1431: iconst_3
    //   1432: idiv
    //   1433: iconst_4
    //   1434: imul
    //   1435: newarray byte
    //   1437: astore #5
    //   1439: iconst_0
    //   1440: istore #7
    //   1442: iconst_0
    //   1443: istore #8
    //   1445: iload #7
    //   1447: aload #4
    //   1449: arraylength
    //   1450: if_icmpge -> 1561
    //   1453: aload #5
    //   1455: iload #8
    //   1457: aload #6
    //   1459: iload #7
    //   1461: baload
    //   1462: iconst_2
    //   1463: iushr
    //   1464: bipush #63
    //   1466: iand
    //   1467: i2b
    //   1468: bastore
    //   1469: aload #5
    //   1471: iload #8
    //   1473: iconst_1
    //   1474: iadd
    //   1475: aload #6
    //   1477: iload #7
    //   1479: iconst_1
    //   1480: iadd
    //   1481: baload
    //   1482: iconst_4
    //   1483: iushr
    //   1484: bipush #15
    //   1486: iand
    //   1487: aload #6
    //   1489: iload #7
    //   1491: baload
    //   1492: iconst_4
    //   1493: ishl
    //   1494: bipush #63
    //   1496: iand
    //   1497: ior
    //   1498: i2b
    //   1499: bastore
    //   1500: aload #5
    //   1502: iload #8
    //   1504: iconst_2
    //   1505: iadd
    //   1506: aload #6
    //   1508: iload #7
    //   1510: iconst_2
    //   1511: iadd
    //   1512: baload
    //   1513: bipush #6
    //   1515: iushr
    //   1516: iconst_3
    //   1517: iand
    //   1518: aload #6
    //   1520: iload #7
    //   1522: iconst_1
    //   1523: iadd
    //   1524: baload
    //   1525: iconst_2
    //   1526: ishl
    //   1527: bipush #63
    //   1529: iand
    //   1530: ior
    //   1531: i2b
    //   1532: bastore
    //   1533: aload #5
    //   1535: iload #8
    //   1537: iconst_3
    //   1538: iadd
    //   1539: aload #6
    //   1541: iload #7
    //   1543: iconst_2
    //   1544: iadd
    //   1545: baload
    //   1546: bipush #63
    //   1548: iand
    //   1549: i2b
    //   1550: bastore
    //   1551: iinc #7, 3
    //   1554: iinc #8, 4
    //   1557: iload_2
    //   1558: ifeq -> 1445
    //   1561: iconst_0
    //   1562: istore #7
    //   1564: iload #7
    //   1566: aload #5
    //   1568: arraylength
    //   1569: if_icmpge -> 1753
    //   1572: aload #5
    //   1574: iload #7
    //   1576: baload
    //   1577: bipush #26
    //   1579: if_icmpge -> 1607
    //   1582: aload #5
    //   1584: iload #7
    //   1586: aload #5
    //   1588: iload #7
    //   1590: baload
    //   1591: bipush #65
    //   1593: iadd
    //   1594: i2b
    //   1595: bastore
    //   1596: iload_2
    //   1597: ifeq -> 1746
    //   1600: goto -> 1607
    //   1603: invokestatic a : (Ljava/lang/Throwable;)Ljava/lang/Throwable;
    //   1606: athrow
    //   1607: aload #5
    //   1609: iload #7
    //   1611: baload
    //   1612: bipush #52
    //   1614: if_icmpge -> 1652
    //   1617: goto -> 1624
    //   1620: invokestatic a : (Ljava/lang/Throwable;)Ljava/lang/Throwable;
    //   1623: athrow
    //   1624: aload #5
    //   1626: iload #7
    //   1628: aload #5
    //   1630: iload #7
    //   1632: baload
    //   1633: bipush #97
    //   1635: iadd
    //   1636: bipush #26
    //   1638: isub
    //   1639: i2b
    //   1640: bastore
    //   1641: iload_2
    //   1642: ifeq -> 1746
    //   1645: goto -> 1652
    //   1648: invokestatic a : (Ljava/lang/Throwable;)Ljava/lang/Throwable;
    //   1651: athrow
    //   1652: aload #5
    //   1654: iload #7
    //   1656: baload
    //   1657: bipush #62
    //   1659: if_icmpge -> 1697
    //   1662: goto -> 1669
    //   1665: invokestatic a : (Ljava/lang/Throwable;)Ljava/lang/Throwable;
    //   1668: athrow
    //   1669: aload #5
    //   1671: iload #7
    //   1673: aload #5
    //   1675: iload #7
    //   1677: baload
    //   1678: bipush #48
    //   1680: iadd
    //   1681: bipush #52
    //   1683: isub
    //   1684: i2b
    //   1685: bastore
    //   1686: iload_2
    //   1687: ifeq -> 1746
    //   1690: goto -> 1697
    //   1693: invokestatic a : (Ljava/lang/Throwable;)Ljava/lang/Throwable;
    //   1696: athrow
    //   1697: aload #5
    //   1699: iload #7
    //   1701: baload
    //   1702: bipush #63
    //   1704: if_icmpge -> 1732
    //   1707: goto -> 1714
    //   1710: invokestatic a : (Ljava/lang/Throwable;)Ljava/lang/Throwable;
    //   1713: athrow
    //   1714: aload #5
    //   1716: iload #7
    //   1718: bipush #43
    //   1720: bastore
    //   1721: iload_2
    //   1722: ifeq -> 1746
    //   1725: goto -> 1732
    //   1728: invokestatic a : (Ljava/lang/Throwable;)Ljava/lang/Throwable;
    //   1731: athrow
    //   1732: aload #5
    //   1734: iload #7
    //   1736: bipush #47
    //   1738: bastore
    //   1739: goto -> 1746
    //   1742: invokestatic a : (Ljava/lang/Throwable;)Ljava/lang/Throwable;
    //   1745: athrow
    //   1746: iinc #7, 1
    //   1749: iload_2
    //   1750: ifeq -> 1564
    //   1753: aload #5
    //   1755: arraylength
    //   1756: iconst_1
    //   1757: isub
    //   1758: istore #7
    //   1760: iload #7
    //   1762: aload #4
    //   1764: arraylength
    //   1765: iconst_4
    //   1766: imul
    //   1767: iconst_3
    //   1768: idiv
    //   1769: if_icmple -> 1786
    //   1772: aload #5
    //   1774: iload #7
    //   1776: bipush #61
    //   1778: bastore
    //   1779: iinc #7, -1
    //   1782: iload_2
    //   1783: ifeq -> 1760
    //   1786: new java/math/BigInteger
    //   1789: dup
    //   1790: aload #5
    //   1792: invokespecial <init> : ([B)V
    //   1795: invokevirtual abs : ()Ljava/math/BigInteger;
    //   1798: putstatic burp/Zb9k.Zi : Ljava/lang/Object;
    //   1801: sipush #1649
    //   1804: sipush #11579
    //   1807: invokestatic a : (II)Ljava/lang/String;
    //   1810: iconst_1
    //   1811: ldc burp/Zx_x
    //   1813: invokevirtual getClassLoader : ()Ljava/lang/ClassLoader;
    //   1816: invokestatic forName : (Ljava/lang/String;ZLjava/lang/ClassLoader;)Ljava/lang/Class;
    //   1819: invokevirtual getDeclaredFields : ()[Ljava/lang/reflect/Field;
    //   1822: astore #4
    //   1824: aload #4
    //   1826: arraylength
    //   1827: istore #5
    //   1829: iconst_0
    //   1830: istore #6
    //   1832: iload #6
    //   1834: iload #5
    //   1836: if_icmpge -> 1974
    //   1839: aload #4
    //   1841: iload #6
    //   1843: aaload
    //   1844: astore #7
    //   1846: aload #7
    //   1848: invokevirtual getModifiers : ()I
    //   1851: invokestatic isStatic : (I)Z
    //   1854: ifne -> 1864
    //   1857: goto -> 1967
    //   1860: invokestatic a : (Ljava/lang/Throwable;)Ljava/lang/Throwable;
    //   1863: athrow
    //   1864: aload #7
    //   1866: invokevirtual getType : ()Ljava/lang/Class;
    //   1869: astore #8
    //   1871: aload #8
    //   1873: ifnull -> 1954
    //   1876: aload #8
    //   1878: invokevirtual isPrimitive : ()Z
    //   1881: ifne -> 1954
    //   1884: goto -> 1891
    //   1887: invokestatic a : (Ljava/lang/Throwable;)Ljava/lang/Throwable;
    //   1890: athrow
    //   1891: aload #8
    //   1893: invokevirtual getPackage : ()Ljava/lang/Package;
    //   1896: ifnull -> 1954
    //   1899: goto -> 1906
    //   1902: invokestatic a : (Ljava/lang/Throwable;)Ljava/lang/Throwable;
    //   1905: athrow
    //   1906: aload #8
    //   1908: invokevirtual getPackage : ()Ljava/lang/Package;
    //   1911: invokevirtual getName : ()Ljava/lang/String;
    //   1914: ifnull -> 1954
    //   1917: goto -> 1924
    //   1920: invokestatic a : (Ljava/lang/Throwable;)Ljava/lang/Throwable;
    //   1923: athrow
    //   1924: aload #8
    //   1926: invokevirtual getPackage : ()Ljava/lang/Package;
    //   1929: invokevirtual getName : ()Ljava/lang/String;
    //   1932: sipush #1655
    //   1935: sipush #-17400
    //   1938: invokestatic a : (II)Ljava/lang/String;
    //   1941: invokevirtual startsWith : (Ljava/lang/String;)Z
    //   1944: ifne -> 1954
    //   1947: goto -> 1954
    //   1950: invokestatic a : (Ljava/lang/Throwable;)Ljava/lang/Throwable;
    //   1953: athrow
    //   1954: aload #7
    //   1956: iconst_1
    //   1957: invokevirtual setAccessible : (Z)V
    //   1960: aload #7
    //   1962: aconst_null
    //   1963: invokevirtual get : (Ljava/lang/Object;)Ljava/lang/Object;
    //   1966: pop
    //   1967: iinc #6, 1
    //   1970: iload_2
    //   1971: ifeq -> 1832
    //   1974: sipush #1651
    //   1977: sipush #6104
    //   1980: invokestatic a : (II)Ljava/lang/String;
    //   1983: invokestatic forName : (Ljava/lang/String;)Ljava/lang/Class;
    //   1986: invokevirtual getDeclaredMethods : ()[Ljava/lang/reflect/Method;
    //   1989: astore #4
    //   1991: aload #4
    //   1993: arraylength
    //   1994: istore #5
    //   1996: iconst_0
    //   1997: istore #6
    //   1999: iload #6
    //   2001: iload #5
    //   2003: if_icmpge -> 2136
    //   2006: aload #4
    //   2008: iload #6
    //   2010: aaload
    //   2011: astore #7
    //   2013: aload #7
    //   2015: invokevirtual getParameterTypes : ()[Ljava/lang/Class;
    //   2018: pop
    //   2019: aload #7
    //   2021: invokevirtual getModifiers : ()I
    //   2024: invokestatic isStatic : (I)Z
    //   2027: ifeq -> 2122
    //   2030: aload #7
    //   2032: invokevirtual getParameterTypes : ()[Ljava/lang/Class;
    //   2035: arraylength
    //   2036: iconst_2
    //   2037: if_icmpne -> 2122
    //   2040: goto -> 2047
    //   2043: invokestatic a : (Ljava/lang/Throwable;)Ljava/lang/Throwable;
    //   2046: athrow
    //   2047: aload #7
    //   2049: invokevirtual getReturnType : ()Ljava/lang/Class;
    //   2052: getstatic java/lang/Void.TYPE : Ljava/lang/Class;
    //   2055: invokevirtual equals : (Ljava/lang/Object;)Z
    //   2058: ifeq -> 2122
    //   2061: goto -> 2068
    //   2064: invokestatic a : (Ljava/lang/Throwable;)Ljava/lang/Throwable;
    //   2067: athrow
    //   2068: aload #7
    //   2070: iconst_1
    //   2071: invokevirtual setAccessible : (Z)V
    //   2074: aload #7
    //   2076: aconst_null
    //   2077: iconst_2
    //   2078: anewarray java/lang/Object
    //   2081: dup
    //   2082: iconst_0
    //   2083: aload_0
    //   2084: aastore
    //   2085: dup
    //   2086: iconst_1
    //   2087: aload_1
    //   2088: ifnonnull -> 2106
    //   2091: goto -> 2098
    //   2094: invokestatic a : (Ljava/lang/Throwable;)Ljava/lang/Throwable;
    //   2097: athrow
    //   2098: aload_1
    //   2099: goto -> 2113
    //   2102: invokestatic a : (Ljava/lang/Throwable;)Ljava/lang/Throwable;
    //   2105: athrow
    //   2106: aload_1
    //   2107: checkcast [B
    //   2110: invokevirtual clone : ()Ljava/lang/Object;
    //   2113: aastore
    //   2114: invokevirtual invoke : (Ljava/lang/Object;[Ljava/lang/Object;)Ljava/lang/Object;
    //   2117: pop
    //   2118: iload_2
    //   2119: ifeq -> 2136
    //   2122: iinc #6, 1
    //   2125: iload_2
    //   2126: ifeq -> 1999
    //   2129: goto -> 2136
    //   2132: invokestatic a : (Ljava/lang/Throwable;)Ljava/lang/Throwable;
    //   2135: athrow
    //   2136: getstatic burp/Zgkl.ZR : Ljava/lang/String;
    //   2139: getstatic burp/Ztes.ZX : Ljava/lang/Object;
    //   2142: checkcast java/math/BigInteger
    //   2145: invokevirtual intValue : ()I
    //   2148: bipush #32
    //   2150: irem
    //   2151: invokestatic abs : (I)I
    //   2154: invokevirtual charAt : (I)C
    //   2157: getstatic burp/Ze3t.ZG : Ljava/lang/String;
    //   2160: getstatic burp/Zlyf.Zm : Ljava/lang/Object;
    //   2163: checkcast java/math/BigInteger
    //   2166: invokevirtual intValue : ()I
    //   2169: bipush #32
    //   2171: irem
    //   2172: invokestatic abs : (I)I
    //   2175: invokevirtual charAt : (I)C
    //   2178: if_icmpgt -> 2285
    //   2181: getstatic burp/Zsin.ZC : Ljava/lang/String;
    //   2184: getstatic burp/Zejg.ZR : Ljava/lang/Object;
    //   2187: checkcast java/math/BigInteger
    //   2190: invokevirtual intValue : ()I
    //   2193: bipush #32
    //   2195: irem
    //   2196: invokestatic abs : (I)I
    //   2199: invokevirtual charAt : (I)C
    //   2202: getstatic burp/Zlc5.Z_ : Ljava/lang/String;
    //   2205: getstatic burp/Zs33.ZT : Ljava/lang/Object;
    //   2208: checkcast java/math/BigInteger
    //   2211: invokevirtual intValue : ()I
    //   2214: bipush #32
    //   2216: irem
    //   2217: invokestatic abs : (I)I
    //   2220: invokevirtual charAt : (I)C
    //   2223: if_icmpgt -> 2285
    //   2226: goto -> 2233
    //   2229: invokestatic a : (Ljava/lang/Throwable;)Ljava/lang/Throwable;
    //   2232: athrow
    //   2233: getstatic burp/Zz0j.Zf : Ljava/lang/String;
    //   2236: getstatic burp/Zrvb.ZD : Ljava/lang/Object;
    //   2239: checkcast java/math/BigInteger
    //   2242: invokevirtual intValue : ()I
    //   2245: bipush #32
    //   2247: irem
    //   2248: invokestatic abs : (I)I
    //   2251: invokevirtual charAt : (I)C
    //   2254: getstatic burp/Zs59.Zc : Ljava/lang/String;
    //   2257: getstatic burp/Zl1u.Zq : Ljava/lang/Object;
    //   2260: checkcast java/math/BigInteger
    //   2263: invokevirtual intValue : ()I
    //   2266: bipush #32
    //   2268: irem
    //   2269: invokestatic abs : (I)I
    //   2272: invokevirtual charAt : (I)C
    //   2275: if_icmpgt -> 2293
    //   2278: goto -> 2285
    //   2281: invokestatic a : (Ljava/lang/Throwable;)Ljava/lang/Throwable;
    //   2284: athrow
    //   2285: iconst_1
    //   2286: goto -> 2294
    //   2289: invokestatic a : (Ljava/lang/Throwable;)Ljava/lang/Throwable;
    //   2292: athrow
    //   2293: iconst_0
    //   2294: ireturn
    //   2295: astore_3
    //   2296: new java/lang/Exception
    //   2299: dup
    //   2300: aload_3
    //   2301: invokevirtual getMessage : ()Ljava/lang/String;
    //   2304: invokespecial <init> : (Ljava/lang/String;)V
    //   2307: athrow
    // Exception table:
    //   from	to	target	type
    //   4	2294	2295	java/lang/Throwable
    //   22	198	201	java/lang/Throwable
    //   168	235	238	java/lang/Throwable
    //   205	272	275	java/lang/Throwable
    //   242	309	312	java/lang/Throwable
    //   279	346	349	java/lang/Throwable
    //   316	383	386	java/lang/Throwable
    //   353	420	423	java/lang/Throwable
    //   390	457	460	java/lang/Throwable
    //   427	494	497	java/lang/Throwable
    //   464	531	534	java/lang/Throwable
    //   501	568	571	java/lang/Throwable
    //   538	605	608	java/lang/Throwable
    //   575	642	645	java/lang/Throwable
    //   612	679	682	java/lang/Throwable
    //   649	716	719	java/lang/Throwable
    //   686	753	756	java/lang/Throwable
    //   723	790	793	java/lang/Throwable
    //   760	827	830	java/lang/Throwable
    //   797	864	867	java/lang/Throwable
    //   834	901	904	java/lang/Throwable
    //   871	938	941	java/lang/Throwable
    //   908	975	978	java/lang/Throwable
    //   945	1012	1015	java/lang/Throwable
    //   982	1049	1052	java/lang/Throwable
    //   1019	1086	1089	java/lang/Throwable
    //   1056	1123	1126	java/lang/Throwable
    //   1093	1160	1163	java/lang/Throwable
    //   1130	1197	1200	java/lang/Throwable
    //   1167	1234	1237	java/lang/Throwable
    //   1204	1271	1274	java/lang/Throwable
    //   1241	1308	1311	java/lang/Throwable
    //   1278	1341	1344	java/lang/Throwable
    //   1572	1600	1603	java/lang/Throwable
    //   1582	1617	1620	java/lang/Throwable
    //   1607	1645	1648	java/lang/Throwable
    //   1624	1662	1665	java/lang/Throwable
    //   1652	1690	1693	java/lang/Throwable
    //   1669	1707	1710	java/lang/Throwable
    //   1697	1725	1728	java/lang/Throwable
    //   1714	1739	1742	java/lang/Throwable
    //   1846	1860	1860	java/lang/Throwable
    //   1871	1884	1887	java/lang/Throwable
    //   1876	1899	1902	java/lang/Throwable
    //   1891	1917	1920	java/lang/Throwable
    //   1906	1947	1950	java/lang/Throwable
    //   2013	2040	2043	java/lang/Throwable
    //   2030	2061	2064	java/lang/Throwable
    //   2047	2091	2094	java/lang/Throwable
    //   2068	2102	2102	java/lang/Throwable
    //   2113	2129	2132	java/lang/Throwable
    //   2136	2226	2229	java/lang/Throwable
    //   2181	2278	2281	java/lang/Throwable
    //   2233	2289	2289	java/lang/Throwable
  }
  
  static void Za(Object[] paramArrayOfObject, Object paramObject) throws Throwable {}
  
  static {
    // Byte code:
    //   0: bipush #8
    //   2: anewarray java/lang/String
    //   5: astore #5
    //   7: iconst_0
    //   8: istore_3
    //   9: ldc 'Ã²aÂˆÂžÂ‚uÃ¶T{ ÂºBÃ´ÂŠÃ…Â´Â‹Ã’ÃžMÂ \\nXjÂ·9LÃ¿(Ãœ%cXÂ© Â¢Â“Ã§\\tÂ’<Â„5 Ã†Ãº}MÃ€?ÃžQkÂ\\t$ÂˆcÂžÃ­Â©5~C8Ã’Ã®nÂ#Â³Â•ÂƒÂ›Ã©Ã´Ã¼Â¹Â¦ÃˆÂ Â“Â®MÃ»ÂŸzÃ€H`ÂšKÃšÂ‰%Ã®Ã¾Ã¾Â»Ã‘KÂœÃÃ½5ÃˆO@Â \\r3RÂ¾Âœe UITÃ¸!Ã‘Â‡Ã½Â”Â·ÃœD8Â«9Ã°Â¹Â€Â¹ei."4ÂŒ2'
    //   11: dup
    //   12: astore_2
    //   13: invokevirtual length : ()I
    //   16: istore #4
    //   18: bipush #9
    //   20: istore_1
    //   21: iconst_m1
    //   22: istore_0
    //   23: bipush #19
    //   25: iinc #0, 1
    //   28: aload_2
    //   29: iload_0
    //   30: dup
    //   31: iload_1
    //   32: iadd
    //   33: invokevirtual substring : (II)Ljava/lang/String;
    //   36: iconst_m1
    //   37: goto -> 143
    //   40: aload #5
    //   42: swap
    //   43: iload_3
    //   44: iinc #3, 1
    //   47: swap
    //   48: aastore
    //   49: iload_0
    //   50: iload_1
    //   51: iadd
    //   52: dup
    //   53: istore_0
    //   54: iload #4
    //   56: if_icmpge -> 68
    //   59: aload_2
    //   60: iload_0
    //   61: invokevirtual charAt : (I)C
    //   64: istore_1
    //   65: goto -> 23
    //   68: ldc 'Ã®Ã¼9dÂ•>\y\\tÂˆÃ¾Ã“yÃ½Â_'
    //   70: dup
    //   71: astore_2
    //   72: invokevirtual length : ()I
    //   75: istore #4
    //   77: bipush #9
    //   79: istore_1
    //   80: iconst_m1
    //   81: istore_0
    //   82: bipush #104
    //   84: iinc #0, 1
    //   87: aload_2
    //   88: iload_0
    //   89: dup
    //   90: iload_1
    //   91: iadd
    //   92: invokevirtual substring : (II)Ljava/lang/String;
    //   95: iconst_0
    //   96: goto -> 143
    //   99: aload #5
    //   101: swap
    //   102: iload_3
    //   103: iinc #3, 1
    //   106: swap
    //   107: aastore
    //   108: iload_0
    //   109: iload_1
    //   110: iadd
    //   111: dup
    //   112: istore_0
    //   113: iload #4
    //   115: if_icmpge -> 127
    //   118: aload_2
    //   119: iload_0
    //   120: invokevirtual charAt : (I)C
    //   123: istore_1
    //   124: goto -> 82
    //   127: aload #5
    //   129: putstatic burp/Zeyt.a : [Ljava/lang/String;
    //   132: bipush #8
    //   134: anewarray java/lang/String
    //   137: putstatic burp/Zeyt.b : [Ljava/lang/String;
    //   140: goto -> 300
    //   143: dup_x2
    //   144: pop
    //   145: invokevirtual toCharArray : ()[C
    //   148: dup_x1
    //   149: arraylength
    //   150: dup_x2
    //   151: pop
    //   152: iconst_0
    //   153: istore #6
    //   155: dup2_x1
    //   156: pop2
    //   157: dup_x2
    //   158: iconst_1
    //   159: if_icmpgt -> 260
    //   162: dup2
    //   163: swap
    //   164: iload #6
    //   166: dup2_x1
    //   167: caload
    //   168: swap
    //   169: iload #6
    //   171: bipush #7
    //   173: irem
    //   174: tableswitch default -> 242, 0 -> 212, 1 -> 217, 2 -> 222, 3 -> 227, 4 -> 232, 5 -> 237
    //   212: bipush #101
    //   214: goto -> 244
    //   217: bipush #34
    //   219: goto -> 244
    //   222: bipush #87
    //   224: goto -> 244
    //   227: bipush #44
    //   229: goto -> 244
    //   232: bipush #26
    //   234: goto -> 244
    //   237: bipush #118
    //   239: goto -> 244
    //   242: bipush #19
    //   244: ixor
    //   245: ixor
    //   246: i2c
    //   247: castore
    //   248: iinc #6, 1
    //   251: dup
    //   252: ifne -> 260
    //   255: dup2
    //   256: dup_x1
    //   257: goto -> 166
    //   260: dup2_x1
    //   261: pop2
    //   262: dup_x2
    //   263: iload #6
    //   265: if_icmpgt -> 162
    //   268: pop
    //   269: new java/lang/String
    //   272: dup_x1
    //   273: swap
    //   274: invokespecial <init> : ([C)V
    //   277: invokevirtual intern : ()Ljava/lang/String;
    //   280: swap
    //   281: pop
    //   282: swap
    //   283: tableswitch default -> 40, 0 -> 99
    //   300: new java/math/BigInteger
    //   303: dup
    //   304: iconst_1
    //   305: bipush #32
    //   307: newarray byte
    //   309: dup
    //   310: iconst_0
    //   311: bipush #21
    //   313: bastore
    //   314: dup
    //   315: iconst_1
    //   316: bipush #104
    //   318: bastore
    //   319: dup
    //   320: iconst_2
    //   321: bipush #24
    //   323: bastore
    //   324: dup
    //   325: iconst_3
    //   326: bipush #-52
    //   328: bastore
    //   329: dup
    //   330: iconst_4
    //   331: bipush #-56
    //   333: bastore
    //   334: dup
    //   335: iconst_5
    //   336: bipush #-121
    //   338: bastore
    //   339: dup
    //   340: bipush #6
    //   342: bipush #43
    //   344: bastore
    //   345: dup
    //   346: bipush #7
    //   348: bipush #-77
    //   350: bastore
    //   351: dup
    //   352: bipush #8
    //   354: bipush #-37
    //   356: bastore
    //   357: dup
    //   358: bipush #9
    //   360: bipush #-16
    //   362: bastore
    //   363: dup
    //   364: bipush #10
    //   366: bipush #97
    //   368: bastore
    //   369: dup
    //   370: bipush #11
    //   372: bipush #-122
    //   374: bastore
    //   375: dup
    //   376: bipush #12
    //   378: bipush #62
    //   380: bastore
    //   381: dup
    //   382: bipush #13
    //   384: bipush #24
    //   386: bastore
    //   387: dup
    //   388: bipush #14
    //   390: bipush #-30
    //   392: bastore
    //   393: dup
    //   394: bipush #15
    //   396: bipush #29
    //   398: bastore
    //   399: dup
    //   400: bipush #16
    //   402: bipush #18
    //   404: bastore
    //   405: dup
    //   406: bipush #17
    //   408: bipush #99
    //   410: bastore
    //   411: dup
    //   412: bipush #18
    //   414: bipush #-50
    //   416: bastore
    //   417: dup
    //   418: bipush #19
    //   420: bipush #66
    //   422: bastore
    //   423: dup
    //   424: bipush #20
    //   426: bipush #76
    //   428: bastore
    //   429: dup
    //   430: bipush #21
    //   432: bipush #-32
    //   434: bastore
    //   435: dup
    //   436: bipush #22
    //   438: bipush #67
    //   440: bastore
    //   441: dup
    //   442: bipush #23
    //   444: bipush #43
    //   446: bastore
    //   447: dup
    //   448: bipush #24
    //   450: bipush #10
    //   452: bastore
    //   453: dup
    //   454: bipush #25
    //   456: bipush #-69
    //   458: bastore
    //   459: dup
    //   460: bipush #26
    //   462: bipush #-83
    //   464: bastore
    //   465: dup
    //   466: bipush #27
    //   468: bipush #32
    //   470: bastore
    //   471: dup
    //   472: bipush #28
    //   474: bipush #51
    //   476: bastore
    //   477: dup
    //   478: bipush #29
    //   480: bipush #-7
    //   482: bastore
    //   483: dup
    //   484: bipush #30
    //   486: bipush #85
    //   488: bastore
    //   489: dup
    //   490: bipush #31
    //   492: bipush #-111
    //   494: bastore
    //   495: invokespecial <init> : (I[B)V
    //   498: putstatic burp/Zeyt.ZR : Ljava/lang/Object;
    //   501: sipush #1654
    //   504: sipush #-29263
    //   507: invokestatic a : (II)Ljava/lang/String;
    //   510: putstatic burp/Zeyt.ZS : Ljava/lang/String;
    //   513: return
  }
  
  private static Throwable a(Throwable paramThrowable) {
    return paramThrowable;
  }
  
  private static String a(int paramInt1, int paramInt2) {
    int i = (paramInt1 ^ 0x673) & 0xFFFF;
    if (b[i] == null) {
      char[] arrayOfChar = a[i].toCharArray();
      switch (arrayOfChar[0] & 0xFF) {
        case 0:
        
        case 1:
        
        case 2:
        
        case 3:
        
        case 4:
        
        case 5:
        
        case 6:
        
        case 7:
        
        case 8:
        
        case 9:
        
        case 10:
        
        case 11:
        
        case 12:
        
        case 13:
        
        case 14:
        
        case 15:
        
        case 16:
        
        case 17:
        
        case 18:
        
        case 19:
        
        case 20:
        
        case 21:
        
        case 22:
        
        case 23:
        
        case 24:
        
        case 25:
        
        case 26:
        
        case 27:
        
        case 28:
        
        case 29:
        
        case 30:
        
        case 31:
        
        case 32:
        
        case 33:
        
        case 34:
        
        case 35:
        
        case 36:
        
        case 37:
        
        case 38:
        
        case 39:
        
        case 40:
        
        case 41:
        
        case 42:
        
        case 43:
        
        case 44:
        
        case 45:
        
        case 46:
        
        case 47:
        
        case 48:
        
        case 49:
        
        case 50:
        
        case 51:
        
        case 52:
        
        case 53:
        
        case 54:
        
        case 55:
        
        case 56:
        
        case 57:
        
        case 58:
        
        case 59:
        
        case 60:
        
        case 61:
        
        case 62:
        
        case 63:
        
        case 64:
        
        case 65:
        
        case 66:
        
        case 67:
        
        case 68:
        
        case 69:
        
        case 70:
        
        case 71:
        
        case 72:
        
        case 73:
        
        case 74:
        
        case 75:
        
        case 76:
        
        case 77:
        
        case 78:
        
        case 79:
        
        case 80:
        
        case 81:
        
        case 82:
        
        case 83:
        
        case 84:
        
        case 85:
        
        case 86:
        
        case 87:
        
        case 88:
        
        case 89:
        
        case 90:
        
        case 91:
        
        case 92:
        
        case 93:
        
        case 94:
        
        case 95:
        
        case 96:
        
        case 97:
        
        case 98:
        
        case 99:
        
        case 100:
        
        case 101:
        
        case 102:
        
        case 103:
        
        case 104:
        
        case 105:
        
        case 106:
        
        case 107:
        
        case 108:
        
        case 109:
        
        case 110:
        
        case 111:
        
        case 112:
        
        case 113:
        
        case 114:
        
        case 115:
        
        case 116:
        
        case 117:
        
        case 118:
        
        case 119:
        
        case 120:
        
        case 121:
        
        case 122:
        
        case 123:
        
        case 124:
        
        case 125:
        
        case 126:
        
        case 127:
        
        case 128:
        
        case 129:
        
        case 130:
        
        case 131:
        
        case 132:
        
        case 133:
        
        case 134:
        
        case 135:
        
        case 136:
        
        case 137:
        
        case 138:
        
        case 139:
        
        case 140:
        
        case 141:
        
        case 142:
        
        case 143:
        
        case 144:
        
        case 145:
        
        case 146:
        
        case 147:
        
        case 148:
        
        case 149:
        
        case 150:
        
        case 151:
        
        case 152:
        
        case 153:
        
        case 154:
        
        case 155:
        
        case 156:
        
        case 157:
        
        case 158:
        
        case 159:
        
        case 160:
        
        case 161:
        
        case 162:
        
        case 163:
        
        case 164:
        
        case 165:
        
        case 166:
        
        case 167:
        
        case 168:
        
        case 169:
        
        case 170:
        
        case 171:
        
        case 172:
        
        case 173:
        
        case 174:
        
        case 175:
        
        case 176:
        
        case 177:
        
        case 178:
        
        case 179:
        
        case 180:
        
        case 181:
        
        case 182:
        
        case 183:
        
        case 184:
        
        case 185:
        
        case 186:
        
        case 187:
        
        case 188:
        
        case 189:
        
        case 190:
        
        case 191:
        
        case 192:
        
        case 193:
        
        case 194:
        
        case 195:
        
        case 196:
        
        case 197:
        
        case 198:
        
        case 199:
        
        case 200:
        
        case 201:
        
        case 202:
        
        case 203:
        
        case 204:
        
        case 205:
        
        case 206:
        
        case 207:
        
        case 208:
        
        case 209:
        
        case 210:
        
        case 211:
        
        case 212:
        
        case 213:
        
        case 214:
        
        case 215:
        
        case 216:
        
        case 217:
        
        case 218:
        
        case 219:
        
        case 220:
        
        case 221:
        
        case 222:
        
        case 223:
        
        case 224:
        
        case 225:
        
        case 226:
        
        case 227:
        
        case 228:
        
        case 229:
        
        case 230:
        
        case 231:
        
        case 232:
        
        case 233:
        
        case 234:
        
        case 235:
        
        case 236:
        
        case 237:
        
        case 238:
        
        case 239:
        
        case 240:
        
        case 241:
        
        case 242:
        
        case 243:
        
        case 244:
        
        case 245:
        
        case 246:
        
        case 247:
        
        case 248:
        
        case 249:
        
        case 250:
        
        case 251:
        
        case 252:
        
        case 253:
        
        case 254:
        
        default:
          break;
      } 
      char c = 'Ã™';
      int j = (paramInt2 & 0xFF) - c;
      if (j < 0)
        j += 256; 
      int k = ((paramInt2 & 0xFFFF) >>> 8) - c;
      if (k < 0)
        k += 256; 
      for (byte b = 0; b < arrayOfChar.length; b++) {
        int m = b % 2;
        if (m == 0) {
          arrayOfChar[b] = (char)(arrayOfChar[b] ^ j);
          j = ((j >>> 3 | j << 5) ^ arrayOfChar[b]) & 0xFF;
        } else {
          arrayOfChar[b] = (char)(arrayOfChar[b] ^ k);
          k = ((k >>> 3 | k << 5) ^ arrayOfChar[b]) & 0xFF;
        } 
      } 
      b[i] = (new String(arrayOfChar)).intern();
    } 
    return b[i];
  }
}


/* Location:              C:\Program Files\BurpSuitePro\burpsuite_pro.jar!\burp\Zeyt.class
 * Java compiler version: 21 (65.0)
 * JD-Core Version:       1.1.3
 */