package burp;

import java.io.IOException;
import java.io.Reader;
import java.util.Deque;
import java.util.LinkedList;
import javax.swing.text.Segment;
import net.portswigger.Zah;
import net.portswigger.Zk_;

public class Zeyz extends Zeyj {
  private static final char[] Z_;
  
  private static final int[] ZA;
  
  private static final int[] Zh;
  
  private static final int[] ZT;
  
  private static final String[] ZY;
  
  private static final int[] Zo;
  
  private Reader Zc;
  
  private int ZV;
  
  private int Zp = 0;
  
  private char[] ZZ;
  
  private int Zv;
  
  private int Zf;
  
  private int ZP;
  
  private int ZW;
  
  private int Zu;
  
  private boolean ZL = true;
  
  private boolean ZN;
  
  private final Deque<Integer> ZU = new LinkedList<>();
  
  private static final String[] a;
  
  private static final String[] b;
  
  private static int[] ZE() {
    int[] arrayOfInt = new int[185];
    int i = 0;
    i = Zs(a(-1161, -7665), i, arrayOfInt);
    return arrayOfInt;
  }
  
  private static int Zs(String paramString, int paramInt, int[] paramArrayOfint) {
    byte b = 0;
    int i = paramInt;
    int j = paramString.length();
    label12: while (b < j) {
      char c1 = paramString.charAt(b++);
      char c2 = paramString.charAt(b++);
      try {
        while (true) {
          paramArrayOfint[i++] = c2;
          if (--c1 <= '\000')
            continue label12; 
        } 
      } catch (ArrayIndexOutOfBoundsException arrayIndexOutOfBoundsException) {
        throw a(null);
      } 
    } 
    return i;
  }
  
  private static int[] Zc() {
    int[] arrayOfInt = new int[185];
    int i = 0;
    i = Za(a(-1162, -19177), i, arrayOfInt);
    return arrayOfInt;
  }
  
  private static int Za(String paramString, int paramInt, int[] paramArrayOfint) {
    byte b = 0;
    int i = paramInt;
    int j = paramString.length();
    while (b < j) {
      int k = paramString.charAt(b++) << 16;
      paramArrayOfint[i++] = k | paramString.charAt(b++);
    } 
    return i;
  }
  
  private static int[] ZJ() {
    int[] arrayOfInt = new int[6171];
    int i = 0;
    i = ZU(a(-1168, 14408), i, arrayOfInt);
    return arrayOfInt;
  }
  
  private static int ZU(String paramString, int paramInt, int[] paramArrayOfint) {
    byte b = 0;
    int i = paramInt;
    int j = paramString.length();
    label12: while (b < j) {
      char c1 = paramString.charAt(b++);
      char c2 = paramString.charAt(b++);
      c2--;
      try {
        while (true) {
          paramArrayOfint[i++] = c2;
          if (--c1 <= '\000')
            continue label12; 
        } 
      } catch (ArrayIndexOutOfBoundsException arrayIndexOutOfBoundsException) {
        throw a(null);
      } 
    } 
    return i;
  }
  
  private static int[] Zm() {
    int[] arrayOfInt = new int[185];
    int i = 0;
    i = Zn(a(-1167, -11723), i, arrayOfInt);
    return arrayOfInt;
  }
  
  private static int Zn(String paramString, int paramInt, int[] paramArrayOfint) {
    byte b = 0;
    int i = paramInt;
    int j = paramString.length();
    label12: while (b < j) {
      char c1 = paramString.charAt(b++);
      char c2 = paramString.charAt(b++);
      try {
        while (true) {
          paramArrayOfint[i++] = c2;
          if (--c1 <= '\000')
            continue label12; 
        } 
      } catch (ArrayIndexOutOfBoundsException arrayIndexOutOfBoundsException) {
        throw a(null);
      } 
    } 
    return i;
  }
  
  private void Zr(int paramInt) {
    int i = this.ZW + this.ZM;
    Zq(this.ZZ, this.ZW, this.Zv - 1, paramInt, i);
    this.ZW = this.Zv;
  }
  
  private void ZV(int paramInt1, int paramInt2, int paramInt3) {
    int i = paramInt1 + this.ZM;
    Zq(this.ZZ, paramInt1, paramInt2, paramInt3, i);
  }
  
  public Ze7g Z_(int paramInt1, Segment paramSegment, Zska paramZska, int paramInt2) {
    // Byte code:
    //   0: aload_0
    //   1: invokevirtual ZS : ()V
    //   4: invokestatic Zd : ()Ljava/lang/String;
    //   7: aload_0
    //   8: aload_2
    //   9: getfield offset : I
    //   12: ineg
    //   13: iload #4
    //   15: iadd
    //   16: putfield ZM : I
    //   19: astore #5
    //   21: aload_3
    //   22: invokevirtual ZX : ()I
    //   25: istore #7
    //   27: iload #7
    //   29: lookupswitch default -> 64, 14 -> 48
    //   48: iconst_4
    //   49: istore #6
    //   51: aload_0
    //   52: aload_2
    //   53: getfield offset : I
    //   56: putfield ZJ : I
    //   59: aload #5
    //   61: ifnonnull -> 67
    //   64: iconst_0
    //   65: istore #6
    //   67: aload_0
    //   68: aload_2
    //   69: putfield ZC : Ljavax/swing/text/Segment;
    //   72: aload_0
    //   73: aload_0
    //   74: getfield Zc : Ljava/io/Reader;
    //   77: invokevirtual ZK : (Ljava/io/Reader;)V
    //   80: aload_0
    //   81: getfield ZU : Ljava/util/Deque;
    //   84: invokeinterface isEmpty : ()Z
    //   89: ifne -> 112
    //   92: aload_0
    //   93: getfield ZU : Ljava/util/Deque;
    //   96: invokeinterface getFirst : ()Ljava/lang/Object;
    //   101: checkcast java/lang/Integer
    //   104: invokevirtual intValue : ()I
    //   107: iload #6
    //   109: if_icmpeq -> 130
    //   112: aload_0
    //   113: iload #6
    //   115: invokevirtual ZS : (I)V
    //   118: aload #5
    //   120: ifnonnull -> 143
    //   123: goto -> 130
    //   126: invokestatic a : (Ljava/lang/Exception;)Ljava/lang/Exception;
    //   129: athrow
    //   130: aload_0
    //   131: iload #6
    //   133: invokevirtual Zc : (I)V
    //   136: goto -> 143
    //   139: invokestatic a : (Ljava/lang/Exception;)Ljava/lang/Exception;
    //   142: athrow
    //   143: aload_0
    //   144: invokevirtual Zi : ()Lburp/Ze7g;
    //   147: areturn
    //   148: astore #8
    //   150: aload #8
    //   152: getstatic net/portswigger/Zk_.UNEXPECTED : Lnet/portswigger/Zk_;
    //   155: invokestatic Zl : (Ljava/lang/Throwable;Lnet/portswigger/Zk_;)V
    //   158: new burp/Ze7g
    //   161: dup
    //   162: invokespecial <init> : ()V
    //   165: areturn
    // Exception table:
    //   from	to	target	type
    //   72	147	148	java/io/IOException
    //   92	123	126	java/io/IOException
    //   112	136	139	java/io/IOException
  }
  
  private void ZS(int paramInt) {
    this.ZU.push(Integer.valueOf(paramInt));
    Zc(paramInt);
  }
  
  private void Ze() {
    try {
      if (this.ZU.isEmpty())
        return; 
    } catch (ArrayIndexOutOfBoundsException arrayIndexOutOfBoundsException) {
      throw a(null);
    } 
    this.ZU.pop();
    Zc(((Integer)this.ZU.getFirst()).intValue());
  }
  
  private boolean ZO() {
    try {
    
    } catch (ArrayIndexOutOfBoundsException arrayIndexOutOfBoundsException) {
      throw a(null);
    } 
    return (this.ZP >= this.ZC.offset + this.ZC.count);
  }
  
  public final void ZK(Reader paramReader) {
    this.ZZ = this.ZC.array;
    this.ZW = this.ZC.offset;
    this.Zu = this.ZW + this.ZC.count - 1;
    this.ZP = this.Zv = this.Zf = this.ZC.offset;
    this.Zp = 0;
    this.Zc = paramReader;
    this.ZL = true;
    this.ZN = false;
  }
  
  private static char[] ZL(String paramString) {
    char[] arrayOfChar = new char[65536];
    byte b1 = 0;
    byte b2 = 0;
    label12: while (b1 < 'ÂŠ') {
      char c1 = paramString.charAt(b1++);
      char c2 = paramString.charAt(b1++);
      try {
        while (true) {
          arrayOfChar[b2++] = c2;
          if (--c1 <= '\000')
            continue label12; 
        } 
      } catch (ArrayIndexOutOfBoundsException arrayIndexOutOfBoundsException) {
        throw a(null);
      } 
    } 
    return arrayOfChar;
  }
  
  public final void Zc(int paramInt) {
    this.Zp = paramInt;
  }
  
  private void Zz(int paramInt) {
    String str;
    try {
      str = ZY[paramInt];
    } catch (ArrayIndexOutOfBoundsException arrayIndexOutOfBoundsException) {
      Zah.Zl(arrayIndexOutOfBoundsException, Zk_.UNEXPECTED);
      str = ZY[0];
    } 
    throw new Error(str);
  }
  
  public Ze7g Zi() throws IOException {
    // Byte code:
    //   0: aload_0
    //   1: getfield Zu : I
    //   4: istore #6
    //   6: invokestatic Zd : ()Ljava/lang/String;
    //   9: aload_0
    //   10: getfield ZZ : [C
    //   13: astore #7
    //   15: astore_1
    //   16: getstatic burp/Zeyz.Z_ : [C
    //   19: astore #8
    //   21: getstatic burp/Zeyz.ZT : [I
    //   24: astore #9
    //   26: getstatic burp/Zeyz.Zh : [I
    //   29: astore #10
    //   31: getstatic burp/Zeyz.Zo : [I
    //   34: astore #11
    //   36: aload_0
    //   37: iconst_m1
    //   38: dup_x1
    //   39: putfield Zf : I
    //   42: istore #12
    //   44: aload_0
    //   45: getfield Zv : I
    //   48: istore #5
    //   50: iconst_m1
    //   51: istore_3
    //   52: aload_0
    //   53: aload_0
    //   54: iload #5
    //   56: dup_x1
    //   57: putfield ZW : I
    //   60: dup_x1
    //   61: putfield ZP : I
    //   64: istore #4
    //   66: aload_0
    //   67: aload_0
    //   68: getfield Zp : I
    //   71: putfield ZV : I
    //   74: iconst_0
    //   75: istore #13
    //   77: iload #4
    //   79: iload #6
    //   81: if_icmpge -> 97
    //   84: aload #7
    //   86: iload #4
    //   88: iinc #4, 1
    //   91: caload
    //   92: istore_2
    //   93: aload_1
    //   94: ifnonnull -> 191
    //   97: aload_0
    //   98: getfield ZN : Z
    //   101: ifeq -> 117
    //   104: goto -> 111
    //   107: invokestatic a : (Ljava/lang/Exception;)Ljava/lang/Exception;
    //   110: athrow
    //   111: iconst_m1
    //   112: istore_2
    //   113: aload_1
    //   114: ifnonnull -> 312
    //   117: aload_0
    //   118: iload #4
    //   120: putfield ZP : I
    //   123: aload_0
    //   124: iload #5
    //   126: putfield Zv : I
    //   129: aload_0
    //   130: iload #12
    //   132: putfield Zf : I
    //   135: aload_0
    //   136: invokevirtual ZO : ()Z
    //   139: istore #14
    //   141: aload_0
    //   142: getfield ZP : I
    //   145: istore #4
    //   147: aload_0
    //   148: getfield Zv : I
    //   151: istore #5
    //   153: aload_0
    //   154: getfield ZZ : [C
    //   157: astore #7
    //   159: aload_0
    //   160: getfield Zu : I
    //   163: istore #6
    //   165: aload_0
    //   166: getfield Zf : I
    //   169: istore #12
    //   171: iload #14
    //   173: ifeq -> 182
    //   176: iconst_m1
    //   177: istore_2
    //   178: aload_1
    //   179: ifnonnull -> 312
    //   182: aload #7
    //   184: iload #4
    //   186: iinc #4, 1
    //   189: caload
    //   190: istore_2
    //   191: aload #9
    //   193: aload #10
    //   195: aload_0
    //   196: getfield ZV : I
    //   199: iaload
    //   200: aload #8
    //   202: iload_2
    //   203: caload
    //   204: iadd
    //   205: iaload
    //   206: istore #14
    //   208: iload #14
    //   210: iconst_m1
    //   211: if_icmpne -> 221
    //   214: goto -> 312
    //   217: invokestatic a : (Ljava/lang/Exception;)Ljava/lang/Exception;
    //   220: athrow
    //   221: aload_0
    //   222: iload #14
    //   224: putfield ZV : I
    //   227: aload #11
    //   229: aload_0
    //   230: getfield ZV : I
    //   233: iaload
    //   234: istore #15
    //   236: iload #15
    //   238: iconst_2
    //   239: iand
    //   240: iconst_2
    //   241: if_icmpne -> 248
    //   244: iload #4
    //   246: istore #12
    //   248: iload #15
    //   250: iconst_1
    //   251: iand
    //   252: iconst_1
    //   253: if_icmpne -> 308
    //   256: iload #15
    //   258: iconst_4
    //   259: iand
    //   260: iconst_4
    //   261: if_icmpne -> 279
    //   264: goto -> 271
    //   267: invokestatic a : (Ljava/lang/Exception;)Ljava/lang/Exception;
    //   270: athrow
    //   271: iconst_1
    //   272: goto -> 280
    //   275: invokestatic a : (Ljava/lang/Exception;)Ljava/lang/Exception;
    //   278: athrow
    //   279: iconst_0
    //   280: istore #13
    //   282: aload_0
    //   283: getfield ZV : I
    //   286: istore_3
    //   287: iload #4
    //   289: istore #5
    //   291: iload #15
    //   293: bipush #8
    //   295: iand
    //   296: bipush #8
    //   298: if_icmpne -> 308
    //   301: goto -> 312
    //   304: invokestatic a : (Ljava/lang/Exception;)Ljava/lang/Exception;
    //   307: athrow
    //   308: aload_1
    //   309: ifnonnull -> 77
    //   312: aload_0
    //   313: iload #5
    //   315: putfield Zv : I
    //   318: iload #13
    //   320: ifeq -> 336
    //   323: aload_0
    //   324: iload #12
    //   326: putfield Zv : I
    //   329: goto -> 336
    //   332: invokestatic a : (Ljava/lang/Exception;)Ljava/lang/Exception;
    //   335: athrow
    //   336: iload_3
    //   337: ifge -> 348
    //   340: iload_3
    //   341: goto -> 353
    //   344: invokestatic a : (Ljava/lang/Exception;)Ljava/lang/Exception;
    //   347: athrow
    //   348: getstatic burp/Zeyz.ZA : [I
    //   351: iload_3
    //   352: iaload
    //   353: tableswitch default -> 764, 1 -> 667, 2 -> 530, 3 -> 512, 4 -> 741, 5 -> 580, 6 -> 750, 7 -> 643, 8 -> 560, 9 -> 709, 10 -> 760, 11 -> 687, 12 -> 719, 13 -> 570, 14 -> 677, 15 -> 550, 16 -> 540, 17 -> 590, 18 -> 613, 19 -> 526, 20 -> 536, 21 -> 546, 22 -> 556, 23 -> 566, 24 -> 576, 25 -> 586, 26 -> 609, 27 -> 639, 28 -> 663, 29 -> 673, 30 -> 683, 31 -> 705, 32 -> 715, 33 -> 737, 34 -> 746, 35 -> 756, 36 -> 760
    //   512: aload_0
    //   513: invokevirtual Zf : ()Lburp/Zska;
    //   516: pop
    //   517: aload_0
    //   518: getfield Zz : Lburp/Ze7g;
    //   521: areturn
    //   522: invokestatic a : (Ljava/lang/Exception;)Ljava/lang/Exception;
    //   525: athrow
    //   526: aload_1
    //   527: ifnonnull -> 44
    //   530: aload_0
    //   531: bipush #22
    //   533: invokevirtual Zr : (I)V
    //   536: aload_1
    //   537: ifnonnull -> 44
    //   540: aload_0
    //   541: bipush #11
    //   543: invokevirtual Zr : (I)V
    //   546: aload_1
    //   547: ifnonnull -> 44
    //   550: aload_0
    //   551: bipush #6
    //   553: invokevirtual Zr : (I)V
    //   556: aload_1
    //   557: ifnonnull -> 44
    //   560: aload_0
    //   561: bipush #23
    //   563: invokevirtual Zr : (I)V
    //   566: aload_1
    //   567: ifnonnull -> 44
    //   570: aload_0
    //   571: bipush #18
    //   573: invokevirtual Zr : (I)V
    //   576: aload_1
    //   577: ifnonnull -> 44
    //   580: aload_0
    //   581: bipush #21
    //   583: invokevirtual Zr : (I)V
    //   586: aload_1
    //   587: ifnonnull -> 44
    //   590: aload_0
    //   591: aload_0
    //   592: getfield Zv : I
    //   595: putfield ZJ : I
    //   598: aload_0
    //   599: bipush #14
    //   601: invokevirtual Zr : (I)V
    //   604: aload_0
    //   605: iconst_4
    //   606: invokevirtual ZS : (I)V
    //   609: aload_1
    //   610: ifnonnull -> 44
    //   613: aload_0
    //   614: aload_0
    //   615: getfield ZJ : I
    //   618: aload_0
    //   619: getfield ZW : I
    //   622: iconst_1
    //   623: isub
    //   624: bipush #14
    //   626: invokevirtual ZV : (III)V
    //   629: aload_0
    //   630: bipush #14
    //   632: invokevirtual Zr : (I)V
    //   635: aload_0
    //   636: invokevirtual Ze : ()V
    //   639: aload_1
    //   640: ifnonnull -> 44
    //   643: aload_0
    //   644: aload_0
    //   645: getfield Zv : I
    //   648: putfield ZJ : I
    //   651: aload_0
    //   652: bipush #18
    //   654: invokevirtual Zr : (I)V
    //   657: aload_0
    //   658: bipush #6
    //   660: invokevirtual ZS : (I)V
    //   663: aload_1
    //   664: ifnonnull -> 44
    //   667: aload_0
    //   668: bipush #39
    //   670: invokevirtual Zr : (I)V
    //   673: aload_1
    //   674: ifnonnull -> 44
    //   677: aload_0
    //   678: bipush #20
    //   680: invokevirtual Zr : (I)V
    //   683: aload_1
    //   684: ifnonnull -> 44
    //   687: aload_0
    //   688: bipush #39
    //   690: invokevirtual Zr : (I)V
    //   693: aload_0
    //   694: aload_0
    //   695: getfield Zv : I
    //   698: putfield ZJ : I
    //   701: aload_0
    //   702: invokevirtual Ze : ()V
    //   705: aload_1
    //   706: ifnonnull -> 44
    //   709: aload_0
    //   710: bipush #13
    //   712: invokevirtual Zr : (I)V
    //   715: aload_1
    //   716: ifnonnull -> 44
    //   719: aload_0
    //   720: bipush #21
    //   722: invokevirtual Zr : (I)V
    //   725: aload_0
    //   726: aload_0
    //   727: getfield Zv : I
    //   730: putfield ZJ : I
    //   733: aload_0
    //   734: invokevirtual Ze : ()V
    //   737: aload_1
    //   738: ifnonnull -> 44
    //   741: aload_0
    //   742: iconst_1
    //   743: invokevirtual Zr : (I)V
    //   746: aload_1
    //   747: ifnonnull -> 44
    //   750: aload_0
    //   751: bipush #10
    //   753: invokevirtual Zr : (I)V
    //   756: aload_1
    //   757: ifnonnull -> 44
    //   760: aload_1
    //   761: ifnonnull -> 44
    //   764: iload_2
    //   765: iconst_m1
    //   766: if_icmpne -> 937
    //   769: aload_0
    //   770: getfield ZW : I
    //   773: aload_0
    //   774: getfield ZP : I
    //   777: if_icmpne -> 937
    //   780: goto -> 787
    //   783: invokestatic a : (Ljava/lang/Exception;)Ljava/lang/Exception;
    //   786: athrow
    //   787: aload_0
    //   788: iconst_1
    //   789: putfield ZN : Z
    //   792: aload_0
    //   793: getfield Zp : I
    //   796: lookupswitch default -> 917, 0 -> 860, 4 -> 878, 6 -> 903, 186 -> 874, 187 -> 899, 188 -> 913
    //   856: invokestatic a : (Ljava/lang/Exception;)Ljava/lang/Exception;
    //   859: athrow
    //   860: aload_0
    //   861: invokevirtual Zf : ()Lburp/Zska;
    //   864: pop
    //   865: aload_0
    //   866: getfield Zz : Lburp/Ze7g;
    //   869: areturn
    //   870: invokestatic a : (Ljava/lang/Exception;)Ljava/lang/Exception;
    //   873: athrow
    //   874: aload_1
    //   875: ifnonnull -> 44
    //   878: aload_0
    //   879: aload_0
    //   880: getfield ZJ : I
    //   883: aload_0
    //   884: getfield ZW : I
    //   887: iconst_1
    //   888: isub
    //   889: bipush #14
    //   891: invokevirtual ZV : (III)V
    //   894: aload_0
    //   895: getfield Zz : Lburp/Ze7g;
    //   898: areturn
    //   899: aload_1
    //   900: ifnonnull -> 44
    //   903: aload_0
    //   904: invokevirtual Zf : ()Lburp/Zska;
    //   907: pop
    //   908: aload_0
    //   909: getfield Zz : Lburp/Ze7g;
    //   912: areturn
    //   913: aload_1
    //   914: ifnonnull -> 44
    //   917: aconst_null
    //   918: invokestatic Zwu : ()[Lburp/Zbqc;
    //   921: ifnonnull -> 936
    //   924: ldc 'BJPXwc'
    //   926: invokestatic ZG : (Ljava/lang/String;)V
    //   929: goto -> 936
    //   932: invokestatic a : (Ljava/lang/Exception;)Ljava/lang/Exception;
    //   935: athrow
    //   936: areturn
    //   937: aload_0
    //   938: iconst_1
    //   939: invokevirtual Zz : (I)V
    //   942: goto -> 44
    // Exception table:
    //   from	to	target	type
    //   93	104	107	java/io/IOException
    //   208	217	217	java/io/IOException
    //   248	264	267	java/io/IOException
    //   256	275	275	java/io/IOException
    //   291	304	304	java/io/IOException
    //   312	329	332	java/io/IOException
    //   336	344	344	java/io/IOException
    //   353	522	522	java/io/IOException
    //   764	780	783	java/io/IOException
    //   769	856	856	java/io/IOException
    //   787	870	870	java/io/IOException
    //   917	929	932	java/io/IOException
  }
  
  static {
    // Byte code:
    //   0: bipush #8
    //   2: anewarray java/lang/String
    //   5: astore #5
    //   7: iconst_0
    //   8: istore_3
    //   9: ldc 'Â³5ÃœÂ¬Â–%S=9Â©'Ã]ÃŸCzhrÃ›\\nÂ¬ÃÂ¿<ÂœÂšFiÃ•^Ã‡Â†ÂªÂ”}Q2Â”^\WÃšÃ“Â³lÂ·Â»Ã„Ã»ÃÃµ(Â˜#QRÃ­Ã‚Ã™JaÃŠÃ¸%Â¦Ã—nÃ¤ÃŠÃ€Ãª 9Ã‘Ã‚ÂJ!Âœ1ÃOÂƒÃµhÂ‹4Ã`%pÃš}ÃƒÂ²i25Â·ÂŸÂ•ÃÂƒÂªG\\tÃ¨uDÂ¿qÃ‹Ã»?Â¬>Ã¦Â·ÃÂ‹t-Ã˜Â½ÂR4Â«Â™_@Ã¿Â›ÂÃ©ÃˆW Ã¯Ã¬Â.,Â¶ÂÃˆGFÂ±Â³ÃM,\\rSÃ”Â¹ÃÂ&Â­Â˜Ã»\\b#_Â±Â‰Ã IÃÃJÃdÃ£z\\fÃ·Ã’jÂ¾ÃšÃ©Ã‰LÃ‹Ã•Ã¦Ã†[Â Â¾Â‘Å²#ÂZ7ÂÃÂ„Ã‚ÂÂÂkÂ¢GjÂ·1ÃŒÂ¬Ãš2ÂÂÃ¯Ä˜Â®Ä‹Ã«Ç¶Ç‚Å‡Ë†Â…Ë—Ã¬Ê½ÃÈÃ§FÂ€Ã²(k5EÂ¼Ã´Ã‰ÃFÂ‡hÂŒ7Â©Ã“,"C^4É›Ã•Ì€Â„Î“Ã¬Î·Â¥Ì¨Â­Ì·sÓ–2ÑŠÓ«ÂœÑ”Ã¯Ó¼Ã…Õ¦Â¡Ô·Ã²ÔÕ™Õ\Ö®Ã·Â…Ã†ÕŒÃ!Ã¾Ã²ÂƒÅ”#Æ‚ZÙ²7ÛºÃÛ³Ã‚Ù§ÂÙ·ÂÜ¼Â¢İ¨jÈ›1ÅÉ•Ãšß®ÂŞ¤Ã¯Ü©Â®à£°Ã«à£ˆà¡à œà –Â…à¦Ã¬à¦¹ÃÆ½Ã§à¤¨Â€à¤˜(à¤àªœE×Ã´Õ„ÃÔ›Â‡×†ÂŒ×»Â©Ô„,Õ»Càª¤4HÃ•à«ŠÂ„Ô›Ã¬à©˜Â¥à¨·Â­à©¦sÙ¨2Ø’vÂœÚ¤Ã¯=Ã…Â’Â¡à¬‘Ã²à¬¨à®ƒà¯·\à¬µÃ·à²·Ã†à°¼Ãà°¥Ã¾à°¤Âƒà²—#àµ€Zàµµ7à´ŒÃàµ°Ã‚à¶ŠÂàº¤ÂÂ¢à»—jà»¤1àº„ÇÃšà»¿Âà½¨Ã¯à¿‚Â®Æ™Ã«à¾¶à¿¬à¼´áµÂ…áƒƒÃ¬á•Ãá‚·Ã§áƒ´Â€×¾(á……á‡’EÄ¥Ã´Ä°Ãá†ƒÂ‡á‡ÂŒá…†Â©á†¹,áˆ›CÅ¿4á‰ŠÃ•áˆ‰Â„áˆªÃ¬áˆ™Â¥áŒ€Â­Å¿sáŒ‰2á¦áŒ¢Âœá Ã¯á®Ã…ÄÂ¡Å³Ã²á’‰á’”á†\á‘‚Ã·á–œÃ†á•ŒÃá•ˆÃ¾á—–Âƒá•‰#áššZÅ7á˜ŒÃá˜‹Ã‚á˜šÂÄºÂá™ŸÂ¢áœºjá‘1Æµá®ÃšÅœÂÅ›Ã¯Ç¿Â®ášÃ«á¾ÄƒHÂ—Ã½ÂŒqÂ«{ÃŠ5(Â±Â¥bu]Ã®ÂÃƒÂ¾$Â¢Âœ/Â¨Ã²Â²KYXÂ¥Ã»Ã‰tkÃ†r=3Â¸dÃ»Â’\\fÃ½Ã›ÃAÂ†Â­Â„Ã‰ÂIZÃÃ˜Â„ÃŠYOÃÂ”Ã•Â‹Ã§ià¡¾AV6.ÂšÃ™KPÃ¬1Ã¡ÃO<Ã·BÂ¢5LÂ¬Â°ÂÃ°bÃš?Ã£Ã¹acÂ—tÂÂ· ~~Ã—Â¼Â¡Â‰Â–m\\fÂµrÂÂ²Ã¶ÂÃ£Â B\\nÃ‹FÂ»NZ/ÃšÂ™Âª@Â§ÂÂ™Ã‹F@Â–Ã®kÂ£EYÂ³KÂÃ¶Ã©\\n6Â‘W`ÃµÃ°ÃÃ½Â§~Â¬Âª\\tÃŸÂ‚ÃƒWÃ¡\\rÂ¨?Â†4Â’Â•Ã±.ÂÃšÃŸ.Â³Â¶Ã»ÂºÂƒÂ€4|Â{ÃšÂ–>Ã‰ÂŠcVÂ†Â¨6OÂ…LÂ“Ã¹}Ã‰ÂªÃ‡uÂŸÂªÂ‰Ã·Â°gÂ”ÂƒYÃµ*Ã¿0]]ÂÂ¹Â­Ã±Ã”ÃmCjÃªÃ†Â«bMÃ¼:Ã¼UÂ£Ã½7Â‚Âš Ã ÃµÃ«Âœ\\rÃÃ˜Â‰ÃkÂ’Â€Â\\bÂ€ÂdÃ”\\fÃ¸X{Ã„gÂ®Ã—Â¿ÃƒÂ’Â‹ÃºÂ½y |9vBÃ•Ã Â§Ã¶Â–$Ã“Â;Â§Ã¤Â€`zSo)Â¨Z3[FyÃµgÃŒÃ¦Â©tÃ»Â¤ Ã”ÂL9Ã‹ÂšiBÂ¨\\reÂ‡QÃWÂ‹Â¤tÃ›ÃƒÂ¦TÂSÂ°>ÃÂ—Ã¹gUÃ•Ã€I^Ã¥Ã­+ÂkZ\\bPLPÂÃ Â³Ã¨wÃ‹Â¢wÂ‰Â§s\\b^Â ÂˆQn\\fÃÂ¡Â©Ã¬Ã Ã¸Â€,Ã†Â®ÃªÂ‡Â§ÃÂ£dÂ¶Ã£S9Â¶ Â¢Â–0K_nkÂ¯Â´Ã´Ã¦Â™Â¡ÃŒdÃ›MÂ¯JÃ‚?"Âuk\\bÂ¼LÂÂ„Â³ÂwÂÃ©@Ã‚KÃ‰xv/ÃŒÂ Âƒ2Â¦fÃ‰Ã§Ã”Â±'1*5Ã›[/NÂÃ‹9DÃ–ÃªÃˆ!ÂœÃ™ÃœÂœÃ‡Ã‰Ã Ãƒ!Â‰F#Â´Ã¡ÃƒvÂ‡hÃ#Ã§nAÂÃÂƒÂ²Ã«f(fÃ ÂŸseÂ·Ã‰Â†Ã–Â­AÃ¥Â‚>^\\rÂBIÃ¥Ã¿Ã»Ã,LÂ†Â”7Â‡'XÂ›_cÂ’[Ã¸8"yZÂ³Â“Â³m/Ã’Â±ÃÂ‘u#RUÂºÃ¡IC?xÂœ{eQBiÃªÂ ÂÂ‚hÃ—Â°;nÃœÂ¹Ã0Â¬1ÃˆaÃ‰Â€Â™gÃ…Â¹Ã’hzN\\nÂ¶gÃ†ÃŒÃŠAÂ‹M\\nÂƒjÃ¼Ã¼Ã½Â¾ÃµÃÃ¥Ã¿Ã¾Â„ÂµÂ¥Â–Ã–Â—ÂÂ¼Â®Ã’AÂ‚Â5lÃ«zÃ‡-Ã§Â¤ÂƒÂ“Ã£Â Âš\\t}Â¨ÂÂ´Ã¸Â°Ã‰6$Â»Â¦cÂ™ÃŸ4ÃºÂ-Ã·Ã¹9Ã€Z!Ã¹ÂºÃ…'ÂÃ³RÃÃšÃ›Â¦Ã…TÃšSZL>vÂ—ÂŒ`Ã»Ã’3Â²Ã‚Ã¢~Ã‹Ã¯%Ã™Ã u^Â©!WÃšÃ«Ã†Ã€ÃÂ…Ã¹LUÃ–ÂŠÂ™LÂ¤Â™Â´!NÃºÂ¬Â©Â¶\\nrf,TÂ„ÂŸÂ—H\\rVÃ£Â±Ã¢\\fj6Ã¯UÂ™Â±Ãª{Â€hÂoÃ‹Ã¬\\tÂš\Â¬Ã›Ã—Ã£ÂÃ©CÃ“r\\bhÂ–-Âª}Â¬ÃŠÂÂ‹Â…Â›Ã’Â„[%Â² 1}Q4\\nÂ„ÂŠÂ¦Â‡Ã´Ã­FÂ‚Â­DÃ¸:gÂŸYi,Ã—zÃ€\\rÂ¥Ã‹ÂYTnÃºÃ«Â£](J~*Â‚7&Ã‡PÂ›2-~Â¡wX0:kOÃ¿DÃ¯Ã©Ã­ÂŒ.ÂµÃ†Â’Â™3ÃÂ®ÃƒÂ²&Ã»QÂ€RÂ¿ Ã$<ÃÃ·Ã£ÃÃŒÂˆÃ·\#ÂŒÃ¤Ã³EÃ˜Ã¨fÃ¢ÂœÂ©Ã±oÃ•ÂmÂ•:Â’?ÂŠ4Ã˜Ã‹A~Ã‚Â­Â­Â´BÃªGÂ¶Â€Â”Ã¬Ã¸Ã‚?Â¢rÂ“n`ÃÃ‡Â Ã‰?ÃVÃ›Rz_HPÃ¶UÂœÃ‘Ã¹Â‰Â¦.ÂÂ¤ÃÂ¸r_gÂÃÃÂ¤\ÂºÂ·@-Ã˜Â…Ãµ9Â˜Ã±3#Â¾[Â²XdÂÂ‘Â¿Â£Ã“sÂ€Â‘*pÃ¸d%Â¬!ÃT<gÂ§ÂƒÂ¬.`Â˜AÃ/YÂ‡Ã²Ã±.9Â¸Ã˜GY~AÂ•Â‰FÃ…Ã£ÂÃ«Ã³Â¦YÂ±0{\haoÃÃ¬Ãˆ.Â®Â‡)Âšzs\\f+Ã¾CÃHÃ«Ã‘Â¦_Â‡%Ã‚PÃ“hÃ¢\\fIÂ†Â’/\\rÂ§ÃšÂnÃ³Âµ;Â»Ã…ÂŒÂ›IÃ‹LÃ„|ÂŸjÂ‘R35a6Ã“Ã¹Â½5Ã¨Ãˆ=Ã¢yzÃ¹o"5{Ãƒ{5ÃŠÂ¡ÂŒÃÃ©MÃÂ®C*RÃ·ÂŠÃ„qkÃ“KÂ‡IÂvÃ¿ÃœÂ½Ã–Ã…lqhÂ˜Â¼e6Â‰Â¾_ÃŒcÃƒÃ˜Â·Â¼Â…Â–Â¥Ã•EÂ¾ÃªÂ¬7Â Ã†zÂÂ–Â±=Ã»Â/Ã† ÂºVÂœÃFWÃ¸Â·jÃ–OÂŸÃ³Ã•Â¨Âš\\bÂ‹>Ã“ÃÃ…Ã¾40Ã°;!`ÃÃ³Ã¡<ÂÃ­\\nÂÃ„Ã¶Ã¨Ã¸Ã¥?dÂ±ÃŸ\\f\\nÃŒÂœÂÂ±Â»7Ã¡ÂÃƒÃ£:Ã®-\\nÂˆzÂ¥i#\\ryzJTÃÂ‡Ã°Â’Ã¬SÂÃ½Â½Ã‚Â¼k)2Ã¥ÃŸÂšÃ«soÂ¶>Â³ÂÂªÂ™Ã±Â£\Ã¬ÂŠÂˆVÂª5\\nÃ¤:Ã¶rÃ¾"ÂšÃŸÃ§Â†[xqÂŒÂ²Â–Â³Â°iRÃ¥Ã•CkÂ¹|Â¼Â™Â·1Â³<PQ*7ÂÃ™Ã–/Â—WÃµÃŠH*ÃŸÃ†'Â¦Ã¾Â¾Ã¥Ã·9Â»WQ\\nÂ˜\\f^ÃƒÃ§5!Â¡Â¤VMÃ‹Ã™~F0Â˜DÂ‚Ã¢Ã­ÃªJ\Â­Â·Â•Âj((HÂ™Ã™Â£Ã†u&>Ã“]\\bÃ©ÃŸÃ§Ã‡zÂ»Âº&Ã—<ÃšÃ¿ÂƒÃ›Ã¯!ÃºÃ==Â¦cKrÃ¡^VÂ”ÃªÃ‘E%Â¸Â„Hvl1YÂ†\\fÂ²W6Ã­}BÃ°\\ne+Â™EQÃ­~Â°Ã‰Â‚Ã¡Ã¨YcfÃ°Ã‹Ã»`bsKÃ¹Â–Ã§ÃµÃ£Â³\tÃÂ”Ã¿DÃŸÂ•#ÂÂ¥mÂªÃ¨Â«f{_hÃ²Â¾Ã©Ã­8Ã¦wÃºÂªÂŒÃ¿Â"Ã–Ã„Â¸AXÃ…vGÂÂªD?Ã³YÂ‹#{BÃ¸hgÃ•ÃŸÂ¹Â¶mÃ‘GX\\nVÃ™Ã›Â¨ÃW%Â€Ã»0<CÃ¸NÃ©Ã³Ã¥Â¬Ã™Ã®Ã–Ã¶ioOuÃ¨Â»ÃŒÂ¼Ã†Ã•Â£ÃA:DÃ‡M5qKÂ½$+ÂƒÂ€CÂoFRÂ¢]Ãˆ{9mbÂ·j muÃ‹Â—4NÂ&Ã±ÂµÃ¨n7Â¼ÃœÃ•&ÃÃ¾:Z;fÂšÃ¬.Ã¡Â‹i>`ÃƒÂ¡aD+ÃµÂšÃ®NH6ÂŒ/Ã…pÂÂ™Ã³KÂ¦ÂÂ±\\t{{hÂ…oHÃ¬R<X\\nÃG\\nÂ·aÂµiÃ‰)A7Ã°<{ÃµÂ…ÂÃ¤Ã¾Ã»ÃjÃœÃ¶dÂÃKÂ³\VÃ©ÂiRrÃÂ–cÂ·Â»Ãp>lÃ˜ÂŒdÂ–-Â²NF?Ã¿Ã‡Ã½Â½Â¥Â‘bQÂš6Â¶Â‹ivÂ¡B>wÃ€Ã§Â¸Â¾ÂªÂ½oÂ—hÂ·}ÃZ:?4Â±=bÃªÂ‘ZÂ²)Â$ÂÂƒMÂÃ¹Â³Â¦`Ã£Â/Â•rÂ’6ÂŠ?4Ã¼Ã‹Ã…~RÂ­Â´Â´<y`Â²NÂªÂ£\\nTÃ?ÃŸÃ·Ã›Ã¬Â£KÂ–ÃÃ¥DÂ’ÃªÃŠ\LÂŒ2nÂXÂ›>SÂ¸/Ã½lÃ‹ÃÂƒ&JÂ†Ã´ÂºÂ¤wÂ«RSÂ§JÂ›!-Ã§Ã¸Â±Ã‚1Ã˜DÃ‚Â‰(6x9_eyÃ†Ã±IÃ–Ã«n[ZK3Â±ÂŸSÃ¨'GÃ£Â²Ã‚FÃ­Ã„Â¦Â“Â–ÂÂ¸Â7Â’Â£-RÂµjÂ¤Â•BÃ—Â·ÃB*ZD^ÂpQÂƒQcÂ‹)nÂ·Â¬Ã´ÃœF#Â­Ã¸ÃŸaÃœ-Ã¤Â¢\\fÂ«Â¾Â‚Ã9Ã•Â¸Â¥\\rÂ’wrÃ³Â–AÂ·<Â»9pÂŠÃš&:Ãš@Â¡Ã·Â¼|Ã½ÂµÂŸ3Â¶Ã°5>ÂÂ¨B1ÃškÂ†jP/Ã“Ã¤\\nÂ›<ÂŒÃ—Ã“gÃœÂšpÂ¹Ã™Â¬Ã­Â˜DvÂ“Âƒ(wÃ¯ÂŒÂÃ¹Â¬+Ã¤'
    //   11: dup
    //   12: astore_2
    //   13: invokevirtual length : ()I
    //   16: istore #4
    //   18: bipush #29
    //   20: istore_1
    //   21: iconst_m1
    //   22: istore_0
    //   23: bipush #62
    //   25: iinc #0, 1
    //   28: aload_2
    //   29: iload_0
    //   30: dup
    //   31: iload_1
    //   32: iadd
    //   33: invokevirtual substring : (II)Ljava/lang/String;
    //   36: iconst_m1
    //   37: goto -> 144
    //   40: aload #5
    //   42: swap
    //   43: iload_3
    //   44: iinc #3, 1
    //   47: swap
    //   48: aastore
    //   49: iload_0
    //   50: iload_1
    //   51: iadd
    //   52: dup
    //   53: istore_0
    //   54: iload #4
    //   56: if_icmpge -> 68
    //   59: aload_2
    //   60: iload_0
    //   61: invokevirtual charAt : (I)C
    //   64: istore_1
    //   65: goto -> 23
    //   68: ldc ' Ã¶ÂÂ‘eÃ–0\\rÂ¶Ã™DÂ»9Â‰%Â¢Â´Â…(%vticÃœFeO?Ã‡6Â¿S9ÃÂ—Â°=Ã§Â°MÃ“Ã¥Â£Â†Ã¨Â–ÂªÃ–]=YÃ†Â¶E@Ã|Â¡Ã£"JÂ¯Âœz Ã‘WÂ¯A8CÃÂ™Ã±ÃÂ¢*ÃÂ”Â¬Ã­TÃ€Ã¢nÃÂ‘'NwÃƒ?LrÂÃº34\\twÂ˜Â‰Â‘#Ã£ZÃ©Ã§Â‰Â¹ZÃ‘ÂºÂŒÂ©ÃšÂ¦0Â•ïºµÂ’0Ä¸Ã–#ÂÃ¿x@fÂ¡Ã±]Ã†%\\r\Y0Ã¨\\b8Ã¨68Ã¬Ã±<Â¢?ÂªÂ¬cÃˆb{Â·Âƒ'
    //   70: dup
    //   71: astore_2
    //   72: invokevirtual length : ()I
    //   75: istore #4
    //   77: sipush #138
    //   80: istore_1
    //   81: iconst_m1
    //   82: istore_0
    //   83: bipush #50
    //   85: iinc #0, 1
    //   88: aload_2
    //   89: iload_0
    //   90: dup
    //   91: iload_1
    //   92: iadd
    //   93: invokevirtual substring : (II)Ljava/lang/String;
    //   96: iconst_0
    //   97: goto -> 144
    //   100: aload #5
    //   102: swap
    //   103: iload_3
    //   104: iinc #3, 1
    //   107: swap
    //   108: aastore
    //   109: iload_0
    //   110: iload_1
    //   111: iadd
    //   112: dup
    //   113: istore_0
    //   114: iload #4
    //   116: if_icmpge -> 128
    //   119: aload_2
    //   120: iload_0
    //   121: invokevirtual charAt : (I)C
    //   124: istore_1
    //   125: goto -> 83
    //   128: aload #5
    //   130: putstatic burp/Zeyz.a : [Ljava/lang/String;
    //   133: bipush #8
    //   135: anewarray java/lang/String
    //   138: putstatic burp/Zeyz.b : [Ljava/lang/String;
    //   141: goto -> 300
    //   144: dup_x2
    //   145: pop
    //   146: invokevirtual toCharArray : ()[C
    //   149: dup_x1
    //   150: arraylength
    //   151: dup_x2
    //   152: pop
    //   153: iconst_0
    //   154: istore #6
    //   156: dup2_x1
    //   157: pop2
    //   158: dup_x2
    //   159: iconst_1
    //   160: if_icmpgt -> 260
    //   163: dup2
    //   164: swap
    //   165: iload #6
    //   167: dup2_x1
    //   168: caload
    //   169: swap
    //   170: iload #6
    //   172: bipush #7
    //   174: irem
    //   175: tableswitch default -> 242, 0 -> 212, 1 -> 217, 2 -> 222, 3 -> 227, 4 -> 232, 5 -> 237
    //   212: bipush #70
    //   214: goto -> 244
    //   217: bipush #73
    //   219: goto -> 244
    //   222: bipush #15
    //   224: goto -> 244
    //   227: bipush #22
    //   229: goto -> 244
    //   232: bipush #100
    //   234: goto -> 244
    //   237: bipush #103
    //   239: goto -> 244
    //   242: bipush #77
    //   244: ixor
    //   245: ixor
    //   246: i2c
    //   247: castore
    //   248: iinc #6, 1
    //   251: dup
    //   252: ifne -> 260
    //   255: dup2
    //   256: dup_x1
    //   257: goto -> 167
    //   260: dup2_x1
    //   261: pop2
    //   262: dup_x2
    //   263: iload #6
    //   265: if_icmpgt -> 163
    //   268: pop
    //   269: new java/lang/String
    //   272: dup_x1
    //   273: swap
    //   274: invokespecial <init> : ([C)V
    //   277: invokevirtual intern : ()Ljava/lang/String;
    //   280: swap
    //   281: pop
    //   282: swap
    //   283: tableswitch default -> 40, 0 -> 100
    //   300: sipush #-1165
    //   303: sipush #-9558
    //   306: invokestatic a : (II)Ljava/lang/String;
    //   309: invokestatic ZL : (Ljava/lang/String;)[C
    //   312: putstatic burp/Zeyz.Z_ : [C
    //   315: invokestatic ZE : ()[I
    //   318: putstatic burp/Zeyz.ZA : [I
    //   321: invokestatic Zc : ()[I
    //   324: putstatic burp/Zeyz.Zh : [I
    //   327: invokestatic ZJ : ()[I
    //   330: putstatic burp/Zeyz.ZT : [I
    //   333: iconst_3
    //   334: anewarray java/lang/String
    //   337: dup
    //   338: iconst_0
    //   339: sipush #-1163
    //   342: sipush #-143
    //   345: invokestatic a : (II)Ljava/lang/String;
    //   348: aastore
    //   349: dup
    //   350: iconst_1
    //   351: sipush #-1164
    //   354: sipush #-31496
    //   357: invokestatic a : (II)Ljava/lang/String;
    //   360: aastore
    //   361: dup
    //   362: iconst_2
    //   363: sipush #-1166
    //   366: sipush #18669
    //   369: invokestatic a : (II)Ljava/lang/String;
    //   372: aastore
    //   373: putstatic burp/Zeyz.ZY : [Ljava/lang/String;
    //   376: invokestatic Zm : ()[I
    //   379: putstatic burp/Zeyz.Zo : [I
    //   382: return
  }
  
  private static Exception a(Exception paramException) {
    return paramException;
  }
  
  private static String a(int paramInt1, int paramInt2) {
    int i = (paramInt1 ^ 0xFFFFFB75) & 0xFFFF;
    if (b[i] == null) {
      char[] arrayOfChar = a[i].toCharArray();
      switch (arrayOfChar[0] & 0xFF) {
        case 0:
        
        case 1:
        
        case 2:
        
        case 3:
        
        case 4:
        
        case 5:
        
        case 6:
        
        case 7:
        
        case 8:
        
        case 9:
        
        case 10:
        
        case 11:
        
        case 12:
        
        case 13:
        
        case 14:
        
        case 15:
        
        case 16:
        
        case 17:
        
        case 18:
        
        case 19:
        
        case 20:
        
        case 21:
        
        case 22:
        
        case 23:
        
        case 24:
        
        case 25:
        
        case 26:
        
        case 27:
        
        case 28:
        
        case 29:
        
        case 30:
        
        case 31:
        
        case 32:
        
        case 33:
        
        case 34:
        
        case 35:
        
        case 36:
        
        case 37:
        
        case 38:
        
        case 39:
        
        case 40:
        
        case 41:
        
        case 42:
        
        case 43:
        
        case 44:
        
        case 45:
        
        case 46:
        
        case 47:
        
        case 48:
        
        case 49:
        
        case 50:
        
        case 51:
        
        case 52:
        
        case 53:
        
        case 54:
        
        case 55:
        
        case 56:
        
        case 57:
        
        case 58:
        
        case 59:
        
        case 60:
        
        case 61:
        
        case 62:
        
        case 63:
        
        case 64:
        
        case 65:
        
        case 66:
        
        case 67:
        
        case 68:
        
        case 69:
        
        case 70:
        
        case 71:
        
        case 72:
        
        case 73:
        
        case 74:
        
        case 75:
        
        case 76:
        
        case 77:
        
        case 78:
        
        case 79:
        
        case 80:
        
        case 81:
        
        case 82:
        
        case 83:
        
        case 84:
        
        case 85:
        
        case 86:
        
        case 87:
        
        case 88:
        
        case 89:
        
        case 90:
        
        case 91:
        
        case 92:
        
        case 93:
        
        case 94:
        
        case 95:
        
        case 96:
        
        case 97:
        
        case 98:
        
        case 99:
        
        case 100:
        
        case 101:
        
        case 102:
        
        case 103:
        
        case 104:
        
        case 105:
        
        case 106:
        
        case 107:
        
        case 108:
        
        case 109:
        
        case 110:
        
        case 111:
        
        case 112:
        
        case 113:
        
        case 114:
        
        case 115:
        
        case 116:
        
        case 117:
        
        case 118:
        
        case 119:
        
        case 120:
        
        case 121:
        
        case 122:
        
        case 123:
        
        case 124:
        
        case 125:
        
        case 126:
        
        case 127:
        
        case 128:
        
        case 129:
        
        case 130:
        
        case 131:
        
        case 132:
        
        case 133:
        
        case 134:
        
        case 135:
        
        case 136:
        
        case 137:
        
        case 138:
        
        case 139:
        
        case 140:
        
        case 141:
        
        case 142:
        
        case 143:
        
        case 144:
        
        case 145:
        
        case 146:
        
        case 147:
        
        case 148:
        
        case 149:
        
        case 150:
        
        case 151:
        
        case 152:
        
        case 153:
        
        case 154:
        
        case 155:
        
        case 156:
        
        case 157:
        
        case 158:
        
        case 159:
        
        case 160:
        
        case 161:
        
        case 162:
        
        case 163:
        
        case 164:
        
        case 165:
        
        case 166:
        
        case 167:
        
        case 168:
        
        case 169:
        
        case 170:
        
        case 171:
        
        case 172:
        
        case 173:
        
        case 174:
        
        case 175:
        
        case 176:
        
        case 177:
        
        case 178:
        
        case 179:
        
        case 180:
        
        case 181:
        
        case 182:
        
        case 183:
        
        case 184:
        
        case 185:
        
        case 186:
        
        case 187:
        
        case 188:
        
        case 189:
        
        case 190:
        
        case 191:
        
        case 192:
        
        case 193:
        
        case 194:
        
        case 195:
        
        case 196:
        
        case 197:
        
        case 198:
        
        case 199:
        
        case 200:
        
        case 201:
        
        case 202:
        
        case 203:
        
        case 204:
        
        case 205:
        
        case 206:
        
        case 207:
        
        case 208:
        
        case 209:
        
        case 210:
        
        case 211:
        
        case 212:
        
        case 213:
        
        case 214:
        
        case 215:
        
        case 216:
        
        case 217:
        
        case 218:
        
        case 219:
        
        case 220:
        
        case 221:
        
        case 222:
        
        case 223:
        
        case 224:
        
        case 225:
        
        case 226:
        
        case 227:
        
        case 228:
        
        case 229:
        
        case 230:
        
        case 231:
        
        case 232:
        
        case 233:
        
        case 234:
        
        case 235:
        
        case 236:
        
        case 237:
        
        case 238:
        
        case 239:
        
        case 240:
        
        case 241:
        
        case 242:
        
        case 243:
        
        case 244:
        
        case 245:
        
        case 246:
        
        case 247:
        
        case 248:
        
        case 249:
        
        case 250:
        
        case 251:
        
        case 252:
        
        case 253:
        
        case 254:
        
        default:
          break;
      } 
      char c = 'Â ';
      int j = (paramInt2 & 0xFF) - c;
      if (j < 0)
        j += 256; 
      int k = ((paramInt2 & 0xFFFF) >>> 8) - c;
      if (k < 0)
        k += 256; 
      for (byte b = 0; b < arrayOfChar.length; b++) {
        int m = b % 2;
        if (m == 0) {
          arrayOfChar[b] = (char)(arrayOfChar[b] ^ j);
          j = ((j >>> 3 | j << 5) ^ arrayOfChar[b]) & 0xFF;
        } else {
          arrayOfChar[b] = (char)(arrayOfChar[b] ^ k);
          k = ((k >>> 3 | k << 5) ^ arrayOfChar[b]) & 0xFF;
        } 
      } 
      b[i] = (new String(arrayOfChar)).intern();
    } 
    return b[i];
  }
}


/* Location:              C:\Program Files\BurpSuitePro\burpsuite_pro.jar!\burp\Zeyz.class
 * Java compiler version: 21 (65.0)
 * JD-Core Version:       1.1.3
 */