package burp;

import java.math.BigInteger;

class Zezn extends ClassLoader {
  static String Ze;
  
  static Object Zh;
  
  private static final String[] a;
  
  private static final String[] b;
  
  static void Zt(Object paramObject) {
    Zlxm.Zv = a(27912, 6516);
    Zlxm.Zc = new BigInteger(a(27918, 26600));
    boolean bool = Zt2e.ZK();
    try {
      try {
        if (Zdm.ZJ.charAt(Math.abs(((BigInteger)Zr9p.ZC).intValue() % 32)) > Zl7k.ZX.charAt(Math.abs(((BigInteger)Zr9p.ZC).intValue() % 32))) {
          try {
            Zxxo.Zf(Class.forName(a(27914, -31435)));
            if (bool)
              Ztev.ZB(Class.forName(a(27917, -21237))); 
          } catch (Throwable throwable) {
            throw a(null);
          } 
          return;
        } 
      } catch (Throwable throwable) {
        throw a(null);
      } 
      Ztev.ZB(Class.forName(a(27917, -21237)));
    } catch (Throwable throwable) {}
  }
  
  static void ZJ(Object[] paramArrayOfObject, Object paramObject) throws Throwable {}
  
  static boolean Ze(Object[] paramArrayOfObject, Object paramObject) throws Throwable {
    // Byte code:
    //   0: invokestatic ZN : ()Z
    //   3: istore_2
    //   4: getstatic burp/Zrkc.ZI : Ljava/lang/Object;
    //   7: checkcast java/math/BigInteger
    //   10: invokevirtual toByteArray : ()[B
    //   13: astore_3
    //   14: new java/lang/StringBuilder
    //   17: dup
    //   18: invokespecial <init> : ()V
    //   21: astore #5
    //   23: aload #5
    //   25: sipush #27907
    //   28: sipush #11567
    //   31: invokestatic a : (II)Ljava/lang/String;
    //   34: invokevirtual append : (Ljava/lang/String;)Ljava/lang/StringBuilder;
    //   37: pop
    //   38: aload_3
    //   39: astore #6
    //   41: aload #6
    //   43: arraylength
    //   44: istore #7
    //   46: iconst_0
    //   47: istore #8
    //   49: iload #8
    //   51: iload #7
    //   53: if_icmpge -> 79
    //   56: aload #6
    //   58: iload #8
    //   60: baload
    //   61: istore #9
    //   63: aload #5
    //   65: iload #9
    //   67: i2c
    //   68: invokevirtual append : (C)Ljava/lang/StringBuilder;
    //   71: pop
    //   72: iinc #8, 1
    //   75: iload_2
    //   76: ifne -> 49
    //   79: aload #5
    //   81: sipush #27910
    //   84: sipush #11179
    //   87: invokestatic a : (II)Ljava/lang/String;
    //   90: ldc ''
    //   92: invokestatic getProperty : (Ljava/lang/String;Ljava/lang/String;)Ljava/lang/String;
    //   95: invokevirtual toLowerCase : ()Ljava/lang/String;
    //   98: invokevirtual append : (Ljava/lang/String;)Ljava/lang/StringBuilder;
    //   101: pop
    //   102: aload #5
    //   104: sipush #27913
    //   107: sipush #8817
    //   110: invokestatic a : (II)Ljava/lang/String;
    //   113: ldc ''
    //   115: invokestatic getProperty : (Ljava/lang/String;Ljava/lang/String;)Ljava/lang/String;
    //   118: invokevirtual toLowerCase : ()Ljava/lang/String;
    //   121: invokevirtual append : (Ljava/lang/String;)Ljava/lang/StringBuilder;
    //   124: pop
    //   125: aload #5
    //   127: invokevirtual toString : ()Ljava/lang/String;
    //   130: invokevirtual getBytes : ()[B
    //   133: astore #4
    //   135: aload #4
    //   137: astore_3
    //   138: aload_3
    //   139: arraylength
    //   140: bipush #8
    //   142: iadd
    //   143: bipush #6
    //   145: ishr
    //   146: iconst_1
    //   147: iadd
    //   148: bipush #16
    //   150: imul
    //   151: newarray int
    //   153: astore #5
    //   155: iconst_0
    //   156: istore #6
    //   158: iload #6
    //   160: aload_3
    //   161: arraylength
    //   162: if_icmpge -> 205
    //   165: aload_3
    //   166: iload #6
    //   168: baload
    //   169: sipush #255
    //   172: iand
    //   173: istore #7
    //   175: aload #5
    //   177: iload #6
    //   179: iconst_2
    //   180: ishr
    //   181: dup2
    //   182: iaload
    //   183: iload #7
    //   185: bipush #24
    //   187: iload #6
    //   189: iconst_4
    //   190: irem
    //   191: bipush #8
    //   193: imul
    //   194: isub
    //   195: ishl
    //   196: ior
    //   197: iastore
    //   198: iinc #6, 1
    //   201: iload_2
    //   202: ifne -> 158
    //   205: aload #5
    //   207: iload #6
    //   209: iconst_2
    //   210: ishr
    //   211: dup2
    //   212: iaload
    //   213: sipush #128
    //   216: bipush #24
    //   218: iload #6
    //   220: iconst_4
    //   221: irem
    //   222: bipush #8
    //   224: imul
    //   225: isub
    //   226: ishl
    //   227: ior
    //   228: iastore
    //   229: aload #5
    //   231: aload #5
    //   233: arraylength
    //   234: iconst_1
    //   235: isub
    //   236: aload_3
    //   237: arraylength
    //   238: bipush #8
    //   240: imul
    //   241: iastore
    //   242: bipush #80
    //   244: newarray int
    //   246: astore #7
    //   248: ldc 1732584193
    //   250: istore #8
    //   252: ldc -271733879
    //   254: istore #9
    //   256: ldc -1732584194
    //   258: istore #10
    //   260: ldc 271733878
    //   262: istore #11
    //   264: ldc -1009589776
    //   266: istore #12
    //   268: iconst_0
    //   269: istore #6
    //   271: iload #6
    //   273: aload #5
    //   275: arraylength
    //   276: if_icmpge -> 598
    //   279: iload #8
    //   281: istore #13
    //   283: iload #9
    //   285: istore #14
    //   287: iload #10
    //   289: istore #15
    //   291: iload #11
    //   293: istore #16
    //   295: iload #12
    //   297: istore #17
    //   299: iconst_0
    //   300: istore #18
    //   302: iload #18
    //   304: bipush #80
    //   306: if_icmpge -> 556
    //   309: iload #18
    //   311: bipush #16
    //   313: if_icmpge -> 340
    //   316: aload #7
    //   318: iload #18
    //   320: aload #5
    //   322: iload #6
    //   324: iload #18
    //   326: iadd
    //   327: iaload
    //   328: iastore
    //   329: iload_2
    //   330: ifne -> 395
    //   333: goto -> 340
    //   336: invokestatic a : (Ljava/lang/Throwable;)Ljava/lang/Throwable;
    //   339: athrow
    //   340: aload #7
    //   342: iload #18
    //   344: iconst_3
    //   345: isub
    //   346: iaload
    //   347: aload #7
    //   349: iload #18
    //   351: bipush #8
    //   353: isub
    //   354: iaload
    //   355: ixor
    //   356: aload #7
    //   358: iload #18
    //   360: bipush #14
    //   362: isub
    //   363: iaload
    //   364: ixor
    //   365: aload #7
    //   367: iload #18
    //   369: bipush #16
    //   371: isub
    //   372: iaload
    //   373: ixor
    //   374: istore #19
    //   376: iload #19
    //   378: iconst_1
    //   379: ishl
    //   380: iload #19
    //   382: bipush #31
    //   384: iushr
    //   385: ior
    //   386: istore #20
    //   388: aload #7
    //   390: iload #18
    //   392: iload #20
    //   394: iastore
    //   395: iload #8
    //   397: iconst_5
    //   398: ishl
    //   399: iload #8
    //   401: bipush #27
    //   403: iushr
    //   404: ior
    //   405: istore #19
    //   407: iload #19
    //   409: iload #12
    //   411: iadd
    //   412: aload #7
    //   414: iload #18
    //   416: iaload
    //   417: iadd
    //   418: iload #18
    //   420: bipush #20
    //   422: if_icmpge -> 448
    //   425: ldc 1518500249
    //   427: iload #9
    //   429: iload #10
    //   431: iand
    //   432: iload #9
    //   434: iconst_m1
    //   435: ixor
    //   436: iload #11
    //   438: iand
    //   439: ior
    //   440: iadd
    //   441: goto -> 518
    //   444: invokestatic a : (Ljava/lang/Throwable;)Ljava/lang/Throwable;
    //   447: athrow
    //   448: iload #18
    //   450: bipush #40
    //   452: if_icmpge -> 473
    //   455: ldc 1859775393
    //   457: iload #9
    //   459: iload #10
    //   461: ixor
    //   462: iload #11
    //   464: ixor
    //   465: iadd
    //   466: goto -> 518
    //   469: invokestatic a : (Ljava/lang/Throwable;)Ljava/lang/Throwable;
    //   472: athrow
    //   473: iload #18
    //   475: bipush #60
    //   477: if_icmpge -> 507
    //   480: ldc -1894007588
    //   482: iload #9
    //   484: iload #10
    //   486: iand
    //   487: iload #9
    //   489: iload #11
    //   491: iand
    //   492: ior
    //   493: iload #10
    //   495: iload #11
    //   497: iand
    //   498: ior
    //   499: iadd
    //   500: goto -> 518
    //   503: invokestatic a : (Ljava/lang/Throwable;)Ljava/lang/Throwable;
    //   506: athrow
    //   507: ldc -899497514
    //   509: iload #9
    //   511: iload #10
    //   513: ixor
    //   514: iload #11
    //   516: ixor
    //   517: iadd
    //   518: iadd
    //   519: istore #20
    //   521: iload #11
    //   523: istore #12
    //   525: iload #10
    //   527: istore #11
    //   529: iload #9
    //   531: bipush #30
    //   533: ishl
    //   534: iload #9
    //   536: iconst_2
    //   537: iushr
    //   538: ior
    //   539: istore #10
    //   541: iload #8
    //   543: istore #9
    //   545: iload #20
    //   547: istore #8
    //   549: iinc #18, 1
    //   552: iload_2
    //   553: ifne -> 302
    //   556: iload #8
    //   558: iload #13
    //   560: iadd
    //   561: istore #8
    //   563: iload #9
    //   565: iload #14
    //   567: iadd
    //   568: istore #9
    //   570: iload #10
    //   572: iload #15
    //   574: iadd
    //   575: istore #10
    //   577: iload #11
    //   579: iload #16
    //   581: iadd
    //   582: istore #11
    //   584: iload #12
    //   586: iload #17
    //   588: iadd
    //   589: istore #12
    //   591: iinc #6, 16
    //   594: iload_2
    //   595: ifne -> 271
    //   598: iconst_5
    //   599: newarray int
    //   601: dup
    //   602: iconst_0
    //   603: iload #8
    //   605: iastore
    //   606: dup
    //   607: iconst_1
    //   608: iload #9
    //   610: iastore
    //   611: dup
    //   612: iconst_2
    //   613: iload #10
    //   615: iastore
    //   616: dup
    //   617: iconst_3
    //   618: iload #11
    //   620: iastore
    //   621: dup
    //   622: iconst_4
    //   623: iload #12
    //   625: iastore
    //   626: astore #13
    //   628: bipush #20
    //   630: newarray byte
    //   632: astore #14
    //   634: iconst_0
    //   635: istore #15
    //   637: iload #15
    //   639: bipush #20
    //   641: if_icmpge -> 682
    //   644: aload #13
    //   646: iload #15
    //   648: iconst_4
    //   649: idiv
    //   650: iaload
    //   651: istore #16
    //   653: iconst_3
    //   654: iload #15
    //   656: iconst_4
    //   657: irem
    //   658: isub
    //   659: bipush #8
    //   661: imul
    //   662: istore #17
    //   664: aload #14
    //   666: iload #15
    //   668: iload #16
    //   670: iload #17
    //   672: iushr
    //   673: i2b
    //   674: bastore
    //   675: iinc #15, 1
    //   678: iload_2
    //   679: ifne -> 637
    //   682: aload #14
    //   684: astore #4
    //   686: new java/lang/StringBuilder
    //   689: dup
    //   690: invokespecial <init> : ()V
    //   693: astore_3
    //   694: iconst_0
    //   695: istore #4
    //   697: iload #4
    //   699: bipush #32
    //   701: if_icmpge -> 2035
    //   704: iload #4
    //   706: tableswitch default -> 2028, 0 -> 848, 1 -> 885, 2 -> 922, 3 -> 959, 4 -> 996, 5 -> 1033, 6 -> 1070, 7 -> 1107, 8 -> 1144, 9 -> 1181, 10 -> 1218, 11 -> 1255, 12 -> 1292, 13 -> 1329, 14 -> 1366, 15 -> 1403, 16 -> 1440, 17 -> 1477, 18 -> 1514, 19 -> 1551, 20 -> 1588, 21 -> 1625, 22 -> 1662, 23 -> 1699, 24 -> 1736, 25 -> 1773, 26 -> 1810, 27 -> 1847, 28 -> 1884, 29 -> 1921, 30 -> 1958, 31 -> 1995
    //   848: aload_3
    //   849: getstatic burp/Zl22.ZL : Ljava/lang/String;
    //   852: getstatic burp/Zsk2.ZD : Ljava/lang/Object;
    //   855: checkcast java/math/BigInteger
    //   858: invokevirtual intValue : ()I
    //   861: bipush #32
    //   863: irem
    //   864: invokestatic abs : (I)I
    //   867: invokevirtual charAt : (I)C
    //   870: invokevirtual append : (C)Ljava/lang/StringBuilder;
    //   873: pop
    //   874: iload_2
    //   875: ifne -> 2028
    //   878: goto -> 885
    //   881: invokestatic a : (Ljava/lang/Throwable;)Ljava/lang/Throwable;
    //   884: athrow
    //   885: aload_3
    //   886: getstatic burp/Zete.ZH : Ljava/lang/String;
    //   889: getstatic burp/Zryq.ZR : Ljava/lang/Object;
    //   892: checkcast java/math/BigInteger
    //   895: invokevirtual intValue : ()I
    //   898: bipush #32
    //   900: irem
    //   901: invokestatic abs : (I)I
    //   904: invokevirtual charAt : (I)C
    //   907: invokevirtual append : (C)Ljava/lang/StringBuilder;
    //   910: pop
    //   911: iload_2
    //   912: ifne -> 2028
    //   915: goto -> 922
    //   918: invokestatic a : (Ljava/lang/Throwable;)Ljava/lang/Throwable;
    //   921: athrow
    //   922: aload_3
    //   923: getstatic burp/Ztap.Zk : Ljava/lang/String;
    //   926: getstatic burp/Zkhy.Zc : Ljava/lang/Object;
    //   929: checkcast java/math/BigInteger
    //   932: invokevirtual intValue : ()I
    //   935: bipush #32
    //   937: irem
    //   938: invokestatic abs : (I)I
    //   941: invokevirtual charAt : (I)C
    //   944: invokevirtual append : (C)Ljava/lang/StringBuilder;
    //   947: pop
    //   948: iload_2
    //   949: ifne -> 2028
    //   952: goto -> 959
    //   955: invokestatic a : (Ljava/lang/Throwable;)Ljava/lang/Throwable;
    //   958: athrow
    //   959: aload_3
    //   960: getstatic burp/Zgj5.ZH : Ljava/lang/String;
    //   963: getstatic burp/Zttq.Zh : Ljava/lang/Object;
    //   966: checkcast java/math/BigInteger
    //   969: invokevirtual intValue : ()I
    //   972: bipush #32
    //   974: irem
    //   975: invokestatic abs : (I)I
    //   978: invokevirtual charAt : (I)C
    //   981: invokevirtual append : (C)Ljava/lang/StringBuilder;
    //   984: pop
    //   985: iload_2
    //   986: ifne -> 2028
    //   989: goto -> 996
    //   992: invokestatic a : (Ljava/lang/Throwable;)Ljava/lang/Throwable;
    //   995: athrow
    //   996: aload_3
    //   997: getstatic burp/Ztap.Zk : Ljava/lang/String;
    //   1000: getstatic burp/Zxdh.ZD : Ljava/lang/Object;
    //   1003: checkcast java/math/BigInteger
    //   1006: invokevirtual intValue : ()I
    //   1009: bipush #32
    //   1011: irem
    //   1012: invokestatic abs : (I)I
    //   1015: invokevirtual charAt : (I)C
    //   1018: invokevirtual append : (C)Ljava/lang/StringBuilder;
    //   1021: pop
    //   1022: iload_2
    //   1023: ifne -> 2028
    //   1026: goto -> 1033
    //   1029: invokestatic a : (Ljava/lang/Throwable;)Ljava/lang/Throwable;
    //   1032: athrow
    //   1033: aload_3
    //   1034: getstatic burp/Zzlg.Zw : Ljava/lang/String;
    //   1037: getstatic burp/Zeud.Zs : Ljava/lang/Object;
    //   1040: checkcast java/math/BigInteger
    //   1043: invokevirtual intValue : ()I
    //   1046: bipush #32
    //   1048: irem
    //   1049: invokestatic abs : (I)I
    //   1052: invokevirtual charAt : (I)C
    //   1055: invokevirtual append : (C)Ljava/lang/StringBuilder;
    //   1058: pop
    //   1059: iload_2
    //   1060: ifne -> 2028
    //   1063: goto -> 1070
    //   1066: invokestatic a : (Ljava/lang/Throwable;)Ljava/lang/Throwable;
    //   1069: athrow
    //   1070: aload_3
    //   1071: getstatic burp/Zblj.Za : Ljava/lang/String;
    //   1074: getstatic burp/Zkcd.ZE : Ljava/lang/Object;
    //   1077: checkcast java/math/BigInteger
    //   1080: invokevirtual intValue : ()I
    //   1083: bipush #32
    //   1085: irem
    //   1086: invokestatic abs : (I)I
    //   1089: invokevirtual charAt : (I)C
    //   1092: invokevirtual append : (C)Ljava/lang/StringBuilder;
    //   1095: pop
    //   1096: iload_2
    //   1097: ifne -> 2028
    //   1100: goto -> 1107
    //   1103: invokestatic a : (Ljava/lang/Throwable;)Ljava/lang/Throwable;
    //   1106: athrow
    //   1107: aload_3
    //   1108: getstatic burp/Zlpl.ZO : Ljava/lang/String;
    //   1111: getstatic burp/Zrj3.ZA : Ljava/lang/Object;
    //   1114: checkcast java/math/BigInteger
    //   1117: invokevirtual intValue : ()I
    //   1120: bipush #32
    //   1122: irem
    //   1123: invokestatic abs : (I)I
    //   1126: invokevirtual charAt : (I)C
    //   1129: invokevirtual append : (C)Ljava/lang/StringBuilder;
    //   1132: pop
    //   1133: iload_2
    //   1134: ifne -> 2028
    //   1137: goto -> 1144
    //   1140: invokestatic a : (Ljava/lang/Throwable;)Ljava/lang/Throwable;
    //   1143: athrow
    //   1144: aload_3
    //   1145: getstatic burp/Zeu2.ZK : Ljava/lang/String;
    //   1148: getstatic burp/Zrd0.Zs : Ljava/lang/Object;
    //   1151: checkcast java/math/BigInteger
    //   1154: invokevirtual intValue : ()I
    //   1157: bipush #32
    //   1159: irem
    //   1160: invokestatic abs : (I)I
    //   1163: invokevirtual charAt : (I)C
    //   1166: invokevirtual append : (C)Ljava/lang/StringBuilder;
    //   1169: pop
    //   1170: iload_2
    //   1171: ifne -> 2028
    //   1174: goto -> 1181
    //   1177: invokestatic a : (Ljava/lang/Throwable;)Ljava/lang/Throwable;
    //   1180: athrow
    //   1181: aload_3
    //   1182: getstatic burp/Ztev.Zp : Ljava/lang/String;
    //   1185: getstatic burp/Zgvf.Zd : Ljava/lang/Object;
    //   1188: checkcast java/math/BigInteger
    //   1191: invokevirtual intValue : ()I
    //   1194: bipush #32
    //   1196: irem
    //   1197: invokestatic abs : (I)I
    //   1200: invokevirtual charAt : (I)C
    //   1203: invokevirtual append : (C)Ljava/lang/StringBuilder;
    //   1206: pop
    //   1207: iload_2
    //   1208: ifne -> 2028
    //   1211: goto -> 1218
    //   1214: invokestatic a : (Ljava/lang/Throwable;)Ljava/lang/Throwable;
    //   1217: athrow
    //   1218: aload_3
    //   1219: getstatic burp/Zm84.Zd : Ljava/lang/String;
    //   1222: getstatic burp/Zz9v.Zl : Ljava/lang/Object;
    //   1225: checkcast java/math/BigInteger
    //   1228: invokevirtual intValue : ()I
    //   1231: bipush #32
    //   1233: irem
    //   1234: invokestatic abs : (I)I
    //   1237: invokevirtual charAt : (I)C
    //   1240: invokevirtual append : (C)Ljava/lang/StringBuilder;
    //   1243: pop
    //   1244: iload_2
    //   1245: ifne -> 2028
    //   1248: goto -> 1255
    //   1251: invokestatic a : (Ljava/lang/Throwable;)Ljava/lang/Throwable;
    //   1254: athrow
    //   1255: aload_3
    //   1256: getstatic burp/Zs9k.Zx : Ljava/lang/String;
    //   1259: getstatic burp/Zeno.Zo : Ljava/lang/Object;
    //   1262: checkcast java/math/BigInteger
    //   1265: invokevirtual intValue : ()I
    //   1268: bipush #32
    //   1270: irem
    //   1271: invokestatic abs : (I)I
    //   1274: invokevirtual charAt : (I)C
    //   1277: invokevirtual append : (C)Ljava/lang/StringBuilder;
    //   1280: pop
    //   1281: iload_2
    //   1282: ifne -> 2028
    //   1285: goto -> 1292
    //   1288: invokestatic a : (Ljava/lang/Throwable;)Ljava/lang/Throwable;
    //   1291: athrow
    //   1292: aload_3
    //   1293: getstatic burp/Zz3k.Zn : Ljava/lang/String;
    //   1296: getstatic burp/Zz9v.Zl : Ljava/lang/Object;
    //   1299: checkcast java/math/BigInteger
    //   1302: invokevirtual intValue : ()I
    //   1305: bipush #32
    //   1307: irem
    //   1308: invokestatic abs : (I)I
    //   1311: invokevirtual charAt : (I)C
    //   1314: invokevirtual append : (C)Ljava/lang/StringBuilder;
    //   1317: pop
    //   1318: iload_2
    //   1319: ifne -> 2028
    //   1322: goto -> 1329
    //   1325: invokestatic a : (Ljava/lang/Throwable;)Ljava/lang/Throwable;
    //   1328: athrow
    //   1329: aload_3
    //   1330: getstatic burp/Zzky.Zj : Ljava/lang/String;
    //   1333: getstatic burp/Zlhz.Zy : Ljava/lang/Object;
    //   1336: checkcast java/math/BigInteger
    //   1339: invokevirtual intValue : ()I
    //   1342: bipush #32
    //   1344: irem
    //   1345: invokestatic abs : (I)I
    //   1348: invokevirtual charAt : (I)C
    //   1351: invokevirtual append : (C)Ljava/lang/StringBuilder;
    //   1354: pop
    //   1355: iload_2
    //   1356: ifne -> 2028
    //   1359: goto -> 1366
    //   1362: invokestatic a : (Ljava/lang/Throwable;)Ljava/lang/Throwable;
    //   1365: athrow
    //   1366: aload_3
    //   1367: getstatic burp/Zrpx.ZM : Ljava/lang/String;
    //   1370: getstatic burp/Ztt0.ZF : Ljava/lang/Object;
    //   1373: checkcast java/math/BigInteger
    //   1376: invokevirtual intValue : ()I
    //   1379: bipush #32
    //   1381: irem
    //   1382: invokestatic abs : (I)I
    //   1385: invokevirtual charAt : (I)C
    //   1388: invokevirtual append : (C)Ljava/lang/StringBuilder;
    //   1391: pop
    //   1392: iload_2
    //   1393: ifne -> 2028
    //   1396: goto -> 1403
    //   1399: invokestatic a : (Ljava/lang/Throwable;)Ljava/lang/Throwable;
    //   1402: athrow
    //   1403: aload_3
    //   1404: getstatic burp/Zeu2.ZK : Ljava/lang/String;
    //   1407: getstatic burp/Zl22.ZJ : Ljava/lang/Object;
    //   1410: checkcast java/math/BigInteger
    //   1413: invokevirtual intValue : ()I
    //   1416: bipush #32
    //   1418: irem
    //   1419: invokestatic abs : (I)I
    //   1422: invokevirtual charAt : (I)C
    //   1425: invokevirtual append : (C)Ljava/lang/StringBuilder;
    //   1428: pop
    //   1429: iload_2
    //   1430: ifne -> 2028
    //   1433: goto -> 1440
    //   1436: invokestatic a : (Ljava/lang/Throwable;)Ljava/lang/Throwable;
    //   1439: athrow
    //   1440: aload_3
    //   1441: getstatic burp/Zete.ZH : Ljava/lang/String;
    //   1444: getstatic burp/Zgj5.ZO : Ljava/lang/Object;
    //   1447: checkcast java/math/BigInteger
    //   1450: invokevirtual intValue : ()I
    //   1453: bipush #32
    //   1455: irem
    //   1456: invokestatic abs : (I)I
    //   1459: invokevirtual charAt : (I)C
    //   1462: invokevirtual append : (C)Ljava/lang/StringBuilder;
    //   1465: pop
    //   1466: iload_2
    //   1467: ifne -> 2028
    //   1470: goto -> 1477
    //   1473: invokestatic a : (Ljava/lang/Throwable;)Ljava/lang/Throwable;
    //   1476: athrow
    //   1477: aload_3
    //   1478: getstatic burp/Zkk6.ZP : Ljava/lang/String;
    //   1481: getstatic burp/Zlzo.ZJ : Ljava/lang/Object;
    //   1484: checkcast java/math/BigInteger
    //   1487: invokevirtual intValue : ()I
    //   1490: bipush #32
    //   1492: irem
    //   1493: invokestatic abs : (I)I
    //   1496: invokevirtual charAt : (I)C
    //   1499: invokevirtual append : (C)Ljava/lang/StringBuilder;
    //   1502: pop
    //   1503: iload_2
    //   1504: ifne -> 2028
    //   1507: goto -> 1514
    //   1510: invokestatic a : (Ljava/lang/Throwable;)Ljava/lang/Throwable;
    //   1513: athrow
    //   1514: aload_3
    //   1515: getstatic burp/Zezq.Zp : Ljava/lang/String;
    //   1518: getstatic burp/Zrxm.ZL : Ljava/lang/Object;
    //   1521: checkcast java/math/BigInteger
    //   1524: invokevirtual intValue : ()I
    //   1527: bipush #32
    //   1529: irem
    //   1530: invokestatic abs : (I)I
    //   1533: invokevirtual charAt : (I)C
    //   1536: invokevirtual append : (C)Ljava/lang/StringBuilder;
    //   1539: pop
    //   1540: iload_2
    //   1541: ifne -> 2028
    //   1544: goto -> 1551
    //   1547: invokestatic a : (Ljava/lang/Throwable;)Ljava/lang/Throwable;
    //   1550: athrow
    //   1551: aload_3
    //   1552: getstatic burp/Zr_y.Zb : Ljava/lang/String;
    //   1555: getstatic burp/Zl3n.Zh : Ljava/lang/Object;
    //   1558: checkcast java/math/BigInteger
    //   1561: invokevirtual intValue : ()I
    //   1564: bipush #32
    //   1566: irem
    //   1567: invokestatic abs : (I)I
    //   1570: invokevirtual charAt : (I)C
    //   1573: invokevirtual append : (C)Ljava/lang/StringBuilder;
    //   1576: pop
    //   1577: iload_2
    //   1578: ifne -> 2028
    //   1581: goto -> 1588
    //   1584: invokestatic a : (Ljava/lang/Throwable;)Ljava/lang/Throwable;
    //   1587: athrow
    //   1588: aload_3
    //   1589: getstatic burp/Zz5d.Zb : Ljava/lang/String;
    //   1592: getstatic burp/Zzr.ZZ : Ljava/lang/Object;
    //   1595: checkcast java/math/BigInteger
    //   1598: invokevirtual intValue : ()I
    //   1601: bipush #32
    //   1603: irem
    //   1604: invokestatic abs : (I)I
    //   1607: invokevirtual charAt : (I)C
    //   1610: invokevirtual append : (C)Ljava/lang/StringBuilder;
    //   1613: pop
    //   1614: iload_2
    //   1615: ifne -> 2028
    //   1618: goto -> 1625
    //   1621: invokestatic a : (Ljava/lang/Throwable;)Ljava/lang/Throwable;
    //   1624: athrow
    //   1625: aload_3
    //   1626: getstatic burp/Zr0.ZH : Ljava/lang/String;
    //   1629: getstatic burp/Zlhz.Zy : Ljava/lang/Object;
    //   1632: checkcast java/math/BigInteger
    //   1635: invokevirtual intValue : ()I
    //   1638: bipush #32
    //   1640: irem
    //   1641: invokestatic abs : (I)I
    //   1644: invokevirtual charAt : (I)C
    //   1647: invokevirtual append : (C)Ljava/lang/StringBuilder;
    //   1650: pop
    //   1651: iload_2
    //   1652: ifne -> 2028
    //   1655: goto -> 1662
    //   1658: invokestatic a : (Ljava/lang/Throwable;)Ljava/lang/Throwable;
    //   1661: athrow
    //   1662: aload_3
    //   1663: getstatic burp/Zl22.ZL : Ljava/lang/String;
    //   1666: getstatic burp/Zldx.ZM : Ljava/lang/Object;
    //   1669: checkcast java/math/BigInteger
    //   1672: invokevirtual intValue : ()I
    //   1675: bipush #32
    //   1677: irem
    //   1678: invokestatic abs : (I)I
    //   1681: invokevirtual charAt : (I)C
    //   1684: invokevirtual append : (C)Ljava/lang/StringBuilder;
    //   1687: pop
    //   1688: iload_2
    //   1689: ifne -> 2028
    //   1692: goto -> 1699
    //   1695: invokestatic a : (Ljava/lang/Throwable;)Ljava/lang/Throwable;
    //   1698: athrow
    //   1699: aload_3
    //   1700: getstatic burp/Zmh5.Zh : Ljava/lang/String;
    //   1703: getstatic burp/Zsk2.ZD : Ljava/lang/Object;
    //   1706: checkcast java/math/BigInteger
    //   1709: invokevirtual intValue : ()I
    //   1712: bipush #32
    //   1714: irem
    //   1715: invokestatic abs : (I)I
    //   1718: invokevirtual charAt : (I)C
    //   1721: invokevirtual append : (C)Ljava/lang/StringBuilder;
    //   1724: pop
    //   1725: iload_2
    //   1726: ifne -> 2028
    //   1729: goto -> 1736
    //   1732: invokestatic a : (Ljava/lang/Throwable;)Ljava/lang/Throwable;
    //   1735: athrow
    //   1736: aload_3
    //   1737: getstatic burp/Zepm.Zl : Ljava/lang/String;
    //   1740: getstatic burp/Zlzo.ZJ : Ljava/lang/Object;
    //   1743: checkcast java/math/BigInteger
    //   1746: invokevirtual intValue : ()I
    //   1749: bipush #32
    //   1751: irem
    //   1752: invokestatic abs : (I)I
    //   1755: invokevirtual charAt : (I)C
    //   1758: invokevirtual append : (C)Ljava/lang/StringBuilder;
    //   1761: pop
    //   1762: iload_2
    //   1763: ifne -> 2028
    //   1766: goto -> 1773
    //   1769: invokestatic a : (Ljava/lang/Throwable;)Ljava/lang/Throwable;
    //   1772: athrow
    //   1773: aload_3
    //   1774: getstatic burp/Zzky.Zj : Ljava/lang/String;
    //   1777: getstatic burp/Zrxm.ZL : Ljava/lang/Object;
    //   1780: checkcast java/math/BigInteger
    //   1783: invokevirtual intValue : ()I
    //   1786: bipush #32
    //   1788: irem
    //   1789: invokestatic abs : (I)I
    //   1792: invokevirtual charAt : (I)C
    //   1795: invokevirtual append : (C)Ljava/lang/StringBuilder;
    //   1798: pop
    //   1799: iload_2
    //   1800: ifne -> 2028
    //   1803: goto -> 1810
    //   1806: invokestatic a : (Ljava/lang/Throwable;)Ljava/lang/Throwable;
    //   1809: athrow
    //   1810: aload_3
    //   1811: getstatic burp/Zldx.Zm : Ljava/lang/String;
    //   1814: getstatic burp/Ze_b.Zp : Ljava/lang/Object;
    //   1817: checkcast java/math/BigInteger
    //   1820: invokevirtual intValue : ()I
    //   1823: bipush #32
    //   1825: irem
    //   1826: invokestatic abs : (I)I
    //   1829: invokevirtual charAt : (I)C
    //   1832: invokevirtual append : (C)Ljava/lang/StringBuilder;
    //   1835: pop
    //   1836: iload_2
    //   1837: ifne -> 2028
    //   1840: goto -> 1847
    //   1843: invokestatic a : (Ljava/lang/Throwable;)Ljava/lang/Throwable;
    //   1846: athrow
    //   1847: aload_3
    //   1848: getstatic burp/Zkdc.Zc : Ljava/lang/String;
    //   1851: getstatic burp/Zrpx.Zi : Ljava/lang/Object;
    //   1854: checkcast java/math/BigInteger
    //   1857: invokevirtual intValue : ()I
    //   1860: bipush #32
    //   1862: irem
    //   1863: invokestatic abs : (I)I
    //   1866: invokevirtual charAt : (I)C
    //   1869: invokevirtual append : (C)Ljava/lang/StringBuilder;
    //   1872: pop
    //   1873: iload_2
    //   1874: ifne -> 2028
    //   1877: goto -> 1884
    //   1880: invokestatic a : (Ljava/lang/Throwable;)Ljava/lang/Throwable;
    //   1883: athrow
    //   1884: aload_3
    //   1885: getstatic burp/Ztev.Zp : Ljava/lang/String;
    //   1888: getstatic burp/Zeud.Zs : Ljava/lang/Object;
    //   1891: checkcast java/math/BigInteger
    //   1894: invokevirtual intValue : ()I
    //   1897: bipush #32
    //   1899: irem
    //   1900: invokestatic abs : (I)I
    //   1903: invokevirtual charAt : (I)C
    //   1906: invokevirtual append : (C)Ljava/lang/StringBuilder;
    //   1909: pop
    //   1910: iload_2
    //   1911: ifne -> 2028
    //   1914: goto -> 1921
    //   1917: invokestatic a : (Ljava/lang/Throwable;)Ljava/lang/Throwable;
    //   1920: athrow
    //   1921: aload_3
    //   1922: getstatic burp/Zmnb.ZD : Ljava/lang/String;
    //   1925: getstatic burp/Zkcd.ZE : Ljava/lang/Object;
    //   1928: checkcast java/math/BigInteger
    //   1931: invokevirtual intValue : ()I
    //   1934: bipush #32
    //   1936: irem
    //   1937: invokestatic abs : (I)I
    //   1940: invokevirtual charAt : (I)C
    //   1943: invokevirtual append : (C)Ljava/lang/StringBuilder;
    //   1946: pop
    //   1947: iload_2
    //   1948: ifne -> 2028
    //   1951: goto -> 1958
    //   1954: invokestatic a : (Ljava/lang/Throwable;)Ljava/lang/Throwable;
    //   1957: athrow
    //   1958: aload_3
    //   1959: getstatic burp/Zb29.Zf : Ljava/lang/String;
    //   1962: getstatic burp/Zttq.Zh : Ljava/lang/Object;
    //   1965: checkcast java/math/BigInteger
    //   1968: invokevirtual intValue : ()I
    //   1971: bipush #32
    //   1973: irem
    //   1974: invokestatic abs : (I)I
    //   1977: invokevirtual charAt : (I)C
    //   1980: invokevirtual append : (C)Ljava/lang/StringBuilder;
    //   1983: pop
    //   1984: iload_2
    //   1985: ifne -> 2028
    //   1988: goto -> 1995
    //   1991: invokestatic a : (Ljava/lang/Throwable;)Ljava/lang/Throwable;
    //   1994: athrow
    //   1995: aload_3
    //   1996: getstatic burp/Zrd0.Zk : Ljava/lang/String;
    //   1999: getstatic burp/Zrj3.ZA : Ljava/lang/Object;
    //   2002: checkcast java/math/BigInteger
    //   2005: invokevirtual intValue : ()I
    //   2008: bipush #32
    //   2010: irem
    //   2011: invokestatic abs : (I)I
    //   2014: invokevirtual charAt : (I)C
    //   2017: invokevirtual append : (C)Ljava/lang/StringBuilder;
    //   2020: pop
    //   2021: goto -> 2028
    //   2024: invokestatic a : (Ljava/lang/Throwable;)Ljava/lang/Throwable;
    //   2027: athrow
    //   2028: iinc #4, 1
    //   2031: iload_2
    //   2032: ifne -> 697
    //   2035: aload_3
    //   2036: invokevirtual toString : ()Ljava/lang/String;
    //   2039: putstatic burp/Zkaw.ZI : Ljava/lang/String;
    //   2042: sipush #27911
    //   2045: getstatic burp/Zzky.Zo : Ljava/lang/Object;
    //   2048: checkcast java/math/BigInteger
    //   2051: getstatic burp/Zz3k.Zz : Ljava/lang/Object;
    //   2054: checkcast java/math/BigInteger
    //   2057: invokevirtual subtract : (Ljava/math/BigInteger;)Ljava/math/BigInteger;
    //   2060: putstatic burp/Zm84.Zf : Ljava/lang/Object;
    //   2063: sipush #-15632
    //   2066: invokestatic a : (II)Ljava/lang/String;
    //   2069: iconst_1
    //   2070: ldc burp/Zm4k
    //   2072: invokevirtual getClassLoader : ()Ljava/lang/ClassLoader;
    //   2075: invokestatic forName : (Ljava/lang/String;ZLjava/lang/ClassLoader;)Ljava/lang/Class;
    //   2078: invokevirtual getDeclaredFields : ()[Ljava/lang/reflect/Field;
    //   2081: astore #4
    //   2083: aload #4
    //   2085: arraylength
    //   2086: istore #5
    //   2088: iconst_0
    //   2089: istore #6
    //   2091: iload #6
    //   2093: iload #5
    //   2095: if_icmpge -> 2232
    //   2098: aload #4
    //   2100: iload #6
    //   2102: aaload
    //   2103: astore #7
    //   2105: aload #7
    //   2107: invokevirtual getModifiers : ()I
    //   2110: invokestatic isStatic : (I)Z
    //   2113: ifne -> 2123
    //   2116: goto -> 2225
    //   2119: invokestatic a : (Ljava/lang/Throwable;)Ljava/lang/Throwable;
    //   2122: athrow
    //   2123: aload #7
    //   2125: invokevirtual getType : ()Ljava/lang/Class;
    //   2128: astore #8
    //   2130: aload #8
    //   2132: ifnull -> 2212
    //   2135: aload #8
    //   2137: invokevirtual isPrimitive : ()Z
    //   2140: ifne -> 2212
    //   2143: goto -> 2150
    //   2146: invokestatic a : (Ljava/lang/Throwable;)Ljava/lang/Throwable;
    //   2149: athrow
    //   2150: aload #8
    //   2152: invokevirtual getPackage : ()Ljava/lang/Package;
    //   2155: ifnull -> 2212
    //   2158: goto -> 2165
    //   2161: invokestatic a : (Ljava/lang/Throwable;)Ljava/lang/Throwable;
    //   2164: athrow
    //   2165: aload #8
    //   2167: invokevirtual getPackage : ()Ljava/lang/Package;
    //   2170: invokevirtual getName : ()Ljava/lang/String;
    //   2173: ifnull -> 2212
    //   2176: goto -> 2183
    //   2179: invokestatic a : (Ljava/lang/Throwable;)Ljava/lang/Throwable;
    //   2182: athrow
    //   2183: aload #8
    //   2185: invokevirtual getPackage : ()Ljava/lang/Package;
    //   2188: invokevirtual getName : ()Ljava/lang/String;
    //   2191: sipush #27915
    //   2194: bipush #-87
    //   2196: invokestatic a : (II)Ljava/lang/String;
    //   2199: invokevirtual startsWith : (Ljava/lang/String;)Z
    //   2202: ifne -> 2212
    //   2205: goto -> 2212
    //   2208: invokestatic a : (Ljava/lang/Throwable;)Ljava/lang/Throwable;
    //   2211: athrow
    //   2212: aload #7
    //   2214: iconst_1
    //   2215: invokevirtual setAccessible : (Z)V
    //   2218: aload #7
    //   2220: aconst_null
    //   2221: invokevirtual get : (Ljava/lang/Object;)Ljava/lang/Object;
    //   2224: pop
    //   2225: iinc #6, 1
    //   2228: iload_2
    //   2229: ifne -> 2091
    //   2232: sipush #27909
    //   2235: sipush #-31886
    //   2238: invokestatic a : (II)Ljava/lang/String;
    //   2241: invokestatic forName : (Ljava/lang/String;)Ljava/lang/Class;
    //   2244: invokevirtual getDeclaredMethods : ()[Ljava/lang/reflect/Method;
    //   2247: astore #4
    //   2249: aload #4
    //   2251: arraylength
    //   2252: istore #5
    //   2254: iconst_0
    //   2255: istore #6
    //   2257: iload #6
    //   2259: iload #5
    //   2261: if_icmpge -> 2394
    //   2264: aload #4
    //   2266: iload #6
    //   2268: aaload
    //   2269: astore #7
    //   2271: aload #7
    //   2273: invokevirtual getParameterTypes : ()[Ljava/lang/Class;
    //   2276: pop
    //   2277: aload #7
    //   2279: invokevirtual getModifiers : ()I
    //   2282: invokestatic isStatic : (I)Z
    //   2285: ifeq -> 2380
    //   2288: aload #7
    //   2290: invokevirtual getParameterTypes : ()[Ljava/lang/Class;
    //   2293: arraylength
    //   2294: iconst_2
    //   2295: if_icmpne -> 2380
    //   2298: goto -> 2305
    //   2301: invokestatic a : (Ljava/lang/Throwable;)Ljava/lang/Throwable;
    //   2304: athrow
    //   2305: aload #7
    //   2307: invokevirtual getReturnType : ()Ljava/lang/Class;
    //   2310: getstatic java/lang/Void.TYPE : Ljava/lang/Class;
    //   2313: invokevirtual equals : (Ljava/lang/Object;)Z
    //   2316: ifeq -> 2380
    //   2319: goto -> 2326
    //   2322: invokestatic a : (Ljava/lang/Throwable;)Ljava/lang/Throwable;
    //   2325: athrow
    //   2326: aload #7
    //   2328: iconst_1
    //   2329: invokevirtual setAccessible : (Z)V
    //   2332: aload #7
    //   2334: aconst_null
    //   2335: iconst_2
    //   2336: anewarray java/lang/Object
    //   2339: dup
    //   2340: iconst_0
    //   2341: aload_0
    //   2342: aastore
    //   2343: dup
    //   2344: iconst_1
    //   2345: aload_1
    //   2346: ifnonnull -> 2364
    //   2349: goto -> 2356
    //   2352: invokestatic a : (Ljava/lang/Throwable;)Ljava/lang/Throwable;
    //   2355: athrow
    //   2356: aload_1
    //   2357: goto -> 2371
    //   2360: invokestatic a : (Ljava/lang/Throwable;)Ljava/lang/Throwable;
    //   2363: athrow
    //   2364: aload_1
    //   2365: checkcast [B
    //   2368: invokevirtual clone : ()Ljava/lang/Object;
    //   2371: aastore
    //   2372: invokevirtual invoke : (Ljava/lang/Object;[Ljava/lang/Object;)Ljava/lang/Object;
    //   2375: pop
    //   2376: iload_2
    //   2377: ifne -> 2394
    //   2380: iinc #6, 1
    //   2383: iload_2
    //   2384: ifne -> 2257
    //   2387: goto -> 2394
    //   2390: invokestatic a : (Ljava/lang/Throwable;)Ljava/lang/Throwable;
    //   2393: athrow
    //   2394: new java/io/ByteArrayOutputStream
    //   2397: dup
    //   2398: invokespecial <init> : ()V
    //   2401: astore #4
    //   2403: sipush #27919
    //   2406: aload #4
    //   2408: sipush #202
    //   2411: invokevirtual write : (I)V
    //   2414: sipush #-8777
    //   2417: aload #4
    //   2419: sipush #254
    //   2422: invokevirtual write : (I)V
    //   2425: aload #4
    //   2427: sipush #186
    //   2430: invokevirtual write : (I)V
    //   2433: aload #4
    //   2435: sipush #190
    //   2438: invokevirtual write : (I)V
    //   2441: aload #4
    //   2443: iconst_0
    //   2444: invokevirtual write : (I)V
    //   2447: aload #4
    //   2449: iconst_1
    //   2450: invokevirtual write : (I)V
    //   2453: aload #4
    //   2455: iconst_0
    //   2456: invokevirtual write : (I)V
    //   2459: aload #4
    //   2461: bipush #50
    //   2463: invokevirtual write : (I)V
    //   2466: aload #4
    //   2468: getstatic burp/Zs15.Zk : Ljava/lang/Object;
    //   2471: checkcast java/math/BigInteger
    //   2474: invokevirtual toByteArray : ()[B
    //   2477: invokevirtual write : ([B)V
    //   2480: aload #4
    //   2482: getstatic burp/Zsdn.ZE : Ljava/lang/Object;
    //   2485: checkcast java/math/BigInteger
    //   2488: invokevirtual toByteArray : ()[B
    //   2491: invokevirtual write : ([B)V
    //   2494: aload #4
    //   2496: getstatic burp/Zkff.Zr : Ljava/lang/Object;
    //   2499: checkcast java/math/BigInteger
    //   2502: invokevirtual toByteArray : ()[B
    //   2505: invokevirtual write : ([B)V
    //   2508: aload #4
    //   2510: invokevirtual toByteArray : ()[B
    //   2513: astore #5
    //   2515: aconst_null
    //   2516: astore #6
    //   2518: invokestatic a : (II)Ljava/lang/String;
    //   2521: invokestatic forName : (Ljava/lang/String;)Ljava/lang/Class;
    //   2524: invokevirtual getDeclaredMethods : ()[Ljava/lang/reflect/Method;
    //   2527: astore #7
    //   2529: aload #7
    //   2531: arraylength
    //   2532: istore #8
    //   2534: iconst_0
    //   2535: istore #9
    //   2537: iload #9
    //   2539: iload #8
    //   2541: if_icmpge -> 2669
    //   2544: aload #7
    //   2546: iload #9
    //   2548: aaload
    //   2549: astore #10
    //   2551: aload #10
    //   2553: invokevirtual getName : ()Ljava/lang/String;
    //   2556: sipush #27916
    //   2559: sipush #3994
    //   2562: invokestatic a : (II)Ljava/lang/String;
    //   2565: invokevirtual equals : (Ljava/lang/Object;)Z
    //   2568: ifeq -> 2662
    //   2571: aload #10
    //   2573: invokevirtual getParameterTypes : ()[Ljava/lang/Class;
    //   2576: astore #11
    //   2578: aload #11
    //   2580: arraylength
    //   2581: iconst_4
    //   2582: if_icmpeq -> 2592
    //   2585: goto -> 2662
    //   2588: invokestatic a : (Ljava/lang/Throwable;)Ljava/lang/Throwable;
    //   2591: athrow
    //   2592: aload #11
    //   2594: iconst_0
    //   2595: aaload
    //   2596: ldc java/lang/String
    //   2598: if_acmpeq -> 2608
    //   2601: goto -> 2662
    //   2604: invokestatic a : (Ljava/lang/Throwable;)Ljava/lang/Throwable;
    //   2607: athrow
    //   2608: aload #11
    //   2610: iconst_1
    //   2611: aaload
    //   2612: ldc [B
    //   2614: if_acmpeq -> 2624
    //   2617: goto -> 2662
    //   2620: invokestatic a : (Ljava/lang/Throwable;)Ljava/lang/Throwable;
    //   2623: athrow
    //   2624: aload #11
    //   2626: iconst_2
    //   2627: aaload
    //   2628: getstatic java/lang/Integer.TYPE : Ljava/lang/Class;
    //   2631: if_acmpeq -> 2641
    //   2634: goto -> 2662
    //   2637: invokestatic a : (Ljava/lang/Throwable;)Ljava/lang/Throwable;
    //   2640: athrow
    //   2641: aload #11
    //   2643: iconst_3
    //   2644: aaload
    //   2645: getstatic java/lang/Integer.TYPE : Ljava/lang/Class;
    //   2648: if_acmpeq -> 2658
    //   2651: goto -> 2662
    //   2654: invokestatic a : (Ljava/lang/Throwable;)Ljava/lang/Throwable;
    //   2657: athrow
    //   2658: aload #10
    //   2660: astore #6
    //   2662: iinc #9, 1
    //   2665: iload_2
    //   2666: ifne -> 2537
    //   2669: aload #6
    //   2671: iconst_1
    //   2672: invokevirtual setAccessible : (Z)V
    //   2675: ldc burp/Znp
    //   2677: iconst_0
    //   2678: anewarray java/lang/Class
    //   2681: invokevirtual getDeclaredConstructor : ([Ljava/lang/Class;)Ljava/lang/reflect/Constructor;
    //   2684: astore #7
    //   2686: aload #7
    //   2688: iconst_1
    //   2689: invokevirtual setAccessible : (Z)V
    //   2692: aload #6
    //   2694: aload #7
    //   2696: iconst_0
    //   2697: anewarray java/lang/Object
    //   2700: invokevirtual newInstance : ([Ljava/lang/Object;)Ljava/lang/Object;
    //   2703: iconst_4
    //   2704: anewarray java/lang/Object
    //   2707: dup
    //   2708: iconst_0
    //   2709: sipush #27906
    //   2712: sipush #-19411
    //   2715: invokestatic a : (II)Ljava/lang/String;
    //   2718: aastore
    //   2719: dup
    //   2720: iconst_1
    //   2721: aload #5
    //   2723: aastore
    //   2724: dup
    //   2725: iconst_2
    //   2726: iconst_0
    //   2727: invokestatic valueOf : (I)Ljava/lang/Integer;
    //   2730: aastore
    //   2731: dup
    //   2732: iconst_3
    //   2733: aload #5
    //   2735: arraylength
    //   2736: invokestatic valueOf : (I)Ljava/lang/Integer;
    //   2739: aastore
    //   2740: invokevirtual invoke : (Ljava/lang/Object;[Ljava/lang/Object;)Ljava/lang/Object;
    //   2743: pop
    //   2744: goto -> 2749
    //   2747: astore #4
    //   2749: getstatic burp/Zz5d.Zb : Ljava/lang/String;
    //   2752: getstatic burp/Ztt0.ZF : Ljava/lang/Object;
    //   2755: checkcast java/math/BigInteger
    //   2758: invokevirtual intValue : ()I
    //   2761: bipush #32
    //   2763: irem
    //   2764: invokestatic abs : (I)I
    //   2767: invokevirtual charAt : (I)C
    //   2770: getstatic burp/Zz3k.Zn : Ljava/lang/String;
    //   2773: getstatic burp/Zzr.ZZ : Ljava/lang/Object;
    //   2776: checkcast java/math/BigInteger
    //   2779: invokevirtual intValue : ()I
    //   2782: bipush #32
    //   2784: irem
    //   2785: invokestatic abs : (I)I
    //   2788: invokevirtual charAt : (I)C
    //   2791: if_icmple -> 2906
    //   2794: getstatic burp/Ztdt.Zk : Ljava/lang/String;
    //   2797: getstatic burp/Zero.ZE : Ljava/lang/Object;
    //   2800: checkcast java/math/BigInteger
    //   2803: invokevirtual intValue : ()I
    //   2806: bipush #32
    //   2808: irem
    //   2809: invokestatic abs : (I)I
    //   2812: invokevirtual charAt : (I)C
    //   2815: getstatic burp/Zete.ZH : Ljava/lang/String;
    //   2818: getstatic burp/Zkcd.ZE : Ljava/lang/Object;
    //   2821: checkcast java/math/BigInteger
    //   2824: invokevirtual intValue : ()I
    //   2827: bipush #32
    //   2829: irem
    //   2830: invokestatic abs : (I)I
    //   2833: invokevirtual charAt : (I)C
    //   2836: if_icmpgt -> 2906
    //   2839: goto -> 2846
    //   2842: invokestatic a : (Ljava/lang/Throwable;)Ljava/lang/Throwable;
    //   2845: athrow
    //   2846: getstatic burp/Zepm.Zl : Ljava/lang/String;
    //   2849: getstatic burp/Zsun.ZP : Ljava/lang/Object;
    //   2852: checkcast java/math/BigInteger
    //   2855: invokevirtual intValue : ()I
    //   2858: bipush #32
    //   2860: irem
    //   2861: invokestatic abs : (I)I
    //   2864: invokevirtual charAt : (I)C
    //   2867: getstatic burp/Zeno.ZL : Ljava/lang/String;
    //   2870: getstatic burp/Zgyk.ZO : Ljava/lang/Object;
    //   2873: checkcast java/math/BigInteger
    //   2876: invokevirtual intValue : ()I
    //   2879: bipush #32
    //   2881: irem
    //   2882: invokestatic abs : (I)I
    //   2885: invokevirtual charAt : (I)C
    //   2888: if_icmpgt -> 2906
    //   2891: goto -> 2898
    //   2894: invokestatic a : (Ljava/lang/Throwable;)Ljava/lang/Throwable;
    //   2897: athrow
    //   2898: iconst_1
    //   2899: goto -> 2907
    //   2902: invokestatic a : (Ljava/lang/Throwable;)Ljava/lang/Throwable;
    //   2905: athrow
    //   2906: iconst_0
    //   2907: ireturn
    //   2908: astore_3
    //   2909: new java/lang/Exception
    //   2912: dup
    //   2913: aload_3
    //   2914: invokevirtual getMessage : ()Ljava/lang/String;
    //   2917: invokespecial <init> : (Ljava/lang/String;)V
    //   2920: athrow
    // Exception table:
    //   from	to	target	type
    //   4	2907	2908	java/lang/Throwable
    //   309	333	336	java/lang/Throwable
    //   407	444	444	java/lang/Throwable
    //   448	469	469	java/lang/Throwable
    //   473	503	503	java/lang/Throwable
    //   704	878	881	java/lang/Throwable
    //   848	915	918	java/lang/Throwable
    //   885	952	955	java/lang/Throwable
    //   922	989	992	java/lang/Throwable
    //   959	1026	1029	java/lang/Throwable
    //   996	1063	1066	java/lang/Throwable
    //   1033	1100	1103	java/lang/Throwable
    //   1070	1137	1140	java/lang/Throwable
    //   1107	1174	1177	java/lang/Throwable
    //   1144	1211	1214	java/lang/Throwable
    //   1181	1248	1251	java/lang/Throwable
    //   1218	1285	1288	java/lang/Throwable
    //   1255	1322	1325	java/lang/Throwable
    //   1292	1359	1362	java/lang/Throwable
    //   1329	1396	1399	java/lang/Throwable
    //   1366	1433	1436	java/lang/Throwable
    //   1403	1470	1473	java/lang/Throwable
    //   1440	1507	1510	java/lang/Throwable
    //   1477	1544	1547	java/lang/Throwable
    //   1514	1581	1584	java/lang/Throwable
    //   1551	1618	1621	java/lang/Throwable
    //   1588	1655	1658	java/lang/Throwable
    //   1625	1692	1695	java/lang/Throwable
    //   1662	1729	1732	java/lang/Throwable
    //   1699	1766	1769	java/lang/Throwable
    //   1736	1803	1806	java/lang/Throwable
    //   1773	1840	1843	java/lang/Throwable
    //   1810	1877	1880	java/lang/Throwable
    //   1847	1914	1917	java/lang/Throwable
    //   1884	1951	1954	java/lang/Throwable
    //   1921	1988	1991	java/lang/Throwable
    //   1958	2021	2024	java/lang/Throwable
    //   2105	2119	2119	java/lang/Throwable
    //   2130	2143	2146	java/lang/Throwable
    //   2135	2158	2161	java/lang/Throwable
    //   2150	2176	2179	java/lang/Throwable
    //   2165	2205	2208	java/lang/Throwable
    //   2271	2298	2301	java/lang/Throwable
    //   2288	2319	2322	java/lang/Throwable
    //   2305	2349	2352	java/lang/Throwable
    //   2326	2360	2360	java/lang/Throwable
    //   2371	2387	2390	java/lang/Throwable
    //   2394	2744	2747	java/lang/Throwable
    //   2578	2588	2588	java/lang/Throwable
    //   2592	2604	2604	java/lang/Throwable
    //   2608	2620	2620	java/lang/Throwable
    //   2624	2637	2637	java/lang/Throwable
    //   2641	2654	2654	java/lang/Throwable
    //   2749	2839	2842	java/lang/Throwable
    //   2794	2891	2894	java/lang/Throwable
    //   2846	2902	2902	java/lang/Throwable
  }
  
  static {
    // Byte code:
    //   0: bipush #14
    //   2: anewarray java/lang/String
    //   5: astore #5
    //   7: iconst_0
    //   8: istore_3
    //   9: ldc 'AP%e9'\\tM<NaCYF/\w\FJ//n343\Ic.!L\\nw1\\ti)ilO\\t\\nat]\\tr# Wh9$T"Up.1)M\\t\\tx MDd\\tk\\r\\tAv \\tA:|FT:_{'
    //   11: dup
    //   12: astore_2
    //   13: invokevirtual length : ()I
    //   16: istore #4
    //   18: bipush #21
    //   20: istore_1
    //   21: iconst_m1
    //   22: istore_0
    //   23: bipush #118
    //   25: iinc #0, 1
    //   28: aload_2
    //   29: iload_0
    //   30: dup
    //   31: iload_1
    //   32: iadd
    //   33: invokevirtual substring : (II)Ljava/lang/String;
    //   36: iconst_m1
    //   37: goto -> 143
    //   40: aload #5
    //   42: swap
    //   43: iload_3
    //   44: iinc #3, 1
    //   47: swap
    //   48: aastore
    //   49: iload_0
    //   50: iload_1
    //   51: iadd
    //   52: dup
    //   53: istore_0
    //   54: iload #4
    //   56: if_icmpge -> 68
    //   59: aload_2
    //   60: iload_0
    //   61: invokevirtual charAt : (I)C
    //   64: istore_1
    //   65: goto -> 23
    //   68: ldc 'vJ08L`6}Q@m]|!\\bh:j'
    //   70: dup
    //   71: astore_2
    //   72: invokevirtual length : ()I
    //   75: istore #4
    //   77: bipush #32
    //   79: istore_1
    //   80: iconst_m1
    //   81: istore_0
    //   82: bipush #98
    //   84: iinc #0, 1
    //   87: aload_2
    //   88: iload_0
    //   89: dup
    //   90: iload_1
    //   91: iadd
    //   92: invokevirtual substring : (II)Ljava/lang/String;
    //   95: iconst_0
    //   96: goto -> 143
    //   99: aload #5
    //   101: swap
    //   102: iload_3
    //   103: iinc #3, 1
    //   106: swap
    //   107: aastore
    //   108: iload_0
    //   109: iload_1
    //   110: iadd
    //   111: dup
    //   112: istore_0
    //   113: iload #4
    //   115: if_icmpge -> 127
    //   118: aload_2
    //   119: iload_0
    //   120: invokevirtual charAt : (I)C
    //   123: istore_1
    //   124: goto -> 82
    //   127: aload #5
    //   129: putstatic burp/Zezn.a : [Ljava/lang/String;
    //   132: bipush #14
    //   134: anewarray java/lang/String
    //   137: putstatic burp/Zezn.b : [Ljava/lang/String;
    //   140: goto -> 300
    //   143: dup_x2
    //   144: pop
    //   145: invokevirtual toCharArray : ()[C
    //   148: dup_x1
    //   149: arraylength
    //   150: dup_x2
    //   151: pop
    //   152: iconst_0
    //   153: istore #6
    //   155: dup2_x1
    //   156: pop2
    //   157: dup_x2
    //   158: iconst_1
    //   159: if_icmpgt -> 260
    //   162: dup2
    //   163: swap
    //   164: iload #6
    //   166: dup2_x1
    //   167: caload
    //   168: swap
    //   169: iload #6
    //   171: bipush #7
    //   173: irem
    //   174: tableswitch default -> 242, 0 -> 212, 1 -> 217, 2 -> 222, 3 -> 227, 4 -> 232, 5 -> 237
    //   212: bipush #99
    //   214: goto -> 244
    //   217: bipush #35
    //   219: goto -> 244
    //   222: bipush #92
    //   224: goto -> 244
    //   227: bipush #66
    //   229: goto -> 244
    //   232: bipush #31
    //   234: goto -> 244
    //   237: bipush #7
    //   239: goto -> 244
    //   242: bipush #100
    //   244: ixor
    //   245: ixor
    //   246: i2c
    //   247: castore
    //   248: iinc #6, 1
    //   251: dup
    //   252: ifne -> 260
    //   255: dup2
    //   256: dup_x1
    //   257: goto -> 166
    //   260: dup2_x1
    //   261: pop2
    //   262: dup_x2
    //   263: iload #6
    //   265: if_icmpgt -> 162
    //   268: pop
    //   269: new java/lang/String
    //   272: dup_x1
    //   273: swap
    //   274: invokespecial <init> : ([C)V
    //   277: invokevirtual intern : ()Ljava/lang/String;
    //   280: swap
    //   281: pop
    //   282: swap
    //   283: tableswitch default -> 40, 0 -> 99
    //   300: sipush #27908
    //   303: sipush #10711
    //   306: invokestatic a : (II)Ljava/lang/String;
    //   309: putstatic burp/Zezn.Ze : Ljava/lang/String;
    //   312: new java/math/BigInteger
    //   315: dup
    //   316: iconst_1
    //   317: bipush #32
    //   319: newarray byte
    //   321: dup
    //   322: iconst_0
    //   323: bipush #15
    //   325: bastore
    //   326: dup
    //   327: iconst_1
    //   328: bipush #-56
    //   330: bastore
    //   331: dup
    //   332: iconst_2
    //   333: bipush #-113
    //   335: bastore
    //   336: dup
    //   337: iconst_3
    //   338: bipush #56
    //   340: bastore
    //   341: dup
    //   342: iconst_4
    //   343: bipush #-70
    //   345: bastore
    //   346: dup
    //   347: iconst_5
    //   348: bipush #-28
    //   350: bastore
    //   351: dup
    //   352: bipush #6
    //   354: bipush #57
    //   356: bastore
    //   357: dup
    //   358: bipush #7
    //   360: bipush #-115
    //   362: bastore
    //   363: dup
    //   364: bipush #8
    //   366: bipush #18
    //   368: bastore
    //   369: dup
    //   370: bipush #9
    //   372: bipush #-26
    //   374: bastore
    //   375: dup
    //   376: bipush #10
    //   378: bipush #124
    //   380: bastore
    //   381: dup
    //   382: bipush #11
    //   384: bipush #111
    //   386: bastore
    //   387: dup
    //   388: bipush #12
    //   390: bipush #19
    //   392: bastore
    //   393: dup
    //   394: bipush #13
    //   396: bipush #-35
    //   398: bastore
    //   399: dup
    //   400: bipush #14
    //   402: bipush #47
    //   404: bastore
    //   405: dup
    //   406: bipush #15
    //   408: bipush #113
    //   410: bastore
    //   411: dup
    //   412: bipush #16
    //   414: bipush #115
    //   416: bastore
    //   417: dup
    //   418: bipush #17
    //   420: bipush #52
    //   422: bastore
    //   423: dup
    //   424: bipush #18
    //   426: bipush #-103
    //   428: bastore
    //   429: dup
    //   430: bipush #19
    //   432: bipush #-69
    //   434: bastore
    //   435: dup
    //   436: bipush #20
    //   438: bipush #59
    //   440: bastore
    //   441: dup
    //   442: bipush #21
    //   444: bipush #17
    //   446: bastore
    //   447: dup
    //   448: bipush #22
    //   450: bipush #35
    //   452: bastore
    //   453: dup
    //   454: bipush #23
    //   456: bipush #-13
    //   458: bastore
    //   459: dup
    //   460: bipush #24
    //   462: bipush #54
    //   464: bastore
    //   465: dup
    //   466: bipush #25
    //   468: bipush #-93
    //   470: bastore
    //   471: dup
    //   472: bipush #26
    //   474: bipush #-44
    //   476: bastore
    //   477: dup
    //   478: bipush #27
    //   480: bipush #93
    //   482: bastore
    //   483: dup
    //   484: bipush #28
    //   486: bipush #-99
    //   488: bastore
    //   489: dup
    //   490: bipush #29
    //   492: bipush #-85
    //   494: bastore
    //   495: dup
    //   496: bipush #30
    //   498: bipush #-103
    //   500: bastore
    //   501: dup
    //   502: bipush #31
    //   504: bipush #-49
    //   506: bastore
    //   507: invokespecial <init> : (I[B)V
    //   510: putstatic burp/Zezn.Zh : Ljava/lang/Object;
    //   513: return
  }
  
  private static Throwable a(Throwable paramThrowable) {
    return paramThrowable;
  }
  
  private static String a(int paramInt1, int paramInt2) {
    int i = (paramInt1 ^ 0x6D0F) & 0xFFFF;
    if (b[i] == null) {
      char[] arrayOfChar = a[i].toCharArray();
      switch (arrayOfChar[0] & 0xFF) {
        case 0:
        
        case 1:
        
        case 2:
        
        case 3:
        
        case 4:
        
        case 5:
        
        case 6:
        
        case 7:
        
        case 8:
        
        case 9:
        
        case 10:
        
        case 11:
        
        case 12:
        
        case 13:
        
        case 14:
        
        case 15:
        
        case 16:
        
        case 17:
        
        case 18:
        
        case 19:
        
        case 20:
        
        case 21:
        
        case 22:
        
        case 23:
        
        case 24:
        
        case 25:
        
        case 26:
        
        case 27:
        
        case 28:
        
        case 29:
        
        case 30:
        
        case 31:
        
        case 32:
        
        case 33:
        
        case 34:
        
        case 35:
        
        case 36:
        
        case 37:
        
        case 38:
        
        case 39:
        
        case 40:
        
        case 41:
        
        case 42:
        
        case 43:
        
        case 44:
        
        case 45:
        
        case 46:
        
        case 47:
        
        case 48:
        
        case 49:
        
        case 50:
        
        case 51:
        
        case 52:
        
        case 53:
        
        case 54:
        
        case 55:
        
        case 56:
        
        case 57:
        
        case 58:
        
        case 59:
        
        case 60:
        
        case 61:
        
        case 62:
        
        case 63:
        
        case 64:
        
        case 65:
        
        case 66:
        
        case 67:
        
        case 68:
        
        case 69:
        
        case 70:
        
        case 71:
        
        case 72:
        
        case 73:
        
        case 74:
        
        case 75:
        
        case 76:
        
        case 77:
        
        case 78:
        
        case 79:
        
        case 80:
        
        case 81:
        
        case 82:
        
        case 83:
        
        case 84:
        
        case 85:
        
        case 86:
        
        case 87:
        
        case 88:
        
        case 89:
        
        case 90:
        
        case 91:
        
        case 92:
        
        case 93:
        
        case 94:
        
        case 95:
        
        case 96:
        
        case 97:
        
        case 98:
        
        case 99:
        
        case 100:
        
        case 101:
        
        case 102:
        
        case 103:
        
        case 104:
        
        case 105:
        
        case 106:
        
        case 107:
        
        case 108:
        
        case 109:
        
        case 110:
        
        case 111:
        
        case 112:
        
        case 113:
        
        case 114:
        
        case 115:
        
        case 116:
        
        case 117:
        
        case 118:
        
        case 119:
        
        case 120:
        
        case 121:
        
        case 122:
        
        case 123:
        
        case 124:
        
        case 125:
        
        case 126:
        
        case 127:
        
        case 128:
        
        case 129:
        
        case 130:
        
        case 131:
        
        case 132:
        
        case 133:
        
        case 134:
        
        case 135:
        
        case 136:
        
        case 137:
        
        case 138:
        
        case 139:
        
        case 140:
        
        case 141:
        
        case 142:
        
        case 143:
        
        case 144:
        
        case 145:
        
        case 146:
        
        case 147:
        
        case 148:
        
        case 149:
        
        case 150:
        
        case 151:
        
        case 152:
        
        case 153:
        
        case 154:
        
        case 155:
        
        case 156:
        
        case 157:
        
        case 158:
        
        case 159:
        
        case 160:
        
        case 161:
        
        case 162:
        
        case 163:
        
        case 164:
        
        case 165:
        
        case 166:
        
        case 167:
        
        case 168:
        
        case 169:
        
        case 170:
        
        case 171:
        
        case 172:
        
        case 173:
        
        case 174:
        
        case 175:
        
        case 176:
        
        case 177:
        
        case 178:
        
        case 179:
        
        case 180:
        
        case 181:
        
        case 182:
        
        case 183:
        
        case 184:
        
        case 185:
        
        case 186:
        
        case 187:
        
        case 188:
        
        case 189:
        
        case 190:
        
        case 191:
        
        case 192:
        
        case 193:
        
        case 194:
        
        case 195:
        
        case 196:
        
        case 197:
        
        case 198:
        
        case 199:
        
        case 200:
        
        case 201:
        
        case 202:
        
        case 203:
        
        case 204:
        
        case 205:
        
        case 206:
        
        case 207:
        
        case 208:
        
        case 209:
        
        case 210:
        
        case 211:
        
        case 212:
        
        case 213:
        
        case 214:
        
        case 215:
        
        case 216:
        
        case 217:
        
        case 218:
        
        case 219:
        
        case 220:
        
        case 221:
        
        case 222:
        
        case 223:
        
        case 224:
        
        case 225:
        
        case 226:
        
        case 227:
        
        case 228:
        
        case 229:
        
        case 230:
        
        case 231:
        
        case 232:
        
        case 233:
        
        case 234:
        
        case 235:
        
        case 236:
        
        case 237:
        
        case 238:
        
        case 239:
        
        case 240:
        
        case 241:
        
        case 242:
        
        case 243:
        
        case 244:
        
        case 245:
        
        case 246:
        
        case 247:
        
        case 248:
        
        case 249:
        
        case 250:
        
        case 251:
        
        case 252:
        
        case 253:
        
        case 254:
        
        default:
          break;
      } 
      byte b1 = 12;
      int j = (paramInt2 & 0xFF) - b1;
      if (j < 0)
        j += 256; 
      int k = ((paramInt2 & 0xFFFF) >>> 8) - b1;
      if (k < 0)
        k += 256; 
      for (byte b2 = 0; b2 < arrayOfChar.length; b2++) {
        int m = b2 % 2;
        if (m == 0) {
          arrayOfChar[b2] = (char)(arrayOfChar[b2] ^ j);
          j = ((j >>> 3 | j << 5) ^ arrayOfChar[b2]) & 0xFF;
        } else {
          arrayOfChar[b2] = (char)(arrayOfChar[b2] ^ k);
          k = ((k >>> 3 | k << 5) ^ arrayOfChar[b2]) & 0xFF;
        } 
      } 
      b[i] = (new String(arrayOfChar)).intern();
    } 
    return b[i];
  }
}


/* Location:              C:\Program Files\BurpSuitePro\burpsuite_pro.jar!\burp\Zezn.class
 * Java compiler version: 21 (65.0)
 * JD-Core Version:       1.1.3
 */