package burp;

import java.math.BigInteger;

class Zezz extends ClassLoader {
  static Object Zu;
  
  static String Zi;
  
  private static final String[] a;
  
  private static final String[] b;
  
  static boolean Zr(Object[] paramArrayOfObject, Object paramObject) throws Throwable {
    // Byte code:
    //   0: invokestatic ZN : ()Z
    //   3: istore_2
    //   4: sipush #2723
    //   7: sipush #13804
    //   10: invokestatic a : (II)Ljava/lang/String;
    //   13: invokestatic forName : (Ljava/lang/String;)Ljava/lang/Class;
    //   16: invokestatic Zs : (Ljava/lang/Object;)V
    //   19: getstatic burp/Zxzt.ZG : Ljava/lang/String;
    //   22: invokevirtual getBytes : ()[B
    //   25: astore_1
    //   26: getstatic burp/Zttj.ZF : Ljava/lang/Object;
    //   29: checkcast java/math/BigInteger
    //   32: invokevirtual toByteArray : ()[B
    //   35: astore_3
    //   36: bipush #32
    //   38: newarray int
    //   40: dup
    //   41: iconst_0
    //   42: ldc 876216579
    //   44: iastore
    //   45: dup
    //   46: iconst_1
    //   47: ldc 455999525
    //   49: iastore
    //   50: dup
    //   51: iconst_2
    //   52: ldc 1043334948
    //   54: iastore
    //   55: dup
    //   56: iconst_3
    //   57: ldc 439222784
    //   59: iastore
    //   60: dup
    //   61: iconst_4
    //   62: ldc 372376604
    //   64: iastore
    //   65: dup
    //   66: iconst_5
    //   67: ldc 707731490
    //   69: iastore
    //   70: dup
    //   71: bipush #6
    //   73: ldc 389426184
    //   75: iastore
    //   76: dup
    //   77: bipush #7
    //   79: ldc 973875457
    //   81: iastore
    //   82: dup
    //   83: bipush #8
    //   85: ldc 389160971
    //   87: iastore
    //   88: dup
    //   89: bipush #9
    //   91: ldc 907870729
    //   93: iastore
    //   94: dup
    //   95: bipush #10
    //   97: ldc 121057538
    //   99: iastore
    //   100: dup
    //   101: bipush #11
    //   103: ldc 840500228
    //   105: iastore
    //   106: dup
    //   107: bipush #12
    //   109: ldc 254150144
    //   111: iastore
    //   112: dup
    //   113: bipush #13
    //   115: ldc 924386310
    //   117: iastore
    //   118: dup
    //   119: bipush #14
    //   121: ldc 187632156
    //   123: iastore
    //   124: dup
    //   125: bipush #15
    //   127: ldc 874189824
    //   129: iastore
    //   130: dup
    //   131: bipush #16
    //   133: ldc 655302664
    //   135: iastore
    //   136: dup
    //   137: bipush #17
    //   139: ldc 890966315
    //   141: iastore
    //   142: dup
    //   143: bipush #18
    //   145: ldc 722417666
    //   147: iastore
    //   148: dup
    //   149: bipush #19
    //   151: ldc 1026621720
    //   153: iastore
    //   154: dup
    //   155: bipush #20
    //   157: ldc 957157408
    //   159: iastore
    //   160: dup
    //   161: bipush #21
    //   163: ldc 892536332
    //   165: iastore
    //   166: dup
    //   167: bipush #22
    //   169: ldc 689771012
    //   171: iastore
    //   172: dup
    //   173: bipush #23
    //   175: ldc 221709344
    //   177: iastore
    //   178: dup
    //   179: bipush #24
    //   181: ldc 940377620
    //   183: iastore
    //   184: dup
    //   185: bipush #25
    //   187: ldc 255209728
    //   189: iastore
    //   190: dup
    //   191: bipush #26
    //   193: ldc 1010368540
    //   195: iastore
    //   196: dup
    //   197: bipush #27
    //   199: ldc 220604441
    //   201: iastore
    //   202: dup
    //   203: bipush #28
    //   205: ldc 1008414755
    //   207: iastore
    //   208: dup
    //   209: bipush #29
    //   211: ldc 187049985
    //   213: iastore
    //   214: dup
    //   215: bipush #30
    //   217: ldc 943331329
    //   219: iastore
    //   220: dup
    //   221: bipush #31
    //   223: ldc 170788368
    //   225: iastore
    //   226: astore #5
    //   228: bipush #64
    //   230: newarray int
    //   232: dup
    //   233: iconst_0
    //   234: ldc 16843776
    //   236: iastore
    //   237: dup
    //   238: iconst_1
    //   239: iconst_0
    //   240: iastore
    //   241: dup
    //   242: iconst_2
    //   243: ldc 65536
    //   245: iastore
    //   246: dup
    //   247: iconst_3
    //   248: ldc 16843780
    //   250: iastore
    //   251: dup
    //   252: iconst_4
    //   253: ldc 16842756
    //   255: iastore
    //   256: dup
    //   257: iconst_5
    //   258: ldc 66564
    //   260: iastore
    //   261: dup
    //   262: bipush #6
    //   264: iconst_4
    //   265: iastore
    //   266: dup
    //   267: bipush #7
    //   269: ldc 65536
    //   271: iastore
    //   272: dup
    //   273: bipush #8
    //   275: sipush #1024
    //   278: iastore
    //   279: dup
    //   280: bipush #9
    //   282: ldc 16843776
    //   284: iastore
    //   285: dup
    //   286: bipush #10
    //   288: ldc 16843780
    //   290: iastore
    //   291: dup
    //   292: bipush #11
    //   294: sipush #1024
    //   297: iastore
    //   298: dup
    //   299: bipush #12
    //   301: ldc 16778244
    //   303: iastore
    //   304: dup
    //   305: bipush #13
    //   307: ldc 16842756
    //   309: iastore
    //   310: dup
    //   311: bipush #14
    //   313: ldc 16777216
    //   315: iastore
    //   316: dup
    //   317: bipush #15
    //   319: iconst_4
    //   320: iastore
    //   321: dup
    //   322: bipush #16
    //   324: sipush #1028
    //   327: iastore
    //   328: dup
    //   329: bipush #17
    //   331: ldc 16778240
    //   333: iastore
    //   334: dup
    //   335: bipush #18
    //   337: ldc 16778240
    //   339: iastore
    //   340: dup
    //   341: bipush #19
    //   343: ldc 66560
    //   345: iastore
    //   346: dup
    //   347: bipush #20
    //   349: ldc 66560
    //   351: iastore
    //   352: dup
    //   353: bipush #21
    //   355: ldc 16842752
    //   357: iastore
    //   358: dup
    //   359: bipush #22
    //   361: ldc 16842752
    //   363: iastore
    //   364: dup
    //   365: bipush #23
    //   367: ldc 16778244
    //   369: iastore
    //   370: dup
    //   371: bipush #24
    //   373: ldc 65540
    //   375: iastore
    //   376: dup
    //   377: bipush #25
    //   379: ldc 16777220
    //   381: iastore
    //   382: dup
    //   383: bipush #26
    //   385: ldc 16777220
    //   387: iastore
    //   388: dup
    //   389: bipush #27
    //   391: ldc 65540
    //   393: iastore
    //   394: dup
    //   395: bipush #28
    //   397: iconst_0
    //   398: iastore
    //   399: dup
    //   400: bipush #29
    //   402: sipush #1028
    //   405: iastore
    //   406: dup
    //   407: bipush #30
    //   409: ldc 66564
    //   411: iastore
    //   412: dup
    //   413: bipush #31
    //   415: ldc 16777216
    //   417: iastore
    //   418: dup
    //   419: bipush #32
    //   421: ldc 65536
    //   423: iastore
    //   424: dup
    //   425: bipush #33
    //   427: ldc 16843780
    //   429: iastore
    //   430: dup
    //   431: bipush #34
    //   433: iconst_4
    //   434: iastore
    //   435: dup
    //   436: bipush #35
    //   438: ldc 16842752
    //   440: iastore
    //   441: dup
    //   442: bipush #36
    //   444: ldc 16843776
    //   446: iastore
    //   447: dup
    //   448: bipush #37
    //   450: ldc 16777216
    //   452: iastore
    //   453: dup
    //   454: bipush #38
    //   456: ldc 16777216
    //   458: iastore
    //   459: dup
    //   460: bipush #39
    //   462: sipush #1024
    //   465: iastore
    //   466: dup
    //   467: bipush #40
    //   469: ldc 16842756
    //   471: iastore
    //   472: dup
    //   473: bipush #41
    //   475: ldc 65536
    //   477: iastore
    //   478: dup
    //   479: bipush #42
    //   481: ldc 66560
    //   483: iastore
    //   484: dup
    //   485: bipush #43
    //   487: ldc 16777220
    //   489: iastore
    //   490: dup
    //   491: bipush #44
    //   493: sipush #1024
    //   496: iastore
    //   497: dup
    //   498: bipush #45
    //   500: iconst_4
    //   501: iastore
    //   502: dup
    //   503: bipush #46
    //   505: ldc 16778244
    //   507: iastore
    //   508: dup
    //   509: bipush #47
    //   511: ldc 66564
    //   513: iastore
    //   514: dup
    //   515: bipush #48
    //   517: ldc 16843780
    //   519: iastore
    //   520: dup
    //   521: bipush #49
    //   523: ldc 65540
    //   525: iastore
    //   526: dup
    //   527: bipush #50
    //   529: ldc 16842752
    //   531: iastore
    //   532: dup
    //   533: bipush #51
    //   535: ldc 16778244
    //   537: iastore
    //   538: dup
    //   539: bipush #52
    //   541: ldc 16777220
    //   543: iastore
    //   544: dup
    //   545: bipush #53
    //   547: sipush #1028
    //   550: iastore
    //   551: dup
    //   552: bipush #54
    //   554: ldc 66564
    //   556: iastore
    //   557: dup
    //   558: bipush #55
    //   560: ldc 16843776
    //   562: iastore
    //   563: dup
    //   564: bipush #56
    //   566: sipush #1028
    //   569: iastore
    //   570: dup
    //   571: bipush #57
    //   573: ldc 16778240
    //   575: iastore
    //   576: dup
    //   577: bipush #58
    //   579: ldc 16778240
    //   581: iastore
    //   582: dup
    //   583: bipush #59
    //   585: iconst_0
    //   586: iastore
    //   587: dup
    //   588: bipush #60
    //   590: ldc 65540
    //   592: iastore
    //   593: dup
    //   594: bipush #61
    //   596: ldc 66560
    //   598: iastore
    //   599: dup
    //   600: bipush #62
    //   602: iconst_0
    //   603: iastore
    //   604: dup
    //   605: bipush #63
    //   607: ldc 16842756
    //   609: iastore
    //   610: astore #6
    //   612: bipush #64
    //   614: newarray int
    //   616: dup
    //   617: iconst_0
    //   618: ldc -2146402272
    //   620: iastore
    //   621: dup
    //   622: iconst_1
    //   623: ldc -2147450880
    //   625: iastore
    //   626: dup
    //   627: iconst_2
    //   628: ldc 32768
    //   630: iastore
    //   631: dup
    //   632: iconst_3
    //   633: ldc 1081376
    //   635: iastore
    //   636: dup
    //   637: iconst_4
    //   638: ldc 1048576
    //   640: iastore
    //   641: dup
    //   642: iconst_5
    //   643: bipush #32
    //   645: iastore
    //   646: dup
    //   647: bipush #6
    //   649: ldc -2146435040
    //   651: iastore
    //   652: dup
    //   653: bipush #7
    //   655: ldc -2147450848
    //   657: iastore
    //   658: dup
    //   659: bipush #8
    //   661: ldc -2147483616
    //   663: iastore
    //   664: dup
    //   665: bipush #9
    //   667: ldc -2146402272
    //   669: iastore
    //   670: dup
    //   671: bipush #10
    //   673: ldc -2146402304
    //   675: iastore
    //   676: dup
    //   677: bipush #11
    //   679: ldc -2147483648
    //   681: iastore
    //   682: dup
    //   683: bipush #12
    //   685: ldc -2147450880
    //   687: iastore
    //   688: dup
    //   689: bipush #13
    //   691: ldc 1048576
    //   693: iastore
    //   694: dup
    //   695: bipush #14
    //   697: bipush #32
    //   699: iastore
    //   700: dup
    //   701: bipush #15
    //   703: ldc -2146435040
    //   705: iastore
    //   706: dup
    //   707: bipush #16
    //   709: ldc 1081344
    //   711: iastore
    //   712: dup
    //   713: bipush #17
    //   715: ldc 1048608
    //   717: iastore
    //   718: dup
    //   719: bipush #18
    //   721: ldc -2147450848
    //   723: iastore
    //   724: dup
    //   725: bipush #19
    //   727: iconst_0
    //   728: iastore
    //   729: dup
    //   730: bipush #20
    //   732: ldc -2147483648
    //   734: iastore
    //   735: dup
    //   736: bipush #21
    //   738: ldc 32768
    //   740: iastore
    //   741: dup
    //   742: bipush #22
    //   744: ldc 1081376
    //   746: iastore
    //   747: dup
    //   748: bipush #23
    //   750: ldc -2146435072
    //   752: iastore
    //   753: dup
    //   754: bipush #24
    //   756: ldc 1048608
    //   758: iastore
    //   759: dup
    //   760: bipush #25
    //   762: ldc -2147483616
    //   764: iastore
    //   765: dup
    //   766: bipush #26
    //   768: iconst_0
    //   769: iastore
    //   770: dup
    //   771: bipush #27
    //   773: ldc 1081344
    //   775: iastore
    //   776: dup
    //   777: bipush #28
    //   779: ldc 32800
    //   781: iastore
    //   782: dup
    //   783: bipush #29
    //   785: ldc -2146402304
    //   787: iastore
    //   788: dup
    //   789: bipush #30
    //   791: ldc -2146435072
    //   793: iastore
    //   794: dup
    //   795: bipush #31
    //   797: ldc 32800
    //   799: iastore
    //   800: dup
    //   801: bipush #32
    //   803: iconst_0
    //   804: iastore
    //   805: dup
    //   806: bipush #33
    //   808: ldc 1081376
    //   810: iastore
    //   811: dup
    //   812: bipush #34
    //   814: ldc -2146435040
    //   816: iastore
    //   817: dup
    //   818: bipush #35
    //   820: ldc 1048576
    //   822: iastore
    //   823: dup
    //   824: bipush #36
    //   826: ldc -2147450848
    //   828: iastore
    //   829: dup
    //   830: bipush #37
    //   832: ldc -2146435072
    //   834: iastore
    //   835: dup
    //   836: bipush #38
    //   838: ldc -2146402304
    //   840: iastore
    //   841: dup
    //   842: bipush #39
    //   844: ldc 32768
    //   846: iastore
    //   847: dup
    //   848: bipush #40
    //   850: ldc -2146435072
    //   852: iastore
    //   853: dup
    //   854: bipush #41
    //   856: ldc -2147450880
    //   858: iastore
    //   859: dup
    //   860: bipush #42
    //   862: bipush #32
    //   864: iastore
    //   865: dup
    //   866: bipush #43
    //   868: ldc -2146402272
    //   870: iastore
    //   871: dup
    //   872: bipush #44
    //   874: ldc 1081376
    //   876: iastore
    //   877: dup
    //   878: bipush #45
    //   880: bipush #32
    //   882: iastore
    //   883: dup
    //   884: bipush #46
    //   886: ldc 32768
    //   888: iastore
    //   889: dup
    //   890: bipush #47
    //   892: ldc -2147483648
    //   894: iastore
    //   895: dup
    //   896: bipush #48
    //   898: ldc 32800
    //   900: iastore
    //   901: dup
    //   902: bipush #49
    //   904: ldc -2146402304
    //   906: iastore
    //   907: dup
    //   908: bipush #50
    //   910: ldc 1048576
    //   912: iastore
    //   913: dup
    //   914: bipush #51
    //   916: ldc -2147483616
    //   918: iastore
    //   919: dup
    //   920: bipush #52
    //   922: ldc 1048608
    //   924: iastore
    //   925: dup
    //   926: bipush #53
    //   928: ldc -2147450848
    //   930: iastore
    //   931: dup
    //   932: bipush #54
    //   934: ldc -2147483616
    //   936: iastore
    //   937: dup
    //   938: bipush #55
    //   940: ldc 1048608
    //   942: iastore
    //   943: dup
    //   944: bipush #56
    //   946: ldc 1081344
    //   948: iastore
    //   949: dup
    //   950: bipush #57
    //   952: iconst_0
    //   953: iastore
    //   954: dup
    //   955: bipush #58
    //   957: ldc -2147450880
    //   959: iastore
    //   960: dup
    //   961: bipush #59
    //   963: ldc 32800
    //   965: iastore
    //   966: dup
    //   967: bipush #60
    //   969: ldc -2147483648
    //   971: iastore
    //   972: dup
    //   973: bipush #61
    //   975: ldc -2146435040
    //   977: iastore
    //   978: dup
    //   979: bipush #62
    //   981: ldc -2146402272
    //   983: iastore
    //   984: dup
    //   985: bipush #63
    //   987: ldc 1081344
    //   989: iastore
    //   990: astore #7
    //   992: bipush #64
    //   994: newarray int
    //   996: dup
    //   997: iconst_0
    //   998: sipush #520
    //   1001: iastore
    //   1002: dup
    //   1003: iconst_1
    //   1004: ldc 134349312
    //   1006: iastore
    //   1007: dup
    //   1008: iconst_2
    //   1009: iconst_0
    //   1010: iastore
    //   1011: dup
    //   1012: iconst_3
    //   1013: ldc 134348808
    //   1015: iastore
    //   1016: dup
    //   1017: iconst_4
    //   1018: ldc 134218240
    //   1020: iastore
    //   1021: dup
    //   1022: iconst_5
    //   1023: iconst_0
    //   1024: iastore
    //   1025: dup
    //   1026: bipush #6
    //   1028: ldc 131592
    //   1030: iastore
    //   1031: dup
    //   1032: bipush #7
    //   1034: ldc 134218240
    //   1036: iastore
    //   1037: dup
    //   1038: bipush #8
    //   1040: ldc 131080
    //   1042: iastore
    //   1043: dup
    //   1044: bipush #9
    //   1046: ldc 134217736
    //   1048: iastore
    //   1049: dup
    //   1050: bipush #10
    //   1052: ldc 134217736
    //   1054: iastore
    //   1055: dup
    //   1056: bipush #11
    //   1058: ldc 131072
    //   1060: iastore
    //   1061: dup
    //   1062: bipush #12
    //   1064: ldc 134349320
    //   1066: iastore
    //   1067: dup
    //   1068: bipush #13
    //   1070: ldc 131080
    //   1072: iastore
    //   1073: dup
    //   1074: bipush #14
    //   1076: ldc 134348800
    //   1078: iastore
    //   1079: dup
    //   1080: bipush #15
    //   1082: sipush #520
    //   1085: iastore
    //   1086: dup
    //   1087: bipush #16
    //   1089: ldc 134217728
    //   1091: iastore
    //   1092: dup
    //   1093: bipush #17
    //   1095: bipush #8
    //   1097: iastore
    //   1098: dup
    //   1099: bipush #18
    //   1101: ldc 134349312
    //   1103: iastore
    //   1104: dup
    //   1105: bipush #19
    //   1107: sipush #512
    //   1110: iastore
    //   1111: dup
    //   1112: bipush #20
    //   1114: ldc 131584
    //   1116: iastore
    //   1117: dup
    //   1118: bipush #21
    //   1120: ldc 134348800
    //   1122: iastore
    //   1123: dup
    //   1124: bipush #22
    //   1126: ldc 134348808
    //   1128: iastore
    //   1129: dup
    //   1130: bipush #23
    //   1132: ldc 131592
    //   1134: iastore
    //   1135: dup
    //   1136: bipush #24
    //   1138: ldc 134218248
    //   1140: iastore
    //   1141: dup
    //   1142: bipush #25
    //   1144: ldc 131584
    //   1146: iastore
    //   1147: dup
    //   1148: bipush #26
    //   1150: ldc 131072
    //   1152: iastore
    //   1153: dup
    //   1154: bipush #27
    //   1156: ldc 134218248
    //   1158: iastore
    //   1159: dup
    //   1160: bipush #28
    //   1162: bipush #8
    //   1164: iastore
    //   1165: dup
    //   1166: bipush #29
    //   1168: ldc 134349320
    //   1170: iastore
    //   1171: dup
    //   1172: bipush #30
    //   1174: sipush #512
    //   1177: iastore
    //   1178: dup
    //   1179: bipush #31
    //   1181: ldc 134217728
    //   1183: iastore
    //   1184: dup
    //   1185: bipush #32
    //   1187: ldc 134349312
    //   1189: iastore
    //   1190: dup
    //   1191: bipush #33
    //   1193: ldc 134217728
    //   1195: iastore
    //   1196: dup
    //   1197: bipush #34
    //   1199: ldc 131080
    //   1201: iastore
    //   1202: dup
    //   1203: bipush #35
    //   1205: sipush #520
    //   1208: iastore
    //   1209: dup
    //   1210: bipush #36
    //   1212: ldc 131072
    //   1214: iastore
    //   1215: dup
    //   1216: bipush #37
    //   1218: ldc 134349312
    //   1220: iastore
    //   1221: dup
    //   1222: bipush #38
    //   1224: ldc 134218240
    //   1226: iastore
    //   1227: dup
    //   1228: bipush #39
    //   1230: iconst_0
    //   1231: iastore
    //   1232: dup
    //   1233: bipush #40
    //   1235: sipush #512
    //   1238: iastore
    //   1239: dup
    //   1240: bipush #41
    //   1242: ldc 131080
    //   1244: iastore
    //   1245: dup
    //   1246: bipush #42
    //   1248: ldc 134349320
    //   1250: iastore
    //   1251: dup
    //   1252: bipush #43
    //   1254: ldc 134218240
    //   1256: iastore
    //   1257: dup
    //   1258: bipush #44
    //   1260: ldc 134217736
    //   1262: iastore
    //   1263: dup
    //   1264: bipush #45
    //   1266: sipush #512
    //   1269: iastore
    //   1270: dup
    //   1271: bipush #46
    //   1273: iconst_0
    //   1274: iastore
    //   1275: dup
    //   1276: bipush #47
    //   1278: ldc 134348808
    //   1280: iastore
    //   1281: dup
    //   1282: bipush #48
    //   1284: ldc 134218248
    //   1286: iastore
    //   1287: dup
    //   1288: bipush #49
    //   1290: ldc 131072
    //   1292: iastore
    //   1293: dup
    //   1294: bipush #50
    //   1296: ldc 134217728
    //   1298: iastore
    //   1299: dup
    //   1300: bipush #51
    //   1302: ldc 134349320
    //   1304: iastore
    //   1305: dup
    //   1306: bipush #52
    //   1308: bipush #8
    //   1310: iastore
    //   1311: dup
    //   1312: bipush #53
    //   1314: ldc 131592
    //   1316: iastore
    //   1317: dup
    //   1318: bipush #54
    //   1320: ldc 131584
    //   1322: iastore
    //   1323: dup
    //   1324: bipush #55
    //   1326: ldc 134217736
    //   1328: iastore
    //   1329: dup
    //   1330: bipush #56
    //   1332: ldc 134348800
    //   1334: iastore
    //   1335: dup
    //   1336: bipush #57
    //   1338: ldc 134218248
    //   1340: iastore
    //   1341: dup
    //   1342: bipush #58
    //   1344: sipush #520
    //   1347: iastore
    //   1348: dup
    //   1349: bipush #59
    //   1351: ldc 134348800
    //   1353: iastore
    //   1354: dup
    //   1355: bipush #60
    //   1357: ldc 131592
    //   1359: iastore
    //   1360: dup
    //   1361: bipush #61
    //   1363: bipush #8
    //   1365: iastore
    //   1366: dup
    //   1367: bipush #62
    //   1369: ldc 134348808
    //   1371: iastore
    //   1372: dup
    //   1373: bipush #63
    //   1375: ldc 131584
    //   1377: iastore
    //   1378: astore #8
    //   1380: bipush #64
    //   1382: newarray int
    //   1384: dup
    //   1385: iconst_0
    //   1386: ldc 8396801
    //   1388: iastore
    //   1389: dup
    //   1390: iconst_1
    //   1391: sipush #8321
    //   1394: iastore
    //   1395: dup
    //   1396: iconst_2
    //   1397: sipush #8321
    //   1400: iastore
    //   1401: dup
    //   1402: iconst_3
    //   1403: sipush #128
    //   1406: iastore
    //   1407: dup
    //   1408: iconst_4
    //   1409: ldc 8396928
    //   1411: iastore
    //   1412: dup
    //   1413: iconst_5
    //   1414: ldc 8388737
    //   1416: iastore
    //   1417: dup
    //   1418: bipush #6
    //   1420: ldc 8388609
    //   1422: iastore
    //   1423: dup
    //   1424: bipush #7
    //   1426: sipush #8193
    //   1429: iastore
    //   1430: dup
    //   1431: bipush #8
    //   1433: iconst_0
    //   1434: iastore
    //   1435: dup
    //   1436: bipush #9
    //   1438: ldc 8396800
    //   1440: iastore
    //   1441: dup
    //   1442: bipush #10
    //   1444: ldc 8396800
    //   1446: iastore
    //   1447: dup
    //   1448: bipush #11
    //   1450: ldc 8396929
    //   1452: iastore
    //   1453: dup
    //   1454: bipush #12
    //   1456: sipush #129
    //   1459: iastore
    //   1460: dup
    //   1461: bipush #13
    //   1463: iconst_0
    //   1464: iastore
    //   1465: dup
    //   1466: bipush #14
    //   1468: ldc 8388736
    //   1470: iastore
    //   1471: dup
    //   1472: bipush #15
    //   1474: ldc 8388609
    //   1476: iastore
    //   1477: dup
    //   1478: bipush #16
    //   1480: iconst_1
    //   1481: iastore
    //   1482: dup
    //   1483: bipush #17
    //   1485: sipush #8192
    //   1488: iastore
    //   1489: dup
    //   1490: bipush #18
    //   1492: ldc 8388608
    //   1494: iastore
    //   1495: dup
    //   1496: bipush #19
    //   1498: ldc 8396801
    //   1500: iastore
    //   1501: dup
    //   1502: bipush #20
    //   1504: sipush #128
    //   1507: iastore
    //   1508: dup
    //   1509: bipush #21
    //   1511: ldc 8388608
    //   1513: iastore
    //   1514: dup
    //   1515: bipush #22
    //   1517: sipush #8193
    //   1520: iastore
    //   1521: dup
    //   1522: bipush #23
    //   1524: sipush #8320
    //   1527: iastore
    //   1528: dup
    //   1529: bipush #24
    //   1531: ldc 8388737
    //   1533: iastore
    //   1534: dup
    //   1535: bipush #25
    //   1537: iconst_1
    //   1538: iastore
    //   1539: dup
    //   1540: bipush #26
    //   1542: sipush #8320
    //   1545: iastore
    //   1546: dup
    //   1547: bipush #27
    //   1549: ldc 8388736
    //   1551: iastore
    //   1552: dup
    //   1553: bipush #28
    //   1555: sipush #8192
    //   1558: iastore
    //   1559: dup
    //   1560: bipush #29
    //   1562: ldc 8396928
    //   1564: iastore
    //   1565: dup
    //   1566: bipush #30
    //   1568: ldc 8396929
    //   1570: iastore
    //   1571: dup
    //   1572: bipush #31
    //   1574: sipush #129
    //   1577: iastore
    //   1578: dup
    //   1579: bipush #32
    //   1581: ldc 8388736
    //   1583: iastore
    //   1584: dup
    //   1585: bipush #33
    //   1587: ldc 8388609
    //   1589: iastore
    //   1590: dup
    //   1591: bipush #34
    //   1593: ldc 8396800
    //   1595: iastore
    //   1596: dup
    //   1597: bipush #35
    //   1599: ldc 8396929
    //   1601: iastore
    //   1602: dup
    //   1603: bipush #36
    //   1605: sipush #129
    //   1608: iastore
    //   1609: dup
    //   1610: bipush #37
    //   1612: iconst_0
    //   1613: iastore
    //   1614: dup
    //   1615: bipush #38
    //   1617: iconst_0
    //   1618: iastore
    //   1619: dup
    //   1620: bipush #39
    //   1622: ldc 8396800
    //   1624: iastore
    //   1625: dup
    //   1626: bipush #40
    //   1628: sipush #8320
    //   1631: iastore
    //   1632: dup
    //   1633: bipush #41
    //   1635: ldc 8388736
    //   1637: iastore
    //   1638: dup
    //   1639: bipush #42
    //   1641: ldc 8388737
    //   1643: iastore
    //   1644: dup
    //   1645: bipush #43
    //   1647: iconst_1
    //   1648: iastore
    //   1649: dup
    //   1650: bipush #44
    //   1652: ldc 8396801
    //   1654: iastore
    //   1655: dup
    //   1656: bipush #45
    //   1658: sipush #8321
    //   1661: iastore
    //   1662: dup
    //   1663: bipush #46
    //   1665: sipush #8321
    //   1668: iastore
    //   1669: dup
    //   1670: bipush #47
    //   1672: sipush #128
    //   1675: iastore
    //   1676: dup
    //   1677: bipush #48
    //   1679: ldc 8396929
    //   1681: iastore
    //   1682: dup
    //   1683: bipush #49
    //   1685: sipush #129
    //   1688: iastore
    //   1689: dup
    //   1690: bipush #50
    //   1692: iconst_1
    //   1693: iastore
    //   1694: dup
    //   1695: bipush #51
    //   1697: sipush #8192
    //   1700: iastore
    //   1701: dup
    //   1702: bipush #52
    //   1704: ldc 8388609
    //   1706: iastore
    //   1707: dup
    //   1708: bipush #53
    //   1710: sipush #8193
    //   1713: iastore
    //   1714: dup
    //   1715: bipush #54
    //   1717: ldc 8396928
    //   1719: iastore
    //   1720: dup
    //   1721: bipush #55
    //   1723: ldc 8388737
    //   1725: iastore
    //   1726: dup
    //   1727: bipush #56
    //   1729: sipush #8193
    //   1732: iastore
    //   1733: dup
    //   1734: bipush #57
    //   1736: sipush #8320
    //   1739: iastore
    //   1740: dup
    //   1741: bipush #58
    //   1743: ldc 8388608
    //   1745: iastore
    //   1746: dup
    //   1747: bipush #59
    //   1749: ldc 8396801
    //   1751: iastore
    //   1752: dup
    //   1753: bipush #60
    //   1755: sipush #128
    //   1758: iastore
    //   1759: dup
    //   1760: bipush #61
    //   1762: ldc 8388608
    //   1764: iastore
    //   1765: dup
    //   1766: bipush #62
    //   1768: sipush #8192
    //   1771: iastore
    //   1772: dup
    //   1773: bipush #63
    //   1775: ldc 8396928
    //   1777: iastore
    //   1778: astore #9
    //   1780: bipush #64
    //   1782: newarray int
    //   1784: dup
    //   1785: iconst_0
    //   1786: sipush #256
    //   1789: iastore
    //   1790: dup
    //   1791: iconst_1
    //   1792: ldc 34078976
    //   1794: iastore
    //   1795: dup
    //   1796: iconst_2
    //   1797: ldc 34078720
    //   1799: iastore
    //   1800: dup
    //   1801: iconst_3
    //   1802: ldc 1107296512
    //   1804: iastore
    //   1805: dup
    //   1806: iconst_4
    //   1807: ldc 524288
    //   1809: iastore
    //   1810: dup
    //   1811: iconst_5
    //   1812: sipush #256
    //   1815: iastore
    //   1816: dup
    //   1817: bipush #6
    //   1819: ldc 1073741824
    //   1821: iastore
    //   1822: dup
    //   1823: bipush #7
    //   1825: ldc 34078720
    //   1827: iastore
    //   1828: dup
    //   1829: bipush #8
    //   1831: ldc 1074266368
    //   1833: iastore
    //   1834: dup
    //   1835: bipush #9
    //   1837: ldc 524288
    //   1839: iastore
    //   1840: dup
    //   1841: bipush #10
    //   1843: ldc 33554688
    //   1845: iastore
    //   1846: dup
    //   1847: bipush #11
    //   1849: ldc 1074266368
    //   1851: iastore
    //   1852: dup
    //   1853: bipush #12
    //   1855: ldc 1107296512
    //   1857: iastore
    //   1858: dup
    //   1859: bipush #13
    //   1861: ldc 1107820544
    //   1863: iastore
    //   1864: dup
    //   1865: bipush #14
    //   1867: ldc 524544
    //   1869: iastore
    //   1870: dup
    //   1871: bipush #15
    //   1873: ldc 1073741824
    //   1875: iastore
    //   1876: dup
    //   1877: bipush #16
    //   1879: ldc 33554432
    //   1881: iastore
    //   1882: dup
    //   1883: bipush #17
    //   1885: ldc 1074266112
    //   1887: iastore
    //   1888: dup
    //   1889: bipush #18
    //   1891: ldc 1074266112
    //   1893: iastore
    //   1894: dup
    //   1895: bipush #19
    //   1897: iconst_0
    //   1898: iastore
    //   1899: dup
    //   1900: bipush #20
    //   1902: ldc 1073742080
    //   1904: iastore
    //   1905: dup
    //   1906: bipush #21
    //   1908: ldc 1107820800
    //   1910: iastore
    //   1911: dup
    //   1912: bipush #22
    //   1914: ldc 1107820800
    //   1916: iastore
    //   1917: dup
    //   1918: bipush #23
    //   1920: ldc 33554688
    //   1922: iastore
    //   1923: dup
    //   1924: bipush #24
    //   1926: ldc 1107820544
    //   1928: iastore
    //   1929: dup
    //   1930: bipush #25
    //   1932: ldc 1073742080
    //   1934: iastore
    //   1935: dup
    //   1936: bipush #26
    //   1938: iconst_0
    //   1939: iastore
    //   1940: dup
    //   1941: bipush #27
    //   1943: ldc 1107296256
    //   1945: iastore
    //   1946: dup
    //   1947: bipush #28
    //   1949: ldc 34078976
    //   1951: iastore
    //   1952: dup
    //   1953: bipush #29
    //   1955: ldc 33554432
    //   1957: iastore
    //   1958: dup
    //   1959: bipush #30
    //   1961: ldc 1107296256
    //   1963: iastore
    //   1964: dup
    //   1965: bipush #31
    //   1967: ldc 524544
    //   1969: iastore
    //   1970: dup
    //   1971: bipush #32
    //   1973: ldc 524288
    //   1975: iastore
    //   1976: dup
    //   1977: bipush #33
    //   1979: ldc 1107296512
    //   1981: iastore
    //   1982: dup
    //   1983: bipush #34
    //   1985: sipush #256
    //   1988: iastore
    //   1989: dup
    //   1990: bipush #35
    //   1992: ldc 33554432
    //   1994: iastore
    //   1995: dup
    //   1996: bipush #36
    //   1998: ldc 1073741824
    //   2000: iastore
    //   2001: dup
    //   2002: bipush #37
    //   2004: ldc 34078720
    //   2006: iastore
    //   2007: dup
    //   2008: bipush #38
    //   2010: ldc 1107296512
    //   2012: iastore
    //   2013: dup
    //   2014: bipush #39
    //   2016: ldc 1074266368
    //   2018: iastore
    //   2019: dup
    //   2020: bipush #40
    //   2022: ldc 33554688
    //   2024: iastore
    //   2025: dup
    //   2026: bipush #41
    //   2028: ldc 1073741824
    //   2030: iastore
    //   2031: dup
    //   2032: bipush #42
    //   2034: ldc 1107820544
    //   2036: iastore
    //   2037: dup
    //   2038: bipush #43
    //   2040: ldc 34078976
    //   2042: iastore
    //   2043: dup
    //   2044: bipush #44
    //   2046: ldc 1074266368
    //   2048: iastore
    //   2049: dup
    //   2050: bipush #45
    //   2052: sipush #256
    //   2055: iastore
    //   2056: dup
    //   2057: bipush #46
    //   2059: ldc 33554432
    //   2061: iastore
    //   2062: dup
    //   2063: bipush #47
    //   2065: ldc 1107820544
    //   2067: iastore
    //   2068: dup
    //   2069: bipush #48
    //   2071: ldc 1107820800
    //   2073: iastore
    //   2074: dup
    //   2075: bipush #49
    //   2077: ldc 524544
    //   2079: iastore
    //   2080: dup
    //   2081: bipush #50
    //   2083: ldc 1107296256
    //   2085: iastore
    //   2086: dup
    //   2087: bipush #51
    //   2089: ldc 1107820800
    //   2091: iastore
    //   2092: dup
    //   2093: bipush #52
    //   2095: ldc 34078720
    //   2097: iastore
    //   2098: dup
    //   2099: bipush #53
    //   2101: iconst_0
    //   2102: iastore
    //   2103: dup
    //   2104: bipush #54
    //   2106: ldc 1074266112
    //   2108: iastore
    //   2109: dup
    //   2110: bipush #55
    //   2112: ldc 1107296256
    //   2114: iastore
    //   2115: dup
    //   2116: bipush #56
    //   2118: ldc 524544
    //   2120: iastore
    //   2121: dup
    //   2122: bipush #57
    //   2124: ldc 33554688
    //   2126: iastore
    //   2127: dup
    //   2128: bipush #58
    //   2130: ldc 1073742080
    //   2132: iastore
    //   2133: dup
    //   2134: bipush #59
    //   2136: ldc 524288
    //   2138: iastore
    //   2139: dup
    //   2140: bipush #60
    //   2142: iconst_0
    //   2143: iastore
    //   2144: dup
    //   2145: bipush #61
    //   2147: ldc 1074266112
    //   2149: iastore
    //   2150: dup
    //   2151: bipush #62
    //   2153: ldc 34078976
    //   2155: iastore
    //   2156: dup
    //   2157: bipush #63
    //   2159: ldc 1073742080
    //   2161: iastore
    //   2162: astore #10
    //   2164: bipush #64
    //   2166: newarray int
    //   2168: dup
    //   2169: iconst_0
    //   2170: ldc 536870928
    //   2172: iastore
    //   2173: dup
    //   2174: iconst_1
    //   2175: ldc 541065216
    //   2177: iastore
    //   2178: dup
    //   2179: iconst_2
    //   2180: sipush #16384
    //   2183: iastore
    //   2184: dup
    //   2185: iconst_3
    //   2186: ldc 541081616
    //   2188: iastore
    //   2189: dup
    //   2190: iconst_4
    //   2191: ldc 541065216
    //   2193: iastore
    //   2194: dup
    //   2195: iconst_5
    //   2196: bipush #16
    //   2198: iastore
    //   2199: dup
    //   2200: bipush #6
    //   2202: ldc 541081616
    //   2204: iastore
    //   2205: dup
    //   2206: bipush #7
    //   2208: ldc 4194304
    //   2210: iastore
    //   2211: dup
    //   2212: bipush #8
    //   2214: ldc 536887296
    //   2216: iastore
    //   2217: dup
    //   2218: bipush #9
    //   2220: ldc 4210704
    //   2222: iastore
    //   2223: dup
    //   2224: bipush #10
    //   2226: ldc 4194304
    //   2228: iastore
    //   2229: dup
    //   2230: bipush #11
    //   2232: ldc 536870928
    //   2234: iastore
    //   2235: dup
    //   2236: bipush #12
    //   2238: ldc 4194320
    //   2240: iastore
    //   2241: dup
    //   2242: bipush #13
    //   2244: ldc 536887296
    //   2246: iastore
    //   2247: dup
    //   2248: bipush #14
    //   2250: ldc 536870912
    //   2252: iastore
    //   2253: dup
    //   2254: bipush #15
    //   2256: sipush #16400
    //   2259: iastore
    //   2260: dup
    //   2261: bipush #16
    //   2263: iconst_0
    //   2264: iastore
    //   2265: dup
    //   2266: bipush #17
    //   2268: ldc 4194320
    //   2270: iastore
    //   2271: dup
    //   2272: bipush #18
    //   2274: ldc 536887312
    //   2276: iastore
    //   2277: dup
    //   2278: bipush #19
    //   2280: sipush #16384
    //   2283: iastore
    //   2284: dup
    //   2285: bipush #20
    //   2287: ldc 4210688
    //   2289: iastore
    //   2290: dup
    //   2291: bipush #21
    //   2293: ldc 536887312
    //   2295: iastore
    //   2296: dup
    //   2297: bipush #22
    //   2299: bipush #16
    //   2301: iastore
    //   2302: dup
    //   2303: bipush #23
    //   2305: ldc 541065232
    //   2307: iastore
    //   2308: dup
    //   2309: bipush #24
    //   2311: ldc 541065232
    //   2313: iastore
    //   2314: dup
    //   2315: bipush #25
    //   2317: iconst_0
    //   2318: iastore
    //   2319: dup
    //   2320: bipush #26
    //   2322: ldc 4210704
    //   2324: iastore
    //   2325: dup
    //   2326: bipush #27
    //   2328: ldc 541081600
    //   2330: iastore
    //   2331: dup
    //   2332: bipush #28
    //   2334: sipush #16400
    //   2337: iastore
    //   2338: dup
    //   2339: bipush #29
    //   2341: ldc 4210688
    //   2343: iastore
    //   2344: dup
    //   2345: bipush #30
    //   2347: ldc 541081600
    //   2349: iastore
    //   2350: dup
    //   2351: bipush #31
    //   2353: ldc 536870912
    //   2355: iastore
    //   2356: dup
    //   2357: bipush #32
    //   2359: ldc 536887296
    //   2361: iastore
    //   2362: dup
    //   2363: bipush #33
    //   2365: bipush #16
    //   2367: iastore
    //   2368: dup
    //   2369: bipush #34
    //   2371: ldc 541065232
    //   2373: iastore
    //   2374: dup
    //   2375: bipush #35
    //   2377: ldc 4210688
    //   2379: iastore
    //   2380: dup
    //   2381: bipush #36
    //   2383: ldc 541081616
    //   2385: iastore
    //   2386: dup
    //   2387: bipush #37
    //   2389: ldc 4194304
    //   2391: iastore
    //   2392: dup
    //   2393: bipush #38
    //   2395: sipush #16400
    //   2398: iastore
    //   2399: dup
    //   2400: bipush #39
    //   2402: ldc 536870928
    //   2404: iastore
    //   2405: dup
    //   2406: bipush #40
    //   2408: ldc 4194304
    //   2410: iastore
    //   2411: dup
    //   2412: bipush #41
    //   2414: ldc 536887296
    //   2416: iastore
    //   2417: dup
    //   2418: bipush #42
    //   2420: ldc 536870912
    //   2422: iastore
    //   2423: dup
    //   2424: bipush #43
    //   2426: sipush #16400
    //   2429: iastore
    //   2430: dup
    //   2431: bipush #44
    //   2433: ldc 536870928
    //   2435: iastore
    //   2436: dup
    //   2437: bipush #45
    //   2439: ldc 541081616
    //   2441: iastore
    //   2442: dup
    //   2443: bipush #46
    //   2445: ldc 4210688
    //   2447: iastore
    //   2448: dup
    //   2449: bipush #47
    //   2451: ldc 541065216
    //   2453: iastore
    //   2454: dup
    //   2455: bipush #48
    //   2457: ldc 4210704
    //   2459: iastore
    //   2460: dup
    //   2461: bipush #49
    //   2463: ldc 541081600
    //   2465: iastore
    //   2466: dup
    //   2467: bipush #50
    //   2469: iconst_0
    //   2470: iastore
    //   2471: dup
    //   2472: bipush #51
    //   2474: ldc 541065232
    //   2476: iastore
    //   2477: dup
    //   2478: bipush #52
    //   2480: bipush #16
    //   2482: iastore
    //   2483: dup
    //   2484: bipush #53
    //   2486: sipush #16384
    //   2489: iastore
    //   2490: dup
    //   2491: bipush #54
    //   2493: ldc 541065216
    //   2495: iastore
    //   2496: dup
    //   2497: bipush #55
    //   2499: ldc 4210704
    //   2501: iastore
    //   2502: dup
    //   2503: bipush #56
    //   2505: sipush #16384
    //   2508: iastore
    //   2509: dup
    //   2510: bipush #57
    //   2512: ldc 4194320
    //   2514: iastore
    //   2515: dup
    //   2516: bipush #58
    //   2518: ldc 536887312
    //   2520: iastore
    //   2521: dup
    //   2522: bipush #59
    //   2524: iconst_0
    //   2525: iastore
    //   2526: dup
    //   2527: bipush #60
    //   2529: ldc 541081600
    //   2531: iastore
    //   2532: dup
    //   2533: bipush #61
    //   2535: ldc 536870912
    //   2537: iastore
    //   2538: dup
    //   2539: bipush #62
    //   2541: ldc 4194320
    //   2543: iastore
    //   2544: dup
    //   2545: bipush #63
    //   2547: ldc 536887312
    //   2549: iastore
    //   2550: astore #11
    //   2552: bipush #64
    //   2554: newarray int
    //   2556: dup
    //   2557: iconst_0
    //   2558: ldc 2097152
    //   2560: iastore
    //   2561: dup
    //   2562: iconst_1
    //   2563: ldc 69206018
    //   2565: iastore
    //   2566: dup
    //   2567: iconst_2
    //   2568: ldc 67110914
    //   2570: iastore
    //   2571: dup
    //   2572: iconst_3
    //   2573: iconst_0
    //   2574: iastore
    //   2575: dup
    //   2576: iconst_4
    //   2577: sipush #2048
    //   2580: iastore
    //   2581: dup
    //   2582: iconst_5
    //   2583: ldc 67110914
    //   2585: iastore
    //   2586: dup
    //   2587: bipush #6
    //   2589: ldc 2099202
    //   2591: iastore
    //   2592: dup
    //   2593: bipush #7
    //   2595: ldc 69208064
    //   2597: iastore
    //   2598: dup
    //   2599: bipush #8
    //   2601: ldc 69208066
    //   2603: iastore
    //   2604: dup
    //   2605: bipush #9
    //   2607: ldc 2097152
    //   2609: iastore
    //   2610: dup
    //   2611: bipush #10
    //   2613: iconst_0
    //   2614: iastore
    //   2615: dup
    //   2616: bipush #11
    //   2618: ldc 67108866
    //   2620: iastore
    //   2621: dup
    //   2622: bipush #12
    //   2624: iconst_2
    //   2625: iastore
    //   2626: dup
    //   2627: bipush #13
    //   2629: ldc 67108864
    //   2631: iastore
    //   2632: dup
    //   2633: bipush #14
    //   2635: ldc 69206018
    //   2637: iastore
    //   2638: dup
    //   2639: bipush #15
    //   2641: sipush #2050
    //   2644: iastore
    //   2645: dup
    //   2646: bipush #16
    //   2648: ldc 67110912
    //   2650: iastore
    //   2651: dup
    //   2652: bipush #17
    //   2654: ldc 2099202
    //   2656: iastore
    //   2657: dup
    //   2658: bipush #18
    //   2660: ldc 2097154
    //   2662: iastore
    //   2663: dup
    //   2664: bipush #19
    //   2666: ldc 67110912
    //   2668: iastore
    //   2669: dup
    //   2670: bipush #20
    //   2672: ldc 67108866
    //   2674: iastore
    //   2675: dup
    //   2676: bipush #21
    //   2678: ldc 69206016
    //   2680: iastore
    //   2681: dup
    //   2682: bipush #22
    //   2684: ldc 69208064
    //   2686: iastore
    //   2687: dup
    //   2688: bipush #23
    //   2690: ldc 2097154
    //   2692: iastore
    //   2693: dup
    //   2694: bipush #24
    //   2696: ldc 69206016
    //   2698: iastore
    //   2699: dup
    //   2700: bipush #25
    //   2702: sipush #2048
    //   2705: iastore
    //   2706: dup
    //   2707: bipush #26
    //   2709: sipush #2050
    //   2712: iastore
    //   2713: dup
    //   2714: bipush #27
    //   2716: ldc 69208066
    //   2718: iastore
    //   2719: dup
    //   2720: bipush #28
    //   2722: ldc 2099200
    //   2724: iastore
    //   2725: dup
    //   2726: bipush #29
    //   2728: iconst_2
    //   2729: iastore
    //   2730: dup
    //   2731: bipush #30
    //   2733: ldc 67108864
    //   2735: iastore
    //   2736: dup
    //   2737: bipush #31
    //   2739: ldc 2099200
    //   2741: iastore
    //   2742: dup
    //   2743: bipush #32
    //   2745: ldc 67108864
    //   2747: iastore
    //   2748: dup
    //   2749: bipush #33
    //   2751: ldc 2099200
    //   2753: iastore
    //   2754: dup
    //   2755: bipush #34
    //   2757: ldc 2097152
    //   2759: iastore
    //   2760: dup
    //   2761: bipush #35
    //   2763: ldc 67110914
    //   2765: iastore
    //   2766: dup
    //   2767: bipush #36
    //   2769: ldc 67110914
    //   2771: iastore
    //   2772: dup
    //   2773: bipush #37
    //   2775: ldc 69206018
    //   2777: iastore
    //   2778: dup
    //   2779: bipush #38
    //   2781: ldc 69206018
    //   2783: iastore
    //   2784: dup
    //   2785: bipush #39
    //   2787: iconst_2
    //   2788: iastore
    //   2789: dup
    //   2790: bipush #40
    //   2792: ldc 2097154
    //   2794: iastore
    //   2795: dup
    //   2796: bipush #41
    //   2798: ldc 67108864
    //   2800: iastore
    //   2801: dup
    //   2802: bipush #42
    //   2804: ldc 67110912
    //   2806: iastore
    //   2807: dup
    //   2808: bipush #43
    //   2810: ldc 2097152
    //   2812: iastore
    //   2813: dup
    //   2814: bipush #44
    //   2816: ldc 69208064
    //   2818: iastore
    //   2819: dup
    //   2820: bipush #45
    //   2822: sipush #2050
    //   2825: iastore
    //   2826: dup
    //   2827: bipush #46
    //   2829: ldc 2099202
    //   2831: iastore
    //   2832: dup
    //   2833: bipush #47
    //   2835: ldc 69208064
    //   2837: iastore
    //   2838: dup
    //   2839: bipush #48
    //   2841: sipush #2050
    //   2844: iastore
    //   2845: dup
    //   2846: bipush #49
    //   2848: ldc 67108866
    //   2850: iastore
    //   2851: dup
    //   2852: bipush #50
    //   2854: ldc 69208066
    //   2856: iastore
    //   2857: dup
    //   2858: bipush #51
    //   2860: ldc 69206016
    //   2862: iastore
    //   2863: dup
    //   2864: bipush #52
    //   2866: ldc 2099200
    //   2868: iastore
    //   2869: dup
    //   2870: bipush #53
    //   2872: iconst_0
    //   2873: iastore
    //   2874: dup
    //   2875: bipush #54
    //   2877: iconst_2
    //   2878: iastore
    //   2879: dup
    //   2880: bipush #55
    //   2882: ldc 69208066
    //   2884: iastore
    //   2885: dup
    //   2886: bipush #56
    //   2888: iconst_0
    //   2889: iastore
    //   2890: dup
    //   2891: bipush #57
    //   2893: ldc 2099202
    //   2895: iastore
    //   2896: dup
    //   2897: bipush #58
    //   2899: ldc 69206016
    //   2901: iastore
    //   2902: dup
    //   2903: bipush #59
    //   2905: sipush #2048
    //   2908: iastore
    //   2909: dup
    //   2910: bipush #60
    //   2912: ldc 67108866
    //   2914: iastore
    //   2915: dup
    //   2916: bipush #61
    //   2918: ldc 67110912
    //   2920: iastore
    //   2921: dup
    //   2922: bipush #62
    //   2924: sipush #2048
    //   2927: iastore
    //   2928: dup
    //   2929: bipush #63
    //   2931: ldc 2097154
    //   2933: iastore
    //   2934: astore #12
    //   2936: bipush #64
    //   2938: newarray int
    //   2940: dup
    //   2941: iconst_0
    //   2942: ldc 268439616
    //   2944: iastore
    //   2945: dup
    //   2946: iconst_1
    //   2947: sipush #4096
    //   2950: iastore
    //   2951: dup
    //   2952: iconst_2
    //   2953: ldc 262144
    //   2955: iastore
    //   2956: dup
    //   2957: iconst_3
    //   2958: ldc 268701760
    //   2960: iastore
    //   2961: dup
    //   2962: iconst_4
    //   2963: ldc 268435456
    //   2965: iastore
    //   2966: dup
    //   2967: iconst_5
    //   2968: ldc 268439616
    //   2970: iastore
    //   2971: dup
    //   2972: bipush #6
    //   2974: bipush #64
    //   2976: iastore
    //   2977: dup
    //   2978: bipush #7
    //   2980: ldc 268435456
    //   2982: iastore
    //   2983: dup
    //   2984: bipush #8
    //   2986: ldc 262208
    //   2988: iastore
    //   2989: dup
    //   2990: bipush #9
    //   2992: ldc 268697600
    //   2994: iastore
    //   2995: dup
    //   2996: bipush #10
    //   2998: ldc 268701760
    //   3000: iastore
    //   3001: dup
    //   3002: bipush #11
    //   3004: ldc 266240
    //   3006: iastore
    //   3007: dup
    //   3008: bipush #12
    //   3010: ldc 268701696
    //   3012: iastore
    //   3013: dup
    //   3014: bipush #13
    //   3016: ldc 266304
    //   3018: iastore
    //   3019: dup
    //   3020: bipush #14
    //   3022: sipush #4096
    //   3025: iastore
    //   3026: dup
    //   3027: bipush #15
    //   3029: bipush #64
    //   3031: iastore
    //   3032: dup
    //   3033: bipush #16
    //   3035: ldc 268697600
    //   3037: iastore
    //   3038: dup
    //   3039: bipush #17
    //   3041: ldc 268435520
    //   3043: iastore
    //   3044: dup
    //   3045: bipush #18
    //   3047: ldc 268439552
    //   3049: iastore
    //   3050: dup
    //   3051: bipush #19
    //   3053: sipush #4160
    //   3056: iastore
    //   3057: dup
    //   3058: bipush #20
    //   3060: ldc 266240
    //   3062: iastore
    //   3063: dup
    //   3064: bipush #21
    //   3066: ldc 262208
    //   3068: iastore
    //   3069: dup
    //   3070: bipush #22
    //   3072: ldc 268697664
    //   3074: iastore
    //   3075: dup
    //   3076: bipush #23
    //   3078: ldc 268701696
    //   3080: iastore
    //   3081: dup
    //   3082: bipush #24
    //   3084: sipush #4160
    //   3087: iastore
    //   3088: dup
    //   3089: bipush #25
    //   3091: iconst_0
    //   3092: iastore
    //   3093: dup
    //   3094: bipush #26
    //   3096: iconst_0
    //   3097: iastore
    //   3098: dup
    //   3099: bipush #27
    //   3101: ldc 268697664
    //   3103: iastore
    //   3104: dup
    //   3105: bipush #28
    //   3107: ldc 268435520
    //   3109: iastore
    //   3110: dup
    //   3111: bipush #29
    //   3113: ldc 268439552
    //   3115: iastore
    //   3116: dup
    //   3117: bipush #30
    //   3119: ldc 266304
    //   3121: iastore
    //   3122: dup
    //   3123: bipush #31
    //   3125: ldc 262144
    //   3127: iastore
    //   3128: dup
    //   3129: bipush #32
    //   3131: ldc 266304
    //   3133: iastore
    //   3134: dup
    //   3135: bipush #33
    //   3137: ldc 262144
    //   3139: iastore
    //   3140: dup
    //   3141: bipush #34
    //   3143: ldc 268701696
    //   3145: iastore
    //   3146: dup
    //   3147: bipush #35
    //   3149: sipush #4096
    //   3152: iastore
    //   3153: dup
    //   3154: bipush #36
    //   3156: bipush #64
    //   3158: iastore
    //   3159: dup
    //   3160: bipush #37
    //   3162: ldc 268697664
    //   3164: iastore
    //   3165: dup
    //   3166: bipush #38
    //   3168: sipush #4096
    //   3171: iastore
    //   3172: dup
    //   3173: bipush #39
    //   3175: ldc 266304
    //   3177: iastore
    //   3178: dup
    //   3179: bipush #40
    //   3181: ldc 268439552
    //   3183: iastore
    //   3184: dup
    //   3185: bipush #41
    //   3187: bipush #64
    //   3189: iastore
    //   3190: dup
    //   3191: bipush #42
    //   3193: ldc 268435520
    //   3195: iastore
    //   3196: dup
    //   3197: bipush #43
    //   3199: ldc 268697600
    //   3201: iastore
    //   3202: dup
    //   3203: bipush #44
    //   3205: ldc 268697664
    //   3207: iastore
    //   3208: dup
    //   3209: bipush #45
    //   3211: ldc 268435456
    //   3213: iastore
    //   3214: dup
    //   3215: bipush #46
    //   3217: ldc 262144
    //   3219: iastore
    //   3220: dup
    //   3221: bipush #47
    //   3223: ldc 268439616
    //   3225: iastore
    //   3226: dup
    //   3227: bipush #48
    //   3229: iconst_0
    //   3230: iastore
    //   3231: dup
    //   3232: bipush #49
    //   3234: ldc 268701760
    //   3236: iastore
    //   3237: dup
    //   3238: bipush #50
    //   3240: ldc 262208
    //   3242: iastore
    //   3243: dup
    //   3244: bipush #51
    //   3246: ldc 268435520
    //   3248: iastore
    //   3249: dup
    //   3250: bipush #52
    //   3252: ldc 268697600
    //   3254: iastore
    //   3255: dup
    //   3256: bipush #53
    //   3258: ldc 268439552
    //   3260: iastore
    //   3261: dup
    //   3262: bipush #54
    //   3264: ldc 268439616
    //   3266: iastore
    //   3267: dup
    //   3268: bipush #55
    //   3270: iconst_0
    //   3271: iastore
    //   3272: dup
    //   3273: bipush #56
    //   3275: ldc 268701760
    //   3277: iastore
    //   3278: dup
    //   3279: bipush #57
    //   3281: ldc 266240
    //   3283: iastore
    //   3284: dup
    //   3285: bipush #58
    //   3287: ldc 266240
    //   3289: iastore
    //   3290: dup
    //   3291: bipush #59
    //   3293: sipush #4160
    //   3296: iastore
    //   3297: dup
    //   3298: bipush #60
    //   3300: sipush #4160
    //   3303: iastore
    //   3304: dup
    //   3305: bipush #61
    //   3307: ldc 262208
    //   3309: iastore
    //   3310: dup
    //   3311: bipush #62
    //   3313: ldc 268435456
    //   3315: iastore
    //   3316: dup
    //   3317: bipush #63
    //   3319: ldc 268701696
    //   3321: iastore
    //   3322: astore #13
    //   3324: aload_3
    //   3325: arraylength
    //   3326: istore #14
    //   3328: iload #14
    //   3330: bipush #8
    //   3332: irem
    //   3333: ifeq -> 3357
    //   3336: new java/lang/Exception
    //   3339: dup
    //   3340: sipush #2731
    //   3343: sipush #-3511
    //   3346: invokestatic a : (II)Ljava/lang/String;
    //   3349: invokespecial <init> : (Ljava/lang/String;)V
    //   3352: athrow
    //   3353: invokestatic a : (Ljava/lang/Throwable;)Ljava/lang/Throwable;
    //   3356: athrow
    //   3357: iconst_2
    //   3358: newarray int
    //   3360: astore #15
    //   3362: iload #14
    //   3364: newarray byte
    //   3366: astore #16
    //   3368: iload #14
    //   3370: bipush #8
    //   3372: idiv
    //   3373: istore #17
    //   3375: iconst_0
    //   3376: istore #18
    //   3378: iload #18
    //   3380: iload #17
    //   3382: if_icmpge -> 4296
    //   3385: iload #18
    //   3387: bipush #8
    //   3389: imul
    //   3390: istore #19
    //   3392: iconst_0
    //   3393: istore #20
    //   3395: iload #20
    //   3397: iconst_2
    //   3398: if_icmpge -> 3483
    //   3401: aload #15
    //   3403: iload #20
    //   3405: aload_3
    //   3406: iload #19
    //   3408: iload #20
    //   3410: iconst_4
    //   3411: imul
    //   3412: iadd
    //   3413: baload
    //   3414: sipush #255
    //   3417: iand
    //   3418: bipush #24
    //   3420: ishl
    //   3421: aload_3
    //   3422: iload #19
    //   3424: iload #20
    //   3426: iconst_4
    //   3427: imul
    //   3428: iadd
    //   3429: iconst_1
    //   3430: iadd
    //   3431: baload
    //   3432: sipush #255
    //   3435: iand
    //   3436: bipush #16
    //   3438: ishl
    //   3439: ior
    //   3440: aload_3
    //   3441: iload #19
    //   3443: iload #20
    //   3445: iconst_4
    //   3446: imul
    //   3447: iadd
    //   3448: iconst_2
    //   3449: iadd
    //   3450: baload
    //   3451: sipush #255
    //   3454: iand
    //   3455: bipush #8
    //   3457: ishl
    //   3458: ior
    //   3459: aload_3
    //   3460: iload #19
    //   3462: iload #20
    //   3464: iconst_4
    //   3465: imul
    //   3466: iadd
    //   3467: iconst_3
    //   3468: iadd
    //   3469: baload
    //   3470: sipush #255
    //   3473: iand
    //   3474: ior
    //   3475: iastore
    //   3476: iinc #20, 1
    //   3479: iload_2
    //   3480: ifne -> 3395
    //   3483: iconst_0
    //   3484: istore #25
    //   3486: aload #15
    //   3488: iconst_0
    //   3489: iaload
    //   3490: istore #23
    //   3492: aload #15
    //   3494: iconst_1
    //   3495: iaload
    //   3496: istore #22
    //   3498: iload #23
    //   3500: iconst_4
    //   3501: iushr
    //   3502: iload #22
    //   3504: ixor
    //   3505: ldc 252645135
    //   3507: iand
    //   3508: istore #21
    //   3510: iload #22
    //   3512: iload #21
    //   3514: ixor
    //   3515: istore #22
    //   3517: iload #23
    //   3519: iload #21
    //   3521: iconst_4
    //   3522: ishl
    //   3523: ixor
    //   3524: istore #23
    //   3526: iload #23
    //   3528: bipush #16
    //   3530: iushr
    //   3531: iload #22
    //   3533: ixor
    //   3534: ldc 65535
    //   3536: iand
    //   3537: istore #21
    //   3539: iload #22
    //   3541: iload #21
    //   3543: ixor
    //   3544: istore #22
    //   3546: iload #23
    //   3548: iload #21
    //   3550: bipush #16
    //   3552: ishl
    //   3553: ixor
    //   3554: istore #23
    //   3556: iload #22
    //   3558: iconst_2
    //   3559: iushr
    //   3560: iload #23
    //   3562: ixor
    //   3563: ldc 858993459
    //   3565: iand
    //   3566: istore #21
    //   3568: iload #23
    //   3570: iload #21
    //   3572: ixor
    //   3573: istore #23
    //   3575: iload #22
    //   3577: iload #21
    //   3579: iconst_2
    //   3580: ishl
    //   3581: ixor
    //   3582: istore #22
    //   3584: iload #22
    //   3586: bipush #8
    //   3588: iushr
    //   3589: iload #23
    //   3591: ixor
    //   3592: ldc 16711935
    //   3594: iand
    //   3595: istore #21
    //   3597: iload #23
    //   3599: iload #21
    //   3601: ixor
    //   3602: istore #23
    //   3604: iload #22
    //   3606: iload #21
    //   3608: bipush #8
    //   3610: ishl
    //   3611: ixor
    //   3612: istore #22
    //   3614: iload #22
    //   3616: iconst_1
    //   3617: ishl
    //   3618: iload #22
    //   3620: bipush #31
    //   3622: iushr
    //   3623: iconst_1
    //   3624: iand
    //   3625: ior
    //   3626: istore #22
    //   3628: iload #23
    //   3630: iload #22
    //   3632: ixor
    //   3633: ldc -1431655766
    //   3635: iand
    //   3636: istore #21
    //   3638: iload #23
    //   3640: iload #21
    //   3642: ixor
    //   3643: istore #23
    //   3645: iload #22
    //   3647: iload #21
    //   3649: ixor
    //   3650: istore #22
    //   3652: iload #23
    //   3654: iconst_1
    //   3655: ishl
    //   3656: iload #23
    //   3658: bipush #31
    //   3660: iushr
    //   3661: iconst_1
    //   3662: iand
    //   3663: ior
    //   3664: istore #23
    //   3666: iconst_0
    //   3667: istore #24
    //   3669: iload #24
    //   3671: bipush #8
    //   3673: if_icmpge -> 4011
    //   3676: iload #22
    //   3678: bipush #28
    //   3680: ishl
    //   3681: iload #22
    //   3683: iconst_4
    //   3684: iushr
    //   3685: ior
    //   3686: istore #21
    //   3688: iload #21
    //   3690: aload #5
    //   3692: iload #25
    //   3694: iinc #25, 1
    //   3697: iaload
    //   3698: ixor
    //   3699: istore #21
    //   3701: aload #12
    //   3703: iload #21
    //   3705: bipush #63
    //   3707: iand
    //   3708: iaload
    //   3709: istore #20
    //   3711: iload #20
    //   3713: aload #10
    //   3715: iload #21
    //   3717: bipush #8
    //   3719: iushr
    //   3720: bipush #63
    //   3722: iand
    //   3723: iaload
    //   3724: ior
    //   3725: istore #20
    //   3727: iload #20
    //   3729: aload #8
    //   3731: iload #21
    //   3733: bipush #16
    //   3735: iushr
    //   3736: bipush #63
    //   3738: iand
    //   3739: iaload
    //   3740: ior
    //   3741: istore #20
    //   3743: iload #20
    //   3745: aload #6
    //   3747: iload #21
    //   3749: bipush #24
    //   3751: iushr
    //   3752: bipush #63
    //   3754: iand
    //   3755: iaload
    //   3756: ior
    //   3757: istore #20
    //   3759: iload #22
    //   3761: aload #5
    //   3763: iload #25
    //   3765: iinc #25, 1
    //   3768: iaload
    //   3769: ixor
    //   3770: istore #21
    //   3772: iload #20
    //   3774: aload #13
    //   3776: iload #21
    //   3778: bipush #63
    //   3780: iand
    //   3781: iaload
    //   3782: ior
    //   3783: istore #20
    //   3785: iload #20
    //   3787: aload #11
    //   3789: iload #21
    //   3791: bipush #8
    //   3793: iushr
    //   3794: bipush #63
    //   3796: iand
    //   3797: iaload
    //   3798: ior
    //   3799: istore #20
    //   3801: iload #20
    //   3803: aload #9
    //   3805: iload #21
    //   3807: bipush #16
    //   3809: iushr
    //   3810: bipush #63
    //   3812: iand
    //   3813: iaload
    //   3814: ior
    //   3815: istore #20
    //   3817: iload #20
    //   3819: aload #7
    //   3821: iload #21
    //   3823: bipush #24
    //   3825: iushr
    //   3826: bipush #63
    //   3828: iand
    //   3829: iaload
    //   3830: ior
    //   3831: istore #20
    //   3833: iload #23
    //   3835: iload #20
    //   3837: ixor
    //   3838: istore #23
    //   3840: iload #23
    //   3842: bipush #28
    //   3844: ishl
    //   3845: iload #23
    //   3847: iconst_4
    //   3848: iushr
    //   3849: ior
    //   3850: istore #21
    //   3852: iload #21
    //   3854: aload #5
    //   3856: iload #25
    //   3858: iinc #25, 1
    //   3861: iaload
    //   3862: ixor
    //   3863: istore #21
    //   3865: aload #12
    //   3867: iload #21
    //   3869: bipush #63
    //   3871: iand
    //   3872: iaload
    //   3873: istore #20
    //   3875: iload #20
    //   3877: aload #10
    //   3879: iload #21
    //   3881: bipush #8
    //   3883: iushr
    //   3884: bipush #63
    //   3886: iand
    //   3887: iaload
    //   3888: ior
    //   3889: istore #20
    //   3891: iload #20
    //   3893: aload #8
    //   3895: iload #21
    //   3897: bipush #16
    //   3899: iushr
    //   3900: bipush #63
    //   3902: iand
    //   3903: iaload
    //   3904: ior
    //   3905: istore #20
    //   3907: iload #20
    //   3909: aload #6
    //   3911: iload #21
    //   3913: bipush #24
    //   3915: iushr
    //   3916: bipush #63
    //   3918: iand
    //   3919: iaload
    //   3920: ior
    //   3921: istore #20
    //   3923: iload #23
    //   3925: aload #5
    //   3927: iload #25
    //   3929: iinc #25, 1
    //   3932: iaload
    //   3933: ixor
    //   3934: istore #21
    //   3936: iload #20
    //   3938: aload #13
    //   3940: iload #21
    //   3942: bipush #63
    //   3944: iand
    //   3945: iaload
    //   3946: ior
    //   3947: istore #20
    //   3949: iload #20
    //   3951: aload #11
    //   3953: iload #21
    //   3955: bipush #8
    //   3957: iushr
    //   3958: bipush #63
    //   3960: iand
    //   3961: iaload
    //   3962: ior
    //   3963: istore #20
    //   3965: iload #20
    //   3967: aload #9
    //   3969: iload #21
    //   3971: bipush #16
    //   3973: iushr
    //   3974: bipush #63
    //   3976: iand
    //   3977: iaload
    //   3978: ior
    //   3979: istore #20
    //   3981: iload #20
    //   3983: aload #7
    //   3985: iload #21
    //   3987: bipush #24
    //   3989: iushr
    //   3990: bipush #63
    //   3992: iand
    //   3993: iaload
    //   3994: ior
    //   3995: istore #20
    //   3997: iload #22
    //   3999: iload #20
    //   4001: ixor
    //   4002: istore #22
    //   4004: iinc #24, 1
    //   4007: iload_2
    //   4008: ifne -> 3669
    //   4011: iload #22
    //   4013: bipush #31
    //   4015: ishl
    //   4016: iload #22
    //   4018: iconst_1
    //   4019: iushr
    //   4020: ior
    //   4021: istore #22
    //   4023: iload #23
    //   4025: iload #22
    //   4027: ixor
    //   4028: ldc -1431655766
    //   4030: iand
    //   4031: istore #21
    //   4033: iload #23
    //   4035: iload #21
    //   4037: ixor
    //   4038: istore #23
    //   4040: iload #22
    //   4042: iload #21
    //   4044: ixor
    //   4045: istore #22
    //   4047: iload #23
    //   4049: bipush #31
    //   4051: ishl
    //   4052: iload #23
    //   4054: iconst_1
    //   4055: iushr
    //   4056: ior
    //   4057: istore #23
    //   4059: iload #23
    //   4061: bipush #8
    //   4063: iushr
    //   4064: iload #22
    //   4066: ixor
    //   4067: ldc 16711935
    //   4069: iand
    //   4070: istore #21
    //   4072: iload #22
    //   4074: iload #21
    //   4076: ixor
    //   4077: istore #22
    //   4079: iload #23
    //   4081: iload #21
    //   4083: bipush #8
    //   4085: ishl
    //   4086: ixor
    //   4087: istore #23
    //   4089: iload #23
    //   4091: iconst_2
    //   4092: iushr
    //   4093: iload #22
    //   4095: ixor
    //   4096: ldc 858993459
    //   4098: iand
    //   4099: istore #21
    //   4101: iload #22
    //   4103: iload #21
    //   4105: ixor
    //   4106: istore #22
    //   4108: iload #23
    //   4110: iload #21
    //   4112: iconst_2
    //   4113: ishl
    //   4114: ixor
    //   4115: istore #23
    //   4117: iload #22
    //   4119: bipush #16
    //   4121: iushr
    //   4122: iload #23
    //   4124: ixor
    //   4125: ldc 65535
    //   4127: iand
    //   4128: istore #21
    //   4130: iload #23
    //   4132: iload #21
    //   4134: ixor
    //   4135: istore #23
    //   4137: iload #22
    //   4139: iload #21
    //   4141: bipush #16
    //   4143: ishl
    //   4144: ixor
    //   4145: istore #22
    //   4147: iload #22
    //   4149: iconst_4
    //   4150: iushr
    //   4151: iload #23
    //   4153: ixor
    //   4154: ldc 252645135
    //   4156: iand
    //   4157: istore #21
    //   4159: iload #23
    //   4161: iload #21
    //   4163: ixor
    //   4164: istore #23
    //   4166: iload #22
    //   4168: iload #21
    //   4170: iconst_4
    //   4171: ishl
    //   4172: ixor
    //   4173: istore #22
    //   4175: aload #15
    //   4177: iconst_0
    //   4178: iload #22
    //   4180: iastore
    //   4181: aload #15
    //   4183: iconst_1
    //   4184: iload #23
    //   4186: iastore
    //   4187: iload #18
    //   4189: bipush #8
    //   4191: imul
    //   4192: istore #26
    //   4194: iconst_0
    //   4195: istore #27
    //   4197: iload #27
    //   4199: iconst_2
    //   4200: if_icmpge -> 4289
    //   4203: aload #16
    //   4205: iload #26
    //   4207: iload #27
    //   4209: iconst_4
    //   4210: imul
    //   4211: iadd
    //   4212: aload #15
    //   4214: iload #27
    //   4216: iaload
    //   4217: bipush #24
    //   4219: iushr
    //   4220: i2b
    //   4221: bastore
    //   4222: aload #16
    //   4224: iload #26
    //   4226: iload #27
    //   4228: iconst_4
    //   4229: imul
    //   4230: iadd
    //   4231: iconst_1
    //   4232: iadd
    //   4233: aload #15
    //   4235: iload #27
    //   4237: iaload
    //   4238: bipush #16
    //   4240: iushr
    //   4241: i2b
    //   4242: bastore
    //   4243: aload #16
    //   4245: iload #26
    //   4247: iload #27
    //   4249: iconst_4
    //   4250: imul
    //   4251: iadd
    //   4252: iconst_2
    //   4253: iadd
    //   4254: aload #15
    //   4256: iload #27
    //   4258: iaload
    //   4259: bipush #8
    //   4261: iushr
    //   4262: i2b
    //   4263: bastore
    //   4264: aload #16
    //   4266: iload #26
    //   4268: iload #27
    //   4270: iconst_4
    //   4271: imul
    //   4272: iadd
    //   4273: iconst_3
    //   4274: iadd
    //   4275: aload #15
    //   4277: iload #27
    //   4279: iaload
    //   4280: i2b
    //   4281: bastore
    //   4282: iinc #27, 1
    //   4285: iload_2
    //   4286: ifne -> 4197
    //   4289: iinc #18, 1
    //   4292: iload_2
    //   4293: ifne -> 3378
    //   4296: aload #16
    //   4298: aload #16
    //   4300: arraylength
    //   4301: iconst_1
    //   4302: isub
    //   4303: baload
    //   4304: istore #18
    //   4306: aload #16
    //   4308: arraylength
    //   4309: iload #18
    //   4311: isub
    //   4312: newarray byte
    //   4314: astore #4
    //   4316: aload #16
    //   4318: arraylength
    //   4319: aload #4
    //   4321: arraylength
    //   4322: if_icmpge -> 4346
    //   4325: new java/lang/Exception
    //   4328: dup
    //   4329: sipush #2725
    //   4332: sipush #-17839
    //   4335: invokestatic a : (II)Ljava/lang/String;
    //   4338: invokespecial <init> : (Ljava/lang/String;)V
    //   4341: athrow
    //   4342: invokestatic a : (Ljava/lang/Throwable;)Ljava/lang/Throwable;
    //   4345: athrow
    //   4346: iconst_0
    //   4347: istore #19
    //   4349: iload #19
    //   4351: aload #4
    //   4353: arraylength
    //   4354: if_icmpge -> 4374
    //   4357: aload #4
    //   4359: iload #19
    //   4361: aload #16
    //   4363: iload #19
    //   4365: baload
    //   4366: bastore
    //   4367: iinc #19, 1
    //   4370: iload_2
    //   4371: ifne -> 4349
    //   4374: new java/math/BigInteger
    //   4377: dup
    //   4378: aload #4
    //   4380: invokespecial <init> : ([B)V
    //   4383: invokevirtual abs : ()Ljava/math/BigInteger;
    //   4386: putstatic burp/Zl1u.Zq : Ljava/lang/Object;
    //   4389: new java/lang/StringBuilder
    //   4392: dup
    //   4393: invokespecial <init> : ()V
    //   4396: astore_3
    //   4397: iconst_0
    //   4398: istore #4
    //   4400: iload #4
    //   4402: bipush #32
    //   4404: if_icmpge -> 5739
    //   4407: iload #4
    //   4409: tableswitch default -> 5732, 0 -> 4552, 1 -> 4589, 2 -> 4626, 3 -> 4663, 4 -> 4700, 5 -> 4737, 6 -> 4774, 7 -> 4811, 8 -> 4848, 9 -> 4885, 10 -> 4922, 11 -> 4959, 12 -> 4996, 13 -> 5033, 14 -> 5070, 15 -> 5107, 16 -> 5144, 17 -> 5181, 18 -> 5218, 19 -> 5255, 20 -> 5292, 21 -> 5329, 22 -> 5366, 23 -> 5403, 24 -> 5440, 25 -> 5477, 26 -> 5514, 27 -> 5551, 28 -> 5588, 29 -> 5625, 30 -> 5662, 31 -> 5699
    //   4552: aload_3
    //   4553: getstatic burp/Zls0.ZI : Ljava/lang/String;
    //   4556: getstatic burp/Zeh9.ZY : Ljava/lang/Object;
    //   4559: checkcast java/math/BigInteger
    //   4562: invokevirtual intValue : ()I
    //   4565: bipush #32
    //   4567: irem
    //   4568: invokestatic abs : (I)I
    //   4571: invokevirtual charAt : (I)C
    //   4574: invokevirtual append : (C)Ljava/lang/StringBuilder;
    //   4577: pop
    //   4578: iload_2
    //   4579: ifne -> 5732
    //   4582: goto -> 4589
    //   4585: invokestatic a : (Ljava/lang/Throwable;)Ljava/lang/Throwable;
    //   4588: athrow
    //   4589: aload_3
    //   4590: getstatic burp/Zzbr.Zp : Ljava/lang/String;
    //   4593: getstatic burp/Zex.ZO : Ljava/lang/Object;
    //   4596: checkcast java/math/BigInteger
    //   4599: invokevirtual intValue : ()I
    //   4602: bipush #32
    //   4604: irem
    //   4605: invokestatic abs : (I)I
    //   4608: invokevirtual charAt : (I)C
    //   4611: invokevirtual append : (C)Ljava/lang/StringBuilder;
    //   4614: pop
    //   4615: iload_2
    //   4616: ifne -> 5732
    //   4619: goto -> 4626
    //   4622: invokestatic a : (Ljava/lang/Throwable;)Ljava/lang/Throwable;
    //   4625: athrow
    //   4626: aload_3
    //   4627: getstatic burp/Zxn7.ZG : Ljava/lang/String;
    //   4630: getstatic burp/Ztjh.ZU : Ljava/lang/Object;
    //   4633: checkcast java/math/BigInteger
    //   4636: invokevirtual intValue : ()I
    //   4639: bipush #32
    //   4641: irem
    //   4642: invokestatic abs : (I)I
    //   4645: invokevirtual charAt : (I)C
    //   4648: invokevirtual append : (C)Ljava/lang/StringBuilder;
    //   4651: pop
    //   4652: iload_2
    //   4653: ifne -> 5732
    //   4656: goto -> 4663
    //   4659: invokestatic a : (Ljava/lang/Throwable;)Ljava/lang/Throwable;
    //   4662: athrow
    //   4663: aload_3
    //   4664: getstatic burp/Zsf3.Zb : Ljava/lang/String;
    //   4667: getstatic burp/Zejg.ZR : Ljava/lang/Object;
    //   4670: checkcast java/math/BigInteger
    //   4673: invokevirtual intValue : ()I
    //   4676: bipush #32
    //   4678: irem
    //   4679: invokestatic abs : (I)I
    //   4682: invokevirtual charAt : (I)C
    //   4685: invokevirtual append : (C)Ljava/lang/StringBuilder;
    //   4688: pop
    //   4689: iload_2
    //   4690: ifne -> 5732
    //   4693: goto -> 4700
    //   4696: invokestatic a : (Ljava/lang/Throwable;)Ljava/lang/Throwable;
    //   4699: athrow
    //   4700: aload_3
    //   4701: getstatic burp/Zer1.ZV : Ljava/lang/String;
    //   4704: getstatic burp/Ze_0.ZY : Ljava/lang/Object;
    //   4707: checkcast java/math/BigInteger
    //   4710: invokevirtual intValue : ()I
    //   4713: bipush #32
    //   4715: irem
    //   4716: invokestatic abs : (I)I
    //   4719: invokevirtual charAt : (I)C
    //   4722: invokevirtual append : (C)Ljava/lang/StringBuilder;
    //   4725: pop
    //   4726: iload_2
    //   4727: ifne -> 5732
    //   4730: goto -> 4737
    //   4733: invokestatic a : (Ljava/lang/Throwable;)Ljava/lang/Throwable;
    //   4736: athrow
    //   4737: aload_3
    //   4738: getstatic burp/Zeb3.ZG : Ljava/lang/String;
    //   4741: getstatic burp/Zrd0.Zs : Ljava/lang/Object;
    //   4744: checkcast java/math/BigInteger
    //   4747: invokevirtual intValue : ()I
    //   4750: bipush #32
    //   4752: irem
    //   4753: invokestatic abs : (I)I
    //   4756: invokevirtual charAt : (I)C
    //   4759: invokevirtual append : (C)Ljava/lang/StringBuilder;
    //   4762: pop
    //   4763: iload_2
    //   4764: ifne -> 5732
    //   4767: goto -> 4774
    //   4770: invokestatic a : (Ljava/lang/Throwable;)Ljava/lang/Throwable;
    //   4773: athrow
    //   4774: aload_3
    //   4775: getstatic burp/Zs9k.Zx : Ljava/lang/String;
    //   4778: getstatic burp/Zg4d.Zm : Ljava/lang/Object;
    //   4781: checkcast java/math/BigInteger
    //   4784: invokevirtual intValue : ()I
    //   4787: bipush #32
    //   4789: irem
    //   4790: invokestatic abs : (I)I
    //   4793: invokevirtual charAt : (I)C
    //   4796: invokevirtual append : (C)Ljava/lang/StringBuilder;
    //   4799: pop
    //   4800: iload_2
    //   4801: ifne -> 5732
    //   4804: goto -> 4811
    //   4807: invokestatic a : (Ljava/lang/Throwable;)Ljava/lang/Throwable;
    //   4810: athrow
    //   4811: aload_3
    //   4812: getstatic burp/Zkk2.ZI : Ljava/lang/String;
    //   4815: getstatic burp/Zz7j.ZR : Ljava/lang/Object;
    //   4818: checkcast java/math/BigInteger
    //   4821: invokevirtual intValue : ()I
    //   4824: bipush #32
    //   4826: irem
    //   4827: invokestatic abs : (I)I
    //   4830: invokevirtual charAt : (I)C
    //   4833: invokevirtual append : (C)Ljava/lang/StringBuilder;
    //   4836: pop
    //   4837: iload_2
    //   4838: ifne -> 5732
    //   4841: goto -> 4848
    //   4844: invokestatic a : (Ljava/lang/Throwable;)Ljava/lang/Throwable;
    //   4847: athrow
    //   4848: aload_3
    //   4849: getstatic burp/Zrpx.ZM : Ljava/lang/String;
    //   4852: getstatic burp/Zlp7.ZM : Ljava/lang/Object;
    //   4855: checkcast java/math/BigInteger
    //   4858: invokevirtual intValue : ()I
    //   4861: bipush #32
    //   4863: irem
    //   4864: invokestatic abs : (I)I
    //   4867: invokevirtual charAt : (I)C
    //   4870: invokevirtual append : (C)Ljava/lang/StringBuilder;
    //   4873: pop
    //   4874: iload_2
    //   4875: ifne -> 5732
    //   4878: goto -> 4885
    //   4881: invokestatic a : (Ljava/lang/Throwable;)Ljava/lang/Throwable;
    //   4884: athrow
    //   4885: aload_3
    //   4886: getstatic burp/Zeig.Zg : Ljava/lang/String;
    //   4889: getstatic burp/Zt3l.Zq : Ljava/lang/Object;
    //   4892: checkcast java/math/BigInteger
    //   4895: invokevirtual intValue : ()I
    //   4898: bipush #32
    //   4900: irem
    //   4901: invokestatic abs : (I)I
    //   4904: invokevirtual charAt : (I)C
    //   4907: invokevirtual append : (C)Ljava/lang/StringBuilder;
    //   4910: pop
    //   4911: iload_2
    //   4912: ifne -> 5732
    //   4915: goto -> 4922
    //   4918: invokestatic a : (Ljava/lang/Throwable;)Ljava/lang/Throwable;
    //   4921: athrow
    //   4922: aload_3
    //   4923: getstatic burp/Zml.ZN : Ljava/lang/String;
    //   4926: getstatic burp/Zszz.ZG : Ljava/lang/Object;
    //   4929: checkcast java/math/BigInteger
    //   4932: invokevirtual intValue : ()I
    //   4935: bipush #32
    //   4937: irem
    //   4938: invokestatic abs : (I)I
    //   4941: invokevirtual charAt : (I)C
    //   4944: invokevirtual append : (C)Ljava/lang/StringBuilder;
    //   4947: pop
    //   4948: iload_2
    //   4949: ifne -> 5732
    //   4952: goto -> 4959
    //   4955: invokestatic a : (Ljava/lang/Throwable;)Ljava/lang/Throwable;
    //   4958: athrow
    //   4959: aload_3
    //   4960: getstatic burp/Zewo.ZM : Ljava/lang/String;
    //   4963: getstatic burp/Zr_w.ZK : Ljava/lang/Object;
    //   4966: checkcast java/math/BigInteger
    //   4969: invokevirtual intValue : ()I
    //   4972: bipush #32
    //   4974: irem
    //   4975: invokestatic abs : (I)I
    //   4978: invokevirtual charAt : (I)C
    //   4981: invokevirtual append : (C)Ljava/lang/StringBuilder;
    //   4984: pop
    //   4985: iload_2
    //   4986: ifne -> 5732
    //   4989: goto -> 4996
    //   4992: invokestatic a : (Ljava/lang/Throwable;)Ljava/lang/Throwable;
    //   4995: athrow
    //   4996: aload_3
    //   4997: getstatic burp/Zmdi.ZA : Ljava/lang/String;
    //   5000: getstatic burp/Zsm3.ZC : Ljava/lang/Object;
    //   5003: checkcast java/math/BigInteger
    //   5006: invokevirtual intValue : ()I
    //   5009: bipush #32
    //   5011: irem
    //   5012: invokestatic abs : (I)I
    //   5015: invokevirtual charAt : (I)C
    //   5018: invokevirtual append : (C)Ljava/lang/StringBuilder;
    //   5021: pop
    //   5022: iload_2
    //   5023: ifne -> 5732
    //   5026: goto -> 5033
    //   5029: invokestatic a : (Ljava/lang/Throwable;)Ljava/lang/Throwable;
    //   5032: athrow
    //   5033: aload_3
    //   5034: getstatic burp/Zxxf.Zw : Ljava/lang/String;
    //   5037: getstatic burp/Zdm.ZA : Ljava/lang/Object;
    //   5040: checkcast java/math/BigInteger
    //   5043: invokevirtual intValue : ()I
    //   5046: bipush #32
    //   5048: irem
    //   5049: invokestatic abs : (I)I
    //   5052: invokevirtual charAt : (I)C
    //   5055: invokevirtual append : (C)Ljava/lang/StringBuilder;
    //   5058: pop
    //   5059: iload_2
    //   5060: ifne -> 5732
    //   5063: goto -> 5070
    //   5066: invokestatic a : (Ljava/lang/Throwable;)Ljava/lang/Throwable;
    //   5069: athrow
    //   5070: aload_3
    //   5071: getstatic burp/Zgt7.ZO : Ljava/lang/String;
    //   5074: getstatic burp/Zlbr.Zp : Ljava/lang/Object;
    //   5077: checkcast java/math/BigInteger
    //   5080: invokevirtual intValue : ()I
    //   5083: bipush #32
    //   5085: irem
    //   5086: invokestatic abs : (I)I
    //   5089: invokevirtual charAt : (I)C
    //   5092: invokevirtual append : (C)Ljava/lang/StringBuilder;
    //   5095: pop
    //   5096: iload_2
    //   5097: ifne -> 5732
    //   5100: goto -> 5107
    //   5103: invokestatic a : (Ljava/lang/Throwable;)Ljava/lang/Throwable;
    //   5106: athrow
    //   5107: aload_3
    //   5108: getstatic burp/Ztw4.Zb : Ljava/lang/String;
    //   5111: getstatic burp/Zsf3.ZH : Ljava/lang/Object;
    //   5114: checkcast java/math/BigInteger
    //   5117: invokevirtual intValue : ()I
    //   5120: bipush #32
    //   5122: irem
    //   5123: invokestatic abs : (I)I
    //   5126: invokevirtual charAt : (I)C
    //   5129: invokevirtual append : (C)Ljava/lang/StringBuilder;
    //   5132: pop
    //   5133: iload_2
    //   5134: ifne -> 5732
    //   5137: goto -> 5144
    //   5140: invokestatic a : (Ljava/lang/Throwable;)Ljava/lang/Throwable;
    //   5143: athrow
    //   5144: aload_3
    //   5145: getstatic burp/Zxdh.Zj : Ljava/lang/String;
    //   5148: getstatic burp/Zsdn.ZE : Ljava/lang/Object;
    //   5151: checkcast java/math/BigInteger
    //   5154: invokevirtual intValue : ()I
    //   5157: bipush #32
    //   5159: irem
    //   5160: invokestatic abs : (I)I
    //   5163: invokevirtual charAt : (I)C
    //   5166: invokevirtual append : (C)Ljava/lang/StringBuilder;
    //   5169: pop
    //   5170: iload_2
    //   5171: ifne -> 5732
    //   5174: goto -> 5181
    //   5177: invokestatic a : (Ljava/lang/Throwable;)Ljava/lang/Throwable;
    //   5180: athrow
    //   5181: aload_3
    //   5182: getstatic burp/Zebu.ZI : Ljava/lang/String;
    //   5185: getstatic burp/Zgp_.Zm : Ljava/lang/Object;
    //   5188: checkcast java/math/BigInteger
    //   5191: invokevirtual intValue : ()I
    //   5194: bipush #32
    //   5196: irem
    //   5197: invokestatic abs : (I)I
    //   5200: invokevirtual charAt : (I)C
    //   5203: invokevirtual append : (C)Ljava/lang/StringBuilder;
    //   5206: pop
    //   5207: iload_2
    //   5208: ifne -> 5732
    //   5211: goto -> 5218
    //   5214: invokestatic a : (Ljava/lang/Throwable;)Ljava/lang/Throwable;
    //   5217: athrow
    //   5218: aload_3
    //   5219: getstatic burp/Zgil.ZK : Ljava/lang/String;
    //   5222: getstatic burp/Zrt3.ZG : Ljava/lang/Object;
    //   5225: checkcast java/math/BigInteger
    //   5228: invokevirtual intValue : ()I
    //   5231: bipush #32
    //   5233: irem
    //   5234: invokestatic abs : (I)I
    //   5237: invokevirtual charAt : (I)C
    //   5240: invokevirtual append : (C)Ljava/lang/StringBuilder;
    //   5243: pop
    //   5244: iload_2
    //   5245: ifne -> 5732
    //   5248: goto -> 5255
    //   5251: invokestatic a : (Ljava/lang/Throwable;)Ljava/lang/Throwable;
    //   5254: athrow
    //   5255: aload_3
    //   5256: getstatic burp/Zm14.ZE : Ljava/lang/String;
    //   5259: getstatic burp/Zgwq.Ze : Ljava/lang/Object;
    //   5262: checkcast java/math/BigInteger
    //   5265: invokevirtual intValue : ()I
    //   5268: bipush #32
    //   5270: irem
    //   5271: invokestatic abs : (I)I
    //   5274: invokevirtual charAt : (I)C
    //   5277: invokevirtual append : (C)Ljava/lang/StringBuilder;
    //   5280: pop
    //   5281: iload_2
    //   5282: ifne -> 5732
    //   5285: goto -> 5292
    //   5288: invokestatic a : (Ljava/lang/Throwable;)Ljava/lang/Throwable;
    //   5291: athrow
    //   5292: aload_3
    //   5293: getstatic burp/Zsin.ZC : Ljava/lang/String;
    //   5296: getstatic burp/Zgr1.Zf : Ljava/lang/Object;
    //   5299: checkcast java/math/BigInteger
    //   5302: invokevirtual intValue : ()I
    //   5305: bipush #32
    //   5307: irem
    //   5308: invokestatic abs : (I)I
    //   5311: invokevirtual charAt : (I)C
    //   5314: invokevirtual append : (C)Ljava/lang/StringBuilder;
    //   5317: pop
    //   5318: iload_2
    //   5319: ifne -> 5732
    //   5322: goto -> 5329
    //   5325: invokestatic a : (Ljava/lang/Throwable;)Ljava/lang/Throwable;
    //   5328: athrow
    //   5329: aload_3
    //   5330: getstatic burp/Zg6f.Zf : Ljava/lang/String;
    //   5333: getstatic burp/Ztip.Zc : Ljava/lang/Object;
    //   5336: checkcast java/math/BigInteger
    //   5339: invokevirtual intValue : ()I
    //   5342: bipush #32
    //   5344: irem
    //   5345: invokestatic abs : (I)I
    //   5348: invokevirtual charAt : (I)C
    //   5351: invokevirtual append : (C)Ljava/lang/StringBuilder;
    //   5354: pop
    //   5355: iload_2
    //   5356: ifne -> 5732
    //   5359: goto -> 5366
    //   5362: invokestatic a : (Ljava/lang/Throwable;)Ljava/lang/Throwable;
    //   5365: athrow
    //   5366: aload_3
    //   5367: getstatic burp/Zbzc.ZL : Ljava/lang/String;
    //   5370: getstatic burp/Zkca.ZQ : Ljava/lang/Object;
    //   5373: checkcast java/math/BigInteger
    //   5376: invokevirtual intValue : ()I
    //   5379: bipush #32
    //   5381: irem
    //   5382: invokestatic abs : (I)I
    //   5385: invokevirtual charAt : (I)C
    //   5388: invokevirtual append : (C)Ljava/lang/StringBuilder;
    //   5391: pop
    //   5392: iload_2
    //   5393: ifne -> 5732
    //   5396: goto -> 5403
    //   5399: invokestatic a : (Ljava/lang/Throwable;)Ljava/lang/Throwable;
    //   5402: athrow
    //   5403: aload_3
    //   5404: getstatic burp/Zll8.ZZ : Ljava/lang/String;
    //   5407: getstatic burp/Zxzv.Zg : Ljava/lang/Object;
    //   5410: checkcast java/math/BigInteger
    //   5413: invokevirtual intValue : ()I
    //   5416: bipush #32
    //   5418: irem
    //   5419: invokestatic abs : (I)I
    //   5422: invokevirtual charAt : (I)C
    //   5425: invokevirtual append : (C)Ljava/lang/StringBuilder;
    //   5428: pop
    //   5429: iload_2
    //   5430: ifne -> 5732
    //   5433: goto -> 5440
    //   5436: invokestatic a : (Ljava/lang/Throwable;)Ljava/lang/Throwable;
    //   5439: athrow
    //   5440: aload_3
    //   5441: getstatic burp/Zkjr.Zg : Ljava/lang/String;
    //   5444: getstatic burp/Zs9u.Zd : Ljava/lang/Object;
    //   5447: checkcast java/math/BigInteger
    //   5450: invokevirtual intValue : ()I
    //   5453: bipush #32
    //   5455: irem
    //   5456: invokestatic abs : (I)I
    //   5459: invokevirtual charAt : (I)C
    //   5462: invokevirtual append : (C)Ljava/lang/StringBuilder;
    //   5465: pop
    //   5466: iload_2
    //   5467: ifne -> 5732
    //   5470: goto -> 5477
    //   5473: invokestatic a : (Ljava/lang/Throwable;)Ljava/lang/Throwable;
    //   5476: athrow
    //   5477: aload_3
    //   5478: getstatic burp/Zltb.ZO : Ljava/lang/String;
    //   5481: getstatic burp/Zkm0.ZI : Ljava/lang/Object;
    //   5484: checkcast java/math/BigInteger
    //   5487: invokevirtual intValue : ()I
    //   5490: bipush #32
    //   5492: irem
    //   5493: invokestatic abs : (I)I
    //   5496: invokevirtual charAt : (I)C
    //   5499: invokevirtual append : (C)Ljava/lang/StringBuilder;
    //   5502: pop
    //   5503: iload_2
    //   5504: ifne -> 5732
    //   5507: goto -> 5514
    //   5510: invokestatic a : (Ljava/lang/Throwable;)Ljava/lang/Throwable;
    //   5513: athrow
    //   5514: aload_3
    //   5515: getstatic burp/Zgrf.ZE : Ljava/lang/String;
    //   5518: getstatic burp/Zge1.ZK : Ljava/lang/Object;
    //   5521: checkcast java/math/BigInteger
    //   5524: invokevirtual intValue : ()I
    //   5527: bipush #32
    //   5529: irem
    //   5530: invokestatic abs : (I)I
    //   5533: invokevirtual charAt : (I)C
    //   5536: invokevirtual append : (C)Ljava/lang/StringBuilder;
    //   5539: pop
    //   5540: iload_2
    //   5541: ifne -> 5732
    //   5544: goto -> 5551
    //   5547: invokestatic a : (Ljava/lang/Throwable;)Ljava/lang/Throwable;
    //   5550: athrow
    //   5551: aload_3
    //   5552: getstatic burp/Zei_.ZZ : Ljava/lang/String;
    //   5555: getstatic burp/Zrc0.Zz : Ljava/lang/Object;
    //   5558: checkcast java/math/BigInteger
    //   5561: invokevirtual intValue : ()I
    //   5564: bipush #32
    //   5566: irem
    //   5567: invokestatic abs : (I)I
    //   5570: invokevirtual charAt : (I)C
    //   5573: invokevirtual append : (C)Ljava/lang/StringBuilder;
    //   5576: pop
    //   5577: iload_2
    //   5578: ifne -> 5732
    //   5581: goto -> 5588
    //   5584: invokestatic a : (Ljava/lang/Throwable;)Ljava/lang/Throwable;
    //   5587: athrow
    //   5588: aload_3
    //   5589: getstatic burp/Zg3m.Za : Ljava/lang/String;
    //   5592: getstatic burp/Zz8o.Zg : Ljava/lang/Object;
    //   5595: checkcast java/math/BigInteger
    //   5598: invokevirtual intValue : ()I
    //   5601: bipush #32
    //   5603: irem
    //   5604: invokestatic abs : (I)I
    //   5607: invokevirtual charAt : (I)C
    //   5610: invokevirtual append : (C)Ljava/lang/StringBuilder;
    //   5613: pop
    //   5614: iload_2
    //   5615: ifne -> 5732
    //   5618: goto -> 5625
    //   5621: invokestatic a : (Ljava/lang/Throwable;)Ljava/lang/Throwable;
    //   5624: athrow
    //   5625: aload_3
    //   5626: getstatic burp/Zsej.Zd : Ljava/lang/String;
    //   5629: getstatic burp/Zmze.Zo : Ljava/lang/Object;
    //   5632: checkcast java/math/BigInteger
    //   5635: invokevirtual intValue : ()I
    //   5638: bipush #32
    //   5640: irem
    //   5641: invokestatic abs : (I)I
    //   5644: invokevirtual charAt : (I)C
    //   5647: invokevirtual append : (C)Ljava/lang/StringBuilder;
    //   5650: pop
    //   5651: iload_2
    //   5652: ifne -> 5732
    //   5655: goto -> 5662
    //   5658: invokestatic a : (Ljava/lang/Throwable;)Ljava/lang/Throwable;
    //   5661: athrow
    //   5662: aload_3
    //   5663: getstatic burp/Zr9j.Zc : Ljava/lang/String;
    //   5666: getstatic burp/Zzai.Z_ : Ljava/lang/Object;
    //   5669: checkcast java/math/BigInteger
    //   5672: invokevirtual intValue : ()I
    //   5675: bipush #32
    //   5677: irem
    //   5678: invokestatic abs : (I)I
    //   5681: invokevirtual charAt : (I)C
    //   5684: invokevirtual append : (C)Ljava/lang/StringBuilder;
    //   5687: pop
    //   5688: iload_2
    //   5689: ifne -> 5732
    //   5692: goto -> 5699
    //   5695: invokestatic a : (Ljava/lang/Throwable;)Ljava/lang/Throwable;
    //   5698: athrow
    //   5699: aload_3
    //   5700: getstatic burp/Zeno.ZL : Ljava/lang/String;
    //   5703: getstatic burp/Zzox.Zq : Ljava/lang/Object;
    //   5706: checkcast java/math/BigInteger
    //   5709: invokevirtual intValue : ()I
    //   5712: bipush #32
    //   5714: irem
    //   5715: invokestatic abs : (I)I
    //   5718: invokevirtual charAt : (I)C
    //   5721: invokevirtual append : (C)Ljava/lang/StringBuilder;
    //   5724: pop
    //   5725: goto -> 5732
    //   5728: invokestatic a : (Ljava/lang/Throwable;)Ljava/lang/Throwable;
    //   5731: athrow
    //   5732: iinc #4, 1
    //   5735: iload_2
    //   5736: ifne -> 4400
    //   5739: aload_3
    //   5740: invokevirtual toString : ()Ljava/lang/String;
    //   5743: putstatic burp/Zzk9.Zb : Ljava/lang/String;
    //   5746: getstatic burp/Zmt6.ZK : Ljava/lang/Object;
    //   5749: checkcast java/math/BigInteger
    //   5752: invokevirtual toByteArray : ()[B
    //   5755: astore #4
    //   5757: bipush #32
    //   5759: newarray int
    //   5761: dup
    //   5762: iconst_0
    //   5763: ldc 943331329
    //   5765: iastore
    //   5766: dup
    //   5767: iconst_1
    //   5768: ldc 170788368
    //   5770: iastore
    //   5771: dup
    //   5772: iconst_2
    //   5773: ldc 1008414755
    //   5775: iastore
    //   5776: dup
    //   5777: iconst_3
    //   5778: ldc 187049985
    //   5780: iastore
    //   5781: dup
    //   5782: iconst_4
    //   5783: ldc 1010368540
    //   5785: iastore
    //   5786: dup
    //   5787: iconst_5
    //   5788: ldc 220604441
    //   5790: iastore
    //   5791: dup
    //   5792: bipush #6
    //   5794: ldc 940377620
    //   5796: iastore
    //   5797: dup
    //   5798: bipush #7
    //   5800: ldc 255209728
    //   5802: iastore
    //   5803: dup
    //   5804: bipush #8
    //   5806: ldc 689771012
    //   5808: iastore
    //   5809: dup
    //   5810: bipush #9
    //   5812: ldc 221709344
    //   5814: iastore
    //   5815: dup
    //   5816: bipush #10
    //   5818: ldc 957157408
    //   5820: iastore
    //   5821: dup
    //   5822: bipush #11
    //   5824: ldc 892536332
    //   5826: iastore
    //   5827: dup
    //   5828: bipush #12
    //   5830: ldc 722417666
    //   5832: iastore
    //   5833: dup
    //   5834: bipush #13
    //   5836: ldc 1026621720
    //   5838: iastore
    //   5839: dup
    //   5840: bipush #14
    //   5842: ldc 655302664
    //   5844: iastore
    //   5845: dup
    //   5846: bipush #15
    //   5848: ldc 890966315
    //   5850: iastore
    //   5851: dup
    //   5852: bipush #16
    //   5854: ldc 187632156
    //   5856: iastore
    //   5857: dup
    //   5858: bipush #17
    //   5860: ldc 874189824
    //   5862: iastore
    //   5863: dup
    //   5864: bipush #18
    //   5866: ldc 254150144
    //   5868: iastore
    //   5869: dup
    //   5870: bipush #19
    //   5872: ldc 924386310
    //   5874: iastore
    //   5875: dup
    //   5876: bipush #20
    //   5878: ldc 121057538
    //   5880: iastore
    //   5881: dup
    //   5882: bipush #21
    //   5884: ldc 840500228
    //   5886: iastore
    //   5887: dup
    //   5888: bipush #22
    //   5890: ldc 389160971
    //   5892: iastore
    //   5893: dup
    //   5894: bipush #23
    //   5896: ldc 907870729
    //   5898: iastore
    //   5899: dup
    //   5900: bipush #24
    //   5902: ldc 389426184
    //   5904: iastore
    //   5905: dup
    //   5906: bipush #25
    //   5908: ldc 973875457
    //   5910: iastore
    //   5911: dup
    //   5912: bipush #26
    //   5914: ldc 372376604
    //   5916: iastore
    //   5917: dup
    //   5918: bipush #27
    //   5920: ldc 707731490
    //   5922: iastore
    //   5923: dup
    //   5924: bipush #28
    //   5926: ldc 1043334948
    //   5928: iastore
    //   5929: dup
    //   5930: bipush #29
    //   5932: ldc 439222784
    //   5934: iastore
    //   5935: dup
    //   5936: bipush #30
    //   5938: ldc 876216579
    //   5940: iastore
    //   5941: dup
    //   5942: bipush #31
    //   5944: ldc 455999525
    //   5946: iastore
    //   5947: astore #6
    //   5949: bipush #8
    //   5951: aload #4
    //   5953: arraylength
    //   5954: bipush #8
    //   5956: irem
    //   5957: isub
    //   5958: istore #7
    //   5960: aload #4
    //   5962: arraylength
    //   5963: iload #7
    //   5965: iadd
    //   5966: newarray byte
    //   5968: astore #8
    //   5970: iconst_0
    //   5971: istore #9
    //   5973: iload #9
    //   5975: aload #4
    //   5977: arraylength
    //   5978: if_icmpge -> 5998
    //   5981: aload #8
    //   5983: iload #9
    //   5985: aload #4
    //   5987: iload #9
    //   5989: baload
    //   5990: bastore
    //   5991: iinc #9, 1
    //   5994: iload_2
    //   5995: ifne -> 5973
    //   5998: aload #4
    //   6000: arraylength
    //   6001: istore #9
    //   6003: iload #9
    //   6005: aload #8
    //   6007: arraylength
    //   6008: if_icmpge -> 6026
    //   6011: aload #8
    //   6013: iload #9
    //   6015: iload #7
    //   6017: i2b
    //   6018: bastore
    //   6019: iinc #9, 1
    //   6022: iload_2
    //   6023: ifne -> 6003
    //   6026: aload #8
    //   6028: astore #4
    //   6030: bipush #64
    //   6032: newarray int
    //   6034: dup
    //   6035: iconst_0
    //   6036: ldc 16843776
    //   6038: iastore
    //   6039: dup
    //   6040: iconst_1
    //   6041: iconst_0
    //   6042: iastore
    //   6043: dup
    //   6044: iconst_2
    //   6045: ldc 65536
    //   6047: iastore
    //   6048: dup
    //   6049: iconst_3
    //   6050: ldc 16843780
    //   6052: iastore
    //   6053: dup
    //   6054: iconst_4
    //   6055: ldc 16842756
    //   6057: iastore
    //   6058: dup
    //   6059: iconst_5
    //   6060: ldc 66564
    //   6062: iastore
    //   6063: dup
    //   6064: bipush #6
    //   6066: iconst_4
    //   6067: iastore
    //   6068: dup
    //   6069: bipush #7
    //   6071: ldc 65536
    //   6073: iastore
    //   6074: dup
    //   6075: bipush #8
    //   6077: sipush #1024
    //   6080: iastore
    //   6081: dup
    //   6082: bipush #9
    //   6084: ldc 16843776
    //   6086: iastore
    //   6087: dup
    //   6088: bipush #10
    //   6090: ldc 16843780
    //   6092: iastore
    //   6093: dup
    //   6094: bipush #11
    //   6096: sipush #1024
    //   6099: iastore
    //   6100: dup
    //   6101: bipush #12
    //   6103: ldc 16778244
    //   6105: iastore
    //   6106: dup
    //   6107: bipush #13
    //   6109: ldc 16842756
    //   6111: iastore
    //   6112: dup
    //   6113: bipush #14
    //   6115: ldc 16777216
    //   6117: iastore
    //   6118: dup
    //   6119: bipush #15
    //   6121: iconst_4
    //   6122: iastore
    //   6123: dup
    //   6124: bipush #16
    //   6126: sipush #1028
    //   6129: iastore
    //   6130: dup
    //   6131: bipush #17
    //   6133: ldc 16778240
    //   6135: iastore
    //   6136: dup
    //   6137: bipush #18
    //   6139: ldc 16778240
    //   6141: iastore
    //   6142: dup
    //   6143: bipush #19
    //   6145: ldc 66560
    //   6147: iastore
    //   6148: dup
    //   6149: bipush #20
    //   6151: ldc 66560
    //   6153: iastore
    //   6154: dup
    //   6155: bipush #21
    //   6157: ldc 16842752
    //   6159: iastore
    //   6160: dup
    //   6161: bipush #22
    //   6163: ldc 16842752
    //   6165: iastore
    //   6166: dup
    //   6167: bipush #23
    //   6169: ldc 16778244
    //   6171: iastore
    //   6172: dup
    //   6173: bipush #24
    //   6175: ldc 65540
    //   6177: iastore
    //   6178: dup
    //   6179: bipush #25
    //   6181: ldc 16777220
    //   6183: iastore
    //   6184: dup
    //   6185: bipush #26
    //   6187: ldc 16777220
    //   6189: iastore
    //   6190: dup
    //   6191: bipush #27
    //   6193: ldc 65540
    //   6195: iastore
    //   6196: dup
    //   6197: bipush #28
    //   6199: iconst_0
    //   6200: iastore
    //   6201: dup
    //   6202: bipush #29
    //   6204: sipush #1028
    //   6207: iastore
    //   6208: dup
    //   6209: bipush #30
    //   6211: ldc 66564
    //   6213: iastore
    //   6214: dup
    //   6215: bipush #31
    //   6217: ldc 16777216
    //   6219: iastore
    //   6220: dup
    //   6221: bipush #32
    //   6223: ldc 65536
    //   6225: iastore
    //   6226: dup
    //   6227: bipush #33
    //   6229: ldc 16843780
    //   6231: iastore
    //   6232: dup
    //   6233: bipush #34
    //   6235: iconst_4
    //   6236: iastore
    //   6237: dup
    //   6238: bipush #35
    //   6240: ldc 16842752
    //   6242: iastore
    //   6243: dup
    //   6244: bipush #36
    //   6246: ldc 16843776
    //   6248: iastore
    //   6249: dup
    //   6250: bipush #37
    //   6252: ldc 16777216
    //   6254: iastore
    //   6255: dup
    //   6256: bipush #38
    //   6258: ldc 16777216
    //   6260: iastore
    //   6261: dup
    //   6262: bipush #39
    //   6264: sipush #1024
    //   6267: iastore
    //   6268: dup
    //   6269: bipush #40
    //   6271: ldc 16842756
    //   6273: iastore
    //   6274: dup
    //   6275: bipush #41
    //   6277: ldc 65536
    //   6279: iastore
    //   6280: dup
    //   6281: bipush #42
    //   6283: ldc 66560
    //   6285: iastore
    //   6286: dup
    //   6287: bipush #43
    //   6289: ldc 16777220
    //   6291: iastore
    //   6292: dup
    //   6293: bipush #44
    //   6295: sipush #1024
    //   6298: iastore
    //   6299: dup
    //   6300: bipush #45
    //   6302: iconst_4
    //   6303: iastore
    //   6304: dup
    //   6305: bipush #46
    //   6307: ldc 16778244
    //   6309: iastore
    //   6310: dup
    //   6311: bipush #47
    //   6313: ldc 66564
    //   6315: iastore
    //   6316: dup
    //   6317: bipush #48
    //   6319: ldc 16843780
    //   6321: iastore
    //   6322: dup
    //   6323: bipush #49
    //   6325: ldc 65540
    //   6327: iastore
    //   6328: dup
    //   6329: bipush #50
    //   6331: ldc 16842752
    //   6333: iastore
    //   6334: dup
    //   6335: bipush #51
    //   6337: ldc 16778244
    //   6339: iastore
    //   6340: dup
    //   6341: bipush #52
    //   6343: ldc 16777220
    //   6345: iastore
    //   6346: dup
    //   6347: bipush #53
    //   6349: sipush #1028
    //   6352: iastore
    //   6353: dup
    //   6354: bipush #54
    //   6356: ldc 66564
    //   6358: iastore
    //   6359: dup
    //   6360: bipush #55
    //   6362: ldc 16843776
    //   6364: iastore
    //   6365: dup
    //   6366: bipush #56
    //   6368: sipush #1028
    //   6371: iastore
    //   6372: dup
    //   6373: bipush #57
    //   6375: ldc 16778240
    //   6377: iastore
    //   6378: dup
    //   6379: bipush #58
    //   6381: ldc 16778240
    //   6383: iastore
    //   6384: dup
    //   6385: bipush #59
    //   6387: iconst_0
    //   6388: iastore
    //   6389: dup
    //   6390: bipush #60
    //   6392: ldc 65540
    //   6394: iastore
    //   6395: dup
    //   6396: bipush #61
    //   6398: ldc 66560
    //   6400: iastore
    //   6401: dup
    //   6402: bipush #62
    //   6404: iconst_0
    //   6405: iastore
    //   6406: dup
    //   6407: bipush #63
    //   6409: ldc 16842756
    //   6411: iastore
    //   6412: astore #9
    //   6414: bipush #64
    //   6416: newarray int
    //   6418: dup
    //   6419: iconst_0
    //   6420: ldc -2146402272
    //   6422: iastore
    //   6423: dup
    //   6424: iconst_1
    //   6425: ldc -2147450880
    //   6427: iastore
    //   6428: dup
    //   6429: iconst_2
    //   6430: ldc 32768
    //   6432: iastore
    //   6433: dup
    //   6434: iconst_3
    //   6435: ldc 1081376
    //   6437: iastore
    //   6438: dup
    //   6439: iconst_4
    //   6440: ldc 1048576
    //   6442: iastore
    //   6443: dup
    //   6444: iconst_5
    //   6445: bipush #32
    //   6447: iastore
    //   6448: dup
    //   6449: bipush #6
    //   6451: ldc -2146435040
    //   6453: iastore
    //   6454: dup
    //   6455: bipush #7
    //   6457: ldc -2147450848
    //   6459: iastore
    //   6460: dup
    //   6461: bipush #8
    //   6463: ldc -2147483616
    //   6465: iastore
    //   6466: dup
    //   6467: bipush #9
    //   6469: ldc -2146402272
    //   6471: iastore
    //   6472: dup
    //   6473: bipush #10
    //   6475: ldc -2146402304
    //   6477: iastore
    //   6478: dup
    //   6479: bipush #11
    //   6481: ldc -2147483648
    //   6483: iastore
    //   6484: dup
    //   6485: bipush #12
    //   6487: ldc -2147450880
    //   6489: iastore
    //   6490: dup
    //   6491: bipush #13
    //   6493: ldc 1048576
    //   6495: iastore
    //   6496: dup
    //   6497: bipush #14
    //   6499: bipush #32
    //   6501: iastore
    //   6502: dup
    //   6503: bipush #15
    //   6505: ldc -2146435040
    //   6507: iastore
    //   6508: dup
    //   6509: bipush #16
    //   6511: ldc 1081344
    //   6513: iastore
    //   6514: dup
    //   6515: bipush #17
    //   6517: ldc 1048608
    //   6519: iastore
    //   6520: dup
    //   6521: bipush #18
    //   6523: ldc -2147450848
    //   6525: iastore
    //   6526: dup
    //   6527: bipush #19
    //   6529: iconst_0
    //   6530: iastore
    //   6531: dup
    //   6532: bipush #20
    //   6534: ldc -2147483648
    //   6536: iastore
    //   6537: dup
    //   6538: bipush #21
    //   6540: ldc 32768
    //   6542: iastore
    //   6543: dup
    //   6544: bipush #22
    //   6546: ldc 1081376
    //   6548: iastore
    //   6549: dup
    //   6550: bipush #23
    //   6552: ldc -2146435072
    //   6554: iastore
    //   6555: dup
    //   6556: bipush #24
    //   6558: ldc 1048608
    //   6560: iastore
    //   6561: dup
    //   6562: bipush #25
    //   6564: ldc -2147483616
    //   6566: iastore
    //   6567: dup
    //   6568: bipush #26
    //   6570: iconst_0
    //   6571: iastore
    //   6572: dup
    //   6573: bipush #27
    //   6575: ldc 1081344
    //   6577: iastore
    //   6578: dup
    //   6579: bipush #28
    //   6581: ldc 32800
    //   6583: iastore
    //   6584: dup
    //   6585: bipush #29
    //   6587: ldc -2146402304
    //   6589: iastore
    //   6590: dup
    //   6591: bipush #30
    //   6593: ldc -2146435072
    //   6595: iastore
    //   6596: dup
    //   6597: bipush #31
    //   6599: ldc 32800
    //   6601: iastore
    //   6602: dup
    //   6603: bipush #32
    //   6605: iconst_0
    //   6606: iastore
    //   6607: dup
    //   6608: bipush #33
    //   6610: ldc 1081376
    //   6612: iastore
    //   6613: dup
    //   6614: bipush #34
    //   6616: ldc -2146435040
    //   6618: iastore
    //   6619: dup
    //   6620: bipush #35
    //   6622: ldc 1048576
    //   6624: iastore
    //   6625: dup
    //   6626: bipush #36
    //   6628: ldc -2147450848
    //   6630: iastore
    //   6631: dup
    //   6632: bipush #37
    //   6634: ldc -2146435072
    //   6636: iastore
    //   6637: dup
    //   6638: bipush #38
    //   6640: ldc -2146402304
    //   6642: iastore
    //   6643: dup
    //   6644: bipush #39
    //   6646: ldc 32768
    //   6648: iastore
    //   6649: dup
    //   6650: bipush #40
    //   6652: ldc -2146435072
    //   6654: iastore
    //   6655: dup
    //   6656: bipush #41
    //   6658: ldc -2147450880
    //   6660: iastore
    //   6661: dup
    //   6662: bipush #42
    //   6664: bipush #32
    //   6666: iastore
    //   6667: dup
    //   6668: bipush #43
    //   6670: ldc -2146402272
    //   6672: iastore
    //   6673: dup
    //   6674: bipush #44
    //   6676: ldc 1081376
    //   6678: iastore
    //   6679: dup
    //   6680: bipush #45
    //   6682: bipush #32
    //   6684: iastore
    //   6685: dup
    //   6686: bipush #46
    //   6688: ldc 32768
    //   6690: iastore
    //   6691: dup
    //   6692: bipush #47
    //   6694: ldc -2147483648
    //   6696: iastore
    //   6697: dup
    //   6698: bipush #48
    //   6700: ldc 32800
    //   6702: iastore
    //   6703: dup
    //   6704: bipush #49
    //   6706: ldc -2146402304
    //   6708: iastore
    //   6709: dup
    //   6710: bipush #50
    //   6712: ldc 1048576
    //   6714: iastore
    //   6715: dup
    //   6716: bipush #51
    //   6718: ldc -2147483616
    //   6720: iastore
    //   6721: dup
    //   6722: bipush #52
    //   6724: ldc 1048608
    //   6726: iastore
    //   6727: dup
    //   6728: bipush #53
    //   6730: ldc -2147450848
    //   6732: iastore
    //   6733: dup
    //   6734: bipush #54
    //   6736: ldc -2147483616
    //   6738: iastore
    //   6739: dup
    //   6740: bipush #55
    //   6742: ldc 1048608
    //   6744: iastore
    //   6745: dup
    //   6746: bipush #56
    //   6748: ldc 1081344
    //   6750: iastore
    //   6751: dup
    //   6752: bipush #57
    //   6754: iconst_0
    //   6755: iastore
    //   6756: dup
    //   6757: bipush #58
    //   6759: ldc -2147450880
    //   6761: iastore
    //   6762: dup
    //   6763: bipush #59
    //   6765: ldc 32800
    //   6767: iastore
    //   6768: dup
    //   6769: bipush #60
    //   6771: ldc -2147483648
    //   6773: iastore
    //   6774: dup
    //   6775: bipush #61
    //   6777: ldc -2146435040
    //   6779: iastore
    //   6780: dup
    //   6781: bipush #62
    //   6783: ldc -2146402272
    //   6785: iastore
    //   6786: dup
    //   6787: bipush #63
    //   6789: ldc 1081344
    //   6791: iastore
    //   6792: astore #10
    //   6794: bipush #64
    //   6796: newarray int
    //   6798: dup
    //   6799: iconst_0
    //   6800: sipush #520
    //   6803: iastore
    //   6804: dup
    //   6805: iconst_1
    //   6806: ldc 134349312
    //   6808: iastore
    //   6809: dup
    //   6810: iconst_2
    //   6811: iconst_0
    //   6812: iastore
    //   6813: dup
    //   6814: iconst_3
    //   6815: ldc 134348808
    //   6817: iastore
    //   6818: dup
    //   6819: iconst_4
    //   6820: ldc 134218240
    //   6822: iastore
    //   6823: dup
    //   6824: iconst_5
    //   6825: iconst_0
    //   6826: iastore
    //   6827: dup
    //   6828: bipush #6
    //   6830: ldc 131592
    //   6832: iastore
    //   6833: dup
    //   6834: bipush #7
    //   6836: ldc 134218240
    //   6838: iastore
    //   6839: dup
    //   6840: bipush #8
    //   6842: ldc 131080
    //   6844: iastore
    //   6845: dup
    //   6846: bipush #9
    //   6848: ldc 134217736
    //   6850: iastore
    //   6851: dup
    //   6852: bipush #10
    //   6854: ldc 134217736
    //   6856: iastore
    //   6857: dup
    //   6858: bipush #11
    //   6860: ldc 131072
    //   6862: iastore
    //   6863: dup
    //   6864: bipush #12
    //   6866: ldc 134349320
    //   6868: iastore
    //   6869: dup
    //   6870: bipush #13
    //   6872: ldc 131080
    //   6874: iastore
    //   6875: dup
    //   6876: bipush #14
    //   6878: ldc 134348800
    //   6880: iastore
    //   6881: dup
    //   6882: bipush #15
    //   6884: sipush #520
    //   6887: iastore
    //   6888: dup
    //   6889: bipush #16
    //   6891: ldc 134217728
    //   6893: iastore
    //   6894: dup
    //   6895: bipush #17
    //   6897: bipush #8
    //   6899: iastore
    //   6900: dup
    //   6901: bipush #18
    //   6903: ldc 134349312
    //   6905: iastore
    //   6906: dup
    //   6907: bipush #19
    //   6909: sipush #512
    //   6912: iastore
    //   6913: dup
    //   6914: bipush #20
    //   6916: ldc 131584
    //   6918: iastore
    //   6919: dup
    //   6920: bipush #21
    //   6922: ldc 134348800
    //   6924: iastore
    //   6925: dup
    //   6926: bipush #22
    //   6928: ldc 134348808
    //   6930: iastore
    //   6931: dup
    //   6932: bipush #23
    //   6934: ldc 131592
    //   6936: iastore
    //   6937: dup
    //   6938: bipush #24
    //   6940: ldc 134218248
    //   6942: iastore
    //   6943: dup
    //   6944: bipush #25
    //   6946: ldc 131584
    //   6948: iastore
    //   6949: dup
    //   6950: bipush #26
    //   6952: ldc 131072
    //   6954: iastore
    //   6955: dup
    //   6956: bipush #27
    //   6958: ldc 134218248
    //   6960: iastore
    //   6961: dup
    //   6962: bipush #28
    //   6964: bipush #8
    //   6966: iastore
    //   6967: dup
    //   6968: bipush #29
    //   6970: ldc 134349320
    //   6972: iastore
    //   6973: dup
    //   6974: bipush #30
    //   6976: sipush #512
    //   6979: iastore
    //   6980: dup
    //   6981: bipush #31
    //   6983: ldc 134217728
    //   6985: iastore
    //   6986: dup
    //   6987: bipush #32
    //   6989: ldc 134349312
    //   6991: iastore
    //   6992: dup
    //   6993: bipush #33
    //   6995: ldc 134217728
    //   6997: iastore
    //   6998: dup
    //   6999: bipush #34
    //   7001: ldc 131080
    //   7003: iastore
    //   7004: dup
    //   7005: bipush #35
    //   7007: sipush #520
    //   7010: iastore
    //   7011: dup
    //   7012: bipush #36
    //   7014: ldc 131072
    //   7016: iastore
    //   7017: dup
    //   7018: bipush #37
    //   7020: ldc 134349312
    //   7022: iastore
    //   7023: dup
    //   7024: bipush #38
    //   7026: ldc 134218240
    //   7028: iastore
    //   7029: dup
    //   7030: bipush #39
    //   7032: iconst_0
    //   7033: iastore
    //   7034: dup
    //   7035: bipush #40
    //   7037: sipush #512
    //   7040: iastore
    //   7041: dup
    //   7042: bipush #41
    //   7044: ldc 131080
    //   7046: iastore
    //   7047: dup
    //   7048: bipush #42
    //   7050: ldc 134349320
    //   7052: iastore
    //   7053: dup
    //   7054: bipush #43
    //   7056: ldc 134218240
    //   7058: iastore
    //   7059: dup
    //   7060: bipush #44
    //   7062: ldc 134217736
    //   7064: iastore
    //   7065: dup
    //   7066: bipush #45
    //   7068: sipush #512
    //   7071: iastore
    //   7072: dup
    //   7073: bipush #46
    //   7075: iconst_0
    //   7076: iastore
    //   7077: dup
    //   7078: bipush #47
    //   7080: ldc 134348808
    //   7082: iastore
    //   7083: dup
    //   7084: bipush #48
    //   7086: ldc 134218248
    //   7088: iastore
    //   7089: dup
    //   7090: bipush #49
    //   7092: ldc 131072
    //   7094: iastore
    //   7095: dup
    //   7096: bipush #50
    //   7098: ldc 134217728
    //   7100: iastore
    //   7101: dup
    //   7102: bipush #51
    //   7104: ldc 134349320
    //   7106: iastore
    //   7107: dup
    //   7108: bipush #52
    //   7110: bipush #8
    //   7112: iastore
    //   7113: dup
    //   7114: bipush #53
    //   7116: ldc 131592
    //   7118: iastore
    //   7119: dup
    //   7120: bipush #54
    //   7122: ldc 131584
    //   7124: iastore
    //   7125: dup
    //   7126: bipush #55
    //   7128: ldc 134217736
    //   7130: iastore
    //   7131: dup
    //   7132: bipush #56
    //   7134: ldc 134348800
    //   7136: iastore
    //   7137: dup
    //   7138: bipush #57
    //   7140: ldc 134218248
    //   7142: iastore
    //   7143: dup
    //   7144: bipush #58
    //   7146: sipush #520
    //   7149: iastore
    //   7150: dup
    //   7151: bipush #59
    //   7153: ldc 134348800
    //   7155: iastore
    //   7156: dup
    //   7157: bipush #60
    //   7159: ldc 131592
    //   7161: iastore
    //   7162: dup
    //   7163: bipush #61
    //   7165: bipush #8
    //   7167: iastore
    //   7168: dup
    //   7169: bipush #62
    //   7171: ldc 134348808
    //   7173: iastore
    //   7174: dup
    //   7175: bipush #63
    //   7177: ldc 131584
    //   7179: iastore
    //   7180: astore #11
    //   7182: bipush #64
    //   7184: newarray int
    //   7186: dup
    //   7187: iconst_0
    //   7188: ldc 8396801
    //   7190: iastore
    //   7191: dup
    //   7192: iconst_1
    //   7193: sipush #8321
    //   7196: iastore
    //   7197: dup
    //   7198: iconst_2
    //   7199: sipush #8321
    //   7202: iastore
    //   7203: dup
    //   7204: iconst_3
    //   7205: sipush #128
    //   7208: iastore
    //   7209: dup
    //   7210: iconst_4
    //   7211: ldc 8396928
    //   7213: iastore
    //   7214: dup
    //   7215: iconst_5
    //   7216: ldc 8388737
    //   7218: iastore
    //   7219: dup
    //   7220: bipush #6
    //   7222: ldc 8388609
    //   7224: iastore
    //   7225: dup
    //   7226: bipush #7
    //   7228: sipush #8193
    //   7231: iastore
    //   7232: dup
    //   7233: bipush #8
    //   7235: iconst_0
    //   7236: iastore
    //   7237: dup
    //   7238: bipush #9
    //   7240: ldc 8396800
    //   7242: iastore
    //   7243: dup
    //   7244: bipush #10
    //   7246: ldc 8396800
    //   7248: iastore
    //   7249: dup
    //   7250: bipush #11
    //   7252: ldc 8396929
    //   7254: iastore
    //   7255: dup
    //   7256: bipush #12
    //   7258: sipush #129
    //   7261: iastore
    //   7262: dup
    //   7263: bipush #13
    //   7265: iconst_0
    //   7266: iastore
    //   7267: dup
    //   7268: bipush #14
    //   7270: ldc 8388736
    //   7272: iastore
    //   7273: dup
    //   7274: bipush #15
    //   7276: ldc 8388609
    //   7278: iastore
    //   7279: dup
    //   7280: bipush #16
    //   7282: iconst_1
    //   7283: iastore
    //   7284: dup
    //   7285: bipush #17
    //   7287: sipush #8192
    //   7290: iastore
    //   7291: dup
    //   7292: bipush #18
    //   7294: ldc 8388608
    //   7296: iastore
    //   7297: dup
    //   7298: bipush #19
    //   7300: ldc 8396801
    //   7302: iastore
    //   7303: dup
    //   7304: bipush #20
    //   7306: sipush #128
    //   7309: iastore
    //   7310: dup
    //   7311: bipush #21
    //   7313: ldc 8388608
    //   7315: iastore
    //   7316: dup
    //   7317: bipush #22
    //   7319: sipush #8193
    //   7322: iastore
    //   7323: dup
    //   7324: bipush #23
    //   7326: sipush #8320
    //   7329: iastore
    //   7330: dup
    //   7331: bipush #24
    //   7333: ldc 8388737
    //   7335: iastore
    //   7336: dup
    //   7337: bipush #25
    //   7339: iconst_1
    //   7340: iastore
    //   7341: dup
    //   7342: bipush #26
    //   7344: sipush #8320
    //   7347: iastore
    //   7348: dup
    //   7349: bipush #27
    //   7351: ldc 8388736
    //   7353: iastore
    //   7354: dup
    //   7355: bipush #28
    //   7357: sipush #8192
    //   7360: iastore
    //   7361: dup
    //   7362: bipush #29
    //   7364: ldc 8396928
    //   7366: iastore
    //   7367: dup
    //   7368: bipush #30
    //   7370: ldc 8396929
    //   7372: iastore
    //   7373: dup
    //   7374: bipush #31
    //   7376: sipush #129
    //   7379: iastore
    //   7380: dup
    //   7381: bipush #32
    //   7383: ldc 8388736
    //   7385: iastore
    //   7386: dup
    //   7387: bipush #33
    //   7389: ldc 8388609
    //   7391: iastore
    //   7392: dup
    //   7393: bipush #34
    //   7395: ldc 8396800
    //   7397: iastore
    //   7398: dup
    //   7399: bipush #35
    //   7401: ldc 8396929
    //   7403: iastore
    //   7404: dup
    //   7405: bipush #36
    //   7407: sipush #129
    //   7410: iastore
    //   7411: dup
    //   7412: bipush #37
    //   7414: iconst_0
    //   7415: iastore
    //   7416: dup
    //   7417: bipush #38
    //   7419: iconst_0
    //   7420: iastore
    //   7421: dup
    //   7422: bipush #39
    //   7424: ldc 8396800
    //   7426: iastore
    //   7427: dup
    //   7428: bipush #40
    //   7430: sipush #8320
    //   7433: iastore
    //   7434: dup
    //   7435: bipush #41
    //   7437: ldc 8388736
    //   7439: iastore
    //   7440: dup
    //   7441: bipush #42
    //   7443: ldc 8388737
    //   7445: iastore
    //   7446: dup
    //   7447: bipush #43
    //   7449: iconst_1
    //   7450: iastore
    //   7451: dup
    //   7452: bipush #44
    //   7454: ldc 8396801
    //   7456: iastore
    //   7457: dup
    //   7458: bipush #45
    //   7460: sipush #8321
    //   7463: iastore
    //   7464: dup
    //   7465: bipush #46
    //   7467: sipush #8321
    //   7470: iastore
    //   7471: dup
    //   7472: bipush #47
    //   7474: sipush #128
    //   7477: iastore
    //   7478: dup
    //   7479: bipush #48
    //   7481: ldc 8396929
    //   7483: iastore
    //   7484: dup
    //   7485: bipush #49
    //   7487: sipush #129
    //   7490: iastore
    //   7491: dup
    //   7492: bipush #50
    //   7494: iconst_1
    //   7495: iastore
    //   7496: dup
    //   7497: bipush #51
    //   7499: sipush #8192
    //   7502: iastore
    //   7503: dup
    //   7504: bipush #52
    //   7506: ldc 8388609
    //   7508: iastore
    //   7509: dup
    //   7510: bipush #53
    //   7512: sipush #8193
    //   7515: iastore
    //   7516: dup
    //   7517: bipush #54
    //   7519: ldc 8396928
    //   7521: iastore
    //   7522: dup
    //   7523: bipush #55
    //   7525: ldc 8388737
    //   7527: iastore
    //   7528: dup
    //   7529: bipush #56
    //   7531: sipush #8193
    //   7534: iastore
    //   7535: dup
    //   7536: bipush #57
    //   7538: sipush #8320
    //   7541: iastore
    //   7542: dup
    //   7543: bipush #58
    //   7545: ldc 8388608
    //   7547: iastore
    //   7548: dup
    //   7549: bipush #59
    //   7551: ldc 8396801
    //   7553: iastore
    //   7554: dup
    //   7555: bipush #60
    //   7557: sipush #128
    //   7560: iastore
    //   7561: dup
    //   7562: bipush #61
    //   7564: ldc 8388608
    //   7566: iastore
    //   7567: dup
    //   7568: bipush #62
    //   7570: sipush #8192
    //   7573: iastore
    //   7574: dup
    //   7575: bipush #63
    //   7577: ldc 8396928
    //   7579: iastore
    //   7580: astore #12
    //   7582: bipush #64
    //   7584: newarray int
    //   7586: dup
    //   7587: iconst_0
    //   7588: sipush #256
    //   7591: iastore
    //   7592: dup
    //   7593: iconst_1
    //   7594: ldc 34078976
    //   7596: iastore
    //   7597: dup
    //   7598: iconst_2
    //   7599: ldc 34078720
    //   7601: iastore
    //   7602: dup
    //   7603: iconst_3
    //   7604: ldc 1107296512
    //   7606: iastore
    //   7607: dup
    //   7608: iconst_4
    //   7609: ldc 524288
    //   7611: iastore
    //   7612: dup
    //   7613: iconst_5
    //   7614: sipush #256
    //   7617: iastore
    //   7618: dup
    //   7619: bipush #6
    //   7621: ldc 1073741824
    //   7623: iastore
    //   7624: dup
    //   7625: bipush #7
    //   7627: ldc 34078720
    //   7629: iastore
    //   7630: dup
    //   7631: bipush #8
    //   7633: ldc 1074266368
    //   7635: iastore
    //   7636: dup
    //   7637: bipush #9
    //   7639: ldc 524288
    //   7641: iastore
    //   7642: dup
    //   7643: bipush #10
    //   7645: ldc 33554688
    //   7647: iastore
    //   7648: dup
    //   7649: bipush #11
    //   7651: ldc 1074266368
    //   7653: iastore
    //   7654: dup
    //   7655: bipush #12
    //   7657: ldc 1107296512
    //   7659: iastore
    //   7660: dup
    //   7661: bipush #13
    //   7663: ldc 1107820544
    //   7665: iastore
    //   7666: dup
    //   7667: bipush #14
    //   7669: ldc 524544
    //   7671: iastore
    //   7672: dup
    //   7673: bipush #15
    //   7675: ldc 1073741824
    //   7677: iastore
    //   7678: dup
    //   7679: bipush #16
    //   7681: ldc 33554432
    //   7683: iastore
    //   7684: dup
    //   7685: bipush #17
    //   7687: ldc 1074266112
    //   7689: iastore
    //   7690: dup
    //   7691: bipush #18
    //   7693: ldc 1074266112
    //   7695: iastore
    //   7696: dup
    //   7697: bipush #19
    //   7699: iconst_0
    //   7700: iastore
    //   7701: dup
    //   7702: bipush #20
    //   7704: ldc 1073742080
    //   7706: iastore
    //   7707: dup
    //   7708: bipush #21
    //   7710: ldc 1107820800
    //   7712: iastore
    //   7713: dup
    //   7714: bipush #22
    //   7716: ldc 1107820800
    //   7718: iastore
    //   7719: dup
    //   7720: bipush #23
    //   7722: ldc 33554688
    //   7724: iastore
    //   7725: dup
    //   7726: bipush #24
    //   7728: ldc 1107820544
    //   7730: iastore
    //   7731: dup
    //   7732: bipush #25
    //   7734: ldc 1073742080
    //   7736: iastore
    //   7737: dup
    //   7738: bipush #26
    //   7740: iconst_0
    //   7741: iastore
    //   7742: dup
    //   7743: bipush #27
    //   7745: ldc 1107296256
    //   7747: iastore
    //   7748: dup
    //   7749: bipush #28
    //   7751: ldc 34078976
    //   7753: iastore
    //   7754: dup
    //   7755: bipush #29
    //   7757: ldc 33554432
    //   7759: iastore
    //   7760: dup
    //   7761: bipush #30
    //   7763: ldc 1107296256
    //   7765: iastore
    //   7766: dup
    //   7767: bipush #31
    //   7769: ldc 524544
    //   7771: iastore
    //   7772: dup
    //   7773: bipush #32
    //   7775: ldc 524288
    //   7777: iastore
    //   7778: dup
    //   7779: bipush #33
    //   7781: ldc 1107296512
    //   7783: iastore
    //   7784: dup
    //   7785: bipush #34
    //   7787: sipush #256
    //   7790: iastore
    //   7791: dup
    //   7792: bipush #35
    //   7794: ldc 33554432
    //   7796: iastore
    //   7797: dup
    //   7798: bipush #36
    //   7800: ldc 1073741824
    //   7802: iastore
    //   7803: dup
    //   7804: bipush #37
    //   7806: ldc 34078720
    //   7808: iastore
    //   7809: dup
    //   7810: bipush #38
    //   7812: ldc 1107296512
    //   7814: iastore
    //   7815: dup
    //   7816: bipush #39
    //   7818: ldc 1074266368
    //   7820: iastore
    //   7821: dup
    //   7822: bipush #40
    //   7824: ldc 33554688
    //   7826: iastore
    //   7827: dup
    //   7828: bipush #41
    //   7830: ldc 1073741824
    //   7832: iastore
    //   7833: dup
    //   7834: bipush #42
    //   7836: ldc 1107820544
    //   7838: iastore
    //   7839: dup
    //   7840: bipush #43
    //   7842: ldc 34078976
    //   7844: iastore
    //   7845: dup
    //   7846: bipush #44
    //   7848: ldc 1074266368
    //   7850: iastore
    //   7851: dup
    //   7852: bipush #45
    //   7854: sipush #256
    //   7857: iastore
    //   7858: dup
    //   7859: bipush #46
    //   7861: ldc 33554432
    //   7863: iastore
    //   7864: dup
    //   7865: bipush #47
    //   7867: ldc 1107820544
    //   7869: iastore
    //   7870: dup
    //   7871: bipush #48
    //   7873: ldc 1107820800
    //   7875: iastore
    //   7876: dup
    //   7877: bipush #49
    //   7879: ldc 524544
    //   7881: iastore
    //   7882: dup
    //   7883: bipush #50
    //   7885: ldc 1107296256
    //   7887: iastore
    //   7888: dup
    //   7889: bipush #51
    //   7891: ldc 1107820800
    //   7893: iastore
    //   7894: dup
    //   7895: bipush #52
    //   7897: ldc 34078720
    //   7899: iastore
    //   7900: dup
    //   7901: bipush #53
    //   7903: iconst_0
    //   7904: iastore
    //   7905: dup
    //   7906: bipush #54
    //   7908: ldc 1074266112
    //   7910: iastore
    //   7911: dup
    //   7912: bipush #55
    //   7914: ldc 1107296256
    //   7916: iastore
    //   7917: dup
    //   7918: bipush #56
    //   7920: ldc 524544
    //   7922: iastore
    //   7923: dup
    //   7924: bipush #57
    //   7926: ldc 33554688
    //   7928: iastore
    //   7929: dup
    //   7930: bipush #58
    //   7932: ldc 1073742080
    //   7934: iastore
    //   7935: dup
    //   7936: bipush #59
    //   7938: ldc 524288
    //   7940: iastore
    //   7941: dup
    //   7942: bipush #60
    //   7944: iconst_0
    //   7945: iastore
    //   7946: dup
    //   7947: bipush #61
    //   7949: ldc 1074266112
    //   7951: iastore
    //   7952: dup
    //   7953: bipush #62
    //   7955: ldc 34078976
    //   7957: iastore
    //   7958: dup
    //   7959: bipush #63
    //   7961: ldc 1073742080
    //   7963: iastore
    //   7964: astore #13
    //   7966: bipush #64
    //   7968: newarray int
    //   7970: dup
    //   7971: iconst_0
    //   7972: ldc 536870928
    //   7974: iastore
    //   7975: dup
    //   7976: iconst_1
    //   7977: ldc 541065216
    //   7979: iastore
    //   7980: dup
    //   7981: iconst_2
    //   7982: sipush #16384
    //   7985: iastore
    //   7986: dup
    //   7987: iconst_3
    //   7988: ldc 541081616
    //   7990: iastore
    //   7991: dup
    //   7992: iconst_4
    //   7993: ldc 541065216
    //   7995: iastore
    //   7996: dup
    //   7997: iconst_5
    //   7998: bipush #16
    //   8000: iastore
    //   8001: dup
    //   8002: bipush #6
    //   8004: ldc 541081616
    //   8006: iastore
    //   8007: dup
    //   8008: bipush #7
    //   8010: ldc 4194304
    //   8012: iastore
    //   8013: dup
    //   8014: bipush #8
    //   8016: ldc 536887296
    //   8018: iastore
    //   8019: dup
    //   8020: bipush #9
    //   8022: ldc 4210704
    //   8024: iastore
    //   8025: dup
    //   8026: bipush #10
    //   8028: ldc 4194304
    //   8030: iastore
    //   8031: dup
    //   8032: bipush #11
    //   8034: ldc 536870928
    //   8036: iastore
    //   8037: dup
    //   8038: bipush #12
    //   8040: ldc 4194320
    //   8042: iastore
    //   8043: dup
    //   8044: bipush #13
    //   8046: ldc 536887296
    //   8048: iastore
    //   8049: dup
    //   8050: bipush #14
    //   8052: ldc 536870912
    //   8054: iastore
    //   8055: dup
    //   8056: bipush #15
    //   8058: sipush #16400
    //   8061: iastore
    //   8062: dup
    //   8063: bipush #16
    //   8065: iconst_0
    //   8066: iastore
    //   8067: dup
    //   8068: bipush #17
    //   8070: ldc 4194320
    //   8072: iastore
    //   8073: dup
    //   8074: bipush #18
    //   8076: ldc 536887312
    //   8078: iastore
    //   8079: dup
    //   8080: bipush #19
    //   8082: sipush #16384
    //   8085: iastore
    //   8086: dup
    //   8087: bipush #20
    //   8089: ldc 4210688
    //   8091: iastore
    //   8092: dup
    //   8093: bipush #21
    //   8095: ldc 536887312
    //   8097: iastore
    //   8098: dup
    //   8099: bipush #22
    //   8101: bipush #16
    //   8103: iastore
    //   8104: dup
    //   8105: bipush #23
    //   8107: ldc 541065232
    //   8109: iastore
    //   8110: dup
    //   8111: bipush #24
    //   8113: ldc 541065232
    //   8115: iastore
    //   8116: dup
    //   8117: bipush #25
    //   8119: iconst_0
    //   8120: iastore
    //   8121: dup
    //   8122: bipush #26
    //   8124: ldc 4210704
    //   8126: iastore
    //   8127: dup
    //   8128: bipush #27
    //   8130: ldc 541081600
    //   8132: iastore
    //   8133: dup
    //   8134: bipush #28
    //   8136: sipush #16400
    //   8139: iastore
    //   8140: dup
    //   8141: bipush #29
    //   8143: ldc 4210688
    //   8145: iastore
    //   8146: dup
    //   8147: bipush #30
    //   8149: ldc 541081600
    //   8151: iastore
    //   8152: dup
    //   8153: bipush #31
    //   8155: ldc 536870912
    //   8157: iastore
    //   8158: dup
    //   8159: bipush #32
    //   8161: ldc 536887296
    //   8163: iastore
    //   8164: dup
    //   8165: bipush #33
    //   8167: bipush #16
    //   8169: iastore
    //   8170: dup
    //   8171: bipush #34
    //   8173: ldc 541065232
    //   8175: iastore
    //   8176: dup
    //   8177: bipush #35
    //   8179: ldc 4210688
    //   8181: iastore
    //   8182: dup
    //   8183: bipush #36
    //   8185: ldc 541081616
    //   8187: iastore
    //   8188: dup
    //   8189: bipush #37
    //   8191: ldc 4194304
    //   8193: iastore
    //   8194: dup
    //   8195: bipush #38
    //   8197: sipush #16400
    //   8200: iastore
    //   8201: dup
    //   8202: bipush #39
    //   8204: ldc 536870928
    //   8206: iastore
    //   8207: dup
    //   8208: bipush #40
    //   8210: ldc 4194304
    //   8212: iastore
    //   8213: dup
    //   8214: bipush #41
    //   8216: ldc 536887296
    //   8218: iastore
    //   8219: dup
    //   8220: bipush #42
    //   8222: ldc 536870912
    //   8224: iastore
    //   8225: dup
    //   8226: bipush #43
    //   8228: sipush #16400
    //   8231: iastore
    //   8232: dup
    //   8233: bipush #44
    //   8235: ldc 536870928
    //   8237: iastore
    //   8238: dup
    //   8239: bipush #45
    //   8241: ldc 541081616
    //   8243: iastore
    //   8244: dup
    //   8245: bipush #46
    //   8247: ldc 4210688
    //   8249: iastore
    //   8250: dup
    //   8251: bipush #47
    //   8253: ldc 541065216
    //   8255: iastore
    //   8256: dup
    //   8257: bipush #48
    //   8259: ldc 4210704
    //   8261: iastore
    //   8262: dup
    //   8263: bipush #49
    //   8265: ldc 541081600
    //   8267: iastore
    //   8268: dup
    //   8269: bipush #50
    //   8271: iconst_0
    //   8272: iastore
    //   8273: dup
    //   8274: bipush #51
    //   8276: ldc 541065232
    //   8278: iastore
    //   8279: dup
    //   8280: bipush #52
    //   8282: bipush #16
    //   8284: iastore
    //   8285: dup
    //   8286: bipush #53
    //   8288: sipush #16384
    //   8291: iastore
    //   8292: dup
    //   8293: bipush #54
    //   8295: ldc 541065216
    //   8297: iastore
    //   8298: dup
    //   8299: bipush #55
    //   8301: ldc 4210704
    //   8303: iastore
    //   8304: dup
    //   8305: bipush #56
    //   8307: sipush #16384
    //   8310: iastore
    //   8311: dup
    //   8312: bipush #57
    //   8314: ldc 4194320
    //   8316: iastore
    //   8317: dup
    //   8318: bipush #58
    //   8320: ldc 536887312
    //   8322: iastore
    //   8323: dup
    //   8324: bipush #59
    //   8326: iconst_0
    //   8327: iastore
    //   8328: dup
    //   8329: bipush #60
    //   8331: ldc 541081600
    //   8333: iastore
    //   8334: dup
    //   8335: bipush #61
    //   8337: ldc 536870912
    //   8339: iastore
    //   8340: dup
    //   8341: bipush #62
    //   8343: ldc 4194320
    //   8345: iastore
    //   8346: dup
    //   8347: bipush #63
    //   8349: ldc 536887312
    //   8351: iastore
    //   8352: astore #14
    //   8354: bipush #64
    //   8356: newarray int
    //   8358: dup
    //   8359: iconst_0
    //   8360: ldc 2097152
    //   8362: iastore
    //   8363: dup
    //   8364: iconst_1
    //   8365: ldc 69206018
    //   8367: iastore
    //   8368: dup
    //   8369: iconst_2
    //   8370: ldc 67110914
    //   8372: iastore
    //   8373: dup
    //   8374: iconst_3
    //   8375: iconst_0
    //   8376: iastore
    //   8377: dup
    //   8378: iconst_4
    //   8379: sipush #2048
    //   8382: iastore
    //   8383: dup
    //   8384: iconst_5
    //   8385: ldc 67110914
    //   8387: iastore
    //   8388: dup
    //   8389: bipush #6
    //   8391: ldc 2099202
    //   8393: iastore
    //   8394: dup
    //   8395: bipush #7
    //   8397: ldc 69208064
    //   8399: iastore
    //   8400: dup
    //   8401: bipush #8
    //   8403: ldc 69208066
    //   8405: iastore
    //   8406: dup
    //   8407: bipush #9
    //   8409: ldc 2097152
    //   8411: iastore
    //   8412: dup
    //   8413: bipush #10
    //   8415: iconst_0
    //   8416: iastore
    //   8417: dup
    //   8418: bipush #11
    //   8420: ldc 67108866
    //   8422: iastore
    //   8423: dup
    //   8424: bipush #12
    //   8426: iconst_2
    //   8427: iastore
    //   8428: dup
    //   8429: bipush #13
    //   8431: ldc 67108864
    //   8433: iastore
    //   8434: dup
    //   8435: bipush #14
    //   8437: ldc 69206018
    //   8439: iastore
    //   8440: dup
    //   8441: bipush #15
    //   8443: sipush #2050
    //   8446: iastore
    //   8447: dup
    //   8448: bipush #16
    //   8450: ldc 67110912
    //   8452: iastore
    //   8453: dup
    //   8454: bipush #17
    //   8456: ldc 2099202
    //   8458: iastore
    //   8459: dup
    //   8460: bipush #18
    //   8462: ldc 2097154
    //   8464: iastore
    //   8465: dup
    //   8466: bipush #19
    //   8468: ldc 67110912
    //   8470: iastore
    //   8471: dup
    //   8472: bipush #20
    //   8474: ldc 67108866
    //   8476: iastore
    //   8477: dup
    //   8478: bipush #21
    //   8480: ldc 69206016
    //   8482: iastore
    //   8483: dup
    //   8484: bipush #22
    //   8486: ldc 69208064
    //   8488: iastore
    //   8489: dup
    //   8490: bipush #23
    //   8492: ldc 2097154
    //   8494: iastore
    //   8495: dup
    //   8496: bipush #24
    //   8498: ldc 69206016
    //   8500: iastore
    //   8501: dup
    //   8502: bipush #25
    //   8504: sipush #2048
    //   8507: iastore
    //   8508: dup
    //   8509: bipush #26
    //   8511: sipush #2050
    //   8514: iastore
    //   8515: dup
    //   8516: bipush #27
    //   8518: ldc 69208066
    //   8520: iastore
    //   8521: dup
    //   8522: bipush #28
    //   8524: ldc 2099200
    //   8526: iastore
    //   8527: dup
    //   8528: bipush #29
    //   8530: iconst_2
    //   8531: iastore
    //   8532: dup
    //   8533: bipush #30
    //   8535: ldc 67108864
    //   8537: iastore
    //   8538: dup
    //   8539: bipush #31
    //   8541: ldc 2099200
    //   8543: iastore
    //   8544: dup
    //   8545: bipush #32
    //   8547: ldc 67108864
    //   8549: iastore
    //   8550: dup
    //   8551: bipush #33
    //   8553: ldc 2099200
    //   8555: iastore
    //   8556: dup
    //   8557: bipush #34
    //   8559: ldc 2097152
    //   8561: iastore
    //   8562: dup
    //   8563: bipush #35
    //   8565: ldc 67110914
    //   8567: iastore
    //   8568: dup
    //   8569: bipush #36
    //   8571: ldc 67110914
    //   8573: iastore
    //   8574: dup
    //   8575: bipush #37
    //   8577: ldc 69206018
    //   8579: iastore
    //   8580: dup
    //   8581: bipush #38
    //   8583: ldc 69206018
    //   8585: iastore
    //   8586: dup
    //   8587: bipush #39
    //   8589: iconst_2
    //   8590: iastore
    //   8591: dup
    //   8592: bipush #40
    //   8594: ldc 2097154
    //   8596: iastore
    //   8597: dup
    //   8598: bipush #41
    //   8600: ldc 67108864
    //   8602: iastore
    //   8603: dup
    //   8604: bipush #42
    //   8606: ldc 67110912
    //   8608: iastore
    //   8609: dup
    //   8610: bipush #43
    //   8612: ldc 2097152
    //   8614: iastore
    //   8615: dup
    //   8616: bipush #44
    //   8618: ldc 69208064
    //   8620: iastore
    //   8621: dup
    //   8622: bipush #45
    //   8624: sipush #2050
    //   8627: iastore
    //   8628: dup
    //   8629: bipush #46
    //   8631: ldc 2099202
    //   8633: iastore
    //   8634: dup
    //   8635: bipush #47
    //   8637: ldc 69208064
    //   8639: iastore
    //   8640: dup
    //   8641: bipush #48
    //   8643: sipush #2050
    //   8646: iastore
    //   8647: dup
    //   8648: bipush #49
    //   8650: ldc 67108866
    //   8652: iastore
    //   8653: dup
    //   8654: bipush #50
    //   8656: ldc 69208066
    //   8658: iastore
    //   8659: dup
    //   8660: bipush #51
    //   8662: ldc 69206016
    //   8664: iastore
    //   8665: dup
    //   8666: bipush #52
    //   8668: ldc 2099200
    //   8670: iastore
    //   8671: dup
    //   8672: bipush #53
    //   8674: iconst_0
    //   8675: iastore
    //   8676: dup
    //   8677: bipush #54
    //   8679: iconst_2
    //   8680: iastore
    //   8681: dup
    //   8682: bipush #55
    //   8684: ldc 69208066
    //   8686: iastore
    //   8687: dup
    //   8688: bipush #56
    //   8690: iconst_0
    //   8691: iastore
    //   8692: dup
    //   8693: bipush #57
    //   8695: ldc 2099202
    //   8697: iastore
    //   8698: dup
    //   8699: bipush #58
    //   8701: ldc 69206016
    //   8703: iastore
    //   8704: dup
    //   8705: bipush #59
    //   8707: sipush #2048
    //   8710: iastore
    //   8711: dup
    //   8712: bipush #60
    //   8714: ldc 67108866
    //   8716: iastore
    //   8717: dup
    //   8718: bipush #61
    //   8720: ldc 67110912
    //   8722: iastore
    //   8723: dup
    //   8724: bipush #62
    //   8726: sipush #2048
    //   8729: iastore
    //   8730: dup
    //   8731: bipush #63
    //   8733: ldc 2097154
    //   8735: iastore
    //   8736: astore #15
    //   8738: bipush #64
    //   8740: newarray int
    //   8742: dup
    //   8743: iconst_0
    //   8744: ldc 268439616
    //   8746: iastore
    //   8747: dup
    //   8748: iconst_1
    //   8749: sipush #4096
    //   8752: iastore
    //   8753: dup
    //   8754: iconst_2
    //   8755: ldc 262144
    //   8757: iastore
    //   8758: dup
    //   8759: iconst_3
    //   8760: ldc 268701760
    //   8762: iastore
    //   8763: dup
    //   8764: iconst_4
    //   8765: ldc 268435456
    //   8767: iastore
    //   8768: dup
    //   8769: iconst_5
    //   8770: ldc 268439616
    //   8772: iastore
    //   8773: dup
    //   8774: bipush #6
    //   8776: bipush #64
    //   8778: iastore
    //   8779: dup
    //   8780: bipush #7
    //   8782: ldc 268435456
    //   8784: iastore
    //   8785: dup
    //   8786: bipush #8
    //   8788: ldc 262208
    //   8790: iastore
    //   8791: dup
    //   8792: bipush #9
    //   8794: ldc 268697600
    //   8796: iastore
    //   8797: dup
    //   8798: bipush #10
    //   8800: ldc 268701760
    //   8802: iastore
    //   8803: dup
    //   8804: bipush #11
    //   8806: ldc 266240
    //   8808: iastore
    //   8809: dup
    //   8810: bipush #12
    //   8812: ldc 268701696
    //   8814: iastore
    //   8815: dup
    //   8816: bipush #13
    //   8818: ldc 266304
    //   8820: iastore
    //   8821: dup
    //   8822: bipush #14
    //   8824: sipush #4096
    //   8827: iastore
    //   8828: dup
    //   8829: bipush #15
    //   8831: bipush #64
    //   8833: iastore
    //   8834: dup
    //   8835: bipush #16
    //   8837: ldc 268697600
    //   8839: iastore
    //   8840: dup
    //   8841: bipush #17
    //   8843: ldc 268435520
    //   8845: iastore
    //   8846: dup
    //   8847: bipush #18
    //   8849: ldc 268439552
    //   8851: iastore
    //   8852: dup
    //   8853: bipush #19
    //   8855: sipush #4160
    //   8858: iastore
    //   8859: dup
    //   8860: bipush #20
    //   8862: ldc 266240
    //   8864: iastore
    //   8865: dup
    //   8866: bipush #21
    //   8868: ldc 262208
    //   8870: iastore
    //   8871: dup
    //   8872: bipush #22
    //   8874: ldc 268697664
    //   8876: iastore
    //   8877: dup
    //   8878: bipush #23
    //   8880: ldc 268701696
    //   8882: iastore
    //   8883: dup
    //   8884: bipush #24
    //   8886: sipush #4160
    //   8889: iastore
    //   8890: dup
    //   8891: bipush #25
    //   8893: iconst_0
    //   8894: iastore
    //   8895: dup
    //   8896: bipush #26
    //   8898: iconst_0
    //   8899: iastore
    //   8900: dup
    //   8901: bipush #27
    //   8903: ldc 268697664
    //   8905: iastore
    //   8906: dup
    //   8907: bipush #28
    //   8909: ldc 268435520
    //   8911: iastore
    //   8912: dup
    //   8913: bipush #29
    //   8915: ldc 268439552
    //   8917: iastore
    //   8918: dup
    //   8919: bipush #30
    //   8921: ldc 266304
    //   8923: iastore
    //   8924: dup
    //   8925: bipush #31
    //   8927: ldc 262144
    //   8929: iastore
    //   8930: dup
    //   8931: bipush #32
    //   8933: ldc 266304
    //   8935: iastore
    //   8936: dup
    //   8937: bipush #33
    //   8939: ldc 262144
    //   8941: iastore
    //   8942: dup
    //   8943: bipush #34
    //   8945: ldc 268701696
    //   8947: iastore
    //   8948: dup
    //   8949: bipush #35
    //   8951: sipush #4096
    //   8954: iastore
    //   8955: dup
    //   8956: bipush #36
    //   8958: bipush #64
    //   8960: iastore
    //   8961: dup
    //   8962: bipush #37
    //   8964: ldc 268697664
    //   8966: iastore
    //   8967: dup
    //   8968: bipush #38
    //   8970: sipush #4096
    //   8973: iastore
    //   8974: dup
    //   8975: bipush #39
    //   8977: ldc 266304
    //   8979: iastore
    //   8980: dup
    //   8981: bipush #40
    //   8983: ldc 268439552
    //   8985: iastore
    //   8986: dup
    //   8987: bipush #41
    //   8989: bipush #64
    //   8991: iastore
    //   8992: dup
    //   8993: bipush #42
    //   8995: ldc 268435520
    //   8997: iastore
    //   8998: dup
    //   8999: bipush #43
    //   9001: ldc 268697600
    //   9003: iastore
    //   9004: dup
    //   9005: bipush #44
    //   9007: ldc 268697664
    //   9009: iastore
    //   9010: dup
    //   9011: bipush #45
    //   9013: ldc 268435456
    //   9015: iastore
    //   9016: dup
    //   9017: bipush #46
    //   9019: ldc 262144
    //   9021: iastore
    //   9022: dup
    //   9023: bipush #47
    //   9025: ldc 268439616
    //   9027: iastore
    //   9028: dup
    //   9029: bipush #48
    //   9031: iconst_0
    //   9032: iastore
    //   9033: dup
    //   9034: bipush #49
    //   9036: ldc 268701760
    //   9038: iastore
    //   9039: dup
    //   9040: bipush #50
    //   9042: ldc 262208
    //   9044: iastore
    //   9045: dup
    //   9046: bipush #51
    //   9048: ldc 268435520
    //   9050: iastore
    //   9051: dup
    //   9052: bipush #52
    //   9054: ldc 268697600
    //   9056: iastore
    //   9057: dup
    //   9058: bipush #53
    //   9060: ldc 268439552
    //   9062: iastore
    //   9063: dup
    //   9064: bipush #54
    //   9066: ldc 268439616
    //   9068: iastore
    //   9069: dup
    //   9070: bipush #55
    //   9072: iconst_0
    //   9073: iastore
    //   9074: dup
    //   9075: bipush #56
    //   9077: ldc 268701760
    //   9079: iastore
    //   9080: dup
    //   9081: bipush #57
    //   9083: ldc 266240
    //   9085: iastore
    //   9086: dup
    //   9087: bipush #58
    //   9089: ldc 266240
    //   9091: iastore
    //   9092: dup
    //   9093: bipush #59
    //   9095: sipush #4160
    //   9098: iastore
    //   9099: dup
    //   9100: bipush #60
    //   9102: sipush #4160
    //   9105: iastore
    //   9106: dup
    //   9107: bipush #61
    //   9109: ldc 262208
    //   9111: iastore
    //   9112: dup
    //   9113: bipush #62
    //   9115: ldc 268435456
    //   9117: iastore
    //   9118: dup
    //   9119: bipush #63
    //   9121: ldc 268701696
    //   9123: iastore
    //   9124: astore #16
    //   9126: aload #4
    //   9128: arraylength
    //   9129: istore #17
    //   9131: iconst_2
    //   9132: newarray int
    //   9134: astore #18
    //   9136: iload #17
    //   9138: newarray byte
    //   9140: astore #5
    //   9142: iload #17
    //   9144: bipush #8
    //   9146: idiv
    //   9147: istore #19
    //   9149: iconst_0
    //   9150: istore #20
    //   9152: iload #20
    //   9154: iload #19
    //   9156: if_icmpge -> 10074
    //   9159: iload #20
    //   9161: bipush #8
    //   9163: imul
    //   9164: istore #21
    //   9166: iconst_0
    //   9167: istore #22
    //   9169: iload #22
    //   9171: iconst_2
    //   9172: if_icmpge -> 9261
    //   9175: aload #18
    //   9177: iload #22
    //   9179: aload #4
    //   9181: iload #21
    //   9183: iload #22
    //   9185: iconst_4
    //   9186: imul
    //   9187: iadd
    //   9188: baload
    //   9189: sipush #255
    //   9192: iand
    //   9193: bipush #24
    //   9195: ishl
    //   9196: aload #4
    //   9198: iload #21
    //   9200: iload #22
    //   9202: iconst_4
    //   9203: imul
    //   9204: iadd
    //   9205: iconst_1
    //   9206: iadd
    //   9207: baload
    //   9208: sipush #255
    //   9211: iand
    //   9212: bipush #16
    //   9214: ishl
    //   9215: ior
    //   9216: aload #4
    //   9218: iload #21
    //   9220: iload #22
    //   9222: iconst_4
    //   9223: imul
    //   9224: iadd
    //   9225: iconst_2
    //   9226: iadd
    //   9227: baload
    //   9228: sipush #255
    //   9231: iand
    //   9232: bipush #8
    //   9234: ishl
    //   9235: ior
    //   9236: aload #4
    //   9238: iload #21
    //   9240: iload #22
    //   9242: iconst_4
    //   9243: imul
    //   9244: iadd
    //   9245: iconst_3
    //   9246: iadd
    //   9247: baload
    //   9248: sipush #255
    //   9251: iand
    //   9252: ior
    //   9253: iastore
    //   9254: iinc #22, 1
    //   9257: iload_2
    //   9258: ifne -> 9169
    //   9261: iconst_0
    //   9262: istore #27
    //   9264: aload #18
    //   9266: iconst_0
    //   9267: iaload
    //   9268: istore #25
    //   9270: aload #18
    //   9272: iconst_1
    //   9273: iaload
    //   9274: istore #24
    //   9276: iload #25
    //   9278: iconst_4
    //   9279: iushr
    //   9280: iload #24
    //   9282: ixor
    //   9283: ldc 252645135
    //   9285: iand
    //   9286: istore #23
    //   9288: iload #24
    //   9290: iload #23
    //   9292: ixor
    //   9293: istore #24
    //   9295: iload #25
    //   9297: iload #23
    //   9299: iconst_4
    //   9300: ishl
    //   9301: ixor
    //   9302: istore #25
    //   9304: iload #25
    //   9306: bipush #16
    //   9308: iushr
    //   9309: iload #24
    //   9311: ixor
    //   9312: ldc 65535
    //   9314: iand
    //   9315: istore #23
    //   9317: iload #24
    //   9319: iload #23
    //   9321: ixor
    //   9322: istore #24
    //   9324: iload #25
    //   9326: iload #23
    //   9328: bipush #16
    //   9330: ishl
    //   9331: ixor
    //   9332: istore #25
    //   9334: iload #24
    //   9336: iconst_2
    //   9337: iushr
    //   9338: iload #25
    //   9340: ixor
    //   9341: ldc 858993459
    //   9343: iand
    //   9344: istore #23
    //   9346: iload #25
    //   9348: iload #23
    //   9350: ixor
    //   9351: istore #25
    //   9353: iload #24
    //   9355: iload #23
    //   9357: iconst_2
    //   9358: ishl
    //   9359: ixor
    //   9360: istore #24
    //   9362: iload #24
    //   9364: bipush #8
    //   9366: iushr
    //   9367: iload #25
    //   9369: ixor
    //   9370: ldc 16711935
    //   9372: iand
    //   9373: istore #23
    //   9375: iload #25
    //   9377: iload #23
    //   9379: ixor
    //   9380: istore #25
    //   9382: iload #24
    //   9384: iload #23
    //   9386: bipush #8
    //   9388: ishl
    //   9389: ixor
    //   9390: istore #24
    //   9392: iload #24
    //   9394: iconst_1
    //   9395: ishl
    //   9396: iload #24
    //   9398: bipush #31
    //   9400: iushr
    //   9401: iconst_1
    //   9402: iand
    //   9403: ior
    //   9404: istore #24
    //   9406: iload #25
    //   9408: iload #24
    //   9410: ixor
    //   9411: ldc -1431655766
    //   9413: iand
    //   9414: istore #23
    //   9416: iload #25
    //   9418: iload #23
    //   9420: ixor
    //   9421: istore #25
    //   9423: iload #24
    //   9425: iload #23
    //   9427: ixor
    //   9428: istore #24
    //   9430: iload #25
    //   9432: iconst_1
    //   9433: ishl
    //   9434: iload #25
    //   9436: bipush #31
    //   9438: iushr
    //   9439: iconst_1
    //   9440: iand
    //   9441: ior
    //   9442: istore #25
    //   9444: iconst_0
    //   9445: istore #26
    //   9447: iload #26
    //   9449: bipush #8
    //   9451: if_icmpge -> 9789
    //   9454: iload #24
    //   9456: bipush #28
    //   9458: ishl
    //   9459: iload #24
    //   9461: iconst_4
    //   9462: iushr
    //   9463: ior
    //   9464: istore #23
    //   9466: iload #23
    //   9468: aload #6
    //   9470: iload #27
    //   9472: iinc #27, 1
    //   9475: iaload
    //   9476: ixor
    //   9477: istore #23
    //   9479: aload #15
    //   9481: iload #23
    //   9483: bipush #63
    //   9485: iand
    //   9486: iaload
    //   9487: istore #22
    //   9489: iload #22
    //   9491: aload #13
    //   9493: iload #23
    //   9495: bipush #8
    //   9497: iushr
    //   9498: bipush #63
    //   9500: iand
    //   9501: iaload
    //   9502: ior
    //   9503: istore #22
    //   9505: iload #22
    //   9507: aload #11
    //   9509: iload #23
    //   9511: bipush #16
    //   9513: iushr
    //   9514: bipush #63
    //   9516: iand
    //   9517: iaload
    //   9518: ior
    //   9519: istore #22
    //   9521: iload #22
    //   9523: aload #9
    //   9525: iload #23
    //   9527: bipush #24
    //   9529: iushr
    //   9530: bipush #63
    //   9532: iand
    //   9533: iaload
    //   9534: ior
    //   9535: istore #22
    //   9537: iload #24
    //   9539: aload #6
    //   9541: iload #27
    //   9543: iinc #27, 1
    //   9546: iaload
    //   9547: ixor
    //   9548: istore #23
    //   9550: iload #22
    //   9552: aload #16
    //   9554: iload #23
    //   9556: bipush #63
    //   9558: iand
    //   9559: iaload
    //   9560: ior
    //   9561: istore #22
    //   9563: iload #22
    //   9565: aload #14
    //   9567: iload #23
    //   9569: bipush #8
    //   9571: iushr
    //   9572: bipush #63
    //   9574: iand
    //   9575: iaload
    //   9576: ior
    //   9577: istore #22
    //   9579: iload #22
    //   9581: aload #12
    //   9583: iload #23
    //   9585: bipush #16
    //   9587: iushr
    //   9588: bipush #63
    //   9590: iand
    //   9591: iaload
    //   9592: ior
    //   9593: istore #22
    //   9595: iload #22
    //   9597: aload #10
    //   9599: iload #23
    //   9601: bipush #24
    //   9603: iushr
    //   9604: bipush #63
    //   9606: iand
    //   9607: iaload
    //   9608: ior
    //   9609: istore #22
    //   9611: iload #25
    //   9613: iload #22
    //   9615: ixor
    //   9616: istore #25
    //   9618: iload #25
    //   9620: bipush #28
    //   9622: ishl
    //   9623: iload #25
    //   9625: iconst_4
    //   9626: iushr
    //   9627: ior
    //   9628: istore #23
    //   9630: iload #23
    //   9632: aload #6
    //   9634: iload #27
    //   9636: iinc #27, 1
    //   9639: iaload
    //   9640: ixor
    //   9641: istore #23
    //   9643: aload #15
    //   9645: iload #23
    //   9647: bipush #63
    //   9649: iand
    //   9650: iaload
    //   9651: istore #22
    //   9653: iload #22
    //   9655: aload #13
    //   9657: iload #23
    //   9659: bipush #8
    //   9661: iushr
    //   9662: bipush #63
    //   9664: iand
    //   9665: iaload
    //   9666: ior
    //   9667: istore #22
    //   9669: iload #22
    //   9671: aload #11
    //   9673: iload #23
    //   9675: bipush #16
    //   9677: iushr
    //   9678: bipush #63
    //   9680: iand
    //   9681: iaload
    //   9682: ior
    //   9683: istore #22
    //   9685: iload #22
    //   9687: aload #9
    //   9689: iload #23
    //   9691: bipush #24
    //   9693: iushr
    //   9694: bipush #63
    //   9696: iand
    //   9697: iaload
    //   9698: ior
    //   9699: istore #22
    //   9701: iload #25
    //   9703: aload #6
    //   9705: iload #27
    //   9707: iinc #27, 1
    //   9710: iaload
    //   9711: ixor
    //   9712: istore #23
    //   9714: iload #22
    //   9716: aload #16
    //   9718: iload #23
    //   9720: bipush #63
    //   9722: iand
    //   9723: iaload
    //   9724: ior
    //   9725: istore #22
    //   9727: iload #22
    //   9729: aload #14
    //   9731: iload #23
    //   9733: bipush #8
    //   9735: iushr
    //   9736: bipush #63
    //   9738: iand
    //   9739: iaload
    //   9740: ior
    //   9741: istore #22
    //   9743: iload #22
    //   9745: aload #12
    //   9747: iload #23
    //   9749: bipush #16
    //   9751: iushr
    //   9752: bipush #63
    //   9754: iand
    //   9755: iaload
    //   9756: ior
    //   9757: istore #22
    //   9759: iload #22
    //   9761: aload #10
    //   9763: iload #23
    //   9765: bipush #24
    //   9767: iushr
    //   9768: bipush #63
    //   9770: iand
    //   9771: iaload
    //   9772: ior
    //   9773: istore #22
    //   9775: iload #24
    //   9777: iload #22
    //   9779: ixor
    //   9780: istore #24
    //   9782: iinc #26, 1
    //   9785: iload_2
    //   9786: ifne -> 9447
    //   9789: iload #24
    //   9791: bipush #31
    //   9793: ishl
    //   9794: iload #24
    //   9796: iconst_1
    //   9797: iushr
    //   9798: ior
    //   9799: istore #24
    //   9801: iload #25
    //   9803: iload #24
    //   9805: ixor
    //   9806: ldc -1431655766
    //   9808: iand
    //   9809: istore #23
    //   9811: iload #25
    //   9813: iload #23
    //   9815: ixor
    //   9816: istore #25
    //   9818: iload #24
    //   9820: iload #23
    //   9822: ixor
    //   9823: istore #24
    //   9825: iload #25
    //   9827: bipush #31
    //   9829: ishl
    //   9830: iload #25
    //   9832: iconst_1
    //   9833: iushr
    //   9834: ior
    //   9835: istore #25
    //   9837: iload #25
    //   9839: bipush #8
    //   9841: iushr
    //   9842: iload #24
    //   9844: ixor
    //   9845: ldc 16711935
    //   9847: iand
    //   9848: istore #23
    //   9850: iload #24
    //   9852: iload #23
    //   9854: ixor
    //   9855: istore #24
    //   9857: iload #25
    //   9859: iload #23
    //   9861: bipush #8
    //   9863: ishl
    //   9864: ixor
    //   9865: istore #25
    //   9867: iload #25
    //   9869: iconst_2
    //   9870: iushr
    //   9871: iload #24
    //   9873: ixor
    //   9874: ldc 858993459
    //   9876: iand
    //   9877: istore #23
    //   9879: iload #24
    //   9881: iload #23
    //   9883: ixor
    //   9884: istore #24
    //   9886: iload #25
    //   9888: iload #23
    //   9890: iconst_2
    //   9891: ishl
    //   9892: ixor
    //   9893: istore #25
    //   9895: iload #24
    //   9897: bipush #16
    //   9899: iushr
    //   9900: iload #25
    //   9902: ixor
    //   9903: ldc 65535
    //   9905: iand
    //   9906: istore #23
    //   9908: iload #25
    //   9910: iload #23
    //   9912: ixor
    //   9913: istore #25
    //   9915: iload #24
    //   9917: iload #23
    //   9919: bipush #16
    //   9921: ishl
    //   9922: ixor
    //   9923: istore #24
    //   9925: iload #24
    //   9927: iconst_4
    //   9928: iushr
    //   9929: iload #25
    //   9931: ixor
    //   9932: ldc 252645135
    //   9934: iand
    //   9935: istore #23
    //   9937: iload #25
    //   9939: iload #23
    //   9941: ixor
    //   9942: istore #25
    //   9944: iload #24
    //   9946: iload #23
    //   9948: iconst_4
    //   9949: ishl
    //   9950: ixor
    //   9951: istore #24
    //   9953: aload #18
    //   9955: iconst_0
    //   9956: iload #24
    //   9958: iastore
    //   9959: aload #18
    //   9961: iconst_1
    //   9962: iload #25
    //   9964: iastore
    //   9965: iload #20
    //   9967: bipush #8
    //   9969: imul
    //   9970: istore #28
    //   9972: iconst_0
    //   9973: istore #29
    //   9975: iload #29
    //   9977: iconst_2
    //   9978: if_icmpge -> 10067
    //   9981: aload #5
    //   9983: iload #28
    //   9985: iload #29
    //   9987: iconst_4
    //   9988: imul
    //   9989: iadd
    //   9990: aload #18
    //   9992: iload #29
    //   9994: iaload
    //   9995: bipush #24
    //   9997: iushr
    //   9998: i2b
    //   9999: bastore
    //   10000: aload #5
    //   10002: iload #28
    //   10004: iload #29
    //   10006: iconst_4
    //   10007: imul
    //   10008: iadd
    //   10009: iconst_1
    //   10010: iadd
    //   10011: aload #18
    //   10013: iload #29
    //   10015: iaload
    //   10016: bipush #16
    //   10018: iushr
    //   10019: i2b
    //   10020: bastore
    //   10021: aload #5
    //   10023: iload #28
    //   10025: iload #29
    //   10027: iconst_4
    //   10028: imul
    //   10029: iadd
    //   10030: iconst_2
    //   10031: iadd
    //   10032: aload #18
    //   10034: iload #29
    //   10036: iaload
    //   10037: bipush #8
    //   10039: iushr
    //   10040: i2b
    //   10041: bastore
    //   10042: aload #5
    //   10044: iload #28
    //   10046: iload #29
    //   10048: iconst_4
    //   10049: imul
    //   10050: iadd
    //   10051: iconst_3
    //   10052: iadd
    //   10053: aload #18
    //   10055: iload #29
    //   10057: iaload
    //   10058: i2b
    //   10059: bastore
    //   10060: iinc #29, 1
    //   10063: iload_2
    //   10064: ifne -> 9975
    //   10067: iinc #20, 1
    //   10070: iload_2
    //   10071: ifne -> 9152
    //   10074: new java/math/BigInteger
    //   10077: dup
    //   10078: aload #5
    //   10080: invokespecial <init> : ([B)V
    //   10083: invokevirtual abs : ()Ljava/math/BigInteger;
    //   10086: putstatic burp/Zmhx.ZQ : Ljava/lang/Object;
    //   10089: sipush #2735
    //   10092: sipush #3215
    //   10095: invokestatic a : (II)Ljava/lang/String;
    //   10098: iconst_1
    //   10099: ldc burp/Zmlu
    //   10101: invokevirtual getClassLoader : ()Ljava/lang/ClassLoader;
    //   10104: invokestatic forName : (Ljava/lang/String;ZLjava/lang/ClassLoader;)Ljava/lang/Class;
    //   10107: invokevirtual getDeclaredFields : ()[Ljava/lang/reflect/Field;
    //   10110: astore #4
    //   10112: aload #4
    //   10114: arraylength
    //   10115: istore #5
    //   10117: iconst_0
    //   10118: istore #6
    //   10120: iload #6
    //   10122: iload #5
    //   10124: if_icmpge -> 10262
    //   10127: aload #4
    //   10129: iload #6
    //   10131: aaload
    //   10132: astore #7
    //   10134: aload #7
    //   10136: invokevirtual getModifiers : ()I
    //   10139: invokestatic isStatic : (I)Z
    //   10142: ifne -> 10152
    //   10145: goto -> 10255
    //   10148: invokestatic a : (Ljava/lang/Throwable;)Ljava/lang/Throwable;
    //   10151: athrow
    //   10152: aload #7
    //   10154: invokevirtual getType : ()Ljava/lang/Class;
    //   10157: astore #8
    //   10159: aload #8
    //   10161: ifnull -> 10242
    //   10164: aload #8
    //   10166: invokevirtual isPrimitive : ()Z
    //   10169: ifne -> 10242
    //   10172: goto -> 10179
    //   10175: invokestatic a : (Ljava/lang/Throwable;)Ljava/lang/Throwable;
    //   10178: athrow
    //   10179: aload #8
    //   10181: invokevirtual getPackage : ()Ljava/lang/Package;
    //   10184: ifnull -> 10242
    //   10187: goto -> 10194
    //   10190: invokestatic a : (Ljava/lang/Throwable;)Ljava/lang/Throwable;
    //   10193: athrow
    //   10194: aload #8
    //   10196: invokevirtual getPackage : ()Ljava/lang/Package;
    //   10199: invokevirtual getName : ()Ljava/lang/String;
    //   10202: ifnull -> 10242
    //   10205: goto -> 10212
    //   10208: invokestatic a : (Ljava/lang/Throwable;)Ljava/lang/Throwable;
    //   10211: athrow
    //   10212: aload #8
    //   10214: invokevirtual getPackage : ()Ljava/lang/Package;
    //   10217: invokevirtual getName : ()Ljava/lang/String;
    //   10220: sipush #2721
    //   10223: sipush #25730
    //   10226: invokestatic a : (II)Ljava/lang/String;
    //   10229: invokevirtual startsWith : (Ljava/lang/String;)Z
    //   10232: ifne -> 10242
    //   10235: goto -> 10242
    //   10238: invokestatic a : (Ljava/lang/Throwable;)Ljava/lang/Throwable;
    //   10241: athrow
    //   10242: aload #7
    //   10244: iconst_1
    //   10245: invokevirtual setAccessible : (Z)V
    //   10248: aload #7
    //   10250: aconst_null
    //   10251: invokevirtual get : (Ljava/lang/Object;)Ljava/lang/Object;
    //   10254: pop
    //   10255: iinc #6, 1
    //   10258: iload_2
    //   10259: ifne -> 10120
    //   10262: sipush #2720
    //   10265: sipush #-25401
    //   10268: invokestatic a : (II)Ljava/lang/String;
    //   10271: invokestatic forName : (Ljava/lang/String;)Ljava/lang/Class;
    //   10274: invokevirtual getDeclaredMethods : ()[Ljava/lang/reflect/Method;
    //   10277: astore #4
    //   10279: aload #4
    //   10281: arraylength
    //   10282: istore #5
    //   10284: iconst_0
    //   10285: istore #6
    //   10287: iload #6
    //   10289: iload #5
    //   10291: if_icmpge -> 10424
    //   10294: aload #4
    //   10296: iload #6
    //   10298: aaload
    //   10299: astore #7
    //   10301: aload #7
    //   10303: invokevirtual getParameterTypes : ()[Ljava/lang/Class;
    //   10306: pop
    //   10307: aload #7
    //   10309: invokevirtual getModifiers : ()I
    //   10312: invokestatic isStatic : (I)Z
    //   10315: ifeq -> 10410
    //   10318: aload #7
    //   10320: invokevirtual getParameterTypes : ()[Ljava/lang/Class;
    //   10323: arraylength
    //   10324: iconst_2
    //   10325: if_icmpne -> 10410
    //   10328: goto -> 10335
    //   10331: invokestatic a : (Ljava/lang/Throwable;)Ljava/lang/Throwable;
    //   10334: athrow
    //   10335: aload #7
    //   10337: invokevirtual getReturnType : ()Ljava/lang/Class;
    //   10340: getstatic java/lang/Void.TYPE : Ljava/lang/Class;
    //   10343: invokevirtual equals : (Ljava/lang/Object;)Z
    //   10346: ifeq -> 10410
    //   10349: goto -> 10356
    //   10352: invokestatic a : (Ljava/lang/Throwable;)Ljava/lang/Throwable;
    //   10355: athrow
    //   10356: aload #7
    //   10358: iconst_1
    //   10359: invokevirtual setAccessible : (Z)V
    //   10362: aload #7
    //   10364: aconst_null
    //   10365: iconst_2
    //   10366: anewarray java/lang/Object
    //   10369: dup
    //   10370: iconst_0
    //   10371: aload_0
    //   10372: aastore
    //   10373: dup
    //   10374: iconst_1
    //   10375: aload_1
    //   10376: ifnonnull -> 10394
    //   10379: goto -> 10386
    //   10382: invokestatic a : (Ljava/lang/Throwable;)Ljava/lang/Throwable;
    //   10385: athrow
    //   10386: aload_1
    //   10387: goto -> 10401
    //   10390: invokestatic a : (Ljava/lang/Throwable;)Ljava/lang/Throwable;
    //   10393: athrow
    //   10394: aload_1
    //   10395: checkcast [B
    //   10398: invokevirtual clone : ()Ljava/lang/Object;
    //   10401: aastore
    //   10402: invokevirtual invoke : (Ljava/lang/Object;[Ljava/lang/Object;)Ljava/lang/Object;
    //   10405: pop
    //   10406: iload_2
    //   10407: ifne -> 10424
    //   10410: iinc #6, 1
    //   10413: iload_2
    //   10414: ifne -> 10287
    //   10417: goto -> 10424
    //   10420: invokestatic a : (Ljava/lang/Throwable;)Ljava/lang/Throwable;
    //   10423: athrow
    //   10424: iconst_0
    //   10425: istore #4
    //   10427: sipush #2733
    //   10430: sipush #14693
    //   10433: invokestatic a : (II)Ljava/lang/String;
    //   10436: iconst_1
    //   10437: ldc burp/Zgre
    //   10439: invokevirtual getClassLoader : ()Ljava/lang/ClassLoader;
    //   10442: invokestatic forName : (Ljava/lang/String;ZLjava/lang/ClassLoader;)Ljava/lang/Class;
    //   10445: invokevirtual getDeclaredFields : ()[Ljava/lang/reflect/Field;
    //   10448: astore #5
    //   10450: aload #5
    //   10452: arraylength
    //   10453: istore #6
    //   10455: iconst_0
    //   10456: istore #7
    //   10458: iload #7
    //   10460: iload #6
    //   10462: if_icmpge -> 10600
    //   10465: aload #5
    //   10467: iload #7
    //   10469: aaload
    //   10470: astore #8
    //   10472: aload #8
    //   10474: invokevirtual getModifiers : ()I
    //   10477: invokestatic isStatic : (I)Z
    //   10480: ifne -> 10490
    //   10483: goto -> 10593
    //   10486: invokestatic a : (Ljava/lang/Throwable;)Ljava/lang/Throwable;
    //   10489: athrow
    //   10490: aload #8
    //   10492: invokevirtual getType : ()Ljava/lang/Class;
    //   10495: astore #9
    //   10497: aload #9
    //   10499: ifnull -> 10580
    //   10502: aload #9
    //   10504: invokevirtual isPrimitive : ()Z
    //   10507: ifne -> 10580
    //   10510: goto -> 10517
    //   10513: invokestatic a : (Ljava/lang/Throwable;)Ljava/lang/Throwable;
    //   10516: athrow
    //   10517: aload #9
    //   10519: invokevirtual getPackage : ()Ljava/lang/Package;
    //   10522: ifnull -> 10580
    //   10525: goto -> 10532
    //   10528: invokestatic a : (Ljava/lang/Throwable;)Ljava/lang/Throwable;
    //   10531: athrow
    //   10532: aload #9
    //   10534: invokevirtual getPackage : ()Ljava/lang/Package;
    //   10537: invokevirtual getName : ()Ljava/lang/String;
    //   10540: ifnull -> 10580
    //   10543: goto -> 10550
    //   10546: invokestatic a : (Ljava/lang/Throwable;)Ljava/lang/Throwable;
    //   10549: athrow
    //   10550: aload #9
    //   10552: invokevirtual getPackage : ()Ljava/lang/Package;
    //   10555: invokevirtual getName : ()Ljava/lang/String;
    //   10558: sipush #2724
    //   10561: sipush #3681
    //   10564: invokestatic a : (II)Ljava/lang/String;
    //   10567: invokevirtual startsWith : (Ljava/lang/String;)Z
    //   10570: ifne -> 10580
    //   10573: goto -> 10580
    //   10576: invokestatic a : (Ljava/lang/Throwable;)Ljava/lang/Throwable;
    //   10579: athrow
    //   10580: aload #8
    //   10582: iconst_1
    //   10583: invokevirtual setAccessible : (Z)V
    //   10586: aload #8
    //   10588: aconst_null
    //   10589: invokevirtual get : (Ljava/lang/Object;)Ljava/lang/Object;
    //   10592: pop
    //   10593: iinc #7, 1
    //   10596: iload_2
    //   10597: ifne -> 10458
    //   10600: sipush #2732
    //   10603: sipush #6897
    //   10606: invokestatic a : (II)Ljava/lang/String;
    //   10609: invokestatic forName : (Ljava/lang/String;)Ljava/lang/Class;
    //   10612: invokevirtual getDeclaredMethods : ()[Ljava/lang/reflect/Method;
    //   10615: astore #5
    //   10617: aload #5
    //   10619: arraylength
    //   10620: istore #6
    //   10622: iconst_0
    //   10623: istore #7
    //   10625: iload #7
    //   10627: iload #6
    //   10629: if_icmpge -> 10766
    //   10632: aload #5
    //   10634: iload #7
    //   10636: aaload
    //   10637: astore #8
    //   10639: aload #8
    //   10641: invokevirtual getParameterTypes : ()[Ljava/lang/Class;
    //   10644: pop
    //   10645: aload #8
    //   10647: invokevirtual getModifiers : ()I
    //   10650: invokestatic isStatic : (I)Z
    //   10653: ifeq -> 10752
    //   10656: aload #8
    //   10658: invokevirtual getParameterTypes : ()[Ljava/lang/Class;
    //   10661: arraylength
    //   10662: iconst_2
    //   10663: if_icmpne -> 10752
    //   10666: goto -> 10673
    //   10669: invokestatic a : (Ljava/lang/Throwable;)Ljava/lang/Throwable;
    //   10672: athrow
    //   10673: aload #8
    //   10675: invokevirtual getReturnType : ()Ljava/lang/Class;
    //   10678: getstatic java/lang/Boolean.TYPE : Ljava/lang/Class;
    //   10681: if_acmpne -> 10752
    //   10684: goto -> 10691
    //   10687: invokestatic a : (Ljava/lang/Throwable;)Ljava/lang/Throwable;
    //   10690: athrow
    //   10691: aload #8
    //   10693: iconst_1
    //   10694: invokevirtual setAccessible : (Z)V
    //   10697: aload #8
    //   10699: aconst_null
    //   10700: iconst_2
    //   10701: anewarray java/lang/Object
    //   10704: dup
    //   10705: iconst_0
    //   10706: aload_0
    //   10707: aastore
    //   10708: dup
    //   10709: iconst_1
    //   10710: aload_1
    //   10711: ifnonnull -> 10729
    //   10714: goto -> 10721
    //   10717: invokestatic a : (Ljava/lang/Throwable;)Ljava/lang/Throwable;
    //   10720: athrow
    //   10721: aload_1
    //   10722: goto -> 10736
    //   10725: invokestatic a : (Ljava/lang/Throwable;)Ljava/lang/Throwable;
    //   10728: athrow
    //   10729: aload_1
    //   10730: checkcast [B
    //   10733: invokevirtual clone : ()Ljava/lang/Object;
    //   10736: aastore
    //   10737: invokevirtual invoke : (Ljava/lang/Object;[Ljava/lang/Object;)Ljava/lang/Object;
    //   10740: checkcast java/lang/Boolean
    //   10743: invokevirtual booleanValue : ()Z
    //   10746: istore #4
    //   10748: iload_2
    //   10749: ifne -> 10766
    //   10752: iinc #7, 1
    //   10755: iload_2
    //   10756: ifne -> 10625
    //   10759: goto -> 10766
    //   10762: invokestatic a : (Ljava/lang/Throwable;)Ljava/lang/Throwable;
    //   10765: athrow
    //   10766: iload #4
    //   10768: ireturn
    //   10769: astore_3
    //   10770: new java/lang/Exception
    //   10773: dup
    //   10774: aload_3
    //   10775: invokevirtual getMessage : ()Ljava/lang/String;
    //   10778: invokespecial <init> : (Ljava/lang/String;)V
    //   10781: athrow
    // Exception table:
    //   from	to	target	type
    //   4	10768	10769	java/lang/Throwable
    //   3328	3353	3353	java/lang/Throwable
    //   4316	4342	4342	java/lang/Throwable
    //   4407	4582	4585	java/lang/Throwable
    //   4552	4619	4622	java/lang/Throwable
    //   4589	4656	4659	java/lang/Throwable
    //   4626	4693	4696	java/lang/Throwable
    //   4663	4730	4733	java/lang/Throwable
    //   4700	4767	4770	java/lang/Throwable
    //   4737	4804	4807	java/lang/Throwable
    //   4774	4841	4844	java/lang/Throwable
    //   4811	4878	4881	java/lang/Throwable
    //   4848	4915	4918	java/lang/Throwable
    //   4885	4952	4955	java/lang/Throwable
    //   4922	4989	4992	java/lang/Throwable
    //   4959	5026	5029	java/lang/Throwable
    //   4996	5063	5066	java/lang/Throwable
    //   5033	5100	5103	java/lang/Throwable
    //   5070	5137	5140	java/lang/Throwable
    //   5107	5174	5177	java/lang/Throwable
    //   5144	5211	5214	java/lang/Throwable
    //   5181	5248	5251	java/lang/Throwable
    //   5218	5285	5288	java/lang/Throwable
    //   5255	5322	5325	java/lang/Throwable
    //   5292	5359	5362	java/lang/Throwable
    //   5329	5396	5399	java/lang/Throwable
    //   5366	5433	5436	java/lang/Throwable
    //   5403	5470	5473	java/lang/Throwable
    //   5440	5507	5510	java/lang/Throwable
    //   5477	5544	5547	java/lang/Throwable
    //   5514	5581	5584	java/lang/Throwable
    //   5551	5618	5621	java/lang/Throwable
    //   5588	5655	5658	java/lang/Throwable
    //   5625	5692	5695	java/lang/Throwable
    //   5662	5725	5728	java/lang/Throwable
    //   10134	10148	10148	java/lang/Throwable
    //   10159	10172	10175	java/lang/Throwable
    //   10164	10187	10190	java/lang/Throwable
    //   10179	10205	10208	java/lang/Throwable
    //   10194	10235	10238	java/lang/Throwable
    //   10301	10328	10331	java/lang/Throwable
    //   10318	10349	10352	java/lang/Throwable
    //   10335	10379	10382	java/lang/Throwable
    //   10356	10390	10390	java/lang/Throwable
    //   10401	10417	10420	java/lang/Throwable
    //   10472	10486	10486	java/lang/Throwable
    //   10497	10510	10513	java/lang/Throwable
    //   10502	10525	10528	java/lang/Throwable
    //   10517	10543	10546	java/lang/Throwable
    //   10532	10573	10576	java/lang/Throwable
    //   10639	10666	10669	java/lang/Throwable
    //   10656	10684	10687	java/lang/Throwable
    //   10673	10714	10717	java/lang/Throwable
    //   10691	10725	10725	java/lang/Throwable
    //   10748	10759	10762	java/lang/Throwable
  }
  
  static void Zm(Object[] paramArrayOfObject, Object paramObject) throws Throwable {}
  
  static void ZO(Object paramObject) {
    Zltb.ZO = a(2729, 12394);
    Zltb.ZL = new BigInteger(a(2730, -13686));
    boolean bool = Zt2e.ZN();
    try {
      try {
        if (Zly0.ZE.charAt(Math.abs(((BigInteger)Zgd7.ZZ).intValue() % 32)) > Zgdj.Zt.charAt(Math.abs(((BigInteger)Zty5.Zf).intValue() % 32))) {
          try {
            Zrly.Zu(Class.forName(a(2722, 18824)));
            if (!bool)
              Zz67.ZX(Class.forName(a(2728, 19099))); 
          } catch (Throwable throwable) {
            throw a(null);
          } 
          return;
        } 
      } catch (Throwable throwable) {
        throw a(null);
      } 
      Zz67.ZX(Class.forName(a(2728, 19099)));
    } catch (Throwable throwable) {}
  }
  
  static {
    // Byte code:
    //   0: bipush #14
    //   2: anewarray java/lang/String
    //   5: astore #5
    //   7: iconst_0
    //   8: istore_3
    //   9: ldc 'lZIS_!WEx/CH\\t(3`_v-w<\\nKdm-vMcJjw.=^g(f6n7a4{]TzV[\\\f5/7mk$oIB^a'le\\tg1P\\tsH\\tTa^ ,;L|\\thj}S[q"\\tZw}Dy7\\t.Ku\\tb'
    //   11: dup
    //   12: astore_2
    //   13: invokevirtual length : ()I
    //   16: istore #4
    //   18: bipush #32
    //   20: istore_1
    //   21: iconst_m1
    //   22: istore_0
    //   23: bipush #96
    //   25: iinc #0, 1
    //   28: aload_2
    //   29: iload_0
    //   30: dup
    //   31: iload_1
    //   32: iadd
    //   33: invokevirtual substring : (II)Ljava/lang/String;
    //   36: iconst_m1
    //   37: goto -> 143
    //   40: aload #5
    //   42: swap
    //   43: iload_3
    //   44: iinc #3, 1
    //   47: swap
    //   48: aastore
    //   49: iload_0
    //   50: iload_1
    //   51: iadd
    //   52: dup
    //   53: istore_0
    //   54: iload #4
    //   56: if_icmpge -> 68
    //   59: aload_2
    //   60: iload_0
    //   61: invokevirtual charAt : (I)C
    //   64: istore_1
    //   65: goto -> 23
    //   68: ldc '\\rE(k\\b9- oV2I'
    //   70: dup
    //   71: astore_2
    //   72: invokevirtual length : ()I
    //   75: istore #4
    //   77: bipush #19
    //   79: istore_1
    //   80: iconst_m1
    //   81: istore_0
    //   82: bipush #35
    //   84: iinc #0, 1
    //   87: aload_2
    //   88: iload_0
    //   89: dup
    //   90: iload_1
    //   91: iadd
    //   92: invokevirtual substring : (II)Ljava/lang/String;
    //   95: iconst_0
    //   96: goto -> 143
    //   99: aload #5
    //   101: swap
    //   102: iload_3
    //   103: iinc #3, 1
    //   106: swap
    //   107: aastore
    //   108: iload_0
    //   109: iload_1
    //   110: iadd
    //   111: dup
    //   112: istore_0
    //   113: iload #4
    //   115: if_icmpge -> 127
    //   118: aload_2
    //   119: iload_0
    //   120: invokevirtual charAt : (I)C
    //   123: istore_1
    //   124: goto -> 82
    //   127: aload #5
    //   129: putstatic burp/Zezz.a : [Ljava/lang/String;
    //   132: bipush #14
    //   134: anewarray java/lang/String
    //   137: putstatic burp/Zezz.b : [Ljava/lang/String;
    //   140: goto -> 300
    //   143: dup_x2
    //   144: pop
    //   145: invokevirtual toCharArray : ()[C
    //   148: dup_x1
    //   149: arraylength
    //   150: dup_x2
    //   151: pop
    //   152: iconst_0
    //   153: istore #6
    //   155: dup2_x1
    //   156: pop2
    //   157: dup_x2
    //   158: iconst_1
    //   159: if_icmpgt -> 260
    //   162: dup2
    //   163: swap
    //   164: iload #6
    //   166: dup2_x1
    //   167: caload
    //   168: swap
    //   169: iload #6
    //   171: bipush #7
    //   173: irem
    //   174: tableswitch default -> 242, 0 -> 212, 1 -> 217, 2 -> 222, 3 -> 227, 4 -> 232, 5 -> 237
    //   212: bipush #25
    //   214: goto -> 244
    //   217: bipush #116
    //   219: goto -> 244
    //   222: bipush #37
    //   224: goto -> 244
    //   227: bipush #63
    //   229: goto -> 244
    //   232: bipush #49
    //   234: goto -> 244
    //   237: bipush #15
    //   239: goto -> 244
    //   242: bipush #34
    //   244: ixor
    //   245: ixor
    //   246: i2c
    //   247: castore
    //   248: iinc #6, 1
    //   251: dup
    //   252: ifne -> 260
    //   255: dup2
    //   256: dup_x1
    //   257: goto -> 166
    //   260: dup2_x1
    //   261: pop2
    //   262: dup_x2
    //   263: iload #6
    //   265: if_icmpgt -> 162
    //   268: pop
    //   269: new java/lang/String
    //   272: dup_x1
    //   273: swap
    //   274: invokespecial <init> : ([C)V
    //   277: invokevirtual intern : ()Ljava/lang/String;
    //   280: swap
    //   281: pop
    //   282: swap
    //   283: tableswitch default -> 40, 0 -> 99
    //   300: new java/math/BigInteger
    //   303: dup
    //   304: iconst_1
    //   305: bipush #32
    //   307: newarray byte
    //   309: dup
    //   310: iconst_0
    //   311: bipush #60
    //   313: bastore
    //   314: dup
    //   315: iconst_1
    //   316: bipush #43
    //   318: bastore
    //   319: dup
    //   320: iconst_2
    //   321: bipush #-47
    //   323: bastore
    //   324: dup
    //   325: iconst_3
    //   326: bipush #-63
    //   328: bastore
    //   329: dup
    //   330: iconst_4
    //   331: bipush #-30
    //   333: bastore
    //   334: dup
    //   335: iconst_5
    //   336: bipush #76
    //   338: bastore
    //   339: dup
    //   340: bipush #6
    //   342: bipush #-35
    //   344: bastore
    //   345: dup
    //   346: bipush #7
    //   348: bipush #42
    //   350: bastore
    //   351: dup
    //   352: bipush #8
    //   354: bipush #37
    //   356: bastore
    //   357: dup
    //   358: bipush #9
    //   360: bipush #66
    //   362: bastore
    //   363: dup
    //   364: bipush #10
    //   366: bipush #-43
    //   368: bastore
    //   369: dup
    //   370: bipush #11
    //   372: bipush #123
    //   374: bastore
    //   375: dup
    //   376: bipush #12
    //   378: bipush #45
    //   380: bastore
    //   381: dup
    //   382: bipush #13
    //   384: bipush #-118
    //   386: bastore
    //   387: dup
    //   388: bipush #14
    //   390: bipush #-120
    //   392: bastore
    //   393: dup
    //   394: bipush #15
    //   396: bipush #-126
    //   398: bastore
    //   399: dup
    //   400: bipush #16
    //   402: bipush #58
    //   404: bastore
    //   405: dup
    //   406: bipush #17
    //   408: bipush #-96
    //   410: bastore
    //   411: dup
    //   412: bipush #18
    //   414: bipush #18
    //   416: bastore
    //   417: dup
    //   418: bipush #19
    //   420: bipush #-125
    //   422: bastore
    //   423: dup
    //   424: bipush #20
    //   426: bipush #-31
    //   428: bastore
    //   429: dup
    //   430: bipush #21
    //   432: bipush #110
    //   434: bastore
    //   435: dup
    //   436: bipush #22
    //   438: bipush #-32
    //   440: bastore
    //   441: dup
    //   442: bipush #23
    //   444: bipush #60
    //   446: bastore
    //   447: dup
    //   448: bipush #24
    //   450: bipush #34
    //   452: bastore
    //   453: dup
    //   454: bipush #25
    //   456: bipush #-73
    //   458: bastore
    //   459: dup
    //   460: bipush #26
    //   462: bipush #-106
    //   464: bastore
    //   465: dup
    //   466: bipush #27
    //   468: bipush #-121
    //   470: bastore
    //   471: dup
    //   472: bipush #28
    //   474: bipush #70
    //   476: bastore
    //   477: dup
    //   478: bipush #29
    //   480: bipush #-18
    //   482: bastore
    //   483: dup
    //   484: bipush #30
    //   486: bipush #-54
    //   488: bastore
    //   489: dup
    //   490: bipush #31
    //   492: bipush #44
    //   494: bastore
    //   495: invokespecial <init> : (I[B)V
    //   498: putstatic burp/Zezz.Zu : Ljava/lang/Object;
    //   501: sipush #2734
    //   504: sipush #-26525
    //   507: invokestatic a : (II)Ljava/lang/String;
    //   510: putstatic burp/Zezz.Zi : Ljava/lang/String;
    //   513: return
  }
  
  private static Throwable a(Throwable paramThrowable) {
    return paramThrowable;
  }
  
  private static String a(int paramInt1, int paramInt2) {
    int i = (paramInt1 ^ 0xAA9) & 0xFFFF;
    if (b[i] == null) {
      char[] arrayOfChar = a[i].toCharArray();
      switch (arrayOfChar[0] & 0xFF) {
        case 0:
        
        case 1:
        
        case 2:
        
        case 3:
        
        case 4:
        
        case 5:
        
        case 6:
        
        case 7:
        
        case 8:
        
        case 9:
        
        case 10:
        
        case 11:
        
        case 12:
        
        case 13:
        
        case 14:
        
        case 15:
        
        case 16:
        
        case 17:
        
        case 18:
        
        case 19:
        
        case 20:
        
        case 21:
        
        case 22:
        
        case 23:
        
        case 24:
        
        case 25:
        
        case 26:
        
        case 27:
        
        case 28:
        
        case 29:
        
        case 30:
        
        case 31:
        
        case 32:
        
        case 33:
        
        case 34:
        
        case 35:
        
        case 36:
        
        case 37:
        
        case 38:
        
        case 39:
        
        case 40:
        
        case 41:
        
        case 42:
        
        case 43:
        
        case 44:
        
        case 45:
        
        case 46:
        
        case 47:
        
        case 48:
        
        case 49:
        
        case 50:
        
        case 51:
        
        case 52:
        
        case 53:
        
        case 54:
        
        case 55:
        
        case 56:
        
        case 57:
        
        case 58:
        
        case 59:
        
        case 60:
        
        case 61:
        
        case 62:
        
        case 63:
        
        case 64:
        
        case 65:
        
        case 66:
        
        case 67:
        
        case 68:
        
        case 69:
        
        case 70:
        
        case 71:
        
        case 72:
        
        case 73:
        
        case 74:
        
        case 75:
        
        case 76:
        
        case 77:
        
        case 78:
        
        case 79:
        
        case 80:
        
        case 81:
        
        case 82:
        
        case 83:
        
        case 84:
        
        case 85:
        
        case 86:
        
        case 87:
        
        case 88:
        
        case 89:
        
        case 90:
        
        case 91:
        
        case 92:
        
        case 93:
        
        case 94:
        
        case 95:
        
        case 96:
        
        case 97:
        
        case 98:
        
        case 99:
        
        case 100:
        
        case 101:
        
        case 102:
        
        case 103:
        
        case 104:
        
        case 105:
        
        case 106:
        
        case 107:
        
        case 108:
        
        case 109:
        
        case 110:
        
        case 111:
        
        case 112:
        
        case 113:
        
        case 114:
        
        case 115:
        
        case 116:
        
        case 117:
        
        case 118:
        
        case 119:
        
        case 120:
        
        case 121:
        
        case 122:
        
        case 123:
        
        case 124:
        
        case 125:
        
        case 126:
        
        case 127:
        
        case 128:
        
        case 129:
        
        case 130:
        
        case 131:
        
        case 132:
        
        case 133:
        
        case 134:
        
        case 135:
        
        case 136:
        
        case 137:
        
        case 138:
        
        case 139:
        
        case 140:
        
        case 141:
        
        case 142:
        
        case 143:
        
        case 144:
        
        case 145:
        
        case 146:
        
        case 147:
        
        case 148:
        
        case 149:
        
        case 150:
        
        case 151:
        
        case 152:
        
        case 153:
        
        case 154:
        
        case 155:
        
        case 156:
        
        case 157:
        
        case 158:
        
        case 159:
        
        case 160:
        
        case 161:
        
        case 162:
        
        case 163:
        
        case 164:
        
        case 165:
        
        case 166:
        
        case 167:
        
        case 168:
        
        case 169:
        
        case 170:
        
        case 171:
        
        case 172:
        
        case 173:
        
        case 174:
        
        case 175:
        
        case 176:
        
        case 177:
        
        case 178:
        
        case 179:
        
        case 180:
        
        case 181:
        
        case 182:
        
        case 183:
        
        case 184:
        
        case 185:
        
        case 186:
        
        case 187:
        
        case 188:
        
        case 189:
        
        case 190:
        
        case 191:
        
        case 192:
        
        case 193:
        
        case 194:
        
        case 195:
        
        case 196:
        
        case 197:
        
        case 198:
        
        case 199:
        
        case 200:
        
        case 201:
        
        case 202:
        
        case 203:
        
        case 204:
        
        case 205:
        
        case 206:
        
        case 207:
        
        case 208:
        
        case 209:
        
        case 210:
        
        case 211:
        
        case 212:
        
        case 213:
        
        case 214:
        
        case 215:
        
        case 216:
        
        case 217:
        
        case 218:
        
        case 219:
        
        case 220:
        
        case 221:
        
        case 222:
        
        case 223:
        
        case 224:
        
        case 225:
        
        case 226:
        
        case 227:
        
        case 228:
        
        case 229:
        
        case 230:
        
        case 231:
        
        case 232:
        
        case 233:
        
        case 234:
        
        case 235:
        
        case 236:
        
        case 237:
        
        case 238:
        
        case 239:
        
        case 240:
        
        case 241:
        
        case 242:
        
        case 243:
        
        case 244:
        
        case 245:
        
        case 246:
        
        case 247:
        
        case 248:
        
        case 249:
        
        case 250:
        
        case 251:
        
        case 252:
        
        case 253:
        
        case 254:
        
        default:
          break;
      } 
      char c = '';
      int j = (paramInt2 & 0xFF) - c;
      if (j < 0)
        j += 256; 
      int k = ((paramInt2 & 0xFFFF) >>> 8) - c;
      if (k < 0)
        k += 256; 
      for (byte b = 0; b < arrayOfChar.length; b++) {
        int m = b % 2;
        if (m == 0) {
          arrayOfChar[b] = (char)(arrayOfChar[b] ^ j);
          j = ((j >>> 3 | j << 5) ^ arrayOfChar[b]) & 0xFF;
        } else {
          arrayOfChar[b] = (char)(arrayOfChar[b] ^ k);
          k = ((k >>> 3 | k << 5) ^ arrayOfChar[b]) & 0xFF;
        } 
      } 
      b[i] = (new String(arrayOfChar)).intern();
    } 
    return b[i];
  }
}


/* Location:              C:\Program Files\BurpSuitePro\burpsuite_pro.jar!\burp\Zezz.class
 * Java compiler version: 21 (65.0)
 * JD-Core Version:       1.1.3
 */