package burp;

import java.awt.event.ActionEvent;
import java.awt.event.ActionListener;

class Zg1_ implements ActionListener {
  final Zbpy ZR;
  
  private Zg1_(Zbpy paramZbpy) {}
  
  public void actionPerformed(ActionEvent paramActionEvent) {
    // Byte code:
    //   0: invokestatic ZKe : ()Z
    //   3: istore_2
    //   4: aload_1
    //   5: invokevirtual getSource : ()Ljava/lang/Object;
    //   8: astore_3
    //   9: aload_3
    //   10: aload_0
    //   11: getfield ZR : Lburp/Zbpy;
    //   14: getfield ZD : Lburp/Zsuy;
    //   17: if_acmpne -> 112
    //   20: aload_0
    //   21: getfield ZR : Lburp/Zbpy;
    //   24: getfield ZD : Lburp/Zsuy;
    //   27: invokevirtual isSelected : ()Z
    //   30: istore #4
    //   32: aload_0
    //   33: getfield ZR : Lburp/Zbpy;
    //   36: getfield ZZ : [Lburp/Zxjc;
    //   39: astore #5
    //   41: aload #5
    //   43: arraylength
    //   44: istore #6
    //   46: iconst_0
    //   47: istore #7
    //   49: iload #7
    //   51: iload #6
    //   53: if_icmpge -> 96
    //   56: aload #5
    //   58: iload #7
    //   60: aaload
    //   61: astore #8
    //   63: aload #8
    //   65: iload #4
    //   67: putfield Zm : Z
    //   70: aload_0
    //   71: getfield ZR : Lburp/Zbpy;
    //   74: getfield ZU : Lburp/Zxz8;
    //   77: aload #8
    //   79: getfield Zl : Lburp/Zvs;
    //   82: iload #4
    //   84: invokeinterface ZX : (Lburp/Zvs;Z)V
    //   89: iinc #7, 1
    //   92: iload_2
    //   93: ifne -> 49
    //   96: aload_0
    //   97: getfield ZR : Lburp/Zbpy;
    //   100: getfield ZE : Lburp/Zrn8;
    //   103: invokeinterface ZG : ()V
    //   108: iload_2
    //   109: ifne -> 186
    //   112: aload_3
    //   113: aload_0
    //   114: getfield ZR : Lburp/Zbpy;
    //   117: getfield ZH : Lburp/Zepe;
    //   120: if_acmpne -> 156
    //   123: aload_0
    //   124: getfield ZR : Lburp/Zbpy;
    //   127: getfield Zp : Lburp/Zb93;
    //   130: aload_0
    //   131: getfield ZR : Lburp/Zbpy;
    //   134: getfield Zz : Ljava/awt/Window;
    //   137: aload_0
    //   138: getfield ZR : Lburp/Zbpy;
    //   141: getfield ZZ : [Lburp/Zxjc;
    //   144: iconst_0
    //   145: aaload
    //   146: getfield Zl : Lburp/Zvs;
    //   149: invokevirtual Zw : (Ljava/awt/Window;Lburp/Zvs;)V
    //   152: iload_2
    //   153: ifne -> 186
    //   156: aload_3
    //   157: aload_0
    //   158: getfield ZR : Lburp/Zbpy;
    //   161: getfield ZP : Lburp/Zepe;
    //   164: if_acmpne -> 186
    //   167: aload_0
    //   168: getfield ZR : Lburp/Zbpy;
    //   171: getfield Zp : Lburp/Zb93;
    //   174: aload_0
    //   175: getfield ZR : Lburp/Zbpy;
    //   178: getfield ZZ : [Lburp/Zxjc;
    //   181: iconst_0
    //   182: aaload
    //   183: invokevirtual Zt : (Lburp/Zxjc;)V
    //   186: return
  }
}


/* Location:              C:\Program Files\BurpSuitePro\burpsuite_pro.jar!\burp\Zg1_.class
 * Java compiler version: 21 (65.0)
 * JD-Core Version:       1.1.3
 */