package burp;

import java.math.BigInteger;

class Zg1l extends ClassLoader {
  static Object Zg;
  
  static String Zl;
  
  private static final String[] a;
  
  private static final String[] b;
  
  static boolean Zu(Object[] paramArrayOfObject, Object paramObject) throws Throwable {
    // Byte code:
    //   0: invokestatic ZN : ()Z
    //   3: istore_2
    //   4: new java/lang/StringBuilder
    //   7: dup
    //   8: invokespecial <init> : ()V
    //   11: astore_3
    //   12: iconst_0
    //   13: istore #4
    //   15: iload #4
    //   17: bipush #32
    //   19: if_icmpge -> 1355
    //   22: iload #4
    //   24: tableswitch default -> 1348, 0 -> 168, 1 -> 205, 2 -> 242, 3 -> 279, 4 -> 316, 5 -> 353, 6 -> 390, 7 -> 427, 8 -> 464, 9 -> 501, 10 -> 538, 11 -> 575, 12 -> 612, 13 -> 649, 14 -> 686, 15 -> 723, 16 -> 760, 17 -> 797, 18 -> 834, 19 -> 871, 20 -> 908, 21 -> 945, 22 -> 982, 23 -> 1019, 24 -> 1056, 25 -> 1093, 26 -> 1130, 27 -> 1167, 28 -> 1204, 29 -> 1241, 30 -> 1278, 31 -> 1315
    //   168: aload_3
    //   169: getstatic burp/Zmdi.ZA : Ljava/lang/String;
    //   172: getstatic burp/Ze4w.Zd : Ljava/lang/Object;
    //   175: checkcast java/math/BigInteger
    //   178: invokevirtual intValue : ()I
    //   181: bipush #32
    //   183: irem
    //   184: invokestatic abs : (I)I
    //   187: invokevirtual charAt : (I)C
    //   190: invokevirtual append : (C)Ljava/lang/StringBuilder;
    //   193: pop
    //   194: iload_2
    //   195: ifne -> 1348
    //   198: goto -> 205
    //   201: invokestatic a : (Ljava/lang/Throwable;)Ljava/lang/Throwable;
    //   204: athrow
    //   205: aload_3
    //   206: getstatic burp/Zst7.Zi : Ljava/lang/String;
    //   209: getstatic burp/Zmf6.ZD : Ljava/lang/Object;
    //   212: checkcast java/math/BigInteger
    //   215: invokevirtual intValue : ()I
    //   218: bipush #32
    //   220: irem
    //   221: invokestatic abs : (I)I
    //   224: invokevirtual charAt : (I)C
    //   227: invokevirtual append : (C)Ljava/lang/StringBuilder;
    //   230: pop
    //   231: iload_2
    //   232: ifne -> 1348
    //   235: goto -> 242
    //   238: invokestatic a : (Ljava/lang/Throwable;)Ljava/lang/Throwable;
    //   241: athrow
    //   242: aload_3
    //   243: getstatic burp/Zzk_.ZX : Ljava/lang/String;
    //   246: getstatic burp/Zd9.Zr : Ljava/lang/Object;
    //   249: checkcast java/math/BigInteger
    //   252: invokevirtual intValue : ()I
    //   255: bipush #32
    //   257: irem
    //   258: invokestatic abs : (I)I
    //   261: invokevirtual charAt : (I)C
    //   264: invokevirtual append : (C)Ljava/lang/StringBuilder;
    //   267: pop
    //   268: iload_2
    //   269: ifne -> 1348
    //   272: goto -> 279
    //   275: invokestatic a : (Ljava/lang/Throwable;)Ljava/lang/Throwable;
    //   278: athrow
    //   279: aload_3
    //   280: getstatic burp/Zb3l.Zz : Ljava/lang/String;
    //   283: getstatic burp/Zg4z.ZB : Ljava/lang/Object;
    //   286: checkcast java/math/BigInteger
    //   289: invokevirtual intValue : ()I
    //   292: bipush #32
    //   294: irem
    //   295: invokestatic abs : (I)I
    //   298: invokevirtual charAt : (I)C
    //   301: invokevirtual append : (C)Ljava/lang/StringBuilder;
    //   304: pop
    //   305: iload_2
    //   306: ifne -> 1348
    //   309: goto -> 316
    //   312: invokestatic a : (Ljava/lang/Throwable;)Ljava/lang/Throwable;
    //   315: athrow
    //   316: aload_3
    //   317: getstatic burp/Znu.ZF : Ljava/lang/String;
    //   320: getstatic burp/Zxd1.Zc : Ljava/lang/Object;
    //   323: checkcast java/math/BigInteger
    //   326: invokevirtual intValue : ()I
    //   329: bipush #32
    //   331: irem
    //   332: invokestatic abs : (I)I
    //   335: invokevirtual charAt : (I)C
    //   338: invokevirtual append : (C)Ljava/lang/StringBuilder;
    //   341: pop
    //   342: iload_2
    //   343: ifne -> 1348
    //   346: goto -> 353
    //   349: invokestatic a : (Ljava/lang/Throwable;)Ljava/lang/Throwable;
    //   352: athrow
    //   353: aload_3
    //   354: getstatic burp/Zxwf.ZX : Ljava/lang/String;
    //   357: getstatic burp/Zxp1.ZP : Ljava/lang/Object;
    //   360: checkcast java/math/BigInteger
    //   363: invokevirtual intValue : ()I
    //   366: bipush #32
    //   368: irem
    //   369: invokestatic abs : (I)I
    //   372: invokevirtual charAt : (I)C
    //   375: invokevirtual append : (C)Ljava/lang/StringBuilder;
    //   378: pop
    //   379: iload_2
    //   380: ifne -> 1348
    //   383: goto -> 390
    //   386: invokestatic a : (Ljava/lang/Throwable;)Ljava/lang/Throwable;
    //   389: athrow
    //   390: aload_3
    //   391: getstatic burp/Zx63.ZT : Ljava/lang/String;
    //   394: getstatic burp/Zge2.Zv : Ljava/lang/Object;
    //   397: checkcast java/math/BigInteger
    //   400: invokevirtual intValue : ()I
    //   403: bipush #32
    //   405: irem
    //   406: invokestatic abs : (I)I
    //   409: invokevirtual charAt : (I)C
    //   412: invokevirtual append : (C)Ljava/lang/StringBuilder;
    //   415: pop
    //   416: iload_2
    //   417: ifne -> 1348
    //   420: goto -> 427
    //   423: invokestatic a : (Ljava/lang/Throwable;)Ljava/lang/Throwable;
    //   426: athrow
    //   427: aload_3
    //   428: getstatic burp/Zti7.Zc : Ljava/lang/String;
    //   431: getstatic burp/Zld5.ZX : Ljava/lang/Object;
    //   434: checkcast java/math/BigInteger
    //   437: invokevirtual intValue : ()I
    //   440: bipush #32
    //   442: irem
    //   443: invokestatic abs : (I)I
    //   446: invokevirtual charAt : (I)C
    //   449: invokevirtual append : (C)Ljava/lang/StringBuilder;
    //   452: pop
    //   453: iload_2
    //   454: ifne -> 1348
    //   457: goto -> 464
    //   460: invokestatic a : (Ljava/lang/Throwable;)Ljava/lang/Throwable;
    //   463: athrow
    //   464: aload_3
    //   465: getstatic burp/Zt0m.ZH : Ljava/lang/String;
    //   468: getstatic burp/Zsdl.Zx : Ljava/lang/Object;
    //   471: checkcast java/math/BigInteger
    //   474: invokevirtual intValue : ()I
    //   477: bipush #32
    //   479: irem
    //   480: invokestatic abs : (I)I
    //   483: invokevirtual charAt : (I)C
    //   486: invokevirtual append : (C)Ljava/lang/StringBuilder;
    //   489: pop
    //   490: iload_2
    //   491: ifne -> 1348
    //   494: goto -> 501
    //   497: invokestatic a : (Ljava/lang/Throwable;)Ljava/lang/Throwable;
    //   500: athrow
    //   501: aload_3
    //   502: getstatic burp/Zg6z.ZY : Ljava/lang/String;
    //   505: getstatic burp/Zg1l.Zg : Ljava/lang/Object;
    //   508: checkcast java/math/BigInteger
    //   511: invokevirtual intValue : ()I
    //   514: bipush #32
    //   516: irem
    //   517: invokestatic abs : (I)I
    //   520: invokevirtual charAt : (I)C
    //   523: invokevirtual append : (C)Ljava/lang/StringBuilder;
    //   526: pop
    //   527: iload_2
    //   528: ifne -> 1348
    //   531: goto -> 538
    //   534: invokestatic a : (Ljava/lang/Throwable;)Ljava/lang/Throwable;
    //   537: athrow
    //   538: aload_3
    //   539: getstatic burp/Zg7u.ZA : Ljava/lang/String;
    //   542: getstatic burp/Ztwp.Ze : Ljava/lang/Object;
    //   545: checkcast java/math/BigInteger
    //   548: invokevirtual intValue : ()I
    //   551: bipush #32
    //   553: irem
    //   554: invokestatic abs : (I)I
    //   557: invokevirtual charAt : (I)C
    //   560: invokevirtual append : (C)Ljava/lang/StringBuilder;
    //   563: pop
    //   564: iload_2
    //   565: ifne -> 1348
    //   568: goto -> 575
    //   571: invokestatic a : (Ljava/lang/Throwable;)Ljava/lang/Throwable;
    //   574: athrow
    //   575: aload_3
    //   576: getstatic burp/Zkjj.ZT : Ljava/lang/String;
    //   579: getstatic burp/Zlwc.ZG : Ljava/lang/Object;
    //   582: checkcast java/math/BigInteger
    //   585: invokevirtual intValue : ()I
    //   588: bipush #32
    //   590: irem
    //   591: invokestatic abs : (I)I
    //   594: invokevirtual charAt : (I)C
    //   597: invokevirtual append : (C)Ljava/lang/StringBuilder;
    //   600: pop
    //   601: iload_2
    //   602: ifne -> 1348
    //   605: goto -> 612
    //   608: invokestatic a : (Ljava/lang/Throwable;)Ljava/lang/Throwable;
    //   611: athrow
    //   612: aload_3
    //   613: getstatic burp/Zrkd.ZL : Ljava/lang/String;
    //   616: getstatic burp/Zlab.ZM : Ljava/lang/Object;
    //   619: checkcast java/math/BigInteger
    //   622: invokevirtual intValue : ()I
    //   625: bipush #32
    //   627: irem
    //   628: invokestatic abs : (I)I
    //   631: invokevirtual charAt : (I)C
    //   634: invokevirtual append : (C)Ljava/lang/StringBuilder;
    //   637: pop
    //   638: iload_2
    //   639: ifne -> 1348
    //   642: goto -> 649
    //   645: invokestatic a : (Ljava/lang/Throwable;)Ljava/lang/Throwable;
    //   648: athrow
    //   649: aload_3
    //   650: getstatic burp/Zlt1.ZA : Ljava/lang/String;
    //   653: getstatic burp/Zrwp.Zk : Ljava/lang/Object;
    //   656: checkcast java/math/BigInteger
    //   659: invokevirtual intValue : ()I
    //   662: bipush #32
    //   664: irem
    //   665: invokestatic abs : (I)I
    //   668: invokevirtual charAt : (I)C
    //   671: invokevirtual append : (C)Ljava/lang/StringBuilder;
    //   674: pop
    //   675: iload_2
    //   676: ifne -> 1348
    //   679: goto -> 686
    //   682: invokestatic a : (Ljava/lang/Throwable;)Ljava/lang/Throwable;
    //   685: athrow
    //   686: aload_3
    //   687: getstatic burp/Zbze.ZK : Ljava/lang/String;
    //   690: getstatic burp/Zzc9.ZZ : Ljava/lang/Object;
    //   693: checkcast java/math/BigInteger
    //   696: invokevirtual intValue : ()I
    //   699: bipush #32
    //   701: irem
    //   702: invokestatic abs : (I)I
    //   705: invokevirtual charAt : (I)C
    //   708: invokevirtual append : (C)Ljava/lang/StringBuilder;
    //   711: pop
    //   712: iload_2
    //   713: ifne -> 1348
    //   716: goto -> 723
    //   719: invokestatic a : (Ljava/lang/Throwable;)Ljava/lang/Throwable;
    //   722: athrow
    //   723: aload_3
    //   724: getstatic burp/Zrp2.ZJ : Ljava/lang/String;
    //   727: getstatic burp/Zlo0.Zu : Ljava/lang/Object;
    //   730: checkcast java/math/BigInteger
    //   733: invokevirtual intValue : ()I
    //   736: bipush #32
    //   738: irem
    //   739: invokestatic abs : (I)I
    //   742: invokevirtual charAt : (I)C
    //   745: invokevirtual append : (C)Ljava/lang/StringBuilder;
    //   748: pop
    //   749: iload_2
    //   750: ifne -> 1348
    //   753: goto -> 760
    //   756: invokestatic a : (Ljava/lang/Throwable;)Ljava/lang/Throwable;
    //   759: athrow
    //   760: aload_3
    //   761: getstatic burp/Zz4j.ZS : Ljava/lang/String;
    //   764: getstatic burp/Zsp9.ZV : Ljava/lang/Object;
    //   767: checkcast java/math/BigInteger
    //   770: invokevirtual intValue : ()I
    //   773: bipush #32
    //   775: irem
    //   776: invokestatic abs : (I)I
    //   779: invokevirtual charAt : (I)C
    //   782: invokevirtual append : (C)Ljava/lang/StringBuilder;
    //   785: pop
    //   786: iload_2
    //   787: ifne -> 1348
    //   790: goto -> 797
    //   793: invokestatic a : (Ljava/lang/Throwable;)Ljava/lang/Throwable;
    //   796: athrow
    //   797: aload_3
    //   798: getstatic burp/Zgsb.ZM : Ljava/lang/String;
    //   801: getstatic burp/Zrkw.ZV : Ljava/lang/Object;
    //   804: checkcast java/math/BigInteger
    //   807: invokevirtual intValue : ()I
    //   810: bipush #32
    //   812: irem
    //   813: invokestatic abs : (I)I
    //   816: invokevirtual charAt : (I)C
    //   819: invokevirtual append : (C)Ljava/lang/StringBuilder;
    //   822: pop
    //   823: iload_2
    //   824: ifne -> 1348
    //   827: goto -> 834
    //   830: invokestatic a : (Ljava/lang/Throwable;)Ljava/lang/Throwable;
    //   833: athrow
    //   834: aload_3
    //   835: getstatic burp/Zlf7.ZM : Ljava/lang/String;
    //   838: getstatic burp/Zbx5.ZL : Ljava/lang/Object;
    //   841: checkcast java/math/BigInteger
    //   844: invokevirtual intValue : ()I
    //   847: bipush #32
    //   849: irem
    //   850: invokestatic abs : (I)I
    //   853: invokevirtual charAt : (I)C
    //   856: invokevirtual append : (C)Ljava/lang/StringBuilder;
    //   859: pop
    //   860: iload_2
    //   861: ifne -> 1348
    //   864: goto -> 871
    //   867: invokestatic a : (Ljava/lang/Throwable;)Ljava/lang/Throwable;
    //   870: athrow
    //   871: aload_3
    //   872: getstatic burp/Zgpx.Z_ : Ljava/lang/String;
    //   875: getstatic burp/Zlw8.ZA : Ljava/lang/Object;
    //   878: checkcast java/math/BigInteger
    //   881: invokevirtual intValue : ()I
    //   884: bipush #32
    //   886: irem
    //   887: invokestatic abs : (I)I
    //   890: invokevirtual charAt : (I)C
    //   893: invokevirtual append : (C)Ljava/lang/StringBuilder;
    //   896: pop
    //   897: iload_2
    //   898: ifne -> 1348
    //   901: goto -> 908
    //   904: invokestatic a : (Ljava/lang/Throwable;)Ljava/lang/Throwable;
    //   907: athrow
    //   908: aload_3
    //   909: getstatic burp/Zbx5.Zz : Ljava/lang/String;
    //   912: getstatic burp/Zkeb.ZH : Ljava/lang/Object;
    //   915: checkcast java/math/BigInteger
    //   918: invokevirtual intValue : ()I
    //   921: bipush #32
    //   923: irem
    //   924: invokestatic abs : (I)I
    //   927: invokevirtual charAt : (I)C
    //   930: invokevirtual append : (C)Ljava/lang/StringBuilder;
    //   933: pop
    //   934: iload_2
    //   935: ifne -> 1348
    //   938: goto -> 945
    //   941: invokestatic a : (Ljava/lang/Throwable;)Ljava/lang/Throwable;
    //   944: athrow
    //   945: aload_3
    //   946: getstatic burp/Zmli.Zc : Ljava/lang/String;
    //   949: getstatic burp/Zzts.Zp : Ljava/lang/Object;
    //   952: checkcast java/math/BigInteger
    //   955: invokevirtual intValue : ()I
    //   958: bipush #32
    //   960: irem
    //   961: invokestatic abs : (I)I
    //   964: invokevirtual charAt : (I)C
    //   967: invokevirtual append : (C)Ljava/lang/StringBuilder;
    //   970: pop
    //   971: iload_2
    //   972: ifne -> 1348
    //   975: goto -> 982
    //   978: invokestatic a : (Ljava/lang/Throwable;)Ljava/lang/Throwable;
    //   981: athrow
    //   982: aload_3
    //   983: getstatic burp/Zmli.Zc : Ljava/lang/String;
    //   986: getstatic burp/Zt4p.Zh : Ljava/lang/Object;
    //   989: checkcast java/math/BigInteger
    //   992: invokevirtual intValue : ()I
    //   995: bipush #32
    //   997: irem
    //   998: invokestatic abs : (I)I
    //   1001: invokevirtual charAt : (I)C
    //   1004: invokevirtual append : (C)Ljava/lang/StringBuilder;
    //   1007: pop
    //   1008: iload_2
    //   1009: ifne -> 1348
    //   1012: goto -> 1019
    //   1015: invokestatic a : (Ljava/lang/Throwable;)Ljava/lang/Throwable;
    //   1018: athrow
    //   1019: aload_3
    //   1020: getstatic burp/Zmui.ZY : Ljava/lang/String;
    //   1023: getstatic burp/Zrex.Zr : Ljava/lang/Object;
    //   1026: checkcast java/math/BigInteger
    //   1029: invokevirtual intValue : ()I
    //   1032: bipush #32
    //   1034: irem
    //   1035: invokestatic abs : (I)I
    //   1038: invokevirtual charAt : (I)C
    //   1041: invokevirtual append : (C)Ljava/lang/StringBuilder;
    //   1044: pop
    //   1045: iload_2
    //   1046: ifne -> 1348
    //   1049: goto -> 1056
    //   1052: invokestatic a : (Ljava/lang/Throwable;)Ljava/lang/Throwable;
    //   1055: athrow
    //   1056: aload_3
    //   1057: getstatic burp/Zbli.ZW : Ljava/lang/String;
    //   1060: getstatic burp/Zex0.Ze : Ljava/lang/Object;
    //   1063: checkcast java/math/BigInteger
    //   1066: invokevirtual intValue : ()I
    //   1069: bipush #32
    //   1071: irem
    //   1072: invokestatic abs : (I)I
    //   1075: invokevirtual charAt : (I)C
    //   1078: invokevirtual append : (C)Ljava/lang/StringBuilder;
    //   1081: pop
    //   1082: iload_2
    //   1083: ifne -> 1348
    //   1086: goto -> 1093
    //   1089: invokestatic a : (Ljava/lang/Throwable;)Ljava/lang/Throwable;
    //   1092: athrow
    //   1093: aload_3
    //   1094: getstatic burp/Zxc0.Zh : Ljava/lang/String;
    //   1097: getstatic burp/Zr60.Ze : Ljava/lang/Object;
    //   1100: checkcast java/math/BigInteger
    //   1103: invokevirtual intValue : ()I
    //   1106: bipush #32
    //   1108: irem
    //   1109: invokestatic abs : (I)I
    //   1112: invokevirtual charAt : (I)C
    //   1115: invokevirtual append : (C)Ljava/lang/StringBuilder;
    //   1118: pop
    //   1119: iload_2
    //   1120: ifne -> 1348
    //   1123: goto -> 1130
    //   1126: invokestatic a : (Ljava/lang/Throwable;)Ljava/lang/Throwable;
    //   1129: athrow
    //   1130: aload_3
    //   1131: getstatic burp/Zzii.Zl : Ljava/lang/String;
    //   1134: getstatic burp/Zge2.Zv : Ljava/lang/Object;
    //   1137: checkcast java/math/BigInteger
    //   1140: invokevirtual intValue : ()I
    //   1143: bipush #32
    //   1145: irem
    //   1146: invokestatic abs : (I)I
    //   1149: invokevirtual charAt : (I)C
    //   1152: invokevirtual append : (C)Ljava/lang/StringBuilder;
    //   1155: pop
    //   1156: iload_2
    //   1157: ifne -> 1348
    //   1160: goto -> 1167
    //   1163: invokestatic a : (Ljava/lang/Throwable;)Ljava/lang/Throwable;
    //   1166: athrow
    //   1167: aload_3
    //   1168: getstatic burp/Zlgh.Zm : Ljava/lang/String;
    //   1171: getstatic burp/Zzh5.ZG : Ljava/lang/Object;
    //   1174: checkcast java/math/BigInteger
    //   1177: invokevirtual intValue : ()I
    //   1180: bipush #32
    //   1182: irem
    //   1183: invokestatic abs : (I)I
    //   1186: invokevirtual charAt : (I)C
    //   1189: invokevirtual append : (C)Ljava/lang/StringBuilder;
    //   1192: pop
    //   1193: iload_2
    //   1194: ifne -> 1348
    //   1197: goto -> 1204
    //   1200: invokestatic a : (Ljava/lang/Throwable;)Ljava/lang/Throwable;
    //   1203: athrow
    //   1204: aload_3
    //   1205: getstatic burp/Zg4z.Zm : Ljava/lang/String;
    //   1208: getstatic burp/Zbnz.Zb : Ljava/lang/Object;
    //   1211: checkcast java/math/BigInteger
    //   1214: invokevirtual intValue : ()I
    //   1217: bipush #32
    //   1219: irem
    //   1220: invokestatic abs : (I)I
    //   1223: invokevirtual charAt : (I)C
    //   1226: invokevirtual append : (C)Ljava/lang/StringBuilder;
    //   1229: pop
    //   1230: iload_2
    //   1231: ifne -> 1348
    //   1234: goto -> 1241
    //   1237: invokestatic a : (Ljava/lang/Throwable;)Ljava/lang/Throwable;
    //   1240: athrow
    //   1241: aload_3
    //   1242: getstatic burp/Zrzg.ZX : Ljava/lang/String;
    //   1245: getstatic burp/Zetf.Zs : Ljava/lang/Object;
    //   1248: checkcast java/math/BigInteger
    //   1251: invokevirtual intValue : ()I
    //   1254: bipush #32
    //   1256: irem
    //   1257: invokestatic abs : (I)I
    //   1260: invokevirtual charAt : (I)C
    //   1263: invokevirtual append : (C)Ljava/lang/StringBuilder;
    //   1266: pop
    //   1267: iload_2
    //   1268: ifne -> 1348
    //   1271: goto -> 1278
    //   1274: invokestatic a : (Ljava/lang/Throwable;)Ljava/lang/Throwable;
    //   1277: athrow
    //   1278: aload_3
    //   1279: getstatic burp/Zzpm.Za : Ljava/lang/String;
    //   1282: getstatic burp/Zkca.ZQ : Ljava/lang/Object;
    //   1285: checkcast java/math/BigInteger
    //   1288: invokevirtual intValue : ()I
    //   1291: bipush #32
    //   1293: irem
    //   1294: invokestatic abs : (I)I
    //   1297: invokevirtual charAt : (I)C
    //   1300: invokevirtual append : (C)Ljava/lang/StringBuilder;
    //   1303: pop
    //   1304: iload_2
    //   1305: ifne -> 1348
    //   1308: goto -> 1315
    //   1311: invokestatic a : (Ljava/lang/Throwable;)Ljava/lang/Throwable;
    //   1314: athrow
    //   1315: aload_3
    //   1316: getstatic burp/Zmdf.Zo : Ljava/lang/String;
    //   1319: getstatic burp/Zgio.ZP : Ljava/lang/Object;
    //   1322: checkcast java/math/BigInteger
    //   1325: invokevirtual intValue : ()I
    //   1328: bipush #32
    //   1330: irem
    //   1331: invokestatic abs : (I)I
    //   1334: invokevirtual charAt : (I)C
    //   1337: invokevirtual append : (C)Ljava/lang/StringBuilder;
    //   1340: pop
    //   1341: goto -> 1348
    //   1344: invokestatic a : (Ljava/lang/Throwable;)Ljava/lang/Throwable;
    //   1347: athrow
    //   1348: iinc #4, 1
    //   1351: iload_2
    //   1352: ifne -> 15
    //   1355: aload_3
    //   1356: invokevirtual toString : ()Ljava/lang/String;
    //   1359: putstatic burp/Zrkd.ZL : Ljava/lang/String;
    //   1362: new java/lang/StringBuilder
    //   1365: dup
    //   1366: invokespecial <init> : ()V
    //   1369: astore #4
    //   1371: iconst_0
    //   1372: istore #5
    //   1374: iload #5
    //   1376: bipush #32
    //   1378: if_icmpge -> 2743
    //   1381: iload #5
    //   1383: tableswitch default -> 2736, 0 -> 1524, 1 -> 1562, 2 -> 1600, 3 -> 1638, 4 -> 1676, 5 -> 1714, 6 -> 1752, 7 -> 1790, 8 -> 1828, 9 -> 1866, 10 -> 1904, 11 -> 1942, 12 -> 1980, 13 -> 2018, 14 -> 2056, 15 -> 2094, 16 -> 2132, 17 -> 2170, 18 -> 2208, 19 -> 2246, 20 -> 2284, 21 -> 2322, 22 -> 2360, 23 -> 2398, 24 -> 2436, 25 -> 2474, 26 -> 2512, 27 -> 2550, 28 -> 2588, 29 -> 2626, 30 -> 2664, 31 -> 2702
    //   1524: aload #4
    //   1526: getstatic burp/Zeva.Zo : Ljava/lang/String;
    //   1529: getstatic burp/Zr02.ZB : Ljava/lang/Object;
    //   1532: checkcast java/math/BigInteger
    //   1535: invokevirtual intValue : ()I
    //   1538: bipush #32
    //   1540: irem
    //   1541: invokestatic abs : (I)I
    //   1544: invokevirtual charAt : (I)C
    //   1547: invokevirtual append : (C)Ljava/lang/StringBuilder;
    //   1550: pop
    //   1551: iload_2
    //   1552: ifne -> 2736
    //   1555: goto -> 1562
    //   1558: invokestatic a : (Ljava/lang/Throwable;)Ljava/lang/Throwable;
    //   1561: athrow
    //   1562: aload #4
    //   1564: getstatic burp/Ztwp.ZK : Ljava/lang/String;
    //   1567: getstatic burp/Zea9.Zt : Ljava/lang/Object;
    //   1570: checkcast java/math/BigInteger
    //   1573: invokevirtual intValue : ()I
    //   1576: bipush #32
    //   1578: irem
    //   1579: invokestatic abs : (I)I
    //   1582: invokevirtual charAt : (I)C
    //   1585: invokevirtual append : (C)Ljava/lang/StringBuilder;
    //   1588: pop
    //   1589: iload_2
    //   1590: ifne -> 2736
    //   1593: goto -> 1600
    //   1596: invokestatic a : (Ljava/lang/Throwable;)Ljava/lang/Throwable;
    //   1599: athrow
    //   1600: aload #4
    //   1602: getstatic burp/Ze4w.Zc : Ljava/lang/String;
    //   1605: getstatic burp/Zeqz.ZG : Ljava/lang/Object;
    //   1608: checkcast java/math/BigInteger
    //   1611: invokevirtual intValue : ()I
    //   1614: bipush #32
    //   1616: irem
    //   1617: invokestatic abs : (I)I
    //   1620: invokevirtual charAt : (I)C
    //   1623: invokevirtual append : (C)Ljava/lang/StringBuilder;
    //   1626: pop
    //   1627: iload_2
    //   1628: ifne -> 2736
    //   1631: goto -> 1638
    //   1634: invokestatic a : (Ljava/lang/Throwable;)Ljava/lang/Throwable;
    //   1637: athrow
    //   1638: aload #4
    //   1640: getstatic burp/Zl7b.Zv : Ljava/lang/String;
    //   1643: getstatic burp/Zb2u.ZY : Ljava/lang/Object;
    //   1646: checkcast java/math/BigInteger
    //   1649: invokevirtual intValue : ()I
    //   1652: bipush #32
    //   1654: irem
    //   1655: invokestatic abs : (I)I
    //   1658: invokevirtual charAt : (I)C
    //   1661: invokevirtual append : (C)Ljava/lang/StringBuilder;
    //   1664: pop
    //   1665: iload_2
    //   1666: ifne -> 2736
    //   1669: goto -> 1676
    //   1672: invokestatic a : (Ljava/lang/Throwable;)Ljava/lang/Throwable;
    //   1675: athrow
    //   1676: aload #4
    //   1678: getstatic burp/Zsu2.Zq : Ljava/lang/String;
    //   1681: getstatic burp/Zrfa.Zj : Ljava/lang/Object;
    //   1684: checkcast java/math/BigInteger
    //   1687: invokevirtual intValue : ()I
    //   1690: bipush #32
    //   1692: irem
    //   1693: invokestatic abs : (I)I
    //   1696: invokevirtual charAt : (I)C
    //   1699: invokevirtual append : (C)Ljava/lang/StringBuilder;
    //   1702: pop
    //   1703: iload_2
    //   1704: ifne -> 2736
    //   1707: goto -> 1714
    //   1710: invokestatic a : (Ljava/lang/Throwable;)Ljava/lang/Throwable;
    //   1713: athrow
    //   1714: aload #4
    //   1716: getstatic burp/Zezi.Ze : Ljava/lang/String;
    //   1719: getstatic burp/Zzhx.ZB : Ljava/lang/Object;
    //   1722: checkcast java/math/BigInteger
    //   1725: invokevirtual intValue : ()I
    //   1728: bipush #32
    //   1730: irem
    //   1731: invokestatic abs : (I)I
    //   1734: invokevirtual charAt : (I)C
    //   1737: invokevirtual append : (C)Ljava/lang/StringBuilder;
    //   1740: pop
    //   1741: iload_2
    //   1742: ifne -> 2736
    //   1745: goto -> 1752
    //   1748: invokestatic a : (Ljava/lang/Throwable;)Ljava/lang/Throwable;
    //   1751: athrow
    //   1752: aload #4
    //   1754: getstatic burp/Ze4w.Zc : Ljava/lang/String;
    //   1757: getstatic burp/Zku9.Zp : Ljava/lang/Object;
    //   1760: checkcast java/math/BigInteger
    //   1763: invokevirtual intValue : ()I
    //   1766: bipush #32
    //   1768: irem
    //   1769: invokestatic abs : (I)I
    //   1772: invokevirtual charAt : (I)C
    //   1775: invokevirtual append : (C)Ljava/lang/StringBuilder;
    //   1778: pop
    //   1779: iload_2
    //   1780: ifne -> 2736
    //   1783: goto -> 1790
    //   1786: invokestatic a : (Ljava/lang/Throwable;)Ljava/lang/Throwable;
    //   1789: athrow
    //   1790: aload #4
    //   1792: getstatic burp/Zedq.Zj : Ljava/lang/String;
    //   1795: getstatic burp/Zb9q.ZI : Ljava/lang/Object;
    //   1798: checkcast java/math/BigInteger
    //   1801: invokevirtual intValue : ()I
    //   1804: bipush #32
    //   1806: irem
    //   1807: invokestatic abs : (I)I
    //   1810: invokevirtual charAt : (I)C
    //   1813: invokevirtual append : (C)Ljava/lang/StringBuilder;
    //   1816: pop
    //   1817: iload_2
    //   1818: ifne -> 2736
    //   1821: goto -> 1828
    //   1824: invokestatic a : (Ljava/lang/Throwable;)Ljava/lang/Throwable;
    //   1827: athrow
    //   1828: aload #4
    //   1830: getstatic burp/Zgis.Zh : Ljava/lang/String;
    //   1833: getstatic burp/Zrfa.Zj : Ljava/lang/Object;
    //   1836: checkcast java/math/BigInteger
    //   1839: invokevirtual intValue : ()I
    //   1842: bipush #32
    //   1844: irem
    //   1845: invokestatic abs : (I)I
    //   1848: invokevirtual charAt : (I)C
    //   1851: invokevirtual append : (C)Ljava/lang/StringBuilder;
    //   1854: pop
    //   1855: iload_2
    //   1856: ifne -> 2736
    //   1859: goto -> 1866
    //   1862: invokestatic a : (Ljava/lang/Throwable;)Ljava/lang/Throwable;
    //   1865: athrow
    //   1866: aload #4
    //   1868: getstatic burp/Zl1e.Z_ : Ljava/lang/String;
    //   1871: getstatic burp/Zxxh.Za : Ljava/lang/Object;
    //   1874: checkcast java/math/BigInteger
    //   1877: invokevirtual intValue : ()I
    //   1880: bipush #32
    //   1882: irem
    //   1883: invokestatic abs : (I)I
    //   1886: invokevirtual charAt : (I)C
    //   1889: invokevirtual append : (C)Ljava/lang/StringBuilder;
    //   1892: pop
    //   1893: iload_2
    //   1894: ifne -> 2736
    //   1897: goto -> 1904
    //   1900: invokestatic a : (Ljava/lang/Throwable;)Ljava/lang/Throwable;
    //   1903: athrow
    //   1904: aload #4
    //   1906: getstatic burp/Zelt.ZJ : Ljava/lang/String;
    //   1909: getstatic burp/Zgi9.Zc : Ljava/lang/Object;
    //   1912: checkcast java/math/BigInteger
    //   1915: invokevirtual intValue : ()I
    //   1918: bipush #32
    //   1920: irem
    //   1921: invokestatic abs : (I)I
    //   1924: invokevirtual charAt : (I)C
    //   1927: invokevirtual append : (C)Ljava/lang/StringBuilder;
    //   1930: pop
    //   1931: iload_2
    //   1932: ifne -> 2736
    //   1935: goto -> 1942
    //   1938: invokestatic a : (Ljava/lang/Throwable;)Ljava/lang/Throwable;
    //   1941: athrow
    //   1942: aload #4
    //   1944: getstatic burp/Zrqe.ZB : Ljava/lang/String;
    //   1947: getstatic burp/Zsdl.Zx : Ljava/lang/Object;
    //   1950: checkcast java/math/BigInteger
    //   1953: invokevirtual intValue : ()I
    //   1956: bipush #32
    //   1958: irem
    //   1959: invokestatic abs : (I)I
    //   1962: invokevirtual charAt : (I)C
    //   1965: invokevirtual append : (C)Ljava/lang/StringBuilder;
    //   1968: pop
    //   1969: iload_2
    //   1970: ifne -> 2736
    //   1973: goto -> 1980
    //   1976: invokestatic a : (Ljava/lang/Throwable;)Ljava/lang/Throwable;
    //   1979: athrow
    //   1980: aload #4
    //   1982: getstatic burp/Zgtx.ZN : Ljava/lang/String;
    //   1985: getstatic burp/Zml9.ZH : Ljava/lang/Object;
    //   1988: checkcast java/math/BigInteger
    //   1991: invokevirtual intValue : ()I
    //   1994: bipush #32
    //   1996: irem
    //   1997: invokestatic abs : (I)I
    //   2000: invokevirtual charAt : (I)C
    //   2003: invokevirtual append : (C)Ljava/lang/StringBuilder;
    //   2006: pop
    //   2007: iload_2
    //   2008: ifne -> 2736
    //   2011: goto -> 2018
    //   2014: invokestatic a : (Ljava/lang/Throwable;)Ljava/lang/Throwable;
    //   2017: athrow
    //   2018: aload #4
    //   2020: getstatic burp/Zgsy.Zv : Ljava/lang/String;
    //   2023: getstatic burp/Zge2.Zv : Ljava/lang/Object;
    //   2026: checkcast java/math/BigInteger
    //   2029: invokevirtual intValue : ()I
    //   2032: bipush #32
    //   2034: irem
    //   2035: invokestatic abs : (I)I
    //   2038: invokevirtual charAt : (I)C
    //   2041: invokevirtual append : (C)Ljava/lang/StringBuilder;
    //   2044: pop
    //   2045: iload_2
    //   2046: ifne -> 2736
    //   2049: goto -> 2056
    //   2052: invokestatic a : (Ljava/lang/Throwable;)Ljava/lang/Throwable;
    //   2055: athrow
    //   2056: aload #4
    //   2058: getstatic burp/Zzgb.ZT : Ljava/lang/String;
    //   2061: getstatic burp/Zlt1.ZH : Ljava/lang/Object;
    //   2064: checkcast java/math/BigInteger
    //   2067: invokevirtual intValue : ()I
    //   2070: bipush #32
    //   2072: irem
    //   2073: invokestatic abs : (I)I
    //   2076: invokevirtual charAt : (I)C
    //   2079: invokevirtual append : (C)Ljava/lang/StringBuilder;
    //   2082: pop
    //   2083: iload_2
    //   2084: ifne -> 2736
    //   2087: goto -> 2094
    //   2090: invokestatic a : (Ljava/lang/Throwable;)Ljava/lang/Throwable;
    //   2093: athrow
    //   2094: aload #4
    //   2096: getstatic burp/Zzn6.Za : Ljava/lang/String;
    //   2099: getstatic burp/Zrnt.Zh : Ljava/lang/Object;
    //   2102: checkcast java/math/BigInteger
    //   2105: invokevirtual intValue : ()I
    //   2108: bipush #32
    //   2110: irem
    //   2111: invokestatic abs : (I)I
    //   2114: invokevirtual charAt : (I)C
    //   2117: invokevirtual append : (C)Ljava/lang/StringBuilder;
    //   2120: pop
    //   2121: iload_2
    //   2122: ifne -> 2736
    //   2125: goto -> 2132
    //   2128: invokestatic a : (Ljava/lang/Throwable;)Ljava/lang/Throwable;
    //   2131: athrow
    //   2132: aload #4
    //   2134: getstatic burp/Zsp9.ZA : Ljava/lang/String;
    //   2137: getstatic burp/Zmui.Zz : Ljava/lang/Object;
    //   2140: checkcast java/math/BigInteger
    //   2143: invokevirtual intValue : ()I
    //   2146: bipush #32
    //   2148: irem
    //   2149: invokestatic abs : (I)I
    //   2152: invokevirtual charAt : (I)C
    //   2155: invokevirtual append : (C)Ljava/lang/StringBuilder;
    //   2158: pop
    //   2159: iload_2
    //   2160: ifne -> 2736
    //   2163: goto -> 2170
    //   2166: invokestatic a : (Ljava/lang/Throwable;)Ljava/lang/Throwable;
    //   2169: athrow
    //   2170: aload #4
    //   2172: getstatic burp/Zt1h.Zw : Ljava/lang/String;
    //   2175: getstatic burp/Zxt7.ZV : Ljava/lang/Object;
    //   2178: checkcast java/math/BigInteger
    //   2181: invokevirtual intValue : ()I
    //   2184: bipush #32
    //   2186: irem
    //   2187: invokestatic abs : (I)I
    //   2190: invokevirtual charAt : (I)C
    //   2193: invokevirtual append : (C)Ljava/lang/StringBuilder;
    //   2196: pop
    //   2197: iload_2
    //   2198: ifne -> 2736
    //   2201: goto -> 2208
    //   2204: invokestatic a : (Ljava/lang/Throwable;)Ljava/lang/Throwable;
    //   2207: athrow
    //   2208: aload #4
    //   2210: getstatic burp/Zbun.ZS : Ljava/lang/String;
    //   2213: getstatic burp/Zlwj.ZE : Ljava/lang/Object;
    //   2216: checkcast java/math/BigInteger
    //   2219: invokevirtual intValue : ()I
    //   2222: bipush #32
    //   2224: irem
    //   2225: invokestatic abs : (I)I
    //   2228: invokevirtual charAt : (I)C
    //   2231: invokevirtual append : (C)Ljava/lang/StringBuilder;
    //   2234: pop
    //   2235: iload_2
    //   2236: ifne -> 2736
    //   2239: goto -> 2246
    //   2242: invokestatic a : (Ljava/lang/Throwable;)Ljava/lang/Throwable;
    //   2245: athrow
    //   2246: aload #4
    //   2248: getstatic burp/Zg4l.Z_ : Ljava/lang/String;
    //   2251: getstatic burp/Zg4z.ZB : Ljava/lang/Object;
    //   2254: checkcast java/math/BigInteger
    //   2257: invokevirtual intValue : ()I
    //   2260: bipush #32
    //   2262: irem
    //   2263: invokestatic abs : (I)I
    //   2266: invokevirtual charAt : (I)C
    //   2269: invokevirtual append : (C)Ljava/lang/StringBuilder;
    //   2272: pop
    //   2273: iload_2
    //   2274: ifne -> 2736
    //   2277: goto -> 2284
    //   2280: invokestatic a : (Ljava/lang/Throwable;)Ljava/lang/Throwable;
    //   2283: athrow
    //   2284: aload #4
    //   2286: getstatic burp/Zegw.Zn : Ljava/lang/String;
    //   2289: getstatic burp/Zr36.Za : Ljava/lang/Object;
    //   2292: checkcast java/math/BigInteger
    //   2295: invokevirtual intValue : ()I
    //   2298: bipush #32
    //   2300: irem
    //   2301: invokestatic abs : (I)I
    //   2304: invokevirtual charAt : (I)C
    //   2307: invokevirtual append : (C)Ljava/lang/StringBuilder;
    //   2310: pop
    //   2311: iload_2
    //   2312: ifne -> 2736
    //   2315: goto -> 2322
    //   2318: invokestatic a : (Ljava/lang/Throwable;)Ljava/lang/Throwable;
    //   2321: athrow
    //   2322: aload #4
    //   2324: getstatic burp/Zt6z.ZL : Ljava/lang/String;
    //   2327: getstatic burp/Zge2.Zv : Ljava/lang/Object;
    //   2330: checkcast java/math/BigInteger
    //   2333: invokevirtual intValue : ()I
    //   2336: bipush #32
    //   2338: irem
    //   2339: invokestatic abs : (I)I
    //   2342: invokevirtual charAt : (I)C
    //   2345: invokevirtual append : (C)Ljava/lang/StringBuilder;
    //   2348: pop
    //   2349: iload_2
    //   2350: ifne -> 2736
    //   2353: goto -> 2360
    //   2356: invokestatic a : (Ljava/lang/Throwable;)Ljava/lang/Throwable;
    //   2359: athrow
    //   2360: aload #4
    //   2362: getstatic burp/Zscz.ZJ : Ljava/lang/String;
    //   2365: getstatic burp/Zrzg.ZA : Ljava/lang/Object;
    //   2368: checkcast java/math/BigInteger
    //   2371: invokevirtual intValue : ()I
    //   2374: bipush #32
    //   2376: irem
    //   2377: invokestatic abs : (I)I
    //   2380: invokevirtual charAt : (I)C
    //   2383: invokevirtual append : (C)Ljava/lang/StringBuilder;
    //   2386: pop
    //   2387: iload_2
    //   2388: ifne -> 2736
    //   2391: goto -> 2398
    //   2394: invokestatic a : (Ljava/lang/Throwable;)Ljava/lang/Throwable;
    //   2397: athrow
    //   2398: aload #4
    //   2400: getstatic burp/Zrkd.ZL : Ljava/lang/String;
    //   2403: getstatic burp/Zxci.Zx : Ljava/lang/Object;
    //   2406: checkcast java/math/BigInteger
    //   2409: invokevirtual intValue : ()I
    //   2412: bipush #32
    //   2414: irem
    //   2415: invokestatic abs : (I)I
    //   2418: invokevirtual charAt : (I)C
    //   2421: invokevirtual append : (C)Ljava/lang/StringBuilder;
    //   2424: pop
    //   2425: iload_2
    //   2426: ifne -> 2736
    //   2429: goto -> 2436
    //   2432: invokestatic a : (Ljava/lang/Throwable;)Ljava/lang/Throwable;
    //   2435: athrow
    //   2436: aload #4
    //   2438: getstatic burp/Zsvd.ZB : Ljava/lang/String;
    //   2441: getstatic burp/Zsjw.Zw : Ljava/lang/Object;
    //   2444: checkcast java/math/BigInteger
    //   2447: invokevirtual intValue : ()I
    //   2450: bipush #32
    //   2452: irem
    //   2453: invokestatic abs : (I)I
    //   2456: invokevirtual charAt : (I)C
    //   2459: invokevirtual append : (C)Ljava/lang/StringBuilder;
    //   2462: pop
    //   2463: iload_2
    //   2464: ifne -> 2736
    //   2467: goto -> 2474
    //   2470: invokestatic a : (Ljava/lang/Throwable;)Ljava/lang/Throwable;
    //   2473: athrow
    //   2474: aload #4
    //   2476: getstatic burp/Zql.Zf : Ljava/lang/String;
    //   2479: getstatic burp/Zt85.Zl : Ljava/lang/Object;
    //   2482: checkcast java/math/BigInteger
    //   2485: invokevirtual intValue : ()I
    //   2488: bipush #32
    //   2490: irem
    //   2491: invokestatic abs : (I)I
    //   2494: invokevirtual charAt : (I)C
    //   2497: invokevirtual append : (C)Ljava/lang/StringBuilder;
    //   2500: pop
    //   2501: iload_2
    //   2502: ifne -> 2736
    //   2505: goto -> 2512
    //   2508: invokestatic a : (Ljava/lang/Throwable;)Ljava/lang/Throwable;
    //   2511: athrow
    //   2512: aload #4
    //   2514: getstatic burp/Zsdl.ZJ : Ljava/lang/String;
    //   2517: getstatic burp/Zql.Zt : Ljava/lang/Object;
    //   2520: checkcast java/math/BigInteger
    //   2523: invokevirtual intValue : ()I
    //   2526: bipush #32
    //   2528: irem
    //   2529: invokestatic abs : (I)I
    //   2532: invokevirtual charAt : (I)C
    //   2535: invokevirtual append : (C)Ljava/lang/StringBuilder;
    //   2538: pop
    //   2539: iload_2
    //   2540: ifne -> 2736
    //   2543: goto -> 2550
    //   2546: invokestatic a : (Ljava/lang/Throwable;)Ljava/lang/Throwable;
    //   2549: athrow
    //   2550: aload #4
    //   2552: getstatic burp/Zg61.ZX : Ljava/lang/String;
    //   2555: getstatic burp/Zrqi.Zb : Ljava/lang/Object;
    //   2558: checkcast java/math/BigInteger
    //   2561: invokevirtual intValue : ()I
    //   2564: bipush #32
    //   2566: irem
    //   2567: invokestatic abs : (I)I
    //   2570: invokevirtual charAt : (I)C
    //   2573: invokevirtual append : (C)Ljava/lang/StringBuilder;
    //   2576: pop
    //   2577: iload_2
    //   2578: ifne -> 2736
    //   2581: goto -> 2588
    //   2584: invokestatic a : (Ljava/lang/Throwable;)Ljava/lang/Throwable;
    //   2587: athrow
    //   2588: aload #4
    //   2590: getstatic burp/Zepy.Zg : Ljava/lang/String;
    //   2593: getstatic burp/Zx4u.Zn : Ljava/lang/Object;
    //   2596: checkcast java/math/BigInteger
    //   2599: invokevirtual intValue : ()I
    //   2602: bipush #32
    //   2604: irem
    //   2605: invokestatic abs : (I)I
    //   2608: invokevirtual charAt : (I)C
    //   2611: invokevirtual append : (C)Ljava/lang/StringBuilder;
    //   2614: pop
    //   2615: iload_2
    //   2616: ifne -> 2736
    //   2619: goto -> 2626
    //   2622: invokestatic a : (Ljava/lang/Throwable;)Ljava/lang/Throwable;
    //   2625: athrow
    //   2626: aload #4
    //   2628: getstatic burp/Zrww.ZV : Ljava/lang/String;
    //   2631: getstatic burp/Zbun.ZH : Ljava/lang/Object;
    //   2634: checkcast java/math/BigInteger
    //   2637: invokevirtual intValue : ()I
    //   2640: bipush #32
    //   2642: irem
    //   2643: invokestatic abs : (I)I
    //   2646: invokevirtual charAt : (I)C
    //   2649: invokevirtual append : (C)Ljava/lang/StringBuilder;
    //   2652: pop
    //   2653: iload_2
    //   2654: ifne -> 2736
    //   2657: goto -> 2664
    //   2660: invokestatic a : (Ljava/lang/Throwable;)Ljava/lang/Throwable;
    //   2663: athrow
    //   2664: aload #4
    //   2666: getstatic burp/Zlab.Zp : Ljava/lang/String;
    //   2669: getstatic burp/Zm1d.ZS : Ljava/lang/Object;
    //   2672: checkcast java/math/BigInteger
    //   2675: invokevirtual intValue : ()I
    //   2678: bipush #32
    //   2680: irem
    //   2681: invokestatic abs : (I)I
    //   2684: invokevirtual charAt : (I)C
    //   2687: invokevirtual append : (C)Ljava/lang/StringBuilder;
    //   2690: pop
    //   2691: iload_2
    //   2692: ifne -> 2736
    //   2695: goto -> 2702
    //   2698: invokestatic a : (Ljava/lang/Throwable;)Ljava/lang/Throwable;
    //   2701: athrow
    //   2702: aload #4
    //   2704: getstatic burp/Zxwf.ZX : Ljava/lang/String;
    //   2707: getstatic burp/Zz4j.Zu : Ljava/lang/Object;
    //   2710: checkcast java/math/BigInteger
    //   2713: invokevirtual intValue : ()I
    //   2716: bipush #32
    //   2718: irem
    //   2719: invokestatic abs : (I)I
    //   2722: invokevirtual charAt : (I)C
    //   2725: invokevirtual append : (C)Ljava/lang/StringBuilder;
    //   2728: pop
    //   2729: goto -> 2736
    //   2732: invokestatic a : (Ljava/lang/Throwable;)Ljava/lang/Throwable;
    //   2735: athrow
    //   2736: iinc #5, 1
    //   2739: iload_2
    //   2740: ifne -> 1374
    //   2743: aload #4
    //   2745: invokevirtual toString : ()Ljava/lang/String;
    //   2748: putstatic burp/Zrn4.ZY : Ljava/lang/String;
    //   2751: sipush #-7393
    //   2754: getstatic burp/Zrqi.Zb : Ljava/lang/Object;
    //   2757: checkcast java/math/BigInteger
    //   2760: getstatic burp/Zsfj.ZL : Ljava/lang/Object;
    //   2763: checkcast java/math/BigInteger
    //   2766: invokevirtual add : (Ljava/math/BigInteger;)Ljava/math/BigInteger;
    //   2769: putstatic burp/Zemp.Zr : Ljava/lang/Object;
    //   2772: sipush #4666
    //   2775: invokestatic a : (II)Ljava/lang/String;
    //   2778: iconst_1
    //   2779: ldc burp/Zb0s
    //   2781: invokevirtual getClassLoader : ()Ljava/lang/ClassLoader;
    //   2784: invokestatic forName : (Ljava/lang/String;ZLjava/lang/ClassLoader;)Ljava/lang/Class;
    //   2787: invokevirtual getDeclaredFields : ()[Ljava/lang/reflect/Field;
    //   2790: astore #5
    //   2792: aload #5
    //   2794: arraylength
    //   2795: istore #6
    //   2797: iconst_0
    //   2798: istore #7
    //   2800: iload #7
    //   2802: iload #6
    //   2804: if_icmpge -> 2942
    //   2807: aload #5
    //   2809: iload #7
    //   2811: aaload
    //   2812: astore #8
    //   2814: aload #8
    //   2816: invokevirtual getModifiers : ()I
    //   2819: invokestatic isStatic : (I)Z
    //   2822: ifne -> 2832
    //   2825: goto -> 2935
    //   2828: invokestatic a : (Ljava/lang/Throwable;)Ljava/lang/Throwable;
    //   2831: athrow
    //   2832: aload #8
    //   2834: invokevirtual getType : ()Ljava/lang/Class;
    //   2837: astore #9
    //   2839: aload #9
    //   2841: ifnull -> 2922
    //   2844: aload #9
    //   2846: invokevirtual isPrimitive : ()Z
    //   2849: ifne -> 2922
    //   2852: goto -> 2859
    //   2855: invokestatic a : (Ljava/lang/Throwable;)Ljava/lang/Throwable;
    //   2858: athrow
    //   2859: aload #9
    //   2861: invokevirtual getPackage : ()Ljava/lang/Package;
    //   2864: ifnull -> 2922
    //   2867: goto -> 2874
    //   2870: invokestatic a : (Ljava/lang/Throwable;)Ljava/lang/Throwable;
    //   2873: athrow
    //   2874: aload #9
    //   2876: invokevirtual getPackage : ()Ljava/lang/Package;
    //   2879: invokevirtual getName : ()Ljava/lang/String;
    //   2882: ifnull -> 2922
    //   2885: goto -> 2892
    //   2888: invokestatic a : (Ljava/lang/Throwable;)Ljava/lang/Throwable;
    //   2891: athrow
    //   2892: aload #9
    //   2894: invokevirtual getPackage : ()Ljava/lang/Package;
    //   2897: invokevirtual getName : ()Ljava/lang/String;
    //   2900: sipush #-7395
    //   2903: sipush #-17644
    //   2906: invokestatic a : (II)Ljava/lang/String;
    //   2909: invokevirtual startsWith : (Ljava/lang/String;)Z
    //   2912: ifne -> 2922
    //   2915: goto -> 2922
    //   2918: invokestatic a : (Ljava/lang/Throwable;)Ljava/lang/Throwable;
    //   2921: athrow
    //   2922: aload #8
    //   2924: iconst_1
    //   2925: invokevirtual setAccessible : (Z)V
    //   2928: aload #8
    //   2930: aconst_null
    //   2931: invokevirtual get : (Ljava/lang/Object;)Ljava/lang/Object;
    //   2934: pop
    //   2935: iinc #7, 1
    //   2938: iload_2
    //   2939: ifne -> 2800
    //   2942: sipush #-7400
    //   2945: sipush #-18949
    //   2948: invokestatic a : (II)Ljava/lang/String;
    //   2951: invokestatic forName : (Ljava/lang/String;)Ljava/lang/Class;
    //   2954: invokevirtual getDeclaredMethods : ()[Ljava/lang/reflect/Method;
    //   2957: astore #5
    //   2959: aload #5
    //   2961: arraylength
    //   2962: istore #6
    //   2964: iconst_0
    //   2965: istore #7
    //   2967: iload #7
    //   2969: iload #6
    //   2971: if_icmpge -> 3104
    //   2974: aload #5
    //   2976: iload #7
    //   2978: aaload
    //   2979: astore #8
    //   2981: aload #8
    //   2983: invokevirtual getParameterTypes : ()[Ljava/lang/Class;
    //   2986: pop
    //   2987: aload #8
    //   2989: invokevirtual getModifiers : ()I
    //   2992: invokestatic isStatic : (I)Z
    //   2995: ifeq -> 3090
    //   2998: aload #8
    //   3000: invokevirtual getParameterTypes : ()[Ljava/lang/Class;
    //   3003: arraylength
    //   3004: iconst_2
    //   3005: if_icmpne -> 3090
    //   3008: goto -> 3015
    //   3011: invokestatic a : (Ljava/lang/Throwable;)Ljava/lang/Throwable;
    //   3014: athrow
    //   3015: aload #8
    //   3017: invokevirtual getReturnType : ()Ljava/lang/Class;
    //   3020: getstatic java/lang/Void.TYPE : Ljava/lang/Class;
    //   3023: invokevirtual equals : (Ljava/lang/Object;)Z
    //   3026: ifeq -> 3090
    //   3029: goto -> 3036
    //   3032: invokestatic a : (Ljava/lang/Throwable;)Ljava/lang/Throwable;
    //   3035: athrow
    //   3036: aload #8
    //   3038: iconst_1
    //   3039: invokevirtual setAccessible : (Z)V
    //   3042: aload #8
    //   3044: aconst_null
    //   3045: iconst_2
    //   3046: anewarray java/lang/Object
    //   3049: dup
    //   3050: iconst_0
    //   3051: aload_0
    //   3052: aastore
    //   3053: dup
    //   3054: iconst_1
    //   3055: aload_1
    //   3056: ifnonnull -> 3074
    //   3059: goto -> 3066
    //   3062: invokestatic a : (Ljava/lang/Throwable;)Ljava/lang/Throwable;
    //   3065: athrow
    //   3066: aload_1
    //   3067: goto -> 3081
    //   3070: invokestatic a : (Ljava/lang/Throwable;)Ljava/lang/Throwable;
    //   3073: athrow
    //   3074: aload_1
    //   3075: checkcast [B
    //   3078: invokevirtual clone : ()Ljava/lang/Object;
    //   3081: aastore
    //   3082: invokevirtual invoke : (Ljava/lang/Object;[Ljava/lang/Object;)Ljava/lang/Object;
    //   3085: pop
    //   3086: iload_2
    //   3087: ifne -> 3104
    //   3090: iinc #7, 1
    //   3093: iload_2
    //   3094: ifne -> 2967
    //   3097: goto -> 3104
    //   3100: invokestatic a : (Ljava/lang/Throwable;)Ljava/lang/Throwable;
    //   3103: athrow
    //   3104: getstatic burp/Zkdq.ZG : Ljava/lang/Object;
    //   3107: checkcast java/math/BigInteger
    //   3110: invokevirtual toByteArray : ()[B
    //   3113: astore #5
    //   3115: aload #5
    //   3117: arraylength
    //   3118: bipush #8
    //   3120: iadd
    //   3121: bipush #6
    //   3123: ishr
    //   3124: iconst_1
    //   3125: iadd
    //   3126: bipush #16
    //   3128: imul
    //   3129: newarray int
    //   3131: astore #7
    //   3133: iconst_0
    //   3134: istore #8
    //   3136: iload #8
    //   3138: aload #5
    //   3140: arraylength
    //   3141: if_icmpge -> 3185
    //   3144: aload #5
    //   3146: iload #8
    //   3148: baload
    //   3149: sipush #255
    //   3152: iand
    //   3153: istore #9
    //   3155: aload #7
    //   3157: iload #8
    //   3159: iconst_2
    //   3160: ishr
    //   3161: dup2
    //   3162: iaload
    //   3163: iload #9
    //   3165: bipush #24
    //   3167: iload #8
    //   3169: iconst_4
    //   3170: irem
    //   3171: bipush #8
    //   3173: imul
    //   3174: isub
    //   3175: ishl
    //   3176: ior
    //   3177: iastore
    //   3178: iinc #8, 1
    //   3181: iload_2
    //   3182: ifne -> 3136
    //   3185: aload #7
    //   3187: iload #8
    //   3189: iconst_2
    //   3190: ishr
    //   3191: dup2
    //   3192: iaload
    //   3193: sipush #128
    //   3196: bipush #24
    //   3198: iload #8
    //   3200: iconst_4
    //   3201: irem
    //   3202: bipush #8
    //   3204: imul
    //   3205: isub
    //   3206: ishl
    //   3207: ior
    //   3208: iastore
    //   3209: aload #7
    //   3211: aload #7
    //   3213: arraylength
    //   3214: iconst_1
    //   3215: isub
    //   3216: aload #5
    //   3218: arraylength
    //   3219: bipush #8
    //   3221: imul
    //   3222: iastore
    //   3223: bipush #80
    //   3225: newarray int
    //   3227: astore #9
    //   3229: ldc 1732584193
    //   3231: istore #10
    //   3233: ldc -271733879
    //   3235: istore #11
    //   3237: ldc -1732584194
    //   3239: istore #12
    //   3241: ldc 271733878
    //   3243: istore #13
    //   3245: ldc -1009589776
    //   3247: istore #14
    //   3249: iconst_0
    //   3250: istore #8
    //   3252: iload #8
    //   3254: aload #7
    //   3256: arraylength
    //   3257: if_icmpge -> 3579
    //   3260: iload #10
    //   3262: istore #15
    //   3264: iload #11
    //   3266: istore #16
    //   3268: iload #12
    //   3270: istore #17
    //   3272: iload #13
    //   3274: istore #18
    //   3276: iload #14
    //   3278: istore #19
    //   3280: iconst_0
    //   3281: istore #20
    //   3283: iload #20
    //   3285: bipush #80
    //   3287: if_icmpge -> 3537
    //   3290: iload #20
    //   3292: bipush #16
    //   3294: if_icmpge -> 3321
    //   3297: aload #9
    //   3299: iload #20
    //   3301: aload #7
    //   3303: iload #8
    //   3305: iload #20
    //   3307: iadd
    //   3308: iaload
    //   3309: iastore
    //   3310: iload_2
    //   3311: ifne -> 3376
    //   3314: goto -> 3321
    //   3317: invokestatic a : (Ljava/lang/Throwable;)Ljava/lang/Throwable;
    //   3320: athrow
    //   3321: aload #9
    //   3323: iload #20
    //   3325: iconst_3
    //   3326: isub
    //   3327: iaload
    //   3328: aload #9
    //   3330: iload #20
    //   3332: bipush #8
    //   3334: isub
    //   3335: iaload
    //   3336: ixor
    //   3337: aload #9
    //   3339: iload #20
    //   3341: bipush #14
    //   3343: isub
    //   3344: iaload
    //   3345: ixor
    //   3346: aload #9
    //   3348: iload #20
    //   3350: bipush #16
    //   3352: isub
    //   3353: iaload
    //   3354: ixor
    //   3355: istore #21
    //   3357: iload #21
    //   3359: iconst_1
    //   3360: ishl
    //   3361: iload #21
    //   3363: bipush #31
    //   3365: iushr
    //   3366: ior
    //   3367: istore #22
    //   3369: aload #9
    //   3371: iload #20
    //   3373: iload #22
    //   3375: iastore
    //   3376: iload #10
    //   3378: iconst_5
    //   3379: ishl
    //   3380: iload #10
    //   3382: bipush #27
    //   3384: iushr
    //   3385: ior
    //   3386: istore #21
    //   3388: iload #21
    //   3390: iload #14
    //   3392: iadd
    //   3393: aload #9
    //   3395: iload #20
    //   3397: iaload
    //   3398: iadd
    //   3399: iload #20
    //   3401: bipush #20
    //   3403: if_icmpge -> 3429
    //   3406: ldc 1518500249
    //   3408: iload #11
    //   3410: iload #12
    //   3412: iand
    //   3413: iload #11
    //   3415: iconst_m1
    //   3416: ixor
    //   3417: iload #13
    //   3419: iand
    //   3420: ior
    //   3421: iadd
    //   3422: goto -> 3499
    //   3425: invokestatic a : (Ljava/lang/Throwable;)Ljava/lang/Throwable;
    //   3428: athrow
    //   3429: iload #20
    //   3431: bipush #40
    //   3433: if_icmpge -> 3454
    //   3436: ldc 1859775393
    //   3438: iload #11
    //   3440: iload #12
    //   3442: ixor
    //   3443: iload #13
    //   3445: ixor
    //   3446: iadd
    //   3447: goto -> 3499
    //   3450: invokestatic a : (Ljava/lang/Throwable;)Ljava/lang/Throwable;
    //   3453: athrow
    //   3454: iload #20
    //   3456: bipush #60
    //   3458: if_icmpge -> 3488
    //   3461: ldc -1894007588
    //   3463: iload #11
    //   3465: iload #12
    //   3467: iand
    //   3468: iload #11
    //   3470: iload #13
    //   3472: iand
    //   3473: ior
    //   3474: iload #12
    //   3476: iload #13
    //   3478: iand
    //   3479: ior
    //   3480: iadd
    //   3481: goto -> 3499
    //   3484: invokestatic a : (Ljava/lang/Throwable;)Ljava/lang/Throwable;
    //   3487: athrow
    //   3488: ldc -899497514
    //   3490: iload #11
    //   3492: iload #12
    //   3494: ixor
    //   3495: iload #13
    //   3497: ixor
    //   3498: iadd
    //   3499: iadd
    //   3500: istore #22
    //   3502: iload #13
    //   3504: istore #14
    //   3506: iload #12
    //   3508: istore #13
    //   3510: iload #11
    //   3512: bipush #30
    //   3514: ishl
    //   3515: iload #11
    //   3517: iconst_2
    //   3518: iushr
    //   3519: ior
    //   3520: istore #12
    //   3522: iload #10
    //   3524: istore #11
    //   3526: iload #22
    //   3528: istore #10
    //   3530: iinc #20, 1
    //   3533: iload_2
    //   3534: ifne -> 3283
    //   3537: iload #10
    //   3539: iload #15
    //   3541: iadd
    //   3542: istore #10
    //   3544: iload #11
    //   3546: iload #16
    //   3548: iadd
    //   3549: istore #11
    //   3551: iload #12
    //   3553: iload #17
    //   3555: iadd
    //   3556: istore #12
    //   3558: iload #13
    //   3560: iload #18
    //   3562: iadd
    //   3563: istore #13
    //   3565: iload #14
    //   3567: iload #19
    //   3569: iadd
    //   3570: istore #14
    //   3572: iinc #8, 16
    //   3575: iload_2
    //   3576: ifne -> 3252
    //   3579: iconst_5
    //   3580: newarray int
    //   3582: dup
    //   3583: iconst_0
    //   3584: iload #10
    //   3586: iastore
    //   3587: dup
    //   3588: iconst_1
    //   3589: iload #11
    //   3591: iastore
    //   3592: dup
    //   3593: iconst_2
    //   3594: iload #12
    //   3596: iastore
    //   3597: dup
    //   3598: iconst_3
    //   3599: iload #13
    //   3601: iastore
    //   3602: dup
    //   3603: iconst_4
    //   3604: iload #14
    //   3606: iastore
    //   3607: astore #15
    //   3609: bipush #20
    //   3611: newarray byte
    //   3613: astore #16
    //   3615: iconst_0
    //   3616: istore #17
    //   3618: iload #17
    //   3620: bipush #20
    //   3622: if_icmpge -> 3663
    //   3625: aload #15
    //   3627: iload #17
    //   3629: iconst_4
    //   3630: idiv
    //   3631: iaload
    //   3632: istore #18
    //   3634: iconst_3
    //   3635: iload #17
    //   3637: iconst_4
    //   3638: irem
    //   3639: isub
    //   3640: bipush #8
    //   3642: imul
    //   3643: istore #19
    //   3645: aload #16
    //   3647: iload #17
    //   3649: iload #18
    //   3651: iload #19
    //   3653: iushr
    //   3654: i2b
    //   3655: bastore
    //   3656: iinc #17, 1
    //   3659: iload_2
    //   3660: ifne -> 3618
    //   3663: aload #16
    //   3665: astore #6
    //   3667: new java/io/ByteArrayOutputStream
    //   3670: dup
    //   3671: invokespecial <init> : ()V
    //   3674: astore #5
    //   3676: sipush #-7396
    //   3679: aload #5
    //   3681: sipush #202
    //   3684: invokevirtual write : (I)V
    //   3687: sipush #31461
    //   3690: aload #5
    //   3692: sipush #254
    //   3695: invokevirtual write : (I)V
    //   3698: aload #5
    //   3700: sipush #186
    //   3703: invokevirtual write : (I)V
    //   3706: aload #5
    //   3708: sipush #190
    //   3711: invokevirtual write : (I)V
    //   3714: aload #5
    //   3716: iconst_0
    //   3717: invokevirtual write : (I)V
    //   3720: aload #5
    //   3722: iconst_1
    //   3723: invokevirtual write : (I)V
    //   3726: aload #5
    //   3728: iconst_0
    //   3729: invokevirtual write : (I)V
    //   3732: aload #5
    //   3734: bipush #50
    //   3736: invokevirtual write : (I)V
    //   3739: aload #5
    //   3741: getstatic burp/Zbow.ZS : Ljava/lang/Object;
    //   3744: checkcast java/math/BigInteger
    //   3747: invokevirtual toByteArray : ()[B
    //   3750: invokevirtual write : ([B)V
    //   3753: aload #5
    //   3755: getstatic burp/Zltp.ZT : Ljava/lang/Object;
    //   3758: checkcast java/math/BigInteger
    //   3761: invokevirtual toByteArray : ()[B
    //   3764: invokevirtual write : ([B)V
    //   3767: aload #5
    //   3769: getstatic burp/Zttq.Zh : Ljava/lang/Object;
    //   3772: checkcast java/math/BigInteger
    //   3775: invokevirtual toByteArray : ()[B
    //   3778: invokevirtual write : ([B)V
    //   3781: aload #5
    //   3783: invokevirtual toByteArray : ()[B
    //   3786: astore #6
    //   3788: aconst_null
    //   3789: astore #7
    //   3791: invokestatic a : (II)Ljava/lang/String;
    //   3794: invokestatic forName : (Ljava/lang/String;)Ljava/lang/Class;
    //   3797: invokevirtual getDeclaredMethods : ()[Ljava/lang/reflect/Method;
    //   3800: astore #8
    //   3802: aload #8
    //   3804: arraylength
    //   3805: istore #9
    //   3807: iconst_0
    //   3808: istore #10
    //   3810: iload #10
    //   3812: iload #9
    //   3814: if_icmpge -> 3942
    //   3817: aload #8
    //   3819: iload #10
    //   3821: aaload
    //   3822: astore #11
    //   3824: aload #11
    //   3826: invokevirtual getName : ()Ljava/lang/String;
    //   3829: sipush #-7398
    //   3832: sipush #31442
    //   3835: invokestatic a : (II)Ljava/lang/String;
    //   3838: invokevirtual equals : (Ljava/lang/Object;)Z
    //   3841: ifeq -> 3935
    //   3844: aload #11
    //   3846: invokevirtual getParameterTypes : ()[Ljava/lang/Class;
    //   3849: astore #12
    //   3851: aload #12
    //   3853: arraylength
    //   3854: iconst_4
    //   3855: if_icmpeq -> 3865
    //   3858: goto -> 3935
    //   3861: invokestatic a : (Ljava/lang/Throwable;)Ljava/lang/Throwable;
    //   3864: athrow
    //   3865: aload #12
    //   3867: iconst_0
    //   3868: aaload
    //   3869: ldc java/lang/String
    //   3871: if_acmpeq -> 3881
    //   3874: goto -> 3935
    //   3877: invokestatic a : (Ljava/lang/Throwable;)Ljava/lang/Throwable;
    //   3880: athrow
    //   3881: aload #12
    //   3883: iconst_1
    //   3884: aaload
    //   3885: ldc [B
    //   3887: if_acmpeq -> 3897
    //   3890: goto -> 3935
    //   3893: invokestatic a : (Ljava/lang/Throwable;)Ljava/lang/Throwable;
    //   3896: athrow
    //   3897: aload #12
    //   3899: iconst_2
    //   3900: aaload
    //   3901: getstatic java/lang/Integer.TYPE : Ljava/lang/Class;
    //   3904: if_acmpeq -> 3914
    //   3907: goto -> 3935
    //   3910: invokestatic a : (Ljava/lang/Throwable;)Ljava/lang/Throwable;
    //   3913: athrow
    //   3914: aload #12
    //   3916: iconst_3
    //   3917: aaload
    //   3918: getstatic java/lang/Integer.TYPE : Ljava/lang/Class;
    //   3921: if_acmpeq -> 3931
    //   3924: goto -> 3935
    //   3927: invokestatic a : (Ljava/lang/Throwable;)Ljava/lang/Throwable;
    //   3930: athrow
    //   3931: aload #11
    //   3933: astore #7
    //   3935: iinc #10, 1
    //   3938: iload_2
    //   3939: ifne -> 3810
    //   3942: aload #7
    //   3944: iconst_1
    //   3945: invokevirtual setAccessible : (Z)V
    //   3948: ldc burp/Zbzj
    //   3950: iconst_0
    //   3951: anewarray java/lang/Class
    //   3954: invokevirtual getDeclaredConstructor : ([Ljava/lang/Class;)Ljava/lang/reflect/Constructor;
    //   3957: astore #8
    //   3959: aload #8
    //   3961: iconst_1
    //   3962: invokevirtual setAccessible : (Z)V
    //   3965: aload #7
    //   3967: aload #8
    //   3969: iconst_0
    //   3970: anewarray java/lang/Object
    //   3973: invokevirtual newInstance : ([Ljava/lang/Object;)Ljava/lang/Object;
    //   3976: iconst_4
    //   3977: anewarray java/lang/Object
    //   3980: dup
    //   3981: iconst_0
    //   3982: sipush #-7406
    //   3985: sipush #-218
    //   3988: invokestatic a : (II)Ljava/lang/String;
    //   3991: aastore
    //   3992: dup
    //   3993: iconst_1
    //   3994: aload #6
    //   3996: aastore
    //   3997: dup
    //   3998: iconst_2
    //   3999: iconst_0
    //   4000: invokestatic valueOf : (I)Ljava/lang/Integer;
    //   4003: aastore
    //   4004: dup
    //   4005: iconst_3
    //   4006: aload #6
    //   4008: arraylength
    //   4009: invokestatic valueOf : (I)Ljava/lang/Integer;
    //   4012: aastore
    //   4013: invokevirtual invoke : (Ljava/lang/Object;[Ljava/lang/Object;)Ljava/lang/Object;
    //   4016: pop
    //   4017: goto -> 4022
    //   4020: astore #5
    //   4022: getstatic burp/Zxy6.ZR : Ljava/lang/String;
    //   4025: getstatic burp/Zsn3.Zy : Ljava/lang/Object;
    //   4028: checkcast java/math/BigInteger
    //   4031: invokevirtual intValue : ()I
    //   4034: bipush #32
    //   4036: irem
    //   4037: invokestatic abs : (I)I
    //   4040: invokevirtual charAt : (I)C
    //   4043: getstatic burp/Zz0f.ZW : Ljava/lang/String;
    //   4046: getstatic burp/Zgcg.Zi : Ljava/lang/Object;
    //   4049: checkcast java/math/BigInteger
    //   4052: invokevirtual intValue : ()I
    //   4055: bipush #32
    //   4057: irem
    //   4058: invokestatic abs : (I)I
    //   4061: invokevirtual charAt : (I)C
    //   4064: if_icmpgt -> 4179
    //   4067: getstatic burp/Zebe.ZW : Ljava/lang/String;
    //   4070: getstatic burp/Zr2q.ZS : Ljava/lang/Object;
    //   4073: checkcast java/math/BigInteger
    //   4076: invokevirtual intValue : ()I
    //   4079: bipush #32
    //   4081: irem
    //   4082: invokestatic abs : (I)I
    //   4085: invokevirtual charAt : (I)C
    //   4088: getstatic burp/Zrqe.ZB : Ljava/lang/String;
    //   4091: getstatic burp/Zebc.Zr : Ljava/lang/Object;
    //   4094: checkcast java/math/BigInteger
    //   4097: invokevirtual intValue : ()I
    //   4100: bipush #32
    //   4102: irem
    //   4103: invokestatic abs : (I)I
    //   4106: invokevirtual charAt : (I)C
    //   4109: if_icmpgt -> 4179
    //   4112: goto -> 4119
    //   4115: invokestatic a : (Ljava/lang/Throwable;)Ljava/lang/Throwable;
    //   4118: athrow
    //   4119: getstatic burp/Zrqe.ZB : Ljava/lang/String;
    //   4122: getstatic burp/Zepy.Ze : Ljava/lang/Object;
    //   4125: checkcast java/math/BigInteger
    //   4128: invokevirtual intValue : ()I
    //   4131: bipush #32
    //   4133: irem
    //   4134: invokestatic abs : (I)I
    //   4137: invokevirtual charAt : (I)C
    //   4140: getstatic burp/Zbsz.Zu : Ljava/lang/String;
    //   4143: getstatic burp/Zmf2.Zx : Ljava/lang/Object;
    //   4146: checkcast java/math/BigInteger
    //   4149: invokevirtual intValue : ()I
    //   4152: bipush #32
    //   4154: irem
    //   4155: invokestatic abs : (I)I
    //   4158: invokevirtual charAt : (I)C
    //   4161: if_icmple -> 4179
    //   4164: goto -> 4171
    //   4167: invokestatic a : (Ljava/lang/Throwable;)Ljava/lang/Throwable;
    //   4170: athrow
    //   4171: iconst_1
    //   4172: goto -> 4180
    //   4175: invokestatic a : (Ljava/lang/Throwable;)Ljava/lang/Throwable;
    //   4178: athrow
    //   4179: iconst_0
    //   4180: ireturn
    //   4181: astore_3
    //   4182: new java/lang/Exception
    //   4185: dup
    //   4186: aload_3
    //   4187: invokevirtual getMessage : ()Ljava/lang/String;
    //   4190: invokespecial <init> : (Ljava/lang/String;)V
    //   4193: athrow
    // Exception table:
    //   from	to	target	type
    //   4	4180	4181	java/lang/Throwable
    //   22	198	201	java/lang/Throwable
    //   168	235	238	java/lang/Throwable
    //   205	272	275	java/lang/Throwable
    //   242	309	312	java/lang/Throwable
    //   279	346	349	java/lang/Throwable
    //   316	383	386	java/lang/Throwable
    //   353	420	423	java/lang/Throwable
    //   390	457	460	java/lang/Throwable
    //   427	494	497	java/lang/Throwable
    //   464	531	534	java/lang/Throwable
    //   501	568	571	java/lang/Throwable
    //   538	605	608	java/lang/Throwable
    //   575	642	645	java/lang/Throwable
    //   612	679	682	java/lang/Throwable
    //   649	716	719	java/lang/Throwable
    //   686	753	756	java/lang/Throwable
    //   723	790	793	java/lang/Throwable
    //   760	827	830	java/lang/Throwable
    //   797	864	867	java/lang/Throwable
    //   834	901	904	java/lang/Throwable
    //   871	938	941	java/lang/Throwable
    //   908	975	978	java/lang/Throwable
    //   945	1012	1015	java/lang/Throwable
    //   982	1049	1052	java/lang/Throwable
    //   1019	1086	1089	java/lang/Throwable
    //   1056	1123	1126	java/lang/Throwable
    //   1093	1160	1163	java/lang/Throwable
    //   1130	1197	1200	java/lang/Throwable
    //   1167	1234	1237	java/lang/Throwable
    //   1204	1271	1274	java/lang/Throwable
    //   1241	1308	1311	java/lang/Throwable
    //   1278	1341	1344	java/lang/Throwable
    //   1381	1555	1558	java/lang/Throwable
    //   1524	1593	1596	java/lang/Throwable
    //   1562	1631	1634	java/lang/Throwable
    //   1600	1669	1672	java/lang/Throwable
    //   1638	1707	1710	java/lang/Throwable
    //   1676	1745	1748	java/lang/Throwable
    //   1714	1783	1786	java/lang/Throwable
    //   1752	1821	1824	java/lang/Throwable
    //   1790	1859	1862	java/lang/Throwable
    //   1828	1897	1900	java/lang/Throwable
    //   1866	1935	1938	java/lang/Throwable
    //   1904	1973	1976	java/lang/Throwable
    //   1942	2011	2014	java/lang/Throwable
    //   1980	2049	2052	java/lang/Throwable
    //   2018	2087	2090	java/lang/Throwable
    //   2056	2125	2128	java/lang/Throwable
    //   2094	2163	2166	java/lang/Throwable
    //   2132	2201	2204	java/lang/Throwable
    //   2170	2239	2242	java/lang/Throwable
    //   2208	2277	2280	java/lang/Throwable
    //   2246	2315	2318	java/lang/Throwable
    //   2284	2353	2356	java/lang/Throwable
    //   2322	2391	2394	java/lang/Throwable
    //   2360	2429	2432	java/lang/Throwable
    //   2398	2467	2470	java/lang/Throwable
    //   2436	2505	2508	java/lang/Throwable
    //   2474	2543	2546	java/lang/Throwable
    //   2512	2581	2584	java/lang/Throwable
    //   2550	2619	2622	java/lang/Throwable
    //   2588	2657	2660	java/lang/Throwable
    //   2626	2695	2698	java/lang/Throwable
    //   2664	2729	2732	java/lang/Throwable
    //   2814	2828	2828	java/lang/Throwable
    //   2839	2852	2855	java/lang/Throwable
    //   2844	2867	2870	java/lang/Throwable
    //   2859	2885	2888	java/lang/Throwable
    //   2874	2915	2918	java/lang/Throwable
    //   2981	3008	3011	java/lang/Throwable
    //   2998	3029	3032	java/lang/Throwable
    //   3015	3059	3062	java/lang/Throwable
    //   3036	3070	3070	java/lang/Throwable
    //   3081	3097	3100	java/lang/Throwable
    //   3290	3314	3317	java/lang/Throwable
    //   3388	3425	3425	java/lang/Throwable
    //   3429	3450	3450	java/lang/Throwable
    //   3454	3484	3484	java/lang/Throwable
    //   3667	4017	4020	java/lang/Throwable
    //   3851	3861	3861	java/lang/Throwable
    //   3865	3877	3877	java/lang/Throwable
    //   3881	3893	3893	java/lang/Throwable
    //   3897	3910	3910	java/lang/Throwable
    //   3914	3927	3927	java/lang/Throwable
    //   4022	4112	4115	java/lang/Throwable
    //   4067	4164	4167	java/lang/Throwable
    //   4119	4175	4175	java/lang/Throwable
  }
  
  static void ZK(Object[] paramArrayOfObject, Object paramObject) throws Throwable {}
  
  static void ZY(Object paramObject) {
    Zxdp.ZN = a(-7405, 26375);
    Zxdp.ZW = new BigInteger(a(-7399, 25955));
    boolean bool = Zt2e.ZN();
    try {
      try {
        if (Zeig.Zg.charAt(Math.abs(((BigInteger)Ze2k.ZK).intValue() % 32)) > Zk7o.Zb.charAt(Math.abs(((BigInteger)Zzn6.ZO).intValue() % 32))) {
          try {
            Zm0d.Zk(Class.forName(a(-7397, 18793)));
            if (!bool)
              Ztys.ZG(Class.forName(a(-7407, 2449))); 
          } catch (Throwable throwable) {
            throw a(null);
          } 
          return;
        } 
      } catch (Throwable throwable) {
        throw a(null);
      } 
      Ztys.ZG(Class.forName(a(-7407, 2449)));
    } catch (Throwable throwable) {}
  }
  
  static {
    // Byte code:
    //   0: bipush #11
    //   2: anewarray java/lang/String
    //   5: astore #5
    //   7: iconst_0
    //   8: istore_3
    //   9: ldc ''h(tNP|MJ{M25VFw<[Y\\nW4/GSYX\\f'@{jCYtUc(Ib\\t1B0\\t\\rV= )\--<}oO/q:i6y'KLwctsM DD|tn+[2U}^dc'
    //   11: dup
    //   12: astore_2
    //   13: invokevirtual length : ()I
    //   16: istore #4
    //   18: bipush #9
    //   20: istore_1
    //   21: iconst_m1
    //   22: istore_0
    //   23: bipush #112
    //   25: iinc #0, 1
    //   28: aload_2
    //   29: iload_0
    //   30: dup
    //   31: iload_1
    //   32: iadd
    //   33: invokevirtual substring : (II)Ljava/lang/String;
    //   36: iconst_m1
    //   37: goto -> 143
    //   40: aload #5
    //   42: swap
    //   43: iload_3
    //   44: iinc #3, 1
    //   47: swap
    //   48: aastore
    //   49: iload_0
    //   50: iload_1
    //   51: iadd
    //   52: dup
    //   53: istore_0
    //   54: iload #4
    //   56: if_icmpge -> 68
    //   59: aload_2
    //   60: iload_0
    //   61: invokevirtual charAt : (I)C
    //   64: istore_1
    //   65: goto -> 23
    //   68: ldc 'L\\tnou'
    //   70: dup
    //   71: astore_2
    //   72: invokevirtual length : ()I
    //   75: istore #4
    //   77: bipush #8
    //   79: istore_1
    //   80: iconst_m1
    //   81: istore_0
    //   82: bipush #102
    //   84: iinc #0, 1
    //   87: aload_2
    //   88: iload_0
    //   89: dup
    //   90: iload_1
    //   91: iadd
    //   92: invokevirtual substring : (II)Ljava/lang/String;
    //   95: iconst_0
    //   96: goto -> 143
    //   99: aload #5
    //   101: swap
    //   102: iload_3
    //   103: iinc #3, 1
    //   106: swap
    //   107: aastore
    //   108: iload_0
    //   109: iload_1
    //   110: iadd
    //   111: dup
    //   112: istore_0
    //   113: iload #4
    //   115: if_icmpge -> 127
    //   118: aload_2
    //   119: iload_0
    //   120: invokevirtual charAt : (I)C
    //   123: istore_1
    //   124: goto -> 82
    //   127: aload #5
    //   129: putstatic burp/Zg1l.a : [Ljava/lang/String;
    //   132: bipush #11
    //   134: anewarray java/lang/String
    //   137: putstatic burp/Zg1l.b : [Ljava/lang/String;
    //   140: goto -> 300
    //   143: dup_x2
    //   144: pop
    //   145: invokevirtual toCharArray : ()[C
    //   148: dup_x1
    //   149: arraylength
    //   150: dup_x2
    //   151: pop
    //   152: iconst_0
    //   153: istore #6
    //   155: dup2_x1
    //   156: pop2
    //   157: dup_x2
    //   158: iconst_1
    //   159: if_icmpgt -> 260
    //   162: dup2
    //   163: swap
    //   164: iload #6
    //   166: dup2_x1
    //   167: caload
    //   168: swap
    //   169: iload #6
    //   171: bipush #7
    //   173: irem
    //   174: tableswitch default -> 242, 0 -> 212, 1 -> 217, 2 -> 222, 3 -> 227, 4 -> 232, 5 -> 237
    //   212: bipush #65
    //   214: goto -> 244
    //   217: bipush #91
    //   219: goto -> 244
    //   222: bipush #59
    //   224: goto -> 244
    //   227: bipush #114
    //   229: goto -> 244
    //   232: bipush #114
    //   234: goto -> 244
    //   237: bipush #95
    //   239: goto -> 244
    //   242: bipush #119
    //   244: ixor
    //   245: ixor
    //   246: i2c
    //   247: castore
    //   248: iinc #6, 1
    //   251: dup
    //   252: ifne -> 260
    //   255: dup2
    //   256: dup_x1
    //   257: goto -> 166
    //   260: dup2_x1
    //   261: pop2
    //   262: dup_x2
    //   263: iload #6
    //   265: if_icmpgt -> 162
    //   268: pop
    //   269: new java/lang/String
    //   272: dup_x1
    //   273: swap
    //   274: invokespecial <init> : ([C)V
    //   277: invokevirtual intern : ()Ljava/lang/String;
    //   280: swap
    //   281: pop
    //   282: swap
    //   283: tableswitch default -> 40, 0 -> 99
    //   300: new java/math/BigInteger
    //   303: dup
    //   304: iconst_1
    //   305: bipush #32
    //   307: newarray byte
    //   309: dup
    //   310: iconst_0
    //   311: bipush #9
    //   313: bastore
    //   314: dup
    //   315: iconst_1
    //   316: bipush #-56
    //   318: bastore
    //   319: dup
    //   320: iconst_2
    //   321: bipush #38
    //   323: bastore
    //   324: dup
    //   325: iconst_3
    //   326: bipush #-87
    //   328: bastore
    //   329: dup
    //   330: iconst_4
    //   331: bipush #123
    //   333: bastore
    //   334: dup
    //   335: iconst_5
    //   336: bipush #-122
    //   338: bastore
    //   339: dup
    //   340: bipush #6
    //   342: bipush #-42
    //   344: bastore
    //   345: dup
    //   346: bipush #7
    //   348: bipush #-117
    //   350: bastore
    //   351: dup
    //   352: bipush #8
    //   354: bipush #-82
    //   356: bastore
    //   357: dup
    //   358: bipush #9
    //   360: bipush #-57
    //   362: bastore
    //   363: dup
    //   364: bipush #10
    //   366: bipush #-73
    //   368: bastore
    //   369: dup
    //   370: bipush #11
    //   372: bipush #107
    //   374: bastore
    //   375: dup
    //   376: bipush #12
    //   378: bipush #53
    //   380: bastore
    //   381: dup
    //   382: bipush #13
    //   384: bipush #-8
    //   386: bastore
    //   387: dup
    //   388: bipush #14
    //   390: bipush #-66
    //   392: bastore
    //   393: dup
    //   394: bipush #15
    //   396: bipush #-123
    //   398: bastore
    //   399: dup
    //   400: bipush #16
    //   402: bipush #-75
    //   404: bastore
    //   405: dup
    //   406: bipush #17
    //   408: bipush #-25
    //   410: bastore
    //   411: dup
    //   412: bipush #18
    //   414: bipush #-80
    //   416: bastore
    //   417: dup
    //   418: bipush #19
    //   420: bipush #106
    //   422: bastore
    //   423: dup
    //   424: bipush #20
    //   426: bipush #52
    //   428: bastore
    //   429: dup
    //   430: bipush #21
    //   432: bipush #-2
    //   434: bastore
    //   435: dup
    //   436: bipush #22
    //   438: bipush #-98
    //   440: bastore
    //   441: dup
    //   442: bipush #23
    //   444: bipush #57
    //   446: bastore
    //   447: dup
    //   448: bipush #24
    //   450: bipush #125
    //   452: bastore
    //   453: dup
    //   454: bipush #25
    //   456: bipush #-29
    //   458: bastore
    //   459: dup
    //   460: bipush #26
    //   462: bipush #8
    //   464: bastore
    //   465: dup
    //   466: bipush #27
    //   468: bipush #58
    //   470: bastore
    //   471: dup
    //   472: bipush #28
    //   474: bipush #72
    //   476: bastore
    //   477: dup
    //   478: bipush #29
    //   480: bipush #124
    //   482: bastore
    //   483: dup
    //   484: bipush #30
    //   486: bipush #61
    //   488: bastore
    //   489: dup
    //   490: bipush #31
    //   492: bipush #-61
    //   494: bastore
    //   495: invokespecial <init> : (I[B)V
    //   498: putstatic burp/Zg1l.Zg : Ljava/lang/Object;
    //   501: sipush #-7394
    //   504: sipush #-6880
    //   507: invokestatic a : (II)Ljava/lang/String;
    //   510: putstatic burp/Zg1l.Zl : Ljava/lang/String;
    //   513: return
  }
  
  private static Throwable a(Throwable paramThrowable) {
    return paramThrowable;
  }
  
  private static String a(int paramInt1, int paramInt2) {
    int i = (paramInt1 ^ 0xFFFFE31B) & 0xFFFF;
    if (b[i] == null) {
      char[] arrayOfChar = a[i].toCharArray();
      switch (arrayOfChar[0] & 0xFF) {
        case 0:
        
        case 1:
        
        case 2:
        
        case 3:
        
        case 4:
        
        case 5:
        
        case 6:
        
        case 7:
        
        case 8:
        
        case 9:
        
        case 10:
        
        case 11:
        
        case 12:
        
        case 13:
        
        case 14:
        
        case 15:
        
        case 16:
        
        case 17:
        
        case 18:
        
        case 19:
        
        case 20:
        
        case 21:
        
        case 22:
        
        case 23:
        
        case 24:
        
        case 25:
        
        case 26:
        
        case 27:
        
        case 28:
        
        case 29:
        
        case 30:
        
        case 31:
        
        case 32:
        
        case 33:
        
        case 34:
        
        case 35:
        
        case 36:
        
        case 37:
        
        case 38:
        
        case 39:
        
        case 40:
        
        case 41:
        
        case 42:
        
        case 43:
        
        case 44:
        
        case 45:
        
        case 46:
        
        case 47:
        
        case 48:
        
        case 49:
        
        case 50:
        
        case 51:
        
        case 52:
        
        case 53:
        
        case 54:
        
        case 55:
        
        case 56:
        
        case 57:
        
        case 58:
        
        case 59:
        
        case 60:
        
        case 61:
        
        case 62:
        
        case 63:
        
        case 64:
        
        case 65:
        
        case 66:
        
        case 67:
        
        case 68:
        
        case 69:
        
        case 70:
        
        case 71:
        
        case 72:
        
        case 73:
        
        case 74:
        
        case 75:
        
        case 76:
        
        case 77:
        
        case 78:
        
        case 79:
        
        case 80:
        
        case 81:
        
        case 82:
        
        case 83:
        
        case 84:
        
        case 85:
        
        case 86:
        
        case 87:
        
        case 88:
        
        case 89:
        
        case 90:
        
        case 91:
        
        case 92:
        
        case 93:
        
        case 94:
        
        case 95:
        
        case 96:
        
        case 97:
        
        case 98:
        
        case 99:
        
        case 100:
        
        case 101:
        
        case 102:
        
        case 103:
        
        case 104:
        
        case 105:
        
        case 106:
        
        case 107:
        
        case 108:
        
        case 109:
        
        case 110:
        
        case 111:
        
        case 112:
        
        case 113:
        
        case 114:
        
        case 115:
        
        case 116:
        
        case 117:
        
        case 118:
        
        case 119:
        
        case 120:
        
        case 121:
        
        case 122:
        
        case 123:
        
        case 124:
        
        case 125:
        
        case 126:
        
        case 127:
        
        case 128:
        
        case 129:
        
        case 130:
        
        case 131:
        
        case 132:
        
        case 133:
        
        case 134:
        
        case 135:
        
        case 136:
        
        case 137:
        
        case 138:
        
        case 139:
        
        case 140:
        
        case 141:
        
        case 142:
        
        case 143:
        
        case 144:
        
        case 145:
        
        case 146:
        
        case 147:
        
        case 148:
        
        case 149:
        
        case 150:
        
        case 151:
        
        case 152:
        
        case 153:
        
        case 154:
        
        case 155:
        
        case 156:
        
        case 157:
        
        case 158:
        
        case 159:
        
        case 160:
        
        case 161:
        
        case 162:
        
        case 163:
        
        case 164:
        
        case 165:
        
        case 166:
        
        case 167:
        
        case 168:
        
        case 169:
        
        case 170:
        
        case 171:
        
        case 172:
        
        case 173:
        
        case 174:
        
        case 175:
        
        case 176:
        
        case 177:
        
        case 178:
        
        case 179:
        
        case 180:
        
        case 181:
        
        case 182:
        
        case 183:
        
        case 184:
        
        case 185:
        
        case 186:
        
        case 187:
        
        case 188:
        
        case 189:
        
        case 190:
        
        case 191:
        
        case 192:
        
        case 193:
        
        case 194:
        
        case 195:
        
        case 196:
        
        case 197:
        
        case 198:
        
        case 199:
        
        case 200:
        
        case 201:
        
        case 202:
        
        case 203:
        
        case 204:
        
        case 205:
        
        case 206:
        
        case 207:
        
        case 208:
        
        case 209:
        
        case 210:
        
        case 211:
        
        case 212:
        
        case 213:
        
        case 214:
        
        case 215:
        
        case 216:
        
        case 217:
        
        case 218:
        
        case 219:
        
        case 220:
        
        case 221:
        
        case 222:
        
        case 223:
        
        case 224:
        
        case 225:
        
        case 226:
        
        case 227:
        
        case 228:
        
        case 229:
        
        case 230:
        
        case 231:
        
        case 232:
        
        case 233:
        
        case 234:
        
        case 235:
        
        case 236:
        
        case 237:
        
        case 238:
        
        case 239:
        
        case 240:
        
        case 241:
        
        case 242:
        
        case 243:
        
        case 244:
        
        case 245:
        
        case 246:
        
        case 247:
        
        case 248:
        
        case 249:
        
        case 250:
        
        case 251:
        
        case 252:
        
        case 253:
        
        case 254:
        
        default:
          break;
      } 
      char c = '';
      int j = (paramInt2 & 0xFF) - c;
      if (j < 0)
        j += 256; 
      int k = ((paramInt2 & 0xFFFF) >>> 8) - c;
      if (k < 0)
        k += 256; 
      for (byte b = 0; b < arrayOfChar.length; b++) {
        int m = b % 2;
        if (m == 0) {
          arrayOfChar[b] = (char)(arrayOfChar[b] ^ j);
          j = ((j >>> 3 | j << 5) ^ arrayOfChar[b]) & 0xFF;
        } else {
          arrayOfChar[b] = (char)(arrayOfChar[b] ^ k);
          k = ((k >>> 3 | k << 5) ^ arrayOfChar[b]) & 0xFF;
        } 
      } 
      b[i] = (new String(arrayOfChar)).intern();
    } 
    return b[i];
  }
}


/* Location:              C:\Program Files\BurpSuitePro\burpsuite_pro.jar!\burp\Zg1l.class
 * Java compiler version: 21 (65.0)
 * JD-Core Version:       1.1.3
 */