package burp;

import net.portswigger.Zm2;

public class Zg2e extends Zg2b<Zzem> {
  public static final Zmk7<Zzem> Ze;
  
  public static final Zmk7<Zzem> ZN;
  
  public static final Zmk7<Zzem> Zu;
  
  public static final Zmk7<Zzem> Zp;
  
  public static final Zmk7<Zzem> ZO;
  
  public static final Zmk7<Zzem> Zw;
  
  public Zg2e() {
    super(new Zgjg<>((Zmk7<Zzem>[])new Zmk7[] { Ze, ZN, Zu, Zp, ZO, Zw }));
  }
  
  private static String ZO(Zzem paramZzem) {
    Zt8r zt8r = new Zt8r();
    paramZzem.Zz(zt8r);
    return zt8r.ZK();
  }
  
  private static String Zw(Zzem paramZzem) {
    Zgp6 zgp6 = new Zgp6();
    paramZzem.Zz(zgp6);
    return zgp6.ZR();
  }
  
  private static void lambda$static$3(Zzem paramZzem, Object paramObject) {
    paramZzem.Zxg((String)paramObject);
  }
  
  private static Object lambda$static$2(Zzem paramZzem) {
    return paramZzem.Zg().ZH();
  }
  
  private static Object lambda$static$1(Zzem paramZzem) {
    return paramZzem.Zg().Zr();
  }
  
  private static void lambda$static$0(Zzem paramZzem, Object paramObject) {
    byte b = ((Byte)paramObject).byteValue();
    paramZzem.ZB(b);
    Zlxk.ZS = paramZzem.ZaP();
    Zm2.Zi(Zv8r.COLLABORATOR_INTERACTIONS_HIGHLIGHT, b);
  }
  
  static {
    // Byte code:
    //   0: iconst_5
    //   1: anewarray java/lang/String
    //   4: astore_0
    //   5: iconst_0
    //   6: istore #4
    //   8: ldc 'mDezBeY~RjB}_up}(XtT\^{'
    //   10: dup
    //   11: astore_3
    //   12: invokevirtual length : ()I
    //   15: istore #5
    //   17: iconst_4
    //   18: istore_2
    //   19: iconst_m1
    //   20: istore_1
    //   21: bipush #17
    //   23: iinc #1, 1
    //   26: aload_3
    //   27: iload_1
    //   28: dup
    //   29: iload_2
    //   30: iadd
    //   31: invokevirtual substring : (II)Ljava/lang/String;
    //   34: iconst_m1
    //   35: goto -> 127
    //   38: aload_0
    //   39: swap
    //   40: iload #4
    //   42: iinc #4, 1
    //   45: swap
    //   46: aastore
    //   47: iload_1
    //   48: iload_2
    //   49: iadd
    //   50: dup
    //   51: istore_1
    //   52: iload #5
    //   54: if_icmpge -> 66
    //   57: aload_3
    //   58: iload_1
    //   59: invokevirtual charAt : (I)C
    //   62: istore_2
    //   63: goto -> 21
    //   66: ldc 'QhD%UpM,oM~'
    //   68: dup
    //   69: astore_3
    //   70: invokevirtual length : ()I
    //   73: istore #5
    //   75: iconst_4
    //   76: istore_2
    //   77: iconst_m1
    //   78: istore_1
    //   79: bipush #45
    //   81: iinc #1, 1
    //   84: aload_3
    //   85: iload_1
    //   86: dup
    //   87: iload_2
    //   88: iadd
    //   89: invokevirtual substring : (II)Ljava/lang/String;
    //   92: iconst_0
    //   93: goto -> 127
    //   96: aload_0
    //   97: swap
    //   98: iload #4
    //   100: iinc #4, 1
    //   103: swap
    //   104: aastore
    //   105: iload_1
    //   106: iload_2
    //   107: iadd
    //   108: dup
    //   109: istore_1
    //   110: iload #5
    //   112: if_icmpge -> 124
    //   115: aload_3
    //   116: iload_1
    //   117: invokevirtual charAt : (I)C
    //   120: istore_2
    //   121: goto -> 79
    //   124: goto -> 284
    //   127: dup_x2
    //   128: pop
    //   129: invokevirtual toCharArray : ()[C
    //   132: dup_x1
    //   133: arraylength
    //   134: dup_x2
    //   135: pop
    //   136: iconst_0
    //   137: istore #6
    //   139: dup2_x1
    //   140: pop2
    //   141: dup_x2
    //   142: iconst_1
    //   143: if_icmpgt -> 243
    //   146: dup2
    //   147: swap
    //   148: iload #6
    //   150: dup2_x1
    //   151: caload
    //   152: swap
    //   153: iload #6
    //   155: bipush #7
    //   157: irem
    //   158: tableswitch default -> 225, 0 -> 196, 1 -> 201, 2 -> 206, 3 -> 211, 4 -> 216, 5 -> 221
    //   196: bipush #40
    //   198: goto -> 227
    //   201: bipush #60
    //   203: goto -> 227
    //   206: bipush #25
    //   208: goto -> 227
    //   211: bipush #109
    //   213: goto -> 227
    //   216: bipush #45
    //   218: goto -> 227
    //   221: iconst_1
    //   222: goto -> 227
    //   225: bipush #55
    //   227: ixor
    //   228: ixor
    //   229: i2c
    //   230: castore
    //   231: iinc #6, 1
    //   234: dup
    //   235: ifne -> 243
    //   238: dup2
    //   239: dup_x1
    //   240: goto -> 150
    //   243: dup2_x1
    //   244: pop2
    //   245: dup_x2
    //   246: iload #6
    //   248: if_icmpgt -> 146
    //   251: pop
    //   252: new java/lang/String
    //   255: dup_x1
    //   256: swap
    //   257: invokespecial <init> : ([C)V
    //   260: invokevirtual intern : ()Ljava/lang/String;
    //   263: swap
    //   264: pop
    //   265: swap
    //   266: tableswitch default -> 38, 0 -> 96
    //   284: <illegal opcode> Zl : ()Lburp/Zkuq;
    //   289: invokestatic Zh : (Lburp/Zkuq;)Lburp/Zz_2;
    //   292: ldc '#'
    //   294: invokevirtual ZL : (Ljava/lang/String;)Lburp/Zz_2;
    //   297: ldc java/lang/Integer
    //   299: invokevirtual Zg : (Ljava/lang/Class;)Lburp/Zz_2;
    //   302: bipush #7
    //   304: invokevirtual ZZ : (I)Lburp/Zz_2;
    //   307: iconst_0
    //   308: invokevirtual Zx : (Z)Lburp/Zz_2;
    //   311: new burp/Zm21
    //   314: dup
    //   315: invokespecial <init> : ()V
    //   318: invokevirtual ZM : (Ljavax/swing/table/TableCellRenderer;)Lburp/Zz_2;
    //   321: <illegal opcode> ZG : ()Lburp/Zzbi;
    //   326: invokevirtual ZR : (Lburp/Zzbi;)Lburp/Zz_2;
    //   329: new burp/Zlxk
    //   332: dup
    //   333: invokespecial <init> : ()V
    //   336: invokevirtual Zb : ()Ljavax/swing/table/TableCellEditor;
    //   339: invokevirtual ZE : (Ljavax/swing/table/TableCellEditor;)Lburp/Zz_2;
    //   342: getstatic javax/swing/SortOrder.ASCENDING : Ljavax/swing/SortOrder;
    //   345: invokevirtual ZV : (Ljavax/swing/SortOrder;)Lburp/Zz_2;
    //   348: invokevirtual ZH : ()Lburp/Zmk7;
    //   351: putstatic burp/Zg2e.Ze : Lburp/Zmk7;
    //   354: <illegal opcode> Zl : ()Lburp/Zkuq;
    //   359: invokestatic Zh : (Lburp/Zkuq;)Lburp/Zz_2;
    //   362: aload_0
    //   363: iconst_0
    //   364: aaload
    //   365: invokevirtual ZL : (Ljava/lang/String;)Lburp/Zz_2;
    //   368: ldc java/lang/String
    //   370: invokevirtual Zg : (Ljava/lang/Class;)Lburp/Zz_2;
    //   373: bipush #30
    //   375: invokevirtual ZZ : (I)Lburp/Zz_2;
    //   378: new burp/Zm21
    //   381: dup
    //   382: invokespecial <init> : ()V
    //   385: invokevirtual ZM : (Ljavax/swing/table/TableCellRenderer;)Lburp/Zz_2;
    //   388: invokevirtual ZH : ()Lburp/Zmk7;
    //   391: putstatic burp/Zg2e.ZN : Lburp/Zmk7;
    //   394: <illegal opcode> Zl : ()Lburp/Zkuq;
    //   399: invokestatic Zh : (Lburp/Zkuq;)Lburp/Zz_2;
    //   402: aload_0
    //   403: iconst_3
    //   404: aaload
    //   405: invokevirtual ZL : (Ljava/lang/String;)Lburp/Zz_2;
    //   408: ldc java/lang/String
    //   410: invokevirtual Zg : (Ljava/lang/Class;)Lburp/Zz_2;
    //   413: bipush #10
    //   415: invokevirtual ZZ : (I)Lburp/Zz_2;
    //   418: new burp/Zm21
    //   421: dup
    //   422: invokespecial <init> : ()V
    //   425: invokevirtual ZM : (Ljavax/swing/table/TableCellRenderer;)Lburp/Zz_2;
    //   428: invokevirtual ZH : ()Lburp/Zmk7;
    //   431: putstatic burp/Zg2e.Zu : Lburp/Zmk7;
    //   434: <illegal opcode> Zl : ()Lburp/Zkuq;
    //   439: invokestatic Zh : (Lburp/Zkuq;)Lburp/Zz_2;
    //   442: aload_0
    //   443: iconst_4
    //   444: aaload
    //   445: invokevirtual ZL : (Ljava/lang/String;)Lburp/Zz_2;
    //   448: ldc java/lang/String
    //   450: invokevirtual Zg : (Ljava/lang/Class;)Lburp/Zz_2;
    //   453: bipush #40
    //   455: invokevirtual ZZ : (I)Lburp/Zz_2;
    //   458: new burp/Zm21
    //   461: dup
    //   462: invokespecial <init> : ()V
    //   465: invokevirtual ZM : (Ljavax/swing/table/TableCellRenderer;)Lburp/Zz_2;
    //   468: invokevirtual ZH : ()Lburp/Zmk7;
    //   471: putstatic burp/Zg2e.Zp : Lburp/Zmk7;
    //   474: <illegal opcode> Zl : ()Lburp/Zkuq;
    //   479: invokestatic Zh : (Lburp/Zkuq;)Lburp/Zz_2;
    //   482: aload_0
    //   483: iconst_2
    //   484: aaload
    //   485: invokevirtual ZL : (Ljava/lang/String;)Lburp/Zz_2;
    //   488: ldc java/lang/String
    //   490: invokevirtual Zg : (Ljava/lang/Class;)Lburp/Zz_2;
    //   493: bipush #30
    //   495: invokevirtual ZZ : (I)Lburp/Zz_2;
    //   498: new burp/Zm21
    //   501: dup
    //   502: invokespecial <init> : ()V
    //   505: invokevirtual ZM : (Ljavax/swing/table/TableCellRenderer;)Lburp/Zz_2;
    //   508: invokevirtual ZH : ()Lburp/Zmk7;
    //   511: putstatic burp/Zg2e.ZO : Lburp/Zmk7;
    //   514: <illegal opcode> Zl : ()Lburp/Zkuq;
    //   519: invokestatic Zh : (Lburp/Zkuq;)Lburp/Zz_2;
    //   522: aload_0
    //   523: iconst_1
    //   524: aaload
    //   525: invokevirtual ZL : (Ljava/lang/String;)Lburp/Zz_2;
    //   528: ldc java/lang/String
    //   530: invokevirtual Zg : (Ljava/lang/Class;)Lburp/Zz_2;
    //   533: bipush #50
    //   535: invokevirtual ZZ : (I)Lburp/Zz_2;
    //   538: new burp/Zm21
    //   541: dup
    //   542: invokespecial <init> : ()V
    //   545: invokevirtual ZM : (Ljavax/swing/table/TableCellRenderer;)Lburp/Zz_2;
    //   548: <illegal opcode> ZG : ()Lburp/Zzbi;
    //   553: invokevirtual ZR : (Lburp/Zzbi;)Lburp/Zz_2;
    //   556: invokevirtual ZH : ()Lburp/Zmk7;
    //   559: putstatic burp/Zg2e.Zw : Lburp/Zmk7;
    //   562: return
  }
}


/* Location:              C:\Program Files\BurpSuitePro\burpsuite_pro.jar!\burp\Zg2e.class
 * Java compiler version: 21 (65.0)
 * JD-Core Version:       1.1.3
 */