package burp;

import java.math.BigInteger;

class Zg3m extends ClassLoader {
  static Object ZK;
  
  static String Za;
  
  private static final String[] a;
  
  private static final String[] b;
  
  static void Zc(Object[] paramArrayOfObject, Object paramObject) throws Throwable {}
  
  static void Zm(Object paramObject) {
    Zbzj.Zw = a(-30325, -1615);
    Zbzj.Zz = new BigInteger(a(-30322, 2716));
    boolean bool = Zt2e.ZK();
    try {
      try {
        if (Zbzj.Zw.charAt(Math.abs(((BigInteger)Zbzj.Zz).intValue() % 32)) <= Zbzj.Zw.charAt(Math.abs(((BigInteger)Zbzj.Zz).intValue() % 32))) {
          try {
            Zl5.Zu(Class.forName(a(-30327, 22481)));
            if (bool)
              Zg27.Zi(Class.forName(a(-30323, 25190))); 
          } catch (Throwable throwable) {
            throw a(null);
          } 
          return;
        } 
      } catch (Throwable throwable) {
        throw a(null);
      } 
      Zg27.Zi(Class.forName(a(-30323, 25190)));
    } catch (Throwable throwable) {}
  }
  
  static boolean ZH(Object[] paramArrayOfObject, Object paramObject) throws Throwable {
    // Byte code:
    //   0: invokestatic ZK : ()Z
    //   3: istore_2
    //   4: getstatic burp/Zewq.ZO : Ljava/lang/Object;
    //   7: checkcast java/math/BigInteger
    //   10: getstatic burp/Zs5i.ZD : Ljava/lang/Object;
    //   13: checkcast java/math/BigInteger
    //   16: invokevirtual add : (Ljava/math/BigInteger;)Ljava/math/BigInteger;
    //   19: putstatic burp/Zz0.ZJ : Ljava/lang/Object;
    //   22: new java/lang/StringBuilder
    //   25: dup
    //   26: invokespecial <init> : ()V
    //   29: astore_3
    //   30: iconst_0
    //   31: istore #4
    //   33: iload #4
    //   35: bipush #32
    //   37: if_icmpge -> 1371
    //   40: iload #4
    //   42: tableswitch default -> 1364, 0 -> 184, 1 -> 221, 2 -> 258, 3 -> 295, 4 -> 332, 5 -> 369, 6 -> 406, 7 -> 443, 8 -> 480, 9 -> 517, 10 -> 554, 11 -> 591, 12 -> 628, 13 -> 665, 14 -> 702, 15 -> 739, 16 -> 776, 17 -> 813, 18 -> 850, 19 -> 887, 20 -> 924, 21 -> 961, 22 -> 998, 23 -> 1035, 24 -> 1072, 25 -> 1109, 26 -> 1146, 27 -> 1183, 28 -> 1220, 29 -> 1257, 30 -> 1294, 31 -> 1331
    //   184: aload_3
    //   185: getstatic burp/Ztc2.Zr : Ljava/lang/String;
    //   188: getstatic burp/Zrct.ZV : Ljava/lang/Object;
    //   191: checkcast java/math/BigInteger
    //   194: invokevirtual intValue : ()I
    //   197: bipush #32
    //   199: irem
    //   200: invokestatic abs : (I)I
    //   203: invokevirtual charAt : (I)C
    //   206: invokevirtual append : (C)Ljava/lang/StringBuilder;
    //   209: pop
    //   210: iload_2
    //   211: ifeq -> 1364
    //   214: goto -> 221
    //   217: invokestatic a : (Ljava/lang/Throwable;)Ljava/lang/Throwable;
    //   220: athrow
    //   221: aload_3
    //   222: getstatic burp/Zbzj.Zw : Ljava/lang/String;
    //   225: getstatic burp/Zbxa.ZS : Ljava/lang/Object;
    //   228: checkcast java/math/BigInteger
    //   231: invokevirtual intValue : ()I
    //   234: bipush #32
    //   236: irem
    //   237: invokestatic abs : (I)I
    //   240: invokevirtual charAt : (I)C
    //   243: invokevirtual append : (C)Ljava/lang/StringBuilder;
    //   246: pop
    //   247: iload_2
    //   248: ifeq -> 1364
    //   251: goto -> 258
    //   254: invokestatic a : (Ljava/lang/Throwable;)Ljava/lang/Throwable;
    //   257: athrow
    //   258: aload_3
    //   259: getstatic burp/Ze9.Zh : Ljava/lang/String;
    //   262: getstatic burp/Zeju.Zk : Ljava/lang/Object;
    //   265: checkcast java/math/BigInteger
    //   268: invokevirtual intValue : ()I
    //   271: bipush #32
    //   273: irem
    //   274: invokestatic abs : (I)I
    //   277: invokevirtual charAt : (I)C
    //   280: invokevirtual append : (C)Ljava/lang/StringBuilder;
    //   283: pop
    //   284: iload_2
    //   285: ifeq -> 1364
    //   288: goto -> 295
    //   291: invokestatic a : (Ljava/lang/Throwable;)Ljava/lang/Throwable;
    //   294: athrow
    //   295: aload_3
    //   296: getstatic burp/Zenq.ZG : Ljava/lang/String;
    //   299: getstatic burp/Zs56.ZC : Ljava/lang/Object;
    //   302: checkcast java/math/BigInteger
    //   305: invokevirtual intValue : ()I
    //   308: bipush #32
    //   310: irem
    //   311: invokestatic abs : (I)I
    //   314: invokevirtual charAt : (I)C
    //   317: invokevirtual append : (C)Ljava/lang/StringBuilder;
    //   320: pop
    //   321: iload_2
    //   322: ifeq -> 1364
    //   325: goto -> 332
    //   328: invokestatic a : (Ljava/lang/Throwable;)Ljava/lang/Throwable;
    //   331: athrow
    //   332: aload_3
    //   333: getstatic burp/Zmvk.Z_ : Ljava/lang/String;
    //   336: getstatic burp/Zza3.Zb : Ljava/lang/Object;
    //   339: checkcast java/math/BigInteger
    //   342: invokevirtual intValue : ()I
    //   345: bipush #32
    //   347: irem
    //   348: invokestatic abs : (I)I
    //   351: invokevirtual charAt : (I)C
    //   354: invokevirtual append : (C)Ljava/lang/StringBuilder;
    //   357: pop
    //   358: iload_2
    //   359: ifeq -> 1364
    //   362: goto -> 369
    //   365: invokestatic a : (Ljava/lang/Throwable;)Ljava/lang/Throwable;
    //   368: athrow
    //   369: aload_3
    //   370: getstatic burp/Ztsc.ZL : Ljava/lang/String;
    //   373: getstatic burp/Zmh0.Zt : Ljava/lang/Object;
    //   376: checkcast java/math/BigInteger
    //   379: invokevirtual intValue : ()I
    //   382: bipush #32
    //   384: irem
    //   385: invokestatic abs : (I)I
    //   388: invokevirtual charAt : (I)C
    //   391: invokevirtual append : (C)Ljava/lang/StringBuilder;
    //   394: pop
    //   395: iload_2
    //   396: ifeq -> 1364
    //   399: goto -> 406
    //   402: invokestatic a : (Ljava/lang/Throwable;)Ljava/lang/Throwable;
    //   405: athrow
    //   406: aload_3
    //   407: getstatic burp/Zs5k.ZI : Ljava/lang/String;
    //   410: getstatic burp/Zlwi.Zw : Ljava/lang/Object;
    //   413: checkcast java/math/BigInteger
    //   416: invokevirtual intValue : ()I
    //   419: bipush #32
    //   421: irem
    //   422: invokestatic abs : (I)I
    //   425: invokevirtual charAt : (I)C
    //   428: invokevirtual append : (C)Ljava/lang/StringBuilder;
    //   431: pop
    //   432: iload_2
    //   433: ifeq -> 1364
    //   436: goto -> 443
    //   439: invokestatic a : (Ljava/lang/Throwable;)Ljava/lang/Throwable;
    //   442: athrow
    //   443: aload_3
    //   444: getstatic burp/Zecm.Zv : Ljava/lang/String;
    //   447: getstatic burp/Zl8s.ZY : Ljava/lang/Object;
    //   450: checkcast java/math/BigInteger
    //   453: invokevirtual intValue : ()I
    //   456: bipush #32
    //   458: irem
    //   459: invokestatic abs : (I)I
    //   462: invokevirtual charAt : (I)C
    //   465: invokevirtual append : (C)Ljava/lang/StringBuilder;
    //   468: pop
    //   469: iload_2
    //   470: ifeq -> 1364
    //   473: goto -> 480
    //   476: invokestatic a : (Ljava/lang/Throwable;)Ljava/lang/Throwable;
    //   479: athrow
    //   480: aload_3
    //   481: getstatic burp/Ze9.Zh : Ljava/lang/String;
    //   484: getstatic burp/Zrnw.ZN : Ljava/lang/Object;
    //   487: checkcast java/math/BigInteger
    //   490: invokevirtual intValue : ()I
    //   493: bipush #32
    //   495: irem
    //   496: invokestatic abs : (I)I
    //   499: invokevirtual charAt : (I)C
    //   502: invokevirtual append : (C)Ljava/lang/StringBuilder;
    //   505: pop
    //   506: iload_2
    //   507: ifeq -> 1364
    //   510: goto -> 517
    //   513: invokestatic a : (Ljava/lang/Throwable;)Ljava/lang/Throwable;
    //   516: athrow
    //   517: aload_3
    //   518: getstatic burp/Zth8.ZN : Ljava/lang/String;
    //   521: getstatic burp/Zzoc.Zx : Ljava/lang/Object;
    //   524: checkcast java/math/BigInteger
    //   527: invokevirtual intValue : ()I
    //   530: bipush #32
    //   532: irem
    //   533: invokestatic abs : (I)I
    //   536: invokevirtual charAt : (I)C
    //   539: invokevirtual append : (C)Ljava/lang/StringBuilder;
    //   542: pop
    //   543: iload_2
    //   544: ifeq -> 1364
    //   547: goto -> 554
    //   550: invokestatic a : (Ljava/lang/Throwable;)Ljava/lang/Throwable;
    //   553: athrow
    //   554: aload_3
    //   555: getstatic burp/Zzb2.ZJ : Ljava/lang/String;
    //   558: getstatic burp/Zm5s.ZB : Ljava/lang/Object;
    //   561: checkcast java/math/BigInteger
    //   564: invokevirtual intValue : ()I
    //   567: bipush #32
    //   569: irem
    //   570: invokestatic abs : (I)I
    //   573: invokevirtual charAt : (I)C
    //   576: invokevirtual append : (C)Ljava/lang/StringBuilder;
    //   579: pop
    //   580: iload_2
    //   581: ifeq -> 1364
    //   584: goto -> 591
    //   587: invokestatic a : (Ljava/lang/Throwable;)Ljava/lang/Throwable;
    //   590: athrow
    //   591: aload_3
    //   592: getstatic burp/Zro_.Zz : Ljava/lang/String;
    //   595: getstatic burp/Zg1k.ZG : Ljava/lang/Object;
    //   598: checkcast java/math/BigInteger
    //   601: invokevirtual intValue : ()I
    //   604: bipush #32
    //   606: irem
    //   607: invokestatic abs : (I)I
    //   610: invokevirtual charAt : (I)C
    //   613: invokevirtual append : (C)Ljava/lang/StringBuilder;
    //   616: pop
    //   617: iload_2
    //   618: ifeq -> 1364
    //   621: goto -> 628
    //   624: invokestatic a : (Ljava/lang/Throwable;)Ljava/lang/Throwable;
    //   627: athrow
    //   628: aload_3
    //   629: getstatic burp/Zzxa.Zl : Ljava/lang/String;
    //   632: getstatic burp/Zkc5.ZZ : Ljava/lang/Object;
    //   635: checkcast java/math/BigInteger
    //   638: invokevirtual intValue : ()I
    //   641: bipush #32
    //   643: irem
    //   644: invokestatic abs : (I)I
    //   647: invokevirtual charAt : (I)C
    //   650: invokevirtual append : (C)Ljava/lang/StringBuilder;
    //   653: pop
    //   654: iload_2
    //   655: ifeq -> 1364
    //   658: goto -> 665
    //   661: invokestatic a : (Ljava/lang/Throwable;)Ljava/lang/Throwable;
    //   664: athrow
    //   665: aload_3
    //   666: getstatic burp/Zs5i.ZJ : Ljava/lang/String;
    //   669: getstatic burp/Zzhu.ZW : Ljava/lang/Object;
    //   672: checkcast java/math/BigInteger
    //   675: invokevirtual intValue : ()I
    //   678: bipush #32
    //   680: irem
    //   681: invokestatic abs : (I)I
    //   684: invokevirtual charAt : (I)C
    //   687: invokevirtual append : (C)Ljava/lang/StringBuilder;
    //   690: pop
    //   691: iload_2
    //   692: ifeq -> 1364
    //   695: goto -> 702
    //   698: invokestatic a : (Ljava/lang/Throwable;)Ljava/lang/Throwable;
    //   701: athrow
    //   702: aload_3
    //   703: getstatic burp/Zrxf.ZG : Ljava/lang/String;
    //   706: getstatic burp/Zg1k.ZG : Ljava/lang/Object;
    //   709: checkcast java/math/BigInteger
    //   712: invokevirtual intValue : ()I
    //   715: bipush #32
    //   717: irem
    //   718: invokestatic abs : (I)I
    //   721: invokevirtual charAt : (I)C
    //   724: invokevirtual append : (C)Ljava/lang/StringBuilder;
    //   727: pop
    //   728: iload_2
    //   729: ifeq -> 1364
    //   732: goto -> 739
    //   735: invokestatic a : (Ljava/lang/Throwable;)Ljava/lang/Throwable;
    //   738: athrow
    //   739: aload_3
    //   740: getstatic burp/Zmdm.Za : Ljava/lang/String;
    //   743: getstatic burp/Zz0.ZJ : Ljava/lang/Object;
    //   746: checkcast java/math/BigInteger
    //   749: invokevirtual intValue : ()I
    //   752: bipush #32
    //   754: irem
    //   755: invokestatic abs : (I)I
    //   758: invokevirtual charAt : (I)C
    //   761: invokevirtual append : (C)Ljava/lang/StringBuilder;
    //   764: pop
    //   765: iload_2
    //   766: ifeq -> 1364
    //   769: goto -> 776
    //   772: invokestatic a : (Ljava/lang/Throwable;)Ljava/lang/Throwable;
    //   775: athrow
    //   776: aload_3
    //   777: getstatic burp/Zr9j.Zc : Ljava/lang/String;
    //   780: getstatic burp/Zeai.ZI : Ljava/lang/Object;
    //   783: checkcast java/math/BigInteger
    //   786: invokevirtual intValue : ()I
    //   789: bipush #32
    //   791: irem
    //   792: invokestatic abs : (I)I
    //   795: invokevirtual charAt : (I)C
    //   798: invokevirtual append : (C)Ljava/lang/StringBuilder;
    //   801: pop
    //   802: iload_2
    //   803: ifeq -> 1364
    //   806: goto -> 813
    //   809: invokestatic a : (Ljava/lang/Throwable;)Ljava/lang/Throwable;
    //   812: athrow
    //   813: aload_3
    //   814: getstatic burp/Zlzs.Zp : Ljava/lang/String;
    //   817: getstatic burp/Zewq.ZO : Ljava/lang/Object;
    //   820: checkcast java/math/BigInteger
    //   823: invokevirtual intValue : ()I
    //   826: bipush #32
    //   828: irem
    //   829: invokestatic abs : (I)I
    //   832: invokevirtual charAt : (I)C
    //   835: invokevirtual append : (C)Ljava/lang/StringBuilder;
    //   838: pop
    //   839: iload_2
    //   840: ifeq -> 1364
    //   843: goto -> 850
    //   846: invokestatic a : (Ljava/lang/Throwable;)Ljava/lang/Throwable;
    //   849: athrow
    //   850: aload_3
    //   851: getstatic burp/Ztg3.ZM : Ljava/lang/String;
    //   854: getstatic burp/Zmec.ZY : Ljava/lang/Object;
    //   857: checkcast java/math/BigInteger
    //   860: invokevirtual intValue : ()I
    //   863: bipush #32
    //   865: irem
    //   866: invokestatic abs : (I)I
    //   869: invokevirtual charAt : (I)C
    //   872: invokevirtual append : (C)Ljava/lang/StringBuilder;
    //   875: pop
    //   876: iload_2
    //   877: ifeq -> 1364
    //   880: goto -> 887
    //   883: invokestatic a : (Ljava/lang/Throwable;)Ljava/lang/Throwable;
    //   886: athrow
    //   887: aload_3
    //   888: getstatic burp/Zmvk.Z_ : Ljava/lang/String;
    //   891: getstatic burp/Zgs6.Za : Ljava/lang/Object;
    //   894: checkcast java/math/BigInteger
    //   897: invokevirtual intValue : ()I
    //   900: bipush #32
    //   902: irem
    //   903: invokestatic abs : (I)I
    //   906: invokevirtual charAt : (I)C
    //   909: invokevirtual append : (C)Ljava/lang/StringBuilder;
    //   912: pop
    //   913: iload_2
    //   914: ifeq -> 1364
    //   917: goto -> 924
    //   920: invokestatic a : (Ljava/lang/Throwable;)Ljava/lang/Throwable;
    //   923: athrow
    //   924: aload_3
    //   925: getstatic burp/Zso7.Zr : Ljava/lang/String;
    //   928: getstatic burp/Zevc.Zm : Ljava/lang/Object;
    //   931: checkcast java/math/BigInteger
    //   934: invokevirtual intValue : ()I
    //   937: bipush #32
    //   939: irem
    //   940: invokestatic abs : (I)I
    //   943: invokevirtual charAt : (I)C
    //   946: invokevirtual append : (C)Ljava/lang/StringBuilder;
    //   949: pop
    //   950: iload_2
    //   951: ifeq -> 1364
    //   954: goto -> 961
    //   957: invokestatic a : (Ljava/lang/Throwable;)Ljava/lang/Throwable;
    //   960: athrow
    //   961: aload_3
    //   962: getstatic burp/Zzh9.ZF : Ljava/lang/String;
    //   965: getstatic burp/Zr9j.Zw : Ljava/lang/Object;
    //   968: checkcast java/math/BigInteger
    //   971: invokevirtual intValue : ()I
    //   974: bipush #32
    //   976: irem
    //   977: invokestatic abs : (I)I
    //   980: invokevirtual charAt : (I)C
    //   983: invokevirtual append : (C)Ljava/lang/StringBuilder;
    //   986: pop
    //   987: iload_2
    //   988: ifeq -> 1364
    //   991: goto -> 998
    //   994: invokestatic a : (Ljava/lang/Throwable;)Ljava/lang/Throwable;
    //   997: athrow
    //   998: aload_3
    //   999: getstatic burp/Zl5.ZE : Ljava/lang/String;
    //   1002: getstatic burp/Zxee.Zj : Ljava/lang/Object;
    //   1005: checkcast java/math/BigInteger
    //   1008: invokevirtual intValue : ()I
    //   1011: bipush #32
    //   1013: irem
    //   1014: invokestatic abs : (I)I
    //   1017: invokevirtual charAt : (I)C
    //   1020: invokevirtual append : (C)Ljava/lang/StringBuilder;
    //   1023: pop
    //   1024: iload_2
    //   1025: ifeq -> 1364
    //   1028: goto -> 1035
    //   1031: invokestatic a : (Ljava/lang/Throwable;)Ljava/lang/Throwable;
    //   1034: athrow
    //   1035: aload_3
    //   1036: getstatic burp/Zxee.Zd : Ljava/lang/String;
    //   1039: getstatic burp/Ztsc.Zr : Ljava/lang/Object;
    //   1042: checkcast java/math/BigInteger
    //   1045: invokevirtual intValue : ()I
    //   1048: bipush #32
    //   1050: irem
    //   1051: invokestatic abs : (I)I
    //   1054: invokevirtual charAt : (I)C
    //   1057: invokevirtual append : (C)Ljava/lang/StringBuilder;
    //   1060: pop
    //   1061: iload_2
    //   1062: ifeq -> 1364
    //   1065: goto -> 1072
    //   1068: invokestatic a : (Ljava/lang/Throwable;)Ljava/lang/Throwable;
    //   1071: athrow
    //   1072: aload_3
    //   1073: getstatic burp/Zl1z.Zh : Ljava/lang/String;
    //   1076: getstatic burp/Ztg3.Zg : Ljava/lang/Object;
    //   1079: checkcast java/math/BigInteger
    //   1082: invokevirtual intValue : ()I
    //   1085: bipush #32
    //   1087: irem
    //   1088: invokestatic abs : (I)I
    //   1091: invokevirtual charAt : (I)C
    //   1094: invokevirtual append : (C)Ljava/lang/StringBuilder;
    //   1097: pop
    //   1098: iload_2
    //   1099: ifeq -> 1364
    //   1102: goto -> 1109
    //   1105: invokestatic a : (Ljava/lang/Throwable;)Ljava/lang/Throwable;
    //   1108: athrow
    //   1109: aload_3
    //   1110: getstatic burp/Ztsc.ZL : Ljava/lang/String;
    //   1113: getstatic burp/Zevc.Zm : Ljava/lang/Object;
    //   1116: checkcast java/math/BigInteger
    //   1119: invokevirtual intValue : ()I
    //   1122: bipush #32
    //   1124: irem
    //   1125: invokestatic abs : (I)I
    //   1128: invokevirtual charAt : (I)C
    //   1131: invokevirtual append : (C)Ljava/lang/StringBuilder;
    //   1134: pop
    //   1135: iload_2
    //   1136: ifeq -> 1364
    //   1139: goto -> 1146
    //   1142: invokestatic a : (Ljava/lang/Throwable;)Ljava/lang/Throwable;
    //   1145: athrow
    //   1146: aload_3
    //   1147: getstatic burp/Zzpj.ZR : Ljava/lang/String;
    //   1150: getstatic burp/Ztc2.ZM : Ljava/lang/Object;
    //   1153: checkcast java/math/BigInteger
    //   1156: invokevirtual intValue : ()I
    //   1159: bipush #32
    //   1161: irem
    //   1162: invokestatic abs : (I)I
    //   1165: invokevirtual charAt : (I)C
    //   1168: invokevirtual append : (C)Ljava/lang/StringBuilder;
    //   1171: pop
    //   1172: iload_2
    //   1173: ifeq -> 1364
    //   1176: goto -> 1183
    //   1179: invokestatic a : (Ljava/lang/Throwable;)Ljava/lang/Throwable;
    //   1182: athrow
    //   1183: aload_3
    //   1184: getstatic burp/Ze9.Zh : Ljava/lang/String;
    //   1187: getstatic burp/Ze_e.Za : Ljava/lang/Object;
    //   1190: checkcast java/math/BigInteger
    //   1193: invokevirtual intValue : ()I
    //   1196: bipush #32
    //   1198: irem
    //   1199: invokestatic abs : (I)I
    //   1202: invokevirtual charAt : (I)C
    //   1205: invokevirtual append : (C)Ljava/lang/StringBuilder;
    //   1208: pop
    //   1209: iload_2
    //   1210: ifeq -> 1364
    //   1213: goto -> 1220
    //   1216: invokestatic a : (Ljava/lang/Throwable;)Ljava/lang/Throwable;
    //   1219: athrow
    //   1220: aload_3
    //   1221: getstatic burp/Zmec.Zi : Ljava/lang/String;
    //   1224: getstatic burp/Zsf4.Zr : Ljava/lang/Object;
    //   1227: checkcast java/math/BigInteger
    //   1230: invokevirtual intValue : ()I
    //   1233: bipush #32
    //   1235: irem
    //   1236: invokestatic abs : (I)I
    //   1239: invokevirtual charAt : (I)C
    //   1242: invokevirtual append : (C)Ljava/lang/StringBuilder;
    //   1245: pop
    //   1246: iload_2
    //   1247: ifeq -> 1364
    //   1250: goto -> 1257
    //   1253: invokestatic a : (Ljava/lang/Throwable;)Ljava/lang/Throwable;
    //   1256: athrow
    //   1257: aload_3
    //   1258: getstatic burp/Zzxa.Zl : Ljava/lang/String;
    //   1261: getstatic burp/Zrp3.Zd : Ljava/lang/Object;
    //   1264: checkcast java/math/BigInteger
    //   1267: invokevirtual intValue : ()I
    //   1270: bipush #32
    //   1272: irem
    //   1273: invokestatic abs : (I)I
    //   1276: invokevirtual charAt : (I)C
    //   1279: invokevirtual append : (C)Ljava/lang/StringBuilder;
    //   1282: pop
    //   1283: iload_2
    //   1284: ifeq -> 1364
    //   1287: goto -> 1294
    //   1290: invokestatic a : (Ljava/lang/Throwable;)Ljava/lang/Throwable;
    //   1293: athrow
    //   1294: aload_3
    //   1295: getstatic burp/Zz8o.Zo : Ljava/lang/String;
    //   1298: getstatic burp/Zm14.ZZ : Ljava/lang/Object;
    //   1301: checkcast java/math/BigInteger
    //   1304: invokevirtual intValue : ()I
    //   1307: bipush #32
    //   1309: irem
    //   1310: invokestatic abs : (I)I
    //   1313: invokevirtual charAt : (I)C
    //   1316: invokevirtual append : (C)Ljava/lang/StringBuilder;
    //   1319: pop
    //   1320: iload_2
    //   1321: ifeq -> 1364
    //   1324: goto -> 1331
    //   1327: invokestatic a : (Ljava/lang/Throwable;)Ljava/lang/Throwable;
    //   1330: athrow
    //   1331: aload_3
    //   1332: getstatic burp/Zr8r.Zn : Ljava/lang/String;
    //   1335: getstatic burp/Zkfb.ZN : Ljava/lang/Object;
    //   1338: checkcast java/math/BigInteger
    //   1341: invokevirtual intValue : ()I
    //   1344: bipush #32
    //   1346: irem
    //   1347: invokestatic abs : (I)I
    //   1350: invokevirtual charAt : (I)C
    //   1353: invokevirtual append : (C)Ljava/lang/StringBuilder;
    //   1356: pop
    //   1357: goto -> 1364
    //   1360: invokestatic a : (Ljava/lang/Throwable;)Ljava/lang/Throwable;
    //   1363: athrow
    //   1364: iinc #4, 1
    //   1367: iload_2
    //   1368: ifeq -> 33
    //   1371: aload_3
    //   1372: invokevirtual toString : ()Ljava/lang/String;
    //   1375: putstatic burp/Zrfh.ZH : Ljava/lang/String;
    //   1378: getstatic burp/Zzhu.ZW : Ljava/lang/Object;
    //   1381: checkcast java/math/BigInteger
    //   1384: invokevirtual toByteArray : ()[B
    //   1387: astore #4
    //   1389: bipush #64
    //   1391: newarray byte
    //   1393: dup
    //   1394: iconst_0
    //   1395: bipush #-128
    //   1397: bastore
    //   1398: dup
    //   1399: iconst_1
    //   1400: iconst_0
    //   1401: bastore
    //   1402: dup
    //   1403: iconst_2
    //   1404: iconst_0
    //   1405: bastore
    //   1406: dup
    //   1407: iconst_3
    //   1408: iconst_0
    //   1409: bastore
    //   1410: dup
    //   1411: iconst_4
    //   1412: iconst_0
    //   1413: bastore
    //   1414: dup
    //   1415: iconst_5
    //   1416: iconst_0
    //   1417: bastore
    //   1418: dup
    //   1419: bipush #6
    //   1421: iconst_0
    //   1422: bastore
    //   1423: dup
    //   1424: bipush #7
    //   1426: iconst_0
    //   1427: bastore
    //   1428: dup
    //   1429: bipush #8
    //   1431: iconst_0
    //   1432: bastore
    //   1433: dup
    //   1434: bipush #9
    //   1436: iconst_0
    //   1437: bastore
    //   1438: dup
    //   1439: bipush #10
    //   1441: iconst_0
    //   1442: bastore
    //   1443: dup
    //   1444: bipush #11
    //   1446: iconst_0
    //   1447: bastore
    //   1448: dup
    //   1449: bipush #12
    //   1451: iconst_0
    //   1452: bastore
    //   1453: dup
    //   1454: bipush #13
    //   1456: iconst_0
    //   1457: bastore
    //   1458: dup
    //   1459: bipush #14
    //   1461: iconst_0
    //   1462: bastore
    //   1463: dup
    //   1464: bipush #15
    //   1466: iconst_0
    //   1467: bastore
    //   1468: dup
    //   1469: bipush #16
    //   1471: iconst_0
    //   1472: bastore
    //   1473: dup
    //   1474: bipush #17
    //   1476: iconst_0
    //   1477: bastore
    //   1478: dup
    //   1479: bipush #18
    //   1481: iconst_0
    //   1482: bastore
    //   1483: dup
    //   1484: bipush #19
    //   1486: iconst_0
    //   1487: bastore
    //   1488: dup
    //   1489: bipush #20
    //   1491: iconst_0
    //   1492: bastore
    //   1493: dup
    //   1494: bipush #21
    //   1496: iconst_0
    //   1497: bastore
    //   1498: dup
    //   1499: bipush #22
    //   1501: iconst_0
    //   1502: bastore
    //   1503: dup
    //   1504: bipush #23
    //   1506: iconst_0
    //   1507: bastore
    //   1508: dup
    //   1509: bipush #24
    //   1511: iconst_0
    //   1512: bastore
    //   1513: dup
    //   1514: bipush #25
    //   1516: iconst_0
    //   1517: bastore
    //   1518: dup
    //   1519: bipush #26
    //   1521: iconst_0
    //   1522: bastore
    //   1523: dup
    //   1524: bipush #27
    //   1526: iconst_0
    //   1527: bastore
    //   1528: dup
    //   1529: bipush #28
    //   1531: iconst_0
    //   1532: bastore
    //   1533: dup
    //   1534: bipush #29
    //   1536: iconst_0
    //   1537: bastore
    //   1538: dup
    //   1539: bipush #30
    //   1541: iconst_0
    //   1542: bastore
    //   1543: dup
    //   1544: bipush #31
    //   1546: iconst_0
    //   1547: bastore
    //   1548: dup
    //   1549: bipush #32
    //   1551: iconst_0
    //   1552: bastore
    //   1553: dup
    //   1554: bipush #33
    //   1556: iconst_0
    //   1557: bastore
    //   1558: dup
    //   1559: bipush #34
    //   1561: iconst_0
    //   1562: bastore
    //   1563: dup
    //   1564: bipush #35
    //   1566: iconst_0
    //   1567: bastore
    //   1568: dup
    //   1569: bipush #36
    //   1571: iconst_0
    //   1572: bastore
    //   1573: dup
    //   1574: bipush #37
    //   1576: iconst_0
    //   1577: bastore
    //   1578: dup
    //   1579: bipush #38
    //   1581: iconst_0
    //   1582: bastore
    //   1583: dup
    //   1584: bipush #39
    //   1586: iconst_0
    //   1587: bastore
    //   1588: dup
    //   1589: bipush #40
    //   1591: iconst_0
    //   1592: bastore
    //   1593: dup
    //   1594: bipush #41
    //   1596: iconst_0
    //   1597: bastore
    //   1598: dup
    //   1599: bipush #42
    //   1601: iconst_0
    //   1602: bastore
    //   1603: dup
    //   1604: bipush #43
    //   1606: iconst_0
    //   1607: bastore
    //   1608: dup
    //   1609: bipush #44
    //   1611: iconst_0
    //   1612: bastore
    //   1613: dup
    //   1614: bipush #45
    //   1616: iconst_0
    //   1617: bastore
    //   1618: dup
    //   1619: bipush #46
    //   1621: iconst_0
    //   1622: bastore
    //   1623: dup
    //   1624: bipush #47
    //   1626: iconst_0
    //   1627: bastore
    //   1628: dup
    //   1629: bipush #48
    //   1631: iconst_0
    //   1632: bastore
    //   1633: dup
    //   1634: bipush #49
    //   1636: iconst_0
    //   1637: bastore
    //   1638: dup
    //   1639: bipush #50
    //   1641: iconst_0
    //   1642: bastore
    //   1643: dup
    //   1644: bipush #51
    //   1646: iconst_0
    //   1647: bastore
    //   1648: dup
    //   1649: bipush #52
    //   1651: iconst_0
    //   1652: bastore
    //   1653: dup
    //   1654: bipush #53
    //   1656: iconst_0
    //   1657: bastore
    //   1658: dup
    //   1659: bipush #54
    //   1661: iconst_0
    //   1662: bastore
    //   1663: dup
    //   1664: bipush #55
    //   1666: iconst_0
    //   1667: bastore
    //   1668: dup
    //   1669: bipush #56
    //   1671: iconst_0
    //   1672: bastore
    //   1673: dup
    //   1674: bipush #57
    //   1676: iconst_0
    //   1677: bastore
    //   1678: dup
    //   1679: bipush #58
    //   1681: iconst_0
    //   1682: bastore
    //   1683: dup
    //   1684: bipush #59
    //   1686: iconst_0
    //   1687: bastore
    //   1688: dup
    //   1689: bipush #60
    //   1691: iconst_0
    //   1692: bastore
    //   1693: dup
    //   1694: bipush #61
    //   1696: iconst_0
    //   1697: bastore
    //   1698: dup
    //   1699: bipush #62
    //   1701: iconst_0
    //   1702: bastore
    //   1703: dup
    //   1704: bipush #63
    //   1706: iconst_0
    //   1707: bastore
    //   1708: astore #6
    //   1710: bipush #64
    //   1712: newarray int
    //   1714: dup
    //   1715: iconst_0
    //   1716: ldc 1116352408
    //   1718: iastore
    //   1719: dup
    //   1720: iconst_1
    //   1721: ldc 1899447441
    //   1723: iastore
    //   1724: dup
    //   1725: iconst_2
    //   1726: ldc -1245643825
    //   1728: iastore
    //   1729: dup
    //   1730: iconst_3
    //   1731: ldc -373957723
    //   1733: iastore
    //   1734: dup
    //   1735: iconst_4
    //   1736: ldc 961987163
    //   1738: iastore
    //   1739: dup
    //   1740: iconst_5
    //   1741: ldc 1508970993
    //   1743: iastore
    //   1744: dup
    //   1745: bipush #6
    //   1747: ldc -1841331548
    //   1749: iastore
    //   1750: dup
    //   1751: bipush #7
    //   1753: ldc -1424204075
    //   1755: iastore
    //   1756: dup
    //   1757: bipush #8
    //   1759: ldc -670586216
    //   1761: iastore
    //   1762: dup
    //   1763: bipush #9
    //   1765: ldc 310598401
    //   1767: iastore
    //   1768: dup
    //   1769: bipush #10
    //   1771: ldc 607225278
    //   1773: iastore
    //   1774: dup
    //   1775: bipush #11
    //   1777: ldc 1426881987
    //   1779: iastore
    //   1780: dup
    //   1781: bipush #12
    //   1783: ldc 1925078388
    //   1785: iastore
    //   1786: dup
    //   1787: bipush #13
    //   1789: ldc -2132889090
    //   1791: iastore
    //   1792: dup
    //   1793: bipush #14
    //   1795: ldc -1680079193
    //   1797: iastore
    //   1798: dup
    //   1799: bipush #15
    //   1801: ldc -1046744716
    //   1803: iastore
    //   1804: dup
    //   1805: bipush #16
    //   1807: ldc -459576895
    //   1809: iastore
    //   1810: dup
    //   1811: bipush #17
    //   1813: ldc -272742522
    //   1815: iastore
    //   1816: dup
    //   1817: bipush #18
    //   1819: ldc 264347078
    //   1821: iastore
    //   1822: dup
    //   1823: bipush #19
    //   1825: ldc 604807628
    //   1827: iastore
    //   1828: dup
    //   1829: bipush #20
    //   1831: ldc 770255983
    //   1833: iastore
    //   1834: dup
    //   1835: bipush #21
    //   1837: ldc 1249150122
    //   1839: iastore
    //   1840: dup
    //   1841: bipush #22
    //   1843: ldc 1555081692
    //   1845: iastore
    //   1846: dup
    //   1847: bipush #23
    //   1849: ldc 1996064986
    //   1851: iastore
    //   1852: dup
    //   1853: bipush #24
    //   1855: ldc -1740746414
    //   1857: iastore
    //   1858: dup
    //   1859: bipush #25
    //   1861: ldc -1473132947
    //   1863: iastore
    //   1864: dup
    //   1865: bipush #26
    //   1867: ldc -1341970488
    //   1869: iastore
    //   1870: dup
    //   1871: bipush #27
    //   1873: ldc -1084653625
    //   1875: iastore
    //   1876: dup
    //   1877: bipush #28
    //   1879: ldc -958395405
    //   1881: iastore
    //   1882: dup
    //   1883: bipush #29
    //   1885: ldc -710438585
    //   1887: iastore
    //   1888: dup
    //   1889: bipush #30
    //   1891: ldc 113926993
    //   1893: iastore
    //   1894: dup
    //   1895: bipush #31
    //   1897: ldc 338241895
    //   1899: iastore
    //   1900: dup
    //   1901: bipush #32
    //   1903: ldc 666307205
    //   1905: iastore
    //   1906: dup
    //   1907: bipush #33
    //   1909: ldc 773529912
    //   1911: iastore
    //   1912: dup
    //   1913: bipush #34
    //   1915: ldc 1294757372
    //   1917: iastore
    //   1918: dup
    //   1919: bipush #35
    //   1921: ldc 1396182291
    //   1923: iastore
    //   1924: dup
    //   1925: bipush #36
    //   1927: ldc 1695183700
    //   1929: iastore
    //   1930: dup
    //   1931: bipush #37
    //   1933: ldc 1986661051
    //   1935: iastore
    //   1936: dup
    //   1937: bipush #38
    //   1939: ldc -2117940946
    //   1941: iastore
    //   1942: dup
    //   1943: bipush #39
    //   1945: ldc -1838011259
    //   1947: iastore
    //   1948: dup
    //   1949: bipush #40
    //   1951: ldc -1564481375
    //   1953: iastore
    //   1954: dup
    //   1955: bipush #41
    //   1957: ldc -1474664885
    //   1959: iastore
    //   1960: dup
    //   1961: bipush #42
    //   1963: ldc -1035236496
    //   1965: iastore
    //   1966: dup
    //   1967: bipush #43
    //   1969: ldc -949202525
    //   1971: iastore
    //   1972: dup
    //   1973: bipush #44
    //   1975: ldc -778901479
    //   1977: iastore
    //   1978: dup
    //   1979: bipush #45
    //   1981: ldc -694614492
    //   1983: iastore
    //   1984: dup
    //   1985: bipush #46
    //   1987: ldc -200395387
    //   1989: iastore
    //   1990: dup
    //   1991: bipush #47
    //   1993: ldc 275423344
    //   1995: iastore
    //   1996: dup
    //   1997: bipush #48
    //   1999: ldc 430227734
    //   2001: iastore
    //   2002: dup
    //   2003: bipush #49
    //   2005: ldc 506948616
    //   2007: iastore
    //   2008: dup
    //   2009: bipush #50
    //   2011: ldc 659060556
    //   2013: iastore
    //   2014: dup
    //   2015: bipush #51
    //   2017: ldc 883997877
    //   2019: iastore
    //   2020: dup
    //   2021: bipush #52
    //   2023: ldc 958139571
    //   2025: iastore
    //   2026: dup
    //   2027: bipush #53
    //   2029: ldc 1322822218
    //   2031: iastore
    //   2032: dup
    //   2033: bipush #54
    //   2035: ldc 1537002063
    //   2037: iastore
    //   2038: dup
    //   2039: bipush #55
    //   2041: ldc 1747873779
    //   2043: iastore
    //   2044: dup
    //   2045: bipush #56
    //   2047: ldc 1955562222
    //   2049: iastore
    //   2050: dup
    //   2051: bipush #57
    //   2053: ldc 2024104815
    //   2055: iastore
    //   2056: dup
    //   2057: bipush #58
    //   2059: ldc -2067236844
    //   2061: iastore
    //   2062: dup
    //   2063: bipush #59
    //   2065: ldc -1933114872
    //   2067: iastore
    //   2068: dup
    //   2069: bipush #60
    //   2071: ldc -1866530822
    //   2073: iastore
    //   2074: dup
    //   2075: bipush #61
    //   2077: ldc -1538233109
    //   2079: iastore
    //   2080: dup
    //   2081: bipush #62
    //   2083: ldc -1090935817
    //   2085: iastore
    //   2086: dup
    //   2087: bipush #63
    //   2089: ldc -965641998
    //   2091: iastore
    //   2092: astore #7
    //   2094: iconst_2
    //   2095: newarray int
    //   2097: dup
    //   2098: iconst_0
    //   2099: iconst_0
    //   2100: iastore
    //   2101: dup
    //   2102: iconst_1
    //   2103: iconst_0
    //   2104: iastore
    //   2105: astore #8
    //   2107: bipush #8
    //   2109: newarray int
    //   2111: dup
    //   2112: iconst_0
    //   2113: ldc 1779033703
    //   2115: iastore
    //   2116: dup
    //   2117: iconst_1
    //   2118: ldc -1150833019
    //   2120: iastore
    //   2121: dup
    //   2122: iconst_2
    //   2123: ldc 1013904242
    //   2125: iastore
    //   2126: dup
    //   2127: iconst_3
    //   2128: ldc -1521486534
    //   2130: iastore
    //   2131: dup
    //   2132: iconst_4
    //   2133: ldc 1359893119
    //   2135: iastore
    //   2136: dup
    //   2137: iconst_5
    //   2138: ldc -1694144372
    //   2140: iastore
    //   2141: dup
    //   2142: bipush #6
    //   2144: ldc 528734635
    //   2146: iastore
    //   2147: dup
    //   2148: bipush #7
    //   2150: ldc 1541459225
    //   2152: iastore
    //   2153: astore #9
    //   2155: bipush #64
    //   2157: newarray byte
    //   2159: astore #10
    //   2161: bipush #64
    //   2163: newarray byte
    //   2165: astore #11
    //   2167: aload #4
    //   2169: arraylength
    //   2170: istore #12
    //   2172: aload #8
    //   2174: iconst_0
    //   2175: iaload
    //   2176: bipush #63
    //   2178: iand
    //   2179: istore #13
    //   2181: aload #8
    //   2183: iconst_0
    //   2184: dup2
    //   2185: iaload
    //   2186: iload #12
    //   2188: iadd
    //   2189: iastore
    //   2190: aload #8
    //   2192: iconst_0
    //   2193: dup2
    //   2194: iaload
    //   2195: iconst_m1
    //   2196: iand
    //   2197: iastore
    //   2198: aload #8
    //   2200: iconst_0
    //   2201: iaload
    //   2202: iload #12
    //   2204: if_icmpge -> 2222
    //   2207: aload #8
    //   2209: iconst_1
    //   2210: dup2
    //   2211: iaload
    //   2212: iconst_1
    //   2213: iadd
    //   2214: iastore
    //   2215: goto -> 2222
    //   2218: invokestatic a : (Ljava/lang/Throwable;)Ljava/lang/Throwable;
    //   2221: athrow
    //   2222: iconst_0
    //   2223: istore #14
    //   2225: iload #12
    //   2227: bipush #64
    //   2229: if_icmplt -> 2839
    //   2232: iconst_0
    //   2233: istore #15
    //   2235: iload #15
    //   2237: bipush #64
    //   2239: if_icmpge -> 2262
    //   2242: aload #11
    //   2244: iload #15
    //   2246: aload #4
    //   2248: iload #14
    //   2250: iload #15
    //   2252: iadd
    //   2253: baload
    //   2254: bastore
    //   2255: iinc #15, 1
    //   2258: iload_2
    //   2259: ifeq -> 2235
    //   2262: bipush #64
    //   2264: newarray int
    //   2266: astore #15
    //   2268: bipush #8
    //   2270: newarray int
    //   2272: astore #16
    //   2274: iconst_0
    //   2275: istore #17
    //   2277: iload #17
    //   2279: bipush #8
    //   2281: if_icmpge -> 2301
    //   2284: aload #16
    //   2286: iload #17
    //   2288: aload #9
    //   2290: iload #17
    //   2292: iaload
    //   2293: iastore
    //   2294: iinc #17, 1
    //   2297: iload_2
    //   2298: ifeq -> 2277
    //   2301: iconst_0
    //   2302: istore #17
    //   2304: iload #17
    //   2306: bipush #64
    //   2308: if_icmpge -> 2799
    //   2311: iload #17
    //   2313: bipush #16
    //   2315: if_icmpge -> 2396
    //   2318: aload #15
    //   2320: iload #17
    //   2322: aload #11
    //   2324: iconst_4
    //   2325: iload #17
    //   2327: imul
    //   2328: baload
    //   2329: sipush #255
    //   2332: iand
    //   2333: bipush #24
    //   2335: ishl
    //   2336: aload #11
    //   2338: iconst_4
    //   2339: iload #17
    //   2341: imul
    //   2342: iconst_1
    //   2343: iadd
    //   2344: baload
    //   2345: sipush #255
    //   2348: iand
    //   2349: bipush #16
    //   2351: ishl
    //   2352: ior
    //   2353: aload #11
    //   2355: iconst_4
    //   2356: iload #17
    //   2358: imul
    //   2359: iconst_2
    //   2360: iadd
    //   2361: baload
    //   2362: sipush #255
    //   2365: iand
    //   2366: bipush #8
    //   2368: ishl
    //   2369: ior
    //   2370: aload #11
    //   2372: iconst_4
    //   2373: iload #17
    //   2375: imul
    //   2376: iconst_3
    //   2377: iadd
    //   2378: baload
    //   2379: sipush #255
    //   2382: iand
    //   2383: ior
    //   2384: iastore
    //   2385: iload_2
    //   2386: ifeq -> 2539
    //   2389: goto -> 2396
    //   2392: invokestatic a : (Ljava/lang/Throwable;)Ljava/lang/Throwable;
    //   2395: athrow
    //   2396: aload #15
    //   2398: iload #17
    //   2400: aload #15
    //   2402: iload #17
    //   2404: iconst_2
    //   2405: isub
    //   2406: iaload
    //   2407: bipush #17
    //   2409: iushr
    //   2410: aload #15
    //   2412: iload #17
    //   2414: iconst_2
    //   2415: isub
    //   2416: iaload
    //   2417: bipush #15
    //   2419: ishl
    //   2420: ior
    //   2421: aload #15
    //   2423: iload #17
    //   2425: iconst_2
    //   2426: isub
    //   2427: iaload
    //   2428: bipush #19
    //   2430: iushr
    //   2431: aload #15
    //   2433: iload #17
    //   2435: iconst_2
    //   2436: isub
    //   2437: iaload
    //   2438: bipush #13
    //   2440: ishl
    //   2441: ior
    //   2442: ixor
    //   2443: aload #15
    //   2445: iload #17
    //   2447: iconst_2
    //   2448: isub
    //   2449: iaload
    //   2450: bipush #10
    //   2452: iushr
    //   2453: ixor
    //   2454: aload #15
    //   2456: iload #17
    //   2458: bipush #7
    //   2460: isub
    //   2461: iaload
    //   2462: iadd
    //   2463: aload #15
    //   2465: iload #17
    //   2467: bipush #15
    //   2469: isub
    //   2470: iaload
    //   2471: bipush #7
    //   2473: iushr
    //   2474: aload #15
    //   2476: iload #17
    //   2478: bipush #15
    //   2480: isub
    //   2481: iaload
    //   2482: bipush #25
    //   2484: ishl
    //   2485: ior
    //   2486: aload #15
    //   2488: iload #17
    //   2490: bipush #15
    //   2492: isub
    //   2493: iaload
    //   2494: bipush #18
    //   2496: iushr
    //   2497: aload #15
    //   2499: iload #17
    //   2501: bipush #15
    //   2503: isub
    //   2504: iaload
    //   2505: bipush #14
    //   2507: ishl
    //   2508: ior
    //   2509: ixor
    //   2510: aload #15
    //   2512: iload #17
    //   2514: bipush #15
    //   2516: isub
    //   2517: iaload
    //   2518: iconst_3
    //   2519: iushr
    //   2520: ixor
    //   2521: iadd
    //   2522: aload #15
    //   2524: iload #17
    //   2526: bipush #16
    //   2528: isub
    //   2529: iaload
    //   2530: iadd
    //   2531: iastore
    //   2532: goto -> 2539
    //   2535: invokestatic a : (Ljava/lang/Throwable;)Ljava/lang/Throwable;
    //   2538: athrow
    //   2539: aload #16
    //   2541: bipush #7
    //   2543: iaload
    //   2544: aload #16
    //   2546: iconst_4
    //   2547: iaload
    //   2548: bipush #6
    //   2550: iushr
    //   2551: aload #16
    //   2553: iconst_4
    //   2554: iaload
    //   2555: bipush #26
    //   2557: ishl
    //   2558: ior
    //   2559: aload #16
    //   2561: iconst_4
    //   2562: iaload
    //   2563: bipush #11
    //   2565: iushr
    //   2566: aload #16
    //   2568: iconst_4
    //   2569: iaload
    //   2570: bipush #21
    //   2572: ishl
    //   2573: ior
    //   2574: ixor
    //   2575: aload #16
    //   2577: iconst_4
    //   2578: iaload
    //   2579: bipush #25
    //   2581: iushr
    //   2582: aload #16
    //   2584: iconst_4
    //   2585: iaload
    //   2586: bipush #7
    //   2588: ishl
    //   2589: ior
    //   2590: ixor
    //   2591: iadd
    //   2592: aload #16
    //   2594: bipush #6
    //   2596: iaload
    //   2597: aload #16
    //   2599: iconst_4
    //   2600: iaload
    //   2601: aload #16
    //   2603: iconst_5
    //   2604: iaload
    //   2605: aload #16
    //   2607: bipush #6
    //   2609: iaload
    //   2610: ixor
    //   2611: iand
    //   2612: ixor
    //   2613: iadd
    //   2614: aload #7
    //   2616: iload #17
    //   2618: iaload
    //   2619: iadd
    //   2620: aload #15
    //   2622: iload #17
    //   2624: iaload
    //   2625: iadd
    //   2626: istore #18
    //   2628: aload #16
    //   2630: iconst_0
    //   2631: iaload
    //   2632: iconst_2
    //   2633: iushr
    //   2634: aload #16
    //   2636: iconst_0
    //   2637: iaload
    //   2638: bipush #30
    //   2640: ishl
    //   2641: ior
    //   2642: aload #16
    //   2644: iconst_0
    //   2645: iaload
    //   2646: bipush #13
    //   2648: iushr
    //   2649: aload #16
    //   2651: iconst_0
    //   2652: iaload
    //   2653: bipush #19
    //   2655: ishl
    //   2656: ior
    //   2657: ixor
    //   2658: aload #16
    //   2660: iconst_0
    //   2661: iaload
    //   2662: bipush #22
    //   2664: iushr
    //   2665: aload #16
    //   2667: iconst_0
    //   2668: iaload
    //   2669: bipush #10
    //   2671: ishl
    //   2672: ior
    //   2673: ixor
    //   2674: aload #16
    //   2676: iconst_0
    //   2677: iaload
    //   2678: aload #16
    //   2680: iconst_1
    //   2681: iaload
    //   2682: iand
    //   2683: aload #16
    //   2685: iconst_2
    //   2686: iaload
    //   2687: aload #16
    //   2689: iconst_0
    //   2690: iaload
    //   2691: aload #16
    //   2693: iconst_1
    //   2694: iaload
    //   2695: ior
    //   2696: iand
    //   2697: ior
    //   2698: iadd
    //   2699: istore #19
    //   2701: aload #16
    //   2703: iconst_3
    //   2704: dup2
    //   2705: iaload
    //   2706: iload #18
    //   2708: iadd
    //   2709: iastore
    //   2710: aload #16
    //   2712: bipush #7
    //   2714: iload #18
    //   2716: iload #19
    //   2718: iadd
    //   2719: iastore
    //   2720: aload #16
    //   2722: bipush #7
    //   2724: iaload
    //   2725: istore #18
    //   2727: aload #16
    //   2729: bipush #7
    //   2731: aload #16
    //   2733: bipush #6
    //   2735: iaload
    //   2736: iastore
    //   2737: aload #16
    //   2739: bipush #6
    //   2741: aload #16
    //   2743: iconst_5
    //   2744: iaload
    //   2745: iastore
    //   2746: aload #16
    //   2748: iconst_5
    //   2749: aload #16
    //   2751: iconst_4
    //   2752: iaload
    //   2753: iastore
    //   2754: aload #16
    //   2756: iconst_4
    //   2757: aload #16
    //   2759: iconst_3
    //   2760: iaload
    //   2761: iastore
    //   2762: aload #16
    //   2764: iconst_3
    //   2765: aload #16
    //   2767: iconst_2
    //   2768: iaload
    //   2769: iastore
    //   2770: aload #16
    //   2772: iconst_2
    //   2773: aload #16
    //   2775: iconst_1
    //   2776: iaload
    //   2777: iastore
    //   2778: aload #16
    //   2780: iconst_1
    //   2781: aload #16
    //   2783: iconst_0
    //   2784: iaload
    //   2785: iastore
    //   2786: aload #16
    //   2788: iconst_0
    //   2789: iload #18
    //   2791: iastore
    //   2792: iinc #17, 1
    //   2795: iload_2
    //   2796: ifeq -> 2304
    //   2799: iconst_0
    //   2800: istore #17
    //   2802: iload #17
    //   2804: bipush #8
    //   2806: if_icmpge -> 2829
    //   2809: aload #9
    //   2811: iload #17
    //   2813: dup2
    //   2814: iaload
    //   2815: aload #16
    //   2817: iload #17
    //   2819: iaload
    //   2820: iadd
    //   2821: iastore
    //   2822: iinc #17, 1
    //   2825: iload_2
    //   2826: ifeq -> 2802
    //   2829: iinc #14, 64
    //   2832: iinc #12, -64
    //   2835: iload_2
    //   2836: ifeq -> 2225
    //   2839: iload #12
    //   2841: ifle -> 2877
    //   2844: iconst_0
    //   2845: istore #15
    //   2847: iload #15
    //   2849: iload #12
    //   2851: if_icmpge -> 2877
    //   2854: aload #10
    //   2856: iload #13
    //   2858: iload #15
    //   2860: iadd
    //   2861: aload #4
    //   2863: iload #14
    //   2865: iload #15
    //   2867: iadd
    //   2868: baload
    //   2869: bastore
    //   2870: iinc #15, 1
    //   2873: iload_2
    //   2874: ifeq -> 2847
    //   2877: aload #8
    //   2879: iconst_0
    //   2880: iaload
    //   2881: bipush #29
    //   2883: iushr
    //   2884: aload #8
    //   2886: iconst_1
    //   2887: iaload
    //   2888: iconst_3
    //   2889: ishl
    //   2890: ior
    //   2891: istore #15
    //   2893: aload #8
    //   2895: iconst_0
    //   2896: iaload
    //   2897: iconst_3
    //   2898: ishl
    //   2899: istore #16
    //   2901: aload #8
    //   2903: iconst_0
    //   2904: iaload
    //   2905: bipush #63
    //   2907: iand
    //   2908: istore #17
    //   2910: iload #17
    //   2912: bipush #56
    //   2914: if_icmpge -> 2929
    //   2917: bipush #56
    //   2919: iload #17
    //   2921: isub
    //   2922: goto -> 2934
    //   2925: invokestatic a : (Ljava/lang/Throwable;)Ljava/lang/Throwable;
    //   2928: athrow
    //   2929: bipush #120
    //   2931: iload #17
    //   2933: isub
    //   2934: istore #18
    //   2936: aload #8
    //   2938: iconst_0
    //   2939: iaload
    //   2940: bipush #63
    //   2942: iand
    //   2943: istore #13
    //   2945: bipush #64
    //   2947: iload #13
    //   2949: isub
    //   2950: istore #19
    //   2952: aload #8
    //   2954: iconst_0
    //   2955: dup2
    //   2956: iaload
    //   2957: iload #18
    //   2959: iadd
    //   2960: iastore
    //   2961: aload #8
    //   2963: iconst_0
    //   2964: dup2
    //   2965: iaload
    //   2966: iconst_m1
    //   2967: iand
    //   2968: iastore
    //   2969: aload #8
    //   2971: iconst_0
    //   2972: iaload
    //   2973: iload #18
    //   2975: if_icmpge -> 2993
    //   2978: aload #8
    //   2980: iconst_1
    //   2981: dup2
    //   2982: iaload
    //   2983: iconst_1
    //   2984: iadd
    //   2985: iastore
    //   2986: goto -> 2993
    //   2989: invokestatic a : (Ljava/lang/Throwable;)Ljava/lang/Throwable;
    //   2992: athrow
    //   2993: iconst_0
    //   2994: istore #14
    //   2996: iload #13
    //   2998: ifle -> 3629
    //   3001: iload #18
    //   3003: iload #19
    //   3005: if_icmplt -> 3629
    //   3008: goto -> 3015
    //   3011: invokestatic a : (Ljava/lang/Throwable;)Ljava/lang/Throwable;
    //   3014: athrow
    //   3015: iconst_0
    //   3016: istore #20
    //   3018: iload #20
    //   3020: iload #19
    //   3022: if_icmpge -> 3045
    //   3025: aload #10
    //   3027: iload #13
    //   3029: iload #20
    //   3031: iadd
    //   3032: aload #6
    //   3034: iload #20
    //   3036: baload
    //   3037: bastore
    //   3038: iinc #20, 1
    //   3041: iload_2
    //   3042: ifeq -> 3018
    //   3045: bipush #64
    //   3047: newarray int
    //   3049: astore #20
    //   3051: bipush #8
    //   3053: newarray int
    //   3055: astore #21
    //   3057: iconst_0
    //   3058: istore #22
    //   3060: iload #22
    //   3062: bipush #8
    //   3064: if_icmpge -> 3084
    //   3067: aload #21
    //   3069: iload #22
    //   3071: aload #9
    //   3073: iload #22
    //   3075: iaload
    //   3076: iastore
    //   3077: iinc #22, 1
    //   3080: iload_2
    //   3081: ifeq -> 3060
    //   3084: iconst_0
    //   3085: istore #22
    //   3087: iload #22
    //   3089: bipush #64
    //   3091: if_icmpge -> 3582
    //   3094: iload #22
    //   3096: bipush #16
    //   3098: if_icmpge -> 3179
    //   3101: aload #20
    //   3103: iload #22
    //   3105: aload #10
    //   3107: iconst_4
    //   3108: iload #22
    //   3110: imul
    //   3111: baload
    //   3112: sipush #255
    //   3115: iand
    //   3116: bipush #24
    //   3118: ishl
    //   3119: aload #10
    //   3121: iconst_4
    //   3122: iload #22
    //   3124: imul
    //   3125: iconst_1
    //   3126: iadd
    //   3127: baload
    //   3128: sipush #255
    //   3131: iand
    //   3132: bipush #16
    //   3134: ishl
    //   3135: ior
    //   3136: aload #10
    //   3138: iconst_4
    //   3139: iload #22
    //   3141: imul
    //   3142: iconst_2
    //   3143: iadd
    //   3144: baload
    //   3145: sipush #255
    //   3148: iand
    //   3149: bipush #8
    //   3151: ishl
    //   3152: ior
    //   3153: aload #10
    //   3155: iconst_4
    //   3156: iload #22
    //   3158: imul
    //   3159: iconst_3
    //   3160: iadd
    //   3161: baload
    //   3162: sipush #255
    //   3165: iand
    //   3166: ior
    //   3167: iastore
    //   3168: iload_2
    //   3169: ifeq -> 3322
    //   3172: goto -> 3179
    //   3175: invokestatic a : (Ljava/lang/Throwable;)Ljava/lang/Throwable;
    //   3178: athrow
    //   3179: aload #20
    //   3181: iload #22
    //   3183: aload #20
    //   3185: iload #22
    //   3187: iconst_2
    //   3188: isub
    //   3189: iaload
    //   3190: bipush #17
    //   3192: iushr
    //   3193: aload #20
    //   3195: iload #22
    //   3197: iconst_2
    //   3198: isub
    //   3199: iaload
    //   3200: bipush #15
    //   3202: ishl
    //   3203: ior
    //   3204: aload #20
    //   3206: iload #22
    //   3208: iconst_2
    //   3209: isub
    //   3210: iaload
    //   3211: bipush #19
    //   3213: iushr
    //   3214: aload #20
    //   3216: iload #22
    //   3218: iconst_2
    //   3219: isub
    //   3220: iaload
    //   3221: bipush #13
    //   3223: ishl
    //   3224: ior
    //   3225: ixor
    //   3226: aload #20
    //   3228: iload #22
    //   3230: iconst_2
    //   3231: isub
    //   3232: iaload
    //   3233: bipush #10
    //   3235: iushr
    //   3236: ixor
    //   3237: aload #20
    //   3239: iload #22
    //   3241: bipush #7
    //   3243: isub
    //   3244: iaload
    //   3245: iadd
    //   3246: aload #20
    //   3248: iload #22
    //   3250: bipush #15
    //   3252: isub
    //   3253: iaload
    //   3254: bipush #7
    //   3256: iushr
    //   3257: aload #20
    //   3259: iload #22
    //   3261: bipush #15
    //   3263: isub
    //   3264: iaload
    //   3265: bipush #25
    //   3267: ishl
    //   3268: ior
    //   3269: aload #20
    //   3271: iload #22
    //   3273: bipush #15
    //   3275: isub
    //   3276: iaload
    //   3277: bipush #18
    //   3279: iushr
    //   3280: aload #20
    //   3282: iload #22
    //   3284: bipush #15
    //   3286: isub
    //   3287: iaload
    //   3288: bipush #14
    //   3290: ishl
    //   3291: ior
    //   3292: ixor
    //   3293: aload #20
    //   3295: iload #22
    //   3297: bipush #15
    //   3299: isub
    //   3300: iaload
    //   3301: iconst_3
    //   3302: iushr
    //   3303: ixor
    //   3304: iadd
    //   3305: aload #20
    //   3307: iload #22
    //   3309: bipush #16
    //   3311: isub
    //   3312: iaload
    //   3313: iadd
    //   3314: iastore
    //   3315: goto -> 3322
    //   3318: invokestatic a : (Ljava/lang/Throwable;)Ljava/lang/Throwable;
    //   3321: athrow
    //   3322: aload #21
    //   3324: bipush #7
    //   3326: iaload
    //   3327: aload #21
    //   3329: iconst_4
    //   3330: iaload
    //   3331: bipush #6
    //   3333: iushr
    //   3334: aload #21
    //   3336: iconst_4
    //   3337: iaload
    //   3338: bipush #26
    //   3340: ishl
    //   3341: ior
    //   3342: aload #21
    //   3344: iconst_4
    //   3345: iaload
    //   3346: bipush #11
    //   3348: iushr
    //   3349: aload #21
    //   3351: iconst_4
    //   3352: iaload
    //   3353: bipush #21
    //   3355: ishl
    //   3356: ior
    //   3357: ixor
    //   3358: aload #21
    //   3360: iconst_4
    //   3361: iaload
    //   3362: bipush #25
    //   3364: iushr
    //   3365: aload #21
    //   3367: iconst_4
    //   3368: iaload
    //   3369: bipush #7
    //   3371: ishl
    //   3372: ior
    //   3373: ixor
    //   3374: iadd
    //   3375: aload #21
    //   3377: bipush #6
    //   3379: iaload
    //   3380: aload #21
    //   3382: iconst_4
    //   3383: iaload
    //   3384: aload #21
    //   3386: iconst_5
    //   3387: iaload
    //   3388: aload #21
    //   3390: bipush #6
    //   3392: iaload
    //   3393: ixor
    //   3394: iand
    //   3395: ixor
    //   3396: iadd
    //   3397: aload #7
    //   3399: iload #22
    //   3401: iaload
    //   3402: iadd
    //   3403: aload #20
    //   3405: iload #22
    //   3407: iaload
    //   3408: iadd
    //   3409: istore #23
    //   3411: aload #21
    //   3413: iconst_0
    //   3414: iaload
    //   3415: iconst_2
    //   3416: iushr
    //   3417: aload #21
    //   3419: iconst_0
    //   3420: iaload
    //   3421: bipush #30
    //   3423: ishl
    //   3424: ior
    //   3425: aload #21
    //   3427: iconst_0
    //   3428: iaload
    //   3429: bipush #13
    //   3431: iushr
    //   3432: aload #21
    //   3434: iconst_0
    //   3435: iaload
    //   3436: bipush #19
    //   3438: ishl
    //   3439: ior
    //   3440: ixor
    //   3441: aload #21
    //   3443: iconst_0
    //   3444: iaload
    //   3445: bipush #22
    //   3447: iushr
    //   3448: aload #21
    //   3450: iconst_0
    //   3451: iaload
    //   3452: bipush #10
    //   3454: ishl
    //   3455: ior
    //   3456: ixor
    //   3457: aload #21
    //   3459: iconst_0
    //   3460: iaload
    //   3461: aload #21
    //   3463: iconst_1
    //   3464: iaload
    //   3465: iand
    //   3466: aload #21
    //   3468: iconst_2
    //   3469: iaload
    //   3470: aload #21
    //   3472: iconst_0
    //   3473: iaload
    //   3474: aload #21
    //   3476: iconst_1
    //   3477: iaload
    //   3478: ior
    //   3479: iand
    //   3480: ior
    //   3481: iadd
    //   3482: istore #24
    //   3484: aload #21
    //   3486: iconst_3
    //   3487: dup2
    //   3488: iaload
    //   3489: iload #23
    //   3491: iadd
    //   3492: iastore
    //   3493: aload #21
    //   3495: bipush #7
    //   3497: iload #23
    //   3499: iload #24
    //   3501: iadd
    //   3502: iastore
    //   3503: aload #21
    //   3505: bipush #7
    //   3507: iaload
    //   3508: istore #23
    //   3510: aload #21
    //   3512: bipush #7
    //   3514: aload #21
    //   3516: bipush #6
    //   3518: iaload
    //   3519: iastore
    //   3520: aload #21
    //   3522: bipush #6
    //   3524: aload #21
    //   3526: iconst_5
    //   3527: iaload
    //   3528: iastore
    //   3529: aload #21
    //   3531: iconst_5
    //   3532: aload #21
    //   3534: iconst_4
    //   3535: iaload
    //   3536: iastore
    //   3537: aload #21
    //   3539: iconst_4
    //   3540: aload #21
    //   3542: iconst_3
    //   3543: iaload
    //   3544: iastore
    //   3545: aload #21
    //   3547: iconst_3
    //   3548: aload #21
    //   3550: iconst_2
    //   3551: iaload
    //   3552: iastore
    //   3553: aload #21
    //   3555: iconst_2
    //   3556: aload #21
    //   3558: iconst_1
    //   3559: iaload
    //   3560: iastore
    //   3561: aload #21
    //   3563: iconst_1
    //   3564: aload #21
    //   3566: iconst_0
    //   3567: iaload
    //   3568: iastore
    //   3569: aload #21
    //   3571: iconst_0
    //   3572: iload #23
    //   3574: iastore
    //   3575: iinc #22, 1
    //   3578: iload_2
    //   3579: ifeq -> 3087
    //   3582: iconst_0
    //   3583: istore #22
    //   3585: iload #22
    //   3587: bipush #8
    //   3589: if_icmpge -> 3612
    //   3592: aload #9
    //   3594: iload #22
    //   3596: dup2
    //   3597: iaload
    //   3598: aload #21
    //   3600: iload #22
    //   3602: iaload
    //   3603: iadd
    //   3604: iastore
    //   3605: iinc #22, 1
    //   3608: iload_2
    //   3609: ifeq -> 3585
    //   3612: iload #14
    //   3614: iload #19
    //   3616: iadd
    //   3617: istore #14
    //   3619: iload #18
    //   3621: iload #19
    //   3623: isub
    //   3624: istore #18
    //   3626: iconst_0
    //   3627: istore #13
    //   3629: iload #18
    //   3631: bipush #64
    //   3633: if_icmplt -> 4243
    //   3636: iconst_0
    //   3637: istore #20
    //   3639: iload #20
    //   3641: bipush #64
    //   3643: if_icmpge -> 3666
    //   3646: aload #11
    //   3648: iload #20
    //   3650: aload #6
    //   3652: iload #14
    //   3654: iload #20
    //   3656: iadd
    //   3657: baload
    //   3658: bastore
    //   3659: iinc #20, 1
    //   3662: iload_2
    //   3663: ifeq -> 3639
    //   3666: bipush #64
    //   3668: newarray int
    //   3670: astore #20
    //   3672: bipush #8
    //   3674: newarray int
    //   3676: astore #21
    //   3678: iconst_0
    //   3679: istore #22
    //   3681: iload #22
    //   3683: bipush #8
    //   3685: if_icmpge -> 3705
    //   3688: aload #21
    //   3690: iload #22
    //   3692: aload #9
    //   3694: iload #22
    //   3696: iaload
    //   3697: iastore
    //   3698: iinc #22, 1
    //   3701: iload_2
    //   3702: ifeq -> 3681
    //   3705: iconst_0
    //   3706: istore #22
    //   3708: iload #22
    //   3710: bipush #64
    //   3712: if_icmpge -> 4203
    //   3715: iload #22
    //   3717: bipush #16
    //   3719: if_icmpge -> 3800
    //   3722: aload #20
    //   3724: iload #22
    //   3726: aload #11
    //   3728: iconst_4
    //   3729: iload #22
    //   3731: imul
    //   3732: baload
    //   3733: sipush #255
    //   3736: iand
    //   3737: bipush #24
    //   3739: ishl
    //   3740: aload #11
    //   3742: iconst_4
    //   3743: iload #22
    //   3745: imul
    //   3746: iconst_1
    //   3747: iadd
    //   3748: baload
    //   3749: sipush #255
    //   3752: iand
    //   3753: bipush #16
    //   3755: ishl
    //   3756: ior
    //   3757: aload #11
    //   3759: iconst_4
    //   3760: iload #22
    //   3762: imul
    //   3763: iconst_2
    //   3764: iadd
    //   3765: baload
    //   3766: sipush #255
    //   3769: iand
    //   3770: bipush #8
    //   3772: ishl
    //   3773: ior
    //   3774: aload #11
    //   3776: iconst_4
    //   3777: iload #22
    //   3779: imul
    //   3780: iconst_3
    //   3781: iadd
    //   3782: baload
    //   3783: sipush #255
    //   3786: iand
    //   3787: ior
    //   3788: iastore
    //   3789: iload_2
    //   3790: ifeq -> 3943
    //   3793: goto -> 3800
    //   3796: invokestatic a : (Ljava/lang/Throwable;)Ljava/lang/Throwable;
    //   3799: athrow
    //   3800: aload #20
    //   3802: iload #22
    //   3804: aload #20
    //   3806: iload #22
    //   3808: iconst_2
    //   3809: isub
    //   3810: iaload
    //   3811: bipush #17
    //   3813: iushr
    //   3814: aload #20
    //   3816: iload #22
    //   3818: iconst_2
    //   3819: isub
    //   3820: iaload
    //   3821: bipush #15
    //   3823: ishl
    //   3824: ior
    //   3825: aload #20
    //   3827: iload #22
    //   3829: iconst_2
    //   3830: isub
    //   3831: iaload
    //   3832: bipush #19
    //   3834: iushr
    //   3835: aload #20
    //   3837: iload #22
    //   3839: iconst_2
    //   3840: isub
    //   3841: iaload
    //   3842: bipush #13
    //   3844: ishl
    //   3845: ior
    //   3846: ixor
    //   3847: aload #20
    //   3849: iload #22
    //   3851: iconst_2
    //   3852: isub
    //   3853: iaload
    //   3854: bipush #10
    //   3856: iushr
    //   3857: ixor
    //   3858: aload #20
    //   3860: iload #22
    //   3862: bipush #7
    //   3864: isub
    //   3865: iaload
    //   3866: iadd
    //   3867: aload #20
    //   3869: iload #22
    //   3871: bipush #15
    //   3873: isub
    //   3874: iaload
    //   3875: bipush #7
    //   3877: iushr
    //   3878: aload #20
    //   3880: iload #22
    //   3882: bipush #15
    //   3884: isub
    //   3885: iaload
    //   3886: bipush #25
    //   3888: ishl
    //   3889: ior
    //   3890: aload #20
    //   3892: iload #22
    //   3894: bipush #15
    //   3896: isub
    //   3897: iaload
    //   3898: bipush #18
    //   3900: iushr
    //   3901: aload #20
    //   3903: iload #22
    //   3905: bipush #15
    //   3907: isub
    //   3908: iaload
    //   3909: bipush #14
    //   3911: ishl
    //   3912: ior
    //   3913: ixor
    //   3914: aload #20
    //   3916: iload #22
    //   3918: bipush #15
    //   3920: isub
    //   3921: iaload
    //   3922: iconst_3
    //   3923: iushr
    //   3924: ixor
    //   3925: iadd
    //   3926: aload #20
    //   3928: iload #22
    //   3930: bipush #16
    //   3932: isub
    //   3933: iaload
    //   3934: iadd
    //   3935: iastore
    //   3936: goto -> 3943
    //   3939: invokestatic a : (Ljava/lang/Throwable;)Ljava/lang/Throwable;
    //   3942: athrow
    //   3943: aload #21
    //   3945: bipush #7
    //   3947: iaload
    //   3948: aload #21
    //   3950: iconst_4
    //   3951: iaload
    //   3952: bipush #6
    //   3954: iushr
    //   3955: aload #21
    //   3957: iconst_4
    //   3958: iaload
    //   3959: bipush #26
    //   3961: ishl
    //   3962: ior
    //   3963: aload #21
    //   3965: iconst_4
    //   3966: iaload
    //   3967: bipush #11
    //   3969: iushr
    //   3970: aload #21
    //   3972: iconst_4
    //   3973: iaload
    //   3974: bipush #21
    //   3976: ishl
    //   3977: ior
    //   3978: ixor
    //   3979: aload #21
    //   3981: iconst_4
    //   3982: iaload
    //   3983: bipush #25
    //   3985: iushr
    //   3986: aload #21
    //   3988: iconst_4
    //   3989: iaload
    //   3990: bipush #7
    //   3992: ishl
    //   3993: ior
    //   3994: ixor
    //   3995: iadd
    //   3996: aload #21
    //   3998: bipush #6
    //   4000: iaload
    //   4001: aload #21
    //   4003: iconst_4
    //   4004: iaload
    //   4005: aload #21
    //   4007: iconst_5
    //   4008: iaload
    //   4009: aload #21
    //   4011: bipush #6
    //   4013: iaload
    //   4014: ixor
    //   4015: iand
    //   4016: ixor
    //   4017: iadd
    //   4018: aload #7
    //   4020: iload #22
    //   4022: iaload
    //   4023: iadd
    //   4024: aload #20
    //   4026: iload #22
    //   4028: iaload
    //   4029: iadd
    //   4030: istore #23
    //   4032: aload #21
    //   4034: iconst_0
    //   4035: iaload
    //   4036: iconst_2
    //   4037: iushr
    //   4038: aload #21
    //   4040: iconst_0
    //   4041: iaload
    //   4042: bipush #30
    //   4044: ishl
    //   4045: ior
    //   4046: aload #21
    //   4048: iconst_0
    //   4049: iaload
    //   4050: bipush #13
    //   4052: iushr
    //   4053: aload #21
    //   4055: iconst_0
    //   4056: iaload
    //   4057: bipush #19
    //   4059: ishl
    //   4060: ior
    //   4061: ixor
    //   4062: aload #21
    //   4064: iconst_0
    //   4065: iaload
    //   4066: bipush #22
    //   4068: iushr
    //   4069: aload #21
    //   4071: iconst_0
    //   4072: iaload
    //   4073: bipush #10
    //   4075: ishl
    //   4076: ior
    //   4077: ixor
    //   4078: aload #21
    //   4080: iconst_0
    //   4081: iaload
    //   4082: aload #21
    //   4084: iconst_1
    //   4085: iaload
    //   4086: iand
    //   4087: aload #21
    //   4089: iconst_2
    //   4090: iaload
    //   4091: aload #21
    //   4093: iconst_0
    //   4094: iaload
    //   4095: aload #21
    //   4097: iconst_1
    //   4098: iaload
    //   4099: ior
    //   4100: iand
    //   4101: ior
    //   4102: iadd
    //   4103: istore #24
    //   4105: aload #21
    //   4107: iconst_3
    //   4108: dup2
    //   4109: iaload
    //   4110: iload #23
    //   4112: iadd
    //   4113: iastore
    //   4114: aload #21
    //   4116: bipush #7
    //   4118: iload #23
    //   4120: iload #24
    //   4122: iadd
    //   4123: iastore
    //   4124: aload #21
    //   4126: bipush #7
    //   4128: iaload
    //   4129: istore #23
    //   4131: aload #21
    //   4133: bipush #7
    //   4135: aload #21
    //   4137: bipush #6
    //   4139: iaload
    //   4140: iastore
    //   4141: aload #21
    //   4143: bipush #6
    //   4145: aload #21
    //   4147: iconst_5
    //   4148: iaload
    //   4149: iastore
    //   4150: aload #21
    //   4152: iconst_5
    //   4153: aload #21
    //   4155: iconst_4
    //   4156: iaload
    //   4157: iastore
    //   4158: aload #21
    //   4160: iconst_4
    //   4161: aload #21
    //   4163: iconst_3
    //   4164: iaload
    //   4165: iastore
    //   4166: aload #21
    //   4168: iconst_3
    //   4169: aload #21
    //   4171: iconst_2
    //   4172: iaload
    //   4173: iastore
    //   4174: aload #21
    //   4176: iconst_2
    //   4177: aload #21
    //   4179: iconst_1
    //   4180: iaload
    //   4181: iastore
    //   4182: aload #21
    //   4184: iconst_1
    //   4185: aload #21
    //   4187: iconst_0
    //   4188: iaload
    //   4189: iastore
    //   4190: aload #21
    //   4192: iconst_0
    //   4193: iload #23
    //   4195: iastore
    //   4196: iinc #22, 1
    //   4199: iload_2
    //   4200: ifeq -> 3708
    //   4203: iconst_0
    //   4204: istore #22
    //   4206: iload #22
    //   4208: bipush #8
    //   4210: if_icmpge -> 4233
    //   4213: aload #9
    //   4215: iload #22
    //   4217: dup2
    //   4218: iaload
    //   4219: aload #21
    //   4221: iload #22
    //   4223: iaload
    //   4224: iadd
    //   4225: iastore
    //   4226: iinc #22, 1
    //   4229: iload_2
    //   4230: ifeq -> 4206
    //   4233: iinc #14, 64
    //   4236: iinc #18, -64
    //   4239: iload_2
    //   4240: ifeq -> 3629
    //   4243: iload #18
    //   4245: ifle -> 4281
    //   4248: iconst_0
    //   4249: istore #20
    //   4251: iload #20
    //   4253: iload #18
    //   4255: if_icmpge -> 4281
    //   4258: aload #10
    //   4260: iload #13
    //   4262: iload #20
    //   4264: iadd
    //   4265: aload #6
    //   4267: iload #14
    //   4269: iload #20
    //   4271: iadd
    //   4272: baload
    //   4273: bastore
    //   4274: iinc #20, 1
    //   4277: iload_2
    //   4278: ifeq -> 4251
    //   4281: bipush #8
    //   4283: newarray byte
    //   4285: astore #20
    //   4287: aload #20
    //   4289: iconst_0
    //   4290: iload #15
    //   4292: bipush #24
    //   4294: iushr
    //   4295: i2b
    //   4296: bastore
    //   4297: aload #20
    //   4299: iconst_1
    //   4300: iload #15
    //   4302: bipush #16
    //   4304: iushr
    //   4305: i2b
    //   4306: bastore
    //   4307: aload #20
    //   4309: iconst_2
    //   4310: iload #15
    //   4312: bipush #8
    //   4314: iushr
    //   4315: i2b
    //   4316: bastore
    //   4317: aload #20
    //   4319: iconst_3
    //   4320: iload #15
    //   4322: i2b
    //   4323: bastore
    //   4324: aload #20
    //   4326: iconst_4
    //   4327: iload #16
    //   4329: bipush #24
    //   4331: iushr
    //   4332: i2b
    //   4333: bastore
    //   4334: aload #20
    //   4336: iconst_5
    //   4337: iload #16
    //   4339: bipush #16
    //   4341: iushr
    //   4342: i2b
    //   4343: bastore
    //   4344: aload #20
    //   4346: bipush #6
    //   4348: iload #16
    //   4350: bipush #8
    //   4352: iushr
    //   4353: i2b
    //   4354: bastore
    //   4355: aload #20
    //   4357: bipush #7
    //   4359: iload #16
    //   4361: i2b
    //   4362: bastore
    //   4363: bipush #8
    //   4365: istore #12
    //   4367: aload #8
    //   4369: iconst_0
    //   4370: iaload
    //   4371: bipush #63
    //   4373: iand
    //   4374: istore #13
    //   4376: bipush #64
    //   4378: iload #13
    //   4380: isub
    //   4381: istore #19
    //   4383: aload #8
    //   4385: iconst_0
    //   4386: dup2
    //   4387: iaload
    //   4388: iload #12
    //   4390: iadd
    //   4391: iastore
    //   4392: aload #8
    //   4394: iconst_0
    //   4395: dup2
    //   4396: iaload
    //   4397: iconst_m1
    //   4398: iand
    //   4399: iastore
    //   4400: aload #8
    //   4402: iconst_0
    //   4403: iaload
    //   4404: iload #12
    //   4406: if_icmpge -> 4424
    //   4409: aload #8
    //   4411: iconst_1
    //   4412: dup2
    //   4413: iaload
    //   4414: iconst_1
    //   4415: iadd
    //   4416: iastore
    //   4417: goto -> 4424
    //   4420: invokestatic a : (Ljava/lang/Throwable;)Ljava/lang/Throwable;
    //   4423: athrow
    //   4424: iload #13
    //   4426: ifle -> 5040
    //   4429: iload #12
    //   4431: iload #19
    //   4433: if_icmplt -> 5040
    //   4436: goto -> 4443
    //   4439: invokestatic a : (Ljava/lang/Throwable;)Ljava/lang/Throwable;
    //   4442: athrow
    //   4443: iconst_0
    //   4444: istore #21
    //   4446: iload #21
    //   4448: iload #19
    //   4450: if_icmpge -> 4473
    //   4453: aload #10
    //   4455: iload #13
    //   4457: iload #21
    //   4459: iadd
    //   4460: aload #20
    //   4462: iload #21
    //   4464: baload
    //   4465: bastore
    //   4466: iinc #21, 1
    //   4469: iload_2
    //   4470: ifeq -> 4446
    //   4473: bipush #64
    //   4475: newarray int
    //   4477: astore #21
    //   4479: bipush #8
    //   4481: newarray int
    //   4483: astore #22
    //   4485: iconst_0
    //   4486: istore #23
    //   4488: iload #23
    //   4490: bipush #8
    //   4492: if_icmpge -> 4512
    //   4495: aload #22
    //   4497: iload #23
    //   4499: aload #9
    //   4501: iload #23
    //   4503: iaload
    //   4504: iastore
    //   4505: iinc #23, 1
    //   4508: iload_2
    //   4509: ifeq -> 4488
    //   4512: iconst_0
    //   4513: istore #23
    //   4515: iload #23
    //   4517: bipush #64
    //   4519: if_icmpge -> 5010
    //   4522: iload #23
    //   4524: bipush #16
    //   4526: if_icmpge -> 4607
    //   4529: aload #21
    //   4531: iload #23
    //   4533: aload #10
    //   4535: iconst_4
    //   4536: iload #23
    //   4538: imul
    //   4539: baload
    //   4540: sipush #255
    //   4543: iand
    //   4544: bipush #24
    //   4546: ishl
    //   4547: aload #10
    //   4549: iconst_4
    //   4550: iload #23
    //   4552: imul
    //   4553: iconst_1
    //   4554: iadd
    //   4555: baload
    //   4556: sipush #255
    //   4559: iand
    //   4560: bipush #16
    //   4562: ishl
    //   4563: ior
    //   4564: aload #10
    //   4566: iconst_4
    //   4567: iload #23
    //   4569: imul
    //   4570: iconst_2
    //   4571: iadd
    //   4572: baload
    //   4573: sipush #255
    //   4576: iand
    //   4577: bipush #8
    //   4579: ishl
    //   4580: ior
    //   4581: aload #10
    //   4583: iconst_4
    //   4584: iload #23
    //   4586: imul
    //   4587: iconst_3
    //   4588: iadd
    //   4589: baload
    //   4590: sipush #255
    //   4593: iand
    //   4594: ior
    //   4595: iastore
    //   4596: iload_2
    //   4597: ifeq -> 4750
    //   4600: goto -> 4607
    //   4603: invokestatic a : (Ljava/lang/Throwable;)Ljava/lang/Throwable;
    //   4606: athrow
    //   4607: aload #21
    //   4609: iload #23
    //   4611: aload #21
    //   4613: iload #23
    //   4615: iconst_2
    //   4616: isub
    //   4617: iaload
    //   4618: bipush #17
    //   4620: iushr
    //   4621: aload #21
    //   4623: iload #23
    //   4625: iconst_2
    //   4626: isub
    //   4627: iaload
    //   4628: bipush #15
    //   4630: ishl
    //   4631: ior
    //   4632: aload #21
    //   4634: iload #23
    //   4636: iconst_2
    //   4637: isub
    //   4638: iaload
    //   4639: bipush #19
    //   4641: iushr
    //   4642: aload #21
    //   4644: iload #23
    //   4646: iconst_2
    //   4647: isub
    //   4648: iaload
    //   4649: bipush #13
    //   4651: ishl
    //   4652: ior
    //   4653: ixor
    //   4654: aload #21
    //   4656: iload #23
    //   4658: iconst_2
    //   4659: isub
    //   4660: iaload
    //   4661: bipush #10
    //   4663: iushr
    //   4664: ixor
    //   4665: aload #21
    //   4667: iload #23
    //   4669: bipush #7
    //   4671: isub
    //   4672: iaload
    //   4673: iadd
    //   4674: aload #21
    //   4676: iload #23
    //   4678: bipush #15
    //   4680: isub
    //   4681: iaload
    //   4682: bipush #7
    //   4684: iushr
    //   4685: aload #21
    //   4687: iload #23
    //   4689: bipush #15
    //   4691: isub
    //   4692: iaload
    //   4693: bipush #25
    //   4695: ishl
    //   4696: ior
    //   4697: aload #21
    //   4699: iload #23
    //   4701: bipush #15
    //   4703: isub
    //   4704: iaload
    //   4705: bipush #18
    //   4707: iushr
    //   4708: aload #21
    //   4710: iload #23
    //   4712: bipush #15
    //   4714: isub
    //   4715: iaload
    //   4716: bipush #14
    //   4718: ishl
    //   4719: ior
    //   4720: ixor
    //   4721: aload #21
    //   4723: iload #23
    //   4725: bipush #15
    //   4727: isub
    //   4728: iaload
    //   4729: iconst_3
    //   4730: iushr
    //   4731: ixor
    //   4732: iadd
    //   4733: aload #21
    //   4735: iload #23
    //   4737: bipush #16
    //   4739: isub
    //   4740: iaload
    //   4741: iadd
    //   4742: iastore
    //   4743: goto -> 4750
    //   4746: invokestatic a : (Ljava/lang/Throwable;)Ljava/lang/Throwable;
    //   4749: athrow
    //   4750: aload #22
    //   4752: bipush #7
    //   4754: iaload
    //   4755: aload #22
    //   4757: iconst_4
    //   4758: iaload
    //   4759: bipush #6
    //   4761: iushr
    //   4762: aload #22
    //   4764: iconst_4
    //   4765: iaload
    //   4766: bipush #26
    //   4768: ishl
    //   4769: ior
    //   4770: aload #22
    //   4772: iconst_4
    //   4773: iaload
    //   4774: bipush #11
    //   4776: iushr
    //   4777: aload #22
    //   4779: iconst_4
    //   4780: iaload
    //   4781: bipush #21
    //   4783: ishl
    //   4784: ior
    //   4785: ixor
    //   4786: aload #22
    //   4788: iconst_4
    //   4789: iaload
    //   4790: bipush #25
    //   4792: iushr
    //   4793: aload #22
    //   4795: iconst_4
    //   4796: iaload
    //   4797: bipush #7
    //   4799: ishl
    //   4800: ior
    //   4801: ixor
    //   4802: iadd
    //   4803: aload #22
    //   4805: bipush #6
    //   4807: iaload
    //   4808: aload #22
    //   4810: iconst_4
    //   4811: iaload
    //   4812: aload #22
    //   4814: iconst_5
    //   4815: iaload
    //   4816: aload #22
    //   4818: bipush #6
    //   4820: iaload
    //   4821: ixor
    //   4822: iand
    //   4823: ixor
    //   4824: iadd
    //   4825: aload #7
    //   4827: iload #23
    //   4829: iaload
    //   4830: iadd
    //   4831: aload #21
    //   4833: iload #23
    //   4835: iaload
    //   4836: iadd
    //   4837: istore #24
    //   4839: aload #22
    //   4841: iconst_0
    //   4842: iaload
    //   4843: iconst_2
    //   4844: iushr
    //   4845: aload #22
    //   4847: iconst_0
    //   4848: iaload
    //   4849: bipush #30
    //   4851: ishl
    //   4852: ior
    //   4853: aload #22
    //   4855: iconst_0
    //   4856: iaload
    //   4857: bipush #13
    //   4859: iushr
    //   4860: aload #22
    //   4862: iconst_0
    //   4863: iaload
    //   4864: bipush #19
    //   4866: ishl
    //   4867: ior
    //   4868: ixor
    //   4869: aload #22
    //   4871: iconst_0
    //   4872: iaload
    //   4873: bipush #22
    //   4875: iushr
    //   4876: aload #22
    //   4878: iconst_0
    //   4879: iaload
    //   4880: bipush #10
    //   4882: ishl
    //   4883: ior
    //   4884: ixor
    //   4885: aload #22
    //   4887: iconst_0
    //   4888: iaload
    //   4889: aload #22
    //   4891: iconst_1
    //   4892: iaload
    //   4893: iand
    //   4894: aload #22
    //   4896: iconst_2
    //   4897: iaload
    //   4898: aload #22
    //   4900: iconst_0
    //   4901: iaload
    //   4902: aload #22
    //   4904: iconst_1
    //   4905: iaload
    //   4906: ior
    //   4907: iand
    //   4908: ior
    //   4909: iadd
    //   4910: istore #25
    //   4912: aload #22
    //   4914: iconst_3
    //   4915: dup2
    //   4916: iaload
    //   4917: iload #24
    //   4919: iadd
    //   4920: iastore
    //   4921: aload #22
    //   4923: bipush #7
    //   4925: iload #24
    //   4927: iload #25
    //   4929: iadd
    //   4930: iastore
    //   4931: aload #22
    //   4933: bipush #7
    //   4935: iaload
    //   4936: istore #24
    //   4938: aload #22
    //   4940: bipush #7
    //   4942: aload #22
    //   4944: bipush #6
    //   4946: iaload
    //   4947: iastore
    //   4948: aload #22
    //   4950: bipush #6
    //   4952: aload #22
    //   4954: iconst_5
    //   4955: iaload
    //   4956: iastore
    //   4957: aload #22
    //   4959: iconst_5
    //   4960: aload #22
    //   4962: iconst_4
    //   4963: iaload
    //   4964: iastore
    //   4965: aload #22
    //   4967: iconst_4
    //   4968: aload #22
    //   4970: iconst_3
    //   4971: iaload
    //   4972: iastore
    //   4973: aload #22
    //   4975: iconst_3
    //   4976: aload #22
    //   4978: iconst_2
    //   4979: iaload
    //   4980: iastore
    //   4981: aload #22
    //   4983: iconst_2
    //   4984: aload #22
    //   4986: iconst_1
    //   4987: iaload
    //   4988: iastore
    //   4989: aload #22
    //   4991: iconst_1
    //   4992: aload #22
    //   4994: iconst_0
    //   4995: iaload
    //   4996: iastore
    //   4997: aload #22
    //   4999: iconst_0
    //   5000: iload #24
    //   5002: iastore
    //   5003: iinc #23, 1
    //   5006: iload_2
    //   5007: ifeq -> 4515
    //   5010: iconst_0
    //   5011: istore #23
    //   5013: iload #23
    //   5015: bipush #8
    //   5017: if_icmpge -> 5040
    //   5020: aload #9
    //   5022: iload #23
    //   5024: dup2
    //   5025: iaload
    //   5026: aload #22
    //   5028: iload #23
    //   5030: iaload
    //   5031: iadd
    //   5032: iastore
    //   5033: iinc #23, 1
    //   5036: iload_2
    //   5037: ifeq -> 5013
    //   5040: bipush #32
    //   5042: newarray byte
    //   5044: astore #5
    //   5046: sipush #-30324
    //   5049: aload #5
    //   5051: iconst_0
    //   5052: aload #9
    //   5054: iconst_0
    //   5055: iaload
    //   5056: bipush #24
    //   5058: iushr
    //   5059: i2b
    //   5060: bastore
    //   5061: sipush #26214
    //   5064: aload #5
    //   5066: iconst_1
    //   5067: aload #9
    //   5069: iconst_0
    //   5070: iaload
    //   5071: bipush #16
    //   5073: iushr
    //   5074: i2b
    //   5075: bastore
    //   5076: aload #5
    //   5078: iconst_2
    //   5079: aload #9
    //   5081: iconst_0
    //   5082: iaload
    //   5083: bipush #8
    //   5085: iushr
    //   5086: i2b
    //   5087: bastore
    //   5088: aload #5
    //   5090: iconst_3
    //   5091: aload #9
    //   5093: iconst_0
    //   5094: iaload
    //   5095: i2b
    //   5096: bastore
    //   5097: aload #5
    //   5099: iconst_4
    //   5100: aload #9
    //   5102: iconst_1
    //   5103: iaload
    //   5104: bipush #24
    //   5106: iushr
    //   5107: i2b
    //   5108: bastore
    //   5109: aload #5
    //   5111: iconst_5
    //   5112: aload #9
    //   5114: iconst_1
    //   5115: iaload
    //   5116: bipush #16
    //   5118: iushr
    //   5119: i2b
    //   5120: bastore
    //   5121: aload #5
    //   5123: bipush #6
    //   5125: aload #9
    //   5127: iconst_1
    //   5128: iaload
    //   5129: bipush #8
    //   5131: iushr
    //   5132: i2b
    //   5133: bastore
    //   5134: aload #5
    //   5136: bipush #7
    //   5138: aload #9
    //   5140: iconst_1
    //   5141: iaload
    //   5142: i2b
    //   5143: bastore
    //   5144: aload #5
    //   5146: bipush #8
    //   5148: aload #9
    //   5150: iconst_2
    //   5151: iaload
    //   5152: bipush #24
    //   5154: iushr
    //   5155: i2b
    //   5156: bastore
    //   5157: aload #5
    //   5159: bipush #9
    //   5161: aload #9
    //   5163: iconst_2
    //   5164: iaload
    //   5165: bipush #16
    //   5167: iushr
    //   5168: i2b
    //   5169: bastore
    //   5170: aload #5
    //   5172: bipush #10
    //   5174: aload #9
    //   5176: iconst_2
    //   5177: iaload
    //   5178: bipush #8
    //   5180: iushr
    //   5181: i2b
    //   5182: bastore
    //   5183: aload #5
    //   5185: bipush #11
    //   5187: aload #9
    //   5189: iconst_2
    //   5190: iaload
    //   5191: i2b
    //   5192: bastore
    //   5193: aload #5
    //   5195: bipush #12
    //   5197: aload #9
    //   5199: iconst_3
    //   5200: iaload
    //   5201: bipush #24
    //   5203: iushr
    //   5204: i2b
    //   5205: bastore
    //   5206: aload #5
    //   5208: bipush #13
    //   5210: aload #9
    //   5212: iconst_3
    //   5213: iaload
    //   5214: bipush #16
    //   5216: iushr
    //   5217: i2b
    //   5218: bastore
    //   5219: aload #5
    //   5221: bipush #14
    //   5223: aload #9
    //   5225: iconst_3
    //   5226: iaload
    //   5227: bipush #8
    //   5229: iushr
    //   5230: i2b
    //   5231: bastore
    //   5232: aload #5
    //   5234: bipush #15
    //   5236: aload #9
    //   5238: iconst_3
    //   5239: iaload
    //   5240: i2b
    //   5241: bastore
    //   5242: aload #5
    //   5244: bipush #16
    //   5246: aload #9
    //   5248: iconst_4
    //   5249: iaload
    //   5250: bipush #24
    //   5252: iushr
    //   5253: i2b
    //   5254: bastore
    //   5255: aload #5
    //   5257: bipush #17
    //   5259: aload #9
    //   5261: iconst_4
    //   5262: iaload
    //   5263: bipush #16
    //   5265: iushr
    //   5266: i2b
    //   5267: bastore
    //   5268: aload #5
    //   5270: bipush #18
    //   5272: aload #9
    //   5274: iconst_4
    //   5275: iaload
    //   5276: bipush #8
    //   5278: iushr
    //   5279: i2b
    //   5280: bastore
    //   5281: aload #5
    //   5283: bipush #19
    //   5285: aload #9
    //   5287: iconst_4
    //   5288: iaload
    //   5289: i2b
    //   5290: bastore
    //   5291: aload #5
    //   5293: bipush #20
    //   5295: aload #9
    //   5297: iconst_5
    //   5298: iaload
    //   5299: bipush #24
    //   5301: iushr
    //   5302: i2b
    //   5303: bastore
    //   5304: aload #5
    //   5306: bipush #21
    //   5308: aload #9
    //   5310: iconst_5
    //   5311: iaload
    //   5312: bipush #16
    //   5314: iushr
    //   5315: i2b
    //   5316: bastore
    //   5317: aload #5
    //   5319: bipush #22
    //   5321: aload #9
    //   5323: iconst_5
    //   5324: iaload
    //   5325: bipush #8
    //   5327: iushr
    //   5328: i2b
    //   5329: bastore
    //   5330: aload #5
    //   5332: bipush #23
    //   5334: aload #9
    //   5336: iconst_5
    //   5337: iaload
    //   5338: i2b
    //   5339: bastore
    //   5340: aload #5
    //   5342: bipush #24
    //   5344: aload #9
    //   5346: bipush #6
    //   5348: iaload
    //   5349: bipush #24
    //   5351: iushr
    //   5352: i2b
    //   5353: bastore
    //   5354: aload #5
    //   5356: bipush #25
    //   5358: aload #9
    //   5360: bipush #6
    //   5362: iaload
    //   5363: bipush #16
    //   5365: iushr
    //   5366: i2b
    //   5367: bastore
    //   5368: aload #5
    //   5370: bipush #26
    //   5372: aload #9
    //   5374: bipush #6
    //   5376: iaload
    //   5377: bipush #8
    //   5379: iushr
    //   5380: i2b
    //   5381: bastore
    //   5382: aload #5
    //   5384: bipush #27
    //   5386: aload #9
    //   5388: bipush #6
    //   5390: iaload
    //   5391: i2b
    //   5392: bastore
    //   5393: aload #5
    //   5395: bipush #28
    //   5397: aload #9
    //   5399: bipush #7
    //   5401: iaload
    //   5402: bipush #24
    //   5404: iushr
    //   5405: i2b
    //   5406: bastore
    //   5407: aload #5
    //   5409: bipush #29
    //   5411: aload #9
    //   5413: bipush #7
    //   5415: iaload
    //   5416: bipush #16
    //   5418: iushr
    //   5419: i2b
    //   5420: bastore
    //   5421: aload #5
    //   5423: bipush #30
    //   5425: aload #9
    //   5427: bipush #7
    //   5429: iaload
    //   5430: bipush #8
    //   5432: iushr
    //   5433: i2b
    //   5434: bastore
    //   5435: aload #5
    //   5437: bipush #31
    //   5439: aload #9
    //   5441: bipush #7
    //   5443: iaload
    //   5444: i2b
    //   5445: bastore
    //   5446: new java/math/BigInteger
    //   5449: dup
    //   5450: aload #5
    //   5452: invokespecial <init> : ([B)V
    //   5455: invokevirtual abs : ()Ljava/math/BigInteger;
    //   5458: putstatic burp/Zza3.Zb : Ljava/lang/Object;
    //   5461: invokestatic a : (II)Ljava/lang/String;
    //   5464: iconst_1
    //   5465: ldc burp/Zx4y
    //   5467: invokevirtual getClassLoader : ()Ljava/lang/ClassLoader;
    //   5470: invokestatic forName : (Ljava/lang/String;ZLjava/lang/ClassLoader;)Ljava/lang/Class;
    //   5473: invokevirtual getDeclaredFields : ()[Ljava/lang/reflect/Field;
    //   5476: astore #4
    //   5478: aload #4
    //   5480: arraylength
    //   5481: istore #5
    //   5483: iconst_0
    //   5484: istore #6
    //   5486: iload #6
    //   5488: iload #5
    //   5490: if_icmpge -> 5628
    //   5493: aload #4
    //   5495: iload #6
    //   5497: aaload
    //   5498: astore #7
    //   5500: aload #7
    //   5502: invokevirtual getModifiers : ()I
    //   5505: invokestatic isStatic : (I)Z
    //   5508: ifne -> 5518
    //   5511: goto -> 5621
    //   5514: invokestatic a : (Ljava/lang/Throwable;)Ljava/lang/Throwable;
    //   5517: athrow
    //   5518: aload #7
    //   5520: invokevirtual getType : ()Ljava/lang/Class;
    //   5523: astore #8
    //   5525: aload #8
    //   5527: ifnull -> 5608
    //   5530: aload #8
    //   5532: invokevirtual isPrimitive : ()Z
    //   5535: ifne -> 5608
    //   5538: goto -> 5545
    //   5541: invokestatic a : (Ljava/lang/Throwable;)Ljava/lang/Throwable;
    //   5544: athrow
    //   5545: aload #8
    //   5547: invokevirtual getPackage : ()Ljava/lang/Package;
    //   5550: ifnull -> 5608
    //   5553: goto -> 5560
    //   5556: invokestatic a : (Ljava/lang/Throwable;)Ljava/lang/Throwable;
    //   5559: athrow
    //   5560: aload #8
    //   5562: invokevirtual getPackage : ()Ljava/lang/Package;
    //   5565: invokevirtual getName : ()Ljava/lang/String;
    //   5568: ifnull -> 5608
    //   5571: goto -> 5578
    //   5574: invokestatic a : (Ljava/lang/Throwable;)Ljava/lang/Throwable;
    //   5577: athrow
    //   5578: aload #8
    //   5580: invokevirtual getPackage : ()Ljava/lang/Package;
    //   5583: invokevirtual getName : ()Ljava/lang/String;
    //   5586: sipush #-30336
    //   5589: sipush #5102
    //   5592: invokestatic a : (II)Ljava/lang/String;
    //   5595: invokevirtual startsWith : (Ljava/lang/String;)Z
    //   5598: ifne -> 5608
    //   5601: goto -> 5608
    //   5604: invokestatic a : (Ljava/lang/Throwable;)Ljava/lang/Throwable;
    //   5607: athrow
    //   5608: aload #7
    //   5610: iconst_1
    //   5611: invokevirtual setAccessible : (Z)V
    //   5614: aload #7
    //   5616: aconst_null
    //   5617: invokevirtual get : (Ljava/lang/Object;)Ljava/lang/Object;
    //   5620: pop
    //   5621: iinc #6, 1
    //   5624: iload_2
    //   5625: ifeq -> 5486
    //   5628: sipush #-30328
    //   5631: sipush #-2583
    //   5634: invokestatic a : (II)Ljava/lang/String;
    //   5637: invokestatic forName : (Ljava/lang/String;)Ljava/lang/Class;
    //   5640: invokevirtual getDeclaredMethods : ()[Ljava/lang/reflect/Method;
    //   5643: astore #4
    //   5645: aload #4
    //   5647: arraylength
    //   5648: istore #5
    //   5650: iconst_0
    //   5651: istore #6
    //   5653: iload #6
    //   5655: iload #5
    //   5657: if_icmpge -> 5790
    //   5660: aload #4
    //   5662: iload #6
    //   5664: aaload
    //   5665: astore #7
    //   5667: aload #7
    //   5669: invokevirtual getParameterTypes : ()[Ljava/lang/Class;
    //   5672: pop
    //   5673: aload #7
    //   5675: invokevirtual getModifiers : ()I
    //   5678: invokestatic isStatic : (I)Z
    //   5681: ifeq -> 5776
    //   5684: aload #7
    //   5686: invokevirtual getParameterTypes : ()[Ljava/lang/Class;
    //   5689: arraylength
    //   5690: iconst_2
    //   5691: if_icmpne -> 5776
    //   5694: goto -> 5701
    //   5697: invokestatic a : (Ljava/lang/Throwable;)Ljava/lang/Throwable;
    //   5700: athrow
    //   5701: aload #7
    //   5703: invokevirtual getReturnType : ()Ljava/lang/Class;
    //   5706: getstatic java/lang/Void.TYPE : Ljava/lang/Class;
    //   5709: invokevirtual equals : (Ljava/lang/Object;)Z
    //   5712: ifeq -> 5776
    //   5715: goto -> 5722
    //   5718: invokestatic a : (Ljava/lang/Throwable;)Ljava/lang/Throwable;
    //   5721: athrow
    //   5722: aload #7
    //   5724: iconst_1
    //   5725: invokevirtual setAccessible : (Z)V
    //   5728: aload #7
    //   5730: aconst_null
    //   5731: iconst_2
    //   5732: anewarray java/lang/Object
    //   5735: dup
    //   5736: iconst_0
    //   5737: aload_0
    //   5738: aastore
    //   5739: dup
    //   5740: iconst_1
    //   5741: aload_1
    //   5742: ifnonnull -> 5760
    //   5745: goto -> 5752
    //   5748: invokestatic a : (Ljava/lang/Throwable;)Ljava/lang/Throwable;
    //   5751: athrow
    //   5752: aload_1
    //   5753: goto -> 5767
    //   5756: invokestatic a : (Ljava/lang/Throwable;)Ljava/lang/Throwable;
    //   5759: athrow
    //   5760: aload_1
    //   5761: checkcast [B
    //   5764: invokevirtual clone : ()Ljava/lang/Object;
    //   5767: aastore
    //   5768: invokevirtual invoke : (Ljava/lang/Object;[Ljava/lang/Object;)Ljava/lang/Object;
    //   5771: pop
    //   5772: iload_2
    //   5773: ifeq -> 5790
    //   5776: iinc #6, 1
    //   5779: iload_2
    //   5780: ifeq -> 5653
    //   5783: goto -> 5790
    //   5786: invokestatic a : (Ljava/lang/Throwable;)Ljava/lang/Throwable;
    //   5789: athrow
    //   5790: new java/io/ByteArrayOutputStream
    //   5793: dup
    //   5794: invokespecial <init> : ()V
    //   5797: astore #4
    //   5799: sipush #-30335
    //   5802: aload #4
    //   5804: sipush #202
    //   5807: invokevirtual write : (I)V
    //   5810: sipush #5447
    //   5813: aload #4
    //   5815: sipush #254
    //   5818: invokevirtual write : (I)V
    //   5821: aload #4
    //   5823: sipush #186
    //   5826: invokevirtual write : (I)V
    //   5829: aload #4
    //   5831: sipush #190
    //   5834: invokevirtual write : (I)V
    //   5837: aload #4
    //   5839: iconst_0
    //   5840: invokevirtual write : (I)V
    //   5843: aload #4
    //   5845: iconst_1
    //   5846: invokevirtual write : (I)V
    //   5849: aload #4
    //   5851: iconst_0
    //   5852: invokevirtual write : (I)V
    //   5855: aload #4
    //   5857: bipush #50
    //   5859: invokevirtual write : (I)V
    //   5862: aload #4
    //   5864: getstatic burp/Zzh1.Zf : Ljava/lang/Object;
    //   5867: checkcast java/math/BigInteger
    //   5870: invokevirtual toByteArray : ()[B
    //   5873: invokevirtual write : ([B)V
    //   5876: aload #4
    //   5878: getstatic burp/Zz75.ZX : Ljava/lang/Object;
    //   5881: checkcast java/math/BigInteger
    //   5884: invokevirtual toByteArray : ()[B
    //   5887: invokevirtual write : ([B)V
    //   5890: aload #4
    //   5892: getstatic burp/Zk7o.ZO : Ljava/lang/Object;
    //   5895: checkcast java/math/BigInteger
    //   5898: invokevirtual toByteArray : ()[B
    //   5901: invokevirtual write : ([B)V
    //   5904: aload #4
    //   5906: invokevirtual toByteArray : ()[B
    //   5909: astore #5
    //   5911: aconst_null
    //   5912: astore #6
    //   5914: invokestatic a : (II)Ljava/lang/String;
    //   5917: invokestatic forName : (Ljava/lang/String;)Ljava/lang/Class;
    //   5920: invokevirtual getDeclaredMethods : ()[Ljava/lang/reflect/Method;
    //   5923: astore #7
    //   5925: aload #7
    //   5927: arraylength
    //   5928: istore #8
    //   5930: iconst_0
    //   5931: istore #9
    //   5933: iload #9
    //   5935: iload #8
    //   5937: if_icmpge -> 6065
    //   5940: aload #7
    //   5942: iload #9
    //   5944: aaload
    //   5945: astore #10
    //   5947: aload #10
    //   5949: invokevirtual getName : ()Ljava/lang/String;
    //   5952: sipush #-30333
    //   5955: sipush #30977
    //   5958: invokestatic a : (II)Ljava/lang/String;
    //   5961: invokevirtual equals : (Ljava/lang/Object;)Z
    //   5964: ifeq -> 6058
    //   5967: aload #10
    //   5969: invokevirtual getParameterTypes : ()[Ljava/lang/Class;
    //   5972: astore #11
    //   5974: aload #11
    //   5976: arraylength
    //   5977: iconst_4
    //   5978: if_icmpeq -> 5988
    //   5981: goto -> 6058
    //   5984: invokestatic a : (Ljava/lang/Throwable;)Ljava/lang/Throwable;
    //   5987: athrow
    //   5988: aload #11
    //   5990: iconst_0
    //   5991: aaload
    //   5992: ldc java/lang/String
    //   5994: if_acmpeq -> 6004
    //   5997: goto -> 6058
    //   6000: invokestatic a : (Ljava/lang/Throwable;)Ljava/lang/Throwable;
    //   6003: athrow
    //   6004: aload #11
    //   6006: iconst_1
    //   6007: aaload
    //   6008: ldc [B
    //   6010: if_acmpeq -> 6020
    //   6013: goto -> 6058
    //   6016: invokestatic a : (Ljava/lang/Throwable;)Ljava/lang/Throwable;
    //   6019: athrow
    //   6020: aload #11
    //   6022: iconst_2
    //   6023: aaload
    //   6024: getstatic java/lang/Integer.TYPE : Ljava/lang/Class;
    //   6027: if_acmpeq -> 6037
    //   6030: goto -> 6058
    //   6033: invokestatic a : (Ljava/lang/Throwable;)Ljava/lang/Throwable;
    //   6036: athrow
    //   6037: aload #11
    //   6039: iconst_3
    //   6040: aaload
    //   6041: getstatic java/lang/Integer.TYPE : Ljava/lang/Class;
    //   6044: if_acmpeq -> 6054
    //   6047: goto -> 6058
    //   6050: invokestatic a : (Ljava/lang/Throwable;)Ljava/lang/Throwable;
    //   6053: athrow
    //   6054: aload #10
    //   6056: astore #6
    //   6058: iinc #9, 1
    //   6061: iload_2
    //   6062: ifeq -> 5933
    //   6065: aload #6
    //   6067: iconst_1
    //   6068: invokevirtual setAccessible : (Z)V
    //   6071: ldc burp/Zzr5
    //   6073: iconst_0
    //   6074: anewarray java/lang/Class
    //   6077: invokevirtual getDeclaredConstructor : ([Ljava/lang/Class;)Ljava/lang/reflect/Constructor;
    //   6080: astore #7
    //   6082: aload #7
    //   6084: iconst_1
    //   6085: invokevirtual setAccessible : (Z)V
    //   6088: aload #6
    //   6090: aload #7
    //   6092: iconst_0
    //   6093: anewarray java/lang/Object
    //   6096: invokevirtual newInstance : ([Ljava/lang/Object;)Ljava/lang/Object;
    //   6099: iconst_4
    //   6100: anewarray java/lang/Object
    //   6103: dup
    //   6104: iconst_0
    //   6105: sipush #-30321
    //   6108: sipush #25353
    //   6111: invokestatic a : (II)Ljava/lang/String;
    //   6114: aastore
    //   6115: dup
    //   6116: iconst_1
    //   6117: aload #5
    //   6119: aastore
    //   6120: dup
    //   6121: iconst_2
    //   6122: iconst_0
    //   6123: invokestatic valueOf : (I)Ljava/lang/Integer;
    //   6126: aastore
    //   6127: dup
    //   6128: iconst_3
    //   6129: aload #5
    //   6131: arraylength
    //   6132: invokestatic valueOf : (I)Ljava/lang/Integer;
    //   6135: aastore
    //   6136: invokevirtual invoke : (Ljava/lang/Object;[Ljava/lang/Object;)Ljava/lang/Object;
    //   6139: pop
    //   6140: goto -> 6145
    //   6143: astore #4
    //   6145: getstatic burp/Zrp3.Zf : Ljava/lang/String;
    //   6148: getstatic burp/Zs56.ZC : Ljava/lang/Object;
    //   6151: checkcast java/math/BigInteger
    //   6154: invokevirtual intValue : ()I
    //   6157: bipush #32
    //   6159: irem
    //   6160: invokestatic abs : (I)I
    //   6163: invokevirtual charAt : (I)C
    //   6166: getstatic burp/Zb8_.ZP : Ljava/lang/String;
    //   6169: getstatic burp/Zej5.ZB : Ljava/lang/Object;
    //   6172: checkcast java/math/BigInteger
    //   6175: invokevirtual intValue : ()I
    //   6178: bipush #32
    //   6180: irem
    //   6181: invokestatic abs : (I)I
    //   6184: invokevirtual charAt : (I)C
    //   6187: if_icmpgt -> 6294
    //   6190: getstatic burp/Zmec.Zi : Ljava/lang/String;
    //   6193: getstatic burp/Zeju.Zk : Ljava/lang/Object;
    //   6196: checkcast java/math/BigInteger
    //   6199: invokevirtual intValue : ()I
    //   6202: bipush #32
    //   6204: irem
    //   6205: invokestatic abs : (I)I
    //   6208: invokevirtual charAt : (I)C
    //   6211: getstatic burp/Zrxf.ZG : Ljava/lang/String;
    //   6214: getstatic burp/Zl5.ZY : Ljava/lang/Object;
    //   6217: checkcast java/math/BigInteger
    //   6220: invokevirtual intValue : ()I
    //   6223: bipush #32
    //   6225: irem
    //   6226: invokestatic abs : (I)I
    //   6229: invokevirtual charAt : (I)C
    //   6232: if_icmple -> 6294
    //   6235: goto -> 6242
    //   6238: invokestatic a : (Ljava/lang/Throwable;)Ljava/lang/Throwable;
    //   6241: athrow
    //   6242: getstatic burp/Zl6z.ZL : Ljava/lang/String;
    //   6245: getstatic burp/Zl1z.ZV : Ljava/lang/Object;
    //   6248: checkcast java/math/BigInteger
    //   6251: invokevirtual intValue : ()I
    //   6254: bipush #32
    //   6256: irem
    //   6257: invokestatic abs : (I)I
    //   6260: invokevirtual charAt : (I)C
    //   6263: getstatic burp/Zlhu.ZC : Ljava/lang/String;
    //   6266: getstatic burp/Zml2.Zo : Ljava/lang/Object;
    //   6269: checkcast java/math/BigInteger
    //   6272: invokevirtual intValue : ()I
    //   6275: bipush #32
    //   6277: irem
    //   6278: invokestatic abs : (I)I
    //   6281: invokevirtual charAt : (I)C
    //   6284: if_icmpgt -> 6302
    //   6287: goto -> 6294
    //   6290: invokestatic a : (Ljava/lang/Throwable;)Ljava/lang/Throwable;
    //   6293: athrow
    //   6294: iconst_1
    //   6295: goto -> 6303
    //   6298: invokestatic a : (Ljava/lang/Throwable;)Ljava/lang/Throwable;
    //   6301: athrow
    //   6302: iconst_0
    //   6303: ireturn
    //   6304: astore_3
    //   6305: new java/lang/Exception
    //   6308: dup
    //   6309: aload_3
    //   6310: invokevirtual getMessage : ()Ljava/lang/String;
    //   6313: invokespecial <init> : (Ljava/lang/String;)V
    //   6316: athrow
    // Exception table:
    //   from	to	target	type
    //   4	6303	6304	java/lang/Throwable
    //   40	214	217	java/lang/Throwable
    //   184	251	254	java/lang/Throwable
    //   221	288	291	java/lang/Throwable
    //   258	325	328	java/lang/Throwable
    //   295	362	365	java/lang/Throwable
    //   332	399	402	java/lang/Throwable
    //   369	436	439	java/lang/Throwable
    //   406	473	476	java/lang/Throwable
    //   443	510	513	java/lang/Throwable
    //   480	547	550	java/lang/Throwable
    //   517	584	587	java/lang/Throwable
    //   554	621	624	java/lang/Throwable
    //   591	658	661	java/lang/Throwable
    //   628	695	698	java/lang/Throwable
    //   665	732	735	java/lang/Throwable
    //   702	769	772	java/lang/Throwable
    //   739	806	809	java/lang/Throwable
    //   776	843	846	java/lang/Throwable
    //   813	880	883	java/lang/Throwable
    //   850	917	920	java/lang/Throwable
    //   887	954	957	java/lang/Throwable
    //   924	991	994	java/lang/Throwable
    //   961	1028	1031	java/lang/Throwable
    //   998	1065	1068	java/lang/Throwable
    //   1035	1102	1105	java/lang/Throwable
    //   1072	1139	1142	java/lang/Throwable
    //   1109	1176	1179	java/lang/Throwable
    //   1146	1213	1216	java/lang/Throwable
    //   1183	1250	1253	java/lang/Throwable
    //   1220	1287	1290	java/lang/Throwable
    //   1257	1324	1327	java/lang/Throwable
    //   1294	1357	1360	java/lang/Throwable
    //   2181	2215	2218	java/lang/Throwable
    //   2311	2389	2392	java/lang/Throwable
    //   2318	2532	2535	java/lang/Throwable
    //   2910	2925	2925	java/lang/Throwable
    //   2952	2986	2989	java/lang/Throwable
    //   2996	3008	3011	java/lang/Throwable
    //   3094	3172	3175	java/lang/Throwable
    //   3101	3315	3318	java/lang/Throwable
    //   3715	3793	3796	java/lang/Throwable
    //   3722	3936	3939	java/lang/Throwable
    //   4383	4417	4420	java/lang/Throwable
    //   4424	4436	4439	java/lang/Throwable
    //   4522	4600	4603	java/lang/Throwable
    //   4529	4743	4746	java/lang/Throwable
    //   5500	5514	5514	java/lang/Throwable
    //   5525	5538	5541	java/lang/Throwable
    //   5530	5553	5556	java/lang/Throwable
    //   5545	5571	5574	java/lang/Throwable
    //   5560	5601	5604	java/lang/Throwable
    //   5667	5694	5697	java/lang/Throwable
    //   5684	5715	5718	java/lang/Throwable
    //   5701	5745	5748	java/lang/Throwable
    //   5722	5756	5756	java/lang/Throwable
    //   5767	5783	5786	java/lang/Throwable
    //   5790	6140	6143	java/lang/Throwable
    //   5974	5984	5984	java/lang/Throwable
    //   5988	6000	6000	java/lang/Throwable
    //   6004	6016	6016	java/lang/Throwable
    //   6020	6033	6033	java/lang/Throwable
    //   6037	6050	6050	java/lang/Throwable
    //   6145	6235	6238	java/lang/Throwable
    //   6190	6287	6290	java/lang/Throwable
    //   6242	6298	6298	java/lang/Throwable
  }
  
  static {
    // Byte code:
    //   0: bipush #11
    //   2: anewarray java/lang/String
    //   5: astore #5
    //   7: iconst_0
    //   8: istore_3
    //   9: ldc '*Z\\\t19 /sU8kWae=|nU P\M$b-x%*Fp\\tPa.\\tD1yz\\b\\bP#Mw\\f|i3J\\fbUi`m0" Db4Gh)Hh2JqYAdi\\bkL'
    //   11: dup
    //   12: astore_2
    //   13: invokevirtual length : ()I
    //   16: istore #4
    //   18: bipush #9
    //   20: istore_1
    //   21: iconst_m1
    //   22: istore_0
    //   23: bipush #63
    //   25: iinc #0, 1
    //   28: aload_2
    //   29: iload_0
    //   30: dup
    //   31: iload_1
    //   32: iadd
    //   33: invokevirtual substring : (II)Ljava/lang/String;
    //   36: iconst_m1
    //   37: goto -> 142
    //   40: aload #5
    //   42: swap
    //   43: iload_3
    //   44: iinc #3, 1
    //   47: swap
    //   48: aastore
    //   49: iload_0
    //   50: iload_1
    //   51: iadd
    //   52: dup
    //   53: istore_0
    //   54: iload #4
    //   56: if_icmpge -> 68
    //   59: aload_2
    //   60: iload_0
    //   61: invokevirtual charAt : (I)C
    //   64: istore_1
    //   65: goto -> 23
    //   68: ldc '-lMgB0)'
    //   70: dup
    //   71: astore_2
    //   72: invokevirtual length : ()I
    //   75: istore #4
    //   77: iconst_4
    //   78: istore_1
    //   79: iconst_m1
    //   80: istore_0
    //   81: bipush #101
    //   83: iinc #0, 1
    //   86: aload_2
    //   87: iload_0
    //   88: dup
    //   89: iload_1
    //   90: iadd
    //   91: invokevirtual substring : (II)Ljava/lang/String;
    //   94: iconst_0
    //   95: goto -> 142
    //   98: aload #5
    //   100: swap
    //   101: iload_3
    //   102: iinc #3, 1
    //   105: swap
    //   106: aastore
    //   107: iload_0
    //   108: iload_1
    //   109: iadd
    //   110: dup
    //   111: istore_0
    //   112: iload #4
    //   114: if_icmpge -> 126
    //   117: aload_2
    //   118: iload_0
    //   119: invokevirtual charAt : (I)C
    //   122: istore_1
    //   123: goto -> 81
    //   126: aload #5
    //   128: putstatic burp/Zg3m.a : [Ljava/lang/String;
    //   131: bipush #11
    //   133: anewarray java/lang/String
    //   136: putstatic burp/Zg3m.b : [Ljava/lang/String;
    //   139: goto -> 300
    //   142: dup_x2
    //   143: pop
    //   144: invokevirtual toCharArray : ()[C
    //   147: dup_x1
    //   148: arraylength
    //   149: dup_x2
    //   150: pop
    //   151: iconst_0
    //   152: istore #6
    //   154: dup2_x1
    //   155: pop2
    //   156: dup_x2
    //   157: iconst_1
    //   158: if_icmpgt -> 260
    //   161: dup2
    //   162: swap
    //   163: iload #6
    //   165: dup2_x1
    //   166: caload
    //   167: swap
    //   168: iload #6
    //   170: bipush #7
    //   172: irem
    //   173: tableswitch default -> 242, 0 -> 212, 1 -> 217, 2 -> 222, 3 -> 227, 4 -> 232, 5 -> 237
    //   212: bipush #45
    //   214: goto -> 244
    //   217: bipush #99
    //   219: goto -> 244
    //   222: bipush #62
    //   224: goto -> 244
    //   227: bipush #122
    //   229: goto -> 244
    //   232: bipush #92
    //   234: goto -> 244
    //   237: bipush #63
    //   239: goto -> 244
    //   242: bipush #126
    //   244: ixor
    //   245: ixor
    //   246: i2c
    //   247: castore
    //   248: iinc #6, 1
    //   251: dup
    //   252: ifne -> 260
    //   255: dup2
    //   256: dup_x1
    //   257: goto -> 165
    //   260: dup2_x1
    //   261: pop2
    //   262: dup_x2
    //   263: iload #6
    //   265: if_icmpgt -> 161
    //   268: pop
    //   269: new java/lang/String
    //   272: dup_x1
    //   273: swap
    //   274: invokespecial <init> : ([C)V
    //   277: invokevirtual intern : ()Ljava/lang/String;
    //   280: swap
    //   281: pop
    //   282: swap
    //   283: tableswitch default -> 40, 0 -> 98
    //   300: new java/math/BigInteger
    //   303: dup
    //   304: bipush #32
    //   306: newarray byte
    //   308: dup
    //   309: iconst_0
    //   310: bipush #60
    //   312: bastore
    //   313: dup
    //   314: iconst_1
    //   315: iconst_5
    //   316: bastore
    //   317: dup
    //   318: iconst_2
    //   319: bipush #-49
    //   321: bastore
    //   322: dup
    //   323: iconst_3
    //   324: bipush #44
    //   326: bastore
    //   327: dup
    //   328: iconst_4
    //   329: bipush #-76
    //   331: bastore
    //   332: dup
    //   333: iconst_5
    //   334: bipush #-95
    //   336: bastore
    //   337: dup
    //   338: bipush #6
    //   340: bipush #-51
    //   342: bastore
    //   343: dup
    //   344: bipush #7
    //   346: bipush #-106
    //   348: bastore
    //   349: dup
    //   350: bipush #8
    //   352: bipush #-59
    //   354: bastore
    //   355: dup
    //   356: bipush #9
    //   358: bipush #-56
    //   360: bastore
    //   361: dup
    //   362: bipush #10
    //   364: bipush #-73
    //   366: bastore
    //   367: dup
    //   368: bipush #11
    //   370: bipush #32
    //   372: bastore
    //   373: dup
    //   374: bipush #12
    //   376: bipush #114
    //   378: bastore
    //   379: dup
    //   380: bipush #13
    //   382: bipush #65
    //   384: bastore
    //   385: dup
    //   386: bipush #14
    //   388: bipush #126
    //   390: bastore
    //   391: dup
    //   392: bipush #15
    //   394: bipush #-54
    //   396: bastore
    //   397: dup
    //   398: bipush #16
    //   400: bipush #113
    //   402: bastore
    //   403: dup
    //   404: bipush #17
    //   406: bipush #32
    //   408: bastore
    //   409: dup
    //   410: bipush #18
    //   412: bipush #19
    //   414: bastore
    //   415: dup
    //   416: bipush #19
    //   418: bipush #-103
    //   420: bastore
    //   421: dup
    //   422: bipush #20
    //   424: bipush #-3
    //   426: bastore
    //   427: dup
    //   428: bipush #21
    //   430: bipush #-74
    //   432: bastore
    //   433: dup
    //   434: bipush #22
    //   436: bipush #-104
    //   438: bastore
    //   439: dup
    //   440: bipush #23
    //   442: bipush #-10
    //   444: bastore
    //   445: dup
    //   446: bipush #24
    //   448: bipush #-106
    //   450: bastore
    //   451: dup
    //   452: bipush #25
    //   454: bipush #61
    //   456: bastore
    //   457: dup
    //   458: bipush #26
    //   460: bipush #90
    //   462: bastore
    //   463: dup
    //   464: bipush #27
    //   466: bipush #35
    //   468: bastore
    //   469: dup
    //   470: bipush #28
    //   472: bipush #-123
    //   474: bastore
    //   475: dup
    //   476: bipush #29
    //   478: bipush #-5
    //   480: bastore
    //   481: dup
    //   482: bipush #30
    //   484: bipush #-55
    //   486: bastore
    //   487: dup
    //   488: bipush #31
    //   490: bipush #-21
    //   492: bastore
    //   493: invokespecial <init> : ([B)V
    //   496: putstatic burp/Zg3m.ZK : Ljava/lang/Object;
    //   499: sipush #-30326
    //   502: sipush #30605
    //   505: invokestatic a : (II)Ljava/lang/String;
    //   508: putstatic burp/Zg3m.Za : Ljava/lang/String;
    //   511: return
  }
  
  private static Throwable a(Throwable paramThrowable) {
    return paramThrowable;
  }
  
  private static String a(int paramInt1, int paramInt2) {
    int i = (paramInt1 ^ 0xFFFF8989) & 0xFFFF;
    if (b[i] == null) {
      char[] arrayOfChar = a[i].toCharArray();
      switch (arrayOfChar[0] & 0xFF) {
        case 0:
        
        case 1:
        
        case 2:
        
        case 3:
        
        case 4:
        
        case 5:
        
        case 6:
        
        case 7:
        
        case 8:
        
        case 9:
        
        case 10:
        
        case 11:
        
        case 12:
        
        case 13:
        
        case 14:
        
        case 15:
        
        case 16:
        
        case 17:
        
        case 18:
        
        case 19:
        
        case 20:
        
        case 21:
        
        case 22:
        
        case 23:
        
        case 24:
        
        case 25:
        
        case 26:
        
        case 27:
        
        case 28:
        
        case 29:
        
        case 30:
        
        case 31:
        
        case 32:
        
        case 33:
        
        case 34:
        
        case 35:
        
        case 36:
        
        case 37:
        
        case 38:
        
        case 39:
        
        case 40:
        
        case 41:
        
        case 42:
        
        case 43:
        
        case 44:
        
        case 45:
        
        case 46:
        
        case 47:
        
        case 48:
        
        case 49:
        
        case 50:
        
        case 51:
        
        case 52:
        
        case 53:
        
        case 54:
        
        case 55:
        
        case 56:
        
        case 57:
        
        case 58:
        
        case 59:
        
        case 60:
        
        case 61:
        
        case 62:
        
        case 63:
        
        case 64:
        
        case 65:
        
        case 66:
        
        case 67:
        
        case 68:
        
        case 69:
        
        case 70:
        
        case 71:
        
        case 72:
        
        case 73:
        
        case 74:
        
        case 75:
        
        case 76:
        
        case 77:
        
        case 78:
        
        case 79:
        
        case 80:
        
        case 81:
        
        case 82:
        
        case 83:
        
        case 84:
        
        case 85:
        
        case 86:
        
        case 87:
        
        case 88:
        
        case 89:
        
        case 90:
        
        case 91:
        
        case 92:
        
        case 93:
        
        case 94:
        
        case 95:
        
        case 96:
        
        case 97:
        
        case 98:
        
        case 99:
        
        case 100:
        
        case 101:
        
        case 102:
        
        case 103:
        
        case 104:
        
        case 105:
        
        case 106:
        
        case 107:
        
        case 108:
        
        case 109:
        
        case 110:
        
        case 111:
        
        case 112:
        
        case 113:
        
        case 114:
        
        case 115:
        
        case 116:
        
        case 117:
        
        case 118:
        
        case 119:
        
        case 120:
        
        case 121:
        
        case 122:
        
        case 123:
        
        case 124:
        
        case 125:
        
        case 126:
        
        case 127:
        
        case 128:
        
        case 129:
        
        case 130:
        
        case 131:
        
        case 132:
        
        case 133:
        
        case 134:
        
        case 135:
        
        case 136:
        
        case 137:
        
        case 138:
        
        case 139:
        
        case 140:
        
        case 141:
        
        case 142:
        
        case 143:
        
        case 144:
        
        case 145:
        
        case 146:
        
        case 147:
        
        case 148:
        
        case 149:
        
        case 150:
        
        case 151:
        
        case 152:
        
        case 153:
        
        case 154:
        
        case 155:
        
        case 156:
        
        case 157:
        
        case 158:
        
        case 159:
        
        case 160:
        
        case 161:
        
        case 162:
        
        case 163:
        
        case 164:
        
        case 165:
        
        case 166:
        
        case 167:
        
        case 168:
        
        case 169:
        
        case 170:
        
        case 171:
        
        case 172:
        
        case 173:
        
        case 174:
        
        case 175:
        
        case 176:
        
        case 177:
        
        case 178:
        
        case 179:
        
        case 180:
        
        case 181:
        
        case 182:
        
        case 183:
        
        case 184:
        
        case 185:
        
        case 186:
        
        case 187:
        
        case 188:
        
        case 189:
        
        case 190:
        
        case 191:
        
        case 192:
        
        case 193:
        
        case 194:
        
        case 195:
        
        case 196:
        
        case 197:
        
        case 198:
        
        case 199:
        
        case 200:
        
        case 201:
        
        case 202:
        
        case 203:
        
        case 204:
        
        case 205:
        
        case 206:
        
        case 207:
        
        case 208:
        
        case 209:
        
        case 210:
        
        case 211:
        
        case 212:
        
        case 213:
        
        case 214:
        
        case 215:
        
        case 216:
        
        case 217:
        
        case 218:
        
        case 219:
        
        case 220:
        
        case 221:
        
        case 222:
        
        case 223:
        
        case 224:
        
        case 225:
        
        case 226:
        
        case 227:
        
        case 228:
        
        case 229:
        
        case 230:
        
        case 231:
        
        case 232:
        
        case 233:
        
        case 234:
        
        case 235:
        
        case 236:
        
        case 237:
        
        case 238:
        
        case 239:
        
        case 240:
        
        case 241:
        
        case 242:
        
        case 243:
        
        case 244:
        
        case 245:
        
        case 246:
        
        case 247:
        
        case 248:
        
        case 249:
        
        case 250:
        
        case 251:
        
        case 252:
        
        case 253:
        
        case 254:
        
        default:
          break;
      } 
      char c = '';
      int j = (paramInt2 & 0xFF) - c;
      if (j < 0)
        j += 256; 
      int k = ((paramInt2 & 0xFFFF) >>> 8) - c;
      if (k < 0)
        k += 256; 
      for (byte b = 0; b < arrayOfChar.length; b++) {
        int m = b % 2;
        if (m == 0) {
          arrayOfChar[b] = (char)(arrayOfChar[b] ^ j);
          j = ((j >>> 3 | j << 5) ^ arrayOfChar[b]) & 0xFF;
        } else {
          arrayOfChar[b] = (char)(arrayOfChar[b] ^ k);
          k = ((k >>> 3 | k << 5) ^ arrayOfChar[b]) & 0xFF;
        } 
      } 
      b[i] = (new String(arrayOfChar)).intern();
    } 
    return b[i];
  }
}


/* Location:              C:\Program Files\BurpSuitePro\burpsuite_pro.jar!\burp\Zg3m.class
 * Java compiler version: 21 (65.0)
 * JD-Core Version:       1.1.3
 */