package burp;

import java.math.BigInteger;

class Zg4d extends ClassLoader {
  static Object Zm;
  
  static String ZE;
  
  private static final String[] a;
  
  private static final String[] b;
  
  static void Z_(Object[] paramArrayOfObject, Object paramObject) throws Throwable {}
  
  static void ZG(Object paramObject) {
    Zz75.ZT = a(12043, 6289);
    Zz75.ZX = new BigInteger(a(12050, -31504));
    boolean bool = Zt2e.ZK();
    try {
      try {
        if (Ztlz.ZE.charAt(Math.abs(((BigInteger)Zz75.ZX).intValue() % 32)) > Zera.Zn.charAt(Math.abs(((BigInteger)Zkt7.ZY).intValue() % 32))) {
          try {
            Zgp_.ZG(Class.forName(a(12056, -24771)));
            if (bool)
              Zsqy.Zr(Class.forName(a(12032, -15524))); 
          } catch (Throwable throwable) {
            throw a(null);
          } 
          return;
        } 
      } catch (Throwable throwable) {
        throw a(null);
      } 
      Zsqy.Zr(Class.forName(a(12032, -15524)));
    } catch (Throwable throwable) {}
  }
  
  static boolean Zi(Object[] paramArrayOfObject, Object paramObject) throws Throwable {
    // Byte code:
    //   0: invokestatic ZK : ()Z
    //   3: istore_2
    //   4: new java/lang/StringBuilder
    //   7: dup
    //   8: invokespecial <init> : ()V
    //   11: astore_3
    //   12: iconst_0
    //   13: istore #4
    //   15: iload #4
    //   17: bipush #32
    //   19: if_icmpge -> 1355
    //   22: iload #4
    //   24: tableswitch default -> 1348, 0 -> 168, 1 -> 205, 2 -> 242, 3 -> 279, 4 -> 316, 5 -> 353, 6 -> 390, 7 -> 427, 8 -> 464, 9 -> 501, 10 -> 538, 11 -> 575, 12 -> 612, 13 -> 649, 14 -> 686, 15 -> 723, 16 -> 760, 17 -> 797, 18 -> 834, 19 -> 871, 20 -> 908, 21 -> 945, 22 -> 982, 23 -> 1019, 24 -> 1056, 25 -> 1093, 26 -> 1130, 27 -> 1167, 28 -> 1204, 29 -> 1241, 30 -> 1278, 31 -> 1315
    //   168: aload_3
    //   169: getstatic burp/Zr2i.Z_ : Ljava/lang/String;
    //   172: getstatic burp/Zlrm.ZM : Ljava/lang/Object;
    //   175: checkcast java/math/BigInteger
    //   178: invokevirtual intValue : ()I
    //   181: bipush #32
    //   183: irem
    //   184: invokestatic abs : (I)I
    //   187: invokevirtual charAt : (I)C
    //   190: invokevirtual append : (C)Ljava/lang/StringBuilder;
    //   193: pop
    //   194: iload_2
    //   195: ifeq -> 1348
    //   198: goto -> 205
    //   201: invokestatic a : (Ljava/lang/Throwable;)Ljava/lang/Throwable;
    //   204: athrow
    //   205: aload_3
    //   206: getstatic burp/Zzo5.ZX : Ljava/lang/String;
    //   209: getstatic burp/Zlh8.Zm : Ljava/lang/Object;
    //   212: checkcast java/math/BigInteger
    //   215: invokevirtual intValue : ()I
    //   218: bipush #32
    //   220: irem
    //   221: invokestatic abs : (I)I
    //   224: invokevirtual charAt : (I)C
    //   227: invokevirtual append : (C)Ljava/lang/StringBuilder;
    //   230: pop
    //   231: iload_2
    //   232: ifeq -> 1348
    //   235: goto -> 242
    //   238: invokestatic a : (Ljava/lang/Throwable;)Ljava/lang/Throwable;
    //   241: athrow
    //   242: aload_3
    //   243: getstatic burp/Zmj8.ZL : Ljava/lang/String;
    //   246: getstatic burp/Zxjv.ZY : Ljava/lang/Object;
    //   249: checkcast java/math/BigInteger
    //   252: invokevirtual intValue : ()I
    //   255: bipush #32
    //   257: irem
    //   258: invokestatic abs : (I)I
    //   261: invokevirtual charAt : (I)C
    //   264: invokevirtual append : (C)Ljava/lang/StringBuilder;
    //   267: pop
    //   268: iload_2
    //   269: ifeq -> 1348
    //   272: goto -> 279
    //   275: invokestatic a : (Ljava/lang/Throwable;)Ljava/lang/Throwable;
    //   278: athrow
    //   279: aload_3
    //   280: getstatic burp/Zlf0.ZS : Ljava/lang/String;
    //   283: getstatic burp/Zr1z.Zi : Ljava/lang/Object;
    //   286: checkcast java/math/BigInteger
    //   289: invokevirtual intValue : ()I
    //   292: bipush #32
    //   294: irem
    //   295: invokestatic abs : (I)I
    //   298: invokevirtual charAt : (I)C
    //   301: invokevirtual append : (C)Ljava/lang/StringBuilder;
    //   304: pop
    //   305: iload_2
    //   306: ifeq -> 1348
    //   309: goto -> 316
    //   312: invokestatic a : (Ljava/lang/Throwable;)Ljava/lang/Throwable;
    //   315: athrow
    //   316: aload_3
    //   317: getstatic burp/Zgqi.Zv : Ljava/lang/String;
    //   320: getstatic burp/Zt9_.ZN : Ljava/lang/Object;
    //   323: checkcast java/math/BigInteger
    //   326: invokevirtual intValue : ()I
    //   329: bipush #32
    //   331: irem
    //   332: invokestatic abs : (I)I
    //   335: invokevirtual charAt : (I)C
    //   338: invokevirtual append : (C)Ljava/lang/StringBuilder;
    //   341: pop
    //   342: iload_2
    //   343: ifeq -> 1348
    //   346: goto -> 353
    //   349: invokestatic a : (Ljava/lang/Throwable;)Ljava/lang/Throwable;
    //   352: athrow
    //   353: aload_3
    //   354: getstatic burp/Zli5.Zq : Ljava/lang/String;
    //   357: getstatic burp/Zxjk.Zk : Ljava/lang/Object;
    //   360: checkcast java/math/BigInteger
    //   363: invokevirtual intValue : ()I
    //   366: bipush #32
    //   368: irem
    //   369: invokestatic abs : (I)I
    //   372: invokevirtual charAt : (I)C
    //   375: invokevirtual append : (C)Ljava/lang/StringBuilder;
    //   378: pop
    //   379: iload_2
    //   380: ifeq -> 1348
    //   383: goto -> 390
    //   386: invokestatic a : (Ljava/lang/Throwable;)Ljava/lang/Throwable;
    //   389: athrow
    //   390: aload_3
    //   391: getstatic burp/Zt3f.ZU : Ljava/lang/String;
    //   394: getstatic burp/Zrcy.Zr : Ljava/lang/Object;
    //   397: checkcast java/math/BigInteger
    //   400: invokevirtual intValue : ()I
    //   403: bipush #32
    //   405: irem
    //   406: invokestatic abs : (I)I
    //   409: invokevirtual charAt : (I)C
    //   412: invokevirtual append : (C)Ljava/lang/StringBuilder;
    //   415: pop
    //   416: iload_2
    //   417: ifeq -> 1348
    //   420: goto -> 427
    //   423: invokestatic a : (Ljava/lang/Throwable;)Ljava/lang/Throwable;
    //   426: athrow
    //   427: aload_3
    //   428: getstatic burp/Zest.Zd : Ljava/lang/String;
    //   431: getstatic burp/Zm52.ZR : Ljava/lang/Object;
    //   434: checkcast java/math/BigInteger
    //   437: invokevirtual intValue : ()I
    //   440: bipush #32
    //   442: irem
    //   443: invokestatic abs : (I)I
    //   446: invokevirtual charAt : (I)C
    //   449: invokevirtual append : (C)Ljava/lang/StringBuilder;
    //   452: pop
    //   453: iload_2
    //   454: ifeq -> 1348
    //   457: goto -> 464
    //   460: invokestatic a : (Ljava/lang/Throwable;)Ljava/lang/Throwable;
    //   463: athrow
    //   464: aload_3
    //   465: getstatic burp/Ze54.ZU : Ljava/lang/String;
    //   468: getstatic burp/Ze54.Zx : Ljava/lang/Object;
    //   471: checkcast java/math/BigInteger
    //   474: invokevirtual intValue : ()I
    //   477: bipush #32
    //   479: irem
    //   480: invokestatic abs : (I)I
    //   483: invokevirtual charAt : (I)C
    //   486: invokevirtual append : (C)Ljava/lang/StringBuilder;
    //   489: pop
    //   490: iload_2
    //   491: ifeq -> 1348
    //   494: goto -> 501
    //   497: invokestatic a : (Ljava/lang/Throwable;)Ljava/lang/Throwable;
    //   500: athrow
    //   501: aload_3
    //   502: getstatic burp/Zz6t.Zx : Ljava/lang/String;
    //   505: getstatic burp/Zg6f.Zl : Ljava/lang/Object;
    //   508: checkcast java/math/BigInteger
    //   511: invokevirtual intValue : ()I
    //   514: bipush #32
    //   516: irem
    //   517: invokestatic abs : (I)I
    //   520: invokevirtual charAt : (I)C
    //   523: invokevirtual append : (C)Ljava/lang/StringBuilder;
    //   526: pop
    //   527: iload_2
    //   528: ifeq -> 1348
    //   531: goto -> 538
    //   534: invokestatic a : (Ljava/lang/Throwable;)Ljava/lang/Throwable;
    //   537: athrow
    //   538: aload_3
    //   539: getstatic burp/Zli5.Zq : Ljava/lang/String;
    //   542: getstatic burp/Zs_v.Zs : Ljava/lang/Object;
    //   545: checkcast java/math/BigInteger
    //   548: invokevirtual intValue : ()I
    //   551: bipush #32
    //   553: irem
    //   554: invokestatic abs : (I)I
    //   557: invokevirtual charAt : (I)C
    //   560: invokevirtual append : (C)Ljava/lang/StringBuilder;
    //   563: pop
    //   564: iload_2
    //   565: ifeq -> 1348
    //   568: goto -> 575
    //   571: invokestatic a : (Ljava/lang/Throwable;)Ljava/lang/Throwable;
    //   574: athrow
    //   575: aload_3
    //   576: getstatic burp/Zsxh.Z_ : Ljava/lang/String;
    //   579: getstatic burp/Zest.Zq : Ljava/lang/Object;
    //   582: checkcast java/math/BigInteger
    //   585: invokevirtual intValue : ()I
    //   588: bipush #32
    //   590: irem
    //   591: invokestatic abs : (I)I
    //   594: invokevirtual charAt : (I)C
    //   597: invokevirtual append : (C)Ljava/lang/StringBuilder;
    //   600: pop
    //   601: iload_2
    //   602: ifeq -> 1348
    //   605: goto -> 612
    //   608: invokestatic a : (Ljava/lang/Throwable;)Ljava/lang/Throwable;
    //   611: athrow
    //   612: aload_3
    //   613: getstatic burp/Zram.Ze : Ljava/lang/String;
    //   616: getstatic burp/Zke7.Zj : Ljava/lang/Object;
    //   619: checkcast java/math/BigInteger
    //   622: invokevirtual intValue : ()I
    //   625: bipush #32
    //   627: irem
    //   628: invokestatic abs : (I)I
    //   631: invokevirtual charAt : (I)C
    //   634: invokevirtual append : (C)Ljava/lang/StringBuilder;
    //   637: pop
    //   638: iload_2
    //   639: ifeq -> 1348
    //   642: goto -> 649
    //   645: invokestatic a : (Ljava/lang/Throwable;)Ljava/lang/Throwable;
    //   648: athrow
    //   649: aload_3
    //   650: getstatic burp/Zs83.ZG : Ljava/lang/String;
    //   653: getstatic burp/Zli5.Zt : Ljava/lang/Object;
    //   656: checkcast java/math/BigInteger
    //   659: invokevirtual intValue : ()I
    //   662: bipush #32
    //   664: irem
    //   665: invokestatic abs : (I)I
    //   668: invokevirtual charAt : (I)C
    //   671: invokevirtual append : (C)Ljava/lang/StringBuilder;
    //   674: pop
    //   675: iload_2
    //   676: ifeq -> 1348
    //   679: goto -> 686
    //   682: invokestatic a : (Ljava/lang/Throwable;)Ljava/lang/Throwable;
    //   685: athrow
    //   686: aload_3
    //   687: getstatic burp/Ze8i.ZM : Ljava/lang/String;
    //   690: getstatic burp/Zz2e.Zm : Ljava/lang/Object;
    //   693: checkcast java/math/BigInteger
    //   696: invokevirtual intValue : ()I
    //   699: bipush #32
    //   701: irem
    //   702: invokestatic abs : (I)I
    //   705: invokevirtual charAt : (I)C
    //   708: invokevirtual append : (C)Ljava/lang/StringBuilder;
    //   711: pop
    //   712: iload_2
    //   713: ifeq -> 1348
    //   716: goto -> 723
    //   719: invokestatic a : (Ljava/lang/Throwable;)Ljava/lang/Throwable;
    //   722: athrow
    //   723: aload_3
    //   724: getstatic burp/Zzym.Zj : Ljava/lang/String;
    //   727: getstatic burp/Zkb_.ZG : Ljava/lang/Object;
    //   730: checkcast java/math/BigInteger
    //   733: invokevirtual intValue : ()I
    //   736: bipush #32
    //   738: irem
    //   739: invokestatic abs : (I)I
    //   742: invokevirtual charAt : (I)C
    //   745: invokevirtual append : (C)Ljava/lang/StringBuilder;
    //   748: pop
    //   749: iload_2
    //   750: ifeq -> 1348
    //   753: goto -> 760
    //   756: invokestatic a : (Ljava/lang/Throwable;)Ljava/lang/Throwable;
    //   759: athrow
    //   760: aload_3
    //   761: getstatic burp/Ztye.ZR : Ljava/lang/String;
    //   764: getstatic burp/Zera.Zy : Ljava/lang/Object;
    //   767: checkcast java/math/BigInteger
    //   770: invokevirtual intValue : ()I
    //   773: bipush #32
    //   775: irem
    //   776: invokestatic abs : (I)I
    //   779: invokevirtual charAt : (I)C
    //   782: invokevirtual append : (C)Ljava/lang/StringBuilder;
    //   785: pop
    //   786: iload_2
    //   787: ifeq -> 1348
    //   790: goto -> 797
    //   793: invokestatic a : (Ljava/lang/Throwable;)Ljava/lang/Throwable;
    //   796: athrow
    //   797: aload_3
    //   798: getstatic burp/Zzym.Zj : Ljava/lang/String;
    //   801: getstatic burp/Zqp.ZA : Ljava/lang/Object;
    //   804: checkcast java/math/BigInteger
    //   807: invokevirtual intValue : ()I
    //   810: bipush #32
    //   812: irem
    //   813: invokestatic abs : (I)I
    //   816: invokevirtual charAt : (I)C
    //   819: invokevirtual append : (C)Ljava/lang/StringBuilder;
    //   822: pop
    //   823: iload_2
    //   824: ifeq -> 1348
    //   827: goto -> 834
    //   830: invokestatic a : (Ljava/lang/Throwable;)Ljava/lang/Throwable;
    //   833: athrow
    //   834: aload_3
    //   835: getstatic burp/Zz75.ZT : Ljava/lang/String;
    //   838: getstatic burp/Ztkh.Zh : Ljava/lang/Object;
    //   841: checkcast java/math/BigInteger
    //   844: invokevirtual intValue : ()I
    //   847: bipush #32
    //   849: irem
    //   850: invokestatic abs : (I)I
    //   853: invokevirtual charAt : (I)C
    //   856: invokevirtual append : (C)Ljava/lang/StringBuilder;
    //   859: pop
    //   860: iload_2
    //   861: ifeq -> 1348
    //   864: goto -> 871
    //   867: invokestatic a : (Ljava/lang/Throwable;)Ljava/lang/Throwable;
    //   870: athrow
    //   871: aload_3
    //   872: getstatic burp/Zlpj.Zj : Ljava/lang/String;
    //   875: getstatic burp/Zxn5.Zd : Ljava/lang/Object;
    //   878: checkcast java/math/BigInteger
    //   881: invokevirtual intValue : ()I
    //   884: bipush #32
    //   886: irem
    //   887: invokestatic abs : (I)I
    //   890: invokevirtual charAt : (I)C
    //   893: invokevirtual append : (C)Ljava/lang/StringBuilder;
    //   896: pop
    //   897: iload_2
    //   898: ifeq -> 1348
    //   901: goto -> 908
    //   904: invokestatic a : (Ljava/lang/Throwable;)Ljava/lang/Throwable;
    //   907: athrow
    //   908: aload_3
    //   909: getstatic burp/Zkc8.Za : Ljava/lang/String;
    //   912: getstatic burp/Zzym.ZK : Ljava/lang/Object;
    //   915: checkcast java/math/BigInteger
    //   918: invokevirtual intValue : ()I
    //   921: bipush #32
    //   923: irem
    //   924: invokestatic abs : (I)I
    //   927: invokevirtual charAt : (I)C
    //   930: invokevirtual append : (C)Ljava/lang/StringBuilder;
    //   933: pop
    //   934: iload_2
    //   935: ifeq -> 1348
    //   938: goto -> 945
    //   941: invokestatic a : (Ljava/lang/Throwable;)Ljava/lang/Throwable;
    //   944: athrow
    //   945: aload_3
    //   946: getstatic burp/Zs_3.ZC : Ljava/lang/String;
    //   949: getstatic burp/Zl50.ZV : Ljava/lang/Object;
    //   952: checkcast java/math/BigInteger
    //   955: invokevirtual intValue : ()I
    //   958: bipush #32
    //   960: irem
    //   961: invokestatic abs : (I)I
    //   964: invokevirtual charAt : (I)C
    //   967: invokevirtual append : (C)Ljava/lang/StringBuilder;
    //   970: pop
    //   971: iload_2
    //   972: ifeq -> 1348
    //   975: goto -> 982
    //   978: invokestatic a : (Ljava/lang/Throwable;)Ljava/lang/Throwable;
    //   981: athrow
    //   982: aload_3
    //   983: getstatic burp/Zzoi.ZR : Ljava/lang/String;
    //   986: getstatic burp/Ztye.ZK : Ljava/lang/Object;
    //   989: checkcast java/math/BigInteger
    //   992: invokevirtual intValue : ()I
    //   995: bipush #32
    //   997: irem
    //   998: invokestatic abs : (I)I
    //   1001: invokevirtual charAt : (I)C
    //   1004: invokevirtual append : (C)Ljava/lang/StringBuilder;
    //   1007: pop
    //   1008: iload_2
    //   1009: ifeq -> 1348
    //   1012: goto -> 1019
    //   1015: invokestatic a : (Ljava/lang/Throwable;)Ljava/lang/Throwable;
    //   1018: athrow
    //   1019: aload_3
    //   1020: getstatic burp/Zvo3.Z_ : Ljava/lang/String;
    //   1023: getstatic burp/Zkm0.ZI : Ljava/lang/Object;
    //   1026: checkcast java/math/BigInteger
    //   1029: invokevirtual intValue : ()I
    //   1032: bipush #32
    //   1034: irem
    //   1035: invokestatic abs : (I)I
    //   1038: invokevirtual charAt : (I)C
    //   1041: invokevirtual append : (C)Ljava/lang/StringBuilder;
    //   1044: pop
    //   1045: iload_2
    //   1046: ifeq -> 1348
    //   1049: goto -> 1056
    //   1052: invokestatic a : (Ljava/lang/Throwable;)Ljava/lang/Throwable;
    //   1055: athrow
    //   1056: aload_3
    //   1057: getstatic burp/Zlhy.ZS : Ljava/lang/String;
    //   1060: getstatic burp/Zxn5.Zd : Ljava/lang/Object;
    //   1063: checkcast java/math/BigInteger
    //   1066: invokevirtual intValue : ()I
    //   1069: bipush #32
    //   1071: irem
    //   1072: invokestatic abs : (I)I
    //   1075: invokevirtual charAt : (I)C
    //   1078: invokevirtual append : (C)Ljava/lang/StringBuilder;
    //   1081: pop
    //   1082: iload_2
    //   1083: ifeq -> 1348
    //   1086: goto -> 1093
    //   1089: invokestatic a : (Ljava/lang/Throwable;)Ljava/lang/Throwable;
    //   1092: athrow
    //   1093: aload_3
    //   1094: getstatic burp/Zlem.Zl : Ljava/lang/String;
    //   1097: getstatic burp/Zz2e.Zm : Ljava/lang/Object;
    //   1100: checkcast java/math/BigInteger
    //   1103: invokevirtual intValue : ()I
    //   1106: bipush #32
    //   1108: irem
    //   1109: invokestatic abs : (I)I
    //   1112: invokevirtual charAt : (I)C
    //   1115: invokevirtual append : (C)Ljava/lang/StringBuilder;
    //   1118: pop
    //   1119: iload_2
    //   1120: ifeq -> 1348
    //   1123: goto -> 1130
    //   1126: invokestatic a : (Ljava/lang/Throwable;)Ljava/lang/Throwable;
    //   1129: athrow
    //   1130: aload_3
    //   1131: getstatic burp/Zt98.Zh : Ljava/lang/String;
    //   1134: getstatic burp/Zlx5.Zp : Ljava/lang/Object;
    //   1137: checkcast java/math/BigInteger
    //   1140: invokevirtual intValue : ()I
    //   1143: bipush #32
    //   1145: irem
    //   1146: invokestatic abs : (I)I
    //   1149: invokevirtual charAt : (I)C
    //   1152: invokevirtual append : (C)Ljava/lang/StringBuilder;
    //   1155: pop
    //   1156: iload_2
    //   1157: ifeq -> 1348
    //   1160: goto -> 1167
    //   1163: invokestatic a : (Ljava/lang/Throwable;)Ljava/lang/Throwable;
    //   1166: athrow
    //   1167: aload_3
    //   1168: getstatic burp/Zxn5.ZI : Ljava/lang/String;
    //   1171: getstatic burp/Zb.ZV : Ljava/lang/Object;
    //   1174: checkcast java/math/BigInteger
    //   1177: invokevirtual intValue : ()I
    //   1180: bipush #32
    //   1182: irem
    //   1183: invokestatic abs : (I)I
    //   1186: invokevirtual charAt : (I)C
    //   1189: invokevirtual append : (C)Ljava/lang/StringBuilder;
    //   1192: pop
    //   1193: iload_2
    //   1194: ifeq -> 1348
    //   1197: goto -> 1204
    //   1200: invokestatic a : (Ljava/lang/Throwable;)Ljava/lang/Throwable;
    //   1203: athrow
    //   1204: aload_3
    //   1205: getstatic burp/Zgva.ZV : Ljava/lang/String;
    //   1208: getstatic burp/Ztj5.Zj : Ljava/lang/Object;
    //   1211: checkcast java/math/BigInteger
    //   1214: invokevirtual intValue : ()I
    //   1217: bipush #32
    //   1219: irem
    //   1220: invokestatic abs : (I)I
    //   1223: invokevirtual charAt : (I)C
    //   1226: invokevirtual append : (C)Ljava/lang/StringBuilder;
    //   1229: pop
    //   1230: iload_2
    //   1231: ifeq -> 1348
    //   1234: goto -> 1241
    //   1237: invokestatic a : (Ljava/lang/Throwable;)Ljava/lang/Throwable;
    //   1240: athrow
    //   1241: aload_3
    //   1242: getstatic burp/Zeqg.Zh : Ljava/lang/String;
    //   1245: getstatic burp/Ztdd.ZD : Ljava/lang/Object;
    //   1248: checkcast java/math/BigInteger
    //   1251: invokevirtual intValue : ()I
    //   1254: bipush #32
    //   1256: irem
    //   1257: invokestatic abs : (I)I
    //   1260: invokevirtual charAt : (I)C
    //   1263: invokevirtual append : (C)Ljava/lang/StringBuilder;
    //   1266: pop
    //   1267: iload_2
    //   1268: ifeq -> 1348
    //   1271: goto -> 1278
    //   1274: invokestatic a : (Ljava/lang/Throwable;)Ljava/lang/Throwable;
    //   1277: athrow
    //   1278: aload_3
    //   1279: getstatic burp/Zmhi.ZQ : Ljava/lang/String;
    //   1282: getstatic burp/Zkt7.ZY : Ljava/lang/Object;
    //   1285: checkcast java/math/BigInteger
    //   1288: invokevirtual intValue : ()I
    //   1291: bipush #32
    //   1293: irem
    //   1294: invokestatic abs : (I)I
    //   1297: invokevirtual charAt : (I)C
    //   1300: invokevirtual append : (C)Ljava/lang/StringBuilder;
    //   1303: pop
    //   1304: iload_2
    //   1305: ifeq -> 1348
    //   1308: goto -> 1315
    //   1311: invokestatic a : (Ljava/lang/Throwable;)Ljava/lang/Throwable;
    //   1314: athrow
    //   1315: aload_3
    //   1316: getstatic burp/Zx6d.ZP : Ljava/lang/String;
    //   1319: getstatic burp/Zx6d.ZU : Ljava/lang/Object;
    //   1322: checkcast java/math/BigInteger
    //   1325: invokevirtual intValue : ()I
    //   1328: bipush #32
    //   1330: irem
    //   1331: invokestatic abs : (I)I
    //   1334: invokevirtual charAt : (I)C
    //   1337: invokevirtual append : (C)Ljava/lang/StringBuilder;
    //   1340: pop
    //   1341: goto -> 1348
    //   1344: invokestatic a : (Ljava/lang/Throwable;)Ljava/lang/Throwable;
    //   1347: athrow
    //   1348: iinc #4, 1
    //   1351: iload_2
    //   1352: ifeq -> 15
    //   1355: aload_3
    //   1356: invokevirtual toString : ()Ljava/lang/String;
    //   1359: putstatic burp/Zstb.Zd : Ljava/lang/String;
    //   1362: getstatic burp/Zmhi.ZZ : Ljava/lang/Object;
    //   1365: checkcast java/math/BigInteger
    //   1368: getstatic burp/Zzgh.ZV : Ljava/lang/Object;
    //   1371: checkcast java/math/BigInteger
    //   1374: invokevirtual subtract : (Ljava/math/BigInteger;)Ljava/math/BigInteger;
    //   1377: putstatic burp/Zg4w.ZR : Ljava/lang/Object;
    //   1380: new java/io/ByteArrayOutputStream
    //   1383: dup
    //   1384: invokespecial <init> : ()V
    //   1387: astore #4
    //   1389: getstatic burp/Zg4k.ZB : Ljava/lang/String;
    //   1392: astore #5
    //   1394: iconst_0
    //   1395: istore #6
    //   1397: iload #6
    //   1399: aload #5
    //   1401: invokevirtual length : ()I
    //   1404: if_icmpge -> 1435
    //   1407: aload #4
    //   1409: aload #5
    //   1411: iload #6
    //   1413: iload #6
    //   1415: iconst_2
    //   1416: iadd
    //   1417: invokevirtual substring : (II)Ljava/lang/String;
    //   1420: bipush #16
    //   1422: invokestatic parseInt : (Ljava/lang/String;I)I
    //   1425: invokevirtual write : (I)V
    //   1428: iinc #6, 2
    //   1431: iload_2
    //   1432: ifeq -> 1397
    //   1435: aload #4
    //   1437: invokevirtual toByteArray : ()[B
    //   1440: astore #6
    //   1442: getstatic burp/Zzym.ZK : Ljava/lang/Object;
    //   1445: checkcast java/math/BigInteger
    //   1448: invokevirtual toByteArray : ()[B
    //   1451: astore #7
    //   1453: sipush #256
    //   1456: newarray byte
    //   1458: astore #9
    //   1460: sipush #256
    //   1463: newarray int
    //   1465: astore #10
    //   1467: sipush #256
    //   1470: newarray int
    //   1472: astore #11
    //   1474: sipush #256
    //   1477: newarray int
    //   1479: astore #12
    //   1481: sipush #256
    //   1484: newarray int
    //   1486: astore #13
    //   1488: bipush #10
    //   1490: newarray int
    //   1492: astore #14
    //   1494: sipush #283
    //   1497: istore #15
    //   1499: iconst_0
    //   1500: istore #17
    //   1502: iload #17
    //   1504: sipush #256
    //   1507: if_icmpge -> 1741
    //   1510: sipush #12042
    //   1513: sipush #-7441
    //   1516: invokestatic a : (II)Ljava/lang/String;
    //   1519: iload #17
    //   1521: iconst_1
    //   1522: iushr
    //   1523: invokevirtual charAt : (I)C
    //   1526: istore #26
    //   1528: iload #17
    //   1530: iconst_1
    //   1531: iand
    //   1532: ifne -> 1547
    //   1535: iload #26
    //   1537: bipush #8
    //   1539: iushr
    //   1540: goto -> 1549
    //   1543: invokestatic a : (Ljava/lang/Throwable;)Ljava/lang/Throwable;
    //   1546: athrow
    //   1547: iload #26
    //   1549: i2b
    //   1550: sipush #255
    //   1553: iand
    //   1554: istore #16
    //   1556: iload #17
    //   1558: iconst_1
    //   1559: ishl
    //   1560: istore #18
    //   1562: iload #18
    //   1564: sipush #256
    //   1567: if_icmplt -> 1577
    //   1570: iload #18
    //   1572: iload #15
    //   1574: ixor
    //   1575: istore #18
    //   1577: iload #18
    //   1579: iconst_1
    //   1580: ishl
    //   1581: istore #19
    //   1583: iload #19
    //   1585: sipush #256
    //   1588: if_icmplt -> 1598
    //   1591: iload #19
    //   1593: iload #15
    //   1595: ixor
    //   1596: istore #19
    //   1598: iload #19
    //   1600: iconst_1
    //   1601: ishl
    //   1602: istore #20
    //   1604: iload #20
    //   1606: sipush #256
    //   1609: if_icmplt -> 1619
    //   1612: iload #20
    //   1614: iload #15
    //   1616: ixor
    //   1617: istore #20
    //   1619: iload #20
    //   1621: iload #17
    //   1623: ixor
    //   1624: istore #21
    //   1626: iload #21
    //   1628: iload #18
    //   1630: ixor
    //   1631: istore #22
    //   1633: iload #21
    //   1635: iload #19
    //   1637: ixor
    //   1638: istore #23
    //   1640: iload #20
    //   1642: iload #19
    //   1644: ixor
    //   1645: iload #18
    //   1647: ixor
    //   1648: istore #24
    //   1650: aload #9
    //   1652: iload #17
    //   1654: iload #16
    //   1656: i2b
    //   1657: bastore
    //   1658: aload #10
    //   1660: iload #16
    //   1662: iload #24
    //   1664: bipush #24
    //   1666: ishl
    //   1667: iload #21
    //   1669: bipush #16
    //   1671: ishl
    //   1672: ior
    //   1673: iload #23
    //   1675: bipush #8
    //   1677: ishl
    //   1678: ior
    //   1679: iload #22
    //   1681: ior
    //   1682: dup
    //   1683: istore #25
    //   1685: iastore
    //   1686: aload #11
    //   1688: iload #16
    //   1690: iload #25
    //   1692: bipush #8
    //   1694: iushr
    //   1695: iload #25
    //   1697: bipush #24
    //   1699: ishl
    //   1700: ior
    //   1701: iastore
    //   1702: aload #12
    //   1704: iload #16
    //   1706: iload #25
    //   1708: bipush #16
    //   1710: iushr
    //   1711: iload #25
    //   1713: bipush #16
    //   1715: ishl
    //   1716: ior
    //   1717: iastore
    //   1718: aload #13
    //   1720: iload #16
    //   1722: iload #25
    //   1724: bipush #24
    //   1726: iushr
    //   1727: iload #25
    //   1729: bipush #8
    //   1731: ishl
    //   1732: ior
    //   1733: iastore
    //   1734: iinc #17, 1
    //   1737: iload_2
    //   1738: ifeq -> 1502
    //   1741: iconst_1
    //   1742: istore #26
    //   1744: aload #14
    //   1746: iconst_0
    //   1747: iload #26
    //   1749: bipush #24
    //   1751: ishl
    //   1752: iastore
    //   1753: iconst_1
    //   1754: istore #27
    //   1756: iload #27
    //   1758: bipush #10
    //   1760: if_icmpge -> 1801
    //   1763: iload #26
    //   1765: iconst_1
    //   1766: ishl
    //   1767: istore #26
    //   1769: iload #26
    //   1771: sipush #256
    //   1774: if_icmplt -> 1784
    //   1777: iload #26
    //   1779: iload #15
    //   1781: ixor
    //   1782: istore #26
    //   1784: aload #14
    //   1786: iload #27
    //   1788: iload #26
    //   1790: bipush #24
    //   1792: ishl
    //   1793: iastore
    //   1794: iinc #27, 1
    //   1797: iload_2
    //   1798: ifeq -> 1756
    //   1801: iconst_4
    //   1802: istore #27
    //   1804: iload #27
    //   1806: bipush #6
    //   1808: iadd
    //   1809: istore #28
    //   1811: iconst_4
    //   1812: iload #28
    //   1814: iconst_1
    //   1815: iadd
    //   1816: imul
    //   1817: istore #29
    //   1819: iload #29
    //   1821: newarray int
    //   1823: astore #30
    //   1825: iload #29
    //   1827: newarray int
    //   1829: astore #31
    //   1831: iconst_0
    //   1832: istore #26
    //   1834: iconst_0
    //   1835: istore #33
    //   1837: iconst_0
    //   1838: istore #34
    //   1840: iload #33
    //   1842: iload #27
    //   1844: if_icmpge -> 1912
    //   1847: aload #30
    //   1849: iload #33
    //   1851: aload #6
    //   1853: iload #34
    //   1855: baload
    //   1856: bipush #24
    //   1858: ishl
    //   1859: aload #6
    //   1861: iload #34
    //   1863: iconst_1
    //   1864: iadd
    //   1865: baload
    //   1866: sipush #255
    //   1869: iand
    //   1870: bipush #16
    //   1872: ishl
    //   1873: ior
    //   1874: aload #6
    //   1876: iload #34
    //   1878: iconst_2
    //   1879: iadd
    //   1880: baload
    //   1881: sipush #255
    //   1884: iand
    //   1885: bipush #8
    //   1887: ishl
    //   1888: ior
    //   1889: aload #6
    //   1891: iload #34
    //   1893: iconst_3
    //   1894: iadd
    //   1895: baload
    //   1896: sipush #255
    //   1899: iand
    //   1900: ior
    //   1901: iastore
    //   1902: iinc #33, 1
    //   1905: iinc #34, 4
    //   1908: iload_2
    //   1909: ifeq -> 1840
    //   1912: iload #27
    //   1914: istore #33
    //   1916: iconst_0
    //   1917: istore #34
    //   1919: iload #33
    //   1921: iload #29
    //   1923: if_icmpge -> 2050
    //   1926: aload #30
    //   1928: iload #33
    //   1930: iconst_1
    //   1931: isub
    //   1932: iaload
    //   1933: istore #32
    //   1935: iload #34
    //   1937: ifne -> 2024
    //   1940: iload #27
    //   1942: istore #34
    //   1944: aload #9
    //   1946: iload #32
    //   1948: bipush #16
    //   1950: iushr
    //   1951: sipush #255
    //   1954: iand
    //   1955: baload
    //   1956: bipush #24
    //   1958: ishl
    //   1959: aload #9
    //   1961: iload #32
    //   1963: bipush #8
    //   1965: iushr
    //   1966: sipush #255
    //   1969: iand
    //   1970: baload
    //   1971: sipush #255
    //   1974: iand
    //   1975: bipush #16
    //   1977: ishl
    //   1978: ior
    //   1979: aload #9
    //   1981: iload #32
    //   1983: sipush #255
    //   1986: iand
    //   1987: baload
    //   1988: sipush #255
    //   1991: iand
    //   1992: bipush #8
    //   1994: ishl
    //   1995: ior
    //   1996: aload #9
    //   1998: iload #32
    //   2000: bipush #24
    //   2002: iushr
    //   2003: baload
    //   2004: sipush #255
    //   2007: iand
    //   2008: ior
    //   2009: istore #32
    //   2011: iload #32
    //   2013: aload #14
    //   2015: iload #26
    //   2017: iinc #26, 1
    //   2020: iaload
    //   2021: ixor
    //   2022: istore #32
    //   2024: aload #30
    //   2026: iload #33
    //   2028: aload #30
    //   2030: iload #33
    //   2032: iload #27
    //   2034: isub
    //   2035: iaload
    //   2036: iload #32
    //   2038: ixor
    //   2039: iastore
    //   2040: iinc #33, 1
    //   2043: iinc #34, -1
    //   2046: iload_2
    //   2047: ifeq -> 1919
    //   2050: iconst_0
    //   2051: istore #33
    //   2053: iconst_4
    //   2054: iload #28
    //   2056: imul
    //   2057: istore #34
    //   2059: aload #31
    //   2061: iload #33
    //   2063: aload #30
    //   2065: iload #34
    //   2067: iaload
    //   2068: iastore
    //   2069: aload #31
    //   2071: iload #33
    //   2073: iconst_1
    //   2074: iadd
    //   2075: aload #30
    //   2077: iload #34
    //   2079: iconst_1
    //   2080: iadd
    //   2081: iaload
    //   2082: iastore
    //   2083: aload #31
    //   2085: iload #33
    //   2087: iconst_2
    //   2088: iadd
    //   2089: aload #30
    //   2091: iload #34
    //   2093: iconst_2
    //   2094: iadd
    //   2095: iaload
    //   2096: iastore
    //   2097: aload #31
    //   2099: iload #33
    //   2101: iconst_3
    //   2102: iadd
    //   2103: aload #30
    //   2105: iload #34
    //   2107: iconst_3
    //   2108: iadd
    //   2109: iaload
    //   2110: iastore
    //   2111: iinc #33, 4
    //   2114: iinc #34, -4
    //   2117: iconst_1
    //   2118: istore #36
    //   2120: iload #36
    //   2122: iload #28
    //   2124: if_icmpge -> 2488
    //   2127: aload #30
    //   2129: iload #34
    //   2131: iaload
    //   2132: istore #35
    //   2134: aload #31
    //   2136: iload #33
    //   2138: aload #10
    //   2140: aload #9
    //   2142: iload #35
    //   2144: bipush #24
    //   2146: iushr
    //   2147: baload
    //   2148: sipush #255
    //   2151: iand
    //   2152: iaload
    //   2153: aload #11
    //   2155: aload #9
    //   2157: iload #35
    //   2159: bipush #16
    //   2161: iushr
    //   2162: sipush #255
    //   2165: iand
    //   2166: baload
    //   2167: sipush #255
    //   2170: iand
    //   2171: iaload
    //   2172: ixor
    //   2173: aload #12
    //   2175: aload #9
    //   2177: iload #35
    //   2179: bipush #8
    //   2181: iushr
    //   2182: sipush #255
    //   2185: iand
    //   2186: baload
    //   2187: sipush #255
    //   2190: iand
    //   2191: iaload
    //   2192: ixor
    //   2193: aload #13
    //   2195: aload #9
    //   2197: iload #35
    //   2199: sipush #255
    //   2202: iand
    //   2203: baload
    //   2204: sipush #255
    //   2207: iand
    //   2208: iaload
    //   2209: ixor
    //   2210: iastore
    //   2211: aload #30
    //   2213: iload #34
    //   2215: iconst_1
    //   2216: iadd
    //   2217: iaload
    //   2218: istore #35
    //   2220: aload #31
    //   2222: iload #33
    //   2224: iconst_1
    //   2225: iadd
    //   2226: aload #10
    //   2228: aload #9
    //   2230: iload #35
    //   2232: bipush #24
    //   2234: iushr
    //   2235: baload
    //   2236: sipush #255
    //   2239: iand
    //   2240: iaload
    //   2241: aload #11
    //   2243: aload #9
    //   2245: iload #35
    //   2247: bipush #16
    //   2249: iushr
    //   2250: sipush #255
    //   2253: iand
    //   2254: baload
    //   2255: sipush #255
    //   2258: iand
    //   2259: iaload
    //   2260: ixor
    //   2261: aload #12
    //   2263: aload #9
    //   2265: iload #35
    //   2267: bipush #8
    //   2269: iushr
    //   2270: sipush #255
    //   2273: iand
    //   2274: baload
    //   2275: sipush #255
    //   2278: iand
    //   2279: iaload
    //   2280: ixor
    //   2281: aload #13
    //   2283: aload #9
    //   2285: iload #35
    //   2287: sipush #255
    //   2290: iand
    //   2291: baload
    //   2292: sipush #255
    //   2295: iand
    //   2296: iaload
    //   2297: ixor
    //   2298: iastore
    //   2299: aload #30
    //   2301: iload #34
    //   2303: iconst_2
    //   2304: iadd
    //   2305: iaload
    //   2306: istore #35
    //   2308: aload #31
    //   2310: iload #33
    //   2312: iconst_2
    //   2313: iadd
    //   2314: aload #10
    //   2316: aload #9
    //   2318: iload #35
    //   2320: bipush #24
    //   2322: iushr
    //   2323: baload
    //   2324: sipush #255
    //   2327: iand
    //   2328: iaload
    //   2329: aload #11
    //   2331: aload #9
    //   2333: iload #35
    //   2335: bipush #16
    //   2337: iushr
    //   2338: sipush #255
    //   2341: iand
    //   2342: baload
    //   2343: sipush #255
    //   2346: iand
    //   2347: iaload
    //   2348: ixor
    //   2349: aload #12
    //   2351: aload #9
    //   2353: iload #35
    //   2355: bipush #8
    //   2357: iushr
    //   2358: sipush #255
    //   2361: iand
    //   2362: baload
    //   2363: sipush #255
    //   2366: iand
    //   2367: iaload
    //   2368: ixor
    //   2369: aload #13
    //   2371: aload #9
    //   2373: iload #35
    //   2375: sipush #255
    //   2378: iand
    //   2379: baload
    //   2380: sipush #255
    //   2383: iand
    //   2384: iaload
    //   2385: ixor
    //   2386: iastore
    //   2387: aload #30
    //   2389: iload #34
    //   2391: iconst_3
    //   2392: iadd
    //   2393: iaload
    //   2394: istore #35
    //   2396: aload #31
    //   2398: iload #33
    //   2400: iconst_3
    //   2401: iadd
    //   2402: aload #10
    //   2404: aload #9
    //   2406: iload #35
    //   2408: bipush #24
    //   2410: iushr
    //   2411: baload
    //   2412: sipush #255
    //   2415: iand
    //   2416: iaload
    //   2417: aload #11
    //   2419: aload #9
    //   2421: iload #35
    //   2423: bipush #16
    //   2425: iushr
    //   2426: sipush #255
    //   2429: iand
    //   2430: baload
    //   2431: sipush #255
    //   2434: iand
    //   2435: iaload
    //   2436: ixor
    //   2437: aload #12
    //   2439: aload #9
    //   2441: iload #35
    //   2443: bipush #8
    //   2445: iushr
    //   2446: sipush #255
    //   2449: iand
    //   2450: baload
    //   2451: sipush #255
    //   2454: iand
    //   2455: iaload
    //   2456: ixor
    //   2457: aload #13
    //   2459: aload #9
    //   2461: iload #35
    //   2463: sipush #255
    //   2466: iand
    //   2467: baload
    //   2468: sipush #255
    //   2471: iand
    //   2472: iaload
    //   2473: ixor
    //   2474: iastore
    //   2475: iinc #33, 4
    //   2478: iinc #34, -4
    //   2481: iinc #36, 1
    //   2484: iload_2
    //   2485: ifeq -> 2120
    //   2488: aload #31
    //   2490: iload #33
    //   2492: aload #30
    //   2494: iload #34
    //   2496: iaload
    //   2497: iastore
    //   2498: aload #31
    //   2500: iload #33
    //   2502: iconst_1
    //   2503: iadd
    //   2504: aload #30
    //   2506: iload #34
    //   2508: iconst_1
    //   2509: iadd
    //   2510: iaload
    //   2511: iastore
    //   2512: aload #31
    //   2514: iload #33
    //   2516: iconst_2
    //   2517: iadd
    //   2518: aload #30
    //   2520: iload #34
    //   2522: iconst_2
    //   2523: iadd
    //   2524: iaload
    //   2525: iastore
    //   2526: aload #31
    //   2528: iload #33
    //   2530: iconst_3
    //   2531: iadd
    //   2532: aload #30
    //   2534: iload #34
    //   2536: iconst_3
    //   2537: iadd
    //   2538: iaload
    //   2539: iastore
    //   2540: iconst_0
    //   2541: newarray byte
    //   2543: astore #36
    //   2545: aload #7
    //   2547: arraylength
    //   2548: bipush #16
    //   2550: irem
    //   2551: ifeq -> 2575
    //   2554: new java/lang/Exception
    //   2557: dup
    //   2558: sipush #12059
    //   2561: sipush #-26931
    //   2564: invokestatic a : (II)Ljava/lang/String;
    //   2567: invokespecial <init> : (Ljava/lang/String;)V
    //   2570: athrow
    //   2571: invokestatic a : (Ljava/lang/Throwable;)Ljava/lang/Throwable;
    //   2574: athrow
    //   2575: bipush #10
    //   2577: istore #37
    //   2579: sipush #12057
    //   2582: sipush #256
    //   2585: newarray byte
    //   2587: astore #38
    //   2589: sipush #-12537
    //   2592: sipush #256
    //   2595: newarray int
    //   2597: astore #39
    //   2599: sipush #256
    //   2602: newarray int
    //   2604: astore #40
    //   2606: sipush #256
    //   2609: newarray int
    //   2611: astore #41
    //   2613: sipush #256
    //   2616: newarray int
    //   2618: astore #42
    //   2620: sipush #283
    //   2623: istore #15
    //   2625: invokestatic a : (II)Ljava/lang/String;
    //   2628: astore #43
    //   2630: iconst_0
    //   2631: istore #17
    //   2633: iload #17
    //   2635: sipush #256
    //   2638: if_icmpge -> 2865
    //   2641: aload #43
    //   2643: iload #17
    //   2645: iconst_1
    //   2646: iushr
    //   2647: invokevirtual charAt : (I)C
    //   2650: istore #44
    //   2652: iload #17
    //   2654: iconst_1
    //   2655: iand
    //   2656: ifne -> 2671
    //   2659: iload #44
    //   2661: bipush #8
    //   2663: iushr
    //   2664: goto -> 2673
    //   2667: invokestatic a : (Ljava/lang/Throwable;)Ljava/lang/Throwable;
    //   2670: athrow
    //   2671: iload #44
    //   2673: i2b
    //   2674: sipush #255
    //   2677: iand
    //   2678: istore #16
    //   2680: iload #17
    //   2682: iconst_1
    //   2683: ishl
    //   2684: istore #18
    //   2686: iload #18
    //   2688: sipush #256
    //   2691: if_icmplt -> 2701
    //   2694: iload #18
    //   2696: iload #15
    //   2698: ixor
    //   2699: istore #18
    //   2701: iload #18
    //   2703: iconst_1
    //   2704: ishl
    //   2705: istore #19
    //   2707: iload #19
    //   2709: sipush #256
    //   2712: if_icmplt -> 2722
    //   2715: iload #19
    //   2717: iload #15
    //   2719: ixor
    //   2720: istore #19
    //   2722: iload #19
    //   2724: iconst_1
    //   2725: ishl
    //   2726: istore #20
    //   2728: iload #20
    //   2730: sipush #256
    //   2733: if_icmplt -> 2743
    //   2736: iload #20
    //   2738: iload #15
    //   2740: ixor
    //   2741: istore #20
    //   2743: iload #20
    //   2745: iload #17
    //   2747: ixor
    //   2748: istore #21
    //   2750: iload #21
    //   2752: iload #18
    //   2754: ixor
    //   2755: istore #22
    //   2757: iload #21
    //   2759: iload #19
    //   2761: ixor
    //   2762: istore #23
    //   2764: iload #20
    //   2766: iload #19
    //   2768: ixor
    //   2769: iload #18
    //   2771: ixor
    //   2772: istore #24
    //   2774: aload #38
    //   2776: iload #16
    //   2778: iload #17
    //   2780: i2b
    //   2781: bastore
    //   2782: aload #39
    //   2784: iload #16
    //   2786: iload #24
    //   2788: bipush #24
    //   2790: ishl
    //   2791: iload #21
    //   2793: bipush #16
    //   2795: ishl
    //   2796: ior
    //   2797: iload #23
    //   2799: bipush #8
    //   2801: ishl
    //   2802: ior
    //   2803: iload #22
    //   2805: ior
    //   2806: dup
    //   2807: istore #25
    //   2809: iastore
    //   2810: aload #40
    //   2812: iload #16
    //   2814: iload #25
    //   2816: bipush #8
    //   2818: iushr
    //   2819: iload #25
    //   2821: bipush #24
    //   2823: ishl
    //   2824: ior
    //   2825: iastore
    //   2826: aload #41
    //   2828: iload #16
    //   2830: iload #25
    //   2832: bipush #16
    //   2834: iushr
    //   2835: iload #25
    //   2837: bipush #16
    //   2839: ishl
    //   2840: ior
    //   2841: iastore
    //   2842: aload #42
    //   2844: iload #16
    //   2846: iload #25
    //   2848: bipush #24
    //   2850: iushr
    //   2851: iload #25
    //   2853: bipush #8
    //   2855: ishl
    //   2856: ior
    //   2857: iastore
    //   2858: iinc #17, 1
    //   2861: iload_2
    //   2862: ifeq -> 2633
    //   2865: aload #7
    //   2867: arraylength
    //   2868: newarray byte
    //   2870: astore #44
    //   2872: iconst_0
    //   2873: istore #45
    //   2875: iload #45
    //   2877: aload #7
    //   2879: arraylength
    //   2880: bipush #16
    //   2882: idiv
    //   2883: if_icmpge -> 3797
    //   2886: bipush #16
    //   2888: newarray byte
    //   2890: astore #46
    //   2892: bipush #16
    //   2894: newarray byte
    //   2896: astore #47
    //   2898: iconst_0
    //   2899: istore #48
    //   2901: iload #48
    //   2903: bipush #16
    //   2905: if_icmpge -> 2931
    //   2908: aload #46
    //   2910: iload #48
    //   2912: aload #7
    //   2914: iload #48
    //   2916: iload #45
    //   2918: bipush #16
    //   2920: imul
    //   2921: iadd
    //   2922: baload
    //   2923: bastore
    //   2924: iinc #48, 1
    //   2927: iload_2
    //   2928: ifeq -> 2901
    //   2931: iconst_0
    //   2932: istore #48
    //   2934: aload #46
    //   2936: iconst_0
    //   2937: baload
    //   2938: bipush #24
    //   2940: ishl
    //   2941: aload #46
    //   2943: iconst_1
    //   2944: baload
    //   2945: sipush #255
    //   2948: iand
    //   2949: bipush #16
    //   2951: ishl
    //   2952: ior
    //   2953: aload #46
    //   2955: iconst_2
    //   2956: baload
    //   2957: sipush #255
    //   2960: iand
    //   2961: bipush #8
    //   2963: ishl
    //   2964: ior
    //   2965: aload #46
    //   2967: iconst_3
    //   2968: baload
    //   2969: sipush #255
    //   2972: iand
    //   2973: ior
    //   2974: aload #31
    //   2976: iconst_0
    //   2977: iaload
    //   2978: ixor
    //   2979: istore #50
    //   2981: aload #46
    //   2983: iconst_4
    //   2984: baload
    //   2985: bipush #24
    //   2987: ishl
    //   2988: aload #46
    //   2990: iconst_5
    //   2991: baload
    //   2992: sipush #255
    //   2995: iand
    //   2996: bipush #16
    //   2998: ishl
    //   2999: ior
    //   3000: aload #46
    //   3002: bipush #6
    //   3004: baload
    //   3005: sipush #255
    //   3008: iand
    //   3009: bipush #8
    //   3011: ishl
    //   3012: ior
    //   3013: aload #46
    //   3015: bipush #7
    //   3017: baload
    //   3018: sipush #255
    //   3021: iand
    //   3022: ior
    //   3023: aload #31
    //   3025: iconst_1
    //   3026: iaload
    //   3027: ixor
    //   3028: istore #51
    //   3030: aload #46
    //   3032: bipush #8
    //   3034: baload
    //   3035: bipush #24
    //   3037: ishl
    //   3038: aload #46
    //   3040: bipush #9
    //   3042: baload
    //   3043: sipush #255
    //   3046: iand
    //   3047: bipush #16
    //   3049: ishl
    //   3050: ior
    //   3051: aload #46
    //   3053: bipush #10
    //   3055: baload
    //   3056: sipush #255
    //   3059: iand
    //   3060: bipush #8
    //   3062: ishl
    //   3063: ior
    //   3064: aload #46
    //   3066: bipush #11
    //   3068: baload
    //   3069: sipush #255
    //   3072: iand
    //   3073: ior
    //   3074: aload #31
    //   3076: iconst_2
    //   3077: iaload
    //   3078: ixor
    //   3079: istore #52
    //   3081: aload #46
    //   3083: bipush #12
    //   3085: baload
    //   3086: bipush #24
    //   3088: ishl
    //   3089: aload #46
    //   3091: bipush #13
    //   3093: baload
    //   3094: sipush #255
    //   3097: iand
    //   3098: bipush #16
    //   3100: ishl
    //   3101: ior
    //   3102: aload #46
    //   3104: bipush #14
    //   3106: baload
    //   3107: sipush #255
    //   3110: iand
    //   3111: bipush #8
    //   3113: ishl
    //   3114: ior
    //   3115: aload #46
    //   3117: bipush #15
    //   3119: baload
    //   3120: sipush #255
    //   3123: iand
    //   3124: ior
    //   3125: aload #31
    //   3127: iconst_3
    //   3128: iaload
    //   3129: ixor
    //   3130: istore #53
    //   3132: iconst_1
    //   3133: istore #54
    //   3135: iload #54
    //   3137: iload #37
    //   3139: if_icmpge -> 3382
    //   3142: iinc #48, 4
    //   3145: aload #39
    //   3147: iload #50
    //   3149: bipush #24
    //   3151: iushr
    //   3152: iaload
    //   3153: aload #40
    //   3155: iload #53
    //   3157: bipush #16
    //   3159: iushr
    //   3160: sipush #255
    //   3163: iand
    //   3164: iaload
    //   3165: ixor
    //   3166: aload #41
    //   3168: iload #52
    //   3170: bipush #8
    //   3172: iushr
    //   3173: sipush #255
    //   3176: iand
    //   3177: iaload
    //   3178: ixor
    //   3179: aload #42
    //   3181: iload #51
    //   3183: sipush #255
    //   3186: iand
    //   3187: iaload
    //   3188: ixor
    //   3189: aload #31
    //   3191: iload #48
    //   3193: iaload
    //   3194: ixor
    //   3195: istore #55
    //   3197: aload #39
    //   3199: iload #51
    //   3201: bipush #24
    //   3203: iushr
    //   3204: iaload
    //   3205: aload #40
    //   3207: iload #50
    //   3209: bipush #16
    //   3211: iushr
    //   3212: sipush #255
    //   3215: iand
    //   3216: iaload
    //   3217: ixor
    //   3218: aload #41
    //   3220: iload #53
    //   3222: bipush #8
    //   3224: iushr
    //   3225: sipush #255
    //   3228: iand
    //   3229: iaload
    //   3230: ixor
    //   3231: aload #42
    //   3233: iload #52
    //   3235: sipush #255
    //   3238: iand
    //   3239: iaload
    //   3240: ixor
    //   3241: aload #31
    //   3243: iload #48
    //   3245: iconst_1
    //   3246: iadd
    //   3247: iaload
    //   3248: ixor
    //   3249: istore #56
    //   3251: aload #39
    //   3253: iload #52
    //   3255: bipush #24
    //   3257: iushr
    //   3258: iaload
    //   3259: aload #40
    //   3261: iload #51
    //   3263: bipush #16
    //   3265: iushr
    //   3266: sipush #255
    //   3269: iand
    //   3270: iaload
    //   3271: ixor
    //   3272: aload #41
    //   3274: iload #50
    //   3276: bipush #8
    //   3278: iushr
    //   3279: sipush #255
    //   3282: iand
    //   3283: iaload
    //   3284: ixor
    //   3285: aload #42
    //   3287: iload #53
    //   3289: sipush #255
    //   3292: iand
    //   3293: iaload
    //   3294: ixor
    //   3295: aload #31
    //   3297: iload #48
    //   3299: iconst_2
    //   3300: iadd
    //   3301: iaload
    //   3302: ixor
    //   3303: istore #57
    //   3305: aload #39
    //   3307: iload #53
    //   3309: bipush #24
    //   3311: iushr
    //   3312: iaload
    //   3313: aload #40
    //   3315: iload #52
    //   3317: bipush #16
    //   3319: iushr
    //   3320: sipush #255
    //   3323: iand
    //   3324: iaload
    //   3325: ixor
    //   3326: aload #41
    //   3328: iload #51
    //   3330: bipush #8
    //   3332: iushr
    //   3333: sipush #255
    //   3336: iand
    //   3337: iaload
    //   3338: ixor
    //   3339: aload #42
    //   3341: iload #50
    //   3343: sipush #255
    //   3346: iand
    //   3347: iaload
    //   3348: ixor
    //   3349: aload #31
    //   3351: iload #48
    //   3353: iconst_3
    //   3354: iadd
    //   3355: iaload
    //   3356: ixor
    //   3357: istore #58
    //   3359: iload #55
    //   3361: istore #50
    //   3363: iload #56
    //   3365: istore #51
    //   3367: iload #57
    //   3369: istore #52
    //   3371: iload #58
    //   3373: istore #53
    //   3375: iinc #54, 1
    //   3378: iload_2
    //   3379: ifeq -> 3135
    //   3382: iinc #48, 4
    //   3385: aload #31
    //   3387: iload #48
    //   3389: iaload
    //   3390: istore #49
    //   3392: aload #47
    //   3394: iconst_0
    //   3395: aload #38
    //   3397: iload #50
    //   3399: bipush #24
    //   3401: iushr
    //   3402: baload
    //   3403: iload #49
    //   3405: bipush #24
    //   3407: iushr
    //   3408: ixor
    //   3409: i2b
    //   3410: bastore
    //   3411: aload #47
    //   3413: iconst_1
    //   3414: aload #38
    //   3416: iload #53
    //   3418: bipush #16
    //   3420: iushr
    //   3421: sipush #255
    //   3424: iand
    //   3425: baload
    //   3426: iload #49
    //   3428: bipush #16
    //   3430: iushr
    //   3431: ixor
    //   3432: i2b
    //   3433: bastore
    //   3434: aload #47
    //   3436: iconst_2
    //   3437: aload #38
    //   3439: iload #52
    //   3441: bipush #8
    //   3443: iushr
    //   3444: sipush #255
    //   3447: iand
    //   3448: baload
    //   3449: iload #49
    //   3451: bipush #8
    //   3453: iushr
    //   3454: ixor
    //   3455: i2b
    //   3456: bastore
    //   3457: aload #47
    //   3459: iconst_3
    //   3460: aload #38
    //   3462: iload #51
    //   3464: sipush #255
    //   3467: iand
    //   3468: baload
    //   3469: iload #49
    //   3471: ixor
    //   3472: i2b
    //   3473: bastore
    //   3474: aload #31
    //   3476: iload #48
    //   3478: iconst_1
    //   3479: iadd
    //   3480: iaload
    //   3481: istore #49
    //   3483: aload #47
    //   3485: iconst_4
    //   3486: aload #38
    //   3488: iload #51
    //   3490: bipush #24
    //   3492: iushr
    //   3493: baload
    //   3494: iload #49
    //   3496: bipush #24
    //   3498: iushr
    //   3499: ixor
    //   3500: i2b
    //   3501: bastore
    //   3502: aload #47
    //   3504: iconst_5
    //   3505: aload #38
    //   3507: iload #50
    //   3509: bipush #16
    //   3511: iushr
    //   3512: sipush #255
    //   3515: iand
    //   3516: baload
    //   3517: iload #49
    //   3519: bipush #16
    //   3521: iushr
    //   3522: ixor
    //   3523: i2b
    //   3524: bastore
    //   3525: aload #47
    //   3527: bipush #6
    //   3529: aload #38
    //   3531: iload #53
    //   3533: bipush #8
    //   3535: iushr
    //   3536: sipush #255
    //   3539: iand
    //   3540: baload
    //   3541: iload #49
    //   3543: bipush #8
    //   3545: iushr
    //   3546: ixor
    //   3547: i2b
    //   3548: bastore
    //   3549: aload #47
    //   3551: bipush #7
    //   3553: aload #38
    //   3555: iload #52
    //   3557: sipush #255
    //   3560: iand
    //   3561: baload
    //   3562: iload #49
    //   3564: ixor
    //   3565: i2b
    //   3566: bastore
    //   3567: aload #31
    //   3569: iload #48
    //   3571: iconst_2
    //   3572: iadd
    //   3573: iaload
    //   3574: istore #49
    //   3576: aload #47
    //   3578: bipush #8
    //   3580: aload #38
    //   3582: iload #52
    //   3584: bipush #24
    //   3586: iushr
    //   3587: baload
    //   3588: iload #49
    //   3590: bipush #24
    //   3592: iushr
    //   3593: ixor
    //   3594: i2b
    //   3595: bastore
    //   3596: aload #47
    //   3598: bipush #9
    //   3600: aload #38
    //   3602: iload #51
    //   3604: bipush #16
    //   3606: iushr
    //   3607: sipush #255
    //   3610: iand
    //   3611: baload
    //   3612: iload #49
    //   3614: bipush #16
    //   3616: iushr
    //   3617: ixor
    //   3618: i2b
    //   3619: bastore
    //   3620: aload #47
    //   3622: bipush #10
    //   3624: aload #38
    //   3626: iload #50
    //   3628: bipush #8
    //   3630: iushr
    //   3631: sipush #255
    //   3634: iand
    //   3635: baload
    //   3636: iload #49
    //   3638: bipush #8
    //   3640: iushr
    //   3641: ixor
    //   3642: i2b
    //   3643: bastore
    //   3644: aload #47
    //   3646: bipush #11
    //   3648: aload #38
    //   3650: iload #53
    //   3652: sipush #255
    //   3655: iand
    //   3656: baload
    //   3657: iload #49
    //   3659: ixor
    //   3660: i2b
    //   3661: bastore
    //   3662: aload #31
    //   3664: iload #48
    //   3666: iconst_3
    //   3667: iadd
    //   3668: iaload
    //   3669: istore #49
    //   3671: aload #47
    //   3673: bipush #12
    //   3675: aload #38
    //   3677: iload #53
    //   3679: bipush #24
    //   3681: iushr
    //   3682: baload
    //   3683: iload #49
    //   3685: bipush #24
    //   3687: iushr
    //   3688: ixor
    //   3689: i2b
    //   3690: bastore
    //   3691: aload #47
    //   3693: bipush #13
    //   3695: aload #38
    //   3697: iload #52
    //   3699: bipush #16
    //   3701: iushr
    //   3702: sipush #255
    //   3705: iand
    //   3706: baload
    //   3707: iload #49
    //   3709: bipush #16
    //   3711: iushr
    //   3712: ixor
    //   3713: i2b
    //   3714: bastore
    //   3715: aload #47
    //   3717: bipush #14
    //   3719: aload #38
    //   3721: iload #51
    //   3723: bipush #8
    //   3725: iushr
    //   3726: sipush #255
    //   3729: iand
    //   3730: baload
    //   3731: iload #49
    //   3733: bipush #8
    //   3735: iushr
    //   3736: ixor
    //   3737: i2b
    //   3738: bastore
    //   3739: aload #47
    //   3741: bipush #15
    //   3743: aload #38
    //   3745: iload #50
    //   3747: sipush #255
    //   3750: iand
    //   3751: baload
    //   3752: iload #49
    //   3754: ixor
    //   3755: i2b
    //   3756: bastore
    //   3757: iconst_0
    //   3758: istore #54
    //   3760: iload #54
    //   3762: bipush #16
    //   3764: if_icmpge -> 3790
    //   3767: aload #44
    //   3769: iload #54
    //   3771: iload #45
    //   3773: bipush #16
    //   3775: imul
    //   3776: iadd
    //   3777: aload #47
    //   3779: iload #54
    //   3781: baload
    //   3782: bastore
    //   3783: iinc #54, 1
    //   3786: iload_2
    //   3787: ifeq -> 3760
    //   3790: iinc #45, 1
    //   3793: iload_2
    //   3794: ifeq -> 2875
    //   3797: aload #44
    //   3799: arraylength
    //   3800: ifle -> 3881
    //   3803: aload #44
    //   3805: aload #44
    //   3807: arraylength
    //   3808: iconst_1
    //   3809: isub
    //   3810: baload
    //   3811: istore #45
    //   3813: iload #45
    //   3815: bipush #16
    //   3817: if_icmple -> 3828
    //   3820: aload #44
    //   3822: astore #36
    //   3824: iload_2
    //   3825: ifeq -> 3881
    //   3828: aload #44
    //   3830: arraylength
    //   3831: iload #45
    //   3833: isub
    //   3834: newarray byte
    //   3836: astore #36
    //   3838: iconst_0
    //   3839: istore #46
    //   3841: iload #46
    //   3843: aload #36
    //   3845: arraylength
    //   3846: if_icmpge -> 3881
    //   3849: iload #46
    //   3851: aload #44
    //   3853: arraylength
    //   3854: if_icmpge -> 3881
    //   3857: aload #36
    //   3859: iload #46
    //   3861: aload #44
    //   3863: iload #46
    //   3865: baload
    //   3866: bastore
    //   3867: iinc #46, 1
    //   3870: iload_2
    //   3871: ifeq -> 3841
    //   3874: goto -> 3881
    //   3877: invokestatic a : (Ljava/lang/Throwable;)Ljava/lang/Throwable;
    //   3880: athrow
    //   3881: aload #36
    //   3883: astore #8
    //   3885: sipush #12055
    //   3888: new java/math/BigInteger
    //   3891: dup
    //   3892: aload #8
    //   3894: invokespecial <init> : ([B)V
    //   3897: invokevirtual abs : ()Ljava/math/BigInteger;
    //   3900: putstatic burp/Zix.ZO : Ljava/lang/Object;
    //   3903: sipush #26461
    //   3906: invokestatic a : (II)Ljava/lang/String;
    //   3909: iconst_1
    //   3910: ldc burp/Zvi
    //   3912: invokevirtual getClassLoader : ()Ljava/lang/ClassLoader;
    //   3915: invokestatic forName : (Ljava/lang/String;ZLjava/lang/ClassLoader;)Ljava/lang/Class;
    //   3918: invokevirtual getDeclaredFields : ()[Ljava/lang/reflect/Field;
    //   3921: astore #4
    //   3923: aload #4
    //   3925: arraylength
    //   3926: istore #5
    //   3928: iconst_0
    //   3929: istore #6
    //   3931: iload #6
    //   3933: iload #5
    //   3935: if_icmpge -> 4073
    //   3938: aload #4
    //   3940: iload #6
    //   3942: aaload
    //   3943: astore #7
    //   3945: aload #7
    //   3947: invokevirtual getModifiers : ()I
    //   3950: invokestatic isStatic : (I)Z
    //   3953: ifne -> 3963
    //   3956: goto -> 4066
    //   3959: invokestatic a : (Ljava/lang/Throwable;)Ljava/lang/Throwable;
    //   3962: athrow
    //   3963: aload #7
    //   3965: invokevirtual getType : ()Ljava/lang/Class;
    //   3968: astore #8
    //   3970: aload #8
    //   3972: ifnull -> 4053
    //   3975: aload #8
    //   3977: invokevirtual isPrimitive : ()Z
    //   3980: ifne -> 4053
    //   3983: goto -> 3990
    //   3986: invokestatic a : (Ljava/lang/Throwable;)Ljava/lang/Throwable;
    //   3989: athrow
    //   3990: aload #8
    //   3992: invokevirtual getPackage : ()Ljava/lang/Package;
    //   3995: ifnull -> 4053
    //   3998: goto -> 4005
    //   4001: invokestatic a : (Ljava/lang/Throwable;)Ljava/lang/Throwable;
    //   4004: athrow
    //   4005: aload #8
    //   4007: invokevirtual getPackage : ()Ljava/lang/Package;
    //   4010: invokevirtual getName : ()Ljava/lang/String;
    //   4013: ifnull -> 4053
    //   4016: goto -> 4023
    //   4019: invokestatic a : (Ljava/lang/Throwable;)Ljava/lang/Throwable;
    //   4022: athrow
    //   4023: aload #8
    //   4025: invokevirtual getPackage : ()Ljava/lang/Package;
    //   4028: invokevirtual getName : ()Ljava/lang/String;
    //   4031: sipush #12037
    //   4034: sipush #-7560
    //   4037: invokestatic a : (II)Ljava/lang/String;
    //   4040: invokevirtual startsWith : (Ljava/lang/String;)Z
    //   4043: ifne -> 4053
    //   4046: goto -> 4053
    //   4049: invokestatic a : (Ljava/lang/Throwable;)Ljava/lang/Throwable;
    //   4052: athrow
    //   4053: aload #7
    //   4055: iconst_1
    //   4056: invokevirtual setAccessible : (Z)V
    //   4059: aload #7
    //   4061: aconst_null
    //   4062: invokevirtual get : (Ljava/lang/Object;)Ljava/lang/Object;
    //   4065: pop
    //   4066: iinc #6, 1
    //   4069: iload_2
    //   4070: ifeq -> 3931
    //   4073: sipush #12052
    //   4076: sipush #24767
    //   4079: invokestatic a : (II)Ljava/lang/String;
    //   4082: invokestatic forName : (Ljava/lang/String;)Ljava/lang/Class;
    //   4085: invokevirtual getDeclaredMethods : ()[Ljava/lang/reflect/Method;
    //   4088: astore #4
    //   4090: aload #4
    //   4092: arraylength
    //   4093: istore #5
    //   4095: iconst_0
    //   4096: istore #6
    //   4098: iload #6
    //   4100: iload #5
    //   4102: if_icmpge -> 4235
    //   4105: aload #4
    //   4107: iload #6
    //   4109: aaload
    //   4110: astore #7
    //   4112: aload #7
    //   4114: invokevirtual getParameterTypes : ()[Ljava/lang/Class;
    //   4117: pop
    //   4118: aload #7
    //   4120: invokevirtual getModifiers : ()I
    //   4123: invokestatic isStatic : (I)Z
    //   4126: ifeq -> 4221
    //   4129: aload #7
    //   4131: invokevirtual getParameterTypes : ()[Ljava/lang/Class;
    //   4134: arraylength
    //   4135: iconst_2
    //   4136: if_icmpne -> 4221
    //   4139: goto -> 4146
    //   4142: invokestatic a : (Ljava/lang/Throwable;)Ljava/lang/Throwable;
    //   4145: athrow
    //   4146: aload #7
    //   4148: invokevirtual getReturnType : ()Ljava/lang/Class;
    //   4151: getstatic java/lang/Void.TYPE : Ljava/lang/Class;
    //   4154: invokevirtual equals : (Ljava/lang/Object;)Z
    //   4157: ifeq -> 4221
    //   4160: goto -> 4167
    //   4163: invokestatic a : (Ljava/lang/Throwable;)Ljava/lang/Throwable;
    //   4166: athrow
    //   4167: aload #7
    //   4169: iconst_1
    //   4170: invokevirtual setAccessible : (Z)V
    //   4173: aload #7
    //   4175: aconst_null
    //   4176: iconst_2
    //   4177: anewarray java/lang/Object
    //   4180: dup
    //   4181: iconst_0
    //   4182: aload_0
    //   4183: aastore
    //   4184: dup
    //   4185: iconst_1
    //   4186: aload_1
    //   4187: ifnonnull -> 4205
    //   4190: goto -> 4197
    //   4193: invokestatic a : (Ljava/lang/Throwable;)Ljava/lang/Throwable;
    //   4196: athrow
    //   4197: aload_1
    //   4198: goto -> 4212
    //   4201: invokestatic a : (Ljava/lang/Throwable;)Ljava/lang/Throwable;
    //   4204: athrow
    //   4205: aload_1
    //   4206: checkcast [B
    //   4209: invokevirtual clone : ()Ljava/lang/Object;
    //   4212: aastore
    //   4213: invokevirtual invoke : (Ljava/lang/Object;[Ljava/lang/Object;)Ljava/lang/Object;
    //   4216: pop
    //   4217: iload_2
    //   4218: ifeq -> 4235
    //   4221: iinc #6, 1
    //   4224: iload_2
    //   4225: ifeq -> 4098
    //   4228: goto -> 4235
    //   4231: invokestatic a : (Ljava/lang/Throwable;)Ljava/lang/Throwable;
    //   4234: athrow
    //   4235: iconst_0
    //   4236: istore #4
    //   4238: getstatic burp/Zli5.Zq : Ljava/lang/String;
    //   4241: getstatic burp/Zxjk.Zk : Ljava/lang/Object;
    //   4244: checkcast java/math/BigInteger
    //   4247: invokevirtual intValue : ()I
    //   4250: bipush #32
    //   4252: irem
    //   4253: invokestatic abs : (I)I
    //   4256: invokevirtual charAt : (I)C
    //   4259: getstatic burp/Zgva.ZV : Ljava/lang/String;
    //   4262: getstatic burp/Ztye.ZK : Ljava/lang/Object;
    //   4265: checkcast java/math/BigInteger
    //   4268: invokevirtual intValue : ()I
    //   4271: bipush #32
    //   4273: irem
    //   4274: invokestatic abs : (I)I
    //   4277: invokevirtual charAt : (I)C
    //   4280: if_icmple -> 4625
    //   4283: sipush #12062
    //   4286: sipush #30293
    //   4289: invokestatic a : (II)Ljava/lang/String;
    //   4292: iconst_1
    //   4293: ldc burp/Zgkp
    //   4295: invokevirtual getClassLoader : ()Ljava/lang/ClassLoader;
    //   4298: invokestatic forName : (Ljava/lang/String;ZLjava/lang/ClassLoader;)Ljava/lang/Class;
    //   4301: invokevirtual getDeclaredFields : ()[Ljava/lang/reflect/Field;
    //   4304: astore #5
    //   4306: aload #5
    //   4308: arraylength
    //   4309: istore #6
    //   4311: iconst_0
    //   4312: istore #7
    //   4314: iload #7
    //   4316: iload #6
    //   4318: if_icmpge -> 4456
    //   4321: aload #5
    //   4323: iload #7
    //   4325: aaload
    //   4326: astore #8
    //   4328: aload #8
    //   4330: invokevirtual getModifiers : ()I
    //   4333: invokestatic isStatic : (I)Z
    //   4336: ifne -> 4346
    //   4339: goto -> 4449
    //   4342: invokestatic a : (Ljava/lang/Throwable;)Ljava/lang/Throwable;
    //   4345: athrow
    //   4346: aload #8
    //   4348: invokevirtual getType : ()Ljava/lang/Class;
    //   4351: astore #9
    //   4353: aload #9
    //   4355: ifnull -> 4436
    //   4358: aload #9
    //   4360: invokevirtual isPrimitive : ()Z
    //   4363: ifne -> 4436
    //   4366: goto -> 4373
    //   4369: invokestatic a : (Ljava/lang/Throwable;)Ljava/lang/Throwable;
    //   4372: athrow
    //   4373: aload #9
    //   4375: invokevirtual getPackage : ()Ljava/lang/Package;
    //   4378: ifnull -> 4436
    //   4381: goto -> 4388
    //   4384: invokestatic a : (Ljava/lang/Throwable;)Ljava/lang/Throwable;
    //   4387: athrow
    //   4388: aload #9
    //   4390: invokevirtual getPackage : ()Ljava/lang/Package;
    //   4393: invokevirtual getName : ()Ljava/lang/String;
    //   4396: ifnull -> 4436
    //   4399: goto -> 4406
    //   4402: invokestatic a : (Ljava/lang/Throwable;)Ljava/lang/Throwable;
    //   4405: athrow
    //   4406: aload #9
    //   4408: invokevirtual getPackage : ()Ljava/lang/Package;
    //   4411: invokevirtual getName : ()Ljava/lang/String;
    //   4414: sipush #12038
    //   4417: sipush #11427
    //   4420: invokestatic a : (II)Ljava/lang/String;
    //   4423: invokevirtual startsWith : (Ljava/lang/String;)Z
    //   4426: ifne -> 4436
    //   4429: goto -> 4436
    //   4432: invokestatic a : (Ljava/lang/Throwable;)Ljava/lang/Throwable;
    //   4435: athrow
    //   4436: aload #8
    //   4438: iconst_1
    //   4439: invokevirtual setAccessible : (Z)V
    //   4442: aload #8
    //   4444: aconst_null
    //   4445: invokevirtual get : (Ljava/lang/Object;)Ljava/lang/Object;
    //   4448: pop
    //   4449: iinc #7, 1
    //   4452: iload_2
    //   4453: ifeq -> 4314
    //   4456: sipush #12034
    //   4459: sipush #-19330
    //   4462: invokestatic a : (II)Ljava/lang/String;
    //   4465: invokestatic forName : (Ljava/lang/String;)Ljava/lang/Class;
    //   4468: invokevirtual getDeclaredMethods : ()[Ljava/lang/reflect/Method;
    //   4471: astore #5
    //   4473: aload #5
    //   4475: arraylength
    //   4476: istore #6
    //   4478: iconst_0
    //   4479: istore #7
    //   4481: iload #7
    //   4483: iload #6
    //   4485: if_icmpge -> 4622
    //   4488: aload #5
    //   4490: iload #7
    //   4492: aaload
    //   4493: astore #8
    //   4495: aload #8
    //   4497: invokevirtual getParameterTypes : ()[Ljava/lang/Class;
    //   4500: pop
    //   4501: aload #8
    //   4503: invokevirtual getModifiers : ()I
    //   4506: invokestatic isStatic : (I)Z
    //   4509: ifeq -> 4608
    //   4512: aload #8
    //   4514: invokevirtual getParameterTypes : ()[Ljava/lang/Class;
    //   4517: arraylength
    //   4518: iconst_2
    //   4519: if_icmpne -> 4608
    //   4522: goto -> 4529
    //   4525: invokestatic a : (Ljava/lang/Throwable;)Ljava/lang/Throwable;
    //   4528: athrow
    //   4529: aload #8
    //   4531: invokevirtual getReturnType : ()Ljava/lang/Class;
    //   4534: getstatic java/lang/Boolean.TYPE : Ljava/lang/Class;
    //   4537: if_acmpne -> 4608
    //   4540: goto -> 4547
    //   4543: invokestatic a : (Ljava/lang/Throwable;)Ljava/lang/Throwable;
    //   4546: athrow
    //   4547: aload #8
    //   4549: iconst_1
    //   4550: invokevirtual setAccessible : (Z)V
    //   4553: aload #8
    //   4555: aconst_null
    //   4556: iconst_2
    //   4557: anewarray java/lang/Object
    //   4560: dup
    //   4561: iconst_0
    //   4562: aload_0
    //   4563: aastore
    //   4564: dup
    //   4565: iconst_1
    //   4566: aload_1
    //   4567: ifnonnull -> 4585
    //   4570: goto -> 4577
    //   4573: invokestatic a : (Ljava/lang/Throwable;)Ljava/lang/Throwable;
    //   4576: athrow
    //   4577: aload_1
    //   4578: goto -> 4592
    //   4581: invokestatic a : (Ljava/lang/Throwable;)Ljava/lang/Throwable;
    //   4584: athrow
    //   4585: aload_1
    //   4586: checkcast [B
    //   4589: invokevirtual clone : ()Ljava/lang/Object;
    //   4592: aastore
    //   4593: invokevirtual invoke : (Ljava/lang/Object;[Ljava/lang/Object;)Ljava/lang/Object;
    //   4596: checkcast java/lang/Boolean
    //   4599: invokevirtual booleanValue : ()Z
    //   4602: istore #4
    //   4604: iload_2
    //   4605: ifeq -> 4622
    //   4608: iinc #7, 1
    //   4611: iload_2
    //   4612: ifeq -> 4481
    //   4615: goto -> 4622
    //   4618: invokestatic a : (Ljava/lang/Throwable;)Ljava/lang/Throwable;
    //   4621: athrow
    //   4622: goto -> 4964
    //   4625: sipush #12058
    //   4628: sipush #741
    //   4631: invokestatic a : (II)Ljava/lang/String;
    //   4634: iconst_1
    //   4635: ldc burp/Zsde
    //   4637: invokevirtual getClassLoader : ()Ljava/lang/ClassLoader;
    //   4640: invokestatic forName : (Ljava/lang/String;ZLjava/lang/ClassLoader;)Ljava/lang/Class;
    //   4643: invokevirtual getDeclaredFields : ()[Ljava/lang/reflect/Field;
    //   4646: astore #5
    //   4648: aload #5
    //   4650: arraylength
    //   4651: istore #6
    //   4653: iconst_0
    //   4654: istore #7
    //   4656: iload #7
    //   4658: iload #6
    //   4660: if_icmpge -> 4798
    //   4663: aload #5
    //   4665: iload #7
    //   4667: aaload
    //   4668: astore #8
    //   4670: aload #8
    //   4672: invokevirtual getModifiers : ()I
    //   4675: invokestatic isStatic : (I)Z
    //   4678: ifne -> 4688
    //   4681: goto -> 4791
    //   4684: invokestatic a : (Ljava/lang/Throwable;)Ljava/lang/Throwable;
    //   4687: athrow
    //   4688: aload #8
    //   4690: invokevirtual getType : ()Ljava/lang/Class;
    //   4693: astore #9
    //   4695: aload #9
    //   4697: ifnull -> 4778
    //   4700: aload #9
    //   4702: invokevirtual isPrimitive : ()Z
    //   4705: ifne -> 4778
    //   4708: goto -> 4715
    //   4711: invokestatic a : (Ljava/lang/Throwable;)Ljava/lang/Throwable;
    //   4714: athrow
    //   4715: aload #9
    //   4717: invokevirtual getPackage : ()Ljava/lang/Package;
    //   4720: ifnull -> 4778
    //   4723: goto -> 4730
    //   4726: invokestatic a : (Ljava/lang/Throwable;)Ljava/lang/Throwable;
    //   4729: athrow
    //   4730: aload #9
    //   4732: invokevirtual getPackage : ()Ljava/lang/Package;
    //   4735: invokevirtual getName : ()Ljava/lang/String;
    //   4738: ifnull -> 4778
    //   4741: goto -> 4748
    //   4744: invokestatic a : (Ljava/lang/Throwable;)Ljava/lang/Throwable;
    //   4747: athrow
    //   4748: aload #9
    //   4750: invokevirtual getPackage : ()Ljava/lang/Package;
    //   4753: invokevirtual getName : ()Ljava/lang/String;
    //   4756: sipush #12038
    //   4759: sipush #11427
    //   4762: invokestatic a : (II)Ljava/lang/String;
    //   4765: invokevirtual startsWith : (Ljava/lang/String;)Z
    //   4768: ifne -> 4778
    //   4771: goto -> 4778
    //   4774: invokestatic a : (Ljava/lang/Throwable;)Ljava/lang/Throwable;
    //   4777: athrow
    //   4778: aload #8
    //   4780: iconst_1
    //   4781: invokevirtual setAccessible : (Z)V
    //   4784: aload #8
    //   4786: aconst_null
    //   4787: invokevirtual get : (Ljava/lang/Object;)Ljava/lang/Object;
    //   4790: pop
    //   4791: iinc #7, 1
    //   4794: iload_2
    //   4795: ifeq -> 4656
    //   4798: sipush #12033
    //   4801: sipush #-3052
    //   4804: invokestatic a : (II)Ljava/lang/String;
    //   4807: invokestatic forName : (Ljava/lang/String;)Ljava/lang/Class;
    //   4810: invokevirtual getDeclaredMethods : ()[Ljava/lang/reflect/Method;
    //   4813: astore #5
    //   4815: aload #5
    //   4817: arraylength
    //   4818: istore #6
    //   4820: iconst_0
    //   4821: istore #7
    //   4823: iload #7
    //   4825: iload #6
    //   4827: if_icmpge -> 4964
    //   4830: aload #5
    //   4832: iload #7
    //   4834: aaload
    //   4835: astore #8
    //   4837: aload #8
    //   4839: invokevirtual getParameterTypes : ()[Ljava/lang/Class;
    //   4842: pop
    //   4843: aload #8
    //   4845: invokevirtual getModifiers : ()I
    //   4848: invokestatic isStatic : (I)Z
    //   4851: ifeq -> 4950
    //   4854: aload #8
    //   4856: invokevirtual getParameterTypes : ()[Ljava/lang/Class;
    //   4859: arraylength
    //   4860: iconst_2
    //   4861: if_icmpne -> 4950
    //   4864: goto -> 4871
    //   4867: invokestatic a : (Ljava/lang/Throwable;)Ljava/lang/Throwable;
    //   4870: athrow
    //   4871: aload #8
    //   4873: invokevirtual getReturnType : ()Ljava/lang/Class;
    //   4876: getstatic java/lang/Boolean.TYPE : Ljava/lang/Class;
    //   4879: if_acmpne -> 4950
    //   4882: goto -> 4889
    //   4885: invokestatic a : (Ljava/lang/Throwable;)Ljava/lang/Throwable;
    //   4888: athrow
    //   4889: aload #8
    //   4891: iconst_1
    //   4892: invokevirtual setAccessible : (Z)V
    //   4895: aload #8
    //   4897: aconst_null
    //   4898: iconst_2
    //   4899: anewarray java/lang/Object
    //   4902: dup
    //   4903: iconst_0
    //   4904: aload_0
    //   4905: aastore
    //   4906: dup
    //   4907: iconst_1
    //   4908: aload_1
    //   4909: ifnonnull -> 4927
    //   4912: goto -> 4919
    //   4915: invokestatic a : (Ljava/lang/Throwable;)Ljava/lang/Throwable;
    //   4918: athrow
    //   4919: aload_1
    //   4920: goto -> 4934
    //   4923: invokestatic a : (Ljava/lang/Throwable;)Ljava/lang/Throwable;
    //   4926: athrow
    //   4927: aload_1
    //   4928: checkcast [B
    //   4931: invokevirtual clone : ()Ljava/lang/Object;
    //   4934: aastore
    //   4935: invokevirtual invoke : (Ljava/lang/Object;[Ljava/lang/Object;)Ljava/lang/Object;
    //   4938: checkcast java/lang/Boolean
    //   4941: invokevirtual booleanValue : ()Z
    //   4944: istore #4
    //   4946: iload_2
    //   4947: ifeq -> 4964
    //   4950: iinc #7, 1
    //   4953: iload_2
    //   4954: ifeq -> 4823
    //   4957: goto -> 4964
    //   4960: invokestatic a : (Ljava/lang/Throwable;)Ljava/lang/Throwable;
    //   4963: athrow
    //   4964: iload #4
    //   4966: ifeq -> 4972
    //   4969: iload #4
    //   4971: ireturn
    //   4972: getstatic burp/Zera.Zn : Ljava/lang/String;
    //   4975: getstatic burp/Zzox.Zq : Ljava/lang/Object;
    //   4978: checkcast java/math/BigInteger
    //   4981: invokevirtual intValue : ()I
    //   4984: bipush #32
    //   4986: irem
    //   4987: invokestatic abs : (I)I
    //   4990: invokevirtual charAt : (I)C
    //   4993: getstatic burp/Ze5f.Zt : Ljava/lang/String;
    //   4996: getstatic burp/Zl50.ZV : Ljava/lang/Object;
    //   4999: checkcast java/math/BigInteger
    //   5002: invokevirtual intValue : ()I
    //   5005: bipush #32
    //   5007: irem
    //   5008: invokestatic abs : (I)I
    //   5011: invokevirtual charAt : (I)C
    //   5014: if_icmpgt -> 5360
    //   5017: sipush #12047
    //   5020: sipush #-23885
    //   5023: invokestatic a : (II)Ljava/lang/String;
    //   5026: iconst_1
    //   5027: ldc burp/Zb3z
    //   5029: invokevirtual getClassLoader : ()Ljava/lang/ClassLoader;
    //   5032: invokestatic forName : (Ljava/lang/String;ZLjava/lang/ClassLoader;)Ljava/lang/Class;
    //   5035: invokevirtual getDeclaredFields : ()[Ljava/lang/reflect/Field;
    //   5038: astore #5
    //   5040: aload #5
    //   5042: arraylength
    //   5043: istore #6
    //   5045: iconst_0
    //   5046: istore #7
    //   5048: iload #7
    //   5050: iload #6
    //   5052: if_icmpge -> 5190
    //   5055: aload #5
    //   5057: iload #7
    //   5059: aaload
    //   5060: astore #8
    //   5062: aload #8
    //   5064: invokevirtual getModifiers : ()I
    //   5067: invokestatic isStatic : (I)Z
    //   5070: ifne -> 5080
    //   5073: goto -> 5183
    //   5076: invokestatic a : (Ljava/lang/Throwable;)Ljava/lang/Throwable;
    //   5079: athrow
    //   5080: aload #8
    //   5082: invokevirtual getType : ()Ljava/lang/Class;
    //   5085: astore #9
    //   5087: aload #9
    //   5089: ifnull -> 5170
    //   5092: aload #9
    //   5094: invokevirtual isPrimitive : ()Z
    //   5097: ifne -> 5170
    //   5100: goto -> 5107
    //   5103: invokestatic a : (Ljava/lang/Throwable;)Ljava/lang/Throwable;
    //   5106: athrow
    //   5107: aload #9
    //   5109: invokevirtual getPackage : ()Ljava/lang/Package;
    //   5112: ifnull -> 5170
    //   5115: goto -> 5122
    //   5118: invokestatic a : (Ljava/lang/Throwable;)Ljava/lang/Throwable;
    //   5121: athrow
    //   5122: aload #9
    //   5124: invokevirtual getPackage : ()Ljava/lang/Package;
    //   5127: invokevirtual getName : ()Ljava/lang/String;
    //   5130: ifnull -> 5170
    //   5133: goto -> 5140
    //   5136: invokestatic a : (Ljava/lang/Throwable;)Ljava/lang/Throwable;
    //   5139: athrow
    //   5140: aload #9
    //   5142: invokevirtual getPackage : ()Ljava/lang/Package;
    //   5145: invokevirtual getName : ()Ljava/lang/String;
    //   5148: sipush #12038
    //   5151: sipush #11427
    //   5154: invokestatic a : (II)Ljava/lang/String;
    //   5157: invokevirtual startsWith : (Ljava/lang/String;)Z
    //   5160: ifne -> 5170
    //   5163: goto -> 5170
    //   5166: invokestatic a : (Ljava/lang/Throwable;)Ljava/lang/Throwable;
    //   5169: athrow
    //   5170: aload #8
    //   5172: iconst_1
    //   5173: invokevirtual setAccessible : (Z)V
    //   5176: aload #8
    //   5178: aconst_null
    //   5179: invokevirtual get : (Ljava/lang/Object;)Ljava/lang/Object;
    //   5182: pop
    //   5183: iinc #7, 1
    //   5186: iload_2
    //   5187: ifeq -> 5048
    //   5190: sipush #12054
    //   5193: sipush #5386
    //   5196: invokestatic a : (II)Ljava/lang/String;
    //   5199: invokestatic forName : (Ljava/lang/String;)Ljava/lang/Class;
    //   5202: invokevirtual getDeclaredMethods : ()[Ljava/lang/reflect/Method;
    //   5205: astore #5
    //   5207: aload #5
    //   5209: arraylength
    //   5210: istore #6
    //   5212: iconst_0
    //   5213: istore #7
    //   5215: iload #7
    //   5217: iload #6
    //   5219: if_icmpge -> 5356
    //   5222: aload #5
    //   5224: iload #7
    //   5226: aaload
    //   5227: astore #8
    //   5229: aload #8
    //   5231: invokevirtual getParameterTypes : ()[Ljava/lang/Class;
    //   5234: pop
    //   5235: aload #8
    //   5237: invokevirtual getModifiers : ()I
    //   5240: invokestatic isStatic : (I)Z
    //   5243: ifeq -> 5342
    //   5246: aload #8
    //   5248: invokevirtual getParameterTypes : ()[Ljava/lang/Class;
    //   5251: arraylength
    //   5252: iconst_2
    //   5253: if_icmpne -> 5342
    //   5256: goto -> 5263
    //   5259: invokestatic a : (Ljava/lang/Throwable;)Ljava/lang/Throwable;
    //   5262: athrow
    //   5263: aload #8
    //   5265: invokevirtual getReturnType : ()Ljava/lang/Class;
    //   5268: getstatic java/lang/Boolean.TYPE : Ljava/lang/Class;
    //   5271: if_acmpne -> 5342
    //   5274: goto -> 5281
    //   5277: invokestatic a : (Ljava/lang/Throwable;)Ljava/lang/Throwable;
    //   5280: athrow
    //   5281: aload #8
    //   5283: iconst_1
    //   5284: invokevirtual setAccessible : (Z)V
    //   5287: aload #8
    //   5289: aconst_null
    //   5290: iconst_2
    //   5291: anewarray java/lang/Object
    //   5294: dup
    //   5295: iconst_0
    //   5296: aload_0
    //   5297: aastore
    //   5298: dup
    //   5299: iconst_1
    //   5300: aload_1
    //   5301: ifnonnull -> 5319
    //   5304: goto -> 5311
    //   5307: invokestatic a : (Ljava/lang/Throwable;)Ljava/lang/Throwable;
    //   5310: athrow
    //   5311: aload_1
    //   5312: goto -> 5326
    //   5315: invokestatic a : (Ljava/lang/Throwable;)Ljava/lang/Throwable;
    //   5318: athrow
    //   5319: aload_1
    //   5320: checkcast [B
    //   5323: invokevirtual clone : ()Ljava/lang/Object;
    //   5326: aastore
    //   5327: invokevirtual invoke : (Ljava/lang/Object;[Ljava/lang/Object;)Ljava/lang/Object;
    //   5330: checkcast java/lang/Boolean
    //   5333: invokevirtual booleanValue : ()Z
    //   5336: istore #4
    //   5338: iload_2
    //   5339: ifeq -> 5356
    //   5342: iinc #7, 1
    //   5345: iload_2
    //   5346: ifeq -> 5215
    //   5349: goto -> 5356
    //   5352: invokestatic a : (Ljava/lang/Throwable;)Ljava/lang/Throwable;
    //   5355: athrow
    //   5356: iload_2
    //   5357: ifeq -> 5699
    //   5360: sipush #12045
    //   5363: sipush #-971
    //   5366: invokestatic a : (II)Ljava/lang/String;
    //   5369: iconst_1
    //   5370: ldc burp/Zmnb
    //   5372: invokevirtual getClassLoader : ()Ljava/lang/ClassLoader;
    //   5375: invokestatic forName : (Ljava/lang/String;ZLjava/lang/ClassLoader;)Ljava/lang/Class;
    //   5378: invokevirtual getDeclaredFields : ()[Ljava/lang/reflect/Field;
    //   5381: astore #5
    //   5383: aload #5
    //   5385: arraylength
    //   5386: istore #6
    //   5388: iconst_0
    //   5389: istore #7
    //   5391: iload #7
    //   5393: iload #6
    //   5395: if_icmpge -> 5533
    //   5398: aload #5
    //   5400: iload #7
    //   5402: aaload
    //   5403: astore #8
    //   5405: aload #8
    //   5407: invokevirtual getModifiers : ()I
    //   5410: invokestatic isStatic : (I)Z
    //   5413: ifne -> 5423
    //   5416: goto -> 5526
    //   5419: invokestatic a : (Ljava/lang/Throwable;)Ljava/lang/Throwable;
    //   5422: athrow
    //   5423: aload #8
    //   5425: invokevirtual getType : ()Ljava/lang/Class;
    //   5428: astore #9
    //   5430: aload #9
    //   5432: ifnull -> 5513
    //   5435: aload #9
    //   5437: invokevirtual isPrimitive : ()Z
    //   5440: ifne -> 5513
    //   5443: goto -> 5450
    //   5446: invokestatic a : (Ljava/lang/Throwable;)Ljava/lang/Throwable;
    //   5449: athrow
    //   5450: aload #9
    //   5452: invokevirtual getPackage : ()Ljava/lang/Package;
    //   5455: ifnull -> 5513
    //   5458: goto -> 5465
    //   5461: invokestatic a : (Ljava/lang/Throwable;)Ljava/lang/Throwable;
    //   5464: athrow
    //   5465: aload #9
    //   5467: invokevirtual getPackage : ()Ljava/lang/Package;
    //   5470: invokevirtual getName : ()Ljava/lang/String;
    //   5473: ifnull -> 5513
    //   5476: goto -> 5483
    //   5479: invokestatic a : (Ljava/lang/Throwable;)Ljava/lang/Throwable;
    //   5482: athrow
    //   5483: aload #9
    //   5485: invokevirtual getPackage : ()Ljava/lang/Package;
    //   5488: invokevirtual getName : ()Ljava/lang/String;
    //   5491: sipush #12038
    //   5494: sipush #11427
    //   5497: invokestatic a : (II)Ljava/lang/String;
    //   5500: invokevirtual startsWith : (Ljava/lang/String;)Z
    //   5503: ifne -> 5513
    //   5506: goto -> 5513
    //   5509: invokestatic a : (Ljava/lang/Throwable;)Ljava/lang/Throwable;
    //   5512: athrow
    //   5513: aload #8
    //   5515: iconst_1
    //   5516: invokevirtual setAccessible : (Z)V
    //   5519: aload #8
    //   5521: aconst_null
    //   5522: invokevirtual get : (Ljava/lang/Object;)Ljava/lang/Object;
    //   5525: pop
    //   5526: iinc #7, 1
    //   5529: iload_2
    //   5530: ifeq -> 5391
    //   5533: sipush #12041
    //   5536: sipush #-7007
    //   5539: invokestatic a : (II)Ljava/lang/String;
    //   5542: invokestatic forName : (Ljava/lang/String;)Ljava/lang/Class;
    //   5545: invokevirtual getDeclaredMethods : ()[Ljava/lang/reflect/Method;
    //   5548: astore #5
    //   5550: aload #5
    //   5552: arraylength
    //   5553: istore #6
    //   5555: iconst_0
    //   5556: istore #7
    //   5558: iload #7
    //   5560: iload #6
    //   5562: if_icmpge -> 5699
    //   5565: aload #5
    //   5567: iload #7
    //   5569: aaload
    //   5570: astore #8
    //   5572: aload #8
    //   5574: invokevirtual getParameterTypes : ()[Ljava/lang/Class;
    //   5577: pop
    //   5578: aload #8
    //   5580: invokevirtual getModifiers : ()I
    //   5583: invokestatic isStatic : (I)Z
    //   5586: ifeq -> 5685
    //   5589: aload #8
    //   5591: invokevirtual getParameterTypes : ()[Ljava/lang/Class;
    //   5594: arraylength
    //   5595: iconst_2
    //   5596: if_icmpne -> 5685
    //   5599: goto -> 5606
    //   5602: invokestatic a : (Ljava/lang/Throwable;)Ljava/lang/Throwable;
    //   5605: athrow
    //   5606: aload #8
    //   5608: invokevirtual getReturnType : ()Ljava/lang/Class;
    //   5611: getstatic java/lang/Boolean.TYPE : Ljava/lang/Class;
    //   5614: if_acmpne -> 5685
    //   5617: goto -> 5624
    //   5620: invokestatic a : (Ljava/lang/Throwable;)Ljava/lang/Throwable;
    //   5623: athrow
    //   5624: aload #8
    //   5626: iconst_1
    //   5627: invokevirtual setAccessible : (Z)V
    //   5630: aload #8
    //   5632: aconst_null
    //   5633: iconst_2
    //   5634: anewarray java/lang/Object
    //   5637: dup
    //   5638: iconst_0
    //   5639: aload_0
    //   5640: aastore
    //   5641: dup
    //   5642: iconst_1
    //   5643: aload_1
    //   5644: ifnonnull -> 5662
    //   5647: goto -> 5654
    //   5650: invokestatic a : (Ljava/lang/Throwable;)Ljava/lang/Throwable;
    //   5653: athrow
    //   5654: aload_1
    //   5655: goto -> 5669
    //   5658: invokestatic a : (Ljava/lang/Throwable;)Ljava/lang/Throwable;
    //   5661: athrow
    //   5662: aload_1
    //   5663: checkcast [B
    //   5666: invokevirtual clone : ()Ljava/lang/Object;
    //   5669: aastore
    //   5670: invokevirtual invoke : (Ljava/lang/Object;[Ljava/lang/Object;)Ljava/lang/Object;
    //   5673: checkcast java/lang/Boolean
    //   5676: invokevirtual booleanValue : ()Z
    //   5679: istore #4
    //   5681: iload_2
    //   5682: ifeq -> 5699
    //   5685: iinc #7, 1
    //   5688: iload_2
    //   5689: ifeq -> 5558
    //   5692: goto -> 5699
    //   5695: invokestatic a : (Ljava/lang/Throwable;)Ljava/lang/Throwable;
    //   5698: athrow
    //   5699: iload #4
    //   5701: ifeq -> 5707
    //   5704: iload #4
    //   5706: ireturn
    //   5707: getstatic burp/Zel.Zi : Ljava/lang/String;
    //   5710: getstatic burp/Ze8m.Zm : Ljava/lang/Object;
    //   5713: checkcast java/math/BigInteger
    //   5716: invokevirtual intValue : ()I
    //   5719: bipush #32
    //   5721: irem
    //   5722: invokestatic abs : (I)I
    //   5725: invokevirtual charAt : (I)C
    //   5728: getstatic burp/Zgpp.Zm : Ljava/lang/String;
    //   5731: getstatic burp/Zz0w.ZF : Ljava/lang/Object;
    //   5734: checkcast java/math/BigInteger
    //   5737: invokevirtual intValue : ()I
    //   5740: bipush #32
    //   5742: irem
    //   5743: invokestatic abs : (I)I
    //   5746: invokevirtual charAt : (I)C
    //   5749: if_icmple -> 6095
    //   5752: sipush #12061
    //   5755: sipush #-10699
    //   5758: invokestatic a : (II)Ljava/lang/String;
    //   5761: iconst_1
    //   5762: ldc burp/Zenq
    //   5764: invokevirtual getClassLoader : ()Ljava/lang/ClassLoader;
    //   5767: invokestatic forName : (Ljava/lang/String;ZLjava/lang/ClassLoader;)Ljava/lang/Class;
    //   5770: invokevirtual getDeclaredFields : ()[Ljava/lang/reflect/Field;
    //   5773: astore #5
    //   5775: aload #5
    //   5777: arraylength
    //   5778: istore #6
    //   5780: iconst_0
    //   5781: istore #7
    //   5783: iload #7
    //   5785: iload #6
    //   5787: if_icmpge -> 5925
    //   5790: aload #5
    //   5792: iload #7
    //   5794: aaload
    //   5795: astore #8
    //   5797: aload #8
    //   5799: invokevirtual getModifiers : ()I
    //   5802: invokestatic isStatic : (I)Z
    //   5805: ifne -> 5815
    //   5808: goto -> 5918
    //   5811: invokestatic a : (Ljava/lang/Throwable;)Ljava/lang/Throwable;
    //   5814: athrow
    //   5815: aload #8
    //   5817: invokevirtual getType : ()Ljava/lang/Class;
    //   5820: astore #9
    //   5822: aload #9
    //   5824: ifnull -> 5905
    //   5827: aload #9
    //   5829: invokevirtual isPrimitive : ()Z
    //   5832: ifne -> 5905
    //   5835: goto -> 5842
    //   5838: invokestatic a : (Ljava/lang/Throwable;)Ljava/lang/Throwable;
    //   5841: athrow
    //   5842: aload #9
    //   5844: invokevirtual getPackage : ()Ljava/lang/Package;
    //   5847: ifnull -> 5905
    //   5850: goto -> 5857
    //   5853: invokestatic a : (Ljava/lang/Throwable;)Ljava/lang/Throwable;
    //   5856: athrow
    //   5857: aload #9
    //   5859: invokevirtual getPackage : ()Ljava/lang/Package;
    //   5862: invokevirtual getName : ()Ljava/lang/String;
    //   5865: ifnull -> 5905
    //   5868: goto -> 5875
    //   5871: invokestatic a : (Ljava/lang/Throwable;)Ljava/lang/Throwable;
    //   5874: athrow
    //   5875: aload #9
    //   5877: invokevirtual getPackage : ()Ljava/lang/Package;
    //   5880: invokevirtual getName : ()Ljava/lang/String;
    //   5883: sipush #12038
    //   5886: sipush #11427
    //   5889: invokestatic a : (II)Ljava/lang/String;
    //   5892: invokevirtual startsWith : (Ljava/lang/String;)Z
    //   5895: ifne -> 5905
    //   5898: goto -> 5905
    //   5901: invokestatic a : (Ljava/lang/Throwable;)Ljava/lang/Throwable;
    //   5904: athrow
    //   5905: aload #8
    //   5907: iconst_1
    //   5908: invokevirtual setAccessible : (Z)V
    //   5911: aload #8
    //   5913: aconst_null
    //   5914: invokevirtual get : (Ljava/lang/Object;)Ljava/lang/Object;
    //   5917: pop
    //   5918: iinc #7, 1
    //   5921: iload_2
    //   5922: ifeq -> 5783
    //   5925: sipush #12053
    //   5928: sipush #-28477
    //   5931: invokestatic a : (II)Ljava/lang/String;
    //   5934: invokestatic forName : (Ljava/lang/String;)Ljava/lang/Class;
    //   5937: invokevirtual getDeclaredMethods : ()[Ljava/lang/reflect/Method;
    //   5940: astore #5
    //   5942: aload #5
    //   5944: arraylength
    //   5945: istore #6
    //   5947: iconst_0
    //   5948: istore #7
    //   5950: iload #7
    //   5952: iload #6
    //   5954: if_icmpge -> 6091
    //   5957: aload #5
    //   5959: iload #7
    //   5961: aaload
    //   5962: astore #8
    //   5964: aload #8
    //   5966: invokevirtual getParameterTypes : ()[Ljava/lang/Class;
    //   5969: pop
    //   5970: aload #8
    //   5972: invokevirtual getModifiers : ()I
    //   5975: invokestatic isStatic : (I)Z
    //   5978: ifeq -> 6077
    //   5981: aload #8
    //   5983: invokevirtual getParameterTypes : ()[Ljava/lang/Class;
    //   5986: arraylength
    //   5987: iconst_2
    //   5988: if_icmpne -> 6077
    //   5991: goto -> 5998
    //   5994: invokestatic a : (Ljava/lang/Throwable;)Ljava/lang/Throwable;
    //   5997: athrow
    //   5998: aload #8
    //   6000: invokevirtual getReturnType : ()Ljava/lang/Class;
    //   6003: getstatic java/lang/Boolean.TYPE : Ljava/lang/Class;
    //   6006: if_acmpne -> 6077
    //   6009: goto -> 6016
    //   6012: invokestatic a : (Ljava/lang/Throwable;)Ljava/lang/Throwable;
    //   6015: athrow
    //   6016: aload #8
    //   6018: iconst_1
    //   6019: invokevirtual setAccessible : (Z)V
    //   6022: aload #8
    //   6024: aconst_null
    //   6025: iconst_2
    //   6026: anewarray java/lang/Object
    //   6029: dup
    //   6030: iconst_0
    //   6031: aload_0
    //   6032: aastore
    //   6033: dup
    //   6034: iconst_1
    //   6035: aload_1
    //   6036: ifnonnull -> 6054
    //   6039: goto -> 6046
    //   6042: invokestatic a : (Ljava/lang/Throwable;)Ljava/lang/Throwable;
    //   6045: athrow
    //   6046: aload_1
    //   6047: goto -> 6061
    //   6050: invokestatic a : (Ljava/lang/Throwable;)Ljava/lang/Throwable;
    //   6053: athrow
    //   6054: aload_1
    //   6055: checkcast [B
    //   6058: invokevirtual clone : ()Ljava/lang/Object;
    //   6061: aastore
    //   6062: invokevirtual invoke : (Ljava/lang/Object;[Ljava/lang/Object;)Ljava/lang/Object;
    //   6065: checkcast java/lang/Boolean
    //   6068: invokevirtual booleanValue : ()Z
    //   6071: istore #4
    //   6073: iload_2
    //   6074: ifeq -> 6091
    //   6077: iinc #7, 1
    //   6080: iload_2
    //   6081: ifeq -> 5950
    //   6084: goto -> 6091
    //   6087: invokestatic a : (Ljava/lang/Throwable;)Ljava/lang/Throwable;
    //   6090: athrow
    //   6091: iload_2
    //   6092: ifeq -> 6434
    //   6095: sipush #12039
    //   6098: sipush #512
    //   6101: invokestatic a : (II)Ljava/lang/String;
    //   6104: iconst_1
    //   6105: ldc burp/Zrjg
    //   6107: invokevirtual getClassLoader : ()Ljava/lang/ClassLoader;
    //   6110: invokestatic forName : (Ljava/lang/String;ZLjava/lang/ClassLoader;)Ljava/lang/Class;
    //   6113: invokevirtual getDeclaredFields : ()[Ljava/lang/reflect/Field;
    //   6116: astore #5
    //   6118: aload #5
    //   6120: arraylength
    //   6121: istore #6
    //   6123: iconst_0
    //   6124: istore #7
    //   6126: iload #7
    //   6128: iload #6
    //   6130: if_icmpge -> 6268
    //   6133: aload #5
    //   6135: iload #7
    //   6137: aaload
    //   6138: astore #8
    //   6140: aload #8
    //   6142: invokevirtual getModifiers : ()I
    //   6145: invokestatic isStatic : (I)Z
    //   6148: ifne -> 6158
    //   6151: goto -> 6261
    //   6154: invokestatic a : (Ljava/lang/Throwable;)Ljava/lang/Throwable;
    //   6157: athrow
    //   6158: aload #8
    //   6160: invokevirtual getType : ()Ljava/lang/Class;
    //   6163: astore #9
    //   6165: aload #9
    //   6167: ifnull -> 6248
    //   6170: aload #9
    //   6172: invokevirtual isPrimitive : ()Z
    //   6175: ifne -> 6248
    //   6178: goto -> 6185
    //   6181: invokestatic a : (Ljava/lang/Throwable;)Ljava/lang/Throwable;
    //   6184: athrow
    //   6185: aload #9
    //   6187: invokevirtual getPackage : ()Ljava/lang/Package;
    //   6190: ifnull -> 6248
    //   6193: goto -> 6200
    //   6196: invokestatic a : (Ljava/lang/Throwable;)Ljava/lang/Throwable;
    //   6199: athrow
    //   6200: aload #9
    //   6202: invokevirtual getPackage : ()Ljava/lang/Package;
    //   6205: invokevirtual getName : ()Ljava/lang/String;
    //   6208: ifnull -> 6248
    //   6211: goto -> 6218
    //   6214: invokestatic a : (Ljava/lang/Throwable;)Ljava/lang/Throwable;
    //   6217: athrow
    //   6218: aload #9
    //   6220: invokevirtual getPackage : ()Ljava/lang/Package;
    //   6223: invokevirtual getName : ()Ljava/lang/String;
    //   6226: sipush #12038
    //   6229: sipush #11427
    //   6232: invokestatic a : (II)Ljava/lang/String;
    //   6235: invokevirtual startsWith : (Ljava/lang/String;)Z
    //   6238: ifne -> 6248
    //   6241: goto -> 6248
    //   6244: invokestatic a : (Ljava/lang/Throwable;)Ljava/lang/Throwable;
    //   6247: athrow
    //   6248: aload #8
    //   6250: iconst_1
    //   6251: invokevirtual setAccessible : (Z)V
    //   6254: aload #8
    //   6256: aconst_null
    //   6257: invokevirtual get : (Ljava/lang/Object;)Ljava/lang/Object;
    //   6260: pop
    //   6261: iinc #7, 1
    //   6264: iload_2
    //   6265: ifeq -> 6126
    //   6268: sipush #12049
    //   6271: sipush #27297
    //   6274: invokestatic a : (II)Ljava/lang/String;
    //   6277: invokestatic forName : (Ljava/lang/String;)Ljava/lang/Class;
    //   6280: invokevirtual getDeclaredMethods : ()[Ljava/lang/reflect/Method;
    //   6283: astore #5
    //   6285: aload #5
    //   6287: arraylength
    //   6288: istore #6
    //   6290: iconst_0
    //   6291: istore #7
    //   6293: iload #7
    //   6295: iload #6
    //   6297: if_icmpge -> 6434
    //   6300: aload #5
    //   6302: iload #7
    //   6304: aaload
    //   6305: astore #8
    //   6307: aload #8
    //   6309: invokevirtual getParameterTypes : ()[Ljava/lang/Class;
    //   6312: pop
    //   6313: aload #8
    //   6315: invokevirtual getModifiers : ()I
    //   6318: invokestatic isStatic : (I)Z
    //   6321: ifeq -> 6420
    //   6324: aload #8
    //   6326: invokevirtual getParameterTypes : ()[Ljava/lang/Class;
    //   6329: arraylength
    //   6330: iconst_2
    //   6331: if_icmpne -> 6420
    //   6334: goto -> 6341
    //   6337: invokestatic a : (Ljava/lang/Throwable;)Ljava/lang/Throwable;
    //   6340: athrow
    //   6341: aload #8
    //   6343: invokevirtual getReturnType : ()Ljava/lang/Class;
    //   6346: getstatic java/lang/Boolean.TYPE : Ljava/lang/Class;
    //   6349: if_acmpne -> 6420
    //   6352: goto -> 6359
    //   6355: invokestatic a : (Ljava/lang/Throwable;)Ljava/lang/Throwable;
    //   6358: athrow
    //   6359: aload #8
    //   6361: iconst_1
    //   6362: invokevirtual setAccessible : (Z)V
    //   6365: aload #8
    //   6367: aconst_null
    //   6368: iconst_2
    //   6369: anewarray java/lang/Object
    //   6372: dup
    //   6373: iconst_0
    //   6374: aload_0
    //   6375: aastore
    //   6376: dup
    //   6377: iconst_1
    //   6378: aload_1
    //   6379: ifnonnull -> 6397
    //   6382: goto -> 6389
    //   6385: invokestatic a : (Ljava/lang/Throwable;)Ljava/lang/Throwable;
    //   6388: athrow
    //   6389: aload_1
    //   6390: goto -> 6404
    //   6393: invokestatic a : (Ljava/lang/Throwable;)Ljava/lang/Throwable;
    //   6396: athrow
    //   6397: aload_1
    //   6398: checkcast [B
    //   6401: invokevirtual clone : ()Ljava/lang/Object;
    //   6404: aastore
    //   6405: invokevirtual invoke : (Ljava/lang/Object;[Ljava/lang/Object;)Ljava/lang/Object;
    //   6408: checkcast java/lang/Boolean
    //   6411: invokevirtual booleanValue : ()Z
    //   6414: istore #4
    //   6416: iload_2
    //   6417: ifeq -> 6434
    //   6420: iinc #7, 1
    //   6423: iload_2
    //   6424: ifeq -> 6293
    //   6427: goto -> 6434
    //   6430: invokestatic a : (Ljava/lang/Throwable;)Ljava/lang/Throwable;
    //   6433: athrow
    //   6434: iload #4
    //   6436: ifeq -> 6442
    //   6439: iload #4
    //   6441: ireturn
    //   6442: getstatic burp/Ze64.ZM : Ljava/lang/String;
    //   6445: getstatic burp/Zm7x.Zv : Ljava/lang/Object;
    //   6448: checkcast java/math/BigInteger
    //   6451: invokevirtual intValue : ()I
    //   6454: bipush #32
    //   6456: irem
    //   6457: invokestatic abs : (I)I
    //   6460: invokevirtual charAt : (I)C
    //   6463: getstatic burp/Zg4k.ZB : Ljava/lang/String;
    //   6466: getstatic burp/Zs75.Zo : Ljava/lang/Object;
    //   6469: checkcast java/math/BigInteger
    //   6472: invokevirtual intValue : ()I
    //   6475: bipush #32
    //   6477: irem
    //   6478: invokestatic abs : (I)I
    //   6481: invokevirtual charAt : (I)C
    //   6484: if_icmple -> 6830
    //   6487: sipush #12060
    //   6490: sipush #15055
    //   6493: invokestatic a : (II)Ljava/lang/String;
    //   6496: iconst_1
    //   6497: ldc burp/Zkaw
    //   6499: invokevirtual getClassLoader : ()Ljava/lang/ClassLoader;
    //   6502: invokestatic forName : (Ljava/lang/String;ZLjava/lang/ClassLoader;)Ljava/lang/Class;
    //   6505: invokevirtual getDeclaredFields : ()[Ljava/lang/reflect/Field;
    //   6508: astore #5
    //   6510: aload #5
    //   6512: arraylength
    //   6513: istore #6
    //   6515: iconst_0
    //   6516: istore #7
    //   6518: iload #7
    //   6520: iload #6
    //   6522: if_icmpge -> 6660
    //   6525: aload #5
    //   6527: iload #7
    //   6529: aaload
    //   6530: astore #8
    //   6532: aload #8
    //   6534: invokevirtual getModifiers : ()I
    //   6537: invokestatic isStatic : (I)Z
    //   6540: ifne -> 6550
    //   6543: goto -> 6653
    //   6546: invokestatic a : (Ljava/lang/Throwable;)Ljava/lang/Throwable;
    //   6549: athrow
    //   6550: aload #8
    //   6552: invokevirtual getType : ()Ljava/lang/Class;
    //   6555: astore #9
    //   6557: aload #9
    //   6559: ifnull -> 6640
    //   6562: aload #9
    //   6564: invokevirtual isPrimitive : ()Z
    //   6567: ifne -> 6640
    //   6570: goto -> 6577
    //   6573: invokestatic a : (Ljava/lang/Throwable;)Ljava/lang/Throwable;
    //   6576: athrow
    //   6577: aload #9
    //   6579: invokevirtual getPackage : ()Ljava/lang/Package;
    //   6582: ifnull -> 6640
    //   6585: goto -> 6592
    //   6588: invokestatic a : (Ljava/lang/Throwable;)Ljava/lang/Throwable;
    //   6591: athrow
    //   6592: aload #9
    //   6594: invokevirtual getPackage : ()Ljava/lang/Package;
    //   6597: invokevirtual getName : ()Ljava/lang/String;
    //   6600: ifnull -> 6640
    //   6603: goto -> 6610
    //   6606: invokestatic a : (Ljava/lang/Throwable;)Ljava/lang/Throwable;
    //   6609: athrow
    //   6610: aload #9
    //   6612: invokevirtual getPackage : ()Ljava/lang/Package;
    //   6615: invokevirtual getName : ()Ljava/lang/String;
    //   6618: sipush #12038
    //   6621: sipush #11427
    //   6624: invokestatic a : (II)Ljava/lang/String;
    //   6627: invokevirtual startsWith : (Ljava/lang/String;)Z
    //   6630: ifne -> 6640
    //   6633: goto -> 6640
    //   6636: invokestatic a : (Ljava/lang/Throwable;)Ljava/lang/Throwable;
    //   6639: athrow
    //   6640: aload #8
    //   6642: iconst_1
    //   6643: invokevirtual setAccessible : (Z)V
    //   6646: aload #8
    //   6648: aconst_null
    //   6649: invokevirtual get : (Ljava/lang/Object;)Ljava/lang/Object;
    //   6652: pop
    //   6653: iinc #7, 1
    //   6656: iload_2
    //   6657: ifeq -> 6518
    //   6660: sipush #12036
    //   6663: sipush #15045
    //   6666: invokestatic a : (II)Ljava/lang/String;
    //   6669: invokestatic forName : (Ljava/lang/String;)Ljava/lang/Class;
    //   6672: invokevirtual getDeclaredMethods : ()[Ljava/lang/reflect/Method;
    //   6675: astore #5
    //   6677: aload #5
    //   6679: arraylength
    //   6680: istore #6
    //   6682: iconst_0
    //   6683: istore #7
    //   6685: iload #7
    //   6687: iload #6
    //   6689: if_icmpge -> 6826
    //   6692: aload #5
    //   6694: iload #7
    //   6696: aaload
    //   6697: astore #8
    //   6699: aload #8
    //   6701: invokevirtual getParameterTypes : ()[Ljava/lang/Class;
    //   6704: pop
    //   6705: aload #8
    //   6707: invokevirtual getModifiers : ()I
    //   6710: invokestatic isStatic : (I)Z
    //   6713: ifeq -> 6812
    //   6716: aload #8
    //   6718: invokevirtual getParameterTypes : ()[Ljava/lang/Class;
    //   6721: arraylength
    //   6722: iconst_2
    //   6723: if_icmpne -> 6812
    //   6726: goto -> 6733
    //   6729: invokestatic a : (Ljava/lang/Throwable;)Ljava/lang/Throwable;
    //   6732: athrow
    //   6733: aload #8
    //   6735: invokevirtual getReturnType : ()Ljava/lang/Class;
    //   6738: getstatic java/lang/Boolean.TYPE : Ljava/lang/Class;
    //   6741: if_acmpne -> 6812
    //   6744: goto -> 6751
    //   6747: invokestatic a : (Ljava/lang/Throwable;)Ljava/lang/Throwable;
    //   6750: athrow
    //   6751: aload #8
    //   6753: iconst_1
    //   6754: invokevirtual setAccessible : (Z)V
    //   6757: aload #8
    //   6759: aconst_null
    //   6760: iconst_2
    //   6761: anewarray java/lang/Object
    //   6764: dup
    //   6765: iconst_0
    //   6766: aload_0
    //   6767: aastore
    //   6768: dup
    //   6769: iconst_1
    //   6770: aload_1
    //   6771: ifnonnull -> 6789
    //   6774: goto -> 6781
    //   6777: invokestatic a : (Ljava/lang/Throwable;)Ljava/lang/Throwable;
    //   6780: athrow
    //   6781: aload_1
    //   6782: goto -> 6796
    //   6785: invokestatic a : (Ljava/lang/Throwable;)Ljava/lang/Throwable;
    //   6788: athrow
    //   6789: aload_1
    //   6790: checkcast [B
    //   6793: invokevirtual clone : ()Ljava/lang/Object;
    //   6796: aastore
    //   6797: invokevirtual invoke : (Ljava/lang/Object;[Ljava/lang/Object;)Ljava/lang/Object;
    //   6800: checkcast java/lang/Boolean
    //   6803: invokevirtual booleanValue : ()Z
    //   6806: istore #4
    //   6808: iload_2
    //   6809: ifeq -> 6826
    //   6812: iinc #7, 1
    //   6815: iload_2
    //   6816: ifeq -> 6685
    //   6819: goto -> 6826
    //   6822: invokestatic a : (Ljava/lang/Throwable;)Ljava/lang/Throwable;
    //   6825: athrow
    //   6826: iload_2
    //   6827: ifeq -> 7169
    //   6830: sipush #12035
    //   6833: sipush #-17555
    //   6836: invokestatic a : (II)Ljava/lang/String;
    //   6839: iconst_1
    //   6840: ldc burp/Zm7x
    //   6842: invokevirtual getClassLoader : ()Ljava/lang/ClassLoader;
    //   6845: invokestatic forName : (Ljava/lang/String;ZLjava/lang/ClassLoader;)Ljava/lang/Class;
    //   6848: invokevirtual getDeclaredFields : ()[Ljava/lang/reflect/Field;
    //   6851: astore #5
    //   6853: aload #5
    //   6855: arraylength
    //   6856: istore #6
    //   6858: iconst_0
    //   6859: istore #7
    //   6861: iload #7
    //   6863: iload #6
    //   6865: if_icmpge -> 7003
    //   6868: aload #5
    //   6870: iload #7
    //   6872: aaload
    //   6873: astore #8
    //   6875: aload #8
    //   6877: invokevirtual getModifiers : ()I
    //   6880: invokestatic isStatic : (I)Z
    //   6883: ifne -> 6893
    //   6886: goto -> 6996
    //   6889: invokestatic a : (Ljava/lang/Throwable;)Ljava/lang/Throwable;
    //   6892: athrow
    //   6893: aload #8
    //   6895: invokevirtual getType : ()Ljava/lang/Class;
    //   6898: astore #9
    //   6900: aload #9
    //   6902: ifnull -> 6983
    //   6905: aload #9
    //   6907: invokevirtual isPrimitive : ()Z
    //   6910: ifne -> 6983
    //   6913: goto -> 6920
    //   6916: invokestatic a : (Ljava/lang/Throwable;)Ljava/lang/Throwable;
    //   6919: athrow
    //   6920: aload #9
    //   6922: invokevirtual getPackage : ()Ljava/lang/Package;
    //   6925: ifnull -> 6983
    //   6928: goto -> 6935
    //   6931: invokestatic a : (Ljava/lang/Throwable;)Ljava/lang/Throwable;
    //   6934: athrow
    //   6935: aload #9
    //   6937: invokevirtual getPackage : ()Ljava/lang/Package;
    //   6940: invokevirtual getName : ()Ljava/lang/String;
    //   6943: ifnull -> 6983
    //   6946: goto -> 6953
    //   6949: invokestatic a : (Ljava/lang/Throwable;)Ljava/lang/Throwable;
    //   6952: athrow
    //   6953: aload #9
    //   6955: invokevirtual getPackage : ()Ljava/lang/Package;
    //   6958: invokevirtual getName : ()Ljava/lang/String;
    //   6961: sipush #12038
    //   6964: sipush #11427
    //   6967: invokestatic a : (II)Ljava/lang/String;
    //   6970: invokevirtual startsWith : (Ljava/lang/String;)Z
    //   6973: ifne -> 6983
    //   6976: goto -> 6983
    //   6979: invokestatic a : (Ljava/lang/Throwable;)Ljava/lang/Throwable;
    //   6982: athrow
    //   6983: aload #8
    //   6985: iconst_1
    //   6986: invokevirtual setAccessible : (Z)V
    //   6989: aload #8
    //   6991: aconst_null
    //   6992: invokevirtual get : (Ljava/lang/Object;)Ljava/lang/Object;
    //   6995: pop
    //   6996: iinc #7, 1
    //   6999: iload_2
    //   7000: ifeq -> 6861
    //   7003: sipush #12046
    //   7006: sipush #10356
    //   7009: invokestatic a : (II)Ljava/lang/String;
    //   7012: invokestatic forName : (Ljava/lang/String;)Ljava/lang/Class;
    //   7015: invokevirtual getDeclaredMethods : ()[Ljava/lang/reflect/Method;
    //   7018: astore #5
    //   7020: aload #5
    //   7022: arraylength
    //   7023: istore #6
    //   7025: iconst_0
    //   7026: istore #7
    //   7028: iload #7
    //   7030: iload #6
    //   7032: if_icmpge -> 7169
    //   7035: aload #5
    //   7037: iload #7
    //   7039: aaload
    //   7040: astore #8
    //   7042: aload #8
    //   7044: invokevirtual getParameterTypes : ()[Ljava/lang/Class;
    //   7047: pop
    //   7048: aload #8
    //   7050: invokevirtual getModifiers : ()I
    //   7053: invokestatic isStatic : (I)Z
    //   7056: ifeq -> 7155
    //   7059: aload #8
    //   7061: invokevirtual getParameterTypes : ()[Ljava/lang/Class;
    //   7064: arraylength
    //   7065: iconst_2
    //   7066: if_icmpne -> 7155
    //   7069: goto -> 7076
    //   7072: invokestatic a : (Ljava/lang/Throwable;)Ljava/lang/Throwable;
    //   7075: athrow
    //   7076: aload #8
    //   7078: invokevirtual getReturnType : ()Ljava/lang/Class;
    //   7081: getstatic java/lang/Boolean.TYPE : Ljava/lang/Class;
    //   7084: if_acmpne -> 7155
    //   7087: goto -> 7094
    //   7090: invokestatic a : (Ljava/lang/Throwable;)Ljava/lang/Throwable;
    //   7093: athrow
    //   7094: aload #8
    //   7096: iconst_1
    //   7097: invokevirtual setAccessible : (Z)V
    //   7100: aload #8
    //   7102: aconst_null
    //   7103: iconst_2
    //   7104: anewarray java/lang/Object
    //   7107: dup
    //   7108: iconst_0
    //   7109: aload_0
    //   7110: aastore
    //   7111: dup
    //   7112: iconst_1
    //   7113: aload_1
    //   7114: ifnonnull -> 7132
    //   7117: goto -> 7124
    //   7120: invokestatic a : (Ljava/lang/Throwable;)Ljava/lang/Throwable;
    //   7123: athrow
    //   7124: aload_1
    //   7125: goto -> 7139
    //   7128: invokestatic a : (Ljava/lang/Throwable;)Ljava/lang/Throwable;
    //   7131: athrow
    //   7132: aload_1
    //   7133: checkcast [B
    //   7136: invokevirtual clone : ()Ljava/lang/Object;
    //   7139: aastore
    //   7140: invokevirtual invoke : (Ljava/lang/Object;[Ljava/lang/Object;)Ljava/lang/Object;
    //   7143: checkcast java/lang/Boolean
    //   7146: invokevirtual booleanValue : ()Z
    //   7149: istore #4
    //   7151: iload_2
    //   7152: ifeq -> 7169
    //   7155: iinc #7, 1
    //   7158: iload_2
    //   7159: ifeq -> 7028
    //   7162: goto -> 7169
    //   7165: invokestatic a : (Ljava/lang/Throwable;)Ljava/lang/Throwable;
    //   7168: athrow
    //   7169: iload #4
    //   7171: ifeq -> 7177
    //   7174: iload #4
    //   7176: ireturn
    //   7177: getstatic burp/Zza8.Zm : Ljava/lang/String;
    //   7180: getstatic burp/Zm52.ZR : Ljava/lang/Object;
    //   7183: checkcast java/math/BigInteger
    //   7186: invokevirtual intValue : ()I
    //   7189: bipush #32
    //   7191: irem
    //   7192: invokestatic abs : (I)I
    //   7195: invokevirtual charAt : (I)C
    //   7198: getstatic burp/Zs83.ZG : Ljava/lang/String;
    //   7201: getstatic burp/Zmj8.Zz : Ljava/lang/Object;
    //   7204: checkcast java/math/BigInteger
    //   7207: invokevirtual intValue : ()I
    //   7210: bipush #32
    //   7212: irem
    //   7213: invokestatic abs : (I)I
    //   7216: invokevirtual charAt : (I)C
    //   7219: if_icmple -> 7565
    //   7222: sipush #12063
    //   7225: sipush #-1878
    //   7228: invokestatic a : (II)Ljava/lang/String;
    //   7231: iconst_1
    //   7232: ldc burp/Zmh0
    //   7234: invokevirtual getClassLoader : ()Ljava/lang/ClassLoader;
    //   7237: invokestatic forName : (Ljava/lang/String;ZLjava/lang/ClassLoader;)Ljava/lang/Class;
    //   7240: invokevirtual getDeclaredFields : ()[Ljava/lang/reflect/Field;
    //   7243: astore #5
    //   7245: aload #5
    //   7247: arraylength
    //   7248: istore #6
    //   7250: iconst_0
    //   7251: istore #7
    //   7253: iload #7
    //   7255: iload #6
    //   7257: if_icmpge -> 7395
    //   7260: aload #5
    //   7262: iload #7
    //   7264: aaload
    //   7265: astore #8
    //   7267: aload #8
    //   7269: invokevirtual getModifiers : ()I
    //   7272: invokestatic isStatic : (I)Z
    //   7275: ifne -> 7285
    //   7278: goto -> 7388
    //   7281: invokestatic a : (Ljava/lang/Throwable;)Ljava/lang/Throwable;
    //   7284: athrow
    //   7285: aload #8
    //   7287: invokevirtual getType : ()Ljava/lang/Class;
    //   7290: astore #9
    //   7292: aload #9
    //   7294: ifnull -> 7375
    //   7297: aload #9
    //   7299: invokevirtual isPrimitive : ()Z
    //   7302: ifne -> 7375
    //   7305: goto -> 7312
    //   7308: invokestatic a : (Ljava/lang/Throwable;)Ljava/lang/Throwable;
    //   7311: athrow
    //   7312: aload #9
    //   7314: invokevirtual getPackage : ()Ljava/lang/Package;
    //   7317: ifnull -> 7375
    //   7320: goto -> 7327
    //   7323: invokestatic a : (Ljava/lang/Throwable;)Ljava/lang/Throwable;
    //   7326: athrow
    //   7327: aload #9
    //   7329: invokevirtual getPackage : ()Ljava/lang/Package;
    //   7332: invokevirtual getName : ()Ljava/lang/String;
    //   7335: ifnull -> 7375
    //   7338: goto -> 7345
    //   7341: invokestatic a : (Ljava/lang/Throwable;)Ljava/lang/Throwable;
    //   7344: athrow
    //   7345: aload #9
    //   7347: invokevirtual getPackage : ()Ljava/lang/Package;
    //   7350: invokevirtual getName : ()Ljava/lang/String;
    //   7353: sipush #12038
    //   7356: sipush #11427
    //   7359: invokestatic a : (II)Ljava/lang/String;
    //   7362: invokevirtual startsWith : (Ljava/lang/String;)Z
    //   7365: ifne -> 7375
    //   7368: goto -> 7375
    //   7371: invokestatic a : (Ljava/lang/Throwable;)Ljava/lang/Throwable;
    //   7374: athrow
    //   7375: aload #8
    //   7377: iconst_1
    //   7378: invokevirtual setAccessible : (Z)V
    //   7381: aload #8
    //   7383: aconst_null
    //   7384: invokevirtual get : (Ljava/lang/Object;)Ljava/lang/Object;
    //   7387: pop
    //   7388: iinc #7, 1
    //   7391: iload_2
    //   7392: ifeq -> 7253
    //   7395: sipush #12040
    //   7398: sipush #-28307
    //   7401: invokestatic a : (II)Ljava/lang/String;
    //   7404: invokestatic forName : (Ljava/lang/String;)Ljava/lang/Class;
    //   7407: invokevirtual getDeclaredMethods : ()[Ljava/lang/reflect/Method;
    //   7410: astore #5
    //   7412: aload #5
    //   7414: arraylength
    //   7415: istore #6
    //   7417: iconst_0
    //   7418: istore #7
    //   7420: iload #7
    //   7422: iload #6
    //   7424: if_icmpge -> 7561
    //   7427: aload #5
    //   7429: iload #7
    //   7431: aaload
    //   7432: astore #8
    //   7434: aload #8
    //   7436: invokevirtual getParameterTypes : ()[Ljava/lang/Class;
    //   7439: pop
    //   7440: aload #8
    //   7442: invokevirtual getModifiers : ()I
    //   7445: invokestatic isStatic : (I)Z
    //   7448: ifeq -> 7547
    //   7451: aload #8
    //   7453: invokevirtual getParameterTypes : ()[Ljava/lang/Class;
    //   7456: arraylength
    //   7457: iconst_2
    //   7458: if_icmpne -> 7547
    //   7461: goto -> 7468
    //   7464: invokestatic a : (Ljava/lang/Throwable;)Ljava/lang/Throwable;
    //   7467: athrow
    //   7468: aload #8
    //   7470: invokevirtual getReturnType : ()Ljava/lang/Class;
    //   7473: getstatic java/lang/Boolean.TYPE : Ljava/lang/Class;
    //   7476: if_acmpne -> 7547
    //   7479: goto -> 7486
    //   7482: invokestatic a : (Ljava/lang/Throwable;)Ljava/lang/Throwable;
    //   7485: athrow
    //   7486: aload #8
    //   7488: iconst_1
    //   7489: invokevirtual setAccessible : (Z)V
    //   7492: aload #8
    //   7494: aconst_null
    //   7495: iconst_2
    //   7496: anewarray java/lang/Object
    //   7499: dup
    //   7500: iconst_0
    //   7501: aload_0
    //   7502: aastore
    //   7503: dup
    //   7504: iconst_1
    //   7505: aload_1
    //   7506: ifnonnull -> 7524
    //   7509: goto -> 7516
    //   7512: invokestatic a : (Ljava/lang/Throwable;)Ljava/lang/Throwable;
    //   7515: athrow
    //   7516: aload_1
    //   7517: goto -> 7531
    //   7520: invokestatic a : (Ljava/lang/Throwable;)Ljava/lang/Throwable;
    //   7523: athrow
    //   7524: aload_1
    //   7525: checkcast [B
    //   7528: invokevirtual clone : ()Ljava/lang/Object;
    //   7531: aastore
    //   7532: invokevirtual invoke : (Ljava/lang/Object;[Ljava/lang/Object;)Ljava/lang/Object;
    //   7535: checkcast java/lang/Boolean
    //   7538: invokevirtual booleanValue : ()Z
    //   7541: istore #4
    //   7543: iload_2
    //   7544: ifeq -> 7561
    //   7547: iinc #7, 1
    //   7550: iload_2
    //   7551: ifeq -> 7420
    //   7554: goto -> 7561
    //   7557: invokestatic a : (Ljava/lang/Throwable;)Ljava/lang/Throwable;
    //   7560: athrow
    //   7561: iload_2
    //   7562: ifeq -> 7904
    //   7565: sipush #12044
    //   7568: sipush #18220
    //   7571: invokestatic a : (II)Ljava/lang/String;
    //   7574: iconst_1
    //   7575: ldc burp/Zgqi
    //   7577: invokevirtual getClassLoader : ()Ljava/lang/ClassLoader;
    //   7580: invokestatic forName : (Ljava/lang/String;ZLjava/lang/ClassLoader;)Ljava/lang/Class;
    //   7583: invokevirtual getDeclaredFields : ()[Ljava/lang/reflect/Field;
    //   7586: astore #5
    //   7588: aload #5
    //   7590: arraylength
    //   7591: istore #6
    //   7593: iconst_0
    //   7594: istore #7
    //   7596: iload #7
    //   7598: iload #6
    //   7600: if_icmpge -> 7738
    //   7603: aload #5
    //   7605: iload #7
    //   7607: aaload
    //   7608: astore #8
    //   7610: aload #8
    //   7612: invokevirtual getModifiers : ()I
    //   7615: invokestatic isStatic : (I)Z
    //   7618: ifne -> 7628
    //   7621: goto -> 7731
    //   7624: invokestatic a : (Ljava/lang/Throwable;)Ljava/lang/Throwable;
    //   7627: athrow
    //   7628: aload #8
    //   7630: invokevirtual getType : ()Ljava/lang/Class;
    //   7633: astore #9
    //   7635: aload #9
    //   7637: ifnull -> 7718
    //   7640: aload #9
    //   7642: invokevirtual isPrimitive : ()Z
    //   7645: ifne -> 7718
    //   7648: goto -> 7655
    //   7651: invokestatic a : (Ljava/lang/Throwable;)Ljava/lang/Throwable;
    //   7654: athrow
    //   7655: aload #9
    //   7657: invokevirtual getPackage : ()Ljava/lang/Package;
    //   7660: ifnull -> 7718
    //   7663: goto -> 7670
    //   7666: invokestatic a : (Ljava/lang/Throwable;)Ljava/lang/Throwable;
    //   7669: athrow
    //   7670: aload #9
    //   7672: invokevirtual getPackage : ()Ljava/lang/Package;
    //   7675: invokevirtual getName : ()Ljava/lang/String;
    //   7678: ifnull -> 7718
    //   7681: goto -> 7688
    //   7684: invokestatic a : (Ljava/lang/Throwable;)Ljava/lang/Throwable;
    //   7687: athrow
    //   7688: aload #9
    //   7690: invokevirtual getPackage : ()Ljava/lang/Package;
    //   7693: invokevirtual getName : ()Ljava/lang/String;
    //   7696: sipush #12038
    //   7699: sipush #11427
    //   7702: invokestatic a : (II)Ljava/lang/String;
    //   7705: invokevirtual startsWith : (Ljava/lang/String;)Z
    //   7708: ifne -> 7718
    //   7711: goto -> 7718
    //   7714: invokestatic a : (Ljava/lang/Throwable;)Ljava/lang/Throwable;
    //   7717: athrow
    //   7718: aload #8
    //   7720: iconst_1
    //   7721: invokevirtual setAccessible : (Z)V
    //   7724: aload #8
    //   7726: aconst_null
    //   7727: invokevirtual get : (Ljava/lang/Object;)Ljava/lang/Object;
    //   7730: pop
    //   7731: iinc #7, 1
    //   7734: iload_2
    //   7735: ifeq -> 7596
    //   7738: sipush #12048
    //   7741: sipush #19446
    //   7744: invokestatic a : (II)Ljava/lang/String;
    //   7747: invokestatic forName : (Ljava/lang/String;)Ljava/lang/Class;
    //   7750: invokevirtual getDeclaredMethods : ()[Ljava/lang/reflect/Method;
    //   7753: astore #5
    //   7755: aload #5
    //   7757: arraylength
    //   7758: istore #6
    //   7760: iconst_0
    //   7761: istore #7
    //   7763: iload #7
    //   7765: iload #6
    //   7767: if_icmpge -> 7904
    //   7770: aload #5
    //   7772: iload #7
    //   7774: aaload
    //   7775: astore #8
    //   7777: aload #8
    //   7779: invokevirtual getParameterTypes : ()[Ljava/lang/Class;
    //   7782: pop
    //   7783: aload #8
    //   7785: invokevirtual getModifiers : ()I
    //   7788: invokestatic isStatic : (I)Z
    //   7791: ifeq -> 7890
    //   7794: aload #8
    //   7796: invokevirtual getParameterTypes : ()[Ljava/lang/Class;
    //   7799: arraylength
    //   7800: iconst_2
    //   7801: if_icmpne -> 7890
    //   7804: goto -> 7811
    //   7807: invokestatic a : (Ljava/lang/Throwable;)Ljava/lang/Throwable;
    //   7810: athrow
    //   7811: aload #8
    //   7813: invokevirtual getReturnType : ()Ljava/lang/Class;
    //   7816: getstatic java/lang/Boolean.TYPE : Ljava/lang/Class;
    //   7819: if_acmpne -> 7890
    //   7822: goto -> 7829
    //   7825: invokestatic a : (Ljava/lang/Throwable;)Ljava/lang/Throwable;
    //   7828: athrow
    //   7829: aload #8
    //   7831: iconst_1
    //   7832: invokevirtual setAccessible : (Z)V
    //   7835: aload #8
    //   7837: aconst_null
    //   7838: iconst_2
    //   7839: anewarray java/lang/Object
    //   7842: dup
    //   7843: iconst_0
    //   7844: aload_0
    //   7845: aastore
    //   7846: dup
    //   7847: iconst_1
    //   7848: aload_1
    //   7849: ifnonnull -> 7867
    //   7852: goto -> 7859
    //   7855: invokestatic a : (Ljava/lang/Throwable;)Ljava/lang/Throwable;
    //   7858: athrow
    //   7859: aload_1
    //   7860: goto -> 7874
    //   7863: invokestatic a : (Ljava/lang/Throwable;)Ljava/lang/Throwable;
    //   7866: athrow
    //   7867: aload_1
    //   7868: checkcast [B
    //   7871: invokevirtual clone : ()Ljava/lang/Object;
    //   7874: aastore
    //   7875: invokevirtual invoke : (Ljava/lang/Object;[Ljava/lang/Object;)Ljava/lang/Object;
    //   7878: checkcast java/lang/Boolean
    //   7881: invokevirtual booleanValue : ()Z
    //   7884: istore #4
    //   7886: iload_2
    //   7887: ifeq -> 7904
    //   7890: iinc #7, 1
    //   7893: iload_2
    //   7894: ifeq -> 7763
    //   7897: goto -> 7904
    //   7900: invokestatic a : (Ljava/lang/Throwable;)Ljava/lang/Throwable;
    //   7903: athrow
    //   7904: iload #4
    //   7906: ireturn
    //   7907: astore_3
    //   7908: new java/lang/Exception
    //   7911: dup
    //   7912: aload_3
    //   7913: invokevirtual getMessage : ()Ljava/lang/String;
    //   7916: invokespecial <init> : (Ljava/lang/String;)V
    //   7919: athrow
    // Exception table:
    //   from	to	target	type
    //   4	4971	7907	java/lang/Throwable
    //   22	198	201	java/lang/Throwable
    //   168	235	238	java/lang/Throwable
    //   205	272	275	java/lang/Throwable
    //   242	309	312	java/lang/Throwable
    //   279	346	349	java/lang/Throwable
    //   316	383	386	java/lang/Throwable
    //   353	420	423	java/lang/Throwable
    //   390	457	460	java/lang/Throwable
    //   427	494	497	java/lang/Throwable
    //   464	531	534	java/lang/Throwable
    //   501	568	571	java/lang/Throwable
    //   538	605	608	java/lang/Throwable
    //   575	642	645	java/lang/Throwable
    //   612	679	682	java/lang/Throwable
    //   649	716	719	java/lang/Throwable
    //   686	753	756	java/lang/Throwable
    //   723	790	793	java/lang/Throwable
    //   760	827	830	java/lang/Throwable
    //   797	864	867	java/lang/Throwable
    //   834	901	904	java/lang/Throwable
    //   871	938	941	java/lang/Throwable
    //   908	975	978	java/lang/Throwable
    //   945	1012	1015	java/lang/Throwable
    //   982	1049	1052	java/lang/Throwable
    //   1019	1086	1089	java/lang/Throwable
    //   1056	1123	1126	java/lang/Throwable
    //   1093	1160	1163	java/lang/Throwable
    //   1130	1197	1200	java/lang/Throwable
    //   1167	1234	1237	java/lang/Throwable
    //   1204	1271	1274	java/lang/Throwable
    //   1241	1308	1311	java/lang/Throwable
    //   1278	1341	1344	java/lang/Throwable
    //   1528	1543	1543	java/lang/Throwable
    //   2545	2571	2571	java/lang/Throwable
    //   2652	2667	2667	java/lang/Throwable
    //   3849	3874	3877	java/lang/Throwable
    //   3945	3959	3959	java/lang/Throwable
    //   3970	3983	3986	java/lang/Throwable
    //   3975	3998	4001	java/lang/Throwable
    //   3990	4016	4019	java/lang/Throwable
    //   4005	4046	4049	java/lang/Throwable
    //   4112	4139	4142	java/lang/Throwable
    //   4129	4160	4163	java/lang/Throwable
    //   4146	4190	4193	java/lang/Throwable
    //   4167	4201	4201	java/lang/Throwable
    //   4212	4228	4231	java/lang/Throwable
    //   4328	4342	4342	java/lang/Throwable
    //   4353	4366	4369	java/lang/Throwable
    //   4358	4381	4384	java/lang/Throwable
    //   4373	4399	4402	java/lang/Throwable
    //   4388	4429	4432	java/lang/Throwable
    //   4495	4522	4525	java/lang/Throwable
    //   4512	4540	4543	java/lang/Throwable
    //   4529	4570	4573	java/lang/Throwable
    //   4547	4581	4581	java/lang/Throwable
    //   4604	4615	4618	java/lang/Throwable
    //   4670	4684	4684	java/lang/Throwable
    //   4695	4708	4711	java/lang/Throwable
    //   4700	4723	4726	java/lang/Throwable
    //   4715	4741	4744	java/lang/Throwable
    //   4730	4771	4774	java/lang/Throwable
    //   4837	4864	4867	java/lang/Throwable
    //   4854	4882	4885	java/lang/Throwable
    //   4871	4912	4915	java/lang/Throwable
    //   4889	4923	4923	java/lang/Throwable
    //   4946	4957	4960	java/lang/Throwable
    //   4972	5706	7907	java/lang/Throwable
    //   5062	5076	5076	java/lang/Throwable
    //   5087	5100	5103	java/lang/Throwable
    //   5092	5115	5118	java/lang/Throwable
    //   5107	5133	5136	java/lang/Throwable
    //   5122	5163	5166	java/lang/Throwable
    //   5229	5256	5259	java/lang/Throwable
    //   5246	5274	5277	java/lang/Throwable
    //   5263	5304	5307	java/lang/Throwable
    //   5281	5315	5315	java/lang/Throwable
    //   5338	5349	5352	java/lang/Throwable
    //   5405	5419	5419	java/lang/Throwable
    //   5430	5443	5446	java/lang/Throwable
    //   5435	5458	5461	java/lang/Throwable
    //   5450	5476	5479	java/lang/Throwable
    //   5465	5506	5509	java/lang/Throwable
    //   5572	5599	5602	java/lang/Throwable
    //   5589	5617	5620	java/lang/Throwable
    //   5606	5647	5650	java/lang/Throwable
    //   5624	5658	5658	java/lang/Throwable
    //   5681	5692	5695	java/lang/Throwable
    //   5707	6441	7907	java/lang/Throwable
    //   5797	5811	5811	java/lang/Throwable
    //   5822	5835	5838	java/lang/Throwable
    //   5827	5850	5853	java/lang/Throwable
    //   5842	5868	5871	java/lang/Throwable
    //   5857	5898	5901	java/lang/Throwable
    //   5964	5991	5994	java/lang/Throwable
    //   5981	6009	6012	java/lang/Throwable
    //   5998	6039	6042	java/lang/Throwable
    //   6016	6050	6050	java/lang/Throwable
    //   6073	6084	6087	java/lang/Throwable
    //   6140	6154	6154	java/lang/Throwable
    //   6165	6178	6181	java/lang/Throwable
    //   6170	6193	6196	java/lang/Throwable
    //   6185	6211	6214	java/lang/Throwable
    //   6200	6241	6244	java/lang/Throwable
    //   6307	6334	6337	java/lang/Throwable
    //   6324	6352	6355	java/lang/Throwable
    //   6341	6382	6385	java/lang/Throwable
    //   6359	6393	6393	java/lang/Throwable
    //   6416	6427	6430	java/lang/Throwable
    //   6442	7176	7907	java/lang/Throwable
    //   6532	6546	6546	java/lang/Throwable
    //   6557	6570	6573	java/lang/Throwable
    //   6562	6585	6588	java/lang/Throwable
    //   6577	6603	6606	java/lang/Throwable
    //   6592	6633	6636	java/lang/Throwable
    //   6699	6726	6729	java/lang/Throwable
    //   6716	6744	6747	java/lang/Throwable
    //   6733	6774	6777	java/lang/Throwable
    //   6751	6785	6785	java/lang/Throwable
    //   6808	6819	6822	java/lang/Throwable
    //   6875	6889	6889	java/lang/Throwable
    //   6900	6913	6916	java/lang/Throwable
    //   6905	6928	6931	java/lang/Throwable
    //   6920	6946	6949	java/lang/Throwable
    //   6935	6976	6979	java/lang/Throwable
    //   7042	7069	7072	java/lang/Throwable
    //   7059	7087	7090	java/lang/Throwable
    //   7076	7117	7120	java/lang/Throwable
    //   7094	7128	7128	java/lang/Throwable
    //   7151	7162	7165	java/lang/Throwable
    //   7177	7906	7907	java/lang/Throwable
    //   7267	7281	7281	java/lang/Throwable
    //   7292	7305	7308	java/lang/Throwable
    //   7297	7320	7323	java/lang/Throwable
    //   7312	7338	7341	java/lang/Throwable
    //   7327	7368	7371	java/lang/Throwable
    //   7434	7461	7464	java/lang/Throwable
    //   7451	7479	7482	java/lang/Throwable
    //   7468	7509	7512	java/lang/Throwable
    //   7486	7520	7520	java/lang/Throwable
    //   7543	7554	7557	java/lang/Throwable
    //   7610	7624	7624	java/lang/Throwable
    //   7635	7648	7651	java/lang/Throwable
    //   7640	7663	7666	java/lang/Throwable
    //   7655	7681	7684	java/lang/Throwable
    //   7670	7711	7714	java/lang/Throwable
    //   7777	7804	7807	java/lang/Throwable
    //   7794	7822	7825	java/lang/Throwable
    //   7811	7852	7855	java/lang/Throwable
    //   7829	7863	7863	java/lang/Throwable
    //   7886	7897	7900	java/lang/Throwable
  }
  
  static {
    // Byte code:
    //   0: bipush #32
    //   2: anewarray java/lang/String
    //   5: astore #5
    //   7: iconst_0
    //   8: istore_3
    //   9: ldc 'v-s`a.\\t?\\t[\\nI\\t}pU L3h\\r\\bq#hb??\\tz0.xA\\t~8O\\tKj6\\t7GB\\t!~\\trO\\t\\b'`?X<\\tk\\f<G^N\\t\6n\\t9R\\t[\\nCE\\t!9$9Kt7\\r#1zI[\\tP0k??\\t&\\tg^>\\f\\t"_\\tq}\\tO]Fl 3/ gT@G ?b5=/6MN7nIL1n,|r_\\r `4JdwS~^?nRfOHnQ,X]:'
    //   11: dup
    //   12: astore_2
    //   13: invokevirtual length : ()I
    //   16: istore #4
    //   18: bipush #9
    //   20: istore_1
    //   21: iconst_m1
    //   22: istore_0
    //   23: bipush #79
    //   25: iinc #0, 1
    //   28: aload_2
    //   29: iload_0
    //   30: dup
    //   31: iload_1
    //   32: iadd
    //   33: invokevirtual substring : (II)Ljava/lang/String;
    //   36: iconst_m1
    //   37: goto -> 143
    //   40: aload #5
    //   42: swap
    //   43: iload_3
    //   44: iinc #3, 1
    //   47: swap
    //   48: aastore
    //   49: iload_0
    //   50: iload_1
    //   51: iadd
    //   52: dup
    //   53: istore_0
    //   54: iload #4
    //   56: if_icmpge -> 68
    //   59: aload_2
    //   60: iload_0
    //   61: invokevirtual charAt : (I)C
    //   64: istore_1
    //   65: goto -> 23
    //   68: ldc ':/aT\\tl^ec3'
    //   70: dup
    //   71: astore_2
    //   72: invokevirtual length : ()I
    //   75: istore #4
    //   77: bipush #9
    //   79: istore_1
    //   80: iconst_m1
    //   81: istore_0
    //   82: bipush #57
    //   84: iinc #0, 1
    //   87: aload_2
    //   88: iload_0
    //   89: dup
    //   90: iload_1
    //   91: iadd
    //   92: invokevirtual substring : (II)Ljava/lang/String;
    //   95: iconst_0
    //   96: goto -> 143
    //   99: aload #5
    //   101: swap
    //   102: iload_3
    //   103: iinc #3, 1
    //   106: swap
    //   107: aastore
    //   108: iload_0
    //   109: iload_1
    //   110: iadd
    //   111: dup
    //   112: istore_0
    //   113: iload #4
    //   115: if_icmpge -> 127
    //   118: aload_2
    //   119: iload_0
    //   120: invokevirtual charAt : (I)C
    //   123: istore_1
    //   124: goto -> 82
    //   127: aload #5
    //   129: putstatic burp/Zg4d.a : [Ljava/lang/String;
    //   132: bipush #32
    //   134: anewarray java/lang/String
    //   137: putstatic burp/Zg4d.b : [Ljava/lang/String;
    //   140: goto -> 300
    //   143: dup_x2
    //   144: pop
    //   145: invokevirtual toCharArray : ()[C
    //   148: dup_x1
    //   149: arraylength
    //   150: dup_x2
    //   151: pop
    //   152: iconst_0
    //   153: istore #6
    //   155: dup2_x1
    //   156: pop2
    //   157: dup_x2
    //   158: iconst_1
    //   159: if_icmpgt -> 260
    //   162: dup2
    //   163: swap
    //   164: iload #6
    //   166: dup2_x1
    //   167: caload
    //   168: swap
    //   169: iload #6
    //   171: bipush #7
    //   173: irem
    //   174: tableswitch default -> 242, 0 -> 212, 1 -> 217, 2 -> 222, 3 -> 227, 4 -> 232, 5 -> 237
    //   212: bipush #84
    //   214: goto -> 244
    //   217: bipush #76
    //   219: goto -> 244
    //   222: bipush #17
    //   224: goto -> 244
    //   227: bipush #113
    //   229: goto -> 244
    //   232: bipush #43
    //   234: goto -> 244
    //   237: bipush #105
    //   239: goto -> 244
    //   242: bipush #83
    //   244: ixor
    //   245: ixor
    //   246: i2c
    //   247: castore
    //   248: iinc #6, 1
    //   251: dup
    //   252: ifne -> 260
    //   255: dup2
    //   256: dup_x1
    //   257: goto -> 166
    //   260: dup2_x1
    //   261: pop2
    //   262: dup_x2
    //   263: iload #6
    //   265: if_icmpgt -> 162
    //   268: pop
    //   269: new java/lang/String
    //   272: dup_x1
    //   273: swap
    //   274: invokespecial <init> : ([C)V
    //   277: invokevirtual intern : ()Ljava/lang/String;
    //   280: swap
    //   281: pop
    //   282: swap
    //   283: tableswitch default -> 40, 0 -> 99
    //   300: new java/math/BigInteger
    //   303: dup
    //   304: iconst_1
    //   305: bipush #32
    //   307: newarray byte
    //   309: dup
    //   310: iconst_0
    //   311: bipush #65
    //   313: bastore
    //   314: dup
    //   315: iconst_1
    //   316: bipush #-104
    //   318: bastore
    //   319: dup
    //   320: iconst_2
    //   321: bipush #119
    //   323: bastore
    //   324: dup
    //   325: iconst_3
    //   326: bipush #75
    //   328: bastore
    //   329: dup
    //   330: iconst_4
    //   331: bipush #119
    //   333: bastore
    //   334: dup
    //   335: iconst_5
    //   336: bipush #57
    //   338: bastore
    //   339: dup
    //   340: bipush #6
    //   342: bipush #-53
    //   344: bastore
    //   345: dup
    //   346: bipush #7
    //   348: bipush #-24
    //   350: bastore
    //   351: dup
    //   352: bipush #8
    //   354: bipush #-60
    //   356: bastore
    //   357: dup
    //   358: bipush #9
    //   360: bipush #-46
    //   362: bastore
    //   363: dup
    //   364: bipush #10
    //   366: bipush #27
    //   368: bastore
    //   369: dup
    //   370: bipush #11
    //   372: bipush #65
    //   374: bastore
    //   375: dup
    //   376: bipush #12
    //   378: bipush #100
    //   380: bastore
    //   381: dup
    //   382: bipush #13
    //   384: bipush #-55
    //   386: bastore
    //   387: dup
    //   388: bipush #14
    //   390: bipush #-91
    //   392: bastore
    //   393: dup
    //   394: bipush #15
    //   396: bipush #49
    //   398: bastore
    //   399: dup
    //   400: bipush #16
    //   402: bipush #21
    //   404: bastore
    //   405: dup
    //   406: bipush #17
    //   408: bipush #-79
    //   410: bastore
    //   411: dup
    //   412: bipush #18
    //   414: bipush #-122
    //   416: bastore
    //   417: dup
    //   418: bipush #19
    //   420: bipush #106
    //   422: bastore
    //   423: dup
    //   424: bipush #20
    //   426: bipush #28
    //   428: bastore
    //   429: dup
    //   430: bipush #21
    //   432: bipush #8
    //   434: bastore
    //   435: dup
    //   436: bipush #22
    //   438: bipush #80
    //   440: bastore
    //   441: dup
    //   442: bipush #23
    //   444: bipush #-28
    //   446: bastore
    //   447: dup
    //   448: bipush #24
    //   450: bipush #119
    //   452: bastore
    //   453: dup
    //   454: bipush #25
    //   456: bipush #45
    //   458: bastore
    //   459: dup
    //   460: bipush #26
    //   462: bipush #12
    //   464: bastore
    //   465: dup
    //   466: bipush #27
    //   468: bipush #37
    //   470: bastore
    //   471: dup
    //   472: bipush #28
    //   474: bipush #-125
    //   476: bastore
    //   477: dup
    //   478: bipush #29
    //   480: bipush #-105
    //   482: bastore
    //   483: dup
    //   484: bipush #30
    //   486: bipush #126
    //   488: bastore
    //   489: dup
    //   490: bipush #31
    //   492: bipush #52
    //   494: bastore
    //   495: invokespecial <init> : (I[B)V
    //   498: putstatic burp/Zg4d.Zm : Ljava/lang/Object;
    //   501: sipush #12051
    //   504: sipush #20625
    //   507: invokestatic a : (II)Ljava/lang/String;
    //   510: putstatic burp/Zg4d.ZE : Ljava/lang/String;
    //   513: return
  }
  
  private static Throwable a(Throwable paramThrowable) {
    return paramThrowable;
  }
  
  private static String a(int paramInt1, int paramInt2) {
    int i = (paramInt1 ^ 0x2F0F) & 0xFFFF;
    if (b[i] == null) {
      char[] arrayOfChar = a[i].toCharArray();
      switch (arrayOfChar[0] & 0xFF) {
        case 0:
        
        case 1:
        
        case 2:
        
        case 3:
        
        case 4:
        
        case 5:
        
        case 6:
        
        case 7:
        
        case 8:
        
        case 9:
        
        case 10:
        
        case 11:
        
        case 12:
        
        case 13:
        
        case 14:
        
        case 15:
        
        case 16:
        
        case 17:
        
        case 18:
        
        case 19:
        
        case 20:
        
        case 21:
        
        case 22:
        
        case 23:
        
        case 24:
        
        case 25:
        
        case 26:
        
        case 27:
        
        case 28:
        
        case 29:
        
        case 30:
        
        case 31:
        
        case 32:
        
        case 33:
        
        case 34:
        
        case 35:
        
        case 36:
        
        case 37:
        
        case 38:
        
        case 39:
        
        case 40:
        
        case 41:
        
        case 42:
        
        case 43:
        
        case 44:
        
        case 45:
        
        case 46:
        
        case 47:
        
        case 48:
        
        case 49:
        
        case 50:
        
        case 51:
        
        case 52:
        
        case 53:
        
        case 54:
        
        case 55:
        
        case 56:
        
        case 57:
        
        case 58:
        
        case 59:
        
        case 60:
        
        case 61:
        
        case 62:
        
        case 63:
        
        case 64:
        
        case 65:
        
        case 66:
        
        case 67:
        
        case 68:
        
        case 69:
        
        case 70:
        
        case 71:
        
        case 72:
        
        case 73:
        
        case 74:
        
        case 75:
        
        case 76:
        
        case 77:
        
        case 78:
        
        case 79:
        
        case 80:
        
        case 81:
        
        case 82:
        
        case 83:
        
        case 84:
        
        case 85:
        
        case 86:
        
        case 87:
        
        case 88:
        
        case 89:
        
        case 90:
        
        case 91:
        
        case 92:
        
        case 93:
        
        case 94:
        
        case 95:
        
        case 96:
        
        case 97:
        
        case 98:
        
        case 99:
        
        case 100:
        
        case 101:
        
        case 102:
        
        case 103:
        
        case 104:
        
        case 105:
        
        case 106:
        
        case 107:
        
        case 108:
        
        case 109:
        
        case 110:
        
        case 111:
        
        case 112:
        
        case 113:
        
        case 114:
        
        case 115:
        
        case 116:
        
        case 117:
        
        case 118:
        
        case 119:
        
        case 120:
        
        case 121:
        
        case 122:
        
        case 123:
        
        case 124:
        
        case 125:
        
        case 126:
        
        case 127:
        
        case 128:
        
        case 129:
        
        case 130:
        
        case 131:
        
        case 132:
        
        case 133:
        
        case 134:
        
        case 135:
        
        case 136:
        
        case 137:
        
        case 138:
        
        case 139:
        
        case 140:
        
        case 141:
        
        case 142:
        
        case 143:
        
        case 144:
        
        case 145:
        
        case 146:
        
        case 147:
        
        case 148:
        
        case 149:
        
        case 150:
        
        case 151:
        
        case 152:
        
        case 153:
        
        case 154:
        
        case 155:
        
        case 156:
        
        case 157:
        
        case 158:
        
        case 159:
        
        case 160:
        
        case 161:
        
        case 162:
        
        case 163:
        
        case 164:
        
        case 165:
        
        case 166:
        
        case 167:
        
        case 168:
        
        case 169:
        
        case 170:
        
        case 171:
        
        case 172:
        
        case 173:
        
        case 174:
        
        case 175:
        
        case 176:
        
        case 177:
        
        case 178:
        
        case 179:
        
        case 180:
        
        case 181:
        
        case 182:
        
        case 183:
        
        case 184:
        
        case 185:
        
        case 186:
        
        case 187:
        
        case 188:
        
        case 189:
        
        case 190:
        
        case 191:
        
        case 192:
        
        case 193:
        
        case 194:
        
        case 195:
        
        case 196:
        
        case 197:
        
        case 198:
        
        case 199:
        
        case 200:
        
        case 201:
        
        case 202:
        
        case 203:
        
        case 204:
        
        case 205:
        
        case 206:
        
        case 207:
        
        case 208:
        
        case 209:
        
        case 210:
        
        case 211:
        
        case 212:
        
        case 213:
        
        case 214:
        
        case 215:
        
        case 216:
        
        case 217:
        
        case 218:
        
        case 219:
        
        case 220:
        
        case 221:
        
        case 222:
        
        case 223:
        
        case 224:
        
        case 225:
        
        case 226:
        
        case 227:
        
        case 228:
        
        case 229:
        
        case 230:
        
        case 231:
        
        case 232:
        
        case 233:
        
        case 234:
        
        case 235:
        
        case 236:
        
        case 237:
        
        case 238:
        
        case 239:
        
        case 240:
        
        case 241:
        
        case 242:
        
        case 243:
        
        case 244:
        
        case 245:
        
        case 246:
        
        case 247:
        
        case 248:
        
        case 249:
        
        case 250:
        
        case 251:
        
        case 252:
        
        case 253:
        
        case 254:
        
        default:
          break;
      } 
      byte b1 = 35;
      int j = (paramInt2 & 0xFF) - b1;
      if (j < 0)
        j += 256; 
      int k = ((paramInt2 & 0xFFFF) >>> 8) - b1;
      if (k < 0)
        k += 256; 
      for (byte b2 = 0; b2 < arrayOfChar.length; b2++) {
        int m = b2 % 2;
        if (m == 0) {
          arrayOfChar[b2] = (char)(arrayOfChar[b2] ^ j);
          j = ((j >>> 3 | j << 5) ^ arrayOfChar[b2]) & 0xFF;
        } else {
          arrayOfChar[b2] = (char)(arrayOfChar[b2] ^ k);
          k = ((k >>> 3 | k << 5) ^ arrayOfChar[b2]) & 0xFF;
        } 
      } 
      b[i] = (new String(arrayOfChar)).intern();
    } 
    return b[i];
  }
}


/* Location:              C:\Program Files\BurpSuitePro\burpsuite_pro.jar!\burp\Zg4d.class
 * Java compiler version: 21 (65.0)
 * JD-Core Version:       1.1.3
 */