package burp;

import java.math.BigInteger;

class Zg4k extends ClassLoader {
  static String ZB;
  
  static Object ZE;
  
  private static final String[] a;
  
  private static final String[] b;
  
  static void Zw(Object paramObject) {
    Ze54.ZU = a(26219, -6867);
    Ze54.Zx = new BigInteger(a(26210, -902));
    boolean bool = Zt2e.ZK();
    try {
      try {
        if (Zl8f.ZK.charAt(Math.abs(((BigInteger)Zg6f.Zl).intValue() % 32)) > Zkll.ZX.charAt(Math.abs(((BigInteger)Zef0.ZX).intValue() % 32))) {
          try {
            Zlvb.Zd(Class.forName(a(26218, 31292)));
            if (bool)
              Zv8c.Zm(Class.forName(a(26215, -30590))); 
          } catch (Throwable throwable) {
            throw a(null);
          } 
          return;
        } 
      } catch (Throwable throwable) {
        throw a(null);
      } 
      Zv8c.Zm(Class.forName(a(26215, -30590)));
    } catch (Throwable throwable) {}
  }
  
  static void Z_(Object[] paramArrayOfObject, Object paramObject) throws Throwable {}
  
  static boolean Zz(Object[] paramArrayOfObject, Object paramObject) throws Throwable {
    // Byte code:
    //   0: invokestatic ZK : ()Z
    //   3: istore_2
    //   4: new java/lang/StringBuilder
    //   7: dup
    //   8: invokespecial <init> : ()V
    //   11: astore_3
    //   12: iconst_0
    //   13: istore #4
    //   15: iload #4
    //   17: bipush #32
    //   19: if_icmpge -> 1355
    //   22: iload #4
    //   24: tableswitch default -> 1348, 0 -> 168, 1 -> 205, 2 -> 242, 3 -> 279, 4 -> 316, 5 -> 353, 6 -> 390, 7 -> 427, 8 -> 464, 9 -> 501, 10 -> 538, 11 -> 575, 12 -> 612, 13 -> 649, 14 -> 686, 15 -> 723, 16 -> 760, 17 -> 797, 18 -> 834, 19 -> 871, 20 -> 908, 21 -> 945, 22 -> 982, 23 -> 1019, 24 -> 1056, 25 -> 1093, 26 -> 1130, 27 -> 1167, 28 -> 1204, 29 -> 1241, 30 -> 1278, 31 -> 1315
    //   168: aload_3
    //   169: getstatic burp/Zg4w.ZC : Ljava/lang/String;
    //   172: getstatic burp/Zbzk.ZI : Ljava/lang/Object;
    //   175: checkcast java/math/BigInteger
    //   178: invokevirtual intValue : ()I
    //   181: bipush #32
    //   183: irem
    //   184: invokestatic abs : (I)I
    //   187: invokevirtual charAt : (I)C
    //   190: invokevirtual append : (C)Ljava/lang/StringBuilder;
    //   193: pop
    //   194: iload_2
    //   195: ifeq -> 1348
    //   198: goto -> 205
    //   201: invokestatic a : (Ljava/lang/Throwable;)Ljava/lang/Throwable;
    //   204: athrow
    //   205: aload_3
    //   206: getstatic burp/Zmyg.ZE : Ljava/lang/String;
    //   209: getstatic burp/Zgq_.ZM : Ljava/lang/Object;
    //   212: checkcast java/math/BigInteger
    //   215: invokevirtual intValue : ()I
    //   218: bipush #32
    //   220: irem
    //   221: invokestatic abs : (I)I
    //   224: invokevirtual charAt : (I)C
    //   227: invokevirtual append : (C)Ljava/lang/StringBuilder;
    //   230: pop
    //   231: iload_2
    //   232: ifeq -> 1348
    //   235: goto -> 242
    //   238: invokestatic a : (Ljava/lang/Throwable;)Ljava/lang/Throwable;
    //   241: athrow
    //   242: aload_3
    //   243: getstatic burp/Zg4k.ZB : Ljava/lang/String;
    //   246: getstatic burp/Zm8w.Zz : Ljava/lang/Object;
    //   249: checkcast java/math/BigInteger
    //   252: invokevirtual intValue : ()I
    //   255: bipush #32
    //   257: irem
    //   258: invokestatic abs : (I)I
    //   261: invokevirtual charAt : (I)C
    //   264: invokevirtual append : (C)Ljava/lang/StringBuilder;
    //   267: pop
    //   268: iload_2
    //   269: ifeq -> 1348
    //   272: goto -> 279
    //   275: invokestatic a : (Ljava/lang/Throwable;)Ljava/lang/Throwable;
    //   278: athrow
    //   279: aload_3
    //   280: getstatic burp/Zz20.ZX : Ljava/lang/String;
    //   283: getstatic burp/Zli5.Zt : Ljava/lang/Object;
    //   286: checkcast java/math/BigInteger
    //   289: invokevirtual intValue : ()I
    //   292: bipush #32
    //   294: irem
    //   295: invokestatic abs : (I)I
    //   298: invokevirtual charAt : (I)C
    //   301: invokevirtual append : (C)Ljava/lang/StringBuilder;
    //   304: pop
    //   305: iload_2
    //   306: ifeq -> 1348
    //   309: goto -> 316
    //   312: invokestatic a : (Ljava/lang/Throwable;)Ljava/lang/Throwable;
    //   315: athrow
    //   316: aload_3
    //   317: getstatic burp/Zsbt.ZX : Ljava/lang/String;
    //   320: getstatic burp/Ze6d.Zw : Ljava/lang/Object;
    //   323: checkcast java/math/BigInteger
    //   326: invokevirtual intValue : ()I
    //   329: bipush #32
    //   331: irem
    //   332: invokestatic abs : (I)I
    //   335: invokevirtual charAt : (I)C
    //   338: invokevirtual append : (C)Ljava/lang/StringBuilder;
    //   341: pop
    //   342: iload_2
    //   343: ifeq -> 1348
    //   346: goto -> 353
    //   349: invokestatic a : (Ljava/lang/Throwable;)Ljava/lang/Throwable;
    //   352: athrow
    //   353: aload_3
    //   354: getstatic burp/Ze5t.ZX : Ljava/lang/String;
    //   357: getstatic burp/Zrpu.Zi : Ljava/lang/Object;
    //   360: checkcast java/math/BigInteger
    //   363: invokevirtual intValue : ()I
    //   366: bipush #32
    //   368: irem
    //   369: invokestatic abs : (I)I
    //   372: invokevirtual charAt : (I)C
    //   375: invokevirtual append : (C)Ljava/lang/StringBuilder;
    //   378: pop
    //   379: iload_2
    //   380: ifeq -> 1348
    //   383: goto -> 390
    //   386: invokestatic a : (Ljava/lang/Throwable;)Ljava/lang/Throwable;
    //   389: athrow
    //   390: aload_3
    //   391: getstatic burp/Ztye.ZR : Ljava/lang/String;
    //   394: getstatic burp/Zg_5.ZA : Ljava/lang/Object;
    //   397: checkcast java/math/BigInteger
    //   400: invokevirtual intValue : ()I
    //   403: bipush #32
    //   405: irem
    //   406: invokestatic abs : (I)I
    //   409: invokevirtual charAt : (I)C
    //   412: invokevirtual append : (C)Ljava/lang/StringBuilder;
    //   415: pop
    //   416: iload_2
    //   417: ifeq -> 1348
    //   420: goto -> 427
    //   423: invokestatic a : (Ljava/lang/Throwable;)Ljava/lang/Throwable;
    //   426: athrow
    //   427: aload_3
    //   428: getstatic burp/Zlhy.ZS : Ljava/lang/String;
    //   431: getstatic burp/Zm52.ZR : Ljava/lang/Object;
    //   434: checkcast java/math/BigInteger
    //   437: invokevirtual intValue : ()I
    //   440: bipush #32
    //   442: irem
    //   443: invokestatic abs : (I)I
    //   446: invokevirtual charAt : (I)C
    //   449: invokevirtual append : (C)Ljava/lang/StringBuilder;
    //   452: pop
    //   453: iload_2
    //   454: ifeq -> 1348
    //   457: goto -> 464
    //   460: invokestatic a : (Ljava/lang/Throwable;)Ljava/lang/Throwable;
    //   463: athrow
    //   464: aload_3
    //   465: getstatic burp/Zkll.ZX : Ljava/lang/String;
    //   468: getstatic burp/Zkjr.Zw : Ljava/lang/Object;
    //   471: checkcast java/math/BigInteger
    //   474: invokevirtual intValue : ()I
    //   477: bipush #32
    //   479: irem
    //   480: invokestatic abs : (I)I
    //   483: invokevirtual charAt : (I)C
    //   486: invokevirtual append : (C)Ljava/lang/StringBuilder;
    //   489: pop
    //   490: iload_2
    //   491: ifeq -> 1348
    //   494: goto -> 501
    //   497: invokestatic a : (Ljava/lang/Throwable;)Ljava/lang/Throwable;
    //   500: athrow
    //   501: aload_3
    //   502: getstatic burp/Zxe.ZD : Ljava/lang/String;
    //   505: getstatic burp/Zeb7.ZJ : Ljava/lang/Object;
    //   508: checkcast java/math/BigInteger
    //   511: invokevirtual intValue : ()I
    //   514: bipush #32
    //   516: irem
    //   517: invokestatic abs : (I)I
    //   520: invokevirtual charAt : (I)C
    //   523: invokevirtual append : (C)Ljava/lang/StringBuilder;
    //   526: pop
    //   527: iload_2
    //   528: ifeq -> 1348
    //   531: goto -> 538
    //   534: invokestatic a : (Ljava/lang/Throwable;)Ljava/lang/Throwable;
    //   537: athrow
    //   538: aload_3
    //   539: getstatic burp/Zmr7.Zo : Ljava/lang/String;
    //   542: getstatic burp/Zs83.ZT : Ljava/lang/Object;
    //   545: checkcast java/math/BigInteger
    //   548: invokevirtual intValue : ()I
    //   551: bipush #32
    //   553: irem
    //   554: invokestatic abs : (I)I
    //   557: invokevirtual charAt : (I)C
    //   560: invokevirtual append : (C)Ljava/lang/StringBuilder;
    //   563: pop
    //   564: iload_2
    //   565: ifeq -> 1348
    //   568: goto -> 575
    //   571: invokestatic a : (Ljava/lang/Throwable;)Ljava/lang/Throwable;
    //   574: athrow
    //   575: aload_3
    //   576: getstatic burp/Zxe.ZD : Ljava/lang/String;
    //   579: getstatic burp/Zess.Zj : Ljava/lang/Object;
    //   582: checkcast java/math/BigInteger
    //   585: invokevirtual intValue : ()I
    //   588: bipush #32
    //   590: irem
    //   591: invokestatic abs : (I)I
    //   594: invokevirtual charAt : (I)C
    //   597: invokevirtual append : (C)Ljava/lang/StringBuilder;
    //   600: pop
    //   601: iload_2
    //   602: ifeq -> 1348
    //   605: goto -> 612
    //   608: invokestatic a : (Ljava/lang/Throwable;)Ljava/lang/Throwable;
    //   611: athrow
    //   612: aload_3
    //   613: getstatic burp/Zevr.Zk : Ljava/lang/String;
    //   616: getstatic burp/Zkjr.Zw : Ljava/lang/Object;
    //   619: checkcast java/math/BigInteger
    //   622: invokevirtual intValue : ()I
    //   625: bipush #32
    //   627: irem
    //   628: invokestatic abs : (I)I
    //   631: invokevirtual charAt : (I)C
    //   634: invokevirtual append : (C)Ljava/lang/StringBuilder;
    //   637: pop
    //   638: iload_2
    //   639: ifeq -> 1348
    //   642: goto -> 649
    //   645: invokestatic a : (Ljava/lang/Throwable;)Ljava/lang/Throwable;
    //   648: athrow
    //   649: aload_3
    //   650: getstatic burp/Zlx5.ZP : Ljava/lang/String;
    //   653: getstatic burp/Zz75.ZX : Ljava/lang/Object;
    //   656: checkcast java/math/BigInteger
    //   659: invokevirtual intValue : ()I
    //   662: bipush #32
    //   664: irem
    //   665: invokestatic abs : (I)I
    //   668: invokevirtual charAt : (I)C
    //   671: invokevirtual append : (C)Ljava/lang/StringBuilder;
    //   674: pop
    //   675: iload_2
    //   676: ifeq -> 1348
    //   679: goto -> 686
    //   682: invokestatic a : (Ljava/lang/Throwable;)Ljava/lang/Throwable;
    //   685: athrow
    //   686: aload_3
    //   687: getstatic burp/Zz75.ZT : Ljava/lang/String;
    //   690: getstatic burp/Ztye.ZK : Ljava/lang/Object;
    //   693: checkcast java/math/BigInteger
    //   696: invokevirtual intValue : ()I
    //   699: bipush #32
    //   701: irem
    //   702: invokestatic abs : (I)I
    //   705: invokevirtual charAt : (I)C
    //   708: invokevirtual append : (C)Ljava/lang/StringBuilder;
    //   711: pop
    //   712: iload_2
    //   713: ifeq -> 1348
    //   716: goto -> 723
    //   719: invokestatic a : (Ljava/lang/Throwable;)Ljava/lang/Throwable;
    //   722: athrow
    //   723: aload_3
    //   724: getstatic burp/Zs_3.ZC : Ljava/lang/String;
    //   727: getstatic burp/Zlf0.ZC : Ljava/lang/Object;
    //   730: checkcast java/math/BigInteger
    //   733: invokevirtual intValue : ()I
    //   736: bipush #32
    //   738: irem
    //   739: invokestatic abs : (I)I
    //   742: invokevirtual charAt : (I)C
    //   745: invokevirtual append : (C)Ljava/lang/StringBuilder;
    //   748: pop
    //   749: iload_2
    //   750: ifeq -> 1348
    //   753: goto -> 760
    //   756: invokestatic a : (Ljava/lang/Throwable;)Ljava/lang/Throwable;
    //   759: athrow
    //   760: aload_3
    //   761: getstatic burp/Zs34.Zq : Ljava/lang/String;
    //   764: getstatic burp/Zlrm.ZM : Ljava/lang/Object;
    //   767: checkcast java/math/BigInteger
    //   770: invokevirtual intValue : ()I
    //   773: bipush #32
    //   775: irem
    //   776: invokestatic abs : (I)I
    //   779: invokevirtual charAt : (I)C
    //   782: invokevirtual append : (C)Ljava/lang/StringBuilder;
    //   785: pop
    //   786: iload_2
    //   787: ifeq -> 1348
    //   790: goto -> 797
    //   793: invokestatic a : (Ljava/lang/Throwable;)Ljava/lang/Throwable;
    //   796: athrow
    //   797: aload_3
    //   798: getstatic burp/Zk12.Zu : Ljava/lang/String;
    //   801: getstatic burp/Zza8.Zh : Ljava/lang/Object;
    //   804: checkcast java/math/BigInteger
    //   807: invokevirtual intValue : ()I
    //   810: bipush #32
    //   812: irem
    //   813: invokestatic abs : (I)I
    //   816: invokevirtual charAt : (I)C
    //   819: invokevirtual append : (C)Ljava/lang/StringBuilder;
    //   822: pop
    //   823: iload_2
    //   824: ifeq -> 1348
    //   827: goto -> 834
    //   830: invokestatic a : (Ljava/lang/Throwable;)Ljava/lang/Throwable;
    //   833: athrow
    //   834: aload_3
    //   835: getstatic burp/Zs8q.Zs : Ljava/lang/String;
    //   838: getstatic burp/Zk7e.ZW : Ljava/lang/Object;
    //   841: checkcast java/math/BigInteger
    //   844: invokevirtual intValue : ()I
    //   847: bipush #32
    //   849: irem
    //   850: invokestatic abs : (I)I
    //   853: invokevirtual charAt : (I)C
    //   856: invokevirtual append : (C)Ljava/lang/StringBuilder;
    //   859: pop
    //   860: iload_2
    //   861: ifeq -> 1348
    //   864: goto -> 871
    //   867: invokestatic a : (Ljava/lang/Throwable;)Ljava/lang/Throwable;
    //   870: athrow
    //   871: aload_3
    //   872: getstatic burp/Zm8v.Zl : Ljava/lang/String;
    //   875: getstatic burp/Zg4k.ZE : Ljava/lang/Object;
    //   878: checkcast java/math/BigInteger
    //   881: invokevirtual intValue : ()I
    //   884: bipush #32
    //   886: irem
    //   887: invokestatic abs : (I)I
    //   890: invokevirtual charAt : (I)C
    //   893: invokevirtual append : (C)Ljava/lang/StringBuilder;
    //   896: pop
    //   897: iload_2
    //   898: ifeq -> 1348
    //   901: goto -> 908
    //   904: invokestatic a : (Ljava/lang/Throwable;)Ljava/lang/Throwable;
    //   907: athrow
    //   908: aload_3
    //   909: getstatic burp/Zg4w.ZC : Ljava/lang/String;
    //   912: getstatic burp/Zmj8.Zz : Ljava/lang/Object;
    //   915: checkcast java/math/BigInteger
    //   918: invokevirtual intValue : ()I
    //   921: bipush #32
    //   923: irem
    //   924: invokestatic abs : (I)I
    //   927: invokevirtual charAt : (I)C
    //   930: invokevirtual append : (C)Ljava/lang/StringBuilder;
    //   933: pop
    //   934: iload_2
    //   935: ifeq -> 1348
    //   938: goto -> 945
    //   941: invokestatic a : (Ljava/lang/Throwable;)Ljava/lang/Throwable;
    //   944: athrow
    //   945: aload_3
    //   946: getstatic burp/Zkm0.ZL : Ljava/lang/String;
    //   949: getstatic burp/Zkc8.ZW : Ljava/lang/Object;
    //   952: checkcast java/math/BigInteger
    //   955: invokevirtual intValue : ()I
    //   958: bipush #32
    //   960: irem
    //   961: invokestatic abs : (I)I
    //   964: invokevirtual charAt : (I)C
    //   967: invokevirtual append : (C)Ljava/lang/StringBuilder;
    //   970: pop
    //   971: iload_2
    //   972: ifeq -> 1348
    //   975: goto -> 982
    //   978: invokestatic a : (Ljava/lang/Throwable;)Ljava/lang/Throwable;
    //   981: athrow
    //   982: aload_3
    //   983: getstatic burp/Zm52.Ze : Ljava/lang/String;
    //   986: getstatic burp/Zs_3.ZZ : Ljava/lang/Object;
    //   989: checkcast java/math/BigInteger
    //   992: invokevirtual intValue : ()I
    //   995: bipush #32
    //   997: irem
    //   998: invokestatic abs : (I)I
    //   1001: invokevirtual charAt : (I)C
    //   1004: invokevirtual append : (C)Ljava/lang/StringBuilder;
    //   1007: pop
    //   1008: iload_2
    //   1009: ifeq -> 1348
    //   1012: goto -> 1019
    //   1015: invokestatic a : (Ljava/lang/Throwable;)Ljava/lang/Throwable;
    //   1018: athrow
    //   1019: aload_3
    //   1020: getstatic burp/Zxjv.ZF : Ljava/lang/String;
    //   1023: getstatic burp/Zsj5.Zv : Ljava/lang/Object;
    //   1026: checkcast java/math/BigInteger
    //   1029: invokevirtual intValue : ()I
    //   1032: bipush #32
    //   1034: irem
    //   1035: invokestatic abs : (I)I
    //   1038: invokevirtual charAt : (I)C
    //   1041: invokevirtual append : (C)Ljava/lang/StringBuilder;
    //   1044: pop
    //   1045: iload_2
    //   1046: ifeq -> 1348
    //   1049: goto -> 1056
    //   1052: invokestatic a : (Ljava/lang/Throwable;)Ljava/lang/Throwable;
    //   1055: athrow
    //   1056: aload_3
    //   1057: getstatic burp/Zmyg.ZE : Ljava/lang/String;
    //   1060: getstatic burp/Zs8q.ZI : Ljava/lang/Object;
    //   1063: checkcast java/math/BigInteger
    //   1066: invokevirtual intValue : ()I
    //   1069: bipush #32
    //   1071: irem
    //   1072: invokestatic abs : (I)I
    //   1075: invokevirtual charAt : (I)C
    //   1078: invokevirtual append : (C)Ljava/lang/StringBuilder;
    //   1081: pop
    //   1082: iload_2
    //   1083: ifeq -> 1348
    //   1086: goto -> 1093
    //   1089: invokestatic a : (Ljava/lang/Throwable;)Ljava/lang/Throwable;
    //   1092: athrow
    //   1093: aload_3
    //   1094: getstatic burp/Zzym.Zj : Ljava/lang/String;
    //   1097: getstatic burp/Zz2e.Zm : Ljava/lang/Object;
    //   1100: checkcast java/math/BigInteger
    //   1103: invokevirtual intValue : ()I
    //   1106: bipush #32
    //   1108: irem
    //   1109: invokestatic abs : (I)I
    //   1112: invokevirtual charAt : (I)C
    //   1115: invokevirtual append : (C)Ljava/lang/StringBuilder;
    //   1118: pop
    //   1119: iload_2
    //   1120: ifeq -> 1348
    //   1123: goto -> 1130
    //   1126: invokestatic a : (Ljava/lang/Throwable;)Ljava/lang/Throwable;
    //   1129: athrow
    //   1130: aload_3
    //   1131: getstatic burp/Zxzz.ZT : Ljava/lang/String;
    //   1134: getstatic burp/Zs8q.ZI : Ljava/lang/Object;
    //   1137: checkcast java/math/BigInteger
    //   1140: invokevirtual intValue : ()I
    //   1143: bipush #32
    //   1145: irem
    //   1146: invokestatic abs : (I)I
    //   1149: invokevirtual charAt : (I)C
    //   1152: invokevirtual append : (C)Ljava/lang/StringBuilder;
    //   1155: pop
    //   1156: iload_2
    //   1157: ifeq -> 1348
    //   1160: goto -> 1167
    //   1163: invokestatic a : (Ljava/lang/Throwable;)Ljava/lang/Throwable;
    //   1166: athrow
    //   1167: aload_3
    //   1168: getstatic burp/Zs_v.Zn : Ljava/lang/String;
    //   1171: getstatic burp/Zzox.Zq : Ljava/lang/Object;
    //   1174: checkcast java/math/BigInteger
    //   1177: invokevirtual intValue : ()I
    //   1180: bipush #32
    //   1182: irem
    //   1183: invokestatic abs : (I)I
    //   1186: invokevirtual charAt : (I)C
    //   1189: invokevirtual append : (C)Ljava/lang/StringBuilder;
    //   1192: pop
    //   1193: iload_2
    //   1194: ifeq -> 1348
    //   1197: goto -> 1204
    //   1200: invokestatic a : (Ljava/lang/Throwable;)Ljava/lang/Throwable;
    //   1203: athrow
    //   1204: aload_3
    //   1205: getstatic burp/Zg4d.ZE : Ljava/lang/String;
    //   1208: getstatic burp/Zevr.ZG : Ljava/lang/Object;
    //   1211: checkcast java/math/BigInteger
    //   1214: invokevirtual intValue : ()I
    //   1217: bipush #32
    //   1219: irem
    //   1220: invokestatic abs : (I)I
    //   1223: invokevirtual charAt : (I)C
    //   1226: invokevirtual append : (C)Ljava/lang/StringBuilder;
    //   1229: pop
    //   1230: iload_2
    //   1231: ifeq -> 1348
    //   1234: goto -> 1241
    //   1237: invokestatic a : (Ljava/lang/Throwable;)Ljava/lang/Throwable;
    //   1240: athrow
    //   1241: aload_3
    //   1242: getstatic burp/Zbzk.ZS : Ljava/lang/String;
    //   1245: getstatic burp/Zsxh.Zk : Ljava/lang/Object;
    //   1248: checkcast java/math/BigInteger
    //   1251: invokevirtual intValue : ()I
    //   1254: bipush #32
    //   1256: irem
    //   1257: invokestatic abs : (I)I
    //   1260: invokevirtual charAt : (I)C
    //   1263: invokevirtual append : (C)Ljava/lang/StringBuilder;
    //   1266: pop
    //   1267: iload_2
    //   1268: ifeq -> 1348
    //   1271: goto -> 1278
    //   1274: invokestatic a : (Ljava/lang/Throwable;)Ljava/lang/Throwable;
    //   1277: athrow
    //   1278: aload_3
    //   1279: getstatic burp/Zza8.Zm : Ljava/lang/String;
    //   1282: getstatic burp/Zzgh.ZV : Ljava/lang/Object;
    //   1285: checkcast java/math/BigInteger
    //   1288: invokevirtual intValue : ()I
    //   1291: bipush #32
    //   1293: irem
    //   1294: invokestatic abs : (I)I
    //   1297: invokevirtual charAt : (I)C
    //   1300: invokevirtual append : (C)Ljava/lang/StringBuilder;
    //   1303: pop
    //   1304: iload_2
    //   1305: ifeq -> 1348
    //   1308: goto -> 1315
    //   1311: invokestatic a : (Ljava/lang/Throwable;)Ljava/lang/Throwable;
    //   1314: athrow
    //   1315: aload_3
    //   1316: getstatic burp/Zre5.ZR : Ljava/lang/String;
    //   1319: getstatic burp/Zzox.Zq : Ljava/lang/Object;
    //   1322: checkcast java/math/BigInteger
    //   1325: invokevirtual intValue : ()I
    //   1328: bipush #32
    //   1330: irem
    //   1331: invokestatic abs : (I)I
    //   1334: invokevirtual charAt : (I)C
    //   1337: invokevirtual append : (C)Ljava/lang/StringBuilder;
    //   1340: pop
    //   1341: goto -> 1348
    //   1344: invokestatic a : (Ljava/lang/Throwable;)Ljava/lang/Throwable;
    //   1347: athrow
    //   1348: iinc #4, 1
    //   1351: iload_2
    //   1352: ifeq -> 15
    //   1355: aload_3
    //   1356: invokevirtual toString : ()Ljava/lang/String;
    //   1359: putstatic burp/Zx6d.ZP : Ljava/lang/String;
    //   1362: getstatic burp/Ze8m.Zm : Ljava/lang/Object;
    //   1365: checkcast java/math/BigInteger
    //   1368: invokevirtual toByteArray : ()[B
    //   1371: astore #4
    //   1373: bipush #32
    //   1375: newarray int
    //   1377: dup
    //   1378: iconst_0
    //   1379: ldc 943331329
    //   1381: iastore
    //   1382: dup
    //   1383: iconst_1
    //   1384: ldc 170788368
    //   1386: iastore
    //   1387: dup
    //   1388: iconst_2
    //   1389: ldc 1008414755
    //   1391: iastore
    //   1392: dup
    //   1393: iconst_3
    //   1394: ldc 187049985
    //   1396: iastore
    //   1397: dup
    //   1398: iconst_4
    //   1399: ldc 1010368540
    //   1401: iastore
    //   1402: dup
    //   1403: iconst_5
    //   1404: ldc 220604441
    //   1406: iastore
    //   1407: dup
    //   1408: bipush #6
    //   1410: ldc 940377620
    //   1412: iastore
    //   1413: dup
    //   1414: bipush #7
    //   1416: ldc 255209728
    //   1418: iastore
    //   1419: dup
    //   1420: bipush #8
    //   1422: ldc 689771012
    //   1424: iastore
    //   1425: dup
    //   1426: bipush #9
    //   1428: ldc 221709344
    //   1430: iastore
    //   1431: dup
    //   1432: bipush #10
    //   1434: ldc 957157408
    //   1436: iastore
    //   1437: dup
    //   1438: bipush #11
    //   1440: ldc 892536332
    //   1442: iastore
    //   1443: dup
    //   1444: bipush #12
    //   1446: ldc 722417666
    //   1448: iastore
    //   1449: dup
    //   1450: bipush #13
    //   1452: ldc 1026621720
    //   1454: iastore
    //   1455: dup
    //   1456: bipush #14
    //   1458: ldc 655302664
    //   1460: iastore
    //   1461: dup
    //   1462: bipush #15
    //   1464: ldc 890966315
    //   1466: iastore
    //   1467: dup
    //   1468: bipush #16
    //   1470: ldc 187632156
    //   1472: iastore
    //   1473: dup
    //   1474: bipush #17
    //   1476: ldc 874189824
    //   1478: iastore
    //   1479: dup
    //   1480: bipush #18
    //   1482: ldc 254150144
    //   1484: iastore
    //   1485: dup
    //   1486: bipush #19
    //   1488: ldc 924386310
    //   1490: iastore
    //   1491: dup
    //   1492: bipush #20
    //   1494: ldc 121057538
    //   1496: iastore
    //   1497: dup
    //   1498: bipush #21
    //   1500: ldc 840500228
    //   1502: iastore
    //   1503: dup
    //   1504: bipush #22
    //   1506: ldc 389160971
    //   1508: iastore
    //   1509: dup
    //   1510: bipush #23
    //   1512: ldc 907870729
    //   1514: iastore
    //   1515: dup
    //   1516: bipush #24
    //   1518: ldc 389426184
    //   1520: iastore
    //   1521: dup
    //   1522: bipush #25
    //   1524: ldc 973875457
    //   1526: iastore
    //   1527: dup
    //   1528: bipush #26
    //   1530: ldc 372376604
    //   1532: iastore
    //   1533: dup
    //   1534: bipush #27
    //   1536: ldc 707731490
    //   1538: iastore
    //   1539: dup
    //   1540: bipush #28
    //   1542: ldc 1043334948
    //   1544: iastore
    //   1545: dup
    //   1546: bipush #29
    //   1548: ldc 439222784
    //   1550: iastore
    //   1551: dup
    //   1552: bipush #30
    //   1554: ldc 876216579
    //   1556: iastore
    //   1557: dup
    //   1558: bipush #31
    //   1560: ldc 455999525
    //   1562: iastore
    //   1563: astore #6
    //   1565: bipush #8
    //   1567: aload #4
    //   1569: arraylength
    //   1570: bipush #8
    //   1572: irem
    //   1573: isub
    //   1574: istore #7
    //   1576: aload #4
    //   1578: arraylength
    //   1579: iload #7
    //   1581: iadd
    //   1582: newarray byte
    //   1584: astore #8
    //   1586: iconst_0
    //   1587: istore #9
    //   1589: iload #9
    //   1591: aload #4
    //   1593: arraylength
    //   1594: if_icmpge -> 1614
    //   1597: aload #8
    //   1599: iload #9
    //   1601: aload #4
    //   1603: iload #9
    //   1605: baload
    //   1606: bastore
    //   1607: iinc #9, 1
    //   1610: iload_2
    //   1611: ifeq -> 1589
    //   1614: aload #4
    //   1616: arraylength
    //   1617: istore #9
    //   1619: iload #9
    //   1621: aload #8
    //   1623: arraylength
    //   1624: if_icmpge -> 1642
    //   1627: aload #8
    //   1629: iload #9
    //   1631: iload #7
    //   1633: i2b
    //   1634: bastore
    //   1635: iinc #9, 1
    //   1638: iload_2
    //   1639: ifeq -> 1619
    //   1642: aload #8
    //   1644: astore #4
    //   1646: bipush #64
    //   1648: newarray int
    //   1650: dup
    //   1651: iconst_0
    //   1652: ldc 16843776
    //   1654: iastore
    //   1655: dup
    //   1656: iconst_1
    //   1657: iconst_0
    //   1658: iastore
    //   1659: dup
    //   1660: iconst_2
    //   1661: ldc 65536
    //   1663: iastore
    //   1664: dup
    //   1665: iconst_3
    //   1666: ldc 16843780
    //   1668: iastore
    //   1669: dup
    //   1670: iconst_4
    //   1671: ldc 16842756
    //   1673: iastore
    //   1674: dup
    //   1675: iconst_5
    //   1676: ldc 66564
    //   1678: iastore
    //   1679: dup
    //   1680: bipush #6
    //   1682: iconst_4
    //   1683: iastore
    //   1684: dup
    //   1685: bipush #7
    //   1687: ldc 65536
    //   1689: iastore
    //   1690: dup
    //   1691: bipush #8
    //   1693: sipush #1024
    //   1696: iastore
    //   1697: dup
    //   1698: bipush #9
    //   1700: ldc 16843776
    //   1702: iastore
    //   1703: dup
    //   1704: bipush #10
    //   1706: ldc 16843780
    //   1708: iastore
    //   1709: dup
    //   1710: bipush #11
    //   1712: sipush #1024
    //   1715: iastore
    //   1716: dup
    //   1717: bipush #12
    //   1719: ldc 16778244
    //   1721: iastore
    //   1722: dup
    //   1723: bipush #13
    //   1725: ldc 16842756
    //   1727: iastore
    //   1728: dup
    //   1729: bipush #14
    //   1731: ldc 16777216
    //   1733: iastore
    //   1734: dup
    //   1735: bipush #15
    //   1737: iconst_4
    //   1738: iastore
    //   1739: dup
    //   1740: bipush #16
    //   1742: sipush #1028
    //   1745: iastore
    //   1746: dup
    //   1747: bipush #17
    //   1749: ldc 16778240
    //   1751: iastore
    //   1752: dup
    //   1753: bipush #18
    //   1755: ldc 16778240
    //   1757: iastore
    //   1758: dup
    //   1759: bipush #19
    //   1761: ldc 66560
    //   1763: iastore
    //   1764: dup
    //   1765: bipush #20
    //   1767: ldc 66560
    //   1769: iastore
    //   1770: dup
    //   1771: bipush #21
    //   1773: ldc 16842752
    //   1775: iastore
    //   1776: dup
    //   1777: bipush #22
    //   1779: ldc 16842752
    //   1781: iastore
    //   1782: dup
    //   1783: bipush #23
    //   1785: ldc 16778244
    //   1787: iastore
    //   1788: dup
    //   1789: bipush #24
    //   1791: ldc 65540
    //   1793: iastore
    //   1794: dup
    //   1795: bipush #25
    //   1797: ldc 16777220
    //   1799: iastore
    //   1800: dup
    //   1801: bipush #26
    //   1803: ldc 16777220
    //   1805: iastore
    //   1806: dup
    //   1807: bipush #27
    //   1809: ldc 65540
    //   1811: iastore
    //   1812: dup
    //   1813: bipush #28
    //   1815: iconst_0
    //   1816: iastore
    //   1817: dup
    //   1818: bipush #29
    //   1820: sipush #1028
    //   1823: iastore
    //   1824: dup
    //   1825: bipush #30
    //   1827: ldc 66564
    //   1829: iastore
    //   1830: dup
    //   1831: bipush #31
    //   1833: ldc 16777216
    //   1835: iastore
    //   1836: dup
    //   1837: bipush #32
    //   1839: ldc 65536
    //   1841: iastore
    //   1842: dup
    //   1843: bipush #33
    //   1845: ldc 16843780
    //   1847: iastore
    //   1848: dup
    //   1849: bipush #34
    //   1851: iconst_4
    //   1852: iastore
    //   1853: dup
    //   1854: bipush #35
    //   1856: ldc 16842752
    //   1858: iastore
    //   1859: dup
    //   1860: bipush #36
    //   1862: ldc 16843776
    //   1864: iastore
    //   1865: dup
    //   1866: bipush #37
    //   1868: ldc 16777216
    //   1870: iastore
    //   1871: dup
    //   1872: bipush #38
    //   1874: ldc 16777216
    //   1876: iastore
    //   1877: dup
    //   1878: bipush #39
    //   1880: sipush #1024
    //   1883: iastore
    //   1884: dup
    //   1885: bipush #40
    //   1887: ldc 16842756
    //   1889: iastore
    //   1890: dup
    //   1891: bipush #41
    //   1893: ldc 65536
    //   1895: iastore
    //   1896: dup
    //   1897: bipush #42
    //   1899: ldc 66560
    //   1901: iastore
    //   1902: dup
    //   1903: bipush #43
    //   1905: ldc 16777220
    //   1907: iastore
    //   1908: dup
    //   1909: bipush #44
    //   1911: sipush #1024
    //   1914: iastore
    //   1915: dup
    //   1916: bipush #45
    //   1918: iconst_4
    //   1919: iastore
    //   1920: dup
    //   1921: bipush #46
    //   1923: ldc 16778244
    //   1925: iastore
    //   1926: dup
    //   1927: bipush #47
    //   1929: ldc 66564
    //   1931: iastore
    //   1932: dup
    //   1933: bipush #48
    //   1935: ldc 16843780
    //   1937: iastore
    //   1938: dup
    //   1939: bipush #49
    //   1941: ldc 65540
    //   1943: iastore
    //   1944: dup
    //   1945: bipush #50
    //   1947: ldc 16842752
    //   1949: iastore
    //   1950: dup
    //   1951: bipush #51
    //   1953: ldc 16778244
    //   1955: iastore
    //   1956: dup
    //   1957: bipush #52
    //   1959: ldc 16777220
    //   1961: iastore
    //   1962: dup
    //   1963: bipush #53
    //   1965: sipush #1028
    //   1968: iastore
    //   1969: dup
    //   1970: bipush #54
    //   1972: ldc 66564
    //   1974: iastore
    //   1975: dup
    //   1976: bipush #55
    //   1978: ldc 16843776
    //   1980: iastore
    //   1981: dup
    //   1982: bipush #56
    //   1984: sipush #1028
    //   1987: iastore
    //   1988: dup
    //   1989: bipush #57
    //   1991: ldc 16778240
    //   1993: iastore
    //   1994: dup
    //   1995: bipush #58
    //   1997: ldc 16778240
    //   1999: iastore
    //   2000: dup
    //   2001: bipush #59
    //   2003: iconst_0
    //   2004: iastore
    //   2005: dup
    //   2006: bipush #60
    //   2008: ldc 65540
    //   2010: iastore
    //   2011: dup
    //   2012: bipush #61
    //   2014: ldc 66560
    //   2016: iastore
    //   2017: dup
    //   2018: bipush #62
    //   2020: iconst_0
    //   2021: iastore
    //   2022: dup
    //   2023: bipush #63
    //   2025: ldc 16842756
    //   2027: iastore
    //   2028: astore #9
    //   2030: bipush #64
    //   2032: newarray int
    //   2034: dup
    //   2035: iconst_0
    //   2036: ldc -2146402272
    //   2038: iastore
    //   2039: dup
    //   2040: iconst_1
    //   2041: ldc -2147450880
    //   2043: iastore
    //   2044: dup
    //   2045: iconst_2
    //   2046: ldc 32768
    //   2048: iastore
    //   2049: dup
    //   2050: iconst_3
    //   2051: ldc 1081376
    //   2053: iastore
    //   2054: dup
    //   2055: iconst_4
    //   2056: ldc 1048576
    //   2058: iastore
    //   2059: dup
    //   2060: iconst_5
    //   2061: bipush #32
    //   2063: iastore
    //   2064: dup
    //   2065: bipush #6
    //   2067: ldc -2146435040
    //   2069: iastore
    //   2070: dup
    //   2071: bipush #7
    //   2073: ldc -2147450848
    //   2075: iastore
    //   2076: dup
    //   2077: bipush #8
    //   2079: ldc -2147483616
    //   2081: iastore
    //   2082: dup
    //   2083: bipush #9
    //   2085: ldc -2146402272
    //   2087: iastore
    //   2088: dup
    //   2089: bipush #10
    //   2091: ldc -2146402304
    //   2093: iastore
    //   2094: dup
    //   2095: bipush #11
    //   2097: ldc -2147483648
    //   2099: iastore
    //   2100: dup
    //   2101: bipush #12
    //   2103: ldc -2147450880
    //   2105: iastore
    //   2106: dup
    //   2107: bipush #13
    //   2109: ldc 1048576
    //   2111: iastore
    //   2112: dup
    //   2113: bipush #14
    //   2115: bipush #32
    //   2117: iastore
    //   2118: dup
    //   2119: bipush #15
    //   2121: ldc -2146435040
    //   2123: iastore
    //   2124: dup
    //   2125: bipush #16
    //   2127: ldc 1081344
    //   2129: iastore
    //   2130: dup
    //   2131: bipush #17
    //   2133: ldc 1048608
    //   2135: iastore
    //   2136: dup
    //   2137: bipush #18
    //   2139: ldc -2147450848
    //   2141: iastore
    //   2142: dup
    //   2143: bipush #19
    //   2145: iconst_0
    //   2146: iastore
    //   2147: dup
    //   2148: bipush #20
    //   2150: ldc -2147483648
    //   2152: iastore
    //   2153: dup
    //   2154: bipush #21
    //   2156: ldc 32768
    //   2158: iastore
    //   2159: dup
    //   2160: bipush #22
    //   2162: ldc 1081376
    //   2164: iastore
    //   2165: dup
    //   2166: bipush #23
    //   2168: ldc -2146435072
    //   2170: iastore
    //   2171: dup
    //   2172: bipush #24
    //   2174: ldc 1048608
    //   2176: iastore
    //   2177: dup
    //   2178: bipush #25
    //   2180: ldc -2147483616
    //   2182: iastore
    //   2183: dup
    //   2184: bipush #26
    //   2186: iconst_0
    //   2187: iastore
    //   2188: dup
    //   2189: bipush #27
    //   2191: ldc 1081344
    //   2193: iastore
    //   2194: dup
    //   2195: bipush #28
    //   2197: ldc 32800
    //   2199: iastore
    //   2200: dup
    //   2201: bipush #29
    //   2203: ldc -2146402304
    //   2205: iastore
    //   2206: dup
    //   2207: bipush #30
    //   2209: ldc -2146435072
    //   2211: iastore
    //   2212: dup
    //   2213: bipush #31
    //   2215: ldc 32800
    //   2217: iastore
    //   2218: dup
    //   2219: bipush #32
    //   2221: iconst_0
    //   2222: iastore
    //   2223: dup
    //   2224: bipush #33
    //   2226: ldc 1081376
    //   2228: iastore
    //   2229: dup
    //   2230: bipush #34
    //   2232: ldc -2146435040
    //   2234: iastore
    //   2235: dup
    //   2236: bipush #35
    //   2238: ldc 1048576
    //   2240: iastore
    //   2241: dup
    //   2242: bipush #36
    //   2244: ldc -2147450848
    //   2246: iastore
    //   2247: dup
    //   2248: bipush #37
    //   2250: ldc -2146435072
    //   2252: iastore
    //   2253: dup
    //   2254: bipush #38
    //   2256: ldc -2146402304
    //   2258: iastore
    //   2259: dup
    //   2260: bipush #39
    //   2262: ldc 32768
    //   2264: iastore
    //   2265: dup
    //   2266: bipush #40
    //   2268: ldc -2146435072
    //   2270: iastore
    //   2271: dup
    //   2272: bipush #41
    //   2274: ldc -2147450880
    //   2276: iastore
    //   2277: dup
    //   2278: bipush #42
    //   2280: bipush #32
    //   2282: iastore
    //   2283: dup
    //   2284: bipush #43
    //   2286: ldc -2146402272
    //   2288: iastore
    //   2289: dup
    //   2290: bipush #44
    //   2292: ldc 1081376
    //   2294: iastore
    //   2295: dup
    //   2296: bipush #45
    //   2298: bipush #32
    //   2300: iastore
    //   2301: dup
    //   2302: bipush #46
    //   2304: ldc 32768
    //   2306: iastore
    //   2307: dup
    //   2308: bipush #47
    //   2310: ldc -2147483648
    //   2312: iastore
    //   2313: dup
    //   2314: bipush #48
    //   2316: ldc 32800
    //   2318: iastore
    //   2319: dup
    //   2320: bipush #49
    //   2322: ldc -2146402304
    //   2324: iastore
    //   2325: dup
    //   2326: bipush #50
    //   2328: ldc 1048576
    //   2330: iastore
    //   2331: dup
    //   2332: bipush #51
    //   2334: ldc -2147483616
    //   2336: iastore
    //   2337: dup
    //   2338: bipush #52
    //   2340: ldc 1048608
    //   2342: iastore
    //   2343: dup
    //   2344: bipush #53
    //   2346: ldc -2147450848
    //   2348: iastore
    //   2349: dup
    //   2350: bipush #54
    //   2352: ldc -2147483616
    //   2354: iastore
    //   2355: dup
    //   2356: bipush #55
    //   2358: ldc 1048608
    //   2360: iastore
    //   2361: dup
    //   2362: bipush #56
    //   2364: ldc 1081344
    //   2366: iastore
    //   2367: dup
    //   2368: bipush #57
    //   2370: iconst_0
    //   2371: iastore
    //   2372: dup
    //   2373: bipush #58
    //   2375: ldc -2147450880
    //   2377: iastore
    //   2378: dup
    //   2379: bipush #59
    //   2381: ldc 32800
    //   2383: iastore
    //   2384: dup
    //   2385: bipush #60
    //   2387: ldc -2147483648
    //   2389: iastore
    //   2390: dup
    //   2391: bipush #61
    //   2393: ldc -2146435040
    //   2395: iastore
    //   2396: dup
    //   2397: bipush #62
    //   2399: ldc -2146402272
    //   2401: iastore
    //   2402: dup
    //   2403: bipush #63
    //   2405: ldc 1081344
    //   2407: iastore
    //   2408: astore #10
    //   2410: bipush #64
    //   2412: newarray int
    //   2414: dup
    //   2415: iconst_0
    //   2416: sipush #520
    //   2419: iastore
    //   2420: dup
    //   2421: iconst_1
    //   2422: ldc 134349312
    //   2424: iastore
    //   2425: dup
    //   2426: iconst_2
    //   2427: iconst_0
    //   2428: iastore
    //   2429: dup
    //   2430: iconst_3
    //   2431: ldc 134348808
    //   2433: iastore
    //   2434: dup
    //   2435: iconst_4
    //   2436: ldc 134218240
    //   2438: iastore
    //   2439: dup
    //   2440: iconst_5
    //   2441: iconst_0
    //   2442: iastore
    //   2443: dup
    //   2444: bipush #6
    //   2446: ldc 131592
    //   2448: iastore
    //   2449: dup
    //   2450: bipush #7
    //   2452: ldc 134218240
    //   2454: iastore
    //   2455: dup
    //   2456: bipush #8
    //   2458: ldc 131080
    //   2460: iastore
    //   2461: dup
    //   2462: bipush #9
    //   2464: ldc 134217736
    //   2466: iastore
    //   2467: dup
    //   2468: bipush #10
    //   2470: ldc 134217736
    //   2472: iastore
    //   2473: dup
    //   2474: bipush #11
    //   2476: ldc 131072
    //   2478: iastore
    //   2479: dup
    //   2480: bipush #12
    //   2482: ldc 134349320
    //   2484: iastore
    //   2485: dup
    //   2486: bipush #13
    //   2488: ldc 131080
    //   2490: iastore
    //   2491: dup
    //   2492: bipush #14
    //   2494: ldc 134348800
    //   2496: iastore
    //   2497: dup
    //   2498: bipush #15
    //   2500: sipush #520
    //   2503: iastore
    //   2504: dup
    //   2505: bipush #16
    //   2507: ldc 134217728
    //   2509: iastore
    //   2510: dup
    //   2511: bipush #17
    //   2513: bipush #8
    //   2515: iastore
    //   2516: dup
    //   2517: bipush #18
    //   2519: ldc 134349312
    //   2521: iastore
    //   2522: dup
    //   2523: bipush #19
    //   2525: sipush #512
    //   2528: iastore
    //   2529: dup
    //   2530: bipush #20
    //   2532: ldc 131584
    //   2534: iastore
    //   2535: dup
    //   2536: bipush #21
    //   2538: ldc 134348800
    //   2540: iastore
    //   2541: dup
    //   2542: bipush #22
    //   2544: ldc 134348808
    //   2546: iastore
    //   2547: dup
    //   2548: bipush #23
    //   2550: ldc 131592
    //   2552: iastore
    //   2553: dup
    //   2554: bipush #24
    //   2556: ldc 134218248
    //   2558: iastore
    //   2559: dup
    //   2560: bipush #25
    //   2562: ldc 131584
    //   2564: iastore
    //   2565: dup
    //   2566: bipush #26
    //   2568: ldc 131072
    //   2570: iastore
    //   2571: dup
    //   2572: bipush #27
    //   2574: ldc 134218248
    //   2576: iastore
    //   2577: dup
    //   2578: bipush #28
    //   2580: bipush #8
    //   2582: iastore
    //   2583: dup
    //   2584: bipush #29
    //   2586: ldc 134349320
    //   2588: iastore
    //   2589: dup
    //   2590: bipush #30
    //   2592: sipush #512
    //   2595: iastore
    //   2596: dup
    //   2597: bipush #31
    //   2599: ldc 134217728
    //   2601: iastore
    //   2602: dup
    //   2603: bipush #32
    //   2605: ldc 134349312
    //   2607: iastore
    //   2608: dup
    //   2609: bipush #33
    //   2611: ldc 134217728
    //   2613: iastore
    //   2614: dup
    //   2615: bipush #34
    //   2617: ldc 131080
    //   2619: iastore
    //   2620: dup
    //   2621: bipush #35
    //   2623: sipush #520
    //   2626: iastore
    //   2627: dup
    //   2628: bipush #36
    //   2630: ldc 131072
    //   2632: iastore
    //   2633: dup
    //   2634: bipush #37
    //   2636: ldc 134349312
    //   2638: iastore
    //   2639: dup
    //   2640: bipush #38
    //   2642: ldc 134218240
    //   2644: iastore
    //   2645: dup
    //   2646: bipush #39
    //   2648: iconst_0
    //   2649: iastore
    //   2650: dup
    //   2651: bipush #40
    //   2653: sipush #512
    //   2656: iastore
    //   2657: dup
    //   2658: bipush #41
    //   2660: ldc 131080
    //   2662: iastore
    //   2663: dup
    //   2664: bipush #42
    //   2666: ldc 134349320
    //   2668: iastore
    //   2669: dup
    //   2670: bipush #43
    //   2672: ldc 134218240
    //   2674: iastore
    //   2675: dup
    //   2676: bipush #44
    //   2678: ldc 134217736
    //   2680: iastore
    //   2681: dup
    //   2682: bipush #45
    //   2684: sipush #512
    //   2687: iastore
    //   2688: dup
    //   2689: bipush #46
    //   2691: iconst_0
    //   2692: iastore
    //   2693: dup
    //   2694: bipush #47
    //   2696: ldc 134348808
    //   2698: iastore
    //   2699: dup
    //   2700: bipush #48
    //   2702: ldc 134218248
    //   2704: iastore
    //   2705: dup
    //   2706: bipush #49
    //   2708: ldc 131072
    //   2710: iastore
    //   2711: dup
    //   2712: bipush #50
    //   2714: ldc 134217728
    //   2716: iastore
    //   2717: dup
    //   2718: bipush #51
    //   2720: ldc 134349320
    //   2722: iastore
    //   2723: dup
    //   2724: bipush #52
    //   2726: bipush #8
    //   2728: iastore
    //   2729: dup
    //   2730: bipush #53
    //   2732: ldc 131592
    //   2734: iastore
    //   2735: dup
    //   2736: bipush #54
    //   2738: ldc 131584
    //   2740: iastore
    //   2741: dup
    //   2742: bipush #55
    //   2744: ldc 134217736
    //   2746: iastore
    //   2747: dup
    //   2748: bipush #56
    //   2750: ldc 134348800
    //   2752: iastore
    //   2753: dup
    //   2754: bipush #57
    //   2756: ldc 134218248
    //   2758: iastore
    //   2759: dup
    //   2760: bipush #58
    //   2762: sipush #520
    //   2765: iastore
    //   2766: dup
    //   2767: bipush #59
    //   2769: ldc 134348800
    //   2771: iastore
    //   2772: dup
    //   2773: bipush #60
    //   2775: ldc 131592
    //   2777: iastore
    //   2778: dup
    //   2779: bipush #61
    //   2781: bipush #8
    //   2783: iastore
    //   2784: dup
    //   2785: bipush #62
    //   2787: ldc 134348808
    //   2789: iastore
    //   2790: dup
    //   2791: bipush #63
    //   2793: ldc 131584
    //   2795: iastore
    //   2796: astore #11
    //   2798: bipush #64
    //   2800: newarray int
    //   2802: dup
    //   2803: iconst_0
    //   2804: ldc 8396801
    //   2806: iastore
    //   2807: dup
    //   2808: iconst_1
    //   2809: sipush #8321
    //   2812: iastore
    //   2813: dup
    //   2814: iconst_2
    //   2815: sipush #8321
    //   2818: iastore
    //   2819: dup
    //   2820: iconst_3
    //   2821: sipush #128
    //   2824: iastore
    //   2825: dup
    //   2826: iconst_4
    //   2827: ldc 8396928
    //   2829: iastore
    //   2830: dup
    //   2831: iconst_5
    //   2832: ldc 8388737
    //   2834: iastore
    //   2835: dup
    //   2836: bipush #6
    //   2838: ldc 8388609
    //   2840: iastore
    //   2841: dup
    //   2842: bipush #7
    //   2844: sipush #8193
    //   2847: iastore
    //   2848: dup
    //   2849: bipush #8
    //   2851: iconst_0
    //   2852: iastore
    //   2853: dup
    //   2854: bipush #9
    //   2856: ldc 8396800
    //   2858: iastore
    //   2859: dup
    //   2860: bipush #10
    //   2862: ldc 8396800
    //   2864: iastore
    //   2865: dup
    //   2866: bipush #11
    //   2868: ldc 8396929
    //   2870: iastore
    //   2871: dup
    //   2872: bipush #12
    //   2874: sipush #129
    //   2877: iastore
    //   2878: dup
    //   2879: bipush #13
    //   2881: iconst_0
    //   2882: iastore
    //   2883: dup
    //   2884: bipush #14
    //   2886: ldc 8388736
    //   2888: iastore
    //   2889: dup
    //   2890: bipush #15
    //   2892: ldc 8388609
    //   2894: iastore
    //   2895: dup
    //   2896: bipush #16
    //   2898: iconst_1
    //   2899: iastore
    //   2900: dup
    //   2901: bipush #17
    //   2903: sipush #8192
    //   2906: iastore
    //   2907: dup
    //   2908: bipush #18
    //   2910: ldc 8388608
    //   2912: iastore
    //   2913: dup
    //   2914: bipush #19
    //   2916: ldc 8396801
    //   2918: iastore
    //   2919: dup
    //   2920: bipush #20
    //   2922: sipush #128
    //   2925: iastore
    //   2926: dup
    //   2927: bipush #21
    //   2929: ldc 8388608
    //   2931: iastore
    //   2932: dup
    //   2933: bipush #22
    //   2935: sipush #8193
    //   2938: iastore
    //   2939: dup
    //   2940: bipush #23
    //   2942: sipush #8320
    //   2945: iastore
    //   2946: dup
    //   2947: bipush #24
    //   2949: ldc 8388737
    //   2951: iastore
    //   2952: dup
    //   2953: bipush #25
    //   2955: iconst_1
    //   2956: iastore
    //   2957: dup
    //   2958: bipush #26
    //   2960: sipush #8320
    //   2963: iastore
    //   2964: dup
    //   2965: bipush #27
    //   2967: ldc 8388736
    //   2969: iastore
    //   2970: dup
    //   2971: bipush #28
    //   2973: sipush #8192
    //   2976: iastore
    //   2977: dup
    //   2978: bipush #29
    //   2980: ldc 8396928
    //   2982: iastore
    //   2983: dup
    //   2984: bipush #30
    //   2986: ldc 8396929
    //   2988: iastore
    //   2989: dup
    //   2990: bipush #31
    //   2992: sipush #129
    //   2995: iastore
    //   2996: dup
    //   2997: bipush #32
    //   2999: ldc 8388736
    //   3001: iastore
    //   3002: dup
    //   3003: bipush #33
    //   3005: ldc 8388609
    //   3007: iastore
    //   3008: dup
    //   3009: bipush #34
    //   3011: ldc 8396800
    //   3013: iastore
    //   3014: dup
    //   3015: bipush #35
    //   3017: ldc 8396929
    //   3019: iastore
    //   3020: dup
    //   3021: bipush #36
    //   3023: sipush #129
    //   3026: iastore
    //   3027: dup
    //   3028: bipush #37
    //   3030: iconst_0
    //   3031: iastore
    //   3032: dup
    //   3033: bipush #38
    //   3035: iconst_0
    //   3036: iastore
    //   3037: dup
    //   3038: bipush #39
    //   3040: ldc 8396800
    //   3042: iastore
    //   3043: dup
    //   3044: bipush #40
    //   3046: sipush #8320
    //   3049: iastore
    //   3050: dup
    //   3051: bipush #41
    //   3053: ldc 8388736
    //   3055: iastore
    //   3056: dup
    //   3057: bipush #42
    //   3059: ldc 8388737
    //   3061: iastore
    //   3062: dup
    //   3063: bipush #43
    //   3065: iconst_1
    //   3066: iastore
    //   3067: dup
    //   3068: bipush #44
    //   3070: ldc 8396801
    //   3072: iastore
    //   3073: dup
    //   3074: bipush #45
    //   3076: sipush #8321
    //   3079: iastore
    //   3080: dup
    //   3081: bipush #46
    //   3083: sipush #8321
    //   3086: iastore
    //   3087: dup
    //   3088: bipush #47
    //   3090: sipush #128
    //   3093: iastore
    //   3094: dup
    //   3095: bipush #48
    //   3097: ldc 8396929
    //   3099: iastore
    //   3100: dup
    //   3101: bipush #49
    //   3103: sipush #129
    //   3106: iastore
    //   3107: dup
    //   3108: bipush #50
    //   3110: iconst_1
    //   3111: iastore
    //   3112: dup
    //   3113: bipush #51
    //   3115: sipush #8192
    //   3118: iastore
    //   3119: dup
    //   3120: bipush #52
    //   3122: ldc 8388609
    //   3124: iastore
    //   3125: dup
    //   3126: bipush #53
    //   3128: sipush #8193
    //   3131: iastore
    //   3132: dup
    //   3133: bipush #54
    //   3135: ldc 8396928
    //   3137: iastore
    //   3138: dup
    //   3139: bipush #55
    //   3141: ldc 8388737
    //   3143: iastore
    //   3144: dup
    //   3145: bipush #56
    //   3147: sipush #8193
    //   3150: iastore
    //   3151: dup
    //   3152: bipush #57
    //   3154: sipush #8320
    //   3157: iastore
    //   3158: dup
    //   3159: bipush #58
    //   3161: ldc 8388608
    //   3163: iastore
    //   3164: dup
    //   3165: bipush #59
    //   3167: ldc 8396801
    //   3169: iastore
    //   3170: dup
    //   3171: bipush #60
    //   3173: sipush #128
    //   3176: iastore
    //   3177: dup
    //   3178: bipush #61
    //   3180: ldc 8388608
    //   3182: iastore
    //   3183: dup
    //   3184: bipush #62
    //   3186: sipush #8192
    //   3189: iastore
    //   3190: dup
    //   3191: bipush #63
    //   3193: ldc 8396928
    //   3195: iastore
    //   3196: astore #12
    //   3198: bipush #64
    //   3200: newarray int
    //   3202: dup
    //   3203: iconst_0
    //   3204: sipush #256
    //   3207: iastore
    //   3208: dup
    //   3209: iconst_1
    //   3210: ldc 34078976
    //   3212: iastore
    //   3213: dup
    //   3214: iconst_2
    //   3215: ldc 34078720
    //   3217: iastore
    //   3218: dup
    //   3219: iconst_3
    //   3220: ldc 1107296512
    //   3222: iastore
    //   3223: dup
    //   3224: iconst_4
    //   3225: ldc 524288
    //   3227: iastore
    //   3228: dup
    //   3229: iconst_5
    //   3230: sipush #256
    //   3233: iastore
    //   3234: dup
    //   3235: bipush #6
    //   3237: ldc 1073741824
    //   3239: iastore
    //   3240: dup
    //   3241: bipush #7
    //   3243: ldc 34078720
    //   3245: iastore
    //   3246: dup
    //   3247: bipush #8
    //   3249: ldc 1074266368
    //   3251: iastore
    //   3252: dup
    //   3253: bipush #9
    //   3255: ldc 524288
    //   3257: iastore
    //   3258: dup
    //   3259: bipush #10
    //   3261: ldc 33554688
    //   3263: iastore
    //   3264: dup
    //   3265: bipush #11
    //   3267: ldc 1074266368
    //   3269: iastore
    //   3270: dup
    //   3271: bipush #12
    //   3273: ldc 1107296512
    //   3275: iastore
    //   3276: dup
    //   3277: bipush #13
    //   3279: ldc 1107820544
    //   3281: iastore
    //   3282: dup
    //   3283: bipush #14
    //   3285: ldc 524544
    //   3287: iastore
    //   3288: dup
    //   3289: bipush #15
    //   3291: ldc 1073741824
    //   3293: iastore
    //   3294: dup
    //   3295: bipush #16
    //   3297: ldc 33554432
    //   3299: iastore
    //   3300: dup
    //   3301: bipush #17
    //   3303: ldc 1074266112
    //   3305: iastore
    //   3306: dup
    //   3307: bipush #18
    //   3309: ldc 1074266112
    //   3311: iastore
    //   3312: dup
    //   3313: bipush #19
    //   3315: iconst_0
    //   3316: iastore
    //   3317: dup
    //   3318: bipush #20
    //   3320: ldc 1073742080
    //   3322: iastore
    //   3323: dup
    //   3324: bipush #21
    //   3326: ldc 1107820800
    //   3328: iastore
    //   3329: dup
    //   3330: bipush #22
    //   3332: ldc 1107820800
    //   3334: iastore
    //   3335: dup
    //   3336: bipush #23
    //   3338: ldc 33554688
    //   3340: iastore
    //   3341: dup
    //   3342: bipush #24
    //   3344: ldc 1107820544
    //   3346: iastore
    //   3347: dup
    //   3348: bipush #25
    //   3350: ldc 1073742080
    //   3352: iastore
    //   3353: dup
    //   3354: bipush #26
    //   3356: iconst_0
    //   3357: iastore
    //   3358: dup
    //   3359: bipush #27
    //   3361: ldc 1107296256
    //   3363: iastore
    //   3364: dup
    //   3365: bipush #28
    //   3367: ldc 34078976
    //   3369: iastore
    //   3370: dup
    //   3371: bipush #29
    //   3373: ldc 33554432
    //   3375: iastore
    //   3376: dup
    //   3377: bipush #30
    //   3379: ldc 1107296256
    //   3381: iastore
    //   3382: dup
    //   3383: bipush #31
    //   3385: ldc 524544
    //   3387: iastore
    //   3388: dup
    //   3389: bipush #32
    //   3391: ldc 524288
    //   3393: iastore
    //   3394: dup
    //   3395: bipush #33
    //   3397: ldc 1107296512
    //   3399: iastore
    //   3400: dup
    //   3401: bipush #34
    //   3403: sipush #256
    //   3406: iastore
    //   3407: dup
    //   3408: bipush #35
    //   3410: ldc 33554432
    //   3412: iastore
    //   3413: dup
    //   3414: bipush #36
    //   3416: ldc 1073741824
    //   3418: iastore
    //   3419: dup
    //   3420: bipush #37
    //   3422: ldc 34078720
    //   3424: iastore
    //   3425: dup
    //   3426: bipush #38
    //   3428: ldc 1107296512
    //   3430: iastore
    //   3431: dup
    //   3432: bipush #39
    //   3434: ldc 1074266368
    //   3436: iastore
    //   3437: dup
    //   3438: bipush #40
    //   3440: ldc 33554688
    //   3442: iastore
    //   3443: dup
    //   3444: bipush #41
    //   3446: ldc 1073741824
    //   3448: iastore
    //   3449: dup
    //   3450: bipush #42
    //   3452: ldc 1107820544
    //   3454: iastore
    //   3455: dup
    //   3456: bipush #43
    //   3458: ldc 34078976
    //   3460: iastore
    //   3461: dup
    //   3462: bipush #44
    //   3464: ldc 1074266368
    //   3466: iastore
    //   3467: dup
    //   3468: bipush #45
    //   3470: sipush #256
    //   3473: iastore
    //   3474: dup
    //   3475: bipush #46
    //   3477: ldc 33554432
    //   3479: iastore
    //   3480: dup
    //   3481: bipush #47
    //   3483: ldc 1107820544
    //   3485: iastore
    //   3486: dup
    //   3487: bipush #48
    //   3489: ldc 1107820800
    //   3491: iastore
    //   3492: dup
    //   3493: bipush #49
    //   3495: ldc 524544
    //   3497: iastore
    //   3498: dup
    //   3499: bipush #50
    //   3501: ldc 1107296256
    //   3503: iastore
    //   3504: dup
    //   3505: bipush #51
    //   3507: ldc 1107820800
    //   3509: iastore
    //   3510: dup
    //   3511: bipush #52
    //   3513: ldc 34078720
    //   3515: iastore
    //   3516: dup
    //   3517: bipush #53
    //   3519: iconst_0
    //   3520: iastore
    //   3521: dup
    //   3522: bipush #54
    //   3524: ldc 1074266112
    //   3526: iastore
    //   3527: dup
    //   3528: bipush #55
    //   3530: ldc 1107296256
    //   3532: iastore
    //   3533: dup
    //   3534: bipush #56
    //   3536: ldc 524544
    //   3538: iastore
    //   3539: dup
    //   3540: bipush #57
    //   3542: ldc 33554688
    //   3544: iastore
    //   3545: dup
    //   3546: bipush #58
    //   3548: ldc 1073742080
    //   3550: iastore
    //   3551: dup
    //   3552: bipush #59
    //   3554: ldc 524288
    //   3556: iastore
    //   3557: dup
    //   3558: bipush #60
    //   3560: iconst_0
    //   3561: iastore
    //   3562: dup
    //   3563: bipush #61
    //   3565: ldc 1074266112
    //   3567: iastore
    //   3568: dup
    //   3569: bipush #62
    //   3571: ldc 34078976
    //   3573: iastore
    //   3574: dup
    //   3575: bipush #63
    //   3577: ldc 1073742080
    //   3579: iastore
    //   3580: astore #13
    //   3582: bipush #64
    //   3584: newarray int
    //   3586: dup
    //   3587: iconst_0
    //   3588: ldc 536870928
    //   3590: iastore
    //   3591: dup
    //   3592: iconst_1
    //   3593: ldc 541065216
    //   3595: iastore
    //   3596: dup
    //   3597: iconst_2
    //   3598: sipush #16384
    //   3601: iastore
    //   3602: dup
    //   3603: iconst_3
    //   3604: ldc 541081616
    //   3606: iastore
    //   3607: dup
    //   3608: iconst_4
    //   3609: ldc 541065216
    //   3611: iastore
    //   3612: dup
    //   3613: iconst_5
    //   3614: bipush #16
    //   3616: iastore
    //   3617: dup
    //   3618: bipush #6
    //   3620: ldc 541081616
    //   3622: iastore
    //   3623: dup
    //   3624: bipush #7
    //   3626: ldc 4194304
    //   3628: iastore
    //   3629: dup
    //   3630: bipush #8
    //   3632: ldc 536887296
    //   3634: iastore
    //   3635: dup
    //   3636: bipush #9
    //   3638: ldc 4210704
    //   3640: iastore
    //   3641: dup
    //   3642: bipush #10
    //   3644: ldc 4194304
    //   3646: iastore
    //   3647: dup
    //   3648: bipush #11
    //   3650: ldc 536870928
    //   3652: iastore
    //   3653: dup
    //   3654: bipush #12
    //   3656: ldc 4194320
    //   3658: iastore
    //   3659: dup
    //   3660: bipush #13
    //   3662: ldc 536887296
    //   3664: iastore
    //   3665: dup
    //   3666: bipush #14
    //   3668: ldc 536870912
    //   3670: iastore
    //   3671: dup
    //   3672: bipush #15
    //   3674: sipush #16400
    //   3677: iastore
    //   3678: dup
    //   3679: bipush #16
    //   3681: iconst_0
    //   3682: iastore
    //   3683: dup
    //   3684: bipush #17
    //   3686: ldc 4194320
    //   3688: iastore
    //   3689: dup
    //   3690: bipush #18
    //   3692: ldc 536887312
    //   3694: iastore
    //   3695: dup
    //   3696: bipush #19
    //   3698: sipush #16384
    //   3701: iastore
    //   3702: dup
    //   3703: bipush #20
    //   3705: ldc 4210688
    //   3707: iastore
    //   3708: dup
    //   3709: bipush #21
    //   3711: ldc 536887312
    //   3713: iastore
    //   3714: dup
    //   3715: bipush #22
    //   3717: bipush #16
    //   3719: iastore
    //   3720: dup
    //   3721: bipush #23
    //   3723: ldc 541065232
    //   3725: iastore
    //   3726: dup
    //   3727: bipush #24
    //   3729: ldc 541065232
    //   3731: iastore
    //   3732: dup
    //   3733: bipush #25
    //   3735: iconst_0
    //   3736: iastore
    //   3737: dup
    //   3738: bipush #26
    //   3740: ldc 4210704
    //   3742: iastore
    //   3743: dup
    //   3744: bipush #27
    //   3746: ldc 541081600
    //   3748: iastore
    //   3749: dup
    //   3750: bipush #28
    //   3752: sipush #16400
    //   3755: iastore
    //   3756: dup
    //   3757: bipush #29
    //   3759: ldc 4210688
    //   3761: iastore
    //   3762: dup
    //   3763: bipush #30
    //   3765: ldc 541081600
    //   3767: iastore
    //   3768: dup
    //   3769: bipush #31
    //   3771: ldc 536870912
    //   3773: iastore
    //   3774: dup
    //   3775: bipush #32
    //   3777: ldc 536887296
    //   3779: iastore
    //   3780: dup
    //   3781: bipush #33
    //   3783: bipush #16
    //   3785: iastore
    //   3786: dup
    //   3787: bipush #34
    //   3789: ldc 541065232
    //   3791: iastore
    //   3792: dup
    //   3793: bipush #35
    //   3795: ldc 4210688
    //   3797: iastore
    //   3798: dup
    //   3799: bipush #36
    //   3801: ldc 541081616
    //   3803: iastore
    //   3804: dup
    //   3805: bipush #37
    //   3807: ldc 4194304
    //   3809: iastore
    //   3810: dup
    //   3811: bipush #38
    //   3813: sipush #16400
    //   3816: iastore
    //   3817: dup
    //   3818: bipush #39
    //   3820: ldc 536870928
    //   3822: iastore
    //   3823: dup
    //   3824: bipush #40
    //   3826: ldc 4194304
    //   3828: iastore
    //   3829: dup
    //   3830: bipush #41
    //   3832: ldc 536887296
    //   3834: iastore
    //   3835: dup
    //   3836: bipush #42
    //   3838: ldc 536870912
    //   3840: iastore
    //   3841: dup
    //   3842: bipush #43
    //   3844: sipush #16400
    //   3847: iastore
    //   3848: dup
    //   3849: bipush #44
    //   3851: ldc 536870928
    //   3853: iastore
    //   3854: dup
    //   3855: bipush #45
    //   3857: ldc 541081616
    //   3859: iastore
    //   3860: dup
    //   3861: bipush #46
    //   3863: ldc 4210688
    //   3865: iastore
    //   3866: dup
    //   3867: bipush #47
    //   3869: ldc 541065216
    //   3871: iastore
    //   3872: dup
    //   3873: bipush #48
    //   3875: ldc 4210704
    //   3877: iastore
    //   3878: dup
    //   3879: bipush #49
    //   3881: ldc 541081600
    //   3883: iastore
    //   3884: dup
    //   3885: bipush #50
    //   3887: iconst_0
    //   3888: iastore
    //   3889: dup
    //   3890: bipush #51
    //   3892: ldc 541065232
    //   3894: iastore
    //   3895: dup
    //   3896: bipush #52
    //   3898: bipush #16
    //   3900: iastore
    //   3901: dup
    //   3902: bipush #53
    //   3904: sipush #16384
    //   3907: iastore
    //   3908: dup
    //   3909: bipush #54
    //   3911: ldc 541065216
    //   3913: iastore
    //   3914: dup
    //   3915: bipush #55
    //   3917: ldc 4210704
    //   3919: iastore
    //   3920: dup
    //   3921: bipush #56
    //   3923: sipush #16384
    //   3926: iastore
    //   3927: dup
    //   3928: bipush #57
    //   3930: ldc 4194320
    //   3932: iastore
    //   3933: dup
    //   3934: bipush #58
    //   3936: ldc 536887312
    //   3938: iastore
    //   3939: dup
    //   3940: bipush #59
    //   3942: iconst_0
    //   3943: iastore
    //   3944: dup
    //   3945: bipush #60
    //   3947: ldc 541081600
    //   3949: iastore
    //   3950: dup
    //   3951: bipush #61
    //   3953: ldc 536870912
    //   3955: iastore
    //   3956: dup
    //   3957: bipush #62
    //   3959: ldc 4194320
    //   3961: iastore
    //   3962: dup
    //   3963: bipush #63
    //   3965: ldc 536887312
    //   3967: iastore
    //   3968: astore #14
    //   3970: bipush #64
    //   3972: newarray int
    //   3974: dup
    //   3975: iconst_0
    //   3976: ldc 2097152
    //   3978: iastore
    //   3979: dup
    //   3980: iconst_1
    //   3981: ldc 69206018
    //   3983: iastore
    //   3984: dup
    //   3985: iconst_2
    //   3986: ldc 67110914
    //   3988: iastore
    //   3989: dup
    //   3990: iconst_3
    //   3991: iconst_0
    //   3992: iastore
    //   3993: dup
    //   3994: iconst_4
    //   3995: sipush #2048
    //   3998: iastore
    //   3999: dup
    //   4000: iconst_5
    //   4001: ldc 67110914
    //   4003: iastore
    //   4004: dup
    //   4005: bipush #6
    //   4007: ldc 2099202
    //   4009: iastore
    //   4010: dup
    //   4011: bipush #7
    //   4013: ldc 69208064
    //   4015: iastore
    //   4016: dup
    //   4017: bipush #8
    //   4019: ldc 69208066
    //   4021: iastore
    //   4022: dup
    //   4023: bipush #9
    //   4025: ldc 2097152
    //   4027: iastore
    //   4028: dup
    //   4029: bipush #10
    //   4031: iconst_0
    //   4032: iastore
    //   4033: dup
    //   4034: bipush #11
    //   4036: ldc 67108866
    //   4038: iastore
    //   4039: dup
    //   4040: bipush #12
    //   4042: iconst_2
    //   4043: iastore
    //   4044: dup
    //   4045: bipush #13
    //   4047: ldc 67108864
    //   4049: iastore
    //   4050: dup
    //   4051: bipush #14
    //   4053: ldc 69206018
    //   4055: iastore
    //   4056: dup
    //   4057: bipush #15
    //   4059: sipush #2050
    //   4062: iastore
    //   4063: dup
    //   4064: bipush #16
    //   4066: ldc 67110912
    //   4068: iastore
    //   4069: dup
    //   4070: bipush #17
    //   4072: ldc 2099202
    //   4074: iastore
    //   4075: dup
    //   4076: bipush #18
    //   4078: ldc 2097154
    //   4080: iastore
    //   4081: dup
    //   4082: bipush #19
    //   4084: ldc 67110912
    //   4086: iastore
    //   4087: dup
    //   4088: bipush #20
    //   4090: ldc 67108866
    //   4092: iastore
    //   4093: dup
    //   4094: bipush #21
    //   4096: ldc 69206016
    //   4098: iastore
    //   4099: dup
    //   4100: bipush #22
    //   4102: ldc 69208064
    //   4104: iastore
    //   4105: dup
    //   4106: bipush #23
    //   4108: ldc 2097154
    //   4110: iastore
    //   4111: dup
    //   4112: bipush #24
    //   4114: ldc 69206016
    //   4116: iastore
    //   4117: dup
    //   4118: bipush #25
    //   4120: sipush #2048
    //   4123: iastore
    //   4124: dup
    //   4125: bipush #26
    //   4127: sipush #2050
    //   4130: iastore
    //   4131: dup
    //   4132: bipush #27
    //   4134: ldc 69208066
    //   4136: iastore
    //   4137: dup
    //   4138: bipush #28
    //   4140: ldc 2099200
    //   4142: iastore
    //   4143: dup
    //   4144: bipush #29
    //   4146: iconst_2
    //   4147: iastore
    //   4148: dup
    //   4149: bipush #30
    //   4151: ldc 67108864
    //   4153: iastore
    //   4154: dup
    //   4155: bipush #31
    //   4157: ldc 2099200
    //   4159: iastore
    //   4160: dup
    //   4161: bipush #32
    //   4163: ldc 67108864
    //   4165: iastore
    //   4166: dup
    //   4167: bipush #33
    //   4169: ldc 2099200
    //   4171: iastore
    //   4172: dup
    //   4173: bipush #34
    //   4175: ldc 2097152
    //   4177: iastore
    //   4178: dup
    //   4179: bipush #35
    //   4181: ldc 67110914
    //   4183: iastore
    //   4184: dup
    //   4185: bipush #36
    //   4187: ldc 67110914
    //   4189: iastore
    //   4190: dup
    //   4191: bipush #37
    //   4193: ldc 69206018
    //   4195: iastore
    //   4196: dup
    //   4197: bipush #38
    //   4199: ldc 69206018
    //   4201: iastore
    //   4202: dup
    //   4203: bipush #39
    //   4205: iconst_2
    //   4206: iastore
    //   4207: dup
    //   4208: bipush #40
    //   4210: ldc 2097154
    //   4212: iastore
    //   4213: dup
    //   4214: bipush #41
    //   4216: ldc 67108864
    //   4218: iastore
    //   4219: dup
    //   4220: bipush #42
    //   4222: ldc 67110912
    //   4224: iastore
    //   4225: dup
    //   4226: bipush #43
    //   4228: ldc 2097152
    //   4230: iastore
    //   4231: dup
    //   4232: bipush #44
    //   4234: ldc 69208064
    //   4236: iastore
    //   4237: dup
    //   4238: bipush #45
    //   4240: sipush #2050
    //   4243: iastore
    //   4244: dup
    //   4245: bipush #46
    //   4247: ldc 2099202
    //   4249: iastore
    //   4250: dup
    //   4251: bipush #47
    //   4253: ldc 69208064
    //   4255: iastore
    //   4256: dup
    //   4257: bipush #48
    //   4259: sipush #2050
    //   4262: iastore
    //   4263: dup
    //   4264: bipush #49
    //   4266: ldc 67108866
    //   4268: iastore
    //   4269: dup
    //   4270: bipush #50
    //   4272: ldc 69208066
    //   4274: iastore
    //   4275: dup
    //   4276: bipush #51
    //   4278: ldc 69206016
    //   4280: iastore
    //   4281: dup
    //   4282: bipush #52
    //   4284: ldc 2099200
    //   4286: iastore
    //   4287: dup
    //   4288: bipush #53
    //   4290: iconst_0
    //   4291: iastore
    //   4292: dup
    //   4293: bipush #54
    //   4295: iconst_2
    //   4296: iastore
    //   4297: dup
    //   4298: bipush #55
    //   4300: ldc 69208066
    //   4302: iastore
    //   4303: dup
    //   4304: bipush #56
    //   4306: iconst_0
    //   4307: iastore
    //   4308: dup
    //   4309: bipush #57
    //   4311: ldc 2099202
    //   4313: iastore
    //   4314: dup
    //   4315: bipush #58
    //   4317: ldc 69206016
    //   4319: iastore
    //   4320: dup
    //   4321: bipush #59
    //   4323: sipush #2048
    //   4326: iastore
    //   4327: dup
    //   4328: bipush #60
    //   4330: ldc 67108866
    //   4332: iastore
    //   4333: dup
    //   4334: bipush #61
    //   4336: ldc 67110912
    //   4338: iastore
    //   4339: dup
    //   4340: bipush #62
    //   4342: sipush #2048
    //   4345: iastore
    //   4346: dup
    //   4347: bipush #63
    //   4349: ldc 2097154
    //   4351: iastore
    //   4352: astore #15
    //   4354: bipush #64
    //   4356: newarray int
    //   4358: dup
    //   4359: iconst_0
    //   4360: ldc 268439616
    //   4362: iastore
    //   4363: dup
    //   4364: iconst_1
    //   4365: sipush #4096
    //   4368: iastore
    //   4369: dup
    //   4370: iconst_2
    //   4371: ldc 262144
    //   4373: iastore
    //   4374: dup
    //   4375: iconst_3
    //   4376: ldc 268701760
    //   4378: iastore
    //   4379: dup
    //   4380: iconst_4
    //   4381: ldc 268435456
    //   4383: iastore
    //   4384: dup
    //   4385: iconst_5
    //   4386: ldc 268439616
    //   4388: iastore
    //   4389: dup
    //   4390: bipush #6
    //   4392: bipush #64
    //   4394: iastore
    //   4395: dup
    //   4396: bipush #7
    //   4398: ldc 268435456
    //   4400: iastore
    //   4401: dup
    //   4402: bipush #8
    //   4404: ldc 262208
    //   4406: iastore
    //   4407: dup
    //   4408: bipush #9
    //   4410: ldc 268697600
    //   4412: iastore
    //   4413: dup
    //   4414: bipush #10
    //   4416: ldc 268701760
    //   4418: iastore
    //   4419: dup
    //   4420: bipush #11
    //   4422: ldc 266240
    //   4424: iastore
    //   4425: dup
    //   4426: bipush #12
    //   4428: ldc 268701696
    //   4430: iastore
    //   4431: dup
    //   4432: bipush #13
    //   4434: ldc 266304
    //   4436: iastore
    //   4437: dup
    //   4438: bipush #14
    //   4440: sipush #4096
    //   4443: iastore
    //   4444: dup
    //   4445: bipush #15
    //   4447: bipush #64
    //   4449: iastore
    //   4450: dup
    //   4451: bipush #16
    //   4453: ldc 268697600
    //   4455: iastore
    //   4456: dup
    //   4457: bipush #17
    //   4459: ldc 268435520
    //   4461: iastore
    //   4462: dup
    //   4463: bipush #18
    //   4465: ldc 268439552
    //   4467: iastore
    //   4468: dup
    //   4469: bipush #19
    //   4471: sipush #4160
    //   4474: iastore
    //   4475: dup
    //   4476: bipush #20
    //   4478: ldc 266240
    //   4480: iastore
    //   4481: dup
    //   4482: bipush #21
    //   4484: ldc 262208
    //   4486: iastore
    //   4487: dup
    //   4488: bipush #22
    //   4490: ldc 268697664
    //   4492: iastore
    //   4493: dup
    //   4494: bipush #23
    //   4496: ldc 268701696
    //   4498: iastore
    //   4499: dup
    //   4500: bipush #24
    //   4502: sipush #4160
    //   4505: iastore
    //   4506: dup
    //   4507: bipush #25
    //   4509: iconst_0
    //   4510: iastore
    //   4511: dup
    //   4512: bipush #26
    //   4514: iconst_0
    //   4515: iastore
    //   4516: dup
    //   4517: bipush #27
    //   4519: ldc 268697664
    //   4521: iastore
    //   4522: dup
    //   4523: bipush #28
    //   4525: ldc 268435520
    //   4527: iastore
    //   4528: dup
    //   4529: bipush #29
    //   4531: ldc 268439552
    //   4533: iastore
    //   4534: dup
    //   4535: bipush #30
    //   4537: ldc 266304
    //   4539: iastore
    //   4540: dup
    //   4541: bipush #31
    //   4543: ldc 262144
    //   4545: iastore
    //   4546: dup
    //   4547: bipush #32
    //   4549: ldc 266304
    //   4551: iastore
    //   4552: dup
    //   4553: bipush #33
    //   4555: ldc 262144
    //   4557: iastore
    //   4558: dup
    //   4559: bipush #34
    //   4561: ldc 268701696
    //   4563: iastore
    //   4564: dup
    //   4565: bipush #35
    //   4567: sipush #4096
    //   4570: iastore
    //   4571: dup
    //   4572: bipush #36
    //   4574: bipush #64
    //   4576: iastore
    //   4577: dup
    //   4578: bipush #37
    //   4580: ldc 268697664
    //   4582: iastore
    //   4583: dup
    //   4584: bipush #38
    //   4586: sipush #4096
    //   4589: iastore
    //   4590: dup
    //   4591: bipush #39
    //   4593: ldc 266304
    //   4595: iastore
    //   4596: dup
    //   4597: bipush #40
    //   4599: ldc 268439552
    //   4601: iastore
    //   4602: dup
    //   4603: bipush #41
    //   4605: bipush #64
    //   4607: iastore
    //   4608: dup
    //   4609: bipush #42
    //   4611: ldc 268435520
    //   4613: iastore
    //   4614: dup
    //   4615: bipush #43
    //   4617: ldc 268697600
    //   4619: iastore
    //   4620: dup
    //   4621: bipush #44
    //   4623: ldc 268697664
    //   4625: iastore
    //   4626: dup
    //   4627: bipush #45
    //   4629: ldc 268435456
    //   4631: iastore
    //   4632: dup
    //   4633: bipush #46
    //   4635: ldc 262144
    //   4637: iastore
    //   4638: dup
    //   4639: bipush #47
    //   4641: ldc 268439616
    //   4643: iastore
    //   4644: dup
    //   4645: bipush #48
    //   4647: iconst_0
    //   4648: iastore
    //   4649: dup
    //   4650: bipush #49
    //   4652: ldc 268701760
    //   4654: iastore
    //   4655: dup
    //   4656: bipush #50
    //   4658: ldc 262208
    //   4660: iastore
    //   4661: dup
    //   4662: bipush #51
    //   4664: ldc 268435520
    //   4666: iastore
    //   4667: dup
    //   4668: bipush #52
    //   4670: ldc 268697600
    //   4672: iastore
    //   4673: dup
    //   4674: bipush #53
    //   4676: ldc 268439552
    //   4678: iastore
    //   4679: dup
    //   4680: bipush #54
    //   4682: ldc 268439616
    //   4684: iastore
    //   4685: dup
    //   4686: bipush #55
    //   4688: iconst_0
    //   4689: iastore
    //   4690: dup
    //   4691: bipush #56
    //   4693: ldc 268701760
    //   4695: iastore
    //   4696: dup
    //   4697: bipush #57
    //   4699: ldc 266240
    //   4701: iastore
    //   4702: dup
    //   4703: bipush #58
    //   4705: ldc 266240
    //   4707: iastore
    //   4708: dup
    //   4709: bipush #59
    //   4711: sipush #4160
    //   4714: iastore
    //   4715: dup
    //   4716: bipush #60
    //   4718: sipush #4160
    //   4721: iastore
    //   4722: dup
    //   4723: bipush #61
    //   4725: ldc 262208
    //   4727: iastore
    //   4728: dup
    //   4729: bipush #62
    //   4731: ldc 268435456
    //   4733: iastore
    //   4734: dup
    //   4735: bipush #63
    //   4737: ldc 268701696
    //   4739: iastore
    //   4740: astore #16
    //   4742: aload #4
    //   4744: arraylength
    //   4745: istore #17
    //   4747: iconst_2
    //   4748: newarray int
    //   4750: astore #18
    //   4752: iload #17
    //   4754: newarray byte
    //   4756: astore #5
    //   4758: iload #17
    //   4760: bipush #8
    //   4762: idiv
    //   4763: istore #19
    //   4765: iconst_0
    //   4766: istore #20
    //   4768: iload #20
    //   4770: iload #19
    //   4772: if_icmpge -> 5690
    //   4775: iload #20
    //   4777: bipush #8
    //   4779: imul
    //   4780: istore #21
    //   4782: iconst_0
    //   4783: istore #22
    //   4785: iload #22
    //   4787: iconst_2
    //   4788: if_icmpge -> 4877
    //   4791: aload #18
    //   4793: iload #22
    //   4795: aload #4
    //   4797: iload #21
    //   4799: iload #22
    //   4801: iconst_4
    //   4802: imul
    //   4803: iadd
    //   4804: baload
    //   4805: sipush #255
    //   4808: iand
    //   4809: bipush #24
    //   4811: ishl
    //   4812: aload #4
    //   4814: iload #21
    //   4816: iload #22
    //   4818: iconst_4
    //   4819: imul
    //   4820: iadd
    //   4821: iconst_1
    //   4822: iadd
    //   4823: baload
    //   4824: sipush #255
    //   4827: iand
    //   4828: bipush #16
    //   4830: ishl
    //   4831: ior
    //   4832: aload #4
    //   4834: iload #21
    //   4836: iload #22
    //   4838: iconst_4
    //   4839: imul
    //   4840: iadd
    //   4841: iconst_2
    //   4842: iadd
    //   4843: baload
    //   4844: sipush #255
    //   4847: iand
    //   4848: bipush #8
    //   4850: ishl
    //   4851: ior
    //   4852: aload #4
    //   4854: iload #21
    //   4856: iload #22
    //   4858: iconst_4
    //   4859: imul
    //   4860: iadd
    //   4861: iconst_3
    //   4862: iadd
    //   4863: baload
    //   4864: sipush #255
    //   4867: iand
    //   4868: ior
    //   4869: iastore
    //   4870: iinc #22, 1
    //   4873: iload_2
    //   4874: ifeq -> 4785
    //   4877: iconst_0
    //   4878: istore #27
    //   4880: aload #18
    //   4882: iconst_0
    //   4883: iaload
    //   4884: istore #25
    //   4886: aload #18
    //   4888: iconst_1
    //   4889: iaload
    //   4890: istore #24
    //   4892: iload #25
    //   4894: iconst_4
    //   4895: iushr
    //   4896: iload #24
    //   4898: ixor
    //   4899: ldc 252645135
    //   4901: iand
    //   4902: istore #23
    //   4904: iload #24
    //   4906: iload #23
    //   4908: ixor
    //   4909: istore #24
    //   4911: iload #25
    //   4913: iload #23
    //   4915: iconst_4
    //   4916: ishl
    //   4917: ixor
    //   4918: istore #25
    //   4920: iload #25
    //   4922: bipush #16
    //   4924: iushr
    //   4925: iload #24
    //   4927: ixor
    //   4928: ldc 65535
    //   4930: iand
    //   4931: istore #23
    //   4933: iload #24
    //   4935: iload #23
    //   4937: ixor
    //   4938: istore #24
    //   4940: iload #25
    //   4942: iload #23
    //   4944: bipush #16
    //   4946: ishl
    //   4947: ixor
    //   4948: istore #25
    //   4950: iload #24
    //   4952: iconst_2
    //   4953: iushr
    //   4954: iload #25
    //   4956: ixor
    //   4957: ldc 858993459
    //   4959: iand
    //   4960: istore #23
    //   4962: iload #25
    //   4964: iload #23
    //   4966: ixor
    //   4967: istore #25
    //   4969: iload #24
    //   4971: iload #23
    //   4973: iconst_2
    //   4974: ishl
    //   4975: ixor
    //   4976: istore #24
    //   4978: iload #24
    //   4980: bipush #8
    //   4982: iushr
    //   4983: iload #25
    //   4985: ixor
    //   4986: ldc 16711935
    //   4988: iand
    //   4989: istore #23
    //   4991: iload #25
    //   4993: iload #23
    //   4995: ixor
    //   4996: istore #25
    //   4998: iload #24
    //   5000: iload #23
    //   5002: bipush #8
    //   5004: ishl
    //   5005: ixor
    //   5006: istore #24
    //   5008: iload #24
    //   5010: iconst_1
    //   5011: ishl
    //   5012: iload #24
    //   5014: bipush #31
    //   5016: iushr
    //   5017: iconst_1
    //   5018: iand
    //   5019: ior
    //   5020: istore #24
    //   5022: iload #25
    //   5024: iload #24
    //   5026: ixor
    //   5027: ldc -1431655766
    //   5029: iand
    //   5030: istore #23
    //   5032: iload #25
    //   5034: iload #23
    //   5036: ixor
    //   5037: istore #25
    //   5039: iload #24
    //   5041: iload #23
    //   5043: ixor
    //   5044: istore #24
    //   5046: iload #25
    //   5048: iconst_1
    //   5049: ishl
    //   5050: iload #25
    //   5052: bipush #31
    //   5054: iushr
    //   5055: iconst_1
    //   5056: iand
    //   5057: ior
    //   5058: istore #25
    //   5060: iconst_0
    //   5061: istore #26
    //   5063: iload #26
    //   5065: bipush #8
    //   5067: if_icmpge -> 5405
    //   5070: iload #24
    //   5072: bipush #28
    //   5074: ishl
    //   5075: iload #24
    //   5077: iconst_4
    //   5078: iushr
    //   5079: ior
    //   5080: istore #23
    //   5082: iload #23
    //   5084: aload #6
    //   5086: iload #27
    //   5088: iinc #27, 1
    //   5091: iaload
    //   5092: ixor
    //   5093: istore #23
    //   5095: aload #15
    //   5097: iload #23
    //   5099: bipush #63
    //   5101: iand
    //   5102: iaload
    //   5103: istore #22
    //   5105: iload #22
    //   5107: aload #13
    //   5109: iload #23
    //   5111: bipush #8
    //   5113: iushr
    //   5114: bipush #63
    //   5116: iand
    //   5117: iaload
    //   5118: ior
    //   5119: istore #22
    //   5121: iload #22
    //   5123: aload #11
    //   5125: iload #23
    //   5127: bipush #16
    //   5129: iushr
    //   5130: bipush #63
    //   5132: iand
    //   5133: iaload
    //   5134: ior
    //   5135: istore #22
    //   5137: iload #22
    //   5139: aload #9
    //   5141: iload #23
    //   5143: bipush #24
    //   5145: iushr
    //   5146: bipush #63
    //   5148: iand
    //   5149: iaload
    //   5150: ior
    //   5151: istore #22
    //   5153: iload #24
    //   5155: aload #6
    //   5157: iload #27
    //   5159: iinc #27, 1
    //   5162: iaload
    //   5163: ixor
    //   5164: istore #23
    //   5166: iload #22
    //   5168: aload #16
    //   5170: iload #23
    //   5172: bipush #63
    //   5174: iand
    //   5175: iaload
    //   5176: ior
    //   5177: istore #22
    //   5179: iload #22
    //   5181: aload #14
    //   5183: iload #23
    //   5185: bipush #8
    //   5187: iushr
    //   5188: bipush #63
    //   5190: iand
    //   5191: iaload
    //   5192: ior
    //   5193: istore #22
    //   5195: iload #22
    //   5197: aload #12
    //   5199: iload #23
    //   5201: bipush #16
    //   5203: iushr
    //   5204: bipush #63
    //   5206: iand
    //   5207: iaload
    //   5208: ior
    //   5209: istore #22
    //   5211: iload #22
    //   5213: aload #10
    //   5215: iload #23
    //   5217: bipush #24
    //   5219: iushr
    //   5220: bipush #63
    //   5222: iand
    //   5223: iaload
    //   5224: ior
    //   5225: istore #22
    //   5227: iload #25
    //   5229: iload #22
    //   5231: ixor
    //   5232: istore #25
    //   5234: iload #25
    //   5236: bipush #28
    //   5238: ishl
    //   5239: iload #25
    //   5241: iconst_4
    //   5242: iushr
    //   5243: ior
    //   5244: istore #23
    //   5246: iload #23
    //   5248: aload #6
    //   5250: iload #27
    //   5252: iinc #27, 1
    //   5255: iaload
    //   5256: ixor
    //   5257: istore #23
    //   5259: aload #15
    //   5261: iload #23
    //   5263: bipush #63
    //   5265: iand
    //   5266: iaload
    //   5267: istore #22
    //   5269: iload #22
    //   5271: aload #13
    //   5273: iload #23
    //   5275: bipush #8
    //   5277: iushr
    //   5278: bipush #63
    //   5280: iand
    //   5281: iaload
    //   5282: ior
    //   5283: istore #22
    //   5285: iload #22
    //   5287: aload #11
    //   5289: iload #23
    //   5291: bipush #16
    //   5293: iushr
    //   5294: bipush #63
    //   5296: iand
    //   5297: iaload
    //   5298: ior
    //   5299: istore #22
    //   5301: iload #22
    //   5303: aload #9
    //   5305: iload #23
    //   5307: bipush #24
    //   5309: iushr
    //   5310: bipush #63
    //   5312: iand
    //   5313: iaload
    //   5314: ior
    //   5315: istore #22
    //   5317: iload #25
    //   5319: aload #6
    //   5321: iload #27
    //   5323: iinc #27, 1
    //   5326: iaload
    //   5327: ixor
    //   5328: istore #23
    //   5330: iload #22
    //   5332: aload #16
    //   5334: iload #23
    //   5336: bipush #63
    //   5338: iand
    //   5339: iaload
    //   5340: ior
    //   5341: istore #22
    //   5343: iload #22
    //   5345: aload #14
    //   5347: iload #23
    //   5349: bipush #8
    //   5351: iushr
    //   5352: bipush #63
    //   5354: iand
    //   5355: iaload
    //   5356: ior
    //   5357: istore #22
    //   5359: iload #22
    //   5361: aload #12
    //   5363: iload #23
    //   5365: bipush #16
    //   5367: iushr
    //   5368: bipush #63
    //   5370: iand
    //   5371: iaload
    //   5372: ior
    //   5373: istore #22
    //   5375: iload #22
    //   5377: aload #10
    //   5379: iload #23
    //   5381: bipush #24
    //   5383: iushr
    //   5384: bipush #63
    //   5386: iand
    //   5387: iaload
    //   5388: ior
    //   5389: istore #22
    //   5391: iload #24
    //   5393: iload #22
    //   5395: ixor
    //   5396: istore #24
    //   5398: iinc #26, 1
    //   5401: iload_2
    //   5402: ifeq -> 5063
    //   5405: iload #24
    //   5407: bipush #31
    //   5409: ishl
    //   5410: iload #24
    //   5412: iconst_1
    //   5413: iushr
    //   5414: ior
    //   5415: istore #24
    //   5417: iload #25
    //   5419: iload #24
    //   5421: ixor
    //   5422: ldc -1431655766
    //   5424: iand
    //   5425: istore #23
    //   5427: iload #25
    //   5429: iload #23
    //   5431: ixor
    //   5432: istore #25
    //   5434: iload #24
    //   5436: iload #23
    //   5438: ixor
    //   5439: istore #24
    //   5441: iload #25
    //   5443: bipush #31
    //   5445: ishl
    //   5446: iload #25
    //   5448: iconst_1
    //   5449: iushr
    //   5450: ior
    //   5451: istore #25
    //   5453: iload #25
    //   5455: bipush #8
    //   5457: iushr
    //   5458: iload #24
    //   5460: ixor
    //   5461: ldc 16711935
    //   5463: iand
    //   5464: istore #23
    //   5466: iload #24
    //   5468: iload #23
    //   5470: ixor
    //   5471: istore #24
    //   5473: iload #25
    //   5475: iload #23
    //   5477: bipush #8
    //   5479: ishl
    //   5480: ixor
    //   5481: istore #25
    //   5483: iload #25
    //   5485: iconst_2
    //   5486: iushr
    //   5487: iload #24
    //   5489: ixor
    //   5490: ldc 858993459
    //   5492: iand
    //   5493: istore #23
    //   5495: iload #24
    //   5497: iload #23
    //   5499: ixor
    //   5500: istore #24
    //   5502: iload #25
    //   5504: iload #23
    //   5506: iconst_2
    //   5507: ishl
    //   5508: ixor
    //   5509: istore #25
    //   5511: iload #24
    //   5513: bipush #16
    //   5515: iushr
    //   5516: iload #25
    //   5518: ixor
    //   5519: ldc 65535
    //   5521: iand
    //   5522: istore #23
    //   5524: iload #25
    //   5526: iload #23
    //   5528: ixor
    //   5529: istore #25
    //   5531: iload #24
    //   5533: iload #23
    //   5535: bipush #16
    //   5537: ishl
    //   5538: ixor
    //   5539: istore #24
    //   5541: iload #24
    //   5543: iconst_4
    //   5544: iushr
    //   5545: iload #25
    //   5547: ixor
    //   5548: ldc 252645135
    //   5550: iand
    //   5551: istore #23
    //   5553: iload #25
    //   5555: iload #23
    //   5557: ixor
    //   5558: istore #25
    //   5560: iload #24
    //   5562: iload #23
    //   5564: iconst_4
    //   5565: ishl
    //   5566: ixor
    //   5567: istore #24
    //   5569: aload #18
    //   5571: iconst_0
    //   5572: iload #24
    //   5574: iastore
    //   5575: aload #18
    //   5577: iconst_1
    //   5578: iload #25
    //   5580: iastore
    //   5581: iload #20
    //   5583: bipush #8
    //   5585: imul
    //   5586: istore #28
    //   5588: iconst_0
    //   5589: istore #29
    //   5591: iload #29
    //   5593: iconst_2
    //   5594: if_icmpge -> 5683
    //   5597: aload #5
    //   5599: iload #28
    //   5601: iload #29
    //   5603: iconst_4
    //   5604: imul
    //   5605: iadd
    //   5606: aload #18
    //   5608: iload #29
    //   5610: iaload
    //   5611: bipush #24
    //   5613: iushr
    //   5614: i2b
    //   5615: bastore
    //   5616: aload #5
    //   5618: iload #28
    //   5620: iload #29
    //   5622: iconst_4
    //   5623: imul
    //   5624: iadd
    //   5625: iconst_1
    //   5626: iadd
    //   5627: aload #18
    //   5629: iload #29
    //   5631: iaload
    //   5632: bipush #16
    //   5634: iushr
    //   5635: i2b
    //   5636: bastore
    //   5637: aload #5
    //   5639: iload #28
    //   5641: iload #29
    //   5643: iconst_4
    //   5644: imul
    //   5645: iadd
    //   5646: iconst_2
    //   5647: iadd
    //   5648: aload #18
    //   5650: iload #29
    //   5652: iaload
    //   5653: bipush #8
    //   5655: iushr
    //   5656: i2b
    //   5657: bastore
    //   5658: aload #5
    //   5660: iload #28
    //   5662: iload #29
    //   5664: iconst_4
    //   5665: imul
    //   5666: iadd
    //   5667: iconst_3
    //   5668: iadd
    //   5669: aload #18
    //   5671: iload #29
    //   5673: iaload
    //   5674: i2b
    //   5675: bastore
    //   5676: iinc #29, 1
    //   5679: iload_2
    //   5680: ifeq -> 5591
    //   5683: iinc #20, 1
    //   5686: iload_2
    //   5687: ifeq -> 4768
    //   5690: new java/math/BigInteger
    //   5693: dup
    //   5694: aload #5
    //   5696: invokespecial <init> : ([B)V
    //   5699: invokevirtual abs : ()Ljava/math/BigInteger;
    //   5702: putstatic burp/Zg4k.ZE : Ljava/lang/Object;
    //   5705: sipush #26213
    //   5708: sipush #21242
    //   5711: invokestatic a : (II)Ljava/lang/String;
    //   5714: iconst_1
    //   5715: ldc burp/Zzuh
    //   5717: invokevirtual getClassLoader : ()Ljava/lang/ClassLoader;
    //   5720: invokestatic forName : (Ljava/lang/String;ZLjava/lang/ClassLoader;)Ljava/lang/Class;
    //   5723: invokevirtual getDeclaredFields : ()[Ljava/lang/reflect/Field;
    //   5726: astore #4
    //   5728: aload #4
    //   5730: arraylength
    //   5731: istore #5
    //   5733: iconst_0
    //   5734: istore #6
    //   5736: iload #6
    //   5738: iload #5
    //   5740: if_icmpge -> 5878
    //   5743: aload #4
    //   5745: iload #6
    //   5747: aaload
    //   5748: astore #7
    //   5750: aload #7
    //   5752: invokevirtual getModifiers : ()I
    //   5755: invokestatic isStatic : (I)Z
    //   5758: ifne -> 5768
    //   5761: goto -> 5871
    //   5764: invokestatic a : (Ljava/lang/Throwable;)Ljava/lang/Throwable;
    //   5767: athrow
    //   5768: aload #7
    //   5770: invokevirtual getType : ()Ljava/lang/Class;
    //   5773: astore #8
    //   5775: aload #8
    //   5777: ifnull -> 5858
    //   5780: aload #8
    //   5782: invokevirtual isPrimitive : ()Z
    //   5785: ifne -> 5858
    //   5788: goto -> 5795
    //   5791: invokestatic a : (Ljava/lang/Throwable;)Ljava/lang/Throwable;
    //   5794: athrow
    //   5795: aload #8
    //   5797: invokevirtual getPackage : ()Ljava/lang/Package;
    //   5800: ifnull -> 5858
    //   5803: goto -> 5810
    //   5806: invokestatic a : (Ljava/lang/Throwable;)Ljava/lang/Throwable;
    //   5809: athrow
    //   5810: aload #8
    //   5812: invokevirtual getPackage : ()Ljava/lang/Package;
    //   5815: invokevirtual getName : ()Ljava/lang/String;
    //   5818: ifnull -> 5858
    //   5821: goto -> 5828
    //   5824: invokestatic a : (Ljava/lang/Throwable;)Ljava/lang/Throwable;
    //   5827: athrow
    //   5828: aload #8
    //   5830: invokevirtual getPackage : ()Ljava/lang/Package;
    //   5833: invokevirtual getName : ()Ljava/lang/String;
    //   5836: sipush #26212
    //   5839: sipush #13196
    //   5842: invokestatic a : (II)Ljava/lang/String;
    //   5845: invokevirtual startsWith : (Ljava/lang/String;)Z
    //   5848: ifne -> 5858
    //   5851: goto -> 5858
    //   5854: invokestatic a : (Ljava/lang/Throwable;)Ljava/lang/Throwable;
    //   5857: athrow
    //   5858: aload #7
    //   5860: iconst_1
    //   5861: invokevirtual setAccessible : (Z)V
    //   5864: aload #7
    //   5866: aconst_null
    //   5867: invokevirtual get : (Ljava/lang/Object;)Ljava/lang/Object;
    //   5870: pop
    //   5871: iinc #6, 1
    //   5874: iload_2
    //   5875: ifeq -> 5736
    //   5878: sipush #26208
    //   5881: sipush #-22132
    //   5884: invokestatic a : (II)Ljava/lang/String;
    //   5887: invokestatic forName : (Ljava/lang/String;)Ljava/lang/Class;
    //   5890: invokevirtual getDeclaredMethods : ()[Ljava/lang/reflect/Method;
    //   5893: astore #4
    //   5895: aload #4
    //   5897: arraylength
    //   5898: istore #5
    //   5900: iconst_0
    //   5901: istore #6
    //   5903: iload #6
    //   5905: iload #5
    //   5907: if_icmpge -> 6040
    //   5910: aload #4
    //   5912: iload #6
    //   5914: aaload
    //   5915: astore #7
    //   5917: aload #7
    //   5919: invokevirtual getParameterTypes : ()[Ljava/lang/Class;
    //   5922: pop
    //   5923: aload #7
    //   5925: invokevirtual getModifiers : ()I
    //   5928: invokestatic isStatic : (I)Z
    //   5931: ifeq -> 6026
    //   5934: aload #7
    //   5936: invokevirtual getParameterTypes : ()[Ljava/lang/Class;
    //   5939: arraylength
    //   5940: iconst_2
    //   5941: if_icmpne -> 6026
    //   5944: goto -> 5951
    //   5947: invokestatic a : (Ljava/lang/Throwable;)Ljava/lang/Throwable;
    //   5950: athrow
    //   5951: aload #7
    //   5953: invokevirtual getReturnType : ()Ljava/lang/Class;
    //   5956: getstatic java/lang/Void.TYPE : Ljava/lang/Class;
    //   5959: invokevirtual equals : (Ljava/lang/Object;)Z
    //   5962: ifeq -> 6026
    //   5965: goto -> 5972
    //   5968: invokestatic a : (Ljava/lang/Throwable;)Ljava/lang/Throwable;
    //   5971: athrow
    //   5972: aload #7
    //   5974: iconst_1
    //   5975: invokevirtual setAccessible : (Z)V
    //   5978: aload #7
    //   5980: aconst_null
    //   5981: iconst_2
    //   5982: anewarray java/lang/Object
    //   5985: dup
    //   5986: iconst_0
    //   5987: aload_0
    //   5988: aastore
    //   5989: dup
    //   5990: iconst_1
    //   5991: aload_1
    //   5992: ifnonnull -> 6010
    //   5995: goto -> 6002
    //   5998: invokestatic a : (Ljava/lang/Throwable;)Ljava/lang/Throwable;
    //   6001: athrow
    //   6002: aload_1
    //   6003: goto -> 6017
    //   6006: invokestatic a : (Ljava/lang/Throwable;)Ljava/lang/Throwable;
    //   6009: athrow
    //   6010: aload_1
    //   6011: checkcast [B
    //   6014: invokevirtual clone : ()Ljava/lang/Object;
    //   6017: aastore
    //   6018: invokevirtual invoke : (Ljava/lang/Object;[Ljava/lang/Object;)Ljava/lang/Object;
    //   6021: pop
    //   6022: iload_2
    //   6023: ifeq -> 6040
    //   6026: iinc #6, 1
    //   6029: iload_2
    //   6030: ifeq -> 5903
    //   6033: goto -> 6040
    //   6036: invokestatic a : (Ljava/lang/Throwable;)Ljava/lang/Throwable;
    //   6039: athrow
    //   6040: getstatic burp/Zlpj.Zc : Ljava/lang/Object;
    //   6043: checkcast java/math/BigInteger
    //   6046: invokevirtual intValue : ()I
    //   6049: i2l
    //   6050: invokestatic currentTimeMillis : ()J
    //   6053: ladd
    //   6054: getstatic burp/Zzym.ZK : Ljava/lang/Object;
    //   6057: checkcast java/math/BigInteger
    //   6060: invokevirtual intValue : ()I
    //   6063: i2l
    //   6064: lcmp
    //   6065: ifge -> 6403
    //   6068: sipush #26211
    //   6071: sipush #-20885
    //   6074: invokestatic a : (II)Ljava/lang/String;
    //   6077: iconst_1
    //   6078: ldc burp/Zshq
    //   6080: invokevirtual getClassLoader : ()Ljava/lang/ClassLoader;
    //   6083: invokestatic forName : (Ljava/lang/String;ZLjava/lang/ClassLoader;)Ljava/lang/Class;
    //   6086: invokevirtual getDeclaredFields : ()[Ljava/lang/reflect/Field;
    //   6089: astore #4
    //   6091: aload #4
    //   6093: arraylength
    //   6094: istore #5
    //   6096: iconst_0
    //   6097: istore #6
    //   6099: iload #6
    //   6101: iload #5
    //   6103: if_icmpge -> 6241
    //   6106: aload #4
    //   6108: iload #6
    //   6110: aaload
    //   6111: astore #7
    //   6113: aload #7
    //   6115: invokevirtual getModifiers : ()I
    //   6118: invokestatic isStatic : (I)Z
    //   6121: ifne -> 6131
    //   6124: goto -> 6234
    //   6127: invokestatic a : (Ljava/lang/Throwable;)Ljava/lang/Throwable;
    //   6130: athrow
    //   6131: aload #7
    //   6133: invokevirtual getType : ()Ljava/lang/Class;
    //   6136: astore #8
    //   6138: aload #8
    //   6140: ifnull -> 6221
    //   6143: aload #8
    //   6145: invokevirtual isPrimitive : ()Z
    //   6148: ifne -> 6221
    //   6151: goto -> 6158
    //   6154: invokestatic a : (Ljava/lang/Throwable;)Ljava/lang/Throwable;
    //   6157: athrow
    //   6158: aload #8
    //   6160: invokevirtual getPackage : ()Ljava/lang/Package;
    //   6163: ifnull -> 6221
    //   6166: goto -> 6173
    //   6169: invokestatic a : (Ljava/lang/Throwable;)Ljava/lang/Throwable;
    //   6172: athrow
    //   6173: aload #8
    //   6175: invokevirtual getPackage : ()Ljava/lang/Package;
    //   6178: invokevirtual getName : ()Ljava/lang/String;
    //   6181: ifnull -> 6221
    //   6184: goto -> 6191
    //   6187: invokestatic a : (Ljava/lang/Throwable;)Ljava/lang/Throwable;
    //   6190: athrow
    //   6191: aload #8
    //   6193: invokevirtual getPackage : ()Ljava/lang/Package;
    //   6196: invokevirtual getName : ()Ljava/lang/String;
    //   6199: sipush #26209
    //   6202: sipush #-25374
    //   6205: invokestatic a : (II)Ljava/lang/String;
    //   6208: invokevirtual startsWith : (Ljava/lang/String;)Z
    //   6211: ifne -> 6221
    //   6214: goto -> 6221
    //   6217: invokestatic a : (Ljava/lang/Throwable;)Ljava/lang/Throwable;
    //   6220: athrow
    //   6221: aload #7
    //   6223: iconst_1
    //   6224: invokevirtual setAccessible : (Z)V
    //   6227: aload #7
    //   6229: aconst_null
    //   6230: invokevirtual get : (Ljava/lang/Object;)Ljava/lang/Object;
    //   6233: pop
    //   6234: iinc #6, 1
    //   6237: iload_2
    //   6238: ifeq -> 6099
    //   6241: sipush #26214
    //   6244: sipush #-31941
    //   6247: invokestatic a : (II)Ljava/lang/String;
    //   6250: invokestatic forName : (Ljava/lang/String;)Ljava/lang/Class;
    //   6253: invokevirtual getDeclaredMethods : ()[Ljava/lang/reflect/Method;
    //   6256: astore #4
    //   6258: aload #4
    //   6260: arraylength
    //   6261: istore #5
    //   6263: iconst_0
    //   6264: istore #6
    //   6266: iload #6
    //   6268: iload #5
    //   6270: if_icmpge -> 6403
    //   6273: aload #4
    //   6275: iload #6
    //   6277: aaload
    //   6278: astore #7
    //   6280: aload #7
    //   6282: invokevirtual getParameterTypes : ()[Ljava/lang/Class;
    //   6285: pop
    //   6286: aload #7
    //   6288: invokevirtual getModifiers : ()I
    //   6291: invokestatic isStatic : (I)Z
    //   6294: ifeq -> 6389
    //   6297: aload #7
    //   6299: invokevirtual getParameterTypes : ()[Ljava/lang/Class;
    //   6302: arraylength
    //   6303: iconst_2
    //   6304: if_icmpne -> 6389
    //   6307: goto -> 6314
    //   6310: invokestatic a : (Ljava/lang/Throwable;)Ljava/lang/Throwable;
    //   6313: athrow
    //   6314: aload #7
    //   6316: invokevirtual getReturnType : ()Ljava/lang/Class;
    //   6319: getstatic java/lang/Void.TYPE : Ljava/lang/Class;
    //   6322: invokevirtual equals : (Ljava/lang/Object;)Z
    //   6325: ifeq -> 6389
    //   6328: goto -> 6335
    //   6331: invokestatic a : (Ljava/lang/Throwable;)Ljava/lang/Throwable;
    //   6334: athrow
    //   6335: aload #7
    //   6337: iconst_1
    //   6338: invokevirtual setAccessible : (Z)V
    //   6341: aload #7
    //   6343: aconst_null
    //   6344: iconst_2
    //   6345: anewarray java/lang/Object
    //   6348: dup
    //   6349: iconst_0
    //   6350: aload_0
    //   6351: aastore
    //   6352: dup
    //   6353: iconst_1
    //   6354: aload_1
    //   6355: ifnonnull -> 6373
    //   6358: goto -> 6365
    //   6361: invokestatic a : (Ljava/lang/Throwable;)Ljava/lang/Throwable;
    //   6364: athrow
    //   6365: aload_1
    //   6366: goto -> 6380
    //   6369: invokestatic a : (Ljava/lang/Throwable;)Ljava/lang/Throwable;
    //   6372: athrow
    //   6373: aload_1
    //   6374: checkcast [B
    //   6377: invokevirtual clone : ()Ljava/lang/Object;
    //   6380: aastore
    //   6381: invokevirtual invoke : (Ljava/lang/Object;[Ljava/lang/Object;)Ljava/lang/Object;
    //   6384: pop
    //   6385: iload_2
    //   6386: ifeq -> 6403
    //   6389: iinc #6, 1
    //   6392: iload_2
    //   6393: ifeq -> 6266
    //   6396: goto -> 6403
    //   6399: invokestatic a : (Ljava/lang/Throwable;)Ljava/lang/Throwable;
    //   6402: athrow
    //   6403: getstatic burp/Zl50.Zm : Ljava/lang/String;
    //   6406: getstatic burp/Zz75.ZX : Ljava/lang/Object;
    //   6409: checkcast java/math/BigInteger
    //   6412: invokevirtual intValue : ()I
    //   6415: bipush #32
    //   6417: irem
    //   6418: invokestatic abs : (I)I
    //   6421: invokevirtual charAt : (I)C
    //   6424: getstatic burp/Ztsu.ZE : Ljava/lang/String;
    //   6427: getstatic burp/Zk12.Zh : Ljava/lang/Object;
    //   6430: checkcast java/math/BigInteger
    //   6433: invokevirtual intValue : ()I
    //   6436: bipush #32
    //   6438: irem
    //   6439: invokestatic abs : (I)I
    //   6442: invokevirtual charAt : (I)C
    //   6445: if_icmple -> 6552
    //   6448: getstatic burp/Zrpu.Zy : Ljava/lang/String;
    //   6451: getstatic burp/Zl50.ZV : Ljava/lang/Object;
    //   6454: checkcast java/math/BigInteger
    //   6457: invokevirtual intValue : ()I
    //   6460: bipush #32
    //   6462: irem
    //   6463: invokestatic abs : (I)I
    //   6466: invokevirtual charAt : (I)C
    //   6469: getstatic burp/Zeqg.Zh : Ljava/lang/String;
    //   6472: getstatic burp/Ztye.ZK : Ljava/lang/Object;
    //   6475: checkcast java/math/BigInteger
    //   6478: invokevirtual intValue : ()I
    //   6481: bipush #32
    //   6483: irem
    //   6484: invokestatic abs : (I)I
    //   6487: invokevirtual charAt : (I)C
    //   6490: if_icmpgt -> 6552
    //   6493: goto -> 6500
    //   6496: invokestatic a : (Ljava/lang/Throwable;)Ljava/lang/Throwable;
    //   6499: athrow
    //   6500: getstatic burp/Zs00.Zv : Ljava/lang/String;
    //   6503: getstatic burp/Zlrm.ZM : Ljava/lang/Object;
    //   6506: checkcast java/math/BigInteger
    //   6509: invokevirtual intValue : ()I
    //   6512: bipush #32
    //   6514: irem
    //   6515: invokestatic abs : (I)I
    //   6518: invokevirtual charAt : (I)C
    //   6521: getstatic burp/Zel.Zi : Ljava/lang/String;
    //   6524: getstatic burp/Zs00.ZF : Ljava/lang/Object;
    //   6527: checkcast java/math/BigInteger
    //   6530: invokevirtual intValue : ()I
    //   6533: bipush #32
    //   6535: irem
    //   6536: invokestatic abs : (I)I
    //   6539: invokevirtual charAt : (I)C
    //   6542: if_icmple -> 6560
    //   6545: goto -> 6552
    //   6548: invokestatic a : (Ljava/lang/Throwable;)Ljava/lang/Throwable;
    //   6551: athrow
    //   6552: iconst_1
    //   6553: goto -> 6561
    //   6556: invokestatic a : (Ljava/lang/Throwable;)Ljava/lang/Throwable;
    //   6559: athrow
    //   6560: iconst_0
    //   6561: ireturn
    //   6562: astore_3
    //   6563: new java/lang/Exception
    //   6566: dup
    //   6567: aload_3
    //   6568: invokevirtual getMessage : ()Ljava/lang/String;
    //   6571: invokespecial <init> : (Ljava/lang/String;)V
    //   6574: athrow
    // Exception table:
    //   from	to	target	type
    //   4	6561	6562	java/lang/Throwable
    //   22	198	201	java/lang/Throwable
    //   168	235	238	java/lang/Throwable
    //   205	272	275	java/lang/Throwable
    //   242	309	312	java/lang/Throwable
    //   279	346	349	java/lang/Throwable
    //   316	383	386	java/lang/Throwable
    //   353	420	423	java/lang/Throwable
    //   390	457	460	java/lang/Throwable
    //   427	494	497	java/lang/Throwable
    //   464	531	534	java/lang/Throwable
    //   501	568	571	java/lang/Throwable
    //   538	605	608	java/lang/Throwable
    //   575	642	645	java/lang/Throwable
    //   612	679	682	java/lang/Throwable
    //   649	716	719	java/lang/Throwable
    //   686	753	756	java/lang/Throwable
    //   723	790	793	java/lang/Throwable
    //   760	827	830	java/lang/Throwable
    //   797	864	867	java/lang/Throwable
    //   834	901	904	java/lang/Throwable
    //   871	938	941	java/lang/Throwable
    //   908	975	978	java/lang/Throwable
    //   945	1012	1015	java/lang/Throwable
    //   982	1049	1052	java/lang/Throwable
    //   1019	1086	1089	java/lang/Throwable
    //   1056	1123	1126	java/lang/Throwable
    //   1093	1160	1163	java/lang/Throwable
    //   1130	1197	1200	java/lang/Throwable
    //   1167	1234	1237	java/lang/Throwable
    //   1204	1271	1274	java/lang/Throwable
    //   1241	1308	1311	java/lang/Throwable
    //   1278	1341	1344	java/lang/Throwable
    //   5750	5764	5764	java/lang/Throwable
    //   5775	5788	5791	java/lang/Throwable
    //   5780	5803	5806	java/lang/Throwable
    //   5795	5821	5824	java/lang/Throwable
    //   5810	5851	5854	java/lang/Throwable
    //   5917	5944	5947	java/lang/Throwable
    //   5934	5965	5968	java/lang/Throwable
    //   5951	5995	5998	java/lang/Throwable
    //   5972	6006	6006	java/lang/Throwable
    //   6017	6033	6036	java/lang/Throwable
    //   6113	6127	6127	java/lang/Throwable
    //   6138	6151	6154	java/lang/Throwable
    //   6143	6166	6169	java/lang/Throwable
    //   6158	6184	6187	java/lang/Throwable
    //   6173	6214	6217	java/lang/Throwable
    //   6280	6307	6310	java/lang/Throwable
    //   6297	6328	6331	java/lang/Throwable
    //   6314	6358	6361	java/lang/Throwable
    //   6335	6369	6369	java/lang/Throwable
    //   6380	6396	6399	java/lang/Throwable
    //   6403	6493	6496	java/lang/Throwable
    //   6448	6545	6548	java/lang/Throwable
    //   6500	6556	6556	java/lang/Throwable
  }
  
  static {
    // Byte code:
    //   0: bipush #11
    //   2: anewarray java/lang/String
    //   5: astore #5
    //   7: iconst_0
    //   8: istore_3
    //   9: ldc 'T\\b?cbljH9sC_ExTC>%u~;5%O>cq\\\tZ6+b\\t6DjKQ\\t)pXAU\\t29;;d6\\t.M4\\t8 `r'
    //   11: dup
    //   12: astore_2
    //   13: invokevirtual length : ()I
    //   16: istore #4
    //   18: bipush #77
    //   20: istore_1
    //   21: iconst_m1
    //   22: istore_0
    //   23: bipush #124
    //   25: iinc #0, 1
    //   28: aload_2
    //   29: iload_0
    //   30: dup
    //   31: iload_1
    //   32: iadd
    //   33: invokevirtual substring : (II)Ljava/lang/String;
    //   36: iconst_m1
    //   37: goto -> 143
    //   40: aload #5
    //   42: swap
    //   43: iload_3
    //   44: iinc #3, 1
    //   47: swap
    //   48: aastore
    //   49: iload_0
    //   50: iload_1
    //   51: iadd
    //   52: dup
    //   53: istore_0
    //   54: iload #4
    //   56: if_icmpge -> 68
    //   59: aload_2
    //   60: iload_0
    //   61: invokevirtual charAt : (I)C
    //   64: istore_1
    //   65: goto -> 23
    //   68: ldc 'M\\fD%1%\@B$ *#ru$;(K '
    //   70: dup
    //   71: astore_2
    //   72: invokevirtual length : ()I
    //   75: istore #4
    //   77: bipush #32
    //   79: istore_1
    //   80: iconst_m1
    //   81: istore_0
    //   82: bipush #84
    //   84: iinc #0, 1
    //   87: aload_2
    //   88: iload_0
    //   89: dup
    //   90: iload_1
    //   91: iadd
    //   92: invokevirtual substring : (II)Ljava/lang/String;
    //   95: iconst_0
    //   96: goto -> 143
    //   99: aload #5
    //   101: swap
    //   102: iload_3
    //   103: iinc #3, 1
    //   106: swap
    //   107: aastore
    //   108: iload_0
    //   109: iload_1
    //   110: iadd
    //   111: dup
    //   112: istore_0
    //   113: iload #4
    //   115: if_icmpge -> 127
    //   118: aload_2
    //   119: iload_0
    //   120: invokevirtual charAt : (I)C
    //   123: istore_1
    //   124: goto -> 82
    //   127: aload #5
    //   129: putstatic burp/Zg4k.a : [Ljava/lang/String;
    //   132: bipush #11
    //   134: anewarray java/lang/String
    //   137: putstatic burp/Zg4k.b : [Ljava/lang/String;
    //   140: goto -> 300
    //   143: dup_x2
    //   144: pop
    //   145: invokevirtual toCharArray : ()[C
    //   148: dup_x1
    //   149: arraylength
    //   150: dup_x2
    //   151: pop
    //   152: iconst_0
    //   153: istore #6
    //   155: dup2_x1
    //   156: pop2
    //   157: dup_x2
    //   158: iconst_1
    //   159: if_icmpgt -> 259
    //   162: dup2
    //   163: swap
    //   164: iload #6
    //   166: dup2_x1
    //   167: caload
    //   168: swap
    //   169: iload #6
    //   171: bipush #7
    //   173: irem
    //   174: tableswitch default -> 241, 0 -> 212, 1 -> 217, 2 -> 221, 3 -> 226, 4 -> 231, 5 -> 236
    //   212: bipush #7
    //   214: goto -> 243
    //   217: iconst_1
    //   218: goto -> 243
    //   221: bipush #50
    //   223: goto -> 243
    //   226: bipush #100
    //   228: goto -> 243
    //   231: bipush #30
    //   233: goto -> 243
    //   236: bipush #88
    //   238: goto -> 243
    //   241: bipush #115
    //   243: ixor
    //   244: ixor
    //   245: i2c
    //   246: castore
    //   247: iinc #6, 1
    //   250: dup
    //   251: ifne -> 259
    //   254: dup2
    //   255: dup_x1
    //   256: goto -> 166
    //   259: dup2_x1
    //   260: pop2
    //   261: dup_x2
    //   262: iload #6
    //   264: if_icmpgt -> 162
    //   267: pop
    //   268: new java/lang/String
    //   271: dup_x1
    //   272: swap
    //   273: invokespecial <init> : ([C)V
    //   276: invokevirtual intern : ()Ljava/lang/String;
    //   279: swap
    //   280: pop
    //   281: swap
    //   282: tableswitch default -> 40, 0 -> 99
    //   300: sipush #26216
    //   303: sipush #-31704
    //   306: invokestatic a : (II)Ljava/lang/String;
    //   309: putstatic burp/Zg4k.ZB : Ljava/lang/String;
    //   312: new java/math/BigInteger
    //   315: dup
    //   316: iconst_1
    //   317: bipush #32
    //   319: newarray byte
    //   321: dup
    //   322: iconst_0
    //   323: bipush #83
    //   325: bastore
    //   326: dup
    //   327: iconst_1
    //   328: bipush #47
    //   330: bastore
    //   331: dup
    //   332: iconst_2
    //   333: bipush #6
    //   335: bastore
    //   336: dup
    //   337: iconst_3
    //   338: bipush #76
    //   340: bastore
    //   341: dup
    //   342: iconst_4
    //   343: bipush #82
    //   345: bastore
    //   346: dup
    //   347: iconst_5
    //   348: bipush #-2
    //   350: bastore
    //   351: dup
    //   352: bipush #6
    //   354: bipush #-47
    //   356: bastore
    //   357: dup
    //   358: bipush #7
    //   360: bipush #22
    //   362: bastore
    //   363: dup
    //   364: bipush #8
    //   366: bipush #-124
    //   368: bastore
    //   369: dup
    //   370: bipush #9
    //   372: bipush #101
    //   374: bastore
    //   375: dup
    //   376: bipush #10
    //   378: bipush #-84
    //   380: bastore
    //   381: dup
    //   382: bipush #11
    //   384: bipush #23
    //   386: bastore
    //   387: dup
    //   388: bipush #12
    //   390: bipush #111
    //   392: bastore
    //   393: dup
    //   394: bipush #13
    //   396: bipush #-127
    //   398: bastore
    //   399: dup
    //   400: bipush #14
    //   402: bipush #39
    //   404: bastore
    //   405: dup
    //   406: bipush #15
    //   408: bipush #-21
    //   410: bastore
    //   411: dup
    //   412: bipush #16
    //   414: bipush #-16
    //   416: bastore
    //   417: dup
    //   418: bipush #17
    //   420: bipush #-51
    //   422: bastore
    //   423: dup
    //   424: bipush #18
    //   426: bipush #-34
    //   428: bastore
    //   429: dup
    //   430: bipush #19
    //   432: bipush #-88
    //   434: bastore
    //   435: dup
    //   436: bipush #20
    //   438: bipush #-108
    //   440: bastore
    //   441: dup
    //   442: bipush #21
    //   444: bipush #9
    //   446: bastore
    //   447: dup
    //   448: bipush #22
    //   450: bipush #-64
    //   452: bastore
    //   453: dup
    //   454: bipush #23
    //   456: bipush #-98
    //   458: bastore
    //   459: dup
    //   460: bipush #24
    //   462: iconst_m1
    //   463: bastore
    //   464: dup
    //   465: bipush #25
    //   467: bipush #-35
    //   469: bastore
    //   470: dup
    //   471: bipush #26
    //   473: iconst_3
    //   474: bastore
    //   475: dup
    //   476: bipush #27
    //   478: bipush #101
    //   480: bastore
    //   481: dup
    //   482: bipush #28
    //   484: bipush #-98
    //   486: bastore
    //   487: dup
    //   488: bipush #29
    //   490: bipush #-87
    //   492: bastore
    //   493: dup
    //   494: bipush #30
    //   496: bipush #13
    //   498: bastore
    //   499: dup
    //   500: bipush #31
    //   502: bipush #-31
    //   504: bastore
    //   505: invokespecial <init> : (I[B)V
    //   508: putstatic burp/Zg4k.ZE : Ljava/lang/Object;
    //   511: return
  }
  
  private static Throwable a(Throwable paramThrowable) {
    return paramThrowable;
  }
  
  private static String a(int paramInt1, int paramInt2) {
    int i = (paramInt1 ^ 0x6662) & 0xFFFF;
    if (b[i] == null) {
      char[] arrayOfChar = a[i].toCharArray();
      switch (arrayOfChar[0] & 0xFF) {
        case 0:
        
        case 1:
        
        case 2:
        
        case 3:
        
        case 4:
        
        case 5:
        
        case 6:
        
        case 7:
        
        case 8:
        
        case 9:
        
        case 10:
        
        case 11:
        
        case 12:
        
        case 13:
        
        case 14:
        
        case 15:
        
        case 16:
        
        case 17:
        
        case 18:
        
        case 19:
        
        case 20:
        
        case 21:
        
        case 22:
        
        case 23:
        
        case 24:
        
        case 25:
        
        case 26:
        
        case 27:
        
        case 28:
        
        case 29:
        
        case 30:
        
        case 31:
        
        case 32:
        
        case 33:
        
        case 34:
        
        case 35:
        
        case 36:
        
        case 37:
        
        case 38:
        
        case 39:
        
        case 40:
        
        case 41:
        
        case 42:
        
        case 43:
        
        case 44:
        
        case 45:
        
        case 46:
        
        case 47:
        
        case 48:
        
        case 49:
        
        case 50:
        
        case 51:
        
        case 52:
        
        case 53:
        
        case 54:
        
        case 55:
        
        case 56:
        
        case 57:
        
        case 58:
        
        case 59:
        
        case 60:
        
        case 61:
        
        case 62:
        
        case 63:
        
        case 64:
        
        case 65:
        
        case 66:
        
        case 67:
        
        case 68:
        
        case 69:
        
        case 70:
        
        case 71:
        
        case 72:
        
        case 73:
        
        case 74:
        
        case 75:
        
        case 76:
        
        case 77:
        
        case 78:
        
        case 79:
        
        case 80:
        
        case 81:
        
        case 82:
        
        case 83:
        
        case 84:
        
        case 85:
        
        case 86:
        
        case 87:
        
        case 88:
        
        case 89:
        
        case 90:
        
        case 91:
        
        case 92:
        
        case 93:
        
        case 94:
        
        case 95:
        
        case 96:
        
        case 97:
        
        case 98:
        
        case 99:
        
        case 100:
        
        case 101:
        
        case 102:
        
        case 103:
        
        case 104:
        
        case 105:
        
        case 106:
        
        case 107:
        
        case 108:
        
        case 109:
        
        case 110:
        
        case 111:
        
        case 112:
        
        case 113:
        
        case 114:
        
        case 115:
        
        case 116:
        
        case 117:
        
        case 118:
        
        case 119:
        
        case 120:
        
        case 121:
        
        case 122:
        
        case 123:
        
        case 124:
        
        case 125:
        
        case 126:
        
        case 127:
        
        case 128:
        
        case 129:
        
        case 130:
        
        case 131:
        
        case 132:
        
        case 133:
        
        case 134:
        
        case 135:
        
        case 136:
        
        case 137:
        
        case 138:
        
        case 139:
        
        case 140:
        
        case 141:
        
        case 142:
        
        case 143:
        
        case 144:
        
        case 145:
        
        case 146:
        
        case 147:
        
        case 148:
        
        case 149:
        
        case 150:
        
        case 151:
        
        case 152:
        
        case 153:
        
        case 154:
        
        case 155:
        
        case 156:
        
        case 157:
        
        case 158:
        
        case 159:
        
        case 160:
        
        case 161:
        
        case 162:
        
        case 163:
        
        case 164:
        
        case 165:
        
        case 166:
        
        case 167:
        
        case 168:
        
        case 169:
        
        case 170:
        
        case 171:
        
        case 172:
        
        case 173:
        
        case 174:
        
        case 175:
        
        case 176:
        
        case 177:
        
        case 178:
        
        case 179:
        
        case 180:
        
        case 181:
        
        case 182:
        
        case 183:
        
        case 184:
        
        case 185:
        
        case 186:
        
        case 187:
        
        case 188:
        
        case 189:
        
        case 190:
        
        case 191:
        
        case 192:
        
        case 193:
        
        case 194:
        
        case 195:
        
        case 196:
        
        case 197:
        
        case 198:
        
        case 199:
        
        case 200:
        
        case 201:
        
        case 202:
        
        case 203:
        
        case 204:
        
        case 205:
        
        case 206:
        
        case 207:
        
        case 208:
        
        case 209:
        
        case 210:
        
        case 211:
        
        case 212:
        
        case 213:
        
        case 214:
        
        case 215:
        
        case 216:
        
        case 217:
        
        case 218:
        
        case 219:
        
        case 220:
        
        case 221:
        
        case 222:
        
        case 223:
        
        case 224:
        
        case 225:
        
        case 226:
        
        case 227:
        
        case 228:
        
        case 229:
        
        case 230:
        
        case 231:
        
        case 232:
        
        case 233:
        
        case 234:
        
        case 235:
        
        case 236:
        
        case 237:
        
        case 238:
        
        case 239:
        
        case 240:
        
        case 241:
        
        case 242:
        
        case 243:
        
        case 244:
        
        case 245:
        
        case 246:
        
        case 247:
        
        case 248:
        
        case 249:
        
        case 250:
        
        case 251:
        
        case 252:
        
        case 253:
        
        case 254:
        
        default:
          break;
      } 
      char c = '';
      int j = (paramInt2 & 0xFF) - c;
      if (j < 0)
        j += 256; 
      int k = ((paramInt2 & 0xFFFF) >>> 8) - c;
      if (k < 0)
        k += 256; 
      for (byte b = 0; b < arrayOfChar.length; b++) {
        int m = b % 2;
        if (m == 0) {
          arrayOfChar[b] = (char)(arrayOfChar[b] ^ j);
          j = ((j >>> 3 | j << 5) ^ arrayOfChar[b]) & 0xFF;
        } else {
          arrayOfChar[b] = (char)(arrayOfChar[b] ^ k);
          k = ((k >>> 3 | k << 5) ^ arrayOfChar[b]) & 0xFF;
        } 
      } 
      b[i] = (new String(arrayOfChar)).intern();
    } 
    return b[i];
  }
}


/* Location:              C:\Program Files\BurpSuitePro\burpsuite_pro.jar!\burp\Zg4k.class
 * Java compiler version: 21 (65.0)
 * JD-Core Version:       1.1.3
 */