package burp;

import java.awt.Component;
import java.awt.event.ActionEvent;
import java.util.concurrent.atomic.AtomicReference;
import net.portswigger.Zah;
import net.portswigger.Zk_;
import net.portswigger.Zm2;

public class Zg5d {
  private final Zkbz ZN;
  
  private final Zerg ZD;
  
  private final Zr_4 ZM;
  
  private final Ztwv Zq;
  
  private final Zeew Zx;
  
  private static int[] ZC;
  
  private static final String[] a;
  
  private static final String[] b;
  
  public Zg5d(Zerg paramZerg, Zr_4 paramZr_4, Ztwv paramZtwv, Zeew paramZeew) {
    this.ZD = paramZerg;
    this.ZM = paramZr_4;
    this.Zq = paramZtwv;
    this.Zx = paramZeew;
    this.ZN = new Zkbz();
  }
  
  public Component ZR(Zmgv paramZmgv, Zlbp paramZlbp, boolean paramBoolean, Zgu3 paramZgu3, Zey9 paramZey9) {
    // Byte code:
    //   0: invokestatic Zn : ()[I
    //   3: astore #6
    //   5: aload_1
    //   6: invokeinterface ZoO : ()Lburp/Zstu;
    //   11: astore #7
    //   13: aload #7
    //   15: ifnull -> 26
    //   18: aload #7
    //   20: invokestatic ZY : (Lburp/Zstu;)Ljava/util/Optional;
    //   23: goto -> 29
    //   26: invokestatic empty : ()Ljava/util/Optional;
    //   29: astore #8
    //   31: new burp/Zztv
    //   34: dup
    //   35: sipush #18880
    //   38: sipush #26992
    //   41: invokestatic a : (II)Ljava/lang/String;
    //   44: invokespecial <init> : (Ljava/lang/String;)V
    //   47: astore #9
    //   49: aload #9
    //   51: aload_0
    //   52: sipush #18882
    //   55: sipush #23908
    //   58: invokestatic a : (II)Ljava/lang/String;
    //   61: sipush #18887
    //   64: sipush #-27097
    //   67: invokestatic a : (II)Ljava/lang/String;
    //   70: aload_2
    //   71: iload_3
    //   72: aload #4
    //   74: aload #5
    //   76: getstatic burp/Zrrh.SUITE_MESSAGE_EDITOR_GRAPHQL_SET_INTROSPECTION_QUERY : Lburp/Zrrh;
    //   79: invokevirtual ZY : (Ljava/lang/String;Ljava/lang/String;Lburp/Zlbp;ZLburp/Zgu3;Lburp/Zey9;Lburp/Zrrh;)Lburp/Zepe;
    //   82: invokevirtual add : (Ljavax/swing/JMenuItem;)Ljavax/swing/JMenuItem;
    //   85: pop
    //   86: aload #9
    //   88: aload_0
    //   89: sipush #18884
    //   92: sipush #24524
    //   95: invokestatic a : (II)Ljava/lang/String;
    //   98: sipush #18885
    //   101: sipush #-30960
    //   104: invokestatic a : (II)Ljava/lang/String;
    //   107: aload_2
    //   108: iload_3
    //   109: aload #4
    //   111: aload #5
    //   113: getstatic burp/Zrrh.SUITE_MESSAGE_EDITOR_GRAPHQL_SET_LEGACY_INTROSPECTION_QUERY : Lburp/Zrrh;
    //   116: invokevirtual ZY : (Ljava/lang/String;Ljava/lang/String;Lburp/Zlbp;ZLburp/Zgu3;Lburp/Zey9;Lburp/Zrrh;)Lburp/Zepe;
    //   119: invokevirtual add : (Ljavax/swing/JMenuItem;)Ljavax/swing/JMenuItem;
    //   122: pop
    //   123: aload #9
    //   125: new javax/swing/JSeparator
    //   128: dup
    //   129: invokespecial <init> : ()V
    //   132: invokevirtual add : (Ljava/awt/Component;)Ljava/awt/Component;
    //   135: pop
    //   136: new burp/Zepe
    //   139: dup
    //   140: sipush #18886
    //   143: sipush #-17334
    //   146: invokestatic a : (II)Ljava/lang/String;
    //   149: invokespecial <init> : (Ljava/lang/String;)V
    //   152: astore #10
    //   154: aload #10
    //   156: aload #8
    //   158: invokevirtual isPresent : ()Z
    //   161: invokevirtual setEnabled : (Z)V
    //   164: aload #8
    //   166: aload_0
    //   167: aload #10
    //   169: aload_1
    //   170: aload #5
    //   172: <illegal opcode> accept : (Lburp/Zg5d;Lburp/Zepe;Lburp/Zmgv;Lburp/Zey9;)Ljava/util/function/Consumer;
    //   177: invokevirtual ifPresent : (Ljava/util/function/Consumer;)V
    //   180: aload #9
    //   182: aload #10
    //   184: invokevirtual add : (Ljavax/swing/JMenuItem;)Ljavax/swing/JMenuItem;
    //   187: pop
    //   188: aload #9
    //   190: invokestatic Zwu : ()[Lburp/Zbqc;
    //   193: ifnonnull -> 202
    //   196: iconst_5
    //   197: newarray int
    //   199: invokestatic ZG : ([I)V
    //   202: areturn
  }
  
  private Zepe ZY(String paramString1, String paramString2, Zlbp paramZlbp, boolean paramBoolean, Zgu3 paramZgu3, Zey9 paramZey9, Zrrh paramZrrh) {
    // Byte code:
    //   0: aload #5
    //   2: getstatic burp/Zgu3.HTTP_REQUEST : Lburp/Zgu3;
    //   5: if_acmpne -> 17
    //   8: iload #4
    //   10: ifeq -> 17
    //   13: iconst_1
    //   14: goto -> 18
    //   17: iconst_0
    //   18: istore #8
    //   20: new burp/Zepe
    //   23: dup
    //   24: aload_1
    //   25: aload #5
    //   27: getstatic burp/Zgu3.HTTP_REQUEST : Lburp/Zgu3;
    //   30: if_acmpeq -> 45
    //   33: sipush #18881
    //   36: sipush #-24129
    //   39: invokestatic a : (II)Ljava/lang/String;
    //   42: goto -> 47
    //   45: ldc ''
    //   47: <illegal opcode> makeConcatWithConstants : (Ljava/lang/String;Ljava/lang/String;)Ljava/lang/String;
    //   52: invokespecial <init> : (Ljava/lang/String;)V
    //   55: astore #9
    //   57: aload #9
    //   59: iload #8
    //   61: invokevirtual setEnabled : (Z)V
    //   64: iload #8
    //   66: ifeq -> 86
    //   69: aload #9
    //   71: aload_0
    //   72: aload #7
    //   74: aload_3
    //   75: aload_2
    //   76: aload #6
    //   78: <illegal opcode> actionPerformed : (Lburp/Zg5d;Lburp/Zrrh;Lburp/Zlbp;Ljava/lang/String;Lburp/Zey9;)Ljava/awt/event/ActionListener;
    //   83: invokevirtual addActionListener : (Ljava/awt/event/ActionListener;)V
    //   86: aload #9
    //   88: areturn
  }
  
  private void Zo(Zlbp paramZlbp, String paramString, Zey9 paramZey9) {
    AtomicReference<Zsmh> atomicReference = new AtomicReference();
    paramZlbp.Zh(new Zgf_(this, atomicReference));
    Zsmh zsmh = atomicReference.get();
    Zefx zefx = this.ZN.Ze(paramZey9.Zy(zsmh), paramString, "", true);
    paramZlbp.Zj(zefx.Zb().ZD());
  }
  
  private void ZH(Zmzk paramZmzk, Zey9 paramZey9, Zk_ paramZk_, Zsmh paramZsmh) {
    // Byte code:
    //   0: getstatic burp/Zrrh.SUITE_MESSAGE_EDITOR_GRAPHQL_ADD_INTROSPECTION_ITEMS_TO_SITE_MAP : Lburp/Zrrh;
    //   3: invokestatic ZC : (Lnet/portswigger/Zip;)V
    //   6: aload_3
    //   7: invokevirtual Zq : ()Ljava/util/Optional;
    //   10: aconst_null
    //   11: invokevirtual orElse : (Ljava/lang/Object;)Ljava/lang/Object;
    //   14: checkcast burp/Zsvv
    //   17: astore #5
    //   19: aload #5
    //   21: ifnonnull -> 58
    //   24: getstatic burp/Zze0.SUITE_MESSAGE_EDITOR_GRAPHQL_INTROSPECTION_PARSE_FAILED : Lburp/Zze0;
    //   27: invokestatic Zo : (Lnet/portswigger/Zfp;)V
    //   30: getstatic burp/Zmgc.GRAPHQL_INTROSPECTION_PARSE_FAILED : Lburp/Zmgc;
    //   33: aload_0
    //   34: getfield ZD : Lburp/Zerg;
    //   37: aload_0
    //   38: getfield Zx : Lburp/Zeew;
    //   41: invokevirtual ZI : (Lburp/Zeew;)Lburp/Zx8n;
    //   44: invokeinterface ZY4 : ()Lburp/Zskh;
    //   49: iconst_0
    //   50: anewarray java/lang/Object
    //   53: invokevirtual ZV : (Lburp/Zskh;[Ljava/lang/Object;)Ljava/lang/String;
    //   56: pop
    //   57: return
    //   58: aload_0
    //   59: getfield Zq : Lburp/Ztwv;
    //   62: aload_0
    //   63: aload #5
    //   65: aload_1
    //   66: aload_2
    //   67: aload #4
    //   69: <illegal opcode> run : (Lburp/Zg5d;Lburp/Zsvv;Lburp/Zmzk;Lburp/Zey9;Lburp/Zsmh;)Ljava/lang/Runnable;
    //   74: invokeinterface Zx : (Ljava/lang/Runnable;)Ljava/util/concurrent/Future;
    //   79: pop
    //   80: return
  }
  
  private void Zr(Zmzk paramZmzk, Zey9 paramZey9, Zsvv paramZsvv, Zggo paramZggo, Zsmh paramZsmh) {
    try {
      this.ZD.ZA().Zj(paramZmzk, Zp(paramZsvv, paramZey9, paramZggo, this.ZM, paramZsmh), null, "", null);
    } catch (Exception exception) {
      Zah.Zl(exception, Zk_.UNEXPECTED);
    } 
  }
  
  private Zstu Zp(Zsvv paramZsvv, Zey9 paramZey9, Zggo paramZggo, Zr_4 paramZr_4, Zsmh paramZsmh) {
    Zsda zsda = Zsda.ZF();
    Zzx2 zzx2 = Zxxq.ZZ(paramZsvv, paramZggo, zsda, new Zr90());
    Zefx zefx = paramZey9.Zy(paramZsmh);
    Zrdu zrdu = zefx.ZZ(Zg5d::lambda$buildRequestFor$5).stream().map(Zg5d::lambda$buildRequestFor$6).findFirst().orElse(Zrdu.URL_PARAM);
    zefx = zefx.ZN(new Zrtz(zzx2.Zj(), zefx.Zr(), zrdu, zsda.Zv()));
    return paramZr_4.ZZ(zefx.Zt().ZD());
  }
  
  private static Zrdu lambda$buildRequestFor$6(Zlou paramZlou) {
    return paramZlou.Zx;
  }
  
  private static boolean lambda$buildRequestFor$5(Zlou paramZlou) {
    return paramZlou.ZA.equals(a(18883, -29886));
  }
  
  private void lambda$addIntrospectionTypesToSiteMap$4(Zsvv paramZsvv, Zmzk paramZmzk, Zey9 paramZey9, Zsmh paramZsmh) {
    // Byte code:
    //   0: aload_1
    //   1: iconst_2
    //   2: anewarray burp/Zmfl
    //   5: dup
    //   6: iconst_0
    //   7: getstatic burp/Zmfl.QUERY : Lburp/Zmfl;
    //   10: aastore
    //   11: dup
    //   12: iconst_1
    //   13: getstatic burp/Zmfl.MUTATION : Lburp/Zmfl;
    //   16: aastore
    //   17: invokevirtual ZO : ([Lburp/Zmfl;)Ljava/util/List;
    //   20: aload_0
    //   21: aload_2
    //   22: aload_3
    //   23: aload_1
    //   24: aload #4
    //   26: <illegal opcode> accept : (Lburp/Zg5d;Lburp/Zmzk;Lburp/Zey9;Lburp/Zsvv;Lburp/Zsmh;)Ljava/util/function/Consumer;
    //   31: invokeinterface forEach : (Ljava/util/function/Consumer;)V
    //   36: return
  }
  
  private void lambda$addIntrospectionTypesToSiteMap$3(Zmzk paramZmzk, Zey9 paramZey9, Zsvv paramZsvv, Zsmh paramZsmh, Zggo paramZggo) {
    Zr(paramZmzk, paramZey9, paramZsvv, paramZggo, paramZsmh);
  }
  
  private void lambda$createIntrospectionMenuItem$2(Zrrh paramZrrh, Zlbp paramZlbp, String paramString, Zey9 paramZey9, ActionEvent paramActionEvent) {
    Zm2.ZC(paramZrrh);
    Zo(paramZlbp, paramString, paramZey9);
  }
  
  private void lambda$getGraphQLMenu$1(Zepe paramZepe, Zmgv paramZmgv, Zey9 paramZey9, Zk_ paramZk_) {
    // Byte code:
    //   0: aload_1
    //   1: aload_0
    //   2: aload_2
    //   3: aload_3
    //   4: aload #4
    //   6: <illegal opcode> actionPerformed : (Lburp/Zg5d;Lburp/Zmgv;Lburp/Zey9;Lburp/Zk_;)Ljava/awt/event/ActionListener;
    //   11: invokevirtual addActionListener : (Ljava/awt/event/ActionListener;)V
    //   14: return
  }
  
  private void lambda$getGraphQLMenu$0(Zmgv paramZmgv, Zey9 paramZey9, Zk_ paramZk_, ActionEvent paramActionEvent) {
    ZH(paramZmgv.Zod(), paramZey9, paramZk_, paramZmgv.Zo3().ZP(paramZmgv.Zod(), paramZey9));
  }
  
  public static void ZG(int[] paramArrayOfint) {
    ZC = paramArrayOfint;
  }
  
  public static int[] Zn() {
    return ZC;
  }
  
  static {
    // Byte code:
    //   0: bipush #8
    //   2: anewarray java/lang/String
    //   5: astore #5
    //   7: aconst_null
    //   8: iconst_0
    //   9: istore_3
    //   10: invokestatic ZG : ([I)V
    //   13: ldc 'Â¶Ã„BÂ¶Â‚\\bÃŠÃŒÃ¬Â…l`Â«Ã®zr#Ã·ÂµrÃ†cÂ‘Â•ÃµWÂ˜ÃP3k"ÃƒÂ¢lEÃ¥ÃÃ…Â´Ã¥Â©Ã‡Ã¥cÔÃ’ZÃ³Â‘ÂÃ‘Â¿Â¹uÂ¥Â¿Â¹=Ã£Ã£Â‰ÂšEÃŒ8Ã‰$VÃ·xÃÃ²Â¯VÃÃ²Ã¢|Ã‡TFCTÂ•%tÃ¾uicÂÂ®y"`ÂÃªÂ„Ã½Â½SfÃ¬n`Z{Â”Â”_o|ÂšÂ›Ã©ÃœÃ’Ã¡BfÂ³zÂ»Â²Ã |lÂ‚TÂw$Â™ÃÃˆ ÂIÃ”YÃ°Â³UÃªÂ£Ã¨Ã¿ÂhÂ†W+\Â¨vÂ‚Â¹\\nÂ‚Â¶WÂ³zCÂ´Ã[&Ã¼Â³Â˜Â§SVÂ—]Â…Ã±KÂˆÃ·Â¹Ã¬Q\\rÃ¾$ $tÂ­Ã¦Ã’Â—Â‚Â«Â‰Â¸ÃŒÂ€Ã®J&Ã¿\\tÂ¶yÃ#Ã€tÃ Ã¹FÃ„~U2`Â Ã·Â¢3Â©Ã±BdÃ§cÂ¿Â¦iN$Â¡yÂ£X.Ã°sÃ“Â“Ã­Ã©UJÃ.Â¨Ã¾GÃƒÃµ8Â¦]/(^Â’Ã¡"1ÂÃ«NÃªÂ¾,!Â’\\bÂ±Â˜\\bÃ»3sÃÂ¥ÃƒyÂ…Â¸Ã‡MÂ­"Ãº_nqÃ>!Â°~Ã­ypÃ’Â™-i^ÃŸCÂ™Q/VÃ€t;uÂº:Ã¡ÂŠÃÃ†OÂ‚Ã¦Â!*Â™ÂŸÃº3zÃ¤Â¸^Ã$WÃ³Â°Â…Â }Ã©8Â´Ã´#Ã„QcÂœÂ¡nÂ£Âº.Â¬sXÂ“ÂœÃ‰UÂÂ¦kÃ‚Ã4%Ã”Â­1BÂ©^Ã¬`W{Â°Â”Â _Ã©|Ã¿Ã¯&09Â‘PhÃ±Ã¦Ã™Ã—ÃƒÂ"Ã˜Â„Â£Ã›*qjÃ‡ZÃ…Â…eÃ³OUÂ§ÂŒa/Ã€ÂŠÂ«`Ãº)@ZoÂ Ã±tÃµWsÂ²Ãœ`DÂ‰pÂ¦yÃ€Â•dSÂ¿Ã¯XÃ¹H]0Â·>EEvÃ„wc3Ã¸ÃÃ’Â¡Â„ÂˆÃ¦CÃ¼aÃ¼GÃ¶ÂŸÂ‹ÃŒÂ¾|3bÃ[4Ã†Â±cÂ©Ã¿Ã‚HÃÂ•Ã§ ks7Â•PÂ¹9ÂŠQdq.Ã“R\\rZÂ´Ã‚.P;Â™ÂºÃQÃ¢Ã¼ FÃ‰5Â®Ã‘ÂÃÂ§(Âº=Â†!rÃ™Ã™LarÂšÂƒÂ®Ã§Â¢Â¨Â¡b_0hÂ£YÃ¹Â(Â’Â²Ã†Ã Ã¡5KÃ¼ÃÃ‚Ã²Ã)Â£ÃÃ‚Ã±\\fÃ‡Ã¬YÂÃŒ~aÂ¸vÃ¬xPÃ²Â)Ã©ÃÂ…ÂŒ/pÃ‚<= Ã·Ã¹Ã‹Ã„ÃU=Ã·Â /TGwÂ™ÂµÃˆ ÂÂ® ÃÃ¦ÂŸueÃ¿DÂ¤HÂ¨sÂ·Â“av[xÃ¢Â·W>Â¯gÃ¯^ Ã]7Â’-!~Ã„4EÂcLÃ­Â¼F!LÂ—.WÂ‘Âˆ3Â³XÂ—Âk/ÂwÂ…Â™ÃªÃˆÃ«Ã”ÂgÂœÂ–1ÃÃ•Â§RZÂ}Â©Â¿ÃÂ€Ã£Â¶Ã Ã­Â*Â¦VaH#xX!ÂœÃ³]^4vÃÃ»ÃƒÃ‰ÂµÃ„!Ã¯p\\bywDÃ“Ãˆ\\bJÃCÃŠÂ.HcÂ•W }sÂ°Ã›|wÂ½mÃ‘Ã– Ã²Â‰Âe@)?RÂ²uÂ™KÃ—Â„Â›ÃˆÂ¯Â´Ã‚-Ã‡Ã“2Ã»Ã±Ã·Â¢Ã†Ã·Â¯Â¤"\\fÃ·WCÂœ]Ãˆ\\tÃ¤Â¶Ã«ÂŒÂ†'Y\#RUÃ“TÂƒdvÃ•Ã†ÃšÂ¦5Â£Ã¼Â`oÃµq%ÃŠI8Â«Â¼Â˜\\n$Â˜IÃ®Â¾ÂªÂÂ®C]\\tÂƒIq~Ã§"ÂÃ½Â±'Â°Ã¬Ã½Â¤Â¡Â¹Â‚Â§Â‡Â•Ã¨Ã¨Ã¦Ã»^Â‹Â©v{_&Ã–Â„Â‰Â†Ã¥7qYÂ™ÃÂ…Ã—McÃÃ·ZÃ,:Ã½gÂƒÃ”Ã’gÃÃ†Ã‰ÂˆÃŠ ÂÂª\\tPÃ¾VÂ¸ÂÃ´ÃÃºz+GÃ¦ÂÂ§Â˜Â›Â BÂ›mqÃ…Ã·Â—g\\f)ÂÂ¯ÂœÃ·Â²Â£<Ã 1Ã‘Â•Ã¬Ã«Ã”&89Â\\rÃ¦Â¹zÂ¨ÂV[Â Ã³URÃ·QÃ­iwÃ /l.T\\bwÂ–Â™ÂˆÃˆÂ©Ãš\\twÃ€Ã”]Ã¿,Â¯|Ã€tÂ®Â¢XÃ°3Â–Ã©ÂBÂMbÂ Ã§Ã£s7ÂÃ·gTTÂUÂ­ÃÃ±Â©Ã£6-G@Â½Ã¥-'Ã´7Â•=BkÂ¤CepÃ¶Ãµ#:ÃµÃ´d\\bÂ·ÃEÂ—Â—Â©PÃˆÂ!Â¯\\rÂ”Ã†XÃŠÃ’Â’ÂƒÂŸÂdÃ†Ã–#'Ã uÂ¯tcÃšÂÂ¦FÂ£Â’ÃÂ¥?eÂ¾6Ã¢=ÃªjÂ ÃšcNÃ‘Â­ Ã¢Â¤qxÃ¿Â‰]ÃŒ<Ã®Ã&\\r\\t\Â¶Ã¼Ã‡-"LÃ’Âš Â¨Â¶Ã˜+ÂŒÃ‹Â¹ÃÂ´EÃ‹Ã³Ã­hdÃ€qÂYÂ«ÃÃƒÃ—Â…mÂˆÂ±8W` ÃÃ…HsÃÂ£Ã§Ã£Â‹&ÂŠrÂœÂ³ÃšÃ›Ã­Ã½\\tDry6Ã¢;Ã‹#Ã¹Ã’Ã²Â§Ã‰ÂƒcÂ‹ÃšÃ²Ã§Â§Ã´Ã¢GÂ‘Â¥Ã•Ã®AkÃ¥Â+8\\n{ÂŒÂ’%Âš_Â¸\\fyÃ´u82a ÃŠKÂ…2v7*Ã¡Ã°ÂŠB&Ã¬Ã‚Â›ÂšÂ TÃœÃ‘;Âˆ.Â“Ã–Ã¤IÂt'M'
    //   15: dup
    //   16: astore_2
    //   17: invokevirtual length : ()I
    //   20: istore #4
    //   22: iconst_5
    //   23: istore_1
    //   24: iconst_m1
    //   25: istore_0
    //   26: bipush #59
    //   28: iinc #0, 1
    //   31: aload_2
    //   32: iload_0
    //   33: dup
    //   34: iload_1
    //   35: iadd
    //   36: invokevirtual substring : (II)Ljava/lang/String;
    //   39: iconst_m1
    //   40: goto -> 147
    //   43: aload #5
    //   45: swap
    //   46: iload_3
    //   47: iinc #3, 1
    //   50: swap
    //   51: aastore
    //   52: iload_0
    //   53: iload_1
    //   54: iadd
    //   55: dup
    //   56: istore_0
    //   57: iload #4
    //   59: if_icmpge -> 71
    //   62: aload_2
    //   63: iload_0
    //   64: invokevirtual charAt : (I)C
    //   67: istore_1
    //   68: goto -> 26
    //   71: ldc 'Ã™Â™R)dÃ¡ÂƒÃ²ÂMÃ»Â½Ã»Â‚YÃ¤Ã‡8Ã¯Â—]pÂºH54Ã±NÃ›1ÃZÂˆ\\n|HÃ“4(Ã‘Â²Â mbÂ  ÂÃµ>Â¤Ã¡\ÂÂ§Â Â²vkÂ™ÃšÂ©`CUw:Ã™Ã»ÂŒÃ¹IÂ¥Ã‚OeÂ¾FgÃµÂ­ÂƒÃ¢Ã‡Ã†ÃƒÃ£ Ã±Ã­ÃŠÂ¸Â†Ã´-eNÃ°Ã´LÃ‰>Â£Ã¼Â’}:vp\\tÂ¸Â¹Ã¢\\f*ÂŒxÃ†Â¸cÂ¢QÂÃºÂˆ)HAÃÂ¨Â‰Ãƒ%_Â©Ã“Â‚Ã kj`p[Â¹Ã±\\fFÂ‚4Â®Â«Â©Ã½Ã².Ã‰Â¥Ã¾ÃƒÂ‹|Ã¼Ã˜(ÂclÂ—ÃŸÂ¥L.Â²Â³[uÃˆyÃ­@\\bzy8v[Ã³9)ÂÂ¿)Â(\\rRÃÂ·-1Â´Â¿ÃŒÂ¢6YÃ»|Ãˆ"Ã”IÃ£;TSÃš~Ã†Â‡Ã¾DhyoÂºÃµÃÂ…ÃÂ½Ã„Ã /Ã‡ÂŒÂ Ã—Â†ÃMSÃ½Â²Â¾`Âº7!Ã«*Â”ÃŸÂ©Âƒ6ÂŒ7Â§hu'\\fG\\nÃ²Â¯Ã…Â—Â…Â¥.Ã›Â³vKÂ™ÃÃ´ÃŠ;Ã¾0hÂœ6Ã¥Ã‹Â.Â‡Â…Â½jMÂ²Â”MuÂŠÂ;Âª\#Â†YÂ‡ÂœjÂ¨;W}Ã ÃxÂ‰Ã¨Â¦Ã³Ã:Â1Â¼Ã€Ã”Â‚Â¡&9Ã¹?Ã†Â½-.Â„Q(QÃ°h/0Â²Â±Â‘'Â²Â†kÂ‡Â‡@`;ÃsÃ‘Ã¿ÃcÃ¨SÂ¥ÂŸqOÂqBÂ·p]Ã‹Âƒ*#Ã”%Ã/Ã„bmwÃ›Â¨.rÃ²Â¹G:Ã•^LÂ›ÂÃ‹3+1Ã’Ã¸$Ã¶'ÂˆÃ‘Ã®Â”ÃµuÂc;Ã¶\Ã®Ã+Â‚{\ÂÂXÂ¯Â—<Ã©Ã£eÃ¹DÂ—Ie ÂÂ£ÂµÂˆKAÂ¢Â’ÂÃ¢E.Â•Â’ÃˆÂ›!?Ã“ÂœÃ¤4ÃªÂ‹`&Â»^\\bÃ¸Â“ÂŒNDÂ‡lÃ“VJ?rÂ‘C?V<Â£ÃŸ2isÂ°Ã„BÃ®EÃ Ã¿Â«eNÃšÃ„fÃuc3Â›ÂœÂ¶Â­Ã“z0Ã‚Ã®Ã¢Ã†Â›Â®~Ã¨Â˜Ã·Â£3mkÂ:Â¥ÃÂÂ™Â¥Â€Ã”Ã½Â¶Â®ÂÂ·/Â¡RÂ®qÂ£#I3ÂÃ²Ã¦Ã©jÂ–Â°RÂ¤Ã™Â˜Ã±Â Â£ZO=Ã¤ÂšÂ–ÃÂ¾ÂÂ¡Â¼\\tÃ€Â–Â‚Â uÃ¯LÃµ\\fÃ[Â©zÃ¸?IÂ³_{Ã–8mÂÃ’Â€Ã‹Â’1Â¾Â“TÃ®Â™^F,MÃ•Ã“ÂªÂ¹Ã\\fÃ’Â¦Â‘Ã¬Â…Ã‚Ã˜eÃ´ÃµÂ°Â³Ã‚,Ã¼.0\\t,ÃÃ’lÃ€Â¶`Ã•Ã°K(Ã§Ã¬Â„2Â€Ã\\nWÃšÂˆfF&x\\t,Ã¿Â›Ã9AÂLÂªÂ·Â”Ã¢ÂµQÂÂKÂˆÃÃšb ÃŒÃ >Â¸ÃÃ·GÂŠÃ½UpgÃ¡ÃŸ.Ã§Â±ÂÂ©Â¸!Â"Â™ZÂ¯Â‚Ã®Ã‘ÂŸÃ¥Â¢]Âƒ\\fÃÃºÂ6LÂ–BhÂŒÂ½ÂšÂ®^Ã¨ÂœÂª\\tnÂÃ”KÃ£(Âµ\\bÂ‹VÃ†PÂ§9fÂ´Ã°CÃŒgÃ¼pÂŒÃ•Â¡OÂŸÃ¬ÃÃŠnÂŠÂ¥#Ã…Ã¡PÂ”Ã‹pÂÂ©Â NÃ¡Ã²JSt=9yYÃ…Â™Âš?HÂ§aÂ¹i0cÂ‡Ã–ÃˆmÂƒÃ‹,Â‚Ã—M*Ã:C\\nDÃš]Ã‘iÂ'Ã­Â¾EÃ†Ã®ÂºÃ  Â«ÂšN%ÃŠÂ—ÃÃ¾ÃµNÃ¿Ã¬jÂ°=Ã³6sÂ¦ÃˆÂ½Ã¾Ã¨Ã¯Ã¯ÃµnÃ\H9Âªo`ÂÂ‹Â¸FrQvÂ/GÃŠLZ=ÂƒÃ¤Ã–'S_}ÂŒwÃ•YÃ¶ÃœÂ¥Ã¢Ãƒ\\b\\fÂ¸Â“?FÂ·ÃœÂ³Â’2tÃ²9Â¯EÃˆÃ¿Ãº<ÃªÃ†\\nS<Ã­rÂ†8Ã:Ã¬Ã°\\t+Â–Ã“yÂ‡Â¯BfD;Ã¸ÃÂ…|Ã¬tÃÃ™NÃ¥Â·@WÃ®Â˜Ã:ÂœÃ…Â¢Ã–Â§Ã¿R\\rB28Ã—ÃˆpÂ ÃŒÂ­ÂŠk&Â½RNv\\nÃ‡Â¨\\fÃ¨ÃÂ­Ã§ÂˆÂ®Fb>9Ã®Â·F.RÃ¾rÂ“Â¹\\tNVÂÂ¼Â¾Ã¥Ã†Ã™Â•ÂªÃ³Ãµ=9R<ÂÂºÂ†Ã n:Ã¤Ã—"z9Ã¢ÂºÂºÂ¦\\rqÃšÂ™Ã\\bN\\fÃ´Â™o{Â³Â¢Â¿Ã¾Â£Â©y\\bxÂ¶Â•Ã­Ã„Â°Â¥\\nJÂ·V-Ã·6I\Ã½OÂ‚Â¾Ã§MÂ‰ÂÃ¶Ã‚G{Ã•bÂ‡GÃ¹Ã“Iw[Ã¿Â²P]iÃ–Âª/nÂ“Ã€OO^sÃ°>5p<~Â¸Â®/ÂºltÂ€Â³GÃr8m:ÃºÃ°Ã…kÂÂªÃ ÃŒFlÃ³Ã»sB9Ã¿Â½Ã„ÃÂ•XÃJ\\frÃ·CÃƒ?Ã Ã¨Â„Â­Â¸_Â§{Â†Ã¢ÃÃ‘Â¾Ãv\\bÂ©ÂÂ”Ã†Ã Â¶Â—eÃcuÃ€Ã—\\tÂ¶OÂIZ'
    //   73: dup
    //   74: astore_2
    //   75: invokevirtual length : ()I
    //   78: istore #4
    //   80: sipush #1301
    //   83: istore_1
    //   84: iconst_m1
    //   85: istore_0
    //   86: bipush #86
    //   88: iinc #0, 1
    //   91: aload_2
    //   92: iload_0
    //   93: dup
    //   94: iload_1
    //   95: iadd
    //   96: invokevirtual substring : (II)Ljava/lang/String;
    //   99: iconst_0
    //   100: goto -> 147
    //   103: aload #5
    //   105: swap
    //   106: iload_3
    //   107: iinc #3, 1
    //   110: swap
    //   111: aastore
    //   112: iload_0
    //   113: iload_1
    //   114: iadd
    //   115: dup
    //   116: istore_0
    //   117: iload #4
    //   119: if_icmpge -> 131
    //   122: aload_2
    //   123: iload_0
    //   124: invokevirtual charAt : (I)C
    //   127: istore_1
    //   128: goto -> 86
    //   131: aload #5
    //   133: putstatic burp/Zg5d.a : [Ljava/lang/String;
    //   136: bipush #8
    //   138: anewarray java/lang/String
    //   141: putstatic burp/Zg5d.b : [Ljava/lang/String;
    //   144: goto -> 304
    //   147: dup_x2
    //   148: pop
    //   149: invokevirtual toCharArray : ()[C
    //   152: dup_x1
    //   153: arraylength
    //   154: dup_x2
    //   155: pop
    //   156: iconst_0
    //   157: istore #6
    //   159: dup2_x1
    //   160: pop2
    //   161: dup_x2
    //   162: iconst_1
    //   163: if_icmpgt -> 264
    //   166: dup2
    //   167: swap
    //   168: iload #6
    //   170: dup2_x1
    //   171: caload
    //   172: swap
    //   173: iload #6
    //   175: bipush #7
    //   177: irem
    //   178: tableswitch default -> 246, 0 -> 216, 1 -> 221, 2 -> 226, 3 -> 231, 4 -> 236, 5 -> 241
    //   216: bipush #125
    //   218: goto -> 248
    //   221: bipush #64
    //   223: goto -> 248
    //   226: bipush #96
    //   228: goto -> 248
    //   231: bipush #39
    //   233: goto -> 248
    //   236: bipush #14
    //   238: goto -> 248
    //   241: bipush #71
    //   243: goto -> 248
    //   246: bipush #47
    //   248: ixor
    //   249: ixor
    //   250: i2c
    //   251: castore
    //   252: iinc #6, 1
    //   255: dup
    //   256: ifne -> 264
    //   259: dup2
    //   260: dup_x1
    //   261: goto -> 170
    //   264: dup2_x1
    //   265: pop2
    //   266: dup_x2
    //   267: iload #6
    //   269: if_icmpgt -> 166
    //   272: pop
    //   273: new java/lang/String
    //   276: dup_x1
    //   277: swap
    //   278: invokespecial <init> : ([C)V
    //   281: invokevirtual intern : ()Ljava/lang/String;
    //   284: swap
    //   285: pop
    //   286: swap
    //   287: tableswitch default -> 43, 0 -> 103
    //   304: return
  }
  
  private static String a(int paramInt1, int paramInt2) {
    int i = (paramInt1 ^ 0x49C3) & 0xFFFF;
    if (b[i] == null) {
      char[] arrayOfChar = a[i].toCharArray();
      switch (arrayOfChar[0] & 0xFF) {
        case 0:
        
        case 1:
        
        case 2:
        
        case 3:
        
        case 4:
        
        case 5:
        
        case 6:
        
        case 7:
        
        case 8:
        
        case 9:
        
        case 10:
        
        case 11:
        
        case 12:
        
        case 13:
        
        case 14:
        
        case 15:
        
        case 16:
        
        case 17:
        
        case 18:
        
        case 19:
        
        case 20:
        
        case 21:
        
        case 22:
        
        case 23:
        
        case 24:
        
        case 25:
        
        case 26:
        
        case 27:
        
        case 28:
        
        case 29:
        
        case 30:
        
        case 31:
        
        case 32:
        
        case 33:
        
        case 34:
        
        case 35:
        
        case 36:
        
        case 37:
        
        case 38:
        
        case 39:
        
        case 40:
        
        case 41:
        
        case 42:
        
        case 43:
        
        case 44:
        
        case 45:
        
        case 46:
        
        case 47:
        
        case 48:
        
        case 49:
        
        case 50:
        
        case 51:
        
        case 52:
        
        case 53:
        
        case 54:
        
        case 55:
        
        case 56:
        
        case 57:
        
        case 58:
        
        case 59:
        
        case 60:
        
        case 61:
        
        case 62:
        
        case 63:
        
        case 64:
        
        case 65:
        
        case 66:
        
        case 67:
        
        case 68:
        
        case 69:
        
        case 70:
        
        case 71:
        
        case 72:
        
        case 73:
        
        case 74:
        
        case 75:
        
        case 76:
        
        case 77:
        
        case 78:
        
        case 79:
        
        case 80:
        
        case 81:
        
        case 82:
        
        case 83:
        
        case 84:
        
        case 85:
        
        case 86:
        
        case 87:
        
        case 88:
        
        case 89:
        
        case 90:
        
        case 91:
        
        case 92:
        
        case 93:
        
        case 94:
        
        case 95:
        
        case 96:
        
        case 97:
        
        case 98:
        
        case 99:
        
        case 100:
        
        case 101:
        
        case 102:
        
        case 103:
        
        case 104:
        
        case 105:
        
        case 106:
        
        case 107:
        
        case 108:
        
        case 109:
        
        case 110:
        
        case 111:
        
        case 112:
        
        case 113:
        
        case 114:
        
        case 115:
        
        case 116:
        
        case 117:
        
        case 118:
        
        case 119:
        
        case 120:
        
        case 121:
        
        case 122:
        
        case 123:
        
        case 124:
        
        case 125:
        
        case 126:
        
        case 127:
        
        case 128:
        
        case 129:
        
        case 130:
        
        case 131:
        
        case 132:
        
        case 133:
        
        case 134:
        
        case 135:
        
        case 136:
        
        case 137:
        
        case 138:
        
        case 139:
        
        case 140:
        
        case 141:
        
        case 142:
        
        case 143:
        
        case 144:
        
        case 145:
        
        case 146:
        
        case 147:
        
        case 148:
        
        case 149:
        
        case 150:
        
        case 151:
        
        case 152:
        
        case 153:
        
        case 154:
        
        case 155:
        
        case 156:
        
        case 157:
        
        case 158:
        
        case 159:
        
        case 160:
        
        case 161:
        
        case 162:
        
        case 163:
        
        case 164:
        
        case 165:
        
        case 166:
        
        case 167:
        
        case 168:
        
        case 169:
        
        case 170:
        
        case 171:
        
        case 172:
        
        case 173:
        
        case 174:
        
        case 175:
        
        case 176:
        
        case 177:
        
        case 178:
        
        case 179:
        
        case 180:
        
        case 181:
        
        case 182:
        
        case 183:
        
        case 184:
        
        case 185:
        
        case 186:
        
        case 187:
        
        case 188:
        
        case 189:
        
        case 190:
        
        case 191:
        
        case 192:
        
        case 193:
        
        case 194:
        
        case 195:
        
        case 196:
        
        case 197:
        
        case 198:
        
        case 199:
        
        case 200:
        
        case 201:
        
        case 202:
        
        case 203:
        
        case 204:
        
        case 205:
        
        case 206:
        
        case 207:
        
        case 208:
        
        case 209:
        
        case 210:
        
        case 211:
        
        case 212:
        
        case 213:
        
        case 214:
        
        case 215:
        
        case 216:
        
        case 217:
        
        case 218:
        
        case 219:
        
        case 220:
        
        case 221:
        
        case 222:
        
        case 223:
        
        case 224:
        
        case 225:
        
        case 226:
        
        case 227:
        
        case 228:
        
        case 229:
        
        case 230:
        
        case 231:
        
        case 232:
        
        case 233:
        
        case 234:
        
        case 235:
        
        case 236:
        
        case 237:
        
        case 238:
        
        case 239:
        
        case 240:
        
        case 241:
        
        case 242:
        
        case 243:
        
        case 244:
        
        case 245:
        
        case 246:
        
        case 247:
        
        case 248:
        
        case 249:
        
        case 250:
        
        case 251:
        
        case 252:
        
        case 253:
        
        case 254:
        
        default:
          break;
      } 
      char c = 'Â”';
      int j = (paramInt2 & 0xFF) - c;
      if (j < 0)
        j += 256; 
      int k = ((paramInt2 & 0xFFFF) >>> 8) - c;
      if (k < 0)
        k += 256; 
      for (byte b = 0; b < arrayOfChar.length; b++) {
        int m = b % 2;
        if (m == 0) {
          arrayOfChar[b] = (char)(arrayOfChar[b] ^ j);
          j = ((j >>> 3 | j << 5) ^ arrayOfChar[b]) & 0xFF;
        } else {
          arrayOfChar[b] = (char)(arrayOfChar[b] ^ k);
          k = ((k >>> 3 | k << 5) ^ arrayOfChar[b]) & 0xFF;
        } 
      } 
      b[i] = (new String(arrayOfChar)).intern();
    } 
    return b[i];
  }
}


/* Location:              C:\Program Files\BurpSuitePro\burpsuite_pro.jar!\burp\Zg5d.class
 * Java compiler version: 21 (65.0)
 * JD-Core Version:       1.1.3
 */