package burp;

import java.util.EnumSet;
import java.util.HashMap;

class Zg5r extends HashMap<String, Zg8e> {
  private static final String[] a;
  
  private static final String[] b;
  
  Zg5r() {
    put(a(9850, -23081), Zz8g.Zw(new Zxr5[] { Zz8g.ZN, Zz8g.Zv }));
    put(a(9812, 17618), Zz8g.Zw(new Zxr5[] { Zz8g.ZJ }));
    put(a(9856, -25560), Zz8g.Zw(new Zxr5[] { new Zxr5(Zt9p.NO_HTML_AND_NO_HEADER, EnumSet.of(Zklf.SAFARI, Zklf.OPERA, Zklf.CHROME)), Zz8g.Zj }));
    put(a(9950, 19914), Zz8g.Zw(new Zxr5[] { new Zxr5(Zt9p.NO_HTML_AND_NO_HEADER, EnumSet.of(Zklf.SAFARI, Zklf.OPERA, Zklf.CHROME)), Zz8g.Zj }));
    put(a(9827, -16228), Zz8g.Zw(new Zxr5[] { new Zxr5(Zt9p.NO_HTML_AND_NO_HEADER, EnumSet.of(Zklf.IE11_COMPATIBILITY_MODE)), new Zxr5(Zt9p.HTML_AND_NO_HEADER, EnumSet.of(Zklf.IE11_COMPATIBILITY_MODE)) }));
    put(a(9785, 18114), Zz8g.Zw(new Zxr5[] { Zz8g.ZJ }));
    put(a(9837, -27087), Zz8g.Zw(new Zxr5[] { Zz8g.ZJ }));
    put(a(9902, 17993), Zz8g.Zw(new Zxr5[] { Zz8g.ZN, Zz8g.Zv }));
    put(a(9804, -27795), Zz8g.Zw(new Zxr5[] { Zz8g.ZN, Zz8g.Zv }));
    put(a(9779, 26986), Zz8g.Zw(new Zxr5[] { Zz8g.ZN, Zz8g.Zv }));
    put(a(9815, 5425), Zz8g.Zw(new Zxr5[] { Zz8g.ZN, Zz8g.Zv }));
    put(a(9884, 3642), Zz8g.Zw(new Zxr5[] { Zz8g.ZN, Zz8g.Zv }));
    put(a(9895, -15462), Zz8g.Zw(new Zxr5[] { Zz8g.ZN, Zz8g.Zv }));
    put(a(9982, 31479), Zz8g.Zw(new Zxr5[] { Zz8g.ZP, Zz8g.ZB, Zz8g.ZS, Zz8g.Zo }));
    put(a(9888, -23497), Zz8g.Zw(new Zxr5[] { Zz8g.ZP, Zz8g.ZB, Zz8g.ZS, Zz8g.Zo }));
    put(a(9848, -5696), Zz8g.Zw(new Zxr5[] { Zz8g.ZP, Zz8g.ZB, Zz8g.ZS, Zz8g.Zo }));
    put(a(9923, 11070), Zz8g.Zw(new Zxr5[] { Zz8g.ZP, Zz8g.ZB, Zz8g.ZS, Zz8g.Zo }));
    put(a(9983, -1955), Zz8g.Zw(new Zxr5[] { Zz8g.ZP, Zz8g.ZB, Zz8g.ZS, Zz8g.Zo }));
    put(a(9821, -12951), Zz8g.Zw(new Zxr5[] { Zz8g.ZA, Zz8g.Zx, new Zxr5(Zt9p.NO_HTML_AND_HEADER, EnumSet.of(Zklf.EDGE, new Zklf[] { Zklf.SAFARI, Zklf.IE11_COMPATIBILITY_MODE, Zklf.IE11, Zklf.OPERA, Zklf.CHROME, Zklf.FIREFOX })), new Zxr5(Zt9p.HTML_AND_HEADER, EnumSet.of(Zklf.EDGE, new Zklf[] { Zklf.SAFARI, Zklf.IE11_COMPATIBILITY_MODE, Zklf.IE11, Zklf.OPERA, Zklf.CHROME, Zklf.FIREFOX })) }));
    put(a(9903, -14150), Zz8g.Zw(new Zxr5[] { Zz8g.ZN, Zz8g.Zv }));
    put(a(9749, 15286), Zz8g.Zw(new Zxr5[] { Zz8g.ZN, Zz8g.Zv }));
    put(a(9914, 24663), Zz8g.Zw(new Zxr5[] { Zz8g.ZN, Zz8g.Zv }));
    put(a(9965, -11866), Zz8g.Zw(new Zxr5[] { Zz8g.ZN, Zz8g.Zv }));
    put(a(9784, 5502), Zz8g.Zw(new Zxr5[] { Zz8g.ZP, Zz8g.ZB, Zz8g.ZS, Zz8g.Zo }));
    put(a(9954, 8506), Zz8g.Zw(new Zxr5[] { Zz8g.ZP, Zz8g.ZB, Zz8g.ZS, Zz8g.Zo }));
    put(a(9809, -19567), Zz8g.Zw(new Zxr5[] { Zz8g.Zo, Zz8g.ZP, Zz8g.ZB, Zz8g.ZS }));
    put(a(9953, 5092), Zz8g.Zw(new Zxr5[] { Zz8g.ZP, Zz8g.ZB, Zz8g.ZS, Zz8g.Zo }));
    put(a(9945, -6644), Zz8g.Zw(new Zxr5[] { Zz8g.ZP, Zz8g.ZB, Zz8g.ZS, Zz8g.Zo }));
    put(a(9933, 21647), Zz8g.Zw(new Zxr5[] { Zz8g.ZP, Zz8g.ZB, Zz8g.ZS, Zz8g.Zo }));
    put(a(9858, -6592), Zz8g.Zw(new Zxr5[] { Zz8g.ZP, Zz8g.ZB, Zz8g.ZS, Zz8g.Zo }));
    put(a(9759, 12776), Zz8g.Zw(new Zxr5[] { Zz8g.ZP, Zz8g.ZB, Zz8g.ZS, Zz8g.Zo }));
    put(a(9736, -27236), Zz8g.Zw(new Zxr5[] { Zz8g.ZJ }));
    put(a(9860, 32113), Zz8g.Zw(new Zxr5[] { Zz8g.ZJ }));
    put(a(9913, 10062), Zz8g.Zw(new Zxr5[] { Zz8g.ZJ }));
    put(a(9919, 10706), Zz8g.Zw(new Zxr5[] { Zz8g.ZJ }));
    put(a(9901, 2550), Zz8g.Zw(new Zxr5[] { Zz8g.ZJ }));
    put(a(9800, -8028), Zz8g.Zw(new Zxr5[] { Zz8g.ZJ }));
    put(a(9786, 11420), Zz8g.Zw(new Zxr5[] { Zz8g.ZJ }));
    put(a(9747, -31375), Zz8g.Zw(new Zxr5[] { Zz8g.ZJ }));
    put(a(9976, -29367), Zz8g.Zw(new Zxr5[] { Zz8g.ZJ }));
    put(a(9905, 27219), Zz8g.Zw(new Zxr5[] { Zz8g.ZJ }));
    put(a(9833, -5933), Zz8g.Zw(new Zxr5[] { Zz8g.ZJ }));
    put(a(9750, 6131), Zz8g.Zw(new Zxr5[] { Zz8g.ZJ }));
    put(a(9799, 524), Zz8g.Zw(new Zxr5[] { Zz8g.ZJ }));
    put(a(9790, -20324), Zz8g.Zw(new Zxr5[] { Zz8g.ZJ }));
    put(a(9949, 29181), Zz8g.Zw(new Zxr5[] { Zz8g.ZJ }));
    put(a(9791, 27936), Zz8g.Zw(new Zxr5[] { Zz8g.ZJ }));
    put(a(9843, -21318), Zz8g.Zw(new Zxr5[] { Zz8g.ZJ }));
    put(a(9805, -29739), Zz8g.Zw(new Zxr5[] { Zz8g.ZJ }));
    put(a(9792, 25877), Zz8g.Zw(new Zxr5[] { Zz8g.ZJ }));
    put(a(9851, 3733), Zz8g.Zw(new Zxr5[] { Zz8g.ZJ }));
    put(a(9857, -29161), Zz8g.Zw(new Zxr5[] { Zz8g.ZJ }));
    put(a(9829, 31083), Zz8g.Zw(new Zxr5[] { Zz8g.ZJ }));
    put(a(9980, -31543), Zz8g.Zw(new Zxr5[] { Zz8g.ZJ }));
    put(a(9922, 14997), Zz8g.Zw(new Zxr5[] { Zz8g.ZJ }));
    put(a(9946, -24137), Zz8g.Zw(new Zxr5[] { Zz8g.ZJ }));
    put(a(9907, -30967), Zz8g.Zw(new Zxr5[] { Zz8g.ZJ }));
    put(a(9883, -502), Zz8g.Zw(new Zxr5[] { Zz8g.ZJ }));
    put(a(9819, 13239), Zz8g.Zw(new Zxr5[] { Zz8g.ZJ }));
    put(a(9915, 21924), Zz8g.Zw(new Zxr5[] { Zz8g.ZJ }));
    put(a(9900, -31792), Zz8g.Zw(new Zxr5[] { Zz8g.ZJ }));
    put(a(9904, -24595), Zz8g.Zw(new Zxr5[] { Zz8g.ZJ }));
    put(a(9930, -16860), Zz8g.Zw(new Zxr5[] { Zz8g.ZJ }));
    put(a(9793, 6869), Zz8g.Zw(new Zxr5[] { Zz8g.ZJ }));
    put(a(9734, 30557), Zz8g.Zw(new Zxr5[] { Zz8g.ZJ }));
    put(a(9970, -14195), Zz8g.Zw(new Zxr5[] { Zz8g.ZJ }));
    put(a(9810, -29664), Zz8g.Zw(new Zxr5[] { Zz8g.ZJ }));
    put(a(9974, 608), Zz8g.Zw(new Zxr5[] { Zz8g.ZJ }));
    put(a(9963, -30503), Zz8g.Zw(new Zxr5[] { Zz8g.ZJ }));
    put(a(9869, 4922), Zz8g.Zw(new Zxr5[] { Zz8g.ZJ }));
    put(a(9743, -22764), Zz8g.Zw(new Zxr5[] { Zz8g.ZJ }));
    put(a(9964, 28550), Zz8g.Zw(new Zxr5[] { Zz8g.ZJ }));
    put(a(9966, 26034), Zz8g.Zw(new Zxr5[] { Zz8g.ZJ }));
    put(a(9952, -27040), Zz8g.Zw(new Zxr5[] { Zz8g.ZJ }));
    put(a(9814, 14100), Zz8g.Zw(new Zxr5[] { Zz8g.ZJ }));
    put(a(9758, 4680), Zz8g.Zw(new Zxr5[] { Zz8g.ZJ }));
    put(a(9896, -3654), Zz8g.Zw(new Zxr5[] { Zz8g.ZJ }));
    put(a(9748, 26570), Zz8g.Zw(new Zxr5[] { Zz8g.ZJ }));
    put(a(9897, -13843), Zz8g.Zw(new Zxr5[] { Zz8g.ZJ }));
    put(a(9838, -19035), Zz8g.Zw(new Zxr5[] { Zz8g.ZJ }));
    put(a(9875, -24653), Zz8g.Zw(new Zxr5[] { Zz8g.ZJ }));
    put(a(9926, 32263), Zz8g.Zw(new Zxr5[] { Zz8g.ZJ }));
    put(a(9824, -3660), Zz8g.Zw(new Zxr5[] { Zz8g.ZJ }));
    put(a(9912, 11731), Zz8g.Zw(new Zxr5[] { Zz8g.ZJ }));
    put(a(9754, -3499), Zz8g.Zw(new Zxr5[] { Zz8g.ZJ }));
    put(a(9839, 2596), Zz8g.Zw(new Zxr5[] { Zz8g.ZJ }));
    put(a(9920, 6216), Zz8g.Zw(new Zxr5[] { Zz8g.Zv, Zz8g.ZN }));
    put(a(9835, -23644), Zz8g.Zw(new Zxr5[] { Zz8g.ZJ }));
    put(a(9882, 495), Zz8g.Zw(new Zxr5[] { Zz8g.ZJ }));
    put(a(9886, 1461), Zz8g.Zw(new Zxr5[] { new Zxr5(Zt9p.NO_HTML_AND_NO_HEADER, EnumSet.of(Zklf.EDGE, new Zklf[] { Zklf.SAFARI, Zklf.IE11_COMPATIBILITY_MODE, Zklf.IE11, Zklf.OPERA, Zklf.CHROME })), new Zxr5(Zt9p.HTML_AND_NO_HEADER, EnumSet.of(Zklf.EDGE, new Zklf[] { Zklf.SAFARI, Zklf.IE11_COMPATIBILITY_MODE, Zklf.IE11, Zklf.OPERA, Zklf.CHROME })), new Zxr5(Zt9p.NO_HTML_AND_HEADER, EnumSet.of(Zklf.SAFARI, Zklf.OPERA, Zklf.CHROME)), new Zxr5(Zt9p.HTML_AND_HEADER, EnumSet.of(Zklf.SAFARI, Zklf.OPERA, Zklf.CHROME)) }));
    put(a(9972, 5846), Zz8g.Zw(new Zxr5[] { Zz8g.ZJ }));
    put(a(9911, -31238), Zz8g.Zw(new Zxr5[] { Zz8g.ZP, Zz8g.Zp, Zz8g.ZS, Zz8g.Zo }));
    put(a(9756, 26427), Zz8g.Zw(new Zxr5[] { Zz8g.ZJ }));
    put(a(9889, -14762), Zz8g.Zw(new Zxr5[] { Zz8g.ZJ }));
    put(a(9808, -6323), Zz8g.Zw(new Zxr5[] { Zz8g.ZJ }));
    put(a(9782, 17861), Zz8g.Zw(new Zxr5[] { Zz8g.ZN, Zz8g.Zv }));
    put(a(9755, -1220), Zz8g.Zw(new Zxr5[] { Zz8g.ZJ }));
    put(a(9803, 2233), Zz8g.Zw(new Zxr5[] { Zz8g.ZJ }));
    put(a(9816, -12761), Zz8g.Zw(new Zxr5[] { Zz8g.ZJ }));
    put(a(9887, 4691), Zz8g.Zw(new Zxr5[] { Zz8g.ZJ }));
    put(a(9932, 3203), Zz8g.Zw(new Zxr5[] { Zz8g.ZJ }));
    put(a(9955, 20256), Zz8g.Zw(new Zxr5[] { Zz8g.ZJ }));
    put(a(9817, 12293), Zz8g.Zw(new Zxr5[] { Zz8g.ZN, Zz8g.Zv, new Zxr5(Zt9p.NO_HTML_AND_HEADER, EnumSet.of(Zklf.EDGE, Zklf.IE11_COMPATIBILITY_MODE, Zklf.IE11)), new Zxr5(Zt9p.HTML_AND_HEADER, EnumSet.of(Zklf.EDGE, Zklf.IE11_COMPATIBILITY_MODE, Zklf.IE11)) }));
    put(a(9979, 31418), Zz8g.Zw(new Zxr5[] { Zz8g.ZJ }));
    put(a(9961, 28090), Zz8g.Zw(new Zxr5[] { Zz8g.ZJ }));
    put(a(9806, -10036), Zz8g.Zw(new Zxr5[] { Zz8g.ZJ }));
    put(a(9975, -30998), Zz8g.Zw(new Zxr5[] { Zz8g.ZJ }));
    put(a(9890, -27654), Zz8g.Zw(new Zxr5[] { Zz8g.ZP, Zz8g.Zp, Zz8g.ZS, Zz8g.Zo }));
    put(a(9880, -28097), Zz8g.Zw(new Zxr5[] { new Zxr5(Zt9p.NO_HTML_AND_NO_HEADER, EnumSet.of(Zklf.FIREFOX)), new Zxr5(Zt9p.HTML_AND_NO_HEADER, EnumSet.of(Zklf.IE11_COMPATIBILITY_MODE, Zklf.IE11, Zklf.FIREFOX)), Zz8g.ZS, Zz8g.Zo }));
    put(a(9872, -11009), Zz8g.Zw(new Zxr5[] { Zz8g.ZJ }));
    put(a(9796, 30109), Zz8g.Zw(new Zxr5[] { Zz8g.ZJ }));
    put(a(9943, 481), Zz8g.Zw(new Zxr5[] { Zz8g.ZJ }));
    put(a(9795, -1242), Zz8g.Zw(new Zxr5[] { Zz8g.ZJ }));
    put(a(9820, -26218), Zz8g.Zg);
    put(a(9823, -23665), Zz8g.Zg);
    put(a(9977, -24513), Zz8g.Zg);
    put(a(9940, 9200), Zz8g.Zg);
    put(a(9948, 17335), Zz8g.Zg);
    put(a(9854, -18246), Zz8g.Zg);
    put(a(9801, -15389), Zz8g.Zg);
    put(a(9899, -18881), Zz8g.Zg);
    put(a(9862, 18901), Zz8g.Zg);
    put(a(9960, -13571), Zz8g.Zg);
    put(a(9942, -2217), Zz8g.Zg);
    put(a(9931, -29231), Zz8g.Zg);
    put(a(9745, -8085), Zz8g.Zg);
    put(a(9738, 9442), Zz8g.Zg);
    put(a(9739, 1353), Zz8g.Zg);
    put(a(9846, 3860), Zz8g.Zg);
    put(a(9728, -19998), Zz8g.Zg);
    put(a(9956, 30243), Zz8g.Zg);
    put(a(9740, 19925), Zz8g.Zg);
    put(a(9885, 11725), Zz8g.Zg);
    put(a(9859, -24260), Zz8g.Zg);
    put(a(9908, 24905), Zz8g.Zg);
    put(a(9825, 25090), Zz8g.Zg);
    put(a(9962, -17382), Zz8g.Zg);
    put(a(9928, 15685), Zz8g.Zg);
    put(a(9842, 17806), Zz8g.Zg);
    put(a(9735, 370), Zz8g.Zg);
    put(a(9832, -23231), Zz8g.Zg);
    put(a(9818, -8646), Zz8g.Zg);
    put(a(9958, -27575), Zz8g.Zg);
    put(a(9893, 3068), Zz8g.Zg);
    put(a(9776, -21179), Zz8g.Zg);
    put(a(9788, -12051), Zz8g.Zg);
    put(a(9881, -31275), Zz8g.Zg);
    put(a(9951, -18351), Zz8g.Zg);
    put(a(9777, 6613), Zz8g.Zg);
    put(a(9802, 27597), Zz8g.Zg);
    put(a(9807, -14006), Zz8g.Zg);
    put(a(9871, 19449), Zz8g.Zg);
    put(a(9898, 3787), Zz8g.Zg);
    put(a(9934, 4398), Zz8g.Zg);
    put(a(9826, -11680), Zz8g.Zg);
    put(a(9865, -1454), Zz8g.Zg);
    put(a(9841, 27726), Zz8g.Zg);
    put(a(9916, -30046), Zz8g.Zg);
    put(a(9778, 21007), Zz8g.Zg);
    put(a(9847, -22098), Zz8g.Zg);
    put(a(9834, 6954), Zz8g.Zg);
    put(a(9855, -8803), Zz8g.Zg);
    put(a(9849, -20641), Zz8g.Zg);
    put(a(9939, 16629), Zz8g.Zg);
    put(a(9968, 11221), Zz8g.Zg);
    put(a(9831, -10656), Zz8g.Zg);
    put(a(9937, 9913), Zz8g.Zg);
    put(a(9868, -24090), Zz8g.Zg);
    put(a(9978, -23999), Zz8g.Zg);
    put(a(9742, 21255), Zz8g.Zg);
    put(a(9941, 16292), Zz8g.Zg);
    put(a(9797, -18959), Zz8g.Zg);
    put(a(9789, 31584), Zz8g.Zg);
    put(a(9853, -22325), Zz8g.Zg);
    put(a(9879, -51), Zz8g.Zg);
    put(a(9730, 31914), Zz8g.Zg);
    put(a(9957, -12051), Zz8g.Zg);
    put(a(9927, -20384), Zz8g.Zg);
    put(a(9757, 29327), Zz8g.Zg);
    put(a(9878, -31986), Zz8g.Zg);
    put(a(9861, -16827), Zz8g.Zg);
    put(a(9864, 16614), Zz8g.Zg);
    put(a(9744, 738), Zz8g.Zg);
    put(a(9947, 11230), Zz8g.Zg);
    put(a(9938, 13767), Zz8g.Zg);
    put(a(9891, -27137), Zz8g.Zg);
    put(a(9863, 26780), Zz8g.Zg);
    put(a(9811, -20096), Zz8g.Zg);
    put(a(9969, 23824), Zz8g.Zg);
    put(a(9935, -30192), Zz8g.Zg);
    put(a(9731, 25963), Zz8g.Zg);
    put(a(9877, -11435), Zz8g.Zg);
    put(a(9876, 25928), Zz8g.Zg);
    put(a(9828, -28118), Zz8g.Zg);
    put(a(9874, 22740), Zz8g.Zg);
    put(a(9873, -26724), Zz8g.Zg);
    put(a(9866, 8484), Zz8g.Zg);
    put(a(9845, -2134), Zz8g.Zg);
    put(a(9798, 5226), Zz8g.Zg);
    put(a(9867, -31330), Zz8g.Zg);
    put(a(9836, -17174), Zz8g.Zg);
    put(a(9787, -18099), Zz8g.Zg);
    put(a(9746, -25915), Zz8g.Zg);
    put(a(9794, -1999), Zz8g.Zg);
    put(a(9752, -17346), Zz8g.Zg);
    put(a(9909, 4350), Zz8g.Zg);
    put(a(9917, -31542), Zz8g.Zg);
    put(a(9918, -11496), Zz8g.Zg);
    put(a(9959, 25512), Zz8g.Zg);
    put(a(9973, -11830), Zz8g.Zg);
    put(a(9729, 3261), Zz8g.Zg);
    put(a(9733, -15276), Zz8g.Zg);
    put(a(9870, 3247), Zz8g.Zg);
    put(a(9924, 11843), Zz8g.Zg);
    put(a(9925, -5423), Zz8g.Zg);
    put(a(9971, -16322), Zz8g.Zg);
    put(a(9929, 19791), Zz8g.Zg);
    put(a(9741, 6441), Zz8g.Zg);
    put(a(9967, 29270), Zz8g.Zg);
    put(a(9910, 7779), Zz8g.Zg);
    put(a(9737, -29208), Zz8g.Zg);
    put(a(9732, -21109), Zz8g.Zg);
    put(a(9981, 30495), Zz8g.Zg);
    put(a(9822, 1457), Zz8g.Zg);
    put(a(9892, -11953), Zz8g.Zg);
    put(a(9936, 11177), Zz8g.Zg);
    put(a(9753, -10317), Zz8g.Zg);
    put(a(9944, -18592), Zz8g.Zg);
    put(a(9906, 18112), Zz8g.Zg);
    put(a(9921, 11327), Zz8g.Zg);
    put(a(9894, -4354), Zz8g.Zg);
    put(a(9830, -19414), Zz8g.Zg);
    put(a(9813, -30188), Zz8g.Zg);
    put(a(9852, -1436), Zz8g.Zg);
    put(a(9844, 11727), Zz8g.Zg);
    put(a(9840, 2469), Zz8g.Zg);
    put(a(9751, -22446), Zz8g.Zg);
  }
  
  static {
    // Byte code:
    //   0: sipush #237
    //   3: anewarray java/lang/String
    //   6: astore #5
    //   8: iconst_0
    //   9: istore_3
    //   10: ldc 'bÃµÃ¾.+Ã¦Ã‰Âµ5Â¾oÃ¡Â²[Â¤Ã«"Â‚&Â²0Ã\\b\\nÃ”Â±OÂ¢Ã‹-G^Ã„Â¤rUzÃŸÃ·Ã˜RrFFÂ·cÂ½BÂ²Ã¶\\bÃ–Â•!wÂœÂ‰|FÂ¯!ÃÂ–Â¨&6hÂ¯Ã½Ã¤ÃŠtq*Ã Â¦ÃÃ \\tÂŒÃ•Â²?ÃÃ¯ÂˆGÂŠ&?Ã»DRÃ«Â‹IÃƒÂ¹ÂŒ=Ã«Â«uÂ¢Ã‡Ã‡/=Â­Â”Â™Â†?Ã“ÂÃªÃ¦~pÂ¦ÃœÂ‰Â­xÃš+Â‹Â™Ã£QpÂºÃœÂ’]\\tr,Â›Q[Â‰Ã¹Ã›Â£Âº@Ã¥Â˜H0Â¥oÂ¸Ã¥ÃÂŠÂ™""\\bÃ°\\tÂ¨Â¶kiÃ¿*4ÂŠja\\fÂ¼@Â£ÂºÃ¤Â£Â¿Ã˜ÂÃ›+M:Ã‚Â¦O\ÂÃ“NÃ°YÃª\\bÃ±h2Â‡ÃÂµÃ§tÃ·ÂºÂ·Â–Ã‚`ÃˆÃ¸:Â³.zÃÂšÃ‹Â‘ÃÂ‘ÂÃ·ÂªÃ”\\bÃ•!Â´ÂµÃ•Ã“Â»WÃ…zLl%Ã¤Â¨Â”ÃœÂ¤Ã€ÃµlÂ¦1Ã’Ã¶yrFBÃ€Â.gÃ°WÂ’T;Â¾Â—Ã¶/Â‘Ã‚ÃÃ´\ÃµdÂ¸]Â‡_Ã“GÃ¤j]=Ã®Z]:X;rÃˆÃ­Ã˜Â‰Â©Â¡ÃÂ”Â‹ÂyZNÂ¹wÂ‘Ã}dÃšX4Â¦%Ã¶PÃ¼Ã­!Ã¹-Ã¡Ã˜zbxÂªÃakÂ¼Â™Â´ÂŸÃ¿Ã¿Ã·6ÃˆÂƒxÃÂ‹ÂXÂ¶Â‘1ÂÂ·Ã¶bÃ¼5ÂºZ:ÃŠeÃÃ½lÃ¾|Ã¡\\bÃ®XÂ£ÂÂ‰Â‚YÃÂ‚Ã¡Â•Â„Ã•yÃ’KÃ¹qxcz-Â–Ã¸_Â„GÂ)Â…Â— 'lÂÂÂ¹Ã±Kh\\tÂ–Â9Â‹Ã«wAÃ‹4@Ã–ÂÃ·Â¨\\nAÃ°Ã‡Â¯Ã¾_/Â Ãº"ÂpaÂÃ˜Ã°Â·wÃºÃ¦Â–ÃªÂ5_Â†Â§ÂºBÃ Ã¨uÂ”Ã¯KÂ¾:Ã©Â´Ã\\rÂ•]Â¿Â¨Ãœ@K'ÃˆÂ˜<Ã£Â¤yUÃ³Ã·]RÃ‚FPy{Â¯8Âœ6Y\\tmÂµÂÂ±Â“Ã‚LÂºÃµ\\tÃ²Ã®~ÃšÃ­Â¯Âƒ_n"\\fp3ÂÂ’Ã°Ã¾wÃ“Ã¦Â³Ãª)6Ã„Â•ÂÃƒÂ§ÂÂµÃ™ÂŒdÃ»Ã®Â¸Â˜UÂ¶ÂŠÃ‘sÃEf%Ã™Ã‰Ã¾Ã‹Ã³Â¯F4Ã¼4rÃ‚Ã¢1P.ÃœÂ¤!Y\\bEÃ‰Ã–Â¢'ÃŸÂŒÃŸJÃ°Â¨MÂÂ–\\bÂ‘Ã‘Ã™bÃ·JÃ•ro Ã™Â¶Â«"VÃ¨Â£|Ã«Â¹8VÂªÃ€;$Ã™ÂºÃ¿Â›ÂŠOÂ¤Y(i4\\rÂŒÃ‚Â–z&d{h\\bÃ‚Ã¶Ã¢Â”ÂÂ¦DÃ”Â«6ÃŠÂ‹ÂGMÂƒH#Â”FÃ¿qÃšÃ³\\rÂ¯Ã•EÂ˜\-jÂ›Ã…Â‰<Â¤ÃT8Â¾ÂµGBÃ‹Ã¤Â\\nÃ›w9Â6Ã°Â‰Â¾\\tq\\nÃ»Ã•]ÃƒÂ•ÂšÂ!Ã¹jÃ¾ymÂ¿YÃ”Â‡Ã³Ã¼vVÃ¸Â’h@ÂŸRCwÃ±Â§Ã¢Ã¦Â‚Â•CÂ›WÃ¦+Ã¨Ã—ÂÂ’m;Â¡oÃªÂ‘Ã Ã‘Âµj?`Ã¸Â»Â®Â˜k%Bth gÃŠÃ‹ÃÃ¢FÃŒÃ¾Ã…Â¼+Ã—ÂŒÃ˜RÃœW0Â³Ã‡BJÃ˜Â½8noÃ…*ÃÃÂ¼A)`Z>gKDÂ²0Ã©% ^Ã…Ã¿\\noÂµÃÂ°O7Â´YÂ|ÃœaÃ@Â†Ã¦Ã¨ÂÂÃ¦Â’p;oÂÂ’p\\nÂª<uÂ€ÂŒÃ¤Â¯~Â9{Â¢[Ã¦Ã»(\Â©Ã¢9TÃ®Â¼ÂŸÃ¶Â½ÃœCÂ¯\\f@(Ã¨'Ã©ÃÂ‚kTÃ®6k]Â¬ÂŸ'cOÂ®Â€Ã™Ã§yÂƒopÃ©ÃÂ¨Ã»]Â¶Â€iÂ‚*Ã€Â”Ã–bÃ…ÃÂ˜r3Ã„ZÂ­ ^\\nZÃ“Â‹Y'UWbÂ‡Â¸Â®V}Ã¦AbÃ¯Â™Â¥Â­Jt}<?sÃ„Ã‚Ã±T6CÃ°?nÃ»2ÂºÃ«Â™Ã”tÂ®Â‹ÃµÃ»Â‚J;Â¢iÃ†Â x!Â˜bÃ’xÃ¨ÂŸÃ©ÃÂ‘s>f Â¹Â„2Ã©Ã¸ufÂ_veÂ‚Ã¿ÃŒÂ¹xÃ¬Ã‘\\rÃ„,Ã¦!S(1rÃ‹Â½Â¿G6ÃœtzBÃ£!p,Ã‰Ã°Â½Ã‚ÃŠÃŸÃÃ`Âˆ1AAÃ©ÂA\\fAÂ x~MfÂ¾sQgÂ—Â¡Â¢Â½y/Ã›Â±ÃŠÃ™Ã¶=Â¶\`Ã„#ÃµÃ–..Ã¦iÂµ!Â¾Ã­Ã¡Ã§IÂ¾ÂºÃ˜Â‰Â¡Â"ÃºÂ„ÂÂ¤aÃ˜Â£Â·ÃºÂ«Â–CÂˆ]+gÂ£Ã‘Â˜r\\b\\tRÃµ[Ã§+\\fD!\Ã¥Â¿g5Ã\\nÂMn6IÃƒPÃ†BÂ¯aÂ©Â¾Â»z%?Ã‹LÃ¡Ã²Âµs.ÂšÂ‘Ã¢ÃÃ¸Ã¹HÂ¯Ã‹ÃŠÂ†Ã„-Ã›Ã¯Â­ÃƒÃ‹Ã£Â„Ã±Ã¨Ã‚Ã»w(ÂšÂ˜;\\t/s0Ãº$&Â 7sÂ¼qVxÃ“Ã»YÃ“Bv@\\t}Â¥ÂªÃÃ¼Â¿ÃÂ¸fÃ¨ Ã¯GÂ¨UÂÂˆI:Â–Ã•Ã–9fÂ‰Ã¤Ã\\f`HCÂ•Â±ÃšÃÂ§Ã–Â§(Ã«(Ã¾Ã´qÃšÃ¢Ã·5Ã²Â®Â—Ã£Â«UÃ©ÂŠÂ«:Ã†Â–\\ftÃ«Â¶2`fJÃšÂ—Â³Ã¦Ã»Â¶Â©Ã=3Ã 7\tÂ\\nÃ€uÃ:Â›>2ÃAÂ¼Â§VÃ€xÂˆÃ»2Ã“/vÃ­Â‹Â¸\\tÃºÂ«Â¦\\tÃ«Ã¤Â¨\\b7xÃÂ°+Â°\\f9Â“Ã²Ã¦|Â¥Â¤|BÂ¦Â“Ã¦Â¥kÃ¿f4}PÂ›Â†<L^Ã¡2Ã€uHÃ—>Ã•\\nÃ°Â¾Ã‹C[YÃ™ÂˆÃ¥mÂ˜l'?tÂ­ÃÃœÃ•Â“sD+Ã¼Ã†hr!Â›XÃ”+ÂGGÂˆÂ¼Â¤Ã½(Ã«Ã„I*Â¹Â±ÂšÃ«_u"Â˜\\fiÂŸN Ã°ÃŸwI~ÃÃ¬Ã´Ã®Â–Ã¤ÃÃ·ZÂ­Ã–Â—Â¹GÃ‚Â©+\\fZÂ™6Ã€Â·ÂÂ‹Ã±EÂŒ8e$ Ã­\\fÂµHÂ€I|2'HÂ“ÃŸGÃ…VCÃÂ†Ã³Â¸DÃ“Ã˜&UÃ‘Â™Ã¼ZÂƒ4Ã¼GÂ«ZÃ¥Â¿ÂŸ[Âšg[+Ã¡Ã†IqÂ®Â¶Ã£ÂEÂ Â}_Ã´Â§u8h:Ã£$ÂµÃ¬ÃÂ˜\\r!p&ÃÃ°KÂÂÃ²7Ã¯Ã®4Ã«Ã‡Ã“ÂŸFÂfÃƒ?)\\bÂ‘Â‰Â’Ã©Ã¡Â²%Ãv8ÃºÂµÃBÃšÃ¤2ÂNÃŒÂ¢&ÃŒÂ‚yÂ‰Â†ÃÃœ:gÃºÃ£"Ã‹PÃÃ¡Â‹Â³ÃŠ|"\\nÂ•Ã±gÂªÃ,Ã§gÃ‘\\t\\tÂ½ÂªÂ—RÃÂ¾&"Â©Â©Ã T>Ã³Â§Â‹YvA\\nLtÂ©Â‰Ã…ÃœZÂ¶Â®XÂ„ÃŠÂ¤Ã«Â‰Â£ÂÂ¿Â«3Â€^F!Ã‘a+|Ã¬Â¢Â Ã´Â¥q\\f(Ãµ#Â‹\\tÂ‘ÂÃ§GÃÂ‘Ã§Ã‡Â‘Â¡3JÃ½Â´/Â Â§gÃ¥Â´Ã¾Ã¥Ã¸&\\n&ÃœÃ¤ÂœÂ¾gÃ³\\r;\IJÃ»3Â‹EÃÃÂ·0?0Â¥oÃ°Â¢Â¸Â¼]ÂÂŠÃ½,Â»Ãœ\\t ÃœÂÂ­^ÃšUÂÂ Ã³"Ã«q\\nYÂ€Â¢sÂ MÂ¸Ã€Â¤wÃ«{ÃŸpÂ†0Ã˜5\\bÂ\\bÂ’Ã€Ã¹Ã¿Ã¨GÃœÃœ)Ã‘BÂ–!Ã,Ã¬ P@Ã‹mJJÃ±TÂKÃ…Ã›(Â&]Â­Â§Â½=ÂÃ°Â¥,\\nÃº}hÂ˜Â¨Ã¿TÂ²Â¶sÃ£ÂŠHÂ=Â 7Ã Ã…Â°Ã‘2Â”28Â³Â¬4xÂ³eÃ½ÂŒÂ¸Â³Ã£]Ãƒ9|Â¤3}]Â‡u\\buÃ—JÃ©Ã­ÂŒÃš.Ã›ÂµÂª@`Â¯Âª4a4Â¼rÂ´Ã¢Ã¿PÃ·ÃÂ‹=tÃ•'Ã“HswÃµ Â€Ã¤iAfDÂšÂ¶Y0qÂ ^Ã¡Ã‘\\rÂ+Ã£ÂƒÂ½DT &mÃˆÂ¥ÃÂ‚\>U-Ã—XvÃ§bÂ•@Ã¶Ã˜rj'Â“%FX6(jlAÂ…Ã´ÃŠeÂ±=Ã±B _EÂI(Ã¼Â‘Â½KÂœÃ–ÃÂ²cÃ‘Ã²Â‹ÂªjÂ¥mÂ³ÂÂ‚ÃšÃ¯Ã‰Ã§Â¸Â¢ÂŠÂ•e <Ã´Â¤2Ã½JÂ·ÂˆÂ‚D.zÂ‰;Â¬Ã´Ã«Ã Ã¦Ã¡GDÃŸfKÃšÃÃ–ÂŸgÂŸ-Ã‡h.nÂ¬ÃÂÃ¼Ãy\\nÃ¸Ã¿ÃŠk{KuÃ¶Â—Â—\\f)ÂšÂ‚(Ã„Ã¦Âƒ?}\\rCÃ«Ã»MÃ£Ã­O4Â\\tÃ¾@\\nÂœcÃªRÂ¿6\\n=Â‡FÂ£UVÃ‡sÃÂ³\\rÂ˜%m?PlpÂ¶Â®Â¥^Ã“CjWÂŒÃ#KÂJÂ¾ Ã›\\fÂ§Ã»Ã“y}S ÂÃˆÂ­Ã•\\fÃŠÂ»ÂŒÃ£Â³]5Ã¾Â«X4Â•Â¦ÂµÃ¶BÃµÃ·,Ã¹NÃ°>..Â’Â¨Â“!Ã€Â´Ã¬Âµ1ÃŸ*Ã³Â‚Ã”dÃ£24?Â¶ts "SÃ˜,ÃºÂ¡Â¼Â‡66Ã­AÃ»Ã”ÂÃ£Â©Ã•Â‚-ÃzÂ¶Ã½FKÃ«Ã…Â´ÂŠQ$Â®ÂÂ¬ÂÃÂ¨Â‹Â†Ã”^Ã–ÂŸWZ&iÃ²hÂ‘Â“iÂ‰ÂšÂ­,Ã¼?ÂÂ2ÂªRÃ»Â‹KÃƒÃ¹ÂŒ=ÃªÂ«UÂ¼ÂœÃÃ¦Ã»\\bÃ‹Â»Ã­ÃœÂ¿Â…_Ãp$Â…Ã¾Â„r ÃÃ¿GÂƒÂ¥Â­KÂ­Ã“DZÂiRÃ¤ÂSÃ‡TÃÃ§ÃˆÃ±Â‰ÃŠÃµ+Â²mÂŸÂ›Â¶{H5ÂÂ˜ÃŸÂ¹Â“IÃ©Ã”Â¿Ã Ã¾Â¸Ã¨Ã—Â—gÂš\\tÃŒ]Ã§0Â†OÂ€Ã·Ã™@Ãº<Ã­IÃÂ…QÂ¼"^rÂ”%sÃ·Ã³Ãœ\\r"SÂ’Â¦ Ã¾]9\\rÃ»Ã ÂªÂˆwhÃÃ¯7|_*\\bÃÃ…YEÂ®Ã—!Â„BÂ°Ã£6Ã¶ÃºÃ«4Â–Âˆ@ÂÂ§CÃ¯V7Ã“vÂÃ­}Ã”Â£Â’Âµ(Ã³Â«Ã¬26Ã¶Ã¤Â§Â­`8TÃ‘BÃ»|ÃMÃ€qÂ¬&FÂ¶Ã{7}Â40Â²Â´Ã†bÃ»Ã ÃŠÃ#7Ã‰ÂÃ¿I\\rjÂ¼3VRxÃšÃ»xÃ“fvÃ„Â®Â¬ÂºÂƒhiN\\ty'QÃ—mÂ’Â¡Â´\\nÃ“Â¿Â¯cÃ—Ã\ÂºÃµ#Â—Âš3gÃ”|nÂ¬aÃ¼ Â—ÃŸÂˆÃ²Âµ7Â¹Â®Â½Â¡Ã¾$ÃŒÂ‘Â’Â\\reÃÃ…Ã´Â¸=Â»Â¤WÂ“ÃˆÂ†2oÃ”Ã¸\\bÂ…Â†.a1Ã¬B\|9Ã“Ã€Ã–qÃ–&Ã².1[Ã²|W\\bC Â©4Â‡Ã¡,UÂ‰Â¢Ã¸bS#Ã´Â°Â‰Â¯Â¥Ã‚1Â™ÂÃ’Ã„y4FÂŠÃ€ÂšjNÂ¡Ã¦lÂ¬WÃ“.Â³n\dÃ…ÂÂ‚Ã¡HÂÂÂÂ—|ÂµÂ!Â¶CÃÃŸÂ¼Â¨ÃªÃ¦Â…o?RÃ¶Â¹:Ã®yÂ—nW^Y$ÃªÂ°Ã¯Â†\\tÃ³ÂÂ½Ãªn2Â„DÂ»Â¹4Â‘h^Ã \\naÂ¼Â {ÃÂ¥8Â€ÂµÂ€B3Ã¤ÂÃ©Ã›,T>yÂ¹Ã‘G"Â‘\\f]Ã­Ã’ÂÂ–Ã“Â«QÃŠÂ¢LÂ5 Â’Â²Ã‚Â¢{Ã¸ÃˆÂ«/7Â„Â¹Â™Ã´ajÂ¥Ã±Ã¯*<q5Â¾RÃ´Ã¦Ã·ÃÃ¶Ã“Ã¨#tEÂ›Ã©Â‹Al\Ã'ÃÂ±ÂŠÃ‚rÃ´'Â’Ã¬Â›Â«(lÂœÃŒÂqÃ—MRh~Â¿_ÃˆÃŒpÂ•lÂ¸#Ãµ|Ã®acÃ«Â¹%GÃ±)\\nÂ—Ã‘lJÂAÃ¤P`Ã¬CÂ•Â¢Ã†Ã‰Â°Â±Â¿Ã—Â¤gÂ¶ÂŸo;Ã¬Â·Ã»Â´IWX3Ã¿ESÃf00Ã¢uMÃ¢Ã©Â³uZo_ÃŒOÃ°Ã¥eÂ­Ã°Ã±B\\nÃºÃ‘Â«Ã™J7A/Â§Â°Ã¥[Ã¢ÂµÃ¿LÂ‹HEÂ»8Âƒ$ÃœÃ­Â—Âµ"Ã™>$Â’Ã”J,Ã£)Â½Â²Tu&Ã‡ÃˆÃ°Ã(CkHÃ†#NQtLÂœ`ÂŠÂ…?Ã·Ã³*Â‘^Ã¡Ã°ÃµÂƒnJÂ½z Ã®Â¶1FÃ’Ã«Ã¶Ã’ÂŠÂ$7ÂÂŸÂÂ»Â¨GÂ†M^Ã¥Âˆ7IÃµÂ…ÂµÂµuÂ®oÃ¡_Â¬Â¶OÂ¿Ã¥Ã¿uÃ‰Ã¦LÃ…Ã—Â–,Ã´Â½_ÂƒYÃ ÃŸ?WÂÃ¦Ã™NÃ§ÃŒÂ…'Ã¸Â›'6JTvÂŠÂ‰WÂ‚kÃ—Â–SÂ‘Ã¢ÃgmÂ—>Â‘^Ã³Ã¿ÃŒomÃÂ°,LÃµÃŠÃŸ0Ãµ!/ÂÂ¯0ÃÂ´Â¨b6Ã Â¯Ã½Ã…ÃŠ<\Ã²"Ã™Ãœ\\rÃƒÂ\\f)DiÂº/Â¿Â<Ã‰)Â•Ãr8Â¿Â‡\\bHÃ¤Ã´GÃ«yQÃ®oSIÂ@Ã½ v6ÂŒÂµÂ€Ã¬MÂ²jGÃºÂµÃ1 a.Ã­Ã±Â®Ã¶Â·ÃÃ¾zÂ·XHÂ’\\fÃ¬6Ã“Ã®@Â¤#+Ã¶bÂƒUYÃ±#Ã¿PMÂš]pgÃ¬Ã¤TÂªÃˆ&\\bÂ“EÃ¢Xe9Â–Â³Â–&[Ã©Ã³Ã‰*ÂˆÂªÂ½[Â©Â–={ÃŸÃ„ n'\\fÃ3ÂŠÂ’rÃ¾'Ã“Ã¬Â½Ã¨3Â½Â«ÃEJ\\rÃ‡Ã­Â¬0<ÃŠÂ¥oÃ±\\bÃˆÃ€-Âª5Â¡Â…Â˜Ã™3*PzÂ¹p.Ã¥Â£fbÂƒÃÂ©rÃŒÂ²Â½,Â´Ã Ã¦[@ÃJÂc=sÃ·Ã§Ã“dÂÃ˜`Ã´Â¸Â”Ã®PÃÂ\\ni\\bÃ¸GÃ‰ÂŠ#Â¼\\t Â†~K2Ã«.m>Â½fvÃ¸|Â{Ã’Ãƒ3tnGÃ»Â­Ã‰3\\fQÂ’qb\\bÃ–Ã±\\n`irÂ¶Â³NÂ \\tÃ®qTÂ”#-Ã™ÂºÂ”ÃÂŸbH\\tÂ¬Â»}0n2Ã–Ã¹ÃVÃµÃ‚y-Â«Â \\fÂªÃ‰*\\nÃÂ‰ÂÂ…ÂÃ™Â°qÃ¢\\rÃ°ÃˆÂ‹J2Â¨pÂ±Âˆ?Â½vw|~{Ã¬ÃƒÃ´tÂ–GÃ¤ÂªÃ¯Â£ÂÃœ%Âª\\r\\fÂ>SÂ¢Ã}Â¿,K!ÂˆWÃÃÂ¨KÃ¡JÂ \\f\\nÂ· Â…rÃ»|Â·,$N_UMÃ¢ÂµÂ›ZÃ…Ã¨Ã‰0Â¡Ã²`Ã¯Ã£G|"Â±\\rÂ´Ã¹\\nÂ¯Ã…Â‹#ÂŒÃºÃ©ÃÃˆÂ§Â¬"Â´Â°ÃÃªN,bÂ»Ã¥Â¬Â ÃŒÃ§Â]Ã³Ã²Â¿jEÃ\Â˜'zÃ¨GÃ†Â’Ã‘Ã¶\\rÃ–kÂ®Ã°Â½\\t5SsÃ¾LÂ¦Â»+Ã€ÃµÃ¥M'K\Â£Â®Âª):I\\rPtÂ¹sÂºÂ´!5.iÃ–ÃÃ.Ã±UÃŠÂ‰ÃµXÂ²ÂŸÂ°Â¹ Ã´Â„bÃ„=3ÂˆÃÃ Ã¤oÃ·LC8Ã«*Ã¥Â±Ã¨Â‡Ã²^TÂ‰Ã³Ã¼ÃÃ½\\tw:ze6Â’=~Âˆ(Ã1Â¨Â¶Ã¡ÃµÂÃ—Ã².8dÂ‹Ã‘ÃšH9"9iÂ‹Ã–ÂŸÃ‡Ã‘hÃ.uÂ¬Â¢ÂÂ„Ã˜ÃµÂYÂ‘.Ã¦5 Ã£CHÃšÂ™Â¯Yk'e#Ã™Ã >eyÃ¤PÂ®EusÂ¶oH;Ã³Â¿rÃ¦Ã²ÃŸ*ÃÂ‡ÃšÃ‘Qv8xÂ£Ã¨fÃ£\\t]ÂƒÂ‹wSXÂ§Â§.6wVÃ©Ã¯TÃ±Â‚Ã¿ Â°Ã²Âƒl8Ã¢kÂÃ¹Ã“ÃˆÃ±Ã­ÃŠ.QZÃÂ½lÂ…Ã’Ã?sÃ 7]tÃ«\\tÃÃ¹Ã…LÂˆ6ÂƒÃÂ»Ã¡ÂÃ†i0Ã¬2/Ã–Ã¹ÂVÃÃ‚rnÂ¹Ã–ÂÃ‚`WÂÃ—0ÃÂ´Ib\\nÃ (\\rÃ™Ã›2ÃŸ/Ã±ÂºÃ’~ÃÃj8yÂµÂ¿BÃ”Ã¤Ã³ÂvÃ•Â»>rÂ²Ã§Ã‘d\\fÃ”Â¸Ã©6[Ã’Â™Ã™ÃªZAÂ¿\\rÃµ UÂ…Ãƒ\\fÂÂ¯uÃ´6IR3Â¾E{Ãc0Â¥0Ã£3Ã‡ÃªF2Ã°<Â¸Â–LÃŠÂˆÂ¦Ã„@Âºq|Â‘/!Âƒ.Dw Ã¯mÃ±Â¥Ã¹ÃÂ»=Ã‡YÃsÃ¨#Â–Â±\\fÂ‰Âª^Ã…Ã½Ã¡ÃœÃ€Â¯N\\t\\bÂ³2Â‚eÃ¼Ã…Â“Â°Â» (oÃ¤Â¾ÃµCÂƒ-eÃ¹mÃ±NÃŠÃ…Q_kÃ®cÃŠi1ÂˆÂ¨]V Â’Ã¾Ã©ÃšÂ¯Ã¹Âˆ]nÃ¢wLÂ—JÂ‹|}Â¯Â¨Ã—Ã¡Ã‘ÂƒÂ¨wÃ72.Ã‘ÃÂ˜B'\\nÂ˜+3bDÂ¸Ã¨Ã¢Â°[Â£@Ã²Â˜Âª0Ã¹o3Ã¥Â¯ÂŠÂ¹9Â¶"Â”xfwÂÃšÂ€Ã³TÃƒÂJÂƒhÂ„Kl=Ã¼\\rÂ¦=Ã¤~\\rAcÃœL0Â©ÂŒ\\tÂ¤JGmtkÃ§Â¨ÃÃ Ã‚k&Ã¶9NÂŒQ%'ÃÃ²ÂŠÂªrÃ¹'3Ã¬Â´Ã©Â¬GÃ›Ã•Â‘%Ã»eKÃ¹7JÃªEUaÂœeÃ¼ÂˆOÃ­{ÃŸckÂ¶Â±;kÂ¦YfÂ»8TÂ«Ã£ytÃ¨Ã»Â™zJÃ±F\\te'Â¤Â¶UÃ¢ÃŒÃ·ÂºR>FÃÃyÂ—YÃ‹Â½L\\nÃ¯Si:NÃm1Ã“Â…_Â®+Ã¤Â]Ã¥,Ã—Â¦VÂ½Ã†Â¿Ã`H\0Â¶<#$Ã’Ã¸Â›+ÃÃµÃŒÂ5ÃšÂªSÂœ\Ã†Ã¢aÂ”Â—!XÃ¬ÂªÂ‚?Ã¸Â©Ã´Â·,fqÃ¯Â‚Â”\ÂšL&\\rÃÃ˜Â†SÂ©ZÂ¦Ã®ZÂ‘Â¢O?ÃÃ°'
    //   12: dup
    //   13: astore_2
    //   14: invokevirtual length : ()I
    //   17: istore #4
    //   19: bipush #25
    //   21: istore_1
    //   22: iconst_m1
    //   23: istore_0
    //   24: bipush #36
    //   26: iinc #0, 1
    //   29: aload_2
    //   30: iload_0
    //   31: dup
    //   32: iload_1
    //   33: iadd
    //   34: invokevirtual substring : (II)Ljava/lang/String;
    //   37: iconst_m1
    //   38: goto -> 145
    //   41: aload #5
    //   43: swap
    //   44: iload_3
    //   45: iinc #3, 1
    //   48: swap
    //   49: aastore
    //   50: iload_0
    //   51: iload_1
    //   52: iadd
    //   53: dup
    //   54: istore_0
    //   55: iload #4
    //   57: if_icmpge -> 69
    //   60: aload_2
    //   61: iload_0
    //   62: invokevirtual charAt : (I)C
    //   65: istore_1
    //   66: goto -> 24
    //   69: ldc 'Â¿Ã–HÂÃ…Ã¼2Ã‚Â”OÃ ÂŸÂ¥Ã¸NdÃ•VÂªÂ‹Âˆ=Â«Ã¡\\fFÃ¬Ã¨8\\rÃ¼QÂŸÃpÃšÂšÂ¢\\rÂ°'
    //   71: dup
    //   72: astore_2
    //   73: invokevirtual length : ()I
    //   76: istore #4
    //   78: bipush #32
    //   80: istore_1
    //   81: iconst_m1
    //   82: istore_0
    //   83: bipush #84
    //   85: iinc #0, 1
    //   88: aload_2
    //   89: iload_0
    //   90: dup
    //   91: iload_1
    //   92: iadd
    //   93: invokevirtual substring : (II)Ljava/lang/String;
    //   96: iconst_0
    //   97: goto -> 145
    //   100: aload #5
    //   102: swap
    //   103: iload_3
    //   104: iinc #3, 1
    //   107: swap
    //   108: aastore
    //   109: iload_0
    //   110: iload_1
    //   111: iadd
    //   112: dup
    //   113: istore_0
    //   114: iload #4
    //   116: if_icmpge -> 128
    //   119: aload_2
    //   120: iload_0
    //   121: invokevirtual charAt : (I)C
    //   124: istore_1
    //   125: goto -> 83
    //   128: aload #5
    //   130: putstatic burp/Zg5r.a : [Ljava/lang/String;
    //   133: sipush #237
    //   136: anewarray java/lang/String
    //   139: putstatic burp/Zg5r.b : [Ljava/lang/String;
    //   142: goto -> 304
    //   145: dup_x2
    //   146: pop
    //   147: invokevirtual toCharArray : ()[C
    //   150: dup_x1
    //   151: arraylength
    //   152: dup_x2
    //   153: pop
    //   154: iconst_0
    //   155: istore #6
    //   157: dup2_x1
    //   158: pop2
    //   159: dup_x2
    //   160: iconst_1
    //   161: if_icmpgt -> 264
    //   164: dup2
    //   165: swap
    //   166: iload #6
    //   168: dup2_x1
    //   169: caload
    //   170: swap
    //   171: iload #6
    //   173: bipush #7
    //   175: irem
    //   176: tableswitch default -> 246, 0 -> 216, 1 -> 221, 2 -> 226, 3 -> 231, 4 -> 236, 5 -> 241
    //   216: bipush #51
    //   218: goto -> 248
    //   221: bipush #15
    //   223: goto -> 248
    //   226: bipush #58
    //   228: goto -> 248
    //   231: bipush #103
    //   233: goto -> 248
    //   236: bipush #66
    //   238: goto -> 248
    //   241: bipush #94
    //   243: goto -> 248
    //   246: bipush #57
    //   248: ixor
    //   249: ixor
    //   250: i2c
    //   251: castore
    //   252: iinc #6, 1
    //   255: dup
    //   256: ifne -> 264
    //   259: dup2
    //   260: dup_x1
    //   261: goto -> 168
    //   264: dup2_x1
    //   265: pop2
    //   266: dup_x2
    //   267: iload #6
    //   269: if_icmpgt -> 164
    //   272: pop
    //   273: new java/lang/String
    //   276: dup_x1
    //   277: swap
    //   278: invokespecial <init> : ([C)V
    //   281: invokevirtual intern : ()Ljava/lang/String;
    //   284: swap
    //   285: pop
    //   286: swap
    //   287: tableswitch default -> 41, 0 -> 100
    //   304: return
  }
  
  private static String a(int paramInt1, int paramInt2) {
    int i = (paramInt1 ^ 0x26DA) & 0xFFFF;
    if (b[i] == null) {
      char[] arrayOfChar = a[i].toCharArray();
      switch (arrayOfChar[0] & 0xFF) {
        case 0:
        
        case 1:
        
        case 2:
        
        case 3:
        
        case 4:
        
        case 5:
        
        case 6:
        
        case 7:
        
        case 8:
        
        case 9:
        
        case 10:
        
        case 11:
        
        case 12:
        
        case 13:
        
        case 14:
        
        case 15:
        
        case 16:
        
        case 17:
        
        case 18:
        
        case 19:
        
        case 20:
        
        case 21:
        
        case 22:
        
        case 23:
        
        case 24:
        
        case 25:
        
        case 26:
        
        case 27:
        
        case 28:
        
        case 29:
        
        case 30:
        
        case 31:
        
        case 32:
        
        case 33:
        
        case 34:
        
        case 35:
        
        case 36:
        
        case 37:
        
        case 38:
        
        case 39:
        
        case 40:
        
        case 41:
        
        case 42:
        
        case 43:
        
        case 44:
        
        case 45:
        
        case 46:
        
        case 47:
        
        case 48:
        
        case 49:
        
        case 50:
        
        case 51:
        
        case 52:
        
        case 53:
        
        case 54:
        
        case 55:
        
        case 56:
        
        case 57:
        
        case 58:
        
        case 59:
        
        case 60:
        
        case 61:
        
        case 62:
        
        case 63:
        
        case 64:
        
        case 65:
        
        case 66:
        
        case 67:
        
        case 68:
        
        case 69:
        
        case 70:
        
        case 71:
        
        case 72:
        
        case 73:
        
        case 74:
        
        case 75:
        
        case 76:
        
        case 77:
        
        case 78:
        
        case 79:
        
        case 80:
        
        case 81:
        
        case 82:
        
        case 83:
        
        case 84:
        
        case 85:
        
        case 86:
        
        case 87:
        
        case 88:
        
        case 89:
        
        case 90:
        
        case 91:
        
        case 92:
        
        case 93:
        
        case 94:
        
        case 95:
        
        case 96:
        
        case 97:
        
        case 98:
        
        case 99:
        
        case 100:
        
        case 101:
        
        case 102:
        
        case 103:
        
        case 104:
        
        case 105:
        
        case 106:
        
        case 107:
        
        case 108:
        
        case 109:
        
        case 110:
        
        case 111:
        
        case 112:
        
        case 113:
        
        case 114:
        
        case 115:
        
        case 116:
        
        case 117:
        
        case 118:
        
        case 119:
        
        case 120:
        
        case 121:
        
        case 122:
        
        case 123:
        
        case 124:
        
        case 125:
        
        case 126:
        
        case 127:
        
        case 128:
        
        case 129:
        
        case 130:
        
        case 131:
        
        case 132:
        
        case 133:
        
        case 134:
        
        case 135:
        
        case 136:
        
        case 137:
        
        case 138:
        
        case 139:
        
        case 140:
        
        case 141:
        
        case 142:
        
        case 143:
        
        case 144:
        
        case 145:
        
        case 146:
        
        case 147:
        
        case 148:
        
        case 149:
        
        case 150:
        
        case 151:
        
        case 152:
        
        case 153:
        
        case 154:
        
        case 155:
        
        case 156:
        
        case 157:
        
        case 158:
        
        case 159:
        
        case 160:
        
        case 161:
        
        case 162:
        
        case 163:
        
        case 164:
        
        case 165:
        
        case 166:
        
        case 167:
        
        case 168:
        
        case 169:
        
        case 170:
        
        case 171:
        
        case 172:
        
        case 173:
        
        case 174:
        
        case 175:
        
        case 176:
        
        case 177:
        
        case 178:
        
        case 179:
        
        case 180:
        
        case 181:
        
        case 182:
        
        case 183:
        
        case 184:
        
        case 185:
        
        case 186:
        
        case 187:
        
        case 188:
        
        case 189:
        
        case 190:
        
        case 191:
        
        case 192:
        
        case 193:
        
        case 194:
        
        case 195:
        
        case 196:
        
        case 197:
        
        case 198:
        
        case 199:
        
        case 200:
        
        case 201:
        
        case 202:
        
        case 203:
        
        case 204:
        
        case 205:
        
        case 206:
        
        case 207:
        
        case 208:
        
        case 209:
        
        case 210:
        
        case 211:
        
        case 212:
        
        case 213:
        
        case 214:
        
        case 215:
        
        case 216:
        
        case 217:
        
        case 218:
        
        case 219:
        
        case 220:
        
        case 221:
        
        case 222:
        
        case 223:
        
        case 224:
        
        case 225:
        
        case 226:
        
        case 227:
        
        case 228:
        
        case 229:
        
        case 230:
        
        case 231:
        
        case 232:
        
        case 233:
        
        case 234:
        
        case 235:
        
        case 236:
        
        case 237:
        
        case 238:
        
        case 239:
        
        case 240:
        
        case 241:
        
        case 242:
        
        case 243:
        
        case 244:
        
        case 245:
        
        case 246:
        
        case 247:
        
        case 248:
        
        case 249:
        
        case 250:
        
        case 251:
        
        case 252:
        
        case 253:
        
        case 254:
        
        default:
          break;
      } 
      byte b1 = 107;
      int j = (paramInt2 & 0xFF) - b1;
      if (j < 0)
        j += 256; 
      int k = ((paramInt2 & 0xFFFF) >>> 8) - b1;
      if (k < 0)
        k += 256; 
      for (byte b2 = 0; b2 < arrayOfChar.length; b2++) {
        int m = b2 % 2;
        if (m == 0) {
          arrayOfChar[b2] = (char)(arrayOfChar[b2] ^ j);
          j = ((j >>> 3 | j << 5) ^ arrayOfChar[b2]) & 0xFF;
        } else {
          arrayOfChar[b2] = (char)(arrayOfChar[b2] ^ k);
          k = ((k >>> 3 | k << 5) ^ arrayOfChar[b2]) & 0xFF;
        } 
      } 
      b[i] = (new String(arrayOfChar)).intern();
    } 
    return b[i];
  }
}


/* Location:              C:\Program Files\BurpSuitePro\burpsuite_pro.jar!\burp\Zg5r.class
 * Java compiler version: 21 (65.0)
 * JD-Core Version:       1.1.3
 */