package burp;

import java.math.BigInteger;

class Zg61 extends ClassLoader {
  static Object Zp;
  
  static String ZX;
  
  private static final String[] a;
  
  private static final String[] b;
  
  static boolean ZW(Object[] paramArrayOfObject, Object paramObject) throws Throwable {
    // Byte code:
    //   0: invokestatic ZK : ()Z
    //   3: istore_2
    //   4: new java/lang/StringBuilder
    //   7: dup
    //   8: invokespecial <init> : ()V
    //   11: astore_3
    //   12: iconst_0
    //   13: istore #4
    //   15: iload #4
    //   17: bipush #32
    //   19: if_icmpge -> 1355
    //   22: iload #4
    //   24: tableswitch default -> 1348, 0 -> 168, 1 -> 205, 2 -> 242, 3 -> 279, 4 -> 316, 5 -> 353, 6 -> 390, 7 -> 427, 8 -> 464, 9 -> 501, 10 -> 538, 11 -> 575, 12 -> 612, 13 -> 649, 14 -> 686, 15 -> 723, 16 -> 760, 17 -> 797, 18 -> 834, 19 -> 871, 20 -> 908, 21 -> 945, 22 -> 982, 23 -> 1019, 24 -> 1056, 25 -> 1093, 26 -> 1130, 27 -> 1167, 28 -> 1204, 29 -> 1241, 30 -> 1278, 31 -> 1315
    //   168: aload_3
    //   169: getstatic burp/Zm63.Zs : Ljava/lang/String;
    //   172: getstatic burp/Zbl4.ZW : Ljava/lang/Object;
    //   175: checkcast java/math/BigInteger
    //   178: invokevirtual intValue : ()I
    //   181: bipush #32
    //   183: irem
    //   184: invokestatic abs : (I)I
    //   187: invokevirtual charAt : (I)C
    //   190: invokevirtual append : (C)Ljava/lang/StringBuilder;
    //   193: pop
    //   194: iload_2
    //   195: ifeq -> 1348
    //   198: goto -> 205
    //   201: invokestatic a : (Ljava/lang/Throwable;)Ljava/lang/Throwable;
    //   204: athrow
    //   205: aload_3
    //   206: getstatic burp/Zmyk.Zx : Ljava/lang/String;
    //   209: getstatic burp/Zrov.Zk : Ljava/lang/Object;
    //   212: checkcast java/math/BigInteger
    //   215: invokevirtual intValue : ()I
    //   218: bipush #32
    //   220: irem
    //   221: invokestatic abs : (I)I
    //   224: invokevirtual charAt : (I)C
    //   227: invokevirtual append : (C)Ljava/lang/StringBuilder;
    //   230: pop
    //   231: iload_2
    //   232: ifeq -> 1348
    //   235: goto -> 242
    //   238: invokestatic a : (Ljava/lang/Throwable;)Ljava/lang/Throwable;
    //   241: athrow
    //   242: aload_3
    //   243: getstatic burp/Zmdf.Zo : Ljava/lang/String;
    //   246: getstatic burp/Zxdy.ZZ : Ljava/lang/Object;
    //   249: checkcast java/math/BigInteger
    //   252: invokevirtual intValue : ()I
    //   255: bipush #32
    //   257: irem
    //   258: invokestatic abs : (I)I
    //   261: invokevirtual charAt : (I)C
    //   264: invokevirtual append : (C)Ljava/lang/StringBuilder;
    //   267: pop
    //   268: iload_2
    //   269: ifeq -> 1348
    //   272: goto -> 279
    //   275: invokestatic a : (Ljava/lang/Throwable;)Ljava/lang/Throwable;
    //   278: athrow
    //   279: aload_3
    //   280: getstatic burp/Zrle.ZG : Ljava/lang/String;
    //   283: getstatic burp/Zegv.ZL : Ljava/lang/Object;
    //   286: checkcast java/math/BigInteger
    //   289: invokevirtual intValue : ()I
    //   292: bipush #32
    //   294: irem
    //   295: invokestatic abs : (I)I
    //   298: invokevirtual charAt : (I)C
    //   301: invokevirtual append : (C)Ljava/lang/StringBuilder;
    //   304: pop
    //   305: iload_2
    //   306: ifeq -> 1348
    //   309: goto -> 316
    //   312: invokestatic a : (Ljava/lang/Throwable;)Ljava/lang/Throwable;
    //   315: athrow
    //   316: aload_3
    //   317: getstatic burp/Zb3r.Zo : Ljava/lang/String;
    //   320: getstatic burp/Ztzj.Zv : Ljava/lang/Object;
    //   323: checkcast java/math/BigInteger
    //   326: invokevirtual intValue : ()I
    //   329: bipush #32
    //   331: irem
    //   332: invokestatic abs : (I)I
    //   335: invokevirtual charAt : (I)C
    //   338: invokevirtual append : (C)Ljava/lang/StringBuilder;
    //   341: pop
    //   342: iload_2
    //   343: ifeq -> 1348
    //   346: goto -> 353
    //   349: invokestatic a : (Ljava/lang/Throwable;)Ljava/lang/Throwable;
    //   352: athrow
    //   353: aload_3
    //   354: getstatic burp/Zml9.Zw : Ljava/lang/String;
    //   357: getstatic burp/Ztnn.ZA : Ljava/lang/Object;
    //   360: checkcast java/math/BigInteger
    //   363: invokevirtual intValue : ()I
    //   366: bipush #32
    //   368: irem
    //   369: invokestatic abs : (I)I
    //   372: invokevirtual charAt : (I)C
    //   375: invokevirtual append : (C)Ljava/lang/StringBuilder;
    //   378: pop
    //   379: iload_2
    //   380: ifeq -> 1348
    //   383: goto -> 390
    //   386: invokestatic a : (Ljava/lang/Throwable;)Ljava/lang/Throwable;
    //   389: athrow
    //   390: aload_3
    //   391: getstatic burp/Zezi.Ze : Ljava/lang/String;
    //   394: getstatic burp/Zr02.ZB : Ljava/lang/Object;
    //   397: checkcast java/math/BigInteger
    //   400: invokevirtual intValue : ()I
    //   403: bipush #32
    //   405: irem
    //   406: invokestatic abs : (I)I
    //   409: invokevirtual charAt : (I)C
    //   412: invokevirtual append : (C)Ljava/lang/StringBuilder;
    //   415: pop
    //   416: iload_2
    //   417: ifeq -> 1348
    //   420: goto -> 427
    //   423: invokestatic a : (Ljava/lang/Throwable;)Ljava/lang/Throwable;
    //   426: athrow
    //   427: aload_3
    //   428: getstatic burp/Zld5.ZO : Ljava/lang/String;
    //   431: getstatic burp/Zea8.ZF : Ljava/lang/Object;
    //   434: checkcast java/math/BigInteger
    //   437: invokevirtual intValue : ()I
    //   440: bipush #32
    //   442: irem
    //   443: invokestatic abs : (I)I
    //   446: invokevirtual charAt : (I)C
    //   449: invokevirtual append : (C)Ljava/lang/StringBuilder;
    //   452: pop
    //   453: iload_2
    //   454: ifeq -> 1348
    //   457: goto -> 464
    //   460: invokestatic a : (Ljava/lang/Throwable;)Ljava/lang/Throwable;
    //   463: athrow
    //   464: aload_3
    //   465: getstatic burp/Zkhf.Zb : Ljava/lang/String;
    //   468: getstatic burp/Ze4a.ZP : Ljava/lang/Object;
    //   471: checkcast java/math/BigInteger
    //   474: invokevirtual intValue : ()I
    //   477: bipush #32
    //   479: irem
    //   480: invokestatic abs : (I)I
    //   483: invokevirtual charAt : (I)C
    //   486: invokevirtual append : (C)Ljava/lang/StringBuilder;
    //   489: pop
    //   490: iload_2
    //   491: ifeq -> 1348
    //   494: goto -> 501
    //   497: invokestatic a : (Ljava/lang/Throwable;)Ljava/lang/Throwable;
    //   500: athrow
    //   501: aload_3
    //   502: getstatic burp/Znu.ZF : Ljava/lang/String;
    //   505: getstatic burp/Zlxw.Zi : Ljava/lang/Object;
    //   508: checkcast java/math/BigInteger
    //   511: invokevirtual intValue : ()I
    //   514: bipush #32
    //   516: irem
    //   517: invokestatic abs : (I)I
    //   520: invokevirtual charAt : (I)C
    //   523: invokevirtual append : (C)Ljava/lang/StringBuilder;
    //   526: pop
    //   527: iload_2
    //   528: ifeq -> 1348
    //   531: goto -> 538
    //   534: invokestatic a : (Ljava/lang/Throwable;)Ljava/lang/Throwable;
    //   537: athrow
    //   538: aload_3
    //   539: getstatic burp/Zg1l.Zl : Ljava/lang/String;
    //   542: getstatic burp/Zt6z.Zl : Ljava/lang/Object;
    //   545: checkcast java/math/BigInteger
    //   548: invokevirtual intValue : ()I
    //   551: bipush #32
    //   553: irem
    //   554: invokestatic abs : (I)I
    //   557: invokevirtual charAt : (I)C
    //   560: invokevirtual append : (C)Ljava/lang/StringBuilder;
    //   563: pop
    //   564: iload_2
    //   565: ifeq -> 1348
    //   568: goto -> 575
    //   571: invokestatic a : (Ljava/lang/Throwable;)Ljava/lang/Throwable;
    //   574: athrow
    //   575: aload_3
    //   576: getstatic burp/Zrb6.ZP : Ljava/lang/String;
    //   579: getstatic burp/Zs5y.Zd : Ljava/lang/Object;
    //   582: checkcast java/math/BigInteger
    //   585: invokevirtual intValue : ()I
    //   588: bipush #32
    //   590: irem
    //   591: invokestatic abs : (I)I
    //   594: invokevirtual charAt : (I)C
    //   597: invokevirtual append : (C)Ljava/lang/StringBuilder;
    //   600: pop
    //   601: iload_2
    //   602: ifeq -> 1348
    //   605: goto -> 612
    //   608: invokestatic a : (Ljava/lang/Throwable;)Ljava/lang/Throwable;
    //   611: athrow
    //   612: aload_3
    //   613: getstatic burp/Zsn4.ZZ : Ljava/lang/String;
    //   616: getstatic burp/Zz41.Zv : Ljava/lang/Object;
    //   619: checkcast java/math/BigInteger
    //   622: invokevirtual intValue : ()I
    //   625: bipush #32
    //   627: irem
    //   628: invokestatic abs : (I)I
    //   631: invokevirtual charAt : (I)C
    //   634: invokevirtual append : (C)Ljava/lang/StringBuilder;
    //   637: pop
    //   638: iload_2
    //   639: ifeq -> 1348
    //   642: goto -> 649
    //   645: invokestatic a : (Ljava/lang/Throwable;)Ljava/lang/Throwable;
    //   648: athrow
    //   649: aload_3
    //   650: getstatic burp/Zea8.ZE : Ljava/lang/String;
    //   653: getstatic burp/Zgi9.Zc : Ljava/lang/Object;
    //   656: checkcast java/math/BigInteger
    //   659: invokevirtual intValue : ()I
    //   662: bipush #32
    //   664: irem
    //   665: invokestatic abs : (I)I
    //   668: invokevirtual charAt : (I)C
    //   671: invokevirtual append : (C)Ljava/lang/StringBuilder;
    //   674: pop
    //   675: iload_2
    //   676: ifeq -> 1348
    //   679: goto -> 686
    //   682: invokestatic a : (Ljava/lang/Throwable;)Ljava/lang/Throwable;
    //   685: athrow
    //   686: aload_3
    //   687: getstatic burp/Zg6z.ZY : Ljava/lang/String;
    //   690: getstatic burp/Zrex.Zr : Ljava/lang/Object;
    //   693: checkcast java/math/BigInteger
    //   696: invokevirtual intValue : ()I
    //   699: bipush #32
    //   701: irem
    //   702: invokestatic abs : (I)I
    //   705: invokevirtual charAt : (I)C
    //   708: invokevirtual append : (C)Ljava/lang/StringBuilder;
    //   711: pop
    //   712: iload_2
    //   713: ifeq -> 1348
    //   716: goto -> 723
    //   719: invokestatic a : (Ljava/lang/Throwable;)Ljava/lang/Throwable;
    //   722: athrow
    //   723: aload_3
    //   724: getstatic burp/Zx4u.ZL : Ljava/lang/String;
    //   727: getstatic burp/Zr02.ZB : Ljava/lang/Object;
    //   730: checkcast java/math/BigInteger
    //   733: invokevirtual intValue : ()I
    //   736: bipush #32
    //   738: irem
    //   739: invokestatic abs : (I)I
    //   742: invokevirtual charAt : (I)C
    //   745: invokevirtual append : (C)Ljava/lang/StringBuilder;
    //   748: pop
    //   749: iload_2
    //   750: ifeq -> 1348
    //   753: goto -> 760
    //   756: invokestatic a : (Ljava/lang/Throwable;)Ljava/lang/Throwable;
    //   759: athrow
    //   760: aload_3
    //   761: getstatic burp/Ze4g.Zk : Ljava/lang/String;
    //   764: getstatic burp/Zsbv.Zl : Ljava/lang/Object;
    //   767: checkcast java/math/BigInteger
    //   770: invokevirtual intValue : ()I
    //   773: bipush #32
    //   775: irem
    //   776: invokestatic abs : (I)I
    //   779: invokevirtual charAt : (I)C
    //   782: invokevirtual append : (C)Ljava/lang/StringBuilder;
    //   785: pop
    //   786: iload_2
    //   787: ifeq -> 1348
    //   790: goto -> 797
    //   793: invokestatic a : (Ljava/lang/Throwable;)Ljava/lang/Throwable;
    //   796: athrow
    //   797: aload_3
    //   798: getstatic burp/Zbsz.Zu : Ljava/lang/String;
    //   801: getstatic burp/Zg0q.Zf : Ljava/lang/Object;
    //   804: checkcast java/math/BigInteger
    //   807: invokevirtual intValue : ()I
    //   810: bipush #32
    //   812: irem
    //   813: invokestatic abs : (I)I
    //   816: invokevirtual charAt : (I)C
    //   819: invokevirtual append : (C)Ljava/lang/StringBuilder;
    //   822: pop
    //   823: iload_2
    //   824: ifeq -> 1348
    //   827: goto -> 834
    //   830: invokestatic a : (Ljava/lang/Throwable;)Ljava/lang/Throwable;
    //   833: athrow
    //   834: aload_3
    //   835: getstatic burp/Zs0h.ZX : Ljava/lang/String;
    //   838: getstatic burp/Zk92.Zn : Ljava/lang/Object;
    //   841: checkcast java/math/BigInteger
    //   844: invokevirtual intValue : ()I
    //   847: bipush #32
    //   849: irem
    //   850: invokestatic abs : (I)I
    //   853: invokevirtual charAt : (I)C
    //   856: invokevirtual append : (C)Ljava/lang/StringBuilder;
    //   859: pop
    //   860: iload_2
    //   861: ifeq -> 1348
    //   864: goto -> 871
    //   867: invokestatic a : (Ljava/lang/Throwable;)Ljava/lang/Throwable;
    //   870: athrow
    //   871: aload_3
    //   872: getstatic burp/Zd9.Ze : Ljava/lang/String;
    //   875: getstatic burp/Zr36.Za : Ljava/lang/Object;
    //   878: checkcast java/math/BigInteger
    //   881: invokevirtual intValue : ()I
    //   884: bipush #32
    //   886: irem
    //   887: invokestatic abs : (I)I
    //   890: invokevirtual charAt : (I)C
    //   893: invokevirtual append : (C)Ljava/lang/StringBuilder;
    //   896: pop
    //   897: iload_2
    //   898: ifeq -> 1348
    //   901: goto -> 908
    //   904: invokestatic a : (Ljava/lang/Throwable;)Ljava/lang/Throwable;
    //   907: athrow
    //   908: aload_3
    //   909: getstatic burp/Zr14.ZL : Ljava/lang/String;
    //   912: getstatic burp/Zmyk.Za : Ljava/lang/Object;
    //   915: checkcast java/math/BigInteger
    //   918: invokevirtual intValue : ()I
    //   921: bipush #32
    //   923: irem
    //   924: invokestatic abs : (I)I
    //   927: invokevirtual charAt : (I)C
    //   930: invokevirtual append : (C)Ljava/lang/StringBuilder;
    //   933: pop
    //   934: iload_2
    //   935: ifeq -> 1348
    //   938: goto -> 945
    //   941: invokestatic a : (Ljava/lang/Throwable;)Ljava/lang/Throwable;
    //   944: athrow
    //   945: aload_3
    //   946: getstatic burp/Zzah.Zs : Ljava/lang/String;
    //   949: getstatic burp/Zkeb.ZH : Ljava/lang/Object;
    //   952: checkcast java/math/BigInteger
    //   955: invokevirtual intValue : ()I
    //   958: bipush #32
    //   960: irem
    //   961: invokestatic abs : (I)I
    //   964: invokevirtual charAt : (I)C
    //   967: invokevirtual append : (C)Ljava/lang/StringBuilder;
    //   970: pop
    //   971: iload_2
    //   972: ifeq -> 1348
    //   975: goto -> 982
    //   978: invokestatic a : (Ljava/lang/Throwable;)Ljava/lang/Throwable;
    //   981: athrow
    //   982: aload_3
    //   983: getstatic burp/Zlf7.ZM : Ljava/lang/String;
    //   986: getstatic burp/Zb3d.Zw : Ljava/lang/Object;
    //   989: checkcast java/math/BigInteger
    //   992: invokevirtual intValue : ()I
    //   995: bipush #32
    //   997: irem
    //   998: invokestatic abs : (I)I
    //   1001: invokevirtual charAt : (I)C
    //   1004: invokevirtual append : (C)Ljava/lang/StringBuilder;
    //   1007: pop
    //   1008: iload_2
    //   1009: ifeq -> 1348
    //   1012: goto -> 1019
    //   1015: invokestatic a : (Ljava/lang/Throwable;)Ljava/lang/Throwable;
    //   1018: athrow
    //   1019: aload_3
    //   1020: getstatic burp/Zlbd.Zq : Ljava/lang/String;
    //   1023: getstatic burp/Zxju.ZN : Ljava/lang/Object;
    //   1026: checkcast java/math/BigInteger
    //   1029: invokevirtual intValue : ()I
    //   1032: bipush #32
    //   1034: irem
    //   1035: invokestatic abs : (I)I
    //   1038: invokevirtual charAt : (I)C
    //   1041: invokevirtual append : (C)Ljava/lang/StringBuilder;
    //   1044: pop
    //   1045: iload_2
    //   1046: ifeq -> 1348
    //   1049: goto -> 1056
    //   1052: invokestatic a : (Ljava/lang/Throwable;)Ljava/lang/Throwable;
    //   1055: athrow
    //   1056: aload_3
    //   1057: getstatic burp/Zz0y.ZM : Ljava/lang/String;
    //   1060: getstatic burp/Zmlr.Zh : Ljava/lang/Object;
    //   1063: checkcast java/math/BigInteger
    //   1066: invokevirtual intValue : ()I
    //   1069: bipush #32
    //   1071: irem
    //   1072: invokestatic abs : (I)I
    //   1075: invokevirtual charAt : (I)C
    //   1078: invokevirtual append : (C)Ljava/lang/StringBuilder;
    //   1081: pop
    //   1082: iload_2
    //   1083: ifeq -> 1348
    //   1086: goto -> 1093
    //   1089: invokestatic a : (Ljava/lang/Throwable;)Ljava/lang/Throwable;
    //   1092: athrow
    //   1093: aload_3
    //   1094: getstatic burp/Zmtr.Zd : Ljava/lang/String;
    //   1097: getstatic burp/Zs4g.ZC : Ljava/lang/Object;
    //   1100: checkcast java/math/BigInteger
    //   1103: invokevirtual intValue : ()I
    //   1106: bipush #32
    //   1108: irem
    //   1109: invokestatic abs : (I)I
    //   1112: invokevirtual charAt : (I)C
    //   1115: invokevirtual append : (C)Ljava/lang/StringBuilder;
    //   1118: pop
    //   1119: iload_2
    //   1120: ifeq -> 1348
    //   1123: goto -> 1130
    //   1126: invokestatic a : (Ljava/lang/Throwable;)Ljava/lang/Throwable;
    //   1129: athrow
    //   1130: aload_3
    //   1131: getstatic burp/Zml9.Zw : Ljava/lang/String;
    //   1134: getstatic burp/Zrom.ZF : Ljava/lang/Object;
    //   1137: checkcast java/math/BigInteger
    //   1140: invokevirtual intValue : ()I
    //   1143: bipush #32
    //   1145: irem
    //   1146: invokestatic abs : (I)I
    //   1149: invokevirtual charAt : (I)C
    //   1152: invokevirtual append : (C)Ljava/lang/StringBuilder;
    //   1155: pop
    //   1156: iload_2
    //   1157: ifeq -> 1348
    //   1160: goto -> 1167
    //   1163: invokestatic a : (Ljava/lang/Throwable;)Ljava/lang/Throwable;
    //   1166: athrow
    //   1167: aload_3
    //   1168: getstatic burp/Zb3r.Zo : Ljava/lang/String;
    //   1171: getstatic burp/Zsn4.ZQ : Ljava/lang/Object;
    //   1174: checkcast java/math/BigInteger
    //   1177: invokevirtual intValue : ()I
    //   1180: bipush #32
    //   1182: irem
    //   1183: invokestatic abs : (I)I
    //   1186: invokevirtual charAt : (I)C
    //   1189: invokevirtual append : (C)Ljava/lang/StringBuilder;
    //   1192: pop
    //   1193: iload_2
    //   1194: ifeq -> 1348
    //   1197: goto -> 1204
    //   1200: invokestatic a : (Ljava/lang/Throwable;)Ljava/lang/Throwable;
    //   1203: athrow
    //   1204: aload_3
    //   1205: getstatic burp/Zr1t.Ze : Ljava/lang/String;
    //   1208: getstatic burp/Zx5w.Zo : Ljava/lang/Object;
    //   1211: checkcast java/math/BigInteger
    //   1214: invokevirtual intValue : ()I
    //   1217: bipush #32
    //   1219: irem
    //   1220: invokestatic abs : (I)I
    //   1223: invokevirtual charAt : (I)C
    //   1226: invokevirtual append : (C)Ljava/lang/StringBuilder;
    //   1229: pop
    //   1230: iload_2
    //   1231: ifeq -> 1348
    //   1234: goto -> 1241
    //   1237: invokestatic a : (Ljava/lang/Throwable;)Ljava/lang/Throwable;
    //   1240: athrow
    //   1241: aload_3
    //   1242: getstatic burp/Zlbd.Zq : Ljava/lang/String;
    //   1245: getstatic burp/Zkdx.Zn : Ljava/lang/Object;
    //   1248: checkcast java/math/BigInteger
    //   1251: invokevirtual intValue : ()I
    //   1254: bipush #32
    //   1256: irem
    //   1257: invokestatic abs : (I)I
    //   1260: invokevirtual charAt : (I)C
    //   1263: invokevirtual append : (C)Ljava/lang/StringBuilder;
    //   1266: pop
    //   1267: iload_2
    //   1268: ifeq -> 1348
    //   1271: goto -> 1278
    //   1274: invokestatic a : (Ljava/lang/Throwable;)Ljava/lang/Throwable;
    //   1277: athrow
    //   1278: aload_3
    //   1279: getstatic burp/Zb3r.Zo : Ljava/lang/String;
    //   1282: getstatic burp/Zku9.Zp : Ljava/lang/Object;
    //   1285: checkcast java/math/BigInteger
    //   1288: invokevirtual intValue : ()I
    //   1291: bipush #32
    //   1293: irem
    //   1294: invokestatic abs : (I)I
    //   1297: invokevirtual charAt : (I)C
    //   1300: invokevirtual append : (C)Ljava/lang/StringBuilder;
    //   1303: pop
    //   1304: iload_2
    //   1305: ifeq -> 1348
    //   1308: goto -> 1315
    //   1311: invokestatic a : (Ljava/lang/Throwable;)Ljava/lang/Throwable;
    //   1314: athrow
    //   1315: aload_3
    //   1316: getstatic burp/Zbnz.Zp : Ljava/lang/String;
    //   1319: getstatic burp/Ztvy.ZH : Ljava/lang/Object;
    //   1322: checkcast java/math/BigInteger
    //   1325: invokevirtual intValue : ()I
    //   1328: bipush #32
    //   1330: irem
    //   1331: invokestatic abs : (I)I
    //   1334: invokevirtual charAt : (I)C
    //   1337: invokevirtual append : (C)Ljava/lang/StringBuilder;
    //   1340: pop
    //   1341: goto -> 1348
    //   1344: invokestatic a : (Ljava/lang/Throwable;)Ljava/lang/Throwable;
    //   1347: athrow
    //   1348: iinc #4, 1
    //   1351: iload_2
    //   1352: ifeq -> 15
    //   1355: aload_3
    //   1356: invokevirtual toString : ()Ljava/lang/String;
    //   1359: putstatic burp/Zb9q.Zk : Ljava/lang/String;
    //   1362: getstatic burp/Zti7.Zw : Ljava/lang/Object;
    //   1365: checkcast java/math/BigInteger
    //   1368: getstatic burp/Zrqe.ZX : Ljava/lang/Object;
    //   1371: checkcast java/math/BigInteger
    //   1374: invokevirtual add : (Ljava/math/BigInteger;)Ljava/math/BigInteger;
    //   1377: putstatic burp/Zbx5.ZL : Ljava/lang/Object;
    //   1380: new java/lang/StringBuilder
    //   1383: dup
    //   1384: invokespecial <init> : ()V
    //   1387: astore #4
    //   1389: iconst_0
    //   1390: istore #5
    //   1392: iload #5
    //   1394: bipush #32
    //   1396: if_icmpge -> 2763
    //   1399: iload #5
    //   1401: tableswitch default -> 2756, 0 -> 1544, 1 -> 1582, 2 -> 1620, 3 -> 1658, 4 -> 1696, 5 -> 1734, 6 -> 1772, 7 -> 1810, 8 -> 1848, 9 -> 1886, 10 -> 1924, 11 -> 1962, 12 -> 2000, 13 -> 2038, 14 -> 2076, 15 -> 2114, 16 -> 2152, 17 -> 2190, 18 -> 2228, 19 -> 2266, 20 -> 2304, 21 -> 2342, 22 -> 2380, 23 -> 2418, 24 -> 2456, 25 -> 2494, 26 -> 2532, 27 -> 2570, 28 -> 2608, 29 -> 2646, 30 -> 2684, 31 -> 2722
    //   1544: aload #4
    //   1546: getstatic burp/Zes.ZW : Ljava/lang/String;
    //   1549: getstatic burp/Zs_m.Z_ : Ljava/lang/Object;
    //   1552: checkcast java/math/BigInteger
    //   1555: invokevirtual intValue : ()I
    //   1558: bipush #32
    //   1560: irem
    //   1561: invokestatic abs : (I)I
    //   1564: invokevirtual charAt : (I)C
    //   1567: invokevirtual append : (C)Ljava/lang/StringBuilder;
    //   1570: pop
    //   1571: iload_2
    //   1572: ifeq -> 2756
    //   1575: goto -> 1582
    //   1578: invokestatic a : (Ljava/lang/Throwable;)Ljava/lang/Throwable;
    //   1581: athrow
    //   1582: aload #4
    //   1584: getstatic burp/Zly9.ZS : Ljava/lang/String;
    //   1587: getstatic burp/Zspg.ZJ : Ljava/lang/Object;
    //   1590: checkcast java/math/BigInteger
    //   1593: invokevirtual intValue : ()I
    //   1596: bipush #32
    //   1598: irem
    //   1599: invokestatic abs : (I)I
    //   1602: invokevirtual charAt : (I)C
    //   1605: invokevirtual append : (C)Ljava/lang/StringBuilder;
    //   1608: pop
    //   1609: iload_2
    //   1610: ifeq -> 2756
    //   1613: goto -> 1620
    //   1616: invokestatic a : (Ljava/lang/Throwable;)Ljava/lang/Throwable;
    //   1619: athrow
    //   1620: aload #4
    //   1622: getstatic burp/Zml9.Zw : Ljava/lang/String;
    //   1625: getstatic burp/Zbss.Zh : Ljava/lang/Object;
    //   1628: checkcast java/math/BigInteger
    //   1631: invokevirtual intValue : ()I
    //   1634: bipush #32
    //   1636: irem
    //   1637: invokestatic abs : (I)I
    //   1640: invokevirtual charAt : (I)C
    //   1643: invokevirtual append : (C)Ljava/lang/StringBuilder;
    //   1646: pop
    //   1647: iload_2
    //   1648: ifeq -> 2756
    //   1651: goto -> 1658
    //   1654: invokestatic a : (Ljava/lang/Throwable;)Ljava/lang/Throwable;
    //   1657: athrow
    //   1658: aload #4
    //   1660: getstatic burp/Zlid.ZU : Ljava/lang/String;
    //   1663: getstatic burp/Zmh3.ZF : Ljava/lang/Object;
    //   1666: checkcast java/math/BigInteger
    //   1669: invokevirtual intValue : ()I
    //   1672: bipush #32
    //   1674: irem
    //   1675: invokestatic abs : (I)I
    //   1678: invokevirtual charAt : (I)C
    //   1681: invokevirtual append : (C)Ljava/lang/StringBuilder;
    //   1684: pop
    //   1685: iload_2
    //   1686: ifeq -> 2756
    //   1689: goto -> 1696
    //   1692: invokestatic a : (Ljava/lang/Throwable;)Ljava/lang/Throwable;
    //   1695: athrow
    //   1696: aload #4
    //   1698: getstatic burp/Ze7e.Zc : Ljava/lang/String;
    //   1701: getstatic burp/Zs4g.ZC : Ljava/lang/Object;
    //   1704: checkcast java/math/BigInteger
    //   1707: invokevirtual intValue : ()I
    //   1710: bipush #32
    //   1712: irem
    //   1713: invokestatic abs : (I)I
    //   1716: invokevirtual charAt : (I)C
    //   1719: invokevirtual append : (C)Ljava/lang/StringBuilder;
    //   1722: pop
    //   1723: iload_2
    //   1724: ifeq -> 2756
    //   1727: goto -> 1734
    //   1730: invokestatic a : (Ljava/lang/Throwable;)Ljava/lang/Throwable;
    //   1733: athrow
    //   1734: aload #4
    //   1736: getstatic burp/Zmlr.ZJ : Ljava/lang/String;
    //   1739: getstatic burp/Ze6w.Ze : Ljava/lang/Object;
    //   1742: checkcast java/math/BigInteger
    //   1745: invokevirtual intValue : ()I
    //   1748: bipush #32
    //   1750: irem
    //   1751: invokestatic abs : (I)I
    //   1754: invokevirtual charAt : (I)C
    //   1757: invokevirtual append : (C)Ljava/lang/StringBuilder;
    //   1760: pop
    //   1761: iload_2
    //   1762: ifeq -> 2756
    //   1765: goto -> 1772
    //   1768: invokestatic a : (Ljava/lang/Throwable;)Ljava/lang/Throwable;
    //   1771: athrow
    //   1772: aload #4
    //   1774: getstatic burp/Zrqe.ZB : Ljava/lang/String;
    //   1777: getstatic burp/Zb87.Zb : Ljava/lang/Object;
    //   1780: checkcast java/math/BigInteger
    //   1783: invokevirtual intValue : ()I
    //   1786: bipush #32
    //   1788: irem
    //   1789: invokestatic abs : (I)I
    //   1792: invokevirtual charAt : (I)C
    //   1795: invokevirtual append : (C)Ljava/lang/StringBuilder;
    //   1798: pop
    //   1799: iload_2
    //   1800: ifeq -> 2756
    //   1803: goto -> 1810
    //   1806: invokestatic a : (Ljava/lang/Throwable;)Ljava/lang/Throwable;
    //   1809: athrow
    //   1810: aload #4
    //   1812: getstatic burp/Zry1.Zk : Ljava/lang/String;
    //   1815: getstatic burp/Zmli.Zh : Ljava/lang/Object;
    //   1818: checkcast java/math/BigInteger
    //   1821: invokevirtual intValue : ()I
    //   1824: bipush #32
    //   1826: irem
    //   1827: invokestatic abs : (I)I
    //   1830: invokevirtual charAt : (I)C
    //   1833: invokevirtual append : (C)Ljava/lang/StringBuilder;
    //   1836: pop
    //   1837: iload_2
    //   1838: ifeq -> 2756
    //   1841: goto -> 1848
    //   1844: invokestatic a : (Ljava/lang/Throwable;)Ljava/lang/Throwable;
    //   1847: athrow
    //   1848: aload #4
    //   1850: getstatic burp/Zg7u.ZA : Ljava/lang/String;
    //   1853: getstatic burp/Zlwj.ZE : Ljava/lang/Object;
    //   1856: checkcast java/math/BigInteger
    //   1859: invokevirtual intValue : ()I
    //   1862: bipush #32
    //   1864: irem
    //   1865: invokestatic abs : (I)I
    //   1868: invokevirtual charAt : (I)C
    //   1871: invokevirtual append : (C)Ljava/lang/StringBuilder;
    //   1874: pop
    //   1875: iload_2
    //   1876: ifeq -> 2756
    //   1879: goto -> 1886
    //   1882: invokestatic a : (Ljava/lang/Throwable;)Ljava/lang/Throwable;
    //   1885: athrow
    //   1886: aload #4
    //   1888: getstatic burp/Zlt1.ZA : Ljava/lang/String;
    //   1891: getstatic burp/Zmll.ZU : Ljava/lang/Object;
    //   1894: checkcast java/math/BigInteger
    //   1897: invokevirtual intValue : ()I
    //   1900: bipush #32
    //   1902: irem
    //   1903: invokestatic abs : (I)I
    //   1906: invokevirtual charAt : (I)C
    //   1909: invokevirtual append : (C)Ljava/lang/StringBuilder;
    //   1912: pop
    //   1913: iload_2
    //   1914: ifeq -> 2756
    //   1917: goto -> 1924
    //   1920: invokestatic a : (Ljava/lang/Throwable;)Ljava/lang/Throwable;
    //   1923: athrow
    //   1924: aload #4
    //   1926: getstatic burp/Zlwc.ZM : Ljava/lang/String;
    //   1929: getstatic burp/Zrn4.Zq : Ljava/lang/Object;
    //   1932: checkcast java/math/BigInteger
    //   1935: invokevirtual intValue : ()I
    //   1938: bipush #32
    //   1940: irem
    //   1941: invokestatic abs : (I)I
    //   1944: invokevirtual charAt : (I)C
    //   1947: invokevirtual append : (C)Ljava/lang/StringBuilder;
    //   1950: pop
    //   1951: iload_2
    //   1952: ifeq -> 2756
    //   1955: goto -> 1962
    //   1958: invokestatic a : (Ljava/lang/Throwable;)Ljava/lang/Throwable;
    //   1961: athrow
    //   1962: aload #4
    //   1964: getstatic burp/Zsn3.ZS : Ljava/lang/String;
    //   1967: getstatic burp/Zzi_.Zf : Ljava/lang/Object;
    //   1970: checkcast java/math/BigInteger
    //   1973: invokevirtual intValue : ()I
    //   1976: bipush #32
    //   1978: irem
    //   1979: invokestatic abs : (I)I
    //   1982: invokevirtual charAt : (I)C
    //   1985: invokevirtual append : (C)Ljava/lang/StringBuilder;
    //   1988: pop
    //   1989: iload_2
    //   1990: ifeq -> 2756
    //   1993: goto -> 2000
    //   1996: invokestatic a : (Ljava/lang/Throwable;)Ljava/lang/Throwable;
    //   1999: athrow
    //   2000: aload #4
    //   2002: getstatic burp/Zrm6.ZV : Ljava/lang/String;
    //   2005: getstatic burp/Zrip.ZB : Ljava/lang/Object;
    //   2008: checkcast java/math/BigInteger
    //   2011: invokevirtual intValue : ()I
    //   2014: bipush #32
    //   2016: irem
    //   2017: invokestatic abs : (I)I
    //   2020: invokevirtual charAt : (I)C
    //   2023: invokevirtual append : (C)Ljava/lang/StringBuilder;
    //   2026: pop
    //   2027: iload_2
    //   2028: ifeq -> 2756
    //   2031: goto -> 2038
    //   2034: invokestatic a : (Ljava/lang/Throwable;)Ljava/lang/Throwable;
    //   2037: athrow
    //   2038: aload #4
    //   2040: getstatic burp/Zzac.ZE : Ljava/lang/String;
    //   2043: getstatic burp/Zs5y.Zd : Ljava/lang/Object;
    //   2046: checkcast java/math/BigInteger
    //   2049: invokevirtual intValue : ()I
    //   2052: bipush #32
    //   2054: irem
    //   2055: invokestatic abs : (I)I
    //   2058: invokevirtual charAt : (I)C
    //   2061: invokevirtual append : (C)Ljava/lang/StringBuilder;
    //   2064: pop
    //   2065: iload_2
    //   2066: ifeq -> 2756
    //   2069: goto -> 2076
    //   2072: invokestatic a : (Ljava/lang/Throwable;)Ljava/lang/Throwable;
    //   2075: athrow
    //   2076: aload #4
    //   2078: getstatic burp/Zoe.ZE : Ljava/lang/String;
    //   2081: getstatic burp/Zkf6.ZS : Ljava/lang/Object;
    //   2084: checkcast java/math/BigInteger
    //   2087: invokevirtual intValue : ()I
    //   2090: bipush #32
    //   2092: irem
    //   2093: invokestatic abs : (I)I
    //   2096: invokevirtual charAt : (I)C
    //   2099: invokevirtual append : (C)Ljava/lang/StringBuilder;
    //   2102: pop
    //   2103: iload_2
    //   2104: ifeq -> 2756
    //   2107: goto -> 2114
    //   2110: invokestatic a : (Ljava/lang/Throwable;)Ljava/lang/Throwable;
    //   2113: athrow
    //   2114: aload #4
    //   2116: getstatic burp/Zkql.ZR : Ljava/lang/String;
    //   2119: getstatic burp/Zz4j.Zu : Ljava/lang/Object;
    //   2122: checkcast java/math/BigInteger
    //   2125: invokevirtual intValue : ()I
    //   2128: bipush #32
    //   2130: irem
    //   2131: invokestatic abs : (I)I
    //   2134: invokevirtual charAt : (I)C
    //   2137: invokevirtual append : (C)Ljava/lang/StringBuilder;
    //   2140: pop
    //   2141: iload_2
    //   2142: ifeq -> 2756
    //   2145: goto -> 2152
    //   2148: invokestatic a : (Ljava/lang/Throwable;)Ljava/lang/Throwable;
    //   2151: athrow
    //   2152: aload #4
    //   2154: getstatic burp/Zxn9.ZU : Ljava/lang/String;
    //   2157: getstatic burp/Zlbd.ZU : Ljava/lang/Object;
    //   2160: checkcast java/math/BigInteger
    //   2163: invokevirtual intValue : ()I
    //   2166: bipush #32
    //   2168: irem
    //   2169: invokestatic abs : (I)I
    //   2172: invokevirtual charAt : (I)C
    //   2175: invokevirtual append : (C)Ljava/lang/StringBuilder;
    //   2178: pop
    //   2179: iload_2
    //   2180: ifeq -> 2756
    //   2183: goto -> 2190
    //   2186: invokestatic a : (Ljava/lang/Throwable;)Ljava/lang/Throwable;
    //   2189: athrow
    //   2190: aload #4
    //   2192: getstatic burp/Zg6z.ZY : Ljava/lang/String;
    //   2195: getstatic burp/Zt1h.Zb : Ljava/lang/Object;
    //   2198: checkcast java/math/BigInteger
    //   2201: invokevirtual intValue : ()I
    //   2204: bipush #32
    //   2206: irem
    //   2207: invokestatic abs : (I)I
    //   2210: invokevirtual charAt : (I)C
    //   2213: invokevirtual append : (C)Ljava/lang/StringBuilder;
    //   2216: pop
    //   2217: iload_2
    //   2218: ifeq -> 2756
    //   2221: goto -> 2228
    //   2224: invokestatic a : (Ljava/lang/Throwable;)Ljava/lang/Throwable;
    //   2227: athrow
    //   2228: aload #4
    //   2230: getstatic burp/Zsbv.Zr : Ljava/lang/String;
    //   2233: getstatic burp/Zs5y.Zd : Ljava/lang/Object;
    //   2236: checkcast java/math/BigInteger
    //   2239: invokevirtual intValue : ()I
    //   2242: bipush #32
    //   2244: irem
    //   2245: invokestatic abs : (I)I
    //   2248: invokevirtual charAt : (I)C
    //   2251: invokevirtual append : (C)Ljava/lang/StringBuilder;
    //   2254: pop
    //   2255: iload_2
    //   2256: ifeq -> 2756
    //   2259: goto -> 2266
    //   2262: invokestatic a : (Ljava/lang/Throwable;)Ljava/lang/Throwable;
    //   2265: athrow
    //   2266: aload #4
    //   2268: getstatic burp/Zgk9.Zf : Ljava/lang/String;
    //   2271: getstatic burp/Zlxw.Zi : Ljava/lang/Object;
    //   2274: checkcast java/math/BigInteger
    //   2277: invokevirtual intValue : ()I
    //   2280: bipush #32
    //   2282: irem
    //   2283: invokestatic abs : (I)I
    //   2286: invokevirtual charAt : (I)C
    //   2289: invokevirtual append : (C)Ljava/lang/StringBuilder;
    //   2292: pop
    //   2293: iload_2
    //   2294: ifeq -> 2756
    //   2297: goto -> 2304
    //   2300: invokestatic a : (Ljava/lang/Throwable;)Ljava/lang/Throwable;
    //   2303: athrow
    //   2304: aload #4
    //   2306: getstatic burp/Zsn4.ZZ : Ljava/lang/String;
    //   2309: getstatic burp/Zrh_.Zb : Ljava/lang/Object;
    //   2312: checkcast java/math/BigInteger
    //   2315: invokevirtual intValue : ()I
    //   2318: bipush #32
    //   2320: irem
    //   2321: invokestatic abs : (I)I
    //   2324: invokevirtual charAt : (I)C
    //   2327: invokevirtual append : (C)Ljava/lang/StringBuilder;
    //   2330: pop
    //   2331: iload_2
    //   2332: ifeq -> 2756
    //   2335: goto -> 2342
    //   2338: invokestatic a : (Ljava/lang/Throwable;)Ljava/lang/Throwable;
    //   2341: athrow
    //   2342: aload #4
    //   2344: getstatic burp/Zgio.ZS : Ljava/lang/String;
    //   2347: getstatic burp/Zedu.ZL : Ljava/lang/Object;
    //   2350: checkcast java/math/BigInteger
    //   2353: invokevirtual intValue : ()I
    //   2356: bipush #32
    //   2358: irem
    //   2359: invokestatic abs : (I)I
    //   2362: invokevirtual charAt : (I)C
    //   2365: invokevirtual append : (C)Ljava/lang/StringBuilder;
    //   2368: pop
    //   2369: iload_2
    //   2370: ifeq -> 2756
    //   2373: goto -> 2380
    //   2376: invokestatic a : (Ljava/lang/Throwable;)Ljava/lang/Throwable;
    //   2379: athrow
    //   2380: aload #4
    //   2382: getstatic burp/Zmhq.Zy : Ljava/lang/String;
    //   2385: getstatic burp/Ztle.ZP : Ljava/lang/Object;
    //   2388: checkcast java/math/BigInteger
    //   2391: invokevirtual intValue : ()I
    //   2394: bipush #32
    //   2396: irem
    //   2397: invokestatic abs : (I)I
    //   2400: invokevirtual charAt : (I)C
    //   2403: invokevirtual append : (C)Ljava/lang/StringBuilder;
    //   2406: pop
    //   2407: iload_2
    //   2408: ifeq -> 2756
    //   2411: goto -> 2418
    //   2414: invokestatic a : (Ljava/lang/Throwable;)Ljava/lang/Throwable;
    //   2417: athrow
    //   2418: aload #4
    //   2420: getstatic burp/Zrov.ZU : Ljava/lang/String;
    //   2423: getstatic burp/Zt8m.Zf : Ljava/lang/Object;
    //   2426: checkcast java/math/BigInteger
    //   2429: invokevirtual intValue : ()I
    //   2432: bipush #32
    //   2434: irem
    //   2435: invokestatic abs : (I)I
    //   2438: invokevirtual charAt : (I)C
    //   2441: invokevirtual append : (C)Ljava/lang/StringBuilder;
    //   2444: pop
    //   2445: iload_2
    //   2446: ifeq -> 2756
    //   2449: goto -> 2456
    //   2452: invokestatic a : (Ljava/lang/Throwable;)Ljava/lang/Throwable;
    //   2455: athrow
    //   2456: aload #4
    //   2458: getstatic burp/Zrd2.Zj : Ljava/lang/String;
    //   2461: getstatic burp/Zxd1.Zc : Ljava/lang/Object;
    //   2464: checkcast java/math/BigInteger
    //   2467: invokevirtual intValue : ()I
    //   2470: bipush #32
    //   2472: irem
    //   2473: invokestatic abs : (I)I
    //   2476: invokevirtual charAt : (I)C
    //   2479: invokevirtual append : (C)Ljava/lang/StringBuilder;
    //   2482: pop
    //   2483: iload_2
    //   2484: ifeq -> 2756
    //   2487: goto -> 2494
    //   2490: invokestatic a : (Ljava/lang/Throwable;)Ljava/lang/Throwable;
    //   2493: athrow
    //   2494: aload #4
    //   2496: getstatic burp/Zlc2.Zz : Ljava/lang/String;
    //   2499: getstatic burp/Zrnt.Zh : Ljava/lang/Object;
    //   2502: checkcast java/math/BigInteger
    //   2505: invokevirtual intValue : ()I
    //   2508: bipush #32
    //   2510: irem
    //   2511: invokestatic abs : (I)I
    //   2514: invokevirtual charAt : (I)C
    //   2517: invokevirtual append : (C)Ljava/lang/StringBuilder;
    //   2520: pop
    //   2521: iload_2
    //   2522: ifeq -> 2756
    //   2525: goto -> 2532
    //   2528: invokestatic a : (Ljava/lang/Throwable;)Ljava/lang/Throwable;
    //   2531: athrow
    //   2532: aload #4
    //   2534: getstatic burp/Zsvd.ZB : Ljava/lang/String;
    //   2537: getstatic burp/Zl7b.ZK : Ljava/lang/Object;
    //   2540: checkcast java/math/BigInteger
    //   2543: invokevirtual intValue : ()I
    //   2546: bipush #32
    //   2548: irem
    //   2549: invokestatic abs : (I)I
    //   2552: invokevirtual charAt : (I)C
    //   2555: invokevirtual append : (C)Ljava/lang/StringBuilder;
    //   2558: pop
    //   2559: iload_2
    //   2560: ifeq -> 2756
    //   2563: goto -> 2570
    //   2566: invokestatic a : (Ljava/lang/Throwable;)Ljava/lang/Throwable;
    //   2569: athrow
    //   2570: aload #4
    //   2572: getstatic burp/Zmig.ZR : Ljava/lang/String;
    //   2575: getstatic burp/Zxcn.Zq : Ljava/lang/Object;
    //   2578: checkcast java/math/BigInteger
    //   2581: invokevirtual intValue : ()I
    //   2584: bipush #32
    //   2586: irem
    //   2587: invokestatic abs : (I)I
    //   2590: invokevirtual charAt : (I)C
    //   2593: invokevirtual append : (C)Ljava/lang/StringBuilder;
    //   2596: pop
    //   2597: iload_2
    //   2598: ifeq -> 2756
    //   2601: goto -> 2608
    //   2604: invokestatic a : (Ljava/lang/Throwable;)Ljava/lang/Throwable;
    //   2607: athrow
    //   2608: aload #4
    //   2610: getstatic burp/Zmui.ZY : Ljava/lang/String;
    //   2613: getstatic burp/Zso.ZA : Ljava/lang/Object;
    //   2616: checkcast java/math/BigInteger
    //   2619: invokevirtual intValue : ()I
    //   2622: bipush #32
    //   2624: irem
    //   2625: invokestatic abs : (I)I
    //   2628: invokevirtual charAt : (I)C
    //   2631: invokevirtual append : (C)Ljava/lang/StringBuilder;
    //   2634: pop
    //   2635: iload_2
    //   2636: ifeq -> 2756
    //   2639: goto -> 2646
    //   2642: invokestatic a : (Ljava/lang/Throwable;)Ljava/lang/Throwable;
    //   2645: athrow
    //   2646: aload #4
    //   2648: getstatic burp/Zelt.ZJ : Ljava/lang/String;
    //   2651: getstatic burp/Zmpx.ZZ : Ljava/lang/Object;
    //   2654: checkcast java/math/BigInteger
    //   2657: invokevirtual intValue : ()I
    //   2660: bipush #32
    //   2662: irem
    //   2663: invokestatic abs : (I)I
    //   2666: invokevirtual charAt : (I)C
    //   2669: invokevirtual append : (C)Ljava/lang/StringBuilder;
    //   2672: pop
    //   2673: iload_2
    //   2674: ifeq -> 2756
    //   2677: goto -> 2684
    //   2680: invokestatic a : (Ljava/lang/Throwable;)Ljava/lang/Throwable;
    //   2683: athrow
    //   2684: aload #4
    //   2686: getstatic burp/Zmpx.ZC : Ljava/lang/String;
    //   2689: getstatic burp/Zti4.Zi : Ljava/lang/Object;
    //   2692: checkcast java/math/BigInteger
    //   2695: invokevirtual intValue : ()I
    //   2698: bipush #32
    //   2700: irem
    //   2701: invokestatic abs : (I)I
    //   2704: invokevirtual charAt : (I)C
    //   2707: invokevirtual append : (C)Ljava/lang/StringBuilder;
    //   2710: pop
    //   2711: iload_2
    //   2712: ifeq -> 2756
    //   2715: goto -> 2722
    //   2718: invokestatic a : (Ljava/lang/Throwable;)Ljava/lang/Throwable;
    //   2721: athrow
    //   2722: aload #4
    //   2724: getstatic burp/Zt6z.ZL : Ljava/lang/String;
    //   2727: getstatic burp/Zsu2.ZG : Ljava/lang/Object;
    //   2730: checkcast java/math/BigInteger
    //   2733: invokevirtual intValue : ()I
    //   2736: bipush #32
    //   2738: irem
    //   2739: invokestatic abs : (I)I
    //   2742: invokevirtual charAt : (I)C
    //   2745: invokevirtual append : (C)Ljava/lang/StringBuilder;
    //   2748: pop
    //   2749: goto -> 2756
    //   2752: invokestatic a : (Ljava/lang/Throwable;)Ljava/lang/Throwable;
    //   2755: athrow
    //   2756: iinc #5, 1
    //   2759: iload_2
    //   2760: ifeq -> 1392
    //   2763: aload #4
    //   2765: invokevirtual toString : ()Ljava/lang/String;
    //   2768: putstatic burp/Zzn6.Za : Ljava/lang/String;
    //   2771: sipush #-30040
    //   2774: sipush #-27395
    //   2777: invokestatic a : (II)Ljava/lang/String;
    //   2780: iconst_1
    //   2781: ldc burp/Zd8
    //   2783: invokevirtual getClassLoader : ()Ljava/lang/ClassLoader;
    //   2786: invokestatic forName : (Ljava/lang/String;ZLjava/lang/ClassLoader;)Ljava/lang/Class;
    //   2789: invokevirtual getDeclaredFields : ()[Ljava/lang/reflect/Field;
    //   2792: astore #5
    //   2794: aload #5
    //   2796: arraylength
    //   2797: istore #6
    //   2799: iconst_0
    //   2800: istore #7
    //   2802: iload #7
    //   2804: iload #6
    //   2806: if_icmpge -> 2944
    //   2809: aload #5
    //   2811: iload #7
    //   2813: aaload
    //   2814: astore #8
    //   2816: aload #8
    //   2818: invokevirtual getModifiers : ()I
    //   2821: invokestatic isStatic : (I)Z
    //   2824: ifne -> 2834
    //   2827: goto -> 2937
    //   2830: invokestatic a : (Ljava/lang/Throwable;)Ljava/lang/Throwable;
    //   2833: athrow
    //   2834: aload #8
    //   2836: invokevirtual getType : ()Ljava/lang/Class;
    //   2839: astore #9
    //   2841: aload #9
    //   2843: ifnull -> 2924
    //   2846: aload #9
    //   2848: invokevirtual isPrimitive : ()Z
    //   2851: ifne -> 2924
    //   2854: goto -> 2861
    //   2857: invokestatic a : (Ljava/lang/Throwable;)Ljava/lang/Throwable;
    //   2860: athrow
    //   2861: aload #9
    //   2863: invokevirtual getPackage : ()Ljava/lang/Package;
    //   2866: ifnull -> 2924
    //   2869: goto -> 2876
    //   2872: invokestatic a : (Ljava/lang/Throwable;)Ljava/lang/Throwable;
    //   2875: athrow
    //   2876: aload #9
    //   2878: invokevirtual getPackage : ()Ljava/lang/Package;
    //   2881: invokevirtual getName : ()Ljava/lang/String;
    //   2884: ifnull -> 2924
    //   2887: goto -> 2894
    //   2890: invokestatic a : (Ljava/lang/Throwable;)Ljava/lang/Throwable;
    //   2893: athrow
    //   2894: aload #9
    //   2896: invokevirtual getPackage : ()Ljava/lang/Package;
    //   2899: invokevirtual getName : ()Ljava/lang/String;
    //   2902: sipush #-30031
    //   2905: sipush #23487
    //   2908: invokestatic a : (II)Ljava/lang/String;
    //   2911: invokevirtual startsWith : (Ljava/lang/String;)Z
    //   2914: ifne -> 2924
    //   2917: goto -> 2924
    //   2920: invokestatic a : (Ljava/lang/Throwable;)Ljava/lang/Throwable;
    //   2923: athrow
    //   2924: aload #8
    //   2926: iconst_1
    //   2927: invokevirtual setAccessible : (Z)V
    //   2930: aload #8
    //   2932: aconst_null
    //   2933: invokevirtual get : (Ljava/lang/Object;)Ljava/lang/Object;
    //   2936: pop
    //   2937: iinc #7, 1
    //   2940: iload_2
    //   2941: ifeq -> 2802
    //   2944: sipush #-30028
    //   2947: sipush #-18919
    //   2950: invokestatic a : (II)Ljava/lang/String;
    //   2953: invokestatic forName : (Ljava/lang/String;)Ljava/lang/Class;
    //   2956: invokevirtual getDeclaredMethods : ()[Ljava/lang/reflect/Method;
    //   2959: astore #5
    //   2961: aload #5
    //   2963: arraylength
    //   2964: istore #6
    //   2966: iconst_0
    //   2967: istore #7
    //   2969: iload #7
    //   2971: iload #6
    //   2973: if_icmpge -> 3106
    //   2976: aload #5
    //   2978: iload #7
    //   2980: aaload
    //   2981: astore #8
    //   2983: aload #8
    //   2985: invokevirtual getParameterTypes : ()[Ljava/lang/Class;
    //   2988: pop
    //   2989: aload #8
    //   2991: invokevirtual getModifiers : ()I
    //   2994: invokestatic isStatic : (I)Z
    //   2997: ifeq -> 3092
    //   3000: aload #8
    //   3002: invokevirtual getParameterTypes : ()[Ljava/lang/Class;
    //   3005: arraylength
    //   3006: iconst_2
    //   3007: if_icmpne -> 3092
    //   3010: goto -> 3017
    //   3013: invokestatic a : (Ljava/lang/Throwable;)Ljava/lang/Throwable;
    //   3016: athrow
    //   3017: aload #8
    //   3019: invokevirtual getReturnType : ()Ljava/lang/Class;
    //   3022: getstatic java/lang/Void.TYPE : Ljava/lang/Class;
    //   3025: invokevirtual equals : (Ljava/lang/Object;)Z
    //   3028: ifeq -> 3092
    //   3031: goto -> 3038
    //   3034: invokestatic a : (Ljava/lang/Throwable;)Ljava/lang/Throwable;
    //   3037: athrow
    //   3038: aload #8
    //   3040: iconst_1
    //   3041: invokevirtual setAccessible : (Z)V
    //   3044: aload #8
    //   3046: aconst_null
    //   3047: iconst_2
    //   3048: anewarray java/lang/Object
    //   3051: dup
    //   3052: iconst_0
    //   3053: aload_0
    //   3054: aastore
    //   3055: dup
    //   3056: iconst_1
    //   3057: aload_1
    //   3058: ifnonnull -> 3076
    //   3061: goto -> 3068
    //   3064: invokestatic a : (Ljava/lang/Throwable;)Ljava/lang/Throwable;
    //   3067: athrow
    //   3068: aload_1
    //   3069: goto -> 3083
    //   3072: invokestatic a : (Ljava/lang/Throwable;)Ljava/lang/Throwable;
    //   3075: athrow
    //   3076: aload_1
    //   3077: checkcast [B
    //   3080: invokevirtual clone : ()Ljava/lang/Object;
    //   3083: aastore
    //   3084: invokevirtual invoke : (Ljava/lang/Object;[Ljava/lang/Object;)Ljava/lang/Object;
    //   3087: pop
    //   3088: iload_2
    //   3089: ifeq -> 3106
    //   3092: iinc #7, 1
    //   3095: iload_2
    //   3096: ifeq -> 2969
    //   3099: goto -> 3106
    //   3102: invokestatic a : (Ljava/lang/Throwable;)Ljava/lang/Throwable;
    //   3105: athrow
    //   3106: sipush #-30045
    //   3109: sipush #-25459
    //   3112: invokestatic a : (II)Ljava/lang/String;
    //   3115: iconst_1
    //   3116: ldc burp/Ztte
    //   3118: invokevirtual getClassLoader : ()Ljava/lang/ClassLoader;
    //   3121: invokestatic forName : (Ljava/lang/String;ZLjava/lang/ClassLoader;)Ljava/lang/Class;
    //   3124: invokevirtual getDeclaredFields : ()[Ljava/lang/reflect/Field;
    //   3127: astore #5
    //   3129: aload #5
    //   3131: arraylength
    //   3132: istore #6
    //   3134: iconst_0
    //   3135: istore #7
    //   3137: iload #7
    //   3139: iload #6
    //   3141: if_icmpge -> 3279
    //   3144: aload #5
    //   3146: iload #7
    //   3148: aaload
    //   3149: astore #8
    //   3151: aload #8
    //   3153: invokevirtual getModifiers : ()I
    //   3156: invokestatic isStatic : (I)Z
    //   3159: ifne -> 3169
    //   3162: goto -> 3272
    //   3165: invokestatic a : (Ljava/lang/Throwable;)Ljava/lang/Throwable;
    //   3168: athrow
    //   3169: aload #8
    //   3171: invokevirtual getType : ()Ljava/lang/Class;
    //   3174: astore #9
    //   3176: aload #9
    //   3178: ifnull -> 3259
    //   3181: aload #9
    //   3183: invokevirtual isPrimitive : ()Z
    //   3186: ifne -> 3259
    //   3189: goto -> 3196
    //   3192: invokestatic a : (Ljava/lang/Throwable;)Ljava/lang/Throwable;
    //   3195: athrow
    //   3196: aload #9
    //   3198: invokevirtual getPackage : ()Ljava/lang/Package;
    //   3201: ifnull -> 3259
    //   3204: goto -> 3211
    //   3207: invokestatic a : (Ljava/lang/Throwable;)Ljava/lang/Throwable;
    //   3210: athrow
    //   3211: aload #9
    //   3213: invokevirtual getPackage : ()Ljava/lang/Package;
    //   3216: invokevirtual getName : ()Ljava/lang/String;
    //   3219: ifnull -> 3259
    //   3222: goto -> 3229
    //   3225: invokestatic a : (Ljava/lang/Throwable;)Ljava/lang/Throwable;
    //   3228: athrow
    //   3229: aload #9
    //   3231: invokevirtual getPackage : ()Ljava/lang/Package;
    //   3234: invokevirtual getName : ()Ljava/lang/String;
    //   3237: sipush #-30032
    //   3240: sipush #-4427
    //   3243: invokestatic a : (II)Ljava/lang/String;
    //   3246: invokevirtual startsWith : (Ljava/lang/String;)Z
    //   3249: ifne -> 3259
    //   3252: goto -> 3259
    //   3255: invokestatic a : (Ljava/lang/Throwable;)Ljava/lang/Throwable;
    //   3258: athrow
    //   3259: aload #8
    //   3261: iconst_1
    //   3262: invokevirtual setAccessible : (Z)V
    //   3265: aload #8
    //   3267: aconst_null
    //   3268: invokevirtual get : (Ljava/lang/Object;)Ljava/lang/Object;
    //   3271: pop
    //   3272: iinc #7, 1
    //   3275: iload_2
    //   3276: ifeq -> 3137
    //   3279: sipush #-30029
    //   3282: sipush #-25765
    //   3285: invokestatic a : (II)Ljava/lang/String;
    //   3288: invokestatic forName : (Ljava/lang/String;)Ljava/lang/Class;
    //   3291: invokevirtual getDeclaredMethods : ()[Ljava/lang/reflect/Method;
    //   3294: astore #5
    //   3296: aload #5
    //   3298: arraylength
    //   3299: istore #6
    //   3301: iconst_0
    //   3302: istore #7
    //   3304: iload #7
    //   3306: iload #6
    //   3308: if_icmpge -> 3420
    //   3311: aload #5
    //   3313: iload #7
    //   3315: aaload
    //   3316: astore #8
    //   3318: aload #8
    //   3320: invokevirtual getParameterTypes : ()[Ljava/lang/Class;
    //   3323: pop
    //   3324: aload #8
    //   3326: invokevirtual getModifiers : ()I
    //   3329: invokestatic isStatic : (I)Z
    //   3332: ifeq -> 3406
    //   3335: aload #8
    //   3337: invokevirtual getParameterTypes : ()[Ljava/lang/Class;
    //   3340: arraylength
    //   3341: iconst_2
    //   3342: if_icmpne -> 3406
    //   3345: goto -> 3352
    //   3348: invokestatic a : (Ljava/lang/Throwable;)Ljava/lang/Throwable;
    //   3351: athrow
    //   3352: aload #8
    //   3354: invokevirtual getReturnType : ()Ljava/lang/Class;
    //   3357: getstatic java/lang/Boolean.TYPE : Ljava/lang/Class;
    //   3360: if_acmpne -> 3406
    //   3363: goto -> 3370
    //   3366: invokestatic a : (Ljava/lang/Throwable;)Ljava/lang/Throwable;
    //   3369: athrow
    //   3370: aload #8
    //   3372: iconst_1
    //   3373: invokevirtual setAccessible : (Z)V
    //   3376: aload #8
    //   3378: aconst_null
    //   3379: iconst_2
    //   3380: anewarray java/lang/Object
    //   3383: dup
    //   3384: iconst_0
    //   3385: aload_0
    //   3386: aastore
    //   3387: dup
    //   3388: iconst_1
    //   3389: aload_1
    //   3390: aastore
    //   3391: invokevirtual invoke : (Ljava/lang/Object;[Ljava/lang/Object;)Ljava/lang/Object;
    //   3394: pop
    //   3395: iload_2
    //   3396: ifeq -> 3420
    //   3399: goto -> 3406
    //   3402: invokestatic a : (Ljava/lang/Throwable;)Ljava/lang/Throwable;
    //   3405: athrow
    //   3406: iinc #7, 1
    //   3409: iload_2
    //   3410: ifeq -> 3304
    //   3413: goto -> 3420
    //   3416: invokestatic a : (Ljava/lang/Throwable;)Ljava/lang/Throwable;
    //   3419: athrow
    //   3420: iconst_0
    //   3421: istore #5
    //   3423: getstatic burp/Zzts.Zk : Ljava/lang/String;
    //   3426: getstatic burp/Zzii.ZO : Ljava/lang/Object;
    //   3429: checkcast java/math/BigInteger
    //   3432: invokevirtual intValue : ()I
    //   3435: bipush #32
    //   3437: irem
    //   3438: invokestatic abs : (I)I
    //   3441: invokevirtual charAt : (I)C
    //   3444: getstatic burp/Zxju.Zt : Ljava/lang/String;
    //   3447: getstatic burp/Zrzg.ZA : Ljava/lang/Object;
    //   3450: checkcast java/math/BigInteger
    //   3453: invokevirtual intValue : ()I
    //   3456: bipush #32
    //   3458: irem
    //   3459: invokestatic abs : (I)I
    //   3462: invokevirtual charAt : (I)C
    //   3465: if_icmple -> 3810
    //   3468: sipush #-30023
    //   3471: sipush #29427
    //   3474: invokestatic a : (II)Ljava/lang/String;
    //   3477: iconst_1
    //   3478: ldc burp/Zx58
    //   3480: invokevirtual getClassLoader : ()Ljava/lang/ClassLoader;
    //   3483: invokestatic forName : (Ljava/lang/String;ZLjava/lang/ClassLoader;)Ljava/lang/Class;
    //   3486: invokevirtual getDeclaredFields : ()[Ljava/lang/reflect/Field;
    //   3489: astore #6
    //   3491: aload #6
    //   3493: arraylength
    //   3494: istore #7
    //   3496: iconst_0
    //   3497: istore #8
    //   3499: iload #8
    //   3501: iload #7
    //   3503: if_icmpge -> 3641
    //   3506: aload #6
    //   3508: iload #8
    //   3510: aaload
    //   3511: astore #9
    //   3513: aload #9
    //   3515: invokevirtual getModifiers : ()I
    //   3518: invokestatic isStatic : (I)Z
    //   3521: ifne -> 3531
    //   3524: goto -> 3634
    //   3527: invokestatic a : (Ljava/lang/Throwable;)Ljava/lang/Throwable;
    //   3530: athrow
    //   3531: aload #9
    //   3533: invokevirtual getType : ()Ljava/lang/Class;
    //   3536: astore #10
    //   3538: aload #10
    //   3540: ifnull -> 3621
    //   3543: aload #10
    //   3545: invokevirtual isPrimitive : ()Z
    //   3548: ifne -> 3621
    //   3551: goto -> 3558
    //   3554: invokestatic a : (Ljava/lang/Throwable;)Ljava/lang/Throwable;
    //   3557: athrow
    //   3558: aload #10
    //   3560: invokevirtual getPackage : ()Ljava/lang/Package;
    //   3563: ifnull -> 3621
    //   3566: goto -> 3573
    //   3569: invokestatic a : (Ljava/lang/Throwable;)Ljava/lang/Throwable;
    //   3572: athrow
    //   3573: aload #10
    //   3575: invokevirtual getPackage : ()Ljava/lang/Package;
    //   3578: invokevirtual getName : ()Ljava/lang/String;
    //   3581: ifnull -> 3621
    //   3584: goto -> 3591
    //   3587: invokestatic a : (Ljava/lang/Throwable;)Ljava/lang/Throwable;
    //   3590: athrow
    //   3591: aload #10
    //   3593: invokevirtual getPackage : ()Ljava/lang/Package;
    //   3596: invokevirtual getName : ()Ljava/lang/String;
    //   3599: sipush #-30032
    //   3602: sipush #-4427
    //   3605: invokestatic a : (II)Ljava/lang/String;
    //   3608: invokevirtual startsWith : (Ljava/lang/String;)Z
    //   3611: ifne -> 3621
    //   3614: goto -> 3621
    //   3617: invokestatic a : (Ljava/lang/Throwable;)Ljava/lang/Throwable;
    //   3620: athrow
    //   3621: aload #9
    //   3623: iconst_1
    //   3624: invokevirtual setAccessible : (Z)V
    //   3627: aload #9
    //   3629: aconst_null
    //   3630: invokevirtual get : (Ljava/lang/Object;)Ljava/lang/Object;
    //   3633: pop
    //   3634: iinc #8, 1
    //   3637: iload_2
    //   3638: ifeq -> 3499
    //   3641: sipush #-30024
    //   3644: sipush #233
    //   3647: invokestatic a : (II)Ljava/lang/String;
    //   3650: invokestatic forName : (Ljava/lang/String;)Ljava/lang/Class;
    //   3653: invokevirtual getDeclaredMethods : ()[Ljava/lang/reflect/Method;
    //   3656: astore #6
    //   3658: aload #6
    //   3660: arraylength
    //   3661: istore #7
    //   3663: iconst_0
    //   3664: istore #8
    //   3666: iload #8
    //   3668: iload #7
    //   3670: if_icmpge -> 3807
    //   3673: aload #6
    //   3675: iload #8
    //   3677: aaload
    //   3678: astore #9
    //   3680: aload #9
    //   3682: invokevirtual getParameterTypes : ()[Ljava/lang/Class;
    //   3685: pop
    //   3686: aload #9
    //   3688: invokevirtual getModifiers : ()I
    //   3691: invokestatic isStatic : (I)Z
    //   3694: ifeq -> 3793
    //   3697: aload #9
    //   3699: invokevirtual getParameterTypes : ()[Ljava/lang/Class;
    //   3702: arraylength
    //   3703: iconst_2
    //   3704: if_icmpne -> 3793
    //   3707: goto -> 3714
    //   3710: invokestatic a : (Ljava/lang/Throwable;)Ljava/lang/Throwable;
    //   3713: athrow
    //   3714: aload #9
    //   3716: invokevirtual getReturnType : ()Ljava/lang/Class;
    //   3719: getstatic java/lang/Boolean.TYPE : Ljava/lang/Class;
    //   3722: if_acmpne -> 3793
    //   3725: goto -> 3732
    //   3728: invokestatic a : (Ljava/lang/Throwable;)Ljava/lang/Throwable;
    //   3731: athrow
    //   3732: aload #9
    //   3734: iconst_1
    //   3735: invokevirtual setAccessible : (Z)V
    //   3738: aload #9
    //   3740: aconst_null
    //   3741: iconst_2
    //   3742: anewarray java/lang/Object
    //   3745: dup
    //   3746: iconst_0
    //   3747: aload_0
    //   3748: aastore
    //   3749: dup
    //   3750: iconst_1
    //   3751: aload_1
    //   3752: ifnonnull -> 3770
    //   3755: goto -> 3762
    //   3758: invokestatic a : (Ljava/lang/Throwable;)Ljava/lang/Throwable;
    //   3761: athrow
    //   3762: aload_1
    //   3763: goto -> 3777
    //   3766: invokestatic a : (Ljava/lang/Throwable;)Ljava/lang/Throwable;
    //   3769: athrow
    //   3770: aload_1
    //   3771: checkcast [B
    //   3774: invokevirtual clone : ()Ljava/lang/Object;
    //   3777: aastore
    //   3778: invokevirtual invoke : (Ljava/lang/Object;[Ljava/lang/Object;)Ljava/lang/Object;
    //   3781: checkcast java/lang/Boolean
    //   3784: invokevirtual booleanValue : ()Z
    //   3787: istore #5
    //   3789: iload_2
    //   3790: ifeq -> 3807
    //   3793: iinc #8, 1
    //   3796: iload_2
    //   3797: ifeq -> 3666
    //   3800: goto -> 3807
    //   3803: invokestatic a : (Ljava/lang/Throwable;)Ljava/lang/Throwable;
    //   3806: athrow
    //   3807: goto -> 4149
    //   3810: sipush #-30034
    //   3813: sipush #1599
    //   3816: invokestatic a : (II)Ljava/lang/String;
    //   3819: iconst_1
    //   3820: ldc burp/Zg_y
    //   3822: invokevirtual getClassLoader : ()Ljava/lang/ClassLoader;
    //   3825: invokestatic forName : (Ljava/lang/String;ZLjava/lang/ClassLoader;)Ljava/lang/Class;
    //   3828: invokevirtual getDeclaredFields : ()[Ljava/lang/reflect/Field;
    //   3831: astore #6
    //   3833: aload #6
    //   3835: arraylength
    //   3836: istore #7
    //   3838: iconst_0
    //   3839: istore #8
    //   3841: iload #8
    //   3843: iload #7
    //   3845: if_icmpge -> 3983
    //   3848: aload #6
    //   3850: iload #8
    //   3852: aaload
    //   3853: astore #9
    //   3855: aload #9
    //   3857: invokevirtual getModifiers : ()I
    //   3860: invokestatic isStatic : (I)Z
    //   3863: ifne -> 3873
    //   3866: goto -> 3976
    //   3869: invokestatic a : (Ljava/lang/Throwable;)Ljava/lang/Throwable;
    //   3872: athrow
    //   3873: aload #9
    //   3875: invokevirtual getType : ()Ljava/lang/Class;
    //   3878: astore #10
    //   3880: aload #10
    //   3882: ifnull -> 3963
    //   3885: aload #10
    //   3887: invokevirtual isPrimitive : ()Z
    //   3890: ifne -> 3963
    //   3893: goto -> 3900
    //   3896: invokestatic a : (Ljava/lang/Throwable;)Ljava/lang/Throwable;
    //   3899: athrow
    //   3900: aload #10
    //   3902: invokevirtual getPackage : ()Ljava/lang/Package;
    //   3905: ifnull -> 3963
    //   3908: goto -> 3915
    //   3911: invokestatic a : (Ljava/lang/Throwable;)Ljava/lang/Throwable;
    //   3914: athrow
    //   3915: aload #10
    //   3917: invokevirtual getPackage : ()Ljava/lang/Package;
    //   3920: invokevirtual getName : ()Ljava/lang/String;
    //   3923: ifnull -> 3963
    //   3926: goto -> 3933
    //   3929: invokestatic a : (Ljava/lang/Throwable;)Ljava/lang/Throwable;
    //   3932: athrow
    //   3933: aload #10
    //   3935: invokevirtual getPackage : ()Ljava/lang/Package;
    //   3938: invokevirtual getName : ()Ljava/lang/String;
    //   3941: sipush #-30032
    //   3944: sipush #-4427
    //   3947: invokestatic a : (II)Ljava/lang/String;
    //   3950: invokevirtual startsWith : (Ljava/lang/String;)Z
    //   3953: ifne -> 3963
    //   3956: goto -> 3963
    //   3959: invokestatic a : (Ljava/lang/Throwable;)Ljava/lang/Throwable;
    //   3962: athrow
    //   3963: aload #9
    //   3965: iconst_1
    //   3966: invokevirtual setAccessible : (Z)V
    //   3969: aload #9
    //   3971: aconst_null
    //   3972: invokevirtual get : (Ljava/lang/Object;)Ljava/lang/Object;
    //   3975: pop
    //   3976: iinc #8, 1
    //   3979: iload_2
    //   3980: ifeq -> 3841
    //   3983: sipush #-30026
    //   3986: sipush #5188
    //   3989: invokestatic a : (II)Ljava/lang/String;
    //   3992: invokestatic forName : (Ljava/lang/String;)Ljava/lang/Class;
    //   3995: invokevirtual getDeclaredMethods : ()[Ljava/lang/reflect/Method;
    //   3998: astore #6
    //   4000: aload #6
    //   4002: arraylength
    //   4003: istore #7
    //   4005: iconst_0
    //   4006: istore #8
    //   4008: iload #8
    //   4010: iload #7
    //   4012: if_icmpge -> 4149
    //   4015: aload #6
    //   4017: iload #8
    //   4019: aaload
    //   4020: astore #9
    //   4022: aload #9
    //   4024: invokevirtual getParameterTypes : ()[Ljava/lang/Class;
    //   4027: pop
    //   4028: aload #9
    //   4030: invokevirtual getModifiers : ()I
    //   4033: invokestatic isStatic : (I)Z
    //   4036: ifeq -> 4135
    //   4039: aload #9
    //   4041: invokevirtual getParameterTypes : ()[Ljava/lang/Class;
    //   4044: arraylength
    //   4045: iconst_2
    //   4046: if_icmpne -> 4135
    //   4049: goto -> 4056
    //   4052: invokestatic a : (Ljava/lang/Throwable;)Ljava/lang/Throwable;
    //   4055: athrow
    //   4056: aload #9
    //   4058: invokevirtual getReturnType : ()Ljava/lang/Class;
    //   4061: getstatic java/lang/Boolean.TYPE : Ljava/lang/Class;
    //   4064: if_acmpne -> 4135
    //   4067: goto -> 4074
    //   4070: invokestatic a : (Ljava/lang/Throwable;)Ljava/lang/Throwable;
    //   4073: athrow
    //   4074: aload #9
    //   4076: iconst_1
    //   4077: invokevirtual setAccessible : (Z)V
    //   4080: aload #9
    //   4082: aconst_null
    //   4083: iconst_2
    //   4084: anewarray java/lang/Object
    //   4087: dup
    //   4088: iconst_0
    //   4089: aload_0
    //   4090: aastore
    //   4091: dup
    //   4092: iconst_1
    //   4093: aload_1
    //   4094: ifnonnull -> 4112
    //   4097: goto -> 4104
    //   4100: invokestatic a : (Ljava/lang/Throwable;)Ljava/lang/Throwable;
    //   4103: athrow
    //   4104: aload_1
    //   4105: goto -> 4119
    //   4108: invokestatic a : (Ljava/lang/Throwable;)Ljava/lang/Throwable;
    //   4111: athrow
    //   4112: aload_1
    //   4113: checkcast [B
    //   4116: invokevirtual clone : ()Ljava/lang/Object;
    //   4119: aastore
    //   4120: invokevirtual invoke : (Ljava/lang/Object;[Ljava/lang/Object;)Ljava/lang/Object;
    //   4123: checkcast java/lang/Boolean
    //   4126: invokevirtual booleanValue : ()Z
    //   4129: istore #5
    //   4131: iload_2
    //   4132: ifeq -> 4149
    //   4135: iinc #8, 1
    //   4138: iload_2
    //   4139: ifeq -> 4008
    //   4142: goto -> 4149
    //   4145: invokestatic a : (Ljava/lang/Throwable;)Ljava/lang/Throwable;
    //   4148: athrow
    //   4149: iload #5
    //   4151: ifeq -> 4157
    //   4154: iload #5
    //   4156: ireturn
    //   4157: getstatic burp/Zlg2.ZL : Ljava/lang/String;
    //   4160: getstatic burp/Ze1k.ZD : Ljava/lang/Object;
    //   4163: checkcast java/math/BigInteger
    //   4166: invokevirtual intValue : ()I
    //   4169: bipush #32
    //   4171: irem
    //   4172: invokestatic abs : (I)I
    //   4175: invokevirtual charAt : (I)C
    //   4178: getstatic burp/Zthx.Ze : Ljava/lang/String;
    //   4181: getstatic burp/Zzmc.Zg : Ljava/lang/Object;
    //   4184: checkcast java/math/BigInteger
    //   4187: invokevirtual intValue : ()I
    //   4190: bipush #32
    //   4192: irem
    //   4193: invokestatic abs : (I)I
    //   4196: invokevirtual charAt : (I)C
    //   4199: if_icmpgt -> 4545
    //   4202: sipush #-30030
    //   4205: sipush #5939
    //   4208: invokestatic a : (II)Ljava/lang/String;
    //   4211: iconst_1
    //   4212: ldc burp/Ztmy
    //   4214: invokevirtual getClassLoader : ()Ljava/lang/ClassLoader;
    //   4217: invokestatic forName : (Ljava/lang/String;ZLjava/lang/ClassLoader;)Ljava/lang/Class;
    //   4220: invokevirtual getDeclaredFields : ()[Ljava/lang/reflect/Field;
    //   4223: astore #6
    //   4225: aload #6
    //   4227: arraylength
    //   4228: istore #7
    //   4230: iconst_0
    //   4231: istore #8
    //   4233: iload #8
    //   4235: iload #7
    //   4237: if_icmpge -> 4375
    //   4240: aload #6
    //   4242: iload #8
    //   4244: aaload
    //   4245: astore #9
    //   4247: aload #9
    //   4249: invokevirtual getModifiers : ()I
    //   4252: invokestatic isStatic : (I)Z
    //   4255: ifne -> 4265
    //   4258: goto -> 4368
    //   4261: invokestatic a : (Ljava/lang/Throwable;)Ljava/lang/Throwable;
    //   4264: athrow
    //   4265: aload #9
    //   4267: invokevirtual getType : ()Ljava/lang/Class;
    //   4270: astore #10
    //   4272: aload #10
    //   4274: ifnull -> 4355
    //   4277: aload #10
    //   4279: invokevirtual isPrimitive : ()Z
    //   4282: ifne -> 4355
    //   4285: goto -> 4292
    //   4288: invokestatic a : (Ljava/lang/Throwable;)Ljava/lang/Throwable;
    //   4291: athrow
    //   4292: aload #10
    //   4294: invokevirtual getPackage : ()Ljava/lang/Package;
    //   4297: ifnull -> 4355
    //   4300: goto -> 4307
    //   4303: invokestatic a : (Ljava/lang/Throwable;)Ljava/lang/Throwable;
    //   4306: athrow
    //   4307: aload #10
    //   4309: invokevirtual getPackage : ()Ljava/lang/Package;
    //   4312: invokevirtual getName : ()Ljava/lang/String;
    //   4315: ifnull -> 4355
    //   4318: goto -> 4325
    //   4321: invokestatic a : (Ljava/lang/Throwable;)Ljava/lang/Throwable;
    //   4324: athrow
    //   4325: aload #10
    //   4327: invokevirtual getPackage : ()Ljava/lang/Package;
    //   4330: invokevirtual getName : ()Ljava/lang/String;
    //   4333: sipush #-30032
    //   4336: sipush #-4427
    //   4339: invokestatic a : (II)Ljava/lang/String;
    //   4342: invokevirtual startsWith : (Ljava/lang/String;)Z
    //   4345: ifne -> 4355
    //   4348: goto -> 4355
    //   4351: invokestatic a : (Ljava/lang/Throwable;)Ljava/lang/Throwable;
    //   4354: athrow
    //   4355: aload #9
    //   4357: iconst_1
    //   4358: invokevirtual setAccessible : (Z)V
    //   4361: aload #9
    //   4363: aconst_null
    //   4364: invokevirtual get : (Ljava/lang/Object;)Ljava/lang/Object;
    //   4367: pop
    //   4368: iinc #8, 1
    //   4371: iload_2
    //   4372: ifeq -> 4233
    //   4375: sipush #-30022
    //   4378: sipush #8668
    //   4381: invokestatic a : (II)Ljava/lang/String;
    //   4384: invokestatic forName : (Ljava/lang/String;)Ljava/lang/Class;
    //   4387: invokevirtual getDeclaredMethods : ()[Ljava/lang/reflect/Method;
    //   4390: astore #6
    //   4392: aload #6
    //   4394: arraylength
    //   4395: istore #7
    //   4397: iconst_0
    //   4398: istore #8
    //   4400: iload #8
    //   4402: iload #7
    //   4404: if_icmpge -> 4541
    //   4407: aload #6
    //   4409: iload #8
    //   4411: aaload
    //   4412: astore #9
    //   4414: aload #9
    //   4416: invokevirtual getParameterTypes : ()[Ljava/lang/Class;
    //   4419: pop
    //   4420: aload #9
    //   4422: invokevirtual getModifiers : ()I
    //   4425: invokestatic isStatic : (I)Z
    //   4428: ifeq -> 4527
    //   4431: aload #9
    //   4433: invokevirtual getParameterTypes : ()[Ljava/lang/Class;
    //   4436: arraylength
    //   4437: iconst_2
    //   4438: if_icmpne -> 4527
    //   4441: goto -> 4448
    //   4444: invokestatic a : (Ljava/lang/Throwable;)Ljava/lang/Throwable;
    //   4447: athrow
    //   4448: aload #9
    //   4450: invokevirtual getReturnType : ()Ljava/lang/Class;
    //   4453: getstatic java/lang/Boolean.TYPE : Ljava/lang/Class;
    //   4456: if_acmpne -> 4527
    //   4459: goto -> 4466
    //   4462: invokestatic a : (Ljava/lang/Throwable;)Ljava/lang/Throwable;
    //   4465: athrow
    //   4466: aload #9
    //   4468: iconst_1
    //   4469: invokevirtual setAccessible : (Z)V
    //   4472: aload #9
    //   4474: aconst_null
    //   4475: iconst_2
    //   4476: anewarray java/lang/Object
    //   4479: dup
    //   4480: iconst_0
    //   4481: aload_0
    //   4482: aastore
    //   4483: dup
    //   4484: iconst_1
    //   4485: aload_1
    //   4486: ifnonnull -> 4504
    //   4489: goto -> 4496
    //   4492: invokestatic a : (Ljava/lang/Throwable;)Ljava/lang/Throwable;
    //   4495: athrow
    //   4496: aload_1
    //   4497: goto -> 4511
    //   4500: invokestatic a : (Ljava/lang/Throwable;)Ljava/lang/Throwable;
    //   4503: athrow
    //   4504: aload_1
    //   4505: checkcast [B
    //   4508: invokevirtual clone : ()Ljava/lang/Object;
    //   4511: aastore
    //   4512: invokevirtual invoke : (Ljava/lang/Object;[Ljava/lang/Object;)Ljava/lang/Object;
    //   4515: checkcast java/lang/Boolean
    //   4518: invokevirtual booleanValue : ()Z
    //   4521: istore #5
    //   4523: iload_2
    //   4524: ifeq -> 4541
    //   4527: iinc #8, 1
    //   4530: iload_2
    //   4531: ifeq -> 4400
    //   4534: goto -> 4541
    //   4537: invokestatic a : (Ljava/lang/Throwable;)Ljava/lang/Throwable;
    //   4540: athrow
    //   4541: iload_2
    //   4542: ifeq -> 4884
    //   4545: sipush #-30039
    //   4548: sipush #-7172
    //   4551: invokestatic a : (II)Ljava/lang/String;
    //   4554: iconst_1
    //   4555: ldc burp/Zrdy
    //   4557: invokevirtual getClassLoader : ()Ljava/lang/ClassLoader;
    //   4560: invokestatic forName : (Ljava/lang/String;ZLjava/lang/ClassLoader;)Ljava/lang/Class;
    //   4563: invokevirtual getDeclaredFields : ()[Ljava/lang/reflect/Field;
    //   4566: astore #6
    //   4568: aload #6
    //   4570: arraylength
    //   4571: istore #7
    //   4573: iconst_0
    //   4574: istore #8
    //   4576: iload #8
    //   4578: iload #7
    //   4580: if_icmpge -> 4718
    //   4583: aload #6
    //   4585: iload #8
    //   4587: aaload
    //   4588: astore #9
    //   4590: aload #9
    //   4592: invokevirtual getModifiers : ()I
    //   4595: invokestatic isStatic : (I)Z
    //   4598: ifne -> 4608
    //   4601: goto -> 4711
    //   4604: invokestatic a : (Ljava/lang/Throwable;)Ljava/lang/Throwable;
    //   4607: athrow
    //   4608: aload #9
    //   4610: invokevirtual getType : ()Ljava/lang/Class;
    //   4613: astore #10
    //   4615: aload #10
    //   4617: ifnull -> 4698
    //   4620: aload #10
    //   4622: invokevirtual isPrimitive : ()Z
    //   4625: ifne -> 4698
    //   4628: goto -> 4635
    //   4631: invokestatic a : (Ljava/lang/Throwable;)Ljava/lang/Throwable;
    //   4634: athrow
    //   4635: aload #10
    //   4637: invokevirtual getPackage : ()Ljava/lang/Package;
    //   4640: ifnull -> 4698
    //   4643: goto -> 4650
    //   4646: invokestatic a : (Ljava/lang/Throwable;)Ljava/lang/Throwable;
    //   4649: athrow
    //   4650: aload #10
    //   4652: invokevirtual getPackage : ()Ljava/lang/Package;
    //   4655: invokevirtual getName : ()Ljava/lang/String;
    //   4658: ifnull -> 4698
    //   4661: goto -> 4668
    //   4664: invokestatic a : (Ljava/lang/Throwable;)Ljava/lang/Throwable;
    //   4667: athrow
    //   4668: aload #10
    //   4670: invokevirtual getPackage : ()Ljava/lang/Package;
    //   4673: invokevirtual getName : ()Ljava/lang/String;
    //   4676: sipush #-30032
    //   4679: sipush #-4427
    //   4682: invokestatic a : (II)Ljava/lang/String;
    //   4685: invokevirtual startsWith : (Ljava/lang/String;)Z
    //   4688: ifne -> 4698
    //   4691: goto -> 4698
    //   4694: invokestatic a : (Ljava/lang/Throwable;)Ljava/lang/Throwable;
    //   4697: athrow
    //   4698: aload #9
    //   4700: iconst_1
    //   4701: invokevirtual setAccessible : (Z)V
    //   4704: aload #9
    //   4706: aconst_null
    //   4707: invokevirtual get : (Ljava/lang/Object;)Ljava/lang/Object;
    //   4710: pop
    //   4711: iinc #8, 1
    //   4714: iload_2
    //   4715: ifeq -> 4576
    //   4718: sipush #-30021
    //   4721: sipush #-22181
    //   4724: invokestatic a : (II)Ljava/lang/String;
    //   4727: invokestatic forName : (Ljava/lang/String;)Ljava/lang/Class;
    //   4730: invokevirtual getDeclaredMethods : ()[Ljava/lang/reflect/Method;
    //   4733: astore #6
    //   4735: aload #6
    //   4737: arraylength
    //   4738: istore #7
    //   4740: iconst_0
    //   4741: istore #8
    //   4743: iload #8
    //   4745: iload #7
    //   4747: if_icmpge -> 4884
    //   4750: aload #6
    //   4752: iload #8
    //   4754: aaload
    //   4755: astore #9
    //   4757: aload #9
    //   4759: invokevirtual getParameterTypes : ()[Ljava/lang/Class;
    //   4762: pop
    //   4763: aload #9
    //   4765: invokevirtual getModifiers : ()I
    //   4768: invokestatic isStatic : (I)Z
    //   4771: ifeq -> 4870
    //   4774: aload #9
    //   4776: invokevirtual getParameterTypes : ()[Ljava/lang/Class;
    //   4779: arraylength
    //   4780: iconst_2
    //   4781: if_icmpne -> 4870
    //   4784: goto -> 4791
    //   4787: invokestatic a : (Ljava/lang/Throwable;)Ljava/lang/Throwable;
    //   4790: athrow
    //   4791: aload #9
    //   4793: invokevirtual getReturnType : ()Ljava/lang/Class;
    //   4796: getstatic java/lang/Boolean.TYPE : Ljava/lang/Class;
    //   4799: if_acmpne -> 4870
    //   4802: goto -> 4809
    //   4805: invokestatic a : (Ljava/lang/Throwable;)Ljava/lang/Throwable;
    //   4808: athrow
    //   4809: aload #9
    //   4811: iconst_1
    //   4812: invokevirtual setAccessible : (Z)V
    //   4815: aload #9
    //   4817: aconst_null
    //   4818: iconst_2
    //   4819: anewarray java/lang/Object
    //   4822: dup
    //   4823: iconst_0
    //   4824: aload_0
    //   4825: aastore
    //   4826: dup
    //   4827: iconst_1
    //   4828: aload_1
    //   4829: ifnonnull -> 4847
    //   4832: goto -> 4839
    //   4835: invokestatic a : (Ljava/lang/Throwable;)Ljava/lang/Throwable;
    //   4838: athrow
    //   4839: aload_1
    //   4840: goto -> 4854
    //   4843: invokestatic a : (Ljava/lang/Throwable;)Ljava/lang/Throwable;
    //   4846: athrow
    //   4847: aload_1
    //   4848: checkcast [B
    //   4851: invokevirtual clone : ()Ljava/lang/Object;
    //   4854: aastore
    //   4855: invokevirtual invoke : (Ljava/lang/Object;[Ljava/lang/Object;)Ljava/lang/Object;
    //   4858: checkcast java/lang/Boolean
    //   4861: invokevirtual booleanValue : ()Z
    //   4864: istore #5
    //   4866: iload_2
    //   4867: ifeq -> 4884
    //   4870: iinc #8, 1
    //   4873: iload_2
    //   4874: ifeq -> 4743
    //   4877: goto -> 4884
    //   4880: invokestatic a : (Ljava/lang/Throwable;)Ljava/lang/Throwable;
    //   4883: athrow
    //   4884: iload #5
    //   4886: ifeq -> 4892
    //   4889: iload #5
    //   4891: ireturn
    //   4892: getstatic burp/Zg1l.Zl : Ljava/lang/String;
    //   4895: getstatic burp/Zml9.ZH : Ljava/lang/Object;
    //   4898: checkcast java/math/BigInteger
    //   4901: invokevirtual intValue : ()I
    //   4904: bipush #32
    //   4906: irem
    //   4907: invokestatic abs : (I)I
    //   4910: invokevirtual charAt : (I)C
    //   4913: getstatic burp/Zrkd.ZL : Ljava/lang/String;
    //   4916: getstatic burp/Zemp.Zr : Ljava/lang/Object;
    //   4919: checkcast java/math/BigInteger
    //   4922: invokevirtual intValue : ()I
    //   4925: bipush #32
    //   4927: irem
    //   4928: invokestatic abs : (I)I
    //   4931: invokevirtual charAt : (I)C
    //   4934: if_icmpgt -> 5280
    //   4937: sipush #-30046
    //   4940: sipush #1781
    //   4943: invokestatic a : (II)Ljava/lang/String;
    //   4946: iconst_1
    //   4947: ldc burp/Zkqx
    //   4949: invokevirtual getClassLoader : ()Ljava/lang/ClassLoader;
    //   4952: invokestatic forName : (Ljava/lang/String;ZLjava/lang/ClassLoader;)Ljava/lang/Class;
    //   4955: invokevirtual getDeclaredFields : ()[Ljava/lang/reflect/Field;
    //   4958: astore #6
    //   4960: aload #6
    //   4962: arraylength
    //   4963: istore #7
    //   4965: iconst_0
    //   4966: istore #8
    //   4968: iload #8
    //   4970: iload #7
    //   4972: if_icmpge -> 5110
    //   4975: aload #6
    //   4977: iload #8
    //   4979: aaload
    //   4980: astore #9
    //   4982: aload #9
    //   4984: invokevirtual getModifiers : ()I
    //   4987: invokestatic isStatic : (I)Z
    //   4990: ifne -> 5000
    //   4993: goto -> 5103
    //   4996: invokestatic a : (Ljava/lang/Throwable;)Ljava/lang/Throwable;
    //   4999: athrow
    //   5000: aload #9
    //   5002: invokevirtual getType : ()Ljava/lang/Class;
    //   5005: astore #10
    //   5007: aload #10
    //   5009: ifnull -> 5090
    //   5012: aload #10
    //   5014: invokevirtual isPrimitive : ()Z
    //   5017: ifne -> 5090
    //   5020: goto -> 5027
    //   5023: invokestatic a : (Ljava/lang/Throwable;)Ljava/lang/Throwable;
    //   5026: athrow
    //   5027: aload #10
    //   5029: invokevirtual getPackage : ()Ljava/lang/Package;
    //   5032: ifnull -> 5090
    //   5035: goto -> 5042
    //   5038: invokestatic a : (Ljava/lang/Throwable;)Ljava/lang/Throwable;
    //   5041: athrow
    //   5042: aload #10
    //   5044: invokevirtual getPackage : ()Ljava/lang/Package;
    //   5047: invokevirtual getName : ()Ljava/lang/String;
    //   5050: ifnull -> 5090
    //   5053: goto -> 5060
    //   5056: invokestatic a : (Ljava/lang/Throwable;)Ljava/lang/Throwable;
    //   5059: athrow
    //   5060: aload #10
    //   5062: invokevirtual getPackage : ()Ljava/lang/Package;
    //   5065: invokevirtual getName : ()Ljava/lang/String;
    //   5068: sipush #-30032
    //   5071: sipush #-4427
    //   5074: invokestatic a : (II)Ljava/lang/String;
    //   5077: invokevirtual startsWith : (Ljava/lang/String;)Z
    //   5080: ifne -> 5090
    //   5083: goto -> 5090
    //   5086: invokestatic a : (Ljava/lang/Throwable;)Ljava/lang/Throwable;
    //   5089: athrow
    //   5090: aload #9
    //   5092: iconst_1
    //   5093: invokevirtual setAccessible : (Z)V
    //   5096: aload #9
    //   5098: aconst_null
    //   5099: invokevirtual get : (Ljava/lang/Object;)Ljava/lang/Object;
    //   5102: pop
    //   5103: iinc #8, 1
    //   5106: iload_2
    //   5107: ifeq -> 4968
    //   5110: sipush #-30020
    //   5113: sipush #-12941
    //   5116: invokestatic a : (II)Ljava/lang/String;
    //   5119: invokestatic forName : (Ljava/lang/String;)Ljava/lang/Class;
    //   5122: invokevirtual getDeclaredMethods : ()[Ljava/lang/reflect/Method;
    //   5125: astore #6
    //   5127: aload #6
    //   5129: arraylength
    //   5130: istore #7
    //   5132: iconst_0
    //   5133: istore #8
    //   5135: iload #8
    //   5137: iload #7
    //   5139: if_icmpge -> 5276
    //   5142: aload #6
    //   5144: iload #8
    //   5146: aaload
    //   5147: astore #9
    //   5149: aload #9
    //   5151: invokevirtual getParameterTypes : ()[Ljava/lang/Class;
    //   5154: pop
    //   5155: aload #9
    //   5157: invokevirtual getModifiers : ()I
    //   5160: invokestatic isStatic : (I)Z
    //   5163: ifeq -> 5262
    //   5166: aload #9
    //   5168: invokevirtual getParameterTypes : ()[Ljava/lang/Class;
    //   5171: arraylength
    //   5172: iconst_2
    //   5173: if_icmpne -> 5262
    //   5176: goto -> 5183
    //   5179: invokestatic a : (Ljava/lang/Throwable;)Ljava/lang/Throwable;
    //   5182: athrow
    //   5183: aload #9
    //   5185: invokevirtual getReturnType : ()Ljava/lang/Class;
    //   5188: getstatic java/lang/Boolean.TYPE : Ljava/lang/Class;
    //   5191: if_acmpne -> 5262
    //   5194: goto -> 5201
    //   5197: invokestatic a : (Ljava/lang/Throwable;)Ljava/lang/Throwable;
    //   5200: athrow
    //   5201: aload #9
    //   5203: iconst_1
    //   5204: invokevirtual setAccessible : (Z)V
    //   5207: aload #9
    //   5209: aconst_null
    //   5210: iconst_2
    //   5211: anewarray java/lang/Object
    //   5214: dup
    //   5215: iconst_0
    //   5216: aload_0
    //   5217: aastore
    //   5218: dup
    //   5219: iconst_1
    //   5220: aload_1
    //   5221: ifnonnull -> 5239
    //   5224: goto -> 5231
    //   5227: invokestatic a : (Ljava/lang/Throwable;)Ljava/lang/Throwable;
    //   5230: athrow
    //   5231: aload_1
    //   5232: goto -> 5246
    //   5235: invokestatic a : (Ljava/lang/Throwable;)Ljava/lang/Throwable;
    //   5238: athrow
    //   5239: aload_1
    //   5240: checkcast [B
    //   5243: invokevirtual clone : ()Ljava/lang/Object;
    //   5246: aastore
    //   5247: invokevirtual invoke : (Ljava/lang/Object;[Ljava/lang/Object;)Ljava/lang/Object;
    //   5250: checkcast java/lang/Boolean
    //   5253: invokevirtual booleanValue : ()Z
    //   5256: istore #5
    //   5258: iload_2
    //   5259: ifeq -> 5276
    //   5262: iinc #8, 1
    //   5265: iload_2
    //   5266: ifeq -> 5135
    //   5269: goto -> 5276
    //   5272: invokestatic a : (Ljava/lang/Throwable;)Ljava/lang/Throwable;
    //   5275: athrow
    //   5276: iload_2
    //   5277: ifeq -> 5619
    //   5280: sipush #-30025
    //   5283: sipush #-29389
    //   5286: invokestatic a : (II)Ljava/lang/String;
    //   5289: iconst_1
    //   5290: ldc burp/Zgl4
    //   5292: invokevirtual getClassLoader : ()Ljava/lang/ClassLoader;
    //   5295: invokestatic forName : (Ljava/lang/String;ZLjava/lang/ClassLoader;)Ljava/lang/Class;
    //   5298: invokevirtual getDeclaredFields : ()[Ljava/lang/reflect/Field;
    //   5301: astore #6
    //   5303: aload #6
    //   5305: arraylength
    //   5306: istore #7
    //   5308: iconst_0
    //   5309: istore #8
    //   5311: iload #8
    //   5313: iload #7
    //   5315: if_icmpge -> 5453
    //   5318: aload #6
    //   5320: iload #8
    //   5322: aaload
    //   5323: astore #9
    //   5325: aload #9
    //   5327: invokevirtual getModifiers : ()I
    //   5330: invokestatic isStatic : (I)Z
    //   5333: ifne -> 5343
    //   5336: goto -> 5446
    //   5339: invokestatic a : (Ljava/lang/Throwable;)Ljava/lang/Throwable;
    //   5342: athrow
    //   5343: aload #9
    //   5345: invokevirtual getType : ()Ljava/lang/Class;
    //   5348: astore #10
    //   5350: aload #10
    //   5352: ifnull -> 5433
    //   5355: aload #10
    //   5357: invokevirtual isPrimitive : ()Z
    //   5360: ifne -> 5433
    //   5363: goto -> 5370
    //   5366: invokestatic a : (Ljava/lang/Throwable;)Ljava/lang/Throwable;
    //   5369: athrow
    //   5370: aload #10
    //   5372: invokevirtual getPackage : ()Ljava/lang/Package;
    //   5375: ifnull -> 5433
    //   5378: goto -> 5385
    //   5381: invokestatic a : (Ljava/lang/Throwable;)Ljava/lang/Throwable;
    //   5384: athrow
    //   5385: aload #10
    //   5387: invokevirtual getPackage : ()Ljava/lang/Package;
    //   5390: invokevirtual getName : ()Ljava/lang/String;
    //   5393: ifnull -> 5433
    //   5396: goto -> 5403
    //   5399: invokestatic a : (Ljava/lang/Throwable;)Ljava/lang/Throwable;
    //   5402: athrow
    //   5403: aload #10
    //   5405: invokevirtual getPackage : ()Ljava/lang/Package;
    //   5408: invokevirtual getName : ()Ljava/lang/String;
    //   5411: sipush #-30032
    //   5414: sipush #-4427
    //   5417: invokestatic a : (II)Ljava/lang/String;
    //   5420: invokevirtual startsWith : (Ljava/lang/String;)Z
    //   5423: ifne -> 5433
    //   5426: goto -> 5433
    //   5429: invokestatic a : (Ljava/lang/Throwable;)Ljava/lang/Throwable;
    //   5432: athrow
    //   5433: aload #9
    //   5435: iconst_1
    //   5436: invokevirtual setAccessible : (Z)V
    //   5439: aload #9
    //   5441: aconst_null
    //   5442: invokevirtual get : (Ljava/lang/Object;)Ljava/lang/Object;
    //   5445: pop
    //   5446: iinc #8, 1
    //   5449: iload_2
    //   5450: ifeq -> 5311
    //   5453: sipush #-30047
    //   5456: sipush #12619
    //   5459: invokestatic a : (II)Ljava/lang/String;
    //   5462: invokestatic forName : (Ljava/lang/String;)Ljava/lang/Class;
    //   5465: invokevirtual getDeclaredMethods : ()[Ljava/lang/reflect/Method;
    //   5468: astore #6
    //   5470: aload #6
    //   5472: arraylength
    //   5473: istore #7
    //   5475: iconst_0
    //   5476: istore #8
    //   5478: iload #8
    //   5480: iload #7
    //   5482: if_icmpge -> 5619
    //   5485: aload #6
    //   5487: iload #8
    //   5489: aaload
    //   5490: astore #9
    //   5492: aload #9
    //   5494: invokevirtual getParameterTypes : ()[Ljava/lang/Class;
    //   5497: pop
    //   5498: aload #9
    //   5500: invokevirtual getModifiers : ()I
    //   5503: invokestatic isStatic : (I)Z
    //   5506: ifeq -> 5605
    //   5509: aload #9
    //   5511: invokevirtual getParameterTypes : ()[Ljava/lang/Class;
    //   5514: arraylength
    //   5515: iconst_2
    //   5516: if_icmpne -> 5605
    //   5519: goto -> 5526
    //   5522: invokestatic a : (Ljava/lang/Throwable;)Ljava/lang/Throwable;
    //   5525: athrow
    //   5526: aload #9
    //   5528: invokevirtual getReturnType : ()Ljava/lang/Class;
    //   5531: getstatic java/lang/Boolean.TYPE : Ljava/lang/Class;
    //   5534: if_acmpne -> 5605
    //   5537: goto -> 5544
    //   5540: invokestatic a : (Ljava/lang/Throwable;)Ljava/lang/Throwable;
    //   5543: athrow
    //   5544: aload #9
    //   5546: iconst_1
    //   5547: invokevirtual setAccessible : (Z)V
    //   5550: aload #9
    //   5552: aconst_null
    //   5553: iconst_2
    //   5554: anewarray java/lang/Object
    //   5557: dup
    //   5558: iconst_0
    //   5559: aload_0
    //   5560: aastore
    //   5561: dup
    //   5562: iconst_1
    //   5563: aload_1
    //   5564: ifnonnull -> 5582
    //   5567: goto -> 5574
    //   5570: invokestatic a : (Ljava/lang/Throwable;)Ljava/lang/Throwable;
    //   5573: athrow
    //   5574: aload_1
    //   5575: goto -> 5589
    //   5578: invokestatic a : (Ljava/lang/Throwable;)Ljava/lang/Throwable;
    //   5581: athrow
    //   5582: aload_1
    //   5583: checkcast [B
    //   5586: invokevirtual clone : ()Ljava/lang/Object;
    //   5589: aastore
    //   5590: invokevirtual invoke : (Ljava/lang/Object;[Ljava/lang/Object;)Ljava/lang/Object;
    //   5593: checkcast java/lang/Boolean
    //   5596: invokevirtual booleanValue : ()Z
    //   5599: istore #5
    //   5601: iload_2
    //   5602: ifeq -> 5619
    //   5605: iinc #8, 1
    //   5608: iload_2
    //   5609: ifeq -> 5478
    //   5612: goto -> 5619
    //   5615: invokestatic a : (Ljava/lang/Throwable;)Ljava/lang/Throwable;
    //   5618: athrow
    //   5619: iload #5
    //   5621: ifeq -> 5627
    //   5624: iload #5
    //   5626: ireturn
    //   5627: getstatic burp/Zgrz.Zu : Ljava/lang/String;
    //   5630: getstatic burp/Ze6w.Ze : Ljava/lang/Object;
    //   5633: checkcast java/math/BigInteger
    //   5636: invokevirtual intValue : ()I
    //   5639: bipush #32
    //   5641: irem
    //   5642: invokestatic abs : (I)I
    //   5645: invokevirtual charAt : (I)C
    //   5648: getstatic burp/Zr6c.Zf : Ljava/lang/String;
    //   5651: getstatic burp/Zmc_.Zj : Ljava/lang/Object;
    //   5654: checkcast java/math/BigInteger
    //   5657: invokevirtual intValue : ()I
    //   5660: bipush #32
    //   5662: irem
    //   5663: invokestatic abs : (I)I
    //   5666: invokevirtual charAt : (I)C
    //   5669: if_icmpgt -> 6015
    //   5672: sipush #-30037
    //   5675: sipush #-1791
    //   5678: invokestatic a : (II)Ljava/lang/String;
    //   5681: iconst_1
    //   5682: ldc burp/Zql
    //   5684: invokevirtual getClassLoader : ()Ljava/lang/ClassLoader;
    //   5687: invokestatic forName : (Ljava/lang/String;ZLjava/lang/ClassLoader;)Ljava/lang/Class;
    //   5690: invokevirtual getDeclaredFields : ()[Ljava/lang/reflect/Field;
    //   5693: astore #6
    //   5695: aload #6
    //   5697: arraylength
    //   5698: istore #7
    //   5700: iconst_0
    //   5701: istore #8
    //   5703: iload #8
    //   5705: iload #7
    //   5707: if_icmpge -> 5845
    //   5710: aload #6
    //   5712: iload #8
    //   5714: aaload
    //   5715: astore #9
    //   5717: aload #9
    //   5719: invokevirtual getModifiers : ()I
    //   5722: invokestatic isStatic : (I)Z
    //   5725: ifne -> 5735
    //   5728: goto -> 5838
    //   5731: invokestatic a : (Ljava/lang/Throwable;)Ljava/lang/Throwable;
    //   5734: athrow
    //   5735: aload #9
    //   5737: invokevirtual getType : ()Ljava/lang/Class;
    //   5740: astore #10
    //   5742: aload #10
    //   5744: ifnull -> 5825
    //   5747: aload #10
    //   5749: invokevirtual isPrimitive : ()Z
    //   5752: ifne -> 5825
    //   5755: goto -> 5762
    //   5758: invokestatic a : (Ljava/lang/Throwable;)Ljava/lang/Throwable;
    //   5761: athrow
    //   5762: aload #10
    //   5764: invokevirtual getPackage : ()Ljava/lang/Package;
    //   5767: ifnull -> 5825
    //   5770: goto -> 5777
    //   5773: invokestatic a : (Ljava/lang/Throwable;)Ljava/lang/Throwable;
    //   5776: athrow
    //   5777: aload #10
    //   5779: invokevirtual getPackage : ()Ljava/lang/Package;
    //   5782: invokevirtual getName : ()Ljava/lang/String;
    //   5785: ifnull -> 5825
    //   5788: goto -> 5795
    //   5791: invokestatic a : (Ljava/lang/Throwable;)Ljava/lang/Throwable;
    //   5794: athrow
    //   5795: aload #10
    //   5797: invokevirtual getPackage : ()Ljava/lang/Package;
    //   5800: invokevirtual getName : ()Ljava/lang/String;
    //   5803: sipush #-30032
    //   5806: sipush #-4427
    //   5809: invokestatic a : (II)Ljava/lang/String;
    //   5812: invokevirtual startsWith : (Ljava/lang/String;)Z
    //   5815: ifne -> 5825
    //   5818: goto -> 5825
    //   5821: invokestatic a : (Ljava/lang/Throwable;)Ljava/lang/Throwable;
    //   5824: athrow
    //   5825: aload #9
    //   5827: iconst_1
    //   5828: invokevirtual setAccessible : (Z)V
    //   5831: aload #9
    //   5833: aconst_null
    //   5834: invokevirtual get : (Ljava/lang/Object;)Ljava/lang/Object;
    //   5837: pop
    //   5838: iinc #8, 1
    //   5841: iload_2
    //   5842: ifeq -> 5703
    //   5845: sipush #-30018
    //   5848: sipush #3597
    //   5851: invokestatic a : (II)Ljava/lang/String;
    //   5854: invokestatic forName : (Ljava/lang/String;)Ljava/lang/Class;
    //   5857: invokevirtual getDeclaredMethods : ()[Ljava/lang/reflect/Method;
    //   5860: astore #6
    //   5862: aload #6
    //   5864: arraylength
    //   5865: istore #7
    //   5867: iconst_0
    //   5868: istore #8
    //   5870: iload #8
    //   5872: iload #7
    //   5874: if_icmpge -> 6011
    //   5877: aload #6
    //   5879: iload #8
    //   5881: aaload
    //   5882: astore #9
    //   5884: aload #9
    //   5886: invokevirtual getParameterTypes : ()[Ljava/lang/Class;
    //   5889: pop
    //   5890: aload #9
    //   5892: invokevirtual getModifiers : ()I
    //   5895: invokestatic isStatic : (I)Z
    //   5898: ifeq -> 5997
    //   5901: aload #9
    //   5903: invokevirtual getParameterTypes : ()[Ljava/lang/Class;
    //   5906: arraylength
    //   5907: iconst_2
    //   5908: if_icmpne -> 5997
    //   5911: goto -> 5918
    //   5914: invokestatic a : (Ljava/lang/Throwable;)Ljava/lang/Throwable;
    //   5917: athrow
    //   5918: aload #9
    //   5920: invokevirtual getReturnType : ()Ljava/lang/Class;
    //   5923: getstatic java/lang/Boolean.TYPE : Ljava/lang/Class;
    //   5926: if_acmpne -> 5997
    //   5929: goto -> 5936
    //   5932: invokestatic a : (Ljava/lang/Throwable;)Ljava/lang/Throwable;
    //   5935: athrow
    //   5936: aload #9
    //   5938: iconst_1
    //   5939: invokevirtual setAccessible : (Z)V
    //   5942: aload #9
    //   5944: aconst_null
    //   5945: iconst_2
    //   5946: anewarray java/lang/Object
    //   5949: dup
    //   5950: iconst_0
    //   5951: aload_0
    //   5952: aastore
    //   5953: dup
    //   5954: iconst_1
    //   5955: aload_1
    //   5956: ifnonnull -> 5974
    //   5959: goto -> 5966
    //   5962: invokestatic a : (Ljava/lang/Throwable;)Ljava/lang/Throwable;
    //   5965: athrow
    //   5966: aload_1
    //   5967: goto -> 5981
    //   5970: invokestatic a : (Ljava/lang/Throwable;)Ljava/lang/Throwable;
    //   5973: athrow
    //   5974: aload_1
    //   5975: checkcast [B
    //   5978: invokevirtual clone : ()Ljava/lang/Object;
    //   5981: aastore
    //   5982: invokevirtual invoke : (Ljava/lang/Object;[Ljava/lang/Object;)Ljava/lang/Object;
    //   5985: checkcast java/lang/Boolean
    //   5988: invokevirtual booleanValue : ()Z
    //   5991: istore #5
    //   5993: iload_2
    //   5994: ifeq -> 6011
    //   5997: iinc #8, 1
    //   6000: iload_2
    //   6001: ifeq -> 5870
    //   6004: goto -> 6011
    //   6007: invokestatic a : (Ljava/lang/Throwable;)Ljava/lang/Throwable;
    //   6010: athrow
    //   6011: iload_2
    //   6012: ifeq -> 6354
    //   6015: sipush #-30036
    //   6018: sipush #20060
    //   6021: invokestatic a : (II)Ljava/lang/String;
    //   6024: iconst_1
    //   6025: ldc burp/Zmt_
    //   6027: invokevirtual getClassLoader : ()Ljava/lang/ClassLoader;
    //   6030: invokestatic forName : (Ljava/lang/String;ZLjava/lang/ClassLoader;)Ljava/lang/Class;
    //   6033: invokevirtual getDeclaredFields : ()[Ljava/lang/reflect/Field;
    //   6036: astore #6
    //   6038: aload #6
    //   6040: arraylength
    //   6041: istore #7
    //   6043: iconst_0
    //   6044: istore #8
    //   6046: iload #8
    //   6048: iload #7
    //   6050: if_icmpge -> 6188
    //   6053: aload #6
    //   6055: iload #8
    //   6057: aaload
    //   6058: astore #9
    //   6060: aload #9
    //   6062: invokevirtual getModifiers : ()I
    //   6065: invokestatic isStatic : (I)Z
    //   6068: ifne -> 6078
    //   6071: goto -> 6181
    //   6074: invokestatic a : (Ljava/lang/Throwable;)Ljava/lang/Throwable;
    //   6077: athrow
    //   6078: aload #9
    //   6080: invokevirtual getType : ()Ljava/lang/Class;
    //   6083: astore #10
    //   6085: aload #10
    //   6087: ifnull -> 6168
    //   6090: aload #10
    //   6092: invokevirtual isPrimitive : ()Z
    //   6095: ifne -> 6168
    //   6098: goto -> 6105
    //   6101: invokestatic a : (Ljava/lang/Throwable;)Ljava/lang/Throwable;
    //   6104: athrow
    //   6105: aload #10
    //   6107: invokevirtual getPackage : ()Ljava/lang/Package;
    //   6110: ifnull -> 6168
    //   6113: goto -> 6120
    //   6116: invokestatic a : (Ljava/lang/Throwable;)Ljava/lang/Throwable;
    //   6119: athrow
    //   6120: aload #10
    //   6122: invokevirtual getPackage : ()Ljava/lang/Package;
    //   6125: invokevirtual getName : ()Ljava/lang/String;
    //   6128: ifnull -> 6168
    //   6131: goto -> 6138
    //   6134: invokestatic a : (Ljava/lang/Throwable;)Ljava/lang/Throwable;
    //   6137: athrow
    //   6138: aload #10
    //   6140: invokevirtual getPackage : ()Ljava/lang/Package;
    //   6143: invokevirtual getName : ()Ljava/lang/String;
    //   6146: sipush #-30032
    //   6149: sipush #-4427
    //   6152: invokestatic a : (II)Ljava/lang/String;
    //   6155: invokevirtual startsWith : (Ljava/lang/String;)Z
    //   6158: ifne -> 6168
    //   6161: goto -> 6168
    //   6164: invokestatic a : (Ljava/lang/Throwable;)Ljava/lang/Throwable;
    //   6167: athrow
    //   6168: aload #9
    //   6170: iconst_1
    //   6171: invokevirtual setAccessible : (Z)V
    //   6174: aload #9
    //   6176: aconst_null
    //   6177: invokevirtual get : (Ljava/lang/Object;)Ljava/lang/Object;
    //   6180: pop
    //   6181: iinc #8, 1
    //   6184: iload_2
    //   6185: ifeq -> 6046
    //   6188: sipush #-30038
    //   6191: sipush #-1194
    //   6194: invokestatic a : (II)Ljava/lang/String;
    //   6197: invokestatic forName : (Ljava/lang/String;)Ljava/lang/Class;
    //   6200: invokevirtual getDeclaredMethods : ()[Ljava/lang/reflect/Method;
    //   6203: astore #6
    //   6205: aload #6
    //   6207: arraylength
    //   6208: istore #7
    //   6210: iconst_0
    //   6211: istore #8
    //   6213: iload #8
    //   6215: iload #7
    //   6217: if_icmpge -> 6354
    //   6220: aload #6
    //   6222: iload #8
    //   6224: aaload
    //   6225: astore #9
    //   6227: aload #9
    //   6229: invokevirtual getParameterTypes : ()[Ljava/lang/Class;
    //   6232: pop
    //   6233: aload #9
    //   6235: invokevirtual getModifiers : ()I
    //   6238: invokestatic isStatic : (I)Z
    //   6241: ifeq -> 6340
    //   6244: aload #9
    //   6246: invokevirtual getParameterTypes : ()[Ljava/lang/Class;
    //   6249: arraylength
    //   6250: iconst_2
    //   6251: if_icmpne -> 6340
    //   6254: goto -> 6261
    //   6257: invokestatic a : (Ljava/lang/Throwable;)Ljava/lang/Throwable;
    //   6260: athrow
    //   6261: aload #9
    //   6263: invokevirtual getReturnType : ()Ljava/lang/Class;
    //   6266: getstatic java/lang/Boolean.TYPE : Ljava/lang/Class;
    //   6269: if_acmpne -> 6340
    //   6272: goto -> 6279
    //   6275: invokestatic a : (Ljava/lang/Throwable;)Ljava/lang/Throwable;
    //   6278: athrow
    //   6279: aload #9
    //   6281: iconst_1
    //   6282: invokevirtual setAccessible : (Z)V
    //   6285: aload #9
    //   6287: aconst_null
    //   6288: iconst_2
    //   6289: anewarray java/lang/Object
    //   6292: dup
    //   6293: iconst_0
    //   6294: aload_0
    //   6295: aastore
    //   6296: dup
    //   6297: iconst_1
    //   6298: aload_1
    //   6299: ifnonnull -> 6317
    //   6302: goto -> 6309
    //   6305: invokestatic a : (Ljava/lang/Throwable;)Ljava/lang/Throwable;
    //   6308: athrow
    //   6309: aload_1
    //   6310: goto -> 6324
    //   6313: invokestatic a : (Ljava/lang/Throwable;)Ljava/lang/Throwable;
    //   6316: athrow
    //   6317: aload_1
    //   6318: checkcast [B
    //   6321: invokevirtual clone : ()Ljava/lang/Object;
    //   6324: aastore
    //   6325: invokevirtual invoke : (Ljava/lang/Object;[Ljava/lang/Object;)Ljava/lang/Object;
    //   6328: checkcast java/lang/Boolean
    //   6331: invokevirtual booleanValue : ()Z
    //   6334: istore #5
    //   6336: iload_2
    //   6337: ifeq -> 6354
    //   6340: iinc #8, 1
    //   6343: iload_2
    //   6344: ifeq -> 6213
    //   6347: goto -> 6354
    //   6350: invokestatic a : (Ljava/lang/Throwable;)Ljava/lang/Throwable;
    //   6353: athrow
    //   6354: iload #5
    //   6356: ireturn
    //   6357: astore_3
    //   6358: new java/lang/Exception
    //   6361: dup
    //   6362: aload_3
    //   6363: invokevirtual getMessage : ()Ljava/lang/String;
    //   6366: invokespecial <init> : (Ljava/lang/String;)V
    //   6369: athrow
    // Exception table:
    //   from	to	target	type
    //   4	4156	6357	java/lang/Throwable
    //   22	198	201	java/lang/Throwable
    //   168	235	238	java/lang/Throwable
    //   205	272	275	java/lang/Throwable
    //   242	309	312	java/lang/Throwable
    //   279	346	349	java/lang/Throwable
    //   316	383	386	java/lang/Throwable
    //   353	420	423	java/lang/Throwable
    //   390	457	460	java/lang/Throwable
    //   427	494	497	java/lang/Throwable
    //   464	531	534	java/lang/Throwable
    //   501	568	571	java/lang/Throwable
    //   538	605	608	java/lang/Throwable
    //   575	642	645	java/lang/Throwable
    //   612	679	682	java/lang/Throwable
    //   649	716	719	java/lang/Throwable
    //   686	753	756	java/lang/Throwable
    //   723	790	793	java/lang/Throwable
    //   760	827	830	java/lang/Throwable
    //   797	864	867	java/lang/Throwable
    //   834	901	904	java/lang/Throwable
    //   871	938	941	java/lang/Throwable
    //   908	975	978	java/lang/Throwable
    //   945	1012	1015	java/lang/Throwable
    //   982	1049	1052	java/lang/Throwable
    //   1019	1086	1089	java/lang/Throwable
    //   1056	1123	1126	java/lang/Throwable
    //   1093	1160	1163	java/lang/Throwable
    //   1130	1197	1200	java/lang/Throwable
    //   1167	1234	1237	java/lang/Throwable
    //   1204	1271	1274	java/lang/Throwable
    //   1241	1308	1311	java/lang/Throwable
    //   1278	1341	1344	java/lang/Throwable
    //   1399	1575	1578	java/lang/Throwable
    //   1544	1613	1616	java/lang/Throwable
    //   1582	1651	1654	java/lang/Throwable
    //   1620	1689	1692	java/lang/Throwable
    //   1658	1727	1730	java/lang/Throwable
    //   1696	1765	1768	java/lang/Throwable
    //   1734	1803	1806	java/lang/Throwable
    //   1772	1841	1844	java/lang/Throwable
    //   1810	1879	1882	java/lang/Throwable
    //   1848	1917	1920	java/lang/Throwable
    //   1886	1955	1958	java/lang/Throwable
    //   1924	1993	1996	java/lang/Throwable
    //   1962	2031	2034	java/lang/Throwable
    //   2000	2069	2072	java/lang/Throwable
    //   2038	2107	2110	java/lang/Throwable
    //   2076	2145	2148	java/lang/Throwable
    //   2114	2183	2186	java/lang/Throwable
    //   2152	2221	2224	java/lang/Throwable
    //   2190	2259	2262	java/lang/Throwable
    //   2228	2297	2300	java/lang/Throwable
    //   2266	2335	2338	java/lang/Throwable
    //   2304	2373	2376	java/lang/Throwable
    //   2342	2411	2414	java/lang/Throwable
    //   2380	2449	2452	java/lang/Throwable
    //   2418	2487	2490	java/lang/Throwable
    //   2456	2525	2528	java/lang/Throwable
    //   2494	2563	2566	java/lang/Throwable
    //   2532	2601	2604	java/lang/Throwable
    //   2570	2639	2642	java/lang/Throwable
    //   2608	2677	2680	java/lang/Throwable
    //   2646	2715	2718	java/lang/Throwable
    //   2684	2749	2752	java/lang/Throwable
    //   2816	2830	2830	java/lang/Throwable
    //   2841	2854	2857	java/lang/Throwable
    //   2846	2869	2872	java/lang/Throwable
    //   2861	2887	2890	java/lang/Throwable
    //   2876	2917	2920	java/lang/Throwable
    //   2983	3010	3013	java/lang/Throwable
    //   3000	3031	3034	java/lang/Throwable
    //   3017	3061	3064	java/lang/Throwable
    //   3038	3072	3072	java/lang/Throwable
    //   3083	3099	3102	java/lang/Throwable
    //   3151	3165	3165	java/lang/Throwable
    //   3176	3189	3192	java/lang/Throwable
    //   3181	3204	3207	java/lang/Throwable
    //   3196	3222	3225	java/lang/Throwable
    //   3211	3252	3255	java/lang/Throwable
    //   3318	3345	3348	java/lang/Throwable
    //   3335	3363	3366	java/lang/Throwable
    //   3352	3399	3402	java/lang/Throwable
    //   3370	3413	3416	java/lang/Throwable
    //   3513	3527	3527	java/lang/Throwable
    //   3538	3551	3554	java/lang/Throwable
    //   3543	3566	3569	java/lang/Throwable
    //   3558	3584	3587	java/lang/Throwable
    //   3573	3614	3617	java/lang/Throwable
    //   3680	3707	3710	java/lang/Throwable
    //   3697	3725	3728	java/lang/Throwable
    //   3714	3755	3758	java/lang/Throwable
    //   3732	3766	3766	java/lang/Throwable
    //   3789	3800	3803	java/lang/Throwable
    //   3855	3869	3869	java/lang/Throwable
    //   3880	3893	3896	java/lang/Throwable
    //   3885	3908	3911	java/lang/Throwable
    //   3900	3926	3929	java/lang/Throwable
    //   3915	3956	3959	java/lang/Throwable
    //   4022	4049	4052	java/lang/Throwable
    //   4039	4067	4070	java/lang/Throwable
    //   4056	4097	4100	java/lang/Throwable
    //   4074	4108	4108	java/lang/Throwable
    //   4131	4142	4145	java/lang/Throwable
    //   4157	4891	6357	java/lang/Throwable
    //   4247	4261	4261	java/lang/Throwable
    //   4272	4285	4288	java/lang/Throwable
    //   4277	4300	4303	java/lang/Throwable
    //   4292	4318	4321	java/lang/Throwable
    //   4307	4348	4351	java/lang/Throwable
    //   4414	4441	4444	java/lang/Throwable
    //   4431	4459	4462	java/lang/Throwable
    //   4448	4489	4492	java/lang/Throwable
    //   4466	4500	4500	java/lang/Throwable
    //   4523	4534	4537	java/lang/Throwable
    //   4590	4604	4604	java/lang/Throwable
    //   4615	4628	4631	java/lang/Throwable
    //   4620	4643	4646	java/lang/Throwable
    //   4635	4661	4664	java/lang/Throwable
    //   4650	4691	4694	java/lang/Throwable
    //   4757	4784	4787	java/lang/Throwable
    //   4774	4802	4805	java/lang/Throwable
    //   4791	4832	4835	java/lang/Throwable
    //   4809	4843	4843	java/lang/Throwable
    //   4866	4877	4880	java/lang/Throwable
    //   4892	5626	6357	java/lang/Throwable
    //   4982	4996	4996	java/lang/Throwable
    //   5007	5020	5023	java/lang/Throwable
    //   5012	5035	5038	java/lang/Throwable
    //   5027	5053	5056	java/lang/Throwable
    //   5042	5083	5086	java/lang/Throwable
    //   5149	5176	5179	java/lang/Throwable
    //   5166	5194	5197	java/lang/Throwable
    //   5183	5224	5227	java/lang/Throwable
    //   5201	5235	5235	java/lang/Throwable
    //   5258	5269	5272	java/lang/Throwable
    //   5325	5339	5339	java/lang/Throwable
    //   5350	5363	5366	java/lang/Throwable
    //   5355	5378	5381	java/lang/Throwable
    //   5370	5396	5399	java/lang/Throwable
    //   5385	5426	5429	java/lang/Throwable
    //   5492	5519	5522	java/lang/Throwable
    //   5509	5537	5540	java/lang/Throwable
    //   5526	5567	5570	java/lang/Throwable
    //   5544	5578	5578	java/lang/Throwable
    //   5601	5612	5615	java/lang/Throwable
    //   5627	6356	6357	java/lang/Throwable
    //   5717	5731	5731	java/lang/Throwable
    //   5742	5755	5758	java/lang/Throwable
    //   5747	5770	5773	java/lang/Throwable
    //   5762	5788	5791	java/lang/Throwable
    //   5777	5818	5821	java/lang/Throwable
    //   5884	5911	5914	java/lang/Throwable
    //   5901	5929	5932	java/lang/Throwable
    //   5918	5959	5962	java/lang/Throwable
    //   5936	5970	5970	java/lang/Throwable
    //   5993	6004	6007	java/lang/Throwable
    //   6060	6074	6074	java/lang/Throwable
    //   6085	6098	6101	java/lang/Throwable
    //   6090	6113	6116	java/lang/Throwable
    //   6105	6131	6134	java/lang/Throwable
    //   6120	6161	6164	java/lang/Throwable
    //   6227	6254	6257	java/lang/Throwable
    //   6244	6272	6275	java/lang/Throwable
    //   6261	6302	6305	java/lang/Throwable
    //   6279	6313	6313	java/lang/Throwable
    //   6336	6347	6350	java/lang/Throwable
  }
  
  static void Zj(Object[] paramArrayOfObject, Object paramObject) throws Throwable {}
  
  static void ZG(Object paramObject) {
    Zbze.ZK = a(-30027, 4772);
    Zbze.ZM = new BigInteger(a(-30035, -28733));
    boolean bool = Zt2e.ZN();
    try {
      try {
        if (Zrnt.Zy.charAt(Math.abs(((BigInteger)Zzah.Za).intValue() % 32)) <= Zm3x.Zu.charAt(Math.abs(((BigInteger)Zbow.ZS).intValue() % 32))) {
          try {
            Zlpn.ZA(Class.forName(a(-30017, -30145)));
            if (!bool)
              Ztle.Zn(Class.forName(a(-30019, 30090))); 
          } catch (Throwable throwable) {
            throw a(null);
          } 
          return;
        } 
      } catch (Throwable throwable) {
        throw a(null);
      } 
      Ztle.Zn(Class.forName(a(-30019, 30090)));
    } catch (Throwable throwable) {}
  }
  
  static {
    // Byte code:
    //   0: bipush #27
    //   2: anewarray java/lang/String
    //   5: astore #5
    //   7: iconst_0
    //   8: istore_3
    //   9: ldc '.+?\\tE@&\\t>}/Vt\\t{< 4l\\to\\tUQ)\\teD;8i\\tB7U\\t.\\b?\\tlv&6w\\nN\\t|wv]\\ty O$WVnrHj"T@V\\t\\tV\\t\\t7T9L$\\tUX2|\\t:u\\bg\\t\\tZK\\rw Ygm/,iC<=\\t@]M)>\\bCbC&M{og|}~]E\\b$1Q6_.lNTcxC\\t<4O\\t#T"bO'
    //   11: dup
    //   12: astore_2
    //   13: invokevirtual length : ()I
    //   16: istore #4
    //   18: bipush #9
    //   20: istore_1
    //   21: iconst_m1
    //   22: istore_0
    //   23: bipush #30
    //   25: iinc #0, 1
    //   28: aload_2
    //   29: iload_0
    //   30: dup
    //   31: iload_1
    //   32: iadd
    //   33: invokevirtual substring : (II)Ljava/lang/String;
    //   36: iconst_m1
    //   37: goto -> 143
    //   40: aload #5
    //   42: swap
    //   43: iload_3
    //   44: iinc #3, 1
    //   47: swap
    //   48: aastore
    //   49: iload_0
    //   50: iload_1
    //   51: iadd
    //   52: dup
    //   53: istore_0
    //   54: iload #4
    //   56: if_icmpge -> 68
    //   59: aload_2
    //   60: iload_0
    //   61: invokevirtual charAt : (I)C
    //   64: istore_1
    //   65: goto -> 23
    //   68: ldc 'K}`\\t\\ru(!BH='
    //   70: dup
    //   71: astore_2
    //   72: invokevirtual length : ()I
    //   75: istore #4
    //   77: bipush #9
    //   79: istore_1
    //   80: iconst_m1
    //   81: istore_0
    //   82: bipush #108
    //   84: iinc #0, 1
    //   87: aload_2
    //   88: iload_0
    //   89: dup
    //   90: iload_1
    //   91: iadd
    //   92: invokevirtual substring : (II)Ljava/lang/String;
    //   95: iconst_0
    //   96: goto -> 143
    //   99: aload #5
    //   101: swap
    //   102: iload_3
    //   103: iinc #3, 1
    //   106: swap
    //   107: aastore
    //   108: iload_0
    //   109: iload_1
    //   110: iadd
    //   111: dup
    //   112: istore_0
    //   113: iload #4
    //   115: if_icmpge -> 127
    //   118: aload_2
    //   119: iload_0
    //   120: invokevirtual charAt : (I)C
    //   123: istore_1
    //   124: goto -> 82
    //   127: aload #5
    //   129: putstatic burp/Zg61.a : [Ljava/lang/String;
    //   132: bipush #27
    //   134: anewarray java/lang/String
    //   137: putstatic burp/Zg61.b : [Ljava/lang/String;
    //   140: goto -> 300
    //   143: dup_x2
    //   144: pop
    //   145: invokevirtual toCharArray : ()[C
    //   148: dup_x1
    //   149: arraylength
    //   150: dup_x2
    //   151: pop
    //   152: iconst_0
    //   153: istore #6
    //   155: dup2_x1
    //   156: pop2
    //   157: dup_x2
    //   158: iconst_1
    //   159: if_icmpgt -> 259
    //   162: dup2
    //   163: swap
    //   164: iload #6
    //   166: dup2_x1
    //   167: caload
    //   168: swap
    //   169: iload #6
    //   171: bipush #7
    //   173: irem
    //   174: tableswitch default -> 241, 0 -> 212, 1 -> 217, 2 -> 222, 3 -> 227, 4 -> 232, 5 -> 236
    //   212: bipush #94
    //   214: goto -> 243
    //   217: bipush #47
    //   219: goto -> 243
    //   222: bipush #12
    //   224: goto -> 243
    //   227: bipush #123
    //   229: goto -> 243
    //   232: iconst_1
    //   233: goto -> 243
    //   236: bipush #37
    //   238: goto -> 243
    //   241: bipush #10
    //   243: ixor
    //   244: ixor
    //   245: i2c
    //   246: castore
    //   247: iinc #6, 1
    //   250: dup
    //   251: ifne -> 259
    //   254: dup2
    //   255: dup_x1
    //   256: goto -> 166
    //   259: dup2_x1
    //   260: pop2
    //   261: dup_x2
    //   262: iload #6
    //   264: if_icmpgt -> 162
    //   267: pop
    //   268: new java/lang/String
    //   271: dup_x1
    //   272: swap
    //   273: invokespecial <init> : ([C)V
    //   276: invokevirtual intern : ()Ljava/lang/String;
    //   279: swap
    //   280: pop
    //   281: swap
    //   282: tableswitch default -> 40, 0 -> 99
    //   300: new java/math/BigInteger
    //   303: dup
    //   304: iconst_1
    //   305: bipush #32
    //   307: newarray byte
    //   309: dup
    //   310: iconst_0
    //   311: bipush #81
    //   313: bastore
    //   314: dup
    //   315: iconst_1
    //   316: bipush #10
    //   318: bastore
    //   319: dup
    //   320: iconst_2
    //   321: bipush #78
    //   323: bastore
    //   324: dup
    //   325: iconst_3
    //   326: bipush #-98
    //   328: bastore
    //   329: dup
    //   330: iconst_4
    //   331: bipush #-126
    //   333: bastore
    //   334: dup
    //   335: iconst_5
    //   336: bipush #-22
    //   338: bastore
    //   339: dup
    //   340: bipush #6
    //   342: bipush #111
    //   344: bastore
    //   345: dup
    //   346: bipush #7
    //   348: bipush #-82
    //   350: bastore
    //   351: dup
    //   352: bipush #8
    //   354: bipush #-10
    //   356: bastore
    //   357: dup
    //   358: bipush #9
    //   360: bipush #59
    //   362: bastore
    //   363: dup
    //   364: bipush #10
    //   366: bipush #30
    //   368: bastore
    //   369: dup
    //   370: bipush #11
    //   372: bipush #-60
    //   374: bastore
    //   375: dup
    //   376: bipush #12
    //   378: bipush #-8
    //   380: bastore
    //   381: dup
    //   382: bipush #13
    //   384: bipush #-14
    //   386: bastore
    //   387: dup
    //   388: bipush #14
    //   390: bipush #28
    //   392: bastore
    //   393: dup
    //   394: bipush #15
    //   396: bipush #-69
    //   398: bastore
    //   399: dup
    //   400: bipush #16
    //   402: iconst_m1
    //   403: bastore
    //   404: dup
    //   405: bipush #17
    //   407: bipush #-39
    //   409: bastore
    //   410: dup
    //   411: bipush #18
    //   413: bipush #-13
    //   415: bastore
    //   416: dup
    //   417: bipush #19
    //   419: bipush #-84
    //   421: bastore
    //   422: dup
    //   423: bipush #20
    //   425: bipush #-58
    //   427: bastore
    //   428: dup
    //   429: bipush #21
    //   431: bipush #40
    //   433: bastore
    //   434: dup
    //   435: bipush #22
    //   437: bipush #-19
    //   439: bastore
    //   440: dup
    //   441: bipush #23
    //   443: bipush #-112
    //   445: bastore
    //   446: dup
    //   447: bipush #24
    //   449: bipush #-63
    //   451: bastore
    //   452: dup
    //   453: bipush #25
    //   455: bipush #77
    //   457: bastore
    //   458: dup
    //   459: bipush #26
    //   461: bipush #-113
    //   463: bastore
    //   464: dup
    //   465: bipush #27
    //   467: bipush #11
    //   469: bastore
    //   470: dup
    //   471: bipush #28
    //   473: bipush #54
    //   475: bastore
    //   476: dup
    //   477: bipush #29
    //   479: bipush #25
    //   481: bastore
    //   482: dup
    //   483: bipush #30
    //   485: bipush #75
    //   487: bastore
    //   488: dup
    //   489: bipush #31
    //   491: bipush #45
    //   493: bastore
    //   494: invokespecial <init> : (I[B)V
    //   497: putstatic burp/Zg61.Zp : Ljava/lang/Object;
    //   500: sipush #-30033
    //   503: sipush #16884
    //   506: invokestatic a : (II)Ljava/lang/String;
    //   509: putstatic burp/Zg61.ZX : Ljava/lang/String;
    //   512: return
  }
  
  private static Throwable a(Throwable paramThrowable) {
    return paramThrowable;
  }
  
  private static String a(int paramInt1, int paramInt2) {
    int i = (paramInt1 ^ 0xFFFF8ABB) & 0xFFFF;
    if (b[i] == null) {
      char[] arrayOfChar = a[i].toCharArray();
      switch (arrayOfChar[0] & 0xFF) {
        case 0:
        
        case 1:
        
        case 2:
        
        case 3:
        
        case 4:
        
        case 5:
        
        case 6:
        
        case 7:
        
        case 8:
        
        case 9:
        
        case 10:
        
        case 11:
        
        case 12:
        
        case 13:
        
        case 14:
        
        case 15:
        
        case 16:
        
        case 17:
        
        case 18:
        
        case 19:
        
        case 20:
        
        case 21:
        
        case 22:
        
        case 23:
        
        case 24:
        
        case 25:
        
        case 26:
        
        case 27:
        
        case 28:
        
        case 29:
        
        case 30:
        
        case 31:
        
        case 32:
        
        case 33:
        
        case 34:
        
        case 35:
        
        case 36:
        
        case 37:
        
        case 38:
        
        case 39:
        
        case 40:
        
        case 41:
        
        case 42:
        
        case 43:
        
        case 44:
        
        case 45:
        
        case 46:
        
        case 47:
        
        case 48:
        
        case 49:
        
        case 50:
        
        case 51:
        
        case 52:
        
        case 53:
        
        case 54:
        
        case 55:
        
        case 56:
        
        case 57:
        
        case 58:
        
        case 59:
        
        case 60:
        
        case 61:
        
        case 62:
        
        case 63:
        
        case 64:
        
        case 65:
        
        case 66:
        
        case 67:
        
        case 68:
        
        case 69:
        
        case 70:
        
        case 71:
        
        case 72:
        
        case 73:
        
        case 74:
        
        case 75:
        
        case 76:
        
        case 77:
        
        case 78:
        
        case 79:
        
        case 80:
        
        case 81:
        
        case 82:
        
        case 83:
        
        case 84:
        
        case 85:
        
        case 86:
        
        case 87:
        
        case 88:
        
        case 89:
        
        case 90:
        
        case 91:
        
        case 92:
        
        case 93:
        
        case 94:
        
        case 95:
        
        case 96:
        
        case 97:
        
        case 98:
        
        case 99:
        
        case 100:
        
        case 101:
        
        case 102:
        
        case 103:
        
        case 104:
        
        case 105:
        
        case 106:
        
        case 107:
        
        case 108:
        
        case 109:
        
        case 110:
        
        case 111:
        
        case 112:
        
        case 113:
        
        case 114:
        
        case 115:
        
        case 116:
        
        case 117:
        
        case 118:
        
        case 119:
        
        case 120:
        
        case 121:
        
        case 122:
        
        case 123:
        
        case 124:
        
        case 125:
        
        case 126:
        
        case 127:
        
        case 128:
        
        case 129:
        
        case 130:
        
        case 131:
        
        case 132:
        
        case 133:
        
        case 134:
        
        case 135:
        
        case 136:
        
        case 137:
        
        case 138:
        
        case 139:
        
        case 140:
        
        case 141:
        
        case 142:
        
        case 143:
        
        case 144:
        
        case 145:
        
        case 146:
        
        case 147:
        
        case 148:
        
        case 149:
        
        case 150:
        
        case 151:
        
        case 152:
        
        case 153:
        
        case 154:
        
        case 155:
        
        case 156:
        
        case 157:
        
        case 158:
        
        case 159:
        
        case 160:
        
        case 161:
        
        case 162:
        
        case 163:
        
        case 164:
        
        case 165:
        
        case 166:
        
        case 167:
        
        case 168:
        
        case 169:
        
        case 170:
        
        case 171:
        
        case 172:
        
        case 173:
        
        case 174:
        
        case 175:
        
        case 176:
        
        case 177:
        
        case 178:
        
        case 179:
        
        case 180:
        
        case 181:
        
        case 182:
        
        case 183:
        
        case 184:
        
        case 185:
        
        case 186:
        
        case 187:
        
        case 188:
        
        case 189:
        
        case 190:
        
        case 191:
        
        case 192:
        
        case 193:
        
        case 194:
        
        case 195:
        
        case 196:
        
        case 197:
        
        case 198:
        
        case 199:
        
        case 200:
        
        case 201:
        
        case 202:
        
        case 203:
        
        case 204:
        
        case 205:
        
        case 206:
        
        case 207:
        
        case 208:
        
        case 209:
        
        case 210:
        
        case 211:
        
        case 212:
        
        case 213:
        
        case 214:
        
        case 215:
        
        case 216:
        
        case 217:
        
        case 218:
        
        case 219:
        
        case 220:
        
        case 221:
        
        case 222:
        
        case 223:
        
        case 224:
        
        case 225:
        
        case 226:
        
        case 227:
        
        case 228:
        
        case 229:
        
        case 230:
        
        case 231:
        
        case 232:
        
        case 233:
        
        case 234:
        
        case 235:
        
        case 236:
        
        case 237:
        
        case 238:
        
        case 239:
        
        case 240:
        
        case 241:
        
        case 242:
        
        case 243:
        
        case 244:
        
        case 245:
        
        case 246:
        
        case 247:
        
        case 248:
        
        case 249:
        
        case 250:
        
        case 251:
        
        case 252:
        
        case 253:
        
        case 254:
        
        default:
          break;
      } 
      char c = '';
      int j = (paramInt2 & 0xFF) - c;
      if (j < 0)
        j += 256; 
      int k = ((paramInt2 & 0xFFFF) >>> 8) - c;
      if (k < 0)
        k += 256; 
      for (byte b = 0; b < arrayOfChar.length; b++) {
        int m = b % 2;
        if (m == 0) {
          arrayOfChar[b] = (char)(arrayOfChar[b] ^ j);
          j = ((j >>> 3 | j << 5) ^ arrayOfChar[b]) & 0xFF;
        } else {
          arrayOfChar[b] = (char)(arrayOfChar[b] ^ k);
          k = ((k >>> 3 | k << 5) ^ arrayOfChar[b]) & 0xFF;
        } 
      } 
      b[i] = (new String(arrayOfChar)).intern();
    } 
    return b[i];
  }
}


/* Location:              C:\Program Files\BurpSuitePro\burpsuite_pro.jar!\burp\Zg61.class
 * Java compiler version: 21 (65.0)
 * JD-Core Version:       1.1.3
 */