package burp;

import java.math.BigInteger;

class Zg64 extends ClassLoader {
  static String Zv;
  
  static Object Zs;
  
  private static final String[] a;
  
  private static final String[] b;
  
  static void ZT(Object[] paramArrayOfObject, Object paramObject) throws Throwable {}
  
  static boolean ZD(Object[] paramArrayOfObject, Object paramObject) throws Throwable {
    // Byte code:
    //   0: invokestatic ZN : ()Z
    //   3: istore_2
    //   4: new java/lang/StringBuilder
    //   7: dup
    //   8: invokespecial <init> : ()V
    //   11: astore_3
    //   12: iconst_0
    //   13: istore #4
    //   15: iload #4
    //   17: bipush #32
    //   19: if_icmpge -> 1355
    //   22: iload #4
    //   24: tableswitch default -> 1348, 0 -> 168, 1 -> 205, 2 -> 242, 3 -> 279, 4 -> 316, 5 -> 353, 6 -> 390, 7 -> 427, 8 -> 464, 9 -> 501, 10 -> 538, 11 -> 575, 12 -> 612, 13 -> 649, 14 -> 686, 15 -> 723, 16 -> 760, 17 -> 797, 18 -> 834, 19 -> 871, 20 -> 908, 21 -> 945, 22 -> 982, 23 -> 1019, 24 -> 1056, 25 -> 1093, 26 -> 1130, 27 -> 1167, 28 -> 1204, 29 -> 1241, 30 -> 1278, 31 -> 1315
    //   168: aload_3
    //   169: getstatic burp/Zmt_.ZH : Ljava/lang/String;
    //   172: getstatic burp/Zr1t.ZP : Ljava/lang/Object;
    //   175: checkcast java/math/BigInteger
    //   178: invokevirtual intValue : ()I
    //   181: bipush #32
    //   183: irem
    //   184: invokestatic abs : (I)I
    //   187: invokevirtual charAt : (I)C
    //   190: invokevirtual append : (C)Ljava/lang/StringBuilder;
    //   193: pop
    //   194: iload_2
    //   195: ifne -> 1348
    //   198: goto -> 205
    //   201: invokestatic a : (Ljava/lang/Throwable;)Ljava/lang/Throwable;
    //   204: athrow
    //   205: aload_3
    //   206: getstatic burp/Zti7.Zc : Ljava/lang/String;
    //   209: getstatic burp/Znu.Zf : Ljava/lang/Object;
    //   212: checkcast java/math/BigInteger
    //   215: invokevirtual intValue : ()I
    //   218: bipush #32
    //   220: irem
    //   221: invokestatic abs : (I)I
    //   224: invokevirtual charAt : (I)C
    //   227: invokevirtual append : (C)Ljava/lang/StringBuilder;
    //   230: pop
    //   231: iload_2
    //   232: ifne -> 1348
    //   235: goto -> 242
    //   238: invokestatic a : (Ljava/lang/Throwable;)Ljava/lang/Throwable;
    //   241: athrow
    //   242: aload_3
    //   243: getstatic burp/Ze84.Zv : Ljava/lang/String;
    //   246: getstatic burp/Zr14.Zy : Ljava/lang/Object;
    //   249: checkcast java/math/BigInteger
    //   252: invokevirtual intValue : ()I
    //   255: bipush #32
    //   257: irem
    //   258: invokestatic abs : (I)I
    //   261: invokevirtual charAt : (I)C
    //   264: invokevirtual append : (C)Ljava/lang/StringBuilder;
    //   267: pop
    //   268: iload_2
    //   269: ifne -> 1348
    //   272: goto -> 279
    //   275: invokestatic a : (Ljava/lang/Throwable;)Ljava/lang/Throwable;
    //   278: athrow
    //   279: aload_3
    //   280: getstatic burp/Zgpx.Z_ : Ljava/lang/String;
    //   283: getstatic burp/Zexl.ZG : Ljava/lang/Object;
    //   286: checkcast java/math/BigInteger
    //   289: invokevirtual intValue : ()I
    //   292: bipush #32
    //   294: irem
    //   295: invokestatic abs : (I)I
    //   298: invokevirtual charAt : (I)C
    //   301: invokevirtual append : (C)Ljava/lang/StringBuilder;
    //   304: pop
    //   305: iload_2
    //   306: ifne -> 1348
    //   309: goto -> 316
    //   312: invokestatic a : (Ljava/lang/Throwable;)Ljava/lang/Throwable;
    //   315: athrow
    //   316: aload_3
    //   317: getstatic burp/Zrjq.Zx : Ljava/lang/String;
    //   320: getstatic burp/Zt4p.Zh : Ljava/lang/Object;
    //   323: checkcast java/math/BigInteger
    //   326: invokevirtual intValue : ()I
    //   329: bipush #32
    //   331: irem
    //   332: invokestatic abs : (I)I
    //   335: invokevirtual charAt : (I)C
    //   338: invokevirtual append : (C)Ljava/lang/StringBuilder;
    //   341: pop
    //   342: iload_2
    //   343: ifne -> 1348
    //   346: goto -> 353
    //   349: invokestatic a : (Ljava/lang/Throwable;)Ljava/lang/Throwable;
    //   352: athrow
    //   353: aload_3
    //   354: getstatic burp/Zb0q.Zr : Ljava/lang/String;
    //   357: getstatic burp/Zt81.ZY : Ljava/lang/Object;
    //   360: checkcast java/math/BigInteger
    //   363: invokevirtual intValue : ()I
    //   366: bipush #32
    //   368: irem
    //   369: invokestatic abs : (I)I
    //   372: invokevirtual charAt : (I)C
    //   375: invokevirtual append : (C)Ljava/lang/StringBuilder;
    //   378: pop
    //   379: iload_2
    //   380: ifne -> 1348
    //   383: goto -> 390
    //   386: invokestatic a : (Ljava/lang/Throwable;)Ljava/lang/Throwable;
    //   389: athrow
    //   390: aload_3
    //   391: getstatic burp/Zsn4.ZZ : Ljava/lang/String;
    //   394: getstatic burp/Zoe.ZG : Ljava/lang/Object;
    //   397: checkcast java/math/BigInteger
    //   400: invokevirtual intValue : ()I
    //   403: bipush #32
    //   405: irem
    //   406: invokestatic abs : (I)I
    //   409: invokevirtual charAt : (I)C
    //   412: invokevirtual append : (C)Ljava/lang/StringBuilder;
    //   415: pop
    //   416: iload_2
    //   417: ifne -> 1348
    //   420: goto -> 427
    //   423: invokestatic a : (Ljava/lang/Throwable;)Ljava/lang/Throwable;
    //   426: athrow
    //   427: aload_3
    //   428: getstatic burp/Zzht.Zv : Ljava/lang/String;
    //   431: getstatic burp/Zkdq.ZG : Ljava/lang/Object;
    //   434: checkcast java/math/BigInteger
    //   437: invokevirtual intValue : ()I
    //   440: bipush #32
    //   442: irem
    //   443: invokestatic abs : (I)I
    //   446: invokevirtual charAt : (I)C
    //   449: invokevirtual append : (C)Ljava/lang/StringBuilder;
    //   452: pop
    //   453: iload_2
    //   454: ifne -> 1348
    //   457: goto -> 464
    //   460: invokestatic a : (Ljava/lang/Throwable;)Ljava/lang/Throwable;
    //   463: athrow
    //   464: aload_3
    //   465: getstatic burp/Zlbd.Zq : Ljava/lang/String;
    //   468: getstatic burp/Zl2t.ZS : Ljava/lang/Object;
    //   471: checkcast java/math/BigInteger
    //   474: invokevirtual intValue : ()I
    //   477: bipush #32
    //   479: irem
    //   480: invokestatic abs : (I)I
    //   483: invokevirtual charAt : (I)C
    //   486: invokevirtual append : (C)Ljava/lang/StringBuilder;
    //   489: pop
    //   490: iload_2
    //   491: ifne -> 1348
    //   494: goto -> 501
    //   497: invokestatic a : (Ljava/lang/Throwable;)Ljava/lang/Throwable;
    //   500: athrow
    //   501: aload_3
    //   502: getstatic burp/Zt9f.Zg : Ljava/lang/String;
    //   505: getstatic burp/Zso.ZA : Ljava/lang/Object;
    //   508: checkcast java/math/BigInteger
    //   511: invokevirtual intValue : ()I
    //   514: bipush #32
    //   516: irem
    //   517: invokestatic abs : (I)I
    //   520: invokevirtual charAt : (I)C
    //   523: invokevirtual append : (C)Ljava/lang/StringBuilder;
    //   526: pop
    //   527: iload_2
    //   528: ifne -> 1348
    //   531: goto -> 538
    //   534: invokestatic a : (Ljava/lang/Throwable;)Ljava/lang/Throwable;
    //   537: athrow
    //   538: aload_3
    //   539: getstatic burp/Zscz.ZJ : Ljava/lang/String;
    //   542: getstatic burp/Zg61.Zp : Ljava/lang/Object;
    //   545: checkcast java/math/BigInteger
    //   548: invokevirtual intValue : ()I
    //   551: bipush #32
    //   553: irem
    //   554: invokestatic abs : (I)I
    //   557: invokevirtual charAt : (I)C
    //   560: invokevirtual append : (C)Ljava/lang/StringBuilder;
    //   563: pop
    //   564: iload_2
    //   565: ifne -> 1348
    //   568: goto -> 575
    //   571: invokestatic a : (Ljava/lang/Throwable;)Ljava/lang/Throwable;
    //   574: athrow
    //   575: aload_3
    //   576: getstatic burp/Zmlr.ZJ : Ljava/lang/String;
    //   579: getstatic burp/Zedu.ZL : Ljava/lang/Object;
    //   582: checkcast java/math/BigInteger
    //   585: invokevirtual intValue : ()I
    //   588: bipush #32
    //   590: irem
    //   591: invokestatic abs : (I)I
    //   594: invokevirtual charAt : (I)C
    //   597: invokevirtual append : (C)Ljava/lang/StringBuilder;
    //   600: pop
    //   601: iload_2
    //   602: ifne -> 1348
    //   605: goto -> 612
    //   608: invokestatic a : (Ljava/lang/Throwable;)Ljava/lang/Throwable;
    //   611: athrow
    //   612: aload_3
    //   613: getstatic burp/Zs0h.ZX : Ljava/lang/String;
    //   616: getstatic burp/Zxn4.Zx : Ljava/lang/Object;
    //   619: checkcast java/math/BigInteger
    //   622: invokevirtual intValue : ()I
    //   625: bipush #32
    //   627: irem
    //   628: invokestatic abs : (I)I
    //   631: invokevirtual charAt : (I)C
    //   634: invokevirtual append : (C)Ljava/lang/StringBuilder;
    //   637: pop
    //   638: iload_2
    //   639: ifne -> 1348
    //   642: goto -> 649
    //   645: invokestatic a : (Ljava/lang/Throwable;)Ljava/lang/Throwable;
    //   648: athrow
    //   649: aload_3
    //   650: getstatic burp/Zkjj.ZT : Ljava/lang/String;
    //   653: getstatic burp/Zk8i.ZN : Ljava/lang/Object;
    //   656: checkcast java/math/BigInteger
    //   659: invokevirtual intValue : ()I
    //   662: bipush #32
    //   664: irem
    //   665: invokestatic abs : (I)I
    //   668: invokevirtual charAt : (I)C
    //   671: invokevirtual append : (C)Ljava/lang/StringBuilder;
    //   674: pop
    //   675: iload_2
    //   676: ifne -> 1348
    //   679: goto -> 686
    //   682: invokestatic a : (Ljava/lang/Throwable;)Ljava/lang/Throwable;
    //   685: athrow
    //   686: aload_3
    //   687: getstatic burp/Zx5w.Zq : Ljava/lang/String;
    //   690: getstatic burp/Zbli.Zo : Ljava/lang/Object;
    //   693: checkcast java/math/BigInteger
    //   696: invokevirtual intValue : ()I
    //   699: bipush #32
    //   701: irem
    //   702: invokestatic abs : (I)I
    //   705: invokevirtual charAt : (I)C
    //   708: invokevirtual append : (C)Ljava/lang/StringBuilder;
    //   711: pop
    //   712: iload_2
    //   713: ifne -> 1348
    //   716: goto -> 723
    //   719: invokestatic a : (Ljava/lang/Throwable;)Ljava/lang/Throwable;
    //   722: athrow
    //   723: aload_3
    //   724: getstatic burp/Zmn0.Zk : Ljava/lang/String;
    //   727: getstatic burp/Zgsy.ZC : Ljava/lang/Object;
    //   730: checkcast java/math/BigInteger
    //   733: invokevirtual intValue : ()I
    //   736: bipush #32
    //   738: irem
    //   739: invokestatic abs : (I)I
    //   742: invokevirtual charAt : (I)C
    //   745: invokevirtual append : (C)Ljava/lang/StringBuilder;
    //   748: pop
    //   749: iload_2
    //   750: ifne -> 1348
    //   753: goto -> 760
    //   756: invokestatic a : (Ljava/lang/Throwable;)Ljava/lang/Throwable;
    //   759: athrow
    //   760: aload_3
    //   761: getstatic burp/Zk92.Zc : Ljava/lang/String;
    //   764: getstatic burp/Zetf.Zs : Ljava/lang/Object;
    //   767: checkcast java/math/BigInteger
    //   770: invokevirtual intValue : ()I
    //   773: bipush #32
    //   775: irem
    //   776: invokestatic abs : (I)I
    //   779: invokevirtual charAt : (I)C
    //   782: invokevirtual append : (C)Ljava/lang/StringBuilder;
    //   785: pop
    //   786: iload_2
    //   787: ifne -> 1348
    //   790: goto -> 797
    //   793: invokestatic a : (Ljava/lang/Throwable;)Ljava/lang/Throwable;
    //   796: athrow
    //   797: aload_3
    //   798: getstatic burp/Zzyb.Zh : Ljava/lang/String;
    //   801: getstatic burp/Ze4w.Zd : Ljava/lang/Object;
    //   804: checkcast java/math/BigInteger
    //   807: invokevirtual intValue : ()I
    //   810: bipush #32
    //   812: irem
    //   813: invokestatic abs : (I)I
    //   816: invokevirtual charAt : (I)C
    //   819: invokevirtual append : (C)Ljava/lang/StringBuilder;
    //   822: pop
    //   823: iload_2
    //   824: ifne -> 1348
    //   827: goto -> 834
    //   830: invokestatic a : (Ljava/lang/Throwable;)Ljava/lang/Throwable;
    //   833: athrow
    //   834: aload_3
    //   835: getstatic burp/Zzi_.ZG : Ljava/lang/String;
    //   838: getstatic burp/Zrip.ZB : Ljava/lang/Object;
    //   841: checkcast java/math/BigInteger
    //   844: invokevirtual intValue : ()I
    //   847: bipush #32
    //   849: irem
    //   850: invokestatic abs : (I)I
    //   853: invokevirtual charAt : (I)C
    //   856: invokevirtual append : (C)Ljava/lang/StringBuilder;
    //   859: pop
    //   860: iload_2
    //   861: ifne -> 1348
    //   864: goto -> 871
    //   867: invokestatic a : (Ljava/lang/Throwable;)Ljava/lang/Throwable;
    //   870: athrow
    //   871: aload_3
    //   872: getstatic burp/Zer1.ZV : Ljava/lang/String;
    //   875: getstatic burp/Zk8f.ZG : Ljava/lang/Object;
    //   878: checkcast java/math/BigInteger
    //   881: invokevirtual intValue : ()I
    //   884: bipush #32
    //   886: irem
    //   887: invokestatic abs : (I)I
    //   890: invokevirtual charAt : (I)C
    //   893: invokevirtual append : (C)Ljava/lang/StringBuilder;
    //   896: pop
    //   897: iload_2
    //   898: ifne -> 1348
    //   901: goto -> 908
    //   904: invokestatic a : (Ljava/lang/Throwable;)Ljava/lang/Throwable;
    //   907: athrow
    //   908: aload_3
    //   909: getstatic burp/Zgpx.Z_ : Ljava/lang/String;
    //   912: getstatic burp/Zelt.ZC : Ljava/lang/Object;
    //   915: checkcast java/math/BigInteger
    //   918: invokevirtual intValue : ()I
    //   921: bipush #32
    //   923: irem
    //   924: invokestatic abs : (I)I
    //   927: invokevirtual charAt : (I)C
    //   930: invokevirtual append : (C)Ljava/lang/StringBuilder;
    //   933: pop
    //   934: iload_2
    //   935: ifne -> 1348
    //   938: goto -> 945
    //   941: invokestatic a : (Ljava/lang/Throwable;)Ljava/lang/Throwable;
    //   944: athrow
    //   945: aload_3
    //   946: getstatic burp/Zedq.Zj : Ljava/lang/String;
    //   949: getstatic burp/Zs_m.Z_ : Ljava/lang/Object;
    //   952: checkcast java/math/BigInteger
    //   955: invokevirtual intValue : ()I
    //   958: bipush #32
    //   960: irem
    //   961: invokestatic abs : (I)I
    //   964: invokevirtual charAt : (I)C
    //   967: invokevirtual append : (C)Ljava/lang/StringBuilder;
    //   970: pop
    //   971: iload_2
    //   972: ifne -> 1348
    //   975: goto -> 982
    //   978: invokestatic a : (Ljava/lang/Throwable;)Ljava/lang/Throwable;
    //   981: athrow
    //   982: aload_3
    //   983: getstatic burp/Zb2n.Za : Ljava/lang/String;
    //   986: getstatic burp/Zgpx.ZQ : Ljava/lang/Object;
    //   989: checkcast java/math/BigInteger
    //   992: invokevirtual intValue : ()I
    //   995: bipush #32
    //   997: irem
    //   998: invokestatic abs : (I)I
    //   1001: invokevirtual charAt : (I)C
    //   1004: invokevirtual append : (C)Ljava/lang/StringBuilder;
    //   1007: pop
    //   1008: iload_2
    //   1009: ifne -> 1348
    //   1012: goto -> 1019
    //   1015: invokestatic a : (Ljava/lang/Throwable;)Ljava/lang/Throwable;
    //   1018: athrow
    //   1019: aload_3
    //   1020: getstatic burp/Zedq.Zj : Ljava/lang/String;
    //   1023: getstatic burp/Zg61.Zp : Ljava/lang/Object;
    //   1026: checkcast java/math/BigInteger
    //   1029: invokevirtual intValue : ()I
    //   1032: bipush #32
    //   1034: irem
    //   1035: invokestatic abs : (I)I
    //   1038: invokevirtual charAt : (I)C
    //   1041: invokevirtual append : (C)Ljava/lang/StringBuilder;
    //   1044: pop
    //   1045: iload_2
    //   1046: ifne -> 1348
    //   1049: goto -> 1056
    //   1052: invokestatic a : (Ljava/lang/Throwable;)Ljava/lang/Throwable;
    //   1055: athrow
    //   1056: aload_3
    //   1057: getstatic burp/Zrp2.ZJ : Ljava/lang/String;
    //   1060: getstatic burp/Zmkq.Zg : Ljava/lang/Object;
    //   1063: checkcast java/math/BigInteger
    //   1066: invokevirtual intValue : ()I
    //   1069: bipush #32
    //   1071: irem
    //   1072: invokestatic abs : (I)I
    //   1075: invokevirtual charAt : (I)C
    //   1078: invokevirtual append : (C)Ljava/lang/StringBuilder;
    //   1081: pop
    //   1082: iload_2
    //   1083: ifne -> 1348
    //   1086: goto -> 1093
    //   1089: invokestatic a : (Ljava/lang/Throwable;)Ljava/lang/Throwable;
    //   1092: athrow
    //   1093: aload_3
    //   1094: getstatic burp/Zrye.Za : Ljava/lang/String;
    //   1097: getstatic burp/Zmz.ZW : Ljava/lang/Object;
    //   1100: checkcast java/math/BigInteger
    //   1103: invokevirtual intValue : ()I
    //   1106: bipush #32
    //   1108: irem
    //   1109: invokestatic abs : (I)I
    //   1112: invokevirtual charAt : (I)C
    //   1115: invokevirtual append : (C)Ljava/lang/StringBuilder;
    //   1118: pop
    //   1119: iload_2
    //   1120: ifne -> 1348
    //   1123: goto -> 1130
    //   1126: invokestatic a : (Ljava/lang/Throwable;)Ljava/lang/Throwable;
    //   1129: athrow
    //   1130: aload_3
    //   1131: getstatic burp/Zmt_.ZH : Ljava/lang/String;
    //   1134: getstatic burp/Zg7e.Zr : Ljava/lang/Object;
    //   1137: checkcast java/math/BigInteger
    //   1140: invokevirtual intValue : ()I
    //   1143: bipush #32
    //   1145: irem
    //   1146: invokestatic abs : (I)I
    //   1149: invokevirtual charAt : (I)C
    //   1152: invokevirtual append : (C)Ljava/lang/StringBuilder;
    //   1155: pop
    //   1156: iload_2
    //   1157: ifne -> 1348
    //   1160: goto -> 1167
    //   1163: invokestatic a : (Ljava/lang/Throwable;)Ljava/lang/Throwable;
    //   1166: athrow
    //   1167: aload_3
    //   1168: getstatic burp/Zthx.Ze : Ljava/lang/String;
    //   1171: getstatic burp/Zr14.Zy : Ljava/lang/Object;
    //   1174: checkcast java/math/BigInteger
    //   1177: invokevirtual intValue : ()I
    //   1180: bipush #32
    //   1182: irem
    //   1183: invokestatic abs : (I)I
    //   1186: invokevirtual charAt : (I)C
    //   1189: invokevirtual append : (C)Ljava/lang/StringBuilder;
    //   1192: pop
    //   1193: iload_2
    //   1194: ifne -> 1348
    //   1197: goto -> 1204
    //   1200: invokestatic a : (Ljava/lang/Throwable;)Ljava/lang/Throwable;
    //   1203: athrow
    //   1204: aload_3
    //   1205: getstatic burp/Zeqz.ZV : Ljava/lang/String;
    //   1208: getstatic burp/Zsfg.Zm : Ljava/lang/Object;
    //   1211: checkcast java/math/BigInteger
    //   1214: invokevirtual intValue : ()I
    //   1217: bipush #32
    //   1219: irem
    //   1220: invokestatic abs : (I)I
    //   1223: invokevirtual charAt : (I)C
    //   1226: invokevirtual append : (C)Ljava/lang/StringBuilder;
    //   1229: pop
    //   1230: iload_2
    //   1231: ifne -> 1348
    //   1234: goto -> 1241
    //   1237: invokestatic a : (Ljava/lang/Throwable;)Ljava/lang/Throwable;
    //   1240: athrow
    //   1241: aload_3
    //   1242: getstatic burp/Zsdl.ZJ : Ljava/lang/String;
    //   1245: getstatic burp/Zek4.ZR : Ljava/lang/Object;
    //   1248: checkcast java/math/BigInteger
    //   1251: invokevirtual intValue : ()I
    //   1254: bipush #32
    //   1256: irem
    //   1257: invokestatic abs : (I)I
    //   1260: invokevirtual charAt : (I)C
    //   1263: invokevirtual append : (C)Ljava/lang/StringBuilder;
    //   1266: pop
    //   1267: iload_2
    //   1268: ifne -> 1348
    //   1271: goto -> 1278
    //   1274: invokestatic a : (Ljava/lang/Throwable;)Ljava/lang/Throwable;
    //   1277: athrow
    //   1278: aload_3
    //   1279: getstatic burp/Zmn0.Zk : Ljava/lang/String;
    //   1282: getstatic burp/Zsn3.Zy : Ljava/lang/Object;
    //   1285: checkcast java/math/BigInteger
    //   1288: invokevirtual intValue : ()I
    //   1291: bipush #32
    //   1293: irem
    //   1294: invokestatic abs : (I)I
    //   1297: invokevirtual charAt : (I)C
    //   1300: invokevirtual append : (C)Ljava/lang/StringBuilder;
    //   1303: pop
    //   1304: iload_2
    //   1305: ifne -> 1348
    //   1308: goto -> 1315
    //   1311: invokestatic a : (Ljava/lang/Throwable;)Ljava/lang/Throwable;
    //   1314: athrow
    //   1315: aload_3
    //   1316: getstatic burp/Zbsz.Zu : Ljava/lang/String;
    //   1319: getstatic burp/Zg1l.Zg : Ljava/lang/Object;
    //   1322: checkcast java/math/BigInteger
    //   1325: invokevirtual intValue : ()I
    //   1328: bipush #32
    //   1330: irem
    //   1331: invokestatic abs : (I)I
    //   1334: invokevirtual charAt : (I)C
    //   1337: invokevirtual append : (C)Ljava/lang/StringBuilder;
    //   1340: pop
    //   1341: goto -> 1348
    //   1344: invokestatic a : (Ljava/lang/Throwable;)Ljava/lang/Throwable;
    //   1347: athrow
    //   1348: iinc #4, 1
    //   1351: iload_2
    //   1352: ifne -> 15
    //   1355: sipush #-10367
    //   1358: sipush #-22977
    //   1361: invokestatic a : (II)Ljava/lang/String;
    //   1364: invokestatic forName : (Ljava/lang/String;)Ljava/lang/Class;
    //   1367: invokevirtual getDeclaredFields : ()[Ljava/lang/reflect/Field;
    //   1370: astore #4
    //   1372: aload #4
    //   1374: arraylength
    //   1375: istore #5
    //   1377: iconst_0
    //   1378: istore #6
    //   1380: iload #6
    //   1382: iload #5
    //   1384: if_icmpge -> 1461
    //   1387: aload #4
    //   1389: iload #6
    //   1391: aaload
    //   1392: astore #7
    //   1394: aload #7
    //   1396: invokevirtual getType : ()Ljava/lang/Class;
    //   1399: ldc java/lang/String
    //   1401: invokevirtual equals : (Ljava/lang/Object;)Z
    //   1404: ifeq -> 1447
    //   1407: aload #7
    //   1409: iconst_1
    //   1410: invokevirtual setAccessible : (Z)V
    //   1413: aload #7
    //   1415: aconst_null
    //   1416: aload #7
    //   1418: aconst_null
    //   1419: invokevirtual get : (Ljava/lang/Object;)Ljava/lang/Object;
    //   1422: checkcast java/lang/String
    //   1425: getstatic burp/Zg64.Zv : Ljava/lang/String;
    //   1428: <illegal opcode> makeConcatWithConstants : (Ljava/lang/String;Ljava/lang/String;)Ljava/lang/String;
    //   1433: invokevirtual set : (Ljava/lang/Object;Ljava/lang/Object;)V
    //   1436: iload_2
    //   1437: ifne -> 1461
    //   1440: goto -> 1447
    //   1443: invokestatic a : (Ljava/lang/Throwable;)Ljava/lang/Throwable;
    //   1446: athrow
    //   1447: iinc #6, 1
    //   1450: iload_2
    //   1451: ifne -> 1380
    //   1454: goto -> 1461
    //   1457: invokestatic a : (Ljava/lang/Throwable;)Ljava/lang/Throwable;
    //   1460: athrow
    //   1461: sipush #-10365
    //   1464: sipush #19999
    //   1467: invokestatic a : (II)Ljava/lang/String;
    //   1470: iconst_1
    //   1471: ldc burp/Zgl2
    //   1473: invokevirtual getClassLoader : ()Ljava/lang/ClassLoader;
    //   1476: invokestatic forName : (Ljava/lang/String;ZLjava/lang/ClassLoader;)Ljava/lang/Class;
    //   1479: invokevirtual getDeclaredFields : ()[Ljava/lang/reflect/Field;
    //   1482: astore #4
    //   1484: aload #4
    //   1486: arraylength
    //   1487: istore #5
    //   1489: iconst_0
    //   1490: istore #6
    //   1492: iload #6
    //   1494: iload #5
    //   1496: if_icmpge -> 1634
    //   1499: aload #4
    //   1501: iload #6
    //   1503: aaload
    //   1504: astore #7
    //   1506: aload #7
    //   1508: invokevirtual getModifiers : ()I
    //   1511: invokestatic isStatic : (I)Z
    //   1514: ifne -> 1524
    //   1517: goto -> 1627
    //   1520: invokestatic a : (Ljava/lang/Throwable;)Ljava/lang/Throwable;
    //   1523: athrow
    //   1524: aload #7
    //   1526: invokevirtual getType : ()Ljava/lang/Class;
    //   1529: astore #8
    //   1531: aload #8
    //   1533: ifnull -> 1614
    //   1536: aload #8
    //   1538: invokevirtual isPrimitive : ()Z
    //   1541: ifne -> 1614
    //   1544: goto -> 1551
    //   1547: invokestatic a : (Ljava/lang/Throwable;)Ljava/lang/Throwable;
    //   1550: athrow
    //   1551: aload #8
    //   1553: invokevirtual getPackage : ()Ljava/lang/Package;
    //   1556: ifnull -> 1614
    //   1559: goto -> 1566
    //   1562: invokestatic a : (Ljava/lang/Throwable;)Ljava/lang/Throwable;
    //   1565: athrow
    //   1566: aload #8
    //   1568: invokevirtual getPackage : ()Ljava/lang/Package;
    //   1571: invokevirtual getName : ()Ljava/lang/String;
    //   1574: ifnull -> 1614
    //   1577: goto -> 1584
    //   1580: invokestatic a : (Ljava/lang/Throwable;)Ljava/lang/Throwable;
    //   1583: athrow
    //   1584: aload #8
    //   1586: invokevirtual getPackage : ()Ljava/lang/Package;
    //   1589: invokevirtual getName : ()Ljava/lang/String;
    //   1592: sipush #-10364
    //   1595: sipush #31437
    //   1598: invokestatic a : (II)Ljava/lang/String;
    //   1601: invokevirtual startsWith : (Ljava/lang/String;)Z
    //   1604: ifne -> 1614
    //   1607: goto -> 1614
    //   1610: invokestatic a : (Ljava/lang/Throwable;)Ljava/lang/Throwable;
    //   1613: athrow
    //   1614: aload #7
    //   1616: iconst_1
    //   1617: invokevirtual setAccessible : (Z)V
    //   1620: aload #7
    //   1622: aconst_null
    //   1623: invokevirtual get : (Ljava/lang/Object;)Ljava/lang/Object;
    //   1626: pop
    //   1627: iinc #6, 1
    //   1630: iload_2
    //   1631: ifne -> 1492
    //   1634: sipush #-10357
    //   1637: sipush #17814
    //   1640: invokestatic a : (II)Ljava/lang/String;
    //   1643: invokestatic forName : (Ljava/lang/String;)Ljava/lang/Class;
    //   1646: invokevirtual getDeclaredMethods : ()[Ljava/lang/reflect/Method;
    //   1649: astore #4
    //   1651: aload #4
    //   1653: arraylength
    //   1654: istore #5
    //   1656: iconst_0
    //   1657: istore #6
    //   1659: iload #6
    //   1661: iload #5
    //   1663: if_icmpge -> 1796
    //   1666: aload #4
    //   1668: iload #6
    //   1670: aaload
    //   1671: astore #7
    //   1673: aload #7
    //   1675: invokevirtual getParameterTypes : ()[Ljava/lang/Class;
    //   1678: pop
    //   1679: aload #7
    //   1681: invokevirtual getModifiers : ()I
    //   1684: invokestatic isStatic : (I)Z
    //   1687: ifeq -> 1782
    //   1690: aload #7
    //   1692: invokevirtual getParameterTypes : ()[Ljava/lang/Class;
    //   1695: arraylength
    //   1696: iconst_2
    //   1697: if_icmpne -> 1782
    //   1700: goto -> 1707
    //   1703: invokestatic a : (Ljava/lang/Throwable;)Ljava/lang/Throwable;
    //   1706: athrow
    //   1707: aload #7
    //   1709: invokevirtual getReturnType : ()Ljava/lang/Class;
    //   1712: getstatic java/lang/Void.TYPE : Ljava/lang/Class;
    //   1715: invokevirtual equals : (Ljava/lang/Object;)Z
    //   1718: ifeq -> 1782
    //   1721: goto -> 1728
    //   1724: invokestatic a : (Ljava/lang/Throwable;)Ljava/lang/Throwable;
    //   1727: athrow
    //   1728: aload #7
    //   1730: iconst_1
    //   1731: invokevirtual setAccessible : (Z)V
    //   1734: aload #7
    //   1736: aconst_null
    //   1737: iconst_2
    //   1738: anewarray java/lang/Object
    //   1741: dup
    //   1742: iconst_0
    //   1743: aload_0
    //   1744: aastore
    //   1745: dup
    //   1746: iconst_1
    //   1747: aload_1
    //   1748: ifnonnull -> 1766
    //   1751: goto -> 1758
    //   1754: invokestatic a : (Ljava/lang/Throwable;)Ljava/lang/Throwable;
    //   1757: athrow
    //   1758: aload_1
    //   1759: goto -> 1773
    //   1762: invokestatic a : (Ljava/lang/Throwable;)Ljava/lang/Throwable;
    //   1765: athrow
    //   1766: aload_1
    //   1767: checkcast [B
    //   1770: invokevirtual clone : ()Ljava/lang/Object;
    //   1773: aastore
    //   1774: invokevirtual invoke : (Ljava/lang/Object;[Ljava/lang/Object;)Ljava/lang/Object;
    //   1777: pop
    //   1778: iload_2
    //   1779: ifne -> 1796
    //   1782: iinc #6, 1
    //   1785: iload_2
    //   1786: ifne -> 1659
    //   1789: goto -> 1796
    //   1792: invokestatic a : (Ljava/lang/Throwable;)Ljava/lang/Throwable;
    //   1795: athrow
    //   1796: getstatic burp/Zz66.ZM : Ljava/lang/String;
    //   1799: getstatic burp/Ztle.ZP : Ljava/lang/Object;
    //   1802: checkcast java/math/BigInteger
    //   1805: invokevirtual intValue : ()I
    //   1808: bipush #32
    //   1810: irem
    //   1811: invokestatic abs : (I)I
    //   1814: invokevirtual charAt : (I)C
    //   1817: getstatic burp/Zspg.ZG : Ljava/lang/String;
    //   1820: getstatic burp/Zscz.ZN : Ljava/lang/Object;
    //   1823: checkcast java/math/BigInteger
    //   1826: invokevirtual intValue : ()I
    //   1829: bipush #32
    //   1831: irem
    //   1832: invokestatic abs : (I)I
    //   1835: invokevirtual charAt : (I)C
    //   1838: if_icmple -> 1953
    //   1841: getstatic burp/Zr1h.ZS : Ljava/lang/String;
    //   1844: getstatic burp/Zbw5.ZR : Ljava/lang/Object;
    //   1847: checkcast java/math/BigInteger
    //   1850: invokevirtual intValue : ()I
    //   1853: bipush #32
    //   1855: irem
    //   1856: invokestatic abs : (I)I
    //   1859: invokevirtual charAt : (I)C
    //   1862: getstatic burp/Zzac.ZE : Ljava/lang/String;
    //   1865: getstatic burp/Zb3d.Zw : Ljava/lang/Object;
    //   1868: checkcast java/math/BigInteger
    //   1871: invokevirtual intValue : ()I
    //   1874: bipush #32
    //   1876: irem
    //   1877: invokestatic abs : (I)I
    //   1880: invokevirtual charAt : (I)C
    //   1883: if_icmpgt -> 1953
    //   1886: goto -> 1893
    //   1889: invokestatic a : (Ljava/lang/Throwable;)Ljava/lang/Throwable;
    //   1892: athrow
    //   1893: getstatic burp/Zt5t.ZK : Ljava/lang/String;
    //   1896: getstatic burp/Zld9.ZF : Ljava/lang/Object;
    //   1899: checkcast java/math/BigInteger
    //   1902: invokevirtual intValue : ()I
    //   1905: bipush #32
    //   1907: irem
    //   1908: invokestatic abs : (I)I
    //   1911: invokevirtual charAt : (I)C
    //   1914: getstatic burp/Zsn9.Zp : Ljava/lang/String;
    //   1917: getstatic burp/Zrnt.Zh : Ljava/lang/Object;
    //   1920: checkcast java/math/BigInteger
    //   1923: invokevirtual intValue : ()I
    //   1926: bipush #32
    //   1928: irem
    //   1929: invokestatic abs : (I)I
    //   1932: invokevirtual charAt : (I)C
    //   1935: if_icmple -> 1953
    //   1938: goto -> 1945
    //   1941: invokestatic a : (Ljava/lang/Throwable;)Ljava/lang/Throwable;
    //   1944: athrow
    //   1945: iconst_1
    //   1946: goto -> 1954
    //   1949: invokestatic a : (Ljava/lang/Throwable;)Ljava/lang/Throwable;
    //   1952: athrow
    //   1953: iconst_0
    //   1954: ireturn
    //   1955: astore_3
    //   1956: new java/lang/Exception
    //   1959: dup
    //   1960: aload_3
    //   1961: invokevirtual getMessage : ()Ljava/lang/String;
    //   1964: invokespecial <init> : (Ljava/lang/String;)V
    //   1967: athrow
    // Exception table:
    //   from	to	target	type
    //   4	1954	1955	java/lang/Throwable
    //   22	198	201	java/lang/Throwable
    //   168	235	238	java/lang/Throwable
    //   205	272	275	java/lang/Throwable
    //   242	309	312	java/lang/Throwable
    //   279	346	349	java/lang/Throwable
    //   316	383	386	java/lang/Throwable
    //   353	420	423	java/lang/Throwable
    //   390	457	460	java/lang/Throwable
    //   427	494	497	java/lang/Throwable
    //   464	531	534	java/lang/Throwable
    //   501	568	571	java/lang/Throwable
    //   538	605	608	java/lang/Throwable
    //   575	642	645	java/lang/Throwable
    //   612	679	682	java/lang/Throwable
    //   649	716	719	java/lang/Throwable
    //   686	753	756	java/lang/Throwable
    //   723	790	793	java/lang/Throwable
    //   760	827	830	java/lang/Throwable
    //   797	864	867	java/lang/Throwable
    //   834	901	904	java/lang/Throwable
    //   871	938	941	java/lang/Throwable
    //   908	975	978	java/lang/Throwable
    //   945	1012	1015	java/lang/Throwable
    //   982	1049	1052	java/lang/Throwable
    //   1019	1086	1089	java/lang/Throwable
    //   1056	1123	1126	java/lang/Throwable
    //   1093	1160	1163	java/lang/Throwable
    //   1130	1197	1200	java/lang/Throwable
    //   1167	1234	1237	java/lang/Throwable
    //   1204	1271	1274	java/lang/Throwable
    //   1241	1308	1311	java/lang/Throwable
    //   1278	1341	1344	java/lang/Throwable
    //   1394	1440	1443	java/lang/Throwable
    //   1407	1454	1457	java/lang/Throwable
    //   1506	1520	1520	java/lang/Throwable
    //   1531	1544	1547	java/lang/Throwable
    //   1536	1559	1562	java/lang/Throwable
    //   1551	1577	1580	java/lang/Throwable
    //   1566	1607	1610	java/lang/Throwable
    //   1673	1700	1703	java/lang/Throwable
    //   1690	1721	1724	java/lang/Throwable
    //   1707	1751	1754	java/lang/Throwable
    //   1728	1762	1762	java/lang/Throwable
    //   1773	1789	1792	java/lang/Throwable
    //   1796	1886	1889	java/lang/Throwable
    //   1841	1938	1941	java/lang/Throwable
    //   1893	1949	1949	java/lang/Throwable
  }
  
  static void Zv(Object paramObject) {
    Zgrz.Zu = a(-10361, 21735);
    Zgrz.ZX = new BigInteger(1, new byte[] { 
          15, -2, -38, -45, 13, 85, -120, -20, -5, 106, 
          -7, -57, 48, -70, -65, 19, 53, -29, 18, -115, 
          -100, -106, 8, 7, -83, 18, 51, -71, 102, 17, 
          47, -120 });
    boolean bool = Zt2e.ZN();
    try {
      try {
        if (Zsts.ZI.charAt(Math.abs(((BigInteger)Zxjw.ZU).intValue() % 32)) <= Zxc.Zx.charAt(Math.abs(((BigInteger)Zsbd.Zh).intValue() % 32))) {
          try {
            Ze_e.Zi(Class.forName(a(-10363, 8626)));
            if (!bool)
              Zgss.Zg(Class.forName(a(-10368, 25311))); 
          } catch (Throwable throwable) {
            throw a(null);
          } 
          return;
        } 
      } catch (Throwable throwable) {
        throw a(null);
      } 
      Zgss.Zg(Class.forName(a(-10368, 25311)));
    } catch (Throwable throwable) {}
  }
  
  static {
    // Byte code:
    //   0: bipush #9
    //   2: anewarray java/lang/String
    //   5: astore #5
    //   7: iconst_0
    //   8: istore_3
    //   9: ldc 'Â¬Â–ÂŒÂ«bÂ¬)Â…'
    //   11: dup
    //   12: astore_2
    //   13: invokevirtual length : ()I
    //   16: istore #4
    //   18: bipush #9
    //   20: istore_1
    //   21: iconst_m1
    //   22: istore_0
    //   23: iconst_1
    //   24: iinc #0, 1
    //   27: aload_2
    //   28: iload_0
    //   29: dup
    //   30: iload_1
    //   31: iadd
    //   32: invokevirtual substring : (II)Ljava/lang/String;
    //   35: iconst_m1
    //   36: goto -> 201
    //   39: aload #5
    //   41: swap
    //   42: iload_3
    //   43: iinc #3, 1
    //   46: swap
    //   47: aastore
    //   48: iload_0
    //   49: iload_1
    //   50: iadd
    //   51: dup
    //   52: istore_0
    //   53: iload #4
    //   55: if_icmpge -> 67
    //   58: aload_2
    //   59: iload_0
    //   60: invokevirtual charAt : (I)C
    //   63: istore_1
    //   64: goto -> 23
    //   67: ldc 'Ã¹.Ã—Ã±ÂºÃ¾ÃŠ^Ã“ÃºL> 6&.&Ã®ÂœÂ³& Ã°ÃŒvÃ«Ã–Â·3FÃ®Ã²Ã«Ww-ÂœÃ­{Â§Â¤Â+Â¢Ã¶GE`Â¤Â»Ã»Â­TÂ·mÃ˜Ã¹\\fG9ÂÂ‘Â‚Ã…/SÂ‰ÂÂg'Ã•h<Ã¤NÂ²W\\rÃ»Â¦Â¨NÃ¹$Â¨7Ã†Ã…Ã—3pDzÂÃ”Ã“ÃµeÃOÂÂŒÃ†ÂÂ¨ÂÃ“\\rÂÃ¼>Â”Ã£Ã¶Ã‹Ã±ÂºYÂ†ÂªÂ¾]eNÃ­Ã¡ÂÂºq[ÃL^Ã©Ã¬Â¸Â²zÂ‰]Â»Â»XÃ­Â¡z\\rÂ•Ã½Ã…Â•^Â™lÂÂª#/Â“efOÃ°Ã‘Ã‚HÃÃŠÃ¡Â‰RkfÃ³@Ã›Ã¿nÂ³Â­TÂ¢/Ã°Â´1ÂšÃ¦Ã‰'Ã¸Ã¥TÂ©5Â´Ã¶Â‰)Â„Ã‰-9Â‡Ã·@|Â\\nÂªÃ¡Â–Ã½Â†Â´ Ã©}Ãšn>,Â’ÂÂÂ›61Â‡Ãµ8c+Â°Â¦Â¦$Â†Â¶2Ã”Ãœ\\nÂ§Â·Â¥6Â²>MÃÂ¼Â¯ÃÃ•Ã=B w"~~ÃºÃŸ13Â³Â½ÃÂ¸K#ÂƒgÃ¥]Ã¥Â©`I2$Ã–Ã®jÃ¡udÃ¬9s]XOÂ©fÂ¾Â·Â6Â˜Ã½Â—juÃ¸ÃºÃŠ;Ã”Ã½Ã­pÃ”ÂÂ¸&Â¥b!Â‰Ã¤'hÃºÃ€Ã†Ã«Ã€Ã´IÃ°Â¬Ã€IÂ¤Â´Â¢IÂ›ÃµÂ´Â“ÂVvIg\\fÃ°Ã•d_\\t)\\t&Ã¡Â”]rÂ’Â©ÂƒÃÂ¼Â¨!`^RLÂ¨\\n[Ã¡Ã³IVÂ&Ã¦Ã€LarÂŸrÂ¿KÃ”Â—/gÃ“Ã„R3@LÃ¯Â‡Ã¶Ã©I@ÃŒzÃ´1ÂœÃ³\\nÂ˜O7Â¦Ã­7eÃ–BÂ£Â Â§ÂÃ®Â¢Ã¡|&Â”Â¤fÃÂ¶0\\tÃ™Ã°Ã¶Â•Â¢Âr*Â˜Ã¦\ÃÂÂ³ÃÂV(@Â¢Â´Ãº_t9{Ã¯r\\fGÂšOjFÂ¢Â–Â²~GV.Â©ÂªÂÂ©Ã¸Ã¢9v!Â½Ã‰ÃZqÂ¹:ÃˆÂˆÂÃ“Ã]ÃŒÂ’Â¿9Ã¯{&YÃ‰Â²'ÂšÃ¹Â¶Â‹xÃ³%Â¾1Â¸|9Ã¨zI<Âhz>3I'EjÃ¢EQRÃÃ”Â£Â¼Ã„ÃÂƒÂªÃ²Ã£Ã•Â€/ÃÂœÂ€oÃ»Ã»pÃ¡Ã°-Â’Ã·Â¿Â…\ÃbÂ”Ã†Ã­Ã“Â­e\Ã¶ ÂL'Â‹Ã›ÂÂ“1c}ÂªÃ±ol#Â¡Â€bJÃÂ¡Ã§ÂªCÂªVÂMkwÂ„Ã®Âˆ{Ã ÂcÂ¥VvÂÂ¶Â³Ãœx\\bÃ¨:Ã¶*IMÂ¹Ã“bÂ³ÃÂÃ‹Â˜hÃ»ÃŒÂ¨DÂ«A""eÂ‹}k0ÃƒÂ‰^OÃ’Ã¤"Â‡ÂŸÃ«]Ãƒlj3Ã+'GÃ¿Ã¼=Â[Â¯Ã•ÃÂ¯+ÃÃÂšÂ€Â¹)Â´Â–ÃµÃ Â*q5vjÂ¬Ã2+U\\n+Â·51Â„m!hÃ™Â˜Ã„_Ã‹Ã´Ã¯'WÂlÃ¯Âœ\\rgÃ†Ã]8pTÃ¯Ã„Ã¾Ã¥ÃÂŒ3Ã’Â¼Â©ÂºÂ™hÃ¢Ã¢Â©Â•Ã˜+Ã/Ã§Ã¸Ã†Â\\bÃ’Â¡AÂ¬Â—Â\\fÃ”Â¦Â¬Ã«ZKÃ‹Â¸Ã¿?Ã¨Ã­\\nÃ‹Â¿*7Ã“Ã›[Ã´Â¸[Â™Â–ÃÃ­Ã‰Âª*Ã‰ÃˆÂƒYÂ—Ã¨YÃ’ Ã.Â®Ã¾ÃƒÃ€PJÂÃµ=P\\bÃ›ÃÂº\\fÂ€Ã¶Â»dGÂ±Â®Ã¤ÂŒÂ®Âˆ\Â JÂ³{Ã%Â‹G'ÂlÂ¶Ã¿Ã«L/Ã¹Â›Â°he`*ÂFÂ¡Ã’Ã¶Â±Â›Ã—Â’Â¼<yÂ›Â²Ã\ÃŸÃ…Â¥\\tÃ‡Ã—Ã¢Ãˆtc[Â¶uÂ¦ÃÃ‘Â¸]A9Ã Â€TÃµÃJÂ½'ÂÃ Â‚Â»Ã"Â·j1Ã”ÃÂ‡RWYKÃŸ\\tÂ7\ÂdÂŸÃ”Â­GUgÃ·Â”MMÃ™Ã­Ã¡Â•ÃÂÂ¡ÃkÃ‘sxÂ«Ã™Â¹ÂÂ²1Ã¸gÃƒÃ­ÃšpÂ­#YQ2FÃ™Y^Ã´ÂŠCÂaÃ³Ã±Â°{Â¯Â†ÃŠ{LFÃŸÃ¸dÃ±FmÂ£07AR'ÃŸcÃ¹ÂÃ–Ã¶\\rÃšÃ–Ã¼G?!PÂÃ–Â‹Ã¹Â¤Ã‰Â¬eÂŠ9Â²TQa1Â†Â³Ã†`>Â¨Ã…Ã³Âƒ_Â²CÃ¡ Ã'*w7t{Ãµ4Ã¯'-PÃšÂŠÂ£Ã“CGÂ€ÃŒEhÂ®Ã¤Ã½4ÂÂº)Â”Ã¶ÃœSÃ‘Â¦Â˜lY{Â¶Ã°ÃÃsA2`Ã¶Ã“_Ã”ÃƒÃ·Ã¦ÃÃ§Â°iÃ„qÃ³SÂ¬p?Â»(Â™ÂŒ]Â·<Â­Â„Â’!nÃ˜ÃÂ—Â•Ã¬Â»Â¥(a#Â¨ZÂ¤Ã·Â‘1Â¸LÃ‰Ã’\\tÃ”Ã´Â¶)ÃŸVÃ’RÃ‘Ã½bzXrSÂ•ÃÃ»ÂœÃ¥z2Ã¹Â§:bgÂºÂ¬Ãi\\n`uÂ¹xQRI_Ã†Ã‘Ã¬[Ã¼ÃÂ©.ÃÃ¦NÂ®CWÂ(7,Ãµh@+,ÂŒÂ¥\\fÃ˜8Ã¾ÃÃ·Ã›lU<Â¾Ã¡+jÂ½Ã¸pÃ•Â…EÂ²D-Â IÂ…cÃ±Âš7a6Â¼+Ã‡Â‚Â‹VÃ«ÂªÃ›Ã“Â¬~Â¸ÃÃ Ã¸\\r*Ã·rQbÃ‰Â„Â»ÃšO?ÂŸÂ… EÂ”dÂÂ«WOVÃ“Â§Ã¦Â”hgTÃ±ÂªÂ­Â¾RÂ‚ÂŸ//AÂ«D\\nÂ»n3Ã§#Ã³Â‡CÂ‰Ã¤Â†kÂ¥#Ã­^Â¼M\\nÂªdÃ§Ãµa[Â±WAÃŠINÂ˜ÂŒÂ£saÃˆ$,Â²O)ÃÃÃ¹Ã¢6Ã’DÃ­%}DFÂ“g1Ã­Â¼Ã©[%Ã™Ã»3,Â¼Â·ÂºÂ‘k1Â°NÃ°\\t\\fx`ÃŠ<Ã±Â‹Ã¡CÂªÃ™%Ã’cÂ±Â±ÂšÂ¡ÃdÃµTÂxV[Â°Zc'Ã¡ÃM~Â‚Ã¡FÂ¢8Ã­ÃÃÂšÃªrÃ’Ã©BÂ˜Â¦ÂºÂªAÂÃŠE:Ã¡Â€Â³Â½Ã­L+Ã•Ã‹Ã‚z8Ã¹Ã‹rÃZÂ©ÃœlÂ„cÃ°{_Ãˆ{ÂµÂÃ›Ã‚!Â¹Âz~1Ã¨ÃÂ¯4Ã†Â˜+ÃŠÂ½Â¼Ã³~Ã›Ã­ÃÂºÃ™WÂ¶Â´UmÂ¬ÃAHrÃ‰ÂŸkÂ¥Q[ÂŠÂ§^Ã…Ãƒ\\fÃ–Ã¡ÂšiÃ¢9Â»Ã­Ã·ÂMwÃˆÃƒ\\f\\bÂ—ÂÃ‰KFMÃ¤gÂ€YÃ­^*Â¼^Â­Ã¿Â¢fZ]eÂ¢.yÃ—$Ãƒ\\fÂ—aÂ¼Ã°ÃmtÂÂ¶\\t\\nÃƒÂ¥gÂ£\\tHÂÃ²aeÃ¼Ã¤Â‘}Â‰Â­ÂšaÂ¯g};LÃ=tHtrÃ¹Ã¡Â’Â”Â¥Ãº\\ti$Ã·Ã†PXÃÃ¥pzÃ|Â›muÃ‡ÂÂ´Ã¥Â…xÃ’Ã“Â¬MÂ¦Ã¦8;Ã´ÃN[Â€cÃ²Ã‹_oKÂŸÂ¯mJÂš Ãƒ7BQbÂ¢ÂÂ«ÃÃŒHÂ¥Â’1Â£QhÃ—Â…Ã‚Â¼Ã£Ã—Ã¤.Â Ã¦Ã¦BÃ‹~rÂ³IÂ–Â˜%Â¨Â¬Â¬Â–Â”5Ã–mÃ²9dÃ«@Â£`ÃÂ­Ã§Â—Â|vÃ”Ã….ÂªUÃ§M0,ÃªÂ”Ã¸RÃ†r0cÃ‡ÃƒÂ¤Â„7Â˜Â°Â³9uÂ,Â»\\tÃ¾*ÂœÃŠ3WÃ‚Ã±Ã—q\\nÃ¾ÂšÂ„\\fÃ“Ã™Â²DÂÃ¥Â»Ã¯Ãˆ\\fÂƒÂ™LoÃ™Â’Ã—Â˜|,{Ã»UÃIÃ»ÃŒ&aÂÃŒHÃ—Ã¬Â—bF8-Ã¡~Ã±GÃ¼Ãš\\t=Â‚UÃª$Ãª0+}\\r;Â½Ã™Ã›!Â„Â±:lJdÂ€P~Ã |TÃ«Â¥ÂšÂ§Â®ÃŒa)aÃ¶GÂŸÂ¨6Ã¨ÃUÂ„6Ã²Â¤}iFÃª@Ã…Ã«ÂšÃ¥YXÃ‹ Ã‘i2Â«ÂšFÃ¤GÃ­Ãƒ;Â_HZÂ±Ã¯ Ã–Ã„,+Â¹~?Ã´\h3#C\\tÃ›kVÃŸÃ±2ÃŒQaÃŸÃI0ÃÂ¨ÃÂ›ÂŸÃÃ•ÃŸÂ§Â—Â­ÂŠjÃÂ¹-\\b\\bHÃ§ÂˆÂ¿kÃ‡V#3Â¿Â¥Ã•Â¾Â¸+Ã¬yÃŸ}xÂ”/RkÂ¼ÃyfÂšS(Ã´Ã­ÂµÃ¦Ã&Ãº?Â¶QÂµ)Â±Â–zm2QÂ¬MÃ¾Â…Â­Ã±q60QÂ´6Â­Ã™q&]Ã‡\\tÃ¥ÃÃxÂŠÃ¼Â•BÂ™Â«Â•Â‘&Ã¥Â¨Ã„+oÃQÂ¦ppÃÂ‡oÂ¸y475ÃŸ_Ã¯Ã›Â˜v'Â˜%ÂŠÂ”SÂÂÃµÂº9Ã›Â½RÂŒÃ¨Â»Â¬Â²Â£~%Ã­2ÂµxÂ‰EÂÂ¶Ã­Ã¢\\bWbÃ‚Â™Ã/!ÃÃÂÂ®Ã¶< Â²\\fÂ›EÃ±Ã‹Ã´ÂŒÃ§Ã¨+xÂªMÂ¯8ÃŠ`bZ7ÃœZ\\\fdÂ›Ã­;}Â‹Â„Ã¸ÂÃƒBÃªÃ‡Â¯Ã«ÃŠÂ¡Ã»Â—w"Â¡K%Ã´:~@EUÃ³tÃ€Qw:Â„Â°Â‡\\bÃ˜<Â ÃƒÂ¯Ã»Ã¢4Ã‰LÂ®oÂ‘\\n<Âœ>ÂEÃ•Â”,Ã‡6.O\\rÂ®NÃ—jÃŒÂ€Â Ã“KEx!vLÂ”/ÃÃ¯Ã¥Â‰Â‡Â•QÂ‚UZÃ„Â·ctyÃ€"Ã³Ã†Â¯ZÃ«hÂ†Ã¶(1Â¹ÃºÃ£Ã³7/Ã Â‰uL\\fÃ¥elÂœÃ”Â›\\fÃ¬qÃ»QsÂSÃ€Â†ÂŒÃ¬Â·Â‘ÂˆJÂ•>Â˜ÃÂ—ÃŸyvÃ¸Ã±Ã°TaGÂºÂ®Â›DLÂ¬Ã²JTÂ¾fÃ¿cxgg/xqÃ˜Ã˜\\t!Â¨Ã«Ã‚Ã¥ÂŸAÂ¿Â¿Â„Â¸.ÃœÃ¬:Â§Â¤7Â­8Â²ÂmÃ\@Â…V^Â½MÃ¯Ã˜Ã—[qÃ€Â­Ã‡ÂrÃ 0Ã‘ÂˆÃŒÃ™ÃÃÃÃ3ÂÃ Ã®Ã¾$Â¾Â’2Â¸Â¶;Â½Ã Ã´NhÃ§UÃƒÂ“NÂ´KÂ­X[ÃµÃºÃ ÂˆÃ‘ÃªÃRLyf%aÂ„0`*Â”ÃºÂŠpÃ¢.Ã¦BÂ…Â‚ÂÂ‡9o3Ã·Ã¸mÃ·3Ã¼ÂŸÂ³0"\\nÂ©)Ã›'PvÂ“'sÂ‚fÂ£UC86Ã•Â|Ã…GÂ´B\\rvÃªsÂÃ“qÂ˜Ã­#Â‚ÃÃ®:8#TzÃŸfjÃ¥WÂ‡sÂ®Â©:Â³Ã¶(iÃÃ²ÂŒÂ–Ã‘Ãº*Ã²Â¹Ã–YÂ 1WÃ•taÃ‡U9Â]Ã¬Ã´hÂ¾Â«Â“Ã£\\rXt}vÃ¡Â—gÂ—Â™Ã™Ã˜ÂªÃ;Ã©\\rÃ’'U!Â–&Ã—:p06Â»XÂa@Ã€+ Â‡Ã«-ÂµDÂ“%@\\bÃ¥xi>ÃŒu!#['Ã©I#ÃˆÃªÃÃ“VTÃÃ§Ã¾Ã«Â¸Ã—Â»Ã°xÂsdÃšHÂŸ=BÂšÃ½Â€ QQÃ®>Ã¥]MÂ‘AÂ¦<Â±rÃ€Ã¯Ã¬Ã‚Â£Â•&Â„Ã£*"{Ã’4Ã®ÃÃ³KFAJÂ«Ã³Ã‚Â¯Ã‡VpÃ¡!ÃÂŸÃŒÂŠÃ³Ã‚Ã„MQÂ­Â 3\\nÃ˜ÃŸÂÂ•Â‡Â…Ã«\\fÂºYÃ³ K\\tm&#ÂÃ€ÂÂÂ™Ã¯Ã‡Ã¦5Â˜\\bR&yÃ¼ÂÃ¡Â w6Â‡rPYlfÃ±Â¢%Ã¦7Â˜6Ã‘Ã‹@Ã´Ã•OÂ²Ã°cMb)Ã­Ã²Â¼ÂœÃÃ§Y+Â²Ã™Z+#Ã…4^nÃ›wYÃ‰Ã–Â“7Â£WnÃŸÂ‚Â•W&\\f\\fmH(Ã$f"ÃŒÃƒ-_ÃÃ¾KQÃŒ&Â½Â¹nÂ§ÂÃ¾Â„Â‰Z,Â®`nÃ´'xÂ‹Â„ÂÂ™jwÂªÃ¹Â®ÂªÂ­Ã„Â»JA+Ã§Ã¥~EÃ®ÃœoÃˆÃ½\Â£Â¾YxEÃ«hhÃ‘@ÂŠÂ‚ÃJÂ®Â’QHÃ¹ÂµÃ©bÂˆ?7(Ã¼\($Ã¼Q&6Â±Ã¸Â“Â¨Ã³Ã¤Â»Â²Ã½Ã“cÂÂÃ‚ÃŠÂ½Â€Ãˆv4\\nÃ§Â¼Â€Â„)qAÃŸÂ˜Ã·S Ã•Â”Ã‡ÂÃ‘Ã@Â‘ÂœTÂÃ¾Ã¿EÃÂ‡ÃªxphÂ¢-Â†Â­qxÃ›/b1Â°Ã‡Ã°\\ryÂ¹xÂÃ—Â¼Ã—fÂ´5KÂœÂ´Â•Ã¾Â‹H#Ã¨Ã“Â¡Ã‚Ãš-Ã°faÂ¾<ÂŒi=Ã±lXS\Ã”JÃ½Â—{=Ã˜Âµ{iÃ¶iÂ‹ÃµÃŒmÂ¹!Ã£Â†\\t2/YxÂ²%Ã·dÃ’ Ã‚7b.Âˆ|Â¿Ã¥ÃšÂ.FxvÂ·Ã†Y,ÃÃ^_Ã¥Â£Â®Ã†Ã¤Ã©!\\n\\nL)Â­RÃ‘Â–ÃˆÃ§WÃ¤YÂ™)oÂˆÂ¯GÂ¢tÃ’1g4Ã¨{Â¨ÃˆÃ¡Â¦1%Â‹Â‰hÃ‘fÂˆÂ±Ã€Ã·6Ã \+Â¤ÃÃ‹Â´Ã·Ã‡Ã”Ãœ\\bÂ’Â¸Â›zÃ´Â–Â“Ã²Â§Âœ'Ã†ÃµL{k6ÃµJÃƒeOÂ¯Â‘(,Ã§k!@Ã‡Â¹_Ã§EÃ¢9Ã„WÂ¦Â¸8ÂÃ†BÃ».SgoÂ§-mÂŒwÂÂ¾ÂÂ»Ã¿<^Â¨Ã^\ÂÂŠÂ›ÃÂ«Â¼Ã„!Ã¢>Â‹=cVÃ¢Ã¯bÂˆÂ³Ã/Ã‚ r?UÃ¡Â˜Â¹Ãº3Â‘ÃÂ—Ã¦Ã™Â¤@ÃºBIÂ[Â®Ã´*ÂN\\rP~Â¹Â“Ã•4Ã¢eÃ¯Âœ\\fÂ°Ã™Ã—HÃ˜ÃºÃƒÂ•Â†Ã¯RÃ³Ã¹Â§pÂ½Ã®8ÂƒÃ±:2r'SÃÃRÂ£gh\\rÂŒÃ¦Â˜Â‹ÃºÃ™ÂÂ“$Ã”Â­Â¹Â©ÃµH[2Ã€jÃ‡vÂ–aÃ£%(Ã–ÃŸÃˆÂ‹Ã“jFÂ”sÃµ[Â½CÂ¢Ã»Âƒ Ã£ÃÃ«Ã›Â¨}Ã‰Â†ÂœÃ“Â³ÃƒÃ·&}Ã‘Â²Ã¦#Âº5Â¼q<Â·Â·/ÃŠÃ”SÃ£Â”Â‹Â›zÃÂ¦Â¹Ã»Â›ÂˆLÂÃ§Â„Â±Ã»Ã¡tÂ‡`Â“mÃ­ÃŒÂ­Â½XÂ¯)ÃµÂ”kÂƒ@Ã¢Ã€VlÂ¡Â…Ã‡Ã”3Ã»p\tpÃ—Â‰Ã¿Ã‡DS:Âµ)?Â•Â¯Ã¤Ã›PÃºÂ Ã™Ã”Ã¯Â¥Ã€Ã–)Ã“/Ã†zÂ“ÃÃ£Ã¿Â±Ã€ZÂÃ‹Ãƒ,Ãº>ÂœÂ¬Â§\\rÃ¦B!u}%Â¹dÂ¢Â¢Â¡Ã…Ã’aÃ¢pÃ—Ã‹Ã’Ã PÃ¬Â«Â½\\r=Â¦ÂÃšÃ¦Â„Ã‘Ã¡huÃ«Ã“ÂŠ#Â‘Â¥Ã<eÃ¥Ãi~}Â‹uÂ¦Ã…Â©Ã½LÂ¤Â«Â®et~Â§bÃ®=Ã‘Ã®Â¶&9'ÃŠÃµÃÃº}K7Ã…ÃjÂ‡Â‡`Â—Â¦Â†Â“QÂ\\n ÂÃŸÃ©zÃ¨DR Â´zÃ‰P )Â¡Ã¡MyÂœÂ¨LÂ‚0Ry-Ã”vÂ›ÃfaÂ˜Â†ÃÃ¹kÂEÃ TÃ¶HÃŸÃ²ÃšÂ¦Ã°eÃ¼WÃ¨Ãˆ ÃšÂƒk\t^:ÃCÂ­C\Ã†Â»ÃŸÂ™5vÃ¦Â”Ã°ÂÃ¾Â¦PÃÃˆÂ“Â†zRÂ¾Â\\r[ÂÃ„Â«})Ã¨eÃŸE\\fÃ¸Ã‰Â‘Ã…\\t6ÃšÃ‹Â,M/ÃˆÃ’Â“b?Âš1YÂ»Â±`QNÂ€Ã;Â™\Ã€wÃÂˆ\\rYÂ™"Ã™v _!Ã‰Âšv2Ã³Â¯ÃÃ™ÃŸÂªo5Â¹ÂˆaÃƒ(hÃ”Â¿Â„ÂµÃ°a \\n+Ã‰Ã¤Ã›<[ÃŸ!HÂ“Ã¿EÃœ,Â’'Â‡ÃRÂ±,Ã‰Â•P4ÂÂ¾)Â’Ã€]'TÃ·-Â³bÂ‡Â¡Ã«Ã²ltÃ½JrmÂ¹Â´:Ã£'XÃ½SBjÂ”Â‰Â¢Â½Ã®Â€kÂ»yÃˆÃ‘ Ã”Ãw#\\t)p\\fÃ™Ã²Ã°Â»Â]Ã‰,)Â„Âº{ÃµÂ½Â±PÃÃÃ‡Â±ÃºÃ—4=OwÂÂºrÃ¬>9Ã©\\r.Ã-Ã¼@'ÃºÂƒÂÂÃ°Ã»Ã¨Â²Ã¸ÂŠ Â‘Â­WÃ—RÃ›hÃœhKÂÂ½Â¯PÂ¢ÃSÃ¾ÃÂ·Â„3Â‡ÂÃ aÃ•^Ã¸Ã¤Â˜Ã”@5ÂÃ“Ã†!Ãº6Ã((`Y/Ã‡Ã¤OÂŒx ÂœÂªÂºÂ’(Â¶hÃÃ”*Ã–Â­Ã·Â¡KÃ¼Â¤Â½ÂŒ(_Ã–pÃ±WÃ™Ã¼Ã–Ã¦Ã¿Ã9ÃÃ£NQ?Ã¨Â˜Ã‚Ã˜'EgÂªÃ± ?eÂ¾Ã¯b%1Â“XÂ‡Â¬y.Ã·Â¢Ã”Ã¸ÂµÃ±Ã€b0xÂ²Â‘Ã€QÂ¶Â©ÃÃ™Ã¸5%Â›Ã¯Ã´CRkÂ°Â³ÂšvÃ0ÃˆÃ–Ã¶*Ã”8Âª1ÂµÂ´8ÂšÂ¦Â®Ã·-ÃxÂ·})(}1?b)Â¼ÃŒ ÃÃ¹IÂ™Â›ÂÃ‡8=[xÃ—/?ÂƒÂ’Â¢Ã°Ãˆ{Ã¥Ãƒ-Ã©1Ã¨Ã¯Âœ`Ã…Â•mNÂ°Â§-E;ÂTÃRFÂÃ«kL\\nÂ°Â¬Â‰Â’Â¨)ÂµÂ½Â»U=Ã§Ã‚OÂ'Â²Gn+<:iFÂ¬Ã‚2ÂƒÂ¢Ã¡Â†<\\tÃuÂ©Â–GÃ‰Âˆ{ÂÃ­Â¦z?Ã‰JÂŸÂ½Ã’ÂŸÂ‡4Ã¢Â…8SpGÂ¥Â‚Â†Â¯ÂÂŠ$Ã²'ÂºÃ·ÂœÂ³Â1 Â€OÂ7{Ã¬~\\rRÂƒÂ¡;Ã¸Ã™Â¸kÂ Ã›f"Â MÃ¦+&ÃµÂ°Ã›Ã˜HÂº,Â„Ã–Â€Â„Ã´Â¯Ã‚9qÃÃ’LÂšÃ°IÃÂ¦Â•Â†ÃƒÂ—|Â¡Â³pÂ€Â„Â¼Ã¬Ã›ÂGI&/%\\b[Â†Â•Â“7ÂÃ¯Ãºhh!jÃ ÂŸÂÃˆkÂ½@Ã–Ã…oÂ³"Ãƒ aAÂ¢*ÃºÂº\\ba;ÂšJÃªÃ‘\DÃÃŸÂ‚i$Ã¤ÂfpÂ¢gÂ¼cxS{92tÂ™Â†n<_ÂŸHÂ Ã]Â©Â’Ã‚Â‘ZÂ Ã¬qÂšÂ¼bÃ >#VÃ–NÃ¥3(gÂµÂ¹eÃ¨Â•/Â«Ã«Pa"Ã»ÂŠÃ¨<Â›Â«Â‚Â“ji\Ã»g+Ã†yÃ·#Â†Â“Â³Ã¯ÃšÂ¹ÂŸLÃ™Â‚Â«ÂœÂ‚GÃ£Ã³ÃˆÃ€ÂŒ[^ÂœÃÂ‰Ã£Ã•9<}Â‚Â¨(_jÃ­Â˜ÃÃ—Â¡pÃ˜Ã¾7Â§Ã¶Ã²4$Â ÃHÂ™iÂ†eÂŠ+Ã…tQ;Ãšd&92Â Â—YZ\\r:ÂƒÃ’gqÃ–Ã¡Ã£Â¡Ã€l;Ã™PÂ¬Ã¨Â”Â„oÃÂŠÃ½PoÃ¶ÃŒÃ¯(Ã¬.ÂÂ°Ã¥5ÂÃÃ¨PÃ¡Â¡Ã©^Ã£PÃÃ·Ã—TÂª"ÂˆF`Â›Â§Ã¼Â·Ã§Â˜sÂ;_*uÃ•Ã©VÂ¬Ã•Â°Â±Ã§IÂ´TÃ†ÃªmÃ¢%HÂ·bZ}q1Â°Ã´\\nNkÃšÂ½<ÂŸÃ’Â´Ã´Ã£Â’ÂºÃŸ(Ã’nÂ†Â¶djÃŒg\\b{ÃœÃA<ÃºToV)a\\tÃ¸"ÃºEÃ•2ÂbÃ¨Ã™,Ã©Ã§Ã²[ÂNÃ¥Â¥9Ã“Ã6Â¿Â¬Ã®Ã¬-O=Ã–ÂœaÃ›9ÂŸÃ¿\Â†Â¤Â•ÃÃ¾Â™Ã±Â¸Â¼ÃªÂ…Â°ÂÃ«Â‚Â‘\\nrÃ ÂŠcÃ¾ÃÂ¾\\bÂ„Ã¿u#ÂŸÂ€l[Ã®Â†sÃ¡Ã¡Ã›kFÂ²ÂºÂÂšs~Â˜Â¨MbÂÃ¸Ã¶Ã¥c=Ã—lÂ‹}ÂŸÂ¡!ÃƒÂ¿Â±Ã©Â¢ZÃ¡Ã§ÃªÃª\5x$ÃµÃ¤Â¦Â„Â…F1Â·wÃˆÂ½Ã¹\\b~ Â°(oÂ½9!ÂŒÃ€6*Â•4ÂW Â•LÃ£ÂWÃ¹JtGÃ—auÂ‰ÃŒÃ§ÂFÃ¾ÃºÂ¦Ã¶ÃµÂ´QÃ“9OÃ¢AÃ³~\\fW=Â—Ã¢Ã€THÂ’ÂÂ©Ã‰EÂ«Ã‡Â¿f!`Ab=\\ny3Ã‡$QU4Â‡xÃ¹/Ãª:Ã†I\SÂ¡Â3Â‰TÃ¿Ã‡Ã©2;zÃƒÃ¥Ã†ÃÃNww{Â¡<YÂŸÃŸoÃ‡ @Â£\\fZÂ°>+ BÃ¡Ã”'Â˜qoÃ¡eÂÂ‘Â…ÂA3Â½BÂÃ¨ÃŠHÃ¥ÂŠÂšeI"ÂŸÂ£Ã¶rÂ¬!ÂLBÂÃ‡Ã )e|UÂ“j'ry/Â³ÂsbÃ¦"Â»ÃÂ£ÃÃ’Ã£Ã‹Â±Ãª+Â‘ÂŸÂ´ÃªÃ…~W+Â“Ã¥Ã›zÃ£Â’PAÂƒhÂ‚Â’DÂ±Ã’ [\\bÃ¥Ã»3Â¸ÃªÃ®Ã¢Â½Â£Â¬"qt(@+?Ã‰Ã¬Â«ÂX\\nÃª(GÃ¢ÃœÂ”Â«e\\naSfÃŒiÃ…zÂ\\bXÃ§Q{Â•Â£ÂšÃœÂ—RÂˆqÂš1*YÃ“ZÂŸz~ÃºÂˆ}b11Ã€LÃ¼Â—@mÃ™qÃ­h'ulÂ– Â¢Ã‹Ã…qÂ›ÂŒ'Â9&Â¥CbZÃ”ÃŠ\EVVyAÃ†vÂ¾6pÂ ÂµÃšÂŒÃ¬ÂšÃ¾Â—pÂƒÃ·Â’MÃ²Â·T?#Ã³ÃÃ£Ã±Ã¶Â”Ã°Â†ÂŸIÃ&oÂšÃ›Â¬ÃI?Ã€ÂŸÂ Ã”0ÃµÃ‚Â‚Â¥ÂÂ tÃ»pqÃ´pÂÂ»1Ã•Ã²_Â‚Rq2Â‘JviÂ¯jTCÃ¿UÂ³'`Ã—\\fÃ¦{W7Â Ã‰YzDkÃ¸cÂÃÃ²Ã—CÂ‡KÃ‹LÃŠÂ·Ã¾BOÂp}Â‚BÃÂ¯Ã¸<Â‹\\fzÃ¨Ã±MÂ¯NfÂÃ¦ÃƒÃ…Ã„!Â’Â‹ÂŠÃÂ¤poÂŸ\\tFÂ®oÃ¾Ã¹m\\rb(ÃÃƒÂ­"Ã¸mÃˆÃ¿\\fÂ‘\\b}\\tf)Â£Ã¿Â²ÃšÂ¾Ã°~EÃ´Ã­?Ã tÃ¿Â£ÃÃŸ6ÂFÃ“^ÃƒaHÃº'Ã†Â„}Ã‚Â¹Ot1FLxÃ‘pÂ…Â‰Ã¶Â‡Â¦Â¿BÃ°mÃºÃ¿ÂÂ‡Ã›'Ã»Â˜y`Â‹Ã¤Ã¥Â°Ã•Ãƒ"Â„Â­Â£Ã¼ÃÃ©Âš>Ã¹Â 9Â¾OÃ¨gÂ¦ yÂ¤Â™Â¤ |Â…GÂ²Ão'kHHÃfÂ0Ã´Ã Ã“Â†Â¬G\=E.[ Â¦Â¶\\tÂ›Ã²eÃ²qÂ»Â´FÃ·TÃ€Ãš,Â¦ZpÂoÃ¿zk Ã”Rk%Â³Â¥h)Ã¤WÃ€}Ã®w\\.Â¶>\\fÃ Ã«Â¯OÃ¯Ã­-\\b^sÃˆÃºÂµÂ™Ã¾Â†Ã—Ã¯Â¤ÂÂ¬ÃšÃº'Â»WÃ‚ÂtÂ‹Âˆ|Â†Â³\\fÃ§&Ã»Â“Â›MÂ¸\\\f:ÂœÃÂ·Ã2]Ã¯Â†kÂ£Ãš\\bÃ‰YÃˆ8Â…WÂŠÃ·QÂÃˆÂ¬!Â*Ã¡GÂ£ÂŠÃ²Ã½PÂÂ±Â´Ã„Ã±Ã·\\tSÂ“Â„Ã§~9Â”Â°Ã…E1:ivÃ¯ÃœÂ®xÂ‡AÂ›Ã›/Â‚0Ã§NRAÂ‰Â€^D|US4J8Ã’YÂ»F!9BÃŸÂ½ÃKrÂ½ZÂ¬Ã“pU+Â€\GÂŠÃ—Ãœ_ÂÃ‚Â©ÃŸÂ˜)Â¡Ã»Â£Ã¸Â¦Ã¬\\nÃˆÂš"\[Ã”6G+VÂ‰ÃÃ†Ã„Ã‘ÃHÃŒÂ©Ã¡Ã’Â‰FÃ¦Ã¹L\*\\ryÂ‡.Â®Â‘S+Â†[/Ã¬Ã™y1xÃœ\\fÃ§}Â "Ã¡Â•ÂÂ‘ÃÂˆÂ¥ÃŠÃ¼uÃ†Ã»Â…Â¾Â®Ã¹7Â»DÂ£Ã€KÂ³@Â†Â¯Â®mÃ¶sÂ€Â²WaÂ²u*Ã‰MÃ—Ã§Ã¥Â»Â˜Ã¹Ã "Â•Â·ÃœÂ”BÂ¾Â»;ÂŒ{Ã§^oÂ’ÂÂ£Â³_GÃŒÃ¡ÂƒÃ…ÃÂ´WÃ¯rCÂ¯ÂªÂ‰Ã¿Ã’Ã Ã²Ã™N1ÃšÂ‘Â^.ÃœÂ¬cH$^~Ã‚C&Â£Ã°Â«SÃ¯Ã¯<Ã‹=Vqos>KÂœ&Ã…8Â‚Ã‘)Â9j\\bÂ‚#Ã‚hÂ»t_Â¿&=Â—jLÃÂÂ™ÂŠ=uÂ®ÃµÃŸ>OmÂƒÂ…Ã¯Ã®{Ã¤kÂ˜h8ÃŒÂªÂ•8ImÃ¦ÃKÂ¥.Â¡Â›Ãª Ã£gNÂ´Â¡\n4ÃŒCaHÂ»?5Ã‰Ã±ÃšYBÂ¨Â¼^ÃšOÂ“~Â»Â¿Ã¡Ã€ÃµÂÃ’ ÂªÂuÃ ScSNÂ¬ÃÃ»Â¹kÃ‡VÂ¿Â£Ã²Ã¡:Âu[Ã•x9]_ÃÂƒÃœÂ´ÂŒÃ¨%XÂ·CÃ„Ã6Ã•Ã©ÂIBpA]EÂÂ§Ã‚E'T Ã˜Â¥ÃÃ¡Ã´OÃ½Ã¼ÂµÃ¿Ã¦Ã§lÃ¦\\nÂ„#ÃÂ—qOÃ›Ã§Ã­Â¯tbÃÂ®ÃÂGÃ }ÃœÃ®dk"pÃˆE*Ã†ÃÃGÃ¶5\\tÃ†Ã‹@Â¢xJÃn\\tCÂÂŸÃ™jÃ»ÂŒJÃƒÂª%Ã•Ã‰DjÃ“~Ãš"ÃˆÂ’SgÃÂ–eP$Ã¥I#Ã¾`BcFÃ²ÃÃ¡aÂ‹Ã²V\ÃŸ7r;NiÂLÂ”Â Ã³Ã³B?GÃÂ½PÂawld )HÃ·qQÃ¸ÃŠÂ½{}Ã¼Ã€ÂÃ±Ã¯-Â½Ã…ZÂ½Ã±#FÂˆCDÂÃ°P.oZÃ„ÂÃª^ÃŒ\\tqWk]Â¼Ã£Â©Â›ÃŸÃ®Ã¼Ã“%Â¦1RÂ 0\Ã‚mjÂ±~R+ 1Â¾ÂšÂ¬.e0Ã²Ã¨Â®0ÂºYÃƒ{ÃšKÂ½=jÂ„.Â¶ÃÃÂ€ÃÂ¬Â¸Â´Ã´8pÂ€Ã‰ ÃºÂˆ'Ã»?Â·BÃ¬Â¶Ã—V3Â°"ÃºÃ¦Ã¸Ã’Âd0Â™2Ã•4\\tÂšÃºzW tÃ»Ã¯JÂŒÃ“MAÂ‹Â˜Ã¾Ã•Â¤fhÃ»Âš!QÃ¶Â¼Â¿Â¨CgzÂ•Ã‰bfÂ™Â˜SÂ (uÃÃŒÂ¨YLIÂ XÃ¦Ã¹ &Ã¿ÃŒÃ¾XÂ—ÂÃµÂ³]ÂŠÂƒCÂºÃ¥Â°Â†Â`*ÂŒW1Ã¡cÂ¥ÂºÂšÃ“*ÂƒcÃ†\\bÂ‡>6Ã›Â£Â…Â¦Â€Â½(;ÂŒÃ>Â±''Â¦)ov!vÂ•Ã¢Â³._}g:SÃV~Â¹Ã¢NdgÂ„Ãƒ^\\bÂ·ÂŠÃ¿Â€Â—>#\\fjÂ‰Â¿nÂ˜Ã·Ã«*/\\rÃ¦+=Ã‘Â¥ÃºÃˆÂ¤ÃªÂ ÂÂ”Ã¢ÂºÃ+TÂ¨6Â—Ã‘Â’*XÃŒÃ ÃÂ¶( ÂƒÃ¡Ã’Â‘Ã¾||Â¸(5Ã³Ã½ 7Vni}Ã¨Â—Ã“Â²Â‘Â«Â5nN/Â–Ã¾YÂ¹ >jÃŠI<ÂˆÂ½Â¦u0VdÃºÂ³Â¨Â¤Ã€ÂgÃ¬Ã˜e'Â°$5Ã½ÂšÂ­#.Ã¿aÂ¥]x.Ã¶Â¹Ã{Â¥ÃŒÂ­ÂªÃ¶DÃªÃ¯Âœ)ÃµÂ‚+Â²ÂµÃ˜cÃ„Â¡Ã›Â—Ã£vÃ½Â´xÂ›%~UÃ§1X&ÃŒD2OÃ›Â½qÂ©Ã£Ã½Ã·Ã™(Ã‰Ã"ÃŠoFÂŒÂ¾jÃŠ!Ã•Ã›vÂ‡ÃµgÃ­,JX:ÂˆÂ¡Â²({Â°> Ã‚ÂŠ} Â­Ã¢OÂŸ8F\\b<Ã‘Â«e18Ã±ÂÃ£LnÃ„F1WKSZ4dÃ­Â‘Â«giÃ…Ã›Â…qÂ”Â›H;_ÂšCÂ kÂŸ\\fÃ="{Ã¹GG8Â¾ÃªÃ»ÃŸÂ’Â”cÂ­ÃŸ\\nÃ.ÂŸÂ¿Â·Ã¸`3ÃºÂ½Ã‡Â¨Â¢5Â©IÂ—ÂUÂšhÂ¶Ã­[Ã®&Ã¾Â¯KÂ³Â½GÂ˜Â·Â–eAÃ‡Ã¾Ã±BÂ‘ÂŸÃ°Â’ÂÃƒÂ¥Â¦+a>/\\b\\tÃ‘Â†Ã—rsÃ¤Ã…Ã›HÃ›$q}ÃÃAÂ‘ÃœÃœÃ–VÂ›Ã„GÂ„Ã½HÂ¥tÃ™IeÂ¤\\tÂ‡.Â Ã¯Â²Ã­Ã€\\r8vÃ°[1Â¡@Ã‘ÃºÃ¹HÃ¼WÂ‚Ã´wÃŸÃ½LÂ»ÂÃ·"ÃÃÂ†kÂ¶ÃÂ¾Ã ,Â€ÂƒÂ¹Â…\\rSÃ®Ã­Â°%Ã»Ã”ÂšÂ›Â…Ã“Ã­+Ã¡6Ãº*Ã¶\\nÂ°@Ã•xÂŸÃ™Ã<Ã¸Â·;4Â Â¤Â€Â‹JÂ‰x<Â“ArÃºÂ²Â¦Ã†Ã½:Ã´d\\rÂ¥ÃºTp&Â°zÃˆÃL-HÂ…Ã–@Âr$Â¿Â•Â®-Ã“*Tnt.+Â«Ã².ÂµKÂ§GÃ™Ã’c7ÃœÃ”_Ã¡Â“ÂœÂqÃ‰Â¹ÃŒÃµÂ¥Ã¾Â¨Ã±ÂyÂÂº?Ã—Ã¨#iÂÂŠÃ™^2Ã¹Ã¡XÂ™YwbÃ½ÂŸÂ¤Â¿MDÃ=Ã¡uÃƒJyÂ­ÃµÃ¢Ã_ÃÃŸÃ«ÃªGÂ’eÃ‚Ã‘Â·Â¶&ÂŸÂ½VÂ•uÂ¥Ã¬ÂcÃ©Ã«Â§c4}Ã©Ã½Ã¿<?Ã±G$Ã°ÃªMakÂ¹Â±Ã°%Ãš!kÂ¦ÂƒiLÃ¾Âƒ\\bÂÂ—ÃÃÂ¥Ã‰{GÃ¹9^'ÂŸ9N9Ã`Ã…ÃÃÃ©O7{Â²Ã¯Ã¢_Ã†$6T}=Â´ÃÂ·gEÃ–Â²Ã“Ã¡Ã§Ã±&sXÂjÂ·Ã™Â¤Ã”qÂ«UÂ°W\\bXAÃ²Â¿3Ã¨Ã’Â±1Â€4Â¤5ÃrZÃ»:Ã¿Â¡ Ã—Ã²ÂŒÂ­f(\\bÂ8Ã’Â•vÃ‹^Ã«dKÂƒÂœj&zxÃ³Ã†Â¨AÃ¼bnWÃ…rÃƒjÃŒÃ€Ã¥Â¡ÃŠÃ–ÃŠ\\nTÃ„Â§ÃŸÂ˜Â°Â–/qBÃ˜Â¿Â™Â©Â¥1BÃ‚Ã•Â„Â°Ã™ÃŠÃºz Â¸Ã½MÃ¹jÂÃ´Â‹mOÂ–Vw`Ã¸Â¤Â€Ãˆ/J\vÂ‰Â¥PÂº\\fÃ®\\nN(ÂˆtqÃ§1Â£Â·Â¥"Â‰Ã¥ÂºÂ™AÃŠÂ¡$nÂ¥\\bÃŠÂ´TÂ¾Ã†SzauÃªÂ½ÂO@ÃŒiÂ¬Â“ÂŒmÃ¤Â–Ã­Ã£Â¶kqÂ´Ã¹Ã¼tGÃˆ|Â”?Â…fÂÃ…K"eÃ¸gÃ£Ã¹="@ÂšXÂ‡Â¬Â™sÃ•;Âœ\\fÃ˜Â‘Ã‘Â‘Â‰Ã´<g^Â‹Â”Â‰2\\nstÂ’7Â‹ÂˆÃ[!Ã¶ÃœÃ¬@AÂ¾Â…#qÃ¢"vÃ\\rÂ·gÃ»Ã®uÂ±jÂ®Â—ÃªÂœ/Â‰ÂÃ»Ã²,\\bEÃ·ÂšjQ8Ã®%Ã¾7 gUÂ,Â4ÃªaiÂ®>qMÂ±X^[8Â©CÃ)Ã²%Ãƒ"$Â—Ã©.>Ã«Â‰Â—+yÃŒÃ¾Ã´ Ã°Â€Ã—ÃY"ÃœÂ§:\\rÃ‡Ã¡Ã‘Ã–Â‰oÂÃ¦Ã¹Â«iQÃ„t#Ã½ÂŒÃ¡DÃœKÂÃ¤& Ã£NM(ÃÂ­ÂŒÃ´=]'v1+Ã´BÃµaÃ’4b{bÃ›_jÂ›Â¦Ã¥xyÂˆ3x5Ã®Â«Ã”&Ã›Â¬ÂBÃ¶Â„Ã¢Â·Â¨Â²Ã„Ã¶ÂšÂ•)ÂŒÃ¯ÂÂ‘Â¦lÃ‡Â;Ã”\\rÂ…Â³\Ã°M,msÃ•`3Ãª*Ã†Ã§>ÃÃ‹Â†Ã©Ã¨Â›ÃªÃ©"\\fzÃ§Â«Ã™Ã¬ÃÃ‹ ÃÂ‚^Ã¯Â‰Ã£0Ã Â²Â›Ãb3gTtÂ¸Â©Â¹ÂJÃ€(4Ã²Ã”TÂ†RÃ¸Ã­Â†\\bNÃ›TÂ€<Â¿Ã‚*CGÂ­Ã¹Â³3Â€ÂÂÃ‘Ã¯Â­Ã$Ã¡Â¡Â¥ÃŒBÂ«Ân-ÃŸncÃ†Â‚VÃ†Ã¥Â¼Â§ÂÃQÃ‘ÂkF!ZÃ®Â¶_:KÂ³weÂ®Âš@yDTÂ’$\Ã´aÃ³Â‘ÃÃÂ Ã˜=*Ã‘h1Ã†Ã‰Ã–}Â¿Ã˜Ã£.ÃÂ©Â›Â·Ã”Ã¬sÂª@ÂÂ±Ã±.Â³ÂŒÃ»D#LÃ§Ã¡ÂœÂ¼ÂÃ¢ÃˆÃ¹Â™Ã¬FÃ¸Ã“GJxÃ˜Ã°TÃµC'Ã«uw|Ã‰,ÂœYÂ€ÂšÃ‰CvDÂ‚ÃšÂ¥kÂ”)Âš\\fcÃˆÂ‰ÃŠQÂŸQÃ«!Â†iÃ°oAÃ¦\\n@ÂŠÃÂ”Â‘tÂ™ÂŠ"vÃ¡YMÂœHÃ¥Ã„Ã‘\\fÂNÃio!ÂƒJuÂ\\fvÂ˜ÃŒÂ’oÃ™Â‘G8Â—=Â—%lÂƒ(B3<\L\\rÃÂ¯6Ã«Ã§Ã·Ã’NÃ²Ã´sÂ“ÂœÃÃ¸dÃ–4Â¸ Ã¤Ã‰kÂ°Â‹Ã–bÃÂ‹&ÂŸYÂ°[Ã§Ã«_Ã‚Â ÂˆÃ°a\\bÂ§$oÃŸ<Ã­ÂÃ˜Â”Ã˜Ã–zÂVÃ¨-Â€Ã©Â\Ã£Ã‹3ÂœÂ7Â‹Â€Â²b\\nt)iXÃ¾`Ã¦ÂšOÃ¢Â–ifB@Â«\\n#Â„Âš?Ã‡ÃÃ»^Â™ÃœÃ»Ã”Â›Â®uÂŸÂ†Â—Ã­ÃÃƒ\\b,Â•%ÂÃ’Ã—Â†}Ã›Â³CxRÂª8Ã¬]5Ã·Â‹Â†Ã£Ãƒ(Ã•Ã²aÂ¬hÂ‹Ã‚Â¸BÂ®PÃ·Ã¥Â¶Ã´^kdÃ‹ms<ÃÃƒ\\rNJÃ´s8~Ã‡E?/Ã¾Â²\\b_DÂÂ¹Â„J8:Â‘Ã®8Ã¸Â‚s5Ã‡Ã¢ÃƒÃ¿Ã™ÂƒÂ­Ãƒ>_]ÂÃ•jjIÂ¿Â¤Â£Â†Â®_Ã¸ÃµrÃ†ÃªÂ¿Ã»Ã˜-2u"ltXNqÃ˜Ã¶GÃªÂ›Ãˆ~Â¦Ã¬Ã°? BÂ–Ã/Â¯Â“OÂbÃ˜ÃÂ¬Ã–Ã¶Â¶v$Â€Â†Ã³Ã…}ÂªÃºÂ¨N{Â§WÂ´Âª"Ã¼ DÃŒ$Ã€C{Ã™Ã¿FÂ«ÂµÃ”uÃˆÃ°cnÃ´Ã‚LfÂ¿"Â¨Ã‡ÃˆÂ¨LÂ¹Ã¤Â»7)Ã½fÂgqÂŒ]Â›Â¢Ã€?7Ã¦ÂÃ–Â½VÃ©Ã¦Ã›Ã½ÂÃ§jÂ:qÃ³ÂšÂ—Ã…MÂ”Â’Â¸Â±_{Ã«ÃÂ¡Â™Â£hÂ•Ã´Xx[Â–JvÃŒÃ›Ã´ÃÃ½Ã›bÂ¸]zBÃ¥Â”Â„vÂ¿@Â“Â”Ã²NÃ´yÃŸÃ¨Â˜Ã©Ã®,h9jÂ qÂ½Ã·(Ã„ÂÂÃ‡Ã,Ã>\\nYGzÂ‘kÂŒkFÂ„Ã«ÃÂ°>Ã¢{`tcÂ—Â¨|Âš Ã¾1Â¿aÂUeÂ˜MÂ¸Ã‹ZÂ–B8Ã…ÃÃ‡Â¶Â¿EÃ¶Ã¨Â…TFÂ‘Ã¢ÃÃ–Â£Ã¤Â„y$?Ã‹Âµ-Ã‘|>Â•'VÂ¶Â‚ÃœÃ˜WÃ¢B ÂÂ°\\rÂ…xÂ³ zÂ«7QÂ ~BjÃ‘ÃŒ5\Ã¹\ÂµÂ¡Â¼ÂŒÂªÂ’:ÂÃ‹ÂÃ¢Ã´PÂ³Ã…R+Âo/Ã‰Ã¯JbÂ‰wÂŒÃ»kÂ”P}ÃºÂ¥4|ÂÃ¶ Ã ,zÂ‹ÂÂˆÃ«ÂlÂ„ÃˆÂ«Ã•Ã¾Ã´Ã¬Ã‹Ã¬ÂƒG/Â°RÃ‚Ã¾Ã@Ã¬Â†\\nÃ–Â±ÃŠ'3_ÃºIr 8e\\rÃ‡Â¯Â±Ã®Ã¥Ã¤Â§#Ã¯$h'ÂŠÃ¸^ÃŒÃ›ÃšSÃÃ¨Ã•ÃŸÃ¦Ã˜,ÂµÃ„Â˜Ã±UÂHÂ§0-Â’3yÂ£ÃˆnO\\rÂ‹TÂ£oÃ‡Â­Â§]aÂ¦Ã¹GÃŠ#\\f(Ã„Â¥ÂEÂƒÂ¥p%Â2Â†rÂ”Â†UÂ™,"Â¯DÃ†^hÂ±|Ã¿Âª\\fÂªÂ‘ÃŸÂ®\\rÃÃ¡kÂ•>,.i/Â«Â°XÃª+Ã€pÂÂ¿Ã‹Â‰Â±Â Â„ÂÂ‹Â®LaÂ·kBHÂ‹Â¾&9ÂXTÃ½YÃAxtÃ˜Ãµ]Ã®Ã¿}AÃ·Â¥Â„Â†\\bÃ¥cÃ¸MÂ˜RcÃ¾DÃ¬\\rqÃ¢ÂŒÂ•aSÂˆÃ“]$Ã³YÃ‘ÃºÃÂ²Â¸ÃŸÃqÃ“OÂ«Ã¿ÃŸÃ«Ã±fOÂ¥eVÃ’Âª^\\bÃ‹ÃSE:Â†Â›Ã«QÃ‚Ã²$ÃÂ‰Ã¯Ã¨Â„Ã»Â¹Â³ÃŒGÂ½XkÂŠÃ³_JÃsmZÃ“_Ã«Â†|tÃ½s([Â‰u?ÃÃ´Â¶Ã—)Ã˜;Ã“Ã³PÂœ\\t^Â”Â»OÃ‘,\\n`ÃŸ.\\fÃ›6Â©Â·Ã‹\\nÃ§VÃªÃ¶+&%ÃŒÃÃ–ÃÃ™Ã¥4asÃÂŠKÃ»ÃµKÃ¶Ã±ÃœaÂ›Â\\nÂ"Â“Â•\\tÃ^Â¦LÂ¹Â©Â¸Ã‡ÃŠuÃ›.Ã±JvÂ‹Âœ0gZÃ‡4\\ngÂ—]Ã´Â†Ã²xV\\fÃ¹Ã©Â¶Ã»_Â´Ã®R}ÃÃ³Â¨EÂ§Â6ÂŸÂ»hÃºÂ¢ÂÂ¨Â’g|Â¬Â½{Â‚Ã¶NUÂ†Bx Â­ÃƒÂ¯2Ã´9ÃƒÃ¾*\Â±.GE^zÂ§`ÂÃ§:Â—*Â¬Â…Â‹\\bÃ¢Ã™Ã‰ Ã»ZIÂ²`ÂŒÂ³Ã§Ã‚i0Ã€Â†!Â§ÂšgÃ¢Ã¿Ã¬sÂ™\\fÂ³tTÃ IÃšÃ—Â’'Â#0mÂ±GÃŠcÃ'Ã»ÂœÂŒ0g0|Â‡}ÃÂ½\\nÃ¬$Â–Â€;Ã³HCÃ¿ÂºAm+/Â¾a"Â¬Ã§qÃÃ³Ã™ÂŒ\Ã¿ÃšÃ·YÃ½Ã®\\tÂÃ€ Ã°Ã3>Ã‹Ã™AÃÃ™/Â‡J9=Ã“ÃÂ¿Â«\\rÂ…-m@^Â±~Ã›VÂ›Q9-5ÃªPÃ®Â”Ã¬Ã¹Ã–Â¢t~ÃÂ¿T$Ã°ÃÃ”Â¸\\fÂ©d-W7`ÂˆÃº^Â¢XuonÃ³Â²Ã„ÂƒÃ¾Ã·`Ã‹'Â¬QVTÂ¢ÂPRSÃ³y[Ã•ÃƒHÃ­ZÂºÂ®H=Â±Ã¼|ÃƒÂ•mXwAÃ‘Â¯Ã¥fÂŒÃ‡,Ã¹Ã“ÃdÂ†Â½SÂ¼ÃÂ\\fÂ†Ã™Ã Â³CKpÂ™\\b\\n;KÃ´Â‡MÃŸÃ‰Â³{ÃÃ«)QGsÂ®rÃ•Ã½Ã€hA$Ã‹YÂÂ¹lÂœÃ»Ã›;/UÂ†ÂªÃ–Â„Â±Ã?Âm Ã”Ãœ6"ÃµÃ¨Ã£Âš5,ÂªX4Â„Ã¼ÃªWÃš^Ã”VÃ§Ã‚Â‚Ã’Âu2\\fÂ¼Ã¡ÂŸ=iÃ£6Ãª\\rgÂ¿7LCÂÃ†TfÂ¹\\rÃ¨Ã¡\\rÂpÃ’xÃ¾Â†\\nÃ’DÃ¾Â¥Â˜gCÂ”Â¢Ã˜ÂÃ“Ã°Â—ÃÃ±\\nÃ½Â¯Ã¦yÃš'78AÂ±Â„fÃ¿EÂ˜#4#nÃ€ÂµÂ”Ã¤)?Â˜pÃ…Â‰ÂÃ³ÂÃ“ÃÃ¢ÃµÂ½Ã‘ÂÂÂ˜?Ã§Â{bgÃ†ÃºOÂ›Ã¡KfÃ\\fÃ¿Ã¡Ã—pÃ…Ã“Ã¬Ã†xÃ—Â„S_Ã·-Â¡Â›LnÃÂ•Â¨ÂškÂƒ2ÃEÂµÂÃ€Â–ÂŸfÂ¨Â¢Ã§C'bÃ»oÂ˜{Â½9tÂ¢NÃ¹9Â¢Ã!Ã’eRÂƒÃ¿Ãˆ)Â‡Âš\\f:Â³Ã‹Â¦RÃ¸Ã¼ÃœÂ·Â»f0Ã´OÃ…Â—DÃ¼ÃÂ¶Ã’Â°`Ã€Ã—ÂŸÃ¦Â¸SÃ»Ã¼7\\tP"Ã—Ã•Â±Ã³Ã .SCzYÂ£Â±#Â¦\\bÃ ÃŠ\\bÂ®.Â»Â²Â®nÂ‡Ã€Ã¸rÂ‘FÃiÃÃ½Â¿ÂšÂ¤+lZQÂ¿|Â®Â²Â™OÃ³Â‘Ã¿Â¯ÃƒÃ§+O"20ÃrÂ¼hq7Â¤Â£Ã¬DÂ‡Ã§gÂ™Ã´Rp&6Ã¨NÃ€ÃµÂ—`ÂÂŒÂš&Â˜#Âb?w._Ã”[Â©Ã•#Â–Â¶Âµ6ELÃ”M5\\nÃ‚y>eÂ™YÃÃ¯Ã¼QÂ‡8Ã·Ã›Â²RzÃ¶ÂÂ‡Â· \\bÂ‡0PÃŠ\\t2Â¤Ã§Ã¸"Â¤Ã‰\\fÂ½~Ã£IÃ¯ÃTÂ¤Â°Â–Ã„)DÃ°LÃÂ¬Â¥Â©Â–Ã¿Ã¨ÃÃšQÃŠÂ¡MÃ½Â“Ã¹lÂ¾Â˜ÂÃ‰A\\tÃ‰\\byÃ›\\fwhÂ§eÂ¤ÃÃ€ÂÃ†Ã¤#Â§ÂŒQÂŠÃ–DÂ³Ã²?l Ã©ÃªYÂŸbm\\fvOÂ–Â©DnlÃƒÃ­w\\rÃ’Ã‘Â¡zI"cÃ¢oÂ½]ÃšÃ¿/Ã”ÃwÂ¶nÃ†Â‘Â½Ã¡K%Â¿Ã¹Ã¿X%Ã¬Âƒ%Ã‰\\niÃ—DigÂ­Ã¤Â±Ã‘Ã¨Â‚OÃ¿$ÃˆÃ…}ÂµBÃ¡Ã¸Âµ8Ã¤ÂµÃ’ÂŒ:Â Â‚Â¢MEÃ›hu9Ã‰Ã¢Ã¬Ã£Ã—2Ã”zÃ³F+UrÂ¢Â»Â™Ã…)ÂƒÃ˜_Ã›Â‡$Ã•ÃŠBÂ•-FÂ¾Â¦Â”Â¿ÂŒ~~AÃÂ£VÂºNÂ¤Ã™Ã´Ã»Ã…Ã $Ã“!nÃ•Â ÃœÃ¢hÂ±6\\t`\\f)Np^Ã…EÂ»ÂŒÃ¦-!)ÃŸB|FaÃ‚Â«yÃ¾oDÃ¯Â€Â‡\\f<Â¨ÃªÃ°ocÂ•F~Â„eÂ¦}|ÃÂÂ©PÂ“Ã†Ã¨mÂ¹(Â­_s<ÃƒÃœÂ”Â“Ã¯Ã•LÂšÃ‘Âš@Â¦Â’4Ã´Ã¼GÂ^9/LÃŠ,Â€Â¦ÃµÃ¿ÃºNd12xLÂ‹mÃŸÂ­#\\rÃ—Â²~^P~Â¿Â·vhÂ—Â¦Â©\\fÃ¿Â½UÃ Â½ÂÂŒÃ¿7*<|\\tÃTÃšÂ¸#8Ã¨wg5$*]Ã›Ã¥\\rÃ“Â¦Âœ63ÃˆÂ¥4Â¥eÂ˜ÂªiÂ£Ã¼Ã²NÂ·(3ÃÃ«HAa#4Â»h+?$pÂ‚Ã«)De^HÃ¤Â†Ã¹Ã·Â®Ã†Ã‡Â¤ÂŸÃ‰ÃÃ¢Ã©ÂœÃ§Ã®\\rHÂ²Âš3r_Â†TÂ©Â»Â“Ã­ *Ã¨Â˜Ã‘ÂœÂŒÂ»Ã­Â¦Â¦BÂ°:fÂ­X?ÃÂ†ÂˆÂ–Ã´Â«Ã¹Â—6"ÃªW~Â‰oÂ°Â±Â’ÃŸÂ¥Ã• j BÂ§Ã“S#8VÃŒOhXiÃ¹M%Â¯Ã2Â‰Â£Ã·F3>`ÃªQÂ­BPÂŒlÂ¬vÃ±I^Ã¢Ã‚Ã„Â¤Â²Â¹ ÂÃªzsA Â•\\f/Â±Â¾Â¤Ã‡Â½Ã›Ã²DÂ™GÃ–mÃ²ÃŸÂŒ<h%Ã‹0BÂ¼zÂ©Ã¨Ã¸Ã¿Ã«Â­EÂ»^6ÃƒFÃ˜\\tÂ¸@~,`ÃŒxÂ³,Ã¶Â·Â§ZÃš!Ã¤EÂ¦CÃ“Ã¿3iEÂ²^Ã¨iÃ‘Ã‘Â¿Ã¢ÂÃ‹FÃ¹tLÂºHÃœÃ«SÂ !Ãj &Ã«Â¥f'pÂ¨Â½qÃ¾&{i\\f#zÂ‘|ÃÃ¾Â¾R\\n@ÂÃ®ÂƒÃ»hf^Z$Ã‰Ã‡WÃ©Â Â¾s79Â¦Ã½sÃ“jÂÃŒ^Ãº:[ZHÃ¤Ã¾}ÂciÂiÂ±fÃ“Â´Ã¬dÃ°Ã|Â¾Â©E}RvÃ³Ã­ÂÃŒÃœx[Ã~Â“FÂªÃŒÂ¼Â›\\fÂˆh.Â§PÂ›ÃÂ´;YÃŠDÂ—Ã®ÂÃ™ÂÂ“RuTÃ‰Ã—Ã†XÃ­?s<qÂ¥aÂ³l,ÃµÂ†1=)pÂ¥#Ã¢nÂ«gÂ—8=Ã˜7Ã™ÃˆÂ„eTÂˆÃ»Â˜^}ÂšÂ¾`*I$\\tÃµÃ·\\bÂ“q;Â¿GÂ€rÃ¸ÂŠ!Â¼Âš=Â…wÃªÃ¢ÂÂ¡Â€Â*ÃAcÂ¢WWÂ¿OÃ¦ÃŸÃ¢Â†B yGÃˆ\\tÂ_Â²kÂ‚oÂ ÃtÃ¥Ã¡(FÂ™Ã¢5ÃˆÂgÃ¼Ã‰Â”Â}Ã¶Â±:Ã»Ã‘Ã¹TÂŠÂƒb^Ã‚Ã±fÂ¬Â•6Â†Â‚ÃÃµÂ¦Â¸1mCÂº_OÂ©HÃšÃ§Â°aÂ£sÃ©\\f+PWÂ€Ã†Ã‰]Ã·ÃŠÂ•1o<b|k\VÃŒÂÃ‰Ã¡OÃ€Â†Â†*5Â™Ã¹pÃ¥ÃŠ7Â‘z(Â´Ã®CÃ‘Â¶IzTÂ‡Â§T;{Â¢Ã”ÂÃ¥$hÂ½Ã¹Â½Â¹RM_eÂ«Ã‡Â”[*Â¬bÂ¼Â›ÂƒlÂ¿Â»eÃ¯Ã”ÂÂ€Ã†Â„?Ã©~Ã†E\\bÂ¤"<Ã·Â†\\tÂ Ã©ÃÃ•Â²Â«Ã·JÃº%Â¹Â¯Â¬Ã»y1Â¼Ã¡Ã°Â©Ã¤NÂ¹\\fÂ‚BÃ±ÃƒÂ¿WÂ¯PAj_Â™gÃ±ÂšÃ¼Ã˜Â©OÃ‹rÂ·~wMÃ¯Â—Â³Â¤~Âˆh:yÃ 8fÂ®TÃ¥lw'#Â‹Â¾JoBÂ´Â­ÂƒK*ÂšÃÂ°Ã+iÃ£Ã§Â˜Â—Â‰Ã¤@Â’Ã©Ã¬0CÃjÃ€Â£Ã©Ã±2V<Ã†bÃ¼Ã„ÃµdÂ±'eÂ‰Â‹HÃ’Ã¼uÂƒq#Â©<Ã¦q- Ã¨;ÃªÂ‚Ã¹=Âª?Â‚aÂ–Â¿vÂƒp~ÃkÂ‘Ã«$Â”Ã›0Â3uÃ,Ã›?\Ã“Ã£Â¥Ãµzx\Ã›HAiÂ sÃœÂ¹ÃœÃ°Ã¦Ã©ÃšÂ£Ã‘IÂ°ynBzi6Â«*GÃƒFÂ³Â€Ã\\tÂ™Â—jÂ±Ã…Â½CÂ¿XÂ›#IÂÃ–Ã®Â¦*Ã¦Â‘Ã¶Ã³Â¶<RÂ‡ÂœÃ·Ã¤Â€*nJi{Â§\\bÃÃŸ#ÃºY\\fO=Ã‚Â«&Â»Â£Ã´ÃŠÃŸ@.Ã¯Ã»Â“6Ã¤Â¦Ã–ÃƒÃ„KÃ¶}Â—Â¶Â¡Â¦ÃRÃµÂŠÂ“BÃ\vÃÂj9Â…\\bÃšÂ«pNÃƒÃ˜Ã¿Ã˜Ã°Â‚ZÃ­Ã¦`2eÃºÂ¦nÃ¥Â¬Ã•Â½@*Ã‘N_wz,+ÃŸSdÂ¡Z7Ã’Ã½LPÃ°Â¬wÂ§a&dÂ¬lÂ”ldÂ·Â„b</Â®b\\bJÂ‘1Ã—>Ã Ã’aÃ½Ã©!Â£Ã<X4Â¿Ã¶Ã½V(^tRÂ²KMaÃ€Ã¡Ã»'f;Â˜A6nÂ§+ÂE9&ÃŠ8Â¾Ã•2W]L}ÂƒÂ£Â‘Ã€iKUwÂ¦Ã¦Ã’lÃ§}ÂŒlÂ³Â’*Â³iÂ£Ã…~'*YÂ­x2'Ã´B ÃÃ»ÃšÃ°Â˜ÃÂ‡Ã—WpÂ©Â³Â™Ã•hj*yÂ„yÃŠÂ‡ÃŒ*Ã‡2ÂÃ´=Â°ÃÂƒ{Â³ÂŠÃ¬Â“Ã·Â‘g\\b6aÂ’Ã©ÃªÂ¹sÃ½}Ã–Ã¤tÃšTVxsÂLÃ°8\\f^aÃÃÃœÂ€ÂšÂ€ÂÃ·Â¬*Ãªx)>Â¦ÂÂ²"Â™>Ã°Â’Â‚=ÂªcÂ–Ã•t1Ã©Ã§ÂºB5Ã¼-Ã„Â­WÃ‘Ã’Â…I6Â¯Ã¼Ã§)];ÂŒxÂ…VkÃ‰5Ã¯ÂÃ³c#hÃ€Ã³8ÂƒÂÃ‰Ã§0Â«Â¾a@ÂÃÂ„DbÂŠ Ã¼ÂªÂƒkÃ”Ã‡Â«Gx{wÃ»)Ãˆ+2Ã¢Ã xÂ¥yÂ£ÂÂ‚x8QÃ›ÃÂÂ˜Ã­ÂŸ+ÃšÃ·Â¬XÂŒÃªÂªBÃ±Â«I$Ã‰Ã£}8\\bÃšJÃ™ÃÃ¨Ã­pÃŒÂ±1ÃÃ£kÂ™ZF`Ã¿-&%Ã™>ÂƒfÃºÂ¼Â”3`J@ÃºteBÃ»Ã‰)ÃÂ¾^Â™Ã­\\bÂ´7Ã¸ÂŠ\\fÂ¤YzÂ4RnÃ½Ã–ÂÂ½\\nÂŸjÂ±Ã„Ã´SÃ‘Â«Â†<!ZÂ‘ÃŒÃÂ½ÂÃ‡zÃ¡Â§Â£$GÂˆÃ­cÂ¦h/q1Ã¸9QBÂ¾Â„ZÂ—bÃ‡ÃƒÃ°]Ã¿{Â¼Ã`WÃ®$LÂ¬Â®n+ÂŠÃÃ…ÂœÂ¬Â®Ã‘Â¯Â–"@TÃ¯@Â£Â²C1Â½v!Â Â¶rÂ‚Â²Â©RDVRÃ¡Â¬Ã…\\b w'Ã¼3Â—sZQÂƒÃÂ¥Â²Ã‹Ã˜TvÃ¢Â¤^Ã¯hÃ„ÃƒÂ§4Â´Â¹/UÃŸÃ´Ã‹ÃÃ¬Ã©ÂXa|7q0Ã£\WZÂ…Â¼Â¦ÂMÂ…Ã±Â‹F9@ÃÂ ÃœEÃ€Ã—Ã•Â…Â¤ÃÃ¬LÃ¾Ã´r>Ã¶ÃUÃ³Â€ÃXÂªÂ¹3ÂŸDÃ¨ÂÂŸÃ»"0gÂ‰x{0f2\\rÂ¡Ã¢Â¼ÃºÂ¥Yo5YÃ¥'Ã¸Ã6Â—ÃœÂª"}=iÃ›r#Â<|Ã¥ÃŒÂ¶Â…1LpjhÃ¸]Ã¨ÂÂ„=$TÂ–E\\b<ÂµcgkD~ÂœÃ¶Ã¾y:ÂÂŸ ÃÂ®?|Â‚Â¼Â§0P !Ã‰ÃŸÂ½wÃ´Â¡jrRmÂ•\GÂºÂ„Ã®Â†$XÃ„jÂ»Ã¹Â{xHÃ‡Ã ÃÃ¬&Â²HÃ£Ã ÃˆÃ¬Ã¤Â‡Âº\Ã¬Ã±Â±Â½s6DÂ¾\\bÃt`xMÃ¢00RÃ¨ÂŠ-Â¨Ã†Â”Â®ÂeÃœ=Â˜lÂ¥Â–Â¤WqÃ›Âµ\Âš~ Ã“>xÂ-[(Â¯<e}PÃ¾Ã‘Ã›Ã‹}^Ã¿Ã±>cÂ¦Â¥]Rvn(Â–FWÂ¹ÃšÂ¹ÃŠ\\tsaÂ¶M\\n\\rÃªÃ…Â‚ÂŠÃœMuÃ„Â¿@dyÂ…RÂ§Ã›Â<Ã‚Â†ÃºÃ™Â»Ã—Â»ÂµÃÂµ>Â…:pTU\Â‰Ã•Ã’>Ã«Â„Â²lÃ†Â›Ã .AsÃ©\\tÂ¢5\m(Â»Ã´[ÃºÂ¬Â²1Ã cÃ½5Â”ÃƒBÂ˜1J.`Â¸Â %Ã”Â¦gC qÂˆÂºÃ´U\\t;mÂ˜Ã¥Ã\\rYÃ¡Ã²Â§EÂºÃƒ>ÂŒÃ¦Ã Â©>Ã¦\\tH?Ã…ÂŠÂ(Ã™nÂ¶CNÂ¢Â°Â¯Â©Ã¤UTK/Â«9X3_iÂ¯RÃÂ®hÂ™8Ã¸Ã”Â’Ã’Ã—xÃœÂ»Ã”*Â†M-Ã§2ÂX!Â¡\Ã‚Â¬JÃ’Ã‡Â©Â*j7zÃ¯ÃÂ™>GnoÃ‘'\(9l$^`8Â½0$Â²ÂŠÃœ6Ã¯vÃ³Â›Ã”ÂÃ´m}(Ã…QÂ‚`Âœ4'Â¨Â ÃœW|Â©T L6Âª\Ã„Ã¡CÃ³ul[ÃˆY~4CÃ–Â€Â¶Ã‡4Ã…ZÂ—kÂÃ´Nj\\tÂÂÃ€wÃ…Ã‘\\fÃšÂ”Ã‡Â¬Ã¥);Ãk_Â•Â¶Â·E'nÂˆfÃ§Ã¤pÃ˜[MÃ¦Â¡$zÂ±~ÃŒvÂ†e3Â®Ã¦ \\nÂª}Ã°Ã°Â¾Ã‡Ã‚Â€\\t8.;ÃºnÃ†Ãˆ@Ã³Â©;@VÂ«Ã˜3Ã¿Ã–YÃ™ SÃÂ©j]Ã Â¯CÃ±XÃ˜Ã…Â„Ã›Ã´Ã»Ã”ÃŠvÃ´Â›Â’\\r\\ncÃ·QÂ«ÂªW(Â®5Ã†Â·Â Â‰Ã¤ Â›Ã‚Â£dWÂ¤Ã“Ã¾Ã½Ã­Ã—IYLÂº(&hÃ¢ÂƒfÂÃ™SFÂ€Â‹Â¢ÃÃ€Â©ÂÂ¦Â£Ã®0Ã“Ã†MÃ§FÃmÃÂªÃ‚NlYÃ ÃÃ€JÂ£Ã¼G}Â1Ã¯Â˜]ÂÂ±Ã~: Ã‹Ã³Âƒ'ÃŒÃ§M#Â‹CÃ…Ã£ÃœÂ²ÂMÂ¥cÃ¦TmÃÃŒÂ®ÃªÂ˜Â¿Â™i)Ã…=ÂºpL=ÂÂ±Ã†>Â«Ã›Â¼SÃ²Ã“Ã¶ÂÂ¾NÃ…NdÂÃ„Ã¬*Ã¨ ÂºÂ™Ã¥)sÃÂ¼]Ã…Ã‹}Ã®qÃ’+c<1B(Ã˜ÃšÂ†]Â‚Â IMÂ®Â¿Â­7Â¿ÃBÃ´ÃŠÂšÃ£Â„Ã•oÂ¯Â¨"Â•IÃ†-\\t Ã˜ Ã¾Â°Â¶/\\teÂ°Ã“8Ã¾9pÂœÂ£Â¾lÂ“:ÃºÂ ÃªBÂ”|Ãƒ&ÃÂ®:KÂ€Ã‹ÂŠÂÂ—\\fÃ©VÃ™Ã…=Ã–Ã€Â©$Ã±}ÂŠÃ™Ã„Â©ÃŒiÂ½ÂÂ´ÃºÂŒs~Ã–tM1Ã®Â¸Ã—sTÂ‰Ã¿Â„ÂÃ¬4Ã€ÂŸÃ» Ãº#NÂšÃªÂ§ÃÃ¬Ã©t=Â£Ã±Ã¦`=YÃŠÂ² 3Â™/=ÃƒÃ!Ã¦Ã¯FÃ…HrÂ£Ã‘YÃ°Ã‘s"Ã…Ã¶%LÂ¥Ã­Ã¨\\f^Â±ÃšÂ¯Â‹+ÂªÂ³Z_DÂ˜"Â‰Â²|Â€jÃ‘Â¾4Ã´Ã´eZÂ”`Ã¥Ã¨Ã™I^IpOÂµÃ«ÂÃÂ”1kÂ„Â“Âœ'\Ã–NÃ­VÃ§Ã„Ã·Â¨nJÂ”VÂŸ,Â¦OÃÂ³Ã°%Ãƒ1mÃ©Ã…pÃ€0Ã’Ã®;Â–OÃ¸lÃ±ÃŠÃ·E){Ãˆy%PÃ®Ã±Â‘<Â§Â’mÃ•Â©Â ÃˆÃ©')ÃCÂŸ8Â°)cJÂNÂÃŸÃ¦ÂŠ\\nÂ¨Â¦Ã¿Ã¯Ã‚Â¸Â¡Ã§Â©Â–Â!Â­>;RÃ@Ã˜Ã¬Â´Ã¸%:c1Ã³ÃSÂšÃ˜ubÂ³h"Ã¯Ã¶Ã¯IÃ­Ã´rÃ‘}ZMZÂ–Â¤nÂ‰kjjÂ‘HÃ¢Â‘qÃ•RÃ‰Ã¦Ã¼KÂ‹Â¶oÂ}MÂšÃ­8Ã¾fÃ¾ZszÂ Ã»p|<@ÃŠÃ„MÃ®7Â´_Â¯Ã‰AsQÂ¢Ã¸h%Â½Ã¶Â¸uOÃªÃ„Â˜Â¼Ã™S Â’lÂ³Â¢Ã©NÂB@tÂy3ÂšÂ½wÃÂ±Ã­fÂ¢Ã«Â²jÂ‹Ã—Â¶Ã”Âd Ã‘Ã¬qÃŠciotaÃ„7Q~Ã¦Â¾oÂ£3YÃÃ‘ÂsÃ°CÃ¬SBÃÃ‘ÃªÃ‰Ã¤XyÃ¯Ã’Ã£8Â«Â§.Â¾ÃŒÃ‰vÂ³ÃµYÂ±Ã²]BÃ¯9ÃÃ–E)NUÃ¾Ã½>Â«7Â£ÃµÂ™Ã”Ã•Â“SÂ¢ÃŒÂŒ.Ã¹ÃºÂ³pFÂ‡"Â·ÃˆÂ¤Â¹Ã²Â˜|Ã¾ÂQwÃŸÃ£Â§Ã±Ã‚Â½ÃœIÂ¤Ã#:Ã©-ÂºYÂ“Ã±Ã®Â¿Â¬Â±hZ:Â¾T0Â»Ã‹Â¹.+Â¥MÂ¤0\\nÃUÃŠÂ˜QÃˆÂÃˆÂ *Ã†\Â±lÃ§6?}Â¿ÃœÃÃƒ/ÃºÂ—i6Â¨Ã¬Â³I&Â+Ã¾:Ã¥rÂ¤.WÃ‰uJ3:Â°Â z&}SÂ—Âˆ@Â˜Ã…/+tTÃšÂºÂ‚Â»kÂ¬]PÂ„ÂºÂŒÂŠÃ§Ãš9ÃµÂ<*Â´Ã˜Â³k Â¹Ã¸Ã‰Â“mmÃ§Â´Ã¬;:3,Ã³_Ã¨@)4}MÃ„hÂŠ9Ã§Ã»Â…HÃ¤\\bÂ¤Ã¸^Â§Â‡ÂˆÂœÂ¡Â¯$Â®Ã¸DQÃ¾ÂµÃÂ³8Â„ÃÃŸÂÂ²cÃœÂ—ÂˆÂŒ"ÃˆÂÂƒÂ†mÂ‹ÂˆEfÂ¢,Ã‡Ã”ÂLL8Â³Â ÃÃ¿QÂ”Ã„Ã´Â·Ã¨Â¹Â)Ã€ÂœÃ’Ã…;OÂ†ZiÂ­(9ÂÂœÃ‚.ÂŒG&TlÂŠ+ffÃ¥ÂŠB(Ã‡,v6Ã© }Â‰Ã™Ã¾hÂš3g/g8Â¨Ã˜eÃœÂwÃªÃ›Ã¬Â“Ã„AÂ‰NÂ¤\\b]ziZÂiÃ›Â¶Â”@Â¼Â¦ÃÃÃ¢HÂ«tÂœÂ§6Â¿7)Â„Ã–Ã‰@ÂˆfÃ«Ã•eÃ®Ã½ÃiÃ Â”1:Â¼)Ã¼Ã½'Â—9ÃŒÂ’Ã,Ã…Â•Ã¡ÂºÃšÂ‹Â”ÃÃ¾Â‹Â¡Ã Ã³iÃ£Â\\fÂ1UÂŠÂœcÂ°Ã½.Ã‰#Ã¹z.%Ã`'Â‡Âš\\tÃ‰ÂœÃÃ«DÂ<Â¿cfÃ³6vÂ’zÃ¶L.F\\fÃ‹Â¡pÃ©Â§+ÂŸ;Â–Â´Â”ÂŒ 2BÂÂšÂŠeÃ¡Â§4Ã²Â‰J\\tÃ¢Â¡6Â›Ã©Ã¼pÂ€WÂ¥Ã”yÂŠ*ÂœÂ˜Â¹Â¬Ã¤Â§ÃÃ«4qQÃ–Ã§ÂƒÃ¼@HÃZ/ÂÂ‚Â\\bÂ¤4AÃŒ(Â‚Ã’ÂT5Ã¡Â1[X*SÃ Ã‹Â®z^uÂµ:Â¿'Ã›PYÃµÂ¶ÃšÃ”>kÃ¸$IÂ HÃ‘Ã¨Ã¤Ã·Â—Â”4ÂŸÂ¢o~%ÂœÂ™K5ÃWÃµÂ—SÃ¬Ã˜(Ãˆ&Â„V$a\\f\1Â¼ÃˆÂ–Â»Ã¯6$IÃ˜SÃŸÂ§DÂ¾=tÃ‚HHÂ r.Â¢Ã);OÂ!Ã¾ÂÃ„Â¹]%%Â£Ã«lgÂ‚@9Ã Ã¿V~+ÃNVÂ§1Ã´ÂŒÂ™Â½~<ÃÃ€ÂšÃ©3f""Â©*Ã®VKDÃ˜Ã¹Ã”Â±^\\n/\Ã».;kÃŠÂ±Ã¤Ã¤c8KÂ…@wWÂ‚Â¼C%Ã›ÃˆÂ”Ãƒ&Â‡Â’u4ÃªÃŸ$Ã½Ã‚Ã–uÃ“Ã…Ã§Ã›Â¡Ã¾Â˜ ]Z5Â—NÂ‘Ã†Â°Â„_Ã£ÂšÂ”Ã¥ÂhÃ¿Âˆs7Ã³Ã»:'hÂ˜Ã”LÃ—FÃ´iÃ²Ã¥Â»Ã¹ÂKKÂ˜pÃ·Â»ÂµS`^YÂ ÂªX&sÂºÃ¨HÂ»v>+IÂZÂƒAÃ~P)Ã•Ã˜5x~ÂŒ'&Ã1ÃÃšÃ¢DÃ“Ã­Ã­^Ã«dOV(~}Â³8 Ã¯Â¬Â£ÃƒÂˆÃ£Â¥5Ã¯yh'&,[mÃ¾Ã¬ÃŠÂªf%a|Â‘6Â•Ã«Â¼vÃ¼ÂÃ‚\\b{Â¢Ã˜|nÂ½ÃqÂ™Ã¢Ã‘{ÂtÂdGÃ˜Ã§Â’mNÃ«4ÂªBÃ‚aÂ‡ÂšÂ«ÂˆÃrÂ‹Â1]Â¸wc_Ã•!Ã©7 Â*+Â‰Â€Â°ÃªÃ´Â¬Ã©Ã¡ÃŠ?Â»ÃªÃ®\Ã–Â›ÃÂ¨Ã™Â“4ÂŠÃ¶ÂµB\\tÃ¢FVÂœÂ¼IÂ­QÃ¦Â»\Ã£YÂ²/Ã½HÃ§G>Ãœ&Ã”Â·RÂ«E{%UÂHHÂ›q#2Ã®Ã©fÃ!Âª9(0Ã¼iÃ†Ã¦LÂÃ¬Ã‹Â‹Ã³Ã„yÃ™Ã’oÂ² ^Â±Â¯Â Ã†Ã±Ã©Â¶Â7gÃ³9Ã·Â¬Â¬DÂ‹Â¥LÃ½Â†>"Â±Â½dÃ°UÃªÃÂŒ\\tÃ‰!#Â‡x{Ã­Ã¹Ã½pÂœ?Ã­Ã•Â’)Ã­BÃ£M"lÂ¡Ã‰@*HÂ’|ÂÂ¹Ã²ÃˆÃ˜Â¶:+Ã³];6bwÂ’ÂƒÂÃ¬Ã½qÂ‰I Â†Â•818Ã¨7@Ã´Â¿BW<Â¿Ã‡tÂ¾Â¿ÂªÂn&Â¶Ã­>0_ÃÂy{Â…Ã›>Ã­Â±ÂY$Ã’YwgsÃ¥Â´Ã¯Ã£>Ã\\fÃªÂ–/Ã™$lÃ¥Â¶Ã³Â½/Â‡ÃˆH#ÃÂµM^Ã¶Â²Ã¤~OSHAÃ¤ÃOXBÃŸK\\tymÃ¢[&Ã’ÂºÃ¦[&Ã¶Â·Ã˜Ã·\Ã½,[acÂ¢ÂZLqT8[Â§Ã¼Ã“ÃÂ—QÃ«lliAÃº&Ã¼CEÃ¾Â—Â©>]#Â»ÃˆÃ€qÂºÃƒÃ»ÃšÂºÃÃ¶ÃˆÂ§Ã¯Ã™Ã†4%\\rÃrÃªsÂŸÂ€Â»Â‚RÃ£^&^Â§ÂÂ Ã¡7\\ffÂÂ„8Â“8Â¹^Ã®ZÂÂŠÂ¨7Ã…!Â”Â¿WZÃ¹Â–Â¦ÂƒÂÂÂ¡kÂ¬Ã˜ÂªÂ©Ã’Â¶oÂ±ÂŒÃ•%ÃÃ¨'WÃ‹Ã¸UÂ«<H\\n#Ã«ÃœxÂ¬+Â·Â¥cÃŒ(Ã¿Â§Ã—GÃ‚J-)Ã•v2KÃ´NÂµÂ©ÃœÃ uÃ£uql2Â½Ã¬Â”Ã£SÃ¨Â¼\\bÂŒÃÃ‰ÃƒÃ€!Ã›Â”"IÃ‘g+wÂÃ·,~_0;Ã•@dh0A!%[Â¡gÂ«ÂšÂ¹ÂŠÂ\\f20f<Ã™o$7Ã¦ÃˆÂElGÂª&;Â¼}HÂ•Ã¹ÂGÂ§Â¼ÂšÂ»Â?ÃÃ…ZÃ€\\fÃœÃÂ§fÃ—ÃÂ°Ã‡ÂœÂŒ.9uAÂ’sÂœÂ²#xÃ«Â½Â”Ã©Ã«Ã†4ÃC+Â”qÂ…ÂµÃ™Ã¸3$Â‡Ã©?IÃŸÂ´HÂœÂ¿'ÂÃÂ¯ÃAÃÂ¾Q*`z \\rÃ€Ã Ã°EÂµ Â’Ã½Â–gÂ›^Â¢U\\nRÂ¹Â­VÂ»Â¿ÂÃŠÃ­a$Â°TÂ’b\\bÂšÂ¼YÃ‡Ã³\\bÃœXÃˆ:Â°Ã“ÃˆÃ»Ã·Â§ÃŒÂ²\\nÂ²sÂ‰<Ã½QÂ›:Ã¾Y2CxÂ³\Â®Â£Ã„ÃÂ—Ã’Ã¤)@Ã¡Ã¡AoÂ›Â–`o o0|Ã¢Â”ADÃ“{~\\tx#Ã¬\\r}Â‡ÂŒ\\nhÂœÂŸ Â…ÃªÃ½Ã›;>Â³ÃšL_UFÃ£RÂ½Â¸ÂÃ§Ã¥Â¢Â´Â›Ã‰zÂ—Â¥ajÂ£Ã‡F.Âº?Â‡ÂÃ”?TnoÃ†Â»xLVsÂÂ›Â«Â‚Â’xÃ­Â¯"V$Ã¿ajÃ“0Â€4[ÂƒTÃ«Ã˜Â«ZÂ­ÃµÃšÂ«7cÃ›Ã‹:\\fÃ€Ã§k\Â Âƒ[Â”nÃŒlÃ±Ã°$+*Ã‘8Ã–=ÃŠcÃ®TÂ¿yzÂƒÂ„Ã¶Â›H9%ÂŸÃ±yÃ‡-Â–Â’Ãˆ]tSÃ‘'Â¬Ã­vÃ¿L"Âµ\Â·Â¯Â’E#Ã±/\\tÂœ#Q6PDÂ¶Â³Â•Ã‚(Ã‚ÃƒÃ“p%Ã¬-Ã„ÂŒÂ«oÃ¹Âµ%vM>ÂÃ‘uÃ®ÃlÃ˜ÂŒÂ®Â™ÂŒÃ¼7Ãs^#Ã¸ZÂ®Ã²Â†gÃ€Ã¬Â€fÃ¶Ã«KÃÃŠÃšÃ”ÃšMÃ¬Ã‡AÃ­\\tÃ²ÂšÂ–Â•ÂŸR\\ntÂ¶iÂ„{Â¯Ã›H~ÃÃ…Â‡DÂ¹Ã‚HÃ†qÃ°Â½ÃšgqÃ¥Ã¸Â±Â c}Â˜&ÃpÃµIÃ[E2NÂÂMÂ¬Âš/Â®Â»Â¼Ã¸Ã›Â£9Â™oÂµ ÂÂ†1Â‚Â¯Â™Ã¤Â¦Q%yÂ–Ã–Ã¢ÂºÃ¤Lm>Ã›Ã¾:4HÂ¾ZÂ„@Ã•xÃ˜Ã‰YÂ§Â•ÃŒÂjÃ€Ã AÂ°b8Â‚<)aÃu\\rtKÃ¬$Â¾Â‚<Â¦Ã©QÃ½\\fÃ¼Ã€Ã™ÂšVÃ—C)rÃ¿Â¾Â•9Â€Â˜Â€aÃ»tÃ¦aÃ¸}Â«Â³wÂ£ÂÃ¾{ÃƒÂšÃ—8QÃ±ÂV(jÂ¨JÃ’ÃH9Ã­Ã¶ÃšÂ±vÂ¢Â¦ÃµÂƒ9Ã«Ã’)uÂ‰Â½Â§ÂYKjÂ‰ÂÃ«ÂšBÃ™Â…ssgT(Â•-ÃaYÃÂµ Ã¿R=5Ã§Â˜Â€Ã´Le$ÃŸcÂ–WÃJÃˆÃ¾aq;Ãµ2Â‡ÂÂ¸kÂ¿3ÃƒÂ¤Â… Ã’Â’EÃœÃ¤ÂªÂ³Ã Ã—<Âª 8Â†fÃŸÂÂ(VRÂ³Ã›ez/Ã³Â!Âˆ]Â“Â˜@Â™\\fÂ¾Ã–CÃ—<Ã…ÂÂ«QmÂ…Ã©Â°mDÂ?Â¸Ã•?kÂµd ÂšCZÃ¡FrÂÃ¾LÂ°@Â»WÃ‘5\\bRÂ†R@Â¢Ã®Â !Ã=Ã€AÃ£c*Ã½ÃªÃ´Ã¯ÃšUÂºÃ¬Â/8ÂÃ•Â“Ã’Â«_Ã†ÃÂ¨<Â™U\ÂÃ¼@Â§jÃºf (ÃƒÃ¸c#^ÂšIK{oÃµÂ€oÂ‰@JÃÃ¦Â¤"|sFÂ¥ÂƒÃ¿Ã¢Ã©ÂºeÃÂ‹Â‘XÃ»Â˜ÃšÃ·Â³Ã¨Â‰SÂ˜Ã¿|rhlÃ›j\\bÂˆÂ¼Â¸Ãœ^vÃ¯Â’Ã±Ã¾Ã‰Ã®ncq$%O}Ã–cB;ÃªÂ¤Ã™Ã®>ÃˆÂœE`kÃ‘HÃ…Â¡Ã«[Â½Ã‡Â†zÂ²Â‚ÂªÃ‡DN2Â›Â§Â»Â™ÂJÂ³Â„^Â‚Â²Â‹Ã°ÂÂ†Ã¸Â Ã°F Ã­Ã–\\bÃŠÂÂ‚Ãœ}?LÂ—ÂŠ"R=Â–ÂšÃƒÂ»^/Ã’Ãp?Ã‰Ã‚ÃgÂ¹.$Ã«Ã!uÂ—Â£ÂºXPSÂ€6Ã…Â—Ã”Â‚Ã¢Ã\\bI3\ÂˆUÃªÃ•5<#Â¾Â±2ÂªÃ‰Ã¹+DÃ«Ll`Â±Ãª@Â†Ã“Â‚f3OÂ·Â£lÂŸÂ Ã›WÃ¯"!!Ã¢Â²Ã²kÃ“kÂ‹ÂˆÃ§qÃ‹kÃ‡Â‘Ã¿Ã£Ã³Â•Ã©Â±Ã¼wÂ½Âº#;Âˆ>Ã´ÂÃš\6Â§Â¹Ã¼ÃŠÃÃˆ|Ã„ÃªCÂ·Ã†ÂÂ›ZÂ—PÂ›Â´Â”Ã’\\bÂ¹UwÂ¤`\\tP%Ã¿cÃ¸~G,n7/Ã°5ÃÃ¬Ã¢ÂŒ(Â…Ã´Ã£ÃŸ!m,Â‚Â›KHQÂ¼Ã£Â¦Â‚Âh,\\rÃ›Â£ÃŒ~Ã‹SJoÂ–Â´Â–Ã¸w4Ã¤pÂ¤Â– ~Y!Ã™xt'Ã–Â‰~Â›ÃÃ¹AÃ®0i"QfZÂ™Ã„%Â›.Ã…Â¶Â¥hÂ¤EÂš.MÂ¥ÂšUq;Ãu\\fRdQÃÂ›&ÂŠ#;OqsÃZÂœÃÂ¶dÂ¬Ãº\\nQÂ¹g{ALÃÃµÃ‡Â²Â’Ã»ÃÂˆÂ­\\fÃºÂ‰Ã«ÂÃ¾Ã«>Â½Ã¿-Ã¹4ÃCzÂ‘ÃƒÂŠrtÃ—=Â©Ã†rÂ>Â¤ÂŠ#@g&Ã›ÃX%AÂ°Ã“Â½Â‚Ã‰Ãœ:Â³Â•Ã¦8*^Â†ÂÂ‡Ã€5iÂJÂ‘Ã¥-Â—Ã€kÃ¯h\\nÃ^Â¨Ã’ÃÂ‰ÂÂ§IrQÂº Ã¥<Â‘\Ã‰Â \\f 0ÃºÃ°Â‚Â–{Ã²ÂªÂˆU Ã½ÃˆÃ»%Ã­Ã¿Ã„ÂŒtÂ¿ Â·rÂ°Âªi_dÂ¬AÃ£Â»Â¥Ã§Ã¼ÃÃ¿iÃ¹DÃ¤Ã™Ã„Â¾Ã¼Ã´@Â—z\\fGWÂ†Ã»Ãª]b*1Â¬Ã¦ÃšÃ¡Â¸}ÂÂn$Ãˆe\\bC,Â¡Â†Â©UÂ®ÃŠ8Ã©Ã£Â±Â‚Â’\\r$Ã‡Â—9y+Â¬Ã»Â§ÃÂ¹Âª#Ã¾Ã½Ã‚Â´Ã·Mvs:ÂÃœ+Ã†^TÂºoÃ¢Ãƒ@?rvÂ›Ã†!ÂÃ®Â”*DÃµÃ¤iÂ¦Â½Â¹Ãœ\ÂªÂ„Â™Ã»\\tÂ“Â¬!Â«Ãn\\rÂºI0{2\Ã£Ã¹(Ã–|7/$Ã‡ÃšÃ½Ã—Â—Â´.Ã·Ã½AXTcÃ’Ã©,ÃªÂ„Â°hÃÃ®OÃ–Ã¥MF'Ã—Ãi\\ngÂ½JÂ® &Ã£iÂ´Â1LÃ¤Ã¾,ÂµÂÂ§Â´LkÂ‹S{PÂ°Â“V"4kÃ±r\\nÂ§\Ã„ZÂ¢"ÃŠLÂ»=Â¯Ã°Â´^ÃƒhÃ¿;]^~]ÂšÃˆpÂ¾:v(\\nÂœÃ•Â‘Â–Ã†Â‡Â¶[Ã¬ÂÃ¨\ÂŸÂ§Â³Â³SwRÃ¦<Â”>MxÂ£Â¨6`hÂ£vÃ³38Ã–Â´TÃ¤WU4)Ã’Ã¸ÂœwÃ°ÃÂ›9Ã›Ã‚} Â—ÃÂ‰Â´ÂŒÂ–ÃŸÂ›IÃ´?Â’n!Â‹VpÃ­tÂ¦ÃŠT JC\\beÂµÃŒÃ®6N2VÂGoÃ›JÃ‰=\Ã§fÂ¾}sÂ \\tÃ€Â§ÂLÃ§ÃÃÂ»ElHJQbÂ¿Â¬+Â·ÂšÂ­WxÃ€CÂ’\\fÃ·b#2vÃ§R,i>ÂÂ¸pÂ”vÃ˜ÃœÃ¶Ã½Ãº-LAÃªÂ‹\\f0QQR#]Â•pTÃ«Â¡wÂ¬ÃÃ§Â±\\r\\tbÃ©N^Ã·Â˜Â›ÂÃF:Ã‚Â½Ã”Ã¨Ã ÂÂ‰B[Ã—bÃÂƒÃ»v~ÂªÂ—Ã¡mÂ¬Ã¯Ãµ(Â³.u4Â¬Â¤kÂ›N3 C{WÂ—)Ã‚*WJÂ­Â™mÃ²-Ã±Ã€p\\r8,^Â†%Â®j@Ã´Â2ÃƒÃºÂ»IrIÂ–ÃƒÂ²rMÂªÂ±<Ãª5oÂœDÂœGÂ€~\\n3Â»zÃ—KÃ³Â‰Ã ? h&Ã‘ÂÂœqÃ§*Ã–jÃ‚bÃ¬ÂºÂ¶ÂºK;Â¹!ÂœÂ¤ÃœÂ·xdyÃ„Â›?~Â*Ã½Â Âpj;Ã¿ÂªÃƒÂ‡ÃÃˆIMAÃ¡Â¨?m<ÂªuIÃ¯Ã³:OÃ¡&Â»ÂƒÂ¤hlZÃ¨_Â±Ã“Â wuÂ‚JÂ˜ÃŠrÃ½\M~~aR-IUÃ‰5y1_Â;wÂ¬Ã‹Â¶ Ã¦Â±iÂ‚sÃ¯xÃ”r{Ã·Ã†Â®ÂºÃ«Âƒ#^Ã ÃµÂ²ÃŸÃ˜8Ãº5Â©ld8Â¤ÂSÂ¹%ÃµÂ–Ã®Ã "Ã±Â©\\fÃ™Â·ÃˆÃœÃ‚Ã«}Ã­NÃ¥Â²Â‘PK2\\rÂ‘Ã„pXÃfoÃ®.Ã”\\bOÂÃ°GÃ–ZPh)>Ã†#&2*Â¸ÂÃ™wCÂ˜;\\nÃ¤/Â¿Ã†)9ÂÃ‰KÃÂ•Ã¸fÂ³Âƒ\\r5MÃ¿AÃ»;ÂÂœ?@KÂµÂ»Ã‰|WHaÃ lÂ¶Â™Ã¯Ã·Â¬KÃ§vBÃ—-Â´Â°J{Â¤Ãš?Ã«Ã¸ÃÃ…Â£Â›Ã‹mÃˆÃˆÃ¥f2Ã¹Â£ZZÃ•vÂ™Ã¦SDÃœyÃ£0Ã¥Â¿Â¹ÃÃ©ÂÃ¯Ã¡Â¤Ã¿kÃ¯Ã¹\ÂºÂ°.u Â Ã©'Â“Â—Ã¼RÂ±Ã©_RÃ­"Ã…CÃ›\\rÃ’S3<8ÂŸÂ”oÃ½{Ã•t Ã­P`}ÃHÂ«0\ÂªÃ±ÂŸÂ¥GYÃ‡Ã‰]ÃÂºÂ‘Â½Ã¯9yÃ€8L/Ã¹Â¹Ã¥LÃ‘Ã§Ã¼IQÂŒLÃ†Ã»Ã,Ã±S\\frÂ›FÂ‘oÂ¼Â¤Â„(Â¬Â¶\\tÃ¾KH~AÃ¤Ã„Ã°9Â±ÃÃ«Â“}Ã­AÂ§`ÂwmTÃ¶>+_Â†7ÂˆÂ®Ã”1ÃÂ‰Â¸E^Â‡?OÂ¹Ã‹eÃˆÃAIWÂÂ‡qH\\nÂ›}'ÂŸ\\t9ÃÃÃ”Ã€Ã¥ÃÃ´Â–2ÂšÂÃ¬Â€Â±Ã¼5]Â¤Â¶iXmÂ…ÂÃ²Ã‘Ã¼Â”Â¥AÂ¦a+NQÃ—Ã²ÃˆpMÃ³Ã²ÂšKÃ•?Ã©pÃ“ÃŒ$Ã–Ã¬LÂ° &ÂZ`rÂ—ÂšÃ¬>Â¨Ã¶Â§Â•ÂŠ!Ã‚/IÃ«aÃ¾ÃºAÃª-ÃsÂÂ‹Ã\9Ã½Jc4Â“hwÃ§Â·!1Â¯rÂ¾Â–Â¯Â†Â¨\\nnÂ‰Â²Â´Ã¾Â·Â¿\\rÂ¶Ã’5:vÃ·Â·%UÂ¾/Ã…J:ÃºpÃ FÂ¨2Â™Â:Â•Â¼UÃ§Ã¿Â·ÂaK5ÃÂ‰ÂŒÂ‚$HÂŒÃ•ÂƒÂ¶Ã˜Ã¬Ã™Ã”Â„*mÃ‹oÂŸMÃ±Â¿4Ã¨CÂ¨ÂºÃµÂfÂ²Ã±K-ÂŸÂ¬:ÃµÂ»Ã;Â²<Â»Ã€ÃšoPÂŒÃÂ¨"ÂˆÃˆÃ—Â¯Â…{Ã›KeÃ…?BÂ½Ã‚Â³[{SÃ·ÂŸpuÃ¨ÃÂ¥=nÂ¥ÂšÂ‰Â^(SÂƒÃ“Ã†,ÃªSÂ†ÃŸÃºÃ€'SwÃ¬?Â‰Â˜TÃ°Â½/Ã©ÃŒ>-Cw)&Â›Ã¦0CÂ¥2&ÂªÃ£JLÃ‰:ÂªÂµÃ‰Â¯Ã—Â«Ã€'ÃÂ–1AÃ¨9u4q*pwW-Ã»ÃŒÃ€Ãª\\fÃ…Â±Ã½|FÃ·Â¸-%Ã¡Ã¶ÃµÂ Ã¢\\tÂ±ÂÃ©2~Â²<im8'ÂÃÃ³VÃ‹Â†Ã¹Â±Ã‡Ãˆ{Ã©Ã‘QÃŠDxQ~H:OÃ­Ã•8LÃ°0HLhÂ€ÂŸÃ¬rÃ•ÂŒÃºÃ‹Â¬Â‘Ã‡Â½Ox-Â’ÂYÃÃ´zÃÃ‰Ã–Ã¼Â¯ÂŸÂIÂ¦ÃŒÃ­pÂ³&Â‡Â¡T7Ã‹iÂ®Ã» EÃ‚9Â¶Ã¤Â¸Â¼\\rÃ—RÃ†Â®7Ã«ÂŠ=Ã“Ã¥aF5ÃŒA5BÂ\PÂ“ÂœvÂ°ÂœKÂ¼Â­Ã¶]Â¯Â¨DNGW~ÂiÂ˜sjSÃŒÂˆÂŸ\\n Ã®ÃµÂÂŒÂ›Ã¡Â¯Â«ÃÂ‘,Â«Â“ÃŠÃÃ¦DÂ§Ã¹ÂŸÃµ\\fÃ€Â½Ã¥M]Â±3Ah\/ÂÃ¬f GÂ€Ã†Ã“"YX`Ã»ÃµÂ†Ã¿ÃªÃ¼ÃƒyÃÂ²]Ã–1uÃ£rÃ¥jÂ¸]Ã¬Â£ÃˆÃ¿ÂÃµZÃŠuqÂ´u(0NR%Â€1Ã’Â"Ã›}AÃ†Â§ÃŸ{Â¢mdnL[Â¸ÂˆsÃÂÃ–Ã³3Ã©|Ã¨Ã€Ã€WÃ—Âª(Ã¬7Â•ÂƒÃ‹Ã”Â‡<Ã»Ã·ÃšÂ¤Â€Ã¢_[yÃŸ%?ÂT\\f}Âª`Ã£RÃ%R2wÂ¤1Ã¹Ã¯Â\\bÃ’Â·EÂ¼\\b xÂ¤jÃ‚\\fÂ»Ã¤$ÃµÃ–@; Â˜Ã‰Ã®Â­j\\b<# ÂƒAÂ¸ÃÂ½Â«Â…Ã–Ã’ÃªÃ»HÃºbÂ‚dÃ…Â©\\rÃœ#-Ã˜: JÃ¦@$Â›Ã½DÃ‘'[dÂcÃ‘Ã©Ã«Ã˜`Ã–fÂe:Ã„Ã‹ÂºÃ~Ã¼vbc^Ã´o~?ÂUÂ¹Â€Â­ZÂ…Â¿Ã·ÃšÂ‹lÂ›Â¤!Â¥<.+7Ã»Ã®GÃ“5ÂœÃ¬ÃÃ±nnÂ¸Ã¹>Â®ÃÃ®TÃ¹fsÃ‚Â±Â½Ã«ÃÃ7Ã„Ã¬bgV<Ã›ÃÃ©Ã¸CÂ«Â°\\r\\rSÂ³#ÃºcWÂ‰#Â¼ÂŒÃ¨Âª]N@Â§aÃ‰ÃˆÃœÃ§7Â©Ã›QÃ•Â¥'ÂºÃªMÂµ\\rÃÂ°Â«Ã»Â·@ÃªwÃµjÃ’Â´Ã€Â¢fÂ—cÂƒÃMÃ¨Â–YB0rÃ€^Ã¥Ã´Ã‘Ã£9v91BÃÃµqh?#)rÃ†Ã­fÃœÃ…Â´Â‚Ã³ÃÃ™>Ã‡ÃÂ1ÂŒÂ˜Ã°Â™#Â¹7Ã¯9~\\f+1Â¯Ã»Â›Â©Ã§ha.g!y={WvnzÂ€bxG*c}Â¿Â…Â$Ã­RÂ²)Â¢Â¤Ã„PÂ›Ã¶lÃ®Ã¯MÃªÃ„8Ã§rÂœÃ±@Ã†Ã²5.Ã”Âµ\\nÃ³Â´fÃŒÃ€Ã¸Ã”-ÃÃ¨Ã¬[XÃ¥Â¼[Â­Â¥=Ãm,Â}ÃŒÃ¼Ã° Âº"Ã•WÂ‘bÂ’Â³ÃŒ0xinÂ‚kÂ·Ã½zÂ›Ã¥Ã«>ÂªÃ—Â‘Ã“Â†ÂÃ‚Â«Ã‘Â­Â´Ã“tÂ«,HÃŒÃ“ÃŒ6Â®iÃˆÂ±bÃ·9eÂ¢Â¤ÂˆÂÃ¾Ã¦7Ã—bÂ„ÂÂšuÂªÃ¼Â¼ÂŒÃŒUÃ˜'Ã‡Â Ã¬WÂ®Â­sÂ«`Â¹>ÃÂ‹ÂƒÂªJVÂ´ÃƒsÂ¸SÃ£kÂ¾+Ã‰YÂŠÂ‰IquÂˆÃ–0Ã­Ã“ÂškhÃ±qqoÂ¸Ã³#AXÂŸÂ´Â¿Ã”N.gEÃ¯z$+ÃˆCÃ†"W`.Ã»Ã›Â³Â¹Â¹&Â»m\\nÂ’3Â¼Nc!`ÂƒÃ©4ÂªÃ¨SÃ™<`ÃJtÂ‰'%Â…XSÂ„ÂšÂ»nÃ”Â®Â‹DkÂ³Â‚RÂ¼Â™zhjQ}Â™Â‚.Z?Â±Ã½Ã¦Â®Â•GÂ‘Ã…Ã\\rÂ²dÂšÂ•ÃÂ°Ã†Â„Â‡*Â¢4Ã¥gÂ–\\tÃ…Â¬~{46Â£JÃ™QÃ±Ã–Ã‡Ã‘Ã´'Â€Â¼Âˆ')!TÂ“*CÃ˜Ã‘ÂÂ²\\rÂ¡2Â‡ÃAÂ†MÂ•ÂŸÃy?2Ã„Â¹lÃœÂºLJÂµÃ¸TÂ€nÂÃ›frÂŒ#Ãœ#ÂˆÃÃ„Ã…Â„YÃ¼Â–7RÃ¼Â­k[]Â²\\tÃ»*:h'Ã¤Â±Â£ÂÃµÂŠY0Â«Ã¢ÂšÃ’Ã®\Ã´ÂµÃ¿ÃŸ%=Ã±ÃµÂ©Ã¨fÂ…tÂ™JÂŠÂ´Ã¼Â„4 TR8@-Â’Ã¯b\\t\\fÂ¶hÃ¿_ÃÃ³CÃ’ÂšÃ„[Â eÃ Ã£6=ÂªJoÃ¼Ã”vÃ¢&GhÂªÃ„ÂŒÃ°Âˆ>Ã€\\nÂ“iMÃ©=Ãœq<NÂ²Ã‘nÂ«Ã‡Ã»rÂœÃ´Ã™Ã\\fÂÃÂ™Jk-QBÃ¢TÃ§ÂÃ®Ã»ÃÂ²-Â©DkÂ¸JÂ©Â¤VO1,\ÂšmÂ”"Ã˜ÃƒÂ«rÃ¶Ã¿Â’xÃ®]Â¡aÃ›*ÂMÃ¿[Â‰Ã¦(XoÃÃ¡Â“X};Â™Ã”Â³WÃˆÂ²Â–*Â¯LÂšÃ’nÃ=ÃšÂ”Â—ÂqÃˆÂ‰Â©Â¡%ÃˆLÃ]Ã½s&ÃŒÃÃÃ£,Ã¢Ã‰yÂ¿ÃÃ¤Ã‰Â´Ã¼Â´$PGÃ¬jÃ’VJÃÃ²ÃƒÃ£)Â¡Ã´#Â‘KÂ¹Ã£XÃ…\\f\\nÂ‡Ã”Ã§]5.Â²Ã‹Â›qÂ SÂ¬$Â¸ÃªÃ¡Â Â€:Ã &Â‡eÃ¹9Ãi5Ã¢CÃÃ‹?Ã¡.Â©Ã»#ÂÃ­ÂŸÂ§;; t\\tÂ—=f\\fÂ•ÂO,ÃˆÂÃ–>Ã—Ã¿/Â°Â–Ã­7DÃŒÂ›LiÂ†ÃÂ‰1Â™V:Â™<Ã™BÂ·ÃWÃ¼hÃ«lÂµ-Ã“Ã¯ÃŠlÂ—ÃŸÃÂŸÃ¾Â½IÂÃˆÂ«Ã•Ã²_^3%ÃÃÂ©jcÂ¬hbÂ½Â¢Ã¡BÂªEÂ´vÂ›uÂ±moÃµÃº_#WÃ“NÂÃ˜\Â›Ã¯Â¡Ã†Â»IÃ¶Ã½p9ÃŒÃ‘\HÃ¬Ã¾3XÃƒjÃ¸Â©Ã°Â»Â£q]"ÂºYIÃ±Ã¯kTÂ¦Ã¢Â‚ÃˆY0Ã¯Â¿ ZÃ“Â·ÂŸP\\bÂ†Â´Ã&:Â€Â‡ÂŸ/Ã‰huqÂ¬Â F\\nÃ“Ã—ÃŒ[Ã“IÃ—aÂ§Â§Ã”<NÃ¤Â¸Â˜Â™1_Â¥Ãº0Â 1Â§[Â”Â‚Â§\\bÂ–)Ã¥Ã­Â Ã…Â¾Ã‹Â–ÂºÂŸÂšYÃ°hÃŠ}Ã‘)Ã†Â–P$ÂosÃŠÂ¬hÃ¸Ã†jV2{Â»Ã¹Â°ÃœTÃ”a\Âº\\fÂ²Â‚ÃÂ:Â†WÃ¥Â”Â„ÂŒÃ‰PÂFÃ®Ã¦Â£]Ã–ÃŸÂ7Â®Â,v`ÃÃ”7"ÂŒ6SÂ™}BcLÂ›9ÂqÂ¥Â¸Â¹Ã¶Ã©Ã“Â†Â¸N:ÃÂ¦Â§hCÂ©Â$Â§RÃzÂšÂ†Ã’Ã´\Ã·ÃƒÂ \\nÂÂ¤Ã¬Ã·M}\\bLSÂ«Â¤Â–zÃšÂ£Ã‘kEcRÂ³3Ã¼PÃ¡$Ã |Ã›Ã…>ÂšÃÂ¶n8Ã¥ÃlXPÃ‚MzÃ­F-Â”Âº*NÂ”Â¸Â¡Ã¦$Ã¶ÂPhÂÃšÃŠJÃ¸Ã±fÃ±(Â© pCDn$sÂ­Â>UÃ‰&ÂŸÃœ1Ã£zuÃ°Ã„ÂˆbÂ½Ã®Â¨Ã­Ã ^Ã£ÂÂ¡t,{$=Ã¨Ã¦Â· ÃœÂºFFNpÃÂ¬Ã¯Ã˜Ã¹\\bÂš?Ã¾R;Â­lÃŸNe\\n2ÃœÃœÃ¤?Â¾)Ã‹7}AÂ¾Â»ÂÂ»6Â’Ã†ÂŠ6Ã©Â¬OWÂ¶ÂŸÂ˜RÃŸN\\fyoyÃ»Â¹rÃ–ÂÃ—Â©8Ã¶^Â†Ãœ1Ã§ÂšKÃ·ÂœÃ¯>}Â£}OÂŸÂŠ:ÃÂ“Â´Ã´TÂ©Ã‚k*Ã©Â ÃƒwÂ¨jÂ¶NÃ‡Ã±[Â²$\\tÂ¿Â„Ãª2rÃ°UÂ›Â’Ã´ÃÃ•Â‹QÂ¥Â†OTÂ‹Â©KPkÂ´)tHI'Ã£3Ã¥Â‚Â´H*ÃKÃ‚bÂ•To7Ã²Â²?$Â“4yTÃ¬ÃªZÂšÂ‚Â¯Â¥\\fÃ†Â´YvÃšÃ¹{Ã‘Â²Âº\Ã“iÃ•Â»Â•Ã—AAIÂ„Ãˆ\\fÂ¦Â£Ã†wÃ®cXOÃ¼Â±qu\\bÂŒ{UPÃ­ÃÃˆbÃ°-}ÃÂ¤RÂ‘ÂÃÂ¥Â»XÃ¹ÃÃ™gÃ˜ÃdÃ‘Â¨ÂÃ‰Â…Â¦Â£ÃƒÂ©#gvrÂÂ¨OÂn4Ã^WsÂ€Ã’Ãœ/Ã•DvÂŒ9!Ã‰r/Ã˜Ã¨ÃºÃƒRÃƒÂˆÂ»H/Â¿<@#Ã½u.&Ã¿Ã’ÂœÂ“Â¦Ã¬R_}Â£Ã±Âº%Â©Ã‡Ã¥ÂÂ£5Â›(ÃÃ°^Â—sÃ¯p'ÃˆÂ±Â°Ã½~Ã©ÂœÂ¥+ÂÂ¡\\nÃ‰Ã¬+ÂEÂ´SÂÃ­'xÂ¬Â‹t5NÂ±Â¦Ã¹Ã®Â²Â‘*0e3+x~Â™yÂ’epE"Â€ÃŒÃ\\bÂ¡Ã–ÂªeqÂŒpÂªlmPK!Ã£Ã˜TÂšKÂ±Â¶G\\nÃ™Â£ÃšÃ¸Ã°Ã–jGEuÃÂ‹Â¨[ZÃ BÂdÃ‡ÃµU\\tPÃ£Â—RÂ¸Â¦~"Â½Â†ÂºÂ¥TÂ½Â£ÃƒT#?ÃƒCe.Ã½ÂªÂ¹Ã-Â™Â‘Â³Â°hÃ…Â§cÃ·&Ã¶Âˆ,g\\bÃµÂ…Â°Â°Â¸Ã«Â‘<NÃ£Ã†bLw:Ã†Â¢\\bÃ¬Â¿Ã…xÃ„rÂ‘!iÂ¸Ã“4IJ:ÃŠÂ¿Ã¾GOÃ¸Ã·z*ÂŠÂÃˆzX[x\\f'Â¤bk_Â¾mZÃˆiÂ®ÂŸ'oÂ©Â·Ã­Ã±Â©Â…-\\rÃ´|OÂ˜Ã¦<W\\rÂ…Ã™&Ã­ Â´7xFÂH1PÃ¼Â‡Ã¦rÃ»ÂŠBÂºÃ‚=3Ã«k3DÃ°lÃ¹ÂŠiO#nÂÂq?oznÃ”<.ÃÃ™ÂŸÃ„Ã•Â›Â©Â¾VXNÂšÃ ÃÃ›Ã®ÂÃµ/WÂ…Ã¼Ã†Â¸Ã—RÃ¤}&pÂ¥Ã“Â—Ã¯Â¹Â¥!\\fÂÃ”ÂŠM8Ã¤Ã Ã“Ã·Â¼hÃ¨Â•Ã¿SÂˆz$1Â¼8ÃÃ†nÂ”Ã²Â¼ Â¦Â¶ÂoÂ¢Â·Â˜qÃ¶.+x}#Ã°PÂƒÃ†t/>Â‘wÂ¤Ã£uÂ¢Â£Ã¯Â¶>ÂÂŸÃ¦Â Ã¾Â£{Â~ÂOÃ—;ÃW[#ÃªÂ°Ã³ÂÂ¼%ÃŸÃºÂ‰Ã›Ã”Â…Ã¹`Â¼Â­tÃ§Â¬Â†DDfÂ€ Âš,mrÂ–Ã„Ã¤Ã¦Â² Â®Ã‡ÂŸÂ½HÃªÂ·Â¸CÃ½Â¤ÃŸÃ›Ã¸FÂ†{Â‡\\neÂ‡ZEÃ \\bt2Ã–Ã©,ÂªYd\\rÂŒÂ‡Ã‚Ã¬ÃE!Ã•Â—-Ã¨sÂ‚CÂŠÃƒÃ¾U=N zÃªÃ¶Ã¤Â…Ã¸Â‹ÂÂ«Â…oeÂ¢qWaÂˆÂ›Ã€(T\\rÃ¯Ã˜Â˜Â¶Â Ã‹\\nrÃ›Ã†>\\t`Ã£z3HÃ´Â½Â”sÂ¨ÃÃŠLrFÃ¸Â–Â­Â½>!ÃºÃ†Â€ÂµÃ™ÃÃ£o;Y.;Ã®Â©!Ãµ%Â‘Â±Ã½ÂÂ¸Ã†Ã´Â‡Â±7IyÂ„NTrÃ®zÂ¶ÂÃÃªeÂªXÃ˜Â‚8Qj\\fÃˆÂƒÂ“Â™Ã“Ã¦-O)ÃœÂ†+_oÃ«Ã·Â“Ã†ÃƒÂ›y0'#.N<EÃ¾ÃŠÂ™Â¨Â Â«Â¥ E+ÃÃœÂ•Â VWmÃ‡-*bÃœÃ«Ã€]Â5Ã¨Ã§ÃŸ8Ã³9DÃ–6Â£Ã‘Ã”A{ÃµDJkuÃ­ÃŸÃ‚ÃŠ Ã¤Â¿y6sÃ©@Â˜Ã·Ã…TÃ„Ã–Ãƒ7nÂ†1ÂƒÂ¬6Ã„Ã„ÂºÃªÂ‰2jÂeÃ³ku&kV8Ã BÃ¾\\fÂ€ÂXÃ¹yrÂ•ÂŸQÂŠ'ÃŸÃ¦Ã‚ÂÃŸxÃ»pÃŠÃ¿Ã¦ÃºÂ£ÃkÂ¨`Â¹&Ã™Ã…Ã«Ã†Â‘T1Ã†Ã„Â¯\\nÃˆ*Ã¡\%ÃŸdÂ˜1Â£Ã…1LxÃ¢ÂˆÂ”Â*DTÃŠÂ¦ÂÃ¹ÂŠÃ„Â°Â»%Â»Â·Ã´9qÂ·>\\n/Â™1Ã¶Ã¾G}Ã­Ã·fÃªÂ¿:ÃŸb.Â³ÂºÂª/erGu#4Â¬Ã€`ÂœÃh8*ÃšÂ¨hÂ“Ã¿FÂ¶Ã¶Ã–9\\tÂÃ¶Â·ÃoxÃ½I:CÂƒÂ‹Â¥Â‹_2ÂªTÃ—?qÂ«UÃ¦wÂ˜Ã¤Ã)W<}(Ã«Ã+Mpw6HÃ–Ã›{Â ÂºdÂ€Â—Ã™(ÂºÃ–&Ã‰Ã½Â¶Â„BX Ã¢ÂŒ7#Ã¬KTÂÂ…':^ÂÂ¹GÂ¢Â‹PÂ¤$ÂÂ‡)Ã¿Ã¨Â»Ã™Â…Ã Â¹Â—ÃŸH\\f!=6Â¤Lp2Â¦oFÂ¢Ã€O08Â‹Â¼\ÂÃ’Ã–ÃÃœÂ½Â¬[ÂŒÃ¥,Â°Â«`Â†.Â±&sÂ’pÂ­k]ÃÃŒqÂ·Ã Ã +Â”>Â§Â‚Â•YÂÃ–Â½}pS\\bÃÂ¿Âº}j%ÂƒÃŠKÃšBÂ¿Ã¸=Ã‚Ã‰ÂÂ«Ãœ)Â–Â†ÃˆÃº&tÃ”Ã¡ÂÂ‰Ã¨hiÃ½Ã¦Â¼Ã”ÂŸÂ—ÃÂ­Â’ÃfÂ‚Â¡Ã¶Â@Ã’%ÃƒÂ†sÃ”Ã©Â 3q ÃƒdÃ°\GÂ¬Â»Ã°Ã·Â¦,Ã³Â²Ã“+ÂÃŸÂŠÃÃ¿&q\\bI4Â°pÂœÃ­#Â•qÃ«2Â«Â·+Ã©uÂˆDÂ­LÃ­;Â‰Ã–R=qÂ°V[ÃªÃ“$Ã¤Ã–=<uÂÃŒwÃ¥Â¶ÃÂ¤GÃŸÃ¤Ã(Ã·Â˜KÃ¢Â¹jM1Ã¼ÃƒÂ§ÃÂIRÃ…x{6Â·:2h&u#Â±n,ÂÂŒÃœÂ²Â¨ÂµPÃ»oÃ´{Â¦ÂŸÂ¦Â¬O~Ã­Ã†ZFÂ Ã³ÂÂ¾Â»zÂŠÂ¯:/Â‚Ã‰wÂ•Â¬Â§Ã´0Â„*Â®ÂÂNÃ˜Ã¾kÃ‚Ã½Ã´Ã­KÃÂºÃÃ€Ã±MÂ£Ã“Ã¹mÃ·Ã«Ã¹Â½Ã„Â•Â¿oÃÃ…)ÂŒlÂ¯ÂbÃ¤ÃÃªDÃ„/ÃƒÃ…Ã¾&Ã¤Â…^t.z?uÂ»Ã—Ã™lwÂ—Ã…[Ã¿Ã­Ã¬SÂƒÃ´XÂ©azÃ¨Â®Ã¹Â®&ÃŸbL7Â­ÂˆÂ—Ã³Â›Â¶LÂ˜ÂªNHÂ”Â…%) Ã¡Ã’Ã…Ã®uao=Ã‚+Â¯o<"ÂÂŠ;Ã±Â‚ST's}hOÃ€Jb\Ã‚RÃµEÃ’RbC6Â [Â¿OÃªÂµÃ¶Â…Â¾Â‘Ã£Â²=Ã¤dÂ\ÂÂ™Â¼vÃ®Â¬Â±Â·3ÂšÃ¡?JKrÂ®mRÂœÃ™fn/7Â«Â€ÂšGÂ zÂ‰LÂ¹Âœ_Â©Ã©RÂ¨3JÃ{Ã€Â…Ã®Â©\\ra(1AÂ‹Ã—GÂ›hÂ—Ã¢|Ã¡Â‰+Yx5Ã•`Ã¯Â¥6ÃœÂÃˆÂŠÂ¡xÃ°Â¶Ã£{nÃ·iÃ¿Â‘M8ÂƒÂ:ÂƒÂ³7[Â“\Â˜Â¢Ae06Âª4Ã‹ÂAÃŸÃœÂ´Â„ÃœÃÃ·ÃƒbÂ x=ÂÂ½Ã¨X9Ã§kÃ²Â²ÃÃ‡Ã§ÃˆO4Ã´ÂŒdkÂ–Â½ÃƒÃ¾ÃªÂ¬8Â¶_<5iÂ´MÃ‚Ã¿Ã–?|KÃ´RÂˆÂ¸Ã³-0Ã¹Â™ÃºÂ¹WÂŠÂ†RÃ«Â€1qÂ¨@Ã‚ÃˆÂ–6Â¿Â¹Â¢Ã²vÂ‡Ã‰qL}Ã„-f Â’Â¬*\\tYÂŠ$Ã¼.ÃªÂ©-Â—~Ã½FBÂ©Ã¶WN-Ã¯OÂ±5PÃ—qÃ«ÃšÃ£ÃPÂ]Â¦rÂŠÂ¬Â…^QÂ‚Ã¯.ÂsÃšÃ3Ã¨Âº3Ã± Â†7Â°Â•Â—ÃŸ8Ã²0Â‘\\nuÂÃœCÃ„ Ã•rvTÂ‹FÃ¦:Ã¯Â‹Ã¤Ãµ,Ã½Â&Âš0Ã“e6Â™Ã°ÃÃ ÂqÂ­8Ã›ÃÂ˜/Â´AÃ†XUÂÃ²QÂ¥Ã—dnÂ¯Ã£@hnÃ…Ã®ÃÃºÂ›%Ã¶Â)\\fÃˆ&UÃ–Â¸' A*jmÃ‹3[Â“Â·nÂ³Ã=ÂkÃ’L]\\tÃ¥Â•ÂcÃÃƒpÂ„\E'Â’ÂœÃ§7Ãg4HÃ…Â·Ã¸bÃ¨/1xO+\\nÂµÃ…Ã¸CÂŒÃ›\\tp=Ã¢|Ã‘Â+Â¯ÃœÂ‡+>mÂ Ã³D?Â°uÃ™Ã£Ã¨.Â–`U_.Ã[TÂ¤Ã¦Ã»Ã®&Â´JÃ©Â¬Ã’Ã§EÂ€ÃaÃ’lÃ†Â‡O7bsÃŒCÂ˜kÂ¹Â–/by}`Â*JXÂ‹\\rKK\Â½lÃ«Ã˜Â•Ã Â>^G/ÂºB\\fhÂ“Ã›3Â¹Â¢Ã’Â Â .Ã¥{Ã…xtÃ¦Ã™H!"ÃÂ§&tÂµÃ±Â‡FMÃÂŠÃ Â@=&;Â–ÃÂ®Ã¥ÂQÂ§Â¢Â³Â¨%ÂŸÃ¢{^\\bÃ©vÂ°(Â¢sÃ¡GÂ»ÃµÃÂ±s<Â¿Â©\\bÃ¸Ã*tÂ­Â°Âˆ[ÂšhGW~Â‹ÂšÃ‚Ã·Ã•*^(Ã£Â¥ÂSÂƒ3"*Z$ÂÃ¬mÂœOfÂ·Ã²Â€WÃ™Ã™ÃšQ[\\bÃ¤Ã¡ÂµÂ»m:Â’WÂ¶ÂˆÃ}*g(ÂŒÂ¥Â¡ÂÂ¥Ã—Ãµ$Â¶Ã—qi_rXÂ•ÂƒÃ‡FÃ„ÃˆJÃ”@4Â„Â©ÂœÃÃ¸ÃÃ´s\\bÂ±Â¶ÃÂœÂGÂ¦Â…Ã’KqÃ‰ÃÃ¾Ã±J\gxÂÃ¸Â£D.Ã¯Â’Ã±Ã 46ÂŒÂ³e1ÂSÂ€Ã‰B\\bPÂ›Â¦ÂJ8q\\tÃšnDÂ‡Ã•Âœ\\rÂ®\\rtÂˆÃ˜Â?=Â«Â©Âª|ÃÂªÂ‡eCÂu:TÂ½ÂgÂ¥Ã²Â—s\\rÃ›ÂªÂ¾Â™ÃÂ½nÂ¼Â«*Â‚%Â±ÂÃ„\\nÂÃŒwYÂ·zlDÃÃ³O/6Ã­Ã›lÂ«riÃ¤Ã²Â•Â–Â¢XÂ›+zÂ¶Ã‚@{Ã’Â­ÃªÃ´UÃ‚Ã²wÃ˜Â¤Ã“Ã¬Â™ZÂ¼Â¤Ã¨Ã :Ã¥Â“ÃŒÃ½Â®bkÃˆÃ¢_%Â³IÂ† Ã³Â Ã­Ã‰)Â®Â˜Ã‘ohÂ›%j$ 6Â©Ã¼_Â©vÂ²TÂœ|Ã¿Ã°Ã]ÃµxOÃ2Ã I\\b&E-Â‹5Â¥Ã¥Ã¾Â»G6\\rW\Â‘Ã±ÂŠiÂ’Ã¬Ã…Â§Ã¡eÃ²Â˜ÃÂšÃ«UÂ†fÂ…)%Â­4UtÃ‹Â•X4Ã§Â‰Ã—\\fYYrZuÂ¤ÂŠx|i\\bÃœ1(kÃ¹Â—%"Âµ\\r$Â‚Â©Â¯Â€Ã¾Ã•Â£Ã¬ÃƒÂ–@ÂœÂ²ÃXÂ‡ÃªÃšÂ¯Â€Ã³ÂÂ¸]Ã¬Ã²Â¸Ã’ÂºAÃÃ¤Kg)7Â°GiÂ›E@Ã™Ã•ÂÃªÂ¼Â‚[Ã¶Â†Â‰2Â’v=\\rgÂ ÃHÂ¯9YÂ bF$Ã‹Â˜Ã»~Ã¿Â®ÂŒÃ Ã‰Ã—Ã¹lÃˆ%Ã®`Â’Â™I;Ã¼Â–Â¨X*Â¯\\rmÂ„,Â•Âˆ!ZeÂÃ²RPiÂsÂ‰fÃ”Ã¿Âˆ#Ã¢0ÂŒzÃ›Ã†9Ã‚Âš5YÂ¥Ã‡Ã²XÃ¢ÃŠyÂŠÂ¯Ã¤\\tÂ¶Ã€Ã©ÃŠ_]ÃÃ²Ã´NJVÃ½Ã½7Â‰Ã»Ã•UmÂ—Ef-Ã®7ÂŠÃ²Ã¡Ã†SÃ»Ã‡Ã˜\KÃ»Ã¤ÃºÃ„ÃŸcÂ¼TÂ´Â¤#Â€Ã˜cbKÃ¯xGÃ¸Ã„lÂ‚>9%Â®Ã¼[(Ã Ã…UÂ…Â»Ã‚Â°\\tÃ‚`Ã´ÂŒ\\rQamGbTÂ‹Ã’9ÂÃ›Ã°Â­Â…Ã®].N>NÂ«Ã…Â€Â˜Â P`Â‘ÂÃÂ•'Ã¸6Â¢\\fÂÂ»,Ã¶Âµ6ÃŠÂ¨-Ã°Ã¹Â²Â€hÃ—BÂ»TÂªqgz;Ã±Â¬Ã§MÂ½Â™Â«Ã¼Ã˜Â‹Â…KÂ”Â½ÂŒÃ»V|Âšq9Â¤OÂ>Ã‰\\tÂ³AÂ¬Â›Â¿Ã~fÂ­Ã¹\BÃµ7`iÂŒÃ¨tÂ»r.}J\\tVÂ±Â˜Â„Â¿Ã®JÃ–Â ÃœÃÃšÂ¬\\bHÃ–RÃ§Ã”Â„Â½TÂÃ ÂÂ ÂÂ¸$Ã·GÃÃ Â„Ã·Ã¯rÃ¶ÂÂ”Â3\\rÃ¥RÃ¶Â±0\\rKÂ³TÃ•RÂc@v3!BÃˆ_Â«`PP:Â¹j*GÂ¿Ã­Â’Â¬@ÃÃ·\\fÃµDrÂ‘Ã€Â…Ã–Ã°Â…Â¤Ã¢ÃŒ<ÃŸfÃ‘>Ã¡ÃÂ±Ã¾Ã˜$BÂ¡Ã„Â™Â€Ã¼Â¿ÃY_)Ã¹ÂºÂ‰CÃ—#Â¢ÃƒUgÂ±Ã /Â†DÂ°?Ãƒ@Ã¸Â‹Ã‘8ÃŒÃ´`ÂºÂ©Ã™Ã‰BÃªÃ¶ÂƒKÂ™~Ã¨Â²FÃ°Ã„Ã·KÂ¦*Â§Ã„XBrÂ›3Â¬Â„Ãˆ\\n++}ÂªD@d"oÂµÃƒÂ¥Gh#Â«6Â‰\\buSÃ‹Ã–Â‘ÃHÃ“wÃ’.@ÂÂ´Â—B\:Ã»Â¢Ã©7Ã¸cbZ?Ã¥Â’Ã c'ÂˆÃ¯hÂ¡/;ÃŒ`Ã#rÂÂÃ®Â°qÂ“Â¿qÂ ÂÃ¥Ã’ÂÃ¨Â¨rÂœÃœÂŠÃ¹\\rHÂº=GÃ«tÂ‹Â‹Â›rÂ­Â˜NQÂ¯M3ÃÃ›<*eÃ€:ÃŠÂ¦Â°C\\fÂ½ÃjÃš9}Â­MÃˆÂ³Ã°b)Â»@ÃšÂ»FiÃƒÂ·Ã°ÂÃ¸Â¸Â¸Ã•aÃµ+,Ã‘ÂÃ¾Ã‹lÂ¦zÃ¿Â€INÂ›Â¦Ã¸B"ÂªÂ›8ÂºÂ¦Â¢Ã•Ã¢Ã½Â¹Ã¶Â§K-ÂƒÃ˜_ÃšÃ‘F)ÂÂ‹h\\bÃ„Ã«2jÂ…Ã¢Â—Ã¿PÂ˜QÃ£\\f@Ã€Ã¿Ã‰Â‡<ZÂ‚Ã˜ÂXrÂ§ÂªkÂpuxÂƒÃœÂƒaÃ®\\t2Â“Ã¿bRÂˆ%BÃÃ…ÃÂ—Ã·Ã©kÃ¸Ãº3X|oEÃ™FÃ¬\\nÂ£Â·Â0Â¦Ã¨ttÃ»rÃ„Â›Ã¤M-ÂšÃ…o}Â¤ÂµÂ¿#9Ã®{-Â¨Â‰ÂœÃªÃ™@ZÃ»ÂDÃ‘/Ã•Ã¥Ã¶lÃ¾g\\bÂ½AÃ†Ã¨;Â¿&Â¯Â™Â¼8[HÃ«Ã¯xÃµÂ‰Â—Ã“_Ã¶Ã¥Â¥qdÃ•~jÃµ?Â¼-`GTÂš[\\ngÂÂ¢Ã¦Â¥*Ã‰Ã†Ã“4AD^Ã‡ÃŒj-GaÃ’ÂŸÂ…Â›OÃ…Â·\\nÂ™ÃŠÂ¥dVSÂ§Â£UÂÂ«Â†2dXÃˆÂ›IYÂ§Â–Ã¸Ã¼iÃ²Â§sÂ•ÂÃ·Ã§Ã yÂˆÂ’Â¹Â„&Â¾\\nÃvÂ°Â•#Ã·Ã·ÂÃ„Â”5'ZÃ¬.UÃº>\\bÃºÂ‹\\fVÂˆÃ±Â’Â¶ÂŸÃ­*+Â¨Â½Ã¶ÂÂ­Â®Â¯Ã¶LÃ®Âª4bZVÂ§Ã,Â¶6ÃªÂ‰QÃ•K`AÂ‚Ã»Â¶Â¡;ÃŸG0Â™,ÂƒOjÃ²(Â›OhÂ´Â³Ã¤gU|.Ã¿<Â´Ã @Ã GÂªÂ©Â¤PYÂ›Ã„Â®$XÂ3XÂ¼Â¿Ã¤eÃ±vÂ”ÂœW3Ã¤Ã‰Â«Ã™ÃÃ¶%rÃƒÂ‰ÃŠÂ°NÃeÂŸi5Â»SjJÂ•_Ã”ÂG*7Ã®Â¢FÃƒÂ¦ÃÃ“ÃºÃ‰Ã™Ã²Â©Ã©\\fÃ¦|kÃºt6*$Ã«TÃÃ™Ã–Â¬-CJ$Â»Ã²ÃºGÃ›Ã¦{Ã’ÃÂ²Â¾Â«Â†zÃÃ›Ã¢ÃˆtÃ¼^'uÂ¼!Ã«YtDÃ•Âµ/FÃ†Ã»luÂ‡`Ã“Ã°Â’Ã†Â†\\b:Â£B,Â“Â‘U\\bÂÃ”Ã¥Ã„Â“Â™Â´Â®Ã¬XÂŠÃƒÂfm7ÂÃ,Ã•Â¶<$Â³ÃHÂ¹Ã®Ã¤uÃ®Ã´Ã´cÂ¾`lÂ‡qh|TÂ©ÂªPÂˆÂ¦Â€Ã–|$Ã·Â§Â£Ã˜ÂKÂˆVwÂ¶66Ã•Â‡Â£rÃ ÂŸCÂ‹SuÂšÂÃ«Ã¸^Ã—Ã¨Ã“Ã£I\\rÃ³Â"Â‹ÃÃ•Â¡aÂ¢3qÂ/ÃŒÃ³\\fÂ‘Â­Ã¼VÃ­Ã‘{'Âœ1Â‚$Ã©Â®Ã®DÃRzÃ®6Ã•Ã‚Ã«Â‚Ã/?EÂµ)Â½Ã†SRÃ¦ÂºÃ*>Ã /Â¨c8Ã¹m\\fKÂ† Â·Ã’Â±ÂÃ“Â“Ã¨ÂšÂ¨XÂ©\\t7Âµ$ÃŒÃ\\fÂ¹Â¯Â£Ã\\t<ZÃˆuÃƒ6-Ã¶!Ã°Â¡!$F$Ã‚+Ã‘Â‡Ã­Â, GÂŠÂ™{Ã—oÂ›mÂ—B|ÃµÂ‰Â—{Yr5Â”`Ã‡Â¥3Ãœ0ÃˆÂÂ¡ÃºÃ°Ã¦Ã£qnÂ¶i6Ã¿Â”MÂ˜ÂƒÂ‰:Â³g[Â™\Ã™Â¢ie56\\n4ÃŸÂÃƒÃŸÂŒÂ´ÂÃœÂŒÃ»qÃŒ4q0>UÂ@SÃ–]n[ÂµG5ÃÂ®UÃœÃ¤b+Â¡Âœ'Ã”eÃ½4Ã¯Â­{I[Â¦UÂ¬LDÃŒÂ¹ÃƒÃ¸Â½Fs Ãˆ`Ã4Ã‘Ã‚  Ã¢Ã«VÃ«CÂ‘Â¿Ã‡eÃ£@ÃÂ™CGa;\\nÂ®! ){}Ã‰ÃŒÂ¸Â Â¬ÃŒ":Ã’8}Â‰Â´ÃÂ†"Ã™ÃµTEÃ£Ã…\ex4Ã¶Ã²Ã´Ã”Â´Ã’EZÃ¦Ã³:Ã›Â¶Ã“m2Ã•0Ã:Â™ÂƒÂµÂŒÃ¥Ã³Â£EÃ AyÂ¥8wÂ’Â¾Â”ÃµÃ¿ÂyÂ¹Â„<ÃŸEÃ¦elÃ Ã¦iÂ§Ãª~Ã£Ãµl}$wÂ§JÃƒÂ›*ÃOs\\b^ÃµÂŒÂ“Ã¤EvÂÂœÂ‹ÂºÃÂ¥%Â¼ÂœÂ™g|Ã³Ã…#Ã”Ã“Â§Ã™,Â¬pÂ5Â‚/Ã«\4 Â£\D8Â¥Â¾Â¹--uÂ´Ã§ÃŸÂ­ Â‹Ã…Â½Â¡9Âƒ,ÂXÃ¡S\,jÂ¯Â¿.Ã±HÃ¸Ã§Ã¤Â¥Â¹8ÂšIÃŒÂŸÃ¬Âˆk@Â‡Ã›}f~0ÂŸÂ¬,ÂœMÂƒ#Â¿DÃ¾[RÃ½ieÃ¯Â¼Â‹Ã‹)VÂ£ Ã‹WÂ„Â¯Â‹Ã­Ã¾RÂ )Ã¡Ã„dÂ·Â£yCÃ²Ã–ÃšUÃ“ÃµÃ‚B\\tÂsÂŠÃ³Â¡=hjÂ´2Ã„jÂ¶Ã†Â…Ã‹Ã¥Â´s7Ã®u_ÂƒÃ‘Â†Â«Â¼Â«Ã¹OÂnÃ¸Ãª1LÃ’Ã‚Ã…ÂŒ&0Â #uÂšÂºÃ´cÂ½-HÂ¢YÃÂ…qhÃ¹ÃÃ–Ã–`Â¤TMÃÂÂ²kÂ˜@wÂ”Ã›8Â‡Y(Â†Â•IÂÂ½Â—FÂÃavÂ‹j!=Â©"mÃ„Ve8`)Â¹1QÃ®\\tÂ¤7ÂºcrÂ›b VÂ³Â£Â”Ã½ÃŠ1Ã®Â“Ã¸lNÂ°Ã˜dÃœÃÂ„XÃ‘Â§ÂºgÂ—,ÂµÃ®yaÃ¨tigfÃªÃ¯n;Ã™Â¬' dÃ¯Â¥Â‚_?/Â’r9.Â¦Z)Ã¹Ãƒ{rÂ©Ã‰Ã(Ã¹Â¼2B'Â•Ã“f#ÂƒLITÃ¹LÂ¡ÂEÃG-Ã¢ÃƒcÂ¸2ÃºÂ–Â‡Â¢TÂB~Â”HBÂº$}Ã­jÂ´Â³*1ÂƒÂ¬\\rÃÃ‡n(ÃMiPÂ¨Â®d phÃšFÂ¿Â¸Ãº\\rVÃ‚Â-Â€8Â±l~J\\bÂ™Ã‹Â™Â¶ FÃµÃŒFÃ Ã³Ã²GÂ’{rÂªÃ¨Ã‹HÃŠÂ¨6 Ã–Â˜Ã Ã¯+B/Ã Â¶Â½0ÃmeÃ‹Â¿Y#:ÃÂ—S(Te:ZCxlÃ«oÃ’Ã±{Â±ÂºÃ·GÃ•[Â•ÂÂ¯<]HÃ¹N"Â¼N~7Ã¾Ã«Ã†VÃ¨lVÂ‹Ã©BÃ»\Â´Â—rÂgÂÂ¾ fÂ”^Ã¹Â«Y?Â™wz"ÃˆÂ¡Ã¬Ã%Ã“Ã–Â¸Â…bÃ¾Ã­Â¹Â•Â‡\Â¦ÂBÂ¾Â©\\t8ÂšÃ…ÂÂ»tÂ§Ã“RGÂ­fz\>Âƒp\\bÂšÃšeÃ¿Ã’qÂÂ‡*EÃ¤6Ã£Â³GÃÃ»ÃƒÃ¨pÂ¯Ã¨uVÂ¨\\tÂ¸qÂ£X%arÂ¥yUÃ©%zÃ¼UÃ¤Â¾%Â²`ÂÃ›Ã¨Â•Â¾Ã©Â²Â§Ã¤fÂ§Â¸Â¿I&Ã™1Ã†Ã¶\Â½ÂšÃ¸^QÃÃˆ*j0uÃƒÂ¥Ã¾]Â­Â‚81xÂ°-[] Ã¨yÃº6Ã·A\\t9ÃÃŒÃªÂ‚ÂÂ¬5ÃštI&Â€Â’Ã¹Ã…v+Ãª^Ã§Â¬Â®2Â­Ã³h?v5rÃŠÂÂ^<ÂŠÃÂ”KÃ™ÂœÃ–~Â³AÃ€$hÃ·ÂÂŒÂµViÃ’Ã˜Ã´uÂ¨&Â…ÃŸÂŠÃ¢ÃŸÃ¡Ã·Âˆ/Â›ÃˆÃº\\tÃ¾ÃÂº3ÃªÃÂ‹Ãˆ_Ã—Ã½Ã7Ã¢Ã“*LÃ¬p:Ã‰Â»1Ã®}cÃÃ¦Ã¤VÃÃ­Ã°Â†ÂÃ»WÃ $jRÃ™Â¦ÃÂŸÃœfÂ‚Â˜Â cÂˆÃ¡Â¥qÂ™F8Ã­ÂŒÂ…BÂš!Ã‡.LÂ¦}UidÃ¤? Â…Ã»Â‘]Â‡Ã¡Â¯Ã±Ã$t*)8Â³?GaXFÂŒ UÂœ\\nÃ¾Â UTÂÂ¨ÃÃƒF%ÂŒÃ”3GmÂ£Ã“Â"[Ã²x]u)Â·Â£ÃŒpÃ½Ã·Â§W}tÃ°Ã”I/Ã«Â¼/1ÃÂ³o7Ã·SCÃŒÃ…Â¿Â°Ã¥ÂÃºÂºWBÂ´pÂ‚lnSÃÂ¼?Â¹/qAÃ»Â‰Â¯Ã”Â‹1Â®Ã³"Â³8Â„ZaÂ§a7ÂÂÂ‹Ã•'Ã¬Â†jRÃ¾Ã¸=$Ã¿Âœ'{Ã†Â¸hÂ¯ÂŠaÂ¤2ok[qÂŠBÃ¬Ã D4fÃªÂ¢ FÂ¦eÃŸÃÂ„qÂ¿ZÃ\\rÃ®#ÃµÃ£%Ã‡Ã…x\Ã Â¡Â¦Ãª*Ã¥XÂ¢Ã‘Â’oÃ»&Â’Â±ÃŠÂpÂ·_[Ã¹Ã³Â›ÂÂ¡ÂÂ†:ÃºÃÂ‹V6Ã§Â³Ã‹ÂœPÃ; Ã½Â¨MÂ‹Â¡I:Ã\\bÂ¤KÃ‰Ã”Âš/jdÂ¡VÃ<Âƒ\\rÂ¹x_Ã‹Â´Ã©Â¾Ã”Âƒ&ÂšÂ›3FsÂ¨UÃ¢ÂºÂÂ¾GqÂšYÃÂvÂ™Â¡Ã£Ã°Ã Â=Ã‡\\ffÃ¿3&eÃ¶dÂ“Â£4Ã–UÃ¯Â°PÂ±Â«5Â§Â’u7Ã¦Ã8Â…Â®Ã«1\Â˜"|ÃµÂ‡Âœm#Â»AÂˆÂÃ°UÂ²Â›Ã,ÂÂ°Ã±}`ÃˆÃ˜AÃ®uÂ»fÃ¶Ã”Ã•Ã‡2Â¡Â§\Ã§NÃ¢b.Ã¯Ã§Â»Ã‡Â£Ã¹[\\nj35Ã¤Â¾\\rÂ²\\bÃ‘Ã“0Ã Â´tYSÂ¨qÂ¦ÂÃ°LÂŒÂ¸kÃŸ4Cu#\\fÃ…Ãˆ\Â”RÃ•Â®ÃHBÃ›Ã‰IÂ³(FÃ±ÂÂ„UzÂƒAÂ»Â²Ã›Â¤Ã¥ÂœÂ„ÂdÃ¼Â“Ã•/Ã–RÃ§Ã©$\\tÂ­Â°Â¯-ÂÂ¯|Ã»P6ÂÃ£lL>Â¤ÃšÂÂ¡).ÃµÃ”Ã·\\bÃ,D0ÂƒÃƒÂ¼aÂ›(Â—Ã½HÃ­QÃlZÂ§Â¹/1hÃ Ã£Ã§%Ã™(Â–KM^Â¯Ã¤ÂjÂ€Â§ÃƒyeÃ¾| Â“Â®Â­Ãœ}Â‹%Â¾Â„ÃCVÃ¾Ã©Ã¿Â¾\\nÂ‹^Â¥!wÂ€Â¬ÂÃ®^Â¢Â‚iÃ‘ÃŒbÂ¶cY[Ã¶Ã•Z5\\rÃŸÃ·C9Â–uÂ‹3Â%li4RÃ”fÂ´Â„Â†ÂµÃƒÃ£ÂµÂ³Ã¶q\Â±Â–Â§5Â¼Â’ÂŸÂŠK+Ã¥yv7Ã‡&Â¾=Â„ÃÂš&Â½ÂÃˆ\\f\\tÃNÃ®Ã‘Ã†fRÂ•Â˜4rÃ'96"XdÂ…ÂŸUÃ‡qÃ„Â¤>ÂœYÂ»Â˜ÃµÂ¹(\\nÂ¦Â™Ã ÂYÂŠÃ„utÃ¢Â€ÂƒYÃ»#Ã±Ã—Ã§hÃ·Ãš.JÂŒÃ›Â²VÂ©>*\Ã¯<Ã¶Ã¡Lc3>>Â§ÂPÂ˜\\fÂG=Ã¾GSE!bÂ´ÂºÂ¬ÃƒÂŠ\\r1Ã“vÂµ}Ã¶wÂ…5\\t ÂG\\t4Â6!Â„Ã•Â˜CÃ¹EÃ·`Ã¢|Â‹SÂ·UÃ…Ã¬])qÂ©Ã—?Ã©(rÂšFJÂ—ÂºÃƒÂ¡Â‘Â§Â™7*Ã­?e|BmÂ¥Â¢ÂW\\fÃ Â‹Ã¸ÃMA\\tPÂÂ‡5Ã¹,Â¸$wÂ‚pÂ Ã«SÃŒ\ ÂÃ~XÃŸÃÃÂ¨Ã†Ã¬Ã½Ã¼[>Â½TÃ¯Â¢zÃœuÂ‰=ÃµÂ§ÃÃŸg]Ãš;uÃ•SÂ—Â„\\n\\tÃ¿f+SÃ¾dÂ¹/FÂŒÃ±oÂ‚Ã¢zÂ‰ÂŒÂ®ÃÃ¶mHÃ¿Â£JÃ³oÂÂ¤WIebÂ†Â¥]xÃ‹9OÂºÃÃ¡Â£2\\tTÃ‡fÂ¥ÂÂµÂ£S&bÂÃ•4t =7DÃ½Â ÂÂŠliÃ¶ÃN-Ã³1aSLÃ™ÃŒÂˆÃ™Ã‰Ã»RÂ‰Ã³Â·Ã‘ÂµÃ¢jÃ°Ã½Â~qÃº&Â¦ Ã½\\fÃ³s\\bÃ£Ã¸\\rÂ¯M/Ã¢Â™8<Ã‘+ÃŸÂµC\\b0ÂzÂ¬Â­Ã‹aÂœ\\fÃ­|Â±Â¿ZCÂœAvÃ·Â«*2eÃ¢^Â‡Ã²K7Ã±<h\\tÂ¿Âª:9Ã–Â†Â¨Â¿mnÂ•WdÃ…ÃªfgÃ­Ã…EÃšÃºAÂºÃ¼FÃŒÂƒvÃƒ)ÃLluÂ…,TÂ­Ã²S\Â…vÂÂ‹Ãº=Â ÂŒÂ®Âµ8Ã‡Ã¡Ã„Ã–Ã•NFWÂŸ.\\bÃ³Â€Ã£Â¿Ã]>Ã“Ã¿yÃ´Ã¹Ã(FÂ‚?<Â™ÂŒzÃ…5Â´,iÂ¦Â—Â¬MX\\ns9dO<,|Â‘<ÃÃ‰GÃºVÃÃªÃ¶j:`ÂŸÂ¸6Ã³_8Ã¨SÃ¢u=#Ã¢):Ã“ÃÃ€ÂŒkÃ¨ÃªqÃ¢gÂ¹Ã¬Ã¯sEÃšB=ÃÃ„U(DSÂÃ¼Ã~Ã‚ÂšÂ \\nLVhÂ¶Â±aÂ’Ã™CÂ–Ã¨Â¶ÃÃ­Ã‰ÃÃ°ZÃŠÃ¥ÃŸ~ÃŒÂ‡Ã‡Â‚|ÂµqÃ•Ã¾>|Ã„ÂSÃšqÃ—aÂ¥Â€Â‘XÂ$Â¤ÂŸÃ‹Â¥Ã¦Ã¿Ã®\\t.ÃšAÂ£)@Â­Â‚Ã›gÃ©efÂ½Â‰}>GkÃ–Â©bÂŠ ~Ã™Ã¿tÂ­Â”Ã¾&Â¡|Â§Ã™Ã¢ÂŒÃ•Â¨Ã˜Ã«"e5Â Âœ(DÃšÂ Â­Â»ÃªÃ™M:Â¤Ã¤Ãª8ÂÃ#Â¤ÂœCrUÃ¦Ã¾ÂšjtÂª`iÃ¤v\\tÂ³cÂšÃ¬Â•{*Â¢Âº*Ã‘N@Ã—ÂœÂ§]ÂƒÃ’Ã±ÃªÃ¥Ã­\\fÂŸÂ†Â»fÃ¾J\\tÂ¨Ã„Â­ÂµÂÂ‚Ã²"Ã–Âºh;Ã®ÂœÃ›Ã­Ã™Ã¯dÃŒ#Â„Ã†Â²Âƒ[:ÂˆPZ\\t\\bÃ³vÃ”Ã±ÃÂ„Ã²ÃYjwÃ¥qÃ©ÂŸ5Â–nÃ­sÃœÃ¤Â¦Â‡Ã¥Ã¹Â‡Â¼Ã›sÃ‹Â¤Â¤ÃºCÃEÃ¥Â¥Â®Ã‰ÃªMÂ³Ã’\\tÃ¯Ã›Â¤d*ÂMÃ¹Â¤ÃŠÂ»4^Ã­Ã¿Ã¤Â’jÃ¨ÂÂ·Ã°:ÃƒP;ÂˆÃ‡~=Â¤|Ã·~+Ã¨)(Ã¦ÂœÃ˜Â©\#Ã Ã«Ã”Â®"Â\\tÃ‡Ã›Ã”#Â†i\\n!.>(hÃšÃ’Â‡NÃ®ÃÃ„Â‡NÃ‹.ÃºÃ¹`l!Ã†Â»<ÂºÂŸÂ‹7Ã‹ÃMtÂµdÂ¡Ã§'@TeÃÂ…UÃ–MÃ•?q,yÃ‡Ã¼@CÂ–^Â—Ã¹Ã¨\\tÂ®\\trÂ‹Â wÂ·Â|Â±Ã‡Â¡Ã°Â…Â©Sn7xYÃ¼Â“ÃŒÂABÂ”Ã†3.Â†\\rÂ‹RÃ°ÃÃ»,dÃšÃŠÂºPÂ¹vÃ˜Â¾iYÂ¼\\bÃ‚Ã‹Â™ukN~Ã½O4ÂšÂ’`ÂšÃ“%<Ã®Â¾Â¾Ã\\n]Â“\\tR:ÃŒ.7'ÃESÂ‹Ã’Â»ÃŸÃ¸[ÂšÂªÂÂ‚ÃªzÃ‡ÃˆT^Â§Â¾Ãƒ=QÃµÂ¦Ã¹xÃÂ‘Â±\\n8ÂµHÂ©ChÂºÂ½Ã´oÂªÃ„Ã„Â‚Â£Â¿PFmÃ¤iÂ¹qÂÃÂ®Â³/ÂŒÃ¿AÃ®aO\\fÃ‚|Â§Â¬Â­Â½rv@QÂ¨,Â²Â­xÃŸ>Â˜Â¿^ÃŒM Â‰tÂ®ÂÂ²QzÂ¹U Ã„ÃºÃ·Ã—UÂšÂ˜X8Â™ÃºÃ›Ã¸<';Â¼ssv%Â™'Ã›5Ã‡[\\tÃ—Â-(Ã¡Ã¦,Â¢Ã¶hÂ£MEÂ”!Â²Â±Ã˜'%}Âª$ÃÂ¦ÃšÂ‘Ã®Â¼)\\b@BnÃªÃ©Â½ÂªÂÃBa\\rÃ¶ÃˆÂ©Ã¹Â†Ã›ÃšÂ°k\\nÂ­ÃªWÃ§Â€ÃÃ‡Ã–Â’Â—Ã€TgTGÂÃ¡Ã¼e#$Ã¢ÃÂ¤Ã¯ÂBÂ¿Ã‘Â &ÃCÂ‹Ã·Ã¸m&Â¹Â¬Â©Â°Ã‚)Ã¥ÃƒÃ–PÂŸÃ£Ã²-ÃÂ¾Âµ_Ã‚''@ÂÃšÃ©zÂ™Ã£pÂ±ÃcWCÂ‹Ã’Ã€ Ã½}Ã½Ã®Â²Âˆ.l ÃšÂ·2ÃÃšwÃ¬[Â¸uFÂ“Ã™ Ã¼AÂ€Ã‰QÂ•Âª!Â•Ã¤ÃµÃ·qBÃ©$Â’\\nÃ¸Ã§TÃºÂ©lÃ³Â™Âµ/#eÂ‹Â…[Â®Â‹Ã”pÃ±nÂ®y(ÂÃ£Ã·&2CÂ£hÂ¬Ã£-Ã— Â¥uÃºÂ“Ã¥Â…\\f^Ã—ÃlÂ¶l\\bÂ€ÂºÃ’Â”\\bÃŒxÂ»Ã¶nO9Ã¸?Â€]ÂƒMyCÂ£Ã»)]Ã¨Â°Ã¤O\\rx*P'Â¬^ÂÂ®P ÂºÃ¢ÂÂ²Âˆ&TÂ³U?Ã€Ã…@Y;%Â»R>ÃµÂœÃªJÃ°bÃš!ÃNÃ†Ã¤Â§ÂŸ}Ã–ÃµÃ½Ã&Ã‹DÂ—Ã²ZÂN{<]wÃ‰Â¶ÃÂºÂ—|Ã Ã¥Ã lPYVÂ;RÃ„Ã”ÂÃ¿Â²)_i+ÂÂÃ¼/PÂ€ÃŠÂ¼m\\neÂ°Ã²Ã€PÃ¸Â¯Ã†rÃLÃ©pÃ­ÃƒÃ¦Â¿Âd>Ã²ÃŠlÃ“ M&Â›,AÂ‰ÃÃ‘Ã·\\tÃœONÂ¼Ã²jÃÂ¢zÂ¸ÂŸ~4Â¹ÃšJwÂ‰Â¿ÂºÃ¶zÃµÂ³)`Ã¸\\tÂ›;ÃŸ{dÃ€Â˜Â¼jÂ“sÃ…\Â’RÃNÃ˜ÂÃ¢hÃÃ‰Â½Â®Â¸ÃŒNÃ“Â Ã¯]Â¢tÃ—Ã—MlÃ€Ã¶Ã³Â¾sttÂ¤Â±Â¿&Â¿Â¿B\\rÃ•Ã’qY&#Ã‰Â‘_Ã«Â€IIDÃŸ27HÃˆÃœ*W\n;ÂÃ¥qÃ“Ã«Â¦A%Ã½ÂƒÃ³EHKÃ·mrÃ±Ãµ 63Â¡\\nGÃŸbÂ¥Ã¦PÂ‡Â‚Â¤ÂÃ6ÂšÂŠkÃ§~Â©Ã¿<ÃªÃ¸a\\nÂº_Â°YmÂ¦Â¯Ã•ÂFxÃQÂ€Ã‘QkÃ§}v<3Ã®DÃ¢L#Ã£Ã¡Â˜Ã¡QÃ¾Â¦'Â‰Ã@Ã…Â£&ÃÃ‘Ã¨|ÃÃ½ÃÂ¨Ã»kÃ©Â®Ã½Ã„\\rÂ°ÂÃ¨LÂŸLÂ·J0Ã›ÃK(R\Ã´Âƒ^ÂpÂœaÃ¬eJÃ¼'Ãµ!j=TRV!{ÃÂ0Ã‚Ã“$Â¦ÃŸÂ¾ÂnÂ«)Â‡Â®[.fÂ»!ÂªÃƒÃÂ¯ÃÂ¦Ã®C9}Â’Â´!EÂX7Â·'Â™o4Â‚ÃÂ’rnÂoÃÂ¤5wbBÃ™Â„ 3Ã±ÃªFÃ´b{Â±ÃºÃ’UÃœKÃ‹Â¤Ã´ ÃƒÂ†+Ã¦Ã¡Ã«Ã¬Ã‡Â‰Ãœ Ã£Â½zÂ”vSÂ’E|\\rpwÂ¤Â’Ãˆ\\tÃ´WÂ­>Ã¦MÂš!QC[ÂŠ\\nÃ†[\\r$|Â‡Ã€Â’%Ã˜FfÃ’%NÂ¬Â¬Ã¬Ã°0Â­Â«hÃ¯Â…Â„VÃ™mÃ¹Ã›p|Âœ;Â™Â£\\tÃ‡Ã¾Ã´.(Â›Â·}Â’@Âex\\rÃºÂ Ã©SÃ™{-Â½Â¿Ã‹WvNÃµCÃ²9Â¥Ã„Â‹Ã«ÂŠoO`Ã”Ã¯)\\b\Â]ÃGÂ‚Ã®ÃÃ§Ã†'ÂŠm]Â—Ã´Ã°Ã‰Ã£Â­4q7Â´rÃ´lo:VÂƒÂ´I6ÃºÂšÃ”hÃ‘*B-Â¿Ã‘|g Â‰Â“Â”Gz\Ã£fÃ¢Â§Â©*+s!ÃºÂ¹Ã„/Â¤9Ã¦Â†Ã£PitÃ²ÃŸÂÃ¿]Ã¼Â¿ÂŸÃˆÂ§ÂšKÂ¨PlÃÂ¤Â«bÃ‚DÂ˜/Â­Â¦VRzÂ¹Ã®Â»Ã§Ã¹Ã©Â–\\f:Â‰|Â¾Â•PÂ¯Â¸\\bsÂ§\\fÂ‡Â¤>Ã«Â½\\b}Â£cAÂ‘Ã”Â‘BÃ£Â‰S+Â‡Ã’BzÂ¼Â¼ jÂ²Â°Ã—ÂŒ&&SMÂ·Â”<rÃ¯Ã¹Â…hÃ–LÃ‹iVMÃ”Â¬Â®ÂˆÂ´Â³:Ã©Â‚Â±XzÃ¹9Â²>Ã’Ã‰Z7Ã¥:Â€;thÂÂ™)Â€\\rÃµqÂÂ˜ÂoÃÃ¤Â¶Ã‡Ã«mÂÂÂ‚C ÂÂ£Â¢Ã¤D``Ã”Ã˜_ÃƒrÃšKÂ²t%Ã©ÂŒÃ¹Â¢GÂ¸ÂªÂÃ™bÃ¨LÃxÃ”VÃƒbÃ©HÂ©Â†Â¨GWXVÃÃ®=Ã–ÃµPMÃ¿bpVFj/Â«Â´ÂA}Â·ÃªÂ¾Ã©[ÂªÂ‰Ã¯\QÃ’Ã©RoÂ­ÂˆÂ‹P:ÂÂ¡XÃÃ‘:Ã³Â¸Ã¸FÃšIZpÂ…Â«dÂ¼)ÃˆÂ›Ã#Ã¼pÂ»Â©ÂœÃ¦Ã•ÂÃ´Â¶F,Ã¯Â„ÂÂšÃ’ÂUÃ˜Â§Âˆ5ÃœÂ”VÃhÂºÃ»uÂ“38Â³Â«%YK\\t@Â®Ã¸ÃºÃ£dÂ·Ã«Â¾yÂ¢Â®ZÂ‹Ã´b/Â‹ÂŸÃª4Ã·ÃŠÃ…*Â¦Â©Âª6Â£ Â·Â£)Ã²ÃˆYr(Ãª}$rÂ‚Ã‘"<mÂ¿$ÂˆÃ,Â½QÂÃœÃ¼_qÃ„RÂ®nJÃ‰Â’ÃÃ¼RÃ®0Ã¬Â®QÂ’\\nÃiÃšÂ­Â¿ZyÃ¶)Ã·wÃ›Ã³eÂ¤jÃÃ¤Ã³Ã´(ÃÂÂšÃ¤ÃªaÃ°>Â†c0Â¾TeÂ€Â†ÂŠÂšaÂ§kÃ™\\fÃ©Â¨o$Ãµ1Ãœ.Â£Ã‹Â€6ÂŒÂ¼Ã½ Â‚Â§ÂˆÃ€8Â‰\\nLeeÃ Â¢ÃƒÃ³Â†"Ã Ã·1Ã£,Â†ÃŠ?HÂ®Â›Â¦Qys'Ã§9"Â´Ã°5Â—?Â³Ã‘Â—ÃºTÂ­NÃ£Ã²Ã¡ÂœÃ¤qÂ¦`ÂˆÂ“8Â»|2ÂƒEKb%-Â–ÂŒÃ¸1ÃˆÃ¦Ã—Ã³Â—ÂªÂ¼ÂµRÂ”Â“Â•Â“Ãº\\fÃP\\fÃ³HAÂ—NÂ§8Ã™?V):iiYÂ¶tÂˆTÂ•Ã›gÃ’"Ã¬Ã§@PÃÂ–Â†Ã¾Ã’Â§(fÂi5Â¬Â¬ShÃ•gÂ©Ã HÃ\\f$.Â€)Ã¾Ã‘M\\rOÃ©4jH$ÃºÃ½:Ã›'Ã¹\\tNÃ¡Ã·>Â­ÃªÂ-Âµ ÃŠH[Â»ZDÂƒÃºÂ«Â´|:BÃ‹K$ÂŒÂ¤Â´DÃ¾xÂ¥#8Ã©Ã¬Â¾(2ÃŠÂªPÃ’ÂÃ”Â¹Ã‚BÂ»zÂbÃ„ygASÃª-Â«Â™WhÃ }Ã½ÃÃ¾Â¸DÂ‰ÃšÂÃ¨Â¸Ã¿ÂÂ§]CMÃÃ¸Â†Â¢ÃŸCÂºÃ„Ã—:Â¡ _ÃW>Â²ÃÃ†Ur\\fÂ‡ÂƒÃƒÂ¶lÂ‘6Â²)Z$`LjÃ¾ÃŸÂ´Â›Â§lÃ¿?JÂ¦,Â¼Â– ÃÂ¿Ã¨Â‹3*\IYÃ—\Â¼ÂÂ ÂÂ¾^Â¿\ÃdÂxÃ„ÂˆÂ…Ã‘Ã¾Ã”@Â•Ã˜fFÂ¸,?Ã¯Ã•+]\\r Ãª~Â‹F8Ã´Ãš[ÂÂµÃªÃ§Ã©!`Ã¶^ ÃƒÃ—ÃµÂ¤rÂ©:Ã 9ÃˆÃ©Ã¤Â‰Â¢ebÃœÂ„Ã³ÂuÂ‘cÃ•Â˜}Ã¢Â’Â“Ã¥Â¸Â¥5Â›ÃŒÂ°eEÃ„@[Ã€Q~4>Ã†Â¿Ã»rÂ*'ÃÂ¦$<ÂxlÃ³Â•Â½&nÃ¯Ã¹OÃ ÃÃ’DNÃ¢.Â“qdPÂ„1Ã¯Â†Ã…2Â›dÃˆÂˆ")k \\b+Â¢Ãƒ{qÂ±Â©ÂfÂœ9_NÃ¦ÃÃ‚Â…Â²\lÂˆfÂ—&ÂšÃ›"Ã®gÂ¤D Â¥Â„Ã¬'5Â£nÂ‚Â´Â’Âµ O@y{,Ã’Â‰tGÃ£bQ-Ã‰Ã o%ÂªÃ½ÃµÂ®ÂT\\bÃ‘4Ã§Ã¦Ã“Ã¦CDÂ¯tÃ½Ã«wBP)Â€ÂšPtÂµÃ£ÂÂ˜Ã™Â½Ua>qZ\\r EÂ•Â±Ã¦Ã†Â¬D<NÂªÂ¡^@Ã›iÂ¹|Ã¡Â€_Ã¤jZÂƒÂ‚ÃƒÃ”ÂŸ\\bÂ¢#Ã¡.c\\bXGÃOÃ„Â ÃÂ’k8ÃªÃ¯Â™eÂ“ÃÂ“Â²2rdOZÂµÃ²Â²Ã¼Â‹Â”:Ã¬Â®Ã…=Â´Ã‚Ã¬Ã¦Ã‰Ã…Â¼Â’ÃˆÂ“Â·!Ãµ\\f)H?Ã¹ÃœÂ‘\\rÃ¦Â‘ Ã²ÃµÃŠÂ•Â‚lMÃ“f\\f-Ã›0ÃÃ7/Â­\\tr0ÂŸÃt!:Â¬Ã½Ã­n#Ã BtÂÃ³ÃºÂ‡Ã”LgxPÂ³ÃÃ­Ã¿^Ã¯ÂµÂÃ¡gÃ¿Â¬ÂŠyÃ¥Â¦/BtÃ†ÂŸÃ¦jÃ’Ã†Ã’Ã·kFÂ„Ã—eK'S{Ã«Ã¢Â•4ÃS/Â·Â»ZX#Â°Ã£ltÂ¯-0\\bÂ…Ã¦Â´sJ@Ã¯NÃšKO\\tÂ¢vÃ·Ã£Ã¤uÂ«aykÃ£ÂÂ¼Â™ÃšEÃ´ÂhWÃÃ¤IÃ±Ã¥'8TD\\b(nÃ€Â¦ÃƒÂ·Â‰#(Ã·3Â˜Â§ÂŸFLÃÃ§Â“ÃŸÃ‡_Â¨Â›Â˜Ã¶K^Â’6Â‚RsdÃ›Â˜Ã›Â€7Ã£ÂœÃ¹Â¶ÃˆÃº0Â¡Ã&Ã‹9nÂ‚Ã§Ã”Ã„ÂºuÂ‹Â²4UÃÃ¾uÂ¼ÂÂq\ÂšÂ¶Â‚'Ã¿Â¬Ã‡ÂµTÂŒÃ²$ÃºÂ¨ÃÂ©#Â‹$Ã¥sÃŸf/ÂŒÃ¦r\\fÃŠÃÂ¢j ÂÃ«ÃÂ‘bÂ¿]Ã¦Ã—eÂˆÃŸÂ‹Âœ/ÃƒÂ¤@Ã‡`Ã‡.ÂÂ—Â™WÂ´Â¹&Â¡ÃÃ¾Â©SrÂÃ¥Â°"Ã uÃ”0jDn$Â¨O_}Ã¥jÃ²T4lÃ‚Ã…H{\Ã²Ã´ Ã±Â’Ã®Ã—nÂŒÂ–ÂÂ™ÃŸÂ§ÃÂƒÂ›CkÃ€Ã½Ãš]Ã£\Ã™.ÃÂ¨Â€+Â•Ã‡Â‹Ã¨Ã‰\\fÂ·Âº}Ã¬aÂ©ÂÃ·0Ã»Â¹yÂƒÃ•]ÃÂ¦MÂ”8Â¹Ã•ÂˆÃš'ÃÃ‹Ã‰Â¬Ã°XÃÂªÂ¹Â’Ã±Â®Ã…Â“Â˜ JÃ¼#Ã¬Â±._'bÂ¼Ã‚ Ã­!Â£uIÂ¿[0*Â¤b8ÃŒÂ”YRl!BÂ˜ÂKÃ¨Ã¹Â“Â•Ã”Ã¹ÂœÂ E cÃ¹ÃIeÃ‚ÃƒÂ¸Â°qaÂ¼GÃ·Ã™ÂÂ£NÃ†|ÂœÂ¹PNRÃ¡ÃºÂ¬Ã7Â´Â¯L)Â°ObÃ¬gÂ›Â˜Â¾=?Â¾Ã—xÂ…Â‰Â TÂ¨ÃŒ>\\tÂ‚Â‰Â¢D,SÂlZd"Â‚Ã§ÃªÃ‰ÃŸÃ¤\\tÂ–Âª{ÃÃ®Â˜'Â¯ÃvÂ¼Â©ÂÂ‚Ã¤Ã­Â£Â™Ã¶\\tÃšZÃ¤Ã˜ÂºD\\tSÂ¤J\\nÃ¦Ã•ÂºÃ£pÃ˜Â¨ÂÂÃ™,Ã‘HÂ³Ã”'Ã‘ÃˆÃ–XÂ‘ÃÃ§ÃÃ“Ã¢]GÃŒ36ÃˆÂ‰5evÂªÂ£Ã“_.Âš\\bÂ»Â‰6ÂƒÂ§Z Ã›Â‚AÃ‚Â˜Â™ÃšTÂ¸YG0Ã–Â„Ã”GBsÂÃœÂ¬Mt1Ã®Ã…YÃ’nfÃ¿Ã…Ã¥!KÃ¹1ÃœÂ£+Â¨0>Ã¸yÂ™kÂ)ÂÂ°Â¦Ã“ZÂºÃ¾Â¹Â—Â‹a@ÂˆÃf\\bÃ¾Ã½`\\r-Â‚^aÂ¾Â°pÂ‘h&ÂŠÃœYÂ‘ÃÃÃ£%Â€MrÂ¤Ã„KÃ¦Â¤VÂ¼Ãƒ#ÃÃ±KZoXnÃ³jÃÃÃ‰GÃ‘0Ã®ÃƒÃ¡9Ã¼Ã¬Â…ÂµÂ•cMuÂÃ”8ÃÂšÂƒÃgÂªÂ—Ã‘.ÃÃ§!GÃœKÂ¥iSÃ¾Â–FÂ—Ã¿Ã°Ã½ÃœÂÂ‚H]ÂŸÃŠ;oÃ€ÂÃ Ã»LÃ¥Â«,Ã„Ã¤2~\\fEÃ™Â«Â¼7\\bg\IÃÃ\\f Ã¢ tJ8dÃƒÂ©Ã„Â†HÂ»Â¨)cÃ\\tÂŒ-Â‚Â«JWÃ£Â³Ã•Ã»ÃŸ&Ã€cCÃ’Â…_LÃ°Â“,Ã¥Â Ã–(Â¬Â¥Ã¼Â¾Ã±y9|Ã„7Âº$ÃÂ¹oÂ¹Ã¤Ã“ÃƒÃ—3ÂUÃ @:'l1<ÃªzÂˆÂ°|Ã—eÃ’Â;Â¬ÂÃ¬j+E6Ã£)Ã¢]Ã»&-Ã¶iÃ;Â¿q\\reTÃ¥=ÂºÂ Â¼Â¹Â°>(jÃ­Â Ã·6Â£w\\fÂ˜ÂÂ—Ã½Â–Ã­ÂµÃ Ã°Ã¿JTÃƒÂ‰\\t$Â‰Â½Ã·Â°y\\n)8(Ã‹4Ã¼Ã¹OLÂ‘\\bÂ—Â Ã·ÂYÃ¨Â›Ã¿HÂ¾Ã‹ÂœÂ–iÃ¨ÃœÂ£Ã¢cÃ¼zÂµÃ›Â¬PaÃ©Â½sÃˆ_aV*Ã©|Ã¼Ã“Â°TÂ³uÂ hÃœVvÂ¼FÃ4I\\fo\\tÃ¯FÂŒÂ¿pÂ™Ã™Ã¦tÂoÃ“ÃÃ°Ã¸cÂ…Â´Â¸Ã³n`Ã)Â­:SÃ‹\\fÃŒK;ÃÂƒUÂ½Â¢mÂ¢UlÂ›QÂ•Ã©ÃŠÂ„wÂ˜pÂ£rÃµ@Â²Â¶:Ã„Â¬hHsÃ’Â¾ÃºÃSÂ  Ã¨{ÃŠeÂ¡\\nlFÃ…Ã–^C$%Ã¨!Â–Ã™mÂ—Â›Ã‰HÂiÃ…%Ã—XÃ€ÂÂ£Ã‘Ã›ÂªÂŠÃ¾)Â¼=Â“"Ã—q*\\fJ6Â†+Ã›ÂˆÃ„z{Â¸Â[Â™O%ÂºÂ‘FÂ« }ÂJÂ 6Â†Ã½Â¦ÃŒÃŠ=Â³Ã’I#ÂŠÃŠ"$HÂª\\nÃŒÂ’Â‡Â®g3; Â­o]Â¦Â“@ Ã¬Ã‡Â–Ã«MÂ°Â¾Â¸Ã¿lÃ†c#2{Â€Ã­bÂ†C1-ÃCÃ°Â³ftFÃ¥"3f7AÃ©AVÃ”Ã˜ÃµÃÃ‚ÂxÂ¨ÂN\\bÃ®ÂµmÂ… EÃ«\\bq\\tÃ˜Â©Â‹ÃƒKÃ¬vÃ¨Â®oÂ…"Â¸@|Ã¾6YihÃµÃ‘ÂŠÃ’ÂÃº'WÂŠÃ‰Ã‹Ã•Ã´Â£zCAÃ†Ã€^YÂ·OÃ¹Ã·Â«Ã…Ã†Â=Ã‚Ã¦Â»SkÂ‹TÃ0Â­Â°Â·Â“Â“Ã´7Ã²rÂ…Ã‚Â¬Ã¥Â¿Â­vÂ½Â˜Â Â°Ã¸ÂŸÃ¦fuÂ»Â‘ÃƒhÂŒÃÂ»UÃÂ¸Ã˜Ã²Ã¸Ã“!7Â“Ã˜Ã”Â§Y=Â§\lÃ¶>ÃªÂ¤Â™Ã‡Â¥mÂ‹a\\f\\txÂ©}uÂ¬0^1Ã•)Ã›4Â ,Â“ÃµÃ¼Ã‘hÂ¨Ã¤"6ÃÂ¯Ã½Ã³ÃªTÃ—Ã²Ã¦Â”\\nÂ¯Ã¶\\fÃ«Ã‚H2Ã¹y5=Ã‚Â„nÂ¯fÂµÂ½Ã…LzÃ´ÃƒÂ£WÃ•Ã–Â™Â©Ã·q"}Ã‘Ã¿pmjÂ®Â‡Â­Ã¦uÂ·FÃºÃ§ FWÃ{Â‹Ã»ÂÂ…Â·Â–XÂÃ®Â·Â·Â]Â¥ÃÃ¦WÃ›eÂ‘Ã¿Â§Â’KpNÂÂ±4TÃ‹Ã”+*Ã§Ã„Ã¨Â—Â¶Â¬Â³mÂ²Â—Â¿Ã£ÃÂ•Â¼8Â rÃ¼3Â‰Â‹Ã¥Ã¸\\tÂ”Â¡Â†Ã‹IÃ¹wÃšÂ˜Ã°Â†ÂnÃ®Ã‰\\fS;VÂœÃ¤5ÃšÂÃ™$[{Ã¨Ã›Â¾VÃÃƒÂÂ·ÃÂ±wDÃ—Ã‹Â·YÃ™Ã~wÃÃ€Ã­+q|Âª?ebÃƒÂ‰ÃªÂ¬ÃµÂ²Ã²chÂÃ³ÃµÃ²\\fÃ¡Â—R(%&\\tcÂ…<Ã€\\nÂ3Ã˜Â›Ã‹Ã§ZÃ’Ã¾NÂ¹YÂ¥ÂˆÃÂ”Ã¼eÂ³Â…=Ã«Ã°oÃ£ÃºÃ™uyÂ†Â©N<>Â›Â‚pZÂ¯(Ã”Ã·Ã¼/nJÂ…ÂµÃ¢cÃ°VfhÃƒÂŒqIj>\\rSV\\tÃ‚ÃµÂ‚Ã—t^Â§Â…#Ã†wfÂŸ.EIÃŸÃ„Ã¿Â‚Ã²fÂ±yÂ†5Ã†Â‚&sÃ³UsÂ¨ÃºÃ‚cnÃ¹Ã²Ã’JÂ¾Ã¥|j.^Â‘[Â?NÂ¯ÂœÂ«U\\rÃ¼Ã¥ÃƒÂ‡Ã•E\ÃÃƒÂ©ÃŸGDuÃ·Ã°Â‘\\tÂ-VÂ¼Â™Â‡xÂ›Ã•Â˜Â³ÃÃ±Âœ%ÃÃ‘Â›ÂºÃº]Ã…Ã¢Ã‘\\n}ÂÃ ÃŠ$PÂ’Â“gÃ¹$@Ã²Ã«@Â²ÂÃ5m\wS&V-Â“Ã+Â‹Â¸VDÂ¬\\nIÂ†Â¹[Â›fÂ¤\\fÃ¹Â•3ÂÂˆÃ¬Â„0\\rÃµÃ´%Â¦Ã®ÂªcL!Â­\\bÃ«ÂÂ­Â…Ã¬9Ã›jyÂ™lÂ»ÃÃ†Ã°Ã=Ã¨a\\tÃ§=i'Ã‚Ã'RÂ‹ÂªÂ¹3@Ã´cÃ¾]Â¼3jÃ”Â«Ã/bL8gÂ¿Â†Â…Ã¯7Â³GÂºÃ¬Â -ÃºÃ³IÃ¨$Ã¼ZÂ’Ã°ÂÃGÂ´qÃbÃ§Ã‚ÂšÃ¾Â“\\b\+NÃ²Â›Ã­Â€Â†Ã›6}Ã”@DÃ„tÃµMÂpÂºkÂ“ÃÃŒÂ¨ÂÂµÂÂ¿t2"Kwm[HÃ¬Ã´Ã‘ÃŸa>fAy/\\bÂ‡oÃ Ã³Â¸Â”bÂ­5\\bÂ±|:Â¡DÂ­[Â«Â—Ã¢Â‹Ã„Â»Ã³ÂŸ5Ã‹2Â¢Â¦]Ã‹)9Ã—Ã’Ã½D^ÂšÂªbÃ¶Ã¸^KÂHÂ®V49Â“Â«x(Ã³Â±ÃÃ³[Â¾ÃªoÃ²Â™Â¾Â­Â¯HÃ©AjÃ„Â—<Ã‚Ã¢{JÃ¿Ã´Ã¼+Âˆ:-!\tÃ±Â­r\\n9Ã†Ârz"(Ã‡ÂŠÃÃ‡@kFÃ®Ã­vÂ³&C@Ã´Ã”8Â¬Ã’Â¸fÃœÂ¾Â‰ÂÂ™\Ã±Â¸gÂ¡Â¯Ã’\\nÃ‘ÂÂ’$8Ã‡Â”Â³ÂÃ¦m/Â—Ã‘Â§rÂ¾?Ã”=v;Â²zk0Â«gÃÃƒKHJUÃ»Ã•Ã¾mÂ­3Â»Â–;Â;ÃœÃ„ÂÂ²}Ã±^EÂ´lÃºÃ¹Â¯Ã´Ã¶Â–Ã–ÃŸ/Ã”ÂˆÂ³zB%4JÃglÃŸAÃ¢Â¬Ã¬Ã–zÂŒÂŠÃºÂŠ<Â R3SÃ¶Â‰ 5ÂˆÂ®Â”Ã¨H%ÂÂ¾ÂÃ¯ÃZÃ¶lÃ•Ã³Ã®Ã™Â‚ÃŸÂ•x:Â¬ÃŸÃ”Ã™ÂÂ»Ã¯Ã£SÃ¦Ãºp\\rÃÂ•!ÂJF) Ã¥Â¦Ã–Â†CpÃ¦Ãº Ã™$ÃšÂšÃ¦Â–9k\\bLÃšXÃˆÂŠÂ‰ÂµÂ– :MÂºÃ•}Âƒ~Ã…Â®Â·ÂœÂ™Â¦1VÃ±\\nÃ+Ã½Â¶CÃ­ÃœÃ…Ã¶Â†<5Ã¶NÂ°Ã‚@XÃ…Ã—hÂ'Ã¦Ã¦Ã¶"ÂµÂŠÂ‚oÃ™Ã©Â±Ã¡xÂ¢84$fÂ«/EÃÃ·vÂ²ÃÂ‰^Â¿Ã‹]Â–{Ã`Â¤Â–Ã±Â«Ã‘`Ã¾Â¼kFb3rÃµSÃƒhÂ¸Â+G2YÂ†ÂŠÂ—r=Â¾fjÃŒÃ­[YP,LÂ˜ÂªÂ¸Â¢ \\nÂŒÃ±Â¯Ã¿<Â™Â¸lÂ‹ÂÂšÂ˜ÂÂ” ÂIÂ-ÂªÃµÃšÃ•Ã–ÃˆÃ¢ÂÃ ÃŒÂš-:ÂÃ‹fÃ¶Ã¢Â™LmÃ²Ã”Ã¤Ã¥/Ã—ÂÂ‰kÂ‚Â²\\tÂ¯v@Ã«,Ã¿Â”ÂUÃ°ÂµÃ¿Ã·S~Ã¹Ã¿Â¦Â”.Â¤ÂÂ#?ÃAÂ’.qÃ¶Ã¨ÃŠÃ–EO(,Â¿nÂ˜-Ã›Ãƒ\\fÃªÃª=lÃ„eJFÃ¥eÂ¼ty6EÂ´jÃ‰8wÂ¦"ÃÂ³ÂªÂ˜Ã¶Â­?kÃªÃ–ÂŸÂ¡}MÂPÂ¨Â›Ã¡b$Ã“m7pÃÃ€ÃÃ²Â–ÃÂÂ›Ã“0Ã¥Â«Â·,gt5Â§Ã¹Â–Â™&Ã¸Ã™UvÃŠ;Ã©ÂÃ¤ÃÃ…ÂœÂÃ¥Â†cÂ¿Ã¹ÃšBhFÃ‘>sxÂ­-ÃŸ)Ã¬6Â¶Â»Ã†Â¥ÂÃ‹Ã’Â–Ã”gÃ€Ã‹Â§ÃÃ¾QÃ´Â˜6ÃƒÃƒÃ’ÂhAopb\\rgÂ³Â†ÂŠ Ã”Ã¿/dÂ¡ Ã‰Ã¤Ã¡J5$Â¦'0Ã‰Ã¶FdÃ·6zÃšÂÂÃQÃ³DgÂŠ=Â¨wÃ˜ÂµÃœÃ·~)Â³zÂ²ÃºdÃ“hdÂÃ¶#Â®o\\tÂ¡Â‚ÂƒÃ¨O,`bqo\\tÃÂ¤Â³Â¥Xpe<Ã¬.Ã¢]0Â…ÃÃ¯Âºw1Â°-Â¢,Ã™ABÃ­Â”Â¿4Ãµ zÂ¼yBSÂ‰Â…IÂ€Â½Â«Ã“Â±Ã™CÃ’cÃ¿.J\Ã¡Â–Ã¹vÂE.Ã³J$6XÂ¾;@ÂŒ]\\fÃ‘\\f-IÃ£ÃœÃ¸GÃ¤ÃŠÂ»Â„ÂšÂ£Ã•Â†ÂÂ™Ã¯3ÂµÃ¥;<Âµ@/Â¯Â¾Ã•Q$Ã…Ã |Ã¹{Ã…UIPÂ•ÂªÃ‰Â°nÂ‚Ã—{ÂŒÃ½FÂš\\fÂ·?{Â¾W_0umÃ‰4;ÂŠ<!p%Â–*<Â¼G+ÂD#BÃ˜Â¬tÃ¬+!Ãœ+IAÃ¶Â©ÃœÂ| Ã¶ÂµÃ¹GSÂœÃ‡Â›NÃÃÂ‰UÂ¼Ã¿Â‡hÃºÂ¸(Â´Â¶ZÃ•Â§Ã»QÃlÃŸUÂ€Ã¶Â©3ÂºÃ­Ã€#Ã¾Â›Â„seÃ‚Â—Ã…\\fÂµÃ·Ã–ÃªÃŠ4Ã‚Ã°Âº\\bÃ—XFUÃ‹Â–ÂœKoÃ–FJÃ¨Â·ÂŸoAÃ¿w[Â„Ã¿Ã”Ã‰Ã¤4Â„NÂ“ÃÂ¹`{Â“ÃˆGÂ†ÂŠÂ“Ã–Ã•ÃÃ¿ÂÃ¦Â˜Ã yÃ—Â©Ã RÂ¸I \\tÂ¶Â«Â™Ã°Â’hhÃ•ÂƒÃ…-:'
    //   69: dup
    //   70: astore_2
    //   71: invokevirtual length : ()I
    //   74: istore #4
    //   76: sipush #32767
    //   79: istore_1
    //   80: iconst_m1
    //   81: istore_0
    //   82: bipush #80
    //   84: iinc #0, 1
    //   87: aload_2
    //   88: iload_0
    //   89: dup
    //   90: iload_1
    //   91: iadd
    //   92: invokevirtual substring : (II)Ljava/lang/String;
    //   95: iconst_0
    //   96: goto -> 201
    //   99: aload #5
    //   101: swap
    //   102: iload_3
    //   103: iinc #3, 1
    //   106: swap
    //   107: aastore
    //   108: iload_0
    //   109: iload_1
    //   110: iadd
    //   111: dup
    //   112: istore_0
    //   113: iload #4
    //   115: if_icmpge -> 127
    //   118: aload_2
    //   119: iload_0
    //   120: invokevirtual charAt : (I)C
    //   123: istore_1
    //   124: goto -> 82
    //   127: ldc 'KÃ¹%Ã²Â¹Ã“]Ã\\tÂ©#O~yÃ’Â¬.Ã¸ Â°^Ã³ÂœÃ.Ã•$ÃˆÂ§ÂÂ–Â¡Ã´Ã«Â´Â¿ÃaJÃ™Ã¬Â¦:ÃºhÃ»"â‹¡CL?ÃÃ‹N*Ã±ÂrYz:LÃ±jÃ«ÂŠÃªÂ‡DÃ³gÃ»ÃŸÂ°IÂÃ†.Ã¨\\r@a$YJÂ³kÂ¦Ã½Â¸Y Â«Ã‹Ã£[Ã”$ÃºÃŠIÃ— asÃ‹ÃƒjÂ¥Â™ÂµÂ¥Â§]~Ã¬mÃ—Ã­Â‚Ã£Â©NÃŸ\\nÃ¥Ã”blÂ¯ÃŒÃˆ\\rÂ¬Ã²GÃ–Ã¸LÃ¤{Ã¶'\\tOy)Ã·VkÂœÃšÃˆÂ›ÃÃ‡pÂ»Â¶ZÃ†Âª$dÂ”Ã˜xuÂšÂ¯ÃÃ£Ã¡jÂŠÂ½ÃÃ®ÂÂ¡Â¤2eÂ¨ÂœÃ¨[Â½ÃÃ·.ÂšÂ lSDÃ¤,Â¶i%Ã²\\tOÃ§Â½Ã‹Â†Â”ÂRÂ®Â ~ ÃÃ”Â¹hÃ»{Â¼&Ã…Ã…D=ÂÂšÂ­h;Â´Ã‹YÂ‘Â¿Â¡\\nf"Ã›Â³Ã·Â›9`|DÃ‹Ã¤Â§Â¨AÃ—ÃšÃ˜Ã—jxÃ ÂµÃ”Ã²tÂ„~Ã°KÂ™ÂrÂƒÃ›ÃjWÃ™Â¢!ÃŠÂ«yÃ˜Â…4?Ã†/Ã ÃÂŸÂ¶"fG6} ÂÂš6ÃªJt`Â•Ã4$Ã¦Ã¡Ã¶YÂ’Ã´'ÃŠvÃ´?K>^Ã‹Â“Â–ÃÂ¤Ã—Â¶:Ãœ>UÃ¨Â°KÃŒÃ£ÃÃ¼ÃƒÃ®znÂ¬]ÂÃ‹Â˜Â²ÃœÂ¶Ã«Â«Â¶Â˜ÂÃ¨Ã¥Â‡Â€Â‰Ã‹Ã™zÃ2H0Â¯T:Ã¾ Ã¾Â˜uÃ»(\\bÃÃšÃ\\tkwÃŒÂ¤Ã§Â¯Â¬Ã—zÂµÂ¹Â­iÃeiÂÃºÃœnÃ†+Â¯u!.Ã3Â‰Ã©emÃ¼ÂƒÃR3xÂšÃ¸Ã…ÂºÂ¦fÃ²]Ã¾Â®Ã™Ã¥Â¯\\r&Ã‘ÂŠqÃ‘Â\\rÃ€DÂ­Â‚5Ã¬^WÂ@":Ã†Ã°NAÃ¼EÂ°Z'Ã ;Â°ÂÂÂ¡2"ÂªR0~d!|ÂŠÂ‡Â¡Â±Â®Ã°ÃºÂ²Â·6Â–/ÂÃ”Â£Ã¯eÂ«MÃ¾Ã–Â‡;Ã»8Ã¦ÂŠÂ•ÂœÃºÂ ÃÃ°Â‰Â¤QjÂ¿Ã’Ã§Ã‡IÃ‘kÃ­Â°Ã¼ÃŠX/9ÂÃ»ÂºÃ¨Ã¶RGhÂ¬Ã¯QÃ¯Â¤l`BÃ¡Ã‚?Â¬L+Ã¯t6Â®Â²EÂÃÃ½ÃœÂ¡%O=p\\bÂ¹ÃÂ˜ÂƒÂÂŒtÂ’wZÃ¾Â™Â§Â±]AHY|JÂ‰Ã‰ÃU(87V|Ã·Â§Ã—Â­Ã­ÂŸbÂ‚Â•KZÂ—Ã‡]Ã›ÃŒÃ´Ã€Â—ÂŸ+Ã¢Ã´Â—Â”4!"Ã.Â¯J1ÃÂÃ€uÂÂ˜Ã« tÃ¯Ãˆ4Ã«Â•6Â¯Ã§Ã‰NÂ°Ã\\fJÃMÃ„=LÃ¥ÃÂ‚ÂŠÂ¿Ã´Â²Â«|gÂŠ\W4b5ÂµÂ’Ã’Â‚Â¯U\\tÂ–_Ã¤Â‘Ã¯Â£Â¡wQÂ¾Ã°E*Â›Ã¬Â·Â±ÂŠ5{Ã³_lÃšDj,MmJ{'Â€nGÂ‹Â³ÂÃ®r:Â“ÂŒÂ¤TfJÂ“Â…@Â½ÃÃ€Â»Â™Ã¼'ÂÃ†ÂŠÂ¨KÃÂ®Ã¿_SÃ¹Â¶}d@Â¿ÃŸYÂ½ÂÃ€Â£Â–Q(Ã­plÂ·`Ã¯Â¢Â¢Ã¸RCÃ‚kzlÃ™(/3Â‹Ã£WÃ½lÂ¹jJÂ½Ã¬SÃ©\Ã«Â…R Z,)XÂ N+Ã“8Ã­Ã¯Ã˜ÂškÂªÃ½eÂˆÂWÂ¿Ã’\\t$Ã‰Â“?3Â…3ÂÃ–Â‰Ã°BQ][ÂŸÂ¢Â½Â)Â”\\flÃ¸Ã¤Ã„#Â˜hÃªÃ²Ã«FÃ¢<Ã§1)ÂÂ²Ã”Â²\ÃÂ‡Â Ã°\\r;yvkCÂœ!Ã”Ã«Â ,U8Ã†Ã¶uÃ´Ã—Âªw\\rÃ¹\\r4Â¯Ã§Ã£ ÂŒÂ–ÃŠÃ€kÂ¶Â±Â‚Â¨~&jÂ¶MY]fÃ‹Ã¶Ã¸ÃUQÂ„Ã¶Ã¿ aÂ¢LÂ©Â’Ã€Ã¹/Â‡ ÂšÃ™BÃ°Ã–Ã·ÂŠÂ©Ã»Ã‹RÃ¹Â³Â¥Ã…Â«GÃ™ÃÃµÂÃÃ±Ã–Â¼Â®EmÃÂ«ÂªmÃ†yÃƒÂ‚<Â°Ã¨Â·9ÃÃ¡Ã®Ã·mÃ¡Â¢Ã”Â³Â¹Â”2Â‰D0Ã—Ã©Âº\Â­euÂœÃµ$Ã­51\\nOÂ³Âµ7Ã¥Ã±ÃTÂ£4Ã›ÃƒTcÂ±5ÂšcÃ¤ÂŸrÃÂ’;5Â£Ã†\WxÂ§ÂŠÂ–Ã„ÃHÃ¥Ã¤ XÃ§1ÃƒÃ£ÂW/ Ã‰Q2Â=$?N8HÂ¸J/Ã—cÃ™5Ã¡zÃÂ£ÃšVÂ²l7Â‚^36)J'z\\bÂ´%ÃÂ¦ÂÂ´Â·ÂˆÃ0`B;~Ãš(Â•Â·Ã–Â²Â™Â£]Ã¤Ã´xÃ•ÂÃ¤#Â†Â¼YÃ‰*Â£Â¨PfEv"fÃÂ½`tÃ”2Ã„Â„0ÃºOQÂ1Âµ'Ã‰OÂO-Â“/Â\\bÂ¹Ã„ÂÃ”Â™Ã¨,'Ã¼IÃ´Â±vÃ#Â£Â™Ã™Â¡ÂÂÃ€Â¨ÂŒNbÂ·Ã§Â¶|Â­Â·,Â²l\\rÃ¦Ã¼+ÃšLÂ¦#ÃÂ”Â¾ZÃƒ]9Â¯2bÂ†V]}uÃªÂ„INÃO+ÃŒÃ²ÂƒÃ„OÂ³ÂHt5XÂ‘/Ã°Âˆ,Â²F`\\tÂ¼\\nÃgRÂ®Ã–Ã‡GQÂ±0Ã¶"WyÃ¤ÃÂ¨Â¶ÃÂ°Ã¤9bÃŒÂºV?Ã®bYsÂ…Ã¹nÂ²Â¯zfÃÃ—ÃƒÂ»0Â³Â¹JÃŠ@{9Ã„Â´=Â‡Â¬SÃŒÂ–Â‰aÂŸÃ…Â«Â¨Ã“uÂ¥aÃ´Lc$:Â¥Â¹Â¦Ã›}~Â±ÃŠÂ–Â³Ã¨~h |ÃªQ qdFÃQÃ¶bÃ€qÂ•n:Â¶2Ã¼Ã§Ã¦Â˜=xÂŠÂ™Ã£Â/Â¯ÃÃÃ—sÃ¾Ã£GÂ‹Ã™ÃˆÂµÃ¡fBÂ£Ã‚ Ã‰Â¹\\nÂÂ¿Ã¯Âµ))Ã˜=Ã›QÃ›XÃ‘eWÃºSÂ‹vÂf%Â‚ÂªÃ@"ÃQzÃ°Â”_ÂˆÃ£Ã¾Ã¹ÃU.qÃ²o'Ã½Ã¨[31%ÂºÃ¥\NÃ¡Ã“Â½hÃ¥bÂ¼Â±\Ã†7Ã”ÂŸIx%Â‰ÂÂ‡Ã“Ã€;Ã…:2?Â®ÂŸÃ¥%ÃºU}DÃ–|.ÂW UÃ€%<Â£Ã‡eÃÂ‹Ã—TzÂ¶fÃÂ˜\\b>ÃÃ¾Ã¥jNÂ¾eÂ¿ÃŠ"Ã¶Â®t<>ÂÂ™Ã£\\fl ÂœHpÃ¸abÃ—Â”Â°Â±|Â™^Â„Â½Ã¯Ã Ã­ÃŒÂ¨Ãwrt|ÂÂ¯pÃºvÃÂ»@Ã·Â³ÂÂ˜Ãª%-Â€yÃ¥Ã²FÃ¤hÃ˜Â²(Â¢#Ã†%`ÂmNÃ—bÃ²Â¡Â¤Â—LÃ™Ã¨ÂŒT7KÂ¾Âœ>TpÃÂ—Â°Â±Â€Ã¤(IÃ«Â¶;QNoÂˆÃ¿Ã¿Ã˜,,\\tIÃ±ÂÂš\\fÂƒBÃ¦#dÃ‚NÂ¦Ã³hÂ‚ÂµÂ™2YwÃ®Ã“%xp[Â½A\\nOÂ…Â‰Â˜Â¾Ã ÂšÂ™1Â¦){mÃ³iÂÂŒ'dÃn3Ã«~Â‚Ã®EhwÂŒQÃ’Ã„Ã„Â»ÃÂ­Ã¤HpÃ«,Â”#Ã³kÃ†%Â(Ã“6Â–=Ã¶?Â·Â€ÃŸp^Ã°#Ã‡ Ã2DÂ¡FÂ†Â¬Â”Ã–gÂ´|Ã‰krÃ¿oÂ’j=Ã¤\Â—Â¾]E@Ã‰2Ãƒ\\nOÃÃ»Â¶GÃ—8Ã«Â‘ÂÂ33Â•Ã—ÃŠÃ—ÂÂŒAAÃ—Ã‹Ã¶Â˜QÃ³LÃ¯ÂÂœÃ±WOQÃ¦Â‹Â¿4 +uÃ¼:ÃƒÂ‰ID*Ã™ÃƒÃ–Ã§Â–Ã‰Âb\\nÃ²@&Ã¢ÂŸÂ¾Ã°Â°c1ÂGÃ”,qO[Ã½Â‚o@Â†>&ÃŒÃÃ°OÃ ÃÃ©Âº /5)Â‘ÃŒÂŠ_n\\by`Â«9BNÂ¸Â²Ã©~P2amÃh'>)Â™Ã¥M\Â¹;T4{Ã™ÂªQÂ…lÂ†Ã¾OÂˆÃ«Ã‘Â°Â‡s4LÂ­Q!Â€"`<3JP<Ã¯Ãƒ\\bÃ€Ã£Ã©HÂÂ€lZciÂÂ«\\fÃÃ¤17Â¤Â§.6+[Â’Ã¼b ÂƒRÃ®Â–nÂ¯Ã¢Â¤OÂ¼ÃÂ›Ã°Ã°ÃˆOz.Ã®Ã—K>Â“Ã» ,\\tÂ¥Ã’"Ã¨ÃºNAÃ²Â€lÃƒÂ‰ÃµÂ©INsÂ¾Â–Â¬ÂÂ‚Â›y\\bÂ¯Ã¤_bÂ·"^Â¹Ã“Ã·ÂŒ^Ã£Â¡Â¦sÂ¹8ÂÃ“ÃÂ•DlÂ†Ã…Â™~&lVÂƒÂŒÂ©Â«y$,OÃ³Â¼g\\fÃ”Â£{m\\rÂÂŸ_Ã²Ã£Â’ÂkSÃ´Ã›H_Â¦"Â¨aCÃ©KÂ¯ObÃŠÃ”$Ã²Ã™CÃ‚P-UÂ–Ã»Ã¤LÂº1Ã²kÃ³Ã²kÂ¥^.ÃÃ m\#Ã´Â…Â‡Â˜?ÂŠÂ»FLÃ‹\\fÂ¨Ã™Ã•Ã“Â‰Ã–Ã§Âœ\Â²JJ3~:Ã¿qÂ¢ÃŒwÂ‰Â•Ã†}Ã·ÂÂ¾bÃ¯\pÂ¥4ÂrÃ›Ã¹Â™~ÂQ6R\Â¶*Â«_QÂ‚cÃ¾zÂ»"Ã¸UÃ¾Ã²Ã™Ã€5#Ã¢EÂfÃ¡Ã¸.Ã¸Â¬Ã»ÂŸ+&ÃÂ¦Ã–BÃ½tÃ‹lYÂœICÂ¬Ã›Â©~q|Ã·Â™Ã’Â«ÃŸÃ®Â£Â°)VwÃºÂ€YA#Ã¢U.ÃŠÃ°lÂ’>ÃÂ¸Ã©Â‹Ã¬ÃƒMhÂ†&AV'nÂ¢Â´6Â¼NÂŸÃ®]-Â¢Â‘ÃšÂ¦Â¿nÃ°c5Â¢Ã•Â¢\\nÃ»_ÂUÃ°>,Â–YuÃ¦Ã­Â¥lÃÂÃ…GÃ¨5Â©Â±:`Â¡!Ã¤Ãš\\fÂ¶Â£Â¤Ã¬^BJÃ·\\nÃ†ÃŸ^Ã˜Â’ÃÂÃ…=ZÂ…Â¢5ÃÃš>KÂ€ZÃ¼Â°Â»ÂÂ¶ÃªÂ¶Ã¸Ãˆ$8]CÂœ^.,7Â¢Ã£Â¡Â¤pÃ¨ÂœCrwÃKn'ÃSNÂ¢Â±Â’ÃˆÂ³JÂ•Â–Ã‘Â¥ÂŠZRÃÂÃ–Ã“ÃˆÂ°Â³Ã‘Ã‚ÂÃ–Â…jÂÂÂ¼Â¶Â‘Xx<Ã´Ã•bNÂ‹Ã–CÃµÂ±KSÂ–ÂšÃ2Ã¯+ÃÂ¶Â‚Â±ÂµÃ‰^Â›hÂ&Ãƒd}Ã”1ÂŠÂ‘Â¹vÃ–Â«Â¢Ã€Ã‰Â±Â‹Â…Â“oWx\\tÃ½CpÃ²Ã‘ÃºnÂ²Â $%ÂŒH1Ã¦Â¬Ã¨IÂ“ÂÃ‹Ã¿Cr<Â“}Â—0Â¼YÂ¥FwÃ§&:Â“Â¥ÃÃº@Ã³ÃµÂQÃkl)AX!Â CgÂŸÃWÃ‡Ã±Â­Â”\Ã­Â¥UTÂÃ˜>Â»Â³TÂ­WbbÃƒÂ¼#Â´Â£ÂÂ°yrÃ²_ÂÂ¨Â±Â—d'_>.Ã„Â˜{ÃœZÃ3ÃqÂ·v-Â¥Ã—ZÃ°lÂ‹Ã»2zÂ–ÃšCÂ§bÃ¹Ã²OÂ‹sÃ•Ã¡ÂÂrÃ»Z4l_+~ÃŒGwÃŠb^!Â³N>lÂ›MÂ«ÃšÂ›ÃºÃ­Ã¨Ã¦ÃÂ«iÂ¬Â•Â¸Â¢Ã¶Â¨Ã¯Â©J[Ãœj[Ã¸}Â©_Â«Â²*5C*KÃ®Y Ã£Â¤ÃšÃ”ÃŒÃ¾Ã¼ÃÃ¨Âš8ÃÃ¯Ã Ã–ÃˆÃ‘Â‚ÃšÃ¯Ã³uvJ>Â‰Ã¬Â¡ÂÂÂ‘>iÂ¸*kÃ·Â­ÃŠÃ€Â~\\bÂ¤Â¾Ã“Âº:.vÂ˜#@ÂˆÃ³EKÂ™oÂ–Ã§ÃÃ§ÂŒ0OÂ˜XÃ¶Ã¤6tdbÂ¦Â™Â‡Ãœ?Â‹Â‘Â¢0Ã‡Â¹Ã±-)\]=ÃÃ¨Ã”Ã° ÃÂ°?gÃ¡ÂJÃÂ’Â§@XÂ½ÂÃÃ©Ã†Â¼Ã›Â“{Â¿Â«<YÃŸÃ„ Ã¨Ã…#$$ÂŠÂˆAiÃµÂ˜ÃªÂ¨B5WCÂ³E1Ã˜!PÂŒÃ¾ÃÃÃ‚Y[Ã·Ã‚Ã¯Â‹ Ã£^mÂ­ÂºÃ¹\\fÂƒÂ³ÂÃ¿Ã„Â’Ã‚Ã­F0Ã¨DÂ‚~PÃ¥ÃhÂ¤ÂÃ¦fÃ®Â¿~Â®Ã¡Â®}Âƒ[Â¯Â¬$Ã’0gÃ™Â¥Â’Â‘Â¶|V:ÂªÃ¾DDÃŸÃ»Â¨Â¯3$Â€ÂµÂKÃ¿Ã½Ã´Ã¬Ã©Ã…hÂ–Ã¡_Â£g1Ã’b_Ã¶Ã¶ÃˆÃœÂ“XÃˆÃ‹Â™qQDÃ WÃ¡Â¼Â³Â¸$ :Â¶8Ã²7Â¾2ÃpÃµ%jÂ¥Ã‘aÂ”TOÃ¹*DÂ¬EÂªÃ¼xÂ±Ã´ÃÂ‚ÂÃºvQÂ¸Ã¨`&Â¹{Â‹'qÂ¾nO.\\f\\r\\rÂšÂ—Ã¾Ã¾Â¡Â€ÃÂ«Â¹Ã¨\\nÃ²u5Ã¶\\nÂ¹ZÃÂ¿@dÃkÂmÂ½S|hÃ»Â©Ã³Â¨Ã—L$\iaÃ›Ã‹LÂ¼Ã›Â›Â†'Ã¤vÃÃ²Â»UÂ¯Â‚#ÂnÃÃ¥$+ÂÃ±1GÂš3Ã…Â¸Â³Ã›Ã±\\fÂ›Ã§Ã4Â•Â„zÂ”(Â¶Â±aÃ€Ã’\\bÂ§Â¾Ã‚Â‰TiÃ´Ã¥Â’!Â®+Bn*Ã¹Â™`Â”Âµ"}"&Ã\\n!Â€Ãª7NÃ«8Â²3ÂÂ¹?Ã’&ÂƒÃ«bÂ¿Â‹Ã„{yÃ„ÃŸ\Ãj-RCÂ±Ã—QÃ‚ÃŸÂ…Â‰ÂªÃ†Â¹dÂ²RSvÃ¨Ã”Ã‚ÂœÂ©nÃ«Ã®\\rVmL?*NÃ¥ÃrÂ˜3nÃˆÃ¼="b]Âµi\\nÃ„Ã§ÃµtÃiÃ!\\fÂmo=Â¸ÂO0PÃÂ€iPPa"Â’,ÂIÃ°Ã¢ÃœÂ´Â¨Ã·Âµk&Ã‰Ã¬fKÂÂ€ÂŠÂ˜Â¿1{!\*ÃƒÂ’Ã“\\nÂºÂ™$Ã%%Ã¿Â¢;Ã ÃÂ” *)UÃ„VÂ©ÃšaÂ±BÂ£IÃ¨?Ã±Ã\Â€Ã¯lÃªÂ‹Ã‘RÂ‘zÃÂ‡YVk]\\tÃ0Â®EÃ°%Ã¶ÂŸÃµ'ÂµVPbÂ‚DÂ´xVÃƒÂ¸cÂ­qÃµÃ­Â²Ã–)ÃªÂ•Â±r;Â‡'Ã§Ã€C_Â«Ã™DfeÂŸÃ˜sÂŒ5Âª/dÃ£)Â‹Ã³ÃŠÃ¯Â‡Ã¿Â'Ã•RÂ‰Ã¨Ã7nÂµ"yTYY)Â¸ÂšIÃ©Â¥Ã£Â‡Âª.Â®ÃÂ¾Â“ÃÂªÃ›*Â YÂ‡ueÃ–Â–')Ã˜&Ã„.\Â§Â™Ã\\fÃ»Ã±Âº Ã‹@wÃ¾Ã¸Ã¯Ã‡f[5`Â„[JtÃº'NÃ‰ÂIÃ–brÂ¸9@$Ã”-gÂ¿rÂ©_SÃ¼&Ã„xÂªÃ¡Ãœ+Ã¶?aÃ¹Â¡v|8Â-4qÃ›Â³\\t3Ã?$P;\Â“TÂµ[Ã±ÃŸ$ÂŸfÂ„Â†FÂ·hÂƒÃ…Â´Â³0\\rÃo}Ã§UtÂ°+l}1M)Â´{ÃµÃ„Â›Â‘LÃ¸yÃ‹Ã†Â pÃ‘Ã•EÂ‚ÃXÃ€Â²TÂœÂŠÃ«AÃºÂœÃ·RÃ…?ÃÃÂ‰Â¶TN@Â‰}rÂ—Ãt9Ã—Ã½&B(Âª'Â¼BÃ¶GfÂ‹1>ÂªÃ…fT7Â®~Â¼Â¨Â¾urÂ°u7wÂ¢Ã™bÂ†Â«Ã‡Â§Â¼Â·bÂ˜ÃœLÃ‚}?ÃšÂ˜2|Â¿~xÃÃ‚Ã®ÂÃ†Ã¤Â¢Â¹Ã†ÃÂ½Â»F{Ã˜z?ÃºLZÂXsÂ›ÂÂ»\\bÃƒÂ¬Âª/Ã¹Ã‰Ã¶)Ã‹cYEÃ¯ÃZÂ‰+Â Ã­;(ÂœvÂ‡hÂ„ÃŒeM|lÃ©NÃµqÂ¿:Â–56Â¬Â¸@HÃœYÂÃ•2MÃÃ•ÂŸU\\rvÂÃ­Ã’SÃ¢Â´LÃ¡mÂ¬]lÂ±:Â¾Â®dÂµÃ·Â¶Ã¢K96\\tÃÃ©Ãƒ*Ã—Â’'ÂÂ·ÂÂµMÂ@Ã¥ZÂ€E[Â…b1Â¼6;Ã‰ Â³#]RÃ†mÂ¹ÂÂ©U!Âœ?,DaÃ’/7Ã³-Ã¢)6Ã™}'ÂÃÃ»@Â…Ã¢/Ã”1"yÂ¨NÂˆÃ¤Ã›Â˜Ã“ÂŠZÃ›Ã’ÃœÃ©Â€irÂ±&Ã³ tÂ»NÂ¹Ã  \\f;iDÃŠWÃ¦Â°gÂ°<Â™LÃŠÃ8\\f\\tÂ´^Â²sÂ–Â—^\\rÂ„SucV[Â²mKÂlÃ®0Â²Â‹4aÃ’Ã†4MÂ‡5Ã¦Â¾ÃŠaÂ©Â²l2Ã±Q8Â¦$Â´^Ã¢m:Ã§"Ã­3Ã¾CRÂ€q;ÃºlÃ„m'lÂ¨iÃ¥Ã­p`ÃÂcÂ¬,VÂ‰Â¡NÃ´|Â›Ã¯Â‡Â§b`Ã¾MÃ¹ÃˆjÃ°Ã·ÃÃ“ÃºÃŠÃ–EV?OhÂ³Â¥Ã’ifÃ‘ÃŸpiÃ¥Ã€oÂÃ¯Â¡EÃ‹V0&Ã‰Â‘Â¾oÂ‡AdÂ§Ãª0\\bsÂµ/mÃµÃ§AÂ€\\n2Ã„UÂµ~ÂœZÃ„ÃÂ‰Â˜ÂµÂ‘Â¼ÂŒÂƒkÂ‰Â‘ÃŸÃ–2ÃŸÃµÂ›Â-Â¹Ã¼Ã±Ã„X\\bÂ²,GÃ¿Ã¹3Â§P>!Ã­)"RÃiÂ†Ã *:wÃ‚Â¼Â•#Ã¹PÃˆ0(Â‘Ã­YÂƒÃ¸OÃ½Â„&Â†Â‚w8\\njtÂ¢xÂ Ã”X{T.Ã±Ãr#%~zGÃ…/HÂ¤jÂ“Â®FÃ§Ã¤tÂ’=iÂ‰NÃ—;9Â¤iÂ—Â‚Ã˜ÃÃ“Â«@&Ã¿ÃªwÃÂ¥ÂƒÂ»;Ã¯Ã¸ÂŒ=Â¬ÃšÂŒ(ÂœÃ³ÃŸw>ACÂÃÃ€Ã²Â€Â„Ã¯Âª`Ã«0/WÂšÂˆÂ„MDÂ¿Â¾:Ã¼Â“ÂÃ®{Â†ÃµhÃ‰ÃJÃ™2Ã’Â‹e%ÂÂŠÃ‹Â·ebÃ«ÃXwÂ´RÃ"NÃ™Â‰Â£Ã’Â‘Â’Â¾iÃ¡Â€0nÃ–Ã¶Â»Ã¡ÃŒ^Ã¶oÃªÂ‡Y+Â›Â±\\nÂˆhÂ˜ÃŸÃ|wXÃ¦Ã–wÂŸÃ¤Â“1Â¯bÂ–@^Â»8Â«Â‘Â‰Â¡> Â¦Â¯Ã˜Ã¦cÃ•Â¶c6Â¯Ã®Ã£ÃKÃ’ÂY-'_Ã¥.Âo<Ã›lÂ¢Ã­\\fÂ£<Ã’Ã¼+.}Â±\\tÃ½^ÂŸÃ¸Ã»Ã¾Â“Â‡ÃŠÃµ6Â¾8ÂœÂ»I(AQ3Ã«Ã‹~IÃ¢ÂˆÂ¶Â¾<^Ã‹Â½lJÂ¨Â¢eÃ‡Ã„ÃG\IYÃÃ»OD2sNÂ‹Â‹Ã·Ã¸Ã–I|Ã‘Ã²{Â±Ã¼ÂÃ…)!ÂŠÂœÂ‘ÂƒÃšÃ\\tÃœ`VÂ´Ã‚Ã˜Ã°Â¶Â‡Ã¤eÃ©Â©Ã“ÂƒÂˆÂ¨Ã–Ã‘ÂŒo9WNÃ½Ã·_Ã•ÂºÂ›Â—Â‡UÃ…!Ã…Ã³Ã‚Â³MÃ˜3SÂ¿Â´e]Ã:YVÃ¸Ã‘Ã¨Ã®Ã‡pÃ«Ã“Â©{Â£Ã€gffÂ‹n;ÂÃ¯ÃÂ©:+Ã’Â»Â¬Â”Ã”Â¯@Â’ÃšÃšÂµy:(*}/Ã§2W*6Âg/[Â¾Â«ÃÃŠÂ°Â€Â®=Ã…FDÃ¹Â˜kÃ¹ÂªaÃ‰:!QÂ’ÃšÃŒÃ½<Â¨ÂÂ™Â˜RÃ®Â‚}Ã¶Ã¯IÂ™L)Ã¸\\rÂª)ÂXÃ’Â¿Ã¶,Â‡UXÂ’ÃÂÃ«ÂŒÃ±Ã_Ã…_QÃ€.Ã T}Ã‡ÃKÃM Ã¿ÂšNxÃ–d.\\nIqÂ´Â«Â„e3Â¶Ã¸Ã Â“.Â¿BfÂŠÃŒÂˆ\rPÃªÃ‹eR8;Ã³ÃiZ\\nJÃ‡Â‡ÃÃ²Ã­Âƒ;Ã„Ã•Â•\\nÃƒL]ÃŸÂƒ\\nGGÃ«oÂ¥xC/Â¾{Ã§Ã˜g_Ã›Ã—<}ÂÃ»Ã¡mÂ‰ÂÃdÂ¦Â¦\\t<Â˜ÂÃ«Ã¦PÂŠÃ¬sJ;hTÃ¬Â­Â²Â‡Â¿Ã„Ã¡Â‘ÂÃ¯Â—Ã¯Z\\bbÃÂ™Ã‰V-Â²EÃÃ­TÂ«Â«Â†Ã“/zÃ†^PNÂ Ã“vÂ§Ã€@a&Ã•(Â­Ã€Ã«Ã¥Ã„ÂŠN%TÂ“Â§ÃÂ u6PÃˆÂ¬^Ã† .)Â† ]Ã¨Â6Ã†ÃCYÃ—ÂƒrxÂªÃ¿Â•3oÂ¦lnÂÂÃ‘Â½QÃˆ$ÂcÂ¶Â¨Â¶=YTfÂ®tÃš^&< d:Â³Â‚Âƒ{Ã®Â…Ã±Ã¡$Ã¼O!|Â¼EH)Â¶fÃ®R[i2Ã·ÂšÂ¿Â‚Ã•Â¹VÂŒrÃ²Â³Ãº lÃ¨v2PDÃ½ÂˆKÂ²!Ã˜ÂºÃµ(oKpÂ¾Ã Z_Â›:ÃŠÃ·Â RuÃ¿ÂŸÃ¨H>Ã >dbÂ£Ã’eAÃ‰|Â³Ã‹Ã‚ 2Â³%l{Â¬ÃµÃ¿Â¾@@Â¼Â¼Ã„8Â•ÂÃ‡o]&Ã³Â”Â™Ã¼)Ã¯Ã—ÃºÃ¼4ÂºÃÂ²Â—Â¯lÃ—Ã‡HÂ“JÂš\\rÂ±Â®"Y=Â‚Â”Â¼?\\rÃ–Ãd8Ã½JÂœÂ…Ã³ÂµÃ›EÃ–ttÂ©Ã”=(Â–fÂŠÃ¶f$aÃ´Â…Â†\\tAÃ°ÃµÂ¡Â¸:*Ã•$Â§Ã¤oÃºÃÃ‚ÂÂµÃ€Ã…\\f~Â¶ÂŸÂÂ¾<Ã™ÂˆÃ·5Ã»ÃŸÃ¦BÂ³-ÃÃŸÂ•Â¿Â¸Â©Ã­Â™Ã„Ã¾Ã¸Ã«Â‹wQÂµM'Ã›Â½;;Ã”LhÂ­ÃšÂ¶VÂ©Â³ Ys<e9Ã¯1dOÂ³zÃŠ Ã•Â¥Ã¿,ÂrlÂ±Ã-Z1\\bÃˆL8Â¯Ã¦RÃ±Â­Â“Â¦Â¯ Ã´Â–1ÃXÂ²LÃ´ÃƒÃ Â…Ã¹Â‚Ã•Â“Â¤Ã§J\\nÂª hÂ”Â¸ÃÃ…Â°V4FÂÂ¥HÃA\\fÂƒÃ™Â°Ã£eÂ’\\rÃŒÃ‚ÂœÃ´;Â¾zÃº_Â¾Â±Ã½Ã›eÂ— 1ÃÃ¡ÂŒÃÃ¼Ã¿Â¼ÂªÂ‘0AÂ²Ã•Ã™Ã™5ÂšÂ›Â¯`)zÃ“kIÂ£Ã¸pi?Ã–GÂ©z4\\bÂÂµ\\bÂ¨ÃŸ3MÂ‘8ÃšÃœÂ»Â  ,Ã¡hÂ”Ã WÃ¹Â˜Y0dÂ±Â’sÂz%Â¡QÂ¾"ÃºÃ¬eÂ¦iÃ·Wx*si@Â Â¸Ã§KÃ€Â™Â¤!,ÃÂ‡Ã½Â¸Ã -5Ã¦%BÃ³$&ÂÃ²Ã€Ã³Â¨\\fÂ¹ÃŸÂµ$Q~Ãš[Â¶Â½~Â€Ã´mÂ¾$:Âˆ3fh6ÂŸÂ§ÂœÂ‹Ã¦?niÃ©Â…ÂÃÂ¡/Â«O\\nÂ—\\rglWÂ²6ÂƒT(ÃŠÂ¾m\\bÂ³Â“ÃHÂ‹pÂ™Â˜ÂŠÃ±#Ã¶FÃNÂšgÂ¤Ã¶Â”X sÂ’Ãº-Ã¤Â“'hÃ”mÂ½8Â”F8]Â”ÂˆÂ¶Â²8tÂÂ™Jh<SÂ±JÂ¬qÃÃ­ÂŠÃ½Ã•Ã›ÃœjÂ¶Ã³LÂ–Â²Ã¹Â‚4Ã‹fÃ†dPÂ„Ã®`Ã€~Ã˜NÂ¡Ã”tYÂ‚@/8Ã˜ÃŠÃ¼>[Â§C{Â›"Ã¶&KÃ‹Â¹'ÃšxÂŸÃ¬Ã‰Â¢Ã¼Â¡Â´Âª|yÃ\\tÃƒÃÂ³iÂ´;Ã¥ÂˆÂ¿Â—vÂ™ÂÃ˜Ã©Â™Â¹Ã¿Â¯Â¯ikÂ’FÂ¹XÂ£Ã™Â¢eÃ DÃŸ<Ã€rÂ˜Ã”PDÃ›jÂ¬W\\nÂ˜1Â·Ã²Â«Ãˆ5\\nÃ¿Âœ,ÃŸÃ–Â…Ã”\\bÂˆB1ÂÃ°Â­Z$z(Â¦\\n$Ã¶>Â†CÂ«Â¬Ã‚Â»Ã¯ÂÃ„Ã¡!Â—Ã€A7~ÂˆEÂ†D2\Â¯gÃªÂÂ !Â³Â‚ÃšÃƒUÃˆÂºFcÂ†q{Â–)ÃˆÂˆÂ§Ã¾Â˜Ã›qK&Â¿xÂŒf\tÃŸÂ’ÂˆÂ±V+Â³Â¼ÃÂ€Ã³>KmÂ¡7Â´Â³Â¡ÂœÂƒÃ7Â€Ã„Â¤ÃŸgÂ®Ã=Ã´%Â«\\toÂ½R|hÂ\\rÂŠÃƒÃ›ÂÃ¢NÃ³Â°Ã­Â¶kÂ–Ã‘Ã¤SÂ—Â†Â¡BÂªÃ»\\b-QÃ½Âš^Ã*Ã‘Â«ÂƒÃ•Â¼Ã‘Ã´ÃœÂÃ—5ÂšÂŠÃŒtÃ·ÂŠÃ¶Ã•ÃŒÃ·Â¯Â‡Ã·ÃÃ¢fÂÂ¥Â´ÂÃ¶Ã€Ã¹9Ã¦cÃ«ZÃ€Â¬Ã–'Â¾Â Â”Ã¡Ã¼Â¬Ã€qSÂ¼4ÂœÂŸÃºÂœÂ¦b[NÂ¦ÂÃˆucÂ‹Ã¾Â‹ÂºsÂ¦bÃ„1Ã¹[ÂŠÃ€TÂ™AÂ£IÂŠtÂ¹ÃšÃ <Â4^Ã‡Ã†Â·Â‰Ãª&ÂÂ´ÂÂªiWÂ†ÂºÃ‘Ã¾ÃƒÂÂ›uhAÂŠ_&Â«ÃŸK0)Ã¢(Â¡]QÂ»Ãš ÂÃ¤j[Â¥WÃ’Ã»Â€Ã¹6j\\tÃ†SÃÃ¶cÂ–w<Â£ &PÃÂšTÂ¶#3Â•>Â¶2Â£ÃºQÃ‰aÃl!<GHÂ‡ÂƒÂ¾\\ftÃˆ Â¢Ã½7Â®Â;Ã†Ã¡Ã¶n=ÃÃ¥IÂ…Ã•Ã»^Ã¥ÂœcÂ±Ã¸.Ã¬2eÃ’|ÂÃ¤hÂ´Â›eÂ™cÂ\\t`Â¤Ã¾ÂŠÂ¿Â‰7IRÂ°Â“Â¹Â¿Â©"Ã²Y>Ã¸@WEA0ÃÂ¸XBÂ¥Â¶JdÂºÂƒÂ©ÃƒÃ‘@fÂ–ÂÂ¤ÃÂ·(ÂŸ^Â•ÂeÃŠÂ¼Ã·Â´\\fDÂ»mÃ«$R,Ã”`ÃŠÂÂœÂ–A*X Ã¿Â­NvÂ¾Ã‡/ÃÂÃ¿Â®Ã“ÃÂ¤Â§]@,Ã•ÂªvÂ¿Â bÃÂ´Â€Ã¶Ã @ElÃ”ÂšÂœÃŸÂ°P&Ã·\\f^'Â‹sÂ³5Ã§+^Â©>x'Â°LÂÂ7Ã€&Ã”ZÂ¢Ã±I~ÃªÃƒ6Ã¶Ã@YPKÃ¾3MÃ²E__#ÃÂƒÃ¶1nÂ¯Ã‘yÂ­Âª:Ã¯E Â”Ã¸Ã’RÃ´Â„FHÂ¤Â´ÂgÂ²|Ã—Â sssÂ‹Â‡Â©ÂÂÃÃ£ÂŒÂ¶VhÂšÃŠ97Ã–Â½,zKo$Â8wÂÂ­=QÃ¼&WÃ†Âƒ Ã j.ÂœÃÂ¶]WÂªÃ«Â¼Ã‚Â­b8Â\\tFfAGÃ¡ÃeÃ€ZÂlÂÃº7Ã”Ã™Â“ÂTNÂÂ–Ã¬Ã—[Â¥ Â‡Ã‹\\rÃ‹ÃºBÃgÃÃ½Â»ÂŸi1Ã‚MÂ¶Â€ÃµÂ—Â¿ÃœÂ¬Â™Ã¸Â¹"Ã|Â¢ÃÂ"Ã©Â³Â„Ã’HWÂŒÃ‘Ã’Ã»Â‚Â¥AÂ”'Â¡ÂƒÂ›Â†Ãº_ÂÂ²ÂªÂ‡Ã¡Â±Â±b-^%Ã¯ÃÂ¯Ã—Â¥Â˜ZNÂÂÃˆoÂ²?Â¤Ã‡ÂÂºÂˆÃÃ­+d{Â½I&Â‰Ã7Ãº8Â¶Â‘Â¦|ÂŸSÃÂ¶Â»3Ã‚lÃ˜1Ã£Ã¬67Ã”Ã”Ãˆ+Ãµ:Â‹*^Â·ÃºÂ¼vÂ—LFcN|Ã©Â™Ã‘d=ÃÃ¢Â£Â¤ÃŸÂ–|iÃ„|jÂ‹ÂÃYÃ›KÂ’&cÃ”Â‹uÂ%mÃ¼LÂ”Ã–xuLÃ¾m4Ã±ÃµaÂ–ÃuÃ–ÃƒRÃ¾-Ã´Â”Â’fÃ•VTÃ…Â›Â­Ã¯<Ã¤Ã°\\nÃ¸Ã°ÃˆÂ±?Ã³Â¾cJ=6Ã…Â*Ãµ"ÂÂ¬Â Â¿ÃŸÃŸÃº^OÃ’5ÂÂ†))ÂÂ•ÂˆÃ­ÃˆÃ²\\nÂvÂ€Â ~DÃ“Ã¥Ã¦Â­>Â¤Ãš\\nÃO*Â…Ã±Â¥Ã¶dIÂÂ·Â‚_Â¼Â¥IyMÃ«Ãª3@dÃ´f\\rBÃº.Â˜Â‹ÃƒÂÃ¨`Âˆ!ÃŠÃ™Â‰Â¼PÂ™Ã 'Ã´jÂ´Â¹Â·ÃŸ-\\rwÃŒÃº|Ã°Â‚K^Â„Â­<}Â¢Â®4Â²Y#hÂ Ã¦Ã¡oÃŸÂ—OÃŒÃÃ³ÃŸg?Âƒk\\b\ÂcÂœÃ›Ã“ÂG5ÃT#Ã½_\\nTÃ½Ã‚Ã—ÃgÃ¹tÃœkSÃ¡Q\\nÂ‡MÂyÃªNbr.Ã“Ã¸Â•+Ã™gÂÂÃ¨"]Ã’Ã·Â½Ã¸Ã¾:Ã–-Ã¼Â§fÂ­x-Â„}HÃ°zÃ‰Ã«Ã¦=Ã/-WÂ¹}\\fÂ„_Âœ8Â—ÂŠjÂ¦|Â³|wÃ°ÂqÂ˜]kÂ‚Ã'Â°JQÂ—ÂµÂ¿VVÂ³%YhjZ4o!5Â‹Â”Â¦Ã…Ã˜Ã‘nÃ#Â«Â—Â©Ãš\\nÃ«Ã mÂŠBNÂÂ¶Ã¼Â¹ÂšyÂ‚Ã¬Ã‘Â†>Ã”ZÃ›Ât\Ã¤Â†Â©Â©.H\\tZt~Â¼Ã˜Ã€[MÂ€D~kÃ–ÂˆÂµÂœÂŸÂ‚ÃŒÂ ÂÂ€Ã‘{Â‘2Â§Â£AÂ‰Â‘ÂªÃ3>/Ã¹u$Â¢ÂœseÃˆÂÂ¾RÃ¶+T*dÃªÂœÂ…,Ã9EÂCÂºÂ©wxÃ¯Â¾Ã”'ÂŠÃ‡Ã†ÃºGÃ®Ã½\\tÃ¿Ã„Ã—"XÃ»ÃµÂ£/Ã¦XÂŒÂ“DÂÂÃ«9Â <Â”ÃÃ»rBÃ¸Â‡'Â™G\\r5Ã™$#Ã½Ã†Â™$XvÂ´8Ãœ<RÃˆÃ±Ã¶(ÂÃºÂ¾ÃÂ¥Ã”vQ[Â‘7ÂºÃ¥uÂ½8t\\fÃ»JÂ²>ÃÃ¤El\\r=oÂ®Ã›uO>ÂªÃª\\b$Â³ ÂƒÃÂ¯?Ã¥Âšlt+Ã·Ã·Ã›l0Â²uyÂÃ“Â¨Â¦cÃ¦VÂ˜ÃŸÂ¨Ã¹'Ã—Ã­BÃ¼$wWÃµÃºÂ®J8~rÃ¾=Ã³Ã¦9Ã…Â˜>\\fÂÂ¬Q!\\tÂ»AÃ¨6Ã°Â•Ã¢Ã®!Â‚WÃštÂŒBÂªÂ³xp]Ã¸Ã¿Ã©Â(1Ã¬+Ã•Â™Â¢Â—:Â›Ã Ã"ÂŒDÃ¸Ã‚Ã¾ÃµÂ„Ã•AÂ¥oÃ³$Â’Ã·Ã‹Â£`7LÂ‹VÂ•Â·Ã§Ã-Ã‘ÂŒÂ¼nÂ¹Â»zÃ‘gÃœ@#Â†Â¼bÃ²ÃŸÂŠÃœÂ¨MBÂÂšÃ¡zwÃ¨j=,IJiÂ™Â™ÂBÂ¥bÂJÃ»kÃ§dNQÃ®Ã¸^nÃšÂ¡+Â©Â”Â…Â9JÂ¼ypÃ³AÃšO\\bvÃ´Â»Ã¶SÃ—ÂœÃ²Ã‘ÃºÂ—Ã¤kÂ}jÃ¤ÂiÃ€\\fnq@ÃˆÃ¼ÃÃBPÃªÂ#fÃ¯ZÃ´%Â´Ã’MÃÂ‰msÃ‰Ã°T#Â¾GÂ°Ã¨ÃªÂˆÃ…Ã›gÃºSRÃŒÂ€Ã€ÃŠÃ„Â¤tvÂ¬'3Â…i\\bNÃ¼Â†Ã’QÂ¶Ã‘Ã²Â¢73Ã\ÃÂ°ÃºÃÃUdMB,'Ã†Â¶Â²Â‰Â²zÃ„\\b8~>Ã²bÃ«Â«iEÃš`#ÃŠÂšÂ¸ oÃœÂºÃ¸ Â¯ÃªÃ¶Ã™Â_DÂ‹ÂšÂ»Ã¹Â°ÃšÂ¯Ã¼_1Ã¤=,ZÂŠzÃ«<Ã„iÂ•Ã¿Â–;Â™(zÂ‘Ã¼bÂÃ´Â±Â…Ã Â¾Ã–3Â°Â…Â˜XhxÃ¬\Â³Â¾ÂÃŒÂ’Ã€Â¿Â³Â Âº4Â«Ã”Â—c:Â‰Ã…Ã´}Â«}:Â¬Ã–Â—\BoÃ¦Â«oM)CÃ—Â¦ÂªznACHÂ™SÃš#OÃ¹\\fÂ dÃ’hÃÃ®uÂ~Ã›cÂ†ÂŸq#Ã•*\\bÂ§|Ã½$Â‹Ã“ÂÂ¡\\nÂ¹ÂkÃŒCqÂˆCÂ®ÃˆÃ`Ã›kÃ´Â‘Ã†Ã‹ÃgeÃŒ&\\ra ÂÂ´+dRCqÃ¡Â§Â­Dx^{ÂŸÂ˜ÃºÃ¦Â°Ã§TvWn0ÃˆÂ³ÃµÃ¶ttÂ«Â‚Â‘ÂƒÃŒsÃŠÃ¸Ã’YÂ\\fz8`uÂµÂ‰Â¨Â¬Ã Â²\\tÂ‹:Ã°\\nNÂ¦*#t-ÃÂºÃŸ{Â›Â¬Ã¥ÂÂ¬Ã¹.pgÂ¤Â®@JÃµQ~ÃœoÃ©Â‡Ã§Â·Â‘Â Â‹Ã€mÃ·\\bÃ®SÃ´Â“XgÂ¨6ÃÂ‡Â™Ã¿ÃŠÂ›Ã½Ãœvi{Âµ|AÂ§S%Ã³hÃˆÂ“Ãƒ](Ã­o!Ã‚yÂÂ°Â¯omZÂ´Ã®ÂˆÃ¬7\\fFÂ„ÃRQ3Z( Â…Â ÂÃˆÂ‘Ã¼Â‡Â•pÃ¶[ÂÃÃŸÂfÂ­ÂŸÃ¹Ã™:ÂµÂ¢iÂ³<>u*8Â¦Â­gVÂ¯Ã½Â¦Ã™XÃ½8wÂªBÂ˜Â“Ã½Ã»kdÃ¶3SÂ¢GlÃ\\n]m Ã´Â 6ÃˆÃ£Ã–Â¼_Ã°Â¦Â„ÃµÃ¦Ã´ÃaÃ»Ã´Ã¢Ã¥Â±Y?Âƒ2;\\nS.LÃ•ÂÂ‘`Â­mÃ¯cRfÃ•sÂ§ÃÃ² Ã—Ã­Ã±ÃÂª0{Ã¥]Ã™Ã¹Â€0\\rÂ ÃšÂ­ÃnÂ¹Ã·Â­Ã¥Â›yÂ½^5bIÂ—Â·Â‹Ã‘Â‚Â·(xwJ3\Ã»Ã\\n2Â²:Â¹wÃ©iB#"wMÂ‰XÃºÂ£! Â™DÃ’Ã¡xÂN1[Â‚ÃÃ,ÃºÂµÂ³<rÂ²=Â¦Ã°Ã¾Â§3Y,.YÂ‚TÂ”jJ48ÂªÂ±v!Â–vÃ£Ãy;QWÃ²::Ã¼Â½Â”Ã°Â”Â¥Â£qÃºÂ¯~Â¾8Ã˜| r;Â®@|Â§fu<GÃ€iÂ•3)ÃŒÃœÃ­Ã­SÂ¹Ã±ÃŸÃƒÂŒÂ…N_LÃ»Â³ÃºÂ Â´WÂÂ“Â€UÃ£ÃÃ”zÂ¹Â“Â‰;Ã—Ã¤Ã‰Â“#Â» ÂÂ­28SÂ¾Â±Ã­Â¼sÃ¤yÃ›Ã³Â½Ã“&yÃ¤Ã¹ÃÃq0Â—Â•Â¡ÃŸÂ²\\nb-Â±L&AÃ­Jm:Ã»ÂƒfÃŠJÃ£ÂÃŒ\\rBÂ³Â¤iÃ¦Â‘Â…_IÂ…ÃÂ¶esVÂ£Ã$Ã½(Y&ÃgÃºÃÃ‡Ã•Â¯<_{Ã¢iw"Ã„Ã²Â»3z&Ã½KKÃµZ#Â¯?lkv{Â†;Â¢Ã‹Ã¢SÃ…Â¤5eh\\nÃ¯Ã”Ã‚1_ÃÂ–ÃoÂ“@.ÃŠÂ™Ã™eÃµÃ‹PÃ‡Â…Â»Ã©ÂªÃ«\\tÂˆz)wÂ›+nÂºÃAÂ£?Ã—3Ã“ÃUÂ¾Z0ÃªÂ¡Â»kÃŒ,,\\bzoÂ¦.ÃÂ‰vÂŠÂ¬]LÂ‰+Ã€Â™\\rÃ¡f@Â—IÃ£Ã‚l eNbÂ'Â“L6Ã·AÂšJjKd=yÃ™DÂ€ZgÂ¤Â>Â†OÃ·Ã…rÂ¼Ã«tMÂ’Â¤qÂ£hÂ‚Ã¤BÃ¼Ã¥ÃˆÂ»<%qWÂ <:Z\\fÃ…Ã–Â¿Ã¾SÃ®Ã•fÂ¶Ã‡Â¯ÃºSÃ©uÂ¬+Ã‡@Â½Â°ÃUÃ€3_Â£\Ã#[|Ã€Ã§O1Ã£k~\\nAL\Ã˜Ã)Â¥Ã˜Â´Â‰ÂwZÂˆÂ¨]fÃŠZ*DÂ²Ã’(ImÃ²Ã¸*CÃ—Â·Â¨2Ã¨x9ÃšÂÂ™Â¡Ã•FTOÂšvÃ­Â¢Ã†2;Â\Â·Â©mÃŒÃº'\\bwÃ_bÂ“Â»Ã¹ÂÂ¤5Â¹PÂƒÂˆÃªÂ¶Âƒ\\rÃ‡zFJÂ‰Ã·Ãµ*ÂÂ¤Za}Â¹Ãœ l\\bÃµÂƒCTPÃÃŸ5Â™ÂƒÃ¶ÃkÂŠgÂ½Ã§'J|ÃºÃ°Ã£rÃ¾Ã—WÃ‡Ã‰UÂ‚Â›Â¨?4w9CvÂ¾Ã ÃeÃªÂ¢Â¹;:EnÂ®Ã›ÂxÂÃ”Â¶+AÃÃ²Ãµ)Ã³Â¦IÂ…Ã›&bÂªpvÂ¤0\\tÂ¼NÂ¼Â´Â°Âº#ÂÃ¦Ã¿Â©Â¥Â¯Ã Ã‡ÂÃ’Â¯B|Â„ÂÂ¸PÃ\\bÂˆ|Ã•\\tnÂ–Â·ÃˆfIÂ©ÂœÃŠÂ°#\\f\\t}#Ã•~*Ã’Ã†qÂ«'
    //   129: dup
    //   130: astore_2
    //   131: invokevirtual length : ()I
    //   134: istore #4
    //   136: bipush #9
    //   138: istore_1
    //   139: iconst_m1
    //   140: istore_0
    //   141: iconst_2
    //   142: iinc #0, 1
    //   145: aload_2
    //   146: iload_0
    //   147: dup
    //   148: iload_1
    //   149: iadd
    //   150: invokevirtual substring : (II)Ljava/lang/String;
    //   153: iconst_1
    //   154: goto -> 201
    //   157: aload #5
    //   159: swap
    //   160: iload_3
    //   161: iinc #3, 1
    //   164: swap
    //   165: aastore
    //   166: iload_0
    //   167: iload_1
    //   168: iadd
    //   169: dup
    //   170: istore_0
    //   171: iload #4
    //   173: if_icmpge -> 185
    //   176: aload_2
    //   177: iload_0
    //   178: invokevirtual charAt : (I)C
    //   181: istore_1
    //   182: goto -> 141
    //   185: aload #5
    //   187: putstatic burp/Zg64.a : [Ljava/lang/String;
    //   190: bipush #9
    //   192: anewarray java/lang/String
    //   195: putstatic burp/Zg64.b : [Ljava/lang/String;
    //   198: goto -> 364
    //   201: dup_x2
    //   202: pop
    //   203: invokevirtual toCharArray : ()[C
    //   206: dup_x1
    //   207: arraylength
    //   208: dup_x2
    //   209: pop
    //   210: iconst_0
    //   211: istore #6
    //   213: dup2_x1
    //   214: pop2
    //   215: dup_x2
    //   216: iconst_1
    //   217: if_icmpgt -> 320
    //   220: dup2
    //   221: swap
    //   222: iload #6
    //   224: dup2_x1
    //   225: caload
    //   226: swap
    //   227: iload #6
    //   229: bipush #7
    //   231: irem
    //   232: tableswitch default -> 302, 0 -> 272, 1 -> 277, 2 -> 282, 3 -> 287, 4 -> 292, 5 -> 297
    //   272: bipush #65
    //   274: goto -> 304
    //   277: bipush #95
    //   279: goto -> 304
    //   282: bipush #76
    //   284: goto -> 304
    //   287: bipush #24
    //   289: goto -> 304
    //   292: bipush #73
    //   294: goto -> 304
    //   297: bipush #120
    //   299: goto -> 304
    //   302: bipush #119
    //   304: ixor
    //   305: ixor
    //   306: i2c
    //   307: castore
    //   308: iinc #6, 1
    //   311: dup
    //   312: ifne -> 320
    //   315: dup2
    //   316: dup_x1
    //   317: goto -> 224
    //   320: dup2_x1
    //   321: pop2
    //   322: dup_x2
    //   323: iload #6
    //   325: if_icmpgt -> 220
    //   328: pop
    //   329: new java/lang/String
    //   332: dup_x1
    //   333: swap
    //   334: invokespecial <init> : ([C)V
    //   337: invokevirtual intern : ()Ljava/lang/String;
    //   340: swap
    //   341: pop
    //   342: swap
    //   343: tableswitch default -> 39, 0 -> 99, 1 -> 157
    //   364: sipush #-10366
    //   367: sipush #18910
    //   370: invokestatic a : (II)Ljava/lang/String;
    //   373: putstatic burp/Zg64.Zv : Ljava/lang/String;
    //   376: getstatic burp/Zg64.Zv : Ljava/lang/String;
    //   379: sipush #-10362
    //   382: sipush #11323
    //   385: invokestatic a : (II)Ljava/lang/String;
    //   388: <illegal opcode> makeConcatWithConstants : (Ljava/lang/String;Ljava/lang/String;)Ljava/lang/String;
    //   393: putstatic burp/Zg64.Zv : Ljava/lang/String;
    //   396: new java/math/BigInteger
    //   399: dup
    //   400: bipush #32
    //   402: newarray byte
    //   404: dup
    //   405: iconst_0
    //   406: bipush #11
    //   408: bastore
    //   409: dup
    //   410: iconst_1
    //   411: bipush #-72
    //   413: bastore
    //   414: dup
    //   415: iconst_2
    //   416: bipush #-86
    //   418: bastore
    //   419: dup
    //   420: iconst_3
    //   421: bipush #-8
    //   423: bastore
    //   424: dup
    //   425: iconst_4
    //   426: bipush #17
    //   428: bastore
    //   429: dup
    //   430: iconst_5
    //   431: bipush #23
    //   433: bastore
    //   434: dup
    //   435: bipush #6
    //   437: bipush #-16
    //   439: bastore
    //   440: dup
    //   441: bipush #7
    //   443: bipush #119
    //   445: bastore
    //   446: dup
    //   447: bipush #8
    //   449: bipush #-110
    //   451: bastore
    //   452: dup
    //   453: bipush #9
    //   455: bipush #109
    //   457: bastore
    //   458: dup
    //   459: bipush #10
    //   461: bipush #-4
    //   463: bastore
    //   464: dup
    //   465: bipush #11
    //   467: bipush #-118
    //   469: bastore
    //   470: dup
    //   471: bipush #12
    //   473: bipush #-55
    //   475: bastore
    //   476: dup
    //   477: bipush #13
    //   479: bipush #12
    //   481: bastore
    //   482: dup
    //   483: bipush #14
    //   485: bipush #15
    //   487: bastore
    //   488: dup
    //   489: bipush #15
    //   491: bipush #-110
    //   493: bastore
    //   494: dup
    //   495: bipush #16
    //   497: bipush #22
    //   499: bastore
    //   500: dup
    //   501: bipush #17
    //   503: bipush #73
    //   505: bastore
    //   506: dup
    //   507: bipush #18
    //   509: bipush #48
    //   511: bastore
    //   512: dup
    //   513: bipush #19
    //   515: bipush #-113
    //   517: bastore
    //   518: dup
    //   519: bipush #20
    //   521: bipush #109
    //   523: bastore
    //   524: dup
    //   525: bipush #21
    //   527: bipush #98
    //   529: bastore
    //   530: dup
    //   531: bipush #22
    //   533: bipush #-105
    //   535: bastore
    //   536: dup
    //   537: bipush #23
    //   539: bipush #-122
    //   541: bastore
    //   542: dup
    //   543: bipush #24
    //   545: bipush #-80
    //   547: bastore
    //   548: dup
    //   549: bipush #25
    //   551: bipush #-106
    //   553: bastore
    //   554: dup
    //   555: bipush #26
    //   557: bipush #72
    //   559: bastore
    //   560: dup
    //   561: bipush #27
    //   563: bipush #-118
    //   565: bastore
    //   566: dup
    //   567: bipush #28
    //   569: bipush #-7
    //   571: bastore
    //   572: dup
    //   573: bipush #29
    //   575: bipush #-9
    //   577: bastore
    //   578: dup
    //   579: bipush #30
    //   581: bipush #123
    //   583: bastore
    //   584: dup
    //   585: bipush #31
    //   587: bipush #-92
    //   589: bastore
    //   590: invokespecial <init> : ([B)V
    //   593: putstatic burp/Zg64.Zs : Ljava/lang/Object;
    //   596: return
  }
  
  private static Throwable a(Throwable paramThrowable) {
    return paramThrowable;
  }
  
  private static String a(int paramInt1, int paramInt2) {
    int i = (paramInt1 ^ 0xFFFFD783) & 0xFFFF;
    if (b[i] == null) {
      char[] arrayOfChar = a[i].toCharArray();
      switch (arrayOfChar[0] & 0xFF) {
        case 0:
        
        case 1:
        
        case 2:
        
        case 3:
        
        case 4:
        
        case 5:
        
        case 6:
        
        case 7:
        
        case 8:
        
        case 9:
        
        case 10:
        
        case 11:
        
        case 12:
        
        case 13:
        
        case 14:
        
        case 15:
        
        case 16:
        
        case 17:
        
        case 18:
        
        case 19:
        
        case 20:
        
        case 21:
        
        case 22:
        
        case 23:
        
        case 24:
        
        case 25:
        
        case 26:
        
        case 27:
        
        case 28:
        
        case 29:
        
        case 30:
        
        case 31:
        
        case 32:
        
        case 33:
        
        case 34:
        
        case 35:
        
        case 36:
        
        case 37:
        
        case 38:
        
        case 39:
        
        case 40:
        
        case 41:
        
        case 42:
        
        case 43:
        
        case 44:
        
        case 45:
        
        case 46:
        
        case 47:
        
        case 48:
        
        case 49:
        
        case 50:
        
        case 51:
        
        case 52:
        
        case 53:
        
        case 54:
        
        case 55:
        
        case 56:
        
        case 57:
        
        case 58:
        
        case 59:
        
        case 60:
        
        case 61:
        
        case 62:
        
        case 63:
        
        case 64:
        
        case 65:
        
        case 66:
        
        case 67:
        
        case 68:
        
        case 69:
        
        case 70:
        
        case 71:
        
        case 72:
        
        case 73:
        
        case 74:
        
        case 75:
        
        case 76:
        
        case 77:
        
        case 78:
        
        case 79:
        
        case 80:
        
        case 81:
        
        case 82:
        
        case 83:
        
        case 84:
        
        case 85:
        
        case 86:
        
        case 87:
        
        case 88:
        
        case 89:
        
        case 90:
        
        case 91:
        
        case 92:
        
        case 93:
        
        case 94:
        
        case 95:
        
        case 96:
        
        case 97:
        
        case 98:
        
        case 99:
        
        case 100:
        
        case 101:
        
        case 102:
        
        case 103:
        
        case 104:
        
        case 105:
        
        case 106:
        
        case 107:
        
        case 108:
        
        case 109:
        
        case 110:
        
        case 111:
        
        case 112:
        
        case 113:
        
        case 114:
        
        case 115:
        
        case 116:
        
        case 117:
        
        case 118:
        
        case 119:
        
        case 120:
        
        case 121:
        
        case 122:
        
        case 123:
        
        case 124:
        
        case 125:
        
        case 126:
        
        case 127:
        
        case 128:
        
        case 129:
        
        case 130:
        
        case 131:
        
        case 132:
        
        case 133:
        
        case 134:
        
        case 135:
        
        case 136:
        
        case 137:
        
        case 138:
        
        case 139:
        
        case 140:
        
        case 141:
        
        case 142:
        
        case 143:
        
        case 144:
        
        case 145:
        
        case 146:
        
        case 147:
        
        case 148:
        
        case 149:
        
        case 150:
        
        case 151:
        
        case 152:
        
        case 153:
        
        case 154:
        
        case 155:
        
        case 156:
        
        case 157:
        
        case 158:
        
        case 159:
        
        case 160:
        
        case 161:
        
        case 162:
        
        case 163:
        
        case 164:
        
        case 165:
        
        case 166:
        
        case 167:
        
        case 168:
        
        case 169:
        
        case 170:
        
        case 171:
        
        case 172:
        
        case 173:
        
        case 174:
        
        case 175:
        
        case 176:
        
        case 177:
        
        case 178:
        
        case 179:
        
        case 180:
        
        case 181:
        
        case 182:
        
        case 183:
        
        case 184:
        
        case 185:
        
        case 186:
        
        case 187:
        
        case 188:
        
        case 189:
        
        case 190:
        
        case 191:
        
        case 192:
        
        case 193:
        
        case 194:
        
        case 195:
        
        case 196:
        
        case 197:
        
        case 198:
        
        case 199:
        
        case 200:
        
        case 201:
        
        case 202:
        
        case 203:
        
        case 204:
        
        case 205:
        
        case 206:
        
        case 207:
        
        case 208:
        
        case 209:
        
        case 210:
        
        case 211:
        
        case 212:
        
        case 213:
        
        case 214:
        
        case 215:
        
        case 216:
        
        case 217:
        
        case 218:
        
        case 219:
        
        case 220:
        
        case 221:
        
        case 222:
        
        case 223:
        
        case 224:
        
        case 225:
        
        case 226:
        
        case 227:
        
        case 228:
        
        case 229:
        
        case 230:
        
        case 231:
        
        case 232:
        
        case 233:
        
        case 234:
        
        case 235:
        
        case 236:
        
        case 237:
        
        case 238:
        
        case 239:
        
        case 240:
        
        case 241:
        
        case 242:
        
        case 243:
        
        case 244:
        
        case 245:
        
        case 246:
        
        case 247:
        
        case 248:
        
        case 249:
        
        case 250:
        
        case 251:
        
        case 252:
        
        case 253:
        
        case 254:
        
        default:
          break;
      } 
      byte b1 = 76;
      int j = (paramInt2 & 0xFF) - b1;
      if (j < 0)
        j += 256; 
      int k = ((paramInt2 & 0xFFFF) >>> 8) - b1;
      if (k < 0)
        k += 256; 
      for (byte b2 = 0; b2 < arrayOfChar.length; b2++) {
        int m = b2 % 2;
        if (m == 0) {
          arrayOfChar[b2] = (char)(arrayOfChar[b2] ^ j);
          j = ((j >>> 3 | j << 5) ^ arrayOfChar[b2]) & 0xFF;
        } else {
          arrayOfChar[b2] = (char)(arrayOfChar[b2] ^ k);
          k = ((k >>> 3 | k << 5) ^ arrayOfChar[b2]) & 0xFF;
        } 
      } 
      b[i] = (new String(arrayOfChar)).intern();
    } 
    return b[i];
  }
}


/* Location:              C:\Program Files\BurpSuitePro\burpsuite_pro.jar!\burp\Zg64.class
 * Java compiler version: 21 (65.0)
 * JD-Core Version:       1.1.3
 */