package burp;

import java.math.BigInteger;

class Zg7j extends ClassLoader {
  static String ZR;
  
  static Object Zr;
  
  private static final String[] a;
  
  private static final String[] b;
  
  static boolean Zk(Object[] paramArrayOfObject, Object paramObject) throws Throwable {
    // Byte code:
    //   0: invokestatic ZK : ()Z
    //   3: istore_2
    //   4: new java/lang/StringBuilder
    //   7: dup
    //   8: invokespecial <init> : ()V
    //   11: astore_3
    //   12: iconst_0
    //   13: istore #4
    //   15: iload #4
    //   17: bipush #32
    //   19: if_icmpge -> 1355
    //   22: iload #4
    //   24: tableswitch default -> 1348, 0 -> 168, 1 -> 205, 2 -> 242, 3 -> 279, 4 -> 316, 5 -> 353, 6 -> 390, 7 -> 427, 8 -> 464, 9 -> 501, 10 -> 538, 11 -> 575, 12 -> 612, 13 -> 649, 14 -> 686, 15 -> 723, 16 -> 760, 17 -> 797, 18 -> 834, 19 -> 871, 20 -> 908, 21 -> 945, 22 -> 982, 23 -> 1019, 24 -> 1056, 25 -> 1093, 26 -> 1130, 27 -> 1167, 28 -> 1204, 29 -> 1241, 30 -> 1278, 31 -> 1315
    //   168: aload_3
    //   169: getstatic burp/Zm3x.Zu : Ljava/lang/String;
    //   172: getstatic burp/Zrhp.Zw : Ljava/lang/Object;
    //   175: checkcast java/math/BigInteger
    //   178: invokevirtual intValue : ()I
    //   181: bipush #32
    //   183: irem
    //   184: invokestatic abs : (I)I
    //   187: invokevirtual charAt : (I)C
    //   190: invokevirtual append : (C)Ljava/lang/StringBuilder;
    //   193: pop
    //   194: iload_2
    //   195: ifeq -> 1348
    //   198: goto -> 205
    //   201: invokestatic a : (Ljava/lang/Throwable;)Ljava/lang/Throwable;
    //   204: athrow
    //   205: aload_3
    //   206: getstatic burp/Zzou.ZN : Ljava/lang/String;
    //   209: getstatic burp/Zgcg.Zi : Ljava/lang/Object;
    //   212: checkcast java/math/BigInteger
    //   215: invokevirtual intValue : ()I
    //   218: bipush #32
    //   220: irem
    //   221: invokestatic abs : (I)I
    //   224: invokevirtual charAt : (I)C
    //   227: invokevirtual append : (C)Ljava/lang/StringBuilder;
    //   230: pop
    //   231: iload_2
    //   232: ifeq -> 1348
    //   235: goto -> 242
    //   238: invokestatic a : (Ljava/lang/Throwable;)Ljava/lang/Throwable;
    //   241: athrow
    //   242: aload_3
    //   243: getstatic burp/Zkfb.ZV : Ljava/lang/String;
    //   246: getstatic burp/Zs6g.Zq : Ljava/lang/Object;
    //   249: checkcast java/math/BigInteger
    //   252: invokevirtual intValue : ()I
    //   255: bipush #32
    //   257: irem
    //   258: invokestatic abs : (I)I
    //   261: invokevirtual charAt : (I)C
    //   264: invokevirtual append : (C)Ljava/lang/StringBuilder;
    //   267: pop
    //   268: iload_2
    //   269: ifeq -> 1348
    //   272: goto -> 279
    //   275: invokestatic a : (Ljava/lang/Throwable;)Ljava/lang/Throwable;
    //   278: athrow
    //   279: aload_3
    //   280: getstatic burp/Zzyr.Z_ : Ljava/lang/String;
    //   283: getstatic burp/Zxk9.ZI : Ljava/lang/Object;
    //   286: checkcast java/math/BigInteger
    //   289: invokevirtual intValue : ()I
    //   292: bipush #32
    //   294: irem
    //   295: invokestatic abs : (I)I
    //   298: invokevirtual charAt : (I)C
    //   301: invokevirtual append : (C)Ljava/lang/StringBuilder;
    //   304: pop
    //   305: iload_2
    //   306: ifeq -> 1348
    //   309: goto -> 316
    //   312: invokestatic a : (Ljava/lang/Throwable;)Ljava/lang/Throwable;
    //   315: athrow
    //   316: aload_3
    //   317: getstatic burp/Zxx4.Zq : Ljava/lang/String;
    //   320: getstatic burp/Zeor.Zb : Ljava/lang/Object;
    //   323: checkcast java/math/BigInteger
    //   326: invokevirtual intValue : ()I
    //   329: bipush #32
    //   331: irem
    //   332: invokestatic abs : (I)I
    //   335: invokevirtual charAt : (I)C
    //   338: invokevirtual append : (C)Ljava/lang/StringBuilder;
    //   341: pop
    //   342: iload_2
    //   343: ifeq -> 1348
    //   346: goto -> 353
    //   349: invokestatic a : (Ljava/lang/Throwable;)Ljava/lang/Throwable;
    //   352: athrow
    //   353: aload_3
    //   354: getstatic burp/Zmv9.Zm : Ljava/lang/String;
    //   357: getstatic burp/Zm__.Zz : Ljava/lang/Object;
    //   360: checkcast java/math/BigInteger
    //   363: invokevirtual intValue : ()I
    //   366: bipush #32
    //   368: irem
    //   369: invokestatic abs : (I)I
    //   372: invokevirtual charAt : (I)C
    //   375: invokevirtual append : (C)Ljava/lang/StringBuilder;
    //   378: pop
    //   379: iload_2
    //   380: ifeq -> 1348
    //   383: goto -> 390
    //   386: invokestatic a : (Ljava/lang/Throwable;)Ljava/lang/Throwable;
    //   389: athrow
    //   390: aload_3
    //   391: getstatic burp/Zzo5.ZX : Ljava/lang/String;
    //   394: getstatic burp/Zead.ZI : Ljava/lang/Object;
    //   397: checkcast java/math/BigInteger
    //   400: invokevirtual intValue : ()I
    //   403: bipush #32
    //   405: irem
    //   406: invokestatic abs : (I)I
    //   409: invokevirtual charAt : (I)C
    //   412: invokevirtual append : (C)Ljava/lang/StringBuilder;
    //   415: pop
    //   416: iload_2
    //   417: ifeq -> 1348
    //   420: goto -> 427
    //   423: invokestatic a : (Ljava/lang/Throwable;)Ljava/lang/Throwable;
    //   426: athrow
    //   427: aload_3
    //   428: getstatic burp/Zbp.Z_ : Ljava/lang/String;
    //   431: getstatic burp/Zzpu.ZS : Ljava/lang/Object;
    //   434: checkcast java/math/BigInteger
    //   437: invokevirtual intValue : ()I
    //   440: bipush #32
    //   442: irem
    //   443: invokestatic abs : (I)I
    //   446: invokevirtual charAt : (I)C
    //   449: invokevirtual append : (C)Ljava/lang/StringBuilder;
    //   452: pop
    //   453: iload_2
    //   454: ifeq -> 1348
    //   457: goto -> 464
    //   460: invokestatic a : (Ljava/lang/Throwable;)Ljava/lang/Throwable;
    //   463: athrow
    //   464: aload_3
    //   465: getstatic burp/Zxn9.ZU : Ljava/lang/String;
    //   468: getstatic burp/Zlos.Zk : Ljava/lang/Object;
    //   471: checkcast java/math/BigInteger
    //   474: invokevirtual intValue : ()I
    //   477: bipush #32
    //   479: irem
    //   480: invokestatic abs : (I)I
    //   483: invokevirtual charAt : (I)C
    //   486: invokevirtual append : (C)Ljava/lang/StringBuilder;
    //   489: pop
    //   490: iload_2
    //   491: ifeq -> 1348
    //   494: goto -> 501
    //   497: invokestatic a : (Ljava/lang/Throwable;)Ljava/lang/Throwable;
    //   500: athrow
    //   501: aload_3
    //   502: getstatic burp/Zeuz.Zb : Ljava/lang/String;
    //   505: getstatic burp/Zs9k.ZX : Ljava/lang/Object;
    //   508: checkcast java/math/BigInteger
    //   511: invokevirtual intValue : ()I
    //   514: bipush #32
    //   516: irem
    //   517: invokestatic abs : (I)I
    //   520: invokevirtual charAt : (I)C
    //   523: invokevirtual append : (C)Ljava/lang/StringBuilder;
    //   526: pop
    //   527: iload_2
    //   528: ifeq -> 1348
    //   531: goto -> 538
    //   534: invokestatic a : (Ljava/lang/Throwable;)Ljava/lang/Throwable;
    //   537: athrow
    //   538: aload_3
    //   539: getstatic burp/Zm81.ZY : Ljava/lang/String;
    //   542: getstatic burp/Zl15.Zn : Ljava/lang/Object;
    //   545: checkcast java/math/BigInteger
    //   548: invokevirtual intValue : ()I
    //   551: bipush #32
    //   553: irem
    //   554: invokestatic abs : (I)I
    //   557: invokevirtual charAt : (I)C
    //   560: invokevirtual append : (C)Ljava/lang/StringBuilder;
    //   563: pop
    //   564: iload_2
    //   565: ifeq -> 1348
    //   568: goto -> 575
    //   571: invokestatic a : (Ljava/lang/Throwable;)Ljava/lang/Throwable;
    //   574: athrow
    //   575: aload_3
    //   576: getstatic burp/Zx4k.ZC : Ljava/lang/String;
    //   579: getstatic burp/Zbo7.Zl : Ljava/lang/Object;
    //   582: checkcast java/math/BigInteger
    //   585: invokevirtual intValue : ()I
    //   588: bipush #32
    //   590: irem
    //   591: invokestatic abs : (I)I
    //   594: invokevirtual charAt : (I)C
    //   597: invokevirtual append : (C)Ljava/lang/StringBuilder;
    //   600: pop
    //   601: iload_2
    //   602: ifeq -> 1348
    //   605: goto -> 612
    //   608: invokestatic a : (Ljava/lang/Throwable;)Ljava/lang/Throwable;
    //   611: athrow
    //   612: aload_3
    //   613: getstatic burp/Zg27.ZP : Ljava/lang/String;
    //   616: getstatic burp/Zzr5.Za : Ljava/lang/Object;
    //   619: checkcast java/math/BigInteger
    //   622: invokevirtual intValue : ()I
    //   625: bipush #32
    //   627: irem
    //   628: invokestatic abs : (I)I
    //   631: invokevirtual charAt : (I)C
    //   634: invokevirtual append : (C)Ljava/lang/StringBuilder;
    //   637: pop
    //   638: iload_2
    //   639: ifeq -> 1348
    //   642: goto -> 649
    //   645: invokestatic a : (Ljava/lang/Throwable;)Ljava/lang/Throwable;
    //   648: athrow
    //   649: aload_3
    //   650: getstatic burp/Ztnw.Zr : Ljava/lang/String;
    //   653: getstatic burp/Zxt5.ZG : Ljava/lang/Object;
    //   656: checkcast java/math/BigInteger
    //   659: invokevirtual intValue : ()I
    //   662: bipush #32
    //   664: irem
    //   665: invokestatic abs : (I)I
    //   668: invokevirtual charAt : (I)C
    //   671: invokevirtual append : (C)Ljava/lang/StringBuilder;
    //   674: pop
    //   675: iload_2
    //   676: ifeq -> 1348
    //   679: goto -> 686
    //   682: invokestatic a : (Ljava/lang/Throwable;)Ljava/lang/Throwable;
    //   685: athrow
    //   686: aload_3
    //   687: getstatic burp/Zle6.Zh : Ljava/lang/String;
    //   690: getstatic burp/Ztkh.Zh : Ljava/lang/Object;
    //   693: checkcast java/math/BigInteger
    //   696: invokevirtual intValue : ()I
    //   699: bipush #32
    //   701: irem
    //   702: invokestatic abs : (I)I
    //   705: invokevirtual charAt : (I)C
    //   708: invokevirtual append : (C)Ljava/lang/StringBuilder;
    //   711: pop
    //   712: iload_2
    //   713: ifeq -> 1348
    //   716: goto -> 723
    //   719: invokestatic a : (Ljava/lang/Throwable;)Ljava/lang/Throwable;
    //   722: athrow
    //   723: aload_3
    //   724: getstatic burp/Zxyq.Zr : Ljava/lang/String;
    //   727: getstatic burp/Zbzk.ZI : Ljava/lang/Object;
    //   730: checkcast java/math/BigInteger
    //   733: invokevirtual intValue : ()I
    //   736: bipush #32
    //   738: irem
    //   739: invokestatic abs : (I)I
    //   742: invokevirtual charAt : (I)C
    //   745: invokevirtual append : (C)Ljava/lang/StringBuilder;
    //   748: pop
    //   749: iload_2
    //   750: ifeq -> 1348
    //   753: goto -> 760
    //   756: invokestatic a : (Ljava/lang/Throwable;)Ljava/lang/Throwable;
    //   759: athrow
    //   760: aload_3
    //   761: getstatic burp/Zs_3.ZC : Ljava/lang/String;
    //   764: getstatic burp/Ztes.ZX : Ljava/lang/Object;
    //   767: checkcast java/math/BigInteger
    //   770: invokevirtual intValue : ()I
    //   773: bipush #32
    //   775: irem
    //   776: invokestatic abs : (I)I
    //   779: invokevirtual charAt : (I)C
    //   782: invokevirtual append : (C)Ljava/lang/StringBuilder;
    //   785: pop
    //   786: iload_2
    //   787: ifeq -> 1348
    //   790: goto -> 797
    //   793: invokestatic a : (Ljava/lang/Throwable;)Ljava/lang/Throwable;
    //   796: athrow
    //   797: aload_3
    //   798: getstatic burp/Zxjw.Zv : Ljava/lang/String;
    //   801: getstatic burp/Zg68.Zs : Ljava/lang/Object;
    //   804: checkcast java/math/BigInteger
    //   807: invokevirtual intValue : ()I
    //   810: bipush #32
    //   812: irem
    //   813: invokestatic abs : (I)I
    //   816: invokevirtual charAt : (I)C
    //   819: invokevirtual append : (C)Ljava/lang/StringBuilder;
    //   822: pop
    //   823: iload_2
    //   824: ifeq -> 1348
    //   827: goto -> 834
    //   830: invokestatic a : (Ljava/lang/Throwable;)Ljava/lang/Throwable;
    //   833: athrow
    //   834: aload_3
    //   835: getstatic burp/Zlh2.Zf : Ljava/lang/String;
    //   838: getstatic burp/Zmh5.ZN : Ljava/lang/Object;
    //   841: checkcast java/math/BigInteger
    //   844: invokevirtual intValue : ()I
    //   847: bipush #32
    //   849: irem
    //   850: invokestatic abs : (I)I
    //   853: invokevirtual charAt : (I)C
    //   856: invokevirtual append : (C)Ljava/lang/StringBuilder;
    //   859: pop
    //   860: iload_2
    //   861: ifeq -> 1348
    //   864: goto -> 871
    //   867: invokestatic a : (Ljava/lang/Throwable;)Ljava/lang/Throwable;
    //   870: athrow
    //   871: aload_3
    //   872: getstatic burp/Zmr7.Zo : Ljava/lang/String;
    //   875: getstatic burp/Zs8q.ZI : Ljava/lang/Object;
    //   878: checkcast java/math/BigInteger
    //   881: invokevirtual intValue : ()I
    //   884: bipush #32
    //   886: irem
    //   887: invokestatic abs : (I)I
    //   890: invokevirtual charAt : (I)C
    //   893: invokevirtual append : (C)Ljava/lang/StringBuilder;
    //   896: pop
    //   897: iload_2
    //   898: ifeq -> 1348
    //   901: goto -> 908
    //   904: invokestatic a : (Ljava/lang/Throwable;)Ljava/lang/Throwable;
    //   907: athrow
    //   908: aload_3
    //   909: getstatic burp/Zltz.Za : Ljava/lang/String;
    //   912: getstatic burp/Zg5.Zs : Ljava/lang/Object;
    //   915: checkcast java/math/BigInteger
    //   918: invokevirtual intValue : ()I
    //   921: bipush #32
    //   923: irem
    //   924: invokestatic abs : (I)I
    //   927: invokevirtual charAt : (I)C
    //   930: invokevirtual append : (C)Ljava/lang/StringBuilder;
    //   933: pop
    //   934: iload_2
    //   935: ifeq -> 1348
    //   938: goto -> 945
    //   941: invokestatic a : (Ljava/lang/Throwable;)Ljava/lang/Throwable;
    //   944: athrow
    //   945: aload_3
    //   946: getstatic burp/Zsji.Zr : Ljava/lang/String;
    //   949: getstatic burp/Zbxp.ZW : Ljava/lang/Object;
    //   952: checkcast java/math/BigInteger
    //   955: invokevirtual intValue : ()I
    //   958: bipush #32
    //   960: irem
    //   961: invokestatic abs : (I)I
    //   964: invokevirtual charAt : (I)C
    //   967: invokevirtual append : (C)Ljava/lang/StringBuilder;
    //   970: pop
    //   971: iload_2
    //   972: ifeq -> 1348
    //   975: goto -> 982
    //   978: invokestatic a : (Ljava/lang/Throwable;)Ljava/lang/Throwable;
    //   981: athrow
    //   982: aload_3
    //   983: getstatic burp/Zlna.Zo : Ljava/lang/String;
    //   986: getstatic burp/Ze57.ZR : Ljava/lang/Object;
    //   989: checkcast java/math/BigInteger
    //   992: invokevirtual intValue : ()I
    //   995: bipush #32
    //   997: irem
    //   998: invokestatic abs : (I)I
    //   1001: invokevirtual charAt : (I)C
    //   1004: invokevirtual append : (C)Ljava/lang/StringBuilder;
    //   1007: pop
    //   1008: iload_2
    //   1009: ifeq -> 1348
    //   1012: goto -> 1019
    //   1015: invokestatic a : (Ljava/lang/Throwable;)Ljava/lang/Throwable;
    //   1018: athrow
    //   1019: aload_3
    //   1020: getstatic burp/Zkfb.ZV : Ljava/lang/String;
    //   1023: getstatic burp/Zlna.ZG : Ljava/lang/Object;
    //   1026: checkcast java/math/BigInteger
    //   1029: invokevirtual intValue : ()I
    //   1032: bipush #32
    //   1034: irem
    //   1035: invokestatic abs : (I)I
    //   1038: invokevirtual charAt : (I)C
    //   1041: invokevirtual append : (C)Ljava/lang/StringBuilder;
    //   1044: pop
    //   1045: iload_2
    //   1046: ifeq -> 1348
    //   1049: goto -> 1056
    //   1052: invokestatic a : (Ljava/lang/Throwable;)Ljava/lang/Throwable;
    //   1055: athrow
    //   1056: aload_3
    //   1057: getstatic burp/Zrw7.Zo : Ljava/lang/String;
    //   1060: getstatic burp/Zl4v.ZT : Ljava/lang/Object;
    //   1063: checkcast java/math/BigInteger
    //   1066: invokevirtual intValue : ()I
    //   1069: bipush #32
    //   1071: irem
    //   1072: invokestatic abs : (I)I
    //   1075: invokevirtual charAt : (I)C
    //   1078: invokevirtual append : (C)Ljava/lang/StringBuilder;
    //   1081: pop
    //   1082: iload_2
    //   1083: ifeq -> 1348
    //   1086: goto -> 1093
    //   1089: invokestatic a : (Ljava/lang/Throwable;)Ljava/lang/Throwable;
    //   1092: athrow
    //   1093: aload_3
    //   1094: getstatic burp/Zsm3.Zl : Ljava/lang/String;
    //   1097: getstatic burp/Zzok.ZY : Ljava/lang/Object;
    //   1100: checkcast java/math/BigInteger
    //   1103: invokevirtual intValue : ()I
    //   1106: bipush #32
    //   1108: irem
    //   1109: invokestatic abs : (I)I
    //   1112: invokevirtual charAt : (I)C
    //   1115: invokevirtual append : (C)Ljava/lang/StringBuilder;
    //   1118: pop
    //   1119: iload_2
    //   1120: ifeq -> 1348
    //   1123: goto -> 1130
    //   1126: invokestatic a : (Ljava/lang/Throwable;)Ljava/lang/Throwable;
    //   1129: athrow
    //   1130: aload_3
    //   1131: getstatic burp/Zg97.ZX : Ljava/lang/String;
    //   1134: getstatic burp/Zg8.ZX : Ljava/lang/Object;
    //   1137: checkcast java/math/BigInteger
    //   1140: invokevirtual intValue : ()I
    //   1143: bipush #32
    //   1145: irem
    //   1146: invokestatic abs : (I)I
    //   1149: invokevirtual charAt : (I)C
    //   1152: invokevirtual append : (C)Ljava/lang/StringBuilder;
    //   1155: pop
    //   1156: iload_2
    //   1157: ifeq -> 1348
    //   1160: goto -> 1167
    //   1163: invokestatic a : (Ljava/lang/Throwable;)Ljava/lang/Throwable;
    //   1166: athrow
    //   1167: aload_3
    //   1168: getstatic burp/Zrd4.Zg : Ljava/lang/String;
    //   1171: getstatic burp/Zlo2.ZM : Ljava/lang/Object;
    //   1174: checkcast java/math/BigInteger
    //   1177: invokevirtual intValue : ()I
    //   1180: bipush #32
    //   1182: irem
    //   1183: invokestatic abs : (I)I
    //   1186: invokevirtual charAt : (I)C
    //   1189: invokevirtual append : (C)Ljava/lang/StringBuilder;
    //   1192: pop
    //   1193: iload_2
    //   1194: ifeq -> 1348
    //   1197: goto -> 1204
    //   1200: invokestatic a : (Ljava/lang/Throwable;)Ljava/lang/Throwable;
    //   1203: athrow
    //   1204: aload_3
    //   1205: getstatic burp/Zx58.Zs : Ljava/lang/String;
    //   1208: getstatic burp/Zex.ZO : Ljava/lang/Object;
    //   1211: checkcast java/math/BigInteger
    //   1214: invokevirtual intValue : ()I
    //   1217: bipush #32
    //   1219: irem
    //   1220: invokestatic abs : (I)I
    //   1223: invokevirtual charAt : (I)C
    //   1226: invokevirtual append : (C)Ljava/lang/StringBuilder;
    //   1229: pop
    //   1230: iload_2
    //   1231: ifeq -> 1348
    //   1234: goto -> 1241
    //   1237: invokestatic a : (Ljava/lang/Throwable;)Ljava/lang/Throwable;
    //   1240: athrow
    //   1241: aload_3
    //   1242: getstatic burp/Zg27.ZP : Ljava/lang/String;
    //   1245: getstatic burp/Zssb.ZW : Ljava/lang/Object;
    //   1248: checkcast java/math/BigInteger
    //   1251: invokevirtual intValue : ()I
    //   1254: bipush #32
    //   1256: irem
    //   1257: invokestatic abs : (I)I
    //   1260: invokevirtual charAt : (I)C
    //   1263: invokevirtual append : (C)Ljava/lang/StringBuilder;
    //   1266: pop
    //   1267: iload_2
    //   1268: ifeq -> 1348
    //   1271: goto -> 1278
    //   1274: invokestatic a : (Ljava/lang/Throwable;)Ljava/lang/Throwable;
    //   1277: athrow
    //   1278: aload_3
    //   1279: getstatic burp/Zeju.ZR : Ljava/lang/String;
    //   1282: getstatic burp/Zz4r.ZQ : Ljava/lang/Object;
    //   1285: checkcast java/math/BigInteger
    //   1288: invokevirtual intValue : ()I
    //   1291: bipush #32
    //   1293: irem
    //   1294: invokestatic abs : (I)I
    //   1297: invokevirtual charAt : (I)C
    //   1300: invokevirtual append : (C)Ljava/lang/StringBuilder;
    //   1303: pop
    //   1304: iload_2
    //   1305: ifeq -> 1348
    //   1308: goto -> 1315
    //   1311: invokestatic a : (Ljava/lang/Throwable;)Ljava/lang/Throwable;
    //   1314: athrow
    //   1315: aload_3
    //   1316: getstatic burp/Zs5y.ZO : Ljava/lang/String;
    //   1319: getstatic burp/Zbp.ZD : Ljava/lang/Object;
    //   1322: checkcast java/math/BigInteger
    //   1325: invokevirtual intValue : ()I
    //   1328: bipush #32
    //   1330: irem
    //   1331: invokestatic abs : (I)I
    //   1334: invokevirtual charAt : (I)C
    //   1337: invokevirtual append : (C)Ljava/lang/StringBuilder;
    //   1340: pop
    //   1341: goto -> 1348
    //   1344: invokestatic a : (Ljava/lang/Throwable;)Ljava/lang/Throwable;
    //   1347: athrow
    //   1348: iinc #4, 1
    //   1351: iload_2
    //   1352: ifeq -> 15
    //   1355: aload_3
    //   1356: invokevirtual toString : ()Ljava/lang/String;
    //   1359: putstatic burp/Zgx6.ZX : Ljava/lang/String;
    //   1362: sipush #-10084
    //   1365: sipush #-20174
    //   1368: invokestatic a : (II)Ljava/lang/String;
    //   1371: iconst_1
    //   1372: ldc burp/Zxyu
    //   1374: invokevirtual getClassLoader : ()Ljava/lang/ClassLoader;
    //   1377: invokestatic forName : (Ljava/lang/String;ZLjava/lang/ClassLoader;)Ljava/lang/Class;
    //   1380: invokevirtual getDeclaredFields : ()[Ljava/lang/reflect/Field;
    //   1383: astore #4
    //   1385: aload #4
    //   1387: arraylength
    //   1388: istore #5
    //   1390: iconst_0
    //   1391: istore #6
    //   1393: iload #6
    //   1395: iload #5
    //   1397: if_icmpge -> 1535
    //   1400: aload #4
    //   1402: iload #6
    //   1404: aaload
    //   1405: astore #7
    //   1407: aload #7
    //   1409: invokevirtual getModifiers : ()I
    //   1412: invokestatic isStatic : (I)Z
    //   1415: ifne -> 1425
    //   1418: goto -> 1528
    //   1421: invokestatic a : (Ljava/lang/Throwable;)Ljava/lang/Throwable;
    //   1424: athrow
    //   1425: aload #7
    //   1427: invokevirtual getType : ()Ljava/lang/Class;
    //   1430: astore #8
    //   1432: aload #8
    //   1434: ifnull -> 1515
    //   1437: aload #8
    //   1439: invokevirtual isPrimitive : ()Z
    //   1442: ifne -> 1515
    //   1445: goto -> 1452
    //   1448: invokestatic a : (Ljava/lang/Throwable;)Ljava/lang/Throwable;
    //   1451: athrow
    //   1452: aload #8
    //   1454: invokevirtual getPackage : ()Ljava/lang/Package;
    //   1457: ifnull -> 1515
    //   1460: goto -> 1467
    //   1463: invokestatic a : (Ljava/lang/Throwable;)Ljava/lang/Throwable;
    //   1466: athrow
    //   1467: aload #8
    //   1469: invokevirtual getPackage : ()Ljava/lang/Package;
    //   1472: invokevirtual getName : ()Ljava/lang/String;
    //   1475: ifnull -> 1515
    //   1478: goto -> 1485
    //   1481: invokestatic a : (Ljava/lang/Throwable;)Ljava/lang/Throwable;
    //   1484: athrow
    //   1485: aload #8
    //   1487: invokevirtual getPackage : ()Ljava/lang/Package;
    //   1490: invokevirtual getName : ()Ljava/lang/String;
    //   1493: sipush #-10104
    //   1496: sipush #-13131
    //   1499: invokestatic a : (II)Ljava/lang/String;
    //   1502: invokevirtual startsWith : (Ljava/lang/String;)Z
    //   1505: ifne -> 1515
    //   1508: goto -> 1515
    //   1511: invokestatic a : (Ljava/lang/Throwable;)Ljava/lang/Throwable;
    //   1514: athrow
    //   1515: aload #7
    //   1517: iconst_1
    //   1518: invokevirtual setAccessible : (Z)V
    //   1521: aload #7
    //   1523: aconst_null
    //   1524: invokevirtual get : (Ljava/lang/Object;)Ljava/lang/Object;
    //   1527: pop
    //   1528: iinc #6, 1
    //   1531: iload_2
    //   1532: ifeq -> 1393
    //   1535: sipush #-10091
    //   1538: sipush #2464
    //   1541: invokestatic a : (II)Ljava/lang/String;
    //   1544: invokestatic forName : (Ljava/lang/String;)Ljava/lang/Class;
    //   1547: invokevirtual getDeclaredMethods : ()[Ljava/lang/reflect/Method;
    //   1550: astore #4
    //   1552: aload #4
    //   1554: arraylength
    //   1555: istore #5
    //   1557: iconst_0
    //   1558: istore #6
    //   1560: iload #6
    //   1562: iload #5
    //   1564: if_icmpge -> 1676
    //   1567: aload #4
    //   1569: iload #6
    //   1571: aaload
    //   1572: astore #7
    //   1574: aload #7
    //   1576: invokevirtual getParameterTypes : ()[Ljava/lang/Class;
    //   1579: pop
    //   1580: aload #7
    //   1582: invokevirtual getModifiers : ()I
    //   1585: invokestatic isStatic : (I)Z
    //   1588: ifeq -> 1662
    //   1591: aload #7
    //   1593: invokevirtual getParameterTypes : ()[Ljava/lang/Class;
    //   1596: arraylength
    //   1597: iconst_2
    //   1598: if_icmpne -> 1662
    //   1601: goto -> 1608
    //   1604: invokestatic a : (Ljava/lang/Throwable;)Ljava/lang/Throwable;
    //   1607: athrow
    //   1608: aload #7
    //   1610: invokevirtual getReturnType : ()Ljava/lang/Class;
    //   1613: getstatic java/lang/Boolean.TYPE : Ljava/lang/Class;
    //   1616: if_acmpne -> 1662
    //   1619: goto -> 1626
    //   1622: invokestatic a : (Ljava/lang/Throwable;)Ljava/lang/Throwable;
    //   1625: athrow
    //   1626: aload #7
    //   1628: iconst_1
    //   1629: invokevirtual setAccessible : (Z)V
    //   1632: aload #7
    //   1634: aconst_null
    //   1635: iconst_2
    //   1636: anewarray java/lang/Object
    //   1639: dup
    //   1640: iconst_0
    //   1641: aload_0
    //   1642: aastore
    //   1643: dup
    //   1644: iconst_1
    //   1645: aload_1
    //   1646: aastore
    //   1647: invokevirtual invoke : (Ljava/lang/Object;[Ljava/lang/Object;)Ljava/lang/Object;
    //   1650: pop
    //   1651: iload_2
    //   1652: ifeq -> 1676
    //   1655: goto -> 1662
    //   1658: invokestatic a : (Ljava/lang/Throwable;)Ljava/lang/Throwable;
    //   1661: athrow
    //   1662: iinc #6, 1
    //   1665: iload_2
    //   1666: ifeq -> 1560
    //   1669: goto -> 1676
    //   1672: invokestatic a : (Ljava/lang/Throwable;)Ljava/lang/Throwable;
    //   1675: athrow
    //   1676: sipush #-10086
    //   1679: sipush #11160
    //   1682: invokestatic a : (II)Ljava/lang/String;
    //   1685: iconst_1
    //   1686: ldc burp/Zejj
    //   1688: invokevirtual getClassLoader : ()Ljava/lang/ClassLoader;
    //   1691: invokestatic forName : (Ljava/lang/String;ZLjava/lang/ClassLoader;)Ljava/lang/Class;
    //   1694: invokevirtual getDeclaredFields : ()[Ljava/lang/reflect/Field;
    //   1697: astore #4
    //   1699: aload #4
    //   1701: arraylength
    //   1702: istore #5
    //   1704: iconst_0
    //   1705: istore #6
    //   1707: iload #6
    //   1709: iload #5
    //   1711: if_icmpge -> 1849
    //   1714: aload #4
    //   1716: iload #6
    //   1718: aaload
    //   1719: astore #7
    //   1721: aload #7
    //   1723: invokevirtual getModifiers : ()I
    //   1726: invokestatic isStatic : (I)Z
    //   1729: ifne -> 1739
    //   1732: goto -> 1842
    //   1735: invokestatic a : (Ljava/lang/Throwable;)Ljava/lang/Throwable;
    //   1738: athrow
    //   1739: aload #7
    //   1741: invokevirtual getType : ()Ljava/lang/Class;
    //   1744: astore #8
    //   1746: aload #8
    //   1748: ifnull -> 1829
    //   1751: aload #8
    //   1753: invokevirtual isPrimitive : ()Z
    //   1756: ifne -> 1829
    //   1759: goto -> 1766
    //   1762: invokestatic a : (Ljava/lang/Throwable;)Ljava/lang/Throwable;
    //   1765: athrow
    //   1766: aload #8
    //   1768: invokevirtual getPackage : ()Ljava/lang/Package;
    //   1771: ifnull -> 1829
    //   1774: goto -> 1781
    //   1777: invokestatic a : (Ljava/lang/Throwable;)Ljava/lang/Throwable;
    //   1780: athrow
    //   1781: aload #8
    //   1783: invokevirtual getPackage : ()Ljava/lang/Package;
    //   1786: invokevirtual getName : ()Ljava/lang/String;
    //   1789: ifnull -> 1829
    //   1792: goto -> 1799
    //   1795: invokestatic a : (Ljava/lang/Throwable;)Ljava/lang/Throwable;
    //   1798: athrow
    //   1799: aload #8
    //   1801: invokevirtual getPackage : ()Ljava/lang/Package;
    //   1804: invokevirtual getName : ()Ljava/lang/String;
    //   1807: sipush #-10106
    //   1810: sipush #-10038
    //   1813: invokestatic a : (II)Ljava/lang/String;
    //   1816: invokevirtual startsWith : (Ljava/lang/String;)Z
    //   1819: ifne -> 1829
    //   1822: goto -> 1829
    //   1825: invokestatic a : (Ljava/lang/Throwable;)Ljava/lang/Throwable;
    //   1828: athrow
    //   1829: aload #7
    //   1831: iconst_1
    //   1832: invokevirtual setAccessible : (Z)V
    //   1835: aload #7
    //   1837: aconst_null
    //   1838: invokevirtual get : (Ljava/lang/Object;)Ljava/lang/Object;
    //   1841: pop
    //   1842: iinc #6, 1
    //   1845: iload_2
    //   1846: ifeq -> 1707
    //   1849: sipush #-10087
    //   1852: sipush #-29357
    //   1855: invokestatic a : (II)Ljava/lang/String;
    //   1858: invokestatic forName : (Ljava/lang/String;)Ljava/lang/Class;
    //   1861: invokevirtual getDeclaredMethods : ()[Ljava/lang/reflect/Method;
    //   1864: astore #4
    //   1866: aload #4
    //   1868: arraylength
    //   1869: istore #5
    //   1871: iconst_0
    //   1872: istore #6
    //   1874: iload #6
    //   1876: iload #5
    //   1878: if_icmpge -> 2011
    //   1881: aload #4
    //   1883: iload #6
    //   1885: aaload
    //   1886: astore #7
    //   1888: aload #7
    //   1890: invokevirtual getParameterTypes : ()[Ljava/lang/Class;
    //   1893: pop
    //   1894: aload #7
    //   1896: invokevirtual getModifiers : ()I
    //   1899: invokestatic isStatic : (I)Z
    //   1902: ifeq -> 1997
    //   1905: aload #7
    //   1907: invokevirtual getParameterTypes : ()[Ljava/lang/Class;
    //   1910: arraylength
    //   1911: iconst_2
    //   1912: if_icmpne -> 1997
    //   1915: goto -> 1922
    //   1918: invokestatic a : (Ljava/lang/Throwable;)Ljava/lang/Throwable;
    //   1921: athrow
    //   1922: aload #7
    //   1924: invokevirtual getReturnType : ()Ljava/lang/Class;
    //   1927: getstatic java/lang/Void.TYPE : Ljava/lang/Class;
    //   1930: invokevirtual equals : (Ljava/lang/Object;)Z
    //   1933: ifeq -> 1997
    //   1936: goto -> 1943
    //   1939: invokestatic a : (Ljava/lang/Throwable;)Ljava/lang/Throwable;
    //   1942: athrow
    //   1943: aload #7
    //   1945: iconst_1
    //   1946: invokevirtual setAccessible : (Z)V
    //   1949: aload #7
    //   1951: aconst_null
    //   1952: iconst_2
    //   1953: anewarray java/lang/Object
    //   1956: dup
    //   1957: iconst_0
    //   1958: aload_0
    //   1959: aastore
    //   1960: dup
    //   1961: iconst_1
    //   1962: aload_1
    //   1963: ifnonnull -> 1981
    //   1966: goto -> 1973
    //   1969: invokestatic a : (Ljava/lang/Throwable;)Ljava/lang/Throwable;
    //   1972: athrow
    //   1973: aload_1
    //   1974: goto -> 1988
    //   1977: invokestatic a : (Ljava/lang/Throwable;)Ljava/lang/Throwable;
    //   1980: athrow
    //   1981: aload_1
    //   1982: checkcast [B
    //   1985: invokevirtual clone : ()Ljava/lang/Object;
    //   1988: aastore
    //   1989: invokevirtual invoke : (Ljava/lang/Object;[Ljava/lang/Object;)Ljava/lang/Object;
    //   1992: pop
    //   1993: iload_2
    //   1994: ifeq -> 2011
    //   1997: iinc #6, 1
    //   2000: iload_2
    //   2001: ifeq -> 1874
    //   2004: goto -> 2011
    //   2007: invokestatic a : (Ljava/lang/Throwable;)Ljava/lang/Throwable;
    //   2010: athrow
    //   2011: iconst_0
    //   2012: istore #4
    //   2014: getstatic burp/Zmpc.ZT : Ljava/lang/String;
    //   2017: getstatic burp/Ze6k.Zs : Ljava/lang/Object;
    //   2020: checkcast java/math/BigInteger
    //   2023: invokevirtual intValue : ()I
    //   2026: bipush #32
    //   2028: irem
    //   2029: invokestatic abs : (I)I
    //   2032: invokevirtual charAt : (I)C
    //   2035: getstatic burp/Zk5y.ZZ : Ljava/lang/String;
    //   2038: getstatic burp/Zsbd.Zh : Ljava/lang/Object;
    //   2041: checkcast java/math/BigInteger
    //   2044: invokevirtual intValue : ()I
    //   2047: bipush #32
    //   2049: irem
    //   2050: invokestatic abs : (I)I
    //   2053: invokevirtual charAt : (I)C
    //   2056: if_icmpgt -> 2401
    //   2059: sipush #-10101
    //   2062: sipush #-28550
    //   2065: invokestatic a : (II)Ljava/lang/String;
    //   2068: iconst_1
    //   2069: ldc burp/Zxyp
    //   2071: invokevirtual getClassLoader : ()Ljava/lang/ClassLoader;
    //   2074: invokestatic forName : (Ljava/lang/String;ZLjava/lang/ClassLoader;)Ljava/lang/Class;
    //   2077: invokevirtual getDeclaredFields : ()[Ljava/lang/reflect/Field;
    //   2080: astore #5
    //   2082: aload #5
    //   2084: arraylength
    //   2085: istore #6
    //   2087: iconst_0
    //   2088: istore #7
    //   2090: iload #7
    //   2092: iload #6
    //   2094: if_icmpge -> 2232
    //   2097: aload #5
    //   2099: iload #7
    //   2101: aaload
    //   2102: astore #8
    //   2104: aload #8
    //   2106: invokevirtual getModifiers : ()I
    //   2109: invokestatic isStatic : (I)Z
    //   2112: ifne -> 2122
    //   2115: goto -> 2225
    //   2118: invokestatic a : (Ljava/lang/Throwable;)Ljava/lang/Throwable;
    //   2121: athrow
    //   2122: aload #8
    //   2124: invokevirtual getType : ()Ljava/lang/Class;
    //   2127: astore #9
    //   2129: aload #9
    //   2131: ifnull -> 2212
    //   2134: aload #9
    //   2136: invokevirtual isPrimitive : ()Z
    //   2139: ifne -> 2212
    //   2142: goto -> 2149
    //   2145: invokestatic a : (Ljava/lang/Throwable;)Ljava/lang/Throwable;
    //   2148: athrow
    //   2149: aload #9
    //   2151: invokevirtual getPackage : ()Ljava/lang/Package;
    //   2154: ifnull -> 2212
    //   2157: goto -> 2164
    //   2160: invokestatic a : (Ljava/lang/Throwable;)Ljava/lang/Throwable;
    //   2163: athrow
    //   2164: aload #9
    //   2166: invokevirtual getPackage : ()Ljava/lang/Package;
    //   2169: invokevirtual getName : ()Ljava/lang/String;
    //   2172: ifnull -> 2212
    //   2175: goto -> 2182
    //   2178: invokestatic a : (Ljava/lang/Throwable;)Ljava/lang/Throwable;
    //   2181: athrow
    //   2182: aload #9
    //   2184: invokevirtual getPackage : ()Ljava/lang/Package;
    //   2187: invokevirtual getName : ()Ljava/lang/String;
    //   2190: sipush #-10106
    //   2193: sipush #-10038
    //   2196: invokestatic a : (II)Ljava/lang/String;
    //   2199: invokevirtual startsWith : (Ljava/lang/String;)Z
    //   2202: ifne -> 2212
    //   2205: goto -> 2212
    //   2208: invokestatic a : (Ljava/lang/Throwable;)Ljava/lang/Throwable;
    //   2211: athrow
    //   2212: aload #8
    //   2214: iconst_1
    //   2215: invokevirtual setAccessible : (Z)V
    //   2218: aload #8
    //   2220: aconst_null
    //   2221: invokevirtual get : (Ljava/lang/Object;)Ljava/lang/Object;
    //   2224: pop
    //   2225: iinc #7, 1
    //   2228: iload_2
    //   2229: ifeq -> 2090
    //   2232: sipush #-10083
    //   2235: sipush #-15681
    //   2238: invokestatic a : (II)Ljava/lang/String;
    //   2241: invokestatic forName : (Ljava/lang/String;)Ljava/lang/Class;
    //   2244: invokevirtual getDeclaredMethods : ()[Ljava/lang/reflect/Method;
    //   2247: astore #5
    //   2249: aload #5
    //   2251: arraylength
    //   2252: istore #6
    //   2254: iconst_0
    //   2255: istore #7
    //   2257: iload #7
    //   2259: iload #6
    //   2261: if_icmpge -> 2398
    //   2264: aload #5
    //   2266: iload #7
    //   2268: aaload
    //   2269: astore #8
    //   2271: aload #8
    //   2273: invokevirtual getParameterTypes : ()[Ljava/lang/Class;
    //   2276: pop
    //   2277: aload #8
    //   2279: invokevirtual getModifiers : ()I
    //   2282: invokestatic isStatic : (I)Z
    //   2285: ifeq -> 2384
    //   2288: aload #8
    //   2290: invokevirtual getParameterTypes : ()[Ljava/lang/Class;
    //   2293: arraylength
    //   2294: iconst_2
    //   2295: if_icmpne -> 2384
    //   2298: goto -> 2305
    //   2301: invokestatic a : (Ljava/lang/Throwable;)Ljava/lang/Throwable;
    //   2304: athrow
    //   2305: aload #8
    //   2307: invokevirtual getReturnType : ()Ljava/lang/Class;
    //   2310: getstatic java/lang/Boolean.TYPE : Ljava/lang/Class;
    //   2313: if_acmpne -> 2384
    //   2316: goto -> 2323
    //   2319: invokestatic a : (Ljava/lang/Throwable;)Ljava/lang/Throwable;
    //   2322: athrow
    //   2323: aload #8
    //   2325: iconst_1
    //   2326: invokevirtual setAccessible : (Z)V
    //   2329: aload #8
    //   2331: aconst_null
    //   2332: iconst_2
    //   2333: anewarray java/lang/Object
    //   2336: dup
    //   2337: iconst_0
    //   2338: aload_0
    //   2339: aastore
    //   2340: dup
    //   2341: iconst_1
    //   2342: aload_1
    //   2343: ifnonnull -> 2361
    //   2346: goto -> 2353
    //   2349: invokestatic a : (Ljava/lang/Throwable;)Ljava/lang/Throwable;
    //   2352: athrow
    //   2353: aload_1
    //   2354: goto -> 2368
    //   2357: invokestatic a : (Ljava/lang/Throwable;)Ljava/lang/Throwable;
    //   2360: athrow
    //   2361: aload_1
    //   2362: checkcast [B
    //   2365: invokevirtual clone : ()Ljava/lang/Object;
    //   2368: aastore
    //   2369: invokevirtual invoke : (Ljava/lang/Object;[Ljava/lang/Object;)Ljava/lang/Object;
    //   2372: checkcast java/lang/Boolean
    //   2375: invokevirtual booleanValue : ()Z
    //   2378: istore #4
    //   2380: iload_2
    //   2381: ifeq -> 2398
    //   2384: iinc #7, 1
    //   2387: iload_2
    //   2388: ifeq -> 2257
    //   2391: goto -> 2398
    //   2394: invokestatic a : (Ljava/lang/Throwable;)Ljava/lang/Throwable;
    //   2397: athrow
    //   2398: goto -> 2740
    //   2401: sipush #-10088
    //   2404: sipush #-16520
    //   2407: invokestatic a : (II)Ljava/lang/String;
    //   2410: iconst_1
    //   2411: ldc burp/Zm54
    //   2413: invokevirtual getClassLoader : ()Ljava/lang/ClassLoader;
    //   2416: invokestatic forName : (Ljava/lang/String;ZLjava/lang/ClassLoader;)Ljava/lang/Class;
    //   2419: invokevirtual getDeclaredFields : ()[Ljava/lang/reflect/Field;
    //   2422: astore #5
    //   2424: aload #5
    //   2426: arraylength
    //   2427: istore #6
    //   2429: iconst_0
    //   2430: istore #7
    //   2432: iload #7
    //   2434: iload #6
    //   2436: if_icmpge -> 2574
    //   2439: aload #5
    //   2441: iload #7
    //   2443: aaload
    //   2444: astore #8
    //   2446: aload #8
    //   2448: invokevirtual getModifiers : ()I
    //   2451: invokestatic isStatic : (I)Z
    //   2454: ifne -> 2464
    //   2457: goto -> 2567
    //   2460: invokestatic a : (Ljava/lang/Throwable;)Ljava/lang/Throwable;
    //   2463: athrow
    //   2464: aload #8
    //   2466: invokevirtual getType : ()Ljava/lang/Class;
    //   2469: astore #9
    //   2471: aload #9
    //   2473: ifnull -> 2554
    //   2476: aload #9
    //   2478: invokevirtual isPrimitive : ()Z
    //   2481: ifne -> 2554
    //   2484: goto -> 2491
    //   2487: invokestatic a : (Ljava/lang/Throwable;)Ljava/lang/Throwable;
    //   2490: athrow
    //   2491: aload #9
    //   2493: invokevirtual getPackage : ()Ljava/lang/Package;
    //   2496: ifnull -> 2554
    //   2499: goto -> 2506
    //   2502: invokestatic a : (Ljava/lang/Throwable;)Ljava/lang/Throwable;
    //   2505: athrow
    //   2506: aload #9
    //   2508: invokevirtual getPackage : ()Ljava/lang/Package;
    //   2511: invokevirtual getName : ()Ljava/lang/String;
    //   2514: ifnull -> 2554
    //   2517: goto -> 2524
    //   2520: invokestatic a : (Ljava/lang/Throwable;)Ljava/lang/Throwable;
    //   2523: athrow
    //   2524: aload #9
    //   2526: invokevirtual getPackage : ()Ljava/lang/Package;
    //   2529: invokevirtual getName : ()Ljava/lang/String;
    //   2532: sipush #-10106
    //   2535: sipush #-10038
    //   2538: invokestatic a : (II)Ljava/lang/String;
    //   2541: invokevirtual startsWith : (Ljava/lang/String;)Z
    //   2544: ifne -> 2554
    //   2547: goto -> 2554
    //   2550: invokestatic a : (Ljava/lang/Throwable;)Ljava/lang/Throwable;
    //   2553: athrow
    //   2554: aload #8
    //   2556: iconst_1
    //   2557: invokevirtual setAccessible : (Z)V
    //   2560: aload #8
    //   2562: aconst_null
    //   2563: invokevirtual get : (Ljava/lang/Object;)Ljava/lang/Object;
    //   2566: pop
    //   2567: iinc #7, 1
    //   2570: iload_2
    //   2571: ifeq -> 2432
    //   2574: sipush #-10112
    //   2577: sipush #-9072
    //   2580: invokestatic a : (II)Ljava/lang/String;
    //   2583: invokestatic forName : (Ljava/lang/String;)Ljava/lang/Class;
    //   2586: invokevirtual getDeclaredMethods : ()[Ljava/lang/reflect/Method;
    //   2589: astore #5
    //   2591: aload #5
    //   2593: arraylength
    //   2594: istore #6
    //   2596: iconst_0
    //   2597: istore #7
    //   2599: iload #7
    //   2601: iload #6
    //   2603: if_icmpge -> 2740
    //   2606: aload #5
    //   2608: iload #7
    //   2610: aaload
    //   2611: astore #8
    //   2613: aload #8
    //   2615: invokevirtual getParameterTypes : ()[Ljava/lang/Class;
    //   2618: pop
    //   2619: aload #8
    //   2621: invokevirtual getModifiers : ()I
    //   2624: invokestatic isStatic : (I)Z
    //   2627: ifeq -> 2726
    //   2630: aload #8
    //   2632: invokevirtual getParameterTypes : ()[Ljava/lang/Class;
    //   2635: arraylength
    //   2636: iconst_2
    //   2637: if_icmpne -> 2726
    //   2640: goto -> 2647
    //   2643: invokestatic a : (Ljava/lang/Throwable;)Ljava/lang/Throwable;
    //   2646: athrow
    //   2647: aload #8
    //   2649: invokevirtual getReturnType : ()Ljava/lang/Class;
    //   2652: getstatic java/lang/Boolean.TYPE : Ljava/lang/Class;
    //   2655: if_acmpne -> 2726
    //   2658: goto -> 2665
    //   2661: invokestatic a : (Ljava/lang/Throwable;)Ljava/lang/Throwable;
    //   2664: athrow
    //   2665: aload #8
    //   2667: iconst_1
    //   2668: invokevirtual setAccessible : (Z)V
    //   2671: aload #8
    //   2673: aconst_null
    //   2674: iconst_2
    //   2675: anewarray java/lang/Object
    //   2678: dup
    //   2679: iconst_0
    //   2680: aload_0
    //   2681: aastore
    //   2682: dup
    //   2683: iconst_1
    //   2684: aload_1
    //   2685: ifnonnull -> 2703
    //   2688: goto -> 2695
    //   2691: invokestatic a : (Ljava/lang/Throwable;)Ljava/lang/Throwable;
    //   2694: athrow
    //   2695: aload_1
    //   2696: goto -> 2710
    //   2699: invokestatic a : (Ljava/lang/Throwable;)Ljava/lang/Throwable;
    //   2702: athrow
    //   2703: aload_1
    //   2704: checkcast [B
    //   2707: invokevirtual clone : ()Ljava/lang/Object;
    //   2710: aastore
    //   2711: invokevirtual invoke : (Ljava/lang/Object;[Ljava/lang/Object;)Ljava/lang/Object;
    //   2714: checkcast java/lang/Boolean
    //   2717: invokevirtual booleanValue : ()Z
    //   2720: istore #4
    //   2722: iload_2
    //   2723: ifeq -> 2740
    //   2726: iinc #7, 1
    //   2729: iload_2
    //   2730: ifeq -> 2599
    //   2733: goto -> 2740
    //   2736: invokestatic a : (Ljava/lang/Throwable;)Ljava/lang/Throwable;
    //   2739: athrow
    //   2740: iload #4
    //   2742: ifeq -> 2748
    //   2745: iload #4
    //   2747: ireturn
    //   2748: getstatic burp/Zsbd.ZA : Ljava/lang/String;
    //   2751: getstatic burp/Zxjm.Zn : Ljava/lang/Object;
    //   2754: checkcast java/math/BigInteger
    //   2757: invokevirtual intValue : ()I
    //   2760: bipush #32
    //   2762: irem
    //   2763: invokestatic abs : (I)I
    //   2766: invokevirtual charAt : (I)C
    //   2769: getstatic burp/Zgco.Zh : Ljava/lang/String;
    //   2772: getstatic burp/Zec_.ZN : Ljava/lang/Object;
    //   2775: checkcast java/math/BigInteger
    //   2778: invokevirtual intValue : ()I
    //   2781: bipush #32
    //   2783: irem
    //   2784: invokestatic abs : (I)I
    //   2787: invokevirtual charAt : (I)C
    //   2790: if_icmpgt -> 3136
    //   2793: sipush #-10097
    //   2796: sipush #-14457
    //   2799: invokestatic a : (II)Ljava/lang/String;
    //   2802: iconst_1
    //   2803: ldc burp/Zbqk
    //   2805: invokevirtual getClassLoader : ()Ljava/lang/ClassLoader;
    //   2808: invokestatic forName : (Ljava/lang/String;ZLjava/lang/ClassLoader;)Ljava/lang/Class;
    //   2811: invokevirtual getDeclaredFields : ()[Ljava/lang/reflect/Field;
    //   2814: astore #5
    //   2816: aload #5
    //   2818: arraylength
    //   2819: istore #6
    //   2821: iconst_0
    //   2822: istore #7
    //   2824: iload #7
    //   2826: iload #6
    //   2828: if_icmpge -> 2966
    //   2831: aload #5
    //   2833: iload #7
    //   2835: aaload
    //   2836: astore #8
    //   2838: aload #8
    //   2840: invokevirtual getModifiers : ()I
    //   2843: invokestatic isStatic : (I)Z
    //   2846: ifne -> 2856
    //   2849: goto -> 2959
    //   2852: invokestatic a : (Ljava/lang/Throwable;)Ljava/lang/Throwable;
    //   2855: athrow
    //   2856: aload #8
    //   2858: invokevirtual getType : ()Ljava/lang/Class;
    //   2861: astore #9
    //   2863: aload #9
    //   2865: ifnull -> 2946
    //   2868: aload #9
    //   2870: invokevirtual isPrimitive : ()Z
    //   2873: ifne -> 2946
    //   2876: goto -> 2883
    //   2879: invokestatic a : (Ljava/lang/Throwable;)Ljava/lang/Throwable;
    //   2882: athrow
    //   2883: aload #9
    //   2885: invokevirtual getPackage : ()Ljava/lang/Package;
    //   2888: ifnull -> 2946
    //   2891: goto -> 2898
    //   2894: invokestatic a : (Ljava/lang/Throwable;)Ljava/lang/Throwable;
    //   2897: athrow
    //   2898: aload #9
    //   2900: invokevirtual getPackage : ()Ljava/lang/Package;
    //   2903: invokevirtual getName : ()Ljava/lang/String;
    //   2906: ifnull -> 2946
    //   2909: goto -> 2916
    //   2912: invokestatic a : (Ljava/lang/Throwable;)Ljava/lang/Throwable;
    //   2915: athrow
    //   2916: aload #9
    //   2918: invokevirtual getPackage : ()Ljava/lang/Package;
    //   2921: invokevirtual getName : ()Ljava/lang/String;
    //   2924: sipush #-10106
    //   2927: sipush #-10038
    //   2930: invokestatic a : (II)Ljava/lang/String;
    //   2933: invokevirtual startsWith : (Ljava/lang/String;)Z
    //   2936: ifne -> 2946
    //   2939: goto -> 2946
    //   2942: invokestatic a : (Ljava/lang/Throwable;)Ljava/lang/Throwable;
    //   2945: athrow
    //   2946: aload #8
    //   2948: iconst_1
    //   2949: invokevirtual setAccessible : (Z)V
    //   2952: aload #8
    //   2954: aconst_null
    //   2955: invokevirtual get : (Ljava/lang/Object;)Ljava/lang/Object;
    //   2958: pop
    //   2959: iinc #7, 1
    //   2962: iload_2
    //   2963: ifeq -> 2824
    //   2966: sipush #-10103
    //   2969: sipush #-31188
    //   2972: invokestatic a : (II)Ljava/lang/String;
    //   2975: invokestatic forName : (Ljava/lang/String;)Ljava/lang/Class;
    //   2978: invokevirtual getDeclaredMethods : ()[Ljava/lang/reflect/Method;
    //   2981: astore #5
    //   2983: aload #5
    //   2985: arraylength
    //   2986: istore #6
    //   2988: iconst_0
    //   2989: istore #7
    //   2991: iload #7
    //   2993: iload #6
    //   2995: if_icmpge -> 3132
    //   2998: aload #5
    //   3000: iload #7
    //   3002: aaload
    //   3003: astore #8
    //   3005: aload #8
    //   3007: invokevirtual getParameterTypes : ()[Ljava/lang/Class;
    //   3010: pop
    //   3011: aload #8
    //   3013: invokevirtual getModifiers : ()I
    //   3016: invokestatic isStatic : (I)Z
    //   3019: ifeq -> 3118
    //   3022: aload #8
    //   3024: invokevirtual getParameterTypes : ()[Ljava/lang/Class;
    //   3027: arraylength
    //   3028: iconst_2
    //   3029: if_icmpne -> 3118
    //   3032: goto -> 3039
    //   3035: invokestatic a : (Ljava/lang/Throwable;)Ljava/lang/Throwable;
    //   3038: athrow
    //   3039: aload #8
    //   3041: invokevirtual getReturnType : ()Ljava/lang/Class;
    //   3044: getstatic java/lang/Boolean.TYPE : Ljava/lang/Class;
    //   3047: if_acmpne -> 3118
    //   3050: goto -> 3057
    //   3053: invokestatic a : (Ljava/lang/Throwable;)Ljava/lang/Throwable;
    //   3056: athrow
    //   3057: aload #8
    //   3059: iconst_1
    //   3060: invokevirtual setAccessible : (Z)V
    //   3063: aload #8
    //   3065: aconst_null
    //   3066: iconst_2
    //   3067: anewarray java/lang/Object
    //   3070: dup
    //   3071: iconst_0
    //   3072: aload_0
    //   3073: aastore
    //   3074: dup
    //   3075: iconst_1
    //   3076: aload_1
    //   3077: ifnonnull -> 3095
    //   3080: goto -> 3087
    //   3083: invokestatic a : (Ljava/lang/Throwable;)Ljava/lang/Throwable;
    //   3086: athrow
    //   3087: aload_1
    //   3088: goto -> 3102
    //   3091: invokestatic a : (Ljava/lang/Throwable;)Ljava/lang/Throwable;
    //   3094: athrow
    //   3095: aload_1
    //   3096: checkcast [B
    //   3099: invokevirtual clone : ()Ljava/lang/Object;
    //   3102: aastore
    //   3103: invokevirtual invoke : (Ljava/lang/Object;[Ljava/lang/Object;)Ljava/lang/Object;
    //   3106: checkcast java/lang/Boolean
    //   3109: invokevirtual booleanValue : ()Z
    //   3112: istore #4
    //   3114: iload_2
    //   3115: ifeq -> 3132
    //   3118: iinc #7, 1
    //   3121: iload_2
    //   3122: ifeq -> 2991
    //   3125: goto -> 3132
    //   3128: invokestatic a : (Ljava/lang/Throwable;)Ljava/lang/Throwable;
    //   3131: athrow
    //   3132: iload_2
    //   3133: ifeq -> 3475
    //   3136: sipush #-10098
    //   3139: sipush #-31426
    //   3142: invokestatic a : (II)Ljava/lang/String;
    //   3145: iconst_1
    //   3146: ldc burp/Zmdi
    //   3148: invokevirtual getClassLoader : ()Ljava/lang/ClassLoader;
    //   3151: invokestatic forName : (Ljava/lang/String;ZLjava/lang/ClassLoader;)Ljava/lang/Class;
    //   3154: invokevirtual getDeclaredFields : ()[Ljava/lang/reflect/Field;
    //   3157: astore #5
    //   3159: aload #5
    //   3161: arraylength
    //   3162: istore #6
    //   3164: iconst_0
    //   3165: istore #7
    //   3167: iload #7
    //   3169: iload #6
    //   3171: if_icmpge -> 3309
    //   3174: aload #5
    //   3176: iload #7
    //   3178: aaload
    //   3179: astore #8
    //   3181: aload #8
    //   3183: invokevirtual getModifiers : ()I
    //   3186: invokestatic isStatic : (I)Z
    //   3189: ifne -> 3199
    //   3192: goto -> 3302
    //   3195: invokestatic a : (Ljava/lang/Throwable;)Ljava/lang/Throwable;
    //   3198: athrow
    //   3199: aload #8
    //   3201: invokevirtual getType : ()Ljava/lang/Class;
    //   3204: astore #9
    //   3206: aload #9
    //   3208: ifnull -> 3289
    //   3211: aload #9
    //   3213: invokevirtual isPrimitive : ()Z
    //   3216: ifne -> 3289
    //   3219: goto -> 3226
    //   3222: invokestatic a : (Ljava/lang/Throwable;)Ljava/lang/Throwable;
    //   3225: athrow
    //   3226: aload #9
    //   3228: invokevirtual getPackage : ()Ljava/lang/Package;
    //   3231: ifnull -> 3289
    //   3234: goto -> 3241
    //   3237: invokestatic a : (Ljava/lang/Throwable;)Ljava/lang/Throwable;
    //   3240: athrow
    //   3241: aload #9
    //   3243: invokevirtual getPackage : ()Ljava/lang/Package;
    //   3246: invokevirtual getName : ()Ljava/lang/String;
    //   3249: ifnull -> 3289
    //   3252: goto -> 3259
    //   3255: invokestatic a : (Ljava/lang/Throwable;)Ljava/lang/Throwable;
    //   3258: athrow
    //   3259: aload #9
    //   3261: invokevirtual getPackage : ()Ljava/lang/Package;
    //   3264: invokevirtual getName : ()Ljava/lang/String;
    //   3267: sipush #-10106
    //   3270: sipush #-10038
    //   3273: invokestatic a : (II)Ljava/lang/String;
    //   3276: invokevirtual startsWith : (Ljava/lang/String;)Z
    //   3279: ifne -> 3289
    //   3282: goto -> 3289
    //   3285: invokestatic a : (Ljava/lang/Throwable;)Ljava/lang/Throwable;
    //   3288: athrow
    //   3289: aload #8
    //   3291: iconst_1
    //   3292: invokevirtual setAccessible : (Z)V
    //   3295: aload #8
    //   3297: aconst_null
    //   3298: invokevirtual get : (Ljava/lang/Object;)Ljava/lang/Object;
    //   3301: pop
    //   3302: iinc #7, 1
    //   3305: iload_2
    //   3306: ifeq -> 3167
    //   3309: sipush #-10090
    //   3312: sipush #-17645
    //   3315: invokestatic a : (II)Ljava/lang/String;
    //   3318: invokestatic forName : (Ljava/lang/String;)Ljava/lang/Class;
    //   3321: invokevirtual getDeclaredMethods : ()[Ljava/lang/reflect/Method;
    //   3324: astore #5
    //   3326: aload #5
    //   3328: arraylength
    //   3329: istore #6
    //   3331: iconst_0
    //   3332: istore #7
    //   3334: iload #7
    //   3336: iload #6
    //   3338: if_icmpge -> 3475
    //   3341: aload #5
    //   3343: iload #7
    //   3345: aaload
    //   3346: astore #8
    //   3348: aload #8
    //   3350: invokevirtual getParameterTypes : ()[Ljava/lang/Class;
    //   3353: pop
    //   3354: aload #8
    //   3356: invokevirtual getModifiers : ()I
    //   3359: invokestatic isStatic : (I)Z
    //   3362: ifeq -> 3461
    //   3365: aload #8
    //   3367: invokevirtual getParameterTypes : ()[Ljava/lang/Class;
    //   3370: arraylength
    //   3371: iconst_2
    //   3372: if_icmpne -> 3461
    //   3375: goto -> 3382
    //   3378: invokestatic a : (Ljava/lang/Throwable;)Ljava/lang/Throwable;
    //   3381: athrow
    //   3382: aload #8
    //   3384: invokevirtual getReturnType : ()Ljava/lang/Class;
    //   3387: getstatic java/lang/Boolean.TYPE : Ljava/lang/Class;
    //   3390: if_acmpne -> 3461
    //   3393: goto -> 3400
    //   3396: invokestatic a : (Ljava/lang/Throwable;)Ljava/lang/Throwable;
    //   3399: athrow
    //   3400: aload #8
    //   3402: iconst_1
    //   3403: invokevirtual setAccessible : (Z)V
    //   3406: aload #8
    //   3408: aconst_null
    //   3409: iconst_2
    //   3410: anewarray java/lang/Object
    //   3413: dup
    //   3414: iconst_0
    //   3415: aload_0
    //   3416: aastore
    //   3417: dup
    //   3418: iconst_1
    //   3419: aload_1
    //   3420: ifnonnull -> 3438
    //   3423: goto -> 3430
    //   3426: invokestatic a : (Ljava/lang/Throwable;)Ljava/lang/Throwable;
    //   3429: athrow
    //   3430: aload_1
    //   3431: goto -> 3445
    //   3434: invokestatic a : (Ljava/lang/Throwable;)Ljava/lang/Throwable;
    //   3437: athrow
    //   3438: aload_1
    //   3439: checkcast [B
    //   3442: invokevirtual clone : ()Ljava/lang/Object;
    //   3445: aastore
    //   3446: invokevirtual invoke : (Ljava/lang/Object;[Ljava/lang/Object;)Ljava/lang/Object;
    //   3449: checkcast java/lang/Boolean
    //   3452: invokevirtual booleanValue : ()Z
    //   3455: istore #4
    //   3457: iload_2
    //   3458: ifeq -> 3475
    //   3461: iinc #7, 1
    //   3464: iload_2
    //   3465: ifeq -> 3334
    //   3468: goto -> 3475
    //   3471: invokestatic a : (Ljava/lang/Throwable;)Ljava/lang/Throwable;
    //   3474: athrow
    //   3475: iload #4
    //   3477: ifeq -> 3483
    //   3480: iload #4
    //   3482: ireturn
    //   3483: getstatic burp/Zxxd.Za : Ljava/lang/String;
    //   3486: getstatic burp/Zsk4.Ze : Ljava/lang/Object;
    //   3489: checkcast java/math/BigInteger
    //   3492: invokevirtual intValue : ()I
    //   3495: bipush #32
    //   3497: irem
    //   3498: invokestatic abs : (I)I
    //   3501: invokevirtual charAt : (I)C
    //   3504: getstatic burp/Zrw7.Zo : Ljava/lang/String;
    //   3507: getstatic burp/Zb6e.ZD : Ljava/lang/Object;
    //   3510: checkcast java/math/BigInteger
    //   3513: invokevirtual intValue : ()I
    //   3516: bipush #32
    //   3518: irem
    //   3519: invokestatic abs : (I)I
    //   3522: invokevirtual charAt : (I)C
    //   3525: if_icmple -> 3871
    //   3528: sipush #-10107
    //   3531: sipush #-4597
    //   3534: invokestatic a : (II)Ljava/lang/String;
    //   3537: iconst_1
    //   3538: ldc burp/Zk7w
    //   3540: invokevirtual getClassLoader : ()Ljava/lang/ClassLoader;
    //   3543: invokestatic forName : (Ljava/lang/String;ZLjava/lang/ClassLoader;)Ljava/lang/Class;
    //   3546: invokevirtual getDeclaredFields : ()[Ljava/lang/reflect/Field;
    //   3549: astore #5
    //   3551: aload #5
    //   3553: arraylength
    //   3554: istore #6
    //   3556: iconst_0
    //   3557: istore #7
    //   3559: iload #7
    //   3561: iload #6
    //   3563: if_icmpge -> 3701
    //   3566: aload #5
    //   3568: iload #7
    //   3570: aaload
    //   3571: astore #8
    //   3573: aload #8
    //   3575: invokevirtual getModifiers : ()I
    //   3578: invokestatic isStatic : (I)Z
    //   3581: ifne -> 3591
    //   3584: goto -> 3694
    //   3587: invokestatic a : (Ljava/lang/Throwable;)Ljava/lang/Throwable;
    //   3590: athrow
    //   3591: aload #8
    //   3593: invokevirtual getType : ()Ljava/lang/Class;
    //   3596: astore #9
    //   3598: aload #9
    //   3600: ifnull -> 3681
    //   3603: aload #9
    //   3605: invokevirtual isPrimitive : ()Z
    //   3608: ifne -> 3681
    //   3611: goto -> 3618
    //   3614: invokestatic a : (Ljava/lang/Throwable;)Ljava/lang/Throwable;
    //   3617: athrow
    //   3618: aload #9
    //   3620: invokevirtual getPackage : ()Ljava/lang/Package;
    //   3623: ifnull -> 3681
    //   3626: goto -> 3633
    //   3629: invokestatic a : (Ljava/lang/Throwable;)Ljava/lang/Throwable;
    //   3632: athrow
    //   3633: aload #9
    //   3635: invokevirtual getPackage : ()Ljava/lang/Package;
    //   3638: invokevirtual getName : ()Ljava/lang/String;
    //   3641: ifnull -> 3681
    //   3644: goto -> 3651
    //   3647: invokestatic a : (Ljava/lang/Throwable;)Ljava/lang/Throwable;
    //   3650: athrow
    //   3651: aload #9
    //   3653: invokevirtual getPackage : ()Ljava/lang/Package;
    //   3656: invokevirtual getName : ()Ljava/lang/String;
    //   3659: sipush #-10106
    //   3662: sipush #-10038
    //   3665: invokestatic a : (II)Ljava/lang/String;
    //   3668: invokevirtual startsWith : (Ljava/lang/String;)Z
    //   3671: ifne -> 3681
    //   3674: goto -> 3681
    //   3677: invokestatic a : (Ljava/lang/Throwable;)Ljava/lang/Throwable;
    //   3680: athrow
    //   3681: aload #8
    //   3683: iconst_1
    //   3684: invokevirtual setAccessible : (Z)V
    //   3687: aload #8
    //   3689: aconst_null
    //   3690: invokevirtual get : (Ljava/lang/Object;)Ljava/lang/Object;
    //   3693: pop
    //   3694: iinc #7, 1
    //   3697: iload_2
    //   3698: ifeq -> 3559
    //   3701: sipush #-10109
    //   3704: sipush #16640
    //   3707: invokestatic a : (II)Ljava/lang/String;
    //   3710: invokestatic forName : (Ljava/lang/String;)Ljava/lang/Class;
    //   3713: invokevirtual getDeclaredMethods : ()[Ljava/lang/reflect/Method;
    //   3716: astore #5
    //   3718: aload #5
    //   3720: arraylength
    //   3721: istore #6
    //   3723: iconst_0
    //   3724: istore #7
    //   3726: iload #7
    //   3728: iload #6
    //   3730: if_icmpge -> 3867
    //   3733: aload #5
    //   3735: iload #7
    //   3737: aaload
    //   3738: astore #8
    //   3740: aload #8
    //   3742: invokevirtual getParameterTypes : ()[Ljava/lang/Class;
    //   3745: pop
    //   3746: aload #8
    //   3748: invokevirtual getModifiers : ()I
    //   3751: invokestatic isStatic : (I)Z
    //   3754: ifeq -> 3853
    //   3757: aload #8
    //   3759: invokevirtual getParameterTypes : ()[Ljava/lang/Class;
    //   3762: arraylength
    //   3763: iconst_2
    //   3764: if_icmpne -> 3853
    //   3767: goto -> 3774
    //   3770: invokestatic a : (Ljava/lang/Throwable;)Ljava/lang/Throwable;
    //   3773: athrow
    //   3774: aload #8
    //   3776: invokevirtual getReturnType : ()Ljava/lang/Class;
    //   3779: getstatic java/lang/Boolean.TYPE : Ljava/lang/Class;
    //   3782: if_acmpne -> 3853
    //   3785: goto -> 3792
    //   3788: invokestatic a : (Ljava/lang/Throwable;)Ljava/lang/Throwable;
    //   3791: athrow
    //   3792: aload #8
    //   3794: iconst_1
    //   3795: invokevirtual setAccessible : (Z)V
    //   3798: aload #8
    //   3800: aconst_null
    //   3801: iconst_2
    //   3802: anewarray java/lang/Object
    //   3805: dup
    //   3806: iconst_0
    //   3807: aload_0
    //   3808: aastore
    //   3809: dup
    //   3810: iconst_1
    //   3811: aload_1
    //   3812: ifnonnull -> 3830
    //   3815: goto -> 3822
    //   3818: invokestatic a : (Ljava/lang/Throwable;)Ljava/lang/Throwable;
    //   3821: athrow
    //   3822: aload_1
    //   3823: goto -> 3837
    //   3826: invokestatic a : (Ljava/lang/Throwable;)Ljava/lang/Throwable;
    //   3829: athrow
    //   3830: aload_1
    //   3831: checkcast [B
    //   3834: invokevirtual clone : ()Ljava/lang/Object;
    //   3837: aastore
    //   3838: invokevirtual invoke : (Ljava/lang/Object;[Ljava/lang/Object;)Ljava/lang/Object;
    //   3841: checkcast java/lang/Boolean
    //   3844: invokevirtual booleanValue : ()Z
    //   3847: istore #4
    //   3849: iload_2
    //   3850: ifeq -> 3867
    //   3853: iinc #7, 1
    //   3856: iload_2
    //   3857: ifeq -> 3726
    //   3860: goto -> 3867
    //   3863: invokestatic a : (Ljava/lang/Throwable;)Ljava/lang/Throwable;
    //   3866: athrow
    //   3867: iload_2
    //   3868: ifeq -> 4210
    //   3871: sipush #-10105
    //   3874: sipush #-18724
    //   3877: invokestatic a : (II)Ljava/lang/String;
    //   3880: iconst_1
    //   3881: ldc burp/Zsx6
    //   3883: invokevirtual getClassLoader : ()Ljava/lang/ClassLoader;
    //   3886: invokestatic forName : (Ljava/lang/String;ZLjava/lang/ClassLoader;)Ljava/lang/Class;
    //   3889: invokevirtual getDeclaredFields : ()[Ljava/lang/reflect/Field;
    //   3892: astore #5
    //   3894: aload #5
    //   3896: arraylength
    //   3897: istore #6
    //   3899: iconst_0
    //   3900: istore #7
    //   3902: iload #7
    //   3904: iload #6
    //   3906: if_icmpge -> 4044
    //   3909: aload #5
    //   3911: iload #7
    //   3913: aaload
    //   3914: astore #8
    //   3916: aload #8
    //   3918: invokevirtual getModifiers : ()I
    //   3921: invokestatic isStatic : (I)Z
    //   3924: ifne -> 3934
    //   3927: goto -> 4037
    //   3930: invokestatic a : (Ljava/lang/Throwable;)Ljava/lang/Throwable;
    //   3933: athrow
    //   3934: aload #8
    //   3936: invokevirtual getType : ()Ljava/lang/Class;
    //   3939: astore #9
    //   3941: aload #9
    //   3943: ifnull -> 4024
    //   3946: aload #9
    //   3948: invokevirtual isPrimitive : ()Z
    //   3951: ifne -> 4024
    //   3954: goto -> 3961
    //   3957: invokestatic a : (Ljava/lang/Throwable;)Ljava/lang/Throwable;
    //   3960: athrow
    //   3961: aload #9
    //   3963: invokevirtual getPackage : ()Ljava/lang/Package;
    //   3966: ifnull -> 4024
    //   3969: goto -> 3976
    //   3972: invokestatic a : (Ljava/lang/Throwable;)Ljava/lang/Throwable;
    //   3975: athrow
    //   3976: aload #9
    //   3978: invokevirtual getPackage : ()Ljava/lang/Package;
    //   3981: invokevirtual getName : ()Ljava/lang/String;
    //   3984: ifnull -> 4024
    //   3987: goto -> 3994
    //   3990: invokestatic a : (Ljava/lang/Throwable;)Ljava/lang/Throwable;
    //   3993: athrow
    //   3994: aload #9
    //   3996: invokevirtual getPackage : ()Ljava/lang/Package;
    //   3999: invokevirtual getName : ()Ljava/lang/String;
    //   4002: sipush #-10106
    //   4005: sipush #-10038
    //   4008: invokestatic a : (II)Ljava/lang/String;
    //   4011: invokevirtual startsWith : (Ljava/lang/String;)Z
    //   4014: ifne -> 4024
    //   4017: goto -> 4024
    //   4020: invokestatic a : (Ljava/lang/Throwable;)Ljava/lang/Throwable;
    //   4023: athrow
    //   4024: aload #8
    //   4026: iconst_1
    //   4027: invokevirtual setAccessible : (Z)V
    //   4030: aload #8
    //   4032: aconst_null
    //   4033: invokevirtual get : (Ljava/lang/Object;)Ljava/lang/Object;
    //   4036: pop
    //   4037: iinc #7, 1
    //   4040: iload_2
    //   4041: ifeq -> 3902
    //   4044: sipush #-10099
    //   4047: sipush #-19189
    //   4050: invokestatic a : (II)Ljava/lang/String;
    //   4053: invokestatic forName : (Ljava/lang/String;)Ljava/lang/Class;
    //   4056: invokevirtual getDeclaredMethods : ()[Ljava/lang/reflect/Method;
    //   4059: astore #5
    //   4061: aload #5
    //   4063: arraylength
    //   4064: istore #6
    //   4066: iconst_0
    //   4067: istore #7
    //   4069: iload #7
    //   4071: iload #6
    //   4073: if_icmpge -> 4210
    //   4076: aload #5
    //   4078: iload #7
    //   4080: aaload
    //   4081: astore #8
    //   4083: aload #8
    //   4085: invokevirtual getParameterTypes : ()[Ljava/lang/Class;
    //   4088: pop
    //   4089: aload #8
    //   4091: invokevirtual getModifiers : ()I
    //   4094: invokestatic isStatic : (I)Z
    //   4097: ifeq -> 4196
    //   4100: aload #8
    //   4102: invokevirtual getParameterTypes : ()[Ljava/lang/Class;
    //   4105: arraylength
    //   4106: iconst_2
    //   4107: if_icmpne -> 4196
    //   4110: goto -> 4117
    //   4113: invokestatic a : (Ljava/lang/Throwable;)Ljava/lang/Throwable;
    //   4116: athrow
    //   4117: aload #8
    //   4119: invokevirtual getReturnType : ()Ljava/lang/Class;
    //   4122: getstatic java/lang/Boolean.TYPE : Ljava/lang/Class;
    //   4125: if_acmpne -> 4196
    //   4128: goto -> 4135
    //   4131: invokestatic a : (Ljava/lang/Throwable;)Ljava/lang/Throwable;
    //   4134: athrow
    //   4135: aload #8
    //   4137: iconst_1
    //   4138: invokevirtual setAccessible : (Z)V
    //   4141: aload #8
    //   4143: aconst_null
    //   4144: iconst_2
    //   4145: anewarray java/lang/Object
    //   4148: dup
    //   4149: iconst_0
    //   4150: aload_0
    //   4151: aastore
    //   4152: dup
    //   4153: iconst_1
    //   4154: aload_1
    //   4155: ifnonnull -> 4173
    //   4158: goto -> 4165
    //   4161: invokestatic a : (Ljava/lang/Throwable;)Ljava/lang/Throwable;
    //   4164: athrow
    //   4165: aload_1
    //   4166: goto -> 4180
    //   4169: invokestatic a : (Ljava/lang/Throwable;)Ljava/lang/Throwable;
    //   4172: athrow
    //   4173: aload_1
    //   4174: checkcast [B
    //   4177: invokevirtual clone : ()Ljava/lang/Object;
    //   4180: aastore
    //   4181: invokevirtual invoke : (Ljava/lang/Object;[Ljava/lang/Object;)Ljava/lang/Object;
    //   4184: checkcast java/lang/Boolean
    //   4187: invokevirtual booleanValue : ()Z
    //   4190: istore #4
    //   4192: iload_2
    //   4193: ifeq -> 4210
    //   4196: iinc #7, 1
    //   4199: iload_2
    //   4200: ifeq -> 4069
    //   4203: goto -> 4210
    //   4206: invokestatic a : (Ljava/lang/Throwable;)Ljava/lang/Throwable;
    //   4209: athrow
    //   4210: iload #4
    //   4212: ifeq -> 4218
    //   4215: iload #4
    //   4217: ireturn
    //   4218: getstatic burp/Zx_b.ZD : Ljava/lang/String;
    //   4221: getstatic burp/Zlum.Zj : Ljava/lang/Object;
    //   4224: checkcast java/math/BigInteger
    //   4227: invokevirtual intValue : ()I
    //   4230: bipush #32
    //   4232: irem
    //   4233: invokestatic abs : (I)I
    //   4236: invokevirtual charAt : (I)C
    //   4239: getstatic burp/Zmd.Zf : Ljava/lang/String;
    //   4242: getstatic burp/Zec0.Zg : Ljava/lang/Object;
    //   4245: checkcast java/math/BigInteger
    //   4248: invokevirtual intValue : ()I
    //   4251: bipush #32
    //   4253: irem
    //   4254: invokestatic abs : (I)I
    //   4257: invokevirtual charAt : (I)C
    //   4260: if_icmpgt -> 4606
    //   4263: sipush #-10100
    //   4266: sipush #5055
    //   4269: invokestatic a : (II)Ljava/lang/String;
    //   4272: iconst_1
    //   4273: ldc burp/Zgny
    //   4275: invokevirtual getClassLoader : ()Ljava/lang/ClassLoader;
    //   4278: invokestatic forName : (Ljava/lang/String;ZLjava/lang/ClassLoader;)Ljava/lang/Class;
    //   4281: invokevirtual getDeclaredFields : ()[Ljava/lang/reflect/Field;
    //   4284: astore #5
    //   4286: aload #5
    //   4288: arraylength
    //   4289: istore #6
    //   4291: iconst_0
    //   4292: istore #7
    //   4294: iload #7
    //   4296: iload #6
    //   4298: if_icmpge -> 4436
    //   4301: aload #5
    //   4303: iload #7
    //   4305: aaload
    //   4306: astore #8
    //   4308: aload #8
    //   4310: invokevirtual getModifiers : ()I
    //   4313: invokestatic isStatic : (I)Z
    //   4316: ifne -> 4326
    //   4319: goto -> 4429
    //   4322: invokestatic a : (Ljava/lang/Throwable;)Ljava/lang/Throwable;
    //   4325: athrow
    //   4326: aload #8
    //   4328: invokevirtual getType : ()Ljava/lang/Class;
    //   4331: astore #9
    //   4333: aload #9
    //   4335: ifnull -> 4416
    //   4338: aload #9
    //   4340: invokevirtual isPrimitive : ()Z
    //   4343: ifne -> 4416
    //   4346: goto -> 4353
    //   4349: invokestatic a : (Ljava/lang/Throwable;)Ljava/lang/Throwable;
    //   4352: athrow
    //   4353: aload #9
    //   4355: invokevirtual getPackage : ()Ljava/lang/Package;
    //   4358: ifnull -> 4416
    //   4361: goto -> 4368
    //   4364: invokestatic a : (Ljava/lang/Throwable;)Ljava/lang/Throwable;
    //   4367: athrow
    //   4368: aload #9
    //   4370: invokevirtual getPackage : ()Ljava/lang/Package;
    //   4373: invokevirtual getName : ()Ljava/lang/String;
    //   4376: ifnull -> 4416
    //   4379: goto -> 4386
    //   4382: invokestatic a : (Ljava/lang/Throwable;)Ljava/lang/Throwable;
    //   4385: athrow
    //   4386: aload #9
    //   4388: invokevirtual getPackage : ()Ljava/lang/Package;
    //   4391: invokevirtual getName : ()Ljava/lang/String;
    //   4394: sipush #-10106
    //   4397: sipush #-10038
    //   4400: invokestatic a : (II)Ljava/lang/String;
    //   4403: invokevirtual startsWith : (Ljava/lang/String;)Z
    //   4406: ifne -> 4416
    //   4409: goto -> 4416
    //   4412: invokestatic a : (Ljava/lang/Throwable;)Ljava/lang/Throwable;
    //   4415: athrow
    //   4416: aload #8
    //   4418: iconst_1
    //   4419: invokevirtual setAccessible : (Z)V
    //   4422: aload #8
    //   4424: aconst_null
    //   4425: invokevirtual get : (Ljava/lang/Object;)Ljava/lang/Object;
    //   4428: pop
    //   4429: iinc #7, 1
    //   4432: iload_2
    //   4433: ifeq -> 4294
    //   4436: sipush #-10085
    //   4439: sipush #2958
    //   4442: invokestatic a : (II)Ljava/lang/String;
    //   4445: invokestatic forName : (Ljava/lang/String;)Ljava/lang/Class;
    //   4448: invokevirtual getDeclaredMethods : ()[Ljava/lang/reflect/Method;
    //   4451: astore #5
    //   4453: aload #5
    //   4455: arraylength
    //   4456: istore #6
    //   4458: iconst_0
    //   4459: istore #7
    //   4461: iload #7
    //   4463: iload #6
    //   4465: if_icmpge -> 4602
    //   4468: aload #5
    //   4470: iload #7
    //   4472: aaload
    //   4473: astore #8
    //   4475: aload #8
    //   4477: invokevirtual getParameterTypes : ()[Ljava/lang/Class;
    //   4480: pop
    //   4481: aload #8
    //   4483: invokevirtual getModifiers : ()I
    //   4486: invokestatic isStatic : (I)Z
    //   4489: ifeq -> 4588
    //   4492: aload #8
    //   4494: invokevirtual getParameterTypes : ()[Ljava/lang/Class;
    //   4497: arraylength
    //   4498: iconst_2
    //   4499: if_icmpne -> 4588
    //   4502: goto -> 4509
    //   4505: invokestatic a : (Ljava/lang/Throwable;)Ljava/lang/Throwable;
    //   4508: athrow
    //   4509: aload #8
    //   4511: invokevirtual getReturnType : ()Ljava/lang/Class;
    //   4514: getstatic java/lang/Boolean.TYPE : Ljava/lang/Class;
    //   4517: if_acmpne -> 4588
    //   4520: goto -> 4527
    //   4523: invokestatic a : (Ljava/lang/Throwable;)Ljava/lang/Throwable;
    //   4526: athrow
    //   4527: aload #8
    //   4529: iconst_1
    //   4530: invokevirtual setAccessible : (Z)V
    //   4533: aload #8
    //   4535: aconst_null
    //   4536: iconst_2
    //   4537: anewarray java/lang/Object
    //   4540: dup
    //   4541: iconst_0
    //   4542: aload_0
    //   4543: aastore
    //   4544: dup
    //   4545: iconst_1
    //   4546: aload_1
    //   4547: ifnonnull -> 4565
    //   4550: goto -> 4557
    //   4553: invokestatic a : (Ljava/lang/Throwable;)Ljava/lang/Throwable;
    //   4556: athrow
    //   4557: aload_1
    //   4558: goto -> 4572
    //   4561: invokestatic a : (Ljava/lang/Throwable;)Ljava/lang/Throwable;
    //   4564: athrow
    //   4565: aload_1
    //   4566: checkcast [B
    //   4569: invokevirtual clone : ()Ljava/lang/Object;
    //   4572: aastore
    //   4573: invokevirtual invoke : (Ljava/lang/Object;[Ljava/lang/Object;)Ljava/lang/Object;
    //   4576: checkcast java/lang/Boolean
    //   4579: invokevirtual booleanValue : ()Z
    //   4582: istore #4
    //   4584: iload_2
    //   4585: ifeq -> 4602
    //   4588: iinc #7, 1
    //   4591: iload_2
    //   4592: ifeq -> 4461
    //   4595: goto -> 4602
    //   4598: invokestatic a : (Ljava/lang/Throwable;)Ljava/lang/Throwable;
    //   4601: athrow
    //   4602: iload_2
    //   4603: ifeq -> 4945
    //   4606: sipush #-10081
    //   4609: sipush #31640
    //   4612: invokestatic a : (II)Ljava/lang/String;
    //   4615: iconst_1
    //   4616: ldc burp/Zbo7
    //   4618: invokevirtual getClassLoader : ()Ljava/lang/ClassLoader;
    //   4621: invokestatic forName : (Ljava/lang/String;ZLjava/lang/ClassLoader;)Ljava/lang/Class;
    //   4624: invokevirtual getDeclaredFields : ()[Ljava/lang/reflect/Field;
    //   4627: astore #5
    //   4629: aload #5
    //   4631: arraylength
    //   4632: istore #6
    //   4634: iconst_0
    //   4635: istore #7
    //   4637: iload #7
    //   4639: iload #6
    //   4641: if_icmpge -> 4779
    //   4644: aload #5
    //   4646: iload #7
    //   4648: aaload
    //   4649: astore #8
    //   4651: aload #8
    //   4653: invokevirtual getModifiers : ()I
    //   4656: invokestatic isStatic : (I)Z
    //   4659: ifne -> 4669
    //   4662: goto -> 4772
    //   4665: invokestatic a : (Ljava/lang/Throwable;)Ljava/lang/Throwable;
    //   4668: athrow
    //   4669: aload #8
    //   4671: invokevirtual getType : ()Ljava/lang/Class;
    //   4674: astore #9
    //   4676: aload #9
    //   4678: ifnull -> 4759
    //   4681: aload #9
    //   4683: invokevirtual isPrimitive : ()Z
    //   4686: ifne -> 4759
    //   4689: goto -> 4696
    //   4692: invokestatic a : (Ljava/lang/Throwable;)Ljava/lang/Throwable;
    //   4695: athrow
    //   4696: aload #9
    //   4698: invokevirtual getPackage : ()Ljava/lang/Package;
    //   4701: ifnull -> 4759
    //   4704: goto -> 4711
    //   4707: invokestatic a : (Ljava/lang/Throwable;)Ljava/lang/Throwable;
    //   4710: athrow
    //   4711: aload #9
    //   4713: invokevirtual getPackage : ()Ljava/lang/Package;
    //   4716: invokevirtual getName : ()Ljava/lang/String;
    //   4719: ifnull -> 4759
    //   4722: goto -> 4729
    //   4725: invokestatic a : (Ljava/lang/Throwable;)Ljava/lang/Throwable;
    //   4728: athrow
    //   4729: aload #9
    //   4731: invokevirtual getPackage : ()Ljava/lang/Package;
    //   4734: invokevirtual getName : ()Ljava/lang/String;
    //   4737: sipush #-10106
    //   4740: sipush #-10038
    //   4743: invokestatic a : (II)Ljava/lang/String;
    //   4746: invokevirtual startsWith : (Ljava/lang/String;)Z
    //   4749: ifne -> 4759
    //   4752: goto -> 4759
    //   4755: invokestatic a : (Ljava/lang/Throwable;)Ljava/lang/Throwable;
    //   4758: athrow
    //   4759: aload #8
    //   4761: iconst_1
    //   4762: invokevirtual setAccessible : (Z)V
    //   4765: aload #8
    //   4767: aconst_null
    //   4768: invokevirtual get : (Ljava/lang/Object;)Ljava/lang/Object;
    //   4771: pop
    //   4772: iinc #7, 1
    //   4775: iload_2
    //   4776: ifeq -> 4637
    //   4779: sipush #-10092
    //   4782: sipush #25191
    //   4785: invokestatic a : (II)Ljava/lang/String;
    //   4788: invokestatic forName : (Ljava/lang/String;)Ljava/lang/Class;
    //   4791: invokevirtual getDeclaredMethods : ()[Ljava/lang/reflect/Method;
    //   4794: astore #5
    //   4796: aload #5
    //   4798: arraylength
    //   4799: istore #6
    //   4801: iconst_0
    //   4802: istore #7
    //   4804: iload #7
    //   4806: iload #6
    //   4808: if_icmpge -> 4945
    //   4811: aload #5
    //   4813: iload #7
    //   4815: aaload
    //   4816: astore #8
    //   4818: aload #8
    //   4820: invokevirtual getParameterTypes : ()[Ljava/lang/Class;
    //   4823: pop
    //   4824: aload #8
    //   4826: invokevirtual getModifiers : ()I
    //   4829: invokestatic isStatic : (I)Z
    //   4832: ifeq -> 4931
    //   4835: aload #8
    //   4837: invokevirtual getParameterTypes : ()[Ljava/lang/Class;
    //   4840: arraylength
    //   4841: iconst_2
    //   4842: if_icmpne -> 4931
    //   4845: goto -> 4852
    //   4848: invokestatic a : (Ljava/lang/Throwable;)Ljava/lang/Throwable;
    //   4851: athrow
    //   4852: aload #8
    //   4854: invokevirtual getReturnType : ()Ljava/lang/Class;
    //   4857: getstatic java/lang/Boolean.TYPE : Ljava/lang/Class;
    //   4860: if_acmpne -> 4931
    //   4863: goto -> 4870
    //   4866: invokestatic a : (Ljava/lang/Throwable;)Ljava/lang/Throwable;
    //   4869: athrow
    //   4870: aload #8
    //   4872: iconst_1
    //   4873: invokevirtual setAccessible : (Z)V
    //   4876: aload #8
    //   4878: aconst_null
    //   4879: iconst_2
    //   4880: anewarray java/lang/Object
    //   4883: dup
    //   4884: iconst_0
    //   4885: aload_0
    //   4886: aastore
    //   4887: dup
    //   4888: iconst_1
    //   4889: aload_1
    //   4890: ifnonnull -> 4908
    //   4893: goto -> 4900
    //   4896: invokestatic a : (Ljava/lang/Throwable;)Ljava/lang/Throwable;
    //   4899: athrow
    //   4900: aload_1
    //   4901: goto -> 4915
    //   4904: invokestatic a : (Ljava/lang/Throwable;)Ljava/lang/Throwable;
    //   4907: athrow
    //   4908: aload_1
    //   4909: checkcast [B
    //   4912: invokevirtual clone : ()Ljava/lang/Object;
    //   4915: aastore
    //   4916: invokevirtual invoke : (Ljava/lang/Object;[Ljava/lang/Object;)Ljava/lang/Object;
    //   4919: checkcast java/lang/Boolean
    //   4922: invokevirtual booleanValue : ()Z
    //   4925: istore #4
    //   4927: iload_2
    //   4928: ifeq -> 4945
    //   4931: iinc #7, 1
    //   4934: iload_2
    //   4935: ifeq -> 4804
    //   4938: goto -> 4945
    //   4941: invokestatic a : (Ljava/lang/Throwable;)Ljava/lang/Throwable;
    //   4944: athrow
    //   4945: iload #4
    //   4947: ireturn
    //   4948: astore_3
    //   4949: new java/lang/Exception
    //   4952: dup
    //   4953: aload_3
    //   4954: invokevirtual getMessage : ()Ljava/lang/String;
    //   4957: invokespecial <init> : (Ljava/lang/String;)V
    //   4960: athrow
    // Exception table:
    //   from	to	target	type
    //   4	2747	4948	java/lang/Throwable
    //   22	198	201	java/lang/Throwable
    //   168	235	238	java/lang/Throwable
    //   205	272	275	java/lang/Throwable
    //   242	309	312	java/lang/Throwable
    //   279	346	349	java/lang/Throwable
    //   316	383	386	java/lang/Throwable
    //   353	420	423	java/lang/Throwable
    //   390	457	460	java/lang/Throwable
    //   427	494	497	java/lang/Throwable
    //   464	531	534	java/lang/Throwable
    //   501	568	571	java/lang/Throwable
    //   538	605	608	java/lang/Throwable
    //   575	642	645	java/lang/Throwable
    //   612	679	682	java/lang/Throwable
    //   649	716	719	java/lang/Throwable
    //   686	753	756	java/lang/Throwable
    //   723	790	793	java/lang/Throwable
    //   760	827	830	java/lang/Throwable
    //   797	864	867	java/lang/Throwable
    //   834	901	904	java/lang/Throwable
    //   871	938	941	java/lang/Throwable
    //   908	975	978	java/lang/Throwable
    //   945	1012	1015	java/lang/Throwable
    //   982	1049	1052	java/lang/Throwable
    //   1019	1086	1089	java/lang/Throwable
    //   1056	1123	1126	java/lang/Throwable
    //   1093	1160	1163	java/lang/Throwable
    //   1130	1197	1200	java/lang/Throwable
    //   1167	1234	1237	java/lang/Throwable
    //   1204	1271	1274	java/lang/Throwable
    //   1241	1308	1311	java/lang/Throwable
    //   1278	1341	1344	java/lang/Throwable
    //   1407	1421	1421	java/lang/Throwable
    //   1432	1445	1448	java/lang/Throwable
    //   1437	1460	1463	java/lang/Throwable
    //   1452	1478	1481	java/lang/Throwable
    //   1467	1508	1511	java/lang/Throwable
    //   1574	1601	1604	java/lang/Throwable
    //   1591	1619	1622	java/lang/Throwable
    //   1608	1655	1658	java/lang/Throwable
    //   1626	1669	1672	java/lang/Throwable
    //   1721	1735	1735	java/lang/Throwable
    //   1746	1759	1762	java/lang/Throwable
    //   1751	1774	1777	java/lang/Throwable
    //   1766	1792	1795	java/lang/Throwable
    //   1781	1822	1825	java/lang/Throwable
    //   1888	1915	1918	java/lang/Throwable
    //   1905	1936	1939	java/lang/Throwable
    //   1922	1966	1969	java/lang/Throwable
    //   1943	1977	1977	java/lang/Throwable
    //   1988	2004	2007	java/lang/Throwable
    //   2104	2118	2118	java/lang/Throwable
    //   2129	2142	2145	java/lang/Throwable
    //   2134	2157	2160	java/lang/Throwable
    //   2149	2175	2178	java/lang/Throwable
    //   2164	2205	2208	java/lang/Throwable
    //   2271	2298	2301	java/lang/Throwable
    //   2288	2316	2319	java/lang/Throwable
    //   2305	2346	2349	java/lang/Throwable
    //   2323	2357	2357	java/lang/Throwable
    //   2380	2391	2394	java/lang/Throwable
    //   2446	2460	2460	java/lang/Throwable
    //   2471	2484	2487	java/lang/Throwable
    //   2476	2499	2502	java/lang/Throwable
    //   2491	2517	2520	java/lang/Throwable
    //   2506	2547	2550	java/lang/Throwable
    //   2613	2640	2643	java/lang/Throwable
    //   2630	2658	2661	java/lang/Throwable
    //   2647	2688	2691	java/lang/Throwable
    //   2665	2699	2699	java/lang/Throwable
    //   2722	2733	2736	java/lang/Throwable
    //   2748	3482	4948	java/lang/Throwable
    //   2838	2852	2852	java/lang/Throwable
    //   2863	2876	2879	java/lang/Throwable
    //   2868	2891	2894	java/lang/Throwable
    //   2883	2909	2912	java/lang/Throwable
    //   2898	2939	2942	java/lang/Throwable
    //   3005	3032	3035	java/lang/Throwable
    //   3022	3050	3053	java/lang/Throwable
    //   3039	3080	3083	java/lang/Throwable
    //   3057	3091	3091	java/lang/Throwable
    //   3114	3125	3128	java/lang/Throwable
    //   3181	3195	3195	java/lang/Throwable
    //   3206	3219	3222	java/lang/Throwable
    //   3211	3234	3237	java/lang/Throwable
    //   3226	3252	3255	java/lang/Throwable
    //   3241	3282	3285	java/lang/Throwable
    //   3348	3375	3378	java/lang/Throwable
    //   3365	3393	3396	java/lang/Throwable
    //   3382	3423	3426	java/lang/Throwable
    //   3400	3434	3434	java/lang/Throwable
    //   3457	3468	3471	java/lang/Throwable
    //   3483	4217	4948	java/lang/Throwable
    //   3573	3587	3587	java/lang/Throwable
    //   3598	3611	3614	java/lang/Throwable
    //   3603	3626	3629	java/lang/Throwable
    //   3618	3644	3647	java/lang/Throwable
    //   3633	3674	3677	java/lang/Throwable
    //   3740	3767	3770	java/lang/Throwable
    //   3757	3785	3788	java/lang/Throwable
    //   3774	3815	3818	java/lang/Throwable
    //   3792	3826	3826	java/lang/Throwable
    //   3849	3860	3863	java/lang/Throwable
    //   3916	3930	3930	java/lang/Throwable
    //   3941	3954	3957	java/lang/Throwable
    //   3946	3969	3972	java/lang/Throwable
    //   3961	3987	3990	java/lang/Throwable
    //   3976	4017	4020	java/lang/Throwable
    //   4083	4110	4113	java/lang/Throwable
    //   4100	4128	4131	java/lang/Throwable
    //   4117	4158	4161	java/lang/Throwable
    //   4135	4169	4169	java/lang/Throwable
    //   4192	4203	4206	java/lang/Throwable
    //   4218	4947	4948	java/lang/Throwable
    //   4308	4322	4322	java/lang/Throwable
    //   4333	4346	4349	java/lang/Throwable
    //   4338	4361	4364	java/lang/Throwable
    //   4353	4379	4382	java/lang/Throwable
    //   4368	4409	4412	java/lang/Throwable
    //   4475	4502	4505	java/lang/Throwable
    //   4492	4520	4523	java/lang/Throwable
    //   4509	4550	4553	java/lang/Throwable
    //   4527	4561	4561	java/lang/Throwable
    //   4584	4595	4598	java/lang/Throwable
    //   4651	4665	4665	java/lang/Throwable
    //   4676	4689	4692	java/lang/Throwable
    //   4681	4704	4707	java/lang/Throwable
    //   4696	4722	4725	java/lang/Throwable
    //   4711	4752	4755	java/lang/Throwable
    //   4818	4845	4848	java/lang/Throwable
    //   4835	4863	4866	java/lang/Throwable
    //   4852	4893	4896	java/lang/Throwable
    //   4870	4904	4904	java/lang/Throwable
    //   4927	4938	4941	java/lang/Throwable
  }
  
  static void Zr(Object[] paramArrayOfObject, Object paramObject) throws Throwable {}
  
  static void Zi(Object paramObject) {
    Zmpc.ZT = a(-10108, 4045);
    Zmpc.Zc = new BigInteger(a(-10111, 16149));
    boolean bool = Zt2e.ZK();
    try {
      try {
        if (Zly7.ZC.charAt(Math.abs(((BigInteger)Zboa.Zh).intValue() % 32)) <= Zx_b.ZD.charAt(Math.abs(((BigInteger)Zly7.Zt).intValue() % 32))) {
          try {
            Zr9b.Zd(Class.forName(a(-10089, -11238)));
            if (bool)
              Zgfm.Zd(Class.forName(a(-10102, -554))); 
          } catch (Throwable throwable) {
            throw a(null);
          } 
          return;
        } 
      } catch (Throwable throwable) {
        throw a(null);
      } 
      Zgfm.Zd(Class.forName(a(-10102, -554)));
    } catch (Throwable throwable) {}
  }
  
  static {
    // Byte code:
    //   0: bipush #28
    //   2: anewarray java/lang/String
    //   5: astore #5
    //   7: iconst_0
    //   8: istore_3
    //   9: ldc ''\\n]\\r\\t*sG2\\tt0?.=\\b!:nA\\tUo$\\t=`F\\t$q2/'e>?\\ts(,rM&\\ttC0"& h\\fFc1(+\\rV4\\n68\\tBAPBMP$A6LdNFAm5YqHm<qZjKm6\\bRcLi\\fp+\\r:F=#w<>OqkG&EHt48W\\t:+rkZ\\t BaQ;y XY@K\\rj|59Z^5O%\\t:D_\\tV\\bZS\\tw[\\t@B\\t\C"C|\\t^R3c,hTf\\t:"d'
    //   11: dup
    //   12: astore_2
    //   13: invokevirtual length : ()I
    //   16: istore #4
    //   18: bipush #9
    //   20: istore_1
    //   21: iconst_m1
    //   22: istore_0
    //   23: bipush #75
    //   25: iinc #0, 1
    //   28: aload_2
    //   29: iload_0
    //   30: dup
    //   31: iload_1
    //   32: iadd
    //   33: invokevirtual substring : (II)Ljava/lang/String;
    //   36: iconst_m1
    //   37: goto -> 143
    //   40: aload #5
    //   42: swap
    //   43: iload_3
    //   44: iinc #3, 1
    //   47: swap
    //   48: aastore
    //   49: iload_0
    //   50: iload_1
    //   51: iadd
    //   52: dup
    //   53: istore_0
    //   54: iload #4
    //   56: if_icmpge -> 68
    //   59: aload_2
    //   60: iload_0
    //   61: invokevirtual charAt : (I)C
    //   64: istore_1
    //   65: goto -> 23
    //   68: ldc 'D%\\tFxh'
    //   70: dup
    //   71: astore_2
    //   72: invokevirtual length : ()I
    //   75: istore #4
    //   77: bipush #9
    //   79: istore_1
    //   80: iconst_m1
    //   81: istore_0
    //   82: bipush #60
    //   84: iinc #0, 1
    //   87: aload_2
    //   88: iload_0
    //   89: dup
    //   90: iload_1
    //   91: iadd
    //   92: invokevirtual substring : (II)Ljava/lang/String;
    //   95: iconst_0
    //   96: goto -> 143
    //   99: aload #5
    //   101: swap
    //   102: iload_3
    //   103: iinc #3, 1
    //   106: swap
    //   107: aastore
    //   108: iload_0
    //   109: iload_1
    //   110: iadd
    //   111: dup
    //   112: istore_0
    //   113: iload #4
    //   115: if_icmpge -> 127
    //   118: aload_2
    //   119: iload_0
    //   120: invokevirtual charAt : (I)C
    //   123: istore_1
    //   124: goto -> 82
    //   127: aload #5
    //   129: putstatic burp/Zg7j.a : [Ljava/lang/String;
    //   132: bipush #28
    //   134: anewarray java/lang/String
    //   137: putstatic burp/Zg7j.b : [Ljava/lang/String;
    //   140: goto -> 300
    //   143: dup_x2
    //   144: pop
    //   145: invokevirtual toCharArray : ()[C
    //   148: dup_x1
    //   149: arraylength
    //   150: dup_x2
    //   151: pop
    //   152: iconst_0
    //   153: istore #6
    //   155: dup2_x1
    //   156: pop2
    //   157: dup_x2
    //   158: iconst_1
    //   159: if_icmpgt -> 260
    //   162: dup2
    //   163: swap
    //   164: iload #6
    //   166: dup2_x1
    //   167: caload
    //   168: swap
    //   169: iload #6
    //   171: bipush #7
    //   173: irem
    //   174: tableswitch default -> 242, 0 -> 212, 1 -> 217, 2 -> 222, 3 -> 227, 4 -> 232, 5 -> 237
    //   212: bipush #72
    //   214: goto -> 244
    //   217: bipush #27
    //   219: goto -> 244
    //   222: bipush #49
    //   224: goto -> 244
    //   227: bipush #18
    //   229: goto -> 244
    //   232: bipush #63
    //   234: goto -> 244
    //   237: bipush #14
    //   239: goto -> 244
    //   242: bipush #94
    //   244: ixor
    //   245: ixor
    //   246: i2c
    //   247: castore
    //   248: iinc #6, 1
    //   251: dup
    //   252: ifne -> 260
    //   255: dup2
    //   256: dup_x1
    //   257: goto -> 166
    //   260: dup2_x1
    //   261: pop2
    //   262: dup_x2
    //   263: iload #6
    //   265: if_icmpgt -> 162
    //   268: pop
    //   269: new java/lang/String
    //   272: dup_x1
    //   273: swap
    //   274: invokespecial <init> : ([C)V
    //   277: invokevirtual intern : ()Ljava/lang/String;
    //   280: swap
    //   281: pop
    //   282: swap
    //   283: tableswitch default -> 40, 0 -> 99
    //   300: sipush #-10082
    //   303: sipush #8923
    //   306: invokestatic a : (II)Ljava/lang/String;
    //   309: putstatic burp/Zg7j.ZR : Ljava/lang/String;
    //   312: new java/math/BigInteger
    //   315: dup
    //   316: sipush #-10110
    //   319: sipush #20441
    //   322: invokestatic a : (II)Ljava/lang/String;
    //   325: invokespecial <init> : (Ljava/lang/String;)V
    //   328: putstatic burp/Zg7j.Zr : Ljava/lang/Object;
    //   331: return
  }
  
  private static Throwable a(Throwable paramThrowable) {
    return paramThrowable;
  }
  
  private static String a(int paramInt1, int paramInt2) {
    int i = (paramInt1 ^ 0xFFFFD88F) & 0xFFFF;
    if (b[i] == null) {
      char[] arrayOfChar = a[i].toCharArray();
      switch (arrayOfChar[0] & 0xFF) {
        case 0:
        
        case 1:
        
        case 2:
        
        case 3:
        
        case 4:
        
        case 5:
        
        case 6:
        
        case 7:
        
        case 8:
        
        case 9:
        
        case 10:
        
        case 11:
        
        case 12:
        
        case 13:
        
        case 14:
        
        case 15:
        
        case 16:
        
        case 17:
        
        case 18:
        
        case 19:
        
        case 20:
        
        case 21:
        
        case 22:
        
        case 23:
        
        case 24:
        
        case 25:
        
        case 26:
        
        case 27:
        
        case 28:
        
        case 29:
        
        case 30:
        
        case 31:
        
        case 32:
        
        case 33:
        
        case 34:
        
        case 35:
        
        case 36:
        
        case 37:
        
        case 38:
        
        case 39:
        
        case 40:
        
        case 41:
        
        case 42:
        
        case 43:
        
        case 44:
        
        case 45:
        
        case 46:
        
        case 47:
        
        case 48:
        
        case 49:
        
        case 50:
        
        case 51:
        
        case 52:
        
        case 53:
        
        case 54:
        
        case 55:
        
        case 56:
        
        case 57:
        
        case 58:
        
        case 59:
        
        case 60:
        
        case 61:
        
        case 62:
        
        case 63:
        
        case 64:
        
        case 65:
        
        case 66:
        
        case 67:
        
        case 68:
        
        case 69:
        
        case 70:
        
        case 71:
        
        case 72:
        
        case 73:
        
        case 74:
        
        case 75:
        
        case 76:
        
        case 77:
        
        case 78:
        
        case 79:
        
        case 80:
        
        case 81:
        
        case 82:
        
        case 83:
        
        case 84:
        
        case 85:
        
        case 86:
        
        case 87:
        
        case 88:
        
        case 89:
        
        case 90:
        
        case 91:
        
        case 92:
        
        case 93:
        
        case 94:
        
        case 95:
        
        case 96:
        
        case 97:
        
        case 98:
        
        case 99:
        
        case 100:
        
        case 101:
        
        case 102:
        
        case 103:
        
        case 104:
        
        case 105:
        
        case 106:
        
        case 107:
        
        case 108:
        
        case 109:
        
        case 110:
        
        case 111:
        
        case 112:
        
        case 113:
        
        case 114:
        
        case 115:
        
        case 116:
        
        case 117:
        
        case 118:
        
        case 119:
        
        case 120:
        
        case 121:
        
        case 122:
        
        case 123:
        
        case 124:
        
        case 125:
        
        case 126:
        
        case 127:
        
        case 128:
        
        case 129:
        
        case 130:
        
        case 131:
        
        case 132:
        
        case 133:
        
        case 134:
        
        case 135:
        
        case 136:
        
        case 137:
        
        case 138:
        
        case 139:
        
        case 140:
        
        case 141:
        
        case 142:
        
        case 143:
        
        case 144:
        
        case 145:
        
        case 146:
        
        case 147:
        
        case 148:
        
        case 149:
        
        case 150:
        
        case 151:
        
        case 152:
        
        case 153:
        
        case 154:
        
        case 155:
        
        case 156:
        
        case 157:
        
        case 158:
        
        case 159:
        
        case 160:
        
        case 161:
        
        case 162:
        
        case 163:
        
        case 164:
        
        case 165:
        
        case 166:
        
        case 167:
        
        case 168:
        
        case 169:
        
        case 170:
        
        case 171:
        
        case 172:
        
        case 173:
        
        case 174:
        
        case 175:
        
        case 176:
        
        case 177:
        
        case 178:
        
        case 179:
        
        case 180:
        
        case 181:
        
        case 182:
        
        case 183:
        
        case 184:
        
        case 185:
        
        case 186:
        
        case 187:
        
        case 188:
        
        case 189:
        
        case 190:
        
        case 191:
        
        case 192:
        
        case 193:
        
        case 194:
        
        case 195:
        
        case 196:
        
        case 197:
        
        case 198:
        
        case 199:
        
        case 200:
        
        case 201:
        
        case 202:
        
        case 203:
        
        case 204:
        
        case 205:
        
        case 206:
        
        case 207:
        
        case 208:
        
        case 209:
        
        case 210:
        
        case 211:
        
        case 212:
        
        case 213:
        
        case 214:
        
        case 215:
        
        case 216:
        
        case 217:
        
        case 218:
        
        case 219:
        
        case 220:
        
        case 221:
        
        case 222:
        
        case 223:
        
        case 224:
        
        case 225:
        
        case 226:
        
        case 227:
        
        case 228:
        
        case 229:
        
        case 230:
        
        case 231:
        
        case 232:
        
        case 233:
        
        case 234:
        
        case 235:
        
        case 236:
        
        case 237:
        
        case 238:
        
        case 239:
        
        case 240:
        
        case 241:
        
        case 242:
        
        case 243:
        
        case 244:
        
        case 245:
        
        case 246:
        
        case 247:
        
        case 248:
        
        case 249:
        
        case 250:
        
        case 251:
        
        case 252:
        
        case 253:
        
        case 254:
        
        default:
          break;
      } 
      byte b1 = 117;
      int j = (paramInt2 & 0xFF) - b1;
      if (j < 0)
        j += 256; 
      int k = ((paramInt2 & 0xFFFF) >>> 8) - b1;
      if (k < 0)
        k += 256; 
      for (byte b2 = 0; b2 < arrayOfChar.length; b2++) {
        int m = b2 % 2;
        if (m == 0) {
          arrayOfChar[b2] = (char)(arrayOfChar[b2] ^ j);
          j = ((j >>> 3 | j << 5) ^ arrayOfChar[b2]) & 0xFF;
        } else {
          arrayOfChar[b2] = (char)(arrayOfChar[b2] ^ k);
          k = ((k >>> 3 | k << 5) ^ arrayOfChar[b2]) & 0xFF;
        } 
      } 
      b[i] = (new String(arrayOfChar)).intern();
    } 
    return b[i];
  }
}


/* Location:              C:\Program Files\BurpSuitePro\burpsuite_pro.jar!\burp\Zg7j.class
 * Java compiler version: 21 (65.0)
 * JD-Core Version:       1.1.3
 */