package burp;

import java.math.BigInteger;

class Zg7p extends ClassLoader {
  static Object Zb;
  
  static String ZA;
  
  private static final String[] a;
  
  private static final String[] b;
  
  static void Zy(Object[] paramArrayOfObject, Object paramObject) throws Throwable {}
  
  static boolean ZT(Object[] paramArrayOfObject, Object paramObject) throws Throwable {
    // Byte code:
    //   0: invokestatic ZK : ()Z
    //   3: istore_2
    //   4: getstatic burp/Zehi.Zb : Ljava/lang/Object;
    //   7: checkcast java/math/BigInteger
    //   10: invokevirtual toByteArray : ()[B
    //   13: astore_3
    //   14: bipush #32
    //   16: newarray int
    //   18: dup
    //   19: iconst_0
    //   20: ldc 943331329
    //   22: iastore
    //   23: dup
    //   24: iconst_1
    //   25: ldc 170788368
    //   27: iastore
    //   28: dup
    //   29: iconst_2
    //   30: ldc 1008414755
    //   32: iastore
    //   33: dup
    //   34: iconst_3
    //   35: ldc 187049985
    //   37: iastore
    //   38: dup
    //   39: iconst_4
    //   40: ldc 1010368540
    //   42: iastore
    //   43: dup
    //   44: iconst_5
    //   45: ldc 220604441
    //   47: iastore
    //   48: dup
    //   49: bipush #6
    //   51: ldc 940377620
    //   53: iastore
    //   54: dup
    //   55: bipush #7
    //   57: ldc 255209728
    //   59: iastore
    //   60: dup
    //   61: bipush #8
    //   63: ldc 689771012
    //   65: iastore
    //   66: dup
    //   67: bipush #9
    //   69: ldc 221709344
    //   71: iastore
    //   72: dup
    //   73: bipush #10
    //   75: ldc 957157408
    //   77: iastore
    //   78: dup
    //   79: bipush #11
    //   81: ldc 892536332
    //   83: iastore
    //   84: dup
    //   85: bipush #12
    //   87: ldc 722417666
    //   89: iastore
    //   90: dup
    //   91: bipush #13
    //   93: ldc 1026621720
    //   95: iastore
    //   96: dup
    //   97: bipush #14
    //   99: ldc 655302664
    //   101: iastore
    //   102: dup
    //   103: bipush #15
    //   105: ldc 890966315
    //   107: iastore
    //   108: dup
    //   109: bipush #16
    //   111: ldc 187632156
    //   113: iastore
    //   114: dup
    //   115: bipush #17
    //   117: ldc 874189824
    //   119: iastore
    //   120: dup
    //   121: bipush #18
    //   123: ldc 254150144
    //   125: iastore
    //   126: dup
    //   127: bipush #19
    //   129: ldc 924386310
    //   131: iastore
    //   132: dup
    //   133: bipush #20
    //   135: ldc 121057538
    //   137: iastore
    //   138: dup
    //   139: bipush #21
    //   141: ldc 840500228
    //   143: iastore
    //   144: dup
    //   145: bipush #22
    //   147: ldc 389160971
    //   149: iastore
    //   150: dup
    //   151: bipush #23
    //   153: ldc 907870729
    //   155: iastore
    //   156: dup
    //   157: bipush #24
    //   159: ldc 389426184
    //   161: iastore
    //   162: dup
    //   163: bipush #25
    //   165: ldc 973875457
    //   167: iastore
    //   168: dup
    //   169: bipush #26
    //   171: ldc 372376604
    //   173: iastore
    //   174: dup
    //   175: bipush #27
    //   177: ldc 707731490
    //   179: iastore
    //   180: dup
    //   181: bipush #28
    //   183: ldc 1043334948
    //   185: iastore
    //   186: dup
    //   187: bipush #29
    //   189: ldc 439222784
    //   191: iastore
    //   192: dup
    //   193: bipush #30
    //   195: ldc 876216579
    //   197: iastore
    //   198: dup
    //   199: bipush #31
    //   201: ldc 455999525
    //   203: iastore
    //   204: astore #5
    //   206: bipush #8
    //   208: aload_3
    //   209: arraylength
    //   210: bipush #8
    //   212: irem
    //   213: isub
    //   214: istore #6
    //   216: aload_3
    //   217: arraylength
    //   218: iload #6
    //   220: iadd
    //   221: newarray byte
    //   223: astore #7
    //   225: iconst_0
    //   226: istore #8
    //   228: iload #8
    //   230: aload_3
    //   231: arraylength
    //   232: if_icmpge -> 251
    //   235: aload #7
    //   237: iload #8
    //   239: aload_3
    //   240: iload #8
    //   242: baload
    //   243: bastore
    //   244: iinc #8, 1
    //   247: iload_2
    //   248: ifeq -> 228
    //   251: aload_3
    //   252: arraylength
    //   253: istore #8
    //   255: iload #8
    //   257: aload #7
    //   259: arraylength
    //   260: if_icmpge -> 278
    //   263: aload #7
    //   265: iload #8
    //   267: iload #6
    //   269: i2b
    //   270: bastore
    //   271: iinc #8, 1
    //   274: iload_2
    //   275: ifeq -> 255
    //   278: aload #7
    //   280: astore_3
    //   281: bipush #64
    //   283: newarray int
    //   285: dup
    //   286: iconst_0
    //   287: ldc 16843776
    //   289: iastore
    //   290: dup
    //   291: iconst_1
    //   292: iconst_0
    //   293: iastore
    //   294: dup
    //   295: iconst_2
    //   296: ldc 65536
    //   298: iastore
    //   299: dup
    //   300: iconst_3
    //   301: ldc 16843780
    //   303: iastore
    //   304: dup
    //   305: iconst_4
    //   306: ldc 16842756
    //   308: iastore
    //   309: dup
    //   310: iconst_5
    //   311: ldc 66564
    //   313: iastore
    //   314: dup
    //   315: bipush #6
    //   317: iconst_4
    //   318: iastore
    //   319: dup
    //   320: bipush #7
    //   322: ldc 65536
    //   324: iastore
    //   325: dup
    //   326: bipush #8
    //   328: sipush #1024
    //   331: iastore
    //   332: dup
    //   333: bipush #9
    //   335: ldc 16843776
    //   337: iastore
    //   338: dup
    //   339: bipush #10
    //   341: ldc 16843780
    //   343: iastore
    //   344: dup
    //   345: bipush #11
    //   347: sipush #1024
    //   350: iastore
    //   351: dup
    //   352: bipush #12
    //   354: ldc 16778244
    //   356: iastore
    //   357: dup
    //   358: bipush #13
    //   360: ldc 16842756
    //   362: iastore
    //   363: dup
    //   364: bipush #14
    //   366: ldc 16777216
    //   368: iastore
    //   369: dup
    //   370: bipush #15
    //   372: iconst_4
    //   373: iastore
    //   374: dup
    //   375: bipush #16
    //   377: sipush #1028
    //   380: iastore
    //   381: dup
    //   382: bipush #17
    //   384: ldc 16778240
    //   386: iastore
    //   387: dup
    //   388: bipush #18
    //   390: ldc 16778240
    //   392: iastore
    //   393: dup
    //   394: bipush #19
    //   396: ldc 66560
    //   398: iastore
    //   399: dup
    //   400: bipush #20
    //   402: ldc 66560
    //   404: iastore
    //   405: dup
    //   406: bipush #21
    //   408: ldc 16842752
    //   410: iastore
    //   411: dup
    //   412: bipush #22
    //   414: ldc 16842752
    //   416: iastore
    //   417: dup
    //   418: bipush #23
    //   420: ldc 16778244
    //   422: iastore
    //   423: dup
    //   424: bipush #24
    //   426: ldc 65540
    //   428: iastore
    //   429: dup
    //   430: bipush #25
    //   432: ldc 16777220
    //   434: iastore
    //   435: dup
    //   436: bipush #26
    //   438: ldc 16777220
    //   440: iastore
    //   441: dup
    //   442: bipush #27
    //   444: ldc 65540
    //   446: iastore
    //   447: dup
    //   448: bipush #28
    //   450: iconst_0
    //   451: iastore
    //   452: dup
    //   453: bipush #29
    //   455: sipush #1028
    //   458: iastore
    //   459: dup
    //   460: bipush #30
    //   462: ldc 66564
    //   464: iastore
    //   465: dup
    //   466: bipush #31
    //   468: ldc 16777216
    //   470: iastore
    //   471: dup
    //   472: bipush #32
    //   474: ldc 65536
    //   476: iastore
    //   477: dup
    //   478: bipush #33
    //   480: ldc 16843780
    //   482: iastore
    //   483: dup
    //   484: bipush #34
    //   486: iconst_4
    //   487: iastore
    //   488: dup
    //   489: bipush #35
    //   491: ldc 16842752
    //   493: iastore
    //   494: dup
    //   495: bipush #36
    //   497: ldc 16843776
    //   499: iastore
    //   500: dup
    //   501: bipush #37
    //   503: ldc 16777216
    //   505: iastore
    //   506: dup
    //   507: bipush #38
    //   509: ldc 16777216
    //   511: iastore
    //   512: dup
    //   513: bipush #39
    //   515: sipush #1024
    //   518: iastore
    //   519: dup
    //   520: bipush #40
    //   522: ldc 16842756
    //   524: iastore
    //   525: dup
    //   526: bipush #41
    //   528: ldc 65536
    //   530: iastore
    //   531: dup
    //   532: bipush #42
    //   534: ldc 66560
    //   536: iastore
    //   537: dup
    //   538: bipush #43
    //   540: ldc 16777220
    //   542: iastore
    //   543: dup
    //   544: bipush #44
    //   546: sipush #1024
    //   549: iastore
    //   550: dup
    //   551: bipush #45
    //   553: iconst_4
    //   554: iastore
    //   555: dup
    //   556: bipush #46
    //   558: ldc 16778244
    //   560: iastore
    //   561: dup
    //   562: bipush #47
    //   564: ldc 66564
    //   566: iastore
    //   567: dup
    //   568: bipush #48
    //   570: ldc 16843780
    //   572: iastore
    //   573: dup
    //   574: bipush #49
    //   576: ldc 65540
    //   578: iastore
    //   579: dup
    //   580: bipush #50
    //   582: ldc 16842752
    //   584: iastore
    //   585: dup
    //   586: bipush #51
    //   588: ldc 16778244
    //   590: iastore
    //   591: dup
    //   592: bipush #52
    //   594: ldc 16777220
    //   596: iastore
    //   597: dup
    //   598: bipush #53
    //   600: sipush #1028
    //   603: iastore
    //   604: dup
    //   605: bipush #54
    //   607: ldc 66564
    //   609: iastore
    //   610: dup
    //   611: bipush #55
    //   613: ldc 16843776
    //   615: iastore
    //   616: dup
    //   617: bipush #56
    //   619: sipush #1028
    //   622: iastore
    //   623: dup
    //   624: bipush #57
    //   626: ldc 16778240
    //   628: iastore
    //   629: dup
    //   630: bipush #58
    //   632: ldc 16778240
    //   634: iastore
    //   635: dup
    //   636: bipush #59
    //   638: iconst_0
    //   639: iastore
    //   640: dup
    //   641: bipush #60
    //   643: ldc 65540
    //   645: iastore
    //   646: dup
    //   647: bipush #61
    //   649: ldc 66560
    //   651: iastore
    //   652: dup
    //   653: bipush #62
    //   655: iconst_0
    //   656: iastore
    //   657: dup
    //   658: bipush #63
    //   660: ldc 16842756
    //   662: iastore
    //   663: astore #8
    //   665: bipush #64
    //   667: newarray int
    //   669: dup
    //   670: iconst_0
    //   671: ldc -2146402272
    //   673: iastore
    //   674: dup
    //   675: iconst_1
    //   676: ldc -2147450880
    //   678: iastore
    //   679: dup
    //   680: iconst_2
    //   681: ldc 32768
    //   683: iastore
    //   684: dup
    //   685: iconst_3
    //   686: ldc 1081376
    //   688: iastore
    //   689: dup
    //   690: iconst_4
    //   691: ldc 1048576
    //   693: iastore
    //   694: dup
    //   695: iconst_5
    //   696: bipush #32
    //   698: iastore
    //   699: dup
    //   700: bipush #6
    //   702: ldc -2146435040
    //   704: iastore
    //   705: dup
    //   706: bipush #7
    //   708: ldc -2147450848
    //   710: iastore
    //   711: dup
    //   712: bipush #8
    //   714: ldc -2147483616
    //   716: iastore
    //   717: dup
    //   718: bipush #9
    //   720: ldc -2146402272
    //   722: iastore
    //   723: dup
    //   724: bipush #10
    //   726: ldc -2146402304
    //   728: iastore
    //   729: dup
    //   730: bipush #11
    //   732: ldc -2147483648
    //   734: iastore
    //   735: dup
    //   736: bipush #12
    //   738: ldc -2147450880
    //   740: iastore
    //   741: dup
    //   742: bipush #13
    //   744: ldc 1048576
    //   746: iastore
    //   747: dup
    //   748: bipush #14
    //   750: bipush #32
    //   752: iastore
    //   753: dup
    //   754: bipush #15
    //   756: ldc -2146435040
    //   758: iastore
    //   759: dup
    //   760: bipush #16
    //   762: ldc 1081344
    //   764: iastore
    //   765: dup
    //   766: bipush #17
    //   768: ldc 1048608
    //   770: iastore
    //   771: dup
    //   772: bipush #18
    //   774: ldc -2147450848
    //   776: iastore
    //   777: dup
    //   778: bipush #19
    //   780: iconst_0
    //   781: iastore
    //   782: dup
    //   783: bipush #20
    //   785: ldc -2147483648
    //   787: iastore
    //   788: dup
    //   789: bipush #21
    //   791: ldc 32768
    //   793: iastore
    //   794: dup
    //   795: bipush #22
    //   797: ldc 1081376
    //   799: iastore
    //   800: dup
    //   801: bipush #23
    //   803: ldc -2146435072
    //   805: iastore
    //   806: dup
    //   807: bipush #24
    //   809: ldc 1048608
    //   811: iastore
    //   812: dup
    //   813: bipush #25
    //   815: ldc -2147483616
    //   817: iastore
    //   818: dup
    //   819: bipush #26
    //   821: iconst_0
    //   822: iastore
    //   823: dup
    //   824: bipush #27
    //   826: ldc 1081344
    //   828: iastore
    //   829: dup
    //   830: bipush #28
    //   832: ldc 32800
    //   834: iastore
    //   835: dup
    //   836: bipush #29
    //   838: ldc -2146402304
    //   840: iastore
    //   841: dup
    //   842: bipush #30
    //   844: ldc -2146435072
    //   846: iastore
    //   847: dup
    //   848: bipush #31
    //   850: ldc 32800
    //   852: iastore
    //   853: dup
    //   854: bipush #32
    //   856: iconst_0
    //   857: iastore
    //   858: dup
    //   859: bipush #33
    //   861: ldc 1081376
    //   863: iastore
    //   864: dup
    //   865: bipush #34
    //   867: ldc -2146435040
    //   869: iastore
    //   870: dup
    //   871: bipush #35
    //   873: ldc 1048576
    //   875: iastore
    //   876: dup
    //   877: bipush #36
    //   879: ldc -2147450848
    //   881: iastore
    //   882: dup
    //   883: bipush #37
    //   885: ldc -2146435072
    //   887: iastore
    //   888: dup
    //   889: bipush #38
    //   891: ldc -2146402304
    //   893: iastore
    //   894: dup
    //   895: bipush #39
    //   897: ldc 32768
    //   899: iastore
    //   900: dup
    //   901: bipush #40
    //   903: ldc -2146435072
    //   905: iastore
    //   906: dup
    //   907: bipush #41
    //   909: ldc -2147450880
    //   911: iastore
    //   912: dup
    //   913: bipush #42
    //   915: bipush #32
    //   917: iastore
    //   918: dup
    //   919: bipush #43
    //   921: ldc -2146402272
    //   923: iastore
    //   924: dup
    //   925: bipush #44
    //   927: ldc 1081376
    //   929: iastore
    //   930: dup
    //   931: bipush #45
    //   933: bipush #32
    //   935: iastore
    //   936: dup
    //   937: bipush #46
    //   939: ldc 32768
    //   941: iastore
    //   942: dup
    //   943: bipush #47
    //   945: ldc -2147483648
    //   947: iastore
    //   948: dup
    //   949: bipush #48
    //   951: ldc 32800
    //   953: iastore
    //   954: dup
    //   955: bipush #49
    //   957: ldc -2146402304
    //   959: iastore
    //   960: dup
    //   961: bipush #50
    //   963: ldc 1048576
    //   965: iastore
    //   966: dup
    //   967: bipush #51
    //   969: ldc -2147483616
    //   971: iastore
    //   972: dup
    //   973: bipush #52
    //   975: ldc 1048608
    //   977: iastore
    //   978: dup
    //   979: bipush #53
    //   981: ldc -2147450848
    //   983: iastore
    //   984: dup
    //   985: bipush #54
    //   987: ldc -2147483616
    //   989: iastore
    //   990: dup
    //   991: bipush #55
    //   993: ldc 1048608
    //   995: iastore
    //   996: dup
    //   997: bipush #56
    //   999: ldc 1081344
    //   1001: iastore
    //   1002: dup
    //   1003: bipush #57
    //   1005: iconst_0
    //   1006: iastore
    //   1007: dup
    //   1008: bipush #58
    //   1010: ldc -2147450880
    //   1012: iastore
    //   1013: dup
    //   1014: bipush #59
    //   1016: ldc 32800
    //   1018: iastore
    //   1019: dup
    //   1020: bipush #60
    //   1022: ldc -2147483648
    //   1024: iastore
    //   1025: dup
    //   1026: bipush #61
    //   1028: ldc -2146435040
    //   1030: iastore
    //   1031: dup
    //   1032: bipush #62
    //   1034: ldc -2146402272
    //   1036: iastore
    //   1037: dup
    //   1038: bipush #63
    //   1040: ldc 1081344
    //   1042: iastore
    //   1043: astore #9
    //   1045: bipush #64
    //   1047: newarray int
    //   1049: dup
    //   1050: iconst_0
    //   1051: sipush #520
    //   1054: iastore
    //   1055: dup
    //   1056: iconst_1
    //   1057: ldc 134349312
    //   1059: iastore
    //   1060: dup
    //   1061: iconst_2
    //   1062: iconst_0
    //   1063: iastore
    //   1064: dup
    //   1065: iconst_3
    //   1066: ldc 134348808
    //   1068: iastore
    //   1069: dup
    //   1070: iconst_4
    //   1071: ldc 134218240
    //   1073: iastore
    //   1074: dup
    //   1075: iconst_5
    //   1076: iconst_0
    //   1077: iastore
    //   1078: dup
    //   1079: bipush #6
    //   1081: ldc 131592
    //   1083: iastore
    //   1084: dup
    //   1085: bipush #7
    //   1087: ldc 134218240
    //   1089: iastore
    //   1090: dup
    //   1091: bipush #8
    //   1093: ldc 131080
    //   1095: iastore
    //   1096: dup
    //   1097: bipush #9
    //   1099: ldc 134217736
    //   1101: iastore
    //   1102: dup
    //   1103: bipush #10
    //   1105: ldc 134217736
    //   1107: iastore
    //   1108: dup
    //   1109: bipush #11
    //   1111: ldc 131072
    //   1113: iastore
    //   1114: dup
    //   1115: bipush #12
    //   1117: ldc 134349320
    //   1119: iastore
    //   1120: dup
    //   1121: bipush #13
    //   1123: ldc 131080
    //   1125: iastore
    //   1126: dup
    //   1127: bipush #14
    //   1129: ldc 134348800
    //   1131: iastore
    //   1132: dup
    //   1133: bipush #15
    //   1135: sipush #520
    //   1138: iastore
    //   1139: dup
    //   1140: bipush #16
    //   1142: ldc 134217728
    //   1144: iastore
    //   1145: dup
    //   1146: bipush #17
    //   1148: bipush #8
    //   1150: iastore
    //   1151: dup
    //   1152: bipush #18
    //   1154: ldc 134349312
    //   1156: iastore
    //   1157: dup
    //   1158: bipush #19
    //   1160: sipush #512
    //   1163: iastore
    //   1164: dup
    //   1165: bipush #20
    //   1167: ldc 131584
    //   1169: iastore
    //   1170: dup
    //   1171: bipush #21
    //   1173: ldc 134348800
    //   1175: iastore
    //   1176: dup
    //   1177: bipush #22
    //   1179: ldc 134348808
    //   1181: iastore
    //   1182: dup
    //   1183: bipush #23
    //   1185: ldc 131592
    //   1187: iastore
    //   1188: dup
    //   1189: bipush #24
    //   1191: ldc 134218248
    //   1193: iastore
    //   1194: dup
    //   1195: bipush #25
    //   1197: ldc 131584
    //   1199: iastore
    //   1200: dup
    //   1201: bipush #26
    //   1203: ldc 131072
    //   1205: iastore
    //   1206: dup
    //   1207: bipush #27
    //   1209: ldc 134218248
    //   1211: iastore
    //   1212: dup
    //   1213: bipush #28
    //   1215: bipush #8
    //   1217: iastore
    //   1218: dup
    //   1219: bipush #29
    //   1221: ldc 134349320
    //   1223: iastore
    //   1224: dup
    //   1225: bipush #30
    //   1227: sipush #512
    //   1230: iastore
    //   1231: dup
    //   1232: bipush #31
    //   1234: ldc 134217728
    //   1236: iastore
    //   1237: dup
    //   1238: bipush #32
    //   1240: ldc 134349312
    //   1242: iastore
    //   1243: dup
    //   1244: bipush #33
    //   1246: ldc 134217728
    //   1248: iastore
    //   1249: dup
    //   1250: bipush #34
    //   1252: ldc 131080
    //   1254: iastore
    //   1255: dup
    //   1256: bipush #35
    //   1258: sipush #520
    //   1261: iastore
    //   1262: dup
    //   1263: bipush #36
    //   1265: ldc 131072
    //   1267: iastore
    //   1268: dup
    //   1269: bipush #37
    //   1271: ldc 134349312
    //   1273: iastore
    //   1274: dup
    //   1275: bipush #38
    //   1277: ldc 134218240
    //   1279: iastore
    //   1280: dup
    //   1281: bipush #39
    //   1283: iconst_0
    //   1284: iastore
    //   1285: dup
    //   1286: bipush #40
    //   1288: sipush #512
    //   1291: iastore
    //   1292: dup
    //   1293: bipush #41
    //   1295: ldc 131080
    //   1297: iastore
    //   1298: dup
    //   1299: bipush #42
    //   1301: ldc 134349320
    //   1303: iastore
    //   1304: dup
    //   1305: bipush #43
    //   1307: ldc 134218240
    //   1309: iastore
    //   1310: dup
    //   1311: bipush #44
    //   1313: ldc 134217736
    //   1315: iastore
    //   1316: dup
    //   1317: bipush #45
    //   1319: sipush #512
    //   1322: iastore
    //   1323: dup
    //   1324: bipush #46
    //   1326: iconst_0
    //   1327: iastore
    //   1328: dup
    //   1329: bipush #47
    //   1331: ldc 134348808
    //   1333: iastore
    //   1334: dup
    //   1335: bipush #48
    //   1337: ldc 134218248
    //   1339: iastore
    //   1340: dup
    //   1341: bipush #49
    //   1343: ldc 131072
    //   1345: iastore
    //   1346: dup
    //   1347: bipush #50
    //   1349: ldc 134217728
    //   1351: iastore
    //   1352: dup
    //   1353: bipush #51
    //   1355: ldc 134349320
    //   1357: iastore
    //   1358: dup
    //   1359: bipush #52
    //   1361: bipush #8
    //   1363: iastore
    //   1364: dup
    //   1365: bipush #53
    //   1367: ldc 131592
    //   1369: iastore
    //   1370: dup
    //   1371: bipush #54
    //   1373: ldc 131584
    //   1375: iastore
    //   1376: dup
    //   1377: bipush #55
    //   1379: ldc 134217736
    //   1381: iastore
    //   1382: dup
    //   1383: bipush #56
    //   1385: ldc 134348800
    //   1387: iastore
    //   1388: dup
    //   1389: bipush #57
    //   1391: ldc 134218248
    //   1393: iastore
    //   1394: dup
    //   1395: bipush #58
    //   1397: sipush #520
    //   1400: iastore
    //   1401: dup
    //   1402: bipush #59
    //   1404: ldc 134348800
    //   1406: iastore
    //   1407: dup
    //   1408: bipush #60
    //   1410: ldc 131592
    //   1412: iastore
    //   1413: dup
    //   1414: bipush #61
    //   1416: bipush #8
    //   1418: iastore
    //   1419: dup
    //   1420: bipush #62
    //   1422: ldc 134348808
    //   1424: iastore
    //   1425: dup
    //   1426: bipush #63
    //   1428: ldc 131584
    //   1430: iastore
    //   1431: astore #10
    //   1433: bipush #64
    //   1435: newarray int
    //   1437: dup
    //   1438: iconst_0
    //   1439: ldc 8396801
    //   1441: iastore
    //   1442: dup
    //   1443: iconst_1
    //   1444: sipush #8321
    //   1447: iastore
    //   1448: dup
    //   1449: iconst_2
    //   1450: sipush #8321
    //   1453: iastore
    //   1454: dup
    //   1455: iconst_3
    //   1456: sipush #128
    //   1459: iastore
    //   1460: dup
    //   1461: iconst_4
    //   1462: ldc 8396928
    //   1464: iastore
    //   1465: dup
    //   1466: iconst_5
    //   1467: ldc 8388737
    //   1469: iastore
    //   1470: dup
    //   1471: bipush #6
    //   1473: ldc 8388609
    //   1475: iastore
    //   1476: dup
    //   1477: bipush #7
    //   1479: sipush #8193
    //   1482: iastore
    //   1483: dup
    //   1484: bipush #8
    //   1486: iconst_0
    //   1487: iastore
    //   1488: dup
    //   1489: bipush #9
    //   1491: ldc 8396800
    //   1493: iastore
    //   1494: dup
    //   1495: bipush #10
    //   1497: ldc 8396800
    //   1499: iastore
    //   1500: dup
    //   1501: bipush #11
    //   1503: ldc 8396929
    //   1505: iastore
    //   1506: dup
    //   1507: bipush #12
    //   1509: sipush #129
    //   1512: iastore
    //   1513: dup
    //   1514: bipush #13
    //   1516: iconst_0
    //   1517: iastore
    //   1518: dup
    //   1519: bipush #14
    //   1521: ldc 8388736
    //   1523: iastore
    //   1524: dup
    //   1525: bipush #15
    //   1527: ldc 8388609
    //   1529: iastore
    //   1530: dup
    //   1531: bipush #16
    //   1533: iconst_1
    //   1534: iastore
    //   1535: dup
    //   1536: bipush #17
    //   1538: sipush #8192
    //   1541: iastore
    //   1542: dup
    //   1543: bipush #18
    //   1545: ldc 8388608
    //   1547: iastore
    //   1548: dup
    //   1549: bipush #19
    //   1551: ldc 8396801
    //   1553: iastore
    //   1554: dup
    //   1555: bipush #20
    //   1557: sipush #128
    //   1560: iastore
    //   1561: dup
    //   1562: bipush #21
    //   1564: ldc 8388608
    //   1566: iastore
    //   1567: dup
    //   1568: bipush #22
    //   1570: sipush #8193
    //   1573: iastore
    //   1574: dup
    //   1575: bipush #23
    //   1577: sipush #8320
    //   1580: iastore
    //   1581: dup
    //   1582: bipush #24
    //   1584: ldc 8388737
    //   1586: iastore
    //   1587: dup
    //   1588: bipush #25
    //   1590: iconst_1
    //   1591: iastore
    //   1592: dup
    //   1593: bipush #26
    //   1595: sipush #8320
    //   1598: iastore
    //   1599: dup
    //   1600: bipush #27
    //   1602: ldc 8388736
    //   1604: iastore
    //   1605: dup
    //   1606: bipush #28
    //   1608: sipush #8192
    //   1611: iastore
    //   1612: dup
    //   1613: bipush #29
    //   1615: ldc 8396928
    //   1617: iastore
    //   1618: dup
    //   1619: bipush #30
    //   1621: ldc 8396929
    //   1623: iastore
    //   1624: dup
    //   1625: bipush #31
    //   1627: sipush #129
    //   1630: iastore
    //   1631: dup
    //   1632: bipush #32
    //   1634: ldc 8388736
    //   1636: iastore
    //   1637: dup
    //   1638: bipush #33
    //   1640: ldc 8388609
    //   1642: iastore
    //   1643: dup
    //   1644: bipush #34
    //   1646: ldc 8396800
    //   1648: iastore
    //   1649: dup
    //   1650: bipush #35
    //   1652: ldc 8396929
    //   1654: iastore
    //   1655: dup
    //   1656: bipush #36
    //   1658: sipush #129
    //   1661: iastore
    //   1662: dup
    //   1663: bipush #37
    //   1665: iconst_0
    //   1666: iastore
    //   1667: dup
    //   1668: bipush #38
    //   1670: iconst_0
    //   1671: iastore
    //   1672: dup
    //   1673: bipush #39
    //   1675: ldc 8396800
    //   1677: iastore
    //   1678: dup
    //   1679: bipush #40
    //   1681: sipush #8320
    //   1684: iastore
    //   1685: dup
    //   1686: bipush #41
    //   1688: ldc 8388736
    //   1690: iastore
    //   1691: dup
    //   1692: bipush #42
    //   1694: ldc 8388737
    //   1696: iastore
    //   1697: dup
    //   1698: bipush #43
    //   1700: iconst_1
    //   1701: iastore
    //   1702: dup
    //   1703: bipush #44
    //   1705: ldc 8396801
    //   1707: iastore
    //   1708: dup
    //   1709: bipush #45
    //   1711: sipush #8321
    //   1714: iastore
    //   1715: dup
    //   1716: bipush #46
    //   1718: sipush #8321
    //   1721: iastore
    //   1722: dup
    //   1723: bipush #47
    //   1725: sipush #128
    //   1728: iastore
    //   1729: dup
    //   1730: bipush #48
    //   1732: ldc 8396929
    //   1734: iastore
    //   1735: dup
    //   1736: bipush #49
    //   1738: sipush #129
    //   1741: iastore
    //   1742: dup
    //   1743: bipush #50
    //   1745: iconst_1
    //   1746: iastore
    //   1747: dup
    //   1748: bipush #51
    //   1750: sipush #8192
    //   1753: iastore
    //   1754: dup
    //   1755: bipush #52
    //   1757: ldc 8388609
    //   1759: iastore
    //   1760: dup
    //   1761: bipush #53
    //   1763: sipush #8193
    //   1766: iastore
    //   1767: dup
    //   1768: bipush #54
    //   1770: ldc 8396928
    //   1772: iastore
    //   1773: dup
    //   1774: bipush #55
    //   1776: ldc 8388737
    //   1778: iastore
    //   1779: dup
    //   1780: bipush #56
    //   1782: sipush #8193
    //   1785: iastore
    //   1786: dup
    //   1787: bipush #57
    //   1789: sipush #8320
    //   1792: iastore
    //   1793: dup
    //   1794: bipush #58
    //   1796: ldc 8388608
    //   1798: iastore
    //   1799: dup
    //   1800: bipush #59
    //   1802: ldc 8396801
    //   1804: iastore
    //   1805: dup
    //   1806: bipush #60
    //   1808: sipush #128
    //   1811: iastore
    //   1812: dup
    //   1813: bipush #61
    //   1815: ldc 8388608
    //   1817: iastore
    //   1818: dup
    //   1819: bipush #62
    //   1821: sipush #8192
    //   1824: iastore
    //   1825: dup
    //   1826: bipush #63
    //   1828: ldc 8396928
    //   1830: iastore
    //   1831: astore #11
    //   1833: bipush #64
    //   1835: newarray int
    //   1837: dup
    //   1838: iconst_0
    //   1839: sipush #256
    //   1842: iastore
    //   1843: dup
    //   1844: iconst_1
    //   1845: ldc 34078976
    //   1847: iastore
    //   1848: dup
    //   1849: iconst_2
    //   1850: ldc 34078720
    //   1852: iastore
    //   1853: dup
    //   1854: iconst_3
    //   1855: ldc 1107296512
    //   1857: iastore
    //   1858: dup
    //   1859: iconst_4
    //   1860: ldc 524288
    //   1862: iastore
    //   1863: dup
    //   1864: iconst_5
    //   1865: sipush #256
    //   1868: iastore
    //   1869: dup
    //   1870: bipush #6
    //   1872: ldc 1073741824
    //   1874: iastore
    //   1875: dup
    //   1876: bipush #7
    //   1878: ldc 34078720
    //   1880: iastore
    //   1881: dup
    //   1882: bipush #8
    //   1884: ldc 1074266368
    //   1886: iastore
    //   1887: dup
    //   1888: bipush #9
    //   1890: ldc 524288
    //   1892: iastore
    //   1893: dup
    //   1894: bipush #10
    //   1896: ldc 33554688
    //   1898: iastore
    //   1899: dup
    //   1900: bipush #11
    //   1902: ldc 1074266368
    //   1904: iastore
    //   1905: dup
    //   1906: bipush #12
    //   1908: ldc 1107296512
    //   1910: iastore
    //   1911: dup
    //   1912: bipush #13
    //   1914: ldc 1107820544
    //   1916: iastore
    //   1917: dup
    //   1918: bipush #14
    //   1920: ldc 524544
    //   1922: iastore
    //   1923: dup
    //   1924: bipush #15
    //   1926: ldc 1073741824
    //   1928: iastore
    //   1929: dup
    //   1930: bipush #16
    //   1932: ldc 33554432
    //   1934: iastore
    //   1935: dup
    //   1936: bipush #17
    //   1938: ldc 1074266112
    //   1940: iastore
    //   1941: dup
    //   1942: bipush #18
    //   1944: ldc 1074266112
    //   1946: iastore
    //   1947: dup
    //   1948: bipush #19
    //   1950: iconst_0
    //   1951: iastore
    //   1952: dup
    //   1953: bipush #20
    //   1955: ldc 1073742080
    //   1957: iastore
    //   1958: dup
    //   1959: bipush #21
    //   1961: ldc 1107820800
    //   1963: iastore
    //   1964: dup
    //   1965: bipush #22
    //   1967: ldc 1107820800
    //   1969: iastore
    //   1970: dup
    //   1971: bipush #23
    //   1973: ldc 33554688
    //   1975: iastore
    //   1976: dup
    //   1977: bipush #24
    //   1979: ldc 1107820544
    //   1981: iastore
    //   1982: dup
    //   1983: bipush #25
    //   1985: ldc 1073742080
    //   1987: iastore
    //   1988: dup
    //   1989: bipush #26
    //   1991: iconst_0
    //   1992: iastore
    //   1993: dup
    //   1994: bipush #27
    //   1996: ldc 1107296256
    //   1998: iastore
    //   1999: dup
    //   2000: bipush #28
    //   2002: ldc 34078976
    //   2004: iastore
    //   2005: dup
    //   2006: bipush #29
    //   2008: ldc 33554432
    //   2010: iastore
    //   2011: dup
    //   2012: bipush #30
    //   2014: ldc 1107296256
    //   2016: iastore
    //   2017: dup
    //   2018: bipush #31
    //   2020: ldc 524544
    //   2022: iastore
    //   2023: dup
    //   2024: bipush #32
    //   2026: ldc 524288
    //   2028: iastore
    //   2029: dup
    //   2030: bipush #33
    //   2032: ldc 1107296512
    //   2034: iastore
    //   2035: dup
    //   2036: bipush #34
    //   2038: sipush #256
    //   2041: iastore
    //   2042: dup
    //   2043: bipush #35
    //   2045: ldc 33554432
    //   2047: iastore
    //   2048: dup
    //   2049: bipush #36
    //   2051: ldc 1073741824
    //   2053: iastore
    //   2054: dup
    //   2055: bipush #37
    //   2057: ldc 34078720
    //   2059: iastore
    //   2060: dup
    //   2061: bipush #38
    //   2063: ldc 1107296512
    //   2065: iastore
    //   2066: dup
    //   2067: bipush #39
    //   2069: ldc 1074266368
    //   2071: iastore
    //   2072: dup
    //   2073: bipush #40
    //   2075: ldc 33554688
    //   2077: iastore
    //   2078: dup
    //   2079: bipush #41
    //   2081: ldc 1073741824
    //   2083: iastore
    //   2084: dup
    //   2085: bipush #42
    //   2087: ldc 1107820544
    //   2089: iastore
    //   2090: dup
    //   2091: bipush #43
    //   2093: ldc 34078976
    //   2095: iastore
    //   2096: dup
    //   2097: bipush #44
    //   2099: ldc 1074266368
    //   2101: iastore
    //   2102: dup
    //   2103: bipush #45
    //   2105: sipush #256
    //   2108: iastore
    //   2109: dup
    //   2110: bipush #46
    //   2112: ldc 33554432
    //   2114: iastore
    //   2115: dup
    //   2116: bipush #47
    //   2118: ldc 1107820544
    //   2120: iastore
    //   2121: dup
    //   2122: bipush #48
    //   2124: ldc 1107820800
    //   2126: iastore
    //   2127: dup
    //   2128: bipush #49
    //   2130: ldc 524544
    //   2132: iastore
    //   2133: dup
    //   2134: bipush #50
    //   2136: ldc 1107296256
    //   2138: iastore
    //   2139: dup
    //   2140: bipush #51
    //   2142: ldc 1107820800
    //   2144: iastore
    //   2145: dup
    //   2146: bipush #52
    //   2148: ldc 34078720
    //   2150: iastore
    //   2151: dup
    //   2152: bipush #53
    //   2154: iconst_0
    //   2155: iastore
    //   2156: dup
    //   2157: bipush #54
    //   2159: ldc 1074266112
    //   2161: iastore
    //   2162: dup
    //   2163: bipush #55
    //   2165: ldc 1107296256
    //   2167: iastore
    //   2168: dup
    //   2169: bipush #56
    //   2171: ldc 524544
    //   2173: iastore
    //   2174: dup
    //   2175: bipush #57
    //   2177: ldc 33554688
    //   2179: iastore
    //   2180: dup
    //   2181: bipush #58
    //   2183: ldc 1073742080
    //   2185: iastore
    //   2186: dup
    //   2187: bipush #59
    //   2189: ldc 524288
    //   2191: iastore
    //   2192: dup
    //   2193: bipush #60
    //   2195: iconst_0
    //   2196: iastore
    //   2197: dup
    //   2198: bipush #61
    //   2200: ldc 1074266112
    //   2202: iastore
    //   2203: dup
    //   2204: bipush #62
    //   2206: ldc 34078976
    //   2208: iastore
    //   2209: dup
    //   2210: bipush #63
    //   2212: ldc 1073742080
    //   2214: iastore
    //   2215: astore #12
    //   2217: bipush #64
    //   2219: newarray int
    //   2221: dup
    //   2222: iconst_0
    //   2223: ldc 536870928
    //   2225: iastore
    //   2226: dup
    //   2227: iconst_1
    //   2228: ldc 541065216
    //   2230: iastore
    //   2231: dup
    //   2232: iconst_2
    //   2233: sipush #16384
    //   2236: iastore
    //   2237: dup
    //   2238: iconst_3
    //   2239: ldc 541081616
    //   2241: iastore
    //   2242: dup
    //   2243: iconst_4
    //   2244: ldc 541065216
    //   2246: iastore
    //   2247: dup
    //   2248: iconst_5
    //   2249: bipush #16
    //   2251: iastore
    //   2252: dup
    //   2253: bipush #6
    //   2255: ldc 541081616
    //   2257: iastore
    //   2258: dup
    //   2259: bipush #7
    //   2261: ldc 4194304
    //   2263: iastore
    //   2264: dup
    //   2265: bipush #8
    //   2267: ldc 536887296
    //   2269: iastore
    //   2270: dup
    //   2271: bipush #9
    //   2273: ldc 4210704
    //   2275: iastore
    //   2276: dup
    //   2277: bipush #10
    //   2279: ldc 4194304
    //   2281: iastore
    //   2282: dup
    //   2283: bipush #11
    //   2285: ldc 536870928
    //   2287: iastore
    //   2288: dup
    //   2289: bipush #12
    //   2291: ldc 4194320
    //   2293: iastore
    //   2294: dup
    //   2295: bipush #13
    //   2297: ldc 536887296
    //   2299: iastore
    //   2300: dup
    //   2301: bipush #14
    //   2303: ldc 536870912
    //   2305: iastore
    //   2306: dup
    //   2307: bipush #15
    //   2309: sipush #16400
    //   2312: iastore
    //   2313: dup
    //   2314: bipush #16
    //   2316: iconst_0
    //   2317: iastore
    //   2318: dup
    //   2319: bipush #17
    //   2321: ldc 4194320
    //   2323: iastore
    //   2324: dup
    //   2325: bipush #18
    //   2327: ldc 536887312
    //   2329: iastore
    //   2330: dup
    //   2331: bipush #19
    //   2333: sipush #16384
    //   2336: iastore
    //   2337: dup
    //   2338: bipush #20
    //   2340: ldc 4210688
    //   2342: iastore
    //   2343: dup
    //   2344: bipush #21
    //   2346: ldc 536887312
    //   2348: iastore
    //   2349: dup
    //   2350: bipush #22
    //   2352: bipush #16
    //   2354: iastore
    //   2355: dup
    //   2356: bipush #23
    //   2358: ldc 541065232
    //   2360: iastore
    //   2361: dup
    //   2362: bipush #24
    //   2364: ldc 541065232
    //   2366: iastore
    //   2367: dup
    //   2368: bipush #25
    //   2370: iconst_0
    //   2371: iastore
    //   2372: dup
    //   2373: bipush #26
    //   2375: ldc 4210704
    //   2377: iastore
    //   2378: dup
    //   2379: bipush #27
    //   2381: ldc 541081600
    //   2383: iastore
    //   2384: dup
    //   2385: bipush #28
    //   2387: sipush #16400
    //   2390: iastore
    //   2391: dup
    //   2392: bipush #29
    //   2394: ldc 4210688
    //   2396: iastore
    //   2397: dup
    //   2398: bipush #30
    //   2400: ldc 541081600
    //   2402: iastore
    //   2403: dup
    //   2404: bipush #31
    //   2406: ldc 536870912
    //   2408: iastore
    //   2409: dup
    //   2410: bipush #32
    //   2412: ldc 536887296
    //   2414: iastore
    //   2415: dup
    //   2416: bipush #33
    //   2418: bipush #16
    //   2420: iastore
    //   2421: dup
    //   2422: bipush #34
    //   2424: ldc 541065232
    //   2426: iastore
    //   2427: dup
    //   2428: bipush #35
    //   2430: ldc 4210688
    //   2432: iastore
    //   2433: dup
    //   2434: bipush #36
    //   2436: ldc 541081616
    //   2438: iastore
    //   2439: dup
    //   2440: bipush #37
    //   2442: ldc 4194304
    //   2444: iastore
    //   2445: dup
    //   2446: bipush #38
    //   2448: sipush #16400
    //   2451: iastore
    //   2452: dup
    //   2453: bipush #39
    //   2455: ldc 536870928
    //   2457: iastore
    //   2458: dup
    //   2459: bipush #40
    //   2461: ldc 4194304
    //   2463: iastore
    //   2464: dup
    //   2465: bipush #41
    //   2467: ldc 536887296
    //   2469: iastore
    //   2470: dup
    //   2471: bipush #42
    //   2473: ldc 536870912
    //   2475: iastore
    //   2476: dup
    //   2477: bipush #43
    //   2479: sipush #16400
    //   2482: iastore
    //   2483: dup
    //   2484: bipush #44
    //   2486: ldc 536870928
    //   2488: iastore
    //   2489: dup
    //   2490: bipush #45
    //   2492: ldc 541081616
    //   2494: iastore
    //   2495: dup
    //   2496: bipush #46
    //   2498: ldc 4210688
    //   2500: iastore
    //   2501: dup
    //   2502: bipush #47
    //   2504: ldc 541065216
    //   2506: iastore
    //   2507: dup
    //   2508: bipush #48
    //   2510: ldc 4210704
    //   2512: iastore
    //   2513: dup
    //   2514: bipush #49
    //   2516: ldc 541081600
    //   2518: iastore
    //   2519: dup
    //   2520: bipush #50
    //   2522: iconst_0
    //   2523: iastore
    //   2524: dup
    //   2525: bipush #51
    //   2527: ldc 541065232
    //   2529: iastore
    //   2530: dup
    //   2531: bipush #52
    //   2533: bipush #16
    //   2535: iastore
    //   2536: dup
    //   2537: bipush #53
    //   2539: sipush #16384
    //   2542: iastore
    //   2543: dup
    //   2544: bipush #54
    //   2546: ldc 541065216
    //   2548: iastore
    //   2549: dup
    //   2550: bipush #55
    //   2552: ldc 4210704
    //   2554: iastore
    //   2555: dup
    //   2556: bipush #56
    //   2558: sipush #16384
    //   2561: iastore
    //   2562: dup
    //   2563: bipush #57
    //   2565: ldc 4194320
    //   2567: iastore
    //   2568: dup
    //   2569: bipush #58
    //   2571: ldc 536887312
    //   2573: iastore
    //   2574: dup
    //   2575: bipush #59
    //   2577: iconst_0
    //   2578: iastore
    //   2579: dup
    //   2580: bipush #60
    //   2582: ldc 541081600
    //   2584: iastore
    //   2585: dup
    //   2586: bipush #61
    //   2588: ldc 536870912
    //   2590: iastore
    //   2591: dup
    //   2592: bipush #62
    //   2594: ldc 4194320
    //   2596: iastore
    //   2597: dup
    //   2598: bipush #63
    //   2600: ldc 536887312
    //   2602: iastore
    //   2603: astore #13
    //   2605: bipush #64
    //   2607: newarray int
    //   2609: dup
    //   2610: iconst_0
    //   2611: ldc 2097152
    //   2613: iastore
    //   2614: dup
    //   2615: iconst_1
    //   2616: ldc 69206018
    //   2618: iastore
    //   2619: dup
    //   2620: iconst_2
    //   2621: ldc 67110914
    //   2623: iastore
    //   2624: dup
    //   2625: iconst_3
    //   2626: iconst_0
    //   2627: iastore
    //   2628: dup
    //   2629: iconst_4
    //   2630: sipush #2048
    //   2633: iastore
    //   2634: dup
    //   2635: iconst_5
    //   2636: ldc 67110914
    //   2638: iastore
    //   2639: dup
    //   2640: bipush #6
    //   2642: ldc 2099202
    //   2644: iastore
    //   2645: dup
    //   2646: bipush #7
    //   2648: ldc 69208064
    //   2650: iastore
    //   2651: dup
    //   2652: bipush #8
    //   2654: ldc 69208066
    //   2656: iastore
    //   2657: dup
    //   2658: bipush #9
    //   2660: ldc 2097152
    //   2662: iastore
    //   2663: dup
    //   2664: bipush #10
    //   2666: iconst_0
    //   2667: iastore
    //   2668: dup
    //   2669: bipush #11
    //   2671: ldc 67108866
    //   2673: iastore
    //   2674: dup
    //   2675: bipush #12
    //   2677: iconst_2
    //   2678: iastore
    //   2679: dup
    //   2680: bipush #13
    //   2682: ldc 67108864
    //   2684: iastore
    //   2685: dup
    //   2686: bipush #14
    //   2688: ldc 69206018
    //   2690: iastore
    //   2691: dup
    //   2692: bipush #15
    //   2694: sipush #2050
    //   2697: iastore
    //   2698: dup
    //   2699: bipush #16
    //   2701: ldc 67110912
    //   2703: iastore
    //   2704: dup
    //   2705: bipush #17
    //   2707: ldc 2099202
    //   2709: iastore
    //   2710: dup
    //   2711: bipush #18
    //   2713: ldc 2097154
    //   2715: iastore
    //   2716: dup
    //   2717: bipush #19
    //   2719: ldc 67110912
    //   2721: iastore
    //   2722: dup
    //   2723: bipush #20
    //   2725: ldc 67108866
    //   2727: iastore
    //   2728: dup
    //   2729: bipush #21
    //   2731: ldc 69206016
    //   2733: iastore
    //   2734: dup
    //   2735: bipush #22
    //   2737: ldc 69208064
    //   2739: iastore
    //   2740: dup
    //   2741: bipush #23
    //   2743: ldc 2097154
    //   2745: iastore
    //   2746: dup
    //   2747: bipush #24
    //   2749: ldc 69206016
    //   2751: iastore
    //   2752: dup
    //   2753: bipush #25
    //   2755: sipush #2048
    //   2758: iastore
    //   2759: dup
    //   2760: bipush #26
    //   2762: sipush #2050
    //   2765: iastore
    //   2766: dup
    //   2767: bipush #27
    //   2769: ldc 69208066
    //   2771: iastore
    //   2772: dup
    //   2773: bipush #28
    //   2775: ldc 2099200
    //   2777: iastore
    //   2778: dup
    //   2779: bipush #29
    //   2781: iconst_2
    //   2782: iastore
    //   2783: dup
    //   2784: bipush #30
    //   2786: ldc 67108864
    //   2788: iastore
    //   2789: dup
    //   2790: bipush #31
    //   2792: ldc 2099200
    //   2794: iastore
    //   2795: dup
    //   2796: bipush #32
    //   2798: ldc 67108864
    //   2800: iastore
    //   2801: dup
    //   2802: bipush #33
    //   2804: ldc 2099200
    //   2806: iastore
    //   2807: dup
    //   2808: bipush #34
    //   2810: ldc 2097152
    //   2812: iastore
    //   2813: dup
    //   2814: bipush #35
    //   2816: ldc 67110914
    //   2818: iastore
    //   2819: dup
    //   2820: bipush #36
    //   2822: ldc 67110914
    //   2824: iastore
    //   2825: dup
    //   2826: bipush #37
    //   2828: ldc 69206018
    //   2830: iastore
    //   2831: dup
    //   2832: bipush #38
    //   2834: ldc 69206018
    //   2836: iastore
    //   2837: dup
    //   2838: bipush #39
    //   2840: iconst_2
    //   2841: iastore
    //   2842: dup
    //   2843: bipush #40
    //   2845: ldc 2097154
    //   2847: iastore
    //   2848: dup
    //   2849: bipush #41
    //   2851: ldc 67108864
    //   2853: iastore
    //   2854: dup
    //   2855: bipush #42
    //   2857: ldc 67110912
    //   2859: iastore
    //   2860: dup
    //   2861: bipush #43
    //   2863: ldc 2097152
    //   2865: iastore
    //   2866: dup
    //   2867: bipush #44
    //   2869: ldc 69208064
    //   2871: iastore
    //   2872: dup
    //   2873: bipush #45
    //   2875: sipush #2050
    //   2878: iastore
    //   2879: dup
    //   2880: bipush #46
    //   2882: ldc 2099202
    //   2884: iastore
    //   2885: dup
    //   2886: bipush #47
    //   2888: ldc 69208064
    //   2890: iastore
    //   2891: dup
    //   2892: bipush #48
    //   2894: sipush #2050
    //   2897: iastore
    //   2898: dup
    //   2899: bipush #49
    //   2901: ldc 67108866
    //   2903: iastore
    //   2904: dup
    //   2905: bipush #50
    //   2907: ldc 69208066
    //   2909: iastore
    //   2910: dup
    //   2911: bipush #51
    //   2913: ldc 69206016
    //   2915: iastore
    //   2916: dup
    //   2917: bipush #52
    //   2919: ldc 2099200
    //   2921: iastore
    //   2922: dup
    //   2923: bipush #53
    //   2925: iconst_0
    //   2926: iastore
    //   2927: dup
    //   2928: bipush #54
    //   2930: iconst_2
    //   2931: iastore
    //   2932: dup
    //   2933: bipush #55
    //   2935: ldc 69208066
    //   2937: iastore
    //   2938: dup
    //   2939: bipush #56
    //   2941: iconst_0
    //   2942: iastore
    //   2943: dup
    //   2944: bipush #57
    //   2946: ldc 2099202
    //   2948: iastore
    //   2949: dup
    //   2950: bipush #58
    //   2952: ldc 69206016
    //   2954: iastore
    //   2955: dup
    //   2956: bipush #59
    //   2958: sipush #2048
    //   2961: iastore
    //   2962: dup
    //   2963: bipush #60
    //   2965: ldc 67108866
    //   2967: iastore
    //   2968: dup
    //   2969: bipush #61
    //   2971: ldc 67110912
    //   2973: iastore
    //   2974: dup
    //   2975: bipush #62
    //   2977: sipush #2048
    //   2980: iastore
    //   2981: dup
    //   2982: bipush #63
    //   2984: ldc 2097154
    //   2986: iastore
    //   2987: astore #14
    //   2989: bipush #64
    //   2991: newarray int
    //   2993: dup
    //   2994: iconst_0
    //   2995: ldc 268439616
    //   2997: iastore
    //   2998: dup
    //   2999: iconst_1
    //   3000: sipush #4096
    //   3003: iastore
    //   3004: dup
    //   3005: iconst_2
    //   3006: ldc 262144
    //   3008: iastore
    //   3009: dup
    //   3010: iconst_3
    //   3011: ldc 268701760
    //   3013: iastore
    //   3014: dup
    //   3015: iconst_4
    //   3016: ldc 268435456
    //   3018: iastore
    //   3019: dup
    //   3020: iconst_5
    //   3021: ldc 268439616
    //   3023: iastore
    //   3024: dup
    //   3025: bipush #6
    //   3027: bipush #64
    //   3029: iastore
    //   3030: dup
    //   3031: bipush #7
    //   3033: ldc 268435456
    //   3035: iastore
    //   3036: dup
    //   3037: bipush #8
    //   3039: ldc 262208
    //   3041: iastore
    //   3042: dup
    //   3043: bipush #9
    //   3045: ldc 268697600
    //   3047: iastore
    //   3048: dup
    //   3049: bipush #10
    //   3051: ldc 268701760
    //   3053: iastore
    //   3054: dup
    //   3055: bipush #11
    //   3057: ldc 266240
    //   3059: iastore
    //   3060: dup
    //   3061: bipush #12
    //   3063: ldc 268701696
    //   3065: iastore
    //   3066: dup
    //   3067: bipush #13
    //   3069: ldc 266304
    //   3071: iastore
    //   3072: dup
    //   3073: bipush #14
    //   3075: sipush #4096
    //   3078: iastore
    //   3079: dup
    //   3080: bipush #15
    //   3082: bipush #64
    //   3084: iastore
    //   3085: dup
    //   3086: bipush #16
    //   3088: ldc 268697600
    //   3090: iastore
    //   3091: dup
    //   3092: bipush #17
    //   3094: ldc 268435520
    //   3096: iastore
    //   3097: dup
    //   3098: bipush #18
    //   3100: ldc 268439552
    //   3102: iastore
    //   3103: dup
    //   3104: bipush #19
    //   3106: sipush #4160
    //   3109: iastore
    //   3110: dup
    //   3111: bipush #20
    //   3113: ldc 266240
    //   3115: iastore
    //   3116: dup
    //   3117: bipush #21
    //   3119: ldc 262208
    //   3121: iastore
    //   3122: dup
    //   3123: bipush #22
    //   3125: ldc 268697664
    //   3127: iastore
    //   3128: dup
    //   3129: bipush #23
    //   3131: ldc 268701696
    //   3133: iastore
    //   3134: dup
    //   3135: bipush #24
    //   3137: sipush #4160
    //   3140: iastore
    //   3141: dup
    //   3142: bipush #25
    //   3144: iconst_0
    //   3145: iastore
    //   3146: dup
    //   3147: bipush #26
    //   3149: iconst_0
    //   3150: iastore
    //   3151: dup
    //   3152: bipush #27
    //   3154: ldc 268697664
    //   3156: iastore
    //   3157: dup
    //   3158: bipush #28
    //   3160: ldc 268435520
    //   3162: iastore
    //   3163: dup
    //   3164: bipush #29
    //   3166: ldc 268439552
    //   3168: iastore
    //   3169: dup
    //   3170: bipush #30
    //   3172: ldc 266304
    //   3174: iastore
    //   3175: dup
    //   3176: bipush #31
    //   3178: ldc 262144
    //   3180: iastore
    //   3181: dup
    //   3182: bipush #32
    //   3184: ldc 266304
    //   3186: iastore
    //   3187: dup
    //   3188: bipush #33
    //   3190: ldc 262144
    //   3192: iastore
    //   3193: dup
    //   3194: bipush #34
    //   3196: ldc 268701696
    //   3198: iastore
    //   3199: dup
    //   3200: bipush #35
    //   3202: sipush #4096
    //   3205: iastore
    //   3206: dup
    //   3207: bipush #36
    //   3209: bipush #64
    //   3211: iastore
    //   3212: dup
    //   3213: bipush #37
    //   3215: ldc 268697664
    //   3217: iastore
    //   3218: dup
    //   3219: bipush #38
    //   3221: sipush #4096
    //   3224: iastore
    //   3225: dup
    //   3226: bipush #39
    //   3228: ldc 266304
    //   3230: iastore
    //   3231: dup
    //   3232: bipush #40
    //   3234: ldc 268439552
    //   3236: iastore
    //   3237: dup
    //   3238: bipush #41
    //   3240: bipush #64
    //   3242: iastore
    //   3243: dup
    //   3244: bipush #42
    //   3246: ldc 268435520
    //   3248: iastore
    //   3249: dup
    //   3250: bipush #43
    //   3252: ldc 268697600
    //   3254: iastore
    //   3255: dup
    //   3256: bipush #44
    //   3258: ldc 268697664
    //   3260: iastore
    //   3261: dup
    //   3262: bipush #45
    //   3264: ldc 268435456
    //   3266: iastore
    //   3267: dup
    //   3268: bipush #46
    //   3270: ldc 262144
    //   3272: iastore
    //   3273: dup
    //   3274: bipush #47
    //   3276: ldc 268439616
    //   3278: iastore
    //   3279: dup
    //   3280: bipush #48
    //   3282: iconst_0
    //   3283: iastore
    //   3284: dup
    //   3285: bipush #49
    //   3287: ldc 268701760
    //   3289: iastore
    //   3290: dup
    //   3291: bipush #50
    //   3293: ldc 262208
    //   3295: iastore
    //   3296: dup
    //   3297: bipush #51
    //   3299: ldc 268435520
    //   3301: iastore
    //   3302: dup
    //   3303: bipush #52
    //   3305: ldc 268697600
    //   3307: iastore
    //   3308: dup
    //   3309: bipush #53
    //   3311: ldc 268439552
    //   3313: iastore
    //   3314: dup
    //   3315: bipush #54
    //   3317: ldc 268439616
    //   3319: iastore
    //   3320: dup
    //   3321: bipush #55
    //   3323: iconst_0
    //   3324: iastore
    //   3325: dup
    //   3326: bipush #56
    //   3328: ldc 268701760
    //   3330: iastore
    //   3331: dup
    //   3332: bipush #57
    //   3334: ldc 266240
    //   3336: iastore
    //   3337: dup
    //   3338: bipush #58
    //   3340: ldc 266240
    //   3342: iastore
    //   3343: dup
    //   3344: bipush #59
    //   3346: sipush #4160
    //   3349: iastore
    //   3350: dup
    //   3351: bipush #60
    //   3353: sipush #4160
    //   3356: iastore
    //   3357: dup
    //   3358: bipush #61
    //   3360: ldc 262208
    //   3362: iastore
    //   3363: dup
    //   3364: bipush #62
    //   3366: ldc 268435456
    //   3368: iastore
    //   3369: dup
    //   3370: bipush #63
    //   3372: ldc 268701696
    //   3374: iastore
    //   3375: astore #15
    //   3377: aload_3
    //   3378: arraylength
    //   3379: istore #16
    //   3381: iconst_2
    //   3382: newarray int
    //   3384: astore #17
    //   3386: iload #16
    //   3388: newarray byte
    //   3390: astore #4
    //   3392: iload #16
    //   3394: bipush #8
    //   3396: idiv
    //   3397: istore #18
    //   3399: iconst_0
    //   3400: istore #19
    //   3402: iload #19
    //   3404: iload #18
    //   3406: if_icmpge -> 4320
    //   3409: iload #19
    //   3411: bipush #8
    //   3413: imul
    //   3414: istore #20
    //   3416: iconst_0
    //   3417: istore #21
    //   3419: iload #21
    //   3421: iconst_2
    //   3422: if_icmpge -> 3507
    //   3425: aload #17
    //   3427: iload #21
    //   3429: aload_3
    //   3430: iload #20
    //   3432: iload #21
    //   3434: iconst_4
    //   3435: imul
    //   3436: iadd
    //   3437: baload
    //   3438: sipush #255
    //   3441: iand
    //   3442: bipush #24
    //   3444: ishl
    //   3445: aload_3
    //   3446: iload #20
    //   3448: iload #21
    //   3450: iconst_4
    //   3451: imul
    //   3452: iadd
    //   3453: iconst_1
    //   3454: iadd
    //   3455: baload
    //   3456: sipush #255
    //   3459: iand
    //   3460: bipush #16
    //   3462: ishl
    //   3463: ior
    //   3464: aload_3
    //   3465: iload #20
    //   3467: iload #21
    //   3469: iconst_4
    //   3470: imul
    //   3471: iadd
    //   3472: iconst_2
    //   3473: iadd
    //   3474: baload
    //   3475: sipush #255
    //   3478: iand
    //   3479: bipush #8
    //   3481: ishl
    //   3482: ior
    //   3483: aload_3
    //   3484: iload #20
    //   3486: iload #21
    //   3488: iconst_4
    //   3489: imul
    //   3490: iadd
    //   3491: iconst_3
    //   3492: iadd
    //   3493: baload
    //   3494: sipush #255
    //   3497: iand
    //   3498: ior
    //   3499: iastore
    //   3500: iinc #21, 1
    //   3503: iload_2
    //   3504: ifeq -> 3419
    //   3507: iconst_0
    //   3508: istore #26
    //   3510: aload #17
    //   3512: iconst_0
    //   3513: iaload
    //   3514: istore #24
    //   3516: aload #17
    //   3518: iconst_1
    //   3519: iaload
    //   3520: istore #23
    //   3522: iload #24
    //   3524: iconst_4
    //   3525: iushr
    //   3526: iload #23
    //   3528: ixor
    //   3529: ldc 252645135
    //   3531: iand
    //   3532: istore #22
    //   3534: iload #23
    //   3536: iload #22
    //   3538: ixor
    //   3539: istore #23
    //   3541: iload #24
    //   3543: iload #22
    //   3545: iconst_4
    //   3546: ishl
    //   3547: ixor
    //   3548: istore #24
    //   3550: iload #24
    //   3552: bipush #16
    //   3554: iushr
    //   3555: iload #23
    //   3557: ixor
    //   3558: ldc 65535
    //   3560: iand
    //   3561: istore #22
    //   3563: iload #23
    //   3565: iload #22
    //   3567: ixor
    //   3568: istore #23
    //   3570: iload #24
    //   3572: iload #22
    //   3574: bipush #16
    //   3576: ishl
    //   3577: ixor
    //   3578: istore #24
    //   3580: iload #23
    //   3582: iconst_2
    //   3583: iushr
    //   3584: iload #24
    //   3586: ixor
    //   3587: ldc 858993459
    //   3589: iand
    //   3590: istore #22
    //   3592: iload #24
    //   3594: iload #22
    //   3596: ixor
    //   3597: istore #24
    //   3599: iload #23
    //   3601: iload #22
    //   3603: iconst_2
    //   3604: ishl
    //   3605: ixor
    //   3606: istore #23
    //   3608: iload #23
    //   3610: bipush #8
    //   3612: iushr
    //   3613: iload #24
    //   3615: ixor
    //   3616: ldc 16711935
    //   3618: iand
    //   3619: istore #22
    //   3621: iload #24
    //   3623: iload #22
    //   3625: ixor
    //   3626: istore #24
    //   3628: iload #23
    //   3630: iload #22
    //   3632: bipush #8
    //   3634: ishl
    //   3635: ixor
    //   3636: istore #23
    //   3638: iload #23
    //   3640: iconst_1
    //   3641: ishl
    //   3642: iload #23
    //   3644: bipush #31
    //   3646: iushr
    //   3647: iconst_1
    //   3648: iand
    //   3649: ior
    //   3650: istore #23
    //   3652: iload #24
    //   3654: iload #23
    //   3656: ixor
    //   3657: ldc -1431655766
    //   3659: iand
    //   3660: istore #22
    //   3662: iload #24
    //   3664: iload #22
    //   3666: ixor
    //   3667: istore #24
    //   3669: iload #23
    //   3671: iload #22
    //   3673: ixor
    //   3674: istore #23
    //   3676: iload #24
    //   3678: iconst_1
    //   3679: ishl
    //   3680: iload #24
    //   3682: bipush #31
    //   3684: iushr
    //   3685: iconst_1
    //   3686: iand
    //   3687: ior
    //   3688: istore #24
    //   3690: iconst_0
    //   3691: istore #25
    //   3693: iload #25
    //   3695: bipush #8
    //   3697: if_icmpge -> 4035
    //   3700: iload #23
    //   3702: bipush #28
    //   3704: ishl
    //   3705: iload #23
    //   3707: iconst_4
    //   3708: iushr
    //   3709: ior
    //   3710: istore #22
    //   3712: iload #22
    //   3714: aload #5
    //   3716: iload #26
    //   3718: iinc #26, 1
    //   3721: iaload
    //   3722: ixor
    //   3723: istore #22
    //   3725: aload #14
    //   3727: iload #22
    //   3729: bipush #63
    //   3731: iand
    //   3732: iaload
    //   3733: istore #21
    //   3735: iload #21
    //   3737: aload #12
    //   3739: iload #22
    //   3741: bipush #8
    //   3743: iushr
    //   3744: bipush #63
    //   3746: iand
    //   3747: iaload
    //   3748: ior
    //   3749: istore #21
    //   3751: iload #21
    //   3753: aload #10
    //   3755: iload #22
    //   3757: bipush #16
    //   3759: iushr
    //   3760: bipush #63
    //   3762: iand
    //   3763: iaload
    //   3764: ior
    //   3765: istore #21
    //   3767: iload #21
    //   3769: aload #8
    //   3771: iload #22
    //   3773: bipush #24
    //   3775: iushr
    //   3776: bipush #63
    //   3778: iand
    //   3779: iaload
    //   3780: ior
    //   3781: istore #21
    //   3783: iload #23
    //   3785: aload #5
    //   3787: iload #26
    //   3789: iinc #26, 1
    //   3792: iaload
    //   3793: ixor
    //   3794: istore #22
    //   3796: iload #21
    //   3798: aload #15
    //   3800: iload #22
    //   3802: bipush #63
    //   3804: iand
    //   3805: iaload
    //   3806: ior
    //   3807: istore #21
    //   3809: iload #21
    //   3811: aload #13
    //   3813: iload #22
    //   3815: bipush #8
    //   3817: iushr
    //   3818: bipush #63
    //   3820: iand
    //   3821: iaload
    //   3822: ior
    //   3823: istore #21
    //   3825: iload #21
    //   3827: aload #11
    //   3829: iload #22
    //   3831: bipush #16
    //   3833: iushr
    //   3834: bipush #63
    //   3836: iand
    //   3837: iaload
    //   3838: ior
    //   3839: istore #21
    //   3841: iload #21
    //   3843: aload #9
    //   3845: iload #22
    //   3847: bipush #24
    //   3849: iushr
    //   3850: bipush #63
    //   3852: iand
    //   3853: iaload
    //   3854: ior
    //   3855: istore #21
    //   3857: iload #24
    //   3859: iload #21
    //   3861: ixor
    //   3862: istore #24
    //   3864: iload #24
    //   3866: bipush #28
    //   3868: ishl
    //   3869: iload #24
    //   3871: iconst_4
    //   3872: iushr
    //   3873: ior
    //   3874: istore #22
    //   3876: iload #22
    //   3878: aload #5
    //   3880: iload #26
    //   3882: iinc #26, 1
    //   3885: iaload
    //   3886: ixor
    //   3887: istore #22
    //   3889: aload #14
    //   3891: iload #22
    //   3893: bipush #63
    //   3895: iand
    //   3896: iaload
    //   3897: istore #21
    //   3899: iload #21
    //   3901: aload #12
    //   3903: iload #22
    //   3905: bipush #8
    //   3907: iushr
    //   3908: bipush #63
    //   3910: iand
    //   3911: iaload
    //   3912: ior
    //   3913: istore #21
    //   3915: iload #21
    //   3917: aload #10
    //   3919: iload #22
    //   3921: bipush #16
    //   3923: iushr
    //   3924: bipush #63
    //   3926: iand
    //   3927: iaload
    //   3928: ior
    //   3929: istore #21
    //   3931: iload #21
    //   3933: aload #8
    //   3935: iload #22
    //   3937: bipush #24
    //   3939: iushr
    //   3940: bipush #63
    //   3942: iand
    //   3943: iaload
    //   3944: ior
    //   3945: istore #21
    //   3947: iload #24
    //   3949: aload #5
    //   3951: iload #26
    //   3953: iinc #26, 1
    //   3956: iaload
    //   3957: ixor
    //   3958: istore #22
    //   3960: iload #21
    //   3962: aload #15
    //   3964: iload #22
    //   3966: bipush #63
    //   3968: iand
    //   3969: iaload
    //   3970: ior
    //   3971: istore #21
    //   3973: iload #21
    //   3975: aload #13
    //   3977: iload #22
    //   3979: bipush #8
    //   3981: iushr
    //   3982: bipush #63
    //   3984: iand
    //   3985: iaload
    //   3986: ior
    //   3987: istore #21
    //   3989: iload #21
    //   3991: aload #11
    //   3993: iload #22
    //   3995: bipush #16
    //   3997: iushr
    //   3998: bipush #63
    //   4000: iand
    //   4001: iaload
    //   4002: ior
    //   4003: istore #21
    //   4005: iload #21
    //   4007: aload #9
    //   4009: iload #22
    //   4011: bipush #24
    //   4013: iushr
    //   4014: bipush #63
    //   4016: iand
    //   4017: iaload
    //   4018: ior
    //   4019: istore #21
    //   4021: iload #23
    //   4023: iload #21
    //   4025: ixor
    //   4026: istore #23
    //   4028: iinc #25, 1
    //   4031: iload_2
    //   4032: ifeq -> 3693
    //   4035: iload #23
    //   4037: bipush #31
    //   4039: ishl
    //   4040: iload #23
    //   4042: iconst_1
    //   4043: iushr
    //   4044: ior
    //   4045: istore #23
    //   4047: iload #24
    //   4049: iload #23
    //   4051: ixor
    //   4052: ldc -1431655766
    //   4054: iand
    //   4055: istore #22
    //   4057: iload #24
    //   4059: iload #22
    //   4061: ixor
    //   4062: istore #24
    //   4064: iload #23
    //   4066: iload #22
    //   4068: ixor
    //   4069: istore #23
    //   4071: iload #24
    //   4073: bipush #31
    //   4075: ishl
    //   4076: iload #24
    //   4078: iconst_1
    //   4079: iushr
    //   4080: ior
    //   4081: istore #24
    //   4083: iload #24
    //   4085: bipush #8
    //   4087: iushr
    //   4088: iload #23
    //   4090: ixor
    //   4091: ldc 16711935
    //   4093: iand
    //   4094: istore #22
    //   4096: iload #23
    //   4098: iload #22
    //   4100: ixor
    //   4101: istore #23
    //   4103: iload #24
    //   4105: iload #22
    //   4107: bipush #8
    //   4109: ishl
    //   4110: ixor
    //   4111: istore #24
    //   4113: iload #24
    //   4115: iconst_2
    //   4116: iushr
    //   4117: iload #23
    //   4119: ixor
    //   4120: ldc 858993459
    //   4122: iand
    //   4123: istore #22
    //   4125: iload #23
    //   4127: iload #22
    //   4129: ixor
    //   4130: istore #23
    //   4132: iload #24
    //   4134: iload #22
    //   4136: iconst_2
    //   4137: ishl
    //   4138: ixor
    //   4139: istore #24
    //   4141: iload #23
    //   4143: bipush #16
    //   4145: iushr
    //   4146: iload #24
    //   4148: ixor
    //   4149: ldc 65535
    //   4151: iand
    //   4152: istore #22
    //   4154: iload #24
    //   4156: iload #22
    //   4158: ixor
    //   4159: istore #24
    //   4161: iload #23
    //   4163: iload #22
    //   4165: bipush #16
    //   4167: ishl
    //   4168: ixor
    //   4169: istore #23
    //   4171: iload #23
    //   4173: iconst_4
    //   4174: iushr
    //   4175: iload #24
    //   4177: ixor
    //   4178: ldc 252645135
    //   4180: iand
    //   4181: istore #22
    //   4183: iload #24
    //   4185: iload #22
    //   4187: ixor
    //   4188: istore #24
    //   4190: iload #23
    //   4192: iload #22
    //   4194: iconst_4
    //   4195: ishl
    //   4196: ixor
    //   4197: istore #23
    //   4199: aload #17
    //   4201: iconst_0
    //   4202: iload #23
    //   4204: iastore
    //   4205: aload #17
    //   4207: iconst_1
    //   4208: iload #24
    //   4210: iastore
    //   4211: iload #19
    //   4213: bipush #8
    //   4215: imul
    //   4216: istore #27
    //   4218: iconst_0
    //   4219: istore #28
    //   4221: iload #28
    //   4223: iconst_2
    //   4224: if_icmpge -> 4313
    //   4227: aload #4
    //   4229: iload #27
    //   4231: iload #28
    //   4233: iconst_4
    //   4234: imul
    //   4235: iadd
    //   4236: aload #17
    //   4238: iload #28
    //   4240: iaload
    //   4241: bipush #24
    //   4243: iushr
    //   4244: i2b
    //   4245: bastore
    //   4246: aload #4
    //   4248: iload #27
    //   4250: iload #28
    //   4252: iconst_4
    //   4253: imul
    //   4254: iadd
    //   4255: iconst_1
    //   4256: iadd
    //   4257: aload #17
    //   4259: iload #28
    //   4261: iaload
    //   4262: bipush #16
    //   4264: iushr
    //   4265: i2b
    //   4266: bastore
    //   4267: aload #4
    //   4269: iload #27
    //   4271: iload #28
    //   4273: iconst_4
    //   4274: imul
    //   4275: iadd
    //   4276: iconst_2
    //   4277: iadd
    //   4278: aload #17
    //   4280: iload #28
    //   4282: iaload
    //   4283: bipush #8
    //   4285: iushr
    //   4286: i2b
    //   4287: bastore
    //   4288: aload #4
    //   4290: iload #27
    //   4292: iload #28
    //   4294: iconst_4
    //   4295: imul
    //   4296: iadd
    //   4297: iconst_3
    //   4298: iadd
    //   4299: aload #17
    //   4301: iload #28
    //   4303: iaload
    //   4304: i2b
    //   4305: bastore
    //   4306: iinc #28, 1
    //   4309: iload_2
    //   4310: ifeq -> 4221
    //   4313: iinc #19, 1
    //   4316: iload_2
    //   4317: ifeq -> 3402
    //   4320: new java/math/BigInteger
    //   4323: dup
    //   4324: aload #4
    //   4326: invokespecial <init> : ([B)V
    //   4329: invokevirtual abs : ()Ljava/math/BigInteger;
    //   4332: putstatic burp/Zlos.Zk : Ljava/lang/Object;
    //   4335: getstatic burp/Zg_p.Zx : Ljava/lang/Object;
    //   4338: checkcast java/math/BigInteger
    //   4341: getstatic burp/Zxfu.ZA : Ljava/lang/Object;
    //   4344: checkcast java/math/BigInteger
    //   4347: invokevirtual subtract : (Ljava/math/BigInteger;)Ljava/math/BigInteger;
    //   4350: putstatic burp/Zedz.Za : Ljava/lang/Object;
    //   4353: new java/lang/StringBuilder
    //   4356: dup
    //   4357: invokespecial <init> : ()V
    //   4360: astore_3
    //   4361: iconst_0
    //   4362: istore #4
    //   4364: iload #4
    //   4366: bipush #32
    //   4368: if_icmpge -> 5703
    //   4371: iload #4
    //   4373: tableswitch default -> 5696, 0 -> 4516, 1 -> 4553, 2 -> 4590, 3 -> 4627, 4 -> 4664, 5 -> 4701, 6 -> 4738, 7 -> 4775, 8 -> 4812, 9 -> 4849, 10 -> 4886, 11 -> 4923, 12 -> 4960, 13 -> 4997, 14 -> 5034, 15 -> 5071, 16 -> 5108, 17 -> 5145, 18 -> 5182, 19 -> 5219, 20 -> 5256, 21 -> 5293, 22 -> 5330, 23 -> 5367, 24 -> 5404, 25 -> 5441, 26 -> 5478, 27 -> 5515, 28 -> 5552, 29 -> 5589, 30 -> 5626, 31 -> 5663
    //   4516: aload_3
    //   4517: getstatic burp/Ze3j.ZI : Ljava/lang/String;
    //   4520: getstatic burp/Zzqj.Zq : Ljava/lang/Object;
    //   4523: checkcast java/math/BigInteger
    //   4526: invokevirtual intValue : ()I
    //   4529: bipush #32
    //   4531: irem
    //   4532: invokestatic abs : (I)I
    //   4535: invokevirtual charAt : (I)C
    //   4538: invokevirtual append : (C)Ljava/lang/StringBuilder;
    //   4541: pop
    //   4542: iload_2
    //   4543: ifeq -> 5696
    //   4546: goto -> 4553
    //   4549: invokestatic a : (Ljava/lang/Throwable;)Ljava/lang/Throwable;
    //   4552: athrow
    //   4553: aload_3
    //   4554: getstatic burp/Zz1k.ZC : Ljava/lang/String;
    //   4557: getstatic burp/Zeh9.ZY : Ljava/lang/Object;
    //   4560: checkcast java/math/BigInteger
    //   4563: invokevirtual intValue : ()I
    //   4566: bipush #32
    //   4568: irem
    //   4569: invokestatic abs : (I)I
    //   4572: invokevirtual charAt : (I)C
    //   4575: invokevirtual append : (C)Ljava/lang/StringBuilder;
    //   4578: pop
    //   4579: iload_2
    //   4580: ifeq -> 5696
    //   4583: goto -> 4590
    //   4586: invokestatic a : (Ljava/lang/Throwable;)Ljava/lang/Throwable;
    //   4589: athrow
    //   4590: aload_3
    //   4591: getstatic burp/Zrbp.Ze : Ljava/lang/String;
    //   4594: getstatic burp/Zkbm.Zp : Ljava/lang/Object;
    //   4597: checkcast java/math/BigInteger
    //   4600: invokevirtual intValue : ()I
    //   4603: bipush #32
    //   4605: irem
    //   4606: invokestatic abs : (I)I
    //   4609: invokevirtual charAt : (I)C
    //   4612: invokevirtual append : (C)Ljava/lang/StringBuilder;
    //   4615: pop
    //   4616: iload_2
    //   4617: ifeq -> 5696
    //   4620: goto -> 4627
    //   4623: invokestatic a : (Ljava/lang/Throwable;)Ljava/lang/Throwable;
    //   4626: athrow
    //   4627: aload_3
    //   4628: getstatic burp/Zsgl.ZG : Ljava/lang/String;
    //   4631: getstatic burp/Zgmt.ZX : Ljava/lang/Object;
    //   4634: checkcast java/math/BigInteger
    //   4637: invokevirtual intValue : ()I
    //   4640: bipush #32
    //   4642: irem
    //   4643: invokestatic abs : (I)I
    //   4646: invokevirtual charAt : (I)C
    //   4649: invokevirtual append : (C)Ljava/lang/StringBuilder;
    //   4652: pop
    //   4653: iload_2
    //   4654: ifeq -> 5696
    //   4657: goto -> 4664
    //   4660: invokestatic a : (Ljava/lang/Throwable;)Ljava/lang/Throwable;
    //   4663: athrow
    //   4664: aload_3
    //   4665: getstatic burp/Zl_u.Zc : Ljava/lang/String;
    //   4668: getstatic burp/Zlhm.ZT : Ljava/lang/Object;
    //   4671: checkcast java/math/BigInteger
    //   4674: invokevirtual intValue : ()I
    //   4677: bipush #32
    //   4679: irem
    //   4680: invokestatic abs : (I)I
    //   4683: invokevirtual charAt : (I)C
    //   4686: invokevirtual append : (C)Ljava/lang/StringBuilder;
    //   4689: pop
    //   4690: iload_2
    //   4691: ifeq -> 5696
    //   4694: goto -> 4701
    //   4697: invokestatic a : (Ljava/lang/Throwable;)Ljava/lang/Throwable;
    //   4700: athrow
    //   4701: aload_3
    //   4702: getstatic burp/Zein.ZN : Ljava/lang/String;
    //   4705: getstatic burp/Zb2s.Ze : Ljava/lang/Object;
    //   4708: checkcast java/math/BigInteger
    //   4711: invokevirtual intValue : ()I
    //   4714: bipush #32
    //   4716: irem
    //   4717: invokestatic abs : (I)I
    //   4720: invokevirtual charAt : (I)C
    //   4723: invokevirtual append : (C)Ljava/lang/StringBuilder;
    //   4726: pop
    //   4727: iload_2
    //   4728: ifeq -> 5696
    //   4731: goto -> 4738
    //   4734: invokestatic a : (Ljava/lang/Throwable;)Ljava/lang/Throwable;
    //   4737: athrow
    //   4738: aload_3
    //   4739: getstatic burp/Zsxm.Zq : Ljava/lang/String;
    //   4742: getstatic burp/Ze3d.Ze : Ljava/lang/Object;
    //   4745: checkcast java/math/BigInteger
    //   4748: invokevirtual intValue : ()I
    //   4751: bipush #32
    //   4753: irem
    //   4754: invokestatic abs : (I)I
    //   4757: invokevirtual charAt : (I)C
    //   4760: invokevirtual append : (C)Ljava/lang/StringBuilder;
    //   4763: pop
    //   4764: iload_2
    //   4765: ifeq -> 5696
    //   4768: goto -> 4775
    //   4771: invokestatic a : (Ljava/lang/Throwable;)Ljava/lang/Throwable;
    //   4774: athrow
    //   4775: aload_3
    //   4776: getstatic burp/Zgw0.ZL : Ljava/lang/String;
    //   4779: getstatic burp/Zkig.ZK : Ljava/lang/Object;
    //   4782: checkcast java/math/BigInteger
    //   4785: invokevirtual intValue : ()I
    //   4788: bipush #32
    //   4790: irem
    //   4791: invokestatic abs : (I)I
    //   4794: invokevirtual charAt : (I)C
    //   4797: invokevirtual append : (C)Ljava/lang/StringBuilder;
    //   4800: pop
    //   4801: iload_2
    //   4802: ifeq -> 5696
    //   4805: goto -> 4812
    //   4808: invokestatic a : (Ljava/lang/Throwable;)Ljava/lang/Throwable;
    //   4811: athrow
    //   4812: aload_3
    //   4813: getstatic burp/Zr3q.ZM : Ljava/lang/String;
    //   4816: getstatic burp/Zsby.ZZ : Ljava/lang/Object;
    //   4819: checkcast java/math/BigInteger
    //   4822: invokevirtual intValue : ()I
    //   4825: bipush #32
    //   4827: irem
    //   4828: invokestatic abs : (I)I
    //   4831: invokevirtual charAt : (I)C
    //   4834: invokevirtual append : (C)Ljava/lang/StringBuilder;
    //   4837: pop
    //   4838: iload_2
    //   4839: ifeq -> 5696
    //   4842: goto -> 4849
    //   4845: invokestatic a : (Ljava/lang/Throwable;)Ljava/lang/Throwable;
    //   4848: athrow
    //   4849: aload_3
    //   4850: getstatic burp/Zrnu.ZO : Ljava/lang/String;
    //   4853: getstatic burp/Zzqj.Zq : Ljava/lang/Object;
    //   4856: checkcast java/math/BigInteger
    //   4859: invokevirtual intValue : ()I
    //   4862: bipush #32
    //   4864: irem
    //   4865: invokestatic abs : (I)I
    //   4868: invokevirtual charAt : (I)C
    //   4871: invokevirtual append : (C)Ljava/lang/StringBuilder;
    //   4874: pop
    //   4875: iload_2
    //   4876: ifeq -> 5696
    //   4879: goto -> 4886
    //   4882: invokestatic a : (Ljava/lang/Throwable;)Ljava/lang/Throwable;
    //   4885: athrow
    //   4886: aload_3
    //   4887: getstatic burp/Zbp.Z_ : Ljava/lang/String;
    //   4890: getstatic burp/Ze13.ZD : Ljava/lang/Object;
    //   4893: checkcast java/math/BigInteger
    //   4896: invokevirtual intValue : ()I
    //   4899: bipush #32
    //   4901: irem
    //   4902: invokestatic abs : (I)I
    //   4905: invokevirtual charAt : (I)C
    //   4908: invokevirtual append : (C)Ljava/lang/StringBuilder;
    //   4911: pop
    //   4912: iload_2
    //   4913: ifeq -> 5696
    //   4916: goto -> 4923
    //   4919: invokestatic a : (Ljava/lang/Throwable;)Ljava/lang/Throwable;
    //   4922: athrow
    //   4923: aload_3
    //   4924: getstatic burp/Zrbp.Ze : Ljava/lang/String;
    //   4927: getstatic burp/Zmj4.Zm : Ljava/lang/Object;
    //   4930: checkcast java/math/BigInteger
    //   4933: invokevirtual intValue : ()I
    //   4936: bipush #32
    //   4938: irem
    //   4939: invokestatic abs : (I)I
    //   4942: invokevirtual charAt : (I)C
    //   4945: invokevirtual append : (C)Ljava/lang/StringBuilder;
    //   4948: pop
    //   4949: iload_2
    //   4950: ifeq -> 5696
    //   4953: goto -> 4960
    //   4956: invokestatic a : (Ljava/lang/Throwable;)Ljava/lang/Throwable;
    //   4959: athrow
    //   4960: aload_3
    //   4961: getstatic burp/Ztbf.Zf : Ljava/lang/String;
    //   4964: getstatic burp/Zl2q.Zg : Ljava/lang/Object;
    //   4967: checkcast java/math/BigInteger
    //   4970: invokevirtual intValue : ()I
    //   4973: bipush #32
    //   4975: irem
    //   4976: invokestatic abs : (I)I
    //   4979: invokevirtual charAt : (I)C
    //   4982: invokevirtual append : (C)Ljava/lang/StringBuilder;
    //   4985: pop
    //   4986: iload_2
    //   4987: ifeq -> 5696
    //   4990: goto -> 4997
    //   4993: invokestatic a : (Ljava/lang/Throwable;)Ljava/lang/Throwable;
    //   4996: athrow
    //   4997: aload_3
    //   4998: getstatic burp/Ze3d.ZL : Ljava/lang/String;
    //   5001: getstatic burp/Zrdy.Zt : Ljava/lang/Object;
    //   5004: checkcast java/math/BigInteger
    //   5007: invokevirtual intValue : ()I
    //   5010: bipush #32
    //   5012: irem
    //   5013: invokestatic abs : (I)I
    //   5016: invokevirtual charAt : (I)C
    //   5019: invokevirtual append : (C)Ljava/lang/StringBuilder;
    //   5022: pop
    //   5023: iload_2
    //   5024: ifeq -> 5696
    //   5027: goto -> 5034
    //   5030: invokestatic a : (Ljava/lang/Throwable;)Ljava/lang/Throwable;
    //   5033: athrow
    //   5034: aload_3
    //   5035: getstatic burp/Zd1.ZN : Ljava/lang/String;
    //   5038: getstatic burp/Zgw0.ZM : Ljava/lang/Object;
    //   5041: checkcast java/math/BigInteger
    //   5044: invokevirtual intValue : ()I
    //   5047: bipush #32
    //   5049: irem
    //   5050: invokestatic abs : (I)I
    //   5053: invokevirtual charAt : (I)C
    //   5056: invokevirtual append : (C)Ljava/lang/StringBuilder;
    //   5059: pop
    //   5060: iload_2
    //   5061: ifeq -> 5696
    //   5064: goto -> 5071
    //   5067: invokestatic a : (Ljava/lang/Throwable;)Ljava/lang/Throwable;
    //   5070: athrow
    //   5071: aload_3
    //   5072: getstatic burp/Zxk9.Zx : Ljava/lang/String;
    //   5075: getstatic burp/Zter.Zc : Ljava/lang/Object;
    //   5078: checkcast java/math/BigInteger
    //   5081: invokevirtual intValue : ()I
    //   5084: bipush #32
    //   5086: irem
    //   5087: invokestatic abs : (I)I
    //   5090: invokevirtual charAt : (I)C
    //   5093: invokevirtual append : (C)Ljava/lang/StringBuilder;
    //   5096: pop
    //   5097: iload_2
    //   5098: ifeq -> 5696
    //   5101: goto -> 5108
    //   5104: invokestatic a : (Ljava/lang/Throwable;)Ljava/lang/Throwable;
    //   5107: athrow
    //   5108: aload_3
    //   5109: getstatic burp/Zt4g.Zj : Ljava/lang/String;
    //   5112: getstatic burp/Zxzd.ZD : Ljava/lang/Object;
    //   5115: checkcast java/math/BigInteger
    //   5118: invokevirtual intValue : ()I
    //   5121: bipush #32
    //   5123: irem
    //   5124: invokestatic abs : (I)I
    //   5127: invokevirtual charAt : (I)C
    //   5130: invokevirtual append : (C)Ljava/lang/StringBuilder;
    //   5133: pop
    //   5134: iload_2
    //   5135: ifeq -> 5696
    //   5138: goto -> 5145
    //   5141: invokestatic a : (Ljava/lang/Throwable;)Ljava/lang/Throwable;
    //   5144: athrow
    //   5145: aload_3
    //   5146: getstatic burp/Zxfu.Zo : Ljava/lang/String;
    //   5149: getstatic burp/Zehi.Zb : Ljava/lang/Object;
    //   5152: checkcast java/math/BigInteger
    //   5155: invokevirtual intValue : ()I
    //   5158: bipush #32
    //   5160: irem
    //   5161: invokestatic abs : (I)I
    //   5164: invokevirtual charAt : (I)C
    //   5167: invokevirtual append : (C)Ljava/lang/StringBuilder;
    //   5170: pop
    //   5171: iload_2
    //   5172: ifeq -> 5696
    //   5175: goto -> 5182
    //   5178: invokestatic a : (Ljava/lang/Throwable;)Ljava/lang/Throwable;
    //   5181: athrow
    //   5182: aload_3
    //   5183: getstatic burp/Zgw0.ZL : Ljava/lang/String;
    //   5186: getstatic burp/Zein.Zb : Ljava/lang/Object;
    //   5189: checkcast java/math/BigInteger
    //   5192: invokevirtual intValue : ()I
    //   5195: bipush #32
    //   5197: irem
    //   5198: invokestatic abs : (I)I
    //   5201: invokevirtual charAt : (I)C
    //   5204: invokevirtual append : (C)Ljava/lang/StringBuilder;
    //   5207: pop
    //   5208: iload_2
    //   5209: ifeq -> 5696
    //   5212: goto -> 5219
    //   5215: invokestatic a : (Ljava/lang/Throwable;)Ljava/lang/Throwable;
    //   5218: athrow
    //   5219: aload_3
    //   5220: getstatic burp/Zr8h.Zk : Ljava/lang/String;
    //   5223: getstatic burp/Zedz.Za : Ljava/lang/Object;
    //   5226: checkcast java/math/BigInteger
    //   5229: invokevirtual intValue : ()I
    //   5232: bipush #32
    //   5234: irem
    //   5235: invokestatic abs : (I)I
    //   5238: invokevirtual charAt : (I)C
    //   5241: invokevirtual append : (C)Ljava/lang/StringBuilder;
    //   5244: pop
    //   5245: iload_2
    //   5246: ifeq -> 5696
    //   5249: goto -> 5256
    //   5252: invokestatic a : (Ljava/lang/Throwable;)Ljava/lang/Throwable;
    //   5255: athrow
    //   5256: aload_3
    //   5257: getstatic burp/Zxzd.ZM : Ljava/lang/String;
    //   5260: getstatic burp/Zx4w.Zp : Ljava/lang/Object;
    //   5263: checkcast java/math/BigInteger
    //   5266: invokevirtual intValue : ()I
    //   5269: bipush #32
    //   5271: irem
    //   5272: invokestatic abs : (I)I
    //   5275: invokevirtual charAt : (I)C
    //   5278: invokevirtual append : (C)Ljava/lang/StringBuilder;
    //   5281: pop
    //   5282: iload_2
    //   5283: ifeq -> 5696
    //   5286: goto -> 5293
    //   5289: invokestatic a : (Ljava/lang/Throwable;)Ljava/lang/Throwable;
    //   5292: athrow
    //   5293: aload_3
    //   5294: getstatic burp/Zzip.Za : Ljava/lang/String;
    //   5297: getstatic burp/Zzsq.Zh : Ljava/lang/Object;
    //   5300: checkcast java/math/BigInteger
    //   5303: invokevirtual intValue : ()I
    //   5306: bipush #32
    //   5308: irem
    //   5309: invokestatic abs : (I)I
    //   5312: invokevirtual charAt : (I)C
    //   5315: invokevirtual append : (C)Ljava/lang/StringBuilder;
    //   5318: pop
    //   5319: iload_2
    //   5320: ifeq -> 5696
    //   5323: goto -> 5330
    //   5326: invokestatic a : (Ljava/lang/Throwable;)Ljava/lang/Throwable;
    //   5329: athrow
    //   5330: aload_3
    //   5331: getstatic burp/Zsde.Zi : Ljava/lang/String;
    //   5334: getstatic burp/Zrbp.Z_ : Ljava/lang/Object;
    //   5337: checkcast java/math/BigInteger
    //   5340: invokevirtual intValue : ()I
    //   5343: bipush #32
    //   5345: irem
    //   5346: invokestatic abs : (I)I
    //   5349: invokevirtual charAt : (I)C
    //   5352: invokevirtual append : (C)Ljava/lang/StringBuilder;
    //   5355: pop
    //   5356: iload_2
    //   5357: ifeq -> 5696
    //   5360: goto -> 5367
    //   5363: invokestatic a : (Ljava/lang/Throwable;)Ljava/lang/Throwable;
    //   5366: athrow
    //   5367: aload_3
    //   5368: getstatic burp/Zk9s.ZM : Ljava/lang/String;
    //   5371: getstatic burp/Zb3z.ZR : Ljava/lang/Object;
    //   5374: checkcast java/math/BigInteger
    //   5377: invokevirtual intValue : ()I
    //   5380: bipush #32
    //   5382: irem
    //   5383: invokestatic abs : (I)I
    //   5386: invokevirtual charAt : (I)C
    //   5389: invokevirtual append : (C)Ljava/lang/StringBuilder;
    //   5392: pop
    //   5393: iload_2
    //   5394: ifeq -> 5696
    //   5397: goto -> 5404
    //   5400: invokestatic a : (Ljava/lang/Throwable;)Ljava/lang/Throwable;
    //   5403: athrow
    //   5404: aload_3
    //   5405: getstatic burp/Ztuj.Zk : Ljava/lang/String;
    //   5408: getstatic burp/Zg7z.ZV : Ljava/lang/Object;
    //   5411: checkcast java/math/BigInteger
    //   5414: invokevirtual intValue : ()I
    //   5417: bipush #32
    //   5419: irem
    //   5420: invokestatic abs : (I)I
    //   5423: invokevirtual charAt : (I)C
    //   5426: invokevirtual append : (C)Ljava/lang/StringBuilder;
    //   5429: pop
    //   5430: iload_2
    //   5431: ifeq -> 5696
    //   5434: goto -> 5441
    //   5437: invokestatic a : (Ljava/lang/Throwable;)Ljava/lang/Throwable;
    //   5440: athrow
    //   5441: aload_3
    //   5442: getstatic burp/Zter.ZE : Ljava/lang/String;
    //   5445: getstatic burp/Zsde.Zx : Ljava/lang/Object;
    //   5448: checkcast java/math/BigInteger
    //   5451: invokevirtual intValue : ()I
    //   5454: bipush #32
    //   5456: irem
    //   5457: invokestatic abs : (I)I
    //   5460: invokevirtual charAt : (I)C
    //   5463: invokevirtual append : (C)Ljava/lang/StringBuilder;
    //   5466: pop
    //   5467: iload_2
    //   5468: ifeq -> 5696
    //   5471: goto -> 5478
    //   5474: invokestatic a : (Ljava/lang/Throwable;)Ljava/lang/Throwable;
    //   5477: athrow
    //   5478: aload_3
    //   5479: getstatic burp/Zllw.Zg : Ljava/lang/String;
    //   5482: getstatic burp/Zmj4.Zm : Ljava/lang/Object;
    //   5485: checkcast java/math/BigInteger
    //   5488: invokevirtual intValue : ()I
    //   5491: bipush #32
    //   5493: irem
    //   5494: invokestatic abs : (I)I
    //   5497: invokevirtual charAt : (I)C
    //   5500: invokevirtual append : (C)Ljava/lang/StringBuilder;
    //   5503: pop
    //   5504: iload_2
    //   5505: ifeq -> 5696
    //   5508: goto -> 5515
    //   5511: invokestatic a : (Ljava/lang/Throwable;)Ljava/lang/Throwable;
    //   5514: athrow
    //   5515: aload_3
    //   5516: getstatic burp/Zb3z.Zi : Ljava/lang/String;
    //   5519: getstatic burp/Zxso.ZF : Ljava/lang/Object;
    //   5522: checkcast java/math/BigInteger
    //   5525: invokevirtual intValue : ()I
    //   5528: bipush #32
    //   5530: irem
    //   5531: invokestatic abs : (I)I
    //   5534: invokevirtual charAt : (I)C
    //   5537: invokevirtual append : (C)Ljava/lang/StringBuilder;
    //   5540: pop
    //   5541: iload_2
    //   5542: ifeq -> 5696
    //   5545: goto -> 5552
    //   5548: invokestatic a : (Ljava/lang/Throwable;)Ljava/lang/Throwable;
    //   5551: athrow
    //   5552: aload_3
    //   5553: getstatic burp/Zod.ZS : Ljava/lang/String;
    //   5556: getstatic burp/Zxso.ZF : Ljava/lang/Object;
    //   5559: checkcast java/math/BigInteger
    //   5562: invokevirtual intValue : ()I
    //   5565: bipush #32
    //   5567: irem
    //   5568: invokestatic abs : (I)I
    //   5571: invokevirtual charAt : (I)C
    //   5574: invokevirtual append : (C)Ljava/lang/StringBuilder;
    //   5577: pop
    //   5578: iload_2
    //   5579: ifeq -> 5696
    //   5582: goto -> 5589
    //   5585: invokestatic a : (Ljava/lang/Throwable;)Ljava/lang/Throwable;
    //   5588: athrow
    //   5589: aload_3
    //   5590: getstatic burp/Zr0g.Zf : Ljava/lang/String;
    //   5593: getstatic burp/Ztbf.Zv : Ljava/lang/Object;
    //   5596: checkcast java/math/BigInteger
    //   5599: invokevirtual intValue : ()I
    //   5602: bipush #32
    //   5604: irem
    //   5605: invokestatic abs : (I)I
    //   5608: invokevirtual charAt : (I)C
    //   5611: invokevirtual append : (C)Ljava/lang/StringBuilder;
    //   5614: pop
    //   5615: iload_2
    //   5616: ifeq -> 5696
    //   5619: goto -> 5626
    //   5622: invokestatic a : (Ljava/lang/Throwable;)Ljava/lang/Throwable;
    //   5625: athrow
    //   5626: aload_3
    //   5627: getstatic burp/Zrnu.ZO : Ljava/lang/String;
    //   5630: getstatic burp/Zk9s.ZY : Ljava/lang/Object;
    //   5633: checkcast java/math/BigInteger
    //   5636: invokevirtual intValue : ()I
    //   5639: bipush #32
    //   5641: irem
    //   5642: invokestatic abs : (I)I
    //   5645: invokevirtual charAt : (I)C
    //   5648: invokevirtual append : (C)Ljava/lang/StringBuilder;
    //   5651: pop
    //   5652: iload_2
    //   5653: ifeq -> 5696
    //   5656: goto -> 5663
    //   5659: invokestatic a : (Ljava/lang/Throwable;)Ljava/lang/Throwable;
    //   5662: athrow
    //   5663: aload_3
    //   5664: getstatic burp/Zl_k.Zw : Ljava/lang/String;
    //   5667: getstatic burp/Zl_k.ZH : Ljava/lang/Object;
    //   5670: checkcast java/math/BigInteger
    //   5673: invokevirtual intValue : ()I
    //   5676: bipush #32
    //   5678: irem
    //   5679: invokestatic abs : (I)I
    //   5682: invokevirtual charAt : (I)C
    //   5685: invokevirtual append : (C)Ljava/lang/StringBuilder;
    //   5688: pop
    //   5689: goto -> 5696
    //   5692: invokestatic a : (Ljava/lang/Throwable;)Ljava/lang/Throwable;
    //   5695: athrow
    //   5696: iinc #4, 1
    //   5699: iload_2
    //   5700: ifeq -> 4364
    //   5703: aload_3
    //   5704: invokevirtual toString : ()Ljava/lang/String;
    //   5707: putstatic burp/Zg99.ZH : Ljava/lang/String;
    //   5710: sipush #11794
    //   5713: sipush #31873
    //   5716: invokestatic a : (II)Ljava/lang/String;
    //   5719: iconst_1
    //   5720: ldc burp/Zm5p
    //   5722: invokevirtual getClassLoader : ()Ljava/lang/ClassLoader;
    //   5725: invokestatic forName : (Ljava/lang/String;ZLjava/lang/ClassLoader;)Ljava/lang/Class;
    //   5728: invokevirtual getDeclaredFields : ()[Ljava/lang/reflect/Field;
    //   5731: astore #4
    //   5733: aload #4
    //   5735: arraylength
    //   5736: istore #5
    //   5738: iconst_0
    //   5739: istore #6
    //   5741: iload #6
    //   5743: iload #5
    //   5745: if_icmpge -> 5883
    //   5748: aload #4
    //   5750: iload #6
    //   5752: aaload
    //   5753: astore #7
    //   5755: aload #7
    //   5757: invokevirtual getModifiers : ()I
    //   5760: invokestatic isStatic : (I)Z
    //   5763: ifne -> 5773
    //   5766: goto -> 5876
    //   5769: invokestatic a : (Ljava/lang/Throwable;)Ljava/lang/Throwable;
    //   5772: athrow
    //   5773: aload #7
    //   5775: invokevirtual getType : ()Ljava/lang/Class;
    //   5778: astore #8
    //   5780: aload #8
    //   5782: ifnull -> 5863
    //   5785: aload #8
    //   5787: invokevirtual isPrimitive : ()Z
    //   5790: ifne -> 5863
    //   5793: goto -> 5800
    //   5796: invokestatic a : (Ljava/lang/Throwable;)Ljava/lang/Throwable;
    //   5799: athrow
    //   5800: aload #8
    //   5802: invokevirtual getPackage : ()Ljava/lang/Package;
    //   5805: ifnull -> 5863
    //   5808: goto -> 5815
    //   5811: invokestatic a : (Ljava/lang/Throwable;)Ljava/lang/Throwable;
    //   5814: athrow
    //   5815: aload #8
    //   5817: invokevirtual getPackage : ()Ljava/lang/Package;
    //   5820: invokevirtual getName : ()Ljava/lang/String;
    //   5823: ifnull -> 5863
    //   5826: goto -> 5833
    //   5829: invokestatic a : (Ljava/lang/Throwable;)Ljava/lang/Throwable;
    //   5832: athrow
    //   5833: aload #8
    //   5835: invokevirtual getPackage : ()Ljava/lang/Package;
    //   5838: invokevirtual getName : ()Ljava/lang/String;
    //   5841: sipush #11792
    //   5844: sipush #17491
    //   5847: invokestatic a : (II)Ljava/lang/String;
    //   5850: invokevirtual startsWith : (Ljava/lang/String;)Z
    //   5853: ifne -> 5863
    //   5856: goto -> 5863
    //   5859: invokestatic a : (Ljava/lang/Throwable;)Ljava/lang/Throwable;
    //   5862: athrow
    //   5863: aload #7
    //   5865: iconst_1
    //   5866: invokevirtual setAccessible : (Z)V
    //   5869: aload #7
    //   5871: aconst_null
    //   5872: invokevirtual get : (Ljava/lang/Object;)Ljava/lang/Object;
    //   5875: pop
    //   5876: iinc #6, 1
    //   5879: iload_2
    //   5880: ifeq -> 5741
    //   5883: sipush #11784
    //   5886: sipush #-6436
    //   5889: invokestatic a : (II)Ljava/lang/String;
    //   5892: invokestatic forName : (Ljava/lang/String;)Ljava/lang/Class;
    //   5895: invokevirtual getDeclaredMethods : ()[Ljava/lang/reflect/Method;
    //   5898: astore #4
    //   5900: aload #4
    //   5902: arraylength
    //   5903: istore #5
    //   5905: iconst_0
    //   5906: istore #6
    //   5908: iload #6
    //   5910: iload #5
    //   5912: if_icmpge -> 6045
    //   5915: aload #4
    //   5917: iload #6
    //   5919: aaload
    //   5920: astore #7
    //   5922: aload #7
    //   5924: invokevirtual getParameterTypes : ()[Ljava/lang/Class;
    //   5927: pop
    //   5928: aload #7
    //   5930: invokevirtual getModifiers : ()I
    //   5933: invokestatic isStatic : (I)Z
    //   5936: ifeq -> 6031
    //   5939: aload #7
    //   5941: invokevirtual getParameterTypes : ()[Ljava/lang/Class;
    //   5944: arraylength
    //   5945: iconst_2
    //   5946: if_icmpne -> 6031
    //   5949: goto -> 5956
    //   5952: invokestatic a : (Ljava/lang/Throwable;)Ljava/lang/Throwable;
    //   5955: athrow
    //   5956: aload #7
    //   5958: invokevirtual getReturnType : ()Ljava/lang/Class;
    //   5961: getstatic java/lang/Void.TYPE : Ljava/lang/Class;
    //   5964: invokevirtual equals : (Ljava/lang/Object;)Z
    //   5967: ifeq -> 6031
    //   5970: goto -> 5977
    //   5973: invokestatic a : (Ljava/lang/Throwable;)Ljava/lang/Throwable;
    //   5976: athrow
    //   5977: aload #7
    //   5979: iconst_1
    //   5980: invokevirtual setAccessible : (Z)V
    //   5983: aload #7
    //   5985: aconst_null
    //   5986: iconst_2
    //   5987: anewarray java/lang/Object
    //   5990: dup
    //   5991: iconst_0
    //   5992: aload_0
    //   5993: aastore
    //   5994: dup
    //   5995: iconst_1
    //   5996: aload_1
    //   5997: ifnonnull -> 6015
    //   6000: goto -> 6007
    //   6003: invokestatic a : (Ljava/lang/Throwable;)Ljava/lang/Throwable;
    //   6006: athrow
    //   6007: aload_1
    //   6008: goto -> 6022
    //   6011: invokestatic a : (Ljava/lang/Throwable;)Ljava/lang/Throwable;
    //   6014: athrow
    //   6015: aload_1
    //   6016: checkcast [B
    //   6019: invokevirtual clone : ()Ljava/lang/Object;
    //   6022: aastore
    //   6023: invokevirtual invoke : (Ljava/lang/Object;[Ljava/lang/Object;)Ljava/lang/Object;
    //   6026: pop
    //   6027: iload_2
    //   6028: ifeq -> 6045
    //   6031: iinc #6, 1
    //   6034: iload_2
    //   6035: ifeq -> 5908
    //   6038: goto -> 6045
    //   6041: invokestatic a : (Ljava/lang/Throwable;)Ljava/lang/Throwable;
    //   6044: athrow
    //   6045: getstatic burp/Ztuj.Ze : Ljava/lang/Object;
    //   6048: checkcast java/math/BigInteger
    //   6051: invokevirtual intValue : ()I
    //   6054: i2l
    //   6055: invokestatic currentTimeMillis : ()J
    //   6058: ladd
    //   6059: getstatic burp/Zgw0.ZM : Ljava/lang/Object;
    //   6062: checkcast java/math/BigInteger
    //   6065: invokevirtual intValue : ()I
    //   6068: i2l
    //   6069: lcmp
    //   6070: ifge -> 6408
    //   6073: sipush #11777
    //   6076: sipush #-514
    //   6079: invokestatic a : (II)Ljava/lang/String;
    //   6082: iconst_1
    //   6083: ldc burp/Zxz_
    //   6085: invokevirtual getClassLoader : ()Ljava/lang/ClassLoader;
    //   6088: invokestatic forName : (Ljava/lang/String;ZLjava/lang/ClassLoader;)Ljava/lang/Class;
    //   6091: invokevirtual getDeclaredFields : ()[Ljava/lang/reflect/Field;
    //   6094: astore #4
    //   6096: aload #4
    //   6098: arraylength
    //   6099: istore #5
    //   6101: iconst_0
    //   6102: istore #6
    //   6104: iload #6
    //   6106: iload #5
    //   6108: if_icmpge -> 6246
    //   6111: aload #4
    //   6113: iload #6
    //   6115: aaload
    //   6116: astore #7
    //   6118: aload #7
    //   6120: invokevirtual getModifiers : ()I
    //   6123: invokestatic isStatic : (I)Z
    //   6126: ifne -> 6136
    //   6129: goto -> 6239
    //   6132: invokestatic a : (Ljava/lang/Throwable;)Ljava/lang/Throwable;
    //   6135: athrow
    //   6136: aload #7
    //   6138: invokevirtual getType : ()Ljava/lang/Class;
    //   6141: astore #8
    //   6143: aload #8
    //   6145: ifnull -> 6226
    //   6148: aload #8
    //   6150: invokevirtual isPrimitive : ()Z
    //   6153: ifne -> 6226
    //   6156: goto -> 6163
    //   6159: invokestatic a : (Ljava/lang/Throwable;)Ljava/lang/Throwable;
    //   6162: athrow
    //   6163: aload #8
    //   6165: invokevirtual getPackage : ()Ljava/lang/Package;
    //   6168: ifnull -> 6226
    //   6171: goto -> 6178
    //   6174: invokestatic a : (Ljava/lang/Throwable;)Ljava/lang/Throwable;
    //   6177: athrow
    //   6178: aload #8
    //   6180: invokevirtual getPackage : ()Ljava/lang/Package;
    //   6183: invokevirtual getName : ()Ljava/lang/String;
    //   6186: ifnull -> 6226
    //   6189: goto -> 6196
    //   6192: invokestatic a : (Ljava/lang/Throwable;)Ljava/lang/Throwable;
    //   6195: athrow
    //   6196: aload #8
    //   6198: invokevirtual getPackage : ()Ljava/lang/Package;
    //   6201: invokevirtual getName : ()Ljava/lang/String;
    //   6204: sipush #11798
    //   6207: sipush #-19117
    //   6210: invokestatic a : (II)Ljava/lang/String;
    //   6213: invokevirtual startsWith : (Ljava/lang/String;)Z
    //   6216: ifne -> 6226
    //   6219: goto -> 6226
    //   6222: invokestatic a : (Ljava/lang/Throwable;)Ljava/lang/Throwable;
    //   6225: athrow
    //   6226: aload #7
    //   6228: iconst_1
    //   6229: invokevirtual setAccessible : (Z)V
    //   6232: aload #7
    //   6234: aconst_null
    //   6235: invokevirtual get : (Ljava/lang/Object;)Ljava/lang/Object;
    //   6238: pop
    //   6239: iinc #6, 1
    //   6242: iload_2
    //   6243: ifeq -> 6104
    //   6246: sipush #11787
    //   6249: sipush #-8309
    //   6252: invokestatic a : (II)Ljava/lang/String;
    //   6255: invokestatic forName : (Ljava/lang/String;)Ljava/lang/Class;
    //   6258: invokevirtual getDeclaredMethods : ()[Ljava/lang/reflect/Method;
    //   6261: astore #4
    //   6263: aload #4
    //   6265: arraylength
    //   6266: istore #5
    //   6268: iconst_0
    //   6269: istore #6
    //   6271: iload #6
    //   6273: iload #5
    //   6275: if_icmpge -> 6408
    //   6278: aload #4
    //   6280: iload #6
    //   6282: aaload
    //   6283: astore #7
    //   6285: aload #7
    //   6287: invokevirtual getParameterTypes : ()[Ljava/lang/Class;
    //   6290: pop
    //   6291: aload #7
    //   6293: invokevirtual getModifiers : ()I
    //   6296: invokestatic isStatic : (I)Z
    //   6299: ifeq -> 6394
    //   6302: aload #7
    //   6304: invokevirtual getParameterTypes : ()[Ljava/lang/Class;
    //   6307: arraylength
    //   6308: iconst_2
    //   6309: if_icmpne -> 6394
    //   6312: goto -> 6319
    //   6315: invokestatic a : (Ljava/lang/Throwable;)Ljava/lang/Throwable;
    //   6318: athrow
    //   6319: aload #7
    //   6321: invokevirtual getReturnType : ()Ljava/lang/Class;
    //   6324: getstatic java/lang/Void.TYPE : Ljava/lang/Class;
    //   6327: invokevirtual equals : (Ljava/lang/Object;)Z
    //   6330: ifeq -> 6394
    //   6333: goto -> 6340
    //   6336: invokestatic a : (Ljava/lang/Throwable;)Ljava/lang/Throwable;
    //   6339: athrow
    //   6340: aload #7
    //   6342: iconst_1
    //   6343: invokevirtual setAccessible : (Z)V
    //   6346: aload #7
    //   6348: aconst_null
    //   6349: iconst_2
    //   6350: anewarray java/lang/Object
    //   6353: dup
    //   6354: iconst_0
    //   6355: aload_0
    //   6356: aastore
    //   6357: dup
    //   6358: iconst_1
    //   6359: aload_1
    //   6360: ifnonnull -> 6378
    //   6363: goto -> 6370
    //   6366: invokestatic a : (Ljava/lang/Throwable;)Ljava/lang/Throwable;
    //   6369: athrow
    //   6370: aload_1
    //   6371: goto -> 6385
    //   6374: invokestatic a : (Ljava/lang/Throwable;)Ljava/lang/Throwable;
    //   6377: athrow
    //   6378: aload_1
    //   6379: checkcast [B
    //   6382: invokevirtual clone : ()Ljava/lang/Object;
    //   6385: aastore
    //   6386: invokevirtual invoke : (Ljava/lang/Object;[Ljava/lang/Object;)Ljava/lang/Object;
    //   6389: pop
    //   6390: iload_2
    //   6391: ifeq -> 6408
    //   6394: iinc #6, 1
    //   6397: iload_2
    //   6398: ifeq -> 6271
    //   6401: goto -> 6408
    //   6404: invokestatic a : (Ljava/lang/Throwable;)Ljava/lang/Throwable;
    //   6407: athrow
    //   6408: iconst_0
    //   6409: istore #4
    //   6411: getstatic burp/Zm0s.Zm : Ljava/lang/String;
    //   6414: getstatic burp/Zehi.Zb : Ljava/lang/Object;
    //   6417: checkcast java/math/BigInteger
    //   6420: invokevirtual intValue : ()I
    //   6423: bipush #32
    //   6425: irem
    //   6426: invokestatic abs : (I)I
    //   6429: invokevirtual charAt : (I)C
    //   6432: getstatic burp/Ze3d.ZL : Ljava/lang/String;
    //   6435: getstatic burp/Zein.Zb : Ljava/lang/Object;
    //   6438: checkcast java/math/BigInteger
    //   6441: invokevirtual intValue : ()I
    //   6444: bipush #32
    //   6446: irem
    //   6447: invokestatic abs : (I)I
    //   6450: invokevirtual charAt : (I)C
    //   6453: if_icmple -> 6798
    //   6456: sipush #11779
    //   6459: sipush #28375
    //   6462: invokestatic a : (II)Ljava/lang/String;
    //   6465: iconst_1
    //   6466: ldc burp/Zkv2
    //   6468: invokevirtual getClassLoader : ()Ljava/lang/ClassLoader;
    //   6471: invokestatic forName : (Ljava/lang/String;ZLjava/lang/ClassLoader;)Ljava/lang/Class;
    //   6474: invokevirtual getDeclaredFields : ()[Ljava/lang/reflect/Field;
    //   6477: astore #5
    //   6479: aload #5
    //   6481: arraylength
    //   6482: istore #6
    //   6484: iconst_0
    //   6485: istore #7
    //   6487: iload #7
    //   6489: iload #6
    //   6491: if_icmpge -> 6629
    //   6494: aload #5
    //   6496: iload #7
    //   6498: aaload
    //   6499: astore #8
    //   6501: aload #8
    //   6503: invokevirtual getModifiers : ()I
    //   6506: invokestatic isStatic : (I)Z
    //   6509: ifne -> 6519
    //   6512: goto -> 6622
    //   6515: invokestatic a : (Ljava/lang/Throwable;)Ljava/lang/Throwable;
    //   6518: athrow
    //   6519: aload #8
    //   6521: invokevirtual getType : ()Ljava/lang/Class;
    //   6524: astore #9
    //   6526: aload #9
    //   6528: ifnull -> 6609
    //   6531: aload #9
    //   6533: invokevirtual isPrimitive : ()Z
    //   6536: ifne -> 6609
    //   6539: goto -> 6546
    //   6542: invokestatic a : (Ljava/lang/Throwable;)Ljava/lang/Throwable;
    //   6545: athrow
    //   6546: aload #9
    //   6548: invokevirtual getPackage : ()Ljava/lang/Package;
    //   6551: ifnull -> 6609
    //   6554: goto -> 6561
    //   6557: invokestatic a : (Ljava/lang/Throwable;)Ljava/lang/Throwable;
    //   6560: athrow
    //   6561: aload #9
    //   6563: invokevirtual getPackage : ()Ljava/lang/Package;
    //   6566: invokevirtual getName : ()Ljava/lang/String;
    //   6569: ifnull -> 6609
    //   6572: goto -> 6579
    //   6575: invokestatic a : (Ljava/lang/Throwable;)Ljava/lang/Throwable;
    //   6578: athrow
    //   6579: aload #9
    //   6581: invokevirtual getPackage : ()Ljava/lang/Package;
    //   6584: invokevirtual getName : ()Ljava/lang/String;
    //   6587: sipush #11798
    //   6590: sipush #-19117
    //   6593: invokestatic a : (II)Ljava/lang/String;
    //   6596: invokevirtual startsWith : (Ljava/lang/String;)Z
    //   6599: ifne -> 6609
    //   6602: goto -> 6609
    //   6605: invokestatic a : (Ljava/lang/Throwable;)Ljava/lang/Throwable;
    //   6608: athrow
    //   6609: aload #8
    //   6611: iconst_1
    //   6612: invokevirtual setAccessible : (Z)V
    //   6615: aload #8
    //   6617: aconst_null
    //   6618: invokevirtual get : (Ljava/lang/Object;)Ljava/lang/Object;
    //   6621: pop
    //   6622: iinc #7, 1
    //   6625: iload_2
    //   6626: ifeq -> 6487
    //   6629: sipush #11806
    //   6632: sipush #-29311
    //   6635: invokestatic a : (II)Ljava/lang/String;
    //   6638: invokestatic forName : (Ljava/lang/String;)Ljava/lang/Class;
    //   6641: invokevirtual getDeclaredMethods : ()[Ljava/lang/reflect/Method;
    //   6644: astore #5
    //   6646: aload #5
    //   6648: arraylength
    //   6649: istore #6
    //   6651: iconst_0
    //   6652: istore #7
    //   6654: iload #7
    //   6656: iload #6
    //   6658: if_icmpge -> 6795
    //   6661: aload #5
    //   6663: iload #7
    //   6665: aaload
    //   6666: astore #8
    //   6668: aload #8
    //   6670: invokevirtual getParameterTypes : ()[Ljava/lang/Class;
    //   6673: pop
    //   6674: aload #8
    //   6676: invokevirtual getModifiers : ()I
    //   6679: invokestatic isStatic : (I)Z
    //   6682: ifeq -> 6781
    //   6685: aload #8
    //   6687: invokevirtual getParameterTypes : ()[Ljava/lang/Class;
    //   6690: arraylength
    //   6691: iconst_2
    //   6692: if_icmpne -> 6781
    //   6695: goto -> 6702
    //   6698: invokestatic a : (Ljava/lang/Throwable;)Ljava/lang/Throwable;
    //   6701: athrow
    //   6702: aload #8
    //   6704: invokevirtual getReturnType : ()Ljava/lang/Class;
    //   6707: getstatic java/lang/Boolean.TYPE : Ljava/lang/Class;
    //   6710: if_acmpne -> 6781
    //   6713: goto -> 6720
    //   6716: invokestatic a : (Ljava/lang/Throwable;)Ljava/lang/Throwable;
    //   6719: athrow
    //   6720: aload #8
    //   6722: iconst_1
    //   6723: invokevirtual setAccessible : (Z)V
    //   6726: aload #8
    //   6728: aconst_null
    //   6729: iconst_2
    //   6730: anewarray java/lang/Object
    //   6733: dup
    //   6734: iconst_0
    //   6735: aload_0
    //   6736: aastore
    //   6737: dup
    //   6738: iconst_1
    //   6739: aload_1
    //   6740: ifnonnull -> 6758
    //   6743: goto -> 6750
    //   6746: invokestatic a : (Ljava/lang/Throwable;)Ljava/lang/Throwable;
    //   6749: athrow
    //   6750: aload_1
    //   6751: goto -> 6765
    //   6754: invokestatic a : (Ljava/lang/Throwable;)Ljava/lang/Throwable;
    //   6757: athrow
    //   6758: aload_1
    //   6759: checkcast [B
    //   6762: invokevirtual clone : ()Ljava/lang/Object;
    //   6765: aastore
    //   6766: invokevirtual invoke : (Ljava/lang/Object;[Ljava/lang/Object;)Ljava/lang/Object;
    //   6769: checkcast java/lang/Boolean
    //   6772: invokevirtual booleanValue : ()Z
    //   6775: istore #4
    //   6777: iload_2
    //   6778: ifeq -> 6795
    //   6781: iinc #7, 1
    //   6784: iload_2
    //   6785: ifeq -> 6654
    //   6788: goto -> 6795
    //   6791: invokestatic a : (Ljava/lang/Throwable;)Ljava/lang/Throwable;
    //   6794: athrow
    //   6795: goto -> 7137
    //   6798: sipush #11801
    //   6801: sipush #4945
    //   6804: invokestatic a : (II)Ljava/lang/String;
    //   6807: iconst_1
    //   6808: ldc burp/Zebj
    //   6810: invokevirtual getClassLoader : ()Ljava/lang/ClassLoader;
    //   6813: invokestatic forName : (Ljava/lang/String;ZLjava/lang/ClassLoader;)Ljava/lang/Class;
    //   6816: invokevirtual getDeclaredFields : ()[Ljava/lang/reflect/Field;
    //   6819: astore #5
    //   6821: aload #5
    //   6823: arraylength
    //   6824: istore #6
    //   6826: iconst_0
    //   6827: istore #7
    //   6829: iload #7
    //   6831: iload #6
    //   6833: if_icmpge -> 6971
    //   6836: aload #5
    //   6838: iload #7
    //   6840: aaload
    //   6841: astore #8
    //   6843: aload #8
    //   6845: invokevirtual getModifiers : ()I
    //   6848: invokestatic isStatic : (I)Z
    //   6851: ifne -> 6861
    //   6854: goto -> 6964
    //   6857: invokestatic a : (Ljava/lang/Throwable;)Ljava/lang/Throwable;
    //   6860: athrow
    //   6861: aload #8
    //   6863: invokevirtual getType : ()Ljava/lang/Class;
    //   6866: astore #9
    //   6868: aload #9
    //   6870: ifnull -> 6951
    //   6873: aload #9
    //   6875: invokevirtual isPrimitive : ()Z
    //   6878: ifne -> 6951
    //   6881: goto -> 6888
    //   6884: invokestatic a : (Ljava/lang/Throwable;)Ljava/lang/Throwable;
    //   6887: athrow
    //   6888: aload #9
    //   6890: invokevirtual getPackage : ()Ljava/lang/Package;
    //   6893: ifnull -> 6951
    //   6896: goto -> 6903
    //   6899: invokestatic a : (Ljava/lang/Throwable;)Ljava/lang/Throwable;
    //   6902: athrow
    //   6903: aload #9
    //   6905: invokevirtual getPackage : ()Ljava/lang/Package;
    //   6908: invokevirtual getName : ()Ljava/lang/String;
    //   6911: ifnull -> 6951
    //   6914: goto -> 6921
    //   6917: invokestatic a : (Ljava/lang/Throwable;)Ljava/lang/Throwable;
    //   6920: athrow
    //   6921: aload #9
    //   6923: invokevirtual getPackage : ()Ljava/lang/Package;
    //   6926: invokevirtual getName : ()Ljava/lang/String;
    //   6929: sipush #11798
    //   6932: sipush #-19117
    //   6935: invokestatic a : (II)Ljava/lang/String;
    //   6938: invokevirtual startsWith : (Ljava/lang/String;)Z
    //   6941: ifne -> 6951
    //   6944: goto -> 6951
    //   6947: invokestatic a : (Ljava/lang/Throwable;)Ljava/lang/Throwable;
    //   6950: athrow
    //   6951: aload #8
    //   6953: iconst_1
    //   6954: invokevirtual setAccessible : (Z)V
    //   6957: aload #8
    //   6959: aconst_null
    //   6960: invokevirtual get : (Ljava/lang/Object;)Ljava/lang/Object;
    //   6963: pop
    //   6964: iinc #7, 1
    //   6967: iload_2
    //   6968: ifeq -> 6829
    //   6971: sipush #11800
    //   6974: sipush #-13459
    //   6977: invokestatic a : (II)Ljava/lang/String;
    //   6980: invokestatic forName : (Ljava/lang/String;)Ljava/lang/Class;
    //   6983: invokevirtual getDeclaredMethods : ()[Ljava/lang/reflect/Method;
    //   6986: astore #5
    //   6988: aload #5
    //   6990: arraylength
    //   6991: istore #6
    //   6993: iconst_0
    //   6994: istore #7
    //   6996: iload #7
    //   6998: iload #6
    //   7000: if_icmpge -> 7137
    //   7003: aload #5
    //   7005: iload #7
    //   7007: aaload
    //   7008: astore #8
    //   7010: aload #8
    //   7012: invokevirtual getParameterTypes : ()[Ljava/lang/Class;
    //   7015: pop
    //   7016: aload #8
    //   7018: invokevirtual getModifiers : ()I
    //   7021: invokestatic isStatic : (I)Z
    //   7024: ifeq -> 7123
    //   7027: aload #8
    //   7029: invokevirtual getParameterTypes : ()[Ljava/lang/Class;
    //   7032: arraylength
    //   7033: iconst_2
    //   7034: if_icmpne -> 7123
    //   7037: goto -> 7044
    //   7040: invokestatic a : (Ljava/lang/Throwable;)Ljava/lang/Throwable;
    //   7043: athrow
    //   7044: aload #8
    //   7046: invokevirtual getReturnType : ()Ljava/lang/Class;
    //   7049: getstatic java/lang/Boolean.TYPE : Ljava/lang/Class;
    //   7052: if_acmpne -> 7123
    //   7055: goto -> 7062
    //   7058: invokestatic a : (Ljava/lang/Throwable;)Ljava/lang/Throwable;
    //   7061: athrow
    //   7062: aload #8
    //   7064: iconst_1
    //   7065: invokevirtual setAccessible : (Z)V
    //   7068: aload #8
    //   7070: aconst_null
    //   7071: iconst_2
    //   7072: anewarray java/lang/Object
    //   7075: dup
    //   7076: iconst_0
    //   7077: aload_0
    //   7078: aastore
    //   7079: dup
    //   7080: iconst_1
    //   7081: aload_1
    //   7082: ifnonnull -> 7100
    //   7085: goto -> 7092
    //   7088: invokestatic a : (Ljava/lang/Throwable;)Ljava/lang/Throwable;
    //   7091: athrow
    //   7092: aload_1
    //   7093: goto -> 7107
    //   7096: invokestatic a : (Ljava/lang/Throwable;)Ljava/lang/Throwable;
    //   7099: athrow
    //   7100: aload_1
    //   7101: checkcast [B
    //   7104: invokevirtual clone : ()Ljava/lang/Object;
    //   7107: aastore
    //   7108: invokevirtual invoke : (Ljava/lang/Object;[Ljava/lang/Object;)Ljava/lang/Object;
    //   7111: checkcast java/lang/Boolean
    //   7114: invokevirtual booleanValue : ()Z
    //   7117: istore #4
    //   7119: iload_2
    //   7120: ifeq -> 7137
    //   7123: iinc #7, 1
    //   7126: iload_2
    //   7127: ifeq -> 6996
    //   7130: goto -> 7137
    //   7133: invokestatic a : (Ljava/lang/Throwable;)Ljava/lang/Throwable;
    //   7136: athrow
    //   7137: iload #4
    //   7139: ifeq -> 7145
    //   7142: iload #4
    //   7144: ireturn
    //   7145: getstatic burp/Ztnw.Zr : Ljava/lang/String;
    //   7148: getstatic burp/Zr0u.ZB : Ljava/lang/Object;
    //   7151: checkcast java/math/BigInteger
    //   7154: invokevirtual intValue : ()I
    //   7157: bipush #32
    //   7159: irem
    //   7160: invokestatic abs : (I)I
    //   7163: invokevirtual charAt : (I)C
    //   7166: getstatic burp/Zzip.Za : Ljava/lang/String;
    //   7169: getstatic burp/Zxso.ZF : Ljava/lang/Object;
    //   7172: checkcast java/math/BigInteger
    //   7175: invokevirtual intValue : ()I
    //   7178: bipush #32
    //   7180: irem
    //   7181: invokestatic abs : (I)I
    //   7184: invokevirtual charAt : (I)C
    //   7187: if_icmple -> 7533
    //   7190: sipush #11796
    //   7193: sipush #-6899
    //   7196: invokestatic a : (II)Ljava/lang/String;
    //   7199: iconst_1
    //   7200: ldc burp/Zboa
    //   7202: invokevirtual getClassLoader : ()Ljava/lang/ClassLoader;
    //   7205: invokestatic forName : (Ljava/lang/String;ZLjava/lang/ClassLoader;)Ljava/lang/Class;
    //   7208: invokevirtual getDeclaredFields : ()[Ljava/lang/reflect/Field;
    //   7211: astore #5
    //   7213: aload #5
    //   7215: arraylength
    //   7216: istore #6
    //   7218: iconst_0
    //   7219: istore #7
    //   7221: iload #7
    //   7223: iload #6
    //   7225: if_icmpge -> 7363
    //   7228: aload #5
    //   7230: iload #7
    //   7232: aaload
    //   7233: astore #8
    //   7235: aload #8
    //   7237: invokevirtual getModifiers : ()I
    //   7240: invokestatic isStatic : (I)Z
    //   7243: ifne -> 7253
    //   7246: goto -> 7356
    //   7249: invokestatic a : (Ljava/lang/Throwable;)Ljava/lang/Throwable;
    //   7252: athrow
    //   7253: aload #8
    //   7255: invokevirtual getType : ()Ljava/lang/Class;
    //   7258: astore #9
    //   7260: aload #9
    //   7262: ifnull -> 7343
    //   7265: aload #9
    //   7267: invokevirtual isPrimitive : ()Z
    //   7270: ifne -> 7343
    //   7273: goto -> 7280
    //   7276: invokestatic a : (Ljava/lang/Throwable;)Ljava/lang/Throwable;
    //   7279: athrow
    //   7280: aload #9
    //   7282: invokevirtual getPackage : ()Ljava/lang/Package;
    //   7285: ifnull -> 7343
    //   7288: goto -> 7295
    //   7291: invokestatic a : (Ljava/lang/Throwable;)Ljava/lang/Throwable;
    //   7294: athrow
    //   7295: aload #9
    //   7297: invokevirtual getPackage : ()Ljava/lang/Package;
    //   7300: invokevirtual getName : ()Ljava/lang/String;
    //   7303: ifnull -> 7343
    //   7306: goto -> 7313
    //   7309: invokestatic a : (Ljava/lang/Throwable;)Ljava/lang/Throwable;
    //   7312: athrow
    //   7313: aload #9
    //   7315: invokevirtual getPackage : ()Ljava/lang/Package;
    //   7318: invokevirtual getName : ()Ljava/lang/String;
    //   7321: sipush #11798
    //   7324: sipush #-19117
    //   7327: invokestatic a : (II)Ljava/lang/String;
    //   7330: invokevirtual startsWith : (Ljava/lang/String;)Z
    //   7333: ifne -> 7343
    //   7336: goto -> 7343
    //   7339: invokestatic a : (Ljava/lang/Throwable;)Ljava/lang/Throwable;
    //   7342: athrow
    //   7343: aload #8
    //   7345: iconst_1
    //   7346: invokevirtual setAccessible : (Z)V
    //   7349: aload #8
    //   7351: aconst_null
    //   7352: invokevirtual get : (Ljava/lang/Object;)Ljava/lang/Object;
    //   7355: pop
    //   7356: iinc #7, 1
    //   7359: iload_2
    //   7360: ifeq -> 7221
    //   7363: sipush #11805
    //   7366: sipush #27492
    //   7369: invokestatic a : (II)Ljava/lang/String;
    //   7372: invokestatic forName : (Ljava/lang/String;)Ljava/lang/Class;
    //   7375: invokevirtual getDeclaredMethods : ()[Ljava/lang/reflect/Method;
    //   7378: astore #5
    //   7380: aload #5
    //   7382: arraylength
    //   7383: istore #6
    //   7385: iconst_0
    //   7386: istore #7
    //   7388: iload #7
    //   7390: iload #6
    //   7392: if_icmpge -> 7529
    //   7395: aload #5
    //   7397: iload #7
    //   7399: aaload
    //   7400: astore #8
    //   7402: aload #8
    //   7404: invokevirtual getParameterTypes : ()[Ljava/lang/Class;
    //   7407: pop
    //   7408: aload #8
    //   7410: invokevirtual getModifiers : ()I
    //   7413: invokestatic isStatic : (I)Z
    //   7416: ifeq -> 7515
    //   7419: aload #8
    //   7421: invokevirtual getParameterTypes : ()[Ljava/lang/Class;
    //   7424: arraylength
    //   7425: iconst_2
    //   7426: if_icmpne -> 7515
    //   7429: goto -> 7436
    //   7432: invokestatic a : (Ljava/lang/Throwable;)Ljava/lang/Throwable;
    //   7435: athrow
    //   7436: aload #8
    //   7438: invokevirtual getReturnType : ()Ljava/lang/Class;
    //   7441: getstatic java/lang/Boolean.TYPE : Ljava/lang/Class;
    //   7444: if_acmpne -> 7515
    //   7447: goto -> 7454
    //   7450: invokestatic a : (Ljava/lang/Throwable;)Ljava/lang/Throwable;
    //   7453: athrow
    //   7454: aload #8
    //   7456: iconst_1
    //   7457: invokevirtual setAccessible : (Z)V
    //   7460: aload #8
    //   7462: aconst_null
    //   7463: iconst_2
    //   7464: anewarray java/lang/Object
    //   7467: dup
    //   7468: iconst_0
    //   7469: aload_0
    //   7470: aastore
    //   7471: dup
    //   7472: iconst_1
    //   7473: aload_1
    //   7474: ifnonnull -> 7492
    //   7477: goto -> 7484
    //   7480: invokestatic a : (Ljava/lang/Throwable;)Ljava/lang/Throwable;
    //   7483: athrow
    //   7484: aload_1
    //   7485: goto -> 7499
    //   7488: invokestatic a : (Ljava/lang/Throwable;)Ljava/lang/Throwable;
    //   7491: athrow
    //   7492: aload_1
    //   7493: checkcast [B
    //   7496: invokevirtual clone : ()Ljava/lang/Object;
    //   7499: aastore
    //   7500: invokevirtual invoke : (Ljava/lang/Object;[Ljava/lang/Object;)Ljava/lang/Object;
    //   7503: checkcast java/lang/Boolean
    //   7506: invokevirtual booleanValue : ()Z
    //   7509: istore #4
    //   7511: iload_2
    //   7512: ifeq -> 7529
    //   7515: iinc #7, 1
    //   7518: iload_2
    //   7519: ifeq -> 7388
    //   7522: goto -> 7529
    //   7525: invokestatic a : (Ljava/lang/Throwable;)Ljava/lang/Throwable;
    //   7528: athrow
    //   7529: iload_2
    //   7530: ifeq -> 7872
    //   7533: sipush #11793
    //   7536: sipush #12644
    //   7539: invokestatic a : (II)Ljava/lang/String;
    //   7542: iconst_1
    //   7543: ldc burp/Zmh5
    //   7545: invokevirtual getClassLoader : ()Ljava/lang/ClassLoader;
    //   7548: invokestatic forName : (Ljava/lang/String;ZLjava/lang/ClassLoader;)Ljava/lang/Class;
    //   7551: invokevirtual getDeclaredFields : ()[Ljava/lang/reflect/Field;
    //   7554: astore #5
    //   7556: aload #5
    //   7558: arraylength
    //   7559: istore #6
    //   7561: iconst_0
    //   7562: istore #7
    //   7564: iload #7
    //   7566: iload #6
    //   7568: if_icmpge -> 7706
    //   7571: aload #5
    //   7573: iload #7
    //   7575: aaload
    //   7576: astore #8
    //   7578: aload #8
    //   7580: invokevirtual getModifiers : ()I
    //   7583: invokestatic isStatic : (I)Z
    //   7586: ifne -> 7596
    //   7589: goto -> 7699
    //   7592: invokestatic a : (Ljava/lang/Throwable;)Ljava/lang/Throwable;
    //   7595: athrow
    //   7596: aload #8
    //   7598: invokevirtual getType : ()Ljava/lang/Class;
    //   7601: astore #9
    //   7603: aload #9
    //   7605: ifnull -> 7686
    //   7608: aload #9
    //   7610: invokevirtual isPrimitive : ()Z
    //   7613: ifne -> 7686
    //   7616: goto -> 7623
    //   7619: invokestatic a : (Ljava/lang/Throwable;)Ljava/lang/Throwable;
    //   7622: athrow
    //   7623: aload #9
    //   7625: invokevirtual getPackage : ()Ljava/lang/Package;
    //   7628: ifnull -> 7686
    //   7631: goto -> 7638
    //   7634: invokestatic a : (Ljava/lang/Throwable;)Ljava/lang/Throwable;
    //   7637: athrow
    //   7638: aload #9
    //   7640: invokevirtual getPackage : ()Ljava/lang/Package;
    //   7643: invokevirtual getName : ()Ljava/lang/String;
    //   7646: ifnull -> 7686
    //   7649: goto -> 7656
    //   7652: invokestatic a : (Ljava/lang/Throwable;)Ljava/lang/Throwable;
    //   7655: athrow
    //   7656: aload #9
    //   7658: invokevirtual getPackage : ()Ljava/lang/Package;
    //   7661: invokevirtual getName : ()Ljava/lang/String;
    //   7664: sipush #11798
    //   7667: sipush #-19117
    //   7670: invokestatic a : (II)Ljava/lang/String;
    //   7673: invokevirtual startsWith : (Ljava/lang/String;)Z
    //   7676: ifne -> 7686
    //   7679: goto -> 7686
    //   7682: invokestatic a : (Ljava/lang/Throwable;)Ljava/lang/Throwable;
    //   7685: athrow
    //   7686: aload #8
    //   7688: iconst_1
    //   7689: invokevirtual setAccessible : (Z)V
    //   7692: aload #8
    //   7694: aconst_null
    //   7695: invokevirtual get : (Ljava/lang/Object;)Ljava/lang/Object;
    //   7698: pop
    //   7699: iinc #7, 1
    //   7702: iload_2
    //   7703: ifeq -> 7564
    //   7706: sipush #11791
    //   7709: sipush #5008
    //   7712: invokestatic a : (II)Ljava/lang/String;
    //   7715: invokestatic forName : (Ljava/lang/String;)Ljava/lang/Class;
    //   7718: invokevirtual getDeclaredMethods : ()[Ljava/lang/reflect/Method;
    //   7721: astore #5
    //   7723: aload #5
    //   7725: arraylength
    //   7726: istore #6
    //   7728: iconst_0
    //   7729: istore #7
    //   7731: iload #7
    //   7733: iload #6
    //   7735: if_icmpge -> 7872
    //   7738: aload #5
    //   7740: iload #7
    //   7742: aaload
    //   7743: astore #8
    //   7745: aload #8
    //   7747: invokevirtual getParameterTypes : ()[Ljava/lang/Class;
    //   7750: pop
    //   7751: aload #8
    //   7753: invokevirtual getModifiers : ()I
    //   7756: invokestatic isStatic : (I)Z
    //   7759: ifeq -> 7858
    //   7762: aload #8
    //   7764: invokevirtual getParameterTypes : ()[Ljava/lang/Class;
    //   7767: arraylength
    //   7768: iconst_2
    //   7769: if_icmpne -> 7858
    //   7772: goto -> 7779
    //   7775: invokestatic a : (Ljava/lang/Throwable;)Ljava/lang/Throwable;
    //   7778: athrow
    //   7779: aload #8
    //   7781: invokevirtual getReturnType : ()Ljava/lang/Class;
    //   7784: getstatic java/lang/Boolean.TYPE : Ljava/lang/Class;
    //   7787: if_acmpne -> 7858
    //   7790: goto -> 7797
    //   7793: invokestatic a : (Ljava/lang/Throwable;)Ljava/lang/Throwable;
    //   7796: athrow
    //   7797: aload #8
    //   7799: iconst_1
    //   7800: invokevirtual setAccessible : (Z)V
    //   7803: aload #8
    //   7805: aconst_null
    //   7806: iconst_2
    //   7807: anewarray java/lang/Object
    //   7810: dup
    //   7811: iconst_0
    //   7812: aload_0
    //   7813: aastore
    //   7814: dup
    //   7815: iconst_1
    //   7816: aload_1
    //   7817: ifnonnull -> 7835
    //   7820: goto -> 7827
    //   7823: invokestatic a : (Ljava/lang/Throwable;)Ljava/lang/Throwable;
    //   7826: athrow
    //   7827: aload_1
    //   7828: goto -> 7842
    //   7831: invokestatic a : (Ljava/lang/Throwable;)Ljava/lang/Throwable;
    //   7834: athrow
    //   7835: aload_1
    //   7836: checkcast [B
    //   7839: invokevirtual clone : ()Ljava/lang/Object;
    //   7842: aastore
    //   7843: invokevirtual invoke : (Ljava/lang/Object;[Ljava/lang/Object;)Ljava/lang/Object;
    //   7846: checkcast java/lang/Boolean
    //   7849: invokevirtual booleanValue : ()Z
    //   7852: istore #4
    //   7854: iload_2
    //   7855: ifeq -> 7872
    //   7858: iinc #7, 1
    //   7861: iload_2
    //   7862: ifeq -> 7731
    //   7865: goto -> 7872
    //   7868: invokestatic a : (Ljava/lang/Throwable;)Ljava/lang/Throwable;
    //   7871: athrow
    //   7872: iload #4
    //   7874: ifeq -> 7880
    //   7877: iload #4
    //   7879: ireturn
    //   7880: getstatic burp/Zxwl.Zu : Ljava/lang/String;
    //   7883: getstatic burp/Zlv6.ZN : Ljava/lang/Object;
    //   7886: checkcast java/math/BigInteger
    //   7889: invokevirtual intValue : ()I
    //   7892: bipush #32
    //   7894: irem
    //   7895: invokestatic abs : (I)I
    //   7898: invokevirtual charAt : (I)C
    //   7901: getstatic burp/Ze3d.ZL : Ljava/lang/String;
    //   7904: getstatic burp/Zmj4.Zm : Ljava/lang/Object;
    //   7907: checkcast java/math/BigInteger
    //   7910: invokevirtual intValue : ()I
    //   7913: bipush #32
    //   7915: irem
    //   7916: invokestatic abs : (I)I
    //   7919: invokevirtual charAt : (I)C
    //   7922: if_icmple -> 8268
    //   7925: sipush #11785
    //   7928: sipush #13471
    //   7931: invokestatic a : (II)Ljava/lang/String;
    //   7934: iconst_1
    //   7935: ldc burp/Zmzh
    //   7937: invokevirtual getClassLoader : ()Ljava/lang/ClassLoader;
    //   7940: invokestatic forName : (Ljava/lang/String;ZLjava/lang/ClassLoader;)Ljava/lang/Class;
    //   7943: invokevirtual getDeclaredFields : ()[Ljava/lang/reflect/Field;
    //   7946: astore #5
    //   7948: aload #5
    //   7950: arraylength
    //   7951: istore #6
    //   7953: iconst_0
    //   7954: istore #7
    //   7956: iload #7
    //   7958: iload #6
    //   7960: if_icmpge -> 8098
    //   7963: aload #5
    //   7965: iload #7
    //   7967: aaload
    //   7968: astore #8
    //   7970: aload #8
    //   7972: invokevirtual getModifiers : ()I
    //   7975: invokestatic isStatic : (I)Z
    //   7978: ifne -> 7988
    //   7981: goto -> 8091
    //   7984: invokestatic a : (Ljava/lang/Throwable;)Ljava/lang/Throwable;
    //   7987: athrow
    //   7988: aload #8
    //   7990: invokevirtual getType : ()Ljava/lang/Class;
    //   7993: astore #9
    //   7995: aload #9
    //   7997: ifnull -> 8078
    //   8000: aload #9
    //   8002: invokevirtual isPrimitive : ()Z
    //   8005: ifne -> 8078
    //   8008: goto -> 8015
    //   8011: invokestatic a : (Ljava/lang/Throwable;)Ljava/lang/Throwable;
    //   8014: athrow
    //   8015: aload #9
    //   8017: invokevirtual getPackage : ()Ljava/lang/Package;
    //   8020: ifnull -> 8078
    //   8023: goto -> 8030
    //   8026: invokestatic a : (Ljava/lang/Throwable;)Ljava/lang/Throwable;
    //   8029: athrow
    //   8030: aload #9
    //   8032: invokevirtual getPackage : ()Ljava/lang/Package;
    //   8035: invokevirtual getName : ()Ljava/lang/String;
    //   8038: ifnull -> 8078
    //   8041: goto -> 8048
    //   8044: invokestatic a : (Ljava/lang/Throwable;)Ljava/lang/Throwable;
    //   8047: athrow
    //   8048: aload #9
    //   8050: invokevirtual getPackage : ()Ljava/lang/Package;
    //   8053: invokevirtual getName : ()Ljava/lang/String;
    //   8056: sipush #11798
    //   8059: sipush #-19117
    //   8062: invokestatic a : (II)Ljava/lang/String;
    //   8065: invokevirtual startsWith : (Ljava/lang/String;)Z
    //   8068: ifne -> 8078
    //   8071: goto -> 8078
    //   8074: invokestatic a : (Ljava/lang/Throwable;)Ljava/lang/Throwable;
    //   8077: athrow
    //   8078: aload #8
    //   8080: iconst_1
    //   8081: invokevirtual setAccessible : (Z)V
    //   8084: aload #8
    //   8086: aconst_null
    //   8087: invokevirtual get : (Ljava/lang/Object;)Ljava/lang/Object;
    //   8090: pop
    //   8091: iinc #7, 1
    //   8094: iload_2
    //   8095: ifeq -> 7956
    //   8098: sipush #11790
    //   8101: sipush #17367
    //   8104: invokestatic a : (II)Ljava/lang/String;
    //   8107: invokestatic forName : (Ljava/lang/String;)Ljava/lang/Class;
    //   8110: invokevirtual getDeclaredMethods : ()[Ljava/lang/reflect/Method;
    //   8113: astore #5
    //   8115: aload #5
    //   8117: arraylength
    //   8118: istore #6
    //   8120: iconst_0
    //   8121: istore #7
    //   8123: iload #7
    //   8125: iload #6
    //   8127: if_icmpge -> 8264
    //   8130: aload #5
    //   8132: iload #7
    //   8134: aaload
    //   8135: astore #8
    //   8137: aload #8
    //   8139: invokevirtual getParameterTypes : ()[Ljava/lang/Class;
    //   8142: pop
    //   8143: aload #8
    //   8145: invokevirtual getModifiers : ()I
    //   8148: invokestatic isStatic : (I)Z
    //   8151: ifeq -> 8250
    //   8154: aload #8
    //   8156: invokevirtual getParameterTypes : ()[Ljava/lang/Class;
    //   8159: arraylength
    //   8160: iconst_2
    //   8161: if_icmpne -> 8250
    //   8164: goto -> 8171
    //   8167: invokestatic a : (Ljava/lang/Throwable;)Ljava/lang/Throwable;
    //   8170: athrow
    //   8171: aload #8
    //   8173: invokevirtual getReturnType : ()Ljava/lang/Class;
    //   8176: getstatic java/lang/Boolean.TYPE : Ljava/lang/Class;
    //   8179: if_acmpne -> 8250
    //   8182: goto -> 8189
    //   8185: invokestatic a : (Ljava/lang/Throwable;)Ljava/lang/Throwable;
    //   8188: athrow
    //   8189: aload #8
    //   8191: iconst_1
    //   8192: invokevirtual setAccessible : (Z)V
    //   8195: aload #8
    //   8197: aconst_null
    //   8198: iconst_2
    //   8199: anewarray java/lang/Object
    //   8202: dup
    //   8203: iconst_0
    //   8204: aload_0
    //   8205: aastore
    //   8206: dup
    //   8207: iconst_1
    //   8208: aload_1
    //   8209: ifnonnull -> 8227
    //   8212: goto -> 8219
    //   8215: invokestatic a : (Ljava/lang/Throwable;)Ljava/lang/Throwable;
    //   8218: athrow
    //   8219: aload_1
    //   8220: goto -> 8234
    //   8223: invokestatic a : (Ljava/lang/Throwable;)Ljava/lang/Throwable;
    //   8226: athrow
    //   8227: aload_1
    //   8228: checkcast [B
    //   8231: invokevirtual clone : ()Ljava/lang/Object;
    //   8234: aastore
    //   8235: invokevirtual invoke : (Ljava/lang/Object;[Ljava/lang/Object;)Ljava/lang/Object;
    //   8238: checkcast java/lang/Boolean
    //   8241: invokevirtual booleanValue : ()Z
    //   8244: istore #4
    //   8246: iload_2
    //   8247: ifeq -> 8264
    //   8250: iinc #7, 1
    //   8253: iload_2
    //   8254: ifeq -> 8123
    //   8257: goto -> 8264
    //   8260: invokestatic a : (Ljava/lang/Throwable;)Ljava/lang/Throwable;
    //   8263: athrow
    //   8264: iload_2
    //   8265: ifeq -> 8607
    //   8268: sipush #11776
    //   8271: sipush #-8426
    //   8274: invokestatic a : (II)Ljava/lang/String;
    //   8277: iconst_1
    //   8278: ldc burp/Zkq9
    //   8280: invokevirtual getClassLoader : ()Ljava/lang/ClassLoader;
    //   8283: invokestatic forName : (Ljava/lang/String;ZLjava/lang/ClassLoader;)Ljava/lang/Class;
    //   8286: invokevirtual getDeclaredFields : ()[Ljava/lang/reflect/Field;
    //   8289: astore #5
    //   8291: aload #5
    //   8293: arraylength
    //   8294: istore #6
    //   8296: iconst_0
    //   8297: istore #7
    //   8299: iload #7
    //   8301: iload #6
    //   8303: if_icmpge -> 8441
    //   8306: aload #5
    //   8308: iload #7
    //   8310: aaload
    //   8311: astore #8
    //   8313: aload #8
    //   8315: invokevirtual getModifiers : ()I
    //   8318: invokestatic isStatic : (I)Z
    //   8321: ifne -> 8331
    //   8324: goto -> 8434
    //   8327: invokestatic a : (Ljava/lang/Throwable;)Ljava/lang/Throwable;
    //   8330: athrow
    //   8331: aload #8
    //   8333: invokevirtual getType : ()Ljava/lang/Class;
    //   8336: astore #9
    //   8338: aload #9
    //   8340: ifnull -> 8421
    //   8343: aload #9
    //   8345: invokevirtual isPrimitive : ()Z
    //   8348: ifne -> 8421
    //   8351: goto -> 8358
    //   8354: invokestatic a : (Ljava/lang/Throwable;)Ljava/lang/Throwable;
    //   8357: athrow
    //   8358: aload #9
    //   8360: invokevirtual getPackage : ()Ljava/lang/Package;
    //   8363: ifnull -> 8421
    //   8366: goto -> 8373
    //   8369: invokestatic a : (Ljava/lang/Throwable;)Ljava/lang/Throwable;
    //   8372: athrow
    //   8373: aload #9
    //   8375: invokevirtual getPackage : ()Ljava/lang/Package;
    //   8378: invokevirtual getName : ()Ljava/lang/String;
    //   8381: ifnull -> 8421
    //   8384: goto -> 8391
    //   8387: invokestatic a : (Ljava/lang/Throwable;)Ljava/lang/Throwable;
    //   8390: athrow
    //   8391: aload #9
    //   8393: invokevirtual getPackage : ()Ljava/lang/Package;
    //   8396: invokevirtual getName : ()Ljava/lang/String;
    //   8399: sipush #11798
    //   8402: sipush #-19117
    //   8405: invokestatic a : (II)Ljava/lang/String;
    //   8408: invokevirtual startsWith : (Ljava/lang/String;)Z
    //   8411: ifne -> 8421
    //   8414: goto -> 8421
    //   8417: invokestatic a : (Ljava/lang/Throwable;)Ljava/lang/Throwable;
    //   8420: athrow
    //   8421: aload #8
    //   8423: iconst_1
    //   8424: invokevirtual setAccessible : (Z)V
    //   8427: aload #8
    //   8429: aconst_null
    //   8430: invokevirtual get : (Ljava/lang/Object;)Ljava/lang/Object;
    //   8433: pop
    //   8434: iinc #7, 1
    //   8437: iload_2
    //   8438: ifeq -> 8299
    //   8441: sipush #11797
    //   8444: sipush #4310
    //   8447: invokestatic a : (II)Ljava/lang/String;
    //   8450: invokestatic forName : (Ljava/lang/String;)Ljava/lang/Class;
    //   8453: invokevirtual getDeclaredMethods : ()[Ljava/lang/reflect/Method;
    //   8456: astore #5
    //   8458: aload #5
    //   8460: arraylength
    //   8461: istore #6
    //   8463: iconst_0
    //   8464: istore #7
    //   8466: iload #7
    //   8468: iload #6
    //   8470: if_icmpge -> 8607
    //   8473: aload #5
    //   8475: iload #7
    //   8477: aaload
    //   8478: astore #8
    //   8480: aload #8
    //   8482: invokevirtual getParameterTypes : ()[Ljava/lang/Class;
    //   8485: pop
    //   8486: aload #8
    //   8488: invokevirtual getModifiers : ()I
    //   8491: invokestatic isStatic : (I)Z
    //   8494: ifeq -> 8593
    //   8497: aload #8
    //   8499: invokevirtual getParameterTypes : ()[Ljava/lang/Class;
    //   8502: arraylength
    //   8503: iconst_2
    //   8504: if_icmpne -> 8593
    //   8507: goto -> 8514
    //   8510: invokestatic a : (Ljava/lang/Throwable;)Ljava/lang/Throwable;
    //   8513: athrow
    //   8514: aload #8
    //   8516: invokevirtual getReturnType : ()Ljava/lang/Class;
    //   8519: getstatic java/lang/Boolean.TYPE : Ljava/lang/Class;
    //   8522: if_acmpne -> 8593
    //   8525: goto -> 8532
    //   8528: invokestatic a : (Ljava/lang/Throwable;)Ljava/lang/Throwable;
    //   8531: athrow
    //   8532: aload #8
    //   8534: iconst_1
    //   8535: invokevirtual setAccessible : (Z)V
    //   8538: aload #8
    //   8540: aconst_null
    //   8541: iconst_2
    //   8542: anewarray java/lang/Object
    //   8545: dup
    //   8546: iconst_0
    //   8547: aload_0
    //   8548: aastore
    //   8549: dup
    //   8550: iconst_1
    //   8551: aload_1
    //   8552: ifnonnull -> 8570
    //   8555: goto -> 8562
    //   8558: invokestatic a : (Ljava/lang/Throwable;)Ljava/lang/Throwable;
    //   8561: athrow
    //   8562: aload_1
    //   8563: goto -> 8577
    //   8566: invokestatic a : (Ljava/lang/Throwable;)Ljava/lang/Throwable;
    //   8569: athrow
    //   8570: aload_1
    //   8571: checkcast [B
    //   8574: invokevirtual clone : ()Ljava/lang/Object;
    //   8577: aastore
    //   8578: invokevirtual invoke : (Ljava/lang/Object;[Ljava/lang/Object;)Ljava/lang/Object;
    //   8581: checkcast java/lang/Boolean
    //   8584: invokevirtual booleanValue : ()Z
    //   8587: istore #4
    //   8589: iload_2
    //   8590: ifeq -> 8607
    //   8593: iinc #7, 1
    //   8596: iload_2
    //   8597: ifeq -> 8466
    //   8600: goto -> 8607
    //   8603: invokestatic a : (Ljava/lang/Throwable;)Ljava/lang/Throwable;
    //   8606: athrow
    //   8607: iload #4
    //   8609: ifeq -> 8615
    //   8612: iload #4
    //   8614: ireturn
    //   8615: getstatic burp/Zxk9.Zx : Ljava/lang/String;
    //   8618: getstatic burp/Zg_p.Zx : Ljava/lang/Object;
    //   8621: checkcast java/math/BigInteger
    //   8624: invokevirtual intValue : ()I
    //   8627: bipush #32
    //   8629: irem
    //   8630: invokestatic abs : (I)I
    //   8633: invokevirtual charAt : (I)C
    //   8636: getstatic burp/Zlv6.Zt : Ljava/lang/String;
    //   8639: getstatic burp/Zkbf.Zx : Ljava/lang/Object;
    //   8642: checkcast java/math/BigInteger
    //   8645: invokevirtual intValue : ()I
    //   8648: bipush #32
    //   8650: irem
    //   8651: invokestatic abs : (I)I
    //   8654: invokevirtual charAt : (I)C
    //   8657: if_icmpgt -> 9003
    //   8660: sipush #11804
    //   8663: sipush #-16555
    //   8666: invokestatic a : (II)Ljava/lang/String;
    //   8669: iconst_1
    //   8670: ldc burp/Zldx
    //   8672: invokevirtual getClassLoader : ()Ljava/lang/ClassLoader;
    //   8675: invokestatic forName : (Ljava/lang/String;ZLjava/lang/ClassLoader;)Ljava/lang/Class;
    //   8678: invokevirtual getDeclaredFields : ()[Ljava/lang/reflect/Field;
    //   8681: astore #5
    //   8683: aload #5
    //   8685: arraylength
    //   8686: istore #6
    //   8688: iconst_0
    //   8689: istore #7
    //   8691: iload #7
    //   8693: iload #6
    //   8695: if_icmpge -> 8833
    //   8698: aload #5
    //   8700: iload #7
    //   8702: aaload
    //   8703: astore #8
    //   8705: aload #8
    //   8707: invokevirtual getModifiers : ()I
    //   8710: invokestatic isStatic : (I)Z
    //   8713: ifne -> 8723
    //   8716: goto -> 8826
    //   8719: invokestatic a : (Ljava/lang/Throwable;)Ljava/lang/Throwable;
    //   8722: athrow
    //   8723: aload #8
    //   8725: invokevirtual getType : ()Ljava/lang/Class;
    //   8728: astore #9
    //   8730: aload #9
    //   8732: ifnull -> 8813
    //   8735: aload #9
    //   8737: invokevirtual isPrimitive : ()Z
    //   8740: ifne -> 8813
    //   8743: goto -> 8750
    //   8746: invokestatic a : (Ljava/lang/Throwable;)Ljava/lang/Throwable;
    //   8749: athrow
    //   8750: aload #9
    //   8752: invokevirtual getPackage : ()Ljava/lang/Package;
    //   8755: ifnull -> 8813
    //   8758: goto -> 8765
    //   8761: invokestatic a : (Ljava/lang/Throwable;)Ljava/lang/Throwable;
    //   8764: athrow
    //   8765: aload #9
    //   8767: invokevirtual getPackage : ()Ljava/lang/Package;
    //   8770: invokevirtual getName : ()Ljava/lang/String;
    //   8773: ifnull -> 8813
    //   8776: goto -> 8783
    //   8779: invokestatic a : (Ljava/lang/Throwable;)Ljava/lang/Throwable;
    //   8782: athrow
    //   8783: aload #9
    //   8785: invokevirtual getPackage : ()Ljava/lang/Package;
    //   8788: invokevirtual getName : ()Ljava/lang/String;
    //   8791: sipush #11798
    //   8794: sipush #-19117
    //   8797: invokestatic a : (II)Ljava/lang/String;
    //   8800: invokevirtual startsWith : (Ljava/lang/String;)Z
    //   8803: ifne -> 8813
    //   8806: goto -> 8813
    //   8809: invokestatic a : (Ljava/lang/Throwable;)Ljava/lang/Throwable;
    //   8812: athrow
    //   8813: aload #8
    //   8815: iconst_1
    //   8816: invokevirtual setAccessible : (Z)V
    //   8819: aload #8
    //   8821: aconst_null
    //   8822: invokevirtual get : (Ljava/lang/Object;)Ljava/lang/Object;
    //   8825: pop
    //   8826: iinc #7, 1
    //   8829: iload_2
    //   8830: ifeq -> 8691
    //   8833: sipush #11795
    //   8836: sipush #-2302
    //   8839: invokestatic a : (II)Ljava/lang/String;
    //   8842: invokestatic forName : (Ljava/lang/String;)Ljava/lang/Class;
    //   8845: invokevirtual getDeclaredMethods : ()[Ljava/lang/reflect/Method;
    //   8848: astore #5
    //   8850: aload #5
    //   8852: arraylength
    //   8853: istore #6
    //   8855: iconst_0
    //   8856: istore #7
    //   8858: iload #7
    //   8860: iload #6
    //   8862: if_icmpge -> 8999
    //   8865: aload #5
    //   8867: iload #7
    //   8869: aaload
    //   8870: astore #8
    //   8872: aload #8
    //   8874: invokevirtual getParameterTypes : ()[Ljava/lang/Class;
    //   8877: pop
    //   8878: aload #8
    //   8880: invokevirtual getModifiers : ()I
    //   8883: invokestatic isStatic : (I)Z
    //   8886: ifeq -> 8985
    //   8889: aload #8
    //   8891: invokevirtual getParameterTypes : ()[Ljava/lang/Class;
    //   8894: arraylength
    //   8895: iconst_2
    //   8896: if_icmpne -> 8985
    //   8899: goto -> 8906
    //   8902: invokestatic a : (Ljava/lang/Throwable;)Ljava/lang/Throwable;
    //   8905: athrow
    //   8906: aload #8
    //   8908: invokevirtual getReturnType : ()Ljava/lang/Class;
    //   8911: getstatic java/lang/Boolean.TYPE : Ljava/lang/Class;
    //   8914: if_acmpne -> 8985
    //   8917: goto -> 8924
    //   8920: invokestatic a : (Ljava/lang/Throwable;)Ljava/lang/Throwable;
    //   8923: athrow
    //   8924: aload #8
    //   8926: iconst_1
    //   8927: invokevirtual setAccessible : (Z)V
    //   8930: aload #8
    //   8932: aconst_null
    //   8933: iconst_2
    //   8934: anewarray java/lang/Object
    //   8937: dup
    //   8938: iconst_0
    //   8939: aload_0
    //   8940: aastore
    //   8941: dup
    //   8942: iconst_1
    //   8943: aload_1
    //   8944: ifnonnull -> 8962
    //   8947: goto -> 8954
    //   8950: invokestatic a : (Ljava/lang/Throwable;)Ljava/lang/Throwable;
    //   8953: athrow
    //   8954: aload_1
    //   8955: goto -> 8969
    //   8958: invokestatic a : (Ljava/lang/Throwable;)Ljava/lang/Throwable;
    //   8961: athrow
    //   8962: aload_1
    //   8963: checkcast [B
    //   8966: invokevirtual clone : ()Ljava/lang/Object;
    //   8969: aastore
    //   8970: invokevirtual invoke : (Ljava/lang/Object;[Ljava/lang/Object;)Ljava/lang/Object;
    //   8973: checkcast java/lang/Boolean
    //   8976: invokevirtual booleanValue : ()Z
    //   8979: istore #4
    //   8981: iload_2
    //   8982: ifeq -> 8999
    //   8985: iinc #7, 1
    //   8988: iload_2
    //   8989: ifeq -> 8858
    //   8992: goto -> 8999
    //   8995: invokestatic a : (Ljava/lang/Throwable;)Ljava/lang/Throwable;
    //   8998: athrow
    //   8999: iload_2
    //   9000: ifeq -> 9342
    //   9003: sipush #11807
    //   9006: sipush #6696
    //   9009: invokestatic a : (II)Ljava/lang/String;
    //   9012: iconst_1
    //   9013: ldc burp/Ze40
    //   9015: invokevirtual getClassLoader : ()Ljava/lang/ClassLoader;
    //   9018: invokestatic forName : (Ljava/lang/String;ZLjava/lang/ClassLoader;)Ljava/lang/Class;
    //   9021: invokevirtual getDeclaredFields : ()[Ljava/lang/reflect/Field;
    //   9024: astore #5
    //   9026: aload #5
    //   9028: arraylength
    //   9029: istore #6
    //   9031: iconst_0
    //   9032: istore #7
    //   9034: iload #7
    //   9036: iload #6
    //   9038: if_icmpge -> 9176
    //   9041: aload #5
    //   9043: iload #7
    //   9045: aaload
    //   9046: astore #8
    //   9048: aload #8
    //   9050: invokevirtual getModifiers : ()I
    //   9053: invokestatic isStatic : (I)Z
    //   9056: ifne -> 9066
    //   9059: goto -> 9169
    //   9062: invokestatic a : (Ljava/lang/Throwable;)Ljava/lang/Throwable;
    //   9065: athrow
    //   9066: aload #8
    //   9068: invokevirtual getType : ()Ljava/lang/Class;
    //   9071: astore #9
    //   9073: aload #9
    //   9075: ifnull -> 9156
    //   9078: aload #9
    //   9080: invokevirtual isPrimitive : ()Z
    //   9083: ifne -> 9156
    //   9086: goto -> 9093
    //   9089: invokestatic a : (Ljava/lang/Throwable;)Ljava/lang/Throwable;
    //   9092: athrow
    //   9093: aload #9
    //   9095: invokevirtual getPackage : ()Ljava/lang/Package;
    //   9098: ifnull -> 9156
    //   9101: goto -> 9108
    //   9104: invokestatic a : (Ljava/lang/Throwable;)Ljava/lang/Throwable;
    //   9107: athrow
    //   9108: aload #9
    //   9110: invokevirtual getPackage : ()Ljava/lang/Package;
    //   9113: invokevirtual getName : ()Ljava/lang/String;
    //   9116: ifnull -> 9156
    //   9119: goto -> 9126
    //   9122: invokestatic a : (Ljava/lang/Throwable;)Ljava/lang/Throwable;
    //   9125: athrow
    //   9126: aload #9
    //   9128: invokevirtual getPackage : ()Ljava/lang/Package;
    //   9131: invokevirtual getName : ()Ljava/lang/String;
    //   9134: sipush #11798
    //   9137: sipush #-19117
    //   9140: invokestatic a : (II)Ljava/lang/String;
    //   9143: invokevirtual startsWith : (Ljava/lang/String;)Z
    //   9146: ifne -> 9156
    //   9149: goto -> 9156
    //   9152: invokestatic a : (Ljava/lang/Throwable;)Ljava/lang/Throwable;
    //   9155: athrow
    //   9156: aload #8
    //   9158: iconst_1
    //   9159: invokevirtual setAccessible : (Z)V
    //   9162: aload #8
    //   9164: aconst_null
    //   9165: invokevirtual get : (Ljava/lang/Object;)Ljava/lang/Object;
    //   9168: pop
    //   9169: iinc #7, 1
    //   9172: iload_2
    //   9173: ifeq -> 9034
    //   9176: sipush #11789
    //   9179: sipush #8400
    //   9182: invokestatic a : (II)Ljava/lang/String;
    //   9185: invokestatic forName : (Ljava/lang/String;)Ljava/lang/Class;
    //   9188: invokevirtual getDeclaredMethods : ()[Ljava/lang/reflect/Method;
    //   9191: astore #5
    //   9193: aload #5
    //   9195: arraylength
    //   9196: istore #6
    //   9198: iconst_0
    //   9199: istore #7
    //   9201: iload #7
    //   9203: iload #6
    //   9205: if_icmpge -> 9342
    //   9208: aload #5
    //   9210: iload #7
    //   9212: aaload
    //   9213: astore #8
    //   9215: aload #8
    //   9217: invokevirtual getParameterTypes : ()[Ljava/lang/Class;
    //   9220: pop
    //   9221: aload #8
    //   9223: invokevirtual getModifiers : ()I
    //   9226: invokestatic isStatic : (I)Z
    //   9229: ifeq -> 9328
    //   9232: aload #8
    //   9234: invokevirtual getParameterTypes : ()[Ljava/lang/Class;
    //   9237: arraylength
    //   9238: iconst_2
    //   9239: if_icmpne -> 9328
    //   9242: goto -> 9249
    //   9245: invokestatic a : (Ljava/lang/Throwable;)Ljava/lang/Throwable;
    //   9248: athrow
    //   9249: aload #8
    //   9251: invokevirtual getReturnType : ()Ljava/lang/Class;
    //   9254: getstatic java/lang/Boolean.TYPE : Ljava/lang/Class;
    //   9257: if_acmpne -> 9328
    //   9260: goto -> 9267
    //   9263: invokestatic a : (Ljava/lang/Throwable;)Ljava/lang/Throwable;
    //   9266: athrow
    //   9267: aload #8
    //   9269: iconst_1
    //   9270: invokevirtual setAccessible : (Z)V
    //   9273: aload #8
    //   9275: aconst_null
    //   9276: iconst_2
    //   9277: anewarray java/lang/Object
    //   9280: dup
    //   9281: iconst_0
    //   9282: aload_0
    //   9283: aastore
    //   9284: dup
    //   9285: iconst_1
    //   9286: aload_1
    //   9287: ifnonnull -> 9305
    //   9290: goto -> 9297
    //   9293: invokestatic a : (Ljava/lang/Throwable;)Ljava/lang/Throwable;
    //   9296: athrow
    //   9297: aload_1
    //   9298: goto -> 9312
    //   9301: invokestatic a : (Ljava/lang/Throwable;)Ljava/lang/Throwable;
    //   9304: athrow
    //   9305: aload_1
    //   9306: checkcast [B
    //   9309: invokevirtual clone : ()Ljava/lang/Object;
    //   9312: aastore
    //   9313: invokevirtual invoke : (Ljava/lang/Object;[Ljava/lang/Object;)Ljava/lang/Object;
    //   9316: checkcast java/lang/Boolean
    //   9319: invokevirtual booleanValue : ()Z
    //   9322: istore #4
    //   9324: iload_2
    //   9325: ifeq -> 9342
    //   9328: iinc #7, 1
    //   9331: iload_2
    //   9332: ifeq -> 9201
    //   9335: goto -> 9342
    //   9338: invokestatic a : (Ljava/lang/Throwable;)Ljava/lang/Throwable;
    //   9341: athrow
    //   9342: iload #4
    //   9344: ireturn
    //   9345: astore_3
    //   9346: new java/lang/Exception
    //   9349: dup
    //   9350: aload_3
    //   9351: invokevirtual getMessage : ()Ljava/lang/String;
    //   9354: invokespecial <init> : (Ljava/lang/String;)V
    //   9357: athrow
    // Exception table:
    //   from	to	target	type
    //   4	7144	9345	java/lang/Throwable
    //   4371	4546	4549	java/lang/Throwable
    //   4516	4583	4586	java/lang/Throwable
    //   4553	4620	4623	java/lang/Throwable
    //   4590	4657	4660	java/lang/Throwable
    //   4627	4694	4697	java/lang/Throwable
    //   4664	4731	4734	java/lang/Throwable
    //   4701	4768	4771	java/lang/Throwable
    //   4738	4805	4808	java/lang/Throwable
    //   4775	4842	4845	java/lang/Throwable
    //   4812	4879	4882	java/lang/Throwable
    //   4849	4916	4919	java/lang/Throwable
    //   4886	4953	4956	java/lang/Throwable
    //   4923	4990	4993	java/lang/Throwable
    //   4960	5027	5030	java/lang/Throwable
    //   4997	5064	5067	java/lang/Throwable
    //   5034	5101	5104	java/lang/Throwable
    //   5071	5138	5141	java/lang/Throwable
    //   5108	5175	5178	java/lang/Throwable
    //   5145	5212	5215	java/lang/Throwable
    //   5182	5249	5252	java/lang/Throwable
    //   5219	5286	5289	java/lang/Throwable
    //   5256	5323	5326	java/lang/Throwable
    //   5293	5360	5363	java/lang/Throwable
    //   5330	5397	5400	java/lang/Throwable
    //   5367	5434	5437	java/lang/Throwable
    //   5404	5471	5474	java/lang/Throwable
    //   5441	5508	5511	java/lang/Throwable
    //   5478	5545	5548	java/lang/Throwable
    //   5515	5582	5585	java/lang/Throwable
    //   5552	5619	5622	java/lang/Throwable
    //   5589	5656	5659	java/lang/Throwable
    //   5626	5689	5692	java/lang/Throwable
    //   5755	5769	5769	java/lang/Throwable
    //   5780	5793	5796	java/lang/Throwable
    //   5785	5808	5811	java/lang/Throwable
    //   5800	5826	5829	java/lang/Throwable
    //   5815	5856	5859	java/lang/Throwable
    //   5922	5949	5952	java/lang/Throwable
    //   5939	5970	5973	java/lang/Throwable
    //   5956	6000	6003	java/lang/Throwable
    //   5977	6011	6011	java/lang/Throwable
    //   6022	6038	6041	java/lang/Throwable
    //   6118	6132	6132	java/lang/Throwable
    //   6143	6156	6159	java/lang/Throwable
    //   6148	6171	6174	java/lang/Throwable
    //   6163	6189	6192	java/lang/Throwable
    //   6178	6219	6222	java/lang/Throwable
    //   6285	6312	6315	java/lang/Throwable
    //   6302	6333	6336	java/lang/Throwable
    //   6319	6363	6366	java/lang/Throwable
    //   6340	6374	6374	java/lang/Throwable
    //   6385	6401	6404	java/lang/Throwable
    //   6501	6515	6515	java/lang/Throwable
    //   6526	6539	6542	java/lang/Throwable
    //   6531	6554	6557	java/lang/Throwable
    //   6546	6572	6575	java/lang/Throwable
    //   6561	6602	6605	java/lang/Throwable
    //   6668	6695	6698	java/lang/Throwable
    //   6685	6713	6716	java/lang/Throwable
    //   6702	6743	6746	java/lang/Throwable
    //   6720	6754	6754	java/lang/Throwable
    //   6777	6788	6791	java/lang/Throwable
    //   6843	6857	6857	java/lang/Throwable
    //   6868	6881	6884	java/lang/Throwable
    //   6873	6896	6899	java/lang/Throwable
    //   6888	6914	6917	java/lang/Throwable
    //   6903	6944	6947	java/lang/Throwable
    //   7010	7037	7040	java/lang/Throwable
    //   7027	7055	7058	java/lang/Throwable
    //   7044	7085	7088	java/lang/Throwable
    //   7062	7096	7096	java/lang/Throwable
    //   7119	7130	7133	java/lang/Throwable
    //   7145	7879	9345	java/lang/Throwable
    //   7235	7249	7249	java/lang/Throwable
    //   7260	7273	7276	java/lang/Throwable
    //   7265	7288	7291	java/lang/Throwable
    //   7280	7306	7309	java/lang/Throwable
    //   7295	7336	7339	java/lang/Throwable
    //   7402	7429	7432	java/lang/Throwable
    //   7419	7447	7450	java/lang/Throwable
    //   7436	7477	7480	java/lang/Throwable
    //   7454	7488	7488	java/lang/Throwable
    //   7511	7522	7525	java/lang/Throwable
    //   7578	7592	7592	java/lang/Throwable
    //   7603	7616	7619	java/lang/Throwable
    //   7608	7631	7634	java/lang/Throwable
    //   7623	7649	7652	java/lang/Throwable
    //   7638	7679	7682	java/lang/Throwable
    //   7745	7772	7775	java/lang/Throwable
    //   7762	7790	7793	java/lang/Throwable
    //   7779	7820	7823	java/lang/Throwable
    //   7797	7831	7831	java/lang/Throwable
    //   7854	7865	7868	java/lang/Throwable
    //   7880	8614	9345	java/lang/Throwable
    //   7970	7984	7984	java/lang/Throwable
    //   7995	8008	8011	java/lang/Throwable
    //   8000	8023	8026	java/lang/Throwable
    //   8015	8041	8044	java/lang/Throwable
    //   8030	8071	8074	java/lang/Throwable
    //   8137	8164	8167	java/lang/Throwable
    //   8154	8182	8185	java/lang/Throwable
    //   8171	8212	8215	java/lang/Throwable
    //   8189	8223	8223	java/lang/Throwable
    //   8246	8257	8260	java/lang/Throwable
    //   8313	8327	8327	java/lang/Throwable
    //   8338	8351	8354	java/lang/Throwable
    //   8343	8366	8369	java/lang/Throwable
    //   8358	8384	8387	java/lang/Throwable
    //   8373	8414	8417	java/lang/Throwable
    //   8480	8507	8510	java/lang/Throwable
    //   8497	8525	8528	java/lang/Throwable
    //   8514	8555	8558	java/lang/Throwable
    //   8532	8566	8566	java/lang/Throwable
    //   8589	8600	8603	java/lang/Throwable
    //   8615	9344	9345	java/lang/Throwable
    //   8705	8719	8719	java/lang/Throwable
    //   8730	8743	8746	java/lang/Throwable
    //   8735	8758	8761	java/lang/Throwable
    //   8750	8776	8779	java/lang/Throwable
    //   8765	8806	8809	java/lang/Throwable
    //   8872	8899	8902	java/lang/Throwable
    //   8889	8917	8920	java/lang/Throwable
    //   8906	8947	8950	java/lang/Throwable
    //   8924	8958	8958	java/lang/Throwable
    //   8981	8992	8995	java/lang/Throwable
    //   9048	9062	9062	java/lang/Throwable
    //   9073	9086	9089	java/lang/Throwable
    //   9078	9101	9104	java/lang/Throwable
    //   9093	9119	9122	java/lang/Throwable
    //   9108	9149	9152	java/lang/Throwable
    //   9215	9242	9245	java/lang/Throwable
    //   9232	9260	9263	java/lang/Throwable
    //   9249	9290	9293	java/lang/Throwable
    //   9267	9301	9301	java/lang/Throwable
    //   9324	9335	9338	java/lang/Throwable
  }
  
  static void Zg(Object paramObject) {
    Ztbf.Zf = a(11802, 14784);
    Ztbf.Zv = new BigInteger(a(11786, 2380));
    boolean bool = Zt2e.ZN();
    try {
      try {
        if (Zter.ZE.charAt(Math.abs(((BigInteger)Zgmt.ZX).intValue() % 32)) > Zd1.ZN.charAt(Math.abs(((BigInteger)Zb3z.ZR).intValue() % 32))) {
          try {
            Znp.Zx(Class.forName(a(11803, -21076)));
            if (!bool)
              Zod.Zr(Class.forName(a(11799, 14675))); 
          } catch (Throwable throwable) {
            throw a(null);
          } 
          return;
        } 
      } catch (Throwable throwable) {
        throw a(null);
      } 
      Zod.Zr(Class.forName(a(11799, 14675)));
    } catch (Throwable throwable) {}
  }
  
  static {
    // Byte code:
    //   0: bipush #27
    //   2: anewarray java/lang/String
    //   5: astore #5
    //   7: iconst_0
    //   8: istore_3
    //   9: ldc '\\rqU}\\t\\r5 U\\t^el a2%_R*\\tU)l\\t5e\\t\\t2rx9fm=\\t)"`\\tb-DP#\\t2cZ}f8\\tcq5 \\t/f\\t"Vn%"\\t Wg;\\tdIA\\tS[]"KQDc\\r`4(a>\\tY +Q/DTO4)U{\\r/3-Q\\tm} @}f*uZ9x\\f3A.\\tIz\\tUg\\tk< A'
    //   11: dup
    //   12: astore_2
    //   13: invokevirtual length : ()I
    //   16: istore #4
    //   18: bipush #9
    //   20: istore_1
    //   21: iconst_m1
    //   22: istore_0
    //   23: bipush #102
    //   25: iinc #0, 1
    //   28: aload_2
    //   29: iload_0
    //   30: dup
    //   31: iload_1
    //   32: iadd
    //   33: invokevirtual substring : (II)Ljava/lang/String;
    //   36: iconst_m1
    //   37: goto -> 143
    //   40: aload #5
    //   42: swap
    //   43: iload_3
    //   44: iinc #3, 1
    //   47: swap
    //   48: aastore
    //   49: iload_0
    //   50: iload_1
    //   51: iadd
    //   52: dup
    //   53: istore_0
    //   54: iload #4
    //   56: if_icmpge -> 68
    //   59: aload_2
    //   60: iload_0
    //   61: invokevirtual charAt : (I)C
    //   64: istore_1
    //   65: goto -> 23
    //   68: ldc '(_=~\\t(1_='
    //   70: dup
    //   71: astore_2
    //   72: invokevirtual length : ()I
    //   75: istore #4
    //   77: bipush #9
    //   79: istore_1
    //   80: iconst_m1
    //   81: istore_0
    //   82: bipush #48
    //   84: iinc #0, 1
    //   87: aload_2
    //   88: iload_0
    //   89: dup
    //   90: iload_1
    //   91: iadd
    //   92: invokevirtual substring : (II)Ljava/lang/String;
    //   95: iconst_0
    //   96: goto -> 143
    //   99: aload #5
    //   101: swap
    //   102: iload_3
    //   103: iinc #3, 1
    //   106: swap
    //   107: aastore
    //   108: iload_0
    //   109: iload_1
    //   110: iadd
    //   111: dup
    //   112: istore_0
    //   113: iload #4
    //   115: if_icmpge -> 127
    //   118: aload_2
    //   119: iload_0
    //   120: invokevirtual charAt : (I)C
    //   123: istore_1
    //   124: goto -> 82
    //   127: aload #5
    //   129: putstatic burp/Zg7p.a : [Ljava/lang/String;
    //   132: bipush #27
    //   134: anewarray java/lang/String
    //   137: putstatic burp/Zg7p.b : [Ljava/lang/String;
    //   140: goto -> 300
    //   143: dup_x2
    //   144: pop
    //   145: invokevirtual toCharArray : ()[C
    //   148: dup_x1
    //   149: arraylength
    //   150: dup_x2
    //   151: pop
    //   152: iconst_0
    //   153: istore #6
    //   155: dup2_x1
    //   156: pop2
    //   157: dup_x2
    //   158: iconst_1
    //   159: if_icmpgt -> 260
    //   162: dup2
    //   163: swap
    //   164: iload #6
    //   166: dup2_x1
    //   167: caload
    //   168: swap
    //   169: iload #6
    //   171: bipush #7
    //   173: irem
    //   174: tableswitch default -> 242, 0 -> 212, 1 -> 217, 2 -> 222, 3 -> 227, 4 -> 232, 5 -> 237
    //   212: bipush #81
    //   214: goto -> 244
    //   217: bipush #18
    //   219: goto -> 244
    //   222: bipush #12
    //   224: goto -> 244
    //   227: bipush #117
    //   229: goto -> 244
    //   232: bipush #106
    //   234: goto -> 244
    //   237: bipush #22
    //   239: goto -> 244
    //   242: bipush #40
    //   244: ixor
    //   245: ixor
    //   246: i2c
    //   247: castore
    //   248: iinc #6, 1
    //   251: dup
    //   252: ifne -> 260
    //   255: dup2
    //   256: dup_x1
    //   257: goto -> 166
    //   260: dup2_x1
    //   261: pop2
    //   262: dup_x2
    //   263: iload #6
    //   265: if_icmpgt -> 162
    //   268: pop
    //   269: new java/lang/String
    //   272: dup_x1
    //   273: swap
    //   274: invokespecial <init> : ([C)V
    //   277: invokevirtual intern : ()Ljava/lang/String;
    //   280: swap
    //   281: pop
    //   282: swap
    //   283: tableswitch default -> 40, 0 -> 99
    //   300: new java/math/BigInteger
    //   303: dup
    //   304: bipush #32
    //   306: newarray byte
    //   308: dup
    //   309: iconst_0
    //   310: bipush #62
    //   312: bastore
    //   313: dup
    //   314: iconst_1
    //   315: bipush #91
    //   317: bastore
    //   318: dup
    //   319: iconst_2
    //   320: bipush #-85
    //   322: bastore
    //   323: dup
    //   324: iconst_3
    //   325: bipush #-113
    //   327: bastore
    //   328: dup
    //   329: iconst_4
    //   330: bipush #-122
    //   332: bastore
    //   333: dup
    //   334: iconst_5
    //   335: bipush #123
    //   337: bastore
    //   338: dup
    //   339: bipush #6
    //   341: bipush #-11
    //   343: bastore
    //   344: dup
    //   345: bipush #7
    //   347: bipush #-34
    //   349: bastore
    //   350: dup
    //   351: bipush #8
    //   353: bipush #80
    //   355: bastore
    //   356: dup
    //   357: bipush #9
    //   359: bipush #-127
    //   361: bastore
    //   362: dup
    //   363: bipush #10
    //   365: iconst_0
    //   366: bastore
    //   367: dup
    //   368: bipush #11
    //   370: bipush #6
    //   372: bastore
    //   373: dup
    //   374: bipush #12
    //   376: bipush #125
    //   378: bastore
    //   379: dup
    //   380: bipush #13
    //   382: bipush #-57
    //   384: bastore
    //   385: dup
    //   386: bipush #14
    //   388: bipush #79
    //   390: bastore
    //   391: dup
    //   392: bipush #15
    //   394: bipush #-103
    //   396: bastore
    //   397: dup
    //   398: bipush #16
    //   400: bipush #-126
    //   402: bastore
    //   403: dup
    //   404: bipush #17
    //   406: bipush #47
    //   408: bastore
    //   409: dup
    //   410: bipush #18
    //   412: bipush #33
    //   414: bastore
    //   415: dup
    //   416: bipush #19
    //   418: bipush #-108
    //   420: bastore
    //   421: dup
    //   422: bipush #20
    //   424: bipush #-26
    //   426: bastore
    //   427: dup
    //   428: bipush #21
    //   430: bipush #-60
    //   432: bastore
    //   433: dup
    //   434: bipush #22
    //   436: bipush #16
    //   438: bastore
    //   439: dup
    //   440: bipush #23
    //   442: bipush #127
    //   444: bastore
    //   445: dup
    //   446: bipush #24
    //   448: bipush #-27
    //   450: bastore
    //   451: dup
    //   452: bipush #25
    //   454: bipush #-39
    //   456: bastore
    //   457: dup
    //   458: bipush #26
    //   460: bipush #-47
    //   462: bastore
    //   463: dup
    //   464: bipush #27
    //   466: bipush #121
    //   468: bastore
    //   469: dup
    //   470: bipush #28
    //   472: iconst_m1
    //   473: bastore
    //   474: dup
    //   475: bipush #29
    //   477: bipush #77
    //   479: bastore
    //   480: dup
    //   481: bipush #30
    //   483: bipush #68
    //   485: bastore
    //   486: dup
    //   487: bipush #31
    //   489: bipush #-27
    //   491: bastore
    //   492: invokespecial <init> : ([B)V
    //   495: putstatic burp/Zg7p.Zb : Ljava/lang/Object;
    //   498: sipush #11788
    //   501: sipush #18983
    //   504: invokestatic a : (II)Ljava/lang/String;
    //   507: putstatic burp/Zg7p.ZA : Ljava/lang/String;
    //   510: return
  }
  
  private static Throwable a(Throwable paramThrowable) {
    return paramThrowable;
  }
  
  private static String a(int paramInt1, int paramInt2) {
    int i = (paramInt1 ^ 0x2E19) & 0xFFFF;
    if (b[i] == null) {
      char[] arrayOfChar = a[i].toCharArray();
      switch (arrayOfChar[0] & 0xFF) {
        case 0:
        
        case 1:
        
        case 2:
        
        case 3:
        
        case 4:
        
        case 5:
        
        case 6:
        
        case 7:
        
        case 8:
        
        case 9:
        
        case 10:
        
        case 11:
        
        case 12:
        
        case 13:
        
        case 14:
        
        case 15:
        
        case 16:
        
        case 17:
        
        case 18:
        
        case 19:
        
        case 20:
        
        case 21:
        
        case 22:
        
        case 23:
        
        case 24:
        
        case 25:
        
        case 26:
        
        case 27:
        
        case 28:
        
        case 29:
        
        case 30:
        
        case 31:
        
        case 32:
        
        case 33:
        
        case 34:
        
        case 35:
        
        case 36:
        
        case 37:
        
        case 38:
        
        case 39:
        
        case 40:
        
        case 41:
        
        case 42:
        
        case 43:
        
        case 44:
        
        case 45:
        
        case 46:
        
        case 47:
        
        case 48:
        
        case 49:
        
        case 50:
        
        case 51:
        
        case 52:
        
        case 53:
        
        case 54:
        
        case 55:
        
        case 56:
        
        case 57:
        
        case 58:
        
        case 59:
        
        case 60:
        
        case 61:
        
        case 62:
        
        case 63:
        
        case 64:
        
        case 65:
        
        case 66:
        
        case 67:
        
        case 68:
        
        case 69:
        
        case 70:
        
        case 71:
        
        case 72:
        
        case 73:
        
        case 74:
        
        case 75:
        
        case 76:
        
        case 77:
        
        case 78:
        
        case 79:
        
        case 80:
        
        case 81:
        
        case 82:
        
        case 83:
        
        case 84:
        
        case 85:
        
        case 86:
        
        case 87:
        
        case 88:
        
        case 89:
        
        case 90:
        
        case 91:
        
        case 92:
        
        case 93:
        
        case 94:
        
        case 95:
        
        case 96:
        
        case 97:
        
        case 98:
        
        case 99:
        
        case 100:
        
        case 101:
        
        case 102:
        
        case 103:
        
        case 104:
        
        case 105:
        
        case 106:
        
        case 107:
        
        case 108:
        
        case 109:
        
        case 110:
        
        case 111:
        
        case 112:
        
        case 113:
        
        case 114:
        
        case 115:
        
        case 116:
        
        case 117:
        
        case 118:
        
        case 119:
        
        case 120:
        
        case 121:
        
        case 122:
        
        case 123:
        
        case 124:
        
        case 125:
        
        case 126:
        
        case 127:
        
        case 128:
        
        case 129:
        
        case 130:
        
        case 131:
        
        case 132:
        
        case 133:
        
        case 134:
        
        case 135:
        
        case 136:
        
        case 137:
        
        case 138:
        
        case 139:
        
        case 140:
        
        case 141:
        
        case 142:
        
        case 143:
        
        case 144:
        
        case 145:
        
        case 146:
        
        case 147:
        
        case 148:
        
        case 149:
        
        case 150:
        
        case 151:
        
        case 152:
        
        case 153:
        
        case 154:
        
        case 155:
        
        case 156:
        
        case 157:
        
        case 158:
        
        case 159:
        
        case 160:
        
        case 161:
        
        case 162:
        
        case 163:
        
        case 164:
        
        case 165:
        
        case 166:
        
        case 167:
        
        case 168:
        
        case 169:
        
        case 170:
        
        case 171:
        
        case 172:
        
        case 173:
        
        case 174:
        
        case 175:
        
        case 176:
        
        case 177:
        
        case 178:
        
        case 179:
        
        case 180:
        
        case 181:
        
        case 182:
        
        case 183:
        
        case 184:
        
        case 185:
        
        case 186:
        
        case 187:
        
        case 188:
        
        case 189:
        
        case 190:
        
        case 191:
        
        case 192:
        
        case 193:
        
        case 194:
        
        case 195:
        
        case 196:
        
        case 197:
        
        case 198:
        
        case 199:
        
        case 200:
        
        case 201:
        
        case 202:
        
        case 203:
        
        case 204:
        
        case 205:
        
        case 206:
        
        case 207:
        
        case 208:
        
        case 209:
        
        case 210:
        
        case 211:
        
        case 212:
        
        case 213:
        
        case 214:
        
        case 215:
        
        case 216:
        
        case 217:
        
        case 218:
        
        case 219:
        
        case 220:
        
        case 221:
        
        case 222:
        
        case 223:
        
        case 224:
        
        case 225:
        
        case 226:
        
        case 227:
        
        case 228:
        
        case 229:
        
        case 230:
        
        case 231:
        
        case 232:
        
        case 233:
        
        case 234:
        
        case 235:
        
        case 236:
        
        case 237:
        
        case 238:
        
        case 239:
        
        case 240:
        
        case 241:
        
        case 242:
        
        case 243:
        
        case 244:
        
        case 245:
        
        case 246:
        
        case 247:
        
        case 248:
        
        case 249:
        
        case 250:
        
        case 251:
        
        case 252:
        
        case 253:
        
        case 254:
        
        default:
          break;
      } 
      byte b1 = 0;
      int j = (paramInt2 & 0xFF) - b1;
      if (j < 0)
        j += 256; 
      int k = ((paramInt2 & 0xFFFF) >>> 8) - b1;
      if (k < 0)
        k += 256; 
      for (byte b2 = 0; b2 < arrayOfChar.length; b2++) {
        int m = b2 % 2;
        if (m == 0) {
          arrayOfChar[b2] = (char)(arrayOfChar[b2] ^ j);
          j = ((j >>> 3 | j << 5) ^ arrayOfChar[b2]) & 0xFF;
        } else {
          arrayOfChar[b2] = (char)(arrayOfChar[b2] ^ k);
          k = ((k >>> 3 | k << 5) ^ arrayOfChar[b2]) & 0xFF;
        } 
      } 
      b[i] = (new String(arrayOfChar)).intern();
    } 
    return b[i];
  }
}


/* Location:              C:\Program Files\BurpSuitePro\burpsuite_pro.jar!\burp\Zg7p.class
 * Java compiler version: 21 (65.0)
 * JD-Core Version:       1.1.3
 */