package burp;

import java.math.BigInteger;

class Zg7u extends ClassLoader {
  static String ZA;
  
  static Object Zh;
  
  private static final String[] a;
  
  private static final String[] b;
  
  static boolean Zp(Object[] paramArrayOfObject, Object paramObject) throws Throwable {
    // Byte code:
    //   0: invokestatic ZK : ()Z
    //   3: istore_2
    //   4: ldc2_w 8682522807148012
    //   7: invokestatic currentTimeMillis : ()J
    //   10: lxor
    //   11: lstore #4
    //   13: lload #4
    //   15: ldc2_w 25214903917
    //   18: lmul
    //   19: ldc2_w 11
    //   22: ladd
    //   23: ldc2_w 281474976710655
    //   26: land
    //   27: lstore #4
    //   29: lload #4
    //   31: bipush #32
    //   33: lshl
    //   34: lstore #6
    //   36: lload #4
    //   38: ldc2_w 25214903917
    //   41: lmul
    //   42: ldc2_w 11
    //   45: ladd
    //   46: ldc2_w 281474976710655
    //   49: land
    //   50: lstore #4
    //   52: lload #6
    //   54: lload #4
    //   56: ladd
    //   57: lstore #6
    //   59: bipush #16
    //   61: newarray byte
    //   63: dup
    //   64: iconst_0
    //   65: bipush #48
    //   67: bastore
    //   68: dup
    //   69: iconst_1
    //   70: bipush #49
    //   72: bastore
    //   73: dup
    //   74: iconst_2
    //   75: bipush #50
    //   77: bastore
    //   78: dup
    //   79: iconst_3
    //   80: bipush #51
    //   82: bastore
    //   83: dup
    //   84: iconst_4
    //   85: bipush #52
    //   87: bastore
    //   88: dup
    //   89: iconst_5
    //   90: bipush #53
    //   92: bastore
    //   93: dup
    //   94: bipush #6
    //   96: bipush #54
    //   98: bastore
    //   99: dup
    //   100: bipush #7
    //   102: bipush #55
    //   104: bastore
    //   105: dup
    //   106: bipush #8
    //   108: bipush #56
    //   110: bastore
    //   111: dup
    //   112: bipush #9
    //   114: bipush #57
    //   116: bastore
    //   117: dup
    //   118: bipush #10
    //   120: bipush #97
    //   122: bastore
    //   123: dup
    //   124: bipush #11
    //   126: bipush #98
    //   128: bastore
    //   129: dup
    //   130: bipush #12
    //   132: bipush #99
    //   134: bastore
    //   135: dup
    //   136: bipush #13
    //   138: bipush #100
    //   140: bastore
    //   141: dup
    //   142: bipush #14
    //   144: bipush #101
    //   146: bastore
    //   147: dup
    //   148: bipush #15
    //   150: bipush #102
    //   152: bastore
    //   153: astore #8
    //   155: bipush #64
    //   157: newarray byte
    //   159: astore #9
    //   161: bipush #64
    //   163: istore #10
    //   165: bipush #16
    //   167: istore #11
    //   169: iload #11
    //   171: iconst_1
    //   172: isub
    //   173: i2l
    //   174: lstore #12
    //   176: aload #9
    //   178: iinc #10, -1
    //   181: iload #10
    //   183: aload #8
    //   185: lload #6
    //   187: lload #12
    //   189: land
    //   190: l2i
    //   191: baload
    //   192: bastore
    //   193: lload #6
    //   195: iconst_4
    //   196: lushr
    //   197: lstore #6
    //   199: lload #6
    //   201: lconst_0
    //   202: lcmp
    //   203: ifne -> 176
    //   206: bipush #64
    //   208: iload #10
    //   210: isub
    //   211: newarray byte
    //   213: astore_3
    //   214: iconst_0
    //   215: istore #14
    //   217: iload #14
    //   219: aload_3
    //   220: arraylength
    //   221: if_icmpge -> 243
    //   224: aload_3
    //   225: iload #14
    //   227: aload #9
    //   229: iload #10
    //   231: iload #14
    //   233: iadd
    //   234: baload
    //   235: bastore
    //   236: iinc #14, 1
    //   239: iload_2
    //   240: ifeq -> 217
    //   243: aload_3
    //   244: arraylength
    //   245: bipush #10
    //   247: if_icmplt -> 13
    //   250: getstatic burp/Zgeq.ZT : Ljava/lang/Object;
    //   253: checkcast java/math/BigInteger
    //   256: getstatic burp/Zzhx.ZB : Ljava/lang/Object;
    //   259: checkcast java/math/BigInteger
    //   262: invokevirtual subtract : (Ljava/math/BigInteger;)Ljava/math/BigInteger;
    //   265: putstatic burp/Ztnn.ZA : Ljava/lang/Object;
    //   268: sipush #-24052
    //   271: sipush #-14300
    //   274: invokestatic a : (II)Ljava/lang/String;
    //   277: iconst_1
    //   278: ldc burp/Zmj8
    //   280: invokevirtual getClassLoader : ()Ljava/lang/ClassLoader;
    //   283: invokestatic forName : (Ljava/lang/String;ZLjava/lang/ClassLoader;)Ljava/lang/Class;
    //   286: invokevirtual getDeclaredFields : ()[Ljava/lang/reflect/Field;
    //   289: astore_3
    //   290: aload_3
    //   291: arraylength
    //   292: istore #4
    //   294: iconst_0
    //   295: istore #5
    //   297: iload #5
    //   299: iload #4
    //   301: if_icmpge -> 438
    //   304: aload_3
    //   305: iload #5
    //   307: aaload
    //   308: astore #6
    //   310: aload #6
    //   312: invokevirtual getModifiers : ()I
    //   315: invokestatic isStatic : (I)Z
    //   318: ifne -> 328
    //   321: goto -> 431
    //   324: invokestatic a : (Ljava/lang/Throwable;)Ljava/lang/Throwable;
    //   327: athrow
    //   328: aload #6
    //   330: invokevirtual getType : ()Ljava/lang/Class;
    //   333: astore #7
    //   335: aload #7
    //   337: ifnull -> 418
    //   340: aload #7
    //   342: invokevirtual isPrimitive : ()Z
    //   345: ifne -> 418
    //   348: goto -> 355
    //   351: invokestatic a : (Ljava/lang/Throwable;)Ljava/lang/Throwable;
    //   354: athrow
    //   355: aload #7
    //   357: invokevirtual getPackage : ()Ljava/lang/Package;
    //   360: ifnull -> 418
    //   363: goto -> 370
    //   366: invokestatic a : (Ljava/lang/Throwable;)Ljava/lang/Throwable;
    //   369: athrow
    //   370: aload #7
    //   372: invokevirtual getPackage : ()Ljava/lang/Package;
    //   375: invokevirtual getName : ()Ljava/lang/String;
    //   378: ifnull -> 418
    //   381: goto -> 388
    //   384: invokestatic a : (Ljava/lang/Throwable;)Ljava/lang/Throwable;
    //   387: athrow
    //   388: aload #7
    //   390: invokevirtual getPackage : ()Ljava/lang/Package;
    //   393: invokevirtual getName : ()Ljava/lang/String;
    //   396: sipush #-24055
    //   399: sipush #26087
    //   402: invokestatic a : (II)Ljava/lang/String;
    //   405: invokevirtual startsWith : (Ljava/lang/String;)Z
    //   408: ifne -> 418
    //   411: goto -> 418
    //   414: invokestatic a : (Ljava/lang/Throwable;)Ljava/lang/Throwable;
    //   417: athrow
    //   418: aload #6
    //   420: iconst_1
    //   421: invokevirtual setAccessible : (Z)V
    //   424: aload #6
    //   426: aconst_null
    //   427: invokevirtual get : (Ljava/lang/Object;)Ljava/lang/Object;
    //   430: pop
    //   431: iinc #5, 1
    //   434: iload_2
    //   435: ifeq -> 297
    //   438: sipush #-24053
    //   441: sipush #-6738
    //   444: invokestatic a : (II)Ljava/lang/String;
    //   447: invokestatic forName : (Ljava/lang/String;)Ljava/lang/Class;
    //   450: invokevirtual getDeclaredMethods : ()[Ljava/lang/reflect/Method;
    //   453: astore_3
    //   454: aload_3
    //   455: arraylength
    //   456: istore #4
    //   458: iconst_0
    //   459: istore #5
    //   461: iload #5
    //   463: iload #4
    //   465: if_icmpge -> 597
    //   468: aload_3
    //   469: iload #5
    //   471: aaload
    //   472: astore #6
    //   474: aload #6
    //   476: invokevirtual getParameterTypes : ()[Ljava/lang/Class;
    //   479: pop
    //   480: aload #6
    //   482: invokevirtual getModifiers : ()I
    //   485: invokestatic isStatic : (I)Z
    //   488: ifeq -> 583
    //   491: aload #6
    //   493: invokevirtual getParameterTypes : ()[Ljava/lang/Class;
    //   496: arraylength
    //   497: iconst_2
    //   498: if_icmpne -> 583
    //   501: goto -> 508
    //   504: invokestatic a : (Ljava/lang/Throwable;)Ljava/lang/Throwable;
    //   507: athrow
    //   508: aload #6
    //   510: invokevirtual getReturnType : ()Ljava/lang/Class;
    //   513: getstatic java/lang/Void.TYPE : Ljava/lang/Class;
    //   516: invokevirtual equals : (Ljava/lang/Object;)Z
    //   519: ifeq -> 583
    //   522: goto -> 529
    //   525: invokestatic a : (Ljava/lang/Throwable;)Ljava/lang/Throwable;
    //   528: athrow
    //   529: aload #6
    //   531: iconst_1
    //   532: invokevirtual setAccessible : (Z)V
    //   535: aload #6
    //   537: aconst_null
    //   538: iconst_2
    //   539: anewarray java/lang/Object
    //   542: dup
    //   543: iconst_0
    //   544: aload_0
    //   545: aastore
    //   546: dup
    //   547: iconst_1
    //   548: aload_1
    //   549: ifnonnull -> 567
    //   552: goto -> 559
    //   555: invokestatic a : (Ljava/lang/Throwable;)Ljava/lang/Throwable;
    //   558: athrow
    //   559: aload_1
    //   560: goto -> 574
    //   563: invokestatic a : (Ljava/lang/Throwable;)Ljava/lang/Throwable;
    //   566: athrow
    //   567: aload_1
    //   568: checkcast [B
    //   571: invokevirtual clone : ()Ljava/lang/Object;
    //   574: aastore
    //   575: invokevirtual invoke : (Ljava/lang/Object;[Ljava/lang/Object;)Ljava/lang/Object;
    //   578: pop
    //   579: iload_2
    //   580: ifeq -> 597
    //   583: iinc #5, 1
    //   586: iload_2
    //   587: ifeq -> 461
    //   590: goto -> 597
    //   593: invokestatic a : (Ljava/lang/Throwable;)Ljava/lang/Throwable;
    //   596: athrow
    //   597: getstatic burp/Ztq8.ZI : Ljava/lang/String;
    //   600: getstatic burp/Ztwp.Ze : Ljava/lang/Object;
    //   603: checkcast java/math/BigInteger
    //   606: invokevirtual intValue : ()I
    //   609: bipush #32
    //   611: irem
    //   612: invokestatic abs : (I)I
    //   615: invokevirtual charAt : (I)C
    //   618: getstatic burp/Zetf.Zo : Ljava/lang/String;
    //   621: getstatic burp/Zkkl.ZE : Ljava/lang/Object;
    //   624: checkcast java/math/BigInteger
    //   627: invokevirtual intValue : ()I
    //   630: bipush #32
    //   632: irem
    //   633: invokestatic abs : (I)I
    //   636: invokevirtual charAt : (I)C
    //   639: if_icmpgt -> 746
    //   642: getstatic burp/Zly9.ZS : Ljava/lang/String;
    //   645: getstatic burp/Zr9u.ZX : Ljava/lang/Object;
    //   648: checkcast java/math/BigInteger
    //   651: invokevirtual intValue : ()I
    //   654: bipush #32
    //   656: irem
    //   657: invokestatic abs : (I)I
    //   660: invokevirtual charAt : (I)C
    //   663: getstatic burp/Zr9u.Zc : Ljava/lang/String;
    //   666: getstatic burp/Ztwp.Ze : Ljava/lang/Object;
    //   669: checkcast java/math/BigInteger
    //   672: invokevirtual intValue : ()I
    //   675: bipush #32
    //   677: irem
    //   678: invokestatic abs : (I)I
    //   681: invokevirtual charAt : (I)C
    //   684: if_icmple -> 746
    //   687: goto -> 694
    //   690: invokestatic a : (Ljava/lang/Throwable;)Ljava/lang/Throwable;
    //   693: athrow
    //   694: getstatic burp/Zrw0.Zj : Ljava/lang/String;
    //   697: getstatic burp/Zmt_.Zl : Ljava/lang/Object;
    //   700: checkcast java/math/BigInteger
    //   703: invokevirtual intValue : ()I
    //   706: bipush #32
    //   708: irem
    //   709: invokestatic abs : (I)I
    //   712: invokevirtual charAt : (I)C
    //   715: getstatic burp/Zlgh.Zm : Ljava/lang/String;
    //   718: getstatic burp/Zg4l.ZI : Ljava/lang/Object;
    //   721: checkcast java/math/BigInteger
    //   724: invokevirtual intValue : ()I
    //   727: bipush #32
    //   729: irem
    //   730: invokestatic abs : (I)I
    //   733: invokevirtual charAt : (I)C
    //   736: if_icmpgt -> 754
    //   739: goto -> 746
    //   742: invokestatic a : (Ljava/lang/Throwable;)Ljava/lang/Throwable;
    //   745: athrow
    //   746: iconst_1
    //   747: goto -> 755
    //   750: invokestatic a : (Ljava/lang/Throwable;)Ljava/lang/Throwable;
    //   753: athrow
    //   754: iconst_0
    //   755: ireturn
    //   756: astore_3
    //   757: new java/lang/Exception
    //   760: dup
    //   761: aload_3
    //   762: invokevirtual getMessage : ()Ljava/lang/String;
    //   765: invokespecial <init> : (Ljava/lang/String;)V
    //   768: athrow
    // Exception table:
    //   from	to	target	type
    //   4	755	756	java/lang/Throwable
    //   310	324	324	java/lang/Throwable
    //   335	348	351	java/lang/Throwable
    //   340	363	366	java/lang/Throwable
    //   355	381	384	java/lang/Throwable
    //   370	411	414	java/lang/Throwable
    //   474	501	504	java/lang/Throwable
    //   491	522	525	java/lang/Throwable
    //   508	552	555	java/lang/Throwable
    //   529	563	563	java/lang/Throwable
    //   574	590	593	java/lang/Throwable
    //   597	687	690	java/lang/Throwable
    //   642	739	742	java/lang/Throwable
    //   694	750	750	java/lang/Throwable
  }
  
  static void ZU(Object paramObject) {
    Zrl5.ZG = a(-24056, 13329);
    Zrl5.ZI = new BigInteger(a(-24050, 11849));
    boolean bool = Zt2e.ZK();
    try {
      try {
        if (Zgei.Zl.charAt(Math.abs(((BigInteger)Zb3l.Zl).intValue() % 32)) > Zzl4.ZT.charAt(Math.abs(((BigInteger)Zbw5.ZR).intValue() % 32))) {
          try {
            Zlum.Zk(Class.forName(a(-24049, -19083)));
            if (bool)
              Zlg2.Zx(Class.forName(a(-24054, -17958))); 
          } catch (Throwable throwable) {
            throw a(null);
          } 
          return;
        } 
      } catch (Throwable throwable) {
        throw a(null);
      } 
      Zlg2.Zx(Class.forName(a(-24054, -17958)));
    } catch (Throwable throwable) {}
  }
  
  static void ZF(Object[] paramArrayOfObject, Object paramObject) throws Throwable {}
  
  static {
    // Byte code:
    //   0: bipush #8
    //   2: anewarray java/lang/String
    //   5: astore #5
    //   7: iconst_0
    //   8: istore_3
    //   9: ldc 'EÂ®Ã†9Ã¶GÃ„ÃŸÂªnÂ¼0Ã•Â‡Â´qÂ¸71Ã©ÂµÂÃ’ÃcÂ“[(Ã+^Â˜\\tÂ¦ÃNPÂ–^Âœ\\tÃ—Ã©Â¾Ã€MÃ³Ã©;ÂŒ\\t/Â„\\nÃ¨XÂ‘ @Â³Ã\Ã„bÃ\\bÂ‹Â•|Ã«ÂŸÃŠqÃ¹Â¼Ã©Â¶Ã­Ã§WÃ«'ÃÂ¾Â¾Â­Ã§Ãˆ'
    //   11: dup
    //   12: astore_2
    //   13: invokevirtual length : ()I
    //   16: istore #4
    //   18: bipush #32
    //   20: istore_1
    //   21: iconst_m1
    //   22: istore_0
    //   23: bipush #117
    //   25: iinc #0, 1
    //   28: aload_2
    //   29: iload_0
    //   30: dup
    //   31: iload_1
    //   32: iadd
    //   33: invokevirtual substring : (II)Ljava/lang/String;
    //   36: iconst_m1
    //   37: goto -> 143
    //   40: aload #5
    //   42: swap
    //   43: iload_3
    //   44: iinc #3, 1
    //   47: swap
    //   48: aastore
    //   49: iload_0
    //   50: iload_1
    //   51: iadd
    //   52: dup
    //   53: istore_0
    //   54: iload #4
    //   56: if_icmpge -> 68
    //   59: aload_2
    //   60: iload_0
    //   61: invokevirtual charAt : (I)C
    //   64: istore_1
    //   65: goto -> 23
    //   68: ldc 'amÂ¯TÂ¯:Â”Â€RÃ¸{ÃŠZWÂ«Â‰XÃÂ¶ÃªÂ¶Â»2ÂšÃ•&ioÃ©Â‹Â¼"\\tQ.Ã¢Â‡]ÂžÃ9$ÂŠÃ¢7Ã¶Ã¤Â”k8ÂºgiÂ“{eÂ‚*Â¿Ãˆ\\f AÃ…ÃŠÂ—\\rP\\tÃ Ã•%:CÃ‘PY}'
    //   70: dup
    //   71: astore_2
    //   72: invokevirtual length : ()I
    //   75: istore #4
    //   77: bipush #77
    //   79: istore_1
    //   80: iconst_m1
    //   81: istore_0
    //   82: bipush #79
    //   84: iinc #0, 1
    //   87: aload_2
    //   88: iload_0
    //   89: dup
    //   90: iload_1
    //   91: iadd
    //   92: invokevirtual substring : (II)Ljava/lang/String;
    //   95: iconst_0
    //   96: goto -> 143
    //   99: aload #5
    //   101: swap
    //   102: iload_3
    //   103: iinc #3, 1
    //   106: swap
    //   107: aastore
    //   108: iload_0
    //   109: iload_1
    //   110: iadd
    //   111: dup
    //   112: istore_0
    //   113: iload #4
    //   115: if_icmpge -> 127
    //   118: aload_2
    //   119: iload_0
    //   120: invokevirtual charAt : (I)C
    //   123: istore_1
    //   124: goto -> 82
    //   127: aload #5
    //   129: putstatic burp/Zg7u.a : [Ljava/lang/String;
    //   132: bipush #8
    //   134: anewarray java/lang/String
    //   137: putstatic burp/Zg7u.b : [Ljava/lang/String;
    //   140: goto -> 300
    //   143: dup_x2
    //   144: pop
    //   145: invokevirtual toCharArray : ()[C
    //   148: dup_x1
    //   149: arraylength
    //   150: dup_x2
    //   151: pop
    //   152: iconst_0
    //   153: istore #6
    //   155: dup2_x1
    //   156: pop2
    //   157: dup_x2
    //   158: iconst_1
    //   159: if_icmpgt -> 260
    //   162: dup2
    //   163: swap
    //   164: iload #6
    //   166: dup2_x1
    //   167: caload
    //   168: swap
    //   169: iload #6
    //   171: bipush #7
    //   173: irem
    //   174: tableswitch default -> 242, 0 -> 212, 1 -> 217, 2 -> 222, 3 -> 227, 4 -> 232, 5 -> 237
    //   212: bipush #78
    //   214: goto -> 244
    //   217: bipush #44
    //   219: goto -> 244
    //   222: bipush #10
    //   224: goto -> 244
    //   227: bipush #8
    //   229: goto -> 244
    //   232: bipush #18
    //   234: goto -> 244
    //   237: bipush #21
    //   239: goto -> 244
    //   242: bipush #85
    //   244: ixor
    //   245: ixor
    //   246: i2c
    //   247: castore
    //   248: iinc #6, 1
    //   251: dup
    //   252: ifne -> 260
    //   255: dup2
    //   256: dup_x1
    //   257: goto -> 166
    //   260: dup2_x1
    //   261: pop2
    //   262: dup_x2
    //   263: iload #6
    //   265: if_icmpgt -> 162
    //   268: pop
    //   269: new java/lang/String
    //   272: dup_x1
    //   273: swap
    //   274: invokespecial <init> : ([C)V
    //   277: invokevirtual intern : ()Ljava/lang/String;
    //   280: swap
    //   281: pop
    //   282: swap
    //   283: tableswitch default -> 40, 0 -> 99
    //   300: sipush #-24051
    //   303: sipush #-3450
    //   306: invokestatic a : (II)Ljava/lang/String;
    //   309: putstatic burp/Zg7u.ZA : Ljava/lang/String;
    //   312: new java/math/BigInteger
    //   315: dup
    //   316: iconst_1
    //   317: bipush #32
    //   319: newarray byte
    //   321: dup
    //   322: iconst_0
    //   323: bipush #39
    //   325: bastore
    //   326: dup
    //   327: iconst_1
    //   328: iconst_5
    //   329: bastore
    //   330: dup
    //   331: iconst_2
    //   332: bipush #107
    //   334: bastore
    //   335: dup
    //   336: iconst_3
    //   337: bipush #-98
    //   339: bastore
    //   340: dup
    //   341: iconst_4
    //   342: bipush #24
    //   344: bastore
    //   345: dup
    //   346: iconst_5
    //   347: bipush #-96
    //   349: bastore
    //   350: dup
    //   351: bipush #6
    //   353: bipush #28
    //   355: bastore
    //   356: dup
    //   357: bipush #7
    //   359: bipush #113
    //   361: bastore
    //   362: dup
    //   363: bipush #8
    //   365: bipush #80
    //   367: bastore
    //   368: dup
    //   369: bipush #9
    //   371: bipush #-109
    //   373: bastore
    //   374: dup
    //   375: bipush #10
    //   377: bipush #14
    //   379: bastore
    //   380: dup
    //   381: bipush #11
    //   383: bipush #116
    //   385: bastore
    //   386: dup
    //   387: bipush #12
    //   389: bipush #34
    //   391: bastore
    //   392: dup
    //   393: bipush #13
    //   395: bipush #43
    //   397: bastore
    //   398: dup
    //   399: bipush #14
    //   401: bipush #-65
    //   403: bastore
    //   404: dup
    //   405: bipush #15
    //   407: bipush #66
    //   409: bastore
    //   410: dup
    //   411: bipush #16
    //   413: bipush #-39
    //   415: bastore
    //   416: dup
    //   417: bipush #17
    //   419: bipush #45
    //   421: bastore
    //   422: dup
    //   423: bipush #18
    //   425: bipush #-113
    //   427: bastore
    //   428: dup
    //   429: bipush #19
    //   431: bipush #-15
    //   433: bastore
    //   434: dup
    //   435: bipush #20
    //   437: bipush #8
    //   439: bastore
    //   440: dup
    //   441: bipush #21
    //   443: bipush #31
    //   445: bastore
    //   446: dup
    //   447: bipush #22
    //   449: bipush #-56
    //   451: bastore
    //   452: dup
    //   453: bipush #23
    //   455: bipush #-105
    //   457: bastore
    //   458: dup
    //   459: bipush #24
    //   461: bipush #30
    //   463: bastore
    //   464: dup
    //   465: bipush #25
    //   467: bipush #-16
    //   469: bastore
    //   470: dup
    //   471: bipush #26
    //   473: bipush #-2
    //   475: bastore
    //   476: dup
    //   477: bipush #27
    //   479: bipush #-60
    //   481: bastore
    //   482: dup
    //   483: bipush #28
    //   485: bipush #-93
    //   487: bastore
    //   488: dup
    //   489: bipush #29
    //   491: bipush #27
    //   493: bastore
    //   494: dup
    //   495: bipush #30
    //   497: bipush #-100
    //   499: bastore
    //   500: dup
    //   501: bipush #31
    //   503: bipush #-15
    //   505: bastore
    //   506: invokespecial <init> : (I[B)V
    //   509: putstatic burp/Zg7u.Zh : Ljava/lang/Object;
    //   512: return
  }
  
  private static Throwable a(Throwable paramThrowable) {
    return paramThrowable;
  }
  
  private static String a(int paramInt1, int paramInt2) {
    int i = (paramInt1 ^ 0xFFFFA208) & 0xFFFF;
    if (b[i] == null) {
      char[] arrayOfChar = a[i].toCharArray();
      switch (arrayOfChar[0] & 0xFF) {
        case 0:
        
        case 1:
        
        case 2:
        
        case 3:
        
        case 4:
        
        case 5:
        
        case 6:
        
        case 7:
        
        case 8:
        
        case 9:
        
        case 10:
        
        case 11:
        
        case 12:
        
        case 13:
        
        case 14:
        
        case 15:
        
        case 16:
        
        case 17:
        
        case 18:
        
        case 19:
        
        case 20:
        
        case 21:
        
        case 22:
        
        case 23:
        
        case 24:
        
        case 25:
        
        case 26:
        
        case 27:
        
        case 28:
        
        case 29:
        
        case 30:
        
        case 31:
        
        case 32:
        
        case 33:
        
        case 34:
        
        case 35:
        
        case 36:
        
        case 37:
        
        case 38:
        
        case 39:
        
        case 40:
        
        case 41:
        
        case 42:
        
        case 43:
        
        case 44:
        
        case 45:
        
        case 46:
        
        case 47:
        
        case 48:
        
        case 49:
        
        case 50:
        
        case 51:
        
        case 52:
        
        case 53:
        
        case 54:
        
        case 55:
        
        case 56:
        
        case 57:
        
        case 58:
        
        case 59:
        
        case 60:
        
        case 61:
        
        case 62:
        
        case 63:
        
        case 64:
        
        case 65:
        
        case 66:
        
        case 67:
        
        case 68:
        
        case 69:
        
        case 70:
        
        case 71:
        
        case 72:
        
        case 73:
        
        case 74:
        
        case 75:
        
        case 76:
        
        case 77:
        
        case 78:
        
        case 79:
        
        case 80:
        
        case 81:
        
        case 82:
        
        case 83:
        
        case 84:
        
        case 85:
        
        case 86:
        
        case 87:
        
        case 88:
        
        case 89:
        
        case 90:
        
        case 91:
        
        case 92:
        
        case 93:
        
        case 94:
        
        case 95:
        
        case 96:
        
        case 97:
        
        case 98:
        
        case 99:
        
        case 100:
        
        case 101:
        
        case 102:
        
        case 103:
        
        case 104:
        
        case 105:
        
        case 106:
        
        case 107:
        
        case 108:
        
        case 109:
        
        case 110:
        
        case 111:
        
        case 112:
        
        case 113:
        
        case 114:
        
        case 115:
        
        case 116:
        
        case 117:
        
        case 118:
        
        case 119:
        
        case 120:
        
        case 121:
        
        case 122:
        
        case 123:
        
        case 124:
        
        case 125:
        
        case 126:
        
        case 127:
        
        case 128:
        
        case 129:
        
        case 130:
        
        case 131:
        
        case 132:
        
        case 133:
        
        case 134:
        
        case 135:
        
        case 136:
        
        case 137:
        
        case 138:
        
        case 139:
        
        case 140:
        
        case 141:
        
        case 142:
        
        case 143:
        
        case 144:
        
        case 145:
        
        case 146:
        
        case 147:
        
        case 148:
        
        case 149:
        
        case 150:
        
        case 151:
        
        case 152:
        
        case 153:
        
        case 154:
        
        case 155:
        
        case 156:
        
        case 157:
        
        case 158:
        
        case 159:
        
        case 160:
        
        case 161:
        
        case 162:
        
        case 163:
        
        case 164:
        
        case 165:
        
        case 166:
        
        case 167:
        
        case 168:
        
        case 169:
        
        case 170:
        
        case 171:
        
        case 172:
        
        case 173:
        
        case 174:
        
        case 175:
        
        case 176:
        
        case 177:
        
        case 178:
        
        case 179:
        
        case 180:
        
        case 181:
        
        case 182:
        
        case 183:
        
        case 184:
        
        case 185:
        
        case 186:
        
        case 187:
        
        case 188:
        
        case 189:
        
        case 190:
        
        case 191:
        
        case 192:
        
        case 193:
        
        case 194:
        
        case 195:
        
        case 196:
        
        case 197:
        
        case 198:
        
        case 199:
        
        case 200:
        
        case 201:
        
        case 202:
        
        case 203:
        
        case 204:
        
        case 205:
        
        case 206:
        
        case 207:
        
        case 208:
        
        case 209:
        
        case 210:
        
        case 211:
        
        case 212:
        
        case 213:
        
        case 214:
        
        case 215:
        
        case 216:
        
        case 217:
        
        case 218:
        
        case 219:
        
        case 220:
        
        case 221:
        
        case 222:
        
        case 223:
        
        case 224:
        
        case 225:
        
        case 226:
        
        case 227:
        
        case 228:
        
        case 229:
        
        case 230:
        
        case 231:
        
        case 232:
        
        case 233:
        
        case 234:
        
        case 235:
        
        case 236:
        
        case 237:
        
        case 238:
        
        case 239:
        
        case 240:
        
        case 241:
        
        case 242:
        
        case 243:
        
        case 244:
        
        case 245:
        
        case 246:
        
        case 247:
        
        case 248:
        
        case 249:
        
        case 250:
        
        case 251:
        
        case 252:
        
        case 253:
        
        case 254:
        
        default:
          break;
      } 
      char c = 'Â‘';
      int j = (paramInt2 & 0xFF) - c;
      if (j < 0)
        j += 256; 
      int k = ((paramInt2 & 0xFFFF) >>> 8) - c;
      if (k < 0)
        k += 256; 
      for (byte b = 0; b < arrayOfChar.length; b++) {
        int m = b % 2;
        if (m == 0) {
          arrayOfChar[b] = (char)(arrayOfChar[b] ^ j);
          j = ((j >>> 3 | j << 5) ^ arrayOfChar[b]) & 0xFF;
        } else {
          arrayOfChar[b] = (char)(arrayOfChar[b] ^ k);
          k = ((k >>> 3 | k << 5) ^ arrayOfChar[b]) & 0xFF;
        } 
      } 
      b[i] = (new String(arrayOfChar)).intern();
    } 
    return b[i];
  }
}


/* Location:              C:\Program Files\BurpSuitePro\burpsuite_pro.jar!\burp\Zg7u.class
 * Java compiler version: 21 (65.0)
 * JD-Core Version:       1.1.3
 */