package burp;

import java.awt.Component;
import java.awt.GridBagConstraints;
import java.awt.GridBagLayout;
import java.awt.GridLayout;
import java.awt.event.ActionEvent;
import java.awt.event.KeyEvent;
import java.util.Arrays;
import java.util.regex.Pattern;
import java.util.regex.PatternSyntaxException;
import javax.swing.BorderFactory;
import javax.swing.JComponent;
import javax.swing.SwingUtilities;
import javax.swing.border.TitledBorder;
import net.portswigger.Zah;
import net.portswigger.Zk_;

public class Zg8u extends Zbqc implements Zedo, Zspz, Zm3g {
  private final Zzi Zb;
  
  private final TitledBorder ZX;
  
  private final TitledBorder Zh;
  
  private final TitledBorder ZT;
  
  private final TitledBorder ZR;
  
  private final TitledBorder ZY;
  
  private final TitledBorder ZUm;
  
  private final TitledBorder Zy;
  
  private Zb07 Zx;
  
  private boolean ZD;
  
  private Zbqc Zu;
  
  private Zzdy Zd;
  
  private Zzdy ZH;
  
  private Zzdy Zw;
  
  private Zzdy ZUG;
  
  private Zzdy Z_;
  
  private Zzdy ZL;
  
  private Zzdy Zg;
  
  private Zzdy ZI;
  
  private Zzdy ZO;
  
  private Zzdy Zo;
  
  private Zzdy Zz;
  
  private Zzdy Zl;
  
  private Zzdy ZN;
  
  private Zzdy ZS;
  
  private Zzdy ZZ;
  
  private Zzdy ZM;
  
  private Zzdy ZK;
  
  private Zzdy Zt;
  
  private Zzdy ZG;
  
  private Zzdy ZQ;
  
  private Zzdy Zi;
  
  private Zzdy Zq;
  
  private Zzdy Zv;
  
  private Zzdy ZB;
  
  private Ze0q ZU;
  
  private Ze01 ZW;
  
  private Ze01 ZP;
  
  private Ze01 Zk;
  
  private Ze01 ZE;
  
  private Zbkr ZC;
  
  private Zbqc Zn;
  
  private Zbqc Za;
  
  private Zbqc ZUY;
  
  private Zbqc Zf;
  
  private Zm9v ZV;
  
  private Zbqc Zs;
  
  private Zbqc ZA;
  
  private Zbqc Zj;
  
  private Zbqc Zr;
  
  private Zbqc ZJ;
  
  private Zbqc ZUt;
  
  private Zg85 Zm;
  
  private Zgff ZF;
  
  private Zg85 ZU4;
  
  private static int[] Zc;
  
  private static final String[] a;
  
  private static final String[] b;
  
  public Zg8u(Zzi paramZzi, boolean paramBoolean, Zm6v paramZm6v) {
    this.Zb = paramZzi;
    ZlG();
    this.Zt.setName(a(5983, -1615));
    this.ZF.setName(a(5908, -2627));
    this.ZU.setName(a(5972, -18126));
    this.Zk.setName(a(5920, -12019));
    this.ZE.setName(a(5922, 12032));
    this.ZC.Za(a(5897, -5528), Zk97.DESKTOP_TOOLS_TARGET_SITE_MAP_SITE_MAP_DISPLAY_FILTER, paramZm6v.ZL(this), false, new String[] { a(5981, 29345) });
    this.ZV.setVisible(false);
    this.ZX = (TitledBorder)this.Zr.getBorder();
    this.Zh = (TitledBorder)this.ZA.getBorder();
    this.ZT = (TitledBorder)this.ZJ.getBorder();
    this.ZR = (TitledBorder)this.Zs.getBorder();
    this.ZY = (TitledBorder)this.ZUt.getBorder();
    this.ZUm = (TitledBorder)this.Za.getBorder();
    this.Zy = (TitledBorder)this.ZUY.getBorder();
    if (paramBoolean) {
      this.Zr.remove(this.Zw);
      this.Zj.remove(this.Zs);
    } 
  }
  
  public void updateUI() {
    try {
      super.updateUI();
      Arrays.<Component>stream(getComponents()).forEach(SwingUtilities::updateComponentTreeUI);
      if (this.Zy != null) {
        this.ZX.setTitleFont(Zt00.DEFAULT_FONT.ZV());
        this.Zh.setTitleFont(Zt00.DEFAULT_FONT.ZV());
        this.ZT.setTitleFont(Zt00.DEFAULT_FONT.ZV());
        this.ZR.setTitleFont(Zt00.DEFAULT_FONT.ZV());
        this.ZY.setTitleFont(Zt00.DEFAULT_FONT.ZV());
        this.ZUm.setTitleFont(Zt00.DEFAULT_FONT.ZV());
        this.Zy.setTitleFont(Zt00.DEFAULT_FONT.ZV());
      } 
    } catch (PatternSyntaxException patternSyntaxException) {
      throw a(null);
    } 
  }
  
  public void Zt2() {
    this.Zt.setSelected(this.Zb.Zal());
    this.ZQ.setSelected(this.Zb.ZaM());
    this.ZG.setSelected(this.Zb.ZaD());
    this.Zw.setSelected(this.Zb.ZaW());
    this.ZO.setSelected(this.Zb.Zac());
    this.ZN.setSelected(this.Zb.ZaU());
    this.ZS.setSelected(this.Zb.ZaJ());
    this.Zg.setSelected(this.Zb.ZaL());
    this.Zl.setSelected(this.Zb.Zan());
    this.Zo.setSelected(this.Zb.Zaw());
    this.ZI.setSelected(this.Zb.Zao());
    this.Zz.setSelected(this.Zb.Zap());
    this.Zi.setSelected(this.Zb.ZaV());
    this.Zq.setSelected(this.Zb.ZaE());
    this.Zv.setSelected(this.Zb.ZaZ());
    this.ZB.setSelected(this.Zb.Zab());
    this.Zd.setSelected(this.Zb.Za5());
    this.ZF.setText(this.Zb.Za8());
    this.ZL.setSelected(this.Zb.ZaP());
    this.ZUG.setSelected(this.Zb.Zaj());
    this.Z_.setSelected(this.Zb.Zav());
    this.ZM.setSelected(this.Zb.Zaq());
    this.ZU4.setText(this.Zb.Zam());
    this.ZH.setSelected(this.Zb.Zag());
    this.Zm.setText(this.Zb.ZaA());
    this.ZZ.setSelected(this.Zb.Zar());
    this.ZK.setSelected(this.Zb.Zad());
    ZO((ActionEvent)null);
    Zi((ActionEvent)null);
    Zlq();
  }
  
  public void Zd(Zmf_ paramZmf_) {
    // Byte code:
    //   0: aload_1
    //   1: invokeinterface ZK : ()V
    //   6: aload_0
    //   7: getfield Zt : Lburp/Zzdy;
    //   10: aload_1
    //   11: sipush #5889
    //   14: sipush #24071
    //   17: invokestatic a : (II)Ljava/lang/String;
    //   20: aload_0
    //   21: getfield Zt : Lburp/Zzdy;
    //   24: invokevirtual isSelected : ()Z
    //   27: invokeinterface ZC : (Ljava/lang/String;Z)Z
    //   32: invokevirtual setSelected : (Z)V
    //   35: aload_0
    //   36: getfield ZQ : Lburp/Zzdy;
    //   39: aload_1
    //   40: sipush #5903
    //   43: sipush #6185
    //   46: invokestatic a : (II)Ljava/lang/String;
    //   49: aload_0
    //   50: getfield ZQ : Lburp/Zzdy;
    //   53: invokevirtual isSelected : ()Z
    //   56: invokeinterface ZC : (Ljava/lang/String;Z)Z
    //   61: invokevirtual setSelected : (Z)V
    //   64: aload_0
    //   65: getfield ZG : Lburp/Zzdy;
    //   68: aload_1
    //   69: sipush #5938
    //   72: sipush #-4976
    //   75: invokestatic a : (II)Ljava/lang/String;
    //   78: aload_0
    //   79: getfield ZG : Lburp/Zzdy;
    //   82: invokevirtual isSelected : ()Z
    //   85: invokeinterface ZC : (Ljava/lang/String;Z)Z
    //   90: invokevirtual setSelected : (Z)V
    //   93: aload_0
    //   94: getfield Zw : Lburp/Zzdy;
    //   97: aload_1
    //   98: sipush #5956
    //   101: sipush #-30534
    //   104: invokestatic a : (II)Ljava/lang/String;
    //   107: aload_0
    //   108: getfield Zw : Lburp/Zzdy;
    //   111: invokevirtual isSelected : ()Z
    //   114: invokeinterface ZC : (Ljava/lang/String;Z)Z
    //   119: invokevirtual setSelected : (Z)V
    //   122: aload_0
    //   123: getfield ZO : Lburp/Zzdy;
    //   126: aload_1
    //   127: sipush #5965
    //   130: sipush #-27281
    //   133: invokestatic a : (II)Ljava/lang/String;
    //   136: aload_0
    //   137: getfield ZO : Lburp/Zzdy;
    //   140: invokevirtual isSelected : ()Z
    //   143: invokeinterface ZC : (Ljava/lang/String;Z)Z
    //   148: invokevirtual setSelected : (Z)V
    //   151: aload_0
    //   152: getfield ZN : Lburp/Zzdy;
    //   155: aload_1
    //   156: sipush #5915
    //   159: sipush #-917
    //   162: invokestatic a : (II)Ljava/lang/String;
    //   165: aload_0
    //   166: getfield ZN : Lburp/Zzdy;
    //   169: invokevirtual isSelected : ()Z
    //   172: invokeinterface ZC : (Ljava/lang/String;Z)Z
    //   177: invokevirtual setSelected : (Z)V
    //   180: aload_0
    //   181: getfield ZS : Lburp/Zzdy;
    //   184: aload_1
    //   185: sipush #5932
    //   188: sipush #-8698
    //   191: invokestatic a : (II)Ljava/lang/String;
    //   194: aload_0
    //   195: getfield ZS : Lburp/Zzdy;
    //   198: invokevirtual isSelected : ()Z
    //   201: invokeinterface ZC : (Ljava/lang/String;Z)Z
    //   206: invokevirtual setSelected : (Z)V
    //   209: aload_0
    //   210: getfield Zg : Lburp/Zzdy;
    //   213: aload_1
    //   214: sipush #5909
    //   217: sipush #7164
    //   220: invokestatic a : (II)Ljava/lang/String;
    //   223: aload_0
    //   224: getfield Zg : Lburp/Zzdy;
    //   227: invokevirtual isSelected : ()Z
    //   230: invokeinterface ZC : (Ljava/lang/String;Z)Z
    //   235: invokevirtual setSelected : (Z)V
    //   238: aload_0
    //   239: getfield Zl : Lburp/Zzdy;
    //   242: aload_1
    //   243: sipush #5895
    //   246: sipush #-547
    //   249: invokestatic a : (II)Ljava/lang/String;
    //   252: aload_0
    //   253: getfield Zl : Lburp/Zzdy;
    //   256: invokevirtual isSelected : ()Z
    //   259: invokeinterface ZC : (Ljava/lang/String;Z)Z
    //   264: invokevirtual setSelected : (Z)V
    //   267: aload_0
    //   268: getfield Zo : Lburp/Zzdy;
    //   271: aload_1
    //   272: sipush #5978
    //   275: sipush #-21623
    //   278: invokestatic a : (II)Ljava/lang/String;
    //   281: aload_0
    //   282: getfield Zo : Lburp/Zzdy;
    //   285: invokevirtual isSelected : ()Z
    //   288: invokeinterface ZC : (Ljava/lang/String;Z)Z
    //   293: invokevirtual setSelected : (Z)V
    //   296: aload_0
    //   297: getfield ZI : Lburp/Zzdy;
    //   300: aload_1
    //   301: sipush #5943
    //   304: sipush #-17990
    //   307: invokestatic a : (II)Ljava/lang/String;
    //   310: aload_0
    //   311: getfield ZI : Lburp/Zzdy;
    //   314: invokevirtual isSelected : ()Z
    //   317: invokeinterface ZC : (Ljava/lang/String;Z)Z
    //   322: invokevirtual setSelected : (Z)V
    //   325: aload_0
    //   326: getfield Zz : Lburp/Zzdy;
    //   329: aload_1
    //   330: sipush #5900
    //   333: sipush #17053
    //   336: invokestatic a : (II)Ljava/lang/String;
    //   339: aload_0
    //   340: getfield Zz : Lburp/Zzdy;
    //   343: invokevirtual isSelected : ()Z
    //   346: invokeinterface ZC : (Ljava/lang/String;Z)Z
    //   351: invokevirtual setSelected : (Z)V
    //   354: aload_0
    //   355: getfield Zi : Lburp/Zzdy;
    //   358: aload_1
    //   359: sipush #5961
    //   362: sipush #-9939
    //   365: invokestatic a : (II)Ljava/lang/String;
    //   368: aload_0
    //   369: getfield Zi : Lburp/Zzdy;
    //   372: invokevirtual isSelected : ()Z
    //   375: invokeinterface ZC : (Ljava/lang/String;Z)Z
    //   380: invokevirtual setSelected : (Z)V
    //   383: aload_0
    //   384: getfield Zq : Lburp/Zzdy;
    //   387: aload_1
    //   388: sipush #5925
    //   391: sipush #2562
    //   394: invokestatic a : (II)Ljava/lang/String;
    //   397: aload_0
    //   398: getfield Zq : Lburp/Zzdy;
    //   401: invokevirtual isSelected : ()Z
    //   404: invokeinterface ZC : (Ljava/lang/String;Z)Z
    //   409: invokevirtual setSelected : (Z)V
    //   412: invokestatic ZlL : ()[I
    //   415: aload_0
    //   416: getfield Zv : Lburp/Zzdy;
    //   419: aload_1
    //   420: sipush #5896
    //   423: sipush #-25353
    //   426: invokestatic a : (II)Ljava/lang/String;
    //   429: aload_0
    //   430: getfield Zv : Lburp/Zzdy;
    //   433: invokevirtual isSelected : ()Z
    //   436: invokeinterface ZC : (Ljava/lang/String;Z)Z
    //   441: invokevirtual setSelected : (Z)V
    //   444: aload_0
    //   445: getfield ZB : Lburp/Zzdy;
    //   448: aload_1
    //   449: sipush #5967
    //   452: sipush #27066
    //   455: invokestatic a : (II)Ljava/lang/String;
    //   458: aload_0
    //   459: getfield ZB : Lburp/Zzdy;
    //   462: invokevirtual isSelected : ()Z
    //   465: invokeinterface ZC : (Ljava/lang/String;Z)Z
    //   470: invokevirtual setSelected : (Z)V
    //   473: aload_0
    //   474: getfield Zd : Lburp/Zzdy;
    //   477: aload_1
    //   478: sipush #5962
    //   481: sipush #-17700
    //   484: invokestatic a : (II)Ljava/lang/String;
    //   487: aload_0
    //   488: getfield Zd : Lburp/Zzdy;
    //   491: invokevirtual isSelected : ()Z
    //   494: invokeinterface ZC : (Ljava/lang/String;Z)Z
    //   499: invokevirtual setSelected : (Z)V
    //   502: aload_0
    //   503: getfield ZF : Lburp/Zgff;
    //   506: aload_1
    //   507: sipush #5982
    //   510: sipush #-7475
    //   513: invokestatic a : (II)Ljava/lang/String;
    //   516: aload_0
    //   517: getfield ZF : Lburp/Zgff;
    //   520: invokevirtual getText : ()Ljava/lang/String;
    //   523: invokeinterface Zm : (Ljava/lang/String;Ljava/lang/String;)Ljava/lang/String;
    //   528: invokevirtual setText : (Ljava/lang/String;)V
    //   531: aload_0
    //   532: getfield ZL : Lburp/Zzdy;
    //   535: aload_1
    //   536: sipush #5971
    //   539: sipush #-28797
    //   542: invokestatic a : (II)Ljava/lang/String;
    //   545: aload_0
    //   546: getfield ZL : Lburp/Zzdy;
    //   549: invokevirtual isSelected : ()Z
    //   552: invokeinterface ZC : (Ljava/lang/String;Z)Z
    //   557: invokevirtual setSelected : (Z)V
    //   560: aload_0
    //   561: getfield ZUG : Lburp/Zzdy;
    //   564: aload_1
    //   565: sipush #5969
    //   568: sipush #-5243
    //   571: invokestatic a : (II)Ljava/lang/String;
    //   574: aload_0
    //   575: getfield ZUG : Lburp/Zzdy;
    //   578: invokevirtual isSelected : ()Z
    //   581: invokeinterface ZC : (Ljava/lang/String;Z)Z
    //   586: invokevirtual setSelected : (Z)V
    //   589: aload_0
    //   590: getfield Z_ : Lburp/Zzdy;
    //   593: aload_1
    //   594: sipush #5973
    //   597: sipush #-12089
    //   600: invokestatic a : (II)Ljava/lang/String;
    //   603: aload_0
    //   604: getfield Z_ : Lburp/Zzdy;
    //   607: invokevirtual isSelected : ()Z
    //   610: invokeinterface ZC : (Ljava/lang/String;Z)Z
    //   615: invokevirtual setSelected : (Z)V
    //   618: astore_2
    //   619: aload_0
    //   620: getfield ZM : Lburp/Zzdy;
    //   623: aload_1
    //   624: sipush #5995
    //   627: sipush #993
    //   630: invokestatic a : (II)Ljava/lang/String;
    //   633: aload_0
    //   634: getfield ZM : Lburp/Zzdy;
    //   637: invokevirtual isSelected : ()Z
    //   640: invokeinterface ZC : (Ljava/lang/String;Z)Z
    //   645: invokevirtual setSelected : (Z)V
    //   648: aload_1
    //   649: sipush #5911
    //   652: sipush #-1169
    //   655: invokestatic a : (II)Ljava/lang/String;
    //   658: invokeinterface Ze : (Ljava/lang/String;)Ljava/util/List;
    //   663: astore_3
    //   664: aload_3
    //   665: ifnull -> 685
    //   668: aload_3
    //   669: ldc ','
    //   671: invokestatic Zf : (Ljava/util/Collection;Ljava/lang/String;)Ljava/lang/String;
    //   674: astore #4
    //   676: aload_0
    //   677: getfield ZU4 : Lburp/Zg85;
    //   680: aload #4
    //   682: invokevirtual setText : (Ljava/lang/String;)V
    //   685: aload_0
    //   686: getfield ZH : Lburp/Zzdy;
    //   689: aload_0
    //   690: getfield ZM : Lburp/Zzdy;
    //   693: invokevirtual isSelected : ()Z
    //   696: ifne -> 739
    //   699: aload_1
    //   700: sipush #5941
    //   703: sipush #-6404
    //   706: invokestatic a : (II)Ljava/lang/String;
    //   709: aload_0
    //   710: getfield ZH : Lburp/Zzdy;
    //   713: invokevirtual isSelected : ()Z
    //   716: invokeinterface ZC : (Ljava/lang/String;Z)Z
    //   721: ifeq -> 739
    //   724: goto -> 731
    //   727: invokestatic a : (Ljava/util/regex/PatternSyntaxException;)Ljava/util/regex/PatternSyntaxException;
    //   730: athrow
    //   731: iconst_1
    //   732: goto -> 740
    //   735: invokestatic a : (Ljava/util/regex/PatternSyntaxException;)Ljava/util/regex/PatternSyntaxException;
    //   738: athrow
    //   739: iconst_0
    //   740: invokevirtual setSelected : (Z)V
    //   743: aload_1
    //   744: sipush #5892
    //   747: sipush #-29378
    //   750: invokestatic a : (II)Ljava/lang/String;
    //   753: invokeinterface Ze : (Ljava/lang/String;)Ljava/util/List;
    //   758: astore_3
    //   759: aload_3
    //   760: ifnull -> 780
    //   763: aload_3
    //   764: ldc ','
    //   766: invokestatic Zf : (Ljava/util/Collection;Ljava/lang/String;)Ljava/lang/String;
    //   769: astore #4
    //   771: aload_0
    //   772: getfield Zm : Lburp/Zg85;
    //   775: aload #4
    //   777: invokevirtual setText : (Ljava/lang/String;)V
    //   780: aload_0
    //   781: getfield ZZ : Lburp/Zzdy;
    //   784: aload_1
    //   785: sipush #5959
    //   788: sipush #19655
    //   791: invokestatic a : (II)Ljava/lang/String;
    //   794: aload_0
    //   795: getfield ZZ : Lburp/Zzdy;
    //   798: invokevirtual isSelected : ()Z
    //   801: invokeinterface ZC : (Ljava/lang/String;Z)Z
    //   806: invokevirtual setSelected : (Z)V
    //   809: aload_0
    //   810: getfield ZK : Lburp/Zzdy;
    //   813: aload_1
    //   814: sipush #5947
    //   817: sipush #17951
    //   820: invokestatic a : (II)Ljava/lang/String;
    //   823: aload_0
    //   824: getfield ZK : Lburp/Zzdy;
    //   827: invokevirtual isSelected : ()Z
    //   830: invokeinterface ZC : (Ljava/lang/String;Z)Z
    //   835: invokevirtual setSelected : (Z)V
    //   838: aload_1
    //   839: invokeinterface Zb : ()Z
    //   844: ifeq -> 868
    //   847: aload_0
    //   848: aconst_null
    //   849: invokevirtual ZO : (Ljava/awt/event/ActionEvent;)V
    //   852: aload_0
    //   853: aconst_null
    //   854: invokevirtual Zi : (Ljava/awt/event/ActionEvent;)V
    //   857: aload_0
    //   858: invokevirtual Zlq : ()V
    //   861: goto -> 868
    //   864: invokestatic a : (Ljava/util/regex/PatternSyntaxException;)Ljava/util/regex/PatternSyntaxException;
    //   867: athrow
    //   868: aload_2
    //   869: ifnonnull -> 886
    //   872: iconst_5
    //   873: anewarray burp/Zbqc
    //   876: invokestatic Zr : ([Lburp/Zbqc;)V
    //   879: goto -> 886
    //   882: invokestatic a : (Ljava/util/regex/PatternSyntaxException;)Ljava/util/regex/PatternSyntaxException;
    //   885: athrow
    //   886: return
    // Exception table:
    //   from	to	target	type
    //   685	724	727	java/util/regex/PatternSyntaxException
    //   699	735	735	java/util/regex/PatternSyntaxException
    //   780	861	864	java/util/regex/PatternSyntaxException
    //   868	879	882	java/util/regex/PatternSyntaxException
  }
  
  public void Zl(Zg4j paramZg4j) {
    paramZg4j.Zh(a(5937, -23449), this.Zt.isSelected());
    paramZg4j.Zh(a(5949, -31214), this.ZQ.isSelected());
    paramZg4j.Zh(a(5975, -2357), this.ZG.isSelected());
    paramZg4j.Zh(a(5907, 20410), this.Zw.isSelected());
    paramZg4j.Zh(a(5951, 5406), this.ZO.isSelected());
    paramZg4j.Zh(a(5934, -12176), this.ZN.isSelected());
    paramZg4j.Zh(a(5940, 27992), this.ZS.isSelected());
    paramZg4j.Zh(a(5921, 3411), this.Zg.isSelected());
    paramZg4j.Zh(a(5906, -23780), this.Zl.isSelected());
    paramZg4j.Zh(a(5970, -12759), this.Zo.isSelected());
    paramZg4j.Zh(a(5958, -19950), this.ZI.isSelected());
    paramZg4j.Zh(a(5890, 12513), this.Zz.isSelected());
    paramZg4j.Zh(a(5924, 18653), this.Zi.isSelected());
    paramZg4j.Zh(a(5928, 18427), this.Zq.isSelected());
    paramZg4j.Zh(a(5980, -13859), this.Zv.isSelected());
    paramZg4j.Zh(a(5929, 2735), this.ZB.isSelected());
    paramZg4j.Zh(a(5936, -4210), this.Zd.isSelected());
    paramZg4j.Za(a(5926, -14899), this.ZF.getText());
    paramZg4j.Zh(a(5979, 10178), this.ZL.isSelected());
    paramZg4j.Zh(a(5931, -7203), this.ZUG.isSelected());
    paramZg4j.Zh(a(5933, 29260), this.Z_.isSelected());
    paramZg4j.Zh(a(5968, -18463), this.ZM.isSelected());
    int[] arrayOfInt = ZlL();
    Zzqw zzqw1 = paramZg4j.ZP(a(5957, -19655));
    String[] arrayOfString1 = this.ZU4.getText().split(",");
    int i = arrayOfString1.length;
    int j = 0;
    while (j < i) {
      String str1 = arrayOfString1[j];
      String str2 = str1.trim();
      try {
        if (!str2.isEmpty())
          zzqw1.Zx(new Zzqs(str2)); 
      } catch (PatternSyntaxException patternSyntaxException) {
        throw a(null);
      } 
      j++;
      if (arrayOfInt == null)
        break; 
    } 
    paramZg4j.Zh(a(5976, 2103), this.ZH.isSelected());
    Zzqw zzqw2 = paramZg4j.ZP(a(5964, -25628));
    String[] arrayOfString2 = this.Zm.getText().split(",");
    j = arrayOfString2.length;
    byte b = 0;
    while (b < j) {
      String str1 = arrayOfString2[b];
      String str2 = str1.trim();
      try {
        if (!str2.isEmpty())
          zzqw2.Zx(new Zzqs(str2)); 
      } catch (PatternSyntaxException patternSyntaxException) {
        throw a(null);
      } 
      b++;
      if (arrayOfInt == null)
        break; 
    } 
    paramZg4j.Zh(a(5944, 27156), this.ZZ.isSelected());
    paramZg4j.Zh(a(5942, 7309), this.ZK.isSelected());
  }
  
  private void Zf(boolean paramBoolean) {
    try {
    
    } catch (PatternSyntaxException patternSyntaxException) {
      throw a(null);
    } 
    try {
      this.Zt.setSelected(!paramBoolean);
    } catch (PatternSyntaxException patternSyntaxException) {
      throw a(null);
    } 
    try {
      this.ZQ.setSelected(!paramBoolean);
    } catch (PatternSyntaxException patternSyntaxException) {
      throw a(null);
    } 
    try {
      this.ZG.setSelected(!paramBoolean);
    } catch (PatternSyntaxException patternSyntaxException) {
      throw a(null);
    } 
    try {
      this.Zw.setSelected(!paramBoolean);
      this.ZO.setSelected(paramBoolean);
      this.ZN.setSelected(paramBoolean);
      this.ZS.setSelected(paramBoolean);
      this.Zg.setSelected(paramBoolean);
      this.Zl.setSelected(paramBoolean);
      this.Zo.setSelected(paramBoolean);
      this.ZI.setSelected(paramBoolean);
      this.Zz.setSelected(paramBoolean);
      this.Zi.setSelected(paramBoolean);
      this.Zq.setSelected(paramBoolean);
      this.Zv.setSelected(paramBoolean);
      this.ZB.setSelected(paramBoolean);
    } catch (PatternSyntaxException patternSyntaxException) {
      throw a(null);
    } 
    try {
      this.Zd.setSelected(!paramBoolean);
      if (paramBoolean) {
        this.ZF.setText("");
        this.ZL.setSelected(false);
        this.ZUG.setSelected(false);
        this.Z_.setSelected(false);
        this.ZV.setVisible(false);
        this.ZM.setSelected(false);
        this.ZH.setSelected(false);
        this.ZZ.setSelected(false);
        this.ZK.setSelected(false);
        ZO((ActionEvent)null);
      } 
    } catch (PatternSyntaxException patternSyntaxException) {
      throw a(null);
    } 
  }
  
  private void Zl6() {
    this.ZD = true;
    this.Zb.ZBy(this.Zt.isSelected());
    this.Zb.ZBV(this.ZQ.isSelected());
    this.Zb.ZBv(this.ZG.isSelected());
    this.Zb.ZB2(this.Zw.isSelected());
    this.Zb.ZBR(this.ZO.isSelected());
    this.Zb.ZB_(this.ZN.isSelected());
    this.Zb.ZBa(this.ZS.isSelected());
    this.Zb.ZB1(this.Zg.isSelected());
    this.Zb.ZBK(this.Zl.isSelected());
    this.Zb.ZBg(this.Zo.isSelected());
    this.Zb.ZBl(this.ZI.isSelected());
    this.Zb.ZBs(this.Zz.isSelected());
    this.Zb.ZBO(this.Zi.isSelected());
    this.Zb.ZBo(this.Zq.isSelected());
    this.Zb.ZBC(this.Zv.isSelected());
    this.Zb.ZBB(this.ZB.isSelected());
    this.Zb.ZBP(this.Zd.isSelected());
    this.Zb.ZR(this.ZF.getText());
    this.Zb.ZBr(this.ZL.isSelected());
    this.Zb.ZBq(this.ZUG.isSelected());
    this.Zb.ZBF(this.Z_.isSelected());
    this.Zb.ZBM(this.ZM.isSelected());
    this.Zb.ZB(this.ZU4.getText());
    this.Zb.ZBm(this.ZH.isSelected());
    this.Zb.Zp(this.Zm.getText());
    this.Zb.ZBY(this.ZZ.isSelected());
    this.Zb.ZBS(this.ZK.isSelected());
  }
  
  private void Zls() {
    Zt2();
  }
  
  private void Zlq() {
    int[] arrayOfInt = ZlL();
    if (this.ZL.isSelected()) {
      try {
        Pattern.compile(this.ZF.getText());
        this.ZV.setVisible(false);
        this.ZU.setEnabled(true);
      } catch (PatternSyntaxException patternSyntaxException) {
        try {
          Zah.Zl(patternSyntaxException, Zk_.USER_ERROR);
          this.ZV.setVisible(true);
          this.ZU.setEnabled(false);
          if (arrayOfInt == null) {
            this.ZV.setVisible(false);
            this.ZU.setEnabled(true);
            return;
          } 
        } catch (PatternSyntaxException patternSyntaxException1) {
          throw a(null);
        } 
      } 
      return;
    } 
    this.ZV.setVisible(false);
    this.ZU.setEnabled(true);
  }
  
  public void Zq(Zb07 paramZb07) {
    this.Zx = paramZb07;
    this.ZD = false;
  }
  
  public JComponent Zlj() {
    return this;
  }
  
  public void ZlQ() {
    try {
      if (!this.ZD)
        Zls(); 
    } catch (PatternSyntaxException patternSyntaxException) {
      throw a(null);
    } 
  }
  
  public void Zlt() {
    Zq((ActionEvent)null);
  }
  
  public void Zlm() {
    Zg((ActionEvent)null);
  }
  
  private void ZlG() {
    this.ZC = new Zbkr();
    this.Zj = new Zbqc();
    this.Zr = new Zbqc();
    this.Zt = new Zzdy();
    this.ZQ = new Zzdy();
    this.ZG = new Zzdy();
    this.Zw = new Zzdy();
    this.ZA = new Zbqc();
    this.ZO = new Zzdy();
    this.Zl = new Zzdy();
    this.ZN = new Zzdy();
    this.Zo = new Zzdy();
    this.ZS = new Zzdy();
    this.ZI = new Zzdy();
    this.Zg = new Zzdy();
    this.Zz = new Zzdy();
    this.ZJ = new Zbqc();
    this.Zi = new Zzdy();
    this.Zq = new Zzdy();
    this.Zv = new Zzdy();
    this.ZB = new Zzdy();
    this.Zs = new Zbqc();
    this.Zd = new Zzdy();
    this.Zf = new Zbqc();
    this.ZUt = new Zbqc();
    this.ZF = new Zgff();
    this.ZL = new Zzdy();
    this.ZUG = new Zzdy();
    this.ZV = new Zm9v();
    this.Z_ = new Zzdy();
    this.Za = new Zbqc();
    this.ZM = new Zzdy();
    this.ZU4 = new Zg85();
    this.ZH = new Zzdy();
    this.Zm = new Zg85();
    this.ZUY = new Zbqc();
    this.ZZ = new Zzdy();
    this.ZK = new Zzdy();
    this.Zn = new Zbqc();
    this.Zk = new Ze01();
    this.ZE = new Ze01();
    this.ZP = new Ze01();
    this.Zu = new Zbqc();
    this.ZW = new Ze01();
    this.ZU = new Ze0q();
    setBorder(BorderFactory.createEmptyBorder(10, 10, 10, 10));
    GridBagLayout gridBagLayout1 = new GridBagLayout();
    gridBagLayout1.columnWidths = new int[] { 0, 5, 0 };
    gridBagLayout1.rowHeights = new int[] { 0, 10, 0, 10, 0 };
    setLayout(gridBagLayout1);
    GridBagConstraints gridBagConstraints = new GridBagConstraints();
    gridBagConstraints.gridx = 0;
    gridBagConstraints.gridy = 0;
    gridBagConstraints.anchor = 23;
    add(this.ZC, gridBagConstraints);
    GridBagLayout gridBagLayout2 = new GridBagLayout();
    gridBagLayout2.columnWidths = new int[] { 0, 5, 0, 5, 0, 5, 0 };
    gridBagLayout2.rowHeights = new int[] { 0 };
    this.Zj.setLayout(gridBagLayout2);
    this.Zr.setBorder(BorderFactory.createTitledBorder(a(5904, -19354)));
    this.Zr.setLayout(new GridLayout(4, 0, 0, 5));
    this.Zt.setText(a(5893, 937));
    this.Zr.add(this.Zt);
    this.ZQ.setText(a(5927, 26781));
    this.Zr.add(this.ZQ);
    this.ZG.setText(a(5901, -25071));
    this.Zr.add(this.ZG);
    this.Zw.setText(a(5955, 13814));
    this.Zr.add(this.Zw);
    gridBagConstraints = new GridBagConstraints();
    gridBagConstraints.gridx = 0;
    gridBagConstraints.gridy = 0;
    gridBagConstraints.fill = 1;
    gridBagConstraints.anchor = 23;
    gridBagConstraints.weightx = 0.25D;
    this.Zj.add(this.Zr, gridBagConstraints);
    this.ZA.setBorder(BorderFactory.createTitledBorder(a(5930, 16263)));
    this.ZA.setLayout(new GridLayout(4, 0, 0, 5));
    this.ZO.setText(a(5939, -30406));
    this.ZA.add(this.ZO);
    this.Zl.setText(a(5966, -5605));
    this.ZA.add(this.Zl);
    this.ZN.setText(a(5898, -18960));
    this.ZA.add(this.ZN);
    this.Zo.setText(a(5919, 24806));
    this.ZA.add(this.Zo);
    this.ZS.setText(a(5916, 18038));
    this.ZA.add(this.ZS);
    this.ZI.setText(a(5963, -29449));
    this.ZA.add(this.ZI);
    this.Zg.setText(a(5953, -5496));
    this.ZA.add(this.Zg);
    this.Zz.setText(a(5910, -24281));
    this.ZA.add(this.Zz);
    gridBagConstraints = new GridBagConstraints();
    gridBagConstraints.gridx = 2;
    gridBagConstraints.gridy = 0;
    gridBagConstraints.fill = 1;
    gridBagConstraints.anchor = 23;
    gridBagConstraints.weightx = 0.25D;
    this.Zj.add(this.ZA, gridBagConstraints);
    this.ZJ.setBorder(BorderFactory.createTitledBorder(a(5960, -13286)));
    this.ZJ.setLayout(new GridLayout(4, 0, 0, 5));
    this.Zi.setText(a(5948, -17246));
    this.ZJ.add(this.Zi);
    this.Zq.setText(a(5935, 23073));
    this.ZJ.add(this.Zq);
    this.Zv.setText(a(5891, 332));
    this.ZJ.add(this.Zv);
    this.ZB.setText(a(5914, 20595));
    this.ZJ.add(this.ZB);
    gridBagConstraints = new GridBagConstraints();
    gridBagConstraints.gridx = 4;
    gridBagConstraints.gridy = 0;
    gridBagConstraints.fill = 1;
    gridBagConstraints.anchor = 23;
    gridBagConstraints.weightx = 0.25D;
    this.Zj.add(this.ZJ, gridBagConstraints);
    this.Zs.setBorder(BorderFactory.createTitledBorder(a(5912, 16276)));
    this.Zs.setLayout(new GridLayout(4, 0, 0, 5));
    this.Zd.setText(a(5918, 6012));
    this.Zs.add(this.Zd);
    gridBagConstraints = new GridBagConstraints();
    gridBagConstraints.gridx = 6;
    gridBagConstraints.gridy = 0;
    gridBagConstraints.fill = 1;
    gridBagConstraints.anchor = 23;
    gridBagConstraints.weightx = 0.25D;
    this.Zj.add(this.Zs, gridBagConstraints);
    gridBagConstraints = new GridBagConstraints();
    gridBagConstraints.gridx = 2;
    gridBagConstraints.gridy = 0;
    gridBagConstraints.fill = 2;
    gridBagConstraints.anchor = 23;
    gridBagConstraints.weightx = 1.0D;
    add(this.Zj, gridBagConstraints);
    GridBagLayout gridBagLayout3 = new GridBagLayout();
    gridBagLayout3.columnWidths = new int[] { 0, 5, 0, 5, 0 };
    gridBagLayout3.rowHeights = new int[] { 0 };
    this.Zf.setLayout(gridBagLayout3);
    this.ZUt.setBorder(BorderFactory.createTitledBorder(a(5952, -8097)));
    GridBagLayout gridBagLayout4 = new GridBagLayout();
    gridBagLayout4.columnWidths = new int[] { 0, 5, 0 };
    gridBagLayout4.rowHeights = new int[] { 0, 5, 0, 5, 0 };
    this.ZUt.setLayout(gridBagLayout4);
    this.ZF.setColumns(20);
    this.ZF.ZH(Zlw9.SEARCH_TERM);
    this.ZF.addKeyListener(new Zg46(this));
    gridBagConstraints = new GridBagConstraints();
    gridBagConstraints.gridx = 0;
    gridBagConstraints.gridy = 0;
    gridBagConstraints.gridwidth = 3;
    gridBagConstraints.fill = 2;
    gridBagConstraints.anchor = 18;
    this.ZUt.add(this.ZF, gridBagConstraints);
    this.ZL.setText(a(5974, 10181));
    this.ZL.addActionListener(new Zx4m(this));
    gridBagConstraints = new GridBagConstraints();
    gridBagConstraints.gridx = 0;
    gridBagConstraints.gridy = 2;
    gridBagConstraints.anchor = 1280;
    this.ZUt.add(this.ZL, gridBagConstraints);
    this.ZUG.setText(a(5905, -3545));
    gridBagConstraints = new GridBagConstraints();
    gridBagConstraints.gridx = 0;
    gridBagConstraints.gridy = 4;
    gridBagConstraints.anchor = 18;
    this.ZUt.add(this.ZUG, gridBagConstraints);
    this.ZV.setHorizontalAlignment(4);
    this.ZV.setText(a(5977, -18615));
    gridBagConstraints = new GridBagConstraints();
    gridBagConstraints.gridx = 2;
    gridBagConstraints.gridy = 2;
    gridBagConstraints.anchor = 1536;
    this.ZUt.add(this.ZV, gridBagConstraints);
    this.Z_.setText(a(5917, -4296));
    gridBagConstraints = new GridBagConstraints();
    gridBagConstraints.gridx = 2;
    gridBagConstraints.gridy = 4;
    gridBagConstraints.anchor = 12;
    gridBagConstraints.weightx = 1.0D;
    this.ZUt.add(this.Z_, gridBagConstraints);
    gridBagConstraints = new GridBagConstraints();
    gridBagConstraints.gridx = 0;
    gridBagConstraints.gridy = 0;
    gridBagConstraints.fill = 1;
    gridBagConstraints.anchor = 23;
    gridBagConstraints.weightx = 0.33D;
    this.Zf.add(this.ZUt, gridBagConstraints);
    this.Za.setBorder(BorderFactory.createTitledBorder(a(5888, 17900)));
    this.Za.setRequestFocusEnabled(false);
    GridBagLayout gridBagLayout5 = new GridBagLayout();
    gridBagLayout5.columnWidths = new int[] { 0, 5, 0 };
    gridBagLayout5.rowHeights = new int[] { 0, 10, 0 };
    this.Za.setLayout(gridBagLayout5);
    this.ZM.setText(a(5954, -24898));
    this.ZM.addActionListener(new Zs5c(this));
    gridBagConstraints = new GridBagConstraints();
    gridBagConstraints.gridx = 0;
    gridBagConstraints.gridy = 0;
    gridBagConstraints.anchor = 1280;
    this.Za.add(this.ZM, gridBagConstraints);
    this.ZU4.setColumns(15);
    gridBagConstraints = new GridBagConstraints();
    gridBagConstraints.gridx = 2;
    gridBagConstraints.gridy = 0;
    gridBagConstraints.fill = 2;
    gridBagConstraints.anchor = 1280;
    this.Za.add(this.ZU4, gridBagConstraints);
    this.ZH.setText(a(5950, 4119));
    this.ZH.addActionListener(new Zgts(this));
    gridBagConstraints = new GridBagConstraints();
    gridBagConstraints.gridx = 0;
    gridBagConstraints.gridy = 2;
    gridBagConstraints.anchor = 1280;
    this.Za.add(this.ZH, gridBagConstraints);
    this.Zm.setColumns(15);
    gridBagConstraints = new GridBagConstraints();
    gridBagConstraints.gridx = 2;
    gridBagConstraints.gridy = 2;
    gridBagConstraints.fill = 2;
    gridBagConstraints.anchor = 1280;
    gridBagConstraints.weightx = 1.0D;
    this.Za.add(this.Zm, gridBagConstraints);
    gridBagConstraints = new GridBagConstraints();
    gridBagConstraints.gridx = 2;
    gridBagConstraints.gridy = 0;
    gridBagConstraints.fill = 1;
    gridBagConstraints.anchor = 23;
    gridBagConstraints.weightx = 0.33D;
    this.Zf.add(this.Za, gridBagConstraints);
    this.ZUY.setBorder(BorderFactory.createTitledBorder(a(5946, -29723)));
    this.ZUY.setRequestFocusEnabled(false);
    GridBagLayout gridBagLayout6 = new GridBagLayout();
    gridBagLayout6.columnWidths = new int[] { 0 };
    gridBagLayout6.rowHeights = new int[] { 0, 10, 0 };
    this.ZUY.setLayout(gridBagLayout6);
    this.ZZ.setText(a(5894, 1466));
    gridBagConstraints = new GridBagConstraints();
    gridBagConstraints.gridx = 0;
    gridBagConstraints.gridy = 0;
    gridBagConstraints.anchor = 18;
    gridBagConstraints.weightx = 1.0D;
    this.ZUY.add(this.ZZ, gridBagConstraints);
    this.ZK.setText(a(5913, -30530));
    gridBagConstraints = new GridBagConstraints();
    gridBagConstraints.gridx = 0;
    gridBagConstraints.gridy = 2;
    gridBagConstraints.anchor = 18;
    this.ZUY.add(this.ZK, gridBagConstraints);
    gridBagConstraints = new GridBagConstraints();
    gridBagConstraints.gridx = 4;
    gridBagConstraints.gridy = 0;
    gridBagConstraints.fill = 1;
    gridBagConstraints.anchor = 23;
    gridBagConstraints.weightx = 0.33D;
    this.Zf.add(this.ZUY, gridBagConstraints);
    gridBagConstraints = new GridBagConstraints();
    gridBagConstraints.gridx = 2;
    gridBagConstraints.gridy = 2;
    gridBagConstraints.fill = 2;
    gridBagConstraints.anchor = 23;
    add(this.Zf, gridBagConstraints);
    GridBagLayout gridBagLayout7 = new GridBagLayout();
    gridBagLayout7.columnWidths = new int[] { 0, 5, 0, 5, 0, 5, 0 };
    gridBagLayout7.rowHeights = new int[] { 0 };
    this.Zn.setLayout(gridBagLayout7);
    this.Zk.setText(a(5899, 15421));
    this.Zk.addActionListener(new Zkmq(this));
    gridBagConstraints = new GridBagConstraints();
    gridBagConstraints.gridx = 0;
    gridBagConstraints.gridy = 0;
    gridBagConstraints.anchor = 21;
    this.Zn.add(this.Zk, gridBagConstraints);
    this.ZE.setText(a(5923, -6940));
    this.ZE.addActionListener(new Zzot(this));
    gridBagConstraints = new GridBagConstraints();
    gridBagConstraints.gridx = 2;
    gridBagConstraints.gridy = 0;
    gridBagConstraints.anchor = 21;
    this.Zn.add(this.ZE, gridBagConstraints);
    this.ZP.setText(a(5902, -4766));
    this.ZP.addActionListener(new Zlk5(this));
    gridBagConstraints = new GridBagConstraints();
    gridBagConstraints.gridx = 4;
    gridBagConstraints.gridy = 0;
    gridBagConstraints.anchor = 21;
    this.Zn.add(this.ZP, gridBagConstraints);
    this.Zu.setLayout(new GridLayout(1, 0, 5, 0));
    this.ZW.setText(a(5994, 12419));
    this.ZW.addActionListener(new Zsno(this));
    this.Zu.add(this.ZW);
    this.ZU.setText(a(5945, 30178));
    this.ZU.addActionListener(new Zzph(this));
    this.Zu.add(this.ZU);
    gridBagConstraints = new GridBagConstraints();
    gridBagConstraints.gridx = 6;
    gridBagConstraints.gridy = 0;
    gridBagConstraints.anchor = 22;
    gridBagConstraints.weightx = 1.0D;
    this.Zn.add(this.Zu, gridBagConstraints);
    gridBagConstraints = new GridBagConstraints();
    gridBagConstraints.gridx = 2;
    gridBagConstraints.gridy = 4;
    gridBagConstraints.fill = 2;
    gridBagConstraints.anchor = 23;
    gridBagConstraints.weighty = 1.0D;
    add(this.Zn, gridBagConstraints);
  }
  
  private void ZB(ActionEvent paramActionEvent) {
    Zlq();
  }
  
  private void ZO(ActionEvent paramActionEvent) {
    try {
    
    } catch (PatternSyntaxException patternSyntaxException) {
      throw a(null);
    } 
    this.ZH.setEnabled(!this.ZM.isSelected());
  }
  
  private void Zb(ActionEvent paramActionEvent) {
    Zf(true);
  }
  
  private void ZL(ActionEvent paramActionEvent) {
    Zf(false);
  }
  
  private void Zp(ActionEvent paramActionEvent) {
    Zls();
  }
  
  private void Zg(ActionEvent paramActionEvent) {
    Zls();
    this.Zx.Zgf();
  }
  
  private void Zq(ActionEvent paramActionEvent) {
    Zl6();
    this.Zx.Zgf();
  }
  
  private void Zd(KeyEvent paramKeyEvent) {
    Zlq();
  }
  
  private void Zi(ActionEvent paramActionEvent) {
    try {
    
    } catch (PatternSyntaxException patternSyntaxException) {
      throw a(null);
    } 
    this.ZM.setEnabled(!this.ZH.isSelected());
  }
  
  public static void Zv(int[] paramArrayOfint) {
    Zc = paramArrayOfint;
  }
  
  public static int[] ZlL() {
    return Zc;
  }
  
  private static PatternSyntaxException a(PatternSyntaxException paramPatternSyntaxException) {
    return paramPatternSyntaxException;
  }
  
  static {
    // Byte code:
    //   0: bipush #98
    //   2: anewarray java/lang/String
    //   5: astore #5
    //   7: iconst_0
    //   8: istore_3
    //   9: ldc 'XfN[wH_Â¸{aÂ¯BQÃ³Â²uÂ¦\\nÃ§eÂšÃ´%Â¸Ã²eÃ¡Ãš%Ã²=Ã­sÃ‘Ã—Â¶Ã¶#\\fÃ•O6'Â® Ã¡Â‹Ã·Ã~7Ã¢j\\nÂµÃ¹:ÃœÃ…Ã‡07ÃšÂ«Ã¨Â¡qÂÂ¢Â½Â”J\Ã¸EÂ“fÂ¢Â†Â4ÃšQÃ±Ã€Â¸Â¤Â¬t@ÂœÂ‰Ã®vÂ‰xWÂ—?Ã–lÂ¸7ÃŠXUÂƒÂ”Â…Â”siÂ±ÂÃŠÃ¦-Â‰Ã·ÃÂ®Â©Ã›`ÂQÃ± Ã‡Â•/%UÂ…Ã”(`Ã|Ã±ÃˆÃ¿sp<Â³a[ÂxakXfÃœfqJÂ¾,jÂµÃ¾bÂ³ÃµÃºÂ²ÂŸÂ«=Ã„iÃ£R6Â.ÂLÂµÃ©Â Ã¬Â­Ã‰Â–ÃºTÃÂ…ÂqK('DÂ’ÃŸÂ¯\\n\#Â²YÂ“$Ãµ@#Ã³2qRÂ®Ã§Â®e,ÃÃ¾\\n-Ã˜)Ã¥rRÂ€Ã†Ã\\bÂ‘Ã„ÃšsaÃÃšÃ]Ã¯zÃ®Ã´ÃŒ]*Ã¬0Â¢Ã®RÂ“6Â¸5Â¤rÃ¸Ã·Â“Ã²Â²Â£Â˜Ã…Ã4uVÃ¤x\\tÃ˜Â‹Ã±Ã·Â‚EÃ›IÃ˜;Âš4Â„EÃ§#Â…Ã•;(Â‹Â‰;Â-"'^ÂDÃ”Ã•CtÃ™@Â¹Ã†(Ã­Ã‹Ã…Ã¹Ã²nÂ°ÂªUrxÂŸUÃƒÂ»*!cÂ—Â¸ÂÂ®_Ã™+Ã†Â«iÂ»Â¡Â¹Ã¤}YGÃ€Â¢Â«Â„6AÃ•Â“ Â±Â‚Â·_Â£FÃ‚,ÂœSÂ£$hÂ´Â½Â·Ã‰nÃƒ\\fÃ¦_Ã¶IÂÂš)9Â”Â¼Â›{jÃ“LfÃ¤ Â´@Ã¨ÂÃ§Ã“ÂƒUÃ‹Ã‘I~0Â¤Ã Â¯Â­ 4*[ÂˆÃ˜Ã…wb,ÂŒx_Â¾%[jÂ»Â¹\\bÂ·KÃ˜Â‡Ã¬Â³ÂºÂ¤Â†ÃÃ ÃˆNÃ§\\rÂ–'Â™Ãš'ÂŠ5&KÃ†Ãš\\f78jÂÂœ"!ÃˆÃªÃ‰Ã¼\\ntÂÂÃ†Â§ÃÃ¢\\nOqÃ€\\rÃ‡0Ã¼Ã°Â‘Ã©Â¶Ã­ÃŸÃ–Ã‡Ã•g\\fPGÃ³Â€ÃÃºyBÂÃŸÃš^Ãƒ1Â¸^SÂŒÃŸ)\\tcÃ”YÃ‰Ã´Â›b7?Â˜VÃÃ¸%{Â¹Ã‘Ã¦WÃ‚5Â¥LÂ–Â $(Â  Â­Us*Â´Â£M"c&Â‹uÂ«/ÃŠÂ¬Â¤ÃP&2\\tpÃµbÃ€Ã¬Ã˜`Ã•Â½t;@Â·B,Â¬ÂB{Â¢Ã©Ã¨Â†Â–1q4Â´ÃºÂ¢8Âˆ0ÂˆÃª2Ã´Ã›*Â¸'hjÃg*.Ã—v.Â¢|Ã˜ÂƒÃ›ÂÂµ xÂŒÃArÃ­Â¦VÂÃ…,NÃ±Ã((5Ã«Â…Â¾6VÃ‰ÂŸÂ”EvlÂ¾Â¾Â´ÂÃœÃ¹xÃ‡Ã¾oÃ‡'Â²Ã©Ã¤Â®-'Â­Ã»Â€Â¥dÂ¿[]Â-Ã³e"*ÃŒ2*Â’)Ã«Â©qÃµÃ“pÃ‹Ã€ÃµÃ–nÂÃºÃ 2LÂ±ÃŠÂ‹Ã³+NtÂ›kÂ¶tTA<RV\\fÂ‰PaÂ¥i!3g#Âœ Ã¶hgÂÃ Ã°Ã¡ÃÂÃ”=TwÃ€+Ã°ÂTÃu-ÃšÂ£MÂ¥ÂºÂ„~Â³ Ã· Â»Â‘Â¨Â°Ã»Ã©Ã¤hEÃƒÂ¶ÃƒchÃŠÂƒ1OÃ­Â«*/ÃÃ­Â®Y&mÂ“yÂ–OÃ)&Ã«uÂ³"Â¸Â”]IO9Ãœ1ÂÃÂÃ¡Â²Ã®Â®7XiÂ‡/M+Â³aÃ¡ÃµÃ²ÂcÃœsÂ®Â‹ÂÂÃ¿Â‡$Â–Ã°Ã”%Ã‚Ã«4?Â®Ã«Â€lÂ¡CÂ¸Â¦Ã‡Â#&^!cÃ¯Ã“}Â”Â‚;xÃ«(Ã¦Ã‚Â€Ã±%Ã¢Ã”Ã¯NÂ‘pÂ¾Â½,KLÂ§YÂ¾Ã°"$Â¡,Ã¿:Â©Ã‚Â¹Ãyu\\b5Ã€ÃºwUÂ°Â¼Â¿ÃµÃÂƒj)<4qQ?&Â˜ZÂ ÂŸxJÂƒEÂ°UÃ˜Ã•Ã¯t-Ã„`pÃ§DÃ³wÂˆÂšE3Â»V^Ã©Â¬Â†cÃg'1}Â•{ÃÃ–WÃ–*'Â‹UÂ¿&9mYIÃ¹Âœ)Â‰ÃÂŠÂ˜Â’|48YÃ•Ã— Ã¹Ã—Â•#0*ÂµÂ‘ÃšÂ‹Ã—}:RÂ‰Ã»Ã¿Ã³1Â®leÃ©Ã¦2#Â°Ã“Â‘JjÂ·Ã’Â†\\b]ÂµÂ¾K9JÂ– Ã½ÃƒÃ­Â§?Ã˜VÃ‚Ã©NÃ›\\fÂ”Â’NÃ¡EÂµÃ•1Ã¡Ã™=Ã•J##Â¹Â‘Â„Ã¦Ã¼eÂ Â¢Ã©ÂšÂŒÂ}sÃ¥Â«TÂÃ€ÃœÃ§mÂˆÂ«Â¤Ã³Â¤WÂ·%wÂ³ ;5Â$]{0:ÃŸÂ‰JÃ¿Â¯:TÂŸ9dÂ¯JÂ¥Â±Â¿?Â¬\\n;+ÃµÂÃ“=Ã­ÂœÂœiÂ»Y|Ã¼%u"(Ã¯ÂªÂ•ÂtÂ”Ã®!\\tHÂ˜Â…pÃ€rÃ–Ã‚ÂˆÃˆÃŠÃ½coÃ’Ã»@ÂÂ³ÃœÂ¹%:`Ã´Ã˜Ã²Â¢Ã’XÂšÃ¶Âo}aaÃ¼fD9Â²Ã‚Ã¾Â“`Ã²Ã¢sÃ8Ã¢Â¿ÃÃÂÃ›l%Â…JÂ\\f\\n\\rMaTÃ¢;Â’Ã«ÂœÂ­Ã™nÃÃ·<VLu\\t@\\fÂ„Ã—hBÂoÂ«-)Ã«7m6Â¯Ã»ysÃ¯Â“3ÃƒÂ¨Ã´Ã›N1 Ã‰eÂÃ«rÃˆÂ”Â¹Ã¾Ã°ÂŸÃŸÂºÂ¿RF4PÃŠÂˆVÃ”Â„'B.0Ã‡Ã…gÃ‚ÂbÃ‹Â‚ÃˆÂÂ›lÂ–DÂ­Ã­ÃºÃ£ÃªÂ¦Ã½Â¸Â»jUÂ¡Â˜5YÂ•Â˜fucÂ¢Â¬Â©[Â„Â¥zSÂ£ONehÃ—ÂƒÂ–Â·Â’7\\nÂ‹Ã±Ã€@Â€ÂÃ›__oÃ] Ã“Ãª*>Ã©Âƒ$Â´Ã%Ã¬Ãˆ$Â•ÂˆrÃ¬Â€,Ã\\tÃ±Ã¨Ã»ÃµÂ”Ã´ÂaEXÂ®Â°Â°?5#  _4$7c}ÃŸ{Â—Ã–~Ã–'/U+&Â«?X Â·ÂªÃ“?ÃlÃ™.)DXÃ_OÂqd\\n#ZÂ¹Âµ6Ã N"<BDÂ³WÃ”Cd_%Â‰Â\\rfÂO'Â ?\`Â¼`>?Â±TÃ¢Ã¦Ã¥PÂ°ÃŠÃ«Â—ÃŒ<IrcÂ”ÂˆÂ™Ã†Â™2ÂµÃº\\rÃ”@9Â¦>Â“Â“Ã„ W$aÃ¤Â’ <jQÃŒÃ€z(KÃ†@Â²]Â¨ÂªCÃ@6Â‚%Ã£pÂ·ÂÃºÂ¢Ã¬Ã¥S0Â¤Ã–Ã ?0Ã‹Ã¬Ã¿!DÂ¯iV?KÂš.sÂ†Ã¶Ãº+&Ã”O\\bÂÃª2`\e+Â·2EÂ’Ã„Ã«qBÃ“Â†Ã‹Ãµ\\rnÃ«Â“Ã Ã¿\\b'Â€\\bPÃ…`\\tÃ¹Â¶ZÃ±'Â–ÂÃªÃ£ÂŸÂÃ™%p;bÃÃ€Ã—Ã˜Ã•QtÂ¦@BEÂ C^g4Ã²EHyjÃ€Â‡Â†PÃ’m7Ãƒ0Ã‹Ã’Ã£.pÃ³nÃuÂ®~ÂŸÂ¥$Ã³%Ã‹~Ã™Â£Ã¼4^Ã'TÂ“Ã´ÃªÂÂ‹Ã·6Â‰ÂˆÂŒÃƒ[>ÂÃÃƒÃÃšG-ÂœÃ¤ HhÂ°ÂÃ°Â¾ÃfÃ”@TÃ˜Ã€Ã•Ã°:TidÃšÃ|+^?Ã»Ã¶- anÂ82=Ã¼Âªf:>#Ã…Â°Ã‚\\rÃ¡-0eÃ»bÃÂ‚UÂzÂ™ÂŠÃ›Âº1XÃ™Ã½OÂ¹Ã¿Ã¦Ã¬Ã¬Â´Â¾BH8Â‰Ã¥ÂƒÂ¬+OR=&HÃÃ‰Ã·10ÂªÃˆÂ…S~Â„OÃ½{>ÂƒÂ‡Â´Âš'Â¦sÃ³Ã¢ÂŒ0Â¤ttÂ¶]ZÂ¨%Â¤j'Â™ÂˆÂŠÂ]sVÂ {ÃšÃ£Â•Â¬Ã¸NÃªÃ³Â¸Ã–ÃœeBNÃ„ÂŸ`KÂ€NÂ‹\\t-oÃ¾TDqFÂ¬ÂŠÃµÂŠÃ›kÂÃ…xÂƒq]Â¢%ÃŠ[ÃªÂ¿1NÂªÃ…Â•E|AÂ¯Ã¦%Â–'Ã•Ã«Ã½Ã½QÂ’Â¦,8\\t ÂºÃƒÃ‘\\nÂ¾Â£"f\\rÃ¯p=Âˆ$ÃŒÃˆ*Ã) Â©\\fÃµ|p>Ã€KÃ–Â¹ÂÃ²ÃºÂµÂ¹]ÃÃŸ>Ã­Â®Ã²Ã¼}[)\\b#*qÃŠÂÂÃŸ\\bw\\r.\:Â¯Ã‹;Â©-Ã»MÃ¿Ã£Ã‘Â’ÃÂÃ°DpÂ™\ÃOÃ“XÂÂÃ(Ã”Ã…Â„gm\\rÂÃ¦\{Â’Â…Ã¸d\\fOÃª6Ã¿:\\nyBNÃŸyÃšQÃƒÃŠ(Ã©FÃ 9Ã…Ã©\\tÃ³Â£Â°k#Â¶Ã¬Ã’#LpfzÂ€5gÂ_Â‡|/O'Â²*ÃšÂ‹Â‹;Â¸ÂˆrÂ¶\\twÂ”42ÃªÂÃ±ÃªÃ’ÂµÃª#xÃ¡Ã„Ã’Â¼ÃÂ¢7Ã’ÃÃ±Ã”1Ã¹ÂŠ{%ÂŒÂ"(Â‰/Ã±Ã°Â²ÃÃšÃ”Â‹ÃÂ´Ã²}Â }Ã¢Ã›ZmÂšÂ¾cÃ¾OwÃ¬'*Â‹oÃ‚94Â\\nÃŸÂÃ¾qÂ¢Ã¬Â„Ã—^K\\bGÃ¯Â¾Ã„IÃºNq,Ã«ÂœÃ¿\\f4Â¿Â’&Âƒ2NpbÃ€OÃ˜Ã•3tÃª@ÂBkÂ¬fBfÂ¢JÃ¨Ã²Â–Â¿qÃ¥Â´Ã€Â¢ÂˆÃ˜ÂˆÃ·2WÃ›^6'Â¹PÃ LÂ‹:Â¥+\\rÃ©Â­Ã½HqÂ¸Ã Â›Ã’Â£Â¯Ã¦Ã\\fGÂ—Ã²Ã¥~{Â¬&Â—Ã’&6}JÂ£Â‰Â‰Ã¿Â€1ÂœÃ¨CWÂ­^\\nÃ„Â¾nÂ£Ã‹bÂ¨_%Ã‚Â‡ÂoÃ½ÃšÃ•Â˜\\r.Ã¬Ã¨Â¡Ã¼Vq>Ã¶Â½{.Ãš-rÃ¡Ã½Ã¨Ã“Â¤Ã¶Â˜Ã®\\rlo#Ã°.Ã-ÂšÃ¯}X!,Ã¶TÂ„ÂºÂÃdÂ³=Âƒ&JÂ‰ÃºÂ»0Â…!ÃªÃŸ$cjÂ“Ã–'*Ã‘Â‹Ã‘Â³KÂÃÃ»Â™##o [7Np)XÂ²hÂ”!Â´H/Â…Ã©pÃ€Ã€Â©Ã–Â¹Ã§Ãˆ'Ã½ÃoeÃ»Â¶ÂmÃœb\\rÂ£ÂÃ‡Â”Y'Â®Â’%WÂ“>~OÃƒ)Â…Ã«Â³Â¬Â¸E]s^T."Ã»AÂ‘Â¾Ã¶/fiÃ«Â¶Â»ÂŠÃ¿Â½Ã£Â¨Ã¬Â¬Â™Ã¢ÃÂ’hÂœÂ]Ã Ã¡Ã‡Ã˜Ã‚Ã‹Ã¦oÃ†cÂÂ«Ã&ÃšeÃ¨xqÂ¶Â¢ÃšÂ”Â¦\eE fÃ”Â†_8 MVÂ¾Ã¤ÃM+Â™LLÂÃ‡Â„Â’S&JÂ’ÃºÂ†3iÃª!ÂÃ™}ÂŠaÃÃ¢kÂ¶&Ã¬#Â”~jpwM<QmÂ§"xFÂ²L2Ã¸tÂ¬ZÃ¹Ã²Â³RÂ¶Â·GÃdw\Â¤E|(Ã…+VÂ’Â‰uÃ£&ÃŸÃ•Â©_Ã°Ã²ÂœÃ^Ã—V|Â‰lÂ¤Â¢Ã’\\r>,u6zÂªÃ¶Ã™Ã’Ã»Â§Â±EÃ¸$Ã‘TpPÃªÂŠÂŠÂ»Ã—Ã‹AÃ²Ã‰Ã½+>Â€WÂ¦ÂŒLDÂ­Ã•Ã&ÂµÂ®`TÃ¦iÃ¬)Â‡ÂŠSÂÃlÃ¤ÂŒÃŠqsÂ‘*`Âƒ'g\\n_Â•Â‡|mOP'Â»*Ã»Â‹Â¯;.ÂƒÃ¿Â A2ÂµÃ½4|Ã©Ã©ÂŠÃ¢ÂƒÂ ÃŠÃ¸Â \\nÂ¾Â‹a#Ã³Ã¦Â#Â‰1Ã¨Ã¨Â¬Ã“sÂ¿ÂÃ¤Ã¬/uÂŠÃ¾mÂ‚Â»hÂ³\\bÂ '
    //   11: dup
    //   12: astore_2
    //   13: invokevirtual length : ()I
    //   16: istore #4
    //   18: iconst_3
    //   19: newarray int
    //   21: bipush #8
    //   23: istore_1
    //   24: invokestatic Zv : ([I)V
    //   27: iconst_m1
    //   28: istore_0
    //   29: bipush #54
    //   31: iinc #0, 1
    //   34: aload_2
    //   35: iload_0
    //   36: dup
    //   37: iload_1
    //   38: iadd
    //   39: invokevirtual substring : (II)Ljava/lang/String;
    //   42: iconst_m1
    //   43: goto -> 149
    //   46: aload #5
    //   48: swap
    //   49: iload_3
    //   50: iinc #3, 1
    //   53: swap
    //   54: aastore
    //   55: iload_0
    //   56: iload_1
    //   57: iadd
    //   58: dup
    //   59: istore_0
    //   60: iload #4
    //   62: if_icmpge -> 74
    //   65: aload_2
    //   66: iload_0
    //   67: invokevirtual charAt : (I)C
    //   70: istore_1
    //   71: goto -> 29
    //   74: ldc 'Â™Â™^9y@}ÃšÂ±x&`Ã”^ÂŠÃ…Ã…Â¨ÂKEÂ™Â˜ÂÂºÃX?Ã¥(0> Ã¿AÃ¬Ã’Â˜h[ÂVY;Â³Ã "Â€Ã¤Â±8'
    //   76: dup
    //   77: astore_2
    //   78: invokevirtual length : ()I
    //   81: istore #4
    //   83: bipush #50
    //   85: istore_1
    //   86: iconst_m1
    //   87: istore_0
    //   88: bipush #98
    //   90: iinc #0, 1
    //   93: aload_2
    //   94: iload_0
    //   95: dup
    //   96: iload_1
    //   97: iadd
    //   98: invokevirtual substring : (II)Ljava/lang/String;
    //   101: iconst_0
    //   102: goto -> 149
    //   105: aload #5
    //   107: swap
    //   108: iload_3
    //   109: iinc #3, 1
    //   112: swap
    //   113: aastore
    //   114: iload_0
    //   115: iload_1
    //   116: iadd
    //   117: dup
    //   118: istore_0
    //   119: iload #4
    //   121: if_icmpge -> 133
    //   124: aload_2
    //   125: iload_0
    //   126: invokevirtual charAt : (I)C
    //   129: istore_1
    //   130: goto -> 88
    //   133: aload #5
    //   135: putstatic burp/Zg8u.a : [Ljava/lang/String;
    //   138: bipush #98
    //   140: anewarray java/lang/String
    //   143: putstatic burp/Zg8u.b : [Ljava/lang/String;
    //   146: goto -> 308
    //   149: dup_x2
    //   150: pop
    //   151: invokevirtual toCharArray : ()[C
    //   154: dup_x1
    //   155: arraylength
    //   156: dup_x2
    //   157: pop
    //   158: iconst_0
    //   159: istore #6
    //   161: dup2_x1
    //   162: pop2
    //   163: dup_x2
    //   164: iconst_1
    //   165: if_icmpgt -> 268
    //   168: dup2
    //   169: swap
    //   170: iload #6
    //   172: dup2_x1
    //   173: caload
    //   174: swap
    //   175: iload #6
    //   177: bipush #7
    //   179: irem
    //   180: tableswitch default -> 250, 0 -> 220, 1 -> 225, 2 -> 230, 3 -> 235, 4 -> 240, 5 -> 245
    //   220: bipush #38
    //   222: goto -> 252
    //   225: bipush #81
    //   227: goto -> 252
    //   230: bipush #15
    //   232: goto -> 252
    //   235: bipush #36
    //   237: goto -> 252
    //   240: bipush #36
    //   242: goto -> 252
    //   245: bipush #50
    //   247: goto -> 252
    //   250: bipush #31
    //   252: ixor
    //   253: ixor
    //   254: i2c
    //   255: castore
    //   256: iinc #6, 1
    //   259: dup
    //   260: ifne -> 268
    //   263: dup2
    //   264: dup_x1
    //   265: goto -> 172
    //   268: dup2_x1
    //   269: pop2
    //   270: dup_x2
    //   271: iload #6
    //   273: if_icmpgt -> 168
    //   276: pop
    //   277: new java/lang/String
    //   280: dup_x1
    //   281: swap
    //   282: invokespecial <init> : ([C)V
    //   285: invokevirtual intern : ()Ljava/lang/String;
    //   288: swap
    //   289: pop
    //   290: swap
    //   291: tableswitch default -> 46, 0 -> 105
    //   308: return
  }
  
  private static String a(int paramInt1, int paramInt2) {
    int i = (paramInt1 ^ 0x170B) & 0xFFFF;
    if (b[i] == null) {
      char[] arrayOfChar = a[i].toCharArray();
      switch (arrayOfChar[0] & 0xFF) {
        case 0:
        
        case 1:
        
        case 2:
        
        case 3:
        
        case 4:
        
        case 5:
        
        case 6:
        
        case 7:
        
        case 8:
        
        case 9:
        
        case 10:
        
        case 11:
        
        case 12:
        
        case 13:
        
        case 14:
        
        case 15:
        
        case 16:
        
        case 17:
        
        case 18:
        
        case 19:
        
        case 20:
        
        case 21:
        
        case 22:
        
        case 23:
        
        case 24:
        
        case 25:
        
        case 26:
        
        case 27:
        
        case 28:
        
        case 29:
        
        case 30:
        
        case 31:
        
        case 32:
        
        case 33:
        
        case 34:
        
        case 35:
        
        case 36:
        
        case 37:
        
        case 38:
        
        case 39:
        
        case 40:
        
        case 41:
        
        case 42:
        
        case 43:
        
        case 44:
        
        case 45:
        
        case 46:
        
        case 47:
        
        case 48:
        
        case 49:
        
        case 50:
        
        case 51:
        
        case 52:
        
        case 53:
        
        case 54:
        
        case 55:
        
        case 56:
        
        case 57:
        
        case 58:
        
        case 59:
        
        case 60:
        
        case 61:
        
        case 62:
        
        case 63:
        
        case 64:
        
        case 65:
        
        case 66:
        
        case 67:
        
        case 68:
        
        case 69:
        
        case 70:
        
        case 71:
        
        case 72:
        
        case 73:
        
        case 74:
        
        case 75:
        
        case 76:
        
        case 77:
        
        case 78:
        
        case 79:
        
        case 80:
        
        case 81:
        
        case 82:
        
        case 83:
        
        case 84:
        
        case 85:
        
        case 86:
        
        case 87:
        
        case 88:
        
        case 89:
        
        case 90:
        
        case 91:
        
        case 92:
        
        case 93:
        
        case 94:
        
        case 95:
        
        case 96:
        
        case 97:
        
        case 98:
        
        case 99:
        
        case 100:
        
        case 101:
        
        case 102:
        
        case 103:
        
        case 104:
        
        case 105:
        
        case 106:
        
        case 107:
        
        case 108:
        
        case 109:
        
        case 110:
        
        case 111:
        
        case 112:
        
        case 113:
        
        case 114:
        
        case 115:
        
        case 116:
        
        case 117:
        
        case 118:
        
        case 119:
        
        case 120:
        
        case 121:
        
        case 122:
        
        case 123:
        
        case 124:
        
        case 125:
        
        case 126:
        
        case 127:
        
        case 128:
        
        case 129:
        
        case 130:
        
        case 131:
        
        case 132:
        
        case 133:
        
        case 134:
        
        case 135:
        
        case 136:
        
        case 137:
        
        case 138:
        
        case 139:
        
        case 140:
        
        case 141:
        
        case 142:
        
        case 143:
        
        case 144:
        
        case 145:
        
        case 146:
        
        case 147:
        
        case 148:
        
        case 149:
        
        case 150:
        
        case 151:
        
        case 152:
        
        case 153:
        
        case 154:
        
        case 155:
        
        case 156:
        
        case 157:
        
        case 158:
        
        case 159:
        
        case 160:
        
        case 161:
        
        case 162:
        
        case 163:
        
        case 164:
        
        case 165:
        
        case 166:
        
        case 167:
        
        case 168:
        
        case 169:
        
        case 170:
        
        case 171:
        
        case 172:
        
        case 173:
        
        case 174:
        
        case 175:
        
        case 176:
        
        case 177:
        
        case 178:
        
        case 179:
        
        case 180:
        
        case 181:
        
        case 182:
        
        case 183:
        
        case 184:
        
        case 185:
        
        case 186:
        
        case 187:
        
        case 188:
        
        case 189:
        
        case 190:
        
        case 191:
        
        case 192:
        
        case 193:
        
        case 194:
        
        case 195:
        
        case 196:
        
        case 197:
        
        case 198:
        
        case 199:
        
        case 200:
        
        case 201:
        
        case 202:
        
        case 203:
        
        case 204:
        
        case 205:
        
        case 206:
        
        case 207:
        
        case 208:
        
        case 209:
        
        case 210:
        
        case 211:
        
        case 212:
        
        case 213:
        
        case 214:
        
        case 215:
        
        case 216:
        
        case 217:
        
        case 218:
        
        case 219:
        
        case 220:
        
        case 221:
        
        case 222:
        
        case 223:
        
        case 224:
        
        case 225:
        
        case 226:
        
        case 227:
        
        case 228:
        
        case 229:
        
        case 230:
        
        case 231:
        
        case 232:
        
        case 233:
        
        case 234:
        
        case 235:
        
        case 236:
        
        case 237:
        
        case 238:
        
        case 239:
        
        case 240:
        
        case 241:
        
        case 242:
        
        case 243:
        
        case 244:
        
        case 245:
        
        case 246:
        
        case 247:
        
        case 248:
        
        case 249:
        
        case 250:
        
        case 251:
        
        case 252:
        
        case 253:
        
        case 254:
        
        default:
          break;
      } 
      char c = 'Ãœ';
      int j = (paramInt2 & 0xFF) - c;
      if (j < 0)
        j += 256; 
      int k = ((paramInt2 & 0xFFFF) >>> 8) - c;
      if (k < 0)
        k += 256; 
      for (byte b = 0; b < arrayOfChar.length; b++) {
        int m = b % 2;
        if (m == 0) {
          arrayOfChar[b] = (char)(arrayOfChar[b] ^ j);
          j = ((j >>> 3 | j << 5) ^ arrayOfChar[b]) & 0xFF;
        } else {
          arrayOfChar[b] = (char)(arrayOfChar[b] ^ k);
          k = ((k >>> 3 | k << 5) ^ arrayOfChar[b]) & 0xFF;
        } 
      } 
      b[i] = (new String(arrayOfChar)).intern();
    } 
    return b[i];
  }
}


/* Location:              C:\Program Files\BurpSuitePro\burpsuite_pro.jar!\burp\Zg8u.class
 * Java compiler version: 21 (65.0)
 * JD-Core Version:       1.1.3
 */