package burp;

import java.math.BigInteger;

class Zg_5 extends ClassLoader {
  static String ZG;
  
  static Object ZA;
  
  private static final String[] a;
  
  private static final String[] b;
  
  static void Zg(Object paramObject) {
    Zram.Ze = a(13345, -32716);
    Zram.ZF = new BigInteger(a(13359, -21489));
    boolean bool = Zt2e.ZK();
    try {
      try {
        if (Ze8m.Zx.charAt(Math.abs(((BigInteger)Zkt7.ZY).intValue() % 32)) <= Zmj8.ZL.charAt(Math.abs(((BigInteger)Zt9_.ZN).intValue() % 32))) {
          try {
            Zr1t.ZX(Class.forName(a(13361, -31011)));
            if (bool)
              Zlhq.Zu(Class.forName(a(13363, 21905))); 
          } catch (Throwable throwable) {
            throw a(null);
          } 
          return;
        } 
      } catch (Throwable throwable) {
        throw a(null);
      } 
      Zlhq.Zu(Class.forName(a(13363, 21905)));
    } catch (Throwable throwable) {}
  }
  
  static void ZS(Object[] paramArrayOfObject, Object paramObject) throws Throwable {}
  
  static boolean Zg(Object[] paramArrayOfObject, Object paramObject) throws Throwable {
    // Byte code:
    //   0: invokestatic ZK : ()Z
    //   3: istore_2
    //   4: getstatic burp/Ztkh.Zh : Ljava/lang/Object;
    //   7: checkcast java/math/BigInteger
    //   10: invokevirtual toByteArray : ()[B
    //   13: astore_3
    //   14: bipush #32
    //   16: newarray int
    //   18: dup
    //   19: iconst_0
    //   20: ldc 943331329
    //   22: iastore
    //   23: dup
    //   24: iconst_1
    //   25: ldc 170788368
    //   27: iastore
    //   28: dup
    //   29: iconst_2
    //   30: ldc 1008414755
    //   32: iastore
    //   33: dup
    //   34: iconst_3
    //   35: ldc 187049985
    //   37: iastore
    //   38: dup
    //   39: iconst_4
    //   40: ldc 1010368540
    //   42: iastore
    //   43: dup
    //   44: iconst_5
    //   45: ldc 220604441
    //   47: iastore
    //   48: dup
    //   49: bipush #6
    //   51: ldc 940377620
    //   53: iastore
    //   54: dup
    //   55: bipush #7
    //   57: ldc 255209728
    //   59: iastore
    //   60: dup
    //   61: bipush #8
    //   63: ldc 689771012
    //   65: iastore
    //   66: dup
    //   67: bipush #9
    //   69: ldc 221709344
    //   71: iastore
    //   72: dup
    //   73: bipush #10
    //   75: ldc 957157408
    //   77: iastore
    //   78: dup
    //   79: bipush #11
    //   81: ldc 892536332
    //   83: iastore
    //   84: dup
    //   85: bipush #12
    //   87: ldc 722417666
    //   89: iastore
    //   90: dup
    //   91: bipush #13
    //   93: ldc 1026621720
    //   95: iastore
    //   96: dup
    //   97: bipush #14
    //   99: ldc 655302664
    //   101: iastore
    //   102: dup
    //   103: bipush #15
    //   105: ldc 890966315
    //   107: iastore
    //   108: dup
    //   109: bipush #16
    //   111: ldc 187632156
    //   113: iastore
    //   114: dup
    //   115: bipush #17
    //   117: ldc 874189824
    //   119: iastore
    //   120: dup
    //   121: bipush #18
    //   123: ldc 254150144
    //   125: iastore
    //   126: dup
    //   127: bipush #19
    //   129: ldc 924386310
    //   131: iastore
    //   132: dup
    //   133: bipush #20
    //   135: ldc 121057538
    //   137: iastore
    //   138: dup
    //   139: bipush #21
    //   141: ldc 840500228
    //   143: iastore
    //   144: dup
    //   145: bipush #22
    //   147: ldc 389160971
    //   149: iastore
    //   150: dup
    //   151: bipush #23
    //   153: ldc 907870729
    //   155: iastore
    //   156: dup
    //   157: bipush #24
    //   159: ldc 389426184
    //   161: iastore
    //   162: dup
    //   163: bipush #25
    //   165: ldc 973875457
    //   167: iastore
    //   168: dup
    //   169: bipush #26
    //   171: ldc 372376604
    //   173: iastore
    //   174: dup
    //   175: bipush #27
    //   177: ldc 707731490
    //   179: iastore
    //   180: dup
    //   181: bipush #28
    //   183: ldc 1043334948
    //   185: iastore
    //   186: dup
    //   187: bipush #29
    //   189: ldc 439222784
    //   191: iastore
    //   192: dup
    //   193: bipush #30
    //   195: ldc 876216579
    //   197: iastore
    //   198: dup
    //   199: bipush #31
    //   201: ldc 455999525
    //   203: iastore
    //   204: astore #5
    //   206: bipush #8
    //   208: aload_3
    //   209: arraylength
    //   210: bipush #8
    //   212: irem
    //   213: isub
    //   214: istore #6
    //   216: aload_3
    //   217: arraylength
    //   218: iload #6
    //   220: iadd
    //   221: newarray byte
    //   223: astore #7
    //   225: iconst_0
    //   226: istore #8
    //   228: iload #8
    //   230: aload_3
    //   231: arraylength
    //   232: if_icmpge -> 251
    //   235: aload #7
    //   237: iload #8
    //   239: aload_3
    //   240: iload #8
    //   242: baload
    //   243: bastore
    //   244: iinc #8, 1
    //   247: iload_2
    //   248: ifeq -> 228
    //   251: aload_3
    //   252: arraylength
    //   253: istore #8
    //   255: iload #8
    //   257: aload #7
    //   259: arraylength
    //   260: if_icmpge -> 278
    //   263: aload #7
    //   265: iload #8
    //   267: iload #6
    //   269: i2b
    //   270: bastore
    //   271: iinc #8, 1
    //   274: iload_2
    //   275: ifeq -> 255
    //   278: aload #7
    //   280: astore_3
    //   281: bipush #64
    //   283: newarray int
    //   285: dup
    //   286: iconst_0
    //   287: ldc 16843776
    //   289: iastore
    //   290: dup
    //   291: iconst_1
    //   292: iconst_0
    //   293: iastore
    //   294: dup
    //   295: iconst_2
    //   296: ldc 65536
    //   298: iastore
    //   299: dup
    //   300: iconst_3
    //   301: ldc 16843780
    //   303: iastore
    //   304: dup
    //   305: iconst_4
    //   306: ldc 16842756
    //   308: iastore
    //   309: dup
    //   310: iconst_5
    //   311: ldc 66564
    //   313: iastore
    //   314: dup
    //   315: bipush #6
    //   317: iconst_4
    //   318: iastore
    //   319: dup
    //   320: bipush #7
    //   322: ldc 65536
    //   324: iastore
    //   325: dup
    //   326: bipush #8
    //   328: sipush #1024
    //   331: iastore
    //   332: dup
    //   333: bipush #9
    //   335: ldc 16843776
    //   337: iastore
    //   338: dup
    //   339: bipush #10
    //   341: ldc 16843780
    //   343: iastore
    //   344: dup
    //   345: bipush #11
    //   347: sipush #1024
    //   350: iastore
    //   351: dup
    //   352: bipush #12
    //   354: ldc 16778244
    //   356: iastore
    //   357: dup
    //   358: bipush #13
    //   360: ldc 16842756
    //   362: iastore
    //   363: dup
    //   364: bipush #14
    //   366: ldc 16777216
    //   368: iastore
    //   369: dup
    //   370: bipush #15
    //   372: iconst_4
    //   373: iastore
    //   374: dup
    //   375: bipush #16
    //   377: sipush #1028
    //   380: iastore
    //   381: dup
    //   382: bipush #17
    //   384: ldc 16778240
    //   386: iastore
    //   387: dup
    //   388: bipush #18
    //   390: ldc 16778240
    //   392: iastore
    //   393: dup
    //   394: bipush #19
    //   396: ldc 66560
    //   398: iastore
    //   399: dup
    //   400: bipush #20
    //   402: ldc 66560
    //   404: iastore
    //   405: dup
    //   406: bipush #21
    //   408: ldc 16842752
    //   410: iastore
    //   411: dup
    //   412: bipush #22
    //   414: ldc 16842752
    //   416: iastore
    //   417: dup
    //   418: bipush #23
    //   420: ldc 16778244
    //   422: iastore
    //   423: dup
    //   424: bipush #24
    //   426: ldc 65540
    //   428: iastore
    //   429: dup
    //   430: bipush #25
    //   432: ldc 16777220
    //   434: iastore
    //   435: dup
    //   436: bipush #26
    //   438: ldc 16777220
    //   440: iastore
    //   441: dup
    //   442: bipush #27
    //   444: ldc 65540
    //   446: iastore
    //   447: dup
    //   448: bipush #28
    //   450: iconst_0
    //   451: iastore
    //   452: dup
    //   453: bipush #29
    //   455: sipush #1028
    //   458: iastore
    //   459: dup
    //   460: bipush #30
    //   462: ldc 66564
    //   464: iastore
    //   465: dup
    //   466: bipush #31
    //   468: ldc 16777216
    //   470: iastore
    //   471: dup
    //   472: bipush #32
    //   474: ldc 65536
    //   476: iastore
    //   477: dup
    //   478: bipush #33
    //   480: ldc 16843780
    //   482: iastore
    //   483: dup
    //   484: bipush #34
    //   486: iconst_4
    //   487: iastore
    //   488: dup
    //   489: bipush #35
    //   491: ldc 16842752
    //   493: iastore
    //   494: dup
    //   495: bipush #36
    //   497: ldc 16843776
    //   499: iastore
    //   500: dup
    //   501: bipush #37
    //   503: ldc 16777216
    //   505: iastore
    //   506: dup
    //   507: bipush #38
    //   509: ldc 16777216
    //   511: iastore
    //   512: dup
    //   513: bipush #39
    //   515: sipush #1024
    //   518: iastore
    //   519: dup
    //   520: bipush #40
    //   522: ldc 16842756
    //   524: iastore
    //   525: dup
    //   526: bipush #41
    //   528: ldc 65536
    //   530: iastore
    //   531: dup
    //   532: bipush #42
    //   534: ldc 66560
    //   536: iastore
    //   537: dup
    //   538: bipush #43
    //   540: ldc 16777220
    //   542: iastore
    //   543: dup
    //   544: bipush #44
    //   546: sipush #1024
    //   549: iastore
    //   550: dup
    //   551: bipush #45
    //   553: iconst_4
    //   554: iastore
    //   555: dup
    //   556: bipush #46
    //   558: ldc 16778244
    //   560: iastore
    //   561: dup
    //   562: bipush #47
    //   564: ldc 66564
    //   566: iastore
    //   567: dup
    //   568: bipush #48
    //   570: ldc 16843780
    //   572: iastore
    //   573: dup
    //   574: bipush #49
    //   576: ldc 65540
    //   578: iastore
    //   579: dup
    //   580: bipush #50
    //   582: ldc 16842752
    //   584: iastore
    //   585: dup
    //   586: bipush #51
    //   588: ldc 16778244
    //   590: iastore
    //   591: dup
    //   592: bipush #52
    //   594: ldc 16777220
    //   596: iastore
    //   597: dup
    //   598: bipush #53
    //   600: sipush #1028
    //   603: iastore
    //   604: dup
    //   605: bipush #54
    //   607: ldc 66564
    //   609: iastore
    //   610: dup
    //   611: bipush #55
    //   613: ldc 16843776
    //   615: iastore
    //   616: dup
    //   617: bipush #56
    //   619: sipush #1028
    //   622: iastore
    //   623: dup
    //   624: bipush #57
    //   626: ldc 16778240
    //   628: iastore
    //   629: dup
    //   630: bipush #58
    //   632: ldc 16778240
    //   634: iastore
    //   635: dup
    //   636: bipush #59
    //   638: iconst_0
    //   639: iastore
    //   640: dup
    //   641: bipush #60
    //   643: ldc 65540
    //   645: iastore
    //   646: dup
    //   647: bipush #61
    //   649: ldc 66560
    //   651: iastore
    //   652: dup
    //   653: bipush #62
    //   655: iconst_0
    //   656: iastore
    //   657: dup
    //   658: bipush #63
    //   660: ldc 16842756
    //   662: iastore
    //   663: astore #8
    //   665: bipush #64
    //   667: newarray int
    //   669: dup
    //   670: iconst_0
    //   671: ldc -2146402272
    //   673: iastore
    //   674: dup
    //   675: iconst_1
    //   676: ldc -2147450880
    //   678: iastore
    //   679: dup
    //   680: iconst_2
    //   681: ldc 32768
    //   683: iastore
    //   684: dup
    //   685: iconst_3
    //   686: ldc 1081376
    //   688: iastore
    //   689: dup
    //   690: iconst_4
    //   691: ldc 1048576
    //   693: iastore
    //   694: dup
    //   695: iconst_5
    //   696: bipush #32
    //   698: iastore
    //   699: dup
    //   700: bipush #6
    //   702: ldc -2146435040
    //   704: iastore
    //   705: dup
    //   706: bipush #7
    //   708: ldc -2147450848
    //   710: iastore
    //   711: dup
    //   712: bipush #8
    //   714: ldc -2147483616
    //   716: iastore
    //   717: dup
    //   718: bipush #9
    //   720: ldc -2146402272
    //   722: iastore
    //   723: dup
    //   724: bipush #10
    //   726: ldc -2146402304
    //   728: iastore
    //   729: dup
    //   730: bipush #11
    //   732: ldc -2147483648
    //   734: iastore
    //   735: dup
    //   736: bipush #12
    //   738: ldc -2147450880
    //   740: iastore
    //   741: dup
    //   742: bipush #13
    //   744: ldc 1048576
    //   746: iastore
    //   747: dup
    //   748: bipush #14
    //   750: bipush #32
    //   752: iastore
    //   753: dup
    //   754: bipush #15
    //   756: ldc -2146435040
    //   758: iastore
    //   759: dup
    //   760: bipush #16
    //   762: ldc 1081344
    //   764: iastore
    //   765: dup
    //   766: bipush #17
    //   768: ldc 1048608
    //   770: iastore
    //   771: dup
    //   772: bipush #18
    //   774: ldc -2147450848
    //   776: iastore
    //   777: dup
    //   778: bipush #19
    //   780: iconst_0
    //   781: iastore
    //   782: dup
    //   783: bipush #20
    //   785: ldc -2147483648
    //   787: iastore
    //   788: dup
    //   789: bipush #21
    //   791: ldc 32768
    //   793: iastore
    //   794: dup
    //   795: bipush #22
    //   797: ldc 1081376
    //   799: iastore
    //   800: dup
    //   801: bipush #23
    //   803: ldc -2146435072
    //   805: iastore
    //   806: dup
    //   807: bipush #24
    //   809: ldc 1048608
    //   811: iastore
    //   812: dup
    //   813: bipush #25
    //   815: ldc -2147483616
    //   817: iastore
    //   818: dup
    //   819: bipush #26
    //   821: iconst_0
    //   822: iastore
    //   823: dup
    //   824: bipush #27
    //   826: ldc 1081344
    //   828: iastore
    //   829: dup
    //   830: bipush #28
    //   832: ldc 32800
    //   834: iastore
    //   835: dup
    //   836: bipush #29
    //   838: ldc -2146402304
    //   840: iastore
    //   841: dup
    //   842: bipush #30
    //   844: ldc -2146435072
    //   846: iastore
    //   847: dup
    //   848: bipush #31
    //   850: ldc 32800
    //   852: iastore
    //   853: dup
    //   854: bipush #32
    //   856: iconst_0
    //   857: iastore
    //   858: dup
    //   859: bipush #33
    //   861: ldc 1081376
    //   863: iastore
    //   864: dup
    //   865: bipush #34
    //   867: ldc -2146435040
    //   869: iastore
    //   870: dup
    //   871: bipush #35
    //   873: ldc 1048576
    //   875: iastore
    //   876: dup
    //   877: bipush #36
    //   879: ldc -2147450848
    //   881: iastore
    //   882: dup
    //   883: bipush #37
    //   885: ldc -2146435072
    //   887: iastore
    //   888: dup
    //   889: bipush #38
    //   891: ldc -2146402304
    //   893: iastore
    //   894: dup
    //   895: bipush #39
    //   897: ldc 32768
    //   899: iastore
    //   900: dup
    //   901: bipush #40
    //   903: ldc -2146435072
    //   905: iastore
    //   906: dup
    //   907: bipush #41
    //   909: ldc -2147450880
    //   911: iastore
    //   912: dup
    //   913: bipush #42
    //   915: bipush #32
    //   917: iastore
    //   918: dup
    //   919: bipush #43
    //   921: ldc -2146402272
    //   923: iastore
    //   924: dup
    //   925: bipush #44
    //   927: ldc 1081376
    //   929: iastore
    //   930: dup
    //   931: bipush #45
    //   933: bipush #32
    //   935: iastore
    //   936: dup
    //   937: bipush #46
    //   939: ldc 32768
    //   941: iastore
    //   942: dup
    //   943: bipush #47
    //   945: ldc -2147483648
    //   947: iastore
    //   948: dup
    //   949: bipush #48
    //   951: ldc 32800
    //   953: iastore
    //   954: dup
    //   955: bipush #49
    //   957: ldc -2146402304
    //   959: iastore
    //   960: dup
    //   961: bipush #50
    //   963: ldc 1048576
    //   965: iastore
    //   966: dup
    //   967: bipush #51
    //   969: ldc -2147483616
    //   971: iastore
    //   972: dup
    //   973: bipush #52
    //   975: ldc 1048608
    //   977: iastore
    //   978: dup
    //   979: bipush #53
    //   981: ldc -2147450848
    //   983: iastore
    //   984: dup
    //   985: bipush #54
    //   987: ldc -2147483616
    //   989: iastore
    //   990: dup
    //   991: bipush #55
    //   993: ldc 1048608
    //   995: iastore
    //   996: dup
    //   997: bipush #56
    //   999: ldc 1081344
    //   1001: iastore
    //   1002: dup
    //   1003: bipush #57
    //   1005: iconst_0
    //   1006: iastore
    //   1007: dup
    //   1008: bipush #58
    //   1010: ldc -2147450880
    //   1012: iastore
    //   1013: dup
    //   1014: bipush #59
    //   1016: ldc 32800
    //   1018: iastore
    //   1019: dup
    //   1020: bipush #60
    //   1022: ldc -2147483648
    //   1024: iastore
    //   1025: dup
    //   1026: bipush #61
    //   1028: ldc -2146435040
    //   1030: iastore
    //   1031: dup
    //   1032: bipush #62
    //   1034: ldc -2146402272
    //   1036: iastore
    //   1037: dup
    //   1038: bipush #63
    //   1040: ldc 1081344
    //   1042: iastore
    //   1043: astore #9
    //   1045: bipush #64
    //   1047: newarray int
    //   1049: dup
    //   1050: iconst_0
    //   1051: sipush #520
    //   1054: iastore
    //   1055: dup
    //   1056: iconst_1
    //   1057: ldc 134349312
    //   1059: iastore
    //   1060: dup
    //   1061: iconst_2
    //   1062: iconst_0
    //   1063: iastore
    //   1064: dup
    //   1065: iconst_3
    //   1066: ldc 134348808
    //   1068: iastore
    //   1069: dup
    //   1070: iconst_4
    //   1071: ldc 134218240
    //   1073: iastore
    //   1074: dup
    //   1075: iconst_5
    //   1076: iconst_0
    //   1077: iastore
    //   1078: dup
    //   1079: bipush #6
    //   1081: ldc 131592
    //   1083: iastore
    //   1084: dup
    //   1085: bipush #7
    //   1087: ldc 134218240
    //   1089: iastore
    //   1090: dup
    //   1091: bipush #8
    //   1093: ldc 131080
    //   1095: iastore
    //   1096: dup
    //   1097: bipush #9
    //   1099: ldc 134217736
    //   1101: iastore
    //   1102: dup
    //   1103: bipush #10
    //   1105: ldc 134217736
    //   1107: iastore
    //   1108: dup
    //   1109: bipush #11
    //   1111: ldc 131072
    //   1113: iastore
    //   1114: dup
    //   1115: bipush #12
    //   1117: ldc 134349320
    //   1119: iastore
    //   1120: dup
    //   1121: bipush #13
    //   1123: ldc 131080
    //   1125: iastore
    //   1126: dup
    //   1127: bipush #14
    //   1129: ldc 134348800
    //   1131: iastore
    //   1132: dup
    //   1133: bipush #15
    //   1135: sipush #520
    //   1138: iastore
    //   1139: dup
    //   1140: bipush #16
    //   1142: ldc 134217728
    //   1144: iastore
    //   1145: dup
    //   1146: bipush #17
    //   1148: bipush #8
    //   1150: iastore
    //   1151: dup
    //   1152: bipush #18
    //   1154: ldc 134349312
    //   1156: iastore
    //   1157: dup
    //   1158: bipush #19
    //   1160: sipush #512
    //   1163: iastore
    //   1164: dup
    //   1165: bipush #20
    //   1167: ldc 131584
    //   1169: iastore
    //   1170: dup
    //   1171: bipush #21
    //   1173: ldc 134348800
    //   1175: iastore
    //   1176: dup
    //   1177: bipush #22
    //   1179: ldc 134348808
    //   1181: iastore
    //   1182: dup
    //   1183: bipush #23
    //   1185: ldc 131592
    //   1187: iastore
    //   1188: dup
    //   1189: bipush #24
    //   1191: ldc 134218248
    //   1193: iastore
    //   1194: dup
    //   1195: bipush #25
    //   1197: ldc 131584
    //   1199: iastore
    //   1200: dup
    //   1201: bipush #26
    //   1203: ldc 131072
    //   1205: iastore
    //   1206: dup
    //   1207: bipush #27
    //   1209: ldc 134218248
    //   1211: iastore
    //   1212: dup
    //   1213: bipush #28
    //   1215: bipush #8
    //   1217: iastore
    //   1218: dup
    //   1219: bipush #29
    //   1221: ldc 134349320
    //   1223: iastore
    //   1224: dup
    //   1225: bipush #30
    //   1227: sipush #512
    //   1230: iastore
    //   1231: dup
    //   1232: bipush #31
    //   1234: ldc 134217728
    //   1236: iastore
    //   1237: dup
    //   1238: bipush #32
    //   1240: ldc 134349312
    //   1242: iastore
    //   1243: dup
    //   1244: bipush #33
    //   1246: ldc 134217728
    //   1248: iastore
    //   1249: dup
    //   1250: bipush #34
    //   1252: ldc 131080
    //   1254: iastore
    //   1255: dup
    //   1256: bipush #35
    //   1258: sipush #520
    //   1261: iastore
    //   1262: dup
    //   1263: bipush #36
    //   1265: ldc 131072
    //   1267: iastore
    //   1268: dup
    //   1269: bipush #37
    //   1271: ldc 134349312
    //   1273: iastore
    //   1274: dup
    //   1275: bipush #38
    //   1277: ldc 134218240
    //   1279: iastore
    //   1280: dup
    //   1281: bipush #39
    //   1283: iconst_0
    //   1284: iastore
    //   1285: dup
    //   1286: bipush #40
    //   1288: sipush #512
    //   1291: iastore
    //   1292: dup
    //   1293: bipush #41
    //   1295: ldc 131080
    //   1297: iastore
    //   1298: dup
    //   1299: bipush #42
    //   1301: ldc 134349320
    //   1303: iastore
    //   1304: dup
    //   1305: bipush #43
    //   1307: ldc 134218240
    //   1309: iastore
    //   1310: dup
    //   1311: bipush #44
    //   1313: ldc 134217736
    //   1315: iastore
    //   1316: dup
    //   1317: bipush #45
    //   1319: sipush #512
    //   1322: iastore
    //   1323: dup
    //   1324: bipush #46
    //   1326: iconst_0
    //   1327: iastore
    //   1328: dup
    //   1329: bipush #47
    //   1331: ldc 134348808
    //   1333: iastore
    //   1334: dup
    //   1335: bipush #48
    //   1337: ldc 134218248
    //   1339: iastore
    //   1340: dup
    //   1341: bipush #49
    //   1343: ldc 131072
    //   1345: iastore
    //   1346: dup
    //   1347: bipush #50
    //   1349: ldc 134217728
    //   1351: iastore
    //   1352: dup
    //   1353: bipush #51
    //   1355: ldc 134349320
    //   1357: iastore
    //   1358: dup
    //   1359: bipush #52
    //   1361: bipush #8
    //   1363: iastore
    //   1364: dup
    //   1365: bipush #53
    //   1367: ldc 131592
    //   1369: iastore
    //   1370: dup
    //   1371: bipush #54
    //   1373: ldc 131584
    //   1375: iastore
    //   1376: dup
    //   1377: bipush #55
    //   1379: ldc 134217736
    //   1381: iastore
    //   1382: dup
    //   1383: bipush #56
    //   1385: ldc 134348800
    //   1387: iastore
    //   1388: dup
    //   1389: bipush #57
    //   1391: ldc 134218248
    //   1393: iastore
    //   1394: dup
    //   1395: bipush #58
    //   1397: sipush #520
    //   1400: iastore
    //   1401: dup
    //   1402: bipush #59
    //   1404: ldc 134348800
    //   1406: iastore
    //   1407: dup
    //   1408: bipush #60
    //   1410: ldc 131592
    //   1412: iastore
    //   1413: dup
    //   1414: bipush #61
    //   1416: bipush #8
    //   1418: iastore
    //   1419: dup
    //   1420: bipush #62
    //   1422: ldc 134348808
    //   1424: iastore
    //   1425: dup
    //   1426: bipush #63
    //   1428: ldc 131584
    //   1430: iastore
    //   1431: astore #10
    //   1433: bipush #64
    //   1435: newarray int
    //   1437: dup
    //   1438: iconst_0
    //   1439: ldc 8396801
    //   1441: iastore
    //   1442: dup
    //   1443: iconst_1
    //   1444: sipush #8321
    //   1447: iastore
    //   1448: dup
    //   1449: iconst_2
    //   1450: sipush #8321
    //   1453: iastore
    //   1454: dup
    //   1455: iconst_3
    //   1456: sipush #128
    //   1459: iastore
    //   1460: dup
    //   1461: iconst_4
    //   1462: ldc 8396928
    //   1464: iastore
    //   1465: dup
    //   1466: iconst_5
    //   1467: ldc 8388737
    //   1469: iastore
    //   1470: dup
    //   1471: bipush #6
    //   1473: ldc 8388609
    //   1475: iastore
    //   1476: dup
    //   1477: bipush #7
    //   1479: sipush #8193
    //   1482: iastore
    //   1483: dup
    //   1484: bipush #8
    //   1486: iconst_0
    //   1487: iastore
    //   1488: dup
    //   1489: bipush #9
    //   1491: ldc 8396800
    //   1493: iastore
    //   1494: dup
    //   1495: bipush #10
    //   1497: ldc 8396800
    //   1499: iastore
    //   1500: dup
    //   1501: bipush #11
    //   1503: ldc 8396929
    //   1505: iastore
    //   1506: dup
    //   1507: bipush #12
    //   1509: sipush #129
    //   1512: iastore
    //   1513: dup
    //   1514: bipush #13
    //   1516: iconst_0
    //   1517: iastore
    //   1518: dup
    //   1519: bipush #14
    //   1521: ldc 8388736
    //   1523: iastore
    //   1524: dup
    //   1525: bipush #15
    //   1527: ldc 8388609
    //   1529: iastore
    //   1530: dup
    //   1531: bipush #16
    //   1533: iconst_1
    //   1534: iastore
    //   1535: dup
    //   1536: bipush #17
    //   1538: sipush #8192
    //   1541: iastore
    //   1542: dup
    //   1543: bipush #18
    //   1545: ldc 8388608
    //   1547: iastore
    //   1548: dup
    //   1549: bipush #19
    //   1551: ldc 8396801
    //   1553: iastore
    //   1554: dup
    //   1555: bipush #20
    //   1557: sipush #128
    //   1560: iastore
    //   1561: dup
    //   1562: bipush #21
    //   1564: ldc 8388608
    //   1566: iastore
    //   1567: dup
    //   1568: bipush #22
    //   1570: sipush #8193
    //   1573: iastore
    //   1574: dup
    //   1575: bipush #23
    //   1577: sipush #8320
    //   1580: iastore
    //   1581: dup
    //   1582: bipush #24
    //   1584: ldc 8388737
    //   1586: iastore
    //   1587: dup
    //   1588: bipush #25
    //   1590: iconst_1
    //   1591: iastore
    //   1592: dup
    //   1593: bipush #26
    //   1595: sipush #8320
    //   1598: iastore
    //   1599: dup
    //   1600: bipush #27
    //   1602: ldc 8388736
    //   1604: iastore
    //   1605: dup
    //   1606: bipush #28
    //   1608: sipush #8192
    //   1611: iastore
    //   1612: dup
    //   1613: bipush #29
    //   1615: ldc 8396928
    //   1617: iastore
    //   1618: dup
    //   1619: bipush #30
    //   1621: ldc 8396929
    //   1623: iastore
    //   1624: dup
    //   1625: bipush #31
    //   1627: sipush #129
    //   1630: iastore
    //   1631: dup
    //   1632: bipush #32
    //   1634: ldc 8388736
    //   1636: iastore
    //   1637: dup
    //   1638: bipush #33
    //   1640: ldc 8388609
    //   1642: iastore
    //   1643: dup
    //   1644: bipush #34
    //   1646: ldc 8396800
    //   1648: iastore
    //   1649: dup
    //   1650: bipush #35
    //   1652: ldc 8396929
    //   1654: iastore
    //   1655: dup
    //   1656: bipush #36
    //   1658: sipush #129
    //   1661: iastore
    //   1662: dup
    //   1663: bipush #37
    //   1665: iconst_0
    //   1666: iastore
    //   1667: dup
    //   1668: bipush #38
    //   1670: iconst_0
    //   1671: iastore
    //   1672: dup
    //   1673: bipush #39
    //   1675: ldc 8396800
    //   1677: iastore
    //   1678: dup
    //   1679: bipush #40
    //   1681: sipush #8320
    //   1684: iastore
    //   1685: dup
    //   1686: bipush #41
    //   1688: ldc 8388736
    //   1690: iastore
    //   1691: dup
    //   1692: bipush #42
    //   1694: ldc 8388737
    //   1696: iastore
    //   1697: dup
    //   1698: bipush #43
    //   1700: iconst_1
    //   1701: iastore
    //   1702: dup
    //   1703: bipush #44
    //   1705: ldc 8396801
    //   1707: iastore
    //   1708: dup
    //   1709: bipush #45
    //   1711: sipush #8321
    //   1714: iastore
    //   1715: dup
    //   1716: bipush #46
    //   1718: sipush #8321
    //   1721: iastore
    //   1722: dup
    //   1723: bipush #47
    //   1725: sipush #128
    //   1728: iastore
    //   1729: dup
    //   1730: bipush #48
    //   1732: ldc 8396929
    //   1734: iastore
    //   1735: dup
    //   1736: bipush #49
    //   1738: sipush #129
    //   1741: iastore
    //   1742: dup
    //   1743: bipush #50
    //   1745: iconst_1
    //   1746: iastore
    //   1747: dup
    //   1748: bipush #51
    //   1750: sipush #8192
    //   1753: iastore
    //   1754: dup
    //   1755: bipush #52
    //   1757: ldc 8388609
    //   1759: iastore
    //   1760: dup
    //   1761: bipush #53
    //   1763: sipush #8193
    //   1766: iastore
    //   1767: dup
    //   1768: bipush #54
    //   1770: ldc 8396928
    //   1772: iastore
    //   1773: dup
    //   1774: bipush #55
    //   1776: ldc 8388737
    //   1778: iastore
    //   1779: dup
    //   1780: bipush #56
    //   1782: sipush #8193
    //   1785: iastore
    //   1786: dup
    //   1787: bipush #57
    //   1789: sipush #8320
    //   1792: iastore
    //   1793: dup
    //   1794: bipush #58
    //   1796: ldc 8388608
    //   1798: iastore
    //   1799: dup
    //   1800: bipush #59
    //   1802: ldc 8396801
    //   1804: iastore
    //   1805: dup
    //   1806: bipush #60
    //   1808: sipush #128
    //   1811: iastore
    //   1812: dup
    //   1813: bipush #61
    //   1815: ldc 8388608
    //   1817: iastore
    //   1818: dup
    //   1819: bipush #62
    //   1821: sipush #8192
    //   1824: iastore
    //   1825: dup
    //   1826: bipush #63
    //   1828: ldc 8396928
    //   1830: iastore
    //   1831: astore #11
    //   1833: bipush #64
    //   1835: newarray int
    //   1837: dup
    //   1838: iconst_0
    //   1839: sipush #256
    //   1842: iastore
    //   1843: dup
    //   1844: iconst_1
    //   1845: ldc 34078976
    //   1847: iastore
    //   1848: dup
    //   1849: iconst_2
    //   1850: ldc 34078720
    //   1852: iastore
    //   1853: dup
    //   1854: iconst_3
    //   1855: ldc 1107296512
    //   1857: iastore
    //   1858: dup
    //   1859: iconst_4
    //   1860: ldc 524288
    //   1862: iastore
    //   1863: dup
    //   1864: iconst_5
    //   1865: sipush #256
    //   1868: iastore
    //   1869: dup
    //   1870: bipush #6
    //   1872: ldc 1073741824
    //   1874: iastore
    //   1875: dup
    //   1876: bipush #7
    //   1878: ldc 34078720
    //   1880: iastore
    //   1881: dup
    //   1882: bipush #8
    //   1884: ldc 1074266368
    //   1886: iastore
    //   1887: dup
    //   1888: bipush #9
    //   1890: ldc 524288
    //   1892: iastore
    //   1893: dup
    //   1894: bipush #10
    //   1896: ldc 33554688
    //   1898: iastore
    //   1899: dup
    //   1900: bipush #11
    //   1902: ldc 1074266368
    //   1904: iastore
    //   1905: dup
    //   1906: bipush #12
    //   1908: ldc 1107296512
    //   1910: iastore
    //   1911: dup
    //   1912: bipush #13
    //   1914: ldc 1107820544
    //   1916: iastore
    //   1917: dup
    //   1918: bipush #14
    //   1920: ldc 524544
    //   1922: iastore
    //   1923: dup
    //   1924: bipush #15
    //   1926: ldc 1073741824
    //   1928: iastore
    //   1929: dup
    //   1930: bipush #16
    //   1932: ldc 33554432
    //   1934: iastore
    //   1935: dup
    //   1936: bipush #17
    //   1938: ldc 1074266112
    //   1940: iastore
    //   1941: dup
    //   1942: bipush #18
    //   1944: ldc 1074266112
    //   1946: iastore
    //   1947: dup
    //   1948: bipush #19
    //   1950: iconst_0
    //   1951: iastore
    //   1952: dup
    //   1953: bipush #20
    //   1955: ldc 1073742080
    //   1957: iastore
    //   1958: dup
    //   1959: bipush #21
    //   1961: ldc 1107820800
    //   1963: iastore
    //   1964: dup
    //   1965: bipush #22
    //   1967: ldc 1107820800
    //   1969: iastore
    //   1970: dup
    //   1971: bipush #23
    //   1973: ldc 33554688
    //   1975: iastore
    //   1976: dup
    //   1977: bipush #24
    //   1979: ldc 1107820544
    //   1981: iastore
    //   1982: dup
    //   1983: bipush #25
    //   1985: ldc 1073742080
    //   1987: iastore
    //   1988: dup
    //   1989: bipush #26
    //   1991: iconst_0
    //   1992: iastore
    //   1993: dup
    //   1994: bipush #27
    //   1996: ldc 1107296256
    //   1998: iastore
    //   1999: dup
    //   2000: bipush #28
    //   2002: ldc 34078976
    //   2004: iastore
    //   2005: dup
    //   2006: bipush #29
    //   2008: ldc 33554432
    //   2010: iastore
    //   2011: dup
    //   2012: bipush #30
    //   2014: ldc 1107296256
    //   2016: iastore
    //   2017: dup
    //   2018: bipush #31
    //   2020: ldc 524544
    //   2022: iastore
    //   2023: dup
    //   2024: bipush #32
    //   2026: ldc 524288
    //   2028: iastore
    //   2029: dup
    //   2030: bipush #33
    //   2032: ldc 1107296512
    //   2034: iastore
    //   2035: dup
    //   2036: bipush #34
    //   2038: sipush #256
    //   2041: iastore
    //   2042: dup
    //   2043: bipush #35
    //   2045: ldc 33554432
    //   2047: iastore
    //   2048: dup
    //   2049: bipush #36
    //   2051: ldc 1073741824
    //   2053: iastore
    //   2054: dup
    //   2055: bipush #37
    //   2057: ldc 34078720
    //   2059: iastore
    //   2060: dup
    //   2061: bipush #38
    //   2063: ldc 1107296512
    //   2065: iastore
    //   2066: dup
    //   2067: bipush #39
    //   2069: ldc 1074266368
    //   2071: iastore
    //   2072: dup
    //   2073: bipush #40
    //   2075: ldc 33554688
    //   2077: iastore
    //   2078: dup
    //   2079: bipush #41
    //   2081: ldc 1073741824
    //   2083: iastore
    //   2084: dup
    //   2085: bipush #42
    //   2087: ldc 1107820544
    //   2089: iastore
    //   2090: dup
    //   2091: bipush #43
    //   2093: ldc 34078976
    //   2095: iastore
    //   2096: dup
    //   2097: bipush #44
    //   2099: ldc 1074266368
    //   2101: iastore
    //   2102: dup
    //   2103: bipush #45
    //   2105: sipush #256
    //   2108: iastore
    //   2109: dup
    //   2110: bipush #46
    //   2112: ldc 33554432
    //   2114: iastore
    //   2115: dup
    //   2116: bipush #47
    //   2118: ldc 1107820544
    //   2120: iastore
    //   2121: dup
    //   2122: bipush #48
    //   2124: ldc 1107820800
    //   2126: iastore
    //   2127: dup
    //   2128: bipush #49
    //   2130: ldc 524544
    //   2132: iastore
    //   2133: dup
    //   2134: bipush #50
    //   2136: ldc 1107296256
    //   2138: iastore
    //   2139: dup
    //   2140: bipush #51
    //   2142: ldc 1107820800
    //   2144: iastore
    //   2145: dup
    //   2146: bipush #52
    //   2148: ldc 34078720
    //   2150: iastore
    //   2151: dup
    //   2152: bipush #53
    //   2154: iconst_0
    //   2155: iastore
    //   2156: dup
    //   2157: bipush #54
    //   2159: ldc 1074266112
    //   2161: iastore
    //   2162: dup
    //   2163: bipush #55
    //   2165: ldc 1107296256
    //   2167: iastore
    //   2168: dup
    //   2169: bipush #56
    //   2171: ldc 524544
    //   2173: iastore
    //   2174: dup
    //   2175: bipush #57
    //   2177: ldc 33554688
    //   2179: iastore
    //   2180: dup
    //   2181: bipush #58
    //   2183: ldc 1073742080
    //   2185: iastore
    //   2186: dup
    //   2187: bipush #59
    //   2189: ldc 524288
    //   2191: iastore
    //   2192: dup
    //   2193: bipush #60
    //   2195: iconst_0
    //   2196: iastore
    //   2197: dup
    //   2198: bipush #61
    //   2200: ldc 1074266112
    //   2202: iastore
    //   2203: dup
    //   2204: bipush #62
    //   2206: ldc 34078976
    //   2208: iastore
    //   2209: dup
    //   2210: bipush #63
    //   2212: ldc 1073742080
    //   2214: iastore
    //   2215: astore #12
    //   2217: bipush #64
    //   2219: newarray int
    //   2221: dup
    //   2222: iconst_0
    //   2223: ldc 536870928
    //   2225: iastore
    //   2226: dup
    //   2227: iconst_1
    //   2228: ldc 541065216
    //   2230: iastore
    //   2231: dup
    //   2232: iconst_2
    //   2233: sipush #16384
    //   2236: iastore
    //   2237: dup
    //   2238: iconst_3
    //   2239: ldc 541081616
    //   2241: iastore
    //   2242: dup
    //   2243: iconst_4
    //   2244: ldc 541065216
    //   2246: iastore
    //   2247: dup
    //   2248: iconst_5
    //   2249: bipush #16
    //   2251: iastore
    //   2252: dup
    //   2253: bipush #6
    //   2255: ldc 541081616
    //   2257: iastore
    //   2258: dup
    //   2259: bipush #7
    //   2261: ldc 4194304
    //   2263: iastore
    //   2264: dup
    //   2265: bipush #8
    //   2267: ldc 536887296
    //   2269: iastore
    //   2270: dup
    //   2271: bipush #9
    //   2273: ldc 4210704
    //   2275: iastore
    //   2276: dup
    //   2277: bipush #10
    //   2279: ldc 4194304
    //   2281: iastore
    //   2282: dup
    //   2283: bipush #11
    //   2285: ldc 536870928
    //   2287: iastore
    //   2288: dup
    //   2289: bipush #12
    //   2291: ldc 4194320
    //   2293: iastore
    //   2294: dup
    //   2295: bipush #13
    //   2297: ldc 536887296
    //   2299: iastore
    //   2300: dup
    //   2301: bipush #14
    //   2303: ldc 536870912
    //   2305: iastore
    //   2306: dup
    //   2307: bipush #15
    //   2309: sipush #16400
    //   2312: iastore
    //   2313: dup
    //   2314: bipush #16
    //   2316: iconst_0
    //   2317: iastore
    //   2318: dup
    //   2319: bipush #17
    //   2321: ldc 4194320
    //   2323: iastore
    //   2324: dup
    //   2325: bipush #18
    //   2327: ldc 536887312
    //   2329: iastore
    //   2330: dup
    //   2331: bipush #19
    //   2333: sipush #16384
    //   2336: iastore
    //   2337: dup
    //   2338: bipush #20
    //   2340: ldc 4210688
    //   2342: iastore
    //   2343: dup
    //   2344: bipush #21
    //   2346: ldc 536887312
    //   2348: iastore
    //   2349: dup
    //   2350: bipush #22
    //   2352: bipush #16
    //   2354: iastore
    //   2355: dup
    //   2356: bipush #23
    //   2358: ldc 541065232
    //   2360: iastore
    //   2361: dup
    //   2362: bipush #24
    //   2364: ldc 541065232
    //   2366: iastore
    //   2367: dup
    //   2368: bipush #25
    //   2370: iconst_0
    //   2371: iastore
    //   2372: dup
    //   2373: bipush #26
    //   2375: ldc 4210704
    //   2377: iastore
    //   2378: dup
    //   2379: bipush #27
    //   2381: ldc 541081600
    //   2383: iastore
    //   2384: dup
    //   2385: bipush #28
    //   2387: sipush #16400
    //   2390: iastore
    //   2391: dup
    //   2392: bipush #29
    //   2394: ldc 4210688
    //   2396: iastore
    //   2397: dup
    //   2398: bipush #30
    //   2400: ldc 541081600
    //   2402: iastore
    //   2403: dup
    //   2404: bipush #31
    //   2406: ldc 536870912
    //   2408: iastore
    //   2409: dup
    //   2410: bipush #32
    //   2412: ldc 536887296
    //   2414: iastore
    //   2415: dup
    //   2416: bipush #33
    //   2418: bipush #16
    //   2420: iastore
    //   2421: dup
    //   2422: bipush #34
    //   2424: ldc 541065232
    //   2426: iastore
    //   2427: dup
    //   2428: bipush #35
    //   2430: ldc 4210688
    //   2432: iastore
    //   2433: dup
    //   2434: bipush #36
    //   2436: ldc 541081616
    //   2438: iastore
    //   2439: dup
    //   2440: bipush #37
    //   2442: ldc 4194304
    //   2444: iastore
    //   2445: dup
    //   2446: bipush #38
    //   2448: sipush #16400
    //   2451: iastore
    //   2452: dup
    //   2453: bipush #39
    //   2455: ldc 536870928
    //   2457: iastore
    //   2458: dup
    //   2459: bipush #40
    //   2461: ldc 4194304
    //   2463: iastore
    //   2464: dup
    //   2465: bipush #41
    //   2467: ldc 536887296
    //   2469: iastore
    //   2470: dup
    //   2471: bipush #42
    //   2473: ldc 536870912
    //   2475: iastore
    //   2476: dup
    //   2477: bipush #43
    //   2479: sipush #16400
    //   2482: iastore
    //   2483: dup
    //   2484: bipush #44
    //   2486: ldc 536870928
    //   2488: iastore
    //   2489: dup
    //   2490: bipush #45
    //   2492: ldc 541081616
    //   2494: iastore
    //   2495: dup
    //   2496: bipush #46
    //   2498: ldc 4210688
    //   2500: iastore
    //   2501: dup
    //   2502: bipush #47
    //   2504: ldc 541065216
    //   2506: iastore
    //   2507: dup
    //   2508: bipush #48
    //   2510: ldc 4210704
    //   2512: iastore
    //   2513: dup
    //   2514: bipush #49
    //   2516: ldc 541081600
    //   2518: iastore
    //   2519: dup
    //   2520: bipush #50
    //   2522: iconst_0
    //   2523: iastore
    //   2524: dup
    //   2525: bipush #51
    //   2527: ldc 541065232
    //   2529: iastore
    //   2530: dup
    //   2531: bipush #52
    //   2533: bipush #16
    //   2535: iastore
    //   2536: dup
    //   2537: bipush #53
    //   2539: sipush #16384
    //   2542: iastore
    //   2543: dup
    //   2544: bipush #54
    //   2546: ldc 541065216
    //   2548: iastore
    //   2549: dup
    //   2550: bipush #55
    //   2552: ldc 4210704
    //   2554: iastore
    //   2555: dup
    //   2556: bipush #56
    //   2558: sipush #16384
    //   2561: iastore
    //   2562: dup
    //   2563: bipush #57
    //   2565: ldc 4194320
    //   2567: iastore
    //   2568: dup
    //   2569: bipush #58
    //   2571: ldc 536887312
    //   2573: iastore
    //   2574: dup
    //   2575: bipush #59
    //   2577: iconst_0
    //   2578: iastore
    //   2579: dup
    //   2580: bipush #60
    //   2582: ldc 541081600
    //   2584: iastore
    //   2585: dup
    //   2586: bipush #61
    //   2588: ldc 536870912
    //   2590: iastore
    //   2591: dup
    //   2592: bipush #62
    //   2594: ldc 4194320
    //   2596: iastore
    //   2597: dup
    //   2598: bipush #63
    //   2600: ldc 536887312
    //   2602: iastore
    //   2603: astore #13
    //   2605: bipush #64
    //   2607: newarray int
    //   2609: dup
    //   2610: iconst_0
    //   2611: ldc 2097152
    //   2613: iastore
    //   2614: dup
    //   2615: iconst_1
    //   2616: ldc 69206018
    //   2618: iastore
    //   2619: dup
    //   2620: iconst_2
    //   2621: ldc 67110914
    //   2623: iastore
    //   2624: dup
    //   2625: iconst_3
    //   2626: iconst_0
    //   2627: iastore
    //   2628: dup
    //   2629: iconst_4
    //   2630: sipush #2048
    //   2633: iastore
    //   2634: dup
    //   2635: iconst_5
    //   2636: ldc 67110914
    //   2638: iastore
    //   2639: dup
    //   2640: bipush #6
    //   2642: ldc 2099202
    //   2644: iastore
    //   2645: dup
    //   2646: bipush #7
    //   2648: ldc 69208064
    //   2650: iastore
    //   2651: dup
    //   2652: bipush #8
    //   2654: ldc 69208066
    //   2656: iastore
    //   2657: dup
    //   2658: bipush #9
    //   2660: ldc 2097152
    //   2662: iastore
    //   2663: dup
    //   2664: bipush #10
    //   2666: iconst_0
    //   2667: iastore
    //   2668: dup
    //   2669: bipush #11
    //   2671: ldc 67108866
    //   2673: iastore
    //   2674: dup
    //   2675: bipush #12
    //   2677: iconst_2
    //   2678: iastore
    //   2679: dup
    //   2680: bipush #13
    //   2682: ldc 67108864
    //   2684: iastore
    //   2685: dup
    //   2686: bipush #14
    //   2688: ldc 69206018
    //   2690: iastore
    //   2691: dup
    //   2692: bipush #15
    //   2694: sipush #2050
    //   2697: iastore
    //   2698: dup
    //   2699: bipush #16
    //   2701: ldc 67110912
    //   2703: iastore
    //   2704: dup
    //   2705: bipush #17
    //   2707: ldc 2099202
    //   2709: iastore
    //   2710: dup
    //   2711: bipush #18
    //   2713: ldc 2097154
    //   2715: iastore
    //   2716: dup
    //   2717: bipush #19
    //   2719: ldc 67110912
    //   2721: iastore
    //   2722: dup
    //   2723: bipush #20
    //   2725: ldc 67108866
    //   2727: iastore
    //   2728: dup
    //   2729: bipush #21
    //   2731: ldc 69206016
    //   2733: iastore
    //   2734: dup
    //   2735: bipush #22
    //   2737: ldc 69208064
    //   2739: iastore
    //   2740: dup
    //   2741: bipush #23
    //   2743: ldc 2097154
    //   2745: iastore
    //   2746: dup
    //   2747: bipush #24
    //   2749: ldc 69206016
    //   2751: iastore
    //   2752: dup
    //   2753: bipush #25
    //   2755: sipush #2048
    //   2758: iastore
    //   2759: dup
    //   2760: bipush #26
    //   2762: sipush #2050
    //   2765: iastore
    //   2766: dup
    //   2767: bipush #27
    //   2769: ldc 69208066
    //   2771: iastore
    //   2772: dup
    //   2773: bipush #28
    //   2775: ldc 2099200
    //   2777: iastore
    //   2778: dup
    //   2779: bipush #29
    //   2781: iconst_2
    //   2782: iastore
    //   2783: dup
    //   2784: bipush #30
    //   2786: ldc 67108864
    //   2788: iastore
    //   2789: dup
    //   2790: bipush #31
    //   2792: ldc 2099200
    //   2794: iastore
    //   2795: dup
    //   2796: bipush #32
    //   2798: ldc 67108864
    //   2800: iastore
    //   2801: dup
    //   2802: bipush #33
    //   2804: ldc 2099200
    //   2806: iastore
    //   2807: dup
    //   2808: bipush #34
    //   2810: ldc 2097152
    //   2812: iastore
    //   2813: dup
    //   2814: bipush #35
    //   2816: ldc 67110914
    //   2818: iastore
    //   2819: dup
    //   2820: bipush #36
    //   2822: ldc 67110914
    //   2824: iastore
    //   2825: dup
    //   2826: bipush #37
    //   2828: ldc 69206018
    //   2830: iastore
    //   2831: dup
    //   2832: bipush #38
    //   2834: ldc 69206018
    //   2836: iastore
    //   2837: dup
    //   2838: bipush #39
    //   2840: iconst_2
    //   2841: iastore
    //   2842: dup
    //   2843: bipush #40
    //   2845: ldc 2097154
    //   2847: iastore
    //   2848: dup
    //   2849: bipush #41
    //   2851: ldc 67108864
    //   2853: iastore
    //   2854: dup
    //   2855: bipush #42
    //   2857: ldc 67110912
    //   2859: iastore
    //   2860: dup
    //   2861: bipush #43
    //   2863: ldc 2097152
    //   2865: iastore
    //   2866: dup
    //   2867: bipush #44
    //   2869: ldc 69208064
    //   2871: iastore
    //   2872: dup
    //   2873: bipush #45
    //   2875: sipush #2050
    //   2878: iastore
    //   2879: dup
    //   2880: bipush #46
    //   2882: ldc 2099202
    //   2884: iastore
    //   2885: dup
    //   2886: bipush #47
    //   2888: ldc 69208064
    //   2890: iastore
    //   2891: dup
    //   2892: bipush #48
    //   2894: sipush #2050
    //   2897: iastore
    //   2898: dup
    //   2899: bipush #49
    //   2901: ldc 67108866
    //   2903: iastore
    //   2904: dup
    //   2905: bipush #50
    //   2907: ldc 69208066
    //   2909: iastore
    //   2910: dup
    //   2911: bipush #51
    //   2913: ldc 69206016
    //   2915: iastore
    //   2916: dup
    //   2917: bipush #52
    //   2919: ldc 2099200
    //   2921: iastore
    //   2922: dup
    //   2923: bipush #53
    //   2925: iconst_0
    //   2926: iastore
    //   2927: dup
    //   2928: bipush #54
    //   2930: iconst_2
    //   2931: iastore
    //   2932: dup
    //   2933: bipush #55
    //   2935: ldc 69208066
    //   2937: iastore
    //   2938: dup
    //   2939: bipush #56
    //   2941: iconst_0
    //   2942: iastore
    //   2943: dup
    //   2944: bipush #57
    //   2946: ldc 2099202
    //   2948: iastore
    //   2949: dup
    //   2950: bipush #58
    //   2952: ldc 69206016
    //   2954: iastore
    //   2955: dup
    //   2956: bipush #59
    //   2958: sipush #2048
    //   2961: iastore
    //   2962: dup
    //   2963: bipush #60
    //   2965: ldc 67108866
    //   2967: iastore
    //   2968: dup
    //   2969: bipush #61
    //   2971: ldc 67110912
    //   2973: iastore
    //   2974: dup
    //   2975: bipush #62
    //   2977: sipush #2048
    //   2980: iastore
    //   2981: dup
    //   2982: bipush #63
    //   2984: ldc 2097154
    //   2986: iastore
    //   2987: astore #14
    //   2989: bipush #64
    //   2991: newarray int
    //   2993: dup
    //   2994: iconst_0
    //   2995: ldc 268439616
    //   2997: iastore
    //   2998: dup
    //   2999: iconst_1
    //   3000: sipush #4096
    //   3003: iastore
    //   3004: dup
    //   3005: iconst_2
    //   3006: ldc 262144
    //   3008: iastore
    //   3009: dup
    //   3010: iconst_3
    //   3011: ldc 268701760
    //   3013: iastore
    //   3014: dup
    //   3015: iconst_4
    //   3016: ldc 268435456
    //   3018: iastore
    //   3019: dup
    //   3020: iconst_5
    //   3021: ldc 268439616
    //   3023: iastore
    //   3024: dup
    //   3025: bipush #6
    //   3027: bipush #64
    //   3029: iastore
    //   3030: dup
    //   3031: bipush #7
    //   3033: ldc 268435456
    //   3035: iastore
    //   3036: dup
    //   3037: bipush #8
    //   3039: ldc 262208
    //   3041: iastore
    //   3042: dup
    //   3043: bipush #9
    //   3045: ldc 268697600
    //   3047: iastore
    //   3048: dup
    //   3049: bipush #10
    //   3051: ldc 268701760
    //   3053: iastore
    //   3054: dup
    //   3055: bipush #11
    //   3057: ldc 266240
    //   3059: iastore
    //   3060: dup
    //   3061: bipush #12
    //   3063: ldc 268701696
    //   3065: iastore
    //   3066: dup
    //   3067: bipush #13
    //   3069: ldc 266304
    //   3071: iastore
    //   3072: dup
    //   3073: bipush #14
    //   3075: sipush #4096
    //   3078: iastore
    //   3079: dup
    //   3080: bipush #15
    //   3082: bipush #64
    //   3084: iastore
    //   3085: dup
    //   3086: bipush #16
    //   3088: ldc 268697600
    //   3090: iastore
    //   3091: dup
    //   3092: bipush #17
    //   3094: ldc 268435520
    //   3096: iastore
    //   3097: dup
    //   3098: bipush #18
    //   3100: ldc 268439552
    //   3102: iastore
    //   3103: dup
    //   3104: bipush #19
    //   3106: sipush #4160
    //   3109: iastore
    //   3110: dup
    //   3111: bipush #20
    //   3113: ldc 266240
    //   3115: iastore
    //   3116: dup
    //   3117: bipush #21
    //   3119: ldc 262208
    //   3121: iastore
    //   3122: dup
    //   3123: bipush #22
    //   3125: ldc 268697664
    //   3127: iastore
    //   3128: dup
    //   3129: bipush #23
    //   3131: ldc 268701696
    //   3133: iastore
    //   3134: dup
    //   3135: bipush #24
    //   3137: sipush #4160
    //   3140: iastore
    //   3141: dup
    //   3142: bipush #25
    //   3144: iconst_0
    //   3145: iastore
    //   3146: dup
    //   3147: bipush #26
    //   3149: iconst_0
    //   3150: iastore
    //   3151: dup
    //   3152: bipush #27
    //   3154: ldc 268697664
    //   3156: iastore
    //   3157: dup
    //   3158: bipush #28
    //   3160: ldc 268435520
    //   3162: iastore
    //   3163: dup
    //   3164: bipush #29
    //   3166: ldc 268439552
    //   3168: iastore
    //   3169: dup
    //   3170: bipush #30
    //   3172: ldc 266304
    //   3174: iastore
    //   3175: dup
    //   3176: bipush #31
    //   3178: ldc 262144
    //   3180: iastore
    //   3181: dup
    //   3182: bipush #32
    //   3184: ldc 266304
    //   3186: iastore
    //   3187: dup
    //   3188: bipush #33
    //   3190: ldc 262144
    //   3192: iastore
    //   3193: dup
    //   3194: bipush #34
    //   3196: ldc 268701696
    //   3198: iastore
    //   3199: dup
    //   3200: bipush #35
    //   3202: sipush #4096
    //   3205: iastore
    //   3206: dup
    //   3207: bipush #36
    //   3209: bipush #64
    //   3211: iastore
    //   3212: dup
    //   3213: bipush #37
    //   3215: ldc 268697664
    //   3217: iastore
    //   3218: dup
    //   3219: bipush #38
    //   3221: sipush #4096
    //   3224: iastore
    //   3225: dup
    //   3226: bipush #39
    //   3228: ldc 266304
    //   3230: iastore
    //   3231: dup
    //   3232: bipush #40
    //   3234: ldc 268439552
    //   3236: iastore
    //   3237: dup
    //   3238: bipush #41
    //   3240: bipush #64
    //   3242: iastore
    //   3243: dup
    //   3244: bipush #42
    //   3246: ldc 268435520
    //   3248: iastore
    //   3249: dup
    //   3250: bipush #43
    //   3252: ldc 268697600
    //   3254: iastore
    //   3255: dup
    //   3256: bipush #44
    //   3258: ldc 268697664
    //   3260: iastore
    //   3261: dup
    //   3262: bipush #45
    //   3264: ldc 268435456
    //   3266: iastore
    //   3267: dup
    //   3268: bipush #46
    //   3270: ldc 262144
    //   3272: iastore
    //   3273: dup
    //   3274: bipush #47
    //   3276: ldc 268439616
    //   3278: iastore
    //   3279: dup
    //   3280: bipush #48
    //   3282: iconst_0
    //   3283: iastore
    //   3284: dup
    //   3285: bipush #49
    //   3287: ldc 268701760
    //   3289: iastore
    //   3290: dup
    //   3291: bipush #50
    //   3293: ldc 262208
    //   3295: iastore
    //   3296: dup
    //   3297: bipush #51
    //   3299: ldc 268435520
    //   3301: iastore
    //   3302: dup
    //   3303: bipush #52
    //   3305: ldc 268697600
    //   3307: iastore
    //   3308: dup
    //   3309: bipush #53
    //   3311: ldc 268439552
    //   3313: iastore
    //   3314: dup
    //   3315: bipush #54
    //   3317: ldc 268439616
    //   3319: iastore
    //   3320: dup
    //   3321: bipush #55
    //   3323: iconst_0
    //   3324: iastore
    //   3325: dup
    //   3326: bipush #56
    //   3328: ldc 268701760
    //   3330: iastore
    //   3331: dup
    //   3332: bipush #57
    //   3334: ldc 266240
    //   3336: iastore
    //   3337: dup
    //   3338: bipush #58
    //   3340: ldc 266240
    //   3342: iastore
    //   3343: dup
    //   3344: bipush #59
    //   3346: sipush #4160
    //   3349: iastore
    //   3350: dup
    //   3351: bipush #60
    //   3353: sipush #4160
    //   3356: iastore
    //   3357: dup
    //   3358: bipush #61
    //   3360: ldc 262208
    //   3362: iastore
    //   3363: dup
    //   3364: bipush #62
    //   3366: ldc 268435456
    //   3368: iastore
    //   3369: dup
    //   3370: bipush #63
    //   3372: ldc 268701696
    //   3374: iastore
    //   3375: astore #15
    //   3377: aload_3
    //   3378: arraylength
    //   3379: istore #16
    //   3381: iconst_2
    //   3382: newarray int
    //   3384: astore #17
    //   3386: iload #16
    //   3388: newarray byte
    //   3390: astore #4
    //   3392: iload #16
    //   3394: bipush #8
    //   3396: idiv
    //   3397: istore #18
    //   3399: iconst_0
    //   3400: istore #19
    //   3402: iload #19
    //   3404: iload #18
    //   3406: if_icmpge -> 4320
    //   3409: iload #19
    //   3411: bipush #8
    //   3413: imul
    //   3414: istore #20
    //   3416: iconst_0
    //   3417: istore #21
    //   3419: iload #21
    //   3421: iconst_2
    //   3422: if_icmpge -> 3507
    //   3425: aload #17
    //   3427: iload #21
    //   3429: aload_3
    //   3430: iload #20
    //   3432: iload #21
    //   3434: iconst_4
    //   3435: imul
    //   3436: iadd
    //   3437: baload
    //   3438: sipush #255
    //   3441: iand
    //   3442: bipush #24
    //   3444: ishl
    //   3445: aload_3
    //   3446: iload #20
    //   3448: iload #21
    //   3450: iconst_4
    //   3451: imul
    //   3452: iadd
    //   3453: iconst_1
    //   3454: iadd
    //   3455: baload
    //   3456: sipush #255
    //   3459: iand
    //   3460: bipush #16
    //   3462: ishl
    //   3463: ior
    //   3464: aload_3
    //   3465: iload #20
    //   3467: iload #21
    //   3469: iconst_4
    //   3470: imul
    //   3471: iadd
    //   3472: iconst_2
    //   3473: iadd
    //   3474: baload
    //   3475: sipush #255
    //   3478: iand
    //   3479: bipush #8
    //   3481: ishl
    //   3482: ior
    //   3483: aload_3
    //   3484: iload #20
    //   3486: iload #21
    //   3488: iconst_4
    //   3489: imul
    //   3490: iadd
    //   3491: iconst_3
    //   3492: iadd
    //   3493: baload
    //   3494: sipush #255
    //   3497: iand
    //   3498: ior
    //   3499: iastore
    //   3500: iinc #21, 1
    //   3503: iload_2
    //   3504: ifeq -> 3419
    //   3507: iconst_0
    //   3508: istore #26
    //   3510: aload #17
    //   3512: iconst_0
    //   3513: iaload
    //   3514: istore #24
    //   3516: aload #17
    //   3518: iconst_1
    //   3519: iaload
    //   3520: istore #23
    //   3522: iload #24
    //   3524: iconst_4
    //   3525: iushr
    //   3526: iload #23
    //   3528: ixor
    //   3529: ldc 252645135
    //   3531: iand
    //   3532: istore #22
    //   3534: iload #23
    //   3536: iload #22
    //   3538: ixor
    //   3539: istore #23
    //   3541: iload #24
    //   3543: iload #22
    //   3545: iconst_4
    //   3546: ishl
    //   3547: ixor
    //   3548: istore #24
    //   3550: iload #24
    //   3552: bipush #16
    //   3554: iushr
    //   3555: iload #23
    //   3557: ixor
    //   3558: ldc 65535
    //   3560: iand
    //   3561: istore #22
    //   3563: iload #23
    //   3565: iload #22
    //   3567: ixor
    //   3568: istore #23
    //   3570: iload #24
    //   3572: iload #22
    //   3574: bipush #16
    //   3576: ishl
    //   3577: ixor
    //   3578: istore #24
    //   3580: iload #23
    //   3582: iconst_2
    //   3583: iushr
    //   3584: iload #24
    //   3586: ixor
    //   3587: ldc 858993459
    //   3589: iand
    //   3590: istore #22
    //   3592: iload #24
    //   3594: iload #22
    //   3596: ixor
    //   3597: istore #24
    //   3599: iload #23
    //   3601: iload #22
    //   3603: iconst_2
    //   3604: ishl
    //   3605: ixor
    //   3606: istore #23
    //   3608: iload #23
    //   3610: bipush #8
    //   3612: iushr
    //   3613: iload #24
    //   3615: ixor
    //   3616: ldc 16711935
    //   3618: iand
    //   3619: istore #22
    //   3621: iload #24
    //   3623: iload #22
    //   3625: ixor
    //   3626: istore #24
    //   3628: iload #23
    //   3630: iload #22
    //   3632: bipush #8
    //   3634: ishl
    //   3635: ixor
    //   3636: istore #23
    //   3638: iload #23
    //   3640: iconst_1
    //   3641: ishl
    //   3642: iload #23
    //   3644: bipush #31
    //   3646: iushr
    //   3647: iconst_1
    //   3648: iand
    //   3649: ior
    //   3650: istore #23
    //   3652: iload #24
    //   3654: iload #23
    //   3656: ixor
    //   3657: ldc -1431655766
    //   3659: iand
    //   3660: istore #22
    //   3662: iload #24
    //   3664: iload #22
    //   3666: ixor
    //   3667: istore #24
    //   3669: iload #23
    //   3671: iload #22
    //   3673: ixor
    //   3674: istore #23
    //   3676: iload #24
    //   3678: iconst_1
    //   3679: ishl
    //   3680: iload #24
    //   3682: bipush #31
    //   3684: iushr
    //   3685: iconst_1
    //   3686: iand
    //   3687: ior
    //   3688: istore #24
    //   3690: iconst_0
    //   3691: istore #25
    //   3693: iload #25
    //   3695: bipush #8
    //   3697: if_icmpge -> 4035
    //   3700: iload #23
    //   3702: bipush #28
    //   3704: ishl
    //   3705: iload #23
    //   3707: iconst_4
    //   3708: iushr
    //   3709: ior
    //   3710: istore #22
    //   3712: iload #22
    //   3714: aload #5
    //   3716: iload #26
    //   3718: iinc #26, 1
    //   3721: iaload
    //   3722: ixor
    //   3723: istore #22
    //   3725: aload #14
    //   3727: iload #22
    //   3729: bipush #63
    //   3731: iand
    //   3732: iaload
    //   3733: istore #21
    //   3735: iload #21
    //   3737: aload #12
    //   3739: iload #22
    //   3741: bipush #8
    //   3743: iushr
    //   3744: bipush #63
    //   3746: iand
    //   3747: iaload
    //   3748: ior
    //   3749: istore #21
    //   3751: iload #21
    //   3753: aload #10
    //   3755: iload #22
    //   3757: bipush #16
    //   3759: iushr
    //   3760: bipush #63
    //   3762: iand
    //   3763: iaload
    //   3764: ior
    //   3765: istore #21
    //   3767: iload #21
    //   3769: aload #8
    //   3771: iload #22
    //   3773: bipush #24
    //   3775: iushr
    //   3776: bipush #63
    //   3778: iand
    //   3779: iaload
    //   3780: ior
    //   3781: istore #21
    //   3783: iload #23
    //   3785: aload #5
    //   3787: iload #26
    //   3789: iinc #26, 1
    //   3792: iaload
    //   3793: ixor
    //   3794: istore #22
    //   3796: iload #21
    //   3798: aload #15
    //   3800: iload #22
    //   3802: bipush #63
    //   3804: iand
    //   3805: iaload
    //   3806: ior
    //   3807: istore #21
    //   3809: iload #21
    //   3811: aload #13
    //   3813: iload #22
    //   3815: bipush #8
    //   3817: iushr
    //   3818: bipush #63
    //   3820: iand
    //   3821: iaload
    //   3822: ior
    //   3823: istore #21
    //   3825: iload #21
    //   3827: aload #11
    //   3829: iload #22
    //   3831: bipush #16
    //   3833: iushr
    //   3834: bipush #63
    //   3836: iand
    //   3837: iaload
    //   3838: ior
    //   3839: istore #21
    //   3841: iload #21
    //   3843: aload #9
    //   3845: iload #22
    //   3847: bipush #24
    //   3849: iushr
    //   3850: bipush #63
    //   3852: iand
    //   3853: iaload
    //   3854: ior
    //   3855: istore #21
    //   3857: iload #24
    //   3859: iload #21
    //   3861: ixor
    //   3862: istore #24
    //   3864: iload #24
    //   3866: bipush #28
    //   3868: ishl
    //   3869: iload #24
    //   3871: iconst_4
    //   3872: iushr
    //   3873: ior
    //   3874: istore #22
    //   3876: iload #22
    //   3878: aload #5
    //   3880: iload #26
    //   3882: iinc #26, 1
    //   3885: iaload
    //   3886: ixor
    //   3887: istore #22
    //   3889: aload #14
    //   3891: iload #22
    //   3893: bipush #63
    //   3895: iand
    //   3896: iaload
    //   3897: istore #21
    //   3899: iload #21
    //   3901: aload #12
    //   3903: iload #22
    //   3905: bipush #8
    //   3907: iushr
    //   3908: bipush #63
    //   3910: iand
    //   3911: iaload
    //   3912: ior
    //   3913: istore #21
    //   3915: iload #21
    //   3917: aload #10
    //   3919: iload #22
    //   3921: bipush #16
    //   3923: iushr
    //   3924: bipush #63
    //   3926: iand
    //   3927: iaload
    //   3928: ior
    //   3929: istore #21
    //   3931: iload #21
    //   3933: aload #8
    //   3935: iload #22
    //   3937: bipush #24
    //   3939: iushr
    //   3940: bipush #63
    //   3942: iand
    //   3943: iaload
    //   3944: ior
    //   3945: istore #21
    //   3947: iload #24
    //   3949: aload #5
    //   3951: iload #26
    //   3953: iinc #26, 1
    //   3956: iaload
    //   3957: ixor
    //   3958: istore #22
    //   3960: iload #21
    //   3962: aload #15
    //   3964: iload #22
    //   3966: bipush #63
    //   3968: iand
    //   3969: iaload
    //   3970: ior
    //   3971: istore #21
    //   3973: iload #21
    //   3975: aload #13
    //   3977: iload #22
    //   3979: bipush #8
    //   3981: iushr
    //   3982: bipush #63
    //   3984: iand
    //   3985: iaload
    //   3986: ior
    //   3987: istore #21
    //   3989: iload #21
    //   3991: aload #11
    //   3993: iload #22
    //   3995: bipush #16
    //   3997: iushr
    //   3998: bipush #63
    //   4000: iand
    //   4001: iaload
    //   4002: ior
    //   4003: istore #21
    //   4005: iload #21
    //   4007: aload #9
    //   4009: iload #22
    //   4011: bipush #24
    //   4013: iushr
    //   4014: bipush #63
    //   4016: iand
    //   4017: iaload
    //   4018: ior
    //   4019: istore #21
    //   4021: iload #23
    //   4023: iload #21
    //   4025: ixor
    //   4026: istore #23
    //   4028: iinc #25, 1
    //   4031: iload_2
    //   4032: ifeq -> 3693
    //   4035: iload #23
    //   4037: bipush #31
    //   4039: ishl
    //   4040: iload #23
    //   4042: iconst_1
    //   4043: iushr
    //   4044: ior
    //   4045: istore #23
    //   4047: iload #24
    //   4049: iload #23
    //   4051: ixor
    //   4052: ldc -1431655766
    //   4054: iand
    //   4055: istore #22
    //   4057: iload #24
    //   4059: iload #22
    //   4061: ixor
    //   4062: istore #24
    //   4064: iload #23
    //   4066: iload #22
    //   4068: ixor
    //   4069: istore #23
    //   4071: iload #24
    //   4073: bipush #31
    //   4075: ishl
    //   4076: iload #24
    //   4078: iconst_1
    //   4079: iushr
    //   4080: ior
    //   4081: istore #24
    //   4083: iload #24
    //   4085: bipush #8
    //   4087: iushr
    //   4088: iload #23
    //   4090: ixor
    //   4091: ldc 16711935
    //   4093: iand
    //   4094: istore #22
    //   4096: iload #23
    //   4098: iload #22
    //   4100: ixor
    //   4101: istore #23
    //   4103: iload #24
    //   4105: iload #22
    //   4107: bipush #8
    //   4109: ishl
    //   4110: ixor
    //   4111: istore #24
    //   4113: iload #24
    //   4115: iconst_2
    //   4116: iushr
    //   4117: iload #23
    //   4119: ixor
    //   4120: ldc 858993459
    //   4122: iand
    //   4123: istore #22
    //   4125: iload #23
    //   4127: iload #22
    //   4129: ixor
    //   4130: istore #23
    //   4132: iload #24
    //   4134: iload #22
    //   4136: iconst_2
    //   4137: ishl
    //   4138: ixor
    //   4139: istore #24
    //   4141: iload #23
    //   4143: bipush #16
    //   4145: iushr
    //   4146: iload #24
    //   4148: ixor
    //   4149: ldc 65535
    //   4151: iand
    //   4152: istore #22
    //   4154: iload #24
    //   4156: iload #22
    //   4158: ixor
    //   4159: istore #24
    //   4161: iload #23
    //   4163: iload #22
    //   4165: bipush #16
    //   4167: ishl
    //   4168: ixor
    //   4169: istore #23
    //   4171: iload #23
    //   4173: iconst_4
    //   4174: iushr
    //   4175: iload #24
    //   4177: ixor
    //   4178: ldc 252645135
    //   4180: iand
    //   4181: istore #22
    //   4183: iload #24
    //   4185: iload #22
    //   4187: ixor
    //   4188: istore #24
    //   4190: iload #23
    //   4192: iload #22
    //   4194: iconst_4
    //   4195: ishl
    //   4196: ixor
    //   4197: istore #23
    //   4199: aload #17
    //   4201: iconst_0
    //   4202: iload #23
    //   4204: iastore
    //   4205: aload #17
    //   4207: iconst_1
    //   4208: iload #24
    //   4210: iastore
    //   4211: iload #19
    //   4213: bipush #8
    //   4215: imul
    //   4216: istore #27
    //   4218: iconst_0
    //   4219: istore #28
    //   4221: iload #28
    //   4223: iconst_2
    //   4224: if_icmpge -> 4313
    //   4227: aload #4
    //   4229: iload #27
    //   4231: iload #28
    //   4233: iconst_4
    //   4234: imul
    //   4235: iadd
    //   4236: aload #17
    //   4238: iload #28
    //   4240: iaload
    //   4241: bipush #24
    //   4243: iushr
    //   4244: i2b
    //   4245: bastore
    //   4246: aload #4
    //   4248: iload #27
    //   4250: iload #28
    //   4252: iconst_4
    //   4253: imul
    //   4254: iadd
    //   4255: iconst_1
    //   4256: iadd
    //   4257: aload #17
    //   4259: iload #28
    //   4261: iaload
    //   4262: bipush #16
    //   4264: iushr
    //   4265: i2b
    //   4266: bastore
    //   4267: aload #4
    //   4269: iload #27
    //   4271: iload #28
    //   4273: iconst_4
    //   4274: imul
    //   4275: iadd
    //   4276: iconst_2
    //   4277: iadd
    //   4278: aload #17
    //   4280: iload #28
    //   4282: iaload
    //   4283: bipush #8
    //   4285: iushr
    //   4286: i2b
    //   4287: bastore
    //   4288: aload #4
    //   4290: iload #27
    //   4292: iload #28
    //   4294: iconst_4
    //   4295: imul
    //   4296: iadd
    //   4297: iconst_3
    //   4298: iadd
    //   4299: aload #17
    //   4301: iload #28
    //   4303: iaload
    //   4304: i2b
    //   4305: bastore
    //   4306: iinc #28, 1
    //   4309: iload_2
    //   4310: ifeq -> 4221
    //   4313: iinc #19, 1
    //   4316: iload_2
    //   4317: ifeq -> 3402
    //   4320: new java/math/BigInteger
    //   4323: dup
    //   4324: aload #4
    //   4326: invokespecial <init> : ([B)V
    //   4329: invokevirtual abs : ()Ljava/math/BigInteger;
    //   4332: putstatic burp/Zm7x.Zv : Ljava/lang/Object;
    //   4335: new java/lang/StringBuilder
    //   4338: dup
    //   4339: invokespecial <init> : ()V
    //   4342: astore_3
    //   4343: iconst_0
    //   4344: istore #4
    //   4346: iload #4
    //   4348: bipush #32
    //   4350: if_icmpge -> 5683
    //   4353: iload #4
    //   4355: tableswitch default -> 5676, 0 -> 4496, 1 -> 4533, 2 -> 4570, 3 -> 4607, 4 -> 4644, 5 -> 4681, 6 -> 4718, 7 -> 4755, 8 -> 4792, 9 -> 4829, 10 -> 4866, 11 -> 4903, 12 -> 4940, 13 -> 4977, 14 -> 5014, 15 -> 5051, 16 -> 5088, 17 -> 5125, 18 -> 5162, 19 -> 5199, 20 -> 5236, 21 -> 5273, 22 -> 5310, 23 -> 5347, 24 -> 5384, 25 -> 5421, 26 -> 5458, 27 -> 5495, 28 -> 5532, 29 -> 5569, 30 -> 5606, 31 -> 5643
    //   4496: aload_3
    //   4497: getstatic burp/Zsqy.Zo : Ljava/lang/String;
    //   4500: getstatic burp/Ztfh.Zo : Ljava/lang/Object;
    //   4503: checkcast java/math/BigInteger
    //   4506: invokevirtual intValue : ()I
    //   4509: bipush #32
    //   4511: irem
    //   4512: invokestatic abs : (I)I
    //   4515: invokevirtual charAt : (I)C
    //   4518: invokevirtual append : (C)Ljava/lang/StringBuilder;
    //   4521: pop
    //   4522: iload_2
    //   4523: ifeq -> 5676
    //   4526: goto -> 4533
    //   4529: invokestatic a : (Ljava/lang/Throwable;)Ljava/lang/Throwable;
    //   4532: athrow
    //   4533: aload_3
    //   4534: getstatic burp/Ze54.ZU : Ljava/lang/String;
    //   4537: getstatic burp/Zg_5.ZA : Ljava/lang/Object;
    //   4540: checkcast java/math/BigInteger
    //   4543: invokevirtual intValue : ()I
    //   4546: bipush #32
    //   4548: irem
    //   4549: invokestatic abs : (I)I
    //   4552: invokevirtual charAt : (I)C
    //   4555: invokevirtual append : (C)Ljava/lang/StringBuilder;
    //   4558: pop
    //   4559: iload_2
    //   4560: ifeq -> 5676
    //   4563: goto -> 4570
    //   4566: invokestatic a : (Ljava/lang/Throwable;)Ljava/lang/Throwable;
    //   4569: athrow
    //   4570: aload_3
    //   4571: getstatic burp/Zr2i.Z_ : Ljava/lang/String;
    //   4574: getstatic burp/Ztkh.Zh : Ljava/lang/Object;
    //   4577: checkcast java/math/BigInteger
    //   4580: invokevirtual intValue : ()I
    //   4583: bipush #32
    //   4585: irem
    //   4586: invokestatic abs : (I)I
    //   4589: invokevirtual charAt : (I)C
    //   4592: invokevirtual append : (C)Ljava/lang/StringBuilder;
    //   4595: pop
    //   4596: iload_2
    //   4597: ifeq -> 5676
    //   4600: goto -> 4607
    //   4603: invokestatic a : (Ljava/lang/Throwable;)Ljava/lang/Throwable;
    //   4606: athrow
    //   4607: aload_3
    //   4608: getstatic burp/Zt9_.Zf : Ljava/lang/String;
    //   4611: getstatic burp/Zk7f.Za : Ljava/lang/Object;
    //   4614: checkcast java/math/BigInteger
    //   4617: invokevirtual intValue : ()I
    //   4620: bipush #32
    //   4622: irem
    //   4623: invokestatic abs : (I)I
    //   4626: invokevirtual charAt : (I)C
    //   4629: invokevirtual append : (C)Ljava/lang/StringBuilder;
    //   4632: pop
    //   4633: iload_2
    //   4634: ifeq -> 5676
    //   4637: goto -> 4644
    //   4640: invokestatic a : (Ljava/lang/Throwable;)Ljava/lang/Throwable;
    //   4643: athrow
    //   4644: aload_3
    //   4645: getstatic burp/Zvo3.Z_ : Ljava/lang/String;
    //   4648: getstatic burp/Zm7x.Zv : Ljava/lang/Object;
    //   4651: checkcast java/math/BigInteger
    //   4654: invokevirtual intValue : ()I
    //   4657: bipush #32
    //   4659: irem
    //   4660: invokestatic abs : (I)I
    //   4663: invokevirtual charAt : (I)C
    //   4666: invokevirtual append : (C)Ljava/lang/StringBuilder;
    //   4669: pop
    //   4670: iload_2
    //   4671: ifeq -> 5676
    //   4674: goto -> 4681
    //   4677: invokestatic a : (Ljava/lang/Throwable;)Ljava/lang/Throwable;
    //   4680: athrow
    //   4681: aload_3
    //   4682: getstatic burp/Zxn5.ZI : Ljava/lang/String;
    //   4685: getstatic burp/Ze_t.Za : Ljava/lang/Object;
    //   4688: checkcast java/math/BigInteger
    //   4691: invokevirtual intValue : ()I
    //   4694: bipush #32
    //   4696: irem
    //   4697: invokestatic abs : (I)I
    //   4700: invokevirtual charAt : (I)C
    //   4703: invokevirtual append : (C)Ljava/lang/StringBuilder;
    //   4706: pop
    //   4707: iload_2
    //   4708: ifeq -> 5676
    //   4711: goto -> 4718
    //   4714: invokestatic a : (Ljava/lang/Throwable;)Ljava/lang/Throwable;
    //   4717: athrow
    //   4718: aload_3
    //   4719: getstatic burp/Zxjv.ZF : Ljava/lang/String;
    //   4722: getstatic burp/Zz6t.ZA : Ljava/lang/Object;
    //   4725: checkcast java/math/BigInteger
    //   4728: invokevirtual intValue : ()I
    //   4731: bipush #32
    //   4733: irem
    //   4734: invokestatic abs : (I)I
    //   4737: invokevirtual charAt : (I)C
    //   4740: invokevirtual append : (C)Ljava/lang/StringBuilder;
    //   4743: pop
    //   4744: iload_2
    //   4745: ifeq -> 5676
    //   4748: goto -> 4755
    //   4751: invokestatic a : (Ljava/lang/Throwable;)Ljava/lang/Throwable;
    //   4754: athrow
    //   4755: aload_3
    //   4756: getstatic burp/Zram.Ze : Ljava/lang/String;
    //   4759: getstatic burp/Zeb7.ZJ : Ljava/lang/Object;
    //   4762: checkcast java/math/BigInteger
    //   4765: invokevirtual intValue : ()I
    //   4768: bipush #32
    //   4770: irem
    //   4771: invokestatic abs : (I)I
    //   4774: invokevirtual charAt : (I)C
    //   4777: invokevirtual append : (C)Ljava/lang/StringBuilder;
    //   4780: pop
    //   4781: iload_2
    //   4782: ifeq -> 5676
    //   4785: goto -> 4792
    //   4788: invokestatic a : (Ljava/lang/Throwable;)Ljava/lang/Throwable;
    //   4791: athrow
    //   4792: aload_3
    //   4793: getstatic burp/Ze_t.ZZ : Ljava/lang/String;
    //   4796: getstatic burp/Zs4z.Ze : Ljava/lang/Object;
    //   4799: checkcast java/math/BigInteger
    //   4802: invokevirtual intValue : ()I
    //   4805: bipush #32
    //   4807: irem
    //   4808: invokestatic abs : (I)I
    //   4811: invokevirtual charAt : (I)C
    //   4814: invokevirtual append : (C)Ljava/lang/StringBuilder;
    //   4817: pop
    //   4818: iload_2
    //   4819: ifeq -> 5676
    //   4822: goto -> 4829
    //   4825: invokestatic a : (Ljava/lang/Throwable;)Ljava/lang/Throwable;
    //   4828: athrow
    //   4829: aload_3
    //   4830: getstatic burp/Zrcy.Zq : Ljava/lang/String;
    //   4833: getstatic burp/Zvo3.Ze : Ljava/lang/Object;
    //   4836: checkcast java/math/BigInteger
    //   4839: invokevirtual intValue : ()I
    //   4842: bipush #32
    //   4844: irem
    //   4845: invokestatic abs : (I)I
    //   4848: invokevirtual charAt : (I)C
    //   4851: invokevirtual append : (C)Ljava/lang/StringBuilder;
    //   4854: pop
    //   4855: iload_2
    //   4856: ifeq -> 5676
    //   4859: goto -> 4866
    //   4862: invokestatic a : (Ljava/lang/Throwable;)Ljava/lang/Throwable;
    //   4865: athrow
    //   4866: aload_3
    //   4867: getstatic burp/Zr2i.Z_ : Ljava/lang/String;
    //   4870: getstatic burp/Ztkh.Zh : Ljava/lang/Object;
    //   4873: checkcast java/math/BigInteger
    //   4876: invokevirtual intValue : ()I
    //   4879: bipush #32
    //   4881: irem
    //   4882: invokestatic abs : (I)I
    //   4885: invokevirtual charAt : (I)C
    //   4888: invokevirtual append : (C)Ljava/lang/StringBuilder;
    //   4891: pop
    //   4892: iload_2
    //   4893: ifeq -> 5676
    //   4896: goto -> 4903
    //   4899: invokestatic a : (Ljava/lang/Throwable;)Ljava/lang/Throwable;
    //   4902: athrow
    //   4903: aload_3
    //   4904: getstatic burp/Zg4k.ZB : Ljava/lang/String;
    //   4907: getstatic burp/Zs_3.ZZ : Ljava/lang/Object;
    //   4910: checkcast java/math/BigInteger
    //   4913: invokevirtual intValue : ()I
    //   4916: bipush #32
    //   4918: irem
    //   4919: invokestatic abs : (I)I
    //   4922: invokevirtual charAt : (I)C
    //   4925: invokevirtual append : (C)Ljava/lang/StringBuilder;
    //   4928: pop
    //   4929: iload_2
    //   4930: ifeq -> 5676
    //   4933: goto -> 4940
    //   4936: invokestatic a : (Ljava/lang/Throwable;)Ljava/lang/Throwable;
    //   4939: athrow
    //   4940: aload_3
    //   4941: getstatic burp/Ze_t.ZZ : Ljava/lang/String;
    //   4944: getstatic burp/Zm8w.Zz : Ljava/lang/Object;
    //   4947: checkcast java/math/BigInteger
    //   4950: invokevirtual intValue : ()I
    //   4953: bipush #32
    //   4955: irem
    //   4956: invokestatic abs : (I)I
    //   4959: invokevirtual charAt : (I)C
    //   4962: invokevirtual append : (C)Ljava/lang/StringBuilder;
    //   4965: pop
    //   4966: iload_2
    //   4967: ifeq -> 5676
    //   4970: goto -> 4977
    //   4973: invokestatic a : (Ljava/lang/Throwable;)Ljava/lang/Throwable;
    //   4976: athrow
    //   4977: aload_3
    //   4978: getstatic burp/Zl50.Zm : Ljava/lang/String;
    //   4981: getstatic burp/Zmx6.ZJ : Ljava/lang/Object;
    //   4984: checkcast java/math/BigInteger
    //   4987: invokevirtual intValue : ()I
    //   4990: bipush #32
    //   4992: irem
    //   4993: invokestatic abs : (I)I
    //   4996: invokevirtual charAt : (I)C
    //   4999: invokevirtual append : (C)Ljava/lang/StringBuilder;
    //   5002: pop
    //   5003: iload_2
    //   5004: ifeq -> 5676
    //   5007: goto -> 5014
    //   5010: invokestatic a : (Ljava/lang/Throwable;)Ljava/lang/Throwable;
    //   5013: athrow
    //   5014: aload_3
    //   5015: getstatic burp/Zrtv.ZA : Ljava/lang/String;
    //   5018: getstatic burp/Zzr5.Za : Ljava/lang/Object;
    //   5021: checkcast java/math/BigInteger
    //   5024: invokevirtual intValue : ()I
    //   5027: bipush #32
    //   5029: irem
    //   5030: invokestatic abs : (I)I
    //   5033: invokevirtual charAt : (I)C
    //   5036: invokevirtual append : (C)Ljava/lang/StringBuilder;
    //   5039: pop
    //   5040: iload_2
    //   5041: ifeq -> 5676
    //   5044: goto -> 5051
    //   5047: invokestatic a : (Ljava/lang/Throwable;)Ljava/lang/Throwable;
    //   5050: athrow
    //   5051: aload_3
    //   5052: getstatic burp/Zzr5.Zg : Ljava/lang/String;
    //   5055: getstatic burp/Zzgh.ZV : Ljava/lang/Object;
    //   5058: checkcast java/math/BigInteger
    //   5061: invokevirtual intValue : ()I
    //   5064: bipush #32
    //   5066: irem
    //   5067: invokestatic abs : (I)I
    //   5070: invokevirtual charAt : (I)C
    //   5073: invokevirtual append : (C)Ljava/lang/StringBuilder;
    //   5076: pop
    //   5077: iload_2
    //   5078: ifeq -> 5676
    //   5081: goto -> 5088
    //   5084: invokestatic a : (Ljava/lang/Throwable;)Ljava/lang/Throwable;
    //   5087: athrow
    //   5088: aload_3
    //   5089: getstatic burp/Zs75.Zn : Ljava/lang/String;
    //   5092: getstatic burp/Zkm0.ZI : Ljava/lang/Object;
    //   5095: checkcast java/math/BigInteger
    //   5098: invokevirtual intValue : ()I
    //   5101: bipush #32
    //   5103: irem
    //   5104: invokestatic abs : (I)I
    //   5107: invokevirtual charAt : (I)C
    //   5110: invokevirtual append : (C)Ljava/lang/StringBuilder;
    //   5113: pop
    //   5114: iload_2
    //   5115: ifeq -> 5676
    //   5118: goto -> 5125
    //   5121: invokestatic a : (Ljava/lang/Throwable;)Ljava/lang/Throwable;
    //   5124: athrow
    //   5125: aload_3
    //   5126: getstatic burp/Zm52.Ze : Ljava/lang/String;
    //   5129: getstatic burp/Zv8c.Zx : Ljava/lang/Object;
    //   5132: checkcast java/math/BigInteger
    //   5135: invokevirtual intValue : ()I
    //   5138: bipush #32
    //   5140: irem
    //   5141: invokestatic abs : (I)I
    //   5144: invokevirtual charAt : (I)C
    //   5147: invokevirtual append : (C)Ljava/lang/StringBuilder;
    //   5150: pop
    //   5151: iload_2
    //   5152: ifeq -> 5676
    //   5155: goto -> 5162
    //   5158: invokestatic a : (Ljava/lang/Throwable;)Ljava/lang/Throwable;
    //   5161: athrow
    //   5162: aload_3
    //   5163: getstatic burp/Zvo3.Z_ : Ljava/lang/String;
    //   5166: getstatic burp/Zza8.Zh : Ljava/lang/Object;
    //   5169: checkcast java/math/BigInteger
    //   5172: invokevirtual intValue : ()I
    //   5175: bipush #32
    //   5177: irem
    //   5178: invokestatic abs : (I)I
    //   5181: invokevirtual charAt : (I)C
    //   5184: invokevirtual append : (C)Ljava/lang/StringBuilder;
    //   5187: pop
    //   5188: iload_2
    //   5189: ifeq -> 5676
    //   5192: goto -> 5199
    //   5195: invokestatic a : (Ljava/lang/Throwable;)Ljava/lang/Throwable;
    //   5198: athrow
    //   5199: aload_3
    //   5200: getstatic burp/Zstb.Zd : Ljava/lang/String;
    //   5203: getstatic burp/Zs75.Zo : Ljava/lang/Object;
    //   5206: checkcast java/math/BigInteger
    //   5209: invokevirtual intValue : ()I
    //   5212: bipush #32
    //   5214: irem
    //   5215: invokestatic abs : (I)I
    //   5218: invokevirtual charAt : (I)C
    //   5221: invokevirtual append : (C)Ljava/lang/StringBuilder;
    //   5224: pop
    //   5225: iload_2
    //   5226: ifeq -> 5676
    //   5229: goto -> 5236
    //   5232: invokestatic a : (Ljava/lang/Throwable;)Ljava/lang/Throwable;
    //   5235: athrow
    //   5236: aload_3
    //   5237: getstatic burp/Zs83.ZG : Ljava/lang/String;
    //   5240: getstatic burp/Zstb.ZC : Ljava/lang/Object;
    //   5243: checkcast java/math/BigInteger
    //   5246: invokevirtual intValue : ()I
    //   5249: bipush #32
    //   5251: irem
    //   5252: invokestatic abs : (I)I
    //   5255: invokevirtual charAt : (I)C
    //   5258: invokevirtual append : (C)Ljava/lang/StringBuilder;
    //   5261: pop
    //   5262: iload_2
    //   5263: ifeq -> 5676
    //   5266: goto -> 5273
    //   5269: invokestatic a : (Ljava/lang/Throwable;)Ljava/lang/Throwable;
    //   5272: athrow
    //   5273: aload_3
    //   5274: getstatic burp/Zzo5.ZX : Ljava/lang/String;
    //   5277: getstatic burp/Zke7.Zj : Ljava/lang/Object;
    //   5280: checkcast java/math/BigInteger
    //   5283: invokevirtual intValue : ()I
    //   5286: bipush #32
    //   5288: irem
    //   5289: invokestatic abs : (I)I
    //   5292: invokevirtual charAt : (I)C
    //   5295: invokevirtual append : (C)Ljava/lang/StringBuilder;
    //   5298: pop
    //   5299: iload_2
    //   5300: ifeq -> 5676
    //   5303: goto -> 5310
    //   5306: invokestatic a : (Ljava/lang/Throwable;)Ljava/lang/Throwable;
    //   5309: athrow
    //   5310: aload_3
    //   5311: getstatic burp/Zt0t.ZR : Ljava/lang/String;
    //   5314: getstatic burp/Zxn5.Zd : Ljava/lang/Object;
    //   5317: checkcast java/math/BigInteger
    //   5320: invokevirtual intValue : ()I
    //   5323: bipush #32
    //   5325: irem
    //   5326: invokestatic abs : (I)I
    //   5329: invokevirtual charAt : (I)C
    //   5332: invokevirtual append : (C)Ljava/lang/StringBuilder;
    //   5335: pop
    //   5336: iload_2
    //   5337: ifeq -> 5676
    //   5340: goto -> 5347
    //   5343: invokestatic a : (Ljava/lang/Throwable;)Ljava/lang/Throwable;
    //   5346: athrow
    //   5347: aload_3
    //   5348: getstatic burp/Zb4a.Zi : Ljava/lang/String;
    //   5351: getstatic burp/Zg4k.ZE : Ljava/lang/Object;
    //   5354: checkcast java/math/BigInteger
    //   5357: invokevirtual intValue : ()I
    //   5360: bipush #32
    //   5362: irem
    //   5363: invokestatic abs : (I)I
    //   5366: invokevirtual charAt : (I)C
    //   5369: invokevirtual append : (C)Ljava/lang/StringBuilder;
    //   5372: pop
    //   5373: iload_2
    //   5374: ifeq -> 5676
    //   5377: goto -> 5384
    //   5380: invokestatic a : (Ljava/lang/Throwable;)Ljava/lang/Throwable;
    //   5383: athrow
    //   5384: aload_3
    //   5385: getstatic burp/Zzym.Zj : Ljava/lang/String;
    //   5388: getstatic burp/Zxjk.Zk : Ljava/lang/Object;
    //   5391: checkcast java/math/BigInteger
    //   5394: invokevirtual intValue : ()I
    //   5397: bipush #32
    //   5399: irem
    //   5400: invokestatic abs : (I)I
    //   5403: invokevirtual charAt : (I)C
    //   5406: invokevirtual append : (C)Ljava/lang/StringBuilder;
    //   5409: pop
    //   5410: iload_2
    //   5411: ifeq -> 5676
    //   5414: goto -> 5421
    //   5417: invokestatic a : (Ljava/lang/Throwable;)Ljava/lang/Throwable;
    //   5420: athrow
    //   5421: aload_3
    //   5422: getstatic burp/Zli5.Zq : Ljava/lang/String;
    //   5425: getstatic burp/Zt5j.Zn : Ljava/lang/Object;
    //   5428: checkcast java/math/BigInteger
    //   5431: invokevirtual intValue : ()I
    //   5434: bipush #32
    //   5436: irem
    //   5437: invokestatic abs : (I)I
    //   5440: invokevirtual charAt : (I)C
    //   5443: invokevirtual append : (C)Ljava/lang/StringBuilder;
    //   5446: pop
    //   5447: iload_2
    //   5448: ifeq -> 5676
    //   5451: goto -> 5458
    //   5454: invokestatic a : (Ljava/lang/Throwable;)Ljava/lang/Throwable;
    //   5457: athrow
    //   5458: aload_3
    //   5459: getstatic burp/Zzoi.ZR : Ljava/lang/String;
    //   5462: getstatic burp/Zsqy.ZV : Ljava/lang/Object;
    //   5465: checkcast java/math/BigInteger
    //   5468: invokevirtual intValue : ()I
    //   5471: bipush #32
    //   5473: irem
    //   5474: invokestatic abs : (I)I
    //   5477: invokevirtual charAt : (I)C
    //   5480: invokevirtual append : (C)Ljava/lang/StringBuilder;
    //   5483: pop
    //   5484: iload_2
    //   5485: ifeq -> 5676
    //   5488: goto -> 5495
    //   5491: invokestatic a : (Ljava/lang/Throwable;)Ljava/lang/Throwable;
    //   5494: athrow
    //   5495: aload_3
    //   5496: getstatic burp/Zv8c.ZO : Ljava/lang/String;
    //   5499: getstatic burp/Zxo7.Zi : Ljava/lang/Object;
    //   5502: checkcast java/math/BigInteger
    //   5505: invokevirtual intValue : ()I
    //   5508: bipush #32
    //   5510: irem
    //   5511: invokestatic abs : (I)I
    //   5514: invokevirtual charAt : (I)C
    //   5517: invokevirtual append : (C)Ljava/lang/StringBuilder;
    //   5520: pop
    //   5521: iload_2
    //   5522: ifeq -> 5676
    //   5525: goto -> 5532
    //   5528: invokestatic a : (Ljava/lang/Throwable;)Ljava/lang/Throwable;
    //   5531: athrow
    //   5532: aload_3
    //   5533: getstatic burp/Zlf0.ZS : Ljava/lang/String;
    //   5536: getstatic burp/Zk7f.Za : Ljava/lang/Object;
    //   5539: checkcast java/math/BigInteger
    //   5542: invokevirtual intValue : ()I
    //   5545: bipush #32
    //   5547: irem
    //   5548: invokestatic abs : (I)I
    //   5551: invokevirtual charAt : (I)C
    //   5554: invokevirtual append : (C)Ljava/lang/StringBuilder;
    //   5557: pop
    //   5558: iload_2
    //   5559: ifeq -> 5676
    //   5562: goto -> 5569
    //   5565: invokestatic a : (Ljava/lang/Throwable;)Ljava/lang/Throwable;
    //   5568: athrow
    //   5569: aload_3
    //   5570: getstatic burp/Zzoi.ZR : Ljava/lang/String;
    //   5573: getstatic burp/Zm3p.Zz : Ljava/lang/Object;
    //   5576: checkcast java/math/BigInteger
    //   5579: invokevirtual intValue : ()I
    //   5582: bipush #32
    //   5584: irem
    //   5585: invokestatic abs : (I)I
    //   5588: invokevirtual charAt : (I)C
    //   5591: invokevirtual append : (C)Ljava/lang/StringBuilder;
    //   5594: pop
    //   5595: iload_2
    //   5596: ifeq -> 5676
    //   5599: goto -> 5606
    //   5602: invokestatic a : (Ljava/lang/Throwable;)Ljava/lang/Throwable;
    //   5605: athrow
    //   5606: aload_3
    //   5607: getstatic burp/Zlo5.ZJ : Ljava/lang/String;
    //   5610: getstatic burp/Zr48.ZZ : Ljava/lang/Object;
    //   5613: checkcast java/math/BigInteger
    //   5616: invokevirtual intValue : ()I
    //   5619: bipush #32
    //   5621: irem
    //   5622: invokestatic abs : (I)I
    //   5625: invokevirtual charAt : (I)C
    //   5628: invokevirtual append : (C)Ljava/lang/StringBuilder;
    //   5631: pop
    //   5632: iload_2
    //   5633: ifeq -> 5676
    //   5636: goto -> 5643
    //   5639: invokestatic a : (Ljava/lang/Throwable;)Ljava/lang/Throwable;
    //   5642: athrow
    //   5643: aload_3
    //   5644: getstatic burp/Zeuc.Zp : Ljava/lang/String;
    //   5647: getstatic burp/Zkb_.ZG : Ljava/lang/Object;
    //   5650: checkcast java/math/BigInteger
    //   5653: invokevirtual intValue : ()I
    //   5656: bipush #32
    //   5658: irem
    //   5659: invokestatic abs : (I)I
    //   5662: invokevirtual charAt : (I)C
    //   5665: invokevirtual append : (C)Ljava/lang/StringBuilder;
    //   5668: pop
    //   5669: goto -> 5676
    //   5672: invokestatic a : (Ljava/lang/Throwable;)Ljava/lang/Throwable;
    //   5675: athrow
    //   5676: iinc #4, 1
    //   5679: iload_2
    //   5680: ifeq -> 4346
    //   5683: aload_3
    //   5684: invokevirtual toString : ()Ljava/lang/String;
    //   5687: putstatic burp/Zk7e.ZP : Ljava/lang/String;
    //   5690: sipush #13358
    //   5693: sipush #8657
    //   5696: invokestatic a : (II)Ljava/lang/String;
    //   5699: iconst_1
    //   5700: ldc burp/Zmlu
    //   5702: invokevirtual getClassLoader : ()Ljava/lang/ClassLoader;
    //   5705: invokestatic forName : (Ljava/lang/String;ZLjava/lang/ClassLoader;)Ljava/lang/Class;
    //   5708: invokevirtual getDeclaredFields : ()[Ljava/lang/reflect/Field;
    //   5711: astore #4
    //   5713: aload #4
    //   5715: arraylength
    //   5716: istore #5
    //   5718: iconst_0
    //   5719: istore #6
    //   5721: iload #6
    //   5723: iload #5
    //   5725: if_icmpge -> 5863
    //   5728: aload #4
    //   5730: iload #6
    //   5732: aaload
    //   5733: astore #7
    //   5735: aload #7
    //   5737: invokevirtual getModifiers : ()I
    //   5740: invokestatic isStatic : (I)Z
    //   5743: ifne -> 5753
    //   5746: goto -> 5856
    //   5749: invokestatic a : (Ljava/lang/Throwable;)Ljava/lang/Throwable;
    //   5752: athrow
    //   5753: aload #7
    //   5755: invokevirtual getType : ()Ljava/lang/Class;
    //   5758: astore #8
    //   5760: aload #8
    //   5762: ifnull -> 5843
    //   5765: aload #8
    //   5767: invokevirtual isPrimitive : ()Z
    //   5770: ifne -> 5843
    //   5773: goto -> 5780
    //   5776: invokestatic a : (Ljava/lang/Throwable;)Ljava/lang/Throwable;
    //   5779: athrow
    //   5780: aload #8
    //   5782: invokevirtual getPackage : ()Ljava/lang/Package;
    //   5785: ifnull -> 5843
    //   5788: goto -> 5795
    //   5791: invokestatic a : (Ljava/lang/Throwable;)Ljava/lang/Throwable;
    //   5794: athrow
    //   5795: aload #8
    //   5797: invokevirtual getPackage : ()Ljava/lang/Package;
    //   5800: invokevirtual getName : ()Ljava/lang/String;
    //   5803: ifnull -> 5843
    //   5806: goto -> 5813
    //   5809: invokestatic a : (Ljava/lang/Throwable;)Ljava/lang/Throwable;
    //   5812: athrow
    //   5813: aload #8
    //   5815: invokevirtual getPackage : ()Ljava/lang/Package;
    //   5818: invokevirtual getName : ()Ljava/lang/String;
    //   5821: sipush #13357
    //   5824: sipush #12880
    //   5827: invokestatic a : (II)Ljava/lang/String;
    //   5830: invokevirtual startsWith : (Ljava/lang/String;)Z
    //   5833: ifne -> 5843
    //   5836: goto -> 5843
    //   5839: invokestatic a : (Ljava/lang/Throwable;)Ljava/lang/Throwable;
    //   5842: athrow
    //   5843: aload #7
    //   5845: iconst_1
    //   5846: invokevirtual setAccessible : (Z)V
    //   5849: aload #7
    //   5851: aconst_null
    //   5852: invokevirtual get : (Ljava/lang/Object;)Ljava/lang/Object;
    //   5855: pop
    //   5856: iinc #6, 1
    //   5859: iload_2
    //   5860: ifeq -> 5721
    //   5863: sipush #13350
    //   5866: sipush #9203
    //   5869: invokestatic a : (II)Ljava/lang/String;
    //   5872: invokestatic forName : (Ljava/lang/String;)Ljava/lang/Class;
    //   5875: invokevirtual getDeclaredMethods : ()[Ljava/lang/reflect/Method;
    //   5878: astore #4
    //   5880: aload #4
    //   5882: arraylength
    //   5883: istore #5
    //   5885: iconst_0
    //   5886: istore #6
    //   5888: iload #6
    //   5890: iload #5
    //   5892: if_icmpge -> 6025
    //   5895: aload #4
    //   5897: iload #6
    //   5899: aaload
    //   5900: astore #7
    //   5902: aload #7
    //   5904: invokevirtual getParameterTypes : ()[Ljava/lang/Class;
    //   5907: pop
    //   5908: aload #7
    //   5910: invokevirtual getModifiers : ()I
    //   5913: invokestatic isStatic : (I)Z
    //   5916: ifeq -> 6011
    //   5919: aload #7
    //   5921: invokevirtual getParameterTypes : ()[Ljava/lang/Class;
    //   5924: arraylength
    //   5925: iconst_2
    //   5926: if_icmpne -> 6011
    //   5929: goto -> 5936
    //   5932: invokestatic a : (Ljava/lang/Throwable;)Ljava/lang/Throwable;
    //   5935: athrow
    //   5936: aload #7
    //   5938: invokevirtual getReturnType : ()Ljava/lang/Class;
    //   5941: getstatic java/lang/Void.TYPE : Ljava/lang/Class;
    //   5944: invokevirtual equals : (Ljava/lang/Object;)Z
    //   5947: ifeq -> 6011
    //   5950: goto -> 5957
    //   5953: invokestatic a : (Ljava/lang/Throwable;)Ljava/lang/Throwable;
    //   5956: athrow
    //   5957: aload #7
    //   5959: iconst_1
    //   5960: invokevirtual setAccessible : (Z)V
    //   5963: aload #7
    //   5965: aconst_null
    //   5966: iconst_2
    //   5967: anewarray java/lang/Object
    //   5970: dup
    //   5971: iconst_0
    //   5972: aload_0
    //   5973: aastore
    //   5974: dup
    //   5975: iconst_1
    //   5976: aload_1
    //   5977: ifnonnull -> 5995
    //   5980: goto -> 5987
    //   5983: invokestatic a : (Ljava/lang/Throwable;)Ljava/lang/Throwable;
    //   5986: athrow
    //   5987: aload_1
    //   5988: goto -> 6002
    //   5991: invokestatic a : (Ljava/lang/Throwable;)Ljava/lang/Throwable;
    //   5994: athrow
    //   5995: aload_1
    //   5996: checkcast [B
    //   5999: invokevirtual clone : ()Ljava/lang/Object;
    //   6002: aastore
    //   6003: invokevirtual invoke : (Ljava/lang/Object;[Ljava/lang/Object;)Ljava/lang/Object;
    //   6006: pop
    //   6007: iload_2
    //   6008: ifeq -> 6025
    //   6011: iinc #6, 1
    //   6014: iload_2
    //   6015: ifeq -> 5888
    //   6018: goto -> 6025
    //   6021: invokestatic a : (Ljava/lang/Throwable;)Ljava/lang/Throwable;
    //   6024: athrow
    //   6025: iconst_0
    //   6026: istore #4
    //   6028: getstatic burp/Zkjr.Zg : Ljava/lang/String;
    //   6031: getstatic burp/Zk7e.ZW : Ljava/lang/Object;
    //   6034: checkcast java/math/BigInteger
    //   6037: invokevirtual intValue : ()I
    //   6040: bipush #32
    //   6042: irem
    //   6043: invokestatic abs : (I)I
    //   6046: invokevirtual charAt : (I)C
    //   6049: getstatic burp/Ztdd.ZA : Ljava/lang/String;
    //   6052: getstatic burp/Zeuc.Zd : Ljava/lang/Object;
    //   6055: checkcast java/math/BigInteger
    //   6058: invokevirtual intValue : ()I
    //   6061: bipush #32
    //   6063: irem
    //   6064: invokestatic abs : (I)I
    //   6067: invokevirtual charAt : (I)C
    //   6070: if_icmpgt -> 6415
    //   6073: sipush #13370
    //   6076: sipush #-858
    //   6079: invokestatic a : (II)Ljava/lang/String;
    //   6082: iconst_1
    //   6083: ldc burp/Zl1u
    //   6085: invokevirtual getClassLoader : ()Ljava/lang/ClassLoader;
    //   6088: invokestatic forName : (Ljava/lang/String;ZLjava/lang/ClassLoader;)Ljava/lang/Class;
    //   6091: invokevirtual getDeclaredFields : ()[Ljava/lang/reflect/Field;
    //   6094: astore #5
    //   6096: aload #5
    //   6098: arraylength
    //   6099: istore #6
    //   6101: iconst_0
    //   6102: istore #7
    //   6104: iload #7
    //   6106: iload #6
    //   6108: if_icmpge -> 6246
    //   6111: aload #5
    //   6113: iload #7
    //   6115: aaload
    //   6116: astore #8
    //   6118: aload #8
    //   6120: invokevirtual getModifiers : ()I
    //   6123: invokestatic isStatic : (I)Z
    //   6126: ifne -> 6136
    //   6129: goto -> 6239
    //   6132: invokestatic a : (Ljava/lang/Throwable;)Ljava/lang/Throwable;
    //   6135: athrow
    //   6136: aload #8
    //   6138: invokevirtual getType : ()Ljava/lang/Class;
    //   6141: astore #9
    //   6143: aload #9
    //   6145: ifnull -> 6226
    //   6148: aload #9
    //   6150: invokevirtual isPrimitive : ()Z
    //   6153: ifne -> 6226
    //   6156: goto -> 6163
    //   6159: invokestatic a : (Ljava/lang/Throwable;)Ljava/lang/Throwable;
    //   6162: athrow
    //   6163: aload #9
    //   6165: invokevirtual getPackage : ()Ljava/lang/Package;
    //   6168: ifnull -> 6226
    //   6171: goto -> 6178
    //   6174: invokestatic a : (Ljava/lang/Throwable;)Ljava/lang/Throwable;
    //   6177: athrow
    //   6178: aload #9
    //   6180: invokevirtual getPackage : ()Ljava/lang/Package;
    //   6183: invokevirtual getName : ()Ljava/lang/String;
    //   6186: ifnull -> 6226
    //   6189: goto -> 6196
    //   6192: invokestatic a : (Ljava/lang/Throwable;)Ljava/lang/Throwable;
    //   6195: athrow
    //   6196: aload #9
    //   6198: invokevirtual getPackage : ()Ljava/lang/Package;
    //   6201: invokevirtual getName : ()Ljava/lang/String;
    //   6204: sipush #13369
    //   6207: sipush #-18970
    //   6210: invokestatic a : (II)Ljava/lang/String;
    //   6213: invokevirtual startsWith : (Ljava/lang/String;)Z
    //   6216: ifne -> 6226
    //   6219: goto -> 6226
    //   6222: invokestatic a : (Ljava/lang/Throwable;)Ljava/lang/Throwable;
    //   6225: athrow
    //   6226: aload #8
    //   6228: iconst_1
    //   6229: invokevirtual setAccessible : (Z)V
    //   6232: aload #8
    //   6234: aconst_null
    //   6235: invokevirtual get : (Ljava/lang/Object;)Ljava/lang/Object;
    //   6238: pop
    //   6239: iinc #7, 1
    //   6242: iload_2
    //   6243: ifeq -> 6104
    //   6246: sipush #13371
    //   6249: sipush #-26567
    //   6252: invokestatic a : (II)Ljava/lang/String;
    //   6255: invokestatic forName : (Ljava/lang/String;)Ljava/lang/Class;
    //   6258: invokevirtual getDeclaredMethods : ()[Ljava/lang/reflect/Method;
    //   6261: astore #5
    //   6263: aload #5
    //   6265: arraylength
    //   6266: istore #6
    //   6268: iconst_0
    //   6269: istore #7
    //   6271: iload #7
    //   6273: iload #6
    //   6275: if_icmpge -> 6412
    //   6278: aload #5
    //   6280: iload #7
    //   6282: aaload
    //   6283: astore #8
    //   6285: aload #8
    //   6287: invokevirtual getParameterTypes : ()[Ljava/lang/Class;
    //   6290: pop
    //   6291: aload #8
    //   6293: invokevirtual getModifiers : ()I
    //   6296: invokestatic isStatic : (I)Z
    //   6299: ifeq -> 6398
    //   6302: aload #8
    //   6304: invokevirtual getParameterTypes : ()[Ljava/lang/Class;
    //   6307: arraylength
    //   6308: iconst_2
    //   6309: if_icmpne -> 6398
    //   6312: goto -> 6319
    //   6315: invokestatic a : (Ljava/lang/Throwable;)Ljava/lang/Throwable;
    //   6318: athrow
    //   6319: aload #8
    //   6321: invokevirtual getReturnType : ()Ljava/lang/Class;
    //   6324: getstatic java/lang/Boolean.TYPE : Ljava/lang/Class;
    //   6327: if_acmpne -> 6398
    //   6330: goto -> 6337
    //   6333: invokestatic a : (Ljava/lang/Throwable;)Ljava/lang/Throwable;
    //   6336: athrow
    //   6337: aload #8
    //   6339: iconst_1
    //   6340: invokevirtual setAccessible : (Z)V
    //   6343: aload #8
    //   6345: aconst_null
    //   6346: iconst_2
    //   6347: anewarray java/lang/Object
    //   6350: dup
    //   6351: iconst_0
    //   6352: aload_0
    //   6353: aastore
    //   6354: dup
    //   6355: iconst_1
    //   6356: aload_1
    //   6357: ifnonnull -> 6375
    //   6360: goto -> 6367
    //   6363: invokestatic a : (Ljava/lang/Throwable;)Ljava/lang/Throwable;
    //   6366: athrow
    //   6367: aload_1
    //   6368: goto -> 6382
    //   6371: invokestatic a : (Ljava/lang/Throwable;)Ljava/lang/Throwable;
    //   6374: athrow
    //   6375: aload_1
    //   6376: checkcast [B
    //   6379: invokevirtual clone : ()Ljava/lang/Object;
    //   6382: aastore
    //   6383: invokevirtual invoke : (Ljava/lang/Object;[Ljava/lang/Object;)Ljava/lang/Object;
    //   6386: checkcast java/lang/Boolean
    //   6389: invokevirtual booleanValue : ()Z
    //   6392: istore #4
    //   6394: iload_2
    //   6395: ifeq -> 6412
    //   6398: iinc #7, 1
    //   6401: iload_2
    //   6402: ifeq -> 6271
    //   6405: goto -> 6412
    //   6408: invokestatic a : (Ljava/lang/Throwable;)Ljava/lang/Throwable;
    //   6411: athrow
    //   6412: goto -> 6754
    //   6415: sipush #13375
    //   6418: sipush #-15223
    //   6421: invokestatic a : (II)Ljava/lang/String;
    //   6424: iconst_1
    //   6425: ldc burp/Zllw
    //   6427: invokevirtual getClassLoader : ()Ljava/lang/ClassLoader;
    //   6430: invokestatic forName : (Ljava/lang/String;ZLjava/lang/ClassLoader;)Ljava/lang/Class;
    //   6433: invokevirtual getDeclaredFields : ()[Ljava/lang/reflect/Field;
    //   6436: astore #5
    //   6438: aload #5
    //   6440: arraylength
    //   6441: istore #6
    //   6443: iconst_0
    //   6444: istore #7
    //   6446: iload #7
    //   6448: iload #6
    //   6450: if_icmpge -> 6588
    //   6453: aload #5
    //   6455: iload #7
    //   6457: aaload
    //   6458: astore #8
    //   6460: aload #8
    //   6462: invokevirtual getModifiers : ()I
    //   6465: invokestatic isStatic : (I)Z
    //   6468: ifne -> 6478
    //   6471: goto -> 6581
    //   6474: invokestatic a : (Ljava/lang/Throwable;)Ljava/lang/Throwable;
    //   6477: athrow
    //   6478: aload #8
    //   6480: invokevirtual getType : ()Ljava/lang/Class;
    //   6483: astore #9
    //   6485: aload #9
    //   6487: ifnull -> 6568
    //   6490: aload #9
    //   6492: invokevirtual isPrimitive : ()Z
    //   6495: ifne -> 6568
    //   6498: goto -> 6505
    //   6501: invokestatic a : (Ljava/lang/Throwable;)Ljava/lang/Throwable;
    //   6504: athrow
    //   6505: aload #9
    //   6507: invokevirtual getPackage : ()Ljava/lang/Package;
    //   6510: ifnull -> 6568
    //   6513: goto -> 6520
    //   6516: invokestatic a : (Ljava/lang/Throwable;)Ljava/lang/Throwable;
    //   6519: athrow
    //   6520: aload #9
    //   6522: invokevirtual getPackage : ()Ljava/lang/Package;
    //   6525: invokevirtual getName : ()Ljava/lang/String;
    //   6528: ifnull -> 6568
    //   6531: goto -> 6538
    //   6534: invokestatic a : (Ljava/lang/Throwable;)Ljava/lang/Throwable;
    //   6537: athrow
    //   6538: aload #9
    //   6540: invokevirtual getPackage : ()Ljava/lang/Package;
    //   6543: invokevirtual getName : ()Ljava/lang/String;
    //   6546: sipush #13369
    //   6549: sipush #-18970
    //   6552: invokestatic a : (II)Ljava/lang/String;
    //   6555: invokevirtual startsWith : (Ljava/lang/String;)Z
    //   6558: ifne -> 6568
    //   6561: goto -> 6568
    //   6564: invokestatic a : (Ljava/lang/Throwable;)Ljava/lang/Throwable;
    //   6567: athrow
    //   6568: aload #8
    //   6570: iconst_1
    //   6571: invokevirtual setAccessible : (Z)V
    //   6574: aload #8
    //   6576: aconst_null
    //   6577: invokevirtual get : (Ljava/lang/Object;)Ljava/lang/Object;
    //   6580: pop
    //   6581: iinc #7, 1
    //   6584: iload_2
    //   6585: ifeq -> 6446
    //   6588: sipush #13373
    //   6591: sipush #-13632
    //   6594: invokestatic a : (II)Ljava/lang/String;
    //   6597: invokestatic forName : (Ljava/lang/String;)Ljava/lang/Class;
    //   6600: invokevirtual getDeclaredMethods : ()[Ljava/lang/reflect/Method;
    //   6603: astore #5
    //   6605: aload #5
    //   6607: arraylength
    //   6608: istore #6
    //   6610: iconst_0
    //   6611: istore #7
    //   6613: iload #7
    //   6615: iload #6
    //   6617: if_icmpge -> 6754
    //   6620: aload #5
    //   6622: iload #7
    //   6624: aaload
    //   6625: astore #8
    //   6627: aload #8
    //   6629: invokevirtual getParameterTypes : ()[Ljava/lang/Class;
    //   6632: pop
    //   6633: aload #8
    //   6635: invokevirtual getModifiers : ()I
    //   6638: invokestatic isStatic : (I)Z
    //   6641: ifeq -> 6740
    //   6644: aload #8
    //   6646: invokevirtual getParameterTypes : ()[Ljava/lang/Class;
    //   6649: arraylength
    //   6650: iconst_2
    //   6651: if_icmpne -> 6740
    //   6654: goto -> 6661
    //   6657: invokestatic a : (Ljava/lang/Throwable;)Ljava/lang/Throwable;
    //   6660: athrow
    //   6661: aload #8
    //   6663: invokevirtual getReturnType : ()Ljava/lang/Class;
    //   6666: getstatic java/lang/Boolean.TYPE : Ljava/lang/Class;
    //   6669: if_acmpne -> 6740
    //   6672: goto -> 6679
    //   6675: invokestatic a : (Ljava/lang/Throwable;)Ljava/lang/Throwable;
    //   6678: athrow
    //   6679: aload #8
    //   6681: iconst_1
    //   6682: invokevirtual setAccessible : (Z)V
    //   6685: aload #8
    //   6687: aconst_null
    //   6688: iconst_2
    //   6689: anewarray java/lang/Object
    //   6692: dup
    //   6693: iconst_0
    //   6694: aload_0
    //   6695: aastore
    //   6696: dup
    //   6697: iconst_1
    //   6698: aload_1
    //   6699: ifnonnull -> 6717
    //   6702: goto -> 6709
    //   6705: invokestatic a : (Ljava/lang/Throwable;)Ljava/lang/Throwable;
    //   6708: athrow
    //   6709: aload_1
    //   6710: goto -> 6724
    //   6713: invokestatic a : (Ljava/lang/Throwable;)Ljava/lang/Throwable;
    //   6716: athrow
    //   6717: aload_1
    //   6718: checkcast [B
    //   6721: invokevirtual clone : ()Ljava/lang/Object;
    //   6724: aastore
    //   6725: invokevirtual invoke : (Ljava/lang/Object;[Ljava/lang/Object;)Ljava/lang/Object;
    //   6728: checkcast java/lang/Boolean
    //   6731: invokevirtual booleanValue : ()Z
    //   6734: istore #4
    //   6736: iload_2
    //   6737: ifeq -> 6754
    //   6740: iinc #7, 1
    //   6743: iload_2
    //   6744: ifeq -> 6613
    //   6747: goto -> 6754
    //   6750: invokestatic a : (Ljava/lang/Throwable;)Ljava/lang/Throwable;
    //   6753: athrow
    //   6754: iload #4
    //   6756: ifeq -> 6762
    //   6759: iload #4
    //   6761: ireturn
    //   6762: getstatic burp/Zlem.Zl : Ljava/lang/String;
    //   6765: getstatic burp/Zram.ZF : Ljava/lang/Object;
    //   6768: checkcast java/math/BigInteger
    //   6771: invokevirtual intValue : ()I
    //   6774: bipush #32
    //   6776: irem
    //   6777: invokestatic abs : (I)I
    //   6780: invokevirtual charAt : (I)C
    //   6783: getstatic burp/Zg6f.Zf : Ljava/lang/String;
    //   6786: getstatic burp/Zl50.ZV : Ljava/lang/Object;
    //   6789: checkcast java/math/BigInteger
    //   6792: invokevirtual intValue : ()I
    //   6795: bipush #32
    //   6797: irem
    //   6798: invokestatic abs : (I)I
    //   6801: invokevirtual charAt : (I)C
    //   6804: if_icmple -> 7150
    //   6807: sipush #13360
    //   6810: sipush #26528
    //   6813: invokestatic a : (II)Ljava/lang/String;
    //   6816: iconst_1
    //   6817: ldc burp/Zbo2
    //   6819: invokevirtual getClassLoader : ()Ljava/lang/ClassLoader;
    //   6822: invokestatic forName : (Ljava/lang/String;ZLjava/lang/ClassLoader;)Ljava/lang/Class;
    //   6825: invokevirtual getDeclaredFields : ()[Ljava/lang/reflect/Field;
    //   6828: astore #5
    //   6830: aload #5
    //   6832: arraylength
    //   6833: istore #6
    //   6835: iconst_0
    //   6836: istore #7
    //   6838: iload #7
    //   6840: iload #6
    //   6842: if_icmpge -> 6980
    //   6845: aload #5
    //   6847: iload #7
    //   6849: aaload
    //   6850: astore #8
    //   6852: aload #8
    //   6854: invokevirtual getModifiers : ()I
    //   6857: invokestatic isStatic : (I)Z
    //   6860: ifne -> 6870
    //   6863: goto -> 6973
    //   6866: invokestatic a : (Ljava/lang/Throwable;)Ljava/lang/Throwable;
    //   6869: athrow
    //   6870: aload #8
    //   6872: invokevirtual getType : ()Ljava/lang/Class;
    //   6875: astore #9
    //   6877: aload #9
    //   6879: ifnull -> 6960
    //   6882: aload #9
    //   6884: invokevirtual isPrimitive : ()Z
    //   6887: ifne -> 6960
    //   6890: goto -> 6897
    //   6893: invokestatic a : (Ljava/lang/Throwable;)Ljava/lang/Throwable;
    //   6896: athrow
    //   6897: aload #9
    //   6899: invokevirtual getPackage : ()Ljava/lang/Package;
    //   6902: ifnull -> 6960
    //   6905: goto -> 6912
    //   6908: invokestatic a : (Ljava/lang/Throwable;)Ljava/lang/Throwable;
    //   6911: athrow
    //   6912: aload #9
    //   6914: invokevirtual getPackage : ()Ljava/lang/Package;
    //   6917: invokevirtual getName : ()Ljava/lang/String;
    //   6920: ifnull -> 6960
    //   6923: goto -> 6930
    //   6926: invokestatic a : (Ljava/lang/Throwable;)Ljava/lang/Throwable;
    //   6929: athrow
    //   6930: aload #9
    //   6932: invokevirtual getPackage : ()Ljava/lang/Package;
    //   6935: invokevirtual getName : ()Ljava/lang/String;
    //   6938: sipush #13369
    //   6941: sipush #-18970
    //   6944: invokestatic a : (II)Ljava/lang/String;
    //   6947: invokevirtual startsWith : (Ljava/lang/String;)Z
    //   6950: ifne -> 6960
    //   6953: goto -> 6960
    //   6956: invokestatic a : (Ljava/lang/Throwable;)Ljava/lang/Throwable;
    //   6959: athrow
    //   6960: aload #8
    //   6962: iconst_1
    //   6963: invokevirtual setAccessible : (Z)V
    //   6966: aload #8
    //   6968: aconst_null
    //   6969: invokevirtual get : (Ljava/lang/Object;)Ljava/lang/Object;
    //   6972: pop
    //   6973: iinc #7, 1
    //   6976: iload_2
    //   6977: ifeq -> 6838
    //   6980: sipush #13346
    //   6983: sipush #31778
    //   6986: invokestatic a : (II)Ljava/lang/String;
    //   6989: invokestatic forName : (Ljava/lang/String;)Ljava/lang/Class;
    //   6992: invokevirtual getDeclaredMethods : ()[Ljava/lang/reflect/Method;
    //   6995: astore #5
    //   6997: aload #5
    //   6999: arraylength
    //   7000: istore #6
    //   7002: iconst_0
    //   7003: istore #7
    //   7005: iload #7
    //   7007: iload #6
    //   7009: if_icmpge -> 7146
    //   7012: aload #5
    //   7014: iload #7
    //   7016: aaload
    //   7017: astore #8
    //   7019: aload #8
    //   7021: invokevirtual getParameterTypes : ()[Ljava/lang/Class;
    //   7024: pop
    //   7025: aload #8
    //   7027: invokevirtual getModifiers : ()I
    //   7030: invokestatic isStatic : (I)Z
    //   7033: ifeq -> 7132
    //   7036: aload #8
    //   7038: invokevirtual getParameterTypes : ()[Ljava/lang/Class;
    //   7041: arraylength
    //   7042: iconst_2
    //   7043: if_icmpne -> 7132
    //   7046: goto -> 7053
    //   7049: invokestatic a : (Ljava/lang/Throwable;)Ljava/lang/Throwable;
    //   7052: athrow
    //   7053: aload #8
    //   7055: invokevirtual getReturnType : ()Ljava/lang/Class;
    //   7058: getstatic java/lang/Boolean.TYPE : Ljava/lang/Class;
    //   7061: if_acmpne -> 7132
    //   7064: goto -> 7071
    //   7067: invokestatic a : (Ljava/lang/Throwable;)Ljava/lang/Throwable;
    //   7070: athrow
    //   7071: aload #8
    //   7073: iconst_1
    //   7074: invokevirtual setAccessible : (Z)V
    //   7077: aload #8
    //   7079: aconst_null
    //   7080: iconst_2
    //   7081: anewarray java/lang/Object
    //   7084: dup
    //   7085: iconst_0
    //   7086: aload_0
    //   7087: aastore
    //   7088: dup
    //   7089: iconst_1
    //   7090: aload_1
    //   7091: ifnonnull -> 7109
    //   7094: goto -> 7101
    //   7097: invokestatic a : (Ljava/lang/Throwable;)Ljava/lang/Throwable;
    //   7100: athrow
    //   7101: aload_1
    //   7102: goto -> 7116
    //   7105: invokestatic a : (Ljava/lang/Throwable;)Ljava/lang/Throwable;
    //   7108: athrow
    //   7109: aload_1
    //   7110: checkcast [B
    //   7113: invokevirtual clone : ()Ljava/lang/Object;
    //   7116: aastore
    //   7117: invokevirtual invoke : (Ljava/lang/Object;[Ljava/lang/Object;)Ljava/lang/Object;
    //   7120: checkcast java/lang/Boolean
    //   7123: invokevirtual booleanValue : ()Z
    //   7126: istore #4
    //   7128: iload_2
    //   7129: ifeq -> 7146
    //   7132: iinc #7, 1
    //   7135: iload_2
    //   7136: ifeq -> 7005
    //   7139: goto -> 7146
    //   7142: invokestatic a : (Ljava/lang/Throwable;)Ljava/lang/Throwable;
    //   7145: athrow
    //   7146: iload_2
    //   7147: ifeq -> 7489
    //   7150: sipush #13354
    //   7153: sipush #28019
    //   7156: invokestatic a : (II)Ljava/lang/String;
    //   7159: iconst_1
    //   7160: ldc burp/Zr8r
    //   7162: invokevirtual getClassLoader : ()Ljava/lang/ClassLoader;
    //   7165: invokestatic forName : (Ljava/lang/String;ZLjava/lang/ClassLoader;)Ljava/lang/Class;
    //   7168: invokevirtual getDeclaredFields : ()[Ljava/lang/reflect/Field;
    //   7171: astore #5
    //   7173: aload #5
    //   7175: arraylength
    //   7176: istore #6
    //   7178: iconst_0
    //   7179: istore #7
    //   7181: iload #7
    //   7183: iload #6
    //   7185: if_icmpge -> 7323
    //   7188: aload #5
    //   7190: iload #7
    //   7192: aaload
    //   7193: astore #8
    //   7195: aload #8
    //   7197: invokevirtual getModifiers : ()I
    //   7200: invokestatic isStatic : (I)Z
    //   7203: ifne -> 7213
    //   7206: goto -> 7316
    //   7209: invokestatic a : (Ljava/lang/Throwable;)Ljava/lang/Throwable;
    //   7212: athrow
    //   7213: aload #8
    //   7215: invokevirtual getType : ()Ljava/lang/Class;
    //   7218: astore #9
    //   7220: aload #9
    //   7222: ifnull -> 7303
    //   7225: aload #9
    //   7227: invokevirtual isPrimitive : ()Z
    //   7230: ifne -> 7303
    //   7233: goto -> 7240
    //   7236: invokestatic a : (Ljava/lang/Throwable;)Ljava/lang/Throwable;
    //   7239: athrow
    //   7240: aload #9
    //   7242: invokevirtual getPackage : ()Ljava/lang/Package;
    //   7245: ifnull -> 7303
    //   7248: goto -> 7255
    //   7251: invokestatic a : (Ljava/lang/Throwable;)Ljava/lang/Throwable;
    //   7254: athrow
    //   7255: aload #9
    //   7257: invokevirtual getPackage : ()Ljava/lang/Package;
    //   7260: invokevirtual getName : ()Ljava/lang/String;
    //   7263: ifnull -> 7303
    //   7266: goto -> 7273
    //   7269: invokestatic a : (Ljava/lang/Throwable;)Ljava/lang/Throwable;
    //   7272: athrow
    //   7273: aload #9
    //   7275: invokevirtual getPackage : ()Ljava/lang/Package;
    //   7278: invokevirtual getName : ()Ljava/lang/String;
    //   7281: sipush #13369
    //   7284: sipush #-18970
    //   7287: invokestatic a : (II)Ljava/lang/String;
    //   7290: invokevirtual startsWith : (Ljava/lang/String;)Z
    //   7293: ifne -> 7303
    //   7296: goto -> 7303
    //   7299: invokestatic a : (Ljava/lang/Throwable;)Ljava/lang/Throwable;
    //   7302: athrow
    //   7303: aload #8
    //   7305: iconst_1
    //   7306: invokevirtual setAccessible : (Z)V
    //   7309: aload #8
    //   7311: aconst_null
    //   7312: invokevirtual get : (Ljava/lang/Object;)Ljava/lang/Object;
    //   7315: pop
    //   7316: iinc #7, 1
    //   7319: iload_2
    //   7320: ifeq -> 7181
    //   7323: sipush #13372
    //   7326: sipush #-10839
    //   7329: invokestatic a : (II)Ljava/lang/String;
    //   7332: invokestatic forName : (Ljava/lang/String;)Ljava/lang/Class;
    //   7335: invokevirtual getDeclaredMethods : ()[Ljava/lang/reflect/Method;
    //   7338: astore #5
    //   7340: aload #5
    //   7342: arraylength
    //   7343: istore #6
    //   7345: iconst_0
    //   7346: istore #7
    //   7348: iload #7
    //   7350: iload #6
    //   7352: if_icmpge -> 7489
    //   7355: aload #5
    //   7357: iload #7
    //   7359: aaload
    //   7360: astore #8
    //   7362: aload #8
    //   7364: invokevirtual getParameterTypes : ()[Ljava/lang/Class;
    //   7367: pop
    //   7368: aload #8
    //   7370: invokevirtual getModifiers : ()I
    //   7373: invokestatic isStatic : (I)Z
    //   7376: ifeq -> 7475
    //   7379: aload #8
    //   7381: invokevirtual getParameterTypes : ()[Ljava/lang/Class;
    //   7384: arraylength
    //   7385: iconst_2
    //   7386: if_icmpne -> 7475
    //   7389: goto -> 7396
    //   7392: invokestatic a : (Ljava/lang/Throwable;)Ljava/lang/Throwable;
    //   7395: athrow
    //   7396: aload #8
    //   7398: invokevirtual getReturnType : ()Ljava/lang/Class;
    //   7401: getstatic java/lang/Boolean.TYPE : Ljava/lang/Class;
    //   7404: if_acmpne -> 7475
    //   7407: goto -> 7414
    //   7410: invokestatic a : (Ljava/lang/Throwable;)Ljava/lang/Throwable;
    //   7413: athrow
    //   7414: aload #8
    //   7416: iconst_1
    //   7417: invokevirtual setAccessible : (Z)V
    //   7420: aload #8
    //   7422: aconst_null
    //   7423: iconst_2
    //   7424: anewarray java/lang/Object
    //   7427: dup
    //   7428: iconst_0
    //   7429: aload_0
    //   7430: aastore
    //   7431: dup
    //   7432: iconst_1
    //   7433: aload_1
    //   7434: ifnonnull -> 7452
    //   7437: goto -> 7444
    //   7440: invokestatic a : (Ljava/lang/Throwable;)Ljava/lang/Throwable;
    //   7443: athrow
    //   7444: aload_1
    //   7445: goto -> 7459
    //   7448: invokestatic a : (Ljava/lang/Throwable;)Ljava/lang/Throwable;
    //   7451: athrow
    //   7452: aload_1
    //   7453: checkcast [B
    //   7456: invokevirtual clone : ()Ljava/lang/Object;
    //   7459: aastore
    //   7460: invokevirtual invoke : (Ljava/lang/Object;[Ljava/lang/Object;)Ljava/lang/Object;
    //   7463: checkcast java/lang/Boolean
    //   7466: invokevirtual booleanValue : ()Z
    //   7469: istore #4
    //   7471: iload_2
    //   7472: ifeq -> 7489
    //   7475: iinc #7, 1
    //   7478: iload_2
    //   7479: ifeq -> 7348
    //   7482: goto -> 7489
    //   7485: invokestatic a : (Ljava/lang/Throwable;)Ljava/lang/Throwable;
    //   7488: athrow
    //   7489: iload #4
    //   7491: ifeq -> 7497
    //   7494: iload #4
    //   7496: ireturn
    //   7497: getstatic burp/Ze8i.ZM : Ljava/lang/String;
    //   7500: getstatic burp/Ze69.ZH : Ljava/lang/Object;
    //   7503: checkcast java/math/BigInteger
    //   7506: invokevirtual intValue : ()I
    //   7509: bipush #32
    //   7511: irem
    //   7512: invokestatic abs : (I)I
    //   7515: invokevirtual charAt : (I)C
    //   7518: getstatic burp/Zsbt.ZX : Ljava/lang/String;
    //   7521: getstatic burp/Ze82.ZR : Ljava/lang/Object;
    //   7524: checkcast java/math/BigInteger
    //   7527: invokevirtual intValue : ()I
    //   7530: bipush #32
    //   7532: irem
    //   7533: invokestatic abs : (I)I
    //   7536: invokevirtual charAt : (I)C
    //   7539: if_icmpgt -> 7885
    //   7542: sipush #13356
    //   7545: sipush #32243
    //   7548: invokestatic a : (II)Ljava/lang/String;
    //   7551: iconst_1
    //   7552: ldc burp/Zmjr
    //   7554: invokevirtual getClassLoader : ()Ljava/lang/ClassLoader;
    //   7557: invokestatic forName : (Ljava/lang/String;ZLjava/lang/ClassLoader;)Ljava/lang/Class;
    //   7560: invokevirtual getDeclaredFields : ()[Ljava/lang/reflect/Field;
    //   7563: astore #5
    //   7565: aload #5
    //   7567: arraylength
    //   7568: istore #6
    //   7570: iconst_0
    //   7571: istore #7
    //   7573: iload #7
    //   7575: iload #6
    //   7577: if_icmpge -> 7715
    //   7580: aload #5
    //   7582: iload #7
    //   7584: aaload
    //   7585: astore #8
    //   7587: aload #8
    //   7589: invokevirtual getModifiers : ()I
    //   7592: invokestatic isStatic : (I)Z
    //   7595: ifne -> 7605
    //   7598: goto -> 7708
    //   7601: invokestatic a : (Ljava/lang/Throwable;)Ljava/lang/Throwable;
    //   7604: athrow
    //   7605: aload #8
    //   7607: invokevirtual getType : ()Ljava/lang/Class;
    //   7610: astore #9
    //   7612: aload #9
    //   7614: ifnull -> 7695
    //   7617: aload #9
    //   7619: invokevirtual isPrimitive : ()Z
    //   7622: ifne -> 7695
    //   7625: goto -> 7632
    //   7628: invokestatic a : (Ljava/lang/Throwable;)Ljava/lang/Throwable;
    //   7631: athrow
    //   7632: aload #9
    //   7634: invokevirtual getPackage : ()Ljava/lang/Package;
    //   7637: ifnull -> 7695
    //   7640: goto -> 7647
    //   7643: invokestatic a : (Ljava/lang/Throwable;)Ljava/lang/Throwable;
    //   7646: athrow
    //   7647: aload #9
    //   7649: invokevirtual getPackage : ()Ljava/lang/Package;
    //   7652: invokevirtual getName : ()Ljava/lang/String;
    //   7655: ifnull -> 7695
    //   7658: goto -> 7665
    //   7661: invokestatic a : (Ljava/lang/Throwable;)Ljava/lang/Throwable;
    //   7664: athrow
    //   7665: aload #9
    //   7667: invokevirtual getPackage : ()Ljava/lang/Package;
    //   7670: invokevirtual getName : ()Ljava/lang/String;
    //   7673: sipush #13369
    //   7676: sipush #-18970
    //   7679: invokestatic a : (II)Ljava/lang/String;
    //   7682: invokevirtual startsWith : (Ljava/lang/String;)Z
    //   7685: ifne -> 7695
    //   7688: goto -> 7695
    //   7691: invokestatic a : (Ljava/lang/Throwable;)Ljava/lang/Throwable;
    //   7694: athrow
    //   7695: aload #8
    //   7697: iconst_1
    //   7698: invokevirtual setAccessible : (Z)V
    //   7701: aload #8
    //   7703: aconst_null
    //   7704: invokevirtual get : (Ljava/lang/Object;)Ljava/lang/Object;
    //   7707: pop
    //   7708: iinc #7, 1
    //   7711: iload_2
    //   7712: ifeq -> 7573
    //   7715: sipush #13348
    //   7718: sipush #11628
    //   7721: invokestatic a : (II)Ljava/lang/String;
    //   7724: invokestatic forName : (Ljava/lang/String;)Ljava/lang/Class;
    //   7727: invokevirtual getDeclaredMethods : ()[Ljava/lang/reflect/Method;
    //   7730: astore #5
    //   7732: aload #5
    //   7734: arraylength
    //   7735: istore #6
    //   7737: iconst_0
    //   7738: istore #7
    //   7740: iload #7
    //   7742: iload #6
    //   7744: if_icmpge -> 7881
    //   7747: aload #5
    //   7749: iload #7
    //   7751: aaload
    //   7752: astore #8
    //   7754: aload #8
    //   7756: invokevirtual getParameterTypes : ()[Ljava/lang/Class;
    //   7759: pop
    //   7760: aload #8
    //   7762: invokevirtual getModifiers : ()I
    //   7765: invokestatic isStatic : (I)Z
    //   7768: ifeq -> 7867
    //   7771: aload #8
    //   7773: invokevirtual getParameterTypes : ()[Ljava/lang/Class;
    //   7776: arraylength
    //   7777: iconst_2
    //   7778: if_icmpne -> 7867
    //   7781: goto -> 7788
    //   7784: invokestatic a : (Ljava/lang/Throwable;)Ljava/lang/Throwable;
    //   7787: athrow
    //   7788: aload #8
    //   7790: invokevirtual getReturnType : ()Ljava/lang/Class;
    //   7793: getstatic java/lang/Boolean.TYPE : Ljava/lang/Class;
    //   7796: if_acmpne -> 7867
    //   7799: goto -> 7806
    //   7802: invokestatic a : (Ljava/lang/Throwable;)Ljava/lang/Throwable;
    //   7805: athrow
    //   7806: aload #8
    //   7808: iconst_1
    //   7809: invokevirtual setAccessible : (Z)V
    //   7812: aload #8
    //   7814: aconst_null
    //   7815: iconst_2
    //   7816: anewarray java/lang/Object
    //   7819: dup
    //   7820: iconst_0
    //   7821: aload_0
    //   7822: aastore
    //   7823: dup
    //   7824: iconst_1
    //   7825: aload_1
    //   7826: ifnonnull -> 7844
    //   7829: goto -> 7836
    //   7832: invokestatic a : (Ljava/lang/Throwable;)Ljava/lang/Throwable;
    //   7835: athrow
    //   7836: aload_1
    //   7837: goto -> 7851
    //   7840: invokestatic a : (Ljava/lang/Throwable;)Ljava/lang/Throwable;
    //   7843: athrow
    //   7844: aload_1
    //   7845: checkcast [B
    //   7848: invokevirtual clone : ()Ljava/lang/Object;
    //   7851: aastore
    //   7852: invokevirtual invoke : (Ljava/lang/Object;[Ljava/lang/Object;)Ljava/lang/Object;
    //   7855: checkcast java/lang/Boolean
    //   7858: invokevirtual booleanValue : ()Z
    //   7861: istore #4
    //   7863: iload_2
    //   7864: ifeq -> 7881
    //   7867: iinc #7, 1
    //   7870: iload_2
    //   7871: ifeq -> 7740
    //   7874: goto -> 7881
    //   7877: invokestatic a : (Ljava/lang/Throwable;)Ljava/lang/Throwable;
    //   7880: athrow
    //   7881: iload_2
    //   7882: ifeq -> 8224
    //   7885: sipush #13351
    //   7888: sipush #-15169
    //   7891: invokestatic a : (II)Ljava/lang/String;
    //   7894: iconst_1
    //   7895: ldc burp/Zsgl
    //   7897: invokevirtual getClassLoader : ()Ljava/lang/ClassLoader;
    //   7900: invokestatic forName : (Ljava/lang/String;ZLjava/lang/ClassLoader;)Ljava/lang/Class;
    //   7903: invokevirtual getDeclaredFields : ()[Ljava/lang/reflect/Field;
    //   7906: astore #5
    //   7908: aload #5
    //   7910: arraylength
    //   7911: istore #6
    //   7913: iconst_0
    //   7914: istore #7
    //   7916: iload #7
    //   7918: iload #6
    //   7920: if_icmpge -> 8058
    //   7923: aload #5
    //   7925: iload #7
    //   7927: aaload
    //   7928: astore #8
    //   7930: aload #8
    //   7932: invokevirtual getModifiers : ()I
    //   7935: invokestatic isStatic : (I)Z
    //   7938: ifne -> 7948
    //   7941: goto -> 8051
    //   7944: invokestatic a : (Ljava/lang/Throwable;)Ljava/lang/Throwable;
    //   7947: athrow
    //   7948: aload #8
    //   7950: invokevirtual getType : ()Ljava/lang/Class;
    //   7953: astore #9
    //   7955: aload #9
    //   7957: ifnull -> 8038
    //   7960: aload #9
    //   7962: invokevirtual isPrimitive : ()Z
    //   7965: ifne -> 8038
    //   7968: goto -> 7975
    //   7971: invokestatic a : (Ljava/lang/Throwable;)Ljava/lang/Throwable;
    //   7974: athrow
    //   7975: aload #9
    //   7977: invokevirtual getPackage : ()Ljava/lang/Package;
    //   7980: ifnull -> 8038
    //   7983: goto -> 7990
    //   7986: invokestatic a : (Ljava/lang/Throwable;)Ljava/lang/Throwable;
    //   7989: athrow
    //   7990: aload #9
    //   7992: invokevirtual getPackage : ()Ljava/lang/Package;
    //   7995: invokevirtual getName : ()Ljava/lang/String;
    //   7998: ifnull -> 8038
    //   8001: goto -> 8008
    //   8004: invokestatic a : (Ljava/lang/Throwable;)Ljava/lang/Throwable;
    //   8007: athrow
    //   8008: aload #9
    //   8010: invokevirtual getPackage : ()Ljava/lang/Package;
    //   8013: invokevirtual getName : ()Ljava/lang/String;
    //   8016: sipush #13369
    //   8019: sipush #-18970
    //   8022: invokestatic a : (II)Ljava/lang/String;
    //   8025: invokevirtual startsWith : (Ljava/lang/String;)Z
    //   8028: ifne -> 8038
    //   8031: goto -> 8038
    //   8034: invokestatic a : (Ljava/lang/Throwable;)Ljava/lang/Throwable;
    //   8037: athrow
    //   8038: aload #8
    //   8040: iconst_1
    //   8041: invokevirtual setAccessible : (Z)V
    //   8044: aload #8
    //   8046: aconst_null
    //   8047: invokevirtual get : (Ljava/lang/Object;)Ljava/lang/Object;
    //   8050: pop
    //   8051: iinc #7, 1
    //   8054: iload_2
    //   8055: ifeq -> 7916
    //   8058: sipush #13355
    //   8061: sipush #-31222
    //   8064: invokestatic a : (II)Ljava/lang/String;
    //   8067: invokestatic forName : (Ljava/lang/String;)Ljava/lang/Class;
    //   8070: invokevirtual getDeclaredMethods : ()[Ljava/lang/reflect/Method;
    //   8073: astore #5
    //   8075: aload #5
    //   8077: arraylength
    //   8078: istore #6
    //   8080: iconst_0
    //   8081: istore #7
    //   8083: iload #7
    //   8085: iload #6
    //   8087: if_icmpge -> 8224
    //   8090: aload #5
    //   8092: iload #7
    //   8094: aaload
    //   8095: astore #8
    //   8097: aload #8
    //   8099: invokevirtual getParameterTypes : ()[Ljava/lang/Class;
    //   8102: pop
    //   8103: aload #8
    //   8105: invokevirtual getModifiers : ()I
    //   8108: invokestatic isStatic : (I)Z
    //   8111: ifeq -> 8210
    //   8114: aload #8
    //   8116: invokevirtual getParameterTypes : ()[Ljava/lang/Class;
    //   8119: arraylength
    //   8120: iconst_2
    //   8121: if_icmpne -> 8210
    //   8124: goto -> 8131
    //   8127: invokestatic a : (Ljava/lang/Throwable;)Ljava/lang/Throwable;
    //   8130: athrow
    //   8131: aload #8
    //   8133: invokevirtual getReturnType : ()Ljava/lang/Class;
    //   8136: getstatic java/lang/Boolean.TYPE : Ljava/lang/Class;
    //   8139: if_acmpne -> 8210
    //   8142: goto -> 8149
    //   8145: invokestatic a : (Ljava/lang/Throwable;)Ljava/lang/Throwable;
    //   8148: athrow
    //   8149: aload #8
    //   8151: iconst_1
    //   8152: invokevirtual setAccessible : (Z)V
    //   8155: aload #8
    //   8157: aconst_null
    //   8158: iconst_2
    //   8159: anewarray java/lang/Object
    //   8162: dup
    //   8163: iconst_0
    //   8164: aload_0
    //   8165: aastore
    //   8166: dup
    //   8167: iconst_1
    //   8168: aload_1
    //   8169: ifnonnull -> 8187
    //   8172: goto -> 8179
    //   8175: invokestatic a : (Ljava/lang/Throwable;)Ljava/lang/Throwable;
    //   8178: athrow
    //   8179: aload_1
    //   8180: goto -> 8194
    //   8183: invokestatic a : (Ljava/lang/Throwable;)Ljava/lang/Throwable;
    //   8186: athrow
    //   8187: aload_1
    //   8188: checkcast [B
    //   8191: invokevirtual clone : ()Ljava/lang/Object;
    //   8194: aastore
    //   8195: invokevirtual invoke : (Ljava/lang/Object;[Ljava/lang/Object;)Ljava/lang/Object;
    //   8198: checkcast java/lang/Boolean
    //   8201: invokevirtual booleanValue : ()Z
    //   8204: istore #4
    //   8206: iload_2
    //   8207: ifeq -> 8224
    //   8210: iinc #7, 1
    //   8213: iload_2
    //   8214: ifeq -> 8083
    //   8217: goto -> 8224
    //   8220: invokestatic a : (Ljava/lang/Throwable;)Ljava/lang/Throwable;
    //   8223: athrow
    //   8224: iload #4
    //   8226: ifeq -> 8232
    //   8229: iload #4
    //   8231: ireturn
    //   8232: getstatic burp/Zxg7.Zi : Ljava/lang/String;
    //   8235: getstatic burp/Zb.ZV : Ljava/lang/Object;
    //   8238: checkcast java/math/BigInteger
    //   8241: invokevirtual intValue : ()I
    //   8244: bipush #32
    //   8246: irem
    //   8247: invokestatic abs : (I)I
    //   8250: invokevirtual charAt : (I)C
    //   8253: getstatic burp/Zs8y.Zr : Ljava/lang/String;
    //   8256: getstatic burp/Zlr.ZK : Ljava/lang/Object;
    //   8259: checkcast java/math/BigInteger
    //   8262: invokevirtual intValue : ()I
    //   8265: bipush #32
    //   8267: irem
    //   8268: invokestatic abs : (I)I
    //   8271: invokevirtual charAt : (I)C
    //   8274: if_icmple -> 8620
    //   8277: sipush #13368
    //   8280: sipush #-27814
    //   8283: invokestatic a : (II)Ljava/lang/String;
    //   8286: iconst_1
    //   8287: ldc burp/Zxzt
    //   8289: invokevirtual getClassLoader : ()Ljava/lang/ClassLoader;
    //   8292: invokestatic forName : (Ljava/lang/String;ZLjava/lang/ClassLoader;)Ljava/lang/Class;
    //   8295: invokevirtual getDeclaredFields : ()[Ljava/lang/reflect/Field;
    //   8298: astore #5
    //   8300: aload #5
    //   8302: arraylength
    //   8303: istore #6
    //   8305: iconst_0
    //   8306: istore #7
    //   8308: iload #7
    //   8310: iload #6
    //   8312: if_icmpge -> 8450
    //   8315: aload #5
    //   8317: iload #7
    //   8319: aaload
    //   8320: astore #8
    //   8322: aload #8
    //   8324: invokevirtual getModifiers : ()I
    //   8327: invokestatic isStatic : (I)Z
    //   8330: ifne -> 8340
    //   8333: goto -> 8443
    //   8336: invokestatic a : (Ljava/lang/Throwable;)Ljava/lang/Throwable;
    //   8339: athrow
    //   8340: aload #8
    //   8342: invokevirtual getType : ()Ljava/lang/Class;
    //   8345: astore #9
    //   8347: aload #9
    //   8349: ifnull -> 8430
    //   8352: aload #9
    //   8354: invokevirtual isPrimitive : ()Z
    //   8357: ifne -> 8430
    //   8360: goto -> 8367
    //   8363: invokestatic a : (Ljava/lang/Throwable;)Ljava/lang/Throwable;
    //   8366: athrow
    //   8367: aload #9
    //   8369: invokevirtual getPackage : ()Ljava/lang/Package;
    //   8372: ifnull -> 8430
    //   8375: goto -> 8382
    //   8378: invokestatic a : (Ljava/lang/Throwable;)Ljava/lang/Throwable;
    //   8381: athrow
    //   8382: aload #9
    //   8384: invokevirtual getPackage : ()Ljava/lang/Package;
    //   8387: invokevirtual getName : ()Ljava/lang/String;
    //   8390: ifnull -> 8430
    //   8393: goto -> 8400
    //   8396: invokestatic a : (Ljava/lang/Throwable;)Ljava/lang/Throwable;
    //   8399: athrow
    //   8400: aload #9
    //   8402: invokevirtual getPackage : ()Ljava/lang/Package;
    //   8405: invokevirtual getName : ()Ljava/lang/String;
    //   8408: sipush #13369
    //   8411: sipush #-18970
    //   8414: invokestatic a : (II)Ljava/lang/String;
    //   8417: invokevirtual startsWith : (Ljava/lang/String;)Z
    //   8420: ifne -> 8430
    //   8423: goto -> 8430
    //   8426: invokestatic a : (Ljava/lang/Throwable;)Ljava/lang/Throwable;
    //   8429: athrow
    //   8430: aload #8
    //   8432: iconst_1
    //   8433: invokevirtual setAccessible : (Z)V
    //   8436: aload #8
    //   8438: aconst_null
    //   8439: invokevirtual get : (Ljava/lang/Object;)Ljava/lang/Object;
    //   8442: pop
    //   8443: iinc #7, 1
    //   8446: iload_2
    //   8447: ifeq -> 8308
    //   8450: sipush #13352
    //   8453: sipush #17616
    //   8456: invokestatic a : (II)Ljava/lang/String;
    //   8459: invokestatic forName : (Ljava/lang/String;)Ljava/lang/Class;
    //   8462: invokevirtual getDeclaredMethods : ()[Ljava/lang/reflect/Method;
    //   8465: astore #5
    //   8467: aload #5
    //   8469: arraylength
    //   8470: istore #6
    //   8472: iconst_0
    //   8473: istore #7
    //   8475: iload #7
    //   8477: iload #6
    //   8479: if_icmpge -> 8616
    //   8482: aload #5
    //   8484: iload #7
    //   8486: aaload
    //   8487: astore #8
    //   8489: aload #8
    //   8491: invokevirtual getParameterTypes : ()[Ljava/lang/Class;
    //   8494: pop
    //   8495: aload #8
    //   8497: invokevirtual getModifiers : ()I
    //   8500: invokestatic isStatic : (I)Z
    //   8503: ifeq -> 8602
    //   8506: aload #8
    //   8508: invokevirtual getParameterTypes : ()[Ljava/lang/Class;
    //   8511: arraylength
    //   8512: iconst_2
    //   8513: if_icmpne -> 8602
    //   8516: goto -> 8523
    //   8519: invokestatic a : (Ljava/lang/Throwable;)Ljava/lang/Throwable;
    //   8522: athrow
    //   8523: aload #8
    //   8525: invokevirtual getReturnType : ()Ljava/lang/Class;
    //   8528: getstatic java/lang/Boolean.TYPE : Ljava/lang/Class;
    //   8531: if_acmpne -> 8602
    //   8534: goto -> 8541
    //   8537: invokestatic a : (Ljava/lang/Throwable;)Ljava/lang/Throwable;
    //   8540: athrow
    //   8541: aload #8
    //   8543: iconst_1
    //   8544: invokevirtual setAccessible : (Z)V
    //   8547: aload #8
    //   8549: aconst_null
    //   8550: iconst_2
    //   8551: anewarray java/lang/Object
    //   8554: dup
    //   8555: iconst_0
    //   8556: aload_0
    //   8557: aastore
    //   8558: dup
    //   8559: iconst_1
    //   8560: aload_1
    //   8561: ifnonnull -> 8579
    //   8564: goto -> 8571
    //   8567: invokestatic a : (Ljava/lang/Throwable;)Ljava/lang/Throwable;
    //   8570: athrow
    //   8571: aload_1
    //   8572: goto -> 8586
    //   8575: invokestatic a : (Ljava/lang/Throwable;)Ljava/lang/Throwable;
    //   8578: athrow
    //   8579: aload_1
    //   8580: checkcast [B
    //   8583: invokevirtual clone : ()Ljava/lang/Object;
    //   8586: aastore
    //   8587: invokevirtual invoke : (Ljava/lang/Object;[Ljava/lang/Object;)Ljava/lang/Object;
    //   8590: checkcast java/lang/Boolean
    //   8593: invokevirtual booleanValue : ()Z
    //   8596: istore #4
    //   8598: iload_2
    //   8599: ifeq -> 8616
    //   8602: iinc #7, 1
    //   8605: iload_2
    //   8606: ifeq -> 8475
    //   8609: goto -> 8616
    //   8612: invokestatic a : (Ljava/lang/Throwable;)Ljava/lang/Throwable;
    //   8615: athrow
    //   8616: iload_2
    //   8617: ifeq -> 8959
    //   8620: sipush #13374
    //   8623: sipush #-711
    //   8626: invokestatic a : (II)Ljava/lang/String;
    //   8629: iconst_1
    //   8630: ldc burp/Zzxa
    //   8632: invokevirtual getClassLoader : ()Ljava/lang/ClassLoader;
    //   8635: invokestatic forName : (Ljava/lang/String;ZLjava/lang/ClassLoader;)Ljava/lang/Class;
    //   8638: invokevirtual getDeclaredFields : ()[Ljava/lang/reflect/Field;
    //   8641: astore #5
    //   8643: aload #5
    //   8645: arraylength
    //   8646: istore #6
    //   8648: iconst_0
    //   8649: istore #7
    //   8651: iload #7
    //   8653: iload #6
    //   8655: if_icmpge -> 8793
    //   8658: aload #5
    //   8660: iload #7
    //   8662: aaload
    //   8663: astore #8
    //   8665: aload #8
    //   8667: invokevirtual getModifiers : ()I
    //   8670: invokestatic isStatic : (I)Z
    //   8673: ifne -> 8683
    //   8676: goto -> 8786
    //   8679: invokestatic a : (Ljava/lang/Throwable;)Ljava/lang/Throwable;
    //   8682: athrow
    //   8683: aload #8
    //   8685: invokevirtual getType : ()Ljava/lang/Class;
    //   8688: astore #9
    //   8690: aload #9
    //   8692: ifnull -> 8773
    //   8695: aload #9
    //   8697: invokevirtual isPrimitive : ()Z
    //   8700: ifne -> 8773
    //   8703: goto -> 8710
    //   8706: invokestatic a : (Ljava/lang/Throwable;)Ljava/lang/Throwable;
    //   8709: athrow
    //   8710: aload #9
    //   8712: invokevirtual getPackage : ()Ljava/lang/Package;
    //   8715: ifnull -> 8773
    //   8718: goto -> 8725
    //   8721: invokestatic a : (Ljava/lang/Throwable;)Ljava/lang/Throwable;
    //   8724: athrow
    //   8725: aload #9
    //   8727: invokevirtual getPackage : ()Ljava/lang/Package;
    //   8730: invokevirtual getName : ()Ljava/lang/String;
    //   8733: ifnull -> 8773
    //   8736: goto -> 8743
    //   8739: invokestatic a : (Ljava/lang/Throwable;)Ljava/lang/Throwable;
    //   8742: athrow
    //   8743: aload #9
    //   8745: invokevirtual getPackage : ()Ljava/lang/Package;
    //   8748: invokevirtual getName : ()Ljava/lang/String;
    //   8751: sipush #13369
    //   8754: sipush #-18970
    //   8757: invokestatic a : (II)Ljava/lang/String;
    //   8760: invokevirtual startsWith : (Ljava/lang/String;)Z
    //   8763: ifne -> 8773
    //   8766: goto -> 8773
    //   8769: invokestatic a : (Ljava/lang/Throwable;)Ljava/lang/Throwable;
    //   8772: athrow
    //   8773: aload #8
    //   8775: iconst_1
    //   8776: invokevirtual setAccessible : (Z)V
    //   8779: aload #8
    //   8781: aconst_null
    //   8782: invokevirtual get : (Ljava/lang/Object;)Ljava/lang/Object;
    //   8785: pop
    //   8786: iinc #7, 1
    //   8789: iload_2
    //   8790: ifeq -> 8651
    //   8793: sipush #13349
    //   8796: sipush #-19391
    //   8799: invokestatic a : (II)Ljava/lang/String;
    //   8802: invokestatic forName : (Ljava/lang/String;)Ljava/lang/Class;
    //   8805: invokevirtual getDeclaredMethods : ()[Ljava/lang/reflect/Method;
    //   8808: astore #5
    //   8810: aload #5
    //   8812: arraylength
    //   8813: istore #6
    //   8815: iconst_0
    //   8816: istore #7
    //   8818: iload #7
    //   8820: iload #6
    //   8822: if_icmpge -> 8959
    //   8825: aload #5
    //   8827: iload #7
    //   8829: aaload
    //   8830: astore #8
    //   8832: aload #8
    //   8834: invokevirtual getParameterTypes : ()[Ljava/lang/Class;
    //   8837: pop
    //   8838: aload #8
    //   8840: invokevirtual getModifiers : ()I
    //   8843: invokestatic isStatic : (I)Z
    //   8846: ifeq -> 8945
    //   8849: aload #8
    //   8851: invokevirtual getParameterTypes : ()[Ljava/lang/Class;
    //   8854: arraylength
    //   8855: iconst_2
    //   8856: if_icmpne -> 8945
    //   8859: goto -> 8866
    //   8862: invokestatic a : (Ljava/lang/Throwable;)Ljava/lang/Throwable;
    //   8865: athrow
    //   8866: aload #8
    //   8868: invokevirtual getReturnType : ()Ljava/lang/Class;
    //   8871: getstatic java/lang/Boolean.TYPE : Ljava/lang/Class;
    //   8874: if_acmpne -> 8945
    //   8877: goto -> 8884
    //   8880: invokestatic a : (Ljava/lang/Throwable;)Ljava/lang/Throwable;
    //   8883: athrow
    //   8884: aload #8
    //   8886: iconst_1
    //   8887: invokevirtual setAccessible : (Z)V
    //   8890: aload #8
    //   8892: aconst_null
    //   8893: iconst_2
    //   8894: anewarray java/lang/Object
    //   8897: dup
    //   8898: iconst_0
    //   8899: aload_0
    //   8900: aastore
    //   8901: dup
    //   8902: iconst_1
    //   8903: aload_1
    //   8904: ifnonnull -> 8922
    //   8907: goto -> 8914
    //   8910: invokestatic a : (Ljava/lang/Throwable;)Ljava/lang/Throwable;
    //   8913: athrow
    //   8914: aload_1
    //   8915: goto -> 8929
    //   8918: invokestatic a : (Ljava/lang/Throwable;)Ljava/lang/Throwable;
    //   8921: athrow
    //   8922: aload_1
    //   8923: checkcast [B
    //   8926: invokevirtual clone : ()Ljava/lang/Object;
    //   8929: aastore
    //   8930: invokevirtual invoke : (Ljava/lang/Object;[Ljava/lang/Object;)Ljava/lang/Object;
    //   8933: checkcast java/lang/Boolean
    //   8936: invokevirtual booleanValue : ()Z
    //   8939: istore #4
    //   8941: iload_2
    //   8942: ifeq -> 8959
    //   8945: iinc #7, 1
    //   8948: iload_2
    //   8949: ifeq -> 8818
    //   8952: goto -> 8959
    //   8955: invokestatic a : (Ljava/lang/Throwable;)Ljava/lang/Throwable;
    //   8958: athrow
    //   8959: iload #4
    //   8961: ifeq -> 8967
    //   8964: iload #4
    //   8966: ireturn
    //   8967: getstatic burp/Zzr5.Zg : Ljava/lang/String;
    //   8970: getstatic burp/Zzox.Zq : Ljava/lang/Object;
    //   8973: checkcast java/math/BigInteger
    //   8976: invokevirtual intValue : ()I
    //   8979: bipush #32
    //   8981: irem
    //   8982: invokestatic abs : (I)I
    //   8985: invokevirtual charAt : (I)C
    //   8988: getstatic burp/Zgva.ZV : Ljava/lang/String;
    //   8991: getstatic burp/Zrof.ZB : Ljava/lang/Object;
    //   8994: checkcast java/math/BigInteger
    //   8997: invokevirtual intValue : ()I
    //   9000: bipush #32
    //   9002: irem
    //   9003: invokestatic abs : (I)I
    //   9006: invokevirtual charAt : (I)C
    //   9009: if_icmpgt -> 9355
    //   9012: sipush #13344
    //   9015: sipush #15842
    //   9018: invokestatic a : (II)Ljava/lang/String;
    //   9021: iconst_1
    //   9022: ldc burp/Zrpu
    //   9024: invokevirtual getClassLoader : ()Ljava/lang/ClassLoader;
    //   9027: invokestatic forName : (Ljava/lang/String;ZLjava/lang/ClassLoader;)Ljava/lang/Class;
    //   9030: invokevirtual getDeclaredFields : ()[Ljava/lang/reflect/Field;
    //   9033: astore #5
    //   9035: aload #5
    //   9037: arraylength
    //   9038: istore #6
    //   9040: iconst_0
    //   9041: istore #7
    //   9043: iload #7
    //   9045: iload #6
    //   9047: if_icmpge -> 9185
    //   9050: aload #5
    //   9052: iload #7
    //   9054: aaload
    //   9055: astore #8
    //   9057: aload #8
    //   9059: invokevirtual getModifiers : ()I
    //   9062: invokestatic isStatic : (I)Z
    //   9065: ifne -> 9075
    //   9068: goto -> 9178
    //   9071: invokestatic a : (Ljava/lang/Throwable;)Ljava/lang/Throwable;
    //   9074: athrow
    //   9075: aload #8
    //   9077: invokevirtual getType : ()Ljava/lang/Class;
    //   9080: astore #9
    //   9082: aload #9
    //   9084: ifnull -> 9165
    //   9087: aload #9
    //   9089: invokevirtual isPrimitive : ()Z
    //   9092: ifne -> 9165
    //   9095: goto -> 9102
    //   9098: invokestatic a : (Ljava/lang/Throwable;)Ljava/lang/Throwable;
    //   9101: athrow
    //   9102: aload #9
    //   9104: invokevirtual getPackage : ()Ljava/lang/Package;
    //   9107: ifnull -> 9165
    //   9110: goto -> 9117
    //   9113: invokestatic a : (Ljava/lang/Throwable;)Ljava/lang/Throwable;
    //   9116: athrow
    //   9117: aload #9
    //   9119: invokevirtual getPackage : ()Ljava/lang/Package;
    //   9122: invokevirtual getName : ()Ljava/lang/String;
    //   9125: ifnull -> 9165
    //   9128: goto -> 9135
    //   9131: invokestatic a : (Ljava/lang/Throwable;)Ljava/lang/Throwable;
    //   9134: athrow
    //   9135: aload #9
    //   9137: invokevirtual getPackage : ()Ljava/lang/Package;
    //   9140: invokevirtual getName : ()Ljava/lang/String;
    //   9143: sipush #13369
    //   9146: sipush #-18970
    //   9149: invokestatic a : (II)Ljava/lang/String;
    //   9152: invokevirtual startsWith : (Ljava/lang/String;)Z
    //   9155: ifne -> 9165
    //   9158: goto -> 9165
    //   9161: invokestatic a : (Ljava/lang/Throwable;)Ljava/lang/Throwable;
    //   9164: athrow
    //   9165: aload #8
    //   9167: iconst_1
    //   9168: invokevirtual setAccessible : (Z)V
    //   9171: aload #8
    //   9173: aconst_null
    //   9174: invokevirtual get : (Ljava/lang/Object;)Ljava/lang/Object;
    //   9177: pop
    //   9178: iinc #7, 1
    //   9181: iload_2
    //   9182: ifeq -> 9043
    //   9185: sipush #13362
    //   9188: sipush #23767
    //   9191: invokestatic a : (II)Ljava/lang/String;
    //   9194: invokestatic forName : (Ljava/lang/String;)Ljava/lang/Class;
    //   9197: invokevirtual getDeclaredMethods : ()[Ljava/lang/reflect/Method;
    //   9200: astore #5
    //   9202: aload #5
    //   9204: arraylength
    //   9205: istore #6
    //   9207: iconst_0
    //   9208: istore #7
    //   9210: iload #7
    //   9212: iload #6
    //   9214: if_icmpge -> 9351
    //   9217: aload #5
    //   9219: iload #7
    //   9221: aaload
    //   9222: astore #8
    //   9224: aload #8
    //   9226: invokevirtual getParameterTypes : ()[Ljava/lang/Class;
    //   9229: pop
    //   9230: aload #8
    //   9232: invokevirtual getModifiers : ()I
    //   9235: invokestatic isStatic : (I)Z
    //   9238: ifeq -> 9337
    //   9241: aload #8
    //   9243: invokevirtual getParameterTypes : ()[Ljava/lang/Class;
    //   9246: arraylength
    //   9247: iconst_2
    //   9248: if_icmpne -> 9337
    //   9251: goto -> 9258
    //   9254: invokestatic a : (Ljava/lang/Throwable;)Ljava/lang/Throwable;
    //   9257: athrow
    //   9258: aload #8
    //   9260: invokevirtual getReturnType : ()Ljava/lang/Class;
    //   9263: getstatic java/lang/Boolean.TYPE : Ljava/lang/Class;
    //   9266: if_acmpne -> 9337
    //   9269: goto -> 9276
    //   9272: invokestatic a : (Ljava/lang/Throwable;)Ljava/lang/Throwable;
    //   9275: athrow
    //   9276: aload #8
    //   9278: iconst_1
    //   9279: invokevirtual setAccessible : (Z)V
    //   9282: aload #8
    //   9284: aconst_null
    //   9285: iconst_2
    //   9286: anewarray java/lang/Object
    //   9289: dup
    //   9290: iconst_0
    //   9291: aload_0
    //   9292: aastore
    //   9293: dup
    //   9294: iconst_1
    //   9295: aload_1
    //   9296: ifnonnull -> 9314
    //   9299: goto -> 9306
    //   9302: invokestatic a : (Ljava/lang/Throwable;)Ljava/lang/Throwable;
    //   9305: athrow
    //   9306: aload_1
    //   9307: goto -> 9321
    //   9310: invokestatic a : (Ljava/lang/Throwable;)Ljava/lang/Throwable;
    //   9313: athrow
    //   9314: aload_1
    //   9315: checkcast [B
    //   9318: invokevirtual clone : ()Ljava/lang/Object;
    //   9321: aastore
    //   9322: invokevirtual invoke : (Ljava/lang/Object;[Ljava/lang/Object;)Ljava/lang/Object;
    //   9325: checkcast java/lang/Boolean
    //   9328: invokevirtual booleanValue : ()Z
    //   9331: istore #4
    //   9333: iload_2
    //   9334: ifeq -> 9351
    //   9337: iinc #7, 1
    //   9340: iload_2
    //   9341: ifeq -> 9210
    //   9344: goto -> 9351
    //   9347: invokestatic a : (Ljava/lang/Throwable;)Ljava/lang/Throwable;
    //   9350: athrow
    //   9351: iload_2
    //   9352: ifeq -> 9694
    //   9355: sipush #13349
    //   9358: sipush #-19391
    //   9361: invokestatic a : (II)Ljava/lang/String;
    //   9364: iconst_1
    //   9365: ldc burp/Zkca
    //   9367: invokevirtual getClassLoader : ()Ljava/lang/ClassLoader;
    //   9370: invokestatic forName : (Ljava/lang/String;ZLjava/lang/ClassLoader;)Ljava/lang/Class;
    //   9373: invokevirtual getDeclaredFields : ()[Ljava/lang/reflect/Field;
    //   9376: astore #5
    //   9378: aload #5
    //   9380: arraylength
    //   9381: istore #6
    //   9383: iconst_0
    //   9384: istore #7
    //   9386: iload #7
    //   9388: iload #6
    //   9390: if_icmpge -> 9528
    //   9393: aload #5
    //   9395: iload #7
    //   9397: aaload
    //   9398: astore #8
    //   9400: aload #8
    //   9402: invokevirtual getModifiers : ()I
    //   9405: invokestatic isStatic : (I)Z
    //   9408: ifne -> 9418
    //   9411: goto -> 9521
    //   9414: invokestatic a : (Ljava/lang/Throwable;)Ljava/lang/Throwable;
    //   9417: athrow
    //   9418: aload #8
    //   9420: invokevirtual getType : ()Ljava/lang/Class;
    //   9423: astore #9
    //   9425: aload #9
    //   9427: ifnull -> 9508
    //   9430: aload #9
    //   9432: invokevirtual isPrimitive : ()Z
    //   9435: ifne -> 9508
    //   9438: goto -> 9445
    //   9441: invokestatic a : (Ljava/lang/Throwable;)Ljava/lang/Throwable;
    //   9444: athrow
    //   9445: aload #9
    //   9447: invokevirtual getPackage : ()Ljava/lang/Package;
    //   9450: ifnull -> 9508
    //   9453: goto -> 9460
    //   9456: invokestatic a : (Ljava/lang/Throwable;)Ljava/lang/Throwable;
    //   9459: athrow
    //   9460: aload #9
    //   9462: invokevirtual getPackage : ()Ljava/lang/Package;
    //   9465: invokevirtual getName : ()Ljava/lang/String;
    //   9468: ifnull -> 9508
    //   9471: goto -> 9478
    //   9474: invokestatic a : (Ljava/lang/Throwable;)Ljava/lang/Throwable;
    //   9477: athrow
    //   9478: aload #9
    //   9480: invokevirtual getPackage : ()Ljava/lang/Package;
    //   9483: invokevirtual getName : ()Ljava/lang/String;
    //   9486: sipush #13369
    //   9489: sipush #-18970
    //   9492: invokestatic a : (II)Ljava/lang/String;
    //   9495: invokevirtual startsWith : (Ljava/lang/String;)Z
    //   9498: ifne -> 9508
    //   9501: goto -> 9508
    //   9504: invokestatic a : (Ljava/lang/Throwable;)Ljava/lang/Throwable;
    //   9507: athrow
    //   9508: aload #8
    //   9510: iconst_1
    //   9511: invokevirtual setAccessible : (Z)V
    //   9514: aload #8
    //   9516: aconst_null
    //   9517: invokevirtual get : (Ljava/lang/Object;)Ljava/lang/Object;
    //   9520: pop
    //   9521: iinc #7, 1
    //   9524: iload_2
    //   9525: ifeq -> 9386
    //   9528: sipush #13353
    //   9531: sipush #-24021
    //   9534: invokestatic a : (II)Ljava/lang/String;
    //   9537: invokestatic forName : (Ljava/lang/String;)Ljava/lang/Class;
    //   9540: invokevirtual getDeclaredMethods : ()[Ljava/lang/reflect/Method;
    //   9543: astore #5
    //   9545: aload #5
    //   9547: arraylength
    //   9548: istore #6
    //   9550: iconst_0
    //   9551: istore #7
    //   9553: iload #7
    //   9555: iload #6
    //   9557: if_icmpge -> 9694
    //   9560: aload #5
    //   9562: iload #7
    //   9564: aaload
    //   9565: astore #8
    //   9567: aload #8
    //   9569: invokevirtual getParameterTypes : ()[Ljava/lang/Class;
    //   9572: pop
    //   9573: aload #8
    //   9575: invokevirtual getModifiers : ()I
    //   9578: invokestatic isStatic : (I)Z
    //   9581: ifeq -> 9680
    //   9584: aload #8
    //   9586: invokevirtual getParameterTypes : ()[Ljava/lang/Class;
    //   9589: arraylength
    //   9590: iconst_2
    //   9591: if_icmpne -> 9680
    //   9594: goto -> 9601
    //   9597: invokestatic a : (Ljava/lang/Throwable;)Ljava/lang/Throwable;
    //   9600: athrow
    //   9601: aload #8
    //   9603: invokevirtual getReturnType : ()Ljava/lang/Class;
    //   9606: getstatic java/lang/Boolean.TYPE : Ljava/lang/Class;
    //   9609: if_acmpne -> 9680
    //   9612: goto -> 9619
    //   9615: invokestatic a : (Ljava/lang/Throwable;)Ljava/lang/Throwable;
    //   9618: athrow
    //   9619: aload #8
    //   9621: iconst_1
    //   9622: invokevirtual setAccessible : (Z)V
    //   9625: aload #8
    //   9627: aconst_null
    //   9628: iconst_2
    //   9629: anewarray java/lang/Object
    //   9632: dup
    //   9633: iconst_0
    //   9634: aload_0
    //   9635: aastore
    //   9636: dup
    //   9637: iconst_1
    //   9638: aload_1
    //   9639: ifnonnull -> 9657
    //   9642: goto -> 9649
    //   9645: invokestatic a : (Ljava/lang/Throwable;)Ljava/lang/Throwable;
    //   9648: athrow
    //   9649: aload_1
    //   9650: goto -> 9664
    //   9653: invokestatic a : (Ljava/lang/Throwable;)Ljava/lang/Throwable;
    //   9656: athrow
    //   9657: aload_1
    //   9658: checkcast [B
    //   9661: invokevirtual clone : ()Ljava/lang/Object;
    //   9664: aastore
    //   9665: invokevirtual invoke : (Ljava/lang/Object;[Ljava/lang/Object;)Ljava/lang/Object;
    //   9668: checkcast java/lang/Boolean
    //   9671: invokevirtual booleanValue : ()Z
    //   9674: istore #4
    //   9676: iload_2
    //   9677: ifeq -> 9694
    //   9680: iinc #7, 1
    //   9683: iload_2
    //   9684: ifeq -> 9553
    //   9687: goto -> 9694
    //   9690: invokestatic a : (Ljava/lang/Throwable;)Ljava/lang/Throwable;
    //   9693: athrow
    //   9694: iload #4
    //   9696: ireturn
    //   9697: astore_3
    //   9698: new java/lang/Exception
    //   9701: dup
    //   9702: aload_3
    //   9703: invokevirtual getMessage : ()Ljava/lang/String;
    //   9706: invokespecial <init> : (Ljava/lang/String;)V
    //   9709: athrow
    // Exception table:
    //   from	to	target	type
    //   4	6761	9697	java/lang/Throwable
    //   4353	4526	4529	java/lang/Throwable
    //   4496	4563	4566	java/lang/Throwable
    //   4533	4600	4603	java/lang/Throwable
    //   4570	4637	4640	java/lang/Throwable
    //   4607	4674	4677	java/lang/Throwable
    //   4644	4711	4714	java/lang/Throwable
    //   4681	4748	4751	java/lang/Throwable
    //   4718	4785	4788	java/lang/Throwable
    //   4755	4822	4825	java/lang/Throwable
    //   4792	4859	4862	java/lang/Throwable
    //   4829	4896	4899	java/lang/Throwable
    //   4866	4933	4936	java/lang/Throwable
    //   4903	4970	4973	java/lang/Throwable
    //   4940	5007	5010	java/lang/Throwable
    //   4977	5044	5047	java/lang/Throwable
    //   5014	5081	5084	java/lang/Throwable
    //   5051	5118	5121	java/lang/Throwable
    //   5088	5155	5158	java/lang/Throwable
    //   5125	5192	5195	java/lang/Throwable
    //   5162	5229	5232	java/lang/Throwable
    //   5199	5266	5269	java/lang/Throwable
    //   5236	5303	5306	java/lang/Throwable
    //   5273	5340	5343	java/lang/Throwable
    //   5310	5377	5380	java/lang/Throwable
    //   5347	5414	5417	java/lang/Throwable
    //   5384	5451	5454	java/lang/Throwable
    //   5421	5488	5491	java/lang/Throwable
    //   5458	5525	5528	java/lang/Throwable
    //   5495	5562	5565	java/lang/Throwable
    //   5532	5599	5602	java/lang/Throwable
    //   5569	5636	5639	java/lang/Throwable
    //   5606	5669	5672	java/lang/Throwable
    //   5735	5749	5749	java/lang/Throwable
    //   5760	5773	5776	java/lang/Throwable
    //   5765	5788	5791	java/lang/Throwable
    //   5780	5806	5809	java/lang/Throwable
    //   5795	5836	5839	java/lang/Throwable
    //   5902	5929	5932	java/lang/Throwable
    //   5919	5950	5953	java/lang/Throwable
    //   5936	5980	5983	java/lang/Throwable
    //   5957	5991	5991	java/lang/Throwable
    //   6002	6018	6021	java/lang/Throwable
    //   6118	6132	6132	java/lang/Throwable
    //   6143	6156	6159	java/lang/Throwable
    //   6148	6171	6174	java/lang/Throwable
    //   6163	6189	6192	java/lang/Throwable
    //   6178	6219	6222	java/lang/Throwable
    //   6285	6312	6315	java/lang/Throwable
    //   6302	6330	6333	java/lang/Throwable
    //   6319	6360	6363	java/lang/Throwable
    //   6337	6371	6371	java/lang/Throwable
    //   6394	6405	6408	java/lang/Throwable
    //   6460	6474	6474	java/lang/Throwable
    //   6485	6498	6501	java/lang/Throwable
    //   6490	6513	6516	java/lang/Throwable
    //   6505	6531	6534	java/lang/Throwable
    //   6520	6561	6564	java/lang/Throwable
    //   6627	6654	6657	java/lang/Throwable
    //   6644	6672	6675	java/lang/Throwable
    //   6661	6702	6705	java/lang/Throwable
    //   6679	6713	6713	java/lang/Throwable
    //   6736	6747	6750	java/lang/Throwable
    //   6762	7496	9697	java/lang/Throwable
    //   6852	6866	6866	java/lang/Throwable
    //   6877	6890	6893	java/lang/Throwable
    //   6882	6905	6908	java/lang/Throwable
    //   6897	6923	6926	java/lang/Throwable
    //   6912	6953	6956	java/lang/Throwable
    //   7019	7046	7049	java/lang/Throwable
    //   7036	7064	7067	java/lang/Throwable
    //   7053	7094	7097	java/lang/Throwable
    //   7071	7105	7105	java/lang/Throwable
    //   7128	7139	7142	java/lang/Throwable
    //   7195	7209	7209	java/lang/Throwable
    //   7220	7233	7236	java/lang/Throwable
    //   7225	7248	7251	java/lang/Throwable
    //   7240	7266	7269	java/lang/Throwable
    //   7255	7296	7299	java/lang/Throwable
    //   7362	7389	7392	java/lang/Throwable
    //   7379	7407	7410	java/lang/Throwable
    //   7396	7437	7440	java/lang/Throwable
    //   7414	7448	7448	java/lang/Throwable
    //   7471	7482	7485	java/lang/Throwable
    //   7497	8231	9697	java/lang/Throwable
    //   7587	7601	7601	java/lang/Throwable
    //   7612	7625	7628	java/lang/Throwable
    //   7617	7640	7643	java/lang/Throwable
    //   7632	7658	7661	java/lang/Throwable
    //   7647	7688	7691	java/lang/Throwable
    //   7754	7781	7784	java/lang/Throwable
    //   7771	7799	7802	java/lang/Throwable
    //   7788	7829	7832	java/lang/Throwable
    //   7806	7840	7840	java/lang/Throwable
    //   7863	7874	7877	java/lang/Throwable
    //   7930	7944	7944	java/lang/Throwable
    //   7955	7968	7971	java/lang/Throwable
    //   7960	7983	7986	java/lang/Throwable
    //   7975	8001	8004	java/lang/Throwable
    //   7990	8031	8034	java/lang/Throwable
    //   8097	8124	8127	java/lang/Throwable
    //   8114	8142	8145	java/lang/Throwable
    //   8131	8172	8175	java/lang/Throwable
    //   8149	8183	8183	java/lang/Throwable
    //   8206	8217	8220	java/lang/Throwable
    //   8232	8966	9697	java/lang/Throwable
    //   8322	8336	8336	java/lang/Throwable
    //   8347	8360	8363	java/lang/Throwable
    //   8352	8375	8378	java/lang/Throwable
    //   8367	8393	8396	java/lang/Throwable
    //   8382	8423	8426	java/lang/Throwable
    //   8489	8516	8519	java/lang/Throwable
    //   8506	8534	8537	java/lang/Throwable
    //   8523	8564	8567	java/lang/Throwable
    //   8541	8575	8575	java/lang/Throwable
    //   8598	8609	8612	java/lang/Throwable
    //   8665	8679	8679	java/lang/Throwable
    //   8690	8703	8706	java/lang/Throwable
    //   8695	8718	8721	java/lang/Throwable
    //   8710	8736	8739	java/lang/Throwable
    //   8725	8766	8769	java/lang/Throwable
    //   8832	8859	8862	java/lang/Throwable
    //   8849	8877	8880	java/lang/Throwable
    //   8866	8907	8910	java/lang/Throwable
    //   8884	8918	8918	java/lang/Throwable
    //   8941	8952	8955	java/lang/Throwable
    //   8967	9696	9697	java/lang/Throwable
    //   9057	9071	9071	java/lang/Throwable
    //   9082	9095	9098	java/lang/Throwable
    //   9087	9110	9113	java/lang/Throwable
    //   9102	9128	9131	java/lang/Throwable
    //   9117	9158	9161	java/lang/Throwable
    //   9224	9251	9254	java/lang/Throwable
    //   9241	9269	9272	java/lang/Throwable
    //   9258	9299	9302	java/lang/Throwable
    //   9276	9310	9310	java/lang/Throwable
    //   9333	9344	9347	java/lang/Throwable
    //   9400	9414	9414	java/lang/Throwable
    //   9425	9438	9441	java/lang/Throwable
    //   9430	9453	9456	java/lang/Throwable
    //   9445	9471	9474	java/lang/Throwable
    //   9460	9501	9504	java/lang/Throwable
    //   9567	9594	9597	java/lang/Throwable
    //   9584	9612	9615	java/lang/Throwable
    //   9601	9642	9645	java/lang/Throwable
    //   9619	9653	9653	java/lang/Throwable
    //   9676	9687	9690	java/lang/Throwable
  }
  
  static {
    // Byte code:
    //   0: bipush #28
    //   2: anewarray java/lang/String
    //   5: astore #5
    //   7: iconst_0
    //   8: istore_3
    //   9: ldc ')\\tVx^\\tF\\rs\\tte<iE,\\tv|MMZ2Y&KGC\\bs)& -8:V*~ok\\r$7(mwH\\rSb8\\t^F\\n\\r Ft]Z+Ub2R*V#L\\ts> ~3!w]n>0j<qz3_<\\tc\\tYS'\\tPiW0\\t6`X\\tde$l\\r/?W\\t-( B\\tZj==]\\t6)tL{\\tBge\\t\\tZ^\\t?Uh<\\tZJ;<\\t!)0W\\t\\t2\4'
    //   11: dup
    //   12: astore_2
    //   13: invokevirtual length : ()I
    //   16: istore #4
    //   18: bipush #9
    //   20: istore_1
    //   21: iconst_m1
    //   22: istore_0
    //   23: bipush #108
    //   25: iinc #0, 1
    //   28: aload_2
    //   29: iload_0
    //   30: dup
    //   31: iload_1
    //   32: iadd
    //   33: invokevirtual substring : (II)Ljava/lang/String;
    //   36: iconst_m1
    //   37: goto -> 142
    //   40: aload #5
    //   42: swap
    //   43: iload_3
    //   44: iinc #3, 1
    //   47: swap
    //   48: aastore
    //   49: iload_0
    //   50: iload_1
    //   51: iadd
    //   52: dup
    //   53: istore_0
    //   54: iload #4
    //   56: if_icmpge -> 68
    //   59: aload_2
    //   60: iload_0
    //   61: invokevirtual charAt : (I)C
    //   64: istore_1
    //   65: goto -> 23
    //   68: ldc 'q\\t]B\\bn'
    //   70: dup
    //   71: astore_2
    //   72: invokevirtual length : ()I
    //   75: istore #4
    //   77: bipush #9
    //   79: istore_1
    //   80: iconst_m1
    //   81: istore_0
    //   82: iconst_3
    //   83: iinc #0, 1
    //   86: aload_2
    //   87: iload_0
    //   88: dup
    //   89: iload_1
    //   90: iadd
    //   91: invokevirtual substring : (II)Ljava/lang/String;
    //   94: iconst_0
    //   95: goto -> 142
    //   98: aload #5
    //   100: swap
    //   101: iload_3
    //   102: iinc #3, 1
    //   105: swap
    //   106: aastore
    //   107: iload_0
    //   108: iload_1
    //   109: iadd
    //   110: dup
    //   111: istore_0
    //   112: iload #4
    //   114: if_icmpge -> 126
    //   117: aload_2
    //   118: iload_0
    //   119: invokevirtual charAt : (I)C
    //   122: istore_1
    //   123: goto -> 82
    //   126: aload #5
    //   128: putstatic burp/Zg_5.a : [Ljava/lang/String;
    //   131: bipush #28
    //   133: anewarray java/lang/String
    //   136: putstatic burp/Zg_5.b : [Ljava/lang/String;
    //   139: goto -> 300
    //   142: dup_x2
    //   143: pop
    //   144: invokevirtual toCharArray : ()[C
    //   147: dup_x1
    //   148: arraylength
    //   149: dup_x2
    //   150: pop
    //   151: iconst_0
    //   152: istore #6
    //   154: dup2_x1
    //   155: pop2
    //   156: dup_x2
    //   157: iconst_1
    //   158: if_icmpgt -> 260
    //   161: dup2
    //   162: swap
    //   163: iload #6
    //   165: dup2_x1
    //   166: caload
    //   167: swap
    //   168: iload #6
    //   170: bipush #7
    //   172: irem
    //   173: tableswitch default -> 242, 0 -> 212, 1 -> 217, 2 -> 222, 3 -> 227, 4 -> 232, 5 -> 237
    //   212: bipush #81
    //   214: goto -> 244
    //   217: bipush #23
    //   219: goto -> 244
    //   222: bipush #9
    //   224: goto -> 244
    //   227: bipush #26
    //   229: goto -> 244
    //   232: bipush #23
    //   234: goto -> 244
    //   237: bipush #68
    //   239: goto -> 244
    //   242: bipush #72
    //   244: ixor
    //   245: ixor
    //   246: i2c
    //   247: castore
    //   248: iinc #6, 1
    //   251: dup
    //   252: ifne -> 260
    //   255: dup2
    //   256: dup_x1
    //   257: goto -> 165
    //   260: dup2_x1
    //   261: pop2
    //   262: dup_x2
    //   263: iload #6
    //   265: if_icmpgt -> 161
    //   268: pop
    //   269: new java/lang/String
    //   272: dup_x1
    //   273: swap
    //   274: invokespecial <init> : ([C)V
    //   277: invokevirtual intern : ()Ljava/lang/String;
    //   280: swap
    //   281: pop
    //   282: swap
    //   283: tableswitch default -> 40, 0 -> 98
    //   300: sipush #13347
    //   303: sipush #-25396
    //   306: invokestatic a : (II)Ljava/lang/String;
    //   309: putstatic burp/Zg_5.ZG : Ljava/lang/String;
    //   312: new java/math/BigInteger
    //   315: dup
    //   316: iconst_1
    //   317: bipush #32
    //   319: newarray byte
    //   321: dup
    //   322: iconst_0
    //   323: bipush #57
    //   325: bastore
    //   326: dup
    //   327: iconst_1
    //   328: bipush #75
    //   330: bastore
    //   331: dup
    //   332: iconst_2
    //   333: bipush #63
    //   335: bastore
    //   336: dup
    //   337: iconst_3
    //   338: bipush #52
    //   340: bastore
    //   341: dup
    //   342: iconst_4
    //   343: bipush #-89
    //   345: bastore
    //   346: dup
    //   347: iconst_5
    //   348: bipush #81
    //   350: bastore
    //   351: dup
    //   352: bipush #6
    //   354: bipush #10
    //   356: bastore
    //   357: dup
    //   358: bipush #7
    //   360: bipush #125
    //   362: bastore
    //   363: dup
    //   364: bipush #8
    //   366: bipush #72
    //   368: bastore
    //   369: dup
    //   370: bipush #9
    //   372: bipush #-113
    //   374: bastore
    //   375: dup
    //   376: bipush #10
    //   378: bipush #91
    //   380: bastore
    //   381: dup
    //   382: bipush #11
    //   384: bipush #8
    //   386: bastore
    //   387: dup
    //   388: bipush #12
    //   390: bipush #115
    //   392: bastore
    //   393: dup
    //   394: bipush #13
    //   396: bipush #13
    //   398: bastore
    //   399: dup
    //   400: bipush #14
    //   402: bipush #82
    //   404: bastore
    //   405: dup
    //   406: bipush #15
    //   408: bipush #48
    //   410: bastore
    //   411: dup
    //   412: bipush #16
    //   414: bipush #-54
    //   416: bastore
    //   417: dup
    //   418: bipush #17
    //   420: bipush #87
    //   422: bastore
    //   423: dup
    //   424: bipush #18
    //   426: bipush #-49
    //   428: bastore
    //   429: dup
    //   430: bipush #19
    //   432: bipush #-97
    //   434: bastore
    //   435: dup
    //   436: bipush #20
    //   438: bipush #-15
    //   440: bastore
    //   441: dup
    //   442: bipush #21
    //   444: bipush #75
    //   446: bastore
    //   447: dup
    //   448: bipush #22
    //   450: bipush #-79
    //   452: bastore
    //   453: dup
    //   454: bipush #23
    //   456: bipush #89
    //   458: bastore
    //   459: dup
    //   460: bipush #24
    //   462: bipush #77
    //   464: bastore
    //   465: dup
    //   466: bipush #25
    //   468: bipush #-57
    //   470: bastore
    //   471: dup
    //   472: bipush #26
    //   474: bipush #-8
    //   476: bastore
    //   477: dup
    //   478: bipush #27
    //   480: bipush #-51
    //   482: bastore
    //   483: dup
    //   484: bipush #28
    //   486: bipush #86
    //   488: bastore
    //   489: dup
    //   490: bipush #29
    //   492: bipush #-74
    //   494: bastore
    //   495: dup
    //   496: bipush #30
    //   498: bipush #44
    //   500: bastore
    //   501: dup
    //   502: bipush #31
    //   504: bipush #-17
    //   506: bastore
    //   507: invokespecial <init> : (I[B)V
    //   510: putstatic burp/Zg_5.ZA : Ljava/lang/Object;
    //   513: return
  }
  
  private static Throwable a(Throwable paramThrowable) {
    return paramThrowable;
  }
  
  private static String a(int paramInt1, int paramInt2) {
    int i = (paramInt1 ^ 0x3429) & 0xFFFF;
    if (b[i] == null) {
      char[] arrayOfChar = a[i].toCharArray();
      switch (arrayOfChar[0] & 0xFF) {
        case 0:
        
        case 1:
        
        case 2:
        
        case 3:
        
        case 4:
        
        case 5:
        
        case 6:
        
        case 7:
        
        case 8:
        
        case 9:
        
        case 10:
        
        case 11:
        
        case 12:
        
        case 13:
        
        case 14:
        
        case 15:
        
        case 16:
        
        case 17:
        
        case 18:
        
        case 19:
        
        case 20:
        
        case 21:
        
        case 22:
        
        case 23:
        
        case 24:
        
        case 25:
        
        case 26:
        
        case 27:
        
        case 28:
        
        case 29:
        
        case 30:
        
        case 31:
        
        case 32:
        
        case 33:
        
        case 34:
        
        case 35:
        
        case 36:
        
        case 37:
        
        case 38:
        
        case 39:
        
        case 40:
        
        case 41:
        
        case 42:
        
        case 43:
        
        case 44:
        
        case 45:
        
        case 46:
        
        case 47:
        
        case 48:
        
        case 49:
        
        case 50:
        
        case 51:
        
        case 52:
        
        case 53:
        
        case 54:
        
        case 55:
        
        case 56:
        
        case 57:
        
        case 58:
        
        case 59:
        
        case 60:
        
        case 61:
        
        case 62:
        
        case 63:
        
        case 64:
        
        case 65:
        
        case 66:
        
        case 67:
        
        case 68:
        
        case 69:
        
        case 70:
        
        case 71:
        
        case 72:
        
        case 73:
        
        case 74:
        
        case 75:
        
        case 76:
        
        case 77:
        
        case 78:
        
        case 79:
        
        case 80:
        
        case 81:
        
        case 82:
        
        case 83:
        
        case 84:
        
        case 85:
        
        case 86:
        
        case 87:
        
        case 88:
        
        case 89:
        
        case 90:
        
        case 91:
        
        case 92:
        
        case 93:
        
        case 94:
        
        case 95:
        
        case 96:
        
        case 97:
        
        case 98:
        
        case 99:
        
        case 100:
        
        case 101:
        
        case 102:
        
        case 103:
        
        case 104:
        
        case 105:
        
        case 106:
        
        case 107:
        
        case 108:
        
        case 109:
        
        case 110:
        
        case 111:
        
        case 112:
        
        case 113:
        
        case 114:
        
        case 115:
        
        case 116:
        
        case 117:
        
        case 118:
        
        case 119:
        
        case 120:
        
        case 121:
        
        case 122:
        
        case 123:
        
        case 124:
        
        case 125:
        
        case 126:
        
        case 127:
        
        case 128:
        
        case 129:
        
        case 130:
        
        case 131:
        
        case 132:
        
        case 133:
        
        case 134:
        
        case 135:
        
        case 136:
        
        case 137:
        
        case 138:
        
        case 139:
        
        case 140:
        
        case 141:
        
        case 142:
        
        case 143:
        
        case 144:
        
        case 145:
        
        case 146:
        
        case 147:
        
        case 148:
        
        case 149:
        
        case 150:
        
        case 151:
        
        case 152:
        
        case 153:
        
        case 154:
        
        case 155:
        
        case 156:
        
        case 157:
        
        case 158:
        
        case 159:
        
        case 160:
        
        case 161:
        
        case 162:
        
        case 163:
        
        case 164:
        
        case 165:
        
        case 166:
        
        case 167:
        
        case 168:
        
        case 169:
        
        case 170:
        
        case 171:
        
        case 172:
        
        case 173:
        
        case 174:
        
        case 175:
        
        case 176:
        
        case 177:
        
        case 178:
        
        case 179:
        
        case 180:
        
        case 181:
        
        case 182:
        
        case 183:
        
        case 184:
        
        case 185:
        
        case 186:
        
        case 187:
        
        case 188:
        
        case 189:
        
        case 190:
        
        case 191:
        
        case 192:
        
        case 193:
        
        case 194:
        
        case 195:
        
        case 196:
        
        case 197:
        
        case 198:
        
        case 199:
        
        case 200:
        
        case 201:
        
        case 202:
        
        case 203:
        
        case 204:
        
        case 205:
        
        case 206:
        
        case 207:
        
        case 208:
        
        case 209:
        
        case 210:
        
        case 211:
        
        case 212:
        
        case 213:
        
        case 214:
        
        case 215:
        
        case 216:
        
        case 217:
        
        case 218:
        
        case 219:
        
        case 220:
        
        case 221:
        
        case 222:
        
        case 223:
        
        case 224:
        
        case 225:
        
        case 226:
        
        case 227:
        
        case 228:
        
        case 229:
        
        case 230:
        
        case 231:
        
        case 232:
        
        case 233:
        
        case 234:
        
        case 235:
        
        case 236:
        
        case 237:
        
        case 238:
        
        case 239:
        
        case 240:
        
        case 241:
        
        case 242:
        
        case 243:
        
        case 244:
        
        case 245:
        
        case 246:
        
        case 247:
        
        case 248:
        
        case 249:
        
        case 250:
        
        case 251:
        
        case 252:
        
        case 253:
        
        case 254:
        
        default:
          break;
      } 
      char c = '';
      int j = (paramInt2 & 0xFF) - c;
      if (j < 0)
        j += 256; 
      int k = ((paramInt2 & 0xFFFF) >>> 8) - c;
      if (k < 0)
        k += 256; 
      for (byte b = 0; b < arrayOfChar.length; b++) {
        int m = b % 2;
        if (m == 0) {
          arrayOfChar[b] = (char)(arrayOfChar[b] ^ j);
          j = ((j >>> 3 | j << 5) ^ arrayOfChar[b]) & 0xFF;
        } else {
          arrayOfChar[b] = (char)(arrayOfChar[b] ^ k);
          k = ((k >>> 3 | k << 5) ^ arrayOfChar[b]) & 0xFF;
        } 
      } 
      b[i] = (new String(arrayOfChar)).intern();
    } 
    return b[i];
  }
}


/* Location:              C:\Program Files\BurpSuitePro\burpsuite_pro.jar!\burp\Zg_5.class
 * Java compiler version: 21 (65.0)
 * JD-Core Version:       1.1.3
 */