package burp;

import java.util.prefs.Preferences;
import net.portswigger.Zah;
import net.portswigger.Zk_;

public class Zgbm {
  private static final String[] a;
  
  private static final String[] b;
  
  public static void ZZ(Preferences paramPreferences, String paramString1, String paramString2) {
    // Byte code:
    //   0: invokestatic ZcN : ()[I
    //   3: astore_3
    //   4: aload_1
    //   5: invokevirtual length : ()I
    //   8: bipush #75
    //   10: if_icmple -> 34
    //   13: new java/lang/Exception
    //   16: dup
    //   17: sipush #11972
    //   20: sipush #27231
    //   23: invokestatic a : (II)Ljava/lang/String;
    //   26: invokespecial <init> : (Ljava/lang/String;)V
    //   29: athrow
    //   30: invokestatic a : (Ljava/lang/Exception;)Ljava/lang/Exception;
    //   33: athrow
    //   34: iconst_1
    //   35: istore #4
    //   37: aload_2
    //   38: invokevirtual length : ()I
    //   41: sipush #8192
    //   44: if_icmpgt -> 64
    //   47: aload_0
    //   48: aload_1
    //   49: aload_2
    //   50: invokevirtual put : (Ljava/lang/String;Ljava/lang/String;)V
    //   53: aload_3
    //   54: ifnonnull -> 161
    //   57: goto -> 64
    //   60: invokestatic a : (Ljava/lang/Exception;)Ljava/lang/Exception;
    //   63: athrow
    //   64: aload_2
    //   65: invokevirtual length : ()I
    //   68: sipush #8192
    //   71: idiv
    //   72: iconst_1
    //   73: iadd
    //   74: istore #5
    //   76: iconst_0
    //   77: istore #6
    //   79: iload #6
    //   81: iload #5
    //   83: if_icmpge -> 157
    //   86: iload #6
    //   88: ifne -> 99
    //   91: aload_1
    //   92: goto -> 107
    //   95: invokestatic a : (Ljava/lang/Exception;)Ljava/lang/Exception;
    //   98: athrow
    //   99: aload_1
    //   100: iload #6
    //   102: <illegal opcode> makeConcatWithConstants : (Ljava/lang/String;I)Ljava/lang/String;
    //   107: astore #7
    //   109: iload #6
    //   111: sipush #8192
    //   114: imul
    //   115: istore #8
    //   117: iload #8
    //   119: sipush #8192
    //   122: iadd
    //   123: aload_2
    //   124: invokevirtual length : ()I
    //   127: invokestatic min : (II)I
    //   130: istore #9
    //   132: aload_2
    //   133: iload #8
    //   135: iload #9
    //   137: invokevirtual substring : (II)Ljava/lang/String;
    //   140: astore #10
    //   142: aload_0
    //   143: aload #7
    //   145: aload #10
    //   147: invokevirtual put : (Ljava/lang/String;Ljava/lang/String;)V
    //   150: iinc #6, 1
    //   153: aload_3
    //   154: ifnonnull -> 79
    //   157: iload #5
    //   159: istore #4
    //   161: aconst_null
    //   162: aload_0
    //   163: aload_1
    //   164: iload #4
    //   166: <illegal opcode> makeConcatWithConstants : (Ljava/lang/String;I)Ljava/lang/String;
    //   171: aconst_null
    //   172: invokevirtual get : (Ljava/lang/String;Ljava/lang/String;)Ljava/lang/String;
    //   175: if_acmpeq -> 197
    //   178: aload_0
    //   179: aload_1
    //   180: iload #4
    //   182: <illegal opcode> makeConcatWithConstants : (Ljava/lang/String;I)Ljava/lang/String;
    //   187: invokevirtual remove : (Ljava/lang/String;)V
    //   190: iinc #4, 1
    //   193: aload_3
    //   194: ifnonnull -> 161
    //   197: goto -> 210
    //   200: astore #4
    //   202: aload #4
    //   204: getstatic net/portswigger/Zk_.UNEXPECTED : Lnet/portswigger/Zk_;
    //   207: invokestatic Zl : (Ljava/lang/Throwable;Lnet/portswigger/Zk_;)V
    //   210: return
    // Exception table:
    //   from	to	target	type
    //   4	30	30	java/lang/Exception
    //   4	197	200	java/lang/Exception
    //   37	57	60	java/lang/Exception
    //   86	95	95	java/lang/Exception
  }
  
  public static String ZB(Preferences paramPreferences, String paramString) {
    int[] arrayOfInt = Zkro.ZcN();
    String str = paramPreferences.get(paramString, null);
    if (str == null)
      return null; 
    if (str.length() < 8192)
      return str; 
    StringBuilder stringBuilder = new StringBuilder(str);
    byte b = 1;
    do {
      String str1 = paramPreferences.get(paramString + "_" + paramString, null);
      if (str1 == null)
        break; 
      stringBuilder.append(str1);
      b++;
    } while (arrayOfInt != null);
    return stringBuilder.toString();
  }
  
  public static boolean ZO(Preferences paramPreferences, String paramString) {
    int[] arrayOfInt = Zkro.ZcN();
    try {
      try {
        if (paramString.length() > 75)
          throw new Exception(a(11973, 14653)); 
      } catch (Exception exception) {
        throw a(null);
      } 
      boolean bool = false;
      byte b = 0;
      do {
        String str = !b ? paramString : (paramString + "_" + paramString);
        try {
          if (null == paramPreferences.get(str, null))
            break; 
        } catch (Exception exception) {
          throw a(null);
        } 
        paramPreferences.remove(str);
        bool = true;
        b++;
      } while (arrayOfInt != null);
      return bool;
    } catch (Exception exception) {
      Zah.Zl(exception, Zk_.UNEXPECTED);
      return false;
    } 
  }
  
  private static Exception a(Exception paramException) {
    return paramException;
  }
  
  static {
    // Byte code:
    //   0: iconst_2
    //   1: anewarray java/lang/String
    //   4: astore #5
    //   6: iconst_0
    //   7: istore_3
    //   8: ldc 'Ã¨Ã¿Â¶Â„Ã©Ã·Â¬'|s}Ã³Â•eÃ®Â·dÃ—sÂºÂ‡Â·[ÂTÃ–[Ã‘Ã¸ÃÂžÃ•aÂ±Ãº-Â¾Ã™Ã¶Ã„Âž'
    //   10: dup
    //   11: astore_2
    //   12: invokevirtual length : ()I
    //   15: istore #4
    //   17: bipush #24
    //   19: istore_1
    //   20: iconst_m1
    //   21: istore_0
    //   22: bipush #116
    //   24: iinc #0, 1
    //   27: aload_2
    //   28: iload_0
    //   29: dup
    //   30: iload_1
    //   31: iadd
    //   32: invokevirtual substring : (II)Ljava/lang/String;
    //   35: iconst_m1
    //   36: goto -> 82
    //   39: aload #5
    //   41: swap
    //   42: iload_3
    //   43: iinc #3, 1
    //   46: swap
    //   47: aastore
    //   48: iload_0
    //   49: iload_1
    //   50: iadd
    //   51: dup
    //   52: istore_0
    //   53: iload #4
    //   55: if_icmpge -> 67
    //   58: aload_2
    //   59: iload_0
    //   60: invokevirtual charAt : (I)C
    //   63: istore_1
    //   64: goto -> 22
    //   67: aload #5
    //   69: putstatic burp/Zgbm.a : [Ljava/lang/String;
    //   72: iconst_2
    //   73: anewarray java/lang/String
    //   76: putstatic burp/Zgbm.b : [Ljava/lang/String;
    //   79: goto -> 227
    //   82: dup_x2
    //   83: pop
    //   84: invokevirtual toCharArray : ()[C
    //   87: dup_x1
    //   88: arraylength
    //   89: dup_x2
    //   90: pop
    //   91: iconst_0
    //   92: istore #6
    //   94: dup2_x1
    //   95: pop2
    //   96: dup_x2
    //   97: iconst_1
    //   98: if_icmpgt -> 200
    //   101: dup2
    //   102: swap
    //   103: iload #6
    //   105: dup2_x1
    //   106: caload
    //   107: swap
    //   108: iload #6
    //   110: bipush #7
    //   112: irem
    //   113: tableswitch default -> 182, 0 -> 152, 1 -> 157, 2 -> 162, 3 -> 167, 4 -> 172, 5 -> 177
    //   152: bipush #95
    //   154: goto -> 184
    //   157: bipush #106
    //   159: goto -> 184
    //   162: bipush #121
    //   164: goto -> 184
    //   167: bipush #6
    //   169: goto -> 184
    //   172: bipush #79
    //   174: goto -> 184
    //   177: bipush #14
    //   179: goto -> 184
    //   182: bipush #13
    //   184: ixor
    //   185: ixor
    //   186: i2c
    //   187: castore
    //   188: iinc #6, 1
    //   191: dup
    //   192: ifne -> 200
    //   195: dup2
    //   196: dup_x1
    //   197: goto -> 105
    //   200: dup2_x1
    //   201: pop2
    //   202: dup_x2
    //   203: iload #6
    //   205: if_icmpgt -> 101
    //   208: pop
    //   209: new java/lang/String
    //   212: dup_x1
    //   213: swap
    //   214: invokespecial <init> : ([C)V
    //   217: invokevirtual intern : ()Ljava/lang/String;
    //   220: swap
    //   221: pop
    //   222: swap
    //   223: pop
    //   224: goto -> 39
    //   227: return
  }
  
  private static String a(int paramInt1, int paramInt2) {
    int i = (paramInt1 ^ 0x2EC4) & 0xFFFF;
    if (b[i] == null) {
      char[] arrayOfChar = a[i].toCharArray();
      switch (arrayOfChar[0] & 0xFF) {
        case 0:
        
        case 1:
        
        case 2:
        
        case 3:
        
        case 4:
        
        case 5:
        
        case 6:
        
        case 7:
        
        case 8:
        
        case 9:
        
        case 10:
        
        case 11:
        
        case 12:
        
        case 13:
        
        case 14:
        
        case 15:
        
        case 16:
        
        case 17:
        
        case 18:
        
        case 19:
        
        case 20:
        
        case 21:
        
        case 22:
        
        case 23:
        
        case 24:
        
        case 25:
        
        case 26:
        
        case 27:
        
        case 28:
        
        case 29:
        
        case 30:
        
        case 31:
        
        case 32:
        
        case 33:
        
        case 34:
        
        case 35:
        
        case 36:
        
        case 37:
        
        case 38:
        
        case 39:
        
        case 40:
        
        case 41:
        
        case 42:
        
        case 43:
        
        case 44:
        
        case 45:
        
        case 46:
        
        case 47:
        
        case 48:
        
        case 49:
        
        case 50:
        
        case 51:
        
        case 52:
        
        case 53:
        
        case 54:
        
        case 55:
        
        case 56:
        
        case 57:
        
        case 58:
        
        case 59:
        
        case 60:
        
        case 61:
        
        case 62:
        
        case 63:
        
        case 64:
        
        case 65:
        
        case 66:
        
        case 67:
        
        case 68:
        
        case 69:
        
        case 70:
        
        case 71:
        
        case 72:
        
        case 73:
        
        case 74:
        
        case 75:
        
        case 76:
        
        case 77:
        
        case 78:
        
        case 79:
        
        case 80:
        
        case 81:
        
        case 82:
        
        case 83:
        
        case 84:
        
        case 85:
        
        case 86:
        
        case 87:
        
        case 88:
        
        case 89:
        
        case 90:
        
        case 91:
        
        case 92:
        
        case 93:
        
        case 94:
        
        case 95:
        
        case 96:
        
        case 97:
        
        case 98:
        
        case 99:
        
        case 100:
        
        case 101:
        
        case 102:
        
        case 103:
        
        case 104:
        
        case 105:
        
        case 106:
        
        case 107:
        
        case 108:
        
        case 109:
        
        case 110:
        
        case 111:
        
        case 112:
        
        case 113:
        
        case 114:
        
        case 115:
        
        case 116:
        
        case 117:
        
        case 118:
        
        case 119:
        
        case 120:
        
        case 121:
        
        case 122:
        
        case 123:
        
        case 124:
        
        case 125:
        
        case 126:
        
        case 127:
        
        case 128:
        
        case 129:
        
        case 130:
        
        case 131:
        
        case 132:
        
        case 133:
        
        case 134:
        
        case 135:
        
        case 136:
        
        case 137:
        
        case 138:
        
        case 139:
        
        case 140:
        
        case 141:
        
        case 142:
        
        case 143:
        
        case 144:
        
        case 145:
        
        case 146:
        
        case 147:
        
        case 148:
        
        case 149:
        
        case 150:
        
        case 151:
        
        case 152:
        
        case 153:
        
        case 154:
        
        case 155:
        
        case 156:
        
        case 157:
        
        case 158:
        
        case 159:
        
        case 160:
        
        case 161:
        
        case 162:
        
        case 163:
        
        case 164:
        
        case 165:
        
        case 166:
        
        case 167:
        
        case 168:
        
        case 169:
        
        case 170:
        
        case 171:
        
        case 172:
        
        case 173:
        
        case 174:
        
        case 175:
        
        case 176:
        
        case 177:
        
        case 178:
        
        case 179:
        
        case 180:
        
        case 181:
        
        case 182:
        
        case 183:
        
        case 184:
        
        case 185:
        
        case 186:
        
        case 187:
        
        case 188:
        
        case 189:
        
        case 190:
        
        case 191:
        
        case 192:
        
        case 193:
        
        case 194:
        
        case 195:
        
        case 196:
        
        case 197:
        
        case 198:
        
        case 199:
        
        case 200:
        
        case 201:
        
        case 202:
        
        case 203:
        
        case 204:
        
        case 205:
        
        case 206:
        
        case 207:
        
        case 208:
        
        case 209:
        
        case 210:
        
        case 211:
        
        case 212:
        
        case 213:
        
        case 214:
        
        case 215:
        
        case 216:
        
        case 217:
        
        case 218:
        
        case 219:
        
        case 220:
        
        case 221:
        
        case 222:
        
        case 223:
        
        case 224:
        
        case 225:
        
        case 226:
        
        case 227:
        
        case 228:
        
        case 229:
        
        case 230:
        
        case 231:
        
        case 232:
        
        case 233:
        
        case 234:
        
        case 235:
        
        case 236:
        
        case 237:
        
        case 238:
        
        case 239:
        
        case 240:
        
        case 241:
        
        case 242:
        
        case 243:
        
        case 244:
        
        case 245:
        
        case 246:
        
        case 247:
        
        case 248:
        
        case 249:
        
        case 250:
        
        case 251:
        
        case 252:
        
        case 253:
        
        case 254:
        
        default:
          break;
      } 
      char c = 'Ã™';
      int j = (paramInt2 & 0xFF) - c;
      if (j < 0)
        j += 256; 
      int k = ((paramInt2 & 0xFFFF) >>> 8) - c;
      if (k < 0)
        k += 256; 
      for (byte b = 0; b < arrayOfChar.length; b++) {
        int m = b % 2;
        if (m == 0) {
          arrayOfChar[b] = (char)(arrayOfChar[b] ^ j);
          j = ((j >>> 3 | j << 5) ^ arrayOfChar[b]) & 0xFF;
        } else {
          arrayOfChar[b] = (char)(arrayOfChar[b] ^ k);
          k = ((k >>> 3 | k << 5) ^ arrayOfChar[b]) & 0xFF;
        } 
      } 
      b[i] = (new String(arrayOfChar)).intern();
    } 
    return b[i];
  }
}


/* Location:              C:\Program Files\BurpSuitePro\burpsuite_pro.jar!\burp\Zgbm.class
 * Java compiler version: 21 (65.0)
 * JD-Core Version:       1.1.3
 */