package burp;

import java.math.BigInteger;

class Zgco extends ClassLoader {
  static String Zh;
  
  static Object Zx;
  
  private static final String[] a;
  
  private static final String[] b;
  
  static boolean Zd(Object[] paramArrayOfObject, Object paramObject) throws Throwable {
    // Byte code:
    //   0: invokestatic ZN : ()Z
    //   3: istore_2
    //   4: sipush #-28088
    //   7: sipush #2031
    //   10: invokestatic a : (II)Ljava/lang/String;
    //   13: invokestatic forName : (Ljava/lang/String;)Ljava/lang/Class;
    //   16: invokestatic ZB : (Ljava/lang/Object;)V
    //   19: getstatic burp/Zsx6.ZN : Ljava/lang/Object;
    //   22: checkcast java/math/BigInteger
    //   25: invokevirtual toByteArray : ()[B
    //   28: astore_3
    //   29: aload_3
    //   30: arraylength
    //   31: bipush #8
    //   33: iadd
    //   34: bipush #6
    //   36: ishr
    //   37: iconst_1
    //   38: iadd
    //   39: bipush #16
    //   41: imul
    //   42: newarray int
    //   44: astore #5
    //   46: iconst_0
    //   47: istore #6
    //   49: iload #6
    //   51: aload_3
    //   52: arraylength
    //   53: if_icmpge -> 96
    //   56: aload_3
    //   57: iload #6
    //   59: baload
    //   60: sipush #255
    //   63: iand
    //   64: istore #7
    //   66: aload #5
    //   68: iload #6
    //   70: iconst_2
    //   71: ishr
    //   72: dup2
    //   73: iaload
    //   74: iload #7
    //   76: bipush #24
    //   78: iload #6
    //   80: iconst_4
    //   81: irem
    //   82: bipush #8
    //   84: imul
    //   85: isub
    //   86: ishl
    //   87: ior
    //   88: iastore
    //   89: iinc #6, 1
    //   92: iload_2
    //   93: ifne -> 49
    //   96: aload #5
    //   98: iload #6
    //   100: iconst_2
    //   101: ishr
    //   102: dup2
    //   103: iaload
    //   104: sipush #128
    //   107: bipush #24
    //   109: iload #6
    //   111: iconst_4
    //   112: irem
    //   113: bipush #8
    //   115: imul
    //   116: isub
    //   117: ishl
    //   118: ior
    //   119: iastore
    //   120: aload #5
    //   122: aload #5
    //   124: arraylength
    //   125: iconst_1
    //   126: isub
    //   127: aload_3
    //   128: arraylength
    //   129: bipush #8
    //   131: imul
    //   132: iastore
    //   133: bipush #80
    //   135: newarray int
    //   137: astore #7
    //   139: ldc 1732584193
    //   141: istore #8
    //   143: ldc -271733879
    //   145: istore #9
    //   147: ldc -1732584194
    //   149: istore #10
    //   151: ldc 271733878
    //   153: istore #11
    //   155: ldc -1009589776
    //   157: istore #12
    //   159: iconst_0
    //   160: istore #6
    //   162: iload #6
    //   164: aload #5
    //   166: arraylength
    //   167: if_icmpge -> 489
    //   170: iload #8
    //   172: istore #13
    //   174: iload #9
    //   176: istore #14
    //   178: iload #10
    //   180: istore #15
    //   182: iload #11
    //   184: istore #16
    //   186: iload #12
    //   188: istore #17
    //   190: iconst_0
    //   191: istore #18
    //   193: iload #18
    //   195: bipush #80
    //   197: if_icmpge -> 447
    //   200: iload #18
    //   202: bipush #16
    //   204: if_icmpge -> 231
    //   207: aload #7
    //   209: iload #18
    //   211: aload #5
    //   213: iload #6
    //   215: iload #18
    //   217: iadd
    //   218: iaload
    //   219: iastore
    //   220: iload_2
    //   221: ifne -> 286
    //   224: goto -> 231
    //   227: invokestatic a : (Ljava/lang/Throwable;)Ljava/lang/Throwable;
    //   230: athrow
    //   231: aload #7
    //   233: iload #18
    //   235: iconst_3
    //   236: isub
    //   237: iaload
    //   238: aload #7
    //   240: iload #18
    //   242: bipush #8
    //   244: isub
    //   245: iaload
    //   246: ixor
    //   247: aload #7
    //   249: iload #18
    //   251: bipush #14
    //   253: isub
    //   254: iaload
    //   255: ixor
    //   256: aload #7
    //   258: iload #18
    //   260: bipush #16
    //   262: isub
    //   263: iaload
    //   264: ixor
    //   265: istore #19
    //   267: iload #19
    //   269: iconst_1
    //   270: ishl
    //   271: iload #19
    //   273: bipush #31
    //   275: iushr
    //   276: ior
    //   277: istore #20
    //   279: aload #7
    //   281: iload #18
    //   283: iload #20
    //   285: iastore
    //   286: iload #8
    //   288: iconst_5
    //   289: ishl
    //   290: iload #8
    //   292: bipush #27
    //   294: iushr
    //   295: ior
    //   296: istore #19
    //   298: iload #19
    //   300: iload #12
    //   302: iadd
    //   303: aload #7
    //   305: iload #18
    //   307: iaload
    //   308: iadd
    //   309: iload #18
    //   311: bipush #20
    //   313: if_icmpge -> 339
    //   316: ldc 1518500249
    //   318: iload #9
    //   320: iload #10
    //   322: iand
    //   323: iload #9
    //   325: iconst_m1
    //   326: ixor
    //   327: iload #11
    //   329: iand
    //   330: ior
    //   331: iadd
    //   332: goto -> 409
    //   335: invokestatic a : (Ljava/lang/Throwable;)Ljava/lang/Throwable;
    //   338: athrow
    //   339: iload #18
    //   341: bipush #40
    //   343: if_icmpge -> 364
    //   346: ldc 1859775393
    //   348: iload #9
    //   350: iload #10
    //   352: ixor
    //   353: iload #11
    //   355: ixor
    //   356: iadd
    //   357: goto -> 409
    //   360: invokestatic a : (Ljava/lang/Throwable;)Ljava/lang/Throwable;
    //   363: athrow
    //   364: iload #18
    //   366: bipush #60
    //   368: if_icmpge -> 398
    //   371: ldc -1894007588
    //   373: iload #9
    //   375: iload #10
    //   377: iand
    //   378: iload #9
    //   380: iload #11
    //   382: iand
    //   383: ior
    //   384: iload #10
    //   386: iload #11
    //   388: iand
    //   389: ior
    //   390: iadd
    //   391: goto -> 409
    //   394: invokestatic a : (Ljava/lang/Throwable;)Ljava/lang/Throwable;
    //   397: athrow
    //   398: ldc -899497514
    //   400: iload #9
    //   402: iload #10
    //   404: ixor
    //   405: iload #11
    //   407: ixor
    //   408: iadd
    //   409: iadd
    //   410: istore #20
    //   412: iload #11
    //   414: istore #12
    //   416: iload #10
    //   418: istore #11
    //   420: iload #9
    //   422: bipush #30
    //   424: ishl
    //   425: iload #9
    //   427: iconst_2
    //   428: iushr
    //   429: ior
    //   430: istore #10
    //   432: iload #8
    //   434: istore #9
    //   436: iload #20
    //   438: istore #8
    //   440: iinc #18, 1
    //   443: iload_2
    //   444: ifne -> 193
    //   447: iload #8
    //   449: iload #13
    //   451: iadd
    //   452: istore #8
    //   454: iload #9
    //   456: iload #14
    //   458: iadd
    //   459: istore #9
    //   461: iload #10
    //   463: iload #15
    //   465: iadd
    //   466: istore #10
    //   468: iload #11
    //   470: iload #16
    //   472: iadd
    //   473: istore #11
    //   475: iload #12
    //   477: iload #17
    //   479: iadd
    //   480: istore #12
    //   482: iinc #6, 16
    //   485: iload_2
    //   486: ifne -> 162
    //   489: iconst_5
    //   490: newarray int
    //   492: dup
    //   493: iconst_0
    //   494: iload #8
    //   496: iastore
    //   497: dup
    //   498: iconst_1
    //   499: iload #9
    //   501: iastore
    //   502: dup
    //   503: iconst_2
    //   504: iload #10
    //   506: iastore
    //   507: dup
    //   508: iconst_3
    //   509: iload #11
    //   511: iastore
    //   512: dup
    //   513: iconst_4
    //   514: iload #12
    //   516: iastore
    //   517: astore #13
    //   519: bipush #20
    //   521: newarray byte
    //   523: astore #14
    //   525: iconst_0
    //   526: istore #15
    //   528: iload #15
    //   530: bipush #20
    //   532: if_icmpge -> 573
    //   535: aload #13
    //   537: iload #15
    //   539: iconst_4
    //   540: idiv
    //   541: iaload
    //   542: istore #16
    //   544: iconst_3
    //   545: iload #15
    //   547: iconst_4
    //   548: irem
    //   549: isub
    //   550: bipush #8
    //   552: imul
    //   553: istore #17
    //   555: aload #14
    //   557: iload #15
    //   559: iload #16
    //   561: iload #17
    //   563: iushr
    //   564: i2b
    //   565: bastore
    //   566: iinc #15, 1
    //   569: iload_2
    //   570: ifne -> 528
    //   573: aload #14
    //   575: astore #4
    //   577: new java/math/BigInteger
    //   580: dup
    //   581: aload #4
    //   583: invokespecial <init> : ([B)V
    //   586: invokevirtual abs : ()Ljava/math/BigInteger;
    //   589: putstatic burp/Zxjm.Zn : Ljava/lang/Object;
    //   592: new java/io/ByteArrayOutputStream
    //   595: dup
    //   596: invokespecial <init> : ()V
    //   599: astore_3
    //   600: getstatic burp/Ztfr.Zo : Ljava/lang/String;
    //   603: astore #4
    //   605: iconst_0
    //   606: istore #5
    //   608: iload #5
    //   610: aload #4
    //   612: invokevirtual length : ()I
    //   615: if_icmpge -> 645
    //   618: aload_3
    //   619: aload #4
    //   621: iload #5
    //   623: iload #5
    //   625: iconst_2
    //   626: iadd
    //   627: invokevirtual substring : (II)Ljava/lang/String;
    //   630: bipush #16
    //   632: invokestatic parseInt : (Ljava/lang/String;I)I
    //   635: invokevirtual write : (I)V
    //   638: iinc #5, 2
    //   641: iload_2
    //   642: ifne -> 608
    //   645: aload_3
    //   646: invokevirtual toByteArray : ()[B
    //   649: astore #5
    //   651: getstatic burp/Zg27.ZQ : Ljava/lang/Object;
    //   654: checkcast java/math/BigInteger
    //   657: invokevirtual toByteArray : ()[B
    //   660: astore #6
    //   662: sipush #256
    //   665: newarray byte
    //   667: astore #8
    //   669: sipush #256
    //   672: newarray int
    //   674: astore #9
    //   676: sipush #256
    //   679: newarray int
    //   681: astore #10
    //   683: sipush #256
    //   686: newarray int
    //   688: astore #11
    //   690: sipush #256
    //   693: newarray int
    //   695: astore #12
    //   697: bipush #10
    //   699: newarray int
    //   701: astore #13
    //   703: sipush #283
    //   706: istore #14
    //   708: iconst_0
    //   709: istore #16
    //   711: iload #16
    //   713: sipush #256
    //   716: if_icmpge -> 950
    //   719: sipush #-28080
    //   722: sipush #-32402
    //   725: invokestatic a : (II)Ljava/lang/String;
    //   728: iload #16
    //   730: iconst_1
    //   731: iushr
    //   732: invokevirtual charAt : (I)C
    //   735: istore #25
    //   737: iload #16
    //   739: iconst_1
    //   740: iand
    //   741: ifne -> 756
    //   744: iload #25
    //   746: bipush #8
    //   748: iushr
    //   749: goto -> 758
    //   752: invokestatic a : (Ljava/lang/Throwable;)Ljava/lang/Throwable;
    //   755: athrow
    //   756: iload #25
    //   758: i2b
    //   759: sipush #255
    //   762: iand
    //   763: istore #15
    //   765: iload #16
    //   767: iconst_1
    //   768: ishl
    //   769: istore #17
    //   771: iload #17
    //   773: sipush #256
    //   776: if_icmplt -> 786
    //   779: iload #17
    //   781: iload #14
    //   783: ixor
    //   784: istore #17
    //   786: iload #17
    //   788: iconst_1
    //   789: ishl
    //   790: istore #18
    //   792: iload #18
    //   794: sipush #256
    //   797: if_icmplt -> 807
    //   800: iload #18
    //   802: iload #14
    //   804: ixor
    //   805: istore #18
    //   807: iload #18
    //   809: iconst_1
    //   810: ishl
    //   811: istore #19
    //   813: iload #19
    //   815: sipush #256
    //   818: if_icmplt -> 828
    //   821: iload #19
    //   823: iload #14
    //   825: ixor
    //   826: istore #19
    //   828: iload #19
    //   830: iload #16
    //   832: ixor
    //   833: istore #20
    //   835: iload #20
    //   837: iload #17
    //   839: ixor
    //   840: istore #21
    //   842: iload #20
    //   844: iload #18
    //   846: ixor
    //   847: istore #22
    //   849: iload #19
    //   851: iload #18
    //   853: ixor
    //   854: iload #17
    //   856: ixor
    //   857: istore #23
    //   859: aload #8
    //   861: iload #16
    //   863: iload #15
    //   865: i2b
    //   866: bastore
    //   867: aload #9
    //   869: iload #15
    //   871: iload #23
    //   873: bipush #24
    //   875: ishl
    //   876: iload #20
    //   878: bipush #16
    //   880: ishl
    //   881: ior
    //   882: iload #22
    //   884: bipush #8
    //   886: ishl
    //   887: ior
    //   888: iload #21
    //   890: ior
    //   891: dup
    //   892: istore #24
    //   894: iastore
    //   895: aload #10
    //   897: iload #15
    //   899: iload #24
    //   901: bipush #8
    //   903: iushr
    //   904: iload #24
    //   906: bipush #24
    //   908: ishl
    //   909: ior
    //   910: iastore
    //   911: aload #11
    //   913: iload #15
    //   915: iload #24
    //   917: bipush #16
    //   919: iushr
    //   920: iload #24
    //   922: bipush #16
    //   924: ishl
    //   925: ior
    //   926: iastore
    //   927: aload #12
    //   929: iload #15
    //   931: iload #24
    //   933: bipush #24
    //   935: iushr
    //   936: iload #24
    //   938: bipush #8
    //   940: ishl
    //   941: ior
    //   942: iastore
    //   943: iinc #16, 1
    //   946: iload_2
    //   947: ifne -> 711
    //   950: iconst_1
    //   951: istore #25
    //   953: aload #13
    //   955: iconst_0
    //   956: iload #25
    //   958: bipush #24
    //   960: ishl
    //   961: iastore
    //   962: iconst_1
    //   963: istore #26
    //   965: iload #26
    //   967: bipush #10
    //   969: if_icmpge -> 1010
    //   972: iload #25
    //   974: iconst_1
    //   975: ishl
    //   976: istore #25
    //   978: iload #25
    //   980: sipush #256
    //   983: if_icmplt -> 993
    //   986: iload #25
    //   988: iload #14
    //   990: ixor
    //   991: istore #25
    //   993: aload #13
    //   995: iload #26
    //   997: iload #25
    //   999: bipush #24
    //   1001: ishl
    //   1002: iastore
    //   1003: iinc #26, 1
    //   1006: iload_2
    //   1007: ifne -> 965
    //   1010: iconst_4
    //   1011: istore #26
    //   1013: iload #26
    //   1015: bipush #6
    //   1017: iadd
    //   1018: istore #27
    //   1020: iconst_4
    //   1021: iload #27
    //   1023: iconst_1
    //   1024: iadd
    //   1025: imul
    //   1026: istore #28
    //   1028: iload #28
    //   1030: newarray int
    //   1032: astore #29
    //   1034: iload #28
    //   1036: newarray int
    //   1038: astore #30
    //   1040: iconst_0
    //   1041: istore #25
    //   1043: iconst_0
    //   1044: istore #32
    //   1046: iconst_0
    //   1047: istore #33
    //   1049: iload #32
    //   1051: iload #26
    //   1053: if_icmpge -> 1121
    //   1056: aload #29
    //   1058: iload #32
    //   1060: aload #5
    //   1062: iload #33
    //   1064: baload
    //   1065: bipush #24
    //   1067: ishl
    //   1068: aload #5
    //   1070: iload #33
    //   1072: iconst_1
    //   1073: iadd
    //   1074: baload
    //   1075: sipush #255
    //   1078: iand
    //   1079: bipush #16
    //   1081: ishl
    //   1082: ior
    //   1083: aload #5
    //   1085: iload #33
    //   1087: iconst_2
    //   1088: iadd
    //   1089: baload
    //   1090: sipush #255
    //   1093: iand
    //   1094: bipush #8
    //   1096: ishl
    //   1097: ior
    //   1098: aload #5
    //   1100: iload #33
    //   1102: iconst_3
    //   1103: iadd
    //   1104: baload
    //   1105: sipush #255
    //   1108: iand
    //   1109: ior
    //   1110: iastore
    //   1111: iinc #32, 1
    //   1114: iinc #33, 4
    //   1117: iload_2
    //   1118: ifne -> 1049
    //   1121: iload #26
    //   1123: istore #32
    //   1125: iconst_0
    //   1126: istore #33
    //   1128: iload #32
    //   1130: iload #28
    //   1132: if_icmpge -> 1259
    //   1135: aload #29
    //   1137: iload #32
    //   1139: iconst_1
    //   1140: isub
    //   1141: iaload
    //   1142: istore #31
    //   1144: iload #33
    //   1146: ifne -> 1233
    //   1149: iload #26
    //   1151: istore #33
    //   1153: aload #8
    //   1155: iload #31
    //   1157: bipush #16
    //   1159: iushr
    //   1160: sipush #255
    //   1163: iand
    //   1164: baload
    //   1165: bipush #24
    //   1167: ishl
    //   1168: aload #8
    //   1170: iload #31
    //   1172: bipush #8
    //   1174: iushr
    //   1175: sipush #255
    //   1178: iand
    //   1179: baload
    //   1180: sipush #255
    //   1183: iand
    //   1184: bipush #16
    //   1186: ishl
    //   1187: ior
    //   1188: aload #8
    //   1190: iload #31
    //   1192: sipush #255
    //   1195: iand
    //   1196: baload
    //   1197: sipush #255
    //   1200: iand
    //   1201: bipush #8
    //   1203: ishl
    //   1204: ior
    //   1205: aload #8
    //   1207: iload #31
    //   1209: bipush #24
    //   1211: iushr
    //   1212: baload
    //   1213: sipush #255
    //   1216: iand
    //   1217: ior
    //   1218: istore #31
    //   1220: iload #31
    //   1222: aload #13
    //   1224: iload #25
    //   1226: iinc #25, 1
    //   1229: iaload
    //   1230: ixor
    //   1231: istore #31
    //   1233: aload #29
    //   1235: iload #32
    //   1237: aload #29
    //   1239: iload #32
    //   1241: iload #26
    //   1243: isub
    //   1244: iaload
    //   1245: iload #31
    //   1247: ixor
    //   1248: iastore
    //   1249: iinc #32, 1
    //   1252: iinc #33, -1
    //   1255: iload_2
    //   1256: ifne -> 1128
    //   1259: iconst_0
    //   1260: istore #32
    //   1262: iconst_4
    //   1263: iload #27
    //   1265: imul
    //   1266: istore #33
    //   1268: aload #30
    //   1270: iload #32
    //   1272: aload #29
    //   1274: iload #33
    //   1276: iaload
    //   1277: iastore
    //   1278: aload #30
    //   1280: iload #32
    //   1282: iconst_1
    //   1283: iadd
    //   1284: aload #29
    //   1286: iload #33
    //   1288: iconst_1
    //   1289: iadd
    //   1290: iaload
    //   1291: iastore
    //   1292: aload #30
    //   1294: iload #32
    //   1296: iconst_2
    //   1297: iadd
    //   1298: aload #29
    //   1300: iload #33
    //   1302: iconst_2
    //   1303: iadd
    //   1304: iaload
    //   1305: iastore
    //   1306: aload #30
    //   1308: iload #32
    //   1310: iconst_3
    //   1311: iadd
    //   1312: aload #29
    //   1314: iload #33
    //   1316: iconst_3
    //   1317: iadd
    //   1318: iaload
    //   1319: iastore
    //   1320: iinc #32, 4
    //   1323: iinc #33, -4
    //   1326: iconst_1
    //   1327: istore #35
    //   1329: iload #35
    //   1331: iload #27
    //   1333: if_icmpge -> 1697
    //   1336: aload #29
    //   1338: iload #33
    //   1340: iaload
    //   1341: istore #34
    //   1343: aload #30
    //   1345: iload #32
    //   1347: aload #9
    //   1349: aload #8
    //   1351: iload #34
    //   1353: bipush #24
    //   1355: iushr
    //   1356: baload
    //   1357: sipush #255
    //   1360: iand
    //   1361: iaload
    //   1362: aload #10
    //   1364: aload #8
    //   1366: iload #34
    //   1368: bipush #16
    //   1370: iushr
    //   1371: sipush #255
    //   1374: iand
    //   1375: baload
    //   1376: sipush #255
    //   1379: iand
    //   1380: iaload
    //   1381: ixor
    //   1382: aload #11
    //   1384: aload #8
    //   1386: iload #34
    //   1388: bipush #8
    //   1390: iushr
    //   1391: sipush #255
    //   1394: iand
    //   1395: baload
    //   1396: sipush #255
    //   1399: iand
    //   1400: iaload
    //   1401: ixor
    //   1402: aload #12
    //   1404: aload #8
    //   1406: iload #34
    //   1408: sipush #255
    //   1411: iand
    //   1412: baload
    //   1413: sipush #255
    //   1416: iand
    //   1417: iaload
    //   1418: ixor
    //   1419: iastore
    //   1420: aload #29
    //   1422: iload #33
    //   1424: iconst_1
    //   1425: iadd
    //   1426: iaload
    //   1427: istore #34
    //   1429: aload #30
    //   1431: iload #32
    //   1433: iconst_1
    //   1434: iadd
    //   1435: aload #9
    //   1437: aload #8
    //   1439: iload #34
    //   1441: bipush #24
    //   1443: iushr
    //   1444: baload
    //   1445: sipush #255
    //   1448: iand
    //   1449: iaload
    //   1450: aload #10
    //   1452: aload #8
    //   1454: iload #34
    //   1456: bipush #16
    //   1458: iushr
    //   1459: sipush #255
    //   1462: iand
    //   1463: baload
    //   1464: sipush #255
    //   1467: iand
    //   1468: iaload
    //   1469: ixor
    //   1470: aload #11
    //   1472: aload #8
    //   1474: iload #34
    //   1476: bipush #8
    //   1478: iushr
    //   1479: sipush #255
    //   1482: iand
    //   1483: baload
    //   1484: sipush #255
    //   1487: iand
    //   1488: iaload
    //   1489: ixor
    //   1490: aload #12
    //   1492: aload #8
    //   1494: iload #34
    //   1496: sipush #255
    //   1499: iand
    //   1500: baload
    //   1501: sipush #255
    //   1504: iand
    //   1505: iaload
    //   1506: ixor
    //   1507: iastore
    //   1508: aload #29
    //   1510: iload #33
    //   1512: iconst_2
    //   1513: iadd
    //   1514: iaload
    //   1515: istore #34
    //   1517: aload #30
    //   1519: iload #32
    //   1521: iconst_2
    //   1522: iadd
    //   1523: aload #9
    //   1525: aload #8
    //   1527: iload #34
    //   1529: bipush #24
    //   1531: iushr
    //   1532: baload
    //   1533: sipush #255
    //   1536: iand
    //   1537: iaload
    //   1538: aload #10
    //   1540: aload #8
    //   1542: iload #34
    //   1544: bipush #16
    //   1546: iushr
    //   1547: sipush #255
    //   1550: iand
    //   1551: baload
    //   1552: sipush #255
    //   1555: iand
    //   1556: iaload
    //   1557: ixor
    //   1558: aload #11
    //   1560: aload #8
    //   1562: iload #34
    //   1564: bipush #8
    //   1566: iushr
    //   1567: sipush #255
    //   1570: iand
    //   1571: baload
    //   1572: sipush #255
    //   1575: iand
    //   1576: iaload
    //   1577: ixor
    //   1578: aload #12
    //   1580: aload #8
    //   1582: iload #34
    //   1584: sipush #255
    //   1587: iand
    //   1588: baload
    //   1589: sipush #255
    //   1592: iand
    //   1593: iaload
    //   1594: ixor
    //   1595: iastore
    //   1596: aload #29
    //   1598: iload #33
    //   1600: iconst_3
    //   1601: iadd
    //   1602: iaload
    //   1603: istore #34
    //   1605: aload #30
    //   1607: iload #32
    //   1609: iconst_3
    //   1610: iadd
    //   1611: aload #9
    //   1613: aload #8
    //   1615: iload #34
    //   1617: bipush #24
    //   1619: iushr
    //   1620: baload
    //   1621: sipush #255
    //   1624: iand
    //   1625: iaload
    //   1626: aload #10
    //   1628: aload #8
    //   1630: iload #34
    //   1632: bipush #16
    //   1634: iushr
    //   1635: sipush #255
    //   1638: iand
    //   1639: baload
    //   1640: sipush #255
    //   1643: iand
    //   1644: iaload
    //   1645: ixor
    //   1646: aload #11
    //   1648: aload #8
    //   1650: iload #34
    //   1652: bipush #8
    //   1654: iushr
    //   1655: sipush #255
    //   1658: iand
    //   1659: baload
    //   1660: sipush #255
    //   1663: iand
    //   1664: iaload
    //   1665: ixor
    //   1666: aload #12
    //   1668: aload #8
    //   1670: iload #34
    //   1672: sipush #255
    //   1675: iand
    //   1676: baload
    //   1677: sipush #255
    //   1680: iand
    //   1681: iaload
    //   1682: ixor
    //   1683: iastore
    //   1684: iinc #32, 4
    //   1687: iinc #33, -4
    //   1690: iinc #35, 1
    //   1693: iload_2
    //   1694: ifne -> 1329
    //   1697: aload #30
    //   1699: iload #32
    //   1701: aload #29
    //   1703: iload #33
    //   1705: iaload
    //   1706: iastore
    //   1707: aload #30
    //   1709: iload #32
    //   1711: iconst_1
    //   1712: iadd
    //   1713: aload #29
    //   1715: iload #33
    //   1717: iconst_1
    //   1718: iadd
    //   1719: iaload
    //   1720: iastore
    //   1721: aload #30
    //   1723: iload #32
    //   1725: iconst_2
    //   1726: iadd
    //   1727: aload #29
    //   1729: iload #33
    //   1731: iconst_2
    //   1732: iadd
    //   1733: iaload
    //   1734: iastore
    //   1735: aload #30
    //   1737: iload #32
    //   1739: iconst_3
    //   1740: iadd
    //   1741: aload #29
    //   1743: iload #33
    //   1745: iconst_3
    //   1746: iadd
    //   1747: iaload
    //   1748: iastore
    //   1749: iconst_0
    //   1750: newarray byte
    //   1752: astore #35
    //   1754: aload #6
    //   1756: arraylength
    //   1757: bipush #16
    //   1759: irem
    //   1760: ifeq -> 1784
    //   1763: new java/lang/Exception
    //   1766: dup
    //   1767: sipush #-28082
    //   1770: sipush #-15094
    //   1773: invokestatic a : (II)Ljava/lang/String;
    //   1776: invokespecial <init> : (Ljava/lang/String;)V
    //   1779: athrow
    //   1780: invokestatic a : (Ljava/lang/Throwable;)Ljava/lang/Throwable;
    //   1783: athrow
    //   1784: bipush #10
    //   1786: istore #36
    //   1788: sipush #-28077
    //   1791: sipush #256
    //   1794: newarray byte
    //   1796: astore #37
    //   1798: sipush #3901
    //   1801: sipush #256
    //   1804: newarray int
    //   1806: astore #38
    //   1808: sipush #256
    //   1811: newarray int
    //   1813: astore #39
    //   1815: sipush #256
    //   1818: newarray int
    //   1820: astore #40
    //   1822: sipush #256
    //   1825: newarray int
    //   1827: astore #41
    //   1829: sipush #283
    //   1832: istore #14
    //   1834: invokestatic a : (II)Ljava/lang/String;
    //   1837: astore #42
    //   1839: iconst_0
    //   1840: istore #16
    //   1842: iload #16
    //   1844: sipush #256
    //   1847: if_icmpge -> 2074
    //   1850: aload #42
    //   1852: iload #16
    //   1854: iconst_1
    //   1855: iushr
    //   1856: invokevirtual charAt : (I)C
    //   1859: istore #43
    //   1861: iload #16
    //   1863: iconst_1
    //   1864: iand
    //   1865: ifne -> 1880
    //   1868: iload #43
    //   1870: bipush #8
    //   1872: iushr
    //   1873: goto -> 1882
    //   1876: invokestatic a : (Ljava/lang/Throwable;)Ljava/lang/Throwable;
    //   1879: athrow
    //   1880: iload #43
    //   1882: i2b
    //   1883: sipush #255
    //   1886: iand
    //   1887: istore #15
    //   1889: iload #16
    //   1891: iconst_1
    //   1892: ishl
    //   1893: istore #17
    //   1895: iload #17
    //   1897: sipush #256
    //   1900: if_icmplt -> 1910
    //   1903: iload #17
    //   1905: iload #14
    //   1907: ixor
    //   1908: istore #17
    //   1910: iload #17
    //   1912: iconst_1
    //   1913: ishl
    //   1914: istore #18
    //   1916: iload #18
    //   1918: sipush #256
    //   1921: if_icmplt -> 1931
    //   1924: iload #18
    //   1926: iload #14
    //   1928: ixor
    //   1929: istore #18
    //   1931: iload #18
    //   1933: iconst_1
    //   1934: ishl
    //   1935: istore #19
    //   1937: iload #19
    //   1939: sipush #256
    //   1942: if_icmplt -> 1952
    //   1945: iload #19
    //   1947: iload #14
    //   1949: ixor
    //   1950: istore #19
    //   1952: iload #19
    //   1954: iload #16
    //   1956: ixor
    //   1957: istore #20
    //   1959: iload #20
    //   1961: iload #17
    //   1963: ixor
    //   1964: istore #21
    //   1966: iload #20
    //   1968: iload #18
    //   1970: ixor
    //   1971: istore #22
    //   1973: iload #19
    //   1975: iload #18
    //   1977: ixor
    //   1978: iload #17
    //   1980: ixor
    //   1981: istore #23
    //   1983: aload #37
    //   1985: iload #15
    //   1987: iload #16
    //   1989: i2b
    //   1990: bastore
    //   1991: aload #38
    //   1993: iload #15
    //   1995: iload #23
    //   1997: bipush #24
    //   1999: ishl
    //   2000: iload #20
    //   2002: bipush #16
    //   2004: ishl
    //   2005: ior
    //   2006: iload #22
    //   2008: bipush #8
    //   2010: ishl
    //   2011: ior
    //   2012: iload #21
    //   2014: ior
    //   2015: dup
    //   2016: istore #24
    //   2018: iastore
    //   2019: aload #39
    //   2021: iload #15
    //   2023: iload #24
    //   2025: bipush #8
    //   2027: iushr
    //   2028: iload #24
    //   2030: bipush #24
    //   2032: ishl
    //   2033: ior
    //   2034: iastore
    //   2035: aload #40
    //   2037: iload #15
    //   2039: iload #24
    //   2041: bipush #16
    //   2043: iushr
    //   2044: iload #24
    //   2046: bipush #16
    //   2048: ishl
    //   2049: ior
    //   2050: iastore
    //   2051: aload #41
    //   2053: iload #15
    //   2055: iload #24
    //   2057: bipush #24
    //   2059: iushr
    //   2060: iload #24
    //   2062: bipush #8
    //   2064: ishl
    //   2065: ior
    //   2066: iastore
    //   2067: iinc #16, 1
    //   2070: iload_2
    //   2071: ifne -> 1842
    //   2074: aload #6
    //   2076: arraylength
    //   2077: newarray byte
    //   2079: astore #43
    //   2081: iconst_0
    //   2082: istore #44
    //   2084: iload #44
    //   2086: aload #6
    //   2088: arraylength
    //   2089: bipush #16
    //   2091: idiv
    //   2092: if_icmpge -> 3006
    //   2095: bipush #16
    //   2097: newarray byte
    //   2099: astore #45
    //   2101: bipush #16
    //   2103: newarray byte
    //   2105: astore #46
    //   2107: iconst_0
    //   2108: istore #47
    //   2110: iload #47
    //   2112: bipush #16
    //   2114: if_icmpge -> 2140
    //   2117: aload #45
    //   2119: iload #47
    //   2121: aload #6
    //   2123: iload #47
    //   2125: iload #44
    //   2127: bipush #16
    //   2129: imul
    //   2130: iadd
    //   2131: baload
    //   2132: bastore
    //   2133: iinc #47, 1
    //   2136: iload_2
    //   2137: ifne -> 2110
    //   2140: iconst_0
    //   2141: istore #47
    //   2143: aload #45
    //   2145: iconst_0
    //   2146: baload
    //   2147: bipush #24
    //   2149: ishl
    //   2150: aload #45
    //   2152: iconst_1
    //   2153: baload
    //   2154: sipush #255
    //   2157: iand
    //   2158: bipush #16
    //   2160: ishl
    //   2161: ior
    //   2162: aload #45
    //   2164: iconst_2
    //   2165: baload
    //   2166: sipush #255
    //   2169: iand
    //   2170: bipush #8
    //   2172: ishl
    //   2173: ior
    //   2174: aload #45
    //   2176: iconst_3
    //   2177: baload
    //   2178: sipush #255
    //   2181: iand
    //   2182: ior
    //   2183: aload #30
    //   2185: iconst_0
    //   2186: iaload
    //   2187: ixor
    //   2188: istore #49
    //   2190: aload #45
    //   2192: iconst_4
    //   2193: baload
    //   2194: bipush #24
    //   2196: ishl
    //   2197: aload #45
    //   2199: iconst_5
    //   2200: baload
    //   2201: sipush #255
    //   2204: iand
    //   2205: bipush #16
    //   2207: ishl
    //   2208: ior
    //   2209: aload #45
    //   2211: bipush #6
    //   2213: baload
    //   2214: sipush #255
    //   2217: iand
    //   2218: bipush #8
    //   2220: ishl
    //   2221: ior
    //   2222: aload #45
    //   2224: bipush #7
    //   2226: baload
    //   2227: sipush #255
    //   2230: iand
    //   2231: ior
    //   2232: aload #30
    //   2234: iconst_1
    //   2235: iaload
    //   2236: ixor
    //   2237: istore #50
    //   2239: aload #45
    //   2241: bipush #8
    //   2243: baload
    //   2244: bipush #24
    //   2246: ishl
    //   2247: aload #45
    //   2249: bipush #9
    //   2251: baload
    //   2252: sipush #255
    //   2255: iand
    //   2256: bipush #16
    //   2258: ishl
    //   2259: ior
    //   2260: aload #45
    //   2262: bipush #10
    //   2264: baload
    //   2265: sipush #255
    //   2268: iand
    //   2269: bipush #8
    //   2271: ishl
    //   2272: ior
    //   2273: aload #45
    //   2275: bipush #11
    //   2277: baload
    //   2278: sipush #255
    //   2281: iand
    //   2282: ior
    //   2283: aload #30
    //   2285: iconst_2
    //   2286: iaload
    //   2287: ixor
    //   2288: istore #51
    //   2290: aload #45
    //   2292: bipush #12
    //   2294: baload
    //   2295: bipush #24
    //   2297: ishl
    //   2298: aload #45
    //   2300: bipush #13
    //   2302: baload
    //   2303: sipush #255
    //   2306: iand
    //   2307: bipush #16
    //   2309: ishl
    //   2310: ior
    //   2311: aload #45
    //   2313: bipush #14
    //   2315: baload
    //   2316: sipush #255
    //   2319: iand
    //   2320: bipush #8
    //   2322: ishl
    //   2323: ior
    //   2324: aload #45
    //   2326: bipush #15
    //   2328: baload
    //   2329: sipush #255
    //   2332: iand
    //   2333: ior
    //   2334: aload #30
    //   2336: iconst_3
    //   2337: iaload
    //   2338: ixor
    //   2339: istore #52
    //   2341: iconst_1
    //   2342: istore #53
    //   2344: iload #53
    //   2346: iload #36
    //   2348: if_icmpge -> 2591
    //   2351: iinc #47, 4
    //   2354: aload #38
    //   2356: iload #49
    //   2358: bipush #24
    //   2360: iushr
    //   2361: iaload
    //   2362: aload #39
    //   2364: iload #52
    //   2366: bipush #16
    //   2368: iushr
    //   2369: sipush #255
    //   2372: iand
    //   2373: iaload
    //   2374: ixor
    //   2375: aload #40
    //   2377: iload #51
    //   2379: bipush #8
    //   2381: iushr
    //   2382: sipush #255
    //   2385: iand
    //   2386: iaload
    //   2387: ixor
    //   2388: aload #41
    //   2390: iload #50
    //   2392: sipush #255
    //   2395: iand
    //   2396: iaload
    //   2397: ixor
    //   2398: aload #30
    //   2400: iload #47
    //   2402: iaload
    //   2403: ixor
    //   2404: istore #54
    //   2406: aload #38
    //   2408: iload #50
    //   2410: bipush #24
    //   2412: iushr
    //   2413: iaload
    //   2414: aload #39
    //   2416: iload #49
    //   2418: bipush #16
    //   2420: iushr
    //   2421: sipush #255
    //   2424: iand
    //   2425: iaload
    //   2426: ixor
    //   2427: aload #40
    //   2429: iload #52
    //   2431: bipush #8
    //   2433: iushr
    //   2434: sipush #255
    //   2437: iand
    //   2438: iaload
    //   2439: ixor
    //   2440: aload #41
    //   2442: iload #51
    //   2444: sipush #255
    //   2447: iand
    //   2448: iaload
    //   2449: ixor
    //   2450: aload #30
    //   2452: iload #47
    //   2454: iconst_1
    //   2455: iadd
    //   2456: iaload
    //   2457: ixor
    //   2458: istore #55
    //   2460: aload #38
    //   2462: iload #51
    //   2464: bipush #24
    //   2466: iushr
    //   2467: iaload
    //   2468: aload #39
    //   2470: iload #50
    //   2472: bipush #16
    //   2474: iushr
    //   2475: sipush #255
    //   2478: iand
    //   2479: iaload
    //   2480: ixor
    //   2481: aload #40
    //   2483: iload #49
    //   2485: bipush #8
    //   2487: iushr
    //   2488: sipush #255
    //   2491: iand
    //   2492: iaload
    //   2493: ixor
    //   2494: aload #41
    //   2496: iload #52
    //   2498: sipush #255
    //   2501: iand
    //   2502: iaload
    //   2503: ixor
    //   2504: aload #30
    //   2506: iload #47
    //   2508: iconst_2
    //   2509: iadd
    //   2510: iaload
    //   2511: ixor
    //   2512: istore #56
    //   2514: aload #38
    //   2516: iload #52
    //   2518: bipush #24
    //   2520: iushr
    //   2521: iaload
    //   2522: aload #39
    //   2524: iload #51
    //   2526: bipush #16
    //   2528: iushr
    //   2529: sipush #255
    //   2532: iand
    //   2533: iaload
    //   2534: ixor
    //   2535: aload #40
    //   2537: iload #50
    //   2539: bipush #8
    //   2541: iushr
    //   2542: sipush #255
    //   2545: iand
    //   2546: iaload
    //   2547: ixor
    //   2548: aload #41
    //   2550: iload #49
    //   2552: sipush #255
    //   2555: iand
    //   2556: iaload
    //   2557: ixor
    //   2558: aload #30
    //   2560: iload #47
    //   2562: iconst_3
    //   2563: iadd
    //   2564: iaload
    //   2565: ixor
    //   2566: istore #57
    //   2568: iload #54
    //   2570: istore #49
    //   2572: iload #55
    //   2574: istore #50
    //   2576: iload #56
    //   2578: istore #51
    //   2580: iload #57
    //   2582: istore #52
    //   2584: iinc #53, 1
    //   2587: iload_2
    //   2588: ifne -> 2344
    //   2591: iinc #47, 4
    //   2594: aload #30
    //   2596: iload #47
    //   2598: iaload
    //   2599: istore #48
    //   2601: aload #46
    //   2603: iconst_0
    //   2604: aload #37
    //   2606: iload #49
    //   2608: bipush #24
    //   2610: iushr
    //   2611: baload
    //   2612: iload #48
    //   2614: bipush #24
    //   2616: iushr
    //   2617: ixor
    //   2618: i2b
    //   2619: bastore
    //   2620: aload #46
    //   2622: iconst_1
    //   2623: aload #37
    //   2625: iload #52
    //   2627: bipush #16
    //   2629: iushr
    //   2630: sipush #255
    //   2633: iand
    //   2634: baload
    //   2635: iload #48
    //   2637: bipush #16
    //   2639: iushr
    //   2640: ixor
    //   2641: i2b
    //   2642: bastore
    //   2643: aload #46
    //   2645: iconst_2
    //   2646: aload #37
    //   2648: iload #51
    //   2650: bipush #8
    //   2652: iushr
    //   2653: sipush #255
    //   2656: iand
    //   2657: baload
    //   2658: iload #48
    //   2660: bipush #8
    //   2662: iushr
    //   2663: ixor
    //   2664: i2b
    //   2665: bastore
    //   2666: aload #46
    //   2668: iconst_3
    //   2669: aload #37
    //   2671: iload #50
    //   2673: sipush #255
    //   2676: iand
    //   2677: baload
    //   2678: iload #48
    //   2680: ixor
    //   2681: i2b
    //   2682: bastore
    //   2683: aload #30
    //   2685: iload #47
    //   2687: iconst_1
    //   2688: iadd
    //   2689: iaload
    //   2690: istore #48
    //   2692: aload #46
    //   2694: iconst_4
    //   2695: aload #37
    //   2697: iload #50
    //   2699: bipush #24
    //   2701: iushr
    //   2702: baload
    //   2703: iload #48
    //   2705: bipush #24
    //   2707: iushr
    //   2708: ixor
    //   2709: i2b
    //   2710: bastore
    //   2711: aload #46
    //   2713: iconst_5
    //   2714: aload #37
    //   2716: iload #49
    //   2718: bipush #16
    //   2720: iushr
    //   2721: sipush #255
    //   2724: iand
    //   2725: baload
    //   2726: iload #48
    //   2728: bipush #16
    //   2730: iushr
    //   2731: ixor
    //   2732: i2b
    //   2733: bastore
    //   2734: aload #46
    //   2736: bipush #6
    //   2738: aload #37
    //   2740: iload #52
    //   2742: bipush #8
    //   2744: iushr
    //   2745: sipush #255
    //   2748: iand
    //   2749: baload
    //   2750: iload #48
    //   2752: bipush #8
    //   2754: iushr
    //   2755: ixor
    //   2756: i2b
    //   2757: bastore
    //   2758: aload #46
    //   2760: bipush #7
    //   2762: aload #37
    //   2764: iload #51
    //   2766: sipush #255
    //   2769: iand
    //   2770: baload
    //   2771: iload #48
    //   2773: ixor
    //   2774: i2b
    //   2775: bastore
    //   2776: aload #30
    //   2778: iload #47
    //   2780: iconst_2
    //   2781: iadd
    //   2782: iaload
    //   2783: istore #48
    //   2785: aload #46
    //   2787: bipush #8
    //   2789: aload #37
    //   2791: iload #51
    //   2793: bipush #24
    //   2795: iushr
    //   2796: baload
    //   2797: iload #48
    //   2799: bipush #24
    //   2801: iushr
    //   2802: ixor
    //   2803: i2b
    //   2804: bastore
    //   2805: aload #46
    //   2807: bipush #9
    //   2809: aload #37
    //   2811: iload #50
    //   2813: bipush #16
    //   2815: iushr
    //   2816: sipush #255
    //   2819: iand
    //   2820: baload
    //   2821: iload #48
    //   2823: bipush #16
    //   2825: iushr
    //   2826: ixor
    //   2827: i2b
    //   2828: bastore
    //   2829: aload #46
    //   2831: bipush #10
    //   2833: aload #37
    //   2835: iload #49
    //   2837: bipush #8
    //   2839: iushr
    //   2840: sipush #255
    //   2843: iand
    //   2844: baload
    //   2845: iload #48
    //   2847: bipush #8
    //   2849: iushr
    //   2850: ixor
    //   2851: i2b
    //   2852: bastore
    //   2853: aload #46
    //   2855: bipush #11
    //   2857: aload #37
    //   2859: iload #52
    //   2861: sipush #255
    //   2864: iand
    //   2865: baload
    //   2866: iload #48
    //   2868: ixor
    //   2869: i2b
    //   2870: bastore
    //   2871: aload #30
    //   2873: iload #47
    //   2875: iconst_3
    //   2876: iadd
    //   2877: iaload
    //   2878: istore #48
    //   2880: aload #46
    //   2882: bipush #12
    //   2884: aload #37
    //   2886: iload #52
    //   2888: bipush #24
    //   2890: iushr
    //   2891: baload
    //   2892: iload #48
    //   2894: bipush #24
    //   2896: iushr
    //   2897: ixor
    //   2898: i2b
    //   2899: bastore
    //   2900: aload #46
    //   2902: bipush #13
    //   2904: aload #37
    //   2906: iload #51
    //   2908: bipush #16
    //   2910: iushr
    //   2911: sipush #255
    //   2914: iand
    //   2915: baload
    //   2916: iload #48
    //   2918: bipush #16
    //   2920: iushr
    //   2921: ixor
    //   2922: i2b
    //   2923: bastore
    //   2924: aload #46
    //   2926: bipush #14
    //   2928: aload #37
    //   2930: iload #50
    //   2932: bipush #8
    //   2934: iushr
    //   2935: sipush #255
    //   2938: iand
    //   2939: baload
    //   2940: iload #48
    //   2942: bipush #8
    //   2944: iushr
    //   2945: ixor
    //   2946: i2b
    //   2947: bastore
    //   2948: aload #46
    //   2950: bipush #15
    //   2952: aload #37
    //   2954: iload #49
    //   2956: sipush #255
    //   2959: iand
    //   2960: baload
    //   2961: iload #48
    //   2963: ixor
    //   2964: i2b
    //   2965: bastore
    //   2966: iconst_0
    //   2967: istore #53
    //   2969: iload #53
    //   2971: bipush #16
    //   2973: if_icmpge -> 2999
    //   2976: aload #43
    //   2978: iload #53
    //   2980: iload #44
    //   2982: bipush #16
    //   2984: imul
    //   2985: iadd
    //   2986: aload #46
    //   2988: iload #53
    //   2990: baload
    //   2991: bastore
    //   2992: iinc #53, 1
    //   2995: iload_2
    //   2996: ifne -> 2969
    //   2999: iinc #44, 1
    //   3002: iload_2
    //   3003: ifne -> 2084
    //   3006: aload #43
    //   3008: arraylength
    //   3009: ifle -> 3090
    //   3012: aload #43
    //   3014: aload #43
    //   3016: arraylength
    //   3017: iconst_1
    //   3018: isub
    //   3019: baload
    //   3020: istore #44
    //   3022: iload #44
    //   3024: bipush #16
    //   3026: if_icmple -> 3037
    //   3029: aload #43
    //   3031: astore #35
    //   3033: iload_2
    //   3034: ifne -> 3090
    //   3037: aload #43
    //   3039: arraylength
    //   3040: iload #44
    //   3042: isub
    //   3043: newarray byte
    //   3045: astore #35
    //   3047: iconst_0
    //   3048: istore #45
    //   3050: iload #45
    //   3052: aload #35
    //   3054: arraylength
    //   3055: if_icmpge -> 3090
    //   3058: iload #45
    //   3060: aload #43
    //   3062: arraylength
    //   3063: if_icmpge -> 3090
    //   3066: aload #35
    //   3068: iload #45
    //   3070: aload #43
    //   3072: iload #45
    //   3074: baload
    //   3075: bastore
    //   3076: iinc #45, 1
    //   3079: iload_2
    //   3080: ifne -> 3050
    //   3083: goto -> 3090
    //   3086: invokestatic a : (Ljava/lang/Throwable;)Ljava/lang/Throwable;
    //   3089: athrow
    //   3090: aload #35
    //   3092: astore #7
    //   3094: new java/math/BigInteger
    //   3097: dup
    //   3098: aload #7
    //   3100: invokespecial <init> : ([B)V
    //   3103: invokevirtual abs : ()Ljava/math/BigInteger;
    //   3106: putstatic burp/Zegk.ZR : Ljava/lang/Object;
    //   3109: new java/lang/StringBuilder
    //   3112: dup
    //   3113: invokespecial <init> : ()V
    //   3116: astore_3
    //   3117: iconst_0
    //   3118: istore #4
    //   3120: iload #4
    //   3122: bipush #32
    //   3124: if_icmpge -> 4459
    //   3127: iload #4
    //   3129: tableswitch default -> 4452, 0 -> 3272, 1 -> 3309, 2 -> 3346, 3 -> 3383, 4 -> 3420, 5 -> 3457, 6 -> 3494, 7 -> 3531, 8 -> 3568, 9 -> 3605, 10 -> 3642, 11 -> 3679, 12 -> 3716, 13 -> 3753, 14 -> 3790, 15 -> 3827, 16 -> 3864, 17 -> 3901, 18 -> 3938, 19 -> 3975, 20 -> 4012, 21 -> 4049, 22 -> 4086, 23 -> 4123, 24 -> 4160, 25 -> 4197, 26 -> 4234, 27 -> 4271, 28 -> 4308, 29 -> 4345, 30 -> 4382, 31 -> 4419
    //   3272: aload_3
    //   3273: getstatic burp/Zrva.Zr : Ljava/lang/String;
    //   3276: getstatic burp/Zs15.Zk : Ljava/lang/Object;
    //   3279: checkcast java/math/BigInteger
    //   3282: invokevirtual intValue : ()I
    //   3285: bipush #32
    //   3287: irem
    //   3288: invokestatic abs : (I)I
    //   3291: invokevirtual charAt : (I)C
    //   3294: invokevirtual append : (C)Ljava/lang/StringBuilder;
    //   3297: pop
    //   3298: iload_2
    //   3299: ifne -> 4452
    //   3302: goto -> 3309
    //   3305: invokestatic a : (Ljava/lang/Throwable;)Ljava/lang/Throwable;
    //   3308: athrow
    //   3309: aload_3
    //   3310: getstatic burp/Ze4x.Zk : Ljava/lang/String;
    //   3313: getstatic burp/Zt3l.Zq : Ljava/lang/Object;
    //   3316: checkcast java/math/BigInteger
    //   3319: invokevirtual intValue : ()I
    //   3322: bipush #32
    //   3324: irem
    //   3325: invokestatic abs : (I)I
    //   3328: invokevirtual charAt : (I)C
    //   3331: invokevirtual append : (C)Ljava/lang/StringBuilder;
    //   3334: pop
    //   3335: iload_2
    //   3336: ifne -> 4452
    //   3339: goto -> 3346
    //   3342: invokestatic a : (Ljava/lang/Throwable;)Ljava/lang/Throwable;
    //   3345: athrow
    //   3346: aload_3
    //   3347: getstatic burp/Zrp3.Zf : Ljava/lang/String;
    //   3350: getstatic burp/Zzok.ZY : Ljava/lang/Object;
    //   3353: checkcast java/math/BigInteger
    //   3356: invokevirtual intValue : ()I
    //   3359: bipush #32
    //   3361: irem
    //   3362: invokestatic abs : (I)I
    //   3365: invokevirtual charAt : (I)C
    //   3368: invokevirtual append : (C)Ljava/lang/StringBuilder;
    //   3371: pop
    //   3372: iload_2
    //   3373: ifne -> 4452
    //   3376: goto -> 3383
    //   3379: invokestatic a : (Ljava/lang/Throwable;)Ljava/lang/Throwable;
    //   3382: athrow
    //   3383: aload_3
    //   3384: getstatic burp/Zgco.Zh : Ljava/lang/String;
    //   3387: getstatic burp/Zeb3.Zb : Ljava/lang/Object;
    //   3390: checkcast java/math/BigInteger
    //   3393: invokevirtual intValue : ()I
    //   3396: bipush #32
    //   3398: irem
    //   3399: invokestatic abs : (I)I
    //   3402: invokevirtual charAt : (I)C
    //   3405: invokevirtual append : (C)Ljava/lang/StringBuilder;
    //   3408: pop
    //   3409: iload_2
    //   3410: ifne -> 4452
    //   3413: goto -> 3420
    //   3416: invokestatic a : (Ljava/lang/Throwable;)Ljava/lang/Throwable;
    //   3419: athrow
    //   3420: aload_3
    //   3421: getstatic burp/Zbu.ZV : Ljava/lang/String;
    //   3424: getstatic burp/Zf.Zh : Ljava/lang/Object;
    //   3427: checkcast java/math/BigInteger
    //   3430: invokevirtual intValue : ()I
    //   3433: bipush #32
    //   3435: irem
    //   3436: invokestatic abs : (I)I
    //   3439: invokevirtual charAt : (I)C
    //   3442: invokevirtual append : (C)Ljava/lang/StringBuilder;
    //   3445: pop
    //   3446: iload_2
    //   3447: ifne -> 4452
    //   3450: goto -> 3457
    //   3453: invokestatic a : (Ljava/lang/Throwable;)Ljava/lang/Throwable;
    //   3456: athrow
    //   3457: aload_3
    //   3458: getstatic burp/Zsji.Zr : Ljava/lang/String;
    //   3461: getstatic burp/Zg27.ZQ : Ljava/lang/Object;
    //   3464: checkcast java/math/BigInteger
    //   3467: invokevirtual intValue : ()I
    //   3470: bipush #32
    //   3472: irem
    //   3473: invokestatic abs : (I)I
    //   3476: invokevirtual charAt : (I)C
    //   3479: invokevirtual append : (C)Ljava/lang/StringBuilder;
    //   3482: pop
    //   3483: iload_2
    //   3484: ifne -> 4452
    //   3487: goto -> 3494
    //   3490: invokestatic a : (Ljava/lang/Throwable;)Ljava/lang/Throwable;
    //   3493: athrow
    //   3494: aload_3
    //   3495: getstatic burp/Zgvf.ZM : Ljava/lang/String;
    //   3498: getstatic burp/Zb20.Zq : Ljava/lang/Object;
    //   3501: checkcast java/math/BigInteger
    //   3504: invokevirtual intValue : ()I
    //   3507: bipush #32
    //   3509: irem
    //   3510: invokestatic abs : (I)I
    //   3513: invokevirtual charAt : (I)C
    //   3516: invokevirtual append : (C)Ljava/lang/StringBuilder;
    //   3519: pop
    //   3520: iload_2
    //   3521: ifne -> 4452
    //   3524: goto -> 3531
    //   3527: invokestatic a : (Ljava/lang/Throwable;)Ljava/lang/Throwable;
    //   3530: athrow
    //   3531: aload_3
    //   3532: getstatic burp/Zm0s.Zm : Ljava/lang/String;
    //   3535: getstatic burp/Zlhm.ZT : Ljava/lang/Object;
    //   3538: checkcast java/math/BigInteger
    //   3541: invokevirtual intValue : ()I
    //   3544: bipush #32
    //   3546: irem
    //   3547: invokestatic abs : (I)I
    //   3550: invokevirtual charAt : (I)C
    //   3553: invokevirtual append : (C)Ljava/lang/StringBuilder;
    //   3556: pop
    //   3557: iload_2
    //   3558: ifne -> 4452
    //   3561: goto -> 3568
    //   3564: invokestatic a : (Ljava/lang/Throwable;)Ljava/lang/Throwable;
    //   3567: athrow
    //   3568: aload_3
    //   3569: getstatic burp/Zlfi.Zg : Ljava/lang/String;
    //   3572: getstatic burp/Zljx.ZZ : Ljava/lang/Object;
    //   3575: checkcast java/math/BigInteger
    //   3578: invokevirtual intValue : ()I
    //   3581: bipush #32
    //   3583: irem
    //   3584: invokestatic abs : (I)I
    //   3587: invokevirtual charAt : (I)C
    //   3590: invokevirtual append : (C)Ljava/lang/StringBuilder;
    //   3593: pop
    //   3594: iload_2
    //   3595: ifne -> 4452
    //   3598: goto -> 3605
    //   3601: invokestatic a : (Ljava/lang/Throwable;)Ljava/lang/Throwable;
    //   3604: athrow
    //   3605: aload_3
    //   3606: getstatic burp/Zsin.ZC : Ljava/lang/String;
    //   3609: getstatic burp/Zzri.ZG : Ljava/lang/Object;
    //   3612: checkcast java/math/BigInteger
    //   3615: invokevirtual intValue : ()I
    //   3618: bipush #32
    //   3620: irem
    //   3621: invokestatic abs : (I)I
    //   3624: invokevirtual charAt : (I)C
    //   3627: invokevirtual append : (C)Ljava/lang/StringBuilder;
    //   3630: pop
    //   3631: iload_2
    //   3632: ifne -> 4452
    //   3635: goto -> 3642
    //   3638: invokestatic a : (Ljava/lang/Throwable;)Ljava/lang/Throwable;
    //   3641: athrow
    //   3642: aload_3
    //   3643: getstatic burp/Zs6g.ZU : Ljava/lang/String;
    //   3646: getstatic burp/Zm14.ZZ : Ljava/lang/Object;
    //   3649: checkcast java/math/BigInteger
    //   3652: invokevirtual intValue : ()I
    //   3655: bipush #32
    //   3657: irem
    //   3658: invokestatic abs : (I)I
    //   3661: invokevirtual charAt : (I)C
    //   3664: invokevirtual append : (C)Ljava/lang/StringBuilder;
    //   3667: pop
    //   3668: iload_2
    //   3669: ifne -> 4452
    //   3672: goto -> 3679
    //   3675: invokestatic a : (Ljava/lang/Throwable;)Ljava/lang/Throwable;
    //   3678: athrow
    //   3679: aload_3
    //   3680: getstatic burp/Ztap.Zk : Ljava/lang/String;
    //   3683: getstatic burp/Zl8i.ZY : Ljava/lang/Object;
    //   3686: checkcast java/math/BigInteger
    //   3689: invokevirtual intValue : ()I
    //   3692: bipush #32
    //   3694: irem
    //   3695: invokestatic abs : (I)I
    //   3698: invokevirtual charAt : (I)C
    //   3701: invokevirtual append : (C)Ljava/lang/StringBuilder;
    //   3704: pop
    //   3705: iload_2
    //   3706: ifne -> 4452
    //   3709: goto -> 3716
    //   3712: invokestatic a : (Ljava/lang/Throwable;)Ljava/lang/Throwable;
    //   3715: athrow
    //   3716: aload_3
    //   3717: getstatic burp/Zxzv.ZI : Ljava/lang/String;
    //   3720: getstatic burp/Zxpb.Zo : Ljava/lang/Object;
    //   3723: checkcast java/math/BigInteger
    //   3726: invokevirtual intValue : ()I
    //   3729: bipush #32
    //   3731: irem
    //   3732: invokestatic abs : (I)I
    //   3735: invokevirtual charAt : (I)C
    //   3738: invokevirtual append : (C)Ljava/lang/StringBuilder;
    //   3741: pop
    //   3742: iload_2
    //   3743: ifne -> 4452
    //   3746: goto -> 3753
    //   3749: invokestatic a : (Ljava/lang/Throwable;)Ljava/lang/Throwable;
    //   3752: athrow
    //   3753: aload_3
    //   3754: getstatic burp/Zxt5.ZM : Ljava/lang/String;
    //   3757: getstatic burp/Zs_3.ZZ : Ljava/lang/Object;
    //   3760: checkcast java/math/BigInteger
    //   3763: invokevirtual intValue : ()I
    //   3766: bipush #32
    //   3768: irem
    //   3769: invokestatic abs : (I)I
    //   3772: invokevirtual charAt : (I)C
    //   3775: invokevirtual append : (C)Ljava/lang/StringBuilder;
    //   3778: pop
    //   3779: iload_2
    //   3780: ifne -> 4452
    //   3783: goto -> 3790
    //   3786: invokestatic a : (Ljava/lang/Throwable;)Ljava/lang/Throwable;
    //   3789: athrow
    //   3790: aload_3
    //   3791: getstatic burp/Zblj.Za : Ljava/lang/String;
    //   3794: getstatic burp/Zrod.ZX : Ljava/lang/Object;
    //   3797: checkcast java/math/BigInteger
    //   3800: invokevirtual intValue : ()I
    //   3803: bipush #32
    //   3805: irem
    //   3806: invokestatic abs : (I)I
    //   3809: invokevirtual charAt : (I)C
    //   3812: invokevirtual append : (C)Ljava/lang/StringBuilder;
    //   3815: pop
    //   3816: iload_2
    //   3817: ifne -> 4452
    //   3820: goto -> 3827
    //   3823: invokestatic a : (Ljava/lang/Throwable;)Ljava/lang/Throwable;
    //   3826: athrow
    //   3827: aload_3
    //   3828: getstatic burp/Zlyf.ZU : Ljava/lang/String;
    //   3831: getstatic burp/Zm0s.Zl : Ljava/lang/Object;
    //   3834: checkcast java/math/BigInteger
    //   3837: invokevirtual intValue : ()I
    //   3840: bipush #32
    //   3842: irem
    //   3843: invokestatic abs : (I)I
    //   3846: invokevirtual charAt : (I)C
    //   3849: invokevirtual append : (C)Ljava/lang/StringBuilder;
    //   3852: pop
    //   3853: iload_2
    //   3854: ifne -> 4452
    //   3857: goto -> 3864
    //   3860: invokestatic a : (Ljava/lang/Throwable;)Ljava/lang/Throwable;
    //   3863: athrow
    //   3864: aload_3
    //   3865: getstatic burp/Zl1q.ZY : Ljava/lang/String;
    //   3868: getstatic burp/Zro5.ZT : Ljava/lang/Object;
    //   3871: checkcast java/math/BigInteger
    //   3874: invokevirtual intValue : ()I
    //   3877: bipush #32
    //   3879: irem
    //   3880: invokestatic abs : (I)I
    //   3883: invokevirtual charAt : (I)C
    //   3886: invokevirtual append : (C)Ljava/lang/StringBuilder;
    //   3889: pop
    //   3890: iload_2
    //   3891: ifne -> 4452
    //   3894: goto -> 3901
    //   3897: invokestatic a : (Ljava/lang/Throwable;)Ljava/lang/Throwable;
    //   3900: athrow
    //   3901: aload_3
    //   3902: getstatic burp/Zb8v.Zo : Ljava/lang/String;
    //   3905: getstatic burp/Zxn7.ZU : Ljava/lang/Object;
    //   3908: checkcast java/math/BigInteger
    //   3911: invokevirtual intValue : ()I
    //   3914: bipush #32
    //   3916: irem
    //   3917: invokestatic abs : (I)I
    //   3920: invokevirtual charAt : (I)C
    //   3923: invokevirtual append : (C)Ljava/lang/StringBuilder;
    //   3926: pop
    //   3927: iload_2
    //   3928: ifne -> 4452
    //   3931: goto -> 3938
    //   3934: invokestatic a : (Ljava/lang/Throwable;)Ljava/lang/Throwable;
    //   3937: athrow
    //   3938: aload_3
    //   3939: getstatic burp/Ztvp.ZZ : Ljava/lang/String;
    //   3942: getstatic burp/Zs9x.Zo : Ljava/lang/Object;
    //   3945: checkcast java/math/BigInteger
    //   3948: invokevirtual intValue : ()I
    //   3951: bipush #32
    //   3953: irem
    //   3954: invokestatic abs : (I)I
    //   3957: invokevirtual charAt : (I)C
    //   3960: invokevirtual append : (C)Ljava/lang/StringBuilder;
    //   3963: pop
    //   3964: iload_2
    //   3965: ifne -> 4452
    //   3968: goto -> 3975
    //   3971: invokestatic a : (Ljava/lang/Throwable;)Ljava/lang/Throwable;
    //   3974: athrow
    //   3975: aload_3
    //   3976: getstatic burp/Zk9s.ZM : Ljava/lang/String;
    //   3979: getstatic burp/Zkaw.ZB : Ljava/lang/Object;
    //   3982: checkcast java/math/BigInteger
    //   3985: invokevirtual intValue : ()I
    //   3988: bipush #32
    //   3990: irem
    //   3991: invokestatic abs : (I)I
    //   3994: invokevirtual charAt : (I)C
    //   3997: invokevirtual append : (C)Ljava/lang/StringBuilder;
    //   4000: pop
    //   4001: iload_2
    //   4002: ifne -> 4452
    //   4005: goto -> 4012
    //   4008: invokestatic a : (Ljava/lang/Throwable;)Ljava/lang/Throwable;
    //   4011: athrow
    //   4012: aload_3
    //   4013: getstatic burp/Zmou.ZP : Ljava/lang/String;
    //   4016: getstatic burp/Ztuj.Ze : Ljava/lang/Object;
    //   4019: checkcast java/math/BigInteger
    //   4022: invokevirtual intValue : ()I
    //   4025: bipush #32
    //   4027: irem
    //   4028: invokestatic abs : (I)I
    //   4031: invokevirtual charAt : (I)C
    //   4034: invokevirtual append : (C)Ljava/lang/StringBuilder;
    //   4037: pop
    //   4038: iload_2
    //   4039: ifne -> 4452
    //   4042: goto -> 4049
    //   4045: invokestatic a : (Ljava/lang/Throwable;)Ljava/lang/Throwable;
    //   4048: athrow
    //   4049: aload_3
    //   4050: getstatic burp/Zmhx.ZD : Ljava/lang/String;
    //   4053: getstatic burp/Zgh3.ZZ : Ljava/lang/Object;
    //   4056: checkcast java/math/BigInteger
    //   4059: invokevirtual intValue : ()I
    //   4062: bipush #32
    //   4064: irem
    //   4065: invokestatic abs : (I)I
    //   4068: invokevirtual charAt : (I)C
    //   4071: invokevirtual append : (C)Ljava/lang/StringBuilder;
    //   4074: pop
    //   4075: iload_2
    //   4076: ifne -> 4452
    //   4079: goto -> 4086
    //   4082: invokestatic a : (Ljava/lang/Throwable;)Ljava/lang/Throwable;
    //   4085: athrow
    //   4086: aload_3
    //   4087: getstatic burp/Zlr2.ZV : Ljava/lang/String;
    //   4090: getstatic burp/Zgvl.ZK : Ljava/lang/Object;
    //   4093: checkcast java/math/BigInteger
    //   4096: invokevirtual intValue : ()I
    //   4099: bipush #32
    //   4101: irem
    //   4102: invokestatic abs : (I)I
    //   4105: invokevirtual charAt : (I)C
    //   4108: invokevirtual append : (C)Ljava/lang/StringBuilder;
    //   4111: pop
    //   4112: iload_2
    //   4113: ifne -> 4452
    //   4116: goto -> 4123
    //   4119: invokestatic a : (Ljava/lang/Throwable;)Ljava/lang/Throwable;
    //   4122: athrow
    //   4123: aload_3
    //   4124: getstatic burp/Zmha.Zo : Ljava/lang/String;
    //   4127: getstatic burp/Zs75.Zo : Ljava/lang/Object;
    //   4130: checkcast java/math/BigInteger
    //   4133: invokevirtual intValue : ()I
    //   4136: bipush #32
    //   4138: irem
    //   4139: invokestatic abs : (I)I
    //   4142: invokevirtual charAt : (I)C
    //   4145: invokevirtual append : (C)Ljava/lang/StringBuilder;
    //   4148: pop
    //   4149: iload_2
    //   4150: ifne -> 4452
    //   4153: goto -> 4160
    //   4156: invokestatic a : (Ljava/lang/Throwable;)Ljava/lang/Throwable;
    //   4159: athrow
    //   4160: aload_3
    //   4161: getstatic burp/Zsot.Zb : Ljava/lang/String;
    //   4164: getstatic burp/Zlps.ZU : Ljava/lang/Object;
    //   4167: checkcast java/math/BigInteger
    //   4170: invokevirtual intValue : ()I
    //   4173: bipush #32
    //   4175: irem
    //   4176: invokestatic abs : (I)I
    //   4179: invokevirtual charAt : (I)C
    //   4182: invokevirtual append : (C)Ljava/lang/StringBuilder;
    //   4185: pop
    //   4186: iload_2
    //   4187: ifne -> 4452
    //   4190: goto -> 4197
    //   4193: invokestatic a : (Ljava/lang/Throwable;)Ljava/lang/Throwable;
    //   4196: athrow
    //   4197: aload_3
    //   4198: getstatic burp/Zs59.Zc : Ljava/lang/String;
    //   4201: getstatic burp/Zr48.ZZ : Ljava/lang/Object;
    //   4204: checkcast java/math/BigInteger
    //   4207: invokevirtual intValue : ()I
    //   4210: bipush #32
    //   4212: irem
    //   4213: invokestatic abs : (I)I
    //   4216: invokevirtual charAt : (I)C
    //   4219: invokevirtual append : (C)Ljava/lang/StringBuilder;
    //   4222: pop
    //   4223: iload_2
    //   4224: ifne -> 4452
    //   4227: goto -> 4234
    //   4230: invokestatic a : (Ljava/lang/Throwable;)Ljava/lang/Throwable;
    //   4233: athrow
    //   4234: aload_3
    //   4235: getstatic burp/Zkv2.Z_ : Ljava/lang/String;
    //   4238: getstatic burp/Zmvk.ZK : Ljava/lang/Object;
    //   4241: checkcast java/math/BigInteger
    //   4244: invokevirtual intValue : ()I
    //   4247: bipush #32
    //   4249: irem
    //   4250: invokestatic abs : (I)I
    //   4253: invokevirtual charAt : (I)C
    //   4256: invokevirtual append : (C)Ljava/lang/StringBuilder;
    //   4259: pop
    //   4260: iload_2
    //   4261: ifne -> 4452
    //   4264: goto -> 4271
    //   4267: invokestatic a : (Ljava/lang/Throwable;)Ljava/lang/Throwable;
    //   4270: athrow
    //   4271: aload_3
    //   4272: getstatic burp/Zlfg.Zb : Ljava/lang/String;
    //   4275: getstatic burp/Zeuz.Zp : Ljava/lang/Object;
    //   4278: checkcast java/math/BigInteger
    //   4281: invokevirtual intValue : ()I
    //   4284: bipush #32
    //   4286: irem
    //   4287: invokestatic abs : (I)I
    //   4290: invokevirtual charAt : (I)C
    //   4293: invokevirtual append : (C)Ljava/lang/StringBuilder;
    //   4296: pop
    //   4297: iload_2
    //   4298: ifne -> 4452
    //   4301: goto -> 4308
    //   4304: invokestatic a : (Ljava/lang/Throwable;)Ljava/lang/Throwable;
    //   4307: athrow
    //   4308: aload_3
    //   4309: getstatic burp/Zg3v.Zt : Ljava/lang/String;
    //   4312: getstatic burp/Zevc.Zm : Ljava/lang/Object;
    //   4315: checkcast java/math/BigInteger
    //   4318: invokevirtual intValue : ()I
    //   4321: bipush #32
    //   4323: irem
    //   4324: invokestatic abs : (I)I
    //   4327: invokevirtual charAt : (I)C
    //   4330: invokevirtual append : (C)Ljava/lang/StringBuilder;
    //   4333: pop
    //   4334: iload_2
    //   4335: ifne -> 4452
    //   4338: goto -> 4345
    //   4341: invokestatic a : (Ljava/lang/Throwable;)Ljava/lang/Throwable;
    //   4344: athrow
    //   4345: aload_3
    //   4346: getstatic burp/Ztuj.Zk : Ljava/lang/String;
    //   4349: getstatic burp/Zk8b.ZK : Ljava/lang/Object;
    //   4352: checkcast java/math/BigInteger
    //   4355: invokevirtual intValue : ()I
    //   4358: bipush #32
    //   4360: irem
    //   4361: invokestatic abs : (I)I
    //   4364: invokevirtual charAt : (I)C
    //   4367: invokevirtual append : (C)Ljava/lang/StringBuilder;
    //   4370: pop
    //   4371: iload_2
    //   4372: ifne -> 4452
    //   4375: goto -> 4382
    //   4378: invokestatic a : (Ljava/lang/Throwable;)Ljava/lang/Throwable;
    //   4381: athrow
    //   4382: aload_3
    //   4383: getstatic burp/Zgkl.ZR : Ljava/lang/String;
    //   4386: getstatic burp/Ztkh.Zh : Ljava/lang/Object;
    //   4389: checkcast java/math/BigInteger
    //   4392: invokevirtual intValue : ()I
    //   4395: bipush #32
    //   4397: irem
    //   4398: invokestatic abs : (I)I
    //   4401: invokevirtual charAt : (I)C
    //   4404: invokevirtual append : (C)Ljava/lang/StringBuilder;
    //   4407: pop
    //   4408: iload_2
    //   4409: ifne -> 4452
    //   4412: goto -> 4419
    //   4415: invokestatic a : (Ljava/lang/Throwable;)Ljava/lang/Throwable;
    //   4418: athrow
    //   4419: aload_3
    //   4420: getstatic burp/Ze54.ZU : Ljava/lang/String;
    //   4423: getstatic burp/Zgz1.ZX : Ljava/lang/Object;
    //   4426: checkcast java/math/BigInteger
    //   4429: invokevirtual intValue : ()I
    //   4432: bipush #32
    //   4434: irem
    //   4435: invokestatic abs : (I)I
    //   4438: invokevirtual charAt : (I)C
    //   4441: invokevirtual append : (C)Ljava/lang/StringBuilder;
    //   4444: pop
    //   4445: goto -> 4452
    //   4448: invokestatic a : (Ljava/lang/Throwable;)Ljava/lang/Throwable;
    //   4451: athrow
    //   4452: iinc #4, 1
    //   4455: iload_2
    //   4456: ifne -> 3120
    //   4459: aload_3
    //   4460: invokevirtual toString : ()Ljava/lang/String;
    //   4463: putstatic burp/Zsdn.Zf : Ljava/lang/String;
    //   4466: sipush #-28091
    //   4469: sipush #9070
    //   4472: invokestatic a : (II)Ljava/lang/String;
    //   4475: iconst_1
    //   4476: ldc burp/Zl1q
    //   4478: invokevirtual getClassLoader : ()Ljava/lang/ClassLoader;
    //   4481: invokestatic forName : (Ljava/lang/String;ZLjava/lang/ClassLoader;)Ljava/lang/Class;
    //   4484: invokevirtual getDeclaredFields : ()[Ljava/lang/reflect/Field;
    //   4487: astore #4
    //   4489: aload #4
    //   4491: arraylength
    //   4492: istore #5
    //   4494: iconst_0
    //   4495: istore #6
    //   4497: iload #6
    //   4499: iload #5
    //   4501: if_icmpge -> 4639
    //   4504: aload #4
    //   4506: iload #6
    //   4508: aaload
    //   4509: astore #7
    //   4511: aload #7
    //   4513: invokevirtual getModifiers : ()I
    //   4516: invokestatic isStatic : (I)Z
    //   4519: ifne -> 4529
    //   4522: goto -> 4632
    //   4525: invokestatic a : (Ljava/lang/Throwable;)Ljava/lang/Throwable;
    //   4528: athrow
    //   4529: aload #7
    //   4531: invokevirtual getType : ()Ljava/lang/Class;
    //   4534: astore #8
    //   4536: aload #8
    //   4538: ifnull -> 4619
    //   4541: aload #8
    //   4543: invokevirtual isPrimitive : ()Z
    //   4546: ifne -> 4619
    //   4549: goto -> 4556
    //   4552: invokestatic a : (Ljava/lang/Throwable;)Ljava/lang/Throwable;
    //   4555: athrow
    //   4556: aload #8
    //   4558: invokevirtual getPackage : ()Ljava/lang/Package;
    //   4561: ifnull -> 4619
    //   4564: goto -> 4571
    //   4567: invokestatic a : (Ljava/lang/Throwable;)Ljava/lang/Throwable;
    //   4570: athrow
    //   4571: aload #8
    //   4573: invokevirtual getPackage : ()Ljava/lang/Package;
    //   4576: invokevirtual getName : ()Ljava/lang/String;
    //   4579: ifnull -> 4619
    //   4582: goto -> 4589
    //   4585: invokestatic a : (Ljava/lang/Throwable;)Ljava/lang/Throwable;
    //   4588: athrow
    //   4589: aload #8
    //   4591: invokevirtual getPackage : ()Ljava/lang/Package;
    //   4594: invokevirtual getName : ()Ljava/lang/String;
    //   4597: sipush #-28066
    //   4600: sipush #-9898
    //   4603: invokestatic a : (II)Ljava/lang/String;
    //   4606: invokevirtual startsWith : (Ljava/lang/String;)Z
    //   4609: ifne -> 4619
    //   4612: goto -> 4619
    //   4615: invokestatic a : (Ljava/lang/Throwable;)Ljava/lang/Throwable;
    //   4618: athrow
    //   4619: aload #7
    //   4621: iconst_1
    //   4622: invokevirtual setAccessible : (Z)V
    //   4625: aload #7
    //   4627: aconst_null
    //   4628: invokevirtual get : (Ljava/lang/Object;)Ljava/lang/Object;
    //   4631: pop
    //   4632: iinc #6, 1
    //   4635: iload_2
    //   4636: ifne -> 4497
    //   4639: sipush #-28081
    //   4642: sipush #-28607
    //   4645: invokestatic a : (II)Ljava/lang/String;
    //   4648: invokestatic forName : (Ljava/lang/String;)Ljava/lang/Class;
    //   4651: invokevirtual getDeclaredMethods : ()[Ljava/lang/reflect/Method;
    //   4654: astore #4
    //   4656: aload #4
    //   4658: arraylength
    //   4659: istore #5
    //   4661: iconst_0
    //   4662: istore #6
    //   4664: iload #6
    //   4666: iload #5
    //   4668: if_icmpge -> 4798
    //   4671: aload #4
    //   4673: iload #6
    //   4675: aaload
    //   4676: astore #7
    //   4678: aload #7
    //   4680: invokevirtual getParameterTypes : ()[Ljava/lang/Class;
    //   4683: pop
    //   4684: aload #7
    //   4686: invokevirtual getModifiers : ()I
    //   4689: invokestatic isStatic : (I)Z
    //   4692: ifeq -> 4784
    //   4695: aload #7
    //   4697: invokevirtual getParameterTypes : ()[Ljava/lang/Class;
    //   4700: arraylength
    //   4701: iconst_2
    //   4702: if_icmpne -> 4784
    //   4705: goto -> 4712
    //   4708: invokestatic a : (Ljava/lang/Throwable;)Ljava/lang/Throwable;
    //   4711: athrow
    //   4712: aload #7
    //   4714: invokevirtual getReturnType : ()Ljava/lang/Class;
    //   4717: getstatic java/lang/Boolean.TYPE : Ljava/lang/Class;
    //   4720: if_acmpne -> 4784
    //   4723: goto -> 4730
    //   4726: invokestatic a : (Ljava/lang/Throwable;)Ljava/lang/Throwable;
    //   4729: athrow
    //   4730: aload #7
    //   4732: iconst_1
    //   4733: invokevirtual setAccessible : (Z)V
    //   4736: aload #7
    //   4738: aconst_null
    //   4739: iconst_2
    //   4740: anewarray java/lang/Object
    //   4743: dup
    //   4744: iconst_0
    //   4745: aload_0
    //   4746: aastore
    //   4747: dup
    //   4748: iconst_1
    //   4749: aload_1
    //   4750: ifnonnull -> 4768
    //   4753: goto -> 4760
    //   4756: invokestatic a : (Ljava/lang/Throwable;)Ljava/lang/Throwable;
    //   4759: athrow
    //   4760: aload_1
    //   4761: goto -> 4775
    //   4764: invokestatic a : (Ljava/lang/Throwable;)Ljava/lang/Throwable;
    //   4767: athrow
    //   4768: aload_1
    //   4769: checkcast [B
    //   4772: invokevirtual clone : ()Ljava/lang/Object;
    //   4775: aastore
    //   4776: invokevirtual invoke : (Ljava/lang/Object;[Ljava/lang/Object;)Ljava/lang/Object;
    //   4779: pop
    //   4780: iload_2
    //   4781: ifne -> 4798
    //   4784: iinc #6, 1
    //   4787: iload_2
    //   4788: ifne -> 4664
    //   4791: goto -> 4798
    //   4794: invokestatic a : (Ljava/lang/Throwable;)Ljava/lang/Throwable;
    //   4797: athrow
    //   4798: sipush #-28074
    //   4801: sipush #-4723
    //   4804: invokestatic a : (II)Ljava/lang/String;
    //   4807: iconst_1
    //   4808: ldc burp/Zvi
    //   4810: invokevirtual getClassLoader : ()Ljava/lang/ClassLoader;
    //   4813: invokestatic forName : (Ljava/lang/String;ZLjava/lang/ClassLoader;)Ljava/lang/Class;
    //   4816: invokevirtual getDeclaredFields : ()[Ljava/lang/reflect/Field;
    //   4819: astore #4
    //   4821: aload #4
    //   4823: arraylength
    //   4824: istore #5
    //   4826: iconst_0
    //   4827: istore #6
    //   4829: iload #6
    //   4831: iload #5
    //   4833: if_icmpge -> 4971
    //   4836: aload #4
    //   4838: iload #6
    //   4840: aaload
    //   4841: astore #7
    //   4843: aload #7
    //   4845: invokevirtual getModifiers : ()I
    //   4848: invokestatic isStatic : (I)Z
    //   4851: ifne -> 4861
    //   4854: goto -> 4964
    //   4857: invokestatic a : (Ljava/lang/Throwable;)Ljava/lang/Throwable;
    //   4860: athrow
    //   4861: aload #7
    //   4863: invokevirtual getType : ()Ljava/lang/Class;
    //   4866: astore #8
    //   4868: aload #8
    //   4870: ifnull -> 4951
    //   4873: aload #8
    //   4875: invokevirtual isPrimitive : ()Z
    //   4878: ifne -> 4951
    //   4881: goto -> 4888
    //   4884: invokestatic a : (Ljava/lang/Throwable;)Ljava/lang/Throwable;
    //   4887: athrow
    //   4888: aload #8
    //   4890: invokevirtual getPackage : ()Ljava/lang/Package;
    //   4893: ifnull -> 4951
    //   4896: goto -> 4903
    //   4899: invokestatic a : (Ljava/lang/Throwable;)Ljava/lang/Throwable;
    //   4902: athrow
    //   4903: aload #8
    //   4905: invokevirtual getPackage : ()Ljava/lang/Package;
    //   4908: invokevirtual getName : ()Ljava/lang/String;
    //   4911: ifnull -> 4951
    //   4914: goto -> 4921
    //   4917: invokestatic a : (Ljava/lang/Throwable;)Ljava/lang/Throwable;
    //   4920: athrow
    //   4921: aload #8
    //   4923: invokevirtual getPackage : ()Ljava/lang/Package;
    //   4926: invokevirtual getName : ()Ljava/lang/String;
    //   4929: sipush #-28096
    //   4932: sipush #26624
    //   4935: invokestatic a : (II)Ljava/lang/String;
    //   4938: invokevirtual startsWith : (Ljava/lang/String;)Z
    //   4941: ifne -> 4951
    //   4944: goto -> 4951
    //   4947: invokestatic a : (Ljava/lang/Throwable;)Ljava/lang/Throwable;
    //   4950: athrow
    //   4951: aload #7
    //   4953: iconst_1
    //   4954: invokevirtual setAccessible : (Z)V
    //   4957: aload #7
    //   4959: aconst_null
    //   4960: invokevirtual get : (Ljava/lang/Object;)Ljava/lang/Object;
    //   4963: pop
    //   4964: iinc #6, 1
    //   4967: iload_2
    //   4968: ifne -> 4829
    //   4971: sipush #-28083
    //   4974: sipush #20777
    //   4977: invokestatic a : (II)Ljava/lang/String;
    //   4980: invokestatic forName : (Ljava/lang/String;)Ljava/lang/Class;
    //   4983: invokevirtual getDeclaredMethods : ()[Ljava/lang/reflect/Method;
    //   4986: astore #4
    //   4988: aload #4
    //   4990: arraylength
    //   4991: istore #5
    //   4993: iconst_0
    //   4994: istore #6
    //   4996: iload #6
    //   4998: iload #5
    //   5000: if_icmpge -> 5133
    //   5003: aload #4
    //   5005: iload #6
    //   5007: aaload
    //   5008: astore #7
    //   5010: aload #7
    //   5012: invokevirtual getParameterTypes : ()[Ljava/lang/Class;
    //   5015: pop
    //   5016: aload #7
    //   5018: invokevirtual getModifiers : ()I
    //   5021: invokestatic isStatic : (I)Z
    //   5024: ifeq -> 5119
    //   5027: aload #7
    //   5029: invokevirtual getParameterTypes : ()[Ljava/lang/Class;
    //   5032: arraylength
    //   5033: iconst_2
    //   5034: if_icmpne -> 5119
    //   5037: goto -> 5044
    //   5040: invokestatic a : (Ljava/lang/Throwable;)Ljava/lang/Throwable;
    //   5043: athrow
    //   5044: aload #7
    //   5046: invokevirtual getReturnType : ()Ljava/lang/Class;
    //   5049: getstatic java/lang/Void.TYPE : Ljava/lang/Class;
    //   5052: invokevirtual equals : (Ljava/lang/Object;)Z
    //   5055: ifeq -> 5119
    //   5058: goto -> 5065
    //   5061: invokestatic a : (Ljava/lang/Throwable;)Ljava/lang/Throwable;
    //   5064: athrow
    //   5065: aload #7
    //   5067: iconst_1
    //   5068: invokevirtual setAccessible : (Z)V
    //   5071: aload #7
    //   5073: aconst_null
    //   5074: iconst_2
    //   5075: anewarray java/lang/Object
    //   5078: dup
    //   5079: iconst_0
    //   5080: aload_0
    //   5081: aastore
    //   5082: dup
    //   5083: iconst_1
    //   5084: aload_1
    //   5085: ifnonnull -> 5103
    //   5088: goto -> 5095
    //   5091: invokestatic a : (Ljava/lang/Throwable;)Ljava/lang/Throwable;
    //   5094: athrow
    //   5095: aload_1
    //   5096: goto -> 5110
    //   5099: invokestatic a : (Ljava/lang/Throwable;)Ljava/lang/Throwable;
    //   5102: athrow
    //   5103: aload_1
    //   5104: checkcast [B
    //   5107: invokevirtual clone : ()Ljava/lang/Object;
    //   5110: aastore
    //   5111: invokevirtual invoke : (Ljava/lang/Object;[Ljava/lang/Object;)Ljava/lang/Object;
    //   5114: pop
    //   5115: iload_2
    //   5116: ifne -> 5133
    //   5119: iinc #6, 1
    //   5122: iload_2
    //   5123: ifne -> 4996
    //   5126: goto -> 5133
    //   5129: invokestatic a : (Ljava/lang/Throwable;)Ljava/lang/Throwable;
    //   5132: athrow
    //   5133: iconst_0
    //   5134: istore #4
    //   5136: getstatic burp/Zb9m.Zc : Ljava/lang/String;
    //   5139: getstatic burp/Ze7y.Zh : Ljava/lang/Object;
    //   5142: checkcast java/math/BigInteger
    //   5145: invokevirtual intValue : ()I
    //   5148: bipush #32
    //   5150: irem
    //   5151: invokestatic abs : (I)I
    //   5154: invokevirtual charAt : (I)C
    //   5157: getstatic burp/Zm81.ZY : Ljava/lang/String;
    //   5160: getstatic burp/Zk8g.Zb : Ljava/lang/Object;
    //   5163: checkcast java/math/BigInteger
    //   5166: invokevirtual intValue : ()I
    //   5169: bipush #32
    //   5171: irem
    //   5172: invokestatic abs : (I)I
    //   5175: invokevirtual charAt : (I)C
    //   5178: if_icmpgt -> 5523
    //   5181: sipush #-28085
    //   5184: sipush #-24970
    //   5187: invokestatic a : (II)Ljava/lang/String;
    //   5190: iconst_1
    //   5191: ldc burp/Zxe
    //   5193: invokevirtual getClassLoader : ()Ljava/lang/ClassLoader;
    //   5196: invokestatic forName : (Ljava/lang/String;ZLjava/lang/ClassLoader;)Ljava/lang/Class;
    //   5199: invokevirtual getDeclaredFields : ()[Ljava/lang/reflect/Field;
    //   5202: astore #5
    //   5204: aload #5
    //   5206: arraylength
    //   5207: istore #6
    //   5209: iconst_0
    //   5210: istore #7
    //   5212: iload #7
    //   5214: iload #6
    //   5216: if_icmpge -> 5354
    //   5219: aload #5
    //   5221: iload #7
    //   5223: aaload
    //   5224: astore #8
    //   5226: aload #8
    //   5228: invokevirtual getModifiers : ()I
    //   5231: invokestatic isStatic : (I)Z
    //   5234: ifne -> 5244
    //   5237: goto -> 5347
    //   5240: invokestatic a : (Ljava/lang/Throwable;)Ljava/lang/Throwable;
    //   5243: athrow
    //   5244: aload #8
    //   5246: invokevirtual getType : ()Ljava/lang/Class;
    //   5249: astore #9
    //   5251: aload #9
    //   5253: ifnull -> 5334
    //   5256: aload #9
    //   5258: invokevirtual isPrimitive : ()Z
    //   5261: ifne -> 5334
    //   5264: goto -> 5271
    //   5267: invokestatic a : (Ljava/lang/Throwable;)Ljava/lang/Throwable;
    //   5270: athrow
    //   5271: aload #9
    //   5273: invokevirtual getPackage : ()Ljava/lang/Package;
    //   5276: ifnull -> 5334
    //   5279: goto -> 5286
    //   5282: invokestatic a : (Ljava/lang/Throwable;)Ljava/lang/Throwable;
    //   5285: athrow
    //   5286: aload #9
    //   5288: invokevirtual getPackage : ()Ljava/lang/Package;
    //   5291: invokevirtual getName : ()Ljava/lang/String;
    //   5294: ifnull -> 5334
    //   5297: goto -> 5304
    //   5300: invokestatic a : (Ljava/lang/Throwable;)Ljava/lang/Throwable;
    //   5303: athrow
    //   5304: aload #9
    //   5306: invokevirtual getPackage : ()Ljava/lang/Package;
    //   5309: invokevirtual getName : ()Ljava/lang/String;
    //   5312: sipush #-28096
    //   5315: sipush #26624
    //   5318: invokestatic a : (II)Ljava/lang/String;
    //   5321: invokevirtual startsWith : (Ljava/lang/String;)Z
    //   5324: ifne -> 5334
    //   5327: goto -> 5334
    //   5330: invokestatic a : (Ljava/lang/Throwable;)Ljava/lang/Throwable;
    //   5333: athrow
    //   5334: aload #8
    //   5336: iconst_1
    //   5337: invokevirtual setAccessible : (Z)V
    //   5340: aload #8
    //   5342: aconst_null
    //   5343: invokevirtual get : (Ljava/lang/Object;)Ljava/lang/Object;
    //   5346: pop
    //   5347: iinc #7, 1
    //   5350: iload_2
    //   5351: ifne -> 5212
    //   5354: sipush #-28065
    //   5357: sipush #-19900
    //   5360: invokestatic a : (II)Ljava/lang/String;
    //   5363: invokestatic forName : (Ljava/lang/String;)Ljava/lang/Class;
    //   5366: invokevirtual getDeclaredMethods : ()[Ljava/lang/reflect/Method;
    //   5369: astore #5
    //   5371: aload #5
    //   5373: arraylength
    //   5374: istore #6
    //   5376: iconst_0
    //   5377: istore #7
    //   5379: iload #7
    //   5381: iload #6
    //   5383: if_icmpge -> 5520
    //   5386: aload #5
    //   5388: iload #7
    //   5390: aaload
    //   5391: astore #8
    //   5393: aload #8
    //   5395: invokevirtual getParameterTypes : ()[Ljava/lang/Class;
    //   5398: pop
    //   5399: aload #8
    //   5401: invokevirtual getModifiers : ()I
    //   5404: invokestatic isStatic : (I)Z
    //   5407: ifeq -> 5506
    //   5410: aload #8
    //   5412: invokevirtual getParameterTypes : ()[Ljava/lang/Class;
    //   5415: arraylength
    //   5416: iconst_2
    //   5417: if_icmpne -> 5506
    //   5420: goto -> 5427
    //   5423: invokestatic a : (Ljava/lang/Throwable;)Ljava/lang/Throwable;
    //   5426: athrow
    //   5427: aload #8
    //   5429: invokevirtual getReturnType : ()Ljava/lang/Class;
    //   5432: getstatic java/lang/Boolean.TYPE : Ljava/lang/Class;
    //   5435: if_acmpne -> 5506
    //   5438: goto -> 5445
    //   5441: invokestatic a : (Ljava/lang/Throwable;)Ljava/lang/Throwable;
    //   5444: athrow
    //   5445: aload #8
    //   5447: iconst_1
    //   5448: invokevirtual setAccessible : (Z)V
    //   5451: aload #8
    //   5453: aconst_null
    //   5454: iconst_2
    //   5455: anewarray java/lang/Object
    //   5458: dup
    //   5459: iconst_0
    //   5460: aload_0
    //   5461: aastore
    //   5462: dup
    //   5463: iconst_1
    //   5464: aload_1
    //   5465: ifnonnull -> 5483
    //   5468: goto -> 5475
    //   5471: invokestatic a : (Ljava/lang/Throwable;)Ljava/lang/Throwable;
    //   5474: athrow
    //   5475: aload_1
    //   5476: goto -> 5490
    //   5479: invokestatic a : (Ljava/lang/Throwable;)Ljava/lang/Throwable;
    //   5482: athrow
    //   5483: aload_1
    //   5484: checkcast [B
    //   5487: invokevirtual clone : ()Ljava/lang/Object;
    //   5490: aastore
    //   5491: invokevirtual invoke : (Ljava/lang/Object;[Ljava/lang/Object;)Ljava/lang/Object;
    //   5494: checkcast java/lang/Boolean
    //   5497: invokevirtual booleanValue : ()Z
    //   5500: istore #4
    //   5502: iload_2
    //   5503: ifne -> 5520
    //   5506: iinc #7, 1
    //   5509: iload_2
    //   5510: ifne -> 5379
    //   5513: goto -> 5520
    //   5516: invokestatic a : (Ljava/lang/Throwable;)Ljava/lang/Throwable;
    //   5519: athrow
    //   5520: goto -> 5862
    //   5523: sipush #-28073
    //   5526: sipush #24920
    //   5529: invokestatic a : (II)Ljava/lang/String;
    //   5532: iconst_1
    //   5533: ldc burp/Zsf7
    //   5535: invokevirtual getClassLoader : ()Ljava/lang/ClassLoader;
    //   5538: invokestatic forName : (Ljava/lang/String;ZLjava/lang/ClassLoader;)Ljava/lang/Class;
    //   5541: invokevirtual getDeclaredFields : ()[Ljava/lang/reflect/Field;
    //   5544: astore #5
    //   5546: aload #5
    //   5548: arraylength
    //   5549: istore #6
    //   5551: iconst_0
    //   5552: istore #7
    //   5554: iload #7
    //   5556: iload #6
    //   5558: if_icmpge -> 5696
    //   5561: aload #5
    //   5563: iload #7
    //   5565: aaload
    //   5566: astore #8
    //   5568: aload #8
    //   5570: invokevirtual getModifiers : ()I
    //   5573: invokestatic isStatic : (I)Z
    //   5576: ifne -> 5586
    //   5579: goto -> 5689
    //   5582: invokestatic a : (Ljava/lang/Throwable;)Ljava/lang/Throwable;
    //   5585: athrow
    //   5586: aload #8
    //   5588: invokevirtual getType : ()Ljava/lang/Class;
    //   5591: astore #9
    //   5593: aload #9
    //   5595: ifnull -> 5676
    //   5598: aload #9
    //   5600: invokevirtual isPrimitive : ()Z
    //   5603: ifne -> 5676
    //   5606: goto -> 5613
    //   5609: invokestatic a : (Ljava/lang/Throwable;)Ljava/lang/Throwable;
    //   5612: athrow
    //   5613: aload #9
    //   5615: invokevirtual getPackage : ()Ljava/lang/Package;
    //   5618: ifnull -> 5676
    //   5621: goto -> 5628
    //   5624: invokestatic a : (Ljava/lang/Throwable;)Ljava/lang/Throwable;
    //   5627: athrow
    //   5628: aload #9
    //   5630: invokevirtual getPackage : ()Ljava/lang/Package;
    //   5633: invokevirtual getName : ()Ljava/lang/String;
    //   5636: ifnull -> 5676
    //   5639: goto -> 5646
    //   5642: invokestatic a : (Ljava/lang/Throwable;)Ljava/lang/Throwable;
    //   5645: athrow
    //   5646: aload #9
    //   5648: invokevirtual getPackage : ()Ljava/lang/Package;
    //   5651: invokevirtual getName : ()Ljava/lang/String;
    //   5654: sipush #-28096
    //   5657: sipush #26624
    //   5660: invokestatic a : (II)Ljava/lang/String;
    //   5663: invokevirtual startsWith : (Ljava/lang/String;)Z
    //   5666: ifne -> 5676
    //   5669: goto -> 5676
    //   5672: invokestatic a : (Ljava/lang/Throwable;)Ljava/lang/Throwable;
    //   5675: athrow
    //   5676: aload #8
    //   5678: iconst_1
    //   5679: invokevirtual setAccessible : (Z)V
    //   5682: aload #8
    //   5684: aconst_null
    //   5685: invokevirtual get : (Ljava/lang/Object;)Ljava/lang/Object;
    //   5688: pop
    //   5689: iinc #7, 1
    //   5692: iload_2
    //   5693: ifne -> 5554
    //   5696: sipush #-28076
    //   5699: sipush #-7286
    //   5702: invokestatic a : (II)Ljava/lang/String;
    //   5705: invokestatic forName : (Ljava/lang/String;)Ljava/lang/Class;
    //   5708: invokevirtual getDeclaredMethods : ()[Ljava/lang/reflect/Method;
    //   5711: astore #5
    //   5713: aload #5
    //   5715: arraylength
    //   5716: istore #6
    //   5718: iconst_0
    //   5719: istore #7
    //   5721: iload #7
    //   5723: iload #6
    //   5725: if_icmpge -> 5862
    //   5728: aload #5
    //   5730: iload #7
    //   5732: aaload
    //   5733: astore #8
    //   5735: aload #8
    //   5737: invokevirtual getParameterTypes : ()[Ljava/lang/Class;
    //   5740: pop
    //   5741: aload #8
    //   5743: invokevirtual getModifiers : ()I
    //   5746: invokestatic isStatic : (I)Z
    //   5749: ifeq -> 5848
    //   5752: aload #8
    //   5754: invokevirtual getParameterTypes : ()[Ljava/lang/Class;
    //   5757: arraylength
    //   5758: iconst_2
    //   5759: if_icmpne -> 5848
    //   5762: goto -> 5769
    //   5765: invokestatic a : (Ljava/lang/Throwable;)Ljava/lang/Throwable;
    //   5768: athrow
    //   5769: aload #8
    //   5771: invokevirtual getReturnType : ()Ljava/lang/Class;
    //   5774: getstatic java/lang/Boolean.TYPE : Ljava/lang/Class;
    //   5777: if_acmpne -> 5848
    //   5780: goto -> 5787
    //   5783: invokestatic a : (Ljava/lang/Throwable;)Ljava/lang/Throwable;
    //   5786: athrow
    //   5787: aload #8
    //   5789: iconst_1
    //   5790: invokevirtual setAccessible : (Z)V
    //   5793: aload #8
    //   5795: aconst_null
    //   5796: iconst_2
    //   5797: anewarray java/lang/Object
    //   5800: dup
    //   5801: iconst_0
    //   5802: aload_0
    //   5803: aastore
    //   5804: dup
    //   5805: iconst_1
    //   5806: aload_1
    //   5807: ifnonnull -> 5825
    //   5810: goto -> 5817
    //   5813: invokestatic a : (Ljava/lang/Throwable;)Ljava/lang/Throwable;
    //   5816: athrow
    //   5817: aload_1
    //   5818: goto -> 5832
    //   5821: invokestatic a : (Ljava/lang/Throwable;)Ljava/lang/Throwable;
    //   5824: athrow
    //   5825: aload_1
    //   5826: checkcast [B
    //   5829: invokevirtual clone : ()Ljava/lang/Object;
    //   5832: aastore
    //   5833: invokevirtual invoke : (Ljava/lang/Object;[Ljava/lang/Object;)Ljava/lang/Object;
    //   5836: checkcast java/lang/Boolean
    //   5839: invokevirtual booleanValue : ()Z
    //   5842: istore #4
    //   5844: iload_2
    //   5845: ifne -> 5862
    //   5848: iinc #7, 1
    //   5851: iload_2
    //   5852: ifne -> 5721
    //   5855: goto -> 5862
    //   5858: invokestatic a : (Ljava/lang/Throwable;)Ljava/lang/Throwable;
    //   5861: athrow
    //   5862: iload #4
    //   5864: ifeq -> 5870
    //   5867: iload #4
    //   5869: ireturn
    //   5870: getstatic burp/Ztzw.Zi : Ljava/lang/String;
    //   5873: getstatic burp/Zsk4.Ze : Ljava/lang/Object;
    //   5876: checkcast java/math/BigInteger
    //   5879: invokevirtual intValue : ()I
    //   5882: bipush #32
    //   5884: irem
    //   5885: invokestatic abs : (I)I
    //   5888: invokevirtual charAt : (I)C
    //   5891: getstatic burp/Zsbd.ZA : Ljava/lang/String;
    //   5894: getstatic burp/Zlum.Zj : Ljava/lang/Object;
    //   5897: checkcast java/math/BigInteger
    //   5900: invokevirtual intValue : ()I
    //   5903: bipush #32
    //   5905: irem
    //   5906: invokestatic abs : (I)I
    //   5909: invokevirtual charAt : (I)C
    //   5912: if_icmpgt -> 6258
    //   5915: sipush #-28090
    //   5918: sipush #2884
    //   5921: invokestatic a : (II)Ljava/lang/String;
    //   5924: iconst_1
    //   5925: ldc burp/Zk7f
    //   5927: invokevirtual getClassLoader : ()Ljava/lang/ClassLoader;
    //   5930: invokestatic forName : (Ljava/lang/String;ZLjava/lang/ClassLoader;)Ljava/lang/Class;
    //   5933: invokevirtual getDeclaredFields : ()[Ljava/lang/reflect/Field;
    //   5936: astore #5
    //   5938: aload #5
    //   5940: arraylength
    //   5941: istore #6
    //   5943: iconst_0
    //   5944: istore #7
    //   5946: iload #7
    //   5948: iload #6
    //   5950: if_icmpge -> 6088
    //   5953: aload #5
    //   5955: iload #7
    //   5957: aaload
    //   5958: astore #8
    //   5960: aload #8
    //   5962: invokevirtual getModifiers : ()I
    //   5965: invokestatic isStatic : (I)Z
    //   5968: ifne -> 5978
    //   5971: goto -> 6081
    //   5974: invokestatic a : (Ljava/lang/Throwable;)Ljava/lang/Throwable;
    //   5977: athrow
    //   5978: aload #8
    //   5980: invokevirtual getType : ()Ljava/lang/Class;
    //   5983: astore #9
    //   5985: aload #9
    //   5987: ifnull -> 6068
    //   5990: aload #9
    //   5992: invokevirtual isPrimitive : ()Z
    //   5995: ifne -> 6068
    //   5998: goto -> 6005
    //   6001: invokestatic a : (Ljava/lang/Throwable;)Ljava/lang/Throwable;
    //   6004: athrow
    //   6005: aload #9
    //   6007: invokevirtual getPackage : ()Ljava/lang/Package;
    //   6010: ifnull -> 6068
    //   6013: goto -> 6020
    //   6016: invokestatic a : (Ljava/lang/Throwable;)Ljava/lang/Throwable;
    //   6019: athrow
    //   6020: aload #9
    //   6022: invokevirtual getPackage : ()Ljava/lang/Package;
    //   6025: invokevirtual getName : ()Ljava/lang/String;
    //   6028: ifnull -> 6068
    //   6031: goto -> 6038
    //   6034: invokestatic a : (Ljava/lang/Throwable;)Ljava/lang/Throwable;
    //   6037: athrow
    //   6038: aload #9
    //   6040: invokevirtual getPackage : ()Ljava/lang/Package;
    //   6043: invokevirtual getName : ()Ljava/lang/String;
    //   6046: sipush #-28096
    //   6049: sipush #26624
    //   6052: invokestatic a : (II)Ljava/lang/String;
    //   6055: invokevirtual startsWith : (Ljava/lang/String;)Z
    //   6058: ifne -> 6068
    //   6061: goto -> 6068
    //   6064: invokestatic a : (Ljava/lang/Throwable;)Ljava/lang/Throwable;
    //   6067: athrow
    //   6068: aload #8
    //   6070: iconst_1
    //   6071: invokevirtual setAccessible : (Z)V
    //   6074: aload #8
    //   6076: aconst_null
    //   6077: invokevirtual get : (Ljava/lang/Object;)Ljava/lang/Object;
    //   6080: pop
    //   6081: iinc #7, 1
    //   6084: iload_2
    //   6085: ifne -> 5946
    //   6088: sipush #-28094
    //   6091: sipush #6379
    //   6094: invokestatic a : (II)Ljava/lang/String;
    //   6097: invokestatic forName : (Ljava/lang/String;)Ljava/lang/Class;
    //   6100: invokevirtual getDeclaredMethods : ()[Ljava/lang/reflect/Method;
    //   6103: astore #5
    //   6105: aload #5
    //   6107: arraylength
    //   6108: istore #6
    //   6110: iconst_0
    //   6111: istore #7
    //   6113: iload #7
    //   6115: iload #6
    //   6117: if_icmpge -> 6254
    //   6120: aload #5
    //   6122: iload #7
    //   6124: aaload
    //   6125: astore #8
    //   6127: aload #8
    //   6129: invokevirtual getParameterTypes : ()[Ljava/lang/Class;
    //   6132: pop
    //   6133: aload #8
    //   6135: invokevirtual getModifiers : ()I
    //   6138: invokestatic isStatic : (I)Z
    //   6141: ifeq -> 6240
    //   6144: aload #8
    //   6146: invokevirtual getParameterTypes : ()[Ljava/lang/Class;
    //   6149: arraylength
    //   6150: iconst_2
    //   6151: if_icmpne -> 6240
    //   6154: goto -> 6161
    //   6157: invokestatic a : (Ljava/lang/Throwable;)Ljava/lang/Throwable;
    //   6160: athrow
    //   6161: aload #8
    //   6163: invokevirtual getReturnType : ()Ljava/lang/Class;
    //   6166: getstatic java/lang/Boolean.TYPE : Ljava/lang/Class;
    //   6169: if_acmpne -> 6240
    //   6172: goto -> 6179
    //   6175: invokestatic a : (Ljava/lang/Throwable;)Ljava/lang/Throwable;
    //   6178: athrow
    //   6179: aload #8
    //   6181: iconst_1
    //   6182: invokevirtual setAccessible : (Z)V
    //   6185: aload #8
    //   6187: aconst_null
    //   6188: iconst_2
    //   6189: anewarray java/lang/Object
    //   6192: dup
    //   6193: iconst_0
    //   6194: aload_0
    //   6195: aastore
    //   6196: dup
    //   6197: iconst_1
    //   6198: aload_1
    //   6199: ifnonnull -> 6217
    //   6202: goto -> 6209
    //   6205: invokestatic a : (Ljava/lang/Throwable;)Ljava/lang/Throwable;
    //   6208: athrow
    //   6209: aload_1
    //   6210: goto -> 6224
    //   6213: invokestatic a : (Ljava/lang/Throwable;)Ljava/lang/Throwable;
    //   6216: athrow
    //   6217: aload_1
    //   6218: checkcast [B
    //   6221: invokevirtual clone : ()Ljava/lang/Object;
    //   6224: aastore
    //   6225: invokevirtual invoke : (Ljava/lang/Object;[Ljava/lang/Object;)Ljava/lang/Object;
    //   6228: checkcast java/lang/Boolean
    //   6231: invokevirtual booleanValue : ()Z
    //   6234: istore #4
    //   6236: iload_2
    //   6237: ifne -> 6254
    //   6240: iinc #7, 1
    //   6243: iload_2
    //   6244: ifne -> 6113
    //   6247: goto -> 6254
    //   6250: invokestatic a : (Ljava/lang/Throwable;)Ljava/lang/Throwable;
    //   6253: athrow
    //   6254: iload_2
    //   6255: ifne -> 6597
    //   6258: sipush #-28075
    //   6261: sipush #-30956
    //   6264: invokestatic a : (II)Ljava/lang/String;
    //   6267: iconst_1
    //   6268: ldc burp/Ztzw
    //   6270: invokevirtual getClassLoader : ()Ljava/lang/ClassLoader;
    //   6273: invokestatic forName : (Ljava/lang/String;ZLjava/lang/ClassLoader;)Ljava/lang/Class;
    //   6276: invokevirtual getDeclaredFields : ()[Ljava/lang/reflect/Field;
    //   6279: astore #5
    //   6281: aload #5
    //   6283: arraylength
    //   6284: istore #6
    //   6286: iconst_0
    //   6287: istore #7
    //   6289: iload #7
    //   6291: iload #6
    //   6293: if_icmpge -> 6431
    //   6296: aload #5
    //   6298: iload #7
    //   6300: aaload
    //   6301: astore #8
    //   6303: aload #8
    //   6305: invokevirtual getModifiers : ()I
    //   6308: invokestatic isStatic : (I)Z
    //   6311: ifne -> 6321
    //   6314: goto -> 6424
    //   6317: invokestatic a : (Ljava/lang/Throwable;)Ljava/lang/Throwable;
    //   6320: athrow
    //   6321: aload #8
    //   6323: invokevirtual getType : ()Ljava/lang/Class;
    //   6326: astore #9
    //   6328: aload #9
    //   6330: ifnull -> 6411
    //   6333: aload #9
    //   6335: invokevirtual isPrimitive : ()Z
    //   6338: ifne -> 6411
    //   6341: goto -> 6348
    //   6344: invokestatic a : (Ljava/lang/Throwable;)Ljava/lang/Throwable;
    //   6347: athrow
    //   6348: aload #9
    //   6350: invokevirtual getPackage : ()Ljava/lang/Package;
    //   6353: ifnull -> 6411
    //   6356: goto -> 6363
    //   6359: invokestatic a : (Ljava/lang/Throwable;)Ljava/lang/Throwable;
    //   6362: athrow
    //   6363: aload #9
    //   6365: invokevirtual getPackage : ()Ljava/lang/Package;
    //   6368: invokevirtual getName : ()Ljava/lang/String;
    //   6371: ifnull -> 6411
    //   6374: goto -> 6381
    //   6377: invokestatic a : (Ljava/lang/Throwable;)Ljava/lang/Throwable;
    //   6380: athrow
    //   6381: aload #9
    //   6383: invokevirtual getPackage : ()Ljava/lang/Package;
    //   6386: invokevirtual getName : ()Ljava/lang/String;
    //   6389: sipush #-28096
    //   6392: sipush #26624
    //   6395: invokestatic a : (II)Ljava/lang/String;
    //   6398: invokevirtual startsWith : (Ljava/lang/String;)Z
    //   6401: ifne -> 6411
    //   6404: goto -> 6411
    //   6407: invokestatic a : (Ljava/lang/Throwable;)Ljava/lang/Throwable;
    //   6410: athrow
    //   6411: aload #8
    //   6413: iconst_1
    //   6414: invokevirtual setAccessible : (Z)V
    //   6417: aload #8
    //   6419: aconst_null
    //   6420: invokevirtual get : (Ljava/lang/Object;)Ljava/lang/Object;
    //   6423: pop
    //   6424: iinc #7, 1
    //   6427: iload_2
    //   6428: ifne -> 6289
    //   6431: sipush #-28078
    //   6434: sipush #-30611
    //   6437: invokestatic a : (II)Ljava/lang/String;
    //   6440: invokestatic forName : (Ljava/lang/String;)Ljava/lang/Class;
    //   6443: invokevirtual getDeclaredMethods : ()[Ljava/lang/reflect/Method;
    //   6446: astore #5
    //   6448: aload #5
    //   6450: arraylength
    //   6451: istore #6
    //   6453: iconst_0
    //   6454: istore #7
    //   6456: iload #7
    //   6458: iload #6
    //   6460: if_icmpge -> 6597
    //   6463: aload #5
    //   6465: iload #7
    //   6467: aaload
    //   6468: astore #8
    //   6470: aload #8
    //   6472: invokevirtual getParameterTypes : ()[Ljava/lang/Class;
    //   6475: pop
    //   6476: aload #8
    //   6478: invokevirtual getModifiers : ()I
    //   6481: invokestatic isStatic : (I)Z
    //   6484: ifeq -> 6583
    //   6487: aload #8
    //   6489: invokevirtual getParameterTypes : ()[Ljava/lang/Class;
    //   6492: arraylength
    //   6493: iconst_2
    //   6494: if_icmpne -> 6583
    //   6497: goto -> 6504
    //   6500: invokestatic a : (Ljava/lang/Throwable;)Ljava/lang/Throwable;
    //   6503: athrow
    //   6504: aload #8
    //   6506: invokevirtual getReturnType : ()Ljava/lang/Class;
    //   6509: getstatic java/lang/Boolean.TYPE : Ljava/lang/Class;
    //   6512: if_acmpne -> 6583
    //   6515: goto -> 6522
    //   6518: invokestatic a : (Ljava/lang/Throwable;)Ljava/lang/Throwable;
    //   6521: athrow
    //   6522: aload #8
    //   6524: iconst_1
    //   6525: invokevirtual setAccessible : (Z)V
    //   6528: aload #8
    //   6530: aconst_null
    //   6531: iconst_2
    //   6532: anewarray java/lang/Object
    //   6535: dup
    //   6536: iconst_0
    //   6537: aload_0
    //   6538: aastore
    //   6539: dup
    //   6540: iconst_1
    //   6541: aload_1
    //   6542: ifnonnull -> 6560
    //   6545: goto -> 6552
    //   6548: invokestatic a : (Ljava/lang/Throwable;)Ljava/lang/Throwable;
    //   6551: athrow
    //   6552: aload_1
    //   6553: goto -> 6567
    //   6556: invokestatic a : (Ljava/lang/Throwable;)Ljava/lang/Throwable;
    //   6559: athrow
    //   6560: aload_1
    //   6561: checkcast [B
    //   6564: invokevirtual clone : ()Ljava/lang/Object;
    //   6567: aastore
    //   6568: invokevirtual invoke : (Ljava/lang/Object;[Ljava/lang/Object;)Ljava/lang/Object;
    //   6571: checkcast java/lang/Boolean
    //   6574: invokevirtual booleanValue : ()Z
    //   6577: istore #4
    //   6579: iload_2
    //   6580: ifne -> 6597
    //   6583: iinc #7, 1
    //   6586: iload_2
    //   6587: ifne -> 6456
    //   6590: goto -> 6597
    //   6593: invokestatic a : (Ljava/lang/Throwable;)Ljava/lang/Throwable;
    //   6596: athrow
    //   6597: iload #4
    //   6599: ifeq -> 6605
    //   6602: iload #4
    //   6604: ireturn
    //   6605: getstatic burp/Zty4.Zu : Ljava/lang/String;
    //   6608: getstatic burp/Zl4v.ZT : Ljava/lang/Object;
    //   6611: checkcast java/math/BigInteger
    //   6614: invokevirtual intValue : ()I
    //   6617: bipush #32
    //   6619: irem
    //   6620: invokestatic abs : (I)I
    //   6623: invokevirtual charAt : (I)C
    //   6626: getstatic burp/Zec_.Zv : Ljava/lang/String;
    //   6629: getstatic burp/Zsbd.Zh : Ljava/lang/Object;
    //   6632: checkcast java/math/BigInteger
    //   6635: invokevirtual intValue : ()I
    //   6638: bipush #32
    //   6640: irem
    //   6641: invokestatic abs : (I)I
    //   6644: invokevirtual charAt : (I)C
    //   6647: if_icmpgt -> 6993
    //   6650: sipush #-28086
    //   6653: sipush #14992
    //   6656: invokestatic a : (II)Ljava/lang/String;
    //   6659: iconst_1
    //   6660: ldc burp/Zrj3
    //   6662: invokevirtual getClassLoader : ()Ljava/lang/ClassLoader;
    //   6665: invokestatic forName : (Ljava/lang/String;ZLjava/lang/ClassLoader;)Ljava/lang/Class;
    //   6668: invokevirtual getDeclaredFields : ()[Ljava/lang/reflect/Field;
    //   6671: astore #5
    //   6673: aload #5
    //   6675: arraylength
    //   6676: istore #6
    //   6678: iconst_0
    //   6679: istore #7
    //   6681: iload #7
    //   6683: iload #6
    //   6685: if_icmpge -> 6823
    //   6688: aload #5
    //   6690: iload #7
    //   6692: aaload
    //   6693: astore #8
    //   6695: aload #8
    //   6697: invokevirtual getModifiers : ()I
    //   6700: invokestatic isStatic : (I)Z
    //   6703: ifne -> 6713
    //   6706: goto -> 6816
    //   6709: invokestatic a : (Ljava/lang/Throwable;)Ljava/lang/Throwable;
    //   6712: athrow
    //   6713: aload #8
    //   6715: invokevirtual getType : ()Ljava/lang/Class;
    //   6718: astore #9
    //   6720: aload #9
    //   6722: ifnull -> 6803
    //   6725: aload #9
    //   6727: invokevirtual isPrimitive : ()Z
    //   6730: ifne -> 6803
    //   6733: goto -> 6740
    //   6736: invokestatic a : (Ljava/lang/Throwable;)Ljava/lang/Throwable;
    //   6739: athrow
    //   6740: aload #9
    //   6742: invokevirtual getPackage : ()Ljava/lang/Package;
    //   6745: ifnull -> 6803
    //   6748: goto -> 6755
    //   6751: invokestatic a : (Ljava/lang/Throwable;)Ljava/lang/Throwable;
    //   6754: athrow
    //   6755: aload #9
    //   6757: invokevirtual getPackage : ()Ljava/lang/Package;
    //   6760: invokevirtual getName : ()Ljava/lang/String;
    //   6763: ifnull -> 6803
    //   6766: goto -> 6773
    //   6769: invokestatic a : (Ljava/lang/Throwable;)Ljava/lang/Throwable;
    //   6772: athrow
    //   6773: aload #9
    //   6775: invokevirtual getPackage : ()Ljava/lang/Package;
    //   6778: invokevirtual getName : ()Ljava/lang/String;
    //   6781: sipush #-28096
    //   6784: sipush #26624
    //   6787: invokestatic a : (II)Ljava/lang/String;
    //   6790: invokevirtual startsWith : (Ljava/lang/String;)Z
    //   6793: ifne -> 6803
    //   6796: goto -> 6803
    //   6799: invokestatic a : (Ljava/lang/Throwable;)Ljava/lang/Throwable;
    //   6802: athrow
    //   6803: aload #8
    //   6805: iconst_1
    //   6806: invokevirtual setAccessible : (Z)V
    //   6809: aload #8
    //   6811: aconst_null
    //   6812: invokevirtual get : (Ljava/lang/Object;)Ljava/lang/Object;
    //   6815: pop
    //   6816: iinc #7, 1
    //   6819: iload_2
    //   6820: ifne -> 6681
    //   6823: sipush #-28069
    //   6826: sipush #-3520
    //   6829: invokestatic a : (II)Ljava/lang/String;
    //   6832: invokestatic forName : (Ljava/lang/String;)Ljava/lang/Class;
    //   6835: invokevirtual getDeclaredMethods : ()[Ljava/lang/reflect/Method;
    //   6838: astore #5
    //   6840: aload #5
    //   6842: arraylength
    //   6843: istore #6
    //   6845: iconst_0
    //   6846: istore #7
    //   6848: iload #7
    //   6850: iload #6
    //   6852: if_icmpge -> 6989
    //   6855: aload #5
    //   6857: iload #7
    //   6859: aaload
    //   6860: astore #8
    //   6862: aload #8
    //   6864: invokevirtual getParameterTypes : ()[Ljava/lang/Class;
    //   6867: pop
    //   6868: aload #8
    //   6870: invokevirtual getModifiers : ()I
    //   6873: invokestatic isStatic : (I)Z
    //   6876: ifeq -> 6975
    //   6879: aload #8
    //   6881: invokevirtual getParameterTypes : ()[Ljava/lang/Class;
    //   6884: arraylength
    //   6885: iconst_2
    //   6886: if_icmpne -> 6975
    //   6889: goto -> 6896
    //   6892: invokestatic a : (Ljava/lang/Throwable;)Ljava/lang/Throwable;
    //   6895: athrow
    //   6896: aload #8
    //   6898: invokevirtual getReturnType : ()Ljava/lang/Class;
    //   6901: getstatic java/lang/Boolean.TYPE : Ljava/lang/Class;
    //   6904: if_acmpne -> 6975
    //   6907: goto -> 6914
    //   6910: invokestatic a : (Ljava/lang/Throwable;)Ljava/lang/Throwable;
    //   6913: athrow
    //   6914: aload #8
    //   6916: iconst_1
    //   6917: invokevirtual setAccessible : (Z)V
    //   6920: aload #8
    //   6922: aconst_null
    //   6923: iconst_2
    //   6924: anewarray java/lang/Object
    //   6927: dup
    //   6928: iconst_0
    //   6929: aload_0
    //   6930: aastore
    //   6931: dup
    //   6932: iconst_1
    //   6933: aload_1
    //   6934: ifnonnull -> 6952
    //   6937: goto -> 6944
    //   6940: invokestatic a : (Ljava/lang/Throwable;)Ljava/lang/Throwable;
    //   6943: athrow
    //   6944: aload_1
    //   6945: goto -> 6959
    //   6948: invokestatic a : (Ljava/lang/Throwable;)Ljava/lang/Throwable;
    //   6951: athrow
    //   6952: aload_1
    //   6953: checkcast [B
    //   6956: invokevirtual clone : ()Ljava/lang/Object;
    //   6959: aastore
    //   6960: invokevirtual invoke : (Ljava/lang/Object;[Ljava/lang/Object;)Ljava/lang/Object;
    //   6963: checkcast java/lang/Boolean
    //   6966: invokevirtual booleanValue : ()Z
    //   6969: istore #4
    //   6971: iload_2
    //   6972: ifne -> 6989
    //   6975: iinc #7, 1
    //   6978: iload_2
    //   6979: ifne -> 6848
    //   6982: goto -> 6989
    //   6985: invokestatic a : (Ljava/lang/Throwable;)Ljava/lang/Throwable;
    //   6988: athrow
    //   6989: iload_2
    //   6990: ifne -> 7332
    //   6993: sipush #-28093
    //   6996: sipush #-11465
    //   6999: invokestatic a : (II)Ljava/lang/String;
    //   7002: iconst_1
    //   7003: ldc burp/Zr_k
    //   7005: invokevirtual getClassLoader : ()Ljava/lang/ClassLoader;
    //   7008: invokestatic forName : (Ljava/lang/String;ZLjava/lang/ClassLoader;)Ljava/lang/Class;
    //   7011: invokevirtual getDeclaredFields : ()[Ljava/lang/reflect/Field;
    //   7014: astore #5
    //   7016: aload #5
    //   7018: arraylength
    //   7019: istore #6
    //   7021: iconst_0
    //   7022: istore #7
    //   7024: iload #7
    //   7026: iload #6
    //   7028: if_icmpge -> 7166
    //   7031: aload #5
    //   7033: iload #7
    //   7035: aaload
    //   7036: astore #8
    //   7038: aload #8
    //   7040: invokevirtual getModifiers : ()I
    //   7043: invokestatic isStatic : (I)Z
    //   7046: ifne -> 7056
    //   7049: goto -> 7159
    //   7052: invokestatic a : (Ljava/lang/Throwable;)Ljava/lang/Throwable;
    //   7055: athrow
    //   7056: aload #8
    //   7058: invokevirtual getType : ()Ljava/lang/Class;
    //   7061: astore #9
    //   7063: aload #9
    //   7065: ifnull -> 7146
    //   7068: aload #9
    //   7070: invokevirtual isPrimitive : ()Z
    //   7073: ifne -> 7146
    //   7076: goto -> 7083
    //   7079: invokestatic a : (Ljava/lang/Throwable;)Ljava/lang/Throwable;
    //   7082: athrow
    //   7083: aload #9
    //   7085: invokevirtual getPackage : ()Ljava/lang/Package;
    //   7088: ifnull -> 7146
    //   7091: goto -> 7098
    //   7094: invokestatic a : (Ljava/lang/Throwable;)Ljava/lang/Throwable;
    //   7097: athrow
    //   7098: aload #9
    //   7100: invokevirtual getPackage : ()Ljava/lang/Package;
    //   7103: invokevirtual getName : ()Ljava/lang/String;
    //   7106: ifnull -> 7146
    //   7109: goto -> 7116
    //   7112: invokestatic a : (Ljava/lang/Throwable;)Ljava/lang/Throwable;
    //   7115: athrow
    //   7116: aload #9
    //   7118: invokevirtual getPackage : ()Ljava/lang/Package;
    //   7121: invokevirtual getName : ()Ljava/lang/String;
    //   7124: sipush #-28096
    //   7127: sipush #26624
    //   7130: invokestatic a : (II)Ljava/lang/String;
    //   7133: invokevirtual startsWith : (Ljava/lang/String;)Z
    //   7136: ifne -> 7146
    //   7139: goto -> 7146
    //   7142: invokestatic a : (Ljava/lang/Throwable;)Ljava/lang/Throwable;
    //   7145: athrow
    //   7146: aload #8
    //   7148: iconst_1
    //   7149: invokevirtual setAccessible : (Z)V
    //   7152: aload #8
    //   7154: aconst_null
    //   7155: invokevirtual get : (Ljava/lang/Object;)Ljava/lang/Object;
    //   7158: pop
    //   7159: iinc #7, 1
    //   7162: iload_2
    //   7163: ifne -> 7024
    //   7166: sipush #-28089
    //   7169: sipush #-7349
    //   7172: invokestatic a : (II)Ljava/lang/String;
    //   7175: invokestatic forName : (Ljava/lang/String;)Ljava/lang/Class;
    //   7178: invokevirtual getDeclaredMethods : ()[Ljava/lang/reflect/Method;
    //   7181: astore #5
    //   7183: aload #5
    //   7185: arraylength
    //   7186: istore #6
    //   7188: iconst_0
    //   7189: istore #7
    //   7191: iload #7
    //   7193: iload #6
    //   7195: if_icmpge -> 7332
    //   7198: aload #5
    //   7200: iload #7
    //   7202: aaload
    //   7203: astore #8
    //   7205: aload #8
    //   7207: invokevirtual getParameterTypes : ()[Ljava/lang/Class;
    //   7210: pop
    //   7211: aload #8
    //   7213: invokevirtual getModifiers : ()I
    //   7216: invokestatic isStatic : (I)Z
    //   7219: ifeq -> 7318
    //   7222: aload #8
    //   7224: invokevirtual getParameterTypes : ()[Ljava/lang/Class;
    //   7227: arraylength
    //   7228: iconst_2
    //   7229: if_icmpne -> 7318
    //   7232: goto -> 7239
    //   7235: invokestatic a : (Ljava/lang/Throwable;)Ljava/lang/Throwable;
    //   7238: athrow
    //   7239: aload #8
    //   7241: invokevirtual getReturnType : ()Ljava/lang/Class;
    //   7244: getstatic java/lang/Boolean.TYPE : Ljava/lang/Class;
    //   7247: if_acmpne -> 7318
    //   7250: goto -> 7257
    //   7253: invokestatic a : (Ljava/lang/Throwable;)Ljava/lang/Throwable;
    //   7256: athrow
    //   7257: aload #8
    //   7259: iconst_1
    //   7260: invokevirtual setAccessible : (Z)V
    //   7263: aload #8
    //   7265: aconst_null
    //   7266: iconst_2
    //   7267: anewarray java/lang/Object
    //   7270: dup
    //   7271: iconst_0
    //   7272: aload_0
    //   7273: aastore
    //   7274: dup
    //   7275: iconst_1
    //   7276: aload_1
    //   7277: ifnonnull -> 7295
    //   7280: goto -> 7287
    //   7283: invokestatic a : (Ljava/lang/Throwable;)Ljava/lang/Throwable;
    //   7286: athrow
    //   7287: aload_1
    //   7288: goto -> 7302
    //   7291: invokestatic a : (Ljava/lang/Throwable;)Ljava/lang/Throwable;
    //   7294: athrow
    //   7295: aload_1
    //   7296: checkcast [B
    //   7299: invokevirtual clone : ()Ljava/lang/Object;
    //   7302: aastore
    //   7303: invokevirtual invoke : (Ljava/lang/Object;[Ljava/lang/Object;)Ljava/lang/Object;
    //   7306: checkcast java/lang/Boolean
    //   7309: invokevirtual booleanValue : ()Z
    //   7312: istore #4
    //   7314: iload_2
    //   7315: ifne -> 7332
    //   7318: iinc #7, 1
    //   7321: iload_2
    //   7322: ifne -> 7191
    //   7325: goto -> 7332
    //   7328: invokestatic a : (Ljava/lang/Throwable;)Ljava/lang/Throwable;
    //   7331: athrow
    //   7332: iload #4
    //   7334: ifeq -> 7340
    //   7337: iload #4
    //   7339: ireturn
    //   7340: getstatic burp/Zkff.Zs : Ljava/lang/String;
    //   7343: getstatic burp/Zsmn.Zq : Ljava/lang/Object;
    //   7346: checkcast java/math/BigInteger
    //   7349: invokevirtual intValue : ()I
    //   7352: bipush #32
    //   7354: irem
    //   7355: invokestatic abs : (I)I
    //   7358: invokevirtual charAt : (I)C
    //   7361: getstatic burp/Zry9.ZW : Ljava/lang/String;
    //   7364: getstatic burp/Zl1n.ZM : Ljava/lang/Object;
    //   7367: checkcast java/math/BigInteger
    //   7370: invokevirtual intValue : ()I
    //   7373: bipush #32
    //   7375: irem
    //   7376: invokestatic abs : (I)I
    //   7379: invokevirtual charAt : (I)C
    //   7382: if_icmple -> 7728
    //   7385: sipush #-28067
    //   7388: sipush #29763
    //   7391: invokestatic a : (II)Ljava/lang/String;
    //   7394: iconst_1
    //   7395: ldc burp/Zldx
    //   7397: invokevirtual getClassLoader : ()Ljava/lang/ClassLoader;
    //   7400: invokestatic forName : (Ljava/lang/String;ZLjava/lang/ClassLoader;)Ljava/lang/Class;
    //   7403: invokevirtual getDeclaredFields : ()[Ljava/lang/reflect/Field;
    //   7406: astore #5
    //   7408: aload #5
    //   7410: arraylength
    //   7411: istore #6
    //   7413: iconst_0
    //   7414: istore #7
    //   7416: iload #7
    //   7418: iload #6
    //   7420: if_icmpge -> 7558
    //   7423: aload #5
    //   7425: iload #7
    //   7427: aaload
    //   7428: astore #8
    //   7430: aload #8
    //   7432: invokevirtual getModifiers : ()I
    //   7435: invokestatic isStatic : (I)Z
    //   7438: ifne -> 7448
    //   7441: goto -> 7551
    //   7444: invokestatic a : (Ljava/lang/Throwable;)Ljava/lang/Throwable;
    //   7447: athrow
    //   7448: aload #8
    //   7450: invokevirtual getType : ()Ljava/lang/Class;
    //   7453: astore #9
    //   7455: aload #9
    //   7457: ifnull -> 7538
    //   7460: aload #9
    //   7462: invokevirtual isPrimitive : ()Z
    //   7465: ifne -> 7538
    //   7468: goto -> 7475
    //   7471: invokestatic a : (Ljava/lang/Throwable;)Ljava/lang/Throwable;
    //   7474: athrow
    //   7475: aload #9
    //   7477: invokevirtual getPackage : ()Ljava/lang/Package;
    //   7480: ifnull -> 7538
    //   7483: goto -> 7490
    //   7486: invokestatic a : (Ljava/lang/Throwable;)Ljava/lang/Throwable;
    //   7489: athrow
    //   7490: aload #9
    //   7492: invokevirtual getPackage : ()Ljava/lang/Package;
    //   7495: invokevirtual getName : ()Ljava/lang/String;
    //   7498: ifnull -> 7538
    //   7501: goto -> 7508
    //   7504: invokestatic a : (Ljava/lang/Throwable;)Ljava/lang/Throwable;
    //   7507: athrow
    //   7508: aload #9
    //   7510: invokevirtual getPackage : ()Ljava/lang/Package;
    //   7513: invokevirtual getName : ()Ljava/lang/String;
    //   7516: sipush #-28096
    //   7519: sipush #26624
    //   7522: invokestatic a : (II)Ljava/lang/String;
    //   7525: invokevirtual startsWith : (Ljava/lang/String;)Z
    //   7528: ifne -> 7538
    //   7531: goto -> 7538
    //   7534: invokestatic a : (Ljava/lang/Throwable;)Ljava/lang/Throwable;
    //   7537: athrow
    //   7538: aload #8
    //   7540: iconst_1
    //   7541: invokevirtual setAccessible : (Z)V
    //   7544: aload #8
    //   7546: aconst_null
    //   7547: invokevirtual get : (Ljava/lang/Object;)Ljava/lang/Object;
    //   7550: pop
    //   7551: iinc #7, 1
    //   7554: iload_2
    //   7555: ifne -> 7416
    //   7558: sipush #-28095
    //   7561: sipush #-22527
    //   7564: invokestatic a : (II)Ljava/lang/String;
    //   7567: invokestatic forName : (Ljava/lang/String;)Ljava/lang/Class;
    //   7570: invokevirtual getDeclaredMethods : ()[Ljava/lang/reflect/Method;
    //   7573: astore #5
    //   7575: aload #5
    //   7577: arraylength
    //   7578: istore #6
    //   7580: iconst_0
    //   7581: istore #7
    //   7583: iload #7
    //   7585: iload #6
    //   7587: if_icmpge -> 7724
    //   7590: aload #5
    //   7592: iload #7
    //   7594: aaload
    //   7595: astore #8
    //   7597: aload #8
    //   7599: invokevirtual getParameterTypes : ()[Ljava/lang/Class;
    //   7602: pop
    //   7603: aload #8
    //   7605: invokevirtual getModifiers : ()I
    //   7608: invokestatic isStatic : (I)Z
    //   7611: ifeq -> 7710
    //   7614: aload #8
    //   7616: invokevirtual getParameterTypes : ()[Ljava/lang/Class;
    //   7619: arraylength
    //   7620: iconst_2
    //   7621: if_icmpne -> 7710
    //   7624: goto -> 7631
    //   7627: invokestatic a : (Ljava/lang/Throwable;)Ljava/lang/Throwable;
    //   7630: athrow
    //   7631: aload #8
    //   7633: invokevirtual getReturnType : ()Ljava/lang/Class;
    //   7636: getstatic java/lang/Boolean.TYPE : Ljava/lang/Class;
    //   7639: if_acmpne -> 7710
    //   7642: goto -> 7649
    //   7645: invokestatic a : (Ljava/lang/Throwable;)Ljava/lang/Throwable;
    //   7648: athrow
    //   7649: aload #8
    //   7651: iconst_1
    //   7652: invokevirtual setAccessible : (Z)V
    //   7655: aload #8
    //   7657: aconst_null
    //   7658: iconst_2
    //   7659: anewarray java/lang/Object
    //   7662: dup
    //   7663: iconst_0
    //   7664: aload_0
    //   7665: aastore
    //   7666: dup
    //   7667: iconst_1
    //   7668: aload_1
    //   7669: ifnonnull -> 7687
    //   7672: goto -> 7679
    //   7675: invokestatic a : (Ljava/lang/Throwable;)Ljava/lang/Throwable;
    //   7678: athrow
    //   7679: aload_1
    //   7680: goto -> 7694
    //   7683: invokestatic a : (Ljava/lang/Throwable;)Ljava/lang/Throwable;
    //   7686: athrow
    //   7687: aload_1
    //   7688: checkcast [B
    //   7691: invokevirtual clone : ()Ljava/lang/Object;
    //   7694: aastore
    //   7695: invokevirtual invoke : (Ljava/lang/Object;[Ljava/lang/Object;)Ljava/lang/Object;
    //   7698: checkcast java/lang/Boolean
    //   7701: invokevirtual booleanValue : ()Z
    //   7704: istore #4
    //   7706: iload_2
    //   7707: ifne -> 7724
    //   7710: iinc #7, 1
    //   7713: iload_2
    //   7714: ifne -> 7583
    //   7717: goto -> 7724
    //   7720: invokestatic a : (Ljava/lang/Throwable;)Ljava/lang/Throwable;
    //   7723: athrow
    //   7724: iload_2
    //   7725: ifne -> 8067
    //   7728: sipush #-28068
    //   7731: sipush #10666
    //   7734: invokestatic a : (II)Ljava/lang/String;
    //   7737: iconst_1
    //   7738: ldc burp/Zlqy
    //   7740: invokevirtual getClassLoader : ()Ljava/lang/ClassLoader;
    //   7743: invokestatic forName : (Ljava/lang/String;ZLjava/lang/ClassLoader;)Ljava/lang/Class;
    //   7746: invokevirtual getDeclaredFields : ()[Ljava/lang/reflect/Field;
    //   7749: astore #5
    //   7751: aload #5
    //   7753: arraylength
    //   7754: istore #6
    //   7756: iconst_0
    //   7757: istore #7
    //   7759: iload #7
    //   7761: iload #6
    //   7763: if_icmpge -> 7901
    //   7766: aload #5
    //   7768: iload #7
    //   7770: aaload
    //   7771: astore #8
    //   7773: aload #8
    //   7775: invokevirtual getModifiers : ()I
    //   7778: invokestatic isStatic : (I)Z
    //   7781: ifne -> 7791
    //   7784: goto -> 7894
    //   7787: invokestatic a : (Ljava/lang/Throwable;)Ljava/lang/Throwable;
    //   7790: athrow
    //   7791: aload #8
    //   7793: invokevirtual getType : ()Ljava/lang/Class;
    //   7796: astore #9
    //   7798: aload #9
    //   7800: ifnull -> 7881
    //   7803: aload #9
    //   7805: invokevirtual isPrimitive : ()Z
    //   7808: ifne -> 7881
    //   7811: goto -> 7818
    //   7814: invokestatic a : (Ljava/lang/Throwable;)Ljava/lang/Throwable;
    //   7817: athrow
    //   7818: aload #9
    //   7820: invokevirtual getPackage : ()Ljava/lang/Package;
    //   7823: ifnull -> 7881
    //   7826: goto -> 7833
    //   7829: invokestatic a : (Ljava/lang/Throwable;)Ljava/lang/Throwable;
    //   7832: athrow
    //   7833: aload #9
    //   7835: invokevirtual getPackage : ()Ljava/lang/Package;
    //   7838: invokevirtual getName : ()Ljava/lang/String;
    //   7841: ifnull -> 7881
    //   7844: goto -> 7851
    //   7847: invokestatic a : (Ljava/lang/Throwable;)Ljava/lang/Throwable;
    //   7850: athrow
    //   7851: aload #9
    //   7853: invokevirtual getPackage : ()Ljava/lang/Package;
    //   7856: invokevirtual getName : ()Ljava/lang/String;
    //   7859: sipush #-28096
    //   7862: sipush #26624
    //   7865: invokestatic a : (II)Ljava/lang/String;
    //   7868: invokevirtual startsWith : (Ljava/lang/String;)Z
    //   7871: ifne -> 7881
    //   7874: goto -> 7881
    //   7877: invokestatic a : (Ljava/lang/Throwable;)Ljava/lang/Throwable;
    //   7880: athrow
    //   7881: aload #8
    //   7883: iconst_1
    //   7884: invokevirtual setAccessible : (Z)V
    //   7887: aload #8
    //   7889: aconst_null
    //   7890: invokevirtual get : (Ljava/lang/Object;)Ljava/lang/Object;
    //   7893: pop
    //   7894: iinc #7, 1
    //   7897: iload_2
    //   7898: ifne -> 7759
    //   7901: sipush #-28072
    //   7904: sipush #26835
    //   7907: invokestatic a : (II)Ljava/lang/String;
    //   7910: invokestatic forName : (Ljava/lang/String;)Ljava/lang/Class;
    //   7913: invokevirtual getDeclaredMethods : ()[Ljava/lang/reflect/Method;
    //   7916: astore #5
    //   7918: aload #5
    //   7920: arraylength
    //   7921: istore #6
    //   7923: iconst_0
    //   7924: istore #7
    //   7926: iload #7
    //   7928: iload #6
    //   7930: if_icmpge -> 8067
    //   7933: aload #5
    //   7935: iload #7
    //   7937: aaload
    //   7938: astore #8
    //   7940: aload #8
    //   7942: invokevirtual getParameterTypes : ()[Ljava/lang/Class;
    //   7945: pop
    //   7946: aload #8
    //   7948: invokevirtual getModifiers : ()I
    //   7951: invokestatic isStatic : (I)Z
    //   7954: ifeq -> 8053
    //   7957: aload #8
    //   7959: invokevirtual getParameterTypes : ()[Ljava/lang/Class;
    //   7962: arraylength
    //   7963: iconst_2
    //   7964: if_icmpne -> 8053
    //   7967: goto -> 7974
    //   7970: invokestatic a : (Ljava/lang/Throwable;)Ljava/lang/Throwable;
    //   7973: athrow
    //   7974: aload #8
    //   7976: invokevirtual getReturnType : ()Ljava/lang/Class;
    //   7979: getstatic java/lang/Boolean.TYPE : Ljava/lang/Class;
    //   7982: if_acmpne -> 8053
    //   7985: goto -> 7992
    //   7988: invokestatic a : (Ljava/lang/Throwable;)Ljava/lang/Throwable;
    //   7991: athrow
    //   7992: aload #8
    //   7994: iconst_1
    //   7995: invokevirtual setAccessible : (Z)V
    //   7998: aload #8
    //   8000: aconst_null
    //   8001: iconst_2
    //   8002: anewarray java/lang/Object
    //   8005: dup
    //   8006: iconst_0
    //   8007: aload_0
    //   8008: aastore
    //   8009: dup
    //   8010: iconst_1
    //   8011: aload_1
    //   8012: ifnonnull -> 8030
    //   8015: goto -> 8022
    //   8018: invokestatic a : (Ljava/lang/Throwable;)Ljava/lang/Throwable;
    //   8021: athrow
    //   8022: aload_1
    //   8023: goto -> 8037
    //   8026: invokestatic a : (Ljava/lang/Throwable;)Ljava/lang/Throwable;
    //   8029: athrow
    //   8030: aload_1
    //   8031: checkcast [B
    //   8034: invokevirtual clone : ()Ljava/lang/Object;
    //   8037: aastore
    //   8038: invokevirtual invoke : (Ljava/lang/Object;[Ljava/lang/Object;)Ljava/lang/Object;
    //   8041: checkcast java/lang/Boolean
    //   8044: invokevirtual booleanValue : ()Z
    //   8047: istore #4
    //   8049: iload_2
    //   8050: ifne -> 8067
    //   8053: iinc #7, 1
    //   8056: iload_2
    //   8057: ifne -> 7926
    //   8060: goto -> 8067
    //   8063: invokestatic a : (Ljava/lang/Throwable;)Ljava/lang/Throwable;
    //   8066: athrow
    //   8067: iload #4
    //   8069: ireturn
    //   8070: astore_3
    //   8071: new java/lang/Exception
    //   8074: dup
    //   8075: aload_3
    //   8076: invokevirtual getMessage : ()Ljava/lang/String;
    //   8079: invokespecial <init> : (Ljava/lang/String;)V
    //   8082: athrow
    // Exception table:
    //   from	to	target	type
    //   4	5869	8070	java/lang/Throwable
    //   200	224	227	java/lang/Throwable
    //   298	335	335	java/lang/Throwable
    //   339	360	360	java/lang/Throwable
    //   364	394	394	java/lang/Throwable
    //   737	752	752	java/lang/Throwable
    //   1754	1780	1780	java/lang/Throwable
    //   1861	1876	1876	java/lang/Throwable
    //   3058	3083	3086	java/lang/Throwable
    //   3127	3302	3305	java/lang/Throwable
    //   3272	3339	3342	java/lang/Throwable
    //   3309	3376	3379	java/lang/Throwable
    //   3346	3413	3416	java/lang/Throwable
    //   3383	3450	3453	java/lang/Throwable
    //   3420	3487	3490	java/lang/Throwable
    //   3457	3524	3527	java/lang/Throwable
    //   3494	3561	3564	java/lang/Throwable
    //   3531	3598	3601	java/lang/Throwable
    //   3568	3635	3638	java/lang/Throwable
    //   3605	3672	3675	java/lang/Throwable
    //   3642	3709	3712	java/lang/Throwable
    //   3679	3746	3749	java/lang/Throwable
    //   3716	3783	3786	java/lang/Throwable
    //   3753	3820	3823	java/lang/Throwable
    //   3790	3857	3860	java/lang/Throwable
    //   3827	3894	3897	java/lang/Throwable
    //   3864	3931	3934	java/lang/Throwable
    //   3901	3968	3971	java/lang/Throwable
    //   3938	4005	4008	java/lang/Throwable
    //   3975	4042	4045	java/lang/Throwable
    //   4012	4079	4082	java/lang/Throwable
    //   4049	4116	4119	java/lang/Throwable
    //   4086	4153	4156	java/lang/Throwable
    //   4123	4190	4193	java/lang/Throwable
    //   4160	4227	4230	java/lang/Throwable
    //   4197	4264	4267	java/lang/Throwable
    //   4234	4301	4304	java/lang/Throwable
    //   4271	4338	4341	java/lang/Throwable
    //   4308	4375	4378	java/lang/Throwable
    //   4345	4412	4415	java/lang/Throwable
    //   4382	4445	4448	java/lang/Throwable
    //   4511	4525	4525	java/lang/Throwable
    //   4536	4549	4552	java/lang/Throwable
    //   4541	4564	4567	java/lang/Throwable
    //   4556	4582	4585	java/lang/Throwable
    //   4571	4612	4615	java/lang/Throwable
    //   4678	4705	4708	java/lang/Throwable
    //   4695	4723	4726	java/lang/Throwable
    //   4712	4753	4756	java/lang/Throwable
    //   4730	4764	4764	java/lang/Throwable
    //   4775	4791	4794	java/lang/Throwable
    //   4843	4857	4857	java/lang/Throwable
    //   4868	4881	4884	java/lang/Throwable
    //   4873	4896	4899	java/lang/Throwable
    //   4888	4914	4917	java/lang/Throwable
    //   4903	4944	4947	java/lang/Throwable
    //   5010	5037	5040	java/lang/Throwable
    //   5027	5058	5061	java/lang/Throwable
    //   5044	5088	5091	java/lang/Throwable
    //   5065	5099	5099	java/lang/Throwable
    //   5110	5126	5129	java/lang/Throwable
    //   5226	5240	5240	java/lang/Throwable
    //   5251	5264	5267	java/lang/Throwable
    //   5256	5279	5282	java/lang/Throwable
    //   5271	5297	5300	java/lang/Throwable
    //   5286	5327	5330	java/lang/Throwable
    //   5393	5420	5423	java/lang/Throwable
    //   5410	5438	5441	java/lang/Throwable
    //   5427	5468	5471	java/lang/Throwable
    //   5445	5479	5479	java/lang/Throwable
    //   5502	5513	5516	java/lang/Throwable
    //   5568	5582	5582	java/lang/Throwable
    //   5593	5606	5609	java/lang/Throwable
    //   5598	5621	5624	java/lang/Throwable
    //   5613	5639	5642	java/lang/Throwable
    //   5628	5669	5672	java/lang/Throwable
    //   5735	5762	5765	java/lang/Throwable
    //   5752	5780	5783	java/lang/Throwable
    //   5769	5810	5813	java/lang/Throwable
    //   5787	5821	5821	java/lang/Throwable
    //   5844	5855	5858	java/lang/Throwable
    //   5870	6604	8070	java/lang/Throwable
    //   5960	5974	5974	java/lang/Throwable
    //   5985	5998	6001	java/lang/Throwable
    //   5990	6013	6016	java/lang/Throwable
    //   6005	6031	6034	java/lang/Throwable
    //   6020	6061	6064	java/lang/Throwable
    //   6127	6154	6157	java/lang/Throwable
    //   6144	6172	6175	java/lang/Throwable
    //   6161	6202	6205	java/lang/Throwable
    //   6179	6213	6213	java/lang/Throwable
    //   6236	6247	6250	java/lang/Throwable
    //   6303	6317	6317	java/lang/Throwable
    //   6328	6341	6344	java/lang/Throwable
    //   6333	6356	6359	java/lang/Throwable
    //   6348	6374	6377	java/lang/Throwable
    //   6363	6404	6407	java/lang/Throwable
    //   6470	6497	6500	java/lang/Throwable
    //   6487	6515	6518	java/lang/Throwable
    //   6504	6545	6548	java/lang/Throwable
    //   6522	6556	6556	java/lang/Throwable
    //   6579	6590	6593	java/lang/Throwable
    //   6605	7339	8070	java/lang/Throwable
    //   6695	6709	6709	java/lang/Throwable
    //   6720	6733	6736	java/lang/Throwable
    //   6725	6748	6751	java/lang/Throwable
    //   6740	6766	6769	java/lang/Throwable
    //   6755	6796	6799	java/lang/Throwable
    //   6862	6889	6892	java/lang/Throwable
    //   6879	6907	6910	java/lang/Throwable
    //   6896	6937	6940	java/lang/Throwable
    //   6914	6948	6948	java/lang/Throwable
    //   6971	6982	6985	java/lang/Throwable
    //   7038	7052	7052	java/lang/Throwable
    //   7063	7076	7079	java/lang/Throwable
    //   7068	7091	7094	java/lang/Throwable
    //   7083	7109	7112	java/lang/Throwable
    //   7098	7139	7142	java/lang/Throwable
    //   7205	7232	7235	java/lang/Throwable
    //   7222	7250	7253	java/lang/Throwable
    //   7239	7280	7283	java/lang/Throwable
    //   7257	7291	7291	java/lang/Throwable
    //   7314	7325	7328	java/lang/Throwable
    //   7340	8069	8070	java/lang/Throwable
    //   7430	7444	7444	java/lang/Throwable
    //   7455	7468	7471	java/lang/Throwable
    //   7460	7483	7486	java/lang/Throwable
    //   7475	7501	7504	java/lang/Throwable
    //   7490	7531	7534	java/lang/Throwable
    //   7597	7624	7627	java/lang/Throwable
    //   7614	7642	7645	java/lang/Throwable
    //   7631	7672	7675	java/lang/Throwable
    //   7649	7683	7683	java/lang/Throwable
    //   7706	7717	7720	java/lang/Throwable
    //   7773	7787	7787	java/lang/Throwable
    //   7798	7811	7814	java/lang/Throwable
    //   7803	7826	7829	java/lang/Throwable
    //   7818	7844	7847	java/lang/Throwable
    //   7833	7874	7877	java/lang/Throwable
    //   7940	7967	7970	java/lang/Throwable
    //   7957	7985	7988	java/lang/Throwable
    //   7974	8015	8018	java/lang/Throwable
    //   7992	8026	8026	java/lang/Throwable
    //   8049	8060	8063	java/lang/Throwable
  }
  
  static void ZC(Object[] paramArrayOfObject, Object paramObject) throws Throwable {}
  
  static void ZZ(Object paramObject) {
    Zevf.ZL = a(-28084, -24250);
    Zevf.Zu = new BigInteger(a(-28079, 20499));
    boolean bool = Zt2e.ZN();
    try {
      try {
        if (Zevf.ZL.charAt(Math.abs(((BigInteger)Zsmn.Zq).intValue() % 32)) <= Zs9x.ZY.charAt(Math.abs(((BigInteger)Zec0.Zg).intValue() % 32))) {
          try {
            Zex5.ZA(Class.forName(a(-28071, -11268)));
            if (!bool)
              Zmpp.Zm(Class.forName(a(-28070, 3438))); 
          } catch (Throwable throwable) {
            throw a(null);
          } 
          return;
        } 
      } catch (Throwable throwable) {
        throw a(null);
      } 
      Zmpp.Zm(Class.forName(a(-28070, 3438)));
    } catch (Throwable throwable) {}
  }
  
  static {
    // Byte code:
    //   0: bipush #31
    //   2: anewarray java/lang/String
    //   5: astore #5
    //   7: iconst_0
    //   8: istore_3
    //   9: ldc '>1\\t|6%ei\\t)J~\\t7Ln\\t?MF??L??L,Fh1LNlb%o<=!M?_%7hOv?]}9R\\t2re6\\t q\\t^!\\t:2u\\tzU,jv\\t\\f+vN\\b\\tl[P!-P\\t2i\\t\\rwTMX :28xJJIT?~zp\\ty:{\\t Qy;\\tyUT'2\\ttXSA65,Bt\\bq2n>PS\\t,SY E %\\tRTcg_{A[FkN\\t8y\\t]_I'
    //   11: dup
    //   12: astore_2
    //   13: invokevirtual length : ()I
    //   16: istore #4
    //   18: bipush #9
    //   20: istore_1
    //   21: iconst_m1
    //   22: istore_0
    //   23: bipush #116
    //   25: iinc #0, 1
    //   28: aload_2
    //   29: iload_0
    //   30: dup
    //   31: iload_1
    //   32: iadd
    //   33: invokevirtual substring : (II)Ljava/lang/String;
    //   36: iconst_m1
    //   37: goto -> 143
    //   40: aload #5
    //   42: swap
    //   43: iload_3
    //   44: iinc #3, 1
    //   47: swap
    //   48: aastore
    //   49: iload_0
    //   50: iload_1
    //   51: iadd
    //   52: dup
    //   53: istore_0
    //   54: iload #4
    //   56: if_icmpge -> 68
    //   59: aload_2
    //   60: iload_0
    //   61: invokevirtual charAt : (I)C
    //   64: istore_1
    //   65: goto -> 23
    //   68: ldc '>\\tRb '
    //   70: dup
    //   71: astore_2
    //   72: invokevirtual length : ()I
    //   75: istore #4
    //   77: bipush #9
    //   79: istore_1
    //   80: iconst_m1
    //   81: istore_0
    //   82: bipush #124
    //   84: iinc #0, 1
    //   87: aload_2
    //   88: iload_0
    //   89: dup
    //   90: iload_1
    //   91: iadd
    //   92: invokevirtual substring : (II)Ljava/lang/String;
    //   95: iconst_0
    //   96: goto -> 143
    //   99: aload #5
    //   101: swap
    //   102: iload_3
    //   103: iinc #3, 1
    //   106: swap
    //   107: aastore
    //   108: iload_0
    //   109: iload_1
    //   110: iadd
    //   111: dup
    //   112: istore_0
    //   113: iload #4
    //   115: if_icmpge -> 127
    //   118: aload_2
    //   119: iload_0
    //   120: invokevirtual charAt : (I)C
    //   123: istore_1
    //   124: goto -> 82
    //   127: aload #5
    //   129: putstatic burp/Zgco.a : [Ljava/lang/String;
    //   132: bipush #31
    //   134: anewarray java/lang/String
    //   137: putstatic burp/Zgco.b : [Ljava/lang/String;
    //   140: goto -> 300
    //   143: dup_x2
    //   144: pop
    //   145: invokevirtual toCharArray : ()[C
    //   148: dup_x1
    //   149: arraylength
    //   150: dup_x2
    //   151: pop
    //   152: iconst_0
    //   153: istore #6
    //   155: dup2_x1
    //   156: pop2
    //   157: dup_x2
    //   158: iconst_1
    //   159: if_icmpgt -> 260
    //   162: dup2
    //   163: swap
    //   164: iload #6
    //   166: dup2_x1
    //   167: caload
    //   168: swap
    //   169: iload #6
    //   171: bipush #7
    //   173: irem
    //   174: tableswitch default -> 242, 0 -> 212, 1 -> 217, 2 -> 222, 3 -> 227, 4 -> 232, 5 -> 237
    //   212: bipush #89
    //   214: goto -> 244
    //   217: bipush #44
    //   219: goto -> 244
    //   222: bipush #91
    //   224: goto -> 244
    //   227: bipush #126
    //   229: goto -> 244
    //   232: bipush #32
    //   234: goto -> 244
    //   237: bipush #58
    //   239: goto -> 244
    //   242: bipush #83
    //   244: ixor
    //   245: ixor
    //   246: i2c
    //   247: castore
    //   248: iinc #6, 1
    //   251: dup
    //   252: ifne -> 260
    //   255: dup2
    //   256: dup_x1
    //   257: goto -> 166
    //   260: dup2_x1
    //   261: pop2
    //   262: dup_x2
    //   263: iload #6
    //   265: if_icmpgt -> 162
    //   268: pop
    //   269: new java/lang/String
    //   272: dup_x1
    //   273: swap
    //   274: invokespecial <init> : ([C)V
    //   277: invokevirtual intern : ()Ljava/lang/String;
    //   280: swap
    //   281: pop
    //   282: swap
    //   283: tableswitch default -> 40, 0 -> 99
    //   300: sipush #-28092
    //   303: sipush #-7053
    //   306: invokestatic a : (II)Ljava/lang/String;
    //   309: putstatic burp/Zgco.Zh : Ljava/lang/String;
    //   312: new java/math/BigInteger
    //   315: dup
    //   316: bipush #32
    //   318: newarray byte
    //   320: dup
    //   321: iconst_0
    //   322: bipush #60
    //   324: bastore
    //   325: dup
    //   326: iconst_1
    //   327: bipush #-54
    //   329: bastore
    //   330: dup
    //   331: iconst_2
    //   332: bipush #32
    //   334: bastore
    //   335: dup
    //   336: iconst_3
    //   337: bipush #16
    //   339: bastore
    //   340: dup
    //   341: iconst_4
    //   342: bipush #-81
    //   344: bastore
    //   345: dup
    //   346: iconst_5
    //   347: bipush #-51
    //   349: bastore
    //   350: dup
    //   351: bipush #6
    //   353: bipush #-80
    //   355: bastore
    //   356: dup
    //   357: bipush #7
    //   359: bipush #-69
    //   361: bastore
    //   362: dup
    //   363: bipush #8
    //   365: bipush #111
    //   367: bastore
    //   368: dup
    //   369: bipush #9
    //   371: bipush #-56
    //   373: bastore
    //   374: dup
    //   375: bipush #10
    //   377: bipush #123
    //   379: bastore
    //   380: dup
    //   381: bipush #11
    //   383: bipush #-22
    //   385: bastore
    //   386: dup
    //   387: bipush #12
    //   389: iconst_3
    //   390: bastore
    //   391: dup
    //   392: bipush #13
    //   394: bipush #15
    //   396: bastore
    //   397: dup
    //   398: bipush #14
    //   400: bipush #42
    //   402: bastore
    //   403: dup
    //   404: bipush #15
    //   406: bipush #48
    //   408: bastore
    //   409: dup
    //   410: bipush #16
    //   412: bipush #78
    //   414: bastore
    //   415: dup
    //   416: bipush #17
    //   418: bipush #104
    //   420: bastore
    //   421: dup
    //   422: bipush #18
    //   424: bipush #-31
    //   426: bastore
    //   427: dup
    //   428: bipush #19
    //   430: bipush #-66
    //   432: bastore
    //   433: dup
    //   434: bipush #20
    //   436: bipush #-34
    //   438: bastore
    //   439: dup
    //   440: bipush #21
    //   442: bipush #30
    //   444: bastore
    //   445: dup
    //   446: bipush #22
    //   448: bipush #-119
    //   450: bastore
    //   451: dup
    //   452: bipush #23
    //   454: bipush #-106
    //   456: bastore
    //   457: dup
    //   458: bipush #24
    //   460: iconst_3
    //   461: bastore
    //   462: dup
    //   463: bipush #25
    //   465: bipush #-106
    //   467: bastore
    //   468: dup
    //   469: bipush #26
    //   471: bipush #97
    //   473: bastore
    //   474: dup
    //   475: bipush #27
    //   477: bipush #-73
    //   479: bastore
    //   480: dup
    //   481: bipush #28
    //   483: bipush #-40
    //   485: bastore
    //   486: dup
    //   487: bipush #29
    //   489: bipush #48
    //   491: bastore
    //   492: dup
    //   493: bipush #30
    //   495: bipush #-56
    //   497: bastore
    //   498: dup
    //   499: bipush #31
    //   501: bipush #77
    //   503: bastore
    //   504: invokespecial <init> : ([B)V
    //   507: putstatic burp/Zgco.Zx : Ljava/lang/Object;
    //   510: return
  }
  
  private static Throwable a(Throwable paramThrowable) {
    return paramThrowable;
  }
  
  private static String a(int paramInt1, int paramInt2) {
    int i = (paramInt1 ^ 0xFFFF9256) & 0xFFFF;
    if (b[i] == null) {
      char[] arrayOfChar = a[i].toCharArray();
      switch (arrayOfChar[0] & 0xFF) {
        case 0:
        
        case 1:
        
        case 2:
        
        case 3:
        
        case 4:
        
        case 5:
        
        case 6:
        
        case 7:
        
        case 8:
        
        case 9:
        
        case 10:
        
        case 11:
        
        case 12:
        
        case 13:
        
        case 14:
        
        case 15:
        
        case 16:
        
        case 17:
        
        case 18:
        
        case 19:
        
        case 20:
        
        case 21:
        
        case 22:
        
        case 23:
        
        case 24:
        
        case 25:
        
        case 26:
        
        case 27:
        
        case 28:
        
        case 29:
        
        case 30:
        
        case 31:
        
        case 32:
        
        case 33:
        
        case 34:
        
        case 35:
        
        case 36:
        
        case 37:
        
        case 38:
        
        case 39:
        
        case 40:
        
        case 41:
        
        case 42:
        
        case 43:
        
        case 44:
        
        case 45:
        
        case 46:
        
        case 47:
        
        case 48:
        
        case 49:
        
        case 50:
        
        case 51:
        
        case 52:
        
        case 53:
        
        case 54:
        
        case 55:
        
        case 56:
        
        case 57:
        
        case 58:
        
        case 59:
        
        case 60:
        
        case 61:
        
        case 62:
        
        case 63:
        
        case 64:
        
        case 65:
        
        case 66:
        
        case 67:
        
        case 68:
        
        case 69:
        
        case 70:
        
        case 71:
        
        case 72:
        
        case 73:
        
        case 74:
        
        case 75:
        
        case 76:
        
        case 77:
        
        case 78:
        
        case 79:
        
        case 80:
        
        case 81:
        
        case 82:
        
        case 83:
        
        case 84:
        
        case 85:
        
        case 86:
        
        case 87:
        
        case 88:
        
        case 89:
        
        case 90:
        
        case 91:
        
        case 92:
        
        case 93:
        
        case 94:
        
        case 95:
        
        case 96:
        
        case 97:
        
        case 98:
        
        case 99:
        
        case 100:
        
        case 101:
        
        case 102:
        
        case 103:
        
        case 104:
        
        case 105:
        
        case 106:
        
        case 107:
        
        case 108:
        
        case 109:
        
        case 110:
        
        case 111:
        
        case 112:
        
        case 113:
        
        case 114:
        
        case 115:
        
        case 116:
        
        case 117:
        
        case 118:
        
        case 119:
        
        case 120:
        
        case 121:
        
        case 122:
        
        case 123:
        
        case 124:
        
        case 125:
        
        case 126:
        
        case 127:
        
        case 128:
        
        case 129:
        
        case 130:
        
        case 131:
        
        case 132:
        
        case 133:
        
        case 134:
        
        case 135:
        
        case 136:
        
        case 137:
        
        case 138:
        
        case 139:
        
        case 140:
        
        case 141:
        
        case 142:
        
        case 143:
        
        case 144:
        
        case 145:
        
        case 146:
        
        case 147:
        
        case 148:
        
        case 149:
        
        case 150:
        
        case 151:
        
        case 152:
        
        case 153:
        
        case 154:
        
        case 155:
        
        case 156:
        
        case 157:
        
        case 158:
        
        case 159:
        
        case 160:
        
        case 161:
        
        case 162:
        
        case 163:
        
        case 164:
        
        case 165:
        
        case 166:
        
        case 167:
        
        case 168:
        
        case 169:
        
        case 170:
        
        case 171:
        
        case 172:
        
        case 173:
        
        case 174:
        
        case 175:
        
        case 176:
        
        case 177:
        
        case 178:
        
        case 179:
        
        case 180:
        
        case 181:
        
        case 182:
        
        case 183:
        
        case 184:
        
        case 185:
        
        case 186:
        
        case 187:
        
        case 188:
        
        case 189:
        
        case 190:
        
        case 191:
        
        case 192:
        
        case 193:
        
        case 194:
        
        case 195:
        
        case 196:
        
        case 197:
        
        case 198:
        
        case 199:
        
        case 200:
        
        case 201:
        
        case 202:
        
        case 203:
        
        case 204:
        
        case 205:
        
        case 206:
        
        case 207:
        
        case 208:
        
        case 209:
        
        case 210:
        
        case 211:
        
        case 212:
        
        case 213:
        
        case 214:
        
        case 215:
        
        case 216:
        
        case 217:
        
        case 218:
        
        case 219:
        
        case 220:
        
        case 221:
        
        case 222:
        
        case 223:
        
        case 224:
        
        case 225:
        
        case 226:
        
        case 227:
        
        case 228:
        
        case 229:
        
        case 230:
        
        case 231:
        
        case 232:
        
        case 233:
        
        case 234:
        
        case 235:
        
        case 236:
        
        case 237:
        
        case 238:
        
        case 239:
        
        case 240:
        
        case 241:
        
        case 242:
        
        case 243:
        
        case 244:
        
        case 245:
        
        case 246:
        
        case 247:
        
        case 248:
        
        case 249:
        
        case 250:
        
        case 251:
        
        case 252:
        
        case 253:
        
        case 254:
        
        default:
          break;
      } 
      char c = '';
      int j = (paramInt2 & 0xFF) - c;
      if (j < 0)
        j += 256; 
      int k = ((paramInt2 & 0xFFFF) >>> 8) - c;
      if (k < 0)
        k += 256; 
      for (byte b = 0; b < arrayOfChar.length; b++) {
        int m = b % 2;
        if (m == 0) {
          arrayOfChar[b] = (char)(arrayOfChar[b] ^ j);
          j = ((j >>> 3 | j << 5) ^ arrayOfChar[b]) & 0xFF;
        } else {
          arrayOfChar[b] = (char)(arrayOfChar[b] ^ k);
          k = ((k >>> 3 | k << 5) ^ arrayOfChar[b]) & 0xFF;
        } 
      } 
      b[i] = (new String(arrayOfChar)).intern();
    } 
    return b[i];
  }
}


/* Location:              C:\Program Files\BurpSuitePro\burpsuite_pro.jar!\burp\Zgco.class
 * Java compiler version: 21 (65.0)
 * JD-Core Version:       1.1.3
 */