package burp;

import java.math.BigInteger;

class Zgd7 extends ClassLoader {
  static String Zs;
  
  static Object ZZ;
  
  private static final String[] a;
  
  private static final String[] b;
  
  static void Zh(Object paramObject) {
    Zeyt.ZS = a(25271, 14882);
    Zeyt.ZR = new BigInteger(a(25268, 18547));
    boolean bool = Zt2e.ZN();
    try {
      try {
        if (Zeyt.ZS.charAt(Math.abs(((BigInteger)Zeyt.ZR).intValue() % 32)) > Zeyt.ZS.charAt(Math.abs(((BigInteger)Zeyt.ZR).intValue() % 32))) {
          try {
            Zgil.ZM(Class.forName(a(25266, 10114)));
            if (!bool)
              Zmhx.Zd(Class.forName(a(25269, 23929))); 
          } catch (Throwable throwable) {
            throw a(null);
          } 
          return;
        } 
      } catch (Throwable throwable) {
        throw a(null);
      } 
      Zmhx.Zd(Class.forName(a(25269, 23929)));
    } catch (Throwable throwable) {}
  }
  
  static boolean Zo(Object[] paramArrayOfObject, Object paramObject) throws Throwable {
    // Byte code:
    //   0: invokestatic ZK : ()Z
    //   3: istore_2
    //   4: getstatic burp/Zmiy.Zi : Ljava/lang/Object;
    //   7: checkcast java/math/BigInteger
    //   10: invokevirtual toByteArray : ()[B
    //   13: astore_3
    //   14: bipush #64
    //   16: newarray byte
    //   18: dup
    //   19: iconst_0
    //   20: bipush #-128
    //   22: bastore
    //   23: dup
    //   24: iconst_1
    //   25: iconst_0
    //   26: bastore
    //   27: dup
    //   28: iconst_2
    //   29: iconst_0
    //   30: bastore
    //   31: dup
    //   32: iconst_3
    //   33: iconst_0
    //   34: bastore
    //   35: dup
    //   36: iconst_4
    //   37: iconst_0
    //   38: bastore
    //   39: dup
    //   40: iconst_5
    //   41: iconst_0
    //   42: bastore
    //   43: dup
    //   44: bipush #6
    //   46: iconst_0
    //   47: bastore
    //   48: dup
    //   49: bipush #7
    //   51: iconst_0
    //   52: bastore
    //   53: dup
    //   54: bipush #8
    //   56: iconst_0
    //   57: bastore
    //   58: dup
    //   59: bipush #9
    //   61: iconst_0
    //   62: bastore
    //   63: dup
    //   64: bipush #10
    //   66: iconst_0
    //   67: bastore
    //   68: dup
    //   69: bipush #11
    //   71: iconst_0
    //   72: bastore
    //   73: dup
    //   74: bipush #12
    //   76: iconst_0
    //   77: bastore
    //   78: dup
    //   79: bipush #13
    //   81: iconst_0
    //   82: bastore
    //   83: dup
    //   84: bipush #14
    //   86: iconst_0
    //   87: bastore
    //   88: dup
    //   89: bipush #15
    //   91: iconst_0
    //   92: bastore
    //   93: dup
    //   94: bipush #16
    //   96: iconst_0
    //   97: bastore
    //   98: dup
    //   99: bipush #17
    //   101: iconst_0
    //   102: bastore
    //   103: dup
    //   104: bipush #18
    //   106: iconst_0
    //   107: bastore
    //   108: dup
    //   109: bipush #19
    //   111: iconst_0
    //   112: bastore
    //   113: dup
    //   114: bipush #20
    //   116: iconst_0
    //   117: bastore
    //   118: dup
    //   119: bipush #21
    //   121: iconst_0
    //   122: bastore
    //   123: dup
    //   124: bipush #22
    //   126: iconst_0
    //   127: bastore
    //   128: dup
    //   129: bipush #23
    //   131: iconst_0
    //   132: bastore
    //   133: dup
    //   134: bipush #24
    //   136: iconst_0
    //   137: bastore
    //   138: dup
    //   139: bipush #25
    //   141: iconst_0
    //   142: bastore
    //   143: dup
    //   144: bipush #26
    //   146: iconst_0
    //   147: bastore
    //   148: dup
    //   149: bipush #27
    //   151: iconst_0
    //   152: bastore
    //   153: dup
    //   154: bipush #28
    //   156: iconst_0
    //   157: bastore
    //   158: dup
    //   159: bipush #29
    //   161: iconst_0
    //   162: bastore
    //   163: dup
    //   164: bipush #30
    //   166: iconst_0
    //   167: bastore
    //   168: dup
    //   169: bipush #31
    //   171: iconst_0
    //   172: bastore
    //   173: dup
    //   174: bipush #32
    //   176: iconst_0
    //   177: bastore
    //   178: dup
    //   179: bipush #33
    //   181: iconst_0
    //   182: bastore
    //   183: dup
    //   184: bipush #34
    //   186: iconst_0
    //   187: bastore
    //   188: dup
    //   189: bipush #35
    //   191: iconst_0
    //   192: bastore
    //   193: dup
    //   194: bipush #36
    //   196: iconst_0
    //   197: bastore
    //   198: dup
    //   199: bipush #37
    //   201: iconst_0
    //   202: bastore
    //   203: dup
    //   204: bipush #38
    //   206: iconst_0
    //   207: bastore
    //   208: dup
    //   209: bipush #39
    //   211: iconst_0
    //   212: bastore
    //   213: dup
    //   214: bipush #40
    //   216: iconst_0
    //   217: bastore
    //   218: dup
    //   219: bipush #41
    //   221: iconst_0
    //   222: bastore
    //   223: dup
    //   224: bipush #42
    //   226: iconst_0
    //   227: bastore
    //   228: dup
    //   229: bipush #43
    //   231: iconst_0
    //   232: bastore
    //   233: dup
    //   234: bipush #44
    //   236: iconst_0
    //   237: bastore
    //   238: dup
    //   239: bipush #45
    //   241: iconst_0
    //   242: bastore
    //   243: dup
    //   244: bipush #46
    //   246: iconst_0
    //   247: bastore
    //   248: dup
    //   249: bipush #47
    //   251: iconst_0
    //   252: bastore
    //   253: dup
    //   254: bipush #48
    //   256: iconst_0
    //   257: bastore
    //   258: dup
    //   259: bipush #49
    //   261: iconst_0
    //   262: bastore
    //   263: dup
    //   264: bipush #50
    //   266: iconst_0
    //   267: bastore
    //   268: dup
    //   269: bipush #51
    //   271: iconst_0
    //   272: bastore
    //   273: dup
    //   274: bipush #52
    //   276: iconst_0
    //   277: bastore
    //   278: dup
    //   279: bipush #53
    //   281: iconst_0
    //   282: bastore
    //   283: dup
    //   284: bipush #54
    //   286: iconst_0
    //   287: bastore
    //   288: dup
    //   289: bipush #55
    //   291: iconst_0
    //   292: bastore
    //   293: dup
    //   294: bipush #56
    //   296: iconst_0
    //   297: bastore
    //   298: dup
    //   299: bipush #57
    //   301: iconst_0
    //   302: bastore
    //   303: dup
    //   304: bipush #58
    //   306: iconst_0
    //   307: bastore
    //   308: dup
    //   309: bipush #59
    //   311: iconst_0
    //   312: bastore
    //   313: dup
    //   314: bipush #60
    //   316: iconst_0
    //   317: bastore
    //   318: dup
    //   319: bipush #61
    //   321: iconst_0
    //   322: bastore
    //   323: dup
    //   324: bipush #62
    //   326: iconst_0
    //   327: bastore
    //   328: dup
    //   329: bipush #63
    //   331: iconst_0
    //   332: bastore
    //   333: astore #5
    //   335: bipush #64
    //   337: newarray int
    //   339: dup
    //   340: iconst_0
    //   341: ldc 1116352408
    //   343: iastore
    //   344: dup
    //   345: iconst_1
    //   346: ldc 1899447441
    //   348: iastore
    //   349: dup
    //   350: iconst_2
    //   351: ldc -1245643825
    //   353: iastore
    //   354: dup
    //   355: iconst_3
    //   356: ldc -373957723
    //   358: iastore
    //   359: dup
    //   360: iconst_4
    //   361: ldc 961987163
    //   363: iastore
    //   364: dup
    //   365: iconst_5
    //   366: ldc 1508970993
    //   368: iastore
    //   369: dup
    //   370: bipush #6
    //   372: ldc -1841331548
    //   374: iastore
    //   375: dup
    //   376: bipush #7
    //   378: ldc -1424204075
    //   380: iastore
    //   381: dup
    //   382: bipush #8
    //   384: ldc -670586216
    //   386: iastore
    //   387: dup
    //   388: bipush #9
    //   390: ldc 310598401
    //   392: iastore
    //   393: dup
    //   394: bipush #10
    //   396: ldc 607225278
    //   398: iastore
    //   399: dup
    //   400: bipush #11
    //   402: ldc 1426881987
    //   404: iastore
    //   405: dup
    //   406: bipush #12
    //   408: ldc 1925078388
    //   410: iastore
    //   411: dup
    //   412: bipush #13
    //   414: ldc -2132889090
    //   416: iastore
    //   417: dup
    //   418: bipush #14
    //   420: ldc -1680079193
    //   422: iastore
    //   423: dup
    //   424: bipush #15
    //   426: ldc -1046744716
    //   428: iastore
    //   429: dup
    //   430: bipush #16
    //   432: ldc -459576895
    //   434: iastore
    //   435: dup
    //   436: bipush #17
    //   438: ldc -272742522
    //   440: iastore
    //   441: dup
    //   442: bipush #18
    //   444: ldc 264347078
    //   446: iastore
    //   447: dup
    //   448: bipush #19
    //   450: ldc 604807628
    //   452: iastore
    //   453: dup
    //   454: bipush #20
    //   456: ldc 770255983
    //   458: iastore
    //   459: dup
    //   460: bipush #21
    //   462: ldc 1249150122
    //   464: iastore
    //   465: dup
    //   466: bipush #22
    //   468: ldc 1555081692
    //   470: iastore
    //   471: dup
    //   472: bipush #23
    //   474: ldc 1996064986
    //   476: iastore
    //   477: dup
    //   478: bipush #24
    //   480: ldc -1740746414
    //   482: iastore
    //   483: dup
    //   484: bipush #25
    //   486: ldc -1473132947
    //   488: iastore
    //   489: dup
    //   490: bipush #26
    //   492: ldc -1341970488
    //   494: iastore
    //   495: dup
    //   496: bipush #27
    //   498: ldc -1084653625
    //   500: iastore
    //   501: dup
    //   502: bipush #28
    //   504: ldc -958395405
    //   506: iastore
    //   507: dup
    //   508: bipush #29
    //   510: ldc -710438585
    //   512: iastore
    //   513: dup
    //   514: bipush #30
    //   516: ldc 113926993
    //   518: iastore
    //   519: dup
    //   520: bipush #31
    //   522: ldc 338241895
    //   524: iastore
    //   525: dup
    //   526: bipush #32
    //   528: ldc 666307205
    //   530: iastore
    //   531: dup
    //   532: bipush #33
    //   534: ldc 773529912
    //   536: iastore
    //   537: dup
    //   538: bipush #34
    //   540: ldc 1294757372
    //   542: iastore
    //   543: dup
    //   544: bipush #35
    //   546: ldc 1396182291
    //   548: iastore
    //   549: dup
    //   550: bipush #36
    //   552: ldc 1695183700
    //   554: iastore
    //   555: dup
    //   556: bipush #37
    //   558: ldc 1986661051
    //   560: iastore
    //   561: dup
    //   562: bipush #38
    //   564: ldc -2117940946
    //   566: iastore
    //   567: dup
    //   568: bipush #39
    //   570: ldc -1838011259
    //   572: iastore
    //   573: dup
    //   574: bipush #40
    //   576: ldc -1564481375
    //   578: iastore
    //   579: dup
    //   580: bipush #41
    //   582: ldc -1474664885
    //   584: iastore
    //   585: dup
    //   586: bipush #42
    //   588: ldc -1035236496
    //   590: iastore
    //   591: dup
    //   592: bipush #43
    //   594: ldc -949202525
    //   596: iastore
    //   597: dup
    //   598: bipush #44
    //   600: ldc -778901479
    //   602: iastore
    //   603: dup
    //   604: bipush #45
    //   606: ldc -694614492
    //   608: iastore
    //   609: dup
    //   610: bipush #46
    //   612: ldc -200395387
    //   614: iastore
    //   615: dup
    //   616: bipush #47
    //   618: ldc 275423344
    //   620: iastore
    //   621: dup
    //   622: bipush #48
    //   624: ldc 430227734
    //   626: iastore
    //   627: dup
    //   628: bipush #49
    //   630: ldc 506948616
    //   632: iastore
    //   633: dup
    //   634: bipush #50
    //   636: ldc 659060556
    //   638: iastore
    //   639: dup
    //   640: bipush #51
    //   642: ldc 883997877
    //   644: iastore
    //   645: dup
    //   646: bipush #52
    //   648: ldc 958139571
    //   650: iastore
    //   651: dup
    //   652: bipush #53
    //   654: ldc 1322822218
    //   656: iastore
    //   657: dup
    //   658: bipush #54
    //   660: ldc 1537002063
    //   662: iastore
    //   663: dup
    //   664: bipush #55
    //   666: ldc 1747873779
    //   668: iastore
    //   669: dup
    //   670: bipush #56
    //   672: ldc 1955562222
    //   674: iastore
    //   675: dup
    //   676: bipush #57
    //   678: ldc 2024104815
    //   680: iastore
    //   681: dup
    //   682: bipush #58
    //   684: ldc -2067236844
    //   686: iastore
    //   687: dup
    //   688: bipush #59
    //   690: ldc -1933114872
    //   692: iastore
    //   693: dup
    //   694: bipush #60
    //   696: ldc -1866530822
    //   698: iastore
    //   699: dup
    //   700: bipush #61
    //   702: ldc -1538233109
    //   704: iastore
    //   705: dup
    //   706: bipush #62
    //   708: ldc -1090935817
    //   710: iastore
    //   711: dup
    //   712: bipush #63
    //   714: ldc -965641998
    //   716: iastore
    //   717: astore #6
    //   719: iconst_2
    //   720: newarray int
    //   722: dup
    //   723: iconst_0
    //   724: iconst_0
    //   725: iastore
    //   726: dup
    //   727: iconst_1
    //   728: iconst_0
    //   729: iastore
    //   730: astore #7
    //   732: bipush #8
    //   734: newarray int
    //   736: dup
    //   737: iconst_0
    //   738: ldc 1779033703
    //   740: iastore
    //   741: dup
    //   742: iconst_1
    //   743: ldc -1150833019
    //   745: iastore
    //   746: dup
    //   747: iconst_2
    //   748: ldc 1013904242
    //   750: iastore
    //   751: dup
    //   752: iconst_3
    //   753: ldc -1521486534
    //   755: iastore
    //   756: dup
    //   757: iconst_4
    //   758: ldc 1359893119
    //   760: iastore
    //   761: dup
    //   762: iconst_5
    //   763: ldc -1694144372
    //   765: iastore
    //   766: dup
    //   767: bipush #6
    //   769: ldc 528734635
    //   771: iastore
    //   772: dup
    //   773: bipush #7
    //   775: ldc 1541459225
    //   777: iastore
    //   778: astore #8
    //   780: bipush #64
    //   782: newarray byte
    //   784: astore #9
    //   786: bipush #64
    //   788: newarray byte
    //   790: astore #10
    //   792: aload_3
    //   793: arraylength
    //   794: istore #11
    //   796: aload #7
    //   798: iconst_0
    //   799: iaload
    //   800: bipush #63
    //   802: iand
    //   803: istore #12
    //   805: aload #7
    //   807: iconst_0
    //   808: dup2
    //   809: iaload
    //   810: iload #11
    //   812: iadd
    //   813: iastore
    //   814: aload #7
    //   816: iconst_0
    //   817: dup2
    //   818: iaload
    //   819: iconst_m1
    //   820: iand
    //   821: iastore
    //   822: aload #7
    //   824: iconst_0
    //   825: iaload
    //   826: iload #11
    //   828: if_icmpge -> 846
    //   831: aload #7
    //   833: iconst_1
    //   834: dup2
    //   835: iaload
    //   836: iconst_1
    //   837: iadd
    //   838: iastore
    //   839: goto -> 846
    //   842: invokestatic a : (Ljava/lang/Throwable;)Ljava/lang/Throwable;
    //   845: athrow
    //   846: iconst_0
    //   847: istore #13
    //   849: iload #11
    //   851: bipush #64
    //   853: if_icmplt -> 1462
    //   856: iconst_0
    //   857: istore #14
    //   859: iload #14
    //   861: bipush #64
    //   863: if_icmpge -> 885
    //   866: aload #10
    //   868: iload #14
    //   870: aload_3
    //   871: iload #13
    //   873: iload #14
    //   875: iadd
    //   876: baload
    //   877: bastore
    //   878: iinc #14, 1
    //   881: iload_2
    //   882: ifeq -> 859
    //   885: bipush #64
    //   887: newarray int
    //   889: astore #14
    //   891: bipush #8
    //   893: newarray int
    //   895: astore #15
    //   897: iconst_0
    //   898: istore #16
    //   900: iload #16
    //   902: bipush #8
    //   904: if_icmpge -> 924
    //   907: aload #15
    //   909: iload #16
    //   911: aload #8
    //   913: iload #16
    //   915: iaload
    //   916: iastore
    //   917: iinc #16, 1
    //   920: iload_2
    //   921: ifeq -> 900
    //   924: iconst_0
    //   925: istore #16
    //   927: iload #16
    //   929: bipush #64
    //   931: if_icmpge -> 1422
    //   934: iload #16
    //   936: bipush #16
    //   938: if_icmpge -> 1019
    //   941: aload #14
    //   943: iload #16
    //   945: aload #10
    //   947: iconst_4
    //   948: iload #16
    //   950: imul
    //   951: baload
    //   952: sipush #255
    //   955: iand
    //   956: bipush #24
    //   958: ishl
    //   959: aload #10
    //   961: iconst_4
    //   962: iload #16
    //   964: imul
    //   965: iconst_1
    //   966: iadd
    //   967: baload
    //   968: sipush #255
    //   971: iand
    //   972: bipush #16
    //   974: ishl
    //   975: ior
    //   976: aload #10
    //   978: iconst_4
    //   979: iload #16
    //   981: imul
    //   982: iconst_2
    //   983: iadd
    //   984: baload
    //   985: sipush #255
    //   988: iand
    //   989: bipush #8
    //   991: ishl
    //   992: ior
    //   993: aload #10
    //   995: iconst_4
    //   996: iload #16
    //   998: imul
    //   999: iconst_3
    //   1000: iadd
    //   1001: baload
    //   1002: sipush #255
    //   1005: iand
    //   1006: ior
    //   1007: iastore
    //   1008: iload_2
    //   1009: ifeq -> 1162
    //   1012: goto -> 1019
    //   1015: invokestatic a : (Ljava/lang/Throwable;)Ljava/lang/Throwable;
    //   1018: athrow
    //   1019: aload #14
    //   1021: iload #16
    //   1023: aload #14
    //   1025: iload #16
    //   1027: iconst_2
    //   1028: isub
    //   1029: iaload
    //   1030: bipush #17
    //   1032: iushr
    //   1033: aload #14
    //   1035: iload #16
    //   1037: iconst_2
    //   1038: isub
    //   1039: iaload
    //   1040: bipush #15
    //   1042: ishl
    //   1043: ior
    //   1044: aload #14
    //   1046: iload #16
    //   1048: iconst_2
    //   1049: isub
    //   1050: iaload
    //   1051: bipush #19
    //   1053: iushr
    //   1054: aload #14
    //   1056: iload #16
    //   1058: iconst_2
    //   1059: isub
    //   1060: iaload
    //   1061: bipush #13
    //   1063: ishl
    //   1064: ior
    //   1065: ixor
    //   1066: aload #14
    //   1068: iload #16
    //   1070: iconst_2
    //   1071: isub
    //   1072: iaload
    //   1073: bipush #10
    //   1075: iushr
    //   1076: ixor
    //   1077: aload #14
    //   1079: iload #16
    //   1081: bipush #7
    //   1083: isub
    //   1084: iaload
    //   1085: iadd
    //   1086: aload #14
    //   1088: iload #16
    //   1090: bipush #15
    //   1092: isub
    //   1093: iaload
    //   1094: bipush #7
    //   1096: iushr
    //   1097: aload #14
    //   1099: iload #16
    //   1101: bipush #15
    //   1103: isub
    //   1104: iaload
    //   1105: bipush #25
    //   1107: ishl
    //   1108: ior
    //   1109: aload #14
    //   1111: iload #16
    //   1113: bipush #15
    //   1115: isub
    //   1116: iaload
    //   1117: bipush #18
    //   1119: iushr
    //   1120: aload #14
    //   1122: iload #16
    //   1124: bipush #15
    //   1126: isub
    //   1127: iaload
    //   1128: bipush #14
    //   1130: ishl
    //   1131: ior
    //   1132: ixor
    //   1133: aload #14
    //   1135: iload #16
    //   1137: bipush #15
    //   1139: isub
    //   1140: iaload
    //   1141: iconst_3
    //   1142: iushr
    //   1143: ixor
    //   1144: iadd
    //   1145: aload #14
    //   1147: iload #16
    //   1149: bipush #16
    //   1151: isub
    //   1152: iaload
    //   1153: iadd
    //   1154: iastore
    //   1155: goto -> 1162
    //   1158: invokestatic a : (Ljava/lang/Throwable;)Ljava/lang/Throwable;
    //   1161: athrow
    //   1162: aload #15
    //   1164: bipush #7
    //   1166: iaload
    //   1167: aload #15
    //   1169: iconst_4
    //   1170: iaload
    //   1171: bipush #6
    //   1173: iushr
    //   1174: aload #15
    //   1176: iconst_4
    //   1177: iaload
    //   1178: bipush #26
    //   1180: ishl
    //   1181: ior
    //   1182: aload #15
    //   1184: iconst_4
    //   1185: iaload
    //   1186: bipush #11
    //   1188: iushr
    //   1189: aload #15
    //   1191: iconst_4
    //   1192: iaload
    //   1193: bipush #21
    //   1195: ishl
    //   1196: ior
    //   1197: ixor
    //   1198: aload #15
    //   1200: iconst_4
    //   1201: iaload
    //   1202: bipush #25
    //   1204: iushr
    //   1205: aload #15
    //   1207: iconst_4
    //   1208: iaload
    //   1209: bipush #7
    //   1211: ishl
    //   1212: ior
    //   1213: ixor
    //   1214: iadd
    //   1215: aload #15
    //   1217: bipush #6
    //   1219: iaload
    //   1220: aload #15
    //   1222: iconst_4
    //   1223: iaload
    //   1224: aload #15
    //   1226: iconst_5
    //   1227: iaload
    //   1228: aload #15
    //   1230: bipush #6
    //   1232: iaload
    //   1233: ixor
    //   1234: iand
    //   1235: ixor
    //   1236: iadd
    //   1237: aload #6
    //   1239: iload #16
    //   1241: iaload
    //   1242: iadd
    //   1243: aload #14
    //   1245: iload #16
    //   1247: iaload
    //   1248: iadd
    //   1249: istore #17
    //   1251: aload #15
    //   1253: iconst_0
    //   1254: iaload
    //   1255: iconst_2
    //   1256: iushr
    //   1257: aload #15
    //   1259: iconst_0
    //   1260: iaload
    //   1261: bipush #30
    //   1263: ishl
    //   1264: ior
    //   1265: aload #15
    //   1267: iconst_0
    //   1268: iaload
    //   1269: bipush #13
    //   1271: iushr
    //   1272: aload #15
    //   1274: iconst_0
    //   1275: iaload
    //   1276: bipush #19
    //   1278: ishl
    //   1279: ior
    //   1280: ixor
    //   1281: aload #15
    //   1283: iconst_0
    //   1284: iaload
    //   1285: bipush #22
    //   1287: iushr
    //   1288: aload #15
    //   1290: iconst_0
    //   1291: iaload
    //   1292: bipush #10
    //   1294: ishl
    //   1295: ior
    //   1296: ixor
    //   1297: aload #15
    //   1299: iconst_0
    //   1300: iaload
    //   1301: aload #15
    //   1303: iconst_1
    //   1304: iaload
    //   1305: iand
    //   1306: aload #15
    //   1308: iconst_2
    //   1309: iaload
    //   1310: aload #15
    //   1312: iconst_0
    //   1313: iaload
    //   1314: aload #15
    //   1316: iconst_1
    //   1317: iaload
    //   1318: ior
    //   1319: iand
    //   1320: ior
    //   1321: iadd
    //   1322: istore #18
    //   1324: aload #15
    //   1326: iconst_3
    //   1327: dup2
    //   1328: iaload
    //   1329: iload #17
    //   1331: iadd
    //   1332: iastore
    //   1333: aload #15
    //   1335: bipush #7
    //   1337: iload #17
    //   1339: iload #18
    //   1341: iadd
    //   1342: iastore
    //   1343: aload #15
    //   1345: bipush #7
    //   1347: iaload
    //   1348: istore #17
    //   1350: aload #15
    //   1352: bipush #7
    //   1354: aload #15
    //   1356: bipush #6
    //   1358: iaload
    //   1359: iastore
    //   1360: aload #15
    //   1362: bipush #6
    //   1364: aload #15
    //   1366: iconst_5
    //   1367: iaload
    //   1368: iastore
    //   1369: aload #15
    //   1371: iconst_5
    //   1372: aload #15
    //   1374: iconst_4
    //   1375: iaload
    //   1376: iastore
    //   1377: aload #15
    //   1379: iconst_4
    //   1380: aload #15
    //   1382: iconst_3
    //   1383: iaload
    //   1384: iastore
    //   1385: aload #15
    //   1387: iconst_3
    //   1388: aload #15
    //   1390: iconst_2
    //   1391: iaload
    //   1392: iastore
    //   1393: aload #15
    //   1395: iconst_2
    //   1396: aload #15
    //   1398: iconst_1
    //   1399: iaload
    //   1400: iastore
    //   1401: aload #15
    //   1403: iconst_1
    //   1404: aload #15
    //   1406: iconst_0
    //   1407: iaload
    //   1408: iastore
    //   1409: aload #15
    //   1411: iconst_0
    //   1412: iload #17
    //   1414: iastore
    //   1415: iinc #16, 1
    //   1418: iload_2
    //   1419: ifeq -> 927
    //   1422: iconst_0
    //   1423: istore #16
    //   1425: iload #16
    //   1427: bipush #8
    //   1429: if_icmpge -> 1452
    //   1432: aload #8
    //   1434: iload #16
    //   1436: dup2
    //   1437: iaload
    //   1438: aload #15
    //   1440: iload #16
    //   1442: iaload
    //   1443: iadd
    //   1444: iastore
    //   1445: iinc #16, 1
    //   1448: iload_2
    //   1449: ifeq -> 1425
    //   1452: iinc #13, 64
    //   1455: iinc #11, -64
    //   1458: iload_2
    //   1459: ifeq -> 849
    //   1462: iload #11
    //   1464: ifle -> 1499
    //   1467: iconst_0
    //   1468: istore #14
    //   1470: iload #14
    //   1472: iload #11
    //   1474: if_icmpge -> 1499
    //   1477: aload #9
    //   1479: iload #12
    //   1481: iload #14
    //   1483: iadd
    //   1484: aload_3
    //   1485: iload #13
    //   1487: iload #14
    //   1489: iadd
    //   1490: baload
    //   1491: bastore
    //   1492: iinc #14, 1
    //   1495: iload_2
    //   1496: ifeq -> 1470
    //   1499: aload #7
    //   1501: iconst_0
    //   1502: iaload
    //   1503: bipush #29
    //   1505: iushr
    //   1506: aload #7
    //   1508: iconst_1
    //   1509: iaload
    //   1510: iconst_3
    //   1511: ishl
    //   1512: ior
    //   1513: istore #14
    //   1515: aload #7
    //   1517: iconst_0
    //   1518: iaload
    //   1519: iconst_3
    //   1520: ishl
    //   1521: istore #15
    //   1523: aload #7
    //   1525: iconst_0
    //   1526: iaload
    //   1527: bipush #63
    //   1529: iand
    //   1530: istore #16
    //   1532: iload #16
    //   1534: bipush #56
    //   1536: if_icmpge -> 1551
    //   1539: bipush #56
    //   1541: iload #16
    //   1543: isub
    //   1544: goto -> 1556
    //   1547: invokestatic a : (Ljava/lang/Throwable;)Ljava/lang/Throwable;
    //   1550: athrow
    //   1551: bipush #120
    //   1553: iload #16
    //   1555: isub
    //   1556: istore #17
    //   1558: aload #7
    //   1560: iconst_0
    //   1561: iaload
    //   1562: bipush #63
    //   1564: iand
    //   1565: istore #12
    //   1567: bipush #64
    //   1569: iload #12
    //   1571: isub
    //   1572: istore #18
    //   1574: aload #7
    //   1576: iconst_0
    //   1577: dup2
    //   1578: iaload
    //   1579: iload #17
    //   1581: iadd
    //   1582: iastore
    //   1583: aload #7
    //   1585: iconst_0
    //   1586: dup2
    //   1587: iaload
    //   1588: iconst_m1
    //   1589: iand
    //   1590: iastore
    //   1591: aload #7
    //   1593: iconst_0
    //   1594: iaload
    //   1595: iload #17
    //   1597: if_icmpge -> 1615
    //   1600: aload #7
    //   1602: iconst_1
    //   1603: dup2
    //   1604: iaload
    //   1605: iconst_1
    //   1606: iadd
    //   1607: iastore
    //   1608: goto -> 1615
    //   1611: invokestatic a : (Ljava/lang/Throwable;)Ljava/lang/Throwable;
    //   1614: athrow
    //   1615: iconst_0
    //   1616: istore #13
    //   1618: iload #12
    //   1620: ifle -> 2251
    //   1623: iload #17
    //   1625: iload #18
    //   1627: if_icmplt -> 2251
    //   1630: goto -> 1637
    //   1633: invokestatic a : (Ljava/lang/Throwable;)Ljava/lang/Throwable;
    //   1636: athrow
    //   1637: iconst_0
    //   1638: istore #19
    //   1640: iload #19
    //   1642: iload #18
    //   1644: if_icmpge -> 1667
    //   1647: aload #9
    //   1649: iload #12
    //   1651: iload #19
    //   1653: iadd
    //   1654: aload #5
    //   1656: iload #19
    //   1658: baload
    //   1659: bastore
    //   1660: iinc #19, 1
    //   1663: iload_2
    //   1664: ifeq -> 1640
    //   1667: bipush #64
    //   1669: newarray int
    //   1671: astore #19
    //   1673: bipush #8
    //   1675: newarray int
    //   1677: astore #20
    //   1679: iconst_0
    //   1680: istore #21
    //   1682: iload #21
    //   1684: bipush #8
    //   1686: if_icmpge -> 1706
    //   1689: aload #20
    //   1691: iload #21
    //   1693: aload #8
    //   1695: iload #21
    //   1697: iaload
    //   1698: iastore
    //   1699: iinc #21, 1
    //   1702: iload_2
    //   1703: ifeq -> 1682
    //   1706: iconst_0
    //   1707: istore #21
    //   1709: iload #21
    //   1711: bipush #64
    //   1713: if_icmpge -> 2204
    //   1716: iload #21
    //   1718: bipush #16
    //   1720: if_icmpge -> 1801
    //   1723: aload #19
    //   1725: iload #21
    //   1727: aload #9
    //   1729: iconst_4
    //   1730: iload #21
    //   1732: imul
    //   1733: baload
    //   1734: sipush #255
    //   1737: iand
    //   1738: bipush #24
    //   1740: ishl
    //   1741: aload #9
    //   1743: iconst_4
    //   1744: iload #21
    //   1746: imul
    //   1747: iconst_1
    //   1748: iadd
    //   1749: baload
    //   1750: sipush #255
    //   1753: iand
    //   1754: bipush #16
    //   1756: ishl
    //   1757: ior
    //   1758: aload #9
    //   1760: iconst_4
    //   1761: iload #21
    //   1763: imul
    //   1764: iconst_2
    //   1765: iadd
    //   1766: baload
    //   1767: sipush #255
    //   1770: iand
    //   1771: bipush #8
    //   1773: ishl
    //   1774: ior
    //   1775: aload #9
    //   1777: iconst_4
    //   1778: iload #21
    //   1780: imul
    //   1781: iconst_3
    //   1782: iadd
    //   1783: baload
    //   1784: sipush #255
    //   1787: iand
    //   1788: ior
    //   1789: iastore
    //   1790: iload_2
    //   1791: ifeq -> 1944
    //   1794: goto -> 1801
    //   1797: invokestatic a : (Ljava/lang/Throwable;)Ljava/lang/Throwable;
    //   1800: athrow
    //   1801: aload #19
    //   1803: iload #21
    //   1805: aload #19
    //   1807: iload #21
    //   1809: iconst_2
    //   1810: isub
    //   1811: iaload
    //   1812: bipush #17
    //   1814: iushr
    //   1815: aload #19
    //   1817: iload #21
    //   1819: iconst_2
    //   1820: isub
    //   1821: iaload
    //   1822: bipush #15
    //   1824: ishl
    //   1825: ior
    //   1826: aload #19
    //   1828: iload #21
    //   1830: iconst_2
    //   1831: isub
    //   1832: iaload
    //   1833: bipush #19
    //   1835: iushr
    //   1836: aload #19
    //   1838: iload #21
    //   1840: iconst_2
    //   1841: isub
    //   1842: iaload
    //   1843: bipush #13
    //   1845: ishl
    //   1846: ior
    //   1847: ixor
    //   1848: aload #19
    //   1850: iload #21
    //   1852: iconst_2
    //   1853: isub
    //   1854: iaload
    //   1855: bipush #10
    //   1857: iushr
    //   1858: ixor
    //   1859: aload #19
    //   1861: iload #21
    //   1863: bipush #7
    //   1865: isub
    //   1866: iaload
    //   1867: iadd
    //   1868: aload #19
    //   1870: iload #21
    //   1872: bipush #15
    //   1874: isub
    //   1875: iaload
    //   1876: bipush #7
    //   1878: iushr
    //   1879: aload #19
    //   1881: iload #21
    //   1883: bipush #15
    //   1885: isub
    //   1886: iaload
    //   1887: bipush #25
    //   1889: ishl
    //   1890: ior
    //   1891: aload #19
    //   1893: iload #21
    //   1895: bipush #15
    //   1897: isub
    //   1898: iaload
    //   1899: bipush #18
    //   1901: iushr
    //   1902: aload #19
    //   1904: iload #21
    //   1906: bipush #15
    //   1908: isub
    //   1909: iaload
    //   1910: bipush #14
    //   1912: ishl
    //   1913: ior
    //   1914: ixor
    //   1915: aload #19
    //   1917: iload #21
    //   1919: bipush #15
    //   1921: isub
    //   1922: iaload
    //   1923: iconst_3
    //   1924: iushr
    //   1925: ixor
    //   1926: iadd
    //   1927: aload #19
    //   1929: iload #21
    //   1931: bipush #16
    //   1933: isub
    //   1934: iaload
    //   1935: iadd
    //   1936: iastore
    //   1937: goto -> 1944
    //   1940: invokestatic a : (Ljava/lang/Throwable;)Ljava/lang/Throwable;
    //   1943: athrow
    //   1944: aload #20
    //   1946: bipush #7
    //   1948: iaload
    //   1949: aload #20
    //   1951: iconst_4
    //   1952: iaload
    //   1953: bipush #6
    //   1955: iushr
    //   1956: aload #20
    //   1958: iconst_4
    //   1959: iaload
    //   1960: bipush #26
    //   1962: ishl
    //   1963: ior
    //   1964: aload #20
    //   1966: iconst_4
    //   1967: iaload
    //   1968: bipush #11
    //   1970: iushr
    //   1971: aload #20
    //   1973: iconst_4
    //   1974: iaload
    //   1975: bipush #21
    //   1977: ishl
    //   1978: ior
    //   1979: ixor
    //   1980: aload #20
    //   1982: iconst_4
    //   1983: iaload
    //   1984: bipush #25
    //   1986: iushr
    //   1987: aload #20
    //   1989: iconst_4
    //   1990: iaload
    //   1991: bipush #7
    //   1993: ishl
    //   1994: ior
    //   1995: ixor
    //   1996: iadd
    //   1997: aload #20
    //   1999: bipush #6
    //   2001: iaload
    //   2002: aload #20
    //   2004: iconst_4
    //   2005: iaload
    //   2006: aload #20
    //   2008: iconst_5
    //   2009: iaload
    //   2010: aload #20
    //   2012: bipush #6
    //   2014: iaload
    //   2015: ixor
    //   2016: iand
    //   2017: ixor
    //   2018: iadd
    //   2019: aload #6
    //   2021: iload #21
    //   2023: iaload
    //   2024: iadd
    //   2025: aload #19
    //   2027: iload #21
    //   2029: iaload
    //   2030: iadd
    //   2031: istore #22
    //   2033: aload #20
    //   2035: iconst_0
    //   2036: iaload
    //   2037: iconst_2
    //   2038: iushr
    //   2039: aload #20
    //   2041: iconst_0
    //   2042: iaload
    //   2043: bipush #30
    //   2045: ishl
    //   2046: ior
    //   2047: aload #20
    //   2049: iconst_0
    //   2050: iaload
    //   2051: bipush #13
    //   2053: iushr
    //   2054: aload #20
    //   2056: iconst_0
    //   2057: iaload
    //   2058: bipush #19
    //   2060: ishl
    //   2061: ior
    //   2062: ixor
    //   2063: aload #20
    //   2065: iconst_0
    //   2066: iaload
    //   2067: bipush #22
    //   2069: iushr
    //   2070: aload #20
    //   2072: iconst_0
    //   2073: iaload
    //   2074: bipush #10
    //   2076: ishl
    //   2077: ior
    //   2078: ixor
    //   2079: aload #20
    //   2081: iconst_0
    //   2082: iaload
    //   2083: aload #20
    //   2085: iconst_1
    //   2086: iaload
    //   2087: iand
    //   2088: aload #20
    //   2090: iconst_2
    //   2091: iaload
    //   2092: aload #20
    //   2094: iconst_0
    //   2095: iaload
    //   2096: aload #20
    //   2098: iconst_1
    //   2099: iaload
    //   2100: ior
    //   2101: iand
    //   2102: ior
    //   2103: iadd
    //   2104: istore #23
    //   2106: aload #20
    //   2108: iconst_3
    //   2109: dup2
    //   2110: iaload
    //   2111: iload #22
    //   2113: iadd
    //   2114: iastore
    //   2115: aload #20
    //   2117: bipush #7
    //   2119: iload #22
    //   2121: iload #23
    //   2123: iadd
    //   2124: iastore
    //   2125: aload #20
    //   2127: bipush #7
    //   2129: iaload
    //   2130: istore #22
    //   2132: aload #20
    //   2134: bipush #7
    //   2136: aload #20
    //   2138: bipush #6
    //   2140: iaload
    //   2141: iastore
    //   2142: aload #20
    //   2144: bipush #6
    //   2146: aload #20
    //   2148: iconst_5
    //   2149: iaload
    //   2150: iastore
    //   2151: aload #20
    //   2153: iconst_5
    //   2154: aload #20
    //   2156: iconst_4
    //   2157: iaload
    //   2158: iastore
    //   2159: aload #20
    //   2161: iconst_4
    //   2162: aload #20
    //   2164: iconst_3
    //   2165: iaload
    //   2166: iastore
    //   2167: aload #20
    //   2169: iconst_3
    //   2170: aload #20
    //   2172: iconst_2
    //   2173: iaload
    //   2174: iastore
    //   2175: aload #20
    //   2177: iconst_2
    //   2178: aload #20
    //   2180: iconst_1
    //   2181: iaload
    //   2182: iastore
    //   2183: aload #20
    //   2185: iconst_1
    //   2186: aload #20
    //   2188: iconst_0
    //   2189: iaload
    //   2190: iastore
    //   2191: aload #20
    //   2193: iconst_0
    //   2194: iload #22
    //   2196: iastore
    //   2197: iinc #21, 1
    //   2200: iload_2
    //   2201: ifeq -> 1709
    //   2204: iconst_0
    //   2205: istore #21
    //   2207: iload #21
    //   2209: bipush #8
    //   2211: if_icmpge -> 2234
    //   2214: aload #8
    //   2216: iload #21
    //   2218: dup2
    //   2219: iaload
    //   2220: aload #20
    //   2222: iload #21
    //   2224: iaload
    //   2225: iadd
    //   2226: iastore
    //   2227: iinc #21, 1
    //   2230: iload_2
    //   2231: ifeq -> 2207
    //   2234: iload #13
    //   2236: iload #18
    //   2238: iadd
    //   2239: istore #13
    //   2241: iload #17
    //   2243: iload #18
    //   2245: isub
    //   2246: istore #17
    //   2248: iconst_0
    //   2249: istore #12
    //   2251: iload #17
    //   2253: bipush #64
    //   2255: if_icmplt -> 2865
    //   2258: iconst_0
    //   2259: istore #19
    //   2261: iload #19
    //   2263: bipush #64
    //   2265: if_icmpge -> 2288
    //   2268: aload #10
    //   2270: iload #19
    //   2272: aload #5
    //   2274: iload #13
    //   2276: iload #19
    //   2278: iadd
    //   2279: baload
    //   2280: bastore
    //   2281: iinc #19, 1
    //   2284: iload_2
    //   2285: ifeq -> 2261
    //   2288: bipush #64
    //   2290: newarray int
    //   2292: astore #19
    //   2294: bipush #8
    //   2296: newarray int
    //   2298: astore #20
    //   2300: iconst_0
    //   2301: istore #21
    //   2303: iload #21
    //   2305: bipush #8
    //   2307: if_icmpge -> 2327
    //   2310: aload #20
    //   2312: iload #21
    //   2314: aload #8
    //   2316: iload #21
    //   2318: iaload
    //   2319: iastore
    //   2320: iinc #21, 1
    //   2323: iload_2
    //   2324: ifeq -> 2303
    //   2327: iconst_0
    //   2328: istore #21
    //   2330: iload #21
    //   2332: bipush #64
    //   2334: if_icmpge -> 2825
    //   2337: iload #21
    //   2339: bipush #16
    //   2341: if_icmpge -> 2422
    //   2344: aload #19
    //   2346: iload #21
    //   2348: aload #10
    //   2350: iconst_4
    //   2351: iload #21
    //   2353: imul
    //   2354: baload
    //   2355: sipush #255
    //   2358: iand
    //   2359: bipush #24
    //   2361: ishl
    //   2362: aload #10
    //   2364: iconst_4
    //   2365: iload #21
    //   2367: imul
    //   2368: iconst_1
    //   2369: iadd
    //   2370: baload
    //   2371: sipush #255
    //   2374: iand
    //   2375: bipush #16
    //   2377: ishl
    //   2378: ior
    //   2379: aload #10
    //   2381: iconst_4
    //   2382: iload #21
    //   2384: imul
    //   2385: iconst_2
    //   2386: iadd
    //   2387: baload
    //   2388: sipush #255
    //   2391: iand
    //   2392: bipush #8
    //   2394: ishl
    //   2395: ior
    //   2396: aload #10
    //   2398: iconst_4
    //   2399: iload #21
    //   2401: imul
    //   2402: iconst_3
    //   2403: iadd
    //   2404: baload
    //   2405: sipush #255
    //   2408: iand
    //   2409: ior
    //   2410: iastore
    //   2411: iload_2
    //   2412: ifeq -> 2565
    //   2415: goto -> 2422
    //   2418: invokestatic a : (Ljava/lang/Throwable;)Ljava/lang/Throwable;
    //   2421: athrow
    //   2422: aload #19
    //   2424: iload #21
    //   2426: aload #19
    //   2428: iload #21
    //   2430: iconst_2
    //   2431: isub
    //   2432: iaload
    //   2433: bipush #17
    //   2435: iushr
    //   2436: aload #19
    //   2438: iload #21
    //   2440: iconst_2
    //   2441: isub
    //   2442: iaload
    //   2443: bipush #15
    //   2445: ishl
    //   2446: ior
    //   2447: aload #19
    //   2449: iload #21
    //   2451: iconst_2
    //   2452: isub
    //   2453: iaload
    //   2454: bipush #19
    //   2456: iushr
    //   2457: aload #19
    //   2459: iload #21
    //   2461: iconst_2
    //   2462: isub
    //   2463: iaload
    //   2464: bipush #13
    //   2466: ishl
    //   2467: ior
    //   2468: ixor
    //   2469: aload #19
    //   2471: iload #21
    //   2473: iconst_2
    //   2474: isub
    //   2475: iaload
    //   2476: bipush #10
    //   2478: iushr
    //   2479: ixor
    //   2480: aload #19
    //   2482: iload #21
    //   2484: bipush #7
    //   2486: isub
    //   2487: iaload
    //   2488: iadd
    //   2489: aload #19
    //   2491: iload #21
    //   2493: bipush #15
    //   2495: isub
    //   2496: iaload
    //   2497: bipush #7
    //   2499: iushr
    //   2500: aload #19
    //   2502: iload #21
    //   2504: bipush #15
    //   2506: isub
    //   2507: iaload
    //   2508: bipush #25
    //   2510: ishl
    //   2511: ior
    //   2512: aload #19
    //   2514: iload #21
    //   2516: bipush #15
    //   2518: isub
    //   2519: iaload
    //   2520: bipush #18
    //   2522: iushr
    //   2523: aload #19
    //   2525: iload #21
    //   2527: bipush #15
    //   2529: isub
    //   2530: iaload
    //   2531: bipush #14
    //   2533: ishl
    //   2534: ior
    //   2535: ixor
    //   2536: aload #19
    //   2538: iload #21
    //   2540: bipush #15
    //   2542: isub
    //   2543: iaload
    //   2544: iconst_3
    //   2545: iushr
    //   2546: ixor
    //   2547: iadd
    //   2548: aload #19
    //   2550: iload #21
    //   2552: bipush #16
    //   2554: isub
    //   2555: iaload
    //   2556: iadd
    //   2557: iastore
    //   2558: goto -> 2565
    //   2561: invokestatic a : (Ljava/lang/Throwable;)Ljava/lang/Throwable;
    //   2564: athrow
    //   2565: aload #20
    //   2567: bipush #7
    //   2569: iaload
    //   2570: aload #20
    //   2572: iconst_4
    //   2573: iaload
    //   2574: bipush #6
    //   2576: iushr
    //   2577: aload #20
    //   2579: iconst_4
    //   2580: iaload
    //   2581: bipush #26
    //   2583: ishl
    //   2584: ior
    //   2585: aload #20
    //   2587: iconst_4
    //   2588: iaload
    //   2589: bipush #11
    //   2591: iushr
    //   2592: aload #20
    //   2594: iconst_4
    //   2595: iaload
    //   2596: bipush #21
    //   2598: ishl
    //   2599: ior
    //   2600: ixor
    //   2601: aload #20
    //   2603: iconst_4
    //   2604: iaload
    //   2605: bipush #25
    //   2607: iushr
    //   2608: aload #20
    //   2610: iconst_4
    //   2611: iaload
    //   2612: bipush #7
    //   2614: ishl
    //   2615: ior
    //   2616: ixor
    //   2617: iadd
    //   2618: aload #20
    //   2620: bipush #6
    //   2622: iaload
    //   2623: aload #20
    //   2625: iconst_4
    //   2626: iaload
    //   2627: aload #20
    //   2629: iconst_5
    //   2630: iaload
    //   2631: aload #20
    //   2633: bipush #6
    //   2635: iaload
    //   2636: ixor
    //   2637: iand
    //   2638: ixor
    //   2639: iadd
    //   2640: aload #6
    //   2642: iload #21
    //   2644: iaload
    //   2645: iadd
    //   2646: aload #19
    //   2648: iload #21
    //   2650: iaload
    //   2651: iadd
    //   2652: istore #22
    //   2654: aload #20
    //   2656: iconst_0
    //   2657: iaload
    //   2658: iconst_2
    //   2659: iushr
    //   2660: aload #20
    //   2662: iconst_0
    //   2663: iaload
    //   2664: bipush #30
    //   2666: ishl
    //   2667: ior
    //   2668: aload #20
    //   2670: iconst_0
    //   2671: iaload
    //   2672: bipush #13
    //   2674: iushr
    //   2675: aload #20
    //   2677: iconst_0
    //   2678: iaload
    //   2679: bipush #19
    //   2681: ishl
    //   2682: ior
    //   2683: ixor
    //   2684: aload #20
    //   2686: iconst_0
    //   2687: iaload
    //   2688: bipush #22
    //   2690: iushr
    //   2691: aload #20
    //   2693: iconst_0
    //   2694: iaload
    //   2695: bipush #10
    //   2697: ishl
    //   2698: ior
    //   2699: ixor
    //   2700: aload #20
    //   2702: iconst_0
    //   2703: iaload
    //   2704: aload #20
    //   2706: iconst_1
    //   2707: iaload
    //   2708: iand
    //   2709: aload #20
    //   2711: iconst_2
    //   2712: iaload
    //   2713: aload #20
    //   2715: iconst_0
    //   2716: iaload
    //   2717: aload #20
    //   2719: iconst_1
    //   2720: iaload
    //   2721: ior
    //   2722: iand
    //   2723: ior
    //   2724: iadd
    //   2725: istore #23
    //   2727: aload #20
    //   2729: iconst_3
    //   2730: dup2
    //   2731: iaload
    //   2732: iload #22
    //   2734: iadd
    //   2735: iastore
    //   2736: aload #20
    //   2738: bipush #7
    //   2740: iload #22
    //   2742: iload #23
    //   2744: iadd
    //   2745: iastore
    //   2746: aload #20
    //   2748: bipush #7
    //   2750: iaload
    //   2751: istore #22
    //   2753: aload #20
    //   2755: bipush #7
    //   2757: aload #20
    //   2759: bipush #6
    //   2761: iaload
    //   2762: iastore
    //   2763: aload #20
    //   2765: bipush #6
    //   2767: aload #20
    //   2769: iconst_5
    //   2770: iaload
    //   2771: iastore
    //   2772: aload #20
    //   2774: iconst_5
    //   2775: aload #20
    //   2777: iconst_4
    //   2778: iaload
    //   2779: iastore
    //   2780: aload #20
    //   2782: iconst_4
    //   2783: aload #20
    //   2785: iconst_3
    //   2786: iaload
    //   2787: iastore
    //   2788: aload #20
    //   2790: iconst_3
    //   2791: aload #20
    //   2793: iconst_2
    //   2794: iaload
    //   2795: iastore
    //   2796: aload #20
    //   2798: iconst_2
    //   2799: aload #20
    //   2801: iconst_1
    //   2802: iaload
    //   2803: iastore
    //   2804: aload #20
    //   2806: iconst_1
    //   2807: aload #20
    //   2809: iconst_0
    //   2810: iaload
    //   2811: iastore
    //   2812: aload #20
    //   2814: iconst_0
    //   2815: iload #22
    //   2817: iastore
    //   2818: iinc #21, 1
    //   2821: iload_2
    //   2822: ifeq -> 2330
    //   2825: iconst_0
    //   2826: istore #21
    //   2828: iload #21
    //   2830: bipush #8
    //   2832: if_icmpge -> 2855
    //   2835: aload #8
    //   2837: iload #21
    //   2839: dup2
    //   2840: iaload
    //   2841: aload #20
    //   2843: iload #21
    //   2845: iaload
    //   2846: iadd
    //   2847: iastore
    //   2848: iinc #21, 1
    //   2851: iload_2
    //   2852: ifeq -> 2828
    //   2855: iinc #13, 64
    //   2858: iinc #17, -64
    //   2861: iload_2
    //   2862: ifeq -> 2251
    //   2865: iload #17
    //   2867: ifle -> 2903
    //   2870: iconst_0
    //   2871: istore #19
    //   2873: iload #19
    //   2875: iload #17
    //   2877: if_icmpge -> 2903
    //   2880: aload #9
    //   2882: iload #12
    //   2884: iload #19
    //   2886: iadd
    //   2887: aload #5
    //   2889: iload #13
    //   2891: iload #19
    //   2893: iadd
    //   2894: baload
    //   2895: bastore
    //   2896: iinc #19, 1
    //   2899: iload_2
    //   2900: ifeq -> 2873
    //   2903: bipush #8
    //   2905: newarray byte
    //   2907: astore #19
    //   2909: aload #19
    //   2911: iconst_0
    //   2912: iload #14
    //   2914: bipush #24
    //   2916: iushr
    //   2917: i2b
    //   2918: bastore
    //   2919: aload #19
    //   2921: iconst_1
    //   2922: iload #14
    //   2924: bipush #16
    //   2926: iushr
    //   2927: i2b
    //   2928: bastore
    //   2929: aload #19
    //   2931: iconst_2
    //   2932: iload #14
    //   2934: bipush #8
    //   2936: iushr
    //   2937: i2b
    //   2938: bastore
    //   2939: aload #19
    //   2941: iconst_3
    //   2942: iload #14
    //   2944: i2b
    //   2945: bastore
    //   2946: aload #19
    //   2948: iconst_4
    //   2949: iload #15
    //   2951: bipush #24
    //   2953: iushr
    //   2954: i2b
    //   2955: bastore
    //   2956: aload #19
    //   2958: iconst_5
    //   2959: iload #15
    //   2961: bipush #16
    //   2963: iushr
    //   2964: i2b
    //   2965: bastore
    //   2966: aload #19
    //   2968: bipush #6
    //   2970: iload #15
    //   2972: bipush #8
    //   2974: iushr
    //   2975: i2b
    //   2976: bastore
    //   2977: aload #19
    //   2979: bipush #7
    //   2981: iload #15
    //   2983: i2b
    //   2984: bastore
    //   2985: bipush #8
    //   2987: istore #11
    //   2989: aload #7
    //   2991: iconst_0
    //   2992: iaload
    //   2993: bipush #63
    //   2995: iand
    //   2996: istore #12
    //   2998: bipush #64
    //   3000: iload #12
    //   3002: isub
    //   3003: istore #18
    //   3005: aload #7
    //   3007: iconst_0
    //   3008: dup2
    //   3009: iaload
    //   3010: iload #11
    //   3012: iadd
    //   3013: iastore
    //   3014: aload #7
    //   3016: iconst_0
    //   3017: dup2
    //   3018: iaload
    //   3019: iconst_m1
    //   3020: iand
    //   3021: iastore
    //   3022: aload #7
    //   3024: iconst_0
    //   3025: iaload
    //   3026: iload #11
    //   3028: if_icmpge -> 3046
    //   3031: aload #7
    //   3033: iconst_1
    //   3034: dup2
    //   3035: iaload
    //   3036: iconst_1
    //   3037: iadd
    //   3038: iastore
    //   3039: goto -> 3046
    //   3042: invokestatic a : (Ljava/lang/Throwable;)Ljava/lang/Throwable;
    //   3045: athrow
    //   3046: iload #12
    //   3048: ifle -> 3662
    //   3051: iload #11
    //   3053: iload #18
    //   3055: if_icmplt -> 3662
    //   3058: goto -> 3065
    //   3061: invokestatic a : (Ljava/lang/Throwable;)Ljava/lang/Throwable;
    //   3064: athrow
    //   3065: iconst_0
    //   3066: istore #20
    //   3068: iload #20
    //   3070: iload #18
    //   3072: if_icmpge -> 3095
    //   3075: aload #9
    //   3077: iload #12
    //   3079: iload #20
    //   3081: iadd
    //   3082: aload #19
    //   3084: iload #20
    //   3086: baload
    //   3087: bastore
    //   3088: iinc #20, 1
    //   3091: iload_2
    //   3092: ifeq -> 3068
    //   3095: bipush #64
    //   3097: newarray int
    //   3099: astore #20
    //   3101: bipush #8
    //   3103: newarray int
    //   3105: astore #21
    //   3107: iconst_0
    //   3108: istore #22
    //   3110: iload #22
    //   3112: bipush #8
    //   3114: if_icmpge -> 3134
    //   3117: aload #21
    //   3119: iload #22
    //   3121: aload #8
    //   3123: iload #22
    //   3125: iaload
    //   3126: iastore
    //   3127: iinc #22, 1
    //   3130: iload_2
    //   3131: ifeq -> 3110
    //   3134: iconst_0
    //   3135: istore #22
    //   3137: iload #22
    //   3139: bipush #64
    //   3141: if_icmpge -> 3632
    //   3144: iload #22
    //   3146: bipush #16
    //   3148: if_icmpge -> 3229
    //   3151: aload #20
    //   3153: iload #22
    //   3155: aload #9
    //   3157: iconst_4
    //   3158: iload #22
    //   3160: imul
    //   3161: baload
    //   3162: sipush #255
    //   3165: iand
    //   3166: bipush #24
    //   3168: ishl
    //   3169: aload #9
    //   3171: iconst_4
    //   3172: iload #22
    //   3174: imul
    //   3175: iconst_1
    //   3176: iadd
    //   3177: baload
    //   3178: sipush #255
    //   3181: iand
    //   3182: bipush #16
    //   3184: ishl
    //   3185: ior
    //   3186: aload #9
    //   3188: iconst_4
    //   3189: iload #22
    //   3191: imul
    //   3192: iconst_2
    //   3193: iadd
    //   3194: baload
    //   3195: sipush #255
    //   3198: iand
    //   3199: bipush #8
    //   3201: ishl
    //   3202: ior
    //   3203: aload #9
    //   3205: iconst_4
    //   3206: iload #22
    //   3208: imul
    //   3209: iconst_3
    //   3210: iadd
    //   3211: baload
    //   3212: sipush #255
    //   3215: iand
    //   3216: ior
    //   3217: iastore
    //   3218: iload_2
    //   3219: ifeq -> 3372
    //   3222: goto -> 3229
    //   3225: invokestatic a : (Ljava/lang/Throwable;)Ljava/lang/Throwable;
    //   3228: athrow
    //   3229: aload #20
    //   3231: iload #22
    //   3233: aload #20
    //   3235: iload #22
    //   3237: iconst_2
    //   3238: isub
    //   3239: iaload
    //   3240: bipush #17
    //   3242: iushr
    //   3243: aload #20
    //   3245: iload #22
    //   3247: iconst_2
    //   3248: isub
    //   3249: iaload
    //   3250: bipush #15
    //   3252: ishl
    //   3253: ior
    //   3254: aload #20
    //   3256: iload #22
    //   3258: iconst_2
    //   3259: isub
    //   3260: iaload
    //   3261: bipush #19
    //   3263: iushr
    //   3264: aload #20
    //   3266: iload #22
    //   3268: iconst_2
    //   3269: isub
    //   3270: iaload
    //   3271: bipush #13
    //   3273: ishl
    //   3274: ior
    //   3275: ixor
    //   3276: aload #20
    //   3278: iload #22
    //   3280: iconst_2
    //   3281: isub
    //   3282: iaload
    //   3283: bipush #10
    //   3285: iushr
    //   3286: ixor
    //   3287: aload #20
    //   3289: iload #22
    //   3291: bipush #7
    //   3293: isub
    //   3294: iaload
    //   3295: iadd
    //   3296: aload #20
    //   3298: iload #22
    //   3300: bipush #15
    //   3302: isub
    //   3303: iaload
    //   3304: bipush #7
    //   3306: iushr
    //   3307: aload #20
    //   3309: iload #22
    //   3311: bipush #15
    //   3313: isub
    //   3314: iaload
    //   3315: bipush #25
    //   3317: ishl
    //   3318: ior
    //   3319: aload #20
    //   3321: iload #22
    //   3323: bipush #15
    //   3325: isub
    //   3326: iaload
    //   3327: bipush #18
    //   3329: iushr
    //   3330: aload #20
    //   3332: iload #22
    //   3334: bipush #15
    //   3336: isub
    //   3337: iaload
    //   3338: bipush #14
    //   3340: ishl
    //   3341: ior
    //   3342: ixor
    //   3343: aload #20
    //   3345: iload #22
    //   3347: bipush #15
    //   3349: isub
    //   3350: iaload
    //   3351: iconst_3
    //   3352: iushr
    //   3353: ixor
    //   3354: iadd
    //   3355: aload #20
    //   3357: iload #22
    //   3359: bipush #16
    //   3361: isub
    //   3362: iaload
    //   3363: iadd
    //   3364: iastore
    //   3365: goto -> 3372
    //   3368: invokestatic a : (Ljava/lang/Throwable;)Ljava/lang/Throwable;
    //   3371: athrow
    //   3372: aload #21
    //   3374: bipush #7
    //   3376: iaload
    //   3377: aload #21
    //   3379: iconst_4
    //   3380: iaload
    //   3381: bipush #6
    //   3383: iushr
    //   3384: aload #21
    //   3386: iconst_4
    //   3387: iaload
    //   3388: bipush #26
    //   3390: ishl
    //   3391: ior
    //   3392: aload #21
    //   3394: iconst_4
    //   3395: iaload
    //   3396: bipush #11
    //   3398: iushr
    //   3399: aload #21
    //   3401: iconst_4
    //   3402: iaload
    //   3403: bipush #21
    //   3405: ishl
    //   3406: ior
    //   3407: ixor
    //   3408: aload #21
    //   3410: iconst_4
    //   3411: iaload
    //   3412: bipush #25
    //   3414: iushr
    //   3415: aload #21
    //   3417: iconst_4
    //   3418: iaload
    //   3419: bipush #7
    //   3421: ishl
    //   3422: ior
    //   3423: ixor
    //   3424: iadd
    //   3425: aload #21
    //   3427: bipush #6
    //   3429: iaload
    //   3430: aload #21
    //   3432: iconst_4
    //   3433: iaload
    //   3434: aload #21
    //   3436: iconst_5
    //   3437: iaload
    //   3438: aload #21
    //   3440: bipush #6
    //   3442: iaload
    //   3443: ixor
    //   3444: iand
    //   3445: ixor
    //   3446: iadd
    //   3447: aload #6
    //   3449: iload #22
    //   3451: iaload
    //   3452: iadd
    //   3453: aload #20
    //   3455: iload #22
    //   3457: iaload
    //   3458: iadd
    //   3459: istore #23
    //   3461: aload #21
    //   3463: iconst_0
    //   3464: iaload
    //   3465: iconst_2
    //   3466: iushr
    //   3467: aload #21
    //   3469: iconst_0
    //   3470: iaload
    //   3471: bipush #30
    //   3473: ishl
    //   3474: ior
    //   3475: aload #21
    //   3477: iconst_0
    //   3478: iaload
    //   3479: bipush #13
    //   3481: iushr
    //   3482: aload #21
    //   3484: iconst_0
    //   3485: iaload
    //   3486: bipush #19
    //   3488: ishl
    //   3489: ior
    //   3490: ixor
    //   3491: aload #21
    //   3493: iconst_0
    //   3494: iaload
    //   3495: bipush #22
    //   3497: iushr
    //   3498: aload #21
    //   3500: iconst_0
    //   3501: iaload
    //   3502: bipush #10
    //   3504: ishl
    //   3505: ior
    //   3506: ixor
    //   3507: aload #21
    //   3509: iconst_0
    //   3510: iaload
    //   3511: aload #21
    //   3513: iconst_1
    //   3514: iaload
    //   3515: iand
    //   3516: aload #21
    //   3518: iconst_2
    //   3519: iaload
    //   3520: aload #21
    //   3522: iconst_0
    //   3523: iaload
    //   3524: aload #21
    //   3526: iconst_1
    //   3527: iaload
    //   3528: ior
    //   3529: iand
    //   3530: ior
    //   3531: iadd
    //   3532: istore #24
    //   3534: aload #21
    //   3536: iconst_3
    //   3537: dup2
    //   3538: iaload
    //   3539: iload #23
    //   3541: iadd
    //   3542: iastore
    //   3543: aload #21
    //   3545: bipush #7
    //   3547: iload #23
    //   3549: iload #24
    //   3551: iadd
    //   3552: iastore
    //   3553: aload #21
    //   3555: bipush #7
    //   3557: iaload
    //   3558: istore #23
    //   3560: aload #21
    //   3562: bipush #7
    //   3564: aload #21
    //   3566: bipush #6
    //   3568: iaload
    //   3569: iastore
    //   3570: aload #21
    //   3572: bipush #6
    //   3574: aload #21
    //   3576: iconst_5
    //   3577: iaload
    //   3578: iastore
    //   3579: aload #21
    //   3581: iconst_5
    //   3582: aload #21
    //   3584: iconst_4
    //   3585: iaload
    //   3586: iastore
    //   3587: aload #21
    //   3589: iconst_4
    //   3590: aload #21
    //   3592: iconst_3
    //   3593: iaload
    //   3594: iastore
    //   3595: aload #21
    //   3597: iconst_3
    //   3598: aload #21
    //   3600: iconst_2
    //   3601: iaload
    //   3602: iastore
    //   3603: aload #21
    //   3605: iconst_2
    //   3606: aload #21
    //   3608: iconst_1
    //   3609: iaload
    //   3610: iastore
    //   3611: aload #21
    //   3613: iconst_1
    //   3614: aload #21
    //   3616: iconst_0
    //   3617: iaload
    //   3618: iastore
    //   3619: aload #21
    //   3621: iconst_0
    //   3622: iload #23
    //   3624: iastore
    //   3625: iinc #22, 1
    //   3628: iload_2
    //   3629: ifeq -> 3137
    //   3632: iconst_0
    //   3633: istore #22
    //   3635: iload #22
    //   3637: bipush #8
    //   3639: if_icmpge -> 3662
    //   3642: aload #8
    //   3644: iload #22
    //   3646: dup2
    //   3647: iaload
    //   3648: aload #21
    //   3650: iload #22
    //   3652: iaload
    //   3653: iadd
    //   3654: iastore
    //   3655: iinc #22, 1
    //   3658: iload_2
    //   3659: ifeq -> 3635
    //   3662: bipush #32
    //   3664: newarray byte
    //   3666: astore #4
    //   3668: aload #4
    //   3670: iconst_0
    //   3671: aload #8
    //   3673: iconst_0
    //   3674: iaload
    //   3675: bipush #24
    //   3677: iushr
    //   3678: i2b
    //   3679: bastore
    //   3680: aload #4
    //   3682: iconst_1
    //   3683: aload #8
    //   3685: iconst_0
    //   3686: iaload
    //   3687: bipush #16
    //   3689: iushr
    //   3690: i2b
    //   3691: bastore
    //   3692: aload #4
    //   3694: iconst_2
    //   3695: aload #8
    //   3697: iconst_0
    //   3698: iaload
    //   3699: bipush #8
    //   3701: iushr
    //   3702: i2b
    //   3703: bastore
    //   3704: aload #4
    //   3706: iconst_3
    //   3707: aload #8
    //   3709: iconst_0
    //   3710: iaload
    //   3711: i2b
    //   3712: bastore
    //   3713: aload #4
    //   3715: iconst_4
    //   3716: aload #8
    //   3718: iconst_1
    //   3719: iaload
    //   3720: bipush #24
    //   3722: iushr
    //   3723: i2b
    //   3724: bastore
    //   3725: aload #4
    //   3727: iconst_5
    //   3728: aload #8
    //   3730: iconst_1
    //   3731: iaload
    //   3732: bipush #16
    //   3734: iushr
    //   3735: i2b
    //   3736: bastore
    //   3737: aload #4
    //   3739: bipush #6
    //   3741: aload #8
    //   3743: iconst_1
    //   3744: iaload
    //   3745: bipush #8
    //   3747: iushr
    //   3748: i2b
    //   3749: bastore
    //   3750: aload #4
    //   3752: bipush #7
    //   3754: aload #8
    //   3756: iconst_1
    //   3757: iaload
    //   3758: i2b
    //   3759: bastore
    //   3760: aload #4
    //   3762: bipush #8
    //   3764: aload #8
    //   3766: iconst_2
    //   3767: iaload
    //   3768: bipush #24
    //   3770: iushr
    //   3771: i2b
    //   3772: bastore
    //   3773: aload #4
    //   3775: bipush #9
    //   3777: aload #8
    //   3779: iconst_2
    //   3780: iaload
    //   3781: bipush #16
    //   3783: iushr
    //   3784: i2b
    //   3785: bastore
    //   3786: aload #4
    //   3788: bipush #10
    //   3790: aload #8
    //   3792: iconst_2
    //   3793: iaload
    //   3794: bipush #8
    //   3796: iushr
    //   3797: i2b
    //   3798: bastore
    //   3799: aload #4
    //   3801: bipush #11
    //   3803: aload #8
    //   3805: iconst_2
    //   3806: iaload
    //   3807: i2b
    //   3808: bastore
    //   3809: aload #4
    //   3811: bipush #12
    //   3813: aload #8
    //   3815: iconst_3
    //   3816: iaload
    //   3817: bipush #24
    //   3819: iushr
    //   3820: i2b
    //   3821: bastore
    //   3822: aload #4
    //   3824: bipush #13
    //   3826: aload #8
    //   3828: iconst_3
    //   3829: iaload
    //   3830: bipush #16
    //   3832: iushr
    //   3833: i2b
    //   3834: bastore
    //   3835: aload #4
    //   3837: bipush #14
    //   3839: aload #8
    //   3841: iconst_3
    //   3842: iaload
    //   3843: bipush #8
    //   3845: iushr
    //   3846: i2b
    //   3847: bastore
    //   3848: aload #4
    //   3850: bipush #15
    //   3852: aload #8
    //   3854: iconst_3
    //   3855: iaload
    //   3856: i2b
    //   3857: bastore
    //   3858: aload #4
    //   3860: bipush #16
    //   3862: aload #8
    //   3864: iconst_4
    //   3865: iaload
    //   3866: bipush #24
    //   3868: iushr
    //   3869: i2b
    //   3870: bastore
    //   3871: aload #4
    //   3873: bipush #17
    //   3875: aload #8
    //   3877: iconst_4
    //   3878: iaload
    //   3879: bipush #16
    //   3881: iushr
    //   3882: i2b
    //   3883: bastore
    //   3884: aload #4
    //   3886: bipush #18
    //   3888: aload #8
    //   3890: iconst_4
    //   3891: iaload
    //   3892: bipush #8
    //   3894: iushr
    //   3895: i2b
    //   3896: bastore
    //   3897: aload #4
    //   3899: bipush #19
    //   3901: aload #8
    //   3903: iconst_4
    //   3904: iaload
    //   3905: i2b
    //   3906: bastore
    //   3907: aload #4
    //   3909: bipush #20
    //   3911: aload #8
    //   3913: iconst_5
    //   3914: iaload
    //   3915: bipush #24
    //   3917: iushr
    //   3918: i2b
    //   3919: bastore
    //   3920: aload #4
    //   3922: bipush #21
    //   3924: aload #8
    //   3926: iconst_5
    //   3927: iaload
    //   3928: bipush #16
    //   3930: iushr
    //   3931: i2b
    //   3932: bastore
    //   3933: aload #4
    //   3935: bipush #22
    //   3937: aload #8
    //   3939: iconst_5
    //   3940: iaload
    //   3941: bipush #8
    //   3943: iushr
    //   3944: i2b
    //   3945: bastore
    //   3946: aload #4
    //   3948: bipush #23
    //   3950: aload #8
    //   3952: iconst_5
    //   3953: iaload
    //   3954: i2b
    //   3955: bastore
    //   3956: aload #4
    //   3958: bipush #24
    //   3960: aload #8
    //   3962: bipush #6
    //   3964: iaload
    //   3965: bipush #24
    //   3967: iushr
    //   3968: i2b
    //   3969: bastore
    //   3970: aload #4
    //   3972: bipush #25
    //   3974: aload #8
    //   3976: bipush #6
    //   3978: iaload
    //   3979: bipush #16
    //   3981: iushr
    //   3982: i2b
    //   3983: bastore
    //   3984: aload #4
    //   3986: bipush #26
    //   3988: aload #8
    //   3990: bipush #6
    //   3992: iaload
    //   3993: bipush #8
    //   3995: iushr
    //   3996: i2b
    //   3997: bastore
    //   3998: aload #4
    //   4000: bipush #27
    //   4002: aload #8
    //   4004: bipush #6
    //   4006: iaload
    //   4007: i2b
    //   4008: bastore
    //   4009: aload #4
    //   4011: bipush #28
    //   4013: aload #8
    //   4015: bipush #7
    //   4017: iaload
    //   4018: bipush #24
    //   4020: iushr
    //   4021: i2b
    //   4022: bastore
    //   4023: aload #4
    //   4025: bipush #29
    //   4027: aload #8
    //   4029: bipush #7
    //   4031: iaload
    //   4032: bipush #16
    //   4034: iushr
    //   4035: i2b
    //   4036: bastore
    //   4037: aload #4
    //   4039: bipush #30
    //   4041: aload #8
    //   4043: bipush #7
    //   4045: iaload
    //   4046: bipush #8
    //   4048: iushr
    //   4049: i2b
    //   4050: bastore
    //   4051: aload #4
    //   4053: bipush #31
    //   4055: aload #8
    //   4057: bipush #7
    //   4059: iaload
    //   4060: i2b
    //   4061: bastore
    //   4062: new java/math/BigInteger
    //   4065: dup
    //   4066: aload #4
    //   4068: invokespecial <init> : ([B)V
    //   4071: invokevirtual abs : ()Ljava/math/BigInteger;
    //   4074: putstatic burp/Zl1u.Zq : Ljava/lang/Object;
    //   4077: new java/lang/StringBuilder
    //   4080: dup
    //   4081: invokespecial <init> : ()V
    //   4084: astore_3
    //   4085: iconst_0
    //   4086: istore #4
    //   4088: iload #4
    //   4090: bipush #32
    //   4092: if_icmpge -> 5427
    //   4095: iload #4
    //   4097: tableswitch default -> 5420, 0 -> 4240, 1 -> 4277, 2 -> 4314, 3 -> 4351, 4 -> 4388, 5 -> 4425, 6 -> 4462, 7 -> 4499, 8 -> 4536, 9 -> 4573, 10 -> 4610, 11 -> 4647, 12 -> 4684, 13 -> 4721, 14 -> 4758, 15 -> 4795, 16 -> 4832, 17 -> 4869, 18 -> 4906, 19 -> 4943, 20 -> 4980, 21 -> 5017, 22 -> 5054, 23 -> 5091, 24 -> 5128, 25 -> 5165, 26 -> 5202, 27 -> 5239, 28 -> 5276, 29 -> 5313, 30 -> 5350, 31 -> 5387
    //   4240: aload_3
    //   4241: getstatic burp/Zl_1.ZH : Ljava/lang/String;
    //   4244: getstatic burp/Zs9u.Zd : Ljava/lang/Object;
    //   4247: checkcast java/math/BigInteger
    //   4250: invokevirtual intValue : ()I
    //   4253: bipush #32
    //   4255: irem
    //   4256: invokestatic abs : (I)I
    //   4259: invokevirtual charAt : (I)C
    //   4262: invokevirtual append : (C)Ljava/lang/StringBuilder;
    //   4265: pop
    //   4266: iload_2
    //   4267: ifeq -> 5420
    //   4270: goto -> 4277
    //   4273: invokestatic a : (Ljava/lang/Throwable;)Ljava/lang/Throwable;
    //   4276: athrow
    //   4277: aload_3
    //   4278: getstatic burp/Zoa.ZF : Ljava/lang/String;
    //   4281: getstatic burp/Zty3.Zz : Ljava/lang/Object;
    //   4284: checkcast java/math/BigInteger
    //   4287: invokevirtual intValue : ()I
    //   4290: bipush #32
    //   4292: irem
    //   4293: invokestatic abs : (I)I
    //   4296: invokevirtual charAt : (I)C
    //   4299: invokevirtual append : (C)Ljava/lang/StringBuilder;
    //   4302: pop
    //   4303: iload_2
    //   4304: ifeq -> 5420
    //   4307: goto -> 4314
    //   4310: invokestatic a : (Ljava/lang/Throwable;)Ljava/lang/Throwable;
    //   4313: athrow
    //   4314: aload_3
    //   4315: getstatic burp/Zxn7.ZG : Ljava/lang/String;
    //   4318: getstatic burp/Zgwq.Ze : Ljava/lang/Object;
    //   4321: checkcast java/math/BigInteger
    //   4324: invokevirtual intValue : ()I
    //   4327: bipush #32
    //   4329: irem
    //   4330: invokestatic abs : (I)I
    //   4333: invokevirtual charAt : (I)C
    //   4336: invokevirtual append : (C)Ljava/lang/StringBuilder;
    //   4339: pop
    //   4340: iload_2
    //   4341: ifeq -> 5420
    //   4344: goto -> 4351
    //   4347: invokestatic a : (Ljava/lang/Throwable;)Ljava/lang/Throwable;
    //   4350: athrow
    //   4351: aload_3
    //   4352: getstatic burp/Zl_1.ZH : Ljava/lang/String;
    //   4355: getstatic burp/Zb_u.Zp : Ljava/lang/Object;
    //   4358: checkcast java/math/BigInteger
    //   4361: invokevirtual intValue : ()I
    //   4364: bipush #32
    //   4366: irem
    //   4367: invokestatic abs : (I)I
    //   4370: invokevirtual charAt : (I)C
    //   4373: invokevirtual append : (C)Ljava/lang/StringBuilder;
    //   4376: pop
    //   4377: iload_2
    //   4378: ifeq -> 5420
    //   4381: goto -> 4388
    //   4384: invokestatic a : (Ljava/lang/Throwable;)Ljava/lang/Throwable;
    //   4387: athrow
    //   4388: aload_3
    //   4389: getstatic burp/Zoa.ZF : Ljava/lang/String;
    //   4392: getstatic burp/Zebj.Zf : Ljava/lang/Object;
    //   4395: checkcast java/math/BigInteger
    //   4398: invokevirtual intValue : ()I
    //   4401: bipush #32
    //   4403: irem
    //   4404: invokestatic abs : (I)I
    //   4407: invokevirtual charAt : (I)C
    //   4410: invokevirtual append : (C)Ljava/lang/StringBuilder;
    //   4413: pop
    //   4414: iload_2
    //   4415: ifeq -> 5420
    //   4418: goto -> 4425
    //   4421: invokestatic a : (Ljava/lang/Throwable;)Ljava/lang/Throwable;
    //   4424: athrow
    //   4425: aload_3
    //   4426: getstatic burp/Zgd7.Zs : Ljava/lang/String;
    //   4429: getstatic burp/Zxd0.Za : Ljava/lang/Object;
    //   4432: checkcast java/math/BigInteger
    //   4435: invokevirtual intValue : ()I
    //   4438: bipush #32
    //   4440: irem
    //   4441: invokestatic abs : (I)I
    //   4444: invokevirtual charAt : (I)C
    //   4447: invokevirtual append : (C)Ljava/lang/StringBuilder;
    //   4450: pop
    //   4451: iload_2
    //   4452: ifeq -> 5420
    //   4455: goto -> 4462
    //   4458: invokestatic a : (Ljava/lang/Throwable;)Ljava/lang/Throwable;
    //   4461: athrow
    //   4462: aload_3
    //   4463: getstatic burp/Zzwl.Zy : Ljava/lang/String;
    //   4466: getstatic burp/Zejg.ZR : Ljava/lang/Object;
    //   4469: checkcast java/math/BigInteger
    //   4472: invokevirtual intValue : ()I
    //   4475: bipush #32
    //   4477: irem
    //   4478: invokestatic abs : (I)I
    //   4481: invokevirtual charAt : (I)C
    //   4484: invokevirtual append : (C)Ljava/lang/StringBuilder;
    //   4487: pop
    //   4488: iload_2
    //   4489: ifeq -> 5420
    //   4492: goto -> 4499
    //   4495: invokestatic a : (Ljava/lang/Throwable;)Ljava/lang/Throwable;
    //   4498: athrow
    //   4499: aload_3
    //   4500: getstatic burp/Zkvr.Zm : Ljava/lang/String;
    //   4503: getstatic burp/Zsej.ZT : Ljava/lang/Object;
    //   4506: checkcast java/math/BigInteger
    //   4509: invokevirtual intValue : ()I
    //   4512: bipush #32
    //   4514: irem
    //   4515: invokestatic abs : (I)I
    //   4518: invokevirtual charAt : (I)C
    //   4521: invokevirtual append : (C)Ljava/lang/StringBuilder;
    //   4524: pop
    //   4525: iload_2
    //   4526: ifeq -> 5420
    //   4529: goto -> 4536
    //   4532: invokestatic a : (Ljava/lang/Throwable;)Ljava/lang/Throwable;
    //   4535: athrow
    //   4536: aload_3
    //   4537: getstatic burp/Ze3t.ZG : Ljava/lang/String;
    //   4540: getstatic burp/Zly0.ZB : Ljava/lang/Object;
    //   4543: checkcast java/math/BigInteger
    //   4546: invokevirtual intValue : ()I
    //   4549: bipush #32
    //   4551: irem
    //   4552: invokestatic abs : (I)I
    //   4555: invokevirtual charAt : (I)C
    //   4558: invokevirtual append : (C)Ljava/lang/StringBuilder;
    //   4561: pop
    //   4562: iload_2
    //   4563: ifeq -> 5420
    //   4566: goto -> 4573
    //   4569: invokestatic a : (Ljava/lang/Throwable;)Ljava/lang/Throwable;
    //   4572: athrow
    //   4573: aload_3
    //   4574: getstatic burp/Zeyt.ZS : Ljava/lang/String;
    //   4577: getstatic burp/Zl1u.Zq : Ljava/lang/Object;
    //   4580: checkcast java/math/BigInteger
    //   4583: invokevirtual intValue : ()I
    //   4586: bipush #32
    //   4588: irem
    //   4589: invokestatic abs : (I)I
    //   4592: invokevirtual charAt : (I)C
    //   4595: invokevirtual append : (C)Ljava/lang/StringBuilder;
    //   4598: pop
    //   4599: iload_2
    //   4600: ifeq -> 5420
    //   4603: goto -> 4610
    //   4606: invokestatic a : (Ljava/lang/Throwable;)Ljava/lang/Throwable;
    //   4609: athrow
    //   4610: aload_3
    //   4611: getstatic burp/Zxrd.ZF : Ljava/lang/String;
    //   4614: getstatic burp/Zm06.ZU : Ljava/lang/Object;
    //   4617: checkcast java/math/BigInteger
    //   4620: invokevirtual intValue : ()I
    //   4623: bipush #32
    //   4625: irem
    //   4626: invokestatic abs : (I)I
    //   4629: invokevirtual charAt : (I)C
    //   4632: invokevirtual append : (C)Ljava/lang/StringBuilder;
    //   4635: pop
    //   4636: iload_2
    //   4637: ifeq -> 5420
    //   4640: goto -> 4647
    //   4643: invokestatic a : (Ljava/lang/Throwable;)Ljava/lang/Throwable;
    //   4646: athrow
    //   4647: aload_3
    //   4648: getstatic burp/Zlc5.Z_ : Ljava/lang/String;
    //   4651: getstatic burp/Zead.ZI : Ljava/lang/Object;
    //   4654: checkcast java/math/BigInteger
    //   4657: invokevirtual intValue : ()I
    //   4660: bipush #32
    //   4662: irem
    //   4663: invokestatic abs : (I)I
    //   4666: invokevirtual charAt : (I)C
    //   4669: invokevirtual append : (C)Ljava/lang/StringBuilder;
    //   4672: pop
    //   4673: iload_2
    //   4674: ifeq -> 5420
    //   4677: goto -> 4684
    //   4680: invokestatic a : (Ljava/lang/Throwable;)Ljava/lang/Throwable;
    //   4683: athrow
    //   4684: aload_3
    //   4685: getstatic burp/Zmiy.ZT : Ljava/lang/String;
    //   4688: getstatic burp/Zls_.ZR : Ljava/lang/Object;
    //   4691: checkcast java/math/BigInteger
    //   4694: invokevirtual intValue : ()I
    //   4697: bipush #32
    //   4699: irem
    //   4700: invokestatic abs : (I)I
    //   4703: invokevirtual charAt : (I)C
    //   4706: invokevirtual append : (C)Ljava/lang/StringBuilder;
    //   4709: pop
    //   4710: iload_2
    //   4711: ifeq -> 5420
    //   4714: goto -> 4721
    //   4717: invokestatic a : (Ljava/lang/Throwable;)Ljava/lang/Throwable;
    //   4720: athrow
    //   4721: aload_3
    //   4722: getstatic burp/Zlc5.Z_ : Ljava/lang/String;
    //   4725: getstatic burp/Zkvq.Zz : Ljava/lang/Object;
    //   4728: checkcast java/math/BigInteger
    //   4731: invokevirtual intValue : ()I
    //   4734: bipush #32
    //   4736: irem
    //   4737: invokestatic abs : (I)I
    //   4740: invokevirtual charAt : (I)C
    //   4743: invokevirtual append : (C)Ljava/lang/StringBuilder;
    //   4746: pop
    //   4747: iload_2
    //   4748: ifeq -> 5420
    //   4751: goto -> 4758
    //   4754: invokestatic a : (Ljava/lang/Throwable;)Ljava/lang/Throwable;
    //   4757: athrow
    //   4758: aload_3
    //   4759: getstatic burp/Zre1.ZA : Ljava/lang/String;
    //   4762: getstatic burp/Zxsb.ZN : Ljava/lang/Object;
    //   4765: checkcast java/math/BigInteger
    //   4768: invokevirtual intValue : ()I
    //   4771: bipush #32
    //   4773: irem
    //   4774: invokestatic abs : (I)I
    //   4777: invokevirtual charAt : (I)C
    //   4780: invokevirtual append : (C)Ljava/lang/StringBuilder;
    //   4783: pop
    //   4784: iload_2
    //   4785: ifeq -> 5420
    //   4788: goto -> 4795
    //   4791: invokestatic a : (Ljava/lang/Throwable;)Ljava/lang/Throwable;
    //   4794: athrow
    //   4795: aload_3
    //   4796: getstatic burp/Zl1u.ZO : Ljava/lang/String;
    //   4799: getstatic burp/Zzc7.ZG : Ljava/lang/Object;
    //   4802: checkcast java/math/BigInteger
    //   4805: invokevirtual intValue : ()I
    //   4808: bipush #32
    //   4810: irem
    //   4811: invokestatic abs : (I)I
    //   4814: invokevirtual charAt : (I)C
    //   4817: invokevirtual append : (C)Ljava/lang/StringBuilder;
    //   4820: pop
    //   4821: iload_2
    //   4822: ifeq -> 5420
    //   4825: goto -> 4832
    //   4828: invokestatic a : (Ljava/lang/Throwable;)Ljava/lang/Throwable;
    //   4831: athrow
    //   4832: aload_3
    //   4833: getstatic burp/Zzv.Zy : Ljava/lang/String;
    //   4836: getstatic burp/Ztid.ZL : Ljava/lang/Object;
    //   4839: checkcast java/math/BigInteger
    //   4842: invokevirtual intValue : ()I
    //   4845: bipush #32
    //   4847: irem
    //   4848: invokestatic abs : (I)I
    //   4851: invokevirtual charAt : (I)C
    //   4854: invokevirtual append : (C)Ljava/lang/StringBuilder;
    //   4857: pop
    //   4858: iload_2
    //   4859: ifeq -> 5420
    //   4862: goto -> 4869
    //   4865: invokestatic a : (Ljava/lang/Throwable;)Ljava/lang/Throwable;
    //   4868: athrow
    //   4869: aload_3
    //   4870: getstatic burp/Zty5.Za : Ljava/lang/String;
    //   4873: getstatic burp/Zko9.ZC : Ljava/lang/Object;
    //   4876: checkcast java/math/BigInteger
    //   4879: invokevirtual intValue : ()I
    //   4882: bipush #32
    //   4884: irem
    //   4885: invokestatic abs : (I)I
    //   4888: invokevirtual charAt : (I)C
    //   4891: invokevirtual append : (C)Ljava/lang/StringBuilder;
    //   4894: pop
    //   4895: iload_2
    //   4896: ifeq -> 5420
    //   4899: goto -> 4906
    //   4902: invokestatic a : (Ljava/lang/Throwable;)Ljava/lang/Throwable;
    //   4905: athrow
    //   4906: aload_3
    //   4907: getstatic burp/Zls_.Zn : Ljava/lang/String;
    //   4910: getstatic burp/Zsin.Za : Ljava/lang/Object;
    //   4913: checkcast java/math/BigInteger
    //   4916: invokevirtual intValue : ()I
    //   4919: bipush #32
    //   4921: irem
    //   4922: invokestatic abs : (I)I
    //   4925: invokevirtual charAt : (I)C
    //   4928: invokevirtual append : (C)Ljava/lang/StringBuilder;
    //   4931: pop
    //   4932: iload_2
    //   4933: ifeq -> 5420
    //   4936: goto -> 4943
    //   4939: invokestatic a : (Ljava/lang/Throwable;)Ljava/lang/Throwable;
    //   4942: athrow
    //   4943: aload_3
    //   4944: getstatic burp/Zgdj.Zt : Ljava/lang/String;
    //   4947: getstatic burp/Zz9p.Zw : Ljava/lang/Object;
    //   4950: checkcast java/math/BigInteger
    //   4953: invokevirtual intValue : ()I
    //   4956: bipush #32
    //   4958: irem
    //   4959: invokestatic abs : (I)I
    //   4962: invokevirtual charAt : (I)C
    //   4965: invokevirtual append : (C)Ljava/lang/StringBuilder;
    //   4968: pop
    //   4969: iload_2
    //   4970: ifeq -> 5420
    //   4973: goto -> 4980
    //   4976: invokestatic a : (Ljava/lang/Throwable;)Ljava/lang/Throwable;
    //   4979: athrow
    //   4980: aload_3
    //   4981: getstatic burp/Zzwl.Zy : Ljava/lang/String;
    //   4984: getstatic burp/Zty5.Zf : Ljava/lang/Object;
    //   4987: checkcast java/math/BigInteger
    //   4990: invokevirtual intValue : ()I
    //   4993: bipush #32
    //   4995: irem
    //   4996: invokestatic abs : (I)I
    //   4999: invokevirtual charAt : (I)C
    //   5002: invokevirtual append : (C)Ljava/lang/StringBuilder;
    //   5005: pop
    //   5006: iload_2
    //   5007: ifeq -> 5420
    //   5010: goto -> 5017
    //   5013: invokestatic a : (Ljava/lang/Throwable;)Ljava/lang/Throwable;
    //   5016: athrow
    //   5017: aload_3
    //   5018: getstatic burp/Zljx.ZD : Ljava/lang/String;
    //   5021: getstatic burp/Zsgj.ZK : Ljava/lang/Object;
    //   5024: checkcast java/math/BigInteger
    //   5027: invokevirtual intValue : ()I
    //   5030: bipush #32
    //   5032: irem
    //   5033: invokestatic abs : (I)I
    //   5036: invokevirtual charAt : (I)C
    //   5039: invokevirtual append : (C)Ljava/lang/StringBuilder;
    //   5042: pop
    //   5043: iload_2
    //   5044: ifeq -> 5420
    //   5047: goto -> 5054
    //   5050: invokestatic a : (Ljava/lang/Throwable;)Ljava/lang/Throwable;
    //   5053: athrow
    //   5054: aload_3
    //   5055: getstatic burp/Zlyf.ZU : Ljava/lang/String;
    //   5058: getstatic burp/Zejg.ZR : Ljava/lang/Object;
    //   5061: checkcast java/math/BigInteger
    //   5064: invokevirtual intValue : ()I
    //   5067: bipush #32
    //   5069: irem
    //   5070: invokestatic abs : (I)I
    //   5073: invokevirtual charAt : (I)C
    //   5076: invokevirtual append : (C)Ljava/lang/StringBuilder;
    //   5079: pop
    //   5080: iload_2
    //   5081: ifeq -> 5420
    //   5084: goto -> 5091
    //   5087: invokestatic a : (Ljava/lang/Throwable;)Ljava/lang/Throwable;
    //   5090: athrow
    //   5091: aload_3
    //   5092: getstatic burp/Zei_.ZZ : Ljava/lang/String;
    //   5095: getstatic burp/Zgny.ZR : Ljava/lang/Object;
    //   5098: checkcast java/math/BigInteger
    //   5101: invokevirtual intValue : ()I
    //   5104: bipush #32
    //   5106: irem
    //   5107: invokestatic abs : (I)I
    //   5110: invokevirtual charAt : (I)C
    //   5113: invokevirtual append : (C)Ljava/lang/StringBuilder;
    //   5116: pop
    //   5117: iload_2
    //   5118: ifeq -> 5420
    //   5121: goto -> 5128
    //   5124: invokestatic a : (Ljava/lang/Throwable;)Ljava/lang/Throwable;
    //   5127: athrow
    //   5128: aload_3
    //   5129: getstatic burp/Zmjr.Zc : Ljava/lang/String;
    //   5132: getstatic burp/Zl_1.ZL : Ljava/lang/Object;
    //   5135: checkcast java/math/BigInteger
    //   5138: invokevirtual intValue : ()I
    //   5141: bipush #32
    //   5143: irem
    //   5144: invokestatic abs : (I)I
    //   5147: invokevirtual charAt : (I)C
    //   5150: invokevirtual append : (C)Ljava/lang/StringBuilder;
    //   5153: pop
    //   5154: iload_2
    //   5155: ifeq -> 5420
    //   5158: goto -> 5165
    //   5161: invokestatic a : (Ljava/lang/Throwable;)Ljava/lang/Throwable;
    //   5164: athrow
    //   5165: aload_3
    //   5166: getstatic burp/Zxtn.Zu : Ljava/lang/String;
    //   5169: getstatic burp/Ztte.ZR : Ljava/lang/Object;
    //   5172: checkcast java/math/BigInteger
    //   5175: invokevirtual intValue : ()I
    //   5178: bipush #32
    //   5180: irem
    //   5181: invokestatic abs : (I)I
    //   5184: invokevirtual charAt : (I)C
    //   5187: invokevirtual append : (C)Ljava/lang/StringBuilder;
    //   5190: pop
    //   5191: iload_2
    //   5192: ifeq -> 5420
    //   5195: goto -> 5202
    //   5198: invokestatic a : (Ljava/lang/Throwable;)Ljava/lang/Throwable;
    //   5201: athrow
    //   5202: aload_3
    //   5203: getstatic burp/Zoa.ZF : Ljava/lang/String;
    //   5206: getstatic burp/Zs_.Zs : Ljava/lang/Object;
    //   5209: checkcast java/math/BigInteger
    //   5212: invokevirtual intValue : ()I
    //   5215: bipush #32
    //   5217: irem
    //   5218: invokestatic abs : (I)I
    //   5221: invokevirtual charAt : (I)C
    //   5224: invokevirtual append : (C)Ljava/lang/StringBuilder;
    //   5227: pop
    //   5228: iload_2
    //   5229: ifeq -> 5420
    //   5232: goto -> 5239
    //   5235: invokestatic a : (Ljava/lang/Throwable;)Ljava/lang/Throwable;
    //   5238: athrow
    //   5239: aload_3
    //   5240: getstatic burp/Zkv2.Z_ : Ljava/lang/String;
    //   5243: getstatic burp/Zxsb.ZN : Ljava/lang/Object;
    //   5246: checkcast java/math/BigInteger
    //   5249: invokevirtual intValue : ()I
    //   5252: bipush #32
    //   5254: irem
    //   5255: invokestatic abs : (I)I
    //   5258: invokevirtual charAt : (I)C
    //   5261: invokevirtual append : (C)Ljava/lang/StringBuilder;
    //   5264: pop
    //   5265: iload_2
    //   5266: ifeq -> 5420
    //   5269: goto -> 5276
    //   5272: invokestatic a : (Ljava/lang/Throwable;)Ljava/lang/Throwable;
    //   5275: athrow
    //   5276: aload_3
    //   5277: getstatic burp/Zejg.ZP : Ljava/lang/String;
    //   5280: getstatic burp/Zz9p.Zw : Ljava/lang/Object;
    //   5283: checkcast java/math/BigInteger
    //   5286: invokevirtual intValue : ()I
    //   5289: bipush #32
    //   5291: irem
    //   5292: invokestatic abs : (I)I
    //   5295: invokevirtual charAt : (I)C
    //   5298: invokevirtual append : (C)Ljava/lang/StringBuilder;
    //   5301: pop
    //   5302: iload_2
    //   5303: ifeq -> 5420
    //   5306: goto -> 5313
    //   5309: invokestatic a : (Ljava/lang/Throwable;)Ljava/lang/Throwable;
    //   5312: athrow
    //   5313: aload_3
    //   5314: getstatic burp/Zxoa.Z_ : Ljava/lang/String;
    //   5317: getstatic burp/Zei_.Za : Ljava/lang/Object;
    //   5320: checkcast java/math/BigInteger
    //   5323: invokevirtual intValue : ()I
    //   5326: bipush #32
    //   5328: irem
    //   5329: invokestatic abs : (I)I
    //   5332: invokevirtual charAt : (I)C
    //   5335: invokevirtual append : (C)Ljava/lang/StringBuilder;
    //   5338: pop
    //   5339: iload_2
    //   5340: ifeq -> 5420
    //   5343: goto -> 5350
    //   5346: invokestatic a : (Ljava/lang/Throwable;)Ljava/lang/Throwable;
    //   5349: athrow
    //   5350: aload_3
    //   5351: getstatic burp/Zz0j.Zf : Ljava/lang/String;
    //   5354: getstatic burp/Zgkl.ZK : Ljava/lang/Object;
    //   5357: checkcast java/math/BigInteger
    //   5360: invokevirtual intValue : ()I
    //   5363: bipush #32
    //   5365: irem
    //   5366: invokestatic abs : (I)I
    //   5369: invokevirtual charAt : (I)C
    //   5372: invokevirtual append : (C)Ljava/lang/StringBuilder;
    //   5375: pop
    //   5376: iload_2
    //   5377: ifeq -> 5420
    //   5380: goto -> 5387
    //   5383: invokestatic a : (Ljava/lang/Throwable;)Ljava/lang/Throwable;
    //   5386: athrow
    //   5387: aload_3
    //   5388: getstatic burp/Zejg.ZP : Ljava/lang/String;
    //   5391: getstatic burp/Zttj.ZF : Ljava/lang/Object;
    //   5394: checkcast java/math/BigInteger
    //   5397: invokevirtual intValue : ()I
    //   5400: bipush #32
    //   5402: irem
    //   5403: invokestatic abs : (I)I
    //   5406: invokevirtual charAt : (I)C
    //   5409: invokevirtual append : (C)Ljava/lang/StringBuilder;
    //   5412: pop
    //   5413: goto -> 5420
    //   5416: invokestatic a : (Ljava/lang/Throwable;)Ljava/lang/Throwable;
    //   5419: athrow
    //   5420: iinc #4, 1
    //   5423: iload_2
    //   5424: ifeq -> 4088
    //   5427: aload_3
    //   5428: invokevirtual toString : ()Ljava/lang/String;
    //   5431: putstatic burp/Zlc5.Z_ : Ljava/lang/String;
    //   5434: sipush #25264
    //   5437: sipush #-15193
    //   5440: invokestatic a : (II)Ljava/lang/String;
    //   5443: iconst_1
    //   5444: ldc burp/Zebu
    //   5446: invokevirtual getClassLoader : ()Ljava/lang/ClassLoader;
    //   5449: invokestatic forName : (Ljava/lang/String;ZLjava/lang/ClassLoader;)Ljava/lang/Class;
    //   5452: invokevirtual getDeclaredFields : ()[Ljava/lang/reflect/Field;
    //   5455: astore #4
    //   5457: aload #4
    //   5459: arraylength
    //   5460: istore #5
    //   5462: iconst_0
    //   5463: istore #6
    //   5465: iload #6
    //   5467: iload #5
    //   5469: if_icmpge -> 5607
    //   5472: aload #4
    //   5474: iload #6
    //   5476: aaload
    //   5477: astore #7
    //   5479: aload #7
    //   5481: invokevirtual getModifiers : ()I
    //   5484: invokestatic isStatic : (I)Z
    //   5487: ifne -> 5497
    //   5490: goto -> 5600
    //   5493: invokestatic a : (Ljava/lang/Throwable;)Ljava/lang/Throwable;
    //   5496: athrow
    //   5497: aload #7
    //   5499: invokevirtual getType : ()Ljava/lang/Class;
    //   5502: astore #8
    //   5504: aload #8
    //   5506: ifnull -> 5587
    //   5509: aload #8
    //   5511: invokevirtual isPrimitive : ()Z
    //   5514: ifne -> 5587
    //   5517: goto -> 5524
    //   5520: invokestatic a : (Ljava/lang/Throwable;)Ljava/lang/Throwable;
    //   5523: athrow
    //   5524: aload #8
    //   5526: invokevirtual getPackage : ()Ljava/lang/Package;
    //   5529: ifnull -> 5587
    //   5532: goto -> 5539
    //   5535: invokestatic a : (Ljava/lang/Throwable;)Ljava/lang/Throwable;
    //   5538: athrow
    //   5539: aload #8
    //   5541: invokevirtual getPackage : ()Ljava/lang/Package;
    //   5544: invokevirtual getName : ()Ljava/lang/String;
    //   5547: ifnull -> 5587
    //   5550: goto -> 5557
    //   5553: invokestatic a : (Ljava/lang/Throwable;)Ljava/lang/Throwable;
    //   5556: athrow
    //   5557: aload #8
    //   5559: invokevirtual getPackage : ()Ljava/lang/Package;
    //   5562: invokevirtual getName : ()Ljava/lang/String;
    //   5565: sipush #25265
    //   5568: sipush #-5718
    //   5571: invokestatic a : (II)Ljava/lang/String;
    //   5574: invokevirtual startsWith : (Ljava/lang/String;)Z
    //   5577: ifne -> 5587
    //   5580: goto -> 5587
    //   5583: invokestatic a : (Ljava/lang/Throwable;)Ljava/lang/Throwable;
    //   5586: athrow
    //   5587: aload #7
    //   5589: iconst_1
    //   5590: invokevirtual setAccessible : (Z)V
    //   5593: aload #7
    //   5595: aconst_null
    //   5596: invokevirtual get : (Ljava/lang/Object;)Ljava/lang/Object;
    //   5599: pop
    //   5600: iinc #6, 1
    //   5603: iload_2
    //   5604: ifeq -> 5465
    //   5607: sipush #25267
    //   5610: sipush #11848
    //   5613: invokestatic a : (II)Ljava/lang/String;
    //   5616: invokestatic forName : (Ljava/lang/String;)Ljava/lang/Class;
    //   5619: invokevirtual getDeclaredMethods : ()[Ljava/lang/reflect/Method;
    //   5622: astore #4
    //   5624: aload #4
    //   5626: arraylength
    //   5627: istore #5
    //   5629: iconst_0
    //   5630: istore #6
    //   5632: iload #6
    //   5634: iload #5
    //   5636: if_icmpge -> 5769
    //   5639: aload #4
    //   5641: iload #6
    //   5643: aaload
    //   5644: astore #7
    //   5646: aload #7
    //   5648: invokevirtual getParameterTypes : ()[Ljava/lang/Class;
    //   5651: pop
    //   5652: aload #7
    //   5654: invokevirtual getModifiers : ()I
    //   5657: invokestatic isStatic : (I)Z
    //   5660: ifeq -> 5755
    //   5663: aload #7
    //   5665: invokevirtual getParameterTypes : ()[Ljava/lang/Class;
    //   5668: arraylength
    //   5669: iconst_2
    //   5670: if_icmpne -> 5755
    //   5673: goto -> 5680
    //   5676: invokestatic a : (Ljava/lang/Throwable;)Ljava/lang/Throwable;
    //   5679: athrow
    //   5680: aload #7
    //   5682: invokevirtual getReturnType : ()Ljava/lang/Class;
    //   5685: getstatic java/lang/Void.TYPE : Ljava/lang/Class;
    //   5688: invokevirtual equals : (Ljava/lang/Object;)Z
    //   5691: ifeq -> 5755
    //   5694: goto -> 5701
    //   5697: invokestatic a : (Ljava/lang/Throwable;)Ljava/lang/Throwable;
    //   5700: athrow
    //   5701: aload #7
    //   5703: iconst_1
    //   5704: invokevirtual setAccessible : (Z)V
    //   5707: aload #7
    //   5709: aconst_null
    //   5710: iconst_2
    //   5711: anewarray java/lang/Object
    //   5714: dup
    //   5715: iconst_0
    //   5716: aload_0
    //   5717: aastore
    //   5718: dup
    //   5719: iconst_1
    //   5720: aload_1
    //   5721: ifnonnull -> 5739
    //   5724: goto -> 5731
    //   5727: invokestatic a : (Ljava/lang/Throwable;)Ljava/lang/Throwable;
    //   5730: athrow
    //   5731: aload_1
    //   5732: goto -> 5746
    //   5735: invokestatic a : (Ljava/lang/Throwable;)Ljava/lang/Throwable;
    //   5738: athrow
    //   5739: aload_1
    //   5740: checkcast [B
    //   5743: invokevirtual clone : ()Ljava/lang/Object;
    //   5746: aastore
    //   5747: invokevirtual invoke : (Ljava/lang/Object;[Ljava/lang/Object;)Ljava/lang/Object;
    //   5750: pop
    //   5751: iload_2
    //   5752: ifeq -> 5769
    //   5755: iinc #6, 1
    //   5758: iload_2
    //   5759: ifeq -> 5632
    //   5762: goto -> 5769
    //   5765: invokestatic a : (Ljava/lang/Throwable;)Ljava/lang/Throwable;
    //   5768: athrow
    //   5769: getstatic burp/Zm06.ZU : Ljava/lang/Object;
    //   5772: checkcast java/math/BigInteger
    //   5775: invokevirtual toByteArray : ()[B
    //   5778: astore #4
    //   5780: bipush #64
    //   5782: newarray byte
    //   5784: dup
    //   5785: iconst_0
    //   5786: bipush #-128
    //   5788: bastore
    //   5789: dup
    //   5790: iconst_1
    //   5791: iconst_0
    //   5792: bastore
    //   5793: dup
    //   5794: iconst_2
    //   5795: iconst_0
    //   5796: bastore
    //   5797: dup
    //   5798: iconst_3
    //   5799: iconst_0
    //   5800: bastore
    //   5801: dup
    //   5802: iconst_4
    //   5803: iconst_0
    //   5804: bastore
    //   5805: dup
    //   5806: iconst_5
    //   5807: iconst_0
    //   5808: bastore
    //   5809: dup
    //   5810: bipush #6
    //   5812: iconst_0
    //   5813: bastore
    //   5814: dup
    //   5815: bipush #7
    //   5817: iconst_0
    //   5818: bastore
    //   5819: dup
    //   5820: bipush #8
    //   5822: iconst_0
    //   5823: bastore
    //   5824: dup
    //   5825: bipush #9
    //   5827: iconst_0
    //   5828: bastore
    //   5829: dup
    //   5830: bipush #10
    //   5832: iconst_0
    //   5833: bastore
    //   5834: dup
    //   5835: bipush #11
    //   5837: iconst_0
    //   5838: bastore
    //   5839: dup
    //   5840: bipush #12
    //   5842: iconst_0
    //   5843: bastore
    //   5844: dup
    //   5845: bipush #13
    //   5847: iconst_0
    //   5848: bastore
    //   5849: dup
    //   5850: bipush #14
    //   5852: iconst_0
    //   5853: bastore
    //   5854: dup
    //   5855: bipush #15
    //   5857: iconst_0
    //   5858: bastore
    //   5859: dup
    //   5860: bipush #16
    //   5862: iconst_0
    //   5863: bastore
    //   5864: dup
    //   5865: bipush #17
    //   5867: iconst_0
    //   5868: bastore
    //   5869: dup
    //   5870: bipush #18
    //   5872: iconst_0
    //   5873: bastore
    //   5874: dup
    //   5875: bipush #19
    //   5877: iconst_0
    //   5878: bastore
    //   5879: dup
    //   5880: bipush #20
    //   5882: iconst_0
    //   5883: bastore
    //   5884: dup
    //   5885: bipush #21
    //   5887: iconst_0
    //   5888: bastore
    //   5889: dup
    //   5890: bipush #22
    //   5892: iconst_0
    //   5893: bastore
    //   5894: dup
    //   5895: bipush #23
    //   5897: iconst_0
    //   5898: bastore
    //   5899: dup
    //   5900: bipush #24
    //   5902: iconst_0
    //   5903: bastore
    //   5904: dup
    //   5905: bipush #25
    //   5907: iconst_0
    //   5908: bastore
    //   5909: dup
    //   5910: bipush #26
    //   5912: iconst_0
    //   5913: bastore
    //   5914: dup
    //   5915: bipush #27
    //   5917: iconst_0
    //   5918: bastore
    //   5919: dup
    //   5920: bipush #28
    //   5922: iconst_0
    //   5923: bastore
    //   5924: dup
    //   5925: bipush #29
    //   5927: iconst_0
    //   5928: bastore
    //   5929: dup
    //   5930: bipush #30
    //   5932: iconst_0
    //   5933: bastore
    //   5934: dup
    //   5935: bipush #31
    //   5937: iconst_0
    //   5938: bastore
    //   5939: dup
    //   5940: bipush #32
    //   5942: iconst_0
    //   5943: bastore
    //   5944: dup
    //   5945: bipush #33
    //   5947: iconst_0
    //   5948: bastore
    //   5949: dup
    //   5950: bipush #34
    //   5952: iconst_0
    //   5953: bastore
    //   5954: dup
    //   5955: bipush #35
    //   5957: iconst_0
    //   5958: bastore
    //   5959: dup
    //   5960: bipush #36
    //   5962: iconst_0
    //   5963: bastore
    //   5964: dup
    //   5965: bipush #37
    //   5967: iconst_0
    //   5968: bastore
    //   5969: dup
    //   5970: bipush #38
    //   5972: iconst_0
    //   5973: bastore
    //   5974: dup
    //   5975: bipush #39
    //   5977: iconst_0
    //   5978: bastore
    //   5979: dup
    //   5980: bipush #40
    //   5982: iconst_0
    //   5983: bastore
    //   5984: dup
    //   5985: bipush #41
    //   5987: iconst_0
    //   5988: bastore
    //   5989: dup
    //   5990: bipush #42
    //   5992: iconst_0
    //   5993: bastore
    //   5994: dup
    //   5995: bipush #43
    //   5997: iconst_0
    //   5998: bastore
    //   5999: dup
    //   6000: bipush #44
    //   6002: iconst_0
    //   6003: bastore
    //   6004: dup
    //   6005: bipush #45
    //   6007: iconst_0
    //   6008: bastore
    //   6009: dup
    //   6010: bipush #46
    //   6012: iconst_0
    //   6013: bastore
    //   6014: dup
    //   6015: bipush #47
    //   6017: iconst_0
    //   6018: bastore
    //   6019: dup
    //   6020: bipush #48
    //   6022: iconst_0
    //   6023: bastore
    //   6024: dup
    //   6025: bipush #49
    //   6027: iconst_0
    //   6028: bastore
    //   6029: dup
    //   6030: bipush #50
    //   6032: iconst_0
    //   6033: bastore
    //   6034: dup
    //   6035: bipush #51
    //   6037: iconst_0
    //   6038: bastore
    //   6039: dup
    //   6040: bipush #52
    //   6042: iconst_0
    //   6043: bastore
    //   6044: dup
    //   6045: bipush #53
    //   6047: iconst_0
    //   6048: bastore
    //   6049: dup
    //   6050: bipush #54
    //   6052: iconst_0
    //   6053: bastore
    //   6054: dup
    //   6055: bipush #55
    //   6057: iconst_0
    //   6058: bastore
    //   6059: dup
    //   6060: bipush #56
    //   6062: iconst_0
    //   6063: bastore
    //   6064: dup
    //   6065: bipush #57
    //   6067: iconst_0
    //   6068: bastore
    //   6069: dup
    //   6070: bipush #58
    //   6072: iconst_0
    //   6073: bastore
    //   6074: dup
    //   6075: bipush #59
    //   6077: iconst_0
    //   6078: bastore
    //   6079: dup
    //   6080: bipush #60
    //   6082: iconst_0
    //   6083: bastore
    //   6084: dup
    //   6085: bipush #61
    //   6087: iconst_0
    //   6088: bastore
    //   6089: dup
    //   6090: bipush #62
    //   6092: iconst_0
    //   6093: bastore
    //   6094: dup
    //   6095: bipush #63
    //   6097: iconst_0
    //   6098: bastore
    //   6099: astore #6
    //   6101: bipush #64
    //   6103: newarray int
    //   6105: dup
    //   6106: iconst_0
    //   6107: ldc 1116352408
    //   6109: iastore
    //   6110: dup
    //   6111: iconst_1
    //   6112: ldc 1899447441
    //   6114: iastore
    //   6115: dup
    //   6116: iconst_2
    //   6117: ldc -1245643825
    //   6119: iastore
    //   6120: dup
    //   6121: iconst_3
    //   6122: ldc -373957723
    //   6124: iastore
    //   6125: dup
    //   6126: iconst_4
    //   6127: ldc 961987163
    //   6129: iastore
    //   6130: dup
    //   6131: iconst_5
    //   6132: ldc 1508970993
    //   6134: iastore
    //   6135: dup
    //   6136: bipush #6
    //   6138: ldc -1841331548
    //   6140: iastore
    //   6141: dup
    //   6142: bipush #7
    //   6144: ldc -1424204075
    //   6146: iastore
    //   6147: dup
    //   6148: bipush #8
    //   6150: ldc -670586216
    //   6152: iastore
    //   6153: dup
    //   6154: bipush #9
    //   6156: ldc 310598401
    //   6158: iastore
    //   6159: dup
    //   6160: bipush #10
    //   6162: ldc 607225278
    //   6164: iastore
    //   6165: dup
    //   6166: bipush #11
    //   6168: ldc 1426881987
    //   6170: iastore
    //   6171: dup
    //   6172: bipush #12
    //   6174: ldc 1925078388
    //   6176: iastore
    //   6177: dup
    //   6178: bipush #13
    //   6180: ldc -2132889090
    //   6182: iastore
    //   6183: dup
    //   6184: bipush #14
    //   6186: ldc -1680079193
    //   6188: iastore
    //   6189: dup
    //   6190: bipush #15
    //   6192: ldc -1046744716
    //   6194: iastore
    //   6195: dup
    //   6196: bipush #16
    //   6198: ldc -459576895
    //   6200: iastore
    //   6201: dup
    //   6202: bipush #17
    //   6204: ldc -272742522
    //   6206: iastore
    //   6207: dup
    //   6208: bipush #18
    //   6210: ldc 264347078
    //   6212: iastore
    //   6213: dup
    //   6214: bipush #19
    //   6216: ldc 604807628
    //   6218: iastore
    //   6219: dup
    //   6220: bipush #20
    //   6222: ldc 770255983
    //   6224: iastore
    //   6225: dup
    //   6226: bipush #21
    //   6228: ldc 1249150122
    //   6230: iastore
    //   6231: dup
    //   6232: bipush #22
    //   6234: ldc 1555081692
    //   6236: iastore
    //   6237: dup
    //   6238: bipush #23
    //   6240: ldc 1996064986
    //   6242: iastore
    //   6243: dup
    //   6244: bipush #24
    //   6246: ldc -1740746414
    //   6248: iastore
    //   6249: dup
    //   6250: bipush #25
    //   6252: ldc -1473132947
    //   6254: iastore
    //   6255: dup
    //   6256: bipush #26
    //   6258: ldc -1341970488
    //   6260: iastore
    //   6261: dup
    //   6262: bipush #27
    //   6264: ldc -1084653625
    //   6266: iastore
    //   6267: dup
    //   6268: bipush #28
    //   6270: ldc -958395405
    //   6272: iastore
    //   6273: dup
    //   6274: bipush #29
    //   6276: ldc -710438585
    //   6278: iastore
    //   6279: dup
    //   6280: bipush #30
    //   6282: ldc 113926993
    //   6284: iastore
    //   6285: dup
    //   6286: bipush #31
    //   6288: ldc 338241895
    //   6290: iastore
    //   6291: dup
    //   6292: bipush #32
    //   6294: ldc 666307205
    //   6296: iastore
    //   6297: dup
    //   6298: bipush #33
    //   6300: ldc 773529912
    //   6302: iastore
    //   6303: dup
    //   6304: bipush #34
    //   6306: ldc 1294757372
    //   6308: iastore
    //   6309: dup
    //   6310: bipush #35
    //   6312: ldc 1396182291
    //   6314: iastore
    //   6315: dup
    //   6316: bipush #36
    //   6318: ldc 1695183700
    //   6320: iastore
    //   6321: dup
    //   6322: bipush #37
    //   6324: ldc 1986661051
    //   6326: iastore
    //   6327: dup
    //   6328: bipush #38
    //   6330: ldc -2117940946
    //   6332: iastore
    //   6333: dup
    //   6334: bipush #39
    //   6336: ldc -1838011259
    //   6338: iastore
    //   6339: dup
    //   6340: bipush #40
    //   6342: ldc -1564481375
    //   6344: iastore
    //   6345: dup
    //   6346: bipush #41
    //   6348: ldc -1474664885
    //   6350: iastore
    //   6351: dup
    //   6352: bipush #42
    //   6354: ldc -1035236496
    //   6356: iastore
    //   6357: dup
    //   6358: bipush #43
    //   6360: ldc -949202525
    //   6362: iastore
    //   6363: dup
    //   6364: bipush #44
    //   6366: ldc -778901479
    //   6368: iastore
    //   6369: dup
    //   6370: bipush #45
    //   6372: ldc -694614492
    //   6374: iastore
    //   6375: dup
    //   6376: bipush #46
    //   6378: ldc -200395387
    //   6380: iastore
    //   6381: dup
    //   6382: bipush #47
    //   6384: ldc 275423344
    //   6386: iastore
    //   6387: dup
    //   6388: bipush #48
    //   6390: ldc 430227734
    //   6392: iastore
    //   6393: dup
    //   6394: bipush #49
    //   6396: ldc 506948616
    //   6398: iastore
    //   6399: dup
    //   6400: bipush #50
    //   6402: ldc 659060556
    //   6404: iastore
    //   6405: dup
    //   6406: bipush #51
    //   6408: ldc 883997877
    //   6410: iastore
    //   6411: dup
    //   6412: bipush #52
    //   6414: ldc 958139571
    //   6416: iastore
    //   6417: dup
    //   6418: bipush #53
    //   6420: ldc 1322822218
    //   6422: iastore
    //   6423: dup
    //   6424: bipush #54
    //   6426: ldc 1537002063
    //   6428: iastore
    //   6429: dup
    //   6430: bipush #55
    //   6432: ldc 1747873779
    //   6434: iastore
    //   6435: dup
    //   6436: bipush #56
    //   6438: ldc 1955562222
    //   6440: iastore
    //   6441: dup
    //   6442: bipush #57
    //   6444: ldc 2024104815
    //   6446: iastore
    //   6447: dup
    //   6448: bipush #58
    //   6450: ldc -2067236844
    //   6452: iastore
    //   6453: dup
    //   6454: bipush #59
    //   6456: ldc -1933114872
    //   6458: iastore
    //   6459: dup
    //   6460: bipush #60
    //   6462: ldc -1866530822
    //   6464: iastore
    //   6465: dup
    //   6466: bipush #61
    //   6468: ldc -1538233109
    //   6470: iastore
    //   6471: dup
    //   6472: bipush #62
    //   6474: ldc -1090935817
    //   6476: iastore
    //   6477: dup
    //   6478: bipush #63
    //   6480: ldc -965641998
    //   6482: iastore
    //   6483: astore #7
    //   6485: iconst_2
    //   6486: newarray int
    //   6488: dup
    //   6489: iconst_0
    //   6490: iconst_0
    //   6491: iastore
    //   6492: dup
    //   6493: iconst_1
    //   6494: iconst_0
    //   6495: iastore
    //   6496: astore #8
    //   6498: bipush #8
    //   6500: newarray int
    //   6502: dup
    //   6503: iconst_0
    //   6504: ldc 1779033703
    //   6506: iastore
    //   6507: dup
    //   6508: iconst_1
    //   6509: ldc -1150833019
    //   6511: iastore
    //   6512: dup
    //   6513: iconst_2
    //   6514: ldc 1013904242
    //   6516: iastore
    //   6517: dup
    //   6518: iconst_3
    //   6519: ldc -1521486534
    //   6521: iastore
    //   6522: dup
    //   6523: iconst_4
    //   6524: ldc 1359893119
    //   6526: iastore
    //   6527: dup
    //   6528: iconst_5
    //   6529: ldc -1694144372
    //   6531: iastore
    //   6532: dup
    //   6533: bipush #6
    //   6535: ldc 528734635
    //   6537: iastore
    //   6538: dup
    //   6539: bipush #7
    //   6541: ldc 1541459225
    //   6543: iastore
    //   6544: astore #9
    //   6546: bipush #64
    //   6548: newarray byte
    //   6550: astore #10
    //   6552: bipush #64
    //   6554: newarray byte
    //   6556: astore #11
    //   6558: aload #4
    //   6560: arraylength
    //   6561: istore #12
    //   6563: aload #8
    //   6565: iconst_0
    //   6566: iaload
    //   6567: bipush #63
    //   6569: iand
    //   6570: istore #13
    //   6572: aload #8
    //   6574: iconst_0
    //   6575: dup2
    //   6576: iaload
    //   6577: iload #12
    //   6579: iadd
    //   6580: iastore
    //   6581: aload #8
    //   6583: iconst_0
    //   6584: dup2
    //   6585: iaload
    //   6586: iconst_m1
    //   6587: iand
    //   6588: iastore
    //   6589: aload #8
    //   6591: iconst_0
    //   6592: iaload
    //   6593: iload #12
    //   6595: if_icmpge -> 6613
    //   6598: aload #8
    //   6600: iconst_1
    //   6601: dup2
    //   6602: iaload
    //   6603: iconst_1
    //   6604: iadd
    //   6605: iastore
    //   6606: goto -> 6613
    //   6609: invokestatic a : (Ljava/lang/Throwable;)Ljava/lang/Throwable;
    //   6612: athrow
    //   6613: iconst_0
    //   6614: istore #14
    //   6616: iload #12
    //   6618: bipush #64
    //   6620: if_icmplt -> 7230
    //   6623: iconst_0
    //   6624: istore #15
    //   6626: iload #15
    //   6628: bipush #64
    //   6630: if_icmpge -> 6653
    //   6633: aload #11
    //   6635: iload #15
    //   6637: aload #4
    //   6639: iload #14
    //   6641: iload #15
    //   6643: iadd
    //   6644: baload
    //   6645: bastore
    //   6646: iinc #15, 1
    //   6649: iload_2
    //   6650: ifeq -> 6626
    //   6653: bipush #64
    //   6655: newarray int
    //   6657: astore #15
    //   6659: bipush #8
    //   6661: newarray int
    //   6663: astore #16
    //   6665: iconst_0
    //   6666: istore #17
    //   6668: iload #17
    //   6670: bipush #8
    //   6672: if_icmpge -> 6692
    //   6675: aload #16
    //   6677: iload #17
    //   6679: aload #9
    //   6681: iload #17
    //   6683: iaload
    //   6684: iastore
    //   6685: iinc #17, 1
    //   6688: iload_2
    //   6689: ifeq -> 6668
    //   6692: iconst_0
    //   6693: istore #17
    //   6695: iload #17
    //   6697: bipush #64
    //   6699: if_icmpge -> 7190
    //   6702: iload #17
    //   6704: bipush #16
    //   6706: if_icmpge -> 6787
    //   6709: aload #15
    //   6711: iload #17
    //   6713: aload #11
    //   6715: iconst_4
    //   6716: iload #17
    //   6718: imul
    //   6719: baload
    //   6720: sipush #255
    //   6723: iand
    //   6724: bipush #24
    //   6726: ishl
    //   6727: aload #11
    //   6729: iconst_4
    //   6730: iload #17
    //   6732: imul
    //   6733: iconst_1
    //   6734: iadd
    //   6735: baload
    //   6736: sipush #255
    //   6739: iand
    //   6740: bipush #16
    //   6742: ishl
    //   6743: ior
    //   6744: aload #11
    //   6746: iconst_4
    //   6747: iload #17
    //   6749: imul
    //   6750: iconst_2
    //   6751: iadd
    //   6752: baload
    //   6753: sipush #255
    //   6756: iand
    //   6757: bipush #8
    //   6759: ishl
    //   6760: ior
    //   6761: aload #11
    //   6763: iconst_4
    //   6764: iload #17
    //   6766: imul
    //   6767: iconst_3
    //   6768: iadd
    //   6769: baload
    //   6770: sipush #255
    //   6773: iand
    //   6774: ior
    //   6775: iastore
    //   6776: iload_2
    //   6777: ifeq -> 6930
    //   6780: goto -> 6787
    //   6783: invokestatic a : (Ljava/lang/Throwable;)Ljava/lang/Throwable;
    //   6786: athrow
    //   6787: aload #15
    //   6789: iload #17
    //   6791: aload #15
    //   6793: iload #17
    //   6795: iconst_2
    //   6796: isub
    //   6797: iaload
    //   6798: bipush #17
    //   6800: iushr
    //   6801: aload #15
    //   6803: iload #17
    //   6805: iconst_2
    //   6806: isub
    //   6807: iaload
    //   6808: bipush #15
    //   6810: ishl
    //   6811: ior
    //   6812: aload #15
    //   6814: iload #17
    //   6816: iconst_2
    //   6817: isub
    //   6818: iaload
    //   6819: bipush #19
    //   6821: iushr
    //   6822: aload #15
    //   6824: iload #17
    //   6826: iconst_2
    //   6827: isub
    //   6828: iaload
    //   6829: bipush #13
    //   6831: ishl
    //   6832: ior
    //   6833: ixor
    //   6834: aload #15
    //   6836: iload #17
    //   6838: iconst_2
    //   6839: isub
    //   6840: iaload
    //   6841: bipush #10
    //   6843: iushr
    //   6844: ixor
    //   6845: aload #15
    //   6847: iload #17
    //   6849: bipush #7
    //   6851: isub
    //   6852: iaload
    //   6853: iadd
    //   6854: aload #15
    //   6856: iload #17
    //   6858: bipush #15
    //   6860: isub
    //   6861: iaload
    //   6862: bipush #7
    //   6864: iushr
    //   6865: aload #15
    //   6867: iload #17
    //   6869: bipush #15
    //   6871: isub
    //   6872: iaload
    //   6873: bipush #25
    //   6875: ishl
    //   6876: ior
    //   6877: aload #15
    //   6879: iload #17
    //   6881: bipush #15
    //   6883: isub
    //   6884: iaload
    //   6885: bipush #18
    //   6887: iushr
    //   6888: aload #15
    //   6890: iload #17
    //   6892: bipush #15
    //   6894: isub
    //   6895: iaload
    //   6896: bipush #14
    //   6898: ishl
    //   6899: ior
    //   6900: ixor
    //   6901: aload #15
    //   6903: iload #17
    //   6905: bipush #15
    //   6907: isub
    //   6908: iaload
    //   6909: iconst_3
    //   6910: iushr
    //   6911: ixor
    //   6912: iadd
    //   6913: aload #15
    //   6915: iload #17
    //   6917: bipush #16
    //   6919: isub
    //   6920: iaload
    //   6921: iadd
    //   6922: iastore
    //   6923: goto -> 6930
    //   6926: invokestatic a : (Ljava/lang/Throwable;)Ljava/lang/Throwable;
    //   6929: athrow
    //   6930: aload #16
    //   6932: bipush #7
    //   6934: iaload
    //   6935: aload #16
    //   6937: iconst_4
    //   6938: iaload
    //   6939: bipush #6
    //   6941: iushr
    //   6942: aload #16
    //   6944: iconst_4
    //   6945: iaload
    //   6946: bipush #26
    //   6948: ishl
    //   6949: ior
    //   6950: aload #16
    //   6952: iconst_4
    //   6953: iaload
    //   6954: bipush #11
    //   6956: iushr
    //   6957: aload #16
    //   6959: iconst_4
    //   6960: iaload
    //   6961: bipush #21
    //   6963: ishl
    //   6964: ior
    //   6965: ixor
    //   6966: aload #16
    //   6968: iconst_4
    //   6969: iaload
    //   6970: bipush #25
    //   6972: iushr
    //   6973: aload #16
    //   6975: iconst_4
    //   6976: iaload
    //   6977: bipush #7
    //   6979: ishl
    //   6980: ior
    //   6981: ixor
    //   6982: iadd
    //   6983: aload #16
    //   6985: bipush #6
    //   6987: iaload
    //   6988: aload #16
    //   6990: iconst_4
    //   6991: iaload
    //   6992: aload #16
    //   6994: iconst_5
    //   6995: iaload
    //   6996: aload #16
    //   6998: bipush #6
    //   7000: iaload
    //   7001: ixor
    //   7002: iand
    //   7003: ixor
    //   7004: iadd
    //   7005: aload #7
    //   7007: iload #17
    //   7009: iaload
    //   7010: iadd
    //   7011: aload #15
    //   7013: iload #17
    //   7015: iaload
    //   7016: iadd
    //   7017: istore #18
    //   7019: aload #16
    //   7021: iconst_0
    //   7022: iaload
    //   7023: iconst_2
    //   7024: iushr
    //   7025: aload #16
    //   7027: iconst_0
    //   7028: iaload
    //   7029: bipush #30
    //   7031: ishl
    //   7032: ior
    //   7033: aload #16
    //   7035: iconst_0
    //   7036: iaload
    //   7037: bipush #13
    //   7039: iushr
    //   7040: aload #16
    //   7042: iconst_0
    //   7043: iaload
    //   7044: bipush #19
    //   7046: ishl
    //   7047: ior
    //   7048: ixor
    //   7049: aload #16
    //   7051: iconst_0
    //   7052: iaload
    //   7053: bipush #22
    //   7055: iushr
    //   7056: aload #16
    //   7058: iconst_0
    //   7059: iaload
    //   7060: bipush #10
    //   7062: ishl
    //   7063: ior
    //   7064: ixor
    //   7065: aload #16
    //   7067: iconst_0
    //   7068: iaload
    //   7069: aload #16
    //   7071: iconst_1
    //   7072: iaload
    //   7073: iand
    //   7074: aload #16
    //   7076: iconst_2
    //   7077: iaload
    //   7078: aload #16
    //   7080: iconst_0
    //   7081: iaload
    //   7082: aload #16
    //   7084: iconst_1
    //   7085: iaload
    //   7086: ior
    //   7087: iand
    //   7088: ior
    //   7089: iadd
    //   7090: istore #19
    //   7092: aload #16
    //   7094: iconst_3
    //   7095: dup2
    //   7096: iaload
    //   7097: iload #18
    //   7099: iadd
    //   7100: iastore
    //   7101: aload #16
    //   7103: bipush #7
    //   7105: iload #18
    //   7107: iload #19
    //   7109: iadd
    //   7110: iastore
    //   7111: aload #16
    //   7113: bipush #7
    //   7115: iaload
    //   7116: istore #18
    //   7118: aload #16
    //   7120: bipush #7
    //   7122: aload #16
    //   7124: bipush #6
    //   7126: iaload
    //   7127: iastore
    //   7128: aload #16
    //   7130: bipush #6
    //   7132: aload #16
    //   7134: iconst_5
    //   7135: iaload
    //   7136: iastore
    //   7137: aload #16
    //   7139: iconst_5
    //   7140: aload #16
    //   7142: iconst_4
    //   7143: iaload
    //   7144: iastore
    //   7145: aload #16
    //   7147: iconst_4
    //   7148: aload #16
    //   7150: iconst_3
    //   7151: iaload
    //   7152: iastore
    //   7153: aload #16
    //   7155: iconst_3
    //   7156: aload #16
    //   7158: iconst_2
    //   7159: iaload
    //   7160: iastore
    //   7161: aload #16
    //   7163: iconst_2
    //   7164: aload #16
    //   7166: iconst_1
    //   7167: iaload
    //   7168: iastore
    //   7169: aload #16
    //   7171: iconst_1
    //   7172: aload #16
    //   7174: iconst_0
    //   7175: iaload
    //   7176: iastore
    //   7177: aload #16
    //   7179: iconst_0
    //   7180: iload #18
    //   7182: iastore
    //   7183: iinc #17, 1
    //   7186: iload_2
    //   7187: ifeq -> 6695
    //   7190: iconst_0
    //   7191: istore #17
    //   7193: iload #17
    //   7195: bipush #8
    //   7197: if_icmpge -> 7220
    //   7200: aload #9
    //   7202: iload #17
    //   7204: dup2
    //   7205: iaload
    //   7206: aload #16
    //   7208: iload #17
    //   7210: iaload
    //   7211: iadd
    //   7212: iastore
    //   7213: iinc #17, 1
    //   7216: iload_2
    //   7217: ifeq -> 7193
    //   7220: iinc #14, 64
    //   7223: iinc #12, -64
    //   7226: iload_2
    //   7227: ifeq -> 6616
    //   7230: iload #12
    //   7232: ifle -> 7268
    //   7235: iconst_0
    //   7236: istore #15
    //   7238: iload #15
    //   7240: iload #12
    //   7242: if_icmpge -> 7268
    //   7245: aload #10
    //   7247: iload #13
    //   7249: iload #15
    //   7251: iadd
    //   7252: aload #4
    //   7254: iload #14
    //   7256: iload #15
    //   7258: iadd
    //   7259: baload
    //   7260: bastore
    //   7261: iinc #15, 1
    //   7264: iload_2
    //   7265: ifeq -> 7238
    //   7268: aload #8
    //   7270: iconst_0
    //   7271: iaload
    //   7272: bipush #29
    //   7274: iushr
    //   7275: aload #8
    //   7277: iconst_1
    //   7278: iaload
    //   7279: iconst_3
    //   7280: ishl
    //   7281: ior
    //   7282: istore #15
    //   7284: aload #8
    //   7286: iconst_0
    //   7287: iaload
    //   7288: iconst_3
    //   7289: ishl
    //   7290: istore #16
    //   7292: aload #8
    //   7294: iconst_0
    //   7295: iaload
    //   7296: bipush #63
    //   7298: iand
    //   7299: istore #17
    //   7301: iload #17
    //   7303: bipush #56
    //   7305: if_icmpge -> 7320
    //   7308: bipush #56
    //   7310: iload #17
    //   7312: isub
    //   7313: goto -> 7325
    //   7316: invokestatic a : (Ljava/lang/Throwable;)Ljava/lang/Throwable;
    //   7319: athrow
    //   7320: bipush #120
    //   7322: iload #17
    //   7324: isub
    //   7325: istore #18
    //   7327: aload #8
    //   7329: iconst_0
    //   7330: iaload
    //   7331: bipush #63
    //   7333: iand
    //   7334: istore #13
    //   7336: bipush #64
    //   7338: iload #13
    //   7340: isub
    //   7341: istore #19
    //   7343: aload #8
    //   7345: iconst_0
    //   7346: dup2
    //   7347: iaload
    //   7348: iload #18
    //   7350: iadd
    //   7351: iastore
    //   7352: aload #8
    //   7354: iconst_0
    //   7355: dup2
    //   7356: iaload
    //   7357: iconst_m1
    //   7358: iand
    //   7359: iastore
    //   7360: aload #8
    //   7362: iconst_0
    //   7363: iaload
    //   7364: iload #18
    //   7366: if_icmpge -> 7384
    //   7369: aload #8
    //   7371: iconst_1
    //   7372: dup2
    //   7373: iaload
    //   7374: iconst_1
    //   7375: iadd
    //   7376: iastore
    //   7377: goto -> 7384
    //   7380: invokestatic a : (Ljava/lang/Throwable;)Ljava/lang/Throwable;
    //   7383: athrow
    //   7384: iconst_0
    //   7385: istore #14
    //   7387: iload #13
    //   7389: ifle -> 8020
    //   7392: iload #18
    //   7394: iload #19
    //   7396: if_icmplt -> 8020
    //   7399: goto -> 7406
    //   7402: invokestatic a : (Ljava/lang/Throwable;)Ljava/lang/Throwable;
    //   7405: athrow
    //   7406: iconst_0
    //   7407: istore #20
    //   7409: iload #20
    //   7411: iload #19
    //   7413: if_icmpge -> 7436
    //   7416: aload #10
    //   7418: iload #13
    //   7420: iload #20
    //   7422: iadd
    //   7423: aload #6
    //   7425: iload #20
    //   7427: baload
    //   7428: bastore
    //   7429: iinc #20, 1
    //   7432: iload_2
    //   7433: ifeq -> 7409
    //   7436: bipush #64
    //   7438: newarray int
    //   7440: astore #20
    //   7442: bipush #8
    //   7444: newarray int
    //   7446: astore #21
    //   7448: iconst_0
    //   7449: istore #22
    //   7451: iload #22
    //   7453: bipush #8
    //   7455: if_icmpge -> 7475
    //   7458: aload #21
    //   7460: iload #22
    //   7462: aload #9
    //   7464: iload #22
    //   7466: iaload
    //   7467: iastore
    //   7468: iinc #22, 1
    //   7471: iload_2
    //   7472: ifeq -> 7451
    //   7475: iconst_0
    //   7476: istore #22
    //   7478: iload #22
    //   7480: bipush #64
    //   7482: if_icmpge -> 7973
    //   7485: iload #22
    //   7487: bipush #16
    //   7489: if_icmpge -> 7570
    //   7492: aload #20
    //   7494: iload #22
    //   7496: aload #10
    //   7498: iconst_4
    //   7499: iload #22
    //   7501: imul
    //   7502: baload
    //   7503: sipush #255
    //   7506: iand
    //   7507: bipush #24
    //   7509: ishl
    //   7510: aload #10
    //   7512: iconst_4
    //   7513: iload #22
    //   7515: imul
    //   7516: iconst_1
    //   7517: iadd
    //   7518: baload
    //   7519: sipush #255
    //   7522: iand
    //   7523: bipush #16
    //   7525: ishl
    //   7526: ior
    //   7527: aload #10
    //   7529: iconst_4
    //   7530: iload #22
    //   7532: imul
    //   7533: iconst_2
    //   7534: iadd
    //   7535: baload
    //   7536: sipush #255
    //   7539: iand
    //   7540: bipush #8
    //   7542: ishl
    //   7543: ior
    //   7544: aload #10
    //   7546: iconst_4
    //   7547: iload #22
    //   7549: imul
    //   7550: iconst_3
    //   7551: iadd
    //   7552: baload
    //   7553: sipush #255
    //   7556: iand
    //   7557: ior
    //   7558: iastore
    //   7559: iload_2
    //   7560: ifeq -> 7713
    //   7563: goto -> 7570
    //   7566: invokestatic a : (Ljava/lang/Throwable;)Ljava/lang/Throwable;
    //   7569: athrow
    //   7570: aload #20
    //   7572: iload #22
    //   7574: aload #20
    //   7576: iload #22
    //   7578: iconst_2
    //   7579: isub
    //   7580: iaload
    //   7581: bipush #17
    //   7583: iushr
    //   7584: aload #20
    //   7586: iload #22
    //   7588: iconst_2
    //   7589: isub
    //   7590: iaload
    //   7591: bipush #15
    //   7593: ishl
    //   7594: ior
    //   7595: aload #20
    //   7597: iload #22
    //   7599: iconst_2
    //   7600: isub
    //   7601: iaload
    //   7602: bipush #19
    //   7604: iushr
    //   7605: aload #20
    //   7607: iload #22
    //   7609: iconst_2
    //   7610: isub
    //   7611: iaload
    //   7612: bipush #13
    //   7614: ishl
    //   7615: ior
    //   7616: ixor
    //   7617: aload #20
    //   7619: iload #22
    //   7621: iconst_2
    //   7622: isub
    //   7623: iaload
    //   7624: bipush #10
    //   7626: iushr
    //   7627: ixor
    //   7628: aload #20
    //   7630: iload #22
    //   7632: bipush #7
    //   7634: isub
    //   7635: iaload
    //   7636: iadd
    //   7637: aload #20
    //   7639: iload #22
    //   7641: bipush #15
    //   7643: isub
    //   7644: iaload
    //   7645: bipush #7
    //   7647: iushr
    //   7648: aload #20
    //   7650: iload #22
    //   7652: bipush #15
    //   7654: isub
    //   7655: iaload
    //   7656: bipush #25
    //   7658: ishl
    //   7659: ior
    //   7660: aload #20
    //   7662: iload #22
    //   7664: bipush #15
    //   7666: isub
    //   7667: iaload
    //   7668: bipush #18
    //   7670: iushr
    //   7671: aload #20
    //   7673: iload #22
    //   7675: bipush #15
    //   7677: isub
    //   7678: iaload
    //   7679: bipush #14
    //   7681: ishl
    //   7682: ior
    //   7683: ixor
    //   7684: aload #20
    //   7686: iload #22
    //   7688: bipush #15
    //   7690: isub
    //   7691: iaload
    //   7692: iconst_3
    //   7693: iushr
    //   7694: ixor
    //   7695: iadd
    //   7696: aload #20
    //   7698: iload #22
    //   7700: bipush #16
    //   7702: isub
    //   7703: iaload
    //   7704: iadd
    //   7705: iastore
    //   7706: goto -> 7713
    //   7709: invokestatic a : (Ljava/lang/Throwable;)Ljava/lang/Throwable;
    //   7712: athrow
    //   7713: aload #21
    //   7715: bipush #7
    //   7717: iaload
    //   7718: aload #21
    //   7720: iconst_4
    //   7721: iaload
    //   7722: bipush #6
    //   7724: iushr
    //   7725: aload #21
    //   7727: iconst_4
    //   7728: iaload
    //   7729: bipush #26
    //   7731: ishl
    //   7732: ior
    //   7733: aload #21
    //   7735: iconst_4
    //   7736: iaload
    //   7737: bipush #11
    //   7739: iushr
    //   7740: aload #21
    //   7742: iconst_4
    //   7743: iaload
    //   7744: bipush #21
    //   7746: ishl
    //   7747: ior
    //   7748: ixor
    //   7749: aload #21
    //   7751: iconst_4
    //   7752: iaload
    //   7753: bipush #25
    //   7755: iushr
    //   7756: aload #21
    //   7758: iconst_4
    //   7759: iaload
    //   7760: bipush #7
    //   7762: ishl
    //   7763: ior
    //   7764: ixor
    //   7765: iadd
    //   7766: aload #21
    //   7768: bipush #6
    //   7770: iaload
    //   7771: aload #21
    //   7773: iconst_4
    //   7774: iaload
    //   7775: aload #21
    //   7777: iconst_5
    //   7778: iaload
    //   7779: aload #21
    //   7781: bipush #6
    //   7783: iaload
    //   7784: ixor
    //   7785: iand
    //   7786: ixor
    //   7787: iadd
    //   7788: aload #7
    //   7790: iload #22
    //   7792: iaload
    //   7793: iadd
    //   7794: aload #20
    //   7796: iload #22
    //   7798: iaload
    //   7799: iadd
    //   7800: istore #23
    //   7802: aload #21
    //   7804: iconst_0
    //   7805: iaload
    //   7806: iconst_2
    //   7807: iushr
    //   7808: aload #21
    //   7810: iconst_0
    //   7811: iaload
    //   7812: bipush #30
    //   7814: ishl
    //   7815: ior
    //   7816: aload #21
    //   7818: iconst_0
    //   7819: iaload
    //   7820: bipush #13
    //   7822: iushr
    //   7823: aload #21
    //   7825: iconst_0
    //   7826: iaload
    //   7827: bipush #19
    //   7829: ishl
    //   7830: ior
    //   7831: ixor
    //   7832: aload #21
    //   7834: iconst_0
    //   7835: iaload
    //   7836: bipush #22
    //   7838: iushr
    //   7839: aload #21
    //   7841: iconst_0
    //   7842: iaload
    //   7843: bipush #10
    //   7845: ishl
    //   7846: ior
    //   7847: ixor
    //   7848: aload #21
    //   7850: iconst_0
    //   7851: iaload
    //   7852: aload #21
    //   7854: iconst_1
    //   7855: iaload
    //   7856: iand
    //   7857: aload #21
    //   7859: iconst_2
    //   7860: iaload
    //   7861: aload #21
    //   7863: iconst_0
    //   7864: iaload
    //   7865: aload #21
    //   7867: iconst_1
    //   7868: iaload
    //   7869: ior
    //   7870: iand
    //   7871: ior
    //   7872: iadd
    //   7873: istore #24
    //   7875: aload #21
    //   7877: iconst_3
    //   7878: dup2
    //   7879: iaload
    //   7880: iload #23
    //   7882: iadd
    //   7883: iastore
    //   7884: aload #21
    //   7886: bipush #7
    //   7888: iload #23
    //   7890: iload #24
    //   7892: iadd
    //   7893: iastore
    //   7894: aload #21
    //   7896: bipush #7
    //   7898: iaload
    //   7899: istore #23
    //   7901: aload #21
    //   7903: bipush #7
    //   7905: aload #21
    //   7907: bipush #6
    //   7909: iaload
    //   7910: iastore
    //   7911: aload #21
    //   7913: bipush #6
    //   7915: aload #21
    //   7917: iconst_5
    //   7918: iaload
    //   7919: iastore
    //   7920: aload #21
    //   7922: iconst_5
    //   7923: aload #21
    //   7925: iconst_4
    //   7926: iaload
    //   7927: iastore
    //   7928: aload #21
    //   7930: iconst_4
    //   7931: aload #21
    //   7933: iconst_3
    //   7934: iaload
    //   7935: iastore
    //   7936: aload #21
    //   7938: iconst_3
    //   7939: aload #21
    //   7941: iconst_2
    //   7942: iaload
    //   7943: iastore
    //   7944: aload #21
    //   7946: iconst_2
    //   7947: aload #21
    //   7949: iconst_1
    //   7950: iaload
    //   7951: iastore
    //   7952: aload #21
    //   7954: iconst_1
    //   7955: aload #21
    //   7957: iconst_0
    //   7958: iaload
    //   7959: iastore
    //   7960: aload #21
    //   7962: iconst_0
    //   7963: iload #23
    //   7965: iastore
    //   7966: iinc #22, 1
    //   7969: iload_2
    //   7970: ifeq -> 7478
    //   7973: iconst_0
    //   7974: istore #22
    //   7976: iload #22
    //   7978: bipush #8
    //   7980: if_icmpge -> 8003
    //   7983: aload #9
    //   7985: iload #22
    //   7987: dup2
    //   7988: iaload
    //   7989: aload #21
    //   7991: iload #22
    //   7993: iaload
    //   7994: iadd
    //   7995: iastore
    //   7996: iinc #22, 1
    //   7999: iload_2
    //   8000: ifeq -> 7976
    //   8003: iload #14
    //   8005: iload #19
    //   8007: iadd
    //   8008: istore #14
    //   8010: iload #18
    //   8012: iload #19
    //   8014: isub
    //   8015: istore #18
    //   8017: iconst_0
    //   8018: istore #13
    //   8020: iload #18
    //   8022: bipush #64
    //   8024: if_icmplt -> 8634
    //   8027: iconst_0
    //   8028: istore #20
    //   8030: iload #20
    //   8032: bipush #64
    //   8034: if_icmpge -> 8057
    //   8037: aload #11
    //   8039: iload #20
    //   8041: aload #6
    //   8043: iload #14
    //   8045: iload #20
    //   8047: iadd
    //   8048: baload
    //   8049: bastore
    //   8050: iinc #20, 1
    //   8053: iload_2
    //   8054: ifeq -> 8030
    //   8057: bipush #64
    //   8059: newarray int
    //   8061: astore #20
    //   8063: bipush #8
    //   8065: newarray int
    //   8067: astore #21
    //   8069: iconst_0
    //   8070: istore #22
    //   8072: iload #22
    //   8074: bipush #8
    //   8076: if_icmpge -> 8096
    //   8079: aload #21
    //   8081: iload #22
    //   8083: aload #9
    //   8085: iload #22
    //   8087: iaload
    //   8088: iastore
    //   8089: iinc #22, 1
    //   8092: iload_2
    //   8093: ifeq -> 8072
    //   8096: iconst_0
    //   8097: istore #22
    //   8099: iload #22
    //   8101: bipush #64
    //   8103: if_icmpge -> 8594
    //   8106: iload #22
    //   8108: bipush #16
    //   8110: if_icmpge -> 8191
    //   8113: aload #20
    //   8115: iload #22
    //   8117: aload #11
    //   8119: iconst_4
    //   8120: iload #22
    //   8122: imul
    //   8123: baload
    //   8124: sipush #255
    //   8127: iand
    //   8128: bipush #24
    //   8130: ishl
    //   8131: aload #11
    //   8133: iconst_4
    //   8134: iload #22
    //   8136: imul
    //   8137: iconst_1
    //   8138: iadd
    //   8139: baload
    //   8140: sipush #255
    //   8143: iand
    //   8144: bipush #16
    //   8146: ishl
    //   8147: ior
    //   8148: aload #11
    //   8150: iconst_4
    //   8151: iload #22
    //   8153: imul
    //   8154: iconst_2
    //   8155: iadd
    //   8156: baload
    //   8157: sipush #255
    //   8160: iand
    //   8161: bipush #8
    //   8163: ishl
    //   8164: ior
    //   8165: aload #11
    //   8167: iconst_4
    //   8168: iload #22
    //   8170: imul
    //   8171: iconst_3
    //   8172: iadd
    //   8173: baload
    //   8174: sipush #255
    //   8177: iand
    //   8178: ior
    //   8179: iastore
    //   8180: iload_2
    //   8181: ifeq -> 8334
    //   8184: goto -> 8191
    //   8187: invokestatic a : (Ljava/lang/Throwable;)Ljava/lang/Throwable;
    //   8190: athrow
    //   8191: aload #20
    //   8193: iload #22
    //   8195: aload #20
    //   8197: iload #22
    //   8199: iconst_2
    //   8200: isub
    //   8201: iaload
    //   8202: bipush #17
    //   8204: iushr
    //   8205: aload #20
    //   8207: iload #22
    //   8209: iconst_2
    //   8210: isub
    //   8211: iaload
    //   8212: bipush #15
    //   8214: ishl
    //   8215: ior
    //   8216: aload #20
    //   8218: iload #22
    //   8220: iconst_2
    //   8221: isub
    //   8222: iaload
    //   8223: bipush #19
    //   8225: iushr
    //   8226: aload #20
    //   8228: iload #22
    //   8230: iconst_2
    //   8231: isub
    //   8232: iaload
    //   8233: bipush #13
    //   8235: ishl
    //   8236: ior
    //   8237: ixor
    //   8238: aload #20
    //   8240: iload #22
    //   8242: iconst_2
    //   8243: isub
    //   8244: iaload
    //   8245: bipush #10
    //   8247: iushr
    //   8248: ixor
    //   8249: aload #20
    //   8251: iload #22
    //   8253: bipush #7
    //   8255: isub
    //   8256: iaload
    //   8257: iadd
    //   8258: aload #20
    //   8260: iload #22
    //   8262: bipush #15
    //   8264: isub
    //   8265: iaload
    //   8266: bipush #7
    //   8268: iushr
    //   8269: aload #20
    //   8271: iload #22
    //   8273: bipush #15
    //   8275: isub
    //   8276: iaload
    //   8277: bipush #25
    //   8279: ishl
    //   8280: ior
    //   8281: aload #20
    //   8283: iload #22
    //   8285: bipush #15
    //   8287: isub
    //   8288: iaload
    //   8289: bipush #18
    //   8291: iushr
    //   8292: aload #20
    //   8294: iload #22
    //   8296: bipush #15
    //   8298: isub
    //   8299: iaload
    //   8300: bipush #14
    //   8302: ishl
    //   8303: ior
    //   8304: ixor
    //   8305: aload #20
    //   8307: iload #22
    //   8309: bipush #15
    //   8311: isub
    //   8312: iaload
    //   8313: iconst_3
    //   8314: iushr
    //   8315: ixor
    //   8316: iadd
    //   8317: aload #20
    //   8319: iload #22
    //   8321: bipush #16
    //   8323: isub
    //   8324: iaload
    //   8325: iadd
    //   8326: iastore
    //   8327: goto -> 8334
    //   8330: invokestatic a : (Ljava/lang/Throwable;)Ljava/lang/Throwable;
    //   8333: athrow
    //   8334: aload #21
    //   8336: bipush #7
    //   8338: iaload
    //   8339: aload #21
    //   8341: iconst_4
    //   8342: iaload
    //   8343: bipush #6
    //   8345: iushr
    //   8346: aload #21
    //   8348: iconst_4
    //   8349: iaload
    //   8350: bipush #26
    //   8352: ishl
    //   8353: ior
    //   8354: aload #21
    //   8356: iconst_4
    //   8357: iaload
    //   8358: bipush #11
    //   8360: iushr
    //   8361: aload #21
    //   8363: iconst_4
    //   8364: iaload
    //   8365: bipush #21
    //   8367: ishl
    //   8368: ior
    //   8369: ixor
    //   8370: aload #21
    //   8372: iconst_4
    //   8373: iaload
    //   8374: bipush #25
    //   8376: iushr
    //   8377: aload #21
    //   8379: iconst_4
    //   8380: iaload
    //   8381: bipush #7
    //   8383: ishl
    //   8384: ior
    //   8385: ixor
    //   8386: iadd
    //   8387: aload #21
    //   8389: bipush #6
    //   8391: iaload
    //   8392: aload #21
    //   8394: iconst_4
    //   8395: iaload
    //   8396: aload #21
    //   8398: iconst_5
    //   8399: iaload
    //   8400: aload #21
    //   8402: bipush #6
    //   8404: iaload
    //   8405: ixor
    //   8406: iand
    //   8407: ixor
    //   8408: iadd
    //   8409: aload #7
    //   8411: iload #22
    //   8413: iaload
    //   8414: iadd
    //   8415: aload #20
    //   8417: iload #22
    //   8419: iaload
    //   8420: iadd
    //   8421: istore #23
    //   8423: aload #21
    //   8425: iconst_0
    //   8426: iaload
    //   8427: iconst_2
    //   8428: iushr
    //   8429: aload #21
    //   8431: iconst_0
    //   8432: iaload
    //   8433: bipush #30
    //   8435: ishl
    //   8436: ior
    //   8437: aload #21
    //   8439: iconst_0
    //   8440: iaload
    //   8441: bipush #13
    //   8443: iushr
    //   8444: aload #21
    //   8446: iconst_0
    //   8447: iaload
    //   8448: bipush #19
    //   8450: ishl
    //   8451: ior
    //   8452: ixor
    //   8453: aload #21
    //   8455: iconst_0
    //   8456: iaload
    //   8457: bipush #22
    //   8459: iushr
    //   8460: aload #21
    //   8462: iconst_0
    //   8463: iaload
    //   8464: bipush #10
    //   8466: ishl
    //   8467: ior
    //   8468: ixor
    //   8469: aload #21
    //   8471: iconst_0
    //   8472: iaload
    //   8473: aload #21
    //   8475: iconst_1
    //   8476: iaload
    //   8477: iand
    //   8478: aload #21
    //   8480: iconst_2
    //   8481: iaload
    //   8482: aload #21
    //   8484: iconst_0
    //   8485: iaload
    //   8486: aload #21
    //   8488: iconst_1
    //   8489: iaload
    //   8490: ior
    //   8491: iand
    //   8492: ior
    //   8493: iadd
    //   8494: istore #24
    //   8496: aload #21
    //   8498: iconst_3
    //   8499: dup2
    //   8500: iaload
    //   8501: iload #23
    //   8503: iadd
    //   8504: iastore
    //   8505: aload #21
    //   8507: bipush #7
    //   8509: iload #23
    //   8511: iload #24
    //   8513: iadd
    //   8514: iastore
    //   8515: aload #21
    //   8517: bipush #7
    //   8519: iaload
    //   8520: istore #23
    //   8522: aload #21
    //   8524: bipush #7
    //   8526: aload #21
    //   8528: bipush #6
    //   8530: iaload
    //   8531: iastore
    //   8532: aload #21
    //   8534: bipush #6
    //   8536: aload #21
    //   8538: iconst_5
    //   8539: iaload
    //   8540: iastore
    //   8541: aload #21
    //   8543: iconst_5
    //   8544: aload #21
    //   8546: iconst_4
    //   8547: iaload
    //   8548: iastore
    //   8549: aload #21
    //   8551: iconst_4
    //   8552: aload #21
    //   8554: iconst_3
    //   8555: iaload
    //   8556: iastore
    //   8557: aload #21
    //   8559: iconst_3
    //   8560: aload #21
    //   8562: iconst_2
    //   8563: iaload
    //   8564: iastore
    //   8565: aload #21
    //   8567: iconst_2
    //   8568: aload #21
    //   8570: iconst_1
    //   8571: iaload
    //   8572: iastore
    //   8573: aload #21
    //   8575: iconst_1
    //   8576: aload #21
    //   8578: iconst_0
    //   8579: iaload
    //   8580: iastore
    //   8581: aload #21
    //   8583: iconst_0
    //   8584: iload #23
    //   8586: iastore
    //   8587: iinc #22, 1
    //   8590: iload_2
    //   8591: ifeq -> 8099
    //   8594: iconst_0
    //   8595: istore #22
    //   8597: iload #22
    //   8599: bipush #8
    //   8601: if_icmpge -> 8624
    //   8604: aload #9
    //   8606: iload #22
    //   8608: dup2
    //   8609: iaload
    //   8610: aload #21
    //   8612: iload #22
    //   8614: iaload
    //   8615: iadd
    //   8616: iastore
    //   8617: iinc #22, 1
    //   8620: iload_2
    //   8621: ifeq -> 8597
    //   8624: iinc #14, 64
    //   8627: iinc #18, -64
    //   8630: iload_2
    //   8631: ifeq -> 8020
    //   8634: iload #18
    //   8636: ifle -> 8672
    //   8639: iconst_0
    //   8640: istore #20
    //   8642: iload #20
    //   8644: iload #18
    //   8646: if_icmpge -> 8672
    //   8649: aload #10
    //   8651: iload #13
    //   8653: iload #20
    //   8655: iadd
    //   8656: aload #6
    //   8658: iload #14
    //   8660: iload #20
    //   8662: iadd
    //   8663: baload
    //   8664: bastore
    //   8665: iinc #20, 1
    //   8668: iload_2
    //   8669: ifeq -> 8642
    //   8672: bipush #8
    //   8674: newarray byte
    //   8676: astore #20
    //   8678: aload #20
    //   8680: iconst_0
    //   8681: iload #15
    //   8683: bipush #24
    //   8685: iushr
    //   8686: i2b
    //   8687: bastore
    //   8688: aload #20
    //   8690: iconst_1
    //   8691: iload #15
    //   8693: bipush #16
    //   8695: iushr
    //   8696: i2b
    //   8697: bastore
    //   8698: aload #20
    //   8700: iconst_2
    //   8701: iload #15
    //   8703: bipush #8
    //   8705: iushr
    //   8706: i2b
    //   8707: bastore
    //   8708: aload #20
    //   8710: iconst_3
    //   8711: iload #15
    //   8713: i2b
    //   8714: bastore
    //   8715: aload #20
    //   8717: iconst_4
    //   8718: iload #16
    //   8720: bipush #24
    //   8722: iushr
    //   8723: i2b
    //   8724: bastore
    //   8725: aload #20
    //   8727: iconst_5
    //   8728: iload #16
    //   8730: bipush #16
    //   8732: iushr
    //   8733: i2b
    //   8734: bastore
    //   8735: aload #20
    //   8737: bipush #6
    //   8739: iload #16
    //   8741: bipush #8
    //   8743: iushr
    //   8744: i2b
    //   8745: bastore
    //   8746: aload #20
    //   8748: bipush #7
    //   8750: iload #16
    //   8752: i2b
    //   8753: bastore
    //   8754: bipush #8
    //   8756: istore #12
    //   8758: aload #8
    //   8760: iconst_0
    //   8761: iaload
    //   8762: bipush #63
    //   8764: iand
    //   8765: istore #13
    //   8767: bipush #64
    //   8769: iload #13
    //   8771: isub
    //   8772: istore #19
    //   8774: aload #8
    //   8776: iconst_0
    //   8777: dup2
    //   8778: iaload
    //   8779: iload #12
    //   8781: iadd
    //   8782: iastore
    //   8783: aload #8
    //   8785: iconst_0
    //   8786: dup2
    //   8787: iaload
    //   8788: iconst_m1
    //   8789: iand
    //   8790: iastore
    //   8791: aload #8
    //   8793: iconst_0
    //   8794: iaload
    //   8795: iload #12
    //   8797: if_icmpge -> 8815
    //   8800: aload #8
    //   8802: iconst_1
    //   8803: dup2
    //   8804: iaload
    //   8805: iconst_1
    //   8806: iadd
    //   8807: iastore
    //   8808: goto -> 8815
    //   8811: invokestatic a : (Ljava/lang/Throwable;)Ljava/lang/Throwable;
    //   8814: athrow
    //   8815: iload #13
    //   8817: ifle -> 9431
    //   8820: iload #12
    //   8822: iload #19
    //   8824: if_icmplt -> 9431
    //   8827: goto -> 8834
    //   8830: invokestatic a : (Ljava/lang/Throwable;)Ljava/lang/Throwable;
    //   8833: athrow
    //   8834: iconst_0
    //   8835: istore #21
    //   8837: iload #21
    //   8839: iload #19
    //   8841: if_icmpge -> 8864
    //   8844: aload #10
    //   8846: iload #13
    //   8848: iload #21
    //   8850: iadd
    //   8851: aload #20
    //   8853: iload #21
    //   8855: baload
    //   8856: bastore
    //   8857: iinc #21, 1
    //   8860: iload_2
    //   8861: ifeq -> 8837
    //   8864: bipush #64
    //   8866: newarray int
    //   8868: astore #21
    //   8870: bipush #8
    //   8872: newarray int
    //   8874: astore #22
    //   8876: iconst_0
    //   8877: istore #23
    //   8879: iload #23
    //   8881: bipush #8
    //   8883: if_icmpge -> 8903
    //   8886: aload #22
    //   8888: iload #23
    //   8890: aload #9
    //   8892: iload #23
    //   8894: iaload
    //   8895: iastore
    //   8896: iinc #23, 1
    //   8899: iload_2
    //   8900: ifeq -> 8879
    //   8903: iconst_0
    //   8904: istore #23
    //   8906: iload #23
    //   8908: bipush #64
    //   8910: if_icmpge -> 9401
    //   8913: iload #23
    //   8915: bipush #16
    //   8917: if_icmpge -> 8998
    //   8920: aload #21
    //   8922: iload #23
    //   8924: aload #10
    //   8926: iconst_4
    //   8927: iload #23
    //   8929: imul
    //   8930: baload
    //   8931: sipush #255
    //   8934: iand
    //   8935: bipush #24
    //   8937: ishl
    //   8938: aload #10
    //   8940: iconst_4
    //   8941: iload #23
    //   8943: imul
    //   8944: iconst_1
    //   8945: iadd
    //   8946: baload
    //   8947: sipush #255
    //   8950: iand
    //   8951: bipush #16
    //   8953: ishl
    //   8954: ior
    //   8955: aload #10
    //   8957: iconst_4
    //   8958: iload #23
    //   8960: imul
    //   8961: iconst_2
    //   8962: iadd
    //   8963: baload
    //   8964: sipush #255
    //   8967: iand
    //   8968: bipush #8
    //   8970: ishl
    //   8971: ior
    //   8972: aload #10
    //   8974: iconst_4
    //   8975: iload #23
    //   8977: imul
    //   8978: iconst_3
    //   8979: iadd
    //   8980: baload
    //   8981: sipush #255
    //   8984: iand
    //   8985: ior
    //   8986: iastore
    //   8987: iload_2
    //   8988: ifeq -> 9141
    //   8991: goto -> 8998
    //   8994: invokestatic a : (Ljava/lang/Throwable;)Ljava/lang/Throwable;
    //   8997: athrow
    //   8998: aload #21
    //   9000: iload #23
    //   9002: aload #21
    //   9004: iload #23
    //   9006: iconst_2
    //   9007: isub
    //   9008: iaload
    //   9009: bipush #17
    //   9011: iushr
    //   9012: aload #21
    //   9014: iload #23
    //   9016: iconst_2
    //   9017: isub
    //   9018: iaload
    //   9019: bipush #15
    //   9021: ishl
    //   9022: ior
    //   9023: aload #21
    //   9025: iload #23
    //   9027: iconst_2
    //   9028: isub
    //   9029: iaload
    //   9030: bipush #19
    //   9032: iushr
    //   9033: aload #21
    //   9035: iload #23
    //   9037: iconst_2
    //   9038: isub
    //   9039: iaload
    //   9040: bipush #13
    //   9042: ishl
    //   9043: ior
    //   9044: ixor
    //   9045: aload #21
    //   9047: iload #23
    //   9049: iconst_2
    //   9050: isub
    //   9051: iaload
    //   9052: bipush #10
    //   9054: iushr
    //   9055: ixor
    //   9056: aload #21
    //   9058: iload #23
    //   9060: bipush #7
    //   9062: isub
    //   9063: iaload
    //   9064: iadd
    //   9065: aload #21
    //   9067: iload #23
    //   9069: bipush #15
    //   9071: isub
    //   9072: iaload
    //   9073: bipush #7
    //   9075: iushr
    //   9076: aload #21
    //   9078: iload #23
    //   9080: bipush #15
    //   9082: isub
    //   9083: iaload
    //   9084: bipush #25
    //   9086: ishl
    //   9087: ior
    //   9088: aload #21
    //   9090: iload #23
    //   9092: bipush #15
    //   9094: isub
    //   9095: iaload
    //   9096: bipush #18
    //   9098: iushr
    //   9099: aload #21
    //   9101: iload #23
    //   9103: bipush #15
    //   9105: isub
    //   9106: iaload
    //   9107: bipush #14
    //   9109: ishl
    //   9110: ior
    //   9111: ixor
    //   9112: aload #21
    //   9114: iload #23
    //   9116: bipush #15
    //   9118: isub
    //   9119: iaload
    //   9120: iconst_3
    //   9121: iushr
    //   9122: ixor
    //   9123: iadd
    //   9124: aload #21
    //   9126: iload #23
    //   9128: bipush #16
    //   9130: isub
    //   9131: iaload
    //   9132: iadd
    //   9133: iastore
    //   9134: goto -> 9141
    //   9137: invokestatic a : (Ljava/lang/Throwable;)Ljava/lang/Throwable;
    //   9140: athrow
    //   9141: aload #22
    //   9143: bipush #7
    //   9145: iaload
    //   9146: aload #22
    //   9148: iconst_4
    //   9149: iaload
    //   9150: bipush #6
    //   9152: iushr
    //   9153: aload #22
    //   9155: iconst_4
    //   9156: iaload
    //   9157: bipush #26
    //   9159: ishl
    //   9160: ior
    //   9161: aload #22
    //   9163: iconst_4
    //   9164: iaload
    //   9165: bipush #11
    //   9167: iushr
    //   9168: aload #22
    //   9170: iconst_4
    //   9171: iaload
    //   9172: bipush #21
    //   9174: ishl
    //   9175: ior
    //   9176: ixor
    //   9177: aload #22
    //   9179: iconst_4
    //   9180: iaload
    //   9181: bipush #25
    //   9183: iushr
    //   9184: aload #22
    //   9186: iconst_4
    //   9187: iaload
    //   9188: bipush #7
    //   9190: ishl
    //   9191: ior
    //   9192: ixor
    //   9193: iadd
    //   9194: aload #22
    //   9196: bipush #6
    //   9198: iaload
    //   9199: aload #22
    //   9201: iconst_4
    //   9202: iaload
    //   9203: aload #22
    //   9205: iconst_5
    //   9206: iaload
    //   9207: aload #22
    //   9209: bipush #6
    //   9211: iaload
    //   9212: ixor
    //   9213: iand
    //   9214: ixor
    //   9215: iadd
    //   9216: aload #7
    //   9218: iload #23
    //   9220: iaload
    //   9221: iadd
    //   9222: aload #21
    //   9224: iload #23
    //   9226: iaload
    //   9227: iadd
    //   9228: istore #24
    //   9230: aload #22
    //   9232: iconst_0
    //   9233: iaload
    //   9234: iconst_2
    //   9235: iushr
    //   9236: aload #22
    //   9238: iconst_0
    //   9239: iaload
    //   9240: bipush #30
    //   9242: ishl
    //   9243: ior
    //   9244: aload #22
    //   9246: iconst_0
    //   9247: iaload
    //   9248: bipush #13
    //   9250: iushr
    //   9251: aload #22
    //   9253: iconst_0
    //   9254: iaload
    //   9255: bipush #19
    //   9257: ishl
    //   9258: ior
    //   9259: ixor
    //   9260: aload #22
    //   9262: iconst_0
    //   9263: iaload
    //   9264: bipush #22
    //   9266: iushr
    //   9267: aload #22
    //   9269: iconst_0
    //   9270: iaload
    //   9271: bipush #10
    //   9273: ishl
    //   9274: ior
    //   9275: ixor
    //   9276: aload #22
    //   9278: iconst_0
    //   9279: iaload
    //   9280: aload #22
    //   9282: iconst_1
    //   9283: iaload
    //   9284: iand
    //   9285: aload #22
    //   9287: iconst_2
    //   9288: iaload
    //   9289: aload #22
    //   9291: iconst_0
    //   9292: iaload
    //   9293: aload #22
    //   9295: iconst_1
    //   9296: iaload
    //   9297: ior
    //   9298: iand
    //   9299: ior
    //   9300: iadd
    //   9301: istore #25
    //   9303: aload #22
    //   9305: iconst_3
    //   9306: dup2
    //   9307: iaload
    //   9308: iload #24
    //   9310: iadd
    //   9311: iastore
    //   9312: aload #22
    //   9314: bipush #7
    //   9316: iload #24
    //   9318: iload #25
    //   9320: iadd
    //   9321: iastore
    //   9322: aload #22
    //   9324: bipush #7
    //   9326: iaload
    //   9327: istore #24
    //   9329: aload #22
    //   9331: bipush #7
    //   9333: aload #22
    //   9335: bipush #6
    //   9337: iaload
    //   9338: iastore
    //   9339: aload #22
    //   9341: bipush #6
    //   9343: aload #22
    //   9345: iconst_5
    //   9346: iaload
    //   9347: iastore
    //   9348: aload #22
    //   9350: iconst_5
    //   9351: aload #22
    //   9353: iconst_4
    //   9354: iaload
    //   9355: iastore
    //   9356: aload #22
    //   9358: iconst_4
    //   9359: aload #22
    //   9361: iconst_3
    //   9362: iaload
    //   9363: iastore
    //   9364: aload #22
    //   9366: iconst_3
    //   9367: aload #22
    //   9369: iconst_2
    //   9370: iaload
    //   9371: iastore
    //   9372: aload #22
    //   9374: iconst_2
    //   9375: aload #22
    //   9377: iconst_1
    //   9378: iaload
    //   9379: iastore
    //   9380: aload #22
    //   9382: iconst_1
    //   9383: aload #22
    //   9385: iconst_0
    //   9386: iaload
    //   9387: iastore
    //   9388: aload #22
    //   9390: iconst_0
    //   9391: iload #24
    //   9393: iastore
    //   9394: iinc #23, 1
    //   9397: iload_2
    //   9398: ifeq -> 8906
    //   9401: iconst_0
    //   9402: istore #23
    //   9404: iload #23
    //   9406: bipush #8
    //   9408: if_icmpge -> 9431
    //   9411: aload #9
    //   9413: iload #23
    //   9415: dup2
    //   9416: iaload
    //   9417: aload #22
    //   9419: iload #23
    //   9421: iaload
    //   9422: iadd
    //   9423: iastore
    //   9424: iinc #23, 1
    //   9427: iload_2
    //   9428: ifeq -> 9404
    //   9431: bipush #32
    //   9433: newarray byte
    //   9435: astore #5
    //   9437: aload #5
    //   9439: iconst_0
    //   9440: aload #9
    //   9442: iconst_0
    //   9443: iaload
    //   9444: bipush #24
    //   9446: iushr
    //   9447: i2b
    //   9448: bastore
    //   9449: aload #5
    //   9451: iconst_1
    //   9452: aload #9
    //   9454: iconst_0
    //   9455: iaload
    //   9456: bipush #16
    //   9458: iushr
    //   9459: i2b
    //   9460: bastore
    //   9461: aload #5
    //   9463: iconst_2
    //   9464: aload #9
    //   9466: iconst_0
    //   9467: iaload
    //   9468: bipush #8
    //   9470: iushr
    //   9471: i2b
    //   9472: bastore
    //   9473: aload #5
    //   9475: iconst_3
    //   9476: aload #9
    //   9478: iconst_0
    //   9479: iaload
    //   9480: i2b
    //   9481: bastore
    //   9482: aload #5
    //   9484: iconst_4
    //   9485: aload #9
    //   9487: iconst_1
    //   9488: iaload
    //   9489: bipush #24
    //   9491: iushr
    //   9492: i2b
    //   9493: bastore
    //   9494: aload #5
    //   9496: iconst_5
    //   9497: aload #9
    //   9499: iconst_1
    //   9500: iaload
    //   9501: bipush #16
    //   9503: iushr
    //   9504: i2b
    //   9505: bastore
    //   9506: aload #5
    //   9508: bipush #6
    //   9510: aload #9
    //   9512: iconst_1
    //   9513: iaload
    //   9514: bipush #8
    //   9516: iushr
    //   9517: i2b
    //   9518: bastore
    //   9519: aload #5
    //   9521: bipush #7
    //   9523: aload #9
    //   9525: iconst_1
    //   9526: iaload
    //   9527: i2b
    //   9528: bastore
    //   9529: aload #5
    //   9531: bipush #8
    //   9533: aload #9
    //   9535: iconst_2
    //   9536: iaload
    //   9537: bipush #24
    //   9539: iushr
    //   9540: i2b
    //   9541: bastore
    //   9542: aload #5
    //   9544: bipush #9
    //   9546: aload #9
    //   9548: iconst_2
    //   9549: iaload
    //   9550: bipush #16
    //   9552: iushr
    //   9553: i2b
    //   9554: bastore
    //   9555: aload #5
    //   9557: bipush #10
    //   9559: aload #9
    //   9561: iconst_2
    //   9562: iaload
    //   9563: bipush #8
    //   9565: iushr
    //   9566: i2b
    //   9567: bastore
    //   9568: aload #5
    //   9570: bipush #11
    //   9572: aload #9
    //   9574: iconst_2
    //   9575: iaload
    //   9576: i2b
    //   9577: bastore
    //   9578: aload #5
    //   9580: bipush #12
    //   9582: aload #9
    //   9584: iconst_3
    //   9585: iaload
    //   9586: bipush #24
    //   9588: iushr
    //   9589: i2b
    //   9590: bastore
    //   9591: aload #5
    //   9593: bipush #13
    //   9595: aload #9
    //   9597: iconst_3
    //   9598: iaload
    //   9599: bipush #16
    //   9601: iushr
    //   9602: i2b
    //   9603: bastore
    //   9604: aload #5
    //   9606: bipush #14
    //   9608: aload #9
    //   9610: iconst_3
    //   9611: iaload
    //   9612: bipush #8
    //   9614: iushr
    //   9615: i2b
    //   9616: bastore
    //   9617: aload #5
    //   9619: bipush #15
    //   9621: aload #9
    //   9623: iconst_3
    //   9624: iaload
    //   9625: i2b
    //   9626: bastore
    //   9627: aload #5
    //   9629: bipush #16
    //   9631: aload #9
    //   9633: iconst_4
    //   9634: iaload
    //   9635: bipush #24
    //   9637: iushr
    //   9638: i2b
    //   9639: bastore
    //   9640: aload #5
    //   9642: bipush #17
    //   9644: aload #9
    //   9646: iconst_4
    //   9647: iaload
    //   9648: bipush #16
    //   9650: iushr
    //   9651: i2b
    //   9652: bastore
    //   9653: aload #5
    //   9655: bipush #18
    //   9657: aload #9
    //   9659: iconst_4
    //   9660: iaload
    //   9661: bipush #8
    //   9663: iushr
    //   9664: i2b
    //   9665: bastore
    //   9666: aload #5
    //   9668: bipush #19
    //   9670: aload #9
    //   9672: iconst_4
    //   9673: iaload
    //   9674: i2b
    //   9675: bastore
    //   9676: aload #5
    //   9678: bipush #20
    //   9680: aload #9
    //   9682: iconst_5
    //   9683: iaload
    //   9684: bipush #24
    //   9686: iushr
    //   9687: i2b
    //   9688: bastore
    //   9689: aload #5
    //   9691: bipush #21
    //   9693: aload #9
    //   9695: iconst_5
    //   9696: iaload
    //   9697: bipush #16
    //   9699: iushr
    //   9700: i2b
    //   9701: bastore
    //   9702: aload #5
    //   9704: bipush #22
    //   9706: aload #9
    //   9708: iconst_5
    //   9709: iaload
    //   9710: bipush #8
    //   9712: iushr
    //   9713: i2b
    //   9714: bastore
    //   9715: aload #5
    //   9717: bipush #23
    //   9719: aload #9
    //   9721: iconst_5
    //   9722: iaload
    //   9723: i2b
    //   9724: bastore
    //   9725: aload #5
    //   9727: bipush #24
    //   9729: aload #9
    //   9731: bipush #6
    //   9733: iaload
    //   9734: bipush #24
    //   9736: iushr
    //   9737: i2b
    //   9738: bastore
    //   9739: aload #5
    //   9741: bipush #25
    //   9743: aload #9
    //   9745: bipush #6
    //   9747: iaload
    //   9748: bipush #16
    //   9750: iushr
    //   9751: i2b
    //   9752: bastore
    //   9753: aload #5
    //   9755: bipush #26
    //   9757: aload #9
    //   9759: bipush #6
    //   9761: iaload
    //   9762: bipush #8
    //   9764: iushr
    //   9765: i2b
    //   9766: bastore
    //   9767: aload #5
    //   9769: bipush #27
    //   9771: aload #9
    //   9773: bipush #6
    //   9775: iaload
    //   9776: i2b
    //   9777: bastore
    //   9778: aload #5
    //   9780: bipush #28
    //   9782: aload #9
    //   9784: bipush #7
    //   9786: iaload
    //   9787: bipush #24
    //   9789: iushr
    //   9790: i2b
    //   9791: bastore
    //   9792: aload #5
    //   9794: bipush #29
    //   9796: aload #9
    //   9798: bipush #7
    //   9800: iaload
    //   9801: bipush #16
    //   9803: iushr
    //   9804: i2b
    //   9805: bastore
    //   9806: aload #5
    //   9808: bipush #30
    //   9810: aload #9
    //   9812: bipush #7
    //   9814: iaload
    //   9815: bipush #8
    //   9817: iushr
    //   9818: i2b
    //   9819: bastore
    //   9820: aload #5
    //   9822: bipush #31
    //   9824: aload #9
    //   9826: bipush #7
    //   9828: iaload
    //   9829: i2b
    //   9830: bastore
    //   9831: getstatic burp/Zty5.Za : Ljava/lang/String;
    //   9834: getstatic burp/Zgdj.ZT : Ljava/lang/Object;
    //   9837: checkcast java/math/BigInteger
    //   9840: invokevirtual intValue : ()I
    //   9843: bipush #32
    //   9845: irem
    //   9846: invokestatic abs : (I)I
    //   9849: invokevirtual charAt : (I)C
    //   9852: getstatic burp/Zr_k.Zu : Ljava/lang/String;
    //   9855: getstatic burp/Zxn7.ZU : Ljava/lang/Object;
    //   9858: checkcast java/math/BigInteger
    //   9861: invokevirtual intValue : ()I
    //   9864: bipush #32
    //   9866: irem
    //   9867: invokestatic abs : (I)I
    //   9870: invokevirtual charAt : (I)C
    //   9873: if_icmple -> 9980
    //   9876: getstatic burp/Ze3t.ZG : Ljava/lang/String;
    //   9879: getstatic burp/Zs59.Zw : Ljava/lang/Object;
    //   9882: checkcast java/math/BigInteger
    //   9885: invokevirtual intValue : ()I
    //   9888: bipush #32
    //   9890: irem
    //   9891: invokestatic abs : (I)I
    //   9894: invokevirtual charAt : (I)C
    //   9897: getstatic burp/Zl_9.ZP : Ljava/lang/String;
    //   9900: getstatic burp/Ztd6.ZI : Ljava/lang/Object;
    //   9903: checkcast java/math/BigInteger
    //   9906: invokevirtual intValue : ()I
    //   9909: bipush #32
    //   9911: irem
    //   9912: invokestatic abs : (I)I
    //   9915: invokevirtual charAt : (I)C
    //   9918: if_icmpgt -> 9980
    //   9921: goto -> 9928
    //   9924: invokestatic a : (Ljava/lang/Throwable;)Ljava/lang/Throwable;
    //   9927: athrow
    //   9928: getstatic burp/Zebj.ZF : Ljava/lang/String;
    //   9931: getstatic burp/Zxnm.ZW : Ljava/lang/Object;
    //   9934: checkcast java/math/BigInteger
    //   9937: invokevirtual intValue : ()I
    //   9940: bipush #32
    //   9942: irem
    //   9943: invokestatic abs : (I)I
    //   9946: invokevirtual charAt : (I)C
    //   9949: getstatic burp/Zb_u.ZK : Ljava/lang/String;
    //   9952: getstatic burp/Zgwq.Ze : Ljava/lang/Object;
    //   9955: checkcast java/math/BigInteger
    //   9958: invokevirtual intValue : ()I
    //   9961: bipush #32
    //   9963: irem
    //   9964: invokestatic abs : (I)I
    //   9967: invokevirtual charAt : (I)C
    //   9970: if_icmpgt -> 9988
    //   9973: goto -> 9980
    //   9976: invokestatic a : (Ljava/lang/Throwable;)Ljava/lang/Throwable;
    //   9979: athrow
    //   9980: iconst_1
    //   9981: goto -> 9989
    //   9984: invokestatic a : (Ljava/lang/Throwable;)Ljava/lang/Throwable;
    //   9987: athrow
    //   9988: iconst_0
    //   9989: ireturn
    //   9990: astore_3
    //   9991: new java/lang/Exception
    //   9994: dup
    //   9995: aload_3
    //   9996: invokevirtual getMessage : ()Ljava/lang/String;
    //   9999: invokespecial <init> : (Ljava/lang/String;)V
    //   10002: athrow
    // Exception table:
    //   from	to	target	type
    //   4	9989	9990	java/lang/Throwable
    //   805	839	842	java/lang/Throwable
    //   934	1012	1015	java/lang/Throwable
    //   941	1155	1158	java/lang/Throwable
    //   1532	1547	1547	java/lang/Throwable
    //   1574	1608	1611	java/lang/Throwable
    //   1618	1630	1633	java/lang/Throwable
    //   1716	1794	1797	java/lang/Throwable
    //   1723	1937	1940	java/lang/Throwable
    //   2337	2415	2418	java/lang/Throwable
    //   2344	2558	2561	java/lang/Throwable
    //   3005	3039	3042	java/lang/Throwable
    //   3046	3058	3061	java/lang/Throwable
    //   3144	3222	3225	java/lang/Throwable
    //   3151	3365	3368	java/lang/Throwable
    //   4095	4270	4273	java/lang/Throwable
    //   4240	4307	4310	java/lang/Throwable
    //   4277	4344	4347	java/lang/Throwable
    //   4314	4381	4384	java/lang/Throwable
    //   4351	4418	4421	java/lang/Throwable
    //   4388	4455	4458	java/lang/Throwable
    //   4425	4492	4495	java/lang/Throwable
    //   4462	4529	4532	java/lang/Throwable
    //   4499	4566	4569	java/lang/Throwable
    //   4536	4603	4606	java/lang/Throwable
    //   4573	4640	4643	java/lang/Throwable
    //   4610	4677	4680	java/lang/Throwable
    //   4647	4714	4717	java/lang/Throwable
    //   4684	4751	4754	java/lang/Throwable
    //   4721	4788	4791	java/lang/Throwable
    //   4758	4825	4828	java/lang/Throwable
    //   4795	4862	4865	java/lang/Throwable
    //   4832	4899	4902	java/lang/Throwable
    //   4869	4936	4939	java/lang/Throwable
    //   4906	4973	4976	java/lang/Throwable
    //   4943	5010	5013	java/lang/Throwable
    //   4980	5047	5050	java/lang/Throwable
    //   5017	5084	5087	java/lang/Throwable
    //   5054	5121	5124	java/lang/Throwable
    //   5091	5158	5161	java/lang/Throwable
    //   5128	5195	5198	java/lang/Throwable
    //   5165	5232	5235	java/lang/Throwable
    //   5202	5269	5272	java/lang/Throwable
    //   5239	5306	5309	java/lang/Throwable
    //   5276	5343	5346	java/lang/Throwable
    //   5313	5380	5383	java/lang/Throwable
    //   5350	5413	5416	java/lang/Throwable
    //   5479	5493	5493	java/lang/Throwable
    //   5504	5517	5520	java/lang/Throwable
    //   5509	5532	5535	java/lang/Throwable
    //   5524	5550	5553	java/lang/Throwable
    //   5539	5580	5583	java/lang/Throwable
    //   5646	5673	5676	java/lang/Throwable
    //   5663	5694	5697	java/lang/Throwable
    //   5680	5724	5727	java/lang/Throwable
    //   5701	5735	5735	java/lang/Throwable
    //   5746	5762	5765	java/lang/Throwable
    //   6572	6606	6609	java/lang/Throwable
    //   6702	6780	6783	java/lang/Throwable
    //   6709	6923	6926	java/lang/Throwable
    //   7301	7316	7316	java/lang/Throwable
    //   7343	7377	7380	java/lang/Throwable
    //   7387	7399	7402	java/lang/Throwable
    //   7485	7563	7566	java/lang/Throwable
    //   7492	7706	7709	java/lang/Throwable
    //   8106	8184	8187	java/lang/Throwable
    //   8113	8327	8330	java/lang/Throwable
    //   8774	8808	8811	java/lang/Throwable
    //   8815	8827	8830	java/lang/Throwable
    //   8913	8991	8994	java/lang/Throwable
    //   8920	9134	9137	java/lang/Throwable
    //   9437	9921	9924	java/lang/Throwable
    //   9876	9973	9976	java/lang/Throwable
    //   9928	9984	9984	java/lang/Throwable
  }
  
  static void ZO(Object[] paramArrayOfObject, Object paramObject) throws Throwable {}
  
  static {
    // Byte code:
    //   0: bipush #8
    //   2: anewarray java/lang/String
    //   5: astore #5
    //   7: iconst_0
    //   8: istore_3
    //   9: ldc '!q\Mf&c;\ZXXpq' D:%[R_*:dO+XVMI\\t&W\WU\\rYr?bw\\fH:N)qV(u]:HRNwg?`K}CG\\fx\\t[}\\t_iw\\t|'
    //   11: dup
    //   12: astore_2
    //   13: invokevirtual length : ()I
    //   16: istore #4
    //   18: bipush #32
    //   20: istore_1
    //   21: iconst_m1
    //   22: istore_0
    //   23: bipush #110
    //   25: iinc #0, 1
    //   28: aload_2
    //   29: iload_0
    //   30: dup
    //   31: iload_1
    //   32: iadd
    //   33: invokevirtual substring : (II)Ljava/lang/String;
    //   36: iconst_m1
    //   37: goto -> 143
    //   40: aload #5
    //   42: swap
    //   43: iload_3
    //   44: iinc #3, 1
    //   47: swap
    //   48: aastore
    //   49: iload_0
    //   50: iload_1
    //   51: iadd
    //   52: dup
    //   53: istore_0
    //   54: iload #4
    //   56: if_icmpge -> 68
    //   59: aload_2
    //   60: iload_0
    //   61: invokevirtual charAt : (I)C
    //   64: istore_1
    //   65: goto -> 23
    //   68: ldc '@H@{Okn'
    //   70: dup
    //   71: astore_2
    //   72: invokevirtual length : ()I
    //   75: istore #4
    //   77: bipush #9
    //   79: istore_1
    //   80: iconst_m1
    //   81: istore_0
    //   82: bipush #117
    //   84: iinc #0, 1
    //   87: aload_2
    //   88: iload_0
    //   89: dup
    //   90: iload_1
    //   91: iadd
    //   92: invokevirtual substring : (II)Ljava/lang/String;
    //   95: iconst_0
    //   96: goto -> 143
    //   99: aload #5
    //   101: swap
    //   102: iload_3
    //   103: iinc #3, 1
    //   106: swap
    //   107: aastore
    //   108: iload_0
    //   109: iload_1
    //   110: iadd
    //   111: dup
    //   112: istore_0
    //   113: iload #4
    //   115: if_icmpge -> 127
    //   118: aload_2
    //   119: iload_0
    //   120: invokevirtual charAt : (I)C
    //   123: istore_1
    //   124: goto -> 82
    //   127: aload #5
    //   129: putstatic burp/Zgd7.a : [Ljava/lang/String;
    //   132: bipush #8
    //   134: anewarray java/lang/String
    //   137: putstatic burp/Zgd7.b : [Ljava/lang/String;
    //   140: goto -> 300
    //   143: dup_x2
    //   144: pop
    //   145: invokevirtual toCharArray : ()[C
    //   148: dup_x1
    //   149: arraylength
    //   150: dup_x2
    //   151: pop
    //   152: iconst_0
    //   153: istore #6
    //   155: dup2_x1
    //   156: pop2
    //   157: dup_x2
    //   158: iconst_1
    //   159: if_icmpgt -> 260
    //   162: dup2
    //   163: swap
    //   164: iload #6
    //   166: dup2_x1
    //   167: caload
    //   168: swap
    //   169: iload #6
    //   171: bipush #7
    //   173: irem
    //   174: tableswitch default -> 242, 0 -> 212, 1 -> 217, 2 -> 222, 3 -> 227, 4 -> 232, 5 -> 237
    //   212: bipush #96
    //   214: goto -> 244
    //   217: bipush #28
    //   219: goto -> 244
    //   222: bipush #12
    //   224: goto -> 244
    //   227: bipush #9
    //   229: goto -> 244
    //   232: bipush #75
    //   234: goto -> 244
    //   237: bipush #56
    //   239: goto -> 244
    //   242: bipush #43
    //   244: ixor
    //   245: ixor
    //   246: i2c
    //   247: castore
    //   248: iinc #6, 1
    //   251: dup
    //   252: ifne -> 260
    //   255: dup2
    //   256: dup_x1
    //   257: goto -> 166
    //   260: dup2_x1
    //   261: pop2
    //   262: dup_x2
    //   263: iload #6
    //   265: if_icmpgt -> 162
    //   268: pop
    //   269: new java/lang/String
    //   272: dup_x1
    //   273: swap
    //   274: invokespecial <init> : ([C)V
    //   277: invokevirtual intern : ()Ljava/lang/String;
    //   280: swap
    //   281: pop
    //   282: swap
    //   283: tableswitch default -> 40, 0 -> 99
    //   300: sipush #25270
    //   303: sipush #7086
    //   306: invokestatic a : (II)Ljava/lang/String;
    //   309: putstatic burp/Zgd7.Zs : Ljava/lang/String;
    //   312: new java/math/BigInteger
    //   315: dup
    //   316: iconst_1
    //   317: bipush #32
    //   319: newarray byte
    //   321: dup
    //   322: iconst_0
    //   323: bipush #77
    //   325: bastore
    //   326: dup
    //   327: iconst_1
    //   328: bipush #100
    //   330: bastore
    //   331: dup
    //   332: iconst_2
    //   333: bipush #104
    //   335: bastore
    //   336: dup
    //   337: iconst_3
    //   338: bipush #-15
    //   340: bastore
    //   341: dup
    //   342: iconst_4
    //   343: bipush #43
    //   345: bastore
    //   346: dup
    //   347: iconst_5
    //   348: bipush #17
    //   350: bastore
    //   351: dup
    //   352: bipush #6
    //   354: bipush #-80
    //   356: bastore
    //   357: dup
    //   358: bipush #7
    //   360: bipush #50
    //   362: bastore
    //   363: dup
    //   364: bipush #8
    //   366: bipush #100
    //   368: bastore
    //   369: dup
    //   370: bipush #9
    //   372: bipush #-9
    //   374: bastore
    //   375: dup
    //   376: bipush #10
    //   378: bipush #-126
    //   380: bastore
    //   381: dup
    //   382: bipush #11
    //   384: bipush #-18
    //   386: bastore
    //   387: dup
    //   388: bipush #12
    //   390: bipush #-29
    //   392: bastore
    //   393: dup
    //   394: bipush #13
    //   396: bipush #55
    //   398: bastore
    //   399: dup
    //   400: bipush #14
    //   402: bipush #-75
    //   404: bastore
    //   405: dup
    //   406: bipush #15
    //   408: bipush #-5
    //   410: bastore
    //   411: dup
    //   412: bipush #16
    //   414: bipush #14
    //   416: bastore
    //   417: dup
    //   418: bipush #17
    //   420: bipush #-39
    //   422: bastore
    //   423: dup
    //   424: bipush #18
    //   426: bipush #-124
    //   428: bastore
    //   429: dup
    //   430: bipush #19
    //   432: bipush #107
    //   434: bastore
    //   435: dup
    //   436: bipush #20
    //   438: bipush #-22
    //   440: bastore
    //   441: dup
    //   442: bipush #21
    //   444: bipush #17
    //   446: bastore
    //   447: dup
    //   448: bipush #22
    //   450: bipush #-36
    //   452: bastore
    //   453: dup
    //   454: bipush #23
    //   456: bipush #-16
    //   458: bastore
    //   459: dup
    //   460: bipush #24
    //   462: bipush #30
    //   464: bastore
    //   465: dup
    //   466: bipush #25
    //   468: bipush #26
    //   470: bastore
    //   471: dup
    //   472: bipush #26
    //   474: bipush #-92
    //   476: bastore
    //   477: dup
    //   478: bipush #27
    //   480: bipush #96
    //   482: bastore
    //   483: dup
    //   484: bipush #28
    //   486: bipush #-68
    //   488: bastore
    //   489: dup
    //   490: bipush #29
    //   492: bipush #-13
    //   494: bastore
    //   495: dup
    //   496: bipush #30
    //   498: bipush #81
    //   500: bastore
    //   501: dup
    //   502: bipush #31
    //   504: bipush #-73
    //   506: bastore
    //   507: invokespecial <init> : (I[B)V
    //   510: putstatic burp/Zgd7.ZZ : Ljava/lang/Object;
    //   513: return
  }
  
  private static Throwable a(Throwable paramThrowable) {
    return paramThrowable;
  }
  
  private static String a(int paramInt1, int paramInt2) {
    int i = (paramInt1 ^ 0x62B6) & 0xFFFF;
    if (b[i] == null) {
      char[] arrayOfChar = a[i].toCharArray();
      switch (arrayOfChar[0] & 0xFF) {
        case 0:
        
        case 1:
        
        case 2:
        
        case 3:
        
        case 4:
        
        case 5:
        
        case 6:
        
        case 7:
        
        case 8:
        
        case 9:
        
        case 10:
        
        case 11:
        
        case 12:
        
        case 13:
        
        case 14:
        
        case 15:
        
        case 16:
        
        case 17:
        
        case 18:
        
        case 19:
        
        case 20:
        
        case 21:
        
        case 22:
        
        case 23:
        
        case 24:
        
        case 25:
        
        case 26:
        
        case 27:
        
        case 28:
        
        case 29:
        
        case 30:
        
        case 31:
        
        case 32:
        
        case 33:
        
        case 34:
        
        case 35:
        
        case 36:
        
        case 37:
        
        case 38:
        
        case 39:
        
        case 40:
        
        case 41:
        
        case 42:
        
        case 43:
        
        case 44:
        
        case 45:
        
        case 46:
        
        case 47:
        
        case 48:
        
        case 49:
        
        case 50:
        
        case 51:
        
        case 52:
        
        case 53:
        
        case 54:
        
        case 55:
        
        case 56:
        
        case 57:
        
        case 58:
        
        case 59:
        
        case 60:
        
        case 61:
        
        case 62:
        
        case 63:
        
        case 64:
        
        case 65:
        
        case 66:
        
        case 67:
        
        case 68:
        
        case 69:
        
        case 70:
        
        case 71:
        
        case 72:
        
        case 73:
        
        case 74:
        
        case 75:
        
        case 76:
        
        case 77:
        
        case 78:
        
        case 79:
        
        case 80:
        
        case 81:
        
        case 82:
        
        case 83:
        
        case 84:
        
        case 85:
        
        case 86:
        
        case 87:
        
        case 88:
        
        case 89:
        
        case 90:
        
        case 91:
        
        case 92:
        
        case 93:
        
        case 94:
        
        case 95:
        
        case 96:
        
        case 97:
        
        case 98:
        
        case 99:
        
        case 100:
        
        case 101:
        
        case 102:
        
        case 103:
        
        case 104:
        
        case 105:
        
        case 106:
        
        case 107:
        
        case 108:
        
        case 109:
        
        case 110:
        
        case 111:
        
        case 112:
        
        case 113:
        
        case 114:
        
        case 115:
        
        case 116:
        
        case 117:
        
        case 118:
        
        case 119:
        
        case 120:
        
        case 121:
        
        case 122:
        
        case 123:
        
        case 124:
        
        case 125:
        
        case 126:
        
        case 127:
        
        case 128:
        
        case 129:
        
        case 130:
        
        case 131:
        
        case 132:
        
        case 133:
        
        case 134:
        
        case 135:
        
        case 136:
        
        case 137:
        
        case 138:
        
        case 139:
        
        case 140:
        
        case 141:
        
        case 142:
        
        case 143:
        
        case 144:
        
        case 145:
        
        case 146:
        
        case 147:
        
        case 148:
        
        case 149:
        
        case 150:
        
        case 151:
        
        case 152:
        
        case 153:
        
        case 154:
        
        case 155:
        
        case 156:
        
        case 157:
        
        case 158:
        
        case 159:
        
        case 160:
        
        case 161:
        
        case 162:
        
        case 163:
        
        case 164:
        
        case 165:
        
        case 166:
        
        case 167:
        
        case 168:
        
        case 169:
        
        case 170:
        
        case 171:
        
        case 172:
        
        case 173:
        
        case 174:
        
        case 175:
        
        case 176:
        
        case 177:
        
        case 178:
        
        case 179:
        
        case 180:
        
        case 181:
        
        case 182:
        
        case 183:
        
        case 184:
        
        case 185:
        
        case 186:
        
        case 187:
        
        case 188:
        
        case 189:
        
        case 190:
        
        case 191:
        
        case 192:
        
        case 193:
        
        case 194:
        
        case 195:
        
        case 196:
        
        case 197:
        
        case 198:
        
        case 199:
        
        case 200:
        
        case 201:
        
        case 202:
        
        case 203:
        
        case 204:
        
        case 205:
        
        case 206:
        
        case 207:
        
        case 208:
        
        case 209:
        
        case 210:
        
        case 211:
        
        case 212:
        
        case 213:
        
        case 214:
        
        case 215:
        
        case 216:
        
        case 217:
        
        case 218:
        
        case 219:
        
        case 220:
        
        case 221:
        
        case 222:
        
        case 223:
        
        case 224:
        
        case 225:
        
        case 226:
        
        case 227:
        
        case 228:
        
        case 229:
        
        case 230:
        
        case 231:
        
        case 232:
        
        case 233:
        
        case 234:
        
        case 235:
        
        case 236:
        
        case 237:
        
        case 238:
        
        case 239:
        
        case 240:
        
        case 241:
        
        case 242:
        
        case 243:
        
        case 244:
        
        case 245:
        
        case 246:
        
        case 247:
        
        case 248:
        
        case 249:
        
        case 250:
        
        case 251:
        
        case 252:
        
        case 253:
        
        case 254:
        
        default:
          break;
      } 
      char c = '';
      int j = (paramInt2 & 0xFF) - c;
      if (j < 0)
        j += 256; 
      int k = ((paramInt2 & 0xFFFF) >>> 8) - c;
      if (k < 0)
        k += 256; 
      for (byte b = 0; b < arrayOfChar.length; b++) {
        int m = b % 2;
        if (m == 0) {
          arrayOfChar[b] = (char)(arrayOfChar[b] ^ j);
          j = ((j >>> 3 | j << 5) ^ arrayOfChar[b]) & 0xFF;
        } else {
          arrayOfChar[b] = (char)(arrayOfChar[b] ^ k);
          k = ((k >>> 3 | k << 5) ^ arrayOfChar[b]) & 0xFF;
        } 
      } 
      b[i] = (new String(arrayOfChar)).intern();
    } 
    return b[i];
  }
}


/* Location:              C:\Program Files\BurpSuitePro\burpsuite_pro.jar!\burp\Zgd7.class
 * Java compiler version: 21 (65.0)
 * JD-Core Version:       1.1.3
 */