package burp;

import java.math.BigInteger;

class Zgdj extends ClassLoader {
  static Object ZT;
  
  static String Zt;
  
  private static final String[] a;
  
  private static final String[] b;
  
  static boolean Zh(Object[] paramArrayOfObject, Object paramObject) throws Throwable {
    // Byte code:
    //   0: invokestatic ZK : ()Z
    //   3: istore_2
    //   4: getstatic burp/Zlyf.Zm : Ljava/lang/Object;
    //   7: checkcast java/math/BigInteger
    //   10: invokevirtual toByteArray : ()[B
    //   13: astore_3
    //   14: iconst_0
    //   15: istore #5
    //   17: iconst_0
    //   18: istore #6
    //   20: iload #6
    //   22: aload_3
    //   23: arraylength
    //   24: if_icmpge -> 169
    //   27: aload_3
    //   28: iload #6
    //   30: baload
    //   31: istore #7
    //   33: iload #7
    //   35: bipush #48
    //   37: if_icmplt -> 54
    //   40: iload #7
    //   42: bipush #57
    //   44: if_icmple -> 152
    //   47: goto -> 54
    //   50: invokestatic a : (Ljava/lang/Throwable;)Ljava/lang/Throwable;
    //   53: athrow
    //   54: iload #7
    //   56: bipush #65
    //   58: if_icmplt -> 82
    //   61: goto -> 68
    //   64: invokestatic a : (Ljava/lang/Throwable;)Ljava/lang/Throwable;
    //   67: athrow
    //   68: iload #7
    //   70: bipush #90
    //   72: if_icmple -> 152
    //   75: goto -> 82
    //   78: invokestatic a : (Ljava/lang/Throwable;)Ljava/lang/Throwable;
    //   81: athrow
    //   82: iload #7
    //   84: bipush #97
    //   86: if_icmplt -> 110
    //   89: goto -> 96
    //   92: invokestatic a : (Ljava/lang/Throwable;)Ljava/lang/Throwable;
    //   95: athrow
    //   96: iload #7
    //   98: bipush #122
    //   100: if_icmple -> 152
    //   103: goto -> 110
    //   106: invokestatic a : (Ljava/lang/Throwable;)Ljava/lang/Throwable;
    //   109: athrow
    //   110: iload #7
    //   112: bipush #43
    //   114: if_icmpeq -> 152
    //   117: goto -> 124
    //   120: invokestatic a : (Ljava/lang/Throwable;)Ljava/lang/Throwable;
    //   123: athrow
    //   124: iload #7
    //   126: bipush #47
    //   128: if_icmpeq -> 152
    //   131: goto -> 138
    //   134: invokestatic a : (Ljava/lang/Throwable;)Ljava/lang/Throwable;
    //   137: athrow
    //   138: iload #7
    //   140: bipush #61
    //   142: if_icmpne -> 162
    //   145: goto -> 152
    //   148: invokestatic a : (Ljava/lang/Throwable;)Ljava/lang/Throwable;
    //   151: athrow
    //   152: iinc #5, 1
    //   155: goto -> 162
    //   158: invokestatic a : (Ljava/lang/Throwable;)Ljava/lang/Throwable;
    //   161: athrow
    //   162: iinc #6, 1
    //   165: iload_2
    //   166: ifeq -> 20
    //   169: iload #5
    //   171: newarray byte
    //   173: astore #6
    //   175: iconst_0
    //   176: istore #7
    //   178: iconst_0
    //   179: istore #8
    //   181: iload #8
    //   183: aload_3
    //   184: arraylength
    //   185: if_icmpge -> 337
    //   188: aload_3
    //   189: iload #8
    //   191: baload
    //   192: istore #9
    //   194: iload #9
    //   196: bipush #48
    //   198: if_icmplt -> 215
    //   201: iload #9
    //   203: bipush #57
    //   205: if_icmple -> 313
    //   208: goto -> 215
    //   211: invokestatic a : (Ljava/lang/Throwable;)Ljava/lang/Throwable;
    //   214: athrow
    //   215: iload #9
    //   217: bipush #65
    //   219: if_icmplt -> 243
    //   222: goto -> 229
    //   225: invokestatic a : (Ljava/lang/Throwable;)Ljava/lang/Throwable;
    //   228: athrow
    //   229: iload #9
    //   231: bipush #90
    //   233: if_icmple -> 313
    //   236: goto -> 243
    //   239: invokestatic a : (Ljava/lang/Throwable;)Ljava/lang/Throwable;
    //   242: athrow
    //   243: iload #9
    //   245: bipush #97
    //   247: if_icmplt -> 271
    //   250: goto -> 257
    //   253: invokestatic a : (Ljava/lang/Throwable;)Ljava/lang/Throwable;
    //   256: athrow
    //   257: iload #9
    //   259: bipush #122
    //   261: if_icmple -> 313
    //   264: goto -> 271
    //   267: invokestatic a : (Ljava/lang/Throwable;)Ljava/lang/Throwable;
    //   270: athrow
    //   271: iload #9
    //   273: bipush #43
    //   275: if_icmpeq -> 313
    //   278: goto -> 285
    //   281: invokestatic a : (Ljava/lang/Throwable;)Ljava/lang/Throwable;
    //   284: athrow
    //   285: iload #9
    //   287: bipush #47
    //   289: if_icmpeq -> 313
    //   292: goto -> 299
    //   295: invokestatic a : (Ljava/lang/Throwable;)Ljava/lang/Throwable;
    //   298: athrow
    //   299: iload #9
    //   301: bipush #61
    //   303: if_icmpne -> 330
    //   306: goto -> 313
    //   309: invokestatic a : (Ljava/lang/Throwable;)Ljava/lang/Throwable;
    //   312: athrow
    //   313: aload #6
    //   315: iload #7
    //   317: iload #9
    //   319: bastore
    //   320: iinc #7, 1
    //   323: goto -> 330
    //   326: invokestatic a : (Ljava/lang/Throwable;)Ljava/lang/Throwable;
    //   329: athrow
    //   330: iinc #8, 1
    //   333: iload_2
    //   334: ifeq -> 181
    //   337: aload #6
    //   339: astore #4
    //   341: aload #4
    //   343: astore_3
    //   344: aload_3
    //   345: arraylength
    //   346: istore #5
    //   348: aload_3
    //   349: iload #5
    //   351: iconst_1
    //   352: isub
    //   353: baload
    //   354: bipush #61
    //   356: if_icmpne -> 366
    //   359: iinc #5, -1
    //   362: iload_2
    //   363: ifeq -> 348
    //   366: iload #5
    //   368: aload_3
    //   369: arraylength
    //   370: iconst_4
    //   371: idiv
    //   372: isub
    //   373: newarray byte
    //   375: astore #6
    //   377: iconst_0
    //   378: istore #7
    //   380: iload #7
    //   382: aload_3
    //   383: arraylength
    //   384: if_icmpge -> 646
    //   387: aload_3
    //   388: iload #7
    //   390: baload
    //   391: bipush #61
    //   393: if_icmpne -> 412
    //   396: aload_3
    //   397: iload #7
    //   399: iconst_0
    //   400: bastore
    //   401: iload_2
    //   402: ifeq -> 639
    //   405: goto -> 412
    //   408: invokestatic a : (Ljava/lang/Throwable;)Ljava/lang/Throwable;
    //   411: athrow
    //   412: aload_3
    //   413: iload #7
    //   415: baload
    //   416: bipush #47
    //   418: if_icmpne -> 445
    //   421: goto -> 428
    //   424: invokestatic a : (Ljava/lang/Throwable;)Ljava/lang/Throwable;
    //   427: athrow
    //   428: aload_3
    //   429: iload #7
    //   431: bipush #63
    //   433: bastore
    //   434: iload_2
    //   435: ifeq -> 639
    //   438: goto -> 445
    //   441: invokestatic a : (Ljava/lang/Throwable;)Ljava/lang/Throwable;
    //   444: athrow
    //   445: aload_3
    //   446: iload #7
    //   448: baload
    //   449: bipush #43
    //   451: if_icmpne -> 478
    //   454: goto -> 461
    //   457: invokestatic a : (Ljava/lang/Throwable;)Ljava/lang/Throwable;
    //   460: athrow
    //   461: aload_3
    //   462: iload #7
    //   464: bipush #62
    //   466: bastore
    //   467: iload_2
    //   468: ifeq -> 639
    //   471: goto -> 478
    //   474: invokestatic a : (Ljava/lang/Throwable;)Ljava/lang/Throwable;
    //   477: athrow
    //   478: aload_3
    //   479: iload #7
    //   481: baload
    //   482: bipush #48
    //   484: if_icmplt -> 533
    //   487: goto -> 494
    //   490: invokestatic a : (Ljava/lang/Throwable;)Ljava/lang/Throwable;
    //   493: athrow
    //   494: aload_3
    //   495: iload #7
    //   497: baload
    //   498: bipush #57
    //   500: if_icmpgt -> 533
    //   503: goto -> 510
    //   506: invokestatic a : (Ljava/lang/Throwable;)Ljava/lang/Throwable;
    //   509: athrow
    //   510: aload_3
    //   511: iload #7
    //   513: aload_3
    //   514: iload #7
    //   516: baload
    //   517: bipush #-4
    //   519: isub
    //   520: i2b
    //   521: bastore
    //   522: iload_2
    //   523: ifeq -> 639
    //   526: goto -> 533
    //   529: invokestatic a : (Ljava/lang/Throwable;)Ljava/lang/Throwable;
    //   532: athrow
    //   533: aload_3
    //   534: iload #7
    //   536: baload
    //   537: bipush #97
    //   539: if_icmplt -> 588
    //   542: goto -> 549
    //   545: invokestatic a : (Ljava/lang/Throwable;)Ljava/lang/Throwable;
    //   548: athrow
    //   549: aload_3
    //   550: iload #7
    //   552: baload
    //   553: bipush #122
    //   555: if_icmpgt -> 588
    //   558: goto -> 565
    //   561: invokestatic a : (Ljava/lang/Throwable;)Ljava/lang/Throwable;
    //   564: athrow
    //   565: aload_3
    //   566: iload #7
    //   568: aload_3
    //   569: iload #7
    //   571: baload
    //   572: bipush #71
    //   574: isub
    //   575: i2b
    //   576: bastore
    //   577: iload_2
    //   578: ifeq -> 639
    //   581: goto -> 588
    //   584: invokestatic a : (Ljava/lang/Throwable;)Ljava/lang/Throwable;
    //   587: athrow
    //   588: aload_3
    //   589: iload #7
    //   591: baload
    //   592: bipush #65
    //   594: if_icmplt -> 639
    //   597: goto -> 604
    //   600: invokestatic a : (Ljava/lang/Throwable;)Ljava/lang/Throwable;
    //   603: athrow
    //   604: aload_3
    //   605: iload #7
    //   607: baload
    //   608: bipush #90
    //   610: if_icmpgt -> 639
    //   613: goto -> 620
    //   616: invokestatic a : (Ljava/lang/Throwable;)Ljava/lang/Throwable;
    //   619: athrow
    //   620: aload_3
    //   621: iload #7
    //   623: aload_3
    //   624: iload #7
    //   626: baload
    //   627: bipush #65
    //   629: isub
    //   630: i2b
    //   631: bastore
    //   632: goto -> 639
    //   635: invokestatic a : (Ljava/lang/Throwable;)Ljava/lang/Throwable;
    //   638: athrow
    //   639: iinc #7, 1
    //   642: iload_2
    //   643: ifeq -> 380
    //   646: iconst_0
    //   647: istore #7
    //   649: iconst_0
    //   650: istore #8
    //   652: iload #8
    //   654: aload #6
    //   656: arraylength
    //   657: iconst_2
    //   658: isub
    //   659: if_icmpge -> 762
    //   662: aload #6
    //   664: iload #8
    //   666: aload_3
    //   667: iload #7
    //   669: baload
    //   670: iconst_2
    //   671: ishl
    //   672: sipush #255
    //   675: iand
    //   676: aload_3
    //   677: iload #7
    //   679: iconst_1
    //   680: iadd
    //   681: baload
    //   682: iconst_4
    //   683: iushr
    //   684: iconst_3
    //   685: iand
    //   686: ior
    //   687: i2b
    //   688: bastore
    //   689: aload #6
    //   691: iload #8
    //   693: iconst_1
    //   694: iadd
    //   695: aload_3
    //   696: iload #7
    //   698: iconst_1
    //   699: iadd
    //   700: baload
    //   701: iconst_4
    //   702: ishl
    //   703: sipush #255
    //   706: iand
    //   707: aload_3
    //   708: iload #7
    //   710: iconst_2
    //   711: iadd
    //   712: baload
    //   713: iconst_2
    //   714: iushr
    //   715: bipush #15
    //   717: iand
    //   718: ior
    //   719: i2b
    //   720: bastore
    //   721: aload #6
    //   723: iload #8
    //   725: iconst_2
    //   726: iadd
    //   727: aload_3
    //   728: iload #7
    //   730: iconst_2
    //   731: iadd
    //   732: baload
    //   733: bipush #6
    //   735: ishl
    //   736: sipush #255
    //   739: iand
    //   740: aload_3
    //   741: iload #7
    //   743: iconst_3
    //   744: iadd
    //   745: baload
    //   746: bipush #63
    //   748: iand
    //   749: ior
    //   750: i2b
    //   751: bastore
    //   752: iinc #7, 4
    //   755: iinc #8, 3
    //   758: iload_2
    //   759: ifeq -> 652
    //   762: iload #8
    //   764: aload #6
    //   766: arraylength
    //   767: if_icmpge -> 804
    //   770: aload #6
    //   772: iload #8
    //   774: aload_3
    //   775: iload #7
    //   777: baload
    //   778: iconst_2
    //   779: ishl
    //   780: sipush #255
    //   783: iand
    //   784: aload_3
    //   785: iload #7
    //   787: iconst_1
    //   788: iadd
    //   789: baload
    //   790: iconst_4
    //   791: iushr
    //   792: iconst_3
    //   793: iand
    //   794: ior
    //   795: i2b
    //   796: bastore
    //   797: goto -> 804
    //   800: invokestatic a : (Ljava/lang/Throwable;)Ljava/lang/Throwable;
    //   803: athrow
    //   804: iinc #8, 1
    //   807: iload #8
    //   809: aload #6
    //   811: arraylength
    //   812: if_icmpge -> 852
    //   815: aload #6
    //   817: iload #8
    //   819: aload_3
    //   820: iload #7
    //   822: iconst_1
    //   823: iadd
    //   824: baload
    //   825: iconst_4
    //   826: ishl
    //   827: sipush #255
    //   830: iand
    //   831: aload_3
    //   832: iload #7
    //   834: iconst_2
    //   835: iadd
    //   836: baload
    //   837: iconst_2
    //   838: iushr
    //   839: bipush #15
    //   841: iand
    //   842: ior
    //   843: i2b
    //   844: bastore
    //   845: goto -> 852
    //   848: invokestatic a : (Ljava/lang/Throwable;)Ljava/lang/Throwable;
    //   851: athrow
    //   852: aload #6
    //   854: astore #4
    //   856: new java/math/BigInteger
    //   859: dup
    //   860: aload #4
    //   862: invokespecial <init> : ([B)V
    //   865: invokevirtual abs : ()Ljava/math/BigInteger;
    //   868: putstatic burp/Zejg.ZR : Ljava/lang/Object;
    //   871: new java/lang/StringBuilder
    //   874: dup
    //   875: invokespecial <init> : ()V
    //   878: astore_3
    //   879: iconst_0
    //   880: istore #4
    //   882: iload #4
    //   884: bipush #32
    //   886: if_icmpge -> 2219
    //   889: iload #4
    //   891: tableswitch default -> 2212, 0 -> 1032, 1 -> 1069, 2 -> 1106, 3 -> 1143, 4 -> 1180, 5 -> 1217, 6 -> 1254, 7 -> 1291, 8 -> 1328, 9 -> 1365, 10 -> 1402, 11 -> 1439, 12 -> 1476, 13 -> 1513, 14 -> 1550, 15 -> 1587, 16 -> 1624, 17 -> 1661, 18 -> 1698, 19 -> 1735, 20 -> 1772, 21 -> 1809, 22 -> 1846, 23 -> 1883, 24 -> 1920, 25 -> 1957, 26 -> 1994, 27 -> 2031, 28 -> 2068, 29 -> 2105, 30 -> 2142, 31 -> 2179
    //   1032: aload_3
    //   1033: getstatic burp/Zljx.ZD : Ljava/lang/String;
    //   1036: getstatic burp/Zebj.Zf : Ljava/lang/Object;
    //   1039: checkcast java/math/BigInteger
    //   1042: invokevirtual intValue : ()I
    //   1045: bipush #32
    //   1047: irem
    //   1048: invokestatic abs : (I)I
    //   1051: invokevirtual charAt : (I)C
    //   1054: invokevirtual append : (C)Ljava/lang/StringBuilder;
    //   1057: pop
    //   1058: iload_2
    //   1059: ifeq -> 2212
    //   1062: goto -> 1069
    //   1065: invokestatic a : (Ljava/lang/Throwable;)Ljava/lang/Throwable;
    //   1068: athrow
    //   1069: aload_3
    //   1070: getstatic burp/Zmhx.ZD : Ljava/lang/String;
    //   1073: getstatic burp/Zei_.Za : Ljava/lang/Object;
    //   1076: checkcast java/math/BigInteger
    //   1079: invokevirtual intValue : ()I
    //   1082: bipush #32
    //   1084: irem
    //   1085: invokestatic abs : (I)I
    //   1088: invokevirtual charAt : (I)C
    //   1091: invokevirtual append : (C)Ljava/lang/StringBuilder;
    //   1094: pop
    //   1095: iload_2
    //   1096: ifeq -> 2212
    //   1099: goto -> 1106
    //   1102: invokestatic a : (Ljava/lang/Throwable;)Ljava/lang/Throwable;
    //   1105: athrow
    //   1106: aload_3
    //   1107: getstatic burp/Zxyq.Zr : Ljava/lang/String;
    //   1110: getstatic burp/Zz58.ZD : Ljava/lang/Object;
    //   1113: checkcast java/math/BigInteger
    //   1116: invokevirtual intValue : ()I
    //   1119: bipush #32
    //   1121: irem
    //   1122: invokestatic abs : (I)I
    //   1125: invokevirtual charAt : (I)C
    //   1128: invokevirtual append : (C)Ljava/lang/StringBuilder;
    //   1131: pop
    //   1132: iload_2
    //   1133: ifeq -> 2212
    //   1136: goto -> 1143
    //   1139: invokestatic a : (Ljava/lang/Throwable;)Ljava/lang/Throwable;
    //   1142: athrow
    //   1143: aload_3
    //   1144: getstatic burp/Zb3p.ZX : Ljava/lang/String;
    //   1147: getstatic burp/Zmt6.ZK : Ljava/lang/Object;
    //   1150: checkcast java/math/BigInteger
    //   1153: invokevirtual intValue : ()I
    //   1156: bipush #32
    //   1158: irem
    //   1159: invokestatic abs : (I)I
    //   1162: invokevirtual charAt : (I)C
    //   1165: invokevirtual append : (C)Ljava/lang/StringBuilder;
    //   1168: pop
    //   1169: iload_2
    //   1170: ifeq -> 2212
    //   1173: goto -> 1180
    //   1176: invokestatic a : (Ljava/lang/Throwable;)Ljava/lang/Throwable;
    //   1179: athrow
    //   1180: aload_3
    //   1181: getstatic burp/Ztpa.ZZ : Ljava/lang/String;
    //   1184: getstatic burp/Zmiy.Zi : Ljava/lang/Object;
    //   1187: checkcast java/math/BigInteger
    //   1190: invokevirtual intValue : ()I
    //   1193: bipush #32
    //   1195: irem
    //   1196: invokestatic abs : (I)I
    //   1199: invokevirtual charAt : (I)C
    //   1202: invokevirtual append : (C)Ljava/lang/StringBuilder;
    //   1205: pop
    //   1206: iload_2
    //   1207: ifeq -> 2212
    //   1210: goto -> 1217
    //   1213: invokestatic a : (Ljava/lang/Throwable;)Ljava/lang/Throwable;
    //   1216: athrow
    //   1217: aload_3
    //   1218: getstatic burp/Zzwl.Zy : Ljava/lang/String;
    //   1221: getstatic burp/Zkul.Zb : Ljava/lang/Object;
    //   1224: checkcast java/math/BigInteger
    //   1227: invokevirtual intValue : ()I
    //   1230: bipush #32
    //   1232: irem
    //   1233: invokestatic abs : (I)I
    //   1236: invokevirtual charAt : (I)C
    //   1239: invokevirtual append : (C)Ljava/lang/StringBuilder;
    //   1242: pop
    //   1243: iload_2
    //   1244: ifeq -> 2212
    //   1247: goto -> 1254
    //   1250: invokestatic a : (Ljava/lang/Throwable;)Ljava/lang/Throwable;
    //   1253: athrow
    //   1254: aload_3
    //   1255: getstatic burp/Zty3.ZW : Ljava/lang/String;
    //   1258: getstatic burp/Zk7w.ZF : Ljava/lang/Object;
    //   1261: checkcast java/math/BigInteger
    //   1264: invokevirtual intValue : ()I
    //   1267: bipush #32
    //   1269: irem
    //   1270: invokestatic abs : (I)I
    //   1273: invokevirtual charAt : (I)C
    //   1276: invokevirtual append : (C)Ljava/lang/StringBuilder;
    //   1279: pop
    //   1280: iload_2
    //   1281: ifeq -> 2212
    //   1284: goto -> 1291
    //   1287: invokestatic a : (Ljava/lang/Throwable;)Ljava/lang/Throwable;
    //   1290: athrow
    //   1291: aload_3
    //   1292: getstatic burp/Zs0b.ZT : Ljava/lang/String;
    //   1295: getstatic burp/Zsin.Za : Ljava/lang/Object;
    //   1298: checkcast java/math/BigInteger
    //   1301: invokevirtual intValue : ()I
    //   1304: bipush #32
    //   1306: irem
    //   1307: invokestatic abs : (I)I
    //   1310: invokevirtual charAt : (I)C
    //   1313: invokevirtual append : (C)Ljava/lang/StringBuilder;
    //   1316: pop
    //   1317: iload_2
    //   1318: ifeq -> 2212
    //   1321: goto -> 1328
    //   1324: invokestatic a : (Ljava/lang/Throwable;)Ljava/lang/Throwable;
    //   1327: athrow
    //   1328: aload_3
    //   1329: getstatic burp/Zlc5.Z_ : Ljava/lang/String;
    //   1332: getstatic burp/Zgny.ZR : Ljava/lang/Object;
    //   1335: checkcast java/math/BigInteger
    //   1338: invokevirtual intValue : ()I
    //   1341: bipush #32
    //   1343: irem
    //   1344: invokestatic abs : (I)I
    //   1347: invokevirtual charAt : (I)C
    //   1350: invokevirtual append : (C)Ljava/lang/StringBuilder;
    //   1353: pop
    //   1354: iload_2
    //   1355: ifeq -> 2212
    //   1358: goto -> 1365
    //   1361: invokestatic a : (Ljava/lang/Throwable;)Ljava/lang/Throwable;
    //   1364: athrow
    //   1365: aload_3
    //   1366: getstatic burp/Zz9p.ZC : Ljava/lang/String;
    //   1369: getstatic burp/Zsgj.ZK : Ljava/lang/Object;
    //   1372: checkcast java/math/BigInteger
    //   1375: invokevirtual intValue : ()I
    //   1378: bipush #32
    //   1380: irem
    //   1381: invokestatic abs : (I)I
    //   1384: invokevirtual charAt : (I)C
    //   1387: invokevirtual append : (C)Ljava/lang/StringBuilder;
    //   1390: pop
    //   1391: iload_2
    //   1392: ifeq -> 2212
    //   1395: goto -> 1402
    //   1398: invokestatic a : (Ljava/lang/Throwable;)Ljava/lang/Throwable;
    //   1401: athrow
    //   1402: aload_3
    //   1403: getstatic burp/Zsej.Zd : Ljava/lang/String;
    //   1406: getstatic burp/Zxsb.ZN : Ljava/lang/Object;
    //   1409: checkcast java/math/BigInteger
    //   1412: invokevirtual intValue : ()I
    //   1415: bipush #32
    //   1417: irem
    //   1418: invokestatic abs : (I)I
    //   1421: invokevirtual charAt : (I)C
    //   1424: invokevirtual append : (C)Ljava/lang/StringBuilder;
    //   1427: pop
    //   1428: iload_2
    //   1429: ifeq -> 2212
    //   1432: goto -> 1439
    //   1435: invokestatic a : (Ljava/lang/Throwable;)Ljava/lang/Throwable;
    //   1438: athrow
    //   1439: aload_3
    //   1440: getstatic burp/Zxd0.Zc : Ljava/lang/String;
    //   1443: getstatic burp/Zlyf.Zm : Ljava/lang/Object;
    //   1446: checkcast java/math/BigInteger
    //   1449: invokevirtual intValue : ()I
    //   1452: bipush #32
    //   1454: irem
    //   1455: invokestatic abs : (I)I
    //   1458: invokevirtual charAt : (I)C
    //   1461: invokevirtual append : (C)Ljava/lang/StringBuilder;
    //   1464: pop
    //   1465: iload_2
    //   1466: ifeq -> 2212
    //   1469: goto -> 1476
    //   1472: invokestatic a : (Ljava/lang/Throwable;)Ljava/lang/Throwable;
    //   1475: athrow
    //   1476: aload_3
    //   1477: getstatic burp/Ztte.ZD : Ljava/lang/String;
    //   1480: getstatic burp/Zxoa.Zr : Ljava/lang/Object;
    //   1483: checkcast java/math/BigInteger
    //   1486: invokevirtual intValue : ()I
    //   1489: bipush #32
    //   1491: irem
    //   1492: invokestatic abs : (I)I
    //   1495: invokevirtual charAt : (I)C
    //   1498: invokevirtual append : (C)Ljava/lang/StringBuilder;
    //   1501: pop
    //   1502: iload_2
    //   1503: ifeq -> 2212
    //   1506: goto -> 1513
    //   1509: invokestatic a : (Ljava/lang/Throwable;)Ljava/lang/Throwable;
    //   1512: athrow
    //   1513: aload_3
    //   1514: getstatic burp/Zejg.ZP : Ljava/lang/String;
    //   1517: getstatic burp/Zmjr.ZU : Ljava/lang/Object;
    //   1520: checkcast java/math/BigInteger
    //   1523: invokevirtual intValue : ()I
    //   1526: bipush #32
    //   1528: irem
    //   1529: invokestatic abs : (I)I
    //   1532: invokevirtual charAt : (I)C
    //   1535: invokevirtual append : (C)Ljava/lang/StringBuilder;
    //   1538: pop
    //   1539: iload_2
    //   1540: ifeq -> 2212
    //   1543: goto -> 1550
    //   1546: invokestatic a : (Ljava/lang/Throwable;)Ljava/lang/Throwable;
    //   1549: athrow
    //   1550: aload_3
    //   1551: getstatic burp/Zsgj.ZN : Ljava/lang/String;
    //   1554: getstatic burp/Zeyt.ZR : Ljava/lang/Object;
    //   1557: checkcast java/math/BigInteger
    //   1560: invokevirtual intValue : ()I
    //   1563: bipush #32
    //   1565: irem
    //   1566: invokestatic abs : (I)I
    //   1569: invokevirtual charAt : (I)C
    //   1572: invokevirtual append : (C)Ljava/lang/StringBuilder;
    //   1575: pop
    //   1576: iload_2
    //   1577: ifeq -> 2212
    //   1580: goto -> 1587
    //   1583: invokestatic a : (Ljava/lang/Throwable;)Ljava/lang/Throwable;
    //   1586: athrow
    //   1587: aload_3
    //   1588: getstatic burp/Zlc5.Z_ : Ljava/lang/String;
    //   1591: getstatic burp/Zxnm.ZW : Ljava/lang/Object;
    //   1594: checkcast java/math/BigInteger
    //   1597: invokevirtual intValue : ()I
    //   1600: bipush #32
    //   1602: irem
    //   1603: invokestatic abs : (I)I
    //   1606: invokevirtual charAt : (I)C
    //   1609: invokevirtual append : (C)Ljava/lang/StringBuilder;
    //   1612: pop
    //   1613: iload_2
    //   1614: ifeq -> 2212
    //   1617: goto -> 1624
    //   1620: invokestatic a : (Ljava/lang/Throwable;)Ljava/lang/Throwable;
    //   1623: athrow
    //   1624: aload_3
    //   1625: getstatic burp/Zead.Zo : Ljava/lang/String;
    //   1628: getstatic burp/Ztte.ZR : Ljava/lang/Object;
    //   1631: checkcast java/math/BigInteger
    //   1634: invokevirtual intValue : ()I
    //   1637: bipush #32
    //   1639: irem
    //   1640: invokestatic abs : (I)I
    //   1643: invokevirtual charAt : (I)C
    //   1646: invokevirtual append : (C)Ljava/lang/StringBuilder;
    //   1649: pop
    //   1650: iload_2
    //   1651: ifeq -> 2212
    //   1654: goto -> 1661
    //   1657: invokestatic a : (Ljava/lang/Throwable;)Ljava/lang/Throwable;
    //   1660: athrow
    //   1661: aload_3
    //   1662: getstatic burp/Zlyf.ZU : Ljava/lang/String;
    //   1665: getstatic burp/Zgkl.ZK : Ljava/lang/Object;
    //   1668: checkcast java/math/BigInteger
    //   1671: invokevirtual intValue : ()I
    //   1674: bipush #32
    //   1676: irem
    //   1677: invokestatic abs : (I)I
    //   1680: invokevirtual charAt : (I)C
    //   1683: invokevirtual append : (C)Ljava/lang/StringBuilder;
    //   1686: pop
    //   1687: iload_2
    //   1688: ifeq -> 2212
    //   1691: goto -> 1698
    //   1694: invokestatic a : (Ljava/lang/Throwable;)Ljava/lang/Throwable;
    //   1697: athrow
    //   1698: aload_3
    //   1699: getstatic burp/Ztid.Zz : Ljava/lang/String;
    //   1702: getstatic burp/Zei_.Za : Ljava/lang/Object;
    //   1705: checkcast java/math/BigInteger
    //   1708: invokevirtual intValue : ()I
    //   1711: bipush #32
    //   1713: irem
    //   1714: invokestatic abs : (I)I
    //   1717: invokevirtual charAt : (I)C
    //   1720: invokevirtual append : (C)Ljava/lang/StringBuilder;
    //   1723: pop
    //   1724: iload_2
    //   1725: ifeq -> 2212
    //   1728: goto -> 1735
    //   1731: invokestatic a : (Ljava/lang/Throwable;)Ljava/lang/Throwable;
    //   1734: athrow
    //   1735: aload_3
    //   1736: getstatic burp/Zghe.Zi : Ljava/lang/String;
    //   1739: getstatic burp/Zs0b.ZI : Ljava/lang/Object;
    //   1742: checkcast java/math/BigInteger
    //   1745: invokevirtual intValue : ()I
    //   1748: bipush #32
    //   1750: irem
    //   1751: invokestatic abs : (I)I
    //   1754: invokevirtual charAt : (I)C
    //   1757: invokevirtual append : (C)Ljava/lang/StringBuilder;
    //   1760: pop
    //   1761: iload_2
    //   1762: ifeq -> 2212
    //   1765: goto -> 1772
    //   1768: invokestatic a : (Ljava/lang/Throwable;)Ljava/lang/Throwable;
    //   1771: athrow
    //   1772: aload_3
    //   1773: getstatic burp/Zzc7.ZN : Ljava/lang/String;
    //   1776: getstatic burp/Zkvr.Zb : Ljava/lang/Object;
    //   1779: checkcast java/math/BigInteger
    //   1782: invokevirtual intValue : ()I
    //   1785: bipush #32
    //   1787: irem
    //   1788: invokestatic abs : (I)I
    //   1791: invokevirtual charAt : (I)C
    //   1794: invokevirtual append : (C)Ljava/lang/StringBuilder;
    //   1797: pop
    //   1798: iload_2
    //   1799: ifeq -> 2212
    //   1802: goto -> 1809
    //   1805: invokestatic a : (Ljava/lang/Throwable;)Ljava/lang/Throwable;
    //   1808: athrow
    //   1809: aload_3
    //   1810: getstatic burp/Zejg.ZP : Ljava/lang/String;
    //   1813: getstatic burp/Zmjr.ZU : Ljava/lang/Object;
    //   1816: checkcast java/math/BigInteger
    //   1819: invokevirtual intValue : ()I
    //   1822: bipush #32
    //   1824: irem
    //   1825: invokestatic abs : (I)I
    //   1828: invokevirtual charAt : (I)C
    //   1831: invokevirtual append : (C)Ljava/lang/StringBuilder;
    //   1834: pop
    //   1835: iload_2
    //   1836: ifeq -> 2212
    //   1839: goto -> 1846
    //   1842: invokestatic a : (Ljava/lang/Throwable;)Ljava/lang/Throwable;
    //   1845: athrow
    //   1846: aload_3
    //   1847: getstatic burp/Zb9k.Za : Ljava/lang/String;
    //   1850: getstatic burp/Zl_1.ZL : Ljava/lang/Object;
    //   1853: checkcast java/math/BigInteger
    //   1856: invokevirtual intValue : ()I
    //   1859: bipush #32
    //   1861: irem
    //   1862: invokestatic abs : (I)I
    //   1865: invokevirtual charAt : (I)C
    //   1868: invokevirtual append : (C)Ljava/lang/StringBuilder;
    //   1871: pop
    //   1872: iload_2
    //   1873: ifeq -> 2212
    //   1876: goto -> 1883
    //   1879: invokestatic a : (Ljava/lang/Throwable;)Ljava/lang/Throwable;
    //   1882: athrow
    //   1883: aload_3
    //   1884: getstatic burp/Zb3p.ZX : Ljava/lang/String;
    //   1887: getstatic burp/Zre1.ZN : Ljava/lang/Object;
    //   1890: checkcast java/math/BigInteger
    //   1893: invokevirtual intValue : ()I
    //   1896: bipush #32
    //   1898: irem
    //   1899: invokestatic abs : (I)I
    //   1902: invokevirtual charAt : (I)C
    //   1905: invokevirtual append : (C)Ljava/lang/StringBuilder;
    //   1908: pop
    //   1909: iload_2
    //   1910: ifeq -> 2212
    //   1913: goto -> 1920
    //   1916: invokestatic a : (Ljava/lang/Throwable;)Ljava/lang/Throwable;
    //   1919: athrow
    //   1920: aload_3
    //   1921: getstatic burp/Zs33.ZX : Ljava/lang/String;
    //   1924: getstatic burp/Zty5.Zf : Ljava/lang/Object;
    //   1927: checkcast java/math/BigInteger
    //   1930: invokevirtual intValue : ()I
    //   1933: bipush #32
    //   1935: irem
    //   1936: invokestatic abs : (I)I
    //   1939: invokevirtual charAt : (I)C
    //   1942: invokevirtual append : (C)Ljava/lang/StringBuilder;
    //   1945: pop
    //   1946: iload_2
    //   1947: ifeq -> 2212
    //   1950: goto -> 1957
    //   1953: invokestatic a : (Ljava/lang/Throwable;)Ljava/lang/Throwable;
    //   1956: athrow
    //   1957: aload_3
    //   1958: getstatic burp/Zkul.ZJ : Ljava/lang/String;
    //   1961: getstatic burp/Zezz.Zu : Ljava/lang/Object;
    //   1964: checkcast java/math/BigInteger
    //   1967: invokevirtual intValue : ()I
    //   1970: bipush #32
    //   1972: irem
    //   1973: invokestatic abs : (I)I
    //   1976: invokevirtual charAt : (I)C
    //   1979: invokevirtual append : (C)Ljava/lang/StringBuilder;
    //   1982: pop
    //   1983: iload_2
    //   1984: ifeq -> 2212
    //   1987: goto -> 1994
    //   1990: invokestatic a : (Ljava/lang/Throwable;)Ljava/lang/Throwable;
    //   1993: athrow
    //   1994: aload_3
    //   1995: getstatic burp/Zgwq.ZV : Ljava/lang/String;
    //   1998: getstatic burp/Zr_k.Zx : Ljava/lang/Object;
    //   2001: checkcast java/math/BigInteger
    //   2004: invokevirtual intValue : ()I
    //   2007: bipush #32
    //   2009: irem
    //   2010: invokestatic abs : (I)I
    //   2013: invokevirtual charAt : (I)C
    //   2016: invokevirtual append : (C)Ljava/lang/StringBuilder;
    //   2019: pop
    //   2020: iload_2
    //   2021: ifeq -> 2212
    //   2024: goto -> 2031
    //   2027: invokestatic a : (Ljava/lang/Throwable;)Ljava/lang/Throwable;
    //   2030: athrow
    //   2031: aload_3
    //   2032: getstatic burp/Zlc5.Z_ : Ljava/lang/String;
    //   2035: getstatic burp/Zsgj.ZK : Ljava/lang/Object;
    //   2038: checkcast java/math/BigInteger
    //   2041: invokevirtual intValue : ()I
    //   2044: bipush #32
    //   2046: irem
    //   2047: invokestatic abs : (I)I
    //   2050: invokevirtual charAt : (I)C
    //   2053: invokevirtual append : (C)Ljava/lang/StringBuilder;
    //   2056: pop
    //   2057: iload_2
    //   2058: ifeq -> 2212
    //   2061: goto -> 2068
    //   2064: invokestatic a : (Ljava/lang/Throwable;)Ljava/lang/Throwable;
    //   2067: athrow
    //   2068: aload_3
    //   2069: getstatic burp/Zgwq.ZV : Ljava/lang/String;
    //   2072: getstatic burp/Zxyq.ZQ : Ljava/lang/Object;
    //   2075: checkcast java/math/BigInteger
    //   2078: invokevirtual intValue : ()I
    //   2081: bipush #32
    //   2083: irem
    //   2084: invokestatic abs : (I)I
    //   2087: invokevirtual charAt : (I)C
    //   2090: invokevirtual append : (C)Ljava/lang/StringBuilder;
    //   2093: pop
    //   2094: iload_2
    //   2095: ifeq -> 2212
    //   2098: goto -> 2105
    //   2101: invokestatic a : (Ljava/lang/Throwable;)Ljava/lang/Throwable;
    //   2104: athrow
    //   2105: aload_3
    //   2106: getstatic burp/Ztes.Zo : Ljava/lang/String;
    //   2109: getstatic burp/Zkv2.ZC : Ljava/lang/Object;
    //   2112: checkcast java/math/BigInteger
    //   2115: invokevirtual intValue : ()I
    //   2118: bipush #32
    //   2120: irem
    //   2121: invokestatic abs : (I)I
    //   2124: invokevirtual charAt : (I)C
    //   2127: invokevirtual append : (C)Ljava/lang/StringBuilder;
    //   2130: pop
    //   2131: iload_2
    //   2132: ifeq -> 2212
    //   2135: goto -> 2142
    //   2138: invokestatic a : (Ljava/lang/Throwable;)Ljava/lang/Throwable;
    //   2141: athrow
    //   2142: aload_3
    //   2143: getstatic burp/Zl_9.ZP : Ljava/lang/String;
    //   2146: getstatic burp/Zmt6.ZK : Ljava/lang/Object;
    //   2149: checkcast java/math/BigInteger
    //   2152: invokevirtual intValue : ()I
    //   2155: bipush #32
    //   2157: irem
    //   2158: invokestatic abs : (I)I
    //   2161: invokevirtual charAt : (I)C
    //   2164: invokevirtual append : (C)Ljava/lang/StringBuilder;
    //   2167: pop
    //   2168: iload_2
    //   2169: ifeq -> 2212
    //   2172: goto -> 2179
    //   2175: invokestatic a : (Ljava/lang/Throwable;)Ljava/lang/Throwable;
    //   2178: athrow
    //   2179: aload_3
    //   2180: getstatic burp/Zs33.ZX : Ljava/lang/String;
    //   2183: getstatic burp/Zgdt.Zb : Ljava/lang/Object;
    //   2186: checkcast java/math/BigInteger
    //   2189: invokevirtual intValue : ()I
    //   2192: bipush #32
    //   2194: irem
    //   2195: invokestatic abs : (I)I
    //   2198: invokevirtual charAt : (I)C
    //   2201: invokevirtual append : (C)Ljava/lang/StringBuilder;
    //   2204: pop
    //   2205: goto -> 2212
    //   2208: invokestatic a : (Ljava/lang/Throwable;)Ljava/lang/Throwable;
    //   2211: athrow
    //   2212: iinc #4, 1
    //   2215: iload_2
    //   2216: ifeq -> 882
    //   2219: aload_3
    //   2220: invokevirtual toString : ()Ljava/lang/String;
    //   2223: putstatic burp/Zr_k.Zu : Ljava/lang/String;
    //   2226: sipush #19865
    //   2229: getstatic burp/Zmhx.ZQ : Ljava/lang/Object;
    //   2232: checkcast java/math/BigInteger
    //   2235: getstatic burp/Zs36.Zs : Ljava/lang/Object;
    //   2238: checkcast java/math/BigInteger
    //   2241: invokevirtual subtract : (Ljava/math/BigInteger;)Ljava/math/BigInteger;
    //   2244: putstatic burp/Zkku.Zz : Ljava/lang/Object;
    //   2247: sipush #22096
    //   2250: invokestatic a : (II)Ljava/lang/String;
    //   2253: iconst_1
    //   2254: ldc burp/Ztdg
    //   2256: invokevirtual getClassLoader : ()Ljava/lang/ClassLoader;
    //   2259: invokestatic forName : (Ljava/lang/String;ZLjava/lang/ClassLoader;)Ljava/lang/Class;
    //   2262: invokevirtual getDeclaredFields : ()[Ljava/lang/reflect/Field;
    //   2265: astore #4
    //   2267: aload #4
    //   2269: arraylength
    //   2270: istore #5
    //   2272: iconst_0
    //   2273: istore #6
    //   2275: iload #6
    //   2277: iload #5
    //   2279: if_icmpge -> 2417
    //   2282: aload #4
    //   2284: iload #6
    //   2286: aaload
    //   2287: astore #7
    //   2289: aload #7
    //   2291: invokevirtual getModifiers : ()I
    //   2294: invokestatic isStatic : (I)Z
    //   2297: ifne -> 2307
    //   2300: goto -> 2410
    //   2303: invokestatic a : (Ljava/lang/Throwable;)Ljava/lang/Throwable;
    //   2306: athrow
    //   2307: aload #7
    //   2309: invokevirtual getType : ()Ljava/lang/Class;
    //   2312: astore #8
    //   2314: aload #8
    //   2316: ifnull -> 2397
    //   2319: aload #8
    //   2321: invokevirtual isPrimitive : ()Z
    //   2324: ifne -> 2397
    //   2327: goto -> 2334
    //   2330: invokestatic a : (Ljava/lang/Throwable;)Ljava/lang/Throwable;
    //   2333: athrow
    //   2334: aload #8
    //   2336: invokevirtual getPackage : ()Ljava/lang/Package;
    //   2339: ifnull -> 2397
    //   2342: goto -> 2349
    //   2345: invokestatic a : (Ljava/lang/Throwable;)Ljava/lang/Throwable;
    //   2348: athrow
    //   2349: aload #8
    //   2351: invokevirtual getPackage : ()Ljava/lang/Package;
    //   2354: invokevirtual getName : ()Ljava/lang/String;
    //   2357: ifnull -> 2397
    //   2360: goto -> 2367
    //   2363: invokestatic a : (Ljava/lang/Throwable;)Ljava/lang/Throwable;
    //   2366: athrow
    //   2367: aload #8
    //   2369: invokevirtual getPackage : ()Ljava/lang/Package;
    //   2372: invokevirtual getName : ()Ljava/lang/String;
    //   2375: sipush #19860
    //   2378: sipush #28711
    //   2381: invokestatic a : (II)Ljava/lang/String;
    //   2384: invokevirtual startsWith : (Ljava/lang/String;)Z
    //   2387: ifne -> 2397
    //   2390: goto -> 2397
    //   2393: invokestatic a : (Ljava/lang/Throwable;)Ljava/lang/Throwable;
    //   2396: athrow
    //   2397: aload #7
    //   2399: iconst_1
    //   2400: invokevirtual setAccessible : (Z)V
    //   2403: aload #7
    //   2405: aconst_null
    //   2406: invokevirtual get : (Ljava/lang/Object;)Ljava/lang/Object;
    //   2409: pop
    //   2410: iinc #6, 1
    //   2413: iload_2
    //   2414: ifeq -> 2275
    //   2417: sipush #19855
    //   2420: sipush #7778
    //   2423: invokestatic a : (II)Ljava/lang/String;
    //   2426: invokestatic forName : (Ljava/lang/String;)Ljava/lang/Class;
    //   2429: invokevirtual getDeclaredMethods : ()[Ljava/lang/reflect/Method;
    //   2432: astore #4
    //   2434: aload #4
    //   2436: arraylength
    //   2437: istore #5
    //   2439: iconst_0
    //   2440: istore #6
    //   2442: iload #6
    //   2444: iload #5
    //   2446: if_icmpge -> 2579
    //   2449: aload #4
    //   2451: iload #6
    //   2453: aaload
    //   2454: astore #7
    //   2456: aload #7
    //   2458: invokevirtual getParameterTypes : ()[Ljava/lang/Class;
    //   2461: pop
    //   2462: aload #7
    //   2464: invokevirtual getModifiers : ()I
    //   2467: invokestatic isStatic : (I)Z
    //   2470: ifeq -> 2565
    //   2473: aload #7
    //   2475: invokevirtual getParameterTypes : ()[Ljava/lang/Class;
    //   2478: arraylength
    //   2479: iconst_2
    //   2480: if_icmpne -> 2565
    //   2483: goto -> 2490
    //   2486: invokestatic a : (Ljava/lang/Throwable;)Ljava/lang/Throwable;
    //   2489: athrow
    //   2490: aload #7
    //   2492: invokevirtual getReturnType : ()Ljava/lang/Class;
    //   2495: getstatic java/lang/Void.TYPE : Ljava/lang/Class;
    //   2498: invokevirtual equals : (Ljava/lang/Object;)Z
    //   2501: ifeq -> 2565
    //   2504: goto -> 2511
    //   2507: invokestatic a : (Ljava/lang/Throwable;)Ljava/lang/Throwable;
    //   2510: athrow
    //   2511: aload #7
    //   2513: iconst_1
    //   2514: invokevirtual setAccessible : (Z)V
    //   2517: aload #7
    //   2519: aconst_null
    //   2520: iconst_2
    //   2521: anewarray java/lang/Object
    //   2524: dup
    //   2525: iconst_0
    //   2526: aload_0
    //   2527: aastore
    //   2528: dup
    //   2529: iconst_1
    //   2530: aload_1
    //   2531: ifnonnull -> 2549
    //   2534: goto -> 2541
    //   2537: invokestatic a : (Ljava/lang/Throwable;)Ljava/lang/Throwable;
    //   2540: athrow
    //   2541: aload_1
    //   2542: goto -> 2556
    //   2545: invokestatic a : (Ljava/lang/Throwable;)Ljava/lang/Throwable;
    //   2548: athrow
    //   2549: aload_1
    //   2550: checkcast [B
    //   2553: invokevirtual clone : ()Ljava/lang/Object;
    //   2556: aastore
    //   2557: invokevirtual invoke : (Ljava/lang/Object;[Ljava/lang/Object;)Ljava/lang/Object;
    //   2560: pop
    //   2561: iload_2
    //   2562: ifeq -> 2579
    //   2565: iinc #6, 1
    //   2568: iload_2
    //   2569: ifeq -> 2442
    //   2572: goto -> 2579
    //   2575: invokestatic a : (Ljava/lang/Throwable;)Ljava/lang/Throwable;
    //   2578: athrow
    //   2579: ldc2_w 8682522807148012
    //   2582: invokestatic currentTimeMillis : ()J
    //   2585: lxor
    //   2586: lstore #5
    //   2588: lload #5
    //   2590: ldc2_w 25214903917
    //   2593: lmul
    //   2594: ldc2_w 11
    //   2597: ladd
    //   2598: ldc2_w 281474976710655
    //   2601: land
    //   2602: lstore #5
    //   2604: lload #5
    //   2606: bipush #32
    //   2608: lshl
    //   2609: lstore #7
    //   2611: lload #5
    //   2613: ldc2_w 25214903917
    //   2616: lmul
    //   2617: ldc2_w 11
    //   2620: ladd
    //   2621: ldc2_w 281474976710655
    //   2624: land
    //   2625: lstore #5
    //   2627: lload #7
    //   2629: lload #5
    //   2631: ladd
    //   2632: lstore #7
    //   2634: bipush #16
    //   2636: newarray byte
    //   2638: dup
    //   2639: iconst_0
    //   2640: bipush #48
    //   2642: bastore
    //   2643: dup
    //   2644: iconst_1
    //   2645: bipush #49
    //   2647: bastore
    //   2648: dup
    //   2649: iconst_2
    //   2650: bipush #50
    //   2652: bastore
    //   2653: dup
    //   2654: iconst_3
    //   2655: bipush #51
    //   2657: bastore
    //   2658: dup
    //   2659: iconst_4
    //   2660: bipush #52
    //   2662: bastore
    //   2663: dup
    //   2664: iconst_5
    //   2665: bipush #53
    //   2667: bastore
    //   2668: dup
    //   2669: bipush #6
    //   2671: bipush #54
    //   2673: bastore
    //   2674: dup
    //   2675: bipush #7
    //   2677: bipush #55
    //   2679: bastore
    //   2680: dup
    //   2681: bipush #8
    //   2683: bipush #56
    //   2685: bastore
    //   2686: dup
    //   2687: bipush #9
    //   2689: bipush #57
    //   2691: bastore
    //   2692: dup
    //   2693: bipush #10
    //   2695: bipush #97
    //   2697: bastore
    //   2698: dup
    //   2699: bipush #11
    //   2701: bipush #98
    //   2703: bastore
    //   2704: dup
    //   2705: bipush #12
    //   2707: bipush #99
    //   2709: bastore
    //   2710: dup
    //   2711: bipush #13
    //   2713: bipush #100
    //   2715: bastore
    //   2716: dup
    //   2717: bipush #14
    //   2719: bipush #101
    //   2721: bastore
    //   2722: dup
    //   2723: bipush #15
    //   2725: bipush #102
    //   2727: bastore
    //   2728: astore #9
    //   2730: bipush #64
    //   2732: newarray byte
    //   2734: astore #10
    //   2736: bipush #64
    //   2738: istore #11
    //   2740: bipush #16
    //   2742: istore #12
    //   2744: iload #12
    //   2746: iconst_1
    //   2747: isub
    //   2748: i2l
    //   2749: lstore #13
    //   2751: aload #10
    //   2753: iinc #11, -1
    //   2756: iload #11
    //   2758: aload #9
    //   2760: lload #7
    //   2762: lload #13
    //   2764: land
    //   2765: l2i
    //   2766: baload
    //   2767: bastore
    //   2768: lload #7
    //   2770: iconst_4
    //   2771: lushr
    //   2772: lstore #7
    //   2774: lload #7
    //   2776: lconst_0
    //   2777: lcmp
    //   2778: ifne -> 2751
    //   2781: bipush #64
    //   2783: iload #11
    //   2785: isub
    //   2786: newarray byte
    //   2788: astore #4
    //   2790: iconst_0
    //   2791: istore #15
    //   2793: iload #15
    //   2795: aload #4
    //   2797: arraylength
    //   2798: if_icmpge -> 2821
    //   2801: aload #4
    //   2803: iload #15
    //   2805: aload #10
    //   2807: iload #11
    //   2809: iload #15
    //   2811: iadd
    //   2812: baload
    //   2813: bastore
    //   2814: iinc #15, 1
    //   2817: iload_2
    //   2818: ifeq -> 2793
    //   2821: aload #4
    //   2823: arraylength
    //   2824: bipush #10
    //   2826: if_icmplt -> 2588
    //   2829: iconst_0
    //   2830: istore #4
    //   2832: getstatic burp/Zl_1.ZH : Ljava/lang/String;
    //   2835: getstatic burp/Zs59.Zw : Ljava/lang/Object;
    //   2838: checkcast java/math/BigInteger
    //   2841: invokevirtual intValue : ()I
    //   2844: bipush #32
    //   2846: irem
    //   2847: invokestatic abs : (I)I
    //   2850: invokevirtual charAt : (I)C
    //   2853: getstatic burp/Zxoa.Z_ : Ljava/lang/String;
    //   2856: getstatic burp/Zlno.ZU : Ljava/lang/Object;
    //   2859: checkcast java/math/BigInteger
    //   2862: invokevirtual intValue : ()I
    //   2865: bipush #32
    //   2867: irem
    //   2868: invokestatic abs : (I)I
    //   2871: invokevirtual charAt : (I)C
    //   2874: if_icmpgt -> 3219
    //   2877: sipush #19850
    //   2880: sipush #4329
    //   2883: invokestatic a : (II)Ljava/lang/String;
    //   2886: iconst_1
    //   2887: ldc burp/Zxzp
    //   2889: invokevirtual getClassLoader : ()Ljava/lang/ClassLoader;
    //   2892: invokestatic forName : (Ljava/lang/String;ZLjava/lang/ClassLoader;)Ljava/lang/Class;
    //   2895: invokevirtual getDeclaredFields : ()[Ljava/lang/reflect/Field;
    //   2898: astore #5
    //   2900: aload #5
    //   2902: arraylength
    //   2903: istore #6
    //   2905: iconst_0
    //   2906: istore #7
    //   2908: iload #7
    //   2910: iload #6
    //   2912: if_icmpge -> 3050
    //   2915: aload #5
    //   2917: iload #7
    //   2919: aaload
    //   2920: astore #8
    //   2922: aload #8
    //   2924: invokevirtual getModifiers : ()I
    //   2927: invokestatic isStatic : (I)Z
    //   2930: ifne -> 2940
    //   2933: goto -> 3043
    //   2936: invokestatic a : (Ljava/lang/Throwable;)Ljava/lang/Throwable;
    //   2939: athrow
    //   2940: aload #8
    //   2942: invokevirtual getType : ()Ljava/lang/Class;
    //   2945: astore #9
    //   2947: aload #9
    //   2949: ifnull -> 3030
    //   2952: aload #9
    //   2954: invokevirtual isPrimitive : ()Z
    //   2957: ifne -> 3030
    //   2960: goto -> 2967
    //   2963: invokestatic a : (Ljava/lang/Throwable;)Ljava/lang/Throwable;
    //   2966: athrow
    //   2967: aload #9
    //   2969: invokevirtual getPackage : ()Ljava/lang/Package;
    //   2972: ifnull -> 3030
    //   2975: goto -> 2982
    //   2978: invokestatic a : (Ljava/lang/Throwable;)Ljava/lang/Throwable;
    //   2981: athrow
    //   2982: aload #9
    //   2984: invokevirtual getPackage : ()Ljava/lang/Package;
    //   2987: invokevirtual getName : ()Ljava/lang/String;
    //   2990: ifnull -> 3030
    //   2993: goto -> 3000
    //   2996: invokestatic a : (Ljava/lang/Throwable;)Ljava/lang/Throwable;
    //   2999: athrow
    //   3000: aload #9
    //   3002: invokevirtual getPackage : ()Ljava/lang/Package;
    //   3005: invokevirtual getName : ()Ljava/lang/String;
    //   3008: sipush #19852
    //   3011: sipush #5694
    //   3014: invokestatic a : (II)Ljava/lang/String;
    //   3017: invokevirtual startsWith : (Ljava/lang/String;)Z
    //   3020: ifne -> 3030
    //   3023: goto -> 3030
    //   3026: invokestatic a : (Ljava/lang/Throwable;)Ljava/lang/Throwable;
    //   3029: athrow
    //   3030: aload #8
    //   3032: iconst_1
    //   3033: invokevirtual setAccessible : (Z)V
    //   3036: aload #8
    //   3038: aconst_null
    //   3039: invokevirtual get : (Ljava/lang/Object;)Ljava/lang/Object;
    //   3042: pop
    //   3043: iinc #7, 1
    //   3046: iload_2
    //   3047: ifeq -> 2908
    //   3050: sipush #19851
    //   3053: sipush #-918
    //   3056: invokestatic a : (II)Ljava/lang/String;
    //   3059: invokestatic forName : (Ljava/lang/String;)Ljava/lang/Class;
    //   3062: invokevirtual getDeclaredMethods : ()[Ljava/lang/reflect/Method;
    //   3065: astore #5
    //   3067: aload #5
    //   3069: arraylength
    //   3070: istore #6
    //   3072: iconst_0
    //   3073: istore #7
    //   3075: iload #7
    //   3077: iload #6
    //   3079: if_icmpge -> 3216
    //   3082: aload #5
    //   3084: iload #7
    //   3086: aaload
    //   3087: astore #8
    //   3089: aload #8
    //   3091: invokevirtual getParameterTypes : ()[Ljava/lang/Class;
    //   3094: pop
    //   3095: aload #8
    //   3097: invokevirtual getModifiers : ()I
    //   3100: invokestatic isStatic : (I)Z
    //   3103: ifeq -> 3202
    //   3106: aload #8
    //   3108: invokevirtual getParameterTypes : ()[Ljava/lang/Class;
    //   3111: arraylength
    //   3112: iconst_2
    //   3113: if_icmpne -> 3202
    //   3116: goto -> 3123
    //   3119: invokestatic a : (Ljava/lang/Throwable;)Ljava/lang/Throwable;
    //   3122: athrow
    //   3123: aload #8
    //   3125: invokevirtual getReturnType : ()Ljava/lang/Class;
    //   3128: getstatic java/lang/Boolean.TYPE : Ljava/lang/Class;
    //   3131: if_acmpne -> 3202
    //   3134: goto -> 3141
    //   3137: invokestatic a : (Ljava/lang/Throwable;)Ljava/lang/Throwable;
    //   3140: athrow
    //   3141: aload #8
    //   3143: iconst_1
    //   3144: invokevirtual setAccessible : (Z)V
    //   3147: aload #8
    //   3149: aconst_null
    //   3150: iconst_2
    //   3151: anewarray java/lang/Object
    //   3154: dup
    //   3155: iconst_0
    //   3156: aload_0
    //   3157: aastore
    //   3158: dup
    //   3159: iconst_1
    //   3160: aload_1
    //   3161: ifnonnull -> 3179
    //   3164: goto -> 3171
    //   3167: invokestatic a : (Ljava/lang/Throwable;)Ljava/lang/Throwable;
    //   3170: athrow
    //   3171: aload_1
    //   3172: goto -> 3186
    //   3175: invokestatic a : (Ljava/lang/Throwable;)Ljava/lang/Throwable;
    //   3178: athrow
    //   3179: aload_1
    //   3180: checkcast [B
    //   3183: invokevirtual clone : ()Ljava/lang/Object;
    //   3186: aastore
    //   3187: invokevirtual invoke : (Ljava/lang/Object;[Ljava/lang/Object;)Ljava/lang/Object;
    //   3190: checkcast java/lang/Boolean
    //   3193: invokevirtual booleanValue : ()Z
    //   3196: istore #4
    //   3198: iload_2
    //   3199: ifeq -> 3216
    //   3202: iinc #7, 1
    //   3205: iload_2
    //   3206: ifeq -> 3075
    //   3209: goto -> 3216
    //   3212: invokestatic a : (Ljava/lang/Throwable;)Ljava/lang/Throwable;
    //   3215: athrow
    //   3216: goto -> 3558
    //   3219: sipush #19870
    //   3222: sipush #30921
    //   3225: invokestatic a : (II)Ljava/lang/String;
    //   3228: iconst_1
    //   3229: ldc burp/Zl_9
    //   3231: invokevirtual getClassLoader : ()Ljava/lang/ClassLoader;
    //   3234: invokestatic forName : (Ljava/lang/String;ZLjava/lang/ClassLoader;)Ljava/lang/Class;
    //   3237: invokevirtual getDeclaredFields : ()[Ljava/lang/reflect/Field;
    //   3240: astore #5
    //   3242: aload #5
    //   3244: arraylength
    //   3245: istore #6
    //   3247: iconst_0
    //   3248: istore #7
    //   3250: iload #7
    //   3252: iload #6
    //   3254: if_icmpge -> 3392
    //   3257: aload #5
    //   3259: iload #7
    //   3261: aaload
    //   3262: astore #8
    //   3264: aload #8
    //   3266: invokevirtual getModifiers : ()I
    //   3269: invokestatic isStatic : (I)Z
    //   3272: ifne -> 3282
    //   3275: goto -> 3385
    //   3278: invokestatic a : (Ljava/lang/Throwable;)Ljava/lang/Throwable;
    //   3281: athrow
    //   3282: aload #8
    //   3284: invokevirtual getType : ()Ljava/lang/Class;
    //   3287: astore #9
    //   3289: aload #9
    //   3291: ifnull -> 3372
    //   3294: aload #9
    //   3296: invokevirtual isPrimitive : ()Z
    //   3299: ifne -> 3372
    //   3302: goto -> 3309
    //   3305: invokestatic a : (Ljava/lang/Throwable;)Ljava/lang/Throwable;
    //   3308: athrow
    //   3309: aload #9
    //   3311: invokevirtual getPackage : ()Ljava/lang/Package;
    //   3314: ifnull -> 3372
    //   3317: goto -> 3324
    //   3320: invokestatic a : (Ljava/lang/Throwable;)Ljava/lang/Throwable;
    //   3323: athrow
    //   3324: aload #9
    //   3326: invokevirtual getPackage : ()Ljava/lang/Package;
    //   3329: invokevirtual getName : ()Ljava/lang/String;
    //   3332: ifnull -> 3372
    //   3335: goto -> 3342
    //   3338: invokestatic a : (Ljava/lang/Throwable;)Ljava/lang/Throwable;
    //   3341: athrow
    //   3342: aload #9
    //   3344: invokevirtual getPackage : ()Ljava/lang/Package;
    //   3347: invokevirtual getName : ()Ljava/lang/String;
    //   3350: sipush #19852
    //   3353: sipush #5694
    //   3356: invokestatic a : (II)Ljava/lang/String;
    //   3359: invokevirtual startsWith : (Ljava/lang/String;)Z
    //   3362: ifne -> 3372
    //   3365: goto -> 3372
    //   3368: invokestatic a : (Ljava/lang/Throwable;)Ljava/lang/Throwable;
    //   3371: athrow
    //   3372: aload #8
    //   3374: iconst_1
    //   3375: invokevirtual setAccessible : (Z)V
    //   3378: aload #8
    //   3380: aconst_null
    //   3381: invokevirtual get : (Ljava/lang/Object;)Ljava/lang/Object;
    //   3384: pop
    //   3385: iinc #7, 1
    //   3388: iload_2
    //   3389: ifeq -> 3250
    //   3392: sipush #19856
    //   3395: sipush #-15290
    //   3398: invokestatic a : (II)Ljava/lang/String;
    //   3401: invokestatic forName : (Ljava/lang/String;)Ljava/lang/Class;
    //   3404: invokevirtual getDeclaredMethods : ()[Ljava/lang/reflect/Method;
    //   3407: astore #5
    //   3409: aload #5
    //   3411: arraylength
    //   3412: istore #6
    //   3414: iconst_0
    //   3415: istore #7
    //   3417: iload #7
    //   3419: iload #6
    //   3421: if_icmpge -> 3558
    //   3424: aload #5
    //   3426: iload #7
    //   3428: aaload
    //   3429: astore #8
    //   3431: aload #8
    //   3433: invokevirtual getParameterTypes : ()[Ljava/lang/Class;
    //   3436: pop
    //   3437: aload #8
    //   3439: invokevirtual getModifiers : ()I
    //   3442: invokestatic isStatic : (I)Z
    //   3445: ifeq -> 3544
    //   3448: aload #8
    //   3450: invokevirtual getParameterTypes : ()[Ljava/lang/Class;
    //   3453: arraylength
    //   3454: iconst_2
    //   3455: if_icmpne -> 3544
    //   3458: goto -> 3465
    //   3461: invokestatic a : (Ljava/lang/Throwable;)Ljava/lang/Throwable;
    //   3464: athrow
    //   3465: aload #8
    //   3467: invokevirtual getReturnType : ()Ljava/lang/Class;
    //   3470: getstatic java/lang/Boolean.TYPE : Ljava/lang/Class;
    //   3473: if_acmpne -> 3544
    //   3476: goto -> 3483
    //   3479: invokestatic a : (Ljava/lang/Throwable;)Ljava/lang/Throwable;
    //   3482: athrow
    //   3483: aload #8
    //   3485: iconst_1
    //   3486: invokevirtual setAccessible : (Z)V
    //   3489: aload #8
    //   3491: aconst_null
    //   3492: iconst_2
    //   3493: anewarray java/lang/Object
    //   3496: dup
    //   3497: iconst_0
    //   3498: aload_0
    //   3499: aastore
    //   3500: dup
    //   3501: iconst_1
    //   3502: aload_1
    //   3503: ifnonnull -> 3521
    //   3506: goto -> 3513
    //   3509: invokestatic a : (Ljava/lang/Throwable;)Ljava/lang/Throwable;
    //   3512: athrow
    //   3513: aload_1
    //   3514: goto -> 3528
    //   3517: invokestatic a : (Ljava/lang/Throwable;)Ljava/lang/Throwable;
    //   3520: athrow
    //   3521: aload_1
    //   3522: checkcast [B
    //   3525: invokevirtual clone : ()Ljava/lang/Object;
    //   3528: aastore
    //   3529: invokevirtual invoke : (Ljava/lang/Object;[Ljava/lang/Object;)Ljava/lang/Object;
    //   3532: checkcast java/lang/Boolean
    //   3535: invokevirtual booleanValue : ()Z
    //   3538: istore #4
    //   3540: iload_2
    //   3541: ifeq -> 3558
    //   3544: iinc #7, 1
    //   3547: iload_2
    //   3548: ifeq -> 3417
    //   3551: goto -> 3558
    //   3554: invokestatic a : (Ljava/lang/Throwable;)Ljava/lang/Throwable;
    //   3557: athrow
    //   3558: iload #4
    //   3560: ifeq -> 3566
    //   3563: iload #4
    //   3565: ireturn
    //   3566: getstatic burp/Zmiy.ZT : Ljava/lang/String;
    //   3569: getstatic burp/Ztte.ZR : Ljava/lang/Object;
    //   3572: checkcast java/math/BigInteger
    //   3575: invokevirtual intValue : ()I
    //   3578: bipush #32
    //   3580: irem
    //   3581: invokestatic abs : (I)I
    //   3584: invokevirtual charAt : (I)C
    //   3587: getstatic burp/Zgd7.Zs : Ljava/lang/String;
    //   3590: getstatic burp/Zl1u.Zq : Ljava/lang/Object;
    //   3593: checkcast java/math/BigInteger
    //   3596: invokevirtual intValue : ()I
    //   3599: bipush #32
    //   3601: irem
    //   3602: invokestatic abs : (I)I
    //   3605: invokevirtual charAt : (I)C
    //   3608: if_icmpgt -> 3954
    //   3611: sipush #19853
    //   3614: sipush #-20338
    //   3617: invokestatic a : (II)Ljava/lang/String;
    //   3620: iconst_1
    //   3621: ldc burp/Zkdq
    //   3623: invokevirtual getClassLoader : ()Ljava/lang/ClassLoader;
    //   3626: invokestatic forName : (Ljava/lang/String;ZLjava/lang/ClassLoader;)Ljava/lang/Class;
    //   3629: invokevirtual getDeclaredFields : ()[Ljava/lang/reflect/Field;
    //   3632: astore #5
    //   3634: aload #5
    //   3636: arraylength
    //   3637: istore #6
    //   3639: iconst_0
    //   3640: istore #7
    //   3642: iload #7
    //   3644: iload #6
    //   3646: if_icmpge -> 3784
    //   3649: aload #5
    //   3651: iload #7
    //   3653: aaload
    //   3654: astore #8
    //   3656: aload #8
    //   3658: invokevirtual getModifiers : ()I
    //   3661: invokestatic isStatic : (I)Z
    //   3664: ifne -> 3674
    //   3667: goto -> 3777
    //   3670: invokestatic a : (Ljava/lang/Throwable;)Ljava/lang/Throwable;
    //   3673: athrow
    //   3674: aload #8
    //   3676: invokevirtual getType : ()Ljava/lang/Class;
    //   3679: astore #9
    //   3681: aload #9
    //   3683: ifnull -> 3764
    //   3686: aload #9
    //   3688: invokevirtual isPrimitive : ()Z
    //   3691: ifne -> 3764
    //   3694: goto -> 3701
    //   3697: invokestatic a : (Ljava/lang/Throwable;)Ljava/lang/Throwable;
    //   3700: athrow
    //   3701: aload #9
    //   3703: invokevirtual getPackage : ()Ljava/lang/Package;
    //   3706: ifnull -> 3764
    //   3709: goto -> 3716
    //   3712: invokestatic a : (Ljava/lang/Throwable;)Ljava/lang/Throwable;
    //   3715: athrow
    //   3716: aload #9
    //   3718: invokevirtual getPackage : ()Ljava/lang/Package;
    //   3721: invokevirtual getName : ()Ljava/lang/String;
    //   3724: ifnull -> 3764
    //   3727: goto -> 3734
    //   3730: invokestatic a : (Ljava/lang/Throwable;)Ljava/lang/Throwable;
    //   3733: athrow
    //   3734: aload #9
    //   3736: invokevirtual getPackage : ()Ljava/lang/Package;
    //   3739: invokevirtual getName : ()Ljava/lang/String;
    //   3742: sipush #19852
    //   3745: sipush #5694
    //   3748: invokestatic a : (II)Ljava/lang/String;
    //   3751: invokevirtual startsWith : (Ljava/lang/String;)Z
    //   3754: ifne -> 3764
    //   3757: goto -> 3764
    //   3760: invokestatic a : (Ljava/lang/Throwable;)Ljava/lang/Throwable;
    //   3763: athrow
    //   3764: aload #8
    //   3766: iconst_1
    //   3767: invokevirtual setAccessible : (Z)V
    //   3770: aload #8
    //   3772: aconst_null
    //   3773: invokevirtual get : (Ljava/lang/Object;)Ljava/lang/Object;
    //   3776: pop
    //   3777: iinc #7, 1
    //   3780: iload_2
    //   3781: ifeq -> 3642
    //   3784: sipush #19857
    //   3787: sipush #-28537
    //   3790: invokestatic a : (II)Ljava/lang/String;
    //   3793: invokestatic forName : (Ljava/lang/String;)Ljava/lang/Class;
    //   3796: invokevirtual getDeclaredMethods : ()[Ljava/lang/reflect/Method;
    //   3799: astore #5
    //   3801: aload #5
    //   3803: arraylength
    //   3804: istore #6
    //   3806: iconst_0
    //   3807: istore #7
    //   3809: iload #7
    //   3811: iload #6
    //   3813: if_icmpge -> 3950
    //   3816: aload #5
    //   3818: iload #7
    //   3820: aaload
    //   3821: astore #8
    //   3823: aload #8
    //   3825: invokevirtual getParameterTypes : ()[Ljava/lang/Class;
    //   3828: pop
    //   3829: aload #8
    //   3831: invokevirtual getModifiers : ()I
    //   3834: invokestatic isStatic : (I)Z
    //   3837: ifeq -> 3936
    //   3840: aload #8
    //   3842: invokevirtual getParameterTypes : ()[Ljava/lang/Class;
    //   3845: arraylength
    //   3846: iconst_2
    //   3847: if_icmpne -> 3936
    //   3850: goto -> 3857
    //   3853: invokestatic a : (Ljava/lang/Throwable;)Ljava/lang/Throwable;
    //   3856: athrow
    //   3857: aload #8
    //   3859: invokevirtual getReturnType : ()Ljava/lang/Class;
    //   3862: getstatic java/lang/Boolean.TYPE : Ljava/lang/Class;
    //   3865: if_acmpne -> 3936
    //   3868: goto -> 3875
    //   3871: invokestatic a : (Ljava/lang/Throwable;)Ljava/lang/Throwable;
    //   3874: athrow
    //   3875: aload #8
    //   3877: iconst_1
    //   3878: invokevirtual setAccessible : (Z)V
    //   3881: aload #8
    //   3883: aconst_null
    //   3884: iconst_2
    //   3885: anewarray java/lang/Object
    //   3888: dup
    //   3889: iconst_0
    //   3890: aload_0
    //   3891: aastore
    //   3892: dup
    //   3893: iconst_1
    //   3894: aload_1
    //   3895: ifnonnull -> 3913
    //   3898: goto -> 3905
    //   3901: invokestatic a : (Ljava/lang/Throwable;)Ljava/lang/Throwable;
    //   3904: athrow
    //   3905: aload_1
    //   3906: goto -> 3920
    //   3909: invokestatic a : (Ljava/lang/Throwable;)Ljava/lang/Throwable;
    //   3912: athrow
    //   3913: aload_1
    //   3914: checkcast [B
    //   3917: invokevirtual clone : ()Ljava/lang/Object;
    //   3920: aastore
    //   3921: invokevirtual invoke : (Ljava/lang/Object;[Ljava/lang/Object;)Ljava/lang/Object;
    //   3924: checkcast java/lang/Boolean
    //   3927: invokevirtual booleanValue : ()Z
    //   3930: istore #4
    //   3932: iload_2
    //   3933: ifeq -> 3950
    //   3936: iinc #7, 1
    //   3939: iload_2
    //   3940: ifeq -> 3809
    //   3943: goto -> 3950
    //   3946: invokestatic a : (Ljava/lang/Throwable;)Ljava/lang/Throwable;
    //   3949: athrow
    //   3950: iload_2
    //   3951: ifeq -> 4293
    //   3954: sipush #19871
    //   3957: sipush #15711
    //   3960: invokestatic a : (II)Ljava/lang/String;
    //   3963: iconst_1
    //   3964: ldc burp/Ztip
    //   3966: invokevirtual getClassLoader : ()Ljava/lang/ClassLoader;
    //   3969: invokestatic forName : (Ljava/lang/String;ZLjava/lang/ClassLoader;)Ljava/lang/Class;
    //   3972: invokevirtual getDeclaredFields : ()[Ljava/lang/reflect/Field;
    //   3975: astore #5
    //   3977: aload #5
    //   3979: arraylength
    //   3980: istore #6
    //   3982: iconst_0
    //   3983: istore #7
    //   3985: iload #7
    //   3987: iload #6
    //   3989: if_icmpge -> 4127
    //   3992: aload #5
    //   3994: iload #7
    //   3996: aaload
    //   3997: astore #8
    //   3999: aload #8
    //   4001: invokevirtual getModifiers : ()I
    //   4004: invokestatic isStatic : (I)Z
    //   4007: ifne -> 4017
    //   4010: goto -> 4120
    //   4013: invokestatic a : (Ljava/lang/Throwable;)Ljava/lang/Throwable;
    //   4016: athrow
    //   4017: aload #8
    //   4019: invokevirtual getType : ()Ljava/lang/Class;
    //   4022: astore #9
    //   4024: aload #9
    //   4026: ifnull -> 4107
    //   4029: aload #9
    //   4031: invokevirtual isPrimitive : ()Z
    //   4034: ifne -> 4107
    //   4037: goto -> 4044
    //   4040: invokestatic a : (Ljava/lang/Throwable;)Ljava/lang/Throwable;
    //   4043: athrow
    //   4044: aload #9
    //   4046: invokevirtual getPackage : ()Ljava/lang/Package;
    //   4049: ifnull -> 4107
    //   4052: goto -> 4059
    //   4055: invokestatic a : (Ljava/lang/Throwable;)Ljava/lang/Throwable;
    //   4058: athrow
    //   4059: aload #9
    //   4061: invokevirtual getPackage : ()Ljava/lang/Package;
    //   4064: invokevirtual getName : ()Ljava/lang/String;
    //   4067: ifnull -> 4107
    //   4070: goto -> 4077
    //   4073: invokestatic a : (Ljava/lang/Throwable;)Ljava/lang/Throwable;
    //   4076: athrow
    //   4077: aload #9
    //   4079: invokevirtual getPackage : ()Ljava/lang/Package;
    //   4082: invokevirtual getName : ()Ljava/lang/String;
    //   4085: sipush #19852
    //   4088: sipush #5694
    //   4091: invokestatic a : (II)Ljava/lang/String;
    //   4094: invokevirtual startsWith : (Ljava/lang/String;)Z
    //   4097: ifne -> 4107
    //   4100: goto -> 4107
    //   4103: invokestatic a : (Ljava/lang/Throwable;)Ljava/lang/Throwable;
    //   4106: athrow
    //   4107: aload #8
    //   4109: iconst_1
    //   4110: invokevirtual setAccessible : (Z)V
    //   4113: aload #8
    //   4115: aconst_null
    //   4116: invokevirtual get : (Ljava/lang/Object;)Ljava/lang/Object;
    //   4119: pop
    //   4120: iinc #7, 1
    //   4123: iload_2
    //   4124: ifeq -> 3985
    //   4127: sipush #19854
    //   4130: sipush #27624
    //   4133: invokestatic a : (II)Ljava/lang/String;
    //   4136: invokestatic forName : (Ljava/lang/String;)Ljava/lang/Class;
    //   4139: invokevirtual getDeclaredMethods : ()[Ljava/lang/reflect/Method;
    //   4142: astore #5
    //   4144: aload #5
    //   4146: arraylength
    //   4147: istore #6
    //   4149: iconst_0
    //   4150: istore #7
    //   4152: iload #7
    //   4154: iload #6
    //   4156: if_icmpge -> 4293
    //   4159: aload #5
    //   4161: iload #7
    //   4163: aaload
    //   4164: astore #8
    //   4166: aload #8
    //   4168: invokevirtual getParameterTypes : ()[Ljava/lang/Class;
    //   4171: pop
    //   4172: aload #8
    //   4174: invokevirtual getModifiers : ()I
    //   4177: invokestatic isStatic : (I)Z
    //   4180: ifeq -> 4279
    //   4183: aload #8
    //   4185: invokevirtual getParameterTypes : ()[Ljava/lang/Class;
    //   4188: arraylength
    //   4189: iconst_2
    //   4190: if_icmpne -> 4279
    //   4193: goto -> 4200
    //   4196: invokestatic a : (Ljava/lang/Throwable;)Ljava/lang/Throwable;
    //   4199: athrow
    //   4200: aload #8
    //   4202: invokevirtual getReturnType : ()Ljava/lang/Class;
    //   4205: getstatic java/lang/Boolean.TYPE : Ljava/lang/Class;
    //   4208: if_acmpne -> 4279
    //   4211: goto -> 4218
    //   4214: invokestatic a : (Ljava/lang/Throwable;)Ljava/lang/Throwable;
    //   4217: athrow
    //   4218: aload #8
    //   4220: iconst_1
    //   4221: invokevirtual setAccessible : (Z)V
    //   4224: aload #8
    //   4226: aconst_null
    //   4227: iconst_2
    //   4228: anewarray java/lang/Object
    //   4231: dup
    //   4232: iconst_0
    //   4233: aload_0
    //   4234: aastore
    //   4235: dup
    //   4236: iconst_1
    //   4237: aload_1
    //   4238: ifnonnull -> 4256
    //   4241: goto -> 4248
    //   4244: invokestatic a : (Ljava/lang/Throwable;)Ljava/lang/Throwable;
    //   4247: athrow
    //   4248: aload_1
    //   4249: goto -> 4263
    //   4252: invokestatic a : (Ljava/lang/Throwable;)Ljava/lang/Throwable;
    //   4255: athrow
    //   4256: aload_1
    //   4257: checkcast [B
    //   4260: invokevirtual clone : ()Ljava/lang/Object;
    //   4263: aastore
    //   4264: invokevirtual invoke : (Ljava/lang/Object;[Ljava/lang/Object;)Ljava/lang/Object;
    //   4267: checkcast java/lang/Boolean
    //   4270: invokevirtual booleanValue : ()Z
    //   4273: istore #4
    //   4275: iload_2
    //   4276: ifeq -> 4293
    //   4279: iinc #7, 1
    //   4282: iload_2
    //   4283: ifeq -> 4152
    //   4286: goto -> 4293
    //   4289: invokestatic a : (Ljava/lang/Throwable;)Ljava/lang/Throwable;
    //   4292: athrow
    //   4293: iload #4
    //   4295: ifeq -> 4301
    //   4298: iload #4
    //   4300: ireturn
    //   4301: getstatic burp/Zxtn.Zu : Ljava/lang/String;
    //   4304: getstatic burp/Zs33.ZT : Ljava/lang/Object;
    //   4307: checkcast java/math/BigInteger
    //   4310: invokevirtual intValue : ()I
    //   4313: bipush #32
    //   4315: irem
    //   4316: invokestatic abs : (I)I
    //   4319: invokevirtual charAt : (I)C
    //   4322: getstatic burp/Zmiy.ZT : Ljava/lang/String;
    //   4325: getstatic burp/Zkul.Zb : Ljava/lang/Object;
    //   4328: checkcast java/math/BigInteger
    //   4331: invokevirtual intValue : ()I
    //   4334: bipush #32
    //   4336: irem
    //   4337: invokestatic abs : (I)I
    //   4340: invokevirtual charAt : (I)C
    //   4343: if_icmple -> 4689
    //   4346: sipush #19855
    //   4349: sipush #7778
    //   4352: invokestatic a : (II)Ljava/lang/String;
    //   4355: iconst_1
    //   4356: ldc burp/Zr5k
    //   4358: invokevirtual getClassLoader : ()Ljava/lang/ClassLoader;
    //   4361: invokestatic forName : (Ljava/lang/String;ZLjava/lang/ClassLoader;)Ljava/lang/Class;
    //   4364: invokevirtual getDeclaredFields : ()[Ljava/lang/reflect/Field;
    //   4367: astore #5
    //   4369: aload #5
    //   4371: arraylength
    //   4372: istore #6
    //   4374: iconst_0
    //   4375: istore #7
    //   4377: iload #7
    //   4379: iload #6
    //   4381: if_icmpge -> 4519
    //   4384: aload #5
    //   4386: iload #7
    //   4388: aaload
    //   4389: astore #8
    //   4391: aload #8
    //   4393: invokevirtual getModifiers : ()I
    //   4396: invokestatic isStatic : (I)Z
    //   4399: ifne -> 4409
    //   4402: goto -> 4512
    //   4405: invokestatic a : (Ljava/lang/Throwable;)Ljava/lang/Throwable;
    //   4408: athrow
    //   4409: aload #8
    //   4411: invokevirtual getType : ()Ljava/lang/Class;
    //   4414: astore #9
    //   4416: aload #9
    //   4418: ifnull -> 4499
    //   4421: aload #9
    //   4423: invokevirtual isPrimitive : ()Z
    //   4426: ifne -> 4499
    //   4429: goto -> 4436
    //   4432: invokestatic a : (Ljava/lang/Throwable;)Ljava/lang/Throwable;
    //   4435: athrow
    //   4436: aload #9
    //   4438: invokevirtual getPackage : ()Ljava/lang/Package;
    //   4441: ifnull -> 4499
    //   4444: goto -> 4451
    //   4447: invokestatic a : (Ljava/lang/Throwable;)Ljava/lang/Throwable;
    //   4450: athrow
    //   4451: aload #9
    //   4453: invokevirtual getPackage : ()Ljava/lang/Package;
    //   4456: invokevirtual getName : ()Ljava/lang/String;
    //   4459: ifnull -> 4499
    //   4462: goto -> 4469
    //   4465: invokestatic a : (Ljava/lang/Throwable;)Ljava/lang/Throwable;
    //   4468: athrow
    //   4469: aload #9
    //   4471: invokevirtual getPackage : ()Ljava/lang/Package;
    //   4474: invokevirtual getName : ()Ljava/lang/String;
    //   4477: sipush #19852
    //   4480: sipush #5694
    //   4483: invokestatic a : (II)Ljava/lang/String;
    //   4486: invokevirtual startsWith : (Ljava/lang/String;)Z
    //   4489: ifne -> 4499
    //   4492: goto -> 4499
    //   4495: invokestatic a : (Ljava/lang/Throwable;)Ljava/lang/Throwable;
    //   4498: athrow
    //   4499: aload #8
    //   4501: iconst_1
    //   4502: invokevirtual setAccessible : (Z)V
    //   4505: aload #8
    //   4507: aconst_null
    //   4508: invokevirtual get : (Ljava/lang/Object;)Ljava/lang/Object;
    //   4511: pop
    //   4512: iinc #7, 1
    //   4515: iload_2
    //   4516: ifeq -> 4377
    //   4519: sipush #19855
    //   4522: sipush #7778
    //   4525: invokestatic a : (II)Ljava/lang/String;
    //   4528: invokestatic forName : (Ljava/lang/String;)Ljava/lang/Class;
    //   4531: invokevirtual getDeclaredMethods : ()[Ljava/lang/reflect/Method;
    //   4534: astore #5
    //   4536: aload #5
    //   4538: arraylength
    //   4539: istore #6
    //   4541: iconst_0
    //   4542: istore #7
    //   4544: iload #7
    //   4546: iload #6
    //   4548: if_icmpge -> 4685
    //   4551: aload #5
    //   4553: iload #7
    //   4555: aaload
    //   4556: astore #8
    //   4558: aload #8
    //   4560: invokevirtual getParameterTypes : ()[Ljava/lang/Class;
    //   4563: pop
    //   4564: aload #8
    //   4566: invokevirtual getModifiers : ()I
    //   4569: invokestatic isStatic : (I)Z
    //   4572: ifeq -> 4671
    //   4575: aload #8
    //   4577: invokevirtual getParameterTypes : ()[Ljava/lang/Class;
    //   4580: arraylength
    //   4581: iconst_2
    //   4582: if_icmpne -> 4671
    //   4585: goto -> 4592
    //   4588: invokestatic a : (Ljava/lang/Throwable;)Ljava/lang/Throwable;
    //   4591: athrow
    //   4592: aload #8
    //   4594: invokevirtual getReturnType : ()Ljava/lang/Class;
    //   4597: getstatic java/lang/Boolean.TYPE : Ljava/lang/Class;
    //   4600: if_acmpne -> 4671
    //   4603: goto -> 4610
    //   4606: invokestatic a : (Ljava/lang/Throwable;)Ljava/lang/Throwable;
    //   4609: athrow
    //   4610: aload #8
    //   4612: iconst_1
    //   4613: invokevirtual setAccessible : (Z)V
    //   4616: aload #8
    //   4618: aconst_null
    //   4619: iconst_2
    //   4620: anewarray java/lang/Object
    //   4623: dup
    //   4624: iconst_0
    //   4625: aload_0
    //   4626: aastore
    //   4627: dup
    //   4628: iconst_1
    //   4629: aload_1
    //   4630: ifnonnull -> 4648
    //   4633: goto -> 4640
    //   4636: invokestatic a : (Ljava/lang/Throwable;)Ljava/lang/Throwable;
    //   4639: athrow
    //   4640: aload_1
    //   4641: goto -> 4655
    //   4644: invokestatic a : (Ljava/lang/Throwable;)Ljava/lang/Throwable;
    //   4647: athrow
    //   4648: aload_1
    //   4649: checkcast [B
    //   4652: invokevirtual clone : ()Ljava/lang/Object;
    //   4655: aastore
    //   4656: invokevirtual invoke : (Ljava/lang/Object;[Ljava/lang/Object;)Ljava/lang/Object;
    //   4659: checkcast java/lang/Boolean
    //   4662: invokevirtual booleanValue : ()Z
    //   4665: istore #4
    //   4667: iload_2
    //   4668: ifeq -> 4685
    //   4671: iinc #7, 1
    //   4674: iload_2
    //   4675: ifeq -> 4544
    //   4678: goto -> 4685
    //   4681: invokestatic a : (Ljava/lang/Throwable;)Ljava/lang/Throwable;
    //   4684: athrow
    //   4685: iload_2
    //   4686: ifeq -> 5028
    //   4689: sipush #19866
    //   4692: sipush #-22457
    //   4695: invokestatic a : (II)Ljava/lang/String;
    //   4698: iconst_1
    //   4699: ldc burp/Zlhk
    //   4701: invokevirtual getClassLoader : ()Ljava/lang/ClassLoader;
    //   4704: invokestatic forName : (Ljava/lang/String;ZLjava/lang/ClassLoader;)Ljava/lang/Class;
    //   4707: invokevirtual getDeclaredFields : ()[Ljava/lang/reflect/Field;
    //   4710: astore #5
    //   4712: aload #5
    //   4714: arraylength
    //   4715: istore #6
    //   4717: iconst_0
    //   4718: istore #7
    //   4720: iload #7
    //   4722: iload #6
    //   4724: if_icmpge -> 4862
    //   4727: aload #5
    //   4729: iload #7
    //   4731: aaload
    //   4732: astore #8
    //   4734: aload #8
    //   4736: invokevirtual getModifiers : ()I
    //   4739: invokestatic isStatic : (I)Z
    //   4742: ifne -> 4752
    //   4745: goto -> 4855
    //   4748: invokestatic a : (Ljava/lang/Throwable;)Ljava/lang/Throwable;
    //   4751: athrow
    //   4752: aload #8
    //   4754: invokevirtual getType : ()Ljava/lang/Class;
    //   4757: astore #9
    //   4759: aload #9
    //   4761: ifnull -> 4842
    //   4764: aload #9
    //   4766: invokevirtual isPrimitive : ()Z
    //   4769: ifne -> 4842
    //   4772: goto -> 4779
    //   4775: invokestatic a : (Ljava/lang/Throwable;)Ljava/lang/Throwable;
    //   4778: athrow
    //   4779: aload #9
    //   4781: invokevirtual getPackage : ()Ljava/lang/Package;
    //   4784: ifnull -> 4842
    //   4787: goto -> 4794
    //   4790: invokestatic a : (Ljava/lang/Throwable;)Ljava/lang/Throwable;
    //   4793: athrow
    //   4794: aload #9
    //   4796: invokevirtual getPackage : ()Ljava/lang/Package;
    //   4799: invokevirtual getName : ()Ljava/lang/String;
    //   4802: ifnull -> 4842
    //   4805: goto -> 4812
    //   4808: invokestatic a : (Ljava/lang/Throwable;)Ljava/lang/Throwable;
    //   4811: athrow
    //   4812: aload #9
    //   4814: invokevirtual getPackage : ()Ljava/lang/Package;
    //   4817: invokevirtual getName : ()Ljava/lang/String;
    //   4820: sipush #19852
    //   4823: sipush #5694
    //   4826: invokestatic a : (II)Ljava/lang/String;
    //   4829: invokevirtual startsWith : (Ljava/lang/String;)Z
    //   4832: ifne -> 4842
    //   4835: goto -> 4842
    //   4838: invokestatic a : (Ljava/lang/Throwable;)Ljava/lang/Throwable;
    //   4841: athrow
    //   4842: aload #8
    //   4844: iconst_1
    //   4845: invokevirtual setAccessible : (Z)V
    //   4848: aload #8
    //   4850: aconst_null
    //   4851: invokevirtual get : (Ljava/lang/Object;)Ljava/lang/Object;
    //   4854: pop
    //   4855: iinc #7, 1
    //   4858: iload_2
    //   4859: ifeq -> 4720
    //   4862: sipush #19868
    //   4865: sipush #-30017
    //   4868: invokestatic a : (II)Ljava/lang/String;
    //   4871: invokestatic forName : (Ljava/lang/String;)Ljava/lang/Class;
    //   4874: invokevirtual getDeclaredMethods : ()[Ljava/lang/reflect/Method;
    //   4877: astore #5
    //   4879: aload #5
    //   4881: arraylength
    //   4882: istore #6
    //   4884: iconst_0
    //   4885: istore #7
    //   4887: iload #7
    //   4889: iload #6
    //   4891: if_icmpge -> 5028
    //   4894: aload #5
    //   4896: iload #7
    //   4898: aaload
    //   4899: astore #8
    //   4901: aload #8
    //   4903: invokevirtual getParameterTypes : ()[Ljava/lang/Class;
    //   4906: pop
    //   4907: aload #8
    //   4909: invokevirtual getModifiers : ()I
    //   4912: invokestatic isStatic : (I)Z
    //   4915: ifeq -> 5014
    //   4918: aload #8
    //   4920: invokevirtual getParameterTypes : ()[Ljava/lang/Class;
    //   4923: arraylength
    //   4924: iconst_2
    //   4925: if_icmpne -> 5014
    //   4928: goto -> 4935
    //   4931: invokestatic a : (Ljava/lang/Throwable;)Ljava/lang/Throwable;
    //   4934: athrow
    //   4935: aload #8
    //   4937: invokevirtual getReturnType : ()Ljava/lang/Class;
    //   4940: getstatic java/lang/Boolean.TYPE : Ljava/lang/Class;
    //   4943: if_acmpne -> 5014
    //   4946: goto -> 4953
    //   4949: invokestatic a : (Ljava/lang/Throwable;)Ljava/lang/Throwable;
    //   4952: athrow
    //   4953: aload #8
    //   4955: iconst_1
    //   4956: invokevirtual setAccessible : (Z)V
    //   4959: aload #8
    //   4961: aconst_null
    //   4962: iconst_2
    //   4963: anewarray java/lang/Object
    //   4966: dup
    //   4967: iconst_0
    //   4968: aload_0
    //   4969: aastore
    //   4970: dup
    //   4971: iconst_1
    //   4972: aload_1
    //   4973: ifnonnull -> 4991
    //   4976: goto -> 4983
    //   4979: invokestatic a : (Ljava/lang/Throwable;)Ljava/lang/Throwable;
    //   4982: athrow
    //   4983: aload_1
    //   4984: goto -> 4998
    //   4987: invokestatic a : (Ljava/lang/Throwable;)Ljava/lang/Throwable;
    //   4990: athrow
    //   4991: aload_1
    //   4992: checkcast [B
    //   4995: invokevirtual clone : ()Ljava/lang/Object;
    //   4998: aastore
    //   4999: invokevirtual invoke : (Ljava/lang/Object;[Ljava/lang/Object;)Ljava/lang/Object;
    //   5002: checkcast java/lang/Boolean
    //   5005: invokevirtual booleanValue : ()Z
    //   5008: istore #4
    //   5010: iload_2
    //   5011: ifeq -> 5028
    //   5014: iinc #7, 1
    //   5017: iload_2
    //   5018: ifeq -> 4887
    //   5021: goto -> 5028
    //   5024: invokestatic a : (Ljava/lang/Throwable;)Ljava/lang/Throwable;
    //   5027: athrow
    //   5028: iload #4
    //   5030: ifeq -> 5036
    //   5033: iload #4
    //   5035: ireturn
    //   5036: getstatic burp/Zebj.ZF : Ljava/lang/String;
    //   5039: getstatic burp/Zl_9.ZM : Ljava/lang/Object;
    //   5042: checkcast java/math/BigInteger
    //   5045: invokevirtual intValue : ()I
    //   5048: bipush #32
    //   5050: irem
    //   5051: invokestatic abs : (I)I
    //   5054: invokevirtual charAt : (I)C
    //   5057: getstatic burp/Ztid.Zz : Ljava/lang/String;
    //   5060: getstatic burp/Ztd6.ZI : Ljava/lang/Object;
    //   5063: checkcast java/math/BigInteger
    //   5066: invokevirtual intValue : ()I
    //   5069: bipush #32
    //   5071: irem
    //   5072: invokestatic abs : (I)I
    //   5075: invokevirtual charAt : (I)C
    //   5078: if_icmpgt -> 5424
    //   5081: sipush #19849
    //   5084: sipush #20102
    //   5087: invokestatic a : (II)Ljava/lang/String;
    //   5090: iconst_1
    //   5091: ldc burp/Zs8s
    //   5093: invokevirtual getClassLoader : ()Ljava/lang/ClassLoader;
    //   5096: invokestatic forName : (Ljava/lang/String;ZLjava/lang/ClassLoader;)Ljava/lang/Class;
    //   5099: invokevirtual getDeclaredFields : ()[Ljava/lang/reflect/Field;
    //   5102: astore #5
    //   5104: aload #5
    //   5106: arraylength
    //   5107: istore #6
    //   5109: iconst_0
    //   5110: istore #7
    //   5112: iload #7
    //   5114: iload #6
    //   5116: if_icmpge -> 5254
    //   5119: aload #5
    //   5121: iload #7
    //   5123: aaload
    //   5124: astore #8
    //   5126: aload #8
    //   5128: invokevirtual getModifiers : ()I
    //   5131: invokestatic isStatic : (I)Z
    //   5134: ifne -> 5144
    //   5137: goto -> 5247
    //   5140: invokestatic a : (Ljava/lang/Throwable;)Ljava/lang/Throwable;
    //   5143: athrow
    //   5144: aload #8
    //   5146: invokevirtual getType : ()Ljava/lang/Class;
    //   5149: astore #9
    //   5151: aload #9
    //   5153: ifnull -> 5234
    //   5156: aload #9
    //   5158: invokevirtual isPrimitive : ()Z
    //   5161: ifne -> 5234
    //   5164: goto -> 5171
    //   5167: invokestatic a : (Ljava/lang/Throwable;)Ljava/lang/Throwable;
    //   5170: athrow
    //   5171: aload #9
    //   5173: invokevirtual getPackage : ()Ljava/lang/Package;
    //   5176: ifnull -> 5234
    //   5179: goto -> 5186
    //   5182: invokestatic a : (Ljava/lang/Throwable;)Ljava/lang/Throwable;
    //   5185: athrow
    //   5186: aload #9
    //   5188: invokevirtual getPackage : ()Ljava/lang/Package;
    //   5191: invokevirtual getName : ()Ljava/lang/String;
    //   5194: ifnull -> 5234
    //   5197: goto -> 5204
    //   5200: invokestatic a : (Ljava/lang/Throwable;)Ljava/lang/Throwable;
    //   5203: athrow
    //   5204: aload #9
    //   5206: invokevirtual getPackage : ()Ljava/lang/Package;
    //   5209: invokevirtual getName : ()Ljava/lang/String;
    //   5212: sipush #19852
    //   5215: sipush #5694
    //   5218: invokestatic a : (II)Ljava/lang/String;
    //   5221: invokevirtual startsWith : (Ljava/lang/String;)Z
    //   5224: ifne -> 5234
    //   5227: goto -> 5234
    //   5230: invokestatic a : (Ljava/lang/Throwable;)Ljava/lang/Throwable;
    //   5233: athrow
    //   5234: aload #8
    //   5236: iconst_1
    //   5237: invokevirtual setAccessible : (Z)V
    //   5240: aload #8
    //   5242: aconst_null
    //   5243: invokevirtual get : (Ljava/lang/Object;)Ljava/lang/Object;
    //   5246: pop
    //   5247: iinc #7, 1
    //   5250: iload_2
    //   5251: ifeq -> 5112
    //   5254: sipush #19858
    //   5257: sipush #563
    //   5260: invokestatic a : (II)Ljava/lang/String;
    //   5263: invokestatic forName : (Ljava/lang/String;)Ljava/lang/Class;
    //   5266: invokevirtual getDeclaredMethods : ()[Ljava/lang/reflect/Method;
    //   5269: astore #5
    //   5271: aload #5
    //   5273: arraylength
    //   5274: istore #6
    //   5276: iconst_0
    //   5277: istore #7
    //   5279: iload #7
    //   5281: iload #6
    //   5283: if_icmpge -> 5420
    //   5286: aload #5
    //   5288: iload #7
    //   5290: aaload
    //   5291: astore #8
    //   5293: aload #8
    //   5295: invokevirtual getParameterTypes : ()[Ljava/lang/Class;
    //   5298: pop
    //   5299: aload #8
    //   5301: invokevirtual getModifiers : ()I
    //   5304: invokestatic isStatic : (I)Z
    //   5307: ifeq -> 5406
    //   5310: aload #8
    //   5312: invokevirtual getParameterTypes : ()[Ljava/lang/Class;
    //   5315: arraylength
    //   5316: iconst_2
    //   5317: if_icmpne -> 5406
    //   5320: goto -> 5327
    //   5323: invokestatic a : (Ljava/lang/Throwable;)Ljava/lang/Throwable;
    //   5326: athrow
    //   5327: aload #8
    //   5329: invokevirtual getReturnType : ()Ljava/lang/Class;
    //   5332: getstatic java/lang/Boolean.TYPE : Ljava/lang/Class;
    //   5335: if_acmpne -> 5406
    //   5338: goto -> 5345
    //   5341: invokestatic a : (Ljava/lang/Throwable;)Ljava/lang/Throwable;
    //   5344: athrow
    //   5345: aload #8
    //   5347: iconst_1
    //   5348: invokevirtual setAccessible : (Z)V
    //   5351: aload #8
    //   5353: aconst_null
    //   5354: iconst_2
    //   5355: anewarray java/lang/Object
    //   5358: dup
    //   5359: iconst_0
    //   5360: aload_0
    //   5361: aastore
    //   5362: dup
    //   5363: iconst_1
    //   5364: aload_1
    //   5365: ifnonnull -> 5383
    //   5368: goto -> 5375
    //   5371: invokestatic a : (Ljava/lang/Throwable;)Ljava/lang/Throwable;
    //   5374: athrow
    //   5375: aload_1
    //   5376: goto -> 5390
    //   5379: invokestatic a : (Ljava/lang/Throwable;)Ljava/lang/Throwable;
    //   5382: athrow
    //   5383: aload_1
    //   5384: checkcast [B
    //   5387: invokevirtual clone : ()Ljava/lang/Object;
    //   5390: aastore
    //   5391: invokevirtual invoke : (Ljava/lang/Object;[Ljava/lang/Object;)Ljava/lang/Object;
    //   5394: checkcast java/lang/Boolean
    //   5397: invokevirtual booleanValue : ()Z
    //   5400: istore #4
    //   5402: iload_2
    //   5403: ifeq -> 5420
    //   5406: iinc #7, 1
    //   5409: iload_2
    //   5410: ifeq -> 5279
    //   5413: goto -> 5420
    //   5416: invokestatic a : (Ljava/lang/Throwable;)Ljava/lang/Throwable;
    //   5419: athrow
    //   5420: iload_2
    //   5421: ifeq -> 5763
    //   5424: sipush #19861
    //   5427: sipush #13244
    //   5430: invokestatic a : (II)Ljava/lang/String;
    //   5433: iconst_1
    //   5434: ldc burp/Zrpy
    //   5436: invokevirtual getClassLoader : ()Ljava/lang/ClassLoader;
    //   5439: invokestatic forName : (Ljava/lang/String;ZLjava/lang/ClassLoader;)Ljava/lang/Class;
    //   5442: invokevirtual getDeclaredFields : ()[Ljava/lang/reflect/Field;
    //   5445: astore #5
    //   5447: aload #5
    //   5449: arraylength
    //   5450: istore #6
    //   5452: iconst_0
    //   5453: istore #7
    //   5455: iload #7
    //   5457: iload #6
    //   5459: if_icmpge -> 5597
    //   5462: aload #5
    //   5464: iload #7
    //   5466: aaload
    //   5467: astore #8
    //   5469: aload #8
    //   5471: invokevirtual getModifiers : ()I
    //   5474: invokestatic isStatic : (I)Z
    //   5477: ifne -> 5487
    //   5480: goto -> 5590
    //   5483: invokestatic a : (Ljava/lang/Throwable;)Ljava/lang/Throwable;
    //   5486: athrow
    //   5487: aload #8
    //   5489: invokevirtual getType : ()Ljava/lang/Class;
    //   5492: astore #9
    //   5494: aload #9
    //   5496: ifnull -> 5577
    //   5499: aload #9
    //   5501: invokevirtual isPrimitive : ()Z
    //   5504: ifne -> 5577
    //   5507: goto -> 5514
    //   5510: invokestatic a : (Ljava/lang/Throwable;)Ljava/lang/Throwable;
    //   5513: athrow
    //   5514: aload #9
    //   5516: invokevirtual getPackage : ()Ljava/lang/Package;
    //   5519: ifnull -> 5577
    //   5522: goto -> 5529
    //   5525: invokestatic a : (Ljava/lang/Throwable;)Ljava/lang/Throwable;
    //   5528: athrow
    //   5529: aload #9
    //   5531: invokevirtual getPackage : ()Ljava/lang/Package;
    //   5534: invokevirtual getName : ()Ljava/lang/String;
    //   5537: ifnull -> 5577
    //   5540: goto -> 5547
    //   5543: invokestatic a : (Ljava/lang/Throwable;)Ljava/lang/Throwable;
    //   5546: athrow
    //   5547: aload #9
    //   5549: invokevirtual getPackage : ()Ljava/lang/Package;
    //   5552: invokevirtual getName : ()Ljava/lang/String;
    //   5555: sipush #19852
    //   5558: sipush #5694
    //   5561: invokestatic a : (II)Ljava/lang/String;
    //   5564: invokevirtual startsWith : (Ljava/lang/String;)Z
    //   5567: ifne -> 5577
    //   5570: goto -> 5577
    //   5573: invokestatic a : (Ljava/lang/Throwable;)Ljava/lang/Throwable;
    //   5576: athrow
    //   5577: aload #8
    //   5579: iconst_1
    //   5580: invokevirtual setAccessible : (Z)V
    //   5583: aload #8
    //   5585: aconst_null
    //   5586: invokevirtual get : (Ljava/lang/Object;)Ljava/lang/Object;
    //   5589: pop
    //   5590: iinc #7, 1
    //   5593: iload_2
    //   5594: ifeq -> 5455
    //   5597: sipush #19848
    //   5600: sipush #-2060
    //   5603: invokestatic a : (II)Ljava/lang/String;
    //   5606: invokestatic forName : (Ljava/lang/String;)Ljava/lang/Class;
    //   5609: invokevirtual getDeclaredMethods : ()[Ljava/lang/reflect/Method;
    //   5612: astore #5
    //   5614: aload #5
    //   5616: arraylength
    //   5617: istore #6
    //   5619: iconst_0
    //   5620: istore #7
    //   5622: iload #7
    //   5624: iload #6
    //   5626: if_icmpge -> 5763
    //   5629: aload #5
    //   5631: iload #7
    //   5633: aaload
    //   5634: astore #8
    //   5636: aload #8
    //   5638: invokevirtual getParameterTypes : ()[Ljava/lang/Class;
    //   5641: pop
    //   5642: aload #8
    //   5644: invokevirtual getModifiers : ()I
    //   5647: invokestatic isStatic : (I)Z
    //   5650: ifeq -> 5749
    //   5653: aload #8
    //   5655: invokevirtual getParameterTypes : ()[Ljava/lang/Class;
    //   5658: arraylength
    //   5659: iconst_2
    //   5660: if_icmpne -> 5749
    //   5663: goto -> 5670
    //   5666: invokestatic a : (Ljava/lang/Throwable;)Ljava/lang/Throwable;
    //   5669: athrow
    //   5670: aload #8
    //   5672: invokevirtual getReturnType : ()Ljava/lang/Class;
    //   5675: getstatic java/lang/Boolean.TYPE : Ljava/lang/Class;
    //   5678: if_acmpne -> 5749
    //   5681: goto -> 5688
    //   5684: invokestatic a : (Ljava/lang/Throwable;)Ljava/lang/Throwable;
    //   5687: athrow
    //   5688: aload #8
    //   5690: iconst_1
    //   5691: invokevirtual setAccessible : (Z)V
    //   5694: aload #8
    //   5696: aconst_null
    //   5697: iconst_2
    //   5698: anewarray java/lang/Object
    //   5701: dup
    //   5702: iconst_0
    //   5703: aload_0
    //   5704: aastore
    //   5705: dup
    //   5706: iconst_1
    //   5707: aload_1
    //   5708: ifnonnull -> 5726
    //   5711: goto -> 5718
    //   5714: invokestatic a : (Ljava/lang/Throwable;)Ljava/lang/Throwable;
    //   5717: athrow
    //   5718: aload_1
    //   5719: goto -> 5733
    //   5722: invokestatic a : (Ljava/lang/Throwable;)Ljava/lang/Throwable;
    //   5725: athrow
    //   5726: aload_1
    //   5727: checkcast [B
    //   5730: invokevirtual clone : ()Ljava/lang/Object;
    //   5733: aastore
    //   5734: invokevirtual invoke : (Ljava/lang/Object;[Ljava/lang/Object;)Ljava/lang/Object;
    //   5737: checkcast java/lang/Boolean
    //   5740: invokevirtual booleanValue : ()Z
    //   5743: istore #4
    //   5745: iload_2
    //   5746: ifeq -> 5763
    //   5749: iinc #7, 1
    //   5752: iload_2
    //   5753: ifeq -> 5622
    //   5756: goto -> 5763
    //   5759: invokestatic a : (Ljava/lang/Throwable;)Ljava/lang/Throwable;
    //   5762: athrow
    //   5763: iload #4
    //   5765: ireturn
    //   5766: astore_3
    //   5767: new java/lang/Exception
    //   5770: dup
    //   5771: aload_3
    //   5772: invokevirtual getMessage : ()Ljava/lang/String;
    //   5775: invokespecial <init> : (Ljava/lang/String;)V
    //   5778: athrow
    // Exception table:
    //   from	to	target	type
    //   4	3565	5766	java/lang/Throwable
    //   33	47	50	java/lang/Throwable
    //   40	61	64	java/lang/Throwable
    //   54	75	78	java/lang/Throwable
    //   68	89	92	java/lang/Throwable
    //   82	103	106	java/lang/Throwable
    //   96	117	120	java/lang/Throwable
    //   110	131	134	java/lang/Throwable
    //   124	145	148	java/lang/Throwable
    //   138	155	158	java/lang/Throwable
    //   194	208	211	java/lang/Throwable
    //   201	222	225	java/lang/Throwable
    //   215	236	239	java/lang/Throwable
    //   229	250	253	java/lang/Throwable
    //   243	264	267	java/lang/Throwable
    //   257	278	281	java/lang/Throwable
    //   271	292	295	java/lang/Throwable
    //   285	306	309	java/lang/Throwable
    //   299	323	326	java/lang/Throwable
    //   387	405	408	java/lang/Throwable
    //   396	421	424	java/lang/Throwable
    //   412	438	441	java/lang/Throwable
    //   428	454	457	java/lang/Throwable
    //   445	471	474	java/lang/Throwable
    //   461	487	490	java/lang/Throwable
    //   478	503	506	java/lang/Throwable
    //   494	526	529	java/lang/Throwable
    //   510	542	545	java/lang/Throwable
    //   533	558	561	java/lang/Throwable
    //   549	581	584	java/lang/Throwable
    //   565	597	600	java/lang/Throwable
    //   588	613	616	java/lang/Throwable
    //   604	632	635	java/lang/Throwable
    //   762	797	800	java/lang/Throwable
    //   804	845	848	java/lang/Throwable
    //   889	1062	1065	java/lang/Throwable
    //   1032	1099	1102	java/lang/Throwable
    //   1069	1136	1139	java/lang/Throwable
    //   1106	1173	1176	java/lang/Throwable
    //   1143	1210	1213	java/lang/Throwable
    //   1180	1247	1250	java/lang/Throwable
    //   1217	1284	1287	java/lang/Throwable
    //   1254	1321	1324	java/lang/Throwable
    //   1291	1358	1361	java/lang/Throwable
    //   1328	1395	1398	java/lang/Throwable
    //   1365	1432	1435	java/lang/Throwable
    //   1402	1469	1472	java/lang/Throwable
    //   1439	1506	1509	java/lang/Throwable
    //   1476	1543	1546	java/lang/Throwable
    //   1513	1580	1583	java/lang/Throwable
    //   1550	1617	1620	java/lang/Throwable
    //   1587	1654	1657	java/lang/Throwable
    //   1624	1691	1694	java/lang/Throwable
    //   1661	1728	1731	java/lang/Throwable
    //   1698	1765	1768	java/lang/Throwable
    //   1735	1802	1805	java/lang/Throwable
    //   1772	1839	1842	java/lang/Throwable
    //   1809	1876	1879	java/lang/Throwable
    //   1846	1913	1916	java/lang/Throwable
    //   1883	1950	1953	java/lang/Throwable
    //   1920	1987	1990	java/lang/Throwable
    //   1957	2024	2027	java/lang/Throwable
    //   1994	2061	2064	java/lang/Throwable
    //   2031	2098	2101	java/lang/Throwable
    //   2068	2135	2138	java/lang/Throwable
    //   2105	2172	2175	java/lang/Throwable
    //   2142	2205	2208	java/lang/Throwable
    //   2289	2303	2303	java/lang/Throwable
    //   2314	2327	2330	java/lang/Throwable
    //   2319	2342	2345	java/lang/Throwable
    //   2334	2360	2363	java/lang/Throwable
    //   2349	2390	2393	java/lang/Throwable
    //   2456	2483	2486	java/lang/Throwable
    //   2473	2504	2507	java/lang/Throwable
    //   2490	2534	2537	java/lang/Throwable
    //   2511	2545	2545	java/lang/Throwable
    //   2556	2572	2575	java/lang/Throwable
    //   2922	2936	2936	java/lang/Throwable
    //   2947	2960	2963	java/lang/Throwable
    //   2952	2975	2978	java/lang/Throwable
    //   2967	2993	2996	java/lang/Throwable
    //   2982	3023	3026	java/lang/Throwable
    //   3089	3116	3119	java/lang/Throwable
    //   3106	3134	3137	java/lang/Throwable
    //   3123	3164	3167	java/lang/Throwable
    //   3141	3175	3175	java/lang/Throwable
    //   3198	3209	3212	java/lang/Throwable
    //   3264	3278	3278	java/lang/Throwable
    //   3289	3302	3305	java/lang/Throwable
    //   3294	3317	3320	java/lang/Throwable
    //   3309	3335	3338	java/lang/Throwable
    //   3324	3365	3368	java/lang/Throwable
    //   3431	3458	3461	java/lang/Throwable
    //   3448	3476	3479	java/lang/Throwable
    //   3465	3506	3509	java/lang/Throwable
    //   3483	3517	3517	java/lang/Throwable
    //   3540	3551	3554	java/lang/Throwable
    //   3566	4300	5766	java/lang/Throwable
    //   3656	3670	3670	java/lang/Throwable
    //   3681	3694	3697	java/lang/Throwable
    //   3686	3709	3712	java/lang/Throwable
    //   3701	3727	3730	java/lang/Throwable
    //   3716	3757	3760	java/lang/Throwable
    //   3823	3850	3853	java/lang/Throwable
    //   3840	3868	3871	java/lang/Throwable
    //   3857	3898	3901	java/lang/Throwable
    //   3875	3909	3909	java/lang/Throwable
    //   3932	3943	3946	java/lang/Throwable
    //   3999	4013	4013	java/lang/Throwable
    //   4024	4037	4040	java/lang/Throwable
    //   4029	4052	4055	java/lang/Throwable
    //   4044	4070	4073	java/lang/Throwable
    //   4059	4100	4103	java/lang/Throwable
    //   4166	4193	4196	java/lang/Throwable
    //   4183	4211	4214	java/lang/Throwable
    //   4200	4241	4244	java/lang/Throwable
    //   4218	4252	4252	java/lang/Throwable
    //   4275	4286	4289	java/lang/Throwable
    //   4301	5035	5766	java/lang/Throwable
    //   4391	4405	4405	java/lang/Throwable
    //   4416	4429	4432	java/lang/Throwable
    //   4421	4444	4447	java/lang/Throwable
    //   4436	4462	4465	java/lang/Throwable
    //   4451	4492	4495	java/lang/Throwable
    //   4558	4585	4588	java/lang/Throwable
    //   4575	4603	4606	java/lang/Throwable
    //   4592	4633	4636	java/lang/Throwable
    //   4610	4644	4644	java/lang/Throwable
    //   4667	4678	4681	java/lang/Throwable
    //   4734	4748	4748	java/lang/Throwable
    //   4759	4772	4775	java/lang/Throwable
    //   4764	4787	4790	java/lang/Throwable
    //   4779	4805	4808	java/lang/Throwable
    //   4794	4835	4838	java/lang/Throwable
    //   4901	4928	4931	java/lang/Throwable
    //   4918	4946	4949	java/lang/Throwable
    //   4935	4976	4979	java/lang/Throwable
    //   4953	4987	4987	java/lang/Throwable
    //   5010	5021	5024	java/lang/Throwable
    //   5036	5765	5766	java/lang/Throwable
    //   5126	5140	5140	java/lang/Throwable
    //   5151	5164	5167	java/lang/Throwable
    //   5156	5179	5182	java/lang/Throwable
    //   5171	5197	5200	java/lang/Throwable
    //   5186	5227	5230	java/lang/Throwable
    //   5293	5320	5323	java/lang/Throwable
    //   5310	5338	5341	java/lang/Throwable
    //   5327	5368	5371	java/lang/Throwable
    //   5345	5379	5379	java/lang/Throwable
    //   5402	5413	5416	java/lang/Throwable
    //   5469	5483	5483	java/lang/Throwable
    //   5494	5507	5510	java/lang/Throwable
    //   5499	5522	5525	java/lang/Throwable
    //   5514	5540	5543	java/lang/Throwable
    //   5529	5570	5573	java/lang/Throwable
    //   5636	5663	5666	java/lang/Throwable
    //   5653	5681	5684	java/lang/Throwable
    //   5670	5711	5714	java/lang/Throwable
    //   5688	5722	5722	java/lang/Throwable
    //   5745	5756	5759	java/lang/Throwable
  }
  
  static void Zw(Object paramObject) {
    Zewo.ZM = a(19869, 17326);
    Zewo.ZZ = new BigInteger(a(19864, 17752));
    boolean bool = Zt2e.ZK();
    try {
      try {
        if (Zly0.ZE.charAt(Math.abs(((BigInteger)Zly0.ZB).intValue() % 32)) > Zty3.ZW.charAt(Math.abs(((BigInteger)Zghe.ZJ).intValue() % 32))) {
          try {
            Zro5.Zm(Class.forName(a(19862, 1182)));
            if (bool)
              Zkv2.Zc(Class.forName(a(19859, 25040))); 
          } catch (Throwable throwable) {
            throw a(null);
          } 
          return;
        } 
      } catch (Throwable throwable) {
        throw a(null);
      } 
      Zkv2.Zc(Class.forName(a(19859, 25040)));
    } catch (Throwable throwable) {}
  }
  
  static void Ze(Object[] paramArrayOfObject, Object paramObject) throws Throwable {}
  
  static {
    // Byte code:
    //   0: bipush #24
    //   2: anewarray java/lang/String
    //   5: astore #5
    //   7: iconst_0
    //   8: istore_3
    //   9: ldc 'a<oKLxE-H\\n?l4rkMe{iahrJ)+0\\fcMIGd|YHP\\nOca,)|X/R64c4~+zF:'12r\\t}[n\\tW@\\n\\t-P\\tJ, x\\fl,y`-\\nt'r9o\\t m*py\\t4O\\t<-*k\\t\\tO;.\\tQ| _O\\tId5Q22%\\r\\ty3Uz\\t1I\\tb6e"\\tNwcBR\\tD6:L\\tRHE\\tiW:g'
    //   11: dup
    //   12: astore_2
    //   13: invokevirtual length : ()I
    //   16: istore #4
    //   18: bipush #8
    //   20: istore_1
    //   21: iconst_m1
    //   22: istore_0
    //   23: bipush #67
    //   25: iinc #0, 1
    //   28: aload_2
    //   29: iload_0
    //   30: dup
    //   31: iload_1
    //   32: iadd
    //   33: invokevirtual substring : (II)Ljava/lang/String;
    //   36: iconst_m1
    //   37: goto -> 142
    //   40: aload #5
    //   42: swap
    //   43: iload_3
    //   44: iinc #3, 1
    //   47: swap
    //   48: aastore
    //   49: iload_0
    //   50: iload_1
    //   51: iadd
    //   52: dup
    //   53: istore_0
    //   54: iload #4
    //   56: if_icmpge -> 68
    //   59: aload_2
    //   60: iload_0
    //   61: invokevirtual charAt : (I)C
    //   64: istore_1
    //   65: goto -> 23
    //   68: ldc ':j\\t '
    //   70: dup
    //   71: astore_2
    //   72: invokevirtual length : ()I
    //   75: istore #4
    //   77: iconst_4
    //   78: istore_1
    //   79: iconst_m1
    //   80: istore_0
    //   81: bipush #11
    //   83: iinc #0, 1
    //   86: aload_2
    //   87: iload_0
    //   88: dup
    //   89: iload_1
    //   90: iadd
    //   91: invokevirtual substring : (II)Ljava/lang/String;
    //   94: iconst_0
    //   95: goto -> 142
    //   98: aload #5
    //   100: swap
    //   101: iload_3
    //   102: iinc #3, 1
    //   105: swap
    //   106: aastore
    //   107: iload_0
    //   108: iload_1
    //   109: iadd
    //   110: dup
    //   111: istore_0
    //   112: iload #4
    //   114: if_icmpge -> 126
    //   117: aload_2
    //   118: iload_0
    //   119: invokevirtual charAt : (I)C
    //   122: istore_1
    //   123: goto -> 81
    //   126: aload #5
    //   128: putstatic burp/Zgdj.a : [Ljava/lang/String;
    //   131: bipush #24
    //   133: anewarray java/lang/String
    //   136: putstatic burp/Zgdj.b : [Ljava/lang/String;
    //   139: goto -> 300
    //   142: dup_x2
    //   143: pop
    //   144: invokevirtual toCharArray : ()[C
    //   147: dup_x1
    //   148: arraylength
    //   149: dup_x2
    //   150: pop
    //   151: iconst_0
    //   152: istore #6
    //   154: dup2_x1
    //   155: pop2
    //   156: dup_x2
    //   157: iconst_1
    //   158: if_icmpgt -> 260
    //   161: dup2
    //   162: swap
    //   163: iload #6
    //   165: dup2_x1
    //   166: caload
    //   167: swap
    //   168: iload #6
    //   170: bipush #7
    //   172: irem
    //   173: tableswitch default -> 242, 0 -> 212, 1 -> 217, 2 -> 222, 3 -> 227, 4 -> 232, 5 -> 237
    //   212: bipush #86
    //   214: goto -> 244
    //   217: bipush #125
    //   219: goto -> 244
    //   222: bipush #23
    //   224: goto -> 244
    //   227: bipush #85
    //   229: goto -> 244
    //   232: bipush #21
    //   234: goto -> 244
    //   237: bipush #117
    //   239: goto -> 244
    //   242: bipush #28
    //   244: ixor
    //   245: ixor
    //   246: i2c
    //   247: castore
    //   248: iinc #6, 1
    //   251: dup
    //   252: ifne -> 260
    //   255: dup2
    //   256: dup_x1
    //   257: goto -> 165
    //   260: dup2_x1
    //   261: pop2
    //   262: dup_x2
    //   263: iload #6
    //   265: if_icmpgt -> 161
    //   268: pop
    //   269: new java/lang/String
    //   272: dup_x1
    //   273: swap
    //   274: invokespecial <init> : ([C)V
    //   277: invokevirtual intern : ()Ljava/lang/String;
    //   280: swap
    //   281: pop
    //   282: swap
    //   283: tableswitch default -> 40, 0 -> 98
    //   300: new java/math/BigInteger
    //   303: dup
    //   304: sipush #19867
    //   307: sipush #16284
    //   310: invokestatic a : (II)Ljava/lang/String;
    //   313: invokespecial <init> : (Ljava/lang/String;)V
    //   316: putstatic burp/Zgdj.ZT : Ljava/lang/Object;
    //   319: sipush #19863
    //   322: sipush #-7313
    //   325: invokestatic a : (II)Ljava/lang/String;
    //   328: putstatic burp/Zgdj.Zt : Ljava/lang/String;
    //   331: return
  }
  
  private static Throwable a(Throwable paramThrowable) {
    return paramThrowable;
  }
  
  private static String a(int paramInt1, int paramInt2) {
    int i = (paramInt1 ^ 0x4D9A) & 0xFFFF;
    if (b[i] == null) {
      char[] arrayOfChar = a[i].toCharArray();
      switch (arrayOfChar[0] & 0xFF) {
        case 0:
        
        case 1:
        
        case 2:
        
        case 3:
        
        case 4:
        
        case 5:
        
        case 6:
        
        case 7:
        
        case 8:
        
        case 9:
        
        case 10:
        
        case 11:
        
        case 12:
        
        case 13:
        
        case 14:
        
        case 15:
        
        case 16:
        
        case 17:
        
        case 18:
        
        case 19:
        
        case 20:
        
        case 21:
        
        case 22:
        
        case 23:
        
        case 24:
        
        case 25:
        
        case 26:
        
        case 27:
        
        case 28:
        
        case 29:
        
        case 30:
        
        case 31:
        
        case 32:
        
        case 33:
        
        case 34:
        
        case 35:
        
        case 36:
        
        case 37:
        
        case 38:
        
        case 39:
        
        case 40:
        
        case 41:
        
        case 42:
        
        case 43:
        
        case 44:
        
        case 45:
        
        case 46:
        
        case 47:
        
        case 48:
        
        case 49:
        
        case 50:
        
        case 51:
        
        case 52:
        
        case 53:
        
        case 54:
        
        case 55:
        
        case 56:
        
        case 57:
        
        case 58:
        
        case 59:
        
        case 60:
        
        case 61:
        
        case 62:
        
        case 63:
        
        case 64:
        
        case 65:
        
        case 66:
        
        case 67:
        
        case 68:
        
        case 69:
        
        case 70:
        
        case 71:
        
        case 72:
        
        case 73:
        
        case 74:
        
        case 75:
        
        case 76:
        
        case 77:
        
        case 78:
        
        case 79:
        
        case 80:
        
        case 81:
        
        case 82:
        
        case 83:
        
        case 84:
        
        case 85:
        
        case 86:
        
        case 87:
        
        case 88:
        
        case 89:
        
        case 90:
        
        case 91:
        
        case 92:
        
        case 93:
        
        case 94:
        
        case 95:
        
        case 96:
        
        case 97:
        
        case 98:
        
        case 99:
        
        case 100:
        
        case 101:
        
        case 102:
        
        case 103:
        
        case 104:
        
        case 105:
        
        case 106:
        
        case 107:
        
        case 108:
        
        case 109:
        
        case 110:
        
        case 111:
        
        case 112:
        
        case 113:
        
        case 114:
        
        case 115:
        
        case 116:
        
        case 117:
        
        case 118:
        
        case 119:
        
        case 120:
        
        case 121:
        
        case 122:
        
        case 123:
        
        case 124:
        
        case 125:
        
        case 126:
        
        case 127:
        
        case 128:
        
        case 129:
        
        case 130:
        
        case 131:
        
        case 132:
        
        case 133:
        
        case 134:
        
        case 135:
        
        case 136:
        
        case 137:
        
        case 138:
        
        case 139:
        
        case 140:
        
        case 141:
        
        case 142:
        
        case 143:
        
        case 144:
        
        case 145:
        
        case 146:
        
        case 147:
        
        case 148:
        
        case 149:
        
        case 150:
        
        case 151:
        
        case 152:
        
        case 153:
        
        case 154:
        
        case 155:
        
        case 156:
        
        case 157:
        
        case 158:
        
        case 159:
        
        case 160:
        
        case 161:
        
        case 162:
        
        case 163:
        
        case 164:
        
        case 165:
        
        case 166:
        
        case 167:
        
        case 168:
        
        case 169:
        
        case 170:
        
        case 171:
        
        case 172:
        
        case 173:
        
        case 174:
        
        case 175:
        
        case 176:
        
        case 177:
        
        case 178:
        
        case 179:
        
        case 180:
        
        case 181:
        
        case 182:
        
        case 183:
        
        case 184:
        
        case 185:
        
        case 186:
        
        case 187:
        
        case 188:
        
        case 189:
        
        case 190:
        
        case 191:
        
        case 192:
        
        case 193:
        
        case 194:
        
        case 195:
        
        case 196:
        
        case 197:
        
        case 198:
        
        case 199:
        
        case 200:
        
        case 201:
        
        case 202:
        
        case 203:
        
        case 204:
        
        case 205:
        
        case 206:
        
        case 207:
        
        case 208:
        
        case 209:
        
        case 210:
        
        case 211:
        
        case 212:
        
        case 213:
        
        case 214:
        
        case 215:
        
        case 216:
        
        case 217:
        
        case 218:
        
        case 219:
        
        case 220:
        
        case 221:
        
        case 222:
        
        case 223:
        
        case 224:
        
        case 225:
        
        case 226:
        
        case 227:
        
        case 228:
        
        case 229:
        
        case 230:
        
        case 231:
        
        case 232:
        
        case 233:
        
        case 234:
        
        case 235:
        
        case 236:
        
        case 237:
        
        case 238:
        
        case 239:
        
        case 240:
        
        case 241:
        
        case 242:
        
        case 243:
        
        case 244:
        
        case 245:
        
        case 246:
        
        case 247:
        
        case 248:
        
        case 249:
        
        case 250:
        
        case 251:
        
        case 252:
        
        case 253:
        
        case 254:
        
        default:
          break;
      } 
      char c = '';
      int j = (paramInt2 & 0xFF) - c;
      if (j < 0)
        j += 256; 
      int k = ((paramInt2 & 0xFFFF) >>> 8) - c;
      if (k < 0)
        k += 256; 
      for (byte b = 0; b < arrayOfChar.length; b++) {
        int m = b % 2;
        if (m == 0) {
          arrayOfChar[b] = (char)(arrayOfChar[b] ^ j);
          j = ((j >>> 3 | j << 5) ^ arrayOfChar[b]) & 0xFF;
        } else {
          arrayOfChar[b] = (char)(arrayOfChar[b] ^ k);
          k = ((k >>> 3 | k << 5) ^ arrayOfChar[b]) & 0xFF;
        } 
      } 
      b[i] = (new String(arrayOfChar)).intern();
    } 
    return b[i];
  }
}


/* Location:              C:\Program Files\BurpSuitePro\burpsuite_pro.jar!\burp\Zgdj.class
 * Java compiler version: 21 (65.0)
 * JD-Core Version:       1.1.3
 */