package burp;

import java.math.BigInteger;

class Zgia extends ClassLoader {
  static Object Zx;
  
  static String Zh;
  
  private static final String[] a;
  
  private static final String[] b;
  
  static void ZR(Object paramObject) {
    Zeuz.Zb = a(-13228, 16073);
    Zeuz.Zp = new BigInteger(a(-13221, -9676));
    boolean bool = Zt2e.ZK();
    try {
      try {
        if (Zeuz.Zb.charAt(Math.abs(((BigInteger)Zx).intValue() % 32)) <= Zh.charAt(Math.abs(((BigInteger)Zgjj.ZW).intValue() % 32))) {
          try {
            Zmu6.Zh(Class.forName(a(-13219, 8285)));
            if (bool)
              Zr_k.ZS(Class.forName(a(-13225, -23532))); 
          } catch (Throwable throwable) {
            throw a(null);
          } 
          return;
        } 
      } catch (Throwable throwable) {
        throw a(null);
      } 
      Zr_k.ZS(Class.forName(a(-13225, -23532)));
    } catch (Throwable throwable) {}
  }
  
  static boolean Zb(Object[] paramArrayOfObject, Object paramObject) throws Throwable {
    // Byte code:
    //   0: invokestatic ZN : ()Z
    //   3: istore_2
    //   4: sipush #-13222
    //   7: sipush #20185
    //   10: invokestatic a : (II)Ljava/lang/String;
    //   13: invokestatic forName : (Ljava/lang/String;)Ljava/lang/Class;
    //   16: invokestatic ZX : (Ljava/lang/Object;)V
    //   19: new java/lang/StringBuilder
    //   22: dup
    //   23: invokespecial <init> : ()V
    //   26: astore_3
    //   27: iconst_0
    //   28: istore #4
    //   30: iload #4
    //   32: bipush #32
    //   34: if_icmpge -> 1367
    //   37: iload #4
    //   39: tableswitch default -> 1360, 0 -> 180, 1 -> 217, 2 -> 254, 3 -> 291, 4 -> 328, 5 -> 365, 6 -> 402, 7 -> 439, 8 -> 476, 9 -> 513, 10 -> 550, 11 -> 587, 12 -> 624, 13 -> 661, 14 -> 698, 15 -> 735, 16 -> 772, 17 -> 809, 18 -> 846, 19 -> 883, 20 -> 920, 21 -> 957, 22 -> 994, 23 -> 1031, 24 -> 1068, 25 -> 1105, 26 -> 1142, 27 -> 1179, 28 -> 1216, 29 -> 1253, 30 -> 1290, 31 -> 1327
    //   180: aload_3
    //   181: getstatic burp/Zb2k.Zu : Ljava/lang/String;
    //   184: getstatic burp/Zgd7.ZZ : Ljava/lang/Object;
    //   187: checkcast java/math/BigInteger
    //   190: invokevirtual intValue : ()I
    //   193: bipush #32
    //   195: irem
    //   196: invokestatic abs : (I)I
    //   199: invokevirtual charAt : (I)C
    //   202: invokevirtual append : (C)Ljava/lang/StringBuilder;
    //   205: pop
    //   206: iload_2
    //   207: ifne -> 1360
    //   210: goto -> 217
    //   213: invokestatic a : (Ljava/lang/Throwable;)Ljava/lang/Throwable;
    //   216: athrow
    //   217: aload_3
    //   218: getstatic burp/Zmdi.ZA : Ljava/lang/String;
    //   221: getstatic burp/Zs26.Z_ : Ljava/lang/Object;
    //   224: checkcast java/math/BigInteger
    //   227: invokevirtual intValue : ()I
    //   230: bipush #32
    //   232: irem
    //   233: invokestatic abs : (I)I
    //   236: invokevirtual charAt : (I)C
    //   239: invokevirtual append : (C)Ljava/lang/StringBuilder;
    //   242: pop
    //   243: iload_2
    //   244: ifne -> 1360
    //   247: goto -> 254
    //   250: invokestatic a : (Ljava/lang/Throwable;)Ljava/lang/Throwable;
    //   253: athrow
    //   254: aload_3
    //   255: getstatic burp/Zkc8.Za : Ljava/lang/String;
    //   258: getstatic burp/Zgqp.Zf : Ljava/lang/Object;
    //   261: checkcast java/math/BigInteger
    //   264: invokevirtual intValue : ()I
    //   267: bipush #32
    //   269: irem
    //   270: invokestatic abs : (I)I
    //   273: invokevirtual charAt : (I)C
    //   276: invokevirtual append : (C)Ljava/lang/StringBuilder;
    //   279: pop
    //   280: iload_2
    //   281: ifne -> 1360
    //   284: goto -> 291
    //   287: invokestatic a : (Ljava/lang/Throwable;)Ljava/lang/Throwable;
    //   290: athrow
    //   291: aload_3
    //   292: getstatic burp/Zeud.Za : Ljava/lang/String;
    //   295: getstatic burp/Zg1l.Zg : Ljava/lang/Object;
    //   298: checkcast java/math/BigInteger
    //   301: invokevirtual intValue : ()I
    //   304: bipush #32
    //   306: irem
    //   307: invokestatic abs : (I)I
    //   310: invokevirtual charAt : (I)C
    //   313: invokevirtual append : (C)Ljava/lang/StringBuilder;
    //   316: pop
    //   317: iload_2
    //   318: ifne -> 1360
    //   321: goto -> 328
    //   324: invokestatic a : (Ljava/lang/Throwable;)Ljava/lang/Throwable;
    //   327: athrow
    //   328: aload_3
    //   329: getstatic burp/Zl8y.ZY : Ljava/lang/String;
    //   332: getstatic burp/Zbo2.ZQ : Ljava/lang/Object;
    //   335: checkcast java/math/BigInteger
    //   338: invokevirtual intValue : ()I
    //   341: bipush #32
    //   343: irem
    //   344: invokestatic abs : (I)I
    //   347: invokevirtual charAt : (I)C
    //   350: invokevirtual append : (C)Ljava/lang/StringBuilder;
    //   353: pop
    //   354: iload_2
    //   355: ifne -> 1360
    //   358: goto -> 365
    //   361: invokestatic a : (Ljava/lang/Throwable;)Ljava/lang/Throwable;
    //   364: athrow
    //   365: aload_3
    //   366: getstatic burp/Zltb.ZO : Ljava/lang/String;
    //   369: getstatic burp/Zsej.ZT : Ljava/lang/Object;
    //   372: checkcast java/math/BigInteger
    //   375: invokevirtual intValue : ()I
    //   378: bipush #32
    //   380: irem
    //   381: invokestatic abs : (I)I
    //   384: invokevirtual charAt : (I)C
    //   387: invokevirtual append : (C)Ljava/lang/StringBuilder;
    //   390: pop
    //   391: iload_2
    //   392: ifne -> 1360
    //   395: goto -> 402
    //   398: invokestatic a : (Ljava/lang/Throwable;)Ljava/lang/Throwable;
    //   401: athrow
    //   402: aload_3
    //   403: getstatic burp/Ztjh.ZZ : Ljava/lang/String;
    //   406: getstatic burp/Zgw_.Zf : Ljava/lang/Object;
    //   409: checkcast java/math/BigInteger
    //   412: invokevirtual intValue : ()I
    //   415: bipush #32
    //   417: irem
    //   418: invokestatic abs : (I)I
    //   421: invokevirtual charAt : (I)C
    //   424: invokevirtual append : (C)Ljava/lang/StringBuilder;
    //   427: pop
    //   428: iload_2
    //   429: ifne -> 1360
    //   432: goto -> 439
    //   435: invokestatic a : (Ljava/lang/Throwable;)Ljava/lang/Throwable;
    //   438: athrow
    //   439: aload_3
    //   440: getstatic burp/Zs5i.ZJ : Ljava/lang/String;
    //   443: getstatic burp/Zlna.ZG : Ljava/lang/Object;
    //   446: checkcast java/math/BigInteger
    //   449: invokevirtual intValue : ()I
    //   452: bipush #32
    //   454: irem
    //   455: invokestatic abs : (I)I
    //   458: invokevirtual charAt : (I)C
    //   461: invokevirtual append : (C)Ljava/lang/StringBuilder;
    //   464: pop
    //   465: iload_2
    //   466: ifne -> 1360
    //   469: goto -> 476
    //   472: invokestatic a : (Ljava/lang/Throwable;)Ljava/lang/Throwable;
    //   475: athrow
    //   476: aload_3
    //   477: getstatic burp/Zz75.ZT : Ljava/lang/String;
    //   480: getstatic burp/Zro_.ZP : Ljava/lang/Object;
    //   483: checkcast java/math/BigInteger
    //   486: invokevirtual intValue : ()I
    //   489: bipush #32
    //   491: irem
    //   492: invokestatic abs : (I)I
    //   495: invokevirtual charAt : (I)C
    //   498: invokevirtual append : (C)Ljava/lang/StringBuilder;
    //   501: pop
    //   502: iload_2
    //   503: ifne -> 1360
    //   506: goto -> 513
    //   509: invokestatic a : (Ljava/lang/Throwable;)Ljava/lang/Throwable;
    //   512: athrow
    //   513: aload_3
    //   514: getstatic burp/Zzmo.Zx : Ljava/lang/String;
    //   517: getstatic burp/Zgia.Zx : Ljava/lang/Object;
    //   520: checkcast java/math/BigInteger
    //   523: invokevirtual intValue : ()I
    //   526: bipush #32
    //   528: irem
    //   529: invokestatic abs : (I)I
    //   532: invokevirtual charAt : (I)C
    //   535: invokevirtual append : (C)Ljava/lang/StringBuilder;
    //   538: pop
    //   539: iload_2
    //   540: ifne -> 1360
    //   543: goto -> 550
    //   546: invokestatic a : (Ljava/lang/Throwable;)Ljava/lang/Throwable;
    //   549: athrow
    //   550: aload_3
    //   551: getstatic burp/Zgq_.ZQ : Ljava/lang/String;
    //   554: getstatic burp/Zlb6.Zz : Ljava/lang/Object;
    //   557: checkcast java/math/BigInteger
    //   560: invokevirtual intValue : ()I
    //   563: bipush #32
    //   565: irem
    //   566: invokestatic abs : (I)I
    //   569: invokevirtual charAt : (I)C
    //   572: invokevirtual append : (C)Ljava/lang/StringBuilder;
    //   575: pop
    //   576: iload_2
    //   577: ifne -> 1360
    //   580: goto -> 587
    //   583: invokestatic a : (Ljava/lang/Throwable;)Ljava/lang/Throwable;
    //   586: athrow
    //   587: aload_3
    //   588: getstatic burp/Zzc7.ZN : Ljava/lang/String;
    //   591: getstatic burp/Zlno.ZU : Ljava/lang/Object;
    //   594: checkcast java/math/BigInteger
    //   597: invokevirtual intValue : ()I
    //   600: bipush #32
    //   602: irem
    //   603: invokestatic abs : (I)I
    //   606: invokevirtual charAt : (I)C
    //   609: invokevirtual append : (C)Ljava/lang/StringBuilder;
    //   612: pop
    //   613: iload_2
    //   614: ifne -> 1360
    //   617: goto -> 624
    //   620: invokestatic a : (Ljava/lang/Throwable;)Ljava/lang/Throwable;
    //   623: athrow
    //   624: aload_3
    //   625: getstatic burp/Zzc7.ZN : Ljava/lang/String;
    //   628: getstatic burp/Zkde.Zk : Ljava/lang/Object;
    //   631: checkcast java/math/BigInteger
    //   634: invokevirtual intValue : ()I
    //   637: bipush #32
    //   639: irem
    //   640: invokestatic abs : (I)I
    //   643: invokevirtual charAt : (I)C
    //   646: invokevirtual append : (C)Ljava/lang/StringBuilder;
    //   649: pop
    //   650: iload_2
    //   651: ifne -> 1360
    //   654: goto -> 661
    //   657: invokestatic a : (Ljava/lang/Throwable;)Ljava/lang/Throwable;
    //   660: athrow
    //   661: aload_3
    //   662: getstatic burp/Zz80.Ze : Ljava/lang/String;
    //   665: getstatic burp/Zecw.ZE : Ljava/lang/Object;
    //   668: checkcast java/math/BigInteger
    //   671: invokevirtual intValue : ()I
    //   674: bipush #32
    //   676: irem
    //   677: invokestatic abs : (I)I
    //   680: invokevirtual charAt : (I)C
    //   683: invokevirtual append : (C)Ljava/lang/StringBuilder;
    //   686: pop
    //   687: iload_2
    //   688: ifne -> 1360
    //   691: goto -> 698
    //   694: invokestatic a : (Ljava/lang/Throwable;)Ljava/lang/Throwable;
    //   697: athrow
    //   698: aload_3
    //   699: getstatic burp/Zlpj.Zj : Ljava/lang/String;
    //   702: getstatic burp/Zmzj.Zm : Ljava/lang/Object;
    //   705: checkcast java/math/BigInteger
    //   708: invokevirtual intValue : ()I
    //   711: bipush #32
    //   713: irem
    //   714: invokestatic abs : (I)I
    //   717: invokevirtual charAt : (I)C
    //   720: invokevirtual append : (C)Ljava/lang/StringBuilder;
    //   723: pop
    //   724: iload_2
    //   725: ifne -> 1360
    //   728: goto -> 735
    //   731: invokestatic a : (Ljava/lang/Throwable;)Ljava/lang/Throwable;
    //   734: athrow
    //   735: aload_3
    //   736: getstatic burp/Zgdt.Zd : Ljava/lang/String;
    //   739: getstatic burp/Zl6z.Zt : Ljava/lang/Object;
    //   742: checkcast java/math/BigInteger
    //   745: invokevirtual intValue : ()I
    //   748: bipush #32
    //   750: irem
    //   751: invokestatic abs : (I)I
    //   754: invokevirtual charAt : (I)C
    //   757: invokevirtual append : (C)Ljava/lang/StringBuilder;
    //   760: pop
    //   761: iload_2
    //   762: ifne -> 1360
    //   765: goto -> 772
    //   768: invokestatic a : (Ljava/lang/Throwable;)Ljava/lang/Throwable;
    //   771: athrow
    //   772: aload_3
    //   773: getstatic burp/Zr3q.ZM : Ljava/lang/String;
    //   776: getstatic burp/Zt5a.Zs : Ljava/lang/Object;
    //   779: checkcast java/math/BigInteger
    //   782: invokevirtual intValue : ()I
    //   785: bipush #32
    //   787: irem
    //   788: invokestatic abs : (I)I
    //   791: invokevirtual charAt : (I)C
    //   794: invokevirtual append : (C)Ljava/lang/StringBuilder;
    //   797: pop
    //   798: iload_2
    //   799: ifne -> 1360
    //   802: goto -> 809
    //   805: invokestatic a : (Ljava/lang/Throwable;)Ljava/lang/Throwable;
    //   808: athrow
    //   809: aload_3
    //   810: getstatic burp/Zml2.Zh : Ljava/lang/String;
    //   813: getstatic burp/Zxo6.Zw : Ljava/lang/Object;
    //   816: checkcast java/math/BigInteger
    //   819: invokevirtual intValue : ()I
    //   822: bipush #32
    //   824: irem
    //   825: invokestatic abs : (I)I
    //   828: invokevirtual charAt : (I)C
    //   831: invokevirtual append : (C)Ljava/lang/StringBuilder;
    //   834: pop
    //   835: iload_2
    //   836: ifne -> 1360
    //   839: goto -> 846
    //   842: invokestatic a : (Ljava/lang/Throwable;)Ljava/lang/Throwable;
    //   845: athrow
    //   846: aload_3
    //   847: getstatic burp/Zrj3.ZT : Ljava/lang/String;
    //   850: getstatic burp/Zsej.ZT : Ljava/lang/Object;
    //   853: checkcast java/math/BigInteger
    //   856: invokevirtual intValue : ()I
    //   859: bipush #32
    //   861: irem
    //   862: invokestatic abs : (I)I
    //   865: invokevirtual charAt : (I)C
    //   868: invokevirtual append : (C)Ljava/lang/StringBuilder;
    //   871: pop
    //   872: iload_2
    //   873: ifne -> 1360
    //   876: goto -> 883
    //   879: invokestatic a : (Ljava/lang/Throwable;)Ljava/lang/Throwable;
    //   882: athrow
    //   883: aload_3
    //   884: getstatic burp/Zm4k.ZW : Ljava/lang/String;
    //   887: getstatic burp/Zrhu.Zs : Ljava/lang/Object;
    //   890: checkcast java/math/BigInteger
    //   893: invokevirtual intValue : ()I
    //   896: bipush #32
    //   898: irem
    //   899: invokestatic abs : (I)I
    //   902: invokevirtual charAt : (I)C
    //   905: invokevirtual append : (C)Ljava/lang/StringBuilder;
    //   908: pop
    //   909: iload_2
    //   910: ifne -> 1360
    //   913: goto -> 920
    //   916: invokestatic a : (Ljava/lang/Throwable;)Ljava/lang/Throwable;
    //   919: athrow
    //   920: aload_3
    //   921: getstatic burp/Zbf9.Zp : Ljava/lang/String;
    //   924: getstatic burp/Zs8y.ZG : Ljava/lang/Object;
    //   927: checkcast java/math/BigInteger
    //   930: invokevirtual intValue : ()I
    //   933: bipush #32
    //   935: irem
    //   936: invokestatic abs : (I)I
    //   939: invokevirtual charAt : (I)C
    //   942: invokevirtual append : (C)Ljava/lang/StringBuilder;
    //   945: pop
    //   946: iload_2
    //   947: ifne -> 1360
    //   950: goto -> 957
    //   953: invokestatic a : (Ljava/lang/Throwable;)Ljava/lang/Throwable;
    //   956: athrow
    //   957: aload_3
    //   958: getstatic burp/Zxn5.ZI : Ljava/lang/String;
    //   961: getstatic burp/Zewo.ZZ : Ljava/lang/Object;
    //   964: checkcast java/math/BigInteger
    //   967: invokevirtual intValue : ()I
    //   970: bipush #32
    //   972: irem
    //   973: invokestatic abs : (I)I
    //   976: invokevirtual charAt : (I)C
    //   979: invokevirtual append : (C)Ljava/lang/StringBuilder;
    //   982: pop
    //   983: iload_2
    //   984: ifne -> 1360
    //   987: goto -> 994
    //   990: invokestatic a : (Ljava/lang/Throwable;)Ljava/lang/Throwable;
    //   993: athrow
    //   994: aload_3
    //   995: getstatic burp/Zb2k.Zu : Ljava/lang/String;
    //   998: getstatic burp/Zzs9.ZO : Ljava/lang/Object;
    //   1001: checkcast java/math/BigInteger
    //   1004: invokevirtual intValue : ()I
    //   1007: bipush #32
    //   1009: irem
    //   1010: invokestatic abs : (I)I
    //   1013: invokevirtual charAt : (I)C
    //   1016: invokevirtual append : (C)Ljava/lang/StringBuilder;
    //   1019: pop
    //   1020: iload_2
    //   1021: ifne -> 1360
    //   1024: goto -> 1031
    //   1027: invokestatic a : (Ljava/lang/Throwable;)Ljava/lang/Throwable;
    //   1030: athrow
    //   1031: aload_3
    //   1032: getstatic burp/Ztgj.Zw : Ljava/lang/String;
    //   1035: getstatic burp/Zec0.Zg : Ljava/lang/Object;
    //   1038: checkcast java/math/BigInteger
    //   1041: invokevirtual intValue : ()I
    //   1044: bipush #32
    //   1046: irem
    //   1047: invokestatic abs : (I)I
    //   1050: invokevirtual charAt : (I)C
    //   1053: invokevirtual append : (C)Ljava/lang/StringBuilder;
    //   1056: pop
    //   1057: iload_2
    //   1058: ifne -> 1360
    //   1061: goto -> 1068
    //   1064: invokestatic a : (Ljava/lang/Throwable;)Ljava/lang/Throwable;
    //   1067: athrow
    //   1068: aload_3
    //   1069: getstatic burp/Zxtn.Zu : Ljava/lang/String;
    //   1072: getstatic burp/Zgz1.ZX : Ljava/lang/Object;
    //   1075: checkcast java/math/BigInteger
    //   1078: invokevirtual intValue : ()I
    //   1081: bipush #32
    //   1083: irem
    //   1084: invokestatic abs : (I)I
    //   1087: invokevirtual charAt : (I)C
    //   1090: invokevirtual append : (C)Ljava/lang/StringBuilder;
    //   1093: pop
    //   1094: iload_2
    //   1095: ifne -> 1360
    //   1098: goto -> 1105
    //   1101: invokestatic a : (Ljava/lang/Throwable;)Ljava/lang/Throwable;
    //   1104: athrow
    //   1105: aload_3
    //   1106: getstatic burp/Ztdt.Zk : Ljava/lang/String;
    //   1109: getstatic burp/Zlem.ZI : Ljava/lang/Object;
    //   1112: checkcast java/math/BigInteger
    //   1115: invokevirtual intValue : ()I
    //   1118: bipush #32
    //   1120: irem
    //   1121: invokestatic abs : (I)I
    //   1124: invokevirtual charAt : (I)C
    //   1127: invokevirtual append : (C)Ljava/lang/StringBuilder;
    //   1130: pop
    //   1131: iload_2
    //   1132: ifne -> 1360
    //   1135: goto -> 1142
    //   1138: invokestatic a : (Ljava/lang/Throwable;)Ljava/lang/Throwable;
    //   1141: athrow
    //   1142: aload_3
    //   1143: getstatic burp/Zx4k.ZC : Ljava/lang/String;
    //   1146: getstatic burp/Zmdm.ZZ : Ljava/lang/Object;
    //   1149: checkcast java/math/BigInteger
    //   1152: invokevirtual intValue : ()I
    //   1155: bipush #32
    //   1157: irem
    //   1158: invokestatic abs : (I)I
    //   1161: invokevirtual charAt : (I)C
    //   1164: invokevirtual append : (C)Ljava/lang/StringBuilder;
    //   1167: pop
    //   1168: iload_2
    //   1169: ifne -> 1360
    //   1172: goto -> 1179
    //   1175: invokestatic a : (Ljava/lang/Throwable;)Ljava/lang/Throwable;
    //   1178: athrow
    //   1179: aload_3
    //   1180: getstatic burp/Zlhy.ZS : Ljava/lang/String;
    //   1183: getstatic burp/Zzmo.ZI : Ljava/lang/Object;
    //   1186: checkcast java/math/BigInteger
    //   1189: invokevirtual intValue : ()I
    //   1192: bipush #32
    //   1194: irem
    //   1195: invokestatic abs : (I)I
    //   1198: invokevirtual charAt : (I)C
    //   1201: invokevirtual append : (C)Ljava/lang/StringBuilder;
    //   1204: pop
    //   1205: iload_2
    //   1206: ifne -> 1360
    //   1209: goto -> 1216
    //   1212: invokestatic a : (Ljava/lang/Throwable;)Ljava/lang/Throwable;
    //   1215: athrow
    //   1216: aload_3
    //   1217: getstatic burp/Zbsr.Zq : Ljava/lang/String;
    //   1220: getstatic burp/Ztev.Zr : Ljava/lang/Object;
    //   1223: checkcast java/math/BigInteger
    //   1226: invokevirtual intValue : ()I
    //   1229: bipush #32
    //   1231: irem
    //   1232: invokestatic abs : (I)I
    //   1235: invokevirtual charAt : (I)C
    //   1238: invokevirtual append : (C)Ljava/lang/StringBuilder;
    //   1241: pop
    //   1242: iload_2
    //   1243: ifne -> 1360
    //   1246: goto -> 1253
    //   1249: invokestatic a : (Ljava/lang/Throwable;)Ljava/lang/Throwable;
    //   1252: athrow
    //   1253: aload_3
    //   1254: getstatic burp/Zb_u.ZK : Ljava/lang/String;
    //   1257: getstatic burp/Zsji.Zg : Ljava/lang/Object;
    //   1260: checkcast java/math/BigInteger
    //   1263: invokevirtual intValue : ()I
    //   1266: bipush #32
    //   1268: irem
    //   1269: invokestatic abs : (I)I
    //   1272: invokevirtual charAt : (I)C
    //   1275: invokevirtual append : (C)Ljava/lang/StringBuilder;
    //   1278: pop
    //   1279: iload_2
    //   1280: ifne -> 1360
    //   1283: goto -> 1290
    //   1286: invokestatic a : (Ljava/lang/Throwable;)Ljava/lang/Throwable;
    //   1289: athrow
    //   1290: aload_3
    //   1291: getstatic burp/Zg3m.Za : Ljava/lang/String;
    //   1294: getstatic burp/Zeju.Zk : Ljava/lang/Object;
    //   1297: checkcast java/math/BigInteger
    //   1300: invokevirtual intValue : ()I
    //   1303: bipush #32
    //   1305: irem
    //   1306: invokestatic abs : (I)I
    //   1309: invokevirtual charAt : (I)C
    //   1312: invokevirtual append : (C)Ljava/lang/StringBuilder;
    //   1315: pop
    //   1316: iload_2
    //   1317: ifne -> 1360
    //   1320: goto -> 1327
    //   1323: invokestatic a : (Ljava/lang/Throwable;)Ljava/lang/Throwable;
    //   1326: athrow
    //   1327: aload_3
    //   1328: getstatic burp/Zd1.ZN : Ljava/lang/String;
    //   1331: getstatic burp/Zm84.Zf : Ljava/lang/Object;
    //   1334: checkcast java/math/BigInteger
    //   1337: invokevirtual intValue : ()I
    //   1340: bipush #32
    //   1342: irem
    //   1343: invokestatic abs : (I)I
    //   1346: invokevirtual charAt : (I)C
    //   1349: invokevirtual append : (C)Ljava/lang/StringBuilder;
    //   1352: pop
    //   1353: goto -> 1360
    //   1356: invokestatic a : (Ljava/lang/Throwable;)Ljava/lang/Throwable;
    //   1359: athrow
    //   1360: iinc #4, 1
    //   1363: iload_2
    //   1364: ifne -> 30
    //   1367: aload_3
    //   1368: invokevirtual toString : ()Ljava/lang/String;
    //   1371: putstatic burp/Zep8.ZC : Ljava/lang/String;
    //   1374: getstatic burp/Zsjo.ZB : Ljava/lang/Object;
    //   1377: checkcast java/math/BigInteger
    //   1380: invokevirtual toByteArray : ()[B
    //   1383: astore #4
    //   1385: new java/lang/StringBuilder
    //   1388: dup
    //   1389: invokespecial <init> : ()V
    //   1392: astore #6
    //   1394: aload #6
    //   1396: sipush #-13217
    //   1399: sipush #5319
    //   1402: invokestatic a : (II)Ljava/lang/String;
    //   1405: invokevirtual append : (Ljava/lang/String;)Ljava/lang/StringBuilder;
    //   1408: pop
    //   1409: aload #4
    //   1411: astore #7
    //   1413: aload #7
    //   1415: arraylength
    //   1416: istore #8
    //   1418: iconst_0
    //   1419: istore #9
    //   1421: iload #9
    //   1423: iload #8
    //   1425: if_icmpge -> 1451
    //   1428: aload #7
    //   1430: iload #9
    //   1432: baload
    //   1433: istore #10
    //   1435: aload #6
    //   1437: iload #10
    //   1439: i2c
    //   1440: invokevirtual append : (C)Ljava/lang/StringBuilder;
    //   1443: pop
    //   1444: iinc #9, 1
    //   1447: iload_2
    //   1448: ifne -> 1421
    //   1451: aload #6
    //   1453: sipush #-13232
    //   1456: sipush #-30987
    //   1459: invokestatic a : (II)Ljava/lang/String;
    //   1462: ldc ''
    //   1464: invokestatic getProperty : (Ljava/lang/String;Ljava/lang/String;)Ljava/lang/String;
    //   1467: invokevirtual toLowerCase : ()Ljava/lang/String;
    //   1470: invokevirtual append : (Ljava/lang/String;)Ljava/lang/StringBuilder;
    //   1473: pop
    //   1474: aload #6
    //   1476: sipush #-13226
    //   1479: sipush #-6669
    //   1482: invokestatic a : (II)Ljava/lang/String;
    //   1485: ldc ''
    //   1487: invokestatic getProperty : (Ljava/lang/String;Ljava/lang/String;)Ljava/lang/String;
    //   1490: invokevirtual toLowerCase : ()Ljava/lang/String;
    //   1493: invokevirtual append : (Ljava/lang/String;)Ljava/lang/StringBuilder;
    //   1496: pop
    //   1497: aload #6
    //   1499: invokevirtual toString : ()Ljava/lang/String;
    //   1502: invokevirtual getBytes : ()[B
    //   1505: astore #5
    //   1507: aload #5
    //   1509: astore #4
    //   1511: aload #4
    //   1513: arraylength
    //   1514: bipush #8
    //   1516: iadd
    //   1517: bipush #6
    //   1519: ishr
    //   1520: iconst_1
    //   1521: iadd
    //   1522: bipush #16
    //   1524: imul
    //   1525: newarray int
    //   1527: astore #6
    //   1529: iconst_0
    //   1530: istore #7
    //   1532: iload #7
    //   1534: aload #4
    //   1536: arraylength
    //   1537: if_icmpge -> 1581
    //   1540: aload #4
    //   1542: iload #7
    //   1544: baload
    //   1545: sipush #255
    //   1548: iand
    //   1549: istore #8
    //   1551: aload #6
    //   1553: iload #7
    //   1555: iconst_2
    //   1556: ishr
    //   1557: dup2
    //   1558: iaload
    //   1559: iload #8
    //   1561: bipush #24
    //   1563: iload #7
    //   1565: iconst_4
    //   1566: irem
    //   1567: bipush #8
    //   1569: imul
    //   1570: isub
    //   1571: ishl
    //   1572: ior
    //   1573: iastore
    //   1574: iinc #7, 1
    //   1577: iload_2
    //   1578: ifne -> 1532
    //   1581: aload #6
    //   1583: iload #7
    //   1585: iconst_2
    //   1586: ishr
    //   1587: dup2
    //   1588: iaload
    //   1589: sipush #128
    //   1592: bipush #24
    //   1594: iload #7
    //   1596: iconst_4
    //   1597: irem
    //   1598: bipush #8
    //   1600: imul
    //   1601: isub
    //   1602: ishl
    //   1603: ior
    //   1604: iastore
    //   1605: aload #6
    //   1607: aload #6
    //   1609: arraylength
    //   1610: iconst_1
    //   1611: isub
    //   1612: aload #4
    //   1614: arraylength
    //   1615: bipush #8
    //   1617: imul
    //   1618: iastore
    //   1619: bipush #80
    //   1621: newarray int
    //   1623: astore #8
    //   1625: ldc 1732584193
    //   1627: istore #9
    //   1629: ldc -271733879
    //   1631: istore #10
    //   1633: ldc -1732584194
    //   1635: istore #11
    //   1637: ldc 271733878
    //   1639: istore #12
    //   1641: ldc -1009589776
    //   1643: istore #13
    //   1645: iconst_0
    //   1646: istore #7
    //   1648: iload #7
    //   1650: aload #6
    //   1652: arraylength
    //   1653: if_icmpge -> 1975
    //   1656: iload #9
    //   1658: istore #14
    //   1660: iload #10
    //   1662: istore #15
    //   1664: iload #11
    //   1666: istore #16
    //   1668: iload #12
    //   1670: istore #17
    //   1672: iload #13
    //   1674: istore #18
    //   1676: iconst_0
    //   1677: istore #19
    //   1679: iload #19
    //   1681: bipush #80
    //   1683: if_icmpge -> 1933
    //   1686: iload #19
    //   1688: bipush #16
    //   1690: if_icmpge -> 1717
    //   1693: aload #8
    //   1695: iload #19
    //   1697: aload #6
    //   1699: iload #7
    //   1701: iload #19
    //   1703: iadd
    //   1704: iaload
    //   1705: iastore
    //   1706: iload_2
    //   1707: ifne -> 1772
    //   1710: goto -> 1717
    //   1713: invokestatic a : (Ljava/lang/Throwable;)Ljava/lang/Throwable;
    //   1716: athrow
    //   1717: aload #8
    //   1719: iload #19
    //   1721: iconst_3
    //   1722: isub
    //   1723: iaload
    //   1724: aload #8
    //   1726: iload #19
    //   1728: bipush #8
    //   1730: isub
    //   1731: iaload
    //   1732: ixor
    //   1733: aload #8
    //   1735: iload #19
    //   1737: bipush #14
    //   1739: isub
    //   1740: iaload
    //   1741: ixor
    //   1742: aload #8
    //   1744: iload #19
    //   1746: bipush #16
    //   1748: isub
    //   1749: iaload
    //   1750: ixor
    //   1751: istore #20
    //   1753: iload #20
    //   1755: iconst_1
    //   1756: ishl
    //   1757: iload #20
    //   1759: bipush #31
    //   1761: iushr
    //   1762: ior
    //   1763: istore #21
    //   1765: aload #8
    //   1767: iload #19
    //   1769: iload #21
    //   1771: iastore
    //   1772: iload #9
    //   1774: iconst_5
    //   1775: ishl
    //   1776: iload #9
    //   1778: bipush #27
    //   1780: iushr
    //   1781: ior
    //   1782: istore #20
    //   1784: iload #20
    //   1786: iload #13
    //   1788: iadd
    //   1789: aload #8
    //   1791: iload #19
    //   1793: iaload
    //   1794: iadd
    //   1795: iload #19
    //   1797: bipush #20
    //   1799: if_icmpge -> 1825
    //   1802: ldc 1518500249
    //   1804: iload #10
    //   1806: iload #11
    //   1808: iand
    //   1809: iload #10
    //   1811: iconst_m1
    //   1812: ixor
    //   1813: iload #12
    //   1815: iand
    //   1816: ior
    //   1817: iadd
    //   1818: goto -> 1895
    //   1821: invokestatic a : (Ljava/lang/Throwable;)Ljava/lang/Throwable;
    //   1824: athrow
    //   1825: iload #19
    //   1827: bipush #40
    //   1829: if_icmpge -> 1850
    //   1832: ldc 1859775393
    //   1834: iload #10
    //   1836: iload #11
    //   1838: ixor
    //   1839: iload #12
    //   1841: ixor
    //   1842: iadd
    //   1843: goto -> 1895
    //   1846: invokestatic a : (Ljava/lang/Throwable;)Ljava/lang/Throwable;
    //   1849: athrow
    //   1850: iload #19
    //   1852: bipush #60
    //   1854: if_icmpge -> 1884
    //   1857: ldc -1894007588
    //   1859: iload #10
    //   1861: iload #11
    //   1863: iand
    //   1864: iload #10
    //   1866: iload #12
    //   1868: iand
    //   1869: ior
    //   1870: iload #11
    //   1872: iload #12
    //   1874: iand
    //   1875: ior
    //   1876: iadd
    //   1877: goto -> 1895
    //   1880: invokestatic a : (Ljava/lang/Throwable;)Ljava/lang/Throwable;
    //   1883: athrow
    //   1884: ldc -899497514
    //   1886: iload #10
    //   1888: iload #11
    //   1890: ixor
    //   1891: iload #12
    //   1893: ixor
    //   1894: iadd
    //   1895: iadd
    //   1896: istore #21
    //   1898: iload #12
    //   1900: istore #13
    //   1902: iload #11
    //   1904: istore #12
    //   1906: iload #10
    //   1908: bipush #30
    //   1910: ishl
    //   1911: iload #10
    //   1913: iconst_2
    //   1914: iushr
    //   1915: ior
    //   1916: istore #11
    //   1918: iload #9
    //   1920: istore #10
    //   1922: iload #21
    //   1924: istore #9
    //   1926: iinc #19, 1
    //   1929: iload_2
    //   1930: ifne -> 1679
    //   1933: iload #9
    //   1935: iload #14
    //   1937: iadd
    //   1938: istore #9
    //   1940: iload #10
    //   1942: iload #15
    //   1944: iadd
    //   1945: istore #10
    //   1947: iload #11
    //   1949: iload #16
    //   1951: iadd
    //   1952: istore #11
    //   1954: iload #12
    //   1956: iload #17
    //   1958: iadd
    //   1959: istore #12
    //   1961: iload #13
    //   1963: iload #18
    //   1965: iadd
    //   1966: istore #13
    //   1968: iinc #7, 16
    //   1971: iload_2
    //   1972: ifne -> 1648
    //   1975: iconst_5
    //   1976: newarray int
    //   1978: dup
    //   1979: iconst_0
    //   1980: iload #9
    //   1982: iastore
    //   1983: dup
    //   1984: iconst_1
    //   1985: iload #10
    //   1987: iastore
    //   1988: dup
    //   1989: iconst_2
    //   1990: iload #11
    //   1992: iastore
    //   1993: dup
    //   1994: iconst_3
    //   1995: iload #12
    //   1997: iastore
    //   1998: dup
    //   1999: iconst_4
    //   2000: iload #13
    //   2002: iastore
    //   2003: astore #14
    //   2005: bipush #20
    //   2007: newarray byte
    //   2009: astore #15
    //   2011: iconst_0
    //   2012: istore #16
    //   2014: iload #16
    //   2016: bipush #20
    //   2018: if_icmpge -> 2059
    //   2021: aload #14
    //   2023: iload #16
    //   2025: iconst_4
    //   2026: idiv
    //   2027: iaload
    //   2028: istore #17
    //   2030: iconst_3
    //   2031: iload #16
    //   2033: iconst_4
    //   2034: irem
    //   2035: isub
    //   2036: bipush #8
    //   2038: imul
    //   2039: istore #18
    //   2041: aload #15
    //   2043: iload #16
    //   2045: iload #17
    //   2047: iload #18
    //   2049: iushr
    //   2050: i2b
    //   2051: bastore
    //   2052: iinc #16, 1
    //   2055: iload_2
    //   2056: ifne -> 2014
    //   2059: aload #15
    //   2061: astore #5
    //   2063: getstatic burp/Zva.Zu : Ljava/lang/Object;
    //   2066: checkcast java/math/BigInteger
    //   2069: invokevirtual toByteArray : ()[B
    //   2072: astore #4
    //   2074: bipush #32
    //   2076: newarray int
    //   2078: dup
    //   2079: iconst_0
    //   2080: ldc 943331329
    //   2082: iastore
    //   2083: dup
    //   2084: iconst_1
    //   2085: ldc 170788368
    //   2087: iastore
    //   2088: dup
    //   2089: iconst_2
    //   2090: ldc 1008414755
    //   2092: iastore
    //   2093: dup
    //   2094: iconst_3
    //   2095: ldc 187049985
    //   2097: iastore
    //   2098: dup
    //   2099: iconst_4
    //   2100: ldc 1010368540
    //   2102: iastore
    //   2103: dup
    //   2104: iconst_5
    //   2105: ldc 220604441
    //   2107: iastore
    //   2108: dup
    //   2109: bipush #6
    //   2111: ldc 940377620
    //   2113: iastore
    //   2114: dup
    //   2115: bipush #7
    //   2117: ldc 255209728
    //   2119: iastore
    //   2120: dup
    //   2121: bipush #8
    //   2123: ldc 689771012
    //   2125: iastore
    //   2126: dup
    //   2127: bipush #9
    //   2129: ldc 221709344
    //   2131: iastore
    //   2132: dup
    //   2133: bipush #10
    //   2135: ldc 957157408
    //   2137: iastore
    //   2138: dup
    //   2139: bipush #11
    //   2141: ldc 892536332
    //   2143: iastore
    //   2144: dup
    //   2145: bipush #12
    //   2147: ldc 722417666
    //   2149: iastore
    //   2150: dup
    //   2151: bipush #13
    //   2153: ldc 1026621720
    //   2155: iastore
    //   2156: dup
    //   2157: bipush #14
    //   2159: ldc 655302664
    //   2161: iastore
    //   2162: dup
    //   2163: bipush #15
    //   2165: ldc 890966315
    //   2167: iastore
    //   2168: dup
    //   2169: bipush #16
    //   2171: ldc 187632156
    //   2173: iastore
    //   2174: dup
    //   2175: bipush #17
    //   2177: ldc 874189824
    //   2179: iastore
    //   2180: dup
    //   2181: bipush #18
    //   2183: ldc 254150144
    //   2185: iastore
    //   2186: dup
    //   2187: bipush #19
    //   2189: ldc 924386310
    //   2191: iastore
    //   2192: dup
    //   2193: bipush #20
    //   2195: ldc 121057538
    //   2197: iastore
    //   2198: dup
    //   2199: bipush #21
    //   2201: ldc 840500228
    //   2203: iastore
    //   2204: dup
    //   2205: bipush #22
    //   2207: ldc 389160971
    //   2209: iastore
    //   2210: dup
    //   2211: bipush #23
    //   2213: ldc 907870729
    //   2215: iastore
    //   2216: dup
    //   2217: bipush #24
    //   2219: ldc 389426184
    //   2221: iastore
    //   2222: dup
    //   2223: bipush #25
    //   2225: ldc 973875457
    //   2227: iastore
    //   2228: dup
    //   2229: bipush #26
    //   2231: ldc 372376604
    //   2233: iastore
    //   2234: dup
    //   2235: bipush #27
    //   2237: ldc 707731490
    //   2239: iastore
    //   2240: dup
    //   2241: bipush #28
    //   2243: ldc 1043334948
    //   2245: iastore
    //   2246: dup
    //   2247: bipush #29
    //   2249: ldc 439222784
    //   2251: iastore
    //   2252: dup
    //   2253: bipush #30
    //   2255: ldc 876216579
    //   2257: iastore
    //   2258: dup
    //   2259: bipush #31
    //   2261: ldc 455999525
    //   2263: iastore
    //   2264: astore #6
    //   2266: bipush #8
    //   2268: aload #4
    //   2270: arraylength
    //   2271: bipush #8
    //   2273: irem
    //   2274: isub
    //   2275: istore #7
    //   2277: aload #4
    //   2279: arraylength
    //   2280: iload #7
    //   2282: iadd
    //   2283: newarray byte
    //   2285: astore #8
    //   2287: iconst_0
    //   2288: istore #9
    //   2290: iload #9
    //   2292: aload #4
    //   2294: arraylength
    //   2295: if_icmpge -> 2315
    //   2298: aload #8
    //   2300: iload #9
    //   2302: aload #4
    //   2304: iload #9
    //   2306: baload
    //   2307: bastore
    //   2308: iinc #9, 1
    //   2311: iload_2
    //   2312: ifne -> 2290
    //   2315: aload #4
    //   2317: arraylength
    //   2318: istore #9
    //   2320: iload #9
    //   2322: aload #8
    //   2324: arraylength
    //   2325: if_icmpge -> 2343
    //   2328: aload #8
    //   2330: iload #9
    //   2332: iload #7
    //   2334: i2b
    //   2335: bastore
    //   2336: iinc #9, 1
    //   2339: iload_2
    //   2340: ifne -> 2320
    //   2343: aload #8
    //   2345: astore #4
    //   2347: bipush #64
    //   2349: newarray int
    //   2351: dup
    //   2352: iconst_0
    //   2353: ldc 16843776
    //   2355: iastore
    //   2356: dup
    //   2357: iconst_1
    //   2358: iconst_0
    //   2359: iastore
    //   2360: dup
    //   2361: iconst_2
    //   2362: ldc 65536
    //   2364: iastore
    //   2365: dup
    //   2366: iconst_3
    //   2367: ldc 16843780
    //   2369: iastore
    //   2370: dup
    //   2371: iconst_4
    //   2372: ldc 16842756
    //   2374: iastore
    //   2375: dup
    //   2376: iconst_5
    //   2377: ldc 66564
    //   2379: iastore
    //   2380: dup
    //   2381: bipush #6
    //   2383: iconst_4
    //   2384: iastore
    //   2385: dup
    //   2386: bipush #7
    //   2388: ldc 65536
    //   2390: iastore
    //   2391: dup
    //   2392: bipush #8
    //   2394: sipush #1024
    //   2397: iastore
    //   2398: dup
    //   2399: bipush #9
    //   2401: ldc 16843776
    //   2403: iastore
    //   2404: dup
    //   2405: bipush #10
    //   2407: ldc 16843780
    //   2409: iastore
    //   2410: dup
    //   2411: bipush #11
    //   2413: sipush #1024
    //   2416: iastore
    //   2417: dup
    //   2418: bipush #12
    //   2420: ldc 16778244
    //   2422: iastore
    //   2423: dup
    //   2424: bipush #13
    //   2426: ldc 16842756
    //   2428: iastore
    //   2429: dup
    //   2430: bipush #14
    //   2432: ldc 16777216
    //   2434: iastore
    //   2435: dup
    //   2436: bipush #15
    //   2438: iconst_4
    //   2439: iastore
    //   2440: dup
    //   2441: bipush #16
    //   2443: sipush #1028
    //   2446: iastore
    //   2447: dup
    //   2448: bipush #17
    //   2450: ldc 16778240
    //   2452: iastore
    //   2453: dup
    //   2454: bipush #18
    //   2456: ldc 16778240
    //   2458: iastore
    //   2459: dup
    //   2460: bipush #19
    //   2462: ldc 66560
    //   2464: iastore
    //   2465: dup
    //   2466: bipush #20
    //   2468: ldc 66560
    //   2470: iastore
    //   2471: dup
    //   2472: bipush #21
    //   2474: ldc 16842752
    //   2476: iastore
    //   2477: dup
    //   2478: bipush #22
    //   2480: ldc 16842752
    //   2482: iastore
    //   2483: dup
    //   2484: bipush #23
    //   2486: ldc 16778244
    //   2488: iastore
    //   2489: dup
    //   2490: bipush #24
    //   2492: ldc 65540
    //   2494: iastore
    //   2495: dup
    //   2496: bipush #25
    //   2498: ldc 16777220
    //   2500: iastore
    //   2501: dup
    //   2502: bipush #26
    //   2504: ldc 16777220
    //   2506: iastore
    //   2507: dup
    //   2508: bipush #27
    //   2510: ldc 65540
    //   2512: iastore
    //   2513: dup
    //   2514: bipush #28
    //   2516: iconst_0
    //   2517: iastore
    //   2518: dup
    //   2519: bipush #29
    //   2521: sipush #1028
    //   2524: iastore
    //   2525: dup
    //   2526: bipush #30
    //   2528: ldc 66564
    //   2530: iastore
    //   2531: dup
    //   2532: bipush #31
    //   2534: ldc 16777216
    //   2536: iastore
    //   2537: dup
    //   2538: bipush #32
    //   2540: ldc 65536
    //   2542: iastore
    //   2543: dup
    //   2544: bipush #33
    //   2546: ldc 16843780
    //   2548: iastore
    //   2549: dup
    //   2550: bipush #34
    //   2552: iconst_4
    //   2553: iastore
    //   2554: dup
    //   2555: bipush #35
    //   2557: ldc 16842752
    //   2559: iastore
    //   2560: dup
    //   2561: bipush #36
    //   2563: ldc 16843776
    //   2565: iastore
    //   2566: dup
    //   2567: bipush #37
    //   2569: ldc 16777216
    //   2571: iastore
    //   2572: dup
    //   2573: bipush #38
    //   2575: ldc 16777216
    //   2577: iastore
    //   2578: dup
    //   2579: bipush #39
    //   2581: sipush #1024
    //   2584: iastore
    //   2585: dup
    //   2586: bipush #40
    //   2588: ldc 16842756
    //   2590: iastore
    //   2591: dup
    //   2592: bipush #41
    //   2594: ldc 65536
    //   2596: iastore
    //   2597: dup
    //   2598: bipush #42
    //   2600: ldc 66560
    //   2602: iastore
    //   2603: dup
    //   2604: bipush #43
    //   2606: ldc 16777220
    //   2608: iastore
    //   2609: dup
    //   2610: bipush #44
    //   2612: sipush #1024
    //   2615: iastore
    //   2616: dup
    //   2617: bipush #45
    //   2619: iconst_4
    //   2620: iastore
    //   2621: dup
    //   2622: bipush #46
    //   2624: ldc 16778244
    //   2626: iastore
    //   2627: dup
    //   2628: bipush #47
    //   2630: ldc 66564
    //   2632: iastore
    //   2633: dup
    //   2634: bipush #48
    //   2636: ldc 16843780
    //   2638: iastore
    //   2639: dup
    //   2640: bipush #49
    //   2642: ldc 65540
    //   2644: iastore
    //   2645: dup
    //   2646: bipush #50
    //   2648: ldc 16842752
    //   2650: iastore
    //   2651: dup
    //   2652: bipush #51
    //   2654: ldc 16778244
    //   2656: iastore
    //   2657: dup
    //   2658: bipush #52
    //   2660: ldc 16777220
    //   2662: iastore
    //   2663: dup
    //   2664: bipush #53
    //   2666: sipush #1028
    //   2669: iastore
    //   2670: dup
    //   2671: bipush #54
    //   2673: ldc 66564
    //   2675: iastore
    //   2676: dup
    //   2677: bipush #55
    //   2679: ldc 16843776
    //   2681: iastore
    //   2682: dup
    //   2683: bipush #56
    //   2685: sipush #1028
    //   2688: iastore
    //   2689: dup
    //   2690: bipush #57
    //   2692: ldc 16778240
    //   2694: iastore
    //   2695: dup
    //   2696: bipush #58
    //   2698: ldc 16778240
    //   2700: iastore
    //   2701: dup
    //   2702: bipush #59
    //   2704: iconst_0
    //   2705: iastore
    //   2706: dup
    //   2707: bipush #60
    //   2709: ldc 65540
    //   2711: iastore
    //   2712: dup
    //   2713: bipush #61
    //   2715: ldc 66560
    //   2717: iastore
    //   2718: dup
    //   2719: bipush #62
    //   2721: iconst_0
    //   2722: iastore
    //   2723: dup
    //   2724: bipush #63
    //   2726: ldc 16842756
    //   2728: iastore
    //   2729: astore #9
    //   2731: bipush #64
    //   2733: newarray int
    //   2735: dup
    //   2736: iconst_0
    //   2737: ldc -2146402272
    //   2739: iastore
    //   2740: dup
    //   2741: iconst_1
    //   2742: ldc -2147450880
    //   2744: iastore
    //   2745: dup
    //   2746: iconst_2
    //   2747: ldc 32768
    //   2749: iastore
    //   2750: dup
    //   2751: iconst_3
    //   2752: ldc 1081376
    //   2754: iastore
    //   2755: dup
    //   2756: iconst_4
    //   2757: ldc 1048576
    //   2759: iastore
    //   2760: dup
    //   2761: iconst_5
    //   2762: bipush #32
    //   2764: iastore
    //   2765: dup
    //   2766: bipush #6
    //   2768: ldc -2146435040
    //   2770: iastore
    //   2771: dup
    //   2772: bipush #7
    //   2774: ldc -2147450848
    //   2776: iastore
    //   2777: dup
    //   2778: bipush #8
    //   2780: ldc -2147483616
    //   2782: iastore
    //   2783: dup
    //   2784: bipush #9
    //   2786: ldc -2146402272
    //   2788: iastore
    //   2789: dup
    //   2790: bipush #10
    //   2792: ldc -2146402304
    //   2794: iastore
    //   2795: dup
    //   2796: bipush #11
    //   2798: ldc -2147483648
    //   2800: iastore
    //   2801: dup
    //   2802: bipush #12
    //   2804: ldc -2147450880
    //   2806: iastore
    //   2807: dup
    //   2808: bipush #13
    //   2810: ldc 1048576
    //   2812: iastore
    //   2813: dup
    //   2814: bipush #14
    //   2816: bipush #32
    //   2818: iastore
    //   2819: dup
    //   2820: bipush #15
    //   2822: ldc -2146435040
    //   2824: iastore
    //   2825: dup
    //   2826: bipush #16
    //   2828: ldc 1081344
    //   2830: iastore
    //   2831: dup
    //   2832: bipush #17
    //   2834: ldc 1048608
    //   2836: iastore
    //   2837: dup
    //   2838: bipush #18
    //   2840: ldc -2147450848
    //   2842: iastore
    //   2843: dup
    //   2844: bipush #19
    //   2846: iconst_0
    //   2847: iastore
    //   2848: dup
    //   2849: bipush #20
    //   2851: ldc -2147483648
    //   2853: iastore
    //   2854: dup
    //   2855: bipush #21
    //   2857: ldc 32768
    //   2859: iastore
    //   2860: dup
    //   2861: bipush #22
    //   2863: ldc 1081376
    //   2865: iastore
    //   2866: dup
    //   2867: bipush #23
    //   2869: ldc -2146435072
    //   2871: iastore
    //   2872: dup
    //   2873: bipush #24
    //   2875: ldc 1048608
    //   2877: iastore
    //   2878: dup
    //   2879: bipush #25
    //   2881: ldc -2147483616
    //   2883: iastore
    //   2884: dup
    //   2885: bipush #26
    //   2887: iconst_0
    //   2888: iastore
    //   2889: dup
    //   2890: bipush #27
    //   2892: ldc 1081344
    //   2894: iastore
    //   2895: dup
    //   2896: bipush #28
    //   2898: ldc 32800
    //   2900: iastore
    //   2901: dup
    //   2902: bipush #29
    //   2904: ldc -2146402304
    //   2906: iastore
    //   2907: dup
    //   2908: bipush #30
    //   2910: ldc -2146435072
    //   2912: iastore
    //   2913: dup
    //   2914: bipush #31
    //   2916: ldc 32800
    //   2918: iastore
    //   2919: dup
    //   2920: bipush #32
    //   2922: iconst_0
    //   2923: iastore
    //   2924: dup
    //   2925: bipush #33
    //   2927: ldc 1081376
    //   2929: iastore
    //   2930: dup
    //   2931: bipush #34
    //   2933: ldc -2146435040
    //   2935: iastore
    //   2936: dup
    //   2937: bipush #35
    //   2939: ldc 1048576
    //   2941: iastore
    //   2942: dup
    //   2943: bipush #36
    //   2945: ldc -2147450848
    //   2947: iastore
    //   2948: dup
    //   2949: bipush #37
    //   2951: ldc -2146435072
    //   2953: iastore
    //   2954: dup
    //   2955: bipush #38
    //   2957: ldc -2146402304
    //   2959: iastore
    //   2960: dup
    //   2961: bipush #39
    //   2963: ldc 32768
    //   2965: iastore
    //   2966: dup
    //   2967: bipush #40
    //   2969: ldc -2146435072
    //   2971: iastore
    //   2972: dup
    //   2973: bipush #41
    //   2975: ldc -2147450880
    //   2977: iastore
    //   2978: dup
    //   2979: bipush #42
    //   2981: bipush #32
    //   2983: iastore
    //   2984: dup
    //   2985: bipush #43
    //   2987: ldc -2146402272
    //   2989: iastore
    //   2990: dup
    //   2991: bipush #44
    //   2993: ldc 1081376
    //   2995: iastore
    //   2996: dup
    //   2997: bipush #45
    //   2999: bipush #32
    //   3001: iastore
    //   3002: dup
    //   3003: bipush #46
    //   3005: ldc 32768
    //   3007: iastore
    //   3008: dup
    //   3009: bipush #47
    //   3011: ldc -2147483648
    //   3013: iastore
    //   3014: dup
    //   3015: bipush #48
    //   3017: ldc 32800
    //   3019: iastore
    //   3020: dup
    //   3021: bipush #49
    //   3023: ldc -2146402304
    //   3025: iastore
    //   3026: dup
    //   3027: bipush #50
    //   3029: ldc 1048576
    //   3031: iastore
    //   3032: dup
    //   3033: bipush #51
    //   3035: ldc -2147483616
    //   3037: iastore
    //   3038: dup
    //   3039: bipush #52
    //   3041: ldc 1048608
    //   3043: iastore
    //   3044: dup
    //   3045: bipush #53
    //   3047: ldc -2147450848
    //   3049: iastore
    //   3050: dup
    //   3051: bipush #54
    //   3053: ldc -2147483616
    //   3055: iastore
    //   3056: dup
    //   3057: bipush #55
    //   3059: ldc 1048608
    //   3061: iastore
    //   3062: dup
    //   3063: bipush #56
    //   3065: ldc 1081344
    //   3067: iastore
    //   3068: dup
    //   3069: bipush #57
    //   3071: iconst_0
    //   3072: iastore
    //   3073: dup
    //   3074: bipush #58
    //   3076: ldc -2147450880
    //   3078: iastore
    //   3079: dup
    //   3080: bipush #59
    //   3082: ldc 32800
    //   3084: iastore
    //   3085: dup
    //   3086: bipush #60
    //   3088: ldc -2147483648
    //   3090: iastore
    //   3091: dup
    //   3092: bipush #61
    //   3094: ldc -2146435040
    //   3096: iastore
    //   3097: dup
    //   3098: bipush #62
    //   3100: ldc -2146402272
    //   3102: iastore
    //   3103: dup
    //   3104: bipush #63
    //   3106: ldc 1081344
    //   3108: iastore
    //   3109: astore #10
    //   3111: bipush #64
    //   3113: newarray int
    //   3115: dup
    //   3116: iconst_0
    //   3117: sipush #520
    //   3120: iastore
    //   3121: dup
    //   3122: iconst_1
    //   3123: ldc 134349312
    //   3125: iastore
    //   3126: dup
    //   3127: iconst_2
    //   3128: iconst_0
    //   3129: iastore
    //   3130: dup
    //   3131: iconst_3
    //   3132: ldc 134348808
    //   3134: iastore
    //   3135: dup
    //   3136: iconst_4
    //   3137: ldc 134218240
    //   3139: iastore
    //   3140: dup
    //   3141: iconst_5
    //   3142: iconst_0
    //   3143: iastore
    //   3144: dup
    //   3145: bipush #6
    //   3147: ldc 131592
    //   3149: iastore
    //   3150: dup
    //   3151: bipush #7
    //   3153: ldc 134218240
    //   3155: iastore
    //   3156: dup
    //   3157: bipush #8
    //   3159: ldc 131080
    //   3161: iastore
    //   3162: dup
    //   3163: bipush #9
    //   3165: ldc 134217736
    //   3167: iastore
    //   3168: dup
    //   3169: bipush #10
    //   3171: ldc 134217736
    //   3173: iastore
    //   3174: dup
    //   3175: bipush #11
    //   3177: ldc 131072
    //   3179: iastore
    //   3180: dup
    //   3181: bipush #12
    //   3183: ldc 134349320
    //   3185: iastore
    //   3186: dup
    //   3187: bipush #13
    //   3189: ldc 131080
    //   3191: iastore
    //   3192: dup
    //   3193: bipush #14
    //   3195: ldc 134348800
    //   3197: iastore
    //   3198: dup
    //   3199: bipush #15
    //   3201: sipush #520
    //   3204: iastore
    //   3205: dup
    //   3206: bipush #16
    //   3208: ldc 134217728
    //   3210: iastore
    //   3211: dup
    //   3212: bipush #17
    //   3214: bipush #8
    //   3216: iastore
    //   3217: dup
    //   3218: bipush #18
    //   3220: ldc 134349312
    //   3222: iastore
    //   3223: dup
    //   3224: bipush #19
    //   3226: sipush #512
    //   3229: iastore
    //   3230: dup
    //   3231: bipush #20
    //   3233: ldc 131584
    //   3235: iastore
    //   3236: dup
    //   3237: bipush #21
    //   3239: ldc 134348800
    //   3241: iastore
    //   3242: dup
    //   3243: bipush #22
    //   3245: ldc 134348808
    //   3247: iastore
    //   3248: dup
    //   3249: bipush #23
    //   3251: ldc 131592
    //   3253: iastore
    //   3254: dup
    //   3255: bipush #24
    //   3257: ldc 134218248
    //   3259: iastore
    //   3260: dup
    //   3261: bipush #25
    //   3263: ldc 131584
    //   3265: iastore
    //   3266: dup
    //   3267: bipush #26
    //   3269: ldc 131072
    //   3271: iastore
    //   3272: dup
    //   3273: bipush #27
    //   3275: ldc 134218248
    //   3277: iastore
    //   3278: dup
    //   3279: bipush #28
    //   3281: bipush #8
    //   3283: iastore
    //   3284: dup
    //   3285: bipush #29
    //   3287: ldc 134349320
    //   3289: iastore
    //   3290: dup
    //   3291: bipush #30
    //   3293: sipush #512
    //   3296: iastore
    //   3297: dup
    //   3298: bipush #31
    //   3300: ldc 134217728
    //   3302: iastore
    //   3303: dup
    //   3304: bipush #32
    //   3306: ldc 134349312
    //   3308: iastore
    //   3309: dup
    //   3310: bipush #33
    //   3312: ldc 134217728
    //   3314: iastore
    //   3315: dup
    //   3316: bipush #34
    //   3318: ldc 131080
    //   3320: iastore
    //   3321: dup
    //   3322: bipush #35
    //   3324: sipush #520
    //   3327: iastore
    //   3328: dup
    //   3329: bipush #36
    //   3331: ldc 131072
    //   3333: iastore
    //   3334: dup
    //   3335: bipush #37
    //   3337: ldc 134349312
    //   3339: iastore
    //   3340: dup
    //   3341: bipush #38
    //   3343: ldc 134218240
    //   3345: iastore
    //   3346: dup
    //   3347: bipush #39
    //   3349: iconst_0
    //   3350: iastore
    //   3351: dup
    //   3352: bipush #40
    //   3354: sipush #512
    //   3357: iastore
    //   3358: dup
    //   3359: bipush #41
    //   3361: ldc 131080
    //   3363: iastore
    //   3364: dup
    //   3365: bipush #42
    //   3367: ldc 134349320
    //   3369: iastore
    //   3370: dup
    //   3371: bipush #43
    //   3373: ldc 134218240
    //   3375: iastore
    //   3376: dup
    //   3377: bipush #44
    //   3379: ldc 134217736
    //   3381: iastore
    //   3382: dup
    //   3383: bipush #45
    //   3385: sipush #512
    //   3388: iastore
    //   3389: dup
    //   3390: bipush #46
    //   3392: iconst_0
    //   3393: iastore
    //   3394: dup
    //   3395: bipush #47
    //   3397: ldc 134348808
    //   3399: iastore
    //   3400: dup
    //   3401: bipush #48
    //   3403: ldc 134218248
    //   3405: iastore
    //   3406: dup
    //   3407: bipush #49
    //   3409: ldc 131072
    //   3411: iastore
    //   3412: dup
    //   3413: bipush #50
    //   3415: ldc 134217728
    //   3417: iastore
    //   3418: dup
    //   3419: bipush #51
    //   3421: ldc 134349320
    //   3423: iastore
    //   3424: dup
    //   3425: bipush #52
    //   3427: bipush #8
    //   3429: iastore
    //   3430: dup
    //   3431: bipush #53
    //   3433: ldc 131592
    //   3435: iastore
    //   3436: dup
    //   3437: bipush #54
    //   3439: ldc 131584
    //   3441: iastore
    //   3442: dup
    //   3443: bipush #55
    //   3445: ldc 134217736
    //   3447: iastore
    //   3448: dup
    //   3449: bipush #56
    //   3451: ldc 134348800
    //   3453: iastore
    //   3454: dup
    //   3455: bipush #57
    //   3457: ldc 134218248
    //   3459: iastore
    //   3460: dup
    //   3461: bipush #58
    //   3463: sipush #520
    //   3466: iastore
    //   3467: dup
    //   3468: bipush #59
    //   3470: ldc 134348800
    //   3472: iastore
    //   3473: dup
    //   3474: bipush #60
    //   3476: ldc 131592
    //   3478: iastore
    //   3479: dup
    //   3480: bipush #61
    //   3482: bipush #8
    //   3484: iastore
    //   3485: dup
    //   3486: bipush #62
    //   3488: ldc 134348808
    //   3490: iastore
    //   3491: dup
    //   3492: bipush #63
    //   3494: ldc 131584
    //   3496: iastore
    //   3497: astore #11
    //   3499: bipush #64
    //   3501: newarray int
    //   3503: dup
    //   3504: iconst_0
    //   3505: ldc 8396801
    //   3507: iastore
    //   3508: dup
    //   3509: iconst_1
    //   3510: sipush #8321
    //   3513: iastore
    //   3514: dup
    //   3515: iconst_2
    //   3516: sipush #8321
    //   3519: iastore
    //   3520: dup
    //   3521: iconst_3
    //   3522: sipush #128
    //   3525: iastore
    //   3526: dup
    //   3527: iconst_4
    //   3528: ldc 8396928
    //   3530: iastore
    //   3531: dup
    //   3532: iconst_5
    //   3533: ldc 8388737
    //   3535: iastore
    //   3536: dup
    //   3537: bipush #6
    //   3539: ldc 8388609
    //   3541: iastore
    //   3542: dup
    //   3543: bipush #7
    //   3545: sipush #8193
    //   3548: iastore
    //   3549: dup
    //   3550: bipush #8
    //   3552: iconst_0
    //   3553: iastore
    //   3554: dup
    //   3555: bipush #9
    //   3557: ldc 8396800
    //   3559: iastore
    //   3560: dup
    //   3561: bipush #10
    //   3563: ldc 8396800
    //   3565: iastore
    //   3566: dup
    //   3567: bipush #11
    //   3569: ldc 8396929
    //   3571: iastore
    //   3572: dup
    //   3573: bipush #12
    //   3575: sipush #129
    //   3578: iastore
    //   3579: dup
    //   3580: bipush #13
    //   3582: iconst_0
    //   3583: iastore
    //   3584: dup
    //   3585: bipush #14
    //   3587: ldc 8388736
    //   3589: iastore
    //   3590: dup
    //   3591: bipush #15
    //   3593: ldc 8388609
    //   3595: iastore
    //   3596: dup
    //   3597: bipush #16
    //   3599: iconst_1
    //   3600: iastore
    //   3601: dup
    //   3602: bipush #17
    //   3604: sipush #8192
    //   3607: iastore
    //   3608: dup
    //   3609: bipush #18
    //   3611: ldc 8388608
    //   3613: iastore
    //   3614: dup
    //   3615: bipush #19
    //   3617: ldc 8396801
    //   3619: iastore
    //   3620: dup
    //   3621: bipush #20
    //   3623: sipush #128
    //   3626: iastore
    //   3627: dup
    //   3628: bipush #21
    //   3630: ldc 8388608
    //   3632: iastore
    //   3633: dup
    //   3634: bipush #22
    //   3636: sipush #8193
    //   3639: iastore
    //   3640: dup
    //   3641: bipush #23
    //   3643: sipush #8320
    //   3646: iastore
    //   3647: dup
    //   3648: bipush #24
    //   3650: ldc 8388737
    //   3652: iastore
    //   3653: dup
    //   3654: bipush #25
    //   3656: iconst_1
    //   3657: iastore
    //   3658: dup
    //   3659: bipush #26
    //   3661: sipush #8320
    //   3664: iastore
    //   3665: dup
    //   3666: bipush #27
    //   3668: ldc 8388736
    //   3670: iastore
    //   3671: dup
    //   3672: bipush #28
    //   3674: sipush #8192
    //   3677: iastore
    //   3678: dup
    //   3679: bipush #29
    //   3681: ldc 8396928
    //   3683: iastore
    //   3684: dup
    //   3685: bipush #30
    //   3687: ldc 8396929
    //   3689: iastore
    //   3690: dup
    //   3691: bipush #31
    //   3693: sipush #129
    //   3696: iastore
    //   3697: dup
    //   3698: bipush #32
    //   3700: ldc 8388736
    //   3702: iastore
    //   3703: dup
    //   3704: bipush #33
    //   3706: ldc 8388609
    //   3708: iastore
    //   3709: dup
    //   3710: bipush #34
    //   3712: ldc 8396800
    //   3714: iastore
    //   3715: dup
    //   3716: bipush #35
    //   3718: ldc 8396929
    //   3720: iastore
    //   3721: dup
    //   3722: bipush #36
    //   3724: sipush #129
    //   3727: iastore
    //   3728: dup
    //   3729: bipush #37
    //   3731: iconst_0
    //   3732: iastore
    //   3733: dup
    //   3734: bipush #38
    //   3736: iconst_0
    //   3737: iastore
    //   3738: dup
    //   3739: bipush #39
    //   3741: ldc 8396800
    //   3743: iastore
    //   3744: dup
    //   3745: bipush #40
    //   3747: sipush #8320
    //   3750: iastore
    //   3751: dup
    //   3752: bipush #41
    //   3754: ldc 8388736
    //   3756: iastore
    //   3757: dup
    //   3758: bipush #42
    //   3760: ldc 8388737
    //   3762: iastore
    //   3763: dup
    //   3764: bipush #43
    //   3766: iconst_1
    //   3767: iastore
    //   3768: dup
    //   3769: bipush #44
    //   3771: ldc 8396801
    //   3773: iastore
    //   3774: dup
    //   3775: bipush #45
    //   3777: sipush #8321
    //   3780: iastore
    //   3781: dup
    //   3782: bipush #46
    //   3784: sipush #8321
    //   3787: iastore
    //   3788: dup
    //   3789: bipush #47
    //   3791: sipush #128
    //   3794: iastore
    //   3795: dup
    //   3796: bipush #48
    //   3798: ldc 8396929
    //   3800: iastore
    //   3801: dup
    //   3802: bipush #49
    //   3804: sipush #129
    //   3807: iastore
    //   3808: dup
    //   3809: bipush #50
    //   3811: iconst_1
    //   3812: iastore
    //   3813: dup
    //   3814: bipush #51
    //   3816: sipush #8192
    //   3819: iastore
    //   3820: dup
    //   3821: bipush #52
    //   3823: ldc 8388609
    //   3825: iastore
    //   3826: dup
    //   3827: bipush #53
    //   3829: sipush #8193
    //   3832: iastore
    //   3833: dup
    //   3834: bipush #54
    //   3836: ldc 8396928
    //   3838: iastore
    //   3839: dup
    //   3840: bipush #55
    //   3842: ldc 8388737
    //   3844: iastore
    //   3845: dup
    //   3846: bipush #56
    //   3848: sipush #8193
    //   3851: iastore
    //   3852: dup
    //   3853: bipush #57
    //   3855: sipush #8320
    //   3858: iastore
    //   3859: dup
    //   3860: bipush #58
    //   3862: ldc 8388608
    //   3864: iastore
    //   3865: dup
    //   3866: bipush #59
    //   3868: ldc 8396801
    //   3870: iastore
    //   3871: dup
    //   3872: bipush #60
    //   3874: sipush #128
    //   3877: iastore
    //   3878: dup
    //   3879: bipush #61
    //   3881: ldc 8388608
    //   3883: iastore
    //   3884: dup
    //   3885: bipush #62
    //   3887: sipush #8192
    //   3890: iastore
    //   3891: dup
    //   3892: bipush #63
    //   3894: ldc 8396928
    //   3896: iastore
    //   3897: astore #12
    //   3899: bipush #64
    //   3901: newarray int
    //   3903: dup
    //   3904: iconst_0
    //   3905: sipush #256
    //   3908: iastore
    //   3909: dup
    //   3910: iconst_1
    //   3911: ldc 34078976
    //   3913: iastore
    //   3914: dup
    //   3915: iconst_2
    //   3916: ldc 34078720
    //   3918: iastore
    //   3919: dup
    //   3920: iconst_3
    //   3921: ldc 1107296512
    //   3923: iastore
    //   3924: dup
    //   3925: iconst_4
    //   3926: ldc 524288
    //   3928: iastore
    //   3929: dup
    //   3930: iconst_5
    //   3931: sipush #256
    //   3934: iastore
    //   3935: dup
    //   3936: bipush #6
    //   3938: ldc 1073741824
    //   3940: iastore
    //   3941: dup
    //   3942: bipush #7
    //   3944: ldc 34078720
    //   3946: iastore
    //   3947: dup
    //   3948: bipush #8
    //   3950: ldc 1074266368
    //   3952: iastore
    //   3953: dup
    //   3954: bipush #9
    //   3956: ldc 524288
    //   3958: iastore
    //   3959: dup
    //   3960: bipush #10
    //   3962: ldc 33554688
    //   3964: iastore
    //   3965: dup
    //   3966: bipush #11
    //   3968: ldc 1074266368
    //   3970: iastore
    //   3971: dup
    //   3972: bipush #12
    //   3974: ldc 1107296512
    //   3976: iastore
    //   3977: dup
    //   3978: bipush #13
    //   3980: ldc 1107820544
    //   3982: iastore
    //   3983: dup
    //   3984: bipush #14
    //   3986: ldc 524544
    //   3988: iastore
    //   3989: dup
    //   3990: bipush #15
    //   3992: ldc 1073741824
    //   3994: iastore
    //   3995: dup
    //   3996: bipush #16
    //   3998: ldc 33554432
    //   4000: iastore
    //   4001: dup
    //   4002: bipush #17
    //   4004: ldc 1074266112
    //   4006: iastore
    //   4007: dup
    //   4008: bipush #18
    //   4010: ldc 1074266112
    //   4012: iastore
    //   4013: dup
    //   4014: bipush #19
    //   4016: iconst_0
    //   4017: iastore
    //   4018: dup
    //   4019: bipush #20
    //   4021: ldc 1073742080
    //   4023: iastore
    //   4024: dup
    //   4025: bipush #21
    //   4027: ldc 1107820800
    //   4029: iastore
    //   4030: dup
    //   4031: bipush #22
    //   4033: ldc 1107820800
    //   4035: iastore
    //   4036: dup
    //   4037: bipush #23
    //   4039: ldc 33554688
    //   4041: iastore
    //   4042: dup
    //   4043: bipush #24
    //   4045: ldc 1107820544
    //   4047: iastore
    //   4048: dup
    //   4049: bipush #25
    //   4051: ldc 1073742080
    //   4053: iastore
    //   4054: dup
    //   4055: bipush #26
    //   4057: iconst_0
    //   4058: iastore
    //   4059: dup
    //   4060: bipush #27
    //   4062: ldc 1107296256
    //   4064: iastore
    //   4065: dup
    //   4066: bipush #28
    //   4068: ldc 34078976
    //   4070: iastore
    //   4071: dup
    //   4072: bipush #29
    //   4074: ldc 33554432
    //   4076: iastore
    //   4077: dup
    //   4078: bipush #30
    //   4080: ldc 1107296256
    //   4082: iastore
    //   4083: dup
    //   4084: bipush #31
    //   4086: ldc 524544
    //   4088: iastore
    //   4089: dup
    //   4090: bipush #32
    //   4092: ldc 524288
    //   4094: iastore
    //   4095: dup
    //   4096: bipush #33
    //   4098: ldc 1107296512
    //   4100: iastore
    //   4101: dup
    //   4102: bipush #34
    //   4104: sipush #256
    //   4107: iastore
    //   4108: dup
    //   4109: bipush #35
    //   4111: ldc 33554432
    //   4113: iastore
    //   4114: dup
    //   4115: bipush #36
    //   4117: ldc 1073741824
    //   4119: iastore
    //   4120: dup
    //   4121: bipush #37
    //   4123: ldc 34078720
    //   4125: iastore
    //   4126: dup
    //   4127: bipush #38
    //   4129: ldc 1107296512
    //   4131: iastore
    //   4132: dup
    //   4133: bipush #39
    //   4135: ldc 1074266368
    //   4137: iastore
    //   4138: dup
    //   4139: bipush #40
    //   4141: ldc 33554688
    //   4143: iastore
    //   4144: dup
    //   4145: bipush #41
    //   4147: ldc 1073741824
    //   4149: iastore
    //   4150: dup
    //   4151: bipush #42
    //   4153: ldc 1107820544
    //   4155: iastore
    //   4156: dup
    //   4157: bipush #43
    //   4159: ldc 34078976
    //   4161: iastore
    //   4162: dup
    //   4163: bipush #44
    //   4165: ldc 1074266368
    //   4167: iastore
    //   4168: dup
    //   4169: bipush #45
    //   4171: sipush #256
    //   4174: iastore
    //   4175: dup
    //   4176: bipush #46
    //   4178: ldc 33554432
    //   4180: iastore
    //   4181: dup
    //   4182: bipush #47
    //   4184: ldc 1107820544
    //   4186: iastore
    //   4187: dup
    //   4188: bipush #48
    //   4190: ldc 1107820800
    //   4192: iastore
    //   4193: dup
    //   4194: bipush #49
    //   4196: ldc 524544
    //   4198: iastore
    //   4199: dup
    //   4200: bipush #50
    //   4202: ldc 1107296256
    //   4204: iastore
    //   4205: dup
    //   4206: bipush #51
    //   4208: ldc 1107820800
    //   4210: iastore
    //   4211: dup
    //   4212: bipush #52
    //   4214: ldc 34078720
    //   4216: iastore
    //   4217: dup
    //   4218: bipush #53
    //   4220: iconst_0
    //   4221: iastore
    //   4222: dup
    //   4223: bipush #54
    //   4225: ldc 1074266112
    //   4227: iastore
    //   4228: dup
    //   4229: bipush #55
    //   4231: ldc 1107296256
    //   4233: iastore
    //   4234: dup
    //   4235: bipush #56
    //   4237: ldc 524544
    //   4239: iastore
    //   4240: dup
    //   4241: bipush #57
    //   4243: ldc 33554688
    //   4245: iastore
    //   4246: dup
    //   4247: bipush #58
    //   4249: ldc 1073742080
    //   4251: iastore
    //   4252: dup
    //   4253: bipush #59
    //   4255: ldc 524288
    //   4257: iastore
    //   4258: dup
    //   4259: bipush #60
    //   4261: iconst_0
    //   4262: iastore
    //   4263: dup
    //   4264: bipush #61
    //   4266: ldc 1074266112
    //   4268: iastore
    //   4269: dup
    //   4270: bipush #62
    //   4272: ldc 34078976
    //   4274: iastore
    //   4275: dup
    //   4276: bipush #63
    //   4278: ldc 1073742080
    //   4280: iastore
    //   4281: astore #13
    //   4283: bipush #64
    //   4285: newarray int
    //   4287: dup
    //   4288: iconst_0
    //   4289: ldc 536870928
    //   4291: iastore
    //   4292: dup
    //   4293: iconst_1
    //   4294: ldc 541065216
    //   4296: iastore
    //   4297: dup
    //   4298: iconst_2
    //   4299: sipush #16384
    //   4302: iastore
    //   4303: dup
    //   4304: iconst_3
    //   4305: ldc 541081616
    //   4307: iastore
    //   4308: dup
    //   4309: iconst_4
    //   4310: ldc 541065216
    //   4312: iastore
    //   4313: dup
    //   4314: iconst_5
    //   4315: bipush #16
    //   4317: iastore
    //   4318: dup
    //   4319: bipush #6
    //   4321: ldc 541081616
    //   4323: iastore
    //   4324: dup
    //   4325: bipush #7
    //   4327: ldc 4194304
    //   4329: iastore
    //   4330: dup
    //   4331: bipush #8
    //   4333: ldc 536887296
    //   4335: iastore
    //   4336: dup
    //   4337: bipush #9
    //   4339: ldc 4210704
    //   4341: iastore
    //   4342: dup
    //   4343: bipush #10
    //   4345: ldc 4194304
    //   4347: iastore
    //   4348: dup
    //   4349: bipush #11
    //   4351: ldc 536870928
    //   4353: iastore
    //   4354: dup
    //   4355: bipush #12
    //   4357: ldc 4194320
    //   4359: iastore
    //   4360: dup
    //   4361: bipush #13
    //   4363: ldc 536887296
    //   4365: iastore
    //   4366: dup
    //   4367: bipush #14
    //   4369: ldc 536870912
    //   4371: iastore
    //   4372: dup
    //   4373: bipush #15
    //   4375: sipush #16400
    //   4378: iastore
    //   4379: dup
    //   4380: bipush #16
    //   4382: iconst_0
    //   4383: iastore
    //   4384: dup
    //   4385: bipush #17
    //   4387: ldc 4194320
    //   4389: iastore
    //   4390: dup
    //   4391: bipush #18
    //   4393: ldc 536887312
    //   4395: iastore
    //   4396: dup
    //   4397: bipush #19
    //   4399: sipush #16384
    //   4402: iastore
    //   4403: dup
    //   4404: bipush #20
    //   4406: ldc 4210688
    //   4408: iastore
    //   4409: dup
    //   4410: bipush #21
    //   4412: ldc 536887312
    //   4414: iastore
    //   4415: dup
    //   4416: bipush #22
    //   4418: bipush #16
    //   4420: iastore
    //   4421: dup
    //   4422: bipush #23
    //   4424: ldc 541065232
    //   4426: iastore
    //   4427: dup
    //   4428: bipush #24
    //   4430: ldc 541065232
    //   4432: iastore
    //   4433: dup
    //   4434: bipush #25
    //   4436: iconst_0
    //   4437: iastore
    //   4438: dup
    //   4439: bipush #26
    //   4441: ldc 4210704
    //   4443: iastore
    //   4444: dup
    //   4445: bipush #27
    //   4447: ldc 541081600
    //   4449: iastore
    //   4450: dup
    //   4451: bipush #28
    //   4453: sipush #16400
    //   4456: iastore
    //   4457: dup
    //   4458: bipush #29
    //   4460: ldc 4210688
    //   4462: iastore
    //   4463: dup
    //   4464: bipush #30
    //   4466: ldc 541081600
    //   4468: iastore
    //   4469: dup
    //   4470: bipush #31
    //   4472: ldc 536870912
    //   4474: iastore
    //   4475: dup
    //   4476: bipush #32
    //   4478: ldc 536887296
    //   4480: iastore
    //   4481: dup
    //   4482: bipush #33
    //   4484: bipush #16
    //   4486: iastore
    //   4487: dup
    //   4488: bipush #34
    //   4490: ldc 541065232
    //   4492: iastore
    //   4493: dup
    //   4494: bipush #35
    //   4496: ldc 4210688
    //   4498: iastore
    //   4499: dup
    //   4500: bipush #36
    //   4502: ldc 541081616
    //   4504: iastore
    //   4505: dup
    //   4506: bipush #37
    //   4508: ldc 4194304
    //   4510: iastore
    //   4511: dup
    //   4512: bipush #38
    //   4514: sipush #16400
    //   4517: iastore
    //   4518: dup
    //   4519: bipush #39
    //   4521: ldc 536870928
    //   4523: iastore
    //   4524: dup
    //   4525: bipush #40
    //   4527: ldc 4194304
    //   4529: iastore
    //   4530: dup
    //   4531: bipush #41
    //   4533: ldc 536887296
    //   4535: iastore
    //   4536: dup
    //   4537: bipush #42
    //   4539: ldc 536870912
    //   4541: iastore
    //   4542: dup
    //   4543: bipush #43
    //   4545: sipush #16400
    //   4548: iastore
    //   4549: dup
    //   4550: bipush #44
    //   4552: ldc 536870928
    //   4554: iastore
    //   4555: dup
    //   4556: bipush #45
    //   4558: ldc 541081616
    //   4560: iastore
    //   4561: dup
    //   4562: bipush #46
    //   4564: ldc 4210688
    //   4566: iastore
    //   4567: dup
    //   4568: bipush #47
    //   4570: ldc 541065216
    //   4572: iastore
    //   4573: dup
    //   4574: bipush #48
    //   4576: ldc 4210704
    //   4578: iastore
    //   4579: dup
    //   4580: bipush #49
    //   4582: ldc 541081600
    //   4584: iastore
    //   4585: dup
    //   4586: bipush #50
    //   4588: iconst_0
    //   4589: iastore
    //   4590: dup
    //   4591: bipush #51
    //   4593: ldc 541065232
    //   4595: iastore
    //   4596: dup
    //   4597: bipush #52
    //   4599: bipush #16
    //   4601: iastore
    //   4602: dup
    //   4603: bipush #53
    //   4605: sipush #16384
    //   4608: iastore
    //   4609: dup
    //   4610: bipush #54
    //   4612: ldc 541065216
    //   4614: iastore
    //   4615: dup
    //   4616: bipush #55
    //   4618: ldc 4210704
    //   4620: iastore
    //   4621: dup
    //   4622: bipush #56
    //   4624: sipush #16384
    //   4627: iastore
    //   4628: dup
    //   4629: bipush #57
    //   4631: ldc 4194320
    //   4633: iastore
    //   4634: dup
    //   4635: bipush #58
    //   4637: ldc 536887312
    //   4639: iastore
    //   4640: dup
    //   4641: bipush #59
    //   4643: iconst_0
    //   4644: iastore
    //   4645: dup
    //   4646: bipush #60
    //   4648: ldc 541081600
    //   4650: iastore
    //   4651: dup
    //   4652: bipush #61
    //   4654: ldc 536870912
    //   4656: iastore
    //   4657: dup
    //   4658: bipush #62
    //   4660: ldc 4194320
    //   4662: iastore
    //   4663: dup
    //   4664: bipush #63
    //   4666: ldc 536887312
    //   4668: iastore
    //   4669: astore #14
    //   4671: bipush #64
    //   4673: newarray int
    //   4675: dup
    //   4676: iconst_0
    //   4677: ldc 2097152
    //   4679: iastore
    //   4680: dup
    //   4681: iconst_1
    //   4682: ldc 69206018
    //   4684: iastore
    //   4685: dup
    //   4686: iconst_2
    //   4687: ldc 67110914
    //   4689: iastore
    //   4690: dup
    //   4691: iconst_3
    //   4692: iconst_0
    //   4693: iastore
    //   4694: dup
    //   4695: iconst_4
    //   4696: sipush #2048
    //   4699: iastore
    //   4700: dup
    //   4701: iconst_5
    //   4702: ldc 67110914
    //   4704: iastore
    //   4705: dup
    //   4706: bipush #6
    //   4708: ldc 2099202
    //   4710: iastore
    //   4711: dup
    //   4712: bipush #7
    //   4714: ldc 69208064
    //   4716: iastore
    //   4717: dup
    //   4718: bipush #8
    //   4720: ldc 69208066
    //   4722: iastore
    //   4723: dup
    //   4724: bipush #9
    //   4726: ldc 2097152
    //   4728: iastore
    //   4729: dup
    //   4730: bipush #10
    //   4732: iconst_0
    //   4733: iastore
    //   4734: dup
    //   4735: bipush #11
    //   4737: ldc 67108866
    //   4739: iastore
    //   4740: dup
    //   4741: bipush #12
    //   4743: iconst_2
    //   4744: iastore
    //   4745: dup
    //   4746: bipush #13
    //   4748: ldc 67108864
    //   4750: iastore
    //   4751: dup
    //   4752: bipush #14
    //   4754: ldc 69206018
    //   4756: iastore
    //   4757: dup
    //   4758: bipush #15
    //   4760: sipush #2050
    //   4763: iastore
    //   4764: dup
    //   4765: bipush #16
    //   4767: ldc 67110912
    //   4769: iastore
    //   4770: dup
    //   4771: bipush #17
    //   4773: ldc 2099202
    //   4775: iastore
    //   4776: dup
    //   4777: bipush #18
    //   4779: ldc 2097154
    //   4781: iastore
    //   4782: dup
    //   4783: bipush #19
    //   4785: ldc 67110912
    //   4787: iastore
    //   4788: dup
    //   4789: bipush #20
    //   4791: ldc 67108866
    //   4793: iastore
    //   4794: dup
    //   4795: bipush #21
    //   4797: ldc 69206016
    //   4799: iastore
    //   4800: dup
    //   4801: bipush #22
    //   4803: ldc 69208064
    //   4805: iastore
    //   4806: dup
    //   4807: bipush #23
    //   4809: ldc 2097154
    //   4811: iastore
    //   4812: dup
    //   4813: bipush #24
    //   4815: ldc 69206016
    //   4817: iastore
    //   4818: dup
    //   4819: bipush #25
    //   4821: sipush #2048
    //   4824: iastore
    //   4825: dup
    //   4826: bipush #26
    //   4828: sipush #2050
    //   4831: iastore
    //   4832: dup
    //   4833: bipush #27
    //   4835: ldc 69208066
    //   4837: iastore
    //   4838: dup
    //   4839: bipush #28
    //   4841: ldc 2099200
    //   4843: iastore
    //   4844: dup
    //   4845: bipush #29
    //   4847: iconst_2
    //   4848: iastore
    //   4849: dup
    //   4850: bipush #30
    //   4852: ldc 67108864
    //   4854: iastore
    //   4855: dup
    //   4856: bipush #31
    //   4858: ldc 2099200
    //   4860: iastore
    //   4861: dup
    //   4862: bipush #32
    //   4864: ldc 67108864
    //   4866: iastore
    //   4867: dup
    //   4868: bipush #33
    //   4870: ldc 2099200
    //   4872: iastore
    //   4873: dup
    //   4874: bipush #34
    //   4876: ldc 2097152
    //   4878: iastore
    //   4879: dup
    //   4880: bipush #35
    //   4882: ldc 67110914
    //   4884: iastore
    //   4885: dup
    //   4886: bipush #36
    //   4888: ldc 67110914
    //   4890: iastore
    //   4891: dup
    //   4892: bipush #37
    //   4894: ldc 69206018
    //   4896: iastore
    //   4897: dup
    //   4898: bipush #38
    //   4900: ldc 69206018
    //   4902: iastore
    //   4903: dup
    //   4904: bipush #39
    //   4906: iconst_2
    //   4907: iastore
    //   4908: dup
    //   4909: bipush #40
    //   4911: ldc 2097154
    //   4913: iastore
    //   4914: dup
    //   4915: bipush #41
    //   4917: ldc 67108864
    //   4919: iastore
    //   4920: dup
    //   4921: bipush #42
    //   4923: ldc 67110912
    //   4925: iastore
    //   4926: dup
    //   4927: bipush #43
    //   4929: ldc 2097152
    //   4931: iastore
    //   4932: dup
    //   4933: bipush #44
    //   4935: ldc 69208064
    //   4937: iastore
    //   4938: dup
    //   4939: bipush #45
    //   4941: sipush #2050
    //   4944: iastore
    //   4945: dup
    //   4946: bipush #46
    //   4948: ldc 2099202
    //   4950: iastore
    //   4951: dup
    //   4952: bipush #47
    //   4954: ldc 69208064
    //   4956: iastore
    //   4957: dup
    //   4958: bipush #48
    //   4960: sipush #2050
    //   4963: iastore
    //   4964: dup
    //   4965: bipush #49
    //   4967: ldc 67108866
    //   4969: iastore
    //   4970: dup
    //   4971: bipush #50
    //   4973: ldc 69208066
    //   4975: iastore
    //   4976: dup
    //   4977: bipush #51
    //   4979: ldc 69206016
    //   4981: iastore
    //   4982: dup
    //   4983: bipush #52
    //   4985: ldc 2099200
    //   4987: iastore
    //   4988: dup
    //   4989: bipush #53
    //   4991: iconst_0
    //   4992: iastore
    //   4993: dup
    //   4994: bipush #54
    //   4996: iconst_2
    //   4997: iastore
    //   4998: dup
    //   4999: bipush #55
    //   5001: ldc 69208066
    //   5003: iastore
    //   5004: dup
    //   5005: bipush #56
    //   5007: iconst_0
    //   5008: iastore
    //   5009: dup
    //   5010: bipush #57
    //   5012: ldc 2099202
    //   5014: iastore
    //   5015: dup
    //   5016: bipush #58
    //   5018: ldc 69206016
    //   5020: iastore
    //   5021: dup
    //   5022: bipush #59
    //   5024: sipush #2048
    //   5027: iastore
    //   5028: dup
    //   5029: bipush #60
    //   5031: ldc 67108866
    //   5033: iastore
    //   5034: dup
    //   5035: bipush #61
    //   5037: ldc 67110912
    //   5039: iastore
    //   5040: dup
    //   5041: bipush #62
    //   5043: sipush #2048
    //   5046: iastore
    //   5047: dup
    //   5048: bipush #63
    //   5050: ldc 2097154
    //   5052: iastore
    //   5053: astore #15
    //   5055: bipush #64
    //   5057: newarray int
    //   5059: dup
    //   5060: iconst_0
    //   5061: ldc 268439616
    //   5063: iastore
    //   5064: dup
    //   5065: iconst_1
    //   5066: sipush #4096
    //   5069: iastore
    //   5070: dup
    //   5071: iconst_2
    //   5072: ldc 262144
    //   5074: iastore
    //   5075: dup
    //   5076: iconst_3
    //   5077: ldc 268701760
    //   5079: iastore
    //   5080: dup
    //   5081: iconst_4
    //   5082: ldc 268435456
    //   5084: iastore
    //   5085: dup
    //   5086: iconst_5
    //   5087: ldc 268439616
    //   5089: iastore
    //   5090: dup
    //   5091: bipush #6
    //   5093: bipush #64
    //   5095: iastore
    //   5096: dup
    //   5097: bipush #7
    //   5099: ldc 268435456
    //   5101: iastore
    //   5102: dup
    //   5103: bipush #8
    //   5105: ldc 262208
    //   5107: iastore
    //   5108: dup
    //   5109: bipush #9
    //   5111: ldc 268697600
    //   5113: iastore
    //   5114: dup
    //   5115: bipush #10
    //   5117: ldc 268701760
    //   5119: iastore
    //   5120: dup
    //   5121: bipush #11
    //   5123: ldc 266240
    //   5125: iastore
    //   5126: dup
    //   5127: bipush #12
    //   5129: ldc 268701696
    //   5131: iastore
    //   5132: dup
    //   5133: bipush #13
    //   5135: ldc 266304
    //   5137: iastore
    //   5138: dup
    //   5139: bipush #14
    //   5141: sipush #4096
    //   5144: iastore
    //   5145: dup
    //   5146: bipush #15
    //   5148: bipush #64
    //   5150: iastore
    //   5151: dup
    //   5152: bipush #16
    //   5154: ldc 268697600
    //   5156: iastore
    //   5157: dup
    //   5158: bipush #17
    //   5160: ldc 268435520
    //   5162: iastore
    //   5163: dup
    //   5164: bipush #18
    //   5166: ldc 268439552
    //   5168: iastore
    //   5169: dup
    //   5170: bipush #19
    //   5172: sipush #4160
    //   5175: iastore
    //   5176: dup
    //   5177: bipush #20
    //   5179: ldc 266240
    //   5181: iastore
    //   5182: dup
    //   5183: bipush #21
    //   5185: ldc 262208
    //   5187: iastore
    //   5188: dup
    //   5189: bipush #22
    //   5191: ldc 268697664
    //   5193: iastore
    //   5194: dup
    //   5195: bipush #23
    //   5197: ldc 268701696
    //   5199: iastore
    //   5200: dup
    //   5201: bipush #24
    //   5203: sipush #4160
    //   5206: iastore
    //   5207: dup
    //   5208: bipush #25
    //   5210: iconst_0
    //   5211: iastore
    //   5212: dup
    //   5213: bipush #26
    //   5215: iconst_0
    //   5216: iastore
    //   5217: dup
    //   5218: bipush #27
    //   5220: ldc 268697664
    //   5222: iastore
    //   5223: dup
    //   5224: bipush #28
    //   5226: ldc 268435520
    //   5228: iastore
    //   5229: dup
    //   5230: bipush #29
    //   5232: ldc 268439552
    //   5234: iastore
    //   5235: dup
    //   5236: bipush #30
    //   5238: ldc 266304
    //   5240: iastore
    //   5241: dup
    //   5242: bipush #31
    //   5244: ldc 262144
    //   5246: iastore
    //   5247: dup
    //   5248: bipush #32
    //   5250: ldc 266304
    //   5252: iastore
    //   5253: dup
    //   5254: bipush #33
    //   5256: ldc 262144
    //   5258: iastore
    //   5259: dup
    //   5260: bipush #34
    //   5262: ldc 268701696
    //   5264: iastore
    //   5265: dup
    //   5266: bipush #35
    //   5268: sipush #4096
    //   5271: iastore
    //   5272: dup
    //   5273: bipush #36
    //   5275: bipush #64
    //   5277: iastore
    //   5278: dup
    //   5279: bipush #37
    //   5281: ldc 268697664
    //   5283: iastore
    //   5284: dup
    //   5285: bipush #38
    //   5287: sipush #4096
    //   5290: iastore
    //   5291: dup
    //   5292: bipush #39
    //   5294: ldc 266304
    //   5296: iastore
    //   5297: dup
    //   5298: bipush #40
    //   5300: ldc 268439552
    //   5302: iastore
    //   5303: dup
    //   5304: bipush #41
    //   5306: bipush #64
    //   5308: iastore
    //   5309: dup
    //   5310: bipush #42
    //   5312: ldc 268435520
    //   5314: iastore
    //   5315: dup
    //   5316: bipush #43
    //   5318: ldc 268697600
    //   5320: iastore
    //   5321: dup
    //   5322: bipush #44
    //   5324: ldc 268697664
    //   5326: iastore
    //   5327: dup
    //   5328: bipush #45
    //   5330: ldc 268435456
    //   5332: iastore
    //   5333: dup
    //   5334: bipush #46
    //   5336: ldc 262144
    //   5338: iastore
    //   5339: dup
    //   5340: bipush #47
    //   5342: ldc 268439616
    //   5344: iastore
    //   5345: dup
    //   5346: bipush #48
    //   5348: iconst_0
    //   5349: iastore
    //   5350: dup
    //   5351: bipush #49
    //   5353: ldc 268701760
    //   5355: iastore
    //   5356: dup
    //   5357: bipush #50
    //   5359: ldc 262208
    //   5361: iastore
    //   5362: dup
    //   5363: bipush #51
    //   5365: ldc 268435520
    //   5367: iastore
    //   5368: dup
    //   5369: bipush #52
    //   5371: ldc 268697600
    //   5373: iastore
    //   5374: dup
    //   5375: bipush #53
    //   5377: ldc 268439552
    //   5379: iastore
    //   5380: dup
    //   5381: bipush #54
    //   5383: ldc 268439616
    //   5385: iastore
    //   5386: dup
    //   5387: bipush #55
    //   5389: iconst_0
    //   5390: iastore
    //   5391: dup
    //   5392: bipush #56
    //   5394: ldc 268701760
    //   5396: iastore
    //   5397: dup
    //   5398: bipush #57
    //   5400: ldc 266240
    //   5402: iastore
    //   5403: dup
    //   5404: bipush #58
    //   5406: ldc 266240
    //   5408: iastore
    //   5409: dup
    //   5410: bipush #59
    //   5412: sipush #4160
    //   5415: iastore
    //   5416: dup
    //   5417: bipush #60
    //   5419: sipush #4160
    //   5422: iastore
    //   5423: dup
    //   5424: bipush #61
    //   5426: ldc 262208
    //   5428: iastore
    //   5429: dup
    //   5430: bipush #62
    //   5432: ldc 268435456
    //   5434: iastore
    //   5435: dup
    //   5436: bipush #63
    //   5438: ldc 268701696
    //   5440: iastore
    //   5441: astore #16
    //   5443: aload #4
    //   5445: arraylength
    //   5446: istore #17
    //   5448: iconst_2
    //   5449: newarray int
    //   5451: astore #18
    //   5453: iload #17
    //   5455: newarray byte
    //   5457: astore #5
    //   5459: iload #17
    //   5461: bipush #8
    //   5463: idiv
    //   5464: istore #19
    //   5466: iconst_0
    //   5467: istore #20
    //   5469: iload #20
    //   5471: iload #19
    //   5473: if_icmpge -> 6391
    //   5476: iload #20
    //   5478: bipush #8
    //   5480: imul
    //   5481: istore #21
    //   5483: iconst_0
    //   5484: istore #22
    //   5486: iload #22
    //   5488: iconst_2
    //   5489: if_icmpge -> 5578
    //   5492: aload #18
    //   5494: iload #22
    //   5496: aload #4
    //   5498: iload #21
    //   5500: iload #22
    //   5502: iconst_4
    //   5503: imul
    //   5504: iadd
    //   5505: baload
    //   5506: sipush #255
    //   5509: iand
    //   5510: bipush #24
    //   5512: ishl
    //   5513: aload #4
    //   5515: iload #21
    //   5517: iload #22
    //   5519: iconst_4
    //   5520: imul
    //   5521: iadd
    //   5522: iconst_1
    //   5523: iadd
    //   5524: baload
    //   5525: sipush #255
    //   5528: iand
    //   5529: bipush #16
    //   5531: ishl
    //   5532: ior
    //   5533: aload #4
    //   5535: iload #21
    //   5537: iload #22
    //   5539: iconst_4
    //   5540: imul
    //   5541: iadd
    //   5542: iconst_2
    //   5543: iadd
    //   5544: baload
    //   5545: sipush #255
    //   5548: iand
    //   5549: bipush #8
    //   5551: ishl
    //   5552: ior
    //   5553: aload #4
    //   5555: iload #21
    //   5557: iload #22
    //   5559: iconst_4
    //   5560: imul
    //   5561: iadd
    //   5562: iconst_3
    //   5563: iadd
    //   5564: baload
    //   5565: sipush #255
    //   5568: iand
    //   5569: ior
    //   5570: iastore
    //   5571: iinc #22, 1
    //   5574: iload_2
    //   5575: ifne -> 5486
    //   5578: iconst_0
    //   5579: istore #27
    //   5581: aload #18
    //   5583: iconst_0
    //   5584: iaload
    //   5585: istore #25
    //   5587: aload #18
    //   5589: iconst_1
    //   5590: iaload
    //   5591: istore #24
    //   5593: iload #25
    //   5595: iconst_4
    //   5596: iushr
    //   5597: iload #24
    //   5599: ixor
    //   5600: ldc 252645135
    //   5602: iand
    //   5603: istore #23
    //   5605: iload #24
    //   5607: iload #23
    //   5609: ixor
    //   5610: istore #24
    //   5612: iload #25
    //   5614: iload #23
    //   5616: iconst_4
    //   5617: ishl
    //   5618: ixor
    //   5619: istore #25
    //   5621: iload #25
    //   5623: bipush #16
    //   5625: iushr
    //   5626: iload #24
    //   5628: ixor
    //   5629: ldc 65535
    //   5631: iand
    //   5632: istore #23
    //   5634: iload #24
    //   5636: iload #23
    //   5638: ixor
    //   5639: istore #24
    //   5641: iload #25
    //   5643: iload #23
    //   5645: bipush #16
    //   5647: ishl
    //   5648: ixor
    //   5649: istore #25
    //   5651: iload #24
    //   5653: iconst_2
    //   5654: iushr
    //   5655: iload #25
    //   5657: ixor
    //   5658: ldc 858993459
    //   5660: iand
    //   5661: istore #23
    //   5663: iload #25
    //   5665: iload #23
    //   5667: ixor
    //   5668: istore #25
    //   5670: iload #24
    //   5672: iload #23
    //   5674: iconst_2
    //   5675: ishl
    //   5676: ixor
    //   5677: istore #24
    //   5679: iload #24
    //   5681: bipush #8
    //   5683: iushr
    //   5684: iload #25
    //   5686: ixor
    //   5687: ldc 16711935
    //   5689: iand
    //   5690: istore #23
    //   5692: iload #25
    //   5694: iload #23
    //   5696: ixor
    //   5697: istore #25
    //   5699: iload #24
    //   5701: iload #23
    //   5703: bipush #8
    //   5705: ishl
    //   5706: ixor
    //   5707: istore #24
    //   5709: iload #24
    //   5711: iconst_1
    //   5712: ishl
    //   5713: iload #24
    //   5715: bipush #31
    //   5717: iushr
    //   5718: iconst_1
    //   5719: iand
    //   5720: ior
    //   5721: istore #24
    //   5723: iload #25
    //   5725: iload #24
    //   5727: ixor
    //   5728: ldc -1431655766
    //   5730: iand
    //   5731: istore #23
    //   5733: iload #25
    //   5735: iload #23
    //   5737: ixor
    //   5738: istore #25
    //   5740: iload #24
    //   5742: iload #23
    //   5744: ixor
    //   5745: istore #24
    //   5747: iload #25
    //   5749: iconst_1
    //   5750: ishl
    //   5751: iload #25
    //   5753: bipush #31
    //   5755: iushr
    //   5756: iconst_1
    //   5757: iand
    //   5758: ior
    //   5759: istore #25
    //   5761: iconst_0
    //   5762: istore #26
    //   5764: iload #26
    //   5766: bipush #8
    //   5768: if_icmpge -> 6106
    //   5771: iload #24
    //   5773: bipush #28
    //   5775: ishl
    //   5776: iload #24
    //   5778: iconst_4
    //   5779: iushr
    //   5780: ior
    //   5781: istore #23
    //   5783: iload #23
    //   5785: aload #6
    //   5787: iload #27
    //   5789: iinc #27, 1
    //   5792: iaload
    //   5793: ixor
    //   5794: istore #23
    //   5796: aload #15
    //   5798: iload #23
    //   5800: bipush #63
    //   5802: iand
    //   5803: iaload
    //   5804: istore #22
    //   5806: iload #22
    //   5808: aload #13
    //   5810: iload #23
    //   5812: bipush #8
    //   5814: iushr
    //   5815: bipush #63
    //   5817: iand
    //   5818: iaload
    //   5819: ior
    //   5820: istore #22
    //   5822: iload #22
    //   5824: aload #11
    //   5826: iload #23
    //   5828: bipush #16
    //   5830: iushr
    //   5831: bipush #63
    //   5833: iand
    //   5834: iaload
    //   5835: ior
    //   5836: istore #22
    //   5838: iload #22
    //   5840: aload #9
    //   5842: iload #23
    //   5844: bipush #24
    //   5846: iushr
    //   5847: bipush #63
    //   5849: iand
    //   5850: iaload
    //   5851: ior
    //   5852: istore #22
    //   5854: iload #24
    //   5856: aload #6
    //   5858: iload #27
    //   5860: iinc #27, 1
    //   5863: iaload
    //   5864: ixor
    //   5865: istore #23
    //   5867: iload #22
    //   5869: aload #16
    //   5871: iload #23
    //   5873: bipush #63
    //   5875: iand
    //   5876: iaload
    //   5877: ior
    //   5878: istore #22
    //   5880: iload #22
    //   5882: aload #14
    //   5884: iload #23
    //   5886: bipush #8
    //   5888: iushr
    //   5889: bipush #63
    //   5891: iand
    //   5892: iaload
    //   5893: ior
    //   5894: istore #22
    //   5896: iload #22
    //   5898: aload #12
    //   5900: iload #23
    //   5902: bipush #16
    //   5904: iushr
    //   5905: bipush #63
    //   5907: iand
    //   5908: iaload
    //   5909: ior
    //   5910: istore #22
    //   5912: iload #22
    //   5914: aload #10
    //   5916: iload #23
    //   5918: bipush #24
    //   5920: iushr
    //   5921: bipush #63
    //   5923: iand
    //   5924: iaload
    //   5925: ior
    //   5926: istore #22
    //   5928: iload #25
    //   5930: iload #22
    //   5932: ixor
    //   5933: istore #25
    //   5935: iload #25
    //   5937: bipush #28
    //   5939: ishl
    //   5940: iload #25
    //   5942: iconst_4
    //   5943: iushr
    //   5944: ior
    //   5945: istore #23
    //   5947: iload #23
    //   5949: aload #6
    //   5951: iload #27
    //   5953: iinc #27, 1
    //   5956: iaload
    //   5957: ixor
    //   5958: istore #23
    //   5960: aload #15
    //   5962: iload #23
    //   5964: bipush #63
    //   5966: iand
    //   5967: iaload
    //   5968: istore #22
    //   5970: iload #22
    //   5972: aload #13
    //   5974: iload #23
    //   5976: bipush #8
    //   5978: iushr
    //   5979: bipush #63
    //   5981: iand
    //   5982: iaload
    //   5983: ior
    //   5984: istore #22
    //   5986: iload #22
    //   5988: aload #11
    //   5990: iload #23
    //   5992: bipush #16
    //   5994: iushr
    //   5995: bipush #63
    //   5997: iand
    //   5998: iaload
    //   5999: ior
    //   6000: istore #22
    //   6002: iload #22
    //   6004: aload #9
    //   6006: iload #23
    //   6008: bipush #24
    //   6010: iushr
    //   6011: bipush #63
    //   6013: iand
    //   6014: iaload
    //   6015: ior
    //   6016: istore #22
    //   6018: iload #25
    //   6020: aload #6
    //   6022: iload #27
    //   6024: iinc #27, 1
    //   6027: iaload
    //   6028: ixor
    //   6029: istore #23
    //   6031: iload #22
    //   6033: aload #16
    //   6035: iload #23
    //   6037: bipush #63
    //   6039: iand
    //   6040: iaload
    //   6041: ior
    //   6042: istore #22
    //   6044: iload #22
    //   6046: aload #14
    //   6048: iload #23
    //   6050: bipush #8
    //   6052: iushr
    //   6053: bipush #63
    //   6055: iand
    //   6056: iaload
    //   6057: ior
    //   6058: istore #22
    //   6060: iload #22
    //   6062: aload #12
    //   6064: iload #23
    //   6066: bipush #16
    //   6068: iushr
    //   6069: bipush #63
    //   6071: iand
    //   6072: iaload
    //   6073: ior
    //   6074: istore #22
    //   6076: iload #22
    //   6078: aload #10
    //   6080: iload #23
    //   6082: bipush #24
    //   6084: iushr
    //   6085: bipush #63
    //   6087: iand
    //   6088: iaload
    //   6089: ior
    //   6090: istore #22
    //   6092: iload #24
    //   6094: iload #22
    //   6096: ixor
    //   6097: istore #24
    //   6099: iinc #26, 1
    //   6102: iload_2
    //   6103: ifne -> 5764
    //   6106: iload #24
    //   6108: bipush #31
    //   6110: ishl
    //   6111: iload #24
    //   6113: iconst_1
    //   6114: iushr
    //   6115: ior
    //   6116: istore #24
    //   6118: iload #25
    //   6120: iload #24
    //   6122: ixor
    //   6123: ldc -1431655766
    //   6125: iand
    //   6126: istore #23
    //   6128: iload #25
    //   6130: iload #23
    //   6132: ixor
    //   6133: istore #25
    //   6135: iload #24
    //   6137: iload #23
    //   6139: ixor
    //   6140: istore #24
    //   6142: iload #25
    //   6144: bipush #31
    //   6146: ishl
    //   6147: iload #25
    //   6149: iconst_1
    //   6150: iushr
    //   6151: ior
    //   6152: istore #25
    //   6154: iload #25
    //   6156: bipush #8
    //   6158: iushr
    //   6159: iload #24
    //   6161: ixor
    //   6162: ldc 16711935
    //   6164: iand
    //   6165: istore #23
    //   6167: iload #24
    //   6169: iload #23
    //   6171: ixor
    //   6172: istore #24
    //   6174: iload #25
    //   6176: iload #23
    //   6178: bipush #8
    //   6180: ishl
    //   6181: ixor
    //   6182: istore #25
    //   6184: iload #25
    //   6186: iconst_2
    //   6187: iushr
    //   6188: iload #24
    //   6190: ixor
    //   6191: ldc 858993459
    //   6193: iand
    //   6194: istore #23
    //   6196: iload #24
    //   6198: iload #23
    //   6200: ixor
    //   6201: istore #24
    //   6203: iload #25
    //   6205: iload #23
    //   6207: iconst_2
    //   6208: ishl
    //   6209: ixor
    //   6210: istore #25
    //   6212: iload #24
    //   6214: bipush #16
    //   6216: iushr
    //   6217: iload #25
    //   6219: ixor
    //   6220: ldc 65535
    //   6222: iand
    //   6223: istore #23
    //   6225: iload #25
    //   6227: iload #23
    //   6229: ixor
    //   6230: istore #25
    //   6232: iload #24
    //   6234: iload #23
    //   6236: bipush #16
    //   6238: ishl
    //   6239: ixor
    //   6240: istore #24
    //   6242: iload #24
    //   6244: iconst_4
    //   6245: iushr
    //   6246: iload #25
    //   6248: ixor
    //   6249: ldc 252645135
    //   6251: iand
    //   6252: istore #23
    //   6254: iload #25
    //   6256: iload #23
    //   6258: ixor
    //   6259: istore #25
    //   6261: iload #24
    //   6263: iload #23
    //   6265: iconst_4
    //   6266: ishl
    //   6267: ixor
    //   6268: istore #24
    //   6270: aload #18
    //   6272: iconst_0
    //   6273: iload #24
    //   6275: iastore
    //   6276: aload #18
    //   6278: iconst_1
    //   6279: iload #25
    //   6281: iastore
    //   6282: iload #20
    //   6284: bipush #8
    //   6286: imul
    //   6287: istore #28
    //   6289: iconst_0
    //   6290: istore #29
    //   6292: iload #29
    //   6294: iconst_2
    //   6295: if_icmpge -> 6384
    //   6298: aload #5
    //   6300: iload #28
    //   6302: iload #29
    //   6304: iconst_4
    //   6305: imul
    //   6306: iadd
    //   6307: aload #18
    //   6309: iload #29
    //   6311: iaload
    //   6312: bipush #24
    //   6314: iushr
    //   6315: i2b
    //   6316: bastore
    //   6317: aload #5
    //   6319: iload #28
    //   6321: iload #29
    //   6323: iconst_4
    //   6324: imul
    //   6325: iadd
    //   6326: iconst_1
    //   6327: iadd
    //   6328: aload #18
    //   6330: iload #29
    //   6332: iaload
    //   6333: bipush #16
    //   6335: iushr
    //   6336: i2b
    //   6337: bastore
    //   6338: aload #5
    //   6340: iload #28
    //   6342: iload #29
    //   6344: iconst_4
    //   6345: imul
    //   6346: iadd
    //   6347: iconst_2
    //   6348: iadd
    //   6349: aload #18
    //   6351: iload #29
    //   6353: iaload
    //   6354: bipush #8
    //   6356: iushr
    //   6357: i2b
    //   6358: bastore
    //   6359: aload #5
    //   6361: iload #28
    //   6363: iload #29
    //   6365: iconst_4
    //   6366: imul
    //   6367: iadd
    //   6368: iconst_3
    //   6369: iadd
    //   6370: aload #18
    //   6372: iload #29
    //   6374: iaload
    //   6375: i2b
    //   6376: bastore
    //   6377: iinc #29, 1
    //   6380: iload_2
    //   6381: ifne -> 6292
    //   6384: iinc #20, 1
    //   6387: iload_2
    //   6388: ifne -> 5469
    //   6391: new java/math/BigInteger
    //   6394: dup
    //   6395: aload #5
    //   6397: invokespecial <init> : ([B)V
    //   6400: invokevirtual abs : ()Ljava/math/BigInteger;
    //   6403: putstatic burp/Zmha.ZM : Ljava/lang/Object;
    //   6406: sipush #-13231
    //   6409: sipush #14853
    //   6412: invokestatic a : (II)Ljava/lang/String;
    //   6415: iconst_1
    //   6416: ldc burp/Zkw
    //   6418: invokevirtual getClassLoader : ()Ljava/lang/ClassLoader;
    //   6421: invokestatic forName : (Ljava/lang/String;ZLjava/lang/ClassLoader;)Ljava/lang/Class;
    //   6424: invokevirtual getDeclaredFields : ()[Ljava/lang/reflect/Field;
    //   6427: astore #4
    //   6429: aload #4
    //   6431: arraylength
    //   6432: istore #5
    //   6434: iconst_0
    //   6435: istore #6
    //   6437: iload #6
    //   6439: iload #5
    //   6441: if_icmpge -> 6579
    //   6444: aload #4
    //   6446: iload #6
    //   6448: aaload
    //   6449: astore #7
    //   6451: aload #7
    //   6453: invokevirtual getModifiers : ()I
    //   6456: invokestatic isStatic : (I)Z
    //   6459: ifne -> 6469
    //   6462: goto -> 6572
    //   6465: invokestatic a : (Ljava/lang/Throwable;)Ljava/lang/Throwable;
    //   6468: athrow
    //   6469: aload #7
    //   6471: invokevirtual getType : ()Ljava/lang/Class;
    //   6474: astore #8
    //   6476: aload #8
    //   6478: ifnull -> 6559
    //   6481: aload #8
    //   6483: invokevirtual isPrimitive : ()Z
    //   6486: ifne -> 6559
    //   6489: goto -> 6496
    //   6492: invokestatic a : (Ljava/lang/Throwable;)Ljava/lang/Throwable;
    //   6495: athrow
    //   6496: aload #8
    //   6498: invokevirtual getPackage : ()Ljava/lang/Package;
    //   6501: ifnull -> 6559
    //   6504: goto -> 6511
    //   6507: invokestatic a : (Ljava/lang/Throwable;)Ljava/lang/Throwable;
    //   6510: athrow
    //   6511: aload #8
    //   6513: invokevirtual getPackage : ()Ljava/lang/Package;
    //   6516: invokevirtual getName : ()Ljava/lang/String;
    //   6519: ifnull -> 6559
    //   6522: goto -> 6529
    //   6525: invokestatic a : (Ljava/lang/Throwable;)Ljava/lang/Throwable;
    //   6528: athrow
    //   6529: aload #8
    //   6531: invokevirtual getPackage : ()Ljava/lang/Package;
    //   6534: invokevirtual getName : ()Ljava/lang/String;
    //   6537: sipush #-13227
    //   6540: sipush #-10068
    //   6543: invokestatic a : (II)Ljava/lang/String;
    //   6546: invokevirtual startsWith : (Ljava/lang/String;)Z
    //   6549: ifne -> 6559
    //   6552: goto -> 6559
    //   6555: invokestatic a : (Ljava/lang/Throwable;)Ljava/lang/Throwable;
    //   6558: athrow
    //   6559: aload #7
    //   6561: iconst_1
    //   6562: invokevirtual setAccessible : (Z)V
    //   6565: aload #7
    //   6567: aconst_null
    //   6568: invokevirtual get : (Ljava/lang/Object;)Ljava/lang/Object;
    //   6571: pop
    //   6572: iinc #6, 1
    //   6575: iload_2
    //   6576: ifne -> 6437
    //   6579: sipush #-13230
    //   6582: sipush #-14925
    //   6585: invokestatic a : (II)Ljava/lang/String;
    //   6588: invokestatic forName : (Ljava/lang/String;)Ljava/lang/Class;
    //   6591: invokevirtual getDeclaredMethods : ()[Ljava/lang/reflect/Method;
    //   6594: astore #4
    //   6596: aload #4
    //   6598: arraylength
    //   6599: istore #5
    //   6601: iconst_0
    //   6602: istore #6
    //   6604: iload #6
    //   6606: iload #5
    //   6608: if_icmpge -> 6741
    //   6611: aload #4
    //   6613: iload #6
    //   6615: aaload
    //   6616: astore #7
    //   6618: aload #7
    //   6620: invokevirtual getParameterTypes : ()[Ljava/lang/Class;
    //   6623: pop
    //   6624: aload #7
    //   6626: invokevirtual getModifiers : ()I
    //   6629: invokestatic isStatic : (I)Z
    //   6632: ifeq -> 6727
    //   6635: aload #7
    //   6637: invokevirtual getParameterTypes : ()[Ljava/lang/Class;
    //   6640: arraylength
    //   6641: iconst_2
    //   6642: if_icmpne -> 6727
    //   6645: goto -> 6652
    //   6648: invokestatic a : (Ljava/lang/Throwable;)Ljava/lang/Throwable;
    //   6651: athrow
    //   6652: aload #7
    //   6654: invokevirtual getReturnType : ()Ljava/lang/Class;
    //   6657: getstatic java/lang/Void.TYPE : Ljava/lang/Class;
    //   6660: invokevirtual equals : (Ljava/lang/Object;)Z
    //   6663: ifeq -> 6727
    //   6666: goto -> 6673
    //   6669: invokestatic a : (Ljava/lang/Throwable;)Ljava/lang/Throwable;
    //   6672: athrow
    //   6673: aload #7
    //   6675: iconst_1
    //   6676: invokevirtual setAccessible : (Z)V
    //   6679: aload #7
    //   6681: aconst_null
    //   6682: iconst_2
    //   6683: anewarray java/lang/Object
    //   6686: dup
    //   6687: iconst_0
    //   6688: aload_0
    //   6689: aastore
    //   6690: dup
    //   6691: iconst_1
    //   6692: aload_1
    //   6693: ifnonnull -> 6711
    //   6696: goto -> 6703
    //   6699: invokestatic a : (Ljava/lang/Throwable;)Ljava/lang/Throwable;
    //   6702: athrow
    //   6703: aload_1
    //   6704: goto -> 6718
    //   6707: invokestatic a : (Ljava/lang/Throwable;)Ljava/lang/Throwable;
    //   6710: athrow
    //   6711: aload_1
    //   6712: checkcast [B
    //   6715: invokevirtual clone : ()Ljava/lang/Object;
    //   6718: aastore
    //   6719: invokevirtual invoke : (Ljava/lang/Object;[Ljava/lang/Object;)Ljava/lang/Object;
    //   6722: pop
    //   6723: iload_2
    //   6724: ifne -> 6741
    //   6727: iinc #6, 1
    //   6730: iload_2
    //   6731: ifne -> 6604
    //   6734: goto -> 6741
    //   6737: invokestatic a : (Ljava/lang/Throwable;)Ljava/lang/Throwable;
    //   6740: athrow
    //   6741: iconst_0
    //   6742: istore #4
    //   6744: sipush #-13218
    //   6747: sipush #12648
    //   6750: invokestatic a : (II)Ljava/lang/String;
    //   6753: iconst_1
    //   6754: ldc burp/Zep1
    //   6756: invokevirtual getClassLoader : ()Ljava/lang/ClassLoader;
    //   6759: invokestatic forName : (Ljava/lang/String;ZLjava/lang/ClassLoader;)Ljava/lang/Class;
    //   6762: invokevirtual getDeclaredFields : ()[Ljava/lang/reflect/Field;
    //   6765: astore #5
    //   6767: aload #5
    //   6769: arraylength
    //   6770: istore #6
    //   6772: iconst_0
    //   6773: istore #7
    //   6775: iload #7
    //   6777: iload #6
    //   6779: if_icmpge -> 6917
    //   6782: aload #5
    //   6784: iload #7
    //   6786: aaload
    //   6787: astore #8
    //   6789: aload #8
    //   6791: invokevirtual getModifiers : ()I
    //   6794: invokestatic isStatic : (I)Z
    //   6797: ifne -> 6807
    //   6800: goto -> 6910
    //   6803: invokestatic a : (Ljava/lang/Throwable;)Ljava/lang/Throwable;
    //   6806: athrow
    //   6807: aload #8
    //   6809: invokevirtual getType : ()Ljava/lang/Class;
    //   6812: astore #9
    //   6814: aload #9
    //   6816: ifnull -> 6897
    //   6819: aload #9
    //   6821: invokevirtual isPrimitive : ()Z
    //   6824: ifne -> 6897
    //   6827: goto -> 6834
    //   6830: invokestatic a : (Ljava/lang/Throwable;)Ljava/lang/Throwable;
    //   6833: athrow
    //   6834: aload #9
    //   6836: invokevirtual getPackage : ()Ljava/lang/Package;
    //   6839: ifnull -> 6897
    //   6842: goto -> 6849
    //   6845: invokestatic a : (Ljava/lang/Throwable;)Ljava/lang/Throwable;
    //   6848: athrow
    //   6849: aload #9
    //   6851: invokevirtual getPackage : ()Ljava/lang/Package;
    //   6854: invokevirtual getName : ()Ljava/lang/String;
    //   6857: ifnull -> 6897
    //   6860: goto -> 6867
    //   6863: invokestatic a : (Ljava/lang/Throwable;)Ljava/lang/Throwable;
    //   6866: athrow
    //   6867: aload #9
    //   6869: invokevirtual getPackage : ()Ljava/lang/Package;
    //   6872: invokevirtual getName : ()Ljava/lang/String;
    //   6875: sipush #-13220
    //   6878: sipush #14021
    //   6881: invokestatic a : (II)Ljava/lang/String;
    //   6884: invokevirtual startsWith : (Ljava/lang/String;)Z
    //   6887: ifne -> 6897
    //   6890: goto -> 6897
    //   6893: invokestatic a : (Ljava/lang/Throwable;)Ljava/lang/Throwable;
    //   6896: athrow
    //   6897: aload #8
    //   6899: iconst_1
    //   6900: invokevirtual setAccessible : (Z)V
    //   6903: aload #8
    //   6905: aconst_null
    //   6906: invokevirtual get : (Ljava/lang/Object;)Ljava/lang/Object;
    //   6909: pop
    //   6910: iinc #7, 1
    //   6913: iload_2
    //   6914: ifne -> 6775
    //   6917: sipush #-13223
    //   6920: sipush #-16483
    //   6923: invokestatic a : (II)Ljava/lang/String;
    //   6926: invokestatic forName : (Ljava/lang/String;)Ljava/lang/Class;
    //   6929: invokevirtual getDeclaredMethods : ()[Ljava/lang/reflect/Method;
    //   6932: astore #5
    //   6934: aload #5
    //   6936: arraylength
    //   6937: istore #6
    //   6939: iconst_0
    //   6940: istore #7
    //   6942: iload #7
    //   6944: iload #6
    //   6946: if_icmpge -> 7083
    //   6949: aload #5
    //   6951: iload #7
    //   6953: aaload
    //   6954: astore #8
    //   6956: aload #8
    //   6958: invokevirtual getParameterTypes : ()[Ljava/lang/Class;
    //   6961: pop
    //   6962: aload #8
    //   6964: invokevirtual getModifiers : ()I
    //   6967: invokestatic isStatic : (I)Z
    //   6970: ifeq -> 7069
    //   6973: aload #8
    //   6975: invokevirtual getParameterTypes : ()[Ljava/lang/Class;
    //   6978: arraylength
    //   6979: iconst_2
    //   6980: if_icmpne -> 7069
    //   6983: goto -> 6990
    //   6986: invokestatic a : (Ljava/lang/Throwable;)Ljava/lang/Throwable;
    //   6989: athrow
    //   6990: aload #8
    //   6992: invokevirtual getReturnType : ()Ljava/lang/Class;
    //   6995: getstatic java/lang/Boolean.TYPE : Ljava/lang/Class;
    //   6998: if_acmpne -> 7069
    //   7001: goto -> 7008
    //   7004: invokestatic a : (Ljava/lang/Throwable;)Ljava/lang/Throwable;
    //   7007: athrow
    //   7008: aload #8
    //   7010: iconst_1
    //   7011: invokevirtual setAccessible : (Z)V
    //   7014: aload #8
    //   7016: aconst_null
    //   7017: iconst_2
    //   7018: anewarray java/lang/Object
    //   7021: dup
    //   7022: iconst_0
    //   7023: aload_0
    //   7024: aastore
    //   7025: dup
    //   7026: iconst_1
    //   7027: aload_1
    //   7028: ifnonnull -> 7046
    //   7031: goto -> 7038
    //   7034: invokestatic a : (Ljava/lang/Throwable;)Ljava/lang/Throwable;
    //   7037: athrow
    //   7038: aload_1
    //   7039: goto -> 7053
    //   7042: invokestatic a : (Ljava/lang/Throwable;)Ljava/lang/Throwable;
    //   7045: athrow
    //   7046: aload_1
    //   7047: checkcast [B
    //   7050: invokevirtual clone : ()Ljava/lang/Object;
    //   7053: aastore
    //   7054: invokevirtual invoke : (Ljava/lang/Object;[Ljava/lang/Object;)Ljava/lang/Object;
    //   7057: checkcast java/lang/Boolean
    //   7060: invokevirtual booleanValue : ()Z
    //   7063: istore #4
    //   7065: iload_2
    //   7066: ifne -> 7083
    //   7069: iinc #7, 1
    //   7072: iload_2
    //   7073: ifne -> 6942
    //   7076: goto -> 7083
    //   7079: invokestatic a : (Ljava/lang/Throwable;)Ljava/lang/Throwable;
    //   7082: athrow
    //   7083: iload #4
    //   7085: ireturn
    //   7086: astore_3
    //   7087: new java/lang/Exception
    //   7090: dup
    //   7091: aload_3
    //   7092: invokevirtual getMessage : ()Ljava/lang/String;
    //   7095: invokespecial <init> : (Ljava/lang/String;)V
    //   7098: athrow
    // Exception table:
    //   from	to	target	type
    //   4	7085	7086	java/lang/Throwable
    //   37	210	213	java/lang/Throwable
    //   180	247	250	java/lang/Throwable
    //   217	284	287	java/lang/Throwable
    //   254	321	324	java/lang/Throwable
    //   291	358	361	java/lang/Throwable
    //   328	395	398	java/lang/Throwable
    //   365	432	435	java/lang/Throwable
    //   402	469	472	java/lang/Throwable
    //   439	506	509	java/lang/Throwable
    //   476	543	546	java/lang/Throwable
    //   513	580	583	java/lang/Throwable
    //   550	617	620	java/lang/Throwable
    //   587	654	657	java/lang/Throwable
    //   624	691	694	java/lang/Throwable
    //   661	728	731	java/lang/Throwable
    //   698	765	768	java/lang/Throwable
    //   735	802	805	java/lang/Throwable
    //   772	839	842	java/lang/Throwable
    //   809	876	879	java/lang/Throwable
    //   846	913	916	java/lang/Throwable
    //   883	950	953	java/lang/Throwable
    //   920	987	990	java/lang/Throwable
    //   957	1024	1027	java/lang/Throwable
    //   994	1061	1064	java/lang/Throwable
    //   1031	1098	1101	java/lang/Throwable
    //   1068	1135	1138	java/lang/Throwable
    //   1105	1172	1175	java/lang/Throwable
    //   1142	1209	1212	java/lang/Throwable
    //   1179	1246	1249	java/lang/Throwable
    //   1216	1283	1286	java/lang/Throwable
    //   1253	1320	1323	java/lang/Throwable
    //   1290	1353	1356	java/lang/Throwable
    //   1686	1710	1713	java/lang/Throwable
    //   1784	1821	1821	java/lang/Throwable
    //   1825	1846	1846	java/lang/Throwable
    //   1850	1880	1880	java/lang/Throwable
    //   6451	6465	6465	java/lang/Throwable
    //   6476	6489	6492	java/lang/Throwable
    //   6481	6504	6507	java/lang/Throwable
    //   6496	6522	6525	java/lang/Throwable
    //   6511	6552	6555	java/lang/Throwable
    //   6618	6645	6648	java/lang/Throwable
    //   6635	6666	6669	java/lang/Throwable
    //   6652	6696	6699	java/lang/Throwable
    //   6673	6707	6707	java/lang/Throwable
    //   6718	6734	6737	java/lang/Throwable
    //   6789	6803	6803	java/lang/Throwable
    //   6814	6827	6830	java/lang/Throwable
    //   6819	6842	6845	java/lang/Throwable
    //   6834	6860	6863	java/lang/Throwable
    //   6849	6890	6893	java/lang/Throwable
    //   6956	6983	6986	java/lang/Throwable
    //   6973	7001	7004	java/lang/Throwable
    //   6990	7031	7034	java/lang/Throwable
    //   7008	7042	7042	java/lang/Throwable
    //   7065	7076	7079	java/lang/Throwable
  }
  
  static void Zl(Object[] paramArrayOfObject, Object paramObject) throws Throwable {}
  
  static {
    // Byte code:
    //   0: bipush #16
    //   2: anewarray java/lang/String
    //   5: astore #5
    //   7: iconst_0
    //   8: istore_3
    //   9: ldc 'Ru2EA,CC4#u3q&atre}Z+/ep!\\t_mi<;=>\\tY+\ \\t$1eM6\\rect<8>+`\\n;=7J.M\\tYxHp nXyC,S} >D9:>t\\f2Kp\\t; E\\t\hj?I\\t %Sj8S|O3;H\\t!c#v\\t)E\\r\\tX|y#r6\\to3Z9'
    //   11: dup
    //   12: astore_2
    //   13: invokevirtual length : ()I
    //   16: istore #4
    //   18: bipush #77
    //   20: istore_1
    //   21: iconst_m1
    //   22: istore_0
    //   23: bipush #9
    //   25: iinc #0, 1
    //   28: aload_2
    //   29: iload_0
    //   30: dup
    //   31: iload_1
    //   32: iadd
    //   33: invokevirtual substring : (II)Ljava/lang/String;
    //   36: iconst_m1
    //   37: goto -> 142
    //   40: aload #5
    //   42: swap
    //   43: iload_3
    //   44: iinc #3, 1
    //   47: swap
    //   48: aastore
    //   49: iload_0
    //   50: iload_1
    //   51: iadd
    //   52: dup
    //   53: istore_0
    //   54: iload #4
    //   56: if_icmpge -> 68
    //   59: aload_2
    //   60: iload_0
    //   61: invokevirtual charAt : (I)C
    //   64: istore_1
    //   65: goto -> 23
    //   68: ldc 't 2DjU7GAr`{+a+'
    //   70: dup
    //   71: astore_2
    //   72: invokevirtual length : ()I
    //   75: istore #4
    //   77: iconst_4
    //   78: istore_1
    //   79: iconst_m1
    //   80: istore_0
    //   81: bipush #18
    //   83: iinc #0, 1
    //   86: aload_2
    //   87: iload_0
    //   88: dup
    //   89: iload_1
    //   90: iadd
    //   91: invokevirtual substring : (II)Ljava/lang/String;
    //   94: iconst_0
    //   95: goto -> 142
    //   98: aload #5
    //   100: swap
    //   101: iload_3
    //   102: iinc #3, 1
    //   105: swap
    //   106: aastore
    //   107: iload_0
    //   108: iload_1
    //   109: iadd
    //   110: dup
    //   111: istore_0
    //   112: iload #4
    //   114: if_icmpge -> 126
    //   117: aload_2
    //   118: iload_0
    //   119: invokevirtual charAt : (I)C
    //   122: istore_1
    //   123: goto -> 81
    //   126: aload #5
    //   128: putstatic burp/Zgia.a : [Ljava/lang/String;
    //   131: bipush #16
    //   133: anewarray java/lang/String
    //   136: putstatic burp/Zgia.b : [Ljava/lang/String;
    //   139: goto -> 300
    //   142: dup_x2
    //   143: pop
    //   144: invokevirtual toCharArray : ()[C
    //   147: dup_x1
    //   148: arraylength
    //   149: dup_x2
    //   150: pop
    //   151: iconst_0
    //   152: istore #6
    //   154: dup2_x1
    //   155: pop2
    //   156: dup_x2
    //   157: iconst_1
    //   158: if_icmpgt -> 260
    //   161: dup2
    //   162: swap
    //   163: iload #6
    //   165: dup2_x1
    //   166: caload
    //   167: swap
    //   168: iload #6
    //   170: bipush #7
    //   172: irem
    //   173: tableswitch default -> 242, 0 -> 212, 1 -> 217, 2 -> 222, 3 -> 227, 4 -> 232, 5 -> 237
    //   212: bipush #117
    //   214: goto -> 244
    //   217: bipush #17
    //   219: goto -> 244
    //   222: bipush #59
    //   224: goto -> 244
    //   227: bipush #28
    //   229: goto -> 244
    //   232: bipush #47
    //   234: goto -> 244
    //   237: bipush #35
    //   239: goto -> 244
    //   242: bipush #25
    //   244: ixor
    //   245: ixor
    //   246: i2c
    //   247: castore
    //   248: iinc #6, 1
    //   251: dup
    //   252: ifne -> 260
    //   255: dup2
    //   256: dup_x1
    //   257: goto -> 165
    //   260: dup2_x1
    //   261: pop2
    //   262: dup_x2
    //   263: iload #6
    //   265: if_icmpgt -> 161
    //   268: pop
    //   269: new java/lang/String
    //   272: dup_x1
    //   273: swap
    //   274: invokespecial <init> : ([C)V
    //   277: invokevirtual intern : ()Ljava/lang/String;
    //   280: swap
    //   281: pop
    //   282: swap
    //   283: tableswitch default -> 40, 0 -> 98
    //   300: new java/math/BigInteger
    //   303: dup
    //   304: sipush #-13224
    //   307: sipush #31508
    //   310: invokestatic a : (II)Ljava/lang/String;
    //   313: invokespecial <init> : (Ljava/lang/String;)V
    //   316: putstatic burp/Zgia.Zx : Ljava/lang/Object;
    //   319: sipush #-13229
    //   322: sipush #-4046
    //   325: invokestatic a : (II)Ljava/lang/String;
    //   328: putstatic burp/Zgia.Zh : Ljava/lang/String;
    //   331: return
  }
  
  private static Throwable a(Throwable paramThrowable) {
    return paramThrowable;
  }
  
  private static String a(int paramInt1, int paramInt2) {
    int i = (paramInt1 ^ 0xFFFFCC5B) & 0xFFFF;
    if (b[i] == null) {
      char[] arrayOfChar = a[i].toCharArray();
      switch (arrayOfChar[0] & 0xFF) {
        case 0:
        
        case 1:
        
        case 2:
        
        case 3:
        
        case 4:
        
        case 5:
        
        case 6:
        
        case 7:
        
        case 8:
        
        case 9:
        
        case 10:
        
        case 11:
        
        case 12:
        
        case 13:
        
        case 14:
        
        case 15:
        
        case 16:
        
        case 17:
        
        case 18:
        
        case 19:
        
        case 20:
        
        case 21:
        
        case 22:
        
        case 23:
        
        case 24:
        
        case 25:
        
        case 26:
        
        case 27:
        
        case 28:
        
        case 29:
        
        case 30:
        
        case 31:
        
        case 32:
        
        case 33:
        
        case 34:
        
        case 35:
        
        case 36:
        
        case 37:
        
        case 38:
        
        case 39:
        
        case 40:
        
        case 41:
        
        case 42:
        
        case 43:
        
        case 44:
        
        case 45:
        
        case 46:
        
        case 47:
        
        case 48:
        
        case 49:
        
        case 50:
        
        case 51:
        
        case 52:
        
        case 53:
        
        case 54:
        
        case 55:
        
        case 56:
        
        case 57:
        
        case 58:
        
        case 59:
        
        case 60:
        
        case 61:
        
        case 62:
        
        case 63:
        
        case 64:
        
        case 65:
        
        case 66:
        
        case 67:
        
        case 68:
        
        case 69:
        
        case 70:
        
        case 71:
        
        case 72:
        
        case 73:
        
        case 74:
        
        case 75:
        
        case 76:
        
        case 77:
        
        case 78:
        
        case 79:
        
        case 80:
        
        case 81:
        
        case 82:
        
        case 83:
        
        case 84:
        
        case 85:
        
        case 86:
        
        case 87:
        
        case 88:
        
        case 89:
        
        case 90:
        
        case 91:
        
        case 92:
        
        case 93:
        
        case 94:
        
        case 95:
        
        case 96:
        
        case 97:
        
        case 98:
        
        case 99:
        
        case 100:
        
        case 101:
        
        case 102:
        
        case 103:
        
        case 104:
        
        case 105:
        
        case 106:
        
        case 107:
        
        case 108:
        
        case 109:
        
        case 110:
        
        case 111:
        
        case 112:
        
        case 113:
        
        case 114:
        
        case 115:
        
        case 116:
        
        case 117:
        
        case 118:
        
        case 119:
        
        case 120:
        
        case 121:
        
        case 122:
        
        case 123:
        
        case 124:
        
        case 125:
        
        case 126:
        
        case 127:
        
        case 128:
        
        case 129:
        
        case 130:
        
        case 131:
        
        case 132:
        
        case 133:
        
        case 134:
        
        case 135:
        
        case 136:
        
        case 137:
        
        case 138:
        
        case 139:
        
        case 140:
        
        case 141:
        
        case 142:
        
        case 143:
        
        case 144:
        
        case 145:
        
        case 146:
        
        case 147:
        
        case 148:
        
        case 149:
        
        case 150:
        
        case 151:
        
        case 152:
        
        case 153:
        
        case 154:
        
        case 155:
        
        case 156:
        
        case 157:
        
        case 158:
        
        case 159:
        
        case 160:
        
        case 161:
        
        case 162:
        
        case 163:
        
        case 164:
        
        case 165:
        
        case 166:
        
        case 167:
        
        case 168:
        
        case 169:
        
        case 170:
        
        case 171:
        
        case 172:
        
        case 173:
        
        case 174:
        
        case 175:
        
        case 176:
        
        case 177:
        
        case 178:
        
        case 179:
        
        case 180:
        
        case 181:
        
        case 182:
        
        case 183:
        
        case 184:
        
        case 185:
        
        case 186:
        
        case 187:
        
        case 188:
        
        case 189:
        
        case 190:
        
        case 191:
        
        case 192:
        
        case 193:
        
        case 194:
        
        case 195:
        
        case 196:
        
        case 197:
        
        case 198:
        
        case 199:
        
        case 200:
        
        case 201:
        
        case 202:
        
        case 203:
        
        case 204:
        
        case 205:
        
        case 206:
        
        case 207:
        
        case 208:
        
        case 209:
        
        case 210:
        
        case 211:
        
        case 212:
        
        case 213:
        
        case 214:
        
        case 215:
        
        case 216:
        
        case 217:
        
        case 218:
        
        case 219:
        
        case 220:
        
        case 221:
        
        case 222:
        
        case 223:
        
        case 224:
        
        case 225:
        
        case 226:
        
        case 227:
        
        case 228:
        
        case 229:
        
        case 230:
        
        case 231:
        
        case 232:
        
        case 233:
        
        case 234:
        
        case 235:
        
        case 236:
        
        case 237:
        
        case 238:
        
        case 239:
        
        case 240:
        
        case 241:
        
        case 242:
        
        case 243:
        
        case 244:
        
        case 245:
        
        case 246:
        
        case 247:
        
        case 248:
        
        case 249:
        
        case 250:
        
        case 251:
        
        case 252:
        
        case 253:
        
        case 254:
        
        default:
          break;
      } 
      byte b1 = 67;
      int j = (paramInt2 & 0xFF) - b1;
      if (j < 0)
        j += 256; 
      int k = ((paramInt2 & 0xFFFF) >>> 8) - b1;
      if (k < 0)
        k += 256; 
      for (byte b2 = 0; b2 < arrayOfChar.length; b2++) {
        int m = b2 % 2;
        if (m == 0) {
          arrayOfChar[b2] = (char)(arrayOfChar[b2] ^ j);
          j = ((j >>> 3 | j << 5) ^ arrayOfChar[b2]) & 0xFF;
        } else {
          arrayOfChar[b2] = (char)(arrayOfChar[b2] ^ k);
          k = ((k >>> 3 | k << 5) ^ arrayOfChar[b2]) & 0xFF;
        } 
      } 
      b[i] = (new String(arrayOfChar)).intern();
    } 
    return b[i];
  }
}


/* Location:              C:\Program Files\BurpSuitePro\burpsuite_pro.jar!\burp\Zgia.class
 * Java compiler version: 21 (65.0)
 * JD-Core Version:       1.1.3
 */