package burp;

import java.math.BigInteger;

class Zgjs extends ClassLoader {
  static Object Za;
  
  static String Zp;
  
  private static final String[] a;
  
  private static final String[] b;
  
  static void ZW(Object paramObject) {
    Ze_0.Zi = a(-31454, -11294);
    Ze_0.ZY = new BigInteger(a(-31439, -3566));
    boolean bool = Zt2e.ZN();
    try {
      try {
        if (Zzri.ZL.charAt(Math.abs(((BigInteger)Zkq9.Ze).intValue() % 32)) <= Zrly.ZS.charAt(Math.abs(((BigInteger)Zlo4.ZC).intValue() % 32))) {
          try {
            Zm84.Zt(Class.forName(a(-31427, 6851)));
            if (!bool)
              Zbo2.Zw(Class.forName(a(-31429, 22700))); 
          } catch (Throwable throwable) {
            throw a(null);
          } 
          return;
        } 
      } catch (Throwable throwable) {
        throw a(null);
      } 
      Zbo2.Zw(Class.forName(a(-31429, 22700)));
    } catch (Throwable throwable) {}
  }
  
  static void ZC(Object[] paramArrayOfObject, Object paramObject) throws Throwable {}
  
  static boolean ZX(Object[] paramArrayOfObject, Object paramObject) throws Throwable {
    // Byte code:
    //   0: invokestatic ZN : ()Z
    //   3: istore_2
    //   4: sipush #-31445
    //   7: sipush #-28459
    //   10: invokestatic a : (II)Ljava/lang/String;
    //   13: invokestatic forName : (Ljava/lang/String;)Ljava/lang/Class;
    //   16: invokestatic Zx : (Ljava/lang/Object;)V
    //   19: getstatic burp/Zl6e.Zo : Ljava/lang/Object;
    //   22: checkcast java/math/BigInteger
    //   25: getstatic burp/Zeqw.ZV : Ljava/lang/Object;
    //   28: checkcast java/math/BigInteger
    //   31: invokevirtual add : (Ljava/math/BigInteger;)Ljava/math/BigInteger;
    //   34: putstatic burp/Zls_.ZR : Ljava/lang/Object;
    //   37: new java/lang/StringBuilder
    //   40: dup
    //   41: invokespecial <init> : ()V
    //   44: astore_3
    //   45: iconst_0
    //   46: istore #4
    //   48: iload #4
    //   50: bipush #32
    //   52: if_icmpge -> 1387
    //   55: iload #4
    //   57: tableswitch default -> 1380, 0 -> 200, 1 -> 237, 2 -> 274, 3 -> 311, 4 -> 348, 5 -> 385, 6 -> 422, 7 -> 459, 8 -> 496, 9 -> 533, 10 -> 570, 11 -> 607, 12 -> 644, 13 -> 681, 14 -> 718, 15 -> 755, 16 -> 792, 17 -> 829, 18 -> 866, 19 -> 903, 20 -> 940, 21 -> 977, 22 -> 1014, 23 -> 1051, 24 -> 1088, 25 -> 1125, 26 -> 1162, 27 -> 1199, 28 -> 1236, 29 -> 1273, 30 -> 1310, 31 -> 1347
    //   200: aload_3
    //   201: getstatic burp/Zg_5.ZG : Ljava/lang/String;
    //   204: getstatic burp/Zzwl.Z_ : Ljava/lang/Object;
    //   207: checkcast java/math/BigInteger
    //   210: invokevirtual intValue : ()I
    //   213: bipush #32
    //   215: irem
    //   216: invokestatic abs : (I)I
    //   219: invokevirtual charAt : (I)C
    //   222: invokevirtual append : (C)Ljava/lang/StringBuilder;
    //   225: pop
    //   226: iload_2
    //   227: ifne -> 1380
    //   230: goto -> 237
    //   233: invokestatic a : (Ljava/lang/Throwable;)Ljava/lang/Throwable;
    //   236: athrow
    //   237: aload_3
    //   238: getstatic burp/Zz80.Ze : Ljava/lang/String;
    //   241: getstatic burp/Ztp.Zp : Ljava/lang/Object;
    //   244: checkcast java/math/BigInteger
    //   247: invokevirtual intValue : ()I
    //   250: bipush #32
    //   252: irem
    //   253: invokestatic abs : (I)I
    //   256: invokevirtual charAt : (I)C
    //   259: invokevirtual append : (C)Ljava/lang/StringBuilder;
    //   262: pop
    //   263: iload_2
    //   264: ifne -> 1380
    //   267: goto -> 274
    //   270: invokestatic a : (Ljava/lang/Throwable;)Ljava/lang/Throwable;
    //   273: athrow
    //   274: aload_3
    //   275: getstatic burp/Zezz.Zi : Ljava/lang/String;
    //   278: getstatic burp/Zk7w.ZF : Ljava/lang/Object;
    //   281: checkcast java/math/BigInteger
    //   284: invokevirtual intValue : ()I
    //   287: bipush #32
    //   289: irem
    //   290: invokestatic abs : (I)I
    //   293: invokevirtual charAt : (I)C
    //   296: invokevirtual append : (C)Ljava/lang/StringBuilder;
    //   299: pop
    //   300: iload_2
    //   301: ifne -> 1380
    //   304: goto -> 311
    //   307: invokestatic a : (Ljava/lang/Throwable;)Ljava/lang/Throwable;
    //   310: athrow
    //   311: aload_3
    //   312: getstatic burp/Zm06.Zg : Ljava/lang/String;
    //   315: getstatic burp/Zty5.Zf : Ljava/lang/Object;
    //   318: checkcast java/math/BigInteger
    //   321: invokevirtual intValue : ()I
    //   324: bipush #32
    //   326: irem
    //   327: invokestatic abs : (I)I
    //   330: invokevirtual charAt : (I)C
    //   333: invokevirtual append : (C)Ljava/lang/StringBuilder;
    //   336: pop
    //   337: iload_2
    //   338: ifne -> 1380
    //   341: goto -> 348
    //   344: invokestatic a : (Ljava/lang/Throwable;)Ljava/lang/Throwable;
    //   347: athrow
    //   348: aload_3
    //   349: getstatic burp/Zr0g.Zf : Ljava/lang/String;
    //   352: getstatic burp/Zshq.ZK : Ljava/lang/Object;
    //   355: checkcast java/math/BigInteger
    //   358: invokevirtual intValue : ()I
    //   361: bipush #32
    //   363: irem
    //   364: invokestatic abs : (I)I
    //   367: invokevirtual charAt : (I)C
    //   370: invokevirtual append : (C)Ljava/lang/StringBuilder;
    //   373: pop
    //   374: iload_2
    //   375: ifne -> 1380
    //   378: goto -> 385
    //   381: invokestatic a : (Ljava/lang/Throwable;)Ljava/lang/Throwable;
    //   384: athrow
    //   385: aload_3
    //   386: getstatic burp/Zs0b.ZT : Ljava/lang/String;
    //   389: getstatic burp/Zxe.Zg : Ljava/lang/Object;
    //   392: checkcast java/math/BigInteger
    //   395: invokevirtual intValue : ()I
    //   398: bipush #32
    //   400: irem
    //   401: invokestatic abs : (I)I
    //   404: invokevirtual charAt : (I)C
    //   407: invokevirtual append : (C)Ljava/lang/StringBuilder;
    //   410: pop
    //   411: iload_2
    //   412: ifne -> 1380
    //   415: goto -> 422
    //   418: invokestatic a : (Ljava/lang/Throwable;)Ljava/lang/Throwable;
    //   421: athrow
    //   422: aload_3
    //   423: getstatic burp/Zltb.ZO : Ljava/lang/String;
    //   426: getstatic burp/Zgco.Zx : Ljava/lang/Object;
    //   429: checkcast java/math/BigInteger
    //   432: invokevirtual intValue : ()I
    //   435: bipush #32
    //   437: irem
    //   438: invokestatic abs : (I)I
    //   441: invokevirtual charAt : (I)C
    //   444: invokevirtual append : (C)Ljava/lang/StringBuilder;
    //   447: pop
    //   448: iload_2
    //   449: ifne -> 1380
    //   452: goto -> 459
    //   455: invokestatic a : (Ljava/lang/Throwable;)Ljava/lang/Throwable;
    //   458: athrow
    //   459: aload_3
    //   460: getstatic burp/Zty2.ZR : Ljava/lang/String;
    //   463: getstatic burp/Zx5w.Zo : Ljava/lang/Object;
    //   466: checkcast java/math/BigInteger
    //   469: invokevirtual intValue : ()I
    //   472: bipush #32
    //   474: irem
    //   475: invokestatic abs : (I)I
    //   478: invokevirtual charAt : (I)C
    //   481: invokevirtual append : (C)Ljava/lang/StringBuilder;
    //   484: pop
    //   485: iload_2
    //   486: ifne -> 1380
    //   489: goto -> 496
    //   492: invokestatic a : (Ljava/lang/Throwable;)Ljava/lang/Throwable;
    //   495: athrow
    //   496: aload_3
    //   497: getstatic burp/Ztnw.Zr : Ljava/lang/String;
    //   500: getstatic burp/Zgss.Zl : Ljava/lang/Object;
    //   503: checkcast java/math/BigInteger
    //   506: invokevirtual intValue : ()I
    //   509: bipush #32
    //   511: irem
    //   512: invokestatic abs : (I)I
    //   515: invokevirtual charAt : (I)C
    //   518: invokevirtual append : (C)Ljava/lang/StringBuilder;
    //   521: pop
    //   522: iload_2
    //   523: ifne -> 1380
    //   526: goto -> 533
    //   529: invokestatic a : (Ljava/lang/Throwable;)Ljava/lang/Throwable;
    //   532: athrow
    //   533: aload_3
    //   534: getstatic burp/Zrd3.Z_ : Ljava/lang/String;
    //   537: getstatic burp/Zzoc.Zx : Ljava/lang/Object;
    //   540: checkcast java/math/BigInteger
    //   543: invokevirtual intValue : ()I
    //   546: bipush #32
    //   548: irem
    //   549: invokestatic abs : (I)I
    //   552: invokevirtual charAt : (I)C
    //   555: invokevirtual append : (C)Ljava/lang/StringBuilder;
    //   558: pop
    //   559: iload_2
    //   560: ifne -> 1380
    //   563: goto -> 570
    //   566: invokestatic a : (Ljava/lang/Throwable;)Ljava/lang/Throwable;
    //   569: athrow
    //   570: aload_3
    //   571: getstatic burp/Zs8s.Za : Ljava/lang/String;
    //   574: getstatic burp/Zzxv.ZZ : Ljava/lang/Object;
    //   577: checkcast java/math/BigInteger
    //   580: invokevirtual intValue : ()I
    //   583: bipush #32
    //   585: irem
    //   586: invokestatic abs : (I)I
    //   589: invokevirtual charAt : (I)C
    //   592: invokevirtual append : (C)Ljava/lang/StringBuilder;
    //   595: pop
    //   596: iload_2
    //   597: ifne -> 1380
    //   600: goto -> 607
    //   603: invokestatic a : (Ljava/lang/Throwable;)Ljava/lang/Throwable;
    //   606: athrow
    //   607: aload_3
    //   608: getstatic burp/Zx54.Zs : Ljava/lang/String;
    //   611: getstatic burp/Zldx.ZM : Ljava/lang/Object;
    //   614: checkcast java/math/BigInteger
    //   617: invokevirtual intValue : ()I
    //   620: bipush #32
    //   622: irem
    //   623: invokestatic abs : (I)I
    //   626: invokevirtual charAt : (I)C
    //   629: invokevirtual append : (C)Ljava/lang/StringBuilder;
    //   632: pop
    //   633: iload_2
    //   634: ifne -> 1380
    //   637: goto -> 644
    //   640: invokestatic a : (Ljava/lang/Throwable;)Ljava/lang/Throwable;
    //   643: athrow
    //   644: aload_3
    //   645: getstatic burp/Ztd6.Zu : Ljava/lang/String;
    //   648: getstatic burp/Zlo2.ZM : Ljava/lang/Object;
    //   651: checkcast java/math/BigInteger
    //   654: invokevirtual intValue : ()I
    //   657: bipush #32
    //   659: irem
    //   660: invokestatic abs : (I)I
    //   663: invokevirtual charAt : (I)C
    //   666: invokevirtual append : (C)Ljava/lang/StringBuilder;
    //   669: pop
    //   670: iload_2
    //   671: ifne -> 1380
    //   674: goto -> 681
    //   677: invokestatic a : (Ljava/lang/Throwable;)Ljava/lang/Throwable;
    //   680: athrow
    //   681: aload_3
    //   682: getstatic burp/Zzb2.ZJ : Ljava/lang/String;
    //   685: getstatic burp/Zr8g.ZF : Ljava/lang/Object;
    //   688: checkcast java/math/BigInteger
    //   691: invokevirtual intValue : ()I
    //   694: bipush #32
    //   696: irem
    //   697: invokestatic abs : (I)I
    //   700: invokevirtual charAt : (I)C
    //   703: invokevirtual append : (C)Ljava/lang/StringBuilder;
    //   706: pop
    //   707: iload_2
    //   708: ifne -> 1380
    //   711: goto -> 718
    //   714: invokestatic a : (Ljava/lang/Throwable;)Ljava/lang/Throwable;
    //   717: athrow
    //   718: aload_3
    //   719: getstatic burp/Zzlg.Zw : Ljava/lang/String;
    //   722: getstatic burp/Zgta.ZF : Ljava/lang/Object;
    //   725: checkcast java/math/BigInteger
    //   728: invokevirtual intValue : ()I
    //   731: bipush #32
    //   733: irem
    //   734: invokestatic abs : (I)I
    //   737: invokevirtual charAt : (I)C
    //   740: invokevirtual append : (C)Ljava/lang/StringBuilder;
    //   743: pop
    //   744: iload_2
    //   745: ifne -> 1380
    //   748: goto -> 755
    //   751: invokestatic a : (Ljava/lang/Throwable;)Ljava/lang/Throwable;
    //   754: athrow
    //   755: aload_3
    //   756: getstatic burp/Zr8s.ZA : Ljava/lang/String;
    //   759: getstatic burp/Zlvx.ZM : Ljava/lang/Object;
    //   762: checkcast java/math/BigInteger
    //   765: invokevirtual intValue : ()I
    //   768: bipush #32
    //   770: irem
    //   771: invokestatic abs : (I)I
    //   774: invokevirtual charAt : (I)C
    //   777: invokevirtual append : (C)Ljava/lang/StringBuilder;
    //   780: pop
    //   781: iload_2
    //   782: ifne -> 1380
    //   785: goto -> 792
    //   788: invokestatic a : (Ljava/lang/Throwable;)Ljava/lang/Throwable;
    //   791: athrow
    //   792: aload_3
    //   793: getstatic burp/Zrka.Zy : Ljava/lang/String;
    //   796: getstatic burp/Zel.ZB : Ljava/lang/Object;
    //   799: checkcast java/math/BigInteger
    //   802: invokevirtual intValue : ()I
    //   805: bipush #32
    //   807: irem
    //   808: invokestatic abs : (I)I
    //   811: invokevirtual charAt : (I)C
    //   814: invokevirtual append : (C)Ljava/lang/StringBuilder;
    //   817: pop
    //   818: iload_2
    //   819: ifne -> 1380
    //   822: goto -> 829
    //   825: invokestatic a : (Ljava/lang/Throwable;)Ljava/lang/Throwable;
    //   828: athrow
    //   829: aload_3
    //   830: getstatic burp/Zewq.ZV : Ljava/lang/String;
    //   833: getstatic burp/Zzah.Za : Ljava/lang/Object;
    //   836: checkcast java/math/BigInteger
    //   839: invokevirtual intValue : ()I
    //   842: bipush #32
    //   844: irem
    //   845: invokestatic abs : (I)I
    //   848: invokevirtual charAt : (I)C
    //   851: invokevirtual append : (C)Ljava/lang/StringBuilder;
    //   854: pop
    //   855: iload_2
    //   856: ifne -> 1380
    //   859: goto -> 866
    //   862: invokestatic a : (Ljava/lang/Throwable;)Ljava/lang/Throwable;
    //   865: athrow
    //   866: aload_3
    //   867: getstatic burp/Ze6k.ZM : Ljava/lang/String;
    //   870: getstatic burp/Zrxf.ZS : Ljava/lang/Object;
    //   873: checkcast java/math/BigInteger
    //   876: invokevirtual intValue : ()I
    //   879: bipush #32
    //   881: irem
    //   882: invokestatic abs : (I)I
    //   885: invokevirtual charAt : (I)C
    //   888: invokevirtual append : (C)Ljava/lang/StringBuilder;
    //   891: pop
    //   892: iload_2
    //   893: ifne -> 1380
    //   896: goto -> 903
    //   899: invokestatic a : (Ljava/lang/Throwable;)Ljava/lang/Throwable;
    //   902: athrow
    //   903: aload_3
    //   904: getstatic burp/Zsq6.Zm : Ljava/lang/String;
    //   907: getstatic burp/Zmjw.ZD : Ljava/lang/Object;
    //   910: checkcast java/math/BigInteger
    //   913: invokevirtual intValue : ()I
    //   916: bipush #32
    //   918: irem
    //   919: invokestatic abs : (I)I
    //   922: invokevirtual charAt : (I)C
    //   925: invokevirtual append : (C)Ljava/lang/StringBuilder;
    //   928: pop
    //   929: iload_2
    //   930: ifne -> 1380
    //   933: goto -> 940
    //   936: invokestatic a : (Ljava/lang/Throwable;)Ljava/lang/Throwable;
    //   939: athrow
    //   940: aload_3
    //   941: getstatic burp/Zrx5.ZD : Ljava/lang/String;
    //   944: getstatic burp/Zzef.Zw : Ljava/lang/Object;
    //   947: checkcast java/math/BigInteger
    //   950: invokevirtual intValue : ()I
    //   953: bipush #32
    //   955: irem
    //   956: invokestatic abs : (I)I
    //   959: invokevirtual charAt : (I)C
    //   962: invokevirtual append : (C)Ljava/lang/StringBuilder;
    //   965: pop
    //   966: iload_2
    //   967: ifne -> 1380
    //   970: goto -> 977
    //   973: invokestatic a : (Ljava/lang/Throwable;)Ljava/lang/Throwable;
    //   976: athrow
    //   977: aload_3
    //   978: getstatic burp/Zltb.ZO : Ljava/lang/String;
    //   981: getstatic burp/Zk9s.ZY : Ljava/lang/Object;
    //   984: checkcast java/math/BigInteger
    //   987: invokevirtual intValue : ()I
    //   990: bipush #32
    //   992: irem
    //   993: invokestatic abs : (I)I
    //   996: invokevirtual charAt : (I)C
    //   999: invokevirtual append : (C)Ljava/lang/StringBuilder;
    //   1002: pop
    //   1003: iload_2
    //   1004: ifne -> 1380
    //   1007: goto -> 1014
    //   1010: invokestatic a : (Ljava/lang/Throwable;)Ljava/lang/Throwable;
    //   1013: athrow
    //   1014: aload_3
    //   1015: getstatic burp/Zb1.Z_ : Ljava/lang/String;
    //   1018: getstatic burp/Zb8y.ZI : Ljava/lang/Object;
    //   1021: checkcast java/math/BigInteger
    //   1024: invokevirtual intValue : ()I
    //   1027: bipush #32
    //   1029: irem
    //   1030: invokestatic abs : (I)I
    //   1033: invokevirtual charAt : (I)C
    //   1036: invokevirtual append : (C)Ljava/lang/StringBuilder;
    //   1039: pop
    //   1040: iload_2
    //   1041: ifne -> 1380
    //   1044: goto -> 1051
    //   1047: invokestatic a : (Ljava/lang/Throwable;)Ljava/lang/Throwable;
    //   1050: athrow
    //   1051: aload_3
    //   1052: getstatic burp/Zkaw.ZI : Ljava/lang/String;
    //   1055: getstatic burp/Zm06.ZU : Ljava/lang/Object;
    //   1058: checkcast java/math/BigInteger
    //   1061: invokevirtual intValue : ()I
    //   1064: bipush #32
    //   1066: irem
    //   1067: invokestatic abs : (I)I
    //   1070: invokevirtual charAt : (I)C
    //   1073: invokevirtual append : (C)Ljava/lang/StringBuilder;
    //   1076: pop
    //   1077: iload_2
    //   1078: ifne -> 1380
    //   1081: goto -> 1088
    //   1084: invokestatic a : (Ljava/lang/Throwable;)Ljava/lang/Throwable;
    //   1087: athrow
    //   1088: aload_3
    //   1089: getstatic burp/Ze_l.ZY : Ljava/lang/String;
    //   1092: getstatic burp/Zgr1.Zf : Ljava/lang/Object;
    //   1095: checkcast java/math/BigInteger
    //   1098: invokevirtual intValue : ()I
    //   1101: bipush #32
    //   1103: irem
    //   1104: invokestatic abs : (I)I
    //   1107: invokevirtual charAt : (I)C
    //   1110: invokevirtual append : (C)Ljava/lang/StringBuilder;
    //   1113: pop
    //   1114: iload_2
    //   1115: ifne -> 1380
    //   1118: goto -> 1125
    //   1121: invokestatic a : (Ljava/lang/Throwable;)Ljava/lang/Throwable;
    //   1124: athrow
    //   1125: aload_3
    //   1126: getstatic burp/Zlw8.Zs : Ljava/lang/String;
    //   1129: getstatic burp/Zrj3.ZA : Ljava/lang/Object;
    //   1132: checkcast java/math/BigInteger
    //   1135: invokevirtual intValue : ()I
    //   1138: bipush #32
    //   1140: irem
    //   1141: invokestatic abs : (I)I
    //   1144: invokevirtual charAt : (I)C
    //   1147: invokevirtual append : (C)Ljava/lang/StringBuilder;
    //   1150: pop
    //   1151: iload_2
    //   1152: ifne -> 1380
    //   1155: goto -> 1162
    //   1158: invokestatic a : (Ljava/lang/Throwable;)Ljava/lang/Throwable;
    //   1161: athrow
    //   1162: aload_3
    //   1163: getstatic burp/Zgdt.Zd : Ljava/lang/String;
    //   1166: getstatic burp/Zs0h.ZU : Ljava/lang/Object;
    //   1169: checkcast java/math/BigInteger
    //   1172: invokevirtual intValue : ()I
    //   1175: bipush #32
    //   1177: irem
    //   1178: invokestatic abs : (I)I
    //   1181: invokevirtual charAt : (I)C
    //   1184: invokevirtual append : (C)Ljava/lang/StringBuilder;
    //   1187: pop
    //   1188: iload_2
    //   1189: ifne -> 1380
    //   1192: goto -> 1199
    //   1195: invokestatic a : (Ljava/lang/Throwable;)Ljava/lang/Throwable;
    //   1198: athrow
    //   1199: aload_3
    //   1200: getstatic burp/Zt7x.Zu : Ljava/lang/String;
    //   1203: getstatic burp/Zt4g.Zv : Ljava/lang/Object;
    //   1206: checkcast java/math/BigInteger
    //   1209: invokevirtual intValue : ()I
    //   1212: bipush #32
    //   1214: irem
    //   1215: invokestatic abs : (I)I
    //   1218: invokevirtual charAt : (I)C
    //   1221: invokevirtual append : (C)Ljava/lang/StringBuilder;
    //   1224: pop
    //   1225: iload_2
    //   1226: ifne -> 1380
    //   1229: goto -> 1236
    //   1232: invokestatic a : (Ljava/lang/Throwable;)Ljava/lang/Throwable;
    //   1235: athrow
    //   1236: aload_3
    //   1237: getstatic burp/Zs_3.ZC : Ljava/lang/String;
    //   1240: getstatic burp/Ztdd.ZD : Ljava/lang/Object;
    //   1243: checkcast java/math/BigInteger
    //   1246: invokevirtual intValue : ()I
    //   1249: bipush #32
    //   1251: irem
    //   1252: invokestatic abs : (I)I
    //   1255: invokevirtual charAt : (I)C
    //   1258: invokevirtual append : (C)Ljava/lang/StringBuilder;
    //   1261: pop
    //   1262: iload_2
    //   1263: ifne -> 1380
    //   1266: goto -> 1273
    //   1269: invokestatic a : (Ljava/lang/Throwable;)Ljava/lang/Throwable;
    //   1272: athrow
    //   1273: aload_3
    //   1274: getstatic burp/Zgp_.Zn : Ljava/lang/String;
    //   1277: getstatic burp/Zrf9.Zu : Ljava/lang/Object;
    //   1280: checkcast java/math/BigInteger
    //   1283: invokevirtual intValue : ()I
    //   1286: bipush #32
    //   1288: irem
    //   1289: invokestatic abs : (I)I
    //   1292: invokevirtual charAt : (I)C
    //   1295: invokevirtual append : (C)Ljava/lang/StringBuilder;
    //   1298: pop
    //   1299: iload_2
    //   1300: ifne -> 1380
    //   1303: goto -> 1310
    //   1306: invokestatic a : (Ljava/lang/Throwable;)Ljava/lang/Throwable;
    //   1309: athrow
    //   1310: aload_3
    //   1311: getstatic burp/Zl_9.ZP : Ljava/lang/String;
    //   1314: getstatic burp/Zm54.ZS : Ljava/lang/Object;
    //   1317: checkcast java/math/BigInteger
    //   1320: invokevirtual intValue : ()I
    //   1323: bipush #32
    //   1325: irem
    //   1326: invokestatic abs : (I)I
    //   1329: invokevirtual charAt : (I)C
    //   1332: invokevirtual append : (C)Ljava/lang/StringBuilder;
    //   1335: pop
    //   1336: iload_2
    //   1337: ifne -> 1380
    //   1340: goto -> 1347
    //   1343: invokestatic a : (Ljava/lang/Throwable;)Ljava/lang/Throwable;
    //   1346: athrow
    //   1347: aload_3
    //   1348: getstatic burp/Zenq.ZG : Ljava/lang/String;
    //   1351: getstatic burp/Zrd0.Zs : Ljava/lang/Object;
    //   1354: checkcast java/math/BigInteger
    //   1357: invokevirtual intValue : ()I
    //   1360: bipush #32
    //   1362: irem
    //   1363: invokestatic abs : (I)I
    //   1366: invokevirtual charAt : (I)C
    //   1369: invokevirtual append : (C)Ljava/lang/StringBuilder;
    //   1372: pop
    //   1373: goto -> 1380
    //   1376: invokestatic a : (Ljava/lang/Throwable;)Ljava/lang/Throwable;
    //   1379: athrow
    //   1380: iinc #4, 1
    //   1383: iload_2
    //   1384: ifne -> 48
    //   1387: aload_3
    //   1388: invokevirtual toString : ()Ljava/lang/String;
    //   1391: putstatic burp/Ze4x.Zk : Ljava/lang/String;
    //   1394: getstatic burp/Zb6a.Zz : Ljava/lang/Object;
    //   1397: checkcast java/math/BigInteger
    //   1400: invokevirtual toByteArray : ()[B
    //   1403: astore #4
    //   1405: bipush #64
    //   1407: newarray byte
    //   1409: dup
    //   1410: iconst_0
    //   1411: bipush #-128
    //   1413: bastore
    //   1414: dup
    //   1415: iconst_1
    //   1416: iconst_0
    //   1417: bastore
    //   1418: dup
    //   1419: iconst_2
    //   1420: iconst_0
    //   1421: bastore
    //   1422: dup
    //   1423: iconst_3
    //   1424: iconst_0
    //   1425: bastore
    //   1426: dup
    //   1427: iconst_4
    //   1428: iconst_0
    //   1429: bastore
    //   1430: dup
    //   1431: iconst_5
    //   1432: iconst_0
    //   1433: bastore
    //   1434: dup
    //   1435: bipush #6
    //   1437: iconst_0
    //   1438: bastore
    //   1439: dup
    //   1440: bipush #7
    //   1442: iconst_0
    //   1443: bastore
    //   1444: dup
    //   1445: bipush #8
    //   1447: iconst_0
    //   1448: bastore
    //   1449: dup
    //   1450: bipush #9
    //   1452: iconst_0
    //   1453: bastore
    //   1454: dup
    //   1455: bipush #10
    //   1457: iconst_0
    //   1458: bastore
    //   1459: dup
    //   1460: bipush #11
    //   1462: iconst_0
    //   1463: bastore
    //   1464: dup
    //   1465: bipush #12
    //   1467: iconst_0
    //   1468: bastore
    //   1469: dup
    //   1470: bipush #13
    //   1472: iconst_0
    //   1473: bastore
    //   1474: dup
    //   1475: bipush #14
    //   1477: iconst_0
    //   1478: bastore
    //   1479: dup
    //   1480: bipush #15
    //   1482: iconst_0
    //   1483: bastore
    //   1484: dup
    //   1485: bipush #16
    //   1487: iconst_0
    //   1488: bastore
    //   1489: dup
    //   1490: bipush #17
    //   1492: iconst_0
    //   1493: bastore
    //   1494: dup
    //   1495: bipush #18
    //   1497: iconst_0
    //   1498: bastore
    //   1499: dup
    //   1500: bipush #19
    //   1502: iconst_0
    //   1503: bastore
    //   1504: dup
    //   1505: bipush #20
    //   1507: iconst_0
    //   1508: bastore
    //   1509: dup
    //   1510: bipush #21
    //   1512: iconst_0
    //   1513: bastore
    //   1514: dup
    //   1515: bipush #22
    //   1517: iconst_0
    //   1518: bastore
    //   1519: dup
    //   1520: bipush #23
    //   1522: iconst_0
    //   1523: bastore
    //   1524: dup
    //   1525: bipush #24
    //   1527: iconst_0
    //   1528: bastore
    //   1529: dup
    //   1530: bipush #25
    //   1532: iconst_0
    //   1533: bastore
    //   1534: dup
    //   1535: bipush #26
    //   1537: iconst_0
    //   1538: bastore
    //   1539: dup
    //   1540: bipush #27
    //   1542: iconst_0
    //   1543: bastore
    //   1544: dup
    //   1545: bipush #28
    //   1547: iconst_0
    //   1548: bastore
    //   1549: dup
    //   1550: bipush #29
    //   1552: iconst_0
    //   1553: bastore
    //   1554: dup
    //   1555: bipush #30
    //   1557: iconst_0
    //   1558: bastore
    //   1559: dup
    //   1560: bipush #31
    //   1562: iconst_0
    //   1563: bastore
    //   1564: dup
    //   1565: bipush #32
    //   1567: iconst_0
    //   1568: bastore
    //   1569: dup
    //   1570: bipush #33
    //   1572: iconst_0
    //   1573: bastore
    //   1574: dup
    //   1575: bipush #34
    //   1577: iconst_0
    //   1578: bastore
    //   1579: dup
    //   1580: bipush #35
    //   1582: iconst_0
    //   1583: bastore
    //   1584: dup
    //   1585: bipush #36
    //   1587: iconst_0
    //   1588: bastore
    //   1589: dup
    //   1590: bipush #37
    //   1592: iconst_0
    //   1593: bastore
    //   1594: dup
    //   1595: bipush #38
    //   1597: iconst_0
    //   1598: bastore
    //   1599: dup
    //   1600: bipush #39
    //   1602: iconst_0
    //   1603: bastore
    //   1604: dup
    //   1605: bipush #40
    //   1607: iconst_0
    //   1608: bastore
    //   1609: dup
    //   1610: bipush #41
    //   1612: iconst_0
    //   1613: bastore
    //   1614: dup
    //   1615: bipush #42
    //   1617: iconst_0
    //   1618: bastore
    //   1619: dup
    //   1620: bipush #43
    //   1622: iconst_0
    //   1623: bastore
    //   1624: dup
    //   1625: bipush #44
    //   1627: iconst_0
    //   1628: bastore
    //   1629: dup
    //   1630: bipush #45
    //   1632: iconst_0
    //   1633: bastore
    //   1634: dup
    //   1635: bipush #46
    //   1637: iconst_0
    //   1638: bastore
    //   1639: dup
    //   1640: bipush #47
    //   1642: iconst_0
    //   1643: bastore
    //   1644: dup
    //   1645: bipush #48
    //   1647: iconst_0
    //   1648: bastore
    //   1649: dup
    //   1650: bipush #49
    //   1652: iconst_0
    //   1653: bastore
    //   1654: dup
    //   1655: bipush #50
    //   1657: iconst_0
    //   1658: bastore
    //   1659: dup
    //   1660: bipush #51
    //   1662: iconst_0
    //   1663: bastore
    //   1664: dup
    //   1665: bipush #52
    //   1667: iconst_0
    //   1668: bastore
    //   1669: dup
    //   1670: bipush #53
    //   1672: iconst_0
    //   1673: bastore
    //   1674: dup
    //   1675: bipush #54
    //   1677: iconst_0
    //   1678: bastore
    //   1679: dup
    //   1680: bipush #55
    //   1682: iconst_0
    //   1683: bastore
    //   1684: dup
    //   1685: bipush #56
    //   1687: iconst_0
    //   1688: bastore
    //   1689: dup
    //   1690: bipush #57
    //   1692: iconst_0
    //   1693: bastore
    //   1694: dup
    //   1695: bipush #58
    //   1697: iconst_0
    //   1698: bastore
    //   1699: dup
    //   1700: bipush #59
    //   1702: iconst_0
    //   1703: bastore
    //   1704: dup
    //   1705: bipush #60
    //   1707: iconst_0
    //   1708: bastore
    //   1709: dup
    //   1710: bipush #61
    //   1712: iconst_0
    //   1713: bastore
    //   1714: dup
    //   1715: bipush #62
    //   1717: iconst_0
    //   1718: bastore
    //   1719: dup
    //   1720: bipush #63
    //   1722: iconst_0
    //   1723: bastore
    //   1724: astore #6
    //   1726: bipush #64
    //   1728: newarray int
    //   1730: dup
    //   1731: iconst_0
    //   1732: ldc 1116352408
    //   1734: iastore
    //   1735: dup
    //   1736: iconst_1
    //   1737: ldc 1899447441
    //   1739: iastore
    //   1740: dup
    //   1741: iconst_2
    //   1742: ldc -1245643825
    //   1744: iastore
    //   1745: dup
    //   1746: iconst_3
    //   1747: ldc -373957723
    //   1749: iastore
    //   1750: dup
    //   1751: iconst_4
    //   1752: ldc 961987163
    //   1754: iastore
    //   1755: dup
    //   1756: iconst_5
    //   1757: ldc 1508970993
    //   1759: iastore
    //   1760: dup
    //   1761: bipush #6
    //   1763: ldc -1841331548
    //   1765: iastore
    //   1766: dup
    //   1767: bipush #7
    //   1769: ldc -1424204075
    //   1771: iastore
    //   1772: dup
    //   1773: bipush #8
    //   1775: ldc -670586216
    //   1777: iastore
    //   1778: dup
    //   1779: bipush #9
    //   1781: ldc 310598401
    //   1783: iastore
    //   1784: dup
    //   1785: bipush #10
    //   1787: ldc 607225278
    //   1789: iastore
    //   1790: dup
    //   1791: bipush #11
    //   1793: ldc 1426881987
    //   1795: iastore
    //   1796: dup
    //   1797: bipush #12
    //   1799: ldc 1925078388
    //   1801: iastore
    //   1802: dup
    //   1803: bipush #13
    //   1805: ldc -2132889090
    //   1807: iastore
    //   1808: dup
    //   1809: bipush #14
    //   1811: ldc -1680079193
    //   1813: iastore
    //   1814: dup
    //   1815: bipush #15
    //   1817: ldc -1046744716
    //   1819: iastore
    //   1820: dup
    //   1821: bipush #16
    //   1823: ldc -459576895
    //   1825: iastore
    //   1826: dup
    //   1827: bipush #17
    //   1829: ldc -272742522
    //   1831: iastore
    //   1832: dup
    //   1833: bipush #18
    //   1835: ldc 264347078
    //   1837: iastore
    //   1838: dup
    //   1839: bipush #19
    //   1841: ldc 604807628
    //   1843: iastore
    //   1844: dup
    //   1845: bipush #20
    //   1847: ldc 770255983
    //   1849: iastore
    //   1850: dup
    //   1851: bipush #21
    //   1853: ldc 1249150122
    //   1855: iastore
    //   1856: dup
    //   1857: bipush #22
    //   1859: ldc 1555081692
    //   1861: iastore
    //   1862: dup
    //   1863: bipush #23
    //   1865: ldc 1996064986
    //   1867: iastore
    //   1868: dup
    //   1869: bipush #24
    //   1871: ldc -1740746414
    //   1873: iastore
    //   1874: dup
    //   1875: bipush #25
    //   1877: ldc -1473132947
    //   1879: iastore
    //   1880: dup
    //   1881: bipush #26
    //   1883: ldc -1341970488
    //   1885: iastore
    //   1886: dup
    //   1887: bipush #27
    //   1889: ldc -1084653625
    //   1891: iastore
    //   1892: dup
    //   1893: bipush #28
    //   1895: ldc -958395405
    //   1897: iastore
    //   1898: dup
    //   1899: bipush #29
    //   1901: ldc -710438585
    //   1903: iastore
    //   1904: dup
    //   1905: bipush #30
    //   1907: ldc 113926993
    //   1909: iastore
    //   1910: dup
    //   1911: bipush #31
    //   1913: ldc 338241895
    //   1915: iastore
    //   1916: dup
    //   1917: bipush #32
    //   1919: ldc 666307205
    //   1921: iastore
    //   1922: dup
    //   1923: bipush #33
    //   1925: ldc 773529912
    //   1927: iastore
    //   1928: dup
    //   1929: bipush #34
    //   1931: ldc 1294757372
    //   1933: iastore
    //   1934: dup
    //   1935: bipush #35
    //   1937: ldc 1396182291
    //   1939: iastore
    //   1940: dup
    //   1941: bipush #36
    //   1943: ldc 1695183700
    //   1945: iastore
    //   1946: dup
    //   1947: bipush #37
    //   1949: ldc 1986661051
    //   1951: iastore
    //   1952: dup
    //   1953: bipush #38
    //   1955: ldc -2117940946
    //   1957: iastore
    //   1958: dup
    //   1959: bipush #39
    //   1961: ldc -1838011259
    //   1963: iastore
    //   1964: dup
    //   1965: bipush #40
    //   1967: ldc -1564481375
    //   1969: iastore
    //   1970: dup
    //   1971: bipush #41
    //   1973: ldc -1474664885
    //   1975: iastore
    //   1976: dup
    //   1977: bipush #42
    //   1979: ldc -1035236496
    //   1981: iastore
    //   1982: dup
    //   1983: bipush #43
    //   1985: ldc -949202525
    //   1987: iastore
    //   1988: dup
    //   1989: bipush #44
    //   1991: ldc -778901479
    //   1993: iastore
    //   1994: dup
    //   1995: bipush #45
    //   1997: ldc -694614492
    //   1999: iastore
    //   2000: dup
    //   2001: bipush #46
    //   2003: ldc -200395387
    //   2005: iastore
    //   2006: dup
    //   2007: bipush #47
    //   2009: ldc 275423344
    //   2011: iastore
    //   2012: dup
    //   2013: bipush #48
    //   2015: ldc 430227734
    //   2017: iastore
    //   2018: dup
    //   2019: bipush #49
    //   2021: ldc 506948616
    //   2023: iastore
    //   2024: dup
    //   2025: bipush #50
    //   2027: ldc 659060556
    //   2029: iastore
    //   2030: dup
    //   2031: bipush #51
    //   2033: ldc 883997877
    //   2035: iastore
    //   2036: dup
    //   2037: bipush #52
    //   2039: ldc 958139571
    //   2041: iastore
    //   2042: dup
    //   2043: bipush #53
    //   2045: ldc 1322822218
    //   2047: iastore
    //   2048: dup
    //   2049: bipush #54
    //   2051: ldc 1537002063
    //   2053: iastore
    //   2054: dup
    //   2055: bipush #55
    //   2057: ldc 1747873779
    //   2059: iastore
    //   2060: dup
    //   2061: bipush #56
    //   2063: ldc 1955562222
    //   2065: iastore
    //   2066: dup
    //   2067: bipush #57
    //   2069: ldc 2024104815
    //   2071: iastore
    //   2072: dup
    //   2073: bipush #58
    //   2075: ldc -2067236844
    //   2077: iastore
    //   2078: dup
    //   2079: bipush #59
    //   2081: ldc -1933114872
    //   2083: iastore
    //   2084: dup
    //   2085: bipush #60
    //   2087: ldc -1866530822
    //   2089: iastore
    //   2090: dup
    //   2091: bipush #61
    //   2093: ldc -1538233109
    //   2095: iastore
    //   2096: dup
    //   2097: bipush #62
    //   2099: ldc -1090935817
    //   2101: iastore
    //   2102: dup
    //   2103: bipush #63
    //   2105: ldc -965641998
    //   2107: iastore
    //   2108: astore #7
    //   2110: iconst_2
    //   2111: newarray int
    //   2113: dup
    //   2114: iconst_0
    //   2115: iconst_0
    //   2116: iastore
    //   2117: dup
    //   2118: iconst_1
    //   2119: iconst_0
    //   2120: iastore
    //   2121: astore #8
    //   2123: bipush #8
    //   2125: newarray int
    //   2127: dup
    //   2128: iconst_0
    //   2129: ldc 1779033703
    //   2131: iastore
    //   2132: dup
    //   2133: iconst_1
    //   2134: ldc -1150833019
    //   2136: iastore
    //   2137: dup
    //   2138: iconst_2
    //   2139: ldc 1013904242
    //   2141: iastore
    //   2142: dup
    //   2143: iconst_3
    //   2144: ldc -1521486534
    //   2146: iastore
    //   2147: dup
    //   2148: iconst_4
    //   2149: ldc 1359893119
    //   2151: iastore
    //   2152: dup
    //   2153: iconst_5
    //   2154: ldc -1694144372
    //   2156: iastore
    //   2157: dup
    //   2158: bipush #6
    //   2160: ldc 528734635
    //   2162: iastore
    //   2163: dup
    //   2164: bipush #7
    //   2166: ldc 1541459225
    //   2168: iastore
    //   2169: astore #9
    //   2171: bipush #64
    //   2173: newarray byte
    //   2175: astore #10
    //   2177: bipush #64
    //   2179: newarray byte
    //   2181: astore #11
    //   2183: aload #4
    //   2185: arraylength
    //   2186: istore #12
    //   2188: aload #8
    //   2190: iconst_0
    //   2191: iaload
    //   2192: bipush #63
    //   2194: iand
    //   2195: istore #13
    //   2197: aload #8
    //   2199: iconst_0
    //   2200: dup2
    //   2201: iaload
    //   2202: iload #12
    //   2204: iadd
    //   2205: iastore
    //   2206: aload #8
    //   2208: iconst_0
    //   2209: dup2
    //   2210: iaload
    //   2211: iconst_m1
    //   2212: iand
    //   2213: iastore
    //   2214: aload #8
    //   2216: iconst_0
    //   2217: iaload
    //   2218: iload #12
    //   2220: if_icmpge -> 2238
    //   2223: aload #8
    //   2225: iconst_1
    //   2226: dup2
    //   2227: iaload
    //   2228: iconst_1
    //   2229: iadd
    //   2230: iastore
    //   2231: goto -> 2238
    //   2234: invokestatic a : (Ljava/lang/Throwable;)Ljava/lang/Throwable;
    //   2237: athrow
    //   2238: iconst_0
    //   2239: istore #14
    //   2241: iload #12
    //   2243: bipush #64
    //   2245: if_icmplt -> 2855
    //   2248: iconst_0
    //   2249: istore #15
    //   2251: iload #15
    //   2253: bipush #64
    //   2255: if_icmpge -> 2278
    //   2258: aload #11
    //   2260: iload #15
    //   2262: aload #4
    //   2264: iload #14
    //   2266: iload #15
    //   2268: iadd
    //   2269: baload
    //   2270: bastore
    //   2271: iinc #15, 1
    //   2274: iload_2
    //   2275: ifne -> 2251
    //   2278: bipush #64
    //   2280: newarray int
    //   2282: astore #15
    //   2284: bipush #8
    //   2286: newarray int
    //   2288: astore #16
    //   2290: iconst_0
    //   2291: istore #17
    //   2293: iload #17
    //   2295: bipush #8
    //   2297: if_icmpge -> 2317
    //   2300: aload #16
    //   2302: iload #17
    //   2304: aload #9
    //   2306: iload #17
    //   2308: iaload
    //   2309: iastore
    //   2310: iinc #17, 1
    //   2313: iload_2
    //   2314: ifne -> 2293
    //   2317: iconst_0
    //   2318: istore #17
    //   2320: iload #17
    //   2322: bipush #64
    //   2324: if_icmpge -> 2815
    //   2327: iload #17
    //   2329: bipush #16
    //   2331: if_icmpge -> 2412
    //   2334: aload #15
    //   2336: iload #17
    //   2338: aload #11
    //   2340: iconst_4
    //   2341: iload #17
    //   2343: imul
    //   2344: baload
    //   2345: sipush #255
    //   2348: iand
    //   2349: bipush #24
    //   2351: ishl
    //   2352: aload #11
    //   2354: iconst_4
    //   2355: iload #17
    //   2357: imul
    //   2358: iconst_1
    //   2359: iadd
    //   2360: baload
    //   2361: sipush #255
    //   2364: iand
    //   2365: bipush #16
    //   2367: ishl
    //   2368: ior
    //   2369: aload #11
    //   2371: iconst_4
    //   2372: iload #17
    //   2374: imul
    //   2375: iconst_2
    //   2376: iadd
    //   2377: baload
    //   2378: sipush #255
    //   2381: iand
    //   2382: bipush #8
    //   2384: ishl
    //   2385: ior
    //   2386: aload #11
    //   2388: iconst_4
    //   2389: iload #17
    //   2391: imul
    //   2392: iconst_3
    //   2393: iadd
    //   2394: baload
    //   2395: sipush #255
    //   2398: iand
    //   2399: ior
    //   2400: iastore
    //   2401: iload_2
    //   2402: ifne -> 2555
    //   2405: goto -> 2412
    //   2408: invokestatic a : (Ljava/lang/Throwable;)Ljava/lang/Throwable;
    //   2411: athrow
    //   2412: aload #15
    //   2414: iload #17
    //   2416: aload #15
    //   2418: iload #17
    //   2420: iconst_2
    //   2421: isub
    //   2422: iaload
    //   2423: bipush #17
    //   2425: iushr
    //   2426: aload #15
    //   2428: iload #17
    //   2430: iconst_2
    //   2431: isub
    //   2432: iaload
    //   2433: bipush #15
    //   2435: ishl
    //   2436: ior
    //   2437: aload #15
    //   2439: iload #17
    //   2441: iconst_2
    //   2442: isub
    //   2443: iaload
    //   2444: bipush #19
    //   2446: iushr
    //   2447: aload #15
    //   2449: iload #17
    //   2451: iconst_2
    //   2452: isub
    //   2453: iaload
    //   2454: bipush #13
    //   2456: ishl
    //   2457: ior
    //   2458: ixor
    //   2459: aload #15
    //   2461: iload #17
    //   2463: iconst_2
    //   2464: isub
    //   2465: iaload
    //   2466: bipush #10
    //   2468: iushr
    //   2469: ixor
    //   2470: aload #15
    //   2472: iload #17
    //   2474: bipush #7
    //   2476: isub
    //   2477: iaload
    //   2478: iadd
    //   2479: aload #15
    //   2481: iload #17
    //   2483: bipush #15
    //   2485: isub
    //   2486: iaload
    //   2487: bipush #7
    //   2489: iushr
    //   2490: aload #15
    //   2492: iload #17
    //   2494: bipush #15
    //   2496: isub
    //   2497: iaload
    //   2498: bipush #25
    //   2500: ishl
    //   2501: ior
    //   2502: aload #15
    //   2504: iload #17
    //   2506: bipush #15
    //   2508: isub
    //   2509: iaload
    //   2510: bipush #18
    //   2512: iushr
    //   2513: aload #15
    //   2515: iload #17
    //   2517: bipush #15
    //   2519: isub
    //   2520: iaload
    //   2521: bipush #14
    //   2523: ishl
    //   2524: ior
    //   2525: ixor
    //   2526: aload #15
    //   2528: iload #17
    //   2530: bipush #15
    //   2532: isub
    //   2533: iaload
    //   2534: iconst_3
    //   2535: iushr
    //   2536: ixor
    //   2537: iadd
    //   2538: aload #15
    //   2540: iload #17
    //   2542: bipush #16
    //   2544: isub
    //   2545: iaload
    //   2546: iadd
    //   2547: iastore
    //   2548: goto -> 2555
    //   2551: invokestatic a : (Ljava/lang/Throwable;)Ljava/lang/Throwable;
    //   2554: athrow
    //   2555: aload #16
    //   2557: bipush #7
    //   2559: iaload
    //   2560: aload #16
    //   2562: iconst_4
    //   2563: iaload
    //   2564: bipush #6
    //   2566: iushr
    //   2567: aload #16
    //   2569: iconst_4
    //   2570: iaload
    //   2571: bipush #26
    //   2573: ishl
    //   2574: ior
    //   2575: aload #16
    //   2577: iconst_4
    //   2578: iaload
    //   2579: bipush #11
    //   2581: iushr
    //   2582: aload #16
    //   2584: iconst_4
    //   2585: iaload
    //   2586: bipush #21
    //   2588: ishl
    //   2589: ior
    //   2590: ixor
    //   2591: aload #16
    //   2593: iconst_4
    //   2594: iaload
    //   2595: bipush #25
    //   2597: iushr
    //   2598: aload #16
    //   2600: iconst_4
    //   2601: iaload
    //   2602: bipush #7
    //   2604: ishl
    //   2605: ior
    //   2606: ixor
    //   2607: iadd
    //   2608: aload #16
    //   2610: bipush #6
    //   2612: iaload
    //   2613: aload #16
    //   2615: iconst_4
    //   2616: iaload
    //   2617: aload #16
    //   2619: iconst_5
    //   2620: iaload
    //   2621: aload #16
    //   2623: bipush #6
    //   2625: iaload
    //   2626: ixor
    //   2627: iand
    //   2628: ixor
    //   2629: iadd
    //   2630: aload #7
    //   2632: iload #17
    //   2634: iaload
    //   2635: iadd
    //   2636: aload #15
    //   2638: iload #17
    //   2640: iaload
    //   2641: iadd
    //   2642: istore #18
    //   2644: aload #16
    //   2646: iconst_0
    //   2647: iaload
    //   2648: iconst_2
    //   2649: iushr
    //   2650: aload #16
    //   2652: iconst_0
    //   2653: iaload
    //   2654: bipush #30
    //   2656: ishl
    //   2657: ior
    //   2658: aload #16
    //   2660: iconst_0
    //   2661: iaload
    //   2662: bipush #13
    //   2664: iushr
    //   2665: aload #16
    //   2667: iconst_0
    //   2668: iaload
    //   2669: bipush #19
    //   2671: ishl
    //   2672: ior
    //   2673: ixor
    //   2674: aload #16
    //   2676: iconst_0
    //   2677: iaload
    //   2678: bipush #22
    //   2680: iushr
    //   2681: aload #16
    //   2683: iconst_0
    //   2684: iaload
    //   2685: bipush #10
    //   2687: ishl
    //   2688: ior
    //   2689: ixor
    //   2690: aload #16
    //   2692: iconst_0
    //   2693: iaload
    //   2694: aload #16
    //   2696: iconst_1
    //   2697: iaload
    //   2698: iand
    //   2699: aload #16
    //   2701: iconst_2
    //   2702: iaload
    //   2703: aload #16
    //   2705: iconst_0
    //   2706: iaload
    //   2707: aload #16
    //   2709: iconst_1
    //   2710: iaload
    //   2711: ior
    //   2712: iand
    //   2713: ior
    //   2714: iadd
    //   2715: istore #19
    //   2717: aload #16
    //   2719: iconst_3
    //   2720: dup2
    //   2721: iaload
    //   2722: iload #18
    //   2724: iadd
    //   2725: iastore
    //   2726: aload #16
    //   2728: bipush #7
    //   2730: iload #18
    //   2732: iload #19
    //   2734: iadd
    //   2735: iastore
    //   2736: aload #16
    //   2738: bipush #7
    //   2740: iaload
    //   2741: istore #18
    //   2743: aload #16
    //   2745: bipush #7
    //   2747: aload #16
    //   2749: bipush #6
    //   2751: iaload
    //   2752: iastore
    //   2753: aload #16
    //   2755: bipush #6
    //   2757: aload #16
    //   2759: iconst_5
    //   2760: iaload
    //   2761: iastore
    //   2762: aload #16
    //   2764: iconst_5
    //   2765: aload #16
    //   2767: iconst_4
    //   2768: iaload
    //   2769: iastore
    //   2770: aload #16
    //   2772: iconst_4
    //   2773: aload #16
    //   2775: iconst_3
    //   2776: iaload
    //   2777: iastore
    //   2778: aload #16
    //   2780: iconst_3
    //   2781: aload #16
    //   2783: iconst_2
    //   2784: iaload
    //   2785: iastore
    //   2786: aload #16
    //   2788: iconst_2
    //   2789: aload #16
    //   2791: iconst_1
    //   2792: iaload
    //   2793: iastore
    //   2794: aload #16
    //   2796: iconst_1
    //   2797: aload #16
    //   2799: iconst_0
    //   2800: iaload
    //   2801: iastore
    //   2802: aload #16
    //   2804: iconst_0
    //   2805: iload #18
    //   2807: iastore
    //   2808: iinc #17, 1
    //   2811: iload_2
    //   2812: ifne -> 2320
    //   2815: iconst_0
    //   2816: istore #17
    //   2818: iload #17
    //   2820: bipush #8
    //   2822: if_icmpge -> 2845
    //   2825: aload #9
    //   2827: iload #17
    //   2829: dup2
    //   2830: iaload
    //   2831: aload #16
    //   2833: iload #17
    //   2835: iaload
    //   2836: iadd
    //   2837: iastore
    //   2838: iinc #17, 1
    //   2841: iload_2
    //   2842: ifne -> 2818
    //   2845: iinc #14, 64
    //   2848: iinc #12, -64
    //   2851: iload_2
    //   2852: ifne -> 2241
    //   2855: iload #12
    //   2857: ifle -> 2893
    //   2860: iconst_0
    //   2861: istore #15
    //   2863: iload #15
    //   2865: iload #12
    //   2867: if_icmpge -> 2893
    //   2870: aload #10
    //   2872: iload #13
    //   2874: iload #15
    //   2876: iadd
    //   2877: aload #4
    //   2879: iload #14
    //   2881: iload #15
    //   2883: iadd
    //   2884: baload
    //   2885: bastore
    //   2886: iinc #15, 1
    //   2889: iload_2
    //   2890: ifne -> 2863
    //   2893: aload #8
    //   2895: iconst_0
    //   2896: iaload
    //   2897: bipush #29
    //   2899: iushr
    //   2900: aload #8
    //   2902: iconst_1
    //   2903: iaload
    //   2904: iconst_3
    //   2905: ishl
    //   2906: ior
    //   2907: istore #15
    //   2909: aload #8
    //   2911: iconst_0
    //   2912: iaload
    //   2913: iconst_3
    //   2914: ishl
    //   2915: istore #16
    //   2917: aload #8
    //   2919: iconst_0
    //   2920: iaload
    //   2921: bipush #63
    //   2923: iand
    //   2924: istore #17
    //   2926: iload #17
    //   2928: bipush #56
    //   2930: if_icmpge -> 2945
    //   2933: bipush #56
    //   2935: iload #17
    //   2937: isub
    //   2938: goto -> 2950
    //   2941: invokestatic a : (Ljava/lang/Throwable;)Ljava/lang/Throwable;
    //   2944: athrow
    //   2945: bipush #120
    //   2947: iload #17
    //   2949: isub
    //   2950: istore #18
    //   2952: aload #8
    //   2954: iconst_0
    //   2955: iaload
    //   2956: bipush #63
    //   2958: iand
    //   2959: istore #13
    //   2961: bipush #64
    //   2963: iload #13
    //   2965: isub
    //   2966: istore #19
    //   2968: aload #8
    //   2970: iconst_0
    //   2971: dup2
    //   2972: iaload
    //   2973: iload #18
    //   2975: iadd
    //   2976: iastore
    //   2977: aload #8
    //   2979: iconst_0
    //   2980: dup2
    //   2981: iaload
    //   2982: iconst_m1
    //   2983: iand
    //   2984: iastore
    //   2985: aload #8
    //   2987: iconst_0
    //   2988: iaload
    //   2989: iload #18
    //   2991: if_icmpge -> 3009
    //   2994: aload #8
    //   2996: iconst_1
    //   2997: dup2
    //   2998: iaload
    //   2999: iconst_1
    //   3000: iadd
    //   3001: iastore
    //   3002: goto -> 3009
    //   3005: invokestatic a : (Ljava/lang/Throwable;)Ljava/lang/Throwable;
    //   3008: athrow
    //   3009: iconst_0
    //   3010: istore #14
    //   3012: iload #13
    //   3014: ifle -> 3645
    //   3017: iload #18
    //   3019: iload #19
    //   3021: if_icmplt -> 3645
    //   3024: goto -> 3031
    //   3027: invokestatic a : (Ljava/lang/Throwable;)Ljava/lang/Throwable;
    //   3030: athrow
    //   3031: iconst_0
    //   3032: istore #20
    //   3034: iload #20
    //   3036: iload #19
    //   3038: if_icmpge -> 3061
    //   3041: aload #10
    //   3043: iload #13
    //   3045: iload #20
    //   3047: iadd
    //   3048: aload #6
    //   3050: iload #20
    //   3052: baload
    //   3053: bastore
    //   3054: iinc #20, 1
    //   3057: iload_2
    //   3058: ifne -> 3034
    //   3061: bipush #64
    //   3063: newarray int
    //   3065: astore #20
    //   3067: bipush #8
    //   3069: newarray int
    //   3071: astore #21
    //   3073: iconst_0
    //   3074: istore #22
    //   3076: iload #22
    //   3078: bipush #8
    //   3080: if_icmpge -> 3100
    //   3083: aload #21
    //   3085: iload #22
    //   3087: aload #9
    //   3089: iload #22
    //   3091: iaload
    //   3092: iastore
    //   3093: iinc #22, 1
    //   3096: iload_2
    //   3097: ifne -> 3076
    //   3100: iconst_0
    //   3101: istore #22
    //   3103: iload #22
    //   3105: bipush #64
    //   3107: if_icmpge -> 3598
    //   3110: iload #22
    //   3112: bipush #16
    //   3114: if_icmpge -> 3195
    //   3117: aload #20
    //   3119: iload #22
    //   3121: aload #10
    //   3123: iconst_4
    //   3124: iload #22
    //   3126: imul
    //   3127: baload
    //   3128: sipush #255
    //   3131: iand
    //   3132: bipush #24
    //   3134: ishl
    //   3135: aload #10
    //   3137: iconst_4
    //   3138: iload #22
    //   3140: imul
    //   3141: iconst_1
    //   3142: iadd
    //   3143: baload
    //   3144: sipush #255
    //   3147: iand
    //   3148: bipush #16
    //   3150: ishl
    //   3151: ior
    //   3152: aload #10
    //   3154: iconst_4
    //   3155: iload #22
    //   3157: imul
    //   3158: iconst_2
    //   3159: iadd
    //   3160: baload
    //   3161: sipush #255
    //   3164: iand
    //   3165: bipush #8
    //   3167: ishl
    //   3168: ior
    //   3169: aload #10
    //   3171: iconst_4
    //   3172: iload #22
    //   3174: imul
    //   3175: iconst_3
    //   3176: iadd
    //   3177: baload
    //   3178: sipush #255
    //   3181: iand
    //   3182: ior
    //   3183: iastore
    //   3184: iload_2
    //   3185: ifne -> 3338
    //   3188: goto -> 3195
    //   3191: invokestatic a : (Ljava/lang/Throwable;)Ljava/lang/Throwable;
    //   3194: athrow
    //   3195: aload #20
    //   3197: iload #22
    //   3199: aload #20
    //   3201: iload #22
    //   3203: iconst_2
    //   3204: isub
    //   3205: iaload
    //   3206: bipush #17
    //   3208: iushr
    //   3209: aload #20
    //   3211: iload #22
    //   3213: iconst_2
    //   3214: isub
    //   3215: iaload
    //   3216: bipush #15
    //   3218: ishl
    //   3219: ior
    //   3220: aload #20
    //   3222: iload #22
    //   3224: iconst_2
    //   3225: isub
    //   3226: iaload
    //   3227: bipush #19
    //   3229: iushr
    //   3230: aload #20
    //   3232: iload #22
    //   3234: iconst_2
    //   3235: isub
    //   3236: iaload
    //   3237: bipush #13
    //   3239: ishl
    //   3240: ior
    //   3241: ixor
    //   3242: aload #20
    //   3244: iload #22
    //   3246: iconst_2
    //   3247: isub
    //   3248: iaload
    //   3249: bipush #10
    //   3251: iushr
    //   3252: ixor
    //   3253: aload #20
    //   3255: iload #22
    //   3257: bipush #7
    //   3259: isub
    //   3260: iaload
    //   3261: iadd
    //   3262: aload #20
    //   3264: iload #22
    //   3266: bipush #15
    //   3268: isub
    //   3269: iaload
    //   3270: bipush #7
    //   3272: iushr
    //   3273: aload #20
    //   3275: iload #22
    //   3277: bipush #15
    //   3279: isub
    //   3280: iaload
    //   3281: bipush #25
    //   3283: ishl
    //   3284: ior
    //   3285: aload #20
    //   3287: iload #22
    //   3289: bipush #15
    //   3291: isub
    //   3292: iaload
    //   3293: bipush #18
    //   3295: iushr
    //   3296: aload #20
    //   3298: iload #22
    //   3300: bipush #15
    //   3302: isub
    //   3303: iaload
    //   3304: bipush #14
    //   3306: ishl
    //   3307: ior
    //   3308: ixor
    //   3309: aload #20
    //   3311: iload #22
    //   3313: bipush #15
    //   3315: isub
    //   3316: iaload
    //   3317: iconst_3
    //   3318: iushr
    //   3319: ixor
    //   3320: iadd
    //   3321: aload #20
    //   3323: iload #22
    //   3325: bipush #16
    //   3327: isub
    //   3328: iaload
    //   3329: iadd
    //   3330: iastore
    //   3331: goto -> 3338
    //   3334: invokestatic a : (Ljava/lang/Throwable;)Ljava/lang/Throwable;
    //   3337: athrow
    //   3338: aload #21
    //   3340: bipush #7
    //   3342: iaload
    //   3343: aload #21
    //   3345: iconst_4
    //   3346: iaload
    //   3347: bipush #6
    //   3349: iushr
    //   3350: aload #21
    //   3352: iconst_4
    //   3353: iaload
    //   3354: bipush #26
    //   3356: ishl
    //   3357: ior
    //   3358: aload #21
    //   3360: iconst_4
    //   3361: iaload
    //   3362: bipush #11
    //   3364: iushr
    //   3365: aload #21
    //   3367: iconst_4
    //   3368: iaload
    //   3369: bipush #21
    //   3371: ishl
    //   3372: ior
    //   3373: ixor
    //   3374: aload #21
    //   3376: iconst_4
    //   3377: iaload
    //   3378: bipush #25
    //   3380: iushr
    //   3381: aload #21
    //   3383: iconst_4
    //   3384: iaload
    //   3385: bipush #7
    //   3387: ishl
    //   3388: ior
    //   3389: ixor
    //   3390: iadd
    //   3391: aload #21
    //   3393: bipush #6
    //   3395: iaload
    //   3396: aload #21
    //   3398: iconst_4
    //   3399: iaload
    //   3400: aload #21
    //   3402: iconst_5
    //   3403: iaload
    //   3404: aload #21
    //   3406: bipush #6
    //   3408: iaload
    //   3409: ixor
    //   3410: iand
    //   3411: ixor
    //   3412: iadd
    //   3413: aload #7
    //   3415: iload #22
    //   3417: iaload
    //   3418: iadd
    //   3419: aload #20
    //   3421: iload #22
    //   3423: iaload
    //   3424: iadd
    //   3425: istore #23
    //   3427: aload #21
    //   3429: iconst_0
    //   3430: iaload
    //   3431: iconst_2
    //   3432: iushr
    //   3433: aload #21
    //   3435: iconst_0
    //   3436: iaload
    //   3437: bipush #30
    //   3439: ishl
    //   3440: ior
    //   3441: aload #21
    //   3443: iconst_0
    //   3444: iaload
    //   3445: bipush #13
    //   3447: iushr
    //   3448: aload #21
    //   3450: iconst_0
    //   3451: iaload
    //   3452: bipush #19
    //   3454: ishl
    //   3455: ior
    //   3456: ixor
    //   3457: aload #21
    //   3459: iconst_0
    //   3460: iaload
    //   3461: bipush #22
    //   3463: iushr
    //   3464: aload #21
    //   3466: iconst_0
    //   3467: iaload
    //   3468: bipush #10
    //   3470: ishl
    //   3471: ior
    //   3472: ixor
    //   3473: aload #21
    //   3475: iconst_0
    //   3476: iaload
    //   3477: aload #21
    //   3479: iconst_1
    //   3480: iaload
    //   3481: iand
    //   3482: aload #21
    //   3484: iconst_2
    //   3485: iaload
    //   3486: aload #21
    //   3488: iconst_0
    //   3489: iaload
    //   3490: aload #21
    //   3492: iconst_1
    //   3493: iaload
    //   3494: ior
    //   3495: iand
    //   3496: ior
    //   3497: iadd
    //   3498: istore #24
    //   3500: aload #21
    //   3502: iconst_3
    //   3503: dup2
    //   3504: iaload
    //   3505: iload #23
    //   3507: iadd
    //   3508: iastore
    //   3509: aload #21
    //   3511: bipush #7
    //   3513: iload #23
    //   3515: iload #24
    //   3517: iadd
    //   3518: iastore
    //   3519: aload #21
    //   3521: bipush #7
    //   3523: iaload
    //   3524: istore #23
    //   3526: aload #21
    //   3528: bipush #7
    //   3530: aload #21
    //   3532: bipush #6
    //   3534: iaload
    //   3535: iastore
    //   3536: aload #21
    //   3538: bipush #6
    //   3540: aload #21
    //   3542: iconst_5
    //   3543: iaload
    //   3544: iastore
    //   3545: aload #21
    //   3547: iconst_5
    //   3548: aload #21
    //   3550: iconst_4
    //   3551: iaload
    //   3552: iastore
    //   3553: aload #21
    //   3555: iconst_4
    //   3556: aload #21
    //   3558: iconst_3
    //   3559: iaload
    //   3560: iastore
    //   3561: aload #21
    //   3563: iconst_3
    //   3564: aload #21
    //   3566: iconst_2
    //   3567: iaload
    //   3568: iastore
    //   3569: aload #21
    //   3571: iconst_2
    //   3572: aload #21
    //   3574: iconst_1
    //   3575: iaload
    //   3576: iastore
    //   3577: aload #21
    //   3579: iconst_1
    //   3580: aload #21
    //   3582: iconst_0
    //   3583: iaload
    //   3584: iastore
    //   3585: aload #21
    //   3587: iconst_0
    //   3588: iload #23
    //   3590: iastore
    //   3591: iinc #22, 1
    //   3594: iload_2
    //   3595: ifne -> 3103
    //   3598: iconst_0
    //   3599: istore #22
    //   3601: iload #22
    //   3603: bipush #8
    //   3605: if_icmpge -> 3628
    //   3608: aload #9
    //   3610: iload #22
    //   3612: dup2
    //   3613: iaload
    //   3614: aload #21
    //   3616: iload #22
    //   3618: iaload
    //   3619: iadd
    //   3620: iastore
    //   3621: iinc #22, 1
    //   3624: iload_2
    //   3625: ifne -> 3601
    //   3628: iload #14
    //   3630: iload #19
    //   3632: iadd
    //   3633: istore #14
    //   3635: iload #18
    //   3637: iload #19
    //   3639: isub
    //   3640: istore #18
    //   3642: iconst_0
    //   3643: istore #13
    //   3645: iload #18
    //   3647: bipush #64
    //   3649: if_icmplt -> 4259
    //   3652: iconst_0
    //   3653: istore #20
    //   3655: iload #20
    //   3657: bipush #64
    //   3659: if_icmpge -> 3682
    //   3662: aload #11
    //   3664: iload #20
    //   3666: aload #6
    //   3668: iload #14
    //   3670: iload #20
    //   3672: iadd
    //   3673: baload
    //   3674: bastore
    //   3675: iinc #20, 1
    //   3678: iload_2
    //   3679: ifne -> 3655
    //   3682: bipush #64
    //   3684: newarray int
    //   3686: astore #20
    //   3688: bipush #8
    //   3690: newarray int
    //   3692: astore #21
    //   3694: iconst_0
    //   3695: istore #22
    //   3697: iload #22
    //   3699: bipush #8
    //   3701: if_icmpge -> 3721
    //   3704: aload #21
    //   3706: iload #22
    //   3708: aload #9
    //   3710: iload #22
    //   3712: iaload
    //   3713: iastore
    //   3714: iinc #22, 1
    //   3717: iload_2
    //   3718: ifne -> 3697
    //   3721: iconst_0
    //   3722: istore #22
    //   3724: iload #22
    //   3726: bipush #64
    //   3728: if_icmpge -> 4219
    //   3731: iload #22
    //   3733: bipush #16
    //   3735: if_icmpge -> 3816
    //   3738: aload #20
    //   3740: iload #22
    //   3742: aload #11
    //   3744: iconst_4
    //   3745: iload #22
    //   3747: imul
    //   3748: baload
    //   3749: sipush #255
    //   3752: iand
    //   3753: bipush #24
    //   3755: ishl
    //   3756: aload #11
    //   3758: iconst_4
    //   3759: iload #22
    //   3761: imul
    //   3762: iconst_1
    //   3763: iadd
    //   3764: baload
    //   3765: sipush #255
    //   3768: iand
    //   3769: bipush #16
    //   3771: ishl
    //   3772: ior
    //   3773: aload #11
    //   3775: iconst_4
    //   3776: iload #22
    //   3778: imul
    //   3779: iconst_2
    //   3780: iadd
    //   3781: baload
    //   3782: sipush #255
    //   3785: iand
    //   3786: bipush #8
    //   3788: ishl
    //   3789: ior
    //   3790: aload #11
    //   3792: iconst_4
    //   3793: iload #22
    //   3795: imul
    //   3796: iconst_3
    //   3797: iadd
    //   3798: baload
    //   3799: sipush #255
    //   3802: iand
    //   3803: ior
    //   3804: iastore
    //   3805: iload_2
    //   3806: ifne -> 3959
    //   3809: goto -> 3816
    //   3812: invokestatic a : (Ljava/lang/Throwable;)Ljava/lang/Throwable;
    //   3815: athrow
    //   3816: aload #20
    //   3818: iload #22
    //   3820: aload #20
    //   3822: iload #22
    //   3824: iconst_2
    //   3825: isub
    //   3826: iaload
    //   3827: bipush #17
    //   3829: iushr
    //   3830: aload #20
    //   3832: iload #22
    //   3834: iconst_2
    //   3835: isub
    //   3836: iaload
    //   3837: bipush #15
    //   3839: ishl
    //   3840: ior
    //   3841: aload #20
    //   3843: iload #22
    //   3845: iconst_2
    //   3846: isub
    //   3847: iaload
    //   3848: bipush #19
    //   3850: iushr
    //   3851: aload #20
    //   3853: iload #22
    //   3855: iconst_2
    //   3856: isub
    //   3857: iaload
    //   3858: bipush #13
    //   3860: ishl
    //   3861: ior
    //   3862: ixor
    //   3863: aload #20
    //   3865: iload #22
    //   3867: iconst_2
    //   3868: isub
    //   3869: iaload
    //   3870: bipush #10
    //   3872: iushr
    //   3873: ixor
    //   3874: aload #20
    //   3876: iload #22
    //   3878: bipush #7
    //   3880: isub
    //   3881: iaload
    //   3882: iadd
    //   3883: aload #20
    //   3885: iload #22
    //   3887: bipush #15
    //   3889: isub
    //   3890: iaload
    //   3891: bipush #7
    //   3893: iushr
    //   3894: aload #20
    //   3896: iload #22
    //   3898: bipush #15
    //   3900: isub
    //   3901: iaload
    //   3902: bipush #25
    //   3904: ishl
    //   3905: ior
    //   3906: aload #20
    //   3908: iload #22
    //   3910: bipush #15
    //   3912: isub
    //   3913: iaload
    //   3914: bipush #18
    //   3916: iushr
    //   3917: aload #20
    //   3919: iload #22
    //   3921: bipush #15
    //   3923: isub
    //   3924: iaload
    //   3925: bipush #14
    //   3927: ishl
    //   3928: ior
    //   3929: ixor
    //   3930: aload #20
    //   3932: iload #22
    //   3934: bipush #15
    //   3936: isub
    //   3937: iaload
    //   3938: iconst_3
    //   3939: iushr
    //   3940: ixor
    //   3941: iadd
    //   3942: aload #20
    //   3944: iload #22
    //   3946: bipush #16
    //   3948: isub
    //   3949: iaload
    //   3950: iadd
    //   3951: iastore
    //   3952: goto -> 3959
    //   3955: invokestatic a : (Ljava/lang/Throwable;)Ljava/lang/Throwable;
    //   3958: athrow
    //   3959: aload #21
    //   3961: bipush #7
    //   3963: iaload
    //   3964: aload #21
    //   3966: iconst_4
    //   3967: iaload
    //   3968: bipush #6
    //   3970: iushr
    //   3971: aload #21
    //   3973: iconst_4
    //   3974: iaload
    //   3975: bipush #26
    //   3977: ishl
    //   3978: ior
    //   3979: aload #21
    //   3981: iconst_4
    //   3982: iaload
    //   3983: bipush #11
    //   3985: iushr
    //   3986: aload #21
    //   3988: iconst_4
    //   3989: iaload
    //   3990: bipush #21
    //   3992: ishl
    //   3993: ior
    //   3994: ixor
    //   3995: aload #21
    //   3997: iconst_4
    //   3998: iaload
    //   3999: bipush #25
    //   4001: iushr
    //   4002: aload #21
    //   4004: iconst_4
    //   4005: iaload
    //   4006: bipush #7
    //   4008: ishl
    //   4009: ior
    //   4010: ixor
    //   4011: iadd
    //   4012: aload #21
    //   4014: bipush #6
    //   4016: iaload
    //   4017: aload #21
    //   4019: iconst_4
    //   4020: iaload
    //   4021: aload #21
    //   4023: iconst_5
    //   4024: iaload
    //   4025: aload #21
    //   4027: bipush #6
    //   4029: iaload
    //   4030: ixor
    //   4031: iand
    //   4032: ixor
    //   4033: iadd
    //   4034: aload #7
    //   4036: iload #22
    //   4038: iaload
    //   4039: iadd
    //   4040: aload #20
    //   4042: iload #22
    //   4044: iaload
    //   4045: iadd
    //   4046: istore #23
    //   4048: aload #21
    //   4050: iconst_0
    //   4051: iaload
    //   4052: iconst_2
    //   4053: iushr
    //   4054: aload #21
    //   4056: iconst_0
    //   4057: iaload
    //   4058: bipush #30
    //   4060: ishl
    //   4061: ior
    //   4062: aload #21
    //   4064: iconst_0
    //   4065: iaload
    //   4066: bipush #13
    //   4068: iushr
    //   4069: aload #21
    //   4071: iconst_0
    //   4072: iaload
    //   4073: bipush #19
    //   4075: ishl
    //   4076: ior
    //   4077: ixor
    //   4078: aload #21
    //   4080: iconst_0
    //   4081: iaload
    //   4082: bipush #22
    //   4084: iushr
    //   4085: aload #21
    //   4087: iconst_0
    //   4088: iaload
    //   4089: bipush #10
    //   4091: ishl
    //   4092: ior
    //   4093: ixor
    //   4094: aload #21
    //   4096: iconst_0
    //   4097: iaload
    //   4098: aload #21
    //   4100: iconst_1
    //   4101: iaload
    //   4102: iand
    //   4103: aload #21
    //   4105: iconst_2
    //   4106: iaload
    //   4107: aload #21
    //   4109: iconst_0
    //   4110: iaload
    //   4111: aload #21
    //   4113: iconst_1
    //   4114: iaload
    //   4115: ior
    //   4116: iand
    //   4117: ior
    //   4118: iadd
    //   4119: istore #24
    //   4121: aload #21
    //   4123: iconst_3
    //   4124: dup2
    //   4125: iaload
    //   4126: iload #23
    //   4128: iadd
    //   4129: iastore
    //   4130: aload #21
    //   4132: bipush #7
    //   4134: iload #23
    //   4136: iload #24
    //   4138: iadd
    //   4139: iastore
    //   4140: aload #21
    //   4142: bipush #7
    //   4144: iaload
    //   4145: istore #23
    //   4147: aload #21
    //   4149: bipush #7
    //   4151: aload #21
    //   4153: bipush #6
    //   4155: iaload
    //   4156: iastore
    //   4157: aload #21
    //   4159: bipush #6
    //   4161: aload #21
    //   4163: iconst_5
    //   4164: iaload
    //   4165: iastore
    //   4166: aload #21
    //   4168: iconst_5
    //   4169: aload #21
    //   4171: iconst_4
    //   4172: iaload
    //   4173: iastore
    //   4174: aload #21
    //   4176: iconst_4
    //   4177: aload #21
    //   4179: iconst_3
    //   4180: iaload
    //   4181: iastore
    //   4182: aload #21
    //   4184: iconst_3
    //   4185: aload #21
    //   4187: iconst_2
    //   4188: iaload
    //   4189: iastore
    //   4190: aload #21
    //   4192: iconst_2
    //   4193: aload #21
    //   4195: iconst_1
    //   4196: iaload
    //   4197: iastore
    //   4198: aload #21
    //   4200: iconst_1
    //   4201: aload #21
    //   4203: iconst_0
    //   4204: iaload
    //   4205: iastore
    //   4206: aload #21
    //   4208: iconst_0
    //   4209: iload #23
    //   4211: iastore
    //   4212: iinc #22, 1
    //   4215: iload_2
    //   4216: ifne -> 3724
    //   4219: iconst_0
    //   4220: istore #22
    //   4222: iload #22
    //   4224: bipush #8
    //   4226: if_icmpge -> 4249
    //   4229: aload #9
    //   4231: iload #22
    //   4233: dup2
    //   4234: iaload
    //   4235: aload #21
    //   4237: iload #22
    //   4239: iaload
    //   4240: iadd
    //   4241: iastore
    //   4242: iinc #22, 1
    //   4245: iload_2
    //   4246: ifne -> 4222
    //   4249: iinc #14, 64
    //   4252: iinc #18, -64
    //   4255: iload_2
    //   4256: ifne -> 3645
    //   4259: iload #18
    //   4261: ifle -> 4297
    //   4264: iconst_0
    //   4265: istore #20
    //   4267: iload #20
    //   4269: iload #18
    //   4271: if_icmpge -> 4297
    //   4274: aload #10
    //   4276: iload #13
    //   4278: iload #20
    //   4280: iadd
    //   4281: aload #6
    //   4283: iload #14
    //   4285: iload #20
    //   4287: iadd
    //   4288: baload
    //   4289: bastore
    //   4290: iinc #20, 1
    //   4293: iload_2
    //   4294: ifne -> 4267
    //   4297: bipush #8
    //   4299: newarray byte
    //   4301: astore #20
    //   4303: aload #20
    //   4305: iconst_0
    //   4306: iload #15
    //   4308: bipush #24
    //   4310: iushr
    //   4311: i2b
    //   4312: bastore
    //   4313: aload #20
    //   4315: iconst_1
    //   4316: iload #15
    //   4318: bipush #16
    //   4320: iushr
    //   4321: i2b
    //   4322: bastore
    //   4323: aload #20
    //   4325: iconst_2
    //   4326: iload #15
    //   4328: bipush #8
    //   4330: iushr
    //   4331: i2b
    //   4332: bastore
    //   4333: aload #20
    //   4335: iconst_3
    //   4336: iload #15
    //   4338: i2b
    //   4339: bastore
    //   4340: aload #20
    //   4342: iconst_4
    //   4343: iload #16
    //   4345: bipush #24
    //   4347: iushr
    //   4348: i2b
    //   4349: bastore
    //   4350: aload #20
    //   4352: iconst_5
    //   4353: iload #16
    //   4355: bipush #16
    //   4357: iushr
    //   4358: i2b
    //   4359: bastore
    //   4360: aload #20
    //   4362: bipush #6
    //   4364: iload #16
    //   4366: bipush #8
    //   4368: iushr
    //   4369: i2b
    //   4370: bastore
    //   4371: aload #20
    //   4373: bipush #7
    //   4375: iload #16
    //   4377: i2b
    //   4378: bastore
    //   4379: bipush #8
    //   4381: istore #12
    //   4383: aload #8
    //   4385: iconst_0
    //   4386: iaload
    //   4387: bipush #63
    //   4389: iand
    //   4390: istore #13
    //   4392: bipush #64
    //   4394: iload #13
    //   4396: isub
    //   4397: istore #19
    //   4399: aload #8
    //   4401: iconst_0
    //   4402: dup2
    //   4403: iaload
    //   4404: iload #12
    //   4406: iadd
    //   4407: iastore
    //   4408: aload #8
    //   4410: iconst_0
    //   4411: dup2
    //   4412: iaload
    //   4413: iconst_m1
    //   4414: iand
    //   4415: iastore
    //   4416: aload #8
    //   4418: iconst_0
    //   4419: iaload
    //   4420: iload #12
    //   4422: if_icmpge -> 4440
    //   4425: aload #8
    //   4427: iconst_1
    //   4428: dup2
    //   4429: iaload
    //   4430: iconst_1
    //   4431: iadd
    //   4432: iastore
    //   4433: goto -> 4440
    //   4436: invokestatic a : (Ljava/lang/Throwable;)Ljava/lang/Throwable;
    //   4439: athrow
    //   4440: iload #13
    //   4442: ifle -> 5056
    //   4445: iload #12
    //   4447: iload #19
    //   4449: if_icmplt -> 5056
    //   4452: goto -> 4459
    //   4455: invokestatic a : (Ljava/lang/Throwable;)Ljava/lang/Throwable;
    //   4458: athrow
    //   4459: iconst_0
    //   4460: istore #21
    //   4462: iload #21
    //   4464: iload #19
    //   4466: if_icmpge -> 4489
    //   4469: aload #10
    //   4471: iload #13
    //   4473: iload #21
    //   4475: iadd
    //   4476: aload #20
    //   4478: iload #21
    //   4480: baload
    //   4481: bastore
    //   4482: iinc #21, 1
    //   4485: iload_2
    //   4486: ifne -> 4462
    //   4489: bipush #64
    //   4491: newarray int
    //   4493: astore #21
    //   4495: bipush #8
    //   4497: newarray int
    //   4499: astore #22
    //   4501: iconst_0
    //   4502: istore #23
    //   4504: iload #23
    //   4506: bipush #8
    //   4508: if_icmpge -> 4528
    //   4511: aload #22
    //   4513: iload #23
    //   4515: aload #9
    //   4517: iload #23
    //   4519: iaload
    //   4520: iastore
    //   4521: iinc #23, 1
    //   4524: iload_2
    //   4525: ifne -> 4504
    //   4528: iconst_0
    //   4529: istore #23
    //   4531: iload #23
    //   4533: bipush #64
    //   4535: if_icmpge -> 5026
    //   4538: iload #23
    //   4540: bipush #16
    //   4542: if_icmpge -> 4623
    //   4545: aload #21
    //   4547: iload #23
    //   4549: aload #10
    //   4551: iconst_4
    //   4552: iload #23
    //   4554: imul
    //   4555: baload
    //   4556: sipush #255
    //   4559: iand
    //   4560: bipush #24
    //   4562: ishl
    //   4563: aload #10
    //   4565: iconst_4
    //   4566: iload #23
    //   4568: imul
    //   4569: iconst_1
    //   4570: iadd
    //   4571: baload
    //   4572: sipush #255
    //   4575: iand
    //   4576: bipush #16
    //   4578: ishl
    //   4579: ior
    //   4580: aload #10
    //   4582: iconst_4
    //   4583: iload #23
    //   4585: imul
    //   4586: iconst_2
    //   4587: iadd
    //   4588: baload
    //   4589: sipush #255
    //   4592: iand
    //   4593: bipush #8
    //   4595: ishl
    //   4596: ior
    //   4597: aload #10
    //   4599: iconst_4
    //   4600: iload #23
    //   4602: imul
    //   4603: iconst_3
    //   4604: iadd
    //   4605: baload
    //   4606: sipush #255
    //   4609: iand
    //   4610: ior
    //   4611: iastore
    //   4612: iload_2
    //   4613: ifne -> 4766
    //   4616: goto -> 4623
    //   4619: invokestatic a : (Ljava/lang/Throwable;)Ljava/lang/Throwable;
    //   4622: athrow
    //   4623: aload #21
    //   4625: iload #23
    //   4627: aload #21
    //   4629: iload #23
    //   4631: iconst_2
    //   4632: isub
    //   4633: iaload
    //   4634: bipush #17
    //   4636: iushr
    //   4637: aload #21
    //   4639: iload #23
    //   4641: iconst_2
    //   4642: isub
    //   4643: iaload
    //   4644: bipush #15
    //   4646: ishl
    //   4647: ior
    //   4648: aload #21
    //   4650: iload #23
    //   4652: iconst_2
    //   4653: isub
    //   4654: iaload
    //   4655: bipush #19
    //   4657: iushr
    //   4658: aload #21
    //   4660: iload #23
    //   4662: iconst_2
    //   4663: isub
    //   4664: iaload
    //   4665: bipush #13
    //   4667: ishl
    //   4668: ior
    //   4669: ixor
    //   4670: aload #21
    //   4672: iload #23
    //   4674: iconst_2
    //   4675: isub
    //   4676: iaload
    //   4677: bipush #10
    //   4679: iushr
    //   4680: ixor
    //   4681: aload #21
    //   4683: iload #23
    //   4685: bipush #7
    //   4687: isub
    //   4688: iaload
    //   4689: iadd
    //   4690: aload #21
    //   4692: iload #23
    //   4694: bipush #15
    //   4696: isub
    //   4697: iaload
    //   4698: bipush #7
    //   4700: iushr
    //   4701: aload #21
    //   4703: iload #23
    //   4705: bipush #15
    //   4707: isub
    //   4708: iaload
    //   4709: bipush #25
    //   4711: ishl
    //   4712: ior
    //   4713: aload #21
    //   4715: iload #23
    //   4717: bipush #15
    //   4719: isub
    //   4720: iaload
    //   4721: bipush #18
    //   4723: iushr
    //   4724: aload #21
    //   4726: iload #23
    //   4728: bipush #15
    //   4730: isub
    //   4731: iaload
    //   4732: bipush #14
    //   4734: ishl
    //   4735: ior
    //   4736: ixor
    //   4737: aload #21
    //   4739: iload #23
    //   4741: bipush #15
    //   4743: isub
    //   4744: iaload
    //   4745: iconst_3
    //   4746: iushr
    //   4747: ixor
    //   4748: iadd
    //   4749: aload #21
    //   4751: iload #23
    //   4753: bipush #16
    //   4755: isub
    //   4756: iaload
    //   4757: iadd
    //   4758: iastore
    //   4759: goto -> 4766
    //   4762: invokestatic a : (Ljava/lang/Throwable;)Ljava/lang/Throwable;
    //   4765: athrow
    //   4766: aload #22
    //   4768: bipush #7
    //   4770: iaload
    //   4771: aload #22
    //   4773: iconst_4
    //   4774: iaload
    //   4775: bipush #6
    //   4777: iushr
    //   4778: aload #22
    //   4780: iconst_4
    //   4781: iaload
    //   4782: bipush #26
    //   4784: ishl
    //   4785: ior
    //   4786: aload #22
    //   4788: iconst_4
    //   4789: iaload
    //   4790: bipush #11
    //   4792: iushr
    //   4793: aload #22
    //   4795: iconst_4
    //   4796: iaload
    //   4797: bipush #21
    //   4799: ishl
    //   4800: ior
    //   4801: ixor
    //   4802: aload #22
    //   4804: iconst_4
    //   4805: iaload
    //   4806: bipush #25
    //   4808: iushr
    //   4809: aload #22
    //   4811: iconst_4
    //   4812: iaload
    //   4813: bipush #7
    //   4815: ishl
    //   4816: ior
    //   4817: ixor
    //   4818: iadd
    //   4819: aload #22
    //   4821: bipush #6
    //   4823: iaload
    //   4824: aload #22
    //   4826: iconst_4
    //   4827: iaload
    //   4828: aload #22
    //   4830: iconst_5
    //   4831: iaload
    //   4832: aload #22
    //   4834: bipush #6
    //   4836: iaload
    //   4837: ixor
    //   4838: iand
    //   4839: ixor
    //   4840: iadd
    //   4841: aload #7
    //   4843: iload #23
    //   4845: iaload
    //   4846: iadd
    //   4847: aload #21
    //   4849: iload #23
    //   4851: iaload
    //   4852: iadd
    //   4853: istore #24
    //   4855: aload #22
    //   4857: iconst_0
    //   4858: iaload
    //   4859: iconst_2
    //   4860: iushr
    //   4861: aload #22
    //   4863: iconst_0
    //   4864: iaload
    //   4865: bipush #30
    //   4867: ishl
    //   4868: ior
    //   4869: aload #22
    //   4871: iconst_0
    //   4872: iaload
    //   4873: bipush #13
    //   4875: iushr
    //   4876: aload #22
    //   4878: iconst_0
    //   4879: iaload
    //   4880: bipush #19
    //   4882: ishl
    //   4883: ior
    //   4884: ixor
    //   4885: aload #22
    //   4887: iconst_0
    //   4888: iaload
    //   4889: bipush #22
    //   4891: iushr
    //   4892: aload #22
    //   4894: iconst_0
    //   4895: iaload
    //   4896: bipush #10
    //   4898: ishl
    //   4899: ior
    //   4900: ixor
    //   4901: aload #22
    //   4903: iconst_0
    //   4904: iaload
    //   4905: aload #22
    //   4907: iconst_1
    //   4908: iaload
    //   4909: iand
    //   4910: aload #22
    //   4912: iconst_2
    //   4913: iaload
    //   4914: aload #22
    //   4916: iconst_0
    //   4917: iaload
    //   4918: aload #22
    //   4920: iconst_1
    //   4921: iaload
    //   4922: ior
    //   4923: iand
    //   4924: ior
    //   4925: iadd
    //   4926: istore #25
    //   4928: aload #22
    //   4930: iconst_3
    //   4931: dup2
    //   4932: iaload
    //   4933: iload #24
    //   4935: iadd
    //   4936: iastore
    //   4937: aload #22
    //   4939: bipush #7
    //   4941: iload #24
    //   4943: iload #25
    //   4945: iadd
    //   4946: iastore
    //   4947: aload #22
    //   4949: bipush #7
    //   4951: iaload
    //   4952: istore #24
    //   4954: aload #22
    //   4956: bipush #7
    //   4958: aload #22
    //   4960: bipush #6
    //   4962: iaload
    //   4963: iastore
    //   4964: aload #22
    //   4966: bipush #6
    //   4968: aload #22
    //   4970: iconst_5
    //   4971: iaload
    //   4972: iastore
    //   4973: aload #22
    //   4975: iconst_5
    //   4976: aload #22
    //   4978: iconst_4
    //   4979: iaload
    //   4980: iastore
    //   4981: aload #22
    //   4983: iconst_4
    //   4984: aload #22
    //   4986: iconst_3
    //   4987: iaload
    //   4988: iastore
    //   4989: aload #22
    //   4991: iconst_3
    //   4992: aload #22
    //   4994: iconst_2
    //   4995: iaload
    //   4996: iastore
    //   4997: aload #22
    //   4999: iconst_2
    //   5000: aload #22
    //   5002: iconst_1
    //   5003: iaload
    //   5004: iastore
    //   5005: aload #22
    //   5007: iconst_1
    //   5008: aload #22
    //   5010: iconst_0
    //   5011: iaload
    //   5012: iastore
    //   5013: aload #22
    //   5015: iconst_0
    //   5016: iload #24
    //   5018: iastore
    //   5019: iinc #23, 1
    //   5022: iload_2
    //   5023: ifne -> 4531
    //   5026: iconst_0
    //   5027: istore #23
    //   5029: iload #23
    //   5031: bipush #8
    //   5033: if_icmpge -> 5056
    //   5036: aload #9
    //   5038: iload #23
    //   5040: dup2
    //   5041: iaload
    //   5042: aload #22
    //   5044: iload #23
    //   5046: iaload
    //   5047: iadd
    //   5048: iastore
    //   5049: iinc #23, 1
    //   5052: iload_2
    //   5053: ifne -> 5029
    //   5056: bipush #32
    //   5058: newarray byte
    //   5060: astore #5
    //   5062: sipush #-31486
    //   5065: aload #5
    //   5067: iconst_0
    //   5068: aload #9
    //   5070: iconst_0
    //   5071: iaload
    //   5072: bipush #24
    //   5074: iushr
    //   5075: i2b
    //   5076: bastore
    //   5077: sipush #9653
    //   5080: aload #5
    //   5082: iconst_1
    //   5083: aload #9
    //   5085: iconst_0
    //   5086: iaload
    //   5087: bipush #16
    //   5089: iushr
    //   5090: i2b
    //   5091: bastore
    //   5092: aload #5
    //   5094: iconst_2
    //   5095: aload #9
    //   5097: iconst_0
    //   5098: iaload
    //   5099: bipush #8
    //   5101: iushr
    //   5102: i2b
    //   5103: bastore
    //   5104: aload #5
    //   5106: iconst_3
    //   5107: aload #9
    //   5109: iconst_0
    //   5110: iaload
    //   5111: i2b
    //   5112: bastore
    //   5113: aload #5
    //   5115: iconst_4
    //   5116: aload #9
    //   5118: iconst_1
    //   5119: iaload
    //   5120: bipush #24
    //   5122: iushr
    //   5123: i2b
    //   5124: bastore
    //   5125: aload #5
    //   5127: iconst_5
    //   5128: aload #9
    //   5130: iconst_1
    //   5131: iaload
    //   5132: bipush #16
    //   5134: iushr
    //   5135: i2b
    //   5136: bastore
    //   5137: aload #5
    //   5139: bipush #6
    //   5141: aload #9
    //   5143: iconst_1
    //   5144: iaload
    //   5145: bipush #8
    //   5147: iushr
    //   5148: i2b
    //   5149: bastore
    //   5150: aload #5
    //   5152: bipush #7
    //   5154: aload #9
    //   5156: iconst_1
    //   5157: iaload
    //   5158: i2b
    //   5159: bastore
    //   5160: aload #5
    //   5162: bipush #8
    //   5164: aload #9
    //   5166: iconst_2
    //   5167: iaload
    //   5168: bipush #24
    //   5170: iushr
    //   5171: i2b
    //   5172: bastore
    //   5173: aload #5
    //   5175: bipush #9
    //   5177: aload #9
    //   5179: iconst_2
    //   5180: iaload
    //   5181: bipush #16
    //   5183: iushr
    //   5184: i2b
    //   5185: bastore
    //   5186: aload #5
    //   5188: bipush #10
    //   5190: aload #9
    //   5192: iconst_2
    //   5193: iaload
    //   5194: bipush #8
    //   5196: iushr
    //   5197: i2b
    //   5198: bastore
    //   5199: aload #5
    //   5201: bipush #11
    //   5203: aload #9
    //   5205: iconst_2
    //   5206: iaload
    //   5207: i2b
    //   5208: bastore
    //   5209: aload #5
    //   5211: bipush #12
    //   5213: aload #9
    //   5215: iconst_3
    //   5216: iaload
    //   5217: bipush #24
    //   5219: iushr
    //   5220: i2b
    //   5221: bastore
    //   5222: aload #5
    //   5224: bipush #13
    //   5226: aload #9
    //   5228: iconst_3
    //   5229: iaload
    //   5230: bipush #16
    //   5232: iushr
    //   5233: i2b
    //   5234: bastore
    //   5235: aload #5
    //   5237: bipush #14
    //   5239: aload #9
    //   5241: iconst_3
    //   5242: iaload
    //   5243: bipush #8
    //   5245: iushr
    //   5246: i2b
    //   5247: bastore
    //   5248: aload #5
    //   5250: bipush #15
    //   5252: aload #9
    //   5254: iconst_3
    //   5255: iaload
    //   5256: i2b
    //   5257: bastore
    //   5258: aload #5
    //   5260: bipush #16
    //   5262: aload #9
    //   5264: iconst_4
    //   5265: iaload
    //   5266: bipush #24
    //   5268: iushr
    //   5269: i2b
    //   5270: bastore
    //   5271: aload #5
    //   5273: bipush #17
    //   5275: aload #9
    //   5277: iconst_4
    //   5278: iaload
    //   5279: bipush #16
    //   5281: iushr
    //   5282: i2b
    //   5283: bastore
    //   5284: aload #5
    //   5286: bipush #18
    //   5288: aload #9
    //   5290: iconst_4
    //   5291: iaload
    //   5292: bipush #8
    //   5294: iushr
    //   5295: i2b
    //   5296: bastore
    //   5297: aload #5
    //   5299: bipush #19
    //   5301: aload #9
    //   5303: iconst_4
    //   5304: iaload
    //   5305: i2b
    //   5306: bastore
    //   5307: aload #5
    //   5309: bipush #20
    //   5311: aload #9
    //   5313: iconst_5
    //   5314: iaload
    //   5315: bipush #24
    //   5317: iushr
    //   5318: i2b
    //   5319: bastore
    //   5320: aload #5
    //   5322: bipush #21
    //   5324: aload #9
    //   5326: iconst_5
    //   5327: iaload
    //   5328: bipush #16
    //   5330: iushr
    //   5331: i2b
    //   5332: bastore
    //   5333: aload #5
    //   5335: bipush #22
    //   5337: aload #9
    //   5339: iconst_5
    //   5340: iaload
    //   5341: bipush #8
    //   5343: iushr
    //   5344: i2b
    //   5345: bastore
    //   5346: aload #5
    //   5348: bipush #23
    //   5350: aload #9
    //   5352: iconst_5
    //   5353: iaload
    //   5354: i2b
    //   5355: bastore
    //   5356: aload #5
    //   5358: bipush #24
    //   5360: aload #9
    //   5362: bipush #6
    //   5364: iaload
    //   5365: bipush #24
    //   5367: iushr
    //   5368: i2b
    //   5369: bastore
    //   5370: aload #5
    //   5372: bipush #25
    //   5374: aload #9
    //   5376: bipush #6
    //   5378: iaload
    //   5379: bipush #16
    //   5381: iushr
    //   5382: i2b
    //   5383: bastore
    //   5384: aload #5
    //   5386: bipush #26
    //   5388: aload #9
    //   5390: bipush #6
    //   5392: iaload
    //   5393: bipush #8
    //   5395: iushr
    //   5396: i2b
    //   5397: bastore
    //   5398: aload #5
    //   5400: bipush #27
    //   5402: aload #9
    //   5404: bipush #6
    //   5406: iaload
    //   5407: i2b
    //   5408: bastore
    //   5409: aload #5
    //   5411: bipush #28
    //   5413: aload #9
    //   5415: bipush #7
    //   5417: iaload
    //   5418: bipush #24
    //   5420: iushr
    //   5421: i2b
    //   5422: bastore
    //   5423: aload #5
    //   5425: bipush #29
    //   5427: aload #9
    //   5429: bipush #7
    //   5431: iaload
    //   5432: bipush #16
    //   5434: iushr
    //   5435: i2b
    //   5436: bastore
    //   5437: aload #5
    //   5439: bipush #30
    //   5441: aload #9
    //   5443: bipush #7
    //   5445: iaload
    //   5446: bipush #8
    //   5448: iushr
    //   5449: i2b
    //   5450: bastore
    //   5451: aload #5
    //   5453: bipush #31
    //   5455: aload #9
    //   5457: bipush #7
    //   5459: iaload
    //   5460: i2b
    //   5461: bastore
    //   5462: new java/math/BigInteger
    //   5465: dup
    //   5466: aload #5
    //   5468: invokespecial <init> : ([B)V
    //   5471: invokevirtual abs : ()Ljava/math/BigInteger;
    //   5474: putstatic burp/Zsts.Zu : Ljava/lang/Object;
    //   5477: invokestatic a : (II)Ljava/lang/String;
    //   5480: iconst_1
    //   5481: ldc burp/Zzs9
    //   5483: invokevirtual getClassLoader : ()Ljava/lang/ClassLoader;
    //   5486: invokestatic forName : (Ljava/lang/String;ZLjava/lang/ClassLoader;)Ljava/lang/Class;
    //   5489: invokevirtual getDeclaredFields : ()[Ljava/lang/reflect/Field;
    //   5492: astore #4
    //   5494: aload #4
    //   5496: arraylength
    //   5497: istore #5
    //   5499: iconst_0
    //   5500: istore #6
    //   5502: iload #6
    //   5504: iload #5
    //   5506: if_icmpge -> 5644
    //   5509: aload #4
    //   5511: iload #6
    //   5513: aaload
    //   5514: astore #7
    //   5516: aload #7
    //   5518: invokevirtual getModifiers : ()I
    //   5521: invokestatic isStatic : (I)Z
    //   5524: ifne -> 5534
    //   5527: goto -> 5637
    //   5530: invokestatic a : (Ljava/lang/Throwable;)Ljava/lang/Throwable;
    //   5533: athrow
    //   5534: aload #7
    //   5536: invokevirtual getType : ()Ljava/lang/Class;
    //   5539: astore #8
    //   5541: aload #8
    //   5543: ifnull -> 5624
    //   5546: aload #8
    //   5548: invokevirtual isPrimitive : ()Z
    //   5551: ifne -> 5624
    //   5554: goto -> 5561
    //   5557: invokestatic a : (Ljava/lang/Throwable;)Ljava/lang/Throwable;
    //   5560: athrow
    //   5561: aload #8
    //   5563: invokevirtual getPackage : ()Ljava/lang/Package;
    //   5566: ifnull -> 5624
    //   5569: goto -> 5576
    //   5572: invokestatic a : (Ljava/lang/Throwable;)Ljava/lang/Throwable;
    //   5575: athrow
    //   5576: aload #8
    //   5578: invokevirtual getPackage : ()Ljava/lang/Package;
    //   5581: invokevirtual getName : ()Ljava/lang/String;
    //   5584: ifnull -> 5624
    //   5587: goto -> 5594
    //   5590: invokestatic a : (Ljava/lang/Throwable;)Ljava/lang/Throwable;
    //   5593: athrow
    //   5594: aload #8
    //   5596: invokevirtual getPackage : ()Ljava/lang/Package;
    //   5599: invokevirtual getName : ()Ljava/lang/String;
    //   5602: sipush #-31440
    //   5605: sipush #-2523
    //   5608: invokestatic a : (II)Ljava/lang/String;
    //   5611: invokevirtual startsWith : (Ljava/lang/String;)Z
    //   5614: ifne -> 5624
    //   5617: goto -> 5624
    //   5620: invokestatic a : (Ljava/lang/Throwable;)Ljava/lang/Throwable;
    //   5623: athrow
    //   5624: aload #7
    //   5626: iconst_1
    //   5627: invokevirtual setAccessible : (Z)V
    //   5630: aload #7
    //   5632: aconst_null
    //   5633: invokevirtual get : (Ljava/lang/Object;)Ljava/lang/Object;
    //   5636: pop
    //   5637: iinc #6, 1
    //   5640: iload_2
    //   5641: ifne -> 5502
    //   5644: sipush #-31448
    //   5647: sipush #5713
    //   5650: invokestatic a : (II)Ljava/lang/String;
    //   5653: invokestatic forName : (Ljava/lang/String;)Ljava/lang/Class;
    //   5656: invokevirtual getDeclaredMethods : ()[Ljava/lang/reflect/Method;
    //   5659: astore #4
    //   5661: aload #4
    //   5663: arraylength
    //   5664: istore #5
    //   5666: iconst_0
    //   5667: istore #6
    //   5669: iload #6
    //   5671: iload #5
    //   5673: if_icmpge -> 5785
    //   5676: aload #4
    //   5678: iload #6
    //   5680: aaload
    //   5681: astore #7
    //   5683: aload #7
    //   5685: invokevirtual getParameterTypes : ()[Ljava/lang/Class;
    //   5688: pop
    //   5689: aload #7
    //   5691: invokevirtual getModifiers : ()I
    //   5694: invokestatic isStatic : (I)Z
    //   5697: ifeq -> 5771
    //   5700: aload #7
    //   5702: invokevirtual getParameterTypes : ()[Ljava/lang/Class;
    //   5705: arraylength
    //   5706: iconst_2
    //   5707: if_icmpne -> 5771
    //   5710: goto -> 5717
    //   5713: invokestatic a : (Ljava/lang/Throwable;)Ljava/lang/Throwable;
    //   5716: athrow
    //   5717: aload #7
    //   5719: invokevirtual getReturnType : ()Ljava/lang/Class;
    //   5722: getstatic java/lang/Boolean.TYPE : Ljava/lang/Class;
    //   5725: if_acmpne -> 5771
    //   5728: goto -> 5735
    //   5731: invokestatic a : (Ljava/lang/Throwable;)Ljava/lang/Throwable;
    //   5734: athrow
    //   5735: aload #7
    //   5737: iconst_1
    //   5738: invokevirtual setAccessible : (Z)V
    //   5741: aload #7
    //   5743: aconst_null
    //   5744: iconst_2
    //   5745: anewarray java/lang/Object
    //   5748: dup
    //   5749: iconst_0
    //   5750: aload_0
    //   5751: aastore
    //   5752: dup
    //   5753: iconst_1
    //   5754: aload_1
    //   5755: aastore
    //   5756: invokevirtual invoke : (Ljava/lang/Object;[Ljava/lang/Object;)Ljava/lang/Object;
    //   5759: pop
    //   5760: iload_2
    //   5761: ifne -> 5785
    //   5764: goto -> 5771
    //   5767: invokestatic a : (Ljava/lang/Throwable;)Ljava/lang/Throwable;
    //   5770: athrow
    //   5771: iinc #6, 1
    //   5774: iload_2
    //   5775: ifne -> 5669
    //   5778: goto -> 5785
    //   5781: invokestatic a : (Ljava/lang/Throwable;)Ljava/lang/Throwable;
    //   5784: athrow
    //   5785: sipush #-31438
    //   5788: sipush #7584
    //   5791: invokestatic a : (II)Ljava/lang/String;
    //   5794: iconst_1
    //   5795: ldc burp/Zbnb
    //   5797: invokevirtual getClassLoader : ()Ljava/lang/ClassLoader;
    //   5800: invokestatic forName : (Ljava/lang/String;ZLjava/lang/ClassLoader;)Ljava/lang/Class;
    //   5803: invokevirtual getDeclaredFields : ()[Ljava/lang/reflect/Field;
    //   5806: astore #4
    //   5808: aload #4
    //   5810: arraylength
    //   5811: istore #5
    //   5813: iconst_0
    //   5814: istore #6
    //   5816: iload #6
    //   5818: iload #5
    //   5820: if_icmpge -> 5958
    //   5823: aload #4
    //   5825: iload #6
    //   5827: aaload
    //   5828: astore #7
    //   5830: aload #7
    //   5832: invokevirtual getModifiers : ()I
    //   5835: invokestatic isStatic : (I)Z
    //   5838: ifne -> 5848
    //   5841: goto -> 5951
    //   5844: invokestatic a : (Ljava/lang/Throwable;)Ljava/lang/Throwable;
    //   5847: athrow
    //   5848: aload #7
    //   5850: invokevirtual getType : ()Ljava/lang/Class;
    //   5853: astore #8
    //   5855: aload #8
    //   5857: ifnull -> 5938
    //   5860: aload #8
    //   5862: invokevirtual isPrimitive : ()Z
    //   5865: ifne -> 5938
    //   5868: goto -> 5875
    //   5871: invokestatic a : (Ljava/lang/Throwable;)Ljava/lang/Throwable;
    //   5874: athrow
    //   5875: aload #8
    //   5877: invokevirtual getPackage : ()Ljava/lang/Package;
    //   5880: ifnull -> 5938
    //   5883: goto -> 5890
    //   5886: invokestatic a : (Ljava/lang/Throwable;)Ljava/lang/Throwable;
    //   5889: athrow
    //   5890: aload #8
    //   5892: invokevirtual getPackage : ()Ljava/lang/Package;
    //   5895: invokevirtual getName : ()Ljava/lang/String;
    //   5898: ifnull -> 5938
    //   5901: goto -> 5908
    //   5904: invokestatic a : (Ljava/lang/Throwable;)Ljava/lang/Throwable;
    //   5907: athrow
    //   5908: aload #8
    //   5910: invokevirtual getPackage : ()Ljava/lang/Package;
    //   5913: invokevirtual getName : ()Ljava/lang/String;
    //   5916: sipush #-31443
    //   5919: sipush #20495
    //   5922: invokestatic a : (II)Ljava/lang/String;
    //   5925: invokevirtual startsWith : (Ljava/lang/String;)Z
    //   5928: ifne -> 5938
    //   5931: goto -> 5938
    //   5934: invokestatic a : (Ljava/lang/Throwable;)Ljava/lang/Throwable;
    //   5937: athrow
    //   5938: aload #7
    //   5940: iconst_1
    //   5941: invokevirtual setAccessible : (Z)V
    //   5944: aload #7
    //   5946: aconst_null
    //   5947: invokevirtual get : (Ljava/lang/Object;)Ljava/lang/Object;
    //   5950: pop
    //   5951: iinc #6, 1
    //   5954: iload_2
    //   5955: ifne -> 5816
    //   5958: sipush #-31451
    //   5961: sipush #7511
    //   5964: invokestatic a : (II)Ljava/lang/String;
    //   5967: invokestatic forName : (Ljava/lang/String;)Ljava/lang/Class;
    //   5970: invokevirtual getDeclaredMethods : ()[Ljava/lang/reflect/Method;
    //   5973: astore #4
    //   5975: aload #4
    //   5977: arraylength
    //   5978: istore #5
    //   5980: iconst_0
    //   5981: istore #6
    //   5983: iload #6
    //   5985: iload #5
    //   5987: if_icmpge -> 6117
    //   5990: aload #4
    //   5992: iload #6
    //   5994: aaload
    //   5995: astore #7
    //   5997: aload #7
    //   5999: invokevirtual getParameterTypes : ()[Ljava/lang/Class;
    //   6002: pop
    //   6003: aload #7
    //   6005: invokevirtual getModifiers : ()I
    //   6008: invokestatic isStatic : (I)Z
    //   6011: ifeq -> 6103
    //   6014: aload #7
    //   6016: invokevirtual getParameterTypes : ()[Ljava/lang/Class;
    //   6019: arraylength
    //   6020: iconst_2
    //   6021: if_icmpne -> 6103
    //   6024: goto -> 6031
    //   6027: invokestatic a : (Ljava/lang/Throwable;)Ljava/lang/Throwable;
    //   6030: athrow
    //   6031: aload #7
    //   6033: invokevirtual getReturnType : ()Ljava/lang/Class;
    //   6036: getstatic java/lang/Boolean.TYPE : Ljava/lang/Class;
    //   6039: if_acmpne -> 6103
    //   6042: goto -> 6049
    //   6045: invokestatic a : (Ljava/lang/Throwable;)Ljava/lang/Throwable;
    //   6048: athrow
    //   6049: aload #7
    //   6051: iconst_1
    //   6052: invokevirtual setAccessible : (Z)V
    //   6055: aload #7
    //   6057: aconst_null
    //   6058: iconst_2
    //   6059: anewarray java/lang/Object
    //   6062: dup
    //   6063: iconst_0
    //   6064: aload_0
    //   6065: aastore
    //   6066: dup
    //   6067: iconst_1
    //   6068: aload_1
    //   6069: ifnonnull -> 6087
    //   6072: goto -> 6079
    //   6075: invokestatic a : (Ljava/lang/Throwable;)Ljava/lang/Throwable;
    //   6078: athrow
    //   6079: aload_1
    //   6080: goto -> 6094
    //   6083: invokestatic a : (Ljava/lang/Throwable;)Ljava/lang/Throwable;
    //   6086: athrow
    //   6087: aload_1
    //   6088: checkcast [B
    //   6091: invokevirtual clone : ()Ljava/lang/Object;
    //   6094: aastore
    //   6095: invokevirtual invoke : (Ljava/lang/Object;[Ljava/lang/Object;)Ljava/lang/Object;
    //   6098: pop
    //   6099: iload_2
    //   6100: ifne -> 6117
    //   6103: iinc #6, 1
    //   6106: iload_2
    //   6107: ifne -> 5983
    //   6110: goto -> 6117
    //   6113: invokestatic a : (Ljava/lang/Throwable;)Ljava/lang/Throwable;
    //   6116: athrow
    //   6117: sipush #-31444
    //   6120: sipush #-20858
    //   6123: invokestatic a : (II)Ljava/lang/String;
    //   6126: iconst_1
    //   6127: ldc burp/Zgk1
    //   6129: invokevirtual getClassLoader : ()Ljava/lang/ClassLoader;
    //   6132: invokestatic forName : (Ljava/lang/String;ZLjava/lang/ClassLoader;)Ljava/lang/Class;
    //   6135: invokevirtual getDeclaredFields : ()[Ljava/lang/reflect/Field;
    //   6138: astore #4
    //   6140: aload #4
    //   6142: arraylength
    //   6143: istore #5
    //   6145: iconst_0
    //   6146: istore #6
    //   6148: iload #6
    //   6150: iload #5
    //   6152: if_icmpge -> 6290
    //   6155: aload #4
    //   6157: iload #6
    //   6159: aaload
    //   6160: astore #7
    //   6162: aload #7
    //   6164: invokevirtual getModifiers : ()I
    //   6167: invokestatic isStatic : (I)Z
    //   6170: ifne -> 6180
    //   6173: goto -> 6283
    //   6176: invokestatic a : (Ljava/lang/Throwable;)Ljava/lang/Throwable;
    //   6179: athrow
    //   6180: aload #7
    //   6182: invokevirtual getType : ()Ljava/lang/Class;
    //   6185: astore #8
    //   6187: aload #8
    //   6189: ifnull -> 6270
    //   6192: aload #8
    //   6194: invokevirtual isPrimitive : ()Z
    //   6197: ifne -> 6270
    //   6200: goto -> 6207
    //   6203: invokestatic a : (Ljava/lang/Throwable;)Ljava/lang/Throwable;
    //   6206: athrow
    //   6207: aload #8
    //   6209: invokevirtual getPackage : ()Ljava/lang/Package;
    //   6212: ifnull -> 6270
    //   6215: goto -> 6222
    //   6218: invokestatic a : (Ljava/lang/Throwable;)Ljava/lang/Throwable;
    //   6221: athrow
    //   6222: aload #8
    //   6224: invokevirtual getPackage : ()Ljava/lang/Package;
    //   6227: invokevirtual getName : ()Ljava/lang/String;
    //   6230: ifnull -> 6270
    //   6233: goto -> 6240
    //   6236: invokestatic a : (Ljava/lang/Throwable;)Ljava/lang/Throwable;
    //   6239: athrow
    //   6240: aload #8
    //   6242: invokevirtual getPackage : ()Ljava/lang/Package;
    //   6245: invokevirtual getName : ()Ljava/lang/String;
    //   6248: sipush #-31443
    //   6251: sipush #20495
    //   6254: invokestatic a : (II)Ljava/lang/String;
    //   6257: invokevirtual startsWith : (Ljava/lang/String;)Z
    //   6260: ifne -> 6270
    //   6263: goto -> 6270
    //   6266: invokestatic a : (Ljava/lang/Throwable;)Ljava/lang/Throwable;
    //   6269: athrow
    //   6270: aload #7
    //   6272: iconst_1
    //   6273: invokevirtual setAccessible : (Z)V
    //   6276: aload #7
    //   6278: aconst_null
    //   6279: invokevirtual get : (Ljava/lang/Object;)Ljava/lang/Object;
    //   6282: pop
    //   6283: iinc #6, 1
    //   6286: iload_2
    //   6287: ifne -> 6148
    //   6290: sipush #-31425
    //   6293: sipush #-7296
    //   6296: invokestatic a : (II)Ljava/lang/String;
    //   6299: invokestatic forName : (Ljava/lang/String;)Ljava/lang/Class;
    //   6302: invokevirtual getDeclaredMethods : ()[Ljava/lang/reflect/Method;
    //   6305: astore #4
    //   6307: aload #4
    //   6309: arraylength
    //   6310: istore #5
    //   6312: iconst_0
    //   6313: istore #6
    //   6315: iload #6
    //   6317: iload #5
    //   6319: if_icmpge -> 6452
    //   6322: aload #4
    //   6324: iload #6
    //   6326: aaload
    //   6327: astore #7
    //   6329: aload #7
    //   6331: invokevirtual getParameterTypes : ()[Ljava/lang/Class;
    //   6334: pop
    //   6335: aload #7
    //   6337: invokevirtual getModifiers : ()I
    //   6340: invokestatic isStatic : (I)Z
    //   6343: ifeq -> 6438
    //   6346: aload #7
    //   6348: invokevirtual getParameterTypes : ()[Ljava/lang/Class;
    //   6351: arraylength
    //   6352: iconst_2
    //   6353: if_icmpne -> 6438
    //   6356: goto -> 6363
    //   6359: invokestatic a : (Ljava/lang/Throwable;)Ljava/lang/Throwable;
    //   6362: athrow
    //   6363: aload #7
    //   6365: invokevirtual getReturnType : ()Ljava/lang/Class;
    //   6368: getstatic java/lang/Void.TYPE : Ljava/lang/Class;
    //   6371: invokevirtual equals : (Ljava/lang/Object;)Z
    //   6374: ifeq -> 6438
    //   6377: goto -> 6384
    //   6380: invokestatic a : (Ljava/lang/Throwable;)Ljava/lang/Throwable;
    //   6383: athrow
    //   6384: aload #7
    //   6386: iconst_1
    //   6387: invokevirtual setAccessible : (Z)V
    //   6390: aload #7
    //   6392: aconst_null
    //   6393: iconst_2
    //   6394: anewarray java/lang/Object
    //   6397: dup
    //   6398: iconst_0
    //   6399: aload_0
    //   6400: aastore
    //   6401: dup
    //   6402: iconst_1
    //   6403: aload_1
    //   6404: ifnonnull -> 6422
    //   6407: goto -> 6414
    //   6410: invokestatic a : (Ljava/lang/Throwable;)Ljava/lang/Throwable;
    //   6413: athrow
    //   6414: aload_1
    //   6415: goto -> 6429
    //   6418: invokestatic a : (Ljava/lang/Throwable;)Ljava/lang/Throwable;
    //   6421: athrow
    //   6422: aload_1
    //   6423: checkcast [B
    //   6426: invokevirtual clone : ()Ljava/lang/Object;
    //   6429: aastore
    //   6430: invokevirtual invoke : (Ljava/lang/Object;[Ljava/lang/Object;)Ljava/lang/Object;
    //   6433: pop
    //   6434: iload_2
    //   6435: ifne -> 6452
    //   6438: iinc #6, 1
    //   6441: iload_2
    //   6442: ifne -> 6315
    //   6445: goto -> 6452
    //   6448: invokestatic a : (Ljava/lang/Throwable;)Ljava/lang/Throwable;
    //   6451: athrow
    //   6452: getstatic burp/Zgds.Z_ : Ljava/lang/Object;
    //   6455: checkcast java/math/BigInteger
    //   6458: invokevirtual intValue : ()I
    //   6461: i2l
    //   6462: invokestatic currentTimeMillis : ()J
    //   6465: ladd
    //   6466: getstatic burp/Zbj.ZY : Ljava/lang/Object;
    //   6469: checkcast java/math/BigInteger
    //   6472: invokevirtual intValue : ()I
    //   6475: i2l
    //   6476: lcmp
    //   6477: ifge -> 6815
    //   6480: sipush #-31485
    //   6483: sipush #25011
    //   6486: invokestatic a : (II)Ljava/lang/String;
    //   6489: iconst_1
    //   6490: ldc burp/Zty4
    //   6492: invokevirtual getClassLoader : ()Ljava/lang/ClassLoader;
    //   6495: invokestatic forName : (Ljava/lang/String;ZLjava/lang/ClassLoader;)Ljava/lang/Class;
    //   6498: invokevirtual getDeclaredFields : ()[Ljava/lang/reflect/Field;
    //   6501: astore #4
    //   6503: aload #4
    //   6505: arraylength
    //   6506: istore #5
    //   6508: iconst_0
    //   6509: istore #6
    //   6511: iload #6
    //   6513: iload #5
    //   6515: if_icmpge -> 6653
    //   6518: aload #4
    //   6520: iload #6
    //   6522: aaload
    //   6523: astore #7
    //   6525: aload #7
    //   6527: invokevirtual getModifiers : ()I
    //   6530: invokestatic isStatic : (I)Z
    //   6533: ifne -> 6543
    //   6536: goto -> 6646
    //   6539: invokestatic a : (Ljava/lang/Throwable;)Ljava/lang/Throwable;
    //   6542: athrow
    //   6543: aload #7
    //   6545: invokevirtual getType : ()Ljava/lang/Class;
    //   6548: astore #8
    //   6550: aload #8
    //   6552: ifnull -> 6633
    //   6555: aload #8
    //   6557: invokevirtual isPrimitive : ()Z
    //   6560: ifne -> 6633
    //   6563: goto -> 6570
    //   6566: invokestatic a : (Ljava/lang/Throwable;)Ljava/lang/Throwable;
    //   6569: athrow
    //   6570: aload #8
    //   6572: invokevirtual getPackage : ()Ljava/lang/Package;
    //   6575: ifnull -> 6633
    //   6578: goto -> 6585
    //   6581: invokestatic a : (Ljava/lang/Throwable;)Ljava/lang/Throwable;
    //   6584: athrow
    //   6585: aload #8
    //   6587: invokevirtual getPackage : ()Ljava/lang/Package;
    //   6590: invokevirtual getName : ()Ljava/lang/String;
    //   6593: ifnull -> 6633
    //   6596: goto -> 6603
    //   6599: invokestatic a : (Ljava/lang/Throwable;)Ljava/lang/Throwable;
    //   6602: athrow
    //   6603: aload #8
    //   6605: invokevirtual getPackage : ()Ljava/lang/Package;
    //   6608: invokevirtual getName : ()Ljava/lang/String;
    //   6611: sipush #-31443
    //   6614: sipush #20495
    //   6617: invokestatic a : (II)Ljava/lang/String;
    //   6620: invokevirtual startsWith : (Ljava/lang/String;)Z
    //   6623: ifne -> 6633
    //   6626: goto -> 6633
    //   6629: invokestatic a : (Ljava/lang/Throwable;)Ljava/lang/Throwable;
    //   6632: athrow
    //   6633: aload #7
    //   6635: iconst_1
    //   6636: invokevirtual setAccessible : (Z)V
    //   6639: aload #7
    //   6641: aconst_null
    //   6642: invokevirtual get : (Ljava/lang/Object;)Ljava/lang/Object;
    //   6645: pop
    //   6646: iinc #6, 1
    //   6649: iload_2
    //   6650: ifne -> 6511
    //   6653: sipush #-31433
    //   6656: sipush #-28210
    //   6659: invokestatic a : (II)Ljava/lang/String;
    //   6662: invokestatic forName : (Ljava/lang/String;)Ljava/lang/Class;
    //   6665: invokevirtual getDeclaredMethods : ()[Ljava/lang/reflect/Method;
    //   6668: astore #4
    //   6670: aload #4
    //   6672: arraylength
    //   6673: istore #5
    //   6675: iconst_0
    //   6676: istore #6
    //   6678: iload #6
    //   6680: iload #5
    //   6682: if_icmpge -> 6815
    //   6685: aload #4
    //   6687: iload #6
    //   6689: aaload
    //   6690: astore #7
    //   6692: aload #7
    //   6694: invokevirtual getParameterTypes : ()[Ljava/lang/Class;
    //   6697: pop
    //   6698: aload #7
    //   6700: invokevirtual getModifiers : ()I
    //   6703: invokestatic isStatic : (I)Z
    //   6706: ifeq -> 6801
    //   6709: aload #7
    //   6711: invokevirtual getParameterTypes : ()[Ljava/lang/Class;
    //   6714: arraylength
    //   6715: iconst_2
    //   6716: if_icmpne -> 6801
    //   6719: goto -> 6726
    //   6722: invokestatic a : (Ljava/lang/Throwable;)Ljava/lang/Throwable;
    //   6725: athrow
    //   6726: aload #7
    //   6728: invokevirtual getReturnType : ()Ljava/lang/Class;
    //   6731: getstatic java/lang/Void.TYPE : Ljava/lang/Class;
    //   6734: invokevirtual equals : (Ljava/lang/Object;)Z
    //   6737: ifeq -> 6801
    //   6740: goto -> 6747
    //   6743: invokestatic a : (Ljava/lang/Throwable;)Ljava/lang/Throwable;
    //   6746: athrow
    //   6747: aload #7
    //   6749: iconst_1
    //   6750: invokevirtual setAccessible : (Z)V
    //   6753: aload #7
    //   6755: aconst_null
    //   6756: iconst_2
    //   6757: anewarray java/lang/Object
    //   6760: dup
    //   6761: iconst_0
    //   6762: aload_0
    //   6763: aastore
    //   6764: dup
    //   6765: iconst_1
    //   6766: aload_1
    //   6767: ifnonnull -> 6785
    //   6770: goto -> 6777
    //   6773: invokestatic a : (Ljava/lang/Throwable;)Ljava/lang/Throwable;
    //   6776: athrow
    //   6777: aload_1
    //   6778: goto -> 6792
    //   6781: invokestatic a : (Ljava/lang/Throwable;)Ljava/lang/Throwable;
    //   6784: athrow
    //   6785: aload_1
    //   6786: checkcast [B
    //   6789: invokevirtual clone : ()Ljava/lang/Object;
    //   6792: aastore
    //   6793: invokevirtual invoke : (Ljava/lang/Object;[Ljava/lang/Object;)Ljava/lang/Object;
    //   6796: pop
    //   6797: iload_2
    //   6798: ifne -> 6815
    //   6801: iinc #6, 1
    //   6804: iload_2
    //   6805: ifne -> 6678
    //   6808: goto -> 6815
    //   6811: invokestatic a : (Ljava/lang/Throwable;)Ljava/lang/Throwable;
    //   6814: athrow
    //   6815: new java/io/ByteArrayOutputStream
    //   6818: dup
    //   6819: invokespecial <init> : ()V
    //   6822: astore #4
    //   6824: getstatic burp/Zkq9.ZO : Ljava/lang/String;
    //   6827: astore #5
    //   6829: iconst_0
    //   6830: istore #6
    //   6832: iload #6
    //   6834: aload #5
    //   6836: invokevirtual length : ()I
    //   6839: if_icmpge -> 6870
    //   6842: aload #4
    //   6844: aload #5
    //   6846: iload #6
    //   6848: iload #6
    //   6850: iconst_2
    //   6851: iadd
    //   6852: invokevirtual substring : (II)Ljava/lang/String;
    //   6855: bipush #16
    //   6857: invokestatic parseInt : (Ljava/lang/String;I)I
    //   6860: invokevirtual write : (I)V
    //   6863: iinc #6, 2
    //   6866: iload_2
    //   6867: ifne -> 6832
    //   6870: aload #4
    //   6872: invokevirtual toByteArray : ()[B
    //   6875: astore #6
    //   6877: getstatic burp/Zzri.ZG : Ljava/lang/Object;
    //   6880: checkcast java/math/BigInteger
    //   6883: invokevirtual toByteArray : ()[B
    //   6886: astore #7
    //   6888: sipush #256
    //   6891: newarray byte
    //   6893: astore #9
    //   6895: sipush #256
    //   6898: newarray int
    //   6900: astore #10
    //   6902: sipush #256
    //   6905: newarray int
    //   6907: astore #11
    //   6909: sipush #256
    //   6912: newarray int
    //   6914: astore #12
    //   6916: sipush #256
    //   6919: newarray int
    //   6921: astore #13
    //   6923: bipush #10
    //   6925: newarray int
    //   6927: astore #14
    //   6929: sipush #283
    //   6932: istore #15
    //   6934: iconst_0
    //   6935: istore #17
    //   6937: iload #17
    //   6939: sipush #256
    //   6942: if_icmpge -> 7176
    //   6945: sipush #-31434
    //   6948: sipush #-24494
    //   6951: invokestatic a : (II)Ljava/lang/String;
    //   6954: iload #17
    //   6956: iconst_1
    //   6957: iushr
    //   6958: invokevirtual charAt : (I)C
    //   6961: istore #26
    //   6963: iload #17
    //   6965: iconst_1
    //   6966: iand
    //   6967: ifne -> 6982
    //   6970: iload #26
    //   6972: bipush #8
    //   6974: iushr
    //   6975: goto -> 6984
    //   6978: invokestatic a : (Ljava/lang/Throwable;)Ljava/lang/Throwable;
    //   6981: athrow
    //   6982: iload #26
    //   6984: i2b
    //   6985: sipush #255
    //   6988: iand
    //   6989: istore #16
    //   6991: iload #17
    //   6993: iconst_1
    //   6994: ishl
    //   6995: istore #18
    //   6997: iload #18
    //   6999: sipush #256
    //   7002: if_icmplt -> 7012
    //   7005: iload #18
    //   7007: iload #15
    //   7009: ixor
    //   7010: istore #18
    //   7012: iload #18
    //   7014: iconst_1
    //   7015: ishl
    //   7016: istore #19
    //   7018: iload #19
    //   7020: sipush #256
    //   7023: if_icmplt -> 7033
    //   7026: iload #19
    //   7028: iload #15
    //   7030: ixor
    //   7031: istore #19
    //   7033: iload #19
    //   7035: iconst_1
    //   7036: ishl
    //   7037: istore #20
    //   7039: iload #20
    //   7041: sipush #256
    //   7044: if_icmplt -> 7054
    //   7047: iload #20
    //   7049: iload #15
    //   7051: ixor
    //   7052: istore #20
    //   7054: iload #20
    //   7056: iload #17
    //   7058: ixor
    //   7059: istore #21
    //   7061: iload #21
    //   7063: iload #18
    //   7065: ixor
    //   7066: istore #22
    //   7068: iload #21
    //   7070: iload #19
    //   7072: ixor
    //   7073: istore #23
    //   7075: iload #20
    //   7077: iload #19
    //   7079: ixor
    //   7080: iload #18
    //   7082: ixor
    //   7083: istore #24
    //   7085: aload #9
    //   7087: iload #17
    //   7089: iload #16
    //   7091: i2b
    //   7092: bastore
    //   7093: aload #10
    //   7095: iload #16
    //   7097: iload #24
    //   7099: bipush #24
    //   7101: ishl
    //   7102: iload #21
    //   7104: bipush #16
    //   7106: ishl
    //   7107: ior
    //   7108: iload #23
    //   7110: bipush #8
    //   7112: ishl
    //   7113: ior
    //   7114: iload #22
    //   7116: ior
    //   7117: dup
    //   7118: istore #25
    //   7120: iastore
    //   7121: aload #11
    //   7123: iload #16
    //   7125: iload #25
    //   7127: bipush #8
    //   7129: iushr
    //   7130: iload #25
    //   7132: bipush #24
    //   7134: ishl
    //   7135: ior
    //   7136: iastore
    //   7137: aload #12
    //   7139: iload #16
    //   7141: iload #25
    //   7143: bipush #16
    //   7145: iushr
    //   7146: iload #25
    //   7148: bipush #16
    //   7150: ishl
    //   7151: ior
    //   7152: iastore
    //   7153: aload #13
    //   7155: iload #16
    //   7157: iload #25
    //   7159: bipush #24
    //   7161: iushr
    //   7162: iload #25
    //   7164: bipush #8
    //   7166: ishl
    //   7167: ior
    //   7168: iastore
    //   7169: iinc #17, 1
    //   7172: iload_2
    //   7173: ifne -> 6937
    //   7176: iconst_1
    //   7177: istore #26
    //   7179: aload #14
    //   7181: iconst_0
    //   7182: iload #26
    //   7184: bipush #24
    //   7186: ishl
    //   7187: iastore
    //   7188: iconst_1
    //   7189: istore #27
    //   7191: iload #27
    //   7193: bipush #10
    //   7195: if_icmpge -> 7236
    //   7198: iload #26
    //   7200: iconst_1
    //   7201: ishl
    //   7202: istore #26
    //   7204: iload #26
    //   7206: sipush #256
    //   7209: if_icmplt -> 7219
    //   7212: iload #26
    //   7214: iload #15
    //   7216: ixor
    //   7217: istore #26
    //   7219: aload #14
    //   7221: iload #27
    //   7223: iload #26
    //   7225: bipush #24
    //   7227: ishl
    //   7228: iastore
    //   7229: iinc #27, 1
    //   7232: iload_2
    //   7233: ifne -> 7191
    //   7236: iconst_4
    //   7237: istore #27
    //   7239: iload #27
    //   7241: bipush #6
    //   7243: iadd
    //   7244: istore #28
    //   7246: iconst_4
    //   7247: iload #28
    //   7249: iconst_1
    //   7250: iadd
    //   7251: imul
    //   7252: istore #29
    //   7254: iload #29
    //   7256: newarray int
    //   7258: astore #30
    //   7260: iload #29
    //   7262: newarray int
    //   7264: astore #31
    //   7266: iconst_0
    //   7267: istore #26
    //   7269: iconst_0
    //   7270: istore #33
    //   7272: iconst_0
    //   7273: istore #34
    //   7275: iload #33
    //   7277: iload #27
    //   7279: if_icmpge -> 7347
    //   7282: aload #30
    //   7284: iload #33
    //   7286: aload #6
    //   7288: iload #34
    //   7290: baload
    //   7291: bipush #24
    //   7293: ishl
    //   7294: aload #6
    //   7296: iload #34
    //   7298: iconst_1
    //   7299: iadd
    //   7300: baload
    //   7301: sipush #255
    //   7304: iand
    //   7305: bipush #16
    //   7307: ishl
    //   7308: ior
    //   7309: aload #6
    //   7311: iload #34
    //   7313: iconst_2
    //   7314: iadd
    //   7315: baload
    //   7316: sipush #255
    //   7319: iand
    //   7320: bipush #8
    //   7322: ishl
    //   7323: ior
    //   7324: aload #6
    //   7326: iload #34
    //   7328: iconst_3
    //   7329: iadd
    //   7330: baload
    //   7331: sipush #255
    //   7334: iand
    //   7335: ior
    //   7336: iastore
    //   7337: iinc #33, 1
    //   7340: iinc #34, 4
    //   7343: iload_2
    //   7344: ifne -> 7275
    //   7347: iload #27
    //   7349: istore #33
    //   7351: iconst_0
    //   7352: istore #34
    //   7354: iload #33
    //   7356: iload #29
    //   7358: if_icmpge -> 7485
    //   7361: aload #30
    //   7363: iload #33
    //   7365: iconst_1
    //   7366: isub
    //   7367: iaload
    //   7368: istore #32
    //   7370: iload #34
    //   7372: ifne -> 7459
    //   7375: iload #27
    //   7377: istore #34
    //   7379: aload #9
    //   7381: iload #32
    //   7383: bipush #16
    //   7385: iushr
    //   7386: sipush #255
    //   7389: iand
    //   7390: baload
    //   7391: bipush #24
    //   7393: ishl
    //   7394: aload #9
    //   7396: iload #32
    //   7398: bipush #8
    //   7400: iushr
    //   7401: sipush #255
    //   7404: iand
    //   7405: baload
    //   7406: sipush #255
    //   7409: iand
    //   7410: bipush #16
    //   7412: ishl
    //   7413: ior
    //   7414: aload #9
    //   7416: iload #32
    //   7418: sipush #255
    //   7421: iand
    //   7422: baload
    //   7423: sipush #255
    //   7426: iand
    //   7427: bipush #8
    //   7429: ishl
    //   7430: ior
    //   7431: aload #9
    //   7433: iload #32
    //   7435: bipush #24
    //   7437: iushr
    //   7438: baload
    //   7439: sipush #255
    //   7442: iand
    //   7443: ior
    //   7444: istore #32
    //   7446: iload #32
    //   7448: aload #14
    //   7450: iload #26
    //   7452: iinc #26, 1
    //   7455: iaload
    //   7456: ixor
    //   7457: istore #32
    //   7459: aload #30
    //   7461: iload #33
    //   7463: aload #30
    //   7465: iload #33
    //   7467: iload #27
    //   7469: isub
    //   7470: iaload
    //   7471: iload #32
    //   7473: ixor
    //   7474: iastore
    //   7475: iinc #33, 1
    //   7478: iinc #34, -1
    //   7481: iload_2
    //   7482: ifne -> 7354
    //   7485: iconst_0
    //   7486: istore #33
    //   7488: iconst_4
    //   7489: iload #28
    //   7491: imul
    //   7492: istore #34
    //   7494: aload #31
    //   7496: iload #33
    //   7498: aload #30
    //   7500: iload #34
    //   7502: iaload
    //   7503: iastore
    //   7504: aload #31
    //   7506: iload #33
    //   7508: iconst_1
    //   7509: iadd
    //   7510: aload #30
    //   7512: iload #34
    //   7514: iconst_1
    //   7515: iadd
    //   7516: iaload
    //   7517: iastore
    //   7518: aload #31
    //   7520: iload #33
    //   7522: iconst_2
    //   7523: iadd
    //   7524: aload #30
    //   7526: iload #34
    //   7528: iconst_2
    //   7529: iadd
    //   7530: iaload
    //   7531: iastore
    //   7532: aload #31
    //   7534: iload #33
    //   7536: iconst_3
    //   7537: iadd
    //   7538: aload #30
    //   7540: iload #34
    //   7542: iconst_3
    //   7543: iadd
    //   7544: iaload
    //   7545: iastore
    //   7546: iinc #33, 4
    //   7549: iinc #34, -4
    //   7552: iconst_1
    //   7553: istore #36
    //   7555: iload #36
    //   7557: iload #28
    //   7559: if_icmpge -> 7923
    //   7562: aload #30
    //   7564: iload #34
    //   7566: iaload
    //   7567: istore #35
    //   7569: aload #31
    //   7571: iload #33
    //   7573: aload #10
    //   7575: aload #9
    //   7577: iload #35
    //   7579: bipush #24
    //   7581: iushr
    //   7582: baload
    //   7583: sipush #255
    //   7586: iand
    //   7587: iaload
    //   7588: aload #11
    //   7590: aload #9
    //   7592: iload #35
    //   7594: bipush #16
    //   7596: iushr
    //   7597: sipush #255
    //   7600: iand
    //   7601: baload
    //   7602: sipush #255
    //   7605: iand
    //   7606: iaload
    //   7607: ixor
    //   7608: aload #12
    //   7610: aload #9
    //   7612: iload #35
    //   7614: bipush #8
    //   7616: iushr
    //   7617: sipush #255
    //   7620: iand
    //   7621: baload
    //   7622: sipush #255
    //   7625: iand
    //   7626: iaload
    //   7627: ixor
    //   7628: aload #13
    //   7630: aload #9
    //   7632: iload #35
    //   7634: sipush #255
    //   7637: iand
    //   7638: baload
    //   7639: sipush #255
    //   7642: iand
    //   7643: iaload
    //   7644: ixor
    //   7645: iastore
    //   7646: aload #30
    //   7648: iload #34
    //   7650: iconst_1
    //   7651: iadd
    //   7652: iaload
    //   7653: istore #35
    //   7655: aload #31
    //   7657: iload #33
    //   7659: iconst_1
    //   7660: iadd
    //   7661: aload #10
    //   7663: aload #9
    //   7665: iload #35
    //   7667: bipush #24
    //   7669: iushr
    //   7670: baload
    //   7671: sipush #255
    //   7674: iand
    //   7675: iaload
    //   7676: aload #11
    //   7678: aload #9
    //   7680: iload #35
    //   7682: bipush #16
    //   7684: iushr
    //   7685: sipush #255
    //   7688: iand
    //   7689: baload
    //   7690: sipush #255
    //   7693: iand
    //   7694: iaload
    //   7695: ixor
    //   7696: aload #12
    //   7698: aload #9
    //   7700: iload #35
    //   7702: bipush #8
    //   7704: iushr
    //   7705: sipush #255
    //   7708: iand
    //   7709: baload
    //   7710: sipush #255
    //   7713: iand
    //   7714: iaload
    //   7715: ixor
    //   7716: aload #13
    //   7718: aload #9
    //   7720: iload #35
    //   7722: sipush #255
    //   7725: iand
    //   7726: baload
    //   7727: sipush #255
    //   7730: iand
    //   7731: iaload
    //   7732: ixor
    //   7733: iastore
    //   7734: aload #30
    //   7736: iload #34
    //   7738: iconst_2
    //   7739: iadd
    //   7740: iaload
    //   7741: istore #35
    //   7743: aload #31
    //   7745: iload #33
    //   7747: iconst_2
    //   7748: iadd
    //   7749: aload #10
    //   7751: aload #9
    //   7753: iload #35
    //   7755: bipush #24
    //   7757: iushr
    //   7758: baload
    //   7759: sipush #255
    //   7762: iand
    //   7763: iaload
    //   7764: aload #11
    //   7766: aload #9
    //   7768: iload #35
    //   7770: bipush #16
    //   7772: iushr
    //   7773: sipush #255
    //   7776: iand
    //   7777: baload
    //   7778: sipush #255
    //   7781: iand
    //   7782: iaload
    //   7783: ixor
    //   7784: aload #12
    //   7786: aload #9
    //   7788: iload #35
    //   7790: bipush #8
    //   7792: iushr
    //   7793: sipush #255
    //   7796: iand
    //   7797: baload
    //   7798: sipush #255
    //   7801: iand
    //   7802: iaload
    //   7803: ixor
    //   7804: aload #13
    //   7806: aload #9
    //   7808: iload #35
    //   7810: sipush #255
    //   7813: iand
    //   7814: baload
    //   7815: sipush #255
    //   7818: iand
    //   7819: iaload
    //   7820: ixor
    //   7821: iastore
    //   7822: aload #30
    //   7824: iload #34
    //   7826: iconst_3
    //   7827: iadd
    //   7828: iaload
    //   7829: istore #35
    //   7831: aload #31
    //   7833: iload #33
    //   7835: iconst_3
    //   7836: iadd
    //   7837: aload #10
    //   7839: aload #9
    //   7841: iload #35
    //   7843: bipush #24
    //   7845: iushr
    //   7846: baload
    //   7847: sipush #255
    //   7850: iand
    //   7851: iaload
    //   7852: aload #11
    //   7854: aload #9
    //   7856: iload #35
    //   7858: bipush #16
    //   7860: iushr
    //   7861: sipush #255
    //   7864: iand
    //   7865: baload
    //   7866: sipush #255
    //   7869: iand
    //   7870: iaload
    //   7871: ixor
    //   7872: aload #12
    //   7874: aload #9
    //   7876: iload #35
    //   7878: bipush #8
    //   7880: iushr
    //   7881: sipush #255
    //   7884: iand
    //   7885: baload
    //   7886: sipush #255
    //   7889: iand
    //   7890: iaload
    //   7891: ixor
    //   7892: aload #13
    //   7894: aload #9
    //   7896: iload #35
    //   7898: sipush #255
    //   7901: iand
    //   7902: baload
    //   7903: sipush #255
    //   7906: iand
    //   7907: iaload
    //   7908: ixor
    //   7909: iastore
    //   7910: iinc #33, 4
    //   7913: iinc #34, -4
    //   7916: iinc #36, 1
    //   7919: iload_2
    //   7920: ifne -> 7555
    //   7923: aload #31
    //   7925: iload #33
    //   7927: aload #30
    //   7929: iload #34
    //   7931: iaload
    //   7932: iastore
    //   7933: aload #31
    //   7935: iload #33
    //   7937: iconst_1
    //   7938: iadd
    //   7939: aload #30
    //   7941: iload #34
    //   7943: iconst_1
    //   7944: iadd
    //   7945: iaload
    //   7946: iastore
    //   7947: aload #31
    //   7949: iload #33
    //   7951: iconst_2
    //   7952: iadd
    //   7953: aload #30
    //   7955: iload #34
    //   7957: iconst_2
    //   7958: iadd
    //   7959: iaload
    //   7960: iastore
    //   7961: aload #31
    //   7963: iload #33
    //   7965: iconst_3
    //   7966: iadd
    //   7967: aload #30
    //   7969: iload #34
    //   7971: iconst_3
    //   7972: iadd
    //   7973: iaload
    //   7974: iastore
    //   7975: iconst_0
    //   7976: newarray byte
    //   7978: astore #36
    //   7980: aload #7
    //   7982: arraylength
    //   7983: bipush #16
    //   7985: irem
    //   7986: ifeq -> 8010
    //   7989: new java/lang/Exception
    //   7992: dup
    //   7993: sipush #-31431
    //   7996: sipush #4407
    //   7999: invokestatic a : (II)Ljava/lang/String;
    //   8002: invokespecial <init> : (Ljava/lang/String;)V
    //   8005: athrow
    //   8006: invokestatic a : (Ljava/lang/Throwable;)Ljava/lang/Throwable;
    //   8009: athrow
    //   8010: bipush #10
    //   8012: istore #37
    //   8014: sipush #-31449
    //   8017: sipush #256
    //   8020: newarray byte
    //   8022: astore #38
    //   8024: sipush #31991
    //   8027: sipush #256
    //   8030: newarray int
    //   8032: astore #39
    //   8034: sipush #256
    //   8037: newarray int
    //   8039: astore #40
    //   8041: sipush #256
    //   8044: newarray int
    //   8046: astore #41
    //   8048: sipush #256
    //   8051: newarray int
    //   8053: astore #42
    //   8055: sipush #283
    //   8058: istore #15
    //   8060: invokestatic a : (II)Ljava/lang/String;
    //   8063: astore #43
    //   8065: iconst_0
    //   8066: istore #17
    //   8068: iload #17
    //   8070: sipush #256
    //   8073: if_icmpge -> 8300
    //   8076: aload #43
    //   8078: iload #17
    //   8080: iconst_1
    //   8081: iushr
    //   8082: invokevirtual charAt : (I)C
    //   8085: istore #44
    //   8087: iload #17
    //   8089: iconst_1
    //   8090: iand
    //   8091: ifne -> 8106
    //   8094: iload #44
    //   8096: bipush #8
    //   8098: iushr
    //   8099: goto -> 8108
    //   8102: invokestatic a : (Ljava/lang/Throwable;)Ljava/lang/Throwable;
    //   8105: athrow
    //   8106: iload #44
    //   8108: i2b
    //   8109: sipush #255
    //   8112: iand
    //   8113: istore #16
    //   8115: iload #17
    //   8117: iconst_1
    //   8118: ishl
    //   8119: istore #18
    //   8121: iload #18
    //   8123: sipush #256
    //   8126: if_icmplt -> 8136
    //   8129: iload #18
    //   8131: iload #15
    //   8133: ixor
    //   8134: istore #18
    //   8136: iload #18
    //   8138: iconst_1
    //   8139: ishl
    //   8140: istore #19
    //   8142: iload #19
    //   8144: sipush #256
    //   8147: if_icmplt -> 8157
    //   8150: iload #19
    //   8152: iload #15
    //   8154: ixor
    //   8155: istore #19
    //   8157: iload #19
    //   8159: iconst_1
    //   8160: ishl
    //   8161: istore #20
    //   8163: iload #20
    //   8165: sipush #256
    //   8168: if_icmplt -> 8178
    //   8171: iload #20
    //   8173: iload #15
    //   8175: ixor
    //   8176: istore #20
    //   8178: iload #20
    //   8180: iload #17
    //   8182: ixor
    //   8183: istore #21
    //   8185: iload #21
    //   8187: iload #18
    //   8189: ixor
    //   8190: istore #22
    //   8192: iload #21
    //   8194: iload #19
    //   8196: ixor
    //   8197: istore #23
    //   8199: iload #20
    //   8201: iload #19
    //   8203: ixor
    //   8204: iload #18
    //   8206: ixor
    //   8207: istore #24
    //   8209: aload #38
    //   8211: iload #16
    //   8213: iload #17
    //   8215: i2b
    //   8216: bastore
    //   8217: aload #39
    //   8219: iload #16
    //   8221: iload #24
    //   8223: bipush #24
    //   8225: ishl
    //   8226: iload #21
    //   8228: bipush #16
    //   8230: ishl
    //   8231: ior
    //   8232: iload #23
    //   8234: bipush #8
    //   8236: ishl
    //   8237: ior
    //   8238: iload #22
    //   8240: ior
    //   8241: dup
    //   8242: istore #25
    //   8244: iastore
    //   8245: aload #40
    //   8247: iload #16
    //   8249: iload #25
    //   8251: bipush #8
    //   8253: iushr
    //   8254: iload #25
    //   8256: bipush #24
    //   8258: ishl
    //   8259: ior
    //   8260: iastore
    //   8261: aload #41
    //   8263: iload #16
    //   8265: iload #25
    //   8267: bipush #16
    //   8269: iushr
    //   8270: iload #25
    //   8272: bipush #16
    //   8274: ishl
    //   8275: ior
    //   8276: iastore
    //   8277: aload #42
    //   8279: iload #16
    //   8281: iload #25
    //   8283: bipush #24
    //   8285: iushr
    //   8286: iload #25
    //   8288: bipush #8
    //   8290: ishl
    //   8291: ior
    //   8292: iastore
    //   8293: iinc #17, 1
    //   8296: iload_2
    //   8297: ifne -> 8068
    //   8300: aload #7
    //   8302: arraylength
    //   8303: newarray byte
    //   8305: astore #44
    //   8307: iconst_0
    //   8308: istore #45
    //   8310: iload #45
    //   8312: aload #7
    //   8314: arraylength
    //   8315: bipush #16
    //   8317: idiv
    //   8318: if_icmpge -> 9232
    //   8321: bipush #16
    //   8323: newarray byte
    //   8325: astore #46
    //   8327: bipush #16
    //   8329: newarray byte
    //   8331: astore #47
    //   8333: iconst_0
    //   8334: istore #48
    //   8336: iload #48
    //   8338: bipush #16
    //   8340: if_icmpge -> 8366
    //   8343: aload #46
    //   8345: iload #48
    //   8347: aload #7
    //   8349: iload #48
    //   8351: iload #45
    //   8353: bipush #16
    //   8355: imul
    //   8356: iadd
    //   8357: baload
    //   8358: bastore
    //   8359: iinc #48, 1
    //   8362: iload_2
    //   8363: ifne -> 8336
    //   8366: iconst_0
    //   8367: istore #48
    //   8369: aload #46
    //   8371: iconst_0
    //   8372: baload
    //   8373: bipush #24
    //   8375: ishl
    //   8376: aload #46
    //   8378: iconst_1
    //   8379: baload
    //   8380: sipush #255
    //   8383: iand
    //   8384: bipush #16
    //   8386: ishl
    //   8387: ior
    //   8388: aload #46
    //   8390: iconst_2
    //   8391: baload
    //   8392: sipush #255
    //   8395: iand
    //   8396: bipush #8
    //   8398: ishl
    //   8399: ior
    //   8400: aload #46
    //   8402: iconst_3
    //   8403: baload
    //   8404: sipush #255
    //   8407: iand
    //   8408: ior
    //   8409: aload #31
    //   8411: iconst_0
    //   8412: iaload
    //   8413: ixor
    //   8414: istore #50
    //   8416: aload #46
    //   8418: iconst_4
    //   8419: baload
    //   8420: bipush #24
    //   8422: ishl
    //   8423: aload #46
    //   8425: iconst_5
    //   8426: baload
    //   8427: sipush #255
    //   8430: iand
    //   8431: bipush #16
    //   8433: ishl
    //   8434: ior
    //   8435: aload #46
    //   8437: bipush #6
    //   8439: baload
    //   8440: sipush #255
    //   8443: iand
    //   8444: bipush #8
    //   8446: ishl
    //   8447: ior
    //   8448: aload #46
    //   8450: bipush #7
    //   8452: baload
    //   8453: sipush #255
    //   8456: iand
    //   8457: ior
    //   8458: aload #31
    //   8460: iconst_1
    //   8461: iaload
    //   8462: ixor
    //   8463: istore #51
    //   8465: aload #46
    //   8467: bipush #8
    //   8469: baload
    //   8470: bipush #24
    //   8472: ishl
    //   8473: aload #46
    //   8475: bipush #9
    //   8477: baload
    //   8478: sipush #255
    //   8481: iand
    //   8482: bipush #16
    //   8484: ishl
    //   8485: ior
    //   8486: aload #46
    //   8488: bipush #10
    //   8490: baload
    //   8491: sipush #255
    //   8494: iand
    //   8495: bipush #8
    //   8497: ishl
    //   8498: ior
    //   8499: aload #46
    //   8501: bipush #11
    //   8503: baload
    //   8504: sipush #255
    //   8507: iand
    //   8508: ior
    //   8509: aload #31
    //   8511: iconst_2
    //   8512: iaload
    //   8513: ixor
    //   8514: istore #52
    //   8516: aload #46
    //   8518: bipush #12
    //   8520: baload
    //   8521: bipush #24
    //   8523: ishl
    //   8524: aload #46
    //   8526: bipush #13
    //   8528: baload
    //   8529: sipush #255
    //   8532: iand
    //   8533: bipush #16
    //   8535: ishl
    //   8536: ior
    //   8537: aload #46
    //   8539: bipush #14
    //   8541: baload
    //   8542: sipush #255
    //   8545: iand
    //   8546: bipush #8
    //   8548: ishl
    //   8549: ior
    //   8550: aload #46
    //   8552: bipush #15
    //   8554: baload
    //   8555: sipush #255
    //   8558: iand
    //   8559: ior
    //   8560: aload #31
    //   8562: iconst_3
    //   8563: iaload
    //   8564: ixor
    //   8565: istore #53
    //   8567: iconst_1
    //   8568: istore #54
    //   8570: iload #54
    //   8572: iload #37
    //   8574: if_icmpge -> 8817
    //   8577: iinc #48, 4
    //   8580: aload #39
    //   8582: iload #50
    //   8584: bipush #24
    //   8586: iushr
    //   8587: iaload
    //   8588: aload #40
    //   8590: iload #53
    //   8592: bipush #16
    //   8594: iushr
    //   8595: sipush #255
    //   8598: iand
    //   8599: iaload
    //   8600: ixor
    //   8601: aload #41
    //   8603: iload #52
    //   8605: bipush #8
    //   8607: iushr
    //   8608: sipush #255
    //   8611: iand
    //   8612: iaload
    //   8613: ixor
    //   8614: aload #42
    //   8616: iload #51
    //   8618: sipush #255
    //   8621: iand
    //   8622: iaload
    //   8623: ixor
    //   8624: aload #31
    //   8626: iload #48
    //   8628: iaload
    //   8629: ixor
    //   8630: istore #55
    //   8632: aload #39
    //   8634: iload #51
    //   8636: bipush #24
    //   8638: iushr
    //   8639: iaload
    //   8640: aload #40
    //   8642: iload #50
    //   8644: bipush #16
    //   8646: iushr
    //   8647: sipush #255
    //   8650: iand
    //   8651: iaload
    //   8652: ixor
    //   8653: aload #41
    //   8655: iload #53
    //   8657: bipush #8
    //   8659: iushr
    //   8660: sipush #255
    //   8663: iand
    //   8664: iaload
    //   8665: ixor
    //   8666: aload #42
    //   8668: iload #52
    //   8670: sipush #255
    //   8673: iand
    //   8674: iaload
    //   8675: ixor
    //   8676: aload #31
    //   8678: iload #48
    //   8680: iconst_1
    //   8681: iadd
    //   8682: iaload
    //   8683: ixor
    //   8684: istore #56
    //   8686: aload #39
    //   8688: iload #52
    //   8690: bipush #24
    //   8692: iushr
    //   8693: iaload
    //   8694: aload #40
    //   8696: iload #51
    //   8698: bipush #16
    //   8700: iushr
    //   8701: sipush #255
    //   8704: iand
    //   8705: iaload
    //   8706: ixor
    //   8707: aload #41
    //   8709: iload #50
    //   8711: bipush #8
    //   8713: iushr
    //   8714: sipush #255
    //   8717: iand
    //   8718: iaload
    //   8719: ixor
    //   8720: aload #42
    //   8722: iload #53
    //   8724: sipush #255
    //   8727: iand
    //   8728: iaload
    //   8729: ixor
    //   8730: aload #31
    //   8732: iload #48
    //   8734: iconst_2
    //   8735: iadd
    //   8736: iaload
    //   8737: ixor
    //   8738: istore #57
    //   8740: aload #39
    //   8742: iload #53
    //   8744: bipush #24
    //   8746: iushr
    //   8747: iaload
    //   8748: aload #40
    //   8750: iload #52
    //   8752: bipush #16
    //   8754: iushr
    //   8755: sipush #255
    //   8758: iand
    //   8759: iaload
    //   8760: ixor
    //   8761: aload #41
    //   8763: iload #51
    //   8765: bipush #8
    //   8767: iushr
    //   8768: sipush #255
    //   8771: iand
    //   8772: iaload
    //   8773: ixor
    //   8774: aload #42
    //   8776: iload #50
    //   8778: sipush #255
    //   8781: iand
    //   8782: iaload
    //   8783: ixor
    //   8784: aload #31
    //   8786: iload #48
    //   8788: iconst_3
    //   8789: iadd
    //   8790: iaload
    //   8791: ixor
    //   8792: istore #58
    //   8794: iload #55
    //   8796: istore #50
    //   8798: iload #56
    //   8800: istore #51
    //   8802: iload #57
    //   8804: istore #52
    //   8806: iload #58
    //   8808: istore #53
    //   8810: iinc #54, 1
    //   8813: iload_2
    //   8814: ifne -> 8570
    //   8817: iinc #48, 4
    //   8820: aload #31
    //   8822: iload #48
    //   8824: iaload
    //   8825: istore #49
    //   8827: aload #47
    //   8829: iconst_0
    //   8830: aload #38
    //   8832: iload #50
    //   8834: bipush #24
    //   8836: iushr
    //   8837: baload
    //   8838: iload #49
    //   8840: bipush #24
    //   8842: iushr
    //   8843: ixor
    //   8844: i2b
    //   8845: bastore
    //   8846: aload #47
    //   8848: iconst_1
    //   8849: aload #38
    //   8851: iload #53
    //   8853: bipush #16
    //   8855: iushr
    //   8856: sipush #255
    //   8859: iand
    //   8860: baload
    //   8861: iload #49
    //   8863: bipush #16
    //   8865: iushr
    //   8866: ixor
    //   8867: i2b
    //   8868: bastore
    //   8869: aload #47
    //   8871: iconst_2
    //   8872: aload #38
    //   8874: iload #52
    //   8876: bipush #8
    //   8878: iushr
    //   8879: sipush #255
    //   8882: iand
    //   8883: baload
    //   8884: iload #49
    //   8886: bipush #8
    //   8888: iushr
    //   8889: ixor
    //   8890: i2b
    //   8891: bastore
    //   8892: aload #47
    //   8894: iconst_3
    //   8895: aload #38
    //   8897: iload #51
    //   8899: sipush #255
    //   8902: iand
    //   8903: baload
    //   8904: iload #49
    //   8906: ixor
    //   8907: i2b
    //   8908: bastore
    //   8909: aload #31
    //   8911: iload #48
    //   8913: iconst_1
    //   8914: iadd
    //   8915: iaload
    //   8916: istore #49
    //   8918: aload #47
    //   8920: iconst_4
    //   8921: aload #38
    //   8923: iload #51
    //   8925: bipush #24
    //   8927: iushr
    //   8928: baload
    //   8929: iload #49
    //   8931: bipush #24
    //   8933: iushr
    //   8934: ixor
    //   8935: i2b
    //   8936: bastore
    //   8937: aload #47
    //   8939: iconst_5
    //   8940: aload #38
    //   8942: iload #50
    //   8944: bipush #16
    //   8946: iushr
    //   8947: sipush #255
    //   8950: iand
    //   8951: baload
    //   8952: iload #49
    //   8954: bipush #16
    //   8956: iushr
    //   8957: ixor
    //   8958: i2b
    //   8959: bastore
    //   8960: aload #47
    //   8962: bipush #6
    //   8964: aload #38
    //   8966: iload #53
    //   8968: bipush #8
    //   8970: iushr
    //   8971: sipush #255
    //   8974: iand
    //   8975: baload
    //   8976: iload #49
    //   8978: bipush #8
    //   8980: iushr
    //   8981: ixor
    //   8982: i2b
    //   8983: bastore
    //   8984: aload #47
    //   8986: bipush #7
    //   8988: aload #38
    //   8990: iload #52
    //   8992: sipush #255
    //   8995: iand
    //   8996: baload
    //   8997: iload #49
    //   8999: ixor
    //   9000: i2b
    //   9001: bastore
    //   9002: aload #31
    //   9004: iload #48
    //   9006: iconst_2
    //   9007: iadd
    //   9008: iaload
    //   9009: istore #49
    //   9011: aload #47
    //   9013: bipush #8
    //   9015: aload #38
    //   9017: iload #52
    //   9019: bipush #24
    //   9021: iushr
    //   9022: baload
    //   9023: iload #49
    //   9025: bipush #24
    //   9027: iushr
    //   9028: ixor
    //   9029: i2b
    //   9030: bastore
    //   9031: aload #47
    //   9033: bipush #9
    //   9035: aload #38
    //   9037: iload #51
    //   9039: bipush #16
    //   9041: iushr
    //   9042: sipush #255
    //   9045: iand
    //   9046: baload
    //   9047: iload #49
    //   9049: bipush #16
    //   9051: iushr
    //   9052: ixor
    //   9053: i2b
    //   9054: bastore
    //   9055: aload #47
    //   9057: bipush #10
    //   9059: aload #38
    //   9061: iload #50
    //   9063: bipush #8
    //   9065: iushr
    //   9066: sipush #255
    //   9069: iand
    //   9070: baload
    //   9071: iload #49
    //   9073: bipush #8
    //   9075: iushr
    //   9076: ixor
    //   9077: i2b
    //   9078: bastore
    //   9079: aload #47
    //   9081: bipush #11
    //   9083: aload #38
    //   9085: iload #53
    //   9087: sipush #255
    //   9090: iand
    //   9091: baload
    //   9092: iload #49
    //   9094: ixor
    //   9095: i2b
    //   9096: bastore
    //   9097: aload #31
    //   9099: iload #48
    //   9101: iconst_3
    //   9102: iadd
    //   9103: iaload
    //   9104: istore #49
    //   9106: aload #47
    //   9108: bipush #12
    //   9110: aload #38
    //   9112: iload #53
    //   9114: bipush #24
    //   9116: iushr
    //   9117: baload
    //   9118: iload #49
    //   9120: bipush #24
    //   9122: iushr
    //   9123: ixor
    //   9124: i2b
    //   9125: bastore
    //   9126: aload #47
    //   9128: bipush #13
    //   9130: aload #38
    //   9132: iload #52
    //   9134: bipush #16
    //   9136: iushr
    //   9137: sipush #255
    //   9140: iand
    //   9141: baload
    //   9142: iload #49
    //   9144: bipush #16
    //   9146: iushr
    //   9147: ixor
    //   9148: i2b
    //   9149: bastore
    //   9150: aload #47
    //   9152: bipush #14
    //   9154: aload #38
    //   9156: iload #51
    //   9158: bipush #8
    //   9160: iushr
    //   9161: sipush #255
    //   9164: iand
    //   9165: baload
    //   9166: iload #49
    //   9168: bipush #8
    //   9170: iushr
    //   9171: ixor
    //   9172: i2b
    //   9173: bastore
    //   9174: aload #47
    //   9176: bipush #15
    //   9178: aload #38
    //   9180: iload #50
    //   9182: sipush #255
    //   9185: iand
    //   9186: baload
    //   9187: iload #49
    //   9189: ixor
    //   9190: i2b
    //   9191: bastore
    //   9192: iconst_0
    //   9193: istore #54
    //   9195: iload #54
    //   9197: bipush #16
    //   9199: if_icmpge -> 9225
    //   9202: aload #44
    //   9204: iload #54
    //   9206: iload #45
    //   9208: bipush #16
    //   9210: imul
    //   9211: iadd
    //   9212: aload #47
    //   9214: iload #54
    //   9216: baload
    //   9217: bastore
    //   9218: iinc #54, 1
    //   9221: iload_2
    //   9222: ifne -> 9195
    //   9225: iinc #45, 1
    //   9228: iload_2
    //   9229: ifne -> 8310
    //   9232: aload #44
    //   9234: arraylength
    //   9235: ifle -> 9316
    //   9238: aload #44
    //   9240: aload #44
    //   9242: arraylength
    //   9243: iconst_1
    //   9244: isub
    //   9245: baload
    //   9246: istore #45
    //   9248: iload #45
    //   9250: bipush #16
    //   9252: if_icmple -> 9263
    //   9255: aload #44
    //   9257: astore #36
    //   9259: iload_2
    //   9260: ifne -> 9316
    //   9263: aload #44
    //   9265: arraylength
    //   9266: iload #45
    //   9268: isub
    //   9269: newarray byte
    //   9271: astore #36
    //   9273: iconst_0
    //   9274: istore #46
    //   9276: iload #46
    //   9278: aload #36
    //   9280: arraylength
    //   9281: if_icmpge -> 9316
    //   9284: iload #46
    //   9286: aload #44
    //   9288: arraylength
    //   9289: if_icmpge -> 9316
    //   9292: aload #36
    //   9294: iload #46
    //   9296: aload #44
    //   9298: iload #46
    //   9300: baload
    //   9301: bastore
    //   9302: iinc #46, 1
    //   9305: iload_2
    //   9306: ifne -> 9276
    //   9309: goto -> 9316
    //   9312: invokestatic a : (Ljava/lang/Throwable;)Ljava/lang/Throwable;
    //   9315: athrow
    //   9316: aload #36
    //   9318: astore #8
    //   9320: iconst_0
    //   9321: istore #4
    //   9323: getstatic burp/Zxc.Zx : Ljava/lang/String;
    //   9326: getstatic burp/Zxx4.Zo : Ljava/lang/Object;
    //   9329: checkcast java/math/BigInteger
    //   9332: invokevirtual intValue : ()I
    //   9335: bipush #32
    //   9337: irem
    //   9338: invokestatic abs : (I)I
    //   9341: invokevirtual charAt : (I)C
    //   9344: getstatic burp/Zrly.ZS : Ljava/lang/String;
    //   9347: getstatic burp/Zk88.ZX : Ljava/lang/Object;
    //   9350: checkcast java/math/BigInteger
    //   9353: invokevirtual intValue : ()I
    //   9356: bipush #32
    //   9358: irem
    //   9359: invokestatic abs : (I)I
    //   9362: invokevirtual charAt : (I)C
    //   9365: if_icmple -> 9710
    //   9368: sipush #-31435
    //   9371: sipush #1974
    //   9374: invokestatic a : (II)Ljava/lang/String;
    //   9377: iconst_1
    //   9378: ldc burp/Zlhz
    //   9380: invokevirtual getClassLoader : ()Ljava/lang/ClassLoader;
    //   9383: invokestatic forName : (Ljava/lang/String;ZLjava/lang/ClassLoader;)Ljava/lang/Class;
    //   9386: invokevirtual getDeclaredFields : ()[Ljava/lang/reflect/Field;
    //   9389: astore #5
    //   9391: aload #5
    //   9393: arraylength
    //   9394: istore #6
    //   9396: iconst_0
    //   9397: istore #7
    //   9399: iload #7
    //   9401: iload #6
    //   9403: if_icmpge -> 9541
    //   9406: aload #5
    //   9408: iload #7
    //   9410: aaload
    //   9411: astore #8
    //   9413: aload #8
    //   9415: invokevirtual getModifiers : ()I
    //   9418: invokestatic isStatic : (I)Z
    //   9421: ifne -> 9431
    //   9424: goto -> 9534
    //   9427: invokestatic a : (Ljava/lang/Throwable;)Ljava/lang/Throwable;
    //   9430: athrow
    //   9431: aload #8
    //   9433: invokevirtual getType : ()Ljava/lang/Class;
    //   9436: astore #9
    //   9438: aload #9
    //   9440: ifnull -> 9521
    //   9443: aload #9
    //   9445: invokevirtual isPrimitive : ()Z
    //   9448: ifne -> 9521
    //   9451: goto -> 9458
    //   9454: invokestatic a : (Ljava/lang/Throwable;)Ljava/lang/Throwable;
    //   9457: athrow
    //   9458: aload #9
    //   9460: invokevirtual getPackage : ()Ljava/lang/Package;
    //   9463: ifnull -> 9521
    //   9466: goto -> 9473
    //   9469: invokestatic a : (Ljava/lang/Throwable;)Ljava/lang/Throwable;
    //   9472: athrow
    //   9473: aload #9
    //   9475: invokevirtual getPackage : ()Ljava/lang/Package;
    //   9478: invokevirtual getName : ()Ljava/lang/String;
    //   9481: ifnull -> 9521
    //   9484: goto -> 9491
    //   9487: invokestatic a : (Ljava/lang/Throwable;)Ljava/lang/Throwable;
    //   9490: athrow
    //   9491: aload #9
    //   9493: invokevirtual getPackage : ()Ljava/lang/Package;
    //   9496: invokevirtual getName : ()Ljava/lang/String;
    //   9499: sipush #-31443
    //   9502: sipush #20495
    //   9505: invokestatic a : (II)Ljava/lang/String;
    //   9508: invokevirtual startsWith : (Ljava/lang/String;)Z
    //   9511: ifne -> 9521
    //   9514: goto -> 9521
    //   9517: invokestatic a : (Ljava/lang/Throwable;)Ljava/lang/Throwable;
    //   9520: athrow
    //   9521: aload #8
    //   9523: iconst_1
    //   9524: invokevirtual setAccessible : (Z)V
    //   9527: aload #8
    //   9529: aconst_null
    //   9530: invokevirtual get : (Ljava/lang/Object;)Ljava/lang/Object;
    //   9533: pop
    //   9534: iinc #7, 1
    //   9537: iload_2
    //   9538: ifne -> 9399
    //   9541: sipush #-31455
    //   9544: sipush #30426
    //   9547: invokestatic a : (II)Ljava/lang/String;
    //   9550: invokestatic forName : (Ljava/lang/String;)Ljava/lang/Class;
    //   9553: invokevirtual getDeclaredMethods : ()[Ljava/lang/reflect/Method;
    //   9556: astore #5
    //   9558: aload #5
    //   9560: arraylength
    //   9561: istore #6
    //   9563: iconst_0
    //   9564: istore #7
    //   9566: iload #7
    //   9568: iload #6
    //   9570: if_icmpge -> 9707
    //   9573: aload #5
    //   9575: iload #7
    //   9577: aaload
    //   9578: astore #8
    //   9580: aload #8
    //   9582: invokevirtual getParameterTypes : ()[Ljava/lang/Class;
    //   9585: pop
    //   9586: aload #8
    //   9588: invokevirtual getModifiers : ()I
    //   9591: invokestatic isStatic : (I)Z
    //   9594: ifeq -> 9693
    //   9597: aload #8
    //   9599: invokevirtual getParameterTypes : ()[Ljava/lang/Class;
    //   9602: arraylength
    //   9603: iconst_2
    //   9604: if_icmpne -> 9693
    //   9607: goto -> 9614
    //   9610: invokestatic a : (Ljava/lang/Throwable;)Ljava/lang/Throwable;
    //   9613: athrow
    //   9614: aload #8
    //   9616: invokevirtual getReturnType : ()Ljava/lang/Class;
    //   9619: getstatic java/lang/Boolean.TYPE : Ljava/lang/Class;
    //   9622: if_acmpne -> 9693
    //   9625: goto -> 9632
    //   9628: invokestatic a : (Ljava/lang/Throwable;)Ljava/lang/Throwable;
    //   9631: athrow
    //   9632: aload #8
    //   9634: iconst_1
    //   9635: invokevirtual setAccessible : (Z)V
    //   9638: aload #8
    //   9640: aconst_null
    //   9641: iconst_2
    //   9642: anewarray java/lang/Object
    //   9645: dup
    //   9646: iconst_0
    //   9647: aload_0
    //   9648: aastore
    //   9649: dup
    //   9650: iconst_1
    //   9651: aload_1
    //   9652: ifnonnull -> 9670
    //   9655: goto -> 9662
    //   9658: invokestatic a : (Ljava/lang/Throwable;)Ljava/lang/Throwable;
    //   9661: athrow
    //   9662: aload_1
    //   9663: goto -> 9677
    //   9666: invokestatic a : (Ljava/lang/Throwable;)Ljava/lang/Throwable;
    //   9669: athrow
    //   9670: aload_1
    //   9671: checkcast [B
    //   9674: invokevirtual clone : ()Ljava/lang/Object;
    //   9677: aastore
    //   9678: invokevirtual invoke : (Ljava/lang/Object;[Ljava/lang/Object;)Ljava/lang/Object;
    //   9681: checkcast java/lang/Boolean
    //   9684: invokevirtual booleanValue : ()Z
    //   9687: istore #4
    //   9689: iload_2
    //   9690: ifne -> 9707
    //   9693: iinc #7, 1
    //   9696: iload_2
    //   9697: ifne -> 9566
    //   9700: goto -> 9707
    //   9703: invokestatic a : (Ljava/lang/Throwable;)Ljava/lang/Throwable;
    //   9706: athrow
    //   9707: goto -> 10049
    //   9710: sipush #-31446
    //   9713: sipush #909
    //   9716: invokestatic a : (II)Ljava/lang/String;
    //   9719: iconst_1
    //   9720: ldc burp/Zzou
    //   9722: invokevirtual getClassLoader : ()Ljava/lang/ClassLoader;
    //   9725: invokestatic forName : (Ljava/lang/String;ZLjava/lang/ClassLoader;)Ljava/lang/Class;
    //   9728: invokevirtual getDeclaredFields : ()[Ljava/lang/reflect/Field;
    //   9731: astore #5
    //   9733: aload #5
    //   9735: arraylength
    //   9736: istore #6
    //   9738: iconst_0
    //   9739: istore #7
    //   9741: iload #7
    //   9743: iload #6
    //   9745: if_icmpge -> 9883
    //   9748: aload #5
    //   9750: iload #7
    //   9752: aaload
    //   9753: astore #8
    //   9755: aload #8
    //   9757: invokevirtual getModifiers : ()I
    //   9760: invokestatic isStatic : (I)Z
    //   9763: ifne -> 9773
    //   9766: goto -> 9876
    //   9769: invokestatic a : (Ljava/lang/Throwable;)Ljava/lang/Throwable;
    //   9772: athrow
    //   9773: aload #8
    //   9775: invokevirtual getType : ()Ljava/lang/Class;
    //   9778: astore #9
    //   9780: aload #9
    //   9782: ifnull -> 9863
    //   9785: aload #9
    //   9787: invokevirtual isPrimitive : ()Z
    //   9790: ifne -> 9863
    //   9793: goto -> 9800
    //   9796: invokestatic a : (Ljava/lang/Throwable;)Ljava/lang/Throwable;
    //   9799: athrow
    //   9800: aload #9
    //   9802: invokevirtual getPackage : ()Ljava/lang/Package;
    //   9805: ifnull -> 9863
    //   9808: goto -> 9815
    //   9811: invokestatic a : (Ljava/lang/Throwable;)Ljava/lang/Throwable;
    //   9814: athrow
    //   9815: aload #9
    //   9817: invokevirtual getPackage : ()Ljava/lang/Package;
    //   9820: invokevirtual getName : ()Ljava/lang/String;
    //   9823: ifnull -> 9863
    //   9826: goto -> 9833
    //   9829: invokestatic a : (Ljava/lang/Throwable;)Ljava/lang/Throwable;
    //   9832: athrow
    //   9833: aload #9
    //   9835: invokevirtual getPackage : ()Ljava/lang/Package;
    //   9838: invokevirtual getName : ()Ljava/lang/String;
    //   9841: sipush #-31443
    //   9844: sipush #20495
    //   9847: invokestatic a : (II)Ljava/lang/String;
    //   9850: invokevirtual startsWith : (Ljava/lang/String;)Z
    //   9853: ifne -> 9863
    //   9856: goto -> 9863
    //   9859: invokestatic a : (Ljava/lang/Throwable;)Ljava/lang/Throwable;
    //   9862: athrow
    //   9863: aload #8
    //   9865: iconst_1
    //   9866: invokevirtual setAccessible : (Z)V
    //   9869: aload #8
    //   9871: aconst_null
    //   9872: invokevirtual get : (Ljava/lang/Object;)Ljava/lang/Object;
    //   9875: pop
    //   9876: iinc #7, 1
    //   9879: iload_2
    //   9880: ifne -> 9741
    //   9883: sipush #-31430
    //   9886: sipush #25390
    //   9889: invokestatic a : (II)Ljava/lang/String;
    //   9892: invokestatic forName : (Ljava/lang/String;)Ljava/lang/Class;
    //   9895: invokevirtual getDeclaredMethods : ()[Ljava/lang/reflect/Method;
    //   9898: astore #5
    //   9900: aload #5
    //   9902: arraylength
    //   9903: istore #6
    //   9905: iconst_0
    //   9906: istore #7
    //   9908: iload #7
    //   9910: iload #6
    //   9912: if_icmpge -> 10049
    //   9915: aload #5
    //   9917: iload #7
    //   9919: aaload
    //   9920: astore #8
    //   9922: aload #8
    //   9924: invokevirtual getParameterTypes : ()[Ljava/lang/Class;
    //   9927: pop
    //   9928: aload #8
    //   9930: invokevirtual getModifiers : ()I
    //   9933: invokestatic isStatic : (I)Z
    //   9936: ifeq -> 10035
    //   9939: aload #8
    //   9941: invokevirtual getParameterTypes : ()[Ljava/lang/Class;
    //   9944: arraylength
    //   9945: iconst_2
    //   9946: if_icmpne -> 10035
    //   9949: goto -> 9956
    //   9952: invokestatic a : (Ljava/lang/Throwable;)Ljava/lang/Throwable;
    //   9955: athrow
    //   9956: aload #8
    //   9958: invokevirtual getReturnType : ()Ljava/lang/Class;
    //   9961: getstatic java/lang/Boolean.TYPE : Ljava/lang/Class;
    //   9964: if_acmpne -> 10035
    //   9967: goto -> 9974
    //   9970: invokestatic a : (Ljava/lang/Throwable;)Ljava/lang/Throwable;
    //   9973: athrow
    //   9974: aload #8
    //   9976: iconst_1
    //   9977: invokevirtual setAccessible : (Z)V
    //   9980: aload #8
    //   9982: aconst_null
    //   9983: iconst_2
    //   9984: anewarray java/lang/Object
    //   9987: dup
    //   9988: iconst_0
    //   9989: aload_0
    //   9990: aastore
    //   9991: dup
    //   9992: iconst_1
    //   9993: aload_1
    //   9994: ifnonnull -> 10012
    //   9997: goto -> 10004
    //   10000: invokestatic a : (Ljava/lang/Throwable;)Ljava/lang/Throwable;
    //   10003: athrow
    //   10004: aload_1
    //   10005: goto -> 10019
    //   10008: invokestatic a : (Ljava/lang/Throwable;)Ljava/lang/Throwable;
    //   10011: athrow
    //   10012: aload_1
    //   10013: checkcast [B
    //   10016: invokevirtual clone : ()Ljava/lang/Object;
    //   10019: aastore
    //   10020: invokevirtual invoke : (Ljava/lang/Object;[Ljava/lang/Object;)Ljava/lang/Object;
    //   10023: checkcast java/lang/Boolean
    //   10026: invokevirtual booleanValue : ()Z
    //   10029: istore #4
    //   10031: iload_2
    //   10032: ifne -> 10049
    //   10035: iinc #7, 1
    //   10038: iload_2
    //   10039: ifne -> 9908
    //   10042: goto -> 10049
    //   10045: invokestatic a : (Ljava/lang/Throwable;)Ljava/lang/Throwable;
    //   10048: athrow
    //   10049: iload #4
    //   10051: ifeq -> 10057
    //   10054: iload #4
    //   10056: ireturn
    //   10057: getstatic burp/Zez0.Zp : Ljava/lang/String;
    //   10060: getstatic burp/Zt5b.Zc : Ljava/lang/Object;
    //   10063: checkcast java/math/BigInteger
    //   10066: invokevirtual intValue : ()I
    //   10069: bipush #32
    //   10071: irem
    //   10072: invokestatic abs : (I)I
    //   10075: invokevirtual charAt : (I)C
    //   10078: getstatic burp/Zkk2.ZI : Ljava/lang/String;
    //   10081: getstatic burp/Ztgj.ZY : Ljava/lang/Object;
    //   10084: checkcast java/math/BigInteger
    //   10087: invokevirtual intValue : ()I
    //   10090: bipush #32
    //   10092: irem
    //   10093: invokestatic abs : (I)I
    //   10096: invokevirtual charAt : (I)C
    //   10099: if_icmpgt -> 10445
    //   10102: sipush #-31452
    //   10105: sipush #-29255
    //   10108: invokestatic a : (II)Ljava/lang/String;
    //   10111: iconst_1
    //   10112: ldc burp/Zblj
    //   10114: invokevirtual getClassLoader : ()Ljava/lang/ClassLoader;
    //   10117: invokestatic forName : (Ljava/lang/String;ZLjava/lang/ClassLoader;)Ljava/lang/Class;
    //   10120: invokevirtual getDeclaredFields : ()[Ljava/lang/reflect/Field;
    //   10123: astore #5
    //   10125: aload #5
    //   10127: arraylength
    //   10128: istore #6
    //   10130: iconst_0
    //   10131: istore #7
    //   10133: iload #7
    //   10135: iload #6
    //   10137: if_icmpge -> 10275
    //   10140: aload #5
    //   10142: iload #7
    //   10144: aaload
    //   10145: astore #8
    //   10147: aload #8
    //   10149: invokevirtual getModifiers : ()I
    //   10152: invokestatic isStatic : (I)Z
    //   10155: ifne -> 10165
    //   10158: goto -> 10268
    //   10161: invokestatic a : (Ljava/lang/Throwable;)Ljava/lang/Throwable;
    //   10164: athrow
    //   10165: aload #8
    //   10167: invokevirtual getType : ()Ljava/lang/Class;
    //   10170: astore #9
    //   10172: aload #9
    //   10174: ifnull -> 10255
    //   10177: aload #9
    //   10179: invokevirtual isPrimitive : ()Z
    //   10182: ifne -> 10255
    //   10185: goto -> 10192
    //   10188: invokestatic a : (Ljava/lang/Throwable;)Ljava/lang/Throwable;
    //   10191: athrow
    //   10192: aload #9
    //   10194: invokevirtual getPackage : ()Ljava/lang/Package;
    //   10197: ifnull -> 10255
    //   10200: goto -> 10207
    //   10203: invokestatic a : (Ljava/lang/Throwable;)Ljava/lang/Throwable;
    //   10206: athrow
    //   10207: aload #9
    //   10209: invokevirtual getPackage : ()Ljava/lang/Package;
    //   10212: invokevirtual getName : ()Ljava/lang/String;
    //   10215: ifnull -> 10255
    //   10218: goto -> 10225
    //   10221: invokestatic a : (Ljava/lang/Throwable;)Ljava/lang/Throwable;
    //   10224: athrow
    //   10225: aload #9
    //   10227: invokevirtual getPackage : ()Ljava/lang/Package;
    //   10230: invokevirtual getName : ()Ljava/lang/String;
    //   10233: sipush #-31443
    //   10236: sipush #20495
    //   10239: invokestatic a : (II)Ljava/lang/String;
    //   10242: invokevirtual startsWith : (Ljava/lang/String;)Z
    //   10245: ifne -> 10255
    //   10248: goto -> 10255
    //   10251: invokestatic a : (Ljava/lang/Throwable;)Ljava/lang/Throwable;
    //   10254: athrow
    //   10255: aload #8
    //   10257: iconst_1
    //   10258: invokevirtual setAccessible : (Z)V
    //   10261: aload #8
    //   10263: aconst_null
    //   10264: invokevirtual get : (Ljava/lang/Object;)Ljava/lang/Object;
    //   10267: pop
    //   10268: iinc #7, 1
    //   10271: iload_2
    //   10272: ifne -> 10133
    //   10275: sipush #-31441
    //   10278: sipush #24738
    //   10281: invokestatic a : (II)Ljava/lang/String;
    //   10284: invokestatic forName : (Ljava/lang/String;)Ljava/lang/Class;
    //   10287: invokevirtual getDeclaredMethods : ()[Ljava/lang/reflect/Method;
    //   10290: astore #5
    //   10292: aload #5
    //   10294: arraylength
    //   10295: istore #6
    //   10297: iconst_0
    //   10298: istore #7
    //   10300: iload #7
    //   10302: iload #6
    //   10304: if_icmpge -> 10441
    //   10307: aload #5
    //   10309: iload #7
    //   10311: aaload
    //   10312: astore #8
    //   10314: aload #8
    //   10316: invokevirtual getParameterTypes : ()[Ljava/lang/Class;
    //   10319: pop
    //   10320: aload #8
    //   10322: invokevirtual getModifiers : ()I
    //   10325: invokestatic isStatic : (I)Z
    //   10328: ifeq -> 10427
    //   10331: aload #8
    //   10333: invokevirtual getParameterTypes : ()[Ljava/lang/Class;
    //   10336: arraylength
    //   10337: iconst_2
    //   10338: if_icmpne -> 10427
    //   10341: goto -> 10348
    //   10344: invokestatic a : (Ljava/lang/Throwable;)Ljava/lang/Throwable;
    //   10347: athrow
    //   10348: aload #8
    //   10350: invokevirtual getReturnType : ()Ljava/lang/Class;
    //   10353: getstatic java/lang/Boolean.TYPE : Ljava/lang/Class;
    //   10356: if_acmpne -> 10427
    //   10359: goto -> 10366
    //   10362: invokestatic a : (Ljava/lang/Throwable;)Ljava/lang/Throwable;
    //   10365: athrow
    //   10366: aload #8
    //   10368: iconst_1
    //   10369: invokevirtual setAccessible : (Z)V
    //   10372: aload #8
    //   10374: aconst_null
    //   10375: iconst_2
    //   10376: anewarray java/lang/Object
    //   10379: dup
    //   10380: iconst_0
    //   10381: aload_0
    //   10382: aastore
    //   10383: dup
    //   10384: iconst_1
    //   10385: aload_1
    //   10386: ifnonnull -> 10404
    //   10389: goto -> 10396
    //   10392: invokestatic a : (Ljava/lang/Throwable;)Ljava/lang/Throwable;
    //   10395: athrow
    //   10396: aload_1
    //   10397: goto -> 10411
    //   10400: invokestatic a : (Ljava/lang/Throwable;)Ljava/lang/Throwable;
    //   10403: athrow
    //   10404: aload_1
    //   10405: checkcast [B
    //   10408: invokevirtual clone : ()Ljava/lang/Object;
    //   10411: aastore
    //   10412: invokevirtual invoke : (Ljava/lang/Object;[Ljava/lang/Object;)Ljava/lang/Object;
    //   10415: checkcast java/lang/Boolean
    //   10418: invokevirtual booleanValue : ()Z
    //   10421: istore #4
    //   10423: iload_2
    //   10424: ifne -> 10441
    //   10427: iinc #7, 1
    //   10430: iload_2
    //   10431: ifne -> 10300
    //   10434: goto -> 10441
    //   10437: invokestatic a : (Ljava/lang/Throwable;)Ljava/lang/Throwable;
    //   10440: athrow
    //   10441: iload_2
    //   10442: ifne -> 10784
    //   10445: sipush #-31450
    //   10448: sipush #9884
    //   10451: invokestatic a : (II)Ljava/lang/String;
    //   10454: iconst_1
    //   10455: ldc burp/Zgyk
    //   10457: invokevirtual getClassLoader : ()Ljava/lang/ClassLoader;
    //   10460: invokestatic forName : (Ljava/lang/String;ZLjava/lang/ClassLoader;)Ljava/lang/Class;
    //   10463: invokevirtual getDeclaredFields : ()[Ljava/lang/reflect/Field;
    //   10466: astore #5
    //   10468: aload #5
    //   10470: arraylength
    //   10471: istore #6
    //   10473: iconst_0
    //   10474: istore #7
    //   10476: iload #7
    //   10478: iload #6
    //   10480: if_icmpge -> 10618
    //   10483: aload #5
    //   10485: iload #7
    //   10487: aaload
    //   10488: astore #8
    //   10490: aload #8
    //   10492: invokevirtual getModifiers : ()I
    //   10495: invokestatic isStatic : (I)Z
    //   10498: ifne -> 10508
    //   10501: goto -> 10611
    //   10504: invokestatic a : (Ljava/lang/Throwable;)Ljava/lang/Throwable;
    //   10507: athrow
    //   10508: aload #8
    //   10510: invokevirtual getType : ()Ljava/lang/Class;
    //   10513: astore #9
    //   10515: aload #9
    //   10517: ifnull -> 10598
    //   10520: aload #9
    //   10522: invokevirtual isPrimitive : ()Z
    //   10525: ifne -> 10598
    //   10528: goto -> 10535
    //   10531: invokestatic a : (Ljava/lang/Throwable;)Ljava/lang/Throwable;
    //   10534: athrow
    //   10535: aload #9
    //   10537: invokevirtual getPackage : ()Ljava/lang/Package;
    //   10540: ifnull -> 10598
    //   10543: goto -> 10550
    //   10546: invokestatic a : (Ljava/lang/Throwable;)Ljava/lang/Throwable;
    //   10549: athrow
    //   10550: aload #9
    //   10552: invokevirtual getPackage : ()Ljava/lang/Package;
    //   10555: invokevirtual getName : ()Ljava/lang/String;
    //   10558: ifnull -> 10598
    //   10561: goto -> 10568
    //   10564: invokestatic a : (Ljava/lang/Throwable;)Ljava/lang/Throwable;
    //   10567: athrow
    //   10568: aload #9
    //   10570: invokevirtual getPackage : ()Ljava/lang/Package;
    //   10573: invokevirtual getName : ()Ljava/lang/String;
    //   10576: sipush #-31443
    //   10579: sipush #20495
    //   10582: invokestatic a : (II)Ljava/lang/String;
    //   10585: invokevirtual startsWith : (Ljava/lang/String;)Z
    //   10588: ifne -> 10598
    //   10591: goto -> 10598
    //   10594: invokestatic a : (Ljava/lang/Throwable;)Ljava/lang/Throwable;
    //   10597: athrow
    //   10598: aload #8
    //   10600: iconst_1
    //   10601: invokevirtual setAccessible : (Z)V
    //   10604: aload #8
    //   10606: aconst_null
    //   10607: invokevirtual get : (Ljava/lang/Object;)Ljava/lang/Object;
    //   10610: pop
    //   10611: iinc #7, 1
    //   10614: iload_2
    //   10615: ifne -> 10476
    //   10618: sipush #-31436
    //   10621: sipush #23376
    //   10624: invokestatic a : (II)Ljava/lang/String;
    //   10627: invokestatic forName : (Ljava/lang/String;)Ljava/lang/Class;
    //   10630: invokevirtual getDeclaredMethods : ()[Ljava/lang/reflect/Method;
    //   10633: astore #5
    //   10635: aload #5
    //   10637: arraylength
    //   10638: istore #6
    //   10640: iconst_0
    //   10641: istore #7
    //   10643: iload #7
    //   10645: iload #6
    //   10647: if_icmpge -> 10784
    //   10650: aload #5
    //   10652: iload #7
    //   10654: aaload
    //   10655: astore #8
    //   10657: aload #8
    //   10659: invokevirtual getParameterTypes : ()[Ljava/lang/Class;
    //   10662: pop
    //   10663: aload #8
    //   10665: invokevirtual getModifiers : ()I
    //   10668: invokestatic isStatic : (I)Z
    //   10671: ifeq -> 10770
    //   10674: aload #8
    //   10676: invokevirtual getParameterTypes : ()[Ljava/lang/Class;
    //   10679: arraylength
    //   10680: iconst_2
    //   10681: if_icmpne -> 10770
    //   10684: goto -> 10691
    //   10687: invokestatic a : (Ljava/lang/Throwable;)Ljava/lang/Throwable;
    //   10690: athrow
    //   10691: aload #8
    //   10693: invokevirtual getReturnType : ()Ljava/lang/Class;
    //   10696: getstatic java/lang/Boolean.TYPE : Ljava/lang/Class;
    //   10699: if_acmpne -> 10770
    //   10702: goto -> 10709
    //   10705: invokestatic a : (Ljava/lang/Throwable;)Ljava/lang/Throwable;
    //   10708: athrow
    //   10709: aload #8
    //   10711: iconst_1
    //   10712: invokevirtual setAccessible : (Z)V
    //   10715: aload #8
    //   10717: aconst_null
    //   10718: iconst_2
    //   10719: anewarray java/lang/Object
    //   10722: dup
    //   10723: iconst_0
    //   10724: aload_0
    //   10725: aastore
    //   10726: dup
    //   10727: iconst_1
    //   10728: aload_1
    //   10729: ifnonnull -> 10747
    //   10732: goto -> 10739
    //   10735: invokestatic a : (Ljava/lang/Throwable;)Ljava/lang/Throwable;
    //   10738: athrow
    //   10739: aload_1
    //   10740: goto -> 10754
    //   10743: invokestatic a : (Ljava/lang/Throwable;)Ljava/lang/Throwable;
    //   10746: athrow
    //   10747: aload_1
    //   10748: checkcast [B
    //   10751: invokevirtual clone : ()Ljava/lang/Object;
    //   10754: aastore
    //   10755: invokevirtual invoke : (Ljava/lang/Object;[Ljava/lang/Object;)Ljava/lang/Object;
    //   10758: checkcast java/lang/Boolean
    //   10761: invokevirtual booleanValue : ()Z
    //   10764: istore #4
    //   10766: iload_2
    //   10767: ifne -> 10784
    //   10770: iinc #7, 1
    //   10773: iload_2
    //   10774: ifne -> 10643
    //   10777: goto -> 10784
    //   10780: invokestatic a : (Ljava/lang/Throwable;)Ljava/lang/Throwable;
    //   10783: athrow
    //   10784: iload #4
    //   10786: ifeq -> 10792
    //   10789: iload #4
    //   10791: ireturn
    //   10792: getstatic burp/Zgjj.Zi : Ljava/lang/String;
    //   10795: getstatic burp/Zkgp.Zw : Ljava/lang/Object;
    //   10798: checkcast java/math/BigInteger
    //   10801: invokevirtual intValue : ()I
    //   10804: bipush #32
    //   10806: irem
    //   10807: invokestatic abs : (I)I
    //   10810: invokevirtual charAt : (I)C
    //   10813: getstatic burp/Zzh1.Zn : Ljava/lang/String;
    //   10816: getstatic burp/Ze57.ZR : Ljava/lang/Object;
    //   10819: checkcast java/math/BigInteger
    //   10822: invokevirtual intValue : ()I
    //   10825: bipush #32
    //   10827: irem
    //   10828: invokestatic abs : (I)I
    //   10831: invokevirtual charAt : (I)C
    //   10834: if_icmple -> 11180
    //   10837: sipush #-31442
    //   10840: sipush #17719
    //   10843: invokestatic a : (II)Ljava/lang/String;
    //   10846: iconst_1
    //   10847: ldc burp/Zzlg
    //   10849: invokevirtual getClassLoader : ()Ljava/lang/ClassLoader;
    //   10852: invokestatic forName : (Ljava/lang/String;ZLjava/lang/ClassLoader;)Ljava/lang/Class;
    //   10855: invokevirtual getDeclaredFields : ()[Ljava/lang/reflect/Field;
    //   10858: astore #5
    //   10860: aload #5
    //   10862: arraylength
    //   10863: istore #6
    //   10865: iconst_0
    //   10866: istore #7
    //   10868: iload #7
    //   10870: iload #6
    //   10872: if_icmpge -> 11010
    //   10875: aload #5
    //   10877: iload #7
    //   10879: aaload
    //   10880: astore #8
    //   10882: aload #8
    //   10884: invokevirtual getModifiers : ()I
    //   10887: invokestatic isStatic : (I)Z
    //   10890: ifne -> 10900
    //   10893: goto -> 11003
    //   10896: invokestatic a : (Ljava/lang/Throwable;)Ljava/lang/Throwable;
    //   10899: athrow
    //   10900: aload #8
    //   10902: invokevirtual getType : ()Ljava/lang/Class;
    //   10905: astore #9
    //   10907: aload #9
    //   10909: ifnull -> 10990
    //   10912: aload #9
    //   10914: invokevirtual isPrimitive : ()Z
    //   10917: ifne -> 10990
    //   10920: goto -> 10927
    //   10923: invokestatic a : (Ljava/lang/Throwable;)Ljava/lang/Throwable;
    //   10926: athrow
    //   10927: aload #9
    //   10929: invokevirtual getPackage : ()Ljava/lang/Package;
    //   10932: ifnull -> 10990
    //   10935: goto -> 10942
    //   10938: invokestatic a : (Ljava/lang/Throwable;)Ljava/lang/Throwable;
    //   10941: athrow
    //   10942: aload #9
    //   10944: invokevirtual getPackage : ()Ljava/lang/Package;
    //   10947: invokevirtual getName : ()Ljava/lang/String;
    //   10950: ifnull -> 10990
    //   10953: goto -> 10960
    //   10956: invokestatic a : (Ljava/lang/Throwable;)Ljava/lang/Throwable;
    //   10959: athrow
    //   10960: aload #9
    //   10962: invokevirtual getPackage : ()Ljava/lang/Package;
    //   10965: invokevirtual getName : ()Ljava/lang/String;
    //   10968: sipush #-31443
    //   10971: sipush #20495
    //   10974: invokestatic a : (II)Ljava/lang/String;
    //   10977: invokevirtual startsWith : (Ljava/lang/String;)Z
    //   10980: ifne -> 10990
    //   10983: goto -> 10990
    //   10986: invokestatic a : (Ljava/lang/Throwable;)Ljava/lang/Throwable;
    //   10989: athrow
    //   10990: aload #8
    //   10992: iconst_1
    //   10993: invokevirtual setAccessible : (Z)V
    //   10996: aload #8
    //   10998: aconst_null
    //   10999: invokevirtual get : (Ljava/lang/Object;)Ljava/lang/Object;
    //   11002: pop
    //   11003: iinc #7, 1
    //   11006: iload_2
    //   11007: ifne -> 10868
    //   11010: sipush #-31487
    //   11013: sipush #-27557
    //   11016: invokestatic a : (II)Ljava/lang/String;
    //   11019: invokestatic forName : (Ljava/lang/String;)Ljava/lang/Class;
    //   11022: invokevirtual getDeclaredMethods : ()[Ljava/lang/reflect/Method;
    //   11025: astore #5
    //   11027: aload #5
    //   11029: arraylength
    //   11030: istore #6
    //   11032: iconst_0
    //   11033: istore #7
    //   11035: iload #7
    //   11037: iload #6
    //   11039: if_icmpge -> 11176
    //   11042: aload #5
    //   11044: iload #7
    //   11046: aaload
    //   11047: astore #8
    //   11049: aload #8
    //   11051: invokevirtual getParameterTypes : ()[Ljava/lang/Class;
    //   11054: pop
    //   11055: aload #8
    //   11057: invokevirtual getModifiers : ()I
    //   11060: invokestatic isStatic : (I)Z
    //   11063: ifeq -> 11162
    //   11066: aload #8
    //   11068: invokevirtual getParameterTypes : ()[Ljava/lang/Class;
    //   11071: arraylength
    //   11072: iconst_2
    //   11073: if_icmpne -> 11162
    //   11076: goto -> 11083
    //   11079: invokestatic a : (Ljava/lang/Throwable;)Ljava/lang/Throwable;
    //   11082: athrow
    //   11083: aload #8
    //   11085: invokevirtual getReturnType : ()Ljava/lang/Class;
    //   11088: getstatic java/lang/Boolean.TYPE : Ljava/lang/Class;
    //   11091: if_acmpne -> 11162
    //   11094: goto -> 11101
    //   11097: invokestatic a : (Ljava/lang/Throwable;)Ljava/lang/Throwable;
    //   11100: athrow
    //   11101: aload #8
    //   11103: iconst_1
    //   11104: invokevirtual setAccessible : (Z)V
    //   11107: aload #8
    //   11109: aconst_null
    //   11110: iconst_2
    //   11111: anewarray java/lang/Object
    //   11114: dup
    //   11115: iconst_0
    //   11116: aload_0
    //   11117: aastore
    //   11118: dup
    //   11119: iconst_1
    //   11120: aload_1
    //   11121: ifnonnull -> 11139
    //   11124: goto -> 11131
    //   11127: invokestatic a : (Ljava/lang/Throwable;)Ljava/lang/Throwable;
    //   11130: athrow
    //   11131: aload_1
    //   11132: goto -> 11146
    //   11135: invokestatic a : (Ljava/lang/Throwable;)Ljava/lang/Throwable;
    //   11138: athrow
    //   11139: aload_1
    //   11140: checkcast [B
    //   11143: invokevirtual clone : ()Ljava/lang/Object;
    //   11146: aastore
    //   11147: invokevirtual invoke : (Ljava/lang/Object;[Ljava/lang/Object;)Ljava/lang/Object;
    //   11150: checkcast java/lang/Boolean
    //   11153: invokevirtual booleanValue : ()Z
    //   11156: istore #4
    //   11158: iload_2
    //   11159: ifne -> 11176
    //   11162: iinc #7, 1
    //   11165: iload_2
    //   11166: ifne -> 11035
    //   11169: goto -> 11176
    //   11172: invokestatic a : (Ljava/lang/Throwable;)Ljava/lang/Throwable;
    //   11175: athrow
    //   11176: iload_2
    //   11177: ifne -> 11519
    //   11180: sipush #-31426
    //   11183: sipush #11436
    //   11186: invokestatic a : (II)Ljava/lang/String;
    //   11189: iconst_1
    //   11190: ldc burp/Zzqj
    //   11192: invokevirtual getClassLoader : ()Ljava/lang/ClassLoader;
    //   11195: invokestatic forName : (Ljava/lang/String;ZLjava/lang/ClassLoader;)Ljava/lang/Class;
    //   11198: invokevirtual getDeclaredFields : ()[Ljava/lang/reflect/Field;
    //   11201: astore #5
    //   11203: aload #5
    //   11205: arraylength
    //   11206: istore #6
    //   11208: iconst_0
    //   11209: istore #7
    //   11211: iload #7
    //   11213: iload #6
    //   11215: if_icmpge -> 11353
    //   11218: aload #5
    //   11220: iload #7
    //   11222: aaload
    //   11223: astore #8
    //   11225: aload #8
    //   11227: invokevirtual getModifiers : ()I
    //   11230: invokestatic isStatic : (I)Z
    //   11233: ifne -> 11243
    //   11236: goto -> 11346
    //   11239: invokestatic a : (Ljava/lang/Throwable;)Ljava/lang/Throwable;
    //   11242: athrow
    //   11243: aload #8
    //   11245: invokevirtual getType : ()Ljava/lang/Class;
    //   11248: astore #9
    //   11250: aload #9
    //   11252: ifnull -> 11333
    //   11255: aload #9
    //   11257: invokevirtual isPrimitive : ()Z
    //   11260: ifne -> 11333
    //   11263: goto -> 11270
    //   11266: invokestatic a : (Ljava/lang/Throwable;)Ljava/lang/Throwable;
    //   11269: athrow
    //   11270: aload #9
    //   11272: invokevirtual getPackage : ()Ljava/lang/Package;
    //   11275: ifnull -> 11333
    //   11278: goto -> 11285
    //   11281: invokestatic a : (Ljava/lang/Throwable;)Ljava/lang/Throwable;
    //   11284: athrow
    //   11285: aload #9
    //   11287: invokevirtual getPackage : ()Ljava/lang/Package;
    //   11290: invokevirtual getName : ()Ljava/lang/String;
    //   11293: ifnull -> 11333
    //   11296: goto -> 11303
    //   11299: invokestatic a : (Ljava/lang/Throwable;)Ljava/lang/Throwable;
    //   11302: athrow
    //   11303: aload #9
    //   11305: invokevirtual getPackage : ()Ljava/lang/Package;
    //   11308: invokevirtual getName : ()Ljava/lang/String;
    //   11311: sipush #-31443
    //   11314: sipush #20495
    //   11317: invokestatic a : (II)Ljava/lang/String;
    //   11320: invokevirtual startsWith : (Ljava/lang/String;)Z
    //   11323: ifne -> 11333
    //   11326: goto -> 11333
    //   11329: invokestatic a : (Ljava/lang/Throwable;)Ljava/lang/Throwable;
    //   11332: athrow
    //   11333: aload #8
    //   11335: iconst_1
    //   11336: invokevirtual setAccessible : (Z)V
    //   11339: aload #8
    //   11341: aconst_null
    //   11342: invokevirtual get : (Ljava/lang/Object;)Ljava/lang/Object;
    //   11345: pop
    //   11346: iinc #7, 1
    //   11349: iload_2
    //   11350: ifne -> 11211
    //   11353: sipush #-31453
    //   11356: sipush #7919
    //   11359: invokestatic a : (II)Ljava/lang/String;
    //   11362: invokestatic forName : (Ljava/lang/String;)Ljava/lang/Class;
    //   11365: invokevirtual getDeclaredMethods : ()[Ljava/lang/reflect/Method;
    //   11368: astore #5
    //   11370: aload #5
    //   11372: arraylength
    //   11373: istore #6
    //   11375: iconst_0
    //   11376: istore #7
    //   11378: iload #7
    //   11380: iload #6
    //   11382: if_icmpge -> 11519
    //   11385: aload #5
    //   11387: iload #7
    //   11389: aaload
    //   11390: astore #8
    //   11392: aload #8
    //   11394: invokevirtual getParameterTypes : ()[Ljava/lang/Class;
    //   11397: pop
    //   11398: aload #8
    //   11400: invokevirtual getModifiers : ()I
    //   11403: invokestatic isStatic : (I)Z
    //   11406: ifeq -> 11505
    //   11409: aload #8
    //   11411: invokevirtual getParameterTypes : ()[Ljava/lang/Class;
    //   11414: arraylength
    //   11415: iconst_2
    //   11416: if_icmpne -> 11505
    //   11419: goto -> 11426
    //   11422: invokestatic a : (Ljava/lang/Throwable;)Ljava/lang/Throwable;
    //   11425: athrow
    //   11426: aload #8
    //   11428: invokevirtual getReturnType : ()Ljava/lang/Class;
    //   11431: getstatic java/lang/Boolean.TYPE : Ljava/lang/Class;
    //   11434: if_acmpne -> 11505
    //   11437: goto -> 11444
    //   11440: invokestatic a : (Ljava/lang/Throwable;)Ljava/lang/Throwable;
    //   11443: athrow
    //   11444: aload #8
    //   11446: iconst_1
    //   11447: invokevirtual setAccessible : (Z)V
    //   11450: aload #8
    //   11452: aconst_null
    //   11453: iconst_2
    //   11454: anewarray java/lang/Object
    //   11457: dup
    //   11458: iconst_0
    //   11459: aload_0
    //   11460: aastore
    //   11461: dup
    //   11462: iconst_1
    //   11463: aload_1
    //   11464: ifnonnull -> 11482
    //   11467: goto -> 11474
    //   11470: invokestatic a : (Ljava/lang/Throwable;)Ljava/lang/Throwable;
    //   11473: athrow
    //   11474: aload_1
    //   11475: goto -> 11489
    //   11478: invokestatic a : (Ljava/lang/Throwable;)Ljava/lang/Throwable;
    //   11481: athrow
    //   11482: aload_1
    //   11483: checkcast [B
    //   11486: invokevirtual clone : ()Ljava/lang/Object;
    //   11489: aastore
    //   11490: invokevirtual invoke : (Ljava/lang/Object;[Ljava/lang/Object;)Ljava/lang/Object;
    //   11493: checkcast java/lang/Boolean
    //   11496: invokevirtual booleanValue : ()Z
    //   11499: istore #4
    //   11501: iload_2
    //   11502: ifne -> 11519
    //   11505: iinc #7, 1
    //   11508: iload_2
    //   11509: ifne -> 11378
    //   11512: goto -> 11519
    //   11515: invokestatic a : (Ljava/lang/Throwable;)Ljava/lang/Throwable;
    //   11518: athrow
    //   11519: iload #4
    //   11521: ifeq -> 11527
    //   11524: iload #4
    //   11526: ireturn
    //   11527: getstatic burp/Zbo2.Zr : Ljava/lang/String;
    //   11530: getstatic burp/Zva.Zu : Ljava/lang/Object;
    //   11533: checkcast java/math/BigInteger
    //   11536: invokevirtual intValue : ()I
    //   11539: bipush #32
    //   11541: irem
    //   11542: invokestatic abs : (I)I
    //   11545: invokevirtual charAt : (I)C
    //   11548: getstatic burp/Zgly.Zb : Ljava/lang/String;
    //   11551: getstatic burp/Zgia.Zx : Ljava/lang/Object;
    //   11554: checkcast java/math/BigInteger
    //   11557: invokevirtual intValue : ()I
    //   11560: bipush #32
    //   11562: irem
    //   11563: invokestatic abs : (I)I
    //   11566: invokevirtual charAt : (I)C
    //   11569: if_icmple -> 11915
    //   11572: sipush #-31428
    //   11575: sipush #15600
    //   11578: invokestatic a : (II)Ljava/lang/String;
    //   11581: iconst_1
    //   11582: ldc burp/Ztjh
    //   11584: invokevirtual getClassLoader : ()Ljava/lang/ClassLoader;
    //   11587: invokestatic forName : (Ljava/lang/String;ZLjava/lang/ClassLoader;)Ljava/lang/Class;
    //   11590: invokevirtual getDeclaredFields : ()[Ljava/lang/reflect/Field;
    //   11593: astore #5
    //   11595: aload #5
    //   11597: arraylength
    //   11598: istore #6
    //   11600: iconst_0
    //   11601: istore #7
    //   11603: iload #7
    //   11605: iload #6
    //   11607: if_icmpge -> 11745
    //   11610: aload #5
    //   11612: iload #7
    //   11614: aaload
    //   11615: astore #8
    //   11617: aload #8
    //   11619: invokevirtual getModifiers : ()I
    //   11622: invokestatic isStatic : (I)Z
    //   11625: ifne -> 11635
    //   11628: goto -> 11738
    //   11631: invokestatic a : (Ljava/lang/Throwable;)Ljava/lang/Throwable;
    //   11634: athrow
    //   11635: aload #8
    //   11637: invokevirtual getType : ()Ljava/lang/Class;
    //   11640: astore #9
    //   11642: aload #9
    //   11644: ifnull -> 11725
    //   11647: aload #9
    //   11649: invokevirtual isPrimitive : ()Z
    //   11652: ifne -> 11725
    //   11655: goto -> 11662
    //   11658: invokestatic a : (Ljava/lang/Throwable;)Ljava/lang/Throwable;
    //   11661: athrow
    //   11662: aload #9
    //   11664: invokevirtual getPackage : ()Ljava/lang/Package;
    //   11667: ifnull -> 11725
    //   11670: goto -> 11677
    //   11673: invokestatic a : (Ljava/lang/Throwable;)Ljava/lang/Throwable;
    //   11676: athrow
    //   11677: aload #9
    //   11679: invokevirtual getPackage : ()Ljava/lang/Package;
    //   11682: invokevirtual getName : ()Ljava/lang/String;
    //   11685: ifnull -> 11725
    //   11688: goto -> 11695
    //   11691: invokestatic a : (Ljava/lang/Throwable;)Ljava/lang/Throwable;
    //   11694: athrow
    //   11695: aload #9
    //   11697: invokevirtual getPackage : ()Ljava/lang/Package;
    //   11700: invokevirtual getName : ()Ljava/lang/String;
    //   11703: sipush #-31443
    //   11706: sipush #20495
    //   11709: invokestatic a : (II)Ljava/lang/String;
    //   11712: invokevirtual startsWith : (Ljava/lang/String;)Z
    //   11715: ifne -> 11725
    //   11718: goto -> 11725
    //   11721: invokestatic a : (Ljava/lang/Throwable;)Ljava/lang/Throwable;
    //   11724: athrow
    //   11725: aload #8
    //   11727: iconst_1
    //   11728: invokevirtual setAccessible : (Z)V
    //   11731: aload #8
    //   11733: aconst_null
    //   11734: invokevirtual get : (Ljava/lang/Object;)Ljava/lang/Object;
    //   11737: pop
    //   11738: iinc #7, 1
    //   11741: iload_2
    //   11742: ifne -> 11603
    //   11745: sipush #-31437
    //   11748: sipush #258
    //   11751: invokestatic a : (II)Ljava/lang/String;
    //   11754: invokestatic forName : (Ljava/lang/String;)Ljava/lang/Class;
    //   11757: invokevirtual getDeclaredMethods : ()[Ljava/lang/reflect/Method;
    //   11760: astore #5
    //   11762: aload #5
    //   11764: arraylength
    //   11765: istore #6
    //   11767: iconst_0
    //   11768: istore #7
    //   11770: iload #7
    //   11772: iload #6
    //   11774: if_icmpge -> 11911
    //   11777: aload #5
    //   11779: iload #7
    //   11781: aaload
    //   11782: astore #8
    //   11784: aload #8
    //   11786: invokevirtual getParameterTypes : ()[Ljava/lang/Class;
    //   11789: pop
    //   11790: aload #8
    //   11792: invokevirtual getModifiers : ()I
    //   11795: invokestatic isStatic : (I)Z
    //   11798: ifeq -> 11897
    //   11801: aload #8
    //   11803: invokevirtual getParameterTypes : ()[Ljava/lang/Class;
    //   11806: arraylength
    //   11807: iconst_2
    //   11808: if_icmpne -> 11897
    //   11811: goto -> 11818
    //   11814: invokestatic a : (Ljava/lang/Throwable;)Ljava/lang/Throwable;
    //   11817: athrow
    //   11818: aload #8
    //   11820: invokevirtual getReturnType : ()Ljava/lang/Class;
    //   11823: getstatic java/lang/Boolean.TYPE : Ljava/lang/Class;
    //   11826: if_acmpne -> 11897
    //   11829: goto -> 11836
    //   11832: invokestatic a : (Ljava/lang/Throwable;)Ljava/lang/Throwable;
    //   11835: athrow
    //   11836: aload #8
    //   11838: iconst_1
    //   11839: invokevirtual setAccessible : (Z)V
    //   11842: aload #8
    //   11844: aconst_null
    //   11845: iconst_2
    //   11846: anewarray java/lang/Object
    //   11849: dup
    //   11850: iconst_0
    //   11851: aload_0
    //   11852: aastore
    //   11853: dup
    //   11854: iconst_1
    //   11855: aload_1
    //   11856: ifnonnull -> 11874
    //   11859: goto -> 11866
    //   11862: invokestatic a : (Ljava/lang/Throwable;)Ljava/lang/Throwable;
    //   11865: athrow
    //   11866: aload_1
    //   11867: goto -> 11881
    //   11870: invokestatic a : (Ljava/lang/Throwable;)Ljava/lang/Throwable;
    //   11873: athrow
    //   11874: aload_1
    //   11875: checkcast [B
    //   11878: invokevirtual clone : ()Ljava/lang/Object;
    //   11881: aastore
    //   11882: invokevirtual invoke : (Ljava/lang/Object;[Ljava/lang/Object;)Ljava/lang/Object;
    //   11885: checkcast java/lang/Boolean
    //   11888: invokevirtual booleanValue : ()Z
    //   11891: istore #4
    //   11893: iload_2
    //   11894: ifne -> 11911
    //   11897: iinc #7, 1
    //   11900: iload_2
    //   11901: ifne -> 11770
    //   11904: goto -> 11911
    //   11907: invokestatic a : (Ljava/lang/Throwable;)Ljava/lang/Throwable;
    //   11910: athrow
    //   11911: iload_2
    //   11912: ifne -> 12254
    //   11915: sipush #-31432
    //   11918: sipush #-14092
    //   11921: invokestatic a : (II)Ljava/lang/String;
    //   11924: iconst_1
    //   11925: ldc burp/Ztc2
    //   11927: invokevirtual getClassLoader : ()Ljava/lang/ClassLoader;
    //   11930: invokestatic forName : (Ljava/lang/String;ZLjava/lang/ClassLoader;)Ljava/lang/Class;
    //   11933: invokevirtual getDeclaredFields : ()[Ljava/lang/reflect/Field;
    //   11936: astore #5
    //   11938: aload #5
    //   11940: arraylength
    //   11941: istore #6
    //   11943: iconst_0
    //   11944: istore #7
    //   11946: iload #7
    //   11948: iload #6
    //   11950: if_icmpge -> 12088
    //   11953: aload #5
    //   11955: iload #7
    //   11957: aaload
    //   11958: astore #8
    //   11960: aload #8
    //   11962: invokevirtual getModifiers : ()I
    //   11965: invokestatic isStatic : (I)Z
    //   11968: ifne -> 11978
    //   11971: goto -> 12081
    //   11974: invokestatic a : (Ljava/lang/Throwable;)Ljava/lang/Throwable;
    //   11977: athrow
    //   11978: aload #8
    //   11980: invokevirtual getType : ()Ljava/lang/Class;
    //   11983: astore #9
    //   11985: aload #9
    //   11987: ifnull -> 12068
    //   11990: aload #9
    //   11992: invokevirtual isPrimitive : ()Z
    //   11995: ifne -> 12068
    //   11998: goto -> 12005
    //   12001: invokestatic a : (Ljava/lang/Throwable;)Ljava/lang/Throwable;
    //   12004: athrow
    //   12005: aload #9
    //   12007: invokevirtual getPackage : ()Ljava/lang/Package;
    //   12010: ifnull -> 12068
    //   12013: goto -> 12020
    //   12016: invokestatic a : (Ljava/lang/Throwable;)Ljava/lang/Throwable;
    //   12019: athrow
    //   12020: aload #9
    //   12022: invokevirtual getPackage : ()Ljava/lang/Package;
    //   12025: invokevirtual getName : ()Ljava/lang/String;
    //   12028: ifnull -> 12068
    //   12031: goto -> 12038
    //   12034: invokestatic a : (Ljava/lang/Throwable;)Ljava/lang/Throwable;
    //   12037: athrow
    //   12038: aload #9
    //   12040: invokevirtual getPackage : ()Ljava/lang/Package;
    //   12043: invokevirtual getName : ()Ljava/lang/String;
    //   12046: sipush #-31443
    //   12049: sipush #20495
    //   12052: invokestatic a : (II)Ljava/lang/String;
    //   12055: invokevirtual startsWith : (Ljava/lang/String;)Z
    //   12058: ifne -> 12068
    //   12061: goto -> 12068
    //   12064: invokestatic a : (Ljava/lang/Throwable;)Ljava/lang/Throwable;
    //   12067: athrow
    //   12068: aload #8
    //   12070: iconst_1
    //   12071: invokevirtual setAccessible : (Z)V
    //   12074: aload #8
    //   12076: aconst_null
    //   12077: invokevirtual get : (Ljava/lang/Object;)Ljava/lang/Object;
    //   12080: pop
    //   12081: iinc #7, 1
    //   12084: iload_2
    //   12085: ifne -> 11946
    //   12088: sipush #-31447
    //   12091: sipush #-7727
    //   12094: invokestatic a : (II)Ljava/lang/String;
    //   12097: invokestatic forName : (Ljava/lang/String;)Ljava/lang/Class;
    //   12100: invokevirtual getDeclaredMethods : ()[Ljava/lang/reflect/Method;
    //   12103: astore #5
    //   12105: aload #5
    //   12107: arraylength
    //   12108: istore #6
    //   12110: iconst_0
    //   12111: istore #7
    //   12113: iload #7
    //   12115: iload #6
    //   12117: if_icmpge -> 12254
    //   12120: aload #5
    //   12122: iload #7
    //   12124: aaload
    //   12125: astore #8
    //   12127: aload #8
    //   12129: invokevirtual getParameterTypes : ()[Ljava/lang/Class;
    //   12132: pop
    //   12133: aload #8
    //   12135: invokevirtual getModifiers : ()I
    //   12138: invokestatic isStatic : (I)Z
    //   12141: ifeq -> 12240
    //   12144: aload #8
    //   12146: invokevirtual getParameterTypes : ()[Ljava/lang/Class;
    //   12149: arraylength
    //   12150: iconst_2
    //   12151: if_icmpne -> 12240
    //   12154: goto -> 12161
    //   12157: invokestatic a : (Ljava/lang/Throwable;)Ljava/lang/Throwable;
    //   12160: athrow
    //   12161: aload #8
    //   12163: invokevirtual getReturnType : ()Ljava/lang/Class;
    //   12166: getstatic java/lang/Boolean.TYPE : Ljava/lang/Class;
    //   12169: if_acmpne -> 12240
    //   12172: goto -> 12179
    //   12175: invokestatic a : (Ljava/lang/Throwable;)Ljava/lang/Throwable;
    //   12178: athrow
    //   12179: aload #8
    //   12181: iconst_1
    //   12182: invokevirtual setAccessible : (Z)V
    //   12185: aload #8
    //   12187: aconst_null
    //   12188: iconst_2
    //   12189: anewarray java/lang/Object
    //   12192: dup
    //   12193: iconst_0
    //   12194: aload_0
    //   12195: aastore
    //   12196: dup
    //   12197: iconst_1
    //   12198: aload_1
    //   12199: ifnonnull -> 12217
    //   12202: goto -> 12209
    //   12205: invokestatic a : (Ljava/lang/Throwable;)Ljava/lang/Throwable;
    //   12208: athrow
    //   12209: aload_1
    //   12210: goto -> 12224
    //   12213: invokestatic a : (Ljava/lang/Throwable;)Ljava/lang/Throwable;
    //   12216: athrow
    //   12217: aload_1
    //   12218: checkcast [B
    //   12221: invokevirtual clone : ()Ljava/lang/Object;
    //   12224: aastore
    //   12225: invokevirtual invoke : (Ljava/lang/Object;[Ljava/lang/Object;)Ljava/lang/Object;
    //   12228: checkcast java/lang/Boolean
    //   12231: invokevirtual booleanValue : ()Z
    //   12234: istore #4
    //   12236: iload_2
    //   12237: ifne -> 12254
    //   12240: iinc #7, 1
    //   12243: iload_2
    //   12244: ifne -> 12113
    //   12247: goto -> 12254
    //   12250: invokestatic a : (Ljava/lang/Throwable;)Ljava/lang/Throwable;
    //   12253: athrow
    //   12254: iload #4
    //   12256: ireturn
    //   12257: astore_3
    //   12258: new java/lang/Exception
    //   12261: dup
    //   12262: aload_3
    //   12263: invokevirtual getMessage : ()Ljava/lang/String;
    //   12266: invokespecial <init> : (Ljava/lang/String;)V
    //   12269: athrow
    // Exception table:
    //   from	to	target	type
    //   4	10056	12257	java/lang/Throwable
    //   55	230	233	java/lang/Throwable
    //   200	267	270	java/lang/Throwable
    //   237	304	307	java/lang/Throwable
    //   274	341	344	java/lang/Throwable
    //   311	378	381	java/lang/Throwable
    //   348	415	418	java/lang/Throwable
    //   385	452	455	java/lang/Throwable
    //   422	489	492	java/lang/Throwable
    //   459	526	529	java/lang/Throwable
    //   496	563	566	java/lang/Throwable
    //   533	600	603	java/lang/Throwable
    //   570	637	640	java/lang/Throwable
    //   607	674	677	java/lang/Throwable
    //   644	711	714	java/lang/Throwable
    //   681	748	751	java/lang/Throwable
    //   718	785	788	java/lang/Throwable
    //   755	822	825	java/lang/Throwable
    //   792	859	862	java/lang/Throwable
    //   829	896	899	java/lang/Throwable
    //   866	933	936	java/lang/Throwable
    //   903	970	973	java/lang/Throwable
    //   940	1007	1010	java/lang/Throwable
    //   977	1044	1047	java/lang/Throwable
    //   1014	1081	1084	java/lang/Throwable
    //   1051	1118	1121	java/lang/Throwable
    //   1088	1155	1158	java/lang/Throwable
    //   1125	1192	1195	java/lang/Throwable
    //   1162	1229	1232	java/lang/Throwable
    //   1199	1266	1269	java/lang/Throwable
    //   1236	1303	1306	java/lang/Throwable
    //   1273	1340	1343	java/lang/Throwable
    //   1310	1373	1376	java/lang/Throwable
    //   2197	2231	2234	java/lang/Throwable
    //   2327	2405	2408	java/lang/Throwable
    //   2334	2548	2551	java/lang/Throwable
    //   2926	2941	2941	java/lang/Throwable
    //   2968	3002	3005	java/lang/Throwable
    //   3012	3024	3027	java/lang/Throwable
    //   3110	3188	3191	java/lang/Throwable
    //   3117	3331	3334	java/lang/Throwable
    //   3731	3809	3812	java/lang/Throwable
    //   3738	3952	3955	java/lang/Throwable
    //   4399	4433	4436	java/lang/Throwable
    //   4440	4452	4455	java/lang/Throwable
    //   4538	4616	4619	java/lang/Throwable
    //   4545	4759	4762	java/lang/Throwable
    //   5516	5530	5530	java/lang/Throwable
    //   5541	5554	5557	java/lang/Throwable
    //   5546	5569	5572	java/lang/Throwable
    //   5561	5587	5590	java/lang/Throwable
    //   5576	5617	5620	java/lang/Throwable
    //   5683	5710	5713	java/lang/Throwable
    //   5700	5728	5731	java/lang/Throwable
    //   5717	5764	5767	java/lang/Throwable
    //   5735	5778	5781	java/lang/Throwable
    //   5830	5844	5844	java/lang/Throwable
    //   5855	5868	5871	java/lang/Throwable
    //   5860	5883	5886	java/lang/Throwable
    //   5875	5901	5904	java/lang/Throwable
    //   5890	5931	5934	java/lang/Throwable
    //   5997	6024	6027	java/lang/Throwable
    //   6014	6042	6045	java/lang/Throwable
    //   6031	6072	6075	java/lang/Throwable
    //   6049	6083	6083	java/lang/Throwable
    //   6094	6110	6113	java/lang/Throwable
    //   6162	6176	6176	java/lang/Throwable
    //   6187	6200	6203	java/lang/Throwable
    //   6192	6215	6218	java/lang/Throwable
    //   6207	6233	6236	java/lang/Throwable
    //   6222	6263	6266	java/lang/Throwable
    //   6329	6356	6359	java/lang/Throwable
    //   6346	6377	6380	java/lang/Throwable
    //   6363	6407	6410	java/lang/Throwable
    //   6384	6418	6418	java/lang/Throwable
    //   6429	6445	6448	java/lang/Throwable
    //   6525	6539	6539	java/lang/Throwable
    //   6550	6563	6566	java/lang/Throwable
    //   6555	6578	6581	java/lang/Throwable
    //   6570	6596	6599	java/lang/Throwable
    //   6585	6626	6629	java/lang/Throwable
    //   6692	6719	6722	java/lang/Throwable
    //   6709	6740	6743	java/lang/Throwable
    //   6726	6770	6773	java/lang/Throwable
    //   6747	6781	6781	java/lang/Throwable
    //   6792	6808	6811	java/lang/Throwable
    //   6963	6978	6978	java/lang/Throwable
    //   7980	8006	8006	java/lang/Throwable
    //   8087	8102	8102	java/lang/Throwable
    //   9284	9309	9312	java/lang/Throwable
    //   9413	9427	9427	java/lang/Throwable
    //   9438	9451	9454	java/lang/Throwable
    //   9443	9466	9469	java/lang/Throwable
    //   9458	9484	9487	java/lang/Throwable
    //   9473	9514	9517	java/lang/Throwable
    //   9580	9607	9610	java/lang/Throwable
    //   9597	9625	9628	java/lang/Throwable
    //   9614	9655	9658	java/lang/Throwable
    //   9632	9666	9666	java/lang/Throwable
    //   9689	9700	9703	java/lang/Throwable
    //   9755	9769	9769	java/lang/Throwable
    //   9780	9793	9796	java/lang/Throwable
    //   9785	9808	9811	java/lang/Throwable
    //   9800	9826	9829	java/lang/Throwable
    //   9815	9856	9859	java/lang/Throwable
    //   9922	9949	9952	java/lang/Throwable
    //   9939	9967	9970	java/lang/Throwable
    //   9956	9997	10000	java/lang/Throwable
    //   9974	10008	10008	java/lang/Throwable
    //   10031	10042	10045	java/lang/Throwable
    //   10057	10791	12257	java/lang/Throwable
    //   10147	10161	10161	java/lang/Throwable
    //   10172	10185	10188	java/lang/Throwable
    //   10177	10200	10203	java/lang/Throwable
    //   10192	10218	10221	java/lang/Throwable
    //   10207	10248	10251	java/lang/Throwable
    //   10314	10341	10344	java/lang/Throwable
    //   10331	10359	10362	java/lang/Throwable
    //   10348	10389	10392	java/lang/Throwable
    //   10366	10400	10400	java/lang/Throwable
    //   10423	10434	10437	java/lang/Throwable
    //   10490	10504	10504	java/lang/Throwable
    //   10515	10528	10531	java/lang/Throwable
    //   10520	10543	10546	java/lang/Throwable
    //   10535	10561	10564	java/lang/Throwable
    //   10550	10591	10594	java/lang/Throwable
    //   10657	10684	10687	java/lang/Throwable
    //   10674	10702	10705	java/lang/Throwable
    //   10691	10732	10735	java/lang/Throwable
    //   10709	10743	10743	java/lang/Throwable
    //   10766	10777	10780	java/lang/Throwable
    //   10792	11526	12257	java/lang/Throwable
    //   10882	10896	10896	java/lang/Throwable
    //   10907	10920	10923	java/lang/Throwable
    //   10912	10935	10938	java/lang/Throwable
    //   10927	10953	10956	java/lang/Throwable
    //   10942	10983	10986	java/lang/Throwable
    //   11049	11076	11079	java/lang/Throwable
    //   11066	11094	11097	java/lang/Throwable
    //   11083	11124	11127	java/lang/Throwable
    //   11101	11135	11135	java/lang/Throwable
    //   11158	11169	11172	java/lang/Throwable
    //   11225	11239	11239	java/lang/Throwable
    //   11250	11263	11266	java/lang/Throwable
    //   11255	11278	11281	java/lang/Throwable
    //   11270	11296	11299	java/lang/Throwable
    //   11285	11326	11329	java/lang/Throwable
    //   11392	11419	11422	java/lang/Throwable
    //   11409	11437	11440	java/lang/Throwable
    //   11426	11467	11470	java/lang/Throwable
    //   11444	11478	11478	java/lang/Throwable
    //   11501	11512	11515	java/lang/Throwable
    //   11527	12256	12257	java/lang/Throwable
    //   11617	11631	11631	java/lang/Throwable
    //   11642	11655	11658	java/lang/Throwable
    //   11647	11670	11673	java/lang/Throwable
    //   11662	11688	11691	java/lang/Throwable
    //   11677	11718	11721	java/lang/Throwable
    //   11784	11811	11814	java/lang/Throwable
    //   11801	11829	11832	java/lang/Throwable
    //   11818	11859	11862	java/lang/Throwable
    //   11836	11870	11870	java/lang/Throwable
    //   11893	11904	11907	java/lang/Throwable
    //   11960	11974	11974	java/lang/Throwable
    //   11985	11998	12001	java/lang/Throwable
    //   11990	12013	12016	java/lang/Throwable
    //   12005	12031	12034	java/lang/Throwable
    //   12020	12061	12064	java/lang/Throwable
    //   12127	12154	12157	java/lang/Throwable
    //   12144	12172	12175	java/lang/Throwable
    //   12161	12202	12205	java/lang/Throwable
    //   12179	12213	12213	java/lang/Throwable
    //   12236	12247	12250	java/lang/Throwable
  }
  
  static {
    // Byte code:
    //   0: bipush #35
    //   2: anewarray java/lang/String
    //   5: astore #5
    //   7: iconst_0
    //   8: istore_3
    //   9: ldc 'G)BXU-C\\r h)pV&o9\\r*#rKO%\\b0{gIR u~\\te\\fP]jo&Z??\\t7UN\\tu\<\\tG\\biP,\\t~\p9u[\\t3\\r{\\tdi\\tK[\\tN?y,^@au\\t\\n<\\tffS[\\tpsHuM8[Y,\\n%vI3p\\bM| t>-}( 3d+F/[j0'=z9"bF}hK\\tJav??\\t$Wm\\t&rn3@O\\tvd\\t\\n=m{*\\fw\\tDSw8\\t1;"\\tvdH/\\t08{Il\\t4\\tiA2'
    //   11: dup
    //   12: astore_2
    //   13: invokevirtual length : ()I
    //   16: istore #4
    //   18: bipush #9
    //   20: istore_1
    //   21: iconst_m1
    //   22: istore_0
    //   23: bipush #102
    //   25: iinc #0, 1
    //   28: aload_2
    //   29: iload_0
    //   30: dup
    //   31: iload_1
    //   32: iadd
    //   33: invokevirtual substring : (II)Ljava/lang/String;
    //   36: iconst_m1
    //   37: goto -> 143
    //   40: aload #5
    //   42: swap
    //   43: iload_3
    //   44: iinc #3, 1
    //   47: swap
    //   48: aastore
    //   49: iload_0
    //   50: iload_1
    //   51: iadd
    //   52: dup
    //   53: istore_0
    //   54: iload #4
    //   56: if_icmpge -> 68
    //   59: aload_2
    //   60: iload_0
    //   61: invokevirtual charAt : (I)C
    //   64: istore_1
    //   65: goto -> 23
    //   68: ldc '\\n[\\t0{<5s'
    //   70: dup
    //   71: astore_2
    //   72: invokevirtual length : ()I
    //   75: istore #4
    //   77: bipush #9
    //   79: istore_1
    //   80: iconst_m1
    //   81: istore_0
    //   82: bipush #69
    //   84: iinc #0, 1
    //   87: aload_2
    //   88: iload_0
    //   89: dup
    //   90: iload_1
    //   91: iadd
    //   92: invokevirtual substring : (II)Ljava/lang/String;
    //   95: iconst_0
    //   96: goto -> 143
    //   99: aload #5
    //   101: swap
    //   102: iload_3
    //   103: iinc #3, 1
    //   106: swap
    //   107: aastore
    //   108: iload_0
    //   109: iload_1
    //   110: iadd
    //   111: dup
    //   112: istore_0
    //   113: iload #4
    //   115: if_icmpge -> 127
    //   118: aload_2
    //   119: iload_0
    //   120: invokevirtual charAt : (I)C
    //   123: istore_1
    //   124: goto -> 82
    //   127: aload #5
    //   129: putstatic burp/Zgjs.a : [Ljava/lang/String;
    //   132: bipush #35
    //   134: anewarray java/lang/String
    //   137: putstatic burp/Zgjs.b : [Ljava/lang/String;
    //   140: goto -> 300
    //   143: dup_x2
    //   144: pop
    //   145: invokevirtual toCharArray : ()[C
    //   148: dup_x1
    //   149: arraylength
    //   150: dup_x2
    //   151: pop
    //   152: iconst_0
    //   153: istore #6
    //   155: dup2_x1
    //   156: pop2
    //   157: dup_x2
    //   158: iconst_1
    //   159: if_icmpgt -> 260
    //   162: dup2
    //   163: swap
    //   164: iload #6
    //   166: dup2_x1
    //   167: caload
    //   168: swap
    //   169: iload #6
    //   171: bipush #7
    //   173: irem
    //   174: tableswitch default -> 242, 0 -> 212, 1 -> 217, 2 -> 222, 3 -> 227, 4 -> 232, 5 -> 237
    //   212: bipush #66
    //   214: goto -> 244
    //   217: bipush #10
    //   219: goto -> 244
    //   222: bipush #20
    //   224: goto -> 244
    //   227: bipush #61
    //   229: goto -> 244
    //   232: bipush #39
    //   234: goto -> 244
    //   237: bipush #15
    //   239: goto -> 244
    //   242: bipush #52
    //   244: ixor
    //   245: ixor
    //   246: i2c
    //   247: castore
    //   248: iinc #6, 1
    //   251: dup
    //   252: ifne -> 260
    //   255: dup2
    //   256: dup_x1
    //   257: goto -> 166
    //   260: dup2_x1
    //   261: pop2
    //   262: dup_x2
    //   263: iload #6
    //   265: if_icmpgt -> 162
    //   268: pop
    //   269: new java/lang/String
    //   272: dup_x1
    //   273: swap
    //   274: invokespecial <init> : ([C)V
    //   277: invokevirtual intern : ()Ljava/lang/String;
    //   280: swap
    //   281: pop
    //   282: swap
    //   283: tableswitch default -> 40, 0 -> 99
    //   300: new java/math/BigInteger
    //   303: dup
    //   304: iconst_1
    //   305: bipush #32
    //   307: newarray byte
    //   309: dup
    //   310: iconst_0
    //   311: iconst_1
    //   312: bastore
    //   313: dup
    //   314: iconst_1
    //   315: bipush #-43
    //   317: bastore
    //   318: dup
    //   319: iconst_2
    //   320: bipush #32
    //   322: bastore
    //   323: dup
    //   324: iconst_3
    //   325: bipush #94
    //   327: bastore
    //   328: dup
    //   329: iconst_4
    //   330: bipush #-89
    //   332: bastore
    //   333: dup
    //   334: iconst_5
    //   335: bipush #116
    //   337: bastore
    //   338: dup
    //   339: bipush #6
    //   341: bipush #-84
    //   343: bastore
    //   344: dup
    //   345: bipush #7
    //   347: bipush #-63
    //   349: bastore
    //   350: dup
    //   351: bipush #8
    //   353: bipush #-102
    //   355: bastore
    //   356: dup
    //   357: bipush #9
    //   359: bipush #17
    //   361: bastore
    //   362: dup
    //   363: bipush #10
    //   365: bipush #124
    //   367: bastore
    //   368: dup
    //   369: bipush #11
    //   371: bipush #30
    //   373: bastore
    //   374: dup
    //   375: bipush #12
    //   377: bipush #9
    //   379: bastore
    //   380: dup
    //   381: bipush #13
    //   383: bipush #83
    //   385: bastore
    //   386: dup
    //   387: bipush #14
    //   389: bipush #-38
    //   391: bastore
    //   392: dup
    //   393: bipush #15
    //   395: bipush #28
    //   397: bastore
    //   398: dup
    //   399: bipush #16
    //   401: bipush #-111
    //   403: bastore
    //   404: dup
    //   405: bipush #17
    //   407: bipush #-30
    //   409: bastore
    //   410: dup
    //   411: bipush #18
    //   413: bipush #-79
    //   415: bastore
    //   416: dup
    //   417: bipush #19
    //   419: bipush #13
    //   421: bastore
    //   422: dup
    //   423: bipush #20
    //   425: bipush #-68
    //   427: bastore
    //   428: dup
    //   429: bipush #21
    //   431: bipush #30
    //   433: bastore
    //   434: dup
    //   435: bipush #22
    //   437: bipush #54
    //   439: bastore
    //   440: dup
    //   441: bipush #23
    //   443: bipush #76
    //   445: bastore
    //   446: dup
    //   447: bipush #24
    //   449: bipush #-90
    //   451: bastore
    //   452: dup
    //   453: bipush #25
    //   455: bipush #-108
    //   457: bastore
    //   458: dup
    //   459: bipush #26
    //   461: bipush #41
    //   463: bastore
    //   464: dup
    //   465: bipush #27
    //   467: bipush #-95
    //   469: bastore
    //   470: dup
    //   471: bipush #28
    //   473: bipush #-106
    //   475: bastore
    //   476: dup
    //   477: bipush #29
    //   479: bipush #46
    //   481: bastore
    //   482: dup
    //   483: bipush #30
    //   485: bipush #58
    //   487: bastore
    //   488: dup
    //   489: bipush #31
    //   491: bipush #-101
    //   493: bastore
    //   494: invokespecial <init> : (I[B)V
    //   497: putstatic burp/Zgjs.Za : Ljava/lang/Object;
    //   500: sipush #-31456
    //   503: sipush #11230
    //   506: invokestatic a : (II)Ljava/lang/String;
    //   509: putstatic burp/Zgjs.Zp : Ljava/lang/String;
    //   512: return
  }
  
  private static Throwable a(Throwable paramThrowable) {
    return paramThrowable;
  }
  
  private static String a(int paramInt1, int paramInt2) {
    int i = (paramInt1 ^ 0xFFFF8523) & 0xFFFF;
    if (b[i] == null) {
      char[] arrayOfChar = a[i].toCharArray();
      switch (arrayOfChar[0] & 0xFF) {
        case 0:
        
        case 1:
        
        case 2:
        
        case 3:
        
        case 4:
        
        case 5:
        
        case 6:
        
        case 7:
        
        case 8:
        
        case 9:
        
        case 10:
        
        case 11:
        
        case 12:
        
        case 13:
        
        case 14:
        
        case 15:
        
        case 16:
        
        case 17:
        
        case 18:
        
        case 19:
        
        case 20:
        
        case 21:
        
        case 22:
        
        case 23:
        
        case 24:
        
        case 25:
        
        case 26:
        
        case 27:
        
        case 28:
        
        case 29:
        
        case 30:
        
        case 31:
        
        case 32:
        
        case 33:
        
        case 34:
        
        case 35:
        
        case 36:
        
        case 37:
        
        case 38:
        
        case 39:
        
        case 40:
        
        case 41:
        
        case 42:
        
        case 43:
        
        case 44:
        
        case 45:
        
        case 46:
        
        case 47:
        
        case 48:
        
        case 49:
        
        case 50:
        
        case 51:
        
        case 52:
        
        case 53:
        
        case 54:
        
        case 55:
        
        case 56:
        
        case 57:
        
        case 58:
        
        case 59:
        
        case 60:
        
        case 61:
        
        case 62:
        
        case 63:
        
        case 64:
        
        case 65:
        
        case 66:
        
        case 67:
        
        case 68:
        
        case 69:
        
        case 70:
        
        case 71:
        
        case 72:
        
        case 73:
        
        case 74:
        
        case 75:
        
        case 76:
        
        case 77:
        
        case 78:
        
        case 79:
        
        case 80:
        
        case 81:
        
        case 82:
        
        case 83:
        
        case 84:
        
        case 85:
        
        case 86:
        
        case 87:
        
        case 88:
        
        case 89:
        
        case 90:
        
        case 91:
        
        case 92:
        
        case 93:
        
        case 94:
        
        case 95:
        
        case 96:
        
        case 97:
        
        case 98:
        
        case 99:
        
        case 100:
        
        case 101:
        
        case 102:
        
        case 103:
        
        case 104:
        
        case 105:
        
        case 106:
        
        case 107:
        
        case 108:
        
        case 109:
        
        case 110:
        
        case 111:
        
        case 112:
        
        case 113:
        
        case 114:
        
        case 115:
        
        case 116:
        
        case 117:
        
        case 118:
        
        case 119:
        
        case 120:
        
        case 121:
        
        case 122:
        
        case 123:
        
        case 124:
        
        case 125:
        
        case 126:
        
        case 127:
        
        case 128:
        
        case 129:
        
        case 130:
        
        case 131:
        
        case 132:
        
        case 133:
        
        case 134:
        
        case 135:
        
        case 136:
        
        case 137:
        
        case 138:
        
        case 139:
        
        case 140:
        
        case 141:
        
        case 142:
        
        case 143:
        
        case 144:
        
        case 145:
        
        case 146:
        
        case 147:
        
        case 148:
        
        case 149:
        
        case 150:
        
        case 151:
        
        case 152:
        
        case 153:
        
        case 154:
        
        case 155:
        
        case 156:
        
        case 157:
        
        case 158:
        
        case 159:
        
        case 160:
        
        case 161:
        
        case 162:
        
        case 163:
        
        case 164:
        
        case 165:
        
        case 166:
        
        case 167:
        
        case 168:
        
        case 169:
        
        case 170:
        
        case 171:
        
        case 172:
        
        case 173:
        
        case 174:
        
        case 175:
        
        case 176:
        
        case 177:
        
        case 178:
        
        case 179:
        
        case 180:
        
        case 181:
        
        case 182:
        
        case 183:
        
        case 184:
        
        case 185:
        
        case 186:
        
        case 187:
        
        case 188:
        
        case 189:
        
        case 190:
        
        case 191:
        
        case 192:
        
        case 193:
        
        case 194:
        
        case 195:
        
        case 196:
        
        case 197:
        
        case 198:
        
        case 199:
        
        case 200:
        
        case 201:
        
        case 202:
        
        case 203:
        
        case 204:
        
        case 205:
        
        case 206:
        
        case 207:
        
        case 208:
        
        case 209:
        
        case 210:
        
        case 211:
        
        case 212:
        
        case 213:
        
        case 214:
        
        case 215:
        
        case 216:
        
        case 217:
        
        case 218:
        
        case 219:
        
        case 220:
        
        case 221:
        
        case 222:
        
        case 223:
        
        case 224:
        
        case 225:
        
        case 226:
        
        case 227:
        
        case 228:
        
        case 229:
        
        case 230:
        
        case 231:
        
        case 232:
        
        case 233:
        
        case 234:
        
        case 235:
        
        case 236:
        
        case 237:
        
        case 238:
        
        case 239:
        
        case 240:
        
        case 241:
        
        case 242:
        
        case 243:
        
        case 244:
        
        case 245:
        
        case 246:
        
        case 247:
        
        case 248:
        
        case 249:
        
        case 250:
        
        case 251:
        
        case 252:
        
        case 253:
        
        case 254:
        
        default:
          break;
      } 
      byte b1 = 123;
      int j = (paramInt2 & 0xFF) - b1;
      if (j < 0)
        j += 256; 
      int k = ((paramInt2 & 0xFFFF) >>> 8) - b1;
      if (k < 0)
        k += 256; 
      for (byte b2 = 0; b2 < arrayOfChar.length; b2++) {
        int m = b2 % 2;
        if (m == 0) {
          arrayOfChar[b2] = (char)(arrayOfChar[b2] ^ j);
          j = ((j >>> 3 | j << 5) ^ arrayOfChar[b2]) & 0xFF;
        } else {
          arrayOfChar[b2] = (char)(arrayOfChar[b2] ^ k);
          k = ((k >>> 3 | k << 5) ^ arrayOfChar[b2]) & 0xFF;
        } 
      } 
      b[i] = (new String(arrayOfChar)).intern();
    } 
    return b[i];
  }
}


/* Location:              C:\Program Files\BurpSuitePro\burpsuite_pro.jar!\burp\Zgjs.class
 * Java compiler version: 21 (65.0)
 * JD-Core Version:       1.1.3
 */