package burp;

import java.math.BigInteger;

class Zgk9 extends ClassLoader {
  static Object ZD;
  
  static String Zf;
  
  private static final String[] a;
  
  private static final String[] b;
  
  static boolean ZE(Object[] paramArrayOfObject, Object paramObject) throws Throwable {
    // Byte code:
    //   0: invokestatic ZN : ()Z
    //   3: istore_2
    //   4: getstatic burp/Zrym.Zk : Ljava/lang/Object;
    //   7: checkcast java/math/BigInteger
    //   10: invokevirtual toByteArray : ()[B
    //   13: astore_3
    //   14: bipush #32
    //   16: newarray int
    //   18: dup
    //   19: iconst_0
    //   20: ldc 876216579
    //   22: iastore
    //   23: dup
    //   24: iconst_1
    //   25: ldc 455999525
    //   27: iastore
    //   28: dup
    //   29: iconst_2
    //   30: ldc 1043334948
    //   32: iastore
    //   33: dup
    //   34: iconst_3
    //   35: ldc 439222784
    //   37: iastore
    //   38: dup
    //   39: iconst_4
    //   40: ldc 372376604
    //   42: iastore
    //   43: dup
    //   44: iconst_5
    //   45: ldc 707731490
    //   47: iastore
    //   48: dup
    //   49: bipush #6
    //   51: ldc 389426184
    //   53: iastore
    //   54: dup
    //   55: bipush #7
    //   57: ldc 973875457
    //   59: iastore
    //   60: dup
    //   61: bipush #8
    //   63: ldc 389160971
    //   65: iastore
    //   66: dup
    //   67: bipush #9
    //   69: ldc 907870729
    //   71: iastore
    //   72: dup
    //   73: bipush #10
    //   75: ldc 121057538
    //   77: iastore
    //   78: dup
    //   79: bipush #11
    //   81: ldc 840500228
    //   83: iastore
    //   84: dup
    //   85: bipush #12
    //   87: ldc 254150144
    //   89: iastore
    //   90: dup
    //   91: bipush #13
    //   93: ldc 924386310
    //   95: iastore
    //   96: dup
    //   97: bipush #14
    //   99: ldc 187632156
    //   101: iastore
    //   102: dup
    //   103: bipush #15
    //   105: ldc 874189824
    //   107: iastore
    //   108: dup
    //   109: bipush #16
    //   111: ldc 655302664
    //   113: iastore
    //   114: dup
    //   115: bipush #17
    //   117: ldc 890966315
    //   119: iastore
    //   120: dup
    //   121: bipush #18
    //   123: ldc 722417666
    //   125: iastore
    //   126: dup
    //   127: bipush #19
    //   129: ldc 1026621720
    //   131: iastore
    //   132: dup
    //   133: bipush #20
    //   135: ldc 957157408
    //   137: iastore
    //   138: dup
    //   139: bipush #21
    //   141: ldc 892536332
    //   143: iastore
    //   144: dup
    //   145: bipush #22
    //   147: ldc 689771012
    //   149: iastore
    //   150: dup
    //   151: bipush #23
    //   153: ldc 221709344
    //   155: iastore
    //   156: dup
    //   157: bipush #24
    //   159: ldc 940377620
    //   161: iastore
    //   162: dup
    //   163: bipush #25
    //   165: ldc 255209728
    //   167: iastore
    //   168: dup
    //   169: bipush #26
    //   171: ldc 1010368540
    //   173: iastore
    //   174: dup
    //   175: bipush #27
    //   177: ldc 220604441
    //   179: iastore
    //   180: dup
    //   181: bipush #28
    //   183: ldc 1008414755
    //   185: iastore
    //   186: dup
    //   187: bipush #29
    //   189: ldc 187049985
    //   191: iastore
    //   192: dup
    //   193: bipush #30
    //   195: ldc 943331329
    //   197: iastore
    //   198: dup
    //   199: bipush #31
    //   201: ldc 170788368
    //   203: iastore
    //   204: astore #5
    //   206: bipush #64
    //   208: newarray int
    //   210: dup
    //   211: iconst_0
    //   212: ldc 16843776
    //   214: iastore
    //   215: dup
    //   216: iconst_1
    //   217: iconst_0
    //   218: iastore
    //   219: dup
    //   220: iconst_2
    //   221: ldc 65536
    //   223: iastore
    //   224: dup
    //   225: iconst_3
    //   226: ldc 16843780
    //   228: iastore
    //   229: dup
    //   230: iconst_4
    //   231: ldc 16842756
    //   233: iastore
    //   234: dup
    //   235: iconst_5
    //   236: ldc 66564
    //   238: iastore
    //   239: dup
    //   240: bipush #6
    //   242: iconst_4
    //   243: iastore
    //   244: dup
    //   245: bipush #7
    //   247: ldc 65536
    //   249: iastore
    //   250: dup
    //   251: bipush #8
    //   253: sipush #1024
    //   256: iastore
    //   257: dup
    //   258: bipush #9
    //   260: ldc 16843776
    //   262: iastore
    //   263: dup
    //   264: bipush #10
    //   266: ldc 16843780
    //   268: iastore
    //   269: dup
    //   270: bipush #11
    //   272: sipush #1024
    //   275: iastore
    //   276: dup
    //   277: bipush #12
    //   279: ldc 16778244
    //   281: iastore
    //   282: dup
    //   283: bipush #13
    //   285: ldc 16842756
    //   287: iastore
    //   288: dup
    //   289: bipush #14
    //   291: ldc 16777216
    //   293: iastore
    //   294: dup
    //   295: bipush #15
    //   297: iconst_4
    //   298: iastore
    //   299: dup
    //   300: bipush #16
    //   302: sipush #1028
    //   305: iastore
    //   306: dup
    //   307: bipush #17
    //   309: ldc 16778240
    //   311: iastore
    //   312: dup
    //   313: bipush #18
    //   315: ldc 16778240
    //   317: iastore
    //   318: dup
    //   319: bipush #19
    //   321: ldc 66560
    //   323: iastore
    //   324: dup
    //   325: bipush #20
    //   327: ldc 66560
    //   329: iastore
    //   330: dup
    //   331: bipush #21
    //   333: ldc 16842752
    //   335: iastore
    //   336: dup
    //   337: bipush #22
    //   339: ldc 16842752
    //   341: iastore
    //   342: dup
    //   343: bipush #23
    //   345: ldc 16778244
    //   347: iastore
    //   348: dup
    //   349: bipush #24
    //   351: ldc 65540
    //   353: iastore
    //   354: dup
    //   355: bipush #25
    //   357: ldc 16777220
    //   359: iastore
    //   360: dup
    //   361: bipush #26
    //   363: ldc 16777220
    //   365: iastore
    //   366: dup
    //   367: bipush #27
    //   369: ldc 65540
    //   371: iastore
    //   372: dup
    //   373: bipush #28
    //   375: iconst_0
    //   376: iastore
    //   377: dup
    //   378: bipush #29
    //   380: sipush #1028
    //   383: iastore
    //   384: dup
    //   385: bipush #30
    //   387: ldc 66564
    //   389: iastore
    //   390: dup
    //   391: bipush #31
    //   393: ldc 16777216
    //   395: iastore
    //   396: dup
    //   397: bipush #32
    //   399: ldc 65536
    //   401: iastore
    //   402: dup
    //   403: bipush #33
    //   405: ldc 16843780
    //   407: iastore
    //   408: dup
    //   409: bipush #34
    //   411: iconst_4
    //   412: iastore
    //   413: dup
    //   414: bipush #35
    //   416: ldc 16842752
    //   418: iastore
    //   419: dup
    //   420: bipush #36
    //   422: ldc 16843776
    //   424: iastore
    //   425: dup
    //   426: bipush #37
    //   428: ldc 16777216
    //   430: iastore
    //   431: dup
    //   432: bipush #38
    //   434: ldc 16777216
    //   436: iastore
    //   437: dup
    //   438: bipush #39
    //   440: sipush #1024
    //   443: iastore
    //   444: dup
    //   445: bipush #40
    //   447: ldc 16842756
    //   449: iastore
    //   450: dup
    //   451: bipush #41
    //   453: ldc 65536
    //   455: iastore
    //   456: dup
    //   457: bipush #42
    //   459: ldc 66560
    //   461: iastore
    //   462: dup
    //   463: bipush #43
    //   465: ldc 16777220
    //   467: iastore
    //   468: dup
    //   469: bipush #44
    //   471: sipush #1024
    //   474: iastore
    //   475: dup
    //   476: bipush #45
    //   478: iconst_4
    //   479: iastore
    //   480: dup
    //   481: bipush #46
    //   483: ldc 16778244
    //   485: iastore
    //   486: dup
    //   487: bipush #47
    //   489: ldc 66564
    //   491: iastore
    //   492: dup
    //   493: bipush #48
    //   495: ldc 16843780
    //   497: iastore
    //   498: dup
    //   499: bipush #49
    //   501: ldc 65540
    //   503: iastore
    //   504: dup
    //   505: bipush #50
    //   507: ldc 16842752
    //   509: iastore
    //   510: dup
    //   511: bipush #51
    //   513: ldc 16778244
    //   515: iastore
    //   516: dup
    //   517: bipush #52
    //   519: ldc 16777220
    //   521: iastore
    //   522: dup
    //   523: bipush #53
    //   525: sipush #1028
    //   528: iastore
    //   529: dup
    //   530: bipush #54
    //   532: ldc 66564
    //   534: iastore
    //   535: dup
    //   536: bipush #55
    //   538: ldc 16843776
    //   540: iastore
    //   541: dup
    //   542: bipush #56
    //   544: sipush #1028
    //   547: iastore
    //   548: dup
    //   549: bipush #57
    //   551: ldc 16778240
    //   553: iastore
    //   554: dup
    //   555: bipush #58
    //   557: ldc 16778240
    //   559: iastore
    //   560: dup
    //   561: bipush #59
    //   563: iconst_0
    //   564: iastore
    //   565: dup
    //   566: bipush #60
    //   568: ldc 65540
    //   570: iastore
    //   571: dup
    //   572: bipush #61
    //   574: ldc 66560
    //   576: iastore
    //   577: dup
    //   578: bipush #62
    //   580: iconst_0
    //   581: iastore
    //   582: dup
    //   583: bipush #63
    //   585: ldc 16842756
    //   587: iastore
    //   588: astore #6
    //   590: bipush #64
    //   592: newarray int
    //   594: dup
    //   595: iconst_0
    //   596: ldc -2146402272
    //   598: iastore
    //   599: dup
    //   600: iconst_1
    //   601: ldc -2147450880
    //   603: iastore
    //   604: dup
    //   605: iconst_2
    //   606: ldc 32768
    //   608: iastore
    //   609: dup
    //   610: iconst_3
    //   611: ldc 1081376
    //   613: iastore
    //   614: dup
    //   615: iconst_4
    //   616: ldc 1048576
    //   618: iastore
    //   619: dup
    //   620: iconst_5
    //   621: bipush #32
    //   623: iastore
    //   624: dup
    //   625: bipush #6
    //   627: ldc -2146435040
    //   629: iastore
    //   630: dup
    //   631: bipush #7
    //   633: ldc -2147450848
    //   635: iastore
    //   636: dup
    //   637: bipush #8
    //   639: ldc -2147483616
    //   641: iastore
    //   642: dup
    //   643: bipush #9
    //   645: ldc -2146402272
    //   647: iastore
    //   648: dup
    //   649: bipush #10
    //   651: ldc -2146402304
    //   653: iastore
    //   654: dup
    //   655: bipush #11
    //   657: ldc -2147483648
    //   659: iastore
    //   660: dup
    //   661: bipush #12
    //   663: ldc -2147450880
    //   665: iastore
    //   666: dup
    //   667: bipush #13
    //   669: ldc 1048576
    //   671: iastore
    //   672: dup
    //   673: bipush #14
    //   675: bipush #32
    //   677: iastore
    //   678: dup
    //   679: bipush #15
    //   681: ldc -2146435040
    //   683: iastore
    //   684: dup
    //   685: bipush #16
    //   687: ldc 1081344
    //   689: iastore
    //   690: dup
    //   691: bipush #17
    //   693: ldc 1048608
    //   695: iastore
    //   696: dup
    //   697: bipush #18
    //   699: ldc -2147450848
    //   701: iastore
    //   702: dup
    //   703: bipush #19
    //   705: iconst_0
    //   706: iastore
    //   707: dup
    //   708: bipush #20
    //   710: ldc -2147483648
    //   712: iastore
    //   713: dup
    //   714: bipush #21
    //   716: ldc 32768
    //   718: iastore
    //   719: dup
    //   720: bipush #22
    //   722: ldc 1081376
    //   724: iastore
    //   725: dup
    //   726: bipush #23
    //   728: ldc -2146435072
    //   730: iastore
    //   731: dup
    //   732: bipush #24
    //   734: ldc 1048608
    //   736: iastore
    //   737: dup
    //   738: bipush #25
    //   740: ldc -2147483616
    //   742: iastore
    //   743: dup
    //   744: bipush #26
    //   746: iconst_0
    //   747: iastore
    //   748: dup
    //   749: bipush #27
    //   751: ldc 1081344
    //   753: iastore
    //   754: dup
    //   755: bipush #28
    //   757: ldc 32800
    //   759: iastore
    //   760: dup
    //   761: bipush #29
    //   763: ldc -2146402304
    //   765: iastore
    //   766: dup
    //   767: bipush #30
    //   769: ldc -2146435072
    //   771: iastore
    //   772: dup
    //   773: bipush #31
    //   775: ldc 32800
    //   777: iastore
    //   778: dup
    //   779: bipush #32
    //   781: iconst_0
    //   782: iastore
    //   783: dup
    //   784: bipush #33
    //   786: ldc 1081376
    //   788: iastore
    //   789: dup
    //   790: bipush #34
    //   792: ldc -2146435040
    //   794: iastore
    //   795: dup
    //   796: bipush #35
    //   798: ldc 1048576
    //   800: iastore
    //   801: dup
    //   802: bipush #36
    //   804: ldc -2147450848
    //   806: iastore
    //   807: dup
    //   808: bipush #37
    //   810: ldc -2146435072
    //   812: iastore
    //   813: dup
    //   814: bipush #38
    //   816: ldc -2146402304
    //   818: iastore
    //   819: dup
    //   820: bipush #39
    //   822: ldc 32768
    //   824: iastore
    //   825: dup
    //   826: bipush #40
    //   828: ldc -2146435072
    //   830: iastore
    //   831: dup
    //   832: bipush #41
    //   834: ldc -2147450880
    //   836: iastore
    //   837: dup
    //   838: bipush #42
    //   840: bipush #32
    //   842: iastore
    //   843: dup
    //   844: bipush #43
    //   846: ldc -2146402272
    //   848: iastore
    //   849: dup
    //   850: bipush #44
    //   852: ldc 1081376
    //   854: iastore
    //   855: dup
    //   856: bipush #45
    //   858: bipush #32
    //   860: iastore
    //   861: dup
    //   862: bipush #46
    //   864: ldc 32768
    //   866: iastore
    //   867: dup
    //   868: bipush #47
    //   870: ldc -2147483648
    //   872: iastore
    //   873: dup
    //   874: bipush #48
    //   876: ldc 32800
    //   878: iastore
    //   879: dup
    //   880: bipush #49
    //   882: ldc -2146402304
    //   884: iastore
    //   885: dup
    //   886: bipush #50
    //   888: ldc 1048576
    //   890: iastore
    //   891: dup
    //   892: bipush #51
    //   894: ldc -2147483616
    //   896: iastore
    //   897: dup
    //   898: bipush #52
    //   900: ldc 1048608
    //   902: iastore
    //   903: dup
    //   904: bipush #53
    //   906: ldc -2147450848
    //   908: iastore
    //   909: dup
    //   910: bipush #54
    //   912: ldc -2147483616
    //   914: iastore
    //   915: dup
    //   916: bipush #55
    //   918: ldc 1048608
    //   920: iastore
    //   921: dup
    //   922: bipush #56
    //   924: ldc 1081344
    //   926: iastore
    //   927: dup
    //   928: bipush #57
    //   930: iconst_0
    //   931: iastore
    //   932: dup
    //   933: bipush #58
    //   935: ldc -2147450880
    //   937: iastore
    //   938: dup
    //   939: bipush #59
    //   941: ldc 32800
    //   943: iastore
    //   944: dup
    //   945: bipush #60
    //   947: ldc -2147483648
    //   949: iastore
    //   950: dup
    //   951: bipush #61
    //   953: ldc -2146435040
    //   955: iastore
    //   956: dup
    //   957: bipush #62
    //   959: ldc -2146402272
    //   961: iastore
    //   962: dup
    //   963: bipush #63
    //   965: ldc 1081344
    //   967: iastore
    //   968: astore #7
    //   970: bipush #64
    //   972: newarray int
    //   974: dup
    //   975: iconst_0
    //   976: sipush #520
    //   979: iastore
    //   980: dup
    //   981: iconst_1
    //   982: ldc 134349312
    //   984: iastore
    //   985: dup
    //   986: iconst_2
    //   987: iconst_0
    //   988: iastore
    //   989: dup
    //   990: iconst_3
    //   991: ldc 134348808
    //   993: iastore
    //   994: dup
    //   995: iconst_4
    //   996: ldc 134218240
    //   998: iastore
    //   999: dup
    //   1000: iconst_5
    //   1001: iconst_0
    //   1002: iastore
    //   1003: dup
    //   1004: bipush #6
    //   1006: ldc 131592
    //   1008: iastore
    //   1009: dup
    //   1010: bipush #7
    //   1012: ldc 134218240
    //   1014: iastore
    //   1015: dup
    //   1016: bipush #8
    //   1018: ldc 131080
    //   1020: iastore
    //   1021: dup
    //   1022: bipush #9
    //   1024: ldc 134217736
    //   1026: iastore
    //   1027: dup
    //   1028: bipush #10
    //   1030: ldc 134217736
    //   1032: iastore
    //   1033: dup
    //   1034: bipush #11
    //   1036: ldc 131072
    //   1038: iastore
    //   1039: dup
    //   1040: bipush #12
    //   1042: ldc 134349320
    //   1044: iastore
    //   1045: dup
    //   1046: bipush #13
    //   1048: ldc 131080
    //   1050: iastore
    //   1051: dup
    //   1052: bipush #14
    //   1054: ldc 134348800
    //   1056: iastore
    //   1057: dup
    //   1058: bipush #15
    //   1060: sipush #520
    //   1063: iastore
    //   1064: dup
    //   1065: bipush #16
    //   1067: ldc 134217728
    //   1069: iastore
    //   1070: dup
    //   1071: bipush #17
    //   1073: bipush #8
    //   1075: iastore
    //   1076: dup
    //   1077: bipush #18
    //   1079: ldc 134349312
    //   1081: iastore
    //   1082: dup
    //   1083: bipush #19
    //   1085: sipush #512
    //   1088: iastore
    //   1089: dup
    //   1090: bipush #20
    //   1092: ldc 131584
    //   1094: iastore
    //   1095: dup
    //   1096: bipush #21
    //   1098: ldc 134348800
    //   1100: iastore
    //   1101: dup
    //   1102: bipush #22
    //   1104: ldc 134348808
    //   1106: iastore
    //   1107: dup
    //   1108: bipush #23
    //   1110: ldc 131592
    //   1112: iastore
    //   1113: dup
    //   1114: bipush #24
    //   1116: ldc 134218248
    //   1118: iastore
    //   1119: dup
    //   1120: bipush #25
    //   1122: ldc 131584
    //   1124: iastore
    //   1125: dup
    //   1126: bipush #26
    //   1128: ldc 131072
    //   1130: iastore
    //   1131: dup
    //   1132: bipush #27
    //   1134: ldc 134218248
    //   1136: iastore
    //   1137: dup
    //   1138: bipush #28
    //   1140: bipush #8
    //   1142: iastore
    //   1143: dup
    //   1144: bipush #29
    //   1146: ldc 134349320
    //   1148: iastore
    //   1149: dup
    //   1150: bipush #30
    //   1152: sipush #512
    //   1155: iastore
    //   1156: dup
    //   1157: bipush #31
    //   1159: ldc 134217728
    //   1161: iastore
    //   1162: dup
    //   1163: bipush #32
    //   1165: ldc 134349312
    //   1167: iastore
    //   1168: dup
    //   1169: bipush #33
    //   1171: ldc 134217728
    //   1173: iastore
    //   1174: dup
    //   1175: bipush #34
    //   1177: ldc 131080
    //   1179: iastore
    //   1180: dup
    //   1181: bipush #35
    //   1183: sipush #520
    //   1186: iastore
    //   1187: dup
    //   1188: bipush #36
    //   1190: ldc 131072
    //   1192: iastore
    //   1193: dup
    //   1194: bipush #37
    //   1196: ldc 134349312
    //   1198: iastore
    //   1199: dup
    //   1200: bipush #38
    //   1202: ldc 134218240
    //   1204: iastore
    //   1205: dup
    //   1206: bipush #39
    //   1208: iconst_0
    //   1209: iastore
    //   1210: dup
    //   1211: bipush #40
    //   1213: sipush #512
    //   1216: iastore
    //   1217: dup
    //   1218: bipush #41
    //   1220: ldc 131080
    //   1222: iastore
    //   1223: dup
    //   1224: bipush #42
    //   1226: ldc 134349320
    //   1228: iastore
    //   1229: dup
    //   1230: bipush #43
    //   1232: ldc 134218240
    //   1234: iastore
    //   1235: dup
    //   1236: bipush #44
    //   1238: ldc 134217736
    //   1240: iastore
    //   1241: dup
    //   1242: bipush #45
    //   1244: sipush #512
    //   1247: iastore
    //   1248: dup
    //   1249: bipush #46
    //   1251: iconst_0
    //   1252: iastore
    //   1253: dup
    //   1254: bipush #47
    //   1256: ldc 134348808
    //   1258: iastore
    //   1259: dup
    //   1260: bipush #48
    //   1262: ldc 134218248
    //   1264: iastore
    //   1265: dup
    //   1266: bipush #49
    //   1268: ldc 131072
    //   1270: iastore
    //   1271: dup
    //   1272: bipush #50
    //   1274: ldc 134217728
    //   1276: iastore
    //   1277: dup
    //   1278: bipush #51
    //   1280: ldc 134349320
    //   1282: iastore
    //   1283: dup
    //   1284: bipush #52
    //   1286: bipush #8
    //   1288: iastore
    //   1289: dup
    //   1290: bipush #53
    //   1292: ldc 131592
    //   1294: iastore
    //   1295: dup
    //   1296: bipush #54
    //   1298: ldc 131584
    //   1300: iastore
    //   1301: dup
    //   1302: bipush #55
    //   1304: ldc 134217736
    //   1306: iastore
    //   1307: dup
    //   1308: bipush #56
    //   1310: ldc 134348800
    //   1312: iastore
    //   1313: dup
    //   1314: bipush #57
    //   1316: ldc 134218248
    //   1318: iastore
    //   1319: dup
    //   1320: bipush #58
    //   1322: sipush #520
    //   1325: iastore
    //   1326: dup
    //   1327: bipush #59
    //   1329: ldc 134348800
    //   1331: iastore
    //   1332: dup
    //   1333: bipush #60
    //   1335: ldc 131592
    //   1337: iastore
    //   1338: dup
    //   1339: bipush #61
    //   1341: bipush #8
    //   1343: iastore
    //   1344: dup
    //   1345: bipush #62
    //   1347: ldc 134348808
    //   1349: iastore
    //   1350: dup
    //   1351: bipush #63
    //   1353: ldc 131584
    //   1355: iastore
    //   1356: astore #8
    //   1358: bipush #64
    //   1360: newarray int
    //   1362: dup
    //   1363: iconst_0
    //   1364: ldc 8396801
    //   1366: iastore
    //   1367: dup
    //   1368: iconst_1
    //   1369: sipush #8321
    //   1372: iastore
    //   1373: dup
    //   1374: iconst_2
    //   1375: sipush #8321
    //   1378: iastore
    //   1379: dup
    //   1380: iconst_3
    //   1381: sipush #128
    //   1384: iastore
    //   1385: dup
    //   1386: iconst_4
    //   1387: ldc 8396928
    //   1389: iastore
    //   1390: dup
    //   1391: iconst_5
    //   1392: ldc 8388737
    //   1394: iastore
    //   1395: dup
    //   1396: bipush #6
    //   1398: ldc 8388609
    //   1400: iastore
    //   1401: dup
    //   1402: bipush #7
    //   1404: sipush #8193
    //   1407: iastore
    //   1408: dup
    //   1409: bipush #8
    //   1411: iconst_0
    //   1412: iastore
    //   1413: dup
    //   1414: bipush #9
    //   1416: ldc 8396800
    //   1418: iastore
    //   1419: dup
    //   1420: bipush #10
    //   1422: ldc 8396800
    //   1424: iastore
    //   1425: dup
    //   1426: bipush #11
    //   1428: ldc 8396929
    //   1430: iastore
    //   1431: dup
    //   1432: bipush #12
    //   1434: sipush #129
    //   1437: iastore
    //   1438: dup
    //   1439: bipush #13
    //   1441: iconst_0
    //   1442: iastore
    //   1443: dup
    //   1444: bipush #14
    //   1446: ldc 8388736
    //   1448: iastore
    //   1449: dup
    //   1450: bipush #15
    //   1452: ldc 8388609
    //   1454: iastore
    //   1455: dup
    //   1456: bipush #16
    //   1458: iconst_1
    //   1459: iastore
    //   1460: dup
    //   1461: bipush #17
    //   1463: sipush #8192
    //   1466: iastore
    //   1467: dup
    //   1468: bipush #18
    //   1470: ldc 8388608
    //   1472: iastore
    //   1473: dup
    //   1474: bipush #19
    //   1476: ldc 8396801
    //   1478: iastore
    //   1479: dup
    //   1480: bipush #20
    //   1482: sipush #128
    //   1485: iastore
    //   1486: dup
    //   1487: bipush #21
    //   1489: ldc 8388608
    //   1491: iastore
    //   1492: dup
    //   1493: bipush #22
    //   1495: sipush #8193
    //   1498: iastore
    //   1499: dup
    //   1500: bipush #23
    //   1502: sipush #8320
    //   1505: iastore
    //   1506: dup
    //   1507: bipush #24
    //   1509: ldc 8388737
    //   1511: iastore
    //   1512: dup
    //   1513: bipush #25
    //   1515: iconst_1
    //   1516: iastore
    //   1517: dup
    //   1518: bipush #26
    //   1520: sipush #8320
    //   1523: iastore
    //   1524: dup
    //   1525: bipush #27
    //   1527: ldc 8388736
    //   1529: iastore
    //   1530: dup
    //   1531: bipush #28
    //   1533: sipush #8192
    //   1536: iastore
    //   1537: dup
    //   1538: bipush #29
    //   1540: ldc 8396928
    //   1542: iastore
    //   1543: dup
    //   1544: bipush #30
    //   1546: ldc 8396929
    //   1548: iastore
    //   1549: dup
    //   1550: bipush #31
    //   1552: sipush #129
    //   1555: iastore
    //   1556: dup
    //   1557: bipush #32
    //   1559: ldc 8388736
    //   1561: iastore
    //   1562: dup
    //   1563: bipush #33
    //   1565: ldc 8388609
    //   1567: iastore
    //   1568: dup
    //   1569: bipush #34
    //   1571: ldc 8396800
    //   1573: iastore
    //   1574: dup
    //   1575: bipush #35
    //   1577: ldc 8396929
    //   1579: iastore
    //   1580: dup
    //   1581: bipush #36
    //   1583: sipush #129
    //   1586: iastore
    //   1587: dup
    //   1588: bipush #37
    //   1590: iconst_0
    //   1591: iastore
    //   1592: dup
    //   1593: bipush #38
    //   1595: iconst_0
    //   1596: iastore
    //   1597: dup
    //   1598: bipush #39
    //   1600: ldc 8396800
    //   1602: iastore
    //   1603: dup
    //   1604: bipush #40
    //   1606: sipush #8320
    //   1609: iastore
    //   1610: dup
    //   1611: bipush #41
    //   1613: ldc 8388736
    //   1615: iastore
    //   1616: dup
    //   1617: bipush #42
    //   1619: ldc 8388737
    //   1621: iastore
    //   1622: dup
    //   1623: bipush #43
    //   1625: iconst_1
    //   1626: iastore
    //   1627: dup
    //   1628: bipush #44
    //   1630: ldc 8396801
    //   1632: iastore
    //   1633: dup
    //   1634: bipush #45
    //   1636: sipush #8321
    //   1639: iastore
    //   1640: dup
    //   1641: bipush #46
    //   1643: sipush #8321
    //   1646: iastore
    //   1647: dup
    //   1648: bipush #47
    //   1650: sipush #128
    //   1653: iastore
    //   1654: dup
    //   1655: bipush #48
    //   1657: ldc 8396929
    //   1659: iastore
    //   1660: dup
    //   1661: bipush #49
    //   1663: sipush #129
    //   1666: iastore
    //   1667: dup
    //   1668: bipush #50
    //   1670: iconst_1
    //   1671: iastore
    //   1672: dup
    //   1673: bipush #51
    //   1675: sipush #8192
    //   1678: iastore
    //   1679: dup
    //   1680: bipush #52
    //   1682: ldc 8388609
    //   1684: iastore
    //   1685: dup
    //   1686: bipush #53
    //   1688: sipush #8193
    //   1691: iastore
    //   1692: dup
    //   1693: bipush #54
    //   1695: ldc 8396928
    //   1697: iastore
    //   1698: dup
    //   1699: bipush #55
    //   1701: ldc 8388737
    //   1703: iastore
    //   1704: dup
    //   1705: bipush #56
    //   1707: sipush #8193
    //   1710: iastore
    //   1711: dup
    //   1712: bipush #57
    //   1714: sipush #8320
    //   1717: iastore
    //   1718: dup
    //   1719: bipush #58
    //   1721: ldc 8388608
    //   1723: iastore
    //   1724: dup
    //   1725: bipush #59
    //   1727: ldc 8396801
    //   1729: iastore
    //   1730: dup
    //   1731: bipush #60
    //   1733: sipush #128
    //   1736: iastore
    //   1737: dup
    //   1738: bipush #61
    //   1740: ldc 8388608
    //   1742: iastore
    //   1743: dup
    //   1744: bipush #62
    //   1746: sipush #8192
    //   1749: iastore
    //   1750: dup
    //   1751: bipush #63
    //   1753: ldc 8396928
    //   1755: iastore
    //   1756: astore #9
    //   1758: bipush #64
    //   1760: newarray int
    //   1762: dup
    //   1763: iconst_0
    //   1764: sipush #256
    //   1767: iastore
    //   1768: dup
    //   1769: iconst_1
    //   1770: ldc 34078976
    //   1772: iastore
    //   1773: dup
    //   1774: iconst_2
    //   1775: ldc 34078720
    //   1777: iastore
    //   1778: dup
    //   1779: iconst_3
    //   1780: ldc 1107296512
    //   1782: iastore
    //   1783: dup
    //   1784: iconst_4
    //   1785: ldc 524288
    //   1787: iastore
    //   1788: dup
    //   1789: iconst_5
    //   1790: sipush #256
    //   1793: iastore
    //   1794: dup
    //   1795: bipush #6
    //   1797: ldc 1073741824
    //   1799: iastore
    //   1800: dup
    //   1801: bipush #7
    //   1803: ldc 34078720
    //   1805: iastore
    //   1806: dup
    //   1807: bipush #8
    //   1809: ldc 1074266368
    //   1811: iastore
    //   1812: dup
    //   1813: bipush #9
    //   1815: ldc 524288
    //   1817: iastore
    //   1818: dup
    //   1819: bipush #10
    //   1821: ldc 33554688
    //   1823: iastore
    //   1824: dup
    //   1825: bipush #11
    //   1827: ldc 1074266368
    //   1829: iastore
    //   1830: dup
    //   1831: bipush #12
    //   1833: ldc 1107296512
    //   1835: iastore
    //   1836: dup
    //   1837: bipush #13
    //   1839: ldc 1107820544
    //   1841: iastore
    //   1842: dup
    //   1843: bipush #14
    //   1845: ldc 524544
    //   1847: iastore
    //   1848: dup
    //   1849: bipush #15
    //   1851: ldc 1073741824
    //   1853: iastore
    //   1854: dup
    //   1855: bipush #16
    //   1857: ldc 33554432
    //   1859: iastore
    //   1860: dup
    //   1861: bipush #17
    //   1863: ldc 1074266112
    //   1865: iastore
    //   1866: dup
    //   1867: bipush #18
    //   1869: ldc 1074266112
    //   1871: iastore
    //   1872: dup
    //   1873: bipush #19
    //   1875: iconst_0
    //   1876: iastore
    //   1877: dup
    //   1878: bipush #20
    //   1880: ldc 1073742080
    //   1882: iastore
    //   1883: dup
    //   1884: bipush #21
    //   1886: ldc 1107820800
    //   1888: iastore
    //   1889: dup
    //   1890: bipush #22
    //   1892: ldc 1107820800
    //   1894: iastore
    //   1895: dup
    //   1896: bipush #23
    //   1898: ldc 33554688
    //   1900: iastore
    //   1901: dup
    //   1902: bipush #24
    //   1904: ldc 1107820544
    //   1906: iastore
    //   1907: dup
    //   1908: bipush #25
    //   1910: ldc 1073742080
    //   1912: iastore
    //   1913: dup
    //   1914: bipush #26
    //   1916: iconst_0
    //   1917: iastore
    //   1918: dup
    //   1919: bipush #27
    //   1921: ldc 1107296256
    //   1923: iastore
    //   1924: dup
    //   1925: bipush #28
    //   1927: ldc 34078976
    //   1929: iastore
    //   1930: dup
    //   1931: bipush #29
    //   1933: ldc 33554432
    //   1935: iastore
    //   1936: dup
    //   1937: bipush #30
    //   1939: ldc 1107296256
    //   1941: iastore
    //   1942: dup
    //   1943: bipush #31
    //   1945: ldc 524544
    //   1947: iastore
    //   1948: dup
    //   1949: bipush #32
    //   1951: ldc 524288
    //   1953: iastore
    //   1954: dup
    //   1955: bipush #33
    //   1957: ldc 1107296512
    //   1959: iastore
    //   1960: dup
    //   1961: bipush #34
    //   1963: sipush #256
    //   1966: iastore
    //   1967: dup
    //   1968: bipush #35
    //   1970: ldc 33554432
    //   1972: iastore
    //   1973: dup
    //   1974: bipush #36
    //   1976: ldc 1073741824
    //   1978: iastore
    //   1979: dup
    //   1980: bipush #37
    //   1982: ldc 34078720
    //   1984: iastore
    //   1985: dup
    //   1986: bipush #38
    //   1988: ldc 1107296512
    //   1990: iastore
    //   1991: dup
    //   1992: bipush #39
    //   1994: ldc 1074266368
    //   1996: iastore
    //   1997: dup
    //   1998: bipush #40
    //   2000: ldc 33554688
    //   2002: iastore
    //   2003: dup
    //   2004: bipush #41
    //   2006: ldc 1073741824
    //   2008: iastore
    //   2009: dup
    //   2010: bipush #42
    //   2012: ldc 1107820544
    //   2014: iastore
    //   2015: dup
    //   2016: bipush #43
    //   2018: ldc 34078976
    //   2020: iastore
    //   2021: dup
    //   2022: bipush #44
    //   2024: ldc 1074266368
    //   2026: iastore
    //   2027: dup
    //   2028: bipush #45
    //   2030: sipush #256
    //   2033: iastore
    //   2034: dup
    //   2035: bipush #46
    //   2037: ldc 33554432
    //   2039: iastore
    //   2040: dup
    //   2041: bipush #47
    //   2043: ldc 1107820544
    //   2045: iastore
    //   2046: dup
    //   2047: bipush #48
    //   2049: ldc 1107820800
    //   2051: iastore
    //   2052: dup
    //   2053: bipush #49
    //   2055: ldc 524544
    //   2057: iastore
    //   2058: dup
    //   2059: bipush #50
    //   2061: ldc 1107296256
    //   2063: iastore
    //   2064: dup
    //   2065: bipush #51
    //   2067: ldc 1107820800
    //   2069: iastore
    //   2070: dup
    //   2071: bipush #52
    //   2073: ldc 34078720
    //   2075: iastore
    //   2076: dup
    //   2077: bipush #53
    //   2079: iconst_0
    //   2080: iastore
    //   2081: dup
    //   2082: bipush #54
    //   2084: ldc 1074266112
    //   2086: iastore
    //   2087: dup
    //   2088: bipush #55
    //   2090: ldc 1107296256
    //   2092: iastore
    //   2093: dup
    //   2094: bipush #56
    //   2096: ldc 524544
    //   2098: iastore
    //   2099: dup
    //   2100: bipush #57
    //   2102: ldc 33554688
    //   2104: iastore
    //   2105: dup
    //   2106: bipush #58
    //   2108: ldc 1073742080
    //   2110: iastore
    //   2111: dup
    //   2112: bipush #59
    //   2114: ldc 524288
    //   2116: iastore
    //   2117: dup
    //   2118: bipush #60
    //   2120: iconst_0
    //   2121: iastore
    //   2122: dup
    //   2123: bipush #61
    //   2125: ldc 1074266112
    //   2127: iastore
    //   2128: dup
    //   2129: bipush #62
    //   2131: ldc 34078976
    //   2133: iastore
    //   2134: dup
    //   2135: bipush #63
    //   2137: ldc 1073742080
    //   2139: iastore
    //   2140: astore #10
    //   2142: bipush #64
    //   2144: newarray int
    //   2146: dup
    //   2147: iconst_0
    //   2148: ldc 536870928
    //   2150: iastore
    //   2151: dup
    //   2152: iconst_1
    //   2153: ldc 541065216
    //   2155: iastore
    //   2156: dup
    //   2157: iconst_2
    //   2158: sipush #16384
    //   2161: iastore
    //   2162: dup
    //   2163: iconst_3
    //   2164: ldc 541081616
    //   2166: iastore
    //   2167: dup
    //   2168: iconst_4
    //   2169: ldc 541065216
    //   2171: iastore
    //   2172: dup
    //   2173: iconst_5
    //   2174: bipush #16
    //   2176: iastore
    //   2177: dup
    //   2178: bipush #6
    //   2180: ldc 541081616
    //   2182: iastore
    //   2183: dup
    //   2184: bipush #7
    //   2186: ldc 4194304
    //   2188: iastore
    //   2189: dup
    //   2190: bipush #8
    //   2192: ldc 536887296
    //   2194: iastore
    //   2195: dup
    //   2196: bipush #9
    //   2198: ldc 4210704
    //   2200: iastore
    //   2201: dup
    //   2202: bipush #10
    //   2204: ldc 4194304
    //   2206: iastore
    //   2207: dup
    //   2208: bipush #11
    //   2210: ldc 536870928
    //   2212: iastore
    //   2213: dup
    //   2214: bipush #12
    //   2216: ldc 4194320
    //   2218: iastore
    //   2219: dup
    //   2220: bipush #13
    //   2222: ldc 536887296
    //   2224: iastore
    //   2225: dup
    //   2226: bipush #14
    //   2228: ldc 536870912
    //   2230: iastore
    //   2231: dup
    //   2232: bipush #15
    //   2234: sipush #16400
    //   2237: iastore
    //   2238: dup
    //   2239: bipush #16
    //   2241: iconst_0
    //   2242: iastore
    //   2243: dup
    //   2244: bipush #17
    //   2246: ldc 4194320
    //   2248: iastore
    //   2249: dup
    //   2250: bipush #18
    //   2252: ldc 536887312
    //   2254: iastore
    //   2255: dup
    //   2256: bipush #19
    //   2258: sipush #16384
    //   2261: iastore
    //   2262: dup
    //   2263: bipush #20
    //   2265: ldc 4210688
    //   2267: iastore
    //   2268: dup
    //   2269: bipush #21
    //   2271: ldc 536887312
    //   2273: iastore
    //   2274: dup
    //   2275: bipush #22
    //   2277: bipush #16
    //   2279: iastore
    //   2280: dup
    //   2281: bipush #23
    //   2283: ldc 541065232
    //   2285: iastore
    //   2286: dup
    //   2287: bipush #24
    //   2289: ldc 541065232
    //   2291: iastore
    //   2292: dup
    //   2293: bipush #25
    //   2295: iconst_0
    //   2296: iastore
    //   2297: dup
    //   2298: bipush #26
    //   2300: ldc 4210704
    //   2302: iastore
    //   2303: dup
    //   2304: bipush #27
    //   2306: ldc 541081600
    //   2308: iastore
    //   2309: dup
    //   2310: bipush #28
    //   2312: sipush #16400
    //   2315: iastore
    //   2316: dup
    //   2317: bipush #29
    //   2319: ldc 4210688
    //   2321: iastore
    //   2322: dup
    //   2323: bipush #30
    //   2325: ldc 541081600
    //   2327: iastore
    //   2328: dup
    //   2329: bipush #31
    //   2331: ldc 536870912
    //   2333: iastore
    //   2334: dup
    //   2335: bipush #32
    //   2337: ldc 536887296
    //   2339: iastore
    //   2340: dup
    //   2341: bipush #33
    //   2343: bipush #16
    //   2345: iastore
    //   2346: dup
    //   2347: bipush #34
    //   2349: ldc 541065232
    //   2351: iastore
    //   2352: dup
    //   2353: bipush #35
    //   2355: ldc 4210688
    //   2357: iastore
    //   2358: dup
    //   2359: bipush #36
    //   2361: ldc 541081616
    //   2363: iastore
    //   2364: dup
    //   2365: bipush #37
    //   2367: ldc 4194304
    //   2369: iastore
    //   2370: dup
    //   2371: bipush #38
    //   2373: sipush #16400
    //   2376: iastore
    //   2377: dup
    //   2378: bipush #39
    //   2380: ldc 536870928
    //   2382: iastore
    //   2383: dup
    //   2384: bipush #40
    //   2386: ldc 4194304
    //   2388: iastore
    //   2389: dup
    //   2390: bipush #41
    //   2392: ldc 536887296
    //   2394: iastore
    //   2395: dup
    //   2396: bipush #42
    //   2398: ldc 536870912
    //   2400: iastore
    //   2401: dup
    //   2402: bipush #43
    //   2404: sipush #16400
    //   2407: iastore
    //   2408: dup
    //   2409: bipush #44
    //   2411: ldc 536870928
    //   2413: iastore
    //   2414: dup
    //   2415: bipush #45
    //   2417: ldc 541081616
    //   2419: iastore
    //   2420: dup
    //   2421: bipush #46
    //   2423: ldc 4210688
    //   2425: iastore
    //   2426: dup
    //   2427: bipush #47
    //   2429: ldc 541065216
    //   2431: iastore
    //   2432: dup
    //   2433: bipush #48
    //   2435: ldc 4210704
    //   2437: iastore
    //   2438: dup
    //   2439: bipush #49
    //   2441: ldc 541081600
    //   2443: iastore
    //   2444: dup
    //   2445: bipush #50
    //   2447: iconst_0
    //   2448: iastore
    //   2449: dup
    //   2450: bipush #51
    //   2452: ldc 541065232
    //   2454: iastore
    //   2455: dup
    //   2456: bipush #52
    //   2458: bipush #16
    //   2460: iastore
    //   2461: dup
    //   2462: bipush #53
    //   2464: sipush #16384
    //   2467: iastore
    //   2468: dup
    //   2469: bipush #54
    //   2471: ldc 541065216
    //   2473: iastore
    //   2474: dup
    //   2475: bipush #55
    //   2477: ldc 4210704
    //   2479: iastore
    //   2480: dup
    //   2481: bipush #56
    //   2483: sipush #16384
    //   2486: iastore
    //   2487: dup
    //   2488: bipush #57
    //   2490: ldc 4194320
    //   2492: iastore
    //   2493: dup
    //   2494: bipush #58
    //   2496: ldc 536887312
    //   2498: iastore
    //   2499: dup
    //   2500: bipush #59
    //   2502: iconst_0
    //   2503: iastore
    //   2504: dup
    //   2505: bipush #60
    //   2507: ldc 541081600
    //   2509: iastore
    //   2510: dup
    //   2511: bipush #61
    //   2513: ldc 536870912
    //   2515: iastore
    //   2516: dup
    //   2517: bipush #62
    //   2519: ldc 4194320
    //   2521: iastore
    //   2522: dup
    //   2523: bipush #63
    //   2525: ldc 536887312
    //   2527: iastore
    //   2528: astore #11
    //   2530: bipush #64
    //   2532: newarray int
    //   2534: dup
    //   2535: iconst_0
    //   2536: ldc 2097152
    //   2538: iastore
    //   2539: dup
    //   2540: iconst_1
    //   2541: ldc 69206018
    //   2543: iastore
    //   2544: dup
    //   2545: iconst_2
    //   2546: ldc 67110914
    //   2548: iastore
    //   2549: dup
    //   2550: iconst_3
    //   2551: iconst_0
    //   2552: iastore
    //   2553: dup
    //   2554: iconst_4
    //   2555: sipush #2048
    //   2558: iastore
    //   2559: dup
    //   2560: iconst_5
    //   2561: ldc 67110914
    //   2563: iastore
    //   2564: dup
    //   2565: bipush #6
    //   2567: ldc 2099202
    //   2569: iastore
    //   2570: dup
    //   2571: bipush #7
    //   2573: ldc 69208064
    //   2575: iastore
    //   2576: dup
    //   2577: bipush #8
    //   2579: ldc 69208066
    //   2581: iastore
    //   2582: dup
    //   2583: bipush #9
    //   2585: ldc 2097152
    //   2587: iastore
    //   2588: dup
    //   2589: bipush #10
    //   2591: iconst_0
    //   2592: iastore
    //   2593: dup
    //   2594: bipush #11
    //   2596: ldc 67108866
    //   2598: iastore
    //   2599: dup
    //   2600: bipush #12
    //   2602: iconst_2
    //   2603: iastore
    //   2604: dup
    //   2605: bipush #13
    //   2607: ldc 67108864
    //   2609: iastore
    //   2610: dup
    //   2611: bipush #14
    //   2613: ldc 69206018
    //   2615: iastore
    //   2616: dup
    //   2617: bipush #15
    //   2619: sipush #2050
    //   2622: iastore
    //   2623: dup
    //   2624: bipush #16
    //   2626: ldc 67110912
    //   2628: iastore
    //   2629: dup
    //   2630: bipush #17
    //   2632: ldc 2099202
    //   2634: iastore
    //   2635: dup
    //   2636: bipush #18
    //   2638: ldc 2097154
    //   2640: iastore
    //   2641: dup
    //   2642: bipush #19
    //   2644: ldc 67110912
    //   2646: iastore
    //   2647: dup
    //   2648: bipush #20
    //   2650: ldc 67108866
    //   2652: iastore
    //   2653: dup
    //   2654: bipush #21
    //   2656: ldc 69206016
    //   2658: iastore
    //   2659: dup
    //   2660: bipush #22
    //   2662: ldc 69208064
    //   2664: iastore
    //   2665: dup
    //   2666: bipush #23
    //   2668: ldc 2097154
    //   2670: iastore
    //   2671: dup
    //   2672: bipush #24
    //   2674: ldc 69206016
    //   2676: iastore
    //   2677: dup
    //   2678: bipush #25
    //   2680: sipush #2048
    //   2683: iastore
    //   2684: dup
    //   2685: bipush #26
    //   2687: sipush #2050
    //   2690: iastore
    //   2691: dup
    //   2692: bipush #27
    //   2694: ldc 69208066
    //   2696: iastore
    //   2697: dup
    //   2698: bipush #28
    //   2700: ldc 2099200
    //   2702: iastore
    //   2703: dup
    //   2704: bipush #29
    //   2706: iconst_2
    //   2707: iastore
    //   2708: dup
    //   2709: bipush #30
    //   2711: ldc 67108864
    //   2713: iastore
    //   2714: dup
    //   2715: bipush #31
    //   2717: ldc 2099200
    //   2719: iastore
    //   2720: dup
    //   2721: bipush #32
    //   2723: ldc 67108864
    //   2725: iastore
    //   2726: dup
    //   2727: bipush #33
    //   2729: ldc 2099200
    //   2731: iastore
    //   2732: dup
    //   2733: bipush #34
    //   2735: ldc 2097152
    //   2737: iastore
    //   2738: dup
    //   2739: bipush #35
    //   2741: ldc 67110914
    //   2743: iastore
    //   2744: dup
    //   2745: bipush #36
    //   2747: ldc 67110914
    //   2749: iastore
    //   2750: dup
    //   2751: bipush #37
    //   2753: ldc 69206018
    //   2755: iastore
    //   2756: dup
    //   2757: bipush #38
    //   2759: ldc 69206018
    //   2761: iastore
    //   2762: dup
    //   2763: bipush #39
    //   2765: iconst_2
    //   2766: iastore
    //   2767: dup
    //   2768: bipush #40
    //   2770: ldc 2097154
    //   2772: iastore
    //   2773: dup
    //   2774: bipush #41
    //   2776: ldc 67108864
    //   2778: iastore
    //   2779: dup
    //   2780: bipush #42
    //   2782: ldc 67110912
    //   2784: iastore
    //   2785: dup
    //   2786: bipush #43
    //   2788: ldc 2097152
    //   2790: iastore
    //   2791: dup
    //   2792: bipush #44
    //   2794: ldc 69208064
    //   2796: iastore
    //   2797: dup
    //   2798: bipush #45
    //   2800: sipush #2050
    //   2803: iastore
    //   2804: dup
    //   2805: bipush #46
    //   2807: ldc 2099202
    //   2809: iastore
    //   2810: dup
    //   2811: bipush #47
    //   2813: ldc 69208064
    //   2815: iastore
    //   2816: dup
    //   2817: bipush #48
    //   2819: sipush #2050
    //   2822: iastore
    //   2823: dup
    //   2824: bipush #49
    //   2826: ldc 67108866
    //   2828: iastore
    //   2829: dup
    //   2830: bipush #50
    //   2832: ldc 69208066
    //   2834: iastore
    //   2835: dup
    //   2836: bipush #51
    //   2838: ldc 69206016
    //   2840: iastore
    //   2841: dup
    //   2842: bipush #52
    //   2844: ldc 2099200
    //   2846: iastore
    //   2847: dup
    //   2848: bipush #53
    //   2850: iconst_0
    //   2851: iastore
    //   2852: dup
    //   2853: bipush #54
    //   2855: iconst_2
    //   2856: iastore
    //   2857: dup
    //   2858: bipush #55
    //   2860: ldc 69208066
    //   2862: iastore
    //   2863: dup
    //   2864: bipush #56
    //   2866: iconst_0
    //   2867: iastore
    //   2868: dup
    //   2869: bipush #57
    //   2871: ldc 2099202
    //   2873: iastore
    //   2874: dup
    //   2875: bipush #58
    //   2877: ldc 69206016
    //   2879: iastore
    //   2880: dup
    //   2881: bipush #59
    //   2883: sipush #2048
    //   2886: iastore
    //   2887: dup
    //   2888: bipush #60
    //   2890: ldc 67108866
    //   2892: iastore
    //   2893: dup
    //   2894: bipush #61
    //   2896: ldc 67110912
    //   2898: iastore
    //   2899: dup
    //   2900: bipush #62
    //   2902: sipush #2048
    //   2905: iastore
    //   2906: dup
    //   2907: bipush #63
    //   2909: ldc 2097154
    //   2911: iastore
    //   2912: astore #12
    //   2914: bipush #64
    //   2916: newarray int
    //   2918: dup
    //   2919: iconst_0
    //   2920: ldc 268439616
    //   2922: iastore
    //   2923: dup
    //   2924: iconst_1
    //   2925: sipush #4096
    //   2928: iastore
    //   2929: dup
    //   2930: iconst_2
    //   2931: ldc 262144
    //   2933: iastore
    //   2934: dup
    //   2935: iconst_3
    //   2936: ldc 268701760
    //   2938: iastore
    //   2939: dup
    //   2940: iconst_4
    //   2941: ldc 268435456
    //   2943: iastore
    //   2944: dup
    //   2945: iconst_5
    //   2946: ldc 268439616
    //   2948: iastore
    //   2949: dup
    //   2950: bipush #6
    //   2952: bipush #64
    //   2954: iastore
    //   2955: dup
    //   2956: bipush #7
    //   2958: ldc 268435456
    //   2960: iastore
    //   2961: dup
    //   2962: bipush #8
    //   2964: ldc 262208
    //   2966: iastore
    //   2967: dup
    //   2968: bipush #9
    //   2970: ldc 268697600
    //   2972: iastore
    //   2973: dup
    //   2974: bipush #10
    //   2976: ldc 268701760
    //   2978: iastore
    //   2979: dup
    //   2980: bipush #11
    //   2982: ldc 266240
    //   2984: iastore
    //   2985: dup
    //   2986: bipush #12
    //   2988: ldc 268701696
    //   2990: iastore
    //   2991: dup
    //   2992: bipush #13
    //   2994: ldc 266304
    //   2996: iastore
    //   2997: dup
    //   2998: bipush #14
    //   3000: sipush #4096
    //   3003: iastore
    //   3004: dup
    //   3005: bipush #15
    //   3007: bipush #64
    //   3009: iastore
    //   3010: dup
    //   3011: bipush #16
    //   3013: ldc 268697600
    //   3015: iastore
    //   3016: dup
    //   3017: bipush #17
    //   3019: ldc 268435520
    //   3021: iastore
    //   3022: dup
    //   3023: bipush #18
    //   3025: ldc 268439552
    //   3027: iastore
    //   3028: dup
    //   3029: bipush #19
    //   3031: sipush #4160
    //   3034: iastore
    //   3035: dup
    //   3036: bipush #20
    //   3038: ldc 266240
    //   3040: iastore
    //   3041: dup
    //   3042: bipush #21
    //   3044: ldc 262208
    //   3046: iastore
    //   3047: dup
    //   3048: bipush #22
    //   3050: ldc 268697664
    //   3052: iastore
    //   3053: dup
    //   3054: bipush #23
    //   3056: ldc 268701696
    //   3058: iastore
    //   3059: dup
    //   3060: bipush #24
    //   3062: sipush #4160
    //   3065: iastore
    //   3066: dup
    //   3067: bipush #25
    //   3069: iconst_0
    //   3070: iastore
    //   3071: dup
    //   3072: bipush #26
    //   3074: iconst_0
    //   3075: iastore
    //   3076: dup
    //   3077: bipush #27
    //   3079: ldc 268697664
    //   3081: iastore
    //   3082: dup
    //   3083: bipush #28
    //   3085: ldc 268435520
    //   3087: iastore
    //   3088: dup
    //   3089: bipush #29
    //   3091: ldc 268439552
    //   3093: iastore
    //   3094: dup
    //   3095: bipush #30
    //   3097: ldc 266304
    //   3099: iastore
    //   3100: dup
    //   3101: bipush #31
    //   3103: ldc 262144
    //   3105: iastore
    //   3106: dup
    //   3107: bipush #32
    //   3109: ldc 266304
    //   3111: iastore
    //   3112: dup
    //   3113: bipush #33
    //   3115: ldc 262144
    //   3117: iastore
    //   3118: dup
    //   3119: bipush #34
    //   3121: ldc 268701696
    //   3123: iastore
    //   3124: dup
    //   3125: bipush #35
    //   3127: sipush #4096
    //   3130: iastore
    //   3131: dup
    //   3132: bipush #36
    //   3134: bipush #64
    //   3136: iastore
    //   3137: dup
    //   3138: bipush #37
    //   3140: ldc 268697664
    //   3142: iastore
    //   3143: dup
    //   3144: bipush #38
    //   3146: sipush #4096
    //   3149: iastore
    //   3150: dup
    //   3151: bipush #39
    //   3153: ldc 266304
    //   3155: iastore
    //   3156: dup
    //   3157: bipush #40
    //   3159: ldc 268439552
    //   3161: iastore
    //   3162: dup
    //   3163: bipush #41
    //   3165: bipush #64
    //   3167: iastore
    //   3168: dup
    //   3169: bipush #42
    //   3171: ldc 268435520
    //   3173: iastore
    //   3174: dup
    //   3175: bipush #43
    //   3177: ldc 268697600
    //   3179: iastore
    //   3180: dup
    //   3181: bipush #44
    //   3183: ldc 268697664
    //   3185: iastore
    //   3186: dup
    //   3187: bipush #45
    //   3189: ldc 268435456
    //   3191: iastore
    //   3192: dup
    //   3193: bipush #46
    //   3195: ldc 262144
    //   3197: iastore
    //   3198: dup
    //   3199: bipush #47
    //   3201: ldc 268439616
    //   3203: iastore
    //   3204: dup
    //   3205: bipush #48
    //   3207: iconst_0
    //   3208: iastore
    //   3209: dup
    //   3210: bipush #49
    //   3212: ldc 268701760
    //   3214: iastore
    //   3215: dup
    //   3216: bipush #50
    //   3218: ldc 262208
    //   3220: iastore
    //   3221: dup
    //   3222: bipush #51
    //   3224: ldc 268435520
    //   3226: iastore
    //   3227: dup
    //   3228: bipush #52
    //   3230: ldc 268697600
    //   3232: iastore
    //   3233: dup
    //   3234: bipush #53
    //   3236: ldc 268439552
    //   3238: iastore
    //   3239: dup
    //   3240: bipush #54
    //   3242: ldc 268439616
    //   3244: iastore
    //   3245: dup
    //   3246: bipush #55
    //   3248: iconst_0
    //   3249: iastore
    //   3250: dup
    //   3251: bipush #56
    //   3253: ldc 268701760
    //   3255: iastore
    //   3256: dup
    //   3257: bipush #57
    //   3259: ldc 266240
    //   3261: iastore
    //   3262: dup
    //   3263: bipush #58
    //   3265: ldc 266240
    //   3267: iastore
    //   3268: dup
    //   3269: bipush #59
    //   3271: sipush #4160
    //   3274: iastore
    //   3275: dup
    //   3276: bipush #60
    //   3278: sipush #4160
    //   3281: iastore
    //   3282: dup
    //   3283: bipush #61
    //   3285: ldc 262208
    //   3287: iastore
    //   3288: dup
    //   3289: bipush #62
    //   3291: ldc 268435456
    //   3293: iastore
    //   3294: dup
    //   3295: bipush #63
    //   3297: ldc 268701696
    //   3299: iastore
    //   3300: astore #13
    //   3302: aload_3
    //   3303: arraylength
    //   3304: istore #14
    //   3306: iload #14
    //   3308: bipush #8
    //   3310: irem
    //   3311: ifeq -> 3335
    //   3314: new java/lang/Exception
    //   3317: dup
    //   3318: sipush #-5391
    //   3321: sipush #-19131
    //   3324: invokestatic a : (II)Ljava/lang/String;
    //   3327: invokespecial <init> : (Ljava/lang/String;)V
    //   3330: athrow
    //   3331: invokestatic a : (Ljava/lang/Throwable;)Ljava/lang/Throwable;
    //   3334: athrow
    //   3335: iconst_2
    //   3336: newarray int
    //   3338: astore #15
    //   3340: iload #14
    //   3342: newarray byte
    //   3344: astore #16
    //   3346: iload #14
    //   3348: bipush #8
    //   3350: idiv
    //   3351: istore #17
    //   3353: iconst_0
    //   3354: istore #18
    //   3356: iload #18
    //   3358: iload #17
    //   3360: if_icmpge -> 4274
    //   3363: iload #18
    //   3365: bipush #8
    //   3367: imul
    //   3368: istore #19
    //   3370: iconst_0
    //   3371: istore #20
    //   3373: iload #20
    //   3375: iconst_2
    //   3376: if_icmpge -> 3461
    //   3379: aload #15
    //   3381: iload #20
    //   3383: aload_3
    //   3384: iload #19
    //   3386: iload #20
    //   3388: iconst_4
    //   3389: imul
    //   3390: iadd
    //   3391: baload
    //   3392: sipush #255
    //   3395: iand
    //   3396: bipush #24
    //   3398: ishl
    //   3399: aload_3
    //   3400: iload #19
    //   3402: iload #20
    //   3404: iconst_4
    //   3405: imul
    //   3406: iadd
    //   3407: iconst_1
    //   3408: iadd
    //   3409: baload
    //   3410: sipush #255
    //   3413: iand
    //   3414: bipush #16
    //   3416: ishl
    //   3417: ior
    //   3418: aload_3
    //   3419: iload #19
    //   3421: iload #20
    //   3423: iconst_4
    //   3424: imul
    //   3425: iadd
    //   3426: iconst_2
    //   3427: iadd
    //   3428: baload
    //   3429: sipush #255
    //   3432: iand
    //   3433: bipush #8
    //   3435: ishl
    //   3436: ior
    //   3437: aload_3
    //   3438: iload #19
    //   3440: iload #20
    //   3442: iconst_4
    //   3443: imul
    //   3444: iadd
    //   3445: iconst_3
    //   3446: iadd
    //   3447: baload
    //   3448: sipush #255
    //   3451: iand
    //   3452: ior
    //   3453: iastore
    //   3454: iinc #20, 1
    //   3457: iload_2
    //   3458: ifne -> 3373
    //   3461: iconst_0
    //   3462: istore #25
    //   3464: aload #15
    //   3466: iconst_0
    //   3467: iaload
    //   3468: istore #23
    //   3470: aload #15
    //   3472: iconst_1
    //   3473: iaload
    //   3474: istore #22
    //   3476: iload #23
    //   3478: iconst_4
    //   3479: iushr
    //   3480: iload #22
    //   3482: ixor
    //   3483: ldc 252645135
    //   3485: iand
    //   3486: istore #21
    //   3488: iload #22
    //   3490: iload #21
    //   3492: ixor
    //   3493: istore #22
    //   3495: iload #23
    //   3497: iload #21
    //   3499: iconst_4
    //   3500: ishl
    //   3501: ixor
    //   3502: istore #23
    //   3504: iload #23
    //   3506: bipush #16
    //   3508: iushr
    //   3509: iload #22
    //   3511: ixor
    //   3512: ldc 65535
    //   3514: iand
    //   3515: istore #21
    //   3517: iload #22
    //   3519: iload #21
    //   3521: ixor
    //   3522: istore #22
    //   3524: iload #23
    //   3526: iload #21
    //   3528: bipush #16
    //   3530: ishl
    //   3531: ixor
    //   3532: istore #23
    //   3534: iload #22
    //   3536: iconst_2
    //   3537: iushr
    //   3538: iload #23
    //   3540: ixor
    //   3541: ldc 858993459
    //   3543: iand
    //   3544: istore #21
    //   3546: iload #23
    //   3548: iload #21
    //   3550: ixor
    //   3551: istore #23
    //   3553: iload #22
    //   3555: iload #21
    //   3557: iconst_2
    //   3558: ishl
    //   3559: ixor
    //   3560: istore #22
    //   3562: iload #22
    //   3564: bipush #8
    //   3566: iushr
    //   3567: iload #23
    //   3569: ixor
    //   3570: ldc 16711935
    //   3572: iand
    //   3573: istore #21
    //   3575: iload #23
    //   3577: iload #21
    //   3579: ixor
    //   3580: istore #23
    //   3582: iload #22
    //   3584: iload #21
    //   3586: bipush #8
    //   3588: ishl
    //   3589: ixor
    //   3590: istore #22
    //   3592: iload #22
    //   3594: iconst_1
    //   3595: ishl
    //   3596: iload #22
    //   3598: bipush #31
    //   3600: iushr
    //   3601: iconst_1
    //   3602: iand
    //   3603: ior
    //   3604: istore #22
    //   3606: iload #23
    //   3608: iload #22
    //   3610: ixor
    //   3611: ldc -1431655766
    //   3613: iand
    //   3614: istore #21
    //   3616: iload #23
    //   3618: iload #21
    //   3620: ixor
    //   3621: istore #23
    //   3623: iload #22
    //   3625: iload #21
    //   3627: ixor
    //   3628: istore #22
    //   3630: iload #23
    //   3632: iconst_1
    //   3633: ishl
    //   3634: iload #23
    //   3636: bipush #31
    //   3638: iushr
    //   3639: iconst_1
    //   3640: iand
    //   3641: ior
    //   3642: istore #23
    //   3644: iconst_0
    //   3645: istore #24
    //   3647: iload #24
    //   3649: bipush #8
    //   3651: if_icmpge -> 3989
    //   3654: iload #22
    //   3656: bipush #28
    //   3658: ishl
    //   3659: iload #22
    //   3661: iconst_4
    //   3662: iushr
    //   3663: ior
    //   3664: istore #21
    //   3666: iload #21
    //   3668: aload #5
    //   3670: iload #25
    //   3672: iinc #25, 1
    //   3675: iaload
    //   3676: ixor
    //   3677: istore #21
    //   3679: aload #12
    //   3681: iload #21
    //   3683: bipush #63
    //   3685: iand
    //   3686: iaload
    //   3687: istore #20
    //   3689: iload #20
    //   3691: aload #10
    //   3693: iload #21
    //   3695: bipush #8
    //   3697: iushr
    //   3698: bipush #63
    //   3700: iand
    //   3701: iaload
    //   3702: ior
    //   3703: istore #20
    //   3705: iload #20
    //   3707: aload #8
    //   3709: iload #21
    //   3711: bipush #16
    //   3713: iushr
    //   3714: bipush #63
    //   3716: iand
    //   3717: iaload
    //   3718: ior
    //   3719: istore #20
    //   3721: iload #20
    //   3723: aload #6
    //   3725: iload #21
    //   3727: bipush #24
    //   3729: iushr
    //   3730: bipush #63
    //   3732: iand
    //   3733: iaload
    //   3734: ior
    //   3735: istore #20
    //   3737: iload #22
    //   3739: aload #5
    //   3741: iload #25
    //   3743: iinc #25, 1
    //   3746: iaload
    //   3747: ixor
    //   3748: istore #21
    //   3750: iload #20
    //   3752: aload #13
    //   3754: iload #21
    //   3756: bipush #63
    //   3758: iand
    //   3759: iaload
    //   3760: ior
    //   3761: istore #20
    //   3763: iload #20
    //   3765: aload #11
    //   3767: iload #21
    //   3769: bipush #8
    //   3771: iushr
    //   3772: bipush #63
    //   3774: iand
    //   3775: iaload
    //   3776: ior
    //   3777: istore #20
    //   3779: iload #20
    //   3781: aload #9
    //   3783: iload #21
    //   3785: bipush #16
    //   3787: iushr
    //   3788: bipush #63
    //   3790: iand
    //   3791: iaload
    //   3792: ior
    //   3793: istore #20
    //   3795: iload #20
    //   3797: aload #7
    //   3799: iload #21
    //   3801: bipush #24
    //   3803: iushr
    //   3804: bipush #63
    //   3806: iand
    //   3807: iaload
    //   3808: ior
    //   3809: istore #20
    //   3811: iload #23
    //   3813: iload #20
    //   3815: ixor
    //   3816: istore #23
    //   3818: iload #23
    //   3820: bipush #28
    //   3822: ishl
    //   3823: iload #23
    //   3825: iconst_4
    //   3826: iushr
    //   3827: ior
    //   3828: istore #21
    //   3830: iload #21
    //   3832: aload #5
    //   3834: iload #25
    //   3836: iinc #25, 1
    //   3839: iaload
    //   3840: ixor
    //   3841: istore #21
    //   3843: aload #12
    //   3845: iload #21
    //   3847: bipush #63
    //   3849: iand
    //   3850: iaload
    //   3851: istore #20
    //   3853: iload #20
    //   3855: aload #10
    //   3857: iload #21
    //   3859: bipush #8
    //   3861: iushr
    //   3862: bipush #63
    //   3864: iand
    //   3865: iaload
    //   3866: ior
    //   3867: istore #20
    //   3869: iload #20
    //   3871: aload #8
    //   3873: iload #21
    //   3875: bipush #16
    //   3877: iushr
    //   3878: bipush #63
    //   3880: iand
    //   3881: iaload
    //   3882: ior
    //   3883: istore #20
    //   3885: iload #20
    //   3887: aload #6
    //   3889: iload #21
    //   3891: bipush #24
    //   3893: iushr
    //   3894: bipush #63
    //   3896: iand
    //   3897: iaload
    //   3898: ior
    //   3899: istore #20
    //   3901: iload #23
    //   3903: aload #5
    //   3905: iload #25
    //   3907: iinc #25, 1
    //   3910: iaload
    //   3911: ixor
    //   3912: istore #21
    //   3914: iload #20
    //   3916: aload #13
    //   3918: iload #21
    //   3920: bipush #63
    //   3922: iand
    //   3923: iaload
    //   3924: ior
    //   3925: istore #20
    //   3927: iload #20
    //   3929: aload #11
    //   3931: iload #21
    //   3933: bipush #8
    //   3935: iushr
    //   3936: bipush #63
    //   3938: iand
    //   3939: iaload
    //   3940: ior
    //   3941: istore #20
    //   3943: iload #20
    //   3945: aload #9
    //   3947: iload #21
    //   3949: bipush #16
    //   3951: iushr
    //   3952: bipush #63
    //   3954: iand
    //   3955: iaload
    //   3956: ior
    //   3957: istore #20
    //   3959: iload #20
    //   3961: aload #7
    //   3963: iload #21
    //   3965: bipush #24
    //   3967: iushr
    //   3968: bipush #63
    //   3970: iand
    //   3971: iaload
    //   3972: ior
    //   3973: istore #20
    //   3975: iload #22
    //   3977: iload #20
    //   3979: ixor
    //   3980: istore #22
    //   3982: iinc #24, 1
    //   3985: iload_2
    //   3986: ifne -> 3647
    //   3989: iload #22
    //   3991: bipush #31
    //   3993: ishl
    //   3994: iload #22
    //   3996: iconst_1
    //   3997: iushr
    //   3998: ior
    //   3999: istore #22
    //   4001: iload #23
    //   4003: iload #22
    //   4005: ixor
    //   4006: ldc -1431655766
    //   4008: iand
    //   4009: istore #21
    //   4011: iload #23
    //   4013: iload #21
    //   4015: ixor
    //   4016: istore #23
    //   4018: iload #22
    //   4020: iload #21
    //   4022: ixor
    //   4023: istore #22
    //   4025: iload #23
    //   4027: bipush #31
    //   4029: ishl
    //   4030: iload #23
    //   4032: iconst_1
    //   4033: iushr
    //   4034: ior
    //   4035: istore #23
    //   4037: iload #23
    //   4039: bipush #8
    //   4041: iushr
    //   4042: iload #22
    //   4044: ixor
    //   4045: ldc 16711935
    //   4047: iand
    //   4048: istore #21
    //   4050: iload #22
    //   4052: iload #21
    //   4054: ixor
    //   4055: istore #22
    //   4057: iload #23
    //   4059: iload #21
    //   4061: bipush #8
    //   4063: ishl
    //   4064: ixor
    //   4065: istore #23
    //   4067: iload #23
    //   4069: iconst_2
    //   4070: iushr
    //   4071: iload #22
    //   4073: ixor
    //   4074: ldc 858993459
    //   4076: iand
    //   4077: istore #21
    //   4079: iload #22
    //   4081: iload #21
    //   4083: ixor
    //   4084: istore #22
    //   4086: iload #23
    //   4088: iload #21
    //   4090: iconst_2
    //   4091: ishl
    //   4092: ixor
    //   4093: istore #23
    //   4095: iload #22
    //   4097: bipush #16
    //   4099: iushr
    //   4100: iload #23
    //   4102: ixor
    //   4103: ldc 65535
    //   4105: iand
    //   4106: istore #21
    //   4108: iload #23
    //   4110: iload #21
    //   4112: ixor
    //   4113: istore #23
    //   4115: iload #22
    //   4117: iload #21
    //   4119: bipush #16
    //   4121: ishl
    //   4122: ixor
    //   4123: istore #22
    //   4125: iload #22
    //   4127: iconst_4
    //   4128: iushr
    //   4129: iload #23
    //   4131: ixor
    //   4132: ldc 252645135
    //   4134: iand
    //   4135: istore #21
    //   4137: iload #23
    //   4139: iload #21
    //   4141: ixor
    //   4142: istore #23
    //   4144: iload #22
    //   4146: iload #21
    //   4148: iconst_4
    //   4149: ishl
    //   4150: ixor
    //   4151: istore #22
    //   4153: aload #15
    //   4155: iconst_0
    //   4156: iload #22
    //   4158: iastore
    //   4159: aload #15
    //   4161: iconst_1
    //   4162: iload #23
    //   4164: iastore
    //   4165: iload #18
    //   4167: bipush #8
    //   4169: imul
    //   4170: istore #26
    //   4172: iconst_0
    //   4173: istore #27
    //   4175: iload #27
    //   4177: iconst_2
    //   4178: if_icmpge -> 4267
    //   4181: aload #16
    //   4183: iload #26
    //   4185: iload #27
    //   4187: iconst_4
    //   4188: imul
    //   4189: iadd
    //   4190: aload #15
    //   4192: iload #27
    //   4194: iaload
    //   4195: bipush #24
    //   4197: iushr
    //   4198: i2b
    //   4199: bastore
    //   4200: aload #16
    //   4202: iload #26
    //   4204: iload #27
    //   4206: iconst_4
    //   4207: imul
    //   4208: iadd
    //   4209: iconst_1
    //   4210: iadd
    //   4211: aload #15
    //   4213: iload #27
    //   4215: iaload
    //   4216: bipush #16
    //   4218: iushr
    //   4219: i2b
    //   4220: bastore
    //   4221: aload #16
    //   4223: iload #26
    //   4225: iload #27
    //   4227: iconst_4
    //   4228: imul
    //   4229: iadd
    //   4230: iconst_2
    //   4231: iadd
    //   4232: aload #15
    //   4234: iload #27
    //   4236: iaload
    //   4237: bipush #8
    //   4239: iushr
    //   4240: i2b
    //   4241: bastore
    //   4242: aload #16
    //   4244: iload #26
    //   4246: iload #27
    //   4248: iconst_4
    //   4249: imul
    //   4250: iadd
    //   4251: iconst_3
    //   4252: iadd
    //   4253: aload #15
    //   4255: iload #27
    //   4257: iaload
    //   4258: i2b
    //   4259: bastore
    //   4260: iinc #27, 1
    //   4263: iload_2
    //   4264: ifne -> 4175
    //   4267: iinc #18, 1
    //   4270: iload_2
    //   4271: ifne -> 3356
    //   4274: aload #16
    //   4276: aload #16
    //   4278: arraylength
    //   4279: iconst_1
    //   4280: isub
    //   4281: baload
    //   4282: istore #18
    //   4284: aload #16
    //   4286: arraylength
    //   4287: iload #18
    //   4289: isub
    //   4290: newarray byte
    //   4292: astore #4
    //   4294: aload #16
    //   4296: arraylength
    //   4297: aload #4
    //   4299: arraylength
    //   4300: if_icmpge -> 4324
    //   4303: new java/lang/Exception
    //   4306: dup
    //   4307: sipush #-5384
    //   4310: sipush #23936
    //   4313: invokestatic a : (II)Ljava/lang/String;
    //   4316: invokespecial <init> : (Ljava/lang/String;)V
    //   4319: athrow
    //   4320: invokestatic a : (Ljava/lang/Throwable;)Ljava/lang/Throwable;
    //   4323: athrow
    //   4324: iconst_0
    //   4325: istore #19
    //   4327: iload #19
    //   4329: aload #4
    //   4331: arraylength
    //   4332: if_icmpge -> 4352
    //   4335: aload #4
    //   4337: iload #19
    //   4339: aload #16
    //   4341: iload #19
    //   4343: baload
    //   4344: bastore
    //   4345: iinc #19, 1
    //   4348: iload_2
    //   4349: ifne -> 4327
    //   4352: new java/math/BigInteger
    //   4355: dup
    //   4356: aload #4
    //   4358: invokespecial <init> : ([B)V
    //   4361: invokevirtual abs : ()Ljava/math/BigInteger;
    //   4364: putstatic burp/Ztbn.ZA : Ljava/lang/Object;
    //   4367: new java/lang/StringBuilder
    //   4370: dup
    //   4371: invokespecial <init> : ()V
    //   4374: astore_3
    //   4375: iconst_0
    //   4376: istore #4
    //   4378: iload #4
    //   4380: bipush #32
    //   4382: if_icmpge -> 5715
    //   4385: iload #4
    //   4387: tableswitch default -> 5708, 0 -> 4528, 1 -> 4565, 2 -> 4602, 3 -> 4639, 4 -> 4676, 5 -> 4713, 6 -> 4750, 7 -> 4787, 8 -> 4824, 9 -> 4861, 10 -> 4898, 11 -> 4935, 12 -> 4972, 13 -> 5009, 14 -> 5046, 15 -> 5083, 16 -> 5120, 17 -> 5157, 18 -> 5194, 19 -> 5231, 20 -> 5268, 21 -> 5305, 22 -> 5342, 23 -> 5379, 24 -> 5416, 25 -> 5453, 26 -> 5490, 27 -> 5527, 28 -> 5564, 29 -> 5601, 30 -> 5638, 31 -> 5675
    //   4528: aload_3
    //   4529: getstatic burp/Zt5t.ZK : Ljava/lang/String;
    //   4532: getstatic burp/Zrip.ZB : Ljava/lang/Object;
    //   4535: checkcast java/math/BigInteger
    //   4538: invokevirtual intValue : ()I
    //   4541: bipush #32
    //   4543: irem
    //   4544: invokestatic abs : (I)I
    //   4547: invokevirtual charAt : (I)C
    //   4550: invokevirtual append : (C)Ljava/lang/StringBuilder;
    //   4553: pop
    //   4554: iload_2
    //   4555: ifne -> 5708
    //   4558: goto -> 4565
    //   4561: invokestatic a : (Ljava/lang/Throwable;)Ljava/lang/Throwable;
    //   4564: athrow
    //   4565: aload_3
    //   4566: getstatic burp/Zgtd.Zj : Ljava/lang/String;
    //   4569: getstatic burp/Zz0b.ZT : Ljava/lang/Object;
    //   4572: checkcast java/math/BigInteger
    //   4575: invokevirtual intValue : ()I
    //   4578: bipush #32
    //   4580: irem
    //   4581: invokestatic abs : (I)I
    //   4584: invokevirtual charAt : (I)C
    //   4587: invokevirtual append : (C)Ljava/lang/StringBuilder;
    //   4590: pop
    //   4591: iload_2
    //   4592: ifne -> 5708
    //   4595: goto -> 4602
    //   4598: invokestatic a : (Ljava/lang/Throwable;)Ljava/lang/Throwable;
    //   4601: athrow
    //   4602: aload_3
    //   4603: getstatic burp/Zlxr.ZS : Ljava/lang/String;
    //   4606: getstatic burp/Zbnk.Zp : Ljava/lang/Object;
    //   4609: checkcast java/math/BigInteger
    //   4612: invokevirtual intValue : ()I
    //   4615: bipush #32
    //   4617: irem
    //   4618: invokestatic abs : (I)I
    //   4621: invokevirtual charAt : (I)C
    //   4624: invokevirtual append : (C)Ljava/lang/StringBuilder;
    //   4627: pop
    //   4628: iload_2
    //   4629: ifne -> 5708
    //   4632: goto -> 4639
    //   4635: invokestatic a : (Ljava/lang/Throwable;)Ljava/lang/Throwable;
    //   4638: athrow
    //   4639: aload_3
    //   4640: getstatic burp/Zer1.ZV : Ljava/lang/String;
    //   4643: getstatic burp/Zs1d.Zo : Ljava/lang/Object;
    //   4646: checkcast java/math/BigInteger
    //   4649: invokevirtual intValue : ()I
    //   4652: bipush #32
    //   4654: irem
    //   4655: invokestatic abs : (I)I
    //   4658: invokevirtual charAt : (I)C
    //   4661: invokevirtual append : (C)Ljava/lang/StringBuilder;
    //   4664: pop
    //   4665: iload_2
    //   4666: ifne -> 5708
    //   4669: goto -> 4676
    //   4672: invokestatic a : (Ljava/lang/Throwable;)Ljava/lang/Throwable;
    //   4675: athrow
    //   4676: aload_3
    //   4677: getstatic burp/Zly9.ZS : Ljava/lang/String;
    //   4680: getstatic burp/Zst7.ZI : Ljava/lang/Object;
    //   4683: checkcast java/math/BigInteger
    //   4686: invokevirtual intValue : ()I
    //   4689: bipush #32
    //   4691: irem
    //   4692: invokestatic abs : (I)I
    //   4695: invokevirtual charAt : (I)C
    //   4698: invokevirtual append : (C)Ljava/lang/StringBuilder;
    //   4701: pop
    //   4702: iload_2
    //   4703: ifne -> 5708
    //   4706: goto -> 4713
    //   4709: invokestatic a : (Ljava/lang/Throwable;)Ljava/lang/Throwable;
    //   4712: athrow
    //   4713: aload_3
    //   4714: getstatic burp/Zg7e.Zg : Ljava/lang/String;
    //   4717: getstatic burp/Zbsz.ZP : Ljava/lang/Object;
    //   4720: checkcast java/math/BigInteger
    //   4723: invokevirtual intValue : ()I
    //   4726: bipush #32
    //   4728: irem
    //   4729: invokestatic abs : (I)I
    //   4732: invokevirtual charAt : (I)C
    //   4735: invokevirtual append : (C)Ljava/lang/StringBuilder;
    //   4738: pop
    //   4739: iload_2
    //   4740: ifne -> 5708
    //   4743: goto -> 4750
    //   4746: invokestatic a : (Ljava/lang/Throwable;)Ljava/lang/Throwable;
    //   4749: athrow
    //   4750: aload_3
    //   4751: getstatic burp/Zex0.Zk : Ljava/lang/String;
    //   4754: getstatic burp/Zbnz.Zb : Ljava/lang/Object;
    //   4757: checkcast java/math/BigInteger
    //   4760: invokevirtual intValue : ()I
    //   4763: bipush #32
    //   4765: irem
    //   4766: invokestatic abs : (I)I
    //   4769: invokevirtual charAt : (I)C
    //   4772: invokevirtual append : (C)Ljava/lang/StringBuilder;
    //   4775: pop
    //   4776: iload_2
    //   4777: ifne -> 5708
    //   4780: goto -> 4787
    //   4783: invokestatic a : (Ljava/lang/Throwable;)Ljava/lang/Throwable;
    //   4786: athrow
    //   4787: aload_3
    //   4788: getstatic burp/Zmpx.ZC : Ljava/lang/String;
    //   4791: getstatic burp/Zg0f.Zm : Ljava/lang/Object;
    //   4794: checkcast java/math/BigInteger
    //   4797: invokevirtual intValue : ()I
    //   4800: bipush #32
    //   4802: irem
    //   4803: invokestatic abs : (I)I
    //   4806: invokevirtual charAt : (I)C
    //   4809: invokevirtual append : (C)Ljava/lang/StringBuilder;
    //   4812: pop
    //   4813: iload_2
    //   4814: ifne -> 5708
    //   4817: goto -> 4824
    //   4820: invokestatic a : (Ljava/lang/Throwable;)Ljava/lang/Throwable;
    //   4823: athrow
    //   4824: aload_3
    //   4825: getstatic burp/Zm7v.ZX : Ljava/lang/String;
    //   4828: getstatic burp/Zk9q.ZH : Ljava/lang/Object;
    //   4831: checkcast java/math/BigInteger
    //   4834: invokevirtual intValue : ()I
    //   4837: bipush #32
    //   4839: irem
    //   4840: invokestatic abs : (I)I
    //   4843: invokevirtual charAt : (I)C
    //   4846: invokevirtual append : (C)Ljava/lang/StringBuilder;
    //   4849: pop
    //   4850: iload_2
    //   4851: ifne -> 5708
    //   4854: goto -> 4861
    //   4857: invokestatic a : (Ljava/lang/Throwable;)Ljava/lang/Throwable;
    //   4860: athrow
    //   4861: aload_3
    //   4862: getstatic burp/Zlid.ZU : Ljava/lang/String;
    //   4865: getstatic burp/Zkjj.Zh : Ljava/lang/Object;
    //   4868: checkcast java/math/BigInteger
    //   4871: invokevirtual intValue : ()I
    //   4874: bipush #32
    //   4876: irem
    //   4877: invokestatic abs : (I)I
    //   4880: invokevirtual charAt : (I)C
    //   4883: invokevirtual append : (C)Ljava/lang/StringBuilder;
    //   4886: pop
    //   4887: iload_2
    //   4888: ifne -> 5708
    //   4891: goto -> 4898
    //   4894: invokestatic a : (Ljava/lang/Throwable;)Ljava/lang/Throwable;
    //   4897: athrow
    //   4898: aload_3
    //   4899: getstatic burp/Zewr.ZW : Ljava/lang/String;
    //   4902: getstatic burp/Zrfs.ZV : Ljava/lang/Object;
    //   4905: checkcast java/math/BigInteger
    //   4908: invokevirtual intValue : ()I
    //   4911: bipush #32
    //   4913: irem
    //   4914: invokestatic abs : (I)I
    //   4917: invokevirtual charAt : (I)C
    //   4920: invokevirtual append : (C)Ljava/lang/StringBuilder;
    //   4923: pop
    //   4924: iload_2
    //   4925: ifne -> 5708
    //   4928: goto -> 4935
    //   4931: invokestatic a : (Ljava/lang/Throwable;)Ljava/lang/Throwable;
    //   4934: athrow
    //   4935: aload_3
    //   4936: getstatic burp/Zmf6.Zn : Ljava/lang/String;
    //   4939: getstatic burp/Zlxr.Zz : Ljava/lang/Object;
    //   4942: checkcast java/math/BigInteger
    //   4945: invokevirtual intValue : ()I
    //   4948: bipush #32
    //   4950: irem
    //   4951: invokestatic abs : (I)I
    //   4954: invokevirtual charAt : (I)C
    //   4957: invokevirtual append : (C)Ljava/lang/StringBuilder;
    //   4960: pop
    //   4961: iload_2
    //   4962: ifne -> 5708
    //   4965: goto -> 4972
    //   4968: invokestatic a : (Ljava/lang/Throwable;)Ljava/lang/Throwable;
    //   4971: athrow
    //   4972: aload_3
    //   4973: getstatic burp/Zmyk.Zx : Ljava/lang/String;
    //   4976: getstatic burp/Zlxw.Zi : Ljava/lang/Object;
    //   4979: checkcast java/math/BigInteger
    //   4982: invokevirtual intValue : ()I
    //   4985: bipush #32
    //   4987: irem
    //   4988: invokestatic abs : (I)I
    //   4991: invokevirtual charAt : (I)C
    //   4994: invokevirtual append : (C)Ljava/lang/StringBuilder;
    //   4997: pop
    //   4998: iload_2
    //   4999: ifne -> 5708
    //   5002: goto -> 5009
    //   5005: invokestatic a : (Ljava/lang/Throwable;)Ljava/lang/Throwable;
    //   5008: athrow
    //   5009: aload_3
    //   5010: getstatic burp/Zbze.ZK : Ljava/lang/String;
    //   5013: getstatic burp/Zttd.Zi : Ljava/lang/Object;
    //   5016: checkcast java/math/BigInteger
    //   5019: invokevirtual intValue : ()I
    //   5022: bipush #32
    //   5024: irem
    //   5025: invokestatic abs : (I)I
    //   5028: invokevirtual charAt : (I)C
    //   5031: invokevirtual append : (C)Ljava/lang/StringBuilder;
    //   5034: pop
    //   5035: iload_2
    //   5036: ifne -> 5708
    //   5039: goto -> 5046
    //   5042: invokestatic a : (Ljava/lang/Throwable;)Ljava/lang/Throwable;
    //   5045: athrow
    //   5046: aload_3
    //   5047: getstatic burp/Zm_u.Zi : Ljava/lang/String;
    //   5050: getstatic burp/Zzii.ZO : Ljava/lang/Object;
    //   5053: checkcast java/math/BigInteger
    //   5056: invokevirtual intValue : ()I
    //   5059: bipush #32
    //   5061: irem
    //   5062: invokestatic abs : (I)I
    //   5065: invokevirtual charAt : (I)C
    //   5068: invokevirtual append : (C)Ljava/lang/StringBuilder;
    //   5071: pop
    //   5072: iload_2
    //   5073: ifne -> 5708
    //   5076: goto -> 5083
    //   5079: invokestatic a : (Ljava/lang/Throwable;)Ljava/lang/Throwable;
    //   5082: athrow
    //   5083: aload_3
    //   5084: getstatic burp/Zrnk.Zb : Ljava/lang/String;
    //   5087: getstatic burp/Zgi9.Zc : Ljava/lang/Object;
    //   5090: checkcast java/math/BigInteger
    //   5093: invokevirtual intValue : ()I
    //   5096: bipush #32
    //   5098: irem
    //   5099: invokestatic abs : (I)I
    //   5102: invokevirtual charAt : (I)C
    //   5105: invokevirtual append : (C)Ljava/lang/StringBuilder;
    //   5108: pop
    //   5109: iload_2
    //   5110: ifne -> 5708
    //   5113: goto -> 5120
    //   5116: invokestatic a : (Ljava/lang/Throwable;)Ljava/lang/Throwable;
    //   5119: athrow
    //   5120: aload_3
    //   5121: getstatic burp/Zrgo.Z_ : Ljava/lang/String;
    //   5124: getstatic burp/Zs5y.Zd : Ljava/lang/Object;
    //   5127: checkcast java/math/BigInteger
    //   5130: invokevirtual intValue : ()I
    //   5133: bipush #32
    //   5135: irem
    //   5136: invokestatic abs : (I)I
    //   5139: invokevirtual charAt : (I)C
    //   5142: invokevirtual append : (C)Ljava/lang/StringBuilder;
    //   5145: pop
    //   5146: iload_2
    //   5147: ifne -> 5708
    //   5150: goto -> 5157
    //   5153: invokestatic a : (Ljava/lang/Throwable;)Ljava/lang/Throwable;
    //   5156: athrow
    //   5157: aload_3
    //   5158: getstatic burp/Zgk9.Zf : Ljava/lang/String;
    //   5161: getstatic burp/Ztnn.ZA : Ljava/lang/Object;
    //   5164: checkcast java/math/BigInteger
    //   5167: invokevirtual intValue : ()I
    //   5170: bipush #32
    //   5172: irem
    //   5173: invokestatic abs : (I)I
    //   5176: invokevirtual charAt : (I)C
    //   5179: invokevirtual append : (C)Ljava/lang/StringBuilder;
    //   5182: pop
    //   5183: iload_2
    //   5184: ifne -> 5708
    //   5187: goto -> 5194
    //   5190: invokestatic a : (Ljava/lang/Throwable;)Ljava/lang/Throwable;
    //   5193: athrow
    //   5194: aload_3
    //   5195: getstatic burp/Zt1h.Zw : Ljava/lang/String;
    //   5198: getstatic burp/Zlwm.Ze : Ljava/lang/Object;
    //   5201: checkcast java/math/BigInteger
    //   5204: invokevirtual intValue : ()I
    //   5207: bipush #32
    //   5209: irem
    //   5210: invokestatic abs : (I)I
    //   5213: invokevirtual charAt : (I)C
    //   5216: invokevirtual append : (C)Ljava/lang/StringBuilder;
    //   5219: pop
    //   5220: iload_2
    //   5221: ifne -> 5708
    //   5224: goto -> 5231
    //   5227: invokestatic a : (Ljava/lang/Throwable;)Ljava/lang/Throwable;
    //   5230: athrow
    //   5231: aload_3
    //   5232: getstatic burp/Zml9.Zw : Ljava/lang/String;
    //   5235: getstatic burp/Zlg2.ZO : Ljava/lang/Object;
    //   5238: checkcast java/math/BigInteger
    //   5241: invokevirtual intValue : ()I
    //   5244: bipush #32
    //   5246: irem
    //   5247: invokestatic abs : (I)I
    //   5250: invokevirtual charAt : (I)C
    //   5253: invokevirtual append : (C)Ljava/lang/StringBuilder;
    //   5256: pop
    //   5257: iload_2
    //   5258: ifne -> 5708
    //   5261: goto -> 5268
    //   5264: invokestatic a : (Ljava/lang/Throwable;)Ljava/lang/Throwable;
    //   5267: athrow
    //   5268: aload_3
    //   5269: getstatic burp/Ze2k.ZY : Ljava/lang/String;
    //   5272: getstatic burp/Zxp5.ZA : Ljava/lang/Object;
    //   5275: checkcast java/math/BigInteger
    //   5278: invokevirtual intValue : ()I
    //   5281: bipush #32
    //   5283: irem
    //   5284: invokestatic abs : (I)I
    //   5287: invokevirtual charAt : (I)C
    //   5290: invokevirtual append : (C)Ljava/lang/StringBuilder;
    //   5293: pop
    //   5294: iload_2
    //   5295: ifne -> 5708
    //   5298: goto -> 5305
    //   5301: invokestatic a : (Ljava/lang/Throwable;)Ljava/lang/Throwable;
    //   5304: athrow
    //   5305: aload_3
    //   5306: getstatic burp/Zs1k.Zd : Ljava/lang/String;
    //   5309: getstatic burp/Zs4g.ZC : Ljava/lang/Object;
    //   5312: checkcast java/math/BigInteger
    //   5315: invokevirtual intValue : ()I
    //   5318: bipush #32
    //   5320: irem
    //   5321: invokestatic abs : (I)I
    //   5324: invokevirtual charAt : (I)C
    //   5327: invokevirtual append : (C)Ljava/lang/StringBuilder;
    //   5330: pop
    //   5331: iload_2
    //   5332: ifne -> 5708
    //   5335: goto -> 5342
    //   5338: invokestatic a : (Ljava/lang/Throwable;)Ljava/lang/Throwable;
    //   5341: athrow
    //   5342: aload_3
    //   5343: getstatic burp/Zxn4.ZQ : Ljava/lang/String;
    //   5346: getstatic burp/Zrkd.ZO : Ljava/lang/Object;
    //   5349: checkcast java/math/BigInteger
    //   5352: invokevirtual intValue : ()I
    //   5355: bipush #32
    //   5357: irem
    //   5358: invokestatic abs : (I)I
    //   5361: invokevirtual charAt : (I)C
    //   5364: invokevirtual append : (C)Ljava/lang/StringBuilder;
    //   5367: pop
    //   5368: iload_2
    //   5369: ifne -> 5708
    //   5372: goto -> 5379
    //   5375: invokestatic a : (Ljava/lang/Throwable;)Ljava/lang/Throwable;
    //   5378: athrow
    //   5379: aload_3
    //   5380: getstatic burp/Zr02.ZG : Ljava/lang/String;
    //   5383: getstatic burp/Zs8w.ZW : Ljava/lang/Object;
    //   5386: checkcast java/math/BigInteger
    //   5389: invokevirtual intValue : ()I
    //   5392: bipush #32
    //   5394: irem
    //   5395: invokestatic abs : (I)I
    //   5398: invokevirtual charAt : (I)C
    //   5401: invokevirtual append : (C)Ljava/lang/StringBuilder;
    //   5404: pop
    //   5405: iload_2
    //   5406: ifne -> 5708
    //   5409: goto -> 5416
    //   5412: invokestatic a : (Ljava/lang/Throwable;)Ljava/lang/Throwable;
    //   5415: athrow
    //   5416: aload_3
    //   5417: getstatic burp/Zk1.Zg : Ljava/lang/String;
    //   5420: getstatic burp/Ztvg.ZO : Ljava/lang/Object;
    //   5423: checkcast java/math/BigInteger
    //   5426: invokevirtual intValue : ()I
    //   5429: bipush #32
    //   5431: irem
    //   5432: invokestatic abs : (I)I
    //   5435: invokevirtual charAt : (I)C
    //   5438: invokevirtual append : (C)Ljava/lang/StringBuilder;
    //   5441: pop
    //   5442: iload_2
    //   5443: ifne -> 5708
    //   5446: goto -> 5453
    //   5449: invokestatic a : (Ljava/lang/Throwable;)Ljava/lang/Throwable;
    //   5452: athrow
    //   5453: aload_3
    //   5454: getstatic burp/Zos.Za : Ljava/lang/String;
    //   5457: getstatic burp/Zezi.ZQ : Ljava/lang/Object;
    //   5460: checkcast java/math/BigInteger
    //   5463: invokevirtual intValue : ()I
    //   5466: bipush #32
    //   5468: irem
    //   5469: invokestatic abs : (I)I
    //   5472: invokevirtual charAt : (I)C
    //   5475: invokevirtual append : (C)Ljava/lang/StringBuilder;
    //   5478: pop
    //   5479: iload_2
    //   5480: ifne -> 5708
    //   5483: goto -> 5490
    //   5486: invokestatic a : (Ljava/lang/Throwable;)Ljava/lang/Throwable;
    //   5489: athrow
    //   5490: aload_3
    //   5491: getstatic burp/Zmz.Zp : Ljava/lang/String;
    //   5494: getstatic burp/Zxdp.ZW : Ljava/lang/Object;
    //   5497: checkcast java/math/BigInteger
    //   5500: invokevirtual intValue : ()I
    //   5503: bipush #32
    //   5505: irem
    //   5506: invokestatic abs : (I)I
    //   5509: invokevirtual charAt : (I)C
    //   5512: invokevirtual append : (C)Ljava/lang/StringBuilder;
    //   5515: pop
    //   5516: iload_2
    //   5517: ifne -> 5708
    //   5520: goto -> 5527
    //   5523: invokestatic a : (Ljava/lang/Throwable;)Ljava/lang/Throwable;
    //   5526: athrow
    //   5527: aload_3
    //   5528: getstatic burp/Zmdi.ZA : Ljava/lang/String;
    //   5531: getstatic burp/Zz41.Zv : Ljava/lang/Object;
    //   5534: checkcast java/math/BigInteger
    //   5537: invokevirtual intValue : ()I
    //   5540: bipush #32
    //   5542: irem
    //   5543: invokestatic abs : (I)I
    //   5546: invokevirtual charAt : (I)C
    //   5549: invokevirtual append : (C)Ljava/lang/StringBuilder;
    //   5552: pop
    //   5553: iload_2
    //   5554: ifne -> 5708
    //   5557: goto -> 5564
    //   5560: invokestatic a : (Ljava/lang/Throwable;)Ljava/lang/Throwable;
    //   5563: athrow
    //   5564: aload_3
    //   5565: getstatic burp/Zeub.ZT : Ljava/lang/String;
    //   5568: getstatic burp/Zkkl.ZE : Ljava/lang/Object;
    //   5571: checkcast java/math/BigInteger
    //   5574: invokevirtual intValue : ()I
    //   5577: bipush #32
    //   5579: irem
    //   5580: invokestatic abs : (I)I
    //   5583: invokevirtual charAt : (I)C
    //   5586: invokevirtual append : (C)Ljava/lang/StringBuilder;
    //   5589: pop
    //   5590: iload_2
    //   5591: ifne -> 5708
    //   5594: goto -> 5601
    //   5597: invokestatic a : (Ljava/lang/Throwable;)Ljava/lang/Throwable;
    //   5600: athrow
    //   5601: aload_3
    //   5602: getstatic burp/Zgtx.ZN : Ljava/lang/String;
    //   5605: getstatic burp/Zb3r.ZI : Ljava/lang/Object;
    //   5608: checkcast java/math/BigInteger
    //   5611: invokevirtual intValue : ()I
    //   5614: bipush #32
    //   5616: irem
    //   5617: invokestatic abs : (I)I
    //   5620: invokevirtual charAt : (I)C
    //   5623: invokevirtual append : (C)Ljava/lang/StringBuilder;
    //   5626: pop
    //   5627: iload_2
    //   5628: ifne -> 5708
    //   5631: goto -> 5638
    //   5634: invokestatic a : (Ljava/lang/Throwable;)Ljava/lang/Throwable;
    //   5637: athrow
    //   5638: aload_3
    //   5639: getstatic burp/Zk9q.Zk : Ljava/lang/String;
    //   5642: getstatic burp/Zzmc.Zg : Ljava/lang/Object;
    //   5645: checkcast java/math/BigInteger
    //   5648: invokevirtual intValue : ()I
    //   5651: bipush #32
    //   5653: irem
    //   5654: invokestatic abs : (I)I
    //   5657: invokevirtual charAt : (I)C
    //   5660: invokevirtual append : (C)Ljava/lang/StringBuilder;
    //   5663: pop
    //   5664: iload_2
    //   5665: ifne -> 5708
    //   5668: goto -> 5675
    //   5671: invokestatic a : (Ljava/lang/Throwable;)Ljava/lang/Throwable;
    //   5674: athrow
    //   5675: aload_3
    //   5676: getstatic burp/Zso.ZL : Ljava/lang/String;
    //   5679: getstatic burp/Zz5e.Zl : Ljava/lang/Object;
    //   5682: checkcast java/math/BigInteger
    //   5685: invokevirtual intValue : ()I
    //   5688: bipush #32
    //   5690: irem
    //   5691: invokestatic abs : (I)I
    //   5694: invokevirtual charAt : (I)C
    //   5697: invokevirtual append : (C)Ljava/lang/StringBuilder;
    //   5700: pop
    //   5701: goto -> 5708
    //   5704: invokestatic a : (Ljava/lang/Throwable;)Ljava/lang/Throwable;
    //   5707: athrow
    //   5708: iinc #4, 1
    //   5711: iload_2
    //   5712: ifne -> 4378
    //   5715: aload_3
    //   5716: invokevirtual toString : ()Ljava/lang/String;
    //   5719: putstatic burp/Zb9q.Zk : Ljava/lang/String;
    //   5722: new java/io/ByteArrayOutputStream
    //   5725: dup
    //   5726: invokespecial <init> : ()V
    //   5729: astore #4
    //   5731: getstatic burp/Zzmc.Zr : Ljava/lang/String;
    //   5734: astore #5
    //   5736: iconst_0
    //   5737: istore #6
    //   5739: iload #6
    //   5741: aload #5
    //   5743: invokevirtual length : ()I
    //   5746: if_icmpge -> 5777
    //   5749: aload #4
    //   5751: aload #5
    //   5753: iload #6
    //   5755: iload #6
    //   5757: iconst_2
    //   5758: iadd
    //   5759: invokevirtual substring : (II)Ljava/lang/String;
    //   5762: bipush #16
    //   5764: invokestatic parseInt : (Ljava/lang/String;I)I
    //   5767: invokevirtual write : (I)V
    //   5770: iinc #6, 2
    //   5773: iload_2
    //   5774: ifne -> 5739
    //   5777: aload #4
    //   5779: invokevirtual toByteArray : ()[B
    //   5782: astore #6
    //   5784: getstatic burp/Zegj.ZT : Ljava/lang/Object;
    //   5787: checkcast java/math/BigInteger
    //   5790: invokevirtual toByteArray : ()[B
    //   5793: astore #7
    //   5795: sipush #256
    //   5798: newarray byte
    //   5800: astore #9
    //   5802: sipush #256
    //   5805: newarray int
    //   5807: astore #10
    //   5809: sipush #256
    //   5812: newarray int
    //   5814: astore #11
    //   5816: sipush #256
    //   5819: newarray int
    //   5821: astore #12
    //   5823: sipush #256
    //   5826: newarray int
    //   5828: astore #13
    //   5830: bipush #10
    //   5832: newarray int
    //   5834: astore #14
    //   5836: sipush #283
    //   5839: istore #15
    //   5841: iconst_0
    //   5842: istore #17
    //   5844: iload #17
    //   5846: sipush #256
    //   5849: if_icmpge -> 6083
    //   5852: sipush #-5383
    //   5855: sipush #31637
    //   5858: invokestatic a : (II)Ljava/lang/String;
    //   5861: iload #17
    //   5863: iconst_1
    //   5864: iushr
    //   5865: invokevirtual charAt : (I)C
    //   5868: istore #26
    //   5870: iload #17
    //   5872: iconst_1
    //   5873: iand
    //   5874: ifne -> 5889
    //   5877: iload #26
    //   5879: bipush #8
    //   5881: iushr
    //   5882: goto -> 5891
    //   5885: invokestatic a : (Ljava/lang/Throwable;)Ljava/lang/Throwable;
    //   5888: athrow
    //   5889: iload #26
    //   5891: i2b
    //   5892: sipush #255
    //   5895: iand
    //   5896: istore #16
    //   5898: iload #17
    //   5900: iconst_1
    //   5901: ishl
    //   5902: istore #18
    //   5904: iload #18
    //   5906: sipush #256
    //   5909: if_icmplt -> 5919
    //   5912: iload #18
    //   5914: iload #15
    //   5916: ixor
    //   5917: istore #18
    //   5919: iload #18
    //   5921: iconst_1
    //   5922: ishl
    //   5923: istore #19
    //   5925: iload #19
    //   5927: sipush #256
    //   5930: if_icmplt -> 5940
    //   5933: iload #19
    //   5935: iload #15
    //   5937: ixor
    //   5938: istore #19
    //   5940: iload #19
    //   5942: iconst_1
    //   5943: ishl
    //   5944: istore #20
    //   5946: iload #20
    //   5948: sipush #256
    //   5951: if_icmplt -> 5961
    //   5954: iload #20
    //   5956: iload #15
    //   5958: ixor
    //   5959: istore #20
    //   5961: iload #20
    //   5963: iload #17
    //   5965: ixor
    //   5966: istore #21
    //   5968: iload #21
    //   5970: iload #18
    //   5972: ixor
    //   5973: istore #22
    //   5975: iload #21
    //   5977: iload #19
    //   5979: ixor
    //   5980: istore #23
    //   5982: iload #20
    //   5984: iload #19
    //   5986: ixor
    //   5987: iload #18
    //   5989: ixor
    //   5990: istore #24
    //   5992: aload #9
    //   5994: iload #17
    //   5996: iload #16
    //   5998: i2b
    //   5999: bastore
    //   6000: aload #10
    //   6002: iload #16
    //   6004: iload #24
    //   6006: bipush #24
    //   6008: ishl
    //   6009: iload #21
    //   6011: bipush #16
    //   6013: ishl
    //   6014: ior
    //   6015: iload #23
    //   6017: bipush #8
    //   6019: ishl
    //   6020: ior
    //   6021: iload #22
    //   6023: ior
    //   6024: dup
    //   6025: istore #25
    //   6027: iastore
    //   6028: aload #11
    //   6030: iload #16
    //   6032: iload #25
    //   6034: bipush #8
    //   6036: iushr
    //   6037: iload #25
    //   6039: bipush #24
    //   6041: ishl
    //   6042: ior
    //   6043: iastore
    //   6044: aload #12
    //   6046: iload #16
    //   6048: iload #25
    //   6050: bipush #16
    //   6052: iushr
    //   6053: iload #25
    //   6055: bipush #16
    //   6057: ishl
    //   6058: ior
    //   6059: iastore
    //   6060: aload #13
    //   6062: iload #16
    //   6064: iload #25
    //   6066: bipush #24
    //   6068: iushr
    //   6069: iload #25
    //   6071: bipush #8
    //   6073: ishl
    //   6074: ior
    //   6075: iastore
    //   6076: iinc #17, 1
    //   6079: iload_2
    //   6080: ifne -> 5844
    //   6083: iconst_1
    //   6084: istore #26
    //   6086: aload #14
    //   6088: iconst_0
    //   6089: iload #26
    //   6091: bipush #24
    //   6093: ishl
    //   6094: iastore
    //   6095: iconst_1
    //   6096: istore #27
    //   6098: iload #27
    //   6100: bipush #10
    //   6102: if_icmpge -> 6143
    //   6105: iload #26
    //   6107: iconst_1
    //   6108: ishl
    //   6109: istore #26
    //   6111: iload #26
    //   6113: sipush #256
    //   6116: if_icmplt -> 6126
    //   6119: iload #26
    //   6121: iload #15
    //   6123: ixor
    //   6124: istore #26
    //   6126: aload #14
    //   6128: iload #27
    //   6130: iload #26
    //   6132: bipush #24
    //   6134: ishl
    //   6135: iastore
    //   6136: iinc #27, 1
    //   6139: iload_2
    //   6140: ifne -> 6098
    //   6143: iconst_4
    //   6144: istore #27
    //   6146: iload #27
    //   6148: bipush #6
    //   6150: iadd
    //   6151: istore #28
    //   6153: iconst_4
    //   6154: iload #28
    //   6156: iconst_1
    //   6157: iadd
    //   6158: imul
    //   6159: istore #29
    //   6161: iload #29
    //   6163: newarray int
    //   6165: astore #30
    //   6167: iload #29
    //   6169: newarray int
    //   6171: astore #31
    //   6173: iconst_0
    //   6174: istore #26
    //   6176: iconst_0
    //   6177: istore #33
    //   6179: iconst_0
    //   6180: istore #34
    //   6182: iload #33
    //   6184: iload #27
    //   6186: if_icmpge -> 6254
    //   6189: aload #30
    //   6191: iload #33
    //   6193: aload #6
    //   6195: iload #34
    //   6197: baload
    //   6198: bipush #24
    //   6200: ishl
    //   6201: aload #6
    //   6203: iload #34
    //   6205: iconst_1
    //   6206: iadd
    //   6207: baload
    //   6208: sipush #255
    //   6211: iand
    //   6212: bipush #16
    //   6214: ishl
    //   6215: ior
    //   6216: aload #6
    //   6218: iload #34
    //   6220: iconst_2
    //   6221: iadd
    //   6222: baload
    //   6223: sipush #255
    //   6226: iand
    //   6227: bipush #8
    //   6229: ishl
    //   6230: ior
    //   6231: aload #6
    //   6233: iload #34
    //   6235: iconst_3
    //   6236: iadd
    //   6237: baload
    //   6238: sipush #255
    //   6241: iand
    //   6242: ior
    //   6243: iastore
    //   6244: iinc #33, 1
    //   6247: iinc #34, 4
    //   6250: iload_2
    //   6251: ifne -> 6182
    //   6254: iload #27
    //   6256: istore #33
    //   6258: iconst_0
    //   6259: istore #34
    //   6261: iload #33
    //   6263: iload #29
    //   6265: if_icmpge -> 6392
    //   6268: aload #30
    //   6270: iload #33
    //   6272: iconst_1
    //   6273: isub
    //   6274: iaload
    //   6275: istore #32
    //   6277: iload #34
    //   6279: ifne -> 6366
    //   6282: iload #27
    //   6284: istore #34
    //   6286: aload #9
    //   6288: iload #32
    //   6290: bipush #16
    //   6292: iushr
    //   6293: sipush #255
    //   6296: iand
    //   6297: baload
    //   6298: bipush #24
    //   6300: ishl
    //   6301: aload #9
    //   6303: iload #32
    //   6305: bipush #8
    //   6307: iushr
    //   6308: sipush #255
    //   6311: iand
    //   6312: baload
    //   6313: sipush #255
    //   6316: iand
    //   6317: bipush #16
    //   6319: ishl
    //   6320: ior
    //   6321: aload #9
    //   6323: iload #32
    //   6325: sipush #255
    //   6328: iand
    //   6329: baload
    //   6330: sipush #255
    //   6333: iand
    //   6334: bipush #8
    //   6336: ishl
    //   6337: ior
    //   6338: aload #9
    //   6340: iload #32
    //   6342: bipush #24
    //   6344: iushr
    //   6345: baload
    //   6346: sipush #255
    //   6349: iand
    //   6350: ior
    //   6351: istore #32
    //   6353: iload #32
    //   6355: aload #14
    //   6357: iload #26
    //   6359: iinc #26, 1
    //   6362: iaload
    //   6363: ixor
    //   6364: istore #32
    //   6366: aload #30
    //   6368: iload #33
    //   6370: aload #30
    //   6372: iload #33
    //   6374: iload #27
    //   6376: isub
    //   6377: iaload
    //   6378: iload #32
    //   6380: ixor
    //   6381: iastore
    //   6382: iinc #33, 1
    //   6385: iinc #34, -1
    //   6388: iload_2
    //   6389: ifne -> 6261
    //   6392: iconst_0
    //   6393: istore #33
    //   6395: iconst_4
    //   6396: iload #28
    //   6398: imul
    //   6399: istore #34
    //   6401: aload #31
    //   6403: iload #33
    //   6405: aload #30
    //   6407: iload #34
    //   6409: iaload
    //   6410: iastore
    //   6411: aload #31
    //   6413: iload #33
    //   6415: iconst_1
    //   6416: iadd
    //   6417: aload #30
    //   6419: iload #34
    //   6421: iconst_1
    //   6422: iadd
    //   6423: iaload
    //   6424: iastore
    //   6425: aload #31
    //   6427: iload #33
    //   6429: iconst_2
    //   6430: iadd
    //   6431: aload #30
    //   6433: iload #34
    //   6435: iconst_2
    //   6436: iadd
    //   6437: iaload
    //   6438: iastore
    //   6439: aload #31
    //   6441: iload #33
    //   6443: iconst_3
    //   6444: iadd
    //   6445: aload #30
    //   6447: iload #34
    //   6449: iconst_3
    //   6450: iadd
    //   6451: iaload
    //   6452: iastore
    //   6453: iinc #33, 4
    //   6456: iinc #34, -4
    //   6459: iconst_1
    //   6460: istore #36
    //   6462: iload #36
    //   6464: iload #28
    //   6466: if_icmpge -> 6830
    //   6469: aload #30
    //   6471: iload #34
    //   6473: iaload
    //   6474: istore #35
    //   6476: aload #31
    //   6478: iload #33
    //   6480: aload #10
    //   6482: aload #9
    //   6484: iload #35
    //   6486: bipush #24
    //   6488: iushr
    //   6489: baload
    //   6490: sipush #255
    //   6493: iand
    //   6494: iaload
    //   6495: aload #11
    //   6497: aload #9
    //   6499: iload #35
    //   6501: bipush #16
    //   6503: iushr
    //   6504: sipush #255
    //   6507: iand
    //   6508: baload
    //   6509: sipush #255
    //   6512: iand
    //   6513: iaload
    //   6514: ixor
    //   6515: aload #12
    //   6517: aload #9
    //   6519: iload #35
    //   6521: bipush #8
    //   6523: iushr
    //   6524: sipush #255
    //   6527: iand
    //   6528: baload
    //   6529: sipush #255
    //   6532: iand
    //   6533: iaload
    //   6534: ixor
    //   6535: aload #13
    //   6537: aload #9
    //   6539: iload #35
    //   6541: sipush #255
    //   6544: iand
    //   6545: baload
    //   6546: sipush #255
    //   6549: iand
    //   6550: iaload
    //   6551: ixor
    //   6552: iastore
    //   6553: aload #30
    //   6555: iload #34
    //   6557: iconst_1
    //   6558: iadd
    //   6559: iaload
    //   6560: istore #35
    //   6562: aload #31
    //   6564: iload #33
    //   6566: iconst_1
    //   6567: iadd
    //   6568: aload #10
    //   6570: aload #9
    //   6572: iload #35
    //   6574: bipush #24
    //   6576: iushr
    //   6577: baload
    //   6578: sipush #255
    //   6581: iand
    //   6582: iaload
    //   6583: aload #11
    //   6585: aload #9
    //   6587: iload #35
    //   6589: bipush #16
    //   6591: iushr
    //   6592: sipush #255
    //   6595: iand
    //   6596: baload
    //   6597: sipush #255
    //   6600: iand
    //   6601: iaload
    //   6602: ixor
    //   6603: aload #12
    //   6605: aload #9
    //   6607: iload #35
    //   6609: bipush #8
    //   6611: iushr
    //   6612: sipush #255
    //   6615: iand
    //   6616: baload
    //   6617: sipush #255
    //   6620: iand
    //   6621: iaload
    //   6622: ixor
    //   6623: aload #13
    //   6625: aload #9
    //   6627: iload #35
    //   6629: sipush #255
    //   6632: iand
    //   6633: baload
    //   6634: sipush #255
    //   6637: iand
    //   6638: iaload
    //   6639: ixor
    //   6640: iastore
    //   6641: aload #30
    //   6643: iload #34
    //   6645: iconst_2
    //   6646: iadd
    //   6647: iaload
    //   6648: istore #35
    //   6650: aload #31
    //   6652: iload #33
    //   6654: iconst_2
    //   6655: iadd
    //   6656: aload #10
    //   6658: aload #9
    //   6660: iload #35
    //   6662: bipush #24
    //   6664: iushr
    //   6665: baload
    //   6666: sipush #255
    //   6669: iand
    //   6670: iaload
    //   6671: aload #11
    //   6673: aload #9
    //   6675: iload #35
    //   6677: bipush #16
    //   6679: iushr
    //   6680: sipush #255
    //   6683: iand
    //   6684: baload
    //   6685: sipush #255
    //   6688: iand
    //   6689: iaload
    //   6690: ixor
    //   6691: aload #12
    //   6693: aload #9
    //   6695: iload #35
    //   6697: bipush #8
    //   6699: iushr
    //   6700: sipush #255
    //   6703: iand
    //   6704: baload
    //   6705: sipush #255
    //   6708: iand
    //   6709: iaload
    //   6710: ixor
    //   6711: aload #13
    //   6713: aload #9
    //   6715: iload #35
    //   6717: sipush #255
    //   6720: iand
    //   6721: baload
    //   6722: sipush #255
    //   6725: iand
    //   6726: iaload
    //   6727: ixor
    //   6728: iastore
    //   6729: aload #30
    //   6731: iload #34
    //   6733: iconst_3
    //   6734: iadd
    //   6735: iaload
    //   6736: istore #35
    //   6738: aload #31
    //   6740: iload #33
    //   6742: iconst_3
    //   6743: iadd
    //   6744: aload #10
    //   6746: aload #9
    //   6748: iload #35
    //   6750: bipush #24
    //   6752: iushr
    //   6753: baload
    //   6754: sipush #255
    //   6757: iand
    //   6758: iaload
    //   6759: aload #11
    //   6761: aload #9
    //   6763: iload #35
    //   6765: bipush #16
    //   6767: iushr
    //   6768: sipush #255
    //   6771: iand
    //   6772: baload
    //   6773: sipush #255
    //   6776: iand
    //   6777: iaload
    //   6778: ixor
    //   6779: aload #12
    //   6781: aload #9
    //   6783: iload #35
    //   6785: bipush #8
    //   6787: iushr
    //   6788: sipush #255
    //   6791: iand
    //   6792: baload
    //   6793: sipush #255
    //   6796: iand
    //   6797: iaload
    //   6798: ixor
    //   6799: aload #13
    //   6801: aload #9
    //   6803: iload #35
    //   6805: sipush #255
    //   6808: iand
    //   6809: baload
    //   6810: sipush #255
    //   6813: iand
    //   6814: iaload
    //   6815: ixor
    //   6816: iastore
    //   6817: iinc #33, 4
    //   6820: iinc #34, -4
    //   6823: iinc #36, 1
    //   6826: iload_2
    //   6827: ifne -> 6462
    //   6830: aload #31
    //   6832: iload #33
    //   6834: aload #30
    //   6836: iload #34
    //   6838: iaload
    //   6839: iastore
    //   6840: aload #31
    //   6842: iload #33
    //   6844: iconst_1
    //   6845: iadd
    //   6846: aload #30
    //   6848: iload #34
    //   6850: iconst_1
    //   6851: iadd
    //   6852: iaload
    //   6853: iastore
    //   6854: aload #31
    //   6856: iload #33
    //   6858: iconst_2
    //   6859: iadd
    //   6860: aload #30
    //   6862: iload #34
    //   6864: iconst_2
    //   6865: iadd
    //   6866: iaload
    //   6867: iastore
    //   6868: aload #31
    //   6870: iload #33
    //   6872: iconst_3
    //   6873: iadd
    //   6874: aload #30
    //   6876: iload #34
    //   6878: iconst_3
    //   6879: iadd
    //   6880: iaload
    //   6881: iastore
    //   6882: iconst_0
    //   6883: newarray byte
    //   6885: astore #36
    //   6887: aload #7
    //   6889: arraylength
    //   6890: bipush #16
    //   6892: irem
    //   6893: ifeq -> 6917
    //   6896: new java/lang/Exception
    //   6899: dup
    //   6900: sipush #-5384
    //   6903: sipush #23936
    //   6906: invokestatic a : (II)Ljava/lang/String;
    //   6909: invokespecial <init> : (Ljava/lang/String;)V
    //   6912: athrow
    //   6913: invokestatic a : (Ljava/lang/Throwable;)Ljava/lang/Throwable;
    //   6916: athrow
    //   6917: bipush #10
    //   6919: istore #37
    //   6921: sipush #-5392
    //   6924: sipush #256
    //   6927: newarray byte
    //   6929: astore #38
    //   6931: sipush #3190
    //   6934: sipush #256
    //   6937: newarray int
    //   6939: astore #39
    //   6941: sipush #256
    //   6944: newarray int
    //   6946: astore #40
    //   6948: sipush #256
    //   6951: newarray int
    //   6953: astore #41
    //   6955: sipush #256
    //   6958: newarray int
    //   6960: astore #42
    //   6962: sipush #283
    //   6965: istore #15
    //   6967: invokestatic a : (II)Ljava/lang/String;
    //   6970: astore #43
    //   6972: iconst_0
    //   6973: istore #17
    //   6975: iload #17
    //   6977: sipush #256
    //   6980: if_icmpge -> 7207
    //   6983: aload #43
    //   6985: iload #17
    //   6987: iconst_1
    //   6988: iushr
    //   6989: invokevirtual charAt : (I)C
    //   6992: istore #44
    //   6994: iload #17
    //   6996: iconst_1
    //   6997: iand
    //   6998: ifne -> 7013
    //   7001: iload #44
    //   7003: bipush #8
    //   7005: iushr
    //   7006: goto -> 7015
    //   7009: invokestatic a : (Ljava/lang/Throwable;)Ljava/lang/Throwable;
    //   7012: athrow
    //   7013: iload #44
    //   7015: i2b
    //   7016: sipush #255
    //   7019: iand
    //   7020: istore #16
    //   7022: iload #17
    //   7024: iconst_1
    //   7025: ishl
    //   7026: istore #18
    //   7028: iload #18
    //   7030: sipush #256
    //   7033: if_icmplt -> 7043
    //   7036: iload #18
    //   7038: iload #15
    //   7040: ixor
    //   7041: istore #18
    //   7043: iload #18
    //   7045: iconst_1
    //   7046: ishl
    //   7047: istore #19
    //   7049: iload #19
    //   7051: sipush #256
    //   7054: if_icmplt -> 7064
    //   7057: iload #19
    //   7059: iload #15
    //   7061: ixor
    //   7062: istore #19
    //   7064: iload #19
    //   7066: iconst_1
    //   7067: ishl
    //   7068: istore #20
    //   7070: iload #20
    //   7072: sipush #256
    //   7075: if_icmplt -> 7085
    //   7078: iload #20
    //   7080: iload #15
    //   7082: ixor
    //   7083: istore #20
    //   7085: iload #20
    //   7087: iload #17
    //   7089: ixor
    //   7090: istore #21
    //   7092: iload #21
    //   7094: iload #18
    //   7096: ixor
    //   7097: istore #22
    //   7099: iload #21
    //   7101: iload #19
    //   7103: ixor
    //   7104: istore #23
    //   7106: iload #20
    //   7108: iload #19
    //   7110: ixor
    //   7111: iload #18
    //   7113: ixor
    //   7114: istore #24
    //   7116: aload #38
    //   7118: iload #16
    //   7120: iload #17
    //   7122: i2b
    //   7123: bastore
    //   7124: aload #39
    //   7126: iload #16
    //   7128: iload #24
    //   7130: bipush #24
    //   7132: ishl
    //   7133: iload #21
    //   7135: bipush #16
    //   7137: ishl
    //   7138: ior
    //   7139: iload #23
    //   7141: bipush #8
    //   7143: ishl
    //   7144: ior
    //   7145: iload #22
    //   7147: ior
    //   7148: dup
    //   7149: istore #25
    //   7151: iastore
    //   7152: aload #40
    //   7154: iload #16
    //   7156: iload #25
    //   7158: bipush #8
    //   7160: iushr
    //   7161: iload #25
    //   7163: bipush #24
    //   7165: ishl
    //   7166: ior
    //   7167: iastore
    //   7168: aload #41
    //   7170: iload #16
    //   7172: iload #25
    //   7174: bipush #16
    //   7176: iushr
    //   7177: iload #25
    //   7179: bipush #16
    //   7181: ishl
    //   7182: ior
    //   7183: iastore
    //   7184: aload #42
    //   7186: iload #16
    //   7188: iload #25
    //   7190: bipush #24
    //   7192: iushr
    //   7193: iload #25
    //   7195: bipush #8
    //   7197: ishl
    //   7198: ior
    //   7199: iastore
    //   7200: iinc #17, 1
    //   7203: iload_2
    //   7204: ifne -> 6975
    //   7207: aload #7
    //   7209: arraylength
    //   7210: newarray byte
    //   7212: astore #44
    //   7214: iconst_0
    //   7215: istore #45
    //   7217: iload #45
    //   7219: aload #7
    //   7221: arraylength
    //   7222: bipush #16
    //   7224: idiv
    //   7225: if_icmpge -> 8139
    //   7228: bipush #16
    //   7230: newarray byte
    //   7232: astore #46
    //   7234: bipush #16
    //   7236: newarray byte
    //   7238: astore #47
    //   7240: iconst_0
    //   7241: istore #48
    //   7243: iload #48
    //   7245: bipush #16
    //   7247: if_icmpge -> 7273
    //   7250: aload #46
    //   7252: iload #48
    //   7254: aload #7
    //   7256: iload #48
    //   7258: iload #45
    //   7260: bipush #16
    //   7262: imul
    //   7263: iadd
    //   7264: baload
    //   7265: bastore
    //   7266: iinc #48, 1
    //   7269: iload_2
    //   7270: ifne -> 7243
    //   7273: iconst_0
    //   7274: istore #48
    //   7276: aload #46
    //   7278: iconst_0
    //   7279: baload
    //   7280: bipush #24
    //   7282: ishl
    //   7283: aload #46
    //   7285: iconst_1
    //   7286: baload
    //   7287: sipush #255
    //   7290: iand
    //   7291: bipush #16
    //   7293: ishl
    //   7294: ior
    //   7295: aload #46
    //   7297: iconst_2
    //   7298: baload
    //   7299: sipush #255
    //   7302: iand
    //   7303: bipush #8
    //   7305: ishl
    //   7306: ior
    //   7307: aload #46
    //   7309: iconst_3
    //   7310: baload
    //   7311: sipush #255
    //   7314: iand
    //   7315: ior
    //   7316: aload #31
    //   7318: iconst_0
    //   7319: iaload
    //   7320: ixor
    //   7321: istore #50
    //   7323: aload #46
    //   7325: iconst_4
    //   7326: baload
    //   7327: bipush #24
    //   7329: ishl
    //   7330: aload #46
    //   7332: iconst_5
    //   7333: baload
    //   7334: sipush #255
    //   7337: iand
    //   7338: bipush #16
    //   7340: ishl
    //   7341: ior
    //   7342: aload #46
    //   7344: bipush #6
    //   7346: baload
    //   7347: sipush #255
    //   7350: iand
    //   7351: bipush #8
    //   7353: ishl
    //   7354: ior
    //   7355: aload #46
    //   7357: bipush #7
    //   7359: baload
    //   7360: sipush #255
    //   7363: iand
    //   7364: ior
    //   7365: aload #31
    //   7367: iconst_1
    //   7368: iaload
    //   7369: ixor
    //   7370: istore #51
    //   7372: aload #46
    //   7374: bipush #8
    //   7376: baload
    //   7377: bipush #24
    //   7379: ishl
    //   7380: aload #46
    //   7382: bipush #9
    //   7384: baload
    //   7385: sipush #255
    //   7388: iand
    //   7389: bipush #16
    //   7391: ishl
    //   7392: ior
    //   7393: aload #46
    //   7395: bipush #10
    //   7397: baload
    //   7398: sipush #255
    //   7401: iand
    //   7402: bipush #8
    //   7404: ishl
    //   7405: ior
    //   7406: aload #46
    //   7408: bipush #11
    //   7410: baload
    //   7411: sipush #255
    //   7414: iand
    //   7415: ior
    //   7416: aload #31
    //   7418: iconst_2
    //   7419: iaload
    //   7420: ixor
    //   7421: istore #52
    //   7423: aload #46
    //   7425: bipush #12
    //   7427: baload
    //   7428: bipush #24
    //   7430: ishl
    //   7431: aload #46
    //   7433: bipush #13
    //   7435: baload
    //   7436: sipush #255
    //   7439: iand
    //   7440: bipush #16
    //   7442: ishl
    //   7443: ior
    //   7444: aload #46
    //   7446: bipush #14
    //   7448: baload
    //   7449: sipush #255
    //   7452: iand
    //   7453: bipush #8
    //   7455: ishl
    //   7456: ior
    //   7457: aload #46
    //   7459: bipush #15
    //   7461: baload
    //   7462: sipush #255
    //   7465: iand
    //   7466: ior
    //   7467: aload #31
    //   7469: iconst_3
    //   7470: iaload
    //   7471: ixor
    //   7472: istore #53
    //   7474: iconst_1
    //   7475: istore #54
    //   7477: iload #54
    //   7479: iload #37
    //   7481: if_icmpge -> 7724
    //   7484: iinc #48, 4
    //   7487: aload #39
    //   7489: iload #50
    //   7491: bipush #24
    //   7493: iushr
    //   7494: iaload
    //   7495: aload #40
    //   7497: iload #53
    //   7499: bipush #16
    //   7501: iushr
    //   7502: sipush #255
    //   7505: iand
    //   7506: iaload
    //   7507: ixor
    //   7508: aload #41
    //   7510: iload #52
    //   7512: bipush #8
    //   7514: iushr
    //   7515: sipush #255
    //   7518: iand
    //   7519: iaload
    //   7520: ixor
    //   7521: aload #42
    //   7523: iload #51
    //   7525: sipush #255
    //   7528: iand
    //   7529: iaload
    //   7530: ixor
    //   7531: aload #31
    //   7533: iload #48
    //   7535: iaload
    //   7536: ixor
    //   7537: istore #55
    //   7539: aload #39
    //   7541: iload #51
    //   7543: bipush #24
    //   7545: iushr
    //   7546: iaload
    //   7547: aload #40
    //   7549: iload #50
    //   7551: bipush #16
    //   7553: iushr
    //   7554: sipush #255
    //   7557: iand
    //   7558: iaload
    //   7559: ixor
    //   7560: aload #41
    //   7562: iload #53
    //   7564: bipush #8
    //   7566: iushr
    //   7567: sipush #255
    //   7570: iand
    //   7571: iaload
    //   7572: ixor
    //   7573: aload #42
    //   7575: iload #52
    //   7577: sipush #255
    //   7580: iand
    //   7581: iaload
    //   7582: ixor
    //   7583: aload #31
    //   7585: iload #48
    //   7587: iconst_1
    //   7588: iadd
    //   7589: iaload
    //   7590: ixor
    //   7591: istore #56
    //   7593: aload #39
    //   7595: iload #52
    //   7597: bipush #24
    //   7599: iushr
    //   7600: iaload
    //   7601: aload #40
    //   7603: iload #51
    //   7605: bipush #16
    //   7607: iushr
    //   7608: sipush #255
    //   7611: iand
    //   7612: iaload
    //   7613: ixor
    //   7614: aload #41
    //   7616: iload #50
    //   7618: bipush #8
    //   7620: iushr
    //   7621: sipush #255
    //   7624: iand
    //   7625: iaload
    //   7626: ixor
    //   7627: aload #42
    //   7629: iload #53
    //   7631: sipush #255
    //   7634: iand
    //   7635: iaload
    //   7636: ixor
    //   7637: aload #31
    //   7639: iload #48
    //   7641: iconst_2
    //   7642: iadd
    //   7643: iaload
    //   7644: ixor
    //   7645: istore #57
    //   7647: aload #39
    //   7649: iload #53
    //   7651: bipush #24
    //   7653: iushr
    //   7654: iaload
    //   7655: aload #40
    //   7657: iload #52
    //   7659: bipush #16
    //   7661: iushr
    //   7662: sipush #255
    //   7665: iand
    //   7666: iaload
    //   7667: ixor
    //   7668: aload #41
    //   7670: iload #51
    //   7672: bipush #8
    //   7674: iushr
    //   7675: sipush #255
    //   7678: iand
    //   7679: iaload
    //   7680: ixor
    //   7681: aload #42
    //   7683: iload #50
    //   7685: sipush #255
    //   7688: iand
    //   7689: iaload
    //   7690: ixor
    //   7691: aload #31
    //   7693: iload #48
    //   7695: iconst_3
    //   7696: iadd
    //   7697: iaload
    //   7698: ixor
    //   7699: istore #58
    //   7701: iload #55
    //   7703: istore #50
    //   7705: iload #56
    //   7707: istore #51
    //   7709: iload #57
    //   7711: istore #52
    //   7713: iload #58
    //   7715: istore #53
    //   7717: iinc #54, 1
    //   7720: iload_2
    //   7721: ifne -> 7477
    //   7724: iinc #48, 4
    //   7727: aload #31
    //   7729: iload #48
    //   7731: iaload
    //   7732: istore #49
    //   7734: aload #47
    //   7736: iconst_0
    //   7737: aload #38
    //   7739: iload #50
    //   7741: bipush #24
    //   7743: iushr
    //   7744: baload
    //   7745: iload #49
    //   7747: bipush #24
    //   7749: iushr
    //   7750: ixor
    //   7751: i2b
    //   7752: bastore
    //   7753: aload #47
    //   7755: iconst_1
    //   7756: aload #38
    //   7758: iload #53
    //   7760: bipush #16
    //   7762: iushr
    //   7763: sipush #255
    //   7766: iand
    //   7767: baload
    //   7768: iload #49
    //   7770: bipush #16
    //   7772: iushr
    //   7773: ixor
    //   7774: i2b
    //   7775: bastore
    //   7776: aload #47
    //   7778: iconst_2
    //   7779: aload #38
    //   7781: iload #52
    //   7783: bipush #8
    //   7785: iushr
    //   7786: sipush #255
    //   7789: iand
    //   7790: baload
    //   7791: iload #49
    //   7793: bipush #8
    //   7795: iushr
    //   7796: ixor
    //   7797: i2b
    //   7798: bastore
    //   7799: aload #47
    //   7801: iconst_3
    //   7802: aload #38
    //   7804: iload #51
    //   7806: sipush #255
    //   7809: iand
    //   7810: baload
    //   7811: iload #49
    //   7813: ixor
    //   7814: i2b
    //   7815: bastore
    //   7816: aload #31
    //   7818: iload #48
    //   7820: iconst_1
    //   7821: iadd
    //   7822: iaload
    //   7823: istore #49
    //   7825: aload #47
    //   7827: iconst_4
    //   7828: aload #38
    //   7830: iload #51
    //   7832: bipush #24
    //   7834: iushr
    //   7835: baload
    //   7836: iload #49
    //   7838: bipush #24
    //   7840: iushr
    //   7841: ixor
    //   7842: i2b
    //   7843: bastore
    //   7844: aload #47
    //   7846: iconst_5
    //   7847: aload #38
    //   7849: iload #50
    //   7851: bipush #16
    //   7853: iushr
    //   7854: sipush #255
    //   7857: iand
    //   7858: baload
    //   7859: iload #49
    //   7861: bipush #16
    //   7863: iushr
    //   7864: ixor
    //   7865: i2b
    //   7866: bastore
    //   7867: aload #47
    //   7869: bipush #6
    //   7871: aload #38
    //   7873: iload #53
    //   7875: bipush #8
    //   7877: iushr
    //   7878: sipush #255
    //   7881: iand
    //   7882: baload
    //   7883: iload #49
    //   7885: bipush #8
    //   7887: iushr
    //   7888: ixor
    //   7889: i2b
    //   7890: bastore
    //   7891: aload #47
    //   7893: bipush #7
    //   7895: aload #38
    //   7897: iload #52
    //   7899: sipush #255
    //   7902: iand
    //   7903: baload
    //   7904: iload #49
    //   7906: ixor
    //   7907: i2b
    //   7908: bastore
    //   7909: aload #31
    //   7911: iload #48
    //   7913: iconst_2
    //   7914: iadd
    //   7915: iaload
    //   7916: istore #49
    //   7918: aload #47
    //   7920: bipush #8
    //   7922: aload #38
    //   7924: iload #52
    //   7926: bipush #24
    //   7928: iushr
    //   7929: baload
    //   7930: iload #49
    //   7932: bipush #24
    //   7934: iushr
    //   7935: ixor
    //   7936: i2b
    //   7937: bastore
    //   7938: aload #47
    //   7940: bipush #9
    //   7942: aload #38
    //   7944: iload #51
    //   7946: bipush #16
    //   7948: iushr
    //   7949: sipush #255
    //   7952: iand
    //   7953: baload
    //   7954: iload #49
    //   7956: bipush #16
    //   7958: iushr
    //   7959: ixor
    //   7960: i2b
    //   7961: bastore
    //   7962: aload #47
    //   7964: bipush #10
    //   7966: aload #38
    //   7968: iload #50
    //   7970: bipush #8
    //   7972: iushr
    //   7973: sipush #255
    //   7976: iand
    //   7977: baload
    //   7978: iload #49
    //   7980: bipush #8
    //   7982: iushr
    //   7983: ixor
    //   7984: i2b
    //   7985: bastore
    //   7986: aload #47
    //   7988: bipush #11
    //   7990: aload #38
    //   7992: iload #53
    //   7994: sipush #255
    //   7997: iand
    //   7998: baload
    //   7999: iload #49
    //   8001: ixor
    //   8002: i2b
    //   8003: bastore
    //   8004: aload #31
    //   8006: iload #48
    //   8008: iconst_3
    //   8009: iadd
    //   8010: iaload
    //   8011: istore #49
    //   8013: aload #47
    //   8015: bipush #12
    //   8017: aload #38
    //   8019: iload #53
    //   8021: bipush #24
    //   8023: iushr
    //   8024: baload
    //   8025: iload #49
    //   8027: bipush #24
    //   8029: iushr
    //   8030: ixor
    //   8031: i2b
    //   8032: bastore
    //   8033: aload #47
    //   8035: bipush #13
    //   8037: aload #38
    //   8039: iload #52
    //   8041: bipush #16
    //   8043: iushr
    //   8044: sipush #255
    //   8047: iand
    //   8048: baload
    //   8049: iload #49
    //   8051: bipush #16
    //   8053: iushr
    //   8054: ixor
    //   8055: i2b
    //   8056: bastore
    //   8057: aload #47
    //   8059: bipush #14
    //   8061: aload #38
    //   8063: iload #51
    //   8065: bipush #8
    //   8067: iushr
    //   8068: sipush #255
    //   8071: iand
    //   8072: baload
    //   8073: iload #49
    //   8075: bipush #8
    //   8077: iushr
    //   8078: ixor
    //   8079: i2b
    //   8080: bastore
    //   8081: aload #47
    //   8083: bipush #15
    //   8085: aload #38
    //   8087: iload #50
    //   8089: sipush #255
    //   8092: iand
    //   8093: baload
    //   8094: iload #49
    //   8096: ixor
    //   8097: i2b
    //   8098: bastore
    //   8099: iconst_0
    //   8100: istore #54
    //   8102: iload #54
    //   8104: bipush #16
    //   8106: if_icmpge -> 8132
    //   8109: aload #44
    //   8111: iload #54
    //   8113: iload #45
    //   8115: bipush #16
    //   8117: imul
    //   8118: iadd
    //   8119: aload #47
    //   8121: iload #54
    //   8123: baload
    //   8124: bastore
    //   8125: iinc #54, 1
    //   8128: iload_2
    //   8129: ifne -> 8102
    //   8132: iinc #45, 1
    //   8135: iload_2
    //   8136: ifne -> 7217
    //   8139: aload #44
    //   8141: arraylength
    //   8142: ifle -> 8223
    //   8145: aload #44
    //   8147: aload #44
    //   8149: arraylength
    //   8150: iconst_1
    //   8151: isub
    //   8152: baload
    //   8153: istore #45
    //   8155: iload #45
    //   8157: bipush #16
    //   8159: if_icmple -> 8170
    //   8162: aload #44
    //   8164: astore #36
    //   8166: iload_2
    //   8167: ifne -> 8223
    //   8170: aload #44
    //   8172: arraylength
    //   8173: iload #45
    //   8175: isub
    //   8176: newarray byte
    //   8178: astore #36
    //   8180: iconst_0
    //   8181: istore #46
    //   8183: iload #46
    //   8185: aload #36
    //   8187: arraylength
    //   8188: if_icmpge -> 8223
    //   8191: iload #46
    //   8193: aload #44
    //   8195: arraylength
    //   8196: if_icmpge -> 8223
    //   8199: aload #36
    //   8201: iload #46
    //   8203: aload #44
    //   8205: iload #46
    //   8207: baload
    //   8208: bastore
    //   8209: iinc #46, 1
    //   8212: iload_2
    //   8213: ifne -> 8183
    //   8216: goto -> 8223
    //   8219: invokestatic a : (Ljava/lang/Throwable;)Ljava/lang/Throwable;
    //   8222: athrow
    //   8223: aload #36
    //   8225: astore #8
    //   8227: sipush #-5385
    //   8230: new java/math/BigInteger
    //   8233: dup
    //   8234: aload #8
    //   8236: invokespecial <init> : ([B)V
    //   8239: invokevirtual abs : ()Ljava/math/BigInteger;
    //   8242: putstatic burp/Zt7x.ZE : Ljava/lang/Object;
    //   8245: sipush #25257
    //   8248: invokestatic a : (II)Ljava/lang/String;
    //   8251: iconst_1
    //   8252: ldc burp/Zsk2
    //   8254: invokevirtual getClassLoader : ()Ljava/lang/ClassLoader;
    //   8257: invokestatic forName : (Ljava/lang/String;ZLjava/lang/ClassLoader;)Ljava/lang/Class;
    //   8260: invokevirtual getDeclaredFields : ()[Ljava/lang/reflect/Field;
    //   8263: astore #4
    //   8265: aload #4
    //   8267: arraylength
    //   8268: istore #5
    //   8270: iconst_0
    //   8271: istore #6
    //   8273: iload #6
    //   8275: iload #5
    //   8277: if_icmpge -> 8415
    //   8280: aload #4
    //   8282: iload #6
    //   8284: aaload
    //   8285: astore #7
    //   8287: aload #7
    //   8289: invokevirtual getModifiers : ()I
    //   8292: invokestatic isStatic : (I)Z
    //   8295: ifne -> 8305
    //   8298: goto -> 8408
    //   8301: invokestatic a : (Ljava/lang/Throwable;)Ljava/lang/Throwable;
    //   8304: athrow
    //   8305: aload #7
    //   8307: invokevirtual getType : ()Ljava/lang/Class;
    //   8310: astore #8
    //   8312: aload #8
    //   8314: ifnull -> 8395
    //   8317: aload #8
    //   8319: invokevirtual isPrimitive : ()Z
    //   8322: ifne -> 8395
    //   8325: goto -> 8332
    //   8328: invokestatic a : (Ljava/lang/Throwable;)Ljava/lang/Throwable;
    //   8331: athrow
    //   8332: aload #8
    //   8334: invokevirtual getPackage : ()Ljava/lang/Package;
    //   8337: ifnull -> 8395
    //   8340: goto -> 8347
    //   8343: invokestatic a : (Ljava/lang/Throwable;)Ljava/lang/Throwable;
    //   8346: athrow
    //   8347: aload #8
    //   8349: invokevirtual getPackage : ()Ljava/lang/Package;
    //   8352: invokevirtual getName : ()Ljava/lang/String;
    //   8355: ifnull -> 8395
    //   8358: goto -> 8365
    //   8361: invokestatic a : (Ljava/lang/Throwable;)Ljava/lang/Throwable;
    //   8364: athrow
    //   8365: aload #8
    //   8367: invokevirtual getPackage : ()Ljava/lang/Package;
    //   8370: invokevirtual getName : ()Ljava/lang/String;
    //   8373: sipush #-5390
    //   8376: sipush #10959
    //   8379: invokestatic a : (II)Ljava/lang/String;
    //   8382: invokevirtual startsWith : (Ljava/lang/String;)Z
    //   8385: ifne -> 8395
    //   8388: goto -> 8395
    //   8391: invokestatic a : (Ljava/lang/Throwable;)Ljava/lang/Throwable;
    //   8394: athrow
    //   8395: aload #7
    //   8397: iconst_1
    //   8398: invokevirtual setAccessible : (Z)V
    //   8401: aload #7
    //   8403: aconst_null
    //   8404: invokevirtual get : (Ljava/lang/Object;)Ljava/lang/Object;
    //   8407: pop
    //   8408: iinc #6, 1
    //   8411: iload_2
    //   8412: ifne -> 8273
    //   8415: sipush #-5378
    //   8418: sipush #-21228
    //   8421: invokestatic a : (II)Ljava/lang/String;
    //   8424: invokestatic forName : (Ljava/lang/String;)Ljava/lang/Class;
    //   8427: invokevirtual getDeclaredMethods : ()[Ljava/lang/reflect/Method;
    //   8430: astore #4
    //   8432: aload #4
    //   8434: arraylength
    //   8435: istore #5
    //   8437: iconst_0
    //   8438: istore #6
    //   8440: iload #6
    //   8442: iload #5
    //   8444: if_icmpge -> 8577
    //   8447: aload #4
    //   8449: iload #6
    //   8451: aaload
    //   8452: astore #7
    //   8454: aload #7
    //   8456: invokevirtual getParameterTypes : ()[Ljava/lang/Class;
    //   8459: pop
    //   8460: aload #7
    //   8462: invokevirtual getModifiers : ()I
    //   8465: invokestatic isStatic : (I)Z
    //   8468: ifeq -> 8563
    //   8471: aload #7
    //   8473: invokevirtual getParameterTypes : ()[Ljava/lang/Class;
    //   8476: arraylength
    //   8477: iconst_2
    //   8478: if_icmpne -> 8563
    //   8481: goto -> 8488
    //   8484: invokestatic a : (Ljava/lang/Throwable;)Ljava/lang/Throwable;
    //   8487: athrow
    //   8488: aload #7
    //   8490: invokevirtual getReturnType : ()Ljava/lang/Class;
    //   8493: getstatic java/lang/Void.TYPE : Ljava/lang/Class;
    //   8496: invokevirtual equals : (Ljava/lang/Object;)Z
    //   8499: ifeq -> 8563
    //   8502: goto -> 8509
    //   8505: invokestatic a : (Ljava/lang/Throwable;)Ljava/lang/Throwable;
    //   8508: athrow
    //   8509: aload #7
    //   8511: iconst_1
    //   8512: invokevirtual setAccessible : (Z)V
    //   8515: aload #7
    //   8517: aconst_null
    //   8518: iconst_2
    //   8519: anewarray java/lang/Object
    //   8522: dup
    //   8523: iconst_0
    //   8524: aload_0
    //   8525: aastore
    //   8526: dup
    //   8527: iconst_1
    //   8528: aload_1
    //   8529: ifnonnull -> 8547
    //   8532: goto -> 8539
    //   8535: invokestatic a : (Ljava/lang/Throwable;)Ljava/lang/Throwable;
    //   8538: athrow
    //   8539: aload_1
    //   8540: goto -> 8554
    //   8543: invokestatic a : (Ljava/lang/Throwable;)Ljava/lang/Throwable;
    //   8546: athrow
    //   8547: aload_1
    //   8548: checkcast [B
    //   8551: invokevirtual clone : ()Ljava/lang/Object;
    //   8554: aastore
    //   8555: invokevirtual invoke : (Ljava/lang/Object;[Ljava/lang/Object;)Ljava/lang/Object;
    //   8558: pop
    //   8559: iload_2
    //   8560: ifne -> 8577
    //   8563: iinc #6, 1
    //   8566: iload_2
    //   8567: ifne -> 8440
    //   8570: goto -> 8577
    //   8573: invokestatic a : (Ljava/lang/Throwable;)Ljava/lang/Throwable;
    //   8576: athrow
    //   8577: getstatic burp/Zlid.Zx : Ljava/lang/Object;
    //   8580: checkcast java/math/BigInteger
    //   8583: invokevirtual intValue : ()I
    //   8586: i2l
    //   8587: invokestatic currentTimeMillis : ()J
    //   8590: ladd
    //   8591: getstatic burp/Zzc9.ZZ : Ljava/lang/Object;
    //   8594: checkcast java/math/BigInteger
    //   8597: invokevirtual intValue : ()I
    //   8600: i2l
    //   8601: lcmp
    //   8602: ifge -> 8940
    //   8605: sipush #-5387
    //   8608: sipush #-19309
    //   8611: invokestatic a : (II)Ljava/lang/String;
    //   8614: iconst_1
    //   8615: ldc burp/Zkvr
    //   8617: invokevirtual getClassLoader : ()Ljava/lang/ClassLoader;
    //   8620: invokestatic forName : (Ljava/lang/String;ZLjava/lang/ClassLoader;)Ljava/lang/Class;
    //   8623: invokevirtual getDeclaredFields : ()[Ljava/lang/reflect/Field;
    //   8626: astore #4
    //   8628: aload #4
    //   8630: arraylength
    //   8631: istore #5
    //   8633: iconst_0
    //   8634: istore #6
    //   8636: iload #6
    //   8638: iload #5
    //   8640: if_icmpge -> 8778
    //   8643: aload #4
    //   8645: iload #6
    //   8647: aaload
    //   8648: astore #7
    //   8650: aload #7
    //   8652: invokevirtual getModifiers : ()I
    //   8655: invokestatic isStatic : (I)Z
    //   8658: ifne -> 8668
    //   8661: goto -> 8771
    //   8664: invokestatic a : (Ljava/lang/Throwable;)Ljava/lang/Throwable;
    //   8667: athrow
    //   8668: aload #7
    //   8670: invokevirtual getType : ()Ljava/lang/Class;
    //   8673: astore #8
    //   8675: aload #8
    //   8677: ifnull -> 8758
    //   8680: aload #8
    //   8682: invokevirtual isPrimitive : ()Z
    //   8685: ifne -> 8758
    //   8688: goto -> 8695
    //   8691: invokestatic a : (Ljava/lang/Throwable;)Ljava/lang/Throwable;
    //   8694: athrow
    //   8695: aload #8
    //   8697: invokevirtual getPackage : ()Ljava/lang/Package;
    //   8700: ifnull -> 8758
    //   8703: goto -> 8710
    //   8706: invokestatic a : (Ljava/lang/Throwable;)Ljava/lang/Throwable;
    //   8709: athrow
    //   8710: aload #8
    //   8712: invokevirtual getPackage : ()Ljava/lang/Package;
    //   8715: invokevirtual getName : ()Ljava/lang/String;
    //   8718: ifnull -> 8758
    //   8721: goto -> 8728
    //   8724: invokestatic a : (Ljava/lang/Throwable;)Ljava/lang/Throwable;
    //   8727: athrow
    //   8728: aload #8
    //   8730: invokevirtual getPackage : ()Ljava/lang/Package;
    //   8733: invokevirtual getName : ()Ljava/lang/String;
    //   8736: sipush #-5389
    //   8739: sipush #-14969
    //   8742: invokestatic a : (II)Ljava/lang/String;
    //   8745: invokevirtual startsWith : (Ljava/lang/String;)Z
    //   8748: ifne -> 8758
    //   8751: goto -> 8758
    //   8754: invokestatic a : (Ljava/lang/Throwable;)Ljava/lang/Throwable;
    //   8757: athrow
    //   8758: aload #7
    //   8760: iconst_1
    //   8761: invokevirtual setAccessible : (Z)V
    //   8764: aload #7
    //   8766: aconst_null
    //   8767: invokevirtual get : (Ljava/lang/Object;)Ljava/lang/Object;
    //   8770: pop
    //   8771: iinc #6, 1
    //   8774: iload_2
    //   8775: ifne -> 8636
    //   8778: sipush #-5379
    //   8781: sipush #-30217
    //   8784: invokestatic a : (II)Ljava/lang/String;
    //   8787: invokestatic forName : (Ljava/lang/String;)Ljava/lang/Class;
    //   8790: invokevirtual getDeclaredMethods : ()[Ljava/lang/reflect/Method;
    //   8793: astore #4
    //   8795: aload #4
    //   8797: arraylength
    //   8798: istore #5
    //   8800: iconst_0
    //   8801: istore #6
    //   8803: iload #6
    //   8805: iload #5
    //   8807: if_icmpge -> 8940
    //   8810: aload #4
    //   8812: iload #6
    //   8814: aaload
    //   8815: astore #7
    //   8817: aload #7
    //   8819: invokevirtual getParameterTypes : ()[Ljava/lang/Class;
    //   8822: pop
    //   8823: aload #7
    //   8825: invokevirtual getModifiers : ()I
    //   8828: invokestatic isStatic : (I)Z
    //   8831: ifeq -> 8926
    //   8834: aload #7
    //   8836: invokevirtual getParameterTypes : ()[Ljava/lang/Class;
    //   8839: arraylength
    //   8840: iconst_2
    //   8841: if_icmpne -> 8926
    //   8844: goto -> 8851
    //   8847: invokestatic a : (Ljava/lang/Throwable;)Ljava/lang/Throwable;
    //   8850: athrow
    //   8851: aload #7
    //   8853: invokevirtual getReturnType : ()Ljava/lang/Class;
    //   8856: getstatic java/lang/Void.TYPE : Ljava/lang/Class;
    //   8859: invokevirtual equals : (Ljava/lang/Object;)Z
    //   8862: ifeq -> 8926
    //   8865: goto -> 8872
    //   8868: invokestatic a : (Ljava/lang/Throwable;)Ljava/lang/Throwable;
    //   8871: athrow
    //   8872: aload #7
    //   8874: iconst_1
    //   8875: invokevirtual setAccessible : (Z)V
    //   8878: aload #7
    //   8880: aconst_null
    //   8881: iconst_2
    //   8882: anewarray java/lang/Object
    //   8885: dup
    //   8886: iconst_0
    //   8887: aload_0
    //   8888: aastore
    //   8889: dup
    //   8890: iconst_1
    //   8891: aload_1
    //   8892: ifnonnull -> 8910
    //   8895: goto -> 8902
    //   8898: invokestatic a : (Ljava/lang/Throwable;)Ljava/lang/Throwable;
    //   8901: athrow
    //   8902: aload_1
    //   8903: goto -> 8917
    //   8906: invokestatic a : (Ljava/lang/Throwable;)Ljava/lang/Throwable;
    //   8909: athrow
    //   8910: aload_1
    //   8911: checkcast [B
    //   8914: invokevirtual clone : ()Ljava/lang/Object;
    //   8917: aastore
    //   8918: invokevirtual invoke : (Ljava/lang/Object;[Ljava/lang/Object;)Ljava/lang/Object;
    //   8921: pop
    //   8922: iload_2
    //   8923: ifne -> 8940
    //   8926: iinc #6, 1
    //   8929: iload_2
    //   8930: ifne -> 8803
    //   8933: goto -> 8940
    //   8936: invokestatic a : (Ljava/lang/Throwable;)Ljava/lang/Throwable;
    //   8939: athrow
    //   8940: getstatic burp/Zti4.ZI : Ljava/lang/String;
    //   8943: getstatic burp/Zrwp.Zk : Ljava/lang/Object;
    //   8946: checkcast java/math/BigInteger
    //   8949: invokevirtual intValue : ()I
    //   8952: bipush #32
    //   8954: irem
    //   8955: invokestatic abs : (I)I
    //   8958: invokevirtual charAt : (I)C
    //   8961: getstatic burp/Zmt_.ZH : Ljava/lang/String;
    //   8964: getstatic burp/Zrm6.Z_ : Ljava/lang/Object;
    //   8967: checkcast java/math/BigInteger
    //   8970: invokevirtual intValue : ()I
    //   8973: bipush #32
    //   8975: irem
    //   8976: invokestatic abs : (I)I
    //   8979: invokevirtual charAt : (I)C
    //   8982: if_icmpgt -> 9089
    //   8985: getstatic burp/Zedu.ZD : Ljava/lang/String;
    //   8988: getstatic burp/Zbow.ZS : Ljava/lang/Object;
    //   8991: checkcast java/math/BigInteger
    //   8994: invokevirtual intValue : ()I
    //   8997: bipush #32
    //   8999: irem
    //   9000: invokestatic abs : (I)I
    //   9003: invokevirtual charAt : (I)C
    //   9006: getstatic burp/Zld5.ZO : Ljava/lang/String;
    //   9009: getstatic burp/Zg0q.Zf : Ljava/lang/Object;
    //   9012: checkcast java/math/BigInteger
    //   9015: invokevirtual intValue : ()I
    //   9018: bipush #32
    //   9020: irem
    //   9021: invokestatic abs : (I)I
    //   9024: invokevirtual charAt : (I)C
    //   9027: if_icmple -> 9089
    //   9030: goto -> 9037
    //   9033: invokestatic a : (Ljava/lang/Throwable;)Ljava/lang/Throwable;
    //   9036: athrow
    //   9037: getstatic burp/Zd9.Ze : Ljava/lang/String;
    //   9040: getstatic burp/Zsjc.ZX : Ljava/lang/Object;
    //   9043: checkcast java/math/BigInteger
    //   9046: invokevirtual intValue : ()I
    //   9049: bipush #32
    //   9051: irem
    //   9052: invokestatic abs : (I)I
    //   9055: invokevirtual charAt : (I)C
    //   9058: getstatic burp/Zg61.ZX : Ljava/lang/String;
    //   9061: getstatic burp/Zmdi.Zw : Ljava/lang/Object;
    //   9064: checkcast java/math/BigInteger
    //   9067: invokevirtual intValue : ()I
    //   9070: bipush #32
    //   9072: irem
    //   9073: invokestatic abs : (I)I
    //   9076: invokevirtual charAt : (I)C
    //   9079: if_icmpgt -> 9097
    //   9082: goto -> 9089
    //   9085: invokestatic a : (Ljava/lang/Throwable;)Ljava/lang/Throwable;
    //   9088: athrow
    //   9089: iconst_1
    //   9090: goto -> 9098
    //   9093: invokestatic a : (Ljava/lang/Throwable;)Ljava/lang/Throwable;
    //   9096: athrow
    //   9097: iconst_0
    //   9098: ireturn
    //   9099: astore_3
    //   9100: new java/lang/Exception
    //   9103: dup
    //   9104: aload_3
    //   9105: invokevirtual getMessage : ()Ljava/lang/String;
    //   9108: invokespecial <init> : (Ljava/lang/String;)V
    //   9111: athrow
    // Exception table:
    //   from	to	target	type
    //   4	9098	9099	java/lang/Throwable
    //   3306	3331	3331	java/lang/Throwable
    //   4294	4320	4320	java/lang/Throwable
    //   4385	4558	4561	java/lang/Throwable
    //   4528	4595	4598	java/lang/Throwable
    //   4565	4632	4635	java/lang/Throwable
    //   4602	4669	4672	java/lang/Throwable
    //   4639	4706	4709	java/lang/Throwable
    //   4676	4743	4746	java/lang/Throwable
    //   4713	4780	4783	java/lang/Throwable
    //   4750	4817	4820	java/lang/Throwable
    //   4787	4854	4857	java/lang/Throwable
    //   4824	4891	4894	java/lang/Throwable
    //   4861	4928	4931	java/lang/Throwable
    //   4898	4965	4968	java/lang/Throwable
    //   4935	5002	5005	java/lang/Throwable
    //   4972	5039	5042	java/lang/Throwable
    //   5009	5076	5079	java/lang/Throwable
    //   5046	5113	5116	java/lang/Throwable
    //   5083	5150	5153	java/lang/Throwable
    //   5120	5187	5190	java/lang/Throwable
    //   5157	5224	5227	java/lang/Throwable
    //   5194	5261	5264	java/lang/Throwable
    //   5231	5298	5301	java/lang/Throwable
    //   5268	5335	5338	java/lang/Throwable
    //   5305	5372	5375	java/lang/Throwable
    //   5342	5409	5412	java/lang/Throwable
    //   5379	5446	5449	java/lang/Throwable
    //   5416	5483	5486	java/lang/Throwable
    //   5453	5520	5523	java/lang/Throwable
    //   5490	5557	5560	java/lang/Throwable
    //   5527	5594	5597	java/lang/Throwable
    //   5564	5631	5634	java/lang/Throwable
    //   5601	5668	5671	java/lang/Throwable
    //   5638	5701	5704	java/lang/Throwable
    //   5870	5885	5885	java/lang/Throwable
    //   6887	6913	6913	java/lang/Throwable
    //   6994	7009	7009	java/lang/Throwable
    //   8191	8216	8219	java/lang/Throwable
    //   8287	8301	8301	java/lang/Throwable
    //   8312	8325	8328	java/lang/Throwable
    //   8317	8340	8343	java/lang/Throwable
    //   8332	8358	8361	java/lang/Throwable
    //   8347	8388	8391	java/lang/Throwable
    //   8454	8481	8484	java/lang/Throwable
    //   8471	8502	8505	java/lang/Throwable
    //   8488	8532	8535	java/lang/Throwable
    //   8509	8543	8543	java/lang/Throwable
    //   8554	8570	8573	java/lang/Throwable
    //   8650	8664	8664	java/lang/Throwable
    //   8675	8688	8691	java/lang/Throwable
    //   8680	8703	8706	java/lang/Throwable
    //   8695	8721	8724	java/lang/Throwable
    //   8710	8751	8754	java/lang/Throwable
    //   8817	8844	8847	java/lang/Throwable
    //   8834	8865	8868	java/lang/Throwable
    //   8851	8895	8898	java/lang/Throwable
    //   8872	8906	8906	java/lang/Throwable
    //   8917	8933	8936	java/lang/Throwable
    //   8940	9030	9033	java/lang/Throwable
    //   8985	9082	9085	java/lang/Throwable
    //   9037	9093	9093	java/lang/Throwable
  }
  
  static void Za(Object paramObject) {
    Zxt7.Zi = a(-5380, -23814);
    Zxt7.ZV = new BigInteger(a(-5382, -12789));
    boolean bool = Zt2e.ZK();
    try {
      try {
        if (Ze25.Zp.charAt(Math.abs(((BigInteger)Zti4.Zi).intValue() % 32)) <= Zrov.ZU.charAt(Math.abs(((BigInteger)Zgis.ZV).intValue() % 32))) {
          try {
            Zbnk.Z_(Class.forName(a(-5386, -27562)));
            if (bool)
              Zbqk.Zm(Class.forName(a(-5377, 15611))); 
          } catch (Throwable throwable) {
            throw a(null);
          } 
          return;
        } 
      } catch (Throwable throwable) {
        throw a(null);
      } 
      Zbqk.Zm(Class.forName(a(-5377, 15611)));
    } catch (Throwable throwable) {}
  }
  
  static void ZA(Object[] paramArrayOfObject, Object paramObject) throws Throwable {}
  
  static {
    // Byte code:
    //   0: bipush #15
    //   2: anewarray java/lang/String
    //   5: astore #5
    //   7: iconst_0
    //   8: istore_3
    //   9: ldc 'BEah;rUkc0\\bs;f\\t \_M\\t\\n&{??_;B>/Y)@>O@[o <L&scv7mc[\\bK"V\\tp\\tEt-'
    //   11: dup
    //   12: astore_2
    //   13: invokevirtual length : ()I
    //   16: istore #4
    //   18: bipush #32
    //   20: istore_1
    //   21: iconst_m1
    //   22: istore_0
    //   23: bipush #61
    //   25: iinc #0, 1
    //   28: aload_2
    //   29: iload_0
    //   30: dup
    //   31: iload_1
    //   32: iadd
    //   33: invokevirtual substring : (II)Ljava/lang/String;
    //   36: iconst_m1
    //   37: goto -> 144
    //   40: aload #5
    //   42: swap
    //   43: iload_3
    //   44: iinc #3, 1
    //   47: swap
    //   48: aastore
    //   49: iload_0
    //   50: iload_1
    //   51: iadd
    //   52: dup
    //   53: istore_0
    //   54: iload #4
    //   56: if_icmpge -> 68
    //   59: aload_2
    //   60: iload_0
    //   61: invokevirtual charAt : (I)C
    //   64: istore_1
    //   65: goto -> 23
    //   68: ldc '??MNw aBe+!b+&\\tc[oDiJ'E7[OKD>\\b>QbF:'
    //   70: dup
    //   71: astore_2
    //   72: invokevirtual length : ()I
    //   75: istore #4
    //   77: sipush #128
    //   80: istore_1
    //   81: iconst_m1
    //   82: istore_0
    //   83: bipush #87
    //   85: iinc #0, 1
    //   88: aload_2
    //   89: iload_0
    //   90: dup
    //   91: iload_1
    //   92: iadd
    //   93: invokevirtual substring : (II)Ljava/lang/String;
    //   96: iconst_0
    //   97: goto -> 144
    //   100: aload #5
    //   102: swap
    //   103: iload_3
    //   104: iinc #3, 1
    //   107: swap
    //   108: aastore
    //   109: iload_0
    //   110: iload_1
    //   111: iadd
    //   112: dup
    //   113: istore_0
    //   114: iload #4
    //   116: if_icmpge -> 128
    //   119: aload_2
    //   120: iload_0
    //   121: invokevirtual charAt : (I)C
    //   124: istore_1
    //   125: goto -> 83
    //   128: aload #5
    //   130: putstatic burp/Zgk9.a : [Ljava/lang/String;
    //   133: bipush #15
    //   135: anewarray java/lang/String
    //   138: putstatic burp/Zgk9.b : [Ljava/lang/String;
    //   141: goto -> 300
    //   144: dup_x2
    //   145: pop
    //   146: invokevirtual toCharArray : ()[C
    //   149: dup_x1
    //   150: arraylength
    //   151: dup_x2
    //   152: pop
    //   153: iconst_0
    //   154: istore #6
    //   156: dup2_x1
    //   157: pop2
    //   158: dup_x2
    //   159: iconst_1
    //   160: if_icmpgt -> 260
    //   163: dup2
    //   164: swap
    //   165: iload #6
    //   167: dup2_x1
    //   168: caload
    //   169: swap
    //   170: iload #6
    //   172: bipush #7
    //   174: irem
    //   175: tableswitch default -> 242, 0 -> 212, 1 -> 217, 2 -> 222, 3 -> 227, 4 -> 232, 5 -> 237
    //   212: bipush #59
    //   214: goto -> 244
    //   217: bipush #90
    //   219: goto -> 244
    //   222: bipush #67
    //   224: goto -> 244
    //   227: bipush #34
    //   229: goto -> 244
    //   232: bipush #38
    //   234: goto -> 244
    //   237: bipush #46
    //   239: goto -> 244
    //   242: bipush #122
    //   244: ixor
    //   245: ixor
    //   246: i2c
    //   247: castore
    //   248: iinc #6, 1
    //   251: dup
    //   252: ifne -> 260
    //   255: dup2
    //   256: dup_x1
    //   257: goto -> 167
    //   260: dup2_x1
    //   261: pop2
    //   262: dup_x2
    //   263: iload #6
    //   265: if_icmpgt -> 163
    //   268: pop
    //   269: new java/lang/String
    //   272: dup_x1
    //   273: swap
    //   274: invokespecial <init> : ([C)V
    //   277: invokevirtual intern : ()Ljava/lang/String;
    //   280: swap
    //   281: pop
    //   282: swap
    //   283: tableswitch default -> 40, 0 -> 100
    //   300: new java/math/BigInteger
    //   303: dup
    //   304: iconst_1
    //   305: bipush #32
    //   307: newarray byte
    //   309: dup
    //   310: iconst_0
    //   311: bipush #83
    //   313: bastore
    //   314: dup
    //   315: iconst_1
    //   316: bipush #-17
    //   318: bastore
    //   319: dup
    //   320: iconst_2
    //   321: bipush #-7
    //   323: bastore
    //   324: dup
    //   325: iconst_3
    //   326: bipush #-51
    //   328: bastore
    //   329: dup
    //   330: iconst_4
    //   331: bipush #43
    //   333: bastore
    //   334: dup
    //   335: iconst_5
    //   336: bipush #-116
    //   338: bastore
    //   339: dup
    //   340: bipush #6
    //   342: bipush #64
    //   344: bastore
    //   345: dup
    //   346: bipush #7
    //   348: bipush #-69
    //   350: bastore
    //   351: dup
    //   352: bipush #8
    //   354: bipush #-26
    //   356: bastore
    //   357: dup
    //   358: bipush #9
    //   360: bipush #77
    //   362: bastore
    //   363: dup
    //   364: bipush #10
    //   366: bipush #16
    //   368: bastore
    //   369: dup
    //   370: bipush #11
    //   372: bipush #124
    //   374: bastore
    //   375: dup
    //   376: bipush #12
    //   378: bipush #-3
    //   380: bastore
    //   381: dup
    //   382: bipush #13
    //   384: bipush #19
    //   386: bastore
    //   387: dup
    //   388: bipush #14
    //   390: bipush #-127
    //   392: bastore
    //   393: dup
    //   394: bipush #15
    //   396: bipush #-3
    //   398: bastore
    //   399: dup
    //   400: bipush #16
    //   402: bipush #-66
    //   404: bastore
    //   405: dup
    //   406: bipush #17
    //   408: bipush #-128
    //   410: bastore
    //   411: dup
    //   412: bipush #18
    //   414: bipush #42
    //   416: bastore
    //   417: dup
    //   418: bipush #19
    //   420: bipush #-78
    //   422: bastore
    //   423: dup
    //   424: bipush #20
    //   426: bipush #65
    //   428: bastore
    //   429: dup
    //   430: bipush #21
    //   432: bipush #64
    //   434: bastore
    //   435: dup
    //   436: bipush #22
    //   438: bipush #-94
    //   440: bastore
    //   441: dup
    //   442: bipush #23
    //   444: bipush #20
    //   446: bastore
    //   447: dup
    //   448: bipush #24
    //   450: bipush #72
    //   452: bastore
    //   453: dup
    //   454: bipush #25
    //   456: bipush #32
    //   458: bastore
    //   459: dup
    //   460: bipush #26
    //   462: bipush #34
    //   464: bastore
    //   465: dup
    //   466: bipush #27
    //   468: bipush #-11
    //   470: bastore
    //   471: dup
    //   472: bipush #28
    //   474: bipush #-98
    //   476: bastore
    //   477: dup
    //   478: bipush #29
    //   480: bipush #-66
    //   482: bastore
    //   483: dup
    //   484: bipush #30
    //   486: bipush #-25
    //   488: bastore
    //   489: dup
    //   490: bipush #31
    //   492: bipush #92
    //   494: bastore
    //   495: invokespecial <init> : (I[B)V
    //   498: putstatic burp/Zgk9.ZD : Ljava/lang/Object;
    //   501: sipush #-5388
    //   504: sipush #-13733
    //   507: invokestatic a : (II)Ljava/lang/String;
    //   510: putstatic burp/Zgk9.Zf : Ljava/lang/String;
    //   513: return
  }
  
  private static Throwable a(Throwable paramThrowable) {
    return paramThrowable;
  }
  
  private static String a(int paramInt1, int paramInt2) {
    int i = (paramInt1 ^ 0xFFFFEAF4) & 0xFFFF;
    if (b[i] == null) {
      char[] arrayOfChar = a[i].toCharArray();
      switch (arrayOfChar[0] & 0xFF) {
        case 0:
        
        case 1:
        
        case 2:
        
        case 3:
        
        case 4:
        
        case 5:
        
        case 6:
        
        case 7:
        
        case 8:
        
        case 9:
        
        case 10:
        
        case 11:
        
        case 12:
        
        case 13:
        
        case 14:
        
        case 15:
        
        case 16:
        
        case 17:
        
        case 18:
        
        case 19:
        
        case 20:
        
        case 21:
        
        case 22:
        
        case 23:
        
        case 24:
        
        case 25:
        
        case 26:
        
        case 27:
        
        case 28:
        
        case 29:
        
        case 30:
        
        case 31:
        
        case 32:
        
        case 33:
        
        case 34:
        
        case 35:
        
        case 36:
        
        case 37:
        
        case 38:
        
        case 39:
        
        case 40:
        
        case 41:
        
        case 42:
        
        case 43:
        
        case 44:
        
        case 45:
        
        case 46:
        
        case 47:
        
        case 48:
        
        case 49:
        
        case 50:
        
        case 51:
        
        case 52:
        
        case 53:
        
        case 54:
        
        case 55:
        
        case 56:
        
        case 57:
        
        case 58:
        
        case 59:
        
        case 60:
        
        case 61:
        
        case 62:
        
        case 63:
        
        case 64:
        
        case 65:
        
        case 66:
        
        case 67:
        
        case 68:
        
        case 69:
        
        case 70:
        
        case 71:
        
        case 72:
        
        case 73:
        
        case 74:
        
        case 75:
        
        case 76:
        
        case 77:
        
        case 78:
        
        case 79:
        
        case 80:
        
        case 81:
        
        case 82:
        
        case 83:
        
        case 84:
        
        case 85:
        
        case 86:
        
        case 87:
        
        case 88:
        
        case 89:
        
        case 90:
        
        case 91:
        
        case 92:
        
        case 93:
        
        case 94:
        
        case 95:
        
        case 96:
        
        case 97:
        
        case 98:
        
        case 99:
        
        case 100:
        
        case 101:
        
        case 102:
        
        case 103:
        
        case 104:
        
        case 105:
        
        case 106:
        
        case 107:
        
        case 108:
        
        case 109:
        
        case 110:
        
        case 111:
        
        case 112:
        
        case 113:
        
        case 114:
        
        case 115:
        
        case 116:
        
        case 117:
        
        case 118:
        
        case 119:
        
        case 120:
        
        case 121:
        
        case 122:
        
        case 123:
        
        case 124:
        
        case 125:
        
        case 126:
        
        case 127:
        
        case 128:
        
        case 129:
        
        case 130:
        
        case 131:
        
        case 132:
        
        case 133:
        
        case 134:
        
        case 135:
        
        case 136:
        
        case 137:
        
        case 138:
        
        case 139:
        
        case 140:
        
        case 141:
        
        case 142:
        
        case 143:
        
        case 144:
        
        case 145:
        
        case 146:
        
        case 147:
        
        case 148:
        
        case 149:
        
        case 150:
        
        case 151:
        
        case 152:
        
        case 153:
        
        case 154:
        
        case 155:
        
        case 156:
        
        case 157:
        
        case 158:
        
        case 159:
        
        case 160:
        
        case 161:
        
        case 162:
        
        case 163:
        
        case 164:
        
        case 165:
        
        case 166:
        
        case 167:
        
        case 168:
        
        case 169:
        
        case 170:
        
        case 171:
        
        case 172:
        
        case 173:
        
        case 174:
        
        case 175:
        
        case 176:
        
        case 177:
        
        case 178:
        
        case 179:
        
        case 180:
        
        case 181:
        
        case 182:
        
        case 183:
        
        case 184:
        
        case 185:
        
        case 186:
        
        case 187:
        
        case 188:
        
        case 189:
        
        case 190:
        
        case 191:
        
        case 192:
        
        case 193:
        
        case 194:
        
        case 195:
        
        case 196:
        
        case 197:
        
        case 198:
        
        case 199:
        
        case 200:
        
        case 201:
        
        case 202:
        
        case 203:
        
        case 204:
        
        case 205:
        
        case 206:
        
        case 207:
        
        case 208:
        
        case 209:
        
        case 210:
        
        case 211:
        
        case 212:
        
        case 213:
        
        case 214:
        
        case 215:
        
        case 216:
        
        case 217:
        
        case 218:
        
        case 219:
        
        case 220:
        
        case 221:
        
        case 222:
        
        case 223:
        
        case 224:
        
        case 225:
        
        case 226:
        
        case 227:
        
        case 228:
        
        case 229:
        
        case 230:
        
        case 231:
        
        case 232:
        
        case 233:
        
        case 234:
        
        case 235:
        
        case 236:
        
        case 237:
        
        case 238:
        
        case 239:
        
        case 240:
        
        case 241:
        
        case 242:
        
        case 243:
        
        case 244:
        
        case 245:
        
        case 246:
        
        case 247:
        
        case 248:
        
        case 249:
        
        case 250:
        
        case 251:
        
        case 252:
        
        case 253:
        
        case 254:
        
        default:
          break;
      } 
      byte b1 = 52;
      int j = (paramInt2 & 0xFF) - b1;
      if (j < 0)
        j += 256; 
      int k = ((paramInt2 & 0xFFFF) >>> 8) - b1;
      if (k < 0)
        k += 256; 
      for (byte b2 = 0; b2 < arrayOfChar.length; b2++) {
        int m = b2 % 2;
        if (m == 0) {
          arrayOfChar[b2] = (char)(arrayOfChar[b2] ^ j);
          j = ((j >>> 3 | j << 5) ^ arrayOfChar[b2]) & 0xFF;
        } else {
          arrayOfChar[b2] = (char)(arrayOfChar[b2] ^ k);
          k = ((k >>> 3 | k << 5) ^ arrayOfChar[b2]) & 0xFF;
        } 
      } 
      b[i] = (new String(arrayOfChar)).intern();
    } 
    return b[i];
  }
}


/* Location:              C:\Program Files\BurpSuitePro\burpsuite_pro.jar!\burp\Zgk9.class
 * Java compiler version: 21 (65.0)
 * JD-Core Version:       1.1.3
 */