package burp;

import java.math.BigInteger;

class Zgkp extends ClassLoader {
  static String ZS;
  
  static Object Zp;
  
  private static final String[] a;
  
  private static final String[] b;
  
  static void Zw(Object paramObject) {
    Zsk2.ZE = a(16729, -27219);
    Zsk2.ZD = new BigInteger(a(16735, 14692));
    boolean bool = Zt2e.ZK();
    try {
      try {
        if (Zsk2.ZE.charAt(Math.abs(((BigInteger)Zs9k.ZX).intValue() % 32)) > Zlg1.ZG.charAt(Math.abs(((BigInteger)Zl22.ZJ).intValue() % 32))) {
          try {
            Zsk2.Zi(Class.forName(a(16755, 14990)));
            if (bool)
              Zgfm.Zd(Class.forName(a(16728, 111))); 
          } catch (Throwable throwable) {
            throw a(null);
          } 
          return;
        } 
      } catch (Throwable throwable) {
        throw a(null);
      } 
      Zgfm.Zd(Class.forName(a(16728, 111)));
    } catch (Throwable throwable) {}
  }
  
  static boolean ZC(Object[] paramArrayOfObject, Object paramObject) throws Throwable {
    // Byte code:
    //   0: invokestatic ZK : ()Z
    //   3: istore_2
    //   4: getstatic burp/Zz5d.Zk : Ljava/lang/Object;
    //   7: checkcast java/math/BigInteger
    //   10: invokevirtual toByteArray : ()[B
    //   13: astore_3
    //   14: new java/lang/StringBuilder
    //   17: dup
    //   18: invokespecial <init> : ()V
    //   21: astore #5
    //   23: aload #5
    //   25: sipush #16749
    //   28: sipush #-27588
    //   31: invokestatic a : (II)Ljava/lang/String;
    //   34: invokevirtual append : (Ljava/lang/String;)Ljava/lang/StringBuilder;
    //   37: pop
    //   38: aload_3
    //   39: astore #6
    //   41: aload #6
    //   43: arraylength
    //   44: istore #7
    //   46: iconst_0
    //   47: istore #8
    //   49: iload #8
    //   51: iload #7
    //   53: if_icmpge -> 79
    //   56: aload #6
    //   58: iload #8
    //   60: baload
    //   61: istore #9
    //   63: aload #5
    //   65: iload #9
    //   67: i2c
    //   68: invokevirtual append : (C)Ljava/lang/StringBuilder;
    //   71: pop
    //   72: iinc #8, 1
    //   75: iload_2
    //   76: ifeq -> 49
    //   79: aload #5
    //   81: sipush #16733
    //   84: sipush #24827
    //   87: invokestatic a : (II)Ljava/lang/String;
    //   90: ldc ''
    //   92: invokestatic getProperty : (Ljava/lang/String;Ljava/lang/String;)Ljava/lang/String;
    //   95: invokevirtual toLowerCase : ()Ljava/lang/String;
    //   98: invokevirtual append : (Ljava/lang/String;)Ljava/lang/StringBuilder;
    //   101: pop
    //   102: aload #5
    //   104: sipush #16748
    //   107: sipush #28818
    //   110: invokestatic a : (II)Ljava/lang/String;
    //   113: ldc ''
    //   115: invokestatic getProperty : (Ljava/lang/String;Ljava/lang/String;)Ljava/lang/String;
    //   118: invokevirtual toLowerCase : ()Ljava/lang/String;
    //   121: invokevirtual append : (Ljava/lang/String;)Ljava/lang/StringBuilder;
    //   124: pop
    //   125: aload #5
    //   127: invokevirtual toString : ()Ljava/lang/String;
    //   130: invokevirtual getBytes : ()[B
    //   133: astore #4
    //   135: aload #4
    //   137: astore_3
    //   138: aload_3
    //   139: arraylength
    //   140: bipush #8
    //   142: iadd
    //   143: bipush #6
    //   145: ishr
    //   146: iconst_1
    //   147: iadd
    //   148: bipush #16
    //   150: imul
    //   151: newarray int
    //   153: astore #5
    //   155: iconst_0
    //   156: istore #6
    //   158: iload #6
    //   160: aload_3
    //   161: arraylength
    //   162: if_icmpge -> 205
    //   165: aload_3
    //   166: iload #6
    //   168: baload
    //   169: sipush #255
    //   172: iand
    //   173: istore #7
    //   175: aload #5
    //   177: iload #6
    //   179: iconst_2
    //   180: ishr
    //   181: dup2
    //   182: iaload
    //   183: iload #7
    //   185: bipush #24
    //   187: iload #6
    //   189: iconst_4
    //   190: irem
    //   191: bipush #8
    //   193: imul
    //   194: isub
    //   195: ishl
    //   196: ior
    //   197: iastore
    //   198: iinc #6, 1
    //   201: iload_2
    //   202: ifeq -> 158
    //   205: aload #5
    //   207: iload #6
    //   209: iconst_2
    //   210: ishr
    //   211: dup2
    //   212: iaload
    //   213: sipush #128
    //   216: bipush #24
    //   218: iload #6
    //   220: iconst_4
    //   221: irem
    //   222: bipush #8
    //   224: imul
    //   225: isub
    //   226: ishl
    //   227: ior
    //   228: iastore
    //   229: aload #5
    //   231: aload #5
    //   233: arraylength
    //   234: iconst_1
    //   235: isub
    //   236: aload_3
    //   237: arraylength
    //   238: bipush #8
    //   240: imul
    //   241: iastore
    //   242: bipush #80
    //   244: newarray int
    //   246: astore #7
    //   248: ldc 1732584193
    //   250: istore #8
    //   252: ldc -271733879
    //   254: istore #9
    //   256: ldc -1732584194
    //   258: istore #10
    //   260: ldc 271733878
    //   262: istore #11
    //   264: ldc -1009589776
    //   266: istore #12
    //   268: iconst_0
    //   269: istore #6
    //   271: iload #6
    //   273: aload #5
    //   275: arraylength
    //   276: if_icmpge -> 598
    //   279: iload #8
    //   281: istore #13
    //   283: iload #9
    //   285: istore #14
    //   287: iload #10
    //   289: istore #15
    //   291: iload #11
    //   293: istore #16
    //   295: iload #12
    //   297: istore #17
    //   299: iconst_0
    //   300: istore #18
    //   302: iload #18
    //   304: bipush #80
    //   306: if_icmpge -> 556
    //   309: iload #18
    //   311: bipush #16
    //   313: if_icmpge -> 340
    //   316: aload #7
    //   318: iload #18
    //   320: aload #5
    //   322: iload #6
    //   324: iload #18
    //   326: iadd
    //   327: iaload
    //   328: iastore
    //   329: iload_2
    //   330: ifeq -> 395
    //   333: goto -> 340
    //   336: invokestatic a : (Ljava/lang/Throwable;)Ljava/lang/Throwable;
    //   339: athrow
    //   340: aload #7
    //   342: iload #18
    //   344: iconst_3
    //   345: isub
    //   346: iaload
    //   347: aload #7
    //   349: iload #18
    //   351: bipush #8
    //   353: isub
    //   354: iaload
    //   355: ixor
    //   356: aload #7
    //   358: iload #18
    //   360: bipush #14
    //   362: isub
    //   363: iaload
    //   364: ixor
    //   365: aload #7
    //   367: iload #18
    //   369: bipush #16
    //   371: isub
    //   372: iaload
    //   373: ixor
    //   374: istore #19
    //   376: iload #19
    //   378: iconst_1
    //   379: ishl
    //   380: iload #19
    //   382: bipush #31
    //   384: iushr
    //   385: ior
    //   386: istore #20
    //   388: aload #7
    //   390: iload #18
    //   392: iload #20
    //   394: iastore
    //   395: iload #8
    //   397: iconst_5
    //   398: ishl
    //   399: iload #8
    //   401: bipush #27
    //   403: iushr
    //   404: ior
    //   405: istore #19
    //   407: iload #19
    //   409: iload #12
    //   411: iadd
    //   412: aload #7
    //   414: iload #18
    //   416: iaload
    //   417: iadd
    //   418: iload #18
    //   420: bipush #20
    //   422: if_icmpge -> 448
    //   425: ldc 1518500249
    //   427: iload #9
    //   429: iload #10
    //   431: iand
    //   432: iload #9
    //   434: iconst_m1
    //   435: ixor
    //   436: iload #11
    //   438: iand
    //   439: ior
    //   440: iadd
    //   441: goto -> 518
    //   444: invokestatic a : (Ljava/lang/Throwable;)Ljava/lang/Throwable;
    //   447: athrow
    //   448: iload #18
    //   450: bipush #40
    //   452: if_icmpge -> 473
    //   455: ldc 1859775393
    //   457: iload #9
    //   459: iload #10
    //   461: ixor
    //   462: iload #11
    //   464: ixor
    //   465: iadd
    //   466: goto -> 518
    //   469: invokestatic a : (Ljava/lang/Throwable;)Ljava/lang/Throwable;
    //   472: athrow
    //   473: iload #18
    //   475: bipush #60
    //   477: if_icmpge -> 507
    //   480: ldc -1894007588
    //   482: iload #9
    //   484: iload #10
    //   486: iand
    //   487: iload #9
    //   489: iload #11
    //   491: iand
    //   492: ior
    //   493: iload #10
    //   495: iload #11
    //   497: iand
    //   498: ior
    //   499: iadd
    //   500: goto -> 518
    //   503: invokestatic a : (Ljava/lang/Throwable;)Ljava/lang/Throwable;
    //   506: athrow
    //   507: ldc -899497514
    //   509: iload #9
    //   511: iload #10
    //   513: ixor
    //   514: iload #11
    //   516: ixor
    //   517: iadd
    //   518: iadd
    //   519: istore #20
    //   521: iload #11
    //   523: istore #12
    //   525: iload #10
    //   527: istore #11
    //   529: iload #9
    //   531: bipush #30
    //   533: ishl
    //   534: iload #9
    //   536: iconst_2
    //   537: iushr
    //   538: ior
    //   539: istore #10
    //   541: iload #8
    //   543: istore #9
    //   545: iload #20
    //   547: istore #8
    //   549: iinc #18, 1
    //   552: iload_2
    //   553: ifeq -> 302
    //   556: iload #8
    //   558: iload #13
    //   560: iadd
    //   561: istore #8
    //   563: iload #9
    //   565: iload #14
    //   567: iadd
    //   568: istore #9
    //   570: iload #10
    //   572: iload #15
    //   574: iadd
    //   575: istore #10
    //   577: iload #11
    //   579: iload #16
    //   581: iadd
    //   582: istore #11
    //   584: iload #12
    //   586: iload #17
    //   588: iadd
    //   589: istore #12
    //   591: iinc #6, 16
    //   594: iload_2
    //   595: ifeq -> 271
    //   598: iconst_5
    //   599: newarray int
    //   601: dup
    //   602: iconst_0
    //   603: iload #8
    //   605: iastore
    //   606: dup
    //   607: iconst_1
    //   608: iload #9
    //   610: iastore
    //   611: dup
    //   612: iconst_2
    //   613: iload #10
    //   615: iastore
    //   616: dup
    //   617: iconst_3
    //   618: iload #11
    //   620: iastore
    //   621: dup
    //   622: iconst_4
    //   623: iload #12
    //   625: iastore
    //   626: astore #13
    //   628: bipush #20
    //   630: newarray byte
    //   632: astore #14
    //   634: iconst_0
    //   635: istore #15
    //   637: iload #15
    //   639: bipush #20
    //   641: if_icmpge -> 682
    //   644: aload #13
    //   646: iload #15
    //   648: iconst_4
    //   649: idiv
    //   650: iaload
    //   651: istore #16
    //   653: iconst_3
    //   654: iload #15
    //   656: iconst_4
    //   657: irem
    //   658: isub
    //   659: bipush #8
    //   661: imul
    //   662: istore #17
    //   664: aload #14
    //   666: iload #15
    //   668: iload #16
    //   670: iload #17
    //   672: iushr
    //   673: i2b
    //   674: bastore
    //   675: iinc #15, 1
    //   678: iload_2
    //   679: ifeq -> 637
    //   682: aload #14
    //   684: astore #4
    //   686: new java/io/ByteArrayOutputStream
    //   689: dup
    //   690: invokespecial <init> : ()V
    //   693: astore_3
    //   694: getstatic burp/Zl3l.Z_ : Ljava/lang/String;
    //   697: astore #4
    //   699: iconst_0
    //   700: istore #5
    //   702: iload #5
    //   704: aload #4
    //   706: invokevirtual length : ()I
    //   709: if_icmpge -> 739
    //   712: aload_3
    //   713: aload #4
    //   715: iload #5
    //   717: iload #5
    //   719: iconst_2
    //   720: iadd
    //   721: invokevirtual substring : (II)Ljava/lang/String;
    //   724: bipush #16
    //   726: invokestatic parseInt : (Ljava/lang/String;I)I
    //   729: invokevirtual write : (I)V
    //   732: iinc #5, 2
    //   735: iload_2
    //   736: ifeq -> 702
    //   739: aload_3
    //   740: invokevirtual toByteArray : ()[B
    //   743: astore #5
    //   745: getstatic burp/Zgvf.Zd : Ljava/lang/Object;
    //   748: checkcast java/math/BigInteger
    //   751: invokevirtual toByteArray : ()[B
    //   754: astore #6
    //   756: sipush #256
    //   759: newarray byte
    //   761: astore #8
    //   763: sipush #256
    //   766: newarray int
    //   768: astore #9
    //   770: sipush #256
    //   773: newarray int
    //   775: astore #10
    //   777: sipush #256
    //   780: newarray int
    //   782: astore #11
    //   784: sipush #256
    //   787: newarray int
    //   789: astore #12
    //   791: bipush #10
    //   793: newarray int
    //   795: astore #13
    //   797: sipush #283
    //   800: istore #14
    //   802: iconst_0
    //   803: istore #16
    //   805: iload #16
    //   807: sipush #256
    //   810: if_icmpge -> 1044
    //   813: sipush #16764
    //   816: sipush #-17010
    //   819: invokestatic a : (II)Ljava/lang/String;
    //   822: iload #16
    //   824: iconst_1
    //   825: iushr
    //   826: invokevirtual charAt : (I)C
    //   829: istore #25
    //   831: iload #16
    //   833: iconst_1
    //   834: iand
    //   835: ifne -> 850
    //   838: iload #25
    //   840: bipush #8
    //   842: iushr
    //   843: goto -> 852
    //   846: invokestatic a : (Ljava/lang/Throwable;)Ljava/lang/Throwable;
    //   849: athrow
    //   850: iload #25
    //   852: i2b
    //   853: sipush #255
    //   856: iand
    //   857: istore #15
    //   859: iload #16
    //   861: iconst_1
    //   862: ishl
    //   863: istore #17
    //   865: iload #17
    //   867: sipush #256
    //   870: if_icmplt -> 880
    //   873: iload #17
    //   875: iload #14
    //   877: ixor
    //   878: istore #17
    //   880: iload #17
    //   882: iconst_1
    //   883: ishl
    //   884: istore #18
    //   886: iload #18
    //   888: sipush #256
    //   891: if_icmplt -> 901
    //   894: iload #18
    //   896: iload #14
    //   898: ixor
    //   899: istore #18
    //   901: iload #18
    //   903: iconst_1
    //   904: ishl
    //   905: istore #19
    //   907: iload #19
    //   909: sipush #256
    //   912: if_icmplt -> 922
    //   915: iload #19
    //   917: iload #14
    //   919: ixor
    //   920: istore #19
    //   922: iload #19
    //   924: iload #16
    //   926: ixor
    //   927: istore #20
    //   929: iload #20
    //   931: iload #17
    //   933: ixor
    //   934: istore #21
    //   936: iload #20
    //   938: iload #18
    //   940: ixor
    //   941: istore #22
    //   943: iload #19
    //   945: iload #18
    //   947: ixor
    //   948: iload #17
    //   950: ixor
    //   951: istore #23
    //   953: aload #8
    //   955: iload #16
    //   957: iload #15
    //   959: i2b
    //   960: bastore
    //   961: aload #9
    //   963: iload #15
    //   965: iload #23
    //   967: bipush #24
    //   969: ishl
    //   970: iload #20
    //   972: bipush #16
    //   974: ishl
    //   975: ior
    //   976: iload #22
    //   978: bipush #8
    //   980: ishl
    //   981: ior
    //   982: iload #21
    //   984: ior
    //   985: dup
    //   986: istore #24
    //   988: iastore
    //   989: aload #10
    //   991: iload #15
    //   993: iload #24
    //   995: bipush #8
    //   997: iushr
    //   998: iload #24
    //   1000: bipush #24
    //   1002: ishl
    //   1003: ior
    //   1004: iastore
    //   1005: aload #11
    //   1007: iload #15
    //   1009: iload #24
    //   1011: bipush #16
    //   1013: iushr
    //   1014: iload #24
    //   1016: bipush #16
    //   1018: ishl
    //   1019: ior
    //   1020: iastore
    //   1021: aload #12
    //   1023: iload #15
    //   1025: iload #24
    //   1027: bipush #24
    //   1029: iushr
    //   1030: iload #24
    //   1032: bipush #8
    //   1034: ishl
    //   1035: ior
    //   1036: iastore
    //   1037: iinc #16, 1
    //   1040: iload_2
    //   1041: ifeq -> 805
    //   1044: iconst_1
    //   1045: istore #25
    //   1047: aload #13
    //   1049: iconst_0
    //   1050: iload #25
    //   1052: bipush #24
    //   1054: ishl
    //   1055: iastore
    //   1056: iconst_1
    //   1057: istore #26
    //   1059: iload #26
    //   1061: bipush #10
    //   1063: if_icmpge -> 1104
    //   1066: iload #25
    //   1068: iconst_1
    //   1069: ishl
    //   1070: istore #25
    //   1072: iload #25
    //   1074: sipush #256
    //   1077: if_icmplt -> 1087
    //   1080: iload #25
    //   1082: iload #14
    //   1084: ixor
    //   1085: istore #25
    //   1087: aload #13
    //   1089: iload #26
    //   1091: iload #25
    //   1093: bipush #24
    //   1095: ishl
    //   1096: iastore
    //   1097: iinc #26, 1
    //   1100: iload_2
    //   1101: ifeq -> 1059
    //   1104: iconst_4
    //   1105: istore #26
    //   1107: iload #26
    //   1109: bipush #6
    //   1111: iadd
    //   1112: istore #27
    //   1114: iconst_4
    //   1115: iload #27
    //   1117: iconst_1
    //   1118: iadd
    //   1119: imul
    //   1120: istore #28
    //   1122: iload #28
    //   1124: newarray int
    //   1126: astore #29
    //   1128: iload #28
    //   1130: newarray int
    //   1132: astore #30
    //   1134: iconst_0
    //   1135: istore #25
    //   1137: iconst_0
    //   1138: istore #32
    //   1140: iconst_0
    //   1141: istore #33
    //   1143: iload #32
    //   1145: iload #26
    //   1147: if_icmpge -> 1215
    //   1150: aload #29
    //   1152: iload #32
    //   1154: aload #5
    //   1156: iload #33
    //   1158: baload
    //   1159: bipush #24
    //   1161: ishl
    //   1162: aload #5
    //   1164: iload #33
    //   1166: iconst_1
    //   1167: iadd
    //   1168: baload
    //   1169: sipush #255
    //   1172: iand
    //   1173: bipush #16
    //   1175: ishl
    //   1176: ior
    //   1177: aload #5
    //   1179: iload #33
    //   1181: iconst_2
    //   1182: iadd
    //   1183: baload
    //   1184: sipush #255
    //   1187: iand
    //   1188: bipush #8
    //   1190: ishl
    //   1191: ior
    //   1192: aload #5
    //   1194: iload #33
    //   1196: iconst_3
    //   1197: iadd
    //   1198: baload
    //   1199: sipush #255
    //   1202: iand
    //   1203: ior
    //   1204: iastore
    //   1205: iinc #32, 1
    //   1208: iinc #33, 4
    //   1211: iload_2
    //   1212: ifeq -> 1143
    //   1215: iload #26
    //   1217: istore #32
    //   1219: iconst_0
    //   1220: istore #33
    //   1222: iload #32
    //   1224: iload #28
    //   1226: if_icmpge -> 1353
    //   1229: aload #29
    //   1231: iload #32
    //   1233: iconst_1
    //   1234: isub
    //   1235: iaload
    //   1236: istore #31
    //   1238: iload #33
    //   1240: ifne -> 1327
    //   1243: iload #26
    //   1245: istore #33
    //   1247: aload #8
    //   1249: iload #31
    //   1251: bipush #16
    //   1253: iushr
    //   1254: sipush #255
    //   1257: iand
    //   1258: baload
    //   1259: bipush #24
    //   1261: ishl
    //   1262: aload #8
    //   1264: iload #31
    //   1266: bipush #8
    //   1268: iushr
    //   1269: sipush #255
    //   1272: iand
    //   1273: baload
    //   1274: sipush #255
    //   1277: iand
    //   1278: bipush #16
    //   1280: ishl
    //   1281: ior
    //   1282: aload #8
    //   1284: iload #31
    //   1286: sipush #255
    //   1289: iand
    //   1290: baload
    //   1291: sipush #255
    //   1294: iand
    //   1295: bipush #8
    //   1297: ishl
    //   1298: ior
    //   1299: aload #8
    //   1301: iload #31
    //   1303: bipush #24
    //   1305: iushr
    //   1306: baload
    //   1307: sipush #255
    //   1310: iand
    //   1311: ior
    //   1312: istore #31
    //   1314: iload #31
    //   1316: aload #13
    //   1318: iload #25
    //   1320: iinc #25, 1
    //   1323: iaload
    //   1324: ixor
    //   1325: istore #31
    //   1327: aload #29
    //   1329: iload #32
    //   1331: aload #29
    //   1333: iload #32
    //   1335: iload #26
    //   1337: isub
    //   1338: iaload
    //   1339: iload #31
    //   1341: ixor
    //   1342: iastore
    //   1343: iinc #32, 1
    //   1346: iinc #33, -1
    //   1349: iload_2
    //   1350: ifeq -> 1222
    //   1353: iconst_0
    //   1354: istore #32
    //   1356: iconst_4
    //   1357: iload #27
    //   1359: imul
    //   1360: istore #33
    //   1362: aload #30
    //   1364: iload #32
    //   1366: aload #29
    //   1368: iload #33
    //   1370: iaload
    //   1371: iastore
    //   1372: aload #30
    //   1374: iload #32
    //   1376: iconst_1
    //   1377: iadd
    //   1378: aload #29
    //   1380: iload #33
    //   1382: iconst_1
    //   1383: iadd
    //   1384: iaload
    //   1385: iastore
    //   1386: aload #30
    //   1388: iload #32
    //   1390: iconst_2
    //   1391: iadd
    //   1392: aload #29
    //   1394: iload #33
    //   1396: iconst_2
    //   1397: iadd
    //   1398: iaload
    //   1399: iastore
    //   1400: aload #30
    //   1402: iload #32
    //   1404: iconst_3
    //   1405: iadd
    //   1406: aload #29
    //   1408: iload #33
    //   1410: iconst_3
    //   1411: iadd
    //   1412: iaload
    //   1413: iastore
    //   1414: iinc #32, 4
    //   1417: iinc #33, -4
    //   1420: iconst_1
    //   1421: istore #35
    //   1423: iload #35
    //   1425: iload #27
    //   1427: if_icmpge -> 1791
    //   1430: aload #29
    //   1432: iload #33
    //   1434: iaload
    //   1435: istore #34
    //   1437: aload #30
    //   1439: iload #32
    //   1441: aload #9
    //   1443: aload #8
    //   1445: iload #34
    //   1447: bipush #24
    //   1449: iushr
    //   1450: baload
    //   1451: sipush #255
    //   1454: iand
    //   1455: iaload
    //   1456: aload #10
    //   1458: aload #8
    //   1460: iload #34
    //   1462: bipush #16
    //   1464: iushr
    //   1465: sipush #255
    //   1468: iand
    //   1469: baload
    //   1470: sipush #255
    //   1473: iand
    //   1474: iaload
    //   1475: ixor
    //   1476: aload #11
    //   1478: aload #8
    //   1480: iload #34
    //   1482: bipush #8
    //   1484: iushr
    //   1485: sipush #255
    //   1488: iand
    //   1489: baload
    //   1490: sipush #255
    //   1493: iand
    //   1494: iaload
    //   1495: ixor
    //   1496: aload #12
    //   1498: aload #8
    //   1500: iload #34
    //   1502: sipush #255
    //   1505: iand
    //   1506: baload
    //   1507: sipush #255
    //   1510: iand
    //   1511: iaload
    //   1512: ixor
    //   1513: iastore
    //   1514: aload #29
    //   1516: iload #33
    //   1518: iconst_1
    //   1519: iadd
    //   1520: iaload
    //   1521: istore #34
    //   1523: aload #30
    //   1525: iload #32
    //   1527: iconst_1
    //   1528: iadd
    //   1529: aload #9
    //   1531: aload #8
    //   1533: iload #34
    //   1535: bipush #24
    //   1537: iushr
    //   1538: baload
    //   1539: sipush #255
    //   1542: iand
    //   1543: iaload
    //   1544: aload #10
    //   1546: aload #8
    //   1548: iload #34
    //   1550: bipush #16
    //   1552: iushr
    //   1553: sipush #255
    //   1556: iand
    //   1557: baload
    //   1558: sipush #255
    //   1561: iand
    //   1562: iaload
    //   1563: ixor
    //   1564: aload #11
    //   1566: aload #8
    //   1568: iload #34
    //   1570: bipush #8
    //   1572: iushr
    //   1573: sipush #255
    //   1576: iand
    //   1577: baload
    //   1578: sipush #255
    //   1581: iand
    //   1582: iaload
    //   1583: ixor
    //   1584: aload #12
    //   1586: aload #8
    //   1588: iload #34
    //   1590: sipush #255
    //   1593: iand
    //   1594: baload
    //   1595: sipush #255
    //   1598: iand
    //   1599: iaload
    //   1600: ixor
    //   1601: iastore
    //   1602: aload #29
    //   1604: iload #33
    //   1606: iconst_2
    //   1607: iadd
    //   1608: iaload
    //   1609: istore #34
    //   1611: aload #30
    //   1613: iload #32
    //   1615: iconst_2
    //   1616: iadd
    //   1617: aload #9
    //   1619: aload #8
    //   1621: iload #34
    //   1623: bipush #24
    //   1625: iushr
    //   1626: baload
    //   1627: sipush #255
    //   1630: iand
    //   1631: iaload
    //   1632: aload #10
    //   1634: aload #8
    //   1636: iload #34
    //   1638: bipush #16
    //   1640: iushr
    //   1641: sipush #255
    //   1644: iand
    //   1645: baload
    //   1646: sipush #255
    //   1649: iand
    //   1650: iaload
    //   1651: ixor
    //   1652: aload #11
    //   1654: aload #8
    //   1656: iload #34
    //   1658: bipush #8
    //   1660: iushr
    //   1661: sipush #255
    //   1664: iand
    //   1665: baload
    //   1666: sipush #255
    //   1669: iand
    //   1670: iaload
    //   1671: ixor
    //   1672: aload #12
    //   1674: aload #8
    //   1676: iload #34
    //   1678: sipush #255
    //   1681: iand
    //   1682: baload
    //   1683: sipush #255
    //   1686: iand
    //   1687: iaload
    //   1688: ixor
    //   1689: iastore
    //   1690: aload #29
    //   1692: iload #33
    //   1694: iconst_3
    //   1695: iadd
    //   1696: iaload
    //   1697: istore #34
    //   1699: aload #30
    //   1701: iload #32
    //   1703: iconst_3
    //   1704: iadd
    //   1705: aload #9
    //   1707: aload #8
    //   1709: iload #34
    //   1711: bipush #24
    //   1713: iushr
    //   1714: baload
    //   1715: sipush #255
    //   1718: iand
    //   1719: iaload
    //   1720: aload #10
    //   1722: aload #8
    //   1724: iload #34
    //   1726: bipush #16
    //   1728: iushr
    //   1729: sipush #255
    //   1732: iand
    //   1733: baload
    //   1734: sipush #255
    //   1737: iand
    //   1738: iaload
    //   1739: ixor
    //   1740: aload #11
    //   1742: aload #8
    //   1744: iload #34
    //   1746: bipush #8
    //   1748: iushr
    //   1749: sipush #255
    //   1752: iand
    //   1753: baload
    //   1754: sipush #255
    //   1757: iand
    //   1758: iaload
    //   1759: ixor
    //   1760: aload #12
    //   1762: aload #8
    //   1764: iload #34
    //   1766: sipush #255
    //   1769: iand
    //   1770: baload
    //   1771: sipush #255
    //   1774: iand
    //   1775: iaload
    //   1776: ixor
    //   1777: iastore
    //   1778: iinc #32, 4
    //   1781: iinc #33, -4
    //   1784: iinc #35, 1
    //   1787: iload_2
    //   1788: ifeq -> 1423
    //   1791: aload #30
    //   1793: iload #32
    //   1795: aload #29
    //   1797: iload #33
    //   1799: iaload
    //   1800: iastore
    //   1801: aload #30
    //   1803: iload #32
    //   1805: iconst_1
    //   1806: iadd
    //   1807: aload #29
    //   1809: iload #33
    //   1811: iconst_1
    //   1812: iadd
    //   1813: iaload
    //   1814: iastore
    //   1815: aload #30
    //   1817: iload #32
    //   1819: iconst_2
    //   1820: iadd
    //   1821: aload #29
    //   1823: iload #33
    //   1825: iconst_2
    //   1826: iadd
    //   1827: iaload
    //   1828: iastore
    //   1829: aload #30
    //   1831: iload #32
    //   1833: iconst_3
    //   1834: iadd
    //   1835: aload #29
    //   1837: iload #33
    //   1839: iconst_3
    //   1840: iadd
    //   1841: iaload
    //   1842: iastore
    //   1843: iconst_0
    //   1844: newarray byte
    //   1846: astore #35
    //   1848: aload #6
    //   1850: arraylength
    //   1851: bipush #16
    //   1853: irem
    //   1854: ifeq -> 1878
    //   1857: new java/lang/Exception
    //   1860: dup
    //   1861: sipush #16750
    //   1864: sipush #29752
    //   1867: invokestatic a : (II)Ljava/lang/String;
    //   1870: invokespecial <init> : (Ljava/lang/String;)V
    //   1873: athrow
    //   1874: invokestatic a : (Ljava/lang/Throwable;)Ljava/lang/Throwable;
    //   1877: athrow
    //   1878: bipush #10
    //   1880: istore #36
    //   1882: sipush #16740
    //   1885: sipush #256
    //   1888: newarray byte
    //   1890: astore #37
    //   1892: sipush #19982
    //   1895: sipush #256
    //   1898: newarray int
    //   1900: astore #38
    //   1902: sipush #256
    //   1905: newarray int
    //   1907: astore #39
    //   1909: sipush #256
    //   1912: newarray int
    //   1914: astore #40
    //   1916: sipush #256
    //   1919: newarray int
    //   1921: astore #41
    //   1923: sipush #283
    //   1926: istore #14
    //   1928: invokestatic a : (II)Ljava/lang/String;
    //   1931: astore #42
    //   1933: iconst_0
    //   1934: istore #16
    //   1936: iload #16
    //   1938: sipush #256
    //   1941: if_icmpge -> 2168
    //   1944: aload #42
    //   1946: iload #16
    //   1948: iconst_1
    //   1949: iushr
    //   1950: invokevirtual charAt : (I)C
    //   1953: istore #43
    //   1955: iload #16
    //   1957: iconst_1
    //   1958: iand
    //   1959: ifne -> 1974
    //   1962: iload #43
    //   1964: bipush #8
    //   1966: iushr
    //   1967: goto -> 1976
    //   1970: invokestatic a : (Ljava/lang/Throwable;)Ljava/lang/Throwable;
    //   1973: athrow
    //   1974: iload #43
    //   1976: i2b
    //   1977: sipush #255
    //   1980: iand
    //   1981: istore #15
    //   1983: iload #16
    //   1985: iconst_1
    //   1986: ishl
    //   1987: istore #17
    //   1989: iload #17
    //   1991: sipush #256
    //   1994: if_icmplt -> 2004
    //   1997: iload #17
    //   1999: iload #14
    //   2001: ixor
    //   2002: istore #17
    //   2004: iload #17
    //   2006: iconst_1
    //   2007: ishl
    //   2008: istore #18
    //   2010: iload #18
    //   2012: sipush #256
    //   2015: if_icmplt -> 2025
    //   2018: iload #18
    //   2020: iload #14
    //   2022: ixor
    //   2023: istore #18
    //   2025: iload #18
    //   2027: iconst_1
    //   2028: ishl
    //   2029: istore #19
    //   2031: iload #19
    //   2033: sipush #256
    //   2036: if_icmplt -> 2046
    //   2039: iload #19
    //   2041: iload #14
    //   2043: ixor
    //   2044: istore #19
    //   2046: iload #19
    //   2048: iload #16
    //   2050: ixor
    //   2051: istore #20
    //   2053: iload #20
    //   2055: iload #17
    //   2057: ixor
    //   2058: istore #21
    //   2060: iload #20
    //   2062: iload #18
    //   2064: ixor
    //   2065: istore #22
    //   2067: iload #19
    //   2069: iload #18
    //   2071: ixor
    //   2072: iload #17
    //   2074: ixor
    //   2075: istore #23
    //   2077: aload #37
    //   2079: iload #15
    //   2081: iload #16
    //   2083: i2b
    //   2084: bastore
    //   2085: aload #38
    //   2087: iload #15
    //   2089: iload #23
    //   2091: bipush #24
    //   2093: ishl
    //   2094: iload #20
    //   2096: bipush #16
    //   2098: ishl
    //   2099: ior
    //   2100: iload #22
    //   2102: bipush #8
    //   2104: ishl
    //   2105: ior
    //   2106: iload #21
    //   2108: ior
    //   2109: dup
    //   2110: istore #24
    //   2112: iastore
    //   2113: aload #39
    //   2115: iload #15
    //   2117: iload #24
    //   2119: bipush #8
    //   2121: iushr
    //   2122: iload #24
    //   2124: bipush #24
    //   2126: ishl
    //   2127: ior
    //   2128: iastore
    //   2129: aload #40
    //   2131: iload #15
    //   2133: iload #24
    //   2135: bipush #16
    //   2137: iushr
    //   2138: iload #24
    //   2140: bipush #16
    //   2142: ishl
    //   2143: ior
    //   2144: iastore
    //   2145: aload #41
    //   2147: iload #15
    //   2149: iload #24
    //   2151: bipush #24
    //   2153: iushr
    //   2154: iload #24
    //   2156: bipush #8
    //   2158: ishl
    //   2159: ior
    //   2160: iastore
    //   2161: iinc #16, 1
    //   2164: iload_2
    //   2165: ifeq -> 1936
    //   2168: aload #6
    //   2170: arraylength
    //   2171: newarray byte
    //   2173: astore #43
    //   2175: iconst_0
    //   2176: istore #44
    //   2178: iload #44
    //   2180: aload #6
    //   2182: arraylength
    //   2183: bipush #16
    //   2185: idiv
    //   2186: if_icmpge -> 3100
    //   2189: bipush #16
    //   2191: newarray byte
    //   2193: astore #45
    //   2195: bipush #16
    //   2197: newarray byte
    //   2199: astore #46
    //   2201: iconst_0
    //   2202: istore #47
    //   2204: iload #47
    //   2206: bipush #16
    //   2208: if_icmpge -> 2234
    //   2211: aload #45
    //   2213: iload #47
    //   2215: aload #6
    //   2217: iload #47
    //   2219: iload #44
    //   2221: bipush #16
    //   2223: imul
    //   2224: iadd
    //   2225: baload
    //   2226: bastore
    //   2227: iinc #47, 1
    //   2230: iload_2
    //   2231: ifeq -> 2204
    //   2234: iconst_0
    //   2235: istore #47
    //   2237: aload #45
    //   2239: iconst_0
    //   2240: baload
    //   2241: bipush #24
    //   2243: ishl
    //   2244: aload #45
    //   2246: iconst_1
    //   2247: baload
    //   2248: sipush #255
    //   2251: iand
    //   2252: bipush #16
    //   2254: ishl
    //   2255: ior
    //   2256: aload #45
    //   2258: iconst_2
    //   2259: baload
    //   2260: sipush #255
    //   2263: iand
    //   2264: bipush #8
    //   2266: ishl
    //   2267: ior
    //   2268: aload #45
    //   2270: iconst_3
    //   2271: baload
    //   2272: sipush #255
    //   2275: iand
    //   2276: ior
    //   2277: aload #30
    //   2279: iconst_0
    //   2280: iaload
    //   2281: ixor
    //   2282: istore #49
    //   2284: aload #45
    //   2286: iconst_4
    //   2287: baload
    //   2288: bipush #24
    //   2290: ishl
    //   2291: aload #45
    //   2293: iconst_5
    //   2294: baload
    //   2295: sipush #255
    //   2298: iand
    //   2299: bipush #16
    //   2301: ishl
    //   2302: ior
    //   2303: aload #45
    //   2305: bipush #6
    //   2307: baload
    //   2308: sipush #255
    //   2311: iand
    //   2312: bipush #8
    //   2314: ishl
    //   2315: ior
    //   2316: aload #45
    //   2318: bipush #7
    //   2320: baload
    //   2321: sipush #255
    //   2324: iand
    //   2325: ior
    //   2326: aload #30
    //   2328: iconst_1
    //   2329: iaload
    //   2330: ixor
    //   2331: istore #50
    //   2333: aload #45
    //   2335: bipush #8
    //   2337: baload
    //   2338: bipush #24
    //   2340: ishl
    //   2341: aload #45
    //   2343: bipush #9
    //   2345: baload
    //   2346: sipush #255
    //   2349: iand
    //   2350: bipush #16
    //   2352: ishl
    //   2353: ior
    //   2354: aload #45
    //   2356: bipush #10
    //   2358: baload
    //   2359: sipush #255
    //   2362: iand
    //   2363: bipush #8
    //   2365: ishl
    //   2366: ior
    //   2367: aload #45
    //   2369: bipush #11
    //   2371: baload
    //   2372: sipush #255
    //   2375: iand
    //   2376: ior
    //   2377: aload #30
    //   2379: iconst_2
    //   2380: iaload
    //   2381: ixor
    //   2382: istore #51
    //   2384: aload #45
    //   2386: bipush #12
    //   2388: baload
    //   2389: bipush #24
    //   2391: ishl
    //   2392: aload #45
    //   2394: bipush #13
    //   2396: baload
    //   2397: sipush #255
    //   2400: iand
    //   2401: bipush #16
    //   2403: ishl
    //   2404: ior
    //   2405: aload #45
    //   2407: bipush #14
    //   2409: baload
    //   2410: sipush #255
    //   2413: iand
    //   2414: bipush #8
    //   2416: ishl
    //   2417: ior
    //   2418: aload #45
    //   2420: bipush #15
    //   2422: baload
    //   2423: sipush #255
    //   2426: iand
    //   2427: ior
    //   2428: aload #30
    //   2430: iconst_3
    //   2431: iaload
    //   2432: ixor
    //   2433: istore #52
    //   2435: iconst_1
    //   2436: istore #53
    //   2438: iload #53
    //   2440: iload #36
    //   2442: if_icmpge -> 2685
    //   2445: iinc #47, 4
    //   2448: aload #38
    //   2450: iload #49
    //   2452: bipush #24
    //   2454: iushr
    //   2455: iaload
    //   2456: aload #39
    //   2458: iload #52
    //   2460: bipush #16
    //   2462: iushr
    //   2463: sipush #255
    //   2466: iand
    //   2467: iaload
    //   2468: ixor
    //   2469: aload #40
    //   2471: iload #51
    //   2473: bipush #8
    //   2475: iushr
    //   2476: sipush #255
    //   2479: iand
    //   2480: iaload
    //   2481: ixor
    //   2482: aload #41
    //   2484: iload #50
    //   2486: sipush #255
    //   2489: iand
    //   2490: iaload
    //   2491: ixor
    //   2492: aload #30
    //   2494: iload #47
    //   2496: iaload
    //   2497: ixor
    //   2498: istore #54
    //   2500: aload #38
    //   2502: iload #50
    //   2504: bipush #24
    //   2506: iushr
    //   2507: iaload
    //   2508: aload #39
    //   2510: iload #49
    //   2512: bipush #16
    //   2514: iushr
    //   2515: sipush #255
    //   2518: iand
    //   2519: iaload
    //   2520: ixor
    //   2521: aload #40
    //   2523: iload #52
    //   2525: bipush #8
    //   2527: iushr
    //   2528: sipush #255
    //   2531: iand
    //   2532: iaload
    //   2533: ixor
    //   2534: aload #41
    //   2536: iload #51
    //   2538: sipush #255
    //   2541: iand
    //   2542: iaload
    //   2543: ixor
    //   2544: aload #30
    //   2546: iload #47
    //   2548: iconst_1
    //   2549: iadd
    //   2550: iaload
    //   2551: ixor
    //   2552: istore #55
    //   2554: aload #38
    //   2556: iload #51
    //   2558: bipush #24
    //   2560: iushr
    //   2561: iaload
    //   2562: aload #39
    //   2564: iload #50
    //   2566: bipush #16
    //   2568: iushr
    //   2569: sipush #255
    //   2572: iand
    //   2573: iaload
    //   2574: ixor
    //   2575: aload #40
    //   2577: iload #49
    //   2579: bipush #8
    //   2581: iushr
    //   2582: sipush #255
    //   2585: iand
    //   2586: iaload
    //   2587: ixor
    //   2588: aload #41
    //   2590: iload #52
    //   2592: sipush #255
    //   2595: iand
    //   2596: iaload
    //   2597: ixor
    //   2598: aload #30
    //   2600: iload #47
    //   2602: iconst_2
    //   2603: iadd
    //   2604: iaload
    //   2605: ixor
    //   2606: istore #56
    //   2608: aload #38
    //   2610: iload #52
    //   2612: bipush #24
    //   2614: iushr
    //   2615: iaload
    //   2616: aload #39
    //   2618: iload #51
    //   2620: bipush #16
    //   2622: iushr
    //   2623: sipush #255
    //   2626: iand
    //   2627: iaload
    //   2628: ixor
    //   2629: aload #40
    //   2631: iload #50
    //   2633: bipush #8
    //   2635: iushr
    //   2636: sipush #255
    //   2639: iand
    //   2640: iaload
    //   2641: ixor
    //   2642: aload #41
    //   2644: iload #49
    //   2646: sipush #255
    //   2649: iand
    //   2650: iaload
    //   2651: ixor
    //   2652: aload #30
    //   2654: iload #47
    //   2656: iconst_3
    //   2657: iadd
    //   2658: iaload
    //   2659: ixor
    //   2660: istore #57
    //   2662: iload #54
    //   2664: istore #49
    //   2666: iload #55
    //   2668: istore #50
    //   2670: iload #56
    //   2672: istore #51
    //   2674: iload #57
    //   2676: istore #52
    //   2678: iinc #53, 1
    //   2681: iload_2
    //   2682: ifeq -> 2438
    //   2685: iinc #47, 4
    //   2688: aload #30
    //   2690: iload #47
    //   2692: iaload
    //   2693: istore #48
    //   2695: aload #46
    //   2697: iconst_0
    //   2698: aload #37
    //   2700: iload #49
    //   2702: bipush #24
    //   2704: iushr
    //   2705: baload
    //   2706: iload #48
    //   2708: bipush #24
    //   2710: iushr
    //   2711: ixor
    //   2712: i2b
    //   2713: bastore
    //   2714: aload #46
    //   2716: iconst_1
    //   2717: aload #37
    //   2719: iload #52
    //   2721: bipush #16
    //   2723: iushr
    //   2724: sipush #255
    //   2727: iand
    //   2728: baload
    //   2729: iload #48
    //   2731: bipush #16
    //   2733: iushr
    //   2734: ixor
    //   2735: i2b
    //   2736: bastore
    //   2737: aload #46
    //   2739: iconst_2
    //   2740: aload #37
    //   2742: iload #51
    //   2744: bipush #8
    //   2746: iushr
    //   2747: sipush #255
    //   2750: iand
    //   2751: baload
    //   2752: iload #48
    //   2754: bipush #8
    //   2756: iushr
    //   2757: ixor
    //   2758: i2b
    //   2759: bastore
    //   2760: aload #46
    //   2762: iconst_3
    //   2763: aload #37
    //   2765: iload #50
    //   2767: sipush #255
    //   2770: iand
    //   2771: baload
    //   2772: iload #48
    //   2774: ixor
    //   2775: i2b
    //   2776: bastore
    //   2777: aload #30
    //   2779: iload #47
    //   2781: iconst_1
    //   2782: iadd
    //   2783: iaload
    //   2784: istore #48
    //   2786: aload #46
    //   2788: iconst_4
    //   2789: aload #37
    //   2791: iload #50
    //   2793: bipush #24
    //   2795: iushr
    //   2796: baload
    //   2797: iload #48
    //   2799: bipush #24
    //   2801: iushr
    //   2802: ixor
    //   2803: i2b
    //   2804: bastore
    //   2805: aload #46
    //   2807: iconst_5
    //   2808: aload #37
    //   2810: iload #49
    //   2812: bipush #16
    //   2814: iushr
    //   2815: sipush #255
    //   2818: iand
    //   2819: baload
    //   2820: iload #48
    //   2822: bipush #16
    //   2824: iushr
    //   2825: ixor
    //   2826: i2b
    //   2827: bastore
    //   2828: aload #46
    //   2830: bipush #6
    //   2832: aload #37
    //   2834: iload #52
    //   2836: bipush #8
    //   2838: iushr
    //   2839: sipush #255
    //   2842: iand
    //   2843: baload
    //   2844: iload #48
    //   2846: bipush #8
    //   2848: iushr
    //   2849: ixor
    //   2850: i2b
    //   2851: bastore
    //   2852: aload #46
    //   2854: bipush #7
    //   2856: aload #37
    //   2858: iload #51
    //   2860: sipush #255
    //   2863: iand
    //   2864: baload
    //   2865: iload #48
    //   2867: ixor
    //   2868: i2b
    //   2869: bastore
    //   2870: aload #30
    //   2872: iload #47
    //   2874: iconst_2
    //   2875: iadd
    //   2876: iaload
    //   2877: istore #48
    //   2879: aload #46
    //   2881: bipush #8
    //   2883: aload #37
    //   2885: iload #51
    //   2887: bipush #24
    //   2889: iushr
    //   2890: baload
    //   2891: iload #48
    //   2893: bipush #24
    //   2895: iushr
    //   2896: ixor
    //   2897: i2b
    //   2898: bastore
    //   2899: aload #46
    //   2901: bipush #9
    //   2903: aload #37
    //   2905: iload #50
    //   2907: bipush #16
    //   2909: iushr
    //   2910: sipush #255
    //   2913: iand
    //   2914: baload
    //   2915: iload #48
    //   2917: bipush #16
    //   2919: iushr
    //   2920: ixor
    //   2921: i2b
    //   2922: bastore
    //   2923: aload #46
    //   2925: bipush #10
    //   2927: aload #37
    //   2929: iload #49
    //   2931: bipush #8
    //   2933: iushr
    //   2934: sipush #255
    //   2937: iand
    //   2938: baload
    //   2939: iload #48
    //   2941: bipush #8
    //   2943: iushr
    //   2944: ixor
    //   2945: i2b
    //   2946: bastore
    //   2947: aload #46
    //   2949: bipush #11
    //   2951: aload #37
    //   2953: iload #52
    //   2955: sipush #255
    //   2958: iand
    //   2959: baload
    //   2960: iload #48
    //   2962: ixor
    //   2963: i2b
    //   2964: bastore
    //   2965: aload #30
    //   2967: iload #47
    //   2969: iconst_3
    //   2970: iadd
    //   2971: iaload
    //   2972: istore #48
    //   2974: aload #46
    //   2976: bipush #12
    //   2978: aload #37
    //   2980: iload #52
    //   2982: bipush #24
    //   2984: iushr
    //   2985: baload
    //   2986: iload #48
    //   2988: bipush #24
    //   2990: iushr
    //   2991: ixor
    //   2992: i2b
    //   2993: bastore
    //   2994: aload #46
    //   2996: bipush #13
    //   2998: aload #37
    //   3000: iload #51
    //   3002: bipush #16
    //   3004: iushr
    //   3005: sipush #255
    //   3008: iand
    //   3009: baload
    //   3010: iload #48
    //   3012: bipush #16
    //   3014: iushr
    //   3015: ixor
    //   3016: i2b
    //   3017: bastore
    //   3018: aload #46
    //   3020: bipush #14
    //   3022: aload #37
    //   3024: iload #50
    //   3026: bipush #8
    //   3028: iushr
    //   3029: sipush #255
    //   3032: iand
    //   3033: baload
    //   3034: iload #48
    //   3036: bipush #8
    //   3038: iushr
    //   3039: ixor
    //   3040: i2b
    //   3041: bastore
    //   3042: aload #46
    //   3044: bipush #15
    //   3046: aload #37
    //   3048: iload #49
    //   3050: sipush #255
    //   3053: iand
    //   3054: baload
    //   3055: iload #48
    //   3057: ixor
    //   3058: i2b
    //   3059: bastore
    //   3060: iconst_0
    //   3061: istore #53
    //   3063: iload #53
    //   3065: bipush #16
    //   3067: if_icmpge -> 3093
    //   3070: aload #43
    //   3072: iload #53
    //   3074: iload #44
    //   3076: bipush #16
    //   3078: imul
    //   3079: iadd
    //   3080: aload #46
    //   3082: iload #53
    //   3084: baload
    //   3085: bastore
    //   3086: iinc #53, 1
    //   3089: iload_2
    //   3090: ifeq -> 3063
    //   3093: iinc #44, 1
    //   3096: iload_2
    //   3097: ifeq -> 2178
    //   3100: aload #43
    //   3102: arraylength
    //   3103: ifle -> 3184
    //   3106: aload #43
    //   3108: aload #43
    //   3110: arraylength
    //   3111: iconst_1
    //   3112: isub
    //   3113: baload
    //   3114: istore #44
    //   3116: iload #44
    //   3118: bipush #16
    //   3120: if_icmple -> 3131
    //   3123: aload #43
    //   3125: astore #35
    //   3127: iload_2
    //   3128: ifeq -> 3184
    //   3131: aload #43
    //   3133: arraylength
    //   3134: iload #44
    //   3136: isub
    //   3137: newarray byte
    //   3139: astore #35
    //   3141: iconst_0
    //   3142: istore #45
    //   3144: iload #45
    //   3146: aload #35
    //   3148: arraylength
    //   3149: if_icmpge -> 3184
    //   3152: iload #45
    //   3154: aload #43
    //   3156: arraylength
    //   3157: if_icmpge -> 3184
    //   3160: aload #35
    //   3162: iload #45
    //   3164: aload #43
    //   3166: iload #45
    //   3168: baload
    //   3169: bastore
    //   3170: iinc #45, 1
    //   3173: iload_2
    //   3174: ifeq -> 3144
    //   3177: goto -> 3184
    //   3180: invokestatic a : (Ljava/lang/Throwable;)Ljava/lang/Throwable;
    //   3183: athrow
    //   3184: aload #35
    //   3186: astore #7
    //   3188: new java/math/BigInteger
    //   3191: dup
    //   3192: aload #7
    //   3194: invokespecial <init> : ([B)V
    //   3197: invokevirtual abs : ()Ljava/math/BigInteger;
    //   3200: putstatic burp/Zle4.Zh : Ljava/lang/Object;
    //   3203: new java/lang/StringBuilder
    //   3206: dup
    //   3207: invokespecial <init> : ()V
    //   3210: astore_3
    //   3211: iconst_0
    //   3212: istore #4
    //   3214: iload #4
    //   3216: bipush #32
    //   3218: if_icmpge -> 4551
    //   3221: iload #4
    //   3223: tableswitch default -> 4544, 0 -> 3364, 1 -> 3401, 2 -> 3438, 3 -> 3475, 4 -> 3512, 5 -> 3549, 6 -> 3586, 7 -> 3623, 8 -> 3660, 9 -> 3697, 10 -> 3734, 11 -> 3771, 12 -> 3808, 13 -> 3845, 14 -> 3882, 15 -> 3919, 16 -> 3956, 17 -> 3993, 18 -> 4030, 19 -> 4067, 20 -> 4104, 21 -> 4141, 22 -> 4178, 23 -> 4215, 24 -> 4252, 25 -> 4289, 26 -> 4326, 27 -> 4363, 28 -> 4400, 29 -> 4437, 30 -> 4474, 31 -> 4511
    //   3364: aload_3
    //   3365: getstatic burp/Ztgv.ZC : Ljava/lang/String;
    //   3368: getstatic burp/Zgdj.ZT : Ljava/lang/Object;
    //   3371: checkcast java/math/BigInteger
    //   3374: invokevirtual intValue : ()I
    //   3377: bipush #32
    //   3379: irem
    //   3380: invokestatic abs : (I)I
    //   3383: invokevirtual charAt : (I)C
    //   3386: invokevirtual append : (C)Ljava/lang/StringBuilder;
    //   3389: pop
    //   3390: iload_2
    //   3391: ifeq -> 4544
    //   3394: goto -> 3401
    //   3397: invokestatic a : (Ljava/lang/Throwable;)Ljava/lang/Throwable;
    //   3400: athrow
    //   3401: aload_3
    //   3402: getstatic burp/Ztw4.Zb : Ljava/lang/String;
    //   3405: getstatic burp/Zxtc.ZF : Ljava/lang/Object;
    //   3408: checkcast java/math/BigInteger
    //   3411: invokevirtual intValue : ()I
    //   3414: bipush #32
    //   3416: irem
    //   3417: invokestatic abs : (I)I
    //   3420: invokevirtual charAt : (I)C
    //   3423: invokevirtual append : (C)Ljava/lang/StringBuilder;
    //   3426: pop
    //   3427: iload_2
    //   3428: ifeq -> 4544
    //   3431: goto -> 3438
    //   3434: invokestatic a : (Ljava/lang/Throwable;)Ljava/lang/Throwable;
    //   3437: athrow
    //   3438: aload_3
    //   3439: getstatic burp/Ze7q.ZW : Ljava/lang/String;
    //   3442: getstatic burp/Zzgh.ZV : Ljava/lang/Object;
    //   3445: checkcast java/math/BigInteger
    //   3448: invokevirtual intValue : ()I
    //   3451: bipush #32
    //   3453: irem
    //   3454: invokestatic abs : (I)I
    //   3457: invokevirtual charAt : (I)C
    //   3460: invokevirtual append : (C)Ljava/lang/StringBuilder;
    //   3463: pop
    //   3464: iload_2
    //   3465: ifeq -> 4544
    //   3468: goto -> 3475
    //   3471: invokestatic a : (Ljava/lang/Throwable;)Ljava/lang/Throwable;
    //   3474: athrow
    //   3475: aload_3
    //   3476: getstatic burp/Zmjw.ZB : Ljava/lang/String;
    //   3479: getstatic burp/Zkfa.Zw : Ljava/lang/Object;
    //   3482: checkcast java/math/BigInteger
    //   3485: invokevirtual intValue : ()I
    //   3488: bipush #32
    //   3490: irem
    //   3491: invokestatic abs : (I)I
    //   3494: invokevirtual charAt : (I)C
    //   3497: invokevirtual append : (C)Ljava/lang/StringBuilder;
    //   3500: pop
    //   3501: iload_2
    //   3502: ifeq -> 4544
    //   3505: goto -> 3512
    //   3508: invokestatic a : (Ljava/lang/Throwable;)Ljava/lang/Throwable;
    //   3511: athrow
    //   3512: aload_3
    //   3513: getstatic burp/Zss6.ZN : Ljava/lang/String;
    //   3516: getstatic burp/Zb8v.ZA : Ljava/lang/Object;
    //   3519: checkcast java/math/BigInteger
    //   3522: invokevirtual intValue : ()I
    //   3525: bipush #32
    //   3527: irem
    //   3528: invokestatic abs : (I)I
    //   3531: invokevirtual charAt : (I)C
    //   3534: invokevirtual append : (C)Ljava/lang/StringBuilder;
    //   3537: pop
    //   3538: iload_2
    //   3539: ifeq -> 4544
    //   3542: goto -> 3549
    //   3545: invokestatic a : (Ljava/lang/Throwable;)Ljava/lang/Throwable;
    //   3548: athrow
    //   3549: aload_3
    //   3550: getstatic burp/Ztte.ZD : Ljava/lang/String;
    //   3553: getstatic burp/Zrjg.ZG : Ljava/lang/Object;
    //   3556: checkcast java/math/BigInteger
    //   3559: invokevirtual intValue : ()I
    //   3562: bipush #32
    //   3564: irem
    //   3565: invokestatic abs : (I)I
    //   3568: invokevirtual charAt : (I)C
    //   3571: invokevirtual append : (C)Ljava/lang/StringBuilder;
    //   3574: pop
    //   3575: iload_2
    //   3576: ifeq -> 4544
    //   3579: goto -> 3586
    //   3582: invokestatic a : (Ljava/lang/Throwable;)Ljava/lang/Throwable;
    //   3585: athrow
    //   3586: aload_3
    //   3587: getstatic burp/Zelc.ZI : Ljava/lang/String;
    //   3590: getstatic burp/Zkw.ZY : Ljava/lang/Object;
    //   3593: checkcast java/math/BigInteger
    //   3596: invokevirtual intValue : ()I
    //   3599: bipush #32
    //   3601: irem
    //   3602: invokestatic abs : (I)I
    //   3605: invokevirtual charAt : (I)C
    //   3608: invokevirtual append : (C)Ljava/lang/StringBuilder;
    //   3611: pop
    //   3612: iload_2
    //   3613: ifeq -> 4544
    //   3616: goto -> 3623
    //   3619: invokestatic a : (Ljava/lang/Throwable;)Ljava/lang/Throwable;
    //   3622: athrow
    //   3623: aload_3
    //   3624: getstatic burp/Ze69.ZA : Ljava/lang/String;
    //   3627: getstatic burp/Zmou.ZT : Ljava/lang/Object;
    //   3630: checkcast java/math/BigInteger
    //   3633: invokevirtual intValue : ()I
    //   3636: bipush #32
    //   3638: irem
    //   3639: invokestatic abs : (I)I
    //   3642: invokevirtual charAt : (I)C
    //   3645: invokevirtual append : (C)Ljava/lang/StringBuilder;
    //   3648: pop
    //   3649: iload_2
    //   3650: ifeq -> 4544
    //   3653: goto -> 3660
    //   3656: invokestatic a : (Ljava/lang/Throwable;)Ljava/lang/Throwable;
    //   3659: athrow
    //   3660: aload_3
    //   3661: getstatic burp/Zlo2.ZJ : Ljava/lang/String;
    //   3664: getstatic burp/Zx_u.Zy : Ljava/lang/Object;
    //   3667: checkcast java/math/BigInteger
    //   3670: invokevirtual intValue : ()I
    //   3673: bipush #32
    //   3675: irem
    //   3676: invokestatic abs : (I)I
    //   3679: invokevirtual charAt : (I)C
    //   3682: invokevirtual append : (C)Ljava/lang/StringBuilder;
    //   3685: pop
    //   3686: iload_2
    //   3687: ifeq -> 4544
    //   3690: goto -> 3697
    //   3693: invokestatic a : (Ljava/lang/Throwable;)Ljava/lang/Throwable;
    //   3696: athrow
    //   3697: aload_3
    //   3698: getstatic burp/Zgyc.Zj : Ljava/lang/String;
    //   3701: getstatic burp/Zf.Zh : Ljava/lang/Object;
    //   3704: checkcast java/math/BigInteger
    //   3707: invokevirtual intValue : ()I
    //   3710: bipush #32
    //   3712: irem
    //   3713: invokestatic abs : (I)I
    //   3716: invokevirtual charAt : (I)C
    //   3719: invokevirtual append : (C)Ljava/lang/StringBuilder;
    //   3722: pop
    //   3723: iload_2
    //   3724: ifeq -> 4544
    //   3727: goto -> 3734
    //   3730: invokestatic a : (Ljava/lang/Throwable;)Ljava/lang/Throwable;
    //   3733: athrow
    //   3734: aload_3
    //   3735: getstatic burp/Zbp_.ZQ : Ljava/lang/String;
    //   3738: getstatic burp/Zrnu.Zs : Ljava/lang/Object;
    //   3741: checkcast java/math/BigInteger
    //   3744: invokevirtual intValue : ()I
    //   3747: bipush #32
    //   3749: irem
    //   3750: invokestatic abs : (I)I
    //   3753: invokevirtual charAt : (I)C
    //   3756: invokevirtual append : (C)Ljava/lang/StringBuilder;
    //   3759: pop
    //   3760: iload_2
    //   3761: ifeq -> 4544
    //   3764: goto -> 3771
    //   3767: invokestatic a : (Ljava/lang/Throwable;)Ljava/lang/Throwable;
    //   3770: athrow
    //   3771: aload_3
    //   3772: getstatic burp/Zt5t.ZK : Ljava/lang/String;
    //   3775: getstatic burp/Zd0.ZT : Ljava/lang/Object;
    //   3778: checkcast java/math/BigInteger
    //   3781: invokevirtual intValue : ()I
    //   3784: bipush #32
    //   3786: irem
    //   3787: invokestatic abs : (I)I
    //   3790: invokevirtual charAt : (I)C
    //   3793: invokevirtual append : (C)Ljava/lang/StringBuilder;
    //   3796: pop
    //   3797: iload_2
    //   3798: ifeq -> 4544
    //   3801: goto -> 3808
    //   3804: invokestatic a : (Ljava/lang/Throwable;)Ljava/lang/Throwable;
    //   3807: athrow
    //   3808: aload_3
    //   3809: getstatic burp/Zs34.Zq : Ljava/lang/String;
    //   3812: getstatic burp/Zgwq.Ze : Ljava/lang/Object;
    //   3815: checkcast java/math/BigInteger
    //   3818: invokevirtual intValue : ()I
    //   3821: bipush #32
    //   3823: irem
    //   3824: invokestatic abs : (I)I
    //   3827: invokevirtual charAt : (I)C
    //   3830: invokevirtual append : (C)Ljava/lang/StringBuilder;
    //   3833: pop
    //   3834: iload_2
    //   3835: ifeq -> 4544
    //   3838: goto -> 3845
    //   3841: invokestatic a : (Ljava/lang/Throwable;)Ljava/lang/Throwable;
    //   3844: athrow
    //   3845: aload_3
    //   3846: getstatic burp/Zr0u.Z_ : Ljava/lang/String;
    //   3849: getstatic burp/Zrx5.ZE : Ljava/lang/Object;
    //   3852: checkcast java/math/BigInteger
    //   3855: invokevirtual intValue : ()I
    //   3858: bipush #32
    //   3860: irem
    //   3861: invokestatic abs : (I)I
    //   3864: invokevirtual charAt : (I)C
    //   3867: invokevirtual append : (C)Ljava/lang/StringBuilder;
    //   3870: pop
    //   3871: iload_2
    //   3872: ifeq -> 4544
    //   3875: goto -> 3882
    //   3878: invokestatic a : (Ljava/lang/Throwable;)Ljava/lang/Throwable;
    //   3881: athrow
    //   3882: aload_3
    //   3883: getstatic burp/Zgco.Zh : Ljava/lang/String;
    //   3886: getstatic burp/Zl22.ZJ : Ljava/lang/Object;
    //   3889: checkcast java/math/BigInteger
    //   3892: invokevirtual intValue : ()I
    //   3895: bipush #32
    //   3897: irem
    //   3898: invokestatic abs : (I)I
    //   3901: invokevirtual charAt : (I)C
    //   3904: invokevirtual append : (C)Ljava/lang/StringBuilder;
    //   3907: pop
    //   3908: iload_2
    //   3909: ifeq -> 4544
    //   3912: goto -> 3919
    //   3915: invokestatic a : (Ljava/lang/Throwable;)Ljava/lang/Throwable;
    //   3918: athrow
    //   3919: aload_3
    //   3920: getstatic burp/Zmjr.Zc : Ljava/lang/String;
    //   3923: getstatic burp/Zrhp.Zw : Ljava/lang/Object;
    //   3926: checkcast java/math/BigInteger
    //   3929: invokevirtual intValue : ()I
    //   3932: bipush #32
    //   3934: irem
    //   3935: invokestatic abs : (I)I
    //   3938: invokevirtual charAt : (I)C
    //   3941: invokevirtual append : (C)Ljava/lang/StringBuilder;
    //   3944: pop
    //   3945: iload_2
    //   3946: ifeq -> 4544
    //   3949: goto -> 3956
    //   3952: invokestatic a : (Ljava/lang/Throwable;)Ljava/lang/Throwable;
    //   3955: athrow
    //   3956: aload_3
    //   3957: getstatic burp/Zrp3.Zf : Ljava/lang/String;
    //   3960: getstatic burp/Zz20.ZN : Ljava/lang/Object;
    //   3963: checkcast java/math/BigInteger
    //   3966: invokevirtual intValue : ()I
    //   3969: bipush #32
    //   3971: irem
    //   3972: invokestatic abs : (I)I
    //   3975: invokevirtual charAt : (I)C
    //   3978: invokevirtual append : (C)Ljava/lang/StringBuilder;
    //   3981: pop
    //   3982: iload_2
    //   3983: ifeq -> 4544
    //   3986: goto -> 3993
    //   3989: invokestatic a : (Ljava/lang/Throwable;)Ljava/lang/Throwable;
    //   3992: athrow
    //   3993: aload_3
    //   3994: getstatic burp/Zml2.Zh : Ljava/lang/String;
    //   3997: getstatic burp/Zlem.ZI : Ljava/lang/Object;
    //   4000: checkcast java/math/BigInteger
    //   4003: invokevirtual intValue : ()I
    //   4006: bipush #32
    //   4008: irem
    //   4009: invokestatic abs : (I)I
    //   4012: invokevirtual charAt : (I)C
    //   4015: invokevirtual append : (C)Ljava/lang/StringBuilder;
    //   4018: pop
    //   4019: iload_2
    //   4020: ifeq -> 4544
    //   4023: goto -> 4030
    //   4026: invokestatic a : (Ljava/lang/Throwable;)Ljava/lang/Throwable;
    //   4029: athrow
    //   4030: aload_3
    //   4031: getstatic burp/Zsji.Zr : Ljava/lang/String;
    //   4034: getstatic burp/Zeno.Zo : Ljava/lang/Object;
    //   4037: checkcast java/math/BigInteger
    //   4040: invokevirtual intValue : ()I
    //   4043: bipush #32
    //   4045: irem
    //   4046: invokestatic abs : (I)I
    //   4049: invokevirtual charAt : (I)C
    //   4052: invokevirtual append : (C)Ljava/lang/StringBuilder;
    //   4055: pop
    //   4056: iload_2
    //   4057: ifeq -> 4544
    //   4060: goto -> 4067
    //   4063: invokestatic a : (Ljava/lang/Throwable;)Ljava/lang/Throwable;
    //   4066: athrow
    //   4067: aload_3
    //   4068: getstatic burp/Zr9p.Za : Ljava/lang/String;
    //   4071: getstatic burp/Zzo5.Zf : Ljava/lang/Object;
    //   4074: checkcast java/math/BigInteger
    //   4077: invokevirtual intValue : ()I
    //   4080: bipush #32
    //   4082: irem
    //   4083: invokestatic abs : (I)I
    //   4086: invokevirtual charAt : (I)C
    //   4089: invokevirtual append : (C)Ljava/lang/StringBuilder;
    //   4092: pop
    //   4093: iload_2
    //   4094: ifeq -> 4544
    //   4097: goto -> 4104
    //   4100: invokestatic a : (Ljava/lang/Throwable;)Ljava/lang/Throwable;
    //   4103: athrow
    //   4104: aload_3
    //   4105: getstatic burp/Zmtf.Zx : Ljava/lang/String;
    //   4108: getstatic burp/Zzna.ZD : Ljava/lang/Object;
    //   4111: checkcast java/math/BigInteger
    //   4114: invokevirtual intValue : ()I
    //   4117: bipush #32
    //   4119: irem
    //   4120: invokestatic abs : (I)I
    //   4123: invokevirtual charAt : (I)C
    //   4126: invokevirtual append : (C)Ljava/lang/StringBuilder;
    //   4129: pop
    //   4130: iload_2
    //   4131: ifeq -> 4544
    //   4134: goto -> 4141
    //   4137: invokestatic a : (Ljava/lang/Throwable;)Ljava/lang/Throwable;
    //   4140: athrow
    //   4141: aload_3
    //   4142: getstatic burp/Zvof.ZR : Ljava/lang/String;
    //   4145: getstatic burp/Zlwi.Zw : Ljava/lang/Object;
    //   4148: checkcast java/math/BigInteger
    //   4151: invokevirtual intValue : ()I
    //   4154: bipush #32
    //   4156: irem
    //   4157: invokestatic abs : (I)I
    //   4160: invokevirtual charAt : (I)C
    //   4163: invokevirtual append : (C)Ljava/lang/StringBuilder;
    //   4166: pop
    //   4167: iload_2
    //   4168: ifeq -> 4544
    //   4171: goto -> 4178
    //   4174: invokestatic a : (Ljava/lang/Throwable;)Ljava/lang/Throwable;
    //   4177: athrow
    //   4178: aload_3
    //   4179: getstatic burp/Zb2p.ZV : Ljava/lang/String;
    //   4182: getstatic burp/Zlv6.ZN : Ljava/lang/Object;
    //   4185: checkcast java/math/BigInteger
    //   4188: invokevirtual intValue : ()I
    //   4191: bipush #32
    //   4193: irem
    //   4194: invokestatic abs : (I)I
    //   4197: invokevirtual charAt : (I)C
    //   4200: invokevirtual append : (C)Ljava/lang/StringBuilder;
    //   4203: pop
    //   4204: iload_2
    //   4205: ifeq -> 4544
    //   4208: goto -> 4215
    //   4211: invokestatic a : (Ljava/lang/Throwable;)Ljava/lang/Throwable;
    //   4214: athrow
    //   4215: aload_3
    //   4216: getstatic burp/Zmrc.Zx : Ljava/lang/String;
    //   4219: getstatic burp/Zkup.Zf : Ljava/lang/Object;
    //   4222: checkcast java/math/BigInteger
    //   4225: invokevirtual intValue : ()I
    //   4228: bipush #32
    //   4230: irem
    //   4231: invokestatic abs : (I)I
    //   4234: invokevirtual charAt : (I)C
    //   4237: invokevirtual append : (C)Ljava/lang/StringBuilder;
    //   4240: pop
    //   4241: iload_2
    //   4242: ifeq -> 4544
    //   4245: goto -> 4252
    //   4248: invokestatic a : (Ljava/lang/Throwable;)Ljava/lang/Throwable;
    //   4251: athrow
    //   4252: aload_3
    //   4253: getstatic burp/Zs5y.ZO : Ljava/lang/String;
    //   4256: getstatic burp/Zstf.ZA : Ljava/lang/Object;
    //   4259: checkcast java/math/BigInteger
    //   4262: invokevirtual intValue : ()I
    //   4265: bipush #32
    //   4267: irem
    //   4268: invokestatic abs : (I)I
    //   4271: invokevirtual charAt : (I)C
    //   4274: invokevirtual append : (C)Ljava/lang/StringBuilder;
    //   4277: pop
    //   4278: iload_2
    //   4279: ifeq -> 4544
    //   4282: goto -> 4289
    //   4285: invokestatic a : (Ljava/lang/Throwable;)Ljava/lang/Throwable;
    //   4288: athrow
    //   4289: aload_3
    //   4290: getstatic burp/Zb8_.ZP : Ljava/lang/String;
    //   4293: getstatic burp/Zr8r.ZR : Ljava/lang/Object;
    //   4296: checkcast java/math/BigInteger
    //   4299: invokevirtual intValue : ()I
    //   4302: bipush #32
    //   4304: irem
    //   4305: invokestatic abs : (I)I
    //   4308: invokevirtual charAt : (I)C
    //   4311: invokevirtual append : (C)Ljava/lang/StringBuilder;
    //   4314: pop
    //   4315: iload_2
    //   4316: ifeq -> 4544
    //   4319: goto -> 4326
    //   4322: invokestatic a : (Ljava/lang/Throwable;)Ljava/lang/Throwable;
    //   4325: athrow
    //   4326: aload_3
    //   4327: getstatic burp/Zb_u.ZK : Ljava/lang/String;
    //   4330: getstatic burp/Ztdd.ZD : Ljava/lang/Object;
    //   4333: checkcast java/math/BigInteger
    //   4336: invokevirtual intValue : ()I
    //   4339: bipush #32
    //   4341: irem
    //   4342: invokestatic abs : (I)I
    //   4345: invokevirtual charAt : (I)C
    //   4348: invokevirtual append : (C)Ljava/lang/StringBuilder;
    //   4351: pop
    //   4352: iload_2
    //   4353: ifeq -> 4544
    //   4356: goto -> 4363
    //   4359: invokestatic a : (Ljava/lang/Throwable;)Ljava/lang/Throwable;
    //   4362: athrow
    //   4363: aload_3
    //   4364: getstatic burp/Zm5p.ZX : Ljava/lang/String;
    //   4367: getstatic burp/Zr9p.ZC : Ljava/lang/Object;
    //   4370: checkcast java/math/BigInteger
    //   4373: invokevirtual intValue : ()I
    //   4376: bipush #32
    //   4378: irem
    //   4379: invokestatic abs : (I)I
    //   4382: invokevirtual charAt : (I)C
    //   4385: invokevirtual append : (C)Ljava/lang/StringBuilder;
    //   4388: pop
    //   4389: iload_2
    //   4390: ifeq -> 4544
    //   4393: goto -> 4400
    //   4396: invokestatic a : (Ljava/lang/Throwable;)Ljava/lang/Throwable;
    //   4399: athrow
    //   4400: aload_3
    //   4401: getstatic burp/Zscf.Zu : Ljava/lang/String;
    //   4404: getstatic burp/Zxdh.ZD : Ljava/lang/Object;
    //   4407: checkcast java/math/BigInteger
    //   4410: invokevirtual intValue : ()I
    //   4413: bipush #32
    //   4415: irem
    //   4416: invokestatic abs : (I)I
    //   4419: invokevirtual charAt : (I)C
    //   4422: invokevirtual append : (C)Ljava/lang/StringBuilder;
    //   4425: pop
    //   4426: iload_2
    //   4427: ifeq -> 4544
    //   4430: goto -> 4437
    //   4433: invokestatic a : (Ljava/lang/Throwable;)Ljava/lang/Throwable;
    //   4436: athrow
    //   4437: aload_3
    //   4438: getstatic burp/Zzoc.Zg : Ljava/lang/String;
    //   4441: getstatic burp/Zex5.Zb : Ljava/lang/Object;
    //   4444: checkcast java/math/BigInteger
    //   4447: invokevirtual intValue : ()I
    //   4450: bipush #32
    //   4452: irem
    //   4453: invokestatic abs : (I)I
    //   4456: invokevirtual charAt : (I)C
    //   4459: invokevirtual append : (C)Ljava/lang/StringBuilder;
    //   4462: pop
    //   4463: iload_2
    //   4464: ifeq -> 4544
    //   4467: goto -> 4474
    //   4470: invokestatic a : (Ljava/lang/Throwable;)Ljava/lang/Throwable;
    //   4473: athrow
    //   4474: aload_3
    //   4475: getstatic burp/Zrf9.ZV : Ljava/lang/String;
    //   4478: getstatic burp/Zzh9.Zv : Ljava/lang/Object;
    //   4481: checkcast java/math/BigInteger
    //   4484: invokevirtual intValue : ()I
    //   4487: bipush #32
    //   4489: irem
    //   4490: invokestatic abs : (I)I
    //   4493: invokevirtual charAt : (I)C
    //   4496: invokevirtual append : (C)Ljava/lang/StringBuilder;
    //   4499: pop
    //   4500: iload_2
    //   4501: ifeq -> 4544
    //   4504: goto -> 4511
    //   4507: invokestatic a : (Ljava/lang/Throwable;)Ljava/lang/Throwable;
    //   4510: athrow
    //   4511: aload_3
    //   4512: getstatic burp/Zgco.Zh : Ljava/lang/String;
    //   4515: getstatic burp/Zlpj.Zc : Ljava/lang/Object;
    //   4518: checkcast java/math/BigInteger
    //   4521: invokevirtual intValue : ()I
    //   4524: bipush #32
    //   4526: irem
    //   4527: invokestatic abs : (I)I
    //   4530: invokevirtual charAt : (I)C
    //   4533: invokevirtual append : (C)Ljava/lang/StringBuilder;
    //   4536: pop
    //   4537: goto -> 4544
    //   4540: invokestatic a : (Ljava/lang/Throwable;)Ljava/lang/Throwable;
    //   4543: athrow
    //   4544: iinc #4, 1
    //   4547: iload_2
    //   4548: ifeq -> 3214
    //   4551: aload_3
    //   4552: invokevirtual toString : ()Ljava/lang/String;
    //   4555: putstatic burp/Zea8.ZE : Ljava/lang/String;
    //   4558: sipush #16754
    //   4561: sipush #-17706
    //   4564: invokestatic a : (II)Ljava/lang/String;
    //   4567: iconst_1
    //   4568: ldc burp/Zoa
    //   4570: invokevirtual getClassLoader : ()Ljava/lang/ClassLoader;
    //   4573: invokestatic forName : (Ljava/lang/String;ZLjava/lang/ClassLoader;)Ljava/lang/Class;
    //   4576: invokevirtual getDeclaredFields : ()[Ljava/lang/reflect/Field;
    //   4579: astore #4
    //   4581: aload #4
    //   4583: arraylength
    //   4584: istore #5
    //   4586: iconst_0
    //   4587: istore #6
    //   4589: iload #6
    //   4591: iload #5
    //   4593: if_icmpge -> 4731
    //   4596: aload #4
    //   4598: iload #6
    //   4600: aaload
    //   4601: astore #7
    //   4603: aload #7
    //   4605: invokevirtual getModifiers : ()I
    //   4608: invokestatic isStatic : (I)Z
    //   4611: ifne -> 4621
    //   4614: goto -> 4724
    //   4617: invokestatic a : (Ljava/lang/Throwable;)Ljava/lang/Throwable;
    //   4620: athrow
    //   4621: aload #7
    //   4623: invokevirtual getType : ()Ljava/lang/Class;
    //   4626: astore #8
    //   4628: aload #8
    //   4630: ifnull -> 4711
    //   4633: aload #8
    //   4635: invokevirtual isPrimitive : ()Z
    //   4638: ifne -> 4711
    //   4641: goto -> 4648
    //   4644: invokestatic a : (Ljava/lang/Throwable;)Ljava/lang/Throwable;
    //   4647: athrow
    //   4648: aload #8
    //   4650: invokevirtual getPackage : ()Ljava/lang/Package;
    //   4653: ifnull -> 4711
    //   4656: goto -> 4663
    //   4659: invokestatic a : (Ljava/lang/Throwable;)Ljava/lang/Throwable;
    //   4662: athrow
    //   4663: aload #8
    //   4665: invokevirtual getPackage : ()Ljava/lang/Package;
    //   4668: invokevirtual getName : ()Ljava/lang/String;
    //   4671: ifnull -> 4711
    //   4674: goto -> 4681
    //   4677: invokestatic a : (Ljava/lang/Throwable;)Ljava/lang/Throwable;
    //   4680: athrow
    //   4681: aload #8
    //   4683: invokevirtual getPackage : ()Ljava/lang/Package;
    //   4686: invokevirtual getName : ()Ljava/lang/String;
    //   4689: sipush #16745
    //   4692: sipush #-28477
    //   4695: invokestatic a : (II)Ljava/lang/String;
    //   4698: invokevirtual startsWith : (Ljava/lang/String;)Z
    //   4701: ifne -> 4711
    //   4704: goto -> 4711
    //   4707: invokestatic a : (Ljava/lang/Throwable;)Ljava/lang/Throwable;
    //   4710: athrow
    //   4711: aload #7
    //   4713: iconst_1
    //   4714: invokevirtual setAccessible : (Z)V
    //   4717: aload #7
    //   4719: aconst_null
    //   4720: invokevirtual get : (Ljava/lang/Object;)Ljava/lang/Object;
    //   4723: pop
    //   4724: iinc #6, 1
    //   4727: iload_2
    //   4728: ifeq -> 4589
    //   4731: sipush #16738
    //   4734: sipush #6886
    //   4737: invokestatic a : (II)Ljava/lang/String;
    //   4740: invokestatic forName : (Ljava/lang/String;)Ljava/lang/Class;
    //   4743: invokevirtual getDeclaredMethods : ()[Ljava/lang/reflect/Method;
    //   4746: astore #4
    //   4748: aload #4
    //   4750: arraylength
    //   4751: istore #5
    //   4753: iconst_0
    //   4754: istore #6
    //   4756: iload #6
    //   4758: iload #5
    //   4760: if_icmpge -> 4872
    //   4763: aload #4
    //   4765: iload #6
    //   4767: aaload
    //   4768: astore #7
    //   4770: aload #7
    //   4772: invokevirtual getParameterTypes : ()[Ljava/lang/Class;
    //   4775: pop
    //   4776: aload #7
    //   4778: invokevirtual getModifiers : ()I
    //   4781: invokestatic isStatic : (I)Z
    //   4784: ifeq -> 4858
    //   4787: aload #7
    //   4789: invokevirtual getParameterTypes : ()[Ljava/lang/Class;
    //   4792: arraylength
    //   4793: iconst_2
    //   4794: if_icmpne -> 4858
    //   4797: goto -> 4804
    //   4800: invokestatic a : (Ljava/lang/Throwable;)Ljava/lang/Throwable;
    //   4803: athrow
    //   4804: aload #7
    //   4806: invokevirtual getReturnType : ()Ljava/lang/Class;
    //   4809: getstatic java/lang/Boolean.TYPE : Ljava/lang/Class;
    //   4812: if_acmpne -> 4858
    //   4815: goto -> 4822
    //   4818: invokestatic a : (Ljava/lang/Throwable;)Ljava/lang/Throwable;
    //   4821: athrow
    //   4822: aload #7
    //   4824: iconst_1
    //   4825: invokevirtual setAccessible : (Z)V
    //   4828: aload #7
    //   4830: aconst_null
    //   4831: iconst_2
    //   4832: anewarray java/lang/Object
    //   4835: dup
    //   4836: iconst_0
    //   4837: aload_0
    //   4838: aastore
    //   4839: dup
    //   4840: iconst_1
    //   4841: aload_1
    //   4842: aastore
    //   4843: invokevirtual invoke : (Ljava/lang/Object;[Ljava/lang/Object;)Ljava/lang/Object;
    //   4846: pop
    //   4847: iload_2
    //   4848: ifeq -> 4872
    //   4851: goto -> 4858
    //   4854: invokestatic a : (Ljava/lang/Throwable;)Ljava/lang/Throwable;
    //   4857: athrow
    //   4858: iinc #6, 1
    //   4861: iload_2
    //   4862: ifeq -> 4756
    //   4865: goto -> 4872
    //   4868: invokestatic a : (Ljava/lang/Throwable;)Ljava/lang/Throwable;
    //   4871: athrow
    //   4872: sipush #16737
    //   4875: sipush #9557
    //   4878: invokestatic a : (II)Ljava/lang/String;
    //   4881: iconst_1
    //   4882: ldc burp/Zldx
    //   4884: invokevirtual getClassLoader : ()Ljava/lang/ClassLoader;
    //   4887: invokestatic forName : (Ljava/lang/String;ZLjava/lang/ClassLoader;)Ljava/lang/Class;
    //   4890: invokevirtual getDeclaredFields : ()[Ljava/lang/reflect/Field;
    //   4893: astore #4
    //   4895: aload #4
    //   4897: arraylength
    //   4898: istore #5
    //   4900: iconst_0
    //   4901: istore #6
    //   4903: iload #6
    //   4905: iload #5
    //   4907: if_icmpge -> 5045
    //   4910: aload #4
    //   4912: iload #6
    //   4914: aaload
    //   4915: astore #7
    //   4917: aload #7
    //   4919: invokevirtual getModifiers : ()I
    //   4922: invokestatic isStatic : (I)Z
    //   4925: ifne -> 4935
    //   4928: goto -> 5038
    //   4931: invokestatic a : (Ljava/lang/Throwable;)Ljava/lang/Throwable;
    //   4934: athrow
    //   4935: aload #7
    //   4937: invokevirtual getType : ()Ljava/lang/Class;
    //   4940: astore #8
    //   4942: aload #8
    //   4944: ifnull -> 5025
    //   4947: aload #8
    //   4949: invokevirtual isPrimitive : ()Z
    //   4952: ifne -> 5025
    //   4955: goto -> 4962
    //   4958: invokestatic a : (Ljava/lang/Throwable;)Ljava/lang/Throwable;
    //   4961: athrow
    //   4962: aload #8
    //   4964: invokevirtual getPackage : ()Ljava/lang/Package;
    //   4967: ifnull -> 5025
    //   4970: goto -> 4977
    //   4973: invokestatic a : (Ljava/lang/Throwable;)Ljava/lang/Throwable;
    //   4976: athrow
    //   4977: aload #8
    //   4979: invokevirtual getPackage : ()Ljava/lang/Package;
    //   4982: invokevirtual getName : ()Ljava/lang/String;
    //   4985: ifnull -> 5025
    //   4988: goto -> 4995
    //   4991: invokestatic a : (Ljava/lang/Throwable;)Ljava/lang/Throwable;
    //   4994: athrow
    //   4995: aload #8
    //   4997: invokevirtual getPackage : ()Ljava/lang/Package;
    //   5000: invokevirtual getName : ()Ljava/lang/String;
    //   5003: sipush #16767
    //   5006: sipush #-11618
    //   5009: invokestatic a : (II)Ljava/lang/String;
    //   5012: invokevirtual startsWith : (Ljava/lang/String;)Z
    //   5015: ifne -> 5025
    //   5018: goto -> 5025
    //   5021: invokestatic a : (Ljava/lang/Throwable;)Ljava/lang/Throwable;
    //   5024: athrow
    //   5025: aload #7
    //   5027: iconst_1
    //   5028: invokevirtual setAccessible : (Z)V
    //   5031: aload #7
    //   5033: aconst_null
    //   5034: invokevirtual get : (Ljava/lang/Object;)Ljava/lang/Object;
    //   5037: pop
    //   5038: iinc #6, 1
    //   5041: iload_2
    //   5042: ifeq -> 4903
    //   5045: sipush #16747
    //   5048: sipush #27886
    //   5051: invokestatic a : (II)Ljava/lang/String;
    //   5054: invokestatic forName : (Ljava/lang/String;)Ljava/lang/Class;
    //   5057: invokevirtual getDeclaredMethods : ()[Ljava/lang/reflect/Method;
    //   5060: astore #4
    //   5062: aload #4
    //   5064: arraylength
    //   5065: istore #5
    //   5067: iconst_0
    //   5068: istore #6
    //   5070: iload #6
    //   5072: iload #5
    //   5074: if_icmpge -> 5204
    //   5077: aload #4
    //   5079: iload #6
    //   5081: aaload
    //   5082: astore #7
    //   5084: aload #7
    //   5086: invokevirtual getParameterTypes : ()[Ljava/lang/Class;
    //   5089: pop
    //   5090: aload #7
    //   5092: invokevirtual getModifiers : ()I
    //   5095: invokestatic isStatic : (I)Z
    //   5098: ifeq -> 5190
    //   5101: aload #7
    //   5103: invokevirtual getParameterTypes : ()[Ljava/lang/Class;
    //   5106: arraylength
    //   5107: iconst_2
    //   5108: if_icmpne -> 5190
    //   5111: goto -> 5118
    //   5114: invokestatic a : (Ljava/lang/Throwable;)Ljava/lang/Throwable;
    //   5117: athrow
    //   5118: aload #7
    //   5120: invokevirtual getReturnType : ()Ljava/lang/Class;
    //   5123: getstatic java/lang/Boolean.TYPE : Ljava/lang/Class;
    //   5126: if_acmpne -> 5190
    //   5129: goto -> 5136
    //   5132: invokestatic a : (Ljava/lang/Throwable;)Ljava/lang/Throwable;
    //   5135: athrow
    //   5136: aload #7
    //   5138: iconst_1
    //   5139: invokevirtual setAccessible : (Z)V
    //   5142: aload #7
    //   5144: aconst_null
    //   5145: iconst_2
    //   5146: anewarray java/lang/Object
    //   5149: dup
    //   5150: iconst_0
    //   5151: aload_0
    //   5152: aastore
    //   5153: dup
    //   5154: iconst_1
    //   5155: aload_1
    //   5156: ifnonnull -> 5174
    //   5159: goto -> 5166
    //   5162: invokestatic a : (Ljava/lang/Throwable;)Ljava/lang/Throwable;
    //   5165: athrow
    //   5166: aload_1
    //   5167: goto -> 5181
    //   5170: invokestatic a : (Ljava/lang/Throwable;)Ljava/lang/Throwable;
    //   5173: athrow
    //   5174: aload_1
    //   5175: checkcast [B
    //   5178: invokevirtual clone : ()Ljava/lang/Object;
    //   5181: aastore
    //   5182: invokevirtual invoke : (Ljava/lang/Object;[Ljava/lang/Object;)Ljava/lang/Object;
    //   5185: pop
    //   5186: iload_2
    //   5187: ifeq -> 5204
    //   5190: iinc #6, 1
    //   5193: iload_2
    //   5194: ifeq -> 5070
    //   5197: goto -> 5204
    //   5200: invokestatic a : (Ljava/lang/Throwable;)Ljava/lang/Throwable;
    //   5203: athrow
    //   5204: sipush #16734
    //   5207: sipush #-13264
    //   5210: invokestatic a : (II)Ljava/lang/String;
    //   5213: iconst_1
    //   5214: ldc burp/Zkor
    //   5216: invokevirtual getClassLoader : ()Ljava/lang/ClassLoader;
    //   5219: invokestatic forName : (Ljava/lang/String;ZLjava/lang/ClassLoader;)Ljava/lang/Class;
    //   5222: invokevirtual getDeclaredFields : ()[Ljava/lang/reflect/Field;
    //   5225: astore #4
    //   5227: aload #4
    //   5229: arraylength
    //   5230: istore #5
    //   5232: iconst_0
    //   5233: istore #6
    //   5235: iload #6
    //   5237: iload #5
    //   5239: if_icmpge -> 5377
    //   5242: aload #4
    //   5244: iload #6
    //   5246: aaload
    //   5247: astore #7
    //   5249: aload #7
    //   5251: invokevirtual getModifiers : ()I
    //   5254: invokestatic isStatic : (I)Z
    //   5257: ifne -> 5267
    //   5260: goto -> 5370
    //   5263: invokestatic a : (Ljava/lang/Throwable;)Ljava/lang/Throwable;
    //   5266: athrow
    //   5267: aload #7
    //   5269: invokevirtual getType : ()Ljava/lang/Class;
    //   5272: astore #8
    //   5274: aload #8
    //   5276: ifnull -> 5357
    //   5279: aload #8
    //   5281: invokevirtual isPrimitive : ()Z
    //   5284: ifne -> 5357
    //   5287: goto -> 5294
    //   5290: invokestatic a : (Ljava/lang/Throwable;)Ljava/lang/Throwable;
    //   5293: athrow
    //   5294: aload #8
    //   5296: invokevirtual getPackage : ()Ljava/lang/Package;
    //   5299: ifnull -> 5357
    //   5302: goto -> 5309
    //   5305: invokestatic a : (Ljava/lang/Throwable;)Ljava/lang/Throwable;
    //   5308: athrow
    //   5309: aload #8
    //   5311: invokevirtual getPackage : ()Ljava/lang/Package;
    //   5314: invokevirtual getName : ()Ljava/lang/String;
    //   5317: ifnull -> 5357
    //   5320: goto -> 5327
    //   5323: invokestatic a : (Ljava/lang/Throwable;)Ljava/lang/Throwable;
    //   5326: athrow
    //   5327: aload #8
    //   5329: invokevirtual getPackage : ()Ljava/lang/Package;
    //   5332: invokevirtual getName : ()Ljava/lang/String;
    //   5335: sipush #16767
    //   5338: sipush #-11618
    //   5341: invokestatic a : (II)Ljava/lang/String;
    //   5344: invokevirtual startsWith : (Ljava/lang/String;)Z
    //   5347: ifne -> 5357
    //   5350: goto -> 5357
    //   5353: invokestatic a : (Ljava/lang/Throwable;)Ljava/lang/Throwable;
    //   5356: athrow
    //   5357: aload #7
    //   5359: iconst_1
    //   5360: invokevirtual setAccessible : (Z)V
    //   5363: aload #7
    //   5365: aconst_null
    //   5366: invokevirtual get : (Ljava/lang/Object;)Ljava/lang/Object;
    //   5369: pop
    //   5370: iinc #6, 1
    //   5373: iload_2
    //   5374: ifeq -> 5235
    //   5377: sipush #16741
    //   5380: sipush #-19704
    //   5383: invokestatic a : (II)Ljava/lang/String;
    //   5386: invokestatic forName : (Ljava/lang/String;)Ljava/lang/Class;
    //   5389: invokevirtual getDeclaredMethods : ()[Ljava/lang/reflect/Method;
    //   5392: astore #4
    //   5394: aload #4
    //   5396: arraylength
    //   5397: istore #5
    //   5399: iconst_0
    //   5400: istore #6
    //   5402: iload #6
    //   5404: iload #5
    //   5406: if_icmpge -> 5539
    //   5409: aload #4
    //   5411: iload #6
    //   5413: aaload
    //   5414: astore #7
    //   5416: aload #7
    //   5418: invokevirtual getParameterTypes : ()[Ljava/lang/Class;
    //   5421: pop
    //   5422: aload #7
    //   5424: invokevirtual getModifiers : ()I
    //   5427: invokestatic isStatic : (I)Z
    //   5430: ifeq -> 5525
    //   5433: aload #7
    //   5435: invokevirtual getParameterTypes : ()[Ljava/lang/Class;
    //   5438: arraylength
    //   5439: iconst_2
    //   5440: if_icmpne -> 5525
    //   5443: goto -> 5450
    //   5446: invokestatic a : (Ljava/lang/Throwable;)Ljava/lang/Throwable;
    //   5449: athrow
    //   5450: aload #7
    //   5452: invokevirtual getReturnType : ()Ljava/lang/Class;
    //   5455: getstatic java/lang/Void.TYPE : Ljava/lang/Class;
    //   5458: invokevirtual equals : (Ljava/lang/Object;)Z
    //   5461: ifeq -> 5525
    //   5464: goto -> 5471
    //   5467: invokestatic a : (Ljava/lang/Throwable;)Ljava/lang/Throwable;
    //   5470: athrow
    //   5471: aload #7
    //   5473: iconst_1
    //   5474: invokevirtual setAccessible : (Z)V
    //   5477: aload #7
    //   5479: aconst_null
    //   5480: iconst_2
    //   5481: anewarray java/lang/Object
    //   5484: dup
    //   5485: iconst_0
    //   5486: aload_0
    //   5487: aastore
    //   5488: dup
    //   5489: iconst_1
    //   5490: aload_1
    //   5491: ifnonnull -> 5509
    //   5494: goto -> 5501
    //   5497: invokestatic a : (Ljava/lang/Throwable;)Ljava/lang/Throwable;
    //   5500: athrow
    //   5501: aload_1
    //   5502: goto -> 5516
    //   5505: invokestatic a : (Ljava/lang/Throwable;)Ljava/lang/Throwable;
    //   5508: athrow
    //   5509: aload_1
    //   5510: checkcast [B
    //   5513: invokevirtual clone : ()Ljava/lang/Object;
    //   5516: aastore
    //   5517: invokevirtual invoke : (Ljava/lang/Object;[Ljava/lang/Object;)Ljava/lang/Object;
    //   5520: pop
    //   5521: iload_2
    //   5522: ifeq -> 5539
    //   5525: iinc #6, 1
    //   5528: iload_2
    //   5529: ifeq -> 5402
    //   5532: goto -> 5539
    //   5535: invokestatic a : (Ljava/lang/Throwable;)Ljava/lang/Throwable;
    //   5538: athrow
    //   5539: new java/io/ByteArrayOutputStream
    //   5542: dup
    //   5543: invokespecial <init> : ()V
    //   5546: astore #4
    //   5548: sipush #16766
    //   5551: aload #4
    //   5553: sipush #202
    //   5556: invokevirtual write : (I)V
    //   5559: sipush #-19171
    //   5562: aload #4
    //   5564: sipush #254
    //   5567: invokevirtual write : (I)V
    //   5570: aload #4
    //   5572: sipush #186
    //   5575: invokevirtual write : (I)V
    //   5578: aload #4
    //   5580: sipush #190
    //   5583: invokevirtual write : (I)V
    //   5586: aload #4
    //   5588: iconst_0
    //   5589: invokevirtual write : (I)V
    //   5592: aload #4
    //   5594: iconst_1
    //   5595: invokevirtual write : (I)V
    //   5598: aload #4
    //   5600: iconst_0
    //   5601: invokevirtual write : (I)V
    //   5604: aload #4
    //   5606: bipush #50
    //   5608: invokevirtual write : (I)V
    //   5611: aload #4
    //   5613: getstatic burp/Zeqr.ZM : Ljava/lang/Object;
    //   5616: checkcast java/math/BigInteger
    //   5619: invokevirtual toByteArray : ()[B
    //   5622: invokevirtual write : ([B)V
    //   5625: aload #4
    //   5627: getstatic burp/Zx58.ZE : Ljava/lang/Object;
    //   5630: checkcast java/math/BigInteger
    //   5633: invokevirtual toByteArray : ()[B
    //   5636: invokevirtual write : ([B)V
    //   5639: aload #4
    //   5641: getstatic burp/Zs00.ZF : Ljava/lang/Object;
    //   5644: checkcast java/math/BigInteger
    //   5647: invokevirtual toByteArray : ()[B
    //   5650: invokevirtual write : ([B)V
    //   5653: aload #4
    //   5655: invokevirtual toByteArray : ()[B
    //   5658: astore #5
    //   5660: aconst_null
    //   5661: astore #6
    //   5663: invokestatic a : (II)Ljava/lang/String;
    //   5666: invokestatic forName : (Ljava/lang/String;)Ljava/lang/Class;
    //   5669: invokevirtual getDeclaredMethods : ()[Ljava/lang/reflect/Method;
    //   5672: astore #7
    //   5674: aload #7
    //   5676: arraylength
    //   5677: istore #8
    //   5679: iconst_0
    //   5680: istore #9
    //   5682: iload #9
    //   5684: iload #8
    //   5686: if_icmpge -> 5814
    //   5689: aload #7
    //   5691: iload #9
    //   5693: aaload
    //   5694: astore #10
    //   5696: aload #10
    //   5698: invokevirtual getName : ()Ljava/lang/String;
    //   5701: sipush #16742
    //   5704: sipush #27498
    //   5707: invokestatic a : (II)Ljava/lang/String;
    //   5710: invokevirtual equals : (Ljava/lang/Object;)Z
    //   5713: ifeq -> 5807
    //   5716: aload #10
    //   5718: invokevirtual getParameterTypes : ()[Ljava/lang/Class;
    //   5721: astore #11
    //   5723: aload #11
    //   5725: arraylength
    //   5726: iconst_4
    //   5727: if_icmpeq -> 5737
    //   5730: goto -> 5807
    //   5733: invokestatic a : (Ljava/lang/Throwable;)Ljava/lang/Throwable;
    //   5736: athrow
    //   5737: aload #11
    //   5739: iconst_0
    //   5740: aaload
    //   5741: ldc java/lang/String
    //   5743: if_acmpeq -> 5753
    //   5746: goto -> 5807
    //   5749: invokestatic a : (Ljava/lang/Throwable;)Ljava/lang/Throwable;
    //   5752: athrow
    //   5753: aload #11
    //   5755: iconst_1
    //   5756: aaload
    //   5757: ldc [B
    //   5759: if_acmpeq -> 5769
    //   5762: goto -> 5807
    //   5765: invokestatic a : (Ljava/lang/Throwable;)Ljava/lang/Throwable;
    //   5768: athrow
    //   5769: aload #11
    //   5771: iconst_2
    //   5772: aaload
    //   5773: getstatic java/lang/Integer.TYPE : Ljava/lang/Class;
    //   5776: if_acmpeq -> 5786
    //   5779: goto -> 5807
    //   5782: invokestatic a : (Ljava/lang/Throwable;)Ljava/lang/Throwable;
    //   5785: athrow
    //   5786: aload #11
    //   5788: iconst_3
    //   5789: aaload
    //   5790: getstatic java/lang/Integer.TYPE : Ljava/lang/Class;
    //   5793: if_acmpeq -> 5803
    //   5796: goto -> 5807
    //   5799: invokestatic a : (Ljava/lang/Throwable;)Ljava/lang/Throwable;
    //   5802: athrow
    //   5803: aload #10
    //   5805: astore #6
    //   5807: iinc #9, 1
    //   5810: iload_2
    //   5811: ifeq -> 5682
    //   5814: aload #6
    //   5816: iconst_1
    //   5817: invokevirtual setAccessible : (Z)V
    //   5820: ldc burp/Zz4r
    //   5822: iconst_0
    //   5823: anewarray java/lang/Class
    //   5826: invokevirtual getDeclaredConstructor : ([Ljava/lang/Class;)Ljava/lang/reflect/Constructor;
    //   5829: astore #7
    //   5831: aload #7
    //   5833: iconst_1
    //   5834: invokevirtual setAccessible : (Z)V
    //   5837: aload #6
    //   5839: aload #7
    //   5841: iconst_0
    //   5842: anewarray java/lang/Object
    //   5845: invokevirtual newInstance : ([Ljava/lang/Object;)Ljava/lang/Object;
    //   5848: iconst_4
    //   5849: anewarray java/lang/Object
    //   5852: dup
    //   5853: iconst_0
    //   5854: sipush #16736
    //   5857: sipush #24186
    //   5860: invokestatic a : (II)Ljava/lang/String;
    //   5863: aastore
    //   5864: dup
    //   5865: iconst_1
    //   5866: aload #5
    //   5868: aastore
    //   5869: dup
    //   5870: iconst_2
    //   5871: iconst_0
    //   5872: invokestatic valueOf : (I)Ljava/lang/Integer;
    //   5875: aastore
    //   5876: dup
    //   5877: iconst_3
    //   5878: aload #5
    //   5880: arraylength
    //   5881: invokestatic valueOf : (I)Ljava/lang/Integer;
    //   5884: aastore
    //   5885: invokevirtual invoke : (Ljava/lang/Object;[Ljava/lang/Object;)Ljava/lang/Object;
    //   5888: pop
    //   5889: goto -> 5894
    //   5892: astore #4
    //   5894: iconst_0
    //   5895: istore #4
    //   5897: getstatic burp/Zz9v.Zv : Ljava/lang/String;
    //   5900: getstatic burp/Zl3n.Zh : Ljava/lang/Object;
    //   5903: checkcast java/math/BigInteger
    //   5906: invokevirtual intValue : ()I
    //   5909: bipush #32
    //   5911: irem
    //   5912: invokestatic abs : (I)I
    //   5915: invokevirtual charAt : (I)C
    //   5918: getstatic burp/Zb_c.ZS : Ljava/lang/String;
    //   5921: getstatic burp/Ze_b.Zp : Ljava/lang/Object;
    //   5924: checkcast java/math/BigInteger
    //   5927: invokevirtual intValue : ()I
    //   5930: bipush #32
    //   5932: irem
    //   5933: invokestatic abs : (I)I
    //   5936: invokevirtual charAt : (I)C
    //   5939: if_icmpgt -> 6284
    //   5942: sipush #16762
    //   5945: sipush #29077
    //   5948: invokestatic a : (II)Ljava/lang/String;
    //   5951: iconst_1
    //   5952: ldc burp/Zb8y
    //   5954: invokevirtual getClassLoader : ()Ljava/lang/ClassLoader;
    //   5957: invokestatic forName : (Ljava/lang/String;ZLjava/lang/ClassLoader;)Ljava/lang/Class;
    //   5960: invokevirtual getDeclaredFields : ()[Ljava/lang/reflect/Field;
    //   5963: astore #5
    //   5965: aload #5
    //   5967: arraylength
    //   5968: istore #6
    //   5970: iconst_0
    //   5971: istore #7
    //   5973: iload #7
    //   5975: iload #6
    //   5977: if_icmpge -> 6115
    //   5980: aload #5
    //   5982: iload #7
    //   5984: aaload
    //   5985: astore #8
    //   5987: aload #8
    //   5989: invokevirtual getModifiers : ()I
    //   5992: invokestatic isStatic : (I)Z
    //   5995: ifne -> 6005
    //   5998: goto -> 6108
    //   6001: invokestatic a : (Ljava/lang/Throwable;)Ljava/lang/Throwable;
    //   6004: athrow
    //   6005: aload #8
    //   6007: invokevirtual getType : ()Ljava/lang/Class;
    //   6010: astore #9
    //   6012: aload #9
    //   6014: ifnull -> 6095
    //   6017: aload #9
    //   6019: invokevirtual isPrimitive : ()Z
    //   6022: ifne -> 6095
    //   6025: goto -> 6032
    //   6028: invokestatic a : (Ljava/lang/Throwable;)Ljava/lang/Throwable;
    //   6031: athrow
    //   6032: aload #9
    //   6034: invokevirtual getPackage : ()Ljava/lang/Package;
    //   6037: ifnull -> 6095
    //   6040: goto -> 6047
    //   6043: invokestatic a : (Ljava/lang/Throwable;)Ljava/lang/Throwable;
    //   6046: athrow
    //   6047: aload #9
    //   6049: invokevirtual getPackage : ()Ljava/lang/Package;
    //   6052: invokevirtual getName : ()Ljava/lang/String;
    //   6055: ifnull -> 6095
    //   6058: goto -> 6065
    //   6061: invokestatic a : (Ljava/lang/Throwable;)Ljava/lang/Throwable;
    //   6064: athrow
    //   6065: aload #9
    //   6067: invokevirtual getPackage : ()Ljava/lang/Package;
    //   6070: invokevirtual getName : ()Ljava/lang/String;
    //   6073: sipush #16767
    //   6076: sipush #-11618
    //   6079: invokestatic a : (II)Ljava/lang/String;
    //   6082: invokevirtual startsWith : (Ljava/lang/String;)Z
    //   6085: ifne -> 6095
    //   6088: goto -> 6095
    //   6091: invokestatic a : (Ljava/lang/Throwable;)Ljava/lang/Throwable;
    //   6094: athrow
    //   6095: aload #8
    //   6097: iconst_1
    //   6098: invokevirtual setAccessible : (Z)V
    //   6101: aload #8
    //   6103: aconst_null
    //   6104: invokevirtual get : (Ljava/lang/Object;)Ljava/lang/Object;
    //   6107: pop
    //   6108: iinc #7, 1
    //   6111: iload_2
    //   6112: ifeq -> 5973
    //   6115: sipush #16746
    //   6118: sipush #-3515
    //   6121: invokestatic a : (II)Ljava/lang/String;
    //   6124: invokestatic forName : (Ljava/lang/String;)Ljava/lang/Class;
    //   6127: invokevirtual getDeclaredMethods : ()[Ljava/lang/reflect/Method;
    //   6130: astore #5
    //   6132: aload #5
    //   6134: arraylength
    //   6135: istore #6
    //   6137: iconst_0
    //   6138: istore #7
    //   6140: iload #7
    //   6142: iload #6
    //   6144: if_icmpge -> 6281
    //   6147: aload #5
    //   6149: iload #7
    //   6151: aaload
    //   6152: astore #8
    //   6154: aload #8
    //   6156: invokevirtual getParameterTypes : ()[Ljava/lang/Class;
    //   6159: pop
    //   6160: aload #8
    //   6162: invokevirtual getModifiers : ()I
    //   6165: invokestatic isStatic : (I)Z
    //   6168: ifeq -> 6267
    //   6171: aload #8
    //   6173: invokevirtual getParameterTypes : ()[Ljava/lang/Class;
    //   6176: arraylength
    //   6177: iconst_2
    //   6178: if_icmpne -> 6267
    //   6181: goto -> 6188
    //   6184: invokestatic a : (Ljava/lang/Throwable;)Ljava/lang/Throwable;
    //   6187: athrow
    //   6188: aload #8
    //   6190: invokevirtual getReturnType : ()Ljava/lang/Class;
    //   6193: getstatic java/lang/Boolean.TYPE : Ljava/lang/Class;
    //   6196: if_acmpne -> 6267
    //   6199: goto -> 6206
    //   6202: invokestatic a : (Ljava/lang/Throwable;)Ljava/lang/Throwable;
    //   6205: athrow
    //   6206: aload #8
    //   6208: iconst_1
    //   6209: invokevirtual setAccessible : (Z)V
    //   6212: aload #8
    //   6214: aconst_null
    //   6215: iconst_2
    //   6216: anewarray java/lang/Object
    //   6219: dup
    //   6220: iconst_0
    //   6221: aload_0
    //   6222: aastore
    //   6223: dup
    //   6224: iconst_1
    //   6225: aload_1
    //   6226: ifnonnull -> 6244
    //   6229: goto -> 6236
    //   6232: invokestatic a : (Ljava/lang/Throwable;)Ljava/lang/Throwable;
    //   6235: athrow
    //   6236: aload_1
    //   6237: goto -> 6251
    //   6240: invokestatic a : (Ljava/lang/Throwable;)Ljava/lang/Throwable;
    //   6243: athrow
    //   6244: aload_1
    //   6245: checkcast [B
    //   6248: invokevirtual clone : ()Ljava/lang/Object;
    //   6251: aastore
    //   6252: invokevirtual invoke : (Ljava/lang/Object;[Ljava/lang/Object;)Ljava/lang/Object;
    //   6255: checkcast java/lang/Boolean
    //   6258: invokevirtual booleanValue : ()Z
    //   6261: istore #4
    //   6263: iload_2
    //   6264: ifeq -> 6281
    //   6267: iinc #7, 1
    //   6270: iload_2
    //   6271: ifeq -> 6140
    //   6274: goto -> 6281
    //   6277: invokestatic a : (Ljava/lang/Throwable;)Ljava/lang/Throwable;
    //   6280: athrow
    //   6281: goto -> 6623
    //   6284: sipush #16732
    //   6287: sipush #6765
    //   6290: invokestatic a : (II)Ljava/lang/String;
    //   6293: iconst_1
    //   6294: ldc burp/Zl22
    //   6296: invokevirtual getClassLoader : ()Ljava/lang/ClassLoader;
    //   6299: invokestatic forName : (Ljava/lang/String;ZLjava/lang/ClassLoader;)Ljava/lang/Class;
    //   6302: invokevirtual getDeclaredFields : ()[Ljava/lang/reflect/Field;
    //   6305: astore #5
    //   6307: aload #5
    //   6309: arraylength
    //   6310: istore #6
    //   6312: iconst_0
    //   6313: istore #7
    //   6315: iload #7
    //   6317: iload #6
    //   6319: if_icmpge -> 6457
    //   6322: aload #5
    //   6324: iload #7
    //   6326: aaload
    //   6327: astore #8
    //   6329: aload #8
    //   6331: invokevirtual getModifiers : ()I
    //   6334: invokestatic isStatic : (I)Z
    //   6337: ifne -> 6347
    //   6340: goto -> 6450
    //   6343: invokestatic a : (Ljava/lang/Throwable;)Ljava/lang/Throwable;
    //   6346: athrow
    //   6347: aload #8
    //   6349: invokevirtual getType : ()Ljava/lang/Class;
    //   6352: astore #9
    //   6354: aload #9
    //   6356: ifnull -> 6437
    //   6359: aload #9
    //   6361: invokevirtual isPrimitive : ()Z
    //   6364: ifne -> 6437
    //   6367: goto -> 6374
    //   6370: invokestatic a : (Ljava/lang/Throwable;)Ljava/lang/Throwable;
    //   6373: athrow
    //   6374: aload #9
    //   6376: invokevirtual getPackage : ()Ljava/lang/Package;
    //   6379: ifnull -> 6437
    //   6382: goto -> 6389
    //   6385: invokestatic a : (Ljava/lang/Throwable;)Ljava/lang/Throwable;
    //   6388: athrow
    //   6389: aload #9
    //   6391: invokevirtual getPackage : ()Ljava/lang/Package;
    //   6394: invokevirtual getName : ()Ljava/lang/String;
    //   6397: ifnull -> 6437
    //   6400: goto -> 6407
    //   6403: invokestatic a : (Ljava/lang/Throwable;)Ljava/lang/Throwable;
    //   6406: athrow
    //   6407: aload #9
    //   6409: invokevirtual getPackage : ()Ljava/lang/Package;
    //   6412: invokevirtual getName : ()Ljava/lang/String;
    //   6415: sipush #16767
    //   6418: sipush #-11618
    //   6421: invokestatic a : (II)Ljava/lang/String;
    //   6424: invokevirtual startsWith : (Ljava/lang/String;)Z
    //   6427: ifne -> 6437
    //   6430: goto -> 6437
    //   6433: invokestatic a : (Ljava/lang/Throwable;)Ljava/lang/Throwable;
    //   6436: athrow
    //   6437: aload #8
    //   6439: iconst_1
    //   6440: invokevirtual setAccessible : (Z)V
    //   6443: aload #8
    //   6445: aconst_null
    //   6446: invokevirtual get : (Ljava/lang/Object;)Ljava/lang/Object;
    //   6449: pop
    //   6450: iinc #7, 1
    //   6453: iload_2
    //   6454: ifeq -> 6315
    //   6457: sipush #16743
    //   6460: sipush #-11000
    //   6463: invokestatic a : (II)Ljava/lang/String;
    //   6466: invokestatic forName : (Ljava/lang/String;)Ljava/lang/Class;
    //   6469: invokevirtual getDeclaredMethods : ()[Ljava/lang/reflect/Method;
    //   6472: astore #5
    //   6474: aload #5
    //   6476: arraylength
    //   6477: istore #6
    //   6479: iconst_0
    //   6480: istore #7
    //   6482: iload #7
    //   6484: iload #6
    //   6486: if_icmpge -> 6623
    //   6489: aload #5
    //   6491: iload #7
    //   6493: aaload
    //   6494: astore #8
    //   6496: aload #8
    //   6498: invokevirtual getParameterTypes : ()[Ljava/lang/Class;
    //   6501: pop
    //   6502: aload #8
    //   6504: invokevirtual getModifiers : ()I
    //   6507: invokestatic isStatic : (I)Z
    //   6510: ifeq -> 6609
    //   6513: aload #8
    //   6515: invokevirtual getParameterTypes : ()[Ljava/lang/Class;
    //   6518: arraylength
    //   6519: iconst_2
    //   6520: if_icmpne -> 6609
    //   6523: goto -> 6530
    //   6526: invokestatic a : (Ljava/lang/Throwable;)Ljava/lang/Throwable;
    //   6529: athrow
    //   6530: aload #8
    //   6532: invokevirtual getReturnType : ()Ljava/lang/Class;
    //   6535: getstatic java/lang/Boolean.TYPE : Ljava/lang/Class;
    //   6538: if_acmpne -> 6609
    //   6541: goto -> 6548
    //   6544: invokestatic a : (Ljava/lang/Throwable;)Ljava/lang/Throwable;
    //   6547: athrow
    //   6548: aload #8
    //   6550: iconst_1
    //   6551: invokevirtual setAccessible : (Z)V
    //   6554: aload #8
    //   6556: aconst_null
    //   6557: iconst_2
    //   6558: anewarray java/lang/Object
    //   6561: dup
    //   6562: iconst_0
    //   6563: aload_0
    //   6564: aastore
    //   6565: dup
    //   6566: iconst_1
    //   6567: aload_1
    //   6568: ifnonnull -> 6586
    //   6571: goto -> 6578
    //   6574: invokestatic a : (Ljava/lang/Throwable;)Ljava/lang/Throwable;
    //   6577: athrow
    //   6578: aload_1
    //   6579: goto -> 6593
    //   6582: invokestatic a : (Ljava/lang/Throwable;)Ljava/lang/Throwable;
    //   6585: athrow
    //   6586: aload_1
    //   6587: checkcast [B
    //   6590: invokevirtual clone : ()Ljava/lang/Object;
    //   6593: aastore
    //   6594: invokevirtual invoke : (Ljava/lang/Object;[Ljava/lang/Object;)Ljava/lang/Object;
    //   6597: checkcast java/lang/Boolean
    //   6600: invokevirtual booleanValue : ()Z
    //   6603: istore #4
    //   6605: iload_2
    //   6606: ifeq -> 6623
    //   6609: iinc #7, 1
    //   6612: iload_2
    //   6613: ifeq -> 6482
    //   6616: goto -> 6623
    //   6619: invokestatic a : (Ljava/lang/Throwable;)Ljava/lang/Throwable;
    //   6622: athrow
    //   6623: iload #4
    //   6625: ifeq -> 6631
    //   6628: iload #4
    //   6630: ireturn
    //   6631: getstatic burp/Zdm.ZJ : Ljava/lang/String;
    //   6634: getstatic burp/Zle4.Zh : Ljava/lang/Object;
    //   6637: checkcast java/math/BigInteger
    //   6640: invokevirtual intValue : ()I
    //   6643: bipush #32
    //   6645: irem
    //   6646: invokestatic abs : (I)I
    //   6649: invokevirtual charAt : (I)C
    //   6652: getstatic burp/Zmh5.Zh : Ljava/lang/String;
    //   6655: getstatic burp/Zr_y.ZI : Ljava/lang/Object;
    //   6658: checkcast java/math/BigInteger
    //   6661: invokevirtual intValue : ()I
    //   6664: bipush #32
    //   6666: irem
    //   6667: invokestatic abs : (I)I
    //   6670: invokevirtual charAt : (I)C
    //   6673: if_icmple -> 7019
    //   6676: sipush #16739
    //   6679: sipush #7135
    //   6682: invokestatic a : (II)Ljava/lang/String;
    //   6685: iconst_1
    //   6686: ldc burp/Zmuj
    //   6688: invokevirtual getClassLoader : ()Ljava/lang/ClassLoader;
    //   6691: invokestatic forName : (Ljava/lang/String;ZLjava/lang/ClassLoader;)Ljava/lang/Class;
    //   6694: invokevirtual getDeclaredFields : ()[Ljava/lang/reflect/Field;
    //   6697: astore #5
    //   6699: aload #5
    //   6701: arraylength
    //   6702: istore #6
    //   6704: iconst_0
    //   6705: istore #7
    //   6707: iload #7
    //   6709: iload #6
    //   6711: if_icmpge -> 6849
    //   6714: aload #5
    //   6716: iload #7
    //   6718: aaload
    //   6719: astore #8
    //   6721: aload #8
    //   6723: invokevirtual getModifiers : ()I
    //   6726: invokestatic isStatic : (I)Z
    //   6729: ifne -> 6739
    //   6732: goto -> 6842
    //   6735: invokestatic a : (Ljava/lang/Throwable;)Ljava/lang/Throwable;
    //   6738: athrow
    //   6739: aload #8
    //   6741: invokevirtual getType : ()Ljava/lang/Class;
    //   6744: astore #9
    //   6746: aload #9
    //   6748: ifnull -> 6829
    //   6751: aload #9
    //   6753: invokevirtual isPrimitive : ()Z
    //   6756: ifne -> 6829
    //   6759: goto -> 6766
    //   6762: invokestatic a : (Ljava/lang/Throwable;)Ljava/lang/Throwable;
    //   6765: athrow
    //   6766: aload #9
    //   6768: invokevirtual getPackage : ()Ljava/lang/Package;
    //   6771: ifnull -> 6829
    //   6774: goto -> 6781
    //   6777: invokestatic a : (Ljava/lang/Throwable;)Ljava/lang/Throwable;
    //   6780: athrow
    //   6781: aload #9
    //   6783: invokevirtual getPackage : ()Ljava/lang/Package;
    //   6786: invokevirtual getName : ()Ljava/lang/String;
    //   6789: ifnull -> 6829
    //   6792: goto -> 6799
    //   6795: invokestatic a : (Ljava/lang/Throwable;)Ljava/lang/Throwable;
    //   6798: athrow
    //   6799: aload #9
    //   6801: invokevirtual getPackage : ()Ljava/lang/Package;
    //   6804: invokevirtual getName : ()Ljava/lang/String;
    //   6807: sipush #16767
    //   6810: sipush #-11618
    //   6813: invokestatic a : (II)Ljava/lang/String;
    //   6816: invokevirtual startsWith : (Ljava/lang/String;)Z
    //   6819: ifne -> 6829
    //   6822: goto -> 6829
    //   6825: invokestatic a : (Ljava/lang/Throwable;)Ljava/lang/Throwable;
    //   6828: athrow
    //   6829: aload #8
    //   6831: iconst_1
    //   6832: invokevirtual setAccessible : (Z)V
    //   6835: aload #8
    //   6837: aconst_null
    //   6838: invokevirtual get : (Ljava/lang/Object;)Ljava/lang/Object;
    //   6841: pop
    //   6842: iinc #7, 1
    //   6845: iload_2
    //   6846: ifeq -> 6707
    //   6849: sipush #16756
    //   6852: sipush #-25832
    //   6855: invokestatic a : (II)Ljava/lang/String;
    //   6858: invokestatic forName : (Ljava/lang/String;)Ljava/lang/Class;
    //   6861: invokevirtual getDeclaredMethods : ()[Ljava/lang/reflect/Method;
    //   6864: astore #5
    //   6866: aload #5
    //   6868: arraylength
    //   6869: istore #6
    //   6871: iconst_0
    //   6872: istore #7
    //   6874: iload #7
    //   6876: iload #6
    //   6878: if_icmpge -> 7015
    //   6881: aload #5
    //   6883: iload #7
    //   6885: aaload
    //   6886: astore #8
    //   6888: aload #8
    //   6890: invokevirtual getParameterTypes : ()[Ljava/lang/Class;
    //   6893: pop
    //   6894: aload #8
    //   6896: invokevirtual getModifiers : ()I
    //   6899: invokestatic isStatic : (I)Z
    //   6902: ifeq -> 7001
    //   6905: aload #8
    //   6907: invokevirtual getParameterTypes : ()[Ljava/lang/Class;
    //   6910: arraylength
    //   6911: iconst_2
    //   6912: if_icmpne -> 7001
    //   6915: goto -> 6922
    //   6918: invokestatic a : (Ljava/lang/Throwable;)Ljava/lang/Throwable;
    //   6921: athrow
    //   6922: aload #8
    //   6924: invokevirtual getReturnType : ()Ljava/lang/Class;
    //   6927: getstatic java/lang/Boolean.TYPE : Ljava/lang/Class;
    //   6930: if_acmpne -> 7001
    //   6933: goto -> 6940
    //   6936: invokestatic a : (Ljava/lang/Throwable;)Ljava/lang/Throwable;
    //   6939: athrow
    //   6940: aload #8
    //   6942: iconst_1
    //   6943: invokevirtual setAccessible : (Z)V
    //   6946: aload #8
    //   6948: aconst_null
    //   6949: iconst_2
    //   6950: anewarray java/lang/Object
    //   6953: dup
    //   6954: iconst_0
    //   6955: aload_0
    //   6956: aastore
    //   6957: dup
    //   6958: iconst_1
    //   6959: aload_1
    //   6960: ifnonnull -> 6978
    //   6963: goto -> 6970
    //   6966: invokestatic a : (Ljava/lang/Throwable;)Ljava/lang/Throwable;
    //   6969: athrow
    //   6970: aload_1
    //   6971: goto -> 6985
    //   6974: invokestatic a : (Ljava/lang/Throwable;)Ljava/lang/Throwable;
    //   6977: athrow
    //   6978: aload_1
    //   6979: checkcast [B
    //   6982: invokevirtual clone : ()Ljava/lang/Object;
    //   6985: aastore
    //   6986: invokevirtual invoke : (Ljava/lang/Object;[Ljava/lang/Object;)Ljava/lang/Object;
    //   6989: checkcast java/lang/Boolean
    //   6992: invokevirtual booleanValue : ()Z
    //   6995: istore #4
    //   6997: iload_2
    //   6998: ifeq -> 7015
    //   7001: iinc #7, 1
    //   7004: iload_2
    //   7005: ifeq -> 6874
    //   7008: goto -> 7015
    //   7011: invokestatic a : (Ljava/lang/Throwable;)Ljava/lang/Throwable;
    //   7014: athrow
    //   7015: iload_2
    //   7016: ifeq -> 7358
    //   7019: sipush #16765
    //   7022: sipush #-14992
    //   7025: invokestatic a : (II)Ljava/lang/String;
    //   7028: iconst_1
    //   7029: ldc burp/Zr4z
    //   7031: invokevirtual getClassLoader : ()Ljava/lang/ClassLoader;
    //   7034: invokestatic forName : (Ljava/lang/String;ZLjava/lang/ClassLoader;)Ljava/lang/Class;
    //   7037: invokevirtual getDeclaredFields : ()[Ljava/lang/reflect/Field;
    //   7040: astore #5
    //   7042: aload #5
    //   7044: arraylength
    //   7045: istore #6
    //   7047: iconst_0
    //   7048: istore #7
    //   7050: iload #7
    //   7052: iload #6
    //   7054: if_icmpge -> 7192
    //   7057: aload #5
    //   7059: iload #7
    //   7061: aaload
    //   7062: astore #8
    //   7064: aload #8
    //   7066: invokevirtual getModifiers : ()I
    //   7069: invokestatic isStatic : (I)Z
    //   7072: ifne -> 7082
    //   7075: goto -> 7185
    //   7078: invokestatic a : (Ljava/lang/Throwable;)Ljava/lang/Throwable;
    //   7081: athrow
    //   7082: aload #8
    //   7084: invokevirtual getType : ()Ljava/lang/Class;
    //   7087: astore #9
    //   7089: aload #9
    //   7091: ifnull -> 7172
    //   7094: aload #9
    //   7096: invokevirtual isPrimitive : ()Z
    //   7099: ifne -> 7172
    //   7102: goto -> 7109
    //   7105: invokestatic a : (Ljava/lang/Throwable;)Ljava/lang/Throwable;
    //   7108: athrow
    //   7109: aload #9
    //   7111: invokevirtual getPackage : ()Ljava/lang/Package;
    //   7114: ifnull -> 7172
    //   7117: goto -> 7124
    //   7120: invokestatic a : (Ljava/lang/Throwable;)Ljava/lang/Throwable;
    //   7123: athrow
    //   7124: aload #9
    //   7126: invokevirtual getPackage : ()Ljava/lang/Package;
    //   7129: invokevirtual getName : ()Ljava/lang/String;
    //   7132: ifnull -> 7172
    //   7135: goto -> 7142
    //   7138: invokestatic a : (Ljava/lang/Throwable;)Ljava/lang/Throwable;
    //   7141: athrow
    //   7142: aload #9
    //   7144: invokevirtual getPackage : ()Ljava/lang/Package;
    //   7147: invokevirtual getName : ()Ljava/lang/String;
    //   7150: sipush #16767
    //   7153: sipush #-11618
    //   7156: invokestatic a : (II)Ljava/lang/String;
    //   7159: invokevirtual startsWith : (Ljava/lang/String;)Z
    //   7162: ifne -> 7172
    //   7165: goto -> 7172
    //   7168: invokestatic a : (Ljava/lang/Throwable;)Ljava/lang/Throwable;
    //   7171: athrow
    //   7172: aload #8
    //   7174: iconst_1
    //   7175: invokevirtual setAccessible : (Z)V
    //   7178: aload #8
    //   7180: aconst_null
    //   7181: invokevirtual get : (Ljava/lang/Object;)Ljava/lang/Object;
    //   7184: pop
    //   7185: iinc #7, 1
    //   7188: iload_2
    //   7189: ifeq -> 7050
    //   7192: sipush #16759
    //   7195: sipush #23437
    //   7198: invokestatic a : (II)Ljava/lang/String;
    //   7201: invokestatic forName : (Ljava/lang/String;)Ljava/lang/Class;
    //   7204: invokevirtual getDeclaredMethods : ()[Ljava/lang/reflect/Method;
    //   7207: astore #5
    //   7209: aload #5
    //   7211: arraylength
    //   7212: istore #6
    //   7214: iconst_0
    //   7215: istore #7
    //   7217: iload #7
    //   7219: iload #6
    //   7221: if_icmpge -> 7358
    //   7224: aload #5
    //   7226: iload #7
    //   7228: aaload
    //   7229: astore #8
    //   7231: aload #8
    //   7233: invokevirtual getParameterTypes : ()[Ljava/lang/Class;
    //   7236: pop
    //   7237: aload #8
    //   7239: invokevirtual getModifiers : ()I
    //   7242: invokestatic isStatic : (I)Z
    //   7245: ifeq -> 7344
    //   7248: aload #8
    //   7250: invokevirtual getParameterTypes : ()[Ljava/lang/Class;
    //   7253: arraylength
    //   7254: iconst_2
    //   7255: if_icmpne -> 7344
    //   7258: goto -> 7265
    //   7261: invokestatic a : (Ljava/lang/Throwable;)Ljava/lang/Throwable;
    //   7264: athrow
    //   7265: aload #8
    //   7267: invokevirtual getReturnType : ()Ljava/lang/Class;
    //   7270: getstatic java/lang/Boolean.TYPE : Ljava/lang/Class;
    //   7273: if_acmpne -> 7344
    //   7276: goto -> 7283
    //   7279: invokestatic a : (Ljava/lang/Throwable;)Ljava/lang/Throwable;
    //   7282: athrow
    //   7283: aload #8
    //   7285: iconst_1
    //   7286: invokevirtual setAccessible : (Z)V
    //   7289: aload #8
    //   7291: aconst_null
    //   7292: iconst_2
    //   7293: anewarray java/lang/Object
    //   7296: dup
    //   7297: iconst_0
    //   7298: aload_0
    //   7299: aastore
    //   7300: dup
    //   7301: iconst_1
    //   7302: aload_1
    //   7303: ifnonnull -> 7321
    //   7306: goto -> 7313
    //   7309: invokestatic a : (Ljava/lang/Throwable;)Ljava/lang/Throwable;
    //   7312: athrow
    //   7313: aload_1
    //   7314: goto -> 7328
    //   7317: invokestatic a : (Ljava/lang/Throwable;)Ljava/lang/Throwable;
    //   7320: athrow
    //   7321: aload_1
    //   7322: checkcast [B
    //   7325: invokevirtual clone : ()Ljava/lang/Object;
    //   7328: aastore
    //   7329: invokevirtual invoke : (Ljava/lang/Object;[Ljava/lang/Object;)Ljava/lang/Object;
    //   7332: checkcast java/lang/Boolean
    //   7335: invokevirtual booleanValue : ()Z
    //   7338: istore #4
    //   7340: iload_2
    //   7341: ifeq -> 7358
    //   7344: iinc #7, 1
    //   7347: iload_2
    //   7348: ifeq -> 7217
    //   7351: goto -> 7358
    //   7354: invokestatic a : (Ljava/lang/Throwable;)Ljava/lang/Throwable;
    //   7357: athrow
    //   7358: iload #4
    //   7360: ifeq -> 7366
    //   7363: iload #4
    //   7365: ireturn
    //   7366: getstatic burp/Zgvf.ZM : Ljava/lang/String;
    //   7369: getstatic burp/Zmcq.Zh : Ljava/lang/Object;
    //   7372: checkcast java/math/BigInteger
    //   7375: invokevirtual intValue : ()I
    //   7378: bipush #32
    //   7380: irem
    //   7381: invokestatic abs : (I)I
    //   7384: invokevirtual charAt : (I)C
    //   7387: getstatic burp/Zexu.Zp : Ljava/lang/String;
    //   7390: getstatic burp/Zb6b.ZU : Ljava/lang/Object;
    //   7393: checkcast java/math/BigInteger
    //   7396: invokevirtual intValue : ()I
    //   7399: bipush #32
    //   7401: irem
    //   7402: invokestatic abs : (I)I
    //   7405: invokevirtual charAt : (I)C
    //   7408: if_icmple -> 7754
    //   7411: sipush #16753
    //   7414: sipush #-6597
    //   7417: invokestatic a : (II)Ljava/lang/String;
    //   7420: iconst_1
    //   7421: ldc burp/Zrom
    //   7423: invokevirtual getClassLoader : ()Ljava/lang/ClassLoader;
    //   7426: invokestatic forName : (Ljava/lang/String;ZLjava/lang/ClassLoader;)Ljava/lang/Class;
    //   7429: invokevirtual getDeclaredFields : ()[Ljava/lang/reflect/Field;
    //   7432: astore #5
    //   7434: aload #5
    //   7436: arraylength
    //   7437: istore #6
    //   7439: iconst_0
    //   7440: istore #7
    //   7442: iload #7
    //   7444: iload #6
    //   7446: if_icmpge -> 7584
    //   7449: aload #5
    //   7451: iload #7
    //   7453: aaload
    //   7454: astore #8
    //   7456: aload #8
    //   7458: invokevirtual getModifiers : ()I
    //   7461: invokestatic isStatic : (I)Z
    //   7464: ifne -> 7474
    //   7467: goto -> 7577
    //   7470: invokestatic a : (Ljava/lang/Throwable;)Ljava/lang/Throwable;
    //   7473: athrow
    //   7474: aload #8
    //   7476: invokevirtual getType : ()Ljava/lang/Class;
    //   7479: astore #9
    //   7481: aload #9
    //   7483: ifnull -> 7564
    //   7486: aload #9
    //   7488: invokevirtual isPrimitive : ()Z
    //   7491: ifne -> 7564
    //   7494: goto -> 7501
    //   7497: invokestatic a : (Ljava/lang/Throwable;)Ljava/lang/Throwable;
    //   7500: athrow
    //   7501: aload #9
    //   7503: invokevirtual getPackage : ()Ljava/lang/Package;
    //   7506: ifnull -> 7564
    //   7509: goto -> 7516
    //   7512: invokestatic a : (Ljava/lang/Throwable;)Ljava/lang/Throwable;
    //   7515: athrow
    //   7516: aload #9
    //   7518: invokevirtual getPackage : ()Ljava/lang/Package;
    //   7521: invokevirtual getName : ()Ljava/lang/String;
    //   7524: ifnull -> 7564
    //   7527: goto -> 7534
    //   7530: invokestatic a : (Ljava/lang/Throwable;)Ljava/lang/Throwable;
    //   7533: athrow
    //   7534: aload #9
    //   7536: invokevirtual getPackage : ()Ljava/lang/Package;
    //   7539: invokevirtual getName : ()Ljava/lang/String;
    //   7542: sipush #16767
    //   7545: sipush #-11618
    //   7548: invokestatic a : (II)Ljava/lang/String;
    //   7551: invokevirtual startsWith : (Ljava/lang/String;)Z
    //   7554: ifne -> 7564
    //   7557: goto -> 7564
    //   7560: invokestatic a : (Ljava/lang/Throwable;)Ljava/lang/Throwable;
    //   7563: athrow
    //   7564: aload #8
    //   7566: iconst_1
    //   7567: invokevirtual setAccessible : (Z)V
    //   7570: aload #8
    //   7572: aconst_null
    //   7573: invokevirtual get : (Ljava/lang/Object;)Ljava/lang/Object;
    //   7576: pop
    //   7577: iinc #7, 1
    //   7580: iload_2
    //   7581: ifeq -> 7442
    //   7584: sipush #16757
    //   7587: sipush #-18180
    //   7590: invokestatic a : (II)Ljava/lang/String;
    //   7593: invokestatic forName : (Ljava/lang/String;)Ljava/lang/Class;
    //   7596: invokevirtual getDeclaredMethods : ()[Ljava/lang/reflect/Method;
    //   7599: astore #5
    //   7601: aload #5
    //   7603: arraylength
    //   7604: istore #6
    //   7606: iconst_0
    //   7607: istore #7
    //   7609: iload #7
    //   7611: iload #6
    //   7613: if_icmpge -> 7750
    //   7616: aload #5
    //   7618: iload #7
    //   7620: aaload
    //   7621: astore #8
    //   7623: aload #8
    //   7625: invokevirtual getParameterTypes : ()[Ljava/lang/Class;
    //   7628: pop
    //   7629: aload #8
    //   7631: invokevirtual getModifiers : ()I
    //   7634: invokestatic isStatic : (I)Z
    //   7637: ifeq -> 7736
    //   7640: aload #8
    //   7642: invokevirtual getParameterTypes : ()[Ljava/lang/Class;
    //   7645: arraylength
    //   7646: iconst_2
    //   7647: if_icmpne -> 7736
    //   7650: goto -> 7657
    //   7653: invokestatic a : (Ljava/lang/Throwable;)Ljava/lang/Throwable;
    //   7656: athrow
    //   7657: aload #8
    //   7659: invokevirtual getReturnType : ()Ljava/lang/Class;
    //   7662: getstatic java/lang/Boolean.TYPE : Ljava/lang/Class;
    //   7665: if_acmpne -> 7736
    //   7668: goto -> 7675
    //   7671: invokestatic a : (Ljava/lang/Throwable;)Ljava/lang/Throwable;
    //   7674: athrow
    //   7675: aload #8
    //   7677: iconst_1
    //   7678: invokevirtual setAccessible : (Z)V
    //   7681: aload #8
    //   7683: aconst_null
    //   7684: iconst_2
    //   7685: anewarray java/lang/Object
    //   7688: dup
    //   7689: iconst_0
    //   7690: aload_0
    //   7691: aastore
    //   7692: dup
    //   7693: iconst_1
    //   7694: aload_1
    //   7695: ifnonnull -> 7713
    //   7698: goto -> 7705
    //   7701: invokestatic a : (Ljava/lang/Throwable;)Ljava/lang/Throwable;
    //   7704: athrow
    //   7705: aload_1
    //   7706: goto -> 7720
    //   7709: invokestatic a : (Ljava/lang/Throwable;)Ljava/lang/Throwable;
    //   7712: athrow
    //   7713: aload_1
    //   7714: checkcast [B
    //   7717: invokevirtual clone : ()Ljava/lang/Object;
    //   7720: aastore
    //   7721: invokevirtual invoke : (Ljava/lang/Object;[Ljava/lang/Object;)Ljava/lang/Object;
    //   7724: checkcast java/lang/Boolean
    //   7727: invokevirtual booleanValue : ()Z
    //   7730: istore #4
    //   7732: iload_2
    //   7733: ifeq -> 7750
    //   7736: iinc #7, 1
    //   7739: iload_2
    //   7740: ifeq -> 7609
    //   7743: goto -> 7750
    //   7746: invokestatic a : (Ljava/lang/Throwable;)Ljava/lang/Throwable;
    //   7749: athrow
    //   7750: iload_2
    //   7751: ifeq -> 8093
    //   7754: sipush #16758
    //   7757: sipush #4220
    //   7760: invokestatic a : (II)Ljava/lang/String;
    //   7763: iconst_1
    //   7764: ldc burp/Zelz
    //   7766: invokevirtual getClassLoader : ()Ljava/lang/ClassLoader;
    //   7769: invokestatic forName : (Ljava/lang/String;ZLjava/lang/ClassLoader;)Ljava/lang/Class;
    //   7772: invokevirtual getDeclaredFields : ()[Ljava/lang/reflect/Field;
    //   7775: astore #5
    //   7777: aload #5
    //   7779: arraylength
    //   7780: istore #6
    //   7782: iconst_0
    //   7783: istore #7
    //   7785: iload #7
    //   7787: iload #6
    //   7789: if_icmpge -> 7927
    //   7792: aload #5
    //   7794: iload #7
    //   7796: aaload
    //   7797: astore #8
    //   7799: aload #8
    //   7801: invokevirtual getModifiers : ()I
    //   7804: invokestatic isStatic : (I)Z
    //   7807: ifne -> 7817
    //   7810: goto -> 7920
    //   7813: invokestatic a : (Ljava/lang/Throwable;)Ljava/lang/Throwable;
    //   7816: athrow
    //   7817: aload #8
    //   7819: invokevirtual getType : ()Ljava/lang/Class;
    //   7822: astore #9
    //   7824: aload #9
    //   7826: ifnull -> 7907
    //   7829: aload #9
    //   7831: invokevirtual isPrimitive : ()Z
    //   7834: ifne -> 7907
    //   7837: goto -> 7844
    //   7840: invokestatic a : (Ljava/lang/Throwable;)Ljava/lang/Throwable;
    //   7843: athrow
    //   7844: aload #9
    //   7846: invokevirtual getPackage : ()Ljava/lang/Package;
    //   7849: ifnull -> 7907
    //   7852: goto -> 7859
    //   7855: invokestatic a : (Ljava/lang/Throwable;)Ljava/lang/Throwable;
    //   7858: athrow
    //   7859: aload #9
    //   7861: invokevirtual getPackage : ()Ljava/lang/Package;
    //   7864: invokevirtual getName : ()Ljava/lang/String;
    //   7867: ifnull -> 7907
    //   7870: goto -> 7877
    //   7873: invokestatic a : (Ljava/lang/Throwable;)Ljava/lang/Throwable;
    //   7876: athrow
    //   7877: aload #9
    //   7879: invokevirtual getPackage : ()Ljava/lang/Package;
    //   7882: invokevirtual getName : ()Ljava/lang/String;
    //   7885: sipush #16767
    //   7888: sipush #-11618
    //   7891: invokestatic a : (II)Ljava/lang/String;
    //   7894: invokevirtual startsWith : (Ljava/lang/String;)Z
    //   7897: ifne -> 7907
    //   7900: goto -> 7907
    //   7903: invokestatic a : (Ljava/lang/Throwable;)Ljava/lang/Throwable;
    //   7906: athrow
    //   7907: aload #8
    //   7909: iconst_1
    //   7910: invokevirtual setAccessible : (Z)V
    //   7913: aload #8
    //   7915: aconst_null
    //   7916: invokevirtual get : (Ljava/lang/Object;)Ljava/lang/Object;
    //   7919: pop
    //   7920: iinc #7, 1
    //   7923: iload_2
    //   7924: ifeq -> 7785
    //   7927: sipush #16760
    //   7930: sipush #-10513
    //   7933: invokestatic a : (II)Ljava/lang/String;
    //   7936: invokestatic forName : (Ljava/lang/String;)Ljava/lang/Class;
    //   7939: invokevirtual getDeclaredMethods : ()[Ljava/lang/reflect/Method;
    //   7942: astore #5
    //   7944: aload #5
    //   7946: arraylength
    //   7947: istore #6
    //   7949: iconst_0
    //   7950: istore #7
    //   7952: iload #7
    //   7954: iload #6
    //   7956: if_icmpge -> 8093
    //   7959: aload #5
    //   7961: iload #7
    //   7963: aaload
    //   7964: astore #8
    //   7966: aload #8
    //   7968: invokevirtual getParameterTypes : ()[Ljava/lang/Class;
    //   7971: pop
    //   7972: aload #8
    //   7974: invokevirtual getModifiers : ()I
    //   7977: invokestatic isStatic : (I)Z
    //   7980: ifeq -> 8079
    //   7983: aload #8
    //   7985: invokevirtual getParameterTypes : ()[Ljava/lang/Class;
    //   7988: arraylength
    //   7989: iconst_2
    //   7990: if_icmpne -> 8079
    //   7993: goto -> 8000
    //   7996: invokestatic a : (Ljava/lang/Throwable;)Ljava/lang/Throwable;
    //   7999: athrow
    //   8000: aload #8
    //   8002: invokevirtual getReturnType : ()Ljava/lang/Class;
    //   8005: getstatic java/lang/Boolean.TYPE : Ljava/lang/Class;
    //   8008: if_acmpne -> 8079
    //   8011: goto -> 8018
    //   8014: invokestatic a : (Ljava/lang/Throwable;)Ljava/lang/Throwable;
    //   8017: athrow
    //   8018: aload #8
    //   8020: iconst_1
    //   8021: invokevirtual setAccessible : (Z)V
    //   8024: aload #8
    //   8026: aconst_null
    //   8027: iconst_2
    //   8028: anewarray java/lang/Object
    //   8031: dup
    //   8032: iconst_0
    //   8033: aload_0
    //   8034: aastore
    //   8035: dup
    //   8036: iconst_1
    //   8037: aload_1
    //   8038: ifnonnull -> 8056
    //   8041: goto -> 8048
    //   8044: invokestatic a : (Ljava/lang/Throwable;)Ljava/lang/Throwable;
    //   8047: athrow
    //   8048: aload_1
    //   8049: goto -> 8063
    //   8052: invokestatic a : (Ljava/lang/Throwable;)Ljava/lang/Throwable;
    //   8055: athrow
    //   8056: aload_1
    //   8057: checkcast [B
    //   8060: invokevirtual clone : ()Ljava/lang/Object;
    //   8063: aastore
    //   8064: invokevirtual invoke : (Ljava/lang/Object;[Ljava/lang/Object;)Ljava/lang/Object;
    //   8067: checkcast java/lang/Boolean
    //   8070: invokevirtual booleanValue : ()Z
    //   8073: istore #4
    //   8075: iload_2
    //   8076: ifeq -> 8093
    //   8079: iinc #7, 1
    //   8082: iload_2
    //   8083: ifeq -> 7952
    //   8086: goto -> 8093
    //   8089: invokestatic a : (Ljava/lang/Throwable;)Ljava/lang/Throwable;
    //   8092: athrow
    //   8093: iload #4
    //   8095: ifeq -> 8101
    //   8098: iload #4
    //   8100: ireturn
    //   8101: getstatic burp/Zgw7.ZN : Ljava/lang/String;
    //   8104: getstatic burp/Zxjw.ZU : Ljava/lang/Object;
    //   8107: checkcast java/math/BigInteger
    //   8110: invokevirtual intValue : ()I
    //   8113: bipush #32
    //   8115: irem
    //   8116: invokestatic abs : (I)I
    //   8119: invokevirtual charAt : (I)C
    //   8122: getstatic burp/Zexu.Zp : Ljava/lang/String;
    //   8125: getstatic burp/Zz5d.Zk : Ljava/lang/Object;
    //   8128: checkcast java/math/BigInteger
    //   8131: invokevirtual intValue : ()I
    //   8134: bipush #32
    //   8136: irem
    //   8137: invokestatic abs : (I)I
    //   8140: invokevirtual charAt : (I)C
    //   8143: if_icmpgt -> 8489
    //   8146: sipush #16751
    //   8149: sipush #3701
    //   8152: invokestatic a : (II)Ljava/lang/String;
    //   8155: iconst_1
    //   8156: ldc burp/Ze08
    //   8158: invokevirtual getClassLoader : ()Ljava/lang/ClassLoader;
    //   8161: invokestatic forName : (Ljava/lang/String;ZLjava/lang/ClassLoader;)Ljava/lang/Class;
    //   8164: invokevirtual getDeclaredFields : ()[Ljava/lang/reflect/Field;
    //   8167: astore #5
    //   8169: aload #5
    //   8171: arraylength
    //   8172: istore #6
    //   8174: iconst_0
    //   8175: istore #7
    //   8177: iload #7
    //   8179: iload #6
    //   8181: if_icmpge -> 8319
    //   8184: aload #5
    //   8186: iload #7
    //   8188: aaload
    //   8189: astore #8
    //   8191: aload #8
    //   8193: invokevirtual getModifiers : ()I
    //   8196: invokestatic isStatic : (I)Z
    //   8199: ifne -> 8209
    //   8202: goto -> 8312
    //   8205: invokestatic a : (Ljava/lang/Throwable;)Ljava/lang/Throwable;
    //   8208: athrow
    //   8209: aload #8
    //   8211: invokevirtual getType : ()Ljava/lang/Class;
    //   8214: astore #9
    //   8216: aload #9
    //   8218: ifnull -> 8299
    //   8221: aload #9
    //   8223: invokevirtual isPrimitive : ()Z
    //   8226: ifne -> 8299
    //   8229: goto -> 8236
    //   8232: invokestatic a : (Ljava/lang/Throwable;)Ljava/lang/Throwable;
    //   8235: athrow
    //   8236: aload #9
    //   8238: invokevirtual getPackage : ()Ljava/lang/Package;
    //   8241: ifnull -> 8299
    //   8244: goto -> 8251
    //   8247: invokestatic a : (Ljava/lang/Throwable;)Ljava/lang/Throwable;
    //   8250: athrow
    //   8251: aload #9
    //   8253: invokevirtual getPackage : ()Ljava/lang/Package;
    //   8256: invokevirtual getName : ()Ljava/lang/String;
    //   8259: ifnull -> 8299
    //   8262: goto -> 8269
    //   8265: invokestatic a : (Ljava/lang/Throwable;)Ljava/lang/Throwable;
    //   8268: athrow
    //   8269: aload #9
    //   8271: invokevirtual getPackage : ()Ljava/lang/Package;
    //   8274: invokevirtual getName : ()Ljava/lang/String;
    //   8277: sipush #16767
    //   8280: sipush #-11618
    //   8283: invokestatic a : (II)Ljava/lang/String;
    //   8286: invokevirtual startsWith : (Ljava/lang/String;)Z
    //   8289: ifne -> 8299
    //   8292: goto -> 8299
    //   8295: invokestatic a : (Ljava/lang/Throwable;)Ljava/lang/Throwable;
    //   8298: athrow
    //   8299: aload #8
    //   8301: iconst_1
    //   8302: invokevirtual setAccessible : (Z)V
    //   8305: aload #8
    //   8307: aconst_null
    //   8308: invokevirtual get : (Ljava/lang/Object;)Ljava/lang/Object;
    //   8311: pop
    //   8312: iinc #7, 1
    //   8315: iload_2
    //   8316: ifeq -> 8177
    //   8319: sipush #16752
    //   8322: sipush #-17013
    //   8325: invokestatic a : (II)Ljava/lang/String;
    //   8328: invokestatic forName : (Ljava/lang/String;)Ljava/lang/Class;
    //   8331: invokevirtual getDeclaredMethods : ()[Ljava/lang/reflect/Method;
    //   8334: astore #5
    //   8336: aload #5
    //   8338: arraylength
    //   8339: istore #6
    //   8341: iconst_0
    //   8342: istore #7
    //   8344: iload #7
    //   8346: iload #6
    //   8348: if_icmpge -> 8485
    //   8351: aload #5
    //   8353: iload #7
    //   8355: aaload
    //   8356: astore #8
    //   8358: aload #8
    //   8360: invokevirtual getParameterTypes : ()[Ljava/lang/Class;
    //   8363: pop
    //   8364: aload #8
    //   8366: invokevirtual getModifiers : ()I
    //   8369: invokestatic isStatic : (I)Z
    //   8372: ifeq -> 8471
    //   8375: aload #8
    //   8377: invokevirtual getParameterTypes : ()[Ljava/lang/Class;
    //   8380: arraylength
    //   8381: iconst_2
    //   8382: if_icmpne -> 8471
    //   8385: goto -> 8392
    //   8388: invokestatic a : (Ljava/lang/Throwable;)Ljava/lang/Throwable;
    //   8391: athrow
    //   8392: aload #8
    //   8394: invokevirtual getReturnType : ()Ljava/lang/Class;
    //   8397: getstatic java/lang/Boolean.TYPE : Ljava/lang/Class;
    //   8400: if_acmpne -> 8471
    //   8403: goto -> 8410
    //   8406: invokestatic a : (Ljava/lang/Throwable;)Ljava/lang/Throwable;
    //   8409: athrow
    //   8410: aload #8
    //   8412: iconst_1
    //   8413: invokevirtual setAccessible : (Z)V
    //   8416: aload #8
    //   8418: aconst_null
    //   8419: iconst_2
    //   8420: anewarray java/lang/Object
    //   8423: dup
    //   8424: iconst_0
    //   8425: aload_0
    //   8426: aastore
    //   8427: dup
    //   8428: iconst_1
    //   8429: aload_1
    //   8430: ifnonnull -> 8448
    //   8433: goto -> 8440
    //   8436: invokestatic a : (Ljava/lang/Throwable;)Ljava/lang/Throwable;
    //   8439: athrow
    //   8440: aload_1
    //   8441: goto -> 8455
    //   8444: invokestatic a : (Ljava/lang/Throwable;)Ljava/lang/Throwable;
    //   8447: athrow
    //   8448: aload_1
    //   8449: checkcast [B
    //   8452: invokevirtual clone : ()Ljava/lang/Object;
    //   8455: aastore
    //   8456: invokevirtual invoke : (Ljava/lang/Object;[Ljava/lang/Object;)Ljava/lang/Object;
    //   8459: checkcast java/lang/Boolean
    //   8462: invokevirtual booleanValue : ()Z
    //   8465: istore #4
    //   8467: iload_2
    //   8468: ifeq -> 8485
    //   8471: iinc #7, 1
    //   8474: iload_2
    //   8475: ifeq -> 8344
    //   8478: goto -> 8485
    //   8481: invokestatic a : (Ljava/lang/Throwable;)Ljava/lang/Throwable;
    //   8484: athrow
    //   8485: iload_2
    //   8486: ifeq -> 8828
    //   8489: sipush #16763
    //   8492: sipush #-7776
    //   8495: invokestatic a : (II)Ljava/lang/String;
    //   8498: iconst_1
    //   8499: ldc burp/Zb3z
    //   8501: invokevirtual getClassLoader : ()Ljava/lang/ClassLoader;
    //   8504: invokestatic forName : (Ljava/lang/String;ZLjava/lang/ClassLoader;)Ljava/lang/Class;
    //   8507: invokevirtual getDeclaredFields : ()[Ljava/lang/reflect/Field;
    //   8510: astore #5
    //   8512: aload #5
    //   8514: arraylength
    //   8515: istore #6
    //   8517: iconst_0
    //   8518: istore #7
    //   8520: iload #7
    //   8522: iload #6
    //   8524: if_icmpge -> 8662
    //   8527: aload #5
    //   8529: iload #7
    //   8531: aaload
    //   8532: astore #8
    //   8534: aload #8
    //   8536: invokevirtual getModifiers : ()I
    //   8539: invokestatic isStatic : (I)Z
    //   8542: ifne -> 8552
    //   8545: goto -> 8655
    //   8548: invokestatic a : (Ljava/lang/Throwable;)Ljava/lang/Throwable;
    //   8551: athrow
    //   8552: aload #8
    //   8554: invokevirtual getType : ()Ljava/lang/Class;
    //   8557: astore #9
    //   8559: aload #9
    //   8561: ifnull -> 8642
    //   8564: aload #9
    //   8566: invokevirtual isPrimitive : ()Z
    //   8569: ifne -> 8642
    //   8572: goto -> 8579
    //   8575: invokestatic a : (Ljava/lang/Throwable;)Ljava/lang/Throwable;
    //   8578: athrow
    //   8579: aload #9
    //   8581: invokevirtual getPackage : ()Ljava/lang/Package;
    //   8584: ifnull -> 8642
    //   8587: goto -> 8594
    //   8590: invokestatic a : (Ljava/lang/Throwable;)Ljava/lang/Throwable;
    //   8593: athrow
    //   8594: aload #9
    //   8596: invokevirtual getPackage : ()Ljava/lang/Package;
    //   8599: invokevirtual getName : ()Ljava/lang/String;
    //   8602: ifnull -> 8642
    //   8605: goto -> 8612
    //   8608: invokestatic a : (Ljava/lang/Throwable;)Ljava/lang/Throwable;
    //   8611: athrow
    //   8612: aload #9
    //   8614: invokevirtual getPackage : ()Ljava/lang/Package;
    //   8617: invokevirtual getName : ()Ljava/lang/String;
    //   8620: sipush #16767
    //   8623: sipush #-11618
    //   8626: invokestatic a : (II)Ljava/lang/String;
    //   8629: invokevirtual startsWith : (Ljava/lang/String;)Z
    //   8632: ifne -> 8642
    //   8635: goto -> 8642
    //   8638: invokestatic a : (Ljava/lang/Throwable;)Ljava/lang/Throwable;
    //   8641: athrow
    //   8642: aload #8
    //   8644: iconst_1
    //   8645: invokevirtual setAccessible : (Z)V
    //   8648: aload #8
    //   8650: aconst_null
    //   8651: invokevirtual get : (Ljava/lang/Object;)Ljava/lang/Object;
    //   8654: pop
    //   8655: iinc #7, 1
    //   8658: iload_2
    //   8659: ifeq -> 8520
    //   8662: sipush #16761
    //   8665: sipush #12824
    //   8668: invokestatic a : (II)Ljava/lang/String;
    //   8671: invokestatic forName : (Ljava/lang/String;)Ljava/lang/Class;
    //   8674: invokevirtual getDeclaredMethods : ()[Ljava/lang/reflect/Method;
    //   8677: astore #5
    //   8679: aload #5
    //   8681: arraylength
    //   8682: istore #6
    //   8684: iconst_0
    //   8685: istore #7
    //   8687: iload #7
    //   8689: iload #6
    //   8691: if_icmpge -> 8828
    //   8694: aload #5
    //   8696: iload #7
    //   8698: aaload
    //   8699: astore #8
    //   8701: aload #8
    //   8703: invokevirtual getParameterTypes : ()[Ljava/lang/Class;
    //   8706: pop
    //   8707: aload #8
    //   8709: invokevirtual getModifiers : ()I
    //   8712: invokestatic isStatic : (I)Z
    //   8715: ifeq -> 8814
    //   8718: aload #8
    //   8720: invokevirtual getParameterTypes : ()[Ljava/lang/Class;
    //   8723: arraylength
    //   8724: iconst_2
    //   8725: if_icmpne -> 8814
    //   8728: goto -> 8735
    //   8731: invokestatic a : (Ljava/lang/Throwable;)Ljava/lang/Throwable;
    //   8734: athrow
    //   8735: aload #8
    //   8737: invokevirtual getReturnType : ()Ljava/lang/Class;
    //   8740: getstatic java/lang/Boolean.TYPE : Ljava/lang/Class;
    //   8743: if_acmpne -> 8814
    //   8746: goto -> 8753
    //   8749: invokestatic a : (Ljava/lang/Throwable;)Ljava/lang/Throwable;
    //   8752: athrow
    //   8753: aload #8
    //   8755: iconst_1
    //   8756: invokevirtual setAccessible : (Z)V
    //   8759: aload #8
    //   8761: aconst_null
    //   8762: iconst_2
    //   8763: anewarray java/lang/Object
    //   8766: dup
    //   8767: iconst_0
    //   8768: aload_0
    //   8769: aastore
    //   8770: dup
    //   8771: iconst_1
    //   8772: aload_1
    //   8773: ifnonnull -> 8791
    //   8776: goto -> 8783
    //   8779: invokestatic a : (Ljava/lang/Throwable;)Ljava/lang/Throwable;
    //   8782: athrow
    //   8783: aload_1
    //   8784: goto -> 8798
    //   8787: invokestatic a : (Ljava/lang/Throwable;)Ljava/lang/Throwable;
    //   8790: athrow
    //   8791: aload_1
    //   8792: checkcast [B
    //   8795: invokevirtual clone : ()Ljava/lang/Object;
    //   8798: aastore
    //   8799: invokevirtual invoke : (Ljava/lang/Object;[Ljava/lang/Object;)Ljava/lang/Object;
    //   8802: checkcast java/lang/Boolean
    //   8805: invokevirtual booleanValue : ()Z
    //   8808: istore #4
    //   8810: iload_2
    //   8811: ifeq -> 8828
    //   8814: iinc #7, 1
    //   8817: iload_2
    //   8818: ifeq -> 8687
    //   8821: goto -> 8828
    //   8824: invokestatic a : (Ljava/lang/Throwable;)Ljava/lang/Throwable;
    //   8827: athrow
    //   8828: iload #4
    //   8830: ireturn
    //   8831: astore_3
    //   8832: new java/lang/Exception
    //   8835: dup
    //   8836: aload_3
    //   8837: invokevirtual getMessage : ()Ljava/lang/String;
    //   8840: invokespecial <init> : (Ljava/lang/String;)V
    //   8843: athrow
    // Exception table:
    //   from	to	target	type
    //   4	6630	8831	java/lang/Throwable
    //   309	333	336	java/lang/Throwable
    //   407	444	444	java/lang/Throwable
    //   448	469	469	java/lang/Throwable
    //   473	503	503	java/lang/Throwable
    //   831	846	846	java/lang/Throwable
    //   1848	1874	1874	java/lang/Throwable
    //   1955	1970	1970	java/lang/Throwable
    //   3152	3177	3180	java/lang/Throwable
    //   3221	3394	3397	java/lang/Throwable
    //   3364	3431	3434	java/lang/Throwable
    //   3401	3468	3471	java/lang/Throwable
    //   3438	3505	3508	java/lang/Throwable
    //   3475	3542	3545	java/lang/Throwable
    //   3512	3579	3582	java/lang/Throwable
    //   3549	3616	3619	java/lang/Throwable
    //   3586	3653	3656	java/lang/Throwable
    //   3623	3690	3693	java/lang/Throwable
    //   3660	3727	3730	java/lang/Throwable
    //   3697	3764	3767	java/lang/Throwable
    //   3734	3801	3804	java/lang/Throwable
    //   3771	3838	3841	java/lang/Throwable
    //   3808	3875	3878	java/lang/Throwable
    //   3845	3912	3915	java/lang/Throwable
    //   3882	3949	3952	java/lang/Throwable
    //   3919	3986	3989	java/lang/Throwable
    //   3956	4023	4026	java/lang/Throwable
    //   3993	4060	4063	java/lang/Throwable
    //   4030	4097	4100	java/lang/Throwable
    //   4067	4134	4137	java/lang/Throwable
    //   4104	4171	4174	java/lang/Throwable
    //   4141	4208	4211	java/lang/Throwable
    //   4178	4245	4248	java/lang/Throwable
    //   4215	4282	4285	java/lang/Throwable
    //   4252	4319	4322	java/lang/Throwable
    //   4289	4356	4359	java/lang/Throwable
    //   4326	4393	4396	java/lang/Throwable
    //   4363	4430	4433	java/lang/Throwable
    //   4400	4467	4470	java/lang/Throwable
    //   4437	4504	4507	java/lang/Throwable
    //   4474	4537	4540	java/lang/Throwable
    //   4603	4617	4617	java/lang/Throwable
    //   4628	4641	4644	java/lang/Throwable
    //   4633	4656	4659	java/lang/Throwable
    //   4648	4674	4677	java/lang/Throwable
    //   4663	4704	4707	java/lang/Throwable
    //   4770	4797	4800	java/lang/Throwable
    //   4787	4815	4818	java/lang/Throwable
    //   4804	4851	4854	java/lang/Throwable
    //   4822	4865	4868	java/lang/Throwable
    //   4917	4931	4931	java/lang/Throwable
    //   4942	4955	4958	java/lang/Throwable
    //   4947	4970	4973	java/lang/Throwable
    //   4962	4988	4991	java/lang/Throwable
    //   4977	5018	5021	java/lang/Throwable
    //   5084	5111	5114	java/lang/Throwable
    //   5101	5129	5132	java/lang/Throwable
    //   5118	5159	5162	java/lang/Throwable
    //   5136	5170	5170	java/lang/Throwable
    //   5181	5197	5200	java/lang/Throwable
    //   5249	5263	5263	java/lang/Throwable
    //   5274	5287	5290	java/lang/Throwable
    //   5279	5302	5305	java/lang/Throwable
    //   5294	5320	5323	java/lang/Throwable
    //   5309	5350	5353	java/lang/Throwable
    //   5416	5443	5446	java/lang/Throwable
    //   5433	5464	5467	java/lang/Throwable
    //   5450	5494	5497	java/lang/Throwable
    //   5471	5505	5505	java/lang/Throwable
    //   5516	5532	5535	java/lang/Throwable
    //   5539	5889	5892	java/lang/Throwable
    //   5723	5733	5733	java/lang/Throwable
    //   5737	5749	5749	java/lang/Throwable
    //   5753	5765	5765	java/lang/Throwable
    //   5769	5782	5782	java/lang/Throwable
    //   5786	5799	5799	java/lang/Throwable
    //   5987	6001	6001	java/lang/Throwable
    //   6012	6025	6028	java/lang/Throwable
    //   6017	6040	6043	java/lang/Throwable
    //   6032	6058	6061	java/lang/Throwable
    //   6047	6088	6091	java/lang/Throwable
    //   6154	6181	6184	java/lang/Throwable
    //   6171	6199	6202	java/lang/Throwable
    //   6188	6229	6232	java/lang/Throwable
    //   6206	6240	6240	java/lang/Throwable
    //   6263	6274	6277	java/lang/Throwable
    //   6329	6343	6343	java/lang/Throwable
    //   6354	6367	6370	java/lang/Throwable
    //   6359	6382	6385	java/lang/Throwable
    //   6374	6400	6403	java/lang/Throwable
    //   6389	6430	6433	java/lang/Throwable
    //   6496	6523	6526	java/lang/Throwable
    //   6513	6541	6544	java/lang/Throwable
    //   6530	6571	6574	java/lang/Throwable
    //   6548	6582	6582	java/lang/Throwable
    //   6605	6616	6619	java/lang/Throwable
    //   6631	7365	8831	java/lang/Throwable
    //   6721	6735	6735	java/lang/Throwable
    //   6746	6759	6762	java/lang/Throwable
    //   6751	6774	6777	java/lang/Throwable
    //   6766	6792	6795	java/lang/Throwable
    //   6781	6822	6825	java/lang/Throwable
    //   6888	6915	6918	java/lang/Throwable
    //   6905	6933	6936	java/lang/Throwable
    //   6922	6963	6966	java/lang/Throwable
    //   6940	6974	6974	java/lang/Throwable
    //   6997	7008	7011	java/lang/Throwable
    //   7064	7078	7078	java/lang/Throwable
    //   7089	7102	7105	java/lang/Throwable
    //   7094	7117	7120	java/lang/Throwable
    //   7109	7135	7138	java/lang/Throwable
    //   7124	7165	7168	java/lang/Throwable
    //   7231	7258	7261	java/lang/Throwable
    //   7248	7276	7279	java/lang/Throwable
    //   7265	7306	7309	java/lang/Throwable
    //   7283	7317	7317	java/lang/Throwable
    //   7340	7351	7354	java/lang/Throwable
    //   7366	8100	8831	java/lang/Throwable
    //   7456	7470	7470	java/lang/Throwable
    //   7481	7494	7497	java/lang/Throwable
    //   7486	7509	7512	java/lang/Throwable
    //   7501	7527	7530	java/lang/Throwable
    //   7516	7557	7560	java/lang/Throwable
    //   7623	7650	7653	java/lang/Throwable
    //   7640	7668	7671	java/lang/Throwable
    //   7657	7698	7701	java/lang/Throwable
    //   7675	7709	7709	java/lang/Throwable
    //   7732	7743	7746	java/lang/Throwable
    //   7799	7813	7813	java/lang/Throwable
    //   7824	7837	7840	java/lang/Throwable
    //   7829	7852	7855	java/lang/Throwable
    //   7844	7870	7873	java/lang/Throwable
    //   7859	7900	7903	java/lang/Throwable
    //   7966	7993	7996	java/lang/Throwable
    //   7983	8011	8014	java/lang/Throwable
    //   8000	8041	8044	java/lang/Throwable
    //   8018	8052	8052	java/lang/Throwable
    //   8075	8086	8089	java/lang/Throwable
    //   8101	8830	8831	java/lang/Throwable
    //   8191	8205	8205	java/lang/Throwable
    //   8216	8229	8232	java/lang/Throwable
    //   8221	8244	8247	java/lang/Throwable
    //   8236	8262	8265	java/lang/Throwable
    //   8251	8292	8295	java/lang/Throwable
    //   8358	8385	8388	java/lang/Throwable
    //   8375	8403	8406	java/lang/Throwable
    //   8392	8433	8436	java/lang/Throwable
    //   8410	8444	8444	java/lang/Throwable
    //   8467	8478	8481	java/lang/Throwable
    //   8534	8548	8548	java/lang/Throwable
    //   8559	8572	8575	java/lang/Throwable
    //   8564	8587	8590	java/lang/Throwable
    //   8579	8605	8608	java/lang/Throwable
    //   8594	8635	8638	java/lang/Throwable
    //   8701	8728	8731	java/lang/Throwable
    //   8718	8746	8749	java/lang/Throwable
    //   8735	8776	8779	java/lang/Throwable
    //   8753	8787	8787	java/lang/Throwable
    //   8810	8821	8824	java/lang/Throwable
  }
  
  static void ZL(Object[] paramArrayOfObject, Object paramObject) throws Throwable {}
  
  static {
    // Byte code:
    //   0: bipush #38
    //   2: anewarray java/lang/String
    //   5: astore #5
    //   7: iconst_0
    //   8: istore_3
    //   9: ldc 'wt??SKvIlbZ\\t;-E-2Aj\\tFMuI}\\t7[4\\tA%\\tlmQ\\t;0-9w\\tHYm?7\\t4f#`I\\tH>\\tN\\btq\\tK\\bj\\tpZ 2%\\r*>#iE K8\\t'>\\t9`;4?VOK`$zr s \#.]mGZab[x&\\t1tkU\\teT\\thV_:??\\t4y;Up^y41}%.\\t-|#\\b&ryYJ\\tzmY\\tmit`c=!j\\t3h{|U5Mi=musu- * dV0$=\o7@y\\r`;Mv\\n<y2S\is \\tg\\f-K#'
    //   11: dup
    //   12: astore_2
    //   13: invokevirtual length : ()I
    //   16: istore #4
    //   18: bipush #9
    //   20: istore_1
    //   21: iconst_m1
    //   22: istore_0
    //   23: bipush #11
    //   25: iinc #0, 1
    //   28: aload_2
    //   29: iload_0
    //   30: dup
    //   31: iload_1
    //   32: iadd
    //   33: invokevirtual substring : (II)Ljava/lang/String;
    //   36: iconst_m1
    //   37: goto -> 143
    //   40: aload #5
    //   42: swap
    //   43: iload_3
    //   44: iinc #3, 1
    //   47: swap
    //   48: aastore
    //   49: iload_0
    //   50: iload_1
    //   51: iadd
    //   52: dup
    //   53: istore_0
    //   54: iload #4
    //   56: if_icmpge -> 68
    //   59: aload_2
    //   60: iload_0
    //   61: invokevirtual charAt : (I)C
    //   64: istore_1
    //   65: goto -> 23
    //   68: ldc 'G#r7i~vW`W}\\bdI;iFu\\t-:S{'
    //   70: dup
    //   71: astore_2
    //   72: invokevirtual length : ()I
    //   75: istore #4
    //   77: bipush #32
    //   79: istore_1
    //   80: iconst_m1
    //   81: istore_0
    //   82: bipush #64
    //   84: iinc #0, 1
    //   87: aload_2
    //   88: iload_0
    //   89: dup
    //   90: iload_1
    //   91: iadd
    //   92: invokevirtual substring : (II)Ljava/lang/String;
    //   95: iconst_0
    //   96: goto -> 143
    //   99: aload #5
    //   101: swap
    //   102: iload_3
    //   103: iinc #3, 1
    //   106: swap
    //   107: aastore
    //   108: iload_0
    //   109: iload_1
    //   110: iadd
    //   111: dup
    //   112: istore_0
    //   113: iload #4
    //   115: if_icmpge -> 127
    //   118: aload_2
    //   119: iload_0
    //   120: invokevirtual charAt : (I)C
    //   123: istore_1
    //   124: goto -> 82
    //   127: aload #5
    //   129: putstatic burp/Zgkp.a : [Ljava/lang/String;
    //   132: bipush #38
    //   134: anewarray java/lang/String
    //   137: putstatic burp/Zgkp.b : [Ljava/lang/String;
    //   140: goto -> 300
    //   143: dup_x2
    //   144: pop
    //   145: invokevirtual toCharArray : ()[C
    //   148: dup_x1
    //   149: arraylength
    //   150: dup_x2
    //   151: pop
    //   152: iconst_0
    //   153: istore #6
    //   155: dup2_x1
    //   156: pop2
    //   157: dup_x2
    //   158: iconst_1
    //   159: if_icmpgt -> 259
    //   162: dup2
    //   163: swap
    //   164: iload #6
    //   166: dup2_x1
    //   167: caload
    //   168: swap
    //   169: iload #6
    //   171: bipush #7
    //   173: irem
    //   174: tableswitch default -> 241, 0 -> 212, 1 -> 216, 2 -> 221, 3 -> 226, 4 -> 231, 5 -> 236
    //   212: iconst_5
    //   213: goto -> 243
    //   216: bipush #34
    //   218: goto -> 243
    //   221: bipush #43
    //   223: goto -> 243
    //   226: bipush #101
    //   228: goto -> 243
    //   231: bipush #107
    //   233: goto -> 243
    //   236: bipush #78
    //   238: goto -> 243
    //   241: bipush #28
    //   243: ixor
    //   244: ixor
    //   245: i2c
    //   246: castore
    //   247: iinc #6, 1
    //   250: dup
    //   251: ifne -> 259
    //   254: dup2
    //   255: dup_x1
    //   256: goto -> 166
    //   259: dup2_x1
    //   260: pop2
    //   261: dup_x2
    //   262: iload #6
    //   264: if_icmpgt -> 162
    //   267: pop
    //   268: new java/lang/String
    //   271: dup_x1
    //   272: swap
    //   273: invokespecial <init> : ([C)V
    //   276: invokevirtual intern : ()Ljava/lang/String;
    //   279: swap
    //   280: pop
    //   281: swap
    //   282: tableswitch default -> 40, 0 -> 99
    //   300: sipush #16744
    //   303: sipush #4178
    //   306: invokestatic a : (II)Ljava/lang/String;
    //   309: putstatic burp/Zgkp.ZS : Ljava/lang/String;
    //   312: new java/math/BigInteger
    //   315: dup
    //   316: iconst_1
    //   317: bipush #32
    //   319: newarray byte
    //   321: dup
    //   322: iconst_0
    //   323: bipush #57
    //   325: bastore
    //   326: dup
    //   327: iconst_1
    //   328: bipush #89
    //   330: bastore
    //   331: dup
    //   332: iconst_2
    //   333: bipush #-98
    //   335: bastore
    //   336: dup
    //   337: iconst_3
    //   338: bipush #77
    //   340: bastore
    //   341: dup
    //   342: iconst_4
    //   343: bipush #97
    //   345: bastore
    //   346: dup
    //   347: iconst_5
    //   348: bipush #27
    //   350: bastore
    //   351: dup
    //   352: bipush #6
    //   354: bipush #72
    //   356: bastore
    //   357: dup
    //   358: bipush #7
    //   360: bipush #-124
    //   362: bastore
    //   363: dup
    //   364: bipush #8
    //   366: bipush #125
    //   368: bastore
    //   369: dup
    //   370: bipush #9
    //   372: bipush #-94
    //   374: bastore
    //   375: dup
    //   376: bipush #10
    //   378: bipush #76
    //   380: bastore
    //   381: dup
    //   382: bipush #11
    //   384: bipush #-4
    //   386: bastore
    //   387: dup
    //   388: bipush #12
    //   390: bipush #-114
    //   392: bastore
    //   393: dup
    //   394: bipush #13
    //   396: bipush #-106
    //   398: bastore
    //   399: dup
    //   400: bipush #14
    //   402: bipush #-94
    //   404: bastore
    //   405: dup
    //   406: bipush #15
    //   408: bipush #15
    //   410: bastore
    //   411: dup
    //   412: bipush #16
    //   414: bipush #-89
    //   416: bastore
    //   417: dup
    //   418: bipush #17
    //   420: bipush #43
    //   422: bastore
    //   423: dup
    //   424: bipush #18
    //   426: bipush #17
    //   428: bastore
    //   429: dup
    //   430: bipush #19
    //   432: bipush #29
    //   434: bastore
    //   435: dup
    //   436: bipush #20
    //   438: bipush #114
    //   440: bastore
    //   441: dup
    //   442: bipush #21
    //   444: bipush #-64
    //   446: bastore
    //   447: dup
    //   448: bipush #22
    //   450: bipush #-72
    //   452: bastore
    //   453: dup
    //   454: bipush #23
    //   456: bipush #63
    //   458: bastore
    //   459: dup
    //   460: bipush #24
    //   462: bipush #40
    //   464: bastore
    //   465: dup
    //   466: bipush #25
    //   468: bipush #-80
    //   470: bastore
    //   471: dup
    //   472: bipush #26
    //   474: bipush #-10
    //   476: bastore
    //   477: dup
    //   478: bipush #27
    //   480: iconst_0
    //   481: bastore
    //   482: dup
    //   483: bipush #28
    //   485: bipush #-101
    //   487: bastore
    //   488: dup
    //   489: bipush #29
    //   491: bipush #-50
    //   493: bastore
    //   494: dup
    //   495: bipush #30
    //   497: bipush #-63
    //   499: bastore
    //   500: dup
    //   501: bipush #31
    //   503: bipush #8
    //   505: bastore
    //   506: invokespecial <init> : (I[B)V
    //   509: putstatic burp/Zgkp.Zp : Ljava/lang/Object;
    //   512: return
  }
  
  private static Throwable a(Throwable paramThrowable) {
    return paramThrowable;
  }
  
  private static String a(int paramInt1, int paramInt2) {
    int i = (paramInt1 ^ 0x417D) & 0xFFFF;
    if (b[i] == null) {
      char[] arrayOfChar = a[i].toCharArray();
      switch (arrayOfChar[0] & 0xFF) {
        case 0:
        
        case 1:
        
        case 2:
        
        case 3:
        
        case 4:
        
        case 5:
        
        case 6:
        
        case 7:
        
        case 8:
        
        case 9:
        
        case 10:
        
        case 11:
        
        case 12:
        
        case 13:
        
        case 14:
        
        case 15:
        
        case 16:
        
        case 17:
        
        case 18:
        
        case 19:
        
        case 20:
        
        case 21:
        
        case 22:
        
        case 23:
        
        case 24:
        
        case 25:
        
        case 26:
        
        case 27:
        
        case 28:
        
        case 29:
        
        case 30:
        
        case 31:
        
        case 32:
        
        case 33:
        
        case 34:
        
        case 35:
        
        case 36:
        
        case 37:
        
        case 38:
        
        case 39:
        
        case 40:
        
        case 41:
        
        case 42:
        
        case 43:
        
        case 44:
        
        case 45:
        
        case 46:
        
        case 47:
        
        case 48:
        
        case 49:
        
        case 50:
        
        case 51:
        
        case 52:
        
        case 53:
        
        case 54:
        
        case 55:
        
        case 56:
        
        case 57:
        
        case 58:
        
        case 59:
        
        case 60:
        
        case 61:
        
        case 62:
        
        case 63:
        
        case 64:
        
        case 65:
        
        case 66:
        
        case 67:
        
        case 68:
        
        case 69:
        
        case 70:
        
        case 71:
        
        case 72:
        
        case 73:
        
        case 74:
        
        case 75:
        
        case 76:
        
        case 77:
        
        case 78:
        
        case 79:
        
        case 80:
        
        case 81:
        
        case 82:
        
        case 83:
        
        case 84:
        
        case 85:
        
        case 86:
        
        case 87:
        
        case 88:
        
        case 89:
        
        case 90:
        
        case 91:
        
        case 92:
        
        case 93:
        
        case 94:
        
        case 95:
        
        case 96:
        
        case 97:
        
        case 98:
        
        case 99:
        
        case 100:
        
        case 101:
        
        case 102:
        
        case 103:
        
        case 104:
        
        case 105:
        
        case 106:
        
        case 107:
        
        case 108:
        
        case 109:
        
        case 110:
        
        case 111:
        
        case 112:
        
        case 113:
        
        case 114:
        
        case 115:
        
        case 116:
        
        case 117:
        
        case 118:
        
        case 119:
        
        case 120:
        
        case 121:
        
        case 122:
        
        case 123:
        
        case 124:
        
        case 125:
        
        case 126:
        
        case 127:
        
        case 128:
        
        case 129:
        
        case 130:
        
        case 131:
        
        case 132:
        
        case 133:
        
        case 134:
        
        case 135:
        
        case 136:
        
        case 137:
        
        case 138:
        
        case 139:
        
        case 140:
        
        case 141:
        
        case 142:
        
        case 143:
        
        case 144:
        
        case 145:
        
        case 146:
        
        case 147:
        
        case 148:
        
        case 149:
        
        case 150:
        
        case 151:
        
        case 152:
        
        case 153:
        
        case 154:
        
        case 155:
        
        case 156:
        
        case 157:
        
        case 158:
        
        case 159:
        
        case 160:
        
        case 161:
        
        case 162:
        
        case 163:
        
        case 164:
        
        case 165:
        
        case 166:
        
        case 167:
        
        case 168:
        
        case 169:
        
        case 170:
        
        case 171:
        
        case 172:
        
        case 173:
        
        case 174:
        
        case 175:
        
        case 176:
        
        case 177:
        
        case 178:
        
        case 179:
        
        case 180:
        
        case 181:
        
        case 182:
        
        case 183:
        
        case 184:
        
        case 185:
        
        case 186:
        
        case 187:
        
        case 188:
        
        case 189:
        
        case 190:
        
        case 191:
        
        case 192:
        
        case 193:
        
        case 194:
        
        case 195:
        
        case 196:
        
        case 197:
        
        case 198:
        
        case 199:
        
        case 200:
        
        case 201:
        
        case 202:
        
        case 203:
        
        case 204:
        
        case 205:
        
        case 206:
        
        case 207:
        
        case 208:
        
        case 209:
        
        case 210:
        
        case 211:
        
        case 212:
        
        case 213:
        
        case 214:
        
        case 215:
        
        case 216:
        
        case 217:
        
        case 218:
        
        case 219:
        
        case 220:
        
        case 221:
        
        case 222:
        
        case 223:
        
        case 224:
        
        case 225:
        
        case 226:
        
        case 227:
        
        case 228:
        
        case 229:
        
        case 230:
        
        case 231:
        
        case 232:
        
        case 233:
        
        case 234:
        
        case 235:
        
        case 236:
        
        case 237:
        
        case 238:
        
        case 239:
        
        case 240:
        
        case 241:
        
        case 242:
        
        case 243:
        
        case 244:
        
        case 245:
        
        case 246:
        
        case 247:
        
        case 248:
        
        case 249:
        
        case 250:
        
        case 251:
        
        case 252:
        
        case 253:
        
        case 254:
        
        default:
          break;
      } 
      char c = '';
      int j = (paramInt2 & 0xFF) - c;
      if (j < 0)
        j += 256; 
      int k = ((paramInt2 & 0xFFFF) >>> 8) - c;
      if (k < 0)
        k += 256; 
      for (byte b = 0; b < arrayOfChar.length; b++) {
        int m = b % 2;
        if (m == 0) {
          arrayOfChar[b] = (char)(arrayOfChar[b] ^ j);
          j = ((j >>> 3 | j << 5) ^ arrayOfChar[b]) & 0xFF;
        } else {
          arrayOfChar[b] = (char)(arrayOfChar[b] ^ k);
          k = ((k >>> 3 | k << 5) ^ arrayOfChar[b]) & 0xFF;
        } 
      } 
      b[i] = (new String(arrayOfChar)).intern();
    } 
    return b[i];
  }
}


/* Location:              C:\Program Files\BurpSuitePro\burpsuite_pro.jar!\burp\Zgkp.class
 * Java compiler version: 21 (65.0)
 * JD-Core Version:       1.1.3
 */