package burp;

class Zglx implements Runnable {
  final Zz_m Zj;
  
  private Zglx(Zz_m paramZz_m) {}
  
  public void run() {
    // Byte code:
    //   0: invokestatic Zp : ()[Lburp/Zbqc;
    //   3: astore_1
    //   4: aload_0
    //   5: getfield Zj : Lburp/Zz_m;
    //   8: invokevirtual ZM : ()Lburp/Zez3;
    //   11: astore_2
    //   12: aload_2
    //   13: ifnonnull -> 20
    //   16: aload_1
    //   17: ifnull -> 402
    //   20: aload_2
    //   21: invokeinterface Zos : ()Lburp/Zstu;
    //   26: astore_3
    //   27: aload_3
    //   28: ifnull -> 47
    //   31: aload_2
    //   32: invokeinterface ZoO : ()Lburp/Zstu;
    //   37: ifnonnull -> 51
    //   40: goto -> 47
    //   43: invokestatic a : (Ljava/lang/Exception;)Ljava/lang/Exception;
    //   46: athrow
    //   47: aload_1
    //   48: ifnull -> 4
    //   51: aload_0
    //   52: getfield Zj : Lburp/Zz_m;
    //   55: getfield Zv : Lburp/Zee3;
    //   58: aload_2
    //   59: invokeinterface Zod : ()Lburp/Zmzk;
    //   64: aload_3
    //   65: invokeinterface ZiD : ()[B
    //   70: invokevirtual Z_ : (Lburp/Zmzk;[B)Lburp/Zg3d;
    //   73: astore #4
    //   75: aload #4
    //   77: invokeinterface Zb : ()Lburp/Zvom;
    //   82: getstatic burp/Zvom.STREAMING_RESPONSE : Lburp/Zvom;
    //   85: if_acmpeq -> 132
    //   88: aload #4
    //   90: invokeinterface Ze : ()Lburp/Zb6q;
    //   95: ifnull -> 132
    //   98: goto -> 105
    //   101: invokestatic a : (Ljava/lang/Exception;)Ljava/lang/Exception;
    //   104: athrow
    //   105: aload #4
    //   107: invokeinterface Ze : ()Lburp/Zb6q;
    //   112: invokeinterface Za : ()Lburp/Zstu;
    //   117: invokeinterface Zpu : ()I
    //   122: ifne -> 136
    //   125: goto -> 132
    //   128: invokestatic a : (Ljava/lang/Exception;)Ljava/lang/Exception;
    //   131: athrow
    //   132: aload_1
    //   133: ifnull -> 4
    //   136: aload #4
    //   138: invokeinterface ZR : ()Lburp/Zefx;
    //   143: invokeinterface ZD : ()[B
    //   148: invokestatic Zy : ([B)Lburp/Zyf;
    //   151: astore_3
    //   152: aload #4
    //   154: invokeinterface Ze : ()Lburp/Zb6q;
    //   159: invokeinterface Za : ()Lburp/Zstu;
    //   164: invokeinterface ZiD : ()[B
    //   169: astore #5
    //   171: aload_0
    //   172: getfield Zj : Lburp/Zz_m;
    //   175: getfield Zr : Lburp/Zr_4;
    //   178: aload #5
    //   180: invokeinterface ZZ : ([B)Lburp/Zstu;
    //   185: astore #6
    //   187: aload_2
    //   188: invokeinterface Zod : ()Lburp/Zmzk;
    //   193: aload_3
    //   194: iconst_1
    //   195: aload_0
    //   196: getfield Zj : Lburp/Zz_m;
    //   199: getfield ZA : Lburp/Zbnt;
    //   202: invokestatic ZY : (Lburp/Zmzk;Lburp/Zstu;BLburp/Zbnt;)Lburp/Zz1p;
    //   205: astore #7
    //   207: aload #7
    //   209: aload #6
    //   211: getstatic burp/Zt0k.HTML_ANALYSIS : Lburp/Zt0k;
    //   214: aload_0
    //   215: getfield Zj : Lburp/Zz_m;
    //   218: getfield ZA : Lburp/Zbnt;
    //   221: invokestatic ZS : (Lburp/Zz1p;Lburp/Zstu;Lburp/Zt0k;Lburp/Zbnt;)Lburp/Zs68;
    //   224: astore #8
    //   226: aload #7
    //   228: invokevirtual ZO : ()I
    //   231: ifle -> 285
    //   234: aload #7
    //   236: invokevirtual ZO : ()I
    //   239: aload_3
    //   240: invokeinterface Zpu : ()I
    //   245: if_icmpge -> 285
    //   248: goto -> 255
    //   251: invokestatic a : (Ljava/lang/Exception;)Ljava/lang/Exception;
    //   254: athrow
    //   255: aload_0
    //   256: getfield Zj : Lburp/Zz_m;
    //   259: getfield ZW : Lburp/Ztdi;
    //   262: aload #7
    //   264: getfield Zo : Lburp/Zlit;
    //   267: aload_3
    //   268: aload #7
    //   270: invokevirtual ZO : ()I
    //   273: iconst_0
    //   274: invokeinterface ZP : (Lburp/Zlit;Lburp/Zstu;IS)Lburp/Zez3;
    //   279: astore #9
    //   281: aload_1
    //   282: ifnull -> 305
    //   285: aload_0
    //   286: getfield Zj : Lburp/Zz_m;
    //   289: getfield ZW : Lburp/Ztdi;
    //   292: aload #7
    //   294: getfield Zo : Lburp/Zlit;
    //   297: iconst_0
    //   298: invokeinterface Zq : (Lburp/Zlit;S)Lburp/Zez3;
    //   303: astore #9
    //   305: new burp/Zsir
    //   308: dup
    //   309: invokespecial <init> : ()V
    //   312: aload_3
    //   313: aload_0
    //   314: getfield Zj : Lburp/Zz_m;
    //   317: getfield Zr : Lburp/Zr_4;
    //   320: invokeinterface Zp : (Lburp/Zr_4;)Lburp/Zstu;
    //   325: aload #7
    //   327: getfield Zb : Ljava/lang/String;
    //   330: invokevirtual Zp : (Lburp/Zstu;Ljava/lang/String;)Lburp/Zsir;
    //   333: aload #6
    //   335: aload #8
    //   337: getfield Zs : I
    //   340: aload #8
    //   342: getfield Zb : S
    //   345: aload #8
    //   347: getfield ZH : Lburp/Zk8m;
    //   350: getfield Zj : S
    //   353: aload #8
    //   355: invokestatic ZO : (Lburp/Zs68;)Ljava/lang/String;
    //   358: invokestatic currentTimeMillis : ()J
    //   361: invokevirtual ZV : (Lburp/Zstu;ISSLjava/lang/String;J)Lburp/Zsir;
    //   364: iconst_2
    //   365: iconst_0
    //   366: invokevirtual ZZ : (BB)Lburp/Zsir;
    //   369: aload #9
    //   371: invokevirtual Zd : (Lburp/Zez3;)V
    //   374: aload_0
    //   375: getfield Zj : Lburp/Zz_m;
    //   378: getfield ZW : Lburp/Ztdi;
    //   381: aload #9
    //   383: invokeinterface ZR : (Lburp/Zez3;)V
    //   388: goto -> 4
    //   391: astore_2
    //   392: aload_2
    //   393: getstatic net/portswigger/Zk_.UNEXPECTED : Lnet/portswigger/Zk_;
    //   396: invokestatic Zl : (Ljava/lang/Throwable;Lnet/portswigger/Zk_;)V
    //   399: goto -> 4
    //   402: return
    // Exception table:
    //   from	to	target	type
    //   4	16	391	java/lang/Exception
    //   20	47	391	java/lang/Exception
    //   27	40	43	java/lang/Exception
    //   51	132	391	java/lang/Exception
    //   75	98	101	java/lang/Exception
    //   88	125	128	java/lang/Exception
    //   136	388	391	java/lang/Exception
    //   226	248	251	java/lang/Exception
  }
  
  private static Exception a(Exception paramException) {
    return paramException;
  }
}


/* Location:              C:\Program Files\BurpSuitePro\burpsuite_pro.jar!\burp\Zglx.class
 * Java compiler version: 21 (65.0)
 * JD-Core Version:       1.1.3
 */