package burp;

public class Zgmi extends Zgmw {
  private boolean Ze;
  
  private boolean ZE;
  
  public void Zh(Zgim paramZgim, Ztu8 paramZtu8) {
    // Byte code:
    //   0: invokestatic ZH : ()[I
    //   3: astore_3
    //   4: aload_0
    //   5: getfield Ze : Z
    //   8: ifeq -> 27
    //   11: aload_2
    //   12: invokestatic ZD : (Lburp/Ztu8;)Z
    //   15: ifeq -> 107
    //   18: aload_0
    //   19: iconst_0
    //   20: putfield Ze : Z
    //   23: aload_3
    //   24: ifnull -> 107
    //   27: aload_0
    //   28: getfield ZE : Z
    //   31: ifeq -> 50
    //   34: aload_2
    //   35: invokestatic ZN : (Lburp/Ztu8;)Z
    //   38: ifeq -> 107
    //   41: aload_0
    //   42: iconst_0
    //   43: putfield ZE : Z
    //   46: aload_3
    //   47: ifnull -> 107
    //   50: aload_2
    //   51: invokestatic ZS : (Lburp/Ztu8;)Z
    //   54: ifeq -> 79
    //   57: aload_2
    //   58: invokeinterface Zlv : ()Ljava/lang/String;
    //   63: astore #4
    //   65: aload #4
    //   67: ifnull -> 75
    //   70: aload_1
    //   71: aload_2
    //   72: invokevirtual ZA : (Lburp/Ztu8;)V
    //   75: aload_3
    //   76: ifnull -> 107
    //   79: aload_2
    //   80: invokestatic ZH : (Lburp/Ztu8;)Z
    //   83: ifeq -> 95
    //   86: aload_0
    //   87: iconst_1
    //   88: putfield Ze : Z
    //   91: aload_3
    //   92: ifnull -> 107
    //   95: aload_2
    //   96: invokestatic ZL : (Lburp/Ztu8;)Z
    //   99: ifeq -> 107
    //   102: aload_0
    //   103: iconst_1
    //   104: putfield ZE : Z
    //   107: return
  }
}


/* Location:              C:\Program Files\BurpSuitePro\burpsuite_pro.jar!\burp\Zgmi.class
 * Java compiler version: 21 (65.0)
 * JD-Core Version:       1.1.3
 */