package burp;

import java.math.BigInteger;

class Zgny extends ClassLoader {
  static Object ZR;
  
  static String Zf;
  
  private static final String[] a;
  
  private static final String[] b;
  
  static boolean Zf(Object[] paramArrayOfObject, Object paramObject) throws Throwable {
    // Byte code:
    //   0: invokestatic ZK : ()Z
    //   3: istore_2
    //   4: getstatic burp/Zkbf.Zx : Ljava/lang/Object;
    //   7: checkcast java/math/BigInteger
    //   10: getstatic burp/Zem6.Zm : Ljava/lang/Object;
    //   13: checkcast java/math/BigInteger
    //   16: invokevirtual subtract : (Ljava/math/BigInteger;)Ljava/math/BigInteger;
    //   19: putstatic burp/Zxzv.Zg : Ljava/lang/Object;
    //   22: getstatic burp/Zmhx.ZQ : Ljava/lang/Object;
    //   25: checkcast java/math/BigInteger
    //   28: invokevirtual toByteArray : ()[B
    //   31: astore_3
    //   32: bipush #32
    //   34: newarray int
    //   36: dup
    //   37: iconst_0
    //   38: ldc 876216579
    //   40: iastore
    //   41: dup
    //   42: iconst_1
    //   43: ldc 455999525
    //   45: iastore
    //   46: dup
    //   47: iconst_2
    //   48: ldc 1043334948
    //   50: iastore
    //   51: dup
    //   52: iconst_3
    //   53: ldc 439222784
    //   55: iastore
    //   56: dup
    //   57: iconst_4
    //   58: ldc 372376604
    //   60: iastore
    //   61: dup
    //   62: iconst_5
    //   63: ldc 707731490
    //   65: iastore
    //   66: dup
    //   67: bipush #6
    //   69: ldc 389426184
    //   71: iastore
    //   72: dup
    //   73: bipush #7
    //   75: ldc 973875457
    //   77: iastore
    //   78: dup
    //   79: bipush #8
    //   81: ldc 389160971
    //   83: iastore
    //   84: dup
    //   85: bipush #9
    //   87: ldc 907870729
    //   89: iastore
    //   90: dup
    //   91: bipush #10
    //   93: ldc 121057538
    //   95: iastore
    //   96: dup
    //   97: bipush #11
    //   99: ldc 840500228
    //   101: iastore
    //   102: dup
    //   103: bipush #12
    //   105: ldc 254150144
    //   107: iastore
    //   108: dup
    //   109: bipush #13
    //   111: ldc 924386310
    //   113: iastore
    //   114: dup
    //   115: bipush #14
    //   117: ldc 187632156
    //   119: iastore
    //   120: dup
    //   121: bipush #15
    //   123: ldc 874189824
    //   125: iastore
    //   126: dup
    //   127: bipush #16
    //   129: ldc 655302664
    //   131: iastore
    //   132: dup
    //   133: bipush #17
    //   135: ldc 890966315
    //   137: iastore
    //   138: dup
    //   139: bipush #18
    //   141: ldc 722417666
    //   143: iastore
    //   144: dup
    //   145: bipush #19
    //   147: ldc 1026621720
    //   149: iastore
    //   150: dup
    //   151: bipush #20
    //   153: ldc 957157408
    //   155: iastore
    //   156: dup
    //   157: bipush #21
    //   159: ldc 892536332
    //   161: iastore
    //   162: dup
    //   163: bipush #22
    //   165: ldc 689771012
    //   167: iastore
    //   168: dup
    //   169: bipush #23
    //   171: ldc 221709344
    //   173: iastore
    //   174: dup
    //   175: bipush #24
    //   177: ldc 940377620
    //   179: iastore
    //   180: dup
    //   181: bipush #25
    //   183: ldc 255209728
    //   185: iastore
    //   186: dup
    //   187: bipush #26
    //   189: ldc 1010368540
    //   191: iastore
    //   192: dup
    //   193: bipush #27
    //   195: ldc 220604441
    //   197: iastore
    //   198: dup
    //   199: bipush #28
    //   201: ldc 1008414755
    //   203: iastore
    //   204: dup
    //   205: bipush #29
    //   207: ldc 187049985
    //   209: iastore
    //   210: dup
    //   211: bipush #30
    //   213: ldc 943331329
    //   215: iastore
    //   216: dup
    //   217: bipush #31
    //   219: ldc 170788368
    //   221: iastore
    //   222: astore #5
    //   224: bipush #64
    //   226: newarray int
    //   228: dup
    //   229: iconst_0
    //   230: ldc 16843776
    //   232: iastore
    //   233: dup
    //   234: iconst_1
    //   235: iconst_0
    //   236: iastore
    //   237: dup
    //   238: iconst_2
    //   239: ldc 65536
    //   241: iastore
    //   242: dup
    //   243: iconst_3
    //   244: ldc 16843780
    //   246: iastore
    //   247: dup
    //   248: iconst_4
    //   249: ldc 16842756
    //   251: iastore
    //   252: dup
    //   253: iconst_5
    //   254: ldc 66564
    //   256: iastore
    //   257: dup
    //   258: bipush #6
    //   260: iconst_4
    //   261: iastore
    //   262: dup
    //   263: bipush #7
    //   265: ldc 65536
    //   267: iastore
    //   268: dup
    //   269: bipush #8
    //   271: sipush #1024
    //   274: iastore
    //   275: dup
    //   276: bipush #9
    //   278: ldc 16843776
    //   280: iastore
    //   281: dup
    //   282: bipush #10
    //   284: ldc 16843780
    //   286: iastore
    //   287: dup
    //   288: bipush #11
    //   290: sipush #1024
    //   293: iastore
    //   294: dup
    //   295: bipush #12
    //   297: ldc 16778244
    //   299: iastore
    //   300: dup
    //   301: bipush #13
    //   303: ldc 16842756
    //   305: iastore
    //   306: dup
    //   307: bipush #14
    //   309: ldc 16777216
    //   311: iastore
    //   312: dup
    //   313: bipush #15
    //   315: iconst_4
    //   316: iastore
    //   317: dup
    //   318: bipush #16
    //   320: sipush #1028
    //   323: iastore
    //   324: dup
    //   325: bipush #17
    //   327: ldc 16778240
    //   329: iastore
    //   330: dup
    //   331: bipush #18
    //   333: ldc 16778240
    //   335: iastore
    //   336: dup
    //   337: bipush #19
    //   339: ldc 66560
    //   341: iastore
    //   342: dup
    //   343: bipush #20
    //   345: ldc 66560
    //   347: iastore
    //   348: dup
    //   349: bipush #21
    //   351: ldc 16842752
    //   353: iastore
    //   354: dup
    //   355: bipush #22
    //   357: ldc 16842752
    //   359: iastore
    //   360: dup
    //   361: bipush #23
    //   363: ldc 16778244
    //   365: iastore
    //   366: dup
    //   367: bipush #24
    //   369: ldc 65540
    //   371: iastore
    //   372: dup
    //   373: bipush #25
    //   375: ldc 16777220
    //   377: iastore
    //   378: dup
    //   379: bipush #26
    //   381: ldc 16777220
    //   383: iastore
    //   384: dup
    //   385: bipush #27
    //   387: ldc 65540
    //   389: iastore
    //   390: dup
    //   391: bipush #28
    //   393: iconst_0
    //   394: iastore
    //   395: dup
    //   396: bipush #29
    //   398: sipush #1028
    //   401: iastore
    //   402: dup
    //   403: bipush #30
    //   405: ldc 66564
    //   407: iastore
    //   408: dup
    //   409: bipush #31
    //   411: ldc 16777216
    //   413: iastore
    //   414: dup
    //   415: bipush #32
    //   417: ldc 65536
    //   419: iastore
    //   420: dup
    //   421: bipush #33
    //   423: ldc 16843780
    //   425: iastore
    //   426: dup
    //   427: bipush #34
    //   429: iconst_4
    //   430: iastore
    //   431: dup
    //   432: bipush #35
    //   434: ldc 16842752
    //   436: iastore
    //   437: dup
    //   438: bipush #36
    //   440: ldc 16843776
    //   442: iastore
    //   443: dup
    //   444: bipush #37
    //   446: ldc 16777216
    //   448: iastore
    //   449: dup
    //   450: bipush #38
    //   452: ldc 16777216
    //   454: iastore
    //   455: dup
    //   456: bipush #39
    //   458: sipush #1024
    //   461: iastore
    //   462: dup
    //   463: bipush #40
    //   465: ldc 16842756
    //   467: iastore
    //   468: dup
    //   469: bipush #41
    //   471: ldc 65536
    //   473: iastore
    //   474: dup
    //   475: bipush #42
    //   477: ldc 66560
    //   479: iastore
    //   480: dup
    //   481: bipush #43
    //   483: ldc 16777220
    //   485: iastore
    //   486: dup
    //   487: bipush #44
    //   489: sipush #1024
    //   492: iastore
    //   493: dup
    //   494: bipush #45
    //   496: iconst_4
    //   497: iastore
    //   498: dup
    //   499: bipush #46
    //   501: ldc 16778244
    //   503: iastore
    //   504: dup
    //   505: bipush #47
    //   507: ldc 66564
    //   509: iastore
    //   510: dup
    //   511: bipush #48
    //   513: ldc 16843780
    //   515: iastore
    //   516: dup
    //   517: bipush #49
    //   519: ldc 65540
    //   521: iastore
    //   522: dup
    //   523: bipush #50
    //   525: ldc 16842752
    //   527: iastore
    //   528: dup
    //   529: bipush #51
    //   531: ldc 16778244
    //   533: iastore
    //   534: dup
    //   535: bipush #52
    //   537: ldc 16777220
    //   539: iastore
    //   540: dup
    //   541: bipush #53
    //   543: sipush #1028
    //   546: iastore
    //   547: dup
    //   548: bipush #54
    //   550: ldc 66564
    //   552: iastore
    //   553: dup
    //   554: bipush #55
    //   556: ldc 16843776
    //   558: iastore
    //   559: dup
    //   560: bipush #56
    //   562: sipush #1028
    //   565: iastore
    //   566: dup
    //   567: bipush #57
    //   569: ldc 16778240
    //   571: iastore
    //   572: dup
    //   573: bipush #58
    //   575: ldc 16778240
    //   577: iastore
    //   578: dup
    //   579: bipush #59
    //   581: iconst_0
    //   582: iastore
    //   583: dup
    //   584: bipush #60
    //   586: ldc 65540
    //   588: iastore
    //   589: dup
    //   590: bipush #61
    //   592: ldc 66560
    //   594: iastore
    //   595: dup
    //   596: bipush #62
    //   598: iconst_0
    //   599: iastore
    //   600: dup
    //   601: bipush #63
    //   603: ldc 16842756
    //   605: iastore
    //   606: astore #6
    //   608: bipush #64
    //   610: newarray int
    //   612: dup
    //   613: iconst_0
    //   614: ldc -2146402272
    //   616: iastore
    //   617: dup
    //   618: iconst_1
    //   619: ldc -2147450880
    //   621: iastore
    //   622: dup
    //   623: iconst_2
    //   624: ldc 32768
    //   626: iastore
    //   627: dup
    //   628: iconst_3
    //   629: ldc 1081376
    //   631: iastore
    //   632: dup
    //   633: iconst_4
    //   634: ldc 1048576
    //   636: iastore
    //   637: dup
    //   638: iconst_5
    //   639: bipush #32
    //   641: iastore
    //   642: dup
    //   643: bipush #6
    //   645: ldc -2146435040
    //   647: iastore
    //   648: dup
    //   649: bipush #7
    //   651: ldc -2147450848
    //   653: iastore
    //   654: dup
    //   655: bipush #8
    //   657: ldc -2147483616
    //   659: iastore
    //   660: dup
    //   661: bipush #9
    //   663: ldc -2146402272
    //   665: iastore
    //   666: dup
    //   667: bipush #10
    //   669: ldc -2146402304
    //   671: iastore
    //   672: dup
    //   673: bipush #11
    //   675: ldc -2147483648
    //   677: iastore
    //   678: dup
    //   679: bipush #12
    //   681: ldc -2147450880
    //   683: iastore
    //   684: dup
    //   685: bipush #13
    //   687: ldc 1048576
    //   689: iastore
    //   690: dup
    //   691: bipush #14
    //   693: bipush #32
    //   695: iastore
    //   696: dup
    //   697: bipush #15
    //   699: ldc -2146435040
    //   701: iastore
    //   702: dup
    //   703: bipush #16
    //   705: ldc 1081344
    //   707: iastore
    //   708: dup
    //   709: bipush #17
    //   711: ldc 1048608
    //   713: iastore
    //   714: dup
    //   715: bipush #18
    //   717: ldc -2147450848
    //   719: iastore
    //   720: dup
    //   721: bipush #19
    //   723: iconst_0
    //   724: iastore
    //   725: dup
    //   726: bipush #20
    //   728: ldc -2147483648
    //   730: iastore
    //   731: dup
    //   732: bipush #21
    //   734: ldc 32768
    //   736: iastore
    //   737: dup
    //   738: bipush #22
    //   740: ldc 1081376
    //   742: iastore
    //   743: dup
    //   744: bipush #23
    //   746: ldc -2146435072
    //   748: iastore
    //   749: dup
    //   750: bipush #24
    //   752: ldc 1048608
    //   754: iastore
    //   755: dup
    //   756: bipush #25
    //   758: ldc -2147483616
    //   760: iastore
    //   761: dup
    //   762: bipush #26
    //   764: iconst_0
    //   765: iastore
    //   766: dup
    //   767: bipush #27
    //   769: ldc 1081344
    //   771: iastore
    //   772: dup
    //   773: bipush #28
    //   775: ldc 32800
    //   777: iastore
    //   778: dup
    //   779: bipush #29
    //   781: ldc -2146402304
    //   783: iastore
    //   784: dup
    //   785: bipush #30
    //   787: ldc -2146435072
    //   789: iastore
    //   790: dup
    //   791: bipush #31
    //   793: ldc 32800
    //   795: iastore
    //   796: dup
    //   797: bipush #32
    //   799: iconst_0
    //   800: iastore
    //   801: dup
    //   802: bipush #33
    //   804: ldc 1081376
    //   806: iastore
    //   807: dup
    //   808: bipush #34
    //   810: ldc -2146435040
    //   812: iastore
    //   813: dup
    //   814: bipush #35
    //   816: ldc 1048576
    //   818: iastore
    //   819: dup
    //   820: bipush #36
    //   822: ldc -2147450848
    //   824: iastore
    //   825: dup
    //   826: bipush #37
    //   828: ldc -2146435072
    //   830: iastore
    //   831: dup
    //   832: bipush #38
    //   834: ldc -2146402304
    //   836: iastore
    //   837: dup
    //   838: bipush #39
    //   840: ldc 32768
    //   842: iastore
    //   843: dup
    //   844: bipush #40
    //   846: ldc -2146435072
    //   848: iastore
    //   849: dup
    //   850: bipush #41
    //   852: ldc -2147450880
    //   854: iastore
    //   855: dup
    //   856: bipush #42
    //   858: bipush #32
    //   860: iastore
    //   861: dup
    //   862: bipush #43
    //   864: ldc -2146402272
    //   866: iastore
    //   867: dup
    //   868: bipush #44
    //   870: ldc 1081376
    //   872: iastore
    //   873: dup
    //   874: bipush #45
    //   876: bipush #32
    //   878: iastore
    //   879: dup
    //   880: bipush #46
    //   882: ldc 32768
    //   884: iastore
    //   885: dup
    //   886: bipush #47
    //   888: ldc -2147483648
    //   890: iastore
    //   891: dup
    //   892: bipush #48
    //   894: ldc 32800
    //   896: iastore
    //   897: dup
    //   898: bipush #49
    //   900: ldc -2146402304
    //   902: iastore
    //   903: dup
    //   904: bipush #50
    //   906: ldc 1048576
    //   908: iastore
    //   909: dup
    //   910: bipush #51
    //   912: ldc -2147483616
    //   914: iastore
    //   915: dup
    //   916: bipush #52
    //   918: ldc 1048608
    //   920: iastore
    //   921: dup
    //   922: bipush #53
    //   924: ldc -2147450848
    //   926: iastore
    //   927: dup
    //   928: bipush #54
    //   930: ldc -2147483616
    //   932: iastore
    //   933: dup
    //   934: bipush #55
    //   936: ldc 1048608
    //   938: iastore
    //   939: dup
    //   940: bipush #56
    //   942: ldc 1081344
    //   944: iastore
    //   945: dup
    //   946: bipush #57
    //   948: iconst_0
    //   949: iastore
    //   950: dup
    //   951: bipush #58
    //   953: ldc -2147450880
    //   955: iastore
    //   956: dup
    //   957: bipush #59
    //   959: ldc 32800
    //   961: iastore
    //   962: dup
    //   963: bipush #60
    //   965: ldc -2147483648
    //   967: iastore
    //   968: dup
    //   969: bipush #61
    //   971: ldc -2146435040
    //   973: iastore
    //   974: dup
    //   975: bipush #62
    //   977: ldc -2146402272
    //   979: iastore
    //   980: dup
    //   981: bipush #63
    //   983: ldc 1081344
    //   985: iastore
    //   986: astore #7
    //   988: bipush #64
    //   990: newarray int
    //   992: dup
    //   993: iconst_0
    //   994: sipush #520
    //   997: iastore
    //   998: dup
    //   999: iconst_1
    //   1000: ldc 134349312
    //   1002: iastore
    //   1003: dup
    //   1004: iconst_2
    //   1005: iconst_0
    //   1006: iastore
    //   1007: dup
    //   1008: iconst_3
    //   1009: ldc 134348808
    //   1011: iastore
    //   1012: dup
    //   1013: iconst_4
    //   1014: ldc 134218240
    //   1016: iastore
    //   1017: dup
    //   1018: iconst_5
    //   1019: iconst_0
    //   1020: iastore
    //   1021: dup
    //   1022: bipush #6
    //   1024: ldc 131592
    //   1026: iastore
    //   1027: dup
    //   1028: bipush #7
    //   1030: ldc 134218240
    //   1032: iastore
    //   1033: dup
    //   1034: bipush #8
    //   1036: ldc 131080
    //   1038: iastore
    //   1039: dup
    //   1040: bipush #9
    //   1042: ldc 134217736
    //   1044: iastore
    //   1045: dup
    //   1046: bipush #10
    //   1048: ldc 134217736
    //   1050: iastore
    //   1051: dup
    //   1052: bipush #11
    //   1054: ldc 131072
    //   1056: iastore
    //   1057: dup
    //   1058: bipush #12
    //   1060: ldc 134349320
    //   1062: iastore
    //   1063: dup
    //   1064: bipush #13
    //   1066: ldc 131080
    //   1068: iastore
    //   1069: dup
    //   1070: bipush #14
    //   1072: ldc 134348800
    //   1074: iastore
    //   1075: dup
    //   1076: bipush #15
    //   1078: sipush #520
    //   1081: iastore
    //   1082: dup
    //   1083: bipush #16
    //   1085: ldc 134217728
    //   1087: iastore
    //   1088: dup
    //   1089: bipush #17
    //   1091: bipush #8
    //   1093: iastore
    //   1094: dup
    //   1095: bipush #18
    //   1097: ldc 134349312
    //   1099: iastore
    //   1100: dup
    //   1101: bipush #19
    //   1103: sipush #512
    //   1106: iastore
    //   1107: dup
    //   1108: bipush #20
    //   1110: ldc 131584
    //   1112: iastore
    //   1113: dup
    //   1114: bipush #21
    //   1116: ldc 134348800
    //   1118: iastore
    //   1119: dup
    //   1120: bipush #22
    //   1122: ldc 134348808
    //   1124: iastore
    //   1125: dup
    //   1126: bipush #23
    //   1128: ldc 131592
    //   1130: iastore
    //   1131: dup
    //   1132: bipush #24
    //   1134: ldc 134218248
    //   1136: iastore
    //   1137: dup
    //   1138: bipush #25
    //   1140: ldc 131584
    //   1142: iastore
    //   1143: dup
    //   1144: bipush #26
    //   1146: ldc 131072
    //   1148: iastore
    //   1149: dup
    //   1150: bipush #27
    //   1152: ldc 134218248
    //   1154: iastore
    //   1155: dup
    //   1156: bipush #28
    //   1158: bipush #8
    //   1160: iastore
    //   1161: dup
    //   1162: bipush #29
    //   1164: ldc 134349320
    //   1166: iastore
    //   1167: dup
    //   1168: bipush #30
    //   1170: sipush #512
    //   1173: iastore
    //   1174: dup
    //   1175: bipush #31
    //   1177: ldc 134217728
    //   1179: iastore
    //   1180: dup
    //   1181: bipush #32
    //   1183: ldc 134349312
    //   1185: iastore
    //   1186: dup
    //   1187: bipush #33
    //   1189: ldc 134217728
    //   1191: iastore
    //   1192: dup
    //   1193: bipush #34
    //   1195: ldc 131080
    //   1197: iastore
    //   1198: dup
    //   1199: bipush #35
    //   1201: sipush #520
    //   1204: iastore
    //   1205: dup
    //   1206: bipush #36
    //   1208: ldc 131072
    //   1210: iastore
    //   1211: dup
    //   1212: bipush #37
    //   1214: ldc 134349312
    //   1216: iastore
    //   1217: dup
    //   1218: bipush #38
    //   1220: ldc 134218240
    //   1222: iastore
    //   1223: dup
    //   1224: bipush #39
    //   1226: iconst_0
    //   1227: iastore
    //   1228: dup
    //   1229: bipush #40
    //   1231: sipush #512
    //   1234: iastore
    //   1235: dup
    //   1236: bipush #41
    //   1238: ldc 131080
    //   1240: iastore
    //   1241: dup
    //   1242: bipush #42
    //   1244: ldc 134349320
    //   1246: iastore
    //   1247: dup
    //   1248: bipush #43
    //   1250: ldc 134218240
    //   1252: iastore
    //   1253: dup
    //   1254: bipush #44
    //   1256: ldc 134217736
    //   1258: iastore
    //   1259: dup
    //   1260: bipush #45
    //   1262: sipush #512
    //   1265: iastore
    //   1266: dup
    //   1267: bipush #46
    //   1269: iconst_0
    //   1270: iastore
    //   1271: dup
    //   1272: bipush #47
    //   1274: ldc 134348808
    //   1276: iastore
    //   1277: dup
    //   1278: bipush #48
    //   1280: ldc 134218248
    //   1282: iastore
    //   1283: dup
    //   1284: bipush #49
    //   1286: ldc 131072
    //   1288: iastore
    //   1289: dup
    //   1290: bipush #50
    //   1292: ldc 134217728
    //   1294: iastore
    //   1295: dup
    //   1296: bipush #51
    //   1298: ldc 134349320
    //   1300: iastore
    //   1301: dup
    //   1302: bipush #52
    //   1304: bipush #8
    //   1306: iastore
    //   1307: dup
    //   1308: bipush #53
    //   1310: ldc 131592
    //   1312: iastore
    //   1313: dup
    //   1314: bipush #54
    //   1316: ldc 131584
    //   1318: iastore
    //   1319: dup
    //   1320: bipush #55
    //   1322: ldc 134217736
    //   1324: iastore
    //   1325: dup
    //   1326: bipush #56
    //   1328: ldc 134348800
    //   1330: iastore
    //   1331: dup
    //   1332: bipush #57
    //   1334: ldc 134218248
    //   1336: iastore
    //   1337: dup
    //   1338: bipush #58
    //   1340: sipush #520
    //   1343: iastore
    //   1344: dup
    //   1345: bipush #59
    //   1347: ldc 134348800
    //   1349: iastore
    //   1350: dup
    //   1351: bipush #60
    //   1353: ldc 131592
    //   1355: iastore
    //   1356: dup
    //   1357: bipush #61
    //   1359: bipush #8
    //   1361: iastore
    //   1362: dup
    //   1363: bipush #62
    //   1365: ldc 134348808
    //   1367: iastore
    //   1368: dup
    //   1369: bipush #63
    //   1371: ldc 131584
    //   1373: iastore
    //   1374: astore #8
    //   1376: bipush #64
    //   1378: newarray int
    //   1380: dup
    //   1381: iconst_0
    //   1382: ldc 8396801
    //   1384: iastore
    //   1385: dup
    //   1386: iconst_1
    //   1387: sipush #8321
    //   1390: iastore
    //   1391: dup
    //   1392: iconst_2
    //   1393: sipush #8321
    //   1396: iastore
    //   1397: dup
    //   1398: iconst_3
    //   1399: sipush #128
    //   1402: iastore
    //   1403: dup
    //   1404: iconst_4
    //   1405: ldc 8396928
    //   1407: iastore
    //   1408: dup
    //   1409: iconst_5
    //   1410: ldc 8388737
    //   1412: iastore
    //   1413: dup
    //   1414: bipush #6
    //   1416: ldc 8388609
    //   1418: iastore
    //   1419: dup
    //   1420: bipush #7
    //   1422: sipush #8193
    //   1425: iastore
    //   1426: dup
    //   1427: bipush #8
    //   1429: iconst_0
    //   1430: iastore
    //   1431: dup
    //   1432: bipush #9
    //   1434: ldc 8396800
    //   1436: iastore
    //   1437: dup
    //   1438: bipush #10
    //   1440: ldc 8396800
    //   1442: iastore
    //   1443: dup
    //   1444: bipush #11
    //   1446: ldc 8396929
    //   1448: iastore
    //   1449: dup
    //   1450: bipush #12
    //   1452: sipush #129
    //   1455: iastore
    //   1456: dup
    //   1457: bipush #13
    //   1459: iconst_0
    //   1460: iastore
    //   1461: dup
    //   1462: bipush #14
    //   1464: ldc 8388736
    //   1466: iastore
    //   1467: dup
    //   1468: bipush #15
    //   1470: ldc 8388609
    //   1472: iastore
    //   1473: dup
    //   1474: bipush #16
    //   1476: iconst_1
    //   1477: iastore
    //   1478: dup
    //   1479: bipush #17
    //   1481: sipush #8192
    //   1484: iastore
    //   1485: dup
    //   1486: bipush #18
    //   1488: ldc 8388608
    //   1490: iastore
    //   1491: dup
    //   1492: bipush #19
    //   1494: ldc 8396801
    //   1496: iastore
    //   1497: dup
    //   1498: bipush #20
    //   1500: sipush #128
    //   1503: iastore
    //   1504: dup
    //   1505: bipush #21
    //   1507: ldc 8388608
    //   1509: iastore
    //   1510: dup
    //   1511: bipush #22
    //   1513: sipush #8193
    //   1516: iastore
    //   1517: dup
    //   1518: bipush #23
    //   1520: sipush #8320
    //   1523: iastore
    //   1524: dup
    //   1525: bipush #24
    //   1527: ldc 8388737
    //   1529: iastore
    //   1530: dup
    //   1531: bipush #25
    //   1533: iconst_1
    //   1534: iastore
    //   1535: dup
    //   1536: bipush #26
    //   1538: sipush #8320
    //   1541: iastore
    //   1542: dup
    //   1543: bipush #27
    //   1545: ldc 8388736
    //   1547: iastore
    //   1548: dup
    //   1549: bipush #28
    //   1551: sipush #8192
    //   1554: iastore
    //   1555: dup
    //   1556: bipush #29
    //   1558: ldc 8396928
    //   1560: iastore
    //   1561: dup
    //   1562: bipush #30
    //   1564: ldc 8396929
    //   1566: iastore
    //   1567: dup
    //   1568: bipush #31
    //   1570: sipush #129
    //   1573: iastore
    //   1574: dup
    //   1575: bipush #32
    //   1577: ldc 8388736
    //   1579: iastore
    //   1580: dup
    //   1581: bipush #33
    //   1583: ldc 8388609
    //   1585: iastore
    //   1586: dup
    //   1587: bipush #34
    //   1589: ldc 8396800
    //   1591: iastore
    //   1592: dup
    //   1593: bipush #35
    //   1595: ldc 8396929
    //   1597: iastore
    //   1598: dup
    //   1599: bipush #36
    //   1601: sipush #129
    //   1604: iastore
    //   1605: dup
    //   1606: bipush #37
    //   1608: iconst_0
    //   1609: iastore
    //   1610: dup
    //   1611: bipush #38
    //   1613: iconst_0
    //   1614: iastore
    //   1615: dup
    //   1616: bipush #39
    //   1618: ldc 8396800
    //   1620: iastore
    //   1621: dup
    //   1622: bipush #40
    //   1624: sipush #8320
    //   1627: iastore
    //   1628: dup
    //   1629: bipush #41
    //   1631: ldc 8388736
    //   1633: iastore
    //   1634: dup
    //   1635: bipush #42
    //   1637: ldc 8388737
    //   1639: iastore
    //   1640: dup
    //   1641: bipush #43
    //   1643: iconst_1
    //   1644: iastore
    //   1645: dup
    //   1646: bipush #44
    //   1648: ldc 8396801
    //   1650: iastore
    //   1651: dup
    //   1652: bipush #45
    //   1654: sipush #8321
    //   1657: iastore
    //   1658: dup
    //   1659: bipush #46
    //   1661: sipush #8321
    //   1664: iastore
    //   1665: dup
    //   1666: bipush #47
    //   1668: sipush #128
    //   1671: iastore
    //   1672: dup
    //   1673: bipush #48
    //   1675: ldc 8396929
    //   1677: iastore
    //   1678: dup
    //   1679: bipush #49
    //   1681: sipush #129
    //   1684: iastore
    //   1685: dup
    //   1686: bipush #50
    //   1688: iconst_1
    //   1689: iastore
    //   1690: dup
    //   1691: bipush #51
    //   1693: sipush #8192
    //   1696: iastore
    //   1697: dup
    //   1698: bipush #52
    //   1700: ldc 8388609
    //   1702: iastore
    //   1703: dup
    //   1704: bipush #53
    //   1706: sipush #8193
    //   1709: iastore
    //   1710: dup
    //   1711: bipush #54
    //   1713: ldc 8396928
    //   1715: iastore
    //   1716: dup
    //   1717: bipush #55
    //   1719: ldc 8388737
    //   1721: iastore
    //   1722: dup
    //   1723: bipush #56
    //   1725: sipush #8193
    //   1728: iastore
    //   1729: dup
    //   1730: bipush #57
    //   1732: sipush #8320
    //   1735: iastore
    //   1736: dup
    //   1737: bipush #58
    //   1739: ldc 8388608
    //   1741: iastore
    //   1742: dup
    //   1743: bipush #59
    //   1745: ldc 8396801
    //   1747: iastore
    //   1748: dup
    //   1749: bipush #60
    //   1751: sipush #128
    //   1754: iastore
    //   1755: dup
    //   1756: bipush #61
    //   1758: ldc 8388608
    //   1760: iastore
    //   1761: dup
    //   1762: bipush #62
    //   1764: sipush #8192
    //   1767: iastore
    //   1768: dup
    //   1769: bipush #63
    //   1771: ldc 8396928
    //   1773: iastore
    //   1774: astore #9
    //   1776: bipush #64
    //   1778: newarray int
    //   1780: dup
    //   1781: iconst_0
    //   1782: sipush #256
    //   1785: iastore
    //   1786: dup
    //   1787: iconst_1
    //   1788: ldc 34078976
    //   1790: iastore
    //   1791: dup
    //   1792: iconst_2
    //   1793: ldc 34078720
    //   1795: iastore
    //   1796: dup
    //   1797: iconst_3
    //   1798: ldc 1107296512
    //   1800: iastore
    //   1801: dup
    //   1802: iconst_4
    //   1803: ldc 524288
    //   1805: iastore
    //   1806: dup
    //   1807: iconst_5
    //   1808: sipush #256
    //   1811: iastore
    //   1812: dup
    //   1813: bipush #6
    //   1815: ldc 1073741824
    //   1817: iastore
    //   1818: dup
    //   1819: bipush #7
    //   1821: ldc 34078720
    //   1823: iastore
    //   1824: dup
    //   1825: bipush #8
    //   1827: ldc 1074266368
    //   1829: iastore
    //   1830: dup
    //   1831: bipush #9
    //   1833: ldc 524288
    //   1835: iastore
    //   1836: dup
    //   1837: bipush #10
    //   1839: ldc 33554688
    //   1841: iastore
    //   1842: dup
    //   1843: bipush #11
    //   1845: ldc 1074266368
    //   1847: iastore
    //   1848: dup
    //   1849: bipush #12
    //   1851: ldc 1107296512
    //   1853: iastore
    //   1854: dup
    //   1855: bipush #13
    //   1857: ldc 1107820544
    //   1859: iastore
    //   1860: dup
    //   1861: bipush #14
    //   1863: ldc 524544
    //   1865: iastore
    //   1866: dup
    //   1867: bipush #15
    //   1869: ldc 1073741824
    //   1871: iastore
    //   1872: dup
    //   1873: bipush #16
    //   1875: ldc 33554432
    //   1877: iastore
    //   1878: dup
    //   1879: bipush #17
    //   1881: ldc 1074266112
    //   1883: iastore
    //   1884: dup
    //   1885: bipush #18
    //   1887: ldc 1074266112
    //   1889: iastore
    //   1890: dup
    //   1891: bipush #19
    //   1893: iconst_0
    //   1894: iastore
    //   1895: dup
    //   1896: bipush #20
    //   1898: ldc 1073742080
    //   1900: iastore
    //   1901: dup
    //   1902: bipush #21
    //   1904: ldc 1107820800
    //   1906: iastore
    //   1907: dup
    //   1908: bipush #22
    //   1910: ldc 1107820800
    //   1912: iastore
    //   1913: dup
    //   1914: bipush #23
    //   1916: ldc 33554688
    //   1918: iastore
    //   1919: dup
    //   1920: bipush #24
    //   1922: ldc 1107820544
    //   1924: iastore
    //   1925: dup
    //   1926: bipush #25
    //   1928: ldc 1073742080
    //   1930: iastore
    //   1931: dup
    //   1932: bipush #26
    //   1934: iconst_0
    //   1935: iastore
    //   1936: dup
    //   1937: bipush #27
    //   1939: ldc 1107296256
    //   1941: iastore
    //   1942: dup
    //   1943: bipush #28
    //   1945: ldc 34078976
    //   1947: iastore
    //   1948: dup
    //   1949: bipush #29
    //   1951: ldc 33554432
    //   1953: iastore
    //   1954: dup
    //   1955: bipush #30
    //   1957: ldc 1107296256
    //   1959: iastore
    //   1960: dup
    //   1961: bipush #31
    //   1963: ldc 524544
    //   1965: iastore
    //   1966: dup
    //   1967: bipush #32
    //   1969: ldc 524288
    //   1971: iastore
    //   1972: dup
    //   1973: bipush #33
    //   1975: ldc 1107296512
    //   1977: iastore
    //   1978: dup
    //   1979: bipush #34
    //   1981: sipush #256
    //   1984: iastore
    //   1985: dup
    //   1986: bipush #35
    //   1988: ldc 33554432
    //   1990: iastore
    //   1991: dup
    //   1992: bipush #36
    //   1994: ldc 1073741824
    //   1996: iastore
    //   1997: dup
    //   1998: bipush #37
    //   2000: ldc 34078720
    //   2002: iastore
    //   2003: dup
    //   2004: bipush #38
    //   2006: ldc 1107296512
    //   2008: iastore
    //   2009: dup
    //   2010: bipush #39
    //   2012: ldc 1074266368
    //   2014: iastore
    //   2015: dup
    //   2016: bipush #40
    //   2018: ldc 33554688
    //   2020: iastore
    //   2021: dup
    //   2022: bipush #41
    //   2024: ldc 1073741824
    //   2026: iastore
    //   2027: dup
    //   2028: bipush #42
    //   2030: ldc 1107820544
    //   2032: iastore
    //   2033: dup
    //   2034: bipush #43
    //   2036: ldc 34078976
    //   2038: iastore
    //   2039: dup
    //   2040: bipush #44
    //   2042: ldc 1074266368
    //   2044: iastore
    //   2045: dup
    //   2046: bipush #45
    //   2048: sipush #256
    //   2051: iastore
    //   2052: dup
    //   2053: bipush #46
    //   2055: ldc 33554432
    //   2057: iastore
    //   2058: dup
    //   2059: bipush #47
    //   2061: ldc 1107820544
    //   2063: iastore
    //   2064: dup
    //   2065: bipush #48
    //   2067: ldc 1107820800
    //   2069: iastore
    //   2070: dup
    //   2071: bipush #49
    //   2073: ldc 524544
    //   2075: iastore
    //   2076: dup
    //   2077: bipush #50
    //   2079: ldc 1107296256
    //   2081: iastore
    //   2082: dup
    //   2083: bipush #51
    //   2085: ldc 1107820800
    //   2087: iastore
    //   2088: dup
    //   2089: bipush #52
    //   2091: ldc 34078720
    //   2093: iastore
    //   2094: dup
    //   2095: bipush #53
    //   2097: iconst_0
    //   2098: iastore
    //   2099: dup
    //   2100: bipush #54
    //   2102: ldc 1074266112
    //   2104: iastore
    //   2105: dup
    //   2106: bipush #55
    //   2108: ldc 1107296256
    //   2110: iastore
    //   2111: dup
    //   2112: bipush #56
    //   2114: ldc 524544
    //   2116: iastore
    //   2117: dup
    //   2118: bipush #57
    //   2120: ldc 33554688
    //   2122: iastore
    //   2123: dup
    //   2124: bipush #58
    //   2126: ldc 1073742080
    //   2128: iastore
    //   2129: dup
    //   2130: bipush #59
    //   2132: ldc 524288
    //   2134: iastore
    //   2135: dup
    //   2136: bipush #60
    //   2138: iconst_0
    //   2139: iastore
    //   2140: dup
    //   2141: bipush #61
    //   2143: ldc 1074266112
    //   2145: iastore
    //   2146: dup
    //   2147: bipush #62
    //   2149: ldc 34078976
    //   2151: iastore
    //   2152: dup
    //   2153: bipush #63
    //   2155: ldc 1073742080
    //   2157: iastore
    //   2158: astore #10
    //   2160: bipush #64
    //   2162: newarray int
    //   2164: dup
    //   2165: iconst_0
    //   2166: ldc 536870928
    //   2168: iastore
    //   2169: dup
    //   2170: iconst_1
    //   2171: ldc 541065216
    //   2173: iastore
    //   2174: dup
    //   2175: iconst_2
    //   2176: sipush #16384
    //   2179: iastore
    //   2180: dup
    //   2181: iconst_3
    //   2182: ldc 541081616
    //   2184: iastore
    //   2185: dup
    //   2186: iconst_4
    //   2187: ldc 541065216
    //   2189: iastore
    //   2190: dup
    //   2191: iconst_5
    //   2192: bipush #16
    //   2194: iastore
    //   2195: dup
    //   2196: bipush #6
    //   2198: ldc 541081616
    //   2200: iastore
    //   2201: dup
    //   2202: bipush #7
    //   2204: ldc 4194304
    //   2206: iastore
    //   2207: dup
    //   2208: bipush #8
    //   2210: ldc 536887296
    //   2212: iastore
    //   2213: dup
    //   2214: bipush #9
    //   2216: ldc 4210704
    //   2218: iastore
    //   2219: dup
    //   2220: bipush #10
    //   2222: ldc 4194304
    //   2224: iastore
    //   2225: dup
    //   2226: bipush #11
    //   2228: ldc 536870928
    //   2230: iastore
    //   2231: dup
    //   2232: bipush #12
    //   2234: ldc 4194320
    //   2236: iastore
    //   2237: dup
    //   2238: bipush #13
    //   2240: ldc 536887296
    //   2242: iastore
    //   2243: dup
    //   2244: bipush #14
    //   2246: ldc 536870912
    //   2248: iastore
    //   2249: dup
    //   2250: bipush #15
    //   2252: sipush #16400
    //   2255: iastore
    //   2256: dup
    //   2257: bipush #16
    //   2259: iconst_0
    //   2260: iastore
    //   2261: dup
    //   2262: bipush #17
    //   2264: ldc 4194320
    //   2266: iastore
    //   2267: dup
    //   2268: bipush #18
    //   2270: ldc 536887312
    //   2272: iastore
    //   2273: dup
    //   2274: bipush #19
    //   2276: sipush #16384
    //   2279: iastore
    //   2280: dup
    //   2281: bipush #20
    //   2283: ldc 4210688
    //   2285: iastore
    //   2286: dup
    //   2287: bipush #21
    //   2289: ldc 536887312
    //   2291: iastore
    //   2292: dup
    //   2293: bipush #22
    //   2295: bipush #16
    //   2297: iastore
    //   2298: dup
    //   2299: bipush #23
    //   2301: ldc 541065232
    //   2303: iastore
    //   2304: dup
    //   2305: bipush #24
    //   2307: ldc 541065232
    //   2309: iastore
    //   2310: dup
    //   2311: bipush #25
    //   2313: iconst_0
    //   2314: iastore
    //   2315: dup
    //   2316: bipush #26
    //   2318: ldc 4210704
    //   2320: iastore
    //   2321: dup
    //   2322: bipush #27
    //   2324: ldc 541081600
    //   2326: iastore
    //   2327: dup
    //   2328: bipush #28
    //   2330: sipush #16400
    //   2333: iastore
    //   2334: dup
    //   2335: bipush #29
    //   2337: ldc 4210688
    //   2339: iastore
    //   2340: dup
    //   2341: bipush #30
    //   2343: ldc 541081600
    //   2345: iastore
    //   2346: dup
    //   2347: bipush #31
    //   2349: ldc 536870912
    //   2351: iastore
    //   2352: dup
    //   2353: bipush #32
    //   2355: ldc 536887296
    //   2357: iastore
    //   2358: dup
    //   2359: bipush #33
    //   2361: bipush #16
    //   2363: iastore
    //   2364: dup
    //   2365: bipush #34
    //   2367: ldc 541065232
    //   2369: iastore
    //   2370: dup
    //   2371: bipush #35
    //   2373: ldc 4210688
    //   2375: iastore
    //   2376: dup
    //   2377: bipush #36
    //   2379: ldc 541081616
    //   2381: iastore
    //   2382: dup
    //   2383: bipush #37
    //   2385: ldc 4194304
    //   2387: iastore
    //   2388: dup
    //   2389: bipush #38
    //   2391: sipush #16400
    //   2394: iastore
    //   2395: dup
    //   2396: bipush #39
    //   2398: ldc 536870928
    //   2400: iastore
    //   2401: dup
    //   2402: bipush #40
    //   2404: ldc 4194304
    //   2406: iastore
    //   2407: dup
    //   2408: bipush #41
    //   2410: ldc 536887296
    //   2412: iastore
    //   2413: dup
    //   2414: bipush #42
    //   2416: ldc 536870912
    //   2418: iastore
    //   2419: dup
    //   2420: bipush #43
    //   2422: sipush #16400
    //   2425: iastore
    //   2426: dup
    //   2427: bipush #44
    //   2429: ldc 536870928
    //   2431: iastore
    //   2432: dup
    //   2433: bipush #45
    //   2435: ldc 541081616
    //   2437: iastore
    //   2438: dup
    //   2439: bipush #46
    //   2441: ldc 4210688
    //   2443: iastore
    //   2444: dup
    //   2445: bipush #47
    //   2447: ldc 541065216
    //   2449: iastore
    //   2450: dup
    //   2451: bipush #48
    //   2453: ldc 4210704
    //   2455: iastore
    //   2456: dup
    //   2457: bipush #49
    //   2459: ldc 541081600
    //   2461: iastore
    //   2462: dup
    //   2463: bipush #50
    //   2465: iconst_0
    //   2466: iastore
    //   2467: dup
    //   2468: bipush #51
    //   2470: ldc 541065232
    //   2472: iastore
    //   2473: dup
    //   2474: bipush #52
    //   2476: bipush #16
    //   2478: iastore
    //   2479: dup
    //   2480: bipush #53
    //   2482: sipush #16384
    //   2485: iastore
    //   2486: dup
    //   2487: bipush #54
    //   2489: ldc 541065216
    //   2491: iastore
    //   2492: dup
    //   2493: bipush #55
    //   2495: ldc 4210704
    //   2497: iastore
    //   2498: dup
    //   2499: bipush #56
    //   2501: sipush #16384
    //   2504: iastore
    //   2505: dup
    //   2506: bipush #57
    //   2508: ldc 4194320
    //   2510: iastore
    //   2511: dup
    //   2512: bipush #58
    //   2514: ldc 536887312
    //   2516: iastore
    //   2517: dup
    //   2518: bipush #59
    //   2520: iconst_0
    //   2521: iastore
    //   2522: dup
    //   2523: bipush #60
    //   2525: ldc 541081600
    //   2527: iastore
    //   2528: dup
    //   2529: bipush #61
    //   2531: ldc 536870912
    //   2533: iastore
    //   2534: dup
    //   2535: bipush #62
    //   2537: ldc 4194320
    //   2539: iastore
    //   2540: dup
    //   2541: bipush #63
    //   2543: ldc 536887312
    //   2545: iastore
    //   2546: astore #11
    //   2548: bipush #64
    //   2550: newarray int
    //   2552: dup
    //   2553: iconst_0
    //   2554: ldc 2097152
    //   2556: iastore
    //   2557: dup
    //   2558: iconst_1
    //   2559: ldc 69206018
    //   2561: iastore
    //   2562: dup
    //   2563: iconst_2
    //   2564: ldc 67110914
    //   2566: iastore
    //   2567: dup
    //   2568: iconst_3
    //   2569: iconst_0
    //   2570: iastore
    //   2571: dup
    //   2572: iconst_4
    //   2573: sipush #2048
    //   2576: iastore
    //   2577: dup
    //   2578: iconst_5
    //   2579: ldc 67110914
    //   2581: iastore
    //   2582: dup
    //   2583: bipush #6
    //   2585: ldc 2099202
    //   2587: iastore
    //   2588: dup
    //   2589: bipush #7
    //   2591: ldc 69208064
    //   2593: iastore
    //   2594: dup
    //   2595: bipush #8
    //   2597: ldc 69208066
    //   2599: iastore
    //   2600: dup
    //   2601: bipush #9
    //   2603: ldc 2097152
    //   2605: iastore
    //   2606: dup
    //   2607: bipush #10
    //   2609: iconst_0
    //   2610: iastore
    //   2611: dup
    //   2612: bipush #11
    //   2614: ldc 67108866
    //   2616: iastore
    //   2617: dup
    //   2618: bipush #12
    //   2620: iconst_2
    //   2621: iastore
    //   2622: dup
    //   2623: bipush #13
    //   2625: ldc 67108864
    //   2627: iastore
    //   2628: dup
    //   2629: bipush #14
    //   2631: ldc 69206018
    //   2633: iastore
    //   2634: dup
    //   2635: bipush #15
    //   2637: sipush #2050
    //   2640: iastore
    //   2641: dup
    //   2642: bipush #16
    //   2644: ldc 67110912
    //   2646: iastore
    //   2647: dup
    //   2648: bipush #17
    //   2650: ldc 2099202
    //   2652: iastore
    //   2653: dup
    //   2654: bipush #18
    //   2656: ldc 2097154
    //   2658: iastore
    //   2659: dup
    //   2660: bipush #19
    //   2662: ldc 67110912
    //   2664: iastore
    //   2665: dup
    //   2666: bipush #20
    //   2668: ldc 67108866
    //   2670: iastore
    //   2671: dup
    //   2672: bipush #21
    //   2674: ldc 69206016
    //   2676: iastore
    //   2677: dup
    //   2678: bipush #22
    //   2680: ldc 69208064
    //   2682: iastore
    //   2683: dup
    //   2684: bipush #23
    //   2686: ldc 2097154
    //   2688: iastore
    //   2689: dup
    //   2690: bipush #24
    //   2692: ldc 69206016
    //   2694: iastore
    //   2695: dup
    //   2696: bipush #25
    //   2698: sipush #2048
    //   2701: iastore
    //   2702: dup
    //   2703: bipush #26
    //   2705: sipush #2050
    //   2708: iastore
    //   2709: dup
    //   2710: bipush #27
    //   2712: ldc 69208066
    //   2714: iastore
    //   2715: dup
    //   2716: bipush #28
    //   2718: ldc 2099200
    //   2720: iastore
    //   2721: dup
    //   2722: bipush #29
    //   2724: iconst_2
    //   2725: iastore
    //   2726: dup
    //   2727: bipush #30
    //   2729: ldc 67108864
    //   2731: iastore
    //   2732: dup
    //   2733: bipush #31
    //   2735: ldc 2099200
    //   2737: iastore
    //   2738: dup
    //   2739: bipush #32
    //   2741: ldc 67108864
    //   2743: iastore
    //   2744: dup
    //   2745: bipush #33
    //   2747: ldc 2099200
    //   2749: iastore
    //   2750: dup
    //   2751: bipush #34
    //   2753: ldc 2097152
    //   2755: iastore
    //   2756: dup
    //   2757: bipush #35
    //   2759: ldc 67110914
    //   2761: iastore
    //   2762: dup
    //   2763: bipush #36
    //   2765: ldc 67110914
    //   2767: iastore
    //   2768: dup
    //   2769: bipush #37
    //   2771: ldc 69206018
    //   2773: iastore
    //   2774: dup
    //   2775: bipush #38
    //   2777: ldc 69206018
    //   2779: iastore
    //   2780: dup
    //   2781: bipush #39
    //   2783: iconst_2
    //   2784: iastore
    //   2785: dup
    //   2786: bipush #40
    //   2788: ldc 2097154
    //   2790: iastore
    //   2791: dup
    //   2792: bipush #41
    //   2794: ldc 67108864
    //   2796: iastore
    //   2797: dup
    //   2798: bipush #42
    //   2800: ldc 67110912
    //   2802: iastore
    //   2803: dup
    //   2804: bipush #43
    //   2806: ldc 2097152
    //   2808: iastore
    //   2809: dup
    //   2810: bipush #44
    //   2812: ldc 69208064
    //   2814: iastore
    //   2815: dup
    //   2816: bipush #45
    //   2818: sipush #2050
    //   2821: iastore
    //   2822: dup
    //   2823: bipush #46
    //   2825: ldc 2099202
    //   2827: iastore
    //   2828: dup
    //   2829: bipush #47
    //   2831: ldc 69208064
    //   2833: iastore
    //   2834: dup
    //   2835: bipush #48
    //   2837: sipush #2050
    //   2840: iastore
    //   2841: dup
    //   2842: bipush #49
    //   2844: ldc 67108866
    //   2846: iastore
    //   2847: dup
    //   2848: bipush #50
    //   2850: ldc 69208066
    //   2852: iastore
    //   2853: dup
    //   2854: bipush #51
    //   2856: ldc 69206016
    //   2858: iastore
    //   2859: dup
    //   2860: bipush #52
    //   2862: ldc 2099200
    //   2864: iastore
    //   2865: dup
    //   2866: bipush #53
    //   2868: iconst_0
    //   2869: iastore
    //   2870: dup
    //   2871: bipush #54
    //   2873: iconst_2
    //   2874: iastore
    //   2875: dup
    //   2876: bipush #55
    //   2878: ldc 69208066
    //   2880: iastore
    //   2881: dup
    //   2882: bipush #56
    //   2884: iconst_0
    //   2885: iastore
    //   2886: dup
    //   2887: bipush #57
    //   2889: ldc 2099202
    //   2891: iastore
    //   2892: dup
    //   2893: bipush #58
    //   2895: ldc 69206016
    //   2897: iastore
    //   2898: dup
    //   2899: bipush #59
    //   2901: sipush #2048
    //   2904: iastore
    //   2905: dup
    //   2906: bipush #60
    //   2908: ldc 67108866
    //   2910: iastore
    //   2911: dup
    //   2912: bipush #61
    //   2914: ldc 67110912
    //   2916: iastore
    //   2917: dup
    //   2918: bipush #62
    //   2920: sipush #2048
    //   2923: iastore
    //   2924: dup
    //   2925: bipush #63
    //   2927: ldc 2097154
    //   2929: iastore
    //   2930: astore #12
    //   2932: bipush #64
    //   2934: newarray int
    //   2936: dup
    //   2937: iconst_0
    //   2938: ldc 268439616
    //   2940: iastore
    //   2941: dup
    //   2942: iconst_1
    //   2943: sipush #4096
    //   2946: iastore
    //   2947: dup
    //   2948: iconst_2
    //   2949: ldc 262144
    //   2951: iastore
    //   2952: dup
    //   2953: iconst_3
    //   2954: ldc 268701760
    //   2956: iastore
    //   2957: dup
    //   2958: iconst_4
    //   2959: ldc 268435456
    //   2961: iastore
    //   2962: dup
    //   2963: iconst_5
    //   2964: ldc 268439616
    //   2966: iastore
    //   2967: dup
    //   2968: bipush #6
    //   2970: bipush #64
    //   2972: iastore
    //   2973: dup
    //   2974: bipush #7
    //   2976: ldc 268435456
    //   2978: iastore
    //   2979: dup
    //   2980: bipush #8
    //   2982: ldc 262208
    //   2984: iastore
    //   2985: dup
    //   2986: bipush #9
    //   2988: ldc 268697600
    //   2990: iastore
    //   2991: dup
    //   2992: bipush #10
    //   2994: ldc 268701760
    //   2996: iastore
    //   2997: dup
    //   2998: bipush #11
    //   3000: ldc 266240
    //   3002: iastore
    //   3003: dup
    //   3004: bipush #12
    //   3006: ldc 268701696
    //   3008: iastore
    //   3009: dup
    //   3010: bipush #13
    //   3012: ldc 266304
    //   3014: iastore
    //   3015: dup
    //   3016: bipush #14
    //   3018: sipush #4096
    //   3021: iastore
    //   3022: dup
    //   3023: bipush #15
    //   3025: bipush #64
    //   3027: iastore
    //   3028: dup
    //   3029: bipush #16
    //   3031: ldc 268697600
    //   3033: iastore
    //   3034: dup
    //   3035: bipush #17
    //   3037: ldc 268435520
    //   3039: iastore
    //   3040: dup
    //   3041: bipush #18
    //   3043: ldc 268439552
    //   3045: iastore
    //   3046: dup
    //   3047: bipush #19
    //   3049: sipush #4160
    //   3052: iastore
    //   3053: dup
    //   3054: bipush #20
    //   3056: ldc 266240
    //   3058: iastore
    //   3059: dup
    //   3060: bipush #21
    //   3062: ldc 262208
    //   3064: iastore
    //   3065: dup
    //   3066: bipush #22
    //   3068: ldc 268697664
    //   3070: iastore
    //   3071: dup
    //   3072: bipush #23
    //   3074: ldc 268701696
    //   3076: iastore
    //   3077: dup
    //   3078: bipush #24
    //   3080: sipush #4160
    //   3083: iastore
    //   3084: dup
    //   3085: bipush #25
    //   3087: iconst_0
    //   3088: iastore
    //   3089: dup
    //   3090: bipush #26
    //   3092: iconst_0
    //   3093: iastore
    //   3094: dup
    //   3095: bipush #27
    //   3097: ldc 268697664
    //   3099: iastore
    //   3100: dup
    //   3101: bipush #28
    //   3103: ldc 268435520
    //   3105: iastore
    //   3106: dup
    //   3107: bipush #29
    //   3109: ldc 268439552
    //   3111: iastore
    //   3112: dup
    //   3113: bipush #30
    //   3115: ldc 266304
    //   3117: iastore
    //   3118: dup
    //   3119: bipush #31
    //   3121: ldc 262144
    //   3123: iastore
    //   3124: dup
    //   3125: bipush #32
    //   3127: ldc 266304
    //   3129: iastore
    //   3130: dup
    //   3131: bipush #33
    //   3133: ldc 262144
    //   3135: iastore
    //   3136: dup
    //   3137: bipush #34
    //   3139: ldc 268701696
    //   3141: iastore
    //   3142: dup
    //   3143: bipush #35
    //   3145: sipush #4096
    //   3148: iastore
    //   3149: dup
    //   3150: bipush #36
    //   3152: bipush #64
    //   3154: iastore
    //   3155: dup
    //   3156: bipush #37
    //   3158: ldc 268697664
    //   3160: iastore
    //   3161: dup
    //   3162: bipush #38
    //   3164: sipush #4096
    //   3167: iastore
    //   3168: dup
    //   3169: bipush #39
    //   3171: ldc 266304
    //   3173: iastore
    //   3174: dup
    //   3175: bipush #40
    //   3177: ldc 268439552
    //   3179: iastore
    //   3180: dup
    //   3181: bipush #41
    //   3183: bipush #64
    //   3185: iastore
    //   3186: dup
    //   3187: bipush #42
    //   3189: ldc 268435520
    //   3191: iastore
    //   3192: dup
    //   3193: bipush #43
    //   3195: ldc 268697600
    //   3197: iastore
    //   3198: dup
    //   3199: bipush #44
    //   3201: ldc 268697664
    //   3203: iastore
    //   3204: dup
    //   3205: bipush #45
    //   3207: ldc 268435456
    //   3209: iastore
    //   3210: dup
    //   3211: bipush #46
    //   3213: ldc 262144
    //   3215: iastore
    //   3216: dup
    //   3217: bipush #47
    //   3219: ldc 268439616
    //   3221: iastore
    //   3222: dup
    //   3223: bipush #48
    //   3225: iconst_0
    //   3226: iastore
    //   3227: dup
    //   3228: bipush #49
    //   3230: ldc 268701760
    //   3232: iastore
    //   3233: dup
    //   3234: bipush #50
    //   3236: ldc 262208
    //   3238: iastore
    //   3239: dup
    //   3240: bipush #51
    //   3242: ldc 268435520
    //   3244: iastore
    //   3245: dup
    //   3246: bipush #52
    //   3248: ldc 268697600
    //   3250: iastore
    //   3251: dup
    //   3252: bipush #53
    //   3254: ldc 268439552
    //   3256: iastore
    //   3257: dup
    //   3258: bipush #54
    //   3260: ldc 268439616
    //   3262: iastore
    //   3263: dup
    //   3264: bipush #55
    //   3266: iconst_0
    //   3267: iastore
    //   3268: dup
    //   3269: bipush #56
    //   3271: ldc 268701760
    //   3273: iastore
    //   3274: dup
    //   3275: bipush #57
    //   3277: ldc 266240
    //   3279: iastore
    //   3280: dup
    //   3281: bipush #58
    //   3283: ldc 266240
    //   3285: iastore
    //   3286: dup
    //   3287: bipush #59
    //   3289: sipush #4160
    //   3292: iastore
    //   3293: dup
    //   3294: bipush #60
    //   3296: sipush #4160
    //   3299: iastore
    //   3300: dup
    //   3301: bipush #61
    //   3303: ldc 262208
    //   3305: iastore
    //   3306: dup
    //   3307: bipush #62
    //   3309: ldc 268435456
    //   3311: iastore
    //   3312: dup
    //   3313: bipush #63
    //   3315: ldc 268701696
    //   3317: iastore
    //   3318: astore #13
    //   3320: aload_3
    //   3321: arraylength
    //   3322: istore #14
    //   3324: iload #14
    //   3326: bipush #8
    //   3328: irem
    //   3329: ifeq -> 3353
    //   3332: new java/lang/Exception
    //   3335: dup
    //   3336: sipush #2609
    //   3339: sipush #2983
    //   3342: invokestatic a : (II)Ljava/lang/String;
    //   3345: invokespecial <init> : (Ljava/lang/String;)V
    //   3348: athrow
    //   3349: invokestatic a : (Ljava/lang/Throwable;)Ljava/lang/Throwable;
    //   3352: athrow
    //   3353: iconst_2
    //   3354: newarray int
    //   3356: astore #15
    //   3358: iload #14
    //   3360: newarray byte
    //   3362: astore #16
    //   3364: iload #14
    //   3366: bipush #8
    //   3368: idiv
    //   3369: istore #17
    //   3371: iconst_0
    //   3372: istore #18
    //   3374: iload #18
    //   3376: iload #17
    //   3378: if_icmpge -> 4292
    //   3381: iload #18
    //   3383: bipush #8
    //   3385: imul
    //   3386: istore #19
    //   3388: iconst_0
    //   3389: istore #20
    //   3391: iload #20
    //   3393: iconst_2
    //   3394: if_icmpge -> 3479
    //   3397: aload #15
    //   3399: iload #20
    //   3401: aload_3
    //   3402: iload #19
    //   3404: iload #20
    //   3406: iconst_4
    //   3407: imul
    //   3408: iadd
    //   3409: baload
    //   3410: sipush #255
    //   3413: iand
    //   3414: bipush #24
    //   3416: ishl
    //   3417: aload_3
    //   3418: iload #19
    //   3420: iload #20
    //   3422: iconst_4
    //   3423: imul
    //   3424: iadd
    //   3425: iconst_1
    //   3426: iadd
    //   3427: baload
    //   3428: sipush #255
    //   3431: iand
    //   3432: bipush #16
    //   3434: ishl
    //   3435: ior
    //   3436: aload_3
    //   3437: iload #19
    //   3439: iload #20
    //   3441: iconst_4
    //   3442: imul
    //   3443: iadd
    //   3444: iconst_2
    //   3445: iadd
    //   3446: baload
    //   3447: sipush #255
    //   3450: iand
    //   3451: bipush #8
    //   3453: ishl
    //   3454: ior
    //   3455: aload_3
    //   3456: iload #19
    //   3458: iload #20
    //   3460: iconst_4
    //   3461: imul
    //   3462: iadd
    //   3463: iconst_3
    //   3464: iadd
    //   3465: baload
    //   3466: sipush #255
    //   3469: iand
    //   3470: ior
    //   3471: iastore
    //   3472: iinc #20, 1
    //   3475: iload_2
    //   3476: ifeq -> 3391
    //   3479: iconst_0
    //   3480: istore #25
    //   3482: aload #15
    //   3484: iconst_0
    //   3485: iaload
    //   3486: istore #23
    //   3488: aload #15
    //   3490: iconst_1
    //   3491: iaload
    //   3492: istore #22
    //   3494: iload #23
    //   3496: iconst_4
    //   3497: iushr
    //   3498: iload #22
    //   3500: ixor
    //   3501: ldc 252645135
    //   3503: iand
    //   3504: istore #21
    //   3506: iload #22
    //   3508: iload #21
    //   3510: ixor
    //   3511: istore #22
    //   3513: iload #23
    //   3515: iload #21
    //   3517: iconst_4
    //   3518: ishl
    //   3519: ixor
    //   3520: istore #23
    //   3522: iload #23
    //   3524: bipush #16
    //   3526: iushr
    //   3527: iload #22
    //   3529: ixor
    //   3530: ldc 65535
    //   3532: iand
    //   3533: istore #21
    //   3535: iload #22
    //   3537: iload #21
    //   3539: ixor
    //   3540: istore #22
    //   3542: iload #23
    //   3544: iload #21
    //   3546: bipush #16
    //   3548: ishl
    //   3549: ixor
    //   3550: istore #23
    //   3552: iload #22
    //   3554: iconst_2
    //   3555: iushr
    //   3556: iload #23
    //   3558: ixor
    //   3559: ldc 858993459
    //   3561: iand
    //   3562: istore #21
    //   3564: iload #23
    //   3566: iload #21
    //   3568: ixor
    //   3569: istore #23
    //   3571: iload #22
    //   3573: iload #21
    //   3575: iconst_2
    //   3576: ishl
    //   3577: ixor
    //   3578: istore #22
    //   3580: iload #22
    //   3582: bipush #8
    //   3584: iushr
    //   3585: iload #23
    //   3587: ixor
    //   3588: ldc 16711935
    //   3590: iand
    //   3591: istore #21
    //   3593: iload #23
    //   3595: iload #21
    //   3597: ixor
    //   3598: istore #23
    //   3600: iload #22
    //   3602: iload #21
    //   3604: bipush #8
    //   3606: ishl
    //   3607: ixor
    //   3608: istore #22
    //   3610: iload #22
    //   3612: iconst_1
    //   3613: ishl
    //   3614: iload #22
    //   3616: bipush #31
    //   3618: iushr
    //   3619: iconst_1
    //   3620: iand
    //   3621: ior
    //   3622: istore #22
    //   3624: iload #23
    //   3626: iload #22
    //   3628: ixor
    //   3629: ldc -1431655766
    //   3631: iand
    //   3632: istore #21
    //   3634: iload #23
    //   3636: iload #21
    //   3638: ixor
    //   3639: istore #23
    //   3641: iload #22
    //   3643: iload #21
    //   3645: ixor
    //   3646: istore #22
    //   3648: iload #23
    //   3650: iconst_1
    //   3651: ishl
    //   3652: iload #23
    //   3654: bipush #31
    //   3656: iushr
    //   3657: iconst_1
    //   3658: iand
    //   3659: ior
    //   3660: istore #23
    //   3662: iconst_0
    //   3663: istore #24
    //   3665: iload #24
    //   3667: bipush #8
    //   3669: if_icmpge -> 4007
    //   3672: iload #22
    //   3674: bipush #28
    //   3676: ishl
    //   3677: iload #22
    //   3679: iconst_4
    //   3680: iushr
    //   3681: ior
    //   3682: istore #21
    //   3684: iload #21
    //   3686: aload #5
    //   3688: iload #25
    //   3690: iinc #25, 1
    //   3693: iaload
    //   3694: ixor
    //   3695: istore #21
    //   3697: aload #12
    //   3699: iload #21
    //   3701: bipush #63
    //   3703: iand
    //   3704: iaload
    //   3705: istore #20
    //   3707: iload #20
    //   3709: aload #10
    //   3711: iload #21
    //   3713: bipush #8
    //   3715: iushr
    //   3716: bipush #63
    //   3718: iand
    //   3719: iaload
    //   3720: ior
    //   3721: istore #20
    //   3723: iload #20
    //   3725: aload #8
    //   3727: iload #21
    //   3729: bipush #16
    //   3731: iushr
    //   3732: bipush #63
    //   3734: iand
    //   3735: iaload
    //   3736: ior
    //   3737: istore #20
    //   3739: iload #20
    //   3741: aload #6
    //   3743: iload #21
    //   3745: bipush #24
    //   3747: iushr
    //   3748: bipush #63
    //   3750: iand
    //   3751: iaload
    //   3752: ior
    //   3753: istore #20
    //   3755: iload #22
    //   3757: aload #5
    //   3759: iload #25
    //   3761: iinc #25, 1
    //   3764: iaload
    //   3765: ixor
    //   3766: istore #21
    //   3768: iload #20
    //   3770: aload #13
    //   3772: iload #21
    //   3774: bipush #63
    //   3776: iand
    //   3777: iaload
    //   3778: ior
    //   3779: istore #20
    //   3781: iload #20
    //   3783: aload #11
    //   3785: iload #21
    //   3787: bipush #8
    //   3789: iushr
    //   3790: bipush #63
    //   3792: iand
    //   3793: iaload
    //   3794: ior
    //   3795: istore #20
    //   3797: iload #20
    //   3799: aload #9
    //   3801: iload #21
    //   3803: bipush #16
    //   3805: iushr
    //   3806: bipush #63
    //   3808: iand
    //   3809: iaload
    //   3810: ior
    //   3811: istore #20
    //   3813: iload #20
    //   3815: aload #7
    //   3817: iload #21
    //   3819: bipush #24
    //   3821: iushr
    //   3822: bipush #63
    //   3824: iand
    //   3825: iaload
    //   3826: ior
    //   3827: istore #20
    //   3829: iload #23
    //   3831: iload #20
    //   3833: ixor
    //   3834: istore #23
    //   3836: iload #23
    //   3838: bipush #28
    //   3840: ishl
    //   3841: iload #23
    //   3843: iconst_4
    //   3844: iushr
    //   3845: ior
    //   3846: istore #21
    //   3848: iload #21
    //   3850: aload #5
    //   3852: iload #25
    //   3854: iinc #25, 1
    //   3857: iaload
    //   3858: ixor
    //   3859: istore #21
    //   3861: aload #12
    //   3863: iload #21
    //   3865: bipush #63
    //   3867: iand
    //   3868: iaload
    //   3869: istore #20
    //   3871: iload #20
    //   3873: aload #10
    //   3875: iload #21
    //   3877: bipush #8
    //   3879: iushr
    //   3880: bipush #63
    //   3882: iand
    //   3883: iaload
    //   3884: ior
    //   3885: istore #20
    //   3887: iload #20
    //   3889: aload #8
    //   3891: iload #21
    //   3893: bipush #16
    //   3895: iushr
    //   3896: bipush #63
    //   3898: iand
    //   3899: iaload
    //   3900: ior
    //   3901: istore #20
    //   3903: iload #20
    //   3905: aload #6
    //   3907: iload #21
    //   3909: bipush #24
    //   3911: iushr
    //   3912: bipush #63
    //   3914: iand
    //   3915: iaload
    //   3916: ior
    //   3917: istore #20
    //   3919: iload #23
    //   3921: aload #5
    //   3923: iload #25
    //   3925: iinc #25, 1
    //   3928: iaload
    //   3929: ixor
    //   3930: istore #21
    //   3932: iload #20
    //   3934: aload #13
    //   3936: iload #21
    //   3938: bipush #63
    //   3940: iand
    //   3941: iaload
    //   3942: ior
    //   3943: istore #20
    //   3945: iload #20
    //   3947: aload #11
    //   3949: iload #21
    //   3951: bipush #8
    //   3953: iushr
    //   3954: bipush #63
    //   3956: iand
    //   3957: iaload
    //   3958: ior
    //   3959: istore #20
    //   3961: iload #20
    //   3963: aload #9
    //   3965: iload #21
    //   3967: bipush #16
    //   3969: iushr
    //   3970: bipush #63
    //   3972: iand
    //   3973: iaload
    //   3974: ior
    //   3975: istore #20
    //   3977: iload #20
    //   3979: aload #7
    //   3981: iload #21
    //   3983: bipush #24
    //   3985: iushr
    //   3986: bipush #63
    //   3988: iand
    //   3989: iaload
    //   3990: ior
    //   3991: istore #20
    //   3993: iload #22
    //   3995: iload #20
    //   3997: ixor
    //   3998: istore #22
    //   4000: iinc #24, 1
    //   4003: iload_2
    //   4004: ifeq -> 3665
    //   4007: iload #22
    //   4009: bipush #31
    //   4011: ishl
    //   4012: iload #22
    //   4014: iconst_1
    //   4015: iushr
    //   4016: ior
    //   4017: istore #22
    //   4019: iload #23
    //   4021: iload #22
    //   4023: ixor
    //   4024: ldc -1431655766
    //   4026: iand
    //   4027: istore #21
    //   4029: iload #23
    //   4031: iload #21
    //   4033: ixor
    //   4034: istore #23
    //   4036: iload #22
    //   4038: iload #21
    //   4040: ixor
    //   4041: istore #22
    //   4043: iload #23
    //   4045: bipush #31
    //   4047: ishl
    //   4048: iload #23
    //   4050: iconst_1
    //   4051: iushr
    //   4052: ior
    //   4053: istore #23
    //   4055: iload #23
    //   4057: bipush #8
    //   4059: iushr
    //   4060: iload #22
    //   4062: ixor
    //   4063: ldc 16711935
    //   4065: iand
    //   4066: istore #21
    //   4068: iload #22
    //   4070: iload #21
    //   4072: ixor
    //   4073: istore #22
    //   4075: iload #23
    //   4077: iload #21
    //   4079: bipush #8
    //   4081: ishl
    //   4082: ixor
    //   4083: istore #23
    //   4085: iload #23
    //   4087: iconst_2
    //   4088: iushr
    //   4089: iload #22
    //   4091: ixor
    //   4092: ldc 858993459
    //   4094: iand
    //   4095: istore #21
    //   4097: iload #22
    //   4099: iload #21
    //   4101: ixor
    //   4102: istore #22
    //   4104: iload #23
    //   4106: iload #21
    //   4108: iconst_2
    //   4109: ishl
    //   4110: ixor
    //   4111: istore #23
    //   4113: iload #22
    //   4115: bipush #16
    //   4117: iushr
    //   4118: iload #23
    //   4120: ixor
    //   4121: ldc 65535
    //   4123: iand
    //   4124: istore #21
    //   4126: iload #23
    //   4128: iload #21
    //   4130: ixor
    //   4131: istore #23
    //   4133: iload #22
    //   4135: iload #21
    //   4137: bipush #16
    //   4139: ishl
    //   4140: ixor
    //   4141: istore #22
    //   4143: iload #22
    //   4145: iconst_4
    //   4146: iushr
    //   4147: iload #23
    //   4149: ixor
    //   4150: ldc 252645135
    //   4152: iand
    //   4153: istore #21
    //   4155: iload #23
    //   4157: iload #21
    //   4159: ixor
    //   4160: istore #23
    //   4162: iload #22
    //   4164: iload #21
    //   4166: iconst_4
    //   4167: ishl
    //   4168: ixor
    //   4169: istore #22
    //   4171: aload #15
    //   4173: iconst_0
    //   4174: iload #22
    //   4176: iastore
    //   4177: aload #15
    //   4179: iconst_1
    //   4180: iload #23
    //   4182: iastore
    //   4183: iload #18
    //   4185: bipush #8
    //   4187: imul
    //   4188: istore #26
    //   4190: iconst_0
    //   4191: istore #27
    //   4193: iload #27
    //   4195: iconst_2
    //   4196: if_icmpge -> 4285
    //   4199: aload #16
    //   4201: iload #26
    //   4203: iload #27
    //   4205: iconst_4
    //   4206: imul
    //   4207: iadd
    //   4208: aload #15
    //   4210: iload #27
    //   4212: iaload
    //   4213: bipush #24
    //   4215: iushr
    //   4216: i2b
    //   4217: bastore
    //   4218: aload #16
    //   4220: iload #26
    //   4222: iload #27
    //   4224: iconst_4
    //   4225: imul
    //   4226: iadd
    //   4227: iconst_1
    //   4228: iadd
    //   4229: aload #15
    //   4231: iload #27
    //   4233: iaload
    //   4234: bipush #16
    //   4236: iushr
    //   4237: i2b
    //   4238: bastore
    //   4239: aload #16
    //   4241: iload #26
    //   4243: iload #27
    //   4245: iconst_4
    //   4246: imul
    //   4247: iadd
    //   4248: iconst_2
    //   4249: iadd
    //   4250: aload #15
    //   4252: iload #27
    //   4254: iaload
    //   4255: bipush #8
    //   4257: iushr
    //   4258: i2b
    //   4259: bastore
    //   4260: aload #16
    //   4262: iload #26
    //   4264: iload #27
    //   4266: iconst_4
    //   4267: imul
    //   4268: iadd
    //   4269: iconst_3
    //   4270: iadd
    //   4271: aload #15
    //   4273: iload #27
    //   4275: iaload
    //   4276: i2b
    //   4277: bastore
    //   4278: iinc #27, 1
    //   4281: iload_2
    //   4282: ifeq -> 4193
    //   4285: iinc #18, 1
    //   4288: iload_2
    //   4289: ifeq -> 3374
    //   4292: aload #16
    //   4294: aload #16
    //   4296: arraylength
    //   4297: iconst_1
    //   4298: isub
    //   4299: baload
    //   4300: istore #18
    //   4302: aload #16
    //   4304: arraylength
    //   4305: iload #18
    //   4307: isub
    //   4308: newarray byte
    //   4310: astore #4
    //   4312: aload #16
    //   4314: arraylength
    //   4315: aload #4
    //   4317: arraylength
    //   4318: if_icmpge -> 4342
    //   4321: new java/lang/Exception
    //   4324: dup
    //   4325: sipush #2616
    //   4328: sipush #22889
    //   4331: invokestatic a : (II)Ljava/lang/String;
    //   4334: invokespecial <init> : (Ljava/lang/String;)V
    //   4337: athrow
    //   4338: invokestatic a : (Ljava/lang/Throwable;)Ljava/lang/Throwable;
    //   4341: athrow
    //   4342: iconst_0
    //   4343: istore #19
    //   4345: iload #19
    //   4347: aload #4
    //   4349: arraylength
    //   4350: if_icmpge -> 4370
    //   4353: aload #4
    //   4355: iload #19
    //   4357: aload #16
    //   4359: iload #19
    //   4361: baload
    //   4362: bastore
    //   4363: iinc #19, 1
    //   4366: iload_2
    //   4367: ifeq -> 4345
    //   4370: new java/math/BigInteger
    //   4373: dup
    //   4374: aload #4
    //   4376: invokespecial <init> : ([B)V
    //   4379: invokevirtual abs : ()Ljava/math/BigInteger;
    //   4382: putstatic burp/Zr3x.Zb : Ljava/lang/Object;
    //   4385: sipush #2599
    //   4388: sipush #22089
    //   4391: invokestatic a : (II)Ljava/lang/String;
    //   4394: iconst_1
    //   4395: ldc burp/Zm_w
    //   4397: invokevirtual getClassLoader : ()Ljava/lang/ClassLoader;
    //   4400: invokestatic forName : (Ljava/lang/String;ZLjava/lang/ClassLoader;)Ljava/lang/Class;
    //   4403: invokevirtual getDeclaredFields : ()[Ljava/lang/reflect/Field;
    //   4406: astore_3
    //   4407: aload_3
    //   4408: arraylength
    //   4409: istore #4
    //   4411: iconst_0
    //   4412: istore #5
    //   4414: iload #5
    //   4416: iload #4
    //   4418: if_icmpge -> 4555
    //   4421: aload_3
    //   4422: iload #5
    //   4424: aaload
    //   4425: astore #6
    //   4427: aload #6
    //   4429: invokevirtual getModifiers : ()I
    //   4432: invokestatic isStatic : (I)Z
    //   4435: ifne -> 4445
    //   4438: goto -> 4548
    //   4441: invokestatic a : (Ljava/lang/Throwable;)Ljava/lang/Throwable;
    //   4444: athrow
    //   4445: aload #6
    //   4447: invokevirtual getType : ()Ljava/lang/Class;
    //   4450: astore #7
    //   4452: aload #7
    //   4454: ifnull -> 4535
    //   4457: aload #7
    //   4459: invokevirtual isPrimitive : ()Z
    //   4462: ifne -> 4535
    //   4465: goto -> 4472
    //   4468: invokestatic a : (Ljava/lang/Throwable;)Ljava/lang/Throwable;
    //   4471: athrow
    //   4472: aload #7
    //   4474: invokevirtual getPackage : ()Ljava/lang/Package;
    //   4477: ifnull -> 4535
    //   4480: goto -> 4487
    //   4483: invokestatic a : (Ljava/lang/Throwable;)Ljava/lang/Throwable;
    //   4486: athrow
    //   4487: aload #7
    //   4489: invokevirtual getPackage : ()Ljava/lang/Package;
    //   4492: invokevirtual getName : ()Ljava/lang/String;
    //   4495: ifnull -> 4535
    //   4498: goto -> 4505
    //   4501: invokestatic a : (Ljava/lang/Throwable;)Ljava/lang/Throwable;
    //   4504: athrow
    //   4505: aload #7
    //   4507: invokevirtual getPackage : ()Ljava/lang/Package;
    //   4510: invokevirtual getName : ()Ljava/lang/String;
    //   4513: sipush #2596
    //   4516: sipush #-6631
    //   4519: invokestatic a : (II)Ljava/lang/String;
    //   4522: invokevirtual startsWith : (Ljava/lang/String;)Z
    //   4525: ifne -> 4535
    //   4528: goto -> 4535
    //   4531: invokestatic a : (Ljava/lang/Throwable;)Ljava/lang/Throwable;
    //   4534: athrow
    //   4535: aload #6
    //   4537: iconst_1
    //   4538: invokevirtual setAccessible : (Z)V
    //   4541: aload #6
    //   4543: aconst_null
    //   4544: invokevirtual get : (Ljava/lang/Object;)Ljava/lang/Object;
    //   4547: pop
    //   4548: iinc #5, 1
    //   4551: iload_2
    //   4552: ifeq -> 4414
    //   4555: sipush #2620
    //   4558: sipush #-6209
    //   4561: invokestatic a : (II)Ljava/lang/String;
    //   4564: invokestatic forName : (Ljava/lang/String;)Ljava/lang/Class;
    //   4567: invokevirtual getDeclaredMethods : ()[Ljava/lang/reflect/Method;
    //   4570: astore_3
    //   4571: aload_3
    //   4572: arraylength
    //   4573: istore #4
    //   4575: iconst_0
    //   4576: istore #5
    //   4578: iload #5
    //   4580: iload #4
    //   4582: if_icmpge -> 4693
    //   4585: aload_3
    //   4586: iload #5
    //   4588: aaload
    //   4589: astore #6
    //   4591: aload #6
    //   4593: invokevirtual getParameterTypes : ()[Ljava/lang/Class;
    //   4596: pop
    //   4597: aload #6
    //   4599: invokevirtual getModifiers : ()I
    //   4602: invokestatic isStatic : (I)Z
    //   4605: ifeq -> 4679
    //   4608: aload #6
    //   4610: invokevirtual getParameterTypes : ()[Ljava/lang/Class;
    //   4613: arraylength
    //   4614: iconst_2
    //   4615: if_icmpne -> 4679
    //   4618: goto -> 4625
    //   4621: invokestatic a : (Ljava/lang/Throwable;)Ljava/lang/Throwable;
    //   4624: athrow
    //   4625: aload #6
    //   4627: invokevirtual getReturnType : ()Ljava/lang/Class;
    //   4630: getstatic java/lang/Boolean.TYPE : Ljava/lang/Class;
    //   4633: if_acmpne -> 4679
    //   4636: goto -> 4643
    //   4639: invokestatic a : (Ljava/lang/Throwable;)Ljava/lang/Throwable;
    //   4642: athrow
    //   4643: aload #6
    //   4645: iconst_1
    //   4646: invokevirtual setAccessible : (Z)V
    //   4649: aload #6
    //   4651: aconst_null
    //   4652: iconst_2
    //   4653: anewarray java/lang/Object
    //   4656: dup
    //   4657: iconst_0
    //   4658: aload_0
    //   4659: aastore
    //   4660: dup
    //   4661: iconst_1
    //   4662: aload_1
    //   4663: aastore
    //   4664: invokevirtual invoke : (Ljava/lang/Object;[Ljava/lang/Object;)Ljava/lang/Object;
    //   4667: pop
    //   4668: iload_2
    //   4669: ifeq -> 4693
    //   4672: goto -> 4679
    //   4675: invokestatic a : (Ljava/lang/Throwable;)Ljava/lang/Throwable;
    //   4678: athrow
    //   4679: iinc #5, 1
    //   4682: iload_2
    //   4683: ifeq -> 4578
    //   4686: goto -> 4693
    //   4689: invokestatic a : (Ljava/lang/Throwable;)Ljava/lang/Throwable;
    //   4692: athrow
    //   4693: sipush #2602
    //   4696: sipush #-19713
    //   4699: invokestatic a : (II)Ljava/lang/String;
    //   4702: iconst_1
    //   4703: ldc burp/Zgta
    //   4705: invokevirtual getClassLoader : ()Ljava/lang/ClassLoader;
    //   4708: invokestatic forName : (Ljava/lang/String;ZLjava/lang/ClassLoader;)Ljava/lang/Class;
    //   4711: invokevirtual getDeclaredFields : ()[Ljava/lang/reflect/Field;
    //   4714: astore_3
    //   4715: aload_3
    //   4716: arraylength
    //   4717: istore #4
    //   4719: iconst_0
    //   4720: istore #5
    //   4722: iload #5
    //   4724: iload #4
    //   4726: if_icmpge -> 4863
    //   4729: aload_3
    //   4730: iload #5
    //   4732: aaload
    //   4733: astore #6
    //   4735: aload #6
    //   4737: invokevirtual getModifiers : ()I
    //   4740: invokestatic isStatic : (I)Z
    //   4743: ifne -> 4753
    //   4746: goto -> 4856
    //   4749: invokestatic a : (Ljava/lang/Throwable;)Ljava/lang/Throwable;
    //   4752: athrow
    //   4753: aload #6
    //   4755: invokevirtual getType : ()Ljava/lang/Class;
    //   4758: astore #7
    //   4760: aload #7
    //   4762: ifnull -> 4843
    //   4765: aload #7
    //   4767: invokevirtual isPrimitive : ()Z
    //   4770: ifne -> 4843
    //   4773: goto -> 4780
    //   4776: invokestatic a : (Ljava/lang/Throwable;)Ljava/lang/Throwable;
    //   4779: athrow
    //   4780: aload #7
    //   4782: invokevirtual getPackage : ()Ljava/lang/Package;
    //   4785: ifnull -> 4843
    //   4788: goto -> 4795
    //   4791: invokestatic a : (Ljava/lang/Throwable;)Ljava/lang/Throwable;
    //   4794: athrow
    //   4795: aload #7
    //   4797: invokevirtual getPackage : ()Ljava/lang/Package;
    //   4800: invokevirtual getName : ()Ljava/lang/String;
    //   4803: ifnull -> 4843
    //   4806: goto -> 4813
    //   4809: invokestatic a : (Ljava/lang/Throwable;)Ljava/lang/Throwable;
    //   4812: athrow
    //   4813: aload #7
    //   4815: invokevirtual getPackage : ()Ljava/lang/Package;
    //   4818: invokevirtual getName : ()Ljava/lang/String;
    //   4821: sipush #2614
    //   4824: sipush #-6687
    //   4827: invokestatic a : (II)Ljava/lang/String;
    //   4830: invokevirtual startsWith : (Ljava/lang/String;)Z
    //   4833: ifne -> 4843
    //   4836: goto -> 4843
    //   4839: invokestatic a : (Ljava/lang/Throwable;)Ljava/lang/Throwable;
    //   4842: athrow
    //   4843: aload #6
    //   4845: iconst_1
    //   4846: invokevirtual setAccessible : (Z)V
    //   4849: aload #6
    //   4851: aconst_null
    //   4852: invokevirtual get : (Ljava/lang/Object;)Ljava/lang/Object;
    //   4855: pop
    //   4856: iinc #5, 1
    //   4859: iload_2
    //   4860: ifeq -> 4722
    //   4863: sipush #2619
    //   4866: sipush #-22336
    //   4869: invokestatic a : (II)Ljava/lang/String;
    //   4872: invokestatic forName : (Ljava/lang/String;)Ljava/lang/Class;
    //   4875: invokevirtual getDeclaredMethods : ()[Ljava/lang/reflect/Method;
    //   4878: astore_3
    //   4879: aload_3
    //   4880: arraylength
    //   4881: istore #4
    //   4883: iconst_0
    //   4884: istore #5
    //   4886: iload #5
    //   4888: iload #4
    //   4890: if_icmpge -> 5022
    //   4893: aload_3
    //   4894: iload #5
    //   4896: aaload
    //   4897: astore #6
    //   4899: aload #6
    //   4901: invokevirtual getParameterTypes : ()[Ljava/lang/Class;
    //   4904: pop
    //   4905: aload #6
    //   4907: invokevirtual getModifiers : ()I
    //   4910: invokestatic isStatic : (I)Z
    //   4913: ifeq -> 5008
    //   4916: aload #6
    //   4918: invokevirtual getParameterTypes : ()[Ljava/lang/Class;
    //   4921: arraylength
    //   4922: iconst_2
    //   4923: if_icmpne -> 5008
    //   4926: goto -> 4933
    //   4929: invokestatic a : (Ljava/lang/Throwable;)Ljava/lang/Throwable;
    //   4932: athrow
    //   4933: aload #6
    //   4935: invokevirtual getReturnType : ()Ljava/lang/Class;
    //   4938: getstatic java/lang/Void.TYPE : Ljava/lang/Class;
    //   4941: invokevirtual equals : (Ljava/lang/Object;)Z
    //   4944: ifeq -> 5008
    //   4947: goto -> 4954
    //   4950: invokestatic a : (Ljava/lang/Throwable;)Ljava/lang/Throwable;
    //   4953: athrow
    //   4954: aload #6
    //   4956: iconst_1
    //   4957: invokevirtual setAccessible : (Z)V
    //   4960: aload #6
    //   4962: aconst_null
    //   4963: iconst_2
    //   4964: anewarray java/lang/Object
    //   4967: dup
    //   4968: iconst_0
    //   4969: aload_0
    //   4970: aastore
    //   4971: dup
    //   4972: iconst_1
    //   4973: aload_1
    //   4974: ifnonnull -> 4992
    //   4977: goto -> 4984
    //   4980: invokestatic a : (Ljava/lang/Throwable;)Ljava/lang/Throwable;
    //   4983: athrow
    //   4984: aload_1
    //   4985: goto -> 4999
    //   4988: invokestatic a : (Ljava/lang/Throwable;)Ljava/lang/Throwable;
    //   4991: athrow
    //   4992: aload_1
    //   4993: checkcast [B
    //   4996: invokevirtual clone : ()Ljava/lang/Object;
    //   4999: aastore
    //   5000: invokevirtual invoke : (Ljava/lang/Object;[Ljava/lang/Object;)Ljava/lang/Object;
    //   5003: pop
    //   5004: iload_2
    //   5005: ifeq -> 5022
    //   5008: iinc #5, 1
    //   5011: iload_2
    //   5012: ifeq -> 4886
    //   5015: goto -> 5022
    //   5018: invokestatic a : (Ljava/lang/Throwable;)Ljava/lang/Throwable;
    //   5021: athrow
    //   5022: new java/io/ByteArrayOutputStream
    //   5025: dup
    //   5026: invokespecial <init> : ()V
    //   5029: astore_3
    //   5030: getstatic burp/Zs59.Zc : Ljava/lang/String;
    //   5033: astore #4
    //   5035: iconst_0
    //   5036: istore #5
    //   5038: iload #5
    //   5040: aload #4
    //   5042: invokevirtual length : ()I
    //   5045: if_icmpge -> 5075
    //   5048: aload_3
    //   5049: aload #4
    //   5051: iload #5
    //   5053: iload #5
    //   5055: iconst_2
    //   5056: iadd
    //   5057: invokevirtual substring : (II)Ljava/lang/String;
    //   5060: bipush #16
    //   5062: invokestatic parseInt : (Ljava/lang/String;I)I
    //   5065: invokevirtual write : (I)V
    //   5068: iinc #5, 2
    //   5071: iload_2
    //   5072: ifeq -> 5038
    //   5075: aload_3
    //   5076: invokevirtual toByteArray : ()[B
    //   5079: astore #5
    //   5081: getstatic burp/Zsej.ZT : Ljava/lang/Object;
    //   5084: checkcast java/math/BigInteger
    //   5087: invokevirtual toByteArray : ()[B
    //   5090: astore #6
    //   5092: sipush #256
    //   5095: newarray byte
    //   5097: astore #8
    //   5099: sipush #256
    //   5102: newarray int
    //   5104: astore #9
    //   5106: sipush #256
    //   5109: newarray int
    //   5111: astore #10
    //   5113: sipush #256
    //   5116: newarray int
    //   5118: astore #11
    //   5120: sipush #256
    //   5123: newarray int
    //   5125: astore #12
    //   5127: bipush #10
    //   5129: newarray int
    //   5131: astore #13
    //   5133: sipush #283
    //   5136: istore #14
    //   5138: iconst_0
    //   5139: istore #16
    //   5141: iload #16
    //   5143: sipush #256
    //   5146: if_icmpge -> 5380
    //   5149: sipush #2597
    //   5152: sipush #31245
    //   5155: invokestatic a : (II)Ljava/lang/String;
    //   5158: iload #16
    //   5160: iconst_1
    //   5161: iushr
    //   5162: invokevirtual charAt : (I)C
    //   5165: istore #25
    //   5167: iload #16
    //   5169: iconst_1
    //   5170: iand
    //   5171: ifne -> 5186
    //   5174: iload #25
    //   5176: bipush #8
    //   5178: iushr
    //   5179: goto -> 5188
    //   5182: invokestatic a : (Ljava/lang/Throwable;)Ljava/lang/Throwable;
    //   5185: athrow
    //   5186: iload #25
    //   5188: i2b
    //   5189: sipush #255
    //   5192: iand
    //   5193: istore #15
    //   5195: iload #16
    //   5197: iconst_1
    //   5198: ishl
    //   5199: istore #17
    //   5201: iload #17
    //   5203: sipush #256
    //   5206: if_icmplt -> 5216
    //   5209: iload #17
    //   5211: iload #14
    //   5213: ixor
    //   5214: istore #17
    //   5216: iload #17
    //   5218: iconst_1
    //   5219: ishl
    //   5220: istore #18
    //   5222: iload #18
    //   5224: sipush #256
    //   5227: if_icmplt -> 5237
    //   5230: iload #18
    //   5232: iload #14
    //   5234: ixor
    //   5235: istore #18
    //   5237: iload #18
    //   5239: iconst_1
    //   5240: ishl
    //   5241: istore #19
    //   5243: iload #19
    //   5245: sipush #256
    //   5248: if_icmplt -> 5258
    //   5251: iload #19
    //   5253: iload #14
    //   5255: ixor
    //   5256: istore #19
    //   5258: iload #19
    //   5260: iload #16
    //   5262: ixor
    //   5263: istore #20
    //   5265: iload #20
    //   5267: iload #17
    //   5269: ixor
    //   5270: istore #21
    //   5272: iload #20
    //   5274: iload #18
    //   5276: ixor
    //   5277: istore #22
    //   5279: iload #19
    //   5281: iload #18
    //   5283: ixor
    //   5284: iload #17
    //   5286: ixor
    //   5287: istore #23
    //   5289: aload #8
    //   5291: iload #16
    //   5293: iload #15
    //   5295: i2b
    //   5296: bastore
    //   5297: aload #9
    //   5299: iload #15
    //   5301: iload #23
    //   5303: bipush #24
    //   5305: ishl
    //   5306: iload #20
    //   5308: bipush #16
    //   5310: ishl
    //   5311: ior
    //   5312: iload #22
    //   5314: bipush #8
    //   5316: ishl
    //   5317: ior
    //   5318: iload #21
    //   5320: ior
    //   5321: dup
    //   5322: istore #24
    //   5324: iastore
    //   5325: aload #10
    //   5327: iload #15
    //   5329: iload #24
    //   5331: bipush #8
    //   5333: iushr
    //   5334: iload #24
    //   5336: bipush #24
    //   5338: ishl
    //   5339: ior
    //   5340: iastore
    //   5341: aload #11
    //   5343: iload #15
    //   5345: iload #24
    //   5347: bipush #16
    //   5349: iushr
    //   5350: iload #24
    //   5352: bipush #16
    //   5354: ishl
    //   5355: ior
    //   5356: iastore
    //   5357: aload #12
    //   5359: iload #15
    //   5361: iload #24
    //   5363: bipush #24
    //   5365: iushr
    //   5366: iload #24
    //   5368: bipush #8
    //   5370: ishl
    //   5371: ior
    //   5372: iastore
    //   5373: iinc #16, 1
    //   5376: iload_2
    //   5377: ifeq -> 5141
    //   5380: iconst_1
    //   5381: istore #25
    //   5383: aload #13
    //   5385: iconst_0
    //   5386: iload #25
    //   5388: bipush #24
    //   5390: ishl
    //   5391: iastore
    //   5392: iconst_1
    //   5393: istore #26
    //   5395: iload #26
    //   5397: bipush #10
    //   5399: if_icmpge -> 5440
    //   5402: iload #25
    //   5404: iconst_1
    //   5405: ishl
    //   5406: istore #25
    //   5408: iload #25
    //   5410: sipush #256
    //   5413: if_icmplt -> 5423
    //   5416: iload #25
    //   5418: iload #14
    //   5420: ixor
    //   5421: istore #25
    //   5423: aload #13
    //   5425: iload #26
    //   5427: iload #25
    //   5429: bipush #24
    //   5431: ishl
    //   5432: iastore
    //   5433: iinc #26, 1
    //   5436: iload_2
    //   5437: ifeq -> 5395
    //   5440: iconst_4
    //   5441: istore #26
    //   5443: iload #26
    //   5445: bipush #6
    //   5447: iadd
    //   5448: istore #27
    //   5450: iconst_4
    //   5451: iload #27
    //   5453: iconst_1
    //   5454: iadd
    //   5455: imul
    //   5456: istore #28
    //   5458: iload #28
    //   5460: newarray int
    //   5462: astore #29
    //   5464: iload #28
    //   5466: newarray int
    //   5468: astore #30
    //   5470: iconst_0
    //   5471: istore #25
    //   5473: iconst_0
    //   5474: istore #32
    //   5476: iconst_0
    //   5477: istore #33
    //   5479: iload #32
    //   5481: iload #26
    //   5483: if_icmpge -> 5551
    //   5486: aload #29
    //   5488: iload #32
    //   5490: aload #5
    //   5492: iload #33
    //   5494: baload
    //   5495: bipush #24
    //   5497: ishl
    //   5498: aload #5
    //   5500: iload #33
    //   5502: iconst_1
    //   5503: iadd
    //   5504: baload
    //   5505: sipush #255
    //   5508: iand
    //   5509: bipush #16
    //   5511: ishl
    //   5512: ior
    //   5513: aload #5
    //   5515: iload #33
    //   5517: iconst_2
    //   5518: iadd
    //   5519: baload
    //   5520: sipush #255
    //   5523: iand
    //   5524: bipush #8
    //   5526: ishl
    //   5527: ior
    //   5528: aload #5
    //   5530: iload #33
    //   5532: iconst_3
    //   5533: iadd
    //   5534: baload
    //   5535: sipush #255
    //   5538: iand
    //   5539: ior
    //   5540: iastore
    //   5541: iinc #32, 1
    //   5544: iinc #33, 4
    //   5547: iload_2
    //   5548: ifeq -> 5479
    //   5551: iload #26
    //   5553: istore #32
    //   5555: iconst_0
    //   5556: istore #33
    //   5558: iload #32
    //   5560: iload #28
    //   5562: if_icmpge -> 5689
    //   5565: aload #29
    //   5567: iload #32
    //   5569: iconst_1
    //   5570: isub
    //   5571: iaload
    //   5572: istore #31
    //   5574: iload #33
    //   5576: ifne -> 5663
    //   5579: iload #26
    //   5581: istore #33
    //   5583: aload #8
    //   5585: iload #31
    //   5587: bipush #16
    //   5589: iushr
    //   5590: sipush #255
    //   5593: iand
    //   5594: baload
    //   5595: bipush #24
    //   5597: ishl
    //   5598: aload #8
    //   5600: iload #31
    //   5602: bipush #8
    //   5604: iushr
    //   5605: sipush #255
    //   5608: iand
    //   5609: baload
    //   5610: sipush #255
    //   5613: iand
    //   5614: bipush #16
    //   5616: ishl
    //   5617: ior
    //   5618: aload #8
    //   5620: iload #31
    //   5622: sipush #255
    //   5625: iand
    //   5626: baload
    //   5627: sipush #255
    //   5630: iand
    //   5631: bipush #8
    //   5633: ishl
    //   5634: ior
    //   5635: aload #8
    //   5637: iload #31
    //   5639: bipush #24
    //   5641: iushr
    //   5642: baload
    //   5643: sipush #255
    //   5646: iand
    //   5647: ior
    //   5648: istore #31
    //   5650: iload #31
    //   5652: aload #13
    //   5654: iload #25
    //   5656: iinc #25, 1
    //   5659: iaload
    //   5660: ixor
    //   5661: istore #31
    //   5663: aload #29
    //   5665: iload #32
    //   5667: aload #29
    //   5669: iload #32
    //   5671: iload #26
    //   5673: isub
    //   5674: iaload
    //   5675: iload #31
    //   5677: ixor
    //   5678: iastore
    //   5679: iinc #32, 1
    //   5682: iinc #33, -1
    //   5685: iload_2
    //   5686: ifeq -> 5558
    //   5689: iconst_0
    //   5690: istore #32
    //   5692: iconst_4
    //   5693: iload #27
    //   5695: imul
    //   5696: istore #33
    //   5698: aload #30
    //   5700: iload #32
    //   5702: aload #29
    //   5704: iload #33
    //   5706: iaload
    //   5707: iastore
    //   5708: aload #30
    //   5710: iload #32
    //   5712: iconst_1
    //   5713: iadd
    //   5714: aload #29
    //   5716: iload #33
    //   5718: iconst_1
    //   5719: iadd
    //   5720: iaload
    //   5721: iastore
    //   5722: aload #30
    //   5724: iload #32
    //   5726: iconst_2
    //   5727: iadd
    //   5728: aload #29
    //   5730: iload #33
    //   5732: iconst_2
    //   5733: iadd
    //   5734: iaload
    //   5735: iastore
    //   5736: aload #30
    //   5738: iload #32
    //   5740: iconst_3
    //   5741: iadd
    //   5742: aload #29
    //   5744: iload #33
    //   5746: iconst_3
    //   5747: iadd
    //   5748: iaload
    //   5749: iastore
    //   5750: iinc #32, 4
    //   5753: iinc #33, -4
    //   5756: iconst_1
    //   5757: istore #35
    //   5759: iload #35
    //   5761: iload #27
    //   5763: if_icmpge -> 6127
    //   5766: aload #29
    //   5768: iload #33
    //   5770: iaload
    //   5771: istore #34
    //   5773: aload #30
    //   5775: iload #32
    //   5777: aload #9
    //   5779: aload #8
    //   5781: iload #34
    //   5783: bipush #24
    //   5785: iushr
    //   5786: baload
    //   5787: sipush #255
    //   5790: iand
    //   5791: iaload
    //   5792: aload #10
    //   5794: aload #8
    //   5796: iload #34
    //   5798: bipush #16
    //   5800: iushr
    //   5801: sipush #255
    //   5804: iand
    //   5805: baload
    //   5806: sipush #255
    //   5809: iand
    //   5810: iaload
    //   5811: ixor
    //   5812: aload #11
    //   5814: aload #8
    //   5816: iload #34
    //   5818: bipush #8
    //   5820: iushr
    //   5821: sipush #255
    //   5824: iand
    //   5825: baload
    //   5826: sipush #255
    //   5829: iand
    //   5830: iaload
    //   5831: ixor
    //   5832: aload #12
    //   5834: aload #8
    //   5836: iload #34
    //   5838: sipush #255
    //   5841: iand
    //   5842: baload
    //   5843: sipush #255
    //   5846: iand
    //   5847: iaload
    //   5848: ixor
    //   5849: iastore
    //   5850: aload #29
    //   5852: iload #33
    //   5854: iconst_1
    //   5855: iadd
    //   5856: iaload
    //   5857: istore #34
    //   5859: aload #30
    //   5861: iload #32
    //   5863: iconst_1
    //   5864: iadd
    //   5865: aload #9
    //   5867: aload #8
    //   5869: iload #34
    //   5871: bipush #24
    //   5873: iushr
    //   5874: baload
    //   5875: sipush #255
    //   5878: iand
    //   5879: iaload
    //   5880: aload #10
    //   5882: aload #8
    //   5884: iload #34
    //   5886: bipush #16
    //   5888: iushr
    //   5889: sipush #255
    //   5892: iand
    //   5893: baload
    //   5894: sipush #255
    //   5897: iand
    //   5898: iaload
    //   5899: ixor
    //   5900: aload #11
    //   5902: aload #8
    //   5904: iload #34
    //   5906: bipush #8
    //   5908: iushr
    //   5909: sipush #255
    //   5912: iand
    //   5913: baload
    //   5914: sipush #255
    //   5917: iand
    //   5918: iaload
    //   5919: ixor
    //   5920: aload #12
    //   5922: aload #8
    //   5924: iload #34
    //   5926: sipush #255
    //   5929: iand
    //   5930: baload
    //   5931: sipush #255
    //   5934: iand
    //   5935: iaload
    //   5936: ixor
    //   5937: iastore
    //   5938: aload #29
    //   5940: iload #33
    //   5942: iconst_2
    //   5943: iadd
    //   5944: iaload
    //   5945: istore #34
    //   5947: aload #30
    //   5949: iload #32
    //   5951: iconst_2
    //   5952: iadd
    //   5953: aload #9
    //   5955: aload #8
    //   5957: iload #34
    //   5959: bipush #24
    //   5961: iushr
    //   5962: baload
    //   5963: sipush #255
    //   5966: iand
    //   5967: iaload
    //   5968: aload #10
    //   5970: aload #8
    //   5972: iload #34
    //   5974: bipush #16
    //   5976: iushr
    //   5977: sipush #255
    //   5980: iand
    //   5981: baload
    //   5982: sipush #255
    //   5985: iand
    //   5986: iaload
    //   5987: ixor
    //   5988: aload #11
    //   5990: aload #8
    //   5992: iload #34
    //   5994: bipush #8
    //   5996: iushr
    //   5997: sipush #255
    //   6000: iand
    //   6001: baload
    //   6002: sipush #255
    //   6005: iand
    //   6006: iaload
    //   6007: ixor
    //   6008: aload #12
    //   6010: aload #8
    //   6012: iload #34
    //   6014: sipush #255
    //   6017: iand
    //   6018: baload
    //   6019: sipush #255
    //   6022: iand
    //   6023: iaload
    //   6024: ixor
    //   6025: iastore
    //   6026: aload #29
    //   6028: iload #33
    //   6030: iconst_3
    //   6031: iadd
    //   6032: iaload
    //   6033: istore #34
    //   6035: aload #30
    //   6037: iload #32
    //   6039: iconst_3
    //   6040: iadd
    //   6041: aload #9
    //   6043: aload #8
    //   6045: iload #34
    //   6047: bipush #24
    //   6049: iushr
    //   6050: baload
    //   6051: sipush #255
    //   6054: iand
    //   6055: iaload
    //   6056: aload #10
    //   6058: aload #8
    //   6060: iload #34
    //   6062: bipush #16
    //   6064: iushr
    //   6065: sipush #255
    //   6068: iand
    //   6069: baload
    //   6070: sipush #255
    //   6073: iand
    //   6074: iaload
    //   6075: ixor
    //   6076: aload #11
    //   6078: aload #8
    //   6080: iload #34
    //   6082: bipush #8
    //   6084: iushr
    //   6085: sipush #255
    //   6088: iand
    //   6089: baload
    //   6090: sipush #255
    //   6093: iand
    //   6094: iaload
    //   6095: ixor
    //   6096: aload #12
    //   6098: aload #8
    //   6100: iload #34
    //   6102: sipush #255
    //   6105: iand
    //   6106: baload
    //   6107: sipush #255
    //   6110: iand
    //   6111: iaload
    //   6112: ixor
    //   6113: iastore
    //   6114: iinc #32, 4
    //   6117: iinc #33, -4
    //   6120: iinc #35, 1
    //   6123: iload_2
    //   6124: ifeq -> 5759
    //   6127: aload #30
    //   6129: iload #32
    //   6131: aload #29
    //   6133: iload #33
    //   6135: iaload
    //   6136: iastore
    //   6137: aload #30
    //   6139: iload #32
    //   6141: iconst_1
    //   6142: iadd
    //   6143: aload #29
    //   6145: iload #33
    //   6147: iconst_1
    //   6148: iadd
    //   6149: iaload
    //   6150: iastore
    //   6151: aload #30
    //   6153: iload #32
    //   6155: iconst_2
    //   6156: iadd
    //   6157: aload #29
    //   6159: iload #33
    //   6161: iconst_2
    //   6162: iadd
    //   6163: iaload
    //   6164: iastore
    //   6165: aload #30
    //   6167: iload #32
    //   6169: iconst_3
    //   6170: iadd
    //   6171: aload #29
    //   6173: iload #33
    //   6175: iconst_3
    //   6176: iadd
    //   6177: iaload
    //   6178: iastore
    //   6179: iconst_0
    //   6180: newarray byte
    //   6182: astore #35
    //   6184: aload #6
    //   6186: arraylength
    //   6187: bipush #16
    //   6189: irem
    //   6190: ifeq -> 6214
    //   6193: new java/lang/Exception
    //   6196: dup
    //   6197: sipush #2616
    //   6200: sipush #22889
    //   6203: invokestatic a : (II)Ljava/lang/String;
    //   6206: invokespecial <init> : (Ljava/lang/String;)V
    //   6209: athrow
    //   6210: invokestatic a : (Ljava/lang/Throwable;)Ljava/lang/Throwable;
    //   6213: athrow
    //   6214: bipush #10
    //   6216: istore #36
    //   6218: sipush #2592
    //   6221: sipush #256
    //   6224: newarray byte
    //   6226: astore #37
    //   6228: sipush #19792
    //   6231: sipush #256
    //   6234: newarray int
    //   6236: astore #38
    //   6238: sipush #256
    //   6241: newarray int
    //   6243: astore #39
    //   6245: sipush #256
    //   6248: newarray int
    //   6250: astore #40
    //   6252: sipush #256
    //   6255: newarray int
    //   6257: astore #41
    //   6259: sipush #283
    //   6262: istore #14
    //   6264: invokestatic a : (II)Ljava/lang/String;
    //   6267: astore #42
    //   6269: iconst_0
    //   6270: istore #16
    //   6272: iload #16
    //   6274: sipush #256
    //   6277: if_icmpge -> 6504
    //   6280: aload #42
    //   6282: iload #16
    //   6284: iconst_1
    //   6285: iushr
    //   6286: invokevirtual charAt : (I)C
    //   6289: istore #43
    //   6291: iload #16
    //   6293: iconst_1
    //   6294: iand
    //   6295: ifne -> 6310
    //   6298: iload #43
    //   6300: bipush #8
    //   6302: iushr
    //   6303: goto -> 6312
    //   6306: invokestatic a : (Ljava/lang/Throwable;)Ljava/lang/Throwable;
    //   6309: athrow
    //   6310: iload #43
    //   6312: i2b
    //   6313: sipush #255
    //   6316: iand
    //   6317: istore #15
    //   6319: iload #16
    //   6321: iconst_1
    //   6322: ishl
    //   6323: istore #17
    //   6325: iload #17
    //   6327: sipush #256
    //   6330: if_icmplt -> 6340
    //   6333: iload #17
    //   6335: iload #14
    //   6337: ixor
    //   6338: istore #17
    //   6340: iload #17
    //   6342: iconst_1
    //   6343: ishl
    //   6344: istore #18
    //   6346: iload #18
    //   6348: sipush #256
    //   6351: if_icmplt -> 6361
    //   6354: iload #18
    //   6356: iload #14
    //   6358: ixor
    //   6359: istore #18
    //   6361: iload #18
    //   6363: iconst_1
    //   6364: ishl
    //   6365: istore #19
    //   6367: iload #19
    //   6369: sipush #256
    //   6372: if_icmplt -> 6382
    //   6375: iload #19
    //   6377: iload #14
    //   6379: ixor
    //   6380: istore #19
    //   6382: iload #19
    //   6384: iload #16
    //   6386: ixor
    //   6387: istore #20
    //   6389: iload #20
    //   6391: iload #17
    //   6393: ixor
    //   6394: istore #21
    //   6396: iload #20
    //   6398: iload #18
    //   6400: ixor
    //   6401: istore #22
    //   6403: iload #19
    //   6405: iload #18
    //   6407: ixor
    //   6408: iload #17
    //   6410: ixor
    //   6411: istore #23
    //   6413: aload #37
    //   6415: iload #15
    //   6417: iload #16
    //   6419: i2b
    //   6420: bastore
    //   6421: aload #38
    //   6423: iload #15
    //   6425: iload #23
    //   6427: bipush #24
    //   6429: ishl
    //   6430: iload #20
    //   6432: bipush #16
    //   6434: ishl
    //   6435: ior
    //   6436: iload #22
    //   6438: bipush #8
    //   6440: ishl
    //   6441: ior
    //   6442: iload #21
    //   6444: ior
    //   6445: dup
    //   6446: istore #24
    //   6448: iastore
    //   6449: aload #39
    //   6451: iload #15
    //   6453: iload #24
    //   6455: bipush #8
    //   6457: iushr
    //   6458: iload #24
    //   6460: bipush #24
    //   6462: ishl
    //   6463: ior
    //   6464: iastore
    //   6465: aload #40
    //   6467: iload #15
    //   6469: iload #24
    //   6471: bipush #16
    //   6473: iushr
    //   6474: iload #24
    //   6476: bipush #16
    //   6478: ishl
    //   6479: ior
    //   6480: iastore
    //   6481: aload #41
    //   6483: iload #15
    //   6485: iload #24
    //   6487: bipush #24
    //   6489: iushr
    //   6490: iload #24
    //   6492: bipush #8
    //   6494: ishl
    //   6495: ior
    //   6496: iastore
    //   6497: iinc #16, 1
    //   6500: iload_2
    //   6501: ifeq -> 6272
    //   6504: aload #6
    //   6506: arraylength
    //   6507: newarray byte
    //   6509: astore #43
    //   6511: iconst_0
    //   6512: istore #44
    //   6514: iload #44
    //   6516: aload #6
    //   6518: arraylength
    //   6519: bipush #16
    //   6521: idiv
    //   6522: if_icmpge -> 7436
    //   6525: bipush #16
    //   6527: newarray byte
    //   6529: astore #45
    //   6531: bipush #16
    //   6533: newarray byte
    //   6535: astore #46
    //   6537: iconst_0
    //   6538: istore #47
    //   6540: iload #47
    //   6542: bipush #16
    //   6544: if_icmpge -> 6570
    //   6547: aload #45
    //   6549: iload #47
    //   6551: aload #6
    //   6553: iload #47
    //   6555: iload #44
    //   6557: bipush #16
    //   6559: imul
    //   6560: iadd
    //   6561: baload
    //   6562: bastore
    //   6563: iinc #47, 1
    //   6566: iload_2
    //   6567: ifeq -> 6540
    //   6570: iconst_0
    //   6571: istore #47
    //   6573: aload #45
    //   6575: iconst_0
    //   6576: baload
    //   6577: bipush #24
    //   6579: ishl
    //   6580: aload #45
    //   6582: iconst_1
    //   6583: baload
    //   6584: sipush #255
    //   6587: iand
    //   6588: bipush #16
    //   6590: ishl
    //   6591: ior
    //   6592: aload #45
    //   6594: iconst_2
    //   6595: baload
    //   6596: sipush #255
    //   6599: iand
    //   6600: bipush #8
    //   6602: ishl
    //   6603: ior
    //   6604: aload #45
    //   6606: iconst_3
    //   6607: baload
    //   6608: sipush #255
    //   6611: iand
    //   6612: ior
    //   6613: aload #30
    //   6615: iconst_0
    //   6616: iaload
    //   6617: ixor
    //   6618: istore #49
    //   6620: aload #45
    //   6622: iconst_4
    //   6623: baload
    //   6624: bipush #24
    //   6626: ishl
    //   6627: aload #45
    //   6629: iconst_5
    //   6630: baload
    //   6631: sipush #255
    //   6634: iand
    //   6635: bipush #16
    //   6637: ishl
    //   6638: ior
    //   6639: aload #45
    //   6641: bipush #6
    //   6643: baload
    //   6644: sipush #255
    //   6647: iand
    //   6648: bipush #8
    //   6650: ishl
    //   6651: ior
    //   6652: aload #45
    //   6654: bipush #7
    //   6656: baload
    //   6657: sipush #255
    //   6660: iand
    //   6661: ior
    //   6662: aload #30
    //   6664: iconst_1
    //   6665: iaload
    //   6666: ixor
    //   6667: istore #50
    //   6669: aload #45
    //   6671: bipush #8
    //   6673: baload
    //   6674: bipush #24
    //   6676: ishl
    //   6677: aload #45
    //   6679: bipush #9
    //   6681: baload
    //   6682: sipush #255
    //   6685: iand
    //   6686: bipush #16
    //   6688: ishl
    //   6689: ior
    //   6690: aload #45
    //   6692: bipush #10
    //   6694: baload
    //   6695: sipush #255
    //   6698: iand
    //   6699: bipush #8
    //   6701: ishl
    //   6702: ior
    //   6703: aload #45
    //   6705: bipush #11
    //   6707: baload
    //   6708: sipush #255
    //   6711: iand
    //   6712: ior
    //   6713: aload #30
    //   6715: iconst_2
    //   6716: iaload
    //   6717: ixor
    //   6718: istore #51
    //   6720: aload #45
    //   6722: bipush #12
    //   6724: baload
    //   6725: bipush #24
    //   6727: ishl
    //   6728: aload #45
    //   6730: bipush #13
    //   6732: baload
    //   6733: sipush #255
    //   6736: iand
    //   6737: bipush #16
    //   6739: ishl
    //   6740: ior
    //   6741: aload #45
    //   6743: bipush #14
    //   6745: baload
    //   6746: sipush #255
    //   6749: iand
    //   6750: bipush #8
    //   6752: ishl
    //   6753: ior
    //   6754: aload #45
    //   6756: bipush #15
    //   6758: baload
    //   6759: sipush #255
    //   6762: iand
    //   6763: ior
    //   6764: aload #30
    //   6766: iconst_3
    //   6767: iaload
    //   6768: ixor
    //   6769: istore #52
    //   6771: iconst_1
    //   6772: istore #53
    //   6774: iload #53
    //   6776: iload #36
    //   6778: if_icmpge -> 7021
    //   6781: iinc #47, 4
    //   6784: aload #38
    //   6786: iload #49
    //   6788: bipush #24
    //   6790: iushr
    //   6791: iaload
    //   6792: aload #39
    //   6794: iload #52
    //   6796: bipush #16
    //   6798: iushr
    //   6799: sipush #255
    //   6802: iand
    //   6803: iaload
    //   6804: ixor
    //   6805: aload #40
    //   6807: iload #51
    //   6809: bipush #8
    //   6811: iushr
    //   6812: sipush #255
    //   6815: iand
    //   6816: iaload
    //   6817: ixor
    //   6818: aload #41
    //   6820: iload #50
    //   6822: sipush #255
    //   6825: iand
    //   6826: iaload
    //   6827: ixor
    //   6828: aload #30
    //   6830: iload #47
    //   6832: iaload
    //   6833: ixor
    //   6834: istore #54
    //   6836: aload #38
    //   6838: iload #50
    //   6840: bipush #24
    //   6842: iushr
    //   6843: iaload
    //   6844: aload #39
    //   6846: iload #49
    //   6848: bipush #16
    //   6850: iushr
    //   6851: sipush #255
    //   6854: iand
    //   6855: iaload
    //   6856: ixor
    //   6857: aload #40
    //   6859: iload #52
    //   6861: bipush #8
    //   6863: iushr
    //   6864: sipush #255
    //   6867: iand
    //   6868: iaload
    //   6869: ixor
    //   6870: aload #41
    //   6872: iload #51
    //   6874: sipush #255
    //   6877: iand
    //   6878: iaload
    //   6879: ixor
    //   6880: aload #30
    //   6882: iload #47
    //   6884: iconst_1
    //   6885: iadd
    //   6886: iaload
    //   6887: ixor
    //   6888: istore #55
    //   6890: aload #38
    //   6892: iload #51
    //   6894: bipush #24
    //   6896: iushr
    //   6897: iaload
    //   6898: aload #39
    //   6900: iload #50
    //   6902: bipush #16
    //   6904: iushr
    //   6905: sipush #255
    //   6908: iand
    //   6909: iaload
    //   6910: ixor
    //   6911: aload #40
    //   6913: iload #49
    //   6915: bipush #8
    //   6917: iushr
    //   6918: sipush #255
    //   6921: iand
    //   6922: iaload
    //   6923: ixor
    //   6924: aload #41
    //   6926: iload #52
    //   6928: sipush #255
    //   6931: iand
    //   6932: iaload
    //   6933: ixor
    //   6934: aload #30
    //   6936: iload #47
    //   6938: iconst_2
    //   6939: iadd
    //   6940: iaload
    //   6941: ixor
    //   6942: istore #56
    //   6944: aload #38
    //   6946: iload #52
    //   6948: bipush #24
    //   6950: iushr
    //   6951: iaload
    //   6952: aload #39
    //   6954: iload #51
    //   6956: bipush #16
    //   6958: iushr
    //   6959: sipush #255
    //   6962: iand
    //   6963: iaload
    //   6964: ixor
    //   6965: aload #40
    //   6967: iload #50
    //   6969: bipush #8
    //   6971: iushr
    //   6972: sipush #255
    //   6975: iand
    //   6976: iaload
    //   6977: ixor
    //   6978: aload #41
    //   6980: iload #49
    //   6982: sipush #255
    //   6985: iand
    //   6986: iaload
    //   6987: ixor
    //   6988: aload #30
    //   6990: iload #47
    //   6992: iconst_3
    //   6993: iadd
    //   6994: iaload
    //   6995: ixor
    //   6996: istore #57
    //   6998: iload #54
    //   7000: istore #49
    //   7002: iload #55
    //   7004: istore #50
    //   7006: iload #56
    //   7008: istore #51
    //   7010: iload #57
    //   7012: istore #52
    //   7014: iinc #53, 1
    //   7017: iload_2
    //   7018: ifeq -> 6774
    //   7021: iinc #47, 4
    //   7024: aload #30
    //   7026: iload #47
    //   7028: iaload
    //   7029: istore #48
    //   7031: aload #46
    //   7033: iconst_0
    //   7034: aload #37
    //   7036: iload #49
    //   7038: bipush #24
    //   7040: iushr
    //   7041: baload
    //   7042: iload #48
    //   7044: bipush #24
    //   7046: iushr
    //   7047: ixor
    //   7048: i2b
    //   7049: bastore
    //   7050: aload #46
    //   7052: iconst_1
    //   7053: aload #37
    //   7055: iload #52
    //   7057: bipush #16
    //   7059: iushr
    //   7060: sipush #255
    //   7063: iand
    //   7064: baload
    //   7065: iload #48
    //   7067: bipush #16
    //   7069: iushr
    //   7070: ixor
    //   7071: i2b
    //   7072: bastore
    //   7073: aload #46
    //   7075: iconst_2
    //   7076: aload #37
    //   7078: iload #51
    //   7080: bipush #8
    //   7082: iushr
    //   7083: sipush #255
    //   7086: iand
    //   7087: baload
    //   7088: iload #48
    //   7090: bipush #8
    //   7092: iushr
    //   7093: ixor
    //   7094: i2b
    //   7095: bastore
    //   7096: aload #46
    //   7098: iconst_3
    //   7099: aload #37
    //   7101: iload #50
    //   7103: sipush #255
    //   7106: iand
    //   7107: baload
    //   7108: iload #48
    //   7110: ixor
    //   7111: i2b
    //   7112: bastore
    //   7113: aload #30
    //   7115: iload #47
    //   7117: iconst_1
    //   7118: iadd
    //   7119: iaload
    //   7120: istore #48
    //   7122: aload #46
    //   7124: iconst_4
    //   7125: aload #37
    //   7127: iload #50
    //   7129: bipush #24
    //   7131: iushr
    //   7132: baload
    //   7133: iload #48
    //   7135: bipush #24
    //   7137: iushr
    //   7138: ixor
    //   7139: i2b
    //   7140: bastore
    //   7141: aload #46
    //   7143: iconst_5
    //   7144: aload #37
    //   7146: iload #49
    //   7148: bipush #16
    //   7150: iushr
    //   7151: sipush #255
    //   7154: iand
    //   7155: baload
    //   7156: iload #48
    //   7158: bipush #16
    //   7160: iushr
    //   7161: ixor
    //   7162: i2b
    //   7163: bastore
    //   7164: aload #46
    //   7166: bipush #6
    //   7168: aload #37
    //   7170: iload #52
    //   7172: bipush #8
    //   7174: iushr
    //   7175: sipush #255
    //   7178: iand
    //   7179: baload
    //   7180: iload #48
    //   7182: bipush #8
    //   7184: iushr
    //   7185: ixor
    //   7186: i2b
    //   7187: bastore
    //   7188: aload #46
    //   7190: bipush #7
    //   7192: aload #37
    //   7194: iload #51
    //   7196: sipush #255
    //   7199: iand
    //   7200: baload
    //   7201: iload #48
    //   7203: ixor
    //   7204: i2b
    //   7205: bastore
    //   7206: aload #30
    //   7208: iload #47
    //   7210: iconst_2
    //   7211: iadd
    //   7212: iaload
    //   7213: istore #48
    //   7215: aload #46
    //   7217: bipush #8
    //   7219: aload #37
    //   7221: iload #51
    //   7223: bipush #24
    //   7225: iushr
    //   7226: baload
    //   7227: iload #48
    //   7229: bipush #24
    //   7231: iushr
    //   7232: ixor
    //   7233: i2b
    //   7234: bastore
    //   7235: aload #46
    //   7237: bipush #9
    //   7239: aload #37
    //   7241: iload #50
    //   7243: bipush #16
    //   7245: iushr
    //   7246: sipush #255
    //   7249: iand
    //   7250: baload
    //   7251: iload #48
    //   7253: bipush #16
    //   7255: iushr
    //   7256: ixor
    //   7257: i2b
    //   7258: bastore
    //   7259: aload #46
    //   7261: bipush #10
    //   7263: aload #37
    //   7265: iload #49
    //   7267: bipush #8
    //   7269: iushr
    //   7270: sipush #255
    //   7273: iand
    //   7274: baload
    //   7275: iload #48
    //   7277: bipush #8
    //   7279: iushr
    //   7280: ixor
    //   7281: i2b
    //   7282: bastore
    //   7283: aload #46
    //   7285: bipush #11
    //   7287: aload #37
    //   7289: iload #52
    //   7291: sipush #255
    //   7294: iand
    //   7295: baload
    //   7296: iload #48
    //   7298: ixor
    //   7299: i2b
    //   7300: bastore
    //   7301: aload #30
    //   7303: iload #47
    //   7305: iconst_3
    //   7306: iadd
    //   7307: iaload
    //   7308: istore #48
    //   7310: aload #46
    //   7312: bipush #12
    //   7314: aload #37
    //   7316: iload #52
    //   7318: bipush #24
    //   7320: iushr
    //   7321: baload
    //   7322: iload #48
    //   7324: bipush #24
    //   7326: iushr
    //   7327: ixor
    //   7328: i2b
    //   7329: bastore
    //   7330: aload #46
    //   7332: bipush #13
    //   7334: aload #37
    //   7336: iload #51
    //   7338: bipush #16
    //   7340: iushr
    //   7341: sipush #255
    //   7344: iand
    //   7345: baload
    //   7346: iload #48
    //   7348: bipush #16
    //   7350: iushr
    //   7351: ixor
    //   7352: i2b
    //   7353: bastore
    //   7354: aload #46
    //   7356: bipush #14
    //   7358: aload #37
    //   7360: iload #50
    //   7362: bipush #8
    //   7364: iushr
    //   7365: sipush #255
    //   7368: iand
    //   7369: baload
    //   7370: iload #48
    //   7372: bipush #8
    //   7374: iushr
    //   7375: ixor
    //   7376: i2b
    //   7377: bastore
    //   7378: aload #46
    //   7380: bipush #15
    //   7382: aload #37
    //   7384: iload #49
    //   7386: sipush #255
    //   7389: iand
    //   7390: baload
    //   7391: iload #48
    //   7393: ixor
    //   7394: i2b
    //   7395: bastore
    //   7396: iconst_0
    //   7397: istore #53
    //   7399: iload #53
    //   7401: bipush #16
    //   7403: if_icmpge -> 7429
    //   7406: aload #43
    //   7408: iload #53
    //   7410: iload #44
    //   7412: bipush #16
    //   7414: imul
    //   7415: iadd
    //   7416: aload #46
    //   7418: iload #53
    //   7420: baload
    //   7421: bastore
    //   7422: iinc #53, 1
    //   7425: iload_2
    //   7426: ifeq -> 7399
    //   7429: iinc #44, 1
    //   7432: iload_2
    //   7433: ifeq -> 6514
    //   7436: aload #43
    //   7438: arraylength
    //   7439: ifle -> 7520
    //   7442: aload #43
    //   7444: aload #43
    //   7446: arraylength
    //   7447: iconst_1
    //   7448: isub
    //   7449: baload
    //   7450: istore #44
    //   7452: iload #44
    //   7454: bipush #16
    //   7456: if_icmple -> 7467
    //   7459: aload #43
    //   7461: astore #35
    //   7463: iload_2
    //   7464: ifeq -> 7520
    //   7467: aload #43
    //   7469: arraylength
    //   7470: iload #44
    //   7472: isub
    //   7473: newarray byte
    //   7475: astore #35
    //   7477: iconst_0
    //   7478: istore #45
    //   7480: iload #45
    //   7482: aload #35
    //   7484: arraylength
    //   7485: if_icmpge -> 7520
    //   7488: iload #45
    //   7490: aload #43
    //   7492: arraylength
    //   7493: if_icmpge -> 7520
    //   7496: aload #35
    //   7498: iload #45
    //   7500: aload #43
    //   7502: iload #45
    //   7504: baload
    //   7505: bastore
    //   7506: iinc #45, 1
    //   7509: iload_2
    //   7510: ifeq -> 7480
    //   7513: goto -> 7520
    //   7516: invokestatic a : (Ljava/lang/Throwable;)Ljava/lang/Throwable;
    //   7519: athrow
    //   7520: aload #35
    //   7522: astore #7
    //   7524: iconst_0
    //   7525: istore_3
    //   7526: getstatic burp/Zxtn.Zu : Ljava/lang/String;
    //   7529: getstatic burp/Zxnm.ZW : Ljava/lang/Object;
    //   7532: checkcast java/math/BigInteger
    //   7535: invokevirtual intValue : ()I
    //   7538: bipush #32
    //   7540: irem
    //   7541: invokestatic abs : (I)I
    //   7544: invokevirtual charAt : (I)C
    //   7547: getstatic burp/Zre1.ZA : Ljava/lang/String;
    //   7550: getstatic burp/Zkul.Zb : Ljava/lang/Object;
    //   7553: checkcast java/math/BigInteger
    //   7556: invokevirtual intValue : ()I
    //   7559: bipush #32
    //   7561: irem
    //   7562: invokestatic abs : (I)I
    //   7565: invokevirtual charAt : (I)C
    //   7568: if_icmple -> 7912
    //   7571: sipush #2617
    //   7574: sipush #-17922
    //   7577: invokestatic a : (II)Ljava/lang/String;
    //   7580: iconst_1
    //   7581: ldc burp/Zre1
    //   7583: invokevirtual getClassLoader : ()Ljava/lang/ClassLoader;
    //   7586: invokestatic forName : (Ljava/lang/String;ZLjava/lang/ClassLoader;)Ljava/lang/Class;
    //   7589: invokevirtual getDeclaredFields : ()[Ljava/lang/reflect/Field;
    //   7592: astore #4
    //   7594: aload #4
    //   7596: arraylength
    //   7597: istore #5
    //   7599: iconst_0
    //   7600: istore #6
    //   7602: iload #6
    //   7604: iload #5
    //   7606: if_icmpge -> 7744
    //   7609: aload #4
    //   7611: iload #6
    //   7613: aaload
    //   7614: astore #7
    //   7616: aload #7
    //   7618: invokevirtual getModifiers : ()I
    //   7621: invokestatic isStatic : (I)Z
    //   7624: ifne -> 7634
    //   7627: goto -> 7737
    //   7630: invokestatic a : (Ljava/lang/Throwable;)Ljava/lang/Throwable;
    //   7633: athrow
    //   7634: aload #7
    //   7636: invokevirtual getType : ()Ljava/lang/Class;
    //   7639: astore #8
    //   7641: aload #8
    //   7643: ifnull -> 7724
    //   7646: aload #8
    //   7648: invokevirtual isPrimitive : ()Z
    //   7651: ifne -> 7724
    //   7654: goto -> 7661
    //   7657: invokestatic a : (Ljava/lang/Throwable;)Ljava/lang/Throwable;
    //   7660: athrow
    //   7661: aload #8
    //   7663: invokevirtual getPackage : ()Ljava/lang/Package;
    //   7666: ifnull -> 7724
    //   7669: goto -> 7676
    //   7672: invokestatic a : (Ljava/lang/Throwable;)Ljava/lang/Throwable;
    //   7675: athrow
    //   7676: aload #8
    //   7678: invokevirtual getPackage : ()Ljava/lang/Package;
    //   7681: invokevirtual getName : ()Ljava/lang/String;
    //   7684: ifnull -> 7724
    //   7687: goto -> 7694
    //   7690: invokestatic a : (Ljava/lang/Throwable;)Ljava/lang/Throwable;
    //   7693: athrow
    //   7694: aload #8
    //   7696: invokevirtual getPackage : ()Ljava/lang/Package;
    //   7699: invokevirtual getName : ()Ljava/lang/String;
    //   7702: sipush #2614
    //   7705: sipush #-6687
    //   7708: invokestatic a : (II)Ljava/lang/String;
    //   7711: invokevirtual startsWith : (Ljava/lang/String;)Z
    //   7714: ifne -> 7724
    //   7717: goto -> 7724
    //   7720: invokestatic a : (Ljava/lang/Throwable;)Ljava/lang/Throwable;
    //   7723: athrow
    //   7724: aload #7
    //   7726: iconst_1
    //   7727: invokevirtual setAccessible : (Z)V
    //   7730: aload #7
    //   7732: aconst_null
    //   7733: invokevirtual get : (Ljava/lang/Object;)Ljava/lang/Object;
    //   7736: pop
    //   7737: iinc #6, 1
    //   7740: iload_2
    //   7741: ifeq -> 7602
    //   7744: sipush #2623
    //   7747: sipush #-28277
    //   7750: invokestatic a : (II)Ljava/lang/String;
    //   7753: invokestatic forName : (Ljava/lang/String;)Ljava/lang/Class;
    //   7756: invokevirtual getDeclaredMethods : ()[Ljava/lang/reflect/Method;
    //   7759: astore #4
    //   7761: aload #4
    //   7763: arraylength
    //   7764: istore #5
    //   7766: iconst_0
    //   7767: istore #6
    //   7769: iload #6
    //   7771: iload #5
    //   7773: if_icmpge -> 7909
    //   7776: aload #4
    //   7778: iload #6
    //   7780: aaload
    //   7781: astore #7
    //   7783: aload #7
    //   7785: invokevirtual getParameterTypes : ()[Ljava/lang/Class;
    //   7788: pop
    //   7789: aload #7
    //   7791: invokevirtual getModifiers : ()I
    //   7794: invokestatic isStatic : (I)Z
    //   7797: ifeq -> 7895
    //   7800: aload #7
    //   7802: invokevirtual getParameterTypes : ()[Ljava/lang/Class;
    //   7805: arraylength
    //   7806: iconst_2
    //   7807: if_icmpne -> 7895
    //   7810: goto -> 7817
    //   7813: invokestatic a : (Ljava/lang/Throwable;)Ljava/lang/Throwable;
    //   7816: athrow
    //   7817: aload #7
    //   7819: invokevirtual getReturnType : ()Ljava/lang/Class;
    //   7822: getstatic java/lang/Boolean.TYPE : Ljava/lang/Class;
    //   7825: if_acmpne -> 7895
    //   7828: goto -> 7835
    //   7831: invokestatic a : (Ljava/lang/Throwable;)Ljava/lang/Throwable;
    //   7834: athrow
    //   7835: aload #7
    //   7837: iconst_1
    //   7838: invokevirtual setAccessible : (Z)V
    //   7841: aload #7
    //   7843: aconst_null
    //   7844: iconst_2
    //   7845: anewarray java/lang/Object
    //   7848: dup
    //   7849: iconst_0
    //   7850: aload_0
    //   7851: aastore
    //   7852: dup
    //   7853: iconst_1
    //   7854: aload_1
    //   7855: ifnonnull -> 7873
    //   7858: goto -> 7865
    //   7861: invokestatic a : (Ljava/lang/Throwable;)Ljava/lang/Throwable;
    //   7864: athrow
    //   7865: aload_1
    //   7866: goto -> 7880
    //   7869: invokestatic a : (Ljava/lang/Throwable;)Ljava/lang/Throwable;
    //   7872: athrow
    //   7873: aload_1
    //   7874: checkcast [B
    //   7877: invokevirtual clone : ()Ljava/lang/Object;
    //   7880: aastore
    //   7881: invokevirtual invoke : (Ljava/lang/Object;[Ljava/lang/Object;)Ljava/lang/Object;
    //   7884: checkcast java/lang/Boolean
    //   7887: invokevirtual booleanValue : ()Z
    //   7890: istore_3
    //   7891: iload_2
    //   7892: ifeq -> 7909
    //   7895: iinc #6, 1
    //   7898: iload_2
    //   7899: ifeq -> 7769
    //   7902: goto -> 7909
    //   7905: invokestatic a : (Ljava/lang/Throwable;)Ljava/lang/Throwable;
    //   7908: athrow
    //   7909: goto -> 8250
    //   7912: sipush #2607
    //   7915: sipush #-7722
    //   7918: invokestatic a : (II)Ljava/lang/String;
    //   7921: iconst_1
    //   7922: ldc burp/Ztq2
    //   7924: invokevirtual getClassLoader : ()Ljava/lang/ClassLoader;
    //   7927: invokestatic forName : (Ljava/lang/String;ZLjava/lang/ClassLoader;)Ljava/lang/Class;
    //   7930: invokevirtual getDeclaredFields : ()[Ljava/lang/reflect/Field;
    //   7933: astore #4
    //   7935: aload #4
    //   7937: arraylength
    //   7938: istore #5
    //   7940: iconst_0
    //   7941: istore #6
    //   7943: iload #6
    //   7945: iload #5
    //   7947: if_icmpge -> 8085
    //   7950: aload #4
    //   7952: iload #6
    //   7954: aaload
    //   7955: astore #7
    //   7957: aload #7
    //   7959: invokevirtual getModifiers : ()I
    //   7962: invokestatic isStatic : (I)Z
    //   7965: ifne -> 7975
    //   7968: goto -> 8078
    //   7971: invokestatic a : (Ljava/lang/Throwable;)Ljava/lang/Throwable;
    //   7974: athrow
    //   7975: aload #7
    //   7977: invokevirtual getType : ()Ljava/lang/Class;
    //   7980: astore #8
    //   7982: aload #8
    //   7984: ifnull -> 8065
    //   7987: aload #8
    //   7989: invokevirtual isPrimitive : ()Z
    //   7992: ifne -> 8065
    //   7995: goto -> 8002
    //   7998: invokestatic a : (Ljava/lang/Throwable;)Ljava/lang/Throwable;
    //   8001: athrow
    //   8002: aload #8
    //   8004: invokevirtual getPackage : ()Ljava/lang/Package;
    //   8007: ifnull -> 8065
    //   8010: goto -> 8017
    //   8013: invokestatic a : (Ljava/lang/Throwable;)Ljava/lang/Throwable;
    //   8016: athrow
    //   8017: aload #8
    //   8019: invokevirtual getPackage : ()Ljava/lang/Package;
    //   8022: invokevirtual getName : ()Ljava/lang/String;
    //   8025: ifnull -> 8065
    //   8028: goto -> 8035
    //   8031: invokestatic a : (Ljava/lang/Throwable;)Ljava/lang/Throwable;
    //   8034: athrow
    //   8035: aload #8
    //   8037: invokevirtual getPackage : ()Ljava/lang/Package;
    //   8040: invokevirtual getName : ()Ljava/lang/String;
    //   8043: sipush #2614
    //   8046: sipush #-6687
    //   8049: invokestatic a : (II)Ljava/lang/String;
    //   8052: invokevirtual startsWith : (Ljava/lang/String;)Z
    //   8055: ifne -> 8065
    //   8058: goto -> 8065
    //   8061: invokestatic a : (Ljava/lang/Throwable;)Ljava/lang/Throwable;
    //   8064: athrow
    //   8065: aload #7
    //   8067: iconst_1
    //   8068: invokevirtual setAccessible : (Z)V
    //   8071: aload #7
    //   8073: aconst_null
    //   8074: invokevirtual get : (Ljava/lang/Object;)Ljava/lang/Object;
    //   8077: pop
    //   8078: iinc #6, 1
    //   8081: iload_2
    //   8082: ifeq -> 7943
    //   8085: sipush #2606
    //   8088: sipush #-20824
    //   8091: invokestatic a : (II)Ljava/lang/String;
    //   8094: invokestatic forName : (Ljava/lang/String;)Ljava/lang/Class;
    //   8097: invokevirtual getDeclaredMethods : ()[Ljava/lang/reflect/Method;
    //   8100: astore #4
    //   8102: aload #4
    //   8104: arraylength
    //   8105: istore #5
    //   8107: iconst_0
    //   8108: istore #6
    //   8110: iload #6
    //   8112: iload #5
    //   8114: if_icmpge -> 8250
    //   8117: aload #4
    //   8119: iload #6
    //   8121: aaload
    //   8122: astore #7
    //   8124: aload #7
    //   8126: invokevirtual getParameterTypes : ()[Ljava/lang/Class;
    //   8129: pop
    //   8130: aload #7
    //   8132: invokevirtual getModifiers : ()I
    //   8135: invokestatic isStatic : (I)Z
    //   8138: ifeq -> 8236
    //   8141: aload #7
    //   8143: invokevirtual getParameterTypes : ()[Ljava/lang/Class;
    //   8146: arraylength
    //   8147: iconst_2
    //   8148: if_icmpne -> 8236
    //   8151: goto -> 8158
    //   8154: invokestatic a : (Ljava/lang/Throwable;)Ljava/lang/Throwable;
    //   8157: athrow
    //   8158: aload #7
    //   8160: invokevirtual getReturnType : ()Ljava/lang/Class;
    //   8163: getstatic java/lang/Boolean.TYPE : Ljava/lang/Class;
    //   8166: if_acmpne -> 8236
    //   8169: goto -> 8176
    //   8172: invokestatic a : (Ljava/lang/Throwable;)Ljava/lang/Throwable;
    //   8175: athrow
    //   8176: aload #7
    //   8178: iconst_1
    //   8179: invokevirtual setAccessible : (Z)V
    //   8182: aload #7
    //   8184: aconst_null
    //   8185: iconst_2
    //   8186: anewarray java/lang/Object
    //   8189: dup
    //   8190: iconst_0
    //   8191: aload_0
    //   8192: aastore
    //   8193: dup
    //   8194: iconst_1
    //   8195: aload_1
    //   8196: ifnonnull -> 8214
    //   8199: goto -> 8206
    //   8202: invokestatic a : (Ljava/lang/Throwable;)Ljava/lang/Throwable;
    //   8205: athrow
    //   8206: aload_1
    //   8207: goto -> 8221
    //   8210: invokestatic a : (Ljava/lang/Throwable;)Ljava/lang/Throwable;
    //   8213: athrow
    //   8214: aload_1
    //   8215: checkcast [B
    //   8218: invokevirtual clone : ()Ljava/lang/Object;
    //   8221: aastore
    //   8222: invokevirtual invoke : (Ljava/lang/Object;[Ljava/lang/Object;)Ljava/lang/Object;
    //   8225: checkcast java/lang/Boolean
    //   8228: invokevirtual booleanValue : ()Z
    //   8231: istore_3
    //   8232: iload_2
    //   8233: ifeq -> 8250
    //   8236: iinc #6, 1
    //   8239: iload_2
    //   8240: ifeq -> 8110
    //   8243: goto -> 8250
    //   8246: invokestatic a : (Ljava/lang/Throwable;)Ljava/lang/Throwable;
    //   8249: athrow
    //   8250: iload_3
    //   8251: ifeq -> 8256
    //   8254: iload_3
    //   8255: ireturn
    //   8256: getstatic burp/Zejg.ZP : Ljava/lang/String;
    //   8259: getstatic burp/Zr8g.ZF : Ljava/lang/Object;
    //   8262: checkcast java/math/BigInteger
    //   8265: invokevirtual intValue : ()I
    //   8268: bipush #32
    //   8270: irem
    //   8271: invokestatic abs : (I)I
    //   8274: invokevirtual charAt : (I)C
    //   8277: getstatic burp/Zxd0.Zc : Ljava/lang/String;
    //   8280: getstatic burp/Zmhx.ZQ : Ljava/lang/Object;
    //   8283: checkcast java/math/BigInteger
    //   8286: invokevirtual intValue : ()I
    //   8289: bipush #32
    //   8291: irem
    //   8292: invokestatic abs : (I)I
    //   8295: invokevirtual charAt : (I)C
    //   8298: if_icmpgt -> 8643
    //   8301: sipush #2605
    //   8304: sipush #18058
    //   8307: invokestatic a : (II)Ljava/lang/String;
    //   8310: iconst_1
    //   8311: ldc burp/Zbu6
    //   8313: invokevirtual getClassLoader : ()Ljava/lang/ClassLoader;
    //   8316: invokestatic forName : (Ljava/lang/String;ZLjava/lang/ClassLoader;)Ljava/lang/Class;
    //   8319: invokevirtual getDeclaredFields : ()[Ljava/lang/reflect/Field;
    //   8322: astore #4
    //   8324: aload #4
    //   8326: arraylength
    //   8327: istore #5
    //   8329: iconst_0
    //   8330: istore #6
    //   8332: iload #6
    //   8334: iload #5
    //   8336: if_icmpge -> 8474
    //   8339: aload #4
    //   8341: iload #6
    //   8343: aaload
    //   8344: astore #7
    //   8346: aload #7
    //   8348: invokevirtual getModifiers : ()I
    //   8351: invokestatic isStatic : (I)Z
    //   8354: ifne -> 8364
    //   8357: goto -> 8467
    //   8360: invokestatic a : (Ljava/lang/Throwable;)Ljava/lang/Throwable;
    //   8363: athrow
    //   8364: aload #7
    //   8366: invokevirtual getType : ()Ljava/lang/Class;
    //   8369: astore #8
    //   8371: aload #8
    //   8373: ifnull -> 8454
    //   8376: aload #8
    //   8378: invokevirtual isPrimitive : ()Z
    //   8381: ifne -> 8454
    //   8384: goto -> 8391
    //   8387: invokestatic a : (Ljava/lang/Throwable;)Ljava/lang/Throwable;
    //   8390: athrow
    //   8391: aload #8
    //   8393: invokevirtual getPackage : ()Ljava/lang/Package;
    //   8396: ifnull -> 8454
    //   8399: goto -> 8406
    //   8402: invokestatic a : (Ljava/lang/Throwable;)Ljava/lang/Throwable;
    //   8405: athrow
    //   8406: aload #8
    //   8408: invokevirtual getPackage : ()Ljava/lang/Package;
    //   8411: invokevirtual getName : ()Ljava/lang/String;
    //   8414: ifnull -> 8454
    //   8417: goto -> 8424
    //   8420: invokestatic a : (Ljava/lang/Throwable;)Ljava/lang/Throwable;
    //   8423: athrow
    //   8424: aload #8
    //   8426: invokevirtual getPackage : ()Ljava/lang/Package;
    //   8429: invokevirtual getName : ()Ljava/lang/String;
    //   8432: sipush #2614
    //   8435: sipush #-6687
    //   8438: invokestatic a : (II)Ljava/lang/String;
    //   8441: invokevirtual startsWith : (Ljava/lang/String;)Z
    //   8444: ifne -> 8454
    //   8447: goto -> 8454
    //   8450: invokestatic a : (Ljava/lang/Throwable;)Ljava/lang/Throwable;
    //   8453: athrow
    //   8454: aload #7
    //   8456: iconst_1
    //   8457: invokevirtual setAccessible : (Z)V
    //   8460: aload #7
    //   8462: aconst_null
    //   8463: invokevirtual get : (Ljava/lang/Object;)Ljava/lang/Object;
    //   8466: pop
    //   8467: iinc #6, 1
    //   8470: iload_2
    //   8471: ifeq -> 8332
    //   8474: sipush #2611
    //   8477: sipush #6986
    //   8480: invokestatic a : (II)Ljava/lang/String;
    //   8483: invokestatic forName : (Ljava/lang/String;)Ljava/lang/Class;
    //   8486: invokevirtual getDeclaredMethods : ()[Ljava/lang/reflect/Method;
    //   8489: astore #4
    //   8491: aload #4
    //   8493: arraylength
    //   8494: istore #5
    //   8496: iconst_0
    //   8497: istore #6
    //   8499: iload #6
    //   8501: iload #5
    //   8503: if_icmpge -> 8639
    //   8506: aload #4
    //   8508: iload #6
    //   8510: aaload
    //   8511: astore #7
    //   8513: aload #7
    //   8515: invokevirtual getParameterTypes : ()[Ljava/lang/Class;
    //   8518: pop
    //   8519: aload #7
    //   8521: invokevirtual getModifiers : ()I
    //   8524: invokestatic isStatic : (I)Z
    //   8527: ifeq -> 8625
    //   8530: aload #7
    //   8532: invokevirtual getParameterTypes : ()[Ljava/lang/Class;
    //   8535: arraylength
    //   8536: iconst_2
    //   8537: if_icmpne -> 8625
    //   8540: goto -> 8547
    //   8543: invokestatic a : (Ljava/lang/Throwable;)Ljava/lang/Throwable;
    //   8546: athrow
    //   8547: aload #7
    //   8549: invokevirtual getReturnType : ()Ljava/lang/Class;
    //   8552: getstatic java/lang/Boolean.TYPE : Ljava/lang/Class;
    //   8555: if_acmpne -> 8625
    //   8558: goto -> 8565
    //   8561: invokestatic a : (Ljava/lang/Throwable;)Ljava/lang/Throwable;
    //   8564: athrow
    //   8565: aload #7
    //   8567: iconst_1
    //   8568: invokevirtual setAccessible : (Z)V
    //   8571: aload #7
    //   8573: aconst_null
    //   8574: iconst_2
    //   8575: anewarray java/lang/Object
    //   8578: dup
    //   8579: iconst_0
    //   8580: aload_0
    //   8581: aastore
    //   8582: dup
    //   8583: iconst_1
    //   8584: aload_1
    //   8585: ifnonnull -> 8603
    //   8588: goto -> 8595
    //   8591: invokestatic a : (Ljava/lang/Throwable;)Ljava/lang/Throwable;
    //   8594: athrow
    //   8595: aload_1
    //   8596: goto -> 8610
    //   8599: invokestatic a : (Ljava/lang/Throwable;)Ljava/lang/Throwable;
    //   8602: athrow
    //   8603: aload_1
    //   8604: checkcast [B
    //   8607: invokevirtual clone : ()Ljava/lang/Object;
    //   8610: aastore
    //   8611: invokevirtual invoke : (Ljava/lang/Object;[Ljava/lang/Object;)Ljava/lang/Object;
    //   8614: checkcast java/lang/Boolean
    //   8617: invokevirtual booleanValue : ()Z
    //   8620: istore_3
    //   8621: iload_2
    //   8622: ifeq -> 8639
    //   8625: iinc #6, 1
    //   8628: iload_2
    //   8629: ifeq -> 8499
    //   8632: goto -> 8639
    //   8635: invokestatic a : (Ljava/lang/Throwable;)Ljava/lang/Throwable;
    //   8638: athrow
    //   8639: iload_2
    //   8640: ifeq -> 8981
    //   8643: sipush #2618
    //   8646: sipush #-19166
    //   8649: invokestatic a : (II)Ljava/lang/String;
    //   8652: iconst_1
    //   8653: ldc burp/Zeud
    //   8655: invokevirtual getClassLoader : ()Ljava/lang/ClassLoader;
    //   8658: invokestatic forName : (Ljava/lang/String;ZLjava/lang/ClassLoader;)Ljava/lang/Class;
    //   8661: invokevirtual getDeclaredFields : ()[Ljava/lang/reflect/Field;
    //   8664: astore #4
    //   8666: aload #4
    //   8668: arraylength
    //   8669: istore #5
    //   8671: iconst_0
    //   8672: istore #6
    //   8674: iload #6
    //   8676: iload #5
    //   8678: if_icmpge -> 8816
    //   8681: aload #4
    //   8683: iload #6
    //   8685: aaload
    //   8686: astore #7
    //   8688: aload #7
    //   8690: invokevirtual getModifiers : ()I
    //   8693: invokestatic isStatic : (I)Z
    //   8696: ifne -> 8706
    //   8699: goto -> 8809
    //   8702: invokestatic a : (Ljava/lang/Throwable;)Ljava/lang/Throwable;
    //   8705: athrow
    //   8706: aload #7
    //   8708: invokevirtual getType : ()Ljava/lang/Class;
    //   8711: astore #8
    //   8713: aload #8
    //   8715: ifnull -> 8796
    //   8718: aload #8
    //   8720: invokevirtual isPrimitive : ()Z
    //   8723: ifne -> 8796
    //   8726: goto -> 8733
    //   8729: invokestatic a : (Ljava/lang/Throwable;)Ljava/lang/Throwable;
    //   8732: athrow
    //   8733: aload #8
    //   8735: invokevirtual getPackage : ()Ljava/lang/Package;
    //   8738: ifnull -> 8796
    //   8741: goto -> 8748
    //   8744: invokestatic a : (Ljava/lang/Throwable;)Ljava/lang/Throwable;
    //   8747: athrow
    //   8748: aload #8
    //   8750: invokevirtual getPackage : ()Ljava/lang/Package;
    //   8753: invokevirtual getName : ()Ljava/lang/String;
    //   8756: ifnull -> 8796
    //   8759: goto -> 8766
    //   8762: invokestatic a : (Ljava/lang/Throwable;)Ljava/lang/Throwable;
    //   8765: athrow
    //   8766: aload #8
    //   8768: invokevirtual getPackage : ()Ljava/lang/Package;
    //   8771: invokevirtual getName : ()Ljava/lang/String;
    //   8774: sipush #2614
    //   8777: sipush #-6687
    //   8780: invokestatic a : (II)Ljava/lang/String;
    //   8783: invokevirtual startsWith : (Ljava/lang/String;)Z
    //   8786: ifne -> 8796
    //   8789: goto -> 8796
    //   8792: invokestatic a : (Ljava/lang/Throwable;)Ljava/lang/Throwable;
    //   8795: athrow
    //   8796: aload #7
    //   8798: iconst_1
    //   8799: invokevirtual setAccessible : (Z)V
    //   8802: aload #7
    //   8804: aconst_null
    //   8805: invokevirtual get : (Ljava/lang/Object;)Ljava/lang/Object;
    //   8808: pop
    //   8809: iinc #6, 1
    //   8812: iload_2
    //   8813: ifeq -> 8674
    //   8816: sipush #2598
    //   8819: sipush #-2511
    //   8822: invokestatic a : (II)Ljava/lang/String;
    //   8825: invokestatic forName : (Ljava/lang/String;)Ljava/lang/Class;
    //   8828: invokevirtual getDeclaredMethods : ()[Ljava/lang/reflect/Method;
    //   8831: astore #4
    //   8833: aload #4
    //   8835: arraylength
    //   8836: istore #5
    //   8838: iconst_0
    //   8839: istore #6
    //   8841: iload #6
    //   8843: iload #5
    //   8845: if_icmpge -> 8981
    //   8848: aload #4
    //   8850: iload #6
    //   8852: aaload
    //   8853: astore #7
    //   8855: aload #7
    //   8857: invokevirtual getParameterTypes : ()[Ljava/lang/Class;
    //   8860: pop
    //   8861: aload #7
    //   8863: invokevirtual getModifiers : ()I
    //   8866: invokestatic isStatic : (I)Z
    //   8869: ifeq -> 8967
    //   8872: aload #7
    //   8874: invokevirtual getParameterTypes : ()[Ljava/lang/Class;
    //   8877: arraylength
    //   8878: iconst_2
    //   8879: if_icmpne -> 8967
    //   8882: goto -> 8889
    //   8885: invokestatic a : (Ljava/lang/Throwable;)Ljava/lang/Throwable;
    //   8888: athrow
    //   8889: aload #7
    //   8891: invokevirtual getReturnType : ()Ljava/lang/Class;
    //   8894: getstatic java/lang/Boolean.TYPE : Ljava/lang/Class;
    //   8897: if_acmpne -> 8967
    //   8900: goto -> 8907
    //   8903: invokestatic a : (Ljava/lang/Throwable;)Ljava/lang/Throwable;
    //   8906: athrow
    //   8907: aload #7
    //   8909: iconst_1
    //   8910: invokevirtual setAccessible : (Z)V
    //   8913: aload #7
    //   8915: aconst_null
    //   8916: iconst_2
    //   8917: anewarray java/lang/Object
    //   8920: dup
    //   8921: iconst_0
    //   8922: aload_0
    //   8923: aastore
    //   8924: dup
    //   8925: iconst_1
    //   8926: aload_1
    //   8927: ifnonnull -> 8945
    //   8930: goto -> 8937
    //   8933: invokestatic a : (Ljava/lang/Throwable;)Ljava/lang/Throwable;
    //   8936: athrow
    //   8937: aload_1
    //   8938: goto -> 8952
    //   8941: invokestatic a : (Ljava/lang/Throwable;)Ljava/lang/Throwable;
    //   8944: athrow
    //   8945: aload_1
    //   8946: checkcast [B
    //   8949: invokevirtual clone : ()Ljava/lang/Object;
    //   8952: aastore
    //   8953: invokevirtual invoke : (Ljava/lang/Object;[Ljava/lang/Object;)Ljava/lang/Object;
    //   8956: checkcast java/lang/Boolean
    //   8959: invokevirtual booleanValue : ()Z
    //   8962: istore_3
    //   8963: iload_2
    //   8964: ifeq -> 8981
    //   8967: iinc #6, 1
    //   8970: iload_2
    //   8971: ifeq -> 8841
    //   8974: goto -> 8981
    //   8977: invokestatic a : (Ljava/lang/Throwable;)Ljava/lang/Throwable;
    //   8980: athrow
    //   8981: iload_3
    //   8982: ifeq -> 8987
    //   8985: iload_3
    //   8986: ireturn
    //   8987: getstatic burp/Zlno.ZM : Ljava/lang/String;
    //   8990: getstatic burp/Zewo.ZZ : Ljava/lang/Object;
    //   8993: checkcast java/math/BigInteger
    //   8996: invokevirtual intValue : ()I
    //   8999: bipush #32
    //   9001: irem
    //   9002: invokestatic abs : (I)I
    //   9005: invokevirtual charAt : (I)C
    //   9008: getstatic burp/Zkul.ZJ : Ljava/lang/String;
    //   9011: getstatic burp/Zezz.Zu : Ljava/lang/Object;
    //   9014: checkcast java/math/BigInteger
    //   9017: invokevirtual intValue : ()I
    //   9020: bipush #32
    //   9022: irem
    //   9023: invokestatic abs : (I)I
    //   9026: invokevirtual charAt : (I)C
    //   9029: if_icmpgt -> 9374
    //   9032: sipush #2612
    //   9035: sipush #5657
    //   9038: invokestatic a : (II)Ljava/lang/String;
    //   9041: iconst_1
    //   9042: ldc burp/Zexn
    //   9044: invokevirtual getClassLoader : ()Ljava/lang/ClassLoader;
    //   9047: invokestatic forName : (Ljava/lang/String;ZLjava/lang/ClassLoader;)Ljava/lang/Class;
    //   9050: invokevirtual getDeclaredFields : ()[Ljava/lang/reflect/Field;
    //   9053: astore #4
    //   9055: aload #4
    //   9057: arraylength
    //   9058: istore #5
    //   9060: iconst_0
    //   9061: istore #6
    //   9063: iload #6
    //   9065: iload #5
    //   9067: if_icmpge -> 9205
    //   9070: aload #4
    //   9072: iload #6
    //   9074: aaload
    //   9075: astore #7
    //   9077: aload #7
    //   9079: invokevirtual getModifiers : ()I
    //   9082: invokestatic isStatic : (I)Z
    //   9085: ifne -> 9095
    //   9088: goto -> 9198
    //   9091: invokestatic a : (Ljava/lang/Throwable;)Ljava/lang/Throwable;
    //   9094: athrow
    //   9095: aload #7
    //   9097: invokevirtual getType : ()Ljava/lang/Class;
    //   9100: astore #8
    //   9102: aload #8
    //   9104: ifnull -> 9185
    //   9107: aload #8
    //   9109: invokevirtual isPrimitive : ()Z
    //   9112: ifne -> 9185
    //   9115: goto -> 9122
    //   9118: invokestatic a : (Ljava/lang/Throwable;)Ljava/lang/Throwable;
    //   9121: athrow
    //   9122: aload #8
    //   9124: invokevirtual getPackage : ()Ljava/lang/Package;
    //   9127: ifnull -> 9185
    //   9130: goto -> 9137
    //   9133: invokestatic a : (Ljava/lang/Throwable;)Ljava/lang/Throwable;
    //   9136: athrow
    //   9137: aload #8
    //   9139: invokevirtual getPackage : ()Ljava/lang/Package;
    //   9142: invokevirtual getName : ()Ljava/lang/String;
    //   9145: ifnull -> 9185
    //   9148: goto -> 9155
    //   9151: invokestatic a : (Ljava/lang/Throwable;)Ljava/lang/Throwable;
    //   9154: athrow
    //   9155: aload #8
    //   9157: invokevirtual getPackage : ()Ljava/lang/Package;
    //   9160: invokevirtual getName : ()Ljava/lang/String;
    //   9163: sipush #2614
    //   9166: sipush #-6687
    //   9169: invokestatic a : (II)Ljava/lang/String;
    //   9172: invokevirtual startsWith : (Ljava/lang/String;)Z
    //   9175: ifne -> 9185
    //   9178: goto -> 9185
    //   9181: invokestatic a : (Ljava/lang/Throwable;)Ljava/lang/Throwable;
    //   9184: athrow
    //   9185: aload #7
    //   9187: iconst_1
    //   9188: invokevirtual setAccessible : (Z)V
    //   9191: aload #7
    //   9193: aconst_null
    //   9194: invokevirtual get : (Ljava/lang/Object;)Ljava/lang/Object;
    //   9197: pop
    //   9198: iinc #6, 1
    //   9201: iload_2
    //   9202: ifeq -> 9063
    //   9205: sipush #2595
    //   9208: sipush #8451
    //   9211: invokestatic a : (II)Ljava/lang/String;
    //   9214: invokestatic forName : (Ljava/lang/String;)Ljava/lang/Class;
    //   9217: invokevirtual getDeclaredMethods : ()[Ljava/lang/reflect/Method;
    //   9220: astore #4
    //   9222: aload #4
    //   9224: arraylength
    //   9225: istore #5
    //   9227: iconst_0
    //   9228: istore #6
    //   9230: iload #6
    //   9232: iload #5
    //   9234: if_icmpge -> 9370
    //   9237: aload #4
    //   9239: iload #6
    //   9241: aaload
    //   9242: astore #7
    //   9244: aload #7
    //   9246: invokevirtual getParameterTypes : ()[Ljava/lang/Class;
    //   9249: pop
    //   9250: aload #7
    //   9252: invokevirtual getModifiers : ()I
    //   9255: invokestatic isStatic : (I)Z
    //   9258: ifeq -> 9356
    //   9261: aload #7
    //   9263: invokevirtual getParameterTypes : ()[Ljava/lang/Class;
    //   9266: arraylength
    //   9267: iconst_2
    //   9268: if_icmpne -> 9356
    //   9271: goto -> 9278
    //   9274: invokestatic a : (Ljava/lang/Throwable;)Ljava/lang/Throwable;
    //   9277: athrow
    //   9278: aload #7
    //   9280: invokevirtual getReturnType : ()Ljava/lang/Class;
    //   9283: getstatic java/lang/Boolean.TYPE : Ljava/lang/Class;
    //   9286: if_acmpne -> 9356
    //   9289: goto -> 9296
    //   9292: invokestatic a : (Ljava/lang/Throwable;)Ljava/lang/Throwable;
    //   9295: athrow
    //   9296: aload #7
    //   9298: iconst_1
    //   9299: invokevirtual setAccessible : (Z)V
    //   9302: aload #7
    //   9304: aconst_null
    //   9305: iconst_2
    //   9306: anewarray java/lang/Object
    //   9309: dup
    //   9310: iconst_0
    //   9311: aload_0
    //   9312: aastore
    //   9313: dup
    //   9314: iconst_1
    //   9315: aload_1
    //   9316: ifnonnull -> 9334
    //   9319: goto -> 9326
    //   9322: invokestatic a : (Ljava/lang/Throwable;)Ljava/lang/Throwable;
    //   9325: athrow
    //   9326: aload_1
    //   9327: goto -> 9341
    //   9330: invokestatic a : (Ljava/lang/Throwable;)Ljava/lang/Throwable;
    //   9333: athrow
    //   9334: aload_1
    //   9335: checkcast [B
    //   9338: invokevirtual clone : ()Ljava/lang/Object;
    //   9341: aastore
    //   9342: invokevirtual invoke : (Ljava/lang/Object;[Ljava/lang/Object;)Ljava/lang/Object;
    //   9345: checkcast java/lang/Boolean
    //   9348: invokevirtual booleanValue : ()Z
    //   9351: istore_3
    //   9352: iload_2
    //   9353: ifeq -> 9370
    //   9356: iinc #6, 1
    //   9359: iload_2
    //   9360: ifeq -> 9230
    //   9363: goto -> 9370
    //   9366: invokestatic a : (Ljava/lang/Throwable;)Ljava/lang/Throwable;
    //   9369: athrow
    //   9370: iload_2
    //   9371: ifeq -> 9712
    //   9374: sipush #2593
    //   9377: sipush #-30147
    //   9380: invokestatic a : (II)Ljava/lang/String;
    //   9383: iconst_1
    //   9384: ldc burp/Zg3v
    //   9386: invokevirtual getClassLoader : ()Ljava/lang/ClassLoader;
    //   9389: invokestatic forName : (Ljava/lang/String;ZLjava/lang/ClassLoader;)Ljava/lang/Class;
    //   9392: invokevirtual getDeclaredFields : ()[Ljava/lang/reflect/Field;
    //   9395: astore #4
    //   9397: aload #4
    //   9399: arraylength
    //   9400: istore #5
    //   9402: iconst_0
    //   9403: istore #6
    //   9405: iload #6
    //   9407: iload #5
    //   9409: if_icmpge -> 9547
    //   9412: aload #4
    //   9414: iload #6
    //   9416: aaload
    //   9417: astore #7
    //   9419: aload #7
    //   9421: invokevirtual getModifiers : ()I
    //   9424: invokestatic isStatic : (I)Z
    //   9427: ifne -> 9437
    //   9430: goto -> 9540
    //   9433: invokestatic a : (Ljava/lang/Throwable;)Ljava/lang/Throwable;
    //   9436: athrow
    //   9437: aload #7
    //   9439: invokevirtual getType : ()Ljava/lang/Class;
    //   9442: astore #8
    //   9444: aload #8
    //   9446: ifnull -> 9527
    //   9449: aload #8
    //   9451: invokevirtual isPrimitive : ()Z
    //   9454: ifne -> 9527
    //   9457: goto -> 9464
    //   9460: invokestatic a : (Ljava/lang/Throwable;)Ljava/lang/Throwable;
    //   9463: athrow
    //   9464: aload #8
    //   9466: invokevirtual getPackage : ()Ljava/lang/Package;
    //   9469: ifnull -> 9527
    //   9472: goto -> 9479
    //   9475: invokestatic a : (Ljava/lang/Throwable;)Ljava/lang/Throwable;
    //   9478: athrow
    //   9479: aload #8
    //   9481: invokevirtual getPackage : ()Ljava/lang/Package;
    //   9484: invokevirtual getName : ()Ljava/lang/String;
    //   9487: ifnull -> 9527
    //   9490: goto -> 9497
    //   9493: invokestatic a : (Ljava/lang/Throwable;)Ljava/lang/Throwable;
    //   9496: athrow
    //   9497: aload #8
    //   9499: invokevirtual getPackage : ()Ljava/lang/Package;
    //   9502: invokevirtual getName : ()Ljava/lang/String;
    //   9505: sipush #2614
    //   9508: sipush #-6687
    //   9511: invokestatic a : (II)Ljava/lang/String;
    //   9514: invokevirtual startsWith : (Ljava/lang/String;)Z
    //   9517: ifne -> 9527
    //   9520: goto -> 9527
    //   9523: invokestatic a : (Ljava/lang/Throwable;)Ljava/lang/Throwable;
    //   9526: athrow
    //   9527: aload #7
    //   9529: iconst_1
    //   9530: invokevirtual setAccessible : (Z)V
    //   9533: aload #7
    //   9535: aconst_null
    //   9536: invokevirtual get : (Ljava/lang/Object;)Ljava/lang/Object;
    //   9539: pop
    //   9540: iinc #6, 1
    //   9543: iload_2
    //   9544: ifeq -> 9405
    //   9547: sipush #2593
    //   9550: sipush #-30147
    //   9553: invokestatic a : (II)Ljava/lang/String;
    //   9556: invokestatic forName : (Ljava/lang/String;)Ljava/lang/Class;
    //   9559: invokevirtual getDeclaredMethods : ()[Ljava/lang/reflect/Method;
    //   9562: astore #4
    //   9564: aload #4
    //   9566: arraylength
    //   9567: istore #5
    //   9569: iconst_0
    //   9570: istore #6
    //   9572: iload #6
    //   9574: iload #5
    //   9576: if_icmpge -> 9712
    //   9579: aload #4
    //   9581: iload #6
    //   9583: aaload
    //   9584: astore #7
    //   9586: aload #7
    //   9588: invokevirtual getParameterTypes : ()[Ljava/lang/Class;
    //   9591: pop
    //   9592: aload #7
    //   9594: invokevirtual getModifiers : ()I
    //   9597: invokestatic isStatic : (I)Z
    //   9600: ifeq -> 9698
    //   9603: aload #7
    //   9605: invokevirtual getParameterTypes : ()[Ljava/lang/Class;
    //   9608: arraylength
    //   9609: iconst_2
    //   9610: if_icmpne -> 9698
    //   9613: goto -> 9620
    //   9616: invokestatic a : (Ljava/lang/Throwable;)Ljava/lang/Throwable;
    //   9619: athrow
    //   9620: aload #7
    //   9622: invokevirtual getReturnType : ()Ljava/lang/Class;
    //   9625: getstatic java/lang/Boolean.TYPE : Ljava/lang/Class;
    //   9628: if_acmpne -> 9698
    //   9631: goto -> 9638
    //   9634: invokestatic a : (Ljava/lang/Throwable;)Ljava/lang/Throwable;
    //   9637: athrow
    //   9638: aload #7
    //   9640: iconst_1
    //   9641: invokevirtual setAccessible : (Z)V
    //   9644: aload #7
    //   9646: aconst_null
    //   9647: iconst_2
    //   9648: anewarray java/lang/Object
    //   9651: dup
    //   9652: iconst_0
    //   9653: aload_0
    //   9654: aastore
    //   9655: dup
    //   9656: iconst_1
    //   9657: aload_1
    //   9658: ifnonnull -> 9676
    //   9661: goto -> 9668
    //   9664: invokestatic a : (Ljava/lang/Throwable;)Ljava/lang/Throwable;
    //   9667: athrow
    //   9668: aload_1
    //   9669: goto -> 9683
    //   9672: invokestatic a : (Ljava/lang/Throwable;)Ljava/lang/Throwable;
    //   9675: athrow
    //   9676: aload_1
    //   9677: checkcast [B
    //   9680: invokevirtual clone : ()Ljava/lang/Object;
    //   9683: aastore
    //   9684: invokevirtual invoke : (Ljava/lang/Object;[Ljava/lang/Object;)Ljava/lang/Object;
    //   9687: checkcast java/lang/Boolean
    //   9690: invokevirtual booleanValue : ()Z
    //   9693: istore_3
    //   9694: iload_2
    //   9695: ifeq -> 9712
    //   9698: iinc #6, 1
    //   9701: iload_2
    //   9702: ifeq -> 9572
    //   9705: goto -> 9712
    //   9708: invokestatic a : (Ljava/lang/Throwable;)Ljava/lang/Throwable;
    //   9711: athrow
    //   9712: iload_3
    //   9713: ifeq -> 9718
    //   9716: iload_3
    //   9717: ireturn
    //   9718: getstatic burp/Zrvb.ZU : Ljava/lang/String;
    //   9721: getstatic burp/Zghe.ZJ : Ljava/lang/Object;
    //   9724: checkcast java/math/BigInteger
    //   9727: invokevirtual intValue : ()I
    //   9730: bipush #32
    //   9732: irem
    //   9733: invokestatic abs : (I)I
    //   9736: invokevirtual charAt : (I)C
    //   9739: getstatic burp/Zls_.Zn : Ljava/lang/String;
    //   9742: getstatic burp/Zmt6.ZK : Ljava/lang/Object;
    //   9745: checkcast java/math/BigInteger
    //   9748: invokevirtual intValue : ()I
    //   9751: bipush #32
    //   9753: irem
    //   9754: invokestatic abs : (I)I
    //   9757: invokevirtual charAt : (I)C
    //   9760: if_icmple -> 10105
    //   9763: sipush #2594
    //   9766: sipush #-11668
    //   9769: invokestatic a : (II)Ljava/lang/String;
    //   9772: iconst_1
    //   9773: ldc burp/Zea9
    //   9775: invokevirtual getClassLoader : ()Ljava/lang/ClassLoader;
    //   9778: invokestatic forName : (Ljava/lang/String;ZLjava/lang/ClassLoader;)Ljava/lang/Class;
    //   9781: invokevirtual getDeclaredFields : ()[Ljava/lang/reflect/Field;
    //   9784: astore #4
    //   9786: aload #4
    //   9788: arraylength
    //   9789: istore #5
    //   9791: iconst_0
    //   9792: istore #6
    //   9794: iload #6
    //   9796: iload #5
    //   9798: if_icmpge -> 9936
    //   9801: aload #4
    //   9803: iload #6
    //   9805: aaload
    //   9806: astore #7
    //   9808: aload #7
    //   9810: invokevirtual getModifiers : ()I
    //   9813: invokestatic isStatic : (I)Z
    //   9816: ifne -> 9826
    //   9819: goto -> 9929
    //   9822: invokestatic a : (Ljava/lang/Throwable;)Ljava/lang/Throwable;
    //   9825: athrow
    //   9826: aload #7
    //   9828: invokevirtual getType : ()Ljava/lang/Class;
    //   9831: astore #8
    //   9833: aload #8
    //   9835: ifnull -> 9916
    //   9838: aload #8
    //   9840: invokevirtual isPrimitive : ()Z
    //   9843: ifne -> 9916
    //   9846: goto -> 9853
    //   9849: invokestatic a : (Ljava/lang/Throwable;)Ljava/lang/Throwable;
    //   9852: athrow
    //   9853: aload #8
    //   9855: invokevirtual getPackage : ()Ljava/lang/Package;
    //   9858: ifnull -> 9916
    //   9861: goto -> 9868
    //   9864: invokestatic a : (Ljava/lang/Throwable;)Ljava/lang/Throwable;
    //   9867: athrow
    //   9868: aload #8
    //   9870: invokevirtual getPackage : ()Ljava/lang/Package;
    //   9873: invokevirtual getName : ()Ljava/lang/String;
    //   9876: ifnull -> 9916
    //   9879: goto -> 9886
    //   9882: invokestatic a : (Ljava/lang/Throwable;)Ljava/lang/Throwable;
    //   9885: athrow
    //   9886: aload #8
    //   9888: invokevirtual getPackage : ()Ljava/lang/Package;
    //   9891: invokevirtual getName : ()Ljava/lang/String;
    //   9894: sipush #2614
    //   9897: sipush #-6687
    //   9900: invokestatic a : (II)Ljava/lang/String;
    //   9903: invokevirtual startsWith : (Ljava/lang/String;)Z
    //   9906: ifne -> 9916
    //   9909: goto -> 9916
    //   9912: invokestatic a : (Ljava/lang/Throwable;)Ljava/lang/Throwable;
    //   9915: athrow
    //   9916: aload #7
    //   9918: iconst_1
    //   9919: invokevirtual setAccessible : (Z)V
    //   9922: aload #7
    //   9924: aconst_null
    //   9925: invokevirtual get : (Ljava/lang/Object;)Ljava/lang/Object;
    //   9928: pop
    //   9929: iinc #6, 1
    //   9932: iload_2
    //   9933: ifeq -> 9794
    //   9936: sipush #2613
    //   9939: sipush #-6650
    //   9942: invokestatic a : (II)Ljava/lang/String;
    //   9945: invokestatic forName : (Ljava/lang/String;)Ljava/lang/Class;
    //   9948: invokevirtual getDeclaredMethods : ()[Ljava/lang/reflect/Method;
    //   9951: astore #4
    //   9953: aload #4
    //   9955: arraylength
    //   9956: istore #5
    //   9958: iconst_0
    //   9959: istore #6
    //   9961: iload #6
    //   9963: iload #5
    //   9965: if_icmpge -> 10101
    //   9968: aload #4
    //   9970: iload #6
    //   9972: aaload
    //   9973: astore #7
    //   9975: aload #7
    //   9977: invokevirtual getParameterTypes : ()[Ljava/lang/Class;
    //   9980: pop
    //   9981: aload #7
    //   9983: invokevirtual getModifiers : ()I
    //   9986: invokestatic isStatic : (I)Z
    //   9989: ifeq -> 10087
    //   9992: aload #7
    //   9994: invokevirtual getParameterTypes : ()[Ljava/lang/Class;
    //   9997: arraylength
    //   9998: iconst_2
    //   9999: if_icmpne -> 10087
    //   10002: goto -> 10009
    //   10005: invokestatic a : (Ljava/lang/Throwable;)Ljava/lang/Throwable;
    //   10008: athrow
    //   10009: aload #7
    //   10011: invokevirtual getReturnType : ()Ljava/lang/Class;
    //   10014: getstatic java/lang/Boolean.TYPE : Ljava/lang/Class;
    //   10017: if_acmpne -> 10087
    //   10020: goto -> 10027
    //   10023: invokestatic a : (Ljava/lang/Throwable;)Ljava/lang/Throwable;
    //   10026: athrow
    //   10027: aload #7
    //   10029: iconst_1
    //   10030: invokevirtual setAccessible : (Z)V
    //   10033: aload #7
    //   10035: aconst_null
    //   10036: iconst_2
    //   10037: anewarray java/lang/Object
    //   10040: dup
    //   10041: iconst_0
    //   10042: aload_0
    //   10043: aastore
    //   10044: dup
    //   10045: iconst_1
    //   10046: aload_1
    //   10047: ifnonnull -> 10065
    //   10050: goto -> 10057
    //   10053: invokestatic a : (Ljava/lang/Throwable;)Ljava/lang/Throwable;
    //   10056: athrow
    //   10057: aload_1
    //   10058: goto -> 10072
    //   10061: invokestatic a : (Ljava/lang/Throwable;)Ljava/lang/Throwable;
    //   10064: athrow
    //   10065: aload_1
    //   10066: checkcast [B
    //   10069: invokevirtual clone : ()Ljava/lang/Object;
    //   10072: aastore
    //   10073: invokevirtual invoke : (Ljava/lang/Object;[Ljava/lang/Object;)Ljava/lang/Object;
    //   10076: checkcast java/lang/Boolean
    //   10079: invokevirtual booleanValue : ()Z
    //   10082: istore_3
    //   10083: iload_2
    //   10084: ifeq -> 10101
    //   10087: iinc #6, 1
    //   10090: iload_2
    //   10091: ifeq -> 9961
    //   10094: goto -> 10101
    //   10097: invokestatic a : (Ljava/lang/Throwable;)Ljava/lang/Throwable;
    //   10100: athrow
    //   10101: iload_2
    //   10102: ifeq -> 10443
    //   10105: sipush #2622
    //   10108: sipush #13474
    //   10111: invokestatic a : (II)Ljava/lang/String;
    //   10114: iconst_1
    //   10115: ldc burp/Zz5l
    //   10117: invokevirtual getClassLoader : ()Ljava/lang/ClassLoader;
    //   10120: invokestatic forName : (Ljava/lang/String;ZLjava/lang/ClassLoader;)Ljava/lang/Class;
    //   10123: invokevirtual getDeclaredFields : ()[Ljava/lang/reflect/Field;
    //   10126: astore #4
    //   10128: aload #4
    //   10130: arraylength
    //   10131: istore #5
    //   10133: iconst_0
    //   10134: istore #6
    //   10136: iload #6
    //   10138: iload #5
    //   10140: if_icmpge -> 10278
    //   10143: aload #4
    //   10145: iload #6
    //   10147: aaload
    //   10148: astore #7
    //   10150: aload #7
    //   10152: invokevirtual getModifiers : ()I
    //   10155: invokestatic isStatic : (I)Z
    //   10158: ifne -> 10168
    //   10161: goto -> 10271
    //   10164: invokestatic a : (Ljava/lang/Throwable;)Ljava/lang/Throwable;
    //   10167: athrow
    //   10168: aload #7
    //   10170: invokevirtual getType : ()Ljava/lang/Class;
    //   10173: astore #8
    //   10175: aload #8
    //   10177: ifnull -> 10258
    //   10180: aload #8
    //   10182: invokevirtual isPrimitive : ()Z
    //   10185: ifne -> 10258
    //   10188: goto -> 10195
    //   10191: invokestatic a : (Ljava/lang/Throwable;)Ljava/lang/Throwable;
    //   10194: athrow
    //   10195: aload #8
    //   10197: invokevirtual getPackage : ()Ljava/lang/Package;
    //   10200: ifnull -> 10258
    //   10203: goto -> 10210
    //   10206: invokestatic a : (Ljava/lang/Throwable;)Ljava/lang/Throwable;
    //   10209: athrow
    //   10210: aload #8
    //   10212: invokevirtual getPackage : ()Ljava/lang/Package;
    //   10215: invokevirtual getName : ()Ljava/lang/String;
    //   10218: ifnull -> 10258
    //   10221: goto -> 10228
    //   10224: invokestatic a : (Ljava/lang/Throwable;)Ljava/lang/Throwable;
    //   10227: athrow
    //   10228: aload #8
    //   10230: invokevirtual getPackage : ()Ljava/lang/Package;
    //   10233: invokevirtual getName : ()Ljava/lang/String;
    //   10236: sipush #2614
    //   10239: sipush #-6687
    //   10242: invokestatic a : (II)Ljava/lang/String;
    //   10245: invokevirtual startsWith : (Ljava/lang/String;)Z
    //   10248: ifne -> 10258
    //   10251: goto -> 10258
    //   10254: invokestatic a : (Ljava/lang/Throwable;)Ljava/lang/Throwable;
    //   10257: athrow
    //   10258: aload #7
    //   10260: iconst_1
    //   10261: invokevirtual setAccessible : (Z)V
    //   10264: aload #7
    //   10266: aconst_null
    //   10267: invokevirtual get : (Ljava/lang/Object;)Ljava/lang/Object;
    //   10270: pop
    //   10271: iinc #6, 1
    //   10274: iload_2
    //   10275: ifeq -> 10136
    //   10278: sipush #2603
    //   10281: sipush #-10233
    //   10284: invokestatic a : (II)Ljava/lang/String;
    //   10287: invokestatic forName : (Ljava/lang/String;)Ljava/lang/Class;
    //   10290: invokevirtual getDeclaredMethods : ()[Ljava/lang/reflect/Method;
    //   10293: astore #4
    //   10295: aload #4
    //   10297: arraylength
    //   10298: istore #5
    //   10300: iconst_0
    //   10301: istore #6
    //   10303: iload #6
    //   10305: iload #5
    //   10307: if_icmpge -> 10443
    //   10310: aload #4
    //   10312: iload #6
    //   10314: aaload
    //   10315: astore #7
    //   10317: aload #7
    //   10319: invokevirtual getParameterTypes : ()[Ljava/lang/Class;
    //   10322: pop
    //   10323: aload #7
    //   10325: invokevirtual getModifiers : ()I
    //   10328: invokestatic isStatic : (I)Z
    //   10331: ifeq -> 10429
    //   10334: aload #7
    //   10336: invokevirtual getParameterTypes : ()[Ljava/lang/Class;
    //   10339: arraylength
    //   10340: iconst_2
    //   10341: if_icmpne -> 10429
    //   10344: goto -> 10351
    //   10347: invokestatic a : (Ljava/lang/Throwable;)Ljava/lang/Throwable;
    //   10350: athrow
    //   10351: aload #7
    //   10353: invokevirtual getReturnType : ()Ljava/lang/Class;
    //   10356: getstatic java/lang/Boolean.TYPE : Ljava/lang/Class;
    //   10359: if_acmpne -> 10429
    //   10362: goto -> 10369
    //   10365: invokestatic a : (Ljava/lang/Throwable;)Ljava/lang/Throwable;
    //   10368: athrow
    //   10369: aload #7
    //   10371: iconst_1
    //   10372: invokevirtual setAccessible : (Z)V
    //   10375: aload #7
    //   10377: aconst_null
    //   10378: iconst_2
    //   10379: anewarray java/lang/Object
    //   10382: dup
    //   10383: iconst_0
    //   10384: aload_0
    //   10385: aastore
    //   10386: dup
    //   10387: iconst_1
    //   10388: aload_1
    //   10389: ifnonnull -> 10407
    //   10392: goto -> 10399
    //   10395: invokestatic a : (Ljava/lang/Throwable;)Ljava/lang/Throwable;
    //   10398: athrow
    //   10399: aload_1
    //   10400: goto -> 10414
    //   10403: invokestatic a : (Ljava/lang/Throwable;)Ljava/lang/Throwable;
    //   10406: athrow
    //   10407: aload_1
    //   10408: checkcast [B
    //   10411: invokevirtual clone : ()Ljava/lang/Object;
    //   10414: aastore
    //   10415: invokevirtual invoke : (Ljava/lang/Object;[Ljava/lang/Object;)Ljava/lang/Object;
    //   10418: checkcast java/lang/Boolean
    //   10421: invokevirtual booleanValue : ()Z
    //   10424: istore_3
    //   10425: iload_2
    //   10426: ifeq -> 10443
    //   10429: iinc #6, 1
    //   10432: iload_2
    //   10433: ifeq -> 10303
    //   10436: goto -> 10443
    //   10439: invokestatic a : (Ljava/lang/Throwable;)Ljava/lang/Throwable;
    //   10442: athrow
    //   10443: iload_3
    //   10444: ireturn
    //   10445: astore_3
    //   10446: new java/lang/Exception
    //   10449: dup
    //   10450: aload_3
    //   10451: invokevirtual getMessage : ()Ljava/lang/String;
    //   10454: invokespecial <init> : (Ljava/lang/String;)V
    //   10457: athrow
    // Exception table:
    //   from	to	target	type
    //   4	8255	10445	java/lang/Throwable
    //   3324	3349	3349	java/lang/Throwable
    //   4312	4338	4338	java/lang/Throwable
    //   4427	4441	4441	java/lang/Throwable
    //   4452	4465	4468	java/lang/Throwable
    //   4457	4480	4483	java/lang/Throwable
    //   4472	4498	4501	java/lang/Throwable
    //   4487	4528	4531	java/lang/Throwable
    //   4591	4618	4621	java/lang/Throwable
    //   4608	4636	4639	java/lang/Throwable
    //   4625	4672	4675	java/lang/Throwable
    //   4643	4686	4689	java/lang/Throwable
    //   4735	4749	4749	java/lang/Throwable
    //   4760	4773	4776	java/lang/Throwable
    //   4765	4788	4791	java/lang/Throwable
    //   4780	4806	4809	java/lang/Throwable
    //   4795	4836	4839	java/lang/Throwable
    //   4899	4926	4929	java/lang/Throwable
    //   4916	4947	4950	java/lang/Throwable
    //   4933	4977	4980	java/lang/Throwable
    //   4954	4988	4988	java/lang/Throwable
    //   4999	5015	5018	java/lang/Throwable
    //   5167	5182	5182	java/lang/Throwable
    //   6184	6210	6210	java/lang/Throwable
    //   6291	6306	6306	java/lang/Throwable
    //   7488	7513	7516	java/lang/Throwable
    //   7616	7630	7630	java/lang/Throwable
    //   7641	7654	7657	java/lang/Throwable
    //   7646	7669	7672	java/lang/Throwable
    //   7661	7687	7690	java/lang/Throwable
    //   7676	7717	7720	java/lang/Throwable
    //   7783	7810	7813	java/lang/Throwable
    //   7800	7828	7831	java/lang/Throwable
    //   7817	7858	7861	java/lang/Throwable
    //   7835	7869	7869	java/lang/Throwable
    //   7891	7902	7905	java/lang/Throwable
    //   7957	7971	7971	java/lang/Throwable
    //   7982	7995	7998	java/lang/Throwable
    //   7987	8010	8013	java/lang/Throwable
    //   8002	8028	8031	java/lang/Throwable
    //   8017	8058	8061	java/lang/Throwable
    //   8124	8151	8154	java/lang/Throwable
    //   8141	8169	8172	java/lang/Throwable
    //   8158	8199	8202	java/lang/Throwable
    //   8176	8210	8210	java/lang/Throwable
    //   8232	8243	8246	java/lang/Throwable
    //   8256	8986	10445	java/lang/Throwable
    //   8346	8360	8360	java/lang/Throwable
    //   8371	8384	8387	java/lang/Throwable
    //   8376	8399	8402	java/lang/Throwable
    //   8391	8417	8420	java/lang/Throwable
    //   8406	8447	8450	java/lang/Throwable
    //   8513	8540	8543	java/lang/Throwable
    //   8530	8558	8561	java/lang/Throwable
    //   8547	8588	8591	java/lang/Throwable
    //   8565	8599	8599	java/lang/Throwable
    //   8621	8632	8635	java/lang/Throwable
    //   8688	8702	8702	java/lang/Throwable
    //   8713	8726	8729	java/lang/Throwable
    //   8718	8741	8744	java/lang/Throwable
    //   8733	8759	8762	java/lang/Throwable
    //   8748	8789	8792	java/lang/Throwable
    //   8855	8882	8885	java/lang/Throwable
    //   8872	8900	8903	java/lang/Throwable
    //   8889	8930	8933	java/lang/Throwable
    //   8907	8941	8941	java/lang/Throwable
    //   8963	8974	8977	java/lang/Throwable
    //   8987	9717	10445	java/lang/Throwable
    //   9077	9091	9091	java/lang/Throwable
    //   9102	9115	9118	java/lang/Throwable
    //   9107	9130	9133	java/lang/Throwable
    //   9122	9148	9151	java/lang/Throwable
    //   9137	9178	9181	java/lang/Throwable
    //   9244	9271	9274	java/lang/Throwable
    //   9261	9289	9292	java/lang/Throwable
    //   9278	9319	9322	java/lang/Throwable
    //   9296	9330	9330	java/lang/Throwable
    //   9352	9363	9366	java/lang/Throwable
    //   9419	9433	9433	java/lang/Throwable
    //   9444	9457	9460	java/lang/Throwable
    //   9449	9472	9475	java/lang/Throwable
    //   9464	9490	9493	java/lang/Throwable
    //   9479	9520	9523	java/lang/Throwable
    //   9586	9613	9616	java/lang/Throwable
    //   9603	9631	9634	java/lang/Throwable
    //   9620	9661	9664	java/lang/Throwable
    //   9638	9672	9672	java/lang/Throwable
    //   9694	9705	9708	java/lang/Throwable
    //   9718	10444	10445	java/lang/Throwable
    //   9808	9822	9822	java/lang/Throwable
    //   9833	9846	9849	java/lang/Throwable
    //   9838	9861	9864	java/lang/Throwable
    //   9853	9879	9882	java/lang/Throwable
    //   9868	9909	9912	java/lang/Throwable
    //   9975	10002	10005	java/lang/Throwable
    //   9992	10020	10023	java/lang/Throwable
    //   10009	10050	10053	java/lang/Throwable
    //   10027	10061	10061	java/lang/Throwable
    //   10083	10094	10097	java/lang/Throwable
    //   10150	10164	10164	java/lang/Throwable
    //   10175	10188	10191	java/lang/Throwable
    //   10180	10203	10206	java/lang/Throwable
    //   10195	10221	10224	java/lang/Throwable
    //   10210	10251	10254	java/lang/Throwable
    //   10317	10344	10347	java/lang/Throwable
    //   10334	10362	10365	java/lang/Throwable
    //   10351	10392	10395	java/lang/Throwable
    //   10369	10403	10403	java/lang/Throwable
    //   10425	10436	10439	java/lang/Throwable
  }
  
  static void Zz(Object paramObject) {
    Zkv2.Z_ = a(2604, -8851);
    Zkv2.ZC = new BigInteger(a(2610, 23847));
    boolean bool = Zt2e.ZK();
    try {
      try {
        if (Ztte.ZD.charAt(Math.abs(((BigInteger)Zxsb.ZN).intValue() % 32)) > Ztes.Zo.charAt(Math.abs(((BigInteger)Zebj.Zf).intValue() % 32))) {
          try {
            Zrw7.ZT(Class.forName(a(2600, -28752)));
            if (bool)
              Zko9.ZX(Class.forName(a(2621, 16288))); 
          } catch (Throwable throwable) {
            throw a(null);
          } 
          return;
        } 
      } catch (Throwable throwable) {
        throw a(null);
      } 
      Zko9.ZX(Class.forName(a(2621, 16288)));
    } catch (Throwable throwable) {}
  }
  
  static void Zk(Object[] paramArrayOfObject, Object paramObject) throws Throwable {}
  
  static {
    // Byte code:
    //   0: bipush #31
    //   2: anewarray java/lang/String
    //   5: astore #5
    //   7: iconst_0
    //   8: istore_3
    //   9: ldc 'Eem\\t/I(j4\\tdt k%94twS{'\\r$}\\te6~Vv\\toR]\\tshM] \\f+kU4%OJ(J8g6i.#!,(_0[E7.G\\tm\\bYXS\\t3?RjE\\txyU|E??u\\tD{\\tsyh\\tQ"<J5??\\t5<\JE$\\t&^)f\\t"<*Y\\tPs\\t, HC+/\\tG-\\trW>PkoVyAQl\~ _^=IE)$L=D\\t8x~U\\tPucB\\ta1lw'
    //   11: dup
    //   12: astore_2
    //   13: invokevirtual length : ()I
    //   16: istore #4
    //   18: bipush #9
    //   20: istore_1
    //   21: iconst_m1
    //   22: istore_0
    //   23: bipush #33
    //   25: iinc #0, 1
    //   28: aload_2
    //   29: iload_0
    //   30: dup
    //   31: iload_1
    //   32: iadd
    //   33: invokevirtual substring : (II)Ljava/lang/String;
    //   36: iconst_m1
    //   37: goto -> 143
    //   40: aload #5
    //   42: swap
    //   43: iload_3
    //   44: iinc #3, 1
    //   47: swap
    //   48: aastore
    //   49: iload_0
    //   50: iload_1
    //   51: iadd
    //   52: dup
    //   53: istore_0
    //   54: iload #4
    //   56: if_icmpge -> 68
    //   59: aload_2
    //   60: iload_0
    //   61: invokevirtual charAt : (I)C
    //   64: istore_1
    //   65: goto -> 23
    //   68: ldc 'wRIZfRfSGz+ \pgz&mU{rrO#{V2-a0rO@EPYeh1P'
    //   70: dup
    //   71: astore_2
    //   72: invokevirtual length : ()I
    //   75: istore #4
    //   77: bipush #77
    //   79: istore_1
    //   80: iconst_m1
    //   81: istore_0
    //   82: bipush #118
    //   84: iinc #0, 1
    //   87: aload_2
    //   88: iload_0
    //   89: dup
    //   90: iload_1
    //   91: iadd
    //   92: invokevirtual substring : (II)Ljava/lang/String;
    //   95: iconst_0
    //   96: goto -> 143
    //   99: aload #5
    //   101: swap
    //   102: iload_3
    //   103: iinc #3, 1
    //   106: swap
    //   107: aastore
    //   108: iload_0
    //   109: iload_1
    //   110: iadd
    //   111: dup
    //   112: istore_0
    //   113: iload #4
    //   115: if_icmpge -> 127
    //   118: aload_2
    //   119: iload_0
    //   120: invokevirtual charAt : (I)C
    //   123: istore_1
    //   124: goto -> 82
    //   127: aload #5
    //   129: putstatic burp/Zgny.a : [Ljava/lang/String;
    //   132: bipush #31
    //   134: anewarray java/lang/String
    //   137: putstatic burp/Zgny.b : [Ljava/lang/String;
    //   140: goto -> 300
    //   143: dup_x2
    //   144: pop
    //   145: invokevirtual toCharArray : ()[C
    //   148: dup_x1
    //   149: arraylength
    //   150: dup_x2
    //   151: pop
    //   152: iconst_0
    //   153: istore #6
    //   155: dup2_x1
    //   156: pop2
    //   157: dup_x2
    //   158: iconst_1
    //   159: if_icmpgt -> 259
    //   162: dup2
    //   163: swap
    //   164: iload #6
    //   166: dup2_x1
    //   167: caload
    //   168: swap
    //   169: iload #6
    //   171: bipush #7
    //   173: irem
    //   174: tableswitch default -> 241, 0 -> 212, 1 -> 217, 2 -> 221, 3 -> 226, 4 -> 231, 5 -> 236
    //   212: bipush #53
    //   214: goto -> 243
    //   217: iconst_2
    //   218: goto -> 243
    //   221: bipush #101
    //   223: goto -> 243
    //   226: bipush #81
    //   228: goto -> 243
    //   231: bipush #118
    //   233: goto -> 243
    //   236: bipush #72
    //   238: goto -> 243
    //   241: bipush #122
    //   243: ixor
    //   244: ixor
    //   245: i2c
    //   246: castore
    //   247: iinc #6, 1
    //   250: dup
    //   251: ifne -> 259
    //   254: dup2
    //   255: dup_x1
    //   256: goto -> 166
    //   259: dup2_x1
    //   260: pop2
    //   261: dup_x2
    //   262: iload #6
    //   264: if_icmpgt -> 162
    //   267: pop
    //   268: new java/lang/String
    //   271: dup_x1
    //   272: swap
    //   273: invokespecial <init> : ([C)V
    //   276: invokevirtual intern : ()Ljava/lang/String;
    //   279: swap
    //   280: pop
    //   281: swap
    //   282: tableswitch default -> 40, 0 -> 99
    //   300: new java/math/BigInteger
    //   303: dup
    //   304: sipush #2601
    //   307: sipush #-16861
    //   310: invokestatic a : (II)Ljava/lang/String;
    //   313: invokespecial <init> : (Ljava/lang/String;)V
    //   316: putstatic burp/Zgny.ZR : Ljava/lang/Object;
    //   319: sipush #2615
    //   322: sipush #16725
    //   325: invokestatic a : (II)Ljava/lang/String;
    //   328: putstatic burp/Zgny.Zf : Ljava/lang/String;
    //   331: return
  }
  
  private static Throwable a(Throwable paramThrowable) {
    return paramThrowable;
  }
  
  private static String a(int paramInt1, int paramInt2) {
    int i = (paramInt1 ^ 0xA2F) & 0xFFFF;
    if (b[i] == null) {
      char[] arrayOfChar = a[i].toCharArray();
      switch (arrayOfChar[0] & 0xFF) {
        case 0:
        
        case 1:
        
        case 2:
        
        case 3:
        
        case 4:
        
        case 5:
        
        case 6:
        
        case 7:
        
        case 8:
        
        case 9:
        
        case 10:
        
        case 11:
        
        case 12:
        
        case 13:
        
        case 14:
        
        case 15:
        
        case 16:
        
        case 17:
        
        case 18:
        
        case 19:
        
        case 20:
        
        case 21:
        
        case 22:
        
        case 23:
        
        case 24:
        
        case 25:
        
        case 26:
        
        case 27:
        
        case 28:
        
        case 29:
        
        case 30:
        
        case 31:
        
        case 32:
        
        case 33:
        
        case 34:
        
        case 35:
        
        case 36:
        
        case 37:
        
        case 38:
        
        case 39:
        
        case 40:
        
        case 41:
        
        case 42:
        
        case 43:
        
        case 44:
        
        case 45:
        
        case 46:
        
        case 47:
        
        case 48:
        
        case 49:
        
        case 50:
        
        case 51:
        
        case 52:
        
        case 53:
        
        case 54:
        
        case 55:
        
        case 56:
        
        case 57:
        
        case 58:
        
        case 59:
        
        case 60:
        
        case 61:
        
        case 62:
        
        case 63:
        
        case 64:
        
        case 65:
        
        case 66:
        
        case 67:
        
        case 68:
        
        case 69:
        
        case 70:
        
        case 71:
        
        case 72:
        
        case 73:
        
        case 74:
        
        case 75:
        
        case 76:
        
        case 77:
        
        case 78:
        
        case 79:
        
        case 80:
        
        case 81:
        
        case 82:
        
        case 83:
        
        case 84:
        
        case 85:
        
        case 86:
        
        case 87:
        
        case 88:
        
        case 89:
        
        case 90:
        
        case 91:
        
        case 92:
        
        case 93:
        
        case 94:
        
        case 95:
        
        case 96:
        
        case 97:
        
        case 98:
        
        case 99:
        
        case 100:
        
        case 101:
        
        case 102:
        
        case 103:
        
        case 104:
        
        case 105:
        
        case 106:
        
        case 107:
        
        case 108:
        
        case 109:
        
        case 110:
        
        case 111:
        
        case 112:
        
        case 113:
        
        case 114:
        
        case 115:
        
        case 116:
        
        case 117:
        
        case 118:
        
        case 119:
        
        case 120:
        
        case 121:
        
        case 122:
        
        case 123:
        
        case 124:
        
        case 125:
        
        case 126:
        
        case 127:
        
        case 128:
        
        case 129:
        
        case 130:
        
        case 131:
        
        case 132:
        
        case 133:
        
        case 134:
        
        case 135:
        
        case 136:
        
        case 137:
        
        case 138:
        
        case 139:
        
        case 140:
        
        case 141:
        
        case 142:
        
        case 143:
        
        case 144:
        
        case 145:
        
        case 146:
        
        case 147:
        
        case 148:
        
        case 149:
        
        case 150:
        
        case 151:
        
        case 152:
        
        case 153:
        
        case 154:
        
        case 155:
        
        case 156:
        
        case 157:
        
        case 158:
        
        case 159:
        
        case 160:
        
        case 161:
        
        case 162:
        
        case 163:
        
        case 164:
        
        case 165:
        
        case 166:
        
        case 167:
        
        case 168:
        
        case 169:
        
        case 170:
        
        case 171:
        
        case 172:
        
        case 173:
        
        case 174:
        
        case 175:
        
        case 176:
        
        case 177:
        
        case 178:
        
        case 179:
        
        case 180:
        
        case 181:
        
        case 182:
        
        case 183:
        
        case 184:
        
        case 185:
        
        case 186:
        
        case 187:
        
        case 188:
        
        case 189:
        
        case 190:
        
        case 191:
        
        case 192:
        
        case 193:
        
        case 194:
        
        case 195:
        
        case 196:
        
        case 197:
        
        case 198:
        
        case 199:
        
        case 200:
        
        case 201:
        
        case 202:
        
        case 203:
        
        case 204:
        
        case 205:
        
        case 206:
        
        case 207:
        
        case 208:
        
        case 209:
        
        case 210:
        
        case 211:
        
        case 212:
        
        case 213:
        
        case 214:
        
        case 215:
        
        case 216:
        
        case 217:
        
        case 218:
        
        case 219:
        
        case 220:
        
        case 221:
        
        case 222:
        
        case 223:
        
        case 224:
        
        case 225:
        
        case 226:
        
        case 227:
        
        case 228:
        
        case 229:
        
        case 230:
        
        case 231:
        
        case 232:
        
        case 233:
        
        case 234:
        
        case 235:
        
        case 236:
        
        case 237:
        
        case 238:
        
        case 239:
        
        case 240:
        
        case 241:
        
        case 242:
        
        case 243:
        
        case 244:
        
        case 245:
        
        case 246:
        
        case 247:
        
        case 248:
        
        case 249:
        
        case 250:
        
        case 251:
        
        case 252:
        
        case 253:
        
        case 254:
        
        default:
          break;
      } 
      char c = '';
      int j = (paramInt2 & 0xFF) - c;
      if (j < 0)
        j += 256; 
      int k = ((paramInt2 & 0xFFFF) >>> 8) - c;
      if (k < 0)
        k += 256; 
      for (byte b = 0; b < arrayOfChar.length; b++) {
        int m = b % 2;
        if (m == 0) {
          arrayOfChar[b] = (char)(arrayOfChar[b] ^ j);
          j = ((j >>> 3 | j << 5) ^ arrayOfChar[b]) & 0xFF;
        } else {
          arrayOfChar[b] = (char)(arrayOfChar[b] ^ k);
          k = ((k >>> 3 | k << 5) ^ arrayOfChar[b]) & 0xFF;
        } 
      } 
      b[i] = (new String(arrayOfChar)).intern();
    } 
    return b[i];
  }
}


/* Location:              C:\Program Files\BurpSuitePro\burpsuite_pro.jar!\burp\Zgny.class
 * Java compiler version: 21 (65.0)
 * JD-Core Version:       1.1.3
 */