package burp;

import java.math.BigInteger;

class Zgqp extends ClassLoader {
  static Object Zf;
  
  static String ZA;
  
  private static final String[] a;
  
  private static final String[] b;
  
  static boolean ZR(Object[] paramArrayOfObject, Object paramObject) throws Throwable {
    // Byte code:
    //   0: invokestatic ZN : ()Z
    //   3: istore_2
    //   4: new java/lang/StringBuilder
    //   7: dup
    //   8: invokespecial <init> : ()V
    //   11: astore_3
    //   12: iconst_0
    //   13: istore #4
    //   15: iload #4
    //   17: bipush #32
    //   19: if_icmpge -> 1355
    //   22: iload #4
    //   24: tableswitch default -> 1348, 0 -> 168, 1 -> 205, 2 -> 242, 3 -> 279, 4 -> 316, 5 -> 353, 6 -> 390, 7 -> 427, 8 -> 464, 9 -> 501, 10 -> 538, 11 -> 575, 12 -> 612, 13 -> 649, 14 -> 686, 15 -> 723, 16 -> 760, 17 -> 797, 18 -> 834, 19 -> 871, 20 -> 908, 21 -> 945, 22 -> 982, 23 -> 1019, 24 -> 1056, 25 -> 1093, 26 -> 1130, 27 -> 1167, 28 -> 1204, 29 -> 1241, 30 -> 1278, 31 -> 1315
    //   168: aload_3
    //   169: getstatic burp/Ztgt.ZQ : Ljava/lang/String;
    //   172: getstatic burp/Zl8l.ZJ : Ljava/lang/Object;
    //   175: checkcast java/math/BigInteger
    //   178: invokevirtual intValue : ()I
    //   181: bipush #32
    //   183: irem
    //   184: invokestatic abs : (I)I
    //   187: invokevirtual charAt : (I)C
    //   190: invokevirtual append : (C)Ljava/lang/StringBuilder;
    //   193: pop
    //   194: iload_2
    //   195: ifne -> 1348
    //   198: goto -> 205
    //   201: invokestatic a : (Ljava/lang/Throwable;)Ljava/lang/Throwable;
    //   204: athrow
    //   205: aload_3
    //   206: getstatic burp/Zz4r.Zq : Ljava/lang/String;
    //   209: getstatic burp/Zgk1.ZD : Ljava/lang/Object;
    //   212: checkcast java/math/BigInteger
    //   215: invokevirtual intValue : ()I
    //   218: bipush #32
    //   220: irem
    //   221: invokestatic abs : (I)I
    //   224: invokevirtual charAt : (I)C
    //   227: invokevirtual append : (C)Ljava/lang/StringBuilder;
    //   230: pop
    //   231: iload_2
    //   232: ifne -> 1348
    //   235: goto -> 242
    //   238: invokestatic a : (Ljava/lang/Throwable;)Ljava/lang/Throwable;
    //   241: athrow
    //   242: aload_3
    //   243: getstatic burp/Zb8x.Zp : Ljava/lang/String;
    //   246: getstatic burp/Zs4v.ZB : Ljava/lang/Object;
    //   249: checkcast java/math/BigInteger
    //   252: invokevirtual intValue : ()I
    //   255: bipush #32
    //   257: irem
    //   258: invokestatic abs : (I)I
    //   261: invokevirtual charAt : (I)C
    //   264: invokevirtual append : (C)Ljava/lang/StringBuilder;
    //   267: pop
    //   268: iload_2
    //   269: ifne -> 1348
    //   272: goto -> 279
    //   275: invokestatic a : (Ljava/lang/Throwable;)Ljava/lang/Throwable;
    //   278: athrow
    //   279: aload_3
    //   280: getstatic burp/Zm54.Zg : Ljava/lang/String;
    //   283: getstatic burp/Ztjh.ZU : Ljava/lang/Object;
    //   286: checkcast java/math/BigInteger
    //   289: invokevirtual intValue : ()I
    //   292: bipush #32
    //   294: irem
    //   295: invokestatic abs : (I)I
    //   298: invokevirtual charAt : (I)C
    //   301: invokevirtual append : (C)Ljava/lang/StringBuilder;
    //   304: pop
    //   305: iload_2
    //   306: ifne -> 1348
    //   309: goto -> 316
    //   312: invokestatic a : (Ljava/lang/Throwable;)Ljava/lang/Throwable;
    //   315: athrow
    //   316: aload_3
    //   317: getstatic burp/Zg_y.ZF : Ljava/lang/String;
    //   320: getstatic burp/Zs4v.ZB : Ljava/lang/Object;
    //   323: checkcast java/math/BigInteger
    //   326: invokevirtual intValue : ()I
    //   329: bipush #32
    //   331: irem
    //   332: invokestatic abs : (I)I
    //   335: invokevirtual charAt : (I)C
    //   338: invokevirtual append : (C)Ljava/lang/StringBuilder;
    //   341: pop
    //   342: iload_2
    //   343: ifne -> 1348
    //   346: goto -> 353
    //   349: invokestatic a : (Ljava/lang/Throwable;)Ljava/lang/Throwable;
    //   352: athrow
    //   353: aload_3
    //   354: getstatic burp/Zlhk.Zb : Ljava/lang/String;
    //   357: getstatic burp/Zebu.Zu : Ljava/lang/Object;
    //   360: checkcast java/math/BigInteger
    //   363: invokevirtual intValue : ()I
    //   366: bipush #32
    //   368: irem
    //   369: invokestatic abs : (I)I
    //   372: invokevirtual charAt : (I)C
    //   375: invokevirtual append : (C)Ljava/lang/StringBuilder;
    //   378: pop
    //   379: iload_2
    //   380: ifne -> 1348
    //   383: goto -> 390
    //   386: invokestatic a : (Ljava/lang/Throwable;)Ljava/lang/Throwable;
    //   389: athrow
    //   390: aload_3
    //   391: getstatic burp/Zs4v.Za : Ljava/lang/String;
    //   394: getstatic burp/Zmcb.ZR : Ljava/lang/Object;
    //   397: checkcast java/math/BigInteger
    //   400: invokevirtual intValue : ()I
    //   403: bipush #32
    //   405: irem
    //   406: invokestatic abs : (I)I
    //   409: invokevirtual charAt : (I)C
    //   412: invokevirtual append : (C)Ljava/lang/StringBuilder;
    //   415: pop
    //   416: iload_2
    //   417: ifne -> 1348
    //   420: goto -> 427
    //   423: invokestatic a : (Ljava/lang/Throwable;)Ljava/lang/Throwable;
    //   426: athrow
    //   427: aload_3
    //   428: getstatic burp/Zlhk.Zb : Ljava/lang/String;
    //   431: getstatic burp/Zvof.Zl : Ljava/lang/Object;
    //   434: checkcast java/math/BigInteger
    //   437: invokevirtual intValue : ()I
    //   440: bipush #32
    //   442: irem
    //   443: invokestatic abs : (I)I
    //   446: invokevirtual charAt : (I)C
    //   449: invokevirtual append : (C)Ljava/lang/StringBuilder;
    //   452: pop
    //   453: iload_2
    //   454: ifne -> 1348
    //   457: goto -> 464
    //   460: invokestatic a : (Ljava/lang/Throwable;)Ljava/lang/Throwable;
    //   463: athrow
    //   464: aload_3
    //   465: getstatic burp/Zlqy.ZZ : Ljava/lang/String;
    //   468: getstatic burp/Zl55.ZZ : Ljava/lang/Object;
    //   471: checkcast java/math/BigInteger
    //   474: invokevirtual intValue : ()I
    //   477: bipush #32
    //   479: irem
    //   480: invokestatic abs : (I)I
    //   483: invokevirtual charAt : (I)C
    //   486: invokevirtual append : (C)Ljava/lang/StringBuilder;
    //   489: pop
    //   490: iload_2
    //   491: ifne -> 1348
    //   494: goto -> 501
    //   497: invokestatic a : (Ljava/lang/Throwable;)Ljava/lang/Throwable;
    //   500: athrow
    //   501: aload_3
    //   502: getstatic burp/Zsn6.Zs : Ljava/lang/String;
    //   505: getstatic burp/Zgil.ZG : Ljava/lang/Object;
    //   508: checkcast java/math/BigInteger
    //   511: invokevirtual intValue : ()I
    //   514: bipush #32
    //   516: irem
    //   517: invokestatic abs : (I)I
    //   520: invokevirtual charAt : (I)C
    //   523: invokevirtual append : (C)Ljava/lang/StringBuilder;
    //   526: pop
    //   527: iload_2
    //   528: ifne -> 1348
    //   531: goto -> 538
    //   534: invokestatic a : (Ljava/lang/Throwable;)Ljava/lang/Throwable;
    //   537: athrow
    //   538: aload_3
    //   539: getstatic burp/Zr3j.Zj : Ljava/lang/String;
    //   542: getstatic burp/Zb9d.Ze : Ljava/lang/Object;
    //   545: checkcast java/math/BigInteger
    //   548: invokevirtual intValue : ()I
    //   551: bipush #32
    //   553: irem
    //   554: invokestatic abs : (I)I
    //   557: invokevirtual charAt : (I)C
    //   560: invokevirtual append : (C)Ljava/lang/StringBuilder;
    //   563: pop
    //   564: iload_2
    //   565: ifne -> 1348
    //   568: goto -> 575
    //   571: invokestatic a : (Ljava/lang/Throwable;)Ljava/lang/Throwable;
    //   574: athrow
    //   575: aload_3
    //   576: getstatic burp/Zgqp.ZA : Ljava/lang/String;
    //   579: getstatic burp/Zx0t.Zt : Ljava/lang/Object;
    //   582: checkcast java/math/BigInteger
    //   585: invokevirtual intValue : ()I
    //   588: bipush #32
    //   590: irem
    //   591: invokestatic abs : (I)I
    //   594: invokevirtual charAt : (I)C
    //   597: invokevirtual append : (C)Ljava/lang/StringBuilder;
    //   600: pop
    //   601: iload_2
    //   602: ifne -> 1348
    //   605: goto -> 612
    //   608: invokestatic a : (Ljava/lang/Throwable;)Ljava/lang/Throwable;
    //   611: athrow
    //   612: aload_3
    //   613: getstatic burp/Zzx8.Z_ : Ljava/lang/String;
    //   616: getstatic burp/Zz5h.ZD : Ljava/lang/Object;
    //   619: checkcast java/math/BigInteger
    //   622: invokevirtual intValue : ()I
    //   625: bipush #32
    //   627: irem
    //   628: invokestatic abs : (I)I
    //   631: invokevirtual charAt : (I)C
    //   634: invokevirtual append : (C)Ljava/lang/StringBuilder;
    //   637: pop
    //   638: iload_2
    //   639: ifne -> 1348
    //   642: goto -> 649
    //   645: invokestatic a : (Ljava/lang/Throwable;)Ljava/lang/Throwable;
    //   648: athrow
    //   649: aload_3
    //   650: getstatic burp/Zxzt.ZG : Ljava/lang/String;
    //   653: getstatic burp/Zeyd.Zl : Ljava/lang/Object;
    //   656: checkcast java/math/BigInteger
    //   659: invokevirtual intValue : ()I
    //   662: bipush #32
    //   664: irem
    //   665: invokestatic abs : (I)I
    //   668: invokevirtual charAt : (I)C
    //   671: invokevirtual append : (C)Ljava/lang/StringBuilder;
    //   674: pop
    //   675: iload_2
    //   676: ifne -> 1348
    //   679: goto -> 686
    //   682: invokestatic a : (Ljava/lang/Throwable;)Ljava/lang/Throwable;
    //   685: athrow
    //   686: aload_3
    //   687: getstatic burp/Zz80.Ze : Ljava/lang/String;
    //   690: getstatic burp/Zxti.ZJ : Ljava/lang/Object;
    //   693: checkcast java/math/BigInteger
    //   696: invokevirtual intValue : ()I
    //   699: bipush #32
    //   701: irem
    //   702: invokestatic abs : (I)I
    //   705: invokevirtual charAt : (I)C
    //   708: invokevirtual append : (C)Ljava/lang/StringBuilder;
    //   711: pop
    //   712: iload_2
    //   713: ifne -> 1348
    //   716: goto -> 723
    //   719: invokestatic a : (Ljava/lang/Throwable;)Ljava/lang/Throwable;
    //   722: athrow
    //   723: aload_3
    //   724: getstatic burp/Zk52.ZL : Ljava/lang/String;
    //   727: getstatic burp/Zz80.ZR : Ljava/lang/Object;
    //   730: checkcast java/math/BigInteger
    //   733: invokevirtual intValue : ()I
    //   736: bipush #32
    //   738: irem
    //   739: invokestatic abs : (I)I
    //   742: invokevirtual charAt : (I)C
    //   745: invokevirtual append : (C)Ljava/lang/StringBuilder;
    //   748: pop
    //   749: iload_2
    //   750: ifne -> 1348
    //   753: goto -> 760
    //   756: invokestatic a : (Ljava/lang/Throwable;)Ljava/lang/Throwable;
    //   759: athrow
    //   760: aload_3
    //   761: getstatic burp/Zlfg.Zb : Ljava/lang/String;
    //   764: getstatic burp/Zep1.ZW : Ljava/lang/Object;
    //   767: checkcast java/math/BigInteger
    //   770: invokevirtual intValue : ()I
    //   773: bipush #32
    //   775: irem
    //   776: invokestatic abs : (I)I
    //   779: invokevirtual charAt : (I)C
    //   782: invokevirtual append : (C)Ljava/lang/StringBuilder;
    //   785: pop
    //   786: iload_2
    //   787: ifne -> 1348
    //   790: goto -> 797
    //   793: invokestatic a : (Ljava/lang/Throwable;)Ljava/lang/Throwable;
    //   796: athrow
    //   797: aload_3
    //   798: getstatic burp/Zrc0.ZL : Ljava/lang/String;
    //   801: getstatic burp/Zlqq.ZV : Ljava/lang/Object;
    //   804: checkcast java/math/BigInteger
    //   807: invokevirtual intValue : ()I
    //   810: bipush #32
    //   812: irem
    //   813: invokestatic abs : (I)I
    //   816: invokevirtual charAt : (I)C
    //   819: invokevirtual append : (C)Ljava/lang/StringBuilder;
    //   822: pop
    //   823: iload_2
    //   824: ifne -> 1348
    //   827: goto -> 834
    //   830: invokestatic a : (Ljava/lang/Throwable;)Ljava/lang/Throwable;
    //   833: athrow
    //   834: aload_3
    //   835: getstatic burp/Zgfq.Zn : Ljava/lang/String;
    //   838: getstatic burp/Zge1.ZK : Ljava/lang/Object;
    //   841: checkcast java/math/BigInteger
    //   844: invokevirtual intValue : ()I
    //   847: bipush #32
    //   849: irem
    //   850: invokestatic abs : (I)I
    //   853: invokevirtual charAt : (I)C
    //   856: invokevirtual append : (C)Ljava/lang/StringBuilder;
    //   859: pop
    //   860: iload_2
    //   861: ifne -> 1348
    //   864: goto -> 871
    //   867: invokestatic a : (Ljava/lang/Throwable;)Ljava/lang/Throwable;
    //   870: athrow
    //   871: aload_3
    //   872: getstatic burp/Zeyd.Zr : Ljava/lang/String;
    //   875: getstatic burp/Ztvn.Zl : Ljava/lang/Object;
    //   878: checkcast java/math/BigInteger
    //   881: invokevirtual intValue : ()I
    //   884: bipush #32
    //   886: irem
    //   887: invokestatic abs : (I)I
    //   890: invokevirtual charAt : (I)C
    //   893: invokevirtual append : (C)Ljava/lang/StringBuilder;
    //   896: pop
    //   897: iload_2
    //   898: ifne -> 1348
    //   901: goto -> 908
    //   904: invokestatic a : (Ljava/lang/Throwable;)Ljava/lang/Throwable;
    //   907: athrow
    //   908: aload_3
    //   909: getstatic burp/Zsji.Zr : Ljava/lang/String;
    //   912: getstatic burp/Zbf9.ZC : Ljava/lang/Object;
    //   915: checkcast java/math/BigInteger
    //   918: invokevirtual intValue : ()I
    //   921: bipush #32
    //   923: irem
    //   924: invokestatic abs : (I)I
    //   927: invokevirtual charAt : (I)C
    //   930: invokevirtual append : (C)Ljava/lang/StringBuilder;
    //   933: pop
    //   934: iload_2
    //   935: ifne -> 1348
    //   938: goto -> 945
    //   941: invokestatic a : (Ljava/lang/Throwable;)Ljava/lang/Throwable;
    //   944: athrow
    //   945: aload_3
    //   946: getstatic burp/Zep8.ZC : Ljava/lang/String;
    //   949: getstatic burp/Zsn6.Zo : Ljava/lang/Object;
    //   952: checkcast java/math/BigInteger
    //   955: invokevirtual intValue : ()I
    //   958: bipush #32
    //   960: irem
    //   961: invokestatic abs : (I)I
    //   964: invokevirtual charAt : (I)C
    //   967: invokevirtual append : (C)Ljava/lang/StringBuilder;
    //   970: pop
    //   971: iload_2
    //   972: ifne -> 1348
    //   975: goto -> 982
    //   978: invokestatic a : (Ljava/lang/Throwable;)Ljava/lang/Throwable;
    //   981: athrow
    //   982: aload_3
    //   983: getstatic burp/Zgil.ZK : Ljava/lang/String;
    //   986: getstatic burp/Zlqy.ZP : Ljava/lang/Object;
    //   989: checkcast java/math/BigInteger
    //   992: invokevirtual intValue : ()I
    //   995: bipush #32
    //   997: irem
    //   998: invokestatic abs : (I)I
    //   1001: invokevirtual charAt : (I)C
    //   1004: invokevirtual append : (C)Ljava/lang/StringBuilder;
    //   1007: pop
    //   1008: iload_2
    //   1009: ifne -> 1348
    //   1012: goto -> 1019
    //   1015: invokestatic a : (Ljava/lang/Throwable;)Ljava/lang/Throwable;
    //   1018: athrow
    //   1019: aload_3
    //   1020: getstatic burp/Zr64.Zj : Ljava/lang/String;
    //   1023: getstatic burp/Zmwu.Zy : Ljava/lang/Object;
    //   1026: checkcast java/math/BigInteger
    //   1029: invokevirtual intValue : ()I
    //   1032: bipush #32
    //   1034: irem
    //   1035: invokestatic abs : (I)I
    //   1038: invokevirtual charAt : (I)C
    //   1041: invokevirtual append : (C)Ljava/lang/StringBuilder;
    //   1044: pop
    //   1045: iload_2
    //   1046: ifne -> 1348
    //   1049: goto -> 1056
    //   1052: invokestatic a : (Ljava/lang/Throwable;)Ljava/lang/Throwable;
    //   1055: athrow
    //   1056: aload_3
    //   1057: getstatic burp/Zkup.Zr : Ljava/lang/String;
    //   1060: getstatic burp/Zm54.ZS : Ljava/lang/Object;
    //   1063: checkcast java/math/BigInteger
    //   1066: invokevirtual intValue : ()I
    //   1069: bipush #32
    //   1071: irem
    //   1072: invokestatic abs : (I)I
    //   1075: invokevirtual charAt : (I)C
    //   1078: invokevirtual append : (C)Ljava/lang/StringBuilder;
    //   1081: pop
    //   1082: iload_2
    //   1083: ifne -> 1348
    //   1086: goto -> 1093
    //   1089: invokestatic a : (Ljava/lang/Throwable;)Ljava/lang/Throwable;
    //   1092: athrow
    //   1093: aload_3
    //   1094: getstatic burp/Zgb9.Zk : Ljava/lang/String;
    //   1097: getstatic burp/Zgz2.Zs : Ljava/lang/Object;
    //   1100: checkcast java/math/BigInteger
    //   1103: invokevirtual intValue : ()I
    //   1106: bipush #32
    //   1108: irem
    //   1109: invokestatic abs : (I)I
    //   1112: invokevirtual charAt : (I)C
    //   1115: invokevirtual append : (C)Ljava/lang/StringBuilder;
    //   1118: pop
    //   1119: iload_2
    //   1120: ifne -> 1348
    //   1123: goto -> 1130
    //   1126: invokestatic a : (Ljava/lang/Throwable;)Ljava/lang/Throwable;
    //   1129: athrow
    //   1130: aload_3
    //   1131: getstatic burp/Zrc0.ZL : Ljava/lang/String;
    //   1134: getstatic burp/Zg_y.ZR : Ljava/lang/Object;
    //   1137: checkcast java/math/BigInteger
    //   1140: invokevirtual intValue : ()I
    //   1143: bipush #32
    //   1145: irem
    //   1146: invokestatic abs : (I)I
    //   1149: invokevirtual charAt : (I)C
    //   1152: invokevirtual append : (C)Ljava/lang/StringBuilder;
    //   1155: pop
    //   1156: iload_2
    //   1157: ifne -> 1348
    //   1160: goto -> 1167
    //   1163: invokestatic a : (Ljava/lang/Throwable;)Ljava/lang/Throwable;
    //   1166: athrow
    //   1167: aload_3
    //   1168: getstatic burp/Zg8.ZE : Ljava/lang/String;
    //   1171: getstatic burp/Zzuh.ZV : Ljava/lang/Object;
    //   1174: checkcast java/math/BigInteger
    //   1177: invokevirtual intValue : ()I
    //   1180: bipush #32
    //   1182: irem
    //   1183: invokestatic abs : (I)I
    //   1186: invokevirtual charAt : (I)C
    //   1189: invokevirtual append : (C)Ljava/lang/StringBuilder;
    //   1192: pop
    //   1193: iload_2
    //   1194: ifne -> 1348
    //   1197: goto -> 1204
    //   1200: invokestatic a : (Ljava/lang/Throwable;)Ljava/lang/Throwable;
    //   1203: athrow
    //   1204: aload_3
    //   1205: getstatic burp/Zvof.ZR : Ljava/lang/String;
    //   1208: getstatic burp/Zeoa.ZF : Ljava/lang/Object;
    //   1211: checkcast java/math/BigInteger
    //   1214: invokevirtual intValue : ()I
    //   1217: bipush #32
    //   1219: irem
    //   1220: invokestatic abs : (I)I
    //   1223: invokevirtual charAt : (I)C
    //   1226: invokevirtual append : (C)Ljava/lang/StringBuilder;
    //   1229: pop
    //   1230: iload_2
    //   1231: ifne -> 1348
    //   1234: goto -> 1241
    //   1237: invokestatic a : (Ljava/lang/Throwable;)Ljava/lang/Throwable;
    //   1240: athrow
    //   1241: aload_3
    //   1242: getstatic burp/Zvof.ZR : Ljava/lang/String;
    //   1245: getstatic burp/Zgz2.Zs : Ljava/lang/Object;
    //   1248: checkcast java/math/BigInteger
    //   1251: invokevirtual intValue : ()I
    //   1254: bipush #32
    //   1256: irem
    //   1257: invokestatic abs : (I)I
    //   1260: invokevirtual charAt : (I)C
    //   1263: invokevirtual append : (C)Ljava/lang/StringBuilder;
    //   1266: pop
    //   1267: iload_2
    //   1268: ifne -> 1348
    //   1271: goto -> 1278
    //   1274: invokestatic a : (Ljava/lang/Throwable;)Ljava/lang/Throwable;
    //   1277: athrow
    //   1278: aload_3
    //   1279: getstatic burp/Zzuh.ZX : Ljava/lang/String;
    //   1282: getstatic burp/Zvof.Zl : Ljava/lang/Object;
    //   1285: checkcast java/math/BigInteger
    //   1288: invokevirtual intValue : ()I
    //   1291: bipush #32
    //   1293: irem
    //   1294: invokestatic abs : (I)I
    //   1297: invokevirtual charAt : (I)C
    //   1300: invokevirtual append : (C)Ljava/lang/StringBuilder;
    //   1303: pop
    //   1304: iload_2
    //   1305: ifne -> 1348
    //   1308: goto -> 1315
    //   1311: invokestatic a : (Ljava/lang/Throwable;)Ljava/lang/Throwable;
    //   1314: athrow
    //   1315: aload_3
    //   1316: getstatic burp/Zep8.ZC : Ljava/lang/String;
    //   1319: getstatic burp/Zr_z.ZT : Ljava/lang/Object;
    //   1322: checkcast java/math/BigInteger
    //   1325: invokevirtual intValue : ()I
    //   1328: bipush #32
    //   1330: irem
    //   1331: invokestatic abs : (I)I
    //   1334: invokevirtual charAt : (I)C
    //   1337: invokevirtual append : (C)Ljava/lang/StringBuilder;
    //   1340: pop
    //   1341: goto -> 1348
    //   1344: invokestatic a : (Ljava/lang/Throwable;)Ljava/lang/Throwable;
    //   1347: athrow
    //   1348: iinc #4, 1
    //   1351: iload_2
    //   1352: ifne -> 15
    //   1355: aload_3
    //   1356: invokevirtual toString : ()Ljava/lang/String;
    //   1359: putstatic burp/Zltp.ZY : Ljava/lang/String;
    //   1362: new java/lang/StringBuilder
    //   1365: dup
    //   1366: invokespecial <init> : ()V
    //   1369: astore #4
    //   1371: iconst_0
    //   1372: istore #5
    //   1374: iload #5
    //   1376: bipush #32
    //   1378: if_icmpge -> 2743
    //   1381: iload #5
    //   1383: tableswitch default -> 2736, 0 -> 1524, 1 -> 1562, 2 -> 1600, 3 -> 1638, 4 -> 1676, 5 -> 1714, 6 -> 1752, 7 -> 1790, 8 -> 1828, 9 -> 1866, 10 -> 1904, 11 -> 1942, 12 -> 1980, 13 -> 2018, 14 -> 2056, 15 -> 2094, 16 -> 2132, 17 -> 2170, 18 -> 2208, 19 -> 2246, 20 -> 2284, 21 -> 2322, 22 -> 2360, 23 -> 2398, 24 -> 2436, 25 -> 2474, 26 -> 2512, 27 -> 2550, 28 -> 2588, 29 -> 2626, 30 -> 2664, 31 -> 2702
    //   1524: aload #4
    //   1526: getstatic burp/Zxti.ZD : Ljava/lang/String;
    //   1529: getstatic burp/Zrc0.Zz : Ljava/lang/Object;
    //   1532: checkcast java/math/BigInteger
    //   1535: invokevirtual intValue : ()I
    //   1538: bipush #32
    //   1540: irem
    //   1541: invokestatic abs : (I)I
    //   1544: invokevirtual charAt : (I)C
    //   1547: invokevirtual append : (C)Ljava/lang/StringBuilder;
    //   1550: pop
    //   1551: iload_2
    //   1552: ifne -> 2736
    //   1555: goto -> 1562
    //   1558: invokestatic a : (Ljava/lang/Throwable;)Ljava/lang/Throwable;
    //   1561: athrow
    //   1562: aload #4
    //   1564: getstatic burp/Zrug.Zq : Ljava/lang/String;
    //   1567: getstatic burp/Zxzt.ZY : Ljava/lang/Object;
    //   1570: checkcast java/math/BigInteger
    //   1573: invokevirtual intValue : ()I
    //   1576: bipush #32
    //   1578: irem
    //   1579: invokestatic abs : (I)I
    //   1582: invokevirtual charAt : (I)C
    //   1585: invokevirtual append : (C)Ljava/lang/StringBuilder;
    //   1588: pop
    //   1589: iload_2
    //   1590: ifne -> 2736
    //   1593: goto -> 1600
    //   1596: invokestatic a : (Ljava/lang/Throwable;)Ljava/lang/Throwable;
    //   1599: athrow
    //   1600: aload #4
    //   1602: getstatic burp/Zlqy.ZZ : Ljava/lang/String;
    //   1605: getstatic burp/Zep1.ZW : Ljava/lang/Object;
    //   1608: checkcast java/math/BigInteger
    //   1611: invokevirtual intValue : ()I
    //   1614: bipush #32
    //   1616: irem
    //   1617: invokestatic abs : (I)I
    //   1620: invokevirtual charAt : (I)C
    //   1623: invokevirtual append : (C)Ljava/lang/StringBuilder;
    //   1626: pop
    //   1627: iload_2
    //   1628: ifne -> 2736
    //   1631: goto -> 1638
    //   1634: invokestatic a : (Ljava/lang/Throwable;)Ljava/lang/Throwable;
    //   1637: athrow
    //   1638: aload #4
    //   1640: getstatic burp/Zrug.Zq : Ljava/lang/String;
    //   1643: getstatic burp/Zlfg.Zv : Ljava/lang/Object;
    //   1646: checkcast java/math/BigInteger
    //   1649: invokevirtual intValue : ()I
    //   1652: bipush #32
    //   1654: irem
    //   1655: invokestatic abs : (I)I
    //   1658: invokevirtual charAt : (I)C
    //   1661: invokevirtual append : (C)Ljava/lang/StringBuilder;
    //   1664: pop
    //   1665: iload_2
    //   1666: ifne -> 2736
    //   1669: goto -> 1676
    //   1672: invokestatic a : (Ljava/lang/Throwable;)Ljava/lang/Throwable;
    //   1675: athrow
    //   1676: aload #4
    //   1678: getstatic burp/Zl55.Zp : Ljava/lang/String;
    //   1681: getstatic burp/Zmwx.Zk : Ljava/lang/Object;
    //   1684: checkcast java/math/BigInteger
    //   1687: invokevirtual intValue : ()I
    //   1690: bipush #32
    //   1692: irem
    //   1693: invokestatic abs : (I)I
    //   1696: invokevirtual charAt : (I)C
    //   1699: invokevirtual append : (C)Ljava/lang/StringBuilder;
    //   1702: pop
    //   1703: iload_2
    //   1704: ifne -> 2736
    //   1707: goto -> 1714
    //   1710: invokestatic a : (Ljava/lang/Throwable;)Ljava/lang/Throwable;
    //   1713: athrow
    //   1714: aload #4
    //   1716: getstatic burp/Zr64.Zj : Ljava/lang/String;
    //   1719: getstatic burp/Zgqp.Zf : Ljava/lang/Object;
    //   1722: checkcast java/math/BigInteger
    //   1725: invokevirtual intValue : ()I
    //   1728: bipush #32
    //   1730: irem
    //   1731: invokestatic abs : (I)I
    //   1734: invokevirtual charAt : (I)C
    //   1737: invokevirtual append : (C)Ljava/lang/StringBuilder;
    //   1740: pop
    //   1741: iload_2
    //   1742: ifne -> 2736
    //   1745: goto -> 1752
    //   1748: invokestatic a : (Ljava/lang/Throwable;)Ljava/lang/Throwable;
    //   1751: athrow
    //   1752: aload #4
    //   1754: getstatic burp/Zkw.ZU : Ljava/lang/String;
    //   1757: getstatic burp/Zm54.ZS : Ljava/lang/Object;
    //   1760: checkcast java/math/BigInteger
    //   1763: invokevirtual intValue : ()I
    //   1766: bipush #32
    //   1768: irem
    //   1769: invokestatic abs : (I)I
    //   1772: invokevirtual charAt : (I)C
    //   1775: invokevirtual append : (C)Ljava/lang/StringBuilder;
    //   1778: pop
    //   1779: iload_2
    //   1780: ifne -> 2736
    //   1783: goto -> 1790
    //   1786: invokestatic a : (Ljava/lang/Throwable;)Ljava/lang/Throwable;
    //   1789: athrow
    //   1790: aload #4
    //   1792: getstatic burp/Zgz2.ZI : Ljava/lang/String;
    //   1795: getstatic burp/Zb8x.Zz : Ljava/lang/Object;
    //   1798: checkcast java/math/BigInteger
    //   1801: invokevirtual intValue : ()I
    //   1804: bipush #32
    //   1806: irem
    //   1807: invokestatic abs : (I)I
    //   1810: invokevirtual charAt : (I)C
    //   1813: invokevirtual append : (C)Ljava/lang/StringBuilder;
    //   1816: pop
    //   1817: iload_2
    //   1818: ifne -> 2736
    //   1821: goto -> 1828
    //   1824: invokestatic a : (Ljava/lang/Throwable;)Ljava/lang/Throwable;
    //   1827: athrow
    //   1828: aload #4
    //   1830: getstatic burp/Zs4v.Za : Ljava/lang/String;
    //   1833: getstatic burp/Zebu.Zu : Ljava/lang/Object;
    //   1836: checkcast java/math/BigInteger
    //   1839: invokevirtual intValue : ()I
    //   1842: bipush #32
    //   1844: irem
    //   1845: invokestatic abs : (I)I
    //   1848: invokevirtual charAt : (I)C
    //   1851: invokevirtual append : (C)Ljava/lang/StringBuilder;
    //   1854: pop
    //   1855: iload_2
    //   1856: ifne -> 2736
    //   1859: goto -> 1866
    //   1862: invokestatic a : (Ljava/lang/Throwable;)Ljava/lang/Throwable;
    //   1865: athrow
    //   1866: aload #4
    //   1868: getstatic burp/Zm3s.Ze : Ljava/lang/String;
    //   1871: getstatic burp/Zgil.ZG : Ljava/lang/Object;
    //   1874: checkcast java/math/BigInteger
    //   1877: invokevirtual intValue : ()I
    //   1880: bipush #32
    //   1882: irem
    //   1883: invokestatic abs : (I)I
    //   1886: invokevirtual charAt : (I)C
    //   1889: invokevirtual append : (C)Ljava/lang/StringBuilder;
    //   1892: pop
    //   1893: iload_2
    //   1894: ifne -> 2736
    //   1897: goto -> 1904
    //   1900: invokestatic a : (Ljava/lang/Throwable;)Ljava/lang/Throwable;
    //   1903: athrow
    //   1904: aload #4
    //   1906: getstatic burp/Zssb.ZY : Ljava/lang/String;
    //   1909: getstatic burp/Zeyd.Zl : Ljava/lang/Object;
    //   1912: checkcast java/math/BigInteger
    //   1915: invokevirtual intValue : ()I
    //   1918: bipush #32
    //   1920: irem
    //   1921: invokestatic abs : (I)I
    //   1924: invokevirtual charAt : (I)C
    //   1927: invokevirtual append : (C)Ljava/lang/StringBuilder;
    //   1930: pop
    //   1931: iload_2
    //   1932: ifne -> 2736
    //   1935: goto -> 1942
    //   1938: invokestatic a : (Ljava/lang/Throwable;)Ljava/lang/Throwable;
    //   1941: athrow
    //   1942: aload #4
    //   1944: getstatic burp/Zl8l.ZG : Ljava/lang/String;
    //   1947: getstatic burp/Zlhk.ZD : Ljava/lang/Object;
    //   1950: checkcast java/math/BigInteger
    //   1953: invokevirtual intValue : ()I
    //   1956: bipush #32
    //   1958: irem
    //   1959: invokestatic abs : (I)I
    //   1962: invokevirtual charAt : (I)C
    //   1965: invokevirtual append : (C)Ljava/lang/StringBuilder;
    //   1968: pop
    //   1969: iload_2
    //   1970: ifne -> 2736
    //   1973: goto -> 1980
    //   1976: invokestatic a : (Ljava/lang/Throwable;)Ljava/lang/Throwable;
    //   1979: athrow
    //   1980: aload #4
    //   1982: getstatic burp/Zrug.Zq : Ljava/lang/String;
    //   1985: getstatic burp/Ztgt.ZU : Ljava/lang/Object;
    //   1988: checkcast java/math/BigInteger
    //   1991: invokevirtual intValue : ()I
    //   1994: bipush #32
    //   1996: irem
    //   1997: invokestatic abs : (I)I
    //   2000: invokevirtual charAt : (I)C
    //   2003: invokevirtual append : (C)Ljava/lang/StringBuilder;
    //   2006: pop
    //   2007: iload_2
    //   2008: ifne -> 2736
    //   2011: goto -> 2018
    //   2014: invokestatic a : (Ljava/lang/Throwable;)Ljava/lang/Throwable;
    //   2017: athrow
    //   2018: aload #4
    //   2020: getstatic burp/Zgl4.ZX : Ljava/lang/String;
    //   2023: getstatic burp/Ze6t.Zu : Ljava/lang/Object;
    //   2026: checkcast java/math/BigInteger
    //   2029: invokevirtual intValue : ()I
    //   2032: bipush #32
    //   2034: irem
    //   2035: invokestatic abs : (I)I
    //   2038: invokevirtual charAt : (I)C
    //   2041: invokevirtual append : (C)Ljava/lang/StringBuilder;
    //   2044: pop
    //   2045: iload_2
    //   2046: ifne -> 2736
    //   2049: goto -> 2056
    //   2052: invokestatic a : (Ljava/lang/Throwable;)Ljava/lang/Throwable;
    //   2055: athrow
    //   2056: aload #4
    //   2058: getstatic burp/Zgz2.ZI : Ljava/lang/String;
    //   2061: getstatic burp/Zrdo.ZK : Ljava/lang/Object;
    //   2064: checkcast java/math/BigInteger
    //   2067: invokevirtual intValue : ()I
    //   2070: bipush #32
    //   2072: irem
    //   2073: invokestatic abs : (I)I
    //   2076: invokevirtual charAt : (I)C
    //   2079: invokevirtual append : (C)Ljava/lang/StringBuilder;
    //   2082: pop
    //   2083: iload_2
    //   2084: ifne -> 2736
    //   2087: goto -> 2094
    //   2090: invokestatic a : (Ljava/lang/Throwable;)Ljava/lang/Throwable;
    //   2093: athrow
    //   2094: aload #4
    //   2096: getstatic burp/Zmwx.ZB : Ljava/lang/String;
    //   2099: getstatic burp/Zmwx.Zk : Ljava/lang/Object;
    //   2102: checkcast java/math/BigInteger
    //   2105: invokevirtual intValue : ()I
    //   2108: bipush #32
    //   2110: irem
    //   2111: invokestatic abs : (I)I
    //   2114: invokevirtual charAt : (I)C
    //   2117: invokevirtual append : (C)Ljava/lang/StringBuilder;
    //   2120: pop
    //   2121: iload_2
    //   2122: ifne -> 2736
    //   2125: goto -> 2132
    //   2128: invokestatic a : (Ljava/lang/Throwable;)Ljava/lang/Throwable;
    //   2131: athrow
    //   2132: aload #4
    //   2134: getstatic burp/Ze6t.ZR : Ljava/lang/String;
    //   2137: getstatic burp/Zstq.Zf : Ljava/lang/Object;
    //   2140: checkcast java/math/BigInteger
    //   2143: invokevirtual intValue : ()I
    //   2146: bipush #32
    //   2148: irem
    //   2149: invokestatic abs : (I)I
    //   2152: invokevirtual charAt : (I)C
    //   2155: invokevirtual append : (C)Ljava/lang/StringBuilder;
    //   2158: pop
    //   2159: iload_2
    //   2160: ifne -> 2736
    //   2163: goto -> 2170
    //   2166: invokestatic a : (Ljava/lang/Throwable;)Ljava/lang/Throwable;
    //   2169: athrow
    //   2170: aload #4
    //   2172: getstatic burp/Zb1.Z_ : Ljava/lang/String;
    //   2175: getstatic burp/Zz5h.ZD : Ljava/lang/Object;
    //   2178: checkcast java/math/BigInteger
    //   2181: invokevirtual intValue : ()I
    //   2184: bipush #32
    //   2186: irem
    //   2187: invokestatic abs : (I)I
    //   2190: invokevirtual charAt : (I)C
    //   2193: invokevirtual append : (C)Ljava/lang/StringBuilder;
    //   2196: pop
    //   2197: iload_2
    //   2198: ifne -> 2736
    //   2201: goto -> 2208
    //   2204: invokestatic a : (Ljava/lang/Throwable;)Ljava/lang/Throwable;
    //   2207: athrow
    //   2208: aload #4
    //   2210: getstatic burp/Zge1.Zx : Ljava/lang/String;
    //   2213: getstatic burp/Zl55.ZZ : Ljava/lang/Object;
    //   2216: checkcast java/math/BigInteger
    //   2219: invokevirtual intValue : ()I
    //   2222: bipush #32
    //   2224: irem
    //   2225: invokestatic abs : (I)I
    //   2228: invokevirtual charAt : (I)C
    //   2231: invokevirtual append : (C)Ljava/lang/StringBuilder;
    //   2234: pop
    //   2235: iload_2
    //   2236: ifne -> 2736
    //   2239: goto -> 2246
    //   2242: invokestatic a : (Ljava/lang/Throwable;)Ljava/lang/Throwable;
    //   2245: athrow
    //   2246: aload #4
    //   2248: getstatic burp/Zx0t.Ze : Ljava/lang/String;
    //   2251: getstatic burp/Zeyd.Zl : Ljava/lang/Object;
    //   2254: checkcast java/math/BigInteger
    //   2257: invokevirtual intValue : ()I
    //   2260: bipush #32
    //   2262: irem
    //   2263: invokestatic abs : (I)I
    //   2266: invokevirtual charAt : (I)C
    //   2269: invokevirtual append : (C)Ljava/lang/StringBuilder;
    //   2272: pop
    //   2273: iload_2
    //   2274: ifne -> 2736
    //   2277: goto -> 2284
    //   2280: invokestatic a : (Ljava/lang/Throwable;)Ljava/lang/Throwable;
    //   2283: athrow
    //   2284: aload #4
    //   2286: getstatic burp/Zbu6.ZQ : Ljava/lang/String;
    //   2289: getstatic burp/Zgh3.ZZ : Ljava/lang/Object;
    //   2292: checkcast java/math/BigInteger
    //   2295: invokevirtual intValue : ()I
    //   2298: bipush #32
    //   2300: irem
    //   2301: invokestatic abs : (I)I
    //   2304: invokevirtual charAt : (I)C
    //   2307: invokevirtual append : (C)Ljava/lang/StringBuilder;
    //   2310: pop
    //   2311: iload_2
    //   2312: ifne -> 2736
    //   2315: goto -> 2322
    //   2318: invokestatic a : (Ljava/lang/Throwable;)Ljava/lang/Throwable;
    //   2321: athrow
    //   2322: aload #4
    //   2324: getstatic burp/Zl8l.ZG : Ljava/lang/String;
    //   2327: getstatic burp/Zb8x.Zz : Ljava/lang/Object;
    //   2330: checkcast java/math/BigInteger
    //   2333: invokevirtual intValue : ()I
    //   2336: bipush #32
    //   2338: irem
    //   2339: invokestatic abs : (I)I
    //   2342: invokevirtual charAt : (I)C
    //   2345: invokevirtual append : (C)Ljava/lang/StringBuilder;
    //   2348: pop
    //   2349: iload_2
    //   2350: ifne -> 2736
    //   2353: goto -> 2360
    //   2356: invokestatic a : (Ljava/lang/Throwable;)Ljava/lang/Throwable;
    //   2359: athrow
    //   2360: aload #4
    //   2362: getstatic burp/Zz5h.Zk : Ljava/lang/String;
    //   2365: getstatic burp/Zr3j.ZT : Ljava/lang/Object;
    //   2368: checkcast java/math/BigInteger
    //   2371: invokevirtual intValue : ()I
    //   2374: bipush #32
    //   2376: irem
    //   2377: invokestatic abs : (I)I
    //   2380: invokevirtual charAt : (I)C
    //   2383: invokevirtual append : (C)Ljava/lang/StringBuilder;
    //   2386: pop
    //   2387: iload_2
    //   2388: ifne -> 2736
    //   2391: goto -> 2398
    //   2394: invokestatic a : (Ljava/lang/Throwable;)Ljava/lang/Throwable;
    //   2397: athrow
    //   2398: aload #4
    //   2400: getstatic burp/Zeyd.Zr : Ljava/lang/String;
    //   2403: getstatic burp/Zltp.ZT : Ljava/lang/Object;
    //   2406: checkcast java/math/BigInteger
    //   2409: invokevirtual intValue : ()I
    //   2412: bipush #32
    //   2414: irem
    //   2415: invokestatic abs : (I)I
    //   2418: invokevirtual charAt : (I)C
    //   2421: invokevirtual append : (C)Ljava/lang/StringBuilder;
    //   2424: pop
    //   2425: iload_2
    //   2426: ifne -> 2736
    //   2429: goto -> 2436
    //   2432: invokestatic a : (Ljava/lang/Throwable;)Ljava/lang/Throwable;
    //   2435: athrow
    //   2436: aload #4
    //   2438: getstatic burp/Zgz1.Zs : Ljava/lang/String;
    //   2441: getstatic burp/Zgil.ZG : Ljava/lang/Object;
    //   2444: checkcast java/math/BigInteger
    //   2447: invokevirtual intValue : ()I
    //   2450: bipush #32
    //   2452: irem
    //   2453: invokestatic abs : (I)I
    //   2456: invokevirtual charAt : (I)C
    //   2459: invokevirtual append : (C)Ljava/lang/StringBuilder;
    //   2462: pop
    //   2463: iload_2
    //   2464: ifne -> 2736
    //   2467: goto -> 2474
    //   2470: invokestatic a : (Ljava/lang/Throwable;)Ljava/lang/Throwable;
    //   2473: athrow
    //   2474: aload #4
    //   2476: getstatic burp/Zlfg.Zb : Ljava/lang/String;
    //   2479: getstatic burp/Zeyd.Zl : Ljava/lang/Object;
    //   2482: checkcast java/math/BigInteger
    //   2485: invokevirtual intValue : ()I
    //   2488: bipush #32
    //   2490: irem
    //   2491: invokestatic abs : (I)I
    //   2494: invokevirtual charAt : (I)C
    //   2497: invokevirtual append : (C)Ljava/lang/StringBuilder;
    //   2500: pop
    //   2501: iload_2
    //   2502: ifne -> 2736
    //   2505: goto -> 2512
    //   2508: invokestatic a : (Ljava/lang/Throwable;)Ljava/lang/Throwable;
    //   2511: athrow
    //   2512: aload #4
    //   2514: getstatic burp/Zgb9.Zk : Ljava/lang/String;
    //   2517: getstatic burp/Zlqy.ZP : Ljava/lang/Object;
    //   2520: checkcast java/math/BigInteger
    //   2523: invokevirtual intValue : ()I
    //   2526: bipush #32
    //   2528: irem
    //   2529: invokestatic abs : (I)I
    //   2532: invokevirtual charAt : (I)C
    //   2535: invokevirtual append : (C)Ljava/lang/StringBuilder;
    //   2538: pop
    //   2539: iload_2
    //   2540: ifne -> 2736
    //   2543: goto -> 2550
    //   2546: invokestatic a : (Ljava/lang/Throwable;)Ljava/lang/Throwable;
    //   2549: athrow
    //   2550: aload #4
    //   2552: getstatic burp/Zl8l.ZG : Ljava/lang/String;
    //   2555: getstatic burp/Zrug.Zp : Ljava/lang/Object;
    //   2558: checkcast java/math/BigInteger
    //   2561: invokevirtual intValue : ()I
    //   2564: bipush #32
    //   2566: irem
    //   2567: invokestatic abs : (I)I
    //   2570: invokevirtual charAt : (I)C
    //   2573: invokevirtual append : (C)Ljava/lang/StringBuilder;
    //   2576: pop
    //   2577: iload_2
    //   2578: ifne -> 2736
    //   2581: goto -> 2588
    //   2584: invokestatic a : (Ljava/lang/Throwable;)Ljava/lang/Throwable;
    //   2587: athrow
    //   2588: aload #4
    //   2590: getstatic burp/Zg3v.Zt : Ljava/lang/String;
    //   2593: getstatic burp/Zzuh.ZV : Ljava/lang/Object;
    //   2596: checkcast java/math/BigInteger
    //   2599: invokevirtual intValue : ()I
    //   2602: bipush #32
    //   2604: irem
    //   2605: invokestatic abs : (I)I
    //   2608: invokevirtual charAt : (I)C
    //   2611: invokevirtual append : (C)Ljava/lang/StringBuilder;
    //   2614: pop
    //   2615: iload_2
    //   2616: ifne -> 2736
    //   2619: goto -> 2626
    //   2622: invokestatic a : (Ljava/lang/Throwable;)Ljava/lang/Throwable;
    //   2625: athrow
    //   2626: aload #4
    //   2628: getstatic burp/Zk7b.ZE : Ljava/lang/String;
    //   2631: getstatic burp/Zm7y.Zr : Ljava/lang/Object;
    //   2634: checkcast java/math/BigInteger
    //   2637: invokevirtual intValue : ()I
    //   2640: bipush #32
    //   2642: irem
    //   2643: invokestatic abs : (I)I
    //   2646: invokevirtual charAt : (I)C
    //   2649: invokevirtual append : (C)Ljava/lang/StringBuilder;
    //   2652: pop
    //   2653: iload_2
    //   2654: ifne -> 2736
    //   2657: goto -> 2664
    //   2660: invokestatic a : (Ljava/lang/Throwable;)Ljava/lang/Throwable;
    //   2663: athrow
    //   2664: aload #4
    //   2666: getstatic burp/Zxzt.ZG : Ljava/lang/String;
    //   2669: getstatic burp/Zlqm.Zw : Ljava/lang/Object;
    //   2672: checkcast java/math/BigInteger
    //   2675: invokevirtual intValue : ()I
    //   2678: bipush #32
    //   2680: irem
    //   2681: invokestatic abs : (I)I
    //   2684: invokevirtual charAt : (I)C
    //   2687: invokevirtual append : (C)Ljava/lang/StringBuilder;
    //   2690: pop
    //   2691: iload_2
    //   2692: ifne -> 2736
    //   2695: goto -> 2702
    //   2698: invokestatic a : (Ljava/lang/Throwable;)Ljava/lang/Throwable;
    //   2701: athrow
    //   2702: aload #4
    //   2704: getstatic burp/Zep8.ZC : Ljava/lang/String;
    //   2707: getstatic burp/Zkor.Ze : Ljava/lang/Object;
    //   2710: checkcast java/math/BigInteger
    //   2713: invokevirtual intValue : ()I
    //   2716: bipush #32
    //   2718: irem
    //   2719: invokestatic abs : (I)I
    //   2722: invokevirtual charAt : (I)C
    //   2725: invokevirtual append : (C)Ljava/lang/StringBuilder;
    //   2728: pop
    //   2729: goto -> 2736
    //   2732: invokestatic a : (Ljava/lang/Throwable;)Ljava/lang/Throwable;
    //   2735: athrow
    //   2736: iinc #5, 1
    //   2739: iload_2
    //   2740: ifne -> 1374
    //   2743: aload #4
    //   2745: invokevirtual toString : ()Ljava/lang/String;
    //   2748: putstatic burp/Zkup.Zr : Ljava/lang/String;
    //   2751: getstatic burp/Zr_z.ZT : Ljava/lang/Object;
    //   2754: checkcast java/math/BigInteger
    //   2757: invokevirtual toByteArray : ()[B
    //   2760: astore #5
    //   2762: bipush #32
    //   2764: newarray int
    //   2766: dup
    //   2767: iconst_0
    //   2768: ldc 943331329
    //   2770: iastore
    //   2771: dup
    //   2772: iconst_1
    //   2773: ldc 170788368
    //   2775: iastore
    //   2776: dup
    //   2777: iconst_2
    //   2778: ldc 1008414755
    //   2780: iastore
    //   2781: dup
    //   2782: iconst_3
    //   2783: ldc 187049985
    //   2785: iastore
    //   2786: dup
    //   2787: iconst_4
    //   2788: ldc 1010368540
    //   2790: iastore
    //   2791: dup
    //   2792: iconst_5
    //   2793: ldc 220604441
    //   2795: iastore
    //   2796: dup
    //   2797: bipush #6
    //   2799: ldc 940377620
    //   2801: iastore
    //   2802: dup
    //   2803: bipush #7
    //   2805: ldc 255209728
    //   2807: iastore
    //   2808: dup
    //   2809: bipush #8
    //   2811: ldc 689771012
    //   2813: iastore
    //   2814: dup
    //   2815: bipush #9
    //   2817: ldc 221709344
    //   2819: iastore
    //   2820: dup
    //   2821: bipush #10
    //   2823: ldc 957157408
    //   2825: iastore
    //   2826: dup
    //   2827: bipush #11
    //   2829: ldc 892536332
    //   2831: iastore
    //   2832: dup
    //   2833: bipush #12
    //   2835: ldc 722417666
    //   2837: iastore
    //   2838: dup
    //   2839: bipush #13
    //   2841: ldc 1026621720
    //   2843: iastore
    //   2844: dup
    //   2845: bipush #14
    //   2847: ldc 655302664
    //   2849: iastore
    //   2850: dup
    //   2851: bipush #15
    //   2853: ldc 890966315
    //   2855: iastore
    //   2856: dup
    //   2857: bipush #16
    //   2859: ldc 187632156
    //   2861: iastore
    //   2862: dup
    //   2863: bipush #17
    //   2865: ldc 874189824
    //   2867: iastore
    //   2868: dup
    //   2869: bipush #18
    //   2871: ldc 254150144
    //   2873: iastore
    //   2874: dup
    //   2875: bipush #19
    //   2877: ldc 924386310
    //   2879: iastore
    //   2880: dup
    //   2881: bipush #20
    //   2883: ldc 121057538
    //   2885: iastore
    //   2886: dup
    //   2887: bipush #21
    //   2889: ldc 840500228
    //   2891: iastore
    //   2892: dup
    //   2893: bipush #22
    //   2895: ldc 389160971
    //   2897: iastore
    //   2898: dup
    //   2899: bipush #23
    //   2901: ldc 907870729
    //   2903: iastore
    //   2904: dup
    //   2905: bipush #24
    //   2907: ldc 389426184
    //   2909: iastore
    //   2910: dup
    //   2911: bipush #25
    //   2913: ldc 973875457
    //   2915: iastore
    //   2916: dup
    //   2917: bipush #26
    //   2919: ldc 372376604
    //   2921: iastore
    //   2922: dup
    //   2923: bipush #27
    //   2925: ldc 707731490
    //   2927: iastore
    //   2928: dup
    //   2929: bipush #28
    //   2931: ldc 1043334948
    //   2933: iastore
    //   2934: dup
    //   2935: bipush #29
    //   2937: ldc 439222784
    //   2939: iastore
    //   2940: dup
    //   2941: bipush #30
    //   2943: ldc 876216579
    //   2945: iastore
    //   2946: dup
    //   2947: bipush #31
    //   2949: ldc 455999525
    //   2951: iastore
    //   2952: astore #7
    //   2954: bipush #8
    //   2956: aload #5
    //   2958: arraylength
    //   2959: bipush #8
    //   2961: irem
    //   2962: isub
    //   2963: istore #8
    //   2965: aload #5
    //   2967: arraylength
    //   2968: iload #8
    //   2970: iadd
    //   2971: newarray byte
    //   2973: astore #9
    //   2975: iconst_0
    //   2976: istore #10
    //   2978: iload #10
    //   2980: aload #5
    //   2982: arraylength
    //   2983: if_icmpge -> 3003
    //   2986: aload #9
    //   2988: iload #10
    //   2990: aload #5
    //   2992: iload #10
    //   2994: baload
    //   2995: bastore
    //   2996: iinc #10, 1
    //   2999: iload_2
    //   3000: ifne -> 2978
    //   3003: aload #5
    //   3005: arraylength
    //   3006: istore #10
    //   3008: iload #10
    //   3010: aload #9
    //   3012: arraylength
    //   3013: if_icmpge -> 3031
    //   3016: aload #9
    //   3018: iload #10
    //   3020: iload #8
    //   3022: i2b
    //   3023: bastore
    //   3024: iinc #10, 1
    //   3027: iload_2
    //   3028: ifne -> 3008
    //   3031: aload #9
    //   3033: astore #5
    //   3035: bipush #64
    //   3037: newarray int
    //   3039: dup
    //   3040: iconst_0
    //   3041: ldc 16843776
    //   3043: iastore
    //   3044: dup
    //   3045: iconst_1
    //   3046: iconst_0
    //   3047: iastore
    //   3048: dup
    //   3049: iconst_2
    //   3050: ldc 65536
    //   3052: iastore
    //   3053: dup
    //   3054: iconst_3
    //   3055: ldc 16843780
    //   3057: iastore
    //   3058: dup
    //   3059: iconst_4
    //   3060: ldc 16842756
    //   3062: iastore
    //   3063: dup
    //   3064: iconst_5
    //   3065: ldc 66564
    //   3067: iastore
    //   3068: dup
    //   3069: bipush #6
    //   3071: iconst_4
    //   3072: iastore
    //   3073: dup
    //   3074: bipush #7
    //   3076: ldc 65536
    //   3078: iastore
    //   3079: dup
    //   3080: bipush #8
    //   3082: sipush #1024
    //   3085: iastore
    //   3086: dup
    //   3087: bipush #9
    //   3089: ldc 16843776
    //   3091: iastore
    //   3092: dup
    //   3093: bipush #10
    //   3095: ldc 16843780
    //   3097: iastore
    //   3098: dup
    //   3099: bipush #11
    //   3101: sipush #1024
    //   3104: iastore
    //   3105: dup
    //   3106: bipush #12
    //   3108: ldc 16778244
    //   3110: iastore
    //   3111: dup
    //   3112: bipush #13
    //   3114: ldc 16842756
    //   3116: iastore
    //   3117: dup
    //   3118: bipush #14
    //   3120: ldc 16777216
    //   3122: iastore
    //   3123: dup
    //   3124: bipush #15
    //   3126: iconst_4
    //   3127: iastore
    //   3128: dup
    //   3129: bipush #16
    //   3131: sipush #1028
    //   3134: iastore
    //   3135: dup
    //   3136: bipush #17
    //   3138: ldc 16778240
    //   3140: iastore
    //   3141: dup
    //   3142: bipush #18
    //   3144: ldc 16778240
    //   3146: iastore
    //   3147: dup
    //   3148: bipush #19
    //   3150: ldc 66560
    //   3152: iastore
    //   3153: dup
    //   3154: bipush #20
    //   3156: ldc 66560
    //   3158: iastore
    //   3159: dup
    //   3160: bipush #21
    //   3162: ldc 16842752
    //   3164: iastore
    //   3165: dup
    //   3166: bipush #22
    //   3168: ldc 16842752
    //   3170: iastore
    //   3171: dup
    //   3172: bipush #23
    //   3174: ldc 16778244
    //   3176: iastore
    //   3177: dup
    //   3178: bipush #24
    //   3180: ldc 65540
    //   3182: iastore
    //   3183: dup
    //   3184: bipush #25
    //   3186: ldc 16777220
    //   3188: iastore
    //   3189: dup
    //   3190: bipush #26
    //   3192: ldc 16777220
    //   3194: iastore
    //   3195: dup
    //   3196: bipush #27
    //   3198: ldc 65540
    //   3200: iastore
    //   3201: dup
    //   3202: bipush #28
    //   3204: iconst_0
    //   3205: iastore
    //   3206: dup
    //   3207: bipush #29
    //   3209: sipush #1028
    //   3212: iastore
    //   3213: dup
    //   3214: bipush #30
    //   3216: ldc 66564
    //   3218: iastore
    //   3219: dup
    //   3220: bipush #31
    //   3222: ldc 16777216
    //   3224: iastore
    //   3225: dup
    //   3226: bipush #32
    //   3228: ldc 65536
    //   3230: iastore
    //   3231: dup
    //   3232: bipush #33
    //   3234: ldc 16843780
    //   3236: iastore
    //   3237: dup
    //   3238: bipush #34
    //   3240: iconst_4
    //   3241: iastore
    //   3242: dup
    //   3243: bipush #35
    //   3245: ldc 16842752
    //   3247: iastore
    //   3248: dup
    //   3249: bipush #36
    //   3251: ldc 16843776
    //   3253: iastore
    //   3254: dup
    //   3255: bipush #37
    //   3257: ldc 16777216
    //   3259: iastore
    //   3260: dup
    //   3261: bipush #38
    //   3263: ldc 16777216
    //   3265: iastore
    //   3266: dup
    //   3267: bipush #39
    //   3269: sipush #1024
    //   3272: iastore
    //   3273: dup
    //   3274: bipush #40
    //   3276: ldc 16842756
    //   3278: iastore
    //   3279: dup
    //   3280: bipush #41
    //   3282: ldc 65536
    //   3284: iastore
    //   3285: dup
    //   3286: bipush #42
    //   3288: ldc 66560
    //   3290: iastore
    //   3291: dup
    //   3292: bipush #43
    //   3294: ldc 16777220
    //   3296: iastore
    //   3297: dup
    //   3298: bipush #44
    //   3300: sipush #1024
    //   3303: iastore
    //   3304: dup
    //   3305: bipush #45
    //   3307: iconst_4
    //   3308: iastore
    //   3309: dup
    //   3310: bipush #46
    //   3312: ldc 16778244
    //   3314: iastore
    //   3315: dup
    //   3316: bipush #47
    //   3318: ldc 66564
    //   3320: iastore
    //   3321: dup
    //   3322: bipush #48
    //   3324: ldc 16843780
    //   3326: iastore
    //   3327: dup
    //   3328: bipush #49
    //   3330: ldc 65540
    //   3332: iastore
    //   3333: dup
    //   3334: bipush #50
    //   3336: ldc 16842752
    //   3338: iastore
    //   3339: dup
    //   3340: bipush #51
    //   3342: ldc 16778244
    //   3344: iastore
    //   3345: dup
    //   3346: bipush #52
    //   3348: ldc 16777220
    //   3350: iastore
    //   3351: dup
    //   3352: bipush #53
    //   3354: sipush #1028
    //   3357: iastore
    //   3358: dup
    //   3359: bipush #54
    //   3361: ldc 66564
    //   3363: iastore
    //   3364: dup
    //   3365: bipush #55
    //   3367: ldc 16843776
    //   3369: iastore
    //   3370: dup
    //   3371: bipush #56
    //   3373: sipush #1028
    //   3376: iastore
    //   3377: dup
    //   3378: bipush #57
    //   3380: ldc 16778240
    //   3382: iastore
    //   3383: dup
    //   3384: bipush #58
    //   3386: ldc 16778240
    //   3388: iastore
    //   3389: dup
    //   3390: bipush #59
    //   3392: iconst_0
    //   3393: iastore
    //   3394: dup
    //   3395: bipush #60
    //   3397: ldc 65540
    //   3399: iastore
    //   3400: dup
    //   3401: bipush #61
    //   3403: ldc 66560
    //   3405: iastore
    //   3406: dup
    //   3407: bipush #62
    //   3409: iconst_0
    //   3410: iastore
    //   3411: dup
    //   3412: bipush #63
    //   3414: ldc 16842756
    //   3416: iastore
    //   3417: astore #10
    //   3419: bipush #64
    //   3421: newarray int
    //   3423: dup
    //   3424: iconst_0
    //   3425: ldc -2146402272
    //   3427: iastore
    //   3428: dup
    //   3429: iconst_1
    //   3430: ldc -2147450880
    //   3432: iastore
    //   3433: dup
    //   3434: iconst_2
    //   3435: ldc 32768
    //   3437: iastore
    //   3438: dup
    //   3439: iconst_3
    //   3440: ldc 1081376
    //   3442: iastore
    //   3443: dup
    //   3444: iconst_4
    //   3445: ldc 1048576
    //   3447: iastore
    //   3448: dup
    //   3449: iconst_5
    //   3450: bipush #32
    //   3452: iastore
    //   3453: dup
    //   3454: bipush #6
    //   3456: ldc -2146435040
    //   3458: iastore
    //   3459: dup
    //   3460: bipush #7
    //   3462: ldc -2147450848
    //   3464: iastore
    //   3465: dup
    //   3466: bipush #8
    //   3468: ldc -2147483616
    //   3470: iastore
    //   3471: dup
    //   3472: bipush #9
    //   3474: ldc -2146402272
    //   3476: iastore
    //   3477: dup
    //   3478: bipush #10
    //   3480: ldc -2146402304
    //   3482: iastore
    //   3483: dup
    //   3484: bipush #11
    //   3486: ldc -2147483648
    //   3488: iastore
    //   3489: dup
    //   3490: bipush #12
    //   3492: ldc -2147450880
    //   3494: iastore
    //   3495: dup
    //   3496: bipush #13
    //   3498: ldc 1048576
    //   3500: iastore
    //   3501: dup
    //   3502: bipush #14
    //   3504: bipush #32
    //   3506: iastore
    //   3507: dup
    //   3508: bipush #15
    //   3510: ldc -2146435040
    //   3512: iastore
    //   3513: dup
    //   3514: bipush #16
    //   3516: ldc 1081344
    //   3518: iastore
    //   3519: dup
    //   3520: bipush #17
    //   3522: ldc 1048608
    //   3524: iastore
    //   3525: dup
    //   3526: bipush #18
    //   3528: ldc -2147450848
    //   3530: iastore
    //   3531: dup
    //   3532: bipush #19
    //   3534: iconst_0
    //   3535: iastore
    //   3536: dup
    //   3537: bipush #20
    //   3539: ldc -2147483648
    //   3541: iastore
    //   3542: dup
    //   3543: bipush #21
    //   3545: ldc 32768
    //   3547: iastore
    //   3548: dup
    //   3549: bipush #22
    //   3551: ldc 1081376
    //   3553: iastore
    //   3554: dup
    //   3555: bipush #23
    //   3557: ldc -2146435072
    //   3559: iastore
    //   3560: dup
    //   3561: bipush #24
    //   3563: ldc 1048608
    //   3565: iastore
    //   3566: dup
    //   3567: bipush #25
    //   3569: ldc -2147483616
    //   3571: iastore
    //   3572: dup
    //   3573: bipush #26
    //   3575: iconst_0
    //   3576: iastore
    //   3577: dup
    //   3578: bipush #27
    //   3580: ldc 1081344
    //   3582: iastore
    //   3583: dup
    //   3584: bipush #28
    //   3586: ldc 32800
    //   3588: iastore
    //   3589: dup
    //   3590: bipush #29
    //   3592: ldc -2146402304
    //   3594: iastore
    //   3595: dup
    //   3596: bipush #30
    //   3598: ldc -2146435072
    //   3600: iastore
    //   3601: dup
    //   3602: bipush #31
    //   3604: ldc 32800
    //   3606: iastore
    //   3607: dup
    //   3608: bipush #32
    //   3610: iconst_0
    //   3611: iastore
    //   3612: dup
    //   3613: bipush #33
    //   3615: ldc 1081376
    //   3617: iastore
    //   3618: dup
    //   3619: bipush #34
    //   3621: ldc -2146435040
    //   3623: iastore
    //   3624: dup
    //   3625: bipush #35
    //   3627: ldc 1048576
    //   3629: iastore
    //   3630: dup
    //   3631: bipush #36
    //   3633: ldc -2147450848
    //   3635: iastore
    //   3636: dup
    //   3637: bipush #37
    //   3639: ldc -2146435072
    //   3641: iastore
    //   3642: dup
    //   3643: bipush #38
    //   3645: ldc -2146402304
    //   3647: iastore
    //   3648: dup
    //   3649: bipush #39
    //   3651: ldc 32768
    //   3653: iastore
    //   3654: dup
    //   3655: bipush #40
    //   3657: ldc -2146435072
    //   3659: iastore
    //   3660: dup
    //   3661: bipush #41
    //   3663: ldc -2147450880
    //   3665: iastore
    //   3666: dup
    //   3667: bipush #42
    //   3669: bipush #32
    //   3671: iastore
    //   3672: dup
    //   3673: bipush #43
    //   3675: ldc -2146402272
    //   3677: iastore
    //   3678: dup
    //   3679: bipush #44
    //   3681: ldc 1081376
    //   3683: iastore
    //   3684: dup
    //   3685: bipush #45
    //   3687: bipush #32
    //   3689: iastore
    //   3690: dup
    //   3691: bipush #46
    //   3693: ldc 32768
    //   3695: iastore
    //   3696: dup
    //   3697: bipush #47
    //   3699: ldc -2147483648
    //   3701: iastore
    //   3702: dup
    //   3703: bipush #48
    //   3705: ldc 32800
    //   3707: iastore
    //   3708: dup
    //   3709: bipush #49
    //   3711: ldc -2146402304
    //   3713: iastore
    //   3714: dup
    //   3715: bipush #50
    //   3717: ldc 1048576
    //   3719: iastore
    //   3720: dup
    //   3721: bipush #51
    //   3723: ldc -2147483616
    //   3725: iastore
    //   3726: dup
    //   3727: bipush #52
    //   3729: ldc 1048608
    //   3731: iastore
    //   3732: dup
    //   3733: bipush #53
    //   3735: ldc -2147450848
    //   3737: iastore
    //   3738: dup
    //   3739: bipush #54
    //   3741: ldc -2147483616
    //   3743: iastore
    //   3744: dup
    //   3745: bipush #55
    //   3747: ldc 1048608
    //   3749: iastore
    //   3750: dup
    //   3751: bipush #56
    //   3753: ldc 1081344
    //   3755: iastore
    //   3756: dup
    //   3757: bipush #57
    //   3759: iconst_0
    //   3760: iastore
    //   3761: dup
    //   3762: bipush #58
    //   3764: ldc -2147450880
    //   3766: iastore
    //   3767: dup
    //   3768: bipush #59
    //   3770: ldc 32800
    //   3772: iastore
    //   3773: dup
    //   3774: bipush #60
    //   3776: ldc -2147483648
    //   3778: iastore
    //   3779: dup
    //   3780: bipush #61
    //   3782: ldc -2146435040
    //   3784: iastore
    //   3785: dup
    //   3786: bipush #62
    //   3788: ldc -2146402272
    //   3790: iastore
    //   3791: dup
    //   3792: bipush #63
    //   3794: ldc 1081344
    //   3796: iastore
    //   3797: astore #11
    //   3799: bipush #64
    //   3801: newarray int
    //   3803: dup
    //   3804: iconst_0
    //   3805: sipush #520
    //   3808: iastore
    //   3809: dup
    //   3810: iconst_1
    //   3811: ldc 134349312
    //   3813: iastore
    //   3814: dup
    //   3815: iconst_2
    //   3816: iconst_0
    //   3817: iastore
    //   3818: dup
    //   3819: iconst_3
    //   3820: ldc 134348808
    //   3822: iastore
    //   3823: dup
    //   3824: iconst_4
    //   3825: ldc 134218240
    //   3827: iastore
    //   3828: dup
    //   3829: iconst_5
    //   3830: iconst_0
    //   3831: iastore
    //   3832: dup
    //   3833: bipush #6
    //   3835: ldc 131592
    //   3837: iastore
    //   3838: dup
    //   3839: bipush #7
    //   3841: ldc 134218240
    //   3843: iastore
    //   3844: dup
    //   3845: bipush #8
    //   3847: ldc 131080
    //   3849: iastore
    //   3850: dup
    //   3851: bipush #9
    //   3853: ldc 134217736
    //   3855: iastore
    //   3856: dup
    //   3857: bipush #10
    //   3859: ldc 134217736
    //   3861: iastore
    //   3862: dup
    //   3863: bipush #11
    //   3865: ldc 131072
    //   3867: iastore
    //   3868: dup
    //   3869: bipush #12
    //   3871: ldc 134349320
    //   3873: iastore
    //   3874: dup
    //   3875: bipush #13
    //   3877: ldc 131080
    //   3879: iastore
    //   3880: dup
    //   3881: bipush #14
    //   3883: ldc 134348800
    //   3885: iastore
    //   3886: dup
    //   3887: bipush #15
    //   3889: sipush #520
    //   3892: iastore
    //   3893: dup
    //   3894: bipush #16
    //   3896: ldc 134217728
    //   3898: iastore
    //   3899: dup
    //   3900: bipush #17
    //   3902: bipush #8
    //   3904: iastore
    //   3905: dup
    //   3906: bipush #18
    //   3908: ldc 134349312
    //   3910: iastore
    //   3911: dup
    //   3912: bipush #19
    //   3914: sipush #512
    //   3917: iastore
    //   3918: dup
    //   3919: bipush #20
    //   3921: ldc 131584
    //   3923: iastore
    //   3924: dup
    //   3925: bipush #21
    //   3927: ldc 134348800
    //   3929: iastore
    //   3930: dup
    //   3931: bipush #22
    //   3933: ldc 134348808
    //   3935: iastore
    //   3936: dup
    //   3937: bipush #23
    //   3939: ldc 131592
    //   3941: iastore
    //   3942: dup
    //   3943: bipush #24
    //   3945: ldc 134218248
    //   3947: iastore
    //   3948: dup
    //   3949: bipush #25
    //   3951: ldc 131584
    //   3953: iastore
    //   3954: dup
    //   3955: bipush #26
    //   3957: ldc 131072
    //   3959: iastore
    //   3960: dup
    //   3961: bipush #27
    //   3963: ldc 134218248
    //   3965: iastore
    //   3966: dup
    //   3967: bipush #28
    //   3969: bipush #8
    //   3971: iastore
    //   3972: dup
    //   3973: bipush #29
    //   3975: ldc 134349320
    //   3977: iastore
    //   3978: dup
    //   3979: bipush #30
    //   3981: sipush #512
    //   3984: iastore
    //   3985: dup
    //   3986: bipush #31
    //   3988: ldc 134217728
    //   3990: iastore
    //   3991: dup
    //   3992: bipush #32
    //   3994: ldc 134349312
    //   3996: iastore
    //   3997: dup
    //   3998: bipush #33
    //   4000: ldc 134217728
    //   4002: iastore
    //   4003: dup
    //   4004: bipush #34
    //   4006: ldc 131080
    //   4008: iastore
    //   4009: dup
    //   4010: bipush #35
    //   4012: sipush #520
    //   4015: iastore
    //   4016: dup
    //   4017: bipush #36
    //   4019: ldc 131072
    //   4021: iastore
    //   4022: dup
    //   4023: bipush #37
    //   4025: ldc 134349312
    //   4027: iastore
    //   4028: dup
    //   4029: bipush #38
    //   4031: ldc 134218240
    //   4033: iastore
    //   4034: dup
    //   4035: bipush #39
    //   4037: iconst_0
    //   4038: iastore
    //   4039: dup
    //   4040: bipush #40
    //   4042: sipush #512
    //   4045: iastore
    //   4046: dup
    //   4047: bipush #41
    //   4049: ldc 131080
    //   4051: iastore
    //   4052: dup
    //   4053: bipush #42
    //   4055: ldc 134349320
    //   4057: iastore
    //   4058: dup
    //   4059: bipush #43
    //   4061: ldc 134218240
    //   4063: iastore
    //   4064: dup
    //   4065: bipush #44
    //   4067: ldc 134217736
    //   4069: iastore
    //   4070: dup
    //   4071: bipush #45
    //   4073: sipush #512
    //   4076: iastore
    //   4077: dup
    //   4078: bipush #46
    //   4080: iconst_0
    //   4081: iastore
    //   4082: dup
    //   4083: bipush #47
    //   4085: ldc 134348808
    //   4087: iastore
    //   4088: dup
    //   4089: bipush #48
    //   4091: ldc 134218248
    //   4093: iastore
    //   4094: dup
    //   4095: bipush #49
    //   4097: ldc 131072
    //   4099: iastore
    //   4100: dup
    //   4101: bipush #50
    //   4103: ldc 134217728
    //   4105: iastore
    //   4106: dup
    //   4107: bipush #51
    //   4109: ldc 134349320
    //   4111: iastore
    //   4112: dup
    //   4113: bipush #52
    //   4115: bipush #8
    //   4117: iastore
    //   4118: dup
    //   4119: bipush #53
    //   4121: ldc 131592
    //   4123: iastore
    //   4124: dup
    //   4125: bipush #54
    //   4127: ldc 131584
    //   4129: iastore
    //   4130: dup
    //   4131: bipush #55
    //   4133: ldc 134217736
    //   4135: iastore
    //   4136: dup
    //   4137: bipush #56
    //   4139: ldc 134348800
    //   4141: iastore
    //   4142: dup
    //   4143: bipush #57
    //   4145: ldc 134218248
    //   4147: iastore
    //   4148: dup
    //   4149: bipush #58
    //   4151: sipush #520
    //   4154: iastore
    //   4155: dup
    //   4156: bipush #59
    //   4158: ldc 134348800
    //   4160: iastore
    //   4161: dup
    //   4162: bipush #60
    //   4164: ldc 131592
    //   4166: iastore
    //   4167: dup
    //   4168: bipush #61
    //   4170: bipush #8
    //   4172: iastore
    //   4173: dup
    //   4174: bipush #62
    //   4176: ldc 134348808
    //   4178: iastore
    //   4179: dup
    //   4180: bipush #63
    //   4182: ldc 131584
    //   4184: iastore
    //   4185: astore #12
    //   4187: bipush #64
    //   4189: newarray int
    //   4191: dup
    //   4192: iconst_0
    //   4193: ldc 8396801
    //   4195: iastore
    //   4196: dup
    //   4197: iconst_1
    //   4198: sipush #8321
    //   4201: iastore
    //   4202: dup
    //   4203: iconst_2
    //   4204: sipush #8321
    //   4207: iastore
    //   4208: dup
    //   4209: iconst_3
    //   4210: sipush #128
    //   4213: iastore
    //   4214: dup
    //   4215: iconst_4
    //   4216: ldc 8396928
    //   4218: iastore
    //   4219: dup
    //   4220: iconst_5
    //   4221: ldc 8388737
    //   4223: iastore
    //   4224: dup
    //   4225: bipush #6
    //   4227: ldc 8388609
    //   4229: iastore
    //   4230: dup
    //   4231: bipush #7
    //   4233: sipush #8193
    //   4236: iastore
    //   4237: dup
    //   4238: bipush #8
    //   4240: iconst_0
    //   4241: iastore
    //   4242: dup
    //   4243: bipush #9
    //   4245: ldc 8396800
    //   4247: iastore
    //   4248: dup
    //   4249: bipush #10
    //   4251: ldc 8396800
    //   4253: iastore
    //   4254: dup
    //   4255: bipush #11
    //   4257: ldc 8396929
    //   4259: iastore
    //   4260: dup
    //   4261: bipush #12
    //   4263: sipush #129
    //   4266: iastore
    //   4267: dup
    //   4268: bipush #13
    //   4270: iconst_0
    //   4271: iastore
    //   4272: dup
    //   4273: bipush #14
    //   4275: ldc 8388736
    //   4277: iastore
    //   4278: dup
    //   4279: bipush #15
    //   4281: ldc 8388609
    //   4283: iastore
    //   4284: dup
    //   4285: bipush #16
    //   4287: iconst_1
    //   4288: iastore
    //   4289: dup
    //   4290: bipush #17
    //   4292: sipush #8192
    //   4295: iastore
    //   4296: dup
    //   4297: bipush #18
    //   4299: ldc 8388608
    //   4301: iastore
    //   4302: dup
    //   4303: bipush #19
    //   4305: ldc 8396801
    //   4307: iastore
    //   4308: dup
    //   4309: bipush #20
    //   4311: sipush #128
    //   4314: iastore
    //   4315: dup
    //   4316: bipush #21
    //   4318: ldc 8388608
    //   4320: iastore
    //   4321: dup
    //   4322: bipush #22
    //   4324: sipush #8193
    //   4327: iastore
    //   4328: dup
    //   4329: bipush #23
    //   4331: sipush #8320
    //   4334: iastore
    //   4335: dup
    //   4336: bipush #24
    //   4338: ldc 8388737
    //   4340: iastore
    //   4341: dup
    //   4342: bipush #25
    //   4344: iconst_1
    //   4345: iastore
    //   4346: dup
    //   4347: bipush #26
    //   4349: sipush #8320
    //   4352: iastore
    //   4353: dup
    //   4354: bipush #27
    //   4356: ldc 8388736
    //   4358: iastore
    //   4359: dup
    //   4360: bipush #28
    //   4362: sipush #8192
    //   4365: iastore
    //   4366: dup
    //   4367: bipush #29
    //   4369: ldc 8396928
    //   4371: iastore
    //   4372: dup
    //   4373: bipush #30
    //   4375: ldc 8396929
    //   4377: iastore
    //   4378: dup
    //   4379: bipush #31
    //   4381: sipush #129
    //   4384: iastore
    //   4385: dup
    //   4386: bipush #32
    //   4388: ldc 8388736
    //   4390: iastore
    //   4391: dup
    //   4392: bipush #33
    //   4394: ldc 8388609
    //   4396: iastore
    //   4397: dup
    //   4398: bipush #34
    //   4400: ldc 8396800
    //   4402: iastore
    //   4403: dup
    //   4404: bipush #35
    //   4406: ldc 8396929
    //   4408: iastore
    //   4409: dup
    //   4410: bipush #36
    //   4412: sipush #129
    //   4415: iastore
    //   4416: dup
    //   4417: bipush #37
    //   4419: iconst_0
    //   4420: iastore
    //   4421: dup
    //   4422: bipush #38
    //   4424: iconst_0
    //   4425: iastore
    //   4426: dup
    //   4427: bipush #39
    //   4429: ldc 8396800
    //   4431: iastore
    //   4432: dup
    //   4433: bipush #40
    //   4435: sipush #8320
    //   4438: iastore
    //   4439: dup
    //   4440: bipush #41
    //   4442: ldc 8388736
    //   4444: iastore
    //   4445: dup
    //   4446: bipush #42
    //   4448: ldc 8388737
    //   4450: iastore
    //   4451: dup
    //   4452: bipush #43
    //   4454: iconst_1
    //   4455: iastore
    //   4456: dup
    //   4457: bipush #44
    //   4459: ldc 8396801
    //   4461: iastore
    //   4462: dup
    //   4463: bipush #45
    //   4465: sipush #8321
    //   4468: iastore
    //   4469: dup
    //   4470: bipush #46
    //   4472: sipush #8321
    //   4475: iastore
    //   4476: dup
    //   4477: bipush #47
    //   4479: sipush #128
    //   4482: iastore
    //   4483: dup
    //   4484: bipush #48
    //   4486: ldc 8396929
    //   4488: iastore
    //   4489: dup
    //   4490: bipush #49
    //   4492: sipush #129
    //   4495: iastore
    //   4496: dup
    //   4497: bipush #50
    //   4499: iconst_1
    //   4500: iastore
    //   4501: dup
    //   4502: bipush #51
    //   4504: sipush #8192
    //   4507: iastore
    //   4508: dup
    //   4509: bipush #52
    //   4511: ldc 8388609
    //   4513: iastore
    //   4514: dup
    //   4515: bipush #53
    //   4517: sipush #8193
    //   4520: iastore
    //   4521: dup
    //   4522: bipush #54
    //   4524: ldc 8396928
    //   4526: iastore
    //   4527: dup
    //   4528: bipush #55
    //   4530: ldc 8388737
    //   4532: iastore
    //   4533: dup
    //   4534: bipush #56
    //   4536: sipush #8193
    //   4539: iastore
    //   4540: dup
    //   4541: bipush #57
    //   4543: sipush #8320
    //   4546: iastore
    //   4547: dup
    //   4548: bipush #58
    //   4550: ldc 8388608
    //   4552: iastore
    //   4553: dup
    //   4554: bipush #59
    //   4556: ldc 8396801
    //   4558: iastore
    //   4559: dup
    //   4560: bipush #60
    //   4562: sipush #128
    //   4565: iastore
    //   4566: dup
    //   4567: bipush #61
    //   4569: ldc 8388608
    //   4571: iastore
    //   4572: dup
    //   4573: bipush #62
    //   4575: sipush #8192
    //   4578: iastore
    //   4579: dup
    //   4580: bipush #63
    //   4582: ldc 8396928
    //   4584: iastore
    //   4585: astore #13
    //   4587: bipush #64
    //   4589: newarray int
    //   4591: dup
    //   4592: iconst_0
    //   4593: sipush #256
    //   4596: iastore
    //   4597: dup
    //   4598: iconst_1
    //   4599: ldc 34078976
    //   4601: iastore
    //   4602: dup
    //   4603: iconst_2
    //   4604: ldc 34078720
    //   4606: iastore
    //   4607: dup
    //   4608: iconst_3
    //   4609: ldc 1107296512
    //   4611: iastore
    //   4612: dup
    //   4613: iconst_4
    //   4614: ldc 524288
    //   4616: iastore
    //   4617: dup
    //   4618: iconst_5
    //   4619: sipush #256
    //   4622: iastore
    //   4623: dup
    //   4624: bipush #6
    //   4626: ldc 1073741824
    //   4628: iastore
    //   4629: dup
    //   4630: bipush #7
    //   4632: ldc 34078720
    //   4634: iastore
    //   4635: dup
    //   4636: bipush #8
    //   4638: ldc 1074266368
    //   4640: iastore
    //   4641: dup
    //   4642: bipush #9
    //   4644: ldc 524288
    //   4646: iastore
    //   4647: dup
    //   4648: bipush #10
    //   4650: ldc 33554688
    //   4652: iastore
    //   4653: dup
    //   4654: bipush #11
    //   4656: ldc 1074266368
    //   4658: iastore
    //   4659: dup
    //   4660: bipush #12
    //   4662: ldc 1107296512
    //   4664: iastore
    //   4665: dup
    //   4666: bipush #13
    //   4668: ldc 1107820544
    //   4670: iastore
    //   4671: dup
    //   4672: bipush #14
    //   4674: ldc 524544
    //   4676: iastore
    //   4677: dup
    //   4678: bipush #15
    //   4680: ldc 1073741824
    //   4682: iastore
    //   4683: dup
    //   4684: bipush #16
    //   4686: ldc 33554432
    //   4688: iastore
    //   4689: dup
    //   4690: bipush #17
    //   4692: ldc 1074266112
    //   4694: iastore
    //   4695: dup
    //   4696: bipush #18
    //   4698: ldc 1074266112
    //   4700: iastore
    //   4701: dup
    //   4702: bipush #19
    //   4704: iconst_0
    //   4705: iastore
    //   4706: dup
    //   4707: bipush #20
    //   4709: ldc 1073742080
    //   4711: iastore
    //   4712: dup
    //   4713: bipush #21
    //   4715: ldc 1107820800
    //   4717: iastore
    //   4718: dup
    //   4719: bipush #22
    //   4721: ldc 1107820800
    //   4723: iastore
    //   4724: dup
    //   4725: bipush #23
    //   4727: ldc 33554688
    //   4729: iastore
    //   4730: dup
    //   4731: bipush #24
    //   4733: ldc 1107820544
    //   4735: iastore
    //   4736: dup
    //   4737: bipush #25
    //   4739: ldc 1073742080
    //   4741: iastore
    //   4742: dup
    //   4743: bipush #26
    //   4745: iconst_0
    //   4746: iastore
    //   4747: dup
    //   4748: bipush #27
    //   4750: ldc 1107296256
    //   4752: iastore
    //   4753: dup
    //   4754: bipush #28
    //   4756: ldc 34078976
    //   4758: iastore
    //   4759: dup
    //   4760: bipush #29
    //   4762: ldc 33554432
    //   4764: iastore
    //   4765: dup
    //   4766: bipush #30
    //   4768: ldc 1107296256
    //   4770: iastore
    //   4771: dup
    //   4772: bipush #31
    //   4774: ldc 524544
    //   4776: iastore
    //   4777: dup
    //   4778: bipush #32
    //   4780: ldc 524288
    //   4782: iastore
    //   4783: dup
    //   4784: bipush #33
    //   4786: ldc 1107296512
    //   4788: iastore
    //   4789: dup
    //   4790: bipush #34
    //   4792: sipush #256
    //   4795: iastore
    //   4796: dup
    //   4797: bipush #35
    //   4799: ldc 33554432
    //   4801: iastore
    //   4802: dup
    //   4803: bipush #36
    //   4805: ldc 1073741824
    //   4807: iastore
    //   4808: dup
    //   4809: bipush #37
    //   4811: ldc 34078720
    //   4813: iastore
    //   4814: dup
    //   4815: bipush #38
    //   4817: ldc 1107296512
    //   4819: iastore
    //   4820: dup
    //   4821: bipush #39
    //   4823: ldc 1074266368
    //   4825: iastore
    //   4826: dup
    //   4827: bipush #40
    //   4829: ldc 33554688
    //   4831: iastore
    //   4832: dup
    //   4833: bipush #41
    //   4835: ldc 1073741824
    //   4837: iastore
    //   4838: dup
    //   4839: bipush #42
    //   4841: ldc 1107820544
    //   4843: iastore
    //   4844: dup
    //   4845: bipush #43
    //   4847: ldc 34078976
    //   4849: iastore
    //   4850: dup
    //   4851: bipush #44
    //   4853: ldc 1074266368
    //   4855: iastore
    //   4856: dup
    //   4857: bipush #45
    //   4859: sipush #256
    //   4862: iastore
    //   4863: dup
    //   4864: bipush #46
    //   4866: ldc 33554432
    //   4868: iastore
    //   4869: dup
    //   4870: bipush #47
    //   4872: ldc 1107820544
    //   4874: iastore
    //   4875: dup
    //   4876: bipush #48
    //   4878: ldc 1107820800
    //   4880: iastore
    //   4881: dup
    //   4882: bipush #49
    //   4884: ldc 524544
    //   4886: iastore
    //   4887: dup
    //   4888: bipush #50
    //   4890: ldc 1107296256
    //   4892: iastore
    //   4893: dup
    //   4894: bipush #51
    //   4896: ldc 1107820800
    //   4898: iastore
    //   4899: dup
    //   4900: bipush #52
    //   4902: ldc 34078720
    //   4904: iastore
    //   4905: dup
    //   4906: bipush #53
    //   4908: iconst_0
    //   4909: iastore
    //   4910: dup
    //   4911: bipush #54
    //   4913: ldc 1074266112
    //   4915: iastore
    //   4916: dup
    //   4917: bipush #55
    //   4919: ldc 1107296256
    //   4921: iastore
    //   4922: dup
    //   4923: bipush #56
    //   4925: ldc 524544
    //   4927: iastore
    //   4928: dup
    //   4929: bipush #57
    //   4931: ldc 33554688
    //   4933: iastore
    //   4934: dup
    //   4935: bipush #58
    //   4937: ldc 1073742080
    //   4939: iastore
    //   4940: dup
    //   4941: bipush #59
    //   4943: ldc 524288
    //   4945: iastore
    //   4946: dup
    //   4947: bipush #60
    //   4949: iconst_0
    //   4950: iastore
    //   4951: dup
    //   4952: bipush #61
    //   4954: ldc 1074266112
    //   4956: iastore
    //   4957: dup
    //   4958: bipush #62
    //   4960: ldc 34078976
    //   4962: iastore
    //   4963: dup
    //   4964: bipush #63
    //   4966: ldc 1073742080
    //   4968: iastore
    //   4969: astore #14
    //   4971: bipush #64
    //   4973: newarray int
    //   4975: dup
    //   4976: iconst_0
    //   4977: ldc 536870928
    //   4979: iastore
    //   4980: dup
    //   4981: iconst_1
    //   4982: ldc 541065216
    //   4984: iastore
    //   4985: dup
    //   4986: iconst_2
    //   4987: sipush #16384
    //   4990: iastore
    //   4991: dup
    //   4992: iconst_3
    //   4993: ldc 541081616
    //   4995: iastore
    //   4996: dup
    //   4997: iconst_4
    //   4998: ldc 541065216
    //   5000: iastore
    //   5001: dup
    //   5002: iconst_5
    //   5003: bipush #16
    //   5005: iastore
    //   5006: dup
    //   5007: bipush #6
    //   5009: ldc 541081616
    //   5011: iastore
    //   5012: dup
    //   5013: bipush #7
    //   5015: ldc 4194304
    //   5017: iastore
    //   5018: dup
    //   5019: bipush #8
    //   5021: ldc 536887296
    //   5023: iastore
    //   5024: dup
    //   5025: bipush #9
    //   5027: ldc 4210704
    //   5029: iastore
    //   5030: dup
    //   5031: bipush #10
    //   5033: ldc 4194304
    //   5035: iastore
    //   5036: dup
    //   5037: bipush #11
    //   5039: ldc 536870928
    //   5041: iastore
    //   5042: dup
    //   5043: bipush #12
    //   5045: ldc 4194320
    //   5047: iastore
    //   5048: dup
    //   5049: bipush #13
    //   5051: ldc 536887296
    //   5053: iastore
    //   5054: dup
    //   5055: bipush #14
    //   5057: ldc 536870912
    //   5059: iastore
    //   5060: dup
    //   5061: bipush #15
    //   5063: sipush #16400
    //   5066: iastore
    //   5067: dup
    //   5068: bipush #16
    //   5070: iconst_0
    //   5071: iastore
    //   5072: dup
    //   5073: bipush #17
    //   5075: ldc 4194320
    //   5077: iastore
    //   5078: dup
    //   5079: bipush #18
    //   5081: ldc 536887312
    //   5083: iastore
    //   5084: dup
    //   5085: bipush #19
    //   5087: sipush #16384
    //   5090: iastore
    //   5091: dup
    //   5092: bipush #20
    //   5094: ldc 4210688
    //   5096: iastore
    //   5097: dup
    //   5098: bipush #21
    //   5100: ldc 536887312
    //   5102: iastore
    //   5103: dup
    //   5104: bipush #22
    //   5106: bipush #16
    //   5108: iastore
    //   5109: dup
    //   5110: bipush #23
    //   5112: ldc 541065232
    //   5114: iastore
    //   5115: dup
    //   5116: bipush #24
    //   5118: ldc 541065232
    //   5120: iastore
    //   5121: dup
    //   5122: bipush #25
    //   5124: iconst_0
    //   5125: iastore
    //   5126: dup
    //   5127: bipush #26
    //   5129: ldc 4210704
    //   5131: iastore
    //   5132: dup
    //   5133: bipush #27
    //   5135: ldc 541081600
    //   5137: iastore
    //   5138: dup
    //   5139: bipush #28
    //   5141: sipush #16400
    //   5144: iastore
    //   5145: dup
    //   5146: bipush #29
    //   5148: ldc 4210688
    //   5150: iastore
    //   5151: dup
    //   5152: bipush #30
    //   5154: ldc 541081600
    //   5156: iastore
    //   5157: dup
    //   5158: bipush #31
    //   5160: ldc 536870912
    //   5162: iastore
    //   5163: dup
    //   5164: bipush #32
    //   5166: ldc 536887296
    //   5168: iastore
    //   5169: dup
    //   5170: bipush #33
    //   5172: bipush #16
    //   5174: iastore
    //   5175: dup
    //   5176: bipush #34
    //   5178: ldc 541065232
    //   5180: iastore
    //   5181: dup
    //   5182: bipush #35
    //   5184: ldc 4210688
    //   5186: iastore
    //   5187: dup
    //   5188: bipush #36
    //   5190: ldc 541081616
    //   5192: iastore
    //   5193: dup
    //   5194: bipush #37
    //   5196: ldc 4194304
    //   5198: iastore
    //   5199: dup
    //   5200: bipush #38
    //   5202: sipush #16400
    //   5205: iastore
    //   5206: dup
    //   5207: bipush #39
    //   5209: ldc 536870928
    //   5211: iastore
    //   5212: dup
    //   5213: bipush #40
    //   5215: ldc 4194304
    //   5217: iastore
    //   5218: dup
    //   5219: bipush #41
    //   5221: ldc 536887296
    //   5223: iastore
    //   5224: dup
    //   5225: bipush #42
    //   5227: ldc 536870912
    //   5229: iastore
    //   5230: dup
    //   5231: bipush #43
    //   5233: sipush #16400
    //   5236: iastore
    //   5237: dup
    //   5238: bipush #44
    //   5240: ldc 536870928
    //   5242: iastore
    //   5243: dup
    //   5244: bipush #45
    //   5246: ldc 541081616
    //   5248: iastore
    //   5249: dup
    //   5250: bipush #46
    //   5252: ldc 4210688
    //   5254: iastore
    //   5255: dup
    //   5256: bipush #47
    //   5258: ldc 541065216
    //   5260: iastore
    //   5261: dup
    //   5262: bipush #48
    //   5264: ldc 4210704
    //   5266: iastore
    //   5267: dup
    //   5268: bipush #49
    //   5270: ldc 541081600
    //   5272: iastore
    //   5273: dup
    //   5274: bipush #50
    //   5276: iconst_0
    //   5277: iastore
    //   5278: dup
    //   5279: bipush #51
    //   5281: ldc 541065232
    //   5283: iastore
    //   5284: dup
    //   5285: bipush #52
    //   5287: bipush #16
    //   5289: iastore
    //   5290: dup
    //   5291: bipush #53
    //   5293: sipush #16384
    //   5296: iastore
    //   5297: dup
    //   5298: bipush #54
    //   5300: ldc 541065216
    //   5302: iastore
    //   5303: dup
    //   5304: bipush #55
    //   5306: ldc 4210704
    //   5308: iastore
    //   5309: dup
    //   5310: bipush #56
    //   5312: sipush #16384
    //   5315: iastore
    //   5316: dup
    //   5317: bipush #57
    //   5319: ldc 4194320
    //   5321: iastore
    //   5322: dup
    //   5323: bipush #58
    //   5325: ldc 536887312
    //   5327: iastore
    //   5328: dup
    //   5329: bipush #59
    //   5331: iconst_0
    //   5332: iastore
    //   5333: dup
    //   5334: bipush #60
    //   5336: ldc 541081600
    //   5338: iastore
    //   5339: dup
    //   5340: bipush #61
    //   5342: ldc 536870912
    //   5344: iastore
    //   5345: dup
    //   5346: bipush #62
    //   5348: ldc 4194320
    //   5350: iastore
    //   5351: dup
    //   5352: bipush #63
    //   5354: ldc 536887312
    //   5356: iastore
    //   5357: astore #15
    //   5359: bipush #64
    //   5361: newarray int
    //   5363: dup
    //   5364: iconst_0
    //   5365: ldc 2097152
    //   5367: iastore
    //   5368: dup
    //   5369: iconst_1
    //   5370: ldc 69206018
    //   5372: iastore
    //   5373: dup
    //   5374: iconst_2
    //   5375: ldc 67110914
    //   5377: iastore
    //   5378: dup
    //   5379: iconst_3
    //   5380: iconst_0
    //   5381: iastore
    //   5382: dup
    //   5383: iconst_4
    //   5384: sipush #2048
    //   5387: iastore
    //   5388: dup
    //   5389: iconst_5
    //   5390: ldc 67110914
    //   5392: iastore
    //   5393: dup
    //   5394: bipush #6
    //   5396: ldc 2099202
    //   5398: iastore
    //   5399: dup
    //   5400: bipush #7
    //   5402: ldc 69208064
    //   5404: iastore
    //   5405: dup
    //   5406: bipush #8
    //   5408: ldc 69208066
    //   5410: iastore
    //   5411: dup
    //   5412: bipush #9
    //   5414: ldc 2097152
    //   5416: iastore
    //   5417: dup
    //   5418: bipush #10
    //   5420: iconst_0
    //   5421: iastore
    //   5422: dup
    //   5423: bipush #11
    //   5425: ldc 67108866
    //   5427: iastore
    //   5428: dup
    //   5429: bipush #12
    //   5431: iconst_2
    //   5432: iastore
    //   5433: dup
    //   5434: bipush #13
    //   5436: ldc 67108864
    //   5438: iastore
    //   5439: dup
    //   5440: bipush #14
    //   5442: ldc 69206018
    //   5444: iastore
    //   5445: dup
    //   5446: bipush #15
    //   5448: sipush #2050
    //   5451: iastore
    //   5452: dup
    //   5453: bipush #16
    //   5455: ldc 67110912
    //   5457: iastore
    //   5458: dup
    //   5459: bipush #17
    //   5461: ldc 2099202
    //   5463: iastore
    //   5464: dup
    //   5465: bipush #18
    //   5467: ldc 2097154
    //   5469: iastore
    //   5470: dup
    //   5471: bipush #19
    //   5473: ldc 67110912
    //   5475: iastore
    //   5476: dup
    //   5477: bipush #20
    //   5479: ldc 67108866
    //   5481: iastore
    //   5482: dup
    //   5483: bipush #21
    //   5485: ldc 69206016
    //   5487: iastore
    //   5488: dup
    //   5489: bipush #22
    //   5491: ldc 69208064
    //   5493: iastore
    //   5494: dup
    //   5495: bipush #23
    //   5497: ldc 2097154
    //   5499: iastore
    //   5500: dup
    //   5501: bipush #24
    //   5503: ldc 69206016
    //   5505: iastore
    //   5506: dup
    //   5507: bipush #25
    //   5509: sipush #2048
    //   5512: iastore
    //   5513: dup
    //   5514: bipush #26
    //   5516: sipush #2050
    //   5519: iastore
    //   5520: dup
    //   5521: bipush #27
    //   5523: ldc 69208066
    //   5525: iastore
    //   5526: dup
    //   5527: bipush #28
    //   5529: ldc 2099200
    //   5531: iastore
    //   5532: dup
    //   5533: bipush #29
    //   5535: iconst_2
    //   5536: iastore
    //   5537: dup
    //   5538: bipush #30
    //   5540: ldc 67108864
    //   5542: iastore
    //   5543: dup
    //   5544: bipush #31
    //   5546: ldc 2099200
    //   5548: iastore
    //   5549: dup
    //   5550: bipush #32
    //   5552: ldc 67108864
    //   5554: iastore
    //   5555: dup
    //   5556: bipush #33
    //   5558: ldc 2099200
    //   5560: iastore
    //   5561: dup
    //   5562: bipush #34
    //   5564: ldc 2097152
    //   5566: iastore
    //   5567: dup
    //   5568: bipush #35
    //   5570: ldc 67110914
    //   5572: iastore
    //   5573: dup
    //   5574: bipush #36
    //   5576: ldc 67110914
    //   5578: iastore
    //   5579: dup
    //   5580: bipush #37
    //   5582: ldc 69206018
    //   5584: iastore
    //   5585: dup
    //   5586: bipush #38
    //   5588: ldc 69206018
    //   5590: iastore
    //   5591: dup
    //   5592: bipush #39
    //   5594: iconst_2
    //   5595: iastore
    //   5596: dup
    //   5597: bipush #40
    //   5599: ldc 2097154
    //   5601: iastore
    //   5602: dup
    //   5603: bipush #41
    //   5605: ldc 67108864
    //   5607: iastore
    //   5608: dup
    //   5609: bipush #42
    //   5611: ldc 67110912
    //   5613: iastore
    //   5614: dup
    //   5615: bipush #43
    //   5617: ldc 2097152
    //   5619: iastore
    //   5620: dup
    //   5621: bipush #44
    //   5623: ldc 69208064
    //   5625: iastore
    //   5626: dup
    //   5627: bipush #45
    //   5629: sipush #2050
    //   5632: iastore
    //   5633: dup
    //   5634: bipush #46
    //   5636: ldc 2099202
    //   5638: iastore
    //   5639: dup
    //   5640: bipush #47
    //   5642: ldc 69208064
    //   5644: iastore
    //   5645: dup
    //   5646: bipush #48
    //   5648: sipush #2050
    //   5651: iastore
    //   5652: dup
    //   5653: bipush #49
    //   5655: ldc 67108866
    //   5657: iastore
    //   5658: dup
    //   5659: bipush #50
    //   5661: ldc 69208066
    //   5663: iastore
    //   5664: dup
    //   5665: bipush #51
    //   5667: ldc 69206016
    //   5669: iastore
    //   5670: dup
    //   5671: bipush #52
    //   5673: ldc 2099200
    //   5675: iastore
    //   5676: dup
    //   5677: bipush #53
    //   5679: iconst_0
    //   5680: iastore
    //   5681: dup
    //   5682: bipush #54
    //   5684: iconst_2
    //   5685: iastore
    //   5686: dup
    //   5687: bipush #55
    //   5689: ldc 69208066
    //   5691: iastore
    //   5692: dup
    //   5693: bipush #56
    //   5695: iconst_0
    //   5696: iastore
    //   5697: dup
    //   5698: bipush #57
    //   5700: ldc 2099202
    //   5702: iastore
    //   5703: dup
    //   5704: bipush #58
    //   5706: ldc 69206016
    //   5708: iastore
    //   5709: dup
    //   5710: bipush #59
    //   5712: sipush #2048
    //   5715: iastore
    //   5716: dup
    //   5717: bipush #60
    //   5719: ldc 67108866
    //   5721: iastore
    //   5722: dup
    //   5723: bipush #61
    //   5725: ldc 67110912
    //   5727: iastore
    //   5728: dup
    //   5729: bipush #62
    //   5731: sipush #2048
    //   5734: iastore
    //   5735: dup
    //   5736: bipush #63
    //   5738: ldc 2097154
    //   5740: iastore
    //   5741: astore #16
    //   5743: bipush #64
    //   5745: newarray int
    //   5747: dup
    //   5748: iconst_0
    //   5749: ldc 268439616
    //   5751: iastore
    //   5752: dup
    //   5753: iconst_1
    //   5754: sipush #4096
    //   5757: iastore
    //   5758: dup
    //   5759: iconst_2
    //   5760: ldc 262144
    //   5762: iastore
    //   5763: dup
    //   5764: iconst_3
    //   5765: ldc 268701760
    //   5767: iastore
    //   5768: dup
    //   5769: iconst_4
    //   5770: ldc 268435456
    //   5772: iastore
    //   5773: dup
    //   5774: iconst_5
    //   5775: ldc 268439616
    //   5777: iastore
    //   5778: dup
    //   5779: bipush #6
    //   5781: bipush #64
    //   5783: iastore
    //   5784: dup
    //   5785: bipush #7
    //   5787: ldc 268435456
    //   5789: iastore
    //   5790: dup
    //   5791: bipush #8
    //   5793: ldc 262208
    //   5795: iastore
    //   5796: dup
    //   5797: bipush #9
    //   5799: ldc 268697600
    //   5801: iastore
    //   5802: dup
    //   5803: bipush #10
    //   5805: ldc 268701760
    //   5807: iastore
    //   5808: dup
    //   5809: bipush #11
    //   5811: ldc 266240
    //   5813: iastore
    //   5814: dup
    //   5815: bipush #12
    //   5817: ldc 268701696
    //   5819: iastore
    //   5820: dup
    //   5821: bipush #13
    //   5823: ldc 266304
    //   5825: iastore
    //   5826: dup
    //   5827: bipush #14
    //   5829: sipush #4096
    //   5832: iastore
    //   5833: dup
    //   5834: bipush #15
    //   5836: bipush #64
    //   5838: iastore
    //   5839: dup
    //   5840: bipush #16
    //   5842: ldc 268697600
    //   5844: iastore
    //   5845: dup
    //   5846: bipush #17
    //   5848: ldc 268435520
    //   5850: iastore
    //   5851: dup
    //   5852: bipush #18
    //   5854: ldc 268439552
    //   5856: iastore
    //   5857: dup
    //   5858: bipush #19
    //   5860: sipush #4160
    //   5863: iastore
    //   5864: dup
    //   5865: bipush #20
    //   5867: ldc 266240
    //   5869: iastore
    //   5870: dup
    //   5871: bipush #21
    //   5873: ldc 262208
    //   5875: iastore
    //   5876: dup
    //   5877: bipush #22
    //   5879: ldc 268697664
    //   5881: iastore
    //   5882: dup
    //   5883: bipush #23
    //   5885: ldc 268701696
    //   5887: iastore
    //   5888: dup
    //   5889: bipush #24
    //   5891: sipush #4160
    //   5894: iastore
    //   5895: dup
    //   5896: bipush #25
    //   5898: iconst_0
    //   5899: iastore
    //   5900: dup
    //   5901: bipush #26
    //   5903: iconst_0
    //   5904: iastore
    //   5905: dup
    //   5906: bipush #27
    //   5908: ldc 268697664
    //   5910: iastore
    //   5911: dup
    //   5912: bipush #28
    //   5914: ldc 268435520
    //   5916: iastore
    //   5917: dup
    //   5918: bipush #29
    //   5920: ldc 268439552
    //   5922: iastore
    //   5923: dup
    //   5924: bipush #30
    //   5926: ldc 266304
    //   5928: iastore
    //   5929: dup
    //   5930: bipush #31
    //   5932: ldc 262144
    //   5934: iastore
    //   5935: dup
    //   5936: bipush #32
    //   5938: ldc 266304
    //   5940: iastore
    //   5941: dup
    //   5942: bipush #33
    //   5944: ldc 262144
    //   5946: iastore
    //   5947: dup
    //   5948: bipush #34
    //   5950: ldc 268701696
    //   5952: iastore
    //   5953: dup
    //   5954: bipush #35
    //   5956: sipush #4096
    //   5959: iastore
    //   5960: dup
    //   5961: bipush #36
    //   5963: bipush #64
    //   5965: iastore
    //   5966: dup
    //   5967: bipush #37
    //   5969: ldc 268697664
    //   5971: iastore
    //   5972: dup
    //   5973: bipush #38
    //   5975: sipush #4096
    //   5978: iastore
    //   5979: dup
    //   5980: bipush #39
    //   5982: ldc 266304
    //   5984: iastore
    //   5985: dup
    //   5986: bipush #40
    //   5988: ldc 268439552
    //   5990: iastore
    //   5991: dup
    //   5992: bipush #41
    //   5994: bipush #64
    //   5996: iastore
    //   5997: dup
    //   5998: bipush #42
    //   6000: ldc 268435520
    //   6002: iastore
    //   6003: dup
    //   6004: bipush #43
    //   6006: ldc 268697600
    //   6008: iastore
    //   6009: dup
    //   6010: bipush #44
    //   6012: ldc 268697664
    //   6014: iastore
    //   6015: dup
    //   6016: bipush #45
    //   6018: ldc 268435456
    //   6020: iastore
    //   6021: dup
    //   6022: bipush #46
    //   6024: ldc 262144
    //   6026: iastore
    //   6027: dup
    //   6028: bipush #47
    //   6030: ldc 268439616
    //   6032: iastore
    //   6033: dup
    //   6034: bipush #48
    //   6036: iconst_0
    //   6037: iastore
    //   6038: dup
    //   6039: bipush #49
    //   6041: ldc 268701760
    //   6043: iastore
    //   6044: dup
    //   6045: bipush #50
    //   6047: ldc 262208
    //   6049: iastore
    //   6050: dup
    //   6051: bipush #51
    //   6053: ldc 268435520
    //   6055: iastore
    //   6056: dup
    //   6057: bipush #52
    //   6059: ldc 268697600
    //   6061: iastore
    //   6062: dup
    //   6063: bipush #53
    //   6065: ldc 268439552
    //   6067: iastore
    //   6068: dup
    //   6069: bipush #54
    //   6071: ldc 268439616
    //   6073: iastore
    //   6074: dup
    //   6075: bipush #55
    //   6077: iconst_0
    //   6078: iastore
    //   6079: dup
    //   6080: bipush #56
    //   6082: ldc 268701760
    //   6084: iastore
    //   6085: dup
    //   6086: bipush #57
    //   6088: ldc 266240
    //   6090: iastore
    //   6091: dup
    //   6092: bipush #58
    //   6094: ldc 266240
    //   6096: iastore
    //   6097: dup
    //   6098: bipush #59
    //   6100: sipush #4160
    //   6103: iastore
    //   6104: dup
    //   6105: bipush #60
    //   6107: sipush #4160
    //   6110: iastore
    //   6111: dup
    //   6112: bipush #61
    //   6114: ldc 262208
    //   6116: iastore
    //   6117: dup
    //   6118: bipush #62
    //   6120: ldc 268435456
    //   6122: iastore
    //   6123: dup
    //   6124: bipush #63
    //   6126: ldc 268701696
    //   6128: iastore
    //   6129: astore #17
    //   6131: aload #5
    //   6133: arraylength
    //   6134: istore #18
    //   6136: iconst_2
    //   6137: newarray int
    //   6139: astore #19
    //   6141: iload #18
    //   6143: newarray byte
    //   6145: astore #6
    //   6147: iload #18
    //   6149: bipush #8
    //   6151: idiv
    //   6152: istore #20
    //   6154: iconst_0
    //   6155: istore #21
    //   6157: iload #21
    //   6159: iload #20
    //   6161: if_icmpge -> 7079
    //   6164: iload #21
    //   6166: bipush #8
    //   6168: imul
    //   6169: istore #22
    //   6171: iconst_0
    //   6172: istore #23
    //   6174: iload #23
    //   6176: iconst_2
    //   6177: if_icmpge -> 6266
    //   6180: aload #19
    //   6182: iload #23
    //   6184: aload #5
    //   6186: iload #22
    //   6188: iload #23
    //   6190: iconst_4
    //   6191: imul
    //   6192: iadd
    //   6193: baload
    //   6194: sipush #255
    //   6197: iand
    //   6198: bipush #24
    //   6200: ishl
    //   6201: aload #5
    //   6203: iload #22
    //   6205: iload #23
    //   6207: iconst_4
    //   6208: imul
    //   6209: iadd
    //   6210: iconst_1
    //   6211: iadd
    //   6212: baload
    //   6213: sipush #255
    //   6216: iand
    //   6217: bipush #16
    //   6219: ishl
    //   6220: ior
    //   6221: aload #5
    //   6223: iload #22
    //   6225: iload #23
    //   6227: iconst_4
    //   6228: imul
    //   6229: iadd
    //   6230: iconst_2
    //   6231: iadd
    //   6232: baload
    //   6233: sipush #255
    //   6236: iand
    //   6237: bipush #8
    //   6239: ishl
    //   6240: ior
    //   6241: aload #5
    //   6243: iload #22
    //   6245: iload #23
    //   6247: iconst_4
    //   6248: imul
    //   6249: iadd
    //   6250: iconst_3
    //   6251: iadd
    //   6252: baload
    //   6253: sipush #255
    //   6256: iand
    //   6257: ior
    //   6258: iastore
    //   6259: iinc #23, 1
    //   6262: iload_2
    //   6263: ifne -> 6174
    //   6266: iconst_0
    //   6267: istore #28
    //   6269: aload #19
    //   6271: iconst_0
    //   6272: iaload
    //   6273: istore #26
    //   6275: aload #19
    //   6277: iconst_1
    //   6278: iaload
    //   6279: istore #25
    //   6281: iload #26
    //   6283: iconst_4
    //   6284: iushr
    //   6285: iload #25
    //   6287: ixor
    //   6288: ldc 252645135
    //   6290: iand
    //   6291: istore #24
    //   6293: iload #25
    //   6295: iload #24
    //   6297: ixor
    //   6298: istore #25
    //   6300: iload #26
    //   6302: iload #24
    //   6304: iconst_4
    //   6305: ishl
    //   6306: ixor
    //   6307: istore #26
    //   6309: iload #26
    //   6311: bipush #16
    //   6313: iushr
    //   6314: iload #25
    //   6316: ixor
    //   6317: ldc 65535
    //   6319: iand
    //   6320: istore #24
    //   6322: iload #25
    //   6324: iload #24
    //   6326: ixor
    //   6327: istore #25
    //   6329: iload #26
    //   6331: iload #24
    //   6333: bipush #16
    //   6335: ishl
    //   6336: ixor
    //   6337: istore #26
    //   6339: iload #25
    //   6341: iconst_2
    //   6342: iushr
    //   6343: iload #26
    //   6345: ixor
    //   6346: ldc 858993459
    //   6348: iand
    //   6349: istore #24
    //   6351: iload #26
    //   6353: iload #24
    //   6355: ixor
    //   6356: istore #26
    //   6358: iload #25
    //   6360: iload #24
    //   6362: iconst_2
    //   6363: ishl
    //   6364: ixor
    //   6365: istore #25
    //   6367: iload #25
    //   6369: bipush #8
    //   6371: iushr
    //   6372: iload #26
    //   6374: ixor
    //   6375: ldc 16711935
    //   6377: iand
    //   6378: istore #24
    //   6380: iload #26
    //   6382: iload #24
    //   6384: ixor
    //   6385: istore #26
    //   6387: iload #25
    //   6389: iload #24
    //   6391: bipush #8
    //   6393: ishl
    //   6394: ixor
    //   6395: istore #25
    //   6397: iload #25
    //   6399: iconst_1
    //   6400: ishl
    //   6401: iload #25
    //   6403: bipush #31
    //   6405: iushr
    //   6406: iconst_1
    //   6407: iand
    //   6408: ior
    //   6409: istore #25
    //   6411: iload #26
    //   6413: iload #25
    //   6415: ixor
    //   6416: ldc -1431655766
    //   6418: iand
    //   6419: istore #24
    //   6421: iload #26
    //   6423: iload #24
    //   6425: ixor
    //   6426: istore #26
    //   6428: iload #25
    //   6430: iload #24
    //   6432: ixor
    //   6433: istore #25
    //   6435: iload #26
    //   6437: iconst_1
    //   6438: ishl
    //   6439: iload #26
    //   6441: bipush #31
    //   6443: iushr
    //   6444: iconst_1
    //   6445: iand
    //   6446: ior
    //   6447: istore #26
    //   6449: iconst_0
    //   6450: istore #27
    //   6452: iload #27
    //   6454: bipush #8
    //   6456: if_icmpge -> 6794
    //   6459: iload #25
    //   6461: bipush #28
    //   6463: ishl
    //   6464: iload #25
    //   6466: iconst_4
    //   6467: iushr
    //   6468: ior
    //   6469: istore #24
    //   6471: iload #24
    //   6473: aload #7
    //   6475: iload #28
    //   6477: iinc #28, 1
    //   6480: iaload
    //   6481: ixor
    //   6482: istore #24
    //   6484: aload #16
    //   6486: iload #24
    //   6488: bipush #63
    //   6490: iand
    //   6491: iaload
    //   6492: istore #23
    //   6494: iload #23
    //   6496: aload #14
    //   6498: iload #24
    //   6500: bipush #8
    //   6502: iushr
    //   6503: bipush #63
    //   6505: iand
    //   6506: iaload
    //   6507: ior
    //   6508: istore #23
    //   6510: iload #23
    //   6512: aload #12
    //   6514: iload #24
    //   6516: bipush #16
    //   6518: iushr
    //   6519: bipush #63
    //   6521: iand
    //   6522: iaload
    //   6523: ior
    //   6524: istore #23
    //   6526: iload #23
    //   6528: aload #10
    //   6530: iload #24
    //   6532: bipush #24
    //   6534: iushr
    //   6535: bipush #63
    //   6537: iand
    //   6538: iaload
    //   6539: ior
    //   6540: istore #23
    //   6542: iload #25
    //   6544: aload #7
    //   6546: iload #28
    //   6548: iinc #28, 1
    //   6551: iaload
    //   6552: ixor
    //   6553: istore #24
    //   6555: iload #23
    //   6557: aload #17
    //   6559: iload #24
    //   6561: bipush #63
    //   6563: iand
    //   6564: iaload
    //   6565: ior
    //   6566: istore #23
    //   6568: iload #23
    //   6570: aload #15
    //   6572: iload #24
    //   6574: bipush #8
    //   6576: iushr
    //   6577: bipush #63
    //   6579: iand
    //   6580: iaload
    //   6581: ior
    //   6582: istore #23
    //   6584: iload #23
    //   6586: aload #13
    //   6588: iload #24
    //   6590: bipush #16
    //   6592: iushr
    //   6593: bipush #63
    //   6595: iand
    //   6596: iaload
    //   6597: ior
    //   6598: istore #23
    //   6600: iload #23
    //   6602: aload #11
    //   6604: iload #24
    //   6606: bipush #24
    //   6608: iushr
    //   6609: bipush #63
    //   6611: iand
    //   6612: iaload
    //   6613: ior
    //   6614: istore #23
    //   6616: iload #26
    //   6618: iload #23
    //   6620: ixor
    //   6621: istore #26
    //   6623: iload #26
    //   6625: bipush #28
    //   6627: ishl
    //   6628: iload #26
    //   6630: iconst_4
    //   6631: iushr
    //   6632: ior
    //   6633: istore #24
    //   6635: iload #24
    //   6637: aload #7
    //   6639: iload #28
    //   6641: iinc #28, 1
    //   6644: iaload
    //   6645: ixor
    //   6646: istore #24
    //   6648: aload #16
    //   6650: iload #24
    //   6652: bipush #63
    //   6654: iand
    //   6655: iaload
    //   6656: istore #23
    //   6658: iload #23
    //   6660: aload #14
    //   6662: iload #24
    //   6664: bipush #8
    //   6666: iushr
    //   6667: bipush #63
    //   6669: iand
    //   6670: iaload
    //   6671: ior
    //   6672: istore #23
    //   6674: iload #23
    //   6676: aload #12
    //   6678: iload #24
    //   6680: bipush #16
    //   6682: iushr
    //   6683: bipush #63
    //   6685: iand
    //   6686: iaload
    //   6687: ior
    //   6688: istore #23
    //   6690: iload #23
    //   6692: aload #10
    //   6694: iload #24
    //   6696: bipush #24
    //   6698: iushr
    //   6699: bipush #63
    //   6701: iand
    //   6702: iaload
    //   6703: ior
    //   6704: istore #23
    //   6706: iload #26
    //   6708: aload #7
    //   6710: iload #28
    //   6712: iinc #28, 1
    //   6715: iaload
    //   6716: ixor
    //   6717: istore #24
    //   6719: iload #23
    //   6721: aload #17
    //   6723: iload #24
    //   6725: bipush #63
    //   6727: iand
    //   6728: iaload
    //   6729: ior
    //   6730: istore #23
    //   6732: iload #23
    //   6734: aload #15
    //   6736: iload #24
    //   6738: bipush #8
    //   6740: iushr
    //   6741: bipush #63
    //   6743: iand
    //   6744: iaload
    //   6745: ior
    //   6746: istore #23
    //   6748: iload #23
    //   6750: aload #13
    //   6752: iload #24
    //   6754: bipush #16
    //   6756: iushr
    //   6757: bipush #63
    //   6759: iand
    //   6760: iaload
    //   6761: ior
    //   6762: istore #23
    //   6764: iload #23
    //   6766: aload #11
    //   6768: iload #24
    //   6770: bipush #24
    //   6772: iushr
    //   6773: bipush #63
    //   6775: iand
    //   6776: iaload
    //   6777: ior
    //   6778: istore #23
    //   6780: iload #25
    //   6782: iload #23
    //   6784: ixor
    //   6785: istore #25
    //   6787: iinc #27, 1
    //   6790: iload_2
    //   6791: ifne -> 6452
    //   6794: iload #25
    //   6796: bipush #31
    //   6798: ishl
    //   6799: iload #25
    //   6801: iconst_1
    //   6802: iushr
    //   6803: ior
    //   6804: istore #25
    //   6806: iload #26
    //   6808: iload #25
    //   6810: ixor
    //   6811: ldc -1431655766
    //   6813: iand
    //   6814: istore #24
    //   6816: iload #26
    //   6818: iload #24
    //   6820: ixor
    //   6821: istore #26
    //   6823: iload #25
    //   6825: iload #24
    //   6827: ixor
    //   6828: istore #25
    //   6830: iload #26
    //   6832: bipush #31
    //   6834: ishl
    //   6835: iload #26
    //   6837: iconst_1
    //   6838: iushr
    //   6839: ior
    //   6840: istore #26
    //   6842: iload #26
    //   6844: bipush #8
    //   6846: iushr
    //   6847: iload #25
    //   6849: ixor
    //   6850: ldc 16711935
    //   6852: iand
    //   6853: istore #24
    //   6855: iload #25
    //   6857: iload #24
    //   6859: ixor
    //   6860: istore #25
    //   6862: iload #26
    //   6864: iload #24
    //   6866: bipush #8
    //   6868: ishl
    //   6869: ixor
    //   6870: istore #26
    //   6872: iload #26
    //   6874: iconst_2
    //   6875: iushr
    //   6876: iload #25
    //   6878: ixor
    //   6879: ldc 858993459
    //   6881: iand
    //   6882: istore #24
    //   6884: iload #25
    //   6886: iload #24
    //   6888: ixor
    //   6889: istore #25
    //   6891: iload #26
    //   6893: iload #24
    //   6895: iconst_2
    //   6896: ishl
    //   6897: ixor
    //   6898: istore #26
    //   6900: iload #25
    //   6902: bipush #16
    //   6904: iushr
    //   6905: iload #26
    //   6907: ixor
    //   6908: ldc 65535
    //   6910: iand
    //   6911: istore #24
    //   6913: iload #26
    //   6915: iload #24
    //   6917: ixor
    //   6918: istore #26
    //   6920: iload #25
    //   6922: iload #24
    //   6924: bipush #16
    //   6926: ishl
    //   6927: ixor
    //   6928: istore #25
    //   6930: iload #25
    //   6932: iconst_4
    //   6933: iushr
    //   6934: iload #26
    //   6936: ixor
    //   6937: ldc 252645135
    //   6939: iand
    //   6940: istore #24
    //   6942: iload #26
    //   6944: iload #24
    //   6946: ixor
    //   6947: istore #26
    //   6949: iload #25
    //   6951: iload #24
    //   6953: iconst_4
    //   6954: ishl
    //   6955: ixor
    //   6956: istore #25
    //   6958: aload #19
    //   6960: iconst_0
    //   6961: iload #25
    //   6963: iastore
    //   6964: aload #19
    //   6966: iconst_1
    //   6967: iload #26
    //   6969: iastore
    //   6970: iload #21
    //   6972: bipush #8
    //   6974: imul
    //   6975: istore #29
    //   6977: iconst_0
    //   6978: istore #30
    //   6980: iload #30
    //   6982: iconst_2
    //   6983: if_icmpge -> 7072
    //   6986: aload #6
    //   6988: iload #29
    //   6990: iload #30
    //   6992: iconst_4
    //   6993: imul
    //   6994: iadd
    //   6995: aload #19
    //   6997: iload #30
    //   6999: iaload
    //   7000: bipush #24
    //   7002: iushr
    //   7003: i2b
    //   7004: bastore
    //   7005: aload #6
    //   7007: iload #29
    //   7009: iload #30
    //   7011: iconst_4
    //   7012: imul
    //   7013: iadd
    //   7014: iconst_1
    //   7015: iadd
    //   7016: aload #19
    //   7018: iload #30
    //   7020: iaload
    //   7021: bipush #16
    //   7023: iushr
    //   7024: i2b
    //   7025: bastore
    //   7026: aload #6
    //   7028: iload #29
    //   7030: iload #30
    //   7032: iconst_4
    //   7033: imul
    //   7034: iadd
    //   7035: iconst_2
    //   7036: iadd
    //   7037: aload #19
    //   7039: iload #30
    //   7041: iaload
    //   7042: bipush #8
    //   7044: iushr
    //   7045: i2b
    //   7046: bastore
    //   7047: aload #6
    //   7049: iload #29
    //   7051: iload #30
    //   7053: iconst_4
    //   7054: imul
    //   7055: iadd
    //   7056: iconst_3
    //   7057: iadd
    //   7058: aload #19
    //   7060: iload #30
    //   7062: iaload
    //   7063: i2b
    //   7064: bastore
    //   7065: iinc #30, 1
    //   7068: iload_2
    //   7069: ifne -> 6980
    //   7072: iinc #21, 1
    //   7075: iload_2
    //   7076: ifne -> 6157
    //   7079: new java/math/BigInteger
    //   7082: dup
    //   7083: aload #6
    //   7085: invokespecial <init> : ([B)V
    //   7088: invokevirtual abs : ()Ljava/math/BigInteger;
    //   7091: putstatic burp/Zgfq.Za : Ljava/lang/Object;
    //   7094: sipush #-5593
    //   7097: sipush #11490
    //   7100: invokestatic a : (II)Ljava/lang/String;
    //   7103: iconst_1
    //   7104: ldc burp/Zxf8
    //   7106: invokevirtual getClassLoader : ()Ljava/lang/ClassLoader;
    //   7109: invokestatic forName : (Ljava/lang/String;ZLjava/lang/ClassLoader;)Ljava/lang/Class;
    //   7112: invokevirtual getDeclaredFields : ()[Ljava/lang/reflect/Field;
    //   7115: astore #5
    //   7117: aload #5
    //   7119: arraylength
    //   7120: istore #6
    //   7122: iconst_0
    //   7123: istore #7
    //   7125: iload #7
    //   7127: iload #6
    //   7129: if_icmpge -> 7267
    //   7132: aload #5
    //   7134: iload #7
    //   7136: aaload
    //   7137: astore #8
    //   7139: aload #8
    //   7141: invokevirtual getModifiers : ()I
    //   7144: invokestatic isStatic : (I)Z
    //   7147: ifne -> 7157
    //   7150: goto -> 7260
    //   7153: invokestatic a : (Ljava/lang/Throwable;)Ljava/lang/Throwable;
    //   7156: athrow
    //   7157: aload #8
    //   7159: invokevirtual getType : ()Ljava/lang/Class;
    //   7162: astore #9
    //   7164: aload #9
    //   7166: ifnull -> 7247
    //   7169: aload #9
    //   7171: invokevirtual isPrimitive : ()Z
    //   7174: ifne -> 7247
    //   7177: goto -> 7184
    //   7180: invokestatic a : (Ljava/lang/Throwable;)Ljava/lang/Throwable;
    //   7183: athrow
    //   7184: aload #9
    //   7186: invokevirtual getPackage : ()Ljava/lang/Package;
    //   7189: ifnull -> 7247
    //   7192: goto -> 7199
    //   7195: invokestatic a : (Ljava/lang/Throwable;)Ljava/lang/Throwable;
    //   7198: athrow
    //   7199: aload #9
    //   7201: invokevirtual getPackage : ()Ljava/lang/Package;
    //   7204: invokevirtual getName : ()Ljava/lang/String;
    //   7207: ifnull -> 7247
    //   7210: goto -> 7217
    //   7213: invokestatic a : (Ljava/lang/Throwable;)Ljava/lang/Throwable;
    //   7216: athrow
    //   7217: aload #9
    //   7219: invokevirtual getPackage : ()Ljava/lang/Package;
    //   7222: invokevirtual getName : ()Ljava/lang/String;
    //   7225: sipush #-5595
    //   7228: sipush #-13294
    //   7231: invokestatic a : (II)Ljava/lang/String;
    //   7234: invokevirtual startsWith : (Ljava/lang/String;)Z
    //   7237: ifne -> 7247
    //   7240: goto -> 7247
    //   7243: invokestatic a : (Ljava/lang/Throwable;)Ljava/lang/Throwable;
    //   7246: athrow
    //   7247: aload #8
    //   7249: iconst_1
    //   7250: invokevirtual setAccessible : (Z)V
    //   7253: aload #8
    //   7255: aconst_null
    //   7256: invokevirtual get : (Ljava/lang/Object;)Ljava/lang/Object;
    //   7259: pop
    //   7260: iinc #7, 1
    //   7263: iload_2
    //   7264: ifne -> 7125
    //   7267: sipush #-5598
    //   7270: sipush #8385
    //   7273: invokestatic a : (II)Ljava/lang/String;
    //   7276: invokestatic forName : (Ljava/lang/String;)Ljava/lang/Class;
    //   7279: invokevirtual getDeclaredMethods : ()[Ljava/lang/reflect/Method;
    //   7282: astore #5
    //   7284: aload #5
    //   7286: arraylength
    //   7287: istore #6
    //   7289: iconst_0
    //   7290: istore #7
    //   7292: iload #7
    //   7294: iload #6
    //   7296: if_icmpge -> 7429
    //   7299: aload #5
    //   7301: iload #7
    //   7303: aaload
    //   7304: astore #8
    //   7306: aload #8
    //   7308: invokevirtual getParameterTypes : ()[Ljava/lang/Class;
    //   7311: pop
    //   7312: aload #8
    //   7314: invokevirtual getModifiers : ()I
    //   7317: invokestatic isStatic : (I)Z
    //   7320: ifeq -> 7415
    //   7323: aload #8
    //   7325: invokevirtual getParameterTypes : ()[Ljava/lang/Class;
    //   7328: arraylength
    //   7329: iconst_2
    //   7330: if_icmpne -> 7415
    //   7333: goto -> 7340
    //   7336: invokestatic a : (Ljava/lang/Throwable;)Ljava/lang/Throwable;
    //   7339: athrow
    //   7340: aload #8
    //   7342: invokevirtual getReturnType : ()Ljava/lang/Class;
    //   7345: getstatic java/lang/Void.TYPE : Ljava/lang/Class;
    //   7348: invokevirtual equals : (Ljava/lang/Object;)Z
    //   7351: ifeq -> 7415
    //   7354: goto -> 7361
    //   7357: invokestatic a : (Ljava/lang/Throwable;)Ljava/lang/Throwable;
    //   7360: athrow
    //   7361: aload #8
    //   7363: iconst_1
    //   7364: invokevirtual setAccessible : (Z)V
    //   7367: aload #8
    //   7369: aconst_null
    //   7370: iconst_2
    //   7371: anewarray java/lang/Object
    //   7374: dup
    //   7375: iconst_0
    //   7376: aload_0
    //   7377: aastore
    //   7378: dup
    //   7379: iconst_1
    //   7380: aload_1
    //   7381: ifnonnull -> 7399
    //   7384: goto -> 7391
    //   7387: invokestatic a : (Ljava/lang/Throwable;)Ljava/lang/Throwable;
    //   7390: athrow
    //   7391: aload_1
    //   7392: goto -> 7406
    //   7395: invokestatic a : (Ljava/lang/Throwable;)Ljava/lang/Throwable;
    //   7398: athrow
    //   7399: aload_1
    //   7400: checkcast [B
    //   7403: invokevirtual clone : ()Ljava/lang/Object;
    //   7406: aastore
    //   7407: invokevirtual invoke : (Ljava/lang/Object;[Ljava/lang/Object;)Ljava/lang/Object;
    //   7410: pop
    //   7411: iload_2
    //   7412: ifne -> 7429
    //   7415: iinc #7, 1
    //   7418: iload_2
    //   7419: ifne -> 7292
    //   7422: goto -> 7429
    //   7425: invokestatic a : (Ljava/lang/Throwable;)Ljava/lang/Throwable;
    //   7428: athrow
    //   7429: getstatic burp/Zxzt.ZG : Ljava/lang/String;
    //   7432: getstatic burp/Zxti.ZJ : Ljava/lang/Object;
    //   7435: checkcast java/math/BigInteger
    //   7438: invokevirtual intValue : ()I
    //   7441: bipush #32
    //   7443: irem
    //   7444: invokestatic abs : (I)I
    //   7447: invokevirtual charAt : (I)C
    //   7450: getstatic burp/Zkby.Zf : Ljava/lang/String;
    //   7453: getstatic burp/Zm54.ZS : Ljava/lang/Object;
    //   7456: checkcast java/math/BigInteger
    //   7459: invokevirtual intValue : ()I
    //   7462: bipush #32
    //   7464: irem
    //   7465: invokestatic abs : (I)I
    //   7468: invokevirtual charAt : (I)C
    //   7471: if_icmple -> 7578
    //   7474: getstatic burp/Zrqd.Zk : Ljava/lang/String;
    //   7477: getstatic burp/Zs4v.ZB : Ljava/lang/Object;
    //   7480: checkcast java/math/BigInteger
    //   7483: invokevirtual intValue : ()I
    //   7486: bipush #32
    //   7488: irem
    //   7489: invokestatic abs : (I)I
    //   7492: invokevirtual charAt : (I)C
    //   7495: getstatic burp/Zgil.ZK : Ljava/lang/String;
    //   7498: getstatic burp/Zsq6.ZS : Ljava/lang/Object;
    //   7501: checkcast java/math/BigInteger
    //   7504: invokevirtual intValue : ()I
    //   7507: bipush #32
    //   7509: irem
    //   7510: invokestatic abs : (I)I
    //   7513: invokevirtual charAt : (I)C
    //   7516: if_icmpgt -> 7578
    //   7519: goto -> 7526
    //   7522: invokestatic a : (Ljava/lang/Throwable;)Ljava/lang/Throwable;
    //   7525: athrow
    //   7526: getstatic burp/Zgx6.ZX : Ljava/lang/String;
    //   7529: getstatic burp/Zs4v.ZB : Ljava/lang/Object;
    //   7532: checkcast java/math/BigInteger
    //   7535: invokevirtual intValue : ()I
    //   7538: bipush #32
    //   7540: irem
    //   7541: invokestatic abs : (I)I
    //   7544: invokevirtual charAt : (I)C
    //   7547: getstatic burp/Zg_y.ZF : Ljava/lang/String;
    //   7550: getstatic burp/Zgb9.Zb : Ljava/lang/Object;
    //   7553: checkcast java/math/BigInteger
    //   7556: invokevirtual intValue : ()I
    //   7559: bipush #32
    //   7561: irem
    //   7562: invokestatic abs : (I)I
    //   7565: invokevirtual charAt : (I)C
    //   7568: if_icmple -> 7586
    //   7571: goto -> 7578
    //   7574: invokestatic a : (Ljava/lang/Throwable;)Ljava/lang/Throwable;
    //   7577: athrow
    //   7578: iconst_1
    //   7579: goto -> 7587
    //   7582: invokestatic a : (Ljava/lang/Throwable;)Ljava/lang/Throwable;
    //   7585: athrow
    //   7586: iconst_0
    //   7587: ireturn
    //   7588: astore_3
    //   7589: new java/lang/Exception
    //   7592: dup
    //   7593: aload_3
    //   7594: invokevirtual getMessage : ()Ljava/lang/String;
    //   7597: invokespecial <init> : (Ljava/lang/String;)V
    //   7600: athrow
    // Exception table:
    //   from	to	target	type
    //   4	7587	7588	java/lang/Throwable
    //   22	198	201	java/lang/Throwable
    //   168	235	238	java/lang/Throwable
    //   205	272	275	java/lang/Throwable
    //   242	309	312	java/lang/Throwable
    //   279	346	349	java/lang/Throwable
    //   316	383	386	java/lang/Throwable
    //   353	420	423	java/lang/Throwable
    //   390	457	460	java/lang/Throwable
    //   427	494	497	java/lang/Throwable
    //   464	531	534	java/lang/Throwable
    //   501	568	571	java/lang/Throwable
    //   538	605	608	java/lang/Throwable
    //   575	642	645	java/lang/Throwable
    //   612	679	682	java/lang/Throwable
    //   649	716	719	java/lang/Throwable
    //   686	753	756	java/lang/Throwable
    //   723	790	793	java/lang/Throwable
    //   760	827	830	java/lang/Throwable
    //   797	864	867	java/lang/Throwable
    //   834	901	904	java/lang/Throwable
    //   871	938	941	java/lang/Throwable
    //   908	975	978	java/lang/Throwable
    //   945	1012	1015	java/lang/Throwable
    //   982	1049	1052	java/lang/Throwable
    //   1019	1086	1089	java/lang/Throwable
    //   1056	1123	1126	java/lang/Throwable
    //   1093	1160	1163	java/lang/Throwable
    //   1130	1197	1200	java/lang/Throwable
    //   1167	1234	1237	java/lang/Throwable
    //   1204	1271	1274	java/lang/Throwable
    //   1241	1308	1311	java/lang/Throwable
    //   1278	1341	1344	java/lang/Throwable
    //   1381	1555	1558	java/lang/Throwable
    //   1524	1593	1596	java/lang/Throwable
    //   1562	1631	1634	java/lang/Throwable
    //   1600	1669	1672	java/lang/Throwable
    //   1638	1707	1710	java/lang/Throwable
    //   1676	1745	1748	java/lang/Throwable
    //   1714	1783	1786	java/lang/Throwable
    //   1752	1821	1824	java/lang/Throwable
    //   1790	1859	1862	java/lang/Throwable
    //   1828	1897	1900	java/lang/Throwable
    //   1866	1935	1938	java/lang/Throwable
    //   1904	1973	1976	java/lang/Throwable
    //   1942	2011	2014	java/lang/Throwable
    //   1980	2049	2052	java/lang/Throwable
    //   2018	2087	2090	java/lang/Throwable
    //   2056	2125	2128	java/lang/Throwable
    //   2094	2163	2166	java/lang/Throwable
    //   2132	2201	2204	java/lang/Throwable
    //   2170	2239	2242	java/lang/Throwable
    //   2208	2277	2280	java/lang/Throwable
    //   2246	2315	2318	java/lang/Throwable
    //   2284	2353	2356	java/lang/Throwable
    //   2322	2391	2394	java/lang/Throwable
    //   2360	2429	2432	java/lang/Throwable
    //   2398	2467	2470	java/lang/Throwable
    //   2436	2505	2508	java/lang/Throwable
    //   2474	2543	2546	java/lang/Throwable
    //   2512	2581	2584	java/lang/Throwable
    //   2550	2619	2622	java/lang/Throwable
    //   2588	2657	2660	java/lang/Throwable
    //   2626	2695	2698	java/lang/Throwable
    //   2664	2729	2732	java/lang/Throwable
    //   7139	7153	7153	java/lang/Throwable
    //   7164	7177	7180	java/lang/Throwable
    //   7169	7192	7195	java/lang/Throwable
    //   7184	7210	7213	java/lang/Throwable
    //   7199	7240	7243	java/lang/Throwable
    //   7306	7333	7336	java/lang/Throwable
    //   7323	7354	7357	java/lang/Throwable
    //   7340	7384	7387	java/lang/Throwable
    //   7361	7395	7395	java/lang/Throwable
    //   7406	7422	7425	java/lang/Throwable
    //   7429	7519	7522	java/lang/Throwable
    //   7474	7571	7574	java/lang/Throwable
    //   7526	7582	7582	java/lang/Throwable
  }
  
  static void Zl(Object paramObject) {
    Zkup.Zr = a(-5594, 30528);
    Zkup.Zf = new BigInteger(a(-5599, -5492));
    boolean bool = Zt2e.ZK();
    try {
      try {
        if (Zgb9.Zk.charAt(Math.abs(((BigInteger)Zgmo.Zo).intValue() % 32)) > Zgb9.Zk.charAt(Math.abs(((BigInteger)Zb8x.Zz).intValue() % 32))) {
          try {
            Ztdt.Zo(Class.forName(a(-5596, -6656)));
            if (bool)
              Ztvn.ZL(Class.forName(a(-5600, 5537))); 
          } catch (Throwable throwable) {
            throw a(null);
          } 
          return;
        } 
      } catch (Throwable throwable) {
        throw a(null);
      } 
      Ztvn.ZL(Class.forName(a(-5600, 5537)));
    } catch (Throwable throwable) {}
  }
  
  static void ZT(Object[] paramArrayOfObject, Object paramObject) throws Throwable {}
  
  static {
    // Byte code:
    //   0: bipush #8
    //   2: anewarray java/lang/String
    //   5: astore #5
    //   7: iconst_0
    //   8: istore_3
    //   9: ldc 'a{\\ty[E61\\teE#*dp (Wd y>GHNI;\\rKLma>RvB~Vh!&c#>"4zd$!~,\\t\\r7aL?_'
    //   11: dup
    //   12: astore_2
    //   13: invokevirtual length : ()I
    //   16: istore #4
    //   18: iconst_4
    //   19: istore_1
    //   20: iconst_m1
    //   21: istore_0
    //   22: bipush #82
    //   24: iinc #0, 1
    //   27: aload_2
    //   28: iload_0
    //   29: dup
    //   30: iload_1
    //   31: iadd
    //   32: invokevirtual substring : (II)Ljava/lang/String;
    //   35: iconst_m1
    //   36: goto -> 142
    //   39: aload #5
    //   41: swap
    //   42: iload_3
    //   43: iinc #3, 1
    //   46: swap
    //   47: aastore
    //   48: iload_0
    //   49: iload_1
    //   50: iadd
    //   51: dup
    //   52: istore_0
    //   53: iload #4
    //   55: if_icmpge -> 67
    //   58: aload_2
    //   59: iload_0
    //   60: invokevirtual charAt : (I)C
    //   63: istore_1
    //   64: goto -> 22
    //   67: ldc 'nG.k\\f.S+x7\\tE'
    //   69: dup
    //   70: astore_2
    //   71: invokevirtual length : ()I
    //   74: istore #4
    //   76: bipush #32
    //   78: istore_1
    //   79: iconst_m1
    //   80: istore_0
    //   81: bipush #67
    //   83: iinc #0, 1
    //   86: aload_2
    //   87: iload_0
    //   88: dup
    //   89: iload_1
    //   90: iadd
    //   91: invokevirtual substring : (II)Ljava/lang/String;
    //   94: iconst_0
    //   95: goto -> 142
    //   98: aload #5
    //   100: swap
    //   101: iload_3
    //   102: iinc #3, 1
    //   105: swap
    //   106: aastore
    //   107: iload_0
    //   108: iload_1
    //   109: iadd
    //   110: dup
    //   111: istore_0
    //   112: iload #4
    //   114: if_icmpge -> 126
    //   117: aload_2
    //   118: iload_0
    //   119: invokevirtual charAt : (I)C
    //   122: istore_1
    //   123: goto -> 81
    //   126: aload #5
    //   128: putstatic burp/Zgqp.a : [Ljava/lang/String;
    //   131: bipush #8
    //   133: anewarray java/lang/String
    //   136: putstatic burp/Zgqp.b : [Ljava/lang/String;
    //   139: goto -> 300
    //   142: dup_x2
    //   143: pop
    //   144: invokevirtual toCharArray : ()[C
    //   147: dup_x1
    //   148: arraylength
    //   149: dup_x2
    //   150: pop
    //   151: iconst_0
    //   152: istore #6
    //   154: dup2_x1
    //   155: pop2
    //   156: dup_x2
    //   157: iconst_1
    //   158: if_icmpgt -> 260
    //   161: dup2
    //   162: swap
    //   163: iload #6
    //   165: dup2_x1
    //   166: caload
    //   167: swap
    //   168: iload #6
    //   170: bipush #7
    //   172: irem
    //   173: tableswitch default -> 242, 0 -> 212, 1 -> 217, 2 -> 222, 3 -> 227, 4 -> 232, 5 -> 237
    //   212: bipush #10
    //   214: goto -> 244
    //   217: bipush #73
    //   219: goto -> 244
    //   222: bipush #63
    //   224: goto -> 244
    //   227: bipush #21
    //   229: goto -> 244
    //   232: bipush #78
    //   234: goto -> 244
    //   237: bipush #25
    //   239: goto -> 244
    //   242: bipush #11
    //   244: ixor
    //   245: ixor
    //   246: i2c
    //   247: castore
    //   248: iinc #6, 1
    //   251: dup
    //   252: ifne -> 260
    //   255: dup2
    //   256: dup_x1
    //   257: goto -> 165
    //   260: dup2_x1
    //   261: pop2
    //   262: dup_x2
    //   263: iload #6
    //   265: if_icmpgt -> 161
    //   268: pop
    //   269: new java/lang/String
    //   272: dup_x1
    //   273: swap
    //   274: invokespecial <init> : ([C)V
    //   277: invokevirtual intern : ()Ljava/lang/String;
    //   280: swap
    //   281: pop
    //   282: swap
    //   283: tableswitch default -> 39, 0 -> 98
    //   300: new java/math/BigInteger
    //   303: dup
    //   304: bipush #32
    //   306: newarray byte
    //   308: dup
    //   309: iconst_0
    //   310: bipush #21
    //   312: bastore
    //   313: dup
    //   314: iconst_1
    //   315: bipush #-13
    //   317: bastore
    //   318: dup
    //   319: iconst_2
    //   320: bipush #86
    //   322: bastore
    //   323: dup
    //   324: iconst_3
    //   325: bipush #-96
    //   327: bastore
    //   328: dup
    //   329: iconst_4
    //   330: bipush #100
    //   332: bastore
    //   333: dup
    //   334: iconst_5
    //   335: bipush #-52
    //   337: bastore
    //   338: dup
    //   339: bipush #6
    //   341: bipush #-51
    //   343: bastore
    //   344: dup
    //   345: bipush #7
    //   347: bipush #-121
    //   349: bastore
    //   350: dup
    //   351: bipush #8
    //   353: bipush #-24
    //   355: bastore
    //   356: dup
    //   357: bipush #9
    //   359: bipush #-119
    //   361: bastore
    //   362: dup
    //   363: bipush #10
    //   365: bipush #6
    //   367: bastore
    //   368: dup
    //   369: bipush #11
    //   371: bipush #111
    //   373: bastore
    //   374: dup
    //   375: bipush #12
    //   377: bipush #-43
    //   379: bastore
    //   380: dup
    //   381: bipush #13
    //   383: bipush #-75
    //   385: bastore
    //   386: dup
    //   387: bipush #14
    //   389: bipush #-71
    //   391: bastore
    //   392: dup
    //   393: bipush #15
    //   395: bipush #-61
    //   397: bastore
    //   398: dup
    //   399: bipush #16
    //   401: bipush #20
    //   403: bastore
    //   404: dup
    //   405: bipush #17
    //   407: bipush #99
    //   409: bastore
    //   410: dup
    //   411: bipush #18
    //   413: bipush #89
    //   415: bastore
    //   416: dup
    //   417: bipush #19
    //   419: bipush #19
    //   421: bastore
    //   422: dup
    //   423: bipush #20
    //   425: bipush #125
    //   427: bastore
    //   428: dup
    //   429: bipush #21
    //   431: bipush #24
    //   433: bastore
    //   434: dup
    //   435: bipush #22
    //   437: bipush #-103
    //   439: bastore
    //   440: dup
    //   441: bipush #23
    //   443: bipush #-25
    //   445: bastore
    //   446: dup
    //   447: bipush #24
    //   449: bipush #-21
    //   451: bastore
    //   452: dup
    //   453: bipush #25
    //   455: bipush #32
    //   457: bastore
    //   458: dup
    //   459: bipush #26
    //   461: bipush #36
    //   463: bastore
    //   464: dup
    //   465: bipush #27
    //   467: bipush #71
    //   469: bastore
    //   470: dup
    //   471: bipush #28
    //   473: bipush #71
    //   475: bastore
    //   476: dup
    //   477: bipush #29
    //   479: bipush #-118
    //   481: bastore
    //   482: dup
    //   483: bipush #30
    //   485: bipush #127
    //   487: bastore
    //   488: dup
    //   489: bipush #31
    //   491: bipush #95
    //   493: bastore
    //   494: invokespecial <init> : ([B)V
    //   497: putstatic burp/Zgqp.Zf : Ljava/lang/Object;
    //   500: sipush #-5597
    //   503: sipush #-2882
    //   506: invokestatic a : (II)Ljava/lang/String;
    //   509: putstatic burp/Zgqp.ZA : Ljava/lang/String;
    //   512: return
  }
  
  private static Throwable a(Throwable paramThrowable) {
    return paramThrowable;
  }
  
  private static String a(int paramInt1, int paramInt2) {
    int i = (paramInt1 ^ 0xFFFFEA25) & 0xFFFF;
    if (b[i] == null) {
      char[] arrayOfChar = a[i].toCharArray();
      switch (arrayOfChar[0] & 0xFF) {
        case 0:
        
        case 1:
        
        case 2:
        
        case 3:
        
        case 4:
        
        case 5:
        
        case 6:
        
        case 7:
        
        case 8:
        
        case 9:
        
        case 10:
        
        case 11:
        
        case 12:
        
        case 13:
        
        case 14:
        
        case 15:
        
        case 16:
        
        case 17:
        
        case 18:
        
        case 19:
        
        case 20:
        
        case 21:
        
        case 22:
        
        case 23:
        
        case 24:
        
        case 25:
        
        case 26:
        
        case 27:
        
        case 28:
        
        case 29:
        
        case 30:
        
        case 31:
        
        case 32:
        
        case 33:
        
        case 34:
        
        case 35:
        
        case 36:
        
        case 37:
        
        case 38:
        
        case 39:
        
        case 40:
        
        case 41:
        
        case 42:
        
        case 43:
        
        case 44:
        
        case 45:
        
        case 46:
        
        case 47:
        
        case 48:
        
        case 49:
        
        case 50:
        
        case 51:
        
        case 52:
        
        case 53:
        
        case 54:
        
        case 55:
        
        case 56:
        
        case 57:
        
        case 58:
        
        case 59:
        
        case 60:
        
        case 61:
        
        case 62:
        
        case 63:
        
        case 64:
        
        case 65:
        
        case 66:
        
        case 67:
        
        case 68:
        
        case 69:
        
        case 70:
        
        case 71:
        
        case 72:
        
        case 73:
        
        case 74:
        
        case 75:
        
        case 76:
        
        case 77:
        
        case 78:
        
        case 79:
        
        case 80:
        
        case 81:
        
        case 82:
        
        case 83:
        
        case 84:
        
        case 85:
        
        case 86:
        
        case 87:
        
        case 88:
        
        case 89:
        
        case 90:
        
        case 91:
        
        case 92:
        
        case 93:
        
        case 94:
        
        case 95:
        
        case 96:
        
        case 97:
        
        case 98:
        
        case 99:
        
        case 100:
        
        case 101:
        
        case 102:
        
        case 103:
        
        case 104:
        
        case 105:
        
        case 106:
        
        case 107:
        
        case 108:
        
        case 109:
        
        case 110:
        
        case 111:
        
        case 112:
        
        case 113:
        
        case 114:
        
        case 115:
        
        case 116:
        
        case 117:
        
        case 118:
        
        case 119:
        
        case 120:
        
        case 121:
        
        case 122:
        
        case 123:
        
        case 124:
        
        case 125:
        
        case 126:
        
        case 127:
        
        case 128:
        
        case 129:
        
        case 130:
        
        case 131:
        
        case 132:
        
        case 133:
        
        case 134:
        
        case 135:
        
        case 136:
        
        case 137:
        
        case 138:
        
        case 139:
        
        case 140:
        
        case 141:
        
        case 142:
        
        case 143:
        
        case 144:
        
        case 145:
        
        case 146:
        
        case 147:
        
        case 148:
        
        case 149:
        
        case 150:
        
        case 151:
        
        case 152:
        
        case 153:
        
        case 154:
        
        case 155:
        
        case 156:
        
        case 157:
        
        case 158:
        
        case 159:
        
        case 160:
        
        case 161:
        
        case 162:
        
        case 163:
        
        case 164:
        
        case 165:
        
        case 166:
        
        case 167:
        
        case 168:
        
        case 169:
        
        case 170:
        
        case 171:
        
        case 172:
        
        case 173:
        
        case 174:
        
        case 175:
        
        case 176:
        
        case 177:
        
        case 178:
        
        case 179:
        
        case 180:
        
        case 181:
        
        case 182:
        
        case 183:
        
        case 184:
        
        case 185:
        
        case 186:
        
        case 187:
        
        case 188:
        
        case 189:
        
        case 190:
        
        case 191:
        
        case 192:
        
        case 193:
        
        case 194:
        
        case 195:
        
        case 196:
        
        case 197:
        
        case 198:
        
        case 199:
        
        case 200:
        
        case 201:
        
        case 202:
        
        case 203:
        
        case 204:
        
        case 205:
        
        case 206:
        
        case 207:
        
        case 208:
        
        case 209:
        
        case 210:
        
        case 211:
        
        case 212:
        
        case 213:
        
        case 214:
        
        case 215:
        
        case 216:
        
        case 217:
        
        case 218:
        
        case 219:
        
        case 220:
        
        case 221:
        
        case 222:
        
        case 223:
        
        case 224:
        
        case 225:
        
        case 226:
        
        case 227:
        
        case 228:
        
        case 229:
        
        case 230:
        
        case 231:
        
        case 232:
        
        case 233:
        
        case 234:
        
        case 235:
        
        case 236:
        
        case 237:
        
        case 238:
        
        case 239:
        
        case 240:
        
        case 241:
        
        case 242:
        
        case 243:
        
        case 244:
        
        case 245:
        
        case 246:
        
        case 247:
        
        case 248:
        
        case 249:
        
        case 250:
        
        case 251:
        
        case 252:
        
        case 253:
        
        case 254:
        
        default:
          break;
      } 
      char c = '';
      int j = (paramInt2 & 0xFF) - c;
      if (j < 0)
        j += 256; 
      int k = ((paramInt2 & 0xFFFF) >>> 8) - c;
      if (k < 0)
        k += 256; 
      for (byte b = 0; b < arrayOfChar.length; b++) {
        int m = b % 2;
        if (m == 0) {
          arrayOfChar[b] = (char)(arrayOfChar[b] ^ j);
          j = ((j >>> 3 | j << 5) ^ arrayOfChar[b]) & 0xFF;
        } else {
          arrayOfChar[b] = (char)(arrayOfChar[b] ^ k);
          k = ((k >>> 3 | k << 5) ^ arrayOfChar[b]) & 0xFF;
        } 
      } 
      b[i] = (new String(arrayOfChar)).intern();
    } 
    return b[i];
  }
}


/* Location:              C:\Program Files\BurpSuitePro\burpsuite_pro.jar!\burp\Zgqp.class
 * Java compiler version: 21 (65.0)
 * JD-Core Version:       1.1.3
 */