package burp;

public class Zgqx extends Zg2b<Ze65> {
  static Zmk7<Ze65> Zm;
  
  static Zmk7<Ze65> Z_;
  
  static Zmk7<Ze65> Zf;
  
  static Zmk7<Ze65> ZB;
  
  static Zmk7<Ze65> ZJ;
  
  static Zmk7<Ze65> Zl;
  
  static Zmk7<Ze65> ZF;
  
  static Zmk7<Ze65> Zn;
  
  static Zmk7<Ze65> Zq;
  
  public Zgqx() {
    super(new Zgjg<>((Zmk7<Ze65>[])new Zmk7[] { Zm, Z_, Zf, ZB, ZJ, Zl, ZF, Zn, Zq }));
  }
  
  static {
    // Byte code:
    //   0: bipush #9
    //   2: anewarray java/lang/String
    //   5: astore_0
    //   6: iconst_0
    //   7: istore #4
    //   9: ldc 'd*>uK3"A66c$#x, d|&=w)\\t}\\nUK5>@&`"!q2c72d2gS,7u}&'x%'
    //   11: dup
    //   12: astore_3
    //   13: invokevirtual length : ()I
    //   16: istore #5
    //   18: bipush #14
    //   20: istore_2
    //   21: iconst_m1
    //   22: istore_1
    //   23: bipush #73
    //   25: iinc #1, 1
    //   28: aload_3
    //   29: iload_1
    //   30: dup
    //   31: iload_2
    //   32: iadd
    //   33: invokevirtual substring : (II)Ljava/lang/String;
    //   36: iconst_m1
    //   37: goto -> 129
    //   40: aload_0
    //   41: swap
    //   42: iload #4
    //   44: iinc #4, 1
    //   47: swap
    //   48: aastore
    //   49: iload_1
    //   50: iload_2
    //   51: iadd
    //   52: dup
    //   53: istore_1
    //   54: iload #5
    //   56: if_icmpge -> 68
    //   59: aload_3
    //   60: iload_1
    //   61: invokevirtual charAt : (I)C
    //   64: istore_2
    //   65: goto -> 23
    //   68: ldc '3GI2|q*X'
    //   70: dup
    //   71: astore_3
    //   72: invokevirtual length : ()I
    //   75: istore #5
    //   77: iconst_3
    //   78: istore_2
    //   79: iconst_m1
    //   80: istore_1
    //   81: bipush #31
    //   83: iinc #1, 1
    //   86: aload_3
    //   87: iload_1
    //   88: dup
    //   89: iload_2
    //   90: iadd
    //   91: invokevirtual substring : (II)Ljava/lang/String;
    //   94: iconst_0
    //   95: goto -> 129
    //   98: aload_0
    //   99: swap
    //   100: iload #4
    //   102: iinc #4, 1
    //   105: swap
    //   106: aastore
    //   107: iload_1
    //   108: iload_2
    //   109: iadd
    //   110: dup
    //   111: istore_1
    //   112: iload #5
    //   114: if_icmpge -> 126
    //   117: aload_3
    //   118: iload_1
    //   119: invokevirtual charAt : (I)C
    //   122: istore_2
    //   123: goto -> 81
    //   126: goto -> 288
    //   129: dup_x2
    //   130: pop
    //   131: invokevirtual toCharArray : ()[C
    //   134: dup_x1
    //   135: arraylength
    //   136: dup_x2
    //   137: pop
    //   138: iconst_0
    //   139: istore #6
    //   141: dup2_x1
    //   142: pop2
    //   143: dup_x2
    //   144: iconst_1
    //   145: if_icmpgt -> 248
    //   148: dup2
    //   149: swap
    //   150: iload #6
    //   152: dup2_x1
    //   153: caload
    //   154: swap
    //   155: iload #6
    //   157: bipush #7
    //   159: irem
    //   160: tableswitch default -> 230, 0 -> 200, 1 -> 205, 2 -> 210, 3 -> 215, 4 -> 220, 5 -> 225
    //   200: bipush #121
    //   202: goto -> 232
    //   205: bipush #10
    //   207: goto -> 232
    //   210: bipush #26
    //   212: goto -> 232
    //   215: bipush #89
    //   217: goto -> 232
    //   220: bipush #34
    //   222: goto -> 232
    //   225: bipush #8
    //   227: goto -> 232
    //   230: bipush #14
    //   232: ixor
    //   233: ixor
    //   234: i2c
    //   235: castore
    //   236: iinc #6, 1
    //   239: dup
    //   240: ifne -> 248
    //   243: dup2
    //   244: dup_x1
    //   245: goto -> 152
    //   248: dup2_x1
    //   249: pop2
    //   250: dup_x2
    //   251: iload #6
    //   253: if_icmpgt -> 148
    //   256: pop
    //   257: new java/lang/String
    //   260: dup_x1
    //   261: swap
    //   262: invokespecial <init> : ([C)V
    //   265: invokevirtual intern : ()Ljava/lang/String;
    //   268: swap
    //   269: pop
    //   270: swap
    //   271: tableswitch default -> 40, 0 -> 98
    //   288: <illegal opcode> Zl : ()Lburp/Zkuq;
    //   293: invokestatic Zh : (Lburp/Zkuq;)Lburp/Zz_2;
    //   296: aload_0
    //   297: iconst_1
    //   298: aaload
    //   299: invokevirtual ZL : (Ljava/lang/String;)Lburp/Zz_2;
    //   302: ldc java/lang/String
    //   304: invokevirtual Zg : (Ljava/lang/Class;)Lburp/Zz_2;
    //   307: bipush #20
    //   309: invokevirtual ZZ : (I)Lburp/Zz_2;
    //   312: invokevirtual ZH : ()Lburp/Zmk7;
    //   315: putstatic burp/Zgqx.Zm : Lburp/Zmk7;
    //   318: <illegal opcode> Zl : ()Lburp/Zkuq;
    //   323: invokestatic Zh : (Lburp/Zkuq;)Lburp/Zz_2;
    //   326: aload_0
    //   327: bipush #6
    //   329: aaload
    //   330: invokevirtual ZL : (Ljava/lang/String;)Lburp/Zz_2;
    //   333: ldc java/lang/String
    //   335: invokevirtual Zg : (Ljava/lang/Class;)Lburp/Zz_2;
    //   338: bipush #8
    //   340: invokevirtual ZZ : (I)Lburp/Zz_2;
    //   343: invokevirtual ZH : ()Lburp/Zmk7;
    //   346: putstatic burp/Zgqx.Z_ : Lburp/Zmk7;
    //   349: <illegal opcode> Zl : ()Lburp/Zkuq;
    //   354: invokestatic Zh : (Lburp/Zkuq;)Lburp/Zz_2;
    //   357: aload_0
    //   358: bipush #7
    //   360: aaload
    //   361: invokevirtual ZL : (Ljava/lang/String;)Lburp/Zz_2;
    //   364: ldc java/lang/String
    //   366: invokevirtual Zg : (Ljava/lang/Class;)Lburp/Zz_2;
    //   369: bipush #25
    //   371: invokevirtual ZZ : (I)Lburp/Zz_2;
    //   374: getstatic javax/swing/SortOrder.ASCENDING : Ljavax/swing/SortOrder;
    //   377: invokevirtual ZV : (Ljavax/swing/SortOrder;)Lburp/Zz_2;
    //   380: getstatic burp/Zlcu.SECONDARY : Lburp/Zlcu;
    //   383: invokevirtual ZA : (Lburp/Zlcu;)Lburp/Zz_2;
    //   386: invokevirtual ZH : ()Lburp/Zmk7;
    //   389: putstatic burp/Zgqx.Zf : Lburp/Zmk7;
    //   392: <illegal opcode> Zl : ()Lburp/Zkuq;
    //   397: invokestatic Zh : (Lburp/Zkuq;)Lburp/Zz_2;
    //   400: aload_0
    //   401: iconst_4
    //   402: aaload
    //   403: invokevirtual ZL : (Ljava/lang/String;)Lburp/Zz_2;
    //   406: ldc java/lang/Boolean
    //   408: invokevirtual Zg : (Ljava/lang/Class;)Lburp/Zz_2;
    //   411: bipush #8
    //   413: invokevirtual ZZ : (I)Lburp/Zz_2;
    //   416: new burp/Zbgu
    //   419: dup
    //   420: invokespecial <init> : ()V
    //   423: invokevirtual ZM : (Ljavax/swing/table/TableCellRenderer;)Lburp/Zz_2;
    //   426: invokevirtual ZH : ()Lburp/Zmk7;
    //   429: putstatic burp/Zgqx.ZB : Lburp/Zmk7;
    //   432: <illegal opcode> Zl : ()Lburp/Zkuq;
    //   437: invokestatic Zh : (Lburp/Zkuq;)Lburp/Zz_2;
    //   440: aload_0
    //   441: iconst_5
    //   442: aaload
    //   443: invokevirtual ZL : (Ljava/lang/String;)Lburp/Zz_2;
    //   446: ldc java/lang/Integer
    //   448: invokevirtual Zg : (Ljava/lang/Class;)Lburp/Zz_2;
    //   451: bipush #13
    //   453: invokevirtual ZZ : (I)Lburp/Zz_2;
    //   456: new burp/Zmqp
    //   459: dup
    //   460: invokespecial <init> : ()V
    //   463: invokevirtual ZM : (Ljavax/swing/table/TableCellRenderer;)Lburp/Zz_2;
    //   466: new burp/Zs46
    //   469: dup
    //   470: invokespecial <init> : ()V
    //   473: invokevirtual Zh : (Ljava/util/Comparator;)Lburp/Zz_2;
    //   476: getstatic javax/swing/SortOrder.ASCENDING : Ljavax/swing/SortOrder;
    //   479: invokevirtual ZV : (Ljavax/swing/SortOrder;)Lburp/Zz_2;
    //   482: getstatic burp/Zlcu.PRIMARY : Lburp/Zlcu;
    //   485: invokevirtual ZA : (Lburp/Zlcu;)Lburp/Zz_2;
    //   488: invokevirtual ZH : ()Lburp/Zmk7;
    //   491: putstatic burp/Zgqx.ZJ : Lburp/Zmk7;
    //   494: <illegal opcode> Zl : ()Lburp/Zkuq;
    //   499: invokestatic Zh : (Lburp/Zkuq;)Lburp/Zz_2;
    //   502: aload_0
    //   503: iconst_2
    //   504: aaload
    //   505: invokevirtual ZL : (Ljava/lang/String;)Lburp/Zz_2;
    //   508: ldc java/lang/Integer
    //   510: invokevirtual Zg : (Ljava/lang/Class;)Lburp/Zz_2;
    //   513: bipush #10
    //   515: invokevirtual ZZ : (I)Lburp/Zz_2;
    //   518: invokevirtual ZH : ()Lburp/Zmk7;
    //   521: putstatic burp/Zgqx.Zl : Lburp/Zmk7;
    //   524: <illegal opcode> Zl : ()Lburp/Zkuq;
    //   529: invokestatic Zh : (Lburp/Zkuq;)Lburp/Zz_2;
    //   532: aload_0
    //   533: iconst_3
    //   534: aaload
    //   535: invokevirtual ZL : (Ljava/lang/String;)Lburp/Zz_2;
    //   538: ldc java/lang/String
    //   540: invokevirtual Zg : (Ljava/lang/Class;)Lburp/Zz_2;
    //   543: bipush #12
    //   545: invokevirtual ZZ : (I)Lburp/Zz_2;
    //   548: invokevirtual ZH : ()Lburp/Zmk7;
    //   551: putstatic burp/Zgqx.ZF : Lburp/Zmk7;
    //   554: <illegal opcode> Zl : ()Lburp/Zkuq;
    //   559: invokestatic Zh : (Lburp/Zkuq;)Lburp/Zz_2;
    //   562: aload_0
    //   563: bipush #8
    //   565: aaload
    //   566: invokevirtual ZL : (Ljava/lang/String;)Lburp/Zz_2;
    //   569: ldc java/lang/String
    //   571: invokevirtual Zg : (Ljava/lang/Class;)Lburp/Zz_2;
    //   574: bipush #22
    //   576: invokevirtual ZZ : (I)Lburp/Zz_2;
    //   579: invokevirtual ZH : ()Lburp/Zmk7;
    //   582: putstatic burp/Zgqx.Zn : Lburp/Zmk7;
    //   585: <illegal opcode> Zl : ()Lburp/Zkuq;
    //   590: invokestatic Zh : (Lburp/Zkuq;)Lburp/Zz_2;
    //   593: aload_0
    //   594: iconst_0
    //   595: aaload
    //   596: invokevirtual ZL : (Ljava/lang/String;)Lburp/Zz_2;
    //   599: ldc java/lang/Long
    //   601: invokevirtual Zg : (Ljava/lang/Class;)Lburp/Zz_2;
    //   604: bipush #20
    //   606: invokevirtual ZZ : (I)Lburp/Zz_2;
    //   609: new burp/Zmqw
    //   612: dup
    //   613: invokespecial <init> : ()V
    //   616: invokevirtual ZM : (Ljavax/swing/table/TableCellRenderer;)Lburp/Zz_2;
    //   619: invokevirtual ZH : ()Lburp/Zmk7;
    //   622: putstatic burp/Zgqx.Zq : Lburp/Zmk7;
    //   625: return
  }
}


/* Location:              C:\Program Files\BurpSuitePro\burpsuite_pro.jar!\burp\Zgqx.class
 * Java compiler version: 21 (65.0)
 * JD-Core Version:       1.1.3
 */