package burp;

import java.math.BigInteger;

class Zgsb extends ClassLoader {
  static String ZM;
  
  static Object Zl;
  
  private static final String[] a;
  
  private static final String[] b;
  
  static boolean Zo(Object[] paramArrayOfObject, Object paramObject) throws Throwable {
    // Byte code:
    //   0: invokestatic ZN : ()Z
    //   3: istore_2
    //   4: getstatic burp/Zg6z.ZS : Ljava/lang/Object;
    //   7: checkcast java/math/BigInteger
    //   10: getstatic burp/Zrov.Zk : Ljava/lang/Object;
    //   13: checkcast java/math/BigInteger
    //   16: invokevirtual add : (Ljava/math/BigInteger;)Ljava/math/BigInteger;
    //   19: putstatic burp/Zzpm.Ze : Ljava/lang/Object;
    //   22: getstatic burp/Zexl.ZG : Ljava/lang/Object;
    //   25: checkcast java/math/BigInteger
    //   28: invokevirtual toByteArray : ()[B
    //   31: astore_3
    //   32: bipush #32
    //   34: newarray int
    //   36: dup
    //   37: iconst_0
    //   38: ldc 876216579
    //   40: iastore
    //   41: dup
    //   42: iconst_1
    //   43: ldc 455999525
    //   45: iastore
    //   46: dup
    //   47: iconst_2
    //   48: ldc 1043334948
    //   50: iastore
    //   51: dup
    //   52: iconst_3
    //   53: ldc 439222784
    //   55: iastore
    //   56: dup
    //   57: iconst_4
    //   58: ldc 372376604
    //   60: iastore
    //   61: dup
    //   62: iconst_5
    //   63: ldc 707731490
    //   65: iastore
    //   66: dup
    //   67: bipush #6
    //   69: ldc 389426184
    //   71: iastore
    //   72: dup
    //   73: bipush #7
    //   75: ldc 973875457
    //   77: iastore
    //   78: dup
    //   79: bipush #8
    //   81: ldc 389160971
    //   83: iastore
    //   84: dup
    //   85: bipush #9
    //   87: ldc 907870729
    //   89: iastore
    //   90: dup
    //   91: bipush #10
    //   93: ldc 121057538
    //   95: iastore
    //   96: dup
    //   97: bipush #11
    //   99: ldc 840500228
    //   101: iastore
    //   102: dup
    //   103: bipush #12
    //   105: ldc 254150144
    //   107: iastore
    //   108: dup
    //   109: bipush #13
    //   111: ldc 924386310
    //   113: iastore
    //   114: dup
    //   115: bipush #14
    //   117: ldc 187632156
    //   119: iastore
    //   120: dup
    //   121: bipush #15
    //   123: ldc 874189824
    //   125: iastore
    //   126: dup
    //   127: bipush #16
    //   129: ldc 655302664
    //   131: iastore
    //   132: dup
    //   133: bipush #17
    //   135: ldc 890966315
    //   137: iastore
    //   138: dup
    //   139: bipush #18
    //   141: ldc 722417666
    //   143: iastore
    //   144: dup
    //   145: bipush #19
    //   147: ldc 1026621720
    //   149: iastore
    //   150: dup
    //   151: bipush #20
    //   153: ldc 957157408
    //   155: iastore
    //   156: dup
    //   157: bipush #21
    //   159: ldc 892536332
    //   161: iastore
    //   162: dup
    //   163: bipush #22
    //   165: ldc 689771012
    //   167: iastore
    //   168: dup
    //   169: bipush #23
    //   171: ldc 221709344
    //   173: iastore
    //   174: dup
    //   175: bipush #24
    //   177: ldc 940377620
    //   179: iastore
    //   180: dup
    //   181: bipush #25
    //   183: ldc 255209728
    //   185: iastore
    //   186: dup
    //   187: bipush #26
    //   189: ldc 1010368540
    //   191: iastore
    //   192: dup
    //   193: bipush #27
    //   195: ldc 220604441
    //   197: iastore
    //   198: dup
    //   199: bipush #28
    //   201: ldc 1008414755
    //   203: iastore
    //   204: dup
    //   205: bipush #29
    //   207: ldc 187049985
    //   209: iastore
    //   210: dup
    //   211: bipush #30
    //   213: ldc 943331329
    //   215: iastore
    //   216: dup
    //   217: bipush #31
    //   219: ldc 170788368
    //   221: iastore
    //   222: astore #5
    //   224: bipush #64
    //   226: newarray int
    //   228: dup
    //   229: iconst_0
    //   230: ldc 16843776
    //   232: iastore
    //   233: dup
    //   234: iconst_1
    //   235: iconst_0
    //   236: iastore
    //   237: dup
    //   238: iconst_2
    //   239: ldc 65536
    //   241: iastore
    //   242: dup
    //   243: iconst_3
    //   244: ldc 16843780
    //   246: iastore
    //   247: dup
    //   248: iconst_4
    //   249: ldc 16842756
    //   251: iastore
    //   252: dup
    //   253: iconst_5
    //   254: ldc 66564
    //   256: iastore
    //   257: dup
    //   258: bipush #6
    //   260: iconst_4
    //   261: iastore
    //   262: dup
    //   263: bipush #7
    //   265: ldc 65536
    //   267: iastore
    //   268: dup
    //   269: bipush #8
    //   271: sipush #1024
    //   274: iastore
    //   275: dup
    //   276: bipush #9
    //   278: ldc 16843776
    //   280: iastore
    //   281: dup
    //   282: bipush #10
    //   284: ldc 16843780
    //   286: iastore
    //   287: dup
    //   288: bipush #11
    //   290: sipush #1024
    //   293: iastore
    //   294: dup
    //   295: bipush #12
    //   297: ldc 16778244
    //   299: iastore
    //   300: dup
    //   301: bipush #13
    //   303: ldc 16842756
    //   305: iastore
    //   306: dup
    //   307: bipush #14
    //   309: ldc 16777216
    //   311: iastore
    //   312: dup
    //   313: bipush #15
    //   315: iconst_4
    //   316: iastore
    //   317: dup
    //   318: bipush #16
    //   320: sipush #1028
    //   323: iastore
    //   324: dup
    //   325: bipush #17
    //   327: ldc 16778240
    //   329: iastore
    //   330: dup
    //   331: bipush #18
    //   333: ldc 16778240
    //   335: iastore
    //   336: dup
    //   337: bipush #19
    //   339: ldc 66560
    //   341: iastore
    //   342: dup
    //   343: bipush #20
    //   345: ldc 66560
    //   347: iastore
    //   348: dup
    //   349: bipush #21
    //   351: ldc 16842752
    //   353: iastore
    //   354: dup
    //   355: bipush #22
    //   357: ldc 16842752
    //   359: iastore
    //   360: dup
    //   361: bipush #23
    //   363: ldc 16778244
    //   365: iastore
    //   366: dup
    //   367: bipush #24
    //   369: ldc 65540
    //   371: iastore
    //   372: dup
    //   373: bipush #25
    //   375: ldc 16777220
    //   377: iastore
    //   378: dup
    //   379: bipush #26
    //   381: ldc 16777220
    //   383: iastore
    //   384: dup
    //   385: bipush #27
    //   387: ldc 65540
    //   389: iastore
    //   390: dup
    //   391: bipush #28
    //   393: iconst_0
    //   394: iastore
    //   395: dup
    //   396: bipush #29
    //   398: sipush #1028
    //   401: iastore
    //   402: dup
    //   403: bipush #30
    //   405: ldc 66564
    //   407: iastore
    //   408: dup
    //   409: bipush #31
    //   411: ldc 16777216
    //   413: iastore
    //   414: dup
    //   415: bipush #32
    //   417: ldc 65536
    //   419: iastore
    //   420: dup
    //   421: bipush #33
    //   423: ldc 16843780
    //   425: iastore
    //   426: dup
    //   427: bipush #34
    //   429: iconst_4
    //   430: iastore
    //   431: dup
    //   432: bipush #35
    //   434: ldc 16842752
    //   436: iastore
    //   437: dup
    //   438: bipush #36
    //   440: ldc 16843776
    //   442: iastore
    //   443: dup
    //   444: bipush #37
    //   446: ldc 16777216
    //   448: iastore
    //   449: dup
    //   450: bipush #38
    //   452: ldc 16777216
    //   454: iastore
    //   455: dup
    //   456: bipush #39
    //   458: sipush #1024
    //   461: iastore
    //   462: dup
    //   463: bipush #40
    //   465: ldc 16842756
    //   467: iastore
    //   468: dup
    //   469: bipush #41
    //   471: ldc 65536
    //   473: iastore
    //   474: dup
    //   475: bipush #42
    //   477: ldc 66560
    //   479: iastore
    //   480: dup
    //   481: bipush #43
    //   483: ldc 16777220
    //   485: iastore
    //   486: dup
    //   487: bipush #44
    //   489: sipush #1024
    //   492: iastore
    //   493: dup
    //   494: bipush #45
    //   496: iconst_4
    //   497: iastore
    //   498: dup
    //   499: bipush #46
    //   501: ldc 16778244
    //   503: iastore
    //   504: dup
    //   505: bipush #47
    //   507: ldc 66564
    //   509: iastore
    //   510: dup
    //   511: bipush #48
    //   513: ldc 16843780
    //   515: iastore
    //   516: dup
    //   517: bipush #49
    //   519: ldc 65540
    //   521: iastore
    //   522: dup
    //   523: bipush #50
    //   525: ldc 16842752
    //   527: iastore
    //   528: dup
    //   529: bipush #51
    //   531: ldc 16778244
    //   533: iastore
    //   534: dup
    //   535: bipush #52
    //   537: ldc 16777220
    //   539: iastore
    //   540: dup
    //   541: bipush #53
    //   543: sipush #1028
    //   546: iastore
    //   547: dup
    //   548: bipush #54
    //   550: ldc 66564
    //   552: iastore
    //   553: dup
    //   554: bipush #55
    //   556: ldc 16843776
    //   558: iastore
    //   559: dup
    //   560: bipush #56
    //   562: sipush #1028
    //   565: iastore
    //   566: dup
    //   567: bipush #57
    //   569: ldc 16778240
    //   571: iastore
    //   572: dup
    //   573: bipush #58
    //   575: ldc 16778240
    //   577: iastore
    //   578: dup
    //   579: bipush #59
    //   581: iconst_0
    //   582: iastore
    //   583: dup
    //   584: bipush #60
    //   586: ldc 65540
    //   588: iastore
    //   589: dup
    //   590: bipush #61
    //   592: ldc 66560
    //   594: iastore
    //   595: dup
    //   596: bipush #62
    //   598: iconst_0
    //   599: iastore
    //   600: dup
    //   601: bipush #63
    //   603: ldc 16842756
    //   605: iastore
    //   606: astore #6
    //   608: bipush #64
    //   610: newarray int
    //   612: dup
    //   613: iconst_0
    //   614: ldc -2146402272
    //   616: iastore
    //   617: dup
    //   618: iconst_1
    //   619: ldc -2147450880
    //   621: iastore
    //   622: dup
    //   623: iconst_2
    //   624: ldc 32768
    //   626: iastore
    //   627: dup
    //   628: iconst_3
    //   629: ldc 1081376
    //   631: iastore
    //   632: dup
    //   633: iconst_4
    //   634: ldc 1048576
    //   636: iastore
    //   637: dup
    //   638: iconst_5
    //   639: bipush #32
    //   641: iastore
    //   642: dup
    //   643: bipush #6
    //   645: ldc -2146435040
    //   647: iastore
    //   648: dup
    //   649: bipush #7
    //   651: ldc -2147450848
    //   653: iastore
    //   654: dup
    //   655: bipush #8
    //   657: ldc -2147483616
    //   659: iastore
    //   660: dup
    //   661: bipush #9
    //   663: ldc -2146402272
    //   665: iastore
    //   666: dup
    //   667: bipush #10
    //   669: ldc -2146402304
    //   671: iastore
    //   672: dup
    //   673: bipush #11
    //   675: ldc -2147483648
    //   677: iastore
    //   678: dup
    //   679: bipush #12
    //   681: ldc -2147450880
    //   683: iastore
    //   684: dup
    //   685: bipush #13
    //   687: ldc 1048576
    //   689: iastore
    //   690: dup
    //   691: bipush #14
    //   693: bipush #32
    //   695: iastore
    //   696: dup
    //   697: bipush #15
    //   699: ldc -2146435040
    //   701: iastore
    //   702: dup
    //   703: bipush #16
    //   705: ldc 1081344
    //   707: iastore
    //   708: dup
    //   709: bipush #17
    //   711: ldc 1048608
    //   713: iastore
    //   714: dup
    //   715: bipush #18
    //   717: ldc -2147450848
    //   719: iastore
    //   720: dup
    //   721: bipush #19
    //   723: iconst_0
    //   724: iastore
    //   725: dup
    //   726: bipush #20
    //   728: ldc -2147483648
    //   730: iastore
    //   731: dup
    //   732: bipush #21
    //   734: ldc 32768
    //   736: iastore
    //   737: dup
    //   738: bipush #22
    //   740: ldc 1081376
    //   742: iastore
    //   743: dup
    //   744: bipush #23
    //   746: ldc -2146435072
    //   748: iastore
    //   749: dup
    //   750: bipush #24
    //   752: ldc 1048608
    //   754: iastore
    //   755: dup
    //   756: bipush #25
    //   758: ldc -2147483616
    //   760: iastore
    //   761: dup
    //   762: bipush #26
    //   764: iconst_0
    //   765: iastore
    //   766: dup
    //   767: bipush #27
    //   769: ldc 1081344
    //   771: iastore
    //   772: dup
    //   773: bipush #28
    //   775: ldc 32800
    //   777: iastore
    //   778: dup
    //   779: bipush #29
    //   781: ldc -2146402304
    //   783: iastore
    //   784: dup
    //   785: bipush #30
    //   787: ldc -2146435072
    //   789: iastore
    //   790: dup
    //   791: bipush #31
    //   793: ldc 32800
    //   795: iastore
    //   796: dup
    //   797: bipush #32
    //   799: iconst_0
    //   800: iastore
    //   801: dup
    //   802: bipush #33
    //   804: ldc 1081376
    //   806: iastore
    //   807: dup
    //   808: bipush #34
    //   810: ldc -2146435040
    //   812: iastore
    //   813: dup
    //   814: bipush #35
    //   816: ldc 1048576
    //   818: iastore
    //   819: dup
    //   820: bipush #36
    //   822: ldc -2147450848
    //   824: iastore
    //   825: dup
    //   826: bipush #37
    //   828: ldc -2146435072
    //   830: iastore
    //   831: dup
    //   832: bipush #38
    //   834: ldc -2146402304
    //   836: iastore
    //   837: dup
    //   838: bipush #39
    //   840: ldc 32768
    //   842: iastore
    //   843: dup
    //   844: bipush #40
    //   846: ldc -2146435072
    //   848: iastore
    //   849: dup
    //   850: bipush #41
    //   852: ldc -2147450880
    //   854: iastore
    //   855: dup
    //   856: bipush #42
    //   858: bipush #32
    //   860: iastore
    //   861: dup
    //   862: bipush #43
    //   864: ldc -2146402272
    //   866: iastore
    //   867: dup
    //   868: bipush #44
    //   870: ldc 1081376
    //   872: iastore
    //   873: dup
    //   874: bipush #45
    //   876: bipush #32
    //   878: iastore
    //   879: dup
    //   880: bipush #46
    //   882: ldc 32768
    //   884: iastore
    //   885: dup
    //   886: bipush #47
    //   888: ldc -2147483648
    //   890: iastore
    //   891: dup
    //   892: bipush #48
    //   894: ldc 32800
    //   896: iastore
    //   897: dup
    //   898: bipush #49
    //   900: ldc -2146402304
    //   902: iastore
    //   903: dup
    //   904: bipush #50
    //   906: ldc 1048576
    //   908: iastore
    //   909: dup
    //   910: bipush #51
    //   912: ldc -2147483616
    //   914: iastore
    //   915: dup
    //   916: bipush #52
    //   918: ldc 1048608
    //   920: iastore
    //   921: dup
    //   922: bipush #53
    //   924: ldc -2147450848
    //   926: iastore
    //   927: dup
    //   928: bipush #54
    //   930: ldc -2147483616
    //   932: iastore
    //   933: dup
    //   934: bipush #55
    //   936: ldc 1048608
    //   938: iastore
    //   939: dup
    //   940: bipush #56
    //   942: ldc 1081344
    //   944: iastore
    //   945: dup
    //   946: bipush #57
    //   948: iconst_0
    //   949: iastore
    //   950: dup
    //   951: bipush #58
    //   953: ldc -2147450880
    //   955: iastore
    //   956: dup
    //   957: bipush #59
    //   959: ldc 32800
    //   961: iastore
    //   962: dup
    //   963: bipush #60
    //   965: ldc -2147483648
    //   967: iastore
    //   968: dup
    //   969: bipush #61
    //   971: ldc -2146435040
    //   973: iastore
    //   974: dup
    //   975: bipush #62
    //   977: ldc -2146402272
    //   979: iastore
    //   980: dup
    //   981: bipush #63
    //   983: ldc 1081344
    //   985: iastore
    //   986: astore #7
    //   988: bipush #64
    //   990: newarray int
    //   992: dup
    //   993: iconst_0
    //   994: sipush #520
    //   997: iastore
    //   998: dup
    //   999: iconst_1
    //   1000: ldc 134349312
    //   1002: iastore
    //   1003: dup
    //   1004: iconst_2
    //   1005: iconst_0
    //   1006: iastore
    //   1007: dup
    //   1008: iconst_3
    //   1009: ldc 134348808
    //   1011: iastore
    //   1012: dup
    //   1013: iconst_4
    //   1014: ldc 134218240
    //   1016: iastore
    //   1017: dup
    //   1018: iconst_5
    //   1019: iconst_0
    //   1020: iastore
    //   1021: dup
    //   1022: bipush #6
    //   1024: ldc 131592
    //   1026: iastore
    //   1027: dup
    //   1028: bipush #7
    //   1030: ldc 134218240
    //   1032: iastore
    //   1033: dup
    //   1034: bipush #8
    //   1036: ldc 131080
    //   1038: iastore
    //   1039: dup
    //   1040: bipush #9
    //   1042: ldc 134217736
    //   1044: iastore
    //   1045: dup
    //   1046: bipush #10
    //   1048: ldc 134217736
    //   1050: iastore
    //   1051: dup
    //   1052: bipush #11
    //   1054: ldc 131072
    //   1056: iastore
    //   1057: dup
    //   1058: bipush #12
    //   1060: ldc 134349320
    //   1062: iastore
    //   1063: dup
    //   1064: bipush #13
    //   1066: ldc 131080
    //   1068: iastore
    //   1069: dup
    //   1070: bipush #14
    //   1072: ldc 134348800
    //   1074: iastore
    //   1075: dup
    //   1076: bipush #15
    //   1078: sipush #520
    //   1081: iastore
    //   1082: dup
    //   1083: bipush #16
    //   1085: ldc 134217728
    //   1087: iastore
    //   1088: dup
    //   1089: bipush #17
    //   1091: bipush #8
    //   1093: iastore
    //   1094: dup
    //   1095: bipush #18
    //   1097: ldc 134349312
    //   1099: iastore
    //   1100: dup
    //   1101: bipush #19
    //   1103: sipush #512
    //   1106: iastore
    //   1107: dup
    //   1108: bipush #20
    //   1110: ldc 131584
    //   1112: iastore
    //   1113: dup
    //   1114: bipush #21
    //   1116: ldc 134348800
    //   1118: iastore
    //   1119: dup
    //   1120: bipush #22
    //   1122: ldc 134348808
    //   1124: iastore
    //   1125: dup
    //   1126: bipush #23
    //   1128: ldc 131592
    //   1130: iastore
    //   1131: dup
    //   1132: bipush #24
    //   1134: ldc 134218248
    //   1136: iastore
    //   1137: dup
    //   1138: bipush #25
    //   1140: ldc 131584
    //   1142: iastore
    //   1143: dup
    //   1144: bipush #26
    //   1146: ldc 131072
    //   1148: iastore
    //   1149: dup
    //   1150: bipush #27
    //   1152: ldc 134218248
    //   1154: iastore
    //   1155: dup
    //   1156: bipush #28
    //   1158: bipush #8
    //   1160: iastore
    //   1161: dup
    //   1162: bipush #29
    //   1164: ldc 134349320
    //   1166: iastore
    //   1167: dup
    //   1168: bipush #30
    //   1170: sipush #512
    //   1173: iastore
    //   1174: dup
    //   1175: bipush #31
    //   1177: ldc 134217728
    //   1179: iastore
    //   1180: dup
    //   1181: bipush #32
    //   1183: ldc 134349312
    //   1185: iastore
    //   1186: dup
    //   1187: bipush #33
    //   1189: ldc 134217728
    //   1191: iastore
    //   1192: dup
    //   1193: bipush #34
    //   1195: ldc 131080
    //   1197: iastore
    //   1198: dup
    //   1199: bipush #35
    //   1201: sipush #520
    //   1204: iastore
    //   1205: dup
    //   1206: bipush #36
    //   1208: ldc 131072
    //   1210: iastore
    //   1211: dup
    //   1212: bipush #37
    //   1214: ldc 134349312
    //   1216: iastore
    //   1217: dup
    //   1218: bipush #38
    //   1220: ldc 134218240
    //   1222: iastore
    //   1223: dup
    //   1224: bipush #39
    //   1226: iconst_0
    //   1227: iastore
    //   1228: dup
    //   1229: bipush #40
    //   1231: sipush #512
    //   1234: iastore
    //   1235: dup
    //   1236: bipush #41
    //   1238: ldc 131080
    //   1240: iastore
    //   1241: dup
    //   1242: bipush #42
    //   1244: ldc 134349320
    //   1246: iastore
    //   1247: dup
    //   1248: bipush #43
    //   1250: ldc 134218240
    //   1252: iastore
    //   1253: dup
    //   1254: bipush #44
    //   1256: ldc 134217736
    //   1258: iastore
    //   1259: dup
    //   1260: bipush #45
    //   1262: sipush #512
    //   1265: iastore
    //   1266: dup
    //   1267: bipush #46
    //   1269: iconst_0
    //   1270: iastore
    //   1271: dup
    //   1272: bipush #47
    //   1274: ldc 134348808
    //   1276: iastore
    //   1277: dup
    //   1278: bipush #48
    //   1280: ldc 134218248
    //   1282: iastore
    //   1283: dup
    //   1284: bipush #49
    //   1286: ldc 131072
    //   1288: iastore
    //   1289: dup
    //   1290: bipush #50
    //   1292: ldc 134217728
    //   1294: iastore
    //   1295: dup
    //   1296: bipush #51
    //   1298: ldc 134349320
    //   1300: iastore
    //   1301: dup
    //   1302: bipush #52
    //   1304: bipush #8
    //   1306: iastore
    //   1307: dup
    //   1308: bipush #53
    //   1310: ldc 131592
    //   1312: iastore
    //   1313: dup
    //   1314: bipush #54
    //   1316: ldc 131584
    //   1318: iastore
    //   1319: dup
    //   1320: bipush #55
    //   1322: ldc 134217736
    //   1324: iastore
    //   1325: dup
    //   1326: bipush #56
    //   1328: ldc 134348800
    //   1330: iastore
    //   1331: dup
    //   1332: bipush #57
    //   1334: ldc 134218248
    //   1336: iastore
    //   1337: dup
    //   1338: bipush #58
    //   1340: sipush #520
    //   1343: iastore
    //   1344: dup
    //   1345: bipush #59
    //   1347: ldc 134348800
    //   1349: iastore
    //   1350: dup
    //   1351: bipush #60
    //   1353: ldc 131592
    //   1355: iastore
    //   1356: dup
    //   1357: bipush #61
    //   1359: bipush #8
    //   1361: iastore
    //   1362: dup
    //   1363: bipush #62
    //   1365: ldc 134348808
    //   1367: iastore
    //   1368: dup
    //   1369: bipush #63
    //   1371: ldc 131584
    //   1373: iastore
    //   1374: astore #8
    //   1376: bipush #64
    //   1378: newarray int
    //   1380: dup
    //   1381: iconst_0
    //   1382: ldc 8396801
    //   1384: iastore
    //   1385: dup
    //   1386: iconst_1
    //   1387: sipush #8321
    //   1390: iastore
    //   1391: dup
    //   1392: iconst_2
    //   1393: sipush #8321
    //   1396: iastore
    //   1397: dup
    //   1398: iconst_3
    //   1399: sipush #128
    //   1402: iastore
    //   1403: dup
    //   1404: iconst_4
    //   1405: ldc 8396928
    //   1407: iastore
    //   1408: dup
    //   1409: iconst_5
    //   1410: ldc 8388737
    //   1412: iastore
    //   1413: dup
    //   1414: bipush #6
    //   1416: ldc 8388609
    //   1418: iastore
    //   1419: dup
    //   1420: bipush #7
    //   1422: sipush #8193
    //   1425: iastore
    //   1426: dup
    //   1427: bipush #8
    //   1429: iconst_0
    //   1430: iastore
    //   1431: dup
    //   1432: bipush #9
    //   1434: ldc 8396800
    //   1436: iastore
    //   1437: dup
    //   1438: bipush #10
    //   1440: ldc 8396800
    //   1442: iastore
    //   1443: dup
    //   1444: bipush #11
    //   1446: ldc 8396929
    //   1448: iastore
    //   1449: dup
    //   1450: bipush #12
    //   1452: sipush #129
    //   1455: iastore
    //   1456: dup
    //   1457: bipush #13
    //   1459: iconst_0
    //   1460: iastore
    //   1461: dup
    //   1462: bipush #14
    //   1464: ldc 8388736
    //   1466: iastore
    //   1467: dup
    //   1468: bipush #15
    //   1470: ldc 8388609
    //   1472: iastore
    //   1473: dup
    //   1474: bipush #16
    //   1476: iconst_1
    //   1477: iastore
    //   1478: dup
    //   1479: bipush #17
    //   1481: sipush #8192
    //   1484: iastore
    //   1485: dup
    //   1486: bipush #18
    //   1488: ldc 8388608
    //   1490: iastore
    //   1491: dup
    //   1492: bipush #19
    //   1494: ldc 8396801
    //   1496: iastore
    //   1497: dup
    //   1498: bipush #20
    //   1500: sipush #128
    //   1503: iastore
    //   1504: dup
    //   1505: bipush #21
    //   1507: ldc 8388608
    //   1509: iastore
    //   1510: dup
    //   1511: bipush #22
    //   1513: sipush #8193
    //   1516: iastore
    //   1517: dup
    //   1518: bipush #23
    //   1520: sipush #8320
    //   1523: iastore
    //   1524: dup
    //   1525: bipush #24
    //   1527: ldc 8388737
    //   1529: iastore
    //   1530: dup
    //   1531: bipush #25
    //   1533: iconst_1
    //   1534: iastore
    //   1535: dup
    //   1536: bipush #26
    //   1538: sipush #8320
    //   1541: iastore
    //   1542: dup
    //   1543: bipush #27
    //   1545: ldc 8388736
    //   1547: iastore
    //   1548: dup
    //   1549: bipush #28
    //   1551: sipush #8192
    //   1554: iastore
    //   1555: dup
    //   1556: bipush #29
    //   1558: ldc 8396928
    //   1560: iastore
    //   1561: dup
    //   1562: bipush #30
    //   1564: ldc 8396929
    //   1566: iastore
    //   1567: dup
    //   1568: bipush #31
    //   1570: sipush #129
    //   1573: iastore
    //   1574: dup
    //   1575: bipush #32
    //   1577: ldc 8388736
    //   1579: iastore
    //   1580: dup
    //   1581: bipush #33
    //   1583: ldc 8388609
    //   1585: iastore
    //   1586: dup
    //   1587: bipush #34
    //   1589: ldc 8396800
    //   1591: iastore
    //   1592: dup
    //   1593: bipush #35
    //   1595: ldc 8396929
    //   1597: iastore
    //   1598: dup
    //   1599: bipush #36
    //   1601: sipush #129
    //   1604: iastore
    //   1605: dup
    //   1606: bipush #37
    //   1608: iconst_0
    //   1609: iastore
    //   1610: dup
    //   1611: bipush #38
    //   1613: iconst_0
    //   1614: iastore
    //   1615: dup
    //   1616: bipush #39
    //   1618: ldc 8396800
    //   1620: iastore
    //   1621: dup
    //   1622: bipush #40
    //   1624: sipush #8320
    //   1627: iastore
    //   1628: dup
    //   1629: bipush #41
    //   1631: ldc 8388736
    //   1633: iastore
    //   1634: dup
    //   1635: bipush #42
    //   1637: ldc 8388737
    //   1639: iastore
    //   1640: dup
    //   1641: bipush #43
    //   1643: iconst_1
    //   1644: iastore
    //   1645: dup
    //   1646: bipush #44
    //   1648: ldc 8396801
    //   1650: iastore
    //   1651: dup
    //   1652: bipush #45
    //   1654: sipush #8321
    //   1657: iastore
    //   1658: dup
    //   1659: bipush #46
    //   1661: sipush #8321
    //   1664: iastore
    //   1665: dup
    //   1666: bipush #47
    //   1668: sipush #128
    //   1671: iastore
    //   1672: dup
    //   1673: bipush #48
    //   1675: ldc 8396929
    //   1677: iastore
    //   1678: dup
    //   1679: bipush #49
    //   1681: sipush #129
    //   1684: iastore
    //   1685: dup
    //   1686: bipush #50
    //   1688: iconst_1
    //   1689: iastore
    //   1690: dup
    //   1691: bipush #51
    //   1693: sipush #8192
    //   1696: iastore
    //   1697: dup
    //   1698: bipush #52
    //   1700: ldc 8388609
    //   1702: iastore
    //   1703: dup
    //   1704: bipush #53
    //   1706: sipush #8193
    //   1709: iastore
    //   1710: dup
    //   1711: bipush #54
    //   1713: ldc 8396928
    //   1715: iastore
    //   1716: dup
    //   1717: bipush #55
    //   1719: ldc 8388737
    //   1721: iastore
    //   1722: dup
    //   1723: bipush #56
    //   1725: sipush #8193
    //   1728: iastore
    //   1729: dup
    //   1730: bipush #57
    //   1732: sipush #8320
    //   1735: iastore
    //   1736: dup
    //   1737: bipush #58
    //   1739: ldc 8388608
    //   1741: iastore
    //   1742: dup
    //   1743: bipush #59
    //   1745: ldc 8396801
    //   1747: iastore
    //   1748: dup
    //   1749: bipush #60
    //   1751: sipush #128
    //   1754: iastore
    //   1755: dup
    //   1756: bipush #61
    //   1758: ldc 8388608
    //   1760: iastore
    //   1761: dup
    //   1762: bipush #62
    //   1764: sipush #8192
    //   1767: iastore
    //   1768: dup
    //   1769: bipush #63
    //   1771: ldc 8396928
    //   1773: iastore
    //   1774: astore #9
    //   1776: bipush #64
    //   1778: newarray int
    //   1780: dup
    //   1781: iconst_0
    //   1782: sipush #256
    //   1785: iastore
    //   1786: dup
    //   1787: iconst_1
    //   1788: ldc 34078976
    //   1790: iastore
    //   1791: dup
    //   1792: iconst_2
    //   1793: ldc 34078720
    //   1795: iastore
    //   1796: dup
    //   1797: iconst_3
    //   1798: ldc 1107296512
    //   1800: iastore
    //   1801: dup
    //   1802: iconst_4
    //   1803: ldc 524288
    //   1805: iastore
    //   1806: dup
    //   1807: iconst_5
    //   1808: sipush #256
    //   1811: iastore
    //   1812: dup
    //   1813: bipush #6
    //   1815: ldc 1073741824
    //   1817: iastore
    //   1818: dup
    //   1819: bipush #7
    //   1821: ldc 34078720
    //   1823: iastore
    //   1824: dup
    //   1825: bipush #8
    //   1827: ldc 1074266368
    //   1829: iastore
    //   1830: dup
    //   1831: bipush #9
    //   1833: ldc 524288
    //   1835: iastore
    //   1836: dup
    //   1837: bipush #10
    //   1839: ldc 33554688
    //   1841: iastore
    //   1842: dup
    //   1843: bipush #11
    //   1845: ldc 1074266368
    //   1847: iastore
    //   1848: dup
    //   1849: bipush #12
    //   1851: ldc 1107296512
    //   1853: iastore
    //   1854: dup
    //   1855: bipush #13
    //   1857: ldc 1107820544
    //   1859: iastore
    //   1860: dup
    //   1861: bipush #14
    //   1863: ldc 524544
    //   1865: iastore
    //   1866: dup
    //   1867: bipush #15
    //   1869: ldc 1073741824
    //   1871: iastore
    //   1872: dup
    //   1873: bipush #16
    //   1875: ldc 33554432
    //   1877: iastore
    //   1878: dup
    //   1879: bipush #17
    //   1881: ldc 1074266112
    //   1883: iastore
    //   1884: dup
    //   1885: bipush #18
    //   1887: ldc 1074266112
    //   1889: iastore
    //   1890: dup
    //   1891: bipush #19
    //   1893: iconst_0
    //   1894: iastore
    //   1895: dup
    //   1896: bipush #20
    //   1898: ldc 1073742080
    //   1900: iastore
    //   1901: dup
    //   1902: bipush #21
    //   1904: ldc 1107820800
    //   1906: iastore
    //   1907: dup
    //   1908: bipush #22
    //   1910: ldc 1107820800
    //   1912: iastore
    //   1913: dup
    //   1914: bipush #23
    //   1916: ldc 33554688
    //   1918: iastore
    //   1919: dup
    //   1920: bipush #24
    //   1922: ldc 1107820544
    //   1924: iastore
    //   1925: dup
    //   1926: bipush #25
    //   1928: ldc 1073742080
    //   1930: iastore
    //   1931: dup
    //   1932: bipush #26
    //   1934: iconst_0
    //   1935: iastore
    //   1936: dup
    //   1937: bipush #27
    //   1939: ldc 1107296256
    //   1941: iastore
    //   1942: dup
    //   1943: bipush #28
    //   1945: ldc 34078976
    //   1947: iastore
    //   1948: dup
    //   1949: bipush #29
    //   1951: ldc 33554432
    //   1953: iastore
    //   1954: dup
    //   1955: bipush #30
    //   1957: ldc 1107296256
    //   1959: iastore
    //   1960: dup
    //   1961: bipush #31
    //   1963: ldc 524544
    //   1965: iastore
    //   1966: dup
    //   1967: bipush #32
    //   1969: ldc 524288
    //   1971: iastore
    //   1972: dup
    //   1973: bipush #33
    //   1975: ldc 1107296512
    //   1977: iastore
    //   1978: dup
    //   1979: bipush #34
    //   1981: sipush #256
    //   1984: iastore
    //   1985: dup
    //   1986: bipush #35
    //   1988: ldc 33554432
    //   1990: iastore
    //   1991: dup
    //   1992: bipush #36
    //   1994: ldc 1073741824
    //   1996: iastore
    //   1997: dup
    //   1998: bipush #37
    //   2000: ldc 34078720
    //   2002: iastore
    //   2003: dup
    //   2004: bipush #38
    //   2006: ldc 1107296512
    //   2008: iastore
    //   2009: dup
    //   2010: bipush #39
    //   2012: ldc 1074266368
    //   2014: iastore
    //   2015: dup
    //   2016: bipush #40
    //   2018: ldc 33554688
    //   2020: iastore
    //   2021: dup
    //   2022: bipush #41
    //   2024: ldc 1073741824
    //   2026: iastore
    //   2027: dup
    //   2028: bipush #42
    //   2030: ldc 1107820544
    //   2032: iastore
    //   2033: dup
    //   2034: bipush #43
    //   2036: ldc 34078976
    //   2038: iastore
    //   2039: dup
    //   2040: bipush #44
    //   2042: ldc 1074266368
    //   2044: iastore
    //   2045: dup
    //   2046: bipush #45
    //   2048: sipush #256
    //   2051: iastore
    //   2052: dup
    //   2053: bipush #46
    //   2055: ldc 33554432
    //   2057: iastore
    //   2058: dup
    //   2059: bipush #47
    //   2061: ldc 1107820544
    //   2063: iastore
    //   2064: dup
    //   2065: bipush #48
    //   2067: ldc 1107820800
    //   2069: iastore
    //   2070: dup
    //   2071: bipush #49
    //   2073: ldc 524544
    //   2075: iastore
    //   2076: dup
    //   2077: bipush #50
    //   2079: ldc 1107296256
    //   2081: iastore
    //   2082: dup
    //   2083: bipush #51
    //   2085: ldc 1107820800
    //   2087: iastore
    //   2088: dup
    //   2089: bipush #52
    //   2091: ldc 34078720
    //   2093: iastore
    //   2094: dup
    //   2095: bipush #53
    //   2097: iconst_0
    //   2098: iastore
    //   2099: dup
    //   2100: bipush #54
    //   2102: ldc 1074266112
    //   2104: iastore
    //   2105: dup
    //   2106: bipush #55
    //   2108: ldc 1107296256
    //   2110: iastore
    //   2111: dup
    //   2112: bipush #56
    //   2114: ldc 524544
    //   2116: iastore
    //   2117: dup
    //   2118: bipush #57
    //   2120: ldc 33554688
    //   2122: iastore
    //   2123: dup
    //   2124: bipush #58
    //   2126: ldc 1073742080
    //   2128: iastore
    //   2129: dup
    //   2130: bipush #59
    //   2132: ldc 524288
    //   2134: iastore
    //   2135: dup
    //   2136: bipush #60
    //   2138: iconst_0
    //   2139: iastore
    //   2140: dup
    //   2141: bipush #61
    //   2143: ldc 1074266112
    //   2145: iastore
    //   2146: dup
    //   2147: bipush #62
    //   2149: ldc 34078976
    //   2151: iastore
    //   2152: dup
    //   2153: bipush #63
    //   2155: ldc 1073742080
    //   2157: iastore
    //   2158: astore #10
    //   2160: bipush #64
    //   2162: newarray int
    //   2164: dup
    //   2165: iconst_0
    //   2166: ldc 536870928
    //   2168: iastore
    //   2169: dup
    //   2170: iconst_1
    //   2171: ldc 541065216
    //   2173: iastore
    //   2174: dup
    //   2175: iconst_2
    //   2176: sipush #16384
    //   2179: iastore
    //   2180: dup
    //   2181: iconst_3
    //   2182: ldc 541081616
    //   2184: iastore
    //   2185: dup
    //   2186: iconst_4
    //   2187: ldc 541065216
    //   2189: iastore
    //   2190: dup
    //   2191: iconst_5
    //   2192: bipush #16
    //   2194: iastore
    //   2195: dup
    //   2196: bipush #6
    //   2198: ldc 541081616
    //   2200: iastore
    //   2201: dup
    //   2202: bipush #7
    //   2204: ldc 4194304
    //   2206: iastore
    //   2207: dup
    //   2208: bipush #8
    //   2210: ldc 536887296
    //   2212: iastore
    //   2213: dup
    //   2214: bipush #9
    //   2216: ldc 4210704
    //   2218: iastore
    //   2219: dup
    //   2220: bipush #10
    //   2222: ldc 4194304
    //   2224: iastore
    //   2225: dup
    //   2226: bipush #11
    //   2228: ldc 536870928
    //   2230: iastore
    //   2231: dup
    //   2232: bipush #12
    //   2234: ldc 4194320
    //   2236: iastore
    //   2237: dup
    //   2238: bipush #13
    //   2240: ldc 536887296
    //   2242: iastore
    //   2243: dup
    //   2244: bipush #14
    //   2246: ldc 536870912
    //   2248: iastore
    //   2249: dup
    //   2250: bipush #15
    //   2252: sipush #16400
    //   2255: iastore
    //   2256: dup
    //   2257: bipush #16
    //   2259: iconst_0
    //   2260: iastore
    //   2261: dup
    //   2262: bipush #17
    //   2264: ldc 4194320
    //   2266: iastore
    //   2267: dup
    //   2268: bipush #18
    //   2270: ldc 536887312
    //   2272: iastore
    //   2273: dup
    //   2274: bipush #19
    //   2276: sipush #16384
    //   2279: iastore
    //   2280: dup
    //   2281: bipush #20
    //   2283: ldc 4210688
    //   2285: iastore
    //   2286: dup
    //   2287: bipush #21
    //   2289: ldc 536887312
    //   2291: iastore
    //   2292: dup
    //   2293: bipush #22
    //   2295: bipush #16
    //   2297: iastore
    //   2298: dup
    //   2299: bipush #23
    //   2301: ldc 541065232
    //   2303: iastore
    //   2304: dup
    //   2305: bipush #24
    //   2307: ldc 541065232
    //   2309: iastore
    //   2310: dup
    //   2311: bipush #25
    //   2313: iconst_0
    //   2314: iastore
    //   2315: dup
    //   2316: bipush #26
    //   2318: ldc 4210704
    //   2320: iastore
    //   2321: dup
    //   2322: bipush #27
    //   2324: ldc 541081600
    //   2326: iastore
    //   2327: dup
    //   2328: bipush #28
    //   2330: sipush #16400
    //   2333: iastore
    //   2334: dup
    //   2335: bipush #29
    //   2337: ldc 4210688
    //   2339: iastore
    //   2340: dup
    //   2341: bipush #30
    //   2343: ldc 541081600
    //   2345: iastore
    //   2346: dup
    //   2347: bipush #31
    //   2349: ldc 536870912
    //   2351: iastore
    //   2352: dup
    //   2353: bipush #32
    //   2355: ldc 536887296
    //   2357: iastore
    //   2358: dup
    //   2359: bipush #33
    //   2361: bipush #16
    //   2363: iastore
    //   2364: dup
    //   2365: bipush #34
    //   2367: ldc 541065232
    //   2369: iastore
    //   2370: dup
    //   2371: bipush #35
    //   2373: ldc 4210688
    //   2375: iastore
    //   2376: dup
    //   2377: bipush #36
    //   2379: ldc 541081616
    //   2381: iastore
    //   2382: dup
    //   2383: bipush #37
    //   2385: ldc 4194304
    //   2387: iastore
    //   2388: dup
    //   2389: bipush #38
    //   2391: sipush #16400
    //   2394: iastore
    //   2395: dup
    //   2396: bipush #39
    //   2398: ldc 536870928
    //   2400: iastore
    //   2401: dup
    //   2402: bipush #40
    //   2404: ldc 4194304
    //   2406: iastore
    //   2407: dup
    //   2408: bipush #41
    //   2410: ldc 536887296
    //   2412: iastore
    //   2413: dup
    //   2414: bipush #42
    //   2416: ldc 536870912
    //   2418: iastore
    //   2419: dup
    //   2420: bipush #43
    //   2422: sipush #16400
    //   2425: iastore
    //   2426: dup
    //   2427: bipush #44
    //   2429: ldc 536870928
    //   2431: iastore
    //   2432: dup
    //   2433: bipush #45
    //   2435: ldc 541081616
    //   2437: iastore
    //   2438: dup
    //   2439: bipush #46
    //   2441: ldc 4210688
    //   2443: iastore
    //   2444: dup
    //   2445: bipush #47
    //   2447: ldc 541065216
    //   2449: iastore
    //   2450: dup
    //   2451: bipush #48
    //   2453: ldc 4210704
    //   2455: iastore
    //   2456: dup
    //   2457: bipush #49
    //   2459: ldc 541081600
    //   2461: iastore
    //   2462: dup
    //   2463: bipush #50
    //   2465: iconst_0
    //   2466: iastore
    //   2467: dup
    //   2468: bipush #51
    //   2470: ldc 541065232
    //   2472: iastore
    //   2473: dup
    //   2474: bipush #52
    //   2476: bipush #16
    //   2478: iastore
    //   2479: dup
    //   2480: bipush #53
    //   2482: sipush #16384
    //   2485: iastore
    //   2486: dup
    //   2487: bipush #54
    //   2489: ldc 541065216
    //   2491: iastore
    //   2492: dup
    //   2493: bipush #55
    //   2495: ldc 4210704
    //   2497: iastore
    //   2498: dup
    //   2499: bipush #56
    //   2501: sipush #16384
    //   2504: iastore
    //   2505: dup
    //   2506: bipush #57
    //   2508: ldc 4194320
    //   2510: iastore
    //   2511: dup
    //   2512: bipush #58
    //   2514: ldc 536887312
    //   2516: iastore
    //   2517: dup
    //   2518: bipush #59
    //   2520: iconst_0
    //   2521: iastore
    //   2522: dup
    //   2523: bipush #60
    //   2525: ldc 541081600
    //   2527: iastore
    //   2528: dup
    //   2529: bipush #61
    //   2531: ldc 536870912
    //   2533: iastore
    //   2534: dup
    //   2535: bipush #62
    //   2537: ldc 4194320
    //   2539: iastore
    //   2540: dup
    //   2541: bipush #63
    //   2543: ldc 536887312
    //   2545: iastore
    //   2546: astore #11
    //   2548: bipush #64
    //   2550: newarray int
    //   2552: dup
    //   2553: iconst_0
    //   2554: ldc 2097152
    //   2556: iastore
    //   2557: dup
    //   2558: iconst_1
    //   2559: ldc 69206018
    //   2561: iastore
    //   2562: dup
    //   2563: iconst_2
    //   2564: ldc 67110914
    //   2566: iastore
    //   2567: dup
    //   2568: iconst_3
    //   2569: iconst_0
    //   2570: iastore
    //   2571: dup
    //   2572: iconst_4
    //   2573: sipush #2048
    //   2576: iastore
    //   2577: dup
    //   2578: iconst_5
    //   2579: ldc 67110914
    //   2581: iastore
    //   2582: dup
    //   2583: bipush #6
    //   2585: ldc 2099202
    //   2587: iastore
    //   2588: dup
    //   2589: bipush #7
    //   2591: ldc 69208064
    //   2593: iastore
    //   2594: dup
    //   2595: bipush #8
    //   2597: ldc 69208066
    //   2599: iastore
    //   2600: dup
    //   2601: bipush #9
    //   2603: ldc 2097152
    //   2605: iastore
    //   2606: dup
    //   2607: bipush #10
    //   2609: iconst_0
    //   2610: iastore
    //   2611: dup
    //   2612: bipush #11
    //   2614: ldc 67108866
    //   2616: iastore
    //   2617: dup
    //   2618: bipush #12
    //   2620: iconst_2
    //   2621: iastore
    //   2622: dup
    //   2623: bipush #13
    //   2625: ldc 67108864
    //   2627: iastore
    //   2628: dup
    //   2629: bipush #14
    //   2631: ldc 69206018
    //   2633: iastore
    //   2634: dup
    //   2635: bipush #15
    //   2637: sipush #2050
    //   2640: iastore
    //   2641: dup
    //   2642: bipush #16
    //   2644: ldc 67110912
    //   2646: iastore
    //   2647: dup
    //   2648: bipush #17
    //   2650: ldc 2099202
    //   2652: iastore
    //   2653: dup
    //   2654: bipush #18
    //   2656: ldc 2097154
    //   2658: iastore
    //   2659: dup
    //   2660: bipush #19
    //   2662: ldc 67110912
    //   2664: iastore
    //   2665: dup
    //   2666: bipush #20
    //   2668: ldc 67108866
    //   2670: iastore
    //   2671: dup
    //   2672: bipush #21
    //   2674: ldc 69206016
    //   2676: iastore
    //   2677: dup
    //   2678: bipush #22
    //   2680: ldc 69208064
    //   2682: iastore
    //   2683: dup
    //   2684: bipush #23
    //   2686: ldc 2097154
    //   2688: iastore
    //   2689: dup
    //   2690: bipush #24
    //   2692: ldc 69206016
    //   2694: iastore
    //   2695: dup
    //   2696: bipush #25
    //   2698: sipush #2048
    //   2701: iastore
    //   2702: dup
    //   2703: bipush #26
    //   2705: sipush #2050
    //   2708: iastore
    //   2709: dup
    //   2710: bipush #27
    //   2712: ldc 69208066
    //   2714: iastore
    //   2715: dup
    //   2716: bipush #28
    //   2718: ldc 2099200
    //   2720: iastore
    //   2721: dup
    //   2722: bipush #29
    //   2724: iconst_2
    //   2725: iastore
    //   2726: dup
    //   2727: bipush #30
    //   2729: ldc 67108864
    //   2731: iastore
    //   2732: dup
    //   2733: bipush #31
    //   2735: ldc 2099200
    //   2737: iastore
    //   2738: dup
    //   2739: bipush #32
    //   2741: ldc 67108864
    //   2743: iastore
    //   2744: dup
    //   2745: bipush #33
    //   2747: ldc 2099200
    //   2749: iastore
    //   2750: dup
    //   2751: bipush #34
    //   2753: ldc 2097152
    //   2755: iastore
    //   2756: dup
    //   2757: bipush #35
    //   2759: ldc 67110914
    //   2761: iastore
    //   2762: dup
    //   2763: bipush #36
    //   2765: ldc 67110914
    //   2767: iastore
    //   2768: dup
    //   2769: bipush #37
    //   2771: ldc 69206018
    //   2773: iastore
    //   2774: dup
    //   2775: bipush #38
    //   2777: ldc 69206018
    //   2779: iastore
    //   2780: dup
    //   2781: bipush #39
    //   2783: iconst_2
    //   2784: iastore
    //   2785: dup
    //   2786: bipush #40
    //   2788: ldc 2097154
    //   2790: iastore
    //   2791: dup
    //   2792: bipush #41
    //   2794: ldc 67108864
    //   2796: iastore
    //   2797: dup
    //   2798: bipush #42
    //   2800: ldc 67110912
    //   2802: iastore
    //   2803: dup
    //   2804: bipush #43
    //   2806: ldc 2097152
    //   2808: iastore
    //   2809: dup
    //   2810: bipush #44
    //   2812: ldc 69208064
    //   2814: iastore
    //   2815: dup
    //   2816: bipush #45
    //   2818: sipush #2050
    //   2821: iastore
    //   2822: dup
    //   2823: bipush #46
    //   2825: ldc 2099202
    //   2827: iastore
    //   2828: dup
    //   2829: bipush #47
    //   2831: ldc 69208064
    //   2833: iastore
    //   2834: dup
    //   2835: bipush #48
    //   2837: sipush #2050
    //   2840: iastore
    //   2841: dup
    //   2842: bipush #49
    //   2844: ldc 67108866
    //   2846: iastore
    //   2847: dup
    //   2848: bipush #50
    //   2850: ldc 69208066
    //   2852: iastore
    //   2853: dup
    //   2854: bipush #51
    //   2856: ldc 69206016
    //   2858: iastore
    //   2859: dup
    //   2860: bipush #52
    //   2862: ldc 2099200
    //   2864: iastore
    //   2865: dup
    //   2866: bipush #53
    //   2868: iconst_0
    //   2869: iastore
    //   2870: dup
    //   2871: bipush #54
    //   2873: iconst_2
    //   2874: iastore
    //   2875: dup
    //   2876: bipush #55
    //   2878: ldc 69208066
    //   2880: iastore
    //   2881: dup
    //   2882: bipush #56
    //   2884: iconst_0
    //   2885: iastore
    //   2886: dup
    //   2887: bipush #57
    //   2889: ldc 2099202
    //   2891: iastore
    //   2892: dup
    //   2893: bipush #58
    //   2895: ldc 69206016
    //   2897: iastore
    //   2898: dup
    //   2899: bipush #59
    //   2901: sipush #2048
    //   2904: iastore
    //   2905: dup
    //   2906: bipush #60
    //   2908: ldc 67108866
    //   2910: iastore
    //   2911: dup
    //   2912: bipush #61
    //   2914: ldc 67110912
    //   2916: iastore
    //   2917: dup
    //   2918: bipush #62
    //   2920: sipush #2048
    //   2923: iastore
    //   2924: dup
    //   2925: bipush #63
    //   2927: ldc 2097154
    //   2929: iastore
    //   2930: astore #12
    //   2932: bipush #64
    //   2934: newarray int
    //   2936: dup
    //   2937: iconst_0
    //   2938: ldc 268439616
    //   2940: iastore
    //   2941: dup
    //   2942: iconst_1
    //   2943: sipush #4096
    //   2946: iastore
    //   2947: dup
    //   2948: iconst_2
    //   2949: ldc 262144
    //   2951: iastore
    //   2952: dup
    //   2953: iconst_3
    //   2954: ldc 268701760
    //   2956: iastore
    //   2957: dup
    //   2958: iconst_4
    //   2959: ldc 268435456
    //   2961: iastore
    //   2962: dup
    //   2963: iconst_5
    //   2964: ldc 268439616
    //   2966: iastore
    //   2967: dup
    //   2968: bipush #6
    //   2970: bipush #64
    //   2972: iastore
    //   2973: dup
    //   2974: bipush #7
    //   2976: ldc 268435456
    //   2978: iastore
    //   2979: dup
    //   2980: bipush #8
    //   2982: ldc 262208
    //   2984: iastore
    //   2985: dup
    //   2986: bipush #9
    //   2988: ldc 268697600
    //   2990: iastore
    //   2991: dup
    //   2992: bipush #10
    //   2994: ldc 268701760
    //   2996: iastore
    //   2997: dup
    //   2998: bipush #11
    //   3000: ldc 266240
    //   3002: iastore
    //   3003: dup
    //   3004: bipush #12
    //   3006: ldc 268701696
    //   3008: iastore
    //   3009: dup
    //   3010: bipush #13
    //   3012: ldc 266304
    //   3014: iastore
    //   3015: dup
    //   3016: bipush #14
    //   3018: sipush #4096
    //   3021: iastore
    //   3022: dup
    //   3023: bipush #15
    //   3025: bipush #64
    //   3027: iastore
    //   3028: dup
    //   3029: bipush #16
    //   3031: ldc 268697600
    //   3033: iastore
    //   3034: dup
    //   3035: bipush #17
    //   3037: ldc 268435520
    //   3039: iastore
    //   3040: dup
    //   3041: bipush #18
    //   3043: ldc 268439552
    //   3045: iastore
    //   3046: dup
    //   3047: bipush #19
    //   3049: sipush #4160
    //   3052: iastore
    //   3053: dup
    //   3054: bipush #20
    //   3056: ldc 266240
    //   3058: iastore
    //   3059: dup
    //   3060: bipush #21
    //   3062: ldc 262208
    //   3064: iastore
    //   3065: dup
    //   3066: bipush #22
    //   3068: ldc 268697664
    //   3070: iastore
    //   3071: dup
    //   3072: bipush #23
    //   3074: ldc 268701696
    //   3076: iastore
    //   3077: dup
    //   3078: bipush #24
    //   3080: sipush #4160
    //   3083: iastore
    //   3084: dup
    //   3085: bipush #25
    //   3087: iconst_0
    //   3088: iastore
    //   3089: dup
    //   3090: bipush #26
    //   3092: iconst_0
    //   3093: iastore
    //   3094: dup
    //   3095: bipush #27
    //   3097: ldc 268697664
    //   3099: iastore
    //   3100: dup
    //   3101: bipush #28
    //   3103: ldc 268435520
    //   3105: iastore
    //   3106: dup
    //   3107: bipush #29
    //   3109: ldc 268439552
    //   3111: iastore
    //   3112: dup
    //   3113: bipush #30
    //   3115: ldc 266304
    //   3117: iastore
    //   3118: dup
    //   3119: bipush #31
    //   3121: ldc 262144
    //   3123: iastore
    //   3124: dup
    //   3125: bipush #32
    //   3127: ldc 266304
    //   3129: iastore
    //   3130: dup
    //   3131: bipush #33
    //   3133: ldc 262144
    //   3135: iastore
    //   3136: dup
    //   3137: bipush #34
    //   3139: ldc 268701696
    //   3141: iastore
    //   3142: dup
    //   3143: bipush #35
    //   3145: sipush #4096
    //   3148: iastore
    //   3149: dup
    //   3150: bipush #36
    //   3152: bipush #64
    //   3154: iastore
    //   3155: dup
    //   3156: bipush #37
    //   3158: ldc 268697664
    //   3160: iastore
    //   3161: dup
    //   3162: bipush #38
    //   3164: sipush #4096
    //   3167: iastore
    //   3168: dup
    //   3169: bipush #39
    //   3171: ldc 266304
    //   3173: iastore
    //   3174: dup
    //   3175: bipush #40
    //   3177: ldc 268439552
    //   3179: iastore
    //   3180: dup
    //   3181: bipush #41
    //   3183: bipush #64
    //   3185: iastore
    //   3186: dup
    //   3187: bipush #42
    //   3189: ldc 268435520
    //   3191: iastore
    //   3192: dup
    //   3193: bipush #43
    //   3195: ldc 268697600
    //   3197: iastore
    //   3198: dup
    //   3199: bipush #44
    //   3201: ldc 268697664
    //   3203: iastore
    //   3204: dup
    //   3205: bipush #45
    //   3207: ldc 268435456
    //   3209: iastore
    //   3210: dup
    //   3211: bipush #46
    //   3213: ldc 262144
    //   3215: iastore
    //   3216: dup
    //   3217: bipush #47
    //   3219: ldc 268439616
    //   3221: iastore
    //   3222: dup
    //   3223: bipush #48
    //   3225: iconst_0
    //   3226: iastore
    //   3227: dup
    //   3228: bipush #49
    //   3230: ldc 268701760
    //   3232: iastore
    //   3233: dup
    //   3234: bipush #50
    //   3236: ldc 262208
    //   3238: iastore
    //   3239: dup
    //   3240: bipush #51
    //   3242: ldc 268435520
    //   3244: iastore
    //   3245: dup
    //   3246: bipush #52
    //   3248: ldc 268697600
    //   3250: iastore
    //   3251: dup
    //   3252: bipush #53
    //   3254: ldc 268439552
    //   3256: iastore
    //   3257: dup
    //   3258: bipush #54
    //   3260: ldc 268439616
    //   3262: iastore
    //   3263: dup
    //   3264: bipush #55
    //   3266: iconst_0
    //   3267: iastore
    //   3268: dup
    //   3269: bipush #56
    //   3271: ldc 268701760
    //   3273: iastore
    //   3274: dup
    //   3275: bipush #57
    //   3277: ldc 266240
    //   3279: iastore
    //   3280: dup
    //   3281: bipush #58
    //   3283: ldc 266240
    //   3285: iastore
    //   3286: dup
    //   3287: bipush #59
    //   3289: sipush #4160
    //   3292: iastore
    //   3293: dup
    //   3294: bipush #60
    //   3296: sipush #4160
    //   3299: iastore
    //   3300: dup
    //   3301: bipush #61
    //   3303: ldc 262208
    //   3305: iastore
    //   3306: dup
    //   3307: bipush #62
    //   3309: ldc 268435456
    //   3311: iastore
    //   3312: dup
    //   3313: bipush #63
    //   3315: ldc 268701696
    //   3317: iastore
    //   3318: astore #13
    //   3320: aload_3
    //   3321: arraylength
    //   3322: istore #14
    //   3324: iload #14
    //   3326: bipush #8
    //   3328: irem
    //   3329: ifeq -> 3353
    //   3332: new java/lang/Exception
    //   3335: dup
    //   3336: sipush #16527
    //   3339: sipush #17160
    //   3342: invokestatic a : (II)Ljava/lang/String;
    //   3345: invokespecial <init> : (Ljava/lang/String;)V
    //   3348: athrow
    //   3349: invokestatic a : (Ljava/lang/Throwable;)Ljava/lang/Throwable;
    //   3352: athrow
    //   3353: iconst_2
    //   3354: newarray int
    //   3356: astore #15
    //   3358: iload #14
    //   3360: newarray byte
    //   3362: astore #16
    //   3364: iload #14
    //   3366: bipush #8
    //   3368: idiv
    //   3369: istore #17
    //   3371: iconst_0
    //   3372: istore #18
    //   3374: iload #18
    //   3376: iload #17
    //   3378: if_icmpge -> 4292
    //   3381: iload #18
    //   3383: bipush #8
    //   3385: imul
    //   3386: istore #19
    //   3388: iconst_0
    //   3389: istore #20
    //   3391: iload #20
    //   3393: iconst_2
    //   3394: if_icmpge -> 3479
    //   3397: aload #15
    //   3399: iload #20
    //   3401: aload_3
    //   3402: iload #19
    //   3404: iload #20
    //   3406: iconst_4
    //   3407: imul
    //   3408: iadd
    //   3409: baload
    //   3410: sipush #255
    //   3413: iand
    //   3414: bipush #24
    //   3416: ishl
    //   3417: aload_3
    //   3418: iload #19
    //   3420: iload #20
    //   3422: iconst_4
    //   3423: imul
    //   3424: iadd
    //   3425: iconst_1
    //   3426: iadd
    //   3427: baload
    //   3428: sipush #255
    //   3431: iand
    //   3432: bipush #16
    //   3434: ishl
    //   3435: ior
    //   3436: aload_3
    //   3437: iload #19
    //   3439: iload #20
    //   3441: iconst_4
    //   3442: imul
    //   3443: iadd
    //   3444: iconst_2
    //   3445: iadd
    //   3446: baload
    //   3447: sipush #255
    //   3450: iand
    //   3451: bipush #8
    //   3453: ishl
    //   3454: ior
    //   3455: aload_3
    //   3456: iload #19
    //   3458: iload #20
    //   3460: iconst_4
    //   3461: imul
    //   3462: iadd
    //   3463: iconst_3
    //   3464: iadd
    //   3465: baload
    //   3466: sipush #255
    //   3469: iand
    //   3470: ior
    //   3471: iastore
    //   3472: iinc #20, 1
    //   3475: iload_2
    //   3476: ifne -> 3391
    //   3479: iconst_0
    //   3480: istore #25
    //   3482: aload #15
    //   3484: iconst_0
    //   3485: iaload
    //   3486: istore #23
    //   3488: aload #15
    //   3490: iconst_1
    //   3491: iaload
    //   3492: istore #22
    //   3494: iload #23
    //   3496: iconst_4
    //   3497: iushr
    //   3498: iload #22
    //   3500: ixor
    //   3501: ldc 252645135
    //   3503: iand
    //   3504: istore #21
    //   3506: iload #22
    //   3508: iload #21
    //   3510: ixor
    //   3511: istore #22
    //   3513: iload #23
    //   3515: iload #21
    //   3517: iconst_4
    //   3518: ishl
    //   3519: ixor
    //   3520: istore #23
    //   3522: iload #23
    //   3524: bipush #16
    //   3526: iushr
    //   3527: iload #22
    //   3529: ixor
    //   3530: ldc 65535
    //   3532: iand
    //   3533: istore #21
    //   3535: iload #22
    //   3537: iload #21
    //   3539: ixor
    //   3540: istore #22
    //   3542: iload #23
    //   3544: iload #21
    //   3546: bipush #16
    //   3548: ishl
    //   3549: ixor
    //   3550: istore #23
    //   3552: iload #22
    //   3554: iconst_2
    //   3555: iushr
    //   3556: iload #23
    //   3558: ixor
    //   3559: ldc 858993459
    //   3561: iand
    //   3562: istore #21
    //   3564: iload #23
    //   3566: iload #21
    //   3568: ixor
    //   3569: istore #23
    //   3571: iload #22
    //   3573: iload #21
    //   3575: iconst_2
    //   3576: ishl
    //   3577: ixor
    //   3578: istore #22
    //   3580: iload #22
    //   3582: bipush #8
    //   3584: iushr
    //   3585: iload #23
    //   3587: ixor
    //   3588: ldc 16711935
    //   3590: iand
    //   3591: istore #21
    //   3593: iload #23
    //   3595: iload #21
    //   3597: ixor
    //   3598: istore #23
    //   3600: iload #22
    //   3602: iload #21
    //   3604: bipush #8
    //   3606: ishl
    //   3607: ixor
    //   3608: istore #22
    //   3610: iload #22
    //   3612: iconst_1
    //   3613: ishl
    //   3614: iload #22
    //   3616: bipush #31
    //   3618: iushr
    //   3619: iconst_1
    //   3620: iand
    //   3621: ior
    //   3622: istore #22
    //   3624: iload #23
    //   3626: iload #22
    //   3628: ixor
    //   3629: ldc -1431655766
    //   3631: iand
    //   3632: istore #21
    //   3634: iload #23
    //   3636: iload #21
    //   3638: ixor
    //   3639: istore #23
    //   3641: iload #22
    //   3643: iload #21
    //   3645: ixor
    //   3646: istore #22
    //   3648: iload #23
    //   3650: iconst_1
    //   3651: ishl
    //   3652: iload #23
    //   3654: bipush #31
    //   3656: iushr
    //   3657: iconst_1
    //   3658: iand
    //   3659: ior
    //   3660: istore #23
    //   3662: iconst_0
    //   3663: istore #24
    //   3665: iload #24
    //   3667: bipush #8
    //   3669: if_icmpge -> 4007
    //   3672: iload #22
    //   3674: bipush #28
    //   3676: ishl
    //   3677: iload #22
    //   3679: iconst_4
    //   3680: iushr
    //   3681: ior
    //   3682: istore #21
    //   3684: iload #21
    //   3686: aload #5
    //   3688: iload #25
    //   3690: iinc #25, 1
    //   3693: iaload
    //   3694: ixor
    //   3695: istore #21
    //   3697: aload #12
    //   3699: iload #21
    //   3701: bipush #63
    //   3703: iand
    //   3704: iaload
    //   3705: istore #20
    //   3707: iload #20
    //   3709: aload #10
    //   3711: iload #21
    //   3713: bipush #8
    //   3715: iushr
    //   3716: bipush #63
    //   3718: iand
    //   3719: iaload
    //   3720: ior
    //   3721: istore #20
    //   3723: iload #20
    //   3725: aload #8
    //   3727: iload #21
    //   3729: bipush #16
    //   3731: iushr
    //   3732: bipush #63
    //   3734: iand
    //   3735: iaload
    //   3736: ior
    //   3737: istore #20
    //   3739: iload #20
    //   3741: aload #6
    //   3743: iload #21
    //   3745: bipush #24
    //   3747: iushr
    //   3748: bipush #63
    //   3750: iand
    //   3751: iaload
    //   3752: ior
    //   3753: istore #20
    //   3755: iload #22
    //   3757: aload #5
    //   3759: iload #25
    //   3761: iinc #25, 1
    //   3764: iaload
    //   3765: ixor
    //   3766: istore #21
    //   3768: iload #20
    //   3770: aload #13
    //   3772: iload #21
    //   3774: bipush #63
    //   3776: iand
    //   3777: iaload
    //   3778: ior
    //   3779: istore #20
    //   3781: iload #20
    //   3783: aload #11
    //   3785: iload #21
    //   3787: bipush #8
    //   3789: iushr
    //   3790: bipush #63
    //   3792: iand
    //   3793: iaload
    //   3794: ior
    //   3795: istore #20
    //   3797: iload #20
    //   3799: aload #9
    //   3801: iload #21
    //   3803: bipush #16
    //   3805: iushr
    //   3806: bipush #63
    //   3808: iand
    //   3809: iaload
    //   3810: ior
    //   3811: istore #20
    //   3813: iload #20
    //   3815: aload #7
    //   3817: iload #21
    //   3819: bipush #24
    //   3821: iushr
    //   3822: bipush #63
    //   3824: iand
    //   3825: iaload
    //   3826: ior
    //   3827: istore #20
    //   3829: iload #23
    //   3831: iload #20
    //   3833: ixor
    //   3834: istore #23
    //   3836: iload #23
    //   3838: bipush #28
    //   3840: ishl
    //   3841: iload #23
    //   3843: iconst_4
    //   3844: iushr
    //   3845: ior
    //   3846: istore #21
    //   3848: iload #21
    //   3850: aload #5
    //   3852: iload #25
    //   3854: iinc #25, 1
    //   3857: iaload
    //   3858: ixor
    //   3859: istore #21
    //   3861: aload #12
    //   3863: iload #21
    //   3865: bipush #63
    //   3867: iand
    //   3868: iaload
    //   3869: istore #20
    //   3871: iload #20
    //   3873: aload #10
    //   3875: iload #21
    //   3877: bipush #8
    //   3879: iushr
    //   3880: bipush #63
    //   3882: iand
    //   3883: iaload
    //   3884: ior
    //   3885: istore #20
    //   3887: iload #20
    //   3889: aload #8
    //   3891: iload #21
    //   3893: bipush #16
    //   3895: iushr
    //   3896: bipush #63
    //   3898: iand
    //   3899: iaload
    //   3900: ior
    //   3901: istore #20
    //   3903: iload #20
    //   3905: aload #6
    //   3907: iload #21
    //   3909: bipush #24
    //   3911: iushr
    //   3912: bipush #63
    //   3914: iand
    //   3915: iaload
    //   3916: ior
    //   3917: istore #20
    //   3919: iload #23
    //   3921: aload #5
    //   3923: iload #25
    //   3925: iinc #25, 1
    //   3928: iaload
    //   3929: ixor
    //   3930: istore #21
    //   3932: iload #20
    //   3934: aload #13
    //   3936: iload #21
    //   3938: bipush #63
    //   3940: iand
    //   3941: iaload
    //   3942: ior
    //   3943: istore #20
    //   3945: iload #20
    //   3947: aload #11
    //   3949: iload #21
    //   3951: bipush #8
    //   3953: iushr
    //   3954: bipush #63
    //   3956: iand
    //   3957: iaload
    //   3958: ior
    //   3959: istore #20
    //   3961: iload #20
    //   3963: aload #9
    //   3965: iload #21
    //   3967: bipush #16
    //   3969: iushr
    //   3970: bipush #63
    //   3972: iand
    //   3973: iaload
    //   3974: ior
    //   3975: istore #20
    //   3977: iload #20
    //   3979: aload #7
    //   3981: iload #21
    //   3983: bipush #24
    //   3985: iushr
    //   3986: bipush #63
    //   3988: iand
    //   3989: iaload
    //   3990: ior
    //   3991: istore #20
    //   3993: iload #22
    //   3995: iload #20
    //   3997: ixor
    //   3998: istore #22
    //   4000: iinc #24, 1
    //   4003: iload_2
    //   4004: ifne -> 3665
    //   4007: iload #22
    //   4009: bipush #31
    //   4011: ishl
    //   4012: iload #22
    //   4014: iconst_1
    //   4015: iushr
    //   4016: ior
    //   4017: istore #22
    //   4019: iload #23
    //   4021: iload #22
    //   4023: ixor
    //   4024: ldc -1431655766
    //   4026: iand
    //   4027: istore #21
    //   4029: iload #23
    //   4031: iload #21
    //   4033: ixor
    //   4034: istore #23
    //   4036: iload #22
    //   4038: iload #21
    //   4040: ixor
    //   4041: istore #22
    //   4043: iload #23
    //   4045: bipush #31
    //   4047: ishl
    //   4048: iload #23
    //   4050: iconst_1
    //   4051: iushr
    //   4052: ior
    //   4053: istore #23
    //   4055: iload #23
    //   4057: bipush #8
    //   4059: iushr
    //   4060: iload #22
    //   4062: ixor
    //   4063: ldc 16711935
    //   4065: iand
    //   4066: istore #21
    //   4068: iload #22
    //   4070: iload #21
    //   4072: ixor
    //   4073: istore #22
    //   4075: iload #23
    //   4077: iload #21
    //   4079: bipush #8
    //   4081: ishl
    //   4082: ixor
    //   4083: istore #23
    //   4085: iload #23
    //   4087: iconst_2
    //   4088: iushr
    //   4089: iload #22
    //   4091: ixor
    //   4092: ldc 858993459
    //   4094: iand
    //   4095: istore #21
    //   4097: iload #22
    //   4099: iload #21
    //   4101: ixor
    //   4102: istore #22
    //   4104: iload #23
    //   4106: iload #21
    //   4108: iconst_2
    //   4109: ishl
    //   4110: ixor
    //   4111: istore #23
    //   4113: iload #22
    //   4115: bipush #16
    //   4117: iushr
    //   4118: iload #23
    //   4120: ixor
    //   4121: ldc 65535
    //   4123: iand
    //   4124: istore #21
    //   4126: iload #23
    //   4128: iload #21
    //   4130: ixor
    //   4131: istore #23
    //   4133: iload #22
    //   4135: iload #21
    //   4137: bipush #16
    //   4139: ishl
    //   4140: ixor
    //   4141: istore #22
    //   4143: iload #22
    //   4145: iconst_4
    //   4146: iushr
    //   4147: iload #23
    //   4149: ixor
    //   4150: ldc 252645135
    //   4152: iand
    //   4153: istore #21
    //   4155: iload #23
    //   4157: iload #21
    //   4159: ixor
    //   4160: istore #23
    //   4162: iload #22
    //   4164: iload #21
    //   4166: iconst_4
    //   4167: ishl
    //   4168: ixor
    //   4169: istore #22
    //   4171: aload #15
    //   4173: iconst_0
    //   4174: iload #22
    //   4176: iastore
    //   4177: aload #15
    //   4179: iconst_1
    //   4180: iload #23
    //   4182: iastore
    //   4183: iload #18
    //   4185: bipush #8
    //   4187: imul
    //   4188: istore #26
    //   4190: iconst_0
    //   4191: istore #27
    //   4193: iload #27
    //   4195: iconst_2
    //   4196: if_icmpge -> 4285
    //   4199: aload #16
    //   4201: iload #26
    //   4203: iload #27
    //   4205: iconst_4
    //   4206: imul
    //   4207: iadd
    //   4208: aload #15
    //   4210: iload #27
    //   4212: iaload
    //   4213: bipush #24
    //   4215: iushr
    //   4216: i2b
    //   4217: bastore
    //   4218: aload #16
    //   4220: iload #26
    //   4222: iload #27
    //   4224: iconst_4
    //   4225: imul
    //   4226: iadd
    //   4227: iconst_1
    //   4228: iadd
    //   4229: aload #15
    //   4231: iload #27
    //   4233: iaload
    //   4234: bipush #16
    //   4236: iushr
    //   4237: i2b
    //   4238: bastore
    //   4239: aload #16
    //   4241: iload #26
    //   4243: iload #27
    //   4245: iconst_4
    //   4246: imul
    //   4247: iadd
    //   4248: iconst_2
    //   4249: iadd
    //   4250: aload #15
    //   4252: iload #27
    //   4254: iaload
    //   4255: bipush #8
    //   4257: iushr
    //   4258: i2b
    //   4259: bastore
    //   4260: aload #16
    //   4262: iload #26
    //   4264: iload #27
    //   4266: iconst_4
    //   4267: imul
    //   4268: iadd
    //   4269: iconst_3
    //   4270: iadd
    //   4271: aload #15
    //   4273: iload #27
    //   4275: iaload
    //   4276: i2b
    //   4277: bastore
    //   4278: iinc #27, 1
    //   4281: iload_2
    //   4282: ifne -> 4193
    //   4285: iinc #18, 1
    //   4288: iload_2
    //   4289: ifne -> 3374
    //   4292: aload #16
    //   4294: aload #16
    //   4296: arraylength
    //   4297: iconst_1
    //   4298: isub
    //   4299: baload
    //   4300: istore #18
    //   4302: aload #16
    //   4304: arraylength
    //   4305: iload #18
    //   4307: isub
    //   4308: newarray byte
    //   4310: astore #4
    //   4312: aload #16
    //   4314: arraylength
    //   4315: aload #4
    //   4317: arraylength
    //   4318: if_icmpge -> 4342
    //   4321: new java/lang/Exception
    //   4324: dup
    //   4325: sipush #16533
    //   4328: sipush #-22953
    //   4331: invokestatic a : (II)Ljava/lang/String;
    //   4334: invokespecial <init> : (Ljava/lang/String;)V
    //   4337: athrow
    //   4338: invokestatic a : (Ljava/lang/Throwable;)Ljava/lang/Throwable;
    //   4341: athrow
    //   4342: iconst_0
    //   4343: istore #19
    //   4345: iload #19
    //   4347: aload #4
    //   4349: arraylength
    //   4350: if_icmpge -> 4370
    //   4353: aload #4
    //   4355: iload #19
    //   4357: aload #16
    //   4359: iload #19
    //   4361: baload
    //   4362: bastore
    //   4363: iinc #19, 1
    //   4366: iload_2
    //   4367: ifne -> 4345
    //   4370: new java/math/BigInteger
    //   4373: dup
    //   4374: aload #4
    //   4376: invokespecial <init> : ([B)V
    //   4379: invokevirtual abs : ()Ljava/math/BigInteger;
    //   4382: putstatic burp/Ztvg.ZO : Ljava/lang/Object;
    //   4385: sipush #16513
    //   4388: sipush #21508
    //   4391: invokestatic a : (II)Ljava/lang/String;
    //   4394: iconst_1
    //   4395: ldc burp/Zl55
    //   4397: invokevirtual getClassLoader : ()Ljava/lang/ClassLoader;
    //   4400: invokestatic forName : (Ljava/lang/String;ZLjava/lang/ClassLoader;)Ljava/lang/Class;
    //   4403: invokevirtual getDeclaredFields : ()[Ljava/lang/reflect/Field;
    //   4406: astore_3
    //   4407: aload_3
    //   4408: arraylength
    //   4409: istore #4
    //   4411: iconst_0
    //   4412: istore #5
    //   4414: iload #5
    //   4416: iload #4
    //   4418: if_icmpge -> 4555
    //   4421: aload_3
    //   4422: iload #5
    //   4424: aaload
    //   4425: astore #6
    //   4427: aload #6
    //   4429: invokevirtual getModifiers : ()I
    //   4432: invokestatic isStatic : (I)Z
    //   4435: ifne -> 4445
    //   4438: goto -> 4548
    //   4441: invokestatic a : (Ljava/lang/Throwable;)Ljava/lang/Throwable;
    //   4444: athrow
    //   4445: aload #6
    //   4447: invokevirtual getType : ()Ljava/lang/Class;
    //   4450: astore #7
    //   4452: aload #7
    //   4454: ifnull -> 4535
    //   4457: aload #7
    //   4459: invokevirtual isPrimitive : ()Z
    //   4462: ifne -> 4535
    //   4465: goto -> 4472
    //   4468: invokestatic a : (Ljava/lang/Throwable;)Ljava/lang/Throwable;
    //   4471: athrow
    //   4472: aload #7
    //   4474: invokevirtual getPackage : ()Ljava/lang/Package;
    //   4477: ifnull -> 4535
    //   4480: goto -> 4487
    //   4483: invokestatic a : (Ljava/lang/Throwable;)Ljava/lang/Throwable;
    //   4486: athrow
    //   4487: aload #7
    //   4489: invokevirtual getPackage : ()Ljava/lang/Package;
    //   4492: invokevirtual getName : ()Ljava/lang/String;
    //   4495: ifnull -> 4535
    //   4498: goto -> 4505
    //   4501: invokestatic a : (Ljava/lang/Throwable;)Ljava/lang/Throwable;
    //   4504: athrow
    //   4505: aload #7
    //   4507: invokevirtual getPackage : ()Ljava/lang/Package;
    //   4510: invokevirtual getName : ()Ljava/lang/String;
    //   4513: sipush #16541
    //   4516: sipush #-13311
    //   4519: invokestatic a : (II)Ljava/lang/String;
    //   4522: invokevirtual startsWith : (Ljava/lang/String;)Z
    //   4525: ifne -> 4535
    //   4528: goto -> 4535
    //   4531: invokestatic a : (Ljava/lang/Throwable;)Ljava/lang/Throwable;
    //   4534: athrow
    //   4535: aload #6
    //   4537: iconst_1
    //   4538: invokevirtual setAccessible : (Z)V
    //   4541: aload #6
    //   4543: aconst_null
    //   4544: invokevirtual get : (Ljava/lang/Object;)Ljava/lang/Object;
    //   4547: pop
    //   4548: iinc #5, 1
    //   4551: iload_2
    //   4552: ifne -> 4414
    //   4555: sipush #16516
    //   4558: sipush #-25229
    //   4561: invokestatic a : (II)Ljava/lang/String;
    //   4564: invokestatic forName : (Ljava/lang/String;)Ljava/lang/Class;
    //   4567: invokevirtual getDeclaredMethods : ()[Ljava/lang/reflect/Method;
    //   4570: astore_3
    //   4571: aload_3
    //   4572: arraylength
    //   4573: istore #4
    //   4575: iconst_0
    //   4576: istore #5
    //   4578: iload #5
    //   4580: iload #4
    //   4582: if_icmpge -> 4714
    //   4585: aload_3
    //   4586: iload #5
    //   4588: aaload
    //   4589: astore #6
    //   4591: aload #6
    //   4593: invokevirtual getParameterTypes : ()[Ljava/lang/Class;
    //   4596: pop
    //   4597: aload #6
    //   4599: invokevirtual getModifiers : ()I
    //   4602: invokestatic isStatic : (I)Z
    //   4605: ifeq -> 4700
    //   4608: aload #6
    //   4610: invokevirtual getParameterTypes : ()[Ljava/lang/Class;
    //   4613: arraylength
    //   4614: iconst_2
    //   4615: if_icmpne -> 4700
    //   4618: goto -> 4625
    //   4621: invokestatic a : (Ljava/lang/Throwable;)Ljava/lang/Throwable;
    //   4624: athrow
    //   4625: aload #6
    //   4627: invokevirtual getReturnType : ()Ljava/lang/Class;
    //   4630: getstatic java/lang/Void.TYPE : Ljava/lang/Class;
    //   4633: invokevirtual equals : (Ljava/lang/Object;)Z
    //   4636: ifeq -> 4700
    //   4639: goto -> 4646
    //   4642: invokestatic a : (Ljava/lang/Throwable;)Ljava/lang/Throwable;
    //   4645: athrow
    //   4646: aload #6
    //   4648: iconst_1
    //   4649: invokevirtual setAccessible : (Z)V
    //   4652: aload #6
    //   4654: aconst_null
    //   4655: iconst_2
    //   4656: anewarray java/lang/Object
    //   4659: dup
    //   4660: iconst_0
    //   4661: aload_0
    //   4662: aastore
    //   4663: dup
    //   4664: iconst_1
    //   4665: aload_1
    //   4666: ifnonnull -> 4684
    //   4669: goto -> 4676
    //   4672: invokestatic a : (Ljava/lang/Throwable;)Ljava/lang/Throwable;
    //   4675: athrow
    //   4676: aload_1
    //   4677: goto -> 4691
    //   4680: invokestatic a : (Ljava/lang/Throwable;)Ljava/lang/Throwable;
    //   4683: athrow
    //   4684: aload_1
    //   4685: checkcast [B
    //   4688: invokevirtual clone : ()Ljava/lang/Object;
    //   4691: aastore
    //   4692: invokevirtual invoke : (Ljava/lang/Object;[Ljava/lang/Object;)Ljava/lang/Object;
    //   4695: pop
    //   4696: iload_2
    //   4697: ifne -> 4714
    //   4700: iinc #5, 1
    //   4703: iload_2
    //   4704: ifne -> 4578
    //   4707: goto -> 4714
    //   4710: invokestatic a : (Ljava/lang/Throwable;)Ljava/lang/Throwable;
    //   4713: athrow
    //   4714: iconst_0
    //   4715: istore_3
    //   4716: getstatic burp/Zvob.Zn : Ljava/lang/String;
    //   4719: getstatic burp/Zxxo.ZJ : Ljava/lang/Object;
    //   4722: checkcast java/math/BigInteger
    //   4725: invokevirtual intValue : ()I
    //   4728: bipush #32
    //   4730: irem
    //   4731: invokestatic abs : (I)I
    //   4734: invokevirtual charAt : (I)C
    //   4737: getstatic burp/Zrww.ZV : Ljava/lang/String;
    //   4740: getstatic burp/Zssc.Zr : Ljava/lang/Object;
    //   4743: checkcast java/math/BigInteger
    //   4746: invokevirtual intValue : ()I
    //   4749: bipush #32
    //   4751: irem
    //   4752: invokestatic abs : (I)I
    //   4755: invokevirtual charAt : (I)C
    //   4758: if_icmpgt -> 5102
    //   4761: sipush #16514
    //   4764: sipush #-9443
    //   4767: invokestatic a : (II)Ljava/lang/String;
    //   4770: iconst_1
    //   4771: ldc burp/Zkk6
    //   4773: invokevirtual getClassLoader : ()Ljava/lang/ClassLoader;
    //   4776: invokestatic forName : (Ljava/lang/String;ZLjava/lang/ClassLoader;)Ljava/lang/Class;
    //   4779: invokevirtual getDeclaredFields : ()[Ljava/lang/reflect/Field;
    //   4782: astore #4
    //   4784: aload #4
    //   4786: arraylength
    //   4787: istore #5
    //   4789: iconst_0
    //   4790: istore #6
    //   4792: iload #6
    //   4794: iload #5
    //   4796: if_icmpge -> 4934
    //   4799: aload #4
    //   4801: iload #6
    //   4803: aaload
    //   4804: astore #7
    //   4806: aload #7
    //   4808: invokevirtual getModifiers : ()I
    //   4811: invokestatic isStatic : (I)Z
    //   4814: ifne -> 4824
    //   4817: goto -> 4927
    //   4820: invokestatic a : (Ljava/lang/Throwable;)Ljava/lang/Throwable;
    //   4823: athrow
    //   4824: aload #7
    //   4826: invokevirtual getType : ()Ljava/lang/Class;
    //   4829: astore #8
    //   4831: aload #8
    //   4833: ifnull -> 4914
    //   4836: aload #8
    //   4838: invokevirtual isPrimitive : ()Z
    //   4841: ifne -> 4914
    //   4844: goto -> 4851
    //   4847: invokestatic a : (Ljava/lang/Throwable;)Ljava/lang/Throwable;
    //   4850: athrow
    //   4851: aload #8
    //   4853: invokevirtual getPackage : ()Ljava/lang/Package;
    //   4856: ifnull -> 4914
    //   4859: goto -> 4866
    //   4862: invokestatic a : (Ljava/lang/Throwable;)Ljava/lang/Throwable;
    //   4865: athrow
    //   4866: aload #8
    //   4868: invokevirtual getPackage : ()Ljava/lang/Package;
    //   4871: invokevirtual getName : ()Ljava/lang/String;
    //   4874: ifnull -> 4914
    //   4877: goto -> 4884
    //   4880: invokestatic a : (Ljava/lang/Throwable;)Ljava/lang/Throwable;
    //   4883: athrow
    //   4884: aload #8
    //   4886: invokevirtual getPackage : ()Ljava/lang/Package;
    //   4889: invokevirtual getName : ()Ljava/lang/String;
    //   4892: sipush #16538
    //   4895: sipush #3416
    //   4898: invokestatic a : (II)Ljava/lang/String;
    //   4901: invokevirtual startsWith : (Ljava/lang/String;)Z
    //   4904: ifne -> 4914
    //   4907: goto -> 4914
    //   4910: invokestatic a : (Ljava/lang/Throwable;)Ljava/lang/Throwable;
    //   4913: athrow
    //   4914: aload #7
    //   4916: iconst_1
    //   4917: invokevirtual setAccessible : (Z)V
    //   4920: aload #7
    //   4922: aconst_null
    //   4923: invokevirtual get : (Ljava/lang/Object;)Ljava/lang/Object;
    //   4926: pop
    //   4927: iinc #6, 1
    //   4930: iload_2
    //   4931: ifne -> 4792
    //   4934: sipush #16524
    //   4937: sipush #-19836
    //   4940: invokestatic a : (II)Ljava/lang/String;
    //   4943: invokestatic forName : (Ljava/lang/String;)Ljava/lang/Class;
    //   4946: invokevirtual getDeclaredMethods : ()[Ljava/lang/reflect/Method;
    //   4949: astore #4
    //   4951: aload #4
    //   4953: arraylength
    //   4954: istore #5
    //   4956: iconst_0
    //   4957: istore #6
    //   4959: iload #6
    //   4961: iload #5
    //   4963: if_icmpge -> 5099
    //   4966: aload #4
    //   4968: iload #6
    //   4970: aaload
    //   4971: astore #7
    //   4973: aload #7
    //   4975: invokevirtual getParameterTypes : ()[Ljava/lang/Class;
    //   4978: pop
    //   4979: aload #7
    //   4981: invokevirtual getModifiers : ()I
    //   4984: invokestatic isStatic : (I)Z
    //   4987: ifeq -> 5085
    //   4990: aload #7
    //   4992: invokevirtual getParameterTypes : ()[Ljava/lang/Class;
    //   4995: arraylength
    //   4996: iconst_2
    //   4997: if_icmpne -> 5085
    //   5000: goto -> 5007
    //   5003: invokestatic a : (Ljava/lang/Throwable;)Ljava/lang/Throwable;
    //   5006: athrow
    //   5007: aload #7
    //   5009: invokevirtual getReturnType : ()Ljava/lang/Class;
    //   5012: getstatic java/lang/Boolean.TYPE : Ljava/lang/Class;
    //   5015: if_acmpne -> 5085
    //   5018: goto -> 5025
    //   5021: invokestatic a : (Ljava/lang/Throwable;)Ljava/lang/Throwable;
    //   5024: athrow
    //   5025: aload #7
    //   5027: iconst_1
    //   5028: invokevirtual setAccessible : (Z)V
    //   5031: aload #7
    //   5033: aconst_null
    //   5034: iconst_2
    //   5035: anewarray java/lang/Object
    //   5038: dup
    //   5039: iconst_0
    //   5040: aload_0
    //   5041: aastore
    //   5042: dup
    //   5043: iconst_1
    //   5044: aload_1
    //   5045: ifnonnull -> 5063
    //   5048: goto -> 5055
    //   5051: invokestatic a : (Ljava/lang/Throwable;)Ljava/lang/Throwable;
    //   5054: athrow
    //   5055: aload_1
    //   5056: goto -> 5070
    //   5059: invokestatic a : (Ljava/lang/Throwable;)Ljava/lang/Throwable;
    //   5062: athrow
    //   5063: aload_1
    //   5064: checkcast [B
    //   5067: invokevirtual clone : ()Ljava/lang/Object;
    //   5070: aastore
    //   5071: invokevirtual invoke : (Ljava/lang/Object;[Ljava/lang/Object;)Ljava/lang/Object;
    //   5074: checkcast java/lang/Boolean
    //   5077: invokevirtual booleanValue : ()Z
    //   5080: istore_3
    //   5081: iload_2
    //   5082: ifne -> 5099
    //   5085: iinc #6, 1
    //   5088: iload_2
    //   5089: ifne -> 4959
    //   5092: goto -> 5099
    //   5095: invokestatic a : (Ljava/lang/Throwable;)Ljava/lang/Throwable;
    //   5098: athrow
    //   5099: goto -> 5440
    //   5102: sipush #16539
    //   5105: sipush #-14245
    //   5108: invokestatic a : (II)Ljava/lang/String;
    //   5111: iconst_1
    //   5112: ldc burp/Zx4w
    //   5114: invokevirtual getClassLoader : ()Ljava/lang/ClassLoader;
    //   5117: invokestatic forName : (Ljava/lang/String;ZLjava/lang/ClassLoader;)Ljava/lang/Class;
    //   5120: invokevirtual getDeclaredFields : ()[Ljava/lang/reflect/Field;
    //   5123: astore #4
    //   5125: aload #4
    //   5127: arraylength
    //   5128: istore #5
    //   5130: iconst_0
    //   5131: istore #6
    //   5133: iload #6
    //   5135: iload #5
    //   5137: if_icmpge -> 5275
    //   5140: aload #4
    //   5142: iload #6
    //   5144: aaload
    //   5145: astore #7
    //   5147: aload #7
    //   5149: invokevirtual getModifiers : ()I
    //   5152: invokestatic isStatic : (I)Z
    //   5155: ifne -> 5165
    //   5158: goto -> 5268
    //   5161: invokestatic a : (Ljava/lang/Throwable;)Ljava/lang/Throwable;
    //   5164: athrow
    //   5165: aload #7
    //   5167: invokevirtual getType : ()Ljava/lang/Class;
    //   5170: astore #8
    //   5172: aload #8
    //   5174: ifnull -> 5255
    //   5177: aload #8
    //   5179: invokevirtual isPrimitive : ()Z
    //   5182: ifne -> 5255
    //   5185: goto -> 5192
    //   5188: invokestatic a : (Ljava/lang/Throwable;)Ljava/lang/Throwable;
    //   5191: athrow
    //   5192: aload #8
    //   5194: invokevirtual getPackage : ()Ljava/lang/Package;
    //   5197: ifnull -> 5255
    //   5200: goto -> 5207
    //   5203: invokestatic a : (Ljava/lang/Throwable;)Ljava/lang/Throwable;
    //   5206: athrow
    //   5207: aload #8
    //   5209: invokevirtual getPackage : ()Ljava/lang/Package;
    //   5212: invokevirtual getName : ()Ljava/lang/String;
    //   5215: ifnull -> 5255
    //   5218: goto -> 5225
    //   5221: invokestatic a : (Ljava/lang/Throwable;)Ljava/lang/Throwable;
    //   5224: athrow
    //   5225: aload #8
    //   5227: invokevirtual getPackage : ()Ljava/lang/Package;
    //   5230: invokevirtual getName : ()Ljava/lang/String;
    //   5233: sipush #16538
    //   5236: sipush #3416
    //   5239: invokestatic a : (II)Ljava/lang/String;
    //   5242: invokevirtual startsWith : (Ljava/lang/String;)Z
    //   5245: ifne -> 5255
    //   5248: goto -> 5255
    //   5251: invokestatic a : (Ljava/lang/Throwable;)Ljava/lang/Throwable;
    //   5254: athrow
    //   5255: aload #7
    //   5257: iconst_1
    //   5258: invokevirtual setAccessible : (Z)V
    //   5261: aload #7
    //   5263: aconst_null
    //   5264: invokevirtual get : (Ljava/lang/Object;)Ljava/lang/Object;
    //   5267: pop
    //   5268: iinc #6, 1
    //   5271: iload_2
    //   5272: ifne -> 5133
    //   5275: sipush #16532
    //   5278: sipush #26947
    //   5281: invokestatic a : (II)Ljava/lang/String;
    //   5284: invokestatic forName : (Ljava/lang/String;)Ljava/lang/Class;
    //   5287: invokevirtual getDeclaredMethods : ()[Ljava/lang/reflect/Method;
    //   5290: astore #4
    //   5292: aload #4
    //   5294: arraylength
    //   5295: istore #5
    //   5297: iconst_0
    //   5298: istore #6
    //   5300: iload #6
    //   5302: iload #5
    //   5304: if_icmpge -> 5440
    //   5307: aload #4
    //   5309: iload #6
    //   5311: aaload
    //   5312: astore #7
    //   5314: aload #7
    //   5316: invokevirtual getParameterTypes : ()[Ljava/lang/Class;
    //   5319: pop
    //   5320: aload #7
    //   5322: invokevirtual getModifiers : ()I
    //   5325: invokestatic isStatic : (I)Z
    //   5328: ifeq -> 5426
    //   5331: aload #7
    //   5333: invokevirtual getParameterTypes : ()[Ljava/lang/Class;
    //   5336: arraylength
    //   5337: iconst_2
    //   5338: if_icmpne -> 5426
    //   5341: goto -> 5348
    //   5344: invokestatic a : (Ljava/lang/Throwable;)Ljava/lang/Throwable;
    //   5347: athrow
    //   5348: aload #7
    //   5350: invokevirtual getReturnType : ()Ljava/lang/Class;
    //   5353: getstatic java/lang/Boolean.TYPE : Ljava/lang/Class;
    //   5356: if_acmpne -> 5426
    //   5359: goto -> 5366
    //   5362: invokestatic a : (Ljava/lang/Throwable;)Ljava/lang/Throwable;
    //   5365: athrow
    //   5366: aload #7
    //   5368: iconst_1
    //   5369: invokevirtual setAccessible : (Z)V
    //   5372: aload #7
    //   5374: aconst_null
    //   5375: iconst_2
    //   5376: anewarray java/lang/Object
    //   5379: dup
    //   5380: iconst_0
    //   5381: aload_0
    //   5382: aastore
    //   5383: dup
    //   5384: iconst_1
    //   5385: aload_1
    //   5386: ifnonnull -> 5404
    //   5389: goto -> 5396
    //   5392: invokestatic a : (Ljava/lang/Throwable;)Ljava/lang/Throwable;
    //   5395: athrow
    //   5396: aload_1
    //   5397: goto -> 5411
    //   5400: invokestatic a : (Ljava/lang/Throwable;)Ljava/lang/Throwable;
    //   5403: athrow
    //   5404: aload_1
    //   5405: checkcast [B
    //   5408: invokevirtual clone : ()Ljava/lang/Object;
    //   5411: aastore
    //   5412: invokevirtual invoke : (Ljava/lang/Object;[Ljava/lang/Object;)Ljava/lang/Object;
    //   5415: checkcast java/lang/Boolean
    //   5418: invokevirtual booleanValue : ()Z
    //   5421: istore_3
    //   5422: iload_2
    //   5423: ifne -> 5440
    //   5426: iinc #6, 1
    //   5429: iload_2
    //   5430: ifne -> 5300
    //   5433: goto -> 5440
    //   5436: invokestatic a : (Ljava/lang/Throwable;)Ljava/lang/Throwable;
    //   5439: athrow
    //   5440: iload_3
    //   5441: ifeq -> 5446
    //   5444: iload_3
    //   5445: ireturn
    //   5446: getstatic burp/Zsvd.ZB : Ljava/lang/String;
    //   5449: getstatic burp/Zlt1.ZH : Ljava/lang/Object;
    //   5452: checkcast java/math/BigInteger
    //   5455: invokevirtual intValue : ()I
    //   5458: bipush #32
    //   5460: irem
    //   5461: invokestatic abs : (I)I
    //   5464: invokevirtual charAt : (I)C
    //   5467: getstatic burp/Zewr.ZW : Ljava/lang/String;
    //   5470: getstatic burp/Zr14.Zy : Ljava/lang/Object;
    //   5473: checkcast java/math/BigInteger
    //   5476: invokevirtual intValue : ()I
    //   5479: bipush #32
    //   5481: irem
    //   5482: invokestatic abs : (I)I
    //   5485: invokevirtual charAt : (I)C
    //   5488: if_icmpgt -> 5833
    //   5491: sipush #16529
    //   5494: sipush #16724
    //   5497: invokestatic a : (II)Ljava/lang/String;
    //   5500: iconst_1
    //   5501: ldc burp/Zg2z
    //   5503: invokevirtual getClassLoader : ()Ljava/lang/ClassLoader;
    //   5506: invokestatic forName : (Ljava/lang/String;ZLjava/lang/ClassLoader;)Ljava/lang/Class;
    //   5509: invokevirtual getDeclaredFields : ()[Ljava/lang/reflect/Field;
    //   5512: astore #4
    //   5514: aload #4
    //   5516: arraylength
    //   5517: istore #5
    //   5519: iconst_0
    //   5520: istore #6
    //   5522: iload #6
    //   5524: iload #5
    //   5526: if_icmpge -> 5664
    //   5529: aload #4
    //   5531: iload #6
    //   5533: aaload
    //   5534: astore #7
    //   5536: aload #7
    //   5538: invokevirtual getModifiers : ()I
    //   5541: invokestatic isStatic : (I)Z
    //   5544: ifne -> 5554
    //   5547: goto -> 5657
    //   5550: invokestatic a : (Ljava/lang/Throwable;)Ljava/lang/Throwable;
    //   5553: athrow
    //   5554: aload #7
    //   5556: invokevirtual getType : ()Ljava/lang/Class;
    //   5559: astore #8
    //   5561: aload #8
    //   5563: ifnull -> 5644
    //   5566: aload #8
    //   5568: invokevirtual isPrimitive : ()Z
    //   5571: ifne -> 5644
    //   5574: goto -> 5581
    //   5577: invokestatic a : (Ljava/lang/Throwable;)Ljava/lang/Throwable;
    //   5580: athrow
    //   5581: aload #8
    //   5583: invokevirtual getPackage : ()Ljava/lang/Package;
    //   5586: ifnull -> 5644
    //   5589: goto -> 5596
    //   5592: invokestatic a : (Ljava/lang/Throwable;)Ljava/lang/Throwable;
    //   5595: athrow
    //   5596: aload #8
    //   5598: invokevirtual getPackage : ()Ljava/lang/Package;
    //   5601: invokevirtual getName : ()Ljava/lang/String;
    //   5604: ifnull -> 5644
    //   5607: goto -> 5614
    //   5610: invokestatic a : (Ljava/lang/Throwable;)Ljava/lang/Throwable;
    //   5613: athrow
    //   5614: aload #8
    //   5616: invokevirtual getPackage : ()Ljava/lang/Package;
    //   5619: invokevirtual getName : ()Ljava/lang/String;
    //   5622: sipush #16538
    //   5625: sipush #3416
    //   5628: invokestatic a : (II)Ljava/lang/String;
    //   5631: invokevirtual startsWith : (Ljava/lang/String;)Z
    //   5634: ifne -> 5644
    //   5637: goto -> 5644
    //   5640: invokestatic a : (Ljava/lang/Throwable;)Ljava/lang/Throwable;
    //   5643: athrow
    //   5644: aload #7
    //   5646: iconst_1
    //   5647: invokevirtual setAccessible : (Z)V
    //   5650: aload #7
    //   5652: aconst_null
    //   5653: invokevirtual get : (Ljava/lang/Object;)Ljava/lang/Object;
    //   5656: pop
    //   5657: iinc #6, 1
    //   5660: iload_2
    //   5661: ifne -> 5522
    //   5664: sipush #16512
    //   5667: sipush #20953
    //   5670: invokestatic a : (II)Ljava/lang/String;
    //   5673: invokestatic forName : (Ljava/lang/String;)Ljava/lang/Class;
    //   5676: invokevirtual getDeclaredMethods : ()[Ljava/lang/reflect/Method;
    //   5679: astore #4
    //   5681: aload #4
    //   5683: arraylength
    //   5684: istore #5
    //   5686: iconst_0
    //   5687: istore #6
    //   5689: iload #6
    //   5691: iload #5
    //   5693: if_icmpge -> 5829
    //   5696: aload #4
    //   5698: iload #6
    //   5700: aaload
    //   5701: astore #7
    //   5703: aload #7
    //   5705: invokevirtual getParameterTypes : ()[Ljava/lang/Class;
    //   5708: pop
    //   5709: aload #7
    //   5711: invokevirtual getModifiers : ()I
    //   5714: invokestatic isStatic : (I)Z
    //   5717: ifeq -> 5815
    //   5720: aload #7
    //   5722: invokevirtual getParameterTypes : ()[Ljava/lang/Class;
    //   5725: arraylength
    //   5726: iconst_2
    //   5727: if_icmpne -> 5815
    //   5730: goto -> 5737
    //   5733: invokestatic a : (Ljava/lang/Throwable;)Ljava/lang/Throwable;
    //   5736: athrow
    //   5737: aload #7
    //   5739: invokevirtual getReturnType : ()Ljava/lang/Class;
    //   5742: getstatic java/lang/Boolean.TYPE : Ljava/lang/Class;
    //   5745: if_acmpne -> 5815
    //   5748: goto -> 5755
    //   5751: invokestatic a : (Ljava/lang/Throwable;)Ljava/lang/Throwable;
    //   5754: athrow
    //   5755: aload #7
    //   5757: iconst_1
    //   5758: invokevirtual setAccessible : (Z)V
    //   5761: aload #7
    //   5763: aconst_null
    //   5764: iconst_2
    //   5765: anewarray java/lang/Object
    //   5768: dup
    //   5769: iconst_0
    //   5770: aload_0
    //   5771: aastore
    //   5772: dup
    //   5773: iconst_1
    //   5774: aload_1
    //   5775: ifnonnull -> 5793
    //   5778: goto -> 5785
    //   5781: invokestatic a : (Ljava/lang/Throwable;)Ljava/lang/Throwable;
    //   5784: athrow
    //   5785: aload_1
    //   5786: goto -> 5800
    //   5789: invokestatic a : (Ljava/lang/Throwable;)Ljava/lang/Throwable;
    //   5792: athrow
    //   5793: aload_1
    //   5794: checkcast [B
    //   5797: invokevirtual clone : ()Ljava/lang/Object;
    //   5800: aastore
    //   5801: invokevirtual invoke : (Ljava/lang/Object;[Ljava/lang/Object;)Ljava/lang/Object;
    //   5804: checkcast java/lang/Boolean
    //   5807: invokevirtual booleanValue : ()Z
    //   5810: istore_3
    //   5811: iload_2
    //   5812: ifne -> 5829
    //   5815: iinc #6, 1
    //   5818: iload_2
    //   5819: ifne -> 5689
    //   5822: goto -> 5829
    //   5825: invokestatic a : (Ljava/lang/Throwable;)Ljava/lang/Throwable;
    //   5828: athrow
    //   5829: iload_2
    //   5830: ifne -> 6171
    //   5833: sipush #16531
    //   5836: sipush #-29536
    //   5839: invokestatic a : (II)Ljava/lang/String;
    //   5842: iconst_1
    //   5843: ldc burp/Zr3x
    //   5845: invokevirtual getClassLoader : ()Ljava/lang/ClassLoader;
    //   5848: invokestatic forName : (Ljava/lang/String;ZLjava/lang/ClassLoader;)Ljava/lang/Class;
    //   5851: invokevirtual getDeclaredFields : ()[Ljava/lang/reflect/Field;
    //   5854: astore #4
    //   5856: aload #4
    //   5858: arraylength
    //   5859: istore #5
    //   5861: iconst_0
    //   5862: istore #6
    //   5864: iload #6
    //   5866: iload #5
    //   5868: if_icmpge -> 6006
    //   5871: aload #4
    //   5873: iload #6
    //   5875: aaload
    //   5876: astore #7
    //   5878: aload #7
    //   5880: invokevirtual getModifiers : ()I
    //   5883: invokestatic isStatic : (I)Z
    //   5886: ifne -> 5896
    //   5889: goto -> 5999
    //   5892: invokestatic a : (Ljava/lang/Throwable;)Ljava/lang/Throwable;
    //   5895: athrow
    //   5896: aload #7
    //   5898: invokevirtual getType : ()Ljava/lang/Class;
    //   5901: astore #8
    //   5903: aload #8
    //   5905: ifnull -> 5986
    //   5908: aload #8
    //   5910: invokevirtual isPrimitive : ()Z
    //   5913: ifne -> 5986
    //   5916: goto -> 5923
    //   5919: invokestatic a : (Ljava/lang/Throwable;)Ljava/lang/Throwable;
    //   5922: athrow
    //   5923: aload #8
    //   5925: invokevirtual getPackage : ()Ljava/lang/Package;
    //   5928: ifnull -> 5986
    //   5931: goto -> 5938
    //   5934: invokestatic a : (Ljava/lang/Throwable;)Ljava/lang/Throwable;
    //   5937: athrow
    //   5938: aload #8
    //   5940: invokevirtual getPackage : ()Ljava/lang/Package;
    //   5943: invokevirtual getName : ()Ljava/lang/String;
    //   5946: ifnull -> 5986
    //   5949: goto -> 5956
    //   5952: invokestatic a : (Ljava/lang/Throwable;)Ljava/lang/Throwable;
    //   5955: athrow
    //   5956: aload #8
    //   5958: invokevirtual getPackage : ()Ljava/lang/Package;
    //   5961: invokevirtual getName : ()Ljava/lang/String;
    //   5964: sipush #16538
    //   5967: sipush #3416
    //   5970: invokestatic a : (II)Ljava/lang/String;
    //   5973: invokevirtual startsWith : (Ljava/lang/String;)Z
    //   5976: ifne -> 5986
    //   5979: goto -> 5986
    //   5982: invokestatic a : (Ljava/lang/Throwable;)Ljava/lang/Throwable;
    //   5985: athrow
    //   5986: aload #7
    //   5988: iconst_1
    //   5989: invokevirtual setAccessible : (Z)V
    //   5992: aload #7
    //   5994: aconst_null
    //   5995: invokevirtual get : (Ljava/lang/Object;)Ljava/lang/Object;
    //   5998: pop
    //   5999: iinc #6, 1
    //   6002: iload_2
    //   6003: ifne -> 5864
    //   6006: sipush #16515
    //   6009: sipush #14596
    //   6012: invokestatic a : (II)Ljava/lang/String;
    //   6015: invokestatic forName : (Ljava/lang/String;)Ljava/lang/Class;
    //   6018: invokevirtual getDeclaredMethods : ()[Ljava/lang/reflect/Method;
    //   6021: astore #4
    //   6023: aload #4
    //   6025: arraylength
    //   6026: istore #5
    //   6028: iconst_0
    //   6029: istore #6
    //   6031: iload #6
    //   6033: iload #5
    //   6035: if_icmpge -> 6171
    //   6038: aload #4
    //   6040: iload #6
    //   6042: aaload
    //   6043: astore #7
    //   6045: aload #7
    //   6047: invokevirtual getParameterTypes : ()[Ljava/lang/Class;
    //   6050: pop
    //   6051: aload #7
    //   6053: invokevirtual getModifiers : ()I
    //   6056: invokestatic isStatic : (I)Z
    //   6059: ifeq -> 6157
    //   6062: aload #7
    //   6064: invokevirtual getParameterTypes : ()[Ljava/lang/Class;
    //   6067: arraylength
    //   6068: iconst_2
    //   6069: if_icmpne -> 6157
    //   6072: goto -> 6079
    //   6075: invokestatic a : (Ljava/lang/Throwable;)Ljava/lang/Throwable;
    //   6078: athrow
    //   6079: aload #7
    //   6081: invokevirtual getReturnType : ()Ljava/lang/Class;
    //   6084: getstatic java/lang/Boolean.TYPE : Ljava/lang/Class;
    //   6087: if_acmpne -> 6157
    //   6090: goto -> 6097
    //   6093: invokestatic a : (Ljava/lang/Throwable;)Ljava/lang/Throwable;
    //   6096: athrow
    //   6097: aload #7
    //   6099: iconst_1
    //   6100: invokevirtual setAccessible : (Z)V
    //   6103: aload #7
    //   6105: aconst_null
    //   6106: iconst_2
    //   6107: anewarray java/lang/Object
    //   6110: dup
    //   6111: iconst_0
    //   6112: aload_0
    //   6113: aastore
    //   6114: dup
    //   6115: iconst_1
    //   6116: aload_1
    //   6117: ifnonnull -> 6135
    //   6120: goto -> 6127
    //   6123: invokestatic a : (Ljava/lang/Throwable;)Ljava/lang/Throwable;
    //   6126: athrow
    //   6127: aload_1
    //   6128: goto -> 6142
    //   6131: invokestatic a : (Ljava/lang/Throwable;)Ljava/lang/Throwable;
    //   6134: athrow
    //   6135: aload_1
    //   6136: checkcast [B
    //   6139: invokevirtual clone : ()Ljava/lang/Object;
    //   6142: aastore
    //   6143: invokevirtual invoke : (Ljava/lang/Object;[Ljava/lang/Object;)Ljava/lang/Object;
    //   6146: checkcast java/lang/Boolean
    //   6149: invokevirtual booleanValue : ()Z
    //   6152: istore_3
    //   6153: iload_2
    //   6154: ifne -> 6171
    //   6157: iinc #6, 1
    //   6160: iload_2
    //   6161: ifne -> 6031
    //   6164: goto -> 6171
    //   6167: invokestatic a : (Ljava/lang/Throwable;)Ljava/lang/Throwable;
    //   6170: athrow
    //   6171: iload_3
    //   6172: ifeq -> 6177
    //   6175: iload_3
    //   6176: ireturn
    //   6177: getstatic burp/Zgtx.ZN : Ljava/lang/String;
    //   6180: getstatic burp/Zrkd.ZO : Ljava/lang/Object;
    //   6183: checkcast java/math/BigInteger
    //   6186: invokevirtual intValue : ()I
    //   6189: bipush #32
    //   6191: irem
    //   6192: invokestatic abs : (I)I
    //   6195: invokevirtual charAt : (I)C
    //   6198: getstatic burp/Zxwf.ZX : Ljava/lang/String;
    //   6201: getstatic burp/Zt5t.Za : Ljava/lang/Object;
    //   6204: checkcast java/math/BigInteger
    //   6207: invokevirtual intValue : ()I
    //   6210: bipush #32
    //   6212: irem
    //   6213: invokestatic abs : (I)I
    //   6216: invokevirtual charAt : (I)C
    //   6219: if_icmple -> 6564
    //   6222: sipush #16540
    //   6225: sipush #-1046
    //   6228: invokestatic a : (II)Ljava/lang/String;
    //   6231: iconst_1
    //   6232: ldc burp/Zldt
    //   6234: invokevirtual getClassLoader : ()Ljava/lang/ClassLoader;
    //   6237: invokestatic forName : (Ljava/lang/String;ZLjava/lang/ClassLoader;)Ljava/lang/Class;
    //   6240: invokevirtual getDeclaredFields : ()[Ljava/lang/reflect/Field;
    //   6243: astore #4
    //   6245: aload #4
    //   6247: arraylength
    //   6248: istore #5
    //   6250: iconst_0
    //   6251: istore #6
    //   6253: iload #6
    //   6255: iload #5
    //   6257: if_icmpge -> 6395
    //   6260: aload #4
    //   6262: iload #6
    //   6264: aaload
    //   6265: astore #7
    //   6267: aload #7
    //   6269: invokevirtual getModifiers : ()I
    //   6272: invokestatic isStatic : (I)Z
    //   6275: ifne -> 6285
    //   6278: goto -> 6388
    //   6281: invokestatic a : (Ljava/lang/Throwable;)Ljava/lang/Throwable;
    //   6284: athrow
    //   6285: aload #7
    //   6287: invokevirtual getType : ()Ljava/lang/Class;
    //   6290: astore #8
    //   6292: aload #8
    //   6294: ifnull -> 6375
    //   6297: aload #8
    //   6299: invokevirtual isPrimitive : ()Z
    //   6302: ifne -> 6375
    //   6305: goto -> 6312
    //   6308: invokestatic a : (Ljava/lang/Throwable;)Ljava/lang/Throwable;
    //   6311: athrow
    //   6312: aload #8
    //   6314: invokevirtual getPackage : ()Ljava/lang/Package;
    //   6317: ifnull -> 6375
    //   6320: goto -> 6327
    //   6323: invokestatic a : (Ljava/lang/Throwable;)Ljava/lang/Throwable;
    //   6326: athrow
    //   6327: aload #8
    //   6329: invokevirtual getPackage : ()Ljava/lang/Package;
    //   6332: invokevirtual getName : ()Ljava/lang/String;
    //   6335: ifnull -> 6375
    //   6338: goto -> 6345
    //   6341: invokestatic a : (Ljava/lang/Throwable;)Ljava/lang/Throwable;
    //   6344: athrow
    //   6345: aload #8
    //   6347: invokevirtual getPackage : ()Ljava/lang/Package;
    //   6350: invokevirtual getName : ()Ljava/lang/String;
    //   6353: sipush #16538
    //   6356: sipush #3416
    //   6359: invokestatic a : (II)Ljava/lang/String;
    //   6362: invokevirtual startsWith : (Ljava/lang/String;)Z
    //   6365: ifne -> 6375
    //   6368: goto -> 6375
    //   6371: invokestatic a : (Ljava/lang/Throwable;)Ljava/lang/Throwable;
    //   6374: athrow
    //   6375: aload #7
    //   6377: iconst_1
    //   6378: invokevirtual setAccessible : (Z)V
    //   6381: aload #7
    //   6383: aconst_null
    //   6384: invokevirtual get : (Ljava/lang/Object;)Ljava/lang/Object;
    //   6387: pop
    //   6388: iinc #6, 1
    //   6391: iload_2
    //   6392: ifne -> 6253
    //   6395: sipush #16519
    //   6398: sipush #2101
    //   6401: invokestatic a : (II)Ljava/lang/String;
    //   6404: invokestatic forName : (Ljava/lang/String;)Ljava/lang/Class;
    //   6407: invokevirtual getDeclaredMethods : ()[Ljava/lang/reflect/Method;
    //   6410: astore #4
    //   6412: aload #4
    //   6414: arraylength
    //   6415: istore #5
    //   6417: iconst_0
    //   6418: istore #6
    //   6420: iload #6
    //   6422: iload #5
    //   6424: if_icmpge -> 6560
    //   6427: aload #4
    //   6429: iload #6
    //   6431: aaload
    //   6432: astore #7
    //   6434: aload #7
    //   6436: invokevirtual getParameterTypes : ()[Ljava/lang/Class;
    //   6439: pop
    //   6440: aload #7
    //   6442: invokevirtual getModifiers : ()I
    //   6445: invokestatic isStatic : (I)Z
    //   6448: ifeq -> 6546
    //   6451: aload #7
    //   6453: invokevirtual getParameterTypes : ()[Ljava/lang/Class;
    //   6456: arraylength
    //   6457: iconst_2
    //   6458: if_icmpne -> 6546
    //   6461: goto -> 6468
    //   6464: invokestatic a : (Ljava/lang/Throwable;)Ljava/lang/Throwable;
    //   6467: athrow
    //   6468: aload #7
    //   6470: invokevirtual getReturnType : ()Ljava/lang/Class;
    //   6473: getstatic java/lang/Boolean.TYPE : Ljava/lang/Class;
    //   6476: if_acmpne -> 6546
    //   6479: goto -> 6486
    //   6482: invokestatic a : (Ljava/lang/Throwable;)Ljava/lang/Throwable;
    //   6485: athrow
    //   6486: aload #7
    //   6488: iconst_1
    //   6489: invokevirtual setAccessible : (Z)V
    //   6492: aload #7
    //   6494: aconst_null
    //   6495: iconst_2
    //   6496: anewarray java/lang/Object
    //   6499: dup
    //   6500: iconst_0
    //   6501: aload_0
    //   6502: aastore
    //   6503: dup
    //   6504: iconst_1
    //   6505: aload_1
    //   6506: ifnonnull -> 6524
    //   6509: goto -> 6516
    //   6512: invokestatic a : (Ljava/lang/Throwable;)Ljava/lang/Throwable;
    //   6515: athrow
    //   6516: aload_1
    //   6517: goto -> 6531
    //   6520: invokestatic a : (Ljava/lang/Throwable;)Ljava/lang/Throwable;
    //   6523: athrow
    //   6524: aload_1
    //   6525: checkcast [B
    //   6528: invokevirtual clone : ()Ljava/lang/Object;
    //   6531: aastore
    //   6532: invokevirtual invoke : (Ljava/lang/Object;[Ljava/lang/Object;)Ljava/lang/Object;
    //   6535: checkcast java/lang/Boolean
    //   6538: invokevirtual booleanValue : ()Z
    //   6541: istore_3
    //   6542: iload_2
    //   6543: ifne -> 6560
    //   6546: iinc #6, 1
    //   6549: iload_2
    //   6550: ifne -> 6420
    //   6553: goto -> 6560
    //   6556: invokestatic a : (Ljava/lang/Throwable;)Ljava/lang/Throwable;
    //   6559: athrow
    //   6560: iload_2
    //   6561: ifne -> 6902
    //   6564: sipush #16543
    //   6567: sipush #-5864
    //   6570: invokestatic a : (II)Ljava/lang/String;
    //   6573: iconst_1
    //   6574: ldc burp/Zl1u
    //   6576: invokevirtual getClassLoader : ()Ljava/lang/ClassLoader;
    //   6579: invokestatic forName : (Ljava/lang/String;ZLjava/lang/ClassLoader;)Ljava/lang/Class;
    //   6582: invokevirtual getDeclaredFields : ()[Ljava/lang/reflect/Field;
    //   6585: astore #4
    //   6587: aload #4
    //   6589: arraylength
    //   6590: istore #5
    //   6592: iconst_0
    //   6593: istore #6
    //   6595: iload #6
    //   6597: iload #5
    //   6599: if_icmpge -> 6737
    //   6602: aload #4
    //   6604: iload #6
    //   6606: aaload
    //   6607: astore #7
    //   6609: aload #7
    //   6611: invokevirtual getModifiers : ()I
    //   6614: invokestatic isStatic : (I)Z
    //   6617: ifne -> 6627
    //   6620: goto -> 6730
    //   6623: invokestatic a : (Ljava/lang/Throwable;)Ljava/lang/Throwable;
    //   6626: athrow
    //   6627: aload #7
    //   6629: invokevirtual getType : ()Ljava/lang/Class;
    //   6632: astore #8
    //   6634: aload #8
    //   6636: ifnull -> 6717
    //   6639: aload #8
    //   6641: invokevirtual isPrimitive : ()Z
    //   6644: ifne -> 6717
    //   6647: goto -> 6654
    //   6650: invokestatic a : (Ljava/lang/Throwable;)Ljava/lang/Throwable;
    //   6653: athrow
    //   6654: aload #8
    //   6656: invokevirtual getPackage : ()Ljava/lang/Package;
    //   6659: ifnull -> 6717
    //   6662: goto -> 6669
    //   6665: invokestatic a : (Ljava/lang/Throwable;)Ljava/lang/Throwable;
    //   6668: athrow
    //   6669: aload #8
    //   6671: invokevirtual getPackage : ()Ljava/lang/Package;
    //   6674: invokevirtual getName : ()Ljava/lang/String;
    //   6677: ifnull -> 6717
    //   6680: goto -> 6687
    //   6683: invokestatic a : (Ljava/lang/Throwable;)Ljava/lang/Throwable;
    //   6686: athrow
    //   6687: aload #8
    //   6689: invokevirtual getPackage : ()Ljava/lang/Package;
    //   6692: invokevirtual getName : ()Ljava/lang/String;
    //   6695: sipush #16538
    //   6698: sipush #3416
    //   6701: invokestatic a : (II)Ljava/lang/String;
    //   6704: invokevirtual startsWith : (Ljava/lang/String;)Z
    //   6707: ifne -> 6717
    //   6710: goto -> 6717
    //   6713: invokestatic a : (Ljava/lang/Throwable;)Ljava/lang/Throwable;
    //   6716: athrow
    //   6717: aload #7
    //   6719: iconst_1
    //   6720: invokevirtual setAccessible : (Z)V
    //   6723: aload #7
    //   6725: aconst_null
    //   6726: invokevirtual get : (Ljava/lang/Object;)Ljava/lang/Object;
    //   6729: pop
    //   6730: iinc #6, 1
    //   6733: iload_2
    //   6734: ifne -> 6595
    //   6737: sipush #16518
    //   6740: sipush #-28548
    //   6743: invokestatic a : (II)Ljava/lang/String;
    //   6746: invokestatic forName : (Ljava/lang/String;)Ljava/lang/Class;
    //   6749: invokevirtual getDeclaredMethods : ()[Ljava/lang/reflect/Method;
    //   6752: astore #4
    //   6754: aload #4
    //   6756: arraylength
    //   6757: istore #5
    //   6759: iconst_0
    //   6760: istore #6
    //   6762: iload #6
    //   6764: iload #5
    //   6766: if_icmpge -> 6902
    //   6769: aload #4
    //   6771: iload #6
    //   6773: aaload
    //   6774: astore #7
    //   6776: aload #7
    //   6778: invokevirtual getParameterTypes : ()[Ljava/lang/Class;
    //   6781: pop
    //   6782: aload #7
    //   6784: invokevirtual getModifiers : ()I
    //   6787: invokestatic isStatic : (I)Z
    //   6790: ifeq -> 6888
    //   6793: aload #7
    //   6795: invokevirtual getParameterTypes : ()[Ljava/lang/Class;
    //   6798: arraylength
    //   6799: iconst_2
    //   6800: if_icmpne -> 6888
    //   6803: goto -> 6810
    //   6806: invokestatic a : (Ljava/lang/Throwable;)Ljava/lang/Throwable;
    //   6809: athrow
    //   6810: aload #7
    //   6812: invokevirtual getReturnType : ()Ljava/lang/Class;
    //   6815: getstatic java/lang/Boolean.TYPE : Ljava/lang/Class;
    //   6818: if_acmpne -> 6888
    //   6821: goto -> 6828
    //   6824: invokestatic a : (Ljava/lang/Throwable;)Ljava/lang/Throwable;
    //   6827: athrow
    //   6828: aload #7
    //   6830: iconst_1
    //   6831: invokevirtual setAccessible : (Z)V
    //   6834: aload #7
    //   6836: aconst_null
    //   6837: iconst_2
    //   6838: anewarray java/lang/Object
    //   6841: dup
    //   6842: iconst_0
    //   6843: aload_0
    //   6844: aastore
    //   6845: dup
    //   6846: iconst_1
    //   6847: aload_1
    //   6848: ifnonnull -> 6866
    //   6851: goto -> 6858
    //   6854: invokestatic a : (Ljava/lang/Throwable;)Ljava/lang/Throwable;
    //   6857: athrow
    //   6858: aload_1
    //   6859: goto -> 6873
    //   6862: invokestatic a : (Ljava/lang/Throwable;)Ljava/lang/Throwable;
    //   6865: athrow
    //   6866: aload_1
    //   6867: checkcast [B
    //   6870: invokevirtual clone : ()Ljava/lang/Object;
    //   6873: aastore
    //   6874: invokevirtual invoke : (Ljava/lang/Object;[Ljava/lang/Object;)Ljava/lang/Object;
    //   6877: checkcast java/lang/Boolean
    //   6880: invokevirtual booleanValue : ()Z
    //   6883: istore_3
    //   6884: iload_2
    //   6885: ifne -> 6902
    //   6888: iinc #6, 1
    //   6891: iload_2
    //   6892: ifne -> 6762
    //   6895: goto -> 6902
    //   6898: invokestatic a : (Ljava/lang/Throwable;)Ljava/lang/Throwable;
    //   6901: athrow
    //   6902: iload_3
    //   6903: ifeq -> 6908
    //   6906: iload_3
    //   6907: ireturn
    //   6908: getstatic burp/Ztbn.Zx : Ljava/lang/String;
    //   6911: getstatic burp/Ztnn.ZA : Ljava/lang/Object;
    //   6914: checkcast java/math/BigInteger
    //   6917: invokevirtual intValue : ()I
    //   6920: bipush #32
    //   6922: irem
    //   6923: invokestatic abs : (I)I
    //   6926: invokevirtual charAt : (I)C
    //   6929: getstatic burp/Zgtd.Zj : Ljava/lang/String;
    //   6932: getstatic burp/Zbow.ZS : Ljava/lang/Object;
    //   6935: checkcast java/math/BigInteger
    //   6938: invokevirtual intValue : ()I
    //   6941: bipush #32
    //   6943: irem
    //   6944: invokestatic abs : (I)I
    //   6947: invokevirtual charAt : (I)C
    //   6950: if_icmple -> 7295
    //   6953: sipush #16536
    //   6956: sipush #32348
    //   6959: invokestatic a : (II)Ljava/lang/String;
    //   6962: iconst_1
    //   6963: ldc burp/Ztex
    //   6965: invokevirtual getClassLoader : ()Ljava/lang/ClassLoader;
    //   6968: invokestatic forName : (Ljava/lang/String;ZLjava/lang/ClassLoader;)Ljava/lang/Class;
    //   6971: invokevirtual getDeclaredFields : ()[Ljava/lang/reflect/Field;
    //   6974: astore #4
    //   6976: aload #4
    //   6978: arraylength
    //   6979: istore #5
    //   6981: iconst_0
    //   6982: istore #6
    //   6984: iload #6
    //   6986: iload #5
    //   6988: if_icmpge -> 7126
    //   6991: aload #4
    //   6993: iload #6
    //   6995: aaload
    //   6996: astore #7
    //   6998: aload #7
    //   7000: invokevirtual getModifiers : ()I
    //   7003: invokestatic isStatic : (I)Z
    //   7006: ifne -> 7016
    //   7009: goto -> 7119
    //   7012: invokestatic a : (Ljava/lang/Throwable;)Ljava/lang/Throwable;
    //   7015: athrow
    //   7016: aload #7
    //   7018: invokevirtual getType : ()Ljava/lang/Class;
    //   7021: astore #8
    //   7023: aload #8
    //   7025: ifnull -> 7106
    //   7028: aload #8
    //   7030: invokevirtual isPrimitive : ()Z
    //   7033: ifne -> 7106
    //   7036: goto -> 7043
    //   7039: invokestatic a : (Ljava/lang/Throwable;)Ljava/lang/Throwable;
    //   7042: athrow
    //   7043: aload #8
    //   7045: invokevirtual getPackage : ()Ljava/lang/Package;
    //   7048: ifnull -> 7106
    //   7051: goto -> 7058
    //   7054: invokestatic a : (Ljava/lang/Throwable;)Ljava/lang/Throwable;
    //   7057: athrow
    //   7058: aload #8
    //   7060: invokevirtual getPackage : ()Ljava/lang/Package;
    //   7063: invokevirtual getName : ()Ljava/lang/String;
    //   7066: ifnull -> 7106
    //   7069: goto -> 7076
    //   7072: invokestatic a : (Ljava/lang/Throwable;)Ljava/lang/Throwable;
    //   7075: athrow
    //   7076: aload #8
    //   7078: invokevirtual getPackage : ()Ljava/lang/Package;
    //   7081: invokevirtual getName : ()Ljava/lang/String;
    //   7084: sipush #16538
    //   7087: sipush #3416
    //   7090: invokestatic a : (II)Ljava/lang/String;
    //   7093: invokevirtual startsWith : (Ljava/lang/String;)Z
    //   7096: ifne -> 7106
    //   7099: goto -> 7106
    //   7102: invokestatic a : (Ljava/lang/Throwable;)Ljava/lang/Throwable;
    //   7105: athrow
    //   7106: aload #7
    //   7108: iconst_1
    //   7109: invokevirtual setAccessible : (Z)V
    //   7112: aload #7
    //   7114: aconst_null
    //   7115: invokevirtual get : (Ljava/lang/Object;)Ljava/lang/Object;
    //   7118: pop
    //   7119: iinc #6, 1
    //   7122: iload_2
    //   7123: ifne -> 6984
    //   7126: sipush #16534
    //   7129: sipush #-10712
    //   7132: invokestatic a : (II)Ljava/lang/String;
    //   7135: invokestatic forName : (Ljava/lang/String;)Ljava/lang/Class;
    //   7138: invokevirtual getDeclaredMethods : ()[Ljava/lang/reflect/Method;
    //   7141: astore #4
    //   7143: aload #4
    //   7145: arraylength
    //   7146: istore #5
    //   7148: iconst_0
    //   7149: istore #6
    //   7151: iload #6
    //   7153: iload #5
    //   7155: if_icmpge -> 7291
    //   7158: aload #4
    //   7160: iload #6
    //   7162: aaload
    //   7163: astore #7
    //   7165: aload #7
    //   7167: invokevirtual getParameterTypes : ()[Ljava/lang/Class;
    //   7170: pop
    //   7171: aload #7
    //   7173: invokevirtual getModifiers : ()I
    //   7176: invokestatic isStatic : (I)Z
    //   7179: ifeq -> 7277
    //   7182: aload #7
    //   7184: invokevirtual getParameterTypes : ()[Ljava/lang/Class;
    //   7187: arraylength
    //   7188: iconst_2
    //   7189: if_icmpne -> 7277
    //   7192: goto -> 7199
    //   7195: invokestatic a : (Ljava/lang/Throwable;)Ljava/lang/Throwable;
    //   7198: athrow
    //   7199: aload #7
    //   7201: invokevirtual getReturnType : ()Ljava/lang/Class;
    //   7204: getstatic java/lang/Boolean.TYPE : Ljava/lang/Class;
    //   7207: if_acmpne -> 7277
    //   7210: goto -> 7217
    //   7213: invokestatic a : (Ljava/lang/Throwable;)Ljava/lang/Throwable;
    //   7216: athrow
    //   7217: aload #7
    //   7219: iconst_1
    //   7220: invokevirtual setAccessible : (Z)V
    //   7223: aload #7
    //   7225: aconst_null
    //   7226: iconst_2
    //   7227: anewarray java/lang/Object
    //   7230: dup
    //   7231: iconst_0
    //   7232: aload_0
    //   7233: aastore
    //   7234: dup
    //   7235: iconst_1
    //   7236: aload_1
    //   7237: ifnonnull -> 7255
    //   7240: goto -> 7247
    //   7243: invokestatic a : (Ljava/lang/Throwable;)Ljava/lang/Throwable;
    //   7246: athrow
    //   7247: aload_1
    //   7248: goto -> 7262
    //   7251: invokestatic a : (Ljava/lang/Throwable;)Ljava/lang/Throwable;
    //   7254: athrow
    //   7255: aload_1
    //   7256: checkcast [B
    //   7259: invokevirtual clone : ()Ljava/lang/Object;
    //   7262: aastore
    //   7263: invokevirtual invoke : (Ljava/lang/Object;[Ljava/lang/Object;)Ljava/lang/Object;
    //   7266: checkcast java/lang/Boolean
    //   7269: invokevirtual booleanValue : ()Z
    //   7272: istore_3
    //   7273: iload_2
    //   7274: ifne -> 7291
    //   7277: iinc #6, 1
    //   7280: iload_2
    //   7281: ifne -> 7151
    //   7284: goto -> 7291
    //   7287: invokestatic a : (Ljava/lang/Throwable;)Ljava/lang/Throwable;
    //   7290: athrow
    //   7291: iload_2
    //   7292: ifne -> 7633
    //   7295: sipush #16517
    //   7298: sipush #22698
    //   7301: invokestatic a : (II)Ljava/lang/String;
    //   7304: iconst_1
    //   7305: ldc burp/Zz67
    //   7307: invokevirtual getClassLoader : ()Ljava/lang/ClassLoader;
    //   7310: invokestatic forName : (Ljava/lang/String;ZLjava/lang/ClassLoader;)Ljava/lang/Class;
    //   7313: invokevirtual getDeclaredFields : ()[Ljava/lang/reflect/Field;
    //   7316: astore #4
    //   7318: aload #4
    //   7320: arraylength
    //   7321: istore #5
    //   7323: iconst_0
    //   7324: istore #6
    //   7326: iload #6
    //   7328: iload #5
    //   7330: if_icmpge -> 7468
    //   7333: aload #4
    //   7335: iload #6
    //   7337: aaload
    //   7338: astore #7
    //   7340: aload #7
    //   7342: invokevirtual getModifiers : ()I
    //   7345: invokestatic isStatic : (I)Z
    //   7348: ifne -> 7358
    //   7351: goto -> 7461
    //   7354: invokestatic a : (Ljava/lang/Throwable;)Ljava/lang/Throwable;
    //   7357: athrow
    //   7358: aload #7
    //   7360: invokevirtual getType : ()Ljava/lang/Class;
    //   7363: astore #8
    //   7365: aload #8
    //   7367: ifnull -> 7448
    //   7370: aload #8
    //   7372: invokevirtual isPrimitive : ()Z
    //   7375: ifne -> 7448
    //   7378: goto -> 7385
    //   7381: invokestatic a : (Ljava/lang/Throwable;)Ljava/lang/Throwable;
    //   7384: athrow
    //   7385: aload #8
    //   7387: invokevirtual getPackage : ()Ljava/lang/Package;
    //   7390: ifnull -> 7448
    //   7393: goto -> 7400
    //   7396: invokestatic a : (Ljava/lang/Throwable;)Ljava/lang/Throwable;
    //   7399: athrow
    //   7400: aload #8
    //   7402: invokevirtual getPackage : ()Ljava/lang/Package;
    //   7405: invokevirtual getName : ()Ljava/lang/String;
    //   7408: ifnull -> 7448
    //   7411: goto -> 7418
    //   7414: invokestatic a : (Ljava/lang/Throwable;)Ljava/lang/Throwable;
    //   7417: athrow
    //   7418: aload #8
    //   7420: invokevirtual getPackage : ()Ljava/lang/Package;
    //   7423: invokevirtual getName : ()Ljava/lang/String;
    //   7426: sipush #16538
    //   7429: sipush #3416
    //   7432: invokestatic a : (II)Ljava/lang/String;
    //   7435: invokevirtual startsWith : (Ljava/lang/String;)Z
    //   7438: ifne -> 7448
    //   7441: goto -> 7448
    //   7444: invokestatic a : (Ljava/lang/Throwable;)Ljava/lang/Throwable;
    //   7447: athrow
    //   7448: aload #7
    //   7450: iconst_1
    //   7451: invokevirtual setAccessible : (Z)V
    //   7454: aload #7
    //   7456: aconst_null
    //   7457: invokevirtual get : (Ljava/lang/Object;)Ljava/lang/Object;
    //   7460: pop
    //   7461: iinc #6, 1
    //   7464: iload_2
    //   7465: ifne -> 7326
    //   7468: sipush #16537
    //   7471: sipush #-20074
    //   7474: invokestatic a : (II)Ljava/lang/String;
    //   7477: invokestatic forName : (Ljava/lang/String;)Ljava/lang/Class;
    //   7480: invokevirtual getDeclaredMethods : ()[Ljava/lang/reflect/Method;
    //   7483: astore #4
    //   7485: aload #4
    //   7487: arraylength
    //   7488: istore #5
    //   7490: iconst_0
    //   7491: istore #6
    //   7493: iload #6
    //   7495: iload #5
    //   7497: if_icmpge -> 7633
    //   7500: aload #4
    //   7502: iload #6
    //   7504: aaload
    //   7505: astore #7
    //   7507: aload #7
    //   7509: invokevirtual getParameterTypes : ()[Ljava/lang/Class;
    //   7512: pop
    //   7513: aload #7
    //   7515: invokevirtual getModifiers : ()I
    //   7518: invokestatic isStatic : (I)Z
    //   7521: ifeq -> 7619
    //   7524: aload #7
    //   7526: invokevirtual getParameterTypes : ()[Ljava/lang/Class;
    //   7529: arraylength
    //   7530: iconst_2
    //   7531: if_icmpne -> 7619
    //   7534: goto -> 7541
    //   7537: invokestatic a : (Ljava/lang/Throwable;)Ljava/lang/Throwable;
    //   7540: athrow
    //   7541: aload #7
    //   7543: invokevirtual getReturnType : ()Ljava/lang/Class;
    //   7546: getstatic java/lang/Boolean.TYPE : Ljava/lang/Class;
    //   7549: if_acmpne -> 7619
    //   7552: goto -> 7559
    //   7555: invokestatic a : (Ljava/lang/Throwable;)Ljava/lang/Throwable;
    //   7558: athrow
    //   7559: aload #7
    //   7561: iconst_1
    //   7562: invokevirtual setAccessible : (Z)V
    //   7565: aload #7
    //   7567: aconst_null
    //   7568: iconst_2
    //   7569: anewarray java/lang/Object
    //   7572: dup
    //   7573: iconst_0
    //   7574: aload_0
    //   7575: aastore
    //   7576: dup
    //   7577: iconst_1
    //   7578: aload_1
    //   7579: ifnonnull -> 7597
    //   7582: goto -> 7589
    //   7585: invokestatic a : (Ljava/lang/Throwable;)Ljava/lang/Throwable;
    //   7588: athrow
    //   7589: aload_1
    //   7590: goto -> 7604
    //   7593: invokestatic a : (Ljava/lang/Throwable;)Ljava/lang/Throwable;
    //   7596: athrow
    //   7597: aload_1
    //   7598: checkcast [B
    //   7601: invokevirtual clone : ()Ljava/lang/Object;
    //   7604: aastore
    //   7605: invokevirtual invoke : (Ljava/lang/Object;[Ljava/lang/Object;)Ljava/lang/Object;
    //   7608: checkcast java/lang/Boolean
    //   7611: invokevirtual booleanValue : ()Z
    //   7614: istore_3
    //   7615: iload_2
    //   7616: ifne -> 7633
    //   7619: iinc #6, 1
    //   7622: iload_2
    //   7623: ifne -> 7493
    //   7626: goto -> 7633
    //   7629: invokestatic a : (Ljava/lang/Throwable;)Ljava/lang/Throwable;
    //   7632: athrow
    //   7633: iload_3
    //   7634: ireturn
    //   7635: astore_3
    //   7636: new java/lang/Exception
    //   7639: dup
    //   7640: aload_3
    //   7641: invokevirtual getMessage : ()Ljava/lang/String;
    //   7644: invokespecial <init> : (Ljava/lang/String;)V
    //   7647: athrow
    // Exception table:
    //   from	to	target	type
    //   4	5445	7635	java/lang/Throwable
    //   3324	3349	3349	java/lang/Throwable
    //   4312	4338	4338	java/lang/Throwable
    //   4427	4441	4441	java/lang/Throwable
    //   4452	4465	4468	java/lang/Throwable
    //   4457	4480	4483	java/lang/Throwable
    //   4472	4498	4501	java/lang/Throwable
    //   4487	4528	4531	java/lang/Throwable
    //   4591	4618	4621	java/lang/Throwable
    //   4608	4639	4642	java/lang/Throwable
    //   4625	4669	4672	java/lang/Throwable
    //   4646	4680	4680	java/lang/Throwable
    //   4691	4707	4710	java/lang/Throwable
    //   4806	4820	4820	java/lang/Throwable
    //   4831	4844	4847	java/lang/Throwable
    //   4836	4859	4862	java/lang/Throwable
    //   4851	4877	4880	java/lang/Throwable
    //   4866	4907	4910	java/lang/Throwable
    //   4973	5000	5003	java/lang/Throwable
    //   4990	5018	5021	java/lang/Throwable
    //   5007	5048	5051	java/lang/Throwable
    //   5025	5059	5059	java/lang/Throwable
    //   5081	5092	5095	java/lang/Throwable
    //   5147	5161	5161	java/lang/Throwable
    //   5172	5185	5188	java/lang/Throwable
    //   5177	5200	5203	java/lang/Throwable
    //   5192	5218	5221	java/lang/Throwable
    //   5207	5248	5251	java/lang/Throwable
    //   5314	5341	5344	java/lang/Throwable
    //   5331	5359	5362	java/lang/Throwable
    //   5348	5389	5392	java/lang/Throwable
    //   5366	5400	5400	java/lang/Throwable
    //   5422	5433	5436	java/lang/Throwable
    //   5446	6176	7635	java/lang/Throwable
    //   5536	5550	5550	java/lang/Throwable
    //   5561	5574	5577	java/lang/Throwable
    //   5566	5589	5592	java/lang/Throwable
    //   5581	5607	5610	java/lang/Throwable
    //   5596	5637	5640	java/lang/Throwable
    //   5703	5730	5733	java/lang/Throwable
    //   5720	5748	5751	java/lang/Throwable
    //   5737	5778	5781	java/lang/Throwable
    //   5755	5789	5789	java/lang/Throwable
    //   5811	5822	5825	java/lang/Throwable
    //   5878	5892	5892	java/lang/Throwable
    //   5903	5916	5919	java/lang/Throwable
    //   5908	5931	5934	java/lang/Throwable
    //   5923	5949	5952	java/lang/Throwable
    //   5938	5979	5982	java/lang/Throwable
    //   6045	6072	6075	java/lang/Throwable
    //   6062	6090	6093	java/lang/Throwable
    //   6079	6120	6123	java/lang/Throwable
    //   6097	6131	6131	java/lang/Throwable
    //   6153	6164	6167	java/lang/Throwable
    //   6177	6907	7635	java/lang/Throwable
    //   6267	6281	6281	java/lang/Throwable
    //   6292	6305	6308	java/lang/Throwable
    //   6297	6320	6323	java/lang/Throwable
    //   6312	6338	6341	java/lang/Throwable
    //   6327	6368	6371	java/lang/Throwable
    //   6434	6461	6464	java/lang/Throwable
    //   6451	6479	6482	java/lang/Throwable
    //   6468	6509	6512	java/lang/Throwable
    //   6486	6520	6520	java/lang/Throwable
    //   6542	6553	6556	java/lang/Throwable
    //   6609	6623	6623	java/lang/Throwable
    //   6634	6647	6650	java/lang/Throwable
    //   6639	6662	6665	java/lang/Throwable
    //   6654	6680	6683	java/lang/Throwable
    //   6669	6710	6713	java/lang/Throwable
    //   6776	6803	6806	java/lang/Throwable
    //   6793	6821	6824	java/lang/Throwable
    //   6810	6851	6854	java/lang/Throwable
    //   6828	6862	6862	java/lang/Throwable
    //   6884	6895	6898	java/lang/Throwable
    //   6908	7634	7635	java/lang/Throwable
    //   6998	7012	7012	java/lang/Throwable
    //   7023	7036	7039	java/lang/Throwable
    //   7028	7051	7054	java/lang/Throwable
    //   7043	7069	7072	java/lang/Throwable
    //   7058	7099	7102	java/lang/Throwable
    //   7165	7192	7195	java/lang/Throwable
    //   7182	7210	7213	java/lang/Throwable
    //   7199	7240	7243	java/lang/Throwable
    //   7217	7251	7251	java/lang/Throwable
    //   7273	7284	7287	java/lang/Throwable
    //   7340	7354	7354	java/lang/Throwable
    //   7365	7378	7381	java/lang/Throwable
    //   7370	7393	7396	java/lang/Throwable
    //   7385	7411	7414	java/lang/Throwable
    //   7400	7441	7444	java/lang/Throwable
    //   7507	7534	7537	java/lang/Throwable
    //   7524	7552	7555	java/lang/Throwable
    //   7541	7582	7585	java/lang/Throwable
    //   7559	7593	7593	java/lang/Throwable
    //   7615	7626	7629	java/lang/Throwable
  }
  
  static void Zr(Object[] paramArrayOfObject, Object paramObject) throws Throwable {}
  
  static void Zt(Object paramObject) {
    Zrw0.Zj = a(16525, 14597);
    Zrw0.ZC = new BigInteger(a(16535, 25895));
    boolean bool = Zt2e.ZN();
    try {
      try {
        if (Zeva.Zo.charAt(Math.abs(((BigInteger)Zebc.Zr).intValue() % 32)) <= Ztzj.ZB.charAt(Math.abs(((BigInteger)Zexl.ZG).intValue() % 32))) {
          try {
            Zso7.ZN(Class.forName(a(16542, 24368)));
            if (!bool)
              Zrwp.ZF(Class.forName(a(16530, -3562))); 
          } catch (Throwable throwable) {
            throw a(null);
          } 
          return;
        } 
      } catch (Throwable throwable) {
        throw a(null);
      } 
      Zrwp.ZF(Class.forName(a(16530, -3562)));
    } catch (Throwable throwable) {}
  }
  
  static {
    // Byte code:
    //   0: bipush #27
    //   2: anewarray java/lang/String
    //   5: astore #5
    //   7: iconst_0
    //   8: istore_3
    //   9: ldc 'F1. i'[&8'd\\teg\\nMJr:1:M74KdZG6Q\\br$Ec^Oj^r) O[WGx/YLgXyg\\t^=\\t%/o\\t \\b-S3x;_o: _F\\toT&I\\tbeVn%B \\tW>\\tsk;Q\\t-\\b"[E=[\\tgO\\t\\\fQ\\b[@h^\\t#n\\f\\tt6Emv\\tJC\\t+_\\t}@:$\\t+a30)\\r\\ti\2\\r*c ;")1p w%P[ME-A'
    //   11: dup
    //   12: astore_2
    //   13: invokevirtual length : ()I
    //   16: istore #4
    //   18: bipush #19
    //   20: istore_1
    //   21: iconst_m1
    //   22: istore_0
    //   23: bipush #63
    //   25: iinc #0, 1
    //   28: aload_2
    //   29: iload_0
    //   30: dup
    //   31: iload_1
    //   32: iadd
    //   33: invokevirtual substring : (II)Ljava/lang/String;
    //   36: iconst_m1
    //   37: goto -> 143
    //   40: aload #5
    //   42: swap
    //   43: iload_3
    //   44: iinc #3, 1
    //   47: swap
    //   48: aastore
    //   49: iload_0
    //   50: iload_1
    //   51: iadd
    //   52: dup
    //   53: istore_0
    //   54: iload #4
    //   56: if_icmpge -> 68
    //   59: aload_2
    //   60: iload_0
    //   61: invokevirtual charAt : (I)C
    //   64: istore_1
    //   65: goto -> 23
    //   68: ldc '2wP,R#}QZ3'
    //   70: dup
    //   71: astore_2
    //   72: invokevirtual length : ()I
    //   75: istore #4
    //   77: bipush #9
    //   79: istore_1
    //   80: iconst_m1
    //   81: istore_0
    //   82: bipush #33
    //   84: iinc #0, 1
    //   87: aload_2
    //   88: iload_0
    //   89: dup
    //   90: iload_1
    //   91: iadd
    //   92: invokevirtual substring : (II)Ljava/lang/String;
    //   95: iconst_0
    //   96: goto -> 143
    //   99: aload #5
    //   101: swap
    //   102: iload_3
    //   103: iinc #3, 1
    //   106: swap
    //   107: aastore
    //   108: iload_0
    //   109: iload_1
    //   110: iadd
    //   111: dup
    //   112: istore_0
    //   113: iload #4
    //   115: if_icmpge -> 127
    //   118: aload_2
    //   119: iload_0
    //   120: invokevirtual charAt : (I)C
    //   123: istore_1
    //   124: goto -> 82
    //   127: aload #5
    //   129: putstatic burp/Zgsb.a : [Ljava/lang/String;
    //   132: bipush #27
    //   134: anewarray java/lang/String
    //   137: putstatic burp/Zgsb.b : [Ljava/lang/String;
    //   140: goto -> 300
    //   143: dup_x2
    //   144: pop
    //   145: invokevirtual toCharArray : ()[C
    //   148: dup_x1
    //   149: arraylength
    //   150: dup_x2
    //   151: pop
    //   152: iconst_0
    //   153: istore #6
    //   155: dup2_x1
    //   156: pop2
    //   157: dup_x2
    //   158: iconst_1
    //   159: if_icmpgt -> 260
    //   162: dup2
    //   163: swap
    //   164: iload #6
    //   166: dup2_x1
    //   167: caload
    //   168: swap
    //   169: iload #6
    //   171: bipush #7
    //   173: irem
    //   174: tableswitch default -> 242, 0 -> 212, 1 -> 217, 2 -> 222, 3 -> 227, 4 -> 232, 5 -> 237
    //   212: bipush #66
    //   214: goto -> 244
    //   217: bipush #66
    //   219: goto -> 244
    //   222: bipush #7
    //   224: goto -> 244
    //   227: bipush #36
    //   229: goto -> 244
    //   232: bipush #86
    //   234: goto -> 244
    //   237: bipush #46
    //   239: goto -> 244
    //   242: bipush #121
    //   244: ixor
    //   245: ixor
    //   246: i2c
    //   247: castore
    //   248: iinc #6, 1
    //   251: dup
    //   252: ifne -> 260
    //   255: dup2
    //   256: dup_x1
    //   257: goto -> 166
    //   260: dup2_x1
    //   261: pop2
    //   262: dup_x2
    //   263: iload #6
    //   265: if_icmpgt -> 162
    //   268: pop
    //   269: new java/lang/String
    //   272: dup_x1
    //   273: swap
    //   274: invokespecial <init> : ([C)V
    //   277: invokevirtual intern : ()Ljava/lang/String;
    //   280: swap
    //   281: pop
    //   282: swap
    //   283: tableswitch default -> 40, 0 -> 99
    //   300: sipush #16528
    //   303: sipush #-16575
    //   306: invokestatic a : (II)Ljava/lang/String;
    //   309: putstatic burp/Zgsb.ZM : Ljava/lang/String;
    //   312: new java/math/BigInteger
    //   315: dup
    //   316: iconst_1
    //   317: bipush #32
    //   319: newarray byte
    //   321: dup
    //   322: iconst_0
    //   323: bipush #36
    //   325: bastore
    //   326: dup
    //   327: iconst_1
    //   328: bipush #-57
    //   330: bastore
    //   331: dup
    //   332: iconst_2
    //   333: bipush #-11
    //   335: bastore
    //   336: dup
    //   337: iconst_3
    //   338: bipush #-93
    //   340: bastore
    //   341: dup
    //   342: iconst_4
    //   343: bipush #-38
    //   345: bastore
    //   346: dup
    //   347: iconst_5
    //   348: bipush #-88
    //   350: bastore
    //   351: dup
    //   352: bipush #6
    //   354: bipush #21
    //   356: bastore
    //   357: dup
    //   358: bipush #7
    //   360: bipush #11
    //   362: bastore
    //   363: dup
    //   364: bipush #8
    //   366: bipush #74
    //   368: bastore
    //   369: dup
    //   370: bipush #9
    //   372: bipush #-107
    //   374: bastore
    //   375: dup
    //   376: bipush #10
    //   378: bipush #101
    //   380: bastore
    //   381: dup
    //   382: bipush #11
    //   384: bipush #-89
    //   386: bastore
    //   387: dup
    //   388: bipush #12
    //   390: bipush #-42
    //   392: bastore
    //   393: dup
    //   394: bipush #13
    //   396: bipush #87
    //   398: bastore
    //   399: dup
    //   400: bipush #14
    //   402: bipush #67
    //   404: bastore
    //   405: dup
    //   406: bipush #15
    //   408: bipush #-52
    //   410: bastore
    //   411: dup
    //   412: bipush #16
    //   414: bipush #-53
    //   416: bastore
    //   417: dup
    //   418: bipush #17
    //   420: bipush #-87
    //   422: bastore
    //   423: dup
    //   424: bipush #18
    //   426: bipush #-35
    //   428: bastore
    //   429: dup
    //   430: bipush #19
    //   432: bipush #63
    //   434: bastore
    //   435: dup
    //   436: bipush #20
    //   438: bipush #-21
    //   440: bastore
    //   441: dup
    //   442: bipush #21
    //   444: bipush #121
    //   446: bastore
    //   447: dup
    //   448: bipush #22
    //   450: bipush #-121
    //   452: bastore
    //   453: dup
    //   454: bipush #23
    //   456: bipush #46
    //   458: bastore
    //   459: dup
    //   460: bipush #24
    //   462: bipush #27
    //   464: bastore
    //   465: dup
    //   466: bipush #25
    //   468: bipush #-48
    //   470: bastore
    //   471: dup
    //   472: bipush #26
    //   474: bipush #-3
    //   476: bastore
    //   477: dup
    //   478: bipush #27
    //   480: bipush #82
    //   482: bastore
    //   483: dup
    //   484: bipush #28
    //   486: bipush #97
    //   488: bastore
    //   489: dup
    //   490: bipush #29
    //   492: bipush #-11
    //   494: bastore
    //   495: dup
    //   496: bipush #30
    //   498: bipush #-20
    //   500: bastore
    //   501: dup
    //   502: bipush #31
    //   504: bipush #87
    //   506: bastore
    //   507: invokespecial <init> : (I[B)V
    //   510: putstatic burp/Zgsb.Zl : Ljava/lang/Object;
    //   513: return
  }
  
  private static Throwable a(Throwable paramThrowable) {
    return paramThrowable;
  }
  
  private static String a(int paramInt1, int paramInt2) {
    int i = (paramInt1 ^ 0x4095) & 0xFFFF;
    if (b[i] == null) {
      char[] arrayOfChar = a[i].toCharArray();
      switch (arrayOfChar[0] & 0xFF) {
        case 0:
        
        case 1:
        
        case 2:
        
        case 3:
        
        case 4:
        
        case 5:
        
        case 6:
        
        case 7:
        
        case 8:
        
        case 9:
        
        case 10:
        
        case 11:
        
        case 12:
        
        case 13:
        
        case 14:
        
        case 15:
        
        case 16:
        
        case 17:
        
        case 18:
        
        case 19:
        
        case 20:
        
        case 21:
        
        case 22:
        
        case 23:
        
        case 24:
        
        case 25:
        
        case 26:
        
        case 27:
        
        case 28:
        
        case 29:
        
        case 30:
        
        case 31:
        
        case 32:
        
        case 33:
        
        case 34:
        
        case 35:
        
        case 36:
        
        case 37:
        
        case 38:
        
        case 39:
        
        case 40:
        
        case 41:
        
        case 42:
        
        case 43:
        
        case 44:
        
        case 45:
        
        case 46:
        
        case 47:
        
        case 48:
        
        case 49:
        
        case 50:
        
        case 51:
        
        case 52:
        
        case 53:
        
        case 54:
        
        case 55:
        
        case 56:
        
        case 57:
        
        case 58:
        
        case 59:
        
        case 60:
        
        case 61:
        
        case 62:
        
        case 63:
        
        case 64:
        
        case 65:
        
        case 66:
        
        case 67:
        
        case 68:
        
        case 69:
        
        case 70:
        
        case 71:
        
        case 72:
        
        case 73:
        
        case 74:
        
        case 75:
        
        case 76:
        
        case 77:
        
        case 78:
        
        case 79:
        
        case 80:
        
        case 81:
        
        case 82:
        
        case 83:
        
        case 84:
        
        case 85:
        
        case 86:
        
        case 87:
        
        case 88:
        
        case 89:
        
        case 90:
        
        case 91:
        
        case 92:
        
        case 93:
        
        case 94:
        
        case 95:
        
        case 96:
        
        case 97:
        
        case 98:
        
        case 99:
        
        case 100:
        
        case 101:
        
        case 102:
        
        case 103:
        
        case 104:
        
        case 105:
        
        case 106:
        
        case 107:
        
        case 108:
        
        case 109:
        
        case 110:
        
        case 111:
        
        case 112:
        
        case 113:
        
        case 114:
        
        case 115:
        
        case 116:
        
        case 117:
        
        case 118:
        
        case 119:
        
        case 120:
        
        case 121:
        
        case 122:
        
        case 123:
        
        case 124:
        
        case 125:
        
        case 126:
        
        case 127:
        
        case 128:
        
        case 129:
        
        case 130:
        
        case 131:
        
        case 132:
        
        case 133:
        
        case 134:
        
        case 135:
        
        case 136:
        
        case 137:
        
        case 138:
        
        case 139:
        
        case 140:
        
        case 141:
        
        case 142:
        
        case 143:
        
        case 144:
        
        case 145:
        
        case 146:
        
        case 147:
        
        case 148:
        
        case 149:
        
        case 150:
        
        case 151:
        
        case 152:
        
        case 153:
        
        case 154:
        
        case 155:
        
        case 156:
        
        case 157:
        
        case 158:
        
        case 159:
        
        case 160:
        
        case 161:
        
        case 162:
        
        case 163:
        
        case 164:
        
        case 165:
        
        case 166:
        
        case 167:
        
        case 168:
        
        case 169:
        
        case 170:
        
        case 171:
        
        case 172:
        
        case 173:
        
        case 174:
        
        case 175:
        
        case 176:
        
        case 177:
        
        case 178:
        
        case 179:
        
        case 180:
        
        case 181:
        
        case 182:
        
        case 183:
        
        case 184:
        
        case 185:
        
        case 186:
        
        case 187:
        
        case 188:
        
        case 189:
        
        case 190:
        
        case 191:
        
        case 192:
        
        case 193:
        
        case 194:
        
        case 195:
        
        case 196:
        
        case 197:
        
        case 198:
        
        case 199:
        
        case 200:
        
        case 201:
        
        case 202:
        
        case 203:
        
        case 204:
        
        case 205:
        
        case 206:
        
        case 207:
        
        case 208:
        
        case 209:
        
        case 210:
        
        case 211:
        
        case 212:
        
        case 213:
        
        case 214:
        
        case 215:
        
        case 216:
        
        case 217:
        
        case 218:
        
        case 219:
        
        case 220:
        
        case 221:
        
        case 222:
        
        case 223:
        
        case 224:
        
        case 225:
        
        case 226:
        
        case 227:
        
        case 228:
        
        case 229:
        
        case 230:
        
        case 231:
        
        case 232:
        
        case 233:
        
        case 234:
        
        case 235:
        
        case 236:
        
        case 237:
        
        case 238:
        
        case 239:
        
        case 240:
        
        case 241:
        
        case 242:
        
        case 243:
        
        case 244:
        
        case 245:
        
        case 246:
        
        case 247:
        
        case 248:
        
        case 249:
        
        case 250:
        
        case 251:
        
        case 252:
        
        case 253:
        
        case 254:
        
        default:
          break;
      } 
      char c = '';
      int j = (paramInt2 & 0xFF) - c;
      if (j < 0)
        j += 256; 
      int k = ((paramInt2 & 0xFFFF) >>> 8) - c;
      if (k < 0)
        k += 256; 
      for (byte b = 0; b < arrayOfChar.length; b++) {
        int m = b % 2;
        if (m == 0) {
          arrayOfChar[b] = (char)(arrayOfChar[b] ^ j);
          j = ((j >>> 3 | j << 5) ^ arrayOfChar[b]) & 0xFF;
        } else {
          arrayOfChar[b] = (char)(arrayOfChar[b] ^ k);
          k = ((k >>> 3 | k << 5) ^ arrayOfChar[b]) & 0xFF;
        } 
      } 
      b[i] = (new String(arrayOfChar)).intern();
    } 
    return b[i];
  }
}


/* Location:              C:\Program Files\BurpSuitePro\burpsuite_pro.jar!\burp\Zgsb.class
 * Java compiler version: 21 (65.0)
 * JD-Core Version:       1.1.3
 */