package burp;

import java.math.BigInteger;

class Zgsk extends ClassLoader {
  static String Zk;
  
  static Object Zh;
  
  private static final String[] a;
  
  private static final String[] b;
  
  static void Ze(Object paramObject) {
    Zlcc.Zw = a(-28072, -14319);
    Zlcc.ZP = new BigInteger(new byte[] { 
          111, -81, 60, 107, -6, -5, 118, 58, 2, 49, 
          93, 106, 10, -55, -64, 14, 60, -44, 80, -108, 
          -59, 19, -127, 36, 12, 104, -38, -85, 103, 56, 
          88, -86 });
    boolean bool = Zt2e.ZK();
    try {
      try {
        if (Zkor.Za.charAt(Math.abs(((BigInteger)Zdk.Zy).intValue() % 32)) <= Zb9q.Zk.charAt(Math.abs(((BigInteger)Zstf.ZA).intValue() % 32))) {
          try {
            Zlxm.ZY(Class.forName(a(-28067, 16284)));
            if (bool)
              Zk5y.ZO(Class.forName(a(-28066, 4262))); 
          } catch (Throwable throwable) {
            throw a(null);
          } 
          return;
        } 
      } catch (Throwable throwable) {
        throw a(null);
      } 
      Zk5y.ZO(Class.forName(a(-28066, 4262)));
    } catch (Throwable throwable) {}
  }
  
  static void Zh(Object[] paramArrayOfObject, Object paramObject) throws Throwable {}
  
  static boolean Zs(Object[] paramArrayOfObject, Object paramObject) throws Throwable {
    // Byte code:
    //   0: invokestatic ZK : ()Z
    //   3: istore_2
    //   4: new java/lang/StringBuilder
    //   7: dup
    //   8: invokespecial <init> : ()V
    //   11: astore_3
    //   12: iconst_0
    //   13: istore #4
    //   15: iload #4
    //   17: bipush #32
    //   19: if_icmpge -> 1355
    //   22: iload #4
    //   24: tableswitch default -> 1348, 0 -> 168, 1 -> 205, 2 -> 242, 3 -> 279, 4 -> 316, 5 -> 353, 6 -> 390, 7 -> 427, 8 -> 464, 9 -> 501, 10 -> 538, 11 -> 575, 12 -> 612, 13 -> 649, 14 -> 686, 15 -> 723, 16 -> 760, 17 -> 797, 18 -> 834, 19 -> 871, 20 -> 908, 21 -> 945, 22 -> 982, 23 -> 1019, 24 -> 1056, 25 -> 1093, 26 -> 1130, 27 -> 1167, 28 -> 1204, 29 -> 1241, 30 -> 1278, 31 -> 1315
    //   168: aload_3
    //   169: getstatic burp/Ztq8.ZI : Ljava/lang/String;
    //   172: getstatic burp/Zrwp.Zk : Ljava/lang/Object;
    //   175: checkcast java/math/BigInteger
    //   178: invokevirtual intValue : ()I
    //   181: bipush #32
    //   183: irem
    //   184: invokestatic abs : (I)I
    //   187: invokevirtual charAt : (I)C
    //   190: invokevirtual append : (C)Ljava/lang/StringBuilder;
    //   193: pop
    //   194: iload_2
    //   195: ifeq -> 1348
    //   198: goto -> 205
    //   201: invokestatic a : (Ljava/lang/Throwable;)Ljava/lang/Throwable;
    //   204: athrow
    //   205: aload_3
    //   206: getstatic burp/Zr9u.Zc : Ljava/lang/String;
    //   209: getstatic burp/Zbwj.ZW : Ljava/lang/Object;
    //   212: checkcast java/math/BigInteger
    //   215: invokevirtual intValue : ()I
    //   218: bipush #32
    //   220: irem
    //   221: invokestatic abs : (I)I
    //   224: invokevirtual charAt : (I)C
    //   227: invokevirtual append : (C)Ljava/lang/StringBuilder;
    //   230: pop
    //   231: iload_2
    //   232: ifeq -> 1348
    //   235: goto -> 242
    //   238: invokestatic a : (Ljava/lang/Throwable;)Ljava/lang/Throwable;
    //   241: athrow
    //   242: aload_3
    //   243: getstatic burp/Ztl6.Zb : Ljava/lang/String;
    //   246: getstatic burp/Zl2t.ZS : Ljava/lang/Object;
    //   249: checkcast java/math/BigInteger
    //   252: invokevirtual intValue : ()I
    //   255: bipush #32
    //   257: irem
    //   258: invokestatic abs : (I)I
    //   261: invokevirtual charAt : (I)C
    //   264: invokevirtual append : (C)Ljava/lang/StringBuilder;
    //   267: pop
    //   268: iload_2
    //   269: ifeq -> 1348
    //   272: goto -> 279
    //   275: invokestatic a : (Ljava/lang/Throwable;)Ljava/lang/Throwable;
    //   278: athrow
    //   279: aload_3
    //   280: getstatic burp/Zr14.ZL : Ljava/lang/String;
    //   283: getstatic burp/Zek4.ZR : Ljava/lang/Object;
    //   286: checkcast java/math/BigInteger
    //   289: invokevirtual intValue : ()I
    //   292: bipush #32
    //   294: irem
    //   295: invokestatic abs : (I)I
    //   298: invokevirtual charAt : (I)C
    //   301: invokevirtual append : (C)Ljava/lang/StringBuilder;
    //   304: pop
    //   305: iload_2
    //   306: ifeq -> 1348
    //   309: goto -> 316
    //   312: invokestatic a : (Ljava/lang/Throwable;)Ljava/lang/Throwable;
    //   315: athrow
    //   316: aload_3
    //   317: getstatic burp/Zgsb.ZM : Ljava/lang/String;
    //   320: getstatic burp/Zejz.ZF : Ljava/lang/Object;
    //   323: checkcast java/math/BigInteger
    //   326: invokevirtual intValue : ()I
    //   329: bipush #32
    //   331: irem
    //   332: invokestatic abs : (I)I
    //   335: invokevirtual charAt : (I)C
    //   338: invokevirtual append : (C)Ljava/lang/StringBuilder;
    //   341: pop
    //   342: iload_2
    //   343: ifeq -> 1348
    //   346: goto -> 353
    //   349: invokestatic a : (Ljava/lang/Throwable;)Ljava/lang/Throwable;
    //   352: athrow
    //   353: aload_3
    //   354: getstatic burp/Zzht.Zv : Ljava/lang/String;
    //   357: getstatic burp/Zg4z.ZB : Ljava/lang/Object;
    //   360: checkcast java/math/BigInteger
    //   363: invokevirtual intValue : ()I
    //   366: bipush #32
    //   368: irem
    //   369: invokestatic abs : (I)I
    //   372: invokevirtual charAt : (I)C
    //   375: invokevirtual append : (C)Ljava/lang/StringBuilder;
    //   378: pop
    //   379: iload_2
    //   380: ifeq -> 1348
    //   383: goto -> 390
    //   386: invokestatic a : (Ljava/lang/Throwable;)Ljava/lang/Throwable;
    //   389: athrow
    //   390: aload_3
    //   391: getstatic burp/Zepy.Zg : Ljava/lang/String;
    //   394: getstatic burp/Zer1.ZL : Ljava/lang/Object;
    //   397: checkcast java/math/BigInteger
    //   400: invokevirtual intValue : ()I
    //   403: bipush #32
    //   405: irem
    //   406: invokestatic abs : (I)I
    //   409: invokevirtual charAt : (I)C
    //   412: invokevirtual append : (C)Ljava/lang/StringBuilder;
    //   415: pop
    //   416: iload_2
    //   417: ifeq -> 1348
    //   420: goto -> 427
    //   423: invokestatic a : (Ljava/lang/Throwable;)Ljava/lang/Throwable;
    //   426: athrow
    //   427: aload_3
    //   428: getstatic burp/Zlbd.Zq : Ljava/lang/String;
    //   431: getstatic burp/Zlid.Zx : Ljava/lang/Object;
    //   434: checkcast java/math/BigInteger
    //   437: invokevirtual intValue : ()I
    //   440: bipush #32
    //   442: irem
    //   443: invokestatic abs : (I)I
    //   446: invokevirtual charAt : (I)C
    //   449: invokevirtual append : (C)Ljava/lang/StringBuilder;
    //   452: pop
    //   453: iload_2
    //   454: ifeq -> 1348
    //   457: goto -> 464
    //   460: invokestatic a : (Ljava/lang/Throwable;)Ljava/lang/Throwable;
    //   463: athrow
    //   464: aload_3
    //   465: getstatic burp/Zspg.ZG : Ljava/lang/String;
    //   468: getstatic burp/Zb3d.Zw : Ljava/lang/Object;
    //   471: checkcast java/math/BigInteger
    //   474: invokevirtual intValue : ()I
    //   477: bipush #32
    //   479: irem
    //   480: invokestatic abs : (I)I
    //   483: invokevirtual charAt : (I)C
    //   486: invokevirtual append : (C)Ljava/lang/StringBuilder;
    //   489: pop
    //   490: iload_2
    //   491: ifeq -> 1348
    //   494: goto -> 501
    //   497: invokestatic a : (Ljava/lang/Throwable;)Ljava/lang/Throwable;
    //   500: athrow
    //   501: aload_3
    //   502: getstatic burp/Ztgv.ZC : Ljava/lang/String;
    //   505: getstatic burp/Ze7e.Z_ : Ljava/lang/Object;
    //   508: checkcast java/math/BigInteger
    //   511: invokevirtual intValue : ()I
    //   514: bipush #32
    //   516: irem
    //   517: invokestatic abs : (I)I
    //   520: invokevirtual charAt : (I)C
    //   523: invokevirtual append : (C)Ljava/lang/StringBuilder;
    //   526: pop
    //   527: iload_2
    //   528: ifeq -> 1348
    //   531: goto -> 538
    //   534: invokestatic a : (Ljava/lang/Throwable;)Ljava/lang/Throwable;
    //   537: athrow
    //   538: aload_3
    //   539: getstatic burp/Zg1l.Zl : Ljava/lang/String;
    //   542: getstatic burp/Zos.ZB : Ljava/lang/Object;
    //   545: checkcast java/math/BigInteger
    //   548: invokevirtual intValue : ()I
    //   551: bipush #32
    //   553: irem
    //   554: invokestatic abs : (I)I
    //   557: invokevirtual charAt : (I)C
    //   560: invokevirtual append : (C)Ljava/lang/StringBuilder;
    //   563: pop
    //   564: iload_2
    //   565: ifeq -> 1348
    //   568: goto -> 575
    //   571: invokestatic a : (Ljava/lang/Throwable;)Ljava/lang/Throwable;
    //   574: athrow
    //   575: aload_3
    //   576: getstatic burp/Zmyk.Zx : Ljava/lang/String;
    //   579: getstatic burp/Zv8d.ZN : Ljava/lang/Object;
    //   582: checkcast java/math/BigInteger
    //   585: invokevirtual intValue : ()I
    //   588: bipush #32
    //   590: irem
    //   591: invokestatic abs : (I)I
    //   594: invokevirtual charAt : (I)C
    //   597: invokevirtual append : (C)Ljava/lang/StringBuilder;
    //   600: pop
    //   601: iload_2
    //   602: ifeq -> 1348
    //   605: goto -> 612
    //   608: invokestatic a : (Ljava/lang/Throwable;)Ljava/lang/Throwable;
    //   611: athrow
    //   612: aload_3
    //   613: getstatic burp/Zxju.Zt : Ljava/lang/String;
    //   616: getstatic burp/Zry1.Zf : Ljava/lang/Object;
    //   619: checkcast java/math/BigInteger
    //   622: invokevirtual intValue : ()I
    //   625: bipush #32
    //   627: irem
    //   628: invokestatic abs : (I)I
    //   631: invokevirtual charAt : (I)C
    //   634: invokevirtual append : (C)Ljava/lang/StringBuilder;
    //   637: pop
    //   638: iload_2
    //   639: ifeq -> 1348
    //   642: goto -> 649
    //   645: invokestatic a : (Ljava/lang/Throwable;)Ljava/lang/Throwable;
    //   648: athrow
    //   649: aload_3
    //   650: getstatic burp/Zmdf.Zo : Ljava/lang/String;
    //   653: getstatic burp/Zz4m.Zo : Ljava/lang/Object;
    //   656: checkcast java/math/BigInteger
    //   659: invokevirtual intValue : ()I
    //   662: bipush #32
    //   664: irem
    //   665: invokestatic abs : (I)I
    //   668: invokevirtual charAt : (I)C
    //   671: invokevirtual append : (C)Ljava/lang/StringBuilder;
    //   674: pop
    //   675: iload_2
    //   676: ifeq -> 1348
    //   679: goto -> 686
    //   682: invokestatic a : (Ljava/lang/Throwable;)Ljava/lang/Throwable;
    //   685: athrow
    //   686: aload_3
    //   687: getstatic burp/Zm3x.Zu : Ljava/lang/String;
    //   690: getstatic burp/Zmli.Zh : Ljava/lang/Object;
    //   693: checkcast java/math/BigInteger
    //   696: invokevirtual intValue : ()I
    //   699: bipush #32
    //   701: irem
    //   702: invokestatic abs : (I)I
    //   705: invokevirtual charAt : (I)C
    //   708: invokevirtual append : (C)Ljava/lang/StringBuilder;
    //   711: pop
    //   712: iload_2
    //   713: ifeq -> 1348
    //   716: goto -> 723
    //   719: invokestatic a : (Ljava/lang/Throwable;)Ljava/lang/Throwable;
    //   722: athrow
    //   723: aload_3
    //   724: getstatic burp/Zm8j.Zp : Ljava/lang/String;
    //   727: getstatic burp/Zt7x.ZE : Ljava/lang/Object;
    //   730: checkcast java/math/BigInteger
    //   733: invokevirtual intValue : ()I
    //   736: bipush #32
    //   738: irem
    //   739: invokestatic abs : (I)I
    //   742: invokevirtual charAt : (I)C
    //   745: invokevirtual append : (C)Ljava/lang/StringBuilder;
    //   748: pop
    //   749: iload_2
    //   750: ifeq -> 1348
    //   753: goto -> 760
    //   756: invokestatic a : (Ljava/lang/Throwable;)Ljava/lang/Throwable;
    //   759: athrow
    //   760: aload_3
    //   761: getstatic burp/Zql.Zf : Ljava/lang/String;
    //   764: getstatic burp/Zt0m.Zt : Ljava/lang/Object;
    //   767: checkcast java/math/BigInteger
    //   770: invokevirtual intValue : ()I
    //   773: bipush #32
    //   775: irem
    //   776: invokestatic abs : (I)I
    //   779: invokevirtual charAt : (I)C
    //   782: invokevirtual append : (C)Ljava/lang/StringBuilder;
    //   785: pop
    //   786: iload_2
    //   787: ifeq -> 1348
    //   790: goto -> 797
    //   793: invokestatic a : (Ljava/lang/Throwable;)Ljava/lang/Throwable;
    //   796: athrow
    //   797: aload_3
    //   798: getstatic burp/Ztbn.Zx : Ljava/lang/String;
    //   801: getstatic burp/Ztgv.Zg : Ljava/lang/Object;
    //   804: checkcast java/math/BigInteger
    //   807: invokevirtual intValue : ()I
    //   810: bipush #32
    //   812: irem
    //   813: invokestatic abs : (I)I
    //   816: invokevirtual charAt : (I)C
    //   819: invokevirtual append : (C)Ljava/lang/StringBuilder;
    //   822: pop
    //   823: iload_2
    //   824: ifeq -> 1348
    //   827: goto -> 834
    //   830: invokestatic a : (Ljava/lang/Throwable;)Ljava/lang/Throwable;
    //   833: athrow
    //   834: aload_3
    //   835: getstatic burp/Zxan.ZJ : Ljava/lang/String;
    //   838: getstatic burp/Zk5k.Zr : Ljava/lang/Object;
    //   841: checkcast java/math/BigInteger
    //   844: invokevirtual intValue : ()I
    //   847: bipush #32
    //   849: irem
    //   850: invokestatic abs : (I)I
    //   853: invokevirtual charAt : (I)C
    //   856: invokevirtual append : (C)Ljava/lang/StringBuilder;
    //   859: pop
    //   860: iload_2
    //   861: ifeq -> 1348
    //   864: goto -> 871
    //   867: invokestatic a : (Ljava/lang/Throwable;)Ljava/lang/Throwable;
    //   870: athrow
    //   871: aload_3
    //   872: getstatic burp/Zeqz.ZV : Ljava/lang/String;
    //   875: getstatic burp/Zoe.ZG : Ljava/lang/Object;
    //   878: checkcast java/math/BigInteger
    //   881: invokevirtual intValue : ()I
    //   884: bipush #32
    //   886: irem
    //   887: invokestatic abs : (I)I
    //   890: invokevirtual charAt : (I)C
    //   893: invokevirtual append : (C)Ljava/lang/StringBuilder;
    //   896: pop
    //   897: iload_2
    //   898: ifeq -> 1348
    //   901: goto -> 908
    //   904: invokestatic a : (Ljava/lang/Throwable;)Ljava/lang/Throwable;
    //   907: athrow
    //   908: aload_3
    //   909: getstatic burp/Zzh5.Zc : Ljava/lang/String;
    //   912: getstatic burp/Zlbd.ZU : Ljava/lang/Object;
    //   915: checkcast java/math/BigInteger
    //   918: invokevirtual intValue : ()I
    //   921: bipush #32
    //   923: irem
    //   924: invokestatic abs : (I)I
    //   927: invokevirtual charAt : (I)C
    //   930: invokevirtual append : (C)Ljava/lang/StringBuilder;
    //   933: pop
    //   934: iload_2
    //   935: ifeq -> 1348
    //   938: goto -> 945
    //   941: invokestatic a : (Ljava/lang/Throwable;)Ljava/lang/Throwable;
    //   944: athrow
    //   945: aload_3
    //   946: getstatic burp/Ze25.Zp : Ljava/lang/String;
    //   949: getstatic burp/Zzk_.Zx : Ljava/lang/Object;
    //   952: checkcast java/math/BigInteger
    //   955: invokevirtual intValue : ()I
    //   958: bipush #32
    //   960: irem
    //   961: invokestatic abs : (I)I
    //   964: invokevirtual charAt : (I)C
    //   967: invokevirtual append : (C)Ljava/lang/StringBuilder;
    //   970: pop
    //   971: iload_2
    //   972: ifeq -> 1348
    //   975: goto -> 982
    //   978: invokestatic a : (Ljava/lang/Throwable;)Ljava/lang/Throwable;
    //   981: athrow
    //   982: aload_3
    //   983: getstatic burp/Zz7m.Zq : Ljava/lang/String;
    //   986: getstatic burp/Zsdl.Zx : Ljava/lang/Object;
    //   989: checkcast java/math/BigInteger
    //   992: invokevirtual intValue : ()I
    //   995: bipush #32
    //   997: irem
    //   998: invokestatic abs : (I)I
    //   1001: invokevirtual charAt : (I)C
    //   1004: invokevirtual append : (C)Ljava/lang/StringBuilder;
    //   1007: pop
    //   1008: iload_2
    //   1009: ifeq -> 1348
    //   1012: goto -> 1019
    //   1015: invokestatic a : (Ljava/lang/Throwable;)Ljava/lang/Throwable;
    //   1018: athrow
    //   1019: aload_3
    //   1020: getstatic burp/Zejz.Zd : Ljava/lang/String;
    //   1023: getstatic burp/Zrip.ZB : Ljava/lang/Object;
    //   1026: checkcast java/math/BigInteger
    //   1029: invokevirtual intValue : ()I
    //   1032: bipush #32
    //   1034: irem
    //   1035: invokestatic abs : (I)I
    //   1038: invokevirtual charAt : (I)C
    //   1041: invokevirtual append : (C)Ljava/lang/StringBuilder;
    //   1044: pop
    //   1045: iload_2
    //   1046: ifeq -> 1348
    //   1049: goto -> 1056
    //   1052: invokestatic a : (Ljava/lang/Throwable;)Ljava/lang/Throwable;
    //   1055: athrow
    //   1056: aload_3
    //   1057: getstatic burp/Zsko.Zd : Ljava/lang/String;
    //   1060: getstatic burp/Zb_1.ZK : Ljava/lang/Object;
    //   1063: checkcast java/math/BigInteger
    //   1066: invokevirtual intValue : ()I
    //   1069: bipush #32
    //   1071: irem
    //   1072: invokestatic abs : (I)I
    //   1075: invokevirtual charAt : (I)C
    //   1078: invokevirtual append : (C)Ljava/lang/StringBuilder;
    //   1081: pop
    //   1082: iload_2
    //   1083: ifeq -> 1348
    //   1086: goto -> 1093
    //   1089: invokestatic a : (Ljava/lang/Throwable;)Ljava/lang/Throwable;
    //   1092: athrow
    //   1093: aload_3
    //   1094: getstatic burp/Zlt1.ZA : Ljava/lang/String;
    //   1097: getstatic burp/Zrom.ZF : Ljava/lang/Object;
    //   1100: checkcast java/math/BigInteger
    //   1103: invokevirtual intValue : ()I
    //   1106: bipush #32
    //   1108: irem
    //   1109: invokestatic abs : (I)I
    //   1112: invokevirtual charAt : (I)C
    //   1115: invokevirtual append : (C)Ljava/lang/StringBuilder;
    //   1118: pop
    //   1119: iload_2
    //   1120: ifeq -> 1348
    //   1123: goto -> 1130
    //   1126: invokestatic a : (Ljava/lang/Throwable;)Ljava/lang/Throwable;
    //   1129: athrow
    //   1130: aload_3
    //   1131: getstatic burp/Zgeq.ZF : Ljava/lang/String;
    //   1134: getstatic burp/Ztq2.Zj : Ljava/lang/Object;
    //   1137: checkcast java/math/BigInteger
    //   1140: invokevirtual intValue : ()I
    //   1143: bipush #32
    //   1145: irem
    //   1146: invokestatic abs : (I)I
    //   1149: invokevirtual charAt : (I)C
    //   1152: invokevirtual append : (C)Ljava/lang/StringBuilder;
    //   1155: pop
    //   1156: iload_2
    //   1157: ifeq -> 1348
    //   1160: goto -> 1167
    //   1163: invokestatic a : (Ljava/lang/Throwable;)Ljava/lang/Throwable;
    //   1166: athrow
    //   1167: aload_3
    //   1168: getstatic burp/Zzmc.Zr : Ljava/lang/String;
    //   1171: getstatic burp/Zegj.ZT : Ljava/lang/Object;
    //   1174: checkcast java/math/BigInteger
    //   1177: invokevirtual intValue : ()I
    //   1180: bipush #32
    //   1182: irem
    //   1183: invokestatic abs : (I)I
    //   1186: invokevirtual charAt : (I)C
    //   1189: invokevirtual append : (C)Ljava/lang/StringBuilder;
    //   1192: pop
    //   1193: iload_2
    //   1194: ifeq -> 1348
    //   1197: goto -> 1204
    //   1200: invokestatic a : (Ljava/lang/Throwable;)Ljava/lang/Throwable;
    //   1203: athrow
    //   1204: aload_3
    //   1205: getstatic burp/Zlc2.Zz : Ljava/lang/String;
    //   1208: getstatic burp/Zx5w.Zo : Ljava/lang/Object;
    //   1211: checkcast java/math/BigInteger
    //   1214: invokevirtual intValue : ()I
    //   1217: bipush #32
    //   1219: irem
    //   1220: invokestatic abs : (I)I
    //   1223: invokevirtual charAt : (I)C
    //   1226: invokevirtual append : (C)Ljava/lang/StringBuilder;
    //   1229: pop
    //   1230: iload_2
    //   1231: ifeq -> 1348
    //   1234: goto -> 1241
    //   1237: invokestatic a : (Ljava/lang/Throwable;)Ljava/lang/Throwable;
    //   1240: athrow
    //   1241: aload_3
    //   1242: getstatic burp/Zzef.Za : Ljava/lang/String;
    //   1245: getstatic burp/Zxan.ZX : Ljava/lang/Object;
    //   1248: checkcast java/math/BigInteger
    //   1251: invokevirtual intValue : ()I
    //   1254: bipush #32
    //   1256: irem
    //   1257: invokestatic abs : (I)I
    //   1260: invokevirtual charAt : (I)C
    //   1263: invokevirtual append : (C)Ljava/lang/StringBuilder;
    //   1266: pop
    //   1267: iload_2
    //   1268: ifeq -> 1348
    //   1271: goto -> 1278
    //   1274: invokestatic a : (Ljava/lang/Throwable;)Ljava/lang/Throwable;
    //   1277: athrow
    //   1278: aload_3
    //   1279: getstatic burp/Zzl4.ZT : Ljava/lang/String;
    //   1282: getstatic burp/Zek4.ZR : Ljava/lang/Object;
    //   1285: checkcast java/math/BigInteger
    //   1288: invokevirtual intValue : ()I
    //   1291: bipush #32
    //   1293: irem
    //   1294: invokestatic abs : (I)I
    //   1297: invokevirtual charAt : (I)C
    //   1300: invokevirtual append : (C)Ljava/lang/StringBuilder;
    //   1303: pop
    //   1304: iload_2
    //   1305: ifeq -> 1348
    //   1308: goto -> 1315
    //   1311: invokestatic a : (Ljava/lang/Throwable;)Ljava/lang/Throwable;
    //   1314: athrow
    //   1315: aload_3
    //   1316: getstatic burp/Zkql.ZR : Ljava/lang/String;
    //   1319: getstatic burp/Zttd.Zi : Ljava/lang/Object;
    //   1322: checkcast java/math/BigInteger
    //   1325: invokevirtual intValue : ()I
    //   1328: bipush #32
    //   1330: irem
    //   1331: invokestatic abs : (I)I
    //   1334: invokevirtual charAt : (I)C
    //   1337: invokevirtual append : (C)Ljava/lang/StringBuilder;
    //   1340: pop
    //   1341: goto -> 1348
    //   1344: invokestatic a : (Ljava/lang/Throwable;)Ljava/lang/Throwable;
    //   1347: athrow
    //   1348: iinc #4, 1
    //   1351: iload_2
    //   1352: ifeq -> 15
    //   1355: sipush #-28079
    //   1358: sipush #-447
    //   1361: invokestatic a : (II)Ljava/lang/String;
    //   1364: invokestatic forName : (Ljava/lang/String;)Ljava/lang/Class;
    //   1367: invokevirtual getDeclaredFields : ()[Ljava/lang/reflect/Field;
    //   1370: astore #4
    //   1372: aload #4
    //   1374: arraylength
    //   1375: istore #5
    //   1377: iconst_0
    //   1378: istore #6
    //   1380: iload #6
    //   1382: iload #5
    //   1384: if_icmpge -> 1461
    //   1387: aload #4
    //   1389: iload #6
    //   1391: aaload
    //   1392: astore #7
    //   1394: aload #7
    //   1396: invokevirtual getType : ()Ljava/lang/Class;
    //   1399: ldc java/lang/String
    //   1401: invokevirtual equals : (Ljava/lang/Object;)Z
    //   1404: ifeq -> 1447
    //   1407: aload #7
    //   1409: iconst_1
    //   1410: invokevirtual setAccessible : (Z)V
    //   1413: aload #7
    //   1415: aconst_null
    //   1416: aload #7
    //   1418: aconst_null
    //   1419: invokevirtual get : (Ljava/lang/Object;)Ljava/lang/Object;
    //   1422: checkcast java/lang/String
    //   1425: getstatic burp/Zgsk.Zk : Ljava/lang/String;
    //   1428: <illegal opcode> makeConcatWithConstants : (Ljava/lang/String;Ljava/lang/String;)Ljava/lang/String;
    //   1433: invokevirtual set : (Ljava/lang/Object;Ljava/lang/Object;)V
    //   1436: iload_2
    //   1437: ifeq -> 1461
    //   1440: goto -> 1447
    //   1443: invokestatic a : (Ljava/lang/Throwable;)Ljava/lang/Throwable;
    //   1446: athrow
    //   1447: iinc #6, 1
    //   1450: iload_2
    //   1451: ifeq -> 1380
    //   1454: goto -> 1461
    //   1457: invokestatic a : (Ljava/lang/Throwable;)Ljava/lang/Throwable;
    //   1460: athrow
    //   1461: sipush #-28065
    //   1464: sipush #-9226
    //   1467: invokestatic a : (II)Ljava/lang/String;
    //   1470: iconst_1
    //   1471: ldc burp/Zgl4
    //   1473: invokevirtual getClassLoader : ()Ljava/lang/ClassLoader;
    //   1476: invokestatic forName : (Ljava/lang/String;ZLjava/lang/ClassLoader;)Ljava/lang/Class;
    //   1479: invokevirtual getDeclaredFields : ()[Ljava/lang/reflect/Field;
    //   1482: astore #4
    //   1484: aload #4
    //   1486: arraylength
    //   1487: istore #5
    //   1489: iconst_0
    //   1490: istore #6
    //   1492: iload #6
    //   1494: iload #5
    //   1496: if_icmpge -> 1634
    //   1499: aload #4
    //   1501: iload #6
    //   1503: aaload
    //   1504: astore #7
    //   1506: aload #7
    //   1508: invokevirtual getModifiers : ()I
    //   1511: invokestatic isStatic : (I)Z
    //   1514: ifne -> 1524
    //   1517: goto -> 1627
    //   1520: invokestatic a : (Ljava/lang/Throwable;)Ljava/lang/Throwable;
    //   1523: athrow
    //   1524: aload #7
    //   1526: invokevirtual getType : ()Ljava/lang/Class;
    //   1529: astore #8
    //   1531: aload #8
    //   1533: ifnull -> 1614
    //   1536: aload #8
    //   1538: invokevirtual isPrimitive : ()Z
    //   1541: ifne -> 1614
    //   1544: goto -> 1551
    //   1547: invokestatic a : (Ljava/lang/Throwable;)Ljava/lang/Throwable;
    //   1550: athrow
    //   1551: aload #8
    //   1553: invokevirtual getPackage : ()Ljava/lang/Package;
    //   1556: ifnull -> 1614
    //   1559: goto -> 1566
    //   1562: invokestatic a : (Ljava/lang/Throwable;)Ljava/lang/Throwable;
    //   1565: athrow
    //   1566: aload #8
    //   1568: invokevirtual getPackage : ()Ljava/lang/Package;
    //   1571: invokevirtual getName : ()Ljava/lang/String;
    //   1574: ifnull -> 1614
    //   1577: goto -> 1584
    //   1580: invokestatic a : (Ljava/lang/Throwable;)Ljava/lang/Throwable;
    //   1583: athrow
    //   1584: aload #8
    //   1586: invokevirtual getPackage : ()Ljava/lang/Package;
    //   1589: invokevirtual getName : ()Ljava/lang/String;
    //   1592: sipush #-28080
    //   1595: sipush #-7660
    //   1598: invokestatic a : (II)Ljava/lang/String;
    //   1601: invokevirtual startsWith : (Ljava/lang/String;)Z
    //   1604: ifne -> 1614
    //   1607: goto -> 1614
    //   1610: invokestatic a : (Ljava/lang/Throwable;)Ljava/lang/Throwable;
    //   1613: athrow
    //   1614: aload #7
    //   1616: iconst_1
    //   1617: invokevirtual setAccessible : (Z)V
    //   1620: aload #7
    //   1622: aconst_null
    //   1623: invokevirtual get : (Ljava/lang/Object;)Ljava/lang/Object;
    //   1626: pop
    //   1627: iinc #6, 1
    //   1630: iload_2
    //   1631: ifeq -> 1492
    //   1634: sipush #-28071
    //   1637: sipush #-2409
    //   1640: invokestatic a : (II)Ljava/lang/String;
    //   1643: invokestatic forName : (Ljava/lang/String;)Ljava/lang/Class;
    //   1646: invokevirtual getDeclaredMethods : ()[Ljava/lang/reflect/Method;
    //   1649: astore #4
    //   1651: aload #4
    //   1653: arraylength
    //   1654: istore #5
    //   1656: iconst_0
    //   1657: istore #6
    //   1659: iload #6
    //   1661: iload #5
    //   1663: if_icmpge -> 1796
    //   1666: aload #4
    //   1668: iload #6
    //   1670: aaload
    //   1671: astore #7
    //   1673: aload #7
    //   1675: invokevirtual getParameterTypes : ()[Ljava/lang/Class;
    //   1678: pop
    //   1679: aload #7
    //   1681: invokevirtual getModifiers : ()I
    //   1684: invokestatic isStatic : (I)Z
    //   1687: ifeq -> 1782
    //   1690: aload #7
    //   1692: invokevirtual getParameterTypes : ()[Ljava/lang/Class;
    //   1695: arraylength
    //   1696: iconst_2
    //   1697: if_icmpne -> 1782
    //   1700: goto -> 1707
    //   1703: invokestatic a : (Ljava/lang/Throwable;)Ljava/lang/Throwable;
    //   1706: athrow
    //   1707: aload #7
    //   1709: invokevirtual getReturnType : ()Ljava/lang/Class;
    //   1712: getstatic java/lang/Void.TYPE : Ljava/lang/Class;
    //   1715: invokevirtual equals : (Ljava/lang/Object;)Z
    //   1718: ifeq -> 1782
    //   1721: goto -> 1728
    //   1724: invokestatic a : (Ljava/lang/Throwable;)Ljava/lang/Throwable;
    //   1727: athrow
    //   1728: aload #7
    //   1730: iconst_1
    //   1731: invokevirtual setAccessible : (Z)V
    //   1734: aload #7
    //   1736: aconst_null
    //   1737: iconst_2
    //   1738: anewarray java/lang/Object
    //   1741: dup
    //   1742: iconst_0
    //   1743: aload_0
    //   1744: aastore
    //   1745: dup
    //   1746: iconst_1
    //   1747: aload_1
    //   1748: ifnonnull -> 1766
    //   1751: goto -> 1758
    //   1754: invokestatic a : (Ljava/lang/Throwable;)Ljava/lang/Throwable;
    //   1757: athrow
    //   1758: aload_1
    //   1759: goto -> 1773
    //   1762: invokestatic a : (Ljava/lang/Throwable;)Ljava/lang/Throwable;
    //   1765: athrow
    //   1766: aload_1
    //   1767: checkcast [B
    //   1770: invokevirtual clone : ()Ljava/lang/Object;
    //   1773: aastore
    //   1774: invokevirtual invoke : (Ljava/lang/Object;[Ljava/lang/Object;)Ljava/lang/Object;
    //   1777: pop
    //   1778: iload_2
    //   1779: ifeq -> 1796
    //   1782: iinc #6, 1
    //   1785: iload_2
    //   1786: ifeq -> 1659
    //   1789: goto -> 1796
    //   1792: invokestatic a : (Ljava/lang/Throwable;)Ljava/lang/Throwable;
    //   1795: athrow
    //   1796: getstatic burp/Zlwc.ZM : Ljava/lang/String;
    //   1799: getstatic burp/Zllk.Zi : Ljava/lang/Object;
    //   1802: checkcast java/math/BigInteger
    //   1805: invokevirtual intValue : ()I
    //   1808: bipush #32
    //   1810: irem
    //   1811: invokestatic abs : (I)I
    //   1814: invokevirtual charAt : (I)C
    //   1817: getstatic burp/Zk9q.Zk : Ljava/lang/String;
    //   1820: getstatic burp/Zg0q.Zf : Ljava/lang/Object;
    //   1823: checkcast java/math/BigInteger
    //   1826: invokevirtual intValue : ()I
    //   1829: bipush #32
    //   1831: irem
    //   1832: invokestatic abs : (I)I
    //   1835: invokevirtual charAt : (I)C
    //   1838: if_icmple -> 1953
    //   1841: getstatic burp/Zscf.Zu : Ljava/lang/String;
    //   1844: getstatic burp/Zm63.ZT : Ljava/lang/Object;
    //   1847: checkcast java/math/BigInteger
    //   1850: invokevirtual intValue : ()I
    //   1853: bipush #32
    //   1855: irem
    //   1856: invokestatic abs : (I)I
    //   1859: invokevirtual charAt : (I)C
    //   1862: getstatic burp/Zg4z.Zm : Ljava/lang/String;
    //   1865: getstatic burp/Zr60.Ze : Ljava/lang/Object;
    //   1868: checkcast java/math/BigInteger
    //   1871: invokevirtual intValue : ()I
    //   1874: bipush #32
    //   1876: irem
    //   1877: invokestatic abs : (I)I
    //   1880: invokevirtual charAt : (I)C
    //   1883: if_icmpgt -> 1953
    //   1886: goto -> 1893
    //   1889: invokestatic a : (Ljava/lang/Throwable;)Ljava/lang/Throwable;
    //   1892: athrow
    //   1893: getstatic burp/Zku9.Zl : Ljava/lang/String;
    //   1896: getstatic burp/Zkql.Zl : Ljava/lang/Object;
    //   1899: checkcast java/math/BigInteger
    //   1902: invokevirtual intValue : ()I
    //   1905: bipush #32
    //   1907: irem
    //   1908: invokestatic abs : (I)I
    //   1911: invokevirtual charAt : (I)C
    //   1914: getstatic burp/Zx5w.Zq : Ljava/lang/String;
    //   1917: getstatic burp/Zxc0.Zl : Ljava/lang/Object;
    //   1920: checkcast java/math/BigInteger
    //   1923: invokevirtual intValue : ()I
    //   1926: bipush #32
    //   1928: irem
    //   1929: invokestatic abs : (I)I
    //   1932: invokevirtual charAt : (I)C
    //   1935: if_icmple -> 1953
    //   1938: goto -> 1945
    //   1941: invokestatic a : (Ljava/lang/Throwable;)Ljava/lang/Throwable;
    //   1944: athrow
    //   1945: iconst_1
    //   1946: goto -> 1954
    //   1949: invokestatic a : (Ljava/lang/Throwable;)Ljava/lang/Throwable;
    //   1952: athrow
    //   1953: iconst_0
    //   1954: ireturn
    //   1955: astore_3
    //   1956: new java/lang/Exception
    //   1959: dup
    //   1960: aload_3
    //   1961: invokevirtual getMessage : ()Ljava/lang/String;
    //   1964: invokespecial <init> : (Ljava/lang/String;)V
    //   1967: athrow
    // Exception table:
    //   from	to	target	type
    //   4	1954	1955	java/lang/Throwable
    //   22	198	201	java/lang/Throwable
    //   168	235	238	java/lang/Throwable
    //   205	272	275	java/lang/Throwable
    //   242	309	312	java/lang/Throwable
    //   279	346	349	java/lang/Throwable
    //   316	383	386	java/lang/Throwable
    //   353	420	423	java/lang/Throwable
    //   390	457	460	java/lang/Throwable
    //   427	494	497	java/lang/Throwable
    //   464	531	534	java/lang/Throwable
    //   501	568	571	java/lang/Throwable
    //   538	605	608	java/lang/Throwable
    //   575	642	645	java/lang/Throwable
    //   612	679	682	java/lang/Throwable
    //   649	716	719	java/lang/Throwable
    //   686	753	756	java/lang/Throwable
    //   723	790	793	java/lang/Throwable
    //   760	827	830	java/lang/Throwable
    //   797	864	867	java/lang/Throwable
    //   834	901	904	java/lang/Throwable
    //   871	938	941	java/lang/Throwable
    //   908	975	978	java/lang/Throwable
    //   945	1012	1015	java/lang/Throwable
    //   982	1049	1052	java/lang/Throwable
    //   1019	1086	1089	java/lang/Throwable
    //   1056	1123	1126	java/lang/Throwable
    //   1093	1160	1163	java/lang/Throwable
    //   1130	1197	1200	java/lang/Throwable
    //   1167	1234	1237	java/lang/Throwable
    //   1204	1271	1274	java/lang/Throwable
    //   1241	1308	1311	java/lang/Throwable
    //   1278	1341	1344	java/lang/Throwable
    //   1394	1440	1443	java/lang/Throwable
    //   1407	1454	1457	java/lang/Throwable
    //   1506	1520	1520	java/lang/Throwable
    //   1531	1544	1547	java/lang/Throwable
    //   1536	1559	1562	java/lang/Throwable
    //   1551	1577	1580	java/lang/Throwable
    //   1566	1607	1610	java/lang/Throwable
    //   1673	1700	1703	java/lang/Throwable
    //   1690	1721	1724	java/lang/Throwable
    //   1707	1751	1754	java/lang/Throwable
    //   1728	1762	1762	java/lang/Throwable
    //   1773	1789	1792	java/lang/Throwable
    //   1796	1886	1889	java/lang/Throwable
    //   1841	1938	1941	java/lang/Throwable
    //   1893	1949	1949	java/lang/Throwable
  }
  
  static {
    // Byte code:
    //   0: bipush #10
    //   2: anewarray java/lang/String
    //   5: astore #5
    //   7: iconst_0
    //   8: istore_3
    //   9: ldc 'A0;kË»º1Jªè¿_>à^\\rET%¡¡_â®c\\t_Ï)"Ñ°oä®'
    //   11: dup
    //   12: astore_2
    //   13: invokevirtual length : ()I
    //   16: istore #4
    //   18: bipush #32
    //   20: istore_1
    //   21: iconst_m1
    //   22: istore_0
    //   23: bipush #63
    //   25: iinc #0, 1
    //   28: aload_2
    //   29: iload_0
    //   30: dup
    //   31: iload_1
    //   32: iadd
    //   33: invokevirtual substring : (II)Ljava/lang/String;
    //   36: iconst_m1
    //   37: goto -> 204
    //   40: aload #5
    //   42: swap
    //   43: iload_3
    //   44: iinc #3, 1
    //   47: swap
    //   48: aastore
    //   49: iload_0
    //   50: iload_1
    //   51: iadd
    //   52: dup
    //   53: istore_0
    //   54: iload #4
    //   56: if_icmpge -> 68
    //   59: aload_2
    //   60: iload_0
    //   61: invokevirtual charAt : (I)C
    //   64: istore_1
    //   65: goto -> 23
    //   68: ldc 'fQ²öa'Jµ¥Lù3G×/²JÒ¯t>máåaÈëk¹V¦'LÄ*êLò=Ù)¡û)\\f ¾|YúRèàµpN<¢~ÎÚ8°^T'^½ÔQ)T:YÏ_¼§Ëè½S:}ÇP¹?R\[t~Ï\\faÈ:²2cæÝ)¦´_AÊØ6Ã"rÆÂy2Õ¦¶©Ïº3*ºLo­\\tÄ]µC0VhMb'qR¡U@)T¢¸ýïöÖì³¡¶jnÀ´·Îj)?­û·Gi6jú!%T4ßYBÎ|³yAÕ$cJ\\n× Ë|ø58EÈ­òÊH^K0I[H±#{êå¸½m®]Ø*ÁÛs:Fõhßè¯Á¤þ*ýoÛb]*\\n}k'«}Â_;Ó¤Ù÷ÐZ|ï¢|Ì7ÈCé²¡£´g£J_§uðq3Dùù·½ßãÑå¬3ý#GiºGNï'VKñ¼%&ÖÔqõê³08ò½#íC-ÚRiÝ`h¡ð¨8oSLµÄ-¿êBhâ­jÏjIúÇ{IP41\\f#KU~`±.Ê7e+Åål¼Oøé$¹hCL]d½Q©jÈÍ®?ÅìóAâãó@Â>.êsÂâhjñHìÛ`(¿äçÃ5~4Ã¨ìe¦$L¤ãaíW> úZ\\tÏ`Ér|W_ay0g¡Ø´(-XO:Øö!÷UÖÎöï;,Ð½^,®´¨<íW¦ø)£À*nc¼iÖj'\\n.F#¯ãÙ¯Ì3J,ããÿúÑÁäR³¾z4Érôä.B\\bÝDcþÌqäÚÙë¨¹uÃA×û¿ÿú:Iáit\\r"{öâïÇ¯aì£ÿ1HË`úuÒríÐ4Ïíó hØã;DâSæì´pß!Á'4Àáwæ¾uß¨°ÝÅçì`Ö8Â÷YÄ4I÷`x];ãw\\b¯Ë ?¥¼²g\\tE1ó7)T¾F¯q¢,ø£&p_|8jåÓøÏ¶ÏÃGX7ÈGIOgÃvÏ³Ôâiß­¢«°°EáÔ¦¹bNþV¨(KÑÑ¨¯cÁ#]VÖ<ÙN®}û2¨Ñ£þí\\n_é:ÑÑ÷©[EèÚ±Êi9e~5rËt\\fè-Y%-\\bãË$w¯þ}Ìt§ÕõÃ\\f³ó\\ruÁ!Ü¦fÒ®ÚìB\\t\\bµlÞh½É\\t%,øP\\t»ÝÀ©5$ÿlnªóOÊ©Ãï4ï¼Çò9Vî'ÿ=sÙ¬éj Ê§As\\t6ìV:ËA¿F¼á?%B3qóâ3ÉDgÆã\\tø5 ¡,Tè Nf³Ï¥Ñ+7qslâlÅ1ÝBNEóú^9fîâàqW.*À½\\bþVJ\K÷tàiêp>Mû4R.¹:¾CµrG¥AG-¯ÕO¶vÃs$êÓq§\\bÅùnÂê OÓ°Å­y§Ø;yPÜÃ}IjíÿoqOºÅÌôX(s¤ÕÆì´;£`5úlÿÈÿiòk4gí\½®?ÓöjÓ4#c¨ÛÊ¡\\n¶\\tüä8ëÉoövGÙÃõhDn{"$9^´®åÖÔQÏÑ{sm7·£äâÍSfÈOõÃKÚ¿|!bo³jCD??9TYûdÙi«äjõÝ¿1ùã':d6°iÇIó\\b§p?#}×ðÅ1ú9r¯à2!0Á£©µ\\fðéQWZ4ÀÌ(¼óÒÉ\\n°ÝÒÉÒ'°Jõÿ³\\tÊã\\bI¢cPæa|®{ð S¥ÿ£²d=)4²TEþtõ¬KÖõYÆ£xgb<BÆA0}<ÜµIA?½üìF2¤)®©ª¥îÝ°OAEªñ^Ãn×]X­Ot¬ï¿¥x¤ejl ©ÀCÓóüP~áõ½LJ_²2óÏµÕß}r´}+ãJ!ÒjáBf5Uç¼±ó¯p&¼áäfU\\b!+AÄc7/\\fÃZ0ÿO¼E«5Íº!;ã!·}«Ú%ä<PjÌa IÉÇ¨!©Ìr²\­©ê2*¥Ô-xóºñÇñoùN(ßG¸Kó¡brµgÖ2ÝÑ¶w¡kSw®-\åïsÐf©r §Yê ò\\t±©([7_ðÉI h£H\û(2dGk=qEüáðkS)¯Àl'DëÿZãÙ¢»}ó!R)jÀJª=ðEet>Ù\µÖ6b×lØ}*!\\nïYÈ÷0>w#Ívì1~F6.ZÛ;ÒJÀA\\fQD)5ÂÒ¼\\r@È£3­µ¤º\\nY©éN>»[;n\\nLÑ»'Æ65\\t7;`AíOÒêw\\bú£qâ²Ë\\fçþ§Xa¢P¥&µ§De,NÞ+»½ºë9;Ú÷¢;9úSÑ¶úîUd*ÐCKÚ|kèNÔì¢Äúx±Íb¤¼P9&<.´÷¼vþ×Xµ¬b4Ý/,ðO¥E{ó\üÏÔÌ®Ò«j&T  ~ÁêqP³PX>ù'à7ªaçs+Z«\\t3W°ÊÔöD'$ØdtëíØÕ@+SV­÷BöS¹i¶«tÂÄ\\ryÒtÕJB{D\\f\\rðÌ!¯-Æ«Zp\\raQHÏ¤Jn!1ÖË³é\\fÐn·\\rZòÔMY\\rH¬3 =ü)eÆMj#@ã:ãèÈyI¯Tg÷D¬ü¼OBÉOÐ®<ø0C³97"&¡ÛïË\\b9³7!.^GD| {¾¥ÕêbAe QyZzQ/UóÌ÷)ÅÒÙ_ÆlÊuÂ8æÏC:e(Ë+)YóïÀÁ(éh_OtÀiVÅ Á0ôÝ.½qívo·éÇ_xêÐ_ñ"|?KÃF÷Íõj¤j§9f(5=.Föï¼Ðç>}ñ¢\\nôÖò.Jxà6NÐ¨!÷<äU·|èpPÚu%Ïpe×l>#Hý»Vùu­s°·s3¾³Î¡¬ÜæKÝíY«-ü¨ý$J>s×¼dÒÑUÄÔ.Ð+/®ÕEêçâ¼6ÁäWÒ¥T,9Ïvm9#\\tR)h°è¸rVZu1lÅyÌ-\\b°;ÌÊ¤±·K.!íº¦|~\\fº±K#VV\\tX\\nº¿_.c|Ä§t³yùþ¯Óü¨ÆBsw\\tøÔãZ¡ú{¼]ôcx0êùÂÍs¶;\»_mM T¶ ïÙÃM­½ÃW¸ÛÓ étLríqØFùÜRàÑCÛnWÄ*.m}&  ©SÜ:ÚR´FÃ9nÌió^¼ðÙÝ\\b<6)ÓmÜïKìØú7{ÏL#ìá!vÚûC9¶Kk0ü©­×|:>¢3Ü*ð©«åN±¿Ät½çë&+fÂ²Á/ImSMÿrïÐd|¾¸z!wÛ\\r¥¼2 iä*e`H¶ðãZtXÙ)Ì³±ÑÜ:ªÛ\\nNê­C;Ïó!¿VÔ¸±¶ªùú£J1£]5d\\n=Í­ªOmOwKpÛdj7ø©BT«à­AéÊ3»ü?x î­¿ÌE«PâÉM^JH^ð»hÔpÓ=%k¶¬8+£ÒÚ^ÏáìÃëUì¹ü+æBóL}MÂ{85'K^&ÉqöòÑ|>.Üî7;©8âæÚá"ð¥¿û×P½À3{°ú#\#5u]YM0?½l¶ÌðP¨&û\\r-3½08úªâô8m©ð(Ú×°FiØÙmÉ@ÃtE¶ä&¾ØÝ?Ç©@ÎZº{QkC() ^V×r°8Ò-Ç¶C%ÎWÝx¶¬uý­\\fÞ¶gÃùB·ðw0Å|!¼jÉ:)hì-DÊ Ëa$fµäùX[-@¿ÈhW¾æx~Ëòà)¼aûRáäÛQ_e%ÎÚZ¡[y±ýÞýù_Ì96ÃÄÏzÆÓÖ©ÅU >ChomÀFÖØ=Qd¾´N3É+Z`&Ç-\\tÀs©M~2Ë$\\r´Ü-üi( zQÎe?°4ýi@ó%³28\\r\¸Ã«ª×OcÊ>¶\\f3d\\tmK×JreW}?X¹'h5'~>2ÜqWÏÈ²Â7è~a;4^ZÎ4ÖnéÀ «_g+;ô:aþ ÍRCn=×5QÆÑ ÙËäÉ±\Ï°{ëÆìÎ´ÄOH\\t#8«ß½ÇÚ:ð6 ¼¨zuÉMîfFã`Éøuu³õ>ßúrsçwî¶PÁ-S-P¤Þe>¹¡ôSßp¾¥¾éàzrlH\\bäè7ÑgÉÃw}ÐñzÄ"åÂ\\tr¦ëkù½\\t\</ÞK¢+æõPLß½_]õéE²ò t6ëØ"Û"ÄÀ\\rÜë´üÃ²\\f¿ãÎ7[OÜH\\rVyë<Q­Éd\\n³æýobÖ¡®þzëýTfh²!yJ6Ù+P¯ÔðRO¥(8Æ6°Ro2ÜÇ0¦L¨#¾LÙÛü\\b»ø§¿©ÓQ©F0_bWÜòÒñÆþ©ú±áGtI!úâÕ7#ã$k¥~Ýz:Ø3ö¿¾<OÌnþ-îCiÆYË ¥ò¹'7Å;dËEûUßjXF >ºÖC¢¢­ð~ôÛCÑæT«W6@UKÀn´4¿ùF`Ôm<Ò/ÑS4¬ìÎ±Ì³J{ 1lBßÏ0Á_jàïçàçòØ_ÏiîéëX<_\\b,\\tè@Ä\\nåÁ¦EU#oPM=©ènÍJ¾ó´Zº5~4íûsUûwÞ b³N=­¤Íyù@÷-&ø§gÙ¨m£Ãù¬X¨§Â,f RrÕÒn&/àòõ-ò»,ë=©ÂIô\\r}Î¯ênRMª®6¦ô`µ¾ð®^×øéâiÌÒxÀ*VØ(uéz+4ûÜ4oh>Ækêêçtrí¯ù}Ê,Mü.29: 8KÈ» AR_n¯ÃFLëEÍßi®+©&QÉ1»5{e/êYÌMÂýÂÌèBF~kÚ·U´èù0Ù¨ogwµ%­Ñ) }J7þàE¬UµdOè&xËËmMIßüÅf|.ý¼XÁR@±yúý²î|¢*]ÈWàÅÉÁ¯D¤Äïøµ$ \\tÔ¬Ö>-¹°àK~PdÚôþ];cPúÑ"ï5ÄaGÕJê=9JAÃ×>¿\©­7o>å¾b²#_#\\f\\f¨#÷RËäg]®k4a>£øóeìcù>E\\fù(AÕEë¯t¦ÊDÅÊ3´R|á)¼,Ì2:õc\\re`BËÇ@|i×II+%·#³©¦&LÜaçGÎ÷ráá³¤Ö¨n 5¢«3YÅù½yØ|,Ç3hÅÿ}+!ó¤¦¶ÒÌZeÐfeÙ¤\\nFd-¸PÐh»?=BcÊí»p¦NøìPÏ×oM!ÖÃ7>5w?Ë"óJBzÎÛÎâÈ.ãØ´ T(j{°H»HO;\\f£}yä@&ñ¥Ö7C³¤DyÐaPÛáZgÒÜvÜªî"%·Ù¸øãç2Pnë~¹@JYx'Æ*rÔ\\b±¨RS]±¿­C³^ÛÕÙl1^ÑlòXñJ¦¤ÈL2n!ðLÅnuS\\nó³ìËÁ\wß?ø&ÓÞô 0KYR\\t 1ýF ÂÂ£½.#]Y`w3ª$âËFÙµ\\t9g³ÉRÈûE·ÚòÇ_,DSDEëÒ¢ñ¥uJøñB-9WfeMETÐÂÚN`p\ß_z0ÝÍÓá4Gd{E ü[Áæ\\fz£µ©®£¼âØ´kç®Y\\rGÕóöy3.Ï;ÙÖ6(òbEK¢¬©D¨ô¢\`9þmÃÁ]oªÂæÌbå+[Åí5n®Õ¸p`¥ËQ±J ±Ù½ÃvC Ç\\r´ÖØÏ£üæÎhaìß\ßº×ÿÑd<àc=5­£uHíäoÖòÉ¸\\bâ11`°®ÈúÁ_{*9vø?ûÈÑÐ;Ö¨Å6º¦ÁEMÙ«°¡Ó`uzÆÑ»AiyIqqK0ÇèZ­}v±ä\\tdf¹HøÄün7,QÆz³´¤öº>?öìi­¦_%ÛoÔW¼³aIÂK7ò¡}´ÚPõ' ³Cd}Ýý÷sGÁo\\rñ\\fô<g\\nàþÈÆdqgÜø­cÏM¯ð2ZkÏ~Å©¯ÄDÿ÷%õ¹o\\rÂ_.o¹Y2<Aö]÷daW^Ìd\í+qRù.;&Î3kÊ°oº§Û~^~¬ö1¡nÁô9øÖu÷£pÙhë!(H1ån«¥5âoÝHýM«ñ7¥0Æ2ß&ÇÞÏ-m +£ã!9¾´ÁOâÀGÞÃ¾÷ÍS?PÍ£7V­.ÏW©\\r¤yök4Eº03/utU¦Y|í\w&Ù9ó·zÃ'x_ëµ\\b½rv^pJ¨\\nWEèáËàªaÀ%ËBQþÏ¨?gjAN¦Ú´YÏ¢0^#¸ç¯ãg¶ét!=ÔCý´m'ºWcÐZø""éo3ÎEÑ'®¹\\f99+Oi;þÿÜõzà{9IÐeëÚ%ÎÖìä­í;&OM·ÉÌÃNöð±'øvµ9m8<p¿Pð·:~|Þ3Õ~À±¡n0±A\\na.¤5¹¯U­á£»z 6¦\úÜÑ«oAÖ¿Sý=nùò¯EHR5ÛG\\bÉ¼5Â[o¶ë[q~Ë«Ý&oä^û\\b´âo.únÓ/ûÏ¶º\\fÙïÔÑ&iáR[=7³ñ.ãéðy0þþ]M"K7Qr§3£V|27Ú,Á!-KiºG¤2Èæ¾àXgÍ'$Ý©é>å©CW·{WçrpÔ¨WtcÓØµ&¼D³»7ë R\\b\f¶9A¾±½BvEFÄ±ÁÒ6ñÅjXPÀ)?Yv"ôI¡(Ké|$³\\nÿvÌ&YÑÌøz!aØÈ£öK@Q>bðÉJ¶j¿á.V@ýûíb7Ó¯×asºøÏì«Pî°«Â|MóâvºZ¼a&öé'XÕëh}*sH¬j¡ú_ÔBÅSãn"×`E×Û¤-®¶*,¯§àìB¨PK¦¢'%»YÚüÑ^\\f5jü\\nûB øì?»ûoèÔàb.t\É[ëv­±|Bù2D´bC¶øïGì¯Ri1¿VI}|7¥ç¥Rñ¸ãÀ{ýÞB¬sÎ]8î#sêÇ2SJfh*´KU>ºªFÊ¶ó\\b-G/ºù8d={k\\naâ=hÌ.S^aéNd"f ÷Ï<~uæ}çE}ÆÌEõJÈ"t÷vKæÿjqð u7>³LÔo¤VòÆÖk¡XÍ|N.Èã5¢íß×d\\tP«ÄC@°¦#V¯vmÕ±U95èÿ\\b£c åUA>1¹#ûXÿu¯Î¯ÕÔfëãè}ûY2r®MöW·)c\\bi¥n÷hm¦\\tû¦©[ZÍ\\fîè0Ê®ãÑNá9Ú£¬¾ù:éPûRX5W©ôNÍ½ºëÜ0>S¿èÖýÂÀì\\rÃNxxÝ[å<¼ÿç¦J?éý\Û§RÅÚs ÷Ly´í×VSÀf®é}f.Ú\\t÷>jÒ2Ëbtj³|ÐÆºy`{;Å¹èñè:g¢Õ¡µE±_"¼ZD\\tÇ4y¦y[¡W1ÊÇEU50\\nAKÜÀ3ê-ÏxþÓòK³²i@AºzsÔN§3õ­ºÝ2í{ ÁïÙ«w>¦Øàf(=ñ<?MâFjB\\\nÐÈ¢[úÙðü=l` áà½y¢Ósc(¡êð(&ç( negý<¦t:Á¦Bw¤¶äß¨»jªÙC²ê;K°Û">mê«º)âickÊâM´nð17«?=m?ý«iTæ9ýº2±LwuCDðÌÞàN¢.]Xô]{349yïçT³ÎÈ1v½ÊÎ\#N[h.-ùÝõÙåzu|0z¸K6_0ÄñÖ{.2Är/ÞÇSiªºýÂèQÝâ\\tXnÚIz¬ )T&NEP¯½Ü,|íglÒ¤T½pí6¤úÛ$µ<-ôÂö:@§×­¡ÆBµ^'Mqoø¦¦[¥/à %iYÖTÇÞËê^@Æwêìà¨&C+|ðÐ×+\\nP:dgWÕ8÷·Õ:v»Seu=ÅÄ%Yõñ]4ô\®×Xgßc[Ä±H=ÉHXüòBÒ¹çgst?Ù³_¿\\fSI0¼NYx?BìÝN#Ã7ä®¦F>èü÷ø>Vê3pø¡ÝÉ®UíÖü®±¹Fs­ã ­ú ZÇ8Oh^|ñ¸Dâ?åQ_û+V6¡Â³Pá£Þ­ã=±EÐ¸çÙ/dÑ¥Çz,p±PQ/QÄ½PUE~~X\þ¢A8\\n`é;\\r·ÛôÁY(1øpÐæÆÒÖ\\rÚÏÊgÙ`4Ï¨ÊÆn½ËÇ;CCT-ð3ÿnh¨ÏÐç <´ßäL$^ò8Æë¥ÅØ)iæÃ«RùæiÀ#èÑ+ûFA®ºç80Å<÷äÍLt&BÏÐ5¸3?Pìünò@®4|VúÔ¥<Óyg²·T½UPh¡êEzñDÍ\\tY\\nÑx×%R±8'Øâà\\n÷à¼J!GÉx\\t];8£Í¸ü¯°¼Û"ØÕQPm_×TÇõ²´ÍÙ~_#ØéÙ-ÄLo=:MñÔ+pk$aÅ,uÉ¶ÝVCh¦TyîÕL\\bú!óÉñ¸7w¹áhM;~wÆ Yíf?­ÓnjºBV÷d7u¹ÃOÂ¼«v¾ä.ÐkÛØzÝ¹~ÍwCÔ$P,¬û/Õ`®âêðÔ'ûz³®ì3Ñ=¯Áæêðxqz ´°ßò_î\AêàÇº{´[bSâH¨._èas(QmÒM~¬ô½uïY»=±vOãó2ªQÒn¹¦ÊSåÙÆ^SL¯U '8{£[;V¼ÖFOüaü6\¤*?¥J0¬¾¹¼|änñíoQz7ß¾:¡=ép¿¹¬naæuèÓ÷tÍÚcEð78tB[HFYÝvì«¶Ãà0)(âïA^g°¶¾~ÄÁ®éàYQeóHIOynèsµÌÙ¡º+)¿hÝµ(ÓßçiõEÐ(NóÑ$£\\n+¨pÊÇLÌ·ð×Æl8¼(U«a\\rÿ @¤öA2·2ã&°oì¿$F«¾¢¹´ªwuu©"ÙDböKäY\\r?1ôUy\\fT[ã`¢¼$Ub³ïãk.©®°¢,ô(åÆj¼vLD§ØßÒÚ`´«G$ëN\\n*s¬õ°{GùGóN½#±I5¬ª,l;m×Uèg,ª^]¦3ò×à_½î8zPvHÊØpÿè!*ã@:4,2r¹kVYpkë_Jú` \\r|-]*øJ¹=A¹¹Qqi*ÆäiJöà3Kç^ÕÔÂFX[ÇYÂ¡/ÍUhó{¿ÞÞ@0ÃúNð¬­Kp¢¢0×pkÞÚ ÿ´ÿÎ`Rã ¦0©¸/ü]ÝÑ8ßÄÔÿ²ÐPT§ÏdûûåÍDn^3÷)ÄD%G6ì"ûû<¹daZý×j¿¾pâoíýÐ;KFzìWSÛ,y°/Æ°PÜ#L "®ôlùk@ÇÌjÿVüÓ[¼ªÁA¿K±Þi¿xÈs[O¡Q#B¯pZsÿ>°ô2?b\\fÆ\\b²+Æ.\\r'Ç×êÞP®v,péyrÜ ÝHï~Rm\\bí§A3 Ü*ñ-f²}t±9+QÕJâË~tGBÿ¶\\fÜÐBä)É?fÆ¨ÑÏ³e"o¼sê ßke!ÆÝíJ¹Î%Íí&\\n+ÅñsA¨_ö¨ÙóþesGØòª=áiâéÞê8H!?¶Û|·ï"ykDÇG ñøÐõøÐp½CÜ-Çëw<3ý/bVõÍé¥qò¥F¡3þþvþI#CµûÍA¥QÚéîÂ¢îKwr5@\\n~sÐtBGRP´yöBÛ0%Zäv¥%°è©\7;^²9² ÞZ!i\\rÃ4ÖÍ<%ýýÄX\\nUÅØ|T øD¥è®=¢\Ù'ël{Ål±u¬8{(YÉdG¾Ò{Ç'¶#Ë²¬ÕûÕ6¡r#<Cq\\t¹ü¯~õÝÎµ`³T}ÇÑ_<(¸ûÕ}¹&$<®±ý+´æ²ëÀU©KlhûMKr1¦é;÷ç®²ÍóßBuþå(E)nm(!Ò^\\tK5[£ ¿ODuïà>¡£\\nvµa0µÜ¥Vs9×cö~¶£_MÛ.Ðõlcëµ"ùEdYÖÌSª[_jÛ¬c2£Æ à9ës¾n¥Zú^û1Ì@dÀ\\fMÕpcû>v6o±u«ÔO5:Ïô£±aðºÐ¿ÛÜ\\nâvX\¢oQhQýï0ÿâsçª¢ÇHê3¢6®~ãlÉe1ã4ûÜwÃ-¹ýàþYZøpøkÌáK|òÕq6íGòÓ~æ`ÉôËìæÈ}<ãÔ^ÅêeÔ|(\\n0zÔûCM1BânoC{»¿FãµÍ×`XúµO¼ÁÎ$ÚÂôO|©\uþ6ÙÂ6ý&´ì<bY,æ,* é²>üîÏGüFó<-u~¡·ø.5ªm&#þU~aÖ Uò¾|Çdg®°(¤b^ë*ôh¡\\r$®ÙJ):îrõeqNdVZ"mwÕ'\\fgC`ùÖªÙÓ¯þÞ°qQR\zt,`ÂºvmfÊ²7Ax`ÈÀ½±bË³¬ï<ÕÜ@ Ç2ÏÛf'TøM¹èçäÑè+ìEÕCÍøÇ±¹-U!â²wg{zÂÒÆ¬CNúá¼ÄíÒàÚsU#³ìkÌ;Ýò.\\t?d¶¢"oU×Õ½H¤_Ì¸Ô¹ùõáübÕOe¬±½/Ë&áã»qqV)à­®¥ò|\%¤Âv@ò<ç+G´<¤ã1·qÆxôÑRÙ½E)D\\bÝêÂPàÒ}ïÑ}÷ø)ü!Øy'Oê§â¶Òl¸îÆ¹4þã·Î¶ì9ßF°£Y©èorbX·þÌåµ!Bh¬z!ÇÇ^°uÇM[N}8º3ýa[ô\\r©jZÝ³Í¤­"àØl6ÔoA¯vü¶ÎÛ¯âH«T[aWÿ%ëõY8QÈÕck6Qã0·Ç¬wkùKÏÄ7\\rÅ/$<O+áQ×¬q¢úsÓ|A©6\\rðxÃÕÑåxÂ/F¡\\n7±¼Nv®ð!ÂÄ¢Q7¦Ø Öx´íùbKµ¹GGF|?%ÌW¯¯£N-M©cq(nQ¬1äU\\tu»©¡ì½1ÍÒâñ39¿ý<«n+Ê{3h÷)û,î9%ÊÅnÓ«ìtôGÑ#BüØÉ,àâ×ÀÖ\\rä¥¸¿<ZMrUW×x÷fËÒ%Zz ÑÅöß\\tvPÛÙKbg0Ødk1bõ;kªÀÁøóo³øÀ|ºu÷fDÆêGZãfÞïc°þ·âFr÷gëÒ"¯´¯L\\fâ\\f\ª"ÅLÍ)Qðïht3 ÷ò·IV÷o9pä÷ºûçú¦LW8(¶C«rcõÂàò"Ë_}´Íí)=y­&É«²wu%jÒ~ÍX"ü"GÄÒnÁPY[<Øó§ÑýN¾Ùß,UÆHLU¸.Á[×¢6h¸Æ,ë çRg Ó9G+~w$Ë¢åS%På:ù\´ô£tì\\t¨7ÈR¶¨2vSòOtî$íÜJÌËª°Ëo­ØL è+_káü`ÓÚÚÆ`9Y,'w{~ og[ð9,t7ç¿Fò×9.yM0¤<ªã²|ÔO*gJ 5í0ÛÃVÄ)|ÕøÉ  2eØ'õÈ¡¾\\n3ÍßEÙB­wxâ$ê3å iÝ\en³\\bªE7ì\\fzF¦F}þZéÏLyùã'7äp\\r\\bgZde­U]²³¨T'sF¯#¦÷Ó¡°ýRÈjüW=ëPÀÞ\\nKÃv2¨9àTÉÎ÷ý¦ÔIÊæä\FÂÏi¬)i)óxÕvæ>ËòñíhÒIA,mýÍÐ¬sñïjçÁÊG>¹p"*Äi`ÝÝÇkÞa<y+øË9*î9ò¬Ü£:0L*:öÛCó0mÍ7×â7´â¥uÅø?_c9)EMVy¾ná6Nü7¯&PÜD÷;Ëe:9¢>(~nÉ/]h êpcNÙ"ý9VFøB¾<õr¥(`l^Qò?'X<ÁÌpapòic$ä÷NËb9Ó\\rË?:>øÜÁÖ1à}@ó©jÜãá)0æGÏ9Q»ò0Z´óKÂ¸ Êjµs@rñ¾ 2~Pw[ÑÆ°\\nôT·º/\\bbãùºUQirÆÖ4®¤æ_i7þkîèRM\\b83*LÎsóè!½]vlúÛµØ³`zB¢¨Å¼ðÉæk«GÃ\\tfX>E¢ïCá¸±(þG4¬¶Is\\t½zª¢}&O%£#ªgÝó²dÿz9}$(Í_êËITïLÂrLÏÎ¨åWÜßq¢)|70BiÁAø\\fI¯Ðéc5å0Ð0c=Ù+©À,:Éî>óeà\\t©×-ÛE^Øà¦¾H3òÉåòû4î*wÑaB:Ð>´q/¿»gî±õGfvy¶úi¯èË]ó+)~K_¤_!8ç/ÏÏÜÄ\-¤ÆÞ«¹ÉU¡áìüÛqË§&µnz­Ì\\n¯+ýâ1zÁè»cC\\b¢! ïe4S²ãdC=F0¼ÑêÉ·ÛÄkXùG%(Kº7#\\bW·:YS ¢/êJ <,ö§OyM\»Nóuø-a«Ù¬Ã(liZ>W<LkuËA¢õ±æúEÑµ[4cAµlù´Û·x<öõ-Â'K¸;A^Ø<?ÄËÓô¬MFd\\r:#ç#ÏãÊú>0ñe­ÞÌ"þ¼ü*#D·ìhí4e\\f©¸sBD/+ì#6q¢ÿ¥ªáúJÙ~¯×ËQ¬ uZ¸ëÜ[·¯+|º¹^^Ì]òz' ¦,\\nj ó¹Â>ïYß J¿Hé¾à­µ¹»;m m'ïÕÿ=1N¹Ò"Qas&\\n\\rÇq.²XTF$UäÛÉ_o?'¤Áa¤håiÁ÷a¢ñ¶õ§Ý&k¸ÁóóGÊ¼ÑË1n54Ê+j*I¤dÕýóJ\\n" (º9ðK=hE5«+5AséZÂ £ò\ïa¹:¯i®JdÉÜ4Lêr÷´¡Ú,xËÕÖF\\nóçeÔqÃq¿PX)ÄÁQùVã¨ÌïãH½fõÀL{¡^¯ËÈ_ÙÊÈ*;Ç´ùò@Ò}òkj¡åZÂÞtU¼rk+) pzgqÛ ,w¾·¹øXce»¹#5BZ\\t^A¸Ñ0­wõrÐ\\t0é­¸»Éx¬5A¬êFüQG²å\\tÞRh½©ÑSN\\nBK*ê¸nãMM1h/!½±ê·VÑvÓ,6P%»ø0T`ÖîÏ¹_@üùù2gLä8uEú-ô'iû¡aLý4ÄÃÐÆ$I\\t<¿\\n±TÓauhÓÇ'»dE²ÝÚòøÙ©1ðÓÑó ï£Ðw êZQw;¶8úYmem}Ìüªm|h\\nÙëæBîqæ¬Úvò_7Aj×èîçÄ¢7&-Ú!WüüÛÎ\"/OCûÇ­zþmÁF?<Ìÿ°tuB¾ØùC¡À\eæw¿zãh°ª«È¤óH¿ö/sÞCùRÂöðj+ôeI÷~xúEçÇþëNáæ®eÍ£/BÉæ/6©ÂÆ¾Ù@£\\n\\bî¦!oàéE´\\t5_\\bÂ± V:\zy··f{ºk1a9d÷Ùfå8$ª{é|9ÒÜ¤ãÍÚQèåvûÎÝÇæg¥bO>UÃ¶õì &hÊBh1®Æôyà7=OÐLLî0lÓ¬ÇD¬ûå$Zã¨w\\rC\ô±FpÚÊÂÓ#ò8*Â$ÕÛÞ¾N¬_¶ô úÙïØÉçpCY´J>Ï[Ö£Ü ØKNèúfHí+^ÉúÙ_(>06Üëç3Ã\\noaª6M­qÞ+J_'t.ÑBj¦ÂÙwîäJZXâ<Ë×È¹X¦¿£ïÀ?Ãø]\\bßY(âzcÁæý¹Z:+××Ý²h|ÈlÌn:·$wY&ëwÐî\\\bÉ~4üüô}êm´¸{qî8«îÝ§#\\n6«ªâfÍ]ªØE"×ûAô7Çê5ëT§î\\b¿®e;ä<û !à& £ã?ôÎAH7=ÒàÙpðs`ÀúúäÎ#­¢ß:ªdýD$'ÒcÓÐ!=ê¤udÎL[ÞÞïJÇ7èzÏ¾´¹»¢dÝMÍt\í@[f]ù>ýjf7JcÀIá:ÿýÉ°x <¥§ãKÌE¹©À\\tê\\r4³ütsU¶°&¡K)´A¥\\t8¹5/ÕjDÿÃÉGÐ*WÉ³÷²Ô)V;ë¡JªôïpüüÓI2Ewx¥ÖN K-ú¤fëðZ7V/®7^õ½~Ú¡àR!Áä¤åmöþðuT§ßTðöí»±ËðØ½ÃÄ¹9rbnÒJÛ¢G¶ûiå²õ· @Y¾$XÛuãý*\\tö§-{Î»¤B "Èz=Áâ¼\\nDAYH&±®Ã ¥7UyL$gqV§ú83µ97F#KÎ-âD*ÂoµI;Á¶Q\\bÂ®eôÛÇ< J¢b©~´7ÛÔì&Wn¦ôzôýuÊ¡A@åø¾eTªS=¦«ùÆkâkï:Çó÷@'ó·CC'/7ì­#Ìü-þÑ=EÃô3\\n«ÔÁ/íODªPZ7[ºôWÖó#µ*Tâÿ&ÇEàcåöA²p­½¢KTMîmôwÐus=·²b¸¢ÊÊ=ÈßÓAk\\ngOGïêèÐ ©!d£g6§ÍÖ¼ZÖêÅ\\nóÑ,~@¿èF{ïTÆEiöû¸w¸0<f0ôÜð;Ì]ÞBùU-62´×í×öÈ#ðKËÞIà4cé:xN.ë¥×OÖãh%;¨QJ\\tK¨¥+n¶=Æê­aVÎp{4Jm_âÚÃÑ´y¾ËÉz2´±úîsýÇÈ¡MR!6\\t¨!ÿ§ÞýAßÖ¬çió§YÑ­½,äz¾Ï|´äÂ¹¿U|m§ëpTIÓ!uî"\\nÂÑ¡^g»£e(r8ÊÐØÛGg\\tl»rOÒ·¿E~a\\rKgÛò÷É¼DIô"¼âóOøZÇJø\¿ÈÞN>ÄÓÐ:ÊÖEF /úhjºAÀe´¯ª~&ö\\nw¢¯IæC9£´^HÝ¼kòhèûëÕI¹q¡Òn\lÖêäÏwýUGü~s]³¬«¸3û)ô_ëfy}8·­b=ï­ø Ñdù+ççùµS¸<Ý{õÄÔü½ç93ÀÏi\\ré ü\\tþy=Ç·é$ÂÉ)âàê¡÷ÿriÑþõöÆH1ß;ûâô+í<Ùx41ùEÏùË×¿¥"@ 'ÍÆÊkÅÊÉÕ¿/r¾ WµØÞ[ðhh#½ÈIä³¸r%N¸h&Ô~ñv¼`Eña¶]þaÙHºqÛºöløþñ2bP7øzr/q'å7.<.,~UC<yZ ²Ï¶Õ·Nì{EHE&«#¶¥(îh3IÃ/ä¢]Q2¨bÜ ¿$Ð7üQ!ªTñuûÇ:Òi­\\n/EÜ-²\j.Bkæí¾ o\\nIl,ªðB´ç¥{cÄdjYæÌº¬×i³÷ð\\t6õ-iªÖ·0b!)NÀÍ±Uú.(¨B&ê\=Æ­«¹íØñÊpÿ¤ÿý,¿°rKæt`®lù¹yXdWM9rD4mw%CFïÝ%¿Æó{}~ìóu\\b!3 úFÑúí³æl^PàêýeÎ «Ë¥Ø×5<ç²TStFd\\tï:>Z7|Ñù¹sþÄ§ö³_MdÀfÐ­6îVÚ`ôÀ a{óµÐ°ñ¦Îñù7Oy;¡B "#ö¥öÓÃùPðÇ4!ô.r½à´ÿ9ùÅ+l®Iãè+ÂÈ¶g|±wèÇÃ>ùUºé%ÒpÓ$¦5^ãý\f²­-e"\\nMê>]³bC<{Ð|âmivM÷ª<©Êè[\\b@sÕGý3M]Ç` 9ÑÈ"$(à8XxX¿ñë=jµ ìÇ×Öàue7`ÔQqboÉhæ°1HünsvïÓñèHÈ%¼ÜRâBÖÚÉJ|U{}æ«eótYrp¦§®þÔä"G?¢$nO4B\\b\ïÎOê #\\bÖ¦úBQÑ/åX«¯=S7~ËÅr¯¤,B®[îGò|ÉFùX`N× ÖZµMð¶ñ°ÅÒåÛA\\nEèþ5®Ô<Ðga¼qXâ!DX¥õ\\f¾îïêêxç\À¯êLåÙBÆÈ¯¹ÚËeÑX=ê¬óMßâ¨õKiè¿8¹¯ÃÝaLÍ¦û+¼x¨©¶Ú¾·NwâîÍz2qi°ÏÐÓóòt\\rÉ<ràìWû*÷¾éÚx73<}µÒ6ª×láìúØÖA2û:&ßµSªi}lþqÈã¬úGüýq©Ô×ÌÃÜûNE®\\tâ^HT¸%iv_Â¡ªâ4ÎzäÊS´]¥§^øãË,ë.«j|B®}zÝ\¯Hæoh¸é"~§&"^þà B¬léðªùGüjó]{ Ë¦qý¡Ö$EXÎ]Óhò2Axéç$ëfËªÝiJ$æ×JKÏw}Åá^&g.àwù/sÅ «ÊÛÄÌÏ\\fÍgXd]?¸àê<l\\n}ú×¾Ôõ7²óÇ¢¨´ |uîüH@±l SÅ¹ K5ÃPLá»4×bC%¥c¯*vÞ=wLÎ~¸§iFU¼L¢ãük¸Ð"z¶'ÿÖÈD6\\reóS\\bg<ç"xêa8,ÙædHh©åXÂ//RñCq°ÍÎ5Çj«0 ^!,+ª7q-ÀÎxR!ïæwXËÔï_\§>udÐvQÁ6"m |ÍdXºæQbÂÑ¾r8Ï­n{©ñâDCÃÍï"Ôg1ÄÔâKã<¸¾&ëB\\f¿O[Z"<pÞ5{ð^Ö\\fò¨øÿðÒ4«q/ã¯'}Jöò¦÷.ëîCøNnª7 pQìhPwùO5ÆCc%)Ì±ãûý¢û®¸¸o¡u¶°-¿M°Úè´sÍ¤4â¨#z©½ÖÖÒI¥¨6KÛkOiU%:÷&+HÇËhï>©¦Î«#à?$ÒMì¡kÖf?Äê5réF¼g¢Ï8{¤B oEß¦¨\\tÖ§D£z§ lw$BjÆÈ>W.þÀÏ|Ô\\b¡¬õ5 µßEÑäföY2"¨0G7x}@ÌÆî[»xö,¹zÑC%ÞDuµ¨`6LNíÃ$U¿¦Ã&\\tò§q!2 \ 6èðo4s5¨ê0¹HåÌý°ÏðG®#­ô¼ÐurÛ3]¾<kÆwû1¶³¾}Í%añ^ ÄÞUpý«Û¶Eè\\t\\fÆj~1)¶ev÷tk2¦ä/öDk£éA:Gª(æS±DGbËµÆ£\çÚÇúb]LÊæØ-Yã>­³ÂW ³åËdþË-¤ÜvMQ+x}j§ãÞ­¹Ö2³}óoÒ­T£ôyãSzµ{+lh(Í;úÍ®7|ûUoËU°ÉJó8Ô3rdx5°¢5H-´úÛê«<e\\bÒr<3I¿|*PtÒ´T Bªê>\¤pÀ¼N<·6ÇpÑöÙç%|Ê)1¥ëÛÜÐr+ ¡C;,©­RÐÊ|­JSä='RAú_ºäÛ°V?ºäGe#³U¬¾:ûÙßÆÕãÃS-é÷,êe¡ûc¢µÝüvánN_»õ9wû7V£±àÙ®ÁÙ¤Àì y½Å²Ólq¤Ì¡R&(x§¹e#Ý"mMr¡QÝC¾³à¥¬ÀúeTé¹ß¥Õ´È@6È Uõ·G:ãÃþ¬î²ý«åÓ\\t;ö"5Fís×Bø ÊÝol;ÃIÝ-hî"\\nÂAø °{äÁ°b--_æ·Üð>ÄWo74øY$~¯üvJ¥òË÷\\f»ÖA­¤®þm£ì6;¡õÄ]úñ¥ítÌ¼7eÚ,à'oJ\ JM^Ãßm1Îal]ÑÑ/(~Î\\r\\b¼'é\\t¡ókSDc¢oÝÚ¸¯cRL=æô¥¡JX`¨0ÉÞÂ^»QqÉ£W1ú9:ãíöMSL)ù¦gý|%²÷ßÕÉmÎRôp¡·~÷A®LM¶³Íº¸KÑ>ú\\tõ÷l%VÑù{Ý7/f¿Ç'ñ°Ñ5åñ'`¹\\r\KNZ)²Í²0¿TìµÀ¸tE§%Íü B)+õÔ¢]ËRuæámu³~À(¬Ö&§ÑzùÛ{á/,É4«©£ÚöÊaI.ÀâÞh­àÇwkaßwÃÖ241î5o?ÏÌìâ T!,·n6f²«èj÷8ã|°^éñæÐ©æË\\bFï¢£Wwm#·¤Ñb\yKe]îb*6h&P×Eªl¿í$C¶)5TMOê\\b­:2ðKy{qÇvÒGh(»q× ÜRhvì|ù×}6.ZGr¶ÁÙ-ÿð`ÞtÚ£KÍÅ_½8d©új¥/eþdqÍÏªQ°E×§ÆA;ù KU yc·k¶OA=nWÿ\ ÒúYãÖÓ!ëêªÁ¼¼Û°ÏJP@îj¥/Â&!\fb¦1TîÏ÷½éëeVhD"G@âÆËS³:ñïû¬G¤ê%XBu¹ÊÄ×Ø/èK` 6¢0ìOYýN®S!RÄ½îH¢Ù¨0÷ÝÇ=Ûc¡¬îÌ¯ò\\rk.*fPÝ ¢¸Dá©ÀGLû¤!UX)zR5íD-µùÉ·§H\\f­½å/¹^ªædÝç]Ðã\ÿç}?uÂpë·³è\\bâU¯Ø½®Øö\2võ_ïÂX5Á1Ð÷©u¢å¿µW(ÅµùgXÐ$ýÏù y´9Ðw¾âN6!ç¦T¶£0#IqÎ³s<M/óëgÎTÚ÷¹¨á·¼Âx!+à*½Yµ Øfxå´u}ÏÁ!/n¥ã§s Nûyó¡¯õ4Ôù|1+<h¬cD{ò~_óR@wxLH "Ê"âÛîöE¡./MZ8ÅÏ\\tªk¯:EðäÇÔ2­U±c2V±ÂâÝu¯¢¤K%«G8v¦H{³8Ü¾mú°\\bÌÈÑ#R.L Äáö\\tëÅj^\\bÊ·µ_¶¢¼¼ávQÏÖå{³rßïý¿T³£leOt¾®Nõ7s pÅî_óÆ@2æ©ái½m\\tÛÃôO\\fÞ|ðÎI¨¿ÖH ñÞG¹%Í\\toÊû÷­Q¼¯É¿Q7¥4·\\fKªÌ,\Q ¯bÉ}CÇÈµÏ cu¹íD@¡üZ¢øÎâ~ÑÎ($Û[§ÃgR1Zä04PSZÈ~h6éG-éV7ÀÈÃ!ñm]CZ>hw'ñ*Qh+LÚfúX$Ò\\fgï6¿pm¨ãû! ®Y8NO6*>Ó°JFÍnÓØwÐÚw,D6¼©¡$y\\n&bì¶¡ª=Ä¤»,¹¥î³P\\t¿yj©NgLH íE°u3gÞ²Q@dTëäMÿÄ 7rÉnI]#¡NgV\\f&êzwBo&Õì2ë¶\\f¥Xz;v[SÛuU¤´^î®¢©\\\b¥Ì¾Tòx=\\b=.ñ?Ú©Sa¹öæÝK×®ð×43+'¥¤I·F=é4ôMÔEK#%H¯ÛY±h\\no÷ùL «@ xvæmaë}ë¦©öqÇÉåðÂm{#PM9ð\AÅ|üÚÕ`r6 !Ì7j¿0¦+e'»iI#£Op?\\t:êl~tæCÆÛ';´Å£yÂUÃH;D¯íõðo'>ô;$LöÈ¸[©ZuJ³'DzÃÓîÍFÏ³ãÇ2YQ}bö©'t!\\bÊÈÁÝëÙ¹ÀZô±å>aTâ Dý'óªÏíS¡c9úVÌ­¯"¿ÞmÉêN¨Åæ°Ñ!Ý&<AÁ5tÐÝf7°¡$\\b}LQÏãnHPêsD Znÿ'©¯Þù9 2M/~È¥*äh©]%(l#vëÕÏ idxû}&÷ÊO\\fªª¾x1²nÉxñkþüÛtq¡;³êèq/Y7Xüò^©û¼kB(î<g7í#@ÞnR£{J¤{]LTY¨½½ËgÖ\\bCêTÝß,ö½¬''¯.Õ'zÒÃødÔ2ü©Ü }Oî:pp¯ûÀþÛþ®·dSîL«á Ì]²m °ûuQÁ!yÈ¦5³Ä(\WXßäxíeq§O}rÍ~§0®êY°,­~G¤«,De[¥¬eÃÛtpXLßP/>x\\tûk6÷@që¿¹¾@È¢eiÇ ìô¹¨üpþJT<[ì°âp/4p)}%3r§wx'Åå*FX¤p·Øsu.Nx²Wl"7ÒÚC{õð1ëDÐv«lXn}"]´ªþÞØ\\fkØ(m4P´;çúd¦±¸)99ûÍñØ½ÕÇêRìôæ2Âe,Df¥ê;§«àk@ÝõË!À]Xb²×ÂtßXÅ_ÓEüXU ð|vq>Ö¿ùà@(VaÈ[~ÊÕUz³\\r!¥¿/X&±"^÷ýùÞ\\n@M~/lê¹TL´¼À´BC]}ÄÈòPz9@6¶Hòp06\\r\¡UWO!Y+<{[·Àÿãq7§se<ÏDJùWCC,NøQú9x>ØWûü+3j\4â!\\rlvÆCcIv®Kq;§Ë\\b4ÃãÊBæ¹)|¸\Oo±\\t¿n6ù0=þ YÀ+V\\tÚù\\fvõ¾ ûá4#òFÏµ«î ¢]à¶ÜÅ©(~¶ßá÷Ùóÿf?øÌ¬-±ÆìÙÿEH{8ÆFëÊ&UPÖ<]·Q;·<àP½ ]ÉìÖ,mgmÿç%+(*Ä\óUW¨èw¼ZDÛ¸7ë%é?éÑ¥é[Y¡~m÷Úåó\\fþô¹UyäàÝªèþ![:?}ðÍ0Ï\Wîô(Ôä¶ÔºU¯ü-ËËþE0ÄÊ/wÑJ7¹»Ü£MðbÕ*o@$=­â\\tãHø9ÃúÌg¦¥ï¯-ÖÏº#Ôü¤þô«ÁÊ9|HÔSysÐòs0)ÐIÜ\ÀÂJ4Þòqeö×uJ\\beCxõÞð¸iÍnï§¤ál\\b¶\\t«#ÄÜÞ½ÛZÖyþh±¯ÈIû:©$áÛq.¶hX{;Ã¥oq´¢x4HR0úæVxF|Äò:nrwÊå*øG.ùq³B~°Ö\\nk±Ê\\nÀ};öTÓLô×/Eã#b.á¿{|ygÊÛ>~Ý¹Pû­½ºÿ}Ñè?dÝLt8[m²À¯'ß¬Öí(6J¸%Ã%' toÃ¤+@NßÐ9Úµt½@$øy/ë/òkø]äÃ[ú/I)Åzq3&½À{VèÕýÙ)câæ¦ëãÐÍÎø\\nø89Q[ÏµÒa'4>²h'Æ3¾ê%Bg¼»[D¾Ç~±Ï¾÷;Ûè0Át\\b VêháðÃèí¾M=ÁÉë û+à/ý:\\\raø=º;wAM\MFxìÉÂÒ07DmïÄxPZ@gp·Ä®ÛCCþ­v\\tëÆØ´×º.*]ãÐ4³¼;ñÕÉÅàX?*ÎÎþÉÁì[¤|pî»^M\\br`Þºä8Sç¦õàt^?Í1Aîöþ¡î !~û)*:vxKÜÔL©2ê@®3}$¦&&5Âè­¸%Åæ±I||þB £ÒåÈ(ý8°H0=cÞñµ¯6.yªµ¤$½Í5Kã+ãç¥¶Ñ\\tÑit¯æ°\ÜaÛL;¹õ6¤ùxÛÕ%t_mËæÝt½\\r½3ô}±§­o(ªºª]IuÁé£¿¯ýØmóµñ¥³^.O ;ÌhêRâÿ¾2VX[æ\\b>:Ü`K/Ñ.íèäiQSÁîiò 7O>frÅy«êØïÀ/¡B«3ëX¡eøÀÔÇMuHõ=ò\\txJÅ OÀyÔ?þb©ØÐØïha1D,hr¢v0!?à4ÌH)G>E°Ð§Fzù\\r"ni}4ÒÑ¦Ll·®ÆàäN±Y'&à@)\\n\Z¥I¢.×æùõ~üÏyÂÍÁ½e>îd\\nÍUåÑ÷ÿ4¸b}ÊÖÊù*©=Q0Eÿâî`ädEtÎ¼\\b»3Dï¸L_§oßxÕ<ähÃt·<ôóAeb¶B#P§wÆ=ÉÚ.\æNöf{éKUb:·JTÈõ0¶_|<»`{Ü4eÍFZù²TDqÿn©@ußyãzå<n@ ëdpï\önË J¢4_DûÅèÄ²¯+|ké1Oc¡¦úÖ_ößóÅvÃÓÌ§aü0¬m2×ëT:?ÒXËßÔÿÕel NPê\i|Z\\f­ç`SûW¦ïAÉYjy­%ÿö,æC?Úù &ù?ê$Düî&ÎÍfµæ{| 3,kNºOÁÿß/ÞpHç GÀAjTV£gâÄ\\b%×}9ÍG´åùØ}?.ÙùPEöµ'&Äç¶v2æÄØ0)bî(òÏ¼ì¹NjÿÈùÅîn:Oò÷Çþ|¶»ÊÄ1/aëýò1JãÁºûµ$¥#N;@lº*2[í^7YG5Âàmÿj³`>OXç863ÓTr'Ý.v{iß­aX"uýæÈÅYt¸C6£¸hÕB³5Ý)ÁÔÇtêÎ\\b¬ÞÀ¬ûwü\\n¼D§]v>{Ç»"¡M¼÷2Ù"Ã aMÎF´æ«ÊF\\töÖl1F3´Jm³1o1Z®,Ú7xÅ>Ã¦¸~K,ñ7M¾3ùá³#¤)I_ KÑû1LeÿNÈg?x7µY\\t°·1xíéD9f#È;JPQéãfkkXÝXÙé\\b¥÷Uµ®ñ+bd}+·¹z«åN{ªòÙ¸A[ügíðÈxy)Sîæë0Í8ö³@EÖþ÷ÓÚpÖ}?¦o3­ä<~KóogµÅçéRª^ÄÖ°\SH$õÝðåXç8\\nÊ^BâèÍ¤g\\n{Üzd·¹Îu}d«<2Û)iRö9Â÷Ø¢í¢Oi~é{+âÝØËú>\\rVéêWØ\\n¸`ôaÔz\\rMÉîÝ¢[P\\f«T2#-oÛsFKÒhåXÄksÖtºd"é(ÿÝAÁùó\\tP#ÅLºAÍ~ÿXÓw>Ç¥ÿüÐIæÏ¶AýD3Û]y#äzõ^ªpÝvDHß\\f×*i~-gÒhHß¶òP*"$ò§¤¡`bWqA,5äl@Â UzzMe? ¢[_=)ÖB^^*ñåO¤ÿ= óO¤ó¸G9ÃÙÓÓ'T¥\ÅJnkä3 i®¿è¥ªtÅ¨àk¬¡Ö¶÷ê¤\\n\\rIHAhÏÀïçµÑ(f:xÿ¦+S2mKGaíx¾3<t¤ÒôacÔÛ'Å«\\bb3Û¢¿LÞE|v\\tÀ¥;þ\\fNF£|kÛC|»¾º=´Î\\fÇ®\\bÝÔíÛíÇoäÙÄ_#Ñ66PBÅ|½à'HYA`**3²5úIÔ§sÌ×\\føbfJ£6EÔ\\n@u¬ºÑÁ\B~ðO6î>MJ¯ü¸(¯pOîöÃ_$WzÙÜìÂ¾V¸\\r¶^Õ\\bõÚa$ûÕ\\\fvWMÏ#fêajÍÁ¢ÁòÃ\\buB®ÖcgaÇQÖ×¿g³Ak ½IlhîhmOÕÈåÁ9.Ûj$Üþÿr3í 4|¬ð¹B\\fªujìÛ°äÏÿ,N¸¿cÉÇL2#Sr²­]½ßmpD8$W3lºª´%0Gêá¦på¬ ePn¯Æ&5XÅ<+ýµdbæ,\\nä<þÕU¨®ÕþªÌ.!Rë×C0ZÕ-gG|?Ùú«P%&|ï¼¼:òÐO¢ô¦zôö¸6=êSpÓ$ó¯R$uè&Á°QgNxoMG)ÑQï. 6\\bäÁq.µ<oÙÐ7ï5¯ra´Á5ùú83'ùPíÄ;Æf|É Ò¦À|¨¶í9Ó´FþO@<Ù4gö^'÷Q0ýÃï"3®Ä*ÏÍ¶Uf"xQé@ÛF3çØÈÿl`¼s\\fÁªéNý·ª§;¹Ê<\\t.÷$ä:ØªkßÜ\\t+i¬g-Óhw¥ÜË#ãª$ÂI®øRz4Zçg%9ª0¼`AyöÕãÜvöEü{Ç\\fd6 Y.qÌ¢~\\t=A?Ñ¬B_\\bnïÁí¤µqvV@°Úà\\bO@:Ý}Uë®x4!8\\btq:µCu,½¦N"gTr$5a_|Ea4)HN7àU­Ö­ö\±Û\\nðR¦ke:LÃSïçmu­dñ7ÌRæ´ÇÒä·8¸mÝZç%Ö¸nº0./r'´áÓ+-¯>ýòÉsèçz¥FEY d®nQþ£`Ü×´Vª\\bzû'quðyG]6ÍköÎò<Ø×õ#É¢Õ:Ê=¢¼´É-Ü5Ó¸L¯sÁ§\\rÁ³¡Ú?­=P©Ë)éÏh|Õ;_HÛXaÿ>Õ¬*d¯Æ¢VÀM¿4±U)Àj\\rËÏç²3mu'M±¯\\rDÞíö¥×;Z|ck^Üi]vºO±ÔÁàVï]\Â¢_½Þ¶Û5rMèüø(%Z¬ÒûÜªGó'GßJ¨y»6m}"²7"Í&89.óìs}óövóü8/¥&ËÓ$§ ß+}à`÷H>Â¾g[ò³yîü7þÓ+gßm}Êr@9·2´R>È`èÅ¹e"¦3 p­¥ßL¾CædßàÆÏ`tä<ç_Å·aèNË&µüLÈM\þWê¯úøXÍEèPäu4ÛÚ{Aì¯\\töó'oÏD×)Ë.ëma5éë\\b­XQò{ñøÄ&¯ÇÀêEúòÐHv!+åÃÁä£VN'à"xR-¬yÛ¤<Óçý¥D\\tÒðËÅøÖ3¾W¢Ç·ûä@eºeå\\t¼·µÀ8£¦&Lá42Re§3\Ù¸æÚÞ½y¾»¯¤Üú\*K°þÒA¼Jü1è¤DÖÜÑòÊ8Êe3©6@L«ÙÝépÓüÛ®6A´Èè©<Jô¡NEwùëxr^ä¤òÁ>tá&wä\aøü3-.Bµ?z¨ï^÷î\HõëÐýÚñ-*¶WFA¶·\\riËÎ}à«~ä) jN¹""vV5c¬`iÅ²É`áßÏµËñP¦ Ð¬q<á?e]¶ÈmzÍ@òf'Ñ 0j`|uq;È(&¬ZÿæÇ5úðK¨§ñ0ÑÇà>ð\\n½²¡\\nÌëã\ÕåyÐ£GÜûé×ÜÐÌ+D³$±Rü×Uá¡,._Hòv\\fÖSM®°yõ#\\r½t6g_-eSÇµÎFç"WÄÙò{äAº {wø±\\fÿ×Ë`èEwA¡ÈB%*ÖõÀiÌÓ»ïÒòáq.Ôñ ý)Þ§ñ¬Í\ ·nIÀÐvR # ªß»a«û$~Ð¾M c¶yÈ°@£m³æÑr­ÏÌÍ«?Å,µééRm\\b/ÐåÓnjÂåHØ§yI~)Õ»ÍV \JGÐ\\k¸\ÜåMl8?Nl±ª]b¿µåTªâRµn»÷\\r6Èwþ$x\\ré{ûP´è'¾YèÐïºí"0îWé\\t8\\nÆqõª¸\\f\\b-¡\\tqP^f§os½o°[S½ë~q­îEÌ5È¨ÎøäìõÔÜspé_ø¶xØÒÜ1ÑHñ<`{/Èeû¶WfâYå¥³=JlÐÿmH¦Å±iñ\\nôAZ³ÚD÷n¢õ3ä0`³\¡haJ\q&¦û !¥,°Y´ ¿1E°6uMwßÈ~©<\\nRÛaä¬pÀ²Ê?Ó©\\t\µQn25¹ðÛÔHÓÚa\\nÇ\òjy.%I?S<ìÿSJåtþÉðÿe66á~Kâ%K¡"í¼ßó|¨6ÖÐ¬(\\b{â@sAUÆa:Erïå§I%³wê\Q± Ý@¦DS<Ë`bÑ`'ÙÎzFoÇÕæÁ¿KÃÏG¶´kòÏÌÜ-¯;ñ²®y±ÔXæ¸ïÔ¿ñ)¬öHl\\ro#IókûD\\bY¦ü p!Ã:äïUÈÚëUìÞË®')ÀZÓF\\foMbUîu­­¡$Mrç"<2Æ;À®1Â*¤.QñS÷Ì¯>]1Z}ÆÉõåÙ3\\b¥fÜ:A Ê0QÒ\\nÊj¼±eÆ½ÇZÑ°«-Ä­µG5;g±ó}4F\\f{Ô:ç(ñõ£¡@¸ÙKòÆ=§§¿*ENXFìh8õ98®-gejnû¹6ÊG­dòÇaxú{¹r]ÊùÄþ`»,¶ømcª^µïÁ8XzU ä]üÔÔ5ÞU»Cq£JTu"Ü9½ÆçA3ù6XÈèpÊïÇ+p\\fã×4¿,÷5/ÑmÜóP2rj`Ú>>|àúyOU$Tp9Â+eó:|B»¦!{tc¤"°·=ªç­qüòb¼½ïU=ÉË¦ßr [é:Â-¬ãW§g¢¬¤°â6hÆì ÙÇÞã[Ã!¹¤JõwJÔKétôZJÛÛ}D¨:È ©UfOèxÜmmû¬ 88ãÝÌõkÙü®\\fwàßxàp¥\\t²@àH­ðei_ÝªÌ¯DïOñ4²±1FÎ;Êá\\fÖøîÐäâ»/(ºx½üb65Éá O#Ð×ª]Õ)OÞq1°3Ü£Ù¦Ù¹66R9ÞäöSåÚ!fÁ8A°±ÄÏÀ?Òq¢!ÜXÀ6#¸íÝHç"Uëzp(?fz%q%\\n©s\\nª´Öl¤ô¹\\fh~R¼á\\f(Fç*ï}}31¾ÁdÆ\\f5ÙpªÔÄ"¬=É`:]O,Sc;Õ@CÂ£å7WÏVÓ¯þ6·þ °kfOUÝL*eI]1åQ(ª'¡é0u\*\\tD!ºíJ4´cks\\bµ]áoá©e=7 ïª;ýNXÈañ®p°\\fJr(mc\ù+O*qY*U¶n×EV1Ãm »:Cÿ8ÍÇé:é^ëË>ªp|åøzYÐÙÊQnPuò²ÁÒóLO¾ÆYóþ§!Åq¢LÎ!ÈSTêZ°(ÝsjKog^ñbñMÙ½]ÑPÍízí-iâ\\fo ×ÉI»±x2&ak^1uºßö³Äá: ;Ãe¦<}F`©¹Ãù Î®ÆÝP¿¹ì\\f'ÈÉÕAÜé\\bk¨#Unxÿ3ðZ#<Ðúà{ªh¬{é÷ï¹Ru¤8Í3z c&Öcn#µwwü4¹Ôª´ã:²¡CRª^Cv£®(pª¥{V°°RÙ@4Ðý\\b[K¶a3ò6l`½âUcc5DiJL3æS>ö­UÜM/¢8¡´«h*å:ÎN&«×3Ò2ñ¾Üü±LÉþ2ÁïûÔK³èÈa¡JËÐsíKÈm¬±;¸OW¿c±^3 îõÏîE JC×4gJ£b ÔÑÀûêð:½%óGË\\fþ(3'ÙðEKÑÿ»®sKs¬6¹g?¿z_M:rfb1xÜæåw­2ã;úÔ»¬´!Tgm:´ÒLmó¢ná_ìÐÏvãÝ?Ls½Ô"|Ê$÷rrè¨Z\--=nCJ¡8ZýÑ&=½î@åFØ· ­V /dl]ÞÂÁbâ±RÎQ"!ÕÆïPKÑÏDM¼á«¿BÜpGâdù.ôSR¨âI\\fzþH5uØÊF|hcÒ©âç{íy¹¢R°=ðñHß\\fØÿÛÏýS²|iïÆ\\têtA]êÎ<¯EÙ_çnpcþ×\\fç+êXCüÏ!¹\\r¡Òg­î¥j4ðÎ\\r%\\nÏ¶?kKk'x¿&fýÕP@%³`èO,Õ®ÑVù¡\MµvdN,×®åÍ³ÂøðÒÊâÐ3g2Ì\\rjºÖfõ_ãAaêº>ÔB¼DN¡º\\r\\nßÏ`/tÏÑ\îÞ½çÊÉOfé8@ñM4*ÿË~ÃòM£aaG\xQ#Î"è.\\rßà µ,Ö·ÿ¦JG1¡Mwue´Æè5@\\nÜ\¥qR@Í1t)ÁPKí´XFÙFf¾BµÊ"OÉ>U«ï±×òã?ÔI\\bWW±^,xH\\nô$ù"%ê:ÏÏW['|eå/ê\\fjAh;s-ê,+Eý­}ÈBéNogEw«Í; kQúïçx¨Gp»T¬Â;gjD¼z¬óD\\t`\\rd?Êgôç7Aºâ;A1ªÚ^ði½]zÙçgñ3pyTPUYT7Ã¨ÛlyV ðæ¢çµmªªTg§Îri.1ÕämùH)ÞÃð\\fe¹ây8\\t.öðQWd¸ê+\\tèRU¨£!u\\nM¡FM3K7/£ÿId}þÅ-¥+KÅ\\bÏÎçw¨û?Ê2ò®ë ÷(Jrÿ\\f\\tB)ÆÀ#ëv\\r¶Pdè9U5ô%î}lÈñ½+6¤OÄ["8QJI¨÷ývÅ_l12íÃ;± Aec¯yþMxiÌ}OÈ:"íB·Ò)ØÔg\\raîÌóì.õj.9þOSæµj«þÚlw3¯È-äÜ­~þçÐß.ÚÏ1ÞÅÿàÓÛP,¢NuL\\rÅ«º§ýHæÚwdÞÍÏ¼Áo©-×Ò¢RÞxÜù¨Ä9%R|ÝËúÙ¡V«¸:&h2G¾Ñ_ ¯¿MÞ93_\\t}ò#|óaÖS;´ü\Qºø \\f jç\\fæ²îa8.¹E¯ ¶1ÒâCÖÁío@)Õ(³á¼Å¨Ò]4(äf-î'Þe¤íÛMÇ,\\fLñ`§ïË¤d&êÛ²|´»ÙØ}\\f{iªêÞ$S}+µc+xâ½sñjº|ß à.Mç2¼ÀKÄð5zÄjµÓ¼¯åt+Î"àY1 näóK]Ý?æFT:Â8tïýH¸â­éæàÅAØ$ÅGv¦\\bØkÛÅ÷ÊD<Ì \\fæÊ'ïÍgw%xÝHÐ.Èè®J°v. í':d$å';T£¼ÈÞêÏ_ì&¤µCu#\\bÌËí=Á±XÊ0ñZðo2!\\f¤Ã)µÀõ@«d´¾%ÓtìSZì«øýG¨#;½­T+î°«äÜ+úüÎòòzMúItÊçF$«fWE|0\\rU!?g,íªT?ä¿7`¾î)=ÏcoçTÝ($»+°ÞýCj@ãgèî¨~5Z2â~­wµ7rfTMèX|Bê°0Üå·\\tU~È°4@Åë I/ü#Ôï~x[#8Aµ!ÛÉF$ýØl\Ù¦ÅÛXÉ? V>Qïî|C¸ðôrn,ÓÅC:¦êÐùr6\\n\\tÂ[.:¤òÌ7ÀrÃ2ÂsE/1ü¸65Ã\\fRõ?8K\\fæ»ÅÉ}sëÖÔ°Ä\\ruZ}A´ý«~A8çüwD¥ªx|Ãómüho±OèP=¾ã6rá+¼sºæc£R8sãqv4o]ð´G]±Ûø­®Ï3-§ Âîñ,Á/Ó«\\rûñD}B9X¶qCôäÐ(qøhß9¨ê@é)ÚóFq|%AÀoá»S:ó=º¥g;À·k£Ñ\\b6xlè+T@5ªÚxckL(2?\\b]$MÜæ=@­q`¸àa\\fIJT1_k\\rv{úµçÚÏÔÈ(!,x\\tá±ØkâXhÁBTG¥öÕãBL`®¨/³Ö4»½ü¹úoÐBå´Ó=ÆÇé ïné§6¾WMáO¹XõÏák\\tÝ@ô0Í\\néQ»Ô¸,I\!Úºà3»IªæRLuá§_^ûB^Cg@''Ëðï0ï@TkÉij¼ö©É\\b°bG>¶iO;j0£Þ¢ìÜí±«º"yô£É~BP»Þd^r(Nº Èq÷ãö=<ëÄ{\Ç Ì|¤º`Îê¦ðÒÀº%-ù_\\tûw0\\t8¤7Û\,ú¥B\\r¬»! l^²®ieÚÖn~ÉÏ5Ãµ_ÙT¶15°7$sY¦¬,È¬#RÐ¨Ûëá{;ßººÚÚ°y×Ê<lQ7â¸¶®üM¿¹­çìJ>ûSíò\\rÿ«éßÊÈËwt­SZÀÞ\\t(8±¼î1Òó¬=ÂMo\\f\\bëºJb¯( ¸Ý\\t`Úf|­ñí¢Ý×%=Näöi «ý :ÜZÄbâÕ·n\\b½êRþ2ý3úvÔªS)DSR¾W^Åã¤\\fy8­I wÜûùDÕï(´>4 ¢Âý¤CÛeM°zð4ROÈ2Oij{ñþ2þÛî·uoësX£AÜÊÂv`ûHìTxp:äÏø¼á©ï.QÉ/åÝvCÓI®I¿ot'\\tàg_È:ÃXG7ZÆÙ{Ø*Þ 1dÁ@=èy×F»@¤èSÀúóN1g·¬À^÷Æzu:§Ø¸_òâ¹µN=öÜ[ànwÙç2tx¿È}²ÅJ²£þBé3Eê%\\fw÷²2aÄpH*jmï8ÚfB¯ú¹ø}@e"·-ý!ªícGV&½dóú)¢â¼Kì]»9SIÀ,vÝ¬u0t$7z¿íÙ'\\fñiÄP1ÕHÑh«ý©±cc/Æ}ÙDç¨Kpó¿¥wê8ÿV:M8£*Ï{çXúö÷ÈÛbY=u1¢ ªzÏµ­ØG\\rËäÅXòÔÍgn-7kÈÿj³4dé¤z8Ï_çc°HÜû#\\f_Î«êÙTÇ·Tð\\b\\r´ÞMÑâ¸éì;éeÂï<ÛÕLd&àhÌ$´ï7+¿þG¹rËEÐ\\n23M2)E<KZF\\r®ºôÍ¼6HØsszv_Ñt#gÃm¬z:2ëvÍ±m¬ ¦*¬_?bJN¢$U%Ö2KwL(ÔÖ·Á¾R@Ãó"Ùâ±sÑ9¹Xõç§]]ÿ¢ Íî«°ÈÇÔáe\\f¥7Yì>kxNa^2<z®Ñ8ôÕâb"4?>k§@ùc\\t«]m?o¤M@P?°×+ÅÔyëµçRâã³}¬ÒzgØ§´6º/"â9LÌjÜ@c¶Sy6ª÷I?6üIqwuzK¨õ±±¨2ÀS\ÀÃå¸§J¾þ¦ôµ](ÕÄUQýÇynà}áÒ´'[½qm:AÝ5ýÅHÛéj^·é8ÇÅÖ¹ï`ð~2±Ø©hÀ6]Í+L:M2*ïÌÿþ3Ö©×mµ"Ðuq"uÇªsMvk¸ÓÓ3"c:Wn&^ZbòYA0bÚÕÞsáÝ¥Xt¿K,:ý±QP0ÑÉ'ÅdâÄÓOÀªÚ]}ì_;ÖÅðqIs5¸Û|ÔY¿E/»JÅÅkøIO/W±a\\fMi5gï2AÄ06irjú>ñ«+BEËÏª¶`â*­ £;cR-;VþõÑ²\³GÒjªMÚÅíM±X-kÒ½V¢JÂWéõ3Ëñ\\ràO&áÎºyY\\tXBÅ`éðöõëöt©Ø _ª\\tAº;?ý¼rÌ:Hóâ RuE±K¼w¦sK\\ta?¸ÿÙ:SNÞ|mOfùN[!À\\tlÆQÅªM¨U§nW ¬E­ßæHÂ%ng¼Ì<¥«Ëtt±]Ð;øLtlÉH¡¥+1y!]ßf!£Íe·Úâí5^£ðÎµËÊnk4ïgÜ^3çLbÅ Üß¼ckp×\\b@L>á¾VÌÎÀìòæ2Èy¦zíøÉ.\\bÇä8ûý8È=o$^Êÿ\½P)uå© öÑ¹é-WNðnÂ]¦pìR¥9·t\\feû -¯û)ãF\\nt³°îÊµô2ò/>b&ªÔÒdÒ«S3Gæªî^(÷C{»¾¤µè{ºëâ|æ+ü2ß4r<ç½ÈÎ(Db¸,I÷ä®+·ÿ¡ëð(¸qö8Ùé¥pÀaYh×ys§¡x;!cQ7W`EÔ("ñrí{ØìÆOÇ/ªsÄN2ê<¡x:EüfçV;ëO¶Î×³¬ÌñkØZÄ­0è) àÉµäõK\\ncEÃò¨\\t*[J#`ôuxÈ¦¿æàÆ{cx:\\f¥|ðB¤ñÒp\\r2ÛLDêÑÑÐó0¢@Ø ÚÎx± ´UAÒ-¤7\ö"Æ RJb²â|¥$ .Øó\\fqª§rèØmá;k§¤_ÓÔÛ\\bÓ^Ï÷Î±±%óp¾2Ómfs°BÍ/ÂÕÜEïÌ¾\\rï.ðÐxz«k7i)zfÌdV\\n{7Ð8ûh96Ev_×ð{þTôéKÝÐîõëª*pµO,÷7ô5ùf_*ÕA6`Ù»EÞÞÐ§.|¶EgÂÈ^ß¥Q4ªº}Êðú@\\f%«³9Br+2ðÑßJ6ÓRSÅ®VÌLN~GUòºÃÌ;V£Õ]j¿,Òä²DvÂcCìw¼ÃÏó|g#f:{1éGóiàëi´DJîÀ¥|¬¶V¾ÞÑ?@ìw03ÚÏ½­b|­òäïÞüTa}Gl¦ÛmÌjZ5¡êPq»9\\fc}\\n5<C.$qVéYÙ\\n¤qhÎ·ºÔ&ÄÃ>z\\fçB{Z e§=\jéý²¬Óü7P·á Í}3R¯Z\\rÞeY9õnOt-AúÈO´ØDpn\\fÞç|OÃ`zªG®îß3wçSÖªëû«ãØá$p\\fnm'Z'Æ4-)5Zµy#3.ùEîýíÞF,¦p×LËùeÙô\\r^y"õs«&¿§§'-ÁïÜ4*ó6õý7YÁ1\\fbsiµÇ\\tHëæ2>ºÚ_9-Ö7'YdóPoÒ^×Z®èø^IÏ´8à6dèAR5¤ÌÑ+´NR\\n5Û¡zÿo"4wgÃ©00íª»ünÏn©=«þ¶:ù&CÛöÍ!)O2z\\r4Zð ;=`µF·\\n\\fï_=\\bkn9~wÈ1n 8\\bõúªdV Ð|ÐDdÁQ¿8­fêä °8tdM\\b i¤³Í?ñuóT<·\«¢V|¶ï¿qgM¥þP±D>à|´pàÐyÌ-¤Ý[\\fV"mM4L÷^)§ÊÍÎ¶æÓóûËG¸!tú»`¢%7#<Ï¼â÷^ ´öê@#D#¢¿µÚ©DNé©vúòE%Ù4¦edµ½Hyì·_Rrí,Û>ú¢ÊÙÂè-þéSÞ¹¬×\:\\ní}ÒZE"óÌÝÅ¨77_GöÀiüêø£O¥0ãbµÐ2Yê&\\töpB¥J¹¡âñ1 p$¸IqÍiCms$!DG©Zæ%M ÍÞäÙªòÞÀó0[V&ãO}ÅáË}îMe.bd?<²ÈaS')\ØE?q­wÊRé¦\\tÃN[ô®¶>W÷;\\rµMñ$ \\txÏË]à]s¿ÞçTâýdY3ë¨jÈ¿å"ôÞ^û¸Ó|ü°8,2äqªV4sjÑé4Íd+_Ë=ø¯aÄM¼ÓØóT#üZ }}ÉêE9 ÜQÂ\\t·¢ßÝ»Îëe¦ñö3¾Ðk\\rÝaoA/TÃêõö[¥E]zÿå¼wªpã\Ë¨y+êFûÈ`ÙÐFÛßH#náË½°e%hÃÀM³ñ@ûsÜºÊ.E¸¾0êã¡ÝDôDLOÈöUñ²$zâ»ÄØàW¢Z3¾j¶\\r4ÈÃFJÿâ¦Ë¾¥fÂHê4~(\\t¢Ü¿xtµñ4-NZ*H'6pR½f±§5û"v%Uà®wÔ\\rÌOêHm ý¿9¼çmb ­*÷b½éöªÁuDLuL&(y\\rà®N£­hu ñ@/-V¡¼®£>&Ò 0ÐøhÁT¨ôæ¦x÷Üqþ \\fEÂ\\f-q°÷Ðªjõ÷=vØ¼³û¹dlÀCK÷Å¿á\\fÆÂä8#ú¨ÂàWÑ³à-ï~\\fßC)ËÁqî¼AÜ^Ã¿÷<Owe=8É®ô)÷æ;Ã8S~¾^NRUvw³%^óÎôyÉ`ûzM,V¹S±*¯\\r½ÒÚOyÂjo¿\ÉÒîÍ?OÂªùpÚúEËsÏè-ÿß`@æD°Ï{ Ò*>ôvÉFÙZ\\fÅyKË×EÌQá*L9FæÝã¯(s®ä¾÷×$sÏ^2ÄÓôGÆ|i\\n[êKLºÓ·wÅæûf[4zw\\tÂK¶N6¥÷*'Åè¹6%,í\\tnM¸õ­ü¼óMYó9ì](FÎIòIs²É23þÒqÌ¶x×IÇD^q;*½¬®ÃfÚ-¾ýwrÎÿ¨éY$Çá¯Úß@r±*b4ä¶¸c:öIoî2î~)dÔQ0!3"¿AúåAbðQj[r¼9£3hqWz1ü_g~ÝÖ¤d¨14çõrdÉÇÚhò¨7¬Ýä_ÇW)ÂY©&S ¯ÿUÚ1± ä)Üµ\\t»Ó¢¡ïatëì¾\\tòøªà½éÉ§ÖýXUÊÖÐÿuâðVþÊ¿sG"½Y¢ËÑ;\\rì¸n«ØØw<ÕÓöQê©9ZsUzLøg¡VÐÿT0Ë±üé}>4;íqÂµcOòÙs1Ç¦¼ìÍW&øs:áM93 Ê´»ùQ½í­v|µçþêL\\f©yê0öAû5ZMk¿?yaüàòð}¦¼¹HCÔ¯ó+e°Q;ÒÐÃ¹M\\bX è´,Õîz\\n×e´iå>ïjn¨'[T7M\\rªèá(@JZÀÖ\\bQLm¶|)¸¬¥%í\\t%ëïrløYü®v~,íµýË÷Ínj5gÙw|p¨¥aËU`oÖ¨do=A¦«WyWãïxu±´ò?Ô 1<ºÅàn÷{\\b«SV!¢J£eü\\tcïlÌ èk³|²!856Ak¥°¾)Ï\\f¶ó´Ädø-Ë\\fÚZa»P¥Hï-µÈ`L·1z®ÂæmðI9®?gq`(,Ñ%º«VJËå\Cébkxik"\\n+´ÂIo8ó;¤¹Ói58_,L{ÒÓGIû¦(ÇJ8Dï=ÕãLÒî³µ¯¶ÚèÓKn$_D=õC7l6$s¥h\\b½Ê6EÛè~oHH*¦"D­êÿ?õë}·SÇÃ$÷º]=ú®(óóu\""Õ5Åu+güØNÖÿ[2Klà5r1í-*[] ÌrfÅW$ DÕ(¼«Ð³cÑ¢ûïe¯$4Ì¡æÏÆ®ÿÎÏ[-X¨qÓÆ¯8ÿcCO>nÚ0KO¢lÌÔ<è¬â»3Eu]Y2R¯ßió¸zB<>ù½ê¹ôf½vÒÙ*¼sb}S8®^p·õMá­mïS:8Z5ô×ØÇú Î~§ÎmgºYz{çe/8?µ¾h:¸FS_eLß\\rÁãèGÝôóÓ'zr0EÇÝRýN©ÁÉÇ;ô©FÅ×ìP¸£{zN9WB,£dZ¦>yÜµåÒ¹òY¢®>yqão¦PÓÉDR¾ \\náî¹S÷Hò¦3AEÀt8C÷w#h<bªITg\\f5«|Õá§ßt*xpºZµ11;"`ak#éw|Z#Æ[z®&÷ßÿKKNí\\tnk½ýD£ÑÑ`ùÑRÝ?ÈWÞ?çOu?-_¬çá\\n¤4q@éhÜT®cöÏÂíÇþDD-¸+]ì©Ìµê"VÀÅP\bXïãý{UâÏ»úÛQ¦ }ôÜ"÷\\fhqÏ¢FRÁ]v`H®tòjõà¾ÚÍMªÑ¹ë¢9·Á¸uÏãÍZxpD"IT\ã4éºLã#E©h]§OØaJYjè0<«þrCS¼üIæúÎçô¡É½NÖÚIåûä1WÚJRÍÔc<­è XnM&%Ô38ÊfÚäVáÄ+Jz>\\t*o¾ýïa¨sxD?5®ÌbyÏÕ¯z.còDmþõý#"iD5³j½ô¡?1¼\\f6kg½«àw(¶2ºo%?® +°-#JIU2ÒVI~ä«Çrîy¹Òë\\rçñW­¼Äº½ïD«2¢(ï?ïò÷,weÄøÙ±ï*µOý\MØT¤¦åâ6:Æç¡Æ÷(å³cfxOL*JO3Lw%ðóV&zÈß_ÚGÓ8UZ $³Õ£NpàAøbÿÃ;l½í',ËQ¯Ìis\\r¢J­Yò¬ÓÛm`´ÕXäeÕb¨ÄàSR®»Oê×¶¯RtCáØ+!PdçÙ=XÄzv\\b¢q.&øº¦QßcQÒöUÞ ë9zxq`DcÓ¯UEÅÞ^è\\b¦pÔ'úaóûæ}>&¢maUØÕ¾±SßKHö[6 ùÂÜXosKÒÜ±§ÒÙe\â~úYïòkôíáö>O mt éFNßU8(f°´,îfóÎ ^~\I ãwª{|:f3Ã}©«¡~¦cÏyûOþlÖnútàOÕù¦ïßøxó·Ïî2°¦Û²øjÁ¯< HÇËriÿK ´Øf|³U,úqYLÕ"!á²°¢àV©µæÎªn0r«'k×iyaD§ÇÜP{Ba¤C}ñÖó¥Ìîè\\r^VTa\\r& óc}tOpy*>ÔUÐI^¶%«ñz95PX¾²\\rPñJX5ë÷K»9­keL+GÔsZ¯¤X½¦j¬GVlâ\\r¦L~pB&Òçã«CýA5A»ýW+^IÉ3¤ýeÉP½¢hd©wdnäëèN±®­£c.tH_0²éÉè\anPGUÅ´±ÌáT;\\tÅ\\f±çÖ÷û¹Y¬ïÓYÚç¦ÿ\\tì/­°)§M¥ çÑ.¾ÝÒÈZÐ'YMùa@æMJÝzbd8û#!\\rywN2ü=É}~¬­Òù1h·7Ù©QOyvÐÞ&]¹fu!37ñrg÷ë¯»GÅÈü_°_ZÙOö~Ü©9ü\\r½G}E²4ëÔfO}¡ ­Æ¶É8Ê\\ní]6öîÿÅu[k«4Æ´ÔíDä\\bè¬3îÜM0²IDÿM4H¨L§9Bw_ßdæj¥· klZ#vÚ>WóªKc\\rkàpÝkëÐL0\\t¦.ýðülÞðiHõþ·Bòº@À ÃLÁ\\r%|Ý?lwØ«hwfM(ÝÌ»ÀOìÌù³lá«Ä[æPÖÃG®Å9G+ë¬¸$ îÙáÉysE:OhzÇ¯í4Ô´ì»¯d9 ¾MKM³E$B° AMþCó¾`õüâa·3¾ïlæô¦cV§6TïsP>ÍFüõN{èÔÌhm\\nä*lm4gÚçVÎ\`2FyéT¥¼VáÕÿÔÈ©Rá7\\b©o*]ÍÃÙ>¸BGð<6^;\\fHb\\rR¨rTM`OÜQöbw1íÐ!º×pîý¬]äNÜýÿHqÝ§h!ïôrÉ·WåpÂ" ±ÕK®fÇë/)»@:½|NOÇ^R8!ö,Aáx9Õ@á/j\Ïýèß=4lTtß¹½ïú½^ÓÖ­¬½XæK?öá?zVõ2,lg ©á^m¶èâqiSvÝÔ|-HÖÏ{sÁ-ÙëÚRÄl~¸Óbó{,'¾ÞYrûhaÇêôµØÞ³ÌDéC"\\rÒ"ÅõöBäxOä"*asé\\fÝïÇ¯º9#@ø??XÜÃld²g£Z]>ývºÞ{@½H[d¡·Ô²vÒ}ÉXÊ_=|8å±éä®ûÏ'b!=` q«pØÇºþRÏör K,ÝÕ¹pR©Gøãâ=ÛYÆÔ^_úèã÷´I>°È\\bKkXoÊ)}4W¸\\n|b¤`4c±aUØªúð,¿-VÓàWzH(2OÓZeû"UqWkÜT´!>±÷Pé9àDç[¤h}ÓRx+vëøÎõ¦}î;ôesÇÊö{mÎ®Ï;ÌoQxÑGT n]ÍFIv\\t ×üç hPHëí%?Êé95s2&n¢S}¢7Hì§E;Î-èRÚÑ¼üþìï Ü©Yñ/º6Gã±rJ©bîýÔîkÍE×:ã0Mä°k©ú©õÿl·b4¿ÅÓO£ÝÞ8n_uö<Ôx©Ç±®»Ü)TûYQSñgYØ6 eö _Â-e¨ò%Y_íS$ø :øÁîüZªwµwü©x½có@\\tw}v ÔC÷èÿ§âøæ4»ãö ðI6iCo{nd§\\rã<h2ÿóßÑºÖõ"y0zÓ?ûÎXjZå3&ÂE»ÌÆ@0f%¦sË?SÈÌ:\\b8g\\fýzCºdÄê\¤'
    //   70: dup
    //   71: astore_2
    //   72: invokevirtual length : ()I
    //   75: istore #4
    //   77: sipush #32767
    //   80: istore_1
    //   81: iconst_m1
    //   82: istore_0
    //   83: bipush #99
    //   85: iinc #0, 1
    //   88: aload_2
    //   89: iload_0
    //   90: dup
    //   91: iload_1
    //   92: iadd
    //   93: invokevirtual substring : (II)Ljava/lang/String;
    //   96: iconst_0
    //   97: goto -> 204
    //   100: aload #5
    //   102: swap
    //   103: iload_3
    //   104: iinc #3, 1
    //   107: swap
    //   108: aastore
    //   109: iload_0
    //   110: iload_1
    //   111: iadd
    //   112: dup
    //   113: istore_0
    //   114: iload #4
    //   116: if_icmpge -> 128
    //   119: aload_2
    //   120: iload_0
    //   121: invokevirtual charAt : (I)C
    //   124: istore_1
    //   125: goto -> 83
    //   128: ldc 'ùhzü0)ÇðKÝ¨¥@âåèCãä¦â'\\b,³XOyîÖ\\bnYyÎ­ª!ÕÙøj0ë!Æqð3øpºãeX4CóåµhpÏIÅÒúÔbÌHz¥°²[FK!í6EÀVÊ'¿b¬4:Ûü\\f»0ýG¿ð=\\fÖ¶Wz®{"ñvµqiqðÃ´úKê"|ðOA\\fÿ¸ø>]áñüL{\\nóêÃts¨50¤¡ª#=ã²=¼uÓÛÏvV°ýGB¼w#Skº¦×WuY4\\r%äñÐëÀý#l¬ñ-¬u1IëSÙîjúy>áVD+òÑ9RÑ¶p¯g(@ÝØÁ¥Û´Ñâÿ{óZ¼öëKè-¹f5¼(u  1\\bÒuïÍ¾Ä²d}ËÖññr¤±syD­+çÇÀo©nÞÙ¶²Øá«Ç\\fî0vî\\t\6÷¼û5­ôß4 Cw vCeÝ\\t1¶ý)æ[Yö×hý/ÅFLl¼%`Ö|þ­{hñ?¯Ø/£Ì©èÙ~EIÈl÷¬¢æçîI,¦n"¦5@j8n¹Ïñz0®JW¹±ï&%\\nþQO\\t\\fJë2aaÐ¥¾)$ÔQfbY-Ð}´öÒ50Zá£Q«IÁ¶u'r´°ÍÎ+oÙWA¼êµ(Ø\\rßj\\rd¦²RÑ*.Ò°$_â8JîS^²I+)À\\nlÿ9¢)2Üö6îÓpÚÞK0LºtLy"¤E@¿£/:¨çyo¥eFý¶F9)ß 3§X<ÿy"V­\\rsß]{±Ö¨Ë30òP(/<»ö¾"\\rjBÍ¦íyL\\bèó¿Q%GÃLÓôº'¦¼´Çöb¹"Wwåj}æÎð0ÜytUSí-?,æÁí¯× \\buÃÒ\\bnC{ý<(U ÛûÇ4¢Hco\Ë*X_¡ÖòÑÊ%bcqptíÿÏ!ùúÿ:ÿ-vU0æ¾\\fY¢áÄy2íUèzµEn=\\tß{cÕQü¨k ge*kI/À¥ÿ,?3cv¶ özÌÔ½ä*§=ðf\\rLÌÈcPgrMy¦Ë0 î¹)ÉçYÙ¿ÐJôd£oãöÁ¿G¡JrCû`¡ê2uóâ¿/æJmã$-Á½ðþæô»ÞçÍQÁ¥ó²L!^Z¡©<â°@M£ãßInBt\\fäÑ±Æ®×_oúG½étiX%Ëâ:i°ØCÄ­hFÑ{d4 âË7{¡åNÉUôºÖnö·Y\\tßóhxï»4=@ìtþX§"ä)üt! Yk\"ÍJHDä´>\\t¦Âúo7Q¹zâ{¾A(÷tòâu²ÿÎøa(©Dïë¢àÂ!Õ\5(»·£r{#Y\\fÁÇYîXwc`|\\f[ÐØîBÂaÍLºbõïz[u\\rÁ\\ntÇ:Í¿T6£QZËeåA1öcûþ8ÁÆMäºÿýb4Z3ÝD(.ò2Üü(ü,öe$LÛ¹R`8UBò#|»¡ìæ|þeÍvÊ\\tcy3àÑ½0ì~iC1õ(Zé3X~§>ÞDØ?¨,äXÇ7&L8"½¸!¿8YuLî6D3»Õ¹½¶"ó=÷ ÃÊÈu\\tK:ÐãwsüPDøh´5Õ¹¯æ\-Î­[áÿìvlPs3x½Tsµ\\f\\bËéò÷; tÞíôaÓî.¨!§Q;ø&º(ÂAO}¹Pe<¼\ÈDcv)³£B:pì"Þ±eZ09ëxÉÉ[F7~TÌCãÜgy¿svì­kÑ!Á$º\\bå lØÜÑ%jæ \\fl_¦­Î»Ûß¼­×mQßoM%ìòæ§½E´$:Wä-B+läTD´çOi þ®ñËåÉ6¿ ìNÌ®Û¼9¯-û>dkËH¬á SèÓ¤:÷ßÒ&V7Ì0UCâb][BÐ¡P< ZÚ£l7#b>©Z\\böeßH×øj­æ«ÔÈ<)¡CjÝK«ãY`×ü<W³Gäñ¬ZÓ¹Ò¸ ÐjW}Ô¨Xò9BS©àÓ¿gêÕ* \\f ªG +qOÌ,±wi|«0ä3tÇËå¸ÔÉ\\bg\\t\\n$^ÄIô=v³²¦A,§À·Ú£¥åEÇÚ¡ïìíêÍ0_öº)Ph0aPñµqÏC{Ä½;\\bvÇ²¥t\\ryGêãÌË¹~s^¹xrIÈÐ\\t«xÜ«zQHÚ,U$UÁÌúKôË^æy¬bùº¥NPÅVý9%îÞóm¦Gåc»$Á['y&1}<¹ô¦dÊ9\\f¨\\fgdÃ´Dûw#ß¿aû¡Ü+2¯Å¹µË@WI-Aò>l1Ài]Úl9Ù!|Z\\rBåFYbFØ.Ë¶fùó1åYh¬e%};8jÏ`µ­ùó0S´Ê¯ÍAuÔO_§à1JrVµ^:¦3zïza¸_ Ðç6Ê¾ÆÉvÚ´E¦aä:Víz.+©²åX¢ÛÖÇ<«uf9+÷Ö±ÚdÚ{r©wÛÐ4ùWZ½Xû>ªt=pTL6ÀÛ¬§w­àco³­M´fGù\\tïÑ¬jß(:[nÚãòÈ®¥¢GøLl,²RËÑ»d­V¾\\t'\\nîÜ_!Xet®@ånïåXáiû4B.Ý\óHqjtr¬ÙÁ£1Ã\\t Å]>Û°.ÿÁÆû¿ª]áªX ÙmëF{h;KÂy¿Ìa_]îÎó´}ÁXª¯Îa±i·º&R&7¤ÔOõÉªØ­ª,¹\\tÅÿáw¯©Û¤Wé7@~úo2F½7Æ)®ÜûÔ<©1|>Ò¹Âè Ç UíÙÄþ¼Ý\\t'òÚÝu®ÛüÒõßø·èüstÑÈè¢¤ý;4äÔM (\\r]ú»Pve\\nERo4<i!KA&.¡bº\\nÇcFîÕ­\\n!ÁFÒ0rR&¶9G\\bDüÀãÙÒÙ§DÛÜcjKÔ>K¸e$¬³tÞÀáÍÉÙbúìVå³ÁÀâK×ÛªA-:¨Ò?n¼Ï@aLÌ=îoLI¿xLÀ>}êIé3±>)M¿JíQNå<üPB-Åaå\\f«ÜmçÜ6ªÑÛûü(z®+ZÎã&-¢ýÓ×r[a³8¹Bkëã\\bø\\f &¢®9f.vã\äkÈJæ¡Àõª±~ºÎ1 ëîu½7¡. õ&VËBæïFxG\\bHmüËá¯âÑZ=´têg7¡ºåà*{ûx/ÞÉ¾'X84ÝORµÀü½h22¯­÷fÙÚ'÷RÅS{fáÜÍ½G1²j%¨mlëý}´ÑÁç^4]~Spº¬¯QU#²uãS®´=ÏY'ITQsê½*JK°iDNçìJ$½Æ­ªáo_¡ÔÉB:ÛV¥f#Ò®¼mÎ?j¼ã®ú\\tüñÇÛõí{×75Õã©ÌwÞRiY»q\\n¹ ³âZ%Ê<91exÝá(Â¦e"µï5bÎÓ7U­IVlzDx9¬F,'·D¬ñÂ\\b\\f+>'t&4dÎÞÿ[¸m¯:ÉtE@|dð\¥æåò%D(Öêñ÷8q³*t\Òdüïúv_>$îP­Aé9ÃÌz{¾pïñûÅÒîØ%ÀìfT\[c®þOb{$JÊ¸³ãóÉ\§6pÉíkj]Caë^aÝºöÉ¿djþ_»Ò*Ð´¥hÑËdp*´ì©z0?Òä6$»ý;N¬Ë»Xø~(0Ô&m\\f_7;â÷¦xßFÚ^SSÎ}moçÌ\\n+\\føXA\\rìêDèÇgÎ£kª¡0råóGrWX>´¾¢êÒÓ®R¨IÙËë¹ÉÎâÌ"½ãSÑZ^E ¢?í¡«l;Üí!µÞâ4þòã5¸É"áQ¯~/1Kn©Wt¥hÔ'¼9éã\LkWö\0m±äuë@b@ókÊ¬gR=WÆ,Õnÿ¯m¥[Ùcú`éé|ðp<²îý_å«¾æ|ªÖhÓ£ n¯Ç¿|rº½Á6µôíÀï·Ò}Su0(Óg4úoÀ¤Ð7­yÑeB¡gâ¾ý*Dõ^\\fUF+¢ðJñ¨J\\n¹Úñ²QT¬£ùq+é±F)Àø<ö³c¾$ÃÅaì>1"'Sùâ¹¾C¬Gô.üíY3v®H6¤þÜñÿ[<Ùo!Sè@3ZÉ»·n8<3[þe'øØ¹Q+müÐbøÐ}³)÷biÓÀeÐ%¬\\rZF#;ïM÷ä¿@év'®ÂÁÍÞº õáw(Ô¶@jüÄ.Ô7ênØÉ$ö¬«È"ô<+b\\r!¶%é±ú&2&LWÉkP°Ú²'v~ÒÑCÃ(ØU½*¤0,Þ"¼õñL¢yÌÈeÀcwã¥LW-\\f²ÞíP¤\\nÐ`¢pÖbôz85·Ö0vQ²·¬¼ ê\¾¹:Ðß_z°1çAØ Î~©¸#©ülÊ|r¹qdeuð©TÚ\\tËçÇ­"ÍÆn&Ô:/âÌ­^ ¦Dó½UD#}É± òú¯ÀÖQmzÓJ|2ÿ?¢y&_â±\\t\\rKÕ%4â­yê+]ìºµ§ÖñSB#qDÆÕ5\\fOsÂQv¿X}cWÀsTTpÁÀáÏ×¹w9ØÙ®BçUas*»ó?¯£(8y­ßj'¢÷&D ä]µ+ áªU*ìi,õ |ãi}Änì&M.L}¸µðfvOA:KâëËlöëÁSìôx0'b¬íùâD*?¹B­.0F\\tiýÙ·<Õ°?ºã#­ú+É7¥F\\f¨j;0ç½^®ÆÂ.Ò¼$"á{×DF;ZpÃ#Ñ)!Myò« [g¹Ü°n½g¿XKÖàC5ÖH½2£ñ¤mÊ¬ÀÄÏ®û\óVLÄ.Óâ6¿dMµÚ×g4ZR¶P`s:°w(½[xeVy i-yAÏ¬«>§Åguê¸ü^-¥V¨nV\\nFGË^p,ñßKÛÊ7¯û·ÑøBç²¤ïÊa+N(ùß¹.}ÍÌBª×§ef[@aÑêu=bvÌ*)T»Ë^CªQ)?4|é¶£;«kÙ¦K ÊÑ°¼µ«|å_ ]fÊ\î¤$G×{äødÿA'ñ"^vÒLÀÖØ`ø¦ÌÀMðÐÉ2ììÃCu[?A(~QÙaÔ1õøÅû\\nÁzrÂ°XÏoiuÛñÔ¯!oàæôZäíà¿áÄTþ éÔ¶Wì9Ês;dóNÒØW%M¥ÅUcC[Îþµ$É0ôKüd)¼Tò_Ö¸Þ$q!GÝýDÜJ®â6»9Ár8t`T^øQ£dÃe]X¤,Hl<¯³ÿî)¨ÃSTÏEÖ¯Ù9·Eâ«èpM6Ì>BIÔè:{Ó_ åùæÍsºÊìå®$ø7=ÖãÁlâÐ¶· OÞ¬*RàTÃhqdqëW8ËÆZ4Ujçè\\tO´m¨5óÒÒÓºmiù\\n¨q6§Øñ8BY½¸\ð¿«±Òüm/Míb¶\\bKPGLfsûC6Á×ã¿yÎ#ôÞôýªxþEß$¹6ÈßÄ¢2,\97ÂÙAÐ[ÂÑð£áÜ]â&T'E±ab:Æi=¿gæ#¦lç±òCÃ½è"$C´ñæ½fºfôttãñÕ<V©~VÂþÀq¦vDî|ñ¨blùABâÀ±¨[x3¤8Pó$ïiúà]_+úÄE6bºj»â·~È÷¬á<O,/5v?¤$_»ffZÁ0¡|§tÛ<º\\rËB¨\\tÅd>ÒwÉBKc?z\\tì#°Ñ;Ën]IÞ×9ù©e´9V>+ÍÏ;ÆÄl.Ì%eã´¬ºu6Úâ×#î)¯­¹PÞ°3¶a×ïò2k-ßäFÿj£ZØVmPÕ¹¥ÞQiW+\\rÁhkl1ÓVJ+[Òs,Là+¹õX¨ðx©öM2ý¶±£?6ðb`°_\\rïè¾Õ^40zÖ_\ÙÍ®ê\\rL^ÌôQnÈbTÓP7Äwëç÷óS£X*ÿå1ô¡A[×·é6$¨mHwìªfâ@Ä&kJyØgÇ­j=½}vWôè,¤R<þÅÔÈpù]\\fÈùZkæcû©Ö|Y-wt?pn23r¼¶níòÌ¹çKoPnÄ/\s6k¥º¡X%u%gsÒpÀ¥ù4ïOêó^É7TÜxà÷\\nÄÈzcÒs§OÈ`{+]³ÃlÒ\Ë0Êº ­º,Z>>@¬]PÂãìàLW|¡Z2ìF¾»ëGö\\fÚÐ«Dògãga?9U(¶ß"D¡^-üú+ÒíÈè`¨óíÕ?FÛ8ÏÉØrðM_Vìø\\f"eò?C4ðç\\tùÑbÞ§P©ºeãÕ`×²ü :\\beõð\\f$åûÜyé\\rÝñSnçè¸\\nnPö'(SÁ®æ¾¿±Cj_Æ^ì¥±9éWo7K$¿hpÆXå¡ï,W¶gø©Þúí,éåßÍKg¬ÆÌ(;Î£Nzoâü\\t³8;üºPE<ßÇEÈ³Éä(qCÌgýw|wQe¥­­ã¶úSäÖÝ<J;º-+É²6\\r«³]*Ø_X¸I;àÃÏ[Ì¿d¾ëîwQZ,\\b*þ¹HµA®ëñ»4<þ{Ú+Û¹É.fìæËÅAX=mÁ\\r¹¬!h&\\n ÍáB[0î[z|^©ÊÊÌ?×b -¨wÙa\É}Hq<ËDIP)³}\\rÆÜºåBlU31ñTCÁ*¾Æ¹\\n«ú^¦HÚê­HsCÑî <¦&S×ÏÍ%ñ5ÝÜË"lö÷ù¡¨Þ×$X÷.?Ù^óW|w©þðJ9Fz7ÈÒòt§SAví¯LR'[j¸ÖÞ:NòÂ+º{ùd8Pz þ5<L!Al9Üeá à¯J«¬FÚ½êeñ#qaþXÄÔÕö-?Ì\\nd&;ÄËí?Þli¡CGâdæçJ~"õÝUï\\býv&±D»Ñç:4\\f¤acÅQÖÒhÝ­9àN®\\bXLÃóÔnÓ¦|óyÀç´Õ·ñÔ"ÿ«3Z.ìà­ÿCh)ÐõYëæ-Ç|\\r\\tÚDtyßt´·Û}8~T>¶AÿvI  ¡P2ZVð}öt³Û,N´ÞA.Äh\\te4*8Þõ\\n'À:Æ#SÂ_K\\f%fÚáÅym©öÐ¥×&ßsT<ðÖ\\b?9ü¯Êõó+õ.\\rÔB(\\tÈaRãíÁ¼ãîÜÑ¨d1ðpkqBQSe\\nFÚ\¿¤J*eEä;Q¹~{,ÚµÖ°¾~.)ú_º¸?L%ug1ÐÀS£/ ¶àÇ½]Î.\\t7 ÎDÁíHD¹Ü7l®q@Øm,9u±J~Ò1ifÑ)HR>ó]Æåá]@¡È¤Ka!õÊüP E#±øþsÔú0ÒL=Ö}$J/à+eê Ì&-êäß/ýöé<,+xI$&,B5Zò× |ÃW&s\\fïraZ½±)¶H;®«¥*üêávèÿÜutVµÈF~dl9ÑØn%2!jP{0¯A¢XPOêáE=÷´ÍFô4õÒ¯Ø*Ë29á¸¨3Ò»kY[}ýî'GPv¼4Í À(þöx83"Â4êÈ]ç ù®²Ã·a-©K#Ù{I0&z¾é\\t÷è¿t£ôÀEìpü\\b"ÒE.{V¹Ñ¼iNbÆ ÒfÈz£fTâÖ<þg*Î>WHKEÎàÁ©>O²b§Ð\\n-&;gýÀH²4Ã8¤£è%Ï¢f>ê^TB~ áIhl\\f­Á´[B\\f'äeºª¦¶{+þK}E"c´Dy3ßº&ÆÑ£§é{+/=ÇD×v13(³EÜpï·Öà#\\fÑéÜòPÆk¹éhåÑ~`Þ2ÅU^F,¥cëòU£<¾ë|vÝGhÃa.ìèdíÄH_ø©7¯õ°{à¡ÿ¼tjÞ¼iB[ºì|Ê¢Æ°«ÁÐ¿\\b^¤äò<¸\\n¾Ýtß(^e\\t<z¨t­ðÕóã¹ÚûTÄlÏðb­\Óc D(a©¬b(ÊÙË@­«2\¸®áÂÓ¡\wù±Ê¡ÝDÈÓp`ÛC0PBW?&ëÙYÛäï«\\f¡ajâb«îKMþ_?O\\tù=6N.ÒJM})(.òÜdG±¹Zü±-ý¸ÂÑ±ÑD¿Uh0äT!ç[^ó4m² þº¤*~xU©Þ<\bJÛyÏ·ÿIVz*­3røM&üì.´²ú`vÀdªLNÎÍkg­¿f½vjH^H}­Òä¨¯ì=3gÎ\\tÏØD\\r¸\\tfñ\\n&±FÂÇýèÈí©,j¼fáHÙ\\nöã¸ª}L®3áÀPy­>0êt$F5\\tV)ä°?Ï,ËÅæi%ÍqÀÏ*òRPë6¼ÆÕÂjþ]'N¼¢É7«çÂÚÛnÿkmlnÛ]Q0sÒq×KZ'ôJ¶¹ç¸ø®äiW`5iÐn+%4uÑ<×2àbîN®P`%XrT·¼I]Ä?>ØTà\\n²ñña¼¾!,skÁÊ#Ë~VCX±«ý¬ÙñÃî'Kiö=«­#èB";ã^¶ßÁÿéT=A%ÍÅÄêûì*¥ÂãX±.6}Ï4´\\r\\tg°} fC¡Ò üÜ]xî´3Ki<RNHðkVÃ\\fNü%Íà=«¤â0 TÒâB»Ú*ðÕ»JûvR}ô\\nôU+uCÐÈp½¿V-qÕ\²§§:Wg£\:¤k«Ã­"i >0Ù¾_&i*{<ÏÎWs&á¥k((Ó£mÊÑËñeCÒWw¢>¬o!Å¸\\f4½\\b%r\\r$pÂÝ!v¥}WÄûõdMÑåEGrAñ;º.vÁµjm«9\\fªo1[P%H«\¯¥ïo$AæguÆ2Yì>ÃwÐ¶¥(Ø§ÒÉ!2¢öÇ¡f{zäÜ²¿°8°u?ÿ·ã+²c´}ü¦Öª3:û{!(úNñZ?Á³¡ÒéðóÞBÌYÇ÷í9SÀc<$\âô9$ÅQfï$Cä{ÇLLÄYL\µ£ÙCÆèßãÌÌcSÞU>Ê»¥F/bÆ¸JôùÃ©®¹#ASKßuÐBÍ¸ßF¾.¤¹®óV4oe6C¡£ãé¶xmØÍ¨Uµú8ÜùH)Ç¸ìü£;ûWÞC9ÑñKdvÅ\´)dIñáÜAp¡ ´¨ 5÷7ù® Ð2Rí«Ü4CÔQ·]w6c¾/N$s»ÿÁ+¯òJærT½2M|i´Ê¾°}öÿDl#Á.×øãÃÞYX~=Ñ\\tÂ"Ü4ø`å®ºqRÏ7øIÍ8<¬<Ïd­Ö½ê´ òÙÁôÊE¢®ÿ}øéPÃ\ÞYZðÉfP¾heöÀ8ÃòÑ\\rbªB\\fíc½F*qRRà©ÉÏÍ¨vÖØ,Z¸îÇóJ1<K¢ÆÕóÃ¹"Tïþ¨¤ØEàe §¹JQÂåÚ¹@¤u6®ñÁApAoþ2ðUçÅûû=HÑ¸jØVãØ^]ÌK[¹»&ÚtíÍûD9ÿ''\\nô AÍ=I_ $ÇmÔVS¾ôÏËg'\°ë1Æáávîd`u>\ú1QWÁ#gP##ëÈ"Ô)\\b&\\b'·~ØÕbËRè}~·ðÔíÒ$Ù·ºÉ÷ÝÓù-'\\t/3ªlx'¹#ÑlxL¸j=Æ¢\Þ©Ë%XM®|¥·MO.ö{ ÕîzÉ°}ÐZ;1Hj\TA(¢ÃeùöðTå`ÁR|eÚRÅ¨ »zJ"BIQ(æzo^oÓY\\n{ò Ý{¯Ç³ß9¯ñõ´Û8ÉûkgaÙÆ´\\bgJRZV]£q%î¡,AßâèQ·O¦ ®½eøùÒ cY¹ÕdÌ\\n:f»ã*îú$E~;«¼á/^,2¼ââ\\f©±±È\\bX·ÔÇk¿9/¦çªÉ0¤CýÂ¼îgü5èièÈÒn'1cÇÍ\\fÝ¬FÕÎÿAÇyÔ¶Y©Ú,ã«vmèKm6îïhfð¯R%T[k!ÑeúgëÈbe ouX¶i²+÷¦òbÉ|+gù2\\t¸¡\\rrÝ¾?·ãlib!rØc®2´±£  )·I¨H=®Ør0éÎßËYo÷\\t«,ã`§V\\fõx!þ±×¯&$ô©Ýç8ómCöÚ²,â®âp®BZ¯ýfõi||UQÐ$hì\\tw!Ùþ*¢Þ*rÇv90U°ð%¢4²$àóMÐ,\(É/í}h!ÒïHz±¥qÊËÊ³!ÝGÇµçx,áþ_íùMæÓZlDö¸ìú/hÑRÀgmrSr5Ý¼>QKwê! þð"ãC"v]k¥LXÝFû2éö`A5Ò5[ÖRUy¯´] s2?ý©Ï\\n]àþ¯n1ê¶\\rAÜ&-$ôÀnáo!²ëÈMRR&·\\tÊÊå¬UÌ\\tâEÖ;fÛÙ3\\tÜÈíÎÒÚ£\\t'Õn)q;Èw'
    //   130: dup
    //   131: astore_2
    //   132: invokevirtual length : ()I
    //   135: istore #4
    //   137: sipush #8929
    //   140: istore_1
    //   141: iconst_m1
    //   142: istore_0
    //   143: bipush #127
    //   145: iinc #0, 1
    //   148: aload_2
    //   149: iload_0
    //   150: dup
    //   151: iload_1
    //   152: iadd
    //   153: invokevirtual substring : (II)Ljava/lang/String;
    //   156: iconst_1
    //   157: goto -> 204
    //   160: aload #5
    //   162: swap
    //   163: iload_3
    //   164: iinc #3, 1
    //   167: swap
    //   168: aastore
    //   169: iload_0
    //   170: iload_1
    //   171: iadd
    //   172: dup
    //   173: istore_0
    //   174: iload #4
    //   176: if_icmpge -> 188
    //   179: aload_2
    //   180: iload_0
    //   181: invokevirtual charAt : (I)C
    //   184: istore_1
    //   185: goto -> 143
    //   188: aload #5
    //   190: putstatic burp/Zgsk.a : [Ljava/lang/String;
    //   193: bipush #10
    //   195: anewarray java/lang/String
    //   198: putstatic burp/Zgsk.b : [Ljava/lang/String;
    //   201: goto -> 364
    //   204: dup_x2
    //   205: pop
    //   206: invokevirtual toCharArray : ()[C
    //   209: dup_x1
    //   210: arraylength
    //   211: dup_x2
    //   212: pop
    //   213: iconst_0
    //   214: istore #6
    //   216: dup2_x1
    //   217: pop2
    //   218: dup_x2
    //   219: iconst_1
    //   220: if_icmpgt -> 320
    //   223: dup2
    //   224: swap
    //   225: iload #6
    //   227: dup2_x1
    //   228: caload
    //   229: swap
    //   230: iload #6
    //   232: bipush #7
    //   234: irem
    //   235: tableswitch default -> 302, 0 -> 272, 1 -> 277, 2 -> 282, 3 -> 287, 4 -> 292, 5 -> 297
    //   272: bipush #41
    //   274: goto -> 304
    //   277: bipush #15
    //   279: goto -> 304
    //   282: bipush #99
    //   284: goto -> 304
    //   287: bipush #73
    //   289: goto -> 304
    //   292: bipush #82
    //   294: goto -> 304
    //   297: bipush #33
    //   299: goto -> 304
    //   302: bipush #94
    //   304: ixor
    //   305: ixor
    //   306: i2c
    //   307: castore
    //   308: iinc #6, 1
    //   311: dup
    //   312: ifne -> 320
    //   315: dup2
    //   316: dup_x1
    //   317: goto -> 227
    //   320: dup2_x1
    //   321: pop2
    //   322: dup_x2
    //   323: iload #6
    //   325: if_icmpgt -> 223
    //   328: pop
    //   329: new java/lang/String
    //   332: dup_x1
    //   333: swap
    //   334: invokespecial <init> : ([C)V
    //   337: invokevirtual intern : ()Ljava/lang/String;
    //   340: swap
    //   341: pop
    //   342: swap
    //   343: tableswitch default -> 40, 0 -> 100, 1 -> 160
    //   364: sipush #-28070
    //   367: sipush #31943
    //   370: invokestatic a : (II)Ljava/lang/String;
    //   373: putstatic burp/Zgsk.Zk : Ljava/lang/String;
    //   376: getstatic burp/Zgsk.Zk : Ljava/lang/String;
    //   379: sipush #-28069
    //   382: sipush #-26140
    //   385: invokestatic a : (II)Ljava/lang/String;
    //   388: <illegal opcode> makeConcatWithConstants : (Ljava/lang/String;Ljava/lang/String;)Ljava/lang/String;
    //   393: putstatic burp/Zgsk.Zk : Ljava/lang/String;
    //   396: new java/math/BigInteger
    //   399: dup
    //   400: sipush #-28068
    //   403: sipush #-31193
    //   406: invokestatic a : (II)Ljava/lang/String;
    //   409: invokespecial <init> : (Ljava/lang/String;)V
    //   412: putstatic burp/Zgsk.Zh : Ljava/lang/Object;
    //   415: return
  }
  
  private static Throwable a(Throwable paramThrowable) {
    return paramThrowable;
  }
  
  private static String a(int paramInt1, int paramInt2) {
    int i = (paramInt1 ^ 0xFFFF9258) & 0xFFFF;
    if (b[i] == null) {
      char[] arrayOfChar = a[i].toCharArray();
      switch (arrayOfChar[0] & 0xFF) {
        case 0:
        
        case 1:
        
        case 2:
        
        case 3:
        
        case 4:
        
        case 5:
        
        case 6:
        
        case 7:
        
        case 8:
        
        case 9:
        
        case 10:
        
        case 11:
        
        case 12:
        
        case 13:
        
        case 14:
        
        case 15:
        
        case 16:
        
        case 17:
        
        case 18:
        
        case 19:
        
        case 20:
        
        case 21:
        
        case 22:
        
        case 23:
        
        case 24:
        
        case 25:
        
        case 26:
        
        case 27:
        
        case 28:
        
        case 29:
        
        case 30:
        
        case 31:
        
        case 32:
        
        case 33:
        
        case 34:
        
        case 35:
        
        case 36:
        
        case 37:
        
        case 38:
        
        case 39:
        
        case 40:
        
        case 41:
        
        case 42:
        
        case 43:
        
        case 44:
        
        case 45:
        
        case 46:
        
        case 47:
        
        case 48:
        
        case 49:
        
        case 50:
        
        case 51:
        
        case 52:
        
        case 53:
        
        case 54:
        
        case 55:
        
        case 56:
        
        case 57:
        
        case 58:
        
        case 59:
        
        case 60:
        
        case 61:
        
        case 62:
        
        case 63:
        
        case 64:
        
        case 65:
        
        case 66:
        
        case 67:
        
        case 68:
        
        case 69:
        
        case 70:
        
        case 71:
        
        case 72:
        
        case 73:
        
        case 74:
        
        case 75:
        
        case 76:
        
        case 77:
        
        case 78:
        
        case 79:
        
        case 80:
        
        case 81:
        
        case 82:
        
        case 83:
        
        case 84:
        
        case 85:
        
        case 86:
        
        case 87:
        
        case 88:
        
        case 89:
        
        case 90:
        
        case 91:
        
        case 92:
        
        case 93:
        
        case 94:
        
        case 95:
        
        case 96:
        
        case 97:
        
        case 98:
        
        case 99:
        
        case 100:
        
        case 101:
        
        case 102:
        
        case 103:
        
        case 104:
        
        case 105:
        
        case 106:
        
        case 107:
        
        case 108:
        
        case 109:
        
        case 110:
        
        case 111:
        
        case 112:
        
        case 113:
        
        case 114:
        
        case 115:
        
        case 116:
        
        case 117:
        
        case 118:
        
        case 119:
        
        case 120:
        
        case 121:
        
        case 122:
        
        case 123:
        
        case 124:
        
        case 125:
        
        case 126:
        
        case 127:
        
        case 128:
        
        case 129:
        
        case 130:
        
        case 131:
        
        case 132:
        
        case 133:
        
        case 134:
        
        case 135:
        
        case 136:
        
        case 137:
        
        case 138:
        
        case 139:
        
        case 140:
        
        case 141:
        
        case 142:
        
        case 143:
        
        case 144:
        
        case 145:
        
        case 146:
        
        case 147:
        
        case 148:
        
        case 149:
        
        case 150:
        
        case 151:
        
        case 152:
        
        case 153:
        
        case 154:
        
        case 155:
        
        case 156:
        
        case 157:
        
        case 158:
        
        case 159:
        
        case 160:
        
        case 161:
        
        case 162:
        
        case 163:
        
        case 164:
        
        case 165:
        
        case 166:
        
        case 167:
        
        case 168:
        
        case 169:
        
        case 170:
        
        case 171:
        
        case 172:
        
        case 173:
        
        case 174:
        
        case 175:
        
        case 176:
        
        case 177:
        
        case 178:
        
        case 179:
        
        case 180:
        
        case 181:
        
        case 182:
        
        case 183:
        
        case 184:
        
        case 185:
        
        case 186:
        
        case 187:
        
        case 188:
        
        case 189:
        
        case 190:
        
        case 191:
        
        case 192:
        
        case 193:
        
        case 194:
        
        case 195:
        
        case 196:
        
        case 197:
        
        case 198:
        
        case 199:
        
        case 200:
        
        case 201:
        
        case 202:
        
        case 203:
        
        case 204:
        
        case 205:
        
        case 206:
        
        case 207:
        
        case 208:
        
        case 209:
        
        case 210:
        
        case 211:
        
        case 212:
        
        case 213:
        
        case 214:
        
        case 215:
        
        case 216:
        
        case 217:
        
        case 218:
        
        case 219:
        
        case 220:
        
        case 221:
        
        case 222:
        
        case 223:
        
        case 224:
        
        case 225:
        
        case 226:
        
        case 227:
        
        case 228:
        
        case 229:
        
        case 230:
        
        case 231:
        
        case 232:
        
        case 233:
        
        case 234:
        
        case 235:
        
        case 236:
        
        case 237:
        
        case 238:
        
        case 239:
        
        case 240:
        
        case 241:
        
        case 242:
        
        case 243:
        
        case 244:
        
        case 245:
        
        case 246:
        
        case 247:
        
        case 248:
        
        case 249:
        
        case 250:
        
        case 251:
        
        case 252:
        
        case 253:
        
        case 254:
        
        default:
          break;
      } 
      byte b1 = 47;
      int j = (paramInt2 & 0xFF) - b1;
      if (j < 0)
        j += 256; 
      int k = ((paramInt2 & 0xFFFF) >>> 8) - b1;
      if (k < 0)
        k += 256; 
      for (byte b2 = 0; b2 < arrayOfChar.length; b2++) {
        int m = b2 % 2;
        if (m == 0) {
          arrayOfChar[b2] = (char)(arrayOfChar[b2] ^ j);
          j = ((j >>> 3 | j << 5) ^ arrayOfChar[b2]) & 0xFF;
        } else {
          arrayOfChar[b2] = (char)(arrayOfChar[b2] ^ k);
          k = ((k >>> 3 | k << 5) ^ arrayOfChar[b2]) & 0xFF;
        } 
      } 
      b[i] = (new String(arrayOfChar)).intern();
    } 
    return b[i];
  }
}


/* Location:              C:\Program Files\BurpSuitePro\burpsuite_pro.jar!\burp\Zgsk.class
 * Java compiler version: 21 (65.0)
 * JD-Core Version:       1.1.3
 */