package burp;

import java.math.BigInteger;

class Zgt7 extends ClassLoader {
  static Object Zn;
  
  static String ZO;
  
  private static final String[] a;
  
  private static final String[] b;
  
  static void ZR(Object paramObject) {
    Zmtf.Zx = a(8861, -10509);
    Zmtf.ZH = new BigInteger(a(8856, -24860));
    boolean bool = Zt2e.ZN();
    try {
      try {
        if (Zrhu.ZJ.charAt(Math.abs(((BigInteger)Zkco.Zg).intValue() % 32)) > Zkco.Zz.charAt(Math.abs(((BigInteger)Zb2k.ZZ).intValue() % 32))) {
          try {
            Zmdm.Za(Class.forName(a(8855, -1054)));
            if (!bool)
              Znp.Zx(Class.forName(a(8857, 20705))); 
          } catch (Throwable throwable) {
            throw a(null);
          } 
          return;
        } 
      } catch (Throwable throwable) {
        throw a(null);
      } 
      Znp.Zx(Class.forName(a(8857, 20705)));
    } catch (Throwable throwable) {}
  }
  
  static boolean ZV(Object[] paramArrayOfObject, Object paramObject) throws Throwable {
    // Byte code:
    //   0: invokestatic ZN : ()Z
    //   3: istore_2
    //   4: new java/lang/StringBuilder
    //   7: dup
    //   8: invokespecial <init> : ()V
    //   11: astore_3
    //   12: iconst_0
    //   13: istore #4
    //   15: iload #4
    //   17: bipush #32
    //   19: if_icmpge -> 1355
    //   22: iload #4
    //   24: tableswitch default -> 1348, 0 -> 168, 1 -> 205, 2 -> 242, 3 -> 279, 4 -> 316, 5 -> 353, 6 -> 390, 7 -> 427, 8 -> 464, 9 -> 501, 10 -> 538, 11 -> 575, 12 -> 612, 13 -> 649, 14 -> 686, 15 -> 723, 16 -> 760, 17 -> 797, 18 -> 834, 19 -> 871, 20 -> 908, 21 -> 945, 22 -> 982, 23 -> 1019, 24 -> 1056, 25 -> 1093, 26 -> 1130, 27 -> 1167, 28 -> 1204, 29 -> 1241, 30 -> 1278, 31 -> 1315
    //   168: aload_3
    //   169: getstatic burp/Zeor.Zj : Ljava/lang/String;
    //   172: getstatic burp/Zlx5.Zp : Ljava/lang/Object;
    //   175: checkcast java/math/BigInteger
    //   178: invokevirtual intValue : ()I
    //   181: bipush #32
    //   183: irem
    //   184: invokestatic abs : (I)I
    //   187: invokevirtual charAt : (I)C
    //   190: invokevirtual append : (C)Ljava/lang/StringBuilder;
    //   193: pop
    //   194: iload_2
    //   195: ifne -> 1348
    //   198: goto -> 205
    //   201: invokestatic a : (Ljava/lang/Throwable;)Ljava/lang/Throwable;
    //   204: athrow
    //   205: aload_3
    //   206: getstatic burp/Zb8y.Zn : Ljava/lang/String;
    //   209: getstatic burp/Zx4y.Zc : Ljava/lang/Object;
    //   212: checkcast java/math/BigInteger
    //   215: invokevirtual intValue : ()I
    //   218: bipush #32
    //   220: irem
    //   221: invokestatic abs : (I)I
    //   224: invokevirtual charAt : (I)C
    //   227: invokevirtual append : (C)Ljava/lang/StringBuilder;
    //   230: pop
    //   231: iload_2
    //   232: ifne -> 1348
    //   235: goto -> 242
    //   238: invokestatic a : (Ljava/lang/Throwable;)Ljava/lang/Throwable;
    //   241: athrow
    //   242: aload_3
    //   243: getstatic burp/Zl3l.Z_ : Ljava/lang/String;
    //   246: getstatic burp/Zecm.ZJ : Ljava/lang/Object;
    //   249: checkcast java/math/BigInteger
    //   252: invokevirtual intValue : ()I
    //   255: bipush #32
    //   257: irem
    //   258: invokestatic abs : (I)I
    //   261: invokevirtual charAt : (I)C
    //   264: invokevirtual append : (C)Ljava/lang/StringBuilder;
    //   267: pop
    //   268: iload_2
    //   269: ifne -> 1348
    //   272: goto -> 279
    //   275: invokestatic a : (Ljava/lang/Throwable;)Ljava/lang/Throwable;
    //   278: athrow
    //   279: aload_3
    //   280: getstatic burp/Zth7.Zf : Ljava/lang/String;
    //   283: getstatic burp/Zg4k.ZE : Ljava/lang/Object;
    //   286: checkcast java/math/BigInteger
    //   289: invokevirtual intValue : ()I
    //   292: bipush #32
    //   294: irem
    //   295: invokestatic abs : (I)I
    //   298: invokevirtual charAt : (I)C
    //   301: invokevirtual append : (C)Ljava/lang/StringBuilder;
    //   304: pop
    //   305: iload_2
    //   306: ifne -> 1348
    //   309: goto -> 316
    //   312: invokestatic a : (Ljava/lang/Throwable;)Ljava/lang/Throwable;
    //   315: athrow
    //   316: aload_3
    //   317: getstatic burp/Zscf.Zu : Ljava/lang/String;
    //   320: getstatic burp/Zt7j.ZH : Ljava/lang/Object;
    //   323: checkcast java/math/BigInteger
    //   326: invokevirtual intValue : ()I
    //   329: bipush #32
    //   331: irem
    //   332: invokestatic abs : (I)I
    //   335: invokevirtual charAt : (I)C
    //   338: invokevirtual append : (C)Ljava/lang/StringBuilder;
    //   341: pop
    //   342: iload_2
    //   343: ifne -> 1348
    //   346: goto -> 353
    //   349: invokestatic a : (Ljava/lang/Throwable;)Ljava/lang/Throwable;
    //   352: athrow
    //   353: aload_3
    //   354: getstatic burp/Ztuj.Zk : Ljava/lang/String;
    //   357: getstatic burp/Zm0v.ZH : Ljava/lang/Object;
    //   360: checkcast java/math/BigInteger
    //   363: invokevirtual intValue : ()I
    //   366: bipush #32
    //   368: irem
    //   369: invokestatic abs : (I)I
    //   372: invokevirtual charAt : (I)C
    //   375: invokevirtual append : (C)Ljava/lang/StringBuilder;
    //   378: pop
    //   379: iload_2
    //   380: ifne -> 1348
    //   383: goto -> 390
    //   386: invokestatic a : (Ljava/lang/Throwable;)Ljava/lang/Throwable;
    //   389: athrow
    //   390: aload_3
    //   391: getstatic burp/Zl5.ZE : Ljava/lang/String;
    //   394: getstatic burp/Zl88.ZK : Ljava/lang/Object;
    //   397: checkcast java/math/BigInteger
    //   400: invokevirtual intValue : ()I
    //   403: bipush #32
    //   405: irem
    //   406: invokestatic abs : (I)I
    //   409: invokevirtual charAt : (I)C
    //   412: invokevirtual append : (C)Ljava/lang/StringBuilder;
    //   415: pop
    //   416: iload_2
    //   417: ifne -> 1348
    //   420: goto -> 427
    //   423: invokestatic a : (Ljava/lang/Throwable;)Ljava/lang/Throwable;
    //   426: athrow
    //   427: aload_3
    //   428: getstatic burp/Zbo2.Zr : Ljava/lang/String;
    //   431: getstatic burp/Zrvb.ZD : Ljava/lang/Object;
    //   434: checkcast java/math/BigInteger
    //   437: invokevirtual intValue : ()I
    //   440: bipush #32
    //   442: irem
    //   443: invokestatic abs : (I)I
    //   446: invokevirtual charAt : (I)C
    //   449: invokevirtual append : (C)Ljava/lang/StringBuilder;
    //   452: pop
    //   453: iload_2
    //   454: ifne -> 1348
    //   457: goto -> 464
    //   460: invokestatic a : (Ljava/lang/Throwable;)Ljava/lang/Throwable;
    //   463: athrow
    //   464: aload_3
    //   465: getstatic burp/Zd0.Zi : Ljava/lang/String;
    //   468: getstatic burp/Zlh2.Zc : Ljava/lang/Object;
    //   471: checkcast java/math/BigInteger
    //   474: invokevirtual intValue : ()I
    //   477: bipush #32
    //   479: irem
    //   480: invokestatic abs : (I)I
    //   483: invokevirtual charAt : (I)C
    //   486: invokevirtual append : (C)Ljava/lang/StringBuilder;
    //   489: pop
    //   490: iload_2
    //   491: ifne -> 1348
    //   494: goto -> 501
    //   497: invokestatic a : (Ljava/lang/Throwable;)Ljava/lang/Throwable;
    //   500: athrow
    //   501: aload_3
    //   502: getstatic burp/Zemp.Zs : Ljava/lang/String;
    //   505: getstatic burp/Zz20.ZN : Ljava/lang/Object;
    //   508: checkcast java/math/BigInteger
    //   511: invokevirtual intValue : ()I
    //   514: bipush #32
    //   516: irem
    //   517: invokestatic abs : (I)I
    //   520: invokevirtual charAt : (I)C
    //   523: invokevirtual append : (C)Ljava/lang/StringBuilder;
    //   526: pop
    //   527: iload_2
    //   528: ifne -> 1348
    //   531: goto -> 538
    //   534: invokestatic a : (Ljava/lang/Throwable;)Ljava/lang/Throwable;
    //   537: athrow
    //   538: aload_3
    //   539: getstatic burp/Zkff.Zs : Ljava/lang/String;
    //   542: getstatic burp/Zx58.ZE : Ljava/lang/Object;
    //   545: checkcast java/math/BigInteger
    //   548: invokevirtual intValue : ()I
    //   551: bipush #32
    //   553: irem
    //   554: invokestatic abs : (I)I
    //   557: invokevirtual charAt : (I)C
    //   560: invokevirtual append : (C)Ljava/lang/StringBuilder;
    //   563: pop
    //   564: iload_2
    //   565: ifne -> 1348
    //   568: goto -> 575
    //   571: invokestatic a : (Ljava/lang/Throwable;)Ljava/lang/Throwable;
    //   574: athrow
    //   575: aload_3
    //   576: getstatic burp/Zl1z.Zh : Ljava/lang/String;
    //   579: getstatic burp/Zs59.Zw : Ljava/lang/Object;
    //   582: checkcast java/math/BigInteger
    //   585: invokevirtual intValue : ()I
    //   588: bipush #32
    //   590: irem
    //   591: invokestatic abs : (I)I
    //   594: invokevirtual charAt : (I)C
    //   597: invokevirtual append : (C)Ljava/lang/StringBuilder;
    //   600: pop
    //   601: iload_2
    //   602: ifne -> 1348
    //   605: goto -> 612
    //   608: invokestatic a : (Ljava/lang/Throwable;)Ljava/lang/Throwable;
    //   611: athrow
    //   612: aload_3
    //   613: getstatic burp/Zx8t.Zi : Ljava/lang/String;
    //   616: getstatic burp/Zmv9.Zw : Ljava/lang/Object;
    //   619: checkcast java/math/BigInteger
    //   622: invokevirtual intValue : ()I
    //   625: bipush #32
    //   627: irem
    //   628: invokestatic abs : (I)I
    //   631: invokevirtual charAt : (I)C
    //   634: invokevirtual append : (C)Ljava/lang/StringBuilder;
    //   637: pop
    //   638: iload_2
    //   639: ifne -> 1348
    //   642: goto -> 649
    //   645: invokestatic a : (Ljava/lang/Throwable;)Ljava/lang/Throwable;
    //   648: athrow
    //   649: aload_3
    //   650: getstatic burp/Zsdn.Zf : Ljava/lang/String;
    //   653: getstatic burp/Ze7y.Zh : Ljava/lang/Object;
    //   656: checkcast java/math/BigInteger
    //   659: invokevirtual intValue : ()I
    //   662: bipush #32
    //   664: irem
    //   665: invokestatic abs : (I)I
    //   668: invokevirtual charAt : (I)C
    //   671: invokevirtual append : (C)Ljava/lang/StringBuilder;
    //   674: pop
    //   675: iload_2
    //   676: ifne -> 1348
    //   679: goto -> 686
    //   682: invokestatic a : (Ljava/lang/Throwable;)Ljava/lang/Throwable;
    //   685: athrow
    //   686: aload_3
    //   687: getstatic burp/Zstq.ZL : Ljava/lang/String;
    //   690: getstatic burp/Ze0w.ZU : Ljava/lang/Object;
    //   693: checkcast java/math/BigInteger
    //   696: invokevirtual intValue : ()I
    //   699: bipush #32
    //   701: irem
    //   702: invokestatic abs : (I)I
    //   705: invokevirtual charAt : (I)C
    //   708: invokevirtual append : (C)Ljava/lang/StringBuilder;
    //   711: pop
    //   712: iload_2
    //   713: ifne -> 1348
    //   716: goto -> 723
    //   719: invokestatic a : (Ljava/lang/Throwable;)Ljava/lang/Throwable;
    //   722: athrow
    //   723: aload_3
    //   724: getstatic burp/Zx_u.Z_ : Ljava/lang/String;
    //   727: getstatic burp/Zzox.Zq : Ljava/lang/Object;
    //   730: checkcast java/math/BigInteger
    //   733: invokevirtual intValue : ()I
    //   736: bipush #32
    //   738: irem
    //   739: invokestatic abs : (I)I
    //   742: invokevirtual charAt : (I)C
    //   745: invokevirtual append : (C)Ljava/lang/StringBuilder;
    //   748: pop
    //   749: iload_2
    //   750: ifne -> 1348
    //   753: goto -> 760
    //   756: invokestatic a : (Ljava/lang/Throwable;)Ljava/lang/Throwable;
    //   759: athrow
    //   760: aload_3
    //   761: getstatic burp/Zmze.ZO : Ljava/lang/String;
    //   764: getstatic burp/Zrcx.Za : Ljava/lang/Object;
    //   767: checkcast java/math/BigInteger
    //   770: invokevirtual intValue : ()I
    //   773: bipush #32
    //   775: irem
    //   776: invokestatic abs : (I)I
    //   779: invokevirtual charAt : (I)C
    //   782: invokevirtual append : (C)Ljava/lang/StringBuilder;
    //   785: pop
    //   786: iload_2
    //   787: ifne -> 1348
    //   790: goto -> 797
    //   793: invokestatic a : (Ljava/lang/Throwable;)Ljava/lang/Throwable;
    //   796: athrow
    //   797: aload_3
    //   798: getstatic burp/Zkbm.Zb : Ljava/lang/String;
    //   801: getstatic burp/Zlwm.Ze : Ljava/lang/Object;
    //   804: checkcast java/math/BigInteger
    //   807: invokevirtual intValue : ()I
    //   810: bipush #32
    //   812: irem
    //   813: invokestatic abs : (I)I
    //   816: invokevirtual charAt : (I)C
    //   819: invokevirtual append : (C)Ljava/lang/StringBuilder;
    //   822: pop
    //   823: iload_2
    //   824: ifne -> 1348
    //   827: goto -> 834
    //   830: invokestatic a : (Ljava/lang/Throwable;)Ljava/lang/Throwable;
    //   833: athrow
    //   834: aload_3
    //   835: getstatic burp/Zefn.Ze : Ljava/lang/String;
    //   838: getstatic burp/Zkup.Zf : Ljava/lang/Object;
    //   841: checkcast java/math/BigInteger
    //   844: invokevirtual intValue : ()I
    //   847: bipush #32
    //   849: irem
    //   850: invokestatic abs : (I)I
    //   853: invokevirtual charAt : (I)C
    //   856: invokevirtual append : (C)Ljava/lang/StringBuilder;
    //   859: pop
    //   860: iload_2
    //   861: ifne -> 1348
    //   864: goto -> 871
    //   867: invokestatic a : (Ljava/lang/Throwable;)Ljava/lang/Throwable;
    //   870: athrow
    //   871: aload_3
    //   872: getstatic burp/Zxd0.Zc : Ljava/lang/String;
    //   875: getstatic burp/Zg_5.ZA : Ljava/lang/Object;
    //   878: checkcast java/math/BigInteger
    //   881: invokevirtual intValue : ()I
    //   884: bipush #32
    //   886: irem
    //   887: invokestatic abs : (I)I
    //   890: invokevirtual charAt : (I)C
    //   893: invokevirtual append : (C)Ljava/lang/StringBuilder;
    //   896: pop
    //   897: iload_2
    //   898: ifne -> 1348
    //   901: goto -> 908
    //   904: invokestatic a : (Ljava/lang/Throwable;)Ljava/lang/Throwable;
    //   907: athrow
    //   908: aload_3
    //   909: getstatic burp/Zg_6.Zc : Ljava/lang/String;
    //   912: getstatic burp/Zmji.ZB : Ljava/lang/Object;
    //   915: checkcast java/math/BigInteger
    //   918: invokevirtual intValue : ()I
    //   921: bipush #32
    //   923: irem
    //   924: invokestatic abs : (I)I
    //   927: invokevirtual charAt : (I)C
    //   930: invokevirtual append : (C)Ljava/lang/StringBuilder;
    //   933: pop
    //   934: iload_2
    //   935: ifne -> 1348
    //   938: goto -> 945
    //   941: invokestatic a : (Ljava/lang/Throwable;)Ljava/lang/Throwable;
    //   944: athrow
    //   945: aload_3
    //   946: getstatic burp/Zl4v.ZD : Ljava/lang/String;
    //   949: getstatic burp/Zttj.ZF : Ljava/lang/Object;
    //   952: checkcast java/math/BigInteger
    //   955: invokevirtual intValue : ()I
    //   958: bipush #32
    //   960: irem
    //   961: invokestatic abs : (I)I
    //   964: invokevirtual charAt : (I)C
    //   967: invokevirtual append : (C)Ljava/lang/StringBuilder;
    //   970: pop
    //   971: iload_2
    //   972: ifne -> 1348
    //   975: goto -> 982
    //   978: invokestatic a : (Ljava/lang/Throwable;)Ljava/lang/Throwable;
    //   981: athrow
    //   982: aload_3
    //   983: getstatic burp/Zlqm.ZQ : Ljava/lang/String;
    //   986: getstatic burp/Zb6a.Zz : Ljava/lang/Object;
    //   989: checkcast java/math/BigInteger
    //   992: invokevirtual intValue : ()I
    //   995: bipush #32
    //   997: irem
    //   998: invokestatic abs : (I)I
    //   1001: invokevirtual charAt : (I)C
    //   1004: invokevirtual append : (C)Ljava/lang/StringBuilder;
    //   1007: pop
    //   1008: iload_2
    //   1009: ifne -> 1348
    //   1012: goto -> 1019
    //   1015: invokestatic a : (Ljava/lang/Throwable;)Ljava/lang/Throwable;
    //   1018: athrow
    //   1019: aload_3
    //   1020: getstatic burp/Zl1u.ZO : Ljava/lang/String;
    //   1023: getstatic burp/Zsf3.ZH : Ljava/lang/Object;
    //   1026: checkcast java/math/BigInteger
    //   1029: invokevirtual intValue : ()I
    //   1032: bipush #32
    //   1034: irem
    //   1035: invokestatic abs : (I)I
    //   1038: invokevirtual charAt : (I)C
    //   1041: invokevirtual append : (C)Ljava/lang/StringBuilder;
    //   1044: pop
    //   1045: iload_2
    //   1046: ifne -> 1348
    //   1049: goto -> 1056
    //   1052: invokestatic a : (Ljava/lang/Throwable;)Ljava/lang/Throwable;
    //   1055: athrow
    //   1056: aload_3
    //   1057: getstatic burp/Zrnu.ZO : Ljava/lang/String;
    //   1060: getstatic burp/Zs0b.ZI : Ljava/lang/Object;
    //   1063: checkcast java/math/BigInteger
    //   1066: invokevirtual intValue : ()I
    //   1069: bipush #32
    //   1071: irem
    //   1072: invokestatic abs : (I)I
    //   1075: invokevirtual charAt : (I)C
    //   1078: invokevirtual append : (C)Ljava/lang/StringBuilder;
    //   1081: pop
    //   1082: iload_2
    //   1083: ifne -> 1348
    //   1086: goto -> 1093
    //   1089: invokestatic a : (Ljava/lang/Throwable;)Ljava/lang/Throwable;
    //   1092: athrow
    //   1093: aload_3
    //   1094: getstatic burp/Zgny.Zf : Ljava/lang/String;
    //   1097: getstatic burp/Zva.Zu : Ljava/lang/Object;
    //   1100: checkcast java/math/BigInteger
    //   1103: invokevirtual intValue : ()I
    //   1106: bipush #32
    //   1108: irem
    //   1109: invokestatic abs : (I)I
    //   1112: invokevirtual charAt : (I)C
    //   1115: invokevirtual append : (C)Ljava/lang/StringBuilder;
    //   1118: pop
    //   1119: iload_2
    //   1120: ifne -> 1348
    //   1123: goto -> 1130
    //   1126: invokestatic a : (Ljava/lang/Throwable;)Ljava/lang/Throwable;
    //   1129: athrow
    //   1130: aload_3
    //   1131: getstatic burp/Zzym.Zj : Ljava/lang/String;
    //   1134: getstatic burp/Zej5.ZB : Ljava/lang/Object;
    //   1137: checkcast java/math/BigInteger
    //   1140: invokevirtual intValue : ()I
    //   1143: bipush #32
    //   1145: irem
    //   1146: invokestatic abs : (I)I
    //   1149: invokevirtual charAt : (I)C
    //   1152: invokevirtual append : (C)Ljava/lang/StringBuilder;
    //   1155: pop
    //   1156: iload_2
    //   1157: ifne -> 1348
    //   1160: goto -> 1167
    //   1163: invokestatic a : (Ljava/lang/Throwable;)Ljava/lang/Throwable;
    //   1166: athrow
    //   1167: aload_3
    //   1168: getstatic burp/Zkyc.ZK : Ljava/lang/String;
    //   1171: getstatic burp/Zrd4.Ze : Ljava/lang/Object;
    //   1174: checkcast java/math/BigInteger
    //   1177: invokevirtual intValue : ()I
    //   1180: bipush #32
    //   1182: irem
    //   1183: invokestatic abs : (I)I
    //   1186: invokevirtual charAt : (I)C
    //   1189: invokevirtual append : (C)Ljava/lang/StringBuilder;
    //   1192: pop
    //   1193: iload_2
    //   1194: ifne -> 1348
    //   1197: goto -> 1204
    //   1200: invokestatic a : (Ljava/lang/Throwable;)Ljava/lang/Throwable;
    //   1203: athrow
    //   1204: aload_3
    //   1205: getstatic burp/Zgkl.ZR : Ljava/lang/String;
    //   1208: getstatic burp/Zvof.Zl : Ljava/lang/Object;
    //   1211: checkcast java/math/BigInteger
    //   1214: invokevirtual intValue : ()I
    //   1217: bipush #32
    //   1219: irem
    //   1220: invokestatic abs : (I)I
    //   1223: invokevirtual charAt : (I)C
    //   1226: invokevirtual append : (C)Ljava/lang/StringBuilder;
    //   1229: pop
    //   1230: iload_2
    //   1231: ifne -> 1348
    //   1234: goto -> 1241
    //   1237: invokestatic a : (Ljava/lang/Throwable;)Ljava/lang/Throwable;
    //   1240: athrow
    //   1241: aload_3
    //   1242: getstatic burp/Zlbr.Zr : Ljava/lang/String;
    //   1245: getstatic burp/Zzuh.ZV : Ljava/lang/Object;
    //   1248: checkcast java/math/BigInteger
    //   1251: invokevirtual intValue : ()I
    //   1254: bipush #32
    //   1256: irem
    //   1257: invokestatic abs : (I)I
    //   1260: invokevirtual charAt : (I)C
    //   1263: invokevirtual append : (C)Ljava/lang/StringBuilder;
    //   1266: pop
    //   1267: iload_2
    //   1268: ifne -> 1348
    //   1271: goto -> 1278
    //   1274: invokestatic a : (Ljava/lang/Throwable;)Ljava/lang/Throwable;
    //   1277: athrow
    //   1278: aload_3
    //   1279: getstatic burp/Zzmo.Zx : Ljava/lang/String;
    //   1282: getstatic burp/Zvk.ZN : Ljava/lang/Object;
    //   1285: checkcast java/math/BigInteger
    //   1288: invokevirtual intValue : ()I
    //   1291: bipush #32
    //   1293: irem
    //   1294: invokestatic abs : (I)I
    //   1297: invokevirtual charAt : (I)C
    //   1300: invokevirtual append : (C)Ljava/lang/StringBuilder;
    //   1303: pop
    //   1304: iload_2
    //   1305: ifne -> 1348
    //   1308: goto -> 1315
    //   1311: invokestatic a : (Ljava/lang/Throwable;)Ljava/lang/Throwable;
    //   1314: athrow
    //   1315: aload_3
    //   1316: getstatic burp/Zg68.Zg : Ljava/lang/String;
    //   1319: getstatic burp/Zltz.Zg : Ljava/lang/Object;
    //   1322: checkcast java/math/BigInteger
    //   1325: invokevirtual intValue : ()I
    //   1328: bipush #32
    //   1330: irem
    //   1331: invokestatic abs : (I)I
    //   1334: invokevirtual charAt : (I)C
    //   1337: invokevirtual append : (C)Ljava/lang/StringBuilder;
    //   1340: pop
    //   1341: goto -> 1348
    //   1344: invokestatic a : (Ljava/lang/Throwable;)Ljava/lang/Throwable;
    //   1347: athrow
    //   1348: iinc #4, 1
    //   1351: iload_2
    //   1352: ifne -> 15
    //   1355: aload_3
    //   1356: invokevirtual toString : ()Ljava/lang/String;
    //   1359: putstatic burp/Zgfq.Zn : Ljava/lang/String;
    //   1362: new java/lang/StringBuilder
    //   1365: dup
    //   1366: invokespecial <init> : ()V
    //   1369: astore #4
    //   1371: iconst_0
    //   1372: istore #5
    //   1374: iload #5
    //   1376: bipush #32
    //   1378: if_icmpge -> 2743
    //   1381: iload #5
    //   1383: tableswitch default -> 2736, 0 -> 1524, 1 -> 1562, 2 -> 1600, 3 -> 1638, 4 -> 1676, 5 -> 1714, 6 -> 1752, 7 -> 1790, 8 -> 1828, 9 -> 1866, 10 -> 1904, 11 -> 1942, 12 -> 1980, 13 -> 2018, 14 -> 2056, 15 -> 2094, 16 -> 2132, 17 -> 2170, 18 -> 2208, 19 -> 2246, 20 -> 2284, 21 -> 2322, 22 -> 2360, 23 -> 2398, 24 -> 2436, 25 -> 2474, 26 -> 2512, 27 -> 2550, 28 -> 2588, 29 -> 2626, 30 -> 2664, 31 -> 2702
    //   1524: aload #4
    //   1526: getstatic burp/Zxn5.ZI : Ljava/lang/String;
    //   1529: getstatic burp/Zly0.ZB : Ljava/lang/Object;
    //   1532: checkcast java/math/BigInteger
    //   1535: invokevirtual intValue : ()I
    //   1538: bipush #32
    //   1540: irem
    //   1541: invokestatic abs : (I)I
    //   1544: invokevirtual charAt : (I)C
    //   1547: invokevirtual append : (C)Ljava/lang/StringBuilder;
    //   1550: pop
    //   1551: iload_2
    //   1552: ifne -> 2736
    //   1555: goto -> 1562
    //   1558: invokestatic a : (Ljava/lang/Throwable;)Ljava/lang/Throwable;
    //   1561: athrow
    //   1562: aload #4
    //   1564: getstatic burp/Zeh9.ZF : Ljava/lang/String;
    //   1567: getstatic burp/Zkdc.Zv : Ljava/lang/Object;
    //   1570: checkcast java/math/BigInteger
    //   1573: invokevirtual intValue : ()I
    //   1576: bipush #32
    //   1578: irem
    //   1579: invokestatic abs : (I)I
    //   1582: invokevirtual charAt : (I)C
    //   1585: invokevirtual append : (C)Ljava/lang/StringBuilder;
    //   1588: pop
    //   1589: iload_2
    //   1590: ifne -> 2736
    //   1593: goto -> 1600
    //   1596: invokestatic a : (Ljava/lang/Throwable;)Ljava/lang/Throwable;
    //   1599: athrow
    //   1600: aload #4
    //   1602: getstatic burp/Zebu.ZI : Ljava/lang/String;
    //   1605: getstatic burp/Zgyc.ZT : Ljava/lang/Object;
    //   1608: checkcast java/math/BigInteger
    //   1611: invokevirtual intValue : ()I
    //   1614: bipush #32
    //   1616: irem
    //   1617: invokestatic abs : (I)I
    //   1620: invokevirtual charAt : (I)C
    //   1623: invokevirtual append : (C)Ljava/lang/StringBuilder;
    //   1626: pop
    //   1627: iload_2
    //   1628: ifne -> 2736
    //   1631: goto -> 1638
    //   1634: invokestatic a : (Ljava/lang/Throwable;)Ljava/lang/Throwable;
    //   1637: athrow
    //   1638: aload #4
    //   1640: getstatic burp/Zmuj.ZG : Ljava/lang/String;
    //   1643: getstatic burp/Zgt6.ZU : Ljava/lang/Object;
    //   1646: checkcast java/math/BigInteger
    //   1649: invokevirtual intValue : ()I
    //   1652: bipush #32
    //   1654: irem
    //   1655: invokestatic abs : (I)I
    //   1658: invokevirtual charAt : (I)C
    //   1661: invokevirtual append : (C)Ljava/lang/StringBuilder;
    //   1664: pop
    //   1665: iload_2
    //   1666: ifne -> 2736
    //   1669: goto -> 1676
    //   1672: invokestatic a : (Ljava/lang/Throwable;)Ljava/lang/Throwable;
    //   1675: athrow
    //   1676: aload #4
    //   1678: getstatic burp/Zs00.Zv : Ljava/lang/String;
    //   1681: getstatic burp/Zea9.Zt : Ljava/lang/Object;
    //   1684: checkcast java/math/BigInteger
    //   1687: invokevirtual intValue : ()I
    //   1690: bipush #32
    //   1692: irem
    //   1693: invokestatic abs : (I)I
    //   1696: invokevirtual charAt : (I)C
    //   1699: invokevirtual append : (C)Ljava/lang/StringBuilder;
    //   1702: pop
    //   1703: iload_2
    //   1704: ifne -> 2736
    //   1707: goto -> 1714
    //   1710: invokestatic a : (Ljava/lang/Throwable;)Ljava/lang/Throwable;
    //   1713: athrow
    //   1714: aload #4
    //   1716: getstatic burp/Zewq.ZV : Ljava/lang/String;
    //   1719: getstatic burp/Zlhk.ZD : Ljava/lang/Object;
    //   1722: checkcast java/math/BigInteger
    //   1725: invokevirtual intValue : ()I
    //   1728: bipush #32
    //   1730: irem
    //   1731: invokestatic abs : (I)I
    //   1734: invokevirtual charAt : (I)C
    //   1737: invokevirtual append : (C)Ljava/lang/StringBuilder;
    //   1740: pop
    //   1741: iload_2
    //   1742: ifne -> 2736
    //   1745: goto -> 1752
    //   1748: invokestatic a : (Ljava/lang/Throwable;)Ljava/lang/Throwable;
    //   1751: athrow
    //   1752: aload #4
    //   1754: getstatic burp/Zkmx.Zg : Ljava/lang/String;
    //   1757: getstatic burp/Zzgh.ZV : Ljava/lang/Object;
    //   1760: checkcast java/math/BigInteger
    //   1763: invokevirtual intValue : ()I
    //   1766: bipush #32
    //   1768: irem
    //   1769: invokestatic abs : (I)I
    //   1772: invokevirtual charAt : (I)C
    //   1775: invokevirtual append : (C)Ljava/lang/StringBuilder;
    //   1778: pop
    //   1779: iload_2
    //   1780: ifne -> 2736
    //   1783: goto -> 1790
    //   1786: invokestatic a : (Ljava/lang/Throwable;)Ljava/lang/Throwable;
    //   1789: athrow
    //   1790: aload #4
    //   1792: getstatic burp/Zb3r.Zo : Ljava/lang/String;
    //   1795: getstatic burp/Zs8q.ZI : Ljava/lang/Object;
    //   1798: checkcast java/math/BigInteger
    //   1801: invokevirtual intValue : ()I
    //   1804: bipush #32
    //   1806: irem
    //   1807: invokestatic abs : (I)I
    //   1810: invokevirtual charAt : (I)C
    //   1813: invokevirtual append : (C)Ljava/lang/StringBuilder;
    //   1816: pop
    //   1817: iload_2
    //   1818: ifne -> 2736
    //   1821: goto -> 1828
    //   1824: invokestatic a : (Ljava/lang/Throwable;)Ljava/lang/Throwable;
    //   1827: athrow
    //   1828: aload #4
    //   1830: getstatic burp/Zgyk.ZB : Ljava/lang/String;
    //   1833: getstatic burp/Zlb6.Zz : Ljava/lang/Object;
    //   1836: checkcast java/math/BigInteger
    //   1839: invokevirtual intValue : ()I
    //   1842: bipush #32
    //   1844: irem
    //   1845: invokestatic abs : (I)I
    //   1848: invokevirtual charAt : (I)C
    //   1851: invokevirtual append : (C)Ljava/lang/StringBuilder;
    //   1854: pop
    //   1855: iload_2
    //   1856: ifne -> 2736
    //   1859: goto -> 1866
    //   1862: invokestatic a : (Ljava/lang/Throwable;)Ljava/lang/Throwable;
    //   1865: athrow
    //   1866: aload #4
    //   1868: getstatic burp/Zl4v.ZD : Ljava/lang/String;
    //   1871: getstatic burp/Zko9.ZC : Ljava/lang/Object;
    //   1874: checkcast java/math/BigInteger
    //   1877: invokevirtual intValue : ()I
    //   1880: bipush #32
    //   1882: irem
    //   1883: invokestatic abs : (I)I
    //   1886: invokevirtual charAt : (I)C
    //   1889: invokevirtual append : (C)Ljava/lang/StringBuilder;
    //   1892: pop
    //   1893: iload_2
    //   1894: ifne -> 2736
    //   1897: goto -> 1904
    //   1900: invokestatic a : (Ljava/lang/Throwable;)Ljava/lang/Throwable;
    //   1903: athrow
    //   1904: aload #4
    //   1906: getstatic burp/Zr8h.Zk : Ljava/lang/String;
    //   1909: getstatic burp/Zr0u.ZB : Ljava/lang/Object;
    //   1912: checkcast java/math/BigInteger
    //   1915: invokevirtual intValue : ()I
    //   1918: bipush #32
    //   1920: irem
    //   1921: invokestatic abs : (I)I
    //   1924: invokevirtual charAt : (I)C
    //   1927: invokevirtual append : (C)Ljava/lang/StringBuilder;
    //   1930: pop
    //   1931: iload_2
    //   1932: ifne -> 2736
    //   1935: goto -> 1942
    //   1938: invokestatic a : (Ljava/lang/Throwable;)Ljava/lang/Throwable;
    //   1941: athrow
    //   1942: aload #4
    //   1944: getstatic burp/Zxyp.Z_ : Ljava/lang/String;
    //   1947: getstatic burp/Zlbt.ZF : Ljava/lang/Object;
    //   1950: checkcast java/math/BigInteger
    //   1953: invokevirtual intValue : ()I
    //   1956: bipush #32
    //   1958: irem
    //   1959: invokestatic abs : (I)I
    //   1962: invokevirtual charAt : (I)C
    //   1965: invokevirtual append : (C)Ljava/lang/StringBuilder;
    //   1968: pop
    //   1969: iload_2
    //   1970: ifne -> 2736
    //   1973: goto -> 1980
    //   1976: invokestatic a : (Ljava/lang/Throwable;)Ljava/lang/Throwable;
    //   1979: athrow
    //   1980: aload #4
    //   1982: getstatic burp/Zls_.Zn : Ljava/lang/String;
    //   1985: getstatic burp/Zgrf.ZN : Ljava/lang/Object;
    //   1988: checkcast java/math/BigInteger
    //   1991: invokevirtual intValue : ()I
    //   1994: bipush #32
    //   1996: irem
    //   1997: invokestatic abs : (I)I
    //   2000: invokevirtual charAt : (I)C
    //   2003: invokevirtual append : (C)Ljava/lang/StringBuilder;
    //   2006: pop
    //   2007: iload_2
    //   2008: ifne -> 2736
    //   2011: goto -> 2018
    //   2014: invokestatic a : (Ljava/lang/Throwable;)Ljava/lang/Throwable;
    //   2017: athrow
    //   2018: aload #4
    //   2020: getstatic burp/Zrcy.Zq : Ljava/lang/String;
    //   2023: getstatic burp/Zgia.Zx : Ljava/lang/Object;
    //   2026: checkcast java/math/BigInteger
    //   2029: invokevirtual intValue : ()I
    //   2032: bipush #32
    //   2034: irem
    //   2035: invokestatic abs : (I)I
    //   2038: invokevirtual charAt : (I)C
    //   2041: invokevirtual append : (C)Ljava/lang/StringBuilder;
    //   2044: pop
    //   2045: iload_2
    //   2046: ifne -> 2736
    //   2049: goto -> 2056
    //   2052: invokestatic a : (Ljava/lang/Throwable;)Ljava/lang/Throwable;
    //   2055: athrow
    //   2056: aload #4
    //   2058: getstatic burp/Zgsy.Zv : Ljava/lang/String;
    //   2061: getstatic burp/Zvi.Zs : Ljava/lang/Object;
    //   2064: checkcast java/math/BigInteger
    //   2067: invokevirtual intValue : ()I
    //   2070: bipush #32
    //   2072: irem
    //   2073: invokestatic abs : (I)I
    //   2076: invokevirtual charAt : (I)C
    //   2079: invokevirtual append : (C)Ljava/lang/StringBuilder;
    //   2082: pop
    //   2083: iload_2
    //   2084: ifne -> 2736
    //   2087: goto -> 2094
    //   2090: invokestatic a : (Ljava/lang/Throwable;)Ljava/lang/Throwable;
    //   2093: athrow
    //   2094: aload #4
    //   2096: getstatic burp/Ze64.ZM : Ljava/lang/String;
    //   2099: getstatic burp/Zkc5.ZZ : Ljava/lang/Object;
    //   2102: checkcast java/math/BigInteger
    //   2105: invokevirtual intValue : ()I
    //   2108: bipush #32
    //   2110: irem
    //   2111: invokestatic abs : (I)I
    //   2114: invokevirtual charAt : (I)C
    //   2117: invokevirtual append : (C)Ljava/lang/StringBuilder;
    //   2120: pop
    //   2121: iload_2
    //   2122: ifne -> 2736
    //   2125: goto -> 2132
    //   2128: invokestatic a : (Ljava/lang/Throwable;)Ljava/lang/Throwable;
    //   2131: athrow
    //   2132: aload #4
    //   2134: getstatic burp/Zttj.ZN : Ljava/lang/String;
    //   2137: getstatic burp/Zlos.Zk : Ljava/lang/Object;
    //   2140: checkcast java/math/BigInteger
    //   2143: invokevirtual intValue : ()I
    //   2146: bipush #32
    //   2148: irem
    //   2149: invokestatic abs : (I)I
    //   2152: invokevirtual charAt : (I)C
    //   2155: invokevirtual append : (C)Ljava/lang/StringBuilder;
    //   2158: pop
    //   2159: iload_2
    //   2160: ifne -> 2736
    //   2163: goto -> 2170
    //   2166: invokestatic a : (Ljava/lang/Throwable;)Ljava/lang/Throwable;
    //   2169: athrow
    //   2170: aload #4
    //   2172: getstatic burp/Zlh2.Zf : Ljava/lang/String;
    //   2175: getstatic burp/Zvi.Zs : Ljava/lang/Object;
    //   2178: checkcast java/math/BigInteger
    //   2181: invokevirtual intValue : ()I
    //   2184: bipush #32
    //   2186: irem
    //   2187: invokestatic abs : (I)I
    //   2190: invokevirtual charAt : (I)C
    //   2193: invokevirtual append : (C)Ljava/lang/StringBuilder;
    //   2196: pop
    //   2197: iload_2
    //   2198: ifne -> 2736
    //   2201: goto -> 2208
    //   2204: invokestatic a : (Ljava/lang/Throwable;)Ljava/lang/Throwable;
    //   2207: athrow
    //   2208: aload #4
    //   2210: getstatic burp/Zbu.ZV : Ljava/lang/String;
    //   2213: getstatic burp/Zrf9.Zu : Ljava/lang/Object;
    //   2216: checkcast java/math/BigInteger
    //   2219: invokevirtual intValue : ()I
    //   2222: bipush #32
    //   2224: irem
    //   2225: invokestatic abs : (I)I
    //   2228: invokevirtual charAt : (I)C
    //   2231: invokevirtual append : (C)Ljava/lang/StringBuilder;
    //   2234: pop
    //   2235: iload_2
    //   2236: ifne -> 2736
    //   2239: goto -> 2246
    //   2242: invokestatic a : (Ljava/lang/Throwable;)Ljava/lang/Throwable;
    //   2245: athrow
    //   2246: aload #4
    //   2248: getstatic burp/Zk7b.ZE : Ljava/lang/String;
    //   2251: getstatic burp/Zrf9.Zu : Ljava/lang/Object;
    //   2254: checkcast java/math/BigInteger
    //   2257: invokevirtual intValue : ()I
    //   2260: bipush #32
    //   2262: irem
    //   2263: invokestatic abs : (I)I
    //   2266: invokevirtual charAt : (I)C
    //   2269: invokevirtual append : (C)Ljava/lang/StringBuilder;
    //   2272: pop
    //   2273: iload_2
    //   2274: ifne -> 2736
    //   2277: goto -> 2284
    //   2280: invokestatic a : (Ljava/lang/Throwable;)Ljava/lang/Throwable;
    //   2283: athrow
    //   2284: aload #4
    //   2286: getstatic burp/Zm8i.Z_ : Ljava/lang/String;
    //   2289: getstatic burp/Zrw7.ZV : Ljava/lang/Object;
    //   2292: checkcast java/math/BigInteger
    //   2295: invokevirtual intValue : ()I
    //   2298: bipush #32
    //   2300: irem
    //   2301: invokestatic abs : (I)I
    //   2304: invokevirtual charAt : (I)C
    //   2307: invokevirtual append : (C)Ljava/lang/StringBuilder;
    //   2310: pop
    //   2311: iload_2
    //   2312: ifne -> 2736
    //   2315: goto -> 2322
    //   2318: invokestatic a : (Ljava/lang/Throwable;)Ljava/lang/Throwable;
    //   2321: athrow
    //   2322: aload #4
    //   2324: getstatic burp/Zb_c.ZS : Ljava/lang/String;
    //   2327: getstatic burp/Zl7k.ZS : Ljava/lang/Object;
    //   2330: checkcast java/math/BigInteger
    //   2333: invokevirtual intValue : ()I
    //   2336: bipush #32
    //   2338: irem
    //   2339: invokestatic abs : (I)I
    //   2342: invokevirtual charAt : (I)C
    //   2345: invokevirtual append : (C)Ljava/lang/StringBuilder;
    //   2348: pop
    //   2349: iload_2
    //   2350: ifne -> 2736
    //   2353: goto -> 2360
    //   2356: invokestatic a : (Ljava/lang/Throwable;)Ljava/lang/Throwable;
    //   2359: athrow
    //   2360: aload #4
    //   2362: getstatic burp/Zb3l.Zz : Ljava/lang/String;
    //   2365: getstatic burp/Zz5l.Zb : Ljava/lang/Object;
    //   2368: checkcast java/math/BigInteger
    //   2371: invokevirtual intValue : ()I
    //   2374: bipush #32
    //   2376: irem
    //   2377: invokestatic abs : (I)I
    //   2380: invokevirtual charAt : (I)C
    //   2383: invokevirtual append : (C)Ljava/lang/StringBuilder;
    //   2386: pop
    //   2387: iload_2
    //   2388: ifne -> 2736
    //   2391: goto -> 2398
    //   2394: invokestatic a : (Ljava/lang/Throwable;)Ljava/lang/Throwable;
    //   2397: athrow
    //   2398: aload #4
    //   2400: getstatic burp/Zxn5.ZI : Ljava/lang/String;
    //   2403: getstatic burp/Zrom.ZF : Ljava/lang/Object;
    //   2406: checkcast java/math/BigInteger
    //   2409: invokevirtual intValue : ()I
    //   2412: bipush #32
    //   2414: irem
    //   2415: invokestatic abs : (I)I
    //   2418: invokevirtual charAt : (I)C
    //   2421: invokevirtual append : (C)Ljava/lang/StringBuilder;
    //   2424: pop
    //   2425: iload_2
    //   2426: ifne -> 2736
    //   2429: goto -> 2436
    //   2432: invokestatic a : (Ljava/lang/Throwable;)Ljava/lang/Throwable;
    //   2435: athrow
    //   2436: aload #4
    //   2438: getstatic burp/Zefn.Ze : Ljava/lang/String;
    //   2441: getstatic burp/Zx_s.ZX : Ljava/lang/Object;
    //   2444: checkcast java/math/BigInteger
    //   2447: invokevirtual intValue : ()I
    //   2450: bipush #32
    //   2452: irem
    //   2453: invokestatic abs : (I)I
    //   2456: invokevirtual charAt : (I)C
    //   2459: invokevirtual append : (C)Ljava/lang/StringBuilder;
    //   2462: pop
    //   2463: iload_2
    //   2464: ifne -> 2736
    //   2467: goto -> 2474
    //   2470: invokestatic a : (Ljava/lang/Throwable;)Ljava/lang/Throwable;
    //   2473: athrow
    //   2474: aload #4
    //   2476: getstatic burp/Zre1.ZA : Ljava/lang/String;
    //   2479: getstatic burp/Zro5.ZT : Ljava/lang/Object;
    //   2482: checkcast java/math/BigInteger
    //   2485: invokevirtual intValue : ()I
    //   2488: bipush #32
    //   2490: irem
    //   2491: invokestatic abs : (I)I
    //   2494: invokevirtual charAt : (I)C
    //   2497: invokevirtual append : (C)Ljava/lang/StringBuilder;
    //   2500: pop
    //   2501: iload_2
    //   2502: ifne -> 2736
    //   2505: goto -> 2512
    //   2508: invokestatic a : (Ljava/lang/Throwable;)Ljava/lang/Throwable;
    //   2511: athrow
    //   2512: aload #4
    //   2514: getstatic burp/Zr9j.Zc : Ljava/lang/String;
    //   2517: getstatic burp/Zttq.Zh : Ljava/lang/Object;
    //   2520: checkcast java/math/BigInteger
    //   2523: invokevirtual intValue : ()I
    //   2526: bipush #32
    //   2528: irem
    //   2529: invokestatic abs : (I)I
    //   2532: invokevirtual charAt : (I)C
    //   2535: invokevirtual append : (C)Ljava/lang/StringBuilder;
    //   2538: pop
    //   2539: iload_2
    //   2540: ifne -> 2736
    //   2543: goto -> 2550
    //   2546: invokestatic a : (Ljava/lang/Throwable;)Ljava/lang/Throwable;
    //   2549: athrow
    //   2550: aload #4
    //   2552: getstatic burp/Zktq.Zc : Ljava/lang/String;
    //   2555: getstatic burp/Zkc5.ZZ : Ljava/lang/Object;
    //   2558: checkcast java/math/BigInteger
    //   2561: invokevirtual intValue : ()I
    //   2564: bipush #32
    //   2566: irem
    //   2567: invokestatic abs : (I)I
    //   2570: invokevirtual charAt : (I)C
    //   2573: invokevirtual append : (C)Ljava/lang/StringBuilder;
    //   2576: pop
    //   2577: iload_2
    //   2578: ifne -> 2736
    //   2581: goto -> 2588
    //   2584: invokestatic a : (Ljava/lang/Throwable;)Ljava/lang/Throwable;
    //   2587: athrow
    //   2588: aload #4
    //   2590: getstatic burp/Zejg.ZP : Ljava/lang/String;
    //   2593: getstatic burp/Zxyp.ZZ : Ljava/lang/Object;
    //   2596: checkcast java/math/BigInteger
    //   2599: invokevirtual intValue : ()I
    //   2602: bipush #32
    //   2604: irem
    //   2605: invokestatic abs : (I)I
    //   2608: invokevirtual charAt : (I)C
    //   2611: invokevirtual append : (C)Ljava/lang/StringBuilder;
    //   2614: pop
    //   2615: iload_2
    //   2616: ifne -> 2736
    //   2619: goto -> 2626
    //   2622: invokestatic a : (Ljava/lang/Throwable;)Ljava/lang/Throwable;
    //   2625: athrow
    //   2626: aload #4
    //   2628: getstatic burp/Zr8s.ZA : Ljava/lang/String;
    //   2631: getstatic burp/Zmh0.Zt : Ljava/lang/Object;
    //   2634: checkcast java/math/BigInteger
    //   2637: invokevirtual intValue : ()I
    //   2640: bipush #32
    //   2642: irem
    //   2643: invokestatic abs : (I)I
    //   2646: invokevirtual charAt : (I)C
    //   2649: invokevirtual append : (C)Ljava/lang/StringBuilder;
    //   2652: pop
    //   2653: iload_2
    //   2654: ifne -> 2736
    //   2657: goto -> 2664
    //   2660: invokestatic a : (Ljava/lang/Throwable;)Ljava/lang/Throwable;
    //   2663: athrow
    //   2664: aload #4
    //   2666: getstatic burp/Zb2p.ZV : Ljava/lang/String;
    //   2669: getstatic burp/Zmhx.ZQ : Ljava/lang/Object;
    //   2672: checkcast java/math/BigInteger
    //   2675: invokevirtual intValue : ()I
    //   2678: bipush #32
    //   2680: irem
    //   2681: invokestatic abs : (I)I
    //   2684: invokevirtual charAt : (I)C
    //   2687: invokevirtual append : (C)Ljava/lang/StringBuilder;
    //   2690: pop
    //   2691: iload_2
    //   2692: ifne -> 2736
    //   2695: goto -> 2702
    //   2698: invokestatic a : (Ljava/lang/Throwable;)Ljava/lang/Throwable;
    //   2701: athrow
    //   2702: aload #4
    //   2704: getstatic burp/Zgds.ZA : Ljava/lang/String;
    //   2707: getstatic burp/Zxx4.Zo : Ljava/lang/Object;
    //   2710: checkcast java/math/BigInteger
    //   2713: invokevirtual intValue : ()I
    //   2716: bipush #32
    //   2718: irem
    //   2719: invokestatic abs : (I)I
    //   2722: invokevirtual charAt : (I)C
    //   2725: invokevirtual append : (C)Ljava/lang/StringBuilder;
    //   2728: pop
    //   2729: goto -> 2736
    //   2732: invokestatic a : (Ljava/lang/Throwable;)Ljava/lang/Throwable;
    //   2735: athrow
    //   2736: iinc #5, 1
    //   2739: iload_2
    //   2740: ifne -> 1374
    //   2743: aload #4
    //   2745: invokevirtual toString : ()Ljava/lang/String;
    //   2748: putstatic burp/Zzap.ZA : Ljava/lang/String;
    //   2751: sipush #8851
    //   2754: getstatic burp/Zgss.Zl : Ljava/lang/Object;
    //   2757: checkcast java/math/BigInteger
    //   2760: getstatic burp/Zlxs.ZK : Ljava/lang/Object;
    //   2763: checkcast java/math/BigInteger
    //   2766: invokevirtual subtract : (Ljava/math/BigInteger;)Ljava/math/BigInteger;
    //   2769: putstatic burp/Zt5a.Zs : Ljava/lang/Object;
    //   2772: sipush #11046
    //   2775: invokestatic a : (II)Ljava/lang/String;
    //   2778: iconst_1
    //   2779: ldc burp/Zl8f
    //   2781: invokevirtual getClassLoader : ()Ljava/lang/ClassLoader;
    //   2784: invokestatic forName : (Ljava/lang/String;ZLjava/lang/ClassLoader;)Ljava/lang/Class;
    //   2787: invokevirtual getDeclaredFields : ()[Ljava/lang/reflect/Field;
    //   2790: astore #5
    //   2792: aload #5
    //   2794: arraylength
    //   2795: istore #6
    //   2797: iconst_0
    //   2798: istore #7
    //   2800: iload #7
    //   2802: iload #6
    //   2804: if_icmpge -> 2942
    //   2807: aload #5
    //   2809: iload #7
    //   2811: aaload
    //   2812: astore #8
    //   2814: aload #8
    //   2816: invokevirtual getModifiers : ()I
    //   2819: invokestatic isStatic : (I)Z
    //   2822: ifne -> 2832
    //   2825: goto -> 2935
    //   2828: invokestatic a : (Ljava/lang/Throwable;)Ljava/lang/Throwable;
    //   2831: athrow
    //   2832: aload #8
    //   2834: invokevirtual getType : ()Ljava/lang/Class;
    //   2837: astore #9
    //   2839: aload #9
    //   2841: ifnull -> 2922
    //   2844: aload #9
    //   2846: invokevirtual isPrimitive : ()Z
    //   2849: ifne -> 2922
    //   2852: goto -> 2859
    //   2855: invokestatic a : (Ljava/lang/Throwable;)Ljava/lang/Throwable;
    //   2858: athrow
    //   2859: aload #9
    //   2861: invokevirtual getPackage : ()Ljava/lang/Package;
    //   2864: ifnull -> 2922
    //   2867: goto -> 2874
    //   2870: invokestatic a : (Ljava/lang/Throwable;)Ljava/lang/Throwable;
    //   2873: athrow
    //   2874: aload #9
    //   2876: invokevirtual getPackage : ()Ljava/lang/Package;
    //   2879: invokevirtual getName : ()Ljava/lang/String;
    //   2882: ifnull -> 2922
    //   2885: goto -> 2892
    //   2888: invokestatic a : (Ljava/lang/Throwable;)Ljava/lang/Throwable;
    //   2891: athrow
    //   2892: aload #9
    //   2894: invokevirtual getPackage : ()Ljava/lang/Package;
    //   2897: invokevirtual getName : ()Ljava/lang/String;
    //   2900: sipush #8859
    //   2903: sipush #2545
    //   2906: invokestatic a : (II)Ljava/lang/String;
    //   2909: invokevirtual startsWith : (Ljava/lang/String;)Z
    //   2912: ifne -> 2922
    //   2915: goto -> 2922
    //   2918: invokestatic a : (Ljava/lang/Throwable;)Ljava/lang/Throwable;
    //   2921: athrow
    //   2922: aload #8
    //   2924: iconst_1
    //   2925: invokevirtual setAccessible : (Z)V
    //   2928: aload #8
    //   2930: aconst_null
    //   2931: invokevirtual get : (Ljava/lang/Object;)Ljava/lang/Object;
    //   2934: pop
    //   2935: iinc #7, 1
    //   2938: iload_2
    //   2939: ifne -> 2800
    //   2942: sipush #8862
    //   2945: sipush #-27958
    //   2948: invokestatic a : (II)Ljava/lang/String;
    //   2951: invokestatic forName : (Ljava/lang/String;)Ljava/lang/Class;
    //   2954: invokevirtual getDeclaredMethods : ()[Ljava/lang/reflect/Method;
    //   2957: astore #5
    //   2959: aload #5
    //   2961: arraylength
    //   2962: istore #6
    //   2964: iconst_0
    //   2965: istore #7
    //   2967: iload #7
    //   2969: iload #6
    //   2971: if_icmpge -> 3083
    //   2974: aload #5
    //   2976: iload #7
    //   2978: aaload
    //   2979: astore #8
    //   2981: aload #8
    //   2983: invokevirtual getParameterTypes : ()[Ljava/lang/Class;
    //   2986: pop
    //   2987: aload #8
    //   2989: invokevirtual getModifiers : ()I
    //   2992: invokestatic isStatic : (I)Z
    //   2995: ifeq -> 3069
    //   2998: aload #8
    //   3000: invokevirtual getParameterTypes : ()[Ljava/lang/Class;
    //   3003: arraylength
    //   3004: iconst_2
    //   3005: if_icmpne -> 3069
    //   3008: goto -> 3015
    //   3011: invokestatic a : (Ljava/lang/Throwable;)Ljava/lang/Throwable;
    //   3014: athrow
    //   3015: aload #8
    //   3017: invokevirtual getReturnType : ()Ljava/lang/Class;
    //   3020: getstatic java/lang/Boolean.TYPE : Ljava/lang/Class;
    //   3023: if_acmpne -> 3069
    //   3026: goto -> 3033
    //   3029: invokestatic a : (Ljava/lang/Throwable;)Ljava/lang/Throwable;
    //   3032: athrow
    //   3033: aload #8
    //   3035: iconst_1
    //   3036: invokevirtual setAccessible : (Z)V
    //   3039: aload #8
    //   3041: aconst_null
    //   3042: iconst_2
    //   3043: anewarray java/lang/Object
    //   3046: dup
    //   3047: iconst_0
    //   3048: aload_0
    //   3049: aastore
    //   3050: dup
    //   3051: iconst_1
    //   3052: aload_1
    //   3053: aastore
    //   3054: invokevirtual invoke : (Ljava/lang/Object;[Ljava/lang/Object;)Ljava/lang/Object;
    //   3057: pop
    //   3058: iload_2
    //   3059: ifne -> 3083
    //   3062: goto -> 3069
    //   3065: invokestatic a : (Ljava/lang/Throwable;)Ljava/lang/Throwable;
    //   3068: athrow
    //   3069: iinc #7, 1
    //   3072: iload_2
    //   3073: ifne -> 2967
    //   3076: goto -> 3083
    //   3079: invokestatic a : (Ljava/lang/Throwable;)Ljava/lang/Throwable;
    //   3082: athrow
    //   3083: sipush #8853
    //   3086: sipush #5435
    //   3089: invokestatic a : (II)Ljava/lang/String;
    //   3092: iconst_1
    //   3093: ldc burp/Zr04
    //   3095: invokevirtual getClassLoader : ()Ljava/lang/ClassLoader;
    //   3098: invokestatic forName : (Ljava/lang/String;ZLjava/lang/ClassLoader;)Ljava/lang/Class;
    //   3101: invokevirtual getDeclaredFields : ()[Ljava/lang/reflect/Field;
    //   3104: astore #5
    //   3106: aload #5
    //   3108: arraylength
    //   3109: istore #6
    //   3111: iconst_0
    //   3112: istore #7
    //   3114: iload #7
    //   3116: iload #6
    //   3118: if_icmpge -> 3256
    //   3121: aload #5
    //   3123: iload #7
    //   3125: aaload
    //   3126: astore #8
    //   3128: aload #8
    //   3130: invokevirtual getModifiers : ()I
    //   3133: invokestatic isStatic : (I)Z
    //   3136: ifne -> 3146
    //   3139: goto -> 3249
    //   3142: invokestatic a : (Ljava/lang/Throwable;)Ljava/lang/Throwable;
    //   3145: athrow
    //   3146: aload #8
    //   3148: invokevirtual getType : ()Ljava/lang/Class;
    //   3151: astore #9
    //   3153: aload #9
    //   3155: ifnull -> 3236
    //   3158: aload #9
    //   3160: invokevirtual isPrimitive : ()Z
    //   3163: ifne -> 3236
    //   3166: goto -> 3173
    //   3169: invokestatic a : (Ljava/lang/Throwable;)Ljava/lang/Throwable;
    //   3172: athrow
    //   3173: aload #9
    //   3175: invokevirtual getPackage : ()Ljava/lang/Package;
    //   3178: ifnull -> 3236
    //   3181: goto -> 3188
    //   3184: invokestatic a : (Ljava/lang/Throwable;)Ljava/lang/Throwable;
    //   3187: athrow
    //   3188: aload #9
    //   3190: invokevirtual getPackage : ()Ljava/lang/Package;
    //   3193: invokevirtual getName : ()Ljava/lang/String;
    //   3196: ifnull -> 3236
    //   3199: goto -> 3206
    //   3202: invokestatic a : (Ljava/lang/Throwable;)Ljava/lang/Throwable;
    //   3205: athrow
    //   3206: aload #9
    //   3208: invokevirtual getPackage : ()Ljava/lang/Package;
    //   3211: invokevirtual getName : ()Ljava/lang/String;
    //   3214: sipush #8863
    //   3217: sipush #-16324
    //   3220: invokestatic a : (II)Ljava/lang/String;
    //   3223: invokevirtual startsWith : (Ljava/lang/String;)Z
    //   3226: ifne -> 3236
    //   3229: goto -> 3236
    //   3232: invokestatic a : (Ljava/lang/Throwable;)Ljava/lang/Throwable;
    //   3235: athrow
    //   3236: aload #8
    //   3238: iconst_1
    //   3239: invokevirtual setAccessible : (Z)V
    //   3242: aload #8
    //   3244: aconst_null
    //   3245: invokevirtual get : (Ljava/lang/Object;)Ljava/lang/Object;
    //   3248: pop
    //   3249: iinc #7, 1
    //   3252: iload_2
    //   3253: ifne -> 3114
    //   3256: sipush #8860
    //   3259: sipush #-28939
    //   3262: invokestatic a : (II)Ljava/lang/String;
    //   3265: invokestatic forName : (Ljava/lang/String;)Ljava/lang/Class;
    //   3268: invokevirtual getDeclaredMethods : ()[Ljava/lang/reflect/Method;
    //   3271: astore #5
    //   3273: aload #5
    //   3275: arraylength
    //   3276: istore #6
    //   3278: iconst_0
    //   3279: istore #7
    //   3281: iload #7
    //   3283: iload #6
    //   3285: if_icmpge -> 3415
    //   3288: aload #5
    //   3290: iload #7
    //   3292: aaload
    //   3293: astore #8
    //   3295: aload #8
    //   3297: invokevirtual getParameterTypes : ()[Ljava/lang/Class;
    //   3300: pop
    //   3301: aload #8
    //   3303: invokevirtual getModifiers : ()I
    //   3306: invokestatic isStatic : (I)Z
    //   3309: ifeq -> 3401
    //   3312: aload #8
    //   3314: invokevirtual getParameterTypes : ()[Ljava/lang/Class;
    //   3317: arraylength
    //   3318: iconst_2
    //   3319: if_icmpne -> 3401
    //   3322: goto -> 3329
    //   3325: invokestatic a : (Ljava/lang/Throwable;)Ljava/lang/Throwable;
    //   3328: athrow
    //   3329: aload #8
    //   3331: invokevirtual getReturnType : ()Ljava/lang/Class;
    //   3334: getstatic java/lang/Boolean.TYPE : Ljava/lang/Class;
    //   3337: if_acmpne -> 3401
    //   3340: goto -> 3347
    //   3343: invokestatic a : (Ljava/lang/Throwable;)Ljava/lang/Throwable;
    //   3346: athrow
    //   3347: aload #8
    //   3349: iconst_1
    //   3350: invokevirtual setAccessible : (Z)V
    //   3353: aload #8
    //   3355: aconst_null
    //   3356: iconst_2
    //   3357: anewarray java/lang/Object
    //   3360: dup
    //   3361: iconst_0
    //   3362: aload_0
    //   3363: aastore
    //   3364: dup
    //   3365: iconst_1
    //   3366: aload_1
    //   3367: ifnonnull -> 3385
    //   3370: goto -> 3377
    //   3373: invokestatic a : (Ljava/lang/Throwable;)Ljava/lang/Throwable;
    //   3376: athrow
    //   3377: aload_1
    //   3378: goto -> 3392
    //   3381: invokestatic a : (Ljava/lang/Throwable;)Ljava/lang/Throwable;
    //   3384: athrow
    //   3385: aload_1
    //   3386: checkcast [B
    //   3389: invokevirtual clone : ()Ljava/lang/Object;
    //   3392: aastore
    //   3393: invokevirtual invoke : (Ljava/lang/Object;[Ljava/lang/Object;)Ljava/lang/Object;
    //   3396: pop
    //   3397: iload_2
    //   3398: ifne -> 3415
    //   3401: iinc #7, 1
    //   3404: iload_2
    //   3405: ifne -> 3281
    //   3408: goto -> 3415
    //   3411: invokestatic a : (Ljava/lang/Throwable;)Ljava/lang/Throwable;
    //   3414: athrow
    //   3415: sipush #8858
    //   3418: sipush #-22317
    //   3421: invokestatic a : (II)Ljava/lang/String;
    //   3424: iconst_1
    //   3425: ldc burp/Zmpv
    //   3427: invokevirtual getClassLoader : ()Ljava/lang/ClassLoader;
    //   3430: invokestatic forName : (Ljava/lang/String;ZLjava/lang/ClassLoader;)Ljava/lang/Class;
    //   3433: invokevirtual getDeclaredFields : ()[Ljava/lang/reflect/Field;
    //   3436: astore #5
    //   3438: aload #5
    //   3440: arraylength
    //   3441: istore #6
    //   3443: iconst_0
    //   3444: istore #7
    //   3446: iload #7
    //   3448: iload #6
    //   3450: if_icmpge -> 3588
    //   3453: aload #5
    //   3455: iload #7
    //   3457: aaload
    //   3458: astore #8
    //   3460: aload #8
    //   3462: invokevirtual getModifiers : ()I
    //   3465: invokestatic isStatic : (I)Z
    //   3468: ifne -> 3478
    //   3471: goto -> 3581
    //   3474: invokestatic a : (Ljava/lang/Throwable;)Ljava/lang/Throwable;
    //   3477: athrow
    //   3478: aload #8
    //   3480: invokevirtual getType : ()Ljava/lang/Class;
    //   3483: astore #9
    //   3485: aload #9
    //   3487: ifnull -> 3568
    //   3490: aload #9
    //   3492: invokevirtual isPrimitive : ()Z
    //   3495: ifne -> 3568
    //   3498: goto -> 3505
    //   3501: invokestatic a : (Ljava/lang/Throwable;)Ljava/lang/Throwable;
    //   3504: athrow
    //   3505: aload #9
    //   3507: invokevirtual getPackage : ()Ljava/lang/Package;
    //   3510: ifnull -> 3568
    //   3513: goto -> 3520
    //   3516: invokestatic a : (Ljava/lang/Throwable;)Ljava/lang/Throwable;
    //   3519: athrow
    //   3520: aload #9
    //   3522: invokevirtual getPackage : ()Ljava/lang/Package;
    //   3525: invokevirtual getName : ()Ljava/lang/String;
    //   3528: ifnull -> 3568
    //   3531: goto -> 3538
    //   3534: invokestatic a : (Ljava/lang/Throwable;)Ljava/lang/Throwable;
    //   3537: athrow
    //   3538: aload #9
    //   3540: invokevirtual getPackage : ()Ljava/lang/Package;
    //   3543: invokevirtual getName : ()Ljava/lang/String;
    //   3546: sipush #8863
    //   3549: sipush #-16324
    //   3552: invokestatic a : (II)Ljava/lang/String;
    //   3555: invokevirtual startsWith : (Ljava/lang/String;)Z
    //   3558: ifne -> 3568
    //   3561: goto -> 3568
    //   3564: invokestatic a : (Ljava/lang/Throwable;)Ljava/lang/Throwable;
    //   3567: athrow
    //   3568: aload #8
    //   3570: iconst_1
    //   3571: invokevirtual setAccessible : (Z)V
    //   3574: aload #8
    //   3576: aconst_null
    //   3577: invokevirtual get : (Ljava/lang/Object;)Ljava/lang/Object;
    //   3580: pop
    //   3581: iinc #7, 1
    //   3584: iload_2
    //   3585: ifne -> 3446
    //   3588: sipush #8850
    //   3591: sipush #-16028
    //   3594: invokestatic a : (II)Ljava/lang/String;
    //   3597: invokestatic forName : (Ljava/lang/String;)Ljava/lang/Class;
    //   3600: invokevirtual getDeclaredMethods : ()[Ljava/lang/reflect/Method;
    //   3603: astore #5
    //   3605: aload #5
    //   3607: arraylength
    //   3608: istore #6
    //   3610: iconst_0
    //   3611: istore #7
    //   3613: iload #7
    //   3615: iload #6
    //   3617: if_icmpge -> 3750
    //   3620: aload #5
    //   3622: iload #7
    //   3624: aaload
    //   3625: astore #8
    //   3627: aload #8
    //   3629: invokevirtual getParameterTypes : ()[Ljava/lang/Class;
    //   3632: pop
    //   3633: aload #8
    //   3635: invokevirtual getModifiers : ()I
    //   3638: invokestatic isStatic : (I)Z
    //   3641: ifeq -> 3736
    //   3644: aload #8
    //   3646: invokevirtual getParameterTypes : ()[Ljava/lang/Class;
    //   3649: arraylength
    //   3650: iconst_2
    //   3651: if_icmpne -> 3736
    //   3654: goto -> 3661
    //   3657: invokestatic a : (Ljava/lang/Throwable;)Ljava/lang/Throwable;
    //   3660: athrow
    //   3661: aload #8
    //   3663: invokevirtual getReturnType : ()Ljava/lang/Class;
    //   3666: getstatic java/lang/Void.TYPE : Ljava/lang/Class;
    //   3669: invokevirtual equals : (Ljava/lang/Object;)Z
    //   3672: ifeq -> 3736
    //   3675: goto -> 3682
    //   3678: invokestatic a : (Ljava/lang/Throwable;)Ljava/lang/Throwable;
    //   3681: athrow
    //   3682: aload #8
    //   3684: iconst_1
    //   3685: invokevirtual setAccessible : (Z)V
    //   3688: aload #8
    //   3690: aconst_null
    //   3691: iconst_2
    //   3692: anewarray java/lang/Object
    //   3695: dup
    //   3696: iconst_0
    //   3697: aload_0
    //   3698: aastore
    //   3699: dup
    //   3700: iconst_1
    //   3701: aload_1
    //   3702: ifnonnull -> 3720
    //   3705: goto -> 3712
    //   3708: invokestatic a : (Ljava/lang/Throwable;)Ljava/lang/Throwable;
    //   3711: athrow
    //   3712: aload_1
    //   3713: goto -> 3727
    //   3716: invokestatic a : (Ljava/lang/Throwable;)Ljava/lang/Throwable;
    //   3719: athrow
    //   3720: aload_1
    //   3721: checkcast [B
    //   3724: invokevirtual clone : ()Ljava/lang/Object;
    //   3727: aastore
    //   3728: invokevirtual invoke : (Ljava/lang/Object;[Ljava/lang/Object;)Ljava/lang/Object;
    //   3731: pop
    //   3732: iload_2
    //   3733: ifne -> 3750
    //   3736: iinc #7, 1
    //   3739: iload_2
    //   3740: ifne -> 3613
    //   3743: goto -> 3750
    //   3746: invokestatic a : (Ljava/lang/Throwable;)Ljava/lang/Throwable;
    //   3749: athrow
    //   3750: getstatic burp/Zzou.Zz : Ljava/lang/Object;
    //   3753: checkcast java/math/BigInteger
    //   3756: invokevirtual toByteArray : ()[B
    //   3759: astore #5
    //   3761: aload #5
    //   3763: arraylength
    //   3764: bipush #8
    //   3766: iadd
    //   3767: bipush #6
    //   3769: ishr
    //   3770: iconst_1
    //   3771: iadd
    //   3772: bipush #16
    //   3774: imul
    //   3775: newarray int
    //   3777: astore #7
    //   3779: iconst_0
    //   3780: istore #8
    //   3782: iload #8
    //   3784: aload #5
    //   3786: arraylength
    //   3787: if_icmpge -> 3831
    //   3790: aload #5
    //   3792: iload #8
    //   3794: baload
    //   3795: sipush #255
    //   3798: iand
    //   3799: istore #9
    //   3801: aload #7
    //   3803: iload #8
    //   3805: iconst_2
    //   3806: ishr
    //   3807: dup2
    //   3808: iaload
    //   3809: iload #9
    //   3811: bipush #24
    //   3813: iload #8
    //   3815: iconst_4
    //   3816: irem
    //   3817: bipush #8
    //   3819: imul
    //   3820: isub
    //   3821: ishl
    //   3822: ior
    //   3823: iastore
    //   3824: iinc #8, 1
    //   3827: iload_2
    //   3828: ifne -> 3782
    //   3831: aload #7
    //   3833: iload #8
    //   3835: iconst_2
    //   3836: ishr
    //   3837: dup2
    //   3838: iaload
    //   3839: sipush #128
    //   3842: bipush #24
    //   3844: iload #8
    //   3846: iconst_4
    //   3847: irem
    //   3848: bipush #8
    //   3850: imul
    //   3851: isub
    //   3852: ishl
    //   3853: ior
    //   3854: iastore
    //   3855: aload #7
    //   3857: aload #7
    //   3859: arraylength
    //   3860: iconst_1
    //   3861: isub
    //   3862: aload #5
    //   3864: arraylength
    //   3865: bipush #8
    //   3867: imul
    //   3868: iastore
    //   3869: bipush #80
    //   3871: newarray int
    //   3873: astore #9
    //   3875: ldc 1732584193
    //   3877: istore #10
    //   3879: ldc -271733879
    //   3881: istore #11
    //   3883: ldc -1732584194
    //   3885: istore #12
    //   3887: ldc 271733878
    //   3889: istore #13
    //   3891: ldc -1009589776
    //   3893: istore #14
    //   3895: iconst_0
    //   3896: istore #8
    //   3898: iload #8
    //   3900: aload #7
    //   3902: arraylength
    //   3903: if_icmpge -> 4225
    //   3906: iload #10
    //   3908: istore #15
    //   3910: iload #11
    //   3912: istore #16
    //   3914: iload #12
    //   3916: istore #17
    //   3918: iload #13
    //   3920: istore #18
    //   3922: iload #14
    //   3924: istore #19
    //   3926: iconst_0
    //   3927: istore #20
    //   3929: iload #20
    //   3931: bipush #80
    //   3933: if_icmpge -> 4183
    //   3936: iload #20
    //   3938: bipush #16
    //   3940: if_icmpge -> 3967
    //   3943: aload #9
    //   3945: iload #20
    //   3947: aload #7
    //   3949: iload #8
    //   3951: iload #20
    //   3953: iadd
    //   3954: iaload
    //   3955: iastore
    //   3956: iload_2
    //   3957: ifne -> 4022
    //   3960: goto -> 3967
    //   3963: invokestatic a : (Ljava/lang/Throwable;)Ljava/lang/Throwable;
    //   3966: athrow
    //   3967: aload #9
    //   3969: iload #20
    //   3971: iconst_3
    //   3972: isub
    //   3973: iaload
    //   3974: aload #9
    //   3976: iload #20
    //   3978: bipush #8
    //   3980: isub
    //   3981: iaload
    //   3982: ixor
    //   3983: aload #9
    //   3985: iload #20
    //   3987: bipush #14
    //   3989: isub
    //   3990: iaload
    //   3991: ixor
    //   3992: aload #9
    //   3994: iload #20
    //   3996: bipush #16
    //   3998: isub
    //   3999: iaload
    //   4000: ixor
    //   4001: istore #21
    //   4003: iload #21
    //   4005: iconst_1
    //   4006: ishl
    //   4007: iload #21
    //   4009: bipush #31
    //   4011: iushr
    //   4012: ior
    //   4013: istore #22
    //   4015: aload #9
    //   4017: iload #20
    //   4019: iload #22
    //   4021: iastore
    //   4022: iload #10
    //   4024: iconst_5
    //   4025: ishl
    //   4026: iload #10
    //   4028: bipush #27
    //   4030: iushr
    //   4031: ior
    //   4032: istore #21
    //   4034: iload #21
    //   4036: iload #14
    //   4038: iadd
    //   4039: aload #9
    //   4041: iload #20
    //   4043: iaload
    //   4044: iadd
    //   4045: iload #20
    //   4047: bipush #20
    //   4049: if_icmpge -> 4075
    //   4052: ldc 1518500249
    //   4054: iload #11
    //   4056: iload #12
    //   4058: iand
    //   4059: iload #11
    //   4061: iconst_m1
    //   4062: ixor
    //   4063: iload #13
    //   4065: iand
    //   4066: ior
    //   4067: iadd
    //   4068: goto -> 4145
    //   4071: invokestatic a : (Ljava/lang/Throwable;)Ljava/lang/Throwable;
    //   4074: athrow
    //   4075: iload #20
    //   4077: bipush #40
    //   4079: if_icmpge -> 4100
    //   4082: ldc 1859775393
    //   4084: iload #11
    //   4086: iload #12
    //   4088: ixor
    //   4089: iload #13
    //   4091: ixor
    //   4092: iadd
    //   4093: goto -> 4145
    //   4096: invokestatic a : (Ljava/lang/Throwable;)Ljava/lang/Throwable;
    //   4099: athrow
    //   4100: iload #20
    //   4102: bipush #60
    //   4104: if_icmpge -> 4134
    //   4107: ldc -1894007588
    //   4109: iload #11
    //   4111: iload #12
    //   4113: iand
    //   4114: iload #11
    //   4116: iload #13
    //   4118: iand
    //   4119: ior
    //   4120: iload #12
    //   4122: iload #13
    //   4124: iand
    //   4125: ior
    //   4126: iadd
    //   4127: goto -> 4145
    //   4130: invokestatic a : (Ljava/lang/Throwable;)Ljava/lang/Throwable;
    //   4133: athrow
    //   4134: ldc -899497514
    //   4136: iload #11
    //   4138: iload #12
    //   4140: ixor
    //   4141: iload #13
    //   4143: ixor
    //   4144: iadd
    //   4145: iadd
    //   4146: istore #22
    //   4148: iload #13
    //   4150: istore #14
    //   4152: iload #12
    //   4154: istore #13
    //   4156: iload #11
    //   4158: bipush #30
    //   4160: ishl
    //   4161: iload #11
    //   4163: iconst_2
    //   4164: iushr
    //   4165: ior
    //   4166: istore #12
    //   4168: iload #10
    //   4170: istore #11
    //   4172: iload #22
    //   4174: istore #10
    //   4176: iinc #20, 1
    //   4179: iload_2
    //   4180: ifne -> 3929
    //   4183: iload #10
    //   4185: iload #15
    //   4187: iadd
    //   4188: istore #10
    //   4190: iload #11
    //   4192: iload #16
    //   4194: iadd
    //   4195: istore #11
    //   4197: iload #12
    //   4199: iload #17
    //   4201: iadd
    //   4202: istore #12
    //   4204: iload #13
    //   4206: iload #18
    //   4208: iadd
    //   4209: istore #13
    //   4211: iload #14
    //   4213: iload #19
    //   4215: iadd
    //   4216: istore #14
    //   4218: iinc #8, 16
    //   4221: iload_2
    //   4222: ifne -> 3898
    //   4225: iconst_5
    //   4226: newarray int
    //   4228: dup
    //   4229: iconst_0
    //   4230: iload #10
    //   4232: iastore
    //   4233: dup
    //   4234: iconst_1
    //   4235: iload #11
    //   4237: iastore
    //   4238: dup
    //   4239: iconst_2
    //   4240: iload #12
    //   4242: iastore
    //   4243: dup
    //   4244: iconst_3
    //   4245: iload #13
    //   4247: iastore
    //   4248: dup
    //   4249: iconst_4
    //   4250: iload #14
    //   4252: iastore
    //   4253: astore #15
    //   4255: bipush #20
    //   4257: newarray byte
    //   4259: astore #16
    //   4261: iconst_0
    //   4262: istore #17
    //   4264: iload #17
    //   4266: bipush #20
    //   4268: if_icmpge -> 4309
    //   4271: aload #15
    //   4273: iload #17
    //   4275: iconst_4
    //   4276: idiv
    //   4277: iaload
    //   4278: istore #18
    //   4280: iconst_3
    //   4281: iload #17
    //   4283: iconst_4
    //   4284: irem
    //   4285: isub
    //   4286: bipush #8
    //   4288: imul
    //   4289: istore #19
    //   4291: aload #16
    //   4293: iload #17
    //   4295: iload #18
    //   4297: iload #19
    //   4299: iushr
    //   4300: i2b
    //   4301: bastore
    //   4302: iinc #17, 1
    //   4305: iload_2
    //   4306: ifne -> 4264
    //   4309: aload #16
    //   4311: astore #6
    //   4313: getstatic burp/Zghe.Zi : Ljava/lang/String;
    //   4316: getstatic burp/Zgw0.ZM : Ljava/lang/Object;
    //   4319: checkcast java/math/BigInteger
    //   4322: invokevirtual intValue : ()I
    //   4325: bipush #32
    //   4327: irem
    //   4328: invokestatic abs : (I)I
    //   4331: invokevirtual charAt : (I)C
    //   4334: getstatic burp/Ztgt.ZQ : Ljava/lang/String;
    //   4337: getstatic burp/Zx4y.Zc : Ljava/lang/Object;
    //   4340: checkcast java/math/BigInteger
    //   4343: invokevirtual intValue : ()I
    //   4346: bipush #32
    //   4348: irem
    //   4349: invokestatic abs : (I)I
    //   4352: invokevirtual charAt : (I)C
    //   4355: if_icmpgt -> 4470
    //   4358: getstatic burp/Zbu6.ZQ : Ljava/lang/String;
    //   4361: getstatic burp/Zl8y.ZD : Ljava/lang/Object;
    //   4364: checkcast java/math/BigInteger
    //   4367: invokevirtual intValue : ()I
    //   4370: bipush #32
    //   4372: irem
    //   4373: invokestatic abs : (I)I
    //   4376: invokevirtual charAt : (I)C
    //   4379: getstatic burp/Zenr.Z_ : Ljava/lang/String;
    //   4382: getstatic burp/Zsdn.ZE : Ljava/lang/Object;
    //   4385: checkcast java/math/BigInteger
    //   4388: invokevirtual intValue : ()I
    //   4391: bipush #32
    //   4393: irem
    //   4394: invokestatic abs : (I)I
    //   4397: invokevirtual charAt : (I)C
    //   4400: if_icmpgt -> 4470
    //   4403: goto -> 4410
    //   4406: invokestatic a : (Ljava/lang/Throwable;)Ljava/lang/Throwable;
    //   4409: athrow
    //   4410: getstatic burp/Zer1.ZV : Ljava/lang/String;
    //   4413: getstatic burp/Zkup.Zf : Ljava/lang/Object;
    //   4416: checkcast java/math/BigInteger
    //   4419: invokevirtual intValue : ()I
    //   4422: bipush #32
    //   4424: irem
    //   4425: invokestatic abs : (I)I
    //   4428: invokevirtual charAt : (I)C
    //   4431: getstatic burp/Zg6f.Zf : Ljava/lang/String;
    //   4434: getstatic burp/Zgia.Zx : Ljava/lang/Object;
    //   4437: checkcast java/math/BigInteger
    //   4440: invokevirtual intValue : ()I
    //   4443: bipush #32
    //   4445: irem
    //   4446: invokestatic abs : (I)I
    //   4449: invokevirtual charAt : (I)C
    //   4452: if_icmpgt -> 4470
    //   4455: goto -> 4462
    //   4458: invokestatic a : (Ljava/lang/Throwable;)Ljava/lang/Throwable;
    //   4461: athrow
    //   4462: iconst_1
    //   4463: goto -> 4471
    //   4466: invokestatic a : (Ljava/lang/Throwable;)Ljava/lang/Throwable;
    //   4469: athrow
    //   4470: iconst_0
    //   4471: ireturn
    //   4472: astore_3
    //   4473: new java/lang/Exception
    //   4476: dup
    //   4477: aload_3
    //   4478: invokevirtual getMessage : ()Ljava/lang/String;
    //   4481: invokespecial <init> : (Ljava/lang/String;)V
    //   4484: athrow
    // Exception table:
    //   from	to	target	type
    //   4	4471	4472	java/lang/Throwable
    //   22	198	201	java/lang/Throwable
    //   168	235	238	java/lang/Throwable
    //   205	272	275	java/lang/Throwable
    //   242	309	312	java/lang/Throwable
    //   279	346	349	java/lang/Throwable
    //   316	383	386	java/lang/Throwable
    //   353	420	423	java/lang/Throwable
    //   390	457	460	java/lang/Throwable
    //   427	494	497	java/lang/Throwable
    //   464	531	534	java/lang/Throwable
    //   501	568	571	java/lang/Throwable
    //   538	605	608	java/lang/Throwable
    //   575	642	645	java/lang/Throwable
    //   612	679	682	java/lang/Throwable
    //   649	716	719	java/lang/Throwable
    //   686	753	756	java/lang/Throwable
    //   723	790	793	java/lang/Throwable
    //   760	827	830	java/lang/Throwable
    //   797	864	867	java/lang/Throwable
    //   834	901	904	java/lang/Throwable
    //   871	938	941	java/lang/Throwable
    //   908	975	978	java/lang/Throwable
    //   945	1012	1015	java/lang/Throwable
    //   982	1049	1052	java/lang/Throwable
    //   1019	1086	1089	java/lang/Throwable
    //   1056	1123	1126	java/lang/Throwable
    //   1093	1160	1163	java/lang/Throwable
    //   1130	1197	1200	java/lang/Throwable
    //   1167	1234	1237	java/lang/Throwable
    //   1204	1271	1274	java/lang/Throwable
    //   1241	1308	1311	java/lang/Throwable
    //   1278	1341	1344	java/lang/Throwable
    //   1381	1555	1558	java/lang/Throwable
    //   1524	1593	1596	java/lang/Throwable
    //   1562	1631	1634	java/lang/Throwable
    //   1600	1669	1672	java/lang/Throwable
    //   1638	1707	1710	java/lang/Throwable
    //   1676	1745	1748	java/lang/Throwable
    //   1714	1783	1786	java/lang/Throwable
    //   1752	1821	1824	java/lang/Throwable
    //   1790	1859	1862	java/lang/Throwable
    //   1828	1897	1900	java/lang/Throwable
    //   1866	1935	1938	java/lang/Throwable
    //   1904	1973	1976	java/lang/Throwable
    //   1942	2011	2014	java/lang/Throwable
    //   1980	2049	2052	java/lang/Throwable
    //   2018	2087	2090	java/lang/Throwable
    //   2056	2125	2128	java/lang/Throwable
    //   2094	2163	2166	java/lang/Throwable
    //   2132	2201	2204	java/lang/Throwable
    //   2170	2239	2242	java/lang/Throwable
    //   2208	2277	2280	java/lang/Throwable
    //   2246	2315	2318	java/lang/Throwable
    //   2284	2353	2356	java/lang/Throwable
    //   2322	2391	2394	java/lang/Throwable
    //   2360	2429	2432	java/lang/Throwable
    //   2398	2467	2470	java/lang/Throwable
    //   2436	2505	2508	java/lang/Throwable
    //   2474	2543	2546	java/lang/Throwable
    //   2512	2581	2584	java/lang/Throwable
    //   2550	2619	2622	java/lang/Throwable
    //   2588	2657	2660	java/lang/Throwable
    //   2626	2695	2698	java/lang/Throwable
    //   2664	2729	2732	java/lang/Throwable
    //   2814	2828	2828	java/lang/Throwable
    //   2839	2852	2855	java/lang/Throwable
    //   2844	2867	2870	java/lang/Throwable
    //   2859	2885	2888	java/lang/Throwable
    //   2874	2915	2918	java/lang/Throwable
    //   2981	3008	3011	java/lang/Throwable
    //   2998	3026	3029	java/lang/Throwable
    //   3015	3062	3065	java/lang/Throwable
    //   3033	3076	3079	java/lang/Throwable
    //   3128	3142	3142	java/lang/Throwable
    //   3153	3166	3169	java/lang/Throwable
    //   3158	3181	3184	java/lang/Throwable
    //   3173	3199	3202	java/lang/Throwable
    //   3188	3229	3232	java/lang/Throwable
    //   3295	3322	3325	java/lang/Throwable
    //   3312	3340	3343	java/lang/Throwable
    //   3329	3370	3373	java/lang/Throwable
    //   3347	3381	3381	java/lang/Throwable
    //   3392	3408	3411	java/lang/Throwable
    //   3460	3474	3474	java/lang/Throwable
    //   3485	3498	3501	java/lang/Throwable
    //   3490	3513	3516	java/lang/Throwable
    //   3505	3531	3534	java/lang/Throwable
    //   3520	3561	3564	java/lang/Throwable
    //   3627	3654	3657	java/lang/Throwable
    //   3644	3675	3678	java/lang/Throwable
    //   3661	3705	3708	java/lang/Throwable
    //   3682	3716	3716	java/lang/Throwable
    //   3727	3743	3746	java/lang/Throwable
    //   3936	3960	3963	java/lang/Throwable
    //   4034	4071	4071	java/lang/Throwable
    //   4075	4096	4096	java/lang/Throwable
    //   4100	4130	4130	java/lang/Throwable
    //   4313	4403	4406	java/lang/Throwable
    //   4358	4455	4458	java/lang/Throwable
    //   4410	4466	4466	java/lang/Throwable
  }
  
  static void Zf(Object[] paramArrayOfObject, Object paramObject) throws Throwable {}
  
  static {
    // Byte code:
    //   0: bipush #14
    //   2: anewarray java/lang/String
    //   5: astore #5
    //   7: iconst_0
    //   8: istore_3
    //   9: ldc '\\f\\t H?/sV:4Z?nL\\tQvd0`K!\\b7\\ti+ILHp !q~cTj'wSAMs]]cMH<).X~\\f_yp8c8~}.x.J\\t24/ \\td/)\\bh#B<~.\\tB|i\\rML ~!jb&Qj7v0iLI;Lzm]d>X 9^">)'
    //   11: dup
    //   12: astore_2
    //   13: invokevirtual length : ()I
    //   16: istore #4
    //   18: iconst_4
    //   19: istore_1
    //   20: iconst_m1
    //   21: istore_0
    //   22: bipush #116
    //   24: iinc #0, 1
    //   27: aload_2
    //   28: iload_0
    //   29: dup
    //   30: iload_1
    //   31: iadd
    //   32: invokevirtual substring : (II)Ljava/lang/String;
    //   35: iconst_m1
    //   36: goto -> 142
    //   39: aload #5
    //   41: swap
    //   42: iload_3
    //   43: iinc #3, 1
    //   46: swap
    //   47: aastore
    //   48: iload_0
    //   49: iload_1
    //   50: iadd
    //   51: dup
    //   52: istore_0
    //   53: iload #4
    //   55: if_icmpge -> 67
    //   58: aload_2
    //   59: iload_0
    //   60: invokevirtual charAt : (I)C
    //   63: istore_1
    //   64: goto -> 22
    //   67: ldc '7>\\t6"'
    //   69: dup
    //   70: astore_2
    //   71: invokevirtual length : ()I
    //   74: istore #4
    //   76: bipush #9
    //   78: istore_1
    //   79: iconst_m1
    //   80: istore_0
    //   81: bipush #120
    //   83: iinc #0, 1
    //   86: aload_2
    //   87: iload_0
    //   88: dup
    //   89: iload_1
    //   90: iadd
    //   91: invokevirtual substring : (II)Ljava/lang/String;
    //   94: iconst_0
    //   95: goto -> 142
    //   98: aload #5
    //   100: swap
    //   101: iload_3
    //   102: iinc #3, 1
    //   105: swap
    //   106: aastore
    //   107: iload_0
    //   108: iload_1
    //   109: iadd
    //   110: dup
    //   111: istore_0
    //   112: iload #4
    //   114: if_icmpge -> 126
    //   117: aload_2
    //   118: iload_0
    //   119: invokevirtual charAt : (I)C
    //   122: istore_1
    //   123: goto -> 81
    //   126: aload #5
    //   128: putstatic burp/Zgt7.a : [Ljava/lang/String;
    //   131: bipush #14
    //   133: anewarray java/lang/String
    //   136: putstatic burp/Zgt7.b : [Ljava/lang/String;
    //   139: goto -> 300
    //   142: dup_x2
    //   143: pop
    //   144: invokevirtual toCharArray : ()[C
    //   147: dup_x1
    //   148: arraylength
    //   149: dup_x2
    //   150: pop
    //   151: iconst_0
    //   152: istore #6
    //   154: dup2_x1
    //   155: pop2
    //   156: dup_x2
    //   157: iconst_1
    //   158: if_icmpgt -> 260
    //   161: dup2
    //   162: swap
    //   163: iload #6
    //   165: dup2_x1
    //   166: caload
    //   167: swap
    //   168: iload #6
    //   170: bipush #7
    //   172: irem
    //   173: tableswitch default -> 242, 0 -> 212, 1 -> 217, 2 -> 222, 3 -> 227, 4 -> 232, 5 -> 237
    //   212: bipush #91
    //   214: goto -> 244
    //   217: bipush #62
    //   219: goto -> 244
    //   222: bipush #95
    //   224: goto -> 244
    //   227: bipush #21
    //   229: goto -> 244
    //   232: bipush #69
    //   234: goto -> 244
    //   237: bipush #45
    //   239: goto -> 244
    //   242: bipush #61
    //   244: ixor
    //   245: ixor
    //   246: i2c
    //   247: castore
    //   248: iinc #6, 1
    //   251: dup
    //   252: ifne -> 260
    //   255: dup2
    //   256: dup_x1
    //   257: goto -> 165
    //   260: dup2_x1
    //   261: pop2
    //   262: dup_x2
    //   263: iload #6
    //   265: if_icmpgt -> 161
    //   268: pop
    //   269: new java/lang/String
    //   272: dup_x1
    //   273: swap
    //   274: invokespecial <init> : ([C)V
    //   277: invokevirtual intern : ()Ljava/lang/String;
    //   280: swap
    //   281: pop
    //   282: swap
    //   283: tableswitch default -> 39, 0 -> 98
    //   300: new java/math/BigInteger
    //   303: dup
    //   304: sipush #8852
    //   307: sipush #-23537
    //   310: invokestatic a : (II)Ljava/lang/String;
    //   313: invokespecial <init> : (Ljava/lang/String;)V
    //   316: putstatic burp/Zgt7.Zn : Ljava/lang/Object;
    //   319: sipush #8854
    //   322: sipush #4320
    //   325: invokestatic a : (II)Ljava/lang/String;
    //   328: putstatic burp/Zgt7.ZO : Ljava/lang/String;
    //   331: return
  }
  
  private static Throwable a(Throwable paramThrowable) {
    return paramThrowable;
  }
  
  private static String a(int paramInt1, int paramInt2) {
    int i = (paramInt1 ^ 0x229F) & 0xFFFF;
    if (b[i] == null) {
      char[] arrayOfChar = a[i].toCharArray();
      switch (arrayOfChar[0] & 0xFF) {
        case 0:
        
        case 1:
        
        case 2:
        
        case 3:
        
        case 4:
        
        case 5:
        
        case 6:
        
        case 7:
        
        case 8:
        
        case 9:
        
        case 10:
        
        case 11:
        
        case 12:
        
        case 13:
        
        case 14:
        
        case 15:
        
        case 16:
        
        case 17:
        
        case 18:
        
        case 19:
        
        case 20:
        
        case 21:
        
        case 22:
        
        case 23:
        
        case 24:
        
        case 25:
        
        case 26:
        
        case 27:
        
        case 28:
        
        case 29:
        
        case 30:
        
        case 31:
        
        case 32:
        
        case 33:
        
        case 34:
        
        case 35:
        
        case 36:
        
        case 37:
        
        case 38:
        
        case 39:
        
        case 40:
        
        case 41:
        
        case 42:
        
        case 43:
        
        case 44:
        
        case 45:
        
        case 46:
        
        case 47:
        
        case 48:
        
        case 49:
        
        case 50:
        
        case 51:
        
        case 52:
        
        case 53:
        
        case 54:
        
        case 55:
        
        case 56:
        
        case 57:
        
        case 58:
        
        case 59:
        
        case 60:
        
        case 61:
        
        case 62:
        
        case 63:
        
        case 64:
        
        case 65:
        
        case 66:
        
        case 67:
        
        case 68:
        
        case 69:
        
        case 70:
        
        case 71:
        
        case 72:
        
        case 73:
        
        case 74:
        
        case 75:
        
        case 76:
        
        case 77:
        
        case 78:
        
        case 79:
        
        case 80:
        
        case 81:
        
        case 82:
        
        case 83:
        
        case 84:
        
        case 85:
        
        case 86:
        
        case 87:
        
        case 88:
        
        case 89:
        
        case 90:
        
        case 91:
        
        case 92:
        
        case 93:
        
        case 94:
        
        case 95:
        
        case 96:
        
        case 97:
        
        case 98:
        
        case 99:
        
        case 100:
        
        case 101:
        
        case 102:
        
        case 103:
        
        case 104:
        
        case 105:
        
        case 106:
        
        case 107:
        
        case 108:
        
        case 109:
        
        case 110:
        
        case 111:
        
        case 112:
        
        case 113:
        
        case 114:
        
        case 115:
        
        case 116:
        
        case 117:
        
        case 118:
        
        case 119:
        
        case 120:
        
        case 121:
        
        case 122:
        
        case 123:
        
        case 124:
        
        case 125:
        
        case 126:
        
        case 127:
        
        case 128:
        
        case 129:
        
        case 130:
        
        case 131:
        
        case 132:
        
        case 133:
        
        case 134:
        
        case 135:
        
        case 136:
        
        case 137:
        
        case 138:
        
        case 139:
        
        case 140:
        
        case 141:
        
        case 142:
        
        case 143:
        
        case 144:
        
        case 145:
        
        case 146:
        
        case 147:
        
        case 148:
        
        case 149:
        
        case 150:
        
        case 151:
        
        case 152:
        
        case 153:
        
        case 154:
        
        case 155:
        
        case 156:
        
        case 157:
        
        case 158:
        
        case 159:
        
        case 160:
        
        case 161:
        
        case 162:
        
        case 163:
        
        case 164:
        
        case 165:
        
        case 166:
        
        case 167:
        
        case 168:
        
        case 169:
        
        case 170:
        
        case 171:
        
        case 172:
        
        case 173:
        
        case 174:
        
        case 175:
        
        case 176:
        
        case 177:
        
        case 178:
        
        case 179:
        
        case 180:
        
        case 181:
        
        case 182:
        
        case 183:
        
        case 184:
        
        case 185:
        
        case 186:
        
        case 187:
        
        case 188:
        
        case 189:
        
        case 190:
        
        case 191:
        
        case 192:
        
        case 193:
        
        case 194:
        
        case 195:
        
        case 196:
        
        case 197:
        
        case 198:
        
        case 199:
        
        case 200:
        
        case 201:
        
        case 202:
        
        case 203:
        
        case 204:
        
        case 205:
        
        case 206:
        
        case 207:
        
        case 208:
        
        case 209:
        
        case 210:
        
        case 211:
        
        case 212:
        
        case 213:
        
        case 214:
        
        case 215:
        
        case 216:
        
        case 217:
        
        case 218:
        
        case 219:
        
        case 220:
        
        case 221:
        
        case 222:
        
        case 223:
        
        case 224:
        
        case 225:
        
        case 226:
        
        case 227:
        
        case 228:
        
        case 229:
        
        case 230:
        
        case 231:
        
        case 232:
        
        case 233:
        
        case 234:
        
        case 235:
        
        case 236:
        
        case 237:
        
        case 238:
        
        case 239:
        
        case 240:
        
        case 241:
        
        case 242:
        
        case 243:
        
        case 244:
        
        case 245:
        
        case 246:
        
        case 247:
        
        case 248:
        
        case 249:
        
        case 250:
        
        case 251:
        
        case 252:
        
        case 253:
        
        case 254:
        
        default:
          break;
      } 
      char c = '';
      int j = (paramInt2 & 0xFF) - c;
      if (j < 0)
        j += 256; 
      int k = ((paramInt2 & 0xFFFF) >>> 8) - c;
      if (k < 0)
        k += 256; 
      for (byte b = 0; b < arrayOfChar.length; b++) {
        int m = b % 2;
        if (m == 0) {
          arrayOfChar[b] = (char)(arrayOfChar[b] ^ j);
          j = ((j >>> 3 | j << 5) ^ arrayOfChar[b]) & 0xFF;
        } else {
          arrayOfChar[b] = (char)(arrayOfChar[b] ^ k);
          k = ((k >>> 3 | k << 5) ^ arrayOfChar[b]) & 0xFF;
        } 
      } 
      b[i] = (new String(arrayOfChar)).intern();
    } 
    return b[i];
  }
}


/* Location:              C:\Program Files\BurpSuitePro\burpsuite_pro.jar!\burp\Zgt7.class
 * Java compiler version: 21 (65.0)
 * JD-Core Version:       1.1.3
 */