package burp;

public class Zgtb implements Zzrl {
  private final Zzrl Zw;
  
  private static final String[] a;
  
  private static final String[] b;
  
  public Zgtb(String paramString, byte paramByte) {
    this.Zw = new Zvo7(new Zzrl[] { new Zsok(new Zzrl[] { new Zryg(paramString, paramByte), new Zm68(a(2145, 16091) + a(2145, 16091) + paramString, false) }), new Zsok(new Zzrl[] { new Zrsx(paramString, paramByte), new Zm68(a(2146, 21507) + a(2146, 21507) + Zsw8.Zz(paramString), false) }) });
  }
  
  public Zsov ZJ(Zlzh paramZlzh, Zgk_ paramZgk_, byte paramByte1, byte paramByte2, Zkv8 paramZkv8, byte[] paramArrayOfbyte) {
    return this.Zw.ZJ(paramZlzh, paramZgk_, paramByte1, paramByte2, paramZkv8, paramArrayOfbyte);
  }
  
  static {
    // Byte code:
    //   0: iconst_3
    //   1: anewarray java/lang/String
    //   4: astore #5
    //   6: iconst_0
    //   7: istore_3
    //   8: ldc '.þßE÷¿'
    //   10: dup
    //   11: astore_2
    //   12: invokevirtual length : ()I
    //   15: istore #4
    //   17: iconst_2
    //   18: istore_1
    //   19: iconst_m1
    //   20: istore_0
    //   21: iconst_2
    //   22: iinc #0, 1
    //   25: aload_2
    //   26: iload_0
    //   27: dup
    //   28: iload_1
    //   29: iadd
    //   30: invokevirtual substring : (II)Ljava/lang/String;
    //   33: iconst_m1
    //   34: goto -> 80
    //   37: aload #5
    //   39: swap
    //   40: iload_3
    //   41: iinc #3, 1
    //   44: swap
    //   45: aastore
    //   46: iload_0
    //   47: iload_1
    //   48: iadd
    //   49: dup
    //   50: istore_0
    //   51: iload #4
    //   53: if_icmpge -> 65
    //   56: aload_2
    //   57: iload_0
    //   58: invokevirtual charAt : (I)C
    //   61: istore_1
    //   62: goto -> 21
    //   65: aload #5
    //   67: putstatic burp/Zgtb.a : [Ljava/lang/String;
    //   70: iconst_3
    //   71: anewarray java/lang/String
    //   74: putstatic burp/Zgtb.b : [Ljava/lang/String;
    //   77: goto -> 221
    //   80: dup_x2
    //   81: pop
    //   82: invokevirtual toCharArray : ()[C
    //   85: dup_x1
    //   86: arraylength
    //   87: dup_x2
    //   88: pop
    //   89: iconst_0
    //   90: istore #6
    //   92: dup2_x1
    //   93: pop2
    //   94: dup_x2
    //   95: iconst_1
    //   96: if_icmpgt -> 194
    //   99: dup2
    //   100: swap
    //   101: iload #6
    //   103: dup2_x1
    //   104: caload
    //   105: swap
    //   106: iload #6
    //   108: bipush #7
    //   110: irem
    //   111: tableswitch default -> 176, 0 -> 148, 1 -> 153, 2 -> 158, 3 -> 162, 4 -> 167, 5 -> 171
    //   148: bipush #89
    //   150: goto -> 178
    //   153: bipush #115
    //   155: goto -> 178
    //   158: iconst_4
    //   159: goto -> 178
    //   162: bipush #63
    //   164: goto -> 178
    //   167: iconst_4
    //   168: goto -> 178
    //   171: bipush #95
    //   173: goto -> 178
    //   176: bipush #102
    //   178: ixor
    //   179: ixor
    //   180: i2c
    //   181: castore
    //   182: iinc #6, 1
    //   185: dup
    //   186: ifne -> 194
    //   189: dup2
    //   190: dup_x1
    //   191: goto -> 103
    //   194: dup2_x1
    //   195: pop2
    //   196: dup_x2
    //   197: iload #6
    //   199: if_icmpgt -> 99
    //   202: pop
    //   203: new java/lang/String
    //   206: dup_x1
    //   207: swap
    //   208: invokespecial <init> : ([C)V
    //   211: invokevirtual intern : ()Ljava/lang/String;
    //   214: swap
    //   215: pop
    //   216: swap
    //   217: pop
    //   218: goto -> 37
    //   221: return
  }
  
  private static String a(int paramInt1, int paramInt2) {
    int i = (paramInt1 ^ 0x860) & 0xFFFF;
    if (b[i] == null) {
      char[] arrayOfChar = a[i].toCharArray();
      switch (arrayOfChar[0] & 0xFF) {
        case 0:
        
        case 1:
        
        case 2:
        
        case 3:
        
        case 4:
        
        case 5:
        
        case 6:
        
        case 7:
        
        case 8:
        
        case 9:
        
        case 10:
        
        case 11:
        
        case 12:
        
        case 13:
        
        case 14:
        
        case 15:
        
        case 16:
        
        case 17:
        
        case 18:
        
        case 19:
        
        case 20:
        
        case 21:
        
        case 22:
        
        case 23:
        
        case 24:
        
        case 25:
        
        case 26:
        
        case 27:
        
        case 28:
        
        case 29:
        
        case 30:
        
        case 31:
        
        case 32:
        
        case 33:
        
        case 34:
        
        case 35:
        
        case 36:
        
        case 37:
        
        case 38:
        
        case 39:
        
        case 40:
        
        case 41:
        
        case 42:
        
        case 43:
        
        case 44:
        
        case 45:
        
        case 46:
        
        case 47:
        
        case 48:
        
        case 49:
        
        case 50:
        
        case 51:
        
        case 52:
        
        case 53:
        
        case 54:
        
        case 55:
        
        case 56:
        
        case 57:
        
        case 58:
        
        case 59:
        
        case 60:
        
        case 61:
        
        case 62:
        
        case 63:
        
        case 64:
        
        case 65:
        
        case 66:
        
        case 67:
        
        case 68:
        
        case 69:
        
        case 70:
        
        case 71:
        
        case 72:
        
        case 73:
        
        case 74:
        
        case 75:
        
        case 76:
        
        case 77:
        
        case 78:
        
        case 79:
        
        case 80:
        
        case 81:
        
        case 82:
        
        case 83:
        
        case 84:
        
        case 85:
        
        case 86:
        
        case 87:
        
        case 88:
        
        case 89:
        
        case 90:
        
        case 91:
        
        case 92:
        
        case 93:
        
        case 94:
        
        case 95:
        
        case 96:
        
        case 97:
        
        case 98:
        
        case 99:
        
        case 100:
        
        case 101:
        
        case 102:
        
        case 103:
        
        case 104:
        
        case 105:
        
        case 106:
        
        case 107:
        
        case 108:
        
        case 109:
        
        case 110:
        
        case 111:
        
        case 112:
        
        case 113:
        
        case 114:
        
        case 115:
        
        case 116:
        
        case 117:
        
        case 118:
        
        case 119:
        
        case 120:
        
        case 121:
        
        case 122:
        
        case 123:
        
        case 124:
        
        case 125:
        
        case 126:
        
        case 127:
        
        case 128:
        
        case 129:
        
        case 130:
        
        case 131:
        
        case 132:
        
        case 133:
        
        case 134:
        
        case 135:
        
        case 136:
        
        case 137:
        
        case 138:
        
        case 139:
        
        case 140:
        
        case 141:
        
        case 142:
        
        case 143:
        
        case 144:
        
        case 145:
        
        case 146:
        
        case 147:
        
        case 148:
        
        case 149:
        
        case 150:
        
        case 151:
        
        case 152:
        
        case 153:
        
        case 154:
        
        case 155:
        
        case 156:
        
        case 157:
        
        case 158:
        
        case 159:
        
        case 160:
        
        case 161:
        
        case 162:
        
        case 163:
        
        case 164:
        
        case 165:
        
        case 166:
        
        case 167:
        
        case 168:
        
        case 169:
        
        case 170:
        
        case 171:
        
        case 172:
        
        case 173:
        
        case 174:
        
        case 175:
        
        case 176:
        
        case 177:
        
        case 178:
        
        case 179:
        
        case 180:
        
        case 181:
        
        case 182:
        
        case 183:
        
        case 184:
        
        case 185:
        
        case 186:
        
        case 187:
        
        case 188:
        
        case 189:
        
        case 190:
        
        case 191:
        
        case 192:
        
        case 193:
        
        case 194:
        
        case 195:
        
        case 196:
        
        case 197:
        
        case 198:
        
        case 199:
        
        case 200:
        
        case 201:
        
        case 202:
        
        case 203:
        
        case 204:
        
        case 205:
        
        case 206:
        
        case 207:
        
        case 208:
        
        case 209:
        
        case 210:
        
        case 211:
        
        case 212:
        
        case 213:
        
        case 214:
        
        case 215:
        
        case 216:
        
        case 217:
        
        case 218:
        
        case 219:
        
        case 220:
        
        case 221:
        
        case 222:
        
        case 223:
        
        case 224:
        
        case 225:
        
        case 226:
        
        case 227:
        
        case 228:
        
        case 229:
        
        case 230:
        
        case 231:
        
        case 232:
        
        case 233:
        
        case 234:
        
        case 235:
        
        case 236:
        
        case 237:
        
        case 238:
        
        case 239:
        
        case 240:
        
        case 241:
        
        case 242:
        
        case 243:
        
        case 244:
        
        case 245:
        
        case 246:
        
        case 247:
        
        case 248:
        
        case 249:
        
        case 250:
        
        case 251:
        
        case 252:
        
        case 253:
        
        case 254:
        
        default:
          break;
      } 
      byte b1 = 13;
      int j = (paramInt2 & 0xFF) - b1;
      if (j < 0)
        j += 256; 
      int k = ((paramInt2 & 0xFFFF) >>> 8) - b1;
      if (k < 0)
        k += 256; 
      for (byte b2 = 0; b2 < arrayOfChar.length; b2++) {
        int m = b2 % 2;
        if (m == 0) {
          arrayOfChar[b2] = (char)(arrayOfChar[b2] ^ j);
          j = ((j >>> 3 | j << 5) ^ arrayOfChar[b2]) & 0xFF;
        } else {
          arrayOfChar[b2] = (char)(arrayOfChar[b2] ^ k);
          k = ((k >>> 3 | k << 5) ^ arrayOfChar[b2]) & 0xFF;
        } 
      } 
      b[i] = (new String(arrayOfChar)).intern();
    } 
    return b[i];
  }
}


/* Location:              C:\Program Files\BurpSuitePro\burpsuite_pro.jar!\burp\Zgtb.class
 * Java compiler version: 21 (65.0)
 * JD-Core Version:       1.1.3
 */