package burp;

import java.math.BigInteger;

class Zgva extends ClassLoader {
  static Object Zr;
  
  static String ZV;
  
  private static final String[] a;
  
  private static final String[] b;
  
  static void ZN(Object[] paramArrayOfObject, Object paramObject) throws Throwable {}
  
  static void ZH(Object paramObject) {
    Zgpp.Zm = a(-10061, 2072);
    Zgpp.Zt = new BigInteger(a(-10059, 2304));
    boolean bool = Zt2e.ZK();
    try {
      try {
        if (Zz0w.ZO.charAt(Math.abs(((BigInteger)Ztlz.ZW).intValue() % 32)) <= Zg4k.ZB.charAt(Math.abs(((BigInteger)Zzmw.ZS).intValue() % 32))) {
          try {
            Zxyu.Zh(Class.forName(a(-10058, -14867)));
            if (bool)
              Zkt7.Zq(Class.forName(a(-10060, 32703))); 
          } catch (Throwable throwable) {
            throw a(null);
          } 
          return;
        } 
      } catch (Throwable throwable) {
        throw a(null);
      } 
      Zkt7.Zq(Class.forName(a(-10060, 32703)));
    } catch (Throwable throwable) {}
  }
  
  static boolean ZE(Object[] paramArrayOfObject, Object paramObject) throws Throwable {
    // Byte code:
    //   0: invokestatic ZN : ()Z
    //   3: istore_2
    //   4: getstatic burp/Zeuc.Zd : Ljava/lang/Object;
    //   7: checkcast java/math/BigInteger
    //   10: invokevirtual toByteArray : ()[B
    //   13: astore_3
    //   14: aload_3
    //   15: arraylength
    //   16: iconst_2
    //   17: iadd
    //   18: newarray byte
    //   20: astore #5
    //   22: iconst_0
    //   23: istore #6
    //   25: iload #6
    //   27: aload_3
    //   28: arraylength
    //   29: if_icmpge -> 48
    //   32: aload #5
    //   34: iload #6
    //   36: aload_3
    //   37: iload #6
    //   39: baload
    //   40: bastore
    //   41: iinc #6, 1
    //   44: iload_2
    //   45: ifne -> 25
    //   48: aload #5
    //   50: arraylength
    //   51: iconst_3
    //   52: idiv
    //   53: iconst_4
    //   54: imul
    //   55: newarray byte
    //   57: astore #4
    //   59: iconst_0
    //   60: istore #6
    //   62: iconst_0
    //   63: istore #7
    //   65: iload #6
    //   67: aload_3
    //   68: arraylength
    //   69: if_icmpge -> 180
    //   72: aload #4
    //   74: iload #7
    //   76: aload #5
    //   78: iload #6
    //   80: baload
    //   81: iconst_2
    //   82: iushr
    //   83: bipush #63
    //   85: iand
    //   86: i2b
    //   87: bastore
    //   88: aload #4
    //   90: iload #7
    //   92: iconst_1
    //   93: iadd
    //   94: aload #5
    //   96: iload #6
    //   98: iconst_1
    //   99: iadd
    //   100: baload
    //   101: iconst_4
    //   102: iushr
    //   103: bipush #15
    //   105: iand
    //   106: aload #5
    //   108: iload #6
    //   110: baload
    //   111: iconst_4
    //   112: ishl
    //   113: bipush #63
    //   115: iand
    //   116: ior
    //   117: i2b
    //   118: bastore
    //   119: aload #4
    //   121: iload #7
    //   123: iconst_2
    //   124: iadd
    //   125: aload #5
    //   127: iload #6
    //   129: iconst_2
    //   130: iadd
    //   131: baload
    //   132: bipush #6
    //   134: iushr
    //   135: iconst_3
    //   136: iand
    //   137: aload #5
    //   139: iload #6
    //   141: iconst_1
    //   142: iadd
    //   143: baload
    //   144: iconst_2
    //   145: ishl
    //   146: bipush #63
    //   148: iand
    //   149: ior
    //   150: i2b
    //   151: bastore
    //   152: aload #4
    //   154: iload #7
    //   156: iconst_3
    //   157: iadd
    //   158: aload #5
    //   160: iload #6
    //   162: iconst_2
    //   163: iadd
    //   164: baload
    //   165: bipush #63
    //   167: iand
    //   168: i2b
    //   169: bastore
    //   170: iinc #6, 3
    //   173: iinc #7, 4
    //   176: iload_2
    //   177: ifne -> 65
    //   180: iconst_0
    //   181: istore #6
    //   183: iload #6
    //   185: aload #4
    //   187: arraylength
    //   188: if_icmpge -> 372
    //   191: aload #4
    //   193: iload #6
    //   195: baload
    //   196: bipush #26
    //   198: if_icmpge -> 226
    //   201: aload #4
    //   203: iload #6
    //   205: aload #4
    //   207: iload #6
    //   209: baload
    //   210: bipush #65
    //   212: iadd
    //   213: i2b
    //   214: bastore
    //   215: iload_2
    //   216: ifne -> 365
    //   219: goto -> 226
    //   222: invokestatic a : (Ljava/lang/Throwable;)Ljava/lang/Throwable;
    //   225: athrow
    //   226: aload #4
    //   228: iload #6
    //   230: baload
    //   231: bipush #52
    //   233: if_icmpge -> 271
    //   236: goto -> 243
    //   239: invokestatic a : (Ljava/lang/Throwable;)Ljava/lang/Throwable;
    //   242: athrow
    //   243: aload #4
    //   245: iload #6
    //   247: aload #4
    //   249: iload #6
    //   251: baload
    //   252: bipush #97
    //   254: iadd
    //   255: bipush #26
    //   257: isub
    //   258: i2b
    //   259: bastore
    //   260: iload_2
    //   261: ifne -> 365
    //   264: goto -> 271
    //   267: invokestatic a : (Ljava/lang/Throwable;)Ljava/lang/Throwable;
    //   270: athrow
    //   271: aload #4
    //   273: iload #6
    //   275: baload
    //   276: bipush #62
    //   278: if_icmpge -> 316
    //   281: goto -> 288
    //   284: invokestatic a : (Ljava/lang/Throwable;)Ljava/lang/Throwable;
    //   287: athrow
    //   288: aload #4
    //   290: iload #6
    //   292: aload #4
    //   294: iload #6
    //   296: baload
    //   297: bipush #48
    //   299: iadd
    //   300: bipush #52
    //   302: isub
    //   303: i2b
    //   304: bastore
    //   305: iload_2
    //   306: ifne -> 365
    //   309: goto -> 316
    //   312: invokestatic a : (Ljava/lang/Throwable;)Ljava/lang/Throwable;
    //   315: athrow
    //   316: aload #4
    //   318: iload #6
    //   320: baload
    //   321: bipush #63
    //   323: if_icmpge -> 351
    //   326: goto -> 333
    //   329: invokestatic a : (Ljava/lang/Throwable;)Ljava/lang/Throwable;
    //   332: athrow
    //   333: aload #4
    //   335: iload #6
    //   337: bipush #43
    //   339: bastore
    //   340: iload_2
    //   341: ifne -> 365
    //   344: goto -> 351
    //   347: invokestatic a : (Ljava/lang/Throwable;)Ljava/lang/Throwable;
    //   350: athrow
    //   351: aload #4
    //   353: iload #6
    //   355: bipush #47
    //   357: bastore
    //   358: goto -> 365
    //   361: invokestatic a : (Ljava/lang/Throwable;)Ljava/lang/Throwable;
    //   364: athrow
    //   365: iinc #6, 1
    //   368: iload_2
    //   369: ifne -> 183
    //   372: aload #4
    //   374: arraylength
    //   375: iconst_1
    //   376: isub
    //   377: istore #6
    //   379: iload #6
    //   381: aload_3
    //   382: arraylength
    //   383: iconst_4
    //   384: imul
    //   385: iconst_3
    //   386: idiv
    //   387: if_icmple -> 404
    //   390: aload #4
    //   392: iload #6
    //   394: bipush #61
    //   396: bastore
    //   397: iinc #6, -1
    //   400: iload_2
    //   401: ifne -> 379
    //   404: new java/math/BigInteger
    //   407: dup
    //   408: aload #4
    //   410: invokespecial <init> : ([B)V
    //   413: invokevirtual abs : ()Ljava/math/BigInteger;
    //   416: putstatic burp/Zg6f.Zl : Ljava/lang/Object;
    //   419: new java/lang/StringBuilder
    //   422: dup
    //   423: invokespecial <init> : ()V
    //   426: astore_3
    //   427: iconst_0
    //   428: istore #4
    //   430: iload #4
    //   432: bipush #32
    //   434: if_icmpge -> 1767
    //   437: iload #4
    //   439: tableswitch default -> 1760, 0 -> 580, 1 -> 617, 2 -> 654, 3 -> 691, 4 -> 728, 5 -> 765, 6 -> 802, 7 -> 839, 8 -> 876, 9 -> 913, 10 -> 950, 11 -> 987, 12 -> 1024, 13 -> 1061, 14 -> 1098, 15 -> 1135, 16 -> 1172, 17 -> 1209, 18 -> 1246, 19 -> 1283, 20 -> 1320, 21 -> 1357, 22 -> 1394, 23 -> 1431, 24 -> 1468, 25 -> 1505, 26 -> 1542, 27 -> 1579, 28 -> 1616, 29 -> 1653, 30 -> 1690, 31 -> 1727
    //   580: aload_3
    //   581: getstatic burp/Zzr5.Zg : Ljava/lang/String;
    //   584: getstatic burp/Zlvb.ZN : Ljava/lang/Object;
    //   587: checkcast java/math/BigInteger
    //   590: invokevirtual intValue : ()I
    //   593: bipush #32
    //   595: irem
    //   596: invokestatic abs : (I)I
    //   599: invokevirtual charAt : (I)C
    //   602: invokevirtual append : (C)Ljava/lang/StringBuilder;
    //   605: pop
    //   606: iload_2
    //   607: ifne -> 1760
    //   610: goto -> 617
    //   613: invokestatic a : (Ljava/lang/Throwable;)Ljava/lang/Throwable;
    //   616: athrow
    //   617: aload_3
    //   618: getstatic burp/Zlx5.ZP : Ljava/lang/String;
    //   621: getstatic burp/Zeoy.Zt : Ljava/lang/Object;
    //   624: checkcast java/math/BigInteger
    //   627: invokevirtual intValue : ()I
    //   630: bipush #32
    //   632: irem
    //   633: invokestatic abs : (I)I
    //   636: invokevirtual charAt : (I)C
    //   639: invokevirtual append : (C)Ljava/lang/StringBuilder;
    //   642: pop
    //   643: iload_2
    //   644: ifne -> 1760
    //   647: goto -> 654
    //   650: invokestatic a : (Ljava/lang/Throwable;)Ljava/lang/Throwable;
    //   653: athrow
    //   654: aload_3
    //   655: getstatic burp/Zeuc.Zp : Ljava/lang/String;
    //   658: getstatic burp/Zzoi.ZI : Ljava/lang/Object;
    //   661: checkcast java/math/BigInteger
    //   664: invokevirtual intValue : ()I
    //   667: bipush #32
    //   669: irem
    //   670: invokestatic abs : (I)I
    //   673: invokevirtual charAt : (I)C
    //   676: invokevirtual append : (C)Ljava/lang/StringBuilder;
    //   679: pop
    //   680: iload_2
    //   681: ifne -> 1760
    //   684: goto -> 691
    //   687: invokestatic a : (Ljava/lang/Throwable;)Ljava/lang/Throwable;
    //   690: athrow
    //   691: aload_3
    //   692: getstatic burp/Zmj8.ZL : Ljava/lang/String;
    //   695: getstatic burp/Ztdd.ZD : Ljava/lang/Object;
    //   698: checkcast java/math/BigInteger
    //   701: invokevirtual intValue : ()I
    //   704: bipush #32
    //   706: irem
    //   707: invokestatic abs : (I)I
    //   710: invokevirtual charAt : (I)C
    //   713: invokevirtual append : (C)Ljava/lang/StringBuilder;
    //   716: pop
    //   717: iload_2
    //   718: ifne -> 1760
    //   721: goto -> 728
    //   724: invokestatic a : (Ljava/lang/Throwable;)Ljava/lang/Throwable;
    //   727: athrow
    //   728: aload_3
    //   729: getstatic burp/Zlo5.ZJ : Ljava/lang/String;
    //   732: getstatic burp/Zex.ZO : Ljava/lang/Object;
    //   735: checkcast java/math/BigInteger
    //   738: invokevirtual intValue : ()I
    //   741: bipush #32
    //   743: irem
    //   744: invokestatic abs : (I)I
    //   747: invokevirtual charAt : (I)C
    //   750: invokevirtual append : (C)Ljava/lang/StringBuilder;
    //   753: pop
    //   754: iload_2
    //   755: ifne -> 1760
    //   758: goto -> 765
    //   761: invokestatic a : (Ljava/lang/Throwable;)Ljava/lang/Throwable;
    //   764: athrow
    //   765: aload_3
    //   766: getstatic burp/Zlh8.ZY : Ljava/lang/String;
    //   769: getstatic burp/Zlr.ZK : Ljava/lang/Object;
    //   772: checkcast java/math/BigInteger
    //   775: invokevirtual intValue : ()I
    //   778: bipush #32
    //   780: irem
    //   781: invokestatic abs : (I)I
    //   784: invokevirtual charAt : (I)C
    //   787: invokevirtual append : (C)Ljava/lang/StringBuilder;
    //   790: pop
    //   791: iload_2
    //   792: ifne -> 1760
    //   795: goto -> 802
    //   798: invokestatic a : (Ljava/lang/Throwable;)Ljava/lang/Throwable;
    //   801: athrow
    //   802: aload_3
    //   803: getstatic burp/Zxg7.Zi : Ljava/lang/String;
    //   806: getstatic burp/Zlnm.Zn : Ljava/lang/Object;
    //   809: checkcast java/math/BigInteger
    //   812: invokevirtual intValue : ()I
    //   815: bipush #32
    //   817: irem
    //   818: invokestatic abs : (I)I
    //   821: invokevirtual charAt : (I)C
    //   824: invokevirtual append : (C)Ljava/lang/StringBuilder;
    //   827: pop
    //   828: iload_2
    //   829: ifne -> 1760
    //   832: goto -> 839
    //   835: invokestatic a : (Ljava/lang/Throwable;)Ljava/lang/Throwable;
    //   838: athrow
    //   839: aload_3
    //   840: getstatic burp/Zess.Zc : Ljava/lang/String;
    //   843: getstatic burp/Zt5j.Zn : Ljava/lang/Object;
    //   846: checkcast java/math/BigInteger
    //   849: invokevirtual intValue : ()I
    //   852: bipush #32
    //   854: irem
    //   855: invokestatic abs : (I)I
    //   858: invokevirtual charAt : (I)C
    //   861: invokevirtual append : (C)Ljava/lang/StringBuilder;
    //   864: pop
    //   865: iload_2
    //   866: ifne -> 1760
    //   869: goto -> 876
    //   872: invokestatic a : (Ljava/lang/Throwable;)Ljava/lang/Throwable;
    //   875: athrow
    //   876: aload_3
    //   877: getstatic burp/Zs00.Zv : Ljava/lang/String;
    //   880: getstatic burp/Zxe.Zg : Ljava/lang/Object;
    //   883: checkcast java/math/BigInteger
    //   886: invokevirtual intValue : ()I
    //   889: bipush #32
    //   891: irem
    //   892: invokestatic abs : (I)I
    //   895: invokevirtual charAt : (I)C
    //   898: invokevirtual append : (C)Ljava/lang/StringBuilder;
    //   901: pop
    //   902: iload_2
    //   903: ifne -> 1760
    //   906: goto -> 913
    //   909: invokestatic a : (Ljava/lang/Throwable;)Ljava/lang/Throwable;
    //   912: athrow
    //   913: aload_3
    //   914: getstatic burp/Zz6t.Zx : Ljava/lang/String;
    //   917: getstatic burp/Ze6d.Zw : Ljava/lang/Object;
    //   920: checkcast java/math/BigInteger
    //   923: invokevirtual intValue : ()I
    //   926: bipush #32
    //   928: irem
    //   929: invokestatic abs : (I)I
    //   932: invokevirtual charAt : (I)C
    //   935: invokevirtual append : (C)Ljava/lang/StringBuilder;
    //   938: pop
    //   939: iload_2
    //   940: ifne -> 1760
    //   943: goto -> 950
    //   946: invokestatic a : (Ljava/lang/Throwable;)Ljava/lang/Throwable;
    //   949: athrow
    //   950: aload_3
    //   951: getstatic burp/Zke7.Zl : Ljava/lang/String;
    //   954: getstatic burp/Zmx6.ZJ : Ljava/lang/Object;
    //   957: checkcast java/math/BigInteger
    //   960: invokevirtual intValue : ()I
    //   963: bipush #32
    //   965: irem
    //   966: invokestatic abs : (I)I
    //   969: invokevirtual charAt : (I)C
    //   972: invokevirtual append : (C)Ljava/lang/StringBuilder;
    //   975: pop
    //   976: iload_2
    //   977: ifne -> 1760
    //   980: goto -> 987
    //   983: invokestatic a : (Ljava/lang/Throwable;)Ljava/lang/Throwable;
    //   986: athrow
    //   987: aload_3
    //   988: getstatic burp/Zsqy.Zo : Ljava/lang/String;
    //   991: getstatic burp/Zrtv.Zg : Ljava/lang/Object;
    //   994: checkcast java/math/BigInteger
    //   997: invokevirtual intValue : ()I
    //   1000: bipush #32
    //   1002: irem
    //   1003: invokestatic abs : (I)I
    //   1006: invokevirtual charAt : (I)C
    //   1009: invokevirtual append : (C)Ljava/lang/StringBuilder;
    //   1012: pop
    //   1013: iload_2
    //   1014: ifne -> 1760
    //   1017: goto -> 1024
    //   1020: invokestatic a : (Ljava/lang/Throwable;)Ljava/lang/Throwable;
    //   1023: athrow
    //   1024: aload_3
    //   1025: getstatic burp/Zt98.Zh : Ljava/lang/String;
    //   1028: getstatic burp/Zrof.ZB : Ljava/lang/Object;
    //   1031: checkcast java/math/BigInteger
    //   1034: invokevirtual intValue : ()I
    //   1037: bipush #32
    //   1039: irem
    //   1040: invokestatic abs : (I)I
    //   1043: invokevirtual charAt : (I)C
    //   1046: invokevirtual append : (C)Ljava/lang/StringBuilder;
    //   1049: pop
    //   1050: iload_2
    //   1051: ifne -> 1760
    //   1054: goto -> 1061
    //   1057: invokestatic a : (Ljava/lang/Throwable;)Ljava/lang/Throwable;
    //   1060: athrow
    //   1061: aload_3
    //   1062: getstatic burp/Zest.Zd : Ljava/lang/String;
    //   1065: getstatic burp/Zzyr.Za : Ljava/lang/Object;
    //   1068: checkcast java/math/BigInteger
    //   1071: invokevirtual intValue : ()I
    //   1074: bipush #32
    //   1076: irem
    //   1077: invokestatic abs : (I)I
    //   1080: invokevirtual charAt : (I)C
    //   1083: invokevirtual append : (C)Ljava/lang/StringBuilder;
    //   1086: pop
    //   1087: iload_2
    //   1088: ifne -> 1760
    //   1091: goto -> 1098
    //   1094: invokestatic a : (Ljava/lang/Throwable;)Ljava/lang/Throwable;
    //   1097: athrow
    //   1098: aload_3
    //   1099: getstatic burp/Zkjr.Zg : Ljava/lang/String;
    //   1102: getstatic burp/Zzmw.ZS : Ljava/lang/Object;
    //   1105: checkcast java/math/BigInteger
    //   1108: invokevirtual intValue : ()I
    //   1111: bipush #32
    //   1113: irem
    //   1114: invokestatic abs : (I)I
    //   1117: invokevirtual charAt : (I)C
    //   1120: invokevirtual append : (C)Ljava/lang/StringBuilder;
    //   1123: pop
    //   1124: iload_2
    //   1125: ifne -> 1760
    //   1128: goto -> 1135
    //   1131: invokestatic a : (Ljava/lang/Throwable;)Ljava/lang/Throwable;
    //   1134: athrow
    //   1135: aload_3
    //   1136: getstatic burp/Zmsn.ZD : Ljava/lang/String;
    //   1139: getstatic burp/Ze64.ZW : Ljava/lang/Object;
    //   1142: checkcast java/math/BigInteger
    //   1145: invokevirtual intValue : ()I
    //   1148: bipush #32
    //   1150: irem
    //   1151: invokestatic abs : (I)I
    //   1154: invokevirtual charAt : (I)C
    //   1157: invokevirtual append : (C)Ljava/lang/StringBuilder;
    //   1160: pop
    //   1161: iload_2
    //   1162: ifne -> 1760
    //   1165: goto -> 1172
    //   1168: invokestatic a : (Ljava/lang/Throwable;)Ljava/lang/Throwable;
    //   1171: athrow
    //   1172: aload_3
    //   1173: getstatic burp/Zt9_.Zf : Ljava/lang/String;
    //   1176: getstatic burp/Ztex.Z_ : Ljava/lang/Object;
    //   1179: checkcast java/math/BigInteger
    //   1182: invokevirtual intValue : ()I
    //   1185: bipush #32
    //   1187: irem
    //   1188: invokestatic abs : (I)I
    //   1191: invokevirtual charAt : (I)C
    //   1194: invokevirtual append : (C)Ljava/lang/StringBuilder;
    //   1197: pop
    //   1198: iload_2
    //   1199: ifne -> 1760
    //   1202: goto -> 1209
    //   1205: invokestatic a : (Ljava/lang/Throwable;)Ljava/lang/Throwable;
    //   1208: athrow
    //   1209: aload_3
    //   1210: getstatic burp/Zlh8.ZY : Ljava/lang/String;
    //   1213: getstatic burp/Zix.ZO : Ljava/lang/Object;
    //   1216: checkcast java/math/BigInteger
    //   1219: invokevirtual intValue : ()I
    //   1222: bipush #32
    //   1224: irem
    //   1225: invokestatic abs : (I)I
    //   1228: invokevirtual charAt : (I)C
    //   1231: invokevirtual append : (C)Ljava/lang/StringBuilder;
    //   1234: pop
    //   1235: iload_2
    //   1236: ifne -> 1760
    //   1239: goto -> 1246
    //   1242: invokestatic a : (Ljava/lang/Throwable;)Ljava/lang/Throwable;
    //   1245: athrow
    //   1246: aload_3
    //   1247: getstatic burp/Zefo.Zb : Ljava/lang/String;
    //   1250: getstatic burp/Ztdd.ZD : Ljava/lang/Object;
    //   1253: checkcast java/math/BigInteger
    //   1256: invokevirtual intValue : ()I
    //   1259: bipush #32
    //   1261: irem
    //   1262: invokestatic abs : (I)I
    //   1265: invokevirtual charAt : (I)C
    //   1268: invokevirtual append : (C)Ljava/lang/StringBuilder;
    //   1271: pop
    //   1272: iload_2
    //   1273: ifne -> 1760
    //   1276: goto -> 1283
    //   1279: invokestatic a : (Ljava/lang/Throwable;)Ljava/lang/Throwable;
    //   1282: athrow
    //   1283: aload_3
    //   1284: getstatic burp/Zrhp.ZQ : Ljava/lang/String;
    //   1287: getstatic burp/Zl39.ZA : Ljava/lang/Object;
    //   1290: checkcast java/math/BigInteger
    //   1293: invokevirtual intValue : ()I
    //   1296: bipush #32
    //   1298: irem
    //   1299: invokestatic abs : (I)I
    //   1302: invokevirtual charAt : (I)C
    //   1305: invokevirtual append : (C)Ljava/lang/StringBuilder;
    //   1308: pop
    //   1309: iload_2
    //   1310: ifne -> 1760
    //   1313: goto -> 1320
    //   1316: invokestatic a : (Ljava/lang/Throwable;)Ljava/lang/Throwable;
    //   1319: athrow
    //   1320: aload_3
    //   1321: getstatic burp/Zgva.ZV : Ljava/lang/String;
    //   1324: getstatic burp/Zzox.Zq : Ljava/lang/Object;
    //   1327: checkcast java/math/BigInteger
    //   1330: invokevirtual intValue : ()I
    //   1333: bipush #32
    //   1335: irem
    //   1336: invokestatic abs : (I)I
    //   1339: invokevirtual charAt : (I)C
    //   1342: invokevirtual append : (C)Ljava/lang/StringBuilder;
    //   1345: pop
    //   1346: iload_2
    //   1347: ifne -> 1760
    //   1350: goto -> 1357
    //   1353: invokestatic a : (Ljava/lang/Throwable;)Ljava/lang/Throwable;
    //   1356: athrow
    //   1357: aload_3
    //   1358: getstatic burp/Zmx6.ZG : Ljava/lang/String;
    //   1361: getstatic burp/Zkc8.ZW : Ljava/lang/Object;
    //   1364: checkcast java/math/BigInteger
    //   1367: invokevirtual intValue : ()I
    //   1370: bipush #32
    //   1372: irem
    //   1373: invokestatic abs : (I)I
    //   1376: invokevirtual charAt : (I)C
    //   1379: invokevirtual append : (C)Ljava/lang/StringBuilder;
    //   1382: pop
    //   1383: iload_2
    //   1384: ifne -> 1760
    //   1387: goto -> 1394
    //   1390: invokestatic a : (Ljava/lang/Throwable;)Ljava/lang/Throwable;
    //   1393: athrow
    //   1394: aload_3
    //   1395: getstatic burp/Zqp.ZX : Ljava/lang/String;
    //   1398: getstatic burp/Zz75.ZX : Ljava/lang/Object;
    //   1401: checkcast java/math/BigInteger
    //   1404: invokevirtual intValue : ()I
    //   1407: bipush #32
    //   1409: irem
    //   1410: invokestatic abs : (I)I
    //   1413: invokevirtual charAt : (I)C
    //   1416: invokevirtual append : (C)Ljava/lang/StringBuilder;
    //   1419: pop
    //   1420: iload_2
    //   1421: ifne -> 1760
    //   1424: goto -> 1431
    //   1427: invokestatic a : (Ljava/lang/Throwable;)Ljava/lang/Throwable;
    //   1430: athrow
    //   1431: aload_3
    //   1432: getstatic burp/Zs2n.ZI : Ljava/lang/String;
    //   1435: getstatic burp/Zera.Zy : Ljava/lang/Object;
    //   1438: checkcast java/math/BigInteger
    //   1441: invokevirtual intValue : ()I
    //   1444: bipush #32
    //   1446: irem
    //   1447: invokestatic abs : (I)I
    //   1450: invokevirtual charAt : (I)C
    //   1453: invokevirtual append : (C)Ljava/lang/StringBuilder;
    //   1456: pop
    //   1457: iload_2
    //   1458: ifne -> 1760
    //   1461: goto -> 1468
    //   1464: invokestatic a : (Ljava/lang/Throwable;)Ljava/lang/Throwable;
    //   1467: athrow
    //   1468: aload_3
    //   1469: getstatic burp/Zb8y.Zn : Ljava/lang/String;
    //   1472: getstatic burp/Zmj8.Zz : Ljava/lang/Object;
    //   1475: checkcast java/math/BigInteger
    //   1478: invokevirtual intValue : ()I
    //   1481: bipush #32
    //   1483: irem
    //   1484: invokestatic abs : (I)I
    //   1487: invokevirtual charAt : (I)C
    //   1490: invokevirtual append : (C)Ljava/lang/StringBuilder;
    //   1493: pop
    //   1494: iload_2
    //   1495: ifne -> 1760
    //   1498: goto -> 1505
    //   1501: invokestatic a : (Ljava/lang/Throwable;)Ljava/lang/Throwable;
    //   1504: athrow
    //   1505: aload_3
    //   1506: getstatic burp/Zsj5.Zn : Ljava/lang/String;
    //   1509: getstatic burp/Zzym.ZK : Ljava/lang/Object;
    //   1512: checkcast java/math/BigInteger
    //   1515: invokevirtual intValue : ()I
    //   1518: bipush #32
    //   1520: irem
    //   1521: invokestatic abs : (I)I
    //   1524: invokevirtual charAt : (I)C
    //   1527: invokevirtual append : (C)Ljava/lang/StringBuilder;
    //   1530: pop
    //   1531: iload_2
    //   1532: ifne -> 1760
    //   1535: goto -> 1542
    //   1538: invokestatic a : (Ljava/lang/Throwable;)Ljava/lang/Throwable;
    //   1541: athrow
    //   1542: aload_3
    //   1543: getstatic burp/Zltz.Za : Ljava/lang/String;
    //   1546: getstatic burp/Zmj8.Zz : Ljava/lang/Object;
    //   1549: checkcast java/math/BigInteger
    //   1552: invokevirtual intValue : ()I
    //   1555: bipush #32
    //   1557: irem
    //   1558: invokestatic abs : (I)I
    //   1561: invokevirtual charAt : (I)C
    //   1564: invokevirtual append : (C)Ljava/lang/StringBuilder;
    //   1567: pop
    //   1568: iload_2
    //   1569: ifne -> 1760
    //   1572: goto -> 1579
    //   1575: invokestatic a : (Ljava/lang/Throwable;)Ljava/lang/Throwable;
    //   1578: athrow
    //   1579: aload_3
    //   1580: getstatic burp/Ztsu.ZE : Ljava/lang/String;
    //   1583: getstatic burp/Zm3p.Zz : Ljava/lang/Object;
    //   1586: checkcast java/math/BigInteger
    //   1589: invokevirtual intValue : ()I
    //   1592: bipush #32
    //   1594: irem
    //   1595: invokestatic abs : (I)I
    //   1598: invokevirtual charAt : (I)C
    //   1601: invokevirtual append : (C)Ljava/lang/StringBuilder;
    //   1604: pop
    //   1605: iload_2
    //   1606: ifne -> 1760
    //   1609: goto -> 1616
    //   1612: invokestatic a : (Ljava/lang/Throwable;)Ljava/lang/Throwable;
    //   1615: athrow
    //   1616: aload_3
    //   1617: getstatic burp/Zl39.ZI : Ljava/lang/String;
    //   1620: getstatic burp/Zxo7.Zi : Ljava/lang/Object;
    //   1623: checkcast java/math/BigInteger
    //   1626: invokevirtual intValue : ()I
    //   1629: bipush #32
    //   1631: irem
    //   1632: invokestatic abs : (I)I
    //   1635: invokevirtual charAt : (I)C
    //   1638: invokevirtual append : (C)Ljava/lang/StringBuilder;
    //   1641: pop
    //   1642: iload_2
    //   1643: ifne -> 1760
    //   1646: goto -> 1653
    //   1649: invokestatic a : (Ljava/lang/Throwable;)Ljava/lang/Throwable;
    //   1652: athrow
    //   1653: aload_3
    //   1654: getstatic burp/Zlpj.Zj : Ljava/lang/String;
    //   1657: getstatic burp/Zgnp.Zm : Ljava/lang/Object;
    //   1660: checkcast java/math/BigInteger
    //   1663: invokevirtual intValue : ()I
    //   1666: bipush #32
    //   1668: irem
    //   1669: invokestatic abs : (I)I
    //   1672: invokevirtual charAt : (I)C
    //   1675: invokevirtual append : (C)Ljava/lang/StringBuilder;
    //   1678: pop
    //   1679: iload_2
    //   1680: ifne -> 1760
    //   1683: goto -> 1690
    //   1686: invokestatic a : (Ljava/lang/Throwable;)Ljava/lang/Throwable;
    //   1689: athrow
    //   1690: aload_3
    //   1691: getstatic burp/Zeoy.ZS : Ljava/lang/String;
    //   1694: getstatic burp/Zz2e.Zm : Ljava/lang/Object;
    //   1697: checkcast java/math/BigInteger
    //   1700: invokevirtual intValue : ()I
    //   1703: bipush #32
    //   1705: irem
    //   1706: invokestatic abs : (I)I
    //   1709: invokevirtual charAt : (I)C
    //   1712: invokevirtual append : (C)Ljava/lang/StringBuilder;
    //   1715: pop
    //   1716: iload_2
    //   1717: ifne -> 1760
    //   1720: goto -> 1727
    //   1723: invokestatic a : (Ljava/lang/Throwable;)Ljava/lang/Throwable;
    //   1726: athrow
    //   1727: aload_3
    //   1728: getstatic burp/Zztk.Zf : Ljava/lang/String;
    //   1731: getstatic burp/Zlvb.ZN : Ljava/lang/Object;
    //   1734: checkcast java/math/BigInteger
    //   1737: invokevirtual intValue : ()I
    //   1740: bipush #32
    //   1742: irem
    //   1743: invokestatic abs : (I)I
    //   1746: invokevirtual charAt : (I)C
    //   1749: invokevirtual append : (C)Ljava/lang/StringBuilder;
    //   1752: pop
    //   1753: goto -> 1760
    //   1756: invokestatic a : (Ljava/lang/Throwable;)Ljava/lang/Throwable;
    //   1759: athrow
    //   1760: iinc #4, 1
    //   1763: iload_2
    //   1764: ifne -> 430
    //   1767: aload_3
    //   1768: invokevirtual toString : ()Ljava/lang/String;
    //   1771: putstatic burp/Ze6d.Zx : Ljava/lang/String;
    //   1774: new java/lang/StringBuilder
    //   1777: dup
    //   1778: invokespecial <init> : ()V
    //   1781: astore #4
    //   1783: iconst_0
    //   1784: istore #5
    //   1786: iload #5
    //   1788: bipush #32
    //   1790: if_icmpge -> 3155
    //   1793: iload #5
    //   1795: tableswitch default -> 3148, 0 -> 1936, 1 -> 1974, 2 -> 2012, 3 -> 2050, 4 -> 2088, 5 -> 2126, 6 -> 2164, 7 -> 2202, 8 -> 2240, 9 -> 2278, 10 -> 2316, 11 -> 2354, 12 -> 2392, 13 -> 2430, 14 -> 2468, 15 -> 2506, 16 -> 2544, 17 -> 2582, 18 -> 2620, 19 -> 2658, 20 -> 2696, 21 -> 2734, 22 -> 2772, 23 -> 2810, 24 -> 2848, 25 -> 2886, 26 -> 2924, 27 -> 2962, 28 -> 3000, 29 -> 3038, 30 -> 3076, 31 -> 3114
    //   1936: aload #4
    //   1938: getstatic burp/Ze6d.Zx : Ljava/lang/String;
    //   1941: getstatic burp/Zke7.Zj : Ljava/lang/Object;
    //   1944: checkcast java/math/BigInteger
    //   1947: invokevirtual intValue : ()I
    //   1950: bipush #32
    //   1952: irem
    //   1953: invokestatic abs : (I)I
    //   1956: invokevirtual charAt : (I)C
    //   1959: invokevirtual append : (C)Ljava/lang/StringBuilder;
    //   1962: pop
    //   1963: iload_2
    //   1964: ifne -> 3148
    //   1967: goto -> 1974
    //   1970: invokestatic a : (Ljava/lang/Throwable;)Ljava/lang/Throwable;
    //   1973: athrow
    //   1974: aload #4
    //   1976: getstatic burp/Ze5t.ZX : Ljava/lang/String;
    //   1979: getstatic burp/Ze_t.Za : Ljava/lang/Object;
    //   1982: checkcast java/math/BigInteger
    //   1985: invokevirtual intValue : ()I
    //   1988: bipush #32
    //   1990: irem
    //   1991: invokestatic abs : (I)I
    //   1994: invokevirtual charAt : (I)C
    //   1997: invokevirtual append : (C)Ljava/lang/StringBuilder;
    //   2000: pop
    //   2001: iload_2
    //   2002: ifne -> 3148
    //   2005: goto -> 2012
    //   2008: invokestatic a : (Ljava/lang/Throwable;)Ljava/lang/Throwable;
    //   2011: athrow
    //   2012: aload #4
    //   2014: getstatic burp/Zlrm.Zt : Ljava/lang/String;
    //   2017: getstatic burp/Zram.ZF : Ljava/lang/Object;
    //   2020: checkcast java/math/BigInteger
    //   2023: invokevirtual intValue : ()I
    //   2026: bipush #32
    //   2028: irem
    //   2029: invokestatic abs : (I)I
    //   2032: invokevirtual charAt : (I)C
    //   2035: invokevirtual append : (C)Ljava/lang/StringBuilder;
    //   2038: pop
    //   2039: iload_2
    //   2040: ifne -> 3148
    //   2043: goto -> 2050
    //   2046: invokestatic a : (Ljava/lang/Throwable;)Ljava/lang/Throwable;
    //   2049: athrow
    //   2050: aload #4
    //   2052: getstatic burp/Zztk.Zf : Ljava/lang/String;
    //   2055: getstatic burp/Zefo.ZW : Ljava/lang/Object;
    //   2058: checkcast java/math/BigInteger
    //   2061: invokevirtual intValue : ()I
    //   2064: bipush #32
    //   2066: irem
    //   2067: invokestatic abs : (I)I
    //   2070: invokevirtual charAt : (I)C
    //   2073: invokevirtual append : (C)Ljava/lang/StringBuilder;
    //   2076: pop
    //   2077: iload_2
    //   2078: ifne -> 3148
    //   2081: goto -> 2088
    //   2084: invokestatic a : (Ljava/lang/Throwable;)Ljava/lang/Throwable;
    //   2087: athrow
    //   2088: aload #4
    //   2090: getstatic burp/Zkb_.ZR : Ljava/lang/String;
    //   2093: getstatic burp/Zs34.ZE : Ljava/lang/Object;
    //   2096: checkcast java/math/BigInteger
    //   2099: invokevirtual intValue : ()I
    //   2102: bipush #32
    //   2104: irem
    //   2105: invokestatic abs : (I)I
    //   2108: invokevirtual charAt : (I)C
    //   2111: invokevirtual append : (C)Ljava/lang/StringBuilder;
    //   2114: pop
    //   2115: iload_2
    //   2116: ifne -> 3148
    //   2119: goto -> 2126
    //   2122: invokestatic a : (Ljava/lang/Throwable;)Ljava/lang/Throwable;
    //   2125: athrow
    //   2126: aload #4
    //   2128: getstatic burp/Zm6h.Za : Ljava/lang/String;
    //   2131: getstatic burp/Zmsn.Zk : Ljava/lang/Object;
    //   2134: checkcast java/math/BigInteger
    //   2137: invokevirtual intValue : ()I
    //   2140: bipush #32
    //   2142: irem
    //   2143: invokestatic abs : (I)I
    //   2146: invokevirtual charAt : (I)C
    //   2149: invokevirtual append : (C)Ljava/lang/StringBuilder;
    //   2152: pop
    //   2153: iload_2
    //   2154: ifne -> 3148
    //   2157: goto -> 2164
    //   2160: invokestatic a : (Ljava/lang/Throwable;)Ljava/lang/Throwable;
    //   2163: athrow
    //   2164: aload #4
    //   2166: getstatic burp/Zzox.ZB : Ljava/lang/String;
    //   2169: getstatic burp/Ztcv.ZY : Ljava/lang/Object;
    //   2172: checkcast java/math/BigInteger
    //   2175: invokevirtual intValue : ()I
    //   2178: bipush #32
    //   2180: irem
    //   2181: invokestatic abs : (I)I
    //   2184: invokevirtual charAt : (I)C
    //   2187: invokevirtual append : (C)Ljava/lang/StringBuilder;
    //   2190: pop
    //   2191: iload_2
    //   2192: ifne -> 3148
    //   2195: goto -> 2202
    //   2198: invokestatic a : (Ljava/lang/Throwable;)Ljava/lang/Throwable;
    //   2201: athrow
    //   2202: aload #4
    //   2204: getstatic burp/Ztye.ZR : Ljava/lang/String;
    //   2207: getstatic burp/Zlnm.Zn : Ljava/lang/Object;
    //   2210: checkcast java/math/BigInteger
    //   2213: invokevirtual intValue : ()I
    //   2216: bipush #32
    //   2218: irem
    //   2219: invokestatic abs : (I)I
    //   2222: invokevirtual charAt : (I)C
    //   2225: invokevirtual append : (C)Ljava/lang/StringBuilder;
    //   2228: pop
    //   2229: iload_2
    //   2230: ifne -> 3148
    //   2233: goto -> 2240
    //   2236: invokestatic a : (Ljava/lang/Throwable;)Ljava/lang/Throwable;
    //   2239: athrow
    //   2240: aload #4
    //   2242: getstatic burp/Zm8w.ZL : Ljava/lang/String;
    //   2245: getstatic burp/Zzmw.ZS : Ljava/lang/Object;
    //   2248: checkcast java/math/BigInteger
    //   2251: invokevirtual intValue : ()I
    //   2254: bipush #32
    //   2256: irem
    //   2257: invokestatic abs : (I)I
    //   2260: invokevirtual charAt : (I)C
    //   2263: invokevirtual append : (C)Ljava/lang/StringBuilder;
    //   2266: pop
    //   2267: iload_2
    //   2268: ifne -> 3148
    //   2271: goto -> 2278
    //   2274: invokestatic a : (Ljava/lang/Throwable;)Ljava/lang/Throwable;
    //   2277: athrow
    //   2278: aload #4
    //   2280: getstatic burp/Ztsu.ZE : Ljava/lang/String;
    //   2283: getstatic burp/Zr48.ZZ : Ljava/lang/Object;
    //   2286: checkcast java/math/BigInteger
    //   2289: invokevirtual intValue : ()I
    //   2292: bipush #32
    //   2294: irem
    //   2295: invokestatic abs : (I)I
    //   2298: invokevirtual charAt : (I)C
    //   2301: invokevirtual append : (C)Ljava/lang/StringBuilder;
    //   2304: pop
    //   2305: iload_2
    //   2306: ifne -> 3148
    //   2309: goto -> 2316
    //   2312: invokestatic a : (Ljava/lang/Throwable;)Ljava/lang/Throwable;
    //   2315: athrow
    //   2316: aload #4
    //   2318: getstatic burp/Zxzz.ZT : Ljava/lang/String;
    //   2321: getstatic burp/Ze69.ZH : Ljava/lang/Object;
    //   2324: checkcast java/math/BigInteger
    //   2327: invokevirtual intValue : ()I
    //   2330: bipush #32
    //   2332: irem
    //   2333: invokestatic abs : (I)I
    //   2336: invokevirtual charAt : (I)C
    //   2339: invokevirtual append : (C)Ljava/lang/StringBuilder;
    //   2342: pop
    //   2343: iload_2
    //   2344: ifne -> 3148
    //   2347: goto -> 2354
    //   2350: invokestatic a : (Ljava/lang/Throwable;)Ljava/lang/Throwable;
    //   2353: athrow
    //   2354: aload #4
    //   2356: getstatic burp/Zef0.ZR : Ljava/lang/String;
    //   2359: getstatic burp/Zl50.ZV : Ljava/lang/Object;
    //   2362: checkcast java/math/BigInteger
    //   2365: invokevirtual intValue : ()I
    //   2368: bipush #32
    //   2370: irem
    //   2371: invokestatic abs : (I)I
    //   2374: invokevirtual charAt : (I)C
    //   2377: invokevirtual append : (C)Ljava/lang/StringBuilder;
    //   2380: pop
    //   2381: iload_2
    //   2382: ifne -> 3148
    //   2385: goto -> 2392
    //   2388: invokestatic a : (Ljava/lang/Throwable;)Ljava/lang/Throwable;
    //   2391: athrow
    //   2392: aload #4
    //   2394: getstatic burp/Zbzk.ZS : Ljava/lang/String;
    //   2397: getstatic burp/Zt3f.Zp : Ljava/lang/Object;
    //   2400: checkcast java/math/BigInteger
    //   2403: invokevirtual intValue : ()I
    //   2406: bipush #32
    //   2408: irem
    //   2409: invokestatic abs : (I)I
    //   2412: invokevirtual charAt : (I)C
    //   2415: invokevirtual append : (C)Ljava/lang/StringBuilder;
    //   2418: pop
    //   2419: iload_2
    //   2420: ifne -> 3148
    //   2423: goto -> 2430
    //   2426: invokestatic a : (Ljava/lang/Throwable;)Ljava/lang/Throwable;
    //   2429: athrow
    //   2430: aload #4
    //   2432: getstatic burp/Zb.Zt : Ljava/lang/String;
    //   2435: getstatic burp/Zkb_.ZG : Ljava/lang/Object;
    //   2438: checkcast java/math/BigInteger
    //   2441: invokevirtual intValue : ()I
    //   2444: bipush #32
    //   2446: irem
    //   2447: invokestatic abs : (I)I
    //   2450: invokevirtual charAt : (I)C
    //   2453: invokevirtual append : (C)Ljava/lang/StringBuilder;
    //   2456: pop
    //   2457: iload_2
    //   2458: ifne -> 3148
    //   2461: goto -> 2468
    //   2464: invokestatic a : (Ljava/lang/Throwable;)Ljava/lang/Throwable;
    //   2467: athrow
    //   2468: aload #4
    //   2470: getstatic burp/Zlo5.ZJ : Ljava/lang/String;
    //   2473: getstatic burp/Zlh8.Zm : Ljava/lang/Object;
    //   2476: checkcast java/math/BigInteger
    //   2479: invokevirtual intValue : ()I
    //   2482: bipush #32
    //   2484: irem
    //   2485: invokestatic abs : (I)I
    //   2488: invokevirtual charAt : (I)C
    //   2491: invokevirtual append : (C)Ljava/lang/StringBuilder;
    //   2494: pop
    //   2495: iload_2
    //   2496: ifne -> 3148
    //   2499: goto -> 2506
    //   2502: invokestatic a : (Ljava/lang/Throwable;)Ljava/lang/Throwable;
    //   2505: athrow
    //   2506: aload #4
    //   2508: getstatic burp/Zzox.ZB : Ljava/lang/String;
    //   2511: getstatic burp/Zs4z.Ze : Ljava/lang/Object;
    //   2514: checkcast java/math/BigInteger
    //   2517: invokevirtual intValue : ()I
    //   2520: bipush #32
    //   2522: irem
    //   2523: invokestatic abs : (I)I
    //   2526: invokevirtual charAt : (I)C
    //   2529: invokevirtual append : (C)Ljava/lang/StringBuilder;
    //   2532: pop
    //   2533: iload_2
    //   2534: ifne -> 3148
    //   2537: goto -> 2544
    //   2540: invokestatic a : (Ljava/lang/Throwable;)Ljava/lang/Throwable;
    //   2543: athrow
    //   2544: aload #4
    //   2546: getstatic burp/Zrcy.Zq : Ljava/lang/String;
    //   2549: getstatic burp/Zeqg.Zm : Ljava/lang/Object;
    //   2552: checkcast java/math/BigInteger
    //   2555: invokevirtual intValue : ()I
    //   2558: bipush #32
    //   2560: irem
    //   2561: invokestatic abs : (I)I
    //   2564: invokevirtual charAt : (I)C
    //   2567: invokevirtual append : (C)Ljava/lang/StringBuilder;
    //   2570: pop
    //   2571: iload_2
    //   2572: ifne -> 3148
    //   2575: goto -> 2582
    //   2578: invokestatic a : (Ljava/lang/Throwable;)Ljava/lang/Throwable;
    //   2581: athrow
    //   2582: aload #4
    //   2584: getstatic burp/Ztdd.ZA : Ljava/lang/String;
    //   2587: getstatic burp/Ztkh.Zh : Ljava/lang/Object;
    //   2590: checkcast java/math/BigInteger
    //   2593: invokevirtual intValue : ()I
    //   2596: bipush #32
    //   2598: irem
    //   2599: invokestatic abs : (I)I
    //   2602: invokevirtual charAt : (I)C
    //   2605: invokevirtual append : (C)Ljava/lang/StringBuilder;
    //   2608: pop
    //   2609: iload_2
    //   2610: ifne -> 3148
    //   2613: goto -> 2620
    //   2616: invokestatic a : (Ljava/lang/Throwable;)Ljava/lang/Throwable;
    //   2619: athrow
    //   2620: aload #4
    //   2622: getstatic burp/Zxn5.ZI : Ljava/lang/String;
    //   2625: getstatic burp/Zrtv.Zg : Ljava/lang/Object;
    //   2628: checkcast java/math/BigInteger
    //   2631: invokevirtual intValue : ()I
    //   2634: bipush #32
    //   2636: irem
    //   2637: invokestatic abs : (I)I
    //   2640: invokevirtual charAt : (I)C
    //   2643: invokevirtual append : (C)Ljava/lang/StringBuilder;
    //   2646: pop
    //   2647: iload_2
    //   2648: ifne -> 3148
    //   2651: goto -> 2658
    //   2654: invokestatic a : (Ljava/lang/Throwable;)Ljava/lang/Throwable;
    //   2657: athrow
    //   2658: aload #4
    //   2660: getstatic burp/Zrcy.Zq : Ljava/lang/String;
    //   2663: getstatic burp/Zkb_.ZG : Ljava/lang/Object;
    //   2666: checkcast java/math/BigInteger
    //   2669: invokevirtual intValue : ()I
    //   2672: bipush #32
    //   2674: irem
    //   2675: invokestatic abs : (I)I
    //   2678: invokevirtual charAt : (I)C
    //   2681: invokevirtual append : (C)Ljava/lang/StringBuilder;
    //   2684: pop
    //   2685: iload_2
    //   2686: ifne -> 3148
    //   2689: goto -> 2696
    //   2692: invokestatic a : (Ljava/lang/Throwable;)Ljava/lang/Throwable;
    //   2695: athrow
    //   2696: aload #4
    //   2698: getstatic burp/Zmx6.ZG : Ljava/lang/String;
    //   2701: getstatic burp/Ztex.Z_ : Ljava/lang/Object;
    //   2704: checkcast java/math/BigInteger
    //   2707: invokevirtual intValue : ()I
    //   2710: bipush #32
    //   2712: irem
    //   2713: invokestatic abs : (I)I
    //   2716: invokevirtual charAt : (I)C
    //   2719: invokevirtual append : (C)Ljava/lang/StringBuilder;
    //   2722: pop
    //   2723: iload_2
    //   2724: ifne -> 3148
    //   2727: goto -> 2734
    //   2730: invokestatic a : (Ljava/lang/Throwable;)Ljava/lang/Throwable;
    //   2733: athrow
    //   2734: aload #4
    //   2736: getstatic burp/Ze_t.ZZ : Ljava/lang/String;
    //   2739: getstatic burp/Ztkh.Zh : Ljava/lang/Object;
    //   2742: checkcast java/math/BigInteger
    //   2745: invokevirtual intValue : ()I
    //   2748: bipush #32
    //   2750: irem
    //   2751: invokestatic abs : (I)I
    //   2754: invokevirtual charAt : (I)C
    //   2757: invokevirtual append : (C)Ljava/lang/StringBuilder;
    //   2760: pop
    //   2761: iload_2
    //   2762: ifne -> 3148
    //   2765: goto -> 2772
    //   2768: invokestatic a : (Ljava/lang/Throwable;)Ljava/lang/Throwable;
    //   2771: athrow
    //   2772: aload #4
    //   2774: getstatic burp/Ze69.ZA : Ljava/lang/String;
    //   2777: getstatic burp/Zex.ZO : Ljava/lang/Object;
    //   2780: checkcast java/math/BigInteger
    //   2783: invokevirtual intValue : ()I
    //   2786: bipush #32
    //   2788: irem
    //   2789: invokestatic abs : (I)I
    //   2792: invokevirtual charAt : (I)C
    //   2795: invokevirtual append : (C)Ljava/lang/StringBuilder;
    //   2798: pop
    //   2799: iload_2
    //   2800: ifne -> 3148
    //   2803: goto -> 2810
    //   2806: invokestatic a : (Ljava/lang/Throwable;)Ljava/lang/Throwable;
    //   2809: athrow
    //   2810: aload #4
    //   2812: getstatic burp/Zmj8.ZL : Ljava/lang/String;
    //   2815: getstatic burp/Zr2i.ZD : Ljava/lang/Object;
    //   2818: checkcast java/math/BigInteger
    //   2821: invokevirtual intValue : ()I
    //   2824: bipush #32
    //   2826: irem
    //   2827: invokestatic abs : (I)I
    //   2830: invokevirtual charAt : (I)C
    //   2833: invokevirtual append : (C)Ljava/lang/StringBuilder;
    //   2836: pop
    //   2837: iload_2
    //   2838: ifne -> 3148
    //   2841: goto -> 2848
    //   2844: invokestatic a : (Ljava/lang/Throwable;)Ljava/lang/Throwable;
    //   2847: athrow
    //   2848: aload #4
    //   2850: getstatic burp/Zv8c.ZO : Ljava/lang/String;
    //   2853: getstatic burp/Zsbt.Zl : Ljava/lang/Object;
    //   2856: checkcast java/math/BigInteger
    //   2859: invokevirtual intValue : ()I
    //   2862: bipush #32
    //   2864: irem
    //   2865: invokestatic abs : (I)I
    //   2868: invokevirtual charAt : (I)C
    //   2871: invokevirtual append : (C)Ljava/lang/StringBuilder;
    //   2874: pop
    //   2875: iload_2
    //   2876: ifne -> 3148
    //   2879: goto -> 2886
    //   2882: invokestatic a : (Ljava/lang/Throwable;)Ljava/lang/Throwable;
    //   2885: athrow
    //   2886: aload #4
    //   2888: getstatic burp/Zlr.ZO : Ljava/lang/String;
    //   2891: getstatic burp/Zv8c.Zx : Ljava/lang/Object;
    //   2894: checkcast java/math/BigInteger
    //   2897: invokevirtual intValue : ()I
    //   2900: bipush #32
    //   2902: irem
    //   2903: invokestatic abs : (I)I
    //   2906: invokevirtual charAt : (I)C
    //   2909: invokevirtual append : (C)Ljava/lang/StringBuilder;
    //   2912: pop
    //   2913: iload_2
    //   2914: ifne -> 3148
    //   2917: goto -> 2924
    //   2920: invokestatic a : (Ljava/lang/Throwable;)Ljava/lang/Throwable;
    //   2923: athrow
    //   2924: aload #4
    //   2926: getstatic burp/Zlck.ZL : Ljava/lang/String;
    //   2929: getstatic burp/Zs8s.ZG : Ljava/lang/Object;
    //   2932: checkcast java/math/BigInteger
    //   2935: invokevirtual intValue : ()I
    //   2938: bipush #32
    //   2940: irem
    //   2941: invokestatic abs : (I)I
    //   2944: invokevirtual charAt : (I)C
    //   2947: invokevirtual append : (C)Ljava/lang/StringBuilder;
    //   2950: pop
    //   2951: iload_2
    //   2952: ifne -> 3148
    //   2955: goto -> 2962
    //   2958: invokestatic a : (Ljava/lang/Throwable;)Ljava/lang/Throwable;
    //   2961: athrow
    //   2962: aload #4
    //   2964: getstatic burp/Zgpp.Zm : Ljava/lang/String;
    //   2967: getstatic burp/Zrhp.Zw : Ljava/lang/Object;
    //   2970: checkcast java/math/BigInteger
    //   2973: invokevirtual intValue : ()I
    //   2976: bipush #32
    //   2978: irem
    //   2979: invokestatic abs : (I)I
    //   2982: invokevirtual charAt : (I)C
    //   2985: invokevirtual append : (C)Ljava/lang/StringBuilder;
    //   2988: pop
    //   2989: iload_2
    //   2990: ifne -> 3148
    //   2993: goto -> 3000
    //   2996: invokestatic a : (Ljava/lang/Throwable;)Ljava/lang/Throwable;
    //   2999: athrow
    //   3000: aload #4
    //   3002: getstatic burp/Zzyr.Z_ : Ljava/lang/String;
    //   3005: getstatic burp/Zs83.ZT : Ljava/lang/Object;
    //   3008: checkcast java/math/BigInteger
    //   3011: invokevirtual intValue : ()I
    //   3014: bipush #32
    //   3016: irem
    //   3017: invokestatic abs : (I)I
    //   3020: invokevirtual charAt : (I)C
    //   3023: invokevirtual append : (C)Ljava/lang/StringBuilder;
    //   3026: pop
    //   3027: iload_2
    //   3028: ifne -> 3148
    //   3031: goto -> 3038
    //   3034: invokestatic a : (Ljava/lang/Throwable;)Ljava/lang/Throwable;
    //   3037: athrow
    //   3038: aload #4
    //   3040: getstatic burp/Zmr7.Zo : Ljava/lang/String;
    //   3043: getstatic burp/Zg_5.ZA : Ljava/lang/Object;
    //   3046: checkcast java/math/BigInteger
    //   3049: invokevirtual intValue : ()I
    //   3052: bipush #32
    //   3054: irem
    //   3055: invokestatic abs : (I)I
    //   3058: invokevirtual charAt : (I)C
    //   3061: invokevirtual append : (C)Ljava/lang/StringBuilder;
    //   3064: pop
    //   3065: iload_2
    //   3066: ifne -> 3148
    //   3069: goto -> 3076
    //   3072: invokestatic a : (Ljava/lang/Throwable;)Ljava/lang/Throwable;
    //   3075: athrow
    //   3076: aload #4
    //   3078: getstatic burp/Zv8c.ZO : Ljava/lang/String;
    //   3081: getstatic burp/Zv8c.Zx : Ljava/lang/Object;
    //   3084: checkcast java/math/BigInteger
    //   3087: invokevirtual intValue : ()I
    //   3090: bipush #32
    //   3092: irem
    //   3093: invokestatic abs : (I)I
    //   3096: invokevirtual charAt : (I)C
    //   3099: invokevirtual append : (C)Ljava/lang/StringBuilder;
    //   3102: pop
    //   3103: iload_2
    //   3104: ifne -> 3148
    //   3107: goto -> 3114
    //   3110: invokestatic a : (Ljava/lang/Throwable;)Ljava/lang/Throwable;
    //   3113: athrow
    //   3114: aload #4
    //   3116: getstatic burp/Zxzz.ZT : Ljava/lang/String;
    //   3119: getstatic burp/Zz20.ZN : Ljava/lang/Object;
    //   3122: checkcast java/math/BigInteger
    //   3125: invokevirtual intValue : ()I
    //   3128: bipush #32
    //   3130: irem
    //   3131: invokestatic abs : (I)I
    //   3134: invokevirtual charAt : (I)C
    //   3137: invokevirtual append : (C)Ljava/lang/StringBuilder;
    //   3140: pop
    //   3141: goto -> 3148
    //   3144: invokestatic a : (Ljava/lang/Throwable;)Ljava/lang/Throwable;
    //   3147: athrow
    //   3148: iinc #5, 1
    //   3151: iload_2
    //   3152: ifne -> 1786
    //   3155: aload #4
    //   3157: invokevirtual toString : ()Ljava/lang/String;
    //   3160: putstatic burp/Zsj5.Zn : Ljava/lang/String;
    //   3163: sipush #-10062
    //   3166: sipush #31864
    //   3169: invokestatic a : (II)Ljava/lang/String;
    //   3172: iconst_1
    //   3173: ldc burp/Zbu6
    //   3175: invokevirtual getClassLoader : ()Ljava/lang/ClassLoader;
    //   3178: invokestatic forName : (Ljava/lang/String;ZLjava/lang/ClassLoader;)Ljava/lang/Class;
    //   3181: invokevirtual getDeclaredFields : ()[Ljava/lang/reflect/Field;
    //   3184: astore #5
    //   3186: aload #5
    //   3188: arraylength
    //   3189: istore #6
    //   3191: iconst_0
    //   3192: istore #7
    //   3194: iload #7
    //   3196: iload #6
    //   3198: if_icmpge -> 3336
    //   3201: aload #5
    //   3203: iload #7
    //   3205: aaload
    //   3206: astore #8
    //   3208: aload #8
    //   3210: invokevirtual getModifiers : ()I
    //   3213: invokestatic isStatic : (I)Z
    //   3216: ifne -> 3226
    //   3219: goto -> 3329
    //   3222: invokestatic a : (Ljava/lang/Throwable;)Ljava/lang/Throwable;
    //   3225: athrow
    //   3226: aload #8
    //   3228: invokevirtual getType : ()Ljava/lang/Class;
    //   3231: astore #9
    //   3233: aload #9
    //   3235: ifnull -> 3316
    //   3238: aload #9
    //   3240: invokevirtual isPrimitive : ()Z
    //   3243: ifne -> 3316
    //   3246: goto -> 3253
    //   3249: invokestatic a : (Ljava/lang/Throwable;)Ljava/lang/Throwable;
    //   3252: athrow
    //   3253: aload #9
    //   3255: invokevirtual getPackage : ()Ljava/lang/Package;
    //   3258: ifnull -> 3316
    //   3261: goto -> 3268
    //   3264: invokestatic a : (Ljava/lang/Throwable;)Ljava/lang/Throwable;
    //   3267: athrow
    //   3268: aload #9
    //   3270: invokevirtual getPackage : ()Ljava/lang/Package;
    //   3273: invokevirtual getName : ()Ljava/lang/String;
    //   3276: ifnull -> 3316
    //   3279: goto -> 3286
    //   3282: invokestatic a : (Ljava/lang/Throwable;)Ljava/lang/Throwable;
    //   3285: athrow
    //   3286: aload #9
    //   3288: invokevirtual getPackage : ()Ljava/lang/Package;
    //   3291: invokevirtual getName : ()Ljava/lang/String;
    //   3294: sipush #-10064
    //   3297: sipush #6132
    //   3300: invokestatic a : (II)Ljava/lang/String;
    //   3303: invokevirtual startsWith : (Ljava/lang/String;)Z
    //   3306: ifne -> 3316
    //   3309: goto -> 3316
    //   3312: invokestatic a : (Ljava/lang/Throwable;)Ljava/lang/Throwable;
    //   3315: athrow
    //   3316: aload #8
    //   3318: iconst_1
    //   3319: invokevirtual setAccessible : (Z)V
    //   3322: aload #8
    //   3324: aconst_null
    //   3325: invokevirtual get : (Ljava/lang/Object;)Ljava/lang/Object;
    //   3328: pop
    //   3329: iinc #7, 1
    //   3332: iload_2
    //   3333: ifne -> 3194
    //   3336: sipush #-10063
    //   3339: sipush #-21835
    //   3342: invokestatic a : (II)Ljava/lang/String;
    //   3345: invokestatic forName : (Ljava/lang/String;)Ljava/lang/Class;
    //   3348: invokevirtual getDeclaredMethods : ()[Ljava/lang/reflect/Method;
    //   3351: astore #5
    //   3353: aload #5
    //   3355: arraylength
    //   3356: istore #6
    //   3358: iconst_0
    //   3359: istore #7
    //   3361: iload #7
    //   3363: iload #6
    //   3365: if_icmpge -> 3498
    //   3368: aload #5
    //   3370: iload #7
    //   3372: aaload
    //   3373: astore #8
    //   3375: aload #8
    //   3377: invokevirtual getParameterTypes : ()[Ljava/lang/Class;
    //   3380: pop
    //   3381: aload #8
    //   3383: invokevirtual getModifiers : ()I
    //   3386: invokestatic isStatic : (I)Z
    //   3389: ifeq -> 3484
    //   3392: aload #8
    //   3394: invokevirtual getParameterTypes : ()[Ljava/lang/Class;
    //   3397: arraylength
    //   3398: iconst_2
    //   3399: if_icmpne -> 3484
    //   3402: goto -> 3409
    //   3405: invokestatic a : (Ljava/lang/Throwable;)Ljava/lang/Throwable;
    //   3408: athrow
    //   3409: aload #8
    //   3411: invokevirtual getReturnType : ()Ljava/lang/Class;
    //   3414: getstatic java/lang/Void.TYPE : Ljava/lang/Class;
    //   3417: invokevirtual equals : (Ljava/lang/Object;)Z
    //   3420: ifeq -> 3484
    //   3423: goto -> 3430
    //   3426: invokestatic a : (Ljava/lang/Throwable;)Ljava/lang/Throwable;
    //   3429: athrow
    //   3430: aload #8
    //   3432: iconst_1
    //   3433: invokevirtual setAccessible : (Z)V
    //   3436: aload #8
    //   3438: aconst_null
    //   3439: iconst_2
    //   3440: anewarray java/lang/Object
    //   3443: dup
    //   3444: iconst_0
    //   3445: aload_0
    //   3446: aastore
    //   3447: dup
    //   3448: iconst_1
    //   3449: aload_1
    //   3450: ifnonnull -> 3468
    //   3453: goto -> 3460
    //   3456: invokestatic a : (Ljava/lang/Throwable;)Ljava/lang/Throwable;
    //   3459: athrow
    //   3460: aload_1
    //   3461: goto -> 3475
    //   3464: invokestatic a : (Ljava/lang/Throwable;)Ljava/lang/Throwable;
    //   3467: athrow
    //   3468: aload_1
    //   3469: checkcast [B
    //   3472: invokevirtual clone : ()Ljava/lang/Object;
    //   3475: aastore
    //   3476: invokevirtual invoke : (Ljava/lang/Object;[Ljava/lang/Object;)Ljava/lang/Object;
    //   3479: pop
    //   3480: iload_2
    //   3481: ifne -> 3498
    //   3484: iinc #7, 1
    //   3487: iload_2
    //   3488: ifne -> 3361
    //   3491: goto -> 3498
    //   3494: invokestatic a : (Ljava/lang/Throwable;)Ljava/lang/Throwable;
    //   3497: athrow
    //   3498: getstatic burp/Zeqg.Zh : Ljava/lang/String;
    //   3501: getstatic burp/Ztcv.ZY : Ljava/lang/Object;
    //   3504: checkcast java/math/BigInteger
    //   3507: invokevirtual intValue : ()I
    //   3510: bipush #32
    //   3512: irem
    //   3513: invokestatic abs : (I)I
    //   3516: invokevirtual charAt : (I)C
    //   3519: getstatic burp/Zg4w.ZC : Ljava/lang/String;
    //   3522: getstatic burp/Zz2e.Zm : Ljava/lang/Object;
    //   3525: checkcast java/math/BigInteger
    //   3528: invokevirtual intValue : ()I
    //   3531: bipush #32
    //   3533: irem
    //   3534: invokestatic abs : (I)I
    //   3537: invokevirtual charAt : (I)C
    //   3540: if_icmpgt -> 3647
    //   3543: getstatic burp/Zkt7.ZM : Ljava/lang/String;
    //   3546: getstatic burp/Zsbt.Zl : Ljava/lang/Object;
    //   3549: checkcast java/math/BigInteger
    //   3552: invokevirtual intValue : ()I
    //   3555: bipush #32
    //   3557: irem
    //   3558: invokestatic abs : (I)I
    //   3561: invokevirtual charAt : (I)C
    //   3564: getstatic burp/Zsj5.Zn : Ljava/lang/String;
    //   3567: getstatic burp/Zex.ZO : Ljava/lang/Object;
    //   3570: checkcast java/math/BigInteger
    //   3573: invokevirtual intValue : ()I
    //   3576: bipush #32
    //   3578: irem
    //   3579: invokestatic abs : (I)I
    //   3582: invokevirtual charAt : (I)C
    //   3585: if_icmpgt -> 3647
    //   3588: goto -> 3595
    //   3591: invokestatic a : (Ljava/lang/Throwable;)Ljava/lang/Throwable;
    //   3594: athrow
    //   3595: getstatic burp/Zr2i.Z_ : Ljava/lang/String;
    //   3598: getstatic burp/Zlhq.Zw : Ljava/lang/Object;
    //   3601: checkcast java/math/BigInteger
    //   3604: invokevirtual intValue : ()I
    //   3607: bipush #32
    //   3609: irem
    //   3610: invokestatic abs : (I)I
    //   3613: invokevirtual charAt : (I)C
    //   3616: getstatic burp/Zgzv.Zy : Ljava/lang/String;
    //   3619: getstatic burp/Zg6f.Zl : Ljava/lang/Object;
    //   3622: checkcast java/math/BigInteger
    //   3625: invokevirtual intValue : ()I
    //   3628: bipush #32
    //   3630: irem
    //   3631: invokestatic abs : (I)I
    //   3634: invokevirtual charAt : (I)C
    //   3637: if_icmple -> 3655
    //   3640: goto -> 3647
    //   3643: invokestatic a : (Ljava/lang/Throwable;)Ljava/lang/Throwable;
    //   3646: athrow
    //   3647: iconst_1
    //   3648: goto -> 3656
    //   3651: invokestatic a : (Ljava/lang/Throwable;)Ljava/lang/Throwable;
    //   3654: athrow
    //   3655: iconst_0
    //   3656: ireturn
    //   3657: astore_3
    //   3658: new java/lang/Exception
    //   3661: dup
    //   3662: aload_3
    //   3663: invokevirtual getMessage : ()Ljava/lang/String;
    //   3666: invokespecial <init> : (Ljava/lang/String;)V
    //   3669: athrow
    // Exception table:
    //   from	to	target	type
    //   4	3656	3657	java/lang/Throwable
    //   191	219	222	java/lang/Throwable
    //   201	236	239	java/lang/Throwable
    //   226	264	267	java/lang/Throwable
    //   243	281	284	java/lang/Throwable
    //   271	309	312	java/lang/Throwable
    //   288	326	329	java/lang/Throwable
    //   316	344	347	java/lang/Throwable
    //   333	358	361	java/lang/Throwable
    //   437	610	613	java/lang/Throwable
    //   580	647	650	java/lang/Throwable
    //   617	684	687	java/lang/Throwable
    //   654	721	724	java/lang/Throwable
    //   691	758	761	java/lang/Throwable
    //   728	795	798	java/lang/Throwable
    //   765	832	835	java/lang/Throwable
    //   802	869	872	java/lang/Throwable
    //   839	906	909	java/lang/Throwable
    //   876	943	946	java/lang/Throwable
    //   913	980	983	java/lang/Throwable
    //   950	1017	1020	java/lang/Throwable
    //   987	1054	1057	java/lang/Throwable
    //   1024	1091	1094	java/lang/Throwable
    //   1061	1128	1131	java/lang/Throwable
    //   1098	1165	1168	java/lang/Throwable
    //   1135	1202	1205	java/lang/Throwable
    //   1172	1239	1242	java/lang/Throwable
    //   1209	1276	1279	java/lang/Throwable
    //   1246	1313	1316	java/lang/Throwable
    //   1283	1350	1353	java/lang/Throwable
    //   1320	1387	1390	java/lang/Throwable
    //   1357	1424	1427	java/lang/Throwable
    //   1394	1461	1464	java/lang/Throwable
    //   1431	1498	1501	java/lang/Throwable
    //   1468	1535	1538	java/lang/Throwable
    //   1505	1572	1575	java/lang/Throwable
    //   1542	1609	1612	java/lang/Throwable
    //   1579	1646	1649	java/lang/Throwable
    //   1616	1683	1686	java/lang/Throwable
    //   1653	1720	1723	java/lang/Throwable
    //   1690	1753	1756	java/lang/Throwable
    //   1793	1967	1970	java/lang/Throwable
    //   1936	2005	2008	java/lang/Throwable
    //   1974	2043	2046	java/lang/Throwable
    //   2012	2081	2084	java/lang/Throwable
    //   2050	2119	2122	java/lang/Throwable
    //   2088	2157	2160	java/lang/Throwable
    //   2126	2195	2198	java/lang/Throwable
    //   2164	2233	2236	java/lang/Throwable
    //   2202	2271	2274	java/lang/Throwable
    //   2240	2309	2312	java/lang/Throwable
    //   2278	2347	2350	java/lang/Throwable
    //   2316	2385	2388	java/lang/Throwable
    //   2354	2423	2426	java/lang/Throwable
    //   2392	2461	2464	java/lang/Throwable
    //   2430	2499	2502	java/lang/Throwable
    //   2468	2537	2540	java/lang/Throwable
    //   2506	2575	2578	java/lang/Throwable
    //   2544	2613	2616	java/lang/Throwable
    //   2582	2651	2654	java/lang/Throwable
    //   2620	2689	2692	java/lang/Throwable
    //   2658	2727	2730	java/lang/Throwable
    //   2696	2765	2768	java/lang/Throwable
    //   2734	2803	2806	java/lang/Throwable
    //   2772	2841	2844	java/lang/Throwable
    //   2810	2879	2882	java/lang/Throwable
    //   2848	2917	2920	java/lang/Throwable
    //   2886	2955	2958	java/lang/Throwable
    //   2924	2993	2996	java/lang/Throwable
    //   2962	3031	3034	java/lang/Throwable
    //   3000	3069	3072	java/lang/Throwable
    //   3038	3107	3110	java/lang/Throwable
    //   3076	3141	3144	java/lang/Throwable
    //   3208	3222	3222	java/lang/Throwable
    //   3233	3246	3249	java/lang/Throwable
    //   3238	3261	3264	java/lang/Throwable
    //   3253	3279	3282	java/lang/Throwable
    //   3268	3309	3312	java/lang/Throwable
    //   3375	3402	3405	java/lang/Throwable
    //   3392	3423	3426	java/lang/Throwable
    //   3409	3453	3456	java/lang/Throwable
    //   3430	3464	3464	java/lang/Throwable
    //   3475	3491	3494	java/lang/Throwable
    //   3498	3588	3591	java/lang/Throwable
    //   3543	3640	3643	java/lang/Throwable
    //   3595	3651	3651	java/lang/Throwable
  }
  
  static {
    // Byte code:
    //   0: bipush #8
    //   2: anewarray java/lang/String
    //   5: astore #5
    //   7: iconst_0
    //   8: istore_3
    //   9: ldc '+RMaCe9J{8,T45L/+\\t;V%u rd7-#Xm`}D ^\\t4\\tl tv=LtOTS]\\t?`5.C\\tpyn='
    //   11: dup
    //   12: astore_2
    //   13: invokevirtual length : ()I
    //   16: istore #4
    //   18: bipush #77
    //   20: istore_1
    //   21: iconst_m1
    //   22: istore_0
    //   23: bipush #86
    //   25: iinc #0, 1
    //   28: aload_2
    //   29: iload_0
    //   30: dup
    //   31: iload_1
    //   32: iadd
    //   33: invokevirtual substring : (II)Ljava/lang/String;
    //   36: iconst_m1
    //   37: goto -> 143
    //   40: aload #5
    //   42: swap
    //   43: iload_3
    //   44: iinc #3, 1
    //   47: swap
    //   48: aastore
    //   49: iload_0
    //   50: iload_1
    //   51: iadd
    //   52: dup
    //   53: istore_0
    //   54: iload #4
    //   56: if_icmpge -> 68
    //   59: aload_2
    //   60: iload_0
    //   61: invokevirtual charAt : (I)C
    //   64: istore_1
    //   65: goto -> 23
    //   68: ldc 'r+hvlo,Gei7/\\tW$4'
    //   70: dup
    //   71: astore_2
    //   72: invokevirtual length : ()I
    //   75: istore #4
    //   77: bipush #32
    //   79: istore_1
    //   80: iconst_m1
    //   81: istore_0
    //   82: bipush #127
    //   84: iinc #0, 1
    //   87: aload_2
    //   88: iload_0
    //   89: dup
    //   90: iload_1
    //   91: iadd
    //   92: invokevirtual substring : (II)Ljava/lang/String;
    //   95: iconst_0
    //   96: goto -> 143
    //   99: aload #5
    //   101: swap
    //   102: iload_3
    //   103: iinc #3, 1
    //   106: swap
    //   107: aastore
    //   108: iload_0
    //   109: iload_1
    //   110: iadd
    //   111: dup
    //   112: istore_0
    //   113: iload #4
    //   115: if_icmpge -> 127
    //   118: aload_2
    //   119: iload_0
    //   120: invokevirtual charAt : (I)C
    //   123: istore_1
    //   124: goto -> 82
    //   127: aload #5
    //   129: putstatic burp/Zgva.a : [Ljava/lang/String;
    //   132: bipush #8
    //   134: anewarray java/lang/String
    //   137: putstatic burp/Zgva.b : [Ljava/lang/String;
    //   140: goto -> 300
    //   143: dup_x2
    //   144: pop
    //   145: invokevirtual toCharArray : ()[C
    //   148: dup_x1
    //   149: arraylength
    //   150: dup_x2
    //   151: pop
    //   152: iconst_0
    //   153: istore #6
    //   155: dup2_x1
    //   156: pop2
    //   157: dup_x2
    //   158: iconst_1
    //   159: if_icmpgt -> 260
    //   162: dup2
    //   163: swap
    //   164: iload #6
    //   166: dup2_x1
    //   167: caload
    //   168: swap
    //   169: iload #6
    //   171: bipush #7
    //   173: irem
    //   174: tableswitch default -> 242, 0 -> 212, 1 -> 217, 2 -> 222, 3 -> 227, 4 -> 232, 5 -> 237
    //   212: bipush #32
    //   214: goto -> 244
    //   217: bipush #64
    //   219: goto -> 244
    //   222: bipush #22
    //   224: goto -> 244
    //   227: bipush #29
    //   229: goto -> 244
    //   232: bipush #30
    //   234: goto -> 244
    //   237: bipush #84
    //   239: goto -> 244
    //   242: bipush #14
    //   244: ixor
    //   245: ixor
    //   246: i2c
    //   247: castore
    //   248: iinc #6, 1
    //   251: dup
    //   252: ifne -> 260
    //   255: dup2
    //   256: dup_x1
    //   257: goto -> 166
    //   260: dup2_x1
    //   261: pop2
    //   262: dup_x2
    //   263: iload #6
    //   265: if_icmpgt -> 162
    //   268: pop
    //   269: new java/lang/String
    //   272: dup_x1
    //   273: swap
    //   274: invokespecial <init> : ([C)V
    //   277: invokevirtual intern : ()Ljava/lang/String;
    //   280: swap
    //   281: pop
    //   282: swap
    //   283: tableswitch default -> 40, 0 -> 99
    //   300: new java/math/BigInteger
    //   303: dup
    //   304: bipush #32
    //   306: newarray byte
    //   308: dup
    //   309: iconst_0
    //   310: bipush #127
    //   312: bastore
    //   313: dup
    //   314: iconst_1
    //   315: bipush #-85
    //   317: bastore
    //   318: dup
    //   319: iconst_2
    //   320: bipush #-26
    //   322: bastore
    //   323: dup
    //   324: iconst_3
    //   325: bipush #-32
    //   327: bastore
    //   328: dup
    //   329: iconst_4
    //   330: bipush #-75
    //   332: bastore
    //   333: dup
    //   334: iconst_5
    //   335: bipush #-82
    //   337: bastore
    //   338: dup
    //   339: bipush #6
    //   341: bipush #-113
    //   343: bastore
    //   344: dup
    //   345: bipush #7
    //   347: bipush #31
    //   349: bastore
    //   350: dup
    //   351: bipush #8
    //   353: bipush #-124
    //   355: bastore
    //   356: dup
    //   357: bipush #9
    //   359: bipush #-43
    //   361: bastore
    //   362: dup
    //   363: bipush #10
    //   365: bipush #-126
    //   367: bastore
    //   368: dup
    //   369: bipush #11
    //   371: bipush #-36
    //   373: bastore
    //   374: dup
    //   375: bipush #12
    //   377: bipush #-14
    //   379: bastore
    //   380: dup
    //   381: bipush #13
    //   383: bipush #-124
    //   385: bastore
    //   386: dup
    //   387: bipush #14
    //   389: bipush #-23
    //   391: bastore
    //   392: dup
    //   393: bipush #15
    //   395: bipush #-119
    //   397: bastore
    //   398: dup
    //   399: bipush #16
    //   401: bipush #-11
    //   403: bastore
    //   404: dup
    //   405: bipush #17
    //   407: bipush #-18
    //   409: bastore
    //   410: dup
    //   411: bipush #18
    //   413: bipush #-84
    //   415: bastore
    //   416: dup
    //   417: bipush #19
    //   419: bipush #-7
    //   421: bastore
    //   422: dup
    //   423: bipush #20
    //   425: bipush #-77
    //   427: bastore
    //   428: dup
    //   429: bipush #21
    //   431: bipush #114
    //   433: bastore
    //   434: dup
    //   435: bipush #22
    //   437: bipush #-29
    //   439: bastore
    //   440: dup
    //   441: bipush #23
    //   443: bipush #101
    //   445: bastore
    //   446: dup
    //   447: bipush #24
    //   449: bipush #-49
    //   451: bastore
    //   452: dup
    //   453: bipush #25
    //   455: bipush #-96
    //   457: bastore
    //   458: dup
    //   459: bipush #26
    //   461: bipush #67
    //   463: bastore
    //   464: dup
    //   465: bipush #27
    //   467: bipush #12
    //   469: bastore
    //   470: dup
    //   471: bipush #28
    //   473: bipush #67
    //   475: bastore
    //   476: dup
    //   477: bipush #29
    //   479: bipush #-21
    //   481: bastore
    //   482: dup
    //   483: bipush #30
    //   485: bipush #-12
    //   487: bastore
    //   488: dup
    //   489: bipush #31
    //   491: bipush #-86
    //   493: bastore
    //   494: invokespecial <init> : ([B)V
    //   497: putstatic burp/Zgva.Zr : Ljava/lang/Object;
    //   500: sipush #-10057
    //   503: sipush #-13876
    //   506: invokestatic a : (II)Ljava/lang/String;
    //   509: putstatic burp/Zgva.ZV : Ljava/lang/String;
    //   512: return
  }
  
  private static Throwable a(Throwable paramThrowable) {
    return paramThrowable;
  }
  
  private static String a(int paramInt1, int paramInt2) {
    int i = (paramInt1 ^ 0xFFFFD8B5) & 0xFFFF;
    if (b[i] == null) {
      char[] arrayOfChar = a[i].toCharArray();
      switch (arrayOfChar[0] & 0xFF) {
        case 0:
        
        case 1:
        
        case 2:
        
        case 3:
        
        case 4:
        
        case 5:
        
        case 6:
        
        case 7:
        
        case 8:
        
        case 9:
        
        case 10:
        
        case 11:
        
        case 12:
        
        case 13:
        
        case 14:
        
        case 15:
        
        case 16:
        
        case 17:
        
        case 18:
        
        case 19:
        
        case 20:
        
        case 21:
        
        case 22:
        
        case 23:
        
        case 24:
        
        case 25:
        
        case 26:
        
        case 27:
        
        case 28:
        
        case 29:
        
        case 30:
        
        case 31:
        
        case 32:
        
        case 33:
        
        case 34:
        
        case 35:
        
        case 36:
        
        case 37:
        
        case 38:
        
        case 39:
        
        case 40:
        
        case 41:
        
        case 42:
        
        case 43:
        
        case 44:
        
        case 45:
        
        case 46:
        
        case 47:
        
        case 48:
        
        case 49:
        
        case 50:
        
        case 51:
        
        case 52:
        
        case 53:
        
        case 54:
        
        case 55:
        
        case 56:
        
        case 57:
        
        case 58:
        
        case 59:
        
        case 60:
        
        case 61:
        
        case 62:
        
        case 63:
        
        case 64:
        
        case 65:
        
        case 66:
        
        case 67:
        
        case 68:
        
        case 69:
        
        case 70:
        
        case 71:
        
        case 72:
        
        case 73:
        
        case 74:
        
        case 75:
        
        case 76:
        
        case 77:
        
        case 78:
        
        case 79:
        
        case 80:
        
        case 81:
        
        case 82:
        
        case 83:
        
        case 84:
        
        case 85:
        
        case 86:
        
        case 87:
        
        case 88:
        
        case 89:
        
        case 90:
        
        case 91:
        
        case 92:
        
        case 93:
        
        case 94:
        
        case 95:
        
        case 96:
        
        case 97:
        
        case 98:
        
        case 99:
        
        case 100:
        
        case 101:
        
        case 102:
        
        case 103:
        
        case 104:
        
        case 105:
        
        case 106:
        
        case 107:
        
        case 108:
        
        case 109:
        
        case 110:
        
        case 111:
        
        case 112:
        
        case 113:
        
        case 114:
        
        case 115:
        
        case 116:
        
        case 117:
        
        case 118:
        
        case 119:
        
        case 120:
        
        case 121:
        
        case 122:
        
        case 123:
        
        case 124:
        
        case 125:
        
        case 126:
        
        case 127:
        
        case 128:
        
        case 129:
        
        case 130:
        
        case 131:
        
        case 132:
        
        case 133:
        
        case 134:
        
        case 135:
        
        case 136:
        
        case 137:
        
        case 138:
        
        case 139:
        
        case 140:
        
        case 141:
        
        case 142:
        
        case 143:
        
        case 144:
        
        case 145:
        
        case 146:
        
        case 147:
        
        case 148:
        
        case 149:
        
        case 150:
        
        case 151:
        
        case 152:
        
        case 153:
        
        case 154:
        
        case 155:
        
        case 156:
        
        case 157:
        
        case 158:
        
        case 159:
        
        case 160:
        
        case 161:
        
        case 162:
        
        case 163:
        
        case 164:
        
        case 165:
        
        case 166:
        
        case 167:
        
        case 168:
        
        case 169:
        
        case 170:
        
        case 171:
        
        case 172:
        
        case 173:
        
        case 174:
        
        case 175:
        
        case 176:
        
        case 177:
        
        case 178:
        
        case 179:
        
        case 180:
        
        case 181:
        
        case 182:
        
        case 183:
        
        case 184:
        
        case 185:
        
        case 186:
        
        case 187:
        
        case 188:
        
        case 189:
        
        case 190:
        
        case 191:
        
        case 192:
        
        case 193:
        
        case 194:
        
        case 195:
        
        case 196:
        
        case 197:
        
        case 198:
        
        case 199:
        
        case 200:
        
        case 201:
        
        case 202:
        
        case 203:
        
        case 204:
        
        case 205:
        
        case 206:
        
        case 207:
        
        case 208:
        
        case 209:
        
        case 210:
        
        case 211:
        
        case 212:
        
        case 213:
        
        case 214:
        
        case 215:
        
        case 216:
        
        case 217:
        
        case 218:
        
        case 219:
        
        case 220:
        
        case 221:
        
        case 222:
        
        case 223:
        
        case 224:
        
        case 225:
        
        case 226:
        
        case 227:
        
        case 228:
        
        case 229:
        
        case 230:
        
        case 231:
        
        case 232:
        
        case 233:
        
        case 234:
        
        case 235:
        
        case 236:
        
        case 237:
        
        case 238:
        
        case 239:
        
        case 240:
        
        case 241:
        
        case 242:
        
        case 243:
        
        case 244:
        
        case 245:
        
        case 246:
        
        case 247:
        
        case 248:
        
        case 249:
        
        case 250:
        
        case 251:
        
        case 252:
        
        case 253:
        
        case 254:
        
        default:
          break;
      } 
      byte b1 = 51;
      int j = (paramInt2 & 0xFF) - b1;
      if (j < 0)
        j += 256; 
      int k = ((paramInt2 & 0xFFFF) >>> 8) - b1;
      if (k < 0)
        k += 256; 
      for (byte b2 = 0; b2 < arrayOfChar.length; b2++) {
        int m = b2 % 2;
        if (m == 0) {
          arrayOfChar[b2] = (char)(arrayOfChar[b2] ^ j);
          j = ((j >>> 3 | j << 5) ^ arrayOfChar[b2]) & 0xFF;
        } else {
          arrayOfChar[b2] = (char)(arrayOfChar[b2] ^ k);
          k = ((k >>> 3 | k << 5) ^ arrayOfChar[b2]) & 0xFF;
        } 
      } 
      b[i] = (new String(arrayOfChar)).intern();
    } 
    return b[i];
  }
}


/* Location:              C:\Program Files\BurpSuitePro\burpsuite_pro.jar!\burp\Zgva.class
 * Java compiler version: 21 (65.0)
 * JD-Core Version:       1.1.3
 */