package burp;

import java.math.BigInteger;

class Zgwu extends ClassLoader {
  static Object ZD;
  
  static String Zd;
  
  private static final String[] a;
  
  private static final String[] b;
  
  static boolean Zn(Object[] paramArrayOfObject, Object paramObject) throws Throwable {
    // Byte code:
    //   0: invokestatic ZN : ()Z
    //   3: istore_2
    //   4: sipush #27779
    //   7: sipush #1708
    //   10: invokestatic a : (II)Ljava/lang/String;
    //   13: invokestatic forName : (Ljava/lang/String;)Ljava/lang/Class;
    //   16: invokestatic Zl : (Ljava/lang/Object;)V
    //   19: getstatic burp/Zmzh.Zk : Ljava/lang/Object;
    //   22: checkcast java/math/BigInteger
    //   25: invokevirtual toByteArray : ()[B
    //   28: astore_3
    //   29: bipush #32
    //   31: newarray int
    //   33: dup
    //   34: iconst_0
    //   35: ldc 876216579
    //   37: iastore
    //   38: dup
    //   39: iconst_1
    //   40: ldc 455999525
    //   42: iastore
    //   43: dup
    //   44: iconst_2
    //   45: ldc 1043334948
    //   47: iastore
    //   48: dup
    //   49: iconst_3
    //   50: ldc 439222784
    //   52: iastore
    //   53: dup
    //   54: iconst_4
    //   55: ldc 372376604
    //   57: iastore
    //   58: dup
    //   59: iconst_5
    //   60: ldc 707731490
    //   62: iastore
    //   63: dup
    //   64: bipush #6
    //   66: ldc 389426184
    //   68: iastore
    //   69: dup
    //   70: bipush #7
    //   72: ldc 973875457
    //   74: iastore
    //   75: dup
    //   76: bipush #8
    //   78: ldc 389160971
    //   80: iastore
    //   81: dup
    //   82: bipush #9
    //   84: ldc 907870729
    //   86: iastore
    //   87: dup
    //   88: bipush #10
    //   90: ldc 121057538
    //   92: iastore
    //   93: dup
    //   94: bipush #11
    //   96: ldc 840500228
    //   98: iastore
    //   99: dup
    //   100: bipush #12
    //   102: ldc 254150144
    //   104: iastore
    //   105: dup
    //   106: bipush #13
    //   108: ldc 924386310
    //   110: iastore
    //   111: dup
    //   112: bipush #14
    //   114: ldc 187632156
    //   116: iastore
    //   117: dup
    //   118: bipush #15
    //   120: ldc 874189824
    //   122: iastore
    //   123: dup
    //   124: bipush #16
    //   126: ldc 655302664
    //   128: iastore
    //   129: dup
    //   130: bipush #17
    //   132: ldc 890966315
    //   134: iastore
    //   135: dup
    //   136: bipush #18
    //   138: ldc 722417666
    //   140: iastore
    //   141: dup
    //   142: bipush #19
    //   144: ldc 1026621720
    //   146: iastore
    //   147: dup
    //   148: bipush #20
    //   150: ldc 957157408
    //   152: iastore
    //   153: dup
    //   154: bipush #21
    //   156: ldc 892536332
    //   158: iastore
    //   159: dup
    //   160: bipush #22
    //   162: ldc 689771012
    //   164: iastore
    //   165: dup
    //   166: bipush #23
    //   168: ldc 221709344
    //   170: iastore
    //   171: dup
    //   172: bipush #24
    //   174: ldc 940377620
    //   176: iastore
    //   177: dup
    //   178: bipush #25
    //   180: ldc 255209728
    //   182: iastore
    //   183: dup
    //   184: bipush #26
    //   186: ldc 1010368540
    //   188: iastore
    //   189: dup
    //   190: bipush #27
    //   192: ldc 220604441
    //   194: iastore
    //   195: dup
    //   196: bipush #28
    //   198: ldc 1008414755
    //   200: iastore
    //   201: dup
    //   202: bipush #29
    //   204: ldc 187049985
    //   206: iastore
    //   207: dup
    //   208: bipush #30
    //   210: ldc 943331329
    //   212: iastore
    //   213: dup
    //   214: bipush #31
    //   216: ldc 170788368
    //   218: iastore
    //   219: astore #5
    //   221: bipush #64
    //   223: newarray int
    //   225: dup
    //   226: iconst_0
    //   227: ldc 16843776
    //   229: iastore
    //   230: dup
    //   231: iconst_1
    //   232: iconst_0
    //   233: iastore
    //   234: dup
    //   235: iconst_2
    //   236: ldc 65536
    //   238: iastore
    //   239: dup
    //   240: iconst_3
    //   241: ldc 16843780
    //   243: iastore
    //   244: dup
    //   245: iconst_4
    //   246: ldc 16842756
    //   248: iastore
    //   249: dup
    //   250: iconst_5
    //   251: ldc 66564
    //   253: iastore
    //   254: dup
    //   255: bipush #6
    //   257: iconst_4
    //   258: iastore
    //   259: dup
    //   260: bipush #7
    //   262: ldc 65536
    //   264: iastore
    //   265: dup
    //   266: bipush #8
    //   268: sipush #1024
    //   271: iastore
    //   272: dup
    //   273: bipush #9
    //   275: ldc 16843776
    //   277: iastore
    //   278: dup
    //   279: bipush #10
    //   281: ldc 16843780
    //   283: iastore
    //   284: dup
    //   285: bipush #11
    //   287: sipush #1024
    //   290: iastore
    //   291: dup
    //   292: bipush #12
    //   294: ldc 16778244
    //   296: iastore
    //   297: dup
    //   298: bipush #13
    //   300: ldc 16842756
    //   302: iastore
    //   303: dup
    //   304: bipush #14
    //   306: ldc 16777216
    //   308: iastore
    //   309: dup
    //   310: bipush #15
    //   312: iconst_4
    //   313: iastore
    //   314: dup
    //   315: bipush #16
    //   317: sipush #1028
    //   320: iastore
    //   321: dup
    //   322: bipush #17
    //   324: ldc 16778240
    //   326: iastore
    //   327: dup
    //   328: bipush #18
    //   330: ldc 16778240
    //   332: iastore
    //   333: dup
    //   334: bipush #19
    //   336: ldc 66560
    //   338: iastore
    //   339: dup
    //   340: bipush #20
    //   342: ldc 66560
    //   344: iastore
    //   345: dup
    //   346: bipush #21
    //   348: ldc 16842752
    //   350: iastore
    //   351: dup
    //   352: bipush #22
    //   354: ldc 16842752
    //   356: iastore
    //   357: dup
    //   358: bipush #23
    //   360: ldc 16778244
    //   362: iastore
    //   363: dup
    //   364: bipush #24
    //   366: ldc 65540
    //   368: iastore
    //   369: dup
    //   370: bipush #25
    //   372: ldc 16777220
    //   374: iastore
    //   375: dup
    //   376: bipush #26
    //   378: ldc 16777220
    //   380: iastore
    //   381: dup
    //   382: bipush #27
    //   384: ldc 65540
    //   386: iastore
    //   387: dup
    //   388: bipush #28
    //   390: iconst_0
    //   391: iastore
    //   392: dup
    //   393: bipush #29
    //   395: sipush #1028
    //   398: iastore
    //   399: dup
    //   400: bipush #30
    //   402: ldc 66564
    //   404: iastore
    //   405: dup
    //   406: bipush #31
    //   408: ldc 16777216
    //   410: iastore
    //   411: dup
    //   412: bipush #32
    //   414: ldc 65536
    //   416: iastore
    //   417: dup
    //   418: bipush #33
    //   420: ldc 16843780
    //   422: iastore
    //   423: dup
    //   424: bipush #34
    //   426: iconst_4
    //   427: iastore
    //   428: dup
    //   429: bipush #35
    //   431: ldc 16842752
    //   433: iastore
    //   434: dup
    //   435: bipush #36
    //   437: ldc 16843776
    //   439: iastore
    //   440: dup
    //   441: bipush #37
    //   443: ldc 16777216
    //   445: iastore
    //   446: dup
    //   447: bipush #38
    //   449: ldc 16777216
    //   451: iastore
    //   452: dup
    //   453: bipush #39
    //   455: sipush #1024
    //   458: iastore
    //   459: dup
    //   460: bipush #40
    //   462: ldc 16842756
    //   464: iastore
    //   465: dup
    //   466: bipush #41
    //   468: ldc 65536
    //   470: iastore
    //   471: dup
    //   472: bipush #42
    //   474: ldc 66560
    //   476: iastore
    //   477: dup
    //   478: bipush #43
    //   480: ldc 16777220
    //   482: iastore
    //   483: dup
    //   484: bipush #44
    //   486: sipush #1024
    //   489: iastore
    //   490: dup
    //   491: bipush #45
    //   493: iconst_4
    //   494: iastore
    //   495: dup
    //   496: bipush #46
    //   498: ldc 16778244
    //   500: iastore
    //   501: dup
    //   502: bipush #47
    //   504: ldc 66564
    //   506: iastore
    //   507: dup
    //   508: bipush #48
    //   510: ldc 16843780
    //   512: iastore
    //   513: dup
    //   514: bipush #49
    //   516: ldc 65540
    //   518: iastore
    //   519: dup
    //   520: bipush #50
    //   522: ldc 16842752
    //   524: iastore
    //   525: dup
    //   526: bipush #51
    //   528: ldc 16778244
    //   530: iastore
    //   531: dup
    //   532: bipush #52
    //   534: ldc 16777220
    //   536: iastore
    //   537: dup
    //   538: bipush #53
    //   540: sipush #1028
    //   543: iastore
    //   544: dup
    //   545: bipush #54
    //   547: ldc 66564
    //   549: iastore
    //   550: dup
    //   551: bipush #55
    //   553: ldc 16843776
    //   555: iastore
    //   556: dup
    //   557: bipush #56
    //   559: sipush #1028
    //   562: iastore
    //   563: dup
    //   564: bipush #57
    //   566: ldc 16778240
    //   568: iastore
    //   569: dup
    //   570: bipush #58
    //   572: ldc 16778240
    //   574: iastore
    //   575: dup
    //   576: bipush #59
    //   578: iconst_0
    //   579: iastore
    //   580: dup
    //   581: bipush #60
    //   583: ldc 65540
    //   585: iastore
    //   586: dup
    //   587: bipush #61
    //   589: ldc 66560
    //   591: iastore
    //   592: dup
    //   593: bipush #62
    //   595: iconst_0
    //   596: iastore
    //   597: dup
    //   598: bipush #63
    //   600: ldc 16842756
    //   602: iastore
    //   603: astore #6
    //   605: bipush #64
    //   607: newarray int
    //   609: dup
    //   610: iconst_0
    //   611: ldc -2146402272
    //   613: iastore
    //   614: dup
    //   615: iconst_1
    //   616: ldc -2147450880
    //   618: iastore
    //   619: dup
    //   620: iconst_2
    //   621: ldc 32768
    //   623: iastore
    //   624: dup
    //   625: iconst_3
    //   626: ldc 1081376
    //   628: iastore
    //   629: dup
    //   630: iconst_4
    //   631: ldc 1048576
    //   633: iastore
    //   634: dup
    //   635: iconst_5
    //   636: bipush #32
    //   638: iastore
    //   639: dup
    //   640: bipush #6
    //   642: ldc -2146435040
    //   644: iastore
    //   645: dup
    //   646: bipush #7
    //   648: ldc -2147450848
    //   650: iastore
    //   651: dup
    //   652: bipush #8
    //   654: ldc -2147483616
    //   656: iastore
    //   657: dup
    //   658: bipush #9
    //   660: ldc -2146402272
    //   662: iastore
    //   663: dup
    //   664: bipush #10
    //   666: ldc -2146402304
    //   668: iastore
    //   669: dup
    //   670: bipush #11
    //   672: ldc -2147483648
    //   674: iastore
    //   675: dup
    //   676: bipush #12
    //   678: ldc -2147450880
    //   680: iastore
    //   681: dup
    //   682: bipush #13
    //   684: ldc 1048576
    //   686: iastore
    //   687: dup
    //   688: bipush #14
    //   690: bipush #32
    //   692: iastore
    //   693: dup
    //   694: bipush #15
    //   696: ldc -2146435040
    //   698: iastore
    //   699: dup
    //   700: bipush #16
    //   702: ldc 1081344
    //   704: iastore
    //   705: dup
    //   706: bipush #17
    //   708: ldc 1048608
    //   710: iastore
    //   711: dup
    //   712: bipush #18
    //   714: ldc -2147450848
    //   716: iastore
    //   717: dup
    //   718: bipush #19
    //   720: iconst_0
    //   721: iastore
    //   722: dup
    //   723: bipush #20
    //   725: ldc -2147483648
    //   727: iastore
    //   728: dup
    //   729: bipush #21
    //   731: ldc 32768
    //   733: iastore
    //   734: dup
    //   735: bipush #22
    //   737: ldc 1081376
    //   739: iastore
    //   740: dup
    //   741: bipush #23
    //   743: ldc -2146435072
    //   745: iastore
    //   746: dup
    //   747: bipush #24
    //   749: ldc 1048608
    //   751: iastore
    //   752: dup
    //   753: bipush #25
    //   755: ldc -2147483616
    //   757: iastore
    //   758: dup
    //   759: bipush #26
    //   761: iconst_0
    //   762: iastore
    //   763: dup
    //   764: bipush #27
    //   766: ldc 1081344
    //   768: iastore
    //   769: dup
    //   770: bipush #28
    //   772: ldc 32800
    //   774: iastore
    //   775: dup
    //   776: bipush #29
    //   778: ldc -2146402304
    //   780: iastore
    //   781: dup
    //   782: bipush #30
    //   784: ldc -2146435072
    //   786: iastore
    //   787: dup
    //   788: bipush #31
    //   790: ldc 32800
    //   792: iastore
    //   793: dup
    //   794: bipush #32
    //   796: iconst_0
    //   797: iastore
    //   798: dup
    //   799: bipush #33
    //   801: ldc 1081376
    //   803: iastore
    //   804: dup
    //   805: bipush #34
    //   807: ldc -2146435040
    //   809: iastore
    //   810: dup
    //   811: bipush #35
    //   813: ldc 1048576
    //   815: iastore
    //   816: dup
    //   817: bipush #36
    //   819: ldc -2147450848
    //   821: iastore
    //   822: dup
    //   823: bipush #37
    //   825: ldc -2146435072
    //   827: iastore
    //   828: dup
    //   829: bipush #38
    //   831: ldc -2146402304
    //   833: iastore
    //   834: dup
    //   835: bipush #39
    //   837: ldc 32768
    //   839: iastore
    //   840: dup
    //   841: bipush #40
    //   843: ldc -2146435072
    //   845: iastore
    //   846: dup
    //   847: bipush #41
    //   849: ldc -2147450880
    //   851: iastore
    //   852: dup
    //   853: bipush #42
    //   855: bipush #32
    //   857: iastore
    //   858: dup
    //   859: bipush #43
    //   861: ldc -2146402272
    //   863: iastore
    //   864: dup
    //   865: bipush #44
    //   867: ldc 1081376
    //   869: iastore
    //   870: dup
    //   871: bipush #45
    //   873: bipush #32
    //   875: iastore
    //   876: dup
    //   877: bipush #46
    //   879: ldc 32768
    //   881: iastore
    //   882: dup
    //   883: bipush #47
    //   885: ldc -2147483648
    //   887: iastore
    //   888: dup
    //   889: bipush #48
    //   891: ldc 32800
    //   893: iastore
    //   894: dup
    //   895: bipush #49
    //   897: ldc -2146402304
    //   899: iastore
    //   900: dup
    //   901: bipush #50
    //   903: ldc 1048576
    //   905: iastore
    //   906: dup
    //   907: bipush #51
    //   909: ldc -2147483616
    //   911: iastore
    //   912: dup
    //   913: bipush #52
    //   915: ldc 1048608
    //   917: iastore
    //   918: dup
    //   919: bipush #53
    //   921: ldc -2147450848
    //   923: iastore
    //   924: dup
    //   925: bipush #54
    //   927: ldc -2147483616
    //   929: iastore
    //   930: dup
    //   931: bipush #55
    //   933: ldc 1048608
    //   935: iastore
    //   936: dup
    //   937: bipush #56
    //   939: ldc 1081344
    //   941: iastore
    //   942: dup
    //   943: bipush #57
    //   945: iconst_0
    //   946: iastore
    //   947: dup
    //   948: bipush #58
    //   950: ldc -2147450880
    //   952: iastore
    //   953: dup
    //   954: bipush #59
    //   956: ldc 32800
    //   958: iastore
    //   959: dup
    //   960: bipush #60
    //   962: ldc -2147483648
    //   964: iastore
    //   965: dup
    //   966: bipush #61
    //   968: ldc -2146435040
    //   970: iastore
    //   971: dup
    //   972: bipush #62
    //   974: ldc -2146402272
    //   976: iastore
    //   977: dup
    //   978: bipush #63
    //   980: ldc 1081344
    //   982: iastore
    //   983: astore #7
    //   985: bipush #64
    //   987: newarray int
    //   989: dup
    //   990: iconst_0
    //   991: sipush #520
    //   994: iastore
    //   995: dup
    //   996: iconst_1
    //   997: ldc 134349312
    //   999: iastore
    //   1000: dup
    //   1001: iconst_2
    //   1002: iconst_0
    //   1003: iastore
    //   1004: dup
    //   1005: iconst_3
    //   1006: ldc 134348808
    //   1008: iastore
    //   1009: dup
    //   1010: iconst_4
    //   1011: ldc 134218240
    //   1013: iastore
    //   1014: dup
    //   1015: iconst_5
    //   1016: iconst_0
    //   1017: iastore
    //   1018: dup
    //   1019: bipush #6
    //   1021: ldc 131592
    //   1023: iastore
    //   1024: dup
    //   1025: bipush #7
    //   1027: ldc 134218240
    //   1029: iastore
    //   1030: dup
    //   1031: bipush #8
    //   1033: ldc 131080
    //   1035: iastore
    //   1036: dup
    //   1037: bipush #9
    //   1039: ldc 134217736
    //   1041: iastore
    //   1042: dup
    //   1043: bipush #10
    //   1045: ldc 134217736
    //   1047: iastore
    //   1048: dup
    //   1049: bipush #11
    //   1051: ldc 131072
    //   1053: iastore
    //   1054: dup
    //   1055: bipush #12
    //   1057: ldc 134349320
    //   1059: iastore
    //   1060: dup
    //   1061: bipush #13
    //   1063: ldc 131080
    //   1065: iastore
    //   1066: dup
    //   1067: bipush #14
    //   1069: ldc 134348800
    //   1071: iastore
    //   1072: dup
    //   1073: bipush #15
    //   1075: sipush #520
    //   1078: iastore
    //   1079: dup
    //   1080: bipush #16
    //   1082: ldc 134217728
    //   1084: iastore
    //   1085: dup
    //   1086: bipush #17
    //   1088: bipush #8
    //   1090: iastore
    //   1091: dup
    //   1092: bipush #18
    //   1094: ldc 134349312
    //   1096: iastore
    //   1097: dup
    //   1098: bipush #19
    //   1100: sipush #512
    //   1103: iastore
    //   1104: dup
    //   1105: bipush #20
    //   1107: ldc 131584
    //   1109: iastore
    //   1110: dup
    //   1111: bipush #21
    //   1113: ldc 134348800
    //   1115: iastore
    //   1116: dup
    //   1117: bipush #22
    //   1119: ldc 134348808
    //   1121: iastore
    //   1122: dup
    //   1123: bipush #23
    //   1125: ldc 131592
    //   1127: iastore
    //   1128: dup
    //   1129: bipush #24
    //   1131: ldc 134218248
    //   1133: iastore
    //   1134: dup
    //   1135: bipush #25
    //   1137: ldc 131584
    //   1139: iastore
    //   1140: dup
    //   1141: bipush #26
    //   1143: ldc 131072
    //   1145: iastore
    //   1146: dup
    //   1147: bipush #27
    //   1149: ldc 134218248
    //   1151: iastore
    //   1152: dup
    //   1153: bipush #28
    //   1155: bipush #8
    //   1157: iastore
    //   1158: dup
    //   1159: bipush #29
    //   1161: ldc 134349320
    //   1163: iastore
    //   1164: dup
    //   1165: bipush #30
    //   1167: sipush #512
    //   1170: iastore
    //   1171: dup
    //   1172: bipush #31
    //   1174: ldc 134217728
    //   1176: iastore
    //   1177: dup
    //   1178: bipush #32
    //   1180: ldc 134349312
    //   1182: iastore
    //   1183: dup
    //   1184: bipush #33
    //   1186: ldc 134217728
    //   1188: iastore
    //   1189: dup
    //   1190: bipush #34
    //   1192: ldc 131080
    //   1194: iastore
    //   1195: dup
    //   1196: bipush #35
    //   1198: sipush #520
    //   1201: iastore
    //   1202: dup
    //   1203: bipush #36
    //   1205: ldc 131072
    //   1207: iastore
    //   1208: dup
    //   1209: bipush #37
    //   1211: ldc 134349312
    //   1213: iastore
    //   1214: dup
    //   1215: bipush #38
    //   1217: ldc 134218240
    //   1219: iastore
    //   1220: dup
    //   1221: bipush #39
    //   1223: iconst_0
    //   1224: iastore
    //   1225: dup
    //   1226: bipush #40
    //   1228: sipush #512
    //   1231: iastore
    //   1232: dup
    //   1233: bipush #41
    //   1235: ldc 131080
    //   1237: iastore
    //   1238: dup
    //   1239: bipush #42
    //   1241: ldc 134349320
    //   1243: iastore
    //   1244: dup
    //   1245: bipush #43
    //   1247: ldc 134218240
    //   1249: iastore
    //   1250: dup
    //   1251: bipush #44
    //   1253: ldc 134217736
    //   1255: iastore
    //   1256: dup
    //   1257: bipush #45
    //   1259: sipush #512
    //   1262: iastore
    //   1263: dup
    //   1264: bipush #46
    //   1266: iconst_0
    //   1267: iastore
    //   1268: dup
    //   1269: bipush #47
    //   1271: ldc 134348808
    //   1273: iastore
    //   1274: dup
    //   1275: bipush #48
    //   1277: ldc 134218248
    //   1279: iastore
    //   1280: dup
    //   1281: bipush #49
    //   1283: ldc 131072
    //   1285: iastore
    //   1286: dup
    //   1287: bipush #50
    //   1289: ldc 134217728
    //   1291: iastore
    //   1292: dup
    //   1293: bipush #51
    //   1295: ldc 134349320
    //   1297: iastore
    //   1298: dup
    //   1299: bipush #52
    //   1301: bipush #8
    //   1303: iastore
    //   1304: dup
    //   1305: bipush #53
    //   1307: ldc 131592
    //   1309: iastore
    //   1310: dup
    //   1311: bipush #54
    //   1313: ldc 131584
    //   1315: iastore
    //   1316: dup
    //   1317: bipush #55
    //   1319: ldc 134217736
    //   1321: iastore
    //   1322: dup
    //   1323: bipush #56
    //   1325: ldc 134348800
    //   1327: iastore
    //   1328: dup
    //   1329: bipush #57
    //   1331: ldc 134218248
    //   1333: iastore
    //   1334: dup
    //   1335: bipush #58
    //   1337: sipush #520
    //   1340: iastore
    //   1341: dup
    //   1342: bipush #59
    //   1344: ldc 134348800
    //   1346: iastore
    //   1347: dup
    //   1348: bipush #60
    //   1350: ldc 131592
    //   1352: iastore
    //   1353: dup
    //   1354: bipush #61
    //   1356: bipush #8
    //   1358: iastore
    //   1359: dup
    //   1360: bipush #62
    //   1362: ldc 134348808
    //   1364: iastore
    //   1365: dup
    //   1366: bipush #63
    //   1368: ldc 131584
    //   1370: iastore
    //   1371: astore #8
    //   1373: bipush #64
    //   1375: newarray int
    //   1377: dup
    //   1378: iconst_0
    //   1379: ldc 8396801
    //   1381: iastore
    //   1382: dup
    //   1383: iconst_1
    //   1384: sipush #8321
    //   1387: iastore
    //   1388: dup
    //   1389: iconst_2
    //   1390: sipush #8321
    //   1393: iastore
    //   1394: dup
    //   1395: iconst_3
    //   1396: sipush #128
    //   1399: iastore
    //   1400: dup
    //   1401: iconst_4
    //   1402: ldc 8396928
    //   1404: iastore
    //   1405: dup
    //   1406: iconst_5
    //   1407: ldc 8388737
    //   1409: iastore
    //   1410: dup
    //   1411: bipush #6
    //   1413: ldc 8388609
    //   1415: iastore
    //   1416: dup
    //   1417: bipush #7
    //   1419: sipush #8193
    //   1422: iastore
    //   1423: dup
    //   1424: bipush #8
    //   1426: iconst_0
    //   1427: iastore
    //   1428: dup
    //   1429: bipush #9
    //   1431: ldc 8396800
    //   1433: iastore
    //   1434: dup
    //   1435: bipush #10
    //   1437: ldc 8396800
    //   1439: iastore
    //   1440: dup
    //   1441: bipush #11
    //   1443: ldc 8396929
    //   1445: iastore
    //   1446: dup
    //   1447: bipush #12
    //   1449: sipush #129
    //   1452: iastore
    //   1453: dup
    //   1454: bipush #13
    //   1456: iconst_0
    //   1457: iastore
    //   1458: dup
    //   1459: bipush #14
    //   1461: ldc 8388736
    //   1463: iastore
    //   1464: dup
    //   1465: bipush #15
    //   1467: ldc 8388609
    //   1469: iastore
    //   1470: dup
    //   1471: bipush #16
    //   1473: iconst_1
    //   1474: iastore
    //   1475: dup
    //   1476: bipush #17
    //   1478: sipush #8192
    //   1481: iastore
    //   1482: dup
    //   1483: bipush #18
    //   1485: ldc 8388608
    //   1487: iastore
    //   1488: dup
    //   1489: bipush #19
    //   1491: ldc 8396801
    //   1493: iastore
    //   1494: dup
    //   1495: bipush #20
    //   1497: sipush #128
    //   1500: iastore
    //   1501: dup
    //   1502: bipush #21
    //   1504: ldc 8388608
    //   1506: iastore
    //   1507: dup
    //   1508: bipush #22
    //   1510: sipush #8193
    //   1513: iastore
    //   1514: dup
    //   1515: bipush #23
    //   1517: sipush #8320
    //   1520: iastore
    //   1521: dup
    //   1522: bipush #24
    //   1524: ldc 8388737
    //   1526: iastore
    //   1527: dup
    //   1528: bipush #25
    //   1530: iconst_1
    //   1531: iastore
    //   1532: dup
    //   1533: bipush #26
    //   1535: sipush #8320
    //   1538: iastore
    //   1539: dup
    //   1540: bipush #27
    //   1542: ldc 8388736
    //   1544: iastore
    //   1545: dup
    //   1546: bipush #28
    //   1548: sipush #8192
    //   1551: iastore
    //   1552: dup
    //   1553: bipush #29
    //   1555: ldc 8396928
    //   1557: iastore
    //   1558: dup
    //   1559: bipush #30
    //   1561: ldc 8396929
    //   1563: iastore
    //   1564: dup
    //   1565: bipush #31
    //   1567: sipush #129
    //   1570: iastore
    //   1571: dup
    //   1572: bipush #32
    //   1574: ldc 8388736
    //   1576: iastore
    //   1577: dup
    //   1578: bipush #33
    //   1580: ldc 8388609
    //   1582: iastore
    //   1583: dup
    //   1584: bipush #34
    //   1586: ldc 8396800
    //   1588: iastore
    //   1589: dup
    //   1590: bipush #35
    //   1592: ldc 8396929
    //   1594: iastore
    //   1595: dup
    //   1596: bipush #36
    //   1598: sipush #129
    //   1601: iastore
    //   1602: dup
    //   1603: bipush #37
    //   1605: iconst_0
    //   1606: iastore
    //   1607: dup
    //   1608: bipush #38
    //   1610: iconst_0
    //   1611: iastore
    //   1612: dup
    //   1613: bipush #39
    //   1615: ldc 8396800
    //   1617: iastore
    //   1618: dup
    //   1619: bipush #40
    //   1621: sipush #8320
    //   1624: iastore
    //   1625: dup
    //   1626: bipush #41
    //   1628: ldc 8388736
    //   1630: iastore
    //   1631: dup
    //   1632: bipush #42
    //   1634: ldc 8388737
    //   1636: iastore
    //   1637: dup
    //   1638: bipush #43
    //   1640: iconst_1
    //   1641: iastore
    //   1642: dup
    //   1643: bipush #44
    //   1645: ldc 8396801
    //   1647: iastore
    //   1648: dup
    //   1649: bipush #45
    //   1651: sipush #8321
    //   1654: iastore
    //   1655: dup
    //   1656: bipush #46
    //   1658: sipush #8321
    //   1661: iastore
    //   1662: dup
    //   1663: bipush #47
    //   1665: sipush #128
    //   1668: iastore
    //   1669: dup
    //   1670: bipush #48
    //   1672: ldc 8396929
    //   1674: iastore
    //   1675: dup
    //   1676: bipush #49
    //   1678: sipush #129
    //   1681: iastore
    //   1682: dup
    //   1683: bipush #50
    //   1685: iconst_1
    //   1686: iastore
    //   1687: dup
    //   1688: bipush #51
    //   1690: sipush #8192
    //   1693: iastore
    //   1694: dup
    //   1695: bipush #52
    //   1697: ldc 8388609
    //   1699: iastore
    //   1700: dup
    //   1701: bipush #53
    //   1703: sipush #8193
    //   1706: iastore
    //   1707: dup
    //   1708: bipush #54
    //   1710: ldc 8396928
    //   1712: iastore
    //   1713: dup
    //   1714: bipush #55
    //   1716: ldc 8388737
    //   1718: iastore
    //   1719: dup
    //   1720: bipush #56
    //   1722: sipush #8193
    //   1725: iastore
    //   1726: dup
    //   1727: bipush #57
    //   1729: sipush #8320
    //   1732: iastore
    //   1733: dup
    //   1734: bipush #58
    //   1736: ldc 8388608
    //   1738: iastore
    //   1739: dup
    //   1740: bipush #59
    //   1742: ldc 8396801
    //   1744: iastore
    //   1745: dup
    //   1746: bipush #60
    //   1748: sipush #128
    //   1751: iastore
    //   1752: dup
    //   1753: bipush #61
    //   1755: ldc 8388608
    //   1757: iastore
    //   1758: dup
    //   1759: bipush #62
    //   1761: sipush #8192
    //   1764: iastore
    //   1765: dup
    //   1766: bipush #63
    //   1768: ldc 8396928
    //   1770: iastore
    //   1771: astore #9
    //   1773: bipush #64
    //   1775: newarray int
    //   1777: dup
    //   1778: iconst_0
    //   1779: sipush #256
    //   1782: iastore
    //   1783: dup
    //   1784: iconst_1
    //   1785: ldc 34078976
    //   1787: iastore
    //   1788: dup
    //   1789: iconst_2
    //   1790: ldc 34078720
    //   1792: iastore
    //   1793: dup
    //   1794: iconst_3
    //   1795: ldc 1107296512
    //   1797: iastore
    //   1798: dup
    //   1799: iconst_4
    //   1800: ldc 524288
    //   1802: iastore
    //   1803: dup
    //   1804: iconst_5
    //   1805: sipush #256
    //   1808: iastore
    //   1809: dup
    //   1810: bipush #6
    //   1812: ldc 1073741824
    //   1814: iastore
    //   1815: dup
    //   1816: bipush #7
    //   1818: ldc 34078720
    //   1820: iastore
    //   1821: dup
    //   1822: bipush #8
    //   1824: ldc 1074266368
    //   1826: iastore
    //   1827: dup
    //   1828: bipush #9
    //   1830: ldc 524288
    //   1832: iastore
    //   1833: dup
    //   1834: bipush #10
    //   1836: ldc 33554688
    //   1838: iastore
    //   1839: dup
    //   1840: bipush #11
    //   1842: ldc 1074266368
    //   1844: iastore
    //   1845: dup
    //   1846: bipush #12
    //   1848: ldc 1107296512
    //   1850: iastore
    //   1851: dup
    //   1852: bipush #13
    //   1854: ldc 1107820544
    //   1856: iastore
    //   1857: dup
    //   1858: bipush #14
    //   1860: ldc 524544
    //   1862: iastore
    //   1863: dup
    //   1864: bipush #15
    //   1866: ldc 1073741824
    //   1868: iastore
    //   1869: dup
    //   1870: bipush #16
    //   1872: ldc 33554432
    //   1874: iastore
    //   1875: dup
    //   1876: bipush #17
    //   1878: ldc 1074266112
    //   1880: iastore
    //   1881: dup
    //   1882: bipush #18
    //   1884: ldc 1074266112
    //   1886: iastore
    //   1887: dup
    //   1888: bipush #19
    //   1890: iconst_0
    //   1891: iastore
    //   1892: dup
    //   1893: bipush #20
    //   1895: ldc 1073742080
    //   1897: iastore
    //   1898: dup
    //   1899: bipush #21
    //   1901: ldc 1107820800
    //   1903: iastore
    //   1904: dup
    //   1905: bipush #22
    //   1907: ldc 1107820800
    //   1909: iastore
    //   1910: dup
    //   1911: bipush #23
    //   1913: ldc 33554688
    //   1915: iastore
    //   1916: dup
    //   1917: bipush #24
    //   1919: ldc 1107820544
    //   1921: iastore
    //   1922: dup
    //   1923: bipush #25
    //   1925: ldc 1073742080
    //   1927: iastore
    //   1928: dup
    //   1929: bipush #26
    //   1931: iconst_0
    //   1932: iastore
    //   1933: dup
    //   1934: bipush #27
    //   1936: ldc 1107296256
    //   1938: iastore
    //   1939: dup
    //   1940: bipush #28
    //   1942: ldc 34078976
    //   1944: iastore
    //   1945: dup
    //   1946: bipush #29
    //   1948: ldc 33554432
    //   1950: iastore
    //   1951: dup
    //   1952: bipush #30
    //   1954: ldc 1107296256
    //   1956: iastore
    //   1957: dup
    //   1958: bipush #31
    //   1960: ldc 524544
    //   1962: iastore
    //   1963: dup
    //   1964: bipush #32
    //   1966: ldc 524288
    //   1968: iastore
    //   1969: dup
    //   1970: bipush #33
    //   1972: ldc 1107296512
    //   1974: iastore
    //   1975: dup
    //   1976: bipush #34
    //   1978: sipush #256
    //   1981: iastore
    //   1982: dup
    //   1983: bipush #35
    //   1985: ldc 33554432
    //   1987: iastore
    //   1988: dup
    //   1989: bipush #36
    //   1991: ldc 1073741824
    //   1993: iastore
    //   1994: dup
    //   1995: bipush #37
    //   1997: ldc 34078720
    //   1999: iastore
    //   2000: dup
    //   2001: bipush #38
    //   2003: ldc 1107296512
    //   2005: iastore
    //   2006: dup
    //   2007: bipush #39
    //   2009: ldc 1074266368
    //   2011: iastore
    //   2012: dup
    //   2013: bipush #40
    //   2015: ldc 33554688
    //   2017: iastore
    //   2018: dup
    //   2019: bipush #41
    //   2021: ldc 1073741824
    //   2023: iastore
    //   2024: dup
    //   2025: bipush #42
    //   2027: ldc 1107820544
    //   2029: iastore
    //   2030: dup
    //   2031: bipush #43
    //   2033: ldc 34078976
    //   2035: iastore
    //   2036: dup
    //   2037: bipush #44
    //   2039: ldc 1074266368
    //   2041: iastore
    //   2042: dup
    //   2043: bipush #45
    //   2045: sipush #256
    //   2048: iastore
    //   2049: dup
    //   2050: bipush #46
    //   2052: ldc 33554432
    //   2054: iastore
    //   2055: dup
    //   2056: bipush #47
    //   2058: ldc 1107820544
    //   2060: iastore
    //   2061: dup
    //   2062: bipush #48
    //   2064: ldc 1107820800
    //   2066: iastore
    //   2067: dup
    //   2068: bipush #49
    //   2070: ldc 524544
    //   2072: iastore
    //   2073: dup
    //   2074: bipush #50
    //   2076: ldc 1107296256
    //   2078: iastore
    //   2079: dup
    //   2080: bipush #51
    //   2082: ldc 1107820800
    //   2084: iastore
    //   2085: dup
    //   2086: bipush #52
    //   2088: ldc 34078720
    //   2090: iastore
    //   2091: dup
    //   2092: bipush #53
    //   2094: iconst_0
    //   2095: iastore
    //   2096: dup
    //   2097: bipush #54
    //   2099: ldc 1074266112
    //   2101: iastore
    //   2102: dup
    //   2103: bipush #55
    //   2105: ldc 1107296256
    //   2107: iastore
    //   2108: dup
    //   2109: bipush #56
    //   2111: ldc 524544
    //   2113: iastore
    //   2114: dup
    //   2115: bipush #57
    //   2117: ldc 33554688
    //   2119: iastore
    //   2120: dup
    //   2121: bipush #58
    //   2123: ldc 1073742080
    //   2125: iastore
    //   2126: dup
    //   2127: bipush #59
    //   2129: ldc 524288
    //   2131: iastore
    //   2132: dup
    //   2133: bipush #60
    //   2135: iconst_0
    //   2136: iastore
    //   2137: dup
    //   2138: bipush #61
    //   2140: ldc 1074266112
    //   2142: iastore
    //   2143: dup
    //   2144: bipush #62
    //   2146: ldc 34078976
    //   2148: iastore
    //   2149: dup
    //   2150: bipush #63
    //   2152: ldc 1073742080
    //   2154: iastore
    //   2155: astore #10
    //   2157: bipush #64
    //   2159: newarray int
    //   2161: dup
    //   2162: iconst_0
    //   2163: ldc 536870928
    //   2165: iastore
    //   2166: dup
    //   2167: iconst_1
    //   2168: ldc 541065216
    //   2170: iastore
    //   2171: dup
    //   2172: iconst_2
    //   2173: sipush #16384
    //   2176: iastore
    //   2177: dup
    //   2178: iconst_3
    //   2179: ldc 541081616
    //   2181: iastore
    //   2182: dup
    //   2183: iconst_4
    //   2184: ldc 541065216
    //   2186: iastore
    //   2187: dup
    //   2188: iconst_5
    //   2189: bipush #16
    //   2191: iastore
    //   2192: dup
    //   2193: bipush #6
    //   2195: ldc 541081616
    //   2197: iastore
    //   2198: dup
    //   2199: bipush #7
    //   2201: ldc 4194304
    //   2203: iastore
    //   2204: dup
    //   2205: bipush #8
    //   2207: ldc 536887296
    //   2209: iastore
    //   2210: dup
    //   2211: bipush #9
    //   2213: ldc 4210704
    //   2215: iastore
    //   2216: dup
    //   2217: bipush #10
    //   2219: ldc 4194304
    //   2221: iastore
    //   2222: dup
    //   2223: bipush #11
    //   2225: ldc 536870928
    //   2227: iastore
    //   2228: dup
    //   2229: bipush #12
    //   2231: ldc 4194320
    //   2233: iastore
    //   2234: dup
    //   2235: bipush #13
    //   2237: ldc 536887296
    //   2239: iastore
    //   2240: dup
    //   2241: bipush #14
    //   2243: ldc 536870912
    //   2245: iastore
    //   2246: dup
    //   2247: bipush #15
    //   2249: sipush #16400
    //   2252: iastore
    //   2253: dup
    //   2254: bipush #16
    //   2256: iconst_0
    //   2257: iastore
    //   2258: dup
    //   2259: bipush #17
    //   2261: ldc 4194320
    //   2263: iastore
    //   2264: dup
    //   2265: bipush #18
    //   2267: ldc 536887312
    //   2269: iastore
    //   2270: dup
    //   2271: bipush #19
    //   2273: sipush #16384
    //   2276: iastore
    //   2277: dup
    //   2278: bipush #20
    //   2280: ldc 4210688
    //   2282: iastore
    //   2283: dup
    //   2284: bipush #21
    //   2286: ldc 536887312
    //   2288: iastore
    //   2289: dup
    //   2290: bipush #22
    //   2292: bipush #16
    //   2294: iastore
    //   2295: dup
    //   2296: bipush #23
    //   2298: ldc 541065232
    //   2300: iastore
    //   2301: dup
    //   2302: bipush #24
    //   2304: ldc 541065232
    //   2306: iastore
    //   2307: dup
    //   2308: bipush #25
    //   2310: iconst_0
    //   2311: iastore
    //   2312: dup
    //   2313: bipush #26
    //   2315: ldc 4210704
    //   2317: iastore
    //   2318: dup
    //   2319: bipush #27
    //   2321: ldc 541081600
    //   2323: iastore
    //   2324: dup
    //   2325: bipush #28
    //   2327: sipush #16400
    //   2330: iastore
    //   2331: dup
    //   2332: bipush #29
    //   2334: ldc 4210688
    //   2336: iastore
    //   2337: dup
    //   2338: bipush #30
    //   2340: ldc 541081600
    //   2342: iastore
    //   2343: dup
    //   2344: bipush #31
    //   2346: ldc 536870912
    //   2348: iastore
    //   2349: dup
    //   2350: bipush #32
    //   2352: ldc 536887296
    //   2354: iastore
    //   2355: dup
    //   2356: bipush #33
    //   2358: bipush #16
    //   2360: iastore
    //   2361: dup
    //   2362: bipush #34
    //   2364: ldc 541065232
    //   2366: iastore
    //   2367: dup
    //   2368: bipush #35
    //   2370: ldc 4210688
    //   2372: iastore
    //   2373: dup
    //   2374: bipush #36
    //   2376: ldc 541081616
    //   2378: iastore
    //   2379: dup
    //   2380: bipush #37
    //   2382: ldc 4194304
    //   2384: iastore
    //   2385: dup
    //   2386: bipush #38
    //   2388: sipush #16400
    //   2391: iastore
    //   2392: dup
    //   2393: bipush #39
    //   2395: ldc 536870928
    //   2397: iastore
    //   2398: dup
    //   2399: bipush #40
    //   2401: ldc 4194304
    //   2403: iastore
    //   2404: dup
    //   2405: bipush #41
    //   2407: ldc 536887296
    //   2409: iastore
    //   2410: dup
    //   2411: bipush #42
    //   2413: ldc 536870912
    //   2415: iastore
    //   2416: dup
    //   2417: bipush #43
    //   2419: sipush #16400
    //   2422: iastore
    //   2423: dup
    //   2424: bipush #44
    //   2426: ldc 536870928
    //   2428: iastore
    //   2429: dup
    //   2430: bipush #45
    //   2432: ldc 541081616
    //   2434: iastore
    //   2435: dup
    //   2436: bipush #46
    //   2438: ldc 4210688
    //   2440: iastore
    //   2441: dup
    //   2442: bipush #47
    //   2444: ldc 541065216
    //   2446: iastore
    //   2447: dup
    //   2448: bipush #48
    //   2450: ldc 4210704
    //   2452: iastore
    //   2453: dup
    //   2454: bipush #49
    //   2456: ldc 541081600
    //   2458: iastore
    //   2459: dup
    //   2460: bipush #50
    //   2462: iconst_0
    //   2463: iastore
    //   2464: dup
    //   2465: bipush #51
    //   2467: ldc 541065232
    //   2469: iastore
    //   2470: dup
    //   2471: bipush #52
    //   2473: bipush #16
    //   2475: iastore
    //   2476: dup
    //   2477: bipush #53
    //   2479: sipush #16384
    //   2482: iastore
    //   2483: dup
    //   2484: bipush #54
    //   2486: ldc 541065216
    //   2488: iastore
    //   2489: dup
    //   2490: bipush #55
    //   2492: ldc 4210704
    //   2494: iastore
    //   2495: dup
    //   2496: bipush #56
    //   2498: sipush #16384
    //   2501: iastore
    //   2502: dup
    //   2503: bipush #57
    //   2505: ldc 4194320
    //   2507: iastore
    //   2508: dup
    //   2509: bipush #58
    //   2511: ldc 536887312
    //   2513: iastore
    //   2514: dup
    //   2515: bipush #59
    //   2517: iconst_0
    //   2518: iastore
    //   2519: dup
    //   2520: bipush #60
    //   2522: ldc 541081600
    //   2524: iastore
    //   2525: dup
    //   2526: bipush #61
    //   2528: ldc 536870912
    //   2530: iastore
    //   2531: dup
    //   2532: bipush #62
    //   2534: ldc 4194320
    //   2536: iastore
    //   2537: dup
    //   2538: bipush #63
    //   2540: ldc 536887312
    //   2542: iastore
    //   2543: astore #11
    //   2545: bipush #64
    //   2547: newarray int
    //   2549: dup
    //   2550: iconst_0
    //   2551: ldc 2097152
    //   2553: iastore
    //   2554: dup
    //   2555: iconst_1
    //   2556: ldc 69206018
    //   2558: iastore
    //   2559: dup
    //   2560: iconst_2
    //   2561: ldc 67110914
    //   2563: iastore
    //   2564: dup
    //   2565: iconst_3
    //   2566: iconst_0
    //   2567: iastore
    //   2568: dup
    //   2569: iconst_4
    //   2570: sipush #2048
    //   2573: iastore
    //   2574: dup
    //   2575: iconst_5
    //   2576: ldc 67110914
    //   2578: iastore
    //   2579: dup
    //   2580: bipush #6
    //   2582: ldc 2099202
    //   2584: iastore
    //   2585: dup
    //   2586: bipush #7
    //   2588: ldc 69208064
    //   2590: iastore
    //   2591: dup
    //   2592: bipush #8
    //   2594: ldc 69208066
    //   2596: iastore
    //   2597: dup
    //   2598: bipush #9
    //   2600: ldc 2097152
    //   2602: iastore
    //   2603: dup
    //   2604: bipush #10
    //   2606: iconst_0
    //   2607: iastore
    //   2608: dup
    //   2609: bipush #11
    //   2611: ldc 67108866
    //   2613: iastore
    //   2614: dup
    //   2615: bipush #12
    //   2617: iconst_2
    //   2618: iastore
    //   2619: dup
    //   2620: bipush #13
    //   2622: ldc 67108864
    //   2624: iastore
    //   2625: dup
    //   2626: bipush #14
    //   2628: ldc 69206018
    //   2630: iastore
    //   2631: dup
    //   2632: bipush #15
    //   2634: sipush #2050
    //   2637: iastore
    //   2638: dup
    //   2639: bipush #16
    //   2641: ldc 67110912
    //   2643: iastore
    //   2644: dup
    //   2645: bipush #17
    //   2647: ldc 2099202
    //   2649: iastore
    //   2650: dup
    //   2651: bipush #18
    //   2653: ldc 2097154
    //   2655: iastore
    //   2656: dup
    //   2657: bipush #19
    //   2659: ldc 67110912
    //   2661: iastore
    //   2662: dup
    //   2663: bipush #20
    //   2665: ldc 67108866
    //   2667: iastore
    //   2668: dup
    //   2669: bipush #21
    //   2671: ldc 69206016
    //   2673: iastore
    //   2674: dup
    //   2675: bipush #22
    //   2677: ldc 69208064
    //   2679: iastore
    //   2680: dup
    //   2681: bipush #23
    //   2683: ldc 2097154
    //   2685: iastore
    //   2686: dup
    //   2687: bipush #24
    //   2689: ldc 69206016
    //   2691: iastore
    //   2692: dup
    //   2693: bipush #25
    //   2695: sipush #2048
    //   2698: iastore
    //   2699: dup
    //   2700: bipush #26
    //   2702: sipush #2050
    //   2705: iastore
    //   2706: dup
    //   2707: bipush #27
    //   2709: ldc 69208066
    //   2711: iastore
    //   2712: dup
    //   2713: bipush #28
    //   2715: ldc 2099200
    //   2717: iastore
    //   2718: dup
    //   2719: bipush #29
    //   2721: iconst_2
    //   2722: iastore
    //   2723: dup
    //   2724: bipush #30
    //   2726: ldc 67108864
    //   2728: iastore
    //   2729: dup
    //   2730: bipush #31
    //   2732: ldc 2099200
    //   2734: iastore
    //   2735: dup
    //   2736: bipush #32
    //   2738: ldc 67108864
    //   2740: iastore
    //   2741: dup
    //   2742: bipush #33
    //   2744: ldc 2099200
    //   2746: iastore
    //   2747: dup
    //   2748: bipush #34
    //   2750: ldc 2097152
    //   2752: iastore
    //   2753: dup
    //   2754: bipush #35
    //   2756: ldc 67110914
    //   2758: iastore
    //   2759: dup
    //   2760: bipush #36
    //   2762: ldc 67110914
    //   2764: iastore
    //   2765: dup
    //   2766: bipush #37
    //   2768: ldc 69206018
    //   2770: iastore
    //   2771: dup
    //   2772: bipush #38
    //   2774: ldc 69206018
    //   2776: iastore
    //   2777: dup
    //   2778: bipush #39
    //   2780: iconst_2
    //   2781: iastore
    //   2782: dup
    //   2783: bipush #40
    //   2785: ldc 2097154
    //   2787: iastore
    //   2788: dup
    //   2789: bipush #41
    //   2791: ldc 67108864
    //   2793: iastore
    //   2794: dup
    //   2795: bipush #42
    //   2797: ldc 67110912
    //   2799: iastore
    //   2800: dup
    //   2801: bipush #43
    //   2803: ldc 2097152
    //   2805: iastore
    //   2806: dup
    //   2807: bipush #44
    //   2809: ldc 69208064
    //   2811: iastore
    //   2812: dup
    //   2813: bipush #45
    //   2815: sipush #2050
    //   2818: iastore
    //   2819: dup
    //   2820: bipush #46
    //   2822: ldc 2099202
    //   2824: iastore
    //   2825: dup
    //   2826: bipush #47
    //   2828: ldc 69208064
    //   2830: iastore
    //   2831: dup
    //   2832: bipush #48
    //   2834: sipush #2050
    //   2837: iastore
    //   2838: dup
    //   2839: bipush #49
    //   2841: ldc 67108866
    //   2843: iastore
    //   2844: dup
    //   2845: bipush #50
    //   2847: ldc 69208066
    //   2849: iastore
    //   2850: dup
    //   2851: bipush #51
    //   2853: ldc 69206016
    //   2855: iastore
    //   2856: dup
    //   2857: bipush #52
    //   2859: ldc 2099200
    //   2861: iastore
    //   2862: dup
    //   2863: bipush #53
    //   2865: iconst_0
    //   2866: iastore
    //   2867: dup
    //   2868: bipush #54
    //   2870: iconst_2
    //   2871: iastore
    //   2872: dup
    //   2873: bipush #55
    //   2875: ldc 69208066
    //   2877: iastore
    //   2878: dup
    //   2879: bipush #56
    //   2881: iconst_0
    //   2882: iastore
    //   2883: dup
    //   2884: bipush #57
    //   2886: ldc 2099202
    //   2888: iastore
    //   2889: dup
    //   2890: bipush #58
    //   2892: ldc 69206016
    //   2894: iastore
    //   2895: dup
    //   2896: bipush #59
    //   2898: sipush #2048
    //   2901: iastore
    //   2902: dup
    //   2903: bipush #60
    //   2905: ldc 67108866
    //   2907: iastore
    //   2908: dup
    //   2909: bipush #61
    //   2911: ldc 67110912
    //   2913: iastore
    //   2914: dup
    //   2915: bipush #62
    //   2917: sipush #2048
    //   2920: iastore
    //   2921: dup
    //   2922: bipush #63
    //   2924: ldc 2097154
    //   2926: iastore
    //   2927: astore #12
    //   2929: bipush #64
    //   2931: newarray int
    //   2933: dup
    //   2934: iconst_0
    //   2935: ldc 268439616
    //   2937: iastore
    //   2938: dup
    //   2939: iconst_1
    //   2940: sipush #4096
    //   2943: iastore
    //   2944: dup
    //   2945: iconst_2
    //   2946: ldc 262144
    //   2948: iastore
    //   2949: dup
    //   2950: iconst_3
    //   2951: ldc 268701760
    //   2953: iastore
    //   2954: dup
    //   2955: iconst_4
    //   2956: ldc 268435456
    //   2958: iastore
    //   2959: dup
    //   2960: iconst_5
    //   2961: ldc 268439616
    //   2963: iastore
    //   2964: dup
    //   2965: bipush #6
    //   2967: bipush #64
    //   2969: iastore
    //   2970: dup
    //   2971: bipush #7
    //   2973: ldc 268435456
    //   2975: iastore
    //   2976: dup
    //   2977: bipush #8
    //   2979: ldc 262208
    //   2981: iastore
    //   2982: dup
    //   2983: bipush #9
    //   2985: ldc 268697600
    //   2987: iastore
    //   2988: dup
    //   2989: bipush #10
    //   2991: ldc 268701760
    //   2993: iastore
    //   2994: dup
    //   2995: bipush #11
    //   2997: ldc 266240
    //   2999: iastore
    //   3000: dup
    //   3001: bipush #12
    //   3003: ldc 268701696
    //   3005: iastore
    //   3006: dup
    //   3007: bipush #13
    //   3009: ldc 266304
    //   3011: iastore
    //   3012: dup
    //   3013: bipush #14
    //   3015: sipush #4096
    //   3018: iastore
    //   3019: dup
    //   3020: bipush #15
    //   3022: bipush #64
    //   3024: iastore
    //   3025: dup
    //   3026: bipush #16
    //   3028: ldc 268697600
    //   3030: iastore
    //   3031: dup
    //   3032: bipush #17
    //   3034: ldc 268435520
    //   3036: iastore
    //   3037: dup
    //   3038: bipush #18
    //   3040: ldc 268439552
    //   3042: iastore
    //   3043: dup
    //   3044: bipush #19
    //   3046: sipush #4160
    //   3049: iastore
    //   3050: dup
    //   3051: bipush #20
    //   3053: ldc 266240
    //   3055: iastore
    //   3056: dup
    //   3057: bipush #21
    //   3059: ldc 262208
    //   3061: iastore
    //   3062: dup
    //   3063: bipush #22
    //   3065: ldc 268697664
    //   3067: iastore
    //   3068: dup
    //   3069: bipush #23
    //   3071: ldc 268701696
    //   3073: iastore
    //   3074: dup
    //   3075: bipush #24
    //   3077: sipush #4160
    //   3080: iastore
    //   3081: dup
    //   3082: bipush #25
    //   3084: iconst_0
    //   3085: iastore
    //   3086: dup
    //   3087: bipush #26
    //   3089: iconst_0
    //   3090: iastore
    //   3091: dup
    //   3092: bipush #27
    //   3094: ldc 268697664
    //   3096: iastore
    //   3097: dup
    //   3098: bipush #28
    //   3100: ldc 268435520
    //   3102: iastore
    //   3103: dup
    //   3104: bipush #29
    //   3106: ldc 268439552
    //   3108: iastore
    //   3109: dup
    //   3110: bipush #30
    //   3112: ldc 266304
    //   3114: iastore
    //   3115: dup
    //   3116: bipush #31
    //   3118: ldc 262144
    //   3120: iastore
    //   3121: dup
    //   3122: bipush #32
    //   3124: ldc 266304
    //   3126: iastore
    //   3127: dup
    //   3128: bipush #33
    //   3130: ldc 262144
    //   3132: iastore
    //   3133: dup
    //   3134: bipush #34
    //   3136: ldc 268701696
    //   3138: iastore
    //   3139: dup
    //   3140: bipush #35
    //   3142: sipush #4096
    //   3145: iastore
    //   3146: dup
    //   3147: bipush #36
    //   3149: bipush #64
    //   3151: iastore
    //   3152: dup
    //   3153: bipush #37
    //   3155: ldc 268697664
    //   3157: iastore
    //   3158: dup
    //   3159: bipush #38
    //   3161: sipush #4096
    //   3164: iastore
    //   3165: dup
    //   3166: bipush #39
    //   3168: ldc 266304
    //   3170: iastore
    //   3171: dup
    //   3172: bipush #40
    //   3174: ldc 268439552
    //   3176: iastore
    //   3177: dup
    //   3178: bipush #41
    //   3180: bipush #64
    //   3182: iastore
    //   3183: dup
    //   3184: bipush #42
    //   3186: ldc 268435520
    //   3188: iastore
    //   3189: dup
    //   3190: bipush #43
    //   3192: ldc 268697600
    //   3194: iastore
    //   3195: dup
    //   3196: bipush #44
    //   3198: ldc 268697664
    //   3200: iastore
    //   3201: dup
    //   3202: bipush #45
    //   3204: ldc 268435456
    //   3206: iastore
    //   3207: dup
    //   3208: bipush #46
    //   3210: ldc 262144
    //   3212: iastore
    //   3213: dup
    //   3214: bipush #47
    //   3216: ldc 268439616
    //   3218: iastore
    //   3219: dup
    //   3220: bipush #48
    //   3222: iconst_0
    //   3223: iastore
    //   3224: dup
    //   3225: bipush #49
    //   3227: ldc 268701760
    //   3229: iastore
    //   3230: dup
    //   3231: bipush #50
    //   3233: ldc 262208
    //   3235: iastore
    //   3236: dup
    //   3237: bipush #51
    //   3239: ldc 268435520
    //   3241: iastore
    //   3242: dup
    //   3243: bipush #52
    //   3245: ldc 268697600
    //   3247: iastore
    //   3248: dup
    //   3249: bipush #53
    //   3251: ldc 268439552
    //   3253: iastore
    //   3254: dup
    //   3255: bipush #54
    //   3257: ldc 268439616
    //   3259: iastore
    //   3260: dup
    //   3261: bipush #55
    //   3263: iconst_0
    //   3264: iastore
    //   3265: dup
    //   3266: bipush #56
    //   3268: ldc 268701760
    //   3270: iastore
    //   3271: dup
    //   3272: bipush #57
    //   3274: ldc 266240
    //   3276: iastore
    //   3277: dup
    //   3278: bipush #58
    //   3280: ldc 266240
    //   3282: iastore
    //   3283: dup
    //   3284: bipush #59
    //   3286: sipush #4160
    //   3289: iastore
    //   3290: dup
    //   3291: bipush #60
    //   3293: sipush #4160
    //   3296: iastore
    //   3297: dup
    //   3298: bipush #61
    //   3300: ldc 262208
    //   3302: iastore
    //   3303: dup
    //   3304: bipush #62
    //   3306: ldc 268435456
    //   3308: iastore
    //   3309: dup
    //   3310: bipush #63
    //   3312: ldc 268701696
    //   3314: iastore
    //   3315: astore #13
    //   3317: aload_3
    //   3318: arraylength
    //   3319: istore #14
    //   3321: iload #14
    //   3323: bipush #8
    //   3325: irem
    //   3326: ifeq -> 3350
    //   3329: new java/lang/Exception
    //   3332: dup
    //   3333: sipush #27783
    //   3336: sipush #-28970
    //   3339: invokestatic a : (II)Ljava/lang/String;
    //   3342: invokespecial <init> : (Ljava/lang/String;)V
    //   3345: athrow
    //   3346: invokestatic a : (Ljava/lang/Throwable;)Ljava/lang/Throwable;
    //   3349: athrow
    //   3350: iconst_2
    //   3351: newarray int
    //   3353: astore #15
    //   3355: iload #14
    //   3357: newarray byte
    //   3359: astore #16
    //   3361: iload #14
    //   3363: bipush #8
    //   3365: idiv
    //   3366: istore #17
    //   3368: iconst_0
    //   3369: istore #18
    //   3371: iload #18
    //   3373: iload #17
    //   3375: if_icmpge -> 4289
    //   3378: iload #18
    //   3380: bipush #8
    //   3382: imul
    //   3383: istore #19
    //   3385: iconst_0
    //   3386: istore #20
    //   3388: iload #20
    //   3390: iconst_2
    //   3391: if_icmpge -> 3476
    //   3394: aload #15
    //   3396: iload #20
    //   3398: aload_3
    //   3399: iload #19
    //   3401: iload #20
    //   3403: iconst_4
    //   3404: imul
    //   3405: iadd
    //   3406: baload
    //   3407: sipush #255
    //   3410: iand
    //   3411: bipush #24
    //   3413: ishl
    //   3414: aload_3
    //   3415: iload #19
    //   3417: iload #20
    //   3419: iconst_4
    //   3420: imul
    //   3421: iadd
    //   3422: iconst_1
    //   3423: iadd
    //   3424: baload
    //   3425: sipush #255
    //   3428: iand
    //   3429: bipush #16
    //   3431: ishl
    //   3432: ior
    //   3433: aload_3
    //   3434: iload #19
    //   3436: iload #20
    //   3438: iconst_4
    //   3439: imul
    //   3440: iadd
    //   3441: iconst_2
    //   3442: iadd
    //   3443: baload
    //   3444: sipush #255
    //   3447: iand
    //   3448: bipush #8
    //   3450: ishl
    //   3451: ior
    //   3452: aload_3
    //   3453: iload #19
    //   3455: iload #20
    //   3457: iconst_4
    //   3458: imul
    //   3459: iadd
    //   3460: iconst_3
    //   3461: iadd
    //   3462: baload
    //   3463: sipush #255
    //   3466: iand
    //   3467: ior
    //   3468: iastore
    //   3469: iinc #20, 1
    //   3472: iload_2
    //   3473: ifne -> 3388
    //   3476: iconst_0
    //   3477: istore #25
    //   3479: aload #15
    //   3481: iconst_0
    //   3482: iaload
    //   3483: istore #23
    //   3485: aload #15
    //   3487: iconst_1
    //   3488: iaload
    //   3489: istore #22
    //   3491: iload #23
    //   3493: iconst_4
    //   3494: iushr
    //   3495: iload #22
    //   3497: ixor
    //   3498: ldc 252645135
    //   3500: iand
    //   3501: istore #21
    //   3503: iload #22
    //   3505: iload #21
    //   3507: ixor
    //   3508: istore #22
    //   3510: iload #23
    //   3512: iload #21
    //   3514: iconst_4
    //   3515: ishl
    //   3516: ixor
    //   3517: istore #23
    //   3519: iload #23
    //   3521: bipush #16
    //   3523: iushr
    //   3524: iload #22
    //   3526: ixor
    //   3527: ldc 65535
    //   3529: iand
    //   3530: istore #21
    //   3532: iload #22
    //   3534: iload #21
    //   3536: ixor
    //   3537: istore #22
    //   3539: iload #23
    //   3541: iload #21
    //   3543: bipush #16
    //   3545: ishl
    //   3546: ixor
    //   3547: istore #23
    //   3549: iload #22
    //   3551: iconst_2
    //   3552: iushr
    //   3553: iload #23
    //   3555: ixor
    //   3556: ldc 858993459
    //   3558: iand
    //   3559: istore #21
    //   3561: iload #23
    //   3563: iload #21
    //   3565: ixor
    //   3566: istore #23
    //   3568: iload #22
    //   3570: iload #21
    //   3572: iconst_2
    //   3573: ishl
    //   3574: ixor
    //   3575: istore #22
    //   3577: iload #22
    //   3579: bipush #8
    //   3581: iushr
    //   3582: iload #23
    //   3584: ixor
    //   3585: ldc 16711935
    //   3587: iand
    //   3588: istore #21
    //   3590: iload #23
    //   3592: iload #21
    //   3594: ixor
    //   3595: istore #23
    //   3597: iload #22
    //   3599: iload #21
    //   3601: bipush #8
    //   3603: ishl
    //   3604: ixor
    //   3605: istore #22
    //   3607: iload #22
    //   3609: iconst_1
    //   3610: ishl
    //   3611: iload #22
    //   3613: bipush #31
    //   3615: iushr
    //   3616: iconst_1
    //   3617: iand
    //   3618: ior
    //   3619: istore #22
    //   3621: iload #23
    //   3623: iload #22
    //   3625: ixor
    //   3626: ldc -1431655766
    //   3628: iand
    //   3629: istore #21
    //   3631: iload #23
    //   3633: iload #21
    //   3635: ixor
    //   3636: istore #23
    //   3638: iload #22
    //   3640: iload #21
    //   3642: ixor
    //   3643: istore #22
    //   3645: iload #23
    //   3647: iconst_1
    //   3648: ishl
    //   3649: iload #23
    //   3651: bipush #31
    //   3653: iushr
    //   3654: iconst_1
    //   3655: iand
    //   3656: ior
    //   3657: istore #23
    //   3659: iconst_0
    //   3660: istore #24
    //   3662: iload #24
    //   3664: bipush #8
    //   3666: if_icmpge -> 4004
    //   3669: iload #22
    //   3671: bipush #28
    //   3673: ishl
    //   3674: iload #22
    //   3676: iconst_4
    //   3677: iushr
    //   3678: ior
    //   3679: istore #21
    //   3681: iload #21
    //   3683: aload #5
    //   3685: iload #25
    //   3687: iinc #25, 1
    //   3690: iaload
    //   3691: ixor
    //   3692: istore #21
    //   3694: aload #12
    //   3696: iload #21
    //   3698: bipush #63
    //   3700: iand
    //   3701: iaload
    //   3702: istore #20
    //   3704: iload #20
    //   3706: aload #10
    //   3708: iload #21
    //   3710: bipush #8
    //   3712: iushr
    //   3713: bipush #63
    //   3715: iand
    //   3716: iaload
    //   3717: ior
    //   3718: istore #20
    //   3720: iload #20
    //   3722: aload #8
    //   3724: iload #21
    //   3726: bipush #16
    //   3728: iushr
    //   3729: bipush #63
    //   3731: iand
    //   3732: iaload
    //   3733: ior
    //   3734: istore #20
    //   3736: iload #20
    //   3738: aload #6
    //   3740: iload #21
    //   3742: bipush #24
    //   3744: iushr
    //   3745: bipush #63
    //   3747: iand
    //   3748: iaload
    //   3749: ior
    //   3750: istore #20
    //   3752: iload #22
    //   3754: aload #5
    //   3756: iload #25
    //   3758: iinc #25, 1
    //   3761: iaload
    //   3762: ixor
    //   3763: istore #21
    //   3765: iload #20
    //   3767: aload #13
    //   3769: iload #21
    //   3771: bipush #63
    //   3773: iand
    //   3774: iaload
    //   3775: ior
    //   3776: istore #20
    //   3778: iload #20
    //   3780: aload #11
    //   3782: iload #21
    //   3784: bipush #8
    //   3786: iushr
    //   3787: bipush #63
    //   3789: iand
    //   3790: iaload
    //   3791: ior
    //   3792: istore #20
    //   3794: iload #20
    //   3796: aload #9
    //   3798: iload #21
    //   3800: bipush #16
    //   3802: iushr
    //   3803: bipush #63
    //   3805: iand
    //   3806: iaload
    //   3807: ior
    //   3808: istore #20
    //   3810: iload #20
    //   3812: aload #7
    //   3814: iload #21
    //   3816: bipush #24
    //   3818: iushr
    //   3819: bipush #63
    //   3821: iand
    //   3822: iaload
    //   3823: ior
    //   3824: istore #20
    //   3826: iload #23
    //   3828: iload #20
    //   3830: ixor
    //   3831: istore #23
    //   3833: iload #23
    //   3835: bipush #28
    //   3837: ishl
    //   3838: iload #23
    //   3840: iconst_4
    //   3841: iushr
    //   3842: ior
    //   3843: istore #21
    //   3845: iload #21
    //   3847: aload #5
    //   3849: iload #25
    //   3851: iinc #25, 1
    //   3854: iaload
    //   3855: ixor
    //   3856: istore #21
    //   3858: aload #12
    //   3860: iload #21
    //   3862: bipush #63
    //   3864: iand
    //   3865: iaload
    //   3866: istore #20
    //   3868: iload #20
    //   3870: aload #10
    //   3872: iload #21
    //   3874: bipush #8
    //   3876: iushr
    //   3877: bipush #63
    //   3879: iand
    //   3880: iaload
    //   3881: ior
    //   3882: istore #20
    //   3884: iload #20
    //   3886: aload #8
    //   3888: iload #21
    //   3890: bipush #16
    //   3892: iushr
    //   3893: bipush #63
    //   3895: iand
    //   3896: iaload
    //   3897: ior
    //   3898: istore #20
    //   3900: iload #20
    //   3902: aload #6
    //   3904: iload #21
    //   3906: bipush #24
    //   3908: iushr
    //   3909: bipush #63
    //   3911: iand
    //   3912: iaload
    //   3913: ior
    //   3914: istore #20
    //   3916: iload #23
    //   3918: aload #5
    //   3920: iload #25
    //   3922: iinc #25, 1
    //   3925: iaload
    //   3926: ixor
    //   3927: istore #21
    //   3929: iload #20
    //   3931: aload #13
    //   3933: iload #21
    //   3935: bipush #63
    //   3937: iand
    //   3938: iaload
    //   3939: ior
    //   3940: istore #20
    //   3942: iload #20
    //   3944: aload #11
    //   3946: iload #21
    //   3948: bipush #8
    //   3950: iushr
    //   3951: bipush #63
    //   3953: iand
    //   3954: iaload
    //   3955: ior
    //   3956: istore #20
    //   3958: iload #20
    //   3960: aload #9
    //   3962: iload #21
    //   3964: bipush #16
    //   3966: iushr
    //   3967: bipush #63
    //   3969: iand
    //   3970: iaload
    //   3971: ior
    //   3972: istore #20
    //   3974: iload #20
    //   3976: aload #7
    //   3978: iload #21
    //   3980: bipush #24
    //   3982: iushr
    //   3983: bipush #63
    //   3985: iand
    //   3986: iaload
    //   3987: ior
    //   3988: istore #20
    //   3990: iload #22
    //   3992: iload #20
    //   3994: ixor
    //   3995: istore #22
    //   3997: iinc #24, 1
    //   4000: iload_2
    //   4001: ifne -> 3662
    //   4004: iload #22
    //   4006: bipush #31
    //   4008: ishl
    //   4009: iload #22
    //   4011: iconst_1
    //   4012: iushr
    //   4013: ior
    //   4014: istore #22
    //   4016: iload #23
    //   4018: iload #22
    //   4020: ixor
    //   4021: ldc -1431655766
    //   4023: iand
    //   4024: istore #21
    //   4026: iload #23
    //   4028: iload #21
    //   4030: ixor
    //   4031: istore #23
    //   4033: iload #22
    //   4035: iload #21
    //   4037: ixor
    //   4038: istore #22
    //   4040: iload #23
    //   4042: bipush #31
    //   4044: ishl
    //   4045: iload #23
    //   4047: iconst_1
    //   4048: iushr
    //   4049: ior
    //   4050: istore #23
    //   4052: iload #23
    //   4054: bipush #8
    //   4056: iushr
    //   4057: iload #22
    //   4059: ixor
    //   4060: ldc 16711935
    //   4062: iand
    //   4063: istore #21
    //   4065: iload #22
    //   4067: iload #21
    //   4069: ixor
    //   4070: istore #22
    //   4072: iload #23
    //   4074: iload #21
    //   4076: bipush #8
    //   4078: ishl
    //   4079: ixor
    //   4080: istore #23
    //   4082: iload #23
    //   4084: iconst_2
    //   4085: iushr
    //   4086: iload #22
    //   4088: ixor
    //   4089: ldc 858993459
    //   4091: iand
    //   4092: istore #21
    //   4094: iload #22
    //   4096: iload #21
    //   4098: ixor
    //   4099: istore #22
    //   4101: iload #23
    //   4103: iload #21
    //   4105: iconst_2
    //   4106: ishl
    //   4107: ixor
    //   4108: istore #23
    //   4110: iload #22
    //   4112: bipush #16
    //   4114: iushr
    //   4115: iload #23
    //   4117: ixor
    //   4118: ldc 65535
    //   4120: iand
    //   4121: istore #21
    //   4123: iload #23
    //   4125: iload #21
    //   4127: ixor
    //   4128: istore #23
    //   4130: iload #22
    //   4132: iload #21
    //   4134: bipush #16
    //   4136: ishl
    //   4137: ixor
    //   4138: istore #22
    //   4140: iload #22
    //   4142: iconst_4
    //   4143: iushr
    //   4144: iload #23
    //   4146: ixor
    //   4147: ldc 252645135
    //   4149: iand
    //   4150: istore #21
    //   4152: iload #23
    //   4154: iload #21
    //   4156: ixor
    //   4157: istore #23
    //   4159: iload #22
    //   4161: iload #21
    //   4163: iconst_4
    //   4164: ishl
    //   4165: ixor
    //   4166: istore #22
    //   4168: aload #15
    //   4170: iconst_0
    //   4171: iload #22
    //   4173: iastore
    //   4174: aload #15
    //   4176: iconst_1
    //   4177: iload #23
    //   4179: iastore
    //   4180: iload #18
    //   4182: bipush #8
    //   4184: imul
    //   4185: istore #26
    //   4187: iconst_0
    //   4188: istore #27
    //   4190: iload #27
    //   4192: iconst_2
    //   4193: if_icmpge -> 4282
    //   4196: aload #16
    //   4198: iload #26
    //   4200: iload #27
    //   4202: iconst_4
    //   4203: imul
    //   4204: iadd
    //   4205: aload #15
    //   4207: iload #27
    //   4209: iaload
    //   4210: bipush #24
    //   4212: iushr
    //   4213: i2b
    //   4214: bastore
    //   4215: aload #16
    //   4217: iload #26
    //   4219: iload #27
    //   4221: iconst_4
    //   4222: imul
    //   4223: iadd
    //   4224: iconst_1
    //   4225: iadd
    //   4226: aload #15
    //   4228: iload #27
    //   4230: iaload
    //   4231: bipush #16
    //   4233: iushr
    //   4234: i2b
    //   4235: bastore
    //   4236: aload #16
    //   4238: iload #26
    //   4240: iload #27
    //   4242: iconst_4
    //   4243: imul
    //   4244: iadd
    //   4245: iconst_2
    //   4246: iadd
    //   4247: aload #15
    //   4249: iload #27
    //   4251: iaload
    //   4252: bipush #8
    //   4254: iushr
    //   4255: i2b
    //   4256: bastore
    //   4257: aload #16
    //   4259: iload #26
    //   4261: iload #27
    //   4263: iconst_4
    //   4264: imul
    //   4265: iadd
    //   4266: iconst_3
    //   4267: iadd
    //   4268: aload #15
    //   4270: iload #27
    //   4272: iaload
    //   4273: i2b
    //   4274: bastore
    //   4275: iinc #27, 1
    //   4278: iload_2
    //   4279: ifne -> 4190
    //   4282: iinc #18, 1
    //   4285: iload_2
    //   4286: ifne -> 3371
    //   4289: aload #16
    //   4291: aload #16
    //   4293: arraylength
    //   4294: iconst_1
    //   4295: isub
    //   4296: baload
    //   4297: istore #18
    //   4299: aload #16
    //   4301: arraylength
    //   4302: iload #18
    //   4304: isub
    //   4305: newarray byte
    //   4307: astore #4
    //   4309: aload #16
    //   4311: arraylength
    //   4312: aload #4
    //   4314: arraylength
    //   4315: if_icmpge -> 4339
    //   4318: new java/lang/Exception
    //   4321: dup
    //   4322: sipush #27784
    //   4325: sipush #32659
    //   4328: invokestatic a : (II)Ljava/lang/String;
    //   4331: invokespecial <init> : (Ljava/lang/String;)V
    //   4334: athrow
    //   4335: invokestatic a : (Ljava/lang/Throwable;)Ljava/lang/Throwable;
    //   4338: athrow
    //   4339: iconst_0
    //   4340: istore #19
    //   4342: iload #19
    //   4344: aload #4
    //   4346: arraylength
    //   4347: if_icmpge -> 4367
    //   4350: aload #4
    //   4352: iload #19
    //   4354: aload #16
    //   4356: iload #19
    //   4358: baload
    //   4359: bastore
    //   4360: iinc #19, 1
    //   4363: iload_2
    //   4364: ifne -> 4342
    //   4367: new java/math/BigInteger
    //   4370: dup
    //   4371: aload #4
    //   4373: invokespecial <init> : ([B)V
    //   4376: invokevirtual abs : ()Ljava/math/BigInteger;
    //   4379: putstatic burp/Zlna.ZG : Ljava/lang/Object;
    //   4382: sipush #27776
    //   4385: sipush #-7573
    //   4388: invokestatic a : (II)Ljava/lang/String;
    //   4391: iconst_1
    //   4392: ldc burp/Zbow
    //   4394: invokevirtual getClassLoader : ()Ljava/lang/ClassLoader;
    //   4397: invokestatic forName : (Ljava/lang/String;ZLjava/lang/ClassLoader;)Ljava/lang/Class;
    //   4400: invokevirtual getDeclaredFields : ()[Ljava/lang/reflect/Field;
    //   4403: astore_3
    //   4404: aload_3
    //   4405: arraylength
    //   4406: istore #4
    //   4408: iconst_0
    //   4409: istore #5
    //   4411: iload #5
    //   4413: iload #4
    //   4415: if_icmpge -> 4552
    //   4418: aload_3
    //   4419: iload #5
    //   4421: aaload
    //   4422: astore #6
    //   4424: aload #6
    //   4426: invokevirtual getModifiers : ()I
    //   4429: invokestatic isStatic : (I)Z
    //   4432: ifne -> 4442
    //   4435: goto -> 4545
    //   4438: invokestatic a : (Ljava/lang/Throwable;)Ljava/lang/Throwable;
    //   4441: athrow
    //   4442: aload #6
    //   4444: invokevirtual getType : ()Ljava/lang/Class;
    //   4447: astore #7
    //   4449: aload #7
    //   4451: ifnull -> 4532
    //   4454: aload #7
    //   4456: invokevirtual isPrimitive : ()Z
    //   4459: ifne -> 4532
    //   4462: goto -> 4469
    //   4465: invokestatic a : (Ljava/lang/Throwable;)Ljava/lang/Throwable;
    //   4468: athrow
    //   4469: aload #7
    //   4471: invokevirtual getPackage : ()Ljava/lang/Package;
    //   4474: ifnull -> 4532
    //   4477: goto -> 4484
    //   4480: invokestatic a : (Ljava/lang/Throwable;)Ljava/lang/Throwable;
    //   4483: athrow
    //   4484: aload #7
    //   4486: invokevirtual getPackage : ()Ljava/lang/Package;
    //   4489: invokevirtual getName : ()Ljava/lang/String;
    //   4492: ifnull -> 4532
    //   4495: goto -> 4502
    //   4498: invokestatic a : (Ljava/lang/Throwable;)Ljava/lang/Throwable;
    //   4501: athrow
    //   4502: aload #7
    //   4504: invokevirtual getPackage : ()Ljava/lang/Package;
    //   4507: invokevirtual getName : ()Ljava/lang/String;
    //   4510: sipush #27787
    //   4513: sipush #18015
    //   4516: invokestatic a : (II)Ljava/lang/String;
    //   4519: invokevirtual startsWith : (Ljava/lang/String;)Z
    //   4522: ifne -> 4532
    //   4525: goto -> 4532
    //   4528: invokestatic a : (Ljava/lang/Throwable;)Ljava/lang/Throwable;
    //   4531: athrow
    //   4532: aload #6
    //   4534: iconst_1
    //   4535: invokevirtual setAccessible : (Z)V
    //   4538: aload #6
    //   4540: aconst_null
    //   4541: invokevirtual get : (Ljava/lang/Object;)Ljava/lang/Object;
    //   4544: pop
    //   4545: iinc #5, 1
    //   4548: iload_2
    //   4549: ifne -> 4411
    //   4552: sipush #27804
    //   4555: sipush #-14273
    //   4558: invokestatic a : (II)Ljava/lang/String;
    //   4561: invokestatic forName : (Ljava/lang/String;)Ljava/lang/Class;
    //   4564: invokevirtual getDeclaredMethods : ()[Ljava/lang/reflect/Method;
    //   4567: astore_3
    //   4568: aload_3
    //   4569: arraylength
    //   4570: istore #4
    //   4572: iconst_0
    //   4573: istore #5
    //   4575: iload #5
    //   4577: iload #4
    //   4579: if_icmpge -> 4711
    //   4582: aload_3
    //   4583: iload #5
    //   4585: aaload
    //   4586: astore #6
    //   4588: aload #6
    //   4590: invokevirtual getParameterTypes : ()[Ljava/lang/Class;
    //   4593: pop
    //   4594: aload #6
    //   4596: invokevirtual getModifiers : ()I
    //   4599: invokestatic isStatic : (I)Z
    //   4602: ifeq -> 4697
    //   4605: aload #6
    //   4607: invokevirtual getParameterTypes : ()[Ljava/lang/Class;
    //   4610: arraylength
    //   4611: iconst_2
    //   4612: if_icmpne -> 4697
    //   4615: goto -> 4622
    //   4618: invokestatic a : (Ljava/lang/Throwable;)Ljava/lang/Throwable;
    //   4621: athrow
    //   4622: aload #6
    //   4624: invokevirtual getReturnType : ()Ljava/lang/Class;
    //   4627: getstatic java/lang/Void.TYPE : Ljava/lang/Class;
    //   4630: invokevirtual equals : (Ljava/lang/Object;)Z
    //   4633: ifeq -> 4697
    //   4636: goto -> 4643
    //   4639: invokestatic a : (Ljava/lang/Throwable;)Ljava/lang/Throwable;
    //   4642: athrow
    //   4643: aload #6
    //   4645: iconst_1
    //   4646: invokevirtual setAccessible : (Z)V
    //   4649: aload #6
    //   4651: aconst_null
    //   4652: iconst_2
    //   4653: anewarray java/lang/Object
    //   4656: dup
    //   4657: iconst_0
    //   4658: aload_0
    //   4659: aastore
    //   4660: dup
    //   4661: iconst_1
    //   4662: aload_1
    //   4663: ifnonnull -> 4681
    //   4666: goto -> 4673
    //   4669: invokestatic a : (Ljava/lang/Throwable;)Ljava/lang/Throwable;
    //   4672: athrow
    //   4673: aload_1
    //   4674: goto -> 4688
    //   4677: invokestatic a : (Ljava/lang/Throwable;)Ljava/lang/Throwable;
    //   4680: athrow
    //   4681: aload_1
    //   4682: checkcast [B
    //   4685: invokevirtual clone : ()Ljava/lang/Object;
    //   4688: aastore
    //   4689: invokevirtual invoke : (Ljava/lang/Object;[Ljava/lang/Object;)Ljava/lang/Object;
    //   4692: pop
    //   4693: iload_2
    //   4694: ifne -> 4711
    //   4697: iinc #5, 1
    //   4700: iload_2
    //   4701: ifne -> 4575
    //   4704: goto -> 4711
    //   4707: invokestatic a : (Ljava/lang/Throwable;)Ljava/lang/Throwable;
    //   4710: athrow
    //   4711: iconst_0
    //   4712: istore_3
    //   4713: getstatic burp/Zbzc.ZL : Ljava/lang/String;
    //   4716: getstatic burp/Ztdx.ZX : Ljava/lang/Object;
    //   4719: checkcast java/math/BigInteger
    //   4722: invokevirtual intValue : ()I
    //   4725: bipush #32
    //   4727: irem
    //   4728: invokestatic abs : (I)I
    //   4731: invokevirtual charAt : (I)C
    //   4734: getstatic burp/Zlo2.ZJ : Ljava/lang/String;
    //   4737: getstatic burp/Zmlu.Zi : Ljava/lang/Object;
    //   4740: checkcast java/math/BigInteger
    //   4743: invokevirtual intValue : ()I
    //   4746: bipush #32
    //   4748: irem
    //   4749: invokestatic abs : (I)I
    //   4752: invokevirtual charAt : (I)C
    //   4755: if_icmple -> 5099
    //   4758: sipush #27797
    //   4761: sipush #-29734
    //   4764: invokestatic a : (II)Ljava/lang/String;
    //   4767: iconst_1
    //   4768: ldc burp/Zrd3
    //   4770: invokevirtual getClassLoader : ()Ljava/lang/ClassLoader;
    //   4773: invokestatic forName : (Ljava/lang/String;ZLjava/lang/ClassLoader;)Ljava/lang/Class;
    //   4776: invokevirtual getDeclaredFields : ()[Ljava/lang/reflect/Field;
    //   4779: astore #4
    //   4781: aload #4
    //   4783: arraylength
    //   4784: istore #5
    //   4786: iconst_0
    //   4787: istore #6
    //   4789: iload #6
    //   4791: iload #5
    //   4793: if_icmpge -> 4931
    //   4796: aload #4
    //   4798: iload #6
    //   4800: aaload
    //   4801: astore #7
    //   4803: aload #7
    //   4805: invokevirtual getModifiers : ()I
    //   4808: invokestatic isStatic : (I)Z
    //   4811: ifne -> 4821
    //   4814: goto -> 4924
    //   4817: invokestatic a : (Ljava/lang/Throwable;)Ljava/lang/Throwable;
    //   4820: athrow
    //   4821: aload #7
    //   4823: invokevirtual getType : ()Ljava/lang/Class;
    //   4826: astore #8
    //   4828: aload #8
    //   4830: ifnull -> 4911
    //   4833: aload #8
    //   4835: invokevirtual isPrimitive : ()Z
    //   4838: ifne -> 4911
    //   4841: goto -> 4848
    //   4844: invokestatic a : (Ljava/lang/Throwable;)Ljava/lang/Throwable;
    //   4847: athrow
    //   4848: aload #8
    //   4850: invokevirtual getPackage : ()Ljava/lang/Package;
    //   4853: ifnull -> 4911
    //   4856: goto -> 4863
    //   4859: invokestatic a : (Ljava/lang/Throwable;)Ljava/lang/Throwable;
    //   4862: athrow
    //   4863: aload #8
    //   4865: invokevirtual getPackage : ()Ljava/lang/Package;
    //   4868: invokevirtual getName : ()Ljava/lang/String;
    //   4871: ifnull -> 4911
    //   4874: goto -> 4881
    //   4877: invokestatic a : (Ljava/lang/Throwable;)Ljava/lang/Throwable;
    //   4880: athrow
    //   4881: aload #8
    //   4883: invokevirtual getPackage : ()Ljava/lang/Package;
    //   4886: invokevirtual getName : ()Ljava/lang/String;
    //   4889: sipush #27785
    //   4892: sipush #-1348
    //   4895: invokestatic a : (II)Ljava/lang/String;
    //   4898: invokevirtual startsWith : (Ljava/lang/String;)Z
    //   4901: ifne -> 4911
    //   4904: goto -> 4911
    //   4907: invokestatic a : (Ljava/lang/Throwable;)Ljava/lang/Throwable;
    //   4910: athrow
    //   4911: aload #7
    //   4913: iconst_1
    //   4914: invokevirtual setAccessible : (Z)V
    //   4917: aload #7
    //   4919: aconst_null
    //   4920: invokevirtual get : (Ljava/lang/Object;)Ljava/lang/Object;
    //   4923: pop
    //   4924: iinc #6, 1
    //   4927: iload_2
    //   4928: ifne -> 4789
    //   4931: sipush #27799
    //   4934: sipush #-12223
    //   4937: invokestatic a : (II)Ljava/lang/String;
    //   4940: invokestatic forName : (Ljava/lang/String;)Ljava/lang/Class;
    //   4943: invokevirtual getDeclaredMethods : ()[Ljava/lang/reflect/Method;
    //   4946: astore #4
    //   4948: aload #4
    //   4950: arraylength
    //   4951: istore #5
    //   4953: iconst_0
    //   4954: istore #6
    //   4956: iload #6
    //   4958: iload #5
    //   4960: if_icmpge -> 5096
    //   4963: aload #4
    //   4965: iload #6
    //   4967: aaload
    //   4968: astore #7
    //   4970: aload #7
    //   4972: invokevirtual getParameterTypes : ()[Ljava/lang/Class;
    //   4975: pop
    //   4976: aload #7
    //   4978: invokevirtual getModifiers : ()I
    //   4981: invokestatic isStatic : (I)Z
    //   4984: ifeq -> 5082
    //   4987: aload #7
    //   4989: invokevirtual getParameterTypes : ()[Ljava/lang/Class;
    //   4992: arraylength
    //   4993: iconst_2
    //   4994: if_icmpne -> 5082
    //   4997: goto -> 5004
    //   5000: invokestatic a : (Ljava/lang/Throwable;)Ljava/lang/Throwable;
    //   5003: athrow
    //   5004: aload #7
    //   5006: invokevirtual getReturnType : ()Ljava/lang/Class;
    //   5009: getstatic java/lang/Boolean.TYPE : Ljava/lang/Class;
    //   5012: if_acmpne -> 5082
    //   5015: goto -> 5022
    //   5018: invokestatic a : (Ljava/lang/Throwable;)Ljava/lang/Throwable;
    //   5021: athrow
    //   5022: aload #7
    //   5024: iconst_1
    //   5025: invokevirtual setAccessible : (Z)V
    //   5028: aload #7
    //   5030: aconst_null
    //   5031: iconst_2
    //   5032: anewarray java/lang/Object
    //   5035: dup
    //   5036: iconst_0
    //   5037: aload_0
    //   5038: aastore
    //   5039: dup
    //   5040: iconst_1
    //   5041: aload_1
    //   5042: ifnonnull -> 5060
    //   5045: goto -> 5052
    //   5048: invokestatic a : (Ljava/lang/Throwable;)Ljava/lang/Throwable;
    //   5051: athrow
    //   5052: aload_1
    //   5053: goto -> 5067
    //   5056: invokestatic a : (Ljava/lang/Throwable;)Ljava/lang/Throwable;
    //   5059: athrow
    //   5060: aload_1
    //   5061: checkcast [B
    //   5064: invokevirtual clone : ()Ljava/lang/Object;
    //   5067: aastore
    //   5068: invokevirtual invoke : (Ljava/lang/Object;[Ljava/lang/Object;)Ljava/lang/Object;
    //   5071: checkcast java/lang/Boolean
    //   5074: invokevirtual booleanValue : ()Z
    //   5077: istore_3
    //   5078: iload_2
    //   5079: ifne -> 5096
    //   5082: iinc #6, 1
    //   5085: iload_2
    //   5086: ifne -> 4956
    //   5089: goto -> 5096
    //   5092: invokestatic a : (Ljava/lang/Throwable;)Ljava/lang/Throwable;
    //   5095: athrow
    //   5096: goto -> 5437
    //   5099: sipush #27807
    //   5102: sipush #-27916
    //   5105: invokestatic a : (II)Ljava/lang/String;
    //   5108: iconst_1
    //   5109: ldc burp/Zmha
    //   5111: invokevirtual getClassLoader : ()Ljava/lang/ClassLoader;
    //   5114: invokestatic forName : (Ljava/lang/String;ZLjava/lang/ClassLoader;)Ljava/lang/Class;
    //   5117: invokevirtual getDeclaredFields : ()[Ljava/lang/reflect/Field;
    //   5120: astore #4
    //   5122: aload #4
    //   5124: arraylength
    //   5125: istore #5
    //   5127: iconst_0
    //   5128: istore #6
    //   5130: iload #6
    //   5132: iload #5
    //   5134: if_icmpge -> 5272
    //   5137: aload #4
    //   5139: iload #6
    //   5141: aaload
    //   5142: astore #7
    //   5144: aload #7
    //   5146: invokevirtual getModifiers : ()I
    //   5149: invokestatic isStatic : (I)Z
    //   5152: ifne -> 5162
    //   5155: goto -> 5265
    //   5158: invokestatic a : (Ljava/lang/Throwable;)Ljava/lang/Throwable;
    //   5161: athrow
    //   5162: aload #7
    //   5164: invokevirtual getType : ()Ljava/lang/Class;
    //   5167: astore #8
    //   5169: aload #8
    //   5171: ifnull -> 5252
    //   5174: aload #8
    //   5176: invokevirtual isPrimitive : ()Z
    //   5179: ifne -> 5252
    //   5182: goto -> 5189
    //   5185: invokestatic a : (Ljava/lang/Throwable;)Ljava/lang/Throwable;
    //   5188: athrow
    //   5189: aload #8
    //   5191: invokevirtual getPackage : ()Ljava/lang/Package;
    //   5194: ifnull -> 5252
    //   5197: goto -> 5204
    //   5200: invokestatic a : (Ljava/lang/Throwable;)Ljava/lang/Throwable;
    //   5203: athrow
    //   5204: aload #8
    //   5206: invokevirtual getPackage : ()Ljava/lang/Package;
    //   5209: invokevirtual getName : ()Ljava/lang/String;
    //   5212: ifnull -> 5252
    //   5215: goto -> 5222
    //   5218: invokestatic a : (Ljava/lang/Throwable;)Ljava/lang/Throwable;
    //   5221: athrow
    //   5222: aload #8
    //   5224: invokevirtual getPackage : ()Ljava/lang/Package;
    //   5227: invokevirtual getName : ()Ljava/lang/String;
    //   5230: sipush #27785
    //   5233: sipush #-1348
    //   5236: invokestatic a : (II)Ljava/lang/String;
    //   5239: invokevirtual startsWith : (Ljava/lang/String;)Z
    //   5242: ifne -> 5252
    //   5245: goto -> 5252
    //   5248: invokestatic a : (Ljava/lang/Throwable;)Ljava/lang/Throwable;
    //   5251: athrow
    //   5252: aload #7
    //   5254: iconst_1
    //   5255: invokevirtual setAccessible : (Z)V
    //   5258: aload #7
    //   5260: aconst_null
    //   5261: invokevirtual get : (Ljava/lang/Object;)Ljava/lang/Object;
    //   5264: pop
    //   5265: iinc #6, 1
    //   5268: iload_2
    //   5269: ifne -> 5130
    //   5272: sipush #27793
    //   5275: sipush #-8170
    //   5278: invokestatic a : (II)Ljava/lang/String;
    //   5281: invokestatic forName : (Ljava/lang/String;)Ljava/lang/Class;
    //   5284: invokevirtual getDeclaredMethods : ()[Ljava/lang/reflect/Method;
    //   5287: astore #4
    //   5289: aload #4
    //   5291: arraylength
    //   5292: istore #5
    //   5294: iconst_0
    //   5295: istore #6
    //   5297: iload #6
    //   5299: iload #5
    //   5301: if_icmpge -> 5437
    //   5304: aload #4
    //   5306: iload #6
    //   5308: aaload
    //   5309: astore #7
    //   5311: aload #7
    //   5313: invokevirtual getParameterTypes : ()[Ljava/lang/Class;
    //   5316: pop
    //   5317: aload #7
    //   5319: invokevirtual getModifiers : ()I
    //   5322: invokestatic isStatic : (I)Z
    //   5325: ifeq -> 5423
    //   5328: aload #7
    //   5330: invokevirtual getParameterTypes : ()[Ljava/lang/Class;
    //   5333: arraylength
    //   5334: iconst_2
    //   5335: if_icmpne -> 5423
    //   5338: goto -> 5345
    //   5341: invokestatic a : (Ljava/lang/Throwable;)Ljava/lang/Throwable;
    //   5344: athrow
    //   5345: aload #7
    //   5347: invokevirtual getReturnType : ()Ljava/lang/Class;
    //   5350: getstatic java/lang/Boolean.TYPE : Ljava/lang/Class;
    //   5353: if_acmpne -> 5423
    //   5356: goto -> 5363
    //   5359: invokestatic a : (Ljava/lang/Throwable;)Ljava/lang/Throwable;
    //   5362: athrow
    //   5363: aload #7
    //   5365: iconst_1
    //   5366: invokevirtual setAccessible : (Z)V
    //   5369: aload #7
    //   5371: aconst_null
    //   5372: iconst_2
    //   5373: anewarray java/lang/Object
    //   5376: dup
    //   5377: iconst_0
    //   5378: aload_0
    //   5379: aastore
    //   5380: dup
    //   5381: iconst_1
    //   5382: aload_1
    //   5383: ifnonnull -> 5401
    //   5386: goto -> 5393
    //   5389: invokestatic a : (Ljava/lang/Throwable;)Ljava/lang/Throwable;
    //   5392: athrow
    //   5393: aload_1
    //   5394: goto -> 5408
    //   5397: invokestatic a : (Ljava/lang/Throwable;)Ljava/lang/Throwable;
    //   5400: athrow
    //   5401: aload_1
    //   5402: checkcast [B
    //   5405: invokevirtual clone : ()Ljava/lang/Object;
    //   5408: aastore
    //   5409: invokevirtual invoke : (Ljava/lang/Object;[Ljava/lang/Object;)Ljava/lang/Object;
    //   5412: checkcast java/lang/Boolean
    //   5415: invokevirtual booleanValue : ()Z
    //   5418: istore_3
    //   5419: iload_2
    //   5420: ifne -> 5437
    //   5423: iinc #6, 1
    //   5426: iload_2
    //   5427: ifne -> 5297
    //   5430: goto -> 5437
    //   5433: invokestatic a : (Ljava/lang/Throwable;)Ljava/lang/Throwable;
    //   5436: athrow
    //   5437: iload_3
    //   5438: ifeq -> 5443
    //   5441: iload_3
    //   5442: ireturn
    //   5443: getstatic burp/Zzou.ZN : Ljava/lang/String;
    //   5446: getstatic burp/Zscs.Zg : Ljava/lang/Object;
    //   5449: checkcast java/math/BigInteger
    //   5452: invokevirtual intValue : ()I
    //   5455: bipush #32
    //   5457: irem
    //   5458: invokestatic abs : (I)I
    //   5461: invokevirtual charAt : (I)C
    //   5464: getstatic burp/Zmrc.Zx : Ljava/lang/String;
    //   5467: getstatic burp/Zdk.Zy : Ljava/lang/Object;
    //   5470: checkcast java/math/BigInteger
    //   5473: invokevirtual intValue : ()I
    //   5476: bipush #32
    //   5478: irem
    //   5479: invokestatic abs : (I)I
    //   5482: invokevirtual charAt : (I)C
    //   5485: if_icmpgt -> 5830
    //   5488: sipush #27777
    //   5491: sipush #-14522
    //   5494: invokestatic a : (II)Ljava/lang/String;
    //   5497: iconst_1
    //   5498: ldc burp/Zs26
    //   5500: invokevirtual getClassLoader : ()Ljava/lang/ClassLoader;
    //   5503: invokestatic forName : (Ljava/lang/String;ZLjava/lang/ClassLoader;)Ljava/lang/Class;
    //   5506: invokevirtual getDeclaredFields : ()[Ljava/lang/reflect/Field;
    //   5509: astore #4
    //   5511: aload #4
    //   5513: arraylength
    //   5514: istore #5
    //   5516: iconst_0
    //   5517: istore #6
    //   5519: iload #6
    //   5521: iload #5
    //   5523: if_icmpge -> 5661
    //   5526: aload #4
    //   5528: iload #6
    //   5530: aaload
    //   5531: astore #7
    //   5533: aload #7
    //   5535: invokevirtual getModifiers : ()I
    //   5538: invokestatic isStatic : (I)Z
    //   5541: ifne -> 5551
    //   5544: goto -> 5654
    //   5547: invokestatic a : (Ljava/lang/Throwable;)Ljava/lang/Throwable;
    //   5550: athrow
    //   5551: aload #7
    //   5553: invokevirtual getType : ()Ljava/lang/Class;
    //   5556: astore #8
    //   5558: aload #8
    //   5560: ifnull -> 5641
    //   5563: aload #8
    //   5565: invokevirtual isPrimitive : ()Z
    //   5568: ifne -> 5641
    //   5571: goto -> 5578
    //   5574: invokestatic a : (Ljava/lang/Throwable;)Ljava/lang/Throwable;
    //   5577: athrow
    //   5578: aload #8
    //   5580: invokevirtual getPackage : ()Ljava/lang/Package;
    //   5583: ifnull -> 5641
    //   5586: goto -> 5593
    //   5589: invokestatic a : (Ljava/lang/Throwable;)Ljava/lang/Throwable;
    //   5592: athrow
    //   5593: aload #8
    //   5595: invokevirtual getPackage : ()Ljava/lang/Package;
    //   5598: invokevirtual getName : ()Ljava/lang/String;
    //   5601: ifnull -> 5641
    //   5604: goto -> 5611
    //   5607: invokestatic a : (Ljava/lang/Throwable;)Ljava/lang/Throwable;
    //   5610: athrow
    //   5611: aload #8
    //   5613: invokevirtual getPackage : ()Ljava/lang/Package;
    //   5616: invokevirtual getName : ()Ljava/lang/String;
    //   5619: sipush #27785
    //   5622: sipush #-1348
    //   5625: invokestatic a : (II)Ljava/lang/String;
    //   5628: invokevirtual startsWith : (Ljava/lang/String;)Z
    //   5631: ifne -> 5641
    //   5634: goto -> 5641
    //   5637: invokestatic a : (Ljava/lang/Throwable;)Ljava/lang/Throwable;
    //   5640: athrow
    //   5641: aload #7
    //   5643: iconst_1
    //   5644: invokevirtual setAccessible : (Z)V
    //   5647: aload #7
    //   5649: aconst_null
    //   5650: invokevirtual get : (Ljava/lang/Object;)Ljava/lang/Object;
    //   5653: pop
    //   5654: iinc #6, 1
    //   5657: iload_2
    //   5658: ifne -> 5519
    //   5661: sipush #27796
    //   5664: sipush #2567
    //   5667: invokestatic a : (II)Ljava/lang/String;
    //   5670: invokestatic forName : (Ljava/lang/String;)Ljava/lang/Class;
    //   5673: invokevirtual getDeclaredMethods : ()[Ljava/lang/reflect/Method;
    //   5676: astore #4
    //   5678: aload #4
    //   5680: arraylength
    //   5681: istore #5
    //   5683: iconst_0
    //   5684: istore #6
    //   5686: iload #6
    //   5688: iload #5
    //   5690: if_icmpge -> 5826
    //   5693: aload #4
    //   5695: iload #6
    //   5697: aaload
    //   5698: astore #7
    //   5700: aload #7
    //   5702: invokevirtual getParameterTypes : ()[Ljava/lang/Class;
    //   5705: pop
    //   5706: aload #7
    //   5708: invokevirtual getModifiers : ()I
    //   5711: invokestatic isStatic : (I)Z
    //   5714: ifeq -> 5812
    //   5717: aload #7
    //   5719: invokevirtual getParameterTypes : ()[Ljava/lang/Class;
    //   5722: arraylength
    //   5723: iconst_2
    //   5724: if_icmpne -> 5812
    //   5727: goto -> 5734
    //   5730: invokestatic a : (Ljava/lang/Throwable;)Ljava/lang/Throwable;
    //   5733: athrow
    //   5734: aload #7
    //   5736: invokevirtual getReturnType : ()Ljava/lang/Class;
    //   5739: getstatic java/lang/Boolean.TYPE : Ljava/lang/Class;
    //   5742: if_acmpne -> 5812
    //   5745: goto -> 5752
    //   5748: invokestatic a : (Ljava/lang/Throwable;)Ljava/lang/Throwable;
    //   5751: athrow
    //   5752: aload #7
    //   5754: iconst_1
    //   5755: invokevirtual setAccessible : (Z)V
    //   5758: aload #7
    //   5760: aconst_null
    //   5761: iconst_2
    //   5762: anewarray java/lang/Object
    //   5765: dup
    //   5766: iconst_0
    //   5767: aload_0
    //   5768: aastore
    //   5769: dup
    //   5770: iconst_1
    //   5771: aload_1
    //   5772: ifnonnull -> 5790
    //   5775: goto -> 5782
    //   5778: invokestatic a : (Ljava/lang/Throwable;)Ljava/lang/Throwable;
    //   5781: athrow
    //   5782: aload_1
    //   5783: goto -> 5797
    //   5786: invokestatic a : (Ljava/lang/Throwable;)Ljava/lang/Throwable;
    //   5789: athrow
    //   5790: aload_1
    //   5791: checkcast [B
    //   5794: invokevirtual clone : ()Ljava/lang/Object;
    //   5797: aastore
    //   5798: invokevirtual invoke : (Ljava/lang/Object;[Ljava/lang/Object;)Ljava/lang/Object;
    //   5801: checkcast java/lang/Boolean
    //   5804: invokevirtual booleanValue : ()Z
    //   5807: istore_3
    //   5808: iload_2
    //   5809: ifne -> 5826
    //   5812: iinc #6, 1
    //   5815: iload_2
    //   5816: ifne -> 5686
    //   5819: goto -> 5826
    //   5822: invokestatic a : (Ljava/lang/Throwable;)Ljava/lang/Throwable;
    //   5825: athrow
    //   5826: iload_2
    //   5827: ifne -> 6168
    //   5830: sipush #27780
    //   5833: sipush #17019
    //   5836: invokestatic a : (II)Ljava/lang/String;
    //   5839: iconst_1
    //   5840: ldc burp/Zr0
    //   5842: invokevirtual getClassLoader : ()Ljava/lang/ClassLoader;
    //   5845: invokestatic forName : (Ljava/lang/String;ZLjava/lang/ClassLoader;)Ljava/lang/Class;
    //   5848: invokevirtual getDeclaredFields : ()[Ljava/lang/reflect/Field;
    //   5851: astore #4
    //   5853: aload #4
    //   5855: arraylength
    //   5856: istore #5
    //   5858: iconst_0
    //   5859: istore #6
    //   5861: iload #6
    //   5863: iload #5
    //   5865: if_icmpge -> 6003
    //   5868: aload #4
    //   5870: iload #6
    //   5872: aaload
    //   5873: astore #7
    //   5875: aload #7
    //   5877: invokevirtual getModifiers : ()I
    //   5880: invokestatic isStatic : (I)Z
    //   5883: ifne -> 5893
    //   5886: goto -> 5996
    //   5889: invokestatic a : (Ljava/lang/Throwable;)Ljava/lang/Throwable;
    //   5892: athrow
    //   5893: aload #7
    //   5895: invokevirtual getType : ()Ljava/lang/Class;
    //   5898: astore #8
    //   5900: aload #8
    //   5902: ifnull -> 5983
    //   5905: aload #8
    //   5907: invokevirtual isPrimitive : ()Z
    //   5910: ifne -> 5983
    //   5913: goto -> 5920
    //   5916: invokestatic a : (Ljava/lang/Throwable;)Ljava/lang/Throwable;
    //   5919: athrow
    //   5920: aload #8
    //   5922: invokevirtual getPackage : ()Ljava/lang/Package;
    //   5925: ifnull -> 5983
    //   5928: goto -> 5935
    //   5931: invokestatic a : (Ljava/lang/Throwable;)Ljava/lang/Throwable;
    //   5934: athrow
    //   5935: aload #8
    //   5937: invokevirtual getPackage : ()Ljava/lang/Package;
    //   5940: invokevirtual getName : ()Ljava/lang/String;
    //   5943: ifnull -> 5983
    //   5946: goto -> 5953
    //   5949: invokestatic a : (Ljava/lang/Throwable;)Ljava/lang/Throwable;
    //   5952: athrow
    //   5953: aload #8
    //   5955: invokevirtual getPackage : ()Ljava/lang/Package;
    //   5958: invokevirtual getName : ()Ljava/lang/String;
    //   5961: sipush #27785
    //   5964: sipush #-1348
    //   5967: invokestatic a : (II)Ljava/lang/String;
    //   5970: invokevirtual startsWith : (Ljava/lang/String;)Z
    //   5973: ifne -> 5983
    //   5976: goto -> 5983
    //   5979: invokestatic a : (Ljava/lang/Throwable;)Ljava/lang/Throwable;
    //   5982: athrow
    //   5983: aload #7
    //   5985: iconst_1
    //   5986: invokevirtual setAccessible : (Z)V
    //   5989: aload #7
    //   5991: aconst_null
    //   5992: invokevirtual get : (Ljava/lang/Object;)Ljava/lang/Object;
    //   5995: pop
    //   5996: iinc #6, 1
    //   5999: iload_2
    //   6000: ifne -> 5861
    //   6003: sipush #27801
    //   6006: sipush #24085
    //   6009: invokestatic a : (II)Ljava/lang/String;
    //   6012: invokestatic forName : (Ljava/lang/String;)Ljava/lang/Class;
    //   6015: invokevirtual getDeclaredMethods : ()[Ljava/lang/reflect/Method;
    //   6018: astore #4
    //   6020: aload #4
    //   6022: arraylength
    //   6023: istore #5
    //   6025: iconst_0
    //   6026: istore #6
    //   6028: iload #6
    //   6030: iload #5
    //   6032: if_icmpge -> 6168
    //   6035: aload #4
    //   6037: iload #6
    //   6039: aaload
    //   6040: astore #7
    //   6042: aload #7
    //   6044: invokevirtual getParameterTypes : ()[Ljava/lang/Class;
    //   6047: pop
    //   6048: aload #7
    //   6050: invokevirtual getModifiers : ()I
    //   6053: invokestatic isStatic : (I)Z
    //   6056: ifeq -> 6154
    //   6059: aload #7
    //   6061: invokevirtual getParameterTypes : ()[Ljava/lang/Class;
    //   6064: arraylength
    //   6065: iconst_2
    //   6066: if_icmpne -> 6154
    //   6069: goto -> 6076
    //   6072: invokestatic a : (Ljava/lang/Throwable;)Ljava/lang/Throwable;
    //   6075: athrow
    //   6076: aload #7
    //   6078: invokevirtual getReturnType : ()Ljava/lang/Class;
    //   6081: getstatic java/lang/Boolean.TYPE : Ljava/lang/Class;
    //   6084: if_acmpne -> 6154
    //   6087: goto -> 6094
    //   6090: invokestatic a : (Ljava/lang/Throwable;)Ljava/lang/Throwable;
    //   6093: athrow
    //   6094: aload #7
    //   6096: iconst_1
    //   6097: invokevirtual setAccessible : (Z)V
    //   6100: aload #7
    //   6102: aconst_null
    //   6103: iconst_2
    //   6104: anewarray java/lang/Object
    //   6107: dup
    //   6108: iconst_0
    //   6109: aload_0
    //   6110: aastore
    //   6111: dup
    //   6112: iconst_1
    //   6113: aload_1
    //   6114: ifnonnull -> 6132
    //   6117: goto -> 6124
    //   6120: invokestatic a : (Ljava/lang/Throwable;)Ljava/lang/Throwable;
    //   6123: athrow
    //   6124: aload_1
    //   6125: goto -> 6139
    //   6128: invokestatic a : (Ljava/lang/Throwable;)Ljava/lang/Throwable;
    //   6131: athrow
    //   6132: aload_1
    //   6133: checkcast [B
    //   6136: invokevirtual clone : ()Ljava/lang/Object;
    //   6139: aastore
    //   6140: invokevirtual invoke : (Ljava/lang/Object;[Ljava/lang/Object;)Ljava/lang/Object;
    //   6143: checkcast java/lang/Boolean
    //   6146: invokevirtual booleanValue : ()Z
    //   6149: istore_3
    //   6150: iload_2
    //   6151: ifne -> 6168
    //   6154: iinc #6, 1
    //   6157: iload_2
    //   6158: ifne -> 6028
    //   6161: goto -> 6168
    //   6164: invokestatic a : (Ljava/lang/Throwable;)Ljava/lang/Throwable;
    //   6167: athrow
    //   6168: iload_3
    //   6169: ifeq -> 6174
    //   6172: iload_3
    //   6173: ireturn
    //   6174: getstatic burp/Zgw_.ZH : Ljava/lang/String;
    //   6177: getstatic burp/Zb9h.Zm : Ljava/lang/Object;
    //   6180: checkcast java/math/BigInteger
    //   6183: invokevirtual intValue : ()I
    //   6186: bipush #32
    //   6188: irem
    //   6189: invokestatic abs : (I)I
    //   6192: invokevirtual charAt : (I)C
    //   6195: getstatic burp/Zg2.ZN : Ljava/lang/String;
    //   6198: getstatic burp/Zmrc.ZU : Ljava/lang/Object;
    //   6201: checkcast java/math/BigInteger
    //   6204: invokevirtual intValue : ()I
    //   6207: bipush #32
    //   6209: irem
    //   6210: invokestatic abs : (I)I
    //   6213: invokevirtual charAt : (I)C
    //   6216: if_icmpgt -> 6561
    //   6219: sipush #27800
    //   6222: sipush #10979
    //   6225: invokestatic a : (II)Ljava/lang/String;
    //   6228: iconst_1
    //   6229: ldc burp/Zcc
    //   6231: invokevirtual getClassLoader : ()Ljava/lang/ClassLoader;
    //   6234: invokestatic forName : (Ljava/lang/String;ZLjava/lang/ClassLoader;)Ljava/lang/Class;
    //   6237: invokevirtual getDeclaredFields : ()[Ljava/lang/reflect/Field;
    //   6240: astore #4
    //   6242: aload #4
    //   6244: arraylength
    //   6245: istore #5
    //   6247: iconst_0
    //   6248: istore #6
    //   6250: iload #6
    //   6252: iload #5
    //   6254: if_icmpge -> 6392
    //   6257: aload #4
    //   6259: iload #6
    //   6261: aaload
    //   6262: astore #7
    //   6264: aload #7
    //   6266: invokevirtual getModifiers : ()I
    //   6269: invokestatic isStatic : (I)Z
    //   6272: ifne -> 6282
    //   6275: goto -> 6385
    //   6278: invokestatic a : (Ljava/lang/Throwable;)Ljava/lang/Throwable;
    //   6281: athrow
    //   6282: aload #7
    //   6284: invokevirtual getType : ()Ljava/lang/Class;
    //   6287: astore #8
    //   6289: aload #8
    //   6291: ifnull -> 6372
    //   6294: aload #8
    //   6296: invokevirtual isPrimitive : ()Z
    //   6299: ifne -> 6372
    //   6302: goto -> 6309
    //   6305: invokestatic a : (Ljava/lang/Throwable;)Ljava/lang/Throwable;
    //   6308: athrow
    //   6309: aload #8
    //   6311: invokevirtual getPackage : ()Ljava/lang/Package;
    //   6314: ifnull -> 6372
    //   6317: goto -> 6324
    //   6320: invokestatic a : (Ljava/lang/Throwable;)Ljava/lang/Throwable;
    //   6323: athrow
    //   6324: aload #8
    //   6326: invokevirtual getPackage : ()Ljava/lang/Package;
    //   6329: invokevirtual getName : ()Ljava/lang/String;
    //   6332: ifnull -> 6372
    //   6335: goto -> 6342
    //   6338: invokestatic a : (Ljava/lang/Throwable;)Ljava/lang/Throwable;
    //   6341: athrow
    //   6342: aload #8
    //   6344: invokevirtual getPackage : ()Ljava/lang/Package;
    //   6347: invokevirtual getName : ()Ljava/lang/String;
    //   6350: sipush #27785
    //   6353: sipush #-1348
    //   6356: invokestatic a : (II)Ljava/lang/String;
    //   6359: invokevirtual startsWith : (Ljava/lang/String;)Z
    //   6362: ifne -> 6372
    //   6365: goto -> 6372
    //   6368: invokestatic a : (Ljava/lang/Throwable;)Ljava/lang/Throwable;
    //   6371: athrow
    //   6372: aload #7
    //   6374: iconst_1
    //   6375: invokevirtual setAccessible : (Z)V
    //   6378: aload #7
    //   6380: aconst_null
    //   6381: invokevirtual get : (Ljava/lang/Object;)Ljava/lang/Object;
    //   6384: pop
    //   6385: iinc #6, 1
    //   6388: iload_2
    //   6389: ifne -> 6250
    //   6392: sipush #27805
    //   6395: sipush #20260
    //   6398: invokestatic a : (II)Ljava/lang/String;
    //   6401: invokestatic forName : (Ljava/lang/String;)Ljava/lang/Class;
    //   6404: invokevirtual getDeclaredMethods : ()[Ljava/lang/reflect/Method;
    //   6407: astore #4
    //   6409: aload #4
    //   6411: arraylength
    //   6412: istore #5
    //   6414: iconst_0
    //   6415: istore #6
    //   6417: iload #6
    //   6419: iload #5
    //   6421: if_icmpge -> 6557
    //   6424: aload #4
    //   6426: iload #6
    //   6428: aaload
    //   6429: astore #7
    //   6431: aload #7
    //   6433: invokevirtual getParameterTypes : ()[Ljava/lang/Class;
    //   6436: pop
    //   6437: aload #7
    //   6439: invokevirtual getModifiers : ()I
    //   6442: invokestatic isStatic : (I)Z
    //   6445: ifeq -> 6543
    //   6448: aload #7
    //   6450: invokevirtual getParameterTypes : ()[Ljava/lang/Class;
    //   6453: arraylength
    //   6454: iconst_2
    //   6455: if_icmpne -> 6543
    //   6458: goto -> 6465
    //   6461: invokestatic a : (Ljava/lang/Throwable;)Ljava/lang/Throwable;
    //   6464: athrow
    //   6465: aload #7
    //   6467: invokevirtual getReturnType : ()Ljava/lang/Class;
    //   6470: getstatic java/lang/Boolean.TYPE : Ljava/lang/Class;
    //   6473: if_acmpne -> 6543
    //   6476: goto -> 6483
    //   6479: invokestatic a : (Ljava/lang/Throwable;)Ljava/lang/Throwable;
    //   6482: athrow
    //   6483: aload #7
    //   6485: iconst_1
    //   6486: invokevirtual setAccessible : (Z)V
    //   6489: aload #7
    //   6491: aconst_null
    //   6492: iconst_2
    //   6493: anewarray java/lang/Object
    //   6496: dup
    //   6497: iconst_0
    //   6498: aload_0
    //   6499: aastore
    //   6500: dup
    //   6501: iconst_1
    //   6502: aload_1
    //   6503: ifnonnull -> 6521
    //   6506: goto -> 6513
    //   6509: invokestatic a : (Ljava/lang/Throwable;)Ljava/lang/Throwable;
    //   6512: athrow
    //   6513: aload_1
    //   6514: goto -> 6528
    //   6517: invokestatic a : (Ljava/lang/Throwable;)Ljava/lang/Throwable;
    //   6520: athrow
    //   6521: aload_1
    //   6522: checkcast [B
    //   6525: invokevirtual clone : ()Ljava/lang/Object;
    //   6528: aastore
    //   6529: invokevirtual invoke : (Ljava/lang/Object;[Ljava/lang/Object;)Ljava/lang/Object;
    //   6532: checkcast java/lang/Boolean
    //   6535: invokevirtual booleanValue : ()Z
    //   6538: istore_3
    //   6539: iload_2
    //   6540: ifne -> 6557
    //   6543: iinc #6, 1
    //   6546: iload_2
    //   6547: ifne -> 6417
    //   6550: goto -> 6557
    //   6553: invokestatic a : (Ljava/lang/Throwable;)Ljava/lang/Throwable;
    //   6556: athrow
    //   6557: iload_2
    //   6558: ifne -> 6899
    //   6561: sipush #27778
    //   6564: sipush #2032
    //   6567: invokestatic a : (II)Ljava/lang/String;
    //   6570: iconst_1
    //   6571: ldc burp/Zkfa
    //   6573: invokevirtual getClassLoader : ()Ljava/lang/ClassLoader;
    //   6576: invokestatic forName : (Ljava/lang/String;ZLjava/lang/ClassLoader;)Ljava/lang/Class;
    //   6579: invokevirtual getDeclaredFields : ()[Ljava/lang/reflect/Field;
    //   6582: astore #4
    //   6584: aload #4
    //   6586: arraylength
    //   6587: istore #5
    //   6589: iconst_0
    //   6590: istore #6
    //   6592: iload #6
    //   6594: iload #5
    //   6596: if_icmpge -> 6734
    //   6599: aload #4
    //   6601: iload #6
    //   6603: aaload
    //   6604: astore #7
    //   6606: aload #7
    //   6608: invokevirtual getModifiers : ()I
    //   6611: invokestatic isStatic : (I)Z
    //   6614: ifne -> 6624
    //   6617: goto -> 6727
    //   6620: invokestatic a : (Ljava/lang/Throwable;)Ljava/lang/Throwable;
    //   6623: athrow
    //   6624: aload #7
    //   6626: invokevirtual getType : ()Ljava/lang/Class;
    //   6629: astore #8
    //   6631: aload #8
    //   6633: ifnull -> 6714
    //   6636: aload #8
    //   6638: invokevirtual isPrimitive : ()Z
    //   6641: ifne -> 6714
    //   6644: goto -> 6651
    //   6647: invokestatic a : (Ljava/lang/Throwable;)Ljava/lang/Throwable;
    //   6650: athrow
    //   6651: aload #8
    //   6653: invokevirtual getPackage : ()Ljava/lang/Package;
    //   6656: ifnull -> 6714
    //   6659: goto -> 6666
    //   6662: invokestatic a : (Ljava/lang/Throwable;)Ljava/lang/Throwable;
    //   6665: athrow
    //   6666: aload #8
    //   6668: invokevirtual getPackage : ()Ljava/lang/Package;
    //   6671: invokevirtual getName : ()Ljava/lang/String;
    //   6674: ifnull -> 6714
    //   6677: goto -> 6684
    //   6680: invokestatic a : (Ljava/lang/Throwable;)Ljava/lang/Throwable;
    //   6683: athrow
    //   6684: aload #8
    //   6686: invokevirtual getPackage : ()Ljava/lang/Package;
    //   6689: invokevirtual getName : ()Ljava/lang/String;
    //   6692: sipush #27785
    //   6695: sipush #-1348
    //   6698: invokestatic a : (II)Ljava/lang/String;
    //   6701: invokevirtual startsWith : (Ljava/lang/String;)Z
    //   6704: ifne -> 6714
    //   6707: goto -> 6714
    //   6710: invokestatic a : (Ljava/lang/Throwable;)Ljava/lang/Throwable;
    //   6713: athrow
    //   6714: aload #7
    //   6716: iconst_1
    //   6717: invokevirtual setAccessible : (Z)V
    //   6720: aload #7
    //   6722: aconst_null
    //   6723: invokevirtual get : (Ljava/lang/Object;)Ljava/lang/Object;
    //   6726: pop
    //   6727: iinc #6, 1
    //   6730: iload_2
    //   6731: ifne -> 6592
    //   6734: sipush #27798
    //   6737: sipush #-4289
    //   6740: invokestatic a : (II)Ljava/lang/String;
    //   6743: invokestatic forName : (Ljava/lang/String;)Ljava/lang/Class;
    //   6746: invokevirtual getDeclaredMethods : ()[Ljava/lang/reflect/Method;
    //   6749: astore #4
    //   6751: aload #4
    //   6753: arraylength
    //   6754: istore #5
    //   6756: iconst_0
    //   6757: istore #6
    //   6759: iload #6
    //   6761: iload #5
    //   6763: if_icmpge -> 6899
    //   6766: aload #4
    //   6768: iload #6
    //   6770: aaload
    //   6771: astore #7
    //   6773: aload #7
    //   6775: invokevirtual getParameterTypes : ()[Ljava/lang/Class;
    //   6778: pop
    //   6779: aload #7
    //   6781: invokevirtual getModifiers : ()I
    //   6784: invokestatic isStatic : (I)Z
    //   6787: ifeq -> 6885
    //   6790: aload #7
    //   6792: invokevirtual getParameterTypes : ()[Ljava/lang/Class;
    //   6795: arraylength
    //   6796: iconst_2
    //   6797: if_icmpne -> 6885
    //   6800: goto -> 6807
    //   6803: invokestatic a : (Ljava/lang/Throwable;)Ljava/lang/Throwable;
    //   6806: athrow
    //   6807: aload #7
    //   6809: invokevirtual getReturnType : ()Ljava/lang/Class;
    //   6812: getstatic java/lang/Boolean.TYPE : Ljava/lang/Class;
    //   6815: if_acmpne -> 6885
    //   6818: goto -> 6825
    //   6821: invokestatic a : (Ljava/lang/Throwable;)Ljava/lang/Throwable;
    //   6824: athrow
    //   6825: aload #7
    //   6827: iconst_1
    //   6828: invokevirtual setAccessible : (Z)V
    //   6831: aload #7
    //   6833: aconst_null
    //   6834: iconst_2
    //   6835: anewarray java/lang/Object
    //   6838: dup
    //   6839: iconst_0
    //   6840: aload_0
    //   6841: aastore
    //   6842: dup
    //   6843: iconst_1
    //   6844: aload_1
    //   6845: ifnonnull -> 6863
    //   6848: goto -> 6855
    //   6851: invokestatic a : (Ljava/lang/Throwable;)Ljava/lang/Throwable;
    //   6854: athrow
    //   6855: aload_1
    //   6856: goto -> 6870
    //   6859: invokestatic a : (Ljava/lang/Throwable;)Ljava/lang/Throwable;
    //   6862: athrow
    //   6863: aload_1
    //   6864: checkcast [B
    //   6867: invokevirtual clone : ()Ljava/lang/Object;
    //   6870: aastore
    //   6871: invokevirtual invoke : (Ljava/lang/Object;[Ljava/lang/Object;)Ljava/lang/Object;
    //   6874: checkcast java/lang/Boolean
    //   6877: invokevirtual booleanValue : ()Z
    //   6880: istore_3
    //   6881: iload_2
    //   6882: ifne -> 6899
    //   6885: iinc #6, 1
    //   6888: iload_2
    //   6889: ifne -> 6759
    //   6892: goto -> 6899
    //   6895: invokestatic a : (Ljava/lang/Throwable;)Ljava/lang/Throwable;
    //   6898: athrow
    //   6899: iload_3
    //   6900: ifeq -> 6905
    //   6903: iload_3
    //   6904: ireturn
    //   6905: getstatic burp/Zeb3.ZG : Ljava/lang/String;
    //   6908: getstatic burp/Zecw.ZE : Ljava/lang/Object;
    //   6911: checkcast java/math/BigInteger
    //   6914: invokevirtual intValue : ()I
    //   6917: bipush #32
    //   6919: irem
    //   6920: invokestatic abs : (I)I
    //   6923: invokevirtual charAt : (I)C
    //   6926: getstatic burp/Zelc.ZI : Ljava/lang/String;
    //   6929: getstatic burp/Zkf9.ZX : Ljava/lang/Object;
    //   6932: checkcast java/math/BigInteger
    //   6935: invokevirtual intValue : ()I
    //   6938: bipush #32
    //   6940: irem
    //   6941: invokestatic abs : (I)I
    //   6944: invokevirtual charAt : (I)C
    //   6947: if_icmple -> 7292
    //   6950: sipush #27792
    //   6953: sipush #-29162
    //   6956: invokestatic a : (II)Ljava/lang/String;
    //   6959: iconst_1
    //   6960: ldc burp/Zxdh
    //   6962: invokevirtual getClassLoader : ()Ljava/lang/ClassLoader;
    //   6965: invokestatic forName : (Ljava/lang/String;ZLjava/lang/ClassLoader;)Ljava/lang/Class;
    //   6968: invokevirtual getDeclaredFields : ()[Ljava/lang/reflect/Field;
    //   6971: astore #4
    //   6973: aload #4
    //   6975: arraylength
    //   6976: istore #5
    //   6978: iconst_0
    //   6979: istore #6
    //   6981: iload #6
    //   6983: iload #5
    //   6985: if_icmpge -> 7123
    //   6988: aload #4
    //   6990: iload #6
    //   6992: aaload
    //   6993: astore #7
    //   6995: aload #7
    //   6997: invokevirtual getModifiers : ()I
    //   7000: invokestatic isStatic : (I)Z
    //   7003: ifne -> 7013
    //   7006: goto -> 7116
    //   7009: invokestatic a : (Ljava/lang/Throwable;)Ljava/lang/Throwable;
    //   7012: athrow
    //   7013: aload #7
    //   7015: invokevirtual getType : ()Ljava/lang/Class;
    //   7018: astore #8
    //   7020: aload #8
    //   7022: ifnull -> 7103
    //   7025: aload #8
    //   7027: invokevirtual isPrimitive : ()Z
    //   7030: ifne -> 7103
    //   7033: goto -> 7040
    //   7036: invokestatic a : (Ljava/lang/Throwable;)Ljava/lang/Throwable;
    //   7039: athrow
    //   7040: aload #8
    //   7042: invokevirtual getPackage : ()Ljava/lang/Package;
    //   7045: ifnull -> 7103
    //   7048: goto -> 7055
    //   7051: invokestatic a : (Ljava/lang/Throwable;)Ljava/lang/Throwable;
    //   7054: athrow
    //   7055: aload #8
    //   7057: invokevirtual getPackage : ()Ljava/lang/Package;
    //   7060: invokevirtual getName : ()Ljava/lang/String;
    //   7063: ifnull -> 7103
    //   7066: goto -> 7073
    //   7069: invokestatic a : (Ljava/lang/Throwable;)Ljava/lang/Throwable;
    //   7072: athrow
    //   7073: aload #8
    //   7075: invokevirtual getPackage : ()Ljava/lang/Package;
    //   7078: invokevirtual getName : ()Ljava/lang/String;
    //   7081: sipush #27785
    //   7084: sipush #-1348
    //   7087: invokestatic a : (II)Ljava/lang/String;
    //   7090: invokevirtual startsWith : (Ljava/lang/String;)Z
    //   7093: ifne -> 7103
    //   7096: goto -> 7103
    //   7099: invokestatic a : (Ljava/lang/Throwable;)Ljava/lang/Throwable;
    //   7102: athrow
    //   7103: aload #7
    //   7105: iconst_1
    //   7106: invokevirtual setAccessible : (Z)V
    //   7109: aload #7
    //   7111: aconst_null
    //   7112: invokevirtual get : (Ljava/lang/Object;)Ljava/lang/Object;
    //   7115: pop
    //   7116: iinc #6, 1
    //   7119: iload_2
    //   7120: ifne -> 6981
    //   7123: sipush #27803
    //   7126: sipush #16374
    //   7129: invokestatic a : (II)Ljava/lang/String;
    //   7132: invokestatic forName : (Ljava/lang/String;)Ljava/lang/Class;
    //   7135: invokevirtual getDeclaredMethods : ()[Ljava/lang/reflect/Method;
    //   7138: astore #4
    //   7140: aload #4
    //   7142: arraylength
    //   7143: istore #5
    //   7145: iconst_0
    //   7146: istore #6
    //   7148: iload #6
    //   7150: iload #5
    //   7152: if_icmpge -> 7288
    //   7155: aload #4
    //   7157: iload #6
    //   7159: aaload
    //   7160: astore #7
    //   7162: aload #7
    //   7164: invokevirtual getParameterTypes : ()[Ljava/lang/Class;
    //   7167: pop
    //   7168: aload #7
    //   7170: invokevirtual getModifiers : ()I
    //   7173: invokestatic isStatic : (I)Z
    //   7176: ifeq -> 7274
    //   7179: aload #7
    //   7181: invokevirtual getParameterTypes : ()[Ljava/lang/Class;
    //   7184: arraylength
    //   7185: iconst_2
    //   7186: if_icmpne -> 7274
    //   7189: goto -> 7196
    //   7192: invokestatic a : (Ljava/lang/Throwable;)Ljava/lang/Throwable;
    //   7195: athrow
    //   7196: aload #7
    //   7198: invokevirtual getReturnType : ()Ljava/lang/Class;
    //   7201: getstatic java/lang/Boolean.TYPE : Ljava/lang/Class;
    //   7204: if_acmpne -> 7274
    //   7207: goto -> 7214
    //   7210: invokestatic a : (Ljava/lang/Throwable;)Ljava/lang/Throwable;
    //   7213: athrow
    //   7214: aload #7
    //   7216: iconst_1
    //   7217: invokevirtual setAccessible : (Z)V
    //   7220: aload #7
    //   7222: aconst_null
    //   7223: iconst_2
    //   7224: anewarray java/lang/Object
    //   7227: dup
    //   7228: iconst_0
    //   7229: aload_0
    //   7230: aastore
    //   7231: dup
    //   7232: iconst_1
    //   7233: aload_1
    //   7234: ifnonnull -> 7252
    //   7237: goto -> 7244
    //   7240: invokestatic a : (Ljava/lang/Throwable;)Ljava/lang/Throwable;
    //   7243: athrow
    //   7244: aload_1
    //   7245: goto -> 7259
    //   7248: invokestatic a : (Ljava/lang/Throwable;)Ljava/lang/Throwable;
    //   7251: athrow
    //   7252: aload_1
    //   7253: checkcast [B
    //   7256: invokevirtual clone : ()Ljava/lang/Object;
    //   7259: aastore
    //   7260: invokevirtual invoke : (Ljava/lang/Object;[Ljava/lang/Object;)Ljava/lang/Object;
    //   7263: checkcast java/lang/Boolean
    //   7266: invokevirtual booleanValue : ()Z
    //   7269: istore_3
    //   7270: iload_2
    //   7271: ifne -> 7288
    //   7274: iinc #6, 1
    //   7277: iload_2
    //   7278: ifne -> 7148
    //   7281: goto -> 7288
    //   7284: invokestatic a : (Ljava/lang/Throwable;)Ljava/lang/Throwable;
    //   7287: athrow
    //   7288: iload_2
    //   7289: ifne -> 7630
    //   7292: sipush #27789
    //   7295: sipush #-29325
    //   7298: invokestatic a : (II)Ljava/lang/String;
    //   7301: iconst_1
    //   7302: ldc burp/Ze0w
    //   7304: invokevirtual getClassLoader : ()Ljava/lang/ClassLoader;
    //   7307: invokestatic forName : (Ljava/lang/String;ZLjava/lang/ClassLoader;)Ljava/lang/Class;
    //   7310: invokevirtual getDeclaredFields : ()[Ljava/lang/reflect/Field;
    //   7313: astore #4
    //   7315: aload #4
    //   7317: arraylength
    //   7318: istore #5
    //   7320: iconst_0
    //   7321: istore #6
    //   7323: iload #6
    //   7325: iload #5
    //   7327: if_icmpge -> 7465
    //   7330: aload #4
    //   7332: iload #6
    //   7334: aaload
    //   7335: astore #7
    //   7337: aload #7
    //   7339: invokevirtual getModifiers : ()I
    //   7342: invokestatic isStatic : (I)Z
    //   7345: ifne -> 7355
    //   7348: goto -> 7458
    //   7351: invokestatic a : (Ljava/lang/Throwable;)Ljava/lang/Throwable;
    //   7354: athrow
    //   7355: aload #7
    //   7357: invokevirtual getType : ()Ljava/lang/Class;
    //   7360: astore #8
    //   7362: aload #8
    //   7364: ifnull -> 7445
    //   7367: aload #8
    //   7369: invokevirtual isPrimitive : ()Z
    //   7372: ifne -> 7445
    //   7375: goto -> 7382
    //   7378: invokestatic a : (Ljava/lang/Throwable;)Ljava/lang/Throwable;
    //   7381: athrow
    //   7382: aload #8
    //   7384: invokevirtual getPackage : ()Ljava/lang/Package;
    //   7387: ifnull -> 7445
    //   7390: goto -> 7397
    //   7393: invokestatic a : (Ljava/lang/Throwable;)Ljava/lang/Throwable;
    //   7396: athrow
    //   7397: aload #8
    //   7399: invokevirtual getPackage : ()Ljava/lang/Package;
    //   7402: invokevirtual getName : ()Ljava/lang/String;
    //   7405: ifnull -> 7445
    //   7408: goto -> 7415
    //   7411: invokestatic a : (Ljava/lang/Throwable;)Ljava/lang/Throwable;
    //   7414: athrow
    //   7415: aload #8
    //   7417: invokevirtual getPackage : ()Ljava/lang/Package;
    //   7420: invokevirtual getName : ()Ljava/lang/String;
    //   7423: sipush #27785
    //   7426: sipush #-1348
    //   7429: invokestatic a : (II)Ljava/lang/String;
    //   7432: invokevirtual startsWith : (Ljava/lang/String;)Z
    //   7435: ifne -> 7445
    //   7438: goto -> 7445
    //   7441: invokestatic a : (Ljava/lang/Throwable;)Ljava/lang/Throwable;
    //   7444: athrow
    //   7445: aload #7
    //   7447: iconst_1
    //   7448: invokevirtual setAccessible : (Z)V
    //   7451: aload #7
    //   7453: aconst_null
    //   7454: invokevirtual get : (Ljava/lang/Object;)Ljava/lang/Object;
    //   7457: pop
    //   7458: iinc #6, 1
    //   7461: iload_2
    //   7462: ifne -> 7323
    //   7465: sipush #27806
    //   7468: sipush #14525
    //   7471: invokestatic a : (II)Ljava/lang/String;
    //   7474: invokestatic forName : (Ljava/lang/String;)Ljava/lang/Class;
    //   7477: invokevirtual getDeclaredMethods : ()[Ljava/lang/reflect/Method;
    //   7480: astore #4
    //   7482: aload #4
    //   7484: arraylength
    //   7485: istore #5
    //   7487: iconst_0
    //   7488: istore #6
    //   7490: iload #6
    //   7492: iload #5
    //   7494: if_icmpge -> 7630
    //   7497: aload #4
    //   7499: iload #6
    //   7501: aaload
    //   7502: astore #7
    //   7504: aload #7
    //   7506: invokevirtual getParameterTypes : ()[Ljava/lang/Class;
    //   7509: pop
    //   7510: aload #7
    //   7512: invokevirtual getModifiers : ()I
    //   7515: invokestatic isStatic : (I)Z
    //   7518: ifeq -> 7616
    //   7521: aload #7
    //   7523: invokevirtual getParameterTypes : ()[Ljava/lang/Class;
    //   7526: arraylength
    //   7527: iconst_2
    //   7528: if_icmpne -> 7616
    //   7531: goto -> 7538
    //   7534: invokestatic a : (Ljava/lang/Throwable;)Ljava/lang/Throwable;
    //   7537: athrow
    //   7538: aload #7
    //   7540: invokevirtual getReturnType : ()Ljava/lang/Class;
    //   7543: getstatic java/lang/Boolean.TYPE : Ljava/lang/Class;
    //   7546: if_acmpne -> 7616
    //   7549: goto -> 7556
    //   7552: invokestatic a : (Ljava/lang/Throwable;)Ljava/lang/Throwable;
    //   7555: athrow
    //   7556: aload #7
    //   7558: iconst_1
    //   7559: invokevirtual setAccessible : (Z)V
    //   7562: aload #7
    //   7564: aconst_null
    //   7565: iconst_2
    //   7566: anewarray java/lang/Object
    //   7569: dup
    //   7570: iconst_0
    //   7571: aload_0
    //   7572: aastore
    //   7573: dup
    //   7574: iconst_1
    //   7575: aload_1
    //   7576: ifnonnull -> 7594
    //   7579: goto -> 7586
    //   7582: invokestatic a : (Ljava/lang/Throwable;)Ljava/lang/Throwable;
    //   7585: athrow
    //   7586: aload_1
    //   7587: goto -> 7601
    //   7590: invokestatic a : (Ljava/lang/Throwable;)Ljava/lang/Throwable;
    //   7593: athrow
    //   7594: aload_1
    //   7595: checkcast [B
    //   7598: invokevirtual clone : ()Ljava/lang/Object;
    //   7601: aastore
    //   7602: invokevirtual invoke : (Ljava/lang/Object;[Ljava/lang/Object;)Ljava/lang/Object;
    //   7605: checkcast java/lang/Boolean
    //   7608: invokevirtual booleanValue : ()Z
    //   7611: istore_3
    //   7612: iload_2
    //   7613: ifne -> 7630
    //   7616: iinc #6, 1
    //   7619: iload_2
    //   7620: ifne -> 7490
    //   7623: goto -> 7630
    //   7626: invokestatic a : (Ljava/lang/Throwable;)Ljava/lang/Throwable;
    //   7629: athrow
    //   7630: iload_3
    //   7631: ireturn
    //   7632: astore_3
    //   7633: new java/lang/Exception
    //   7636: dup
    //   7637: aload_3
    //   7638: invokevirtual getMessage : ()Ljava/lang/String;
    //   7641: invokespecial <init> : (Ljava/lang/String;)V
    //   7644: athrow
    // Exception table:
    //   from	to	target	type
    //   4	5442	7632	java/lang/Throwable
    //   3321	3346	3346	java/lang/Throwable
    //   4309	4335	4335	java/lang/Throwable
    //   4424	4438	4438	java/lang/Throwable
    //   4449	4462	4465	java/lang/Throwable
    //   4454	4477	4480	java/lang/Throwable
    //   4469	4495	4498	java/lang/Throwable
    //   4484	4525	4528	java/lang/Throwable
    //   4588	4615	4618	java/lang/Throwable
    //   4605	4636	4639	java/lang/Throwable
    //   4622	4666	4669	java/lang/Throwable
    //   4643	4677	4677	java/lang/Throwable
    //   4688	4704	4707	java/lang/Throwable
    //   4803	4817	4817	java/lang/Throwable
    //   4828	4841	4844	java/lang/Throwable
    //   4833	4856	4859	java/lang/Throwable
    //   4848	4874	4877	java/lang/Throwable
    //   4863	4904	4907	java/lang/Throwable
    //   4970	4997	5000	java/lang/Throwable
    //   4987	5015	5018	java/lang/Throwable
    //   5004	5045	5048	java/lang/Throwable
    //   5022	5056	5056	java/lang/Throwable
    //   5078	5089	5092	java/lang/Throwable
    //   5144	5158	5158	java/lang/Throwable
    //   5169	5182	5185	java/lang/Throwable
    //   5174	5197	5200	java/lang/Throwable
    //   5189	5215	5218	java/lang/Throwable
    //   5204	5245	5248	java/lang/Throwable
    //   5311	5338	5341	java/lang/Throwable
    //   5328	5356	5359	java/lang/Throwable
    //   5345	5386	5389	java/lang/Throwable
    //   5363	5397	5397	java/lang/Throwable
    //   5419	5430	5433	java/lang/Throwable
    //   5443	6173	7632	java/lang/Throwable
    //   5533	5547	5547	java/lang/Throwable
    //   5558	5571	5574	java/lang/Throwable
    //   5563	5586	5589	java/lang/Throwable
    //   5578	5604	5607	java/lang/Throwable
    //   5593	5634	5637	java/lang/Throwable
    //   5700	5727	5730	java/lang/Throwable
    //   5717	5745	5748	java/lang/Throwable
    //   5734	5775	5778	java/lang/Throwable
    //   5752	5786	5786	java/lang/Throwable
    //   5808	5819	5822	java/lang/Throwable
    //   5875	5889	5889	java/lang/Throwable
    //   5900	5913	5916	java/lang/Throwable
    //   5905	5928	5931	java/lang/Throwable
    //   5920	5946	5949	java/lang/Throwable
    //   5935	5976	5979	java/lang/Throwable
    //   6042	6069	6072	java/lang/Throwable
    //   6059	6087	6090	java/lang/Throwable
    //   6076	6117	6120	java/lang/Throwable
    //   6094	6128	6128	java/lang/Throwable
    //   6150	6161	6164	java/lang/Throwable
    //   6174	6904	7632	java/lang/Throwable
    //   6264	6278	6278	java/lang/Throwable
    //   6289	6302	6305	java/lang/Throwable
    //   6294	6317	6320	java/lang/Throwable
    //   6309	6335	6338	java/lang/Throwable
    //   6324	6365	6368	java/lang/Throwable
    //   6431	6458	6461	java/lang/Throwable
    //   6448	6476	6479	java/lang/Throwable
    //   6465	6506	6509	java/lang/Throwable
    //   6483	6517	6517	java/lang/Throwable
    //   6539	6550	6553	java/lang/Throwable
    //   6606	6620	6620	java/lang/Throwable
    //   6631	6644	6647	java/lang/Throwable
    //   6636	6659	6662	java/lang/Throwable
    //   6651	6677	6680	java/lang/Throwable
    //   6666	6707	6710	java/lang/Throwable
    //   6773	6800	6803	java/lang/Throwable
    //   6790	6818	6821	java/lang/Throwable
    //   6807	6848	6851	java/lang/Throwable
    //   6825	6859	6859	java/lang/Throwable
    //   6881	6892	6895	java/lang/Throwable
    //   6905	7631	7632	java/lang/Throwable
    //   6995	7009	7009	java/lang/Throwable
    //   7020	7033	7036	java/lang/Throwable
    //   7025	7048	7051	java/lang/Throwable
    //   7040	7066	7069	java/lang/Throwable
    //   7055	7096	7099	java/lang/Throwable
    //   7162	7189	7192	java/lang/Throwable
    //   7179	7207	7210	java/lang/Throwable
    //   7196	7237	7240	java/lang/Throwable
    //   7214	7248	7248	java/lang/Throwable
    //   7270	7281	7284	java/lang/Throwable
    //   7337	7351	7351	java/lang/Throwable
    //   7362	7375	7378	java/lang/Throwable
    //   7367	7390	7393	java/lang/Throwable
    //   7382	7408	7411	java/lang/Throwable
    //   7397	7438	7441	java/lang/Throwable
    //   7504	7531	7534	java/lang/Throwable
    //   7521	7549	7552	java/lang/Throwable
    //   7538	7579	7582	java/lang/Throwable
    //   7556	7590	7590	java/lang/Throwable
    //   7612	7623	7626	java/lang/Throwable
  }
  
  static void Zp(Object[] paramArrayOfObject, Object paramObject) throws Throwable {}
  
  static void ZV(Object paramObject) {
    Zm5p.ZX = a(27795, -7133);
    Zm5p.Ze = new BigInteger(a(27794, 22865));
    boolean bool = Zt2e.ZK();
    try {
      try {
        if (Zgw_.ZH.charAt(Math.abs(((BigInteger)Zro5.ZT).intValue() % 32)) <= Zgkn.ZV.charAt(Math.abs(((BigInteger)Zx4y.Zc).intValue() % 32))) {
          try {
            Zb2k.Zg(Class.forName(a(27786, -5334)));
            if (bool)
              Zttj.ZH(Class.forName(a(27802, -957))); 
          } catch (Throwable throwable) {
            throw a(null);
          } 
          return;
        } 
      } catch (Throwable throwable) {
        throw a(null);
      } 
      Zttj.ZH(Class.forName(a(27802, -957)));
    } catch (Throwable throwable) {}
  }
  
  static {
    // Byte code:
    //   0: bipush #29
    //   2: anewarray java/lang/String
    //   5: astore #5
    //   7: iconst_0
    //   8: istore_3
    //   9: ldc '/V}\\t/PV #RSFJ\\rV3=?!MUrl-l"RY17,|\\bqZT^pc\\ntA4bbkk4yop\\t u\\r\\trLK#!-\\t*H^M\\tlt#[6g\\tO;<A\\tCx\\tlH\\tjC9\\t"e&\\tlt^[e%\\t?L\\tB J9\\tH\\tz\\t]iV\\t(qJ3[\\t tS BIX&B\\tGGlZt4\\tdYlgp;Dz)Yc/L~J4W~3#^\07QF!aRqj\\r<yOkR\\bN!)+.VS~=% Ko&n{%Wrg9B^7'W'
    //   11: dup
    //   12: astore_2
    //   13: invokevirtual length : ()I
    //   16: istore #4
    //   18: bipush #9
    //   20: istore_1
    //   21: iconst_m1
    //   22: istore_0
    //   23: bipush #100
    //   25: iinc #0, 1
    //   28: aload_2
    //   29: iload_0
    //   30: dup
    //   31: iload_1
    //   32: iadd
    //   33: invokevirtual substring : (II)Ljava/lang/String;
    //   36: iconst_m1
    //   37: goto -> 143
    //   40: aload #5
    //   42: swap
    //   43: iload_3
    //   44: iinc #3, 1
    //   47: swap
    //   48: aastore
    //   49: iload_0
    //   50: iload_1
    //   51: iadd
    //   52: dup
    //   53: istore_0
    //   54: iload #4
    //   56: if_icmpge -> 68
    //   59: aload_2
    //   60: iload_0
    //   61: invokevirtual charAt : (I)C
    //   64: istore_1
    //   65: goto -> 23
    //   68: ldc '\\t\\t%5\\t)ZP'
    //   70: dup
    //   71: astore_2
    //   72: invokevirtual length : ()I
    //   75: istore #4
    //   77: bipush #8
    //   79: istore_1
    //   80: iconst_m1
    //   81: istore_0
    //   82: bipush #83
    //   84: iinc #0, 1
    //   87: aload_2
    //   88: iload_0
    //   89: dup
    //   90: iload_1
    //   91: iadd
    //   92: invokevirtual substring : (II)Ljava/lang/String;
    //   95: iconst_0
    //   96: goto -> 143
    //   99: aload #5
    //   101: swap
    //   102: iload_3
    //   103: iinc #3, 1
    //   106: swap
    //   107: aastore
    //   108: iload_0
    //   109: iload_1
    //   110: iadd
    //   111: dup
    //   112: istore_0
    //   113: iload #4
    //   115: if_icmpge -> 127
    //   118: aload_2
    //   119: iload_0
    //   120: invokevirtual charAt : (I)C
    //   123: istore_1
    //   124: goto -> 82
    //   127: aload #5
    //   129: putstatic burp/Zgwu.a : [Ljava/lang/String;
    //   132: bipush #29
    //   134: anewarray java/lang/String
    //   137: putstatic burp/Zgwu.b : [Ljava/lang/String;
    //   140: goto -> 300
    //   143: dup_x2
    //   144: pop
    //   145: invokevirtual toCharArray : ()[C
    //   148: dup_x1
    //   149: arraylength
    //   150: dup_x2
    //   151: pop
    //   152: iconst_0
    //   153: istore #6
    //   155: dup2_x1
    //   156: pop2
    //   157: dup_x2
    //   158: iconst_1
    //   159: if_icmpgt -> 260
    //   162: dup2
    //   163: swap
    //   164: iload #6
    //   166: dup2_x1
    //   167: caload
    //   168: swap
    //   169: iload #6
    //   171: bipush #7
    //   173: irem
    //   174: tableswitch default -> 242, 0 -> 212, 1 -> 217, 2 -> 222, 3 -> 227, 4 -> 232, 5 -> 237
    //   212: bipush #51
    //   214: goto -> 244
    //   217: bipush #23
    //   219: goto -> 244
    //   222: bipush #43
    //   224: goto -> 244
    //   227: bipush #99
    //   229: goto -> 244
    //   232: bipush #74
    //   234: goto -> 244
    //   237: bipush #14
    //   239: goto -> 244
    //   242: bipush #124
    //   244: ixor
    //   245: ixor
    //   246: i2c
    //   247: castore
    //   248: iinc #6, 1
    //   251: dup
    //   252: ifne -> 260
    //   255: dup2
    //   256: dup_x1
    //   257: goto -> 166
    //   260: dup2_x1
    //   261: pop2
    //   262: dup_x2
    //   263: iload #6
    //   265: if_icmpgt -> 162
    //   268: pop
    //   269: new java/lang/String
    //   272: dup_x1
    //   273: swap
    //   274: invokespecial <init> : ([C)V
    //   277: invokevirtual intern : ()Ljava/lang/String;
    //   280: swap
    //   281: pop
    //   282: swap
    //   283: tableswitch default -> 40, 0 -> 99
    //   300: new java/math/BigInteger
    //   303: dup
    //   304: sipush #27782
    //   307: sipush #-24012
    //   310: invokestatic a : (II)Ljava/lang/String;
    //   313: invokespecial <init> : (Ljava/lang/String;)V
    //   316: putstatic burp/Zgwu.ZD : Ljava/lang/Object;
    //   319: sipush #27781
    //   322: sipush #-21181
    //   325: invokestatic a : (II)Ljava/lang/String;
    //   328: putstatic burp/Zgwu.Zd : Ljava/lang/String;
    //   331: return
  }
  
  private static Throwable a(Throwable paramThrowable) {
    return paramThrowable;
  }
  
  private static String a(int paramInt1, int paramInt2) {
    int i = (paramInt1 ^ 0x6C91) & 0xFFFF;
    if (b[i] == null) {
      char[] arrayOfChar = a[i].toCharArray();
      switch (arrayOfChar[0] & 0xFF) {
        case 0:
        
        case 1:
        
        case 2:
        
        case 3:
        
        case 4:
        
        case 5:
        
        case 6:
        
        case 7:
        
        case 8:
        
        case 9:
        
        case 10:
        
        case 11:
        
        case 12:
        
        case 13:
        
        case 14:
        
        case 15:
        
        case 16:
        
        case 17:
        
        case 18:
        
        case 19:
        
        case 20:
        
        case 21:
        
        case 22:
        
        case 23:
        
        case 24:
        
        case 25:
        
        case 26:
        
        case 27:
        
        case 28:
        
        case 29:
        
        case 30:
        
        case 31:
        
        case 32:
        
        case 33:
        
        case 34:
        
        case 35:
        
        case 36:
        
        case 37:
        
        case 38:
        
        case 39:
        
        case 40:
        
        case 41:
        
        case 42:
        
        case 43:
        
        case 44:
        
        case 45:
        
        case 46:
        
        case 47:
        
        case 48:
        
        case 49:
        
        case 50:
        
        case 51:
        
        case 52:
        
        case 53:
        
        case 54:
        
        case 55:
        
        case 56:
        
        case 57:
        
        case 58:
        
        case 59:
        
        case 60:
        
        case 61:
        
        case 62:
        
        case 63:
        
        case 64:
        
        case 65:
        
        case 66:
        
        case 67:
        
        case 68:
        
        case 69:
        
        case 70:
        
        case 71:
        
        case 72:
        
        case 73:
        
        case 74:
        
        case 75:
        
        case 76:
        
        case 77:
        
        case 78:
        
        case 79:
        
        case 80:
        
        case 81:
        
        case 82:
        
        case 83:
        
        case 84:
        
        case 85:
        
        case 86:
        
        case 87:
        
        case 88:
        
        case 89:
        
        case 90:
        
        case 91:
        
        case 92:
        
        case 93:
        
        case 94:
        
        case 95:
        
        case 96:
        
        case 97:
        
        case 98:
        
        case 99:
        
        case 100:
        
        case 101:
        
        case 102:
        
        case 103:
        
        case 104:
        
        case 105:
        
        case 106:
        
        case 107:
        
        case 108:
        
        case 109:
        
        case 110:
        
        case 111:
        
        case 112:
        
        case 113:
        
        case 114:
        
        case 115:
        
        case 116:
        
        case 117:
        
        case 118:
        
        case 119:
        
        case 120:
        
        case 121:
        
        case 122:
        
        case 123:
        
        case 124:
        
        case 125:
        
        case 126:
        
        case 127:
        
        case 128:
        
        case 129:
        
        case 130:
        
        case 131:
        
        case 132:
        
        case 133:
        
        case 134:
        
        case 135:
        
        case 136:
        
        case 137:
        
        case 138:
        
        case 139:
        
        case 140:
        
        case 141:
        
        case 142:
        
        case 143:
        
        case 144:
        
        case 145:
        
        case 146:
        
        case 147:
        
        case 148:
        
        case 149:
        
        case 150:
        
        case 151:
        
        case 152:
        
        case 153:
        
        case 154:
        
        case 155:
        
        case 156:
        
        case 157:
        
        case 158:
        
        case 159:
        
        case 160:
        
        case 161:
        
        case 162:
        
        case 163:
        
        case 164:
        
        case 165:
        
        case 166:
        
        case 167:
        
        case 168:
        
        case 169:
        
        case 170:
        
        case 171:
        
        case 172:
        
        case 173:
        
        case 174:
        
        case 175:
        
        case 176:
        
        case 177:
        
        case 178:
        
        case 179:
        
        case 180:
        
        case 181:
        
        case 182:
        
        case 183:
        
        case 184:
        
        case 185:
        
        case 186:
        
        case 187:
        
        case 188:
        
        case 189:
        
        case 190:
        
        case 191:
        
        case 192:
        
        case 193:
        
        case 194:
        
        case 195:
        
        case 196:
        
        case 197:
        
        case 198:
        
        case 199:
        
        case 200:
        
        case 201:
        
        case 202:
        
        case 203:
        
        case 204:
        
        case 205:
        
        case 206:
        
        case 207:
        
        case 208:
        
        case 209:
        
        case 210:
        
        case 211:
        
        case 212:
        
        case 213:
        
        case 214:
        
        case 215:
        
        case 216:
        
        case 217:
        
        case 218:
        
        case 219:
        
        case 220:
        
        case 221:
        
        case 222:
        
        case 223:
        
        case 224:
        
        case 225:
        
        case 226:
        
        case 227:
        
        case 228:
        
        case 229:
        
        case 230:
        
        case 231:
        
        case 232:
        
        case 233:
        
        case 234:
        
        case 235:
        
        case 236:
        
        case 237:
        
        case 238:
        
        case 239:
        
        case 240:
        
        case 241:
        
        case 242:
        
        case 243:
        
        case 244:
        
        case 245:
        
        case 246:
        
        case 247:
        
        case 248:
        
        case 249:
        
        case 250:
        
        case 251:
        
        case 252:
        
        case 253:
        
        case 254:
        
        default:
          break;
      } 
      char c = '';
      int j = (paramInt2 & 0xFF) - c;
      if (j < 0)
        j += 256; 
      int k = ((paramInt2 & 0xFFFF) >>> 8) - c;
      if (k < 0)
        k += 256; 
      for (byte b = 0; b < arrayOfChar.length; b++) {
        int m = b % 2;
        if (m == 0) {
          arrayOfChar[b] = (char)(arrayOfChar[b] ^ j);
          j = ((j >>> 3 | j << 5) ^ arrayOfChar[b]) & 0xFF;
        } else {
          arrayOfChar[b] = (char)(arrayOfChar[b] ^ k);
          k = ((k >>> 3 | k << 5) ^ arrayOfChar[b]) & 0xFF;
        } 
      } 
      b[i] = (new String(arrayOfChar)).intern();
    } 
    return b[i];
  }
}


/* Location:              C:\Program Files\BurpSuitePro\burpsuite_pro.jar!\burp\Zgwu.class
 * Java compiler version: 21 (65.0)
 * JD-Core Version:       1.1.3
 */