package burp;

import java.nio.file.Path;
import java.util.Objects;
import java.util.Optional;
import net.portswigger.Zui;

public class Zgy2 {
  private static final Ztwv Zo;
  
  private final Zgb6 ZA;
  
  private final Zr_4 ZR;
  
  private final Zt4u ZH;
  
  private final Zerg ZJ;
  
  private final Zgzy Zz;
  
  private final Zskh Zp;
  
  private final Zz0n ZY;
  
  private final Zg1j Zq;
  
  private final Zkl6 Zs;
  
  private final Zr_4 Za;
  
  private final Zxl_ ZW;
  
  private final Zsxk Z_;
  
  private final Zlf2 ZO;
  
  private final Zr99 Zk;
  
  private final Zxg9 Zm;
  
  private final Zlyd Zj;
  
  private final Zbl2 ZI;
  
  private final Ztwv ZT;
  
  private final Ztyg Zy;
  
  private final Zgq7 ZK;
  
  private final Ze_7 ZB;
  
  private final Zrgk ZM;
  
  private final Ztrg Zf;
  
  private final Ze5p ZZ;
  
  private final Zlg9 Zb;
  
  private final Zr1m ZC;
  
  private final Zm6v ZL;
  
  private final Zkc6 Zr;
  
  private final Zs4c ZP;
  
  private final Zezx Zd;
  
  private final Zxx6 ZU;
  
  private final Zgdu Zc;
  
  private final Zldl Zg;
  
  private final Zskh Zl;
  
  private final Zbo9 Zw;
  
  private final Zkf1 Ze;
  
  private final Zrud Zx;
  
  private final Zgg0 ZG;
  
  private final Zkee ZX;
  
  private final Zb86 Zh;
  
  private final Zsxe ZS;
  
  private final Zexp ZN;
  
  private final Zxy1 Zn;
  
  private static final String[] a;
  
  private static final String[] b;
  
  public Zgy2(Zz0n paramZz0n, Zt4u paramZt4u, Zerg paramZerg, Zgb6 paramZgb6, Zgzy paramZgzy, Zskh paramZskh, Zg1j paramZg1j, Zkl6 paramZkl6, Ze_7 paramZe_7, Zlf2 paramZlf2, Zr99 paramZr99, Zxg9 paramZxg9, Zlyd paramZlyd, Zbl2 paramZbl2, Ztyg paramZtyg, Zgq7 paramZgq7, Ztwv paramZtwv, Zr_4 paramZr_41, Zr_4 paramZr_42, Zrgk paramZrgk, Ztrg paramZtrg, Ze5p paramZe5p, Zxl_ paramZxl_, Zsxk paramZsxk, Zlg9 paramZlg9, Zr1m paramZr1m, Zm6v paramZm6v, Zkc6 paramZkc6, Zs4c paramZs4c, Zezx paramZezx, Zxx6 paramZxx6, Zgdu paramZgdu, Zldl paramZldl, Zrud paramZrud, Zkf1 paramZkf1, Zlcb paramZlcb, Zkee paramZkee, Zb86 paramZb86, Zbo9 paramZbo9, Zexp paramZexp, Zxy1 paramZxy1) {
    this.ZY = paramZz0n;
    this.ZH = paramZt4u;
    this.ZJ = paramZerg;
    this.ZA = paramZgb6;
    this.Zz = paramZgzy;
    this.Zp = paramZskh;
    this.Zs = paramZkl6;
    this.Zq = paramZg1j;
    this.Za = paramZr_42;
    this.ZW = paramZxl_;
    String str = Zbk_.Zb();
    this.Z_ = paramZsxk;
    this.ZB = paramZe_7;
    this.ZO = paramZlf2;
    this.Zk = paramZr99;
    this.Zm = paramZxg9;
    this.Zj = paramZlyd;
    this.ZI = paramZbl2;
    this.Zy = paramZtyg;
    this.ZK = paramZgq7;
    this.ZT = paramZtwv;
    this.ZR = paramZr_41;
    this.ZM = paramZrgk;
    this.Zf = paramZtrg;
    this.ZZ = paramZe5p;
    this.Zb = paramZlg9;
    this.ZC = Objects.<Zr1m>requireNonNull(paramZr1m);
    this.ZL = Objects.<Zm6v>requireNonNull(paramZm6v);
    this.Zr = paramZkc6;
    this.ZP = paramZs4c;
    this.Zd = paramZezx;
    this.ZU = paramZxx6;
    this.Zc = paramZgdu;
    this.Zg = paramZldl;
    this.Zx = paramZrud;
    this.Ze = paramZkf1;
    this.ZX = paramZkee;
    this.Zh = paramZb86;
    this.Zw = paramZbo9;
    this.ZN = paramZexp;
    this.Zn = paramZxy1;
    this.Zl = paramZerg.ZU(Zeew.TARGET) ? paramZerg.Zj().ZY4() : Zskh.Zo;
    this.ZG = paramZerg.ZU(Zeew.TARGET) ? paramZlcb.ZW(Zeew.TARGET) : Zgg0.ZC;
    this.ZS = new Zsxe(this.Zl);
    if (Zbqc.Zwu() == null)
      Zbk_.ZL("WYscgb"); 
  }
  
  public Zbk1 Zn() {
    return new Zbk1(this.ZA, this.ZC);
  }
  
  public Zba5 ZI() {
    Ztr0 ztr0 = new Ztr0(this.ZN);
    return new Zba5(ztr0);
  }
  
  public Zbk6 ZB() {
    return new Zbk6(this.ZA, this.ZC);
  }
  
  public Zbae ZO() {
    return new Zbae(this.ZA, this.ZC);
  }
  
  public Zbaa ZC() {
    return new Zbaa(this.ZA, this.ZC);
  }
  
  public Zbkp Zu() {
    return new Zbkp(this.ZA, this.ZC);
  }
  
  public Zbap Zx() {
    return new Zbap(this.ZA, this.ZC);
  }
  
  public Zba2 Zk() {
    return new Zba2(this.ZA, this.ZC);
  }
  
  public Zba9 ZJ(Ztsr paramZtsr) {
    return new Zba9(this.ZH, this.Zp, this.ZP, this.Zd, this.ZY.ZM(), paramZtsr);
  }
  
  public Zbam ZW() {
    return new Zbam(this.ZH, this.ZJ, this.ZA, this.ZC);
  }
  
  public Zba4 Zt() {
    return new Zba4(this.ZA, this.ZC, this.Zw);
  }
  
  public Zbar ZU() {
    return new Zbar(this.ZA, this.ZC);
  }
  
  public Zbag ZH() {
    return new Zbag(this.ZA, this.ZC);
  }
  
  public Zba0 Zp() {
    return new Zba0(this.ZU, this.ZA, this.ZC, this.ZR);
  }
  
  public Zbkx Zo() {
    return new Zbkx(this.ZA, this.ZC);
  }
  
  public Zbas ZY() {
    return new Zbas(this.ZA, this.ZC);
  }
  
  public Zbk4 ZJ() {
    Zrgz zrgz = new Zrgz(this.ZN);
    return new Zbk4(zrgz);
  }
  
  public Zba1 ZM() {
    Optional optional = Optional.<Path>ofNullable(Zui.ZD(StartBurp.class)).map(Path::getParent);
    Optional<Zs53> optional1 = optional.filter(Zs53::ZS).or(optional::lambda$createConfigPanelConfigureJvmRamUsage$0).map(Zgy2::lambda$createConfigPanelConfigureJvmRamUsage$1).map(this::lambda$createConfigPanelConfigureJvmRamUsage$2);
    if (optional1.isPresent())
      return new Zba1(optional1.get()); 
    Zs53 zs53 = new Zs53(Path.of(a(276, 22772), new String[0]), Zo);
    Zba1 zba1 = new Zba1(zs53);
    zba1.ZZ();
    return zba1;
  }
  
  public Zbac Zm() {
    return new Zbac(this.ZY, this.ZA, this.Zq, this.ZC);
  }
  
  public Zbks Z_() {
    return new Zbks(this.Zx, new Zr1m(this.ZH, this.Zx.ZZ(), this.ZP, this.ZY.ZM()), this.Ze);
  }
  
  public Zbkz Zj() {
    return new Zbkz(this.ZA, this.ZC);
  }
  
  public Zbk3 Zq() {
    return new Zbk3(this.ZM, this.Zf, this.ZZ, this.ZC);
  }
  
  public Zbkl ZD() {
    return new Zbkl(this.ZY, this.ZH, this.Zl, this.ZA, this.Zz, this.Zs.Zq(), this.Zs.ZB(), this.ZR, this.ZC);
  }
  
  public Zbak ZR() {
    return new Zbak(this.ZY, this.ZH, this.Zl, this.ZA, this.Zz, this.Zs.Zq(), this.Zs.ZB(), this.ZR, this.ZC);
  }
  
  public Zbkw Zy() {
    return new Zbkw(this.ZA, this.ZC);
  }
  
  public Zbad Zi() {
    return new Zbad(this.Zm, this.Zj, this.Za, this.ZR, this.ZC);
  }
  
  public Zbkf ZP() {
    return new Zbkf(this.ZO, this.Zk, this.Zp, this.ZC);
  }
  
  public Zbkj ZQ() {
    return new Zbkj(this.ZA, this.ZC);
  }
  
  public Zbaq ZV() {
    return new Zbaq(this.ZA, this.ZC);
  }
  
  public Zbah ZG() {
    return new Zbah(this.ZA, this.ZC);
  }
  
  public Zbai Zz() {
    return new Zbai(this.Zs.Zd().ZX(), this.ZR, this.ZC);
  }
  
  public Zbk_ Zc() {
    return new Zbk_(this.ZA, this.Zs, this.ZC);
  }
  
  public Zbkn ZL() {
    return new Zbkn(this.ZY, this.ZH, this.ZA, this.Zp, this.ZI, this.ZW, this.Z_, this.ZT, this.Za, this.ZR, this.ZC);
  }
  
  public Zbk0 ZA() {
    return new Zbk0(this.Zz.Z_(), this.ZA, this.ZY.ZD(), this.ZT);
  }
  
  public Zbat Zd() {
    return new Zbat(this.ZA, this.ZC);
  }
  
  public Zbk8 Zj(Zslu paramZslu, Zlaa paramZlaa) {
    Ze4m ze4m = Zj(paramZlaa);
    Objects.requireNonNull(this.ZY);
    Zmxr zmxr = Zmxr.ZW(this.ZY.ZP(), this.ZY.ZU(), this.ZY::ZZ, this.ZA, this.Zz, paramZslu, this.Zs, this.Zl, this.ZT, this.Zr, this.Zb, this.ZG, this.Zn, this.ZS);
    return new Zbk8(this.ZY, this.ZH, this.ZJ, this.Zl, this.ZA, this.Zz, paramZslu, this.Zs, this.ZT, this.ZR, this.Za, this.Zy, this.ZK, zmxr, this.ZC, ze4m);
  }
  
  public Zbau Zv() {
    return new Zbau(this.ZA, this.Zz.Zh(), this.ZC);
  }
  
  public Zbab Zq(Zz28 paramZz28, Zlaa paramZlaa) {
    Ze4m ze4m = Zj(paramZlaa);
    Objects.requireNonNull(this.ZY);
    Zmxr zmxr = Zmxr.ZW(this.ZY.ZP(), this.ZY.ZU(), this.ZY::ZZ, this.ZA, this.Zz, paramZz28, this.Zs, this.Zl, this.ZT, this.Zr, this.Zb, this.ZG, this.Zn, this.ZS);
    return new Zbab(this.ZY, this.ZJ, this.ZA, this.Zz, this.Zs, this.ZT, this.ZR, this.Zy, this.ZK, this.ZC, zmxr, ze4m);
  }
  
  public Zbko Zg() {
    return new Zbko(this.Zz.Zw(), this.ZC);
  }
  
  public Zba3 ZK() {
    return new Zba3(this.ZA, this.Zs, this.ZB, this.ZT, this.ZR, this.ZY.ZP(), this.ZY.ZU(), this.ZC);
  }
  
  public Zba7 ZN() {
    return new Zba7(this.ZA, this.ZC);
  }
  
  public Zbay Ze() {
    return new Zbay(this.ZC, this.Zc, this.Zg);
  }
  
  public Zbav ZH(Zxgc paramZxgc) {
    return new Zbav(paramZxgc, this.ZA, this.ZC);
  }
  
  public Zbmb ZE() {
    Zr1m zr1m = this.ZL.ZL(this.ZX);
    return Zzj4.ZD(this.ZX, zr1m);
  }
  
  public Zbmm ZX() {
    Zr1m zr1m = this.ZL.ZL(this.ZX);
    return new Zbmm(this.ZX, zr1m, this.ZA);
  }
  
  public Zbmb Za() {
    Zr1m zr1m = this.ZL.ZL(this.Zh.Zc());
    return Zzj4.Zj(this.Zh, zr1m);
  }
  
  public Zbmb Zw() {
    Zr1m zr1m = this.ZL.ZL(this.Zh.Zq());
    return Zzj4.ZH(this.Zh, zr1m);
  }
  
  private Ze4m Zj(Zlaa paramZlaa) {
    return new Zsn2(paramZlaa.Zk(Zeew.TARGET, this.Zl, this.ZG), this.Zl, this.ZA);
  }
  
  private Zs53 lambda$createConfigPanelConfigureJvmRamUsage$2(Path paramPath) {
    return new Zs53(paramPath, this.ZT);
  }
  
  private static Path lambda$createConfigPanelConfigureJvmRamUsage$1(Path paramPath) {
    return paramPath.resolve(a(277, -32356));
  }
  
  private static Optional lambda$createConfigPanelConfigureJvmRamUsage$0(Optional paramOptional) {
    return paramOptional.map(Path::getParent).map(Path::getParent).filter(Zs53::ZS);
  }
  
  static {
    // Byte code:
    //   0: iconst_2
    //   1: anewarray java/lang/String
    //   4: astore #5
    //   6: iconst_0
    //   7: istore_3
    //   8: ldc '&/8Ã³Ã7Ã•FÃ·+ÂƒmaÃœÂ±&.Âž|ÃŸn Ã—e`'eÃ‚GÃ¾'
    //   10: dup
    //   11: astore_2
    //   12: invokevirtual length : ()I
    //   15: istore #4
    //   17: bipush #16
    //   19: istore_1
    //   20: iconst_m1
    //   21: istore_0
    //   22: bipush #72
    //   24: iinc #0, 1
    //   27: aload_2
    //   28: iload_0
    //   29: dup
    //   30: iload_1
    //   31: iadd
    //   32: invokevirtual substring : (II)Ljava/lang/String;
    //   35: iconst_m1
    //   36: goto -> 82
    //   39: aload #5
    //   41: swap
    //   42: iload_3
    //   43: iinc #3, 1
    //   46: swap
    //   47: aastore
    //   48: iload_0
    //   49: iload_1
    //   50: iadd
    //   51: dup
    //   52: istore_0
    //   53: iload #4
    //   55: if_icmpge -> 67
    //   58: aload_2
    //   59: iload_0
    //   60: invokevirtual charAt : (I)C
    //   63: istore_1
    //   64: goto -> 22
    //   67: aload #5
    //   69: putstatic burp/Zgy2.a : [Ljava/lang/String;
    //   72: iconst_2
    //   73: anewarray java/lang/String
    //   76: putstatic burp/Zgy2.b : [Ljava/lang/String;
    //   79: goto -> 227
    //   82: dup_x2
    //   83: pop
    //   84: invokevirtual toCharArray : ()[C
    //   87: dup_x1
    //   88: arraylength
    //   89: dup_x2
    //   90: pop
    //   91: iconst_0
    //   92: istore #6
    //   94: dup2_x1
    //   95: pop2
    //   96: dup_x2
    //   97: iconst_1
    //   98: if_icmpgt -> 200
    //   101: dup2
    //   102: swap
    //   103: iload #6
    //   105: dup2_x1
    //   106: caload
    //   107: swap
    //   108: iload #6
    //   110: bipush #7
    //   112: irem
    //   113: tableswitch default -> 182, 0 -> 152, 1 -> 157, 2 -> 162, 3 -> 167, 4 -> 172, 5 -> 177
    //   152: bipush #27
    //   154: goto -> 184
    //   157: bipush #125
    //   159: goto -> 184
    //   162: bipush #83
    //   164: goto -> 184
    //   167: bipush #9
    //   169: goto -> 184
    //   172: bipush #102
    //   174: goto -> 184
    //   177: bipush #91
    //   179: goto -> 184
    //   182: bipush #18
    //   184: ixor
    //   185: ixor
    //   186: i2c
    //   187: castore
    //   188: iinc #6, 1
    //   191: dup
    //   192: ifne -> 200
    //   195: dup2
    //   196: dup_x1
    //   197: goto -> 105
    //   200: dup2_x1
    //   201: pop2
    //   202: dup_x2
    //   203: iload #6
    //   205: if_icmpgt -> 101
    //   208: pop
    //   209: new java/lang/String
    //   212: dup_x1
    //   213: swap
    //   214: invokespecial <init> : ([C)V
    //   217: invokevirtual intern : ()Ljava/lang/String;
    //   220: swap
    //   221: pop
    //   222: swap
    //   223: pop
    //   224: goto -> 39
    //   227: new burp/Zsiz
    //   230: dup
    //   231: invokespecial <init> : ()V
    //   234: putstatic burp/Zgy2.Zo : Lburp/Ztwv;
    //   237: return
  }
  
  private static String a(int paramInt1, int paramInt2) {
    int i = (paramInt1 ^ 0x114) & 0xFFFF;
    if (b[i] == null) {
      char[] arrayOfChar = a[i].toCharArray();
      switch (arrayOfChar[0] & 0xFF) {
        case 0:
        
        case 1:
        
        case 2:
        
        case 3:
        
        case 4:
        
        case 5:
        
        case 6:
        
        case 7:
        
        case 8:
        
        case 9:
        
        case 10:
        
        case 11:
        
        case 12:
        
        case 13:
        
        case 14:
        
        case 15:
        
        case 16:
        
        case 17:
        
        case 18:
        
        case 19:
        
        case 20:
        
        case 21:
        
        case 22:
        
        case 23:
        
        case 24:
        
        case 25:
        
        case 26:
        
        case 27:
        
        case 28:
        
        case 29:
        
        case 30:
        
        case 31:
        
        case 32:
        
        case 33:
        
        case 34:
        
        case 35:
        
        case 36:
        
        case 37:
        
        case 38:
        
        case 39:
        
        case 40:
        
        case 41:
        
        case 42:
        
        case 43:
        
        case 44:
        
        case 45:
        
        case 46:
        
        case 47:
        
        case 48:
        
        case 49:
        
        case 50:
        
        case 51:
        
        case 52:
        
        case 53:
        
        case 54:
        
        case 55:
        
        case 56:
        
        case 57:
        
        case 58:
        
        case 59:
        
        case 60:
        
        case 61:
        
        case 62:
        
        case 63:
        
        case 64:
        
        case 65:
        
        case 66:
        
        case 67:
        
        case 68:
        
        case 69:
        
        case 70:
        
        case 71:
        
        case 72:
        
        case 73:
        
        case 74:
        
        case 75:
        
        case 76:
        
        case 77:
        
        case 78:
        
        case 79:
        
        case 80:
        
        case 81:
        
        case 82:
        
        case 83:
        
        case 84:
        
        case 85:
        
        case 86:
        
        case 87:
        
        case 88:
        
        case 89:
        
        case 90:
        
        case 91:
        
        case 92:
        
        case 93:
        
        case 94:
        
        case 95:
        
        case 96:
        
        case 97:
        
        case 98:
        
        case 99:
        
        case 100:
        
        case 101:
        
        case 102:
        
        case 103:
        
        case 104:
        
        case 105:
        
        case 106:
        
        case 107:
        
        case 108:
        
        case 109:
        
        case 110:
        
        case 111:
        
        case 112:
        
        case 113:
        
        case 114:
        
        case 115:
        
        case 116:
        
        case 117:
        
        case 118:
        
        case 119:
        
        case 120:
        
        case 121:
        
        case 122:
        
        case 123:
        
        case 124:
        
        case 125:
        
        case 126:
        
        case 127:
        
        case 128:
        
        case 129:
        
        case 130:
        
        case 131:
        
        case 132:
        
        case 133:
        
        case 134:
        
        case 135:
        
        case 136:
        
        case 137:
        
        case 138:
        
        case 139:
        
        case 140:
        
        case 141:
        
        case 142:
        
        case 143:
        
        case 144:
        
        case 145:
        
        case 146:
        
        case 147:
        
        case 148:
        
        case 149:
        
        case 150:
        
        case 151:
        
        case 152:
        
        case 153:
        
        case 154:
        
        case 155:
        
        case 156:
        
        case 157:
        
        case 158:
        
        case 159:
        
        case 160:
        
        case 161:
        
        case 162:
        
        case 163:
        
        case 164:
        
        case 165:
        
        case 166:
        
        case 167:
        
        case 168:
        
        case 169:
        
        case 170:
        
        case 171:
        
        case 172:
        
        case 173:
        
        case 174:
        
        case 175:
        
        case 176:
        
        case 177:
        
        case 178:
        
        case 179:
        
        case 180:
        
        case 181:
        
        case 182:
        
        case 183:
        
        case 184:
        
        case 185:
        
        case 186:
        
        case 187:
        
        case 188:
        
        case 189:
        
        case 190:
        
        case 191:
        
        case 192:
        
        case 193:
        
        case 194:
        
        case 195:
        
        case 196:
        
        case 197:
        
        case 198:
        
        case 199:
        
        case 200:
        
        case 201:
        
        case 202:
        
        case 203:
        
        case 204:
        
        case 205:
        
        case 206:
        
        case 207:
        
        case 208:
        
        case 209:
        
        case 210:
        
        case 211:
        
        case 212:
        
        case 213:
        
        case 214:
        
        case 215:
        
        case 216:
        
        case 217:
        
        case 218:
        
        case 219:
        
        case 220:
        
        case 221:
        
        case 222:
        
        case 223:
        
        case 224:
        
        case 225:
        
        case 226:
        
        case 227:
        
        case 228:
        
        case 229:
        
        case 230:
        
        case 231:
        
        case 232:
        
        case 233:
        
        case 234:
        
        case 235:
        
        case 236:
        
        case 237:
        
        case 238:
        
        case 239:
        
        case 240:
        
        case 241:
        
        case 242:
        
        case 243:
        
        case 244:
        
        case 245:
        
        case 246:
        
        case 247:
        
        case 248:
        
        case 249:
        
        case 250:
        
        case 251:
        
        case 252:
        
        case 253:
        
        case 254:
        
        default:
          break;
      } 
      byte b1 = 27;
      int j = (paramInt2 & 0xFF) - b1;
      if (j < 0)
        j += 256; 
      int k = ((paramInt2 & 0xFFFF) >>> 8) - b1;
      if (k < 0)
        k += 256; 
      for (byte b2 = 0; b2 < arrayOfChar.length; b2++) {
        int m = b2 % 2;
        if (m == 0) {
          arrayOfChar[b2] = (char)(arrayOfChar[b2] ^ j);
          j = ((j >>> 3 | j << 5) ^ arrayOfChar[b2]) & 0xFF;
        } else {
          arrayOfChar[b2] = (char)(arrayOfChar[b2] ^ k);
          k = ((k >>> 3 | k << 5) ^ arrayOfChar[b2]) & 0xFF;
        } 
      } 
      b[i] = (new String(arrayOfChar)).intern();
    } 
    return b[i];
  }
}


/* Location:              C:\Program Files\BurpSuitePro\burpsuite_pro.jar!\burp\Zgy2.class
 * Java compiler version: 21 (65.0)
 * JD-Core Version:       1.1.3
 */