package burp;

public class Zgyn implements Zk8x {
  private static final byte[] Zh;
  
  public Short ZT(Zstu paramZstu, Zm7o paramZm7o) {
    return Zlt_.ZL(paramZstu, Zh, false, paramZm7o.Zz()) ? Short.valueOf((short)262) : Short.valueOf((short)1);
  }
  
  static {
    // Byte code:
    //   0: bipush #90
    //   2: ldc 'HO,+5f\\nP"1(f\\nQ*;?u'
    //   4: iconst_m1
    //   5: goto -> 12
    //   8: astore_0
    //   9: goto -> 153
    //   12: dup_x2
    //   13: pop
    //   14: invokevirtual toCharArray : ()[C
    //   17: dup_x1
    //   18: arraylength
    //   19: dup_x2
    //   20: pop
    //   21: iconst_0
    //   22: istore_1
    //   23: dup2_x1
    //   24: pop2
    //   25: dup_x2
    //   26: iconst_1
    //   27: if_icmpgt -> 127
    //   30: dup2
    //   31: swap
    //   32: iload_1
    //   33: dup2_x1
    //   34: caload
    //   35: swap
    //   36: iload_1
    //   37: bipush #7
    //   39: irem
    //   40: tableswitch default -> 109, 0 -> 80, 1 -> 85, 2 -> 90, 3 -> 95, 4 -> 100, 5 -> 104
    //   80: bipush #46
    //   82: goto -> 111
    //   85: bipush #63
    //   87: goto -> 111
    //   90: bipush #103
    //   92: goto -> 111
    //   95: bipush #25
    //   97: goto -> 111
    //   100: iconst_2
    //   101: goto -> 111
    //   104: bipush #28
    //   106: goto -> 111
    //   109: bipush #17
    //   111: ixor
    //   112: ixor
    //   113: i2c
    //   114: castore
    //   115: iinc #1, 1
    //   118: dup
    //   119: ifne -> 127
    //   122: dup2
    //   123: dup_x1
    //   124: goto -> 33
    //   127: dup2_x1
    //   128: pop2
    //   129: dup_x2
    //   130: iload_1
    //   131: if_icmpgt -> 30
    //   134: pop
    //   135: new java/lang/String
    //   138: dup_x1
    //   139: swap
    //   140: invokespecial <init> : ([C)V
    //   143: invokevirtual intern : ()Ljava/lang/String;
    //   146: swap
    //   147: pop
    //   148: swap
    //   149: pop
    //   150: goto -> 8
    //   153: aload_0
    //   154: invokestatic Zy : (Ljava/lang/String;)[B
    //   157: putstatic burp/Zgyn.Zh : [B
    //   160: return
  }
}


/* Location:              C:\Program Files\BurpSuitePro\burpsuite_pro.jar!\burp\Zgyn.class
 * Java compiler version: 21 (65.0)
 * JD-Core Version:       1.1.3
 */