package burp;

import java.math.BigInteger;

class Zk7e extends ClassLoader {
  static String ZP;
  
  static Object ZW;
  
  private static final String[] a;
  
  private static final String[] b;
  
  static void Zc(Object paramObject) {
    Zkjr.Zg = a(-17421, 30308);
    Zkjr.Zw = new BigInteger(a(-17422, -14431));
    boolean bool = Zt2e.ZK();
    try {
      try {
        if (Zzo5.ZX.charAt(Math.abs(((BigInteger)Zex.ZO).intValue() % 32)) <= Zlck.ZL.charAt(Math.abs(((BigInteger)Zr2i.ZD).intValue() % 32))) {
          try {
            Zg_5.Zg(Class.forName(a(-17419, -2743)));
            if (bool)
              Zb8y.ZO(Class.forName(a(-17424, -20865))); 
          } catch (Throwable throwable) {
            throw a(null);
          } 
          return;
        } 
      } catch (Throwable throwable) {
        throw a(null);
      } 
      Zb8y.ZO(Class.forName(a(-17424, -20865)));
    } catch (Throwable throwable) {}
  }
  
  static boolean ZV(Object[] paramArrayOfObject, Object paramObject) throws Throwable {
    // Byte code:
    //   0: invokestatic ZN : ()Z
    //   3: istore_2
    //   4: getstatic burp/Zm3p.Zz : Ljava/lang/Object;
    //   7: checkcast java/math/BigInteger
    //   10: invokevirtual toByteArray : ()[B
    //   13: astore_3
    //   14: aload_3
    //   15: arraylength
    //   16: iconst_2
    //   17: iadd
    //   18: newarray byte
    //   20: astore #5
    //   22: iconst_0
    //   23: istore #6
    //   25: iload #6
    //   27: aload_3
    //   28: arraylength
    //   29: if_icmpge -> 48
    //   32: aload #5
    //   34: iload #6
    //   36: aload_3
    //   37: iload #6
    //   39: baload
    //   40: bastore
    //   41: iinc #6, 1
    //   44: iload_2
    //   45: ifne -> 25
    //   48: aload #5
    //   50: arraylength
    //   51: iconst_3
    //   52: idiv
    //   53: iconst_4
    //   54: imul
    //   55: newarray byte
    //   57: astore #4
    //   59: iconst_0
    //   60: istore #6
    //   62: iconst_0
    //   63: istore #7
    //   65: iload #6
    //   67: aload_3
    //   68: arraylength
    //   69: if_icmpge -> 180
    //   72: aload #4
    //   74: iload #7
    //   76: aload #5
    //   78: iload #6
    //   80: baload
    //   81: iconst_2
    //   82: iushr
    //   83: bipush #63
    //   85: iand
    //   86: i2b
    //   87: bastore
    //   88: aload #4
    //   90: iload #7
    //   92: iconst_1
    //   93: iadd
    //   94: aload #5
    //   96: iload #6
    //   98: iconst_1
    //   99: iadd
    //   100: baload
    //   101: iconst_4
    //   102: iushr
    //   103: bipush #15
    //   105: iand
    //   106: aload #5
    //   108: iload #6
    //   110: baload
    //   111: iconst_4
    //   112: ishl
    //   113: bipush #63
    //   115: iand
    //   116: ior
    //   117: i2b
    //   118: bastore
    //   119: aload #4
    //   121: iload #7
    //   123: iconst_2
    //   124: iadd
    //   125: aload #5
    //   127: iload #6
    //   129: iconst_2
    //   130: iadd
    //   131: baload
    //   132: bipush #6
    //   134: iushr
    //   135: iconst_3
    //   136: iand
    //   137: aload #5
    //   139: iload #6
    //   141: iconst_1
    //   142: iadd
    //   143: baload
    //   144: iconst_2
    //   145: ishl
    //   146: bipush #63
    //   148: iand
    //   149: ior
    //   150: i2b
    //   151: bastore
    //   152: aload #4
    //   154: iload #7
    //   156: iconst_3
    //   157: iadd
    //   158: aload #5
    //   160: iload #6
    //   162: iconst_2
    //   163: iadd
    //   164: baload
    //   165: bipush #63
    //   167: iand
    //   168: i2b
    //   169: bastore
    //   170: iinc #6, 3
    //   173: iinc #7, 4
    //   176: iload_2
    //   177: ifne -> 65
    //   180: iconst_0
    //   181: istore #6
    //   183: iload #6
    //   185: aload #4
    //   187: arraylength
    //   188: if_icmpge -> 372
    //   191: aload #4
    //   193: iload #6
    //   195: baload
    //   196: bipush #26
    //   198: if_icmpge -> 226
    //   201: aload #4
    //   203: iload #6
    //   205: aload #4
    //   207: iload #6
    //   209: baload
    //   210: bipush #65
    //   212: iadd
    //   213: i2b
    //   214: bastore
    //   215: iload_2
    //   216: ifne -> 365
    //   219: goto -> 226
    //   222: invokestatic a : (Ljava/lang/Throwable;)Ljava/lang/Throwable;
    //   225: athrow
    //   226: aload #4
    //   228: iload #6
    //   230: baload
    //   231: bipush #52
    //   233: if_icmpge -> 271
    //   236: goto -> 243
    //   239: invokestatic a : (Ljava/lang/Throwable;)Ljava/lang/Throwable;
    //   242: athrow
    //   243: aload #4
    //   245: iload #6
    //   247: aload #4
    //   249: iload #6
    //   251: baload
    //   252: bipush #97
    //   254: iadd
    //   255: bipush #26
    //   257: isub
    //   258: i2b
    //   259: bastore
    //   260: iload_2
    //   261: ifne -> 365
    //   264: goto -> 271
    //   267: invokestatic a : (Ljava/lang/Throwable;)Ljava/lang/Throwable;
    //   270: athrow
    //   271: aload #4
    //   273: iload #6
    //   275: baload
    //   276: bipush #62
    //   278: if_icmpge -> 316
    //   281: goto -> 288
    //   284: invokestatic a : (Ljava/lang/Throwable;)Ljava/lang/Throwable;
    //   287: athrow
    //   288: aload #4
    //   290: iload #6
    //   292: aload #4
    //   294: iload #6
    //   296: baload
    //   297: bipush #48
    //   299: iadd
    //   300: bipush #52
    //   302: isub
    //   303: i2b
    //   304: bastore
    //   305: iload_2
    //   306: ifne -> 365
    //   309: goto -> 316
    //   312: invokestatic a : (Ljava/lang/Throwable;)Ljava/lang/Throwable;
    //   315: athrow
    //   316: aload #4
    //   318: iload #6
    //   320: baload
    //   321: bipush #63
    //   323: if_icmpge -> 351
    //   326: goto -> 333
    //   329: invokestatic a : (Ljava/lang/Throwable;)Ljava/lang/Throwable;
    //   332: athrow
    //   333: aload #4
    //   335: iload #6
    //   337: bipush #43
    //   339: bastore
    //   340: iload_2
    //   341: ifne -> 365
    //   344: goto -> 351
    //   347: invokestatic a : (Ljava/lang/Throwable;)Ljava/lang/Throwable;
    //   350: athrow
    //   351: aload #4
    //   353: iload #6
    //   355: bipush #47
    //   357: bastore
    //   358: goto -> 365
    //   361: invokestatic a : (Ljava/lang/Throwable;)Ljava/lang/Throwable;
    //   364: athrow
    //   365: iinc #6, 1
    //   368: iload_2
    //   369: ifne -> 183
    //   372: aload #4
    //   374: arraylength
    //   375: iconst_1
    //   376: isub
    //   377: istore #6
    //   379: iload #6
    //   381: aload_3
    //   382: arraylength
    //   383: iconst_4
    //   384: imul
    //   385: iconst_3
    //   386: idiv
    //   387: if_icmple -> 404
    //   390: aload #4
    //   392: iload #6
    //   394: bipush #61
    //   396: bastore
    //   397: iinc #6, -1
    //   400: iload_2
    //   401: ifne -> 379
    //   404: new java/math/BigInteger
    //   407: dup
    //   408: aload #4
    //   410: invokespecial <init> : ([B)V
    //   413: invokevirtual abs : ()Ljava/math/BigInteger;
    //   416: putstatic burp/Zgva.Zr : Ljava/lang/Object;
    //   419: new java/lang/StringBuilder
    //   422: dup
    //   423: invokespecial <init> : ()V
    //   426: astore_3
    //   427: iconst_0
    //   428: istore #4
    //   430: iload #4
    //   432: bipush #32
    //   434: if_icmpge -> 1767
    //   437: iload #4
    //   439: tableswitch default -> 1760, 0 -> 580, 1 -> 617, 2 -> 654, 3 -> 691, 4 -> 728, 5 -> 765, 6 -> 802, 7 -> 839, 8 -> 876, 9 -> 913, 10 -> 950, 11 -> 987, 12 -> 1024, 13 -> 1061, 14 -> 1098, 15 -> 1135, 16 -> 1172, 17 -> 1209, 18 -> 1246, 19 -> 1283, 20 -> 1320, 21 -> 1357, 22 -> 1394, 23 -> 1431, 24 -> 1468, 25 -> 1505, 26 -> 1542, 27 -> 1579, 28 -> 1616, 29 -> 1653, 30 -> 1690, 31 -> 1727
    //   580: aload_3
    //   581: getstatic burp/Zkjr.Zg : Ljava/lang/String;
    //   584: getstatic burp/Zg4k.ZE : Ljava/lang/Object;
    //   587: checkcast java/math/BigInteger
    //   590: invokevirtual intValue : ()I
    //   593: bipush #32
    //   595: irem
    //   596: invokestatic abs : (I)I
    //   599: invokevirtual charAt : (I)C
    //   602: invokevirtual append : (C)Ljava/lang/StringBuilder;
    //   605: pop
    //   606: iload_2
    //   607: ifne -> 1760
    //   610: goto -> 617
    //   613: invokestatic a : (Ljava/lang/Throwable;)Ljava/lang/Throwable;
    //   616: athrow
    //   617: aload_3
    //   618: getstatic burp/Zzyr.Z_ : Ljava/lang/String;
    //   621: getstatic burp/Zztn.ZO : Ljava/lang/Object;
    //   624: checkcast java/math/BigInteger
    //   627: invokevirtual intValue : ()I
    //   630: bipush #32
    //   632: irem
    //   633: invokestatic abs : (I)I
    //   636: invokevirtual charAt : (I)C
    //   639: invokevirtual append : (C)Ljava/lang/StringBuilder;
    //   642: pop
    //   643: iload_2
    //   644: ifne -> 1760
    //   647: goto -> 654
    //   650: invokestatic a : (Ljava/lang/Throwable;)Ljava/lang/Throwable;
    //   653: athrow
    //   654: aload_3
    //   655: getstatic burp/Zl8f.ZK : Ljava/lang/String;
    //   658: getstatic burp/Zel.ZB : Ljava/lang/Object;
    //   661: checkcast java/math/BigInteger
    //   664: invokevirtual intValue : ()I
    //   667: bipush #32
    //   669: irem
    //   670: invokestatic abs : (I)I
    //   673: invokevirtual charAt : (I)C
    //   676: invokevirtual append : (C)Ljava/lang/StringBuilder;
    //   679: pop
    //   680: iload_2
    //   681: ifne -> 1760
    //   684: goto -> 691
    //   687: invokestatic a : (Ljava/lang/Throwable;)Ljava/lang/Throwable;
    //   690: athrow
    //   691: aload_3
    //   692: getstatic burp/Zm4i.Zl : Ljava/lang/String;
    //   695: getstatic burp/Zlpj.Zc : Ljava/lang/Object;
    //   698: checkcast java/math/BigInteger
    //   701: invokevirtual intValue : ()I
    //   704: bipush #32
    //   706: irem
    //   707: invokestatic abs : (I)I
    //   710: invokevirtual charAt : (I)C
    //   713: invokevirtual append : (C)Ljava/lang/StringBuilder;
    //   716: pop
    //   717: iload_2
    //   718: ifne -> 1760
    //   721: goto -> 728
    //   724: invokestatic a : (Ljava/lang/Throwable;)Ljava/lang/Throwable;
    //   727: athrow
    //   728: aload_3
    //   729: getstatic burp/Zli5.Zq : Ljava/lang/String;
    //   732: getstatic burp/Zlr.ZK : Ljava/lang/Object;
    //   735: checkcast java/math/BigInteger
    //   738: invokevirtual intValue : ()I
    //   741: bipush #32
    //   743: irem
    //   744: invokestatic abs : (I)I
    //   747: invokevirtual charAt : (I)C
    //   750: invokevirtual append : (C)Ljava/lang/StringBuilder;
    //   753: pop
    //   754: iload_2
    //   755: ifne -> 1760
    //   758: goto -> 765
    //   761: invokestatic a : (Ljava/lang/Throwable;)Ljava/lang/Throwable;
    //   764: athrow
    //   765: aload_3
    //   766: getstatic burp/Zzc_.Zg : Ljava/lang/String;
    //   769: getstatic burp/Zxg7.Zy : Ljava/lang/Object;
    //   772: checkcast java/math/BigInteger
    //   775: invokevirtual intValue : ()I
    //   778: bipush #32
    //   780: irem
    //   781: invokestatic abs : (I)I
    //   784: invokevirtual charAt : (I)C
    //   787: invokevirtual append : (C)Ljava/lang/StringBuilder;
    //   790: pop
    //   791: iload_2
    //   792: ifne -> 1760
    //   795: goto -> 802
    //   798: invokestatic a : (Ljava/lang/Throwable;)Ljava/lang/Throwable;
    //   801: athrow
    //   802: aload_3
    //   803: getstatic burp/Ztfh.ZU : Ljava/lang/String;
    //   806: getstatic burp/Zr1z.Zi : Ljava/lang/Object;
    //   809: checkcast java/math/BigInteger
    //   812: invokevirtual intValue : ()I
    //   815: bipush #32
    //   817: irem
    //   818: invokestatic abs : (I)I
    //   821: invokevirtual charAt : (I)C
    //   824: invokevirtual append : (C)Ljava/lang/StringBuilder;
    //   827: pop
    //   828: iload_2
    //   829: ifne -> 1760
    //   832: goto -> 839
    //   835: invokestatic a : (Ljava/lang/Throwable;)Ljava/lang/Throwable;
    //   838: athrow
    //   839: aload_3
    //   840: getstatic burp/Zlf0.ZS : Ljava/lang/String;
    //   843: getstatic burp/Zm52.ZR : Ljava/lang/Object;
    //   846: checkcast java/math/BigInteger
    //   849: invokevirtual intValue : ()I
    //   852: bipush #32
    //   854: irem
    //   855: invokestatic abs : (I)I
    //   858: invokevirtual charAt : (I)C
    //   861: invokevirtual append : (C)Ljava/lang/StringBuilder;
    //   864: pop
    //   865: iload_2
    //   866: ifne -> 1760
    //   869: goto -> 876
    //   872: invokestatic a : (Ljava/lang/Throwable;)Ljava/lang/Throwable;
    //   875: athrow
    //   876: aload_3
    //   877: getstatic burp/Zltz.Za : Ljava/lang/String;
    //   880: getstatic burp/Ztfh.Zo : Ljava/lang/Object;
    //   883: checkcast java/math/BigInteger
    //   886: invokevirtual intValue : ()I
    //   889: bipush #32
    //   891: irem
    //   892: invokestatic abs : (I)I
    //   895: invokevirtual charAt : (I)C
    //   898: invokevirtual append : (C)Ljava/lang/StringBuilder;
    //   901: pop
    //   902: iload_2
    //   903: ifne -> 1760
    //   906: goto -> 913
    //   909: invokestatic a : (Ljava/lang/Throwable;)Ljava/lang/Throwable;
    //   912: athrow
    //   913: aload_3
    //   914: getstatic burp/Zlpj.Zj : Ljava/lang/String;
    //   917: getstatic burp/Ze69.ZH : Ljava/lang/Object;
    //   920: checkcast java/math/BigInteger
    //   923: invokevirtual intValue : ()I
    //   926: bipush #32
    //   928: irem
    //   929: invokestatic abs : (I)I
    //   932: invokevirtual charAt : (I)C
    //   935: invokevirtual append : (C)Ljava/lang/StringBuilder;
    //   938: pop
    //   939: iload_2
    //   940: ifne -> 1760
    //   943: goto -> 950
    //   946: invokestatic a : (Ljava/lang/Throwable;)Ljava/lang/Throwable;
    //   949: athrow
    //   950: aload_3
    //   951: getstatic burp/Zs2n.ZI : Ljava/lang/String;
    //   954: getstatic burp/Zs8y.ZG : Ljava/lang/Object;
    //   957: checkcast java/math/BigInteger
    //   960: invokevirtual intValue : ()I
    //   963: bipush #32
    //   965: irem
    //   966: invokestatic abs : (I)I
    //   969: invokevirtual charAt : (I)C
    //   972: invokevirtual append : (C)Ljava/lang/StringBuilder;
    //   975: pop
    //   976: iload_2
    //   977: ifne -> 1760
    //   980: goto -> 987
    //   983: invokestatic a : (Ljava/lang/Throwable;)Ljava/lang/Throwable;
    //   986: athrow
    //   987: aload_3
    //   988: getstatic burp/Zt0t.ZR : Ljava/lang/String;
    //   991: getstatic burp/Zzym.ZK : Ljava/lang/Object;
    //   994: checkcast java/math/BigInteger
    //   997: invokevirtual intValue : ()I
    //   1000: bipush #32
    //   1002: irem
    //   1003: invokestatic abs : (I)I
    //   1006: invokevirtual charAt : (I)C
    //   1009: invokevirtual append : (C)Ljava/lang/StringBuilder;
    //   1012: pop
    //   1013: iload_2
    //   1014: ifne -> 1760
    //   1017: goto -> 1024
    //   1020: invokestatic a : (Ljava/lang/Throwable;)Ljava/lang/Throwable;
    //   1023: athrow
    //   1024: aload_3
    //   1025: getstatic burp/Zrva.Zr : Ljava/lang/String;
    //   1028: getstatic burp/Zera.Zy : Ljava/lang/Object;
    //   1031: checkcast java/math/BigInteger
    //   1034: invokevirtual intValue : ()I
    //   1037: bipush #32
    //   1039: irem
    //   1040: invokestatic abs : (I)I
    //   1043: invokevirtual charAt : (I)C
    //   1046: invokevirtual append : (C)Ljava/lang/StringBuilder;
    //   1049: pop
    //   1050: iload_2
    //   1051: ifne -> 1760
    //   1054: goto -> 1061
    //   1057: invokestatic a : (Ljava/lang/Throwable;)Ljava/lang/Throwable;
    //   1060: athrow
    //   1061: aload_3
    //   1062: getstatic burp/Zs8q.Zs : Ljava/lang/String;
    //   1065: getstatic burp/Zg4k.ZE : Ljava/lang/Object;
    //   1068: checkcast java/math/BigInteger
    //   1071: invokevirtual intValue : ()I
    //   1074: bipush #32
    //   1076: irem
    //   1077: invokestatic abs : (I)I
    //   1080: invokevirtual charAt : (I)C
    //   1083: invokevirtual append : (C)Ljava/lang/StringBuilder;
    //   1086: pop
    //   1087: iload_2
    //   1088: ifne -> 1760
    //   1091: goto -> 1098
    //   1094: invokestatic a : (Ljava/lang/Throwable;)Ljava/lang/Throwable;
    //   1097: athrow
    //   1098: aload_3
    //   1099: getstatic burp/Zevr.Zk : Ljava/lang/String;
    //   1102: getstatic burp/Zx6d.ZU : Ljava/lang/Object;
    //   1105: checkcast java/math/BigInteger
    //   1108: invokevirtual intValue : ()I
    //   1111: bipush #32
    //   1113: irem
    //   1114: invokestatic abs : (I)I
    //   1117: invokevirtual charAt : (I)C
    //   1120: invokevirtual append : (C)Ljava/lang/StringBuilder;
    //   1123: pop
    //   1124: iload_2
    //   1125: ifne -> 1760
    //   1128: goto -> 1135
    //   1131: invokestatic a : (Ljava/lang/Throwable;)Ljava/lang/Throwable;
    //   1134: athrow
    //   1135: aload_3
    //   1136: getstatic burp/Zb8y.Zn : Ljava/lang/String;
    //   1139: getstatic burp/Zrof.ZB : Ljava/lang/Object;
    //   1142: checkcast java/math/BigInteger
    //   1145: invokevirtual intValue : ()I
    //   1148: bipush #32
    //   1150: irem
    //   1151: invokestatic abs : (I)I
    //   1154: invokevirtual charAt : (I)C
    //   1157: invokevirtual append : (C)Ljava/lang/StringBuilder;
    //   1160: pop
    //   1161: iload_2
    //   1162: ifne -> 1760
    //   1165: goto -> 1172
    //   1168: invokestatic a : (Ljava/lang/Throwable;)Ljava/lang/Throwable;
    //   1171: athrow
    //   1172: aload_3
    //   1173: getstatic burp/Ze69.ZA : Ljava/lang/String;
    //   1176: getstatic burp/Zztn.ZO : Ljava/lang/Object;
    //   1179: checkcast java/math/BigInteger
    //   1182: invokevirtual intValue : ()I
    //   1185: bipush #32
    //   1187: irem
    //   1188: invokestatic abs : (I)I
    //   1191: invokevirtual charAt : (I)C
    //   1194: invokevirtual append : (C)Ljava/lang/StringBuilder;
    //   1197: pop
    //   1198: iload_2
    //   1199: ifne -> 1760
    //   1202: goto -> 1209
    //   1205: invokestatic a : (Ljava/lang/Throwable;)Ljava/lang/Throwable;
    //   1208: athrow
    //   1209: aload_3
    //   1210: getstatic burp/Zk12.Zu : Ljava/lang/String;
    //   1213: getstatic burp/Zzox.Zq : Ljava/lang/Object;
    //   1216: checkcast java/math/BigInteger
    //   1219: invokevirtual intValue : ()I
    //   1222: bipush #32
    //   1224: irem
    //   1225: invokestatic abs : (I)I
    //   1228: invokevirtual charAt : (I)C
    //   1231: invokevirtual append : (C)Ljava/lang/StringBuilder;
    //   1234: pop
    //   1235: iload_2
    //   1236: ifne -> 1760
    //   1239: goto -> 1246
    //   1242: invokestatic a : (Ljava/lang/Throwable;)Ljava/lang/Throwable;
    //   1245: athrow
    //   1246: aload_3
    //   1247: getstatic burp/Zgva.ZV : Ljava/lang/String;
    //   1250: getstatic burp/Zm8v.ZU : Ljava/lang/Object;
    //   1253: checkcast java/math/BigInteger
    //   1256: invokevirtual intValue : ()I
    //   1259: bipush #32
    //   1261: irem
    //   1262: invokestatic abs : (I)I
    //   1265: invokevirtual charAt : (I)C
    //   1268: invokevirtual append : (C)Ljava/lang/StringBuilder;
    //   1271: pop
    //   1272: iload_2
    //   1273: ifne -> 1760
    //   1276: goto -> 1283
    //   1279: invokestatic a : (Ljava/lang/Throwable;)Ljava/lang/Throwable;
    //   1282: athrow
    //   1283: aload_3
    //   1284: getstatic burp/Ztfh.ZU : Ljava/lang/String;
    //   1287: getstatic burp/Zs2n.ZK : Ljava/lang/Object;
    //   1290: checkcast java/math/BigInteger
    //   1293: invokevirtual intValue : ()I
    //   1296: bipush #32
    //   1298: irem
    //   1299: invokestatic abs : (I)I
    //   1302: invokevirtual charAt : (I)C
    //   1305: invokevirtual append : (C)Ljava/lang/StringBuilder;
    //   1308: pop
    //   1309: iload_2
    //   1310: ifne -> 1760
    //   1313: goto -> 1320
    //   1316: invokestatic a : (Ljava/lang/Throwable;)Ljava/lang/Throwable;
    //   1319: athrow
    //   1320: aload_3
    //   1321: getstatic burp/Zm4i.Zl : Ljava/lang/String;
    //   1324: getstatic burp/Zeb7.ZJ : Ljava/lang/Object;
    //   1327: checkcast java/math/BigInteger
    //   1330: invokevirtual intValue : ()I
    //   1333: bipush #32
    //   1335: irem
    //   1336: invokestatic abs : (I)I
    //   1339: invokevirtual charAt : (I)C
    //   1342: invokevirtual append : (C)Ljava/lang/StringBuilder;
    //   1345: pop
    //   1346: iload_2
    //   1347: ifne -> 1760
    //   1350: goto -> 1357
    //   1353: invokestatic a : (Ljava/lang/Throwable;)Ljava/lang/Throwable;
    //   1356: athrow
    //   1357: aload_3
    //   1358: getstatic burp/Zzc_.Zg : Ljava/lang/String;
    //   1361: getstatic burp/Zlhq.Zw : Ljava/lang/Object;
    //   1364: checkcast java/math/BigInteger
    //   1367: invokevirtual intValue : ()I
    //   1370: bipush #32
    //   1372: irem
    //   1373: invokestatic abs : (I)I
    //   1376: invokevirtual charAt : (I)C
    //   1379: invokevirtual append : (C)Ljava/lang/StringBuilder;
    //   1382: pop
    //   1383: iload_2
    //   1384: ifne -> 1760
    //   1387: goto -> 1394
    //   1390: invokestatic a : (Ljava/lang/Throwable;)Ljava/lang/Throwable;
    //   1393: athrow
    //   1394: aload_3
    //   1395: getstatic burp/Zrva.Zr : Ljava/lang/String;
    //   1398: getstatic burp/Zlo5.Zf : Ljava/lang/Object;
    //   1401: checkcast java/math/BigInteger
    //   1404: invokevirtual intValue : ()I
    //   1407: bipush #32
    //   1409: irem
    //   1410: invokestatic abs : (I)I
    //   1413: invokevirtual charAt : (I)C
    //   1416: invokevirtual append : (C)Ljava/lang/StringBuilder;
    //   1419: pop
    //   1420: iload_2
    //   1421: ifne -> 1760
    //   1424: goto -> 1431
    //   1427: invokestatic a : (Ljava/lang/Throwable;)Ljava/lang/Throwable;
    //   1430: athrow
    //   1431: aload_3
    //   1432: getstatic burp/Zke7.Zl : Ljava/lang/String;
    //   1435: getstatic burp/Zrva.ZE : Ljava/lang/Object;
    //   1438: checkcast java/math/BigInteger
    //   1441: invokevirtual intValue : ()I
    //   1444: bipush #32
    //   1446: irem
    //   1447: invokestatic abs : (I)I
    //   1450: invokevirtual charAt : (I)C
    //   1453: invokevirtual append : (C)Ljava/lang/StringBuilder;
    //   1456: pop
    //   1457: iload_2
    //   1458: ifne -> 1760
    //   1461: goto -> 1468
    //   1464: invokestatic a : (Ljava/lang/Throwable;)Ljava/lang/Throwable;
    //   1467: athrow
    //   1468: aload_3
    //   1469: getstatic burp/Zstb.Zd : Ljava/lang/String;
    //   1472: getstatic burp/Zlvb.ZN : Ljava/lang/Object;
    //   1475: checkcast java/math/BigInteger
    //   1478: invokevirtual intValue : ()I
    //   1481: bipush #32
    //   1483: irem
    //   1484: invokestatic abs : (I)I
    //   1487: invokevirtual charAt : (I)C
    //   1490: invokevirtual append : (C)Ljava/lang/StringBuilder;
    //   1493: pop
    //   1494: iload_2
    //   1495: ifne -> 1760
    //   1498: goto -> 1505
    //   1501: invokestatic a : (Ljava/lang/Throwable;)Ljava/lang/Throwable;
    //   1504: athrow
    //   1505: aload_3
    //   1506: getstatic burp/Zl8f.ZK : Ljava/lang/String;
    //   1509: getstatic burp/Zli5.Zt : Ljava/lang/Object;
    //   1512: checkcast java/math/BigInteger
    //   1515: invokevirtual intValue : ()I
    //   1518: bipush #32
    //   1520: irem
    //   1521: invokestatic abs : (I)I
    //   1524: invokevirtual charAt : (I)C
    //   1527: invokevirtual append : (C)Ljava/lang/StringBuilder;
    //   1530: pop
    //   1531: iload_2
    //   1532: ifne -> 1760
    //   1535: goto -> 1542
    //   1538: invokestatic a : (Ljava/lang/Throwable;)Ljava/lang/Throwable;
    //   1541: athrow
    //   1542: aload_3
    //   1543: getstatic burp/Zxo7.Zl : Ljava/lang/String;
    //   1546: getstatic burp/Zef0.ZX : Ljava/lang/Object;
    //   1549: checkcast java/math/BigInteger
    //   1552: invokevirtual intValue : ()I
    //   1555: bipush #32
    //   1557: irem
    //   1558: invokestatic abs : (I)I
    //   1561: invokevirtual charAt : (I)C
    //   1564: invokevirtual append : (C)Ljava/lang/StringBuilder;
    //   1567: pop
    //   1568: iload_2
    //   1569: ifne -> 1760
    //   1572: goto -> 1579
    //   1575: invokestatic a : (Ljava/lang/Throwable;)Ljava/lang/Throwable;
    //   1578: athrow
    //   1579: aload_3
    //   1580: getstatic burp/Zsf7.ZS : Ljava/lang/String;
    //   1583: getstatic burp/Zlf0.ZC : Ljava/lang/Object;
    //   1586: checkcast java/math/BigInteger
    //   1589: invokevirtual intValue : ()I
    //   1592: bipush #32
    //   1594: irem
    //   1595: invokestatic abs : (I)I
    //   1598: invokevirtual charAt : (I)C
    //   1601: invokevirtual append : (C)Ljava/lang/StringBuilder;
    //   1604: pop
    //   1605: iload_2
    //   1606: ifne -> 1760
    //   1609: goto -> 1616
    //   1612: invokestatic a : (Ljava/lang/Throwable;)Ljava/lang/Throwable;
    //   1615: athrow
    //   1616: aload_3
    //   1617: getstatic burp/Zs_3.ZC : Ljava/lang/String;
    //   1620: getstatic burp/Zmhi.ZZ : Ljava/lang/Object;
    //   1623: checkcast java/math/BigInteger
    //   1626: invokevirtual intValue : ()I
    //   1629: bipush #32
    //   1631: irem
    //   1632: invokestatic abs : (I)I
    //   1635: invokevirtual charAt : (I)C
    //   1638: invokevirtual append : (C)Ljava/lang/StringBuilder;
    //   1641: pop
    //   1642: iload_2
    //   1643: ifne -> 1760
    //   1646: goto -> 1653
    //   1649: invokestatic a : (Ljava/lang/Throwable;)Ljava/lang/Throwable;
    //   1652: athrow
    //   1653: aload_3
    //   1654: getstatic burp/Zeuc.Zp : Ljava/lang/String;
    //   1657: getstatic burp/Ze8m.Zm : Ljava/lang/Object;
    //   1660: checkcast java/math/BigInteger
    //   1663: invokevirtual intValue : ()I
    //   1666: bipush #32
    //   1668: irem
    //   1669: invokestatic abs : (I)I
    //   1672: invokevirtual charAt : (I)C
    //   1675: invokevirtual append : (C)Ljava/lang/StringBuilder;
    //   1678: pop
    //   1679: iload_2
    //   1680: ifne -> 1760
    //   1683: goto -> 1690
    //   1686: invokestatic a : (Ljava/lang/Throwable;)Ljava/lang/Throwable;
    //   1689: athrow
    //   1690: aload_3
    //   1691: getstatic burp/Zli5.Zq : Ljava/lang/String;
    //   1694: getstatic burp/Zt0t.ZL : Ljava/lang/Object;
    //   1697: checkcast java/math/BigInteger
    //   1700: invokevirtual intValue : ()I
    //   1703: bipush #32
    //   1705: irem
    //   1706: invokestatic abs : (I)I
    //   1709: invokevirtual charAt : (I)C
    //   1712: invokevirtual append : (C)Ljava/lang/StringBuilder;
    //   1715: pop
    //   1716: iload_2
    //   1717: ifne -> 1760
    //   1720: goto -> 1727
    //   1723: invokestatic a : (Ljava/lang/Throwable;)Ljava/lang/Throwable;
    //   1726: athrow
    //   1727: aload_3
    //   1728: getstatic burp/Zk12.Zu : Ljava/lang/String;
    //   1731: getstatic burp/Zza8.Zh : Ljava/lang/Object;
    //   1734: checkcast java/math/BigInteger
    //   1737: invokevirtual intValue : ()I
    //   1740: bipush #32
    //   1742: irem
    //   1743: invokestatic abs : (I)I
    //   1746: invokevirtual charAt : (I)C
    //   1749: invokevirtual append : (C)Ljava/lang/StringBuilder;
    //   1752: pop
    //   1753: goto -> 1760
    //   1756: invokestatic a : (Ljava/lang/Throwable;)Ljava/lang/Throwable;
    //   1759: athrow
    //   1760: iinc #4, 1
    //   1763: iload_2
    //   1764: ifne -> 430
    //   1767: aload_3
    //   1768: invokevirtual toString : ()Ljava/lang/String;
    //   1771: putstatic burp/Zgva.ZV : Ljava/lang/String;
    //   1774: getstatic burp/Zz0w.ZF : Ljava/lang/Object;
    //   1777: checkcast java/math/BigInteger
    //   1780: invokevirtual toByteArray : ()[B
    //   1783: astore #4
    //   1785: bipush #64
    //   1787: newarray byte
    //   1789: dup
    //   1790: iconst_0
    //   1791: bipush #-128
    //   1793: bastore
    //   1794: dup
    //   1795: iconst_1
    //   1796: iconst_0
    //   1797: bastore
    //   1798: dup
    //   1799: iconst_2
    //   1800: iconst_0
    //   1801: bastore
    //   1802: dup
    //   1803: iconst_3
    //   1804: iconst_0
    //   1805: bastore
    //   1806: dup
    //   1807: iconst_4
    //   1808: iconst_0
    //   1809: bastore
    //   1810: dup
    //   1811: iconst_5
    //   1812: iconst_0
    //   1813: bastore
    //   1814: dup
    //   1815: bipush #6
    //   1817: iconst_0
    //   1818: bastore
    //   1819: dup
    //   1820: bipush #7
    //   1822: iconst_0
    //   1823: bastore
    //   1824: dup
    //   1825: bipush #8
    //   1827: iconst_0
    //   1828: bastore
    //   1829: dup
    //   1830: bipush #9
    //   1832: iconst_0
    //   1833: bastore
    //   1834: dup
    //   1835: bipush #10
    //   1837: iconst_0
    //   1838: bastore
    //   1839: dup
    //   1840: bipush #11
    //   1842: iconst_0
    //   1843: bastore
    //   1844: dup
    //   1845: bipush #12
    //   1847: iconst_0
    //   1848: bastore
    //   1849: dup
    //   1850: bipush #13
    //   1852: iconst_0
    //   1853: bastore
    //   1854: dup
    //   1855: bipush #14
    //   1857: iconst_0
    //   1858: bastore
    //   1859: dup
    //   1860: bipush #15
    //   1862: iconst_0
    //   1863: bastore
    //   1864: dup
    //   1865: bipush #16
    //   1867: iconst_0
    //   1868: bastore
    //   1869: dup
    //   1870: bipush #17
    //   1872: iconst_0
    //   1873: bastore
    //   1874: dup
    //   1875: bipush #18
    //   1877: iconst_0
    //   1878: bastore
    //   1879: dup
    //   1880: bipush #19
    //   1882: iconst_0
    //   1883: bastore
    //   1884: dup
    //   1885: bipush #20
    //   1887: iconst_0
    //   1888: bastore
    //   1889: dup
    //   1890: bipush #21
    //   1892: iconst_0
    //   1893: bastore
    //   1894: dup
    //   1895: bipush #22
    //   1897: iconst_0
    //   1898: bastore
    //   1899: dup
    //   1900: bipush #23
    //   1902: iconst_0
    //   1903: bastore
    //   1904: dup
    //   1905: bipush #24
    //   1907: iconst_0
    //   1908: bastore
    //   1909: dup
    //   1910: bipush #25
    //   1912: iconst_0
    //   1913: bastore
    //   1914: dup
    //   1915: bipush #26
    //   1917: iconst_0
    //   1918: bastore
    //   1919: dup
    //   1920: bipush #27
    //   1922: iconst_0
    //   1923: bastore
    //   1924: dup
    //   1925: bipush #28
    //   1927: iconst_0
    //   1928: bastore
    //   1929: dup
    //   1930: bipush #29
    //   1932: iconst_0
    //   1933: bastore
    //   1934: dup
    //   1935: bipush #30
    //   1937: iconst_0
    //   1938: bastore
    //   1939: dup
    //   1940: bipush #31
    //   1942: iconst_0
    //   1943: bastore
    //   1944: dup
    //   1945: bipush #32
    //   1947: iconst_0
    //   1948: bastore
    //   1949: dup
    //   1950: bipush #33
    //   1952: iconst_0
    //   1953: bastore
    //   1954: dup
    //   1955: bipush #34
    //   1957: iconst_0
    //   1958: bastore
    //   1959: dup
    //   1960: bipush #35
    //   1962: iconst_0
    //   1963: bastore
    //   1964: dup
    //   1965: bipush #36
    //   1967: iconst_0
    //   1968: bastore
    //   1969: dup
    //   1970: bipush #37
    //   1972: iconst_0
    //   1973: bastore
    //   1974: dup
    //   1975: bipush #38
    //   1977: iconst_0
    //   1978: bastore
    //   1979: dup
    //   1980: bipush #39
    //   1982: iconst_0
    //   1983: bastore
    //   1984: dup
    //   1985: bipush #40
    //   1987: iconst_0
    //   1988: bastore
    //   1989: dup
    //   1990: bipush #41
    //   1992: iconst_0
    //   1993: bastore
    //   1994: dup
    //   1995: bipush #42
    //   1997: iconst_0
    //   1998: bastore
    //   1999: dup
    //   2000: bipush #43
    //   2002: iconst_0
    //   2003: bastore
    //   2004: dup
    //   2005: bipush #44
    //   2007: iconst_0
    //   2008: bastore
    //   2009: dup
    //   2010: bipush #45
    //   2012: iconst_0
    //   2013: bastore
    //   2014: dup
    //   2015: bipush #46
    //   2017: iconst_0
    //   2018: bastore
    //   2019: dup
    //   2020: bipush #47
    //   2022: iconst_0
    //   2023: bastore
    //   2024: dup
    //   2025: bipush #48
    //   2027: iconst_0
    //   2028: bastore
    //   2029: dup
    //   2030: bipush #49
    //   2032: iconst_0
    //   2033: bastore
    //   2034: dup
    //   2035: bipush #50
    //   2037: iconst_0
    //   2038: bastore
    //   2039: dup
    //   2040: bipush #51
    //   2042: iconst_0
    //   2043: bastore
    //   2044: dup
    //   2045: bipush #52
    //   2047: iconst_0
    //   2048: bastore
    //   2049: dup
    //   2050: bipush #53
    //   2052: iconst_0
    //   2053: bastore
    //   2054: dup
    //   2055: bipush #54
    //   2057: iconst_0
    //   2058: bastore
    //   2059: dup
    //   2060: bipush #55
    //   2062: iconst_0
    //   2063: bastore
    //   2064: dup
    //   2065: bipush #56
    //   2067: iconst_0
    //   2068: bastore
    //   2069: dup
    //   2070: bipush #57
    //   2072: iconst_0
    //   2073: bastore
    //   2074: dup
    //   2075: bipush #58
    //   2077: iconst_0
    //   2078: bastore
    //   2079: dup
    //   2080: bipush #59
    //   2082: iconst_0
    //   2083: bastore
    //   2084: dup
    //   2085: bipush #60
    //   2087: iconst_0
    //   2088: bastore
    //   2089: dup
    //   2090: bipush #61
    //   2092: iconst_0
    //   2093: bastore
    //   2094: dup
    //   2095: bipush #62
    //   2097: iconst_0
    //   2098: bastore
    //   2099: dup
    //   2100: bipush #63
    //   2102: iconst_0
    //   2103: bastore
    //   2104: astore #6
    //   2106: bipush #64
    //   2108: newarray int
    //   2110: dup
    //   2111: iconst_0
    //   2112: ldc 1116352408
    //   2114: iastore
    //   2115: dup
    //   2116: iconst_1
    //   2117: ldc 1899447441
    //   2119: iastore
    //   2120: dup
    //   2121: iconst_2
    //   2122: ldc -1245643825
    //   2124: iastore
    //   2125: dup
    //   2126: iconst_3
    //   2127: ldc -373957723
    //   2129: iastore
    //   2130: dup
    //   2131: iconst_4
    //   2132: ldc 961987163
    //   2134: iastore
    //   2135: dup
    //   2136: iconst_5
    //   2137: ldc 1508970993
    //   2139: iastore
    //   2140: dup
    //   2141: bipush #6
    //   2143: ldc -1841331548
    //   2145: iastore
    //   2146: dup
    //   2147: bipush #7
    //   2149: ldc -1424204075
    //   2151: iastore
    //   2152: dup
    //   2153: bipush #8
    //   2155: ldc -670586216
    //   2157: iastore
    //   2158: dup
    //   2159: bipush #9
    //   2161: ldc 310598401
    //   2163: iastore
    //   2164: dup
    //   2165: bipush #10
    //   2167: ldc 607225278
    //   2169: iastore
    //   2170: dup
    //   2171: bipush #11
    //   2173: ldc 1426881987
    //   2175: iastore
    //   2176: dup
    //   2177: bipush #12
    //   2179: ldc 1925078388
    //   2181: iastore
    //   2182: dup
    //   2183: bipush #13
    //   2185: ldc -2132889090
    //   2187: iastore
    //   2188: dup
    //   2189: bipush #14
    //   2191: ldc -1680079193
    //   2193: iastore
    //   2194: dup
    //   2195: bipush #15
    //   2197: ldc -1046744716
    //   2199: iastore
    //   2200: dup
    //   2201: bipush #16
    //   2203: ldc -459576895
    //   2205: iastore
    //   2206: dup
    //   2207: bipush #17
    //   2209: ldc -272742522
    //   2211: iastore
    //   2212: dup
    //   2213: bipush #18
    //   2215: ldc 264347078
    //   2217: iastore
    //   2218: dup
    //   2219: bipush #19
    //   2221: ldc 604807628
    //   2223: iastore
    //   2224: dup
    //   2225: bipush #20
    //   2227: ldc 770255983
    //   2229: iastore
    //   2230: dup
    //   2231: bipush #21
    //   2233: ldc 1249150122
    //   2235: iastore
    //   2236: dup
    //   2237: bipush #22
    //   2239: ldc 1555081692
    //   2241: iastore
    //   2242: dup
    //   2243: bipush #23
    //   2245: ldc 1996064986
    //   2247: iastore
    //   2248: dup
    //   2249: bipush #24
    //   2251: ldc -1740746414
    //   2253: iastore
    //   2254: dup
    //   2255: bipush #25
    //   2257: ldc -1473132947
    //   2259: iastore
    //   2260: dup
    //   2261: bipush #26
    //   2263: ldc -1341970488
    //   2265: iastore
    //   2266: dup
    //   2267: bipush #27
    //   2269: ldc -1084653625
    //   2271: iastore
    //   2272: dup
    //   2273: bipush #28
    //   2275: ldc -958395405
    //   2277: iastore
    //   2278: dup
    //   2279: bipush #29
    //   2281: ldc -710438585
    //   2283: iastore
    //   2284: dup
    //   2285: bipush #30
    //   2287: ldc 113926993
    //   2289: iastore
    //   2290: dup
    //   2291: bipush #31
    //   2293: ldc 338241895
    //   2295: iastore
    //   2296: dup
    //   2297: bipush #32
    //   2299: ldc 666307205
    //   2301: iastore
    //   2302: dup
    //   2303: bipush #33
    //   2305: ldc 773529912
    //   2307: iastore
    //   2308: dup
    //   2309: bipush #34
    //   2311: ldc 1294757372
    //   2313: iastore
    //   2314: dup
    //   2315: bipush #35
    //   2317: ldc 1396182291
    //   2319: iastore
    //   2320: dup
    //   2321: bipush #36
    //   2323: ldc 1695183700
    //   2325: iastore
    //   2326: dup
    //   2327: bipush #37
    //   2329: ldc 1986661051
    //   2331: iastore
    //   2332: dup
    //   2333: bipush #38
    //   2335: ldc -2117940946
    //   2337: iastore
    //   2338: dup
    //   2339: bipush #39
    //   2341: ldc -1838011259
    //   2343: iastore
    //   2344: dup
    //   2345: bipush #40
    //   2347: ldc -1564481375
    //   2349: iastore
    //   2350: dup
    //   2351: bipush #41
    //   2353: ldc -1474664885
    //   2355: iastore
    //   2356: dup
    //   2357: bipush #42
    //   2359: ldc -1035236496
    //   2361: iastore
    //   2362: dup
    //   2363: bipush #43
    //   2365: ldc -949202525
    //   2367: iastore
    //   2368: dup
    //   2369: bipush #44
    //   2371: ldc -778901479
    //   2373: iastore
    //   2374: dup
    //   2375: bipush #45
    //   2377: ldc -694614492
    //   2379: iastore
    //   2380: dup
    //   2381: bipush #46
    //   2383: ldc -200395387
    //   2385: iastore
    //   2386: dup
    //   2387: bipush #47
    //   2389: ldc 275423344
    //   2391: iastore
    //   2392: dup
    //   2393: bipush #48
    //   2395: ldc 430227734
    //   2397: iastore
    //   2398: dup
    //   2399: bipush #49
    //   2401: ldc 506948616
    //   2403: iastore
    //   2404: dup
    //   2405: bipush #50
    //   2407: ldc 659060556
    //   2409: iastore
    //   2410: dup
    //   2411: bipush #51
    //   2413: ldc 883997877
    //   2415: iastore
    //   2416: dup
    //   2417: bipush #52
    //   2419: ldc 958139571
    //   2421: iastore
    //   2422: dup
    //   2423: bipush #53
    //   2425: ldc 1322822218
    //   2427: iastore
    //   2428: dup
    //   2429: bipush #54
    //   2431: ldc 1537002063
    //   2433: iastore
    //   2434: dup
    //   2435: bipush #55
    //   2437: ldc 1747873779
    //   2439: iastore
    //   2440: dup
    //   2441: bipush #56
    //   2443: ldc 1955562222
    //   2445: iastore
    //   2446: dup
    //   2447: bipush #57
    //   2449: ldc 2024104815
    //   2451: iastore
    //   2452: dup
    //   2453: bipush #58
    //   2455: ldc -2067236844
    //   2457: iastore
    //   2458: dup
    //   2459: bipush #59
    //   2461: ldc -1933114872
    //   2463: iastore
    //   2464: dup
    //   2465: bipush #60
    //   2467: ldc -1866530822
    //   2469: iastore
    //   2470: dup
    //   2471: bipush #61
    //   2473: ldc -1538233109
    //   2475: iastore
    //   2476: dup
    //   2477: bipush #62
    //   2479: ldc -1090935817
    //   2481: iastore
    //   2482: dup
    //   2483: bipush #63
    //   2485: ldc -965641998
    //   2487: iastore
    //   2488: astore #7
    //   2490: iconst_2
    //   2491: newarray int
    //   2493: dup
    //   2494: iconst_0
    //   2495: iconst_0
    //   2496: iastore
    //   2497: dup
    //   2498: iconst_1
    //   2499: iconst_0
    //   2500: iastore
    //   2501: astore #8
    //   2503: bipush #8
    //   2505: newarray int
    //   2507: dup
    //   2508: iconst_0
    //   2509: ldc 1779033703
    //   2511: iastore
    //   2512: dup
    //   2513: iconst_1
    //   2514: ldc -1150833019
    //   2516: iastore
    //   2517: dup
    //   2518: iconst_2
    //   2519: ldc 1013904242
    //   2521: iastore
    //   2522: dup
    //   2523: iconst_3
    //   2524: ldc -1521486534
    //   2526: iastore
    //   2527: dup
    //   2528: iconst_4
    //   2529: ldc 1359893119
    //   2531: iastore
    //   2532: dup
    //   2533: iconst_5
    //   2534: ldc -1694144372
    //   2536: iastore
    //   2537: dup
    //   2538: bipush #6
    //   2540: ldc 528734635
    //   2542: iastore
    //   2543: dup
    //   2544: bipush #7
    //   2546: ldc 1541459225
    //   2548: iastore
    //   2549: astore #9
    //   2551: bipush #64
    //   2553: newarray byte
    //   2555: astore #10
    //   2557: bipush #64
    //   2559: newarray byte
    //   2561: astore #11
    //   2563: aload #4
    //   2565: arraylength
    //   2566: istore #12
    //   2568: aload #8
    //   2570: iconst_0
    //   2571: iaload
    //   2572: bipush #63
    //   2574: iand
    //   2575: istore #13
    //   2577: aload #8
    //   2579: iconst_0
    //   2580: dup2
    //   2581: iaload
    //   2582: iload #12
    //   2584: iadd
    //   2585: iastore
    //   2586: aload #8
    //   2588: iconst_0
    //   2589: dup2
    //   2590: iaload
    //   2591: iconst_m1
    //   2592: iand
    //   2593: iastore
    //   2594: aload #8
    //   2596: iconst_0
    //   2597: iaload
    //   2598: iload #12
    //   2600: if_icmpge -> 2618
    //   2603: aload #8
    //   2605: iconst_1
    //   2606: dup2
    //   2607: iaload
    //   2608: iconst_1
    //   2609: iadd
    //   2610: iastore
    //   2611: goto -> 2618
    //   2614: invokestatic a : (Ljava/lang/Throwable;)Ljava/lang/Throwable;
    //   2617: athrow
    //   2618: iconst_0
    //   2619: istore #14
    //   2621: iload #12
    //   2623: bipush #64
    //   2625: if_icmplt -> 3235
    //   2628: iconst_0
    //   2629: istore #15
    //   2631: iload #15
    //   2633: bipush #64
    //   2635: if_icmpge -> 2658
    //   2638: aload #11
    //   2640: iload #15
    //   2642: aload #4
    //   2644: iload #14
    //   2646: iload #15
    //   2648: iadd
    //   2649: baload
    //   2650: bastore
    //   2651: iinc #15, 1
    //   2654: iload_2
    //   2655: ifne -> 2631
    //   2658: bipush #64
    //   2660: newarray int
    //   2662: astore #15
    //   2664: bipush #8
    //   2666: newarray int
    //   2668: astore #16
    //   2670: iconst_0
    //   2671: istore #17
    //   2673: iload #17
    //   2675: bipush #8
    //   2677: if_icmpge -> 2697
    //   2680: aload #16
    //   2682: iload #17
    //   2684: aload #9
    //   2686: iload #17
    //   2688: iaload
    //   2689: iastore
    //   2690: iinc #17, 1
    //   2693: iload_2
    //   2694: ifne -> 2673
    //   2697: iconst_0
    //   2698: istore #17
    //   2700: iload #17
    //   2702: bipush #64
    //   2704: if_icmpge -> 3195
    //   2707: iload #17
    //   2709: bipush #16
    //   2711: if_icmpge -> 2792
    //   2714: aload #15
    //   2716: iload #17
    //   2718: aload #11
    //   2720: iconst_4
    //   2721: iload #17
    //   2723: imul
    //   2724: baload
    //   2725: sipush #255
    //   2728: iand
    //   2729: bipush #24
    //   2731: ishl
    //   2732: aload #11
    //   2734: iconst_4
    //   2735: iload #17
    //   2737: imul
    //   2738: iconst_1
    //   2739: iadd
    //   2740: baload
    //   2741: sipush #255
    //   2744: iand
    //   2745: bipush #16
    //   2747: ishl
    //   2748: ior
    //   2749: aload #11
    //   2751: iconst_4
    //   2752: iload #17
    //   2754: imul
    //   2755: iconst_2
    //   2756: iadd
    //   2757: baload
    //   2758: sipush #255
    //   2761: iand
    //   2762: bipush #8
    //   2764: ishl
    //   2765: ior
    //   2766: aload #11
    //   2768: iconst_4
    //   2769: iload #17
    //   2771: imul
    //   2772: iconst_3
    //   2773: iadd
    //   2774: baload
    //   2775: sipush #255
    //   2778: iand
    //   2779: ior
    //   2780: iastore
    //   2781: iload_2
    //   2782: ifne -> 2935
    //   2785: goto -> 2792
    //   2788: invokestatic a : (Ljava/lang/Throwable;)Ljava/lang/Throwable;
    //   2791: athrow
    //   2792: aload #15
    //   2794: iload #17
    //   2796: aload #15
    //   2798: iload #17
    //   2800: iconst_2
    //   2801: isub
    //   2802: iaload
    //   2803: bipush #17
    //   2805: iushr
    //   2806: aload #15
    //   2808: iload #17
    //   2810: iconst_2
    //   2811: isub
    //   2812: iaload
    //   2813: bipush #15
    //   2815: ishl
    //   2816: ior
    //   2817: aload #15
    //   2819: iload #17
    //   2821: iconst_2
    //   2822: isub
    //   2823: iaload
    //   2824: bipush #19
    //   2826: iushr
    //   2827: aload #15
    //   2829: iload #17
    //   2831: iconst_2
    //   2832: isub
    //   2833: iaload
    //   2834: bipush #13
    //   2836: ishl
    //   2837: ior
    //   2838: ixor
    //   2839: aload #15
    //   2841: iload #17
    //   2843: iconst_2
    //   2844: isub
    //   2845: iaload
    //   2846: bipush #10
    //   2848: iushr
    //   2849: ixor
    //   2850: aload #15
    //   2852: iload #17
    //   2854: bipush #7
    //   2856: isub
    //   2857: iaload
    //   2858: iadd
    //   2859: aload #15
    //   2861: iload #17
    //   2863: bipush #15
    //   2865: isub
    //   2866: iaload
    //   2867: bipush #7
    //   2869: iushr
    //   2870: aload #15
    //   2872: iload #17
    //   2874: bipush #15
    //   2876: isub
    //   2877: iaload
    //   2878: bipush #25
    //   2880: ishl
    //   2881: ior
    //   2882: aload #15
    //   2884: iload #17
    //   2886: bipush #15
    //   2888: isub
    //   2889: iaload
    //   2890: bipush #18
    //   2892: iushr
    //   2893: aload #15
    //   2895: iload #17
    //   2897: bipush #15
    //   2899: isub
    //   2900: iaload
    //   2901: bipush #14
    //   2903: ishl
    //   2904: ior
    //   2905: ixor
    //   2906: aload #15
    //   2908: iload #17
    //   2910: bipush #15
    //   2912: isub
    //   2913: iaload
    //   2914: iconst_3
    //   2915: iushr
    //   2916: ixor
    //   2917: iadd
    //   2918: aload #15
    //   2920: iload #17
    //   2922: bipush #16
    //   2924: isub
    //   2925: iaload
    //   2926: iadd
    //   2927: iastore
    //   2928: goto -> 2935
    //   2931: invokestatic a : (Ljava/lang/Throwable;)Ljava/lang/Throwable;
    //   2934: athrow
    //   2935: aload #16
    //   2937: bipush #7
    //   2939: iaload
    //   2940: aload #16
    //   2942: iconst_4
    //   2943: iaload
    //   2944: bipush #6
    //   2946: iushr
    //   2947: aload #16
    //   2949: iconst_4
    //   2950: iaload
    //   2951: bipush #26
    //   2953: ishl
    //   2954: ior
    //   2955: aload #16
    //   2957: iconst_4
    //   2958: iaload
    //   2959: bipush #11
    //   2961: iushr
    //   2962: aload #16
    //   2964: iconst_4
    //   2965: iaload
    //   2966: bipush #21
    //   2968: ishl
    //   2969: ior
    //   2970: ixor
    //   2971: aload #16
    //   2973: iconst_4
    //   2974: iaload
    //   2975: bipush #25
    //   2977: iushr
    //   2978: aload #16
    //   2980: iconst_4
    //   2981: iaload
    //   2982: bipush #7
    //   2984: ishl
    //   2985: ior
    //   2986: ixor
    //   2987: iadd
    //   2988: aload #16
    //   2990: bipush #6
    //   2992: iaload
    //   2993: aload #16
    //   2995: iconst_4
    //   2996: iaload
    //   2997: aload #16
    //   2999: iconst_5
    //   3000: iaload
    //   3001: aload #16
    //   3003: bipush #6
    //   3005: iaload
    //   3006: ixor
    //   3007: iand
    //   3008: ixor
    //   3009: iadd
    //   3010: aload #7
    //   3012: iload #17
    //   3014: iaload
    //   3015: iadd
    //   3016: aload #15
    //   3018: iload #17
    //   3020: iaload
    //   3021: iadd
    //   3022: istore #18
    //   3024: aload #16
    //   3026: iconst_0
    //   3027: iaload
    //   3028: iconst_2
    //   3029: iushr
    //   3030: aload #16
    //   3032: iconst_0
    //   3033: iaload
    //   3034: bipush #30
    //   3036: ishl
    //   3037: ior
    //   3038: aload #16
    //   3040: iconst_0
    //   3041: iaload
    //   3042: bipush #13
    //   3044: iushr
    //   3045: aload #16
    //   3047: iconst_0
    //   3048: iaload
    //   3049: bipush #19
    //   3051: ishl
    //   3052: ior
    //   3053: ixor
    //   3054: aload #16
    //   3056: iconst_0
    //   3057: iaload
    //   3058: bipush #22
    //   3060: iushr
    //   3061: aload #16
    //   3063: iconst_0
    //   3064: iaload
    //   3065: bipush #10
    //   3067: ishl
    //   3068: ior
    //   3069: ixor
    //   3070: aload #16
    //   3072: iconst_0
    //   3073: iaload
    //   3074: aload #16
    //   3076: iconst_1
    //   3077: iaload
    //   3078: iand
    //   3079: aload #16
    //   3081: iconst_2
    //   3082: iaload
    //   3083: aload #16
    //   3085: iconst_0
    //   3086: iaload
    //   3087: aload #16
    //   3089: iconst_1
    //   3090: iaload
    //   3091: ior
    //   3092: iand
    //   3093: ior
    //   3094: iadd
    //   3095: istore #19
    //   3097: aload #16
    //   3099: iconst_3
    //   3100: dup2
    //   3101: iaload
    //   3102: iload #18
    //   3104: iadd
    //   3105: iastore
    //   3106: aload #16
    //   3108: bipush #7
    //   3110: iload #18
    //   3112: iload #19
    //   3114: iadd
    //   3115: iastore
    //   3116: aload #16
    //   3118: bipush #7
    //   3120: iaload
    //   3121: istore #18
    //   3123: aload #16
    //   3125: bipush #7
    //   3127: aload #16
    //   3129: bipush #6
    //   3131: iaload
    //   3132: iastore
    //   3133: aload #16
    //   3135: bipush #6
    //   3137: aload #16
    //   3139: iconst_5
    //   3140: iaload
    //   3141: iastore
    //   3142: aload #16
    //   3144: iconst_5
    //   3145: aload #16
    //   3147: iconst_4
    //   3148: iaload
    //   3149: iastore
    //   3150: aload #16
    //   3152: iconst_4
    //   3153: aload #16
    //   3155: iconst_3
    //   3156: iaload
    //   3157: iastore
    //   3158: aload #16
    //   3160: iconst_3
    //   3161: aload #16
    //   3163: iconst_2
    //   3164: iaload
    //   3165: iastore
    //   3166: aload #16
    //   3168: iconst_2
    //   3169: aload #16
    //   3171: iconst_1
    //   3172: iaload
    //   3173: iastore
    //   3174: aload #16
    //   3176: iconst_1
    //   3177: aload #16
    //   3179: iconst_0
    //   3180: iaload
    //   3181: iastore
    //   3182: aload #16
    //   3184: iconst_0
    //   3185: iload #18
    //   3187: iastore
    //   3188: iinc #17, 1
    //   3191: iload_2
    //   3192: ifne -> 2700
    //   3195: iconst_0
    //   3196: istore #17
    //   3198: iload #17
    //   3200: bipush #8
    //   3202: if_icmpge -> 3225
    //   3205: aload #9
    //   3207: iload #17
    //   3209: dup2
    //   3210: iaload
    //   3211: aload #16
    //   3213: iload #17
    //   3215: iaload
    //   3216: iadd
    //   3217: iastore
    //   3218: iinc #17, 1
    //   3221: iload_2
    //   3222: ifne -> 3198
    //   3225: iinc #14, 64
    //   3228: iinc #12, -64
    //   3231: iload_2
    //   3232: ifne -> 2621
    //   3235: iload #12
    //   3237: ifle -> 3273
    //   3240: iconst_0
    //   3241: istore #15
    //   3243: iload #15
    //   3245: iload #12
    //   3247: if_icmpge -> 3273
    //   3250: aload #10
    //   3252: iload #13
    //   3254: iload #15
    //   3256: iadd
    //   3257: aload #4
    //   3259: iload #14
    //   3261: iload #15
    //   3263: iadd
    //   3264: baload
    //   3265: bastore
    //   3266: iinc #15, 1
    //   3269: iload_2
    //   3270: ifne -> 3243
    //   3273: aload #8
    //   3275: iconst_0
    //   3276: iaload
    //   3277: bipush #29
    //   3279: iushr
    //   3280: aload #8
    //   3282: iconst_1
    //   3283: iaload
    //   3284: iconst_3
    //   3285: ishl
    //   3286: ior
    //   3287: istore #15
    //   3289: aload #8
    //   3291: iconst_0
    //   3292: iaload
    //   3293: iconst_3
    //   3294: ishl
    //   3295: istore #16
    //   3297: aload #8
    //   3299: iconst_0
    //   3300: iaload
    //   3301: bipush #63
    //   3303: iand
    //   3304: istore #17
    //   3306: iload #17
    //   3308: bipush #56
    //   3310: if_icmpge -> 3325
    //   3313: bipush #56
    //   3315: iload #17
    //   3317: isub
    //   3318: goto -> 3330
    //   3321: invokestatic a : (Ljava/lang/Throwable;)Ljava/lang/Throwable;
    //   3324: athrow
    //   3325: bipush #120
    //   3327: iload #17
    //   3329: isub
    //   3330: istore #18
    //   3332: aload #8
    //   3334: iconst_0
    //   3335: iaload
    //   3336: bipush #63
    //   3338: iand
    //   3339: istore #13
    //   3341: bipush #64
    //   3343: iload #13
    //   3345: isub
    //   3346: istore #19
    //   3348: aload #8
    //   3350: iconst_0
    //   3351: dup2
    //   3352: iaload
    //   3353: iload #18
    //   3355: iadd
    //   3356: iastore
    //   3357: aload #8
    //   3359: iconst_0
    //   3360: dup2
    //   3361: iaload
    //   3362: iconst_m1
    //   3363: iand
    //   3364: iastore
    //   3365: aload #8
    //   3367: iconst_0
    //   3368: iaload
    //   3369: iload #18
    //   3371: if_icmpge -> 3389
    //   3374: aload #8
    //   3376: iconst_1
    //   3377: dup2
    //   3378: iaload
    //   3379: iconst_1
    //   3380: iadd
    //   3381: iastore
    //   3382: goto -> 3389
    //   3385: invokestatic a : (Ljava/lang/Throwable;)Ljava/lang/Throwable;
    //   3388: athrow
    //   3389: iconst_0
    //   3390: istore #14
    //   3392: iload #13
    //   3394: ifle -> 4025
    //   3397: iload #18
    //   3399: iload #19
    //   3401: if_icmplt -> 4025
    //   3404: goto -> 3411
    //   3407: invokestatic a : (Ljava/lang/Throwable;)Ljava/lang/Throwable;
    //   3410: athrow
    //   3411: iconst_0
    //   3412: istore #20
    //   3414: iload #20
    //   3416: iload #19
    //   3418: if_icmpge -> 3441
    //   3421: aload #10
    //   3423: iload #13
    //   3425: iload #20
    //   3427: iadd
    //   3428: aload #6
    //   3430: iload #20
    //   3432: baload
    //   3433: bastore
    //   3434: iinc #20, 1
    //   3437: iload_2
    //   3438: ifne -> 3414
    //   3441: bipush #64
    //   3443: newarray int
    //   3445: astore #20
    //   3447: bipush #8
    //   3449: newarray int
    //   3451: astore #21
    //   3453: iconst_0
    //   3454: istore #22
    //   3456: iload #22
    //   3458: bipush #8
    //   3460: if_icmpge -> 3480
    //   3463: aload #21
    //   3465: iload #22
    //   3467: aload #9
    //   3469: iload #22
    //   3471: iaload
    //   3472: iastore
    //   3473: iinc #22, 1
    //   3476: iload_2
    //   3477: ifne -> 3456
    //   3480: iconst_0
    //   3481: istore #22
    //   3483: iload #22
    //   3485: bipush #64
    //   3487: if_icmpge -> 3978
    //   3490: iload #22
    //   3492: bipush #16
    //   3494: if_icmpge -> 3575
    //   3497: aload #20
    //   3499: iload #22
    //   3501: aload #10
    //   3503: iconst_4
    //   3504: iload #22
    //   3506: imul
    //   3507: baload
    //   3508: sipush #255
    //   3511: iand
    //   3512: bipush #24
    //   3514: ishl
    //   3515: aload #10
    //   3517: iconst_4
    //   3518: iload #22
    //   3520: imul
    //   3521: iconst_1
    //   3522: iadd
    //   3523: baload
    //   3524: sipush #255
    //   3527: iand
    //   3528: bipush #16
    //   3530: ishl
    //   3531: ior
    //   3532: aload #10
    //   3534: iconst_4
    //   3535: iload #22
    //   3537: imul
    //   3538: iconst_2
    //   3539: iadd
    //   3540: baload
    //   3541: sipush #255
    //   3544: iand
    //   3545: bipush #8
    //   3547: ishl
    //   3548: ior
    //   3549: aload #10
    //   3551: iconst_4
    //   3552: iload #22
    //   3554: imul
    //   3555: iconst_3
    //   3556: iadd
    //   3557: baload
    //   3558: sipush #255
    //   3561: iand
    //   3562: ior
    //   3563: iastore
    //   3564: iload_2
    //   3565: ifne -> 3718
    //   3568: goto -> 3575
    //   3571: invokestatic a : (Ljava/lang/Throwable;)Ljava/lang/Throwable;
    //   3574: athrow
    //   3575: aload #20
    //   3577: iload #22
    //   3579: aload #20
    //   3581: iload #22
    //   3583: iconst_2
    //   3584: isub
    //   3585: iaload
    //   3586: bipush #17
    //   3588: iushr
    //   3589: aload #20
    //   3591: iload #22
    //   3593: iconst_2
    //   3594: isub
    //   3595: iaload
    //   3596: bipush #15
    //   3598: ishl
    //   3599: ior
    //   3600: aload #20
    //   3602: iload #22
    //   3604: iconst_2
    //   3605: isub
    //   3606: iaload
    //   3607: bipush #19
    //   3609: iushr
    //   3610: aload #20
    //   3612: iload #22
    //   3614: iconst_2
    //   3615: isub
    //   3616: iaload
    //   3617: bipush #13
    //   3619: ishl
    //   3620: ior
    //   3621: ixor
    //   3622: aload #20
    //   3624: iload #22
    //   3626: iconst_2
    //   3627: isub
    //   3628: iaload
    //   3629: bipush #10
    //   3631: iushr
    //   3632: ixor
    //   3633: aload #20
    //   3635: iload #22
    //   3637: bipush #7
    //   3639: isub
    //   3640: iaload
    //   3641: iadd
    //   3642: aload #20
    //   3644: iload #22
    //   3646: bipush #15
    //   3648: isub
    //   3649: iaload
    //   3650: bipush #7
    //   3652: iushr
    //   3653: aload #20
    //   3655: iload #22
    //   3657: bipush #15
    //   3659: isub
    //   3660: iaload
    //   3661: bipush #25
    //   3663: ishl
    //   3664: ior
    //   3665: aload #20
    //   3667: iload #22
    //   3669: bipush #15
    //   3671: isub
    //   3672: iaload
    //   3673: bipush #18
    //   3675: iushr
    //   3676: aload #20
    //   3678: iload #22
    //   3680: bipush #15
    //   3682: isub
    //   3683: iaload
    //   3684: bipush #14
    //   3686: ishl
    //   3687: ior
    //   3688: ixor
    //   3689: aload #20
    //   3691: iload #22
    //   3693: bipush #15
    //   3695: isub
    //   3696: iaload
    //   3697: iconst_3
    //   3698: iushr
    //   3699: ixor
    //   3700: iadd
    //   3701: aload #20
    //   3703: iload #22
    //   3705: bipush #16
    //   3707: isub
    //   3708: iaload
    //   3709: iadd
    //   3710: iastore
    //   3711: goto -> 3718
    //   3714: invokestatic a : (Ljava/lang/Throwable;)Ljava/lang/Throwable;
    //   3717: athrow
    //   3718: aload #21
    //   3720: bipush #7
    //   3722: iaload
    //   3723: aload #21
    //   3725: iconst_4
    //   3726: iaload
    //   3727: bipush #6
    //   3729: iushr
    //   3730: aload #21
    //   3732: iconst_4
    //   3733: iaload
    //   3734: bipush #26
    //   3736: ishl
    //   3737: ior
    //   3738: aload #21
    //   3740: iconst_4
    //   3741: iaload
    //   3742: bipush #11
    //   3744: iushr
    //   3745: aload #21
    //   3747: iconst_4
    //   3748: iaload
    //   3749: bipush #21
    //   3751: ishl
    //   3752: ior
    //   3753: ixor
    //   3754: aload #21
    //   3756: iconst_4
    //   3757: iaload
    //   3758: bipush #25
    //   3760: iushr
    //   3761: aload #21
    //   3763: iconst_4
    //   3764: iaload
    //   3765: bipush #7
    //   3767: ishl
    //   3768: ior
    //   3769: ixor
    //   3770: iadd
    //   3771: aload #21
    //   3773: bipush #6
    //   3775: iaload
    //   3776: aload #21
    //   3778: iconst_4
    //   3779: iaload
    //   3780: aload #21
    //   3782: iconst_5
    //   3783: iaload
    //   3784: aload #21
    //   3786: bipush #6
    //   3788: iaload
    //   3789: ixor
    //   3790: iand
    //   3791: ixor
    //   3792: iadd
    //   3793: aload #7
    //   3795: iload #22
    //   3797: iaload
    //   3798: iadd
    //   3799: aload #20
    //   3801: iload #22
    //   3803: iaload
    //   3804: iadd
    //   3805: istore #23
    //   3807: aload #21
    //   3809: iconst_0
    //   3810: iaload
    //   3811: iconst_2
    //   3812: iushr
    //   3813: aload #21
    //   3815: iconst_0
    //   3816: iaload
    //   3817: bipush #30
    //   3819: ishl
    //   3820: ior
    //   3821: aload #21
    //   3823: iconst_0
    //   3824: iaload
    //   3825: bipush #13
    //   3827: iushr
    //   3828: aload #21
    //   3830: iconst_0
    //   3831: iaload
    //   3832: bipush #19
    //   3834: ishl
    //   3835: ior
    //   3836: ixor
    //   3837: aload #21
    //   3839: iconst_0
    //   3840: iaload
    //   3841: bipush #22
    //   3843: iushr
    //   3844: aload #21
    //   3846: iconst_0
    //   3847: iaload
    //   3848: bipush #10
    //   3850: ishl
    //   3851: ior
    //   3852: ixor
    //   3853: aload #21
    //   3855: iconst_0
    //   3856: iaload
    //   3857: aload #21
    //   3859: iconst_1
    //   3860: iaload
    //   3861: iand
    //   3862: aload #21
    //   3864: iconst_2
    //   3865: iaload
    //   3866: aload #21
    //   3868: iconst_0
    //   3869: iaload
    //   3870: aload #21
    //   3872: iconst_1
    //   3873: iaload
    //   3874: ior
    //   3875: iand
    //   3876: ior
    //   3877: iadd
    //   3878: istore #24
    //   3880: aload #21
    //   3882: iconst_3
    //   3883: dup2
    //   3884: iaload
    //   3885: iload #23
    //   3887: iadd
    //   3888: iastore
    //   3889: aload #21
    //   3891: bipush #7
    //   3893: iload #23
    //   3895: iload #24
    //   3897: iadd
    //   3898: iastore
    //   3899: aload #21
    //   3901: bipush #7
    //   3903: iaload
    //   3904: istore #23
    //   3906: aload #21
    //   3908: bipush #7
    //   3910: aload #21
    //   3912: bipush #6
    //   3914: iaload
    //   3915: iastore
    //   3916: aload #21
    //   3918: bipush #6
    //   3920: aload #21
    //   3922: iconst_5
    //   3923: iaload
    //   3924: iastore
    //   3925: aload #21
    //   3927: iconst_5
    //   3928: aload #21
    //   3930: iconst_4
    //   3931: iaload
    //   3932: iastore
    //   3933: aload #21
    //   3935: iconst_4
    //   3936: aload #21
    //   3938: iconst_3
    //   3939: iaload
    //   3940: iastore
    //   3941: aload #21
    //   3943: iconst_3
    //   3944: aload #21
    //   3946: iconst_2
    //   3947: iaload
    //   3948: iastore
    //   3949: aload #21
    //   3951: iconst_2
    //   3952: aload #21
    //   3954: iconst_1
    //   3955: iaload
    //   3956: iastore
    //   3957: aload #21
    //   3959: iconst_1
    //   3960: aload #21
    //   3962: iconst_0
    //   3963: iaload
    //   3964: iastore
    //   3965: aload #21
    //   3967: iconst_0
    //   3968: iload #23
    //   3970: iastore
    //   3971: iinc #22, 1
    //   3974: iload_2
    //   3975: ifne -> 3483
    //   3978: iconst_0
    //   3979: istore #22
    //   3981: iload #22
    //   3983: bipush #8
    //   3985: if_icmpge -> 4008
    //   3988: aload #9
    //   3990: iload #22
    //   3992: dup2
    //   3993: iaload
    //   3994: aload #21
    //   3996: iload #22
    //   3998: iaload
    //   3999: iadd
    //   4000: iastore
    //   4001: iinc #22, 1
    //   4004: iload_2
    //   4005: ifne -> 3981
    //   4008: iload #14
    //   4010: iload #19
    //   4012: iadd
    //   4013: istore #14
    //   4015: iload #18
    //   4017: iload #19
    //   4019: isub
    //   4020: istore #18
    //   4022: iconst_0
    //   4023: istore #13
    //   4025: iload #18
    //   4027: bipush #64
    //   4029: if_icmplt -> 4639
    //   4032: iconst_0
    //   4033: istore #20
    //   4035: iload #20
    //   4037: bipush #64
    //   4039: if_icmpge -> 4062
    //   4042: aload #11
    //   4044: iload #20
    //   4046: aload #6
    //   4048: iload #14
    //   4050: iload #20
    //   4052: iadd
    //   4053: baload
    //   4054: bastore
    //   4055: iinc #20, 1
    //   4058: iload_2
    //   4059: ifne -> 4035
    //   4062: bipush #64
    //   4064: newarray int
    //   4066: astore #20
    //   4068: bipush #8
    //   4070: newarray int
    //   4072: astore #21
    //   4074: iconst_0
    //   4075: istore #22
    //   4077: iload #22
    //   4079: bipush #8
    //   4081: if_icmpge -> 4101
    //   4084: aload #21
    //   4086: iload #22
    //   4088: aload #9
    //   4090: iload #22
    //   4092: iaload
    //   4093: iastore
    //   4094: iinc #22, 1
    //   4097: iload_2
    //   4098: ifne -> 4077
    //   4101: iconst_0
    //   4102: istore #22
    //   4104: iload #22
    //   4106: bipush #64
    //   4108: if_icmpge -> 4599
    //   4111: iload #22
    //   4113: bipush #16
    //   4115: if_icmpge -> 4196
    //   4118: aload #20
    //   4120: iload #22
    //   4122: aload #11
    //   4124: iconst_4
    //   4125: iload #22
    //   4127: imul
    //   4128: baload
    //   4129: sipush #255
    //   4132: iand
    //   4133: bipush #24
    //   4135: ishl
    //   4136: aload #11
    //   4138: iconst_4
    //   4139: iload #22
    //   4141: imul
    //   4142: iconst_1
    //   4143: iadd
    //   4144: baload
    //   4145: sipush #255
    //   4148: iand
    //   4149: bipush #16
    //   4151: ishl
    //   4152: ior
    //   4153: aload #11
    //   4155: iconst_4
    //   4156: iload #22
    //   4158: imul
    //   4159: iconst_2
    //   4160: iadd
    //   4161: baload
    //   4162: sipush #255
    //   4165: iand
    //   4166: bipush #8
    //   4168: ishl
    //   4169: ior
    //   4170: aload #11
    //   4172: iconst_4
    //   4173: iload #22
    //   4175: imul
    //   4176: iconst_3
    //   4177: iadd
    //   4178: baload
    //   4179: sipush #255
    //   4182: iand
    //   4183: ior
    //   4184: iastore
    //   4185: iload_2
    //   4186: ifne -> 4339
    //   4189: goto -> 4196
    //   4192: invokestatic a : (Ljava/lang/Throwable;)Ljava/lang/Throwable;
    //   4195: athrow
    //   4196: aload #20
    //   4198: iload #22
    //   4200: aload #20
    //   4202: iload #22
    //   4204: iconst_2
    //   4205: isub
    //   4206: iaload
    //   4207: bipush #17
    //   4209: iushr
    //   4210: aload #20
    //   4212: iload #22
    //   4214: iconst_2
    //   4215: isub
    //   4216: iaload
    //   4217: bipush #15
    //   4219: ishl
    //   4220: ior
    //   4221: aload #20
    //   4223: iload #22
    //   4225: iconst_2
    //   4226: isub
    //   4227: iaload
    //   4228: bipush #19
    //   4230: iushr
    //   4231: aload #20
    //   4233: iload #22
    //   4235: iconst_2
    //   4236: isub
    //   4237: iaload
    //   4238: bipush #13
    //   4240: ishl
    //   4241: ior
    //   4242: ixor
    //   4243: aload #20
    //   4245: iload #22
    //   4247: iconst_2
    //   4248: isub
    //   4249: iaload
    //   4250: bipush #10
    //   4252: iushr
    //   4253: ixor
    //   4254: aload #20
    //   4256: iload #22
    //   4258: bipush #7
    //   4260: isub
    //   4261: iaload
    //   4262: iadd
    //   4263: aload #20
    //   4265: iload #22
    //   4267: bipush #15
    //   4269: isub
    //   4270: iaload
    //   4271: bipush #7
    //   4273: iushr
    //   4274: aload #20
    //   4276: iload #22
    //   4278: bipush #15
    //   4280: isub
    //   4281: iaload
    //   4282: bipush #25
    //   4284: ishl
    //   4285: ior
    //   4286: aload #20
    //   4288: iload #22
    //   4290: bipush #15
    //   4292: isub
    //   4293: iaload
    //   4294: bipush #18
    //   4296: iushr
    //   4297: aload #20
    //   4299: iload #22
    //   4301: bipush #15
    //   4303: isub
    //   4304: iaload
    //   4305: bipush #14
    //   4307: ishl
    //   4308: ior
    //   4309: ixor
    //   4310: aload #20
    //   4312: iload #22
    //   4314: bipush #15
    //   4316: isub
    //   4317: iaload
    //   4318: iconst_3
    //   4319: iushr
    //   4320: ixor
    //   4321: iadd
    //   4322: aload #20
    //   4324: iload #22
    //   4326: bipush #16
    //   4328: isub
    //   4329: iaload
    //   4330: iadd
    //   4331: iastore
    //   4332: goto -> 4339
    //   4335: invokestatic a : (Ljava/lang/Throwable;)Ljava/lang/Throwable;
    //   4338: athrow
    //   4339: aload #21
    //   4341: bipush #7
    //   4343: iaload
    //   4344: aload #21
    //   4346: iconst_4
    //   4347: iaload
    //   4348: bipush #6
    //   4350: iushr
    //   4351: aload #21
    //   4353: iconst_4
    //   4354: iaload
    //   4355: bipush #26
    //   4357: ishl
    //   4358: ior
    //   4359: aload #21
    //   4361: iconst_4
    //   4362: iaload
    //   4363: bipush #11
    //   4365: iushr
    //   4366: aload #21
    //   4368: iconst_4
    //   4369: iaload
    //   4370: bipush #21
    //   4372: ishl
    //   4373: ior
    //   4374: ixor
    //   4375: aload #21
    //   4377: iconst_4
    //   4378: iaload
    //   4379: bipush #25
    //   4381: iushr
    //   4382: aload #21
    //   4384: iconst_4
    //   4385: iaload
    //   4386: bipush #7
    //   4388: ishl
    //   4389: ior
    //   4390: ixor
    //   4391: iadd
    //   4392: aload #21
    //   4394: bipush #6
    //   4396: iaload
    //   4397: aload #21
    //   4399: iconst_4
    //   4400: iaload
    //   4401: aload #21
    //   4403: iconst_5
    //   4404: iaload
    //   4405: aload #21
    //   4407: bipush #6
    //   4409: iaload
    //   4410: ixor
    //   4411: iand
    //   4412: ixor
    //   4413: iadd
    //   4414: aload #7
    //   4416: iload #22
    //   4418: iaload
    //   4419: iadd
    //   4420: aload #20
    //   4422: iload #22
    //   4424: iaload
    //   4425: iadd
    //   4426: istore #23
    //   4428: aload #21
    //   4430: iconst_0
    //   4431: iaload
    //   4432: iconst_2
    //   4433: iushr
    //   4434: aload #21
    //   4436: iconst_0
    //   4437: iaload
    //   4438: bipush #30
    //   4440: ishl
    //   4441: ior
    //   4442: aload #21
    //   4444: iconst_0
    //   4445: iaload
    //   4446: bipush #13
    //   4448: iushr
    //   4449: aload #21
    //   4451: iconst_0
    //   4452: iaload
    //   4453: bipush #19
    //   4455: ishl
    //   4456: ior
    //   4457: ixor
    //   4458: aload #21
    //   4460: iconst_0
    //   4461: iaload
    //   4462: bipush #22
    //   4464: iushr
    //   4465: aload #21
    //   4467: iconst_0
    //   4468: iaload
    //   4469: bipush #10
    //   4471: ishl
    //   4472: ior
    //   4473: ixor
    //   4474: aload #21
    //   4476: iconst_0
    //   4477: iaload
    //   4478: aload #21
    //   4480: iconst_1
    //   4481: iaload
    //   4482: iand
    //   4483: aload #21
    //   4485: iconst_2
    //   4486: iaload
    //   4487: aload #21
    //   4489: iconst_0
    //   4490: iaload
    //   4491: aload #21
    //   4493: iconst_1
    //   4494: iaload
    //   4495: ior
    //   4496: iand
    //   4497: ior
    //   4498: iadd
    //   4499: istore #24
    //   4501: aload #21
    //   4503: iconst_3
    //   4504: dup2
    //   4505: iaload
    //   4506: iload #23
    //   4508: iadd
    //   4509: iastore
    //   4510: aload #21
    //   4512: bipush #7
    //   4514: iload #23
    //   4516: iload #24
    //   4518: iadd
    //   4519: iastore
    //   4520: aload #21
    //   4522: bipush #7
    //   4524: iaload
    //   4525: istore #23
    //   4527: aload #21
    //   4529: bipush #7
    //   4531: aload #21
    //   4533: bipush #6
    //   4535: iaload
    //   4536: iastore
    //   4537: aload #21
    //   4539: bipush #6
    //   4541: aload #21
    //   4543: iconst_5
    //   4544: iaload
    //   4545: iastore
    //   4546: aload #21
    //   4548: iconst_5
    //   4549: aload #21
    //   4551: iconst_4
    //   4552: iaload
    //   4553: iastore
    //   4554: aload #21
    //   4556: iconst_4
    //   4557: aload #21
    //   4559: iconst_3
    //   4560: iaload
    //   4561: iastore
    //   4562: aload #21
    //   4564: iconst_3
    //   4565: aload #21
    //   4567: iconst_2
    //   4568: iaload
    //   4569: iastore
    //   4570: aload #21
    //   4572: iconst_2
    //   4573: aload #21
    //   4575: iconst_1
    //   4576: iaload
    //   4577: iastore
    //   4578: aload #21
    //   4580: iconst_1
    //   4581: aload #21
    //   4583: iconst_0
    //   4584: iaload
    //   4585: iastore
    //   4586: aload #21
    //   4588: iconst_0
    //   4589: iload #23
    //   4591: iastore
    //   4592: iinc #22, 1
    //   4595: iload_2
    //   4596: ifne -> 4104
    //   4599: iconst_0
    //   4600: istore #22
    //   4602: iload #22
    //   4604: bipush #8
    //   4606: if_icmpge -> 4629
    //   4609: aload #9
    //   4611: iload #22
    //   4613: dup2
    //   4614: iaload
    //   4615: aload #21
    //   4617: iload #22
    //   4619: iaload
    //   4620: iadd
    //   4621: iastore
    //   4622: iinc #22, 1
    //   4625: iload_2
    //   4626: ifne -> 4602
    //   4629: iinc #14, 64
    //   4632: iinc #18, -64
    //   4635: iload_2
    //   4636: ifne -> 4025
    //   4639: iload #18
    //   4641: ifle -> 4677
    //   4644: iconst_0
    //   4645: istore #20
    //   4647: iload #20
    //   4649: iload #18
    //   4651: if_icmpge -> 4677
    //   4654: aload #10
    //   4656: iload #13
    //   4658: iload #20
    //   4660: iadd
    //   4661: aload #6
    //   4663: iload #14
    //   4665: iload #20
    //   4667: iadd
    //   4668: baload
    //   4669: bastore
    //   4670: iinc #20, 1
    //   4673: iload_2
    //   4674: ifne -> 4647
    //   4677: bipush #8
    //   4679: newarray byte
    //   4681: astore #20
    //   4683: aload #20
    //   4685: iconst_0
    //   4686: iload #15
    //   4688: bipush #24
    //   4690: iushr
    //   4691: i2b
    //   4692: bastore
    //   4693: aload #20
    //   4695: iconst_1
    //   4696: iload #15
    //   4698: bipush #16
    //   4700: iushr
    //   4701: i2b
    //   4702: bastore
    //   4703: aload #20
    //   4705: iconst_2
    //   4706: iload #15
    //   4708: bipush #8
    //   4710: iushr
    //   4711: i2b
    //   4712: bastore
    //   4713: aload #20
    //   4715: iconst_3
    //   4716: iload #15
    //   4718: i2b
    //   4719: bastore
    //   4720: aload #20
    //   4722: iconst_4
    //   4723: iload #16
    //   4725: bipush #24
    //   4727: iushr
    //   4728: i2b
    //   4729: bastore
    //   4730: aload #20
    //   4732: iconst_5
    //   4733: iload #16
    //   4735: bipush #16
    //   4737: iushr
    //   4738: i2b
    //   4739: bastore
    //   4740: aload #20
    //   4742: bipush #6
    //   4744: iload #16
    //   4746: bipush #8
    //   4748: iushr
    //   4749: i2b
    //   4750: bastore
    //   4751: aload #20
    //   4753: bipush #7
    //   4755: iload #16
    //   4757: i2b
    //   4758: bastore
    //   4759: bipush #8
    //   4761: istore #12
    //   4763: aload #8
    //   4765: iconst_0
    //   4766: iaload
    //   4767: bipush #63
    //   4769: iand
    //   4770: istore #13
    //   4772: bipush #64
    //   4774: iload #13
    //   4776: isub
    //   4777: istore #19
    //   4779: aload #8
    //   4781: iconst_0
    //   4782: dup2
    //   4783: iaload
    //   4784: iload #12
    //   4786: iadd
    //   4787: iastore
    //   4788: aload #8
    //   4790: iconst_0
    //   4791: dup2
    //   4792: iaload
    //   4793: iconst_m1
    //   4794: iand
    //   4795: iastore
    //   4796: aload #8
    //   4798: iconst_0
    //   4799: iaload
    //   4800: iload #12
    //   4802: if_icmpge -> 4820
    //   4805: aload #8
    //   4807: iconst_1
    //   4808: dup2
    //   4809: iaload
    //   4810: iconst_1
    //   4811: iadd
    //   4812: iastore
    //   4813: goto -> 4820
    //   4816: invokestatic a : (Ljava/lang/Throwable;)Ljava/lang/Throwable;
    //   4819: athrow
    //   4820: iload #13
    //   4822: ifle -> 5436
    //   4825: iload #12
    //   4827: iload #19
    //   4829: if_icmplt -> 5436
    //   4832: goto -> 4839
    //   4835: invokestatic a : (Ljava/lang/Throwable;)Ljava/lang/Throwable;
    //   4838: athrow
    //   4839: iconst_0
    //   4840: istore #21
    //   4842: iload #21
    //   4844: iload #19
    //   4846: if_icmpge -> 4869
    //   4849: aload #10
    //   4851: iload #13
    //   4853: iload #21
    //   4855: iadd
    //   4856: aload #20
    //   4858: iload #21
    //   4860: baload
    //   4861: bastore
    //   4862: iinc #21, 1
    //   4865: iload_2
    //   4866: ifne -> 4842
    //   4869: bipush #64
    //   4871: newarray int
    //   4873: astore #21
    //   4875: bipush #8
    //   4877: newarray int
    //   4879: astore #22
    //   4881: iconst_0
    //   4882: istore #23
    //   4884: iload #23
    //   4886: bipush #8
    //   4888: if_icmpge -> 4908
    //   4891: aload #22
    //   4893: iload #23
    //   4895: aload #9
    //   4897: iload #23
    //   4899: iaload
    //   4900: iastore
    //   4901: iinc #23, 1
    //   4904: iload_2
    //   4905: ifne -> 4884
    //   4908: iconst_0
    //   4909: istore #23
    //   4911: iload #23
    //   4913: bipush #64
    //   4915: if_icmpge -> 5406
    //   4918: iload #23
    //   4920: bipush #16
    //   4922: if_icmpge -> 5003
    //   4925: aload #21
    //   4927: iload #23
    //   4929: aload #10
    //   4931: iconst_4
    //   4932: iload #23
    //   4934: imul
    //   4935: baload
    //   4936: sipush #255
    //   4939: iand
    //   4940: bipush #24
    //   4942: ishl
    //   4943: aload #10
    //   4945: iconst_4
    //   4946: iload #23
    //   4948: imul
    //   4949: iconst_1
    //   4950: iadd
    //   4951: baload
    //   4952: sipush #255
    //   4955: iand
    //   4956: bipush #16
    //   4958: ishl
    //   4959: ior
    //   4960: aload #10
    //   4962: iconst_4
    //   4963: iload #23
    //   4965: imul
    //   4966: iconst_2
    //   4967: iadd
    //   4968: baload
    //   4969: sipush #255
    //   4972: iand
    //   4973: bipush #8
    //   4975: ishl
    //   4976: ior
    //   4977: aload #10
    //   4979: iconst_4
    //   4980: iload #23
    //   4982: imul
    //   4983: iconst_3
    //   4984: iadd
    //   4985: baload
    //   4986: sipush #255
    //   4989: iand
    //   4990: ior
    //   4991: iastore
    //   4992: iload_2
    //   4993: ifne -> 5146
    //   4996: goto -> 5003
    //   4999: invokestatic a : (Ljava/lang/Throwable;)Ljava/lang/Throwable;
    //   5002: athrow
    //   5003: aload #21
    //   5005: iload #23
    //   5007: aload #21
    //   5009: iload #23
    //   5011: iconst_2
    //   5012: isub
    //   5013: iaload
    //   5014: bipush #17
    //   5016: iushr
    //   5017: aload #21
    //   5019: iload #23
    //   5021: iconst_2
    //   5022: isub
    //   5023: iaload
    //   5024: bipush #15
    //   5026: ishl
    //   5027: ior
    //   5028: aload #21
    //   5030: iload #23
    //   5032: iconst_2
    //   5033: isub
    //   5034: iaload
    //   5035: bipush #19
    //   5037: iushr
    //   5038: aload #21
    //   5040: iload #23
    //   5042: iconst_2
    //   5043: isub
    //   5044: iaload
    //   5045: bipush #13
    //   5047: ishl
    //   5048: ior
    //   5049: ixor
    //   5050: aload #21
    //   5052: iload #23
    //   5054: iconst_2
    //   5055: isub
    //   5056: iaload
    //   5057: bipush #10
    //   5059: iushr
    //   5060: ixor
    //   5061: aload #21
    //   5063: iload #23
    //   5065: bipush #7
    //   5067: isub
    //   5068: iaload
    //   5069: iadd
    //   5070: aload #21
    //   5072: iload #23
    //   5074: bipush #15
    //   5076: isub
    //   5077: iaload
    //   5078: bipush #7
    //   5080: iushr
    //   5081: aload #21
    //   5083: iload #23
    //   5085: bipush #15
    //   5087: isub
    //   5088: iaload
    //   5089: bipush #25
    //   5091: ishl
    //   5092: ior
    //   5093: aload #21
    //   5095: iload #23
    //   5097: bipush #15
    //   5099: isub
    //   5100: iaload
    //   5101: bipush #18
    //   5103: iushr
    //   5104: aload #21
    //   5106: iload #23
    //   5108: bipush #15
    //   5110: isub
    //   5111: iaload
    //   5112: bipush #14
    //   5114: ishl
    //   5115: ior
    //   5116: ixor
    //   5117: aload #21
    //   5119: iload #23
    //   5121: bipush #15
    //   5123: isub
    //   5124: iaload
    //   5125: iconst_3
    //   5126: iushr
    //   5127: ixor
    //   5128: iadd
    //   5129: aload #21
    //   5131: iload #23
    //   5133: bipush #16
    //   5135: isub
    //   5136: iaload
    //   5137: iadd
    //   5138: iastore
    //   5139: goto -> 5146
    //   5142: invokestatic a : (Ljava/lang/Throwable;)Ljava/lang/Throwable;
    //   5145: athrow
    //   5146: aload #22
    //   5148: bipush #7
    //   5150: iaload
    //   5151: aload #22
    //   5153: iconst_4
    //   5154: iaload
    //   5155: bipush #6
    //   5157: iushr
    //   5158: aload #22
    //   5160: iconst_4
    //   5161: iaload
    //   5162: bipush #26
    //   5164: ishl
    //   5165: ior
    //   5166: aload #22
    //   5168: iconst_4
    //   5169: iaload
    //   5170: bipush #11
    //   5172: iushr
    //   5173: aload #22
    //   5175: iconst_4
    //   5176: iaload
    //   5177: bipush #21
    //   5179: ishl
    //   5180: ior
    //   5181: ixor
    //   5182: aload #22
    //   5184: iconst_4
    //   5185: iaload
    //   5186: bipush #25
    //   5188: iushr
    //   5189: aload #22
    //   5191: iconst_4
    //   5192: iaload
    //   5193: bipush #7
    //   5195: ishl
    //   5196: ior
    //   5197: ixor
    //   5198: iadd
    //   5199: aload #22
    //   5201: bipush #6
    //   5203: iaload
    //   5204: aload #22
    //   5206: iconst_4
    //   5207: iaload
    //   5208: aload #22
    //   5210: iconst_5
    //   5211: iaload
    //   5212: aload #22
    //   5214: bipush #6
    //   5216: iaload
    //   5217: ixor
    //   5218: iand
    //   5219: ixor
    //   5220: iadd
    //   5221: aload #7
    //   5223: iload #23
    //   5225: iaload
    //   5226: iadd
    //   5227: aload #21
    //   5229: iload #23
    //   5231: iaload
    //   5232: iadd
    //   5233: istore #24
    //   5235: aload #22
    //   5237: iconst_0
    //   5238: iaload
    //   5239: iconst_2
    //   5240: iushr
    //   5241: aload #22
    //   5243: iconst_0
    //   5244: iaload
    //   5245: bipush #30
    //   5247: ishl
    //   5248: ior
    //   5249: aload #22
    //   5251: iconst_0
    //   5252: iaload
    //   5253: bipush #13
    //   5255: iushr
    //   5256: aload #22
    //   5258: iconst_0
    //   5259: iaload
    //   5260: bipush #19
    //   5262: ishl
    //   5263: ior
    //   5264: ixor
    //   5265: aload #22
    //   5267: iconst_0
    //   5268: iaload
    //   5269: bipush #22
    //   5271: iushr
    //   5272: aload #22
    //   5274: iconst_0
    //   5275: iaload
    //   5276: bipush #10
    //   5278: ishl
    //   5279: ior
    //   5280: ixor
    //   5281: aload #22
    //   5283: iconst_0
    //   5284: iaload
    //   5285: aload #22
    //   5287: iconst_1
    //   5288: iaload
    //   5289: iand
    //   5290: aload #22
    //   5292: iconst_2
    //   5293: iaload
    //   5294: aload #22
    //   5296: iconst_0
    //   5297: iaload
    //   5298: aload #22
    //   5300: iconst_1
    //   5301: iaload
    //   5302: ior
    //   5303: iand
    //   5304: ior
    //   5305: iadd
    //   5306: istore #25
    //   5308: aload #22
    //   5310: iconst_3
    //   5311: dup2
    //   5312: iaload
    //   5313: iload #24
    //   5315: iadd
    //   5316: iastore
    //   5317: aload #22
    //   5319: bipush #7
    //   5321: iload #24
    //   5323: iload #25
    //   5325: iadd
    //   5326: iastore
    //   5327: aload #22
    //   5329: bipush #7
    //   5331: iaload
    //   5332: istore #24
    //   5334: aload #22
    //   5336: bipush #7
    //   5338: aload #22
    //   5340: bipush #6
    //   5342: iaload
    //   5343: iastore
    //   5344: aload #22
    //   5346: bipush #6
    //   5348: aload #22
    //   5350: iconst_5
    //   5351: iaload
    //   5352: iastore
    //   5353: aload #22
    //   5355: iconst_5
    //   5356: aload #22
    //   5358: iconst_4
    //   5359: iaload
    //   5360: iastore
    //   5361: aload #22
    //   5363: iconst_4
    //   5364: aload #22
    //   5366: iconst_3
    //   5367: iaload
    //   5368: iastore
    //   5369: aload #22
    //   5371: iconst_3
    //   5372: aload #22
    //   5374: iconst_2
    //   5375: iaload
    //   5376: iastore
    //   5377: aload #22
    //   5379: iconst_2
    //   5380: aload #22
    //   5382: iconst_1
    //   5383: iaload
    //   5384: iastore
    //   5385: aload #22
    //   5387: iconst_1
    //   5388: aload #22
    //   5390: iconst_0
    //   5391: iaload
    //   5392: iastore
    //   5393: aload #22
    //   5395: iconst_0
    //   5396: iload #24
    //   5398: iastore
    //   5399: iinc #23, 1
    //   5402: iload_2
    //   5403: ifne -> 4911
    //   5406: iconst_0
    //   5407: istore #23
    //   5409: iload #23
    //   5411: bipush #8
    //   5413: if_icmpge -> 5436
    //   5416: aload #9
    //   5418: iload #23
    //   5420: dup2
    //   5421: iaload
    //   5422: aload #22
    //   5424: iload #23
    //   5426: iaload
    //   5427: iadd
    //   5428: iastore
    //   5429: iinc #23, 1
    //   5432: iload_2
    //   5433: ifne -> 5409
    //   5436: bipush #32
    //   5438: newarray byte
    //   5440: astore #5
    //   5442: sipush #-17423
    //   5445: aload #5
    //   5447: iconst_0
    //   5448: aload #9
    //   5450: iconst_0
    //   5451: iaload
    //   5452: bipush #24
    //   5454: iushr
    //   5455: i2b
    //   5456: bastore
    //   5457: sipush #-25198
    //   5460: aload #5
    //   5462: iconst_1
    //   5463: aload #9
    //   5465: iconst_0
    //   5466: iaload
    //   5467: bipush #16
    //   5469: iushr
    //   5470: i2b
    //   5471: bastore
    //   5472: aload #5
    //   5474: iconst_2
    //   5475: aload #9
    //   5477: iconst_0
    //   5478: iaload
    //   5479: bipush #8
    //   5481: iushr
    //   5482: i2b
    //   5483: bastore
    //   5484: aload #5
    //   5486: iconst_3
    //   5487: aload #9
    //   5489: iconst_0
    //   5490: iaload
    //   5491: i2b
    //   5492: bastore
    //   5493: aload #5
    //   5495: iconst_4
    //   5496: aload #9
    //   5498: iconst_1
    //   5499: iaload
    //   5500: bipush #24
    //   5502: iushr
    //   5503: i2b
    //   5504: bastore
    //   5505: aload #5
    //   5507: iconst_5
    //   5508: aload #9
    //   5510: iconst_1
    //   5511: iaload
    //   5512: bipush #16
    //   5514: iushr
    //   5515: i2b
    //   5516: bastore
    //   5517: aload #5
    //   5519: bipush #6
    //   5521: aload #9
    //   5523: iconst_1
    //   5524: iaload
    //   5525: bipush #8
    //   5527: iushr
    //   5528: i2b
    //   5529: bastore
    //   5530: aload #5
    //   5532: bipush #7
    //   5534: aload #9
    //   5536: iconst_1
    //   5537: iaload
    //   5538: i2b
    //   5539: bastore
    //   5540: aload #5
    //   5542: bipush #8
    //   5544: aload #9
    //   5546: iconst_2
    //   5547: iaload
    //   5548: bipush #24
    //   5550: iushr
    //   5551: i2b
    //   5552: bastore
    //   5553: aload #5
    //   5555: bipush #9
    //   5557: aload #9
    //   5559: iconst_2
    //   5560: iaload
    //   5561: bipush #16
    //   5563: iushr
    //   5564: i2b
    //   5565: bastore
    //   5566: aload #5
    //   5568: bipush #10
    //   5570: aload #9
    //   5572: iconst_2
    //   5573: iaload
    //   5574: bipush #8
    //   5576: iushr
    //   5577: i2b
    //   5578: bastore
    //   5579: aload #5
    //   5581: bipush #11
    //   5583: aload #9
    //   5585: iconst_2
    //   5586: iaload
    //   5587: i2b
    //   5588: bastore
    //   5589: aload #5
    //   5591: bipush #12
    //   5593: aload #9
    //   5595: iconst_3
    //   5596: iaload
    //   5597: bipush #24
    //   5599: iushr
    //   5600: i2b
    //   5601: bastore
    //   5602: aload #5
    //   5604: bipush #13
    //   5606: aload #9
    //   5608: iconst_3
    //   5609: iaload
    //   5610: bipush #16
    //   5612: iushr
    //   5613: i2b
    //   5614: bastore
    //   5615: aload #5
    //   5617: bipush #14
    //   5619: aload #9
    //   5621: iconst_3
    //   5622: iaload
    //   5623: bipush #8
    //   5625: iushr
    //   5626: i2b
    //   5627: bastore
    //   5628: aload #5
    //   5630: bipush #15
    //   5632: aload #9
    //   5634: iconst_3
    //   5635: iaload
    //   5636: i2b
    //   5637: bastore
    //   5638: aload #5
    //   5640: bipush #16
    //   5642: aload #9
    //   5644: iconst_4
    //   5645: iaload
    //   5646: bipush #24
    //   5648: iushr
    //   5649: i2b
    //   5650: bastore
    //   5651: aload #5
    //   5653: bipush #17
    //   5655: aload #9
    //   5657: iconst_4
    //   5658: iaload
    //   5659: bipush #16
    //   5661: iushr
    //   5662: i2b
    //   5663: bastore
    //   5664: aload #5
    //   5666: bipush #18
    //   5668: aload #9
    //   5670: iconst_4
    //   5671: iaload
    //   5672: bipush #8
    //   5674: iushr
    //   5675: i2b
    //   5676: bastore
    //   5677: aload #5
    //   5679: bipush #19
    //   5681: aload #9
    //   5683: iconst_4
    //   5684: iaload
    //   5685: i2b
    //   5686: bastore
    //   5687: aload #5
    //   5689: bipush #20
    //   5691: aload #9
    //   5693: iconst_5
    //   5694: iaload
    //   5695: bipush #24
    //   5697: iushr
    //   5698: i2b
    //   5699: bastore
    //   5700: aload #5
    //   5702: bipush #21
    //   5704: aload #9
    //   5706: iconst_5
    //   5707: iaload
    //   5708: bipush #16
    //   5710: iushr
    //   5711: i2b
    //   5712: bastore
    //   5713: aload #5
    //   5715: bipush #22
    //   5717: aload #9
    //   5719: iconst_5
    //   5720: iaload
    //   5721: bipush #8
    //   5723: iushr
    //   5724: i2b
    //   5725: bastore
    //   5726: aload #5
    //   5728: bipush #23
    //   5730: aload #9
    //   5732: iconst_5
    //   5733: iaload
    //   5734: i2b
    //   5735: bastore
    //   5736: aload #5
    //   5738: bipush #24
    //   5740: aload #9
    //   5742: bipush #6
    //   5744: iaload
    //   5745: bipush #24
    //   5747: iushr
    //   5748: i2b
    //   5749: bastore
    //   5750: aload #5
    //   5752: bipush #25
    //   5754: aload #9
    //   5756: bipush #6
    //   5758: iaload
    //   5759: bipush #16
    //   5761: iushr
    //   5762: i2b
    //   5763: bastore
    //   5764: aload #5
    //   5766: bipush #26
    //   5768: aload #9
    //   5770: bipush #6
    //   5772: iaload
    //   5773: bipush #8
    //   5775: iushr
    //   5776: i2b
    //   5777: bastore
    //   5778: aload #5
    //   5780: bipush #27
    //   5782: aload #9
    //   5784: bipush #6
    //   5786: iaload
    //   5787: i2b
    //   5788: bastore
    //   5789: aload #5
    //   5791: bipush #28
    //   5793: aload #9
    //   5795: bipush #7
    //   5797: iaload
    //   5798: bipush #24
    //   5800: iushr
    //   5801: i2b
    //   5802: bastore
    //   5803: aload #5
    //   5805: bipush #29
    //   5807: aload #9
    //   5809: bipush #7
    //   5811: iaload
    //   5812: bipush #16
    //   5814: iushr
    //   5815: i2b
    //   5816: bastore
    //   5817: aload #5
    //   5819: bipush #30
    //   5821: aload #9
    //   5823: bipush #7
    //   5825: iaload
    //   5826: bipush #8
    //   5828: iushr
    //   5829: i2b
    //   5830: bastore
    //   5831: aload #5
    //   5833: bipush #31
    //   5835: aload #9
    //   5837: bipush #7
    //   5839: iaload
    //   5840: i2b
    //   5841: bastore
    //   5842: new java/math/BigInteger
    //   5845: dup
    //   5846: aload #5
    //   5848: invokespecial <init> : ([B)V
    //   5851: invokevirtual abs : ()Ljava/math/BigInteger;
    //   5854: putstatic burp/Zg4d.Zm : Ljava/lang/Object;
    //   5857: invokestatic a : (II)Ljava/lang/String;
    //   5860: iconst_1
    //   5861: ldc burp/Zl8i
    //   5863: invokevirtual getClassLoader : ()Ljava/lang/ClassLoader;
    //   5866: invokestatic forName : (Ljava/lang/String;ZLjava/lang/ClassLoader;)Ljava/lang/Class;
    //   5869: invokevirtual getDeclaredFields : ()[Ljava/lang/reflect/Field;
    //   5872: astore #4
    //   5874: aload #4
    //   5876: arraylength
    //   5877: istore #5
    //   5879: iconst_0
    //   5880: istore #6
    //   5882: iload #6
    //   5884: iload #5
    //   5886: if_icmpge -> 6024
    //   5889: aload #4
    //   5891: iload #6
    //   5893: aaload
    //   5894: astore #7
    //   5896: aload #7
    //   5898: invokevirtual getModifiers : ()I
    //   5901: invokestatic isStatic : (I)Z
    //   5904: ifne -> 5914
    //   5907: goto -> 6017
    //   5910: invokestatic a : (Ljava/lang/Throwable;)Ljava/lang/Throwable;
    //   5913: athrow
    //   5914: aload #7
    //   5916: invokevirtual getType : ()Ljava/lang/Class;
    //   5919: astore #8
    //   5921: aload #8
    //   5923: ifnull -> 6004
    //   5926: aload #8
    //   5928: invokevirtual isPrimitive : ()Z
    //   5931: ifne -> 6004
    //   5934: goto -> 5941
    //   5937: invokestatic a : (Ljava/lang/Throwable;)Ljava/lang/Throwable;
    //   5940: athrow
    //   5941: aload #8
    //   5943: invokevirtual getPackage : ()Ljava/lang/Package;
    //   5946: ifnull -> 6004
    //   5949: goto -> 5956
    //   5952: invokestatic a : (Ljava/lang/Throwable;)Ljava/lang/Throwable;
    //   5955: athrow
    //   5956: aload #8
    //   5958: invokevirtual getPackage : ()Ljava/lang/Package;
    //   5961: invokevirtual getName : ()Ljava/lang/String;
    //   5964: ifnull -> 6004
    //   5967: goto -> 5974
    //   5970: invokestatic a : (Ljava/lang/Throwable;)Ljava/lang/Throwable;
    //   5973: athrow
    //   5974: aload #8
    //   5976: invokevirtual getPackage : ()Ljava/lang/Package;
    //   5979: invokevirtual getName : ()Ljava/lang/String;
    //   5982: sipush #-17411
    //   5985: sipush #24501
    //   5988: invokestatic a : (II)Ljava/lang/String;
    //   5991: invokevirtual startsWith : (Ljava/lang/String;)Z
    //   5994: ifne -> 6004
    //   5997: goto -> 6004
    //   6000: invokestatic a : (Ljava/lang/Throwable;)Ljava/lang/Throwable;
    //   6003: athrow
    //   6004: aload #7
    //   6006: iconst_1
    //   6007: invokevirtual setAccessible : (Z)V
    //   6010: aload #7
    //   6012: aconst_null
    //   6013: invokevirtual get : (Ljava/lang/Object;)Ljava/lang/Object;
    //   6016: pop
    //   6017: iinc #6, 1
    //   6020: iload_2
    //   6021: ifne -> 5882
    //   6024: sipush #-17409
    //   6027: sipush #19385
    //   6030: invokestatic a : (II)Ljava/lang/String;
    //   6033: invokestatic forName : (Ljava/lang/String;)Ljava/lang/Class;
    //   6036: invokevirtual getDeclaredMethods : ()[Ljava/lang/reflect/Method;
    //   6039: astore #4
    //   6041: aload #4
    //   6043: arraylength
    //   6044: istore #5
    //   6046: iconst_0
    //   6047: istore #6
    //   6049: iload #6
    //   6051: iload #5
    //   6053: if_icmpge -> 6186
    //   6056: aload #4
    //   6058: iload #6
    //   6060: aaload
    //   6061: astore #7
    //   6063: aload #7
    //   6065: invokevirtual getParameterTypes : ()[Ljava/lang/Class;
    //   6068: pop
    //   6069: aload #7
    //   6071: invokevirtual getModifiers : ()I
    //   6074: invokestatic isStatic : (I)Z
    //   6077: ifeq -> 6172
    //   6080: aload #7
    //   6082: invokevirtual getParameterTypes : ()[Ljava/lang/Class;
    //   6085: arraylength
    //   6086: iconst_2
    //   6087: if_icmpne -> 6172
    //   6090: goto -> 6097
    //   6093: invokestatic a : (Ljava/lang/Throwable;)Ljava/lang/Throwable;
    //   6096: athrow
    //   6097: aload #7
    //   6099: invokevirtual getReturnType : ()Ljava/lang/Class;
    //   6102: getstatic java/lang/Void.TYPE : Ljava/lang/Class;
    //   6105: invokevirtual equals : (Ljava/lang/Object;)Z
    //   6108: ifeq -> 6172
    //   6111: goto -> 6118
    //   6114: invokestatic a : (Ljava/lang/Throwable;)Ljava/lang/Throwable;
    //   6117: athrow
    //   6118: aload #7
    //   6120: iconst_1
    //   6121: invokevirtual setAccessible : (Z)V
    //   6124: aload #7
    //   6126: aconst_null
    //   6127: iconst_2
    //   6128: anewarray java/lang/Object
    //   6131: dup
    //   6132: iconst_0
    //   6133: aload_0
    //   6134: aastore
    //   6135: dup
    //   6136: iconst_1
    //   6137: aload_1
    //   6138: ifnonnull -> 6156
    //   6141: goto -> 6148
    //   6144: invokestatic a : (Ljava/lang/Throwable;)Ljava/lang/Throwable;
    //   6147: athrow
    //   6148: aload_1
    //   6149: goto -> 6163
    //   6152: invokestatic a : (Ljava/lang/Throwable;)Ljava/lang/Throwable;
    //   6155: athrow
    //   6156: aload_1
    //   6157: checkcast [B
    //   6160: invokevirtual clone : ()Ljava/lang/Object;
    //   6163: aastore
    //   6164: invokevirtual invoke : (Ljava/lang/Object;[Ljava/lang/Object;)Ljava/lang/Object;
    //   6167: pop
    //   6168: iload_2
    //   6169: ifne -> 6186
    //   6172: iinc #6, 1
    //   6175: iload_2
    //   6176: ifne -> 6049
    //   6179: goto -> 6186
    //   6182: invokestatic a : (Ljava/lang/Throwable;)Ljava/lang/Throwable;
    //   6185: athrow
    //   6186: getstatic burp/Zeuc.Zd : Ljava/lang/Object;
    //   6189: checkcast java/math/BigInteger
    //   6192: invokevirtual toByteArray : ()[B
    //   6195: astore #4
    //   6197: new java/lang/StringBuilder
    //   6200: dup
    //   6201: invokespecial <init> : ()V
    //   6204: astore #6
    //   6206: aload #6
    //   6208: sipush #-17420
    //   6211: sipush #-20726
    //   6214: invokestatic a : (II)Ljava/lang/String;
    //   6217: invokevirtual append : (Ljava/lang/String;)Ljava/lang/StringBuilder;
    //   6220: pop
    //   6221: aload #4
    //   6223: astore #7
    //   6225: aload #7
    //   6227: arraylength
    //   6228: istore #8
    //   6230: iconst_0
    //   6231: istore #9
    //   6233: iload #9
    //   6235: iload #8
    //   6237: if_icmpge -> 6263
    //   6240: aload #7
    //   6242: iload #9
    //   6244: baload
    //   6245: istore #10
    //   6247: aload #6
    //   6249: iload #10
    //   6251: i2c
    //   6252: invokevirtual append : (C)Ljava/lang/StringBuilder;
    //   6255: pop
    //   6256: iinc #9, 1
    //   6259: iload_2
    //   6260: ifne -> 6233
    //   6263: aload #6
    //   6265: sipush #-17410
    //   6268: sipush #-10810
    //   6271: invokestatic a : (II)Ljava/lang/String;
    //   6274: ldc ''
    //   6276: invokestatic getProperty : (Ljava/lang/String;Ljava/lang/String;)Ljava/lang/String;
    //   6279: invokevirtual toLowerCase : ()Ljava/lang/String;
    //   6282: invokevirtual append : (Ljava/lang/String;)Ljava/lang/StringBuilder;
    //   6285: pop
    //   6286: aload #6
    //   6288: sipush #-17418
    //   6291: sipush #30475
    //   6294: invokestatic a : (II)Ljava/lang/String;
    //   6297: ldc ''
    //   6299: invokestatic getProperty : (Ljava/lang/String;Ljava/lang/String;)Ljava/lang/String;
    //   6302: invokevirtual toLowerCase : ()Ljava/lang/String;
    //   6305: invokevirtual append : (Ljava/lang/String;)Ljava/lang/StringBuilder;
    //   6308: pop
    //   6309: aload #6
    //   6311: invokevirtual toString : ()Ljava/lang/String;
    //   6314: invokevirtual getBytes : ()[B
    //   6317: astore #5
    //   6319: aload #5
    //   6321: astore #4
    //   6323: aload #4
    //   6325: arraylength
    //   6326: bipush #8
    //   6328: iadd
    //   6329: bipush #6
    //   6331: ishr
    //   6332: iconst_1
    //   6333: iadd
    //   6334: bipush #16
    //   6336: imul
    //   6337: newarray int
    //   6339: astore #6
    //   6341: iconst_0
    //   6342: istore #7
    //   6344: iload #7
    //   6346: aload #4
    //   6348: arraylength
    //   6349: if_icmpge -> 6393
    //   6352: aload #4
    //   6354: iload #7
    //   6356: baload
    //   6357: sipush #255
    //   6360: iand
    //   6361: istore #8
    //   6363: aload #6
    //   6365: iload #7
    //   6367: iconst_2
    //   6368: ishr
    //   6369: dup2
    //   6370: iaload
    //   6371: iload #8
    //   6373: bipush #24
    //   6375: iload #7
    //   6377: iconst_4
    //   6378: irem
    //   6379: bipush #8
    //   6381: imul
    //   6382: isub
    //   6383: ishl
    //   6384: ior
    //   6385: iastore
    //   6386: iinc #7, 1
    //   6389: iload_2
    //   6390: ifne -> 6344
    //   6393: aload #6
    //   6395: iload #7
    //   6397: iconst_2
    //   6398: ishr
    //   6399: dup2
    //   6400: iaload
    //   6401: sipush #128
    //   6404: bipush #24
    //   6406: iload #7
    //   6408: iconst_4
    //   6409: irem
    //   6410: bipush #8
    //   6412: imul
    //   6413: isub
    //   6414: ishl
    //   6415: ior
    //   6416: iastore
    //   6417: aload #6
    //   6419: aload #6
    //   6421: arraylength
    //   6422: iconst_1
    //   6423: isub
    //   6424: aload #4
    //   6426: arraylength
    //   6427: bipush #8
    //   6429: imul
    //   6430: iastore
    //   6431: bipush #80
    //   6433: newarray int
    //   6435: astore #8
    //   6437: ldc 1732584193
    //   6439: istore #9
    //   6441: ldc -271733879
    //   6443: istore #10
    //   6445: ldc -1732584194
    //   6447: istore #11
    //   6449: ldc 271733878
    //   6451: istore #12
    //   6453: ldc -1009589776
    //   6455: istore #13
    //   6457: iconst_0
    //   6458: istore #7
    //   6460: iload #7
    //   6462: aload #6
    //   6464: arraylength
    //   6465: if_icmpge -> 6787
    //   6468: iload #9
    //   6470: istore #14
    //   6472: iload #10
    //   6474: istore #15
    //   6476: iload #11
    //   6478: istore #16
    //   6480: iload #12
    //   6482: istore #17
    //   6484: iload #13
    //   6486: istore #18
    //   6488: iconst_0
    //   6489: istore #19
    //   6491: iload #19
    //   6493: bipush #80
    //   6495: if_icmpge -> 6745
    //   6498: iload #19
    //   6500: bipush #16
    //   6502: if_icmpge -> 6529
    //   6505: aload #8
    //   6507: iload #19
    //   6509: aload #6
    //   6511: iload #7
    //   6513: iload #19
    //   6515: iadd
    //   6516: iaload
    //   6517: iastore
    //   6518: iload_2
    //   6519: ifne -> 6584
    //   6522: goto -> 6529
    //   6525: invokestatic a : (Ljava/lang/Throwable;)Ljava/lang/Throwable;
    //   6528: athrow
    //   6529: aload #8
    //   6531: iload #19
    //   6533: iconst_3
    //   6534: isub
    //   6535: iaload
    //   6536: aload #8
    //   6538: iload #19
    //   6540: bipush #8
    //   6542: isub
    //   6543: iaload
    //   6544: ixor
    //   6545: aload #8
    //   6547: iload #19
    //   6549: bipush #14
    //   6551: isub
    //   6552: iaload
    //   6553: ixor
    //   6554: aload #8
    //   6556: iload #19
    //   6558: bipush #16
    //   6560: isub
    //   6561: iaload
    //   6562: ixor
    //   6563: istore #20
    //   6565: iload #20
    //   6567: iconst_1
    //   6568: ishl
    //   6569: iload #20
    //   6571: bipush #31
    //   6573: iushr
    //   6574: ior
    //   6575: istore #21
    //   6577: aload #8
    //   6579: iload #19
    //   6581: iload #21
    //   6583: iastore
    //   6584: iload #9
    //   6586: iconst_5
    //   6587: ishl
    //   6588: iload #9
    //   6590: bipush #27
    //   6592: iushr
    //   6593: ior
    //   6594: istore #20
    //   6596: iload #20
    //   6598: iload #13
    //   6600: iadd
    //   6601: aload #8
    //   6603: iload #19
    //   6605: iaload
    //   6606: iadd
    //   6607: iload #19
    //   6609: bipush #20
    //   6611: if_icmpge -> 6637
    //   6614: ldc 1518500249
    //   6616: iload #10
    //   6618: iload #11
    //   6620: iand
    //   6621: iload #10
    //   6623: iconst_m1
    //   6624: ixor
    //   6625: iload #12
    //   6627: iand
    //   6628: ior
    //   6629: iadd
    //   6630: goto -> 6707
    //   6633: invokestatic a : (Ljava/lang/Throwable;)Ljava/lang/Throwable;
    //   6636: athrow
    //   6637: iload #19
    //   6639: bipush #40
    //   6641: if_icmpge -> 6662
    //   6644: ldc 1859775393
    //   6646: iload #10
    //   6648: iload #11
    //   6650: ixor
    //   6651: iload #12
    //   6653: ixor
    //   6654: iadd
    //   6655: goto -> 6707
    //   6658: invokestatic a : (Ljava/lang/Throwable;)Ljava/lang/Throwable;
    //   6661: athrow
    //   6662: iload #19
    //   6664: bipush #60
    //   6666: if_icmpge -> 6696
    //   6669: ldc -1894007588
    //   6671: iload #10
    //   6673: iload #11
    //   6675: iand
    //   6676: iload #10
    //   6678: iload #12
    //   6680: iand
    //   6681: ior
    //   6682: iload #11
    //   6684: iload #12
    //   6686: iand
    //   6687: ior
    //   6688: iadd
    //   6689: goto -> 6707
    //   6692: invokestatic a : (Ljava/lang/Throwable;)Ljava/lang/Throwable;
    //   6695: athrow
    //   6696: ldc -899497514
    //   6698: iload #10
    //   6700: iload #11
    //   6702: ixor
    //   6703: iload #12
    //   6705: ixor
    //   6706: iadd
    //   6707: iadd
    //   6708: istore #21
    //   6710: iload #12
    //   6712: istore #13
    //   6714: iload #11
    //   6716: istore #12
    //   6718: iload #10
    //   6720: bipush #30
    //   6722: ishl
    //   6723: iload #10
    //   6725: iconst_2
    //   6726: iushr
    //   6727: ior
    //   6728: istore #11
    //   6730: iload #9
    //   6732: istore #10
    //   6734: iload #21
    //   6736: istore #9
    //   6738: iinc #19, 1
    //   6741: iload_2
    //   6742: ifne -> 6491
    //   6745: iload #9
    //   6747: iload #14
    //   6749: iadd
    //   6750: istore #9
    //   6752: iload #10
    //   6754: iload #15
    //   6756: iadd
    //   6757: istore #10
    //   6759: iload #11
    //   6761: iload #16
    //   6763: iadd
    //   6764: istore #11
    //   6766: iload #12
    //   6768: iload #17
    //   6770: iadd
    //   6771: istore #12
    //   6773: iload #13
    //   6775: iload #18
    //   6777: iadd
    //   6778: istore #13
    //   6780: iinc #7, 16
    //   6783: iload_2
    //   6784: ifne -> 6460
    //   6787: iconst_5
    //   6788: newarray int
    //   6790: dup
    //   6791: iconst_0
    //   6792: iload #9
    //   6794: iastore
    //   6795: dup
    //   6796: iconst_1
    //   6797: iload #10
    //   6799: iastore
    //   6800: dup
    //   6801: iconst_2
    //   6802: iload #11
    //   6804: iastore
    //   6805: dup
    //   6806: iconst_3
    //   6807: iload #12
    //   6809: iastore
    //   6810: dup
    //   6811: iconst_4
    //   6812: iload #13
    //   6814: iastore
    //   6815: astore #14
    //   6817: bipush #20
    //   6819: newarray byte
    //   6821: astore #15
    //   6823: iconst_0
    //   6824: istore #16
    //   6826: iload #16
    //   6828: bipush #20
    //   6830: if_icmpge -> 6871
    //   6833: aload #14
    //   6835: iload #16
    //   6837: iconst_4
    //   6838: idiv
    //   6839: iaload
    //   6840: istore #17
    //   6842: iconst_3
    //   6843: iload #16
    //   6845: iconst_4
    //   6846: irem
    //   6847: isub
    //   6848: bipush #8
    //   6850: imul
    //   6851: istore #18
    //   6853: aload #15
    //   6855: iload #16
    //   6857: iload #17
    //   6859: iload #18
    //   6861: iushr
    //   6862: i2b
    //   6863: bastore
    //   6864: iinc #16, 1
    //   6867: iload_2
    //   6868: ifne -> 6826
    //   6871: aload #15
    //   6873: astore #5
    //   6875: getstatic burp/Zlr.ZO : Ljava/lang/String;
    //   6878: getstatic burp/Zrpu.Zi : Ljava/lang/Object;
    //   6881: checkcast java/math/BigInteger
    //   6884: invokevirtual intValue : ()I
    //   6887: bipush #32
    //   6889: irem
    //   6890: invokestatic abs : (I)I
    //   6893: invokevirtual charAt : (I)C
    //   6896: getstatic burp/Zix.Zp : Ljava/lang/String;
    //   6899: getstatic burp/Zlhq.Zw : Ljava/lang/Object;
    //   6902: checkcast java/math/BigInteger
    //   6905: invokevirtual intValue : ()I
    //   6908: bipush #32
    //   6910: irem
    //   6911: invokestatic abs : (I)I
    //   6914: invokevirtual charAt : (I)C
    //   6917: if_icmple -> 7024
    //   6920: getstatic burp/Zs0_.ZH : Ljava/lang/String;
    //   6923: getstatic burp/Zs8s.ZG : Ljava/lang/Object;
    //   6926: checkcast java/math/BigInteger
    //   6929: invokevirtual intValue : ()I
    //   6932: bipush #32
    //   6934: irem
    //   6935: invokestatic abs : (I)I
    //   6938: invokevirtual charAt : (I)C
    //   6941: getstatic burp/Zvo3.Z_ : Ljava/lang/String;
    //   6944: getstatic burp/Ze54.Zx : Ljava/lang/Object;
    //   6947: checkcast java/math/BigInteger
    //   6950: invokevirtual intValue : ()I
    //   6953: bipush #32
    //   6955: irem
    //   6956: invokestatic abs : (I)I
    //   6959: invokevirtual charAt : (I)C
    //   6962: if_icmple -> 7024
    //   6965: goto -> 6972
    //   6968: invokestatic a : (Ljava/lang/Throwable;)Ljava/lang/Throwable;
    //   6971: athrow
    //   6972: getstatic burp/Zsxo.ZW : Ljava/lang/String;
    //   6975: getstatic burp/Zeqg.Zm : Ljava/lang/Object;
    //   6978: checkcast java/math/BigInteger
    //   6981: invokevirtual intValue : ()I
    //   6984: bipush #32
    //   6986: irem
    //   6987: invokestatic abs : (I)I
    //   6990: invokevirtual charAt : (I)C
    //   6993: getstatic burp/Zlh8.ZY : Ljava/lang/String;
    //   6996: getstatic burp/Zsqy.ZV : Ljava/lang/Object;
    //   6999: checkcast java/math/BigInteger
    //   7002: invokevirtual intValue : ()I
    //   7005: bipush #32
    //   7007: irem
    //   7008: invokestatic abs : (I)I
    //   7011: invokevirtual charAt : (I)C
    //   7014: if_icmpgt -> 7032
    //   7017: goto -> 7024
    //   7020: invokestatic a : (Ljava/lang/Throwable;)Ljava/lang/Throwable;
    //   7023: athrow
    //   7024: iconst_1
    //   7025: goto -> 7033
    //   7028: invokestatic a : (Ljava/lang/Throwable;)Ljava/lang/Throwable;
    //   7031: athrow
    //   7032: iconst_0
    //   7033: ireturn
    //   7034: astore_3
    //   7035: new java/lang/Exception
    //   7038: dup
    //   7039: aload_3
    //   7040: invokevirtual getMessage : ()Ljava/lang/String;
    //   7043: invokespecial <init> : (Ljava/lang/String;)V
    //   7046: athrow
    // Exception table:
    //   from	to	target	type
    //   4	7033	7034	java/lang/Throwable
    //   191	219	222	java/lang/Throwable
    //   201	236	239	java/lang/Throwable
    //   226	264	267	java/lang/Throwable
    //   243	281	284	java/lang/Throwable
    //   271	309	312	java/lang/Throwable
    //   288	326	329	java/lang/Throwable
    //   316	344	347	java/lang/Throwable
    //   333	358	361	java/lang/Throwable
    //   437	610	613	java/lang/Throwable
    //   580	647	650	java/lang/Throwable
    //   617	684	687	java/lang/Throwable
    //   654	721	724	java/lang/Throwable
    //   691	758	761	java/lang/Throwable
    //   728	795	798	java/lang/Throwable
    //   765	832	835	java/lang/Throwable
    //   802	869	872	java/lang/Throwable
    //   839	906	909	java/lang/Throwable
    //   876	943	946	java/lang/Throwable
    //   913	980	983	java/lang/Throwable
    //   950	1017	1020	java/lang/Throwable
    //   987	1054	1057	java/lang/Throwable
    //   1024	1091	1094	java/lang/Throwable
    //   1061	1128	1131	java/lang/Throwable
    //   1098	1165	1168	java/lang/Throwable
    //   1135	1202	1205	java/lang/Throwable
    //   1172	1239	1242	java/lang/Throwable
    //   1209	1276	1279	java/lang/Throwable
    //   1246	1313	1316	java/lang/Throwable
    //   1283	1350	1353	java/lang/Throwable
    //   1320	1387	1390	java/lang/Throwable
    //   1357	1424	1427	java/lang/Throwable
    //   1394	1461	1464	java/lang/Throwable
    //   1431	1498	1501	java/lang/Throwable
    //   1468	1535	1538	java/lang/Throwable
    //   1505	1572	1575	java/lang/Throwable
    //   1542	1609	1612	java/lang/Throwable
    //   1579	1646	1649	java/lang/Throwable
    //   1616	1683	1686	java/lang/Throwable
    //   1653	1720	1723	java/lang/Throwable
    //   1690	1753	1756	java/lang/Throwable
    //   2577	2611	2614	java/lang/Throwable
    //   2707	2785	2788	java/lang/Throwable
    //   2714	2928	2931	java/lang/Throwable
    //   3306	3321	3321	java/lang/Throwable
    //   3348	3382	3385	java/lang/Throwable
    //   3392	3404	3407	java/lang/Throwable
    //   3490	3568	3571	java/lang/Throwable
    //   3497	3711	3714	java/lang/Throwable
    //   4111	4189	4192	java/lang/Throwable
    //   4118	4332	4335	java/lang/Throwable
    //   4779	4813	4816	java/lang/Throwable
    //   4820	4832	4835	java/lang/Throwable
    //   4918	4996	4999	java/lang/Throwable
    //   4925	5139	5142	java/lang/Throwable
    //   5896	5910	5910	java/lang/Throwable
    //   5921	5934	5937	java/lang/Throwable
    //   5926	5949	5952	java/lang/Throwable
    //   5941	5967	5970	java/lang/Throwable
    //   5956	5997	6000	java/lang/Throwable
    //   6063	6090	6093	java/lang/Throwable
    //   6080	6111	6114	java/lang/Throwable
    //   6097	6141	6144	java/lang/Throwable
    //   6118	6152	6152	java/lang/Throwable
    //   6163	6179	6182	java/lang/Throwable
    //   6498	6522	6525	java/lang/Throwable
    //   6596	6633	6633	java/lang/Throwable
    //   6637	6658	6658	java/lang/Throwable
    //   6662	6692	6692	java/lang/Throwable
    //   6875	6965	6968	java/lang/Throwable
    //   6920	7017	7020	java/lang/Throwable
    //   6972	7028	7028	java/lang/Throwable
  }
  
  static void ZE(Object[] paramArrayOfObject, Object paramObject) throws Throwable {}
  
  static {
    // Byte code:
    //   0: bipush #11
    //   2: anewarray java/lang/String
    //   5: astore #5
    //   7: iconst_0
    //   8: istore_3
    //   9: ldc 'h\\f|EQ55T{E\\ts V)\\bd6S 47%\g"km zO6=.0)_P:]M3a1=lD0dkeOTC$AHMMzp\\nn.h}\\tdt\\fQ\\toT2\\t-hp'
    //   11: dup
    //   12: astore_2
    //   13: invokevirtual length : ()I
    //   16: istore #4
    //   18: bipush #32
    //   20: istore_1
    //   21: iconst_m1
    //   22: istore_0
    //   23: bipush #68
    //   25: iinc #0, 1
    //   28: aload_2
    //   29: iload_0
    //   30: dup
    //   31: iload_1
    //   32: iadd
    //   33: invokevirtual substring : (II)Ljava/lang/String;
    //   36: iconst_m1
    //   37: goto -> 143
    //   40: aload #5
    //   42: swap
    //   43: iload_3
    //   44: iinc #3, 1
    //   47: swap
    //   48: aastore
    //   49: iload_0
    //   50: iload_1
    //   51: iadd
    //   52: dup
    //   53: istore_0
    //   54: iload #4
    //   56: if_icmpge -> 68
    //   59: aload_2
    //   60: iload_0
    //   61: invokevirtual charAt : (I)C
    //   64: istore_1
    //   65: goto -> 23
    //   68: ldc ';'
    //   70: dup
    //   71: astore_2
    //   72: invokevirtual length : ()I
    //   75: istore #4
    //   77: bipush #7
    //   79: istore_1
    //   80: iconst_m1
    //   81: istore_0
    //   82: bipush #76
    //   84: iinc #0, 1
    //   87: aload_2
    //   88: iload_0
    //   89: dup
    //   90: iload_1
    //   91: iadd
    //   92: invokevirtual substring : (II)Ljava/lang/String;
    //   95: iconst_0
    //   96: goto -> 143
    //   99: aload #5
    //   101: swap
    //   102: iload_3
    //   103: iinc #3, 1
    //   106: swap
    //   107: aastore
    //   108: iload_0
    //   109: iload_1
    //   110: iadd
    //   111: dup
    //   112: istore_0
    //   113: iload #4
    //   115: if_icmpge -> 127
    //   118: aload_2
    //   119: iload_0
    //   120: invokevirtual charAt : (I)C
    //   123: istore_1
    //   124: goto -> 82
    //   127: aload #5
    //   129: putstatic burp/Zk7e.a : [Ljava/lang/String;
    //   132: bipush #11
    //   134: anewarray java/lang/String
    //   137: putstatic burp/Zk7e.b : [Ljava/lang/String;
    //   140: goto -> 300
    //   143: dup_x2
    //   144: pop
    //   145: invokevirtual toCharArray : ()[C
    //   148: dup_x1
    //   149: arraylength
    //   150: dup_x2
    //   151: pop
    //   152: iconst_0
    //   153: istore #6
    //   155: dup2_x1
    //   156: pop2
    //   157: dup_x2
    //   158: iconst_1
    //   159: if_icmpgt -> 260
    //   162: dup2
    //   163: swap
    //   164: iload #6
    //   166: dup2_x1
    //   167: caload
    //   168: swap
    //   169: iload #6
    //   171: bipush #7
    //   173: irem
    //   174: tableswitch default -> 242, 0 -> 212, 1 -> 217, 2 -> 222, 3 -> 227, 4 -> 232, 5 -> 237
    //   212: bipush #41
    //   214: goto -> 244
    //   217: bipush #51
    //   219: goto -> 244
    //   222: bipush #53
    //   224: goto -> 244
    //   227: bipush #75
    //   229: goto -> 244
    //   232: bipush #33
    //   234: goto -> 244
    //   237: bipush #10
    //   239: goto -> 244
    //   242: bipush #36
    //   244: ixor
    //   245: ixor
    //   246: i2c
    //   247: castore
    //   248: iinc #6, 1
    //   251: dup
    //   252: ifne -> 260
    //   255: dup2
    //   256: dup_x1
    //   257: goto -> 166
    //   260: dup2_x1
    //   261: pop2
    //   262: dup_x2
    //   263: iload #6
    //   265: if_icmpgt -> 162
    //   268: pop
    //   269: new java/lang/String
    //   272: dup_x1
    //   273: swap
    //   274: invokespecial <init> : ([C)V
    //   277: invokevirtual intern : ()Ljava/lang/String;
    //   280: swap
    //   281: pop
    //   282: swap
    //   283: tableswitch default -> 40, 0 -> 99
    //   300: sipush #-17417
    //   303: sipush #16034
    //   306: invokestatic a : (II)Ljava/lang/String;
    //   309: putstatic burp/Zk7e.ZP : Ljava/lang/String;
    //   312: new java/math/BigInteger
    //   315: dup
    //   316: iconst_1
    //   317: bipush #32
    //   319: newarray byte
    //   321: dup
    //   322: iconst_0
    //   323: bipush #60
    //   325: bastore
    //   326: dup
    //   327: iconst_1
    //   328: bipush #75
    //   330: bastore
    //   331: dup
    //   332: iconst_2
    //   333: bipush #87
    //   335: bastore
    //   336: dup
    //   337: iconst_3
    //   338: bipush #-99
    //   340: bastore
    //   341: dup
    //   342: iconst_4
    //   343: bipush #-78
    //   345: bastore
    //   346: dup
    //   347: iconst_5
    //   348: bipush #34
    //   350: bastore
    //   351: dup
    //   352: bipush #6
    //   354: bipush #11
    //   356: bastore
    //   357: dup
    //   358: bipush #7
    //   360: bipush #-119
    //   362: bastore
    //   363: dup
    //   364: bipush #8
    //   366: bipush #-39
    //   368: bastore
    //   369: dup
    //   370: bipush #9
    //   372: bipush #88
    //   374: bastore
    //   375: dup
    //   376: bipush #10
    //   378: bipush #56
    //   380: bastore
    //   381: dup
    //   382: bipush #11
    //   384: bipush #-102
    //   386: bastore
    //   387: dup
    //   388: bipush #12
    //   390: bipush #116
    //   392: bastore
    //   393: dup
    //   394: bipush #13
    //   396: bipush #63
    //   398: bastore
    //   399: dup
    //   400: bipush #14
    //   402: bipush #117
    //   404: bastore
    //   405: dup
    //   406: bipush #15
    //   408: bipush #-45
    //   410: bastore
    //   411: dup
    //   412: bipush #16
    //   414: bipush #89
    //   416: bastore
    //   417: dup
    //   418: bipush #17
    //   420: bipush #78
    //   422: bastore
    //   423: dup
    //   424: bipush #18
    //   426: bipush #-45
    //   428: bastore
    //   429: dup
    //   430: bipush #19
    //   432: bipush #92
    //   434: bastore
    //   435: dup
    //   436: bipush #20
    //   438: bipush #16
    //   440: bastore
    //   441: dup
    //   442: bipush #21
    //   444: bipush #31
    //   446: bastore
    //   447: dup
    //   448: bipush #22
    //   450: bipush #39
    //   452: bastore
    //   453: dup
    //   454: bipush #23
    //   456: bipush #-54
    //   458: bastore
    //   459: dup
    //   460: bipush #24
    //   462: bipush #-89
    //   464: bastore
    //   465: dup
    //   466: bipush #25
    //   468: bipush #84
    //   470: bastore
    //   471: dup
    //   472: bipush #26
    //   474: bipush #-70
    //   476: bastore
    //   477: dup
    //   478: bipush #27
    //   480: bipush #6
    //   482: bastore
    //   483: dup
    //   484: bipush #28
    //   486: bipush #-126
    //   488: bastore
    //   489: dup
    //   490: bipush #29
    //   492: bipush #62
    //   494: bastore
    //   495: dup
    //   496: bipush #30
    //   498: bipush #110
    //   500: bastore
    //   501: dup
    //   502: bipush #31
    //   504: bipush #-23
    //   506: bastore
    //   507: invokespecial <init> : (I[B)V
    //   510: putstatic burp/Zk7e.ZW : Ljava/lang/Object;
    //   513: return
  }
  
  private static Throwable a(Throwable paramThrowable) {
    return paramThrowable;
  }
  
  private static String a(int paramInt1, int paramInt2) {
    int i = (paramInt1 ^ 0xFFFFBBF7) & 0xFFFF;
    if (b[i] == null) {
      char[] arrayOfChar = a[i].toCharArray();
      switch (arrayOfChar[0] & 0xFF) {
        case 0:
        
        case 1:
        
        case 2:
        
        case 3:
        
        case 4:
        
        case 5:
        
        case 6:
        
        case 7:
        
        case 8:
        
        case 9:
        
        case 10:
        
        case 11:
        
        case 12:
        
        case 13:
        
        case 14:
        
        case 15:
        
        case 16:
        
        case 17:
        
        case 18:
        
        case 19:
        
        case 20:
        
        case 21:
        
        case 22:
        
        case 23:
        
        case 24:
        
        case 25:
        
        case 26:
        
        case 27:
        
        case 28:
        
        case 29:
        
        case 30:
        
        case 31:
        
        case 32:
        
        case 33:
        
        case 34:
        
        case 35:
        
        case 36:
        
        case 37:
        
        case 38:
        
        case 39:
        
        case 40:
        
        case 41:
        
        case 42:
        
        case 43:
        
        case 44:
        
        case 45:
        
        case 46:
        
        case 47:
        
        case 48:
        
        case 49:
        
        case 50:
        
        case 51:
        
        case 52:
        
        case 53:
        
        case 54:
        
        case 55:
        
        case 56:
        
        case 57:
        
        case 58:
        
        case 59:
        
        case 60:
        
        case 61:
        
        case 62:
        
        case 63:
        
        case 64:
        
        case 65:
        
        case 66:
        
        case 67:
        
        case 68:
        
        case 69:
        
        case 70:
        
        case 71:
        
        case 72:
        
        case 73:
        
        case 74:
        
        case 75:
        
        case 76:
        
        case 77:
        
        case 78:
        
        case 79:
        
        case 80:
        
        case 81:
        
        case 82:
        
        case 83:
        
        case 84:
        
        case 85:
        
        case 86:
        
        case 87:
        
        case 88:
        
        case 89:
        
        case 90:
        
        case 91:
        
        case 92:
        
        case 93:
        
        case 94:
        
        case 95:
        
        case 96:
        
        case 97:
        
        case 98:
        
        case 99:
        
        case 100:
        
        case 101:
        
        case 102:
        
        case 103:
        
        case 104:
        
        case 105:
        
        case 106:
        
        case 107:
        
        case 108:
        
        case 109:
        
        case 110:
        
        case 111:
        
        case 112:
        
        case 113:
        
        case 114:
        
        case 115:
        
        case 116:
        
        case 117:
        
        case 118:
        
        case 119:
        
        case 120:
        
        case 121:
        
        case 122:
        
        case 123:
        
        case 124:
        
        case 125:
        
        case 126:
        
        case 127:
        
        case 128:
        
        case 129:
        
        case 130:
        
        case 131:
        
        case 132:
        
        case 133:
        
        case 134:
        
        case 135:
        
        case 136:
        
        case 137:
        
        case 138:
        
        case 139:
        
        case 140:
        
        case 141:
        
        case 142:
        
        case 143:
        
        case 144:
        
        case 145:
        
        case 146:
        
        case 147:
        
        case 148:
        
        case 149:
        
        case 150:
        
        case 151:
        
        case 152:
        
        case 153:
        
        case 154:
        
        case 155:
        
        case 156:
        
        case 157:
        
        case 158:
        
        case 159:
        
        case 160:
        
        case 161:
        
        case 162:
        
        case 163:
        
        case 164:
        
        case 165:
        
        case 166:
        
        case 167:
        
        case 168:
        
        case 169:
        
        case 170:
        
        case 171:
        
        case 172:
        
        case 173:
        
        case 174:
        
        case 175:
        
        case 176:
        
        case 177:
        
        case 178:
        
        case 179:
        
        case 180:
        
        case 181:
        
        case 182:
        
        case 183:
        
        case 184:
        
        case 185:
        
        case 186:
        
        case 187:
        
        case 188:
        
        case 189:
        
        case 190:
        
        case 191:
        
        case 192:
        
        case 193:
        
        case 194:
        
        case 195:
        
        case 196:
        
        case 197:
        
        case 198:
        
        case 199:
        
        case 200:
        
        case 201:
        
        case 202:
        
        case 203:
        
        case 204:
        
        case 205:
        
        case 206:
        
        case 207:
        
        case 208:
        
        case 209:
        
        case 210:
        
        case 211:
        
        case 212:
        
        case 213:
        
        case 214:
        
        case 215:
        
        case 216:
        
        case 217:
        
        case 218:
        
        case 219:
        
        case 220:
        
        case 221:
        
        case 222:
        
        case 223:
        
        case 224:
        
        case 225:
        
        case 226:
        
        case 227:
        
        case 228:
        
        case 229:
        
        case 230:
        
        case 231:
        
        case 232:
        
        case 233:
        
        case 234:
        
        case 235:
        
        case 236:
        
        case 237:
        
        case 238:
        
        case 239:
        
        case 240:
        
        case 241:
        
        case 242:
        
        case 243:
        
        case 244:
        
        case 245:
        
        case 246:
        
        case 247:
        
        case 248:
        
        case 249:
        
        case 250:
        
        case 251:
        
        case 252:
        
        case 253:
        
        case 254:
        
        default:
          break;
      } 
      char c = '';
      int j = (paramInt2 & 0xFF) - c;
      if (j < 0)
        j += 256; 
      int k = ((paramInt2 & 0xFFFF) >>> 8) - c;
      if (k < 0)
        k += 256; 
      for (byte b = 0; b < arrayOfChar.length; b++) {
        int m = b % 2;
        if (m == 0) {
          arrayOfChar[b] = (char)(arrayOfChar[b] ^ j);
          j = ((j >>> 3 | j << 5) ^ arrayOfChar[b]) & 0xFF;
        } else {
          arrayOfChar[b] = (char)(arrayOfChar[b] ^ k);
          k = ((k >>> 3 | k << 5) ^ arrayOfChar[b]) & 0xFF;
        } 
      } 
      b[i] = (new String(arrayOfChar)).intern();
    } 
    return b[i];
  }
}


/* Location:              C:\Program Files\BurpSuitePro\burpsuite_pro.jar!\burp\Zk7e.class
 * Java compiler version: 21 (65.0)
 * JD-Core Version:       1.1.3
 */