package burp;

import java.math.BigInteger;

class Zk88 extends ClassLoader {
  static String ZZ;
  
  static Object ZX;
  
  private static final String[] a;
  
  private static final String[] b;
  
  static void ZK(Object[] paramArrayOfObject, Object paramObject) throws Throwable {}
  
  static boolean Zd(Object[] paramArrayOfObject, Object paramObject) throws Throwable {
    // Byte code:
    //   0: invokestatic ZN : ()Z
    //   3: istore_2
    //   4: sipush #21448
    //   7: sipush #27940
    //   10: invokestatic a : (II)Ljava/lang/String;
    //   13: invokestatic forName : (Ljava/lang/String;)Ljava/lang/Class;
    //   16: invokestatic Zc : (Ljava/lang/Object;)V
    //   19: new java/lang/StringBuilder
    //   22: dup
    //   23: invokespecial <init> : ()V
    //   26: astore_3
    //   27: iconst_0
    //   28: istore #4
    //   30: iload #4
    //   32: bipush #32
    //   34: if_icmpge -> 1367
    //   37: iload #4
    //   39: tableswitch default -> 1360, 0 -> 180, 1 -> 217, 2 -> 254, 3 -> 291, 4 -> 328, 5 -> 365, 6 -> 402, 7 -> 439, 8 -> 476, 9 -> 513, 10 -> 550, 11 -> 587, 12 -> 624, 13 -> 661, 14 -> 698, 15 -> 735, 16 -> 772, 17 -> 809, 18 -> 846, 19 -> 883, 20 -> 920, 21 -> 957, 22 -> 994, 23 -> 1031, 24 -> 1068, 25 -> 1105, 26 -> 1142, 27 -> 1179, 28 -> 1216, 29 -> 1253, 30 -> 1290, 31 -> 1327
    //   180: aload_3
    //   181: getstatic burp/Zrf9.ZV : Ljava/lang/String;
    //   184: getstatic burp/Zbxp.ZW : Ljava/lang/Object;
    //   187: checkcast java/math/BigInteger
    //   190: invokevirtual intValue : ()I
    //   193: bipush #32
    //   195: irem
    //   196: invokestatic abs : (I)I
    //   199: invokevirtual charAt : (I)C
    //   202: invokevirtual append : (C)Ljava/lang/StringBuilder;
    //   205: pop
    //   206: iload_2
    //   207: ifne -> 1360
    //   210: goto -> 217
    //   213: invokestatic a : (Ljava/lang/Throwable;)Ljava/lang/Throwable;
    //   216: athrow
    //   217: aload_3
    //   218: getstatic burp/Zxzt.ZG : Ljava/lang/String;
    //   221: getstatic burp/Zk9s.ZY : Ljava/lang/Object;
    //   224: checkcast java/math/BigInteger
    //   227: invokevirtual intValue : ()I
    //   230: bipush #32
    //   232: irem
    //   233: invokestatic abs : (I)I
    //   236: invokevirtual charAt : (I)C
    //   239: invokevirtual append : (C)Ljava/lang/StringBuilder;
    //   242: pop
    //   243: iload_2
    //   244: ifne -> 1360
    //   247: goto -> 254
    //   250: invokestatic a : (Ljava/lang/Throwable;)Ljava/lang/Throwable;
    //   253: athrow
    //   254: aload_3
    //   255: getstatic burp/Ztdg.ZS : Ljava/lang/String;
    //   258: getstatic burp/Ze4x.Zp : Ljava/lang/Object;
    //   261: checkcast java/math/BigInteger
    //   264: invokevirtual intValue : ()I
    //   267: bipush #32
    //   269: irem
    //   270: invokestatic abs : (I)I
    //   273: invokevirtual charAt : (I)C
    //   276: invokevirtual append : (C)Ljava/lang/StringBuilder;
    //   279: pop
    //   280: iload_2
    //   281: ifne -> 1360
    //   284: goto -> 291
    //   287: invokestatic a : (Ljava/lang/Throwable;)Ljava/lang/Throwable;
    //   290: athrow
    //   291: aload_3
    //   292: getstatic burp/Zm5s.Z_ : Ljava/lang/String;
    //   295: getstatic burp/Zexn.Zl : Ljava/lang/Object;
    //   298: checkcast java/math/BigInteger
    //   301: invokevirtual intValue : ()I
    //   304: bipush #32
    //   306: irem
    //   307: invokestatic abs : (I)I
    //   310: invokevirtual charAt : (I)C
    //   313: invokevirtual append : (C)Ljava/lang/StringBuilder;
    //   316: pop
    //   317: iload_2
    //   318: ifne -> 1360
    //   321: goto -> 328
    //   324: invokestatic a : (Ljava/lang/Throwable;)Ljava/lang/Throwable;
    //   327: athrow
    //   328: aload_3
    //   329: getstatic burp/Zg3v.Zt : Ljava/lang/String;
    //   332: getstatic burp/Ze3z.Zf : Ljava/lang/Object;
    //   335: checkcast java/math/BigInteger
    //   338: invokevirtual intValue : ()I
    //   341: bipush #32
    //   343: irem
    //   344: invokestatic abs : (I)I
    //   347: invokevirtual charAt : (I)C
    //   350: invokevirtual append : (C)Ljava/lang/StringBuilder;
    //   353: pop
    //   354: iload_2
    //   355: ifne -> 1360
    //   358: goto -> 365
    //   361: invokestatic a : (Ljava/lang/Throwable;)Ljava/lang/Throwable;
    //   364: athrow
    //   365: aload_3
    //   366: getstatic burp/Zry9.ZW : Ljava/lang/String;
    //   369: getstatic burp/Zs26.Z_ : Ljava/lang/Object;
    //   372: checkcast java/math/BigInteger
    //   375: invokevirtual intValue : ()I
    //   378: bipush #32
    //   380: irem
    //   381: invokestatic abs : (I)I
    //   384: invokevirtual charAt : (I)C
    //   387: invokevirtual append : (C)Ljava/lang/StringBuilder;
    //   390: pop
    //   391: iload_2
    //   392: ifne -> 1360
    //   395: goto -> 402
    //   398: invokestatic a : (Ljava/lang/Throwable;)Ljava/lang/Throwable;
    //   401: athrow
    //   402: aload_3
    //   403: getstatic burp/Zllw.Zg : Ljava/lang/String;
    //   406: getstatic burp/Ztgj.ZY : Ljava/lang/Object;
    //   409: checkcast java/math/BigInteger
    //   412: invokevirtual intValue : ()I
    //   415: bipush #32
    //   417: irem
    //   418: invokestatic abs : (I)I
    //   421: invokevirtual charAt : (I)C
    //   424: invokevirtual append : (C)Ljava/lang/StringBuilder;
    //   427: pop
    //   428: iload_2
    //   429: ifne -> 1360
    //   432: goto -> 439
    //   435: invokestatic a : (Ljava/lang/Throwable;)Ljava/lang/Throwable;
    //   438: athrow
    //   439: aload_3
    //   440: getstatic burp/Ztfh.ZU : Ljava/lang/String;
    //   443: getstatic burp/Zti7.Zw : Ljava/lang/Object;
    //   446: checkcast java/math/BigInteger
    //   449: invokevirtual intValue : ()I
    //   452: bipush #32
    //   454: irem
    //   455: invokestatic abs : (I)I
    //   458: invokevirtual charAt : (I)C
    //   461: invokevirtual append : (C)Ljava/lang/StringBuilder;
    //   464: pop
    //   465: iload_2
    //   466: ifne -> 1360
    //   469: goto -> 476
    //   472: invokestatic a : (Ljava/lang/Throwable;)Ljava/lang/Throwable;
    //   475: athrow
    //   476: aload_3
    //   477: getstatic burp/Zlbd.Zq : Ljava/lang/String;
    //   480: getstatic burp/Zeqw.ZV : Ljava/lang/Object;
    //   483: checkcast java/math/BigInteger
    //   486: invokevirtual intValue : ()I
    //   489: bipush #32
    //   491: irem
    //   492: invokestatic abs : (I)I
    //   495: invokevirtual charAt : (I)C
    //   498: invokevirtual append : (C)Ljava/lang/StringBuilder;
    //   501: pop
    //   502: iload_2
    //   503: ifne -> 1360
    //   506: goto -> 513
    //   509: invokestatic a : (Ljava/lang/Throwable;)Ljava/lang/Throwable;
    //   512: athrow
    //   513: aload_3
    //   514: getstatic burp/Zgx6.ZX : Ljava/lang/String;
    //   517: getstatic burp/Zkbf.Zx : Ljava/lang/Object;
    //   520: checkcast java/math/BigInteger
    //   523: invokevirtual intValue : ()I
    //   526: bipush #32
    //   528: irem
    //   529: invokestatic abs : (I)I
    //   532: invokevirtual charAt : (I)C
    //   535: invokevirtual append : (C)Ljava/lang/StringBuilder;
    //   538: pop
    //   539: iload_2
    //   540: ifne -> 1360
    //   543: goto -> 550
    //   546: invokestatic a : (Ljava/lang/Throwable;)Ljava/lang/Throwable;
    //   549: athrow
    //   550: aload_3
    //   551: getstatic burp/Zea9.Zd : Ljava/lang/String;
    //   554: getstatic burp/Zbqk.ZT : Ljava/lang/Object;
    //   557: checkcast java/math/BigInteger
    //   560: invokevirtual intValue : ()I
    //   563: bipush #32
    //   565: irem
    //   566: invokestatic abs : (I)I
    //   569: invokevirtual charAt : (I)C
    //   572: invokevirtual append : (C)Ljava/lang/StringBuilder;
    //   575: pop
    //   576: iload_2
    //   577: ifne -> 1360
    //   580: goto -> 587
    //   583: invokestatic a : (Ljava/lang/Throwable;)Ljava/lang/Throwable;
    //   586: athrow
    //   587: aload_3
    //   588: getstatic burp/Zelz.ZK : Ljava/lang/String;
    //   591: getstatic burp/Zl50.ZV : Ljava/lang/Object;
    //   594: checkcast java/math/BigInteger
    //   597: invokevirtual intValue : ()I
    //   600: bipush #32
    //   602: irem
    //   603: invokestatic abs : (I)I
    //   606: invokevirtual charAt : (I)C
    //   609: invokevirtual append : (C)Ljava/lang/StringBuilder;
    //   612: pop
    //   613: iload_2
    //   614: ifne -> 1360
    //   617: goto -> 624
    //   620: invokestatic a : (Ljava/lang/Throwable;)Ljava/lang/Throwable;
    //   623: athrow
    //   624: aload_3
    //   625: getstatic burp/Zb29.Zf : Ljava/lang/String;
    //   628: getstatic burp/Zt7x.ZE : Ljava/lang/Object;
    //   631: checkcast java/math/BigInteger
    //   634: invokevirtual intValue : ()I
    //   637: bipush #32
    //   639: irem
    //   640: invokestatic abs : (I)I
    //   643: invokevirtual charAt : (I)C
    //   646: invokevirtual append : (C)Ljava/lang/StringBuilder;
    //   649: pop
    //   650: iload_2
    //   651: ifne -> 1360
    //   654: goto -> 661
    //   657: invokestatic a : (Ljava/lang/Throwable;)Ljava/lang/Throwable;
    //   660: athrow
    //   661: aload_3
    //   662: getstatic burp/Zgwh.Zq : Ljava/lang/String;
    //   665: getstatic burp/Zl5d.Za : Ljava/lang/Object;
    //   668: checkcast java/math/BigInteger
    //   671: invokevirtual intValue : ()I
    //   674: bipush #32
    //   676: irem
    //   677: invokestatic abs : (I)I
    //   680: invokevirtual charAt : (I)C
    //   683: invokevirtual append : (C)Ljava/lang/StringBuilder;
    //   686: pop
    //   687: iload_2
    //   688: ifne -> 1360
    //   691: goto -> 698
    //   694: invokestatic a : (Ljava/lang/Throwable;)Ljava/lang/Throwable;
    //   697: athrow
    //   698: aload_3
    //   699: getstatic burp/Zlvb.Zs : Ljava/lang/String;
    //   702: getstatic burp/Zxxf.ZZ : Ljava/lang/Object;
    //   705: checkcast java/math/BigInteger
    //   708: invokevirtual intValue : ()I
    //   711: bipush #32
    //   713: irem
    //   714: invokestatic abs : (I)I
    //   717: invokevirtual charAt : (I)C
    //   720: invokevirtual append : (C)Ljava/lang/StringBuilder;
    //   723: pop
    //   724: iload_2
    //   725: ifne -> 1360
    //   728: goto -> 735
    //   731: invokestatic a : (Ljava/lang/Throwable;)Ljava/lang/Throwable;
    //   734: athrow
    //   735: aload_3
    //   736: getstatic burp/Zxwl.Zu : Ljava/lang/String;
    //   739: getstatic burp/Zl88.ZK : Ljava/lang/Object;
    //   742: checkcast java/math/BigInteger
    //   745: invokevirtual intValue : ()I
    //   748: bipush #32
    //   750: irem
    //   751: invokestatic abs : (I)I
    //   754: invokevirtual charAt : (I)C
    //   757: invokevirtual append : (C)Ljava/lang/StringBuilder;
    //   760: pop
    //   761: iload_2
    //   762: ifne -> 1360
    //   765: goto -> 772
    //   768: invokestatic a : (Ljava/lang/Throwable;)Ljava/lang/Throwable;
    //   771: athrow
    //   772: aload_3
    //   773: getstatic burp/Zlav.ZW : Ljava/lang/String;
    //   776: getstatic burp/Zeqo.ZZ : Ljava/lang/Object;
    //   779: checkcast java/math/BigInteger
    //   782: invokevirtual intValue : ()I
    //   785: bipush #32
    //   787: irem
    //   788: invokestatic abs : (I)I
    //   791: invokevirtual charAt : (I)C
    //   794: invokevirtual append : (C)Ljava/lang/StringBuilder;
    //   797: pop
    //   798: iload_2
    //   799: ifne -> 1360
    //   802: goto -> 809
    //   805: invokestatic a : (Ljava/lang/Throwable;)Ljava/lang/Throwable;
    //   808: athrow
    //   809: aload_3
    //   810: getstatic burp/Zkhy.Zu : Ljava/lang/String;
    //   813: getstatic burp/Zle4.Zh : Ljava/lang/Object;
    //   816: checkcast java/math/BigInteger
    //   819: invokevirtual intValue : ()I
    //   822: bipush #32
    //   824: irem
    //   825: invokestatic abs : (I)I
    //   828: invokevirtual charAt : (I)C
    //   831: invokevirtual append : (C)Ljava/lang/StringBuilder;
    //   834: pop
    //   835: iload_2
    //   836: ifne -> 1360
    //   839: goto -> 846
    //   842: invokestatic a : (Ljava/lang/Throwable;)Ljava/lang/Throwable;
    //   845: athrow
    //   846: aload_3
    //   847: getstatic burp/Zgkp.ZS : Ljava/lang/String;
    //   850: getstatic burp/Zmu6.Zb : Ljava/lang/Object;
    //   853: checkcast java/math/BigInteger
    //   856: invokevirtual intValue : ()I
    //   859: bipush #32
    //   861: irem
    //   862: invokestatic abs : (I)I
    //   865: invokevirtual charAt : (I)C
    //   868: invokevirtual append : (C)Ljava/lang/StringBuilder;
    //   871: pop
    //   872: iload_2
    //   873: ifne -> 1360
    //   876: goto -> 883
    //   879: invokestatic a : (Ljava/lang/Throwable;)Ljava/lang/Throwable;
    //   882: athrow
    //   883: aload_3
    //   884: getstatic burp/Zg3m.Za : Ljava/lang/String;
    //   887: getstatic burp/Zgpx.ZQ : Ljava/lang/Object;
    //   890: checkcast java/math/BigInteger
    //   893: invokevirtual intValue : ()I
    //   896: bipush #32
    //   898: irem
    //   899: invokestatic abs : (I)I
    //   902: invokevirtual charAt : (I)C
    //   905: invokevirtual append : (C)Ljava/lang/StringBuilder;
    //   908: pop
    //   909: iload_2
    //   910: ifne -> 1360
    //   913: goto -> 920
    //   916: invokestatic a : (Ljava/lang/Throwable;)Ljava/lang/Throwable;
    //   919: athrow
    //   920: aload_3
    //   921: getstatic burp/Ze5f.Zt : Ljava/lang/String;
    //   924: getstatic burp/Zl2g.ZG : Ljava/lang/Object;
    //   927: checkcast java/math/BigInteger
    //   930: invokevirtual intValue : ()I
    //   933: bipush #32
    //   935: irem
    //   936: invokestatic abs : (I)I
    //   939: invokevirtual charAt : (I)C
    //   942: invokevirtual append : (C)Ljava/lang/StringBuilder;
    //   945: pop
    //   946: iload_2
    //   947: ifne -> 1360
    //   950: goto -> 957
    //   953: invokestatic a : (Ljava/lang/Throwable;)Ljava/lang/Throwable;
    //   956: athrow
    //   957: aload_3
    //   958: getstatic burp/Zb1.Z_ : Ljava/lang/String;
    //   961: getstatic burp/Zrnu.Zs : Ljava/lang/Object;
    //   964: checkcast java/math/BigInteger
    //   967: invokevirtual intValue : ()I
    //   970: bipush #32
    //   972: irem
    //   973: invokestatic abs : (I)I
    //   976: invokevirtual charAt : (I)C
    //   979: invokevirtual append : (C)Ljava/lang/StringBuilder;
    //   982: pop
    //   983: iload_2
    //   984: ifne -> 1360
    //   987: goto -> 994
    //   990: invokestatic a : (Ljava/lang/Throwable;)Ljava/lang/Throwable;
    //   993: athrow
    //   994: aload_3
    //   995: getstatic burp/Zmh0.Zs : Ljava/lang/String;
    //   998: getstatic burp/Zl_u.ZR : Ljava/lang/Object;
    //   1001: checkcast java/math/BigInteger
    //   1004: invokevirtual intValue : ()I
    //   1007: bipush #32
    //   1009: irem
    //   1010: invokestatic abs : (I)I
    //   1013: invokevirtual charAt : (I)C
    //   1016: invokevirtual append : (C)Ljava/lang/StringBuilder;
    //   1019: pop
    //   1020: iload_2
    //   1021: ifne -> 1360
    //   1024: goto -> 1031
    //   1027: invokestatic a : (Ljava/lang/Throwable;)Ljava/lang/Throwable;
    //   1030: athrow
    //   1031: aload_3
    //   1032: getstatic burp/Zxyu.ZM : Ljava/lang/String;
    //   1035: getstatic burp/Zzh0.Z_ : Ljava/lang/Object;
    //   1038: checkcast java/math/BigInteger
    //   1041: invokevirtual intValue : ()I
    //   1044: bipush #32
    //   1046: irem
    //   1047: invokestatic abs : (I)I
    //   1050: invokevirtual charAt : (I)C
    //   1053: invokevirtual append : (C)Ljava/lang/StringBuilder;
    //   1056: pop
    //   1057: iload_2
    //   1058: ifne -> 1360
    //   1061: goto -> 1068
    //   1064: invokestatic a : (Ljava/lang/Throwable;)Ljava/lang/Throwable;
    //   1067: athrow
    //   1068: aload_3
    //   1069: getstatic burp/Zldt.Zj : Ljava/lang/String;
    //   1072: getstatic burp/Zzri.ZG : Ljava/lang/Object;
    //   1075: checkcast java/math/BigInteger
    //   1078: invokevirtual intValue : ()I
    //   1081: bipush #32
    //   1083: irem
    //   1084: invokestatic abs : (I)I
    //   1087: invokevirtual charAt : (I)C
    //   1090: invokevirtual append : (C)Ljava/lang/StringBuilder;
    //   1093: pop
    //   1094: iload_2
    //   1095: ifne -> 1360
    //   1098: goto -> 1105
    //   1101: invokestatic a : (Ljava/lang/Throwable;)Ljava/lang/Throwable;
    //   1104: athrow
    //   1105: aload_3
    //   1106: getstatic burp/Zead.Zo : Ljava/lang/String;
    //   1109: getstatic burp/Zxc.ZR : Ljava/lang/Object;
    //   1112: checkcast java/math/BigInteger
    //   1115: invokevirtual intValue : ()I
    //   1118: bipush #32
    //   1120: irem
    //   1121: invokestatic abs : (I)I
    //   1124: invokevirtual charAt : (I)C
    //   1127: invokevirtual append : (C)Ljava/lang/StringBuilder;
    //   1130: pop
    //   1131: iload_2
    //   1132: ifne -> 1360
    //   1135: goto -> 1142
    //   1138: invokestatic a : (Ljava/lang/Throwable;)Ljava/lang/Throwable;
    //   1141: athrow
    //   1142: aload_3
    //   1143: getstatic burp/Zz16.ZA : Ljava/lang/String;
    //   1146: getstatic burp/Zod.ZP : Ljava/lang/Object;
    //   1149: checkcast java/math/BigInteger
    //   1152: invokevirtual intValue : ()I
    //   1155: bipush #32
    //   1157: irem
    //   1158: invokestatic abs : (I)I
    //   1161: invokevirtual charAt : (I)C
    //   1164: invokevirtual append : (C)Ljava/lang/StringBuilder;
    //   1167: pop
    //   1168: iload_2
    //   1169: ifne -> 1360
    //   1172: goto -> 1179
    //   1175: invokestatic a : (Ljava/lang/Throwable;)Ljava/lang/Throwable;
    //   1178: athrow
    //   1179: aload_3
    //   1180: getstatic burp/Zbqk.ZZ : Ljava/lang/String;
    //   1183: getstatic burp/Zsx6.ZN : Ljava/lang/Object;
    //   1186: checkcast java/math/BigInteger
    //   1189: invokevirtual intValue : ()I
    //   1192: bipush #32
    //   1194: irem
    //   1195: invokestatic abs : (I)I
    //   1198: invokevirtual charAt : (I)C
    //   1201: invokevirtual append : (C)Ljava/lang/StringBuilder;
    //   1204: pop
    //   1205: iload_2
    //   1206: ifne -> 1360
    //   1209: goto -> 1216
    //   1212: invokestatic a : (Ljava/lang/Throwable;)Ljava/lang/Throwable;
    //   1215: athrow
    //   1216: aload_3
    //   1217: getstatic burp/Zzqj.Zk : Ljava/lang/String;
    //   1220: getstatic burp/Zrpx.Zi : Ljava/lang/Object;
    //   1223: checkcast java/math/BigInteger
    //   1226: invokevirtual intValue : ()I
    //   1229: bipush #32
    //   1231: irem
    //   1232: invokestatic abs : (I)I
    //   1235: invokevirtual charAt : (I)C
    //   1238: invokevirtual append : (C)Ljava/lang/StringBuilder;
    //   1241: pop
    //   1242: iload_2
    //   1243: ifne -> 1360
    //   1246: goto -> 1253
    //   1249: invokestatic a : (Ljava/lang/Throwable;)Ljava/lang/Throwable;
    //   1252: athrow
    //   1253: aload_3
    //   1254: getstatic burp/Zgds.ZA : Ljava/lang/String;
    //   1257: getstatic burp/Zgr1.Zf : Ljava/lang/Object;
    //   1260: checkcast java/math/BigInteger
    //   1263: invokevirtual intValue : ()I
    //   1266: bipush #32
    //   1268: irem
    //   1269: invokestatic abs : (I)I
    //   1272: invokevirtual charAt : (I)C
    //   1275: invokevirtual append : (C)Ljava/lang/StringBuilder;
    //   1278: pop
    //   1279: iload_2
    //   1280: ifne -> 1360
    //   1283: goto -> 1290
    //   1286: invokestatic a : (Ljava/lang/Throwable;)Ljava/lang/Throwable;
    //   1289: athrow
    //   1290: aload_3
    //   1291: getstatic burp/Zb9h.Zf : Ljava/lang/String;
    //   1294: getstatic burp/Zkca.ZQ : Ljava/lang/Object;
    //   1297: checkcast java/math/BigInteger
    //   1300: invokevirtual intValue : ()I
    //   1303: bipush #32
    //   1305: irem
    //   1306: invokestatic abs : (I)I
    //   1309: invokevirtual charAt : (I)C
    //   1312: invokevirtual append : (C)Ljava/lang/StringBuilder;
    //   1315: pop
    //   1316: iload_2
    //   1317: ifne -> 1360
    //   1320: goto -> 1327
    //   1323: invokestatic a : (Ljava/lang/Throwable;)Ljava/lang/Throwable;
    //   1326: athrow
    //   1327: aload_3
    //   1328: getstatic burp/Zsxj.Zp : Ljava/lang/String;
    //   1331: getstatic burp/Zr_w.ZK : Ljava/lang/Object;
    //   1334: checkcast java/math/BigInteger
    //   1337: invokevirtual intValue : ()I
    //   1340: bipush #32
    //   1342: irem
    //   1343: invokestatic abs : (I)I
    //   1346: invokevirtual charAt : (I)C
    //   1349: invokevirtual append : (C)Ljava/lang/StringBuilder;
    //   1352: pop
    //   1353: goto -> 1360
    //   1356: invokestatic a : (Ljava/lang/Throwable;)Ljava/lang/Throwable;
    //   1359: athrow
    //   1360: iinc #4, 1
    //   1363: iload_2
    //   1364: ifne -> 30
    //   1367: aload_3
    //   1368: invokevirtual toString : ()Ljava/lang/String;
    //   1371: putstatic burp/Zml.ZN : Ljava/lang/String;
    //   1374: ldc2_w 8682522807148012
    //   1377: invokestatic currentTimeMillis : ()J
    //   1380: lxor
    //   1381: lstore #5
    //   1383: lload #5
    //   1385: ldc2_w 25214903917
    //   1388: lmul
    //   1389: ldc2_w 11
    //   1392: ladd
    //   1393: ldc2_w 281474976710655
    //   1396: land
    //   1397: lstore #5
    //   1399: lload #5
    //   1401: bipush #32
    //   1403: lshl
    //   1404: lstore #7
    //   1406: lload #5
    //   1408: ldc2_w 25214903917
    //   1411: lmul
    //   1412: ldc2_w 11
    //   1415: ladd
    //   1416: ldc2_w 281474976710655
    //   1419: land
    //   1420: lstore #5
    //   1422: lload #7
    //   1424: lload #5
    //   1426: ladd
    //   1427: lstore #7
    //   1429: bipush #16
    //   1431: newarray byte
    //   1433: dup
    //   1434: iconst_0
    //   1435: bipush #48
    //   1437: bastore
    //   1438: dup
    //   1439: iconst_1
    //   1440: bipush #49
    //   1442: bastore
    //   1443: dup
    //   1444: iconst_2
    //   1445: bipush #50
    //   1447: bastore
    //   1448: dup
    //   1449: iconst_3
    //   1450: bipush #51
    //   1452: bastore
    //   1453: dup
    //   1454: iconst_4
    //   1455: bipush #52
    //   1457: bastore
    //   1458: dup
    //   1459: iconst_5
    //   1460: bipush #53
    //   1462: bastore
    //   1463: dup
    //   1464: bipush #6
    //   1466: bipush #54
    //   1468: bastore
    //   1469: dup
    //   1470: bipush #7
    //   1472: bipush #55
    //   1474: bastore
    //   1475: dup
    //   1476: bipush #8
    //   1478: bipush #56
    //   1480: bastore
    //   1481: dup
    //   1482: bipush #9
    //   1484: bipush #57
    //   1486: bastore
    //   1487: dup
    //   1488: bipush #10
    //   1490: bipush #97
    //   1492: bastore
    //   1493: dup
    //   1494: bipush #11
    //   1496: bipush #98
    //   1498: bastore
    //   1499: dup
    //   1500: bipush #12
    //   1502: bipush #99
    //   1504: bastore
    //   1505: dup
    //   1506: bipush #13
    //   1508: bipush #100
    //   1510: bastore
    //   1511: dup
    //   1512: bipush #14
    //   1514: bipush #101
    //   1516: bastore
    //   1517: dup
    //   1518: bipush #15
    //   1520: bipush #102
    //   1522: bastore
    //   1523: astore #9
    //   1525: bipush #64
    //   1527: newarray byte
    //   1529: astore #10
    //   1531: bipush #64
    //   1533: istore #11
    //   1535: bipush #16
    //   1537: istore #12
    //   1539: iload #12
    //   1541: iconst_1
    //   1542: isub
    //   1543: i2l
    //   1544: lstore #13
    //   1546: aload #10
    //   1548: iinc #11, -1
    //   1551: iload #11
    //   1553: aload #9
    //   1555: lload #7
    //   1557: lload #13
    //   1559: land
    //   1560: l2i
    //   1561: baload
    //   1562: bastore
    //   1563: lload #7
    //   1565: iconst_4
    //   1566: lushr
    //   1567: lstore #7
    //   1569: lload #7
    //   1571: lconst_0
    //   1572: lcmp
    //   1573: ifne -> 1546
    //   1576: bipush #64
    //   1578: iload #11
    //   1580: isub
    //   1581: newarray byte
    //   1583: astore #4
    //   1585: iconst_0
    //   1586: istore #15
    //   1588: iload #15
    //   1590: aload #4
    //   1592: arraylength
    //   1593: if_icmpge -> 1616
    //   1596: aload #4
    //   1598: iload #15
    //   1600: aload #10
    //   1602: iload #11
    //   1604: iload #15
    //   1606: iadd
    //   1607: baload
    //   1608: bastore
    //   1609: iinc #15, 1
    //   1612: iload_2
    //   1613: ifne -> 1588
    //   1616: aload #4
    //   1618: arraylength
    //   1619: bipush #10
    //   1621: if_icmplt -> 1383
    //   1624: sipush #21449
    //   1627: sipush #6823
    //   1630: invokestatic a : (II)Ljava/lang/String;
    //   1633: iconst_1
    //   1634: ldc burp/Zz5d
    //   1636: invokevirtual getClassLoader : ()Ljava/lang/ClassLoader;
    //   1639: invokestatic forName : (Ljava/lang/String;ZLjava/lang/ClassLoader;)Ljava/lang/Class;
    //   1642: invokevirtual getDeclaredFields : ()[Ljava/lang/reflect/Field;
    //   1645: astore #4
    //   1647: aload #4
    //   1649: arraylength
    //   1650: istore #5
    //   1652: iconst_0
    //   1653: istore #6
    //   1655: iload #6
    //   1657: iload #5
    //   1659: if_icmpge -> 1797
    //   1662: aload #4
    //   1664: iload #6
    //   1666: aaload
    //   1667: astore #7
    //   1669: aload #7
    //   1671: invokevirtual getModifiers : ()I
    //   1674: invokestatic isStatic : (I)Z
    //   1677: ifne -> 1687
    //   1680: goto -> 1790
    //   1683: invokestatic a : (Ljava/lang/Throwable;)Ljava/lang/Throwable;
    //   1686: athrow
    //   1687: aload #7
    //   1689: invokevirtual getType : ()Ljava/lang/Class;
    //   1692: astore #8
    //   1694: aload #8
    //   1696: ifnull -> 1777
    //   1699: aload #8
    //   1701: invokevirtual isPrimitive : ()Z
    //   1704: ifne -> 1777
    //   1707: goto -> 1714
    //   1710: invokestatic a : (Ljava/lang/Throwable;)Ljava/lang/Throwable;
    //   1713: athrow
    //   1714: aload #8
    //   1716: invokevirtual getPackage : ()Ljava/lang/Package;
    //   1719: ifnull -> 1777
    //   1722: goto -> 1729
    //   1725: invokestatic a : (Ljava/lang/Throwable;)Ljava/lang/Throwable;
    //   1728: athrow
    //   1729: aload #8
    //   1731: invokevirtual getPackage : ()Ljava/lang/Package;
    //   1734: invokevirtual getName : ()Ljava/lang/String;
    //   1737: ifnull -> 1777
    //   1740: goto -> 1747
    //   1743: invokestatic a : (Ljava/lang/Throwable;)Ljava/lang/Throwable;
    //   1746: athrow
    //   1747: aload #8
    //   1749: invokevirtual getPackage : ()Ljava/lang/Package;
    //   1752: invokevirtual getName : ()Ljava/lang/String;
    //   1755: sipush #21454
    //   1758: sipush #5187
    //   1761: invokestatic a : (II)Ljava/lang/String;
    //   1764: invokevirtual startsWith : (Ljava/lang/String;)Z
    //   1767: ifne -> 1777
    //   1770: goto -> 1777
    //   1773: invokestatic a : (Ljava/lang/Throwable;)Ljava/lang/Throwable;
    //   1776: athrow
    //   1777: aload #7
    //   1779: iconst_1
    //   1780: invokevirtual setAccessible : (Z)V
    //   1783: aload #7
    //   1785: aconst_null
    //   1786: invokevirtual get : (Ljava/lang/Object;)Ljava/lang/Object;
    //   1789: pop
    //   1790: iinc #6, 1
    //   1793: iload_2
    //   1794: ifne -> 1655
    //   1797: sipush #21452
    //   1800: sipush #-17455
    //   1803: invokestatic a : (II)Ljava/lang/String;
    //   1806: invokestatic forName : (Ljava/lang/String;)Ljava/lang/Class;
    //   1809: invokevirtual getDeclaredMethods : ()[Ljava/lang/reflect/Method;
    //   1812: astore #4
    //   1814: aload #4
    //   1816: arraylength
    //   1817: istore #5
    //   1819: iconst_0
    //   1820: istore #6
    //   1822: iload #6
    //   1824: iload #5
    //   1826: if_icmpge -> 1938
    //   1829: aload #4
    //   1831: iload #6
    //   1833: aaload
    //   1834: astore #7
    //   1836: aload #7
    //   1838: invokevirtual getParameterTypes : ()[Ljava/lang/Class;
    //   1841: pop
    //   1842: aload #7
    //   1844: invokevirtual getModifiers : ()I
    //   1847: invokestatic isStatic : (I)Z
    //   1850: ifeq -> 1924
    //   1853: aload #7
    //   1855: invokevirtual getParameterTypes : ()[Ljava/lang/Class;
    //   1858: arraylength
    //   1859: iconst_2
    //   1860: if_icmpne -> 1924
    //   1863: goto -> 1870
    //   1866: invokestatic a : (Ljava/lang/Throwable;)Ljava/lang/Throwable;
    //   1869: athrow
    //   1870: aload #7
    //   1872: invokevirtual getReturnType : ()Ljava/lang/Class;
    //   1875: getstatic java/lang/Boolean.TYPE : Ljava/lang/Class;
    //   1878: if_acmpne -> 1924
    //   1881: goto -> 1888
    //   1884: invokestatic a : (Ljava/lang/Throwable;)Ljava/lang/Throwable;
    //   1887: athrow
    //   1888: aload #7
    //   1890: iconst_1
    //   1891: invokevirtual setAccessible : (Z)V
    //   1894: aload #7
    //   1896: aconst_null
    //   1897: iconst_2
    //   1898: anewarray java/lang/Object
    //   1901: dup
    //   1902: iconst_0
    //   1903: aload_0
    //   1904: aastore
    //   1905: dup
    //   1906: iconst_1
    //   1907: aload_1
    //   1908: aastore
    //   1909: invokevirtual invoke : (Ljava/lang/Object;[Ljava/lang/Object;)Ljava/lang/Object;
    //   1912: pop
    //   1913: iload_2
    //   1914: ifne -> 1938
    //   1917: goto -> 1924
    //   1920: invokestatic a : (Ljava/lang/Throwable;)Ljava/lang/Throwable;
    //   1923: athrow
    //   1924: iinc #6, 1
    //   1927: iload_2
    //   1928: ifne -> 1822
    //   1931: goto -> 1938
    //   1934: invokestatic a : (Ljava/lang/Throwable;)Ljava/lang/Throwable;
    //   1937: athrow
    //   1938: sipush #21443
    //   1941: sipush #-29798
    //   1944: invokestatic a : (II)Ljava/lang/String;
    //   1947: iconst_1
    //   1948: ldc burp/Zx4u
    //   1950: invokevirtual getClassLoader : ()Ljava/lang/ClassLoader;
    //   1953: invokestatic forName : (Ljava/lang/String;ZLjava/lang/ClassLoader;)Ljava/lang/Class;
    //   1956: invokevirtual getDeclaredFields : ()[Ljava/lang/reflect/Field;
    //   1959: astore #4
    //   1961: aload #4
    //   1963: arraylength
    //   1964: istore #5
    //   1966: iconst_0
    //   1967: istore #6
    //   1969: iload #6
    //   1971: iload #5
    //   1973: if_icmpge -> 2111
    //   1976: aload #4
    //   1978: iload #6
    //   1980: aaload
    //   1981: astore #7
    //   1983: aload #7
    //   1985: invokevirtual getModifiers : ()I
    //   1988: invokestatic isStatic : (I)Z
    //   1991: ifne -> 2001
    //   1994: goto -> 2104
    //   1997: invokestatic a : (Ljava/lang/Throwable;)Ljava/lang/Throwable;
    //   2000: athrow
    //   2001: aload #7
    //   2003: invokevirtual getType : ()Ljava/lang/Class;
    //   2006: astore #8
    //   2008: aload #8
    //   2010: ifnull -> 2091
    //   2013: aload #8
    //   2015: invokevirtual isPrimitive : ()Z
    //   2018: ifne -> 2091
    //   2021: goto -> 2028
    //   2024: invokestatic a : (Ljava/lang/Throwable;)Ljava/lang/Throwable;
    //   2027: athrow
    //   2028: aload #8
    //   2030: invokevirtual getPackage : ()Ljava/lang/Package;
    //   2033: ifnull -> 2091
    //   2036: goto -> 2043
    //   2039: invokestatic a : (Ljava/lang/Throwable;)Ljava/lang/Throwable;
    //   2042: athrow
    //   2043: aload #8
    //   2045: invokevirtual getPackage : ()Ljava/lang/Package;
    //   2048: invokevirtual getName : ()Ljava/lang/String;
    //   2051: ifnull -> 2091
    //   2054: goto -> 2061
    //   2057: invokestatic a : (Ljava/lang/Throwable;)Ljava/lang/Throwable;
    //   2060: athrow
    //   2061: aload #8
    //   2063: invokevirtual getPackage : ()Ljava/lang/Package;
    //   2066: invokevirtual getName : ()Ljava/lang/String;
    //   2069: sipush #21455
    //   2072: sipush #30068
    //   2075: invokestatic a : (II)Ljava/lang/String;
    //   2078: invokevirtual startsWith : (Ljava/lang/String;)Z
    //   2081: ifne -> 2091
    //   2084: goto -> 2091
    //   2087: invokestatic a : (Ljava/lang/Throwable;)Ljava/lang/Throwable;
    //   2090: athrow
    //   2091: aload #7
    //   2093: iconst_1
    //   2094: invokevirtual setAccessible : (Z)V
    //   2097: aload #7
    //   2099: aconst_null
    //   2100: invokevirtual get : (Ljava/lang/Object;)Ljava/lang/Object;
    //   2103: pop
    //   2104: iinc #6, 1
    //   2107: iload_2
    //   2108: ifne -> 1969
    //   2111: sipush #21451
    //   2114: sipush #20669
    //   2117: invokestatic a : (II)Ljava/lang/String;
    //   2120: invokestatic forName : (Ljava/lang/String;)Ljava/lang/Class;
    //   2123: invokevirtual getDeclaredMethods : ()[Ljava/lang/reflect/Method;
    //   2126: astore #4
    //   2128: aload #4
    //   2130: arraylength
    //   2131: istore #5
    //   2133: iconst_0
    //   2134: istore #6
    //   2136: iload #6
    //   2138: iload #5
    //   2140: if_icmpge -> 2273
    //   2143: aload #4
    //   2145: iload #6
    //   2147: aaload
    //   2148: astore #7
    //   2150: aload #7
    //   2152: invokevirtual getParameterTypes : ()[Ljava/lang/Class;
    //   2155: pop
    //   2156: aload #7
    //   2158: invokevirtual getModifiers : ()I
    //   2161: invokestatic isStatic : (I)Z
    //   2164: ifeq -> 2259
    //   2167: aload #7
    //   2169: invokevirtual getParameterTypes : ()[Ljava/lang/Class;
    //   2172: arraylength
    //   2173: iconst_2
    //   2174: if_icmpne -> 2259
    //   2177: goto -> 2184
    //   2180: invokestatic a : (Ljava/lang/Throwable;)Ljava/lang/Throwable;
    //   2183: athrow
    //   2184: aload #7
    //   2186: invokevirtual getReturnType : ()Ljava/lang/Class;
    //   2189: getstatic java/lang/Void.TYPE : Ljava/lang/Class;
    //   2192: invokevirtual equals : (Ljava/lang/Object;)Z
    //   2195: ifeq -> 2259
    //   2198: goto -> 2205
    //   2201: invokestatic a : (Ljava/lang/Throwable;)Ljava/lang/Throwable;
    //   2204: athrow
    //   2205: aload #7
    //   2207: iconst_1
    //   2208: invokevirtual setAccessible : (Z)V
    //   2211: aload #7
    //   2213: aconst_null
    //   2214: iconst_2
    //   2215: anewarray java/lang/Object
    //   2218: dup
    //   2219: iconst_0
    //   2220: aload_0
    //   2221: aastore
    //   2222: dup
    //   2223: iconst_1
    //   2224: aload_1
    //   2225: ifnonnull -> 2243
    //   2228: goto -> 2235
    //   2231: invokestatic a : (Ljava/lang/Throwable;)Ljava/lang/Throwable;
    //   2234: athrow
    //   2235: aload_1
    //   2236: goto -> 2250
    //   2239: invokestatic a : (Ljava/lang/Throwable;)Ljava/lang/Throwable;
    //   2242: athrow
    //   2243: aload_1
    //   2244: checkcast [B
    //   2247: invokevirtual clone : ()Ljava/lang/Object;
    //   2250: aastore
    //   2251: invokevirtual invoke : (Ljava/lang/Object;[Ljava/lang/Object;)Ljava/lang/Object;
    //   2254: pop
    //   2255: iload_2
    //   2256: ifne -> 2273
    //   2259: iinc #6, 1
    //   2262: iload_2
    //   2263: ifne -> 2136
    //   2266: goto -> 2273
    //   2269: invokestatic a : (Ljava/lang/Throwable;)Ljava/lang/Throwable;
    //   2272: athrow
    //   2273: getstatic burp/Zmpc.ZT : Ljava/lang/String;
    //   2276: getstatic burp/Zmv9.Zw : Ljava/lang/Object;
    //   2279: checkcast java/math/BigInteger
    //   2282: invokevirtual intValue : ()I
    //   2285: bipush #32
    //   2287: irem
    //   2288: invokestatic abs : (I)I
    //   2291: invokevirtual charAt : (I)C
    //   2294: getstatic burp/Zsji.Zr : Ljava/lang/String;
    //   2297: getstatic burp/Zrbp.Z_ : Ljava/lang/Object;
    //   2300: checkcast java/math/BigInteger
    //   2303: invokevirtual intValue : ()I
    //   2306: bipush #32
    //   2308: irem
    //   2309: invokestatic abs : (I)I
    //   2312: invokevirtual charAt : (I)C
    //   2315: if_icmple -> 2422
    //   2318: getstatic burp/Zmcq.ZY : Ljava/lang/String;
    //   2321: getstatic burp/Zgfm.ZV : Ljava/lang/Object;
    //   2324: checkcast java/math/BigInteger
    //   2327: invokevirtual intValue : ()I
    //   2330: bipush #32
    //   2332: irem
    //   2333: invokestatic abs : (I)I
    //   2336: invokevirtual charAt : (I)C
    //   2339: getstatic burp/Zxzv.ZI : Ljava/lang/String;
    //   2342: getstatic burp/Zm54.ZS : Ljava/lang/Object;
    //   2345: checkcast java/math/BigInteger
    //   2348: invokevirtual intValue : ()I
    //   2351: bipush #32
    //   2353: irem
    //   2354: invokestatic abs : (I)I
    //   2357: invokevirtual charAt : (I)C
    //   2360: if_icmple -> 2422
    //   2363: goto -> 2370
    //   2366: invokestatic a : (Ljava/lang/Throwable;)Ljava/lang/Throwable;
    //   2369: athrow
    //   2370: getstatic burp/Zb8x.Zp : Ljava/lang/String;
    //   2373: getstatic burp/Ztg3.Zg : Ljava/lang/Object;
    //   2376: checkcast java/math/BigInteger
    //   2379: invokevirtual intValue : ()I
    //   2382: bipush #32
    //   2384: irem
    //   2385: invokestatic abs : (I)I
    //   2388: invokevirtual charAt : (I)C
    //   2391: getstatic burp/Zlbt.ZE : Ljava/lang/String;
    //   2394: getstatic burp/Zk7w.ZF : Ljava/lang/Object;
    //   2397: checkcast java/math/BigInteger
    //   2400: invokevirtual intValue : ()I
    //   2403: bipush #32
    //   2405: irem
    //   2406: invokestatic abs : (I)I
    //   2409: invokevirtual charAt : (I)C
    //   2412: if_icmpgt -> 2430
    //   2415: goto -> 2422
    //   2418: invokestatic a : (Ljava/lang/Throwable;)Ljava/lang/Throwable;
    //   2421: athrow
    //   2422: iconst_1
    //   2423: goto -> 2431
    //   2426: invokestatic a : (Ljava/lang/Throwable;)Ljava/lang/Throwable;
    //   2429: athrow
    //   2430: iconst_0
    //   2431: ireturn
    //   2432: astore_3
    //   2433: new java/lang/Exception
    //   2436: dup
    //   2437: aload_3
    //   2438: invokevirtual getMessage : ()Ljava/lang/String;
    //   2441: invokespecial <init> : (Ljava/lang/String;)V
    //   2444: athrow
    // Exception table:
    //   from	to	target	type
    //   4	2431	2432	java/lang/Throwable
    //   37	210	213	java/lang/Throwable
    //   180	247	250	java/lang/Throwable
    //   217	284	287	java/lang/Throwable
    //   254	321	324	java/lang/Throwable
    //   291	358	361	java/lang/Throwable
    //   328	395	398	java/lang/Throwable
    //   365	432	435	java/lang/Throwable
    //   402	469	472	java/lang/Throwable
    //   439	506	509	java/lang/Throwable
    //   476	543	546	java/lang/Throwable
    //   513	580	583	java/lang/Throwable
    //   550	617	620	java/lang/Throwable
    //   587	654	657	java/lang/Throwable
    //   624	691	694	java/lang/Throwable
    //   661	728	731	java/lang/Throwable
    //   698	765	768	java/lang/Throwable
    //   735	802	805	java/lang/Throwable
    //   772	839	842	java/lang/Throwable
    //   809	876	879	java/lang/Throwable
    //   846	913	916	java/lang/Throwable
    //   883	950	953	java/lang/Throwable
    //   920	987	990	java/lang/Throwable
    //   957	1024	1027	java/lang/Throwable
    //   994	1061	1064	java/lang/Throwable
    //   1031	1098	1101	java/lang/Throwable
    //   1068	1135	1138	java/lang/Throwable
    //   1105	1172	1175	java/lang/Throwable
    //   1142	1209	1212	java/lang/Throwable
    //   1179	1246	1249	java/lang/Throwable
    //   1216	1283	1286	java/lang/Throwable
    //   1253	1320	1323	java/lang/Throwable
    //   1290	1353	1356	java/lang/Throwable
    //   1669	1683	1683	java/lang/Throwable
    //   1694	1707	1710	java/lang/Throwable
    //   1699	1722	1725	java/lang/Throwable
    //   1714	1740	1743	java/lang/Throwable
    //   1729	1770	1773	java/lang/Throwable
    //   1836	1863	1866	java/lang/Throwable
    //   1853	1881	1884	java/lang/Throwable
    //   1870	1917	1920	java/lang/Throwable
    //   1888	1931	1934	java/lang/Throwable
    //   1983	1997	1997	java/lang/Throwable
    //   2008	2021	2024	java/lang/Throwable
    //   2013	2036	2039	java/lang/Throwable
    //   2028	2054	2057	java/lang/Throwable
    //   2043	2084	2087	java/lang/Throwable
    //   2150	2177	2180	java/lang/Throwable
    //   2167	2198	2201	java/lang/Throwable
    //   2184	2228	2231	java/lang/Throwable
    //   2205	2239	2239	java/lang/Throwable
    //   2250	2266	2269	java/lang/Throwable
    //   2273	2363	2366	java/lang/Throwable
    //   2318	2415	2418	java/lang/Throwable
    //   2370	2426	2426	java/lang/Throwable
  }
  
  static void ZR(Object paramObject) {
    Zzmo.Zx = a(21450, -26448);
    Zzmo.ZI = new BigInteger(a(21453, 6326));
    boolean bool = Zt2e.ZN();
    try {
      try {
        if (Zkgp.ZM.charAt(Math.abs(((BigInteger)Zxd4.Zt).intValue() % 32)) <= Zgjj.Zi.charAt(Math.abs(((BigInteger)Zrly.ZB).intValue() % 32))) {
          try {
            Zlfg.ZJ(Class.forName(a(21440, -31641)));
            if (!bool)
              Zzri.Zd(Class.forName(a(21441, -24730))); 
          } catch (Throwable throwable) {
            throw a(null);
          } 
          return;
        } 
      } catch (Throwable throwable) {
        throw a(null);
      } 
      Zzri.Zd(Class.forName(a(21441, -24730)));
    } catch (Throwable throwable) {}
  }
  
  static {
    // Byte code:
    //   0: bipush #12
    //   2: anewarray java/lang/String
    //   5: astore #5
    //   7: iconst_0
    //   8: istore_3
    //   9: ldc 'þô!l<ZóåX'eTÈ$W;.B¾æ7W,6B\\t(ó}éX´\\f~\\tzs7ù«!;\\t0åk+ûYté1Þ^uEMÐ\\t³î¥%C:bLMHÎ. vG~~ªüb¸èîm(·-¨,Ùï¯¯ÒEbKØ¼g+D¯\\t§ÿ¡Ïô\\f¡¥A±ø¶[µwq;RË oC¬ó6%-ëRúÁâ,ü3p¼)MiÖ*2ýÀrY\\tWs\\t¶5Ný'
    //   11: dup
    //   12: astore_2
    //   13: invokevirtual length : ()I
    //   16: istore #4
    //   18: bipush #32
    //   20: istore_1
    //   21: iconst_m1
    //   22: istore_0
    //   23: bipush #26
    //   25: iinc #0, 1
    //   28: aload_2
    //   29: iload_0
    //   30: dup
    //   31: iload_1
    //   32: iadd
    //   33: invokevirtual substring : (II)Ljava/lang/String;
    //   36: iconst_m1
    //   37: goto -> 143
    //   40: aload #5
    //   42: swap
    //   43: iload_3
    //   44: iinc #3, 1
    //   47: swap
    //   48: aastore
    //   49: iload_0
    //   50: iload_1
    //   51: iadd
    //   52: dup
    //   53: istore_0
    //   54: iload #4
    //   56: if_icmpge -> 68
    //   59: aload_2
    //   60: iload_0
    //   61: invokevirtual charAt : (I)C
    //   64: istore_1
    //   65: goto -> 23
    //   68: ldc '/ÚPëÓo?\\tå«JÓù½-)'
    //   70: dup
    //   71: astore_2
    //   72: invokevirtual length : ()I
    //   75: istore #4
    //   77: bipush #9
    //   79: istore_1
    //   80: iconst_m1
    //   81: istore_0
    //   82: bipush #57
    //   84: iinc #0, 1
    //   87: aload_2
    //   88: iload_0
    //   89: dup
    //   90: iload_1
    //   91: iadd
    //   92: invokevirtual substring : (II)Ljava/lang/String;
    //   95: iconst_0
    //   96: goto -> 143
    //   99: aload #5
    //   101: swap
    //   102: iload_3
    //   103: iinc #3, 1
    //   106: swap
    //   107: aastore
    //   108: iload_0
    //   109: iload_1
    //   110: iadd
    //   111: dup
    //   112: istore_0
    //   113: iload #4
    //   115: if_icmpge -> 127
    //   118: aload_2
    //   119: iload_0
    //   120: invokevirtual charAt : (I)C
    //   123: istore_1
    //   124: goto -> 82
    //   127: aload #5
    //   129: putstatic burp/Zk88.a : [Ljava/lang/String;
    //   132: bipush #12
    //   134: anewarray java/lang/String
    //   137: putstatic burp/Zk88.b : [Ljava/lang/String;
    //   140: goto -> 300
    //   143: dup_x2
    //   144: pop
    //   145: invokevirtual toCharArray : ()[C
    //   148: dup_x1
    //   149: arraylength
    //   150: dup_x2
    //   151: pop
    //   152: iconst_0
    //   153: istore #6
    //   155: dup2_x1
    //   156: pop2
    //   157: dup_x2
    //   158: iconst_1
    //   159: if_icmpgt -> 260
    //   162: dup2
    //   163: swap
    //   164: iload #6
    //   166: dup2_x1
    //   167: caload
    //   168: swap
    //   169: iload #6
    //   171: bipush #7
    //   173: irem
    //   174: tableswitch default -> 242, 0 -> 212, 1 -> 217, 2 -> 222, 3 -> 227, 4 -> 232, 5 -> 237
    //   212: bipush #30
    //   214: goto -> 244
    //   217: bipush #62
    //   219: goto -> 244
    //   222: bipush #37
    //   224: goto -> 244
    //   227: bipush #77
    //   229: goto -> 244
    //   232: bipush #120
    //   234: goto -> 244
    //   237: bipush #35
    //   239: goto -> 244
    //   242: bipush #78
    //   244: ixor
    //   245: ixor
    //   246: i2c
    //   247: castore
    //   248: iinc #6, 1
    //   251: dup
    //   252: ifne -> 260
    //   255: dup2
    //   256: dup_x1
    //   257: goto -> 166
    //   260: dup2_x1
    //   261: pop2
    //   262: dup_x2
    //   263: iload #6
    //   265: if_icmpgt -> 162
    //   268: pop
    //   269: new java/lang/String
    //   272: dup_x1
    //   273: swap
    //   274: invokespecial <init> : ([C)V
    //   277: invokevirtual intern : ()Ljava/lang/String;
    //   280: swap
    //   281: pop
    //   282: swap
    //   283: tableswitch default -> 40, 0 -> 99
    //   300: sipush #21442
    //   303: sipush #1204
    //   306: invokestatic a : (II)Ljava/lang/String;
    //   309: putstatic burp/Zk88.ZZ : Ljava/lang/String;
    //   312: new java/math/BigInteger
    //   315: dup
    //   316: iconst_1
    //   317: bipush #32
    //   319: newarray byte
    //   321: dup
    //   322: iconst_0
    //   323: bipush #37
    //   325: bastore
    //   326: dup
    //   327: iconst_1
    //   328: bipush #53
    //   330: bastore
    //   331: dup
    //   332: iconst_2
    //   333: bipush #-117
    //   335: bastore
    //   336: dup
    //   337: iconst_3
    //   338: bipush #-78
    //   340: bastore
    //   341: dup
    //   342: iconst_4
    //   343: bipush #42
    //   345: bastore
    //   346: dup
    //   347: iconst_5
    //   348: bipush #-90
    //   350: bastore
    //   351: dup
    //   352: bipush #6
    //   354: bipush #-33
    //   356: bastore
    //   357: dup
    //   358: bipush #7
    //   360: bipush #-107
    //   362: bastore
    //   363: dup
    //   364: bipush #8
    //   366: bipush #23
    //   368: bastore
    //   369: dup
    //   370: bipush #9
    //   372: bipush #56
    //   374: bastore
    //   375: dup
    //   376: bipush #10
    //   378: bipush #60
    //   380: bastore
    //   381: dup
    //   382: bipush #11
    //   384: bipush #-40
    //   386: bastore
    //   387: dup
    //   388: bipush #12
    //   390: bipush #114
    //   392: bastore
    //   393: dup
    //   394: bipush #13
    //   396: bipush #-18
    //   398: bastore
    //   399: dup
    //   400: bipush #14
    //   402: bipush #-107
    //   404: bastore
    //   405: dup
    //   406: bipush #15
    //   408: bipush #-114
    //   410: bastore
    //   411: dup
    //   412: bipush #16
    //   414: bipush #-124
    //   416: bastore
    //   417: dup
    //   418: bipush #17
    //   420: bipush #111
    //   422: bastore
    //   423: dup
    //   424: bipush #18
    //   426: bipush #35
    //   428: bastore
    //   429: dup
    //   430: bipush #19
    //   432: bipush #-98
    //   434: bastore
    //   435: dup
    //   436: bipush #20
    //   438: bipush #43
    //   440: bastore
    //   441: dup
    //   442: bipush #21
    //   444: bipush #-104
    //   446: bastore
    //   447: dup
    //   448: bipush #22
    //   450: bipush #-68
    //   452: bastore
    //   453: dup
    //   454: bipush #23
    //   456: bipush #-74
    //   458: bastore
    //   459: dup
    //   460: bipush #24
    //   462: bipush #-92
    //   464: bastore
    //   465: dup
    //   466: bipush #25
    //   468: bipush #86
    //   470: bastore
    //   471: dup
    //   472: bipush #26
    //   474: bipush #113
    //   476: bastore
    //   477: dup
    //   478: bipush #27
    //   480: bipush #-16
    //   482: bastore
    //   483: dup
    //   484: bipush #28
    //   486: bipush #-20
    //   488: bastore
    //   489: dup
    //   490: bipush #29
    //   492: bipush #-59
    //   494: bastore
    //   495: dup
    //   496: bipush #30
    //   498: bipush #16
    //   500: bastore
    //   501: dup
    //   502: bipush #31
    //   504: bipush #21
    //   506: bastore
    //   507: invokespecial <init> : (I[B)V
    //   510: putstatic burp/Zk88.ZX : Ljava/lang/Object;
    //   513: return
  }
  
  private static Throwable a(Throwable paramThrowable) {
    return paramThrowable;
  }
  
  private static String a(int paramInt1, int paramInt2) {
    int i = (paramInt1 ^ 0x53CA) & 0xFFFF;
    if (b[i] == null) {
      char[] arrayOfChar = a[i].toCharArray();
      switch (arrayOfChar[0] & 0xFF) {
        case 0:
        
        case 1:
        
        case 2:
        
        case 3:
        
        case 4:
        
        case 5:
        
        case 6:
        
        case 7:
        
        case 8:
        
        case 9:
        
        case 10:
        
        case 11:
        
        case 12:
        
        case 13:
        
        case 14:
        
        case 15:
        
        case 16:
        
        case 17:
        
        case 18:
        
        case 19:
        
        case 20:
        
        case 21:
        
        case 22:
        
        case 23:
        
        case 24:
        
        case 25:
        
        case 26:
        
        case 27:
        
        case 28:
        
        case 29:
        
        case 30:
        
        case 31:
        
        case 32:
        
        case 33:
        
        case 34:
        
        case 35:
        
        case 36:
        
        case 37:
        
        case 38:
        
        case 39:
        
        case 40:
        
        case 41:
        
        case 42:
        
        case 43:
        
        case 44:
        
        case 45:
        
        case 46:
        
        case 47:
        
        case 48:
        
        case 49:
        
        case 50:
        
        case 51:
        
        case 52:
        
        case 53:
        
        case 54:
        
        case 55:
        
        case 56:
        
        case 57:
        
        case 58:
        
        case 59:
        
        case 60:
        
        case 61:
        
        case 62:
        
        case 63:
        
        case 64:
        
        case 65:
        
        case 66:
        
        case 67:
        
        case 68:
        
        case 69:
        
        case 70:
        
        case 71:
        
        case 72:
        
        case 73:
        
        case 74:
        
        case 75:
        
        case 76:
        
        case 77:
        
        case 78:
        
        case 79:
        
        case 80:
        
        case 81:
        
        case 82:
        
        case 83:
        
        case 84:
        
        case 85:
        
        case 86:
        
        case 87:
        
        case 88:
        
        case 89:
        
        case 90:
        
        case 91:
        
        case 92:
        
        case 93:
        
        case 94:
        
        case 95:
        
        case 96:
        
        case 97:
        
        case 98:
        
        case 99:
        
        case 100:
        
        case 101:
        
        case 102:
        
        case 103:
        
        case 104:
        
        case 105:
        
        case 106:
        
        case 107:
        
        case 108:
        
        case 109:
        
        case 110:
        
        case 111:
        
        case 112:
        
        case 113:
        
        case 114:
        
        case 115:
        
        case 116:
        
        case 117:
        
        case 118:
        
        case 119:
        
        case 120:
        
        case 121:
        
        case 122:
        
        case 123:
        
        case 124:
        
        case 125:
        
        case 126:
        
        case 127:
        
        case 128:
        
        case 129:
        
        case 130:
        
        case 131:
        
        case 132:
        
        case 133:
        
        case 134:
        
        case 135:
        
        case 136:
        
        case 137:
        
        case 138:
        
        case 139:
        
        case 140:
        
        case 141:
        
        case 142:
        
        case 143:
        
        case 144:
        
        case 145:
        
        case 146:
        
        case 147:
        
        case 148:
        
        case 149:
        
        case 150:
        
        case 151:
        
        case 152:
        
        case 153:
        
        case 154:
        
        case 155:
        
        case 156:
        
        case 157:
        
        case 158:
        
        case 159:
        
        case 160:
        
        case 161:
        
        case 162:
        
        case 163:
        
        case 164:
        
        case 165:
        
        case 166:
        
        case 167:
        
        case 168:
        
        case 169:
        
        case 170:
        
        case 171:
        
        case 172:
        
        case 173:
        
        case 174:
        
        case 175:
        
        case 176:
        
        case 177:
        
        case 178:
        
        case 179:
        
        case 180:
        
        case 181:
        
        case 182:
        
        case 183:
        
        case 184:
        
        case 185:
        
        case 186:
        
        case 187:
        
        case 188:
        
        case 189:
        
        case 190:
        
        case 191:
        
        case 192:
        
        case 193:
        
        case 194:
        
        case 195:
        
        case 196:
        
        case 197:
        
        case 198:
        
        case 199:
        
        case 200:
        
        case 201:
        
        case 202:
        
        case 203:
        
        case 204:
        
        case 205:
        
        case 206:
        
        case 207:
        
        case 208:
        
        case 209:
        
        case 210:
        
        case 211:
        
        case 212:
        
        case 213:
        
        case 214:
        
        case 215:
        
        case 216:
        
        case 217:
        
        case 218:
        
        case 219:
        
        case 220:
        
        case 221:
        
        case 222:
        
        case 223:
        
        case 224:
        
        case 225:
        
        case 226:
        
        case 227:
        
        case 228:
        
        case 229:
        
        case 230:
        
        case 231:
        
        case 232:
        
        case 233:
        
        case 234:
        
        case 235:
        
        case 236:
        
        case 237:
        
        case 238:
        
        case 239:
        
        case 240:
        
        case 241:
        
        case 242:
        
        case 243:
        
        case 244:
        
        case 245:
        
        case 246:
        
        case 247:
        
        case 248:
        
        case 249:
        
        case 250:
        
        case 251:
        
        case 252:
        
        case 253:
        
        case 254:
        
        default:
          break;
      } 
      char c = 'à';
      int j = (paramInt2 & 0xFF) - c;
      if (j < 0)
        j += 256; 
      int k = ((paramInt2 & 0xFFFF) >>> 8) - c;
      if (k < 0)
        k += 256; 
      for (byte b = 0; b < arrayOfChar.length; b++) {
        int m = b % 2;
        if (m == 0) {
          arrayOfChar[b] = (char)(arrayOfChar[b] ^ j);
          j = ((j >>> 3 | j << 5) ^ arrayOfChar[b]) & 0xFF;
        } else {
          arrayOfChar[b] = (char)(arrayOfChar[b] ^ k);
          k = ((k >>> 3 | k << 5) ^ arrayOfChar[b]) & 0xFF;
        } 
      } 
      b[i] = (new String(arrayOfChar)).intern();
    } 
    return b[i];
  }
}


/* Location:              C:\Program Files\BurpSuitePro\burpsuite_pro.jar!\burp\Zk88.class
 * Java compiler version: 21 (65.0)
 * JD-Core Version:       1.1.3
 */