package burp;

import java.math.BigInteger;

class Zk8b extends ClassLoader {
  static String ZT;
  
  static Object ZK;
  
  private static final String[] a;
  
  private static final String[] b;
  
  static void ZQ(Object[] paramArrayOfObject, Object paramObject) throws Throwable {}
  
  static boolean ZK(Object[] paramArrayOfObject, Object paramObject) throws Throwable {
    // Byte code:
    //   0: invokestatic ZN : ()Z
    //   3: istore_2
    //   4: getstatic burp/Zg0j.ZV : Ljava/lang/Object;
    //   7: checkcast java/math/BigInteger
    //   10: invokevirtual toByteArray : ()[B
    //   13: astore_3
    //   14: new java/lang/StringBuilder
    //   17: dup
    //   18: invokespecial <init> : ()V
    //   21: astore #5
    //   23: aload #5
    //   25: sipush #19462
    //   28: sipush #19773
    //   31: invokestatic a : (II)Ljava/lang/String;
    //   34: invokevirtual append : (Ljava/lang/String;)Ljava/lang/StringBuilder;
    //   37: pop
    //   38: aload_3
    //   39: astore #6
    //   41: aload #6
    //   43: arraylength
    //   44: istore #7
    //   46: iconst_0
    //   47: istore #8
    //   49: iload #8
    //   51: iload #7
    //   53: if_icmpge -> 79
    //   56: aload #6
    //   58: iload #8
    //   60: baload
    //   61: istore #9
    //   63: aload #5
    //   65: iload #9
    //   67: i2c
    //   68: invokevirtual append : (C)Ljava/lang/StringBuilder;
    //   71: pop
    //   72: iinc #8, 1
    //   75: iload_2
    //   76: ifne -> 49
    //   79: aload #5
    //   81: sipush #19458
    //   84: sipush #-15575
    //   87: invokestatic a : (II)Ljava/lang/String;
    //   90: ldc ''
    //   92: invokestatic getProperty : (Ljava/lang/String;Ljava/lang/String;)Ljava/lang/String;
    //   95: invokevirtual toLowerCase : ()Ljava/lang/String;
    //   98: invokevirtual append : (Ljava/lang/String;)Ljava/lang/StringBuilder;
    //   101: pop
    //   102: aload #5
    //   104: sipush #19460
    //   107: sipush #-23250
    //   110: invokestatic a : (II)Ljava/lang/String;
    //   113: ldc ''
    //   115: invokestatic getProperty : (Ljava/lang/String;Ljava/lang/String;)Ljava/lang/String;
    //   118: invokevirtual toLowerCase : ()Ljava/lang/String;
    //   121: invokevirtual append : (Ljava/lang/String;)Ljava/lang/StringBuilder;
    //   124: pop
    //   125: aload #5
    //   127: invokevirtual toString : ()Ljava/lang/String;
    //   130: invokevirtual getBytes : ()[B
    //   133: astore #4
    //   135: aload #4
    //   137: astore_3
    //   138: aload_3
    //   139: arraylength
    //   140: bipush #8
    //   142: iadd
    //   143: bipush #6
    //   145: ishr
    //   146: iconst_1
    //   147: iadd
    //   148: bipush #16
    //   150: imul
    //   151: newarray int
    //   153: astore #5
    //   155: iconst_0
    //   156: istore #6
    //   158: iload #6
    //   160: aload_3
    //   161: arraylength
    //   162: if_icmpge -> 205
    //   165: aload_3
    //   166: iload #6
    //   168: baload
    //   169: sipush #255
    //   172: iand
    //   173: istore #7
    //   175: aload #5
    //   177: iload #6
    //   179: iconst_2
    //   180: ishr
    //   181: dup2
    //   182: iaload
    //   183: iload #7
    //   185: bipush #24
    //   187: iload #6
    //   189: iconst_4
    //   190: irem
    //   191: bipush #8
    //   193: imul
    //   194: isub
    //   195: ishl
    //   196: ior
    //   197: iastore
    //   198: iinc #6, 1
    //   201: iload_2
    //   202: ifne -> 158
    //   205: aload #5
    //   207: iload #6
    //   209: iconst_2
    //   210: ishr
    //   211: dup2
    //   212: iaload
    //   213: sipush #128
    //   216: bipush #24
    //   218: iload #6
    //   220: iconst_4
    //   221: irem
    //   222: bipush #8
    //   224: imul
    //   225: isub
    //   226: ishl
    //   227: ior
    //   228: iastore
    //   229: aload #5
    //   231: aload #5
    //   233: arraylength
    //   234: iconst_1
    //   235: isub
    //   236: aload_3
    //   237: arraylength
    //   238: bipush #8
    //   240: imul
    //   241: iastore
    //   242: bipush #80
    //   244: newarray int
    //   246: astore #7
    //   248: ldc 1732584193
    //   250: istore #8
    //   252: ldc -271733879
    //   254: istore #9
    //   256: ldc -1732584194
    //   258: istore #10
    //   260: ldc 271733878
    //   262: istore #11
    //   264: ldc -1009589776
    //   266: istore #12
    //   268: iconst_0
    //   269: istore #6
    //   271: iload #6
    //   273: aload #5
    //   275: arraylength
    //   276: if_icmpge -> 598
    //   279: iload #8
    //   281: istore #13
    //   283: iload #9
    //   285: istore #14
    //   287: iload #10
    //   289: istore #15
    //   291: iload #11
    //   293: istore #16
    //   295: iload #12
    //   297: istore #17
    //   299: iconst_0
    //   300: istore #18
    //   302: iload #18
    //   304: bipush #80
    //   306: if_icmpge -> 556
    //   309: iload #18
    //   311: bipush #16
    //   313: if_icmpge -> 340
    //   316: aload #7
    //   318: iload #18
    //   320: aload #5
    //   322: iload #6
    //   324: iload #18
    //   326: iadd
    //   327: iaload
    //   328: iastore
    //   329: iload_2
    //   330: ifne -> 395
    //   333: goto -> 340
    //   336: invokestatic a : (Ljava/lang/Throwable;)Ljava/lang/Throwable;
    //   339: athrow
    //   340: aload #7
    //   342: iload #18
    //   344: iconst_3
    //   345: isub
    //   346: iaload
    //   347: aload #7
    //   349: iload #18
    //   351: bipush #8
    //   353: isub
    //   354: iaload
    //   355: ixor
    //   356: aload #7
    //   358: iload #18
    //   360: bipush #14
    //   362: isub
    //   363: iaload
    //   364: ixor
    //   365: aload #7
    //   367: iload #18
    //   369: bipush #16
    //   371: isub
    //   372: iaload
    //   373: ixor
    //   374: istore #19
    //   376: iload #19
    //   378: iconst_1
    //   379: ishl
    //   380: iload #19
    //   382: bipush #31
    //   384: iushr
    //   385: ior
    //   386: istore #20
    //   388: aload #7
    //   390: iload #18
    //   392: iload #20
    //   394: iastore
    //   395: iload #8
    //   397: iconst_5
    //   398: ishl
    //   399: iload #8
    //   401: bipush #27
    //   403: iushr
    //   404: ior
    //   405: istore #19
    //   407: iload #19
    //   409: iload #12
    //   411: iadd
    //   412: aload #7
    //   414: iload #18
    //   416: iaload
    //   417: iadd
    //   418: iload #18
    //   420: bipush #20
    //   422: if_icmpge -> 448
    //   425: ldc 1518500249
    //   427: iload #9
    //   429: iload #10
    //   431: iand
    //   432: iload #9
    //   434: iconst_m1
    //   435: ixor
    //   436: iload #11
    //   438: iand
    //   439: ior
    //   440: iadd
    //   441: goto -> 518
    //   444: invokestatic a : (Ljava/lang/Throwable;)Ljava/lang/Throwable;
    //   447: athrow
    //   448: iload #18
    //   450: bipush #40
    //   452: if_icmpge -> 473
    //   455: ldc 1859775393
    //   457: iload #9
    //   459: iload #10
    //   461: ixor
    //   462: iload #11
    //   464: ixor
    //   465: iadd
    //   466: goto -> 518
    //   469: invokestatic a : (Ljava/lang/Throwable;)Ljava/lang/Throwable;
    //   472: athrow
    //   473: iload #18
    //   475: bipush #60
    //   477: if_icmpge -> 507
    //   480: ldc -1894007588
    //   482: iload #9
    //   484: iload #10
    //   486: iand
    //   487: iload #9
    //   489: iload #11
    //   491: iand
    //   492: ior
    //   493: iload #10
    //   495: iload #11
    //   497: iand
    //   498: ior
    //   499: iadd
    //   500: goto -> 518
    //   503: invokestatic a : (Ljava/lang/Throwable;)Ljava/lang/Throwable;
    //   506: athrow
    //   507: ldc -899497514
    //   509: iload #9
    //   511: iload #10
    //   513: ixor
    //   514: iload #11
    //   516: ixor
    //   517: iadd
    //   518: iadd
    //   519: istore #20
    //   521: iload #11
    //   523: istore #12
    //   525: iload #10
    //   527: istore #11
    //   529: iload #9
    //   531: bipush #30
    //   533: ishl
    //   534: iload #9
    //   536: iconst_2
    //   537: iushr
    //   538: ior
    //   539: istore #10
    //   541: iload #8
    //   543: istore #9
    //   545: iload #20
    //   547: istore #8
    //   549: iinc #18, 1
    //   552: iload_2
    //   553: ifne -> 302
    //   556: iload #8
    //   558: iload #13
    //   560: iadd
    //   561: istore #8
    //   563: iload #9
    //   565: iload #14
    //   567: iadd
    //   568: istore #9
    //   570: iload #10
    //   572: iload #15
    //   574: iadd
    //   575: istore #10
    //   577: iload #11
    //   579: iload #16
    //   581: iadd
    //   582: istore #11
    //   584: iload #12
    //   586: iload #17
    //   588: iadd
    //   589: istore #12
    //   591: iinc #6, 16
    //   594: iload_2
    //   595: ifne -> 271
    //   598: iconst_5
    //   599: newarray int
    //   601: dup
    //   602: iconst_0
    //   603: iload #8
    //   605: iastore
    //   606: dup
    //   607: iconst_1
    //   608: iload #9
    //   610: iastore
    //   611: dup
    //   612: iconst_2
    //   613: iload #10
    //   615: iastore
    //   616: dup
    //   617: iconst_3
    //   618: iload #11
    //   620: iastore
    //   621: dup
    //   622: iconst_4
    //   623: iload #12
    //   625: iastore
    //   626: astore #13
    //   628: bipush #20
    //   630: newarray byte
    //   632: astore #14
    //   634: iconst_0
    //   635: istore #15
    //   637: iload #15
    //   639: bipush #20
    //   641: if_icmpge -> 682
    //   644: aload #13
    //   646: iload #15
    //   648: iconst_4
    //   649: idiv
    //   650: iaload
    //   651: istore #16
    //   653: iconst_3
    //   654: iload #15
    //   656: iconst_4
    //   657: irem
    //   658: isub
    //   659: bipush #8
    //   661: imul
    //   662: istore #17
    //   664: aload #14
    //   666: iload #15
    //   668: iload #16
    //   670: iload #17
    //   672: iushr
    //   673: i2b
    //   674: bastore
    //   675: iinc #15, 1
    //   678: iload_2
    //   679: ifne -> 637
    //   682: aload #14
    //   684: astore #4
    //   686: new java/lang/StringBuilder
    //   689: dup
    //   690: invokespecial <init> : ()V
    //   693: astore_3
    //   694: iconst_0
    //   695: istore #4
    //   697: iload #4
    //   699: bipush #32
    //   701: if_icmpge -> 2035
    //   704: iload #4
    //   706: tableswitch default -> 2028, 0 -> 848, 1 -> 885, 2 -> 922, 3 -> 959, 4 -> 996, 5 -> 1033, 6 -> 1070, 7 -> 1107, 8 -> 1144, 9 -> 1181, 10 -> 1218, 11 -> 1255, 12 -> 1292, 13 -> 1329, 14 -> 1366, 15 -> 1403, 16 -> 1440, 17 -> 1477, 18 -> 1514, 19 -> 1551, 20 -> 1588, 21 -> 1625, 22 -> 1662, 23 -> 1699, 24 -> 1736, 25 -> 1773, 26 -> 1810, 27 -> 1847, 28 -> 1884, 29 -> 1921, 30 -> 1958, 31 -> 1995
    //   848: aload_3
    //   849: getstatic burp/Zter.ZE : Ljava/lang/String;
    //   852: getstatic burp/Zr3q.Zn : Ljava/lang/Object;
    //   855: checkcast java/math/BigInteger
    //   858: invokevirtual intValue : ()I
    //   861: bipush #32
    //   863: irem
    //   864: invokestatic abs : (I)I
    //   867: invokevirtual charAt : (I)C
    //   870: invokevirtual append : (C)Ljava/lang/StringBuilder;
    //   873: pop
    //   874: iload_2
    //   875: ifne -> 2028
    //   878: goto -> 885
    //   881: invokestatic a : (Ljava/lang/Throwable;)Ljava/lang/Throwable;
    //   884: athrow
    //   885: aload_3
    //   886: getstatic burp/Zehi.Zi : Ljava/lang/String;
    //   889: getstatic burp/Zd1.ZV : Ljava/lang/Object;
    //   892: checkcast java/math/BigInteger
    //   895: invokevirtual intValue : ()I
    //   898: bipush #32
    //   900: irem
    //   901: invokestatic abs : (I)I
    //   904: invokevirtual charAt : (I)C
    //   907: invokevirtual append : (C)Ljava/lang/StringBuilder;
    //   910: pop
    //   911: iload_2
    //   912: ifne -> 2028
    //   915: goto -> 922
    //   918: invokestatic a : (Ljava/lang/Throwable;)Ljava/lang/Throwable;
    //   921: athrow
    //   922: aload_3
    //   923: getstatic burp/Zd1.ZN : Ljava/lang/String;
    //   926: getstatic burp/Zg0j.ZV : Ljava/lang/Object;
    //   929: checkcast java/math/BigInteger
    //   932: invokevirtual intValue : ()I
    //   935: bipush #32
    //   937: irem
    //   938: invokestatic abs : (I)I
    //   941: invokevirtual charAt : (I)C
    //   944: invokevirtual append : (C)Ljava/lang/StringBuilder;
    //   947: pop
    //   948: iload_2
    //   949: ifne -> 2028
    //   952: goto -> 959
    //   955: invokestatic a : (Ljava/lang/Throwable;)Ljava/lang/Throwable;
    //   958: athrow
    //   959: aload_3
    //   960: getstatic burp/Zxso.ZH : Ljava/lang/String;
    //   963: getstatic burp/Zsde.Zx : Ljava/lang/Object;
    //   966: checkcast java/math/BigInteger
    //   969: invokevirtual intValue : ()I
    //   972: bipush #32
    //   974: irem
    //   975: invokestatic abs : (I)I
    //   978: invokevirtual charAt : (I)C
    //   981: invokevirtual append : (C)Ljava/lang/StringBuilder;
    //   984: pop
    //   985: iload_2
    //   986: ifne -> 2028
    //   989: goto -> 996
    //   992: invokestatic a : (Ljava/lang/Throwable;)Ljava/lang/Throwable;
    //   995: athrow
    //   996: aload_3
    //   997: getstatic burp/Zm__.Zf : Ljava/lang/String;
    //   1000: getstatic burp/Zb3z.ZR : Ljava/lang/Object;
    //   1003: checkcast java/math/BigInteger
    //   1006: invokevirtual intValue : ()I
    //   1009: bipush #32
    //   1011: irem
    //   1012: invokestatic abs : (I)I
    //   1015: invokevirtual charAt : (I)C
    //   1018: invokevirtual append : (C)Ljava/lang/StringBuilder;
    //   1021: pop
    //   1022: iload_2
    //   1023: ifne -> 2028
    //   1026: goto -> 1033
    //   1029: invokestatic a : (Ljava/lang/Throwable;)Ljava/lang/Throwable;
    //   1032: athrow
    //   1033: aload_3
    //   1034: getstatic burp/Zzsq.Zc : Ljava/lang/String;
    //   1037: getstatic burp/Zsm3.ZC : Ljava/lang/Object;
    //   1040: checkcast java/math/BigInteger
    //   1043: invokevirtual intValue : ()I
    //   1046: bipush #32
    //   1048: irem
    //   1049: invokestatic abs : (I)I
    //   1052: invokevirtual charAt : (I)C
    //   1055: invokevirtual append : (C)Ljava/lang/StringBuilder;
    //   1058: pop
    //   1059: iload_2
    //   1060: ifne -> 2028
    //   1063: goto -> 1070
    //   1066: invokestatic a : (Ljava/lang/Throwable;)Ljava/lang/Throwable;
    //   1069: athrow
    //   1070: aload_3
    //   1071: getstatic burp/Ze3d.ZL : Ljava/lang/String;
    //   1074: getstatic burp/Zg7z.ZV : Ljava/lang/Object;
    //   1077: checkcast java/math/BigInteger
    //   1080: invokevirtual intValue : ()I
    //   1083: bipush #32
    //   1085: irem
    //   1086: invokestatic abs : (I)I
    //   1089: invokevirtual charAt : (I)C
    //   1092: invokevirtual append : (C)Ljava/lang/StringBuilder;
    //   1095: pop
    //   1096: iload_2
    //   1097: ifne -> 2028
    //   1100: goto -> 1107
    //   1103: invokestatic a : (Ljava/lang/Throwable;)Ljava/lang/Throwable;
    //   1106: athrow
    //   1107: aload_3
    //   1108: getstatic burp/Zxzd.ZM : Ljava/lang/String;
    //   1111: getstatic burp/Zsxm.Zv : Ljava/lang/Object;
    //   1114: checkcast java/math/BigInteger
    //   1117: invokevirtual intValue : ()I
    //   1120: bipush #32
    //   1122: irem
    //   1123: invokestatic abs : (I)I
    //   1126: invokevirtual charAt : (I)C
    //   1129: invokevirtual append : (C)Ljava/lang/StringBuilder;
    //   1132: pop
    //   1133: iload_2
    //   1134: ifne -> 2028
    //   1137: goto -> 1144
    //   1140: invokestatic a : (Ljava/lang/Throwable;)Ljava/lang/Throwable;
    //   1143: athrow
    //   1144: aload_3
    //   1145: getstatic burp/Zg7p.ZA : Ljava/lang/String;
    //   1148: getstatic burp/Zxfu.ZA : Ljava/lang/Object;
    //   1151: checkcast java/math/BigInteger
    //   1154: invokevirtual intValue : ()I
    //   1157: bipush #32
    //   1159: irem
    //   1160: invokestatic abs : (I)I
    //   1163: invokevirtual charAt : (I)C
    //   1166: invokevirtual append : (C)Ljava/lang/StringBuilder;
    //   1169: pop
    //   1170: iload_2
    //   1171: ifne -> 2028
    //   1174: goto -> 1181
    //   1177: invokestatic a : (Ljava/lang/Throwable;)Ljava/lang/Throwable;
    //   1180: athrow
    //   1181: aload_3
    //   1182: getstatic burp/Zt4g.Zj : Ljava/lang/String;
    //   1185: getstatic burp/Zes_.ZJ : Ljava/lang/Object;
    //   1188: checkcast java/math/BigInteger
    //   1191: invokevirtual intValue : ()I
    //   1194: bipush #32
    //   1196: irem
    //   1197: invokestatic abs : (I)I
    //   1200: invokevirtual charAt : (I)C
    //   1203: invokevirtual append : (C)Ljava/lang/StringBuilder;
    //   1206: pop
    //   1207: iload_2
    //   1208: ifne -> 2028
    //   1211: goto -> 1218
    //   1214: invokestatic a : (Ljava/lang/Throwable;)Ljava/lang/Throwable;
    //   1217: athrow
    //   1218: aload_3
    //   1219: getstatic burp/Zsby.Zx : Ljava/lang/String;
    //   1222: getstatic burp/Zl_k.ZH : Ljava/lang/Object;
    //   1225: checkcast java/math/BigInteger
    //   1228: invokevirtual intValue : ()I
    //   1231: bipush #32
    //   1233: irem
    //   1234: invokestatic abs : (I)I
    //   1237: invokevirtual charAt : (I)C
    //   1240: invokevirtual append : (C)Ljava/lang/StringBuilder;
    //   1243: pop
    //   1244: iload_2
    //   1245: ifne -> 2028
    //   1248: goto -> 1255
    //   1251: invokestatic a : (Ljava/lang/Throwable;)Ljava/lang/Throwable;
    //   1254: athrow
    //   1255: aload_3
    //   1256: getstatic burp/Zlhm.Zx : Ljava/lang/String;
    //   1259: getstatic burp/Zer.Zk : Ljava/lang/Object;
    //   1262: checkcast java/math/BigInteger
    //   1265: invokevirtual intValue : ()I
    //   1268: bipush #32
    //   1270: irem
    //   1271: invokestatic abs : (I)I
    //   1274: invokevirtual charAt : (I)C
    //   1277: invokevirtual append : (C)Ljava/lang/StringBuilder;
    //   1280: pop
    //   1281: iload_2
    //   1282: ifne -> 2028
    //   1285: goto -> 1292
    //   1288: invokestatic a : (Ljava/lang/Throwable;)Ljava/lang/Throwable;
    //   1291: athrow
    //   1292: aload_3
    //   1293: getstatic burp/Zg0j.Ze : Ljava/lang/String;
    //   1296: getstatic burp/Zsm3.ZC : Ljava/lang/Object;
    //   1299: checkcast java/math/BigInteger
    //   1302: invokevirtual intValue : ()I
    //   1305: bipush #32
    //   1307: irem
    //   1308: invokestatic abs : (I)I
    //   1311: invokevirtual charAt : (I)C
    //   1314: invokevirtual append : (C)Ljava/lang/StringBuilder;
    //   1317: pop
    //   1318: iload_2
    //   1319: ifne -> 2028
    //   1322: goto -> 1329
    //   1325: invokestatic a : (Ljava/lang/Throwable;)Ljava/lang/Throwable;
    //   1328: athrow
    //   1329: aload_3
    //   1330: getstatic burp/Zsby.Zx : Ljava/lang/String;
    //   1333: getstatic burp/Zgw0.ZM : Ljava/lang/Object;
    //   1336: checkcast java/math/BigInteger
    //   1339: invokevirtual intValue : ()I
    //   1342: bipush #32
    //   1344: irem
    //   1345: invokestatic abs : (I)I
    //   1348: invokevirtual charAt : (I)C
    //   1351: invokevirtual append : (C)Ljava/lang/StringBuilder;
    //   1354: pop
    //   1355: iload_2
    //   1356: ifne -> 2028
    //   1359: goto -> 1366
    //   1362: invokestatic a : (Ljava/lang/Throwable;)Ljava/lang/Throwable;
    //   1365: athrow
    //   1366: aload_3
    //   1367: getstatic burp/Zz1k.ZC : Ljava/lang/String;
    //   1370: getstatic burp/Zxzj.ZO : Ljava/lang/Object;
    //   1373: checkcast java/math/BigInteger
    //   1376: invokevirtual intValue : ()I
    //   1379: bipush #32
    //   1381: irem
    //   1382: invokestatic abs : (I)I
    //   1385: invokevirtual charAt : (I)C
    //   1388: invokevirtual append : (C)Ljava/lang/StringBuilder;
    //   1391: pop
    //   1392: iload_2
    //   1393: ifne -> 2028
    //   1396: goto -> 1403
    //   1399: invokestatic a : (Ljava/lang/Throwable;)Ljava/lang/Throwable;
    //   1402: athrow
    //   1403: aload_3
    //   1404: getstatic burp/Zm0s.Zm : Ljava/lang/String;
    //   1407: getstatic burp/Zsm3.ZC : Ljava/lang/Object;
    //   1410: checkcast java/math/BigInteger
    //   1413: invokevirtual intValue : ()I
    //   1416: bipush #32
    //   1418: irem
    //   1419: invokestatic abs : (I)I
    //   1422: invokevirtual charAt : (I)C
    //   1425: invokevirtual append : (C)Ljava/lang/StringBuilder;
    //   1428: pop
    //   1429: iload_2
    //   1430: ifne -> 2028
    //   1433: goto -> 1440
    //   1436: invokestatic a : (Ljava/lang/Throwable;)Ljava/lang/Throwable;
    //   1439: athrow
    //   1440: aload_3
    //   1441: getstatic burp/Zzk9.Zb : Ljava/lang/String;
    //   1444: getstatic burp/Zr8h.ZH : Ljava/lang/Object;
    //   1447: checkcast java/math/BigInteger
    //   1450: invokevirtual intValue : ()I
    //   1453: bipush #32
    //   1455: irem
    //   1456: invokestatic abs : (I)I
    //   1459: invokevirtual charAt : (I)C
    //   1462: invokevirtual append : (C)Ljava/lang/StringBuilder;
    //   1465: pop
    //   1466: iload_2
    //   1467: ifne -> 2028
    //   1470: goto -> 1477
    //   1473: invokestatic a : (Ljava/lang/Throwable;)Ljava/lang/Throwable;
    //   1476: athrow
    //   1477: aload_3
    //   1478: getstatic burp/Zb3z.Zi : Ljava/lang/String;
    //   1481: getstatic burp/Zkfz.Zr : Ljava/lang/Object;
    //   1484: checkcast java/math/BigInteger
    //   1487: invokevirtual intValue : ()I
    //   1490: bipush #32
    //   1492: irem
    //   1493: invokestatic abs : (I)I
    //   1496: invokevirtual charAt : (I)C
    //   1499: invokevirtual append : (C)Ljava/lang/StringBuilder;
    //   1502: pop
    //   1503: iload_2
    //   1504: ifne -> 2028
    //   1507: goto -> 1514
    //   1510: invokestatic a : (Ljava/lang/Throwable;)Ljava/lang/Throwable;
    //   1513: athrow
    //   1514: aload_3
    //   1515: getstatic burp/Ze3j.ZI : Ljava/lang/String;
    //   1518: getstatic burp/Zllw.ZW : Ljava/lang/Object;
    //   1521: checkcast java/math/BigInteger
    //   1524: invokevirtual intValue : ()I
    //   1527: bipush #32
    //   1529: irem
    //   1530: invokestatic abs : (I)I
    //   1533: invokevirtual charAt : (I)C
    //   1536: invokevirtual append : (C)Ljava/lang/StringBuilder;
    //   1539: pop
    //   1540: iload_2
    //   1541: ifne -> 2028
    //   1544: goto -> 1551
    //   1547: invokestatic a : (Ljava/lang/Throwable;)Ljava/lang/Throwable;
    //   1550: athrow
    //   1551: aload_3
    //   1552: getstatic burp/Zkig.ZE : Ljava/lang/String;
    //   1555: getstatic burp/Zshq.ZK : Ljava/lang/Object;
    //   1558: checkcast java/math/BigInteger
    //   1561: invokevirtual intValue : ()I
    //   1564: bipush #32
    //   1566: irem
    //   1567: invokestatic abs : (I)I
    //   1570: invokevirtual charAt : (I)C
    //   1573: invokevirtual append : (C)Ljava/lang/StringBuilder;
    //   1576: pop
    //   1577: iload_2
    //   1578: ifne -> 2028
    //   1581: goto -> 1588
    //   1584: invokestatic a : (Ljava/lang/Throwable;)Ljava/lang/Throwable;
    //   1587: athrow
    //   1588: aload_3
    //   1589: getstatic burp/Zb8v.Zo : Ljava/lang/String;
    //   1592: getstatic burp/Zl_u.ZR : Ljava/lang/Object;
    //   1595: checkcast java/math/BigInteger
    //   1598: invokevirtual intValue : ()I
    //   1601: bipush #32
    //   1603: irem
    //   1604: invokestatic abs : (I)I
    //   1607: invokevirtual charAt : (I)C
    //   1610: invokevirtual append : (C)Ljava/lang/StringBuilder;
    //   1613: pop
    //   1614: iload_2
    //   1615: ifne -> 2028
    //   1618: goto -> 1625
    //   1621: invokestatic a : (Ljava/lang/Throwable;)Ljava/lang/Throwable;
    //   1624: athrow
    //   1625: aload_3
    //   1626: getstatic burp/Zd1.ZN : Ljava/lang/String;
    //   1629: getstatic burp/Zxzd.ZD : Ljava/lang/Object;
    //   1632: checkcast java/math/BigInteger
    //   1635: invokevirtual intValue : ()I
    //   1638: bipush #32
    //   1640: irem
    //   1641: invokestatic abs : (I)I
    //   1644: invokevirtual charAt : (I)C
    //   1647: invokevirtual append : (C)Ljava/lang/StringBuilder;
    //   1650: pop
    //   1651: iload_2
    //   1652: ifne -> 2028
    //   1655: goto -> 1662
    //   1658: invokestatic a : (Ljava/lang/Throwable;)Ljava/lang/Throwable;
    //   1661: athrow
    //   1662: aload_3
    //   1663: getstatic burp/Zzap.ZA : Ljava/lang/String;
    //   1666: getstatic burp/Zt4g.Zv : Ljava/lang/Object;
    //   1669: checkcast java/math/BigInteger
    //   1672: invokevirtual intValue : ()I
    //   1675: bipush #32
    //   1677: irem
    //   1678: invokestatic abs : (I)I
    //   1681: invokevirtual charAt : (I)C
    //   1684: invokevirtual append : (C)Ljava/lang/StringBuilder;
    //   1687: pop
    //   1688: iload_2
    //   1689: ifne -> 2028
    //   1692: goto -> 1699
    //   1695: invokestatic a : (Ljava/lang/Throwable;)Ljava/lang/Throwable;
    //   1698: athrow
    //   1699: aload_3
    //   1700: getstatic burp/Zr8h.Zk : Ljava/lang/String;
    //   1703: getstatic burp/Zt3l.Zq : Ljava/lang/Object;
    //   1706: checkcast java/math/BigInteger
    //   1709: invokevirtual intValue : ()I
    //   1712: bipush #32
    //   1714: irem
    //   1715: invokestatic abs : (I)I
    //   1718: invokevirtual charAt : (I)C
    //   1721: invokevirtual append : (C)Ljava/lang/StringBuilder;
    //   1724: pop
    //   1725: iload_2
    //   1726: ifne -> 2028
    //   1729: goto -> 1736
    //   1732: invokestatic a : (Ljava/lang/Throwable;)Ljava/lang/Throwable;
    //   1735: athrow
    //   1736: aload_3
    //   1737: getstatic burp/Zxfu.Zo : Ljava/lang/String;
    //   1740: getstatic burp/Ztuj.Ze : Ljava/lang/Object;
    //   1743: checkcast java/math/BigInteger
    //   1746: invokevirtual intValue : ()I
    //   1749: bipush #32
    //   1751: irem
    //   1752: invokestatic abs : (I)I
    //   1755: invokevirtual charAt : (I)C
    //   1758: invokevirtual append : (C)Ljava/lang/StringBuilder;
    //   1761: pop
    //   1762: iload_2
    //   1763: ifne -> 2028
    //   1766: goto -> 1773
    //   1769: invokestatic a : (Ljava/lang/Throwable;)Ljava/lang/Throwable;
    //   1772: athrow
    //   1773: aload_3
    //   1774: getstatic burp/Zzai.Zy : Ljava/lang/String;
    //   1777: getstatic burp/Zl_u.ZR : Ljava/lang/Object;
    //   1780: checkcast java/math/BigInteger
    //   1783: invokevirtual intValue : ()I
    //   1786: bipush #32
    //   1788: irem
    //   1789: invokestatic abs : (I)I
    //   1792: invokevirtual charAt : (I)C
    //   1795: invokevirtual append : (C)Ljava/lang/StringBuilder;
    //   1798: pop
    //   1799: iload_2
    //   1800: ifne -> 2028
    //   1803: goto -> 1810
    //   1806: invokestatic a : (Ljava/lang/Throwable;)Ljava/lang/Throwable;
    //   1809: athrow
    //   1810: aload_3
    //   1811: getstatic burp/Zter.ZE : Ljava/lang/String;
    //   1814: getstatic burp/Ztbf.Zv : Ljava/lang/Object;
    //   1817: checkcast java/math/BigInteger
    //   1820: invokevirtual intValue : ()I
    //   1823: bipush #32
    //   1825: irem
    //   1826: invokestatic abs : (I)I
    //   1829: invokevirtual charAt : (I)C
    //   1832: invokevirtual append : (C)Ljava/lang/StringBuilder;
    //   1835: pop
    //   1836: iload_2
    //   1837: ifne -> 2028
    //   1840: goto -> 1847
    //   1843: invokestatic a : (Ljava/lang/Throwable;)Ljava/lang/Throwable;
    //   1846: athrow
    //   1847: aload_3
    //   1848: getstatic burp/Zx4w.Zo : Ljava/lang/String;
    //   1851: getstatic burp/Zr0g.Zj : Ljava/lang/Object;
    //   1854: checkcast java/math/BigInteger
    //   1857: invokevirtual intValue : ()I
    //   1860: bipush #32
    //   1862: irem
    //   1863: invokestatic abs : (I)I
    //   1866: invokevirtual charAt : (I)C
    //   1869: invokevirtual append : (C)Ljava/lang/StringBuilder;
    //   1872: pop
    //   1873: iload_2
    //   1874: ifne -> 2028
    //   1877: goto -> 1884
    //   1880: invokestatic a : (Ljava/lang/Throwable;)Ljava/lang/Throwable;
    //   1883: athrow
    //   1884: aload_3
    //   1885: getstatic burp/Zzsq.Zc : Ljava/lang/String;
    //   1888: getstatic burp/Zxso.ZF : Ljava/lang/Object;
    //   1891: checkcast java/math/BigInteger
    //   1894: invokevirtual intValue : ()I
    //   1897: bipush #32
    //   1899: irem
    //   1900: invokestatic abs : (I)I
    //   1903: invokevirtual charAt : (I)C
    //   1906: invokevirtual append : (C)Ljava/lang/StringBuilder;
    //   1909: pop
    //   1910: iload_2
    //   1911: ifne -> 2028
    //   1914: goto -> 1921
    //   1917: invokestatic a : (Ljava/lang/Throwable;)Ljava/lang/Throwable;
    //   1920: athrow
    //   1921: aload_3
    //   1922: getstatic burp/Zedz.Zh : Ljava/lang/String;
    //   1925: getstatic burp/Zk9s.ZY : Ljava/lang/Object;
    //   1928: checkcast java/math/BigInteger
    //   1931: invokevirtual intValue : ()I
    //   1934: bipush #32
    //   1936: irem
    //   1937: invokestatic abs : (I)I
    //   1940: invokevirtual charAt : (I)C
    //   1943: invokevirtual append : (C)Ljava/lang/StringBuilder;
    //   1946: pop
    //   1947: iload_2
    //   1948: ifne -> 2028
    //   1951: goto -> 1958
    //   1954: invokestatic a : (Ljava/lang/Throwable;)Ljava/lang/Throwable;
    //   1957: athrow
    //   1958: aload_3
    //   1959: getstatic burp/Zer.Zp : Ljava/lang/String;
    //   1962: getstatic burp/Zl88.ZK : Ljava/lang/Object;
    //   1965: checkcast java/math/BigInteger
    //   1968: invokevirtual intValue : ()I
    //   1971: bipush #32
    //   1973: irem
    //   1974: invokestatic abs : (I)I
    //   1977: invokevirtual charAt : (I)C
    //   1980: invokevirtual append : (C)Ljava/lang/StringBuilder;
    //   1983: pop
    //   1984: iload_2
    //   1985: ifne -> 2028
    //   1988: goto -> 1995
    //   1991: invokestatic a : (Ljava/lang/Throwable;)Ljava/lang/Throwable;
    //   1994: athrow
    //   1995: aload_3
    //   1996: getstatic burp/Zbo7.ZZ : Ljava/lang/String;
    //   1999: getstatic burp/Zrbp.Z_ : Ljava/lang/Object;
    //   2002: checkcast java/math/BigInteger
    //   2005: invokevirtual intValue : ()I
    //   2008: bipush #32
    //   2010: irem
    //   2011: invokestatic abs : (I)I
    //   2014: invokevirtual charAt : (I)C
    //   2017: invokevirtual append : (C)Ljava/lang/StringBuilder;
    //   2020: pop
    //   2021: goto -> 2028
    //   2024: invokestatic a : (Ljava/lang/Throwable;)Ljava/lang/Throwable;
    //   2027: athrow
    //   2028: iinc #4, 1
    //   2031: iload_2
    //   2032: ifne -> 697
    //   2035: aload_3
    //   2036: invokevirtual toString : ()Ljava/lang/String;
    //   2039: putstatic burp/Zxyp.Z_ : Ljava/lang/String;
    //   2042: sipush #19469
    //   2045: sipush #-8212
    //   2048: invokestatic a : (II)Ljava/lang/String;
    //   2051: iconst_1
    //   2052: ldc burp/Zgq_
    //   2054: invokevirtual getClassLoader : ()Ljava/lang/ClassLoader;
    //   2057: invokestatic forName : (Ljava/lang/String;ZLjava/lang/ClassLoader;)Ljava/lang/Class;
    //   2060: invokevirtual getDeclaredFields : ()[Ljava/lang/reflect/Field;
    //   2063: astore #4
    //   2065: aload #4
    //   2067: arraylength
    //   2068: istore #5
    //   2070: iconst_0
    //   2071: istore #6
    //   2073: iload #6
    //   2075: iload #5
    //   2077: if_icmpge -> 2215
    //   2080: aload #4
    //   2082: iload #6
    //   2084: aaload
    //   2085: astore #7
    //   2087: aload #7
    //   2089: invokevirtual getModifiers : ()I
    //   2092: invokestatic isStatic : (I)Z
    //   2095: ifne -> 2105
    //   2098: goto -> 2208
    //   2101: invokestatic a : (Ljava/lang/Throwable;)Ljava/lang/Throwable;
    //   2104: athrow
    //   2105: aload #7
    //   2107: invokevirtual getType : ()Ljava/lang/Class;
    //   2110: astore #8
    //   2112: aload #8
    //   2114: ifnull -> 2195
    //   2117: aload #8
    //   2119: invokevirtual isPrimitive : ()Z
    //   2122: ifne -> 2195
    //   2125: goto -> 2132
    //   2128: invokestatic a : (Ljava/lang/Throwable;)Ljava/lang/Throwable;
    //   2131: athrow
    //   2132: aload #8
    //   2134: invokevirtual getPackage : ()Ljava/lang/Package;
    //   2137: ifnull -> 2195
    //   2140: goto -> 2147
    //   2143: invokestatic a : (Ljava/lang/Throwable;)Ljava/lang/Throwable;
    //   2146: athrow
    //   2147: aload #8
    //   2149: invokevirtual getPackage : ()Ljava/lang/Package;
    //   2152: invokevirtual getName : ()Ljava/lang/String;
    //   2155: ifnull -> 2195
    //   2158: goto -> 2165
    //   2161: invokestatic a : (Ljava/lang/Throwable;)Ljava/lang/Throwable;
    //   2164: athrow
    //   2165: aload #8
    //   2167: invokevirtual getPackage : ()Ljava/lang/Package;
    //   2170: invokevirtual getName : ()Ljava/lang/String;
    //   2173: sipush #19467
    //   2176: sipush #6171
    //   2179: invokestatic a : (II)Ljava/lang/String;
    //   2182: invokevirtual startsWith : (Ljava/lang/String;)Z
    //   2185: ifne -> 2195
    //   2188: goto -> 2195
    //   2191: invokestatic a : (Ljava/lang/Throwable;)Ljava/lang/Throwable;
    //   2194: athrow
    //   2195: aload #7
    //   2197: iconst_1
    //   2198: invokevirtual setAccessible : (Z)V
    //   2201: aload #7
    //   2203: aconst_null
    //   2204: invokevirtual get : (Ljava/lang/Object;)Ljava/lang/Object;
    //   2207: pop
    //   2208: iinc #6, 1
    //   2211: iload_2
    //   2212: ifne -> 2073
    //   2215: sipush #19470
    //   2218: sipush #-16925
    //   2221: invokestatic a : (II)Ljava/lang/String;
    //   2224: invokestatic forName : (Ljava/lang/String;)Ljava/lang/Class;
    //   2227: invokevirtual getDeclaredMethods : ()[Ljava/lang/reflect/Method;
    //   2230: astore #4
    //   2232: aload #4
    //   2234: arraylength
    //   2235: istore #5
    //   2237: iconst_0
    //   2238: istore #6
    //   2240: iload #6
    //   2242: iload #5
    //   2244: if_icmpge -> 2377
    //   2247: aload #4
    //   2249: iload #6
    //   2251: aaload
    //   2252: astore #7
    //   2254: aload #7
    //   2256: invokevirtual getParameterTypes : ()[Ljava/lang/Class;
    //   2259: pop
    //   2260: aload #7
    //   2262: invokevirtual getModifiers : ()I
    //   2265: invokestatic isStatic : (I)Z
    //   2268: ifeq -> 2363
    //   2271: aload #7
    //   2273: invokevirtual getParameterTypes : ()[Ljava/lang/Class;
    //   2276: arraylength
    //   2277: iconst_2
    //   2278: if_icmpne -> 2363
    //   2281: goto -> 2288
    //   2284: invokestatic a : (Ljava/lang/Throwable;)Ljava/lang/Throwable;
    //   2287: athrow
    //   2288: aload #7
    //   2290: invokevirtual getReturnType : ()Ljava/lang/Class;
    //   2293: getstatic java/lang/Void.TYPE : Ljava/lang/Class;
    //   2296: invokevirtual equals : (Ljava/lang/Object;)Z
    //   2299: ifeq -> 2363
    //   2302: goto -> 2309
    //   2305: invokestatic a : (Ljava/lang/Throwable;)Ljava/lang/Throwable;
    //   2308: athrow
    //   2309: aload #7
    //   2311: iconst_1
    //   2312: invokevirtual setAccessible : (Z)V
    //   2315: aload #7
    //   2317: aconst_null
    //   2318: iconst_2
    //   2319: anewarray java/lang/Object
    //   2322: dup
    //   2323: iconst_0
    //   2324: aload_0
    //   2325: aastore
    //   2326: dup
    //   2327: iconst_1
    //   2328: aload_1
    //   2329: ifnonnull -> 2347
    //   2332: goto -> 2339
    //   2335: invokestatic a : (Ljava/lang/Throwable;)Ljava/lang/Throwable;
    //   2338: athrow
    //   2339: aload_1
    //   2340: goto -> 2354
    //   2343: invokestatic a : (Ljava/lang/Throwable;)Ljava/lang/Throwable;
    //   2346: athrow
    //   2347: aload_1
    //   2348: checkcast [B
    //   2351: invokevirtual clone : ()Ljava/lang/Object;
    //   2354: aastore
    //   2355: invokevirtual invoke : (Ljava/lang/Object;[Ljava/lang/Object;)Ljava/lang/Object;
    //   2358: pop
    //   2359: iload_2
    //   2360: ifne -> 2377
    //   2363: iinc #6, 1
    //   2366: iload_2
    //   2367: ifne -> 2240
    //   2370: goto -> 2377
    //   2373: invokestatic a : (Ljava/lang/Throwable;)Ljava/lang/Throwable;
    //   2376: athrow
    //   2377: new java/io/ByteArrayOutputStream
    //   2380: dup
    //   2381: invokespecial <init> : ()V
    //   2384: astore #4
    //   2386: sipush #19466
    //   2389: aload #4
    //   2391: sipush #202
    //   2394: invokevirtual write : (I)V
    //   2397: sipush #7899
    //   2400: aload #4
    //   2402: sipush #254
    //   2405: invokevirtual write : (I)V
    //   2408: aload #4
    //   2410: sipush #186
    //   2413: invokevirtual write : (I)V
    //   2416: aload #4
    //   2418: sipush #190
    //   2421: invokevirtual write : (I)V
    //   2424: aload #4
    //   2426: iconst_0
    //   2427: invokevirtual write : (I)V
    //   2430: aload #4
    //   2432: iconst_1
    //   2433: invokevirtual write : (I)V
    //   2436: aload #4
    //   2438: iconst_0
    //   2439: invokevirtual write : (I)V
    //   2442: aload #4
    //   2444: bipush #50
    //   2446: invokevirtual write : (I)V
    //   2449: aload #4
    //   2451: getstatic burp/Ze13.ZD : Ljava/lang/Object;
    //   2454: checkcast java/math/BigInteger
    //   2457: invokevirtual toByteArray : ()[B
    //   2460: invokevirtual write : ([B)V
    //   2463: aload #4
    //   2465: getstatic burp/Zenr.ZA : Ljava/lang/Object;
    //   2468: checkcast java/math/BigInteger
    //   2471: invokevirtual toByteArray : ()[B
    //   2474: invokevirtual write : ([B)V
    //   2477: aload #4
    //   2479: getstatic burp/Zlh2.Zc : Ljava/lang/Object;
    //   2482: checkcast java/math/BigInteger
    //   2485: invokevirtual toByteArray : ()[B
    //   2488: invokevirtual write : ([B)V
    //   2491: aload #4
    //   2493: invokevirtual toByteArray : ()[B
    //   2496: astore #5
    //   2498: aconst_null
    //   2499: astore #6
    //   2501: invokestatic a : (II)Ljava/lang/String;
    //   2504: invokestatic forName : (Ljava/lang/String;)Ljava/lang/Class;
    //   2507: invokevirtual getDeclaredMethods : ()[Ljava/lang/reflect/Method;
    //   2510: astore #7
    //   2512: aload #7
    //   2514: arraylength
    //   2515: istore #8
    //   2517: iconst_0
    //   2518: istore #9
    //   2520: iload #9
    //   2522: iload #8
    //   2524: if_icmpge -> 2652
    //   2527: aload #7
    //   2529: iload #9
    //   2531: aaload
    //   2532: astore #10
    //   2534: aload #10
    //   2536: invokevirtual getName : ()Ljava/lang/String;
    //   2539: sipush #19465
    //   2542: sipush #-31269
    //   2545: invokestatic a : (II)Ljava/lang/String;
    //   2548: invokevirtual equals : (Ljava/lang/Object;)Z
    //   2551: ifeq -> 2645
    //   2554: aload #10
    //   2556: invokevirtual getParameterTypes : ()[Ljava/lang/Class;
    //   2559: astore #11
    //   2561: aload #11
    //   2563: arraylength
    //   2564: iconst_4
    //   2565: if_icmpeq -> 2575
    //   2568: goto -> 2645
    //   2571: invokestatic a : (Ljava/lang/Throwable;)Ljava/lang/Throwable;
    //   2574: athrow
    //   2575: aload #11
    //   2577: iconst_0
    //   2578: aaload
    //   2579: ldc java/lang/String
    //   2581: if_acmpeq -> 2591
    //   2584: goto -> 2645
    //   2587: invokestatic a : (Ljava/lang/Throwable;)Ljava/lang/Throwable;
    //   2590: athrow
    //   2591: aload #11
    //   2593: iconst_1
    //   2594: aaload
    //   2595: ldc [B
    //   2597: if_acmpeq -> 2607
    //   2600: goto -> 2645
    //   2603: invokestatic a : (Ljava/lang/Throwable;)Ljava/lang/Throwable;
    //   2606: athrow
    //   2607: aload #11
    //   2609: iconst_2
    //   2610: aaload
    //   2611: getstatic java/lang/Integer.TYPE : Ljava/lang/Class;
    //   2614: if_acmpeq -> 2624
    //   2617: goto -> 2645
    //   2620: invokestatic a : (Ljava/lang/Throwable;)Ljava/lang/Throwable;
    //   2623: athrow
    //   2624: aload #11
    //   2626: iconst_3
    //   2627: aaload
    //   2628: getstatic java/lang/Integer.TYPE : Ljava/lang/Class;
    //   2631: if_acmpeq -> 2641
    //   2634: goto -> 2645
    //   2637: invokestatic a : (Ljava/lang/Throwable;)Ljava/lang/Throwable;
    //   2640: athrow
    //   2641: aload #10
    //   2643: astore #6
    //   2645: iinc #9, 1
    //   2648: iload_2
    //   2649: ifne -> 2520
    //   2652: aload #6
    //   2654: iconst_1
    //   2655: invokevirtual setAccessible : (Z)V
    //   2658: ldc burp/Zzah
    //   2660: iconst_0
    //   2661: anewarray java/lang/Class
    //   2664: invokevirtual getDeclaredConstructor : ([Ljava/lang/Class;)Ljava/lang/reflect/Constructor;
    //   2667: astore #7
    //   2669: aload #7
    //   2671: iconst_1
    //   2672: invokevirtual setAccessible : (Z)V
    //   2675: aload #6
    //   2677: aload #7
    //   2679: iconst_0
    //   2680: anewarray java/lang/Object
    //   2683: invokevirtual newInstance : ([Ljava/lang/Object;)Ljava/lang/Object;
    //   2686: iconst_4
    //   2687: anewarray java/lang/Object
    //   2690: dup
    //   2691: iconst_0
    //   2692: sipush #19459
    //   2695: sipush #-32641
    //   2698: invokestatic a : (II)Ljava/lang/String;
    //   2701: aastore
    //   2702: dup
    //   2703: iconst_1
    //   2704: aload #5
    //   2706: aastore
    //   2707: dup
    //   2708: iconst_2
    //   2709: iconst_0
    //   2710: invokestatic valueOf : (I)Ljava/lang/Integer;
    //   2713: aastore
    //   2714: dup
    //   2715: iconst_3
    //   2716: aload #5
    //   2718: arraylength
    //   2719: invokestatic valueOf : (I)Ljava/lang/Integer;
    //   2722: aastore
    //   2723: invokevirtual invoke : (Ljava/lang/Object;[Ljava/lang/Object;)Ljava/lang/Object;
    //   2726: pop
    //   2727: goto -> 2732
    //   2730: astore #4
    //   2732: getstatic burp/Zter.ZE : Ljava/lang/String;
    //   2735: getstatic burp/Zbsr.ZD : Ljava/lang/Object;
    //   2738: checkcast java/math/BigInteger
    //   2741: invokevirtual intValue : ()I
    //   2744: bipush #32
    //   2746: irem
    //   2747: invokestatic abs : (I)I
    //   2750: invokevirtual charAt : (I)C
    //   2753: getstatic burp/Zer.Zp : Ljava/lang/String;
    //   2756: getstatic burp/Ze13.ZD : Ljava/lang/Object;
    //   2759: checkcast java/math/BigInteger
    //   2762: invokevirtual intValue : ()I
    //   2765: bipush #32
    //   2767: irem
    //   2768: invokestatic abs : (I)I
    //   2771: invokevirtual charAt : (I)C
    //   2774: if_icmple -> 2881
    //   2777: getstatic burp/Zod.ZS : Ljava/lang/String;
    //   2780: getstatic burp/Zkig.ZK : Ljava/lang/Object;
    //   2783: checkcast java/math/BigInteger
    //   2786: invokevirtual intValue : ()I
    //   2789: bipush #32
    //   2791: irem
    //   2792: invokestatic abs : (I)I
    //   2795: invokevirtual charAt : (I)C
    //   2798: getstatic burp/Zkyc.ZK : Ljava/lang/String;
    //   2801: getstatic burp/Zb3z.ZR : Ljava/lang/Object;
    //   2804: checkcast java/math/BigInteger
    //   2807: invokevirtual intValue : ()I
    //   2810: bipush #32
    //   2812: irem
    //   2813: invokestatic abs : (I)I
    //   2816: invokevirtual charAt : (I)C
    //   2819: if_icmple -> 2881
    //   2822: goto -> 2829
    //   2825: invokestatic a : (Ljava/lang/Throwable;)Ljava/lang/Throwable;
    //   2828: athrow
    //   2829: getstatic burp/Zsby.Zx : Ljava/lang/String;
    //   2832: getstatic burp/Zk9s.ZY : Ljava/lang/Object;
    //   2835: checkcast java/math/BigInteger
    //   2838: invokevirtual intValue : ()I
    //   2841: bipush #32
    //   2843: irem
    //   2844: invokestatic abs : (I)I
    //   2847: invokevirtual charAt : (I)C
    //   2850: getstatic burp/Zr0u.Z_ : Ljava/lang/String;
    //   2853: getstatic burp/Zsde.Zx : Ljava/lang/Object;
    //   2856: checkcast java/math/BigInteger
    //   2859: invokevirtual intValue : ()I
    //   2862: bipush #32
    //   2864: irem
    //   2865: invokestatic abs : (I)I
    //   2868: invokevirtual charAt : (I)C
    //   2871: if_icmple -> 2889
    //   2874: goto -> 2881
    //   2877: invokestatic a : (Ljava/lang/Throwable;)Ljava/lang/Throwable;
    //   2880: athrow
    //   2881: iconst_1
    //   2882: goto -> 2890
    //   2885: invokestatic a : (Ljava/lang/Throwable;)Ljava/lang/Throwable;
    //   2888: athrow
    //   2889: iconst_0
    //   2890: ireturn
    //   2891: astore_3
    //   2892: new java/lang/Exception
    //   2895: dup
    //   2896: aload_3
    //   2897: invokevirtual getMessage : ()Ljava/lang/String;
    //   2900: invokespecial <init> : (Ljava/lang/String;)V
    //   2903: athrow
    // Exception table:
    //   from	to	target	type
    //   4	2890	2891	java/lang/Throwable
    //   309	333	336	java/lang/Throwable
    //   407	444	444	java/lang/Throwable
    //   448	469	469	java/lang/Throwable
    //   473	503	503	java/lang/Throwable
    //   704	878	881	java/lang/Throwable
    //   848	915	918	java/lang/Throwable
    //   885	952	955	java/lang/Throwable
    //   922	989	992	java/lang/Throwable
    //   959	1026	1029	java/lang/Throwable
    //   996	1063	1066	java/lang/Throwable
    //   1033	1100	1103	java/lang/Throwable
    //   1070	1137	1140	java/lang/Throwable
    //   1107	1174	1177	java/lang/Throwable
    //   1144	1211	1214	java/lang/Throwable
    //   1181	1248	1251	java/lang/Throwable
    //   1218	1285	1288	java/lang/Throwable
    //   1255	1322	1325	java/lang/Throwable
    //   1292	1359	1362	java/lang/Throwable
    //   1329	1396	1399	java/lang/Throwable
    //   1366	1433	1436	java/lang/Throwable
    //   1403	1470	1473	java/lang/Throwable
    //   1440	1507	1510	java/lang/Throwable
    //   1477	1544	1547	java/lang/Throwable
    //   1514	1581	1584	java/lang/Throwable
    //   1551	1618	1621	java/lang/Throwable
    //   1588	1655	1658	java/lang/Throwable
    //   1625	1692	1695	java/lang/Throwable
    //   1662	1729	1732	java/lang/Throwable
    //   1699	1766	1769	java/lang/Throwable
    //   1736	1803	1806	java/lang/Throwable
    //   1773	1840	1843	java/lang/Throwable
    //   1810	1877	1880	java/lang/Throwable
    //   1847	1914	1917	java/lang/Throwable
    //   1884	1951	1954	java/lang/Throwable
    //   1921	1988	1991	java/lang/Throwable
    //   1958	2021	2024	java/lang/Throwable
    //   2087	2101	2101	java/lang/Throwable
    //   2112	2125	2128	java/lang/Throwable
    //   2117	2140	2143	java/lang/Throwable
    //   2132	2158	2161	java/lang/Throwable
    //   2147	2188	2191	java/lang/Throwable
    //   2254	2281	2284	java/lang/Throwable
    //   2271	2302	2305	java/lang/Throwable
    //   2288	2332	2335	java/lang/Throwable
    //   2309	2343	2343	java/lang/Throwable
    //   2354	2370	2373	java/lang/Throwable
    //   2377	2727	2730	java/lang/Throwable
    //   2561	2571	2571	java/lang/Throwable
    //   2575	2587	2587	java/lang/Throwable
    //   2591	2603	2603	java/lang/Throwable
    //   2607	2620	2620	java/lang/Throwable
    //   2624	2637	2637	java/lang/Throwable
    //   2732	2822	2825	java/lang/Throwable
    //   2777	2874	2877	java/lang/Throwable
    //   2829	2885	2885	java/lang/Throwable
  }
  
  static void Zg(Object paramObject) {
    Zl_u.Zc = a(19471, 28612);
    Zl_u.ZR = new BigInteger(a(19468, 12460));
    boolean bool = Zt2e.ZK();
    try {
      try {
        if (Zxzd.ZM.charAt(Math.abs(((BigInteger)Zkfz.Zr).intValue() % 32)) <= Zxzd.ZM.charAt(Math.abs(((BigInteger)Zd1.ZV).intValue() % 32))) {
          try {
            Zl_u.ZT(Class.forName(a(19461, -6638)));
            if (bool)
              Zl_1.ZP(Class.forName(a(19463, -31838))); 
          } catch (Throwable throwable) {
            throw a(null);
          } 
          return;
        } 
      } catch (Throwable throwable) {
        throw a(null);
      } 
      Zl_1.ZP(Class.forName(a(19463, -31838)));
    } catch (Throwable throwable) {}
  }
  
  static {
    // Byte code:
    //   0: bipush #14
    //   2: anewarray java/lang/String
    //   5: astore #5
    //   7: iconst_0
    //   8: istore_3
    //   9: ldc 'Ã¤Ã¬ÃœnÃ§Ã–Â…Â… ÂŒKÂ«Ã½InÃ§%ÃÂ‘ÂÂ/Ã„Ã¦Â&KÂ¿Ã·ÃŽ}ÃµÃ½ÂŽÂÃ½ÃŒÃ„LÃ¶D"Ã˜Ã†^Â€Ã®mÂ‰EoÃ™Uu2Ã·Ã¨#Ã«<SÃ¼^Â°Ã›MeÂ‰VÃªBD_Â˜ $\@Ã±Ã“'Ã±Ã¼\\nÂ½PL1#YZÂ€CLvÃºÂªÃ‡GÃ¦Â•Ã…[$8Â»)ÂŒ;<\\bBcÂ»l{Ã’Ã¤Â™Ã‘GÃ‚Ã¶"oE|8frÂ®NÂ¯Â§\\t|6Ã¥ÂÂ¬pf Ã½ÃˆÃŽ3Â°Â¨Âº CÂ˜3mÂ®Â„4Âš~ÂŸPÃ¡Ã¬ÂµÂšS,WÂ¹Ãƒ-Ãª]Ã·ÂµÃ®-Â¼+Ã± Â”ÂŸnYÂŒ;;DÂ±Â¢Ã­TÂ¬RÃ‘Â‘Ã¸GÂ²Ã¦Ãƒ>\\fÂ¥DÂ¿fÂ³Ã¤Ãš`\\tJÂ ÂºhLsÃÃ»\\tÂµÂ”Ã¿`\\t[`Â˜p\\bmTÂ›'
    //   11: dup
    //   12: astore_2
    //   13: invokevirtual length : ()I
    //   16: istore #4
    //   18: bipush #8
    //   20: istore_1
    //   21: iconst_m1
    //   22: istore_0
    //   23: bipush #21
    //   25: iinc #0, 1
    //   28: aload_2
    //   29: iload_0
    //   30: dup
    //   31: iload_1
    //   32: iadd
    //   33: invokevirtual substring : (II)Ljava/lang/String;
    //   36: iconst_m1
    //   37: goto -> 143
    //   40: aload #5
    //   42: swap
    //   43: iload_3
    //   44: iinc #3, 1
    //   47: swap
    //   48: aastore
    //   49: iload_0
    //   50: iload_1
    //   51: iadd
    //   52: dup
    //   53: istore_0
    //   54: iload #4
    //   56: if_icmpge -> 68
    //   59: aload_2
    //   60: iload_0
    //   61: invokevirtual charAt : (I)C
    //   64: istore_1
    //   65: goto -> 23
    //   68: ldc 'Â²\\rbÃUÂ‰\\bhGÂ¥Ã³ Â®Â™0'
    //   70: dup
    //   71: astore_2
    //   72: invokevirtual length : ()I
    //   75: istore #4
    //   77: bipush #7
    //   79: istore_1
    //   80: iconst_m1
    //   81: istore_0
    //   82: bipush #113
    //   84: iinc #0, 1
    //   87: aload_2
    //   88: iload_0
    //   89: dup
    //   90: iload_1
    //   91: iadd
    //   92: invokevirtual substring : (II)Ljava/lang/String;
    //   95: iconst_0
    //   96: goto -> 143
    //   99: aload #5
    //   101: swap
    //   102: iload_3
    //   103: iinc #3, 1
    //   106: swap
    //   107: aastore
    //   108: iload_0
    //   109: iload_1
    //   110: iadd
    //   111: dup
    //   112: istore_0
    //   113: iload #4
    //   115: if_icmpge -> 127
    //   118: aload_2
    //   119: iload_0
    //   120: invokevirtual charAt : (I)C
    //   123: istore_1
    //   124: goto -> 82
    //   127: aload #5
    //   129: putstatic burp/Zk8b.a : [Ljava/lang/String;
    //   132: bipush #14
    //   134: anewarray java/lang/String
    //   137: putstatic burp/Zk8b.b : [Ljava/lang/String;
    //   140: goto -> 300
    //   143: dup_x2
    //   144: pop
    //   145: invokevirtual toCharArray : ()[C
    //   148: dup_x1
    //   149: arraylength
    //   150: dup_x2
    //   151: pop
    //   152: iconst_0
    //   153: istore #6
    //   155: dup2_x1
    //   156: pop2
    //   157: dup_x2
    //   158: iconst_1
    //   159: if_icmpgt -> 260
    //   162: dup2
    //   163: swap
    //   164: iload #6
    //   166: dup2_x1
    //   167: caload
    //   168: swap
    //   169: iload #6
    //   171: bipush #7
    //   173: irem
    //   174: tableswitch default -> 242, 0 -> 212, 1 -> 217, 2 -> 222, 3 -> 227, 4 -> 232, 5 -> 237
    //   212: bipush #45
    //   214: goto -> 244
    //   217: bipush #20
    //   219: goto -> 244
    //   222: bipush #14
    //   224: goto -> 244
    //   227: bipush #109
    //   229: goto -> 244
    //   232: bipush #24
    //   234: goto -> 244
    //   237: bipush #37
    //   239: goto -> 244
    //   242: bipush #68
    //   244: ixor
    //   245: ixor
    //   246: i2c
    //   247: castore
    //   248: iinc #6, 1
    //   251: dup
    //   252: ifne -> 260
    //   255: dup2
    //   256: dup_x1
    //   257: goto -> 166
    //   260: dup2_x1
    //   261: pop2
    //   262: dup_x2
    //   263: iload #6
    //   265: if_icmpgt -> 162
    //   268: pop
    //   269: new java/lang/String
    //   272: dup_x1
    //   273: swap
    //   274: invokespecial <init> : ([C)V
    //   277: invokevirtual intern : ()Ljava/lang/String;
    //   280: swap
    //   281: pop
    //   282: swap
    //   283: tableswitch default -> 40, 0 -> 99
    //   300: sipush #19464
    //   303: sipush #-7199
    //   306: invokestatic a : (II)Ljava/lang/String;
    //   309: putstatic burp/Zk8b.ZT : Ljava/lang/String;
    //   312: new java/math/BigInteger
    //   315: dup
    //   316: iconst_1
    //   317: bipush #32
    //   319: newarray byte
    //   321: dup
    //   322: iconst_0
    //   323: bipush #63
    //   325: bastore
    //   326: dup
    //   327: iconst_1
    //   328: bipush #-48
    //   330: bastore
    //   331: dup
    //   332: iconst_2
    //   333: bipush #115
    //   335: bastore
    //   336: dup
    //   337: iconst_3
    //   338: bipush #-89
    //   340: bastore
    //   341: dup
    //   342: iconst_4
    //   343: bipush #-21
    //   345: bastore
    //   346: dup
    //   347: iconst_5
    //   348: bipush #-116
    //   350: bastore
    //   351: dup
    //   352: bipush #6
    //   354: bipush #78
    //   356: bastore
    //   357: dup
    //   358: bipush #7
    //   360: bipush #-84
    //   362: bastore
    //   363: dup
    //   364: bipush #8
    //   366: bipush #57
    //   368: bastore
    //   369: dup
    //   370: bipush #9
    //   372: bipush #-92
    //   374: bastore
    //   375: dup
    //   376: bipush #10
    //   378: bipush #126
    //   380: bastore
    //   381: dup
    //   382: bipush #11
    //   384: bipush #-69
    //   386: bastore
    //   387: dup
    //   388: bipush #12
    //   390: bipush #-93
    //   392: bastore
    //   393: dup
    //   394: bipush #13
    //   396: bipush #-124
    //   398: bastore
    //   399: dup
    //   400: bipush #14
    //   402: bipush #127
    //   404: bastore
    //   405: dup
    //   406: bipush #15
    //   408: bipush #32
    //   410: bastore
    //   411: dup
    //   412: bipush #16
    //   414: bipush #-17
    //   416: bastore
    //   417: dup
    //   418: bipush #17
    //   420: bipush #-84
    //   422: bastore
    //   423: dup
    //   424: bipush #18
    //   426: bipush #94
    //   428: bastore
    //   429: dup
    //   430: bipush #19
    //   432: bipush #-53
    //   434: bastore
    //   435: dup
    //   436: bipush #20
    //   438: bipush #48
    //   440: bastore
    //   441: dup
    //   442: bipush #21
    //   444: bipush #-85
    //   446: bastore
    //   447: dup
    //   448: bipush #22
    //   450: bipush #-97
    //   452: bastore
    //   453: dup
    //   454: bipush #23
    //   456: bipush #62
    //   458: bastore
    //   459: dup
    //   460: bipush #24
    //   462: bipush #53
    //   464: bastore
    //   465: dup
    //   466: bipush #25
    //   468: bipush #-102
    //   470: bastore
    //   471: dup
    //   472: bipush #26
    //   474: bipush #126
    //   476: bastore
    //   477: dup
    //   478: bipush #27
    //   480: bipush #-64
    //   482: bastore
    //   483: dup
    //   484: bipush #28
    //   486: bipush #107
    //   488: bastore
    //   489: dup
    //   490: bipush #29
    //   492: bipush #107
    //   494: bastore
    //   495: dup
    //   496: bipush #30
    //   498: bipush #29
    //   500: bastore
    //   501: dup
    //   502: bipush #31
    //   504: bipush #-54
    //   506: bastore
    //   507: invokespecial <init> : (I[B)V
    //   510: putstatic burp/Zk8b.ZK : Ljava/lang/Object;
    //   513: return
  }
  
  private static Throwable a(Throwable paramThrowable) {
    return paramThrowable;
  }
  
  private static String a(int paramInt1, int paramInt2) {
    int i = (paramInt1 ^ 0x4C0E) & 0xFFFF;
    if (b[i] == null) {
      char[] arrayOfChar = a[i].toCharArray();
      switch (arrayOfChar[0] & 0xFF) {
        case 0:
        
        case 1:
        
        case 2:
        
        case 3:
        
        case 4:
        
        case 5:
        
        case 6:
        
        case 7:
        
        case 8:
        
        case 9:
        
        case 10:
        
        case 11:
        
        case 12:
        
        case 13:
        
        case 14:
        
        case 15:
        
        case 16:
        
        case 17:
        
        case 18:
        
        case 19:
        
        case 20:
        
        case 21:
        
        case 22:
        
        case 23:
        
        case 24:
        
        case 25:
        
        case 26:
        
        case 27:
        
        case 28:
        
        case 29:
        
        case 30:
        
        case 31:
        
        case 32:
        
        case 33:
        
        case 34:
        
        case 35:
        
        case 36:
        
        case 37:
        
        case 38:
        
        case 39:
        
        case 40:
        
        case 41:
        
        case 42:
        
        case 43:
        
        case 44:
        
        case 45:
        
        case 46:
        
        case 47:
        
        case 48:
        
        case 49:
        
        case 50:
        
        case 51:
        
        case 52:
        
        case 53:
        
        case 54:
        
        case 55:
        
        case 56:
        
        case 57:
        
        case 58:
        
        case 59:
        
        case 60:
        
        case 61:
        
        case 62:
        
        case 63:
        
        case 64:
        
        case 65:
        
        case 66:
        
        case 67:
        
        case 68:
        
        case 69:
        
        case 70:
        
        case 71:
        
        case 72:
        
        case 73:
        
        case 74:
        
        case 75:
        
        case 76:
        
        case 77:
        
        case 78:
        
        case 79:
        
        case 80:
        
        case 81:
        
        case 82:
        
        case 83:
        
        case 84:
        
        case 85:
        
        case 86:
        
        case 87:
        
        case 88:
        
        case 89:
        
        case 90:
        
        case 91:
        
        case 92:
        
        case 93:
        
        case 94:
        
        case 95:
        
        case 96:
        
        case 97:
        
        case 98:
        
        case 99:
        
        case 100:
        
        case 101:
        
        case 102:
        
        case 103:
        
        case 104:
        
        case 105:
        
        case 106:
        
        case 107:
        
        case 108:
        
        case 109:
        
        case 110:
        
        case 111:
        
        case 112:
        
        case 113:
        
        case 114:
        
        case 115:
        
        case 116:
        
        case 117:
        
        case 118:
        
        case 119:
        
        case 120:
        
        case 121:
        
        case 122:
        
        case 123:
        
        case 124:
        
        case 125:
        
        case 126:
        
        case 127:
        
        case 128:
        
        case 129:
        
        case 130:
        
        case 131:
        
        case 132:
        
        case 133:
        
        case 134:
        
        case 135:
        
        case 136:
        
        case 137:
        
        case 138:
        
        case 139:
        
        case 140:
        
        case 141:
        
        case 142:
        
        case 143:
        
        case 144:
        
        case 145:
        
        case 146:
        
        case 147:
        
        case 148:
        
        case 149:
        
        case 150:
        
        case 151:
        
        case 152:
        
        case 153:
        
        case 154:
        
        case 155:
        
        case 156:
        
        case 157:
        
        case 158:
        
        case 159:
        
        case 160:
        
        case 161:
        
        case 162:
        
        case 163:
        
        case 164:
        
        case 165:
        
        case 166:
        
        case 167:
        
        case 168:
        
        case 169:
        
        case 170:
        
        case 171:
        
        case 172:
        
        case 173:
        
        case 174:
        
        case 175:
        
        case 176:
        
        case 177:
        
        case 178:
        
        case 179:
        
        case 180:
        
        case 181:
        
        case 182:
        
        case 183:
        
        case 184:
        
        case 185:
        
        case 186:
        
        case 187:
        
        case 188:
        
        case 189:
        
        case 190:
        
        case 191:
        
        case 192:
        
        case 193:
        
        case 194:
        
        case 195:
        
        case 196:
        
        case 197:
        
        case 198:
        
        case 199:
        
        case 200:
        
        case 201:
        
        case 202:
        
        case 203:
        
        case 204:
        
        case 205:
        
        case 206:
        
        case 207:
        
        case 208:
        
        case 209:
        
        case 210:
        
        case 211:
        
        case 212:
        
        case 213:
        
        case 214:
        
        case 215:
        
        case 216:
        
        case 217:
        
        case 218:
        
        case 219:
        
        case 220:
        
        case 221:
        
        case 222:
        
        case 223:
        
        case 224:
        
        case 225:
        
        case 226:
        
        case 227:
        
        case 228:
        
        case 229:
        
        case 230:
        
        case 231:
        
        case 232:
        
        case 233:
        
        case 234:
        
        case 235:
        
        case 236:
        
        case 237:
        
        case 238:
        
        case 239:
        
        case 240:
        
        case 241:
        
        case 242:
        
        case 243:
        
        case 244:
        
        case 245:
        
        case 246:
        
        case 247:
        
        case 248:
        
        case 249:
        
        case 250:
        
        case 251:
        
        case 252:
        
        case 253:
        
        case 254:
        
        default:
          break;
      } 
      char c = 'Â¡';
      int j = (paramInt2 & 0xFF) - c;
      if (j < 0)
        j += 256; 
      int k = ((paramInt2 & 0xFFFF) >>> 8) - c;
      if (k < 0)
        k += 256; 
      for (byte b = 0; b < arrayOfChar.length; b++) {
        int m = b % 2;
        if (m == 0) {
          arrayOfChar[b] = (char)(arrayOfChar[b] ^ j);
          j = ((j >>> 3 | j << 5) ^ arrayOfChar[b]) & 0xFF;
        } else {
          arrayOfChar[b] = (char)(arrayOfChar[b] ^ k);
          k = ((k >>> 3 | k << 5) ^ arrayOfChar[b]) & 0xFF;
        } 
      } 
      b[i] = (new String(arrayOfChar)).intern();
    } 
    return b[i];
  }
}


/* Location:              C:\Program Files\BurpSuitePro\burpsuite_pro.jar!\burp\Zk8b.class
 * Java compiler version: 21 (65.0)
 * JD-Core Version:       1.1.3
 */