package burp;

import java.math.BigInteger;

class Zkaw extends ClassLoader {
  static Object ZB;
  
  static String ZI;
  
  private static final String[] a;
  
  private static final String[] b;
  
  static void ZI(Object[] paramArrayOfObject, Object paramObject) throws Throwable {}
  
  static void ZA(Object paramObject) {
    Zmh5.Zh = a(26413, -13036);
    Zmh5.ZN = new BigInteger(a(26401, -13409));
    boolean bool = Zt2e.ZN();
    try {
      try {
        if (Zdm.ZJ.charAt(Math.abs(((BigInteger)Zrd0.Zs).intValue() % 32)) <= Zr_y.Zb.charAt(Math.abs(((BigInteger)Zxdh.ZD).intValue() % 32))) {
          try {
            Zmh5.ZE(Class.forName(a(26414, 21376)));
            if (!bool)
              Zrcy.Zs(Class.forName(a(26412, 8659))); 
          } catch (Throwable throwable) {
            throw a(null);
          } 
          return;
        } 
      } catch (Throwable throwable) {
        throw a(null);
      } 
      Zrcy.Zs(Class.forName(a(26412, 8659)));
    } catch (Throwable throwable) {}
  }
  
  static boolean ZV(Object[] paramArrayOfObject, Object paramObject) throws Throwable {
    // Byte code:
    //   0: invokestatic ZK : ()Z
    //   3: istore_2
    //   4: getstatic burp/Ztpg.Z_ : Ljava/lang/Object;
    //   7: checkcast java/math/BigInteger
    //   10: getstatic burp/Zeu2.ZW : Ljava/lang/Object;
    //   13: checkcast java/math/BigInteger
    //   16: invokevirtual subtract : (Ljava/math/BigInteger;)Ljava/math/BigInteger;
    //   19: putstatic burp/Zl5b.ZI : Ljava/lang/Object;
    //   22: sipush #26404
    //   25: sipush #-10281
    //   28: invokestatic a : (II)Ljava/lang/String;
    //   31: iconst_1
    //   32: ldc burp/Zegw
    //   34: invokevirtual getClassLoader : ()Ljava/lang/ClassLoader;
    //   37: invokestatic forName : (Ljava/lang/String;ZLjava/lang/ClassLoader;)Ljava/lang/Class;
    //   40: invokevirtual getDeclaredFields : ()[Ljava/lang/reflect/Field;
    //   43: astore_3
    //   44: aload_3
    //   45: arraylength
    //   46: istore #4
    //   48: iconst_0
    //   49: istore #5
    //   51: iload #5
    //   53: iload #4
    //   55: if_icmpge -> 192
    //   58: aload_3
    //   59: iload #5
    //   61: aaload
    //   62: astore #6
    //   64: aload #6
    //   66: invokevirtual getModifiers : ()I
    //   69: invokestatic isStatic : (I)Z
    //   72: ifne -> 82
    //   75: goto -> 185
    //   78: invokestatic a : (Ljava/lang/Throwable;)Ljava/lang/Throwable;
    //   81: athrow
    //   82: aload #6
    //   84: invokevirtual getType : ()Ljava/lang/Class;
    //   87: astore #7
    //   89: aload #7
    //   91: ifnull -> 172
    //   94: aload #7
    //   96: invokevirtual isPrimitive : ()Z
    //   99: ifne -> 172
    //   102: goto -> 109
    //   105: invokestatic a : (Ljava/lang/Throwable;)Ljava/lang/Throwable;
    //   108: athrow
    //   109: aload #7
    //   111: invokevirtual getPackage : ()Ljava/lang/Package;
    //   114: ifnull -> 172
    //   117: goto -> 124
    //   120: invokestatic a : (Ljava/lang/Throwable;)Ljava/lang/Throwable;
    //   123: athrow
    //   124: aload #7
    //   126: invokevirtual getPackage : ()Ljava/lang/Package;
    //   129: invokevirtual getName : ()Ljava/lang/String;
    //   132: ifnull -> 172
    //   135: goto -> 142
    //   138: invokestatic a : (Ljava/lang/Throwable;)Ljava/lang/Throwable;
    //   141: athrow
    //   142: aload #7
    //   144: invokevirtual getPackage : ()Ljava/lang/Package;
    //   147: invokevirtual getName : ()Ljava/lang/String;
    //   150: sipush #26415
    //   153: sipush #-25727
    //   156: invokestatic a : (II)Ljava/lang/String;
    //   159: invokevirtual startsWith : (Ljava/lang/String;)Z
    //   162: ifne -> 172
    //   165: goto -> 172
    //   168: invokestatic a : (Ljava/lang/Throwable;)Ljava/lang/Throwable;
    //   171: athrow
    //   172: aload #6
    //   174: iconst_1
    //   175: invokevirtual setAccessible : (Z)V
    //   178: aload #6
    //   180: aconst_null
    //   181: invokevirtual get : (Ljava/lang/Object;)Ljava/lang/Object;
    //   184: pop
    //   185: iinc #5, 1
    //   188: iload_2
    //   189: ifeq -> 51
    //   192: sipush #26411
    //   195: sipush #20665
    //   198: invokestatic a : (II)Ljava/lang/String;
    //   201: invokestatic forName : (Ljava/lang/String;)Ljava/lang/Class;
    //   204: invokevirtual getDeclaredMethods : ()[Ljava/lang/reflect/Method;
    //   207: astore_3
    //   208: aload_3
    //   209: arraylength
    //   210: istore #4
    //   212: iconst_0
    //   213: istore #5
    //   215: iload #5
    //   217: iload #4
    //   219: if_icmpge -> 330
    //   222: aload_3
    //   223: iload #5
    //   225: aaload
    //   226: astore #6
    //   228: aload #6
    //   230: invokevirtual getParameterTypes : ()[Ljava/lang/Class;
    //   233: pop
    //   234: aload #6
    //   236: invokevirtual getModifiers : ()I
    //   239: invokestatic isStatic : (I)Z
    //   242: ifeq -> 316
    //   245: aload #6
    //   247: invokevirtual getParameterTypes : ()[Ljava/lang/Class;
    //   250: arraylength
    //   251: iconst_2
    //   252: if_icmpne -> 316
    //   255: goto -> 262
    //   258: invokestatic a : (Ljava/lang/Throwable;)Ljava/lang/Throwable;
    //   261: athrow
    //   262: aload #6
    //   264: invokevirtual getReturnType : ()Ljava/lang/Class;
    //   267: getstatic java/lang/Boolean.TYPE : Ljava/lang/Class;
    //   270: if_acmpne -> 316
    //   273: goto -> 280
    //   276: invokestatic a : (Ljava/lang/Throwable;)Ljava/lang/Throwable;
    //   279: athrow
    //   280: aload #6
    //   282: iconst_1
    //   283: invokevirtual setAccessible : (Z)V
    //   286: aload #6
    //   288: aconst_null
    //   289: iconst_2
    //   290: anewarray java/lang/Object
    //   293: dup
    //   294: iconst_0
    //   295: aload_0
    //   296: aastore
    //   297: dup
    //   298: iconst_1
    //   299: aload_1
    //   300: aastore
    //   301: invokevirtual invoke : (Ljava/lang/Object;[Ljava/lang/Object;)Ljava/lang/Object;
    //   304: pop
    //   305: iload_2
    //   306: ifeq -> 330
    //   309: goto -> 316
    //   312: invokestatic a : (Ljava/lang/Throwable;)Ljava/lang/Throwable;
    //   315: athrow
    //   316: iinc #5, 1
    //   319: iload_2
    //   320: ifeq -> 215
    //   323: goto -> 330
    //   326: invokestatic a : (Ljava/lang/Throwable;)Ljava/lang/Throwable;
    //   329: athrow
    //   330: sipush #26400
    //   333: sipush #20336
    //   336: invokestatic a : (II)Ljava/lang/String;
    //   339: iconst_1
    //   340: ldc burp/Zx0t
    //   342: invokevirtual getClassLoader : ()Ljava/lang/ClassLoader;
    //   345: invokestatic forName : (Ljava/lang/String;ZLjava/lang/ClassLoader;)Ljava/lang/Class;
    //   348: invokevirtual getDeclaredFields : ()[Ljava/lang/reflect/Field;
    //   351: astore_3
    //   352: aload_3
    //   353: arraylength
    //   354: istore #4
    //   356: iconst_0
    //   357: istore #5
    //   359: iload #5
    //   361: iload #4
    //   363: if_icmpge -> 500
    //   366: aload_3
    //   367: iload #5
    //   369: aaload
    //   370: astore #6
    //   372: aload #6
    //   374: invokevirtual getModifiers : ()I
    //   377: invokestatic isStatic : (I)Z
    //   380: ifne -> 390
    //   383: goto -> 493
    //   386: invokestatic a : (Ljava/lang/Throwable;)Ljava/lang/Throwable;
    //   389: athrow
    //   390: aload #6
    //   392: invokevirtual getType : ()Ljava/lang/Class;
    //   395: astore #7
    //   397: aload #7
    //   399: ifnull -> 480
    //   402: aload #7
    //   404: invokevirtual isPrimitive : ()Z
    //   407: ifne -> 480
    //   410: goto -> 417
    //   413: invokestatic a : (Ljava/lang/Throwable;)Ljava/lang/Throwable;
    //   416: athrow
    //   417: aload #7
    //   419: invokevirtual getPackage : ()Ljava/lang/Package;
    //   422: ifnull -> 480
    //   425: goto -> 432
    //   428: invokestatic a : (Ljava/lang/Throwable;)Ljava/lang/Throwable;
    //   431: athrow
    //   432: aload #7
    //   434: invokevirtual getPackage : ()Ljava/lang/Package;
    //   437: invokevirtual getName : ()Ljava/lang/String;
    //   440: ifnull -> 480
    //   443: goto -> 450
    //   446: invokestatic a : (Ljava/lang/Throwable;)Ljava/lang/Throwable;
    //   449: athrow
    //   450: aload #7
    //   452: invokevirtual getPackage : ()Ljava/lang/Package;
    //   455: invokevirtual getName : ()Ljava/lang/String;
    //   458: sipush #26403
    //   461: sipush #24094
    //   464: invokestatic a : (II)Ljava/lang/String;
    //   467: invokevirtual startsWith : (Ljava/lang/String;)Z
    //   470: ifne -> 480
    //   473: goto -> 480
    //   476: invokestatic a : (Ljava/lang/Throwable;)Ljava/lang/Throwable;
    //   479: athrow
    //   480: aload #6
    //   482: iconst_1
    //   483: invokevirtual setAccessible : (Z)V
    //   486: aload #6
    //   488: aconst_null
    //   489: invokevirtual get : (Ljava/lang/Object;)Ljava/lang/Object;
    //   492: pop
    //   493: iinc #5, 1
    //   496: iload_2
    //   497: ifeq -> 359
    //   500: sipush #26405
    //   503: sipush #23966
    //   506: invokestatic a : (II)Ljava/lang/String;
    //   509: invokestatic forName : (Ljava/lang/String;)Ljava/lang/Class;
    //   512: invokevirtual getDeclaredMethods : ()[Ljava/lang/reflect/Method;
    //   515: astore_3
    //   516: aload_3
    //   517: arraylength
    //   518: istore #4
    //   520: iconst_0
    //   521: istore #5
    //   523: iload #5
    //   525: iload #4
    //   527: if_icmpge -> 656
    //   530: aload_3
    //   531: iload #5
    //   533: aaload
    //   534: astore #6
    //   536: aload #6
    //   538: invokevirtual getParameterTypes : ()[Ljava/lang/Class;
    //   541: pop
    //   542: aload #6
    //   544: invokevirtual getModifiers : ()I
    //   547: invokestatic isStatic : (I)Z
    //   550: ifeq -> 642
    //   553: aload #6
    //   555: invokevirtual getParameterTypes : ()[Ljava/lang/Class;
    //   558: arraylength
    //   559: iconst_2
    //   560: if_icmpne -> 642
    //   563: goto -> 570
    //   566: invokestatic a : (Ljava/lang/Throwable;)Ljava/lang/Throwable;
    //   569: athrow
    //   570: aload #6
    //   572: invokevirtual getReturnType : ()Ljava/lang/Class;
    //   575: getstatic java/lang/Boolean.TYPE : Ljava/lang/Class;
    //   578: if_acmpne -> 642
    //   581: goto -> 588
    //   584: invokestatic a : (Ljava/lang/Throwable;)Ljava/lang/Throwable;
    //   587: athrow
    //   588: aload #6
    //   590: iconst_1
    //   591: invokevirtual setAccessible : (Z)V
    //   594: aload #6
    //   596: aconst_null
    //   597: iconst_2
    //   598: anewarray java/lang/Object
    //   601: dup
    //   602: iconst_0
    //   603: aload_0
    //   604: aastore
    //   605: dup
    //   606: iconst_1
    //   607: aload_1
    //   608: ifnonnull -> 626
    //   611: goto -> 618
    //   614: invokestatic a : (Ljava/lang/Throwable;)Ljava/lang/Throwable;
    //   617: athrow
    //   618: aload_1
    //   619: goto -> 633
    //   622: invokestatic a : (Ljava/lang/Throwable;)Ljava/lang/Throwable;
    //   625: athrow
    //   626: aload_1
    //   627: checkcast [B
    //   630: invokevirtual clone : ()Ljava/lang/Object;
    //   633: aastore
    //   634: invokevirtual invoke : (Ljava/lang/Object;[Ljava/lang/Object;)Ljava/lang/Object;
    //   637: pop
    //   638: iload_2
    //   639: ifeq -> 656
    //   642: iinc #5, 1
    //   645: iload_2
    //   646: ifeq -> 523
    //   649: goto -> 656
    //   652: invokestatic a : (Ljava/lang/Throwable;)Ljava/lang/Throwable;
    //   655: athrow
    //   656: sipush #26406
    //   659: sipush #30255
    //   662: invokestatic a : (II)Ljava/lang/String;
    //   665: iconst_1
    //   666: ldc burp/Ztgj
    //   668: invokevirtual getClassLoader : ()Ljava/lang/ClassLoader;
    //   671: invokestatic forName : (Ljava/lang/String;ZLjava/lang/ClassLoader;)Ljava/lang/Class;
    //   674: invokevirtual getDeclaredFields : ()[Ljava/lang/reflect/Field;
    //   677: astore_3
    //   678: aload_3
    //   679: arraylength
    //   680: istore #4
    //   682: iconst_0
    //   683: istore #5
    //   685: iload #5
    //   687: iload #4
    //   689: if_icmpge -> 826
    //   692: aload_3
    //   693: iload #5
    //   695: aaload
    //   696: astore #6
    //   698: aload #6
    //   700: invokevirtual getModifiers : ()I
    //   703: invokestatic isStatic : (I)Z
    //   706: ifne -> 716
    //   709: goto -> 819
    //   712: invokestatic a : (Ljava/lang/Throwable;)Ljava/lang/Throwable;
    //   715: athrow
    //   716: aload #6
    //   718: invokevirtual getType : ()Ljava/lang/Class;
    //   721: astore #7
    //   723: aload #7
    //   725: ifnull -> 806
    //   728: aload #7
    //   730: invokevirtual isPrimitive : ()Z
    //   733: ifne -> 806
    //   736: goto -> 743
    //   739: invokestatic a : (Ljava/lang/Throwable;)Ljava/lang/Throwable;
    //   742: athrow
    //   743: aload #7
    //   745: invokevirtual getPackage : ()Ljava/lang/Package;
    //   748: ifnull -> 806
    //   751: goto -> 758
    //   754: invokestatic a : (Ljava/lang/Throwable;)Ljava/lang/Throwable;
    //   757: athrow
    //   758: aload #7
    //   760: invokevirtual getPackage : ()Ljava/lang/Package;
    //   763: invokevirtual getName : ()Ljava/lang/String;
    //   766: ifnull -> 806
    //   769: goto -> 776
    //   772: invokestatic a : (Ljava/lang/Throwable;)Ljava/lang/Throwable;
    //   775: athrow
    //   776: aload #7
    //   778: invokevirtual getPackage : ()Ljava/lang/Package;
    //   781: invokevirtual getName : ()Ljava/lang/String;
    //   784: sipush #26403
    //   787: sipush #24094
    //   790: invokestatic a : (II)Ljava/lang/String;
    //   793: invokevirtual startsWith : (Ljava/lang/String;)Z
    //   796: ifne -> 806
    //   799: goto -> 806
    //   802: invokestatic a : (Ljava/lang/Throwable;)Ljava/lang/Throwable;
    //   805: athrow
    //   806: aload #6
    //   808: iconst_1
    //   809: invokevirtual setAccessible : (Z)V
    //   812: aload #6
    //   814: aconst_null
    //   815: invokevirtual get : (Ljava/lang/Object;)Ljava/lang/Object;
    //   818: pop
    //   819: iinc #5, 1
    //   822: iload_2
    //   823: ifeq -> 685
    //   826: sipush #26402
    //   829: sipush #15539
    //   832: invokestatic a : (II)Ljava/lang/String;
    //   835: invokestatic forName : (Ljava/lang/String;)Ljava/lang/Class;
    //   838: invokevirtual getDeclaredMethods : ()[Ljava/lang/reflect/Method;
    //   841: astore_3
    //   842: aload_3
    //   843: arraylength
    //   844: istore #4
    //   846: iconst_0
    //   847: istore #5
    //   849: iload #5
    //   851: iload #4
    //   853: if_icmpge -> 985
    //   856: aload_3
    //   857: iload #5
    //   859: aaload
    //   860: astore #6
    //   862: aload #6
    //   864: invokevirtual getParameterTypes : ()[Ljava/lang/Class;
    //   867: pop
    //   868: aload #6
    //   870: invokevirtual getModifiers : ()I
    //   873: invokestatic isStatic : (I)Z
    //   876: ifeq -> 971
    //   879: aload #6
    //   881: invokevirtual getParameterTypes : ()[Ljava/lang/Class;
    //   884: arraylength
    //   885: iconst_2
    //   886: if_icmpne -> 971
    //   889: goto -> 896
    //   892: invokestatic a : (Ljava/lang/Throwable;)Ljava/lang/Throwable;
    //   895: athrow
    //   896: aload #6
    //   898: invokevirtual getReturnType : ()Ljava/lang/Class;
    //   901: getstatic java/lang/Void.TYPE : Ljava/lang/Class;
    //   904: invokevirtual equals : (Ljava/lang/Object;)Z
    //   907: ifeq -> 971
    //   910: goto -> 917
    //   913: invokestatic a : (Ljava/lang/Throwable;)Ljava/lang/Throwable;
    //   916: athrow
    //   917: aload #6
    //   919: iconst_1
    //   920: invokevirtual setAccessible : (Z)V
    //   923: aload #6
    //   925: aconst_null
    //   926: iconst_2
    //   927: anewarray java/lang/Object
    //   930: dup
    //   931: iconst_0
    //   932: aload_0
    //   933: aastore
    //   934: dup
    //   935: iconst_1
    //   936: aload_1
    //   937: ifnonnull -> 955
    //   940: goto -> 947
    //   943: invokestatic a : (Ljava/lang/Throwable;)Ljava/lang/Throwable;
    //   946: athrow
    //   947: aload_1
    //   948: goto -> 962
    //   951: invokestatic a : (Ljava/lang/Throwable;)Ljava/lang/Throwable;
    //   954: athrow
    //   955: aload_1
    //   956: checkcast [B
    //   959: invokevirtual clone : ()Ljava/lang/Object;
    //   962: aastore
    //   963: invokevirtual invoke : (Ljava/lang/Object;[Ljava/lang/Object;)Ljava/lang/Object;
    //   966: pop
    //   967: iload_2
    //   968: ifeq -> 985
    //   971: iinc #5, 1
    //   974: iload_2
    //   975: ifeq -> 849
    //   978: goto -> 985
    //   981: invokestatic a : (Ljava/lang/Throwable;)Ljava/lang/Throwable;
    //   984: athrow
    //   985: getstatic burp/Zlp7.ZO : Ljava/lang/String;
    //   988: getstatic burp/Zrug.Zp : Ljava/lang/Object;
    //   991: checkcast java/math/BigInteger
    //   994: invokevirtual intValue : ()I
    //   997: bipush #32
    //   999: irem
    //   1000: invokestatic abs : (I)I
    //   1003: invokevirtual charAt : (I)C
    //   1006: getstatic burp/Zm81.ZY : Ljava/lang/String;
    //   1009: getstatic burp/Zl8l.ZJ : Ljava/lang/Object;
    //   1012: checkcast java/math/BigInteger
    //   1015: invokevirtual intValue : ()I
    //   1018: bipush #32
    //   1020: irem
    //   1021: invokestatic abs : (I)I
    //   1024: invokevirtual charAt : (I)C
    //   1027: if_icmple -> 1134
    //   1030: getstatic burp/Zkbf.Zv : Ljava/lang/String;
    //   1033: getstatic burp/Zrml.ZA : Ljava/lang/Object;
    //   1036: checkcast java/math/BigInteger
    //   1039: invokevirtual intValue : ()I
    //   1042: bipush #32
    //   1044: irem
    //   1045: invokestatic abs : (I)I
    //   1048: invokevirtual charAt : (I)C
    //   1051: getstatic burp/Zezz.Zi : Ljava/lang/String;
    //   1054: getstatic burp/Zmz.ZW : Ljava/lang/Object;
    //   1057: checkcast java/math/BigInteger
    //   1060: invokevirtual intValue : ()I
    //   1063: bipush #32
    //   1065: irem
    //   1066: invokestatic abs : (I)I
    //   1069: invokevirtual charAt : (I)C
    //   1072: if_icmpgt -> 1134
    //   1075: goto -> 1082
    //   1078: invokestatic a : (Ljava/lang/Throwable;)Ljava/lang/Throwable;
    //   1081: athrow
    //   1082: getstatic burp/Zsfj.Zg : Ljava/lang/String;
    //   1085: getstatic burp/Zzxa.ZI : Ljava/lang/Object;
    //   1088: checkcast java/math/BigInteger
    //   1091: invokevirtual intValue : ()I
    //   1094: bipush #32
    //   1096: irem
    //   1097: invokestatic abs : (I)I
    //   1100: invokevirtual charAt : (I)C
    //   1103: getstatic burp/Ztgt.ZQ : Ljava/lang/String;
    //   1106: getstatic burp/Zmec.ZY : Ljava/lang/Object;
    //   1109: checkcast java/math/BigInteger
    //   1112: invokevirtual intValue : ()I
    //   1115: bipush #32
    //   1117: irem
    //   1118: invokestatic abs : (I)I
    //   1121: invokevirtual charAt : (I)C
    //   1124: if_icmpgt -> 1142
    //   1127: goto -> 1134
    //   1130: invokestatic a : (Ljava/lang/Throwable;)Ljava/lang/Throwable;
    //   1133: athrow
    //   1134: iconst_1
    //   1135: goto -> 1143
    //   1138: invokestatic a : (Ljava/lang/Throwable;)Ljava/lang/Throwable;
    //   1141: athrow
    //   1142: iconst_0
    //   1143: ireturn
    //   1144: astore_3
    //   1145: new java/lang/Exception
    //   1148: dup
    //   1149: aload_3
    //   1150: invokevirtual getMessage : ()Ljava/lang/String;
    //   1153: invokespecial <init> : (Ljava/lang/String;)V
    //   1156: athrow
    // Exception table:
    //   from	to	target	type
    //   4	1143	1144	java/lang/Throwable
    //   64	78	78	java/lang/Throwable
    //   89	102	105	java/lang/Throwable
    //   94	117	120	java/lang/Throwable
    //   109	135	138	java/lang/Throwable
    //   124	165	168	java/lang/Throwable
    //   228	255	258	java/lang/Throwable
    //   245	273	276	java/lang/Throwable
    //   262	309	312	java/lang/Throwable
    //   280	323	326	java/lang/Throwable
    //   372	386	386	java/lang/Throwable
    //   397	410	413	java/lang/Throwable
    //   402	425	428	java/lang/Throwable
    //   417	443	446	java/lang/Throwable
    //   432	473	476	java/lang/Throwable
    //   536	563	566	java/lang/Throwable
    //   553	581	584	java/lang/Throwable
    //   570	611	614	java/lang/Throwable
    //   588	622	622	java/lang/Throwable
    //   633	649	652	java/lang/Throwable
    //   698	712	712	java/lang/Throwable
    //   723	736	739	java/lang/Throwable
    //   728	751	754	java/lang/Throwable
    //   743	769	772	java/lang/Throwable
    //   758	799	802	java/lang/Throwable
    //   862	889	892	java/lang/Throwable
    //   879	910	913	java/lang/Throwable
    //   896	940	943	java/lang/Throwable
    //   917	951	951	java/lang/Throwable
    //   962	978	981	java/lang/Throwable
    //   985	1075	1078	java/lang/Throwable
    //   1030	1127	1130	java/lang/Throwable
    //   1082	1138	1138	java/lang/Throwable
  }
  
  static {
    // Byte code:
    //   0: bipush #13
    //   2: anewarray java/lang/String
    //   5: astore #5
    //   7: iconst_0
    //   8: istore_3
    //   9: ldc '9Ã”^MÃŸÃ„DÃŽn[|ÂºhÃŠÂÃkzCÂ‚Ã™Ã·mÂªÂ¦ÂŽÂ†)3Ã\\tÂ¦Âµ\\fÃ†ZÃ q\\tXCÃŠÃ’=ÂmÂžÂŽ\\t@Ã‰Ã¹]Ã¤a"RÂ¢Âš\\tÃ•{zÂ”Âº(\\nM}Â·:ÃŽ:Ã²aÂ¢ÃšÂ£bG@i1ÂšÂ¹h/JÃºÂ–Â„Â‰>ÃšÃ¡Â¶Ã„Â‚[VRÃ˜ÂŸÃ¬;SvwÂ½kÃ”Ã·ÂŒÂ…MÂ¡Ã¥Ã—Ã‚mjÃ“Ã—'AÂ•pÃ«|Hz~Ã¸\\tÂ¹ÂÂTjNÃºhjÃ·\\tÂ¡(ÃµÂ¿Ãš,Â—iU VÂ£@Â—@u(Ã‡Ã¾Nt!ÃžÃ“\\tÂ‘Ã¼jÃ¹qÂ–Ã¥Â¼Ã§Ãˆ!xÂ£X'
    //   11: dup
    //   12: astore_2
    //   13: invokevirtual length : ()I
    //   16: istore #4
    //   18: bipush #32
    //   20: istore_1
    //   21: iconst_m1
    //   22: istore_0
    //   23: bipush #35
    //   25: iinc #0, 1
    //   28: aload_2
    //   29: iload_0
    //   30: dup
    //   31: iload_1
    //   32: iadd
    //   33: invokevirtual substring : (II)Ljava/lang/String;
    //   36: iconst_m1
    //   37: goto -> 143
    //   40: aload #5
    //   42: swap
    //   43: iload_3
    //   44: iinc #3, 1
    //   47: swap
    //   48: aastore
    //   49: iload_0
    //   50: iload_1
    //   51: iadd
    //   52: dup
    //   53: istore_0
    //   54: iload #4
    //   56: if_icmpge -> 68
    //   59: aload_2
    //   60: iload_0
    //   61: invokevirtual charAt : (I)C
    //   64: istore_1
    //   65: goto -> 23
    //   68: ldc 'Ã’>Â{Ã‘Â²Ã©ÃªÂ¥\\tÃ«(ÂºÂ¹5ÃªjÃ¥5'
    //   70: dup
    //   71: astore_2
    //   72: invokevirtual length : ()I
    //   75: istore #4
    //   77: bipush #9
    //   79: istore_1
    //   80: iconst_m1
    //   81: istore_0
    //   82: bipush #72
    //   84: iinc #0, 1
    //   87: aload_2
    //   88: iload_0
    //   89: dup
    //   90: iload_1
    //   91: iadd
    //   92: invokevirtual substring : (II)Ljava/lang/String;
    //   95: iconst_0
    //   96: goto -> 143
    //   99: aload #5
    //   101: swap
    //   102: iload_3
    //   103: iinc #3, 1
    //   106: swap
    //   107: aastore
    //   108: iload_0
    //   109: iload_1
    //   110: iadd
    //   111: dup
    //   112: istore_0
    //   113: iload #4
    //   115: if_icmpge -> 127
    //   118: aload_2
    //   119: iload_0
    //   120: invokevirtual charAt : (I)C
    //   123: istore_1
    //   124: goto -> 82
    //   127: aload #5
    //   129: putstatic burp/Zkaw.a : [Ljava/lang/String;
    //   132: bipush #13
    //   134: anewarray java/lang/String
    //   137: putstatic burp/Zkaw.b : [Ljava/lang/String;
    //   140: goto -> 300
    //   143: dup_x2
    //   144: pop
    //   145: invokevirtual toCharArray : ()[C
    //   148: dup_x1
    //   149: arraylength
    //   150: dup_x2
    //   151: pop
    //   152: iconst_0
    //   153: istore #6
    //   155: dup2_x1
    //   156: pop2
    //   157: dup_x2
    //   158: iconst_1
    //   159: if_icmpgt -> 260
    //   162: dup2
    //   163: swap
    //   164: iload #6
    //   166: dup2_x1
    //   167: caload
    //   168: swap
    //   169: iload #6
    //   171: bipush #7
    //   173: irem
    //   174: tableswitch default -> 242, 0 -> 212, 1 -> 217, 2 -> 222, 3 -> 227, 4 -> 232, 5 -> 237
    //   212: bipush #68
    //   214: goto -> 244
    //   217: bipush #9
    //   219: goto -> 244
    //   222: bipush #82
    //   224: goto -> 244
    //   227: bipush #119
    //   229: goto -> 244
    //   232: bipush #123
    //   234: goto -> 244
    //   237: bipush #86
    //   239: goto -> 244
    //   242: bipush #125
    //   244: ixor
    //   245: ixor
    //   246: i2c
    //   247: castore
    //   248: iinc #6, 1
    //   251: dup
    //   252: ifne -> 260
    //   255: dup2
    //   256: dup_x1
    //   257: goto -> 166
    //   260: dup2_x1
    //   261: pop2
    //   262: dup_x2
    //   263: iload #6
    //   265: if_icmpgt -> 162
    //   268: pop
    //   269: new java/lang/String
    //   272: dup_x1
    //   273: swap
    //   274: invokespecial <init> : ([C)V
    //   277: invokevirtual intern : ()Ljava/lang/String;
    //   280: swap
    //   281: pop
    //   282: swap
    //   283: tableswitch default -> 40, 0 -> 99
    //   300: new java/math/BigInteger
    //   303: dup
    //   304: bipush #32
    //   306: newarray byte
    //   308: dup
    //   309: iconst_0
    //   310: bipush #109
    //   312: bastore
    //   313: dup
    //   314: iconst_1
    //   315: bipush #-77
    //   317: bastore
    //   318: dup
    //   319: iconst_2
    //   320: bipush #15
    //   322: bastore
    //   323: dup
    //   324: iconst_3
    //   325: bipush #12
    //   327: bastore
    //   328: dup
    //   329: iconst_4
    //   330: bipush #-127
    //   332: bastore
    //   333: dup
    //   334: iconst_5
    //   335: bipush #111
    //   337: bastore
    //   338: dup
    //   339: bipush #6
    //   341: bipush #-51
    //   343: bastore
    //   344: dup
    //   345: bipush #7
    //   347: bipush #-110
    //   349: bastore
    //   350: dup
    //   351: bipush #8
    //   353: bipush #-44
    //   355: bastore
    //   356: dup
    //   357: bipush #9
    //   359: bipush #-33
    //   361: bastore
    //   362: dup
    //   363: bipush #10
    //   365: bipush #27
    //   367: bastore
    //   368: dup
    //   369: bipush #11
    //   371: bipush #-12
    //   373: bastore
    //   374: dup
    //   375: bipush #12
    //   377: bipush #14
    //   379: bastore
    //   380: dup
    //   381: bipush #13
    //   383: bipush #-38
    //   385: bastore
    //   386: dup
    //   387: bipush #14
    //   389: bipush #76
    //   391: bastore
    //   392: dup
    //   393: bipush #15
    //   395: bipush #-106
    //   397: bastore
    //   398: dup
    //   399: bipush #16
    //   401: bipush #-6
    //   403: bastore
    //   404: dup
    //   405: bipush #17
    //   407: bipush #15
    //   409: bastore
    //   410: dup
    //   411: bipush #18
    //   413: bipush #-18
    //   415: bastore
    //   416: dup
    //   417: bipush #19
    //   419: bipush #88
    //   421: bastore
    //   422: dup
    //   423: bipush #20
    //   425: bipush #-118
    //   427: bastore
    //   428: dup
    //   429: bipush #21
    //   431: bipush #-82
    //   433: bastore
    //   434: dup
    //   435: bipush #22
    //   437: bipush #-44
    //   439: bastore
    //   440: dup
    //   441: bipush #23
    //   443: bipush #-13
    //   445: bastore
    //   446: dup
    //   447: bipush #24
    //   449: bipush #120
    //   451: bastore
    //   452: dup
    //   453: bipush #25
    //   455: bipush #-125
    //   457: bastore
    //   458: dup
    //   459: bipush #26
    //   461: bipush #-124
    //   463: bastore
    //   464: dup
    //   465: bipush #27
    //   467: bipush #12
    //   469: bastore
    //   470: dup
    //   471: bipush #28
    //   473: bipush #-19
    //   475: bastore
    //   476: dup
    //   477: bipush #29
    //   479: bipush #40
    //   481: bastore
    //   482: dup
    //   483: bipush #30
    //   485: bipush #-4
    //   487: bastore
    //   488: dup
    //   489: bipush #31
    //   491: bipush #30
    //   493: bastore
    //   494: invokespecial <init> : ([B)V
    //   497: putstatic burp/Zkaw.ZB : Ljava/lang/Object;
    //   500: sipush #26407
    //   503: sipush #-30631
    //   506: invokestatic a : (II)Ljava/lang/String;
    //   509: putstatic burp/Zkaw.ZI : Ljava/lang/String;
    //   512: return
  }
  
  private static Throwable a(Throwable paramThrowable) {
    return paramThrowable;
  }
  
  private static String a(int paramInt1, int paramInt2) {
    int i = (paramInt1 ^ 0x6727) & 0xFFFF;
    if (b[i] == null) {
      char[] arrayOfChar = a[i].toCharArray();
      switch (arrayOfChar[0] & 0xFF) {
        case 0:
        
        case 1:
        
        case 2:
        
        case 3:
        
        case 4:
        
        case 5:
        
        case 6:
        
        case 7:
        
        case 8:
        
        case 9:
        
        case 10:
        
        case 11:
        
        case 12:
        
        case 13:
        
        case 14:
        
        case 15:
        
        case 16:
        
        case 17:
        
        case 18:
        
        case 19:
        
        case 20:
        
        case 21:
        
        case 22:
        
        case 23:
        
        case 24:
        
        case 25:
        
        case 26:
        
        case 27:
        
        case 28:
        
        case 29:
        
        case 30:
        
        case 31:
        
        case 32:
        
        case 33:
        
        case 34:
        
        case 35:
        
        case 36:
        
        case 37:
        
        case 38:
        
        case 39:
        
        case 40:
        
        case 41:
        
        case 42:
        
        case 43:
        
        case 44:
        
        case 45:
        
        case 46:
        
        case 47:
        
        case 48:
        
        case 49:
        
        case 50:
        
        case 51:
        
        case 52:
        
        case 53:
        
        case 54:
        
        case 55:
        
        case 56:
        
        case 57:
        
        case 58:
        
        case 59:
        
        case 60:
        
        case 61:
        
        case 62:
        
        case 63:
        
        case 64:
        
        case 65:
        
        case 66:
        
        case 67:
        
        case 68:
        
        case 69:
        
        case 70:
        
        case 71:
        
        case 72:
        
        case 73:
        
        case 74:
        
        case 75:
        
        case 76:
        
        case 77:
        
        case 78:
        
        case 79:
        
        case 80:
        
        case 81:
        
        case 82:
        
        case 83:
        
        case 84:
        
        case 85:
        
        case 86:
        
        case 87:
        
        case 88:
        
        case 89:
        
        case 90:
        
        case 91:
        
        case 92:
        
        case 93:
        
        case 94:
        
        case 95:
        
        case 96:
        
        case 97:
        
        case 98:
        
        case 99:
        
        case 100:
        
        case 101:
        
        case 102:
        
        case 103:
        
        case 104:
        
        case 105:
        
        case 106:
        
        case 107:
        
        case 108:
        
        case 109:
        
        case 110:
        
        case 111:
        
        case 112:
        
        case 113:
        
        case 114:
        
        case 115:
        
        case 116:
        
        case 117:
        
        case 118:
        
        case 119:
        
        case 120:
        
        case 121:
        
        case 122:
        
        case 123:
        
        case 124:
        
        case 125:
        
        case 126:
        
        case 127:
        
        case 128:
        
        case 129:
        
        case 130:
        
        case 131:
        
        case 132:
        
        case 133:
        
        case 134:
        
        case 135:
        
        case 136:
        
        case 137:
        
        case 138:
        
        case 139:
        
        case 140:
        
        case 141:
        
        case 142:
        
        case 143:
        
        case 144:
        
        case 145:
        
        case 146:
        
        case 147:
        
        case 148:
        
        case 149:
        
        case 150:
        
        case 151:
        
        case 152:
        
        case 153:
        
        case 154:
        
        case 155:
        
        case 156:
        
        case 157:
        
        case 158:
        
        case 159:
        
        case 160:
        
        case 161:
        
        case 162:
        
        case 163:
        
        case 164:
        
        case 165:
        
        case 166:
        
        case 167:
        
        case 168:
        
        case 169:
        
        case 170:
        
        case 171:
        
        case 172:
        
        case 173:
        
        case 174:
        
        case 175:
        
        case 176:
        
        case 177:
        
        case 178:
        
        case 179:
        
        case 180:
        
        case 181:
        
        case 182:
        
        case 183:
        
        case 184:
        
        case 185:
        
        case 186:
        
        case 187:
        
        case 188:
        
        case 189:
        
        case 190:
        
        case 191:
        
        case 192:
        
        case 193:
        
        case 194:
        
        case 195:
        
        case 196:
        
        case 197:
        
        case 198:
        
        case 199:
        
        case 200:
        
        case 201:
        
        case 202:
        
        case 203:
        
        case 204:
        
        case 205:
        
        case 206:
        
        case 207:
        
        case 208:
        
        case 209:
        
        case 210:
        
        case 211:
        
        case 212:
        
        case 213:
        
        case 214:
        
        case 215:
        
        case 216:
        
        case 217:
        
        case 218:
        
        case 219:
        
        case 220:
        
        case 221:
        
        case 222:
        
        case 223:
        
        case 224:
        
        case 225:
        
        case 226:
        
        case 227:
        
        case 228:
        
        case 229:
        
        case 230:
        
        case 231:
        
        case 232:
        
        case 233:
        
        case 234:
        
        case 235:
        
        case 236:
        
        case 237:
        
        case 238:
        
        case 239:
        
        case 240:
        
        case 241:
        
        case 242:
        
        case 243:
        
        case 244:
        
        case 245:
        
        case 246:
        
        case 247:
        
        case 248:
        
        case 249:
        
        case 250:
        
        case 251:
        
        case 252:
        
        case 253:
        
        case 254:
        
        default:
          break;
      } 
      byte b1 = 67;
      int j = (paramInt2 & 0xFF) - b1;
      if (j < 0)
        j += 256; 
      int k = ((paramInt2 & 0xFFFF) >>> 8) - b1;
      if (k < 0)
        k += 256; 
      for (byte b2 = 0; b2 < arrayOfChar.length; b2++) {
        int m = b2 % 2;
        if (m == 0) {
          arrayOfChar[b2] = (char)(arrayOfChar[b2] ^ j);
          j = ((j >>> 3 | j << 5) ^ arrayOfChar[b2]) & 0xFF;
        } else {
          arrayOfChar[b2] = (char)(arrayOfChar[b2] ^ k);
          k = ((k >>> 3 | k << 5) ^ arrayOfChar[b2]) & 0xFF;
        } 
      } 
      b[i] = (new String(arrayOfChar)).intern();
    } 
    return b[i];
  }
}


/* Location:              C:\Program Files\BurpSuitePro\burpsuite_pro.jar!\burp\Zkaw.class
 * Java compiler version: 21 (65.0)
 * JD-Core Version:       1.1.3
 */